{
  "type": "Feature",
  "properties": {
    "addr:full":"2831 N Federal Hwy Boca Raton FL 33431",
    "addr:housenumber":"2831",
    "addr:postcode":"33431",
    "addr:street":"N Federal Hwy",
    "iso:country":"US",
    "sg:address":"2831 N Federal Hwy",
    "sg:city":"Boca Raton",
    "sg:classifiers":[
        {
            "category":"Shopping",
            "type":"Retail Goods"
        }
    ],
    "sg:phone":"+1 561 392 0020",
    "sg:postcode":"33431",
    "sg:province":"FL",
    "sg:tags":[
        "hearing",
        "equipment",
        "supply",
        "impaired",
        "aids"
    ],
    "wof:name":"Beltone Hearing Aid Center",
    "wof:placetype":"venue"
},
  "geometry": {"coordinates":[-80.076475,26.375922],"type":"Point"}
}