{
  "type": "Feature",
  "properties": {
    "iso:country":"US",
    "sg:address":"580 SW 124th Ave",
    "sg:city":"Miami",
    "sg:classifiers":[
        {
            "category":"Professional",
            "subcategory":"Computer Services",
            "type":"Services"
        }
    ],
    "sg:phone":"+1 305 220 1674",
    "sg:postcode":"33184",
    "sg:province":"FL",
    "sg:tags":[
        "consultant",
        "designer",
        "system"
    ],
    "wof:name":"Software Regulatory Services",
    "wof:placetype":"venue"
},
  "geometry": {"coordinates":[-80.39678600000001,25.762444],"type":"Point"}
}