{
  "type": "Feature",
  "properties": {
    "addr:full":"431 W Oak St Kissimmee FL 34741",
    "addr:housenumber":"431",
    "addr:postcode":"34741",
    "addr:street":"W Oak St",
    "iso:country":"US",
    "sg:address":"431 W Oak St",
    "sg:city":"Kissimmee",
    "sg:classifiers":[
        {
            "category":"Health Services",
            "subcategory":"Doctor",
            "type":"Services"
        }
    ],
    "sg:phone":"+1 407 933 2500",
    "sg:postcode":"34741",
    "sg:province":"FL",
    "sg:tags":[
        "urologist"
    ],
    "wof:name":"Florida Urology",
    "wof:placetype":"venue"
},
  "geometry": {"coordinates":[-81.409733,28.300982],"type":"Point"}
}