{
  "type": "Feature",
  "properties": {
    "addr:full":"1029 Edison Ave Jacksonville FL 32204",
    "addr:housenumber":"1029",
    "addr:postcode":"32204",
    "addr:street":"Edison Ave",
    "iso:country":"US",
    "sg:address":"1029 Edison Ave",
    "sg:city":"Jacksonville",
    "sg:classifiers":[
        {
            "category":"Social Services",
            "subcategory":"Child Care",
            "type":"Services"
        }
    ],
    "sg:phone":"+1 904 551 1084",
    "sg:postcode":"32204",
    "sg:province":"FL",
    "sg:tags":[
        "day"
    ],
    "wof:name":"123 and ME Daycare",
    "wof:placetype":"venue"
},
  "geometry": {"coordinates":[-81.679345,30.322116],"type":"Point"}
}