{
  "type": "Feature",
  "properties": {
    "addr:full":"501 E Tarpon Ave Tarpon Springs FL 34689",
    "addr:housenumber":"501",
    "addr:postcode":"34689",
    "addr:street":"E Tarpon Ave",
    "iso:country":"US",
    "sg:address":"501 E Tarpon Ave",
    "sg:city":"Tarpon Springs",
    "sg:classifiers":[
        {
            "category":"Social Services",
            "subcategory":"Child Care",
            "type":"Services"
        }
    ],
    "sg:phone":"+1 727 934 2223",
    "sg:postcode":"34689",
    "sg:province":"FL",
    "sg:tags":[
        "kindergarten",
        "academic",
        "school"
    ],
    "wof:name":"Gospel Train Preschool",
    "wof:placetype":"venue"
},
  "geometry": {"coordinates":[-82.74840399999999,28.146238],"type":"Point"}
}