{
  "type": "Feature",
  "properties": {
    "addr:full":"1250 Oceanview Ave Marathon FL 33050",
    "addr:housenumber":"1250",
    "addr:postcode":"33050",
    "addr:street":"Oceanview Ave",
    "iso:country":"US",
    "sg:address":"1250 Oceanview Ave",
    "sg:city":"Marathon",
    "sg:classifiers":[
        {
            "category":"Manufacturing",
            "subcategory":"Metals",
            "type":"Manufacturing & Wholesale Goods"
        },
        {
            "category":"Wholesale",
            "subcategory":"Seafood",
            "type":"Manufacturing & Wholesale Goods"
        }
    ],
    "sg:phone":"+1 305 743 1818",
    "sg:postcode":"33050",
    "sg:province":"FL",
    "sg:tags":[
        "frozen",
        "fresh",
        "product",
        "fish"
    ],
    "wof:name":"Marathon Seafood",
    "wof:placetype":"venue"
},
  "geometry": {"coordinates":[-81.109533,24.704195],"type":"Point"}
}