{
  "type": "Feature",
  "properties": {
    "addr:full":"1004 N L St Lake Worth FL 33460",
    "addr:housenumber":"1004",
    "addr:postcode":"33460",
    "addr:street":"N L St",
    "iso:country":"US",
    "sg:address":"1004 N L St",
    "sg:city":"Lake Worth",
    "sg:classifiers":[
        {
            "category":"Professional",
            "subcategory":"Secretarial Services",
            "type":"Services"
        }
    ],
    "sg:phone":"+1 561 586 7323",
    "sg:postcode":"33460",
    "sg:province":"FL",
    "sg:tags":[
        "reporting",
        "court"
    ],
    "wof:name":"Anne Dix",
    "wof:placetype":"venue"
},
  "geometry": {"coordinates":[-80.053865,26.628618],"type":"Point"}
}