{
  "type": "Feature",
  "properties": {
    "iso:country":"US",
    "sg:address":"331 Airport Pulling Rd S",
    "sg:city":"Naples",
    "sg:classifiers":[
        {
            "category":"Insurance",
            "subcategory":"Insurance Agent",
            "type":"Services"
        }
    ],
    "sg:phone":"+1 239 643 5502",
    "sg:postcode":"34104",
    "sg:province":"FL",
    "wof:name":"Tim Shaw Insurance Group Inc",
    "wof:placetype":"venue"
},
  "geometry": {"coordinates":[-81.766616,26.147887],"type":"Point"}
}