{
  "type": "Feature",
  "properties": {
    "iso:country":"US",
    "sg:address":"1304 SE 19th St",
    "sg:city":"Cape Coral",
    "sg:classifiers":[
        {
            "category":"Professional",
            "subcategory":"Business Services",
            "type":"Services"
        }
    ],
    "sg:phone":"+1 239 772 5295",
    "sg:postcode":"33990",
    "sg:province":"FL",
    "sg:tags":[
        "plastering",
        "pool"
    ],
    "wof:name":"Showcase Pool Plastering Inc",
    "wof:placetype":"venue"
},
  "geometry": {"coordinates":[-81.946601,26.617545],"type":"Point"}
}