{
  "type": "Feature",
  "properties": {
    "iso:country":"US",
    "sg:address":"3950 SW Archer Rd",
    "sg:city":"Gainesville",
    "sg:classifiers":[
        {
            "category":"Restaurant",
            "type":"Food & Drink"
        }
    ],
    "sg:menulink":"http://www.allmenus.com/fl/gainesville/63016-millers-ale-house/menu/",
    "sg:phone":"+1 352 371 0818",
    "sg:postcode":"32608",
    "sg:province":"FL",
    "sg:tags":[
        "american"
    ],
    "wof:name":"Millers Ale House",
    "wof:placetype":"venue"
},
  "geometry": {"coordinates":[-82.382953,29.619026],"type":"Point"}
}