{
  "type": "Feature",
  "properties": {
    "iso:country":"US",
    "sg:address":"6202 N 9th Ave",
    "sg:city":"Pensacola",
    "sg:classifiers":[
        {
            "category":"Health Services",
            "subcategory":"Doctor",
            "type":"Services"
        }
    ],
    "sg:phone":"+1 850 505 9778",
    "sg:postcode":"32503",
    "sg:province":"FL",
    "wof:name":"Laura B McAuley",
    "wof:placetype":"venue"
},
  "geometry": {"coordinates":[-87.19946400000001,30.486198],"type":"Point"}
}