{
  "type": "Feature",
  "properties": {
    "addr:full":"9795 Summer Pl Ponte Vedra Bch FL 32082",
    "addr:housenumber":"9795",
    "addr:postcode":"32082",
    "addr:street":"Summer Pl",
    "iso:country":"US",
    "sg:address":"9795 Summer Pl",
    "sg:city":"Ponte Vedra Bch",
    "sg:classifiers":[
        {
            "category":"Organizations",
            "subcategory":"Community Association",
            "type":"Services"
        }
    ],
    "sg:phone":"+1 904 273 0572",
    "sg:postcode":"32082",
    "sg:province":"FL",
    "sg:tags":[
        "club"
    ],
    "wof:name":"Sawgrass Country Club Sand Bar",
    "wof:placetype":"venue"
},
  "geometry": {"coordinates":[-81.365624,30.193251],"type":"Point"}
}