{
  "type": "Feature",
  "properties": {
    "addr:full":"2830 NE 2nd Ave Miami FL 33137",
    "addr:housenumber":"2830",
    "addr:postcode":"33137",
    "addr:street":"Ne 2Nd Ave",
    "iso:country":"US",
    "sg:address":"2830 NE 2nd Ave",
    "sg:city":"Miami",
    "sg:classifiers":[
        {
            "category":"Restaurant",
            "type":"Food & Drink"
        }
    ],
    "sg:phone":"+1 305 573 4681",
    "sg:postcode":"33137",
    "sg:province":"FL",
    "sg:tags":[
        "cuban",
        "brunch",
        "breakfast"
    ],
    "wof:name":"Enriqueta's Sandwich Shop",
    "wof:placetype":"venue"
},
  "geometry": {"coordinates":[-80.19090300000001,25.804001],"type":"Point"}
}