{
  "type": "Feature",
  "properties": {
    "iso:country":"US",
    "sg:address":"10020 Cross Creek Blvd",
    "sg:city":"Tampa",
    "sg:classifiers":[
        {
            "category":"Restaurant",
            "type":"Food & Drink"
        }
    ],
    "sg:phone":"+1 813 907 6200",
    "sg:postcode":"33647",
    "sg:province":"FL",
    "sg:tags":[
        "shop",
        "coffee"
    ],
    "wof:name":"Bay Beans Inc",
    "wof:placetype":"venue"
},
  "geometry": {"coordinates":[-82.329829,28.14217],"type":"Point"}
}