{
  "type": "Feature",
  "properties": {
    "iso:country":"US",
    "sg:address":"300 S Canal St",
    "sg:city":"Leesburg",
    "sg:classifiers":[
        {
            "category":"Health Services",
            "subcategory":"Doctor",
            "type":"Services"
        }
    ],
    "sg:phone":"+1 352 315 3195",
    "sg:postcode":"34748",
    "sg:province":"FL",
    "sg:tags":[
        "clinic"
    ],
    "wof:name":"Child Protection Team",
    "wof:placetype":"venue"
},
  "geometry": {"coordinates":[-81.87372499999999,28.807336],"type":"Point"}
}