{
  "type": "Feature",
  "properties": {
    "iso:country":"US",
    "sg:address":"308 N Federal Hwy",
    "sg:city":"Hollywood",
    "sg:classifiers":[
        {
            "category":"Building & Trades",
            "subcategory":"Construction",
            "type":"Services"
        }
    ],
    "sg:phone":"+1 954 456 5225",
    "sg:postcode":"33020",
    "sg:province":"FL",
    "sg:tags":[
        "tile",
        "dealer"
    ],
    "wof:name":"Universal Tile Group",
    "wof:placetype":"venue"
},
  "geometry": {"coordinates":[-80.14316700000001,26.014097],"type":"Point"}
}