{
  "type": "Feature",
  "properties": {
    "iso:country":"US",
    "sg:address":"218 Ramsgate Rd",
    "sg:city":"Auburndale",
    "sg:classifiers":[
        {
            "category":"Manufacturing",
            "subcategory":"Wood Products",
            "type":"Manufacturing & Wholesale Goods"
        }
    ],
    "sg:phone":"+1 863 258 0046",
    "sg:postcode":"33823",
    "sg:province":"FL",
    "sg:tags":[
        "mfg"
    ],
    "wof:name":"Jim Horak Woodwork",
    "wof:placetype":"venue"
},
  "geometry": {"coordinates":[-81.80128499999999,28.066119],"type":"Point"}
}