{
  "type": "Feature",
  "properties": {
    "addr:full":"6534 Caroline St Milton FL 32570",
    "addr:housenumber":"6534",
    "addr:postcode":"32570",
    "addr:street":"Caroline St",
    "iso:country":"US",
    "sg:address":"6534 Caroline St",
    "sg:city":"Milton",
    "sg:classifiers":[
        {
            "category":"Restaurant",
            "type":"Food & Drink"
        }
    ],
    "sg:menulink":"http://www.allmenus.com/fl/milton/31901-hungry-howies-pizza/menu/",
    "sg:phone":"+1 850 626 8600",
    "sg:postcode":"32570",
    "sg:province":"FL",
    "sg:tags":[
        "wrap",
        "american",
        "sandwich",
        "pizza"
    ],
    "wof:name":"Hungry Howie's Pizza",
    "wof:placetype":"venue"
},
  "geometry": {"coordinates":[-87.05082899999999,30.618365],"type":"Point"}
}