{
  "type": "Feature",
  "properties": {
    "iso:country":"US",
    "sg:address":"26451 Rookery Lake Dr",
    "sg:city":"Bonita Springs",
    "sg:classifiers":[
        {
            "category":"Manufacturing",
            "subcategory":"Metals",
            "type":"Manufacturing & Wholesale Goods"
        }
    ],
    "sg:phone":"+1 239 390 2424",
    "sg:postcode":"34134",
    "sg:province":"FL",
    "sg:tags":[
        "product",
        "fabricated",
        "mfg"
    ],
    "wof:name":"Safe Decisions Inc",
    "wof:placetype":"venue"
},
  "geometry": {"coordinates":[-81.82002,26.353011],"type":"Point"}
}