{
  "type": "Feature",
  "properties": {
    "iso:country":"US",
    "sg:address":"126 Still Lake Dr",
    "sg:city":"Jupiter",
    "sg:classifiers":[
        {
            "category":"Professional",
            "subcategory":"Management & Consulting",
            "type":"Services"
        }
    ],
    "sg:phone":"+1 561 747 8953",
    "sg:postcode":"33458",
    "sg:province":"FL",
    "sg:tags":[
        "marketing",
        "sales"
    ],
    "wof:name":"Gene Torino Consulting",
    "wof:placetype":"venue"
},
  "geometry": {"coordinates":[-80.135615,26.952173],"type":"Point"}
}