{
  "type": "Feature",
  "properties": {
    "iso:country":"US",
    "sg:address":"226 Holiday Park Blvd NE",
    "sg:city":"Palm Bay",
    "sg:classifiers":[
        {
            "category":"Building & Trades",
            "subcategory":"Construction",
            "type":"Services"
        }
    ],
    "sg:phone":"+1 321 243 8766",
    "sg:postcode":"32907",
    "sg:province":"FL",
    "sg:tags":[
        "resurfacing",
        "laying",
        "refinishing",
        "floor"
    ],
    "wof:name":"A1 Carpet & Tile Flooring Inc",
    "wof:placetype":"venue"
},
  "geometry": {"coordinates":[-80.63730200000001,28.006887],"type":"Point"}
}