{
  "type": "Feature",
  "properties": {
    "iso:country":"US",
    "sg:address":"10221 SW 11th St",
    "sg:city":"Miami",
    "sg:classifiers":[
        {
            "category":"Retail",
            "subcategory":"Repair Shop",
            "type":"Services"
        }
    ],
    "sg:phone":"+1 305 225 5365",
    "sg:postcode":"33174",
    "sg:province":"FL",
    "sg:tags":[
        "equipment-repair",
        "appliance",
        "electric"
    ],
    "sg:website":"http://www.garepair.com",
    "wof:name":"General Appliances Repair Inc",
    "wof:placetype":"venue"
},
  "geometry": {"coordinates":[-80.361,25.7593],"type":"Point"}
}