{
  "type": "Feature",
  "properties": {
    "addr:full":"4957 38th Ave N St Petersburg FL 33710",
    "addr:housenumber":"4957",
    "addr:postcode":"33710",
    "addr:street":"38Th Ave N",
    "iso:country":"US",
    "sg:address":"4957 38th Ave N",
    "sg:city":"St Petersburg",
    "sg:classifiers":[
        {
            "category":"Health Services",
            "subcategory":"Doctor",
            "type":"Services"
        }
    ],
    "sg:phone":"+1 727 522 8878",
    "sg:postcode":"33710",
    "sg:province":"FL",
    "sg:tags":[
        "physician",
        "surgeon"
    ],
    "wof:name":"Le Vine Family Practice",
    "wof:placetype":"venue"
},
  "geometry": {"coordinates":[-82.70101200000001,27.806483],"type":"Point"}
}