{
  "type": "Feature",
  "properties": {
    "addr:full":"510 Bus Park Way Royal Palm Beach FL 33411",
    "addr:housenumber":"510",
    "addr:postcode":"33411",
    "addr:street":"Bus Park Way",
    "iso:country":"US",
    "sg:address":"510 Bus Park Way",
    "sg:city":"Royal Palm Beach",
    "sg:classifiers":[
        {
            "category":"Retail",
            "subcategory":"Repair Shop",
            "type":"Services"
        }
    ],
    "sg:phone":"+1 561 793 4574",
    "sg:postcode":"33411",
    "sg:province":"FL",
    "sg:tags":[
        "repairing",
        "lawn",
        "mower"
    ],
    "wof:name":"Mower Mate",
    "wof:placetype":"venue"
},
  "geometry": {"coordinates":[-80.203802,26.699347],"type":"Point"}
}