{
  "type": "Feature",
  "properties": {
    "iso:country":"US",
    "sg:address":"2895 Point East Dr",
    "sg:city":"Aventura",
    "sg:classifiers":[
        {
            "category":"Organizations",
            "subcategory":"Religious Organization",
            "type":"Services"
        }
    ],
    "sg:phone":"+1 305 932 2527",
    "sg:postcode":"33160",
    "sg:province":"FL",
    "wof:name":"Jewish Community Services Norc Program",
    "wof:placetype":"venue"
},
  "geometry": {"coordinates":[-80.143721,25.93979],"type":"Point"}
}