{
  "type": "Feature",
  "properties": {
    "addr:full":"1897 SW 22nd St Coral Gables FL 33145",
    "addr:housenumber":"1897",
    "addr:postcode":"33145",
    "addr:street":"Sw 22Nd St",
    "iso:country":"US",
    "sg:address":"1897 SW 22nd St",
    "sg:city":"Coral Gables",
    "sg:classifiers":[
        {
            "category":"Professional",
            "type":"Services"
        }
    ],
    "sg:phone":"+1 305 860 0950",
    "sg:postcode":"33145",
    "sg:province":"FL",
    "sg:tags":[
        "establishment"
    ],
    "wof:name":"Om Invest",
    "wof:placetype":"venue"
},
  "geometry": {"coordinates":[-80.22427500000001,25.750885],"type":"Point"}
}