{
  "type": "Feature",
  "properties": {
    "iso:country":"US",
    "sg:address":"115 E Merritt Ave",
    "sg:city":"Merritt Island",
    "sg:classifiers":[
        {
            "category":"Personal",
            "subcategory":"Barber",
            "type":"Services"
        }
    ],
    "sg:phone":"+1 321 452 9084",
    "sg:postcode":"32953",
    "sg:province":"FL",
    "wof:name":"Mutter's Barber Shop",
    "wof:placetype":"venue"
},
  "geometry": {"coordinates":[-80.697462,28.361349],"type":"Point"}
}