{
  "type": "Feature",
  "properties": {
    "iso:country":"US",
    "sg:address":"5101 NW 21st Ave",
    "sg:city":"Fort Lauderdale",
    "sg:classifiers":[
        {
            "category":"Shopping",
            "subcategory":"Pharmacy",
            "type":"Retail Goods"
        }
    ],
    "sg:phone":"+1 954 739 4115",
    "sg:postcode":"33309",
    "sg:province":"FL",
    "sg:website":"www.walgreens.com",
    "wof:name":"Walgreens",
    "wof:placetype":"venue"
},
  "geometry": {"coordinates":[-80.17177100000001,26.191405],"type":"Point"}
}