{
  "type": "Feature",
  "properties": {
    "iso:country":"US",
    "sg:address":"6024 Atlantic Blvd",
    "sg:city":"Jacksonville",
    "sg:classifiers":[
        {
            "category":"Shopping",
            "type":"Retail Goods"
        }
    ],
    "sg:phone":"+1 904 724 7579",
    "sg:postcode":"32207",
    "sg:province":"FL",
    "sg:tags":[
        "coin",
        "dealer",
        "supply"
    ],
    "wof:name":"Duval Coins & Stamps",
    "wof:placetype":"venue"
},
  "geometry": {"coordinates":[-81.598361,30.313657],"type":"Point"}
}