{
  "type": "Feature",
  "properties": {
    "addr:full":"1812 S Parsons Ave Seffner FL 33584",
    "addr:housenumber":"1812",
    "addr:postcode":"33584",
    "addr:street":"S Parsons Ave",
    "iso:country":"US",
    "sg:address":"1812 S Parsons Ave",
    "sg:city":"Seffner",
    "sg:classifiers":[
        {
            "category":"Personal",
            "subcategory":"Beauty Salon",
            "type":"Services"
        }
    ],
    "sg:phone":"+1 813 661 4101",
    "sg:postcode":"33584",
    "sg:province":"FL",
    "sg:tags":[
        "shop"
    ],
    "wof:name":"A Perfect Reflection",
    "wof:placetype":"venue"
},
  "geometry": {"coordinates":[-82.285847,27.980274],"type":"Point"}
}