{
  "type": "Feature",
  "properties": {
    "addr:full":"5501 Cherry St Panama City FL 32404",
    "addr:housenumber":"5501",
    "addr:postcode":"32404",
    "addr:street":"Cherry St",
    "iso:country":"US",
    "sg:address":"5501 Cherry St",
    "sg:city":"Panama City",
    "sg:classifiers":[
        {
            "category":"Insurance",
            "subcategory":"Insurance Agent",
            "type":"Services"
        }
    ],
    "sg:phone":"+1 850 769 8479",
    "sg:postcode":"32404",
    "sg:province":"FL",
    "wof:name":"Nationwide Insurance Claims",
    "wof:placetype":"venue"
},
  "geometry": {"coordinates":[-85.591994,30.145693],"type":"Point"}
}