{
  "type": "Feature",
  "properties": {
    "iso:country":"US",
    "sg:address":"345 Son-In-Law Rd",
    "sg:city":"Bonifay",
    "sg:classifiers":[
        {
            "category":"Travel",
            "subcategory":"Travel Agent",
            "type":"Entertainment"
        }
    ],
    "sg:phone":"+1 850 547 5140",
    "sg:postcode":"32425",
    "sg:province":"FL",
    "sg:tags":[
        "operator",
        "tour"
    ],
    "wof:name":"DK Tours Inc",
    "wof:placetype":"venue"
},
  "geometry": {"coordinates":[-85.678394,30.766186],"type":"Point"}
}