{
  "type": "Feature",
  "properties": {
    "iso:country":"US",
    "sg:address":"1745 Lovewood Rd",
    "sg:city":"Cottondale",
    "sg:classifiers":[
        {
            "category":"Organizations",
            "subcategory":"Religious Organization",
            "type":"Services"
        }
    ],
    "sg:phone":"+1 850 638 5003",
    "sg:postcode":"32431",
    "sg:province":"FL",
    "wof:name":"Lovewood Frewill Baptst Church",
    "wof:placetype":"venue"
},
  "geometry": {"coordinates":[-85.456419,30.827845],"type":"Point"}
}