{
  "type": "Feature",
  "properties": {
    "iso:country":"US",
    "sg:address":"1821 Rogero Rd",
    "sg:city":"Jacksonville",
    "sg:classifiers":[
        {
            "category":"Professional",
            "subcategory":"Accounting & Tax Preparation",
            "type":"Services"
        }
    ],
    "sg:phone":"+1 904 743 4333",
    "sg:postcode":"32211",
    "sg:province":"FL",
    "sg:tags":[
        "return",
        "filing"
    ],
    "wof:name":"Quick Tax Financial Svc",
    "wof:placetype":"venue"
},
  "geometry": {"coordinates":[-81.58908599999999,30.34006],"type":"Point"}
}