{
  "type": "Feature",
  "properties": {
    "iso:country":"US",
    "sg:address":"15248 S Tamiami Trl",
    "sg:city":"Fort Myers",
    "sg:classifiers":[
        {
            "category":"Professional",
            "subcategory":"Management & Consulting",
            "type":"Services"
        }
    ],
    "sg:phone":"+1 239 415 6406",
    "sg:postcode":"33908",
    "sg:province":"FL",
    "sg:tags":[
        "environmental",
        "consultant"
    ],
    "wof:name":"Environmental Risk Management",
    "wof:placetype":"venue"
},
  "geometry": {"coordinates":[-81.868837,26.520446],"type":"Point"}
}