{
  "type": "Feature",
  "properties": {
    "iso:country":"US",
    "sg:address":"6940 N Port Blvd",
    "sg:city":"North Port",
    "sg:classifiers":[
        {
            "category":"Social Services",
            "subcategory":"Job Training",
            "type":"Services"
        }
    ],
    "sg:phone":"+1 941 240 5888",
    "sg:postcode":"34287",
    "sg:province":"FL",
    "sg:tags":[
        "rehabilitation"
    ],
    "wof:name":"Paragon Rehabilitation",
    "wof:placetype":"venue"
},
  "geometry": {"coordinates":[-82.238395,27.038209],"type":"Point"}
}