{
  "type": "Feature",
  "properties": {
    "addr:full":"401 Lakeshore Dr Daytona Beach FL 32114",
    "addr:housenumber":"401",
    "addr:postcode":"32114",
    "addr:street":"Lakeshore Dr",
    "iso:country":"US",
    "sg:address":"401 Lakeshore Dr",
    "sg:city":"Daytona Beach",
    "sg:classifiers":[
        {
            "category":"Organizations",
            "subcategory":"Religious Organization",
            "type":"Services"
        }
    ],
    "sg:phone":"+1 386 253 3339",
    "sg:postcode":"32114",
    "sg:province":"FL",
    "sg:tags":[
        "church"
    ],
    "wof:name":"Tree-Life Outreach Ministies",
    "wof:placetype":"venue"
},
  "geometry": {"coordinates":[-81.05759999999999,29.206184],"type":"Point"}
}