{
  "type": "Feature",
  "properties": {
    "iso:country":"US",
    "sg:address":"7144 Boca Pointe Dr",
    "sg:city":"Boca Raton",
    "sg:classifiers":[
        {
            "category":"Personal",
            "type":"Services"
        }
    ],
    "sg:phone":"+1 561 864 8558",
    "sg:postcode":"33433",
    "sg:province":"FL",
    "sg:tags":[
        "therapist",
        "massage"
    ],
    "wof:name":"Athletic Center",
    "wof:placetype":"venue"
},
  "geometry": {"coordinates":[-80.156773,26.339829],"type":"Point"}
}