{
  "type": "Feature",
  "properties": {
    "iso:country":"US",
    "sg:address":"4871 SW 28th St",
    "sg:city":"Hollywood",
    "sg:classifiers":[
        {
            "category":"Building & Trades",
            "subcategory":"Construction",
            "type":"Services"
        }
    ],
    "sg:phone":"+1 954 981 1032",
    "sg:postcode":"33023",
    "sg:province":"FL",
    "sg:tags":[
        "contractor"
    ],
    "wof:name":"Jerry Demers Drywall",
    "wof:placetype":"venue"
},
  "geometry": {"coordinates":[-80.191698,25.985367],"type":"Point"}
}