{
  "type": "Feature",
  "properties": {
    "iso:country":"US",
    "sg:address":"1737 N Andrews Ave",
    "sg:city":"Fort Lauderdale",
    "sg:classifiers":[
        {
            "category":"Food & Beverages",
            "subcategory":"Groceries & Convenience Stores",
            "type":"Retail Goods"
        }
    ],
    "sg:phone":"+1 954 764 1735",
    "sg:postcode":"33311",
    "sg:province":"FL",
    "wof:name":"AM PM Mini Mart",
    "wof:placetype":"venue"
},
  "geometry": {"coordinates":[-80.14496200000001,26.149026],"type":"Point"}
}