{
  "type": "Feature",
  "properties": {
    "addr:full":"365 Sawmill Ln Ponte Vedra Bch FL 32082",
    "addr:housenumber":"365",
    "addr:postcode":"32082",
    "addr:street":"Sawmill Ln",
    "iso:country":"US",
    "sg:address":"365 Sawmill Ln",
    "sg:city":"Ponte Vedra Bch",
    "sg:classifiers":[
        {
            "category":"Professional",
            "subcategory":"Research",
            "type":"Services"
        }
    ],
    "sg:phone":"+1 904 543 8431",
    "sg:postcode":"32082",
    "sg:province":"FL",
    "sg:tags":[
        "environmental",
        "ecological"
    ],
    "wof:name":"National Exhaust Cleaning",
    "wof:placetype":"venue"
},
  "geometry": {"coordinates":[-81.387945,30.159488],"type":"Point"}
}