{
  "type": "Feature",
  "properties": {
    "addr:full":"8700 New Kings Rd Jacksonville FL 32219",
    "addr:housenumber":"8700",
    "addr:postcode":"32219",
    "addr:street":"New Kings Rd",
    "iso:country":"US",
    "sg:address":"8700 New Kings Rd",
    "sg:city":"Jacksonville",
    "sg:classifiers":[
        {
            "category":"Wholesale",
            "subcategory":"Motor Vehicles",
            "type":"Manufacturing & Wholesale Goods"
        }
    ],
    "sg:phone":"+1 904 388 2256",
    "sg:postcode":"32219",
    "sg:province":"FL",
    "sg:tags":[
        "heavy",
        "duty",
        "general",
        "truck",
        "repair"
    ],
    "wof:name":"Asbell Truck Center Inc",
    "wof:placetype":"venue"
},
  "geometry": {"coordinates":[-81.746055,30.409634],"type":"Point"}
}