{
  "type": "Feature",
  "properties": {
    "iso:country":"US",
    "sg:address":"273 Minorca Ave",
    "sg:city":"Coral Gables",
    "sg:classifiers":[
        {
            "category":"Professional",
            "subcategory":"Business Services",
            "type":"Services"
        },
        {
            "category":"Shopping",
            "subcategory":"Crafts & Fabrics",
            "type":"Retail Goods"
        }
    ],
    "sg:phone":"+1 305 443 2288",
    "sg:postcode":"33134",
    "sg:province":"FL",
    "sg:tags":[
        "sewing",
        "embroidery"
    ],
    "wof:name":"Royal Monogramming",
    "wof:placetype":"venue"
},
  "geometry": {"coordinates":[-80.259478,25.753808],"type":"Point"}
}