{
  "type": "Feature",
  "properties": {
    "addr:full":"1873 Everhart Dr Orlando FL 32806",
    "addr:housenumber":"1873",
    "addr:postcode":"32806",
    "addr:street":"Everhart Dr",
    "iso:country":"US",
    "sg:address":"1873 Everhart Dr",
    "sg:city":"Orlando",
    "sg:classifiers":[
        {
            "category":"Shopping",
            "subcategory":"Bicycles & Sporting Goods",
            "type":"Retail Goods"
        }
    ],
    "sg:phone":"+1 407 894 1145",
    "sg:postcode":"32806",
    "sg:province":"FL",
    "wof:name":"Blackhorse & Sparrow",
    "wof:placetype":"venue"
},
  "geometry": {"coordinates":[-81.34549699999999,28.520027],"type":"Point"}
}