{
  "type": "Feature",
  "properties": {
    "iso:country":"US",
    "sg:address":"1021 NW 95th St",
    "sg:city":"Miami",
    "sg:classifiers":[
        {
            "category":"Food & Beverages",
            "subcategory":"Groceries & Convenience Stores",
            "type":"Retail Goods"
        }
    ],
    "sg:phone":"+1 305 836 9091",
    "sg:postcode":"33150",
    "sg:province":"FL",
    "wof:name":"Quik Stop",
    "wof:placetype":"venue"
},
  "geometry": {"coordinates":[-80.214302,25.861601],"type":"Point"}
}