{
  "type": "Feature",
  "properties": {
    "addr:full":"2360 Wilton Dr Wilton Manors FL 33305",
    "addr:housenumber":"2360",
    "addr:postcode":"33305",
    "addr:street":"Wilton Dr",
    "iso:country":"US",
    "sg:address":"2360 Wilton Dr",
    "sg:city":"Wilton Manors",
    "sg:classifiers":[
        {
            "category":"Professional",
            "subcategory":"Advertising",
            "type":"Services"
        }
    ],
    "sg:phone":"+1 954 563 8122",
    "sg:postcode":"33305",
    "sg:province":"FL",
    "sg:tags":[
        "designer",
        "display",
        "producer"
    ],
    "wof:name":"D B Retail",
    "wof:placetype":"venue"
},
  "geometry": {"coordinates":[-80.13624799999999,26.157505],"type":"Point"}
}