{
  "type": "Feature",
  "properties": {
    "addr:full":"541 Woodview Dr Longwood FL 32779",
    "addr:housenumber":"541",
    "addr:postcode":"32779",
    "addr:street":"Woodview Dr",
    "iso:country":"US",
    "sg:address":"541 Woodview Dr",
    "sg:city":"Longwood",
    "sg:classifiers":[
        {
            "category":"Arena",
            "subcategory":"Sports Club",
            "type":"Entertainment"
        }
    ],
    "sg:phone":"+1 407 862 3305",
    "sg:postcode":"32779",
    "sg:province":"FL",
    "wof:name":"National Intercollegiate Soccr",
    "wof:placetype":"venue"
},
  "geometry": {"coordinates":[-81.411714,28.706213],"type":"Point"}
}