{
  "type": "Feature",
  "properties": {
    "iso:country":"US",
    "sg:address":"1391 N Killian Dr",
    "sg:city":"West Palm Beach",
    "sg:classifiers":[
        {
            "category":"Professional",
            "subcategory":"Detective & Security Services",
            "type":"Services"
        }
    ],
    "sg:phone":"+1 561 841 1969",
    "sg:postcode":"33403",
    "sg:province":"FL",
    "sg:tags":[
        "system"
    ],
    "wof:name":"Total Video Solutions",
    "wof:placetype":"venue"
},
  "geometry": {"coordinates":[-80.08022699999999,26.805776],"type":"Point"}
}