{
  "type": "Feature",
  "properties": {
    "iso:country":"US",
    "sg:address":"4941 E Broadway Ave",
    "sg:city":"Tampa",
    "sg:classifiers":[
        {
            "category":"Personal",
            "subcategory":"Barber",
            "type":"Services"
        }
    ],
    "sg:phone":"+1 813 248 4410",
    "sg:postcode":"33605",
    "sg:province":"FL",
    "sg:tags":[
        "shop"
    ],
    "wof:name":"Cleve Hair Fx",
    "wof:placetype":"venue"
},
  "geometry": {"coordinates":[-82.40244300000001,27.961581],"type":"Point"}
}