{
  "type": "Feature",
  "properties": {
    "addr:full":"4530 Rickover Ct New Port Richey FL 34652",
    "addr:housenumber":"4530",
    "addr:postcode":"34652",
    "addr:street":"Rickover Ct",
    "iso:country":"US",
    "sg:address":"4530 Rickover Ct",
    "sg:city":"New Port Richey",
    "sg:classifiers":[
        {
            "category":"Shopping",
            "subcategory":"Discount & Variety Stores",
            "type":"Retail Goods"
        }
    ],
    "sg:phone":"+1 727 842 3463",
    "sg:postcode":"34652",
    "sg:province":"FL",
    "sg:tags":[
        "merchandise",
        "general"
    ],
    "wof:name":"My Crazy Aunt",
    "wof:placetype":"venue"
},
  "geometry": {"coordinates":[-82.73832,28.241029],"type":"Point"}
}