{
  "type": "Feature",
  "properties": {
    "iso:country":"US",
    "sg:address":"7465 W 19th Ct",
    "sg:city":"Hialeah",
    "sg:classifiers":[
        {
            "category":"Manufacturing",
            "subcategory":"Rubber & Plastics",
            "type":"Manufacturing & Wholesale Goods"
        }
    ],
    "sg:phone":"+1 305 558 4055",
    "sg:postcode":"33014",
    "sg:province":"FL",
    "wof:name":"American Plastics Tech",
    "wof:placetype":"venue"
},
  "geometry": {"coordinates":[-80.322388,25.888442],"type":"Point"}
}