{
  "type": "Feature",
  "properties": {
    "addr:full":"3450 Buschwood Park Dr Tampa FL 33618",
    "addr:housenumber":"3450",
    "addr:postcode":"33618",
    "addr:street":"Buschwood Park Dr",
    "iso:country":"US",
    "sg:address":"3450 Buschwood Park Dr",
    "sg:city":"Tampa",
    "sg:classifiers":[
        {
            "category":"Insurance",
            "subcategory":"Insurance Agent",
            "type":"Services"
        }
    ],
    "sg:phone":"+1 813 353 8840",
    "sg:postcode":"33618",
    "sg:province":"FL",
    "wof:name":"PMI Mortgage Insurance Co",
    "wof:placetype":"venue"
},
  "geometry": {"coordinates":[-82.497165,28.034881],"type":"Point"}
}