{
  "type": "Feature",
  "properties": {
    "addr:full":"605 E Robinson St Orlando FL 32801",
    "addr:housenumber":"605",
    "addr:postcode":"32801",
    "addr:street":"E Robinson St",
    "iso:country":"US",
    "sg:address":"605 E Robinson St",
    "sg:city":"Orlando",
    "sg:classifiers":[
        {
            "category":"Real Estate",
            "subcategory":"Real Estate Agent",
            "type":"Services"
        }
    ],
    "sg:phone":"+1 407 843 7070",
    "sg:postcode":"32801",
    "sg:province":"FL",
    "wof:name":"Realty Capital Advisors Inc",
    "wof:placetype":"venue"
},
  "geometry": {"coordinates":[-81.370045,28.545815],"type":"Point"}
}