{
  "type": "Feature",
  "properties": {
    "addr:full":"7543 W Waters Ave Tampa FL 33615",
    "addr:housenumber":"7543",
    "addr:postcode":"33615",
    "addr:street":"W Waters Ave",
    "iso:country":"US",
    "sg:address":"7543 W Waters Ave",
    "sg:city":"Tampa",
    "sg:classifiers":[
        {
            "category":"Building & Trades",
            "subcategory":"Equipment Rental",
            "type":"Services"
        }
    ],
    "sg:phone":"+1 813 249 1404",
    "sg:postcode":"33615",
    "sg:province":"FL",
    "sg:tags":[
        "appliance"
    ],
    "wof:name":"Rent Way",
    "wof:placetype":"venue"
},
  "geometry": {"coordinates":[-82.564196,28.025961],"type":"Point"}
}