{
  "type": "Feature",
  "properties": {
    "addr:full":"9691 W Colonial Dr Ocoee FL 34761",
    "addr:housenumber":"9691",
    "addr:postcode":"34761",
    "addr:street":"W Colonial Dr",
    "iso:country":"US",
    "sg:address":"9691 W Colonial Dr",
    "sg:city":"Ocoee",
    "sg:classifiers":[
        {
            "category":"Personal",
            "subcategory":"Beauty Salon",
            "type":"Services"
        }
    ],
    "sg:phone":"+1 407 296 3141",
    "sg:postcode":"34761",
    "sg:province":"FL",
    "sg:tags":[
        "shop"
    ],
    "wof:name":"Best Nails",
    "wof:placetype":"venue"
},
  "geometry": {"coordinates":[-81.52107700000001,28.551853],"type":"Point"}
}