{
  "type": "Feature",
  "properties": {
    "iso:country":"US",
    "sg:address":"230 Sunport Ln",
    "sg:city":"Orlando",
    "sg:classifiers":[
        {
            "category":"Real Estate",
            "subcategory":"Real Estate Agent",
            "type":"Services"
        }
    ],
    "sg:phone":"+1 407 854 0494",
    "sg:postcode":"32809",
    "sg:province":"FL",
    "wof:name":"East Group Properties",
    "wof:placetype":"venue"
},
  "geometry": {"coordinates":[-81.373375,28.447226],"type":"Point"}
}