{
  "type": "Feature",
  "properties": {
    "addr:full":"1673 SW 27th Ave Miami FL 33145",
    "addr:housenumber":"1673",
    "addr:postcode":"33145",
    "addr:street":"Sw 27Th Ave",
    "iso:country":"US",
    "sg:address":"1673 SW 27th Ave",
    "sg:city":"Miami",
    "sg:classifiers":[
        {
            "category":"Shopping",
            "subcategory":"Pharmacy",
            "type":"Retail Goods"
        }
    ],
    "sg:phone":"+1 305 854 7995",
    "sg:postcode":"33145",
    "sg:province":"FL",
    "wof:name":"Astro Pharmacy & Discount",
    "wof:placetype":"venue"
},
  "geometry": {"coordinates":[-80.238437,25.756324],"type":"Point"}
}