{
  "type": "Feature",
  "properties": {
    "iso:country":"US",
    "sg:address":"3476 Docksider Dr S",
    "sg:city":"Jacksonville",
    "sg:classifiers":[
        {
            "category":"Building & Trades",
            "subcategory":"Construction",
            "type":"Services"
        }
    ],
    "sg:phone":"+1 904 262 6865",
    "sg:postcode":"32257",
    "sg:province":"FL",
    "sg:tags":[
        "altering",
        "remodeling",
        "contractor"
    ],
    "wof:name":"Evans Brothers",
    "wof:placetype":"venue"
},
  "geometry": {"coordinates":[-81.620411,30.18789],"type":"Point"}
}