{
  "type": "Feature",
  "properties": {
    "addr:full":"9526 SW 40th St Miami FL 33165",
    "addr:housenumber":"9526",
    "addr:postcode":"33165",
    "addr:street":"Sw 40Th St",
    "iso:country":"US",
    "sg:address":"9526 SW 40th St",
    "sg:city":"Miami",
    "sg:classifiers":[
        {
            "category":"Wholesale",
            "subcategory":"Office Equipment",
            "type":"Manufacturing & Wholesale Goods"
        },
        {
            "category":"Professional",
            "subcategory":"Printing & Photocopies",
            "type":"Services"
        },
        {
            "category":"Shopping",
            "subcategory":"Computers & Home Electronics",
            "type":"Retail Goods"
        }
    ],
    "sg:phone":"+1 305 262 1700",
    "sg:postcode":"33165",
    "sg:province":"FL",
    "sg:tags":[
        "scanning",
        "printer",
        "plotting",
        "supply"
    ],
    "sg:website":"http://www.jemqualityprinters.com",
    "wof:name":"Jem Quality Printers Inc",
    "wof:placetype":"venue"
},
  "geometry": {"coordinates":[-80.34998,25.732692],"type":"Point"}
}