{
  "type": "Feature",
  "properties": {
    "addr:full":"2255 NW 102nd Pl Doral FL 33172",
    "addr:housenumber":"2255",
    "addr:postcode":"33172",
    "addr:street":"Nw 102Nd Pl",
    "iso:country":"US",
    "sg:address":"2255 NW 102nd Pl",
    "sg:city":"Doral",
    "sg:classifiers":[
        {
            "category":"Recreation",
            "type":"Entertainment"
        }
    ],
    "sg:phone":"+1 305 640 9767",
    "sg:postcode":"33172",
    "sg:province":"FL",
    "sg:tags":[
        "instruction",
        "gymnastic"
    ],
    "sg:website":"www.oyt.homestead.com",
    "wof:name":"On Your Toes Gymnastics & Dnc",
    "wof:placetype":"venue"
},
  "geometry": {"coordinates":[-80.36260299999999,25.795558],"type":"Point"}
}