{
  "type": "Feature",
  "properties": {
    "addr:full":"4895 Lillian Hwy Pensacola FL 32506",
    "addr:housenumber":"4895",
    "addr:postcode":"32506",
    "addr:street":"Lillian Hwy",
    "iso:country":"US",
    "sg:address":"4895 Lillian Hwy",
    "sg:city":"Pensacola",
    "sg:classifiers":[
        {
            "category":"Bars & Pubs",
            "type":"Food & Drink"
        }
    ],
    "sg:phone":"+1 850 332 6533",
    "sg:postcode":"32506",
    "sg:province":"FL",
    "sg:tags":[
        "tavern"
    ],
    "wof:name":"The Blind Mule",
    "wof:placetype":"venue"
},
  "geometry": {"coordinates":[-87.281913,30.426672],"type":"Point"}
}