{
  "type": "Feature",
  "properties": {
    "addr:full":"1011 8th Ave S Lake Worth FL 33460",
    "addr:housenumber":"1011",
    "addr:postcode":"33460",
    "addr:street":"8Th Ave S",
    "iso:country":"US",
    "sg:address":"1011 8th Ave S",
    "sg:city":"Lake Worth",
    "sg:classifiers":[
        {
            "category":"Home & Garden",
            "subcategory":"Furniture",
            "type":"Retail Goods"
        }
    ],
    "sg:phone":"+1 561 304 0080",
    "sg:postcode":"33460",
    "sg:province":"FL",
    "sg:tags":[
        "top",
        "counter",
        "cabinet"
    ],
    "wof:name":"Counter Tops & Cabinets Direct",
    "wof:placetype":"venue"
},
  "geometry": {"coordinates":[-80.059327,26.606172],"type":"Point"}
}