{
  "type": "Feature",
  "properties": {
    "addr:full":"2219 63rd Ave E Bradenton FL 34203",
    "addr:housenumber":"2219",
    "addr:postcode":"34203",
    "addr:street":"63Rd Ave E",
    "iso:country":"US",
    "sg:address":"2219 63rd Ave E",
    "sg:city":"Bradenton",
    "sg:classifiers":[
        {
            "category":"Building & Trades",
            "subcategory":"Cleaning & Sanitation",
            "type":"Services"
        }
    ],
    "sg:phone":"+1 941 753 9500",
    "sg:postcode":"34203",
    "sg:province":"FL",
    "sg:tags":[
        "awning",
        "canopy"
    ],
    "wof:name":"S & S Maintenance",
    "wof:placetype":"venue"
},
  "geometry": {"coordinates":[-82.5365,27.429279],"type":"Point"}
}