{
  "type": "Feature",
  "properties": {
    "addr:full":"721 Front St Kissimmee FL 34747",
    "addr:housenumber":"721",
    "addr:postcode":"34747",
    "addr:street":"Front St",
    "iso:country":"US",
    "sg:address":"721 Front St",
    "sg:city":"Kissimmee",
    "sg:classifiers":[
        {
            "category":"Real Estate",
            "subcategory":"Real Estate Agent",
            "type":"Services"
        }
    ],
    "sg:phone":"+1 407 566 9797",
    "sg:postcode":"34747",
    "sg:province":"FL",
    "wof:name":"USA Land Sale",
    "wof:placetype":"venue"
},
  "geometry": {"coordinates":[-81.538821,28.313403],"type":"Point"}
}