{
  "type": "Feature",
  "properties": {
    "iso:country":"US",
    "sg:address":"214 E Bearss Ave",
    "sg:city":"Tampa",
    "sg:classifiers":[
        {
            "category":"Restaurant",
            "type":"Food & Drink"
        }
    ],
    "sg:menulink":"http://www.allmenus.com/fl/tampa/60672-cherrys/menu/",
    "sg:phone":"+1 813 269 0205",
    "sg:postcode":"33613",
    "sg:province":"FL",
    "sg:tags":[
        "american"
    ],
    "wof:name":"Cherry's",
    "wof:placetype":"venue"
},
  "geometry": {"coordinates":[-82.458321,28.08811],"type":"Point"}
}