{
  "type": "Feature",
  "properties": {
    "iso:country":"US",
    "sg:address":"7588 Sierra Ter E",
    "sg:city":"Boca Raton",
    "sg:classifiers":[
        {
            "category":"Banks & Credit Unions",
            "subcategory":"Bank",
            "type":"Services"
        }
    ],
    "sg:phone":"+1 561 394 6097",
    "sg:postcode":"33433",
    "sg:province":"FL",
    "sg:tags":[
        "mortgage"
    ],
    "wof:name":"Forman Financial Mortgage Svcs",
    "wof:placetype":"venue"
},
  "geometry": {"coordinates":[-80.163195,26.352471],"type":"Point"}
}