{
  "type": "Feature",
  "properties": {
    "addr:full":"2601 Wells Ave Ste 121 Fern Park FL 32730",
    "addr:housenumber":"2601",
    "addr:postcode":"32730",
    "addr:street":"Wells Ave Ste 121 Fern Park",
    "iso:country":"US",
    "sg:address":"2601 Wells Ave Ste 121",
    "sg:city":"Fern Park",
    "sg:classifiers":[
        {
            "category":"Professional",
            "subcategory":"Computer Services",
            "type":"Services"
        }
    ],
    "sg:phone":"+1 407 767 0025",
    "sg:postcode":"32730",
    "sg:province":"FL",
    "sg:tags":[
        "repair"
    ],
    "sg:website":"www.expandit.us",
    "wof:name":"ExpandIT Solutions US",
    "wof:placetype":"venue"
},
  "geometry": {"coordinates":[-81.346288,28.655952],"type":"Point"}
}