{
  "type": "Feature",
  "properties": {
    "addr:full":"9915 el Camino Real Ave Port Richey FL 34668",
    "addr:housenumber":"9915",
    "addr:postcode":"34668",
    "addr:street":"El Camino Real Ave",
    "iso:country":"US",
    "sg:address":"9915 el Camino Real Ave",
    "sg:city":"Port Richey",
    "sg:classifiers":[
        {
            "category":"Health Services",
            "subcategory":"Clinic",
            "type":"Services"
        }
    ],
    "sg:phone":"+1 727 847 7957",
    "sg:postcode":"34668",
    "sg:province":"FL",
    "sg:tags":[
        "home"
    ],
    "wof:name":"Senior Home Care",
    "wof:placetype":"venue"
},
  "geometry": {"coordinates":[-82.702861,28.298738],"type":"Point"}
}