{
  "type": "Feature",
  "properties": {
    "iso:country":"US",
    "sg:address":"633 Tamiami Trl N",
    "sg:city":"Naples",
    "sg:classifiers":[
        {
            "category":"Professional",
            "subcategory":"Business Services",
            "type":"Services"
        }
    ],
    "sg:phone":"+1 239 261 7464",
    "sg:postcode":"34102",
    "sg:province":"FL",
    "sg:tags":[
        "interior",
        "consultant",
        "design",
        "decorator"
    ],
    "sg:website":"www.hollandsalley.com",
    "wof:name":"Holland Salley Interiors Inc",
    "wof:placetype":"venue"
},
  "geometry": {"coordinates":[-81.79688400000001,26.15575],"type":"Point"}
}