{
  "type": "Feature",
  "properties": {
    "addr:full":"6101 NW 72nd Ave Miami FL 33166",
    "addr:housenumber":"6101",
    "addr:postcode":"33166",
    "addr:street":"Nw 72Nd Ave",
    "iso:country":"US",
    "sg:address":"6101 NW 72nd Ave",
    "sg:city":"Miami",
    "sg:classifiers":[
        {
            "category":"Wholesale",
            "subcategory":"Non-durable Goods",
            "type":"Manufacturing & Wholesale Goods"
        }
    ],
    "sg:phone":"+1 305 477 4330",
    "sg:postcode":"33166",
    "sg:province":"FL",
    "sg:tags":[
        "merchandise",
        "general"
    ],
    "wof:name":"Key Trading Corp",
    "wof:placetype":"venue"
},
  "geometry": {"coordinates":[-80.31385,25.82996],"type":"Point"}
}