{
  "type": "Feature",
  "properties": {
    "iso:country":"US",
    "sg:address":"9620 131st St",
    "sg:city":"Largo",
    "sg:classifiers":[
        {
            "category":"Home & Garden",
            "subcategory":"Garden Supply",
            "type":"Retail Goods"
        }
    ],
    "sg:phone":"+1 727 595 4217",
    "sg:postcode":"33776",
    "sg:province":"FL",
    "sg:tags":[
        "sprinkler"
    ],
    "wof:name":"M D's Landscape & Irrigation",
    "wof:placetype":"venue"
},
  "geometry": {"coordinates":[-82.820044,27.860505],"type":"Point"}
}