{
  "type": "Feature",
  "properties": {
    "addr:full":"14110 Twin Ln Dade City FL 33525",
    "addr:housenumber":"14110",
    "addr:postcode":"33525",
    "addr:street":"Twin Ln",
    "iso:country":"US",
    "sg:address":"14110 Twin Ln",
    "sg:city":"Dade City",
    "sg:classifiers":[
        {
            "category":"Shopping",
            "subcategory":"Computers & Home Electronics",
            "type":"Retail Goods"
        }
    ],
    "sg:phone":"+1 352 588 2218",
    "sg:postcode":"33525",
    "sg:province":"FL",
    "sg:tags":[
        "equipment",
        "satellite",
        "system"
    ],
    "wof:name":"Richard's Satellite Svc",
    "wof:placetype":"venue"
},
  "geometry": {"coordinates":[-82.345321,28.361858],"type":"Point"}
}