{
  "type": "Feature",
  "properties": {
    "iso:country":"US",
    "sg:address":"1865 Brickell Ave",
    "sg:city":"Miami",
    "sg:classifiers":[
        {
            "category":"Professional",
            "subcategory":"Printing & Photocopies",
            "type":"Services"
        }
    ],
    "sg:phone":"+1 305 285 7793",
    "sg:postcode":"33129",
    "sg:province":"FL",
    "sg:tags":[
        "lithographer"
    ],
    "wof:name":"Int'l Printing & Graphic Desig",
    "wof:placetype":"venue"
},
  "geometry": {"coordinates":[-80.200402,25.752681],"type":"Point"}
}