{
  "type": "Feature",
  "properties": {
    "addr:full":"14160 Mustang Trl Southwest Rnchs FL 33330",
    "addr:housenumber":"14160",
    "addr:postcode":"33330",
    "addr:street":"Mustang Trl Southwest Rnchs",
    "iso:country":"US",
    "sg:address":"14160 Mustang Trl",
    "sg:city":"Southwest Rnchs",
    "sg:classifiers":[
        {
            "category":"Banks & Credit Unions",
            "subcategory":"Bank",
            "type":"Services"
        }
    ],
    "sg:phone":"+1 954 615 0150",
    "sg:postcode":"33330",
    "sg:province":"FL",
    "sg:tags":[
        "loan",
        "real estate"
    ],
    "wof:name":"Advantage Mortgage Svc",
    "wof:placetype":"venue"
},
  "geometry": {"coordinates":[-80.329757,26.033134],"type":"Point"}
}