{
  "type": "Feature",
  "properties": {
    "addr:full":"1201 NW Ave L Belle Glade FL 33430",
    "addr:housenumber":"1201",
    "addr:postcode":"33430",
    "addr:street":"Nw Ave L;Glade",
    "iso:country":"US",
    "sg:address":"1201 NW Ave L",
    "sg:city":"Belle Glade",
    "sg:classifiers":[
        {
            "category":"Insurance",
            "subcategory":"Insurance Agent",
            "type":"Services"
        }
    ],
    "sg:phone":"+1 561 996 7186",
    "sg:postcode":"33430",
    "sg:province":"FL",
    "wof:name":"State Farm Insurance",
    "wof:placetype":"venue"
},
  "geometry": {"coordinates":[-80.678843,26.696874],"type":"Point"}
}