{
  "type": "Feature",
  "properties": {
    "iso:country":"US",
    "sg:address":"400 S Orlando Ave",
    "sg:city":"Winter Park",
    "sg:classifiers":[
        {
            "category":"Shopping",
            "subcategory":"Clothing, Apparel, & Fashions",
            "type":"Retail Goods"
        }
    ],
    "sg:phone":"+1 407 628 0888",
    "sg:postcode":"32789",
    "sg:province":"FL",
    "wof:name":"My Sisters Closet",
    "wof:placetype":"venue"
},
  "geometry": {"coordinates":[-81.36511,28.595571],"type":"Point"}
}