{
  "type": "Feature",
  "properties": {
    "addr:full":"6201 NW 3rd Ave Miami FL 33150",
    "addr:housenumber":"6201",
    "addr:postcode":"33150",
    "addr:street":"Nw 3Rd Ave",
    "iso:country":"US",
    "sg:address":"6201 NW 3rd Ave",
    "sg:city":"Miami",
    "sg:classifiers":[
        {
            "category":"Professional",
            "subcategory":"Business Services",
            "type":"Services"
        }
    ],
    "sg:phone":"+1 305 756 9972",
    "sg:postcode":"33150",
    "sg:province":"FL",
    "sg:tags":[
        "telemarketing"
    ],
    "wof:name":"S W",
    "wof:placetype":"venue"
},
  "geometry": {"coordinates":[-80.20211999999999,25.833396],"type":"Point"}
}