{
  "type": "Feature",
  "properties": {
    "iso:country":"US",
    "sg:address":"3002 Forest Rd",
    "sg:city":"Eustis",
    "sg:classifiers":[
        {
            "category":"Home & Garden",
            "subcategory":"Home Furnishings",
            "type":"Retail Goods"
        }
    ],
    "sg:phone":"+1 352 483 1785",
    "sg:postcode":"32726",
    "sg:province":"FL",
    "wof:name":"Upholstery Shoppe Lake County",
    "wof:placetype":"venue"
},
  "geometry": {"coordinates":[-81.64885700000001,28.849964],"type":"Point"}
}