{
  "type": "Feature",
  "properties": {
    "iso:country":"US",
    "sg:address":"5710 SW 91st Ave",
    "sg:city":"Miami",
    "sg:classifiers":[
        {
            "category":"Personal",
            "type":"Services"
        },
        {
            "category":"Professional",
            "subcategory":"Detective & Security Services",
            "type":"Services"
        },
        {
            "category":"Manufacturing",
            "subcategory":"Building Materials",
            "type":"Manufacturing & Wholesale Goods"
        }
    ],
    "sg:phone":"+1 305 273 1066",
    "sg:postcode":"33173",
    "sg:province":"FL",
    "sg:tags":[
        "control",
        "monitoring",
        "fire",
        "alarm",
        "system",
        "systems-wholesale",
        "medical",
        "manufacturer"
    ],
    "wof:name":"Pro Technical Support Corp",
    "wof:placetype":"venue"
},
  "geometry": {"coordinates":[-80.341999,25.715062],"type":"Point"}
}