{
  "type": "Feature",
  "properties": {
    "addr:full":"11974 Blackheath Cir Orlando FL 32837",
    "addr:housenumber":"11974",
    "addr:postcode":"32837",
    "addr:street":"Blackheath Cir",
    "iso:country":"US",
    "sg:address":"11974 Blackheath Cir",
    "sg:city":"Orlando",
    "sg:classifiers":[
        {
            "category":"Freight",
            "type":"Transportation"
        }
    ],
    "sg:phone":"+1 407 816 3893",
    "sg:postcode":"32837",
    "sg:province":"FL",
    "sg:tags":[
        "operator",
        "local",
        "trucking"
    ],
    "wof:name":"Cruz Way Trucking Inc",
    "wof:placetype":"venue"
},
  "geometry": {"coordinates":[-81.397519,28.395098],"type":"Point"}
}