{
  "type": "Feature",
  "properties": {
    "addr:full":"2021 Wilson St Hollywood FL 33020",
    "addr:housenumber":"2021",
    "addr:postcode":"33020",
    "addr:street":"Wilson St",
    "iso:country":"US",
    "sg:address":"2021 Wilson St",
    "sg:city":"Hollywood",
    "sg:classifiers":[
        {
            "category":"Building & Trades",
            "subcategory":"Construction",
            "type":"Services"
        }
    ],
    "sg:phone":"+1 954 929 5122",
    "sg:postcode":"33020",
    "sg:province":"FL",
    "sg:tags":[
        "contractor"
    ],
    "wof:name":"Y2k Installation Inc",
    "wof:placetype":"venue"
},
  "geometry": {"coordinates":[-80.14779799999999,26.027169],"type":"Point"}
}