{
  "type": "Feature",
  "properties": {
    "iso:country":"US",
    "sg:address":"44 Bream St",
    "sg:city":"Haines City",
    "sg:classifiers":[
        {
            "category":"Building & Trades",
            "subcategory":"Construction",
            "type":"Services"
        }
    ],
    "sg:phone":"+1 863 439 2298",
    "sg:postcode":"33844",
    "sg:province":"FL",
    "sg:tags":[
        "contractor"
    ],
    "wof:name":"Bruces Ceramic Tile Inc",
    "wof:placetype":"venue"
},
  "geometry": {"coordinates":[-81.45513800000001,28.0298],"type":"Point"}
}