{
  "type": "Feature",
  "properties": {
    "addr:full":"1910 Park Meadows Dr Fort Myers FL 33907",
    "addr:housenumber":"1910",
    "addr:postcode":"33907",
    "addr:street":"Park Meadows Dr",
    "iso:country":"US",
    "sg:address":"1910 Park Meadows Dr",
    "sg:city":"Fort Myers",
    "sg:classifiers":[
        {
            "category":"Professional",
            "subcategory":"Advertising",
            "type":"Services"
        }
    ],
    "sg:phone":"+1 239 274 5552",
    "sg:postcode":"33907",
    "sg:province":"FL",
    "wof:name":"CARSPONSORSHIP.COM",
    "wof:placetype":"venue"
},
  "geometry": {"coordinates":[-81.88282700000001,26.56697],"type":"Point"}
}