{
  "type": "Feature",
  "properties": {
    "iso:country":"US",
    "sg:address":"1966 Lane Ave S",
    "sg:city":"Jacksonville",
    "sg:classifiers":[
        {
            "category":"Wholesale",
            "subcategory":"Machinery & Supplies",
            "type":"Manufacturing & Wholesale Goods"
        }
    ],
    "sg:phone":"+1 904 389 1115",
    "sg:postcode":"32210",
    "sg:province":"FL",
    "sg:tags":[
        "generator"
    ],
    "sg:website":"http://www.premierpowersystems.com",
    "wof:name":"Premier Power Systems, Inc.",
    "wof:placetype":"venue"
},
  "geometry": {"coordinates":[-81.755256,30.282834],"type":"Point"}
}