{
  "type": "Feature",
  "properties": {
    "addr:full":"1472 Mercy Dr Orlando FL 32808",
    "addr:housenumber":"1472",
    "addr:postcode":"32808",
    "addr:street":"Mercy Dr",
    "iso:country":"US",
    "sg:address":"1472 Mercy Dr",
    "sg:city":"Orlando",
    "sg:classifiers":[
        {
            "category":"Restaurant",
            "type":"Food & Drink"
        }
    ],
    "sg:phone":"+1 407 521 0000",
    "sg:postcode":"32808",
    "sg:province":"FL",
    "sg:tags":[
        "caterer"
    ],
    "wof:name":"J & P Catering & Cakes",
    "wof:placetype":"venue"
},
  "geometry": {"coordinates":[-81.430592,28.561966],"type":"Point"}
}