{
  "type": "Feature",
  "properties": {
    "iso:country":"US",
    "sg:address":"1100 Lee Wagener Blvd",
    "sg:city":"Fort Lauderdale",
    "sg:classifiers":[
        {
            "category":"Professional",
            "subcategory":"Lawyer & Legal Services",
            "type":"Services"
        }
    ],
    "sg:phone":"+1 954 359 3172",
    "sg:postcode":"33315",
    "sg:province":"FL",
    "wof:name":"Moulis & Assoc LLP",
    "wof:placetype":"venue"
},
  "geometry": {"coordinates":[-80.155023,26.070225],"type":"Point"}
}