{
  "type": "Feature",
  "properties": {
    "addr:full":"5996 N Blue Angel Pkwy Pensacola FL 32526",
    "addr:housenumber":"5996",
    "addr:postcode":"32526",
    "addr:street":"N Blue Angel Pkwy",
    "iso:country":"US",
    "sg:address":"5996 N Blue Angel Pkwy",
    "sg:city":"Pensacola",
    "sg:classifiers":[
        {
            "category":"Banks & Credit Unions",
            "subcategory":"Bank",
            "type":"Services"
        }
    ],
    "sg:phone":"+1 850 456 4545",
    "sg:postcode":"32526",
    "sg:province":"FL",
    "wof:name":"Monsanto Employees CU",
    "wof:placetype":"venue"
},
  "geometry": {"coordinates":[-87.324404,30.457661],"type":"Point"}
}