{
  "type": "Feature",
  "properties": {
    "iso:country":"US",
    "sg:address":"12000 Indian Rocks Rd",
    "sg:city":"Largo",
    "sg:classifiers":[
        {
            "category":"Restaurant",
            "type":"Food & Drink"
        }
    ],
    "sg:menulink":"http://www.allmenus.com/fl/clearwater/241152-yayas-flame-broiled-chicken/menu/",
    "sg:phone":"+1 727 595 7911",
    "sg:postcode":"33774",
    "sg:province":"FL",
    "sg:tags":[
        "new",
        "american"
    ],
    "wof:name":"YaYa's Flame Broiled Chicken",
    "wof:placetype":"venue"
},
  "geometry": {"coordinates":[-82.832387,27.88135],"type":"Point"}
}