{
  "type": "Feature",
  "properties": {
    "addr:full":"1 E Hall St Avon Park FL 33825",
    "addr:housenumber":"1",
    "addr:postcode":"33825",
    "addr:street":"E Hall St",
    "iso:country":"US",
    "sg:address":"1 E Hall St",
    "sg:city":"Avon Park",
    "sg:classifiers":[
        {
            "category":"Professional",
            "subcategory":"Business Services",
            "type":"Services"
        }
    ],
    "sg:phone":"+1 863 453 6829",
    "sg:postcode":"33825",
    "sg:province":"FL",
    "sg:tags":[
        "water",
        "treatment"
    ],
    "wof:name":"Williams Water Treatment",
    "wof:placetype":"venue"
},
  "geometry": {"coordinates":[-81.500112,27.589219],"type":"Point"}
}