{
  "type": "Feature",
  "properties": {
    "addr:full":"120 9th Ave N Jacksonville Bch FL 32250",
    "addr:housenumber":"120",
    "addr:postcode":"32250",
    "addr:street":"9Th Ave N",
    "iso:country":"US",
    "sg:address":"120 9th Ave N",
    "sg:city":"Jacksonville Bch",
    "sg:classifiers":[
        {
            "category":"Health Services",
            "subcategory":"Doctor",
            "type":"Services"
        }
    ],
    "sg:phone":"+1 904 246 7554",
    "sg:postcode":"32250",
    "sg:province":"FL",
    "sg:tags":[
        "dentist"
    ],
    "wof:name":"Roy F David DDS",
    "wof:placetype":"venue"
},
  "geometry": {"coordinates":[-81.392279,30.297569],"type":"Point"}
}