{
  "type": "Feature",
  "properties": {
    "addr:full":"1325 Windsor Dr Clearwater FL 33756",
    "addr:housenumber":"1325",
    "addr:postcode":"33756",
    "addr:street":"Windsor Dr",
    "iso:country":"US",
    "sg:address":"1325 Windsor Dr",
    "sg:city":"Clearwater",
    "sg:classifiers":[
        {
            "category":"Home & Garden",
            "subcategory":"Building Materials",
            "type":"Retail Goods"
        }
    ],
    "sg:phone":"+1 727 584 7770",
    "sg:postcode":"33756",
    "sg:province":"FL",
    "sg:tags":[
        "windows"
    ],
    "wof:name":"Archer's Doors & Windows Inc",
    "wof:placetype":"venue"
},
  "geometry": {"coordinates":[-82.780366,27.933588],"type":"Point"}
}