{
  "type": "Feature",
  "properties": {
    "addr:full":"9672 Bayou Bluff Dr Jacksonville FL 32257",
    "addr:housenumber":"9672",
    "addr:postcode":"32257",
    "addr:street":"Bayou Bluff Dr",
    "iso:country":"US",
    "sg:address":"9672 Bayou Bluff Dr",
    "sg:city":"Jacksonville",
    "sg:classifiers":[
        {
            "category":"Professional",
            "subcategory":"Accounting & Tax Preparation",
            "type":"Services"
        }
    ],
    "sg:phone":"+1 904 880 2810",
    "sg:postcode":"32257",
    "sg:province":"FL",
    "sg:tags":[
        "return"
    ],
    "wof:name":"Royal Tax Service",
    "wof:placetype":"venue"
},
  "geometry": {"coordinates":[-81.609075,30.202017],"type":"Point"}
}