{
  "type": "Feature",
  "properties": {
    "addr:full":"1010 Michelle Ct Tavares FL 32778",
    "addr:housenumber":"1010",
    "addr:postcode":"32778",
    "addr:street":"Michelle Ct",
    "iso:country":"US",
    "sg:address":"1010 Michelle Ct",
    "sg:city":"Tavares",
    "sg:classifiers":[
        {
            "category":"Health Services",
            "subcategory":"Medical Lab",
            "type":"Services"
        }
    ],
    "sg:phone":"+1 352 343 5802",
    "sg:postcode":"32778",
    "sg:province":"FL",
    "sg:tags":[
        "laboratory"
    ],
    "wof:name":"Crown & Quill Productions Inc",
    "wof:placetype":"venue"
},
  "geometry": {"coordinates":[-81.717603,28.802526],"type":"Point"}
}