{
  "type": "Feature",
  "properties": {
    "iso:country":"US",
    "sg:address":"320 SW 1 St",
    "sg:city":"Gainesville",
    "sg:classifiers":[
        {
            "category":"Professional",
            "subcategory":"Business Services",
            "type":"Services"
        }
    ],
    "sg:phone":"+1 352 377 3345",
    "sg:postcode":"32601",
    "sg:province":"FL",
    "sg:tags":[
        "interior",
        "consultant",
        "design",
        "decorator"
    ],
    "wof:name":"Warrington's Fine Interiors",
    "wof:placetype":"venue"
},
  "geometry": {"coordinates":[-82.3259,29.648505],"type":"Point"}
}