{
  "type": "Feature",
  "properties": {
    "addr:full":"35 E Blue Heron Blvd Riviera Beach FL 33404",
    "addr:housenumber":"35",
    "addr:postcode":"33404",
    "addr:street":"E Blue Heron Blvd",
    "iso:country":"US",
    "sg:address":"35 E Blue Heron Blvd",
    "sg:city":"Riviera Beach",
    "sg:classifiers":[
        {
            "category":"Retail",
            "subcategory":"Animal Services",
            "type":"Services"
        }
    ],
    "sg:phone":"+1 561 842 3044",
    "sg:postcode":"33404",
    "sg:province":"FL",
    "sg:tags":[
        "pet",
        "grooming",
        "washing"
    ],
    "wof:name":"Canine Beauty Salon",
    "wof:placetype":"venue"
},
  "geometry": {"coordinates":[-80.050392,26.783202],"type":"Point"}
}