{
  "type": "Feature",
  "properties": {
    "addr:full":"561 Cassat Ave Jacksonville FL 32254",
    "addr:housenumber":"561",
    "addr:postcode":"32254",
    "addr:street":"Cassat Ave",
    "iso:country":"US",
    "sg:address":"561 Cassat Ave",
    "sg:city":"Jacksonville",
    "sg:classifiers":[
        {
            "category":"Autos & Motor Vehicles",
            "subcategory":"Auto Supplies",
            "type":"Retail Goods"
        }
    ],
    "sg:phone":"+1 904 388 7366",
    "sg:postcode":"32254",
    "sg:province":"FL",
    "sg:tags":[
        "automobile",
        "parts"
    ],
    "wof:name":"Autozone",
    "wof:placetype":"venue"
},
  "geometry": {"coordinates":[-81.73068000000001,30.318127],"type":"Point"}
}