{
  "type": "Feature",
  "properties": {
    "addr:full":"901 Saxon Blvd Orange City FL 32763",
    "addr:housenumber":"901",
    "addr:postcode":"32763",
    "addr:street":"Saxon Blvd",
    "iso:country":"US",
    "sg:address":"901 Saxon Blvd",
    "sg:city":"Orange City",
    "sg:classifiers":[
        {
            "category":"Home & Garden",
            "subcategory":"Building Materials",
            "type":"Retail Goods"
        }
    ],
    "sg:phone":"+1 386 775 6030",
    "sg:postcode":"32763",
    "sg:province":"FL",
    "wof:name":"Lowes",
    "wof:placetype":"venue"
},
  "geometry": {"coordinates":[-81.28810199999999,28.91123],"type":"Point"}
}