{
  "type": "Feature",
  "properties": {
    "addr:full":"1890 NW 95th Ave Miami FL 33172",
    "addr:housenumber":"1890",
    "addr:postcode":"33172",
    "addr:street":"Nw 95Th Ave",
    "iso:country":"US",
    "sg:address":"1890 NW 95th Ave",
    "sg:city":"Miami",
    "sg:classifiers":[
        {
            "category":"Wholesale",
            "subcategory":"Electrical",
            "type":"Manufacturing & Wholesale Goods"
        }
    ],
    "sg:phone":"+1 305 436 1310",
    "sg:postcode":"33172",
    "sg:province":"FL",
    "sg:tags":[
        "telephone",
        "cellular",
        "accessory"
    ],
    "wof:name":"Bca International",
    "wof:placetype":"venue"
},
  "geometry": {"coordinates":[-80.349388,25.791095],"type":"Point"}
}