{
  "type": "Feature",
  "properties": {
    "iso:country":"US",
    "sg:address":"109 Racetrack Rd NE",
    "sg:city":"Fort Walton Bch",
    "sg:classifiers":[
        {
            "category":"Personal",
            "subcategory":"Beauty Salon",
            "type":"Services"
        }
    ],
    "sg:phone":"+1 850 862 7877",
    "sg:postcode":"32547",
    "sg:province":"FL",
    "sg:tags":[
        "shop",
        "manicuring"
    ],
    "wof:name":"Tran Nail",
    "wof:placetype":"venue"
},
  "geometry": {"coordinates":[-86.60796999999999,30.446376],"type":"Point"}
}