{
  "type": "Feature",
  "properties": {
    "iso:country":"US",
    "sg:address":"9802 Dixie Hwy",
    "sg:city":"Miami",
    "sg:classifiers":[
        {
            "category":"Banks & Credit Unions",
            "subcategory":"Bank",
            "type":"Services"
        }
    ],
    "sg:phone":"+1 305 670 8881",
    "sg:postcode":"33156",
    "sg:province":"FL",
    "sg:tags":[
        "cashing",
        "check"
    ],
    "wof:name":"Check Cashing Store Inc",
    "wof:placetype":"venue"
},
  "geometry": {"coordinates":[-80.318275,25.677691],"type":"Point"}
}