{
  "type": "Feature",
  "properties": {
    "iso:country":"US",
    "sg:address":"3915 Alton Road",
    "sg:city":"Miami Beach",
    "sg:classifiers":[
        {
            "category":"Bakery",
            "type":"Food & Drink"
        },
        {
            "category":"Bagels",
            "subcategory":"None",
            "type":"Food & Drink"
        }
    ],
    "sg:phone":"+1 305 538 0300",
    "sg:postcode":"33140",
    "sg:province":"FL",
    "wof:name":"Bagel Time",
    "wof:placetype":"venue"
},
  "geometry": {"coordinates":[-80.135401,25.812575],"type":"Point"}
}