{
  "type": "Feature",
  "properties": {
    "iso:country":"US",
    "sg:address":"4401 SW 13th St",
    "sg:city":"Gainesville",
    "sg:classifiers":[
        {
            "category":"Travel",
            "subcategory":"Hotels & Motels",
            "type":"Entertainment"
        }
    ],
    "sg:phone":"+1 352 371 3811",
    "sg:postcode":"32608",
    "sg:province":"FL",
    "sg:tags":[
        "operation"
    ],
    "wof:name":"Budget Inn",
    "wof:placetype":"venue"
},
  "geometry": {"coordinates":[-82.34205900000001,29.605524],"type":"Point"}
}