{
  "type": "Feature",
  "properties": {
    "addr:full":"1403 Dunn Ave Jacksonville FL 32218",
    "addr:housenumber":"1403",
    "addr:postcode":"32218",
    "addr:street":"Dunn Ave",
    "iso:country":"US",
    "sg:address":"1403 Dunn Ave",
    "sg:city":"Jacksonville",
    "sg:classifiers":[
        {
            "category":"Health Services",
            "subcategory":"Doctor",
            "type":"Services"
        }
    ],
    "sg:phone":"+1 904 696 6900",
    "sg:postcode":"32218",
    "sg:province":"FL",
    "sg:tags":[
        "medicine",
        "physician",
        "surgeon",
        "internal",
        "surgeons"
    ],
    "wof:name":"Del Rosario Eufrocina MD",
    "wof:placetype":"venue"
},
  "geometry": {"coordinates":[-81.66964299999999,30.429819],"type":"Point"}
}