{
  "type": "Feature",
  "properties": {
    "iso:country":"US",
    "sg:address":"5970 Reynosa Dr",
    "sg:city":"Pensacola",
    "sg:classifiers":[
        {
            "category":"Wholesale",
            "subcategory":"Durable Goods & Equipment",
            "type":"Manufacturing & Wholesale Goods"
        }
    ],
    "sg:phone":"+1 850 478 4330",
    "sg:postcode":"32504",
    "sg:province":"FL",
    "sg:tags":[
        "importer"
    ],
    "wof:name":"Dan Buck Intl Inc",
    "wof:placetype":"venue"
},
  "geometry": {"coordinates":[-87.171069,30.489035],"type":"Point"}
}