{
  "type": "Feature",
  "properties": {
    "addr:full":"8 Ormond Green Blvd Ormond Beach FL 32174",
    "addr:housenumber":"8",
    "addr:postcode":"32174",
    "addr:street":"Ormond Green Blvd",
    "iso:country":"US",
    "sg:address":"8 Ormond Green Blvd",
    "sg:city":"Ormond Beach",
    "sg:classifiers":[
        {
            "category":"Wholesale",
            "subcategory":"Metals & Minerals",
            "type":"Manufacturing & Wholesale Goods"
        }
    ],
    "sg:phone":"+1 386 671 9326",
    "sg:postcode":"32174",
    "sg:province":"FL",
    "sg:tags":[
        "center",
        "aluminum"
    ],
    "wof:name":"Affordable Aluminum Constr Svc",
    "wof:placetype":"venue"
},
  "geometry": {"coordinates":[-81.118213,29.277673],"type":"Point"}
}