{
  "type": "Feature",
  "properties": {
    "addr:full":"6149 W Park Ln Lake Worth FL 33467",
    "addr:housenumber":"6149",
    "addr:postcode":"33467",
    "addr:street":"W Park Ln",
    "iso:country":"US",
    "sg:address":"6149 W Park Ln",
    "sg:city":"Lake Worth",
    "sg:classifiers":[
        {
            "category":"Recreation",
            "type":"Entertainment"
        }
    ],
    "sg:phone":"+1 561 968 5311",
    "sg:postcode":"33467",
    "sg:province":"FL",
    "sg:tags":[
        "stable"
    ],
    "wof:name":"Broad Horizons Equestrian Ctr",
    "wof:placetype":"venue"
},
  "geometry": {"coordinates":[-80.22001299999999,26.575177],"type":"Point"}
}