{
  "type": "Feature",
  "properties": {
    "iso:country":"US",
    "sg:address":"3542 N Federal Hwy",
    "sg:city":"Fort Lauderdale",
    "sg:classifiers":[
        {
            "category":"Home & Garden",
            "subcategory":"Furniture",
            "type":"Retail Goods"
        }
    ],
    "sg:phone":"+1 954 567 0900",
    "sg:postcode":"33308",
    "sg:province":"FL",
    "wof:name":"Wood & Iron Furniture",
    "wof:placetype":"venue"
},
  "geometry": {"coordinates":[-80.11943599999999,26.171841],"type":"Point"}
}