{
  "type": "Feature",
  "properties": {
    "addr:full":"300 5th Ave S Naples FL 34102",
    "addr:housenumber":"300",
    "addr:postcode":"34102",
    "addr:street":"5Th Ave S",
    "iso:country":"US",
    "sg:address":"300 5th Ave S",
    "sg:city":"Naples",
    "sg:classifiers":[
        {
            "category":"Government",
            "subcategory":"Office",
            "type":"Public Place"
        }
    ],
    "sg:phone":"+1 239 262 5591",
    "sg:postcode":"34102",
    "sg:province":"FL",
    "sg:tags":[
        "state",
        "program",
        "health"
    ],
    "wof:name":"For The Health Of It",
    "wof:placetype":"venue"
},
  "geometry": {"coordinates":[-81.80174,26.141081],"type":"Point"}
}