{
  "type": "Feature",
  "properties": {
    "iso:country":"US",
    "sg:address":"2957 W State Road 434 Ste 400",
    "sg:city":"Longwood",
    "sg:classifiers":[
        {
            "category":"Communications",
            "subcategory":"Film & Video Production",
            "type":"Services"
        }
    ],
    "sg:phone":"+1 407 774 1110",
    "sg:postcode":"32779",
    "sg:province":"FL",
    "sg:website":"http://www.icmediapro.com",
    "wof:name":"IC Media Productions",
    "wof:placetype":"venue"
},
  "geometry": {"coordinates":[-81.416121,28.686219],"type":"Point"}
}