{
  "type": "Feature",
  "properties": {
    "iso:country":"US",
    "sg:address":"8201 Chancellor Dr",
    "sg:city":"Orlando",
    "sg:classifiers":[
        {
            "category":"Retail",
            "subcategory":"Auto Rental",
            "type":"Services"
        }
    ],
    "sg:phone":"+1 407 850 0191",
    "sg:postcode":"32809",
    "sg:province":"FL",
    "sg:tags":[
        "truck"
    ],
    "sg:website":"http://www.ryder.com/",
    "wof:name":"Ryder",
    "wof:placetype":"venue"
},
  "geometry": {"coordinates":[-81.41211699999999,28.447411],"type":"Point"}
}