{
  "type": "Feature",
  "properties": {
    "iso:country":"US",
    "sg:address":"6482 Tanglewood Dr NE",
    "sg:city":"Saint Petersburg",
    "sg:classifiers":[
        {
            "category":"Restaurant",
            "type":"Food & Drink"
        }
    ],
    "sg:phone":"+1 727 526 8494",
    "sg:postcode":"33702",
    "sg:province":"FL",
    "sg:tags":[
        "eating"
    ],
    "wof:name":"Fat Freds Bar Bq Inc",
    "wof:placetype":"venue"
},
  "geometry": {"coordinates":[-82.61079700000001,27.829994],"type":"Point"}
}