{
  "type": "Feature",
  "properties": {
    "iso:country":"US",
    "sg:address":"3419 Johnson St",
    "sg:city":"Hollywood",
    "sg:classifiers":[
        {
            "category":"Health Services",
            "subcategory":"Doctor",
            "type":"Services"
        }
    ],
    "sg:phone":"+1 954 989 2800",
    "sg:postcode":"33021",
    "sg:province":"FL",
    "sg:tags":[
        "ophthalmologist"
    ],
    "wof:name":"Wolfe Russell M MD",
    "wof:placetype":"venue"
},
  "geometry": {"coordinates":[-80.177172,26.018351],"type":"Point"}
}