{
  "type": "Feature",
  "properties": {
    "addr:full":"10141 W Broward Blvd Plantation FL 33324",
    "addr:housenumber":"10141",
    "addr:postcode":"33324",
    "addr:street":"W Broward Blvd",
    "iso:country":"US",
    "sg:address":"10141 W Broward Blvd",
    "sg:city":"Plantation",
    "sg:classifiers":[
        {
            "category":"Wholesale",
            "subcategory":"Electrical",
            "type":"Manufacturing & Wholesale Goods"
        }
    ],
    "sg:phone":"+1 954 423 2274",
    "sg:postcode":"33324",
    "sg:province":"FL",
    "sg:tags":[
        "control",
        "security",
        "system"
    ],
    "wof:name":"Surveillance Unlimited",
    "wof:placetype":"venue"
},
  "geometry": {"coordinates":[-80.28364999999999,26.120766],"type":"Point"}
}