{
  "type": "Feature",
  "properties": {
    "addr:full":"5312 SW 6th Pl Ocala FL 34474",
    "addr:housenumber":"5312",
    "addr:postcode":"34474",
    "addr:street":"Sw 6Th Pl",
    "iso:country":"US",
    "sg:address":"5312 SW 6th Pl",
    "sg:city":"Ocala",
    "sg:classifiers":[
        {
            "category":"Banks & Credit Unions",
            "subcategory":"Bank",
            "type":"Services"
        }
    ],
    "sg:phone":"+1 352 237 1763",
    "sg:postcode":"34474",
    "sg:province":"FL",
    "wof:name":"Florida Credit Union",
    "wof:placetype":"venue"
},
  "geometry": {"coordinates":[-82.207549,29.180599],"type":"Point"}
}