{
  "type": "Feature",
  "properties": {
    "iso:country":"US",
    "sg:address":"900 N Broadwalk",
    "sg:city":"Hollywood",
    "sg:classifiers":[
        {
            "category":"Restaurant",
            "type":"Food & Drink"
        }
    ],
    "sg:menulink":"http://www.allmenus.com/fl/hollywood/46865-ocean-alley-restaurant/menu/",
    "sg:phone":"+1 954 921 6171",
    "sg:postcode":"33019",
    "sg:province":"FL",
    "sg:tags":[
        "american"
    ],
    "wof:name":"Ocean Alley Restaurant",
    "wof:placetype":"venue"
},
  "geometry": {"coordinates":[-80.11552500000001,26.017313],"type":"Point"}
}