{
  "type": "Feature",
  "properties": {
    "iso:country":"US",
    "sg:address":"6020 Woodside Dr",
    "sg:city":"Jacksonville",
    "sg:classifiers":[
        {
            "category":"Home & Garden",
            "subcategory":"Carpets & Floor Coverings",
            "type":"Retail Goods"
        }
    ],
    "sg:phone":"+1 904 772 0203",
    "sg:postcode":"32210",
    "sg:province":"FL",
    "wof:name":"Creamer Floors Inc",
    "wof:placetype":"venue"
},
  "geometry": {"coordinates":[-81.741264,30.271052],"type":"Point"}
}