{
  "type": "Feature",
  "properties": {
    "iso:country":"US",
    "sg:address":"402 Office Plz",
    "sg:city":"Tallahassee",
    "sg:classifiers":[
        {
            "category":"Professional",
            "subcategory":"Lawyer & Legal Services",
            "type":"Services"
        }
    ],
    "sg:phone":"+1 850 878 6404",
    "sg:postcode":"32301",
    "sg:province":"FL",
    "sg:tags":[
        "attorney"
    ],
    "sg:website":"www.dealerlawyer.com",
    "wof:name":"Myers & Fuller",
    "wof:placetype":"venue"
},
  "geometry": {"coordinates":[-84.259728,30.447139],"type":"Point"}
}