{
  "type": "Feature",
  "properties": {
    "iso:country":"US",
    "sg:address":"2334 S Cypress Bend Dr",
    "sg:city":"Pompano Beach",
    "sg:classifiers":[
        {
            "category":"Building & Trades",
            "subcategory":"Construction",
            "type":"Services"
        }
    ],
    "sg:phone":"+1 239 482 8547",
    "sg:postcode":"33069",
    "sg:province":"FL",
    "sg:tags":[
        "marine",
        "industrial",
        "coating"
    ],
    "wof:name":"D & E Distributing Co",
    "wof:placetype":"venue"
},
  "geometry": {"coordinates":[-80.15342,26.214978],"type":"Point"}
}