{
  "type": "Feature",
  "properties": {
    "iso:country":"US",
    "sg:address":"806 Cypress Grove Ln",
    "sg:city":"Pompano Beach",
    "sg:classifiers":[
        {
            "category":"Local Transit",
            "type":"Transportation"
        }
    ],
    "sg:phone":"+1 954 298 7664",
    "sg:postcode":"33069",
    "sg:province":"FL",
    "sg:tags":[
        "limousine"
    ],
    "wof:name":"Ride Reliable Roni",
    "wof:placetype":"venue"
},
  "geometry": {"coordinates":[-80.18548699999999,26.216199],"type":"Point"}
}