{
  "type": "Feature",
  "properties": {
    "iso:country":"US",
    "sg:address":"4550 Rock Springs Rd",
    "sg:city":"Apopka",
    "sg:classifiers":[
        {
            "category":"Food & Beverages",
            "subcategory":"Groceries & Convenience Stores",
            "type":"Retail Goods"
        }
    ],
    "sg:phone":"+1 407 521 8452",
    "sg:postcode":"32712",
    "sg:province":"FL",
    "wof:name":"Daniel's Quick Stop",
    "wof:placetype":"venue"
},
  "geometry": {"coordinates":[-81.509024,28.75297],"type":"Point"}
}