{
  "type": "Feature",
  "properties": {
    "iso:country":"US",
    "sg:address":"4735 S Texas Ave",
    "sg:city":"Orlando",
    "sg:classifiers":[
        {
            "category":"Professional",
            "subcategory":"Advertising",
            "type":"Services"
        }
    ],
    "sg:phone":"+1 407 855 3256",
    "sg:postcode":"32839",
    "sg:province":"FL",
    "sg:tags":[
        "consultant"
    ],
    "wof:name":"A K N Advertising",
    "wof:placetype":"venue"
},
  "geometry": {"coordinates":[-81.409183,28.49383],"type":"Point"}
}