{
  "type": "Feature",
  "properties": {
    "addr:full":"4800 N Nob Hill Rd Sunrise FL 33351",
    "addr:housenumber":"4800",
    "addr:postcode":"33351",
    "addr:street":"N Nob Hill Rd",
    "iso:country":"US",
    "sg:address":"4800 N Nob Hill Rd",
    "sg:city":"Sunrise",
    "sg:classifiers":[
        {
            "category":"Health Services",
            "subcategory":"Nursing And Care Facility",
            "type":"Services"
        }
    ],
    "sg:phone":"+1 954 577 3600",
    "sg:postcode":"33351",
    "sg:province":"FL",
    "sg:tags":[
        "home",
        "convalescent"
    ],
    "wof:name":"Sunrise Health & Rehab Ctr",
    "wof:placetype":"venue"
},
  "geometry": {"coordinates":[-80.28419700000001,26.185575],"type":"Point"}
}