{
  "type": "Feature",
  "properties": {
    "addr:full":"310 N Moon Ave Brandon FL 33510",
    "addr:housenumber":"310",
    "addr:postcode":"33510",
    "addr:street":"N Moon Ave",
    "iso:country":"US",
    "sg:address":"310 N Moon Ave",
    "sg:city":"Brandon",
    "sg:classifiers":[
        {
            "category":"Health Services",
            "subcategory":"Clinic",
            "type":"Services"
        }
    ],
    "sg:phone":"+1 813 651 0502",
    "sg:postcode":"33510",
    "sg:province":"FL",
    "sg:tags":[
        "specialty",
        "outpatient"
    ],
    "wof:name":"Epsis Care Inc",
    "wof:placetype":"venue"
},
  "geometry": {"coordinates":[-82.287673,27.943662],"type":"Point"}
}