{
  "type": "Feature",
  "properties": {
    "iso:country":"US",
    "sg:address":"1944 S Combee Rd",
    "sg:city":"Lakeland",
    "sg:classifiers":[
        {
            "category":"Bars & Pubs",
            "type":"Food & Drink"
        }
    ],
    "sg:phone":"+1 863 666 3577",
    "sg:postcode":"33801",
    "sg:province":"FL",
    "sg:tags":[
        "lounge",
        "cocktail"
    ],
    "wof:name":"Sterling Package Lounge & Bar",
    "wof:placetype":"venue"
},
  "geometry": {"coordinates":[-81.907725,28.020231],"type":"Point"}
}