{
  "type": "Feature",
  "properties": {
    "addr:full":"11413 SW 150th Dr Miami FL 33176",
    "addr:housenumber":"11413",
    "addr:postcode":"33176",
    "addr:street":"Sw 150Th Dr",
    "iso:country":"US",
    "sg:address":"11413 SW 150th Dr",
    "sg:city":"Miami",
    "sg:classifiers":[
        {
            "category":"Building & Trades",
            "subcategory":"Construction",
            "type":"Services"
        }
    ],
    "sg:phone":"+1 305 254 1837",
    "sg:postcode":"33176",
    "sg:province":"FL",
    "sg:tags":[
        "house"
    ],
    "wof:name":"Cordoba Homes Inc",
    "wof:placetype":"venue"
},
  "geometry": {"coordinates":[-80.378271,25.62892],"type":"Point"}
}