{
  "type": "Feature",
  "properties": {
    "iso:country":"US",
    "sg:address":"11046 W Flagler St",
    "sg:city":"Miami",
    "sg:classifiers":[
        {
            "category":"Health Services",
            "subcategory":"Doctor",
            "type":"Services"
        }
    ],
    "sg:phone":"+1 305 225 1978",
    "sg:postcode":"33174",
    "sg:province":"FL",
    "wof:name":"West Medical Group",
    "wof:placetype":"venue"
},
  "geometry": {"coordinates":[-80.375603,25.7684],"type":"Point"}
}