{
  "type": "Feature",
  "properties": {
    "addr:full":"408 Bailey Rd Venice FL 34292",
    "addr:housenumber":"408",
    "addr:postcode":"34292",
    "addr:street":"Bailey Rd",
    "iso:country":"US",
    "sg:address":"408 Bailey Rd",
    "sg:city":"Venice",
    "sg:classifiers":[
        {
            "category":"Manufacturing",
            "subcategory":"Retail Goods",
            "type":"Manufacturing & Wholesale Goods"
        }
    ],
    "sg:phone":"+1 941 485 2562",
    "sg:postcode":"34292",
    "sg:province":"FL",
    "sg:tags":[
        "lead",
        "mfg"
    ],
    "wof:name":"Hearts & Wings & Other Things",
    "wof:placetype":"venue"
},
  "geometry": {"coordinates":[-82.404284,27.095053],"type":"Point"}
}