{
  "type": "Feature",
  "properties": {
    "iso:country":"US",
    "sg:address":"1984 SW Bayshore Blvd",
    "sg:city":"Port St Lucie",
    "sg:classifiers":[
        {
            "category":"Building & Trades",
            "subcategory":"Cleaning & Sanitation",
            "type":"Services"
        },
        {
            "category":"Home & Garden",
            "subcategory":"Home Furnishings",
            "type":"Retail Goods"
        }
    ],
    "sg:phone":"+1 772 879 1200",
    "sg:postcode":"34984",
    "sg:province":"FL",
    "sg:tags":[
        "lighting",
        "fixture",
        "maintenance"
    ],
    "wof:name":"Crystal Lighting Center",
    "wof:placetype":"venue"
},
  "geometry": {"coordinates":[-80.356139,27.274852],"type":"Point"}
}