{
  "type": "Feature",
  "properties": {
    "iso:country":"US",
    "sg:address":"11090 Losco Junction Dr",
    "sg:city":"Jacksonville",
    "sg:classifiers":[
        {
            "category":"Wholesale",
            "subcategory":"Stationery",
            "type":"Manufacturing & Wholesale Goods"
        }
    ],
    "sg:phone":"+1 904 268 2502",
    "sg:postcode":"32257",
    "sg:province":"FL",
    "sg:tags":[
        "supply"
    ],
    "wof:name":"Norman B White Jr Inc",
    "wof:placetype":"venue"
},
  "geometry": {"coordinates":[-81.59241299999999,30.172614],"type":"Point"}
}