{
  "type": "Feature",
  "properties": {
    "iso:country":"US",
    "sg:address":"111 NW 6 St",
    "sg:city":"Gainesville",
    "sg:classifiers":[
        {
            "category":"Shopping",
            "subcategory":"Bicycles & Sporting Goods",
            "type":"Retail Goods"
        }
    ],
    "sg:phone":"+1 352 372 8301",
    "sg:postcode":"32601",
    "sg:province":"FL",
    "sg:tags":[
        "gun",
        "gunsmith"
    ],
    "wof:name":"Sapp's Pawn Gun & Archery Shop",
    "wof:placetype":"venue"
},
  "geometry": {"coordinates":[-82.33075700000001,29.652692],"type":"Point"}
}