{
  "type": "Feature",
  "properties": {
    "addr:full":"5060 Seminole Pratt Whitney Rd Loxahatchee FL 33470",
    "addr:housenumber":"5060",
    "addr:postcode":"33470",
    "addr:street":"Seminole Pratt Whitney Rd",
    "iso:country":"US",
    "sg:address":"5060 Seminole Pratt Whitney Rd",
    "sg:city":"Loxahatchee",
    "sg:classifiers":[
        {
            "category":"Government",
            "subcategory":"Fire Station",
            "type":"Public Place"
        }
    ],
    "sg:phone":"+1 561 793 2358",
    "sg:postcode":"33470",
    "sg:province":"FL",
    "sg:tags":[
        "department"
    ],
    "wof:name":"Fire Dept- Fire Station 22",
    "wof:placetype":"venue"
},
  "geometry": {"coordinates":[-80.30735799999999,26.753041],"type":"Point"}
}