{
  "type": "Feature",
  "properties": {
    "iso:country":"US",
    "sg:address":"2029 Vinings Cir",
    "sg:city":"Wellington",
    "sg:classifiers":[
        {
            "category":"Building & Trades",
            "subcategory":"Construction",
            "type":"Services"
        }
    ],
    "sg:phone":"+1 561 792 1352",
    "sg:postcode":"33414",
    "sg:province":"FL",
    "sg:tags":[
        "general",
        "contractor"
    ],
    "wof:name":"Jon Thomas & Co Inc",
    "wof:placetype":"venue"
},
  "geometry": {"coordinates":[-80.241463,26.650204],"type":"Point"}
}