{
  "type": "Feature",
  "properties": {
    "iso:country":"US",
    "sg:address":"5050 Sunbeam Rd",
    "sg:city":"Jacksonville",
    "sg:classifiers":[
        {
            "category":"Professional",
            "subcategory":"Detective & Security Services",
            "type":"Services"
        }
    ],
    "sg:phone":"+1 904 262 4659",
    "sg:postcode":"32257",
    "sg:province":"FL",
    "sg:tags":[
        "repair",
        "computer"
    ],
    "wof:name":"Access Systems LLC",
    "wof:placetype":"venue"
},
  "geometry": {"coordinates":[-81.58150999999999,30.20602],"type":"Point"}
}