{
  "type": "Feature",
  "properties": {
    "addr:full":"1815 S Gadsden St Tallahassee FL 32301",
    "addr:housenumber":"1815",
    "addr:postcode":"32301",
    "addr:street":"S Gadsden St",
    "iso:country":"US",
    "sg:address":"1815 S Gadsden St",
    "sg:city":"Tallahassee",
    "sg:classifiers":[
        {
            "category":"Government",
            "subcategory":"Jail",
            "type":"Public Place"
        }
    ],
    "sg:phone":"+1 850 414 7224",
    "sg:postcode":"32301",
    "sg:province":"FL",
    "sg:tags":[
        "parole"
    ],
    "wof:name":"Tallahassee South Parole Off",
    "wof:placetype":"venue"
},
  "geometry": {"coordinates":[-84.278164,30.424955],"type":"Point"}
}