{
  "type": "Feature",
  "properties": {
    "iso:country":"US",
    "sg:address":"3151 N Orange Blossom Trl",
    "sg:city":"Kissimmee",
    "sg:classifiers":[
        {
            "category":"Education",
            "subcategory":"School",
            "type":"Public Place"
        }
    ],
    "sg:phone":"+1 407 931 4803",
    "sg:postcode":"34744",
    "sg:province":"FL",
    "sg:website":"www.osceola.k12.fl.us",
    "wof:name":"Osceola County School For Arts",
    "wof:placetype":"venue"
},
  "geometry": {"coordinates":[-81.403684,28.336235],"type":"Point"}
}