{
  "type": "Feature",
  "properties": {
    "addr:full":"2777 NE 86th Ln Anthony FL 32617",
    "addr:housenumber":"2777",
    "addr:postcode":"32617",
    "addr:street":"Ne 86Th Ln",
    "iso:country":"US",
    "sg:address":"2777 NE 86th Ln",
    "sg:city":"Anthony",
    "sg:classifiers":[
        {
            "category":"Retail",
            "subcategory":"Auto Repair",
            "type":"Services"
        }
    ],
    "sg:phone":"+1 352 629 7729",
    "sg:postcode":"32617",
    "sg:province":"FL",
    "sg:tags":[
        "repairing",
        "automobile"
    ],
    "wof:name":"Woods Garage",
    "wof:placetype":"venue"
},
  "geometry": {"coordinates":[-82.100622,29.277593],"type":"Point"}
}