{
  "type": "Feature",
  "properties": {
    "iso:country":"US",
    "sg:address":"6101 Ave B",
    "sg:city":"Jacksonville",
    "sg:classifiers":[
        {
            "category":"Social Services",
            "subcategory":"Child Care",
            "type":"Services"
        }
    ],
    "sg:phone":"+1 904 765 7504",
    "sg:postcode":"32209",
    "sg:province":"FL",
    "sg:tags":[
        "day"
    ],
    "wof:name":"Victory Land",
    "wof:placetype":"venue"
},
  "geometry": {"coordinates":[-81.69905199999999,30.38177],"type":"Point"}
}