{
  "type": "Feature",
  "properties": {
    "addr:full":"6767 Knightswood Dr Orlando FL 32818",
    "addr:housenumber":"6767",
    "addr:postcode":"32818",
    "addr:street":"Knightswood Dr",
    "iso:country":"US",
    "sg:address":"6767 Knightswood Dr",
    "sg:city":"Orlando",
    "sg:classifiers":[
        {
            "category":"Real Estate",
            "subcategory":"Surveying",
            "type":"Services"
        }
    ],
    "sg:phone":"+1 407 292 0207",
    "sg:postcode":"32818",
    "sg:province":"FL",
    "sg:tags":[
        "surveyor",
        "land",
        "engineer"
    ],
    "wof:name":"Dann, T M Construction Layout",
    "wof:placetype":"venue"
},
  "geometry": {"coordinates":[-81.47259200000001,28.630139],"type":"Point"}
}