{
  "type": "Feature",
  "properties": {
    "addr:full":"515 Kelly St Destin FL 32541",
    "addr:housenumber":"515",
    "addr:postcode":"32541",
    "addr:street":"Kelly St",
    "iso:country":"US",
    "sg:address":"515 Kelly St",
    "sg:city":"Destin",
    "sg:classifiers":[
        {
            "category":"Building & Trades",
            "subcategory":"Plumbing",
            "type":"Services"
        }
    ],
    "sg:phone":"+1 850 654 5893",
    "sg:postcode":"32541",
    "sg:province":"FL",
    "sg:tags":[
        "contractor"
    ],
    "wof:name":"Bayside Airconditioning & Htg",
    "wof:placetype":"venue"
},
  "geometry": {"coordinates":[-86.49986699999999,30.402299],"type":"Point"}
}