{
  "type": "Feature",
  "properties": {
    "addr:full":"201 189th Ter Sunny Isles Bch FL 33160",
    "addr:housenumber":"201",
    "addr:postcode":"33160",
    "addr:street":"189Th Ter Sunny",
    "iso:country":"US",
    "sg:address":"201 189th Ter",
    "sg:city":"Sunny Isles Bch",
    "sg:classifiers":[
        {
            "category":"Professional",
            "type":"Services"
        }
    ],
    "sg:phone":"+1 305 692 4412",
    "sg:postcode":"33160",
    "sg:province":"FL",
    "sg:tags":[
        "establishment"
    ],
    "wof:name":"J D Int Corp",
    "wof:placetype":"venue"
},
  "geometry": {"coordinates":[-80.125376,25.951062],"type":"Point"}
}