{
  "type": "Feature",
  "properties": {
    "addr:full":"1428 N Lakeside Dr Lake Worth FL 33460",
    "addr:housenumber":"1428",
    "addr:postcode":"33460",
    "addr:street":"N Lakeside Dr",
    "iso:country":"US",
    "sg:address":"1428 N Lakeside Dr",
    "sg:city":"Lake Worth",
    "sg:classifiers":[
        {
            "category":"Building & Trades",
            "subcategory":"Construction",
            "type":"Services"
        }
    ],
    "sg:phone":"+1 561 533 0579",
    "sg:postcode":"33460",
    "sg:province":"FL",
    "sg:tags":[
        "hanging",
        "contractor"
    ],
    "wof:name":"Evolution Studios Inc",
    "wof:placetype":"venue"
},
  "geometry": {"coordinates":[-80.049271,26.633009],"type":"Point"}
}