{
  "type": "Feature",
  "properties": {
    "addr:full":"37 S Federal Hwy Dania FL 33004",
    "addr:housenumber":"37",
    "addr:postcode":"33004",
    "addr:street":"S Federal Hwy",
    "iso:country":"US",
    "sg:address":"37 S Federal Hwy",
    "sg:city":"Dania",
    "sg:classifiers":[
        {
            "category":"Shopping",
            "type":"Retail Goods"
        }
    ],
    "sg:phone":"+1 954 925 1914",
    "sg:postcode":"33004",
    "sg:province":"FL",
    "sg:tags":[
        "art",
        "gallery",
        "dealer"
    ],
    "wof:name":"Tatem Gallery & Studio",
    "wof:placetype":"venue"
},
  "geometry": {"coordinates":[-80.143559,26.051167],"type":"Point"}
}