{
  "type": "Feature",
  "properties": {
    "addr:full":"926 W Tharpe St Tallahassee FL 32303",
    "addr:housenumber":"926",
    "addr:postcode":"32303",
    "addr:street":"W Tharpe St",
    "iso:country":"US",
    "sg:address":"926 W Tharpe St",
    "sg:city":"Tallahassee",
    "sg:classifiers":[
        {
            "category":"Insurance",
            "subcategory":"Insurance Agent",
            "type":"Services"
        }
    ],
    "sg:phone":"+1 850 385 1601",
    "sg:postcode":"32303",
    "sg:province":"FL",
    "wof:name":"Jerrell Lowery Insurance",
    "wof:placetype":"venue"
},
  "geometry": {"coordinates":[-84.298473,30.463727],"type":"Point"}
}