{
  "type": "Feature",
  "properties": {
    "iso:country":"US",
    "sg:address":"3301 Rickenbacker Cswy",
    "sg:city":"Key Biscayne",
    "sg:classifiers":[
        {
            "category":"Recreation",
            "subcategory":"Boat Charter",
            "type":"Entertainment"
        }
    ],
    "sg:phone":"+1 305 361 7368",
    "sg:postcode":"33149",
    "sg:province":"FL",
    "sg:tags":[
        "boating"
    ],
    "wof:name":"Key Biscayne Boat Rentals Inc",
    "wof:placetype":"venue"
},
  "geometry": {"coordinates":[-80.175797,25.745899],"type":"Point"}
}