{
  "type": "Feature",
  "properties": {
    "iso:country":"US",
    "sg:address":"1212 W New Hampshire St",
    "sg:city":"Orlando",
    "sg:classifiers":[
        {
            "category":"Building & Trades",
            "subcategory":"Landscaping Services",
            "type":"Services"
        }
    ],
    "sg:phone":"+1 407 648 0836",
    "sg:postcode":"32804",
    "sg:province":"FL",
    "sg:tags":[
        "landscape"
    ],
    "wof:name":"Oacis",
    "wof:placetype":"venue"
},
  "geometry": {"coordinates":[-81.396638,28.567332],"type":"Point"}
}