{
  "type": "Feature",
  "properties": {
    "iso:country":"US",
    "sg:address":"3834 Exchange Ave",
    "sg:city":"Naples",
    "sg:classifiers":[
        {
            "category":"Retail",
            "subcategory":"Repair Shop",
            "type":"Services"
        }
    ],
    "sg:phone":"+1 239 643 4323",
    "sg:postcode":"34104",
    "sg:province":"FL",
    "sg:tags":[
        "equipment",
        "protection",
        "installation",
        "lightning"
    ],
    "wof:name":"Lightning Protection Systems",
    "wof:placetype":"venue"
},
  "geometry": {"coordinates":[-81.76431700000001,26.158633],"type":"Point"}
}