{
  "type": "Feature",
  "properties": {
    "iso:country":"US",
    "sg:address":"6020 NW 84th Ave",
    "sg:city":"Miami",
    "sg:classifiers":[
        {
            "category":"Professional",
            "subcategory":"Business Services",
            "type":"Services"
        }
    ],
    "sg:phone":"+1 305 468 3609",
    "sg:postcode":"33166",
    "sg:province":"FL",
    "sg:tags":[
        "telemarketing"
    ],
    "wof:name":"O L Distributors",
    "wof:placetype":"venue"
},
  "geometry": {"coordinates":[-80.33394,25.827085],"type":"Point"}
}