{
  "type": "Feature",
  "properties": {
    "iso:country":"US",
    "sg:address":"1790 W 49th St",
    "sg:city":"Hialeah",
    "sg:classifiers":[
        {
            "category":"Banks & Credit Unions",
            "subcategory":"Financial Services",
            "type":"Services"
        }
    ],
    "sg:phone":"+1 786 639 0025",
    "sg:postcode":"33012",
    "sg:province":"FL",
    "sg:tags":[
        "card-merchant",
        "card"
    ],
    "wof:name":"Paramount Appraisals Inc",
    "wof:placetype":"venue"
},
  "geometry": {"coordinates":[-80.318983,25.86652],"type":"Point"}
}