{
  "type": "Feature",
  "properties": {
    "iso:country":"US",
    "sg:address":"5800 France Ave",
    "sg:city":"Jacksonville",
    "sg:classifiers":[
        {
            "category":"Autos & Motor Vehicles",
            "subcategory":"Automobile Sales",
            "type":"Retail Goods"
        }
    ],
    "sg:phone":"+1 904 783 2020",
    "sg:postcode":"32254",
    "sg:province":"FL",
    "sg:tags":[
        "used",
        "classic"
    ],
    "sg:website":"www.donbarrymustang.com",
    "wof:name":"Don Barry Mustangs",
    "wof:placetype":"venue"
},
  "geometry": {"coordinates":[-81.749849,30.316771],"type":"Point"}
}