{
  "type": "Feature",
  "properties": {
    "addr:full":"494 Elkwood Ct Kissimmee FL 34743",
    "addr:housenumber":"494",
    "addr:postcode":"34743",
    "addr:street":"Elkwood Ct",
    "iso:country":"US",
    "sg:address":"494 Elkwood Ct",
    "sg:city":"Kissimmee",
    "sg:classifiers":[
        {
            "category":"Building & Trades",
            "subcategory":"Construction",
            "type":"Services"
        }
    ],
    "sg:phone":"+1 407 348 9076",
    "sg:postcode":"34743",
    "sg:province":"FL",
    "sg:tags":[
        "carpentry",
        "contractor"
    ],
    "wof:name":"Tina Wenige Carpentry",
    "wof:placetype":"venue"
},
  "geometry": {"coordinates":[-81.364181,28.332566],"type":"Point"}
}