{
  "type": "Feature",
  "properties": {
    "iso:country":"US",
    "sg:address":"6891 NW 74th St",
    "sg:city":"Medley",
    "sg:classifiers":[
        {
            "category":"Manufacturing",
            "subcategory":"Paper Products",
            "type":"Manufacturing & Wholesale Goods"
        }
    ],
    "sg:phone":"+1 305 888 2331",
    "sg:postcode":"33166",
    "sg:province":"FL",
    "sg:tags":[
        "paperboard",
        "mills"
    ],
    "sg:website":"www.smurfit.com",
    "wof:name":"Jefferson Smurfit Corp",
    "wof:placetype":"venue"
},
  "geometry": {"coordinates":[-80.306425,25.841219],"type":"Point"}
}