{
  "type": "Feature",
  "properties": {
    "iso:country":"US",
    "sg:address":"4794 SW 72nd Ave",
    "sg:city":"Miami",
    "sg:classifiers":[
        {
            "category":"Health Services",
            "subcategory":"Clinic",
            "type":"Services"
        }
    ],
    "sg:phone":"+1 305 648 0084",
    "sg:postcode":"33155",
    "sg:province":"FL",
    "wof:name":"Lumars Health Care Corp",
    "wof:placetype":"venue"
},
  "geometry": {"coordinates":[-80.31081,25.726355],"type":"Point"}
}