{
  "type": "Feature",
  "properties": {
    "addr:full":"100 NE 2nd St Boca Raton FL 33432",
    "addr:housenumber":"100",
    "addr:postcode":"33432",
    "addr:street":"Ne 2Nd St",
    "iso:country":"US",
    "sg:address":"100 NE 2nd St",
    "sg:city":"Boca Raton",
    "sg:classifiers":[
        {
            "category":"Restaurant",
            "type":"Food & Drink"
        }
    ],
    "sg:phone":"+1 561 470 6250",
    "sg:postcode":"33432",
    "sg:province":"FL",
    "wof:name":"Su Shi Thai",
    "wof:placetype":"venue"
},
  "geometry": {"coordinates":[-80.083731,26.352366],"type":"Point"}
}