{
  "type": "Feature",
  "properties": {
    "iso:country":"US",
    "sg:address":"19635 W Lake Dr",
    "sg:city":"Hialeah",
    "sg:classifiers":[
        {
            "category":"Health Services",
            "subcategory":"Dentist",
            "type":"Services"
        }
    ],
    "sg:phone":"+1 305 816 0096",
    "sg:postcode":"33015",
    "sg:province":"FL",
    "wof:name":"The Dental Genie Staffing Service",
    "wof:placetype":"venue"
},
  "geometry": {"coordinates":[-80.323341,25.951717],"type":"Point"}
}