{
  "type": "Feature",
  "properties": {
    "addr:full":"1799 SW 3rd Ave Miami FL 33129",
    "addr:housenumber":"1799",
    "addr:postcode":"33129",
    "addr:street":"Sw 3Rd Ave",
    "iso:country":"US",
    "sg:address":"1799 SW 3rd Ave",
    "sg:city":"Miami",
    "sg:classifiers":[
        {
            "category":"Health Services",
            "subcategory":"Doctor",
            "type":"Services"
        }
    ],
    "sg:phone":"+1 305 858 3737",
    "sg:postcode":"33129",
    "sg:province":"FL",
    "wof:name":"Reina Monica MD",
    "wof:placetype":"venue"
},
  "geometry": {"coordinates":[-80.200862,25.760128],"type":"Point"}
}