{
  "type": "Feature",
  "properties": {
    "addr:full":"8213 SE 3rd Ct Ocala FL 34480",
    "addr:housenumber":"8213",
    "addr:postcode":"34480",
    "addr:street":"Se 3Rd Ct",
    "iso:country":"US",
    "sg:address":"8213 SE 3rd Ct",
    "sg:city":"Ocala",
    "sg:classifiers":[
        {
            "category":"Autos & Motor Vehicles",
            "subcategory":"Auto Supplies",
            "type":"Retail Goods"
        },
        {
            "category":"Wholesale",
            "subcategory":"Auto Parts",
            "type":"Manufacturing & Wholesale Goods"
        },
        {
            "category":"Shopping",
            "subcategory":"Discount & Variety Stores",
            "type":"Retail Goods"
        }
    ],
    "sg:phone":"+1 352 854 7887",
    "sg:postcode":"34480",
    "sg:province":"FL",
    "sg:tags":[
        "surplus",
        "automobile",
        "accessory",
        "rebuilt-wholesale",
        "supplies-used",
        "rebuilt",
        "salvage",
        "merchandise",
        "manufacturer"
    ],
    "wof:name":"Ocala Junk & Auto Parts",
    "wof:placetype":"venue"
},
  "geometry": {"coordinates":[-82.132462,29.103409],"type":"Point"}
}