{
  "type": "Feature",
  "properties": {
    "iso:country":"US",
    "sg:address":"23 Lupine Ln",
    "sg:city":"Debary",
    "sg:classifiers":[
        {
            "category":"Real Estate",
            "subcategory":"Real Estate Operator",
            "type":"Services"
        }
    ],
    "sg:phone":"+1 386 668 7685",
    "sg:postcode":"32713",
    "sg:province":"FL",
    "sg:tags":[
        "apartment"
    ],
    "wof:name":"Lake Susan Apts",
    "wof:placetype":"venue"
},
  "geometry": {"coordinates":[-81.307503,28.892599],"type":"Point"}
}