{
  "type": "Feature",
  "properties": {
    "addr:full":"1210 International Pkwy S Lake Mary FL 32746",
    "addr:housenumber":"1210",
    "addr:postcode":"32746",
    "addr:street":"International Pkwy S Lake Mary",
    "iso:country":"US",
    "sg:address":"1210 International Pkwy S",
    "sg:city":"Lake Mary",
    "sg:classifiers":[
        {
            "category":"Freight",
            "type":"Transportation"
        },
        {
            "category":"Professional",
            "subcategory":"Printing & Photocopies",
            "type":"Services"
        }
    ],
    "sg:phone":"+1 407 804 1818",
    "sg:postcode":"32746",
    "sg:province":"FL",
    "sg:tags":[
        "shipping"
    ],
    "sg:website":"www.fedex.com/us/office/",
    "wof:name":"FedEx Office Print & Ship Center",
    "wof:placetype":"venue"
},
  "geometry": {"coordinates":[-81.367142,28.754868],"type":"Point"}
}