{
  "type": "Feature",
  "properties": {
    "iso:country":"US",
    "sg:address":"3901 W Sligh Ave",
    "sg:city":"Tampa",
    "sg:classifiers":[
        {
            "category":"Professional",
            "type":"Services"
        }
    ],
    "sg:phone":"+1 813 881 0376",
    "sg:postcode":"33614",
    "sg:province":"FL",
    "wof:name":"R&R General Tractor Service",
    "wof:placetype":"venue"
},
  "geometry": {"coordinates":[-82.508043,28.010761],"type":"Point"}
}