{
  "type": "Feature",
  "properties": {
    "addr:full":"4750 Jog Rd Greenacres FL 33467",
    "addr:housenumber":"4750",
    "addr:postcode":"33467",
    "addr:street":"Jog Rd",
    "iso:country":"US",
    "sg:address":"4750 Jog Rd",
    "sg:city":"Greenacres",
    "sg:classifiers":[
        {
            "category":"Health Services",
            "subcategory":"Doctor",
            "type":"Services"
        }
    ],
    "sg:phone":"+1 561 432 1718",
    "sg:postcode":"33467",
    "sg:province":"FL",
    "sg:tags":[
        "dentist"
    ],
    "wof:name":"Elite Dental",
    "wof:placetype":"venue"
},
  "geometry": {"coordinates":[-80.147065,26.606143],"type":"Point"}
}