{
  "type": "Feature",
  "properties": {
    "iso:country":"US",
    "sg:address":"1306 NW 10th St",
    "sg:city":"Ocala",
    "sg:classifiers":[
        {
            "category":"Personal",
            "subcategory":"Tattoo Parlor",
            "type":"Services"
        }
    ],
    "sg:phone":"+1 352 840 7123",
    "sg:postcode":"34475",
    "sg:province":"FL",
    "sg:tags":[
        "tattooing"
    ],
    "wof:name":"Skin Deep Tattoo",
    "wof:placetype":"venue"
},
  "geometry": {"coordinates":[-82.149524,29.197032],"type":"Point"}
}