{
  "type": "Feature",
  "properties": {
    "iso:country":"US",
    "sg:address":"3700 N US Hwy 441",
    "sg:city":"Ocala",
    "sg:classifiers":[
        {
            "category":"Autos & Motor Vehicles",
            "subcategory":"Automobile Sales",
            "type":"Retail Goods"
        }
    ],
    "sg:phone":"+1 352 351 1979",
    "sg:postcode":"34475",
    "sg:province":"FL",
    "sg:tags":[
        "used"
    ],
    "wof:name":"Z Cars Of Ocala",
    "wof:placetype":"venue"
},
  "geometry": {"coordinates":[-82.147972,29.225126],"type":"Point"}
}