{
  "type": "Feature",
  "properties": {
    "addr:full":"11701 W Okeechobee Rd Hialeah FL 33018",
    "addr:housenumber":"11701",
    "addr:postcode":"33018",
    "addr:street":"W Okeechobee Rd",
    "iso:country":"US",
    "sg:address":"11701 W Okeechobee Rd",
    "sg:city":"Hialeah",
    "sg:classifiers":[
        {
            "category":"Restaurant",
            "type":"Food & Drink"
        }
    ],
    "sg:phone":"+1 305 362 8866",
    "sg:postcode":"33018",
    "sg:province":"FL",
    "sg:tags":[
        "style",
        "family",
        "lunch",
        "american",
        "brunch",
        "breakfast"
    ],
    "sg:website":"http://www.dennys.com",
    "wof:name":"Denny's",
    "wof:placetype":"venue"
},
  "geometry": {"coordinates":[-80.357681,25.88065],"type":"Point"}
}