{
  "type": "Feature",
  "properties": {
    "addr:full":"10200 SW 77th Ct Miami FL 33156",
    "addr:housenumber":"10200",
    "addr:postcode":"33156",
    "addr:street":"Sw 77Th Ct",
    "iso:country":"US",
    "sg:address":"10200 SW 77th Ct",
    "sg:city":"Miami",
    "sg:classifiers":[
        {
            "category":"Retail",
            "subcategory":"Auto Rental",
            "type":"Services"
        }
    ],
    "sg:phone":"+1 305 556 5581",
    "sg:postcode":"33156",
    "sg:province":"FL",
    "sg:tags":[
        "car"
    ],
    "wof:name":"Enterprise Rent-A-Car",
    "wof:placetype":"venue"
},
  "geometry": {"coordinates":[-80.320795,25.675922],"type":"Point"}
}