{
  "type": "Feature",
  "properties": {
    "addr:full":"1514 NW 17th Ct Crystal River FL 34428",
    "addr:housenumber":"1514",
    "addr:postcode":"34428",
    "addr:street":"Nw 17Th Ct",
    "iso:country":"US",
    "sg:address":"1514 NW 17th Ct",
    "sg:city":"Crystal River",
    "sg:classifiers":[
        {
            "category":"Wholesale",
            "subcategory":"Non-durable Goods",
            "type":"Manufacturing & Wholesale Goods"
        }
    ],
    "sg:phone":"+1 352 564 2486",
    "sg:postcode":"34428",
    "sg:province":"FL",
    "wof:name":"Bagleys Cove Products",
    "wof:placetype":"venue"
},
  "geometry": {"coordinates":[-82.62011800000001,28.90839],"type":"Point"}
}