{
  "type": "Feature",
  "properties": {
    "iso:country":"US",
    "sg:address":"6205 Johns Rd",
    "sg:city":"Tampa",
    "sg:classifiers":[
        {
            "category":"Freight",
            "type":"Transportation"
        }
    ],
    "sg:phone":"+1 813 887 4763",
    "sg:postcode":"33634",
    "sg:province":"FL",
    "sg:tags":[
        "delivery"
    ],
    "wof:name":"Mid-South Express Delivery",
    "wof:placetype":"venue"
},
  "geometry": {"coordinates":[-82.54947900000001,28.007506],"type":"Point"}
}