{
  "type": "Feature",
  "properties": {
    "addr:full":"172 1st St Boca Grande FL 33921",
    "addr:housenumber":"172",
    "addr:postcode":"33921",
    "addr:street":"1St St",
    "iso:country":"US",
    "sg:address":"172 1st St",
    "sg:city":"Boca Grande",
    "sg:classifiers":[
        {
            "category":"Professional",
            "subcategory":"Art Services",
            "type":"Services"
        }
    ],
    "sg:phone":"+1 941 964 0085",
    "sg:postcode":"33921",
    "sg:province":"FL",
    "sg:tags":[
        "artist"
    ],
    "wof:name":"Lisa Mullet Gallery",
    "wof:placetype":"venue"
},
  "geometry": {"coordinates":[-82.256784,26.746707],"type":"Point"}
}