{
  "type": "Feature",
  "properties": {
    "addr:full":"5054 Normandy Blvd Jacksonville FL 32205",
    "addr:housenumber":"5054",
    "addr:postcode":"32205",
    "addr:street":"Normandy Blvd",
    "iso:country":"US",
    "sg:address":"5054 Normandy Blvd",
    "sg:city":"Jacksonville",
    "sg:classifiers":[
        {
            "category":"Restaurant",
            "type":"Food & Drink"
        }
    ],
    "sg:menulink":"http://www.allmenus.com/fl/jacksonville/207480-taco-bell/menu/",
    "sg:phone":"+1 904 781 6623",
    "sg:postcode":"32205",
    "sg:province":"FL",
    "sg:tags":[
        "mexican"
    ],
    "wof:name":"Taco Bell",
    "wof:placetype":"venue"
},
  "geometry": {"coordinates":[-81.731729,30.3092],"type":"Point"}
}