{
  "type": "Feature",
  "properties": {
    "addr:full":"3804 Desoto Blvd Palm Harbor FL 34683",
    "addr:housenumber":"3804",
    "addr:postcode":"34683",
    "addr:street":"Desoto Blvd",
    "iso:country":"US",
    "sg:address":"3804 Desoto Blvd",
    "sg:city":"Palm Harbor",
    "sg:classifiers":[
        {
            "category":"Retail",
            "subcategory":"Repair Shop",
            "type":"Services"
        }
    ],
    "sg:phone":"+1 727 937 9794",
    "sg:postcode":"34683",
    "sg:province":"FL",
    "sg:tags":[
        "repairing",
        "lawn",
        "mower"
    ],
    "wof:name":"B T Repair",
    "wof:placetype":"venue"
},
  "geometry": {"coordinates":[-82.770377,28.106438],"type":"Point"}
}