{
  "type": "Feature",
  "properties": {
    "iso:country":"US",
    "sg:address":"3202 Henderson Blvd # 101",
    "sg:city":"Tampa",
    "sg:classifiers":[
        {
            "category":"Professional",
            "type":"Services"
        }
    ],
    "sg:phone":"+1 813 731 1817",
    "sg:postcode":"33609",
    "sg:province":"FL",
    "sg:tags":[
        "transportation"
    ],
    "wof:name":"R & D Transport 1",
    "wof:placetype":"venue"
},
  "geometry": {"coordinates":[-82.49575900000001,27.944321],"type":"Point"}
}