{
  "type": "Feature",
  "properties": {
    "iso:country":"US",
    "sg:address":"4556 Becker Ave",
    "sg:city":"Callahan",
    "sg:classifiers":[
        {
            "category":"Building & Trades",
            "subcategory":"Construction",
            "type":"Services"
        }
    ],
    "sg:phone":"+1 904 545 2208",
    "sg:postcode":"32011",
    "sg:province":"FL",
    "sg:tags":[
        "welding"
    ],
    "wof:name":"Frattle Stairs & Rails In",
    "wof:placetype":"venue"
},
  "geometry": {"coordinates":[-81.801616,30.530135],"type":"Point"}
}