{
  "type": "Feature",
  "properties": {
    "addr:full":"217 Goolsby Blvd Deerfield Beach FL 33442",
    "addr:housenumber":"217",
    "addr:postcode":"33442",
    "addr:street":"Goolsby Blvd",
    "iso:country":"US",
    "sg:address":"217 Goolsby Blvd",
    "sg:city":"Deerfield Beach",
    "sg:classifiers":[
        {
            "category":"Banks & Credit Unions",
            "subcategory":"Bank",
            "type":"Services"
        }
    ],
    "sg:phone":"+1 954 481 2274",
    "sg:postcode":"33442",
    "sg:province":"FL",
    "sg:tags":[
        "broker",
        "mortgage"
    ],
    "wof:name":"J & R Financial Group LLC",
    "wof:placetype":"venue"
},
  "geometry": {"coordinates":[-80.126008,26.312469],"type":"Point"}
}