{
  "type": "Feature",
  "properties": {
    "addr:full":"353 Ronald St Cocoa FL 32927",
    "addr:housenumber":"353",
    "addr:postcode":"32927",
    "addr:street":"Ronald St",
    "iso:country":"US",
    "sg:address":"353 Ronald St",
    "sg:city":"Cocoa",
    "sg:classifiers":[
        {
            "category":"Building & Trades",
            "subcategory":"Landscaping Services",
            "type":"Services"
        }
    ],
    "sg:phone":"+1 321 636 8965",
    "sg:postcode":"32927",
    "sg:province":"FL",
    "sg:tags":[
        "tree"
    ],
    "wof:name":"Top Dog Tree Service",
    "wof:placetype":"venue"
},
  "geometry": {"coordinates":[-80.768162,28.458791],"type":"Point"}
}