{
  "type": "Feature",
  "properties": {
    "addr:full":"4161 NW 5th St Fort Lauderdale FL 33317",
    "addr:housenumber":"4161",
    "addr:postcode":"33317",
    "addr:street":"Nw 5Th St",
    "iso:country":"US",
    "sg:address":"4161 NW 5th St",
    "sg:city":"Fort Lauderdale",
    "sg:classifiers":[
        {
            "category":"Insurance",
            "subcategory":"Hazard Insurance",
            "type":"Services"
        }
    ],
    "sg:phone":"+1 954 581 9993",
    "sg:postcode":"33317",
    "sg:province":"FL",
    "sg:tags":[
        "company",
        "holding"
    ],
    "wof:name":"21st Century Holding Company",
    "wof:placetype":"venue"
},
  "geometry": {"coordinates":[-80.202648,26.128369],"type":"Point"}
}