{
  "type": "Feature",
  "properties": {
    "iso:country":"US",
    "sg:address":"1620 Frances Dr",
    "sg:city":"Apopka",
    "sg:classifiers":[
        {
            "category":"Professional",
            "type":"Services"
        }
    ],
    "sg:phone":"+1 407 523 6567",
    "sg:postcode":"32703",
    "sg:province":"FL",
    "wof:name":"Deborah Force Services",
    "wof:placetype":"venue"
},
  "geometry": {"coordinates":[-81.454747,28.653875],"type":"Point"}
}