{
  "type": "Feature",
  "properties": {
    "addr:full":"754 S 51st St Tampa FL 33619",
    "addr:housenumber":"754",
    "addr:postcode":"33619",
    "addr:street":"S 51St St",
    "iso:country":"US",
    "sg:address":"754 S 51st St",
    "sg:city":"Tampa",
    "sg:classifiers":[
        {
            "category":"Building & Trades",
            "subcategory":"Equipment Rental",
            "type":"Services"
        }
    ],
    "sg:phone":"+1 813 242 8166",
    "sg:postcode":"33619",
    "sg:province":"FL",
    "sg:tags":[
        "party",
        "supply"
    ],
    "wof:name":"Party Supllies-Renting",
    "wof:placetype":"venue"
},
  "geometry": {"coordinates":[-82.399733,27.941848],"type":"Point"}
}