{
  "type": "Feature",
  "properties": {
    "addr:full":"7410 Sunset Dr Miami FL 33143",
    "addr:housenumber":"7410",
    "addr:postcode":"33143",
    "addr:street":"Sunset Dr",
    "iso:country":"US",
    "sg:address":"7410 Sunset Dr",
    "sg:city":"Miami",
    "sg:classifiers":[
        {
            "category":"Social Services",
            "subcategory":"Child Care",
            "type":"Services"
        },
        {
            "category":"Education",
            "subcategory":"Preschool",
            "type":"Public Place"
        },
        {
            "category":"Education",
            "subcategory":"School",
            "type":"Public Place"
        }
    ],
    "sg:phone":"+1 305 661 1287",
    "sg:postcode":"33143",
    "sg:province":"FL",
    "sg:tags":[
        "kindergarten",
        "elementary",
        "nursery",
        "day"
    ],
    "wof:name":"Saint Matthew's Cooperative Preschool",
    "wof:placetype":"venue"
},
  "geometry": {"coordinates":[-80.31390399999999,25.703199],"type":"Point"}
}