{
  "type": "Feature",
  "properties": {
    "iso:country":"US",
    "sg:address":"701 E 4th Ave",
    "sg:city":"Hialeah",
    "sg:classifiers":[
        {
            "category":"Organizations",
            "subcategory":"Religious Organization",
            "type":"Services"
        }
    ],
    "sg:phone":"+1 305 887 9517",
    "sg:postcode":"33010",
    "sg:province":"FL",
    "sg:tags":[
        "church"
    ],
    "wof:name":"Santuario De Corpus Christi Y Regina Coeli",
    "wof:placetype":"venue"
},
  "geometry": {"coordinates":[-80.27359800000001,25.828699],"type":"Point"}
}