{
  "type": "Feature",
  "properties": {
    "addr:full":"211 N Pine Ave Inverness FL 34450",
    "addr:housenumber":"211",
    "addr:postcode":"34450",
    "addr:street":"N Pine Ave",
    "iso:country":"US",
    "sg:address":"211 N Pine Ave",
    "sg:city":"Inverness",
    "sg:classifiers":[
        {
            "category":"Bakery",
            "type":"Food & Drink"
        }
    ],
    "sg:phone":"+1 352 726 2200",
    "sg:postcode":"34450",
    "sg:province":"FL",
    "wof:name":"Ponce's Bakery",
    "wof:placetype":"venue"
},
  "geometry": {"coordinates":[-82.33148199999999,28.837866],"type":"Point"}
}