{
  "type": "Feature",
  "properties": {
    "iso:country":"US",
    "sg:address":"4980 Tamiami Trl N",
    "sg:city":"Naples",
    "sg:classifiers":[
        {
            "category":"Health Services",
            "subcategory":"Health Practitioner",
            "type":"Services"
        }
    ],
    "sg:phone":"+1 239 649 4861",
    "sg:postcode":"34103",
    "sg:province":"FL",
    "sg:tags":[
        "psychotherapist"
    ],
    "wof:name":"Gonzalez Raquel M Lcsw",
    "wof:placetype":"venue"
},
  "geometry": {"coordinates":[-81.80027,26.207032],"type":"Point"}
}