{
  "type": "Feature",
  "properties": {
    "iso:country":"US",
    "sg:address":"2690 Ave E SW",
    "sg:city":"Winter Haven",
    "sg:classifiers":[
        {
            "category":"Retail",
            "subcategory":"Auto Repair",
            "type":"Services"
        }
    ],
    "sg:phone":"+1 863 299 9966",
    "sg:postcode":"33880",
    "sg:province":"FL",
    "sg:tags":[
        "wrecker"
    ],
    "wof:name":"Bolton's Towing",
    "wof:placetype":"venue"
},
  "geometry": {"coordinates":[-81.758847,28.018086],"type":"Point"}
}