{
  "type": "Feature",
  "properties": {
    "addr:full":"3612 E 138th Ave Tampa FL 33613",
    "addr:housenumber":"3612",
    "addr:postcode":"33613",
    "addr:street":"E 138Th Ave",
    "iso:country":"US",
    "sg:address":"3612 E 138th Ave",
    "sg:city":"Tampa",
    "sg:classifiers":[
        {
            "category":"Health Services",
            "subcategory":"Nursing And Care Facility",
            "type":"Services"
        }
    ],
    "sg:phone":"+1 813 972 8775",
    "sg:postcode":"33613",
    "sg:province":"FL",
    "sg:tags":[
        "home",
        "convalescent"
    ],
    "wof:name":"Palm Garden Of Tampa",
    "wof:placetype":"venue"
},
  "geometry": {"coordinates":[-82.421289,28.072934],"type":"Point"}
}