{
  "type": "Feature",
  "properties": {
    "addr:full":"551 Northmoor Ave N Saint Petersburg FL 33702",
    "addr:housenumber":"551",
    "addr:postcode":"33702",
    "addr:street":"Northmoor Ave N",
    "iso:country":"US",
    "sg:address":"551 Northmoor Ave N",
    "sg:city":"Saint Petersburg",
    "sg:classifiers":[
        {
            "category":"Building & Trades",
            "subcategory":"Landscaping Services",
            "type":"Services"
        }
    ],
    "sg:phone":"+1 727 521 4921",
    "sg:postcode":"33702",
    "sg:province":"FL",
    "wof:name":"Ervin T Lawn Grdn Decorations",
    "wof:placetype":"venue"
},
  "geometry": {"coordinates":[-82.643294,27.832919],"type":"Point"}
}