{
  "type": "Feature",
  "properties": {
    "iso:country":"US",
    "sg:address":"8903 Glades Rd",
    "sg:city":"Boca Raton",
    "sg:classifiers":[
        {
            "category":"Social Services",
            "type":"Services"
        }
    ],
    "sg:phone":"+1 561 479 0003",
    "sg:postcode":"33434",
    "sg:province":"FL",
    "sg:tags":[
        "referral"
    ],
    "wof:name":"Jersey Mike's Submarines",
    "wof:placetype":"venue"
},
  "geometry": {"coordinates":[-80.18487500000001,26.367969],"type":"Point"}
}