{
  "type": "Feature",
  "properties": {
    "iso:country":"US",
    "sg:address":"4172 Corporate Sq",
    "sg:city":"Naples",
    "sg:classifiers":[
        {
            "category":"Building & Trades",
            "subcategory":"Construction",
            "type":"Services"
        }
    ],
    "sg:phone":"+1 239 262 4233",
    "sg:postcode":"34104",
    "sg:province":"FL",
    "sg:tags":[
        "house",
        "contractor"
    ],
    "sg:website":"www.currentbuilders.net",
    "wof:name":"Current Builders",
    "wof:placetype":"venue"
},
  "geometry": {"coordinates":[-81.755588,26.155407],"type":"Point"}
}