{
  "type": "Feature",
  "properties": {
    "addr:full":"1516 N Dixie Hwy Hollywood FL 33020",
    "addr:housenumber":"1516",
    "addr:postcode":"33020",
    "addr:street":"N Dixie Hwy",
    "iso:country":"US",
    "sg:address":"1516 N Dixie Hwy",
    "sg:city":"Hollywood",
    "sg:classifiers":[
        {
            "category":"Wholesale",
            "subcategory":"Non-durable Goods",
            "type":"Manufacturing & Wholesale Goods"
        }
    ],
    "sg:phone":"+1 954 925 6591",
    "sg:postcode":"33020",
    "sg:province":"FL",
    "sg:tags":[
        "advertising",
        "specialty"
    ],
    "wof:name":"North South Promotions Inc",
    "wof:placetype":"venue"
},
  "geometry": {"coordinates":[-80.14983100000001,26.025067],"type":"Point"}
}