{
  "type": "Feature",
  "properties": {
    "iso:country":"US",
    "sg:address":"2025 Fowler St",
    "sg:city":"Fort Myers",
    "sg:classifiers":[
        {
            "category":"Retail",
            "subcategory":"Auto Repair",
            "type":"Services"
        }
    ],
    "sg:phone":"+1 239 337 2665",
    "sg:postcode":"33901",
    "sg:province":"FL",
    "sg:tags":[
        "repairing",
        "automobile",
        "radiator"
    ],
    "wof:name":"Auto Radiator Co Of Sw Florida",
    "wof:placetype":"venue"
},
  "geometry": {"coordinates":[-81.86228,26.640281],"type":"Point"}
}