{
  "type": "Feature",
  "properties": {
    "iso:country":"US",
    "sg:address":"26811 S Bay Dr",
    "sg:city":"Bonita Springs",
    "sg:classifiers":[
        {
            "category":"Shopping",
            "subcategory":"Clothing, Apparel, & Fashions",
            "type":"Retail Goods"
        }
    ],
    "sg:phone":"+1 239 948 2288",
    "sg:postcode":"34134",
    "sg:province":"FL",
    "wof:name":"Chico's FAS Inc",
    "wof:placetype":"venue"
},
  "geometry": {"coordinates":[-81.808177,26.351363],"type":"Point"}
}