{
  "type": "Feature",
  "properties": {
    "iso:country":"US",
    "sg:address":"2727 NW 43 St",
    "sg:city":"Gainesville",
    "sg:classifiers":[
        {
            "category":"Professional",
            "subcategory":"Lawyer & Legal Services",
            "type":"Services"
        }
    ],
    "sg:phone":"+1 352 374 8235",
    "sg:postcode":"32606",
    "sg:province":"FL",
    "sg:tags":[
        "attorney"
    ],
    "wof:name":"Kevin E Leary",
    "wof:placetype":"venue"
},
  "geometry": {"coordinates":[-82.38889500000001,29.678442],"type":"Point"}
}