{
  "type": "Feature",
  "properties": {
    "iso:country":"US",
    "sg:address":"3733 N Goldenrod Rd",
    "sg:city":"Winter Park",
    "sg:classifiers":[
        {
            "category":"Real Estate",
            "subcategory":"Real Estate Operator",
            "type":"Services"
        }
    ],
    "sg:phone":"+1 407 677 7070",
    "sg:postcode":"32792",
    "sg:province":"FL",
    "sg:tags":[
        "apartment",
        "complex"
    ],
    "wof:name":"Hunter's Ridge Apartments",
    "wof:placetype":"venue"
},
  "geometry": {"coordinates":[-81.2864,28.594101],"type":"Point"}
}