{
  "type": "Feature",
  "properties": {
    "addr:full":"30125 S Dixie Hwy Homestead FL 33033",
    "addr:housenumber":"30125",
    "addr:postcode":"33033",
    "addr:street":"S Dixie Hwy",
    "iso:country":"US",
    "sg:address":"30125 S Dixie Hwy",
    "sg:city":"Homestead",
    "sg:classifiers":[
        {
            "category":"Bakery",
            "type":"Food & Drink"
        },
        {
            "category":"Coffee & Tea",
            "type":"Food & Drink"
        },
        {
            "category":"Bagels",
            "type":"Food & Drink"
        },
        {
            "category":"Donuts",
            "type":"Food & Drink"
        }
    ],
    "sg:menulink":"http://www.allmenus.com/fl/homestead/137985-dunkin-donuts/menu/",
    "sg:phone":"+1 305 242 5000",
    "sg:postcode":"33033",
    "sg:province":"FL",
    "sg:tags":[
        "american",
        "pastry"
    ],
    "wof:name":"Dunkin' Donuts",
    "wof:placetype":"venue"
},
  "geometry": {"coordinates":[-80.458603,25.486434],"type":"Point"}
}