{
  "type": "Feature",
  "properties": {
    "iso:country":"US",
    "sg:address":"1235 Providence Blvd Ste B",
    "sg:city":"Deltona",
    "sg:classifiers":[
        {
            "category":"Shopping",
            "subcategory":"Pets & Pet Supplies",
            "type":"Retail Goods"
        }
    ],
    "sg:phone":"+1 386 575 2550",
    "sg:postcode":"32725",
    "sg:province":"FL",
    "sg:tags":[
        "store"
    ],
    "wof:name":"Pet Supermarket",
    "wof:placetype":"venue"
},
  "geometry": {"coordinates":[-81.2397,28.899401],"type":"Point"}
}