{
  "type": "Feature",
  "properties": {
    "iso:country":"US",
    "sg:address":"8000 SW 78th St",
    "sg:city":"Miami",
    "sg:classifiers":[
        {
            "category":"Professional",
            "subcategory":"Business Services",
            "type":"Services"
        }
    ],
    "sg:phone":"+1 305 888 1562",
    "sg:postcode":"33143",
    "sg:province":"FL",
    "wof:name":"RMR Services Corp",
    "wof:placetype":"venue"
},
  "geometry": {"coordinates":[-80.322142,25.697278],"type":"Point"}
}