{
  "type": "Feature",
  "properties": {
    "addr:full":"13451 Landstar Blvd Orlando FL 32824",
    "addr:housenumber":"13451",
    "addr:postcode":"32824",
    "addr:street":"Landstar Blvd",
    "iso:country":"US",
    "sg:address":"13451 Landstar Blvd",
    "sg:city":"Orlando",
    "sg:classifiers":[
        {
            "category":"Autos & Motor Vehicles",
            "subcategory":"Fuel & Gas Station",
            "type":"Retail Goods"
        }
    ],
    "sg:phone":"+1 407 856 1117",
    "sg:postcode":"32824",
    "sg:province":"FL",
    "sg:tags":[
        "station",
        "gasoline"
    ],
    "wof:name":"Mobil",
    "wof:placetype":"venue"
},
  "geometry": {"coordinates":[-81.36664399999999,28.372228],"type":"Point"}
}