{
  "type": "Feature",
  "properties": {
    "addr:full":"2456 Willow Drop Way Oviedo FL 32766",
    "addr:housenumber":"2456",
    "addr:postcode":"32766",
    "addr:street":"Willow Drop Way",
    "iso:country":"US",
    "sg:address":"2456 Willow Drop Way",
    "sg:city":"Oviedo",
    "sg:classifiers":[
        {
            "category":"Personal",
            "subcategory":"Beauty Salon",
            "type":"Services"
        }
    ],
    "sg:phone":"+1 321 765 4653",
    "sg:postcode":"32766",
    "sg:province":"FL",
    "wof:name":"Arelis Miller",
    "wof:placetype":"venue"
},
  "geometry": {"coordinates":[-81.145477,28.636601],"type":"Point"}
}