{
  "type": "Feature",
  "properties": {
    "addr:full":"1673 W 28th St West Palm Beach FL 33404",
    "addr:housenumber":"1673",
    "addr:postcode":"33404",
    "addr:street":"W 28Th St",
    "iso:country":"US",
    "sg:address":"1673 W 28th St",
    "sg:city":"West Palm Beach",
    "sg:classifiers":[
        {
            "category":"Professional",
            "subcategory":"Business Services",
            "type":"Services"
        }
    ],
    "sg:phone":"+1 561 882 0665",
    "sg:postcode":"33404",
    "sg:province":"FL",
    "wof:name":"Paperchaserz2000",
    "wof:placetype":"venue"
},
  "geometry": {"coordinates":[-80.08234899999999,26.786159],"type":"Point"}
}