{
  "type": "Feature",
  "properties": {
    "iso:country":"US",
    "sg:address":"10200 NW 29th Ave",
    "sg:city":"Miami",
    "sg:classifiers":[
        {
            "category":"Organizations",
            "subcategory":"Religious Organization",
            "type":"Services"
        }
    ],
    "sg:phone":"+1 305 696 5649",
    "sg:postcode":"33147",
    "sg:province":"FL",
    "wof:name":"Iglesia Bautista LA Hermosa",
    "wof:placetype":"venue"
},
  "geometry": {"coordinates":[-80.244643,25.868105],"type":"Point"}
}