{
  "type": "Feature",
  "properties": {
    "iso:country":"US",
    "sg:address":"3131 S Tamiami Trl",
    "sg:city":"Sarasota",
    "sg:classifiers":[
        {
            "category":"Health Services",
            "subcategory":"Doctor",
            "type":"Services"
        }
    ],
    "sg:phone":"+1 941 954 2020",
    "sg:postcode":"34239",
    "sg:province":"FL",
    "sg:tags":[
        "physician",
        "surgeon",
        "medical"
    ],
    "wof:name":"Palm Coast Eye Center",
    "wof:placetype":"venue"
},
  "geometry": {"coordinates":[-82.530098,27.305753],"type":"Point"}
}