{
  "type": "Feature",
  "properties": {
    "addr:full":"2412 Orange Ave Sanford FL 32771",
    "addr:housenumber":"2412",
    "addr:postcode":"32771",
    "addr:street":"Orange Ave",
    "iso:country":"US",
    "sg:address":"2412 Orange Ave",
    "sg:city":"Sanford",
    "sg:classifiers":[
        {
            "category":"Building & Trades",
            "subcategory":"Pest Control",
            "type":"Services"
        }
    ],
    "sg:phone":"+1 407 322 5846",
    "sg:postcode":"32771",
    "sg:province":"FL",
    "wof:name":"Beadles Pest Control",
    "wof:placetype":"venue"
},
  "geometry": {"coordinates":[-81.259553,28.787185],"type":"Point"}
}