{
  "type": "Feature",
  "properties": {
    "iso:country":"US",
    "sg:address":"2444 NE 1st Blvd",
    "sg:city":"Gainesville",
    "sg:classifiers":[
        {
            "category":"Professional",
            "subcategory":"Business Services",
            "type":"Services"
        }
    ],
    "sg:phone":"+1 352 378 8951",
    "sg:postcode":"32609",
    "sg:province":"FL",
    "sg:tags":[
        "barricade"
    ],
    "wof:name":"Protection Services Inc",
    "wof:placetype":"venue"
},
  "geometry": {"coordinates":[-82.323802,29.675431],"type":"Point"}
}