{
  "type": "Feature",
  "properties": {
    "iso:country":"US",
    "sg:address":"123 E Palmetto Park Rd",
    "sg:city":"Boca Raton",
    "sg:classifiers":[
        {
            "category":"Personal",
            "type":"Services"
        }
    ],
    "sg:phone":"+1 561 447 4100",
    "sg:postcode":"33432",
    "sg:province":"FL",
    "sg:tags":[
        "therapist",
        "massage"
    ],
    "wof:name":"Essential Therapeutic Massage",
    "wof:placetype":"venue"
},
  "geometry": {"coordinates":[-80.08408,26.350601],"type":"Point"}
}