{
  "type": "Feature",
  "properties": {
    "iso:country":"US",
    "sg:address":"10520 E Gobbler Dr",
    "sg:city":"Floral City",
    "sg:classifiers":[
        {
            "category":"Professional",
            "subcategory":"Accounting & Tax Preparation",
            "type":"Services"
        }
    ],
    "sg:phone":"+1 352 860 0073",
    "sg:postcode":"34436",
    "sg:province":"FL",
    "sg:tags":[
        "accountant"
    ],
    "wof:name":"A Counting House",
    "wof:placetype":"venue"
},
  "geometry": {"coordinates":[-82.260347,28.789646],"type":"Point"}
}