{
  "type": "Feature",
  "properties": {
    "iso:country":"US",
    "sg:address":"16771 San Carlos Blvd",
    "sg:city":"Fort Myers",
    "sg:classifiers":[
        {
            "category":"Home & Garden",
            "subcategory":"Furniture",
            "type":"Retail Goods"
        }
    ],
    "sg:phone":"+1 239 454 6666",
    "sg:postcode":"33908",
    "sg:province":"FL",
    "sg:tags":[
        "interior",
        "designer"
    ],
    "wof:name":"Interiors By Martini",
    "wof:placetype":"venue"
},
  "geometry": {"coordinates":[-81.943304,26.49738],"type":"Point"}
}