{
  "type": "Feature",
  "properties": {
    "iso:country":"US",
    "sg:address":"3443 NE Melba Dr",
    "sg:city":"Jensen Beach",
    "sg:classifiers":[
        {
            "category":"Building & Trades",
            "subcategory":"Landscaping Services",
            "type":"Services"
        }
    ],
    "sg:phone":"+1 772 334 5404",
    "sg:postcode":"34957",
    "sg:province":"FL",
    "wof:name":"David Reed Lawn Svc",
    "wof:placetype":"venue"
},
  "geometry": {"coordinates":[-80.234692,27.24643],"type":"Point"}
}