{
  "type": "Feature",
  "properties": {
    "addr:full":"10014 Medallion Bluff Ln Orlando FL 32829",
    "addr:housenumber":"10014",
    "addr:postcode":"32829",
    "addr:street":"Medallion Bluff Ln",
    "iso:country":"US",
    "sg:address":"10014 Medallion Bluff Ln",
    "sg:city":"Orlando",
    "sg:classifiers":[
        {
            "category":"Professional",
            "subcategory":"Management & Consulting",
            "type":"Services"
        }
    ],
    "sg:phone":"+1 407 948 0971",
    "sg:postcode":"32829",
    "sg:province":"FL",
    "sg:tags":[
        "sound",
        "consultant",
        "system"
    ],
    "wof:name":"Infinity Sound Inc",
    "wof:placetype":"venue"
},
  "geometry": {"coordinates":[-81.246191,28.489225],"type":"Point"}
}