{
  "type": "Feature",
  "properties": {
    "addr:full":"6511 E State Road 64 Bradenton FL 34208",
    "addr:housenumber":"6511",
    "addr:postcode":"34208",
    "addr:street":"E State Road 64",
    "iso:country":"US",
    "sg:address":"6511 E State Road 64",
    "sg:city":"Bradenton",
    "sg:classifiers":[
        {
            "category":"Autos & Motor Vehicles",
            "subcategory":"Auto Supplies",
            "type":"Retail Goods"
        },
        {
            "category":"Military Area",
            "subcategory":"Naval Base",
            "type":"Public Place"
        },
        {
            "category":"Retail",
            "subcategory":"Auto Repair",
            "type":"Services"
        }
    ],
    "sg:phone":"+1 941 747 4983",
    "sg:postcode":"34208",
    "sg:province":"FL",
    "sg:tags":[
        "equipment",
        "part",
        "trailers-repair",
        "trailer",
        "hitch"
    ],
    "sg:website":"http://www.sturdybuiltonline.com",
    "wof:name":"Sturdy Built Trailers",
    "wof:placetype":"venue"
},
  "geometry": {"coordinates":[-82.48048,27.492686],"type":"Point"}
}