{
  "type": "Feature",
  "properties": {
    "addr:full":"1506 E 3rd Ave Tampa FL 33605",
    "addr:housenumber":"1506",
    "addr:postcode":"33605",
    "addr:street":"E 3Rd Ave",
    "iso:country":"US",
    "sg:address":"1506 E 3rd Ave",
    "sg:city":"Tampa",
    "sg:classifiers":[
        {
            "category":"Manufacturing",
            "subcategory":"Tools & Machinery",
            "type":"Manufacturing & Wholesale Goods"
        }
    ],
    "sg:phone":"+1 813 248 2008",
    "sg:postcode":"33605",
    "sg:province":"FL",
    "sg:tags":[
        "machine",
        "shop"
    ],
    "wof:name":"Troya Engrg & Fabrication",
    "wof:placetype":"venue"
},
  "geometry": {"coordinates":[-82.441778,27.957475],"type":"Point"}
}