{
  "type": "Feature",
  "properties": {
    "addr:full":"7113 NW 73rd St Fort Lauderdale FL 33321",
    "addr:housenumber":"7113",
    "addr:postcode":"33321",
    "addr:street":"Nw 73Rd St",
    "iso:country":"US",
    "sg:address":"7113 NW 73rd St",
    "sg:city":"Fort Lauderdale",
    "sg:classifiers":[
        {
            "category":"Manufacturing",
            "subcategory":"Tools & Machinery",
            "type":"Manufacturing & Wholesale Goods"
        }
    ],
    "sg:phone":"+1 954 722 7521",
    "sg:postcode":"33321",
    "sg:province":"FL",
    "sg:tags":[
        "surgical",
        "mfg"
    ],
    "wof:name":"Martin Prosthetics & Orthotics",
    "wof:placetype":"venue"
},
  "geometry": {"coordinates":[-80.247443,26.212482],"type":"Point"}
}