{
  "type": "Feature",
  "properties": {
    "iso:country":"US",
    "sg:address":"1319 Lake Dr",
    "sg:city":"Casselberry",
    "sg:classifiers":[
        {
            "category":"Building & Trades",
            "subcategory":"Construction",
            "type":"Services"
        }
    ],
    "sg:phone":"+1 407 262 9311",
    "sg:postcode":"32707",
    "sg:province":"FL",
    "sg:tags":[
        "business",
        "contractor"
    ],
    "sg:website":"www.funnsun.com",
    "wof:name":"Sunrise Pools & Spas",
    "wof:placetype":"venue"
},
  "geometry": {"coordinates":[-81.31017300000001,28.674279],"type":"Point"}
}