{
  "type": "Feature",
  "properties": {
    "addr:full":"803 Jenks Ave Panama City FL 32401",
    "addr:housenumber":"803",
    "addr:postcode":"32401",
    "addr:street":"Jenks Ave",
    "iso:country":"US",
    "sg:address":"803 Jenks Ave",
    "sg:city":"Panama City",
    "sg:classifiers":[
        {
            "category":"Insurance",
            "subcategory":"Insurance Agent",
            "type":"Services"
        }
    ],
    "sg:phone":"+1 850 785 0579",
    "sg:postcode":"32401",
    "sg:province":"FL",
    "sg:tags":[
        "management",
        "disability"
    ],
    "wof:name":"Crawford & Company",
    "wof:placetype":"venue"
},
  "geometry": {"coordinates":[-85.662665,30.164241],"type":"Point"}
}