{
  "type": "Feature",
  "properties": {
    "iso:country":"US",
    "sg:address":"435 SE 3rd St",
    "sg:city":"Hialeah",
    "sg:classifiers":[
        {
            "category":"Real Estate",
            "subcategory":"Real Estate Operator",
            "type":"Services"
        }
    ],
    "sg:phone":"+1 305 887 1629",
    "sg:postcode":"33010",
    "sg:province":"FL",
    "sg:tags":[
        "building",
        "apartment"
    ],
    "wof:name":"Marquez Apartments",
    "wof:placetype":"venue"
},
  "geometry": {"coordinates":[-80.27179700000001,25.820253],"type":"Point"}
}