{
  "type": "Feature",
  "properties": {
    "addr:full":"4613 Mile Stretch Dr Holiday FL 34690",
    "addr:housenumber":"4613",
    "addr:postcode":"34690",
    "addr:street":"Mile Stretch Dr",
    "iso:country":"US",
    "sg:address":"4613 Mile Stretch Dr",
    "sg:city":"Holiday",
    "sg:classifiers":[
        {
            "category":"Autos & Motor Vehicles",
            "subcategory":"Automobile Sales",
            "type":"Retail Goods"
        }
    ],
    "sg:phone":"+1 727 938 2084",
    "sg:postcode":"34690",
    "sg:province":"FL",
    "sg:tags":[
        "used"
    ],
    "wof:name":"Java Auto Sales",
    "wof:placetype":"venue"
},
  "geometry": {"coordinates":[-82.73623499999999,28.188012],"type":"Point"}
}