{
  "type": "Feature",
  "properties": {
    "iso:country":"US",
    "sg:address":"7448 Aloma Ave. Ste 2",
    "sg:city":"Winter Park",
    "sg:classifiers":[
        {
            "category":"Health Services",
            "subcategory":"Health Practitioner",
            "type":"Services"
        },
        {
            "category":"Community Center",
            "type":"Public Place"
        }
    ],
    "sg:phone":"+1 407 478 6868",
    "sg:postcode":"32792",
    "sg:province":"FL",
    "sg:tags":[
        "nutritionist",
        "medical"
    ],
    "sg:website":"www.colonics4bodywellness.com",
    "wof:name":"Professional Therapeutic Care Center",
    "wof:placetype":"venue"
},
  "geometry": {"coordinates":[-81.28709499999999,28.609217],"type":"Point"}
}