{
  "type": "Feature",
  "properties": {
    "addr:full":"7302 W Waters Ave Tampa FL 33634",
    "addr:housenumber":"7302",
    "addr:postcode":"33634",
    "addr:street":"W Waters Ave",
    "iso:country":"US",
    "sg:address":"7302 W Waters Ave",
    "sg:city":"Tampa",
    "sg:classifiers":[
        {
            "category":"Retail",
            "subcategory":"Laundry & Dry Cleaning",
            "type":"Services"
        }
    ],
    "sg:phone":"+1 813 889 9012",
    "sg:postcode":"33634",
    "sg:province":"FL",
    "wof:name":"Three C's Coin Laundry",
    "wof:placetype":"venue"
},
  "geometry": {"coordinates":[-82.560348,28.025674],"type":"Point"}
}