{
  "type": "Feature",
  "properties": {
    "addr:full":"264 State Rd 434 E Winter Springs FL 32708",
    "addr:housenumber":"264",
    "addr:postcode":"32708",
    "addr:street":"State Rd 434 E",
    "iso:country":"US",
    "sg:address":"264 State Rd 434 E",
    "sg:city":"Winter Springs",
    "sg:classifiers":[
        {
            "category":"Real Estate",
            "subcategory":"Real Estate Operator",
            "type":"Services"
        }
    ],
    "sg:phone":"+1 407 327 5252",
    "sg:postcode":"32708",
    "sg:province":"FL",
    "sg:tags":[
        "mall",
        "shopping",
        "center"
    ],
    "wof:name":"Daytona Mall LLC",
    "wof:placetype":"venue"
},
  "geometry": {"coordinates":[-81.30095900000001,28.699227],"type":"Point"}
}