{
  "type": "Feature",
  "properties": {
    "addr:full":"112 Lake Ave Lake Worth FL 33460",
    "addr:housenumber":"112",
    "addr:postcode":"33460",
    "addr:street":"Lake Ave",
    "iso:country":"US",
    "sg:address":"112 Lake Ave",
    "sg:city":"Lake Worth",
    "sg:classifiers":[
        {
            "category":"Real Estate",
            "subcategory":"Real Estate Operator",
            "type":"Services"
        }
    ],
    "sg:phone":"+1 561 585 0186",
    "sg:postcode":"33460",
    "sg:province":"FL",
    "sg:tags":[
        "building",
        "apartment"
    ],
    "wof:name":"Lake Palm Apartments",
    "wof:placetype":"venue"
},
  "geometry": {"coordinates":[-80.05035700000001,26.615789],"type":"Point"}
}