{
  "type": "Feature",
  "properties": {
    "iso:country":"US",
    "sg:address":"1330 SW 160th Ave",
    "sg:city":"Sunrise",
    "sg:classifiers":[
        {
            "category":"Shopping",
            "subcategory":"Department Store",
            "type":"Retail Goods"
        },
        {
            "category":"Home & Garden",
            "subcategory":"Household Appliances",
            "type":"Retail Goods"
        },
        {
            "category":"Building & Trades",
            "subcategory":"Cleaning & Sanitation",
            "type":"Services"
        },
        {
            "category":"Retail",
            "subcategory":"Repair Shop",
            "type":"Services"
        },
        {
            "category":"Building & Trades",
            "subcategory":"Construction",
            "type":"Services"
        }
    ],
    "sg:phone":"+1 954 349 1061",
    "sg:postcode":"33326",
    "sg:province":"FL",
    "sg:tags":[
        "cleaner",
        "cleaners-household-dealers",
        "supply",
        "house",
        "system",
        "equipment",
        "cleaners-repair",
        "vacuum"
    ],
    "sg:website":"http://www.westonvac.com",
    "wof:name":"A All Weston Vacuum & Sewing Co",
    "wof:placetype":"venue"
},
  "geometry": {"coordinates":[-80.362486,26.104111],"type":"Point"}
}