{
  "type": "Feature",
  "properties": {
    "iso:country":"US",
    "sg:address":"9100 S Dadeland Blvd Ste 502",
    "sg:city":"Miami",
    "sg:classifiers":[
        {
            "category":"Health Services",
            "subcategory":"Doctor",
            "type":"Services"
        }
    ],
    "sg:phone":"+1 305 325 1441",
    "sg:postcode":"33156",
    "sg:province":"FL",
    "wof:name":"Mullin Walter R MD",
    "wof:placetype":"venue"
},
  "geometry": {"coordinates":[-80.3146,25.68545],"type":"Point"}
}