{
  "type": "Feature",
  "properties": {
    "addr:full":"256 Miracle Mile Miami FL 33134",
    "addr:housenumber":"256",
    "addr:postcode":"33134",
    "addr:street":"Miracle Mile",
    "iso:country":"US",
    "sg:address":"256 Miracle Mile",
    "sg:city":"Miami",
    "sg:classifiers":[
        {
            "category":"Personal",
            "subcategory":"Massage",
            "type":"Services"
        }
    ],
    "sg:phone":"+1 305 774 0000",
    "sg:postcode":"33134",
    "sg:province":"FL",
    "sg:website":"www.massageenvy.com",
    "wof:name":"Massage Envy",
    "wof:placetype":"venue"
},
  "geometry": {"coordinates":[-80.25990899999999,25.749188],"type":"Point"}
}