{
  "type": "Feature",
  "properties": {
    "addr:full":"595 Mirror Lake Dr N St Petersburg FL 33701",
    "addr:housenumber":"595",
    "addr:postcode":"33701",
    "addr:street":"Mirror Lake Dr N",
    "iso:country":"US",
    "sg:address":"595 Mirror Lake Dr N",
    "sg:city":"St Petersburg",
    "sg:classifiers":[
        {
            "category":"Professional",
            "type":"Services"
        }
    ],
    "sg:phone":"+1 727 550 2110",
    "sg:postcode":"33701",
    "sg:province":"FL",
    "sg:tags":[
        "establishment"
    ],
    "wof:name":"Judith Lee Johnson Studio",
    "wof:placetype":"venue"
},
  "geometry": {"coordinates":[-82.641734,27.775295],"type":"Point"}
}