{
  "type": "Feature",
  "properties": {
    "iso:country":"US",
    "sg:address":"294 Lake Ave",
    "sg:city":"Frostproof",
    "sg:classifiers":[
        {
            "category":"Wholesale",
            "subcategory":"Fruits & Vegetables",
            "type":"Manufacturing & Wholesale Goods"
        }
    ],
    "sg:phone":"+1 863 635 4966",
    "sg:postcode":"33843",
    "sg:province":"FL",
    "sg:tags":[
        "shipper"
    ],
    "wof:name":"Allen L Sullivan Inc",
    "wof:placetype":"venue"
},
  "geometry": {"coordinates":[-81.527835,27.742515],"type":"Point"}
}