{
  "type": "Feature",
  "properties": {
    "addr:full":"609 N Crystal Park Ter Crystal River FL 34429",
    "addr:housenumber":"609",
    "addr:postcode":"34429",
    "addr:street":"N Crystal Park Ter",
    "iso:country":"US",
    "sg:address":"609 N Crystal Park Ter",
    "sg:city":"Crystal River",
    "sg:classifiers":[
        {
            "category":"Manufacturing",
            "subcategory":"Pottery",
            "type":"Manufacturing & Wholesale Goods"
        }
    ],
    "sg:phone":"+1 352 795 1567",
    "sg:postcode":"34429",
    "sg:province":"FL",
    "sg:tags":[
        "product",
        "mfg"
    ],
    "wof:name":"Thrown Stone Pottery",
    "wof:placetype":"venue"
},
  "geometry": {"coordinates":[-82.580625,28.869049],"type":"Point"}
}