{
  "type": "Feature",
  "properties": {
    "iso:country":"US",
    "sg:address":"2932 US Hwy 27",
    "sg:city":"Sebring",
    "sg:classifiers":[
        {
            "category":"Food & Beverages",
            "subcategory":"Fruits & Vegetables",
            "type":"Retail Goods"
        }
    ],
    "sg:phone":"+1 863 385 0808",
    "sg:postcode":"33870",
    "sg:province":"FL",
    "wof:name":"Garden Delight",
    "wof:placetype":"venue"
},
  "geometry": {"coordinates":[-81.44225900000001,27.471016],"type":"Point"}
}