{
  "type": "Feature",
  "properties": {
    "addr:full":"1765 Tamiami Trl S Venice FL 34293",
    "addr:housenumber":"1765",
    "addr:postcode":"34293",
    "addr:street":"Tamiami Trl S",
    "iso:country":"US",
    "sg:address":"1765 Tamiami Trl S",
    "sg:city":"Venice",
    "sg:phone":"+1 941 408 7888",
    "sg:postcode":"34293",
    "sg:province":"FL",
    "wof:name":"Panda Pavilion Chinese Buffet",
    "wof:placetype":"venue"
},
  "geometry": {"coordinates":[-82.421584,27.069373],"type":"Point"}
}