{
  "type": "Feature",
  "properties": {
    "iso:country":"US",
    "sg:address":"7535 N Kendall Dr",
    "sg:city":"Miami",
    "sg:classifiers":[
        {
            "category":"Shopping",
            "subcategory":"Jewelry",
            "type":"Retail Goods"
        }
    ],
    "sg:phone":"+1 305 668 2977",
    "sg:postcode":"33156",
    "sg:province":"FL",
    "sg:tags":[
        "precious",
        "semi-precious",
        "stone",
        "jeweler"
    ],
    "sg:website":"http://www.baileybanksandbiddle.com/",
    "wof:name":"Bailey Banks & Biddle",
    "wof:placetype":"venue"
},
  "geometry": {"coordinates":[-80.31349899999999,25.688742],"type":"Point"}
}