{
  "type": "Feature",
  "properties": {
    "addr:full":"7201 Sandscove Ct Ste 4 Winter Park FL 32792",
    "addr:housenumber":"7201",
    "addr:postcode":"32792",
    "addr:street":"Sandscove Ct Ste 4",
    "iso:country":"US",
    "sg:address":"7201 Sandscove Ct Ste 4",
    "sg:city":"Winter Park",
    "sg:classifiers":[
        {
            "category":"Wholesale",
            "subcategory":"Computers",
            "type":"Manufacturing & Wholesale Goods"
        },
        {
            "category":"Professional",
            "subcategory":"Computer Services",
            "type":"Services"
        }
    ],
    "sg:phone":"+1 407 678 8300",
    "sg:postcode":"32792",
    "sg:province":"FL",
    "sg:tags":[
        "repair"
    ],
    "sg:website":"www.dytech.com",
    "wof:name":"Dytech Group Inc",
    "wof:placetype":"venue"
},
  "geometry": {"coordinates":[-81.304703,28.605101],"type":"Point"}
}