{
  "type": "Feature",
  "properties": {
    "iso:country":"US",
    "sg:address":"5604 14th St W",
    "sg:city":"Bradenton",
    "sg:classifiers":[
        {
            "category":"Building & Trades",
            "subcategory":"Equipment Rental",
            "type":"Services"
        }
    ],
    "sg:phone":"+1 941 752 4421",
    "sg:postcode":"34207",
    "sg:province":"FL",
    "sg:tags":[
        "party",
        "supply"
    ],
    "wof:name":"Apollo Amusements Inc",
    "wof:placetype":"venue"
},
  "geometry": {"coordinates":[-82.575504,27.440397],"type":"Point"}
}