{
  "type": "Feature",
  "properties": {
    "addr:full":"4110 Enterprise Ave Naples FL 34104",
    "addr:housenumber":"4110",
    "addr:postcode":"34104",
    "addr:street":"Enterprise Ave",
    "iso:country":"US",
    "sg:address":"4110 Enterprise Ave",
    "sg:city":"Naples",
    "sg:classifiers":[
        {
            "category":"Home & Garden",
            "subcategory":"Building Materials",
            "type":"Retail Goods"
        }
    ],
    "sg:phone":"+1 239 649 7579",
    "sg:postcode":"34104",
    "sg:province":"FL",
    "sg:tags":[
        "shutter"
    ],
    "sg:website":"www.coastlineshutters.com",
    "wof:name":"Coastline Shutter Corp",
    "wof:placetype":"venue"
},
  "geometry": {"coordinates":[-81.753632,26.160701],"type":"Point"}
}