{
  "type": "Feature",
  "properties": {
    "addr:full":"5320 Birch Ave Sarasota FL 34233",
    "addr:housenumber":"5320",
    "addr:postcode":"34233",
    "addr:street":"Birch Ave",
    "iso:country":"US",
    "sg:address":"5320 Birch Ave",
    "sg:city":"Sarasota",
    "sg:classifiers":[
        {
            "category":"Building & Trades",
            "subcategory":"Construction",
            "type":"Services"
        }
    ],
    "sg:phone":"+1 941 924 3052",
    "sg:postcode":"34233",
    "sg:province":"FL",
    "sg:tags":[
        "contractor"
    ],
    "wof:name":"Stephen Christopher",
    "wof:placetype":"venue"
},
  "geometry": {"coordinates":[-82.46299999999999,27.275687],"type":"Point"}
}