{
  "type": "Feature",
  "properties": {
    "iso:country":"US",
    "sg:address":"4300 N Meridian Rd",
    "sg:city":"Tallahassee",
    "sg:classifiers":[
        {
            "category":"Recreation",
            "type":"Entertainment"
        }
    ],
    "sg:phone":"+1 850 668 0849",
    "sg:postcode":"32312",
    "sg:province":"FL",
    "sg:tags":[
        "stable"
    ],
    "wof:name":"Farm Equestrian Ctr",
    "wof:placetype":"venue"
},
  "geometry": {"coordinates":[-84.27754,30.527727],"type":"Point"}
}