{
  "type": "Feature",
  "properties": {
    "iso:country":"US",
    "sg:address":"651 Egret Cir",
    "sg:city":"Delray Beach",
    "sg:classifiers":[
        {
            "category":"Recreation",
            "type":"Entertainment"
        }
    ],
    "sg:phone":"+1 561 243 9522",
    "sg:postcode":"33444",
    "sg:province":"FL",
    "sg:tags":[
        "tennis",
        "instruction"
    ],
    "wof:name":"Tennix Inc",
    "wof:placetype":"venue"
},
  "geometry": {"coordinates":[-80.078469,26.435311],"type":"Point"}
}