{
  "type": "Feature",
  "properties": {
    "addr:full":"8650 Baymeadows Rd Jacksonville FL 32256",
    "addr:housenumber":"8650",
    "addr:postcode":"32256",
    "addr:street":"Baymeadows Rd",
    "iso:country":"US",
    "sg:address":"8650 Baymeadows Rd",
    "sg:city":"Jacksonville",
    "sg:classifiers":[
        {
            "category":"Restaurant",
            "type":"Food & Drink"
        }
    ],
    "sg:phone":"+1 904 448 0500",
    "sg:postcode":"32256",
    "sg:province":"FL",
    "sg:tags":[
        "eating"
    ],
    "wof:name":"Gator's Dockside Bay Meadows",
    "wof:placetype":"venue"
},
  "geometry": {"coordinates":[-81.58116699999999,30.220709],"type":"Point"}
}