{
  "type": "Feature",
  "properties": {
    "iso:country":"US",
    "sg:address":"1442 NW 196th St",
    "sg:city":"Miami",
    "sg:classifiers":[
        {
            "category":"Retail",
            "subcategory":"Car Wash",
            "type":"Services"
        }
    ],
    "sg:phone":"+1 305 653 1163",
    "sg:postcode":"33169",
    "sg:province":"FL",
    "sg:tags":[
        "carwash"
    ],
    "wof:name":"Superior Car Care",
    "wof:placetype":"venue"
},
  "geometry": {"coordinates":[-80.227268,25.953158],"type":"Point"}
}