{
  "type": "Feature",
  "properties": {
    "iso:country":"US",
    "sg:address":"4201 NE 36th Ave",
    "sg:city":"Ocala",
    "sg:classifiers":[
        {
            "category":"Organizations",
            "subcategory":"Community Association",
            "type":"Services"
        }
    ],
    "sg:phone":"+1 352 629 8836",
    "sg:postcode":"34479",
    "sg:province":"FL",
    "sg:tags":[
        "fraternal"
    ],
    "wof:name":"Fraternal Order Of Eagles",
    "wof:placetype":"venue"
},
  "geometry": {"coordinates":[-82.086884,29.230752],"type":"Point"}
}