{
  "type": "Feature",
  "properties": {
    "addr:full":"619 Waterside Way Sarasota FL 34242",
    "addr:housenumber":"619",
    "addr:postcode":"34242",
    "addr:street":"Waterside Way",
    "iso:country":"US",
    "sg:address":"619 Waterside Way",
    "sg:city":"Sarasota",
    "sg:classifiers":[
        {
            "category":"Professional",
            "subcategory":"Business Services",
            "type":"Services"
        }
    ],
    "sg:phone":"+1 941 349 4990",
    "sg:postcode":"34242",
    "sg:province":"FL",
    "sg:tags":[
        "interior",
        "consultant",
        "design",
        "decorator"
    ],
    "wof:name":"Jean Babcock Interior Exprssns",
    "wof:placetype":"venue"
},
  "geometry": {"coordinates":[-82.557596,27.281807],"type":"Point"}
}