{
  "type": "Feature",
  "properties": {
    "iso:country":"US",
    "sg:address":"2601 SW 37th Ave Ste 601",
    "sg:city":"Miami",
    "sg:classifiers":[
        {
            "category":"Health Services",
            "subcategory":"Doctor",
            "type":"Services"
        }
    ],
    "sg:phone":"+1 305 446 6414",
    "sg:postcode":"33133",
    "sg:province":"FL",
    "sg:tags":[
        "practice",
        "family"
    ],
    "wof:name":"Bosch Pedro Publio MD",
    "wof:placetype":"venue"
},
  "geometry": {"coordinates":[-80.25430299999999,25.743],"type":"Point"}
}