{
  "type": "Feature",
  "properties": {
    "addr:full":"1709 NE 6th Ter Cape Coral FL 33909",
    "addr:housenumber":"1709",
    "addr:postcode":"33909",
    "addr:street":"Ne 6Th Ter",
    "iso:country":"US",
    "sg:address":"1709 NE 6th Ter",
    "sg:city":"Cape Coral",
    "sg:classifiers":[
        {
            "category":"Building & Trades",
            "subcategory":"Construction",
            "type":"Services"
        }
    ],
    "sg:phone":"+1 239 574 9523",
    "sg:postcode":"33909",
    "sg:province":"FL",
    "sg:tags":[
        "general",
        "contractor"
    ],
    "wof:name":"Tropical Bldrs Hm Inspections",
    "wof:placetype":"venue"
},
  "geometry": {"coordinates":[-81.938497,26.664082],"type":"Point"}
}