{
  "type": "Feature",
  "properties": {
    "iso:country":"US",
    "sg:address":"925 NW 82nd Ave",
    "sg:city":"Miami",
    "sg:classifiers":[
        {
            "category":"Organizations",
            "subcategory":"Professional Association",
            "type":"Services"
        }
    ],
    "sg:phone":"+1 786 388 5336",
    "sg:postcode":"33126",
    "sg:province":"FL",
    "sg:tags":[
        "condominium"
    ],
    "wof:name":"Mystic Place Condo Assoc Inc",
    "wof:placetype":"venue"
},
  "geometry": {"coordinates":[-80.32849400000001,25.780156],"type":"Point"}
}