{
  "type": "Feature",
  "properties": {
    "addr:full":"2940 Oakwood Blvd Hollywood FL 33020",
    "addr:housenumber":"2940",
    "addr:postcode":"33020",
    "addr:street":"Oakwood Blvd",
    "iso:country":"US",
    "sg:address":"2940 Oakwood Blvd",
    "sg:city":"Hollywood",
    "sg:classifiers":[
        {
            "category":"Restaurant",
            "type":"Food & Drink"
        }
    ],
    "sg:menulink":"http://www.allmenus.com/fl/hollywood/47944-tgi-fridays/menu/",
    "sg:phone":"+1 954 922 2771",
    "sg:postcode":"33020",
    "sg:province":"FL",
    "sg:tags":[
        "american"
    ],
    "wof:name":"T.G.I. Friday's",
    "wof:placetype":"venue"
},
  "geometry": {"coordinates":[-80.16125700000001,26.043117],"type":"Point"}
}