{
  "type": "Feature",
  "properties": {
    "iso:country":"US",
    "sg:address":"161 Sunset Ave",
    "sg:city":"Palm Beach",
    "sg:classifiers":[
        {
            "category":"Food & Beverages",
            "subcategory":"Groceries & Convenience Stores",
            "type":"Retail Goods"
        }
    ],
    "sg:phone":"+1 561 655 4120",
    "sg:postcode":"33480",
    "sg:province":"FL",
    "sg:tags":[
        "supermarket"
    ],
    "wof:name":"Publix Super Market 161",
    "wof:placetype":"venue"
},
  "geometry": {"coordinates":[-80.03596,26.719117],"type":"Point"}
}