{
  "type": "Feature",
  "properties": {
    "addr:full":"23 N Fernwood Dr Rockledge FL 32955",
    "addr:housenumber":"23",
    "addr:postcode":"32955",
    "addr:street":"N Fernwood Dr",
    "iso:country":"US",
    "sg:address":"23 N Fernwood Dr",
    "sg:city":"Rockledge",
    "sg:classifiers":[
        {
            "category":"Shopping",
            "type":"Retail Goods"
        }
    ],
    "sg:phone":"+1 321 635 9402",
    "sg:postcode":"32955",
    "sg:province":"FL",
    "sg:tags":[
        "merchandise"
    ],
    "wof:name":"Seahorse Tropical Fish",
    "wof:placetype":"venue"
},
  "geometry": {"coordinates":[-80.718795,28.337976],"type":"Point"}
}