{
  "type": "Feature",
  "properties": {
    "addr:full":"3697 SW 7th St Miami FL 33135",
    "addr:housenumber":"3697",
    "addr:postcode":"33135",
    "addr:street":"Sw 7Th St",
    "iso:country":"US",
    "sg:address":"3697 SW 7th St",
    "sg:city":"Miami",
    "sg:classifiers":[
        {
            "category":"Retail",
            "subcategory":"Auto Repair",
            "type":"Services"
        }
    ],
    "sg:phone":"+1 305 448 5043",
    "sg:postcode":"33135",
    "sg:province":"FL",
    "sg:tags":[
        "general"
    ],
    "wof:name":"Erichs Car Care Inc",
    "wof:placetype":"venue"
},
  "geometry": {"coordinates":[-80.254283,25.765686],"type":"Point"}
}