{
  "type": "Feature",
  "properties": {
    "addr:full":"1444 Orange St Clearwater FL 33756",
    "addr:housenumber":"1444",
    "addr:postcode":"33756",
    "addr:street":"Orange St",
    "iso:country":"US",
    "sg:address":"1444 Orange St",
    "sg:city":"Clearwater",
    "sg:classifiers":[
        {
            "category":"Home & Garden",
            "subcategory":"Carpets & Floor Coverings",
            "type":"Retail Goods"
        }
    ],
    "sg:phone":"+1 727 446 8022",
    "sg:postcode":"33756",
    "sg:province":"FL",
    "wof:name":"Randys Magic Carpets",
    "wof:placetype":"venue"
},
  "geometry": {"coordinates":[-82.776848,27.946589],"type":"Point"}
}