{
  "type": "Feature",
  "properties": {
    "iso:country":"US",
    "sg:address":"836 Lincoln Rd",
    "sg:city":"Miami Beach",
    "sg:classifiers":[
        {
            "category":"Shopping",
            "subcategory":"Clothing, Apparel, & Fashions",
            "type":"Retail Goods"
        }
    ],
    "sg:phone":"+1 305 673 2124",
    "sg:postcode":"33139",
    "sg:province":"FL",
    "sg:tags":[
        "sport",
        "wear",
        "sportswear"
    ],
    "wof:name":"Post Blue Jean",
    "wof:placetype":"venue"
},
  "geometry": {"coordinates":[-80.13690200000001,25.790701],"type":"Point"}
}