{
  "type": "Feature",
  "properties": {
    "iso:country":"US",
    "sg:address":"11120 NW 27th St",
    "sg:city":"Fort Lauderdale",
    "sg:classifiers":[
        {
            "category":"Professional",
            "subcategory":"Business Services",
            "type":"Services"
        }
    ],
    "sg:phone":"+1 954 748 4734",
    "sg:postcode":"33322",
    "sg:province":"FL",
    "wof:name":"Mister Goodmath & Associates",
    "wof:placetype":"venue"
},
  "geometry": {"coordinates":[-80.295249,26.158347],"type":"Point"}
}