{
  "type": "Feature",
  "properties": {
    "addr:full":"8833 Perimeter Park Blvd Suite 1004 Jacksonville FL 32216",
    "addr:housenumber":"8833",
    "addr:postcode":"32216",
    "addr:street":"Perimeter Park Blvd Suite 1004",
    "iso:country":"US",
    "sg:address":"8833 Perimeter Park Blvd Suite 1004",
    "sg:city":"Jacksonville",
    "sg:classifiers":[
        {
            "category":"Professional",
            "subcategory":"Detective & Security Services",
            "type":"Services"
        },
        {
            "category":"Manufacturing",
            "subcategory":"Electronics",
            "type":"Manufacturing & Wholesale Goods"
        }
    ],
    "sg:phone":"+1 866 582 9609",
    "sg:postcode":"32216",
    "sg:province":"FL",
    "sg:tags":[
        "control",
        "patrol",
        "fire",
        "equipment-wholesale",
        "consultant",
        "alarm",
        "system",
        "equipment",
        "guard",
        "monitoring",
        "manufacturer"
    ],
    "wof:name":"Defender Securities",
    "wof:placetype":"venue"
},
  "geometry": {"coordinates":[-81.55532700000001,30.253113],"type":"Point"}
}