{
  "type": "Feature",
  "properties": {
    "addr:full":"4860 Sand Stone Ln West Palm Beach FL 33417",
    "addr:housenumber":"4860",
    "addr:postcode":"33417",
    "addr:street":"Sand Stone Ln",
    "iso:country":"US",
    "sg:address":"4860 Sand Stone Ln",
    "sg:city":"West Palm Beach",
    "sg:classifiers":[
        {
            "category":"Real Estate",
            "subcategory":"Real Estate Operator",
            "type":"Services"
        }
    ],
    "sg:phone":"+1 561 478 0138",
    "sg:postcode":"33417",
    "sg:province":"FL",
    "sg:tags":[
        "apartment"
    ],
    "wof:name":"Reflections Apartments",
    "wof:placetype":"venue"
},
  "geometry": {"coordinates":[-80.115219,26.743494],"type":"Point"}
}