{
  "type": "Feature",
  "properties": {
    "iso:country":"US",
    "sg:address":"172 S Belcher Rd",
    "sg:city":"Clearwater",
    "sg:classifiers":[
        {
            "category":"Personal",
            "subcategory":"Beauty Salon",
            "type":"Services"
        }
    ],
    "sg:phone":"+1 727 298 0808",
    "sg:postcode":"33765",
    "sg:province":"FL",
    "sg:tags":[
        "shop"
    ],
    "wof:name":"Body Wrap",
    "wof:placetype":"venue"
},
  "geometry": {"coordinates":[-82.74624,27.964462],"type":"Point"}
}