{
  "type": "Feature",
  "properties": {
    "iso:country":"US",
    "sg:address":"7821 Center Bay Dr",
    "sg:city":"Miami Beach",
    "sg:classifiers":[
        {
            "category":"Building & Trades",
            "subcategory":"Construction",
            "type":"Services"
        }
    ],
    "sg:phone":"+1 305 759 1700",
    "sg:postcode":"33141",
    "sg:province":"FL",
    "sg:tags":[
        "residential"
    ],
    "wof:name":"Clinton Brothers Enterpri",
    "wof:placetype":"venue"
},
  "geometry": {"coordinates":[-80.15879,25.844857],"type":"Point"}
}