{
  "type": "Feature",
  "properties": {
    "iso:country":"US",
    "sg:address":"604 19th Ave NW",
    "sg:city":"Ruskin",
    "sg:classifiers":[
        {
            "category":"Freight",
            "type":"Transportation"
        }
    ],
    "sg:phone":"+1 813 645 5175",
    "sg:postcode":"33570",
    "sg:province":"FL",
    "sg:tags":[
        "shop",
        "operator",
        "beauty",
        "trucking"
    ],
    "wof:name":"Southern Style Transport Inc",
    "wof:placetype":"venue"
},
  "geometry": {"coordinates":[-82.43813400000001,27.735166],"type":"Point"}
}