{
  "type": "Feature",
  "properties": {
    "iso:country":"US",
    "sg:address":"3447 Rocky Gap Pl",
    "sg:city":"Cocoa",
    "sg:classifiers":[
        {
            "category":"Personal",
            "subcategory":"Beauty Salon",
            "type":"Services"
        }
    ],
    "sg:phone":"+1 321 632 2714",
    "sg:postcode":"32926",
    "sg:province":"FL",
    "wof:name":"Pamar Skin",
    "wof:placetype":"venue"
},
  "geometry": {"coordinates":[-80.778789,28.400577],"type":"Point"}
}