{
  "type": "Feature",
  "properties": {
    "iso:country":"US",
    "sg:address":"3177 138th Pl N",
    "sg:city":"Largo",
    "sg:classifiers":[
        {
            "category":"Manufacturing",
            "subcategory":"Printing",
            "type":"Manufacturing & Wholesale Goods"
        }
    ],
    "sg:phone":"+1 727 452 9218",
    "sg:postcode":"33771",
    "sg:province":"FL",
    "sg:tags":[
        "publishing"
    ],
    "wof:name":"Atvina Corp",
    "wof:placetype":"venue"
},
  "geometry": {"coordinates":[-82.75486100000001,27.89842],"type":"Point"}
}