{
  "type": "Feature",
  "properties": {
    "iso:country":"US",
    "sg:address":"4394 S William Ave",
    "sg:city":"Inverness",
    "sg:classifiers":[
        {
            "category":"Social Services",
            "type":"Services"
        }
    ],
    "sg:phone":"+1 352 596 6871",
    "sg:postcode":"34452",
    "sg:province":"FL",
    "wof:name":"Steppin Out",
    "wof:placetype":"venue"
},
  "geometry": {"coordinates":[-82.343411,28.79665],"type":"Point"}
}