{
  "type": "Feature",
  "properties": {
    "iso:country":"US",
    "sg:address":"545 Cass St",
    "sg:city":"Deland",
    "sg:classifiers":[
        {
            "category":"Building & Trades",
            "subcategory":"Construction",
            "type":"Services"
        }
    ],
    "sg:phone":"+1 386 804 4678",
    "sg:postcode":"32720",
    "sg:province":"FL",
    "sg:tags":[
        "contractor",
        "grading"
    ],
    "wof:name":"East Coast Site Control Inc",
    "wof:placetype":"venue"
},
  "geometry": {"coordinates":[-81.330122,29.019724],"type":"Point"}
}