{
  "type": "Feature",
  "properties": {
    "iso:country":"US",
    "sg:address":"1400 S Ocean Dr",
    "sg:city":"Fort Lauderdale",
    "sg:classifiers":[
        {
            "category":"Professional",
            "type":"Services"
        }
    ],
    "sg:phone":"+1 954 922 9704",
    "sg:postcode":"33316",
    "sg:province":"FL",
    "sg:tags":[
        "establishment"
    ],
    "wof:name":"Trafalgar Towers",
    "wof:placetype":"venue"
},
  "geometry": {"coordinates":[-80.10776,26.106012],"type":"Point"}
}