{
  "type": "Feature",
  "properties": {
    "iso:country":"US",
    "sg:address":"1304 W Fairbanks Ave",
    "sg:city":"Winter Park",
    "sg:classifiers":[
        {
            "category":"Banks & Credit Unions",
            "subcategory":"Investment Brokerage",
            "type":"Services"
        }
    ],
    "sg:phone":"+1 407 644 9793",
    "sg:postcode":"32789",
    "sg:province":"FL",
    "sg:tags":[
        "funds",
        "mutual"
    ],
    "wof:name":"National Association NACFC",
    "wof:placetype":"venue"
},
  "geometry": {"coordinates":[-81.366711,28.593028],"type":"Point"}
}