{
  "type": "Feature",
  "properties": {
    "iso:country":"US",
    "sg:address":"905 9th Ave E",
    "sg:city":"Palmetto",
    "sg:classifiers":[
        {
            "category":"Social Services",
            "subcategory":"Child Care",
            "type":"Services"
        }
    ],
    "sg:phone":"+1 941 721 8881",
    "sg:postcode":"34221",
    "sg:province":"FL",
    "sg:tags":[
        "day"
    ],
    "wof:name":"Loving Smiles For Kids Inc",
    "wof:placetype":"venue"
},
  "geometry": {"coordinates":[-82.555289,27.52124],"type":"Point"}
}