{
  "type": "Feature",
  "properties": {
    "iso:country":"US",
    "sg:address":"6537 Central Ave",
    "sg:city":"St Petersburg",
    "sg:classifiers":[
        {
            "category":"Professional",
            "subcategory":"Business Services",
            "type":"Services"
        }
    ],
    "sg:phone":"+1 727 343 3395",
    "sg:postcode":"33710",
    "sg:province":"FL",
    "wof:name":"Magnifying Solutions Inc",
    "wof:placetype":"venue"
},
  "geometry": {"coordinates":[-82.72775300000001,27.7709],"type":"Point"}
}