{
  "type": "Feature",
  "properties": {
    "addr:full":"4200 Cemetery Rd Sebring FL 33870",
    "addr:housenumber":"4200",
    "addr:postcode":"33870",
    "addr:street":"Cemetery Rd",
    "iso:country":"US",
    "sg:address":"4200 Cemetery Rd",
    "sg:city":"Sebring",
    "sg:classifiers":[
        {
            "category":"Government",
            "subcategory":"Office",
            "type":"Public Place"
        },
        {
            "category":"Building & Trades",
            "subcategory":"Construction",
            "type":"Services"
        }
    ],
    "sg:phone":"+1 863 471 5114",
    "sg:postcode":"33870",
    "sg:province":"FL",
    "sg:tags":[
        "village"
    ],
    "wof:name":"Sebring Sewer Plant",
    "wof:placetype":"venue"
},
  "geometry": {"coordinates":[-81.424328,27.507702],"type":"Point"}
}