{
  "type": "Feature",
  "properties": {
    "iso:country":"US",
    "sg:address":"10930 SW 129th St",
    "sg:city":"Miami",
    "sg:classifiers":[
        {
            "category":"Banks & Credit Unions",
            "subcategory":"Bureau De Change",
            "type":"Services"
        },
        {
            "category":"Wholesale",
            "subcategory":"Machinery & Supplies",
            "type":"Manufacturing & Wholesale Goods"
        },
        {
            "category":"Home & Garden",
            "subcategory":"Home Furnishings",
            "type":"Retail Goods"
        },
        {
            "category":"Wholesale",
            "subcategory":"Construction Materials",
            "type":"Manufacturing & Wholesale Goods"
        },
        {
            "category":"Building & Trades",
            "subcategory":"Construction",
            "type":"Services"
        }
    ],
    "sg:phone":"+1 305 793 0358",
    "sg:postcode":"33176",
    "sg:province":"FL",
    "sg:tags":[
        "handling",
        "shelving",
        "platform",
        "mezzanine",
        "rack",
        "pallet",
        "equipment",
        "locker",
        "skid"
    ],
    "sg:website":"http://www.allrackandshelving.com",
    "wof:name":"All Rack & Shelving Inc",
    "wof:placetype":"venue"
},
  "geometry": {"coordinates":[-80.369986,25.649151],"type":"Point"}
}