{
  "type": "Feature",
  "properties": {
    "addr:full":"4411 Bee Ridge Rd Sarasota FL 34233",
    "addr:housenumber":"4411",
    "addr:postcode":"34233",
    "addr:street":"Bee Ridge Rd",
    "iso:country":"US",
    "sg:address":"4411 Bee Ridge Rd",
    "sg:city":"Sarasota",
    "sg:classifiers":[
        {
            "category":"Freight",
            "type":"Transportation"
        }
    ],
    "sg:phone":"+1 941 371 6540",
    "sg:postcode":"34233",
    "sg:province":"FL",
    "sg:tags":[
        "mailing"
    ],
    "wof:name":"UPS Stores 59 The",
    "wof:placetype":"venue"
},
  "geometry": {"coordinates":[-82.476795,27.298823],"type":"Point"}
}