{
  "type": "Feature",
  "properties": {
    "iso:country":"US",
    "sg:address":"10110 Boca Entrada Blvd",
    "sg:city":"Boca Raton",
    "sg:classifiers":[
        {
            "category":"Retail",
            "subcategory":"Laundry & Dry Cleaning",
            "type":"Services"
        }
    ],
    "sg:phone":"+1 561 883 6289",
    "sg:postcode":"33428",
    "sg:province":"FL",
    "wof:name":"Amaral General Cleaning Svc",
    "wof:placetype":"venue"
},
  "geometry": {"coordinates":[-80.20470400000001,26.333259],"type":"Point"}
}