{
  "type": "Feature",
  "properties": {
    "addr:full":"755 Arthur Godfrey Rd Miami Beach FL 33140",
    "addr:housenumber":"755",
    "addr:postcode":"33140",
    "addr:street":"Arthur Godfrey Rd",
    "iso:country":"US",
    "sg:address":"755 Arthur Godfrey Rd",
    "sg:city":"Miami Beach",
    "sg:classifiers":[
        {
            "category":"Professional",
            "subcategory":"Lawyer & Legal Services",
            "type":"Services"
        }
    ],
    "sg:phone":"+1 305 672 3770",
    "sg:postcode":"33140",
    "sg:province":"FL",
    "wof:name":"Rosenbaum International Law Firm",
    "wof:placetype":"venue"
},
  "geometry": {"coordinates":[-80.13216799999999,25.813993],"type":"Point"}
}