{
  "type": "Feature",
  "properties": {
    "addr:full":"274 E Eau Gallie Blvd Indian Hrbr Bch FL 32937",
    "addr:housenumber":"274",
    "addr:postcode":"32937",
    "addr:street":"E Eau Gallie Blvd",
    "iso:country":"US",
    "sg:address":"274 E Eau Gallie Blvd",
    "sg:city":"Indian Hrbr Bch",
    "sg:classifiers":[
        {
            "category":"Autos & Motor Vehicles",
            "subcategory":"Boat Sales",
            "type":"Retail Goods"
        }
    ],
    "sg:phone":"+1 321 777 7622",
    "sg:postcode":"32937",
    "sg:province":"FL",
    "sg:tags":[
        "equipment",
        "marine",
        "supply"
    ],
    "wof:name":"West Marine",
    "wof:placetype":"venue"
},
  "geometry": {"coordinates":[-80.59809,28.138584],"type":"Point"}
}