{
  "type": "Feature",
  "properties": {
    "iso:country":"US",
    "sg:address":"5940 Arthur St",
    "sg:city":"Hollywood",
    "sg:classifiers":[
        {
            "category":"Home & Garden",
            "subcategory":"Carpets & Floor Coverings",
            "type":"Retail Goods"
        }
    ],
    "sg:phone":"+1 954 989 6943",
    "sg:postcode":"33021",
    "sg:province":"FL",
    "wof:name":"Jose Hassan Abdul Latis",
    "wof:placetype":"venue"
},
  "geometry": {"coordinates":[-80.207246,26.02124],"type":"Point"}
}