{
  "type": "Feature",
  "properties": {
    "addr:full":"13615 4th Ave NE Bradenton FL 34212",
    "addr:housenumber":"13615",
    "addr:postcode":"34212",
    "addr:street":"4Th Ave Ne",
    "iso:country":"US",
    "sg:address":"13615 4th Ave NE",
    "sg:city":"Bradenton",
    "sg:classifiers":[
        {
            "category":"Professional",
            "subcategory":"Business Services",
            "type":"Services"
        }
    ],
    "sg:phone":"+1 941 750 0297",
    "sg:postcode":"34212",
    "sg:province":"FL",
    "wof:name":"Suncoast Herpetological",
    "wof:placetype":"venue"
},
  "geometry": {"coordinates":[-82.403633,27.502867],"type":"Point"}
}