{
  "type": "Feature",
  "properties": {
    "addr:full":"1680 SW Coxswain Pl Palm City FL 34990",
    "addr:housenumber":"1680",
    "addr:postcode":"34990",
    "addr:street":"Sw Coxswain Pl",
    "iso:country":"US",
    "sg:address":"1680 SW Coxswain Pl",
    "sg:city":"Palm City",
    "sg:classifiers":[
        {
            "category":"Building & Trades",
            "subcategory":"Construction",
            "type":"Services"
        }
    ],
    "sg:phone":"+1 772 221 0992",
    "sg:postcode":"34990",
    "sg:province":"FL",
    "sg:tags":[
        "house"
    ],
    "wof:name":"Mike Tracy Construction",
    "wof:placetype":"venue"
},
  "geometry": {"coordinates":[-80.276383,27.201076],"type":"Point"}
}