{
  "type": "Feature",
  "properties": {
    "addr:full":"1100 NE 2nd Ter Boca Raton FL 33432",
    "addr:housenumber":"1100",
    "addr:postcode":"33432",
    "addr:street":"Ne 2Nd Ter",
    "iso:country":"US",
    "sg:address":"1100 NE 2nd Ter",
    "sg:city":"Boca Raton",
    "sg:classifiers":[
        {
            "category":"Real Estate",
            "subcategory":"Architect",
            "type":"Services"
        }
    ],
    "sg:phone":"+1 561 392 5653",
    "sg:postcode":"33432",
    "sg:province":"FL",
    "sg:tags":[
        "architectural"
    ],
    "wof:name":"Huddleston Art Studio",
    "wof:placetype":"venue"
},
  "geometry": {"coordinates":[-80.08150500000001,26.361514],"type":"Point"}
}