{
  "type": "Feature",
  "properties": {
    "addr:full":"5389 S Memorial Dr Homosassa FL 34446",
    "addr:housenumber":"5389",
    "addr:postcode":"34446",
    "addr:street":"S Memorial Dr",
    "iso:country":"US",
    "sg:address":"5389 S Memorial Dr",
    "sg:city":"Homosassa",
    "sg:classifiers":[
        {
            "category":"Farming",
            "subcategory":"Fish & Marine Products",
            "type":"Manufacturing & Wholesale Goods"
        }
    ],
    "sg:phone":"+1 352 697 1767",
    "sg:postcode":"34446",
    "sg:province":"FL",
    "sg:tags":[
        "shrimp"
    ],
    "wof:name":"Scott Shrimp",
    "wof:placetype":"venue"
},
  "geometry": {"coordinates":[-82.553189,28.782944],"type":"Point"}
}