{
  "type": "Feature",
  "properties": {
    "addr:full":"4152 W Blue Heron Blvd Riviera Beach FL 33404",
    "addr:housenumber":"4152",
    "addr:postcode":"33404",
    "addr:street":"W Blue Heron Blvd",
    "iso:country":"US",
    "sg:address":"4152 W Blue Heron Blvd",
    "sg:city":"Riviera Beach",
    "sg:classifiers":[
        {
            "category":"Home & Garden",
            "subcategory":"Furniture",
            "type":"Retail Goods"
        }
    ],
    "sg:phone":"+1 561 881 5352",
    "sg:postcode":"33404",
    "sg:province":"FL",
    "wof:name":"Whittington Home Furnishings",
    "wof:placetype":"venue"
},
  "geometry": {"coordinates":[-80.102295,26.78343],"type":"Point"}
}