{
  "type": "Feature",
  "properties": {
    "addr:full":"7895 NW 56th St Doral FL 33166",
    "addr:housenumber":"7895",
    "addr:postcode":"33166",
    "addr:street":"Nw 56Th St",
    "iso:country":"US",
    "sg:address":"7895 NW 56th St",
    "sg:city":"Doral",
    "sg:classifiers":[
        {
            "category":"Wholesale",
            "subcategory":"Durable Goods & Equipment",
            "type":"Manufacturing & Wholesale Goods"
        },
        {
            "category":"Wholesale",
            "subcategory":"Auto Parts",
            "type":"Manufacturing & Wholesale Goods"
        }
    ],
    "sg:phone":"+1 305 593 7074",
    "sg:postcode":"33166",
    "sg:province":"FL",
    "sg:tags":[
        "exporter",
        "truck"
    ],
    "wof:name":"Atlantic Truck Parts & Equip",
    "wof:placetype":"venue"
},
  "geometry": {"coordinates":[-80.32398499999999,25.824447],"type":"Point"}
}