{
  "type": "Feature",
  "properties": {
    "addr:full":"201 NE 152nd St Miami FL 33162",
    "addr:housenumber":"201",
    "addr:postcode":"33162",
    "addr:street":"Ne 152Nd St",
    "iso:country":"US",
    "sg:address":"201 NE 152nd St",
    "sg:city":"Miami",
    "sg:classifiers":[
        {
            "category":"Shopping",
            "type":"Retail Goods"
        }
    ],
    "sg:phone":"+1 786 274 1200",
    "sg:postcode":"33162",
    "sg:province":"FL",
    "sg:tags":[
        "gallery",
        "merchandise"
    ],
    "wof:name":"Art Base",
    "wof:placetype":"venue"
},
  "geometry": {"coordinates":[-80.189651,25.914765],"type":"Point"}
}