{
  "type": "Feature",
  "properties": {
    "addr:full":"110 Shore Ln Sugarloaf Shores FL 33042",
    "addr:housenumber":"110",
    "addr:postcode":"33042",
    "addr:street":"Shore Ln",
    "iso:country":"US",
    "sg:address":"110 Shore Ln",
    "sg:city":"Sugarloaf Shores",
    "sg:classifiers":[
        {
            "category":"Shopping",
            "type":"Retail Goods"
        }
    ],
    "sg:phone":"+1 305 745 2629",
    "sg:postcode":"33042",
    "sg:province":"FL",
    "sg:tags":[
        "aquarium"
    ],
    "wof:name":"Seaquatics",
    "wof:placetype":"venue"
},
  "geometry": {"coordinates":[-81.56428099999999,24.643148],"type":"Point"}
}