{
  "type": "Feature",
  "properties": {
    "addr:full":"3973 Sawyer Rd Sarasota FL 34233",
    "addr:housenumber":"3973",
    "addr:postcode":"34233",
    "addr:street":"Sawyer Rd",
    "iso:country":"US",
    "sg:address":"3973 Sawyer Rd",
    "sg:city":"Sarasota",
    "sg:classifiers":[
        {
            "category":"Manufacturing",
            "subcategory":"Printing",
            "type":"Manufacturing & Wholesale Goods"
        }
    ],
    "sg:phone":"+1 941 922 5954",
    "sg:postcode":"34233",
    "sg:province":"FL",
    "sg:tags":[
        "printer"
    ],
    "sg:website":"www.modernprinting.biz",
    "wof:name":"Modern Printing & Graphics",
    "wof:placetype":"venue"
},
  "geometry": {"coordinates":[-82.489208,27.297405],"type":"Point"}
}