{
  "type": "Feature",
  "properties": {
    "addr:full":"10400 SE 36th Ave Belleview FL 34420",
    "addr:postcode":"10400;34420",
    "addr:street":"Se 36Th Ave",
    "iso:country":"US",
    "sg:address":"10400 SE 36th Ave",
    "sg:city":"Belleview",
    "sg:classifiers":[
        {
            "category":"Education",
            "subcategory":"School",
            "type":"Public Place"
        }
    ],
    "sg:phone":"+1 352 671 6210",
    "sg:postcode":"34420",
    "sg:province":"FL",
    "wof:name":"Belleview High School",
    "wof:placetype":"venue"
},
  "geometry": {"coordinates":[-82.086743,29.070533],"type":"Point"}
}