{
  "type": "Feature",
  "properties": {
    "iso:country":"US",
    "sg:address":"3637 Mobile Hwy",
    "sg:city":"Pensacola",
    "sg:classifiers":[
        {
            "category":"Food & Beverages",
            "subcategory":"Groceries & Convenience Stores",
            "type":"Retail Goods"
        }
    ],
    "sg:phone":"+1 850 434 9313",
    "sg:postcode":"32505",
    "sg:province":"FL",
    "wof:name":"Trisha's One Stop",
    "wof:placetype":"venue"
},
  "geometry": {"coordinates":[-87.25991999999999,30.423322],"type":"Point"}
}