{
  "type": "Feature",
  "properties": {
    "iso:country":"US",
    "sg:address":"2087 Shadow Dr",
    "sg:city":"Geneva",
    "sg:classifiers":[
        {
            "category":"Personal",
            "subcategory":"Beauty Salon",
            "type":"Services"
        },
        {
            "category":"Personal",
            "subcategory":"Skin Care",
            "type":"Services"
        }
    ],
    "sg:phone":"+1 407 786 5262",
    "sg:postcode":"32732",
    "sg:province":"FL",
    "wof:name":"Holistic Skin Care",
    "wof:placetype":"venue"
},
  "geometry": {"coordinates":[-81.14361,28.788992],"type":"Point"}
}