{
  "type": "Feature",
  "properties": {
    "iso:country":"US",
    "sg:address":"2730 Park St",
    "sg:city":"Jacksonville",
    "sg:classifiers":[
        {
            "category":"Shopping",
            "subcategory":"Used Merchandise",
            "type":"Retail Goods"
        }
    ],
    "sg:phone":"+1 904 388 7673",
    "sg:postcode":"32205",
    "sg:province":"FL",
    "sg:tags":[
        "antique"
    ],
    "wof:name":"Prim Rose Antiques",
    "wof:placetype":"venue"
},
  "geometry": {"coordinates":[-81.69538300000001,30.309486],"type":"Point"}
}