{
  "type": "Feature",
  "properties": {
    "iso:country":"US",
    "sg:address":"13833 Bellamy Brothers Blvd",
    "sg:city":"Dade City",
    "sg:classifiers":[
        {
            "category":"Building & Trades",
            "subcategory":"Construction",
            "type":"Services"
        }
    ],
    "sg:phone":"+1 352 588 5080",
    "sg:postcode":"33525",
    "sg:province":"FL",
    "sg:tags":[
        "excavation",
        "contractor"
    ],
    "wof:name":"Yodice Excavating Inc",
    "wof:placetype":"venue"
},
  "geometry": {"coordinates":[-82.35813899999999,28.358865],"type":"Point"}
}