{
  "type": "Feature",
  "properties": {
    "iso:country":"US",
    "sg:address":"5051 Castello Dr",
    "sg:city":"Naples",
    "sg:classifiers":[
        {
            "category":"Recreation",
            "type":"Entertainment"
        }
    ],
    "sg:phone":"+1 239 530 0800",
    "sg:postcode":"34103",
    "sg:province":"FL",
    "sg:tags":[
        "psychic",
        "medium"
    ],
    "wof:name":"Angel Lady Tarot Channeling",
    "wof:placetype":"venue"
},
  "geometry": {"coordinates":[-81.7978,26.209137],"type":"Point"}
}