{
  "type": "Feature",
  "properties": {
    "addr:full":"1729 Mahan Dr Tallahassee FL 32308",
    "addr:housenumber":"1729",
    "addr:postcode":"32308",
    "addr:street":"Mahan Dr",
    "iso:country":"US",
    "sg:address":"1729 Mahan Dr",
    "sg:city":"Tallahassee",
    "sg:classifiers":[
        {
            "category":"Organizations",
            "subcategory":"Religious Organization",
            "type":"Services"
        }
    ],
    "sg:phone":"+1 850 878 9327",
    "sg:postcode":"32308",
    "sg:province":"FL",
    "sg:tags":[
        "spiritualist"
    ],
    "wof:name":"Sister Fay",
    "wof:placetype":"venue"
},
  "geometry": {"coordinates":[-84.253856,30.450643],"type":"Point"}
}