{
  "type": "Feature",
  "properties": {
    "iso:country":"US",
    "sg:address":"4300 Duhme Rd",
    "sg:city":"Saint Petersburg",
    "sg:classifiers":[
        {
            "category":"Professional",
            "subcategory":"Employment Agencies",
            "type":"Services"
        }
    ],
    "sg:phone":"+1 727 391 2000",
    "sg:postcode":"33708",
    "sg:province":"FL",
    "sg:tags":[
        "help",
        "supply"
    ],
    "wof:name":"Interim Services",
    "wof:placetype":"venue"
},
  "geometry": {"coordinates":[-82.792727,27.812008],"type":"Point"}
}