{
  "type": "Feature",
  "properties": {
    "addr:full":"220 S Dixie Hwy Lake Worth FL 33460",
    "addr:housenumber":"220",
    "addr:postcode":"33460",
    "addr:street":"S Dixie Hwy",
    "iso:country":"US",
    "sg:address":"220 S Dixie Hwy",
    "sg:city":"Lake Worth",
    "sg:classifiers":[
        {
            "category":"Health Services",
            "subcategory":"Clinic",
            "type":"Services"
        }
    ],
    "sg:phone":"+1 561 533 0053",
    "sg:postcode":"33460",
    "sg:province":"FL",
    "sg:tags":[
        "specialty",
        "outpatient"
    ],
    "wof:name":"Healthy Mthrs/Hlthy Babies",
    "wof:placetype":"venue"
},
  "geometry": {"coordinates":[-80.057394,26.612496],"type":"Point"}
}