{
  "type": "Feature",
  "properties": {
    "iso:country":"US",
    "sg:address":"3312 NW 38th St",
    "sg:city":"Miami",
    "sg:classifiers":[
        {
            "category":"Autos & Motor Vehicles",
            "subcategory":"Boat Sales",
            "type":"Retail Goods"
        },
        {
            "category":"Retail",
            "subcategory":"Repair Shop",
            "type":"Services"
        }
    ],
    "sg:phone":"+1 305 635 2186",
    "sg:postcode":"33142",
    "sg:province":"FL",
    "sg:tags":[
        "top",
        "upholstery",
        "cover"
    ],
    "wof:name":"Barroso Boat Upholstery",
    "wof:placetype":"venue"
},
  "geometry": {"coordinates":[-80.252359,25.810128],"type":"Point"}
}