{
  "type": "Feature",
  "properties": {
    "addr:full":"204 NE 9th St Pompano Beach FL 33060",
    "addr:housenumber":"204",
    "addr:postcode":"33060",
    "addr:street":"Ne 9Th St",
    "iso:country":"US",
    "sg:address":"204 NE 9th St",
    "sg:city":"Pompano Beach",
    "sg:classifiers":[
        {
            "category":"Building & Trades",
            "subcategory":"Construction",
            "type":"Services"
        }
    ],
    "sg:phone":"+1 954 786 1658",
    "sg:postcode":"33060",
    "sg:province":"FL",
    "sg:tags":[
        "contractor"
    ],
    "wof:name":"Tim Gregory Roofing",
    "wof:placetype":"venue"
},
  "geometry": {"coordinates":[-80.122435,26.239598],"type":"Point"}
}