{
  "type": "Feature",
  "properties": {
    "addr:full":"4600 NW 114th Ave Doral FL 33178",
    "addr:housenumber":"4600",
    "addr:postcode":"33178",
    "addr:street":"Nw 114Th Ave",
    "iso:country":"US",
    "sg:address":"4600 NW 114th Ave",
    "sg:city":"Doral",
    "sg:classifiers":[
        {
            "category":"Real Estate",
            "subcategory":"Real Estate Operator",
            "type":"Services"
        }
    ],
    "sg:phone":"+1 305 718 8330",
    "sg:postcode":"33178",
    "sg:province":"FL",
    "sg:tags":[
        "apartment"
    ],
    "wof:name":"Centergate Doral Apartments",
    "wof:placetype":"venue"
},
  "geometry": {"coordinates":[-80.38159899999999,25.815701],"type":"Point"}
}