{
  "type": "Feature",
  "properties": {
    "addr:full":"20201 Calice Ct Estero FL 33928",
    "addr:postcode":"20201;33928",
    "addr:street":"Calice Ct",
    "iso:country":"US",
    "sg:address":"20201 Calice Ct",
    "sg:city":"Estero",
    "sg:classifiers":[
        {
            "category":"Real Estate",
            "subcategory":"Real Estate Agent",
            "type":"Services"
        }
    ],
    "sg:phone":"+1 239 949 2731",
    "sg:postcode":"33928",
    "sg:province":"FL",
    "sg:tags":[
        "management"
    ],
    "wof:name":"David Gilchrist Properties",
    "wof:placetype":"venue"
},
  "geometry": {"coordinates":[-81.767527,26.442477],"type":"Point"}
}