{
  "type": "Feature",
  "properties": {
    "iso:country":"US",
    "sg:address":"6372 Minton Rd NW",
    "sg:city":"Palm Bay",
    "sg:classifiers":[
        {
            "category":"Home & Garden",
            "subcategory":"Garden Supply",
            "type":"Retail Goods"
        }
    ],
    "sg:phone":"+1 321 725 4355",
    "sg:postcode":"32907",
    "sg:province":"FL",
    "wof:name":"Rodney L Stalvey Sod Service",
    "wof:placetype":"venue"
},
  "geometry": {"coordinates":[-80.672207,28.006342],"type":"Point"}
}