{
  "type": "Feature",
  "properties": {
    "iso:country":"US",
    "sg:address":"1855 NW 70th Ave",
    "sg:city":"Miami",
    "sg:classifiers":[
        {
            "category":"Airline",
            "type":"Transportation"
        }
    ],
    "sg:phone":"+1 305 716 8831",
    "sg:postcode":"33126",
    "sg:province":"FL",
    "wof:name":"Iberia Airlines",
    "wof:placetype":"venue"
},
  "geometry": {"coordinates":[-80.310626,25.79104],"type":"Point"}
}