{
  "type": "Feature",
  "properties": {
    "addr:full":"210 Monument Ave Port St Joe FL 32456",
    "addr:housenumber":"210",
    "addr:postcode":"32456",
    "addr:street":"Monument Ave",
    "iso:country":"US",
    "sg:address":"210 Monument Ave",
    "sg:city":"Port St Joe",
    "sg:classifiers":[
        {
            "category":"Shopping",
            "subcategory":"Department Store",
            "type":"Retail Goods"
        }
    ],
    "sg:phone":"+1 850 227 2099",
    "sg:postcode":"32456",
    "sg:province":"FL",
    "sg:tags":[
        "shop"
    ],
    "wof:name":"Dollar General",
    "wof:placetype":"venue"
},
  "geometry": {"coordinates":[-85.304478,29.814352],"type":"Point"}
}