{
  "type": "Feature",
  "properties": {
    "iso:country":"US",
    "sg:address":"15014 SW 110th Ter",
    "sg:city":"Miami",
    "sg:classifiers":[
        {
            "category":"Professional",
            "type":"Services"
        }
    ],
    "sg:phone":"+1 305 387 8200",
    "sg:postcode":"33196",
    "sg:province":"FL",
    "wof:name":"Jose Correa Lima PA",
    "wof:placetype":"venue"
},
  "geometry": {"coordinates":[-80.43960800000001,25.663928],"type":"Point"}
}