{
  "type": "Feature",
  "properties": {
    "iso:country":"US",
    "sg:address":"2886 Elkcam Blvd",
    "sg:city":"Deltona",
    "sg:classifiers":[
        {
            "category":"Organizations",
            "subcategory":"Religious Organization",
            "type":"Services"
        }
    ],
    "sg:phone":"+1 386 789 2400",
    "sg:postcode":"32738",
    "sg:province":"FL",
    "wof:name":"Deltona Lakes Baptist Church",
    "wof:placetype":"venue"
},
  "geometry": {"coordinates":[-81.184799,28.9303],"type":"Point"}
}