{
  "type": "Feature",
  "properties": {
    "iso:country":"US",
    "sg:address":"8315 SW 153rd Ter",
    "sg:city":"Miami",
    "sg:classifiers":[
        {
            "category":"Banks & Credit Unions",
            "subcategory":"Bank",
            "type":"Services"
        }
    ],
    "sg:phone":"+1 305 255 2025",
    "sg:postcode":"33157",
    "sg:province":"FL",
    "sg:tags":[
        "mortgage"
    ],
    "wof:name":"Coral Reef Finance Inc",
    "wof:placetype":"venue"
},
  "geometry": {"coordinates":[-80.32812,25.627918],"type":"Point"}
}