{
  "type": "Feature",
  "properties": {
    "addr:full":"518 W Flagler St Miami FL 33130",
    "addr:housenumber":"518",
    "addr:postcode":"33130",
    "addr:street":"W Flagler St",
    "iso:country":"US",
    "sg:address":"518 W Flagler St",
    "sg:city":"Miami",
    "sg:classifiers":[
        {
            "category":"Banks & Credit Unions",
            "subcategory":"Bank",
            "type":"Services"
        }
    ],
    "sg:phone":"+1 305 325 9100",
    "sg:postcode":"33130",
    "sg:province":"FL",
    "sg:tags":[
        "loan",
        "real estate"
    ],
    "wof:name":"Hyatt Home Mortgage Inc",
    "wof:placetype":"venue"
},
  "geometry": {"coordinates":[-80.2041,25.773794],"type":"Point"}
}