{
  "type": "Feature",
  "properties": {
    "addr:full":"1063 Hammond Blvd Jacksonville FL 32221",
    "addr:housenumber":"1063",
    "addr:postcode":"32221",
    "addr:street":"Hammond Blvd",
    "iso:country":"US",
    "sg:address":"1063 Hammond Blvd",
    "sg:city":"Jacksonville",
    "sg:classifiers":[
        {
            "category":"Professional",
            "subcategory":"Computer Services",
            "type":"Services"
        }
    ],
    "sg:phone":"+1 904 781 6483",
    "sg:postcode":"32221",
    "sg:province":"FL",
    "wof:name":"Forslund Office Systems",
    "wof:placetype":"venue"
},
  "geometry": {"coordinates":[-81.79799,30.302132],"type":"Point"}
}