{
  "type": "Feature",
  "properties": {
    "iso:country":"US",
    "sg:address":"210 Altamonte Bay Clb Cr",
    "sg:city":"Altamonte Springs",
    "sg:classifiers":[
        {
            "category":"Real Estate",
            "subcategory":"Real Estate Operator",
            "type":"Services"
        }
    ],
    "sg:phone":"+1 407 260 2501",
    "sg:postcode":"32701",
    "sg:province":"FL",
    "sg:tags":[
        "apartment"
    ],
    "wof:name":"Altamonte Bay Club Apts",
    "wof:placetype":"venue"
},
  "geometry": {"coordinates":[-81.376999,28.6602],"type":"Point"}
}