{
  "type": "Feature",
  "properties": {
    "iso:country":"US",
    "sg:address":"3411 N Main Ter",
    "sg:city":"Gainesville",
    "sg:classifiers":[
        {
            "category":"Building & Trades",
            "subcategory":"Plumbing",
            "type":"Services"
        },
        {
            "category":"Retail",
            "subcategory":"Repair Shop",
            "type":"Services"
        },
        {
            "category":"Building & Trades",
            "subcategory":"Construction",
            "type":"Services"
        }
    ],
    "sg:phone":"+1 352 378 9422",
    "sg:postcode":"32609",
    "sg:province":"FL",
    "sg:tags":[
        "plumber",
        "equipment-commercial",
        "system",
        "industrial-servicing",
        "heating",
        "specialty",
        "contractor",
        "air conditioning",
        "refrigerating"
    ],
    "sg:website":"http://www.hurmco.com",
    "wof:name":"Mark Hurm & Co LLC",
    "wof:placetype":"venue"
},
  "geometry": {"coordinates":[-82.324217,29.682255],"type":"Point"}
}