{
  "type": "Feature",
  "properties": {
    "addr:full":"4098 Commercial Way Spring Hill FL 34606",
    "addr:housenumber":"4098",
    "addr:postcode":"34606",
    "addr:street":"Commercial Way",
    "iso:country":"US",
    "sg:address":"4098 Commercial Way",
    "sg:city":"Spring Hill",
    "sg:classifiers":[
        {
            "category":"Real Estate",
            "subcategory":"Real Estate Agent",
            "type":"Services"
        }
    ],
    "sg:phone":"+1 352 666 6658",
    "sg:postcode":"34606",
    "sg:province":"FL",
    "wof:name":"Hedick Group",
    "wof:placetype":"venue"
},
  "geometry": {"coordinates":[-82.60574,28.484323],"type":"Point"}
}