{
  "type": "Feature",
  "properties": {
    "addr:full":"8900 Pensacola Blvd Pensacola FL 32534",
    "addr:housenumber":"8900",
    "addr:postcode":"32534",
    "addr:street":"Pensacola Blvd",
    "iso:country":"US",
    "sg:address":"8900 Pensacola Blvd",
    "sg:city":"Pensacola",
    "sg:classifiers":[
        {
            "category":"Utilities",
            "subcategory":"Telephone",
            "type":"Services"
        },
        {
            "category":"Shopping",
            "subcategory":"Mobile Phones",
            "type":"Retail Goods"
        },
        {
            "category":"Manufacturing",
            "subcategory":"Electronics",
            "type":"Manufacturing & Wholesale Goods"
        },
        {
            "category":"Shopping",
            "subcategory":"Computers & Home Electronics",
            "type":"Retail Goods"
        },
        {
            "category":"Communications",
            "type":"Services"
        }
    ],
    "sg:phone":"+1 850 478 6928",
    "sg:postcode":"32534",
    "sg:province":"FL",
    "sg:tags":[
        "sound",
        "television",
        "theater",
        "supply",
        "system",
        "equipment",
        "radio",
        "cellular",
        "telecommunications-equipment",
        "consumer",
        "store"
    ],
    "sg:website":"http://www.radioshack.com",
    "wof:name":"RadioShack",
    "wof:placetype":"venue"
},
  "geometry": {"coordinates":[-87.27471199999999,30.526529],"type":"Point"}
}