{
  "type": "Feature",
  "properties": {
    "iso:country":"US",
    "sg:address":"506 Gulf Shore Dr",
    "sg:city":"Destin",
    "sg:classifiers":[
        {
            "category":"Real Estate",
            "subcategory":"Real Estate Operator",
            "type":"Services"
        }
    ],
    "sg:phone":"+1 850 837 2767",
    "sg:postcode":"32541",
    "sg:province":"FL",
    "sg:tags":[
        "condominium"
    ],
    "wof:name":"Inlet Reef Club Rental Office",
    "wof:placetype":"venue"
},
  "geometry": {"coordinates":[-86.503311,30.387776],"type":"Point"}
}