{
  "type": "Feature",
  "properties": {
    "iso:country":"US",
    "sg:address":"12995 Cleveland Ave",
    "sg:city":"Fort Myers",
    "sg:classifiers":[
        {
            "category":"Organizations",
            "subcategory":"Religious Organization",
            "type":"Services"
        }
    ],
    "sg:phone":"+1 239 433 3331",
    "sg:postcode":"33907",
    "sg:province":"FL",
    "sg:tags":[
        "church"
    ],
    "wof:name":"Palmcoast Community Church",
    "wof:placetype":"venue"
},
  "geometry": {"coordinates":[-81.871798,26.554451],"type":"Point"}
}