{
  "type": "Feature",
  "properties": {
    "iso:country":"US",
    "sg:address":"309 S Pinellas Ave",
    "sg:city":"Tarpon Springs",
    "sg:classifiers":[
        {
            "category":"Retail",
            "subcategory":"Repair Shop",
            "type":"Services"
        }
    ],
    "sg:phone":"+1 727 938 6967",
    "sg:postcode":"34689",
    "sg:province":"FL",
    "sg:tags":[
        "television",
        "radio"
    ],
    "wof:name":"C & C Electronics",
    "wof:placetype":"venue"
},
  "geometry": {"coordinates":[-82.75654299999999,28.143272],"type":"Point"}
}