{
  "type": "Feature",
  "properties": {
    "addr:full":"350 Maplewood Dr Jupiter FL 33458",
    "addr:housenumber":"350",
    "addr:postcode":"33458",
    "addr:street":"Maplewood Dr",
    "iso:country":"US",
    "sg:address":"350 Maplewood Dr",
    "sg:city":"Jupiter",
    "sg:classifiers":[
        {
            "category":"Sports & Exercise",
            "subcategory":"Bowling",
            "type":"Entertainment"
        }
    ],
    "sg:phone":"+1 561 743 9200",
    "sg:postcode":"33458",
    "sg:province":"FL",
    "sg:tags":[
        "center"
    ],
    "wof:name":"Jupiter Lanes",
    "wof:placetype":"venue"
},
  "geometry": {"coordinates":[-80.125107,26.932858],"type":"Point"}
}