{
  "type": "Feature",
  "properties": {
    "addr:full":"3801 Whitehall St Jacksonville FL 32206",
    "addr:housenumber":"3801",
    "addr:postcode":"32206",
    "addr:street":"Whitehall St",
    "iso:country":"US",
    "sg:address":"3801 Whitehall St",
    "sg:city":"Jacksonville",
    "sg:classifiers":[
        {
            "category":"Professional",
            "subcategory":"Lawyer & Legal Services",
            "type":"Services"
        }
    ],
    "sg:phone":"+1 904 722 9230",
    "sg:postcode":"32206",
    "sg:province":"FL",
    "wof:name":"Atlantic Law Firm Pl",
    "wof:placetype":"venue"
},
  "geometry": {"coordinates":[-81.651383,30.361455],"type":"Point"}
}