{
  "type": "Feature",
  "properties": {
    "addr:full":"8505 NW 29th Dr Pompano Beach FL 33065",
    "addr:housenumber":"8505",
    "addr:postcode":"33065",
    "addr:street":"Nw 29Th Dr",
    "iso:country":"US",
    "sg:address":"8505 NW 29th Dr",
    "sg:city":"Pompano Beach",
    "sg:classifiers":[
        {
            "category":"Professional",
            "subcategory":"Computer Services",
            "type":"Services"
        }
    ],
    "sg:phone":"+1 954 340 2637",
    "sg:postcode":"33065",
    "sg:province":"FL",
    "sg:tags":[
        "design",
        "system"
    ],
    "wof:name":"Larry Zeiler Web Designs",
    "wof:placetype":"venue"
},
  "geometry": {"coordinates":[-80.239942,26.267149],"type":"Point"}
}