{
  "type": "Feature",
  "properties": {
    "addr:full":"2867 Stonewall Pl Sanford FL 32773",
    "addr:housenumber":"2867",
    "addr:postcode":"32773",
    "addr:street":"Stonewall Pl",
    "iso:country":"US",
    "sg:address":"2867 Stonewall Pl",
    "sg:city":"Sanford",
    "sg:classifiers":[
        {
            "category":"Retail",
            "subcategory":"Auto Repair",
            "type":"Services"
        }
    ],
    "sg:phone":"+1 407 330 4000",
    "sg:postcode":"32773",
    "sg:province":"FL",
    "sg:tags":[
        "wrecker"
    ],
    "wof:name":"Central Florida Towing",
    "wof:placetype":"venue"
},
  "geometry": {"coordinates":[-81.30255699999999,28.733685],"type":"Point"}
}