{
  "type": "Feature",
  "properties": {
    "iso:country":"US",
    "sg:address":"515 SW 14th Ct",
    "sg:city":"Fort Lauderdale",
    "sg:classifiers":[
        {
            "category":"Professional",
            "subcategory":"Business Services",
            "type":"Services"
        }
    ],
    "sg:phone":"+1 954 761 9335",
    "sg:postcode":"33315",
    "sg:province":"FL",
    "wof:name":"Venture Yacht Sales Inc",
    "wof:placetype":"venue"
},
  "geometry": {"coordinates":[-80.14795100000001,26.10383],"type":"Point"}
}