{
  "type": "Feature",
  "properties": {
    "addr:full":"187 Brandon Town Center Dr Brandon FL 33511",
    "addr:housenumber":"187",
    "addr:postcode":"33511",
    "addr:street":"Brandon Town Center Dr",
    "iso:country":"US",
    "sg:address":"187 Brandon Town Center Dr",
    "sg:city":"Brandon",
    "sg:classifiers":[
        {
            "category":"Coffee & Tea",
            "type":"Food & Drink"
        }
    ],
    "sg:menulink":"http://www.allmenus.com/fl/brandon/116807-starbucks-coffee/menu/",
    "sg:phone":"+1 813 654 4955",
    "sg:postcode":"33511",
    "sg:province":"FL",
    "sg:tags":[
        "american"
    ],
    "wof:name":"Starbucks Coffee",
    "wof:placetype":"venue"
},
  "geometry": {"coordinates":[-82.32486299999999,27.937426],"type":"Point"}
}