{
  "type": "Feature",
  "properties": {
    "iso:country":"US",
    "sg:address":"930 Pineapple Rd",
    "sg:city":"South Daytona",
    "sg:classifiers":[
        {
            "category":"Shopping",
            "subcategory":"Used Merchandise",
            "type":"Retail Goods"
        }
    ],
    "sg:phone":"+1 386 767 1219",
    "sg:postcode":"32119",
    "sg:province":"FL",
    "sg:tags":[
        "antique"
    ],
    "wof:name":"Father & Son Collectibles",
    "wof:placetype":"venue"
},
  "geometry": {"coordinates":[-81.01665800000001,29.163802],"type":"Point"}
}