{
  "type": "Feature",
  "properties": {
    "iso:country":"US",
    "sg:address":"10707 E Colonial Dr",
    "sg:city":"Orlando",
    "sg:classifiers":[
        {
            "category":"Retail",
            "subcategory":"Laundry & Dry Cleaning",
            "type":"Services"
        }
    ],
    "sg:phone":"+1 407 380 5218",
    "sg:postcode":"32817",
    "sg:province":"FL",
    "sg:tags":[
        "drycleaning",
        "plant"
    ],
    "wof:name":"Valore Cleaners",
    "wof:placetype":"venue"
},
  "geometry": {"coordinates":[-81.22548500000001,28.568983],"type":"Point"}
}