{
  "type": "Feature",
  "properties": {
    "iso:country":"US",
    "sg:address":"38035 Meridian Ave",
    "sg:city":"Dade City",
    "sg:classifiers":[
        {
            "category":"Social Services",
            "type":"Services"
        }
    ],
    "sg:phone":"+1 352 521 0484",
    "sg:postcode":"33525",
    "sg:province":"FL",
    "wof:name":"Dade City Family Ymca",
    "wof:placetype":"venue"
},
  "geometry": {"coordinates":[-82.186717,28.364688],"type":"Point"}
}