{
  "type": "Feature",
  "properties": {
    "iso:country":"US",
    "sg:address":"529 W International Speedway Blvd",
    "sg:city":"Daytona Beach",
    "sg:classifiers":[
        {
            "category":"Wholesale",
            "subcategory":"Toys & Hobbies",
            "type":"Manufacturing & Wholesale Goods"
        }
    ],
    "sg:phone":"+1 386 255 8262",
    "sg:postcode":"32114",
    "sg:province":"FL",
    "sg:tags":[
        "firework"
    ],
    "sg:website":"www.skykingfireworks.com",
    "wof:name":"Sky King Fireworks-Daytona",
    "wof:placetype":"venue"
},
  "geometry": {"coordinates":[-81.026692,29.209146],"type":"Point"}
}