{
  "type": "Feature",
  "properties": {
    "addr:full":"5555 Fielding Ln Sarasota FL 34233",
    "addr:housenumber":"5555",
    "addr:postcode":"34233",
    "addr:street":"Fielding Ln",
    "iso:country":"US",
    "sg:address":"5555 Fielding Ln",
    "sg:city":"Sarasota",
    "sg:classifiers":[
        {
            "category":"Retail",
            "subcategory":"Repair Shop",
            "type":"Services"
        }
    ],
    "sg:phone":"+1 941 924 2230",
    "sg:postcode":"34233",
    "sg:province":"FL",
    "sg:tags":[
        "plumbing",
        "drain",
        "cleaning",
        "sewer"
    ],
    "wof:name":"Pioneer Services & Repairs",
    "wof:placetype":"venue"
},
  "geometry": {"coordinates":[-82.460364,27.274794],"type":"Point"}
}