{
  "type": "Feature",
  "properties": {
    "iso:country":"US",
    "sg:address":"9930 NW 59th Ct",
    "sg:city":"Pompano Beach",
    "sg:classifiers":[
        {
            "category":"Communications",
            "subcategory":"Film & Video Production",
            "type":"Services"
        }
    ],
    "sg:phone":"+1 954 340 1529",
    "sg:postcode":"33076",
    "sg:province":"FL",
    "sg:tags":[
        "motion"
    ],
    "wof:name":"GP Productions Inc",
    "wof:placetype":"venue"
},
  "geometry": {"coordinates":[-80.259073,26.304028],"type":"Point"}
}