{
  "type": "Feature",
  "properties": {
    "iso:country":"US",
    "sg:address":"2262 8th Ave N",
    "sg:city":"Saint Petersburg",
    "sg:classifiers":[
        {
            "category":"Personal",
            "subcategory":"Beauty Salon",
            "type":"Services"
        }
    ],
    "sg:phone":"+1 727 327 2426",
    "sg:postcode":"33713",
    "sg:province":"FL",
    "sg:tags":[
        "shop"
    ],
    "wof:name":"Helio",
    "wof:placetype":"venue"
},
  "geometry": {"coordinates":[-82.66372,27.78007],"type":"Point"}
}