{
  "type": "Feature",
  "properties": {
    "addr:full":"676 Tunghill Dr Tallahassee FL 32317",
    "addr:housenumber":"676",
    "addr:postcode":"32317",
    "addr:street":"Tunghill Dr",
    "iso:country":"US",
    "sg:address":"676 Tunghill Dr",
    "sg:city":"Tallahassee",
    "sg:classifiers":[
        {
            "category":"Professional",
            "subcategory":"Computer Services",
            "type":"Services"
        }
    ],
    "sg:phone":"+1 850 877 3364",
    "sg:postcode":"32317",
    "sg:province":"FL",
    "sg:tags":[
        "graphics"
    ],
    "wof:name":"Pine Apple Computing Solutions",
    "wof:placetype":"venue"
},
  "geometry": {"coordinates":[-84.187324,30.463342],"type":"Point"}
}