{
  "type": "Feature",
  "properties": {
    "iso:country":"US",
    "sg:address":"7052 103rd St",
    "sg:city":"Jacksonville",
    "sg:classifiers":[
        {
            "category":"Freight",
            "type":"Transportation"
        }
    ],
    "sg:phone":"+1 904 777 2859",
    "sg:postcode":"32210",
    "sg:province":"FL",
    "sg:tags":[
        "general"
    ],
    "wof:name":"Private Mini Storage Realty LP",
    "wof:placetype":"venue"
},
  "geometry": {"coordinates":[-81.762739,30.248259],"type":"Point"}
}