{
  "type": "Feature",
  "properties": {
    "addr:full":"15932 NW 48th Ave Hialeah FL 33014",
    "addr:housenumber":"15932",
    "addr:postcode":"33014",
    "addr:street":"Nw 48Th Ave",
    "iso:country":"US",
    "sg:address":"15932 NW 48th Ave",
    "sg:city":"Hialeah",
    "sg:classifiers":[
        {
            "category":"Home & Garden",
            "subcategory":"Building Materials",
            "type":"Retail Goods"
        }
    ],
    "sg:phone":"+1 305 627 1900",
    "sg:postcode":"33014",
    "sg:province":"FL",
    "wof:name":"New Screens",
    "wof:placetype":"venue"
},
  "geometry": {"coordinates":[-80.27883,25.923073],"type":"Point"}
}