{
  "type": "Feature",
  "properties": {
    "iso:country":"US",
    "sg:address":"3616 S Gardenia Ave",
    "sg:city":"Tampa",
    "sg:classifiers":[
        {
            "category":"Landmark",
            "subcategory":"Tourist Information",
            "type":"Public Place"
        }
    ],
    "sg:phone":"+1 813 760 6753",
    "sg:postcode":"33629",
    "sg:province":"FL",
    "sg:tags":[
        "promoter",
        "tours-operators"
    ],
    "wof:name":"Mary Poppins Tour",
    "wof:placetype":"venue"
},
  "geometry": {"coordinates":[-82.529386,27.911214],"type":"Point"}
}