{
  "type": "Feature",
  "properties": {
    "iso:country":"US",
    "sg:address":"2114 Brand Ct",
    "sg:city":"Navarre",
    "sg:classifiers":[
        {
            "category":"Organizations",
            "subcategory":"Religious Organization",
            "type":"Services"
        }
    ],
    "sg:phone":"+1 850 939 9097",
    "sg:postcode":"32566",
    "sg:province":"FL",
    "sg:tags":[
        "church"
    ],
    "sg:website":"www.ministriespromotingrevival.org",
    "wof:name":"Navarre Chapel & Academy",
    "wof:placetype":"venue"
},
  "geometry": {"coordinates":[-86.828816,30.412943],"type":"Point"}
}