{
  "type": "Feature",
  "properties": {
    "addr:full":"5101 Biscayne Blvd Miami FL 33137",
    "addr:housenumber":"5101",
    "addr:postcode":"33137",
    "addr:street":"Biscayne Blvd",
    "iso:country":"US",
    "sg:address":"5101 Biscayne Blvd",
    "sg:city":"Miami",
    "sg:classifiers":[
        {
            "category":"Building & Trades",
            "subcategory":"Locksmith",
            "type":"Services"
        }
    ],
    "sg:phone":"+1 305 351 4159",
    "sg:postcode":"33137",
    "sg:province":"FL",
    "sg:tags":[
        "key"
    ],
    "wof:name":"Adams Locksmith",
    "wof:placetype":"venue"
},
  "geometry": {"coordinates":[-80.186851,25.822892],"type":"Point"}
}