{
  "type": "Feature",
  "properties": {
    "addr:full":"2430 Leaning Pine Ln Oviedo FL 32765",
    "addr:postcode":"2430;32765",
    "addr:street":"Leaning Pine Ln",
    "iso:country":"US",
    "sg:address":"2430 Leaning Pine Ln",
    "sg:city":"Oviedo",
    "sg:classifiers":[
        {
            "category":"Building & Trades",
            "subcategory":"Construction",
            "type":"Services"
        }
    ],
    "sg:phone":"+1 407 366 6052",
    "sg:postcode":"32765",
    "sg:province":"FL",
    "sg:tags":[
        "house"
    ],
    "wof:name":"Westhelle Handyman Svc Thomas",
    "wof:placetype":"venue"
},
  "geometry": {"coordinates":[-81.226145,28.628425],"type":"Point"}
}