{
  "type": "Feature",
  "properties": {
    "addr:full":"6900 S Orange Blossom Trl Orlando FL 32809",
    "addr:housenumber":"6900",
    "addr:postcode":"32809",
    "addr:street":"S Orange Blossom Trl",
    "iso:country":"US",
    "sg:address":"6900 S Orange Blossom Trl",
    "sg:city":"Orlando",
    "sg:classifiers":[
        {
            "category":"Professional",
            "subcategory":"Employment Agencies",
            "type":"Services"
        }
    ],
    "sg:phone":"+1 407 855 9090",
    "sg:postcode":"32809",
    "sg:province":"FL",
    "sg:tags":[
        "opportunity"
    ],
    "wof:name":"Food Staff Of Orlando",
    "wof:placetype":"venue"
},
  "geometry": {"coordinates":[-81.397272,28.463054],"type":"Point"}
}