{
  "type": "Feature",
  "properties": {
    "iso:country":"US",
    "sg:address":"1611 NW 12th Ave",
    "sg:city":"Miami",
    "sg:classifiers":[
        {
            "category":"Health Services",
            "subcategory":"Doctor",
            "type":"Services"
        }
    ],
    "sg:phone":"+1 305 585 6970",
    "sg:postcode":"33136",
    "sg:province":"FL",
    "wof:name":"Zayden Graciela MD",
    "wof:placetype":"venue"
},
  "geometry": {"coordinates":[-80.215103,25.790899],"type":"Point"}
}