{
  "type": "Feature",
  "properties": {
    "iso:country":"US",
    "sg:address":"1375 W Palmetto Park Rd",
    "sg:city":"Boca Raton",
    "sg:classifiers":[
        {
            "category":"Shopping",
            "subcategory":"News",
            "type":"Retail Goods"
        }
    ],
    "sg:phone":"+1 561 368 8813",
    "sg:postcode":"33486",
    "sg:province":"FL",
    "sg:tags":[
        "book"
    ],
    "wof:name":"News Shack Inc The",
    "wof:placetype":"venue"
},
  "geometry": {"coordinates":[-80.113776,26.350823],"type":"Point"}
}