{
  "type": "Feature",
  "properties": {
    "iso:country":"US",
    "sg:address":"13079 SW 133rd Ct",
    "sg:city":"Miami",
    "sg:classifiers":[
        {
            "category":"Professional",
            "subcategory":"Business Services",
            "type":"Services"
        }
    ],
    "sg:phone":"+1 786 544 0130",
    "sg:postcode":"33186",
    "sg:province":"FL",
    "sg:tags":[
        "telemarketing"
    ],
    "wof:name":"Soluciones Medicas",
    "wof:placetype":"venue"
},
  "geometry": {"coordinates":[-80.41006899999999,25.648303],"type":"Point"}
}