{
  "type": "Feature",
  "properties": {
    "addr:full":"2464 Vanderbilt Beach Rd Naples FL 34109",
    "addr:housenumber":"2464",
    "addr:postcode":"34109",
    "addr:street":"Vanderbilt Beach Rd",
    "iso:country":"US",
    "sg:address":"2464 Vanderbilt Beach Rd",
    "sg:city":"Naples",
    "sg:classifiers":[
        {
            "category":"Professional",
            "subcategory":"Management & Consulting",
            "type":"Services"
        }
    ],
    "sg:phone":"+1 239 254 9970",
    "sg:postcode":"34109",
    "sg:province":"FL",
    "sg:tags":[
        "consultant",
        "educational"
    ],
    "wof:name":"Kumon Math & Reading Ctr",
    "wof:placetype":"venue"
},
  "geometry": {"coordinates":[-81.76846500000001,26.243745],"type":"Point"}
}