{
  "type": "Feature",
  "properties": {
    "iso:country":"US",
    "sg:address":"232 Washington Ave",
    "sg:city":"Homestead",
    "sg:classifiers":[
        {
            "category":"Shopping",
            "subcategory":"Computers & Home Electronics",
            "type":"Retail Goods"
        }
    ],
    "sg:phone":"+1 786 243 3871",
    "sg:postcode":"33030",
    "sg:province":"FL",
    "sg:tags":[
        "audio"
    ],
    "wof:name":"Talk Visual",
    "wof:placetype":"venue"
},
  "geometry": {"coordinates":[-80.47637899999999,25.473199],"type":"Point"}
}