{
  "type": "Feature",
  "properties": {
    "addr:full":"22941 144th St Live Oak FL 32060",
    "addr:housenumber":"22941",
    "addr:postcode":"32060",
    "addr:street":"144Th St",
    "iso:country":"US",
    "sg:address":"22941 144th St",
    "sg:city":"Live Oak",
    "sg:classifiers":[
        {
            "category":"Home & Garden",
            "subcategory":"Garden Supply",
            "type":"Retail Goods"
        }
    ],
    "sg:phone":"+1 386 776 1584",
    "sg:postcode":"32060",
    "sg:province":"FL",
    "wof:name":"Lisk Tree Farm",
    "wof:placetype":"venue"
},
  "geometry": {"coordinates":[-83.221317,30.187735],"type":"Point"}
}