{
  "type": "Feature",
  "properties": {
    "addr:full":"4213 E Osborne Ave Tampa FL 33610",
    "addr:housenumber":"4213",
    "addr:postcode":"33610",
    "addr:street":"E Osborne Ave",
    "iso:country":"US",
    "sg:address":"4213 E Osborne Ave",
    "sg:city":"Tampa",
    "sg:classifiers":[
        {
            "category":"Personal",
            "subcategory":"Barber",
            "type":"Services"
        }
    ],
    "sg:phone":"+1 813 622 7512",
    "sg:postcode":"33610",
    "sg:province":"FL",
    "sg:tags":[
        "shop"
    ],
    "wof:name":"Nunn's Barber & Beauty Shop",
    "wof:placetype":"venue"
},
  "geometry": {"coordinates":[-82.41021499999999,27.988704],"type":"Point"}
}