{
  "type": "Feature",
  "properties": {
    "addr:full":"12600 SW 130th St Miami FL 33186",
    "addr:housenumber":"12600",
    "addr:postcode":"33186",
    "addr:street":"Sw 130Th St",
    "iso:country":"US",
    "sg:address":"12600 SW 130th St",
    "sg:city":"Miami",
    "sg:classifiers":[
        {
            "category":"Sports & Exercise",
            "subcategory":"Gym",
            "type":"Entertainment"
        }
    ],
    "sg:phone":"+1 786 573 0088",
    "sg:postcode":"33186",
    "sg:province":"FL",
    "sg:tags":[
        "instruction",
        "gymnastics"
    ],
    "sg:website":"http://www.gymnasticwizards.com",
    "wof:name":"Gymnastic Wizards LLC",
    "wof:placetype":"venue"
},
  "geometry": {"coordinates":[-80.39736000000001,25.64681],"type":"Point"}
}