{
  "type": "Feature",
  "properties": {
    "addr:full":"4810 SW 57th Ter Davie FL 33314",
    "addr:housenumber":"4810",
    "addr:postcode":"33314",
    "addr:street":"Sw 57Th Ter",
    "iso:country":"US",
    "sg:address":"4810 SW 57th Ter",
    "sg:city":"Davie",
    "sg:classifiers":[
        {
            "category":"Wholesale",
            "subcategory":"Toys & Hobbies",
            "type":"Manufacturing & Wholesale Goods"
        }
    ],
    "sg:phone":"+1 954 791 9929",
    "sg:postcode":"33314",
    "sg:province":"FL",
    "wof:name":"Daston Inc",
    "wof:placetype":"venue"
},
  "geometry": {"coordinates":[-80.222745,26.061026],"type":"Point"}
}