{
  "type": "Feature",
  "properties": {
    "addr:full":"109 Flagship Dr Lutz FL 33549",
    "addr:housenumber":"109",
    "addr:postcode":"33549",
    "addr:street":"Flagship Dr",
    "iso:country":"US",
    "sg:address":"109 Flagship Dr",
    "sg:city":"Lutz",
    "sg:classifiers":[
        {
            "category":"Shopping",
            "subcategory":"Jewelry",
            "type":"Retail Goods"
        }
    ],
    "sg:phone":"+1 813 909 1680",
    "sg:postcode":"33549",
    "sg:province":"FL",
    "sg:tags":[
        "jeweler"
    ],
    "wof:name":"T C Dilm Inc",
    "wof:placetype":"venue"
},
  "geometry": {"coordinates":[-82.463145,28.134852],"type":"Point"}
}