{
  "type": "Feature",
  "properties": {
    "iso:country":"US",
    "sg:address":"413 NW 72nd St",
    "sg:city":"Boca Raton",
    "sg:classifiers":[
        {
            "category":"Real Estate",
            "subcategory":"Real Estate Agent",
            "type":"Services"
        }
    ],
    "sg:phone":"+1 561 997 0450",
    "sg:postcode":"33487",
    "sg:province":"FL",
    "wof:name":"Commercial Property Advisors",
    "wof:placetype":"venue"
},
  "geometry": {"coordinates":[-80.085221,26.413826],"type":"Point"}
}