{
  "type": "Feature",
  "properties": {
    "addr:full":"17631 S Dixie Hwy Miami FL 33157",
    "addr:housenumber":"17631",
    "addr:postcode":"33157",
    "addr:street":"S Dixie Hwy",
    "iso:country":"US",
    "sg:address":"17631 S Dixie Hwy",
    "sg:city":"Miami",
    "sg:classifiers":[
        {
            "category":"Manufacturing",
            "subcategory":"Leather Goods",
            "type":"Manufacturing & Wholesale Goods"
        },
        {
            "category":"Autos & Motor Vehicles",
            "subcategory":"Motorcycle Sales",
            "type":"Retail Goods"
        }
    ],
    "sg:phone":"+1 305 235 4023",
    "sg:postcode":"33157",
    "sg:province":"FL",
    "wof:name":"Phil Petersons Harley Davidson",
    "wof:placetype":"venue"
},
  "geometry": {"coordinates":[-80.349098,25.605],"type":"Point"}
}