{
  "type": "Feature",
  "properties": {
    "iso:country":"US",
    "sg:address":"1172 Dixie Hwy",
    "sg:city":"Miami",
    "sg:classifiers":[
        {
            "category":"Professional",
            "subcategory":"Business Services",
            "type":"Services"
        }
    ],
    "sg:phone":"+1 305 269 0030",
    "sg:postcode":"33146",
    "sg:province":"FL",
    "sg:tags":[
        "employment",
        "check"
    ],
    "wof:name":"Florida Asset Locators Inc",
    "wof:placetype":"venue"
},
  "geometry": {"coordinates":[-80.275719,25.715414],"type":"Point"}
}