{
  "type": "Feature",
  "properties": {
    "iso:country":"US",
    "sg:address":"3460 N Courtenay Pkwy",
    "sg:city":"Merritt Island",
    "sg:classifiers":[
        {
            "category":"Retail",
            "subcategory":"Repair Shop",
            "type":"Services"
        }
    ],
    "sg:phone":"+1 321 452 7732",
    "sg:postcode":"32953",
    "sg:province":"FL",
    "sg:tags":[
        "upholsterer"
    ],
    "wof:name":"Custom Upholstery Designs",
    "wof:placetype":"venue"
},
  "geometry": {"coordinates":[-80.706847,28.419451],"type":"Point"}
}