{
  "type": "Feature",
  "properties": {
    "iso:country":"US",
    "sg:address":"4611 W North A St",
    "sg:city":"Tampa",
    "sg:classifiers":[
        {
            "category":"Professional",
            "subcategory":"Advertising",
            "type":"Services"
        }
    ],
    "sg:phone":"+1 813 287 8177",
    "sg:postcode":"33609",
    "sg:province":"FL",
    "sg:tags":[
        "agency"
    ],
    "wof:name":"Dynamedia Of America Inc",
    "wof:placetype":"venue"
},
  "geometry": {"coordinates":[-82.524058,27.945879],"type":"Point"}
}