{
  "type": "Feature",
  "properties": {
    "addr:full":"7301 N Federal Hwy Boca Raton FL 33487",
    "addr:housenumber":"7301",
    "addr:postcode":"33487",
    "addr:street":"N Federal Hwy",
    "iso:country":"US",
    "sg:address":"7301 N Federal Hwy",
    "sg:city":"Boca Raton",
    "sg:classifiers":[
        {
            "category":"Home & Garden",
            "subcategory":"Home Furnishings",
            "type":"Retail Goods"
        }
    ],
    "sg:phone":"+1 561 994 9570",
    "sg:postcode":"33487",
    "sg:province":"FL",
    "sg:tags":[
        "lighting",
        "fixture"
    ],
    "wof:name":"Capitol Lighting",
    "wof:placetype":"venue"
},
  "geometry": {"coordinates":[-80.074771,26.417697],"type":"Point"}
}