{
  "type": "Feature",
  "properties": {
    "iso:country":"US",
    "sg:address":"6801 SE Federal Hwy",
    "sg:city":"Stuart",
    "sg:classifiers":[
        {
            "category":"Retail",
            "subcategory":"Funeral Services",
            "type":"Services"
        }
    ],
    "sg:phone":"+1 772 223 9300",
    "sg:postcode":"34997",
    "sg:province":"FL",
    "sg:tags":[
        "director",
        "home"
    ],
    "wof:name":"Young and Prill Funeral Home",
    "wof:placetype":"venue"
},
  "geometry": {"coordinates":[-80.18866800000001,27.122906],"type":"Point"}
}