{
  "type": "Feature",
  "properties": {
    "addr:full":"919 Lithia Pinecrest Rd Brandon FL 33511",
    "addr:housenumber":"919",
    "addr:postcode":"33511",
    "addr:street":"Lithia Pinecrest Rd",
    "iso:country":"US",
    "sg:address":"919 Lithia Pinecrest Rd",
    "sg:city":"Brandon",
    "sg:classifiers":[
        {
            "category":"Restaurant",
            "type":"Food & Drink"
        }
    ],
    "sg:phone":"+1 813 654 4608",
    "sg:postcode":"33511",
    "sg:province":"FL",
    "sg:tags":[
        "asian",
        "chinese",
        "pan"
    ],
    "wof:name":"China Express",
    "wof:placetype":"venue"
},
  "geometry": {"coordinates":[-82.27076599999999,27.924143],"type":"Point"}
}