{
  "type": "Feature",
  "properties": {
    "iso:country":"US",
    "sg:address":"704 SW 34th St",
    "sg:city":"Fort Lauderdale",
    "sg:classifiers":[
        {
            "category":"Airline",
            "type":"Transportation"
        }
    ],
    "sg:phone":"+1 954 359 0329",
    "sg:postcode":"33315",
    "sg:province":"FL",
    "sg:tags":[
        "company"
    ],
    "sg:website":"www.chalksoceanairways.com",
    "wof:name":"Chalk's International Airlines",
    "wof:placetype":"venue"
},
  "geometry": {"coordinates":[-80.14953199999999,26.08156],"type":"Point"}
}