{
  "type": "Feature",
  "properties": {
    "iso:country":"US",
    "sg:address":"162 Arbor Ln",
    "sg:city":"Tavernier",
    "sg:classifiers":[
        {
            "category":"Building & Trades",
            "subcategory":"Landscaping Services",
            "type":"Services"
        }
    ],
    "sg:phone":"+1 305 853 0276",
    "sg:postcode":"33070",
    "sg:province":"FL",
    "sg:tags":[
        "landscape"
    ],
    "wof:name":"Tawnya Nortons Islands In Sun",
    "wof:placetype":"venue"
},
  "geometry": {"coordinates":[-80.508771,25.017333],"type":"Point"}
}