{
  "type": "Feature",
  "properties": {
    "addr:full":"24 W Enid Dr Key Biscayne FL 33149",
    "addr:housenumber":"24",
    "addr:postcode":"33149",
    "addr:street":"W Enid Dr",
    "iso:country":"US",
    "sg:address":"24 W Enid Dr",
    "sg:city":"Key Biscayne",
    "sg:classifiers":[
        {
            "category":"Health Services",
            "subcategory":"Health Practitioner",
            "type":"Services"
        }
    ],
    "sg:phone":"+1 305 361 8837",
    "sg:postcode":"33149",
    "sg:province":"FL",
    "wof:name":"Rabassa Thompson Annie",
    "wof:placetype":"venue"
},
  "geometry": {"coordinates":[-80.16391900000001,25.690056],"type":"Point"}
}