{
  "type": "Feature",
  "properties": {
    "addr:full":"9522 W Flora St Tampa FL 33615",
    "addr:housenumber":"9522",
    "addr:postcode":"33615",
    "addr:street":"W Flora St",
    "iso:country":"US",
    "sg:address":"9522 W Flora St",
    "sg:city":"Tampa",
    "sg:classifiers":[
        {
            "category":"Building & Trades",
            "subcategory":"Landscaping Services",
            "type":"Services"
        }
    ],
    "sg:phone":"+1 813 888 8846",
    "sg:postcode":"33615",
    "sg:province":"FL",
    "wof:name":"Freedom Lawn Service",
    "wof:placetype":"venue"
},
  "geometry": {"coordinates":[-82.59194599999999,28.012914],"type":"Point"}
}