{
  "type": "Feature",
  "properties": {
    "iso:country":"US",
    "sg:address":"1800 Bridge St",
    "sg:city":"Englewood",
    "sg:classifiers":[
        {
            "category":"Wholesale",
            "subcategory":"Electrical",
            "type":"Manufacturing & Wholesale Goods"
        }
    ],
    "sg:phone":"+1 941 474 2656",
    "sg:postcode":"34223",
    "sg:province":"FL",
    "sg:tags":[
        "control",
        "security",
        "system"
    ],
    "wof:name":"Gulf Coast Security Plus Inc",
    "wof:placetype":"venue"
},
  "geometry": {"coordinates":[-82.39297500000001,27.002109],"type":"Point"}
}