{
  "type": "Feature",
  "properties": {
    "iso:country":"US",
    "sg:address":"701 John Sims Pkwy",
    "sg:city":"Niceville",
    "sg:classifiers":[
        {
            "category":"Professional",
            "subcategory":"Research",
            "type":"Services"
        }
    ],
    "sg:phone":"+1 850 678 9912",
    "sg:postcode":"32578",
    "sg:province":"FL",
    "sg:tags":[
        "nonphysical",
        "commercial"
    ],
    "wof:name":"Modern Technology Solutions",
    "wof:placetype":"venue"
},
  "geometry": {"coordinates":[-86.478155,30.518714],"type":"Point"}
}