{
  "type": "Feature",
  "properties": {
    "iso:country":"US",
    "sg:address":"160 Vilano Rd",
    "sg:city":"St Augustine",
    "sg:classifiers":[
        {
            "category":"Building & Trades",
            "subcategory":"Construction",
            "type":"Services"
        }
    ],
    "sg:phone":"+1 904 824 5178",
    "sg:postcode":"32084",
    "sg:province":"FL",
    "sg:tags":[
        "restoration",
        "preservation"
    ],
    "wof:name":"Historic Property Assoc",
    "wof:placetype":"venue"
},
  "geometry": {"coordinates":[-81.296491,29.916781],"type":"Point"}
}