{
  "type": "Feature",
  "properties": {
    "addr:full":"8700 Pisa Dr Orlando FL 32810",
    "addr:housenumber":"8700",
    "addr:postcode":"32810",
    "addr:street":"Pisa Dr",
    "iso:country":"US",
    "sg:address":"8700 Pisa Dr",
    "sg:city":"Orlando",
    "sg:classifiers":[
        {
            "category":"Sports & Exercise",
            "subcategory":"Gym",
            "type":"Entertainment"
        }
    ],
    "sg:phone":"+1 407 667 9177",
    "sg:postcode":"32810",
    "sg:province":"FL",
    "sg:tags":[
        "club",
        "health",
        "studio",
        "gymnasium"
    ],
    "sg:website":"www.topbodiesfitness.com",
    "wof:name":"Top Bodies Fitness Ctr",
    "wof:placetype":"venue"
},
  "geometry": {"coordinates":[-81.406048,28.637372],"type":"Point"}
}