{
  "type": "Feature",
  "properties": {
    "iso:country":"US",
    "sg:address":"2679 S Woodland Blvd",
    "sg:city":"Deland",
    "sg:classifiers":[
        {
            "category":"Banks & Credit Unions",
            "subcategory":"Bank",
            "type":"Services"
        }
    ],
    "sg:phone":"+1 386 736 3827",
    "sg:postcode":"32720",
    "sg:province":"FL",
    "sg:tags":[
        "cashing",
        "loan",
        "check",
        "broker"
    ],
    "wof:name":"First American Cash Advance",
    "wof:placetype":"venue"
},
  "geometry": {"coordinates":[-81.299353,28.979837],"type":"Point"}
}