{
  "type": "Feature",
  "properties": {
    "addr:full":"2415 Hollywood Blvd Hollywood FL 33020",
    "addr:housenumber":"2415",
    "addr:postcode":"33020",
    "addr:street":"Hollywood Blvd",
    "iso:country":"US",
    "sg:address":"2415 Hollywood Blvd",
    "sg:city":"Hollywood",
    "sg:classifiers":[
        {
            "category":"Real Estate",
            "subcategory":"Real Estate Agent",
            "type":"Services"
        }
    ],
    "sg:phone":"+1 954 927 0007",
    "sg:postcode":"33020",
    "sg:province":"FL",
    "wof:name":"Concasa Realty Inc",
    "wof:placetype":"venue"
},
  "geometry": {"coordinates":[-80.157734,26.011276],"type":"Point"}
}