{
  "type": "Feature",
  "properties": {
    "addr:full":"2237 NW 20th St Miami FL 33142",
    "addr:housenumber":"2237",
    "addr:postcode":"33142",
    "addr:street":"Nw 20Th St",
    "iso:country":"US",
    "sg:address":"2237 NW 20th St",
    "sg:city":"Miami",
    "sg:classifiers":[
        {
            "category":"Shopping",
            "subcategory":"Luggage & Leather Goods",
            "type":"Retail Goods"
        }
    ],
    "sg:phone":"+1 305 635 4204",
    "sg:postcode":"33142",
    "sg:province":"FL",
    "wof:name":"Recan Corp",
    "wof:placetype":"venue"
},
  "geometry": {"coordinates":[-80.23219400000001,25.794576],"type":"Point"}
}