{
  "type": "Feature",
  "properties": {
    "iso:country":"US",
    "sg:address":"940 NW 8th Ave",
    "sg:city":"Pompano Beach",
    "sg:classifiers":[
        {
            "category":"Communications",
            "type":"Services"
        }
    ],
    "sg:phone":"+1 954 532 4638",
    "sg:postcode":"33060",
    "sg:province":"FL",
    "sg:tags":[
        "communication"
    ],
    "wof:name":"Wp Communications Inc",
    "wof:placetype":"venue"
},
  "geometry": {"coordinates":[-80.133438,26.239007],"type":"Point"}
}