{
  "type": "Feature",
  "properties": {
    "addr:full":"7407 Sunset Way St Pete Beach FL 33706",
    "addr:housenumber":"7407",
    "addr:postcode":"33706",
    "addr:street":"Sunset Way St",
    "iso:country":"US",
    "sg:address":"7407 Sunset Way",
    "sg:city":"St Pete Beach",
    "sg:classifiers":[
        {
            "category":"Home & Garden",
            "subcategory":"Building Materials",
            "type":"Retail Goods"
        }
    ],
    "sg:phone":"+1 727 360 6513",
    "sg:postcode":"33706",
    "sg:province":"FL",
    "sg:tags":[
        "screen",
        "window"
    ],
    "wof:name":"Affordable Screen & Window Rpr",
    "wof:placetype":"venue"
},
  "geometry": {"coordinates":[-82.75403799999999,27.740898],"type":"Point"}
}