{
  "type": "Feature",
  "properties": {
    "addr:full":"3868 Heron Ridge Ln Weston FL 33331",
    "addr:housenumber":"3868",
    "addr:postcode":"33331",
    "addr:street":"Heron Ridge Ln",
    "iso:country":"US",
    "sg:address":"3868 Heron Ridge Ln",
    "sg:city":"Weston",
    "sg:classifiers":[
        {
            "category":"Professional",
            "subcategory":"Advertising",
            "type":"Services"
        }
    ],
    "sg:phone":"+1 954 217 8229",
    "sg:postcode":"33331",
    "sg:province":"FL",
    "sg:tags":[
        "distribution"
    ],
    "wof:name":"Transamerica Distribution Fnnc",
    "wof:placetype":"venue"
},
  "geometry": {"coordinates":[-80.38275,26.072179],"type":"Point"}
}