{
  "type": "Feature",
  "properties": {
    "iso:country":"US",
    "sg:address":"617 Azalea St",
    "sg:city":"Panama City Bch",
    "sg:classifiers":[
        {
            "category":"Restaurant",
            "type":"Food & Drink"
        }
    ],
    "sg:phone":"+1 850 233 0403",
    "sg:postcode":"32407",
    "sg:province":"FL",
    "wof:name":"Cajun Inn Inc",
    "wof:placetype":"venue"
},
  "geometry": {"coordinates":[-85.84385399999999,30.20023],"type":"Point"}
}