{
  "type": "Feature",
  "properties": {
    "addr:full":"8810 Dyer Rd Riverview FL 33578",
    "addr:housenumber":"8810",
    "addr:postcode":"33578",
    "addr:street":"Dyer Rd",
    "iso:country":"US",
    "sg:address":"8810 Dyer Rd",
    "sg:city":"Riverview",
    "sg:classifiers":[
        {
            "category":"Building & Trades",
            "subcategory":"Construction",
            "type":"Services"
        }
    ],
    "sg:phone":"+1 813 677 1166",
    "sg:postcode":"33578",
    "sg:province":"FL",
    "sg:tags":[
        "cleaning",
        "carpentry"
    ],
    "wof:name":"3ws Enterprise Inc",
    "wof:placetype":"venue"
},
  "geometry": {"coordinates":[-82.351704,27.861239],"type":"Point"}
}