{
  "type": "Feature",
  "properties": {
    "iso:country":"US",
    "sg:address":"3735 SW 8th St",
    "sg:city":"Coral Gables",
    "sg:classifiers":[
        {
            "category":"Health Services",
            "subcategory":"Doctor",
            "type":"Services"
        }
    ],
    "sg:phone":"+1 305 445 2550",
    "sg:postcode":"33134",
    "sg:province":"FL",
    "wof:name":"Trabanco Carlos L MD",
    "wof:placetype":"venue"
},
  "geometry": {"coordinates":[-80.255898,25.7647],"type":"Point"}
}