{
  "type": "Feature",
  "properties": {
    "addr:full":"7061 Grand National Dr Orlando FL 32819",
    "addr:housenumber":"7061",
    "addr:postcode":"32819",
    "addr:street":"Grand National Dr",
    "iso:country":"US",
    "sg:address":"7061 Grand National Dr",
    "sg:city":"Orlando",
    "sg:classifiers":[
        {
            "category":"Shopping",
            "subcategory":"Catalog Store",
            "type":"Retail Goods"
        },
        {
            "category":"Professional",
            "subcategory":"Management & Consulting",
            "type":"Services"
        }
    ],
    "sg:phone":"+1 407 226 8174",
    "sg:postcode":"32819",
    "sg:province":"FL",
    "sg:tags":[
        "antique",
        "collectible",
        "business",
        "consultant"
    ],
    "wof:name":"Starabillas",
    "wof:placetype":"venue"
},
  "geometry": {"coordinates":[-81.456153,28.458715],"type":"Point"}
}