{
  "type": "Feature",
  "properties": {
    "addr:full":"13475 Atlantic Blvd Ste 17 Jacksonville FL 32225",
    "addr:housenumber":"13475",
    "addr:postcode":"32225",
    "addr:street":"Atlantic Blvd Ste 17",
    "iso:country":"US",
    "sg:address":"13475 Atlantic Blvd Ste 17",
    "sg:city":"Jacksonville",
    "sg:classifiers":[
        {
            "category":"Personal",
            "subcategory":"Massage",
            "type":"Services"
        },
        {
            "category":"Personal",
            "subcategory":"Beauty Salon",
            "type":"Services"
        },
        {
            "category":"Health Services",
            "subcategory":"Health Practitioner",
            "type":"Services"
        },
        {
            "category":"Personal",
            "subcategory":"Skin Care",
            "type":"Services"
        }
    ],
    "sg:phone":"+1 904 302 5741",
    "sg:postcode":"32225",
    "sg:province":"FL",
    "sg:tags":[
        "medicine",
        "alternative",
        "therapist"
    ],
    "sg:website":"http://www.MassageEnvy.com",
    "wof:name":"Massage Envy",
    "wof:placetype":"venue"
},
  "geometry": {"coordinates":[-81.453171,30.320798],"type":"Point"}
}