{
  "type": "Feature",
  "properties": {
    "iso:country":"US",
    "sg:address":"8567 Royal Lakes Dr",
    "sg:city":"Jacksonville",
    "sg:classifiers":[
        {
            "category":"Health Services",
            "subcategory":"Medical Lab",
            "type":"Services"
        }
    ],
    "sg:phone":"+1 904 737 9996",
    "sg:postcode":"32256",
    "sg:province":"FL",
    "sg:tags":[
        "laboratory",
        "dental"
    ],
    "wof:name":"Schemer Dental Ceramics Inc",
    "wof:placetype":"venue"
},
  "geometry": {"coordinates":[-81.554953,30.215134],"type":"Point"}
}