{
  "type": "Feature",
  "properties": {
    "iso:country":"US",
    "sg:address":"2433 S Lake Ave B",
    "sg:city":"Sanford",
    "sg:classifiers":[
        {
            "category":"Professional",
            "type":"Services"
        }
    ],
    "sg:phone":"+1 407 322 7824",
    "sg:postcode":"32771",
    "sg:province":"FL",
    "sg:tags":[
        "harvesting-contract"
    ],
    "wof:name":"Henry Slater Citrus Contractor",
    "wof:placetype":"venue"
},
  "geometry": {"coordinates":[-81.277182,28.788329],"type":"Point"}
}