{
  "type": "Feature",
  "properties": {
    "iso:country":"US",
    "sg:address":"9381 Springview Loop",
    "sg:city":"Estero",
    "sg:classifiers":[
        {
            "category":"Farming",
            "subcategory":"Farm",
            "type":"Manufacturing & Wholesale Goods"
        }
    ],
    "sg:phone":"+1 239 495 7897",
    "sg:postcode":"33928",
    "sg:province":"FL",
    "wof:name":"Constant Farms",
    "wof:placetype":"venue"
},
  "geometry": {"coordinates":[-81.803123,26.447336],"type":"Point"}
}