{
  "type": "Feature",
  "properties": {
    "iso:country":"US",
    "sg:address":"3102 S Orange Ave",
    "sg:city":"Orlando",
    "sg:classifiers":[
        {
            "category":"Retail",
            "subcategory":"Auto Repair",
            "type":"Services"
        }
    ],
    "sg:phone":"+1 407 850 9410",
    "sg:postcode":"32806",
    "sg:province":"FL",
    "sg:tags":[
        "body",
        "automobile",
        "painting",
        "repairing"
    ],
    "wof:name":"Willie's Paint & Body Shop Inc",
    "wof:placetype":"venue"
},
  "geometry": {"coordinates":[-81.37631,28.508785],"type":"Point"}
}