{
  "type": "Feature",
  "properties": {
    "addr:full":"91 NE 167th St Miami FL 33162",
    "addr:housenumber":"91",
    "addr:postcode":"33162",
    "addr:street":"Ne 167Th St",
    "iso:country":"US",
    "sg:address":"91 NE 167th St",
    "sg:city":"Miami",
    "sg:classifiers":[
        {
            "category":"Personal",
            "subcategory":"Nail Salon",
            "type":"Services"
        }
    ],
    "sg:phone":"+1 305 654 8689",
    "sg:postcode":"33162",
    "sg:province":"FL",
    "wof:name":"Diamond Nails",
    "wof:placetype":"venue"
},
  "geometry": {"coordinates":[-80.198601,25.928301],"type":"Point"}
}