{
  "type": "Feature",
  "properties": {
    "iso:country":"US",
    "sg:address":"1390 Duroc Dr",
    "sg:city":"Lake Helen",
    "sg:classifiers":[
        {
            "category":"Building & Trades",
            "subcategory":"Landscaping Services",
            "type":"Services"
        }
    ],
    "sg:phone":"+1 386 532 1066",
    "sg:postcode":"32744",
    "sg:province":"FL",
    "sg:tags":[
        "tree"
    ],
    "wof:name":"Treescapes Tree Removal Svc",
    "wof:placetype":"venue"
},
  "geometry": {"coordinates":[-81.204313,28.974582],"type":"Point"}
}