{
  "type": "Feature",
  "properties": {
    "addr:full":"605 W Bloomingdale Ave Brandon FL 33511",
    "addr:housenumber":"605",
    "addr:postcode":"33511",
    "addr:street":"W Bloomingdale Ave",
    "iso:country":"US",
    "sg:address":"605 W Bloomingdale Ave",
    "sg:city":"Brandon",
    "sg:classifiers":[
        {
            "category":"Personal",
            "subcategory":"Beauty Salon",
            "type":"Services"
        }
    ],
    "sg:phone":"+1 813 689 4423",
    "sg:postcode":"33511",
    "sg:province":"FL",
    "sg:tags":[
        "treatment",
        "skin"
    ],
    "wof:name":"Tranquility Skin Care Studio",
    "wof:placetype":"venue"
},
  "geometry": {"coordinates":[-82.29255000000001,27.893536],"type":"Point"}
}