{
  "type": "Feature",
  "properties": {
    "iso:country":"US",
    "sg:address":"1024 E Orange Ave",
    "sg:city":"Eustis",
    "sg:classifiers":[
        {
            "category":"Freight",
            "type":"Transportation"
        }
    ],
    "sg:phone":"+1 352 357 5221",
    "sg:postcode":"32726",
    "sg:province":"FL",
    "sg:tags":[
        "trucking"
    ],
    "wof:name":"Cletus Nacke Truck Line",
    "wof:placetype":"venue"
},
  "geometry": {"coordinates":[-81.67467499999999,28.852833],"type":"Point"}
}