{
  "type": "Feature",
  "properties": {
    "iso:country":"US",
    "sg:address":"3809 Grand Ave",
    "sg:city":"Miami",
    "sg:classifiers":[
        {
            "category":"Restaurant",
            "type":"Food & Drink"
        }
    ],
    "sg:menulink":"http://www.allmenus.com/fl/miami/241507-hardaways-house-of-wings/menu/",
    "sg:phone":"+1 305 569 7737",
    "sg:postcode":"33133",
    "sg:province":"FL",
    "sg:tags":[
        "american"
    ],
    "wof:name":"Hardaway's House Of Wings",
    "wof:placetype":"venue"
},
  "geometry": {"coordinates":[-80.254723,25.727535],"type":"Point"}
}