{
  "type": "Feature",
  "properties": {
    "iso:country":"US",
    "sg:address":"11515 Pyramid Dr",
    "sg:city":"Odessa",
    "sg:classifiers":[
        {
            "category":"Professional",
            "subcategory":"Advertising",
            "type":"Services"
        },
        {
            "category":"Professional",
            "subcategory":"Printing & Photocopies",
            "type":"Services"
        },
        {
            "category":"Wholesale",
            "subcategory":"Books, Periodicals, & Newspapers",
            "type":"Manufacturing & Wholesale Goods"
        }
    ],
    "sg:phone":"+1 727 376 7200",
    "sg:postcode":"33556",
    "sg:province":"FL",
    "sg:tags":[
        "publisher",
        "services-commercial",
        "direct",
        "mail"
    ],
    "sg:website":"http://www.abcoprint.com",
    "wof:name":"ABCO Graphics & Printing",
    "wof:placetype":"venue"
},
  "geometry": {"coordinates":[-82.62442299999999,28.195551],"type":"Point"}
}