{
  "type": "Feature",
  "properties": {
    "iso:country":"US",
    "sg:address":"1270 Wadsworth St SE",
    "sg:city":"Palm Bay",
    "sg:classifiers":[
        {
            "category":"Building & Trades",
            "subcategory":"Construction",
            "type":"Services"
        }
    ],
    "sg:phone":"+1 321 795 2596",
    "sg:postcode":"32909",
    "sg:province":"FL",
    "sg:tags":[
        "contractor"
    ],
    "wof:name":"Outbound Satellite",
    "wof:placetype":"venue"
},
  "geometry": {"coordinates":[-80.635875,27.97087],"type":"Point"}
}