{
  "type": "Feature",
  "properties": {
    "addr:full":"18319 SW 139th Pl Miami FL 33177",
    "addr:housenumber":"18319",
    "addr:postcode":"33177",
    "addr:street":"Sw 139Th Pl",
    "iso:country":"US",
    "sg:address":"18319 SW 139th Pl",
    "sg:city":"Miami",
    "sg:classifiers":[
        {
            "category":"Food & Beverages",
            "subcategory":"Groceries & Convenience Stores",
            "type":"Retail Goods"
        }
    ],
    "sg:phone":"+1 305 238 1956",
    "sg:postcode":"33177",
    "sg:province":"FL",
    "wof:name":"Yot Chek Wong W Pei Ling",
    "wof:placetype":"venue"
},
  "geometry": {"coordinates":[-80.41839899999999,25.597664],"type":"Point"}
}