{
  "type": "Feature",
  "properties": {
    "iso:country":"US",
    "sg:address":"7880 126th Ave N",
    "sg:city":"Largo",
    "sg:classifiers":[
        {
            "category":"Building & Trades",
            "subcategory":"Landscaping Services",
            "type":"Services"
        }
    ],
    "sg:phone":"+1 727 536 0545",
    "sg:postcode":"33773",
    "sg:province":"FL",
    "wof:name":"Bloomers Flowering Plant Nurs",
    "wof:placetype":"venue"
},
  "geometry": {"coordinates":[-82.746216,27.886896],"type":"Point"}
}