{
  "type": "Feature",
  "properties": {
    "addr:full":"3333 20th St Vero Beach FL 32960",
    "addr:housenumber":"3333",
    "addr:postcode":"32960",
    "addr:street":"20Th St",
    "iso:country":"US",
    "sg:address":"3333 20th St",
    "sg:city":"Vero Beach",
    "sg:classifiers":[
        {
            "category":"Professional",
            "subcategory":"Lawyer & Legal Services",
            "type":"Services"
        }
    ],
    "sg:phone":"+1 772 562 8111",
    "sg:postcode":"32960",
    "sg:province":"FL",
    "wof:name":"Paul R Berg PA",
    "wof:placetype":"venue"
},
  "geometry": {"coordinates":[-80.41970999999999,27.638251],"type":"Point"}
}