{
  "type": "Feature",
  "properties": {
    "iso:country":"US",
    "sg:address":"3050 S Jog Rd",
    "sg:city":"Greenacres",
    "sg:classifiers":[
        {
            "category":"Personal",
            "subcategory":"Beauty Salon",
            "type":"Services"
        },
        {
            "category":"Personal",
            "subcategory":"Tattoo Parlor",
            "type":"Services"
        },
        {
            "category":"Personal",
            "subcategory":"Barber",
            "type":"Services"
        },
        {
            "category":"Personal",
            "subcategory":"Hair Removal",
            "type":"Services"
        }
    ],
    "sg:phone":"+1 561 642 7200",
    "sg:postcode":"33467",
    "sg:province":"FL",
    "sg:tags":[
        "braiding",
        "weaving",
        "stylist"
    ],
    "sg:website":"http://www.facebook.com/nyfbarbertattooshop",
    "wof:name":"New York's Finest Tattoo & Barber Shop",
    "wof:placetype":"venue"
},
  "geometry": {"coordinates":[-80.145985,26.630903],"type":"Point"}
}