{
  "type": "Feature",
  "properties": {
    "iso:country":"US",
    "sg:address":"743 S Deerfield Ave",
    "sg:city":"Deerfield Beach",
    "sg:classifiers":[
        {
            "category":"Retail",
            "subcategory":"Auto Repair",
            "type":"Services"
        }
    ],
    "sg:phone":"+1 954 428 8900",
    "sg:postcode":"33441",
    "sg:province":"FL",
    "sg:tags":[
        "repairing",
        "automobile"
    ],
    "wof:name":"T & B Auto Svc",
    "wof:placetype":"venue"
},
  "geometry": {"coordinates":[-80.103662,26.307113],"type":"Point"}
}