{
  "type": "Feature",
  "properties": {
    "iso:country":"US",
    "sg:address":"2785 Malabar Rd",
    "sg:city":"Malabar",
    "sg:classifiers":[
        {
            "category":"Manufacturing",
            "subcategory":"Printing",
            "type":"Manufacturing & Wholesale Goods"
        }
    ],
    "sg:phone":"+1 321 984 9957",
    "sg:postcode":"32950",
    "sg:province":"FL",
    "sg:tags":[
        "lithographic",
        "commercial"
    ],
    "wof:name":"Stamp Out Stress",
    "wof:placetype":"venue"
},
  "geometry": {"coordinates":[-80.564353,28.004105],"type":"Point"}
}