{
  "type": "Feature",
  "properties": {
    "iso:country":"US",
    "sg:address":"1313 S Killian Dr",
    "sg:city":"Lake Park",
    "sg:classifiers":[
        {
            "category":"Wholesale",
            "subcategory":"Construction Materials",
            "type":"Manufacturing & Wholesale Goods"
        },
        {
            "category":"Building & Trades",
            "subcategory":"Construction",
            "type":"Services"
        }
    ],
    "sg:phone":"+1 561 841 0800",
    "sg:postcode":"33403",
    "sg:province":"FL",
    "sg:tags":[
        "fencing",
        "fence",
        "contractor"
    ],
    "sg:website":"www.poolbarrier.com",
    "wof:name":"Pool Barrier Inc",
    "wof:placetype":"venue"
},
  "geometry": {"coordinates":[-80.08195600000001,26.80514],"type":"Point"}
}