{
  "type": "Feature",
  "properties": {
    "iso:country":"US",
    "sg:address":"155 E Haines Blvd",
    "sg:city":"Lake Alfred",
    "sg:classifiers":[
        {
            "category":"Shopping",
            "subcategory":"Used Merchandise",
            "type":"Retail Goods"
        }
    ],
    "sg:phone":"+1 863 956 2488",
    "sg:postcode":"33850",
    "sg:province":"FL",
    "wof:name":"Lake Alfred Antique Mall",
    "wof:placetype":"venue"
},
  "geometry": {"coordinates":[-81.729084,28.091779],"type":"Point"}
}