{
  "type": "Feature",
  "properties": {
    "addr:full":"1760 Magnolia Harbor Dr Navarre FL 32566",
    "addr:housenumber":"1760",
    "addr:postcode":"32566",
    "addr:street":"Magnolia Harbor Dr",
    "iso:country":"US",
    "sg:address":"1760 Magnolia Harbor Dr",
    "sg:city":"Navarre",
    "sg:classifiers":[
        {
            "category":"Shopping",
            "subcategory":"Bicycles & Sporting Goods",
            "type":"Retail Goods"
        }
    ],
    "sg:phone":"+1 850 515 0224",
    "sg:postcode":"32566",
    "sg:province":"FL",
    "sg:tags":[
        "equipment",
        "playground"
    ],
    "wof:name":"Contract Connection",
    "wof:placetype":"venue"
},
  "geometry": {"coordinates":[-86.914435,30.399204],"type":"Point"}
}