{
  "type": "Feature",
  "properties": {
    "addr:full":"120 Tahiti St Naples FL 34113",
    "addr:housenumber":"120",
    "addr:postcode":"34113",
    "addr:street":"Tahiti St",
    "iso:country":"US",
    "sg:address":"120 Tahiti St",
    "sg:city":"Naples",
    "sg:classifiers":[
        {
            "category":"Building & Trades",
            "subcategory":"Construction",
            "type":"Services"
        }
    ],
    "sg:phone":"+1 239 269 4896",
    "sg:postcode":"34113",
    "sg:province":"FL",
    "sg:tags":[
        "hanging",
        "contractor"
    ],
    "wof:name":"Becky Bowman Painter",
    "wof:placetype":"venue"
},
  "geometry": {"coordinates":[-81.72993099999999,25.979801],"type":"Point"}
}