{
  "type": "Feature",
  "properties": {
    "iso:country":"US",
    "sg:address":"928 Spring Lake Sq",
    "sg:city":"Winter Haven",
    "sg:classifiers":[
        {
            "category":"Shopping",
            "subcategory":"Hobbies, Toys, & Games",
            "type":"Retail Goods"
        }
    ],
    "sg:phone":"+1 863 668 8559",
    "sg:postcode":"33881",
    "sg:province":"FL",
    "sg:tags":[
        "model",
        "supply"
    ],
    "wof:name":"Extreme HOBBY Zone",
    "wof:placetype":"venue"
},
  "geometry": {"coordinates":[-81.735653,28.043067],"type":"Point"}
}