{
  "type": "Feature",
  "properties": {
    "addr:full":"2437 SE 17th St Ocala FL 34471",
    "addr:housenumber":"2437",
    "addr:postcode":"34471",
    "addr:street":"Se 17Th St",
    "iso:country":"US",
    "sg:address":"2437 SE 17th St",
    "sg:city":"Ocala",
    "sg:classifiers":[
        {
            "category":"Professional",
            "subcategory":"Management & Consulting",
            "type":"Services"
        },
        {
            "category":"Banks & Credit Unions",
            "subcategory":"Investment Brokerage",
            "type":"Services"
        },
        {
            "category":"Banks & Credit Unions",
            "subcategory":"Financial Services",
            "type":"Services"
        }
    ],
    "sg:phone":"+1 352 671 5086",
    "sg:postcode":"34471",
    "sg:province":"FL",
    "sg:tags":[
        "planning",
        "advisory",
        "financing",
        "planner",
        "consultant"
    ],
    "wof:name":"Uhler And Vertich Financial Pl",
    "wof:placetype":"venue"
},
  "geometry": {"coordinates":[-82.16652499999999,29.171204],"type":"Point"}
}