{
  "type": "Feature",
  "properties": {
    "iso:country":"US",
    "sg:address":"6049 26th St W",
    "sg:city":"Bradenton",
    "sg:classifiers":[
        {
            "category":"Social Services",
            "subcategory":"Adult Care",
            "type":"Services"
        }
    ],
    "sg:phone":"+1 941 758 8343",
    "sg:postcode":"34207",
    "sg:province":"FL",
    "sg:tags":[
        "organization",
        "senior",
        "citizen"
    ],
    "wof:name":"Senior Friends",
    "wof:placetype":"venue"
},
  "geometry": {"coordinates":[-82.587633,27.435112],"type":"Point"}
}