{
  "type": "Feature",
  "properties": {
    "iso:country":"US",
    "sg:address":"7532 N Armenia Ave",
    "sg:city":"Tampa",
    "sg:classifiers":[
        {
            "category":"Education",
            "subcategory":"Dance Studio",
            "type":"Public Place"
        }
    ],
    "sg:phone":"+1 813 935 7458",
    "sg:postcode":"33604",
    "sg:province":"FL",
    "sg:tags":[
        "instruction",
        "dancing"
    ],
    "wof:name":"Swing City Dance Studio",
    "wof:placetype":"venue"
},
  "geometry": {"coordinates":[-82.48477099999999,28.017322],"type":"Point"}
}