{
  "type": "Feature",
  "properties": {
    "iso:country":"US",
    "sg:address":"618 Michael Ave",
    "sg:city":"Fort Myers",
    "sg:classifiers":[
        {
            "category":"Building & Trades",
            "subcategory":"Plumbing",
            "type":"Services"
        }
    ],
    "sg:phone":"+1 239 332 0339",
    "sg:postcode":"33936",
    "sg:province":"FL",
    "sg:tags":[
        "plumbing",
        "contractor"
    ],
    "wof:name":"Moon Plumbing",
    "wof:placetype":"venue"
},
  "geometry": {"coordinates":[-81.60213299999999,26.624532],"type":"Point"}
}