{
  "type": "Feature",
  "properties": {
    "addr:full":"430 S Yonge St Ormond Beach FL 32174",
    "addr:housenumber":"430",
    "addr:postcode":"32174",
    "addr:street":"S Yonge St",
    "iso:country":"US",
    "sg:address":"430 S Yonge St",
    "sg:city":"Ormond Beach",
    "sg:classifiers":[
        {
            "category":"Home & Garden",
            "subcategory":"Furniture",
            "type":"Retail Goods"
        }
    ],
    "sg:phone":"+1 386 673 9619",
    "sg:postcode":"32174",
    "sg:province":"FL",
    "wof:name":"Hudson's Broyhill Furnitre Inc",
    "wof:placetype":"venue"
},
  "geometry": {"coordinates":[-81.05803400000001,29.275112],"type":"Point"}
}