{
  "type": "Feature",
  "properties": {
    "iso:country":"US",
    "sg:address":"4138 Banbury Cir",
    "sg:city":"Parrish",
    "sg:classifiers":[
        {
            "category":"Personal",
            "type":"Services"
        }
    ],
    "sg:phone":"+1 941 776 9196",
    "sg:postcode":"34219",
    "sg:province":"FL",
    "sg:tags":[
        "control",
        "weight"
    ],
    "wof:name":"Herbalife Distributor",
    "wof:placetype":"venue"
},
  "geometry": {"coordinates":[-82.43014100000001,27.548924],"type":"Point"}
}