{
  "type": "Feature",
  "properties": {
    "iso:country":"US",
    "sg:address":"8332 Fresh Creek",
    "sg:city":"West Palm Beach",
    "sg:classifiers":[
        {
            "category":"Home & Garden",
            "subcategory":"Carpets & Floor Coverings",
            "type":"Retail Goods"
        }
    ],
    "sg:phone":"+1 561 791 1199",
    "sg:postcode":"33411",
    "sg:province":"FL",
    "sg:tags":[
        "dealer",
        "rug"
    ],
    "wof:name":"Nationwide Carpet Upholstery",
    "wof:placetype":"venue"
},
  "geometry": {"coordinates":[-80.173956,26.712892],"type":"Point"}
}