{
  "type": "Feature",
  "properties": {
    "iso:country":"US",
    "sg:address":"304 Hunters Point Ct",
    "sg:city":"Longwood",
    "sg:classifiers":[
        {
            "category":"Real Estate",
            "subcategory":"Surveying",
            "type":"Services"
        }
    ],
    "sg:phone":"+1 407 862 2520",
    "sg:postcode":"32779",
    "sg:province":"FL",
    "sg:tags":[
        "surveyor",
        "land",
        "engineer"
    ],
    "sg:website":"http://www.designsurveys.net",
    "wof:name":"Cliff Alberti PLS - Design Surveys P.A.",
    "wof:placetype":"venue"
},
  "geometry": {"coordinates":[-81.44529900000001,28.697789],"type":"Point"}
}