{
  "type": "Feature",
  "properties": {
    "iso:country":"US",
    "sg:address":"666 16th Pl",
    "sg:city":"Vero Beach",
    "sg:classifiers":[
        {
            "category":"Real Estate",
            "subcategory":"Real Estate Operator",
            "type":"Services"
        }
    ],
    "sg:phone":"+1 772 562 2810",
    "sg:postcode":"32960",
    "sg:province":"FL",
    "sg:tags":[
        "property",
        "lessor"
    ],
    "wof:name":"Elmer Clinker Farm",
    "wof:placetype":"venue"
},
  "geometry": {"coordinates":[-80.385813,27.631624],"type":"Point"}
}