{
  "type": "Feature",
  "properties": {
    "iso:country":"US",
    "sg:address":"3235 Apollo Trl",
    "sg:city":"Tallahassee",
    "sg:classifiers":[
        {
            "category":"Building & Trades",
            "subcategory":"Construction",
            "type":"Services"
        }
    ],
    "sg:phone":"+1 850 668 9919",
    "sg:postcode":"32309",
    "sg:province":"FL",
    "sg:tags":[
        "enclosure",
        "pool",
        "swimming"
    ],
    "wof:name":"Baby Guard Pool Fences",
    "wof:placetype":"venue"
},
  "geometry": {"coordinates":[-84.19538,30.541197],"type":"Point"}
}