{
  "type": "Feature",
  "properties": {
    "addr:full":"205 Co Rd 555 Bartow FL 33830",
    "addr:housenumber":"205;555",
    "addr:postcode":"33830",
    "addr:street":"Co Rd",
    "iso:country":"US",
    "sg:address":"205 Co Rd 555",
    "sg:city":"Bartow",
    "sg:classifiers":[
        {
            "category":"Wholesale",
            "subcategory":"Electrical",
            "type":"Manufacturing & Wholesale Goods"
        }
    ],
    "sg:phone":"+1 863 533 3165",
    "sg:postcode":"33830",
    "sg:province":"FL",
    "sg:tags":[
        "electronic"
    ],
    "wof:name":"Chemco Electric Supply Inc",
    "wof:placetype":"venue"
},
  "geometry": {"coordinates":[-81.88314800000001,27.833066],"type":"Point"}
}