{
  "type": "Feature",
  "properties": {
    "addr:full":"6496 Lake Worth Rd Lake Worth FL 33463",
    "addr:housenumber":"6496",
    "addr:postcode":"33463",
    "addr:street":"Lake Worth Rd",
    "iso:country":"US",
    "sg:address":"6496 Lake Worth Rd",
    "sg:city":"Lake Worth",
    "sg:classifiers":[
        {
            "category":"Restaurant",
            "type":"Food & Drink"
        }
    ],
    "sg:menulink":"http://www.allmenus.com/fl/lake-worth/11430-dennys/menu/",
    "sg:phone":"+1 561 968 1171",
    "sg:postcode":"33463",
    "sg:province":"FL",
    "sg:tags":[
        "american",
        "diner"
    ],
    "wof:name":"Denny's",
    "wof:placetype":"venue"
},
  "geometry": {"coordinates":[-80.146483,26.618862],"type":"Point"}
}