{
  "type": "Feature",
  "properties": {
    "addr:full":"80 SW 5th Ct Pompano Beach FL 33060",
    "addr:housenumber":"80",
    "addr:postcode":"33060",
    "addr:street":"Sw 5Th Ct",
    "iso:country":"US",
    "sg:address":"80 SW 5th Ct",
    "sg:city":"Pompano Beach",
    "sg:classifiers":[
        {
            "category":"Retail",
            "subcategory":"Auto Repair",
            "type":"Services"
        }
    ],
    "sg:phone":"+1 954 946 0241",
    "sg:postcode":"33060",
    "sg:province":"FL",
    "sg:tags":[
        "body"
    ],
    "wof:name":"Body Spot Inc",
    "wof:placetype":"venue"
},
  "geometry": {"coordinates":[-80.12636999999999,26.223379],"type":"Point"}
}