{
  "type": "Feature",
  "properties": {
    "iso:country":"US",
    "sg:address":"174 Semoran Commerce Pl",
    "sg:city":"Apopka",
    "sg:classifiers":[
        {
            "category":"Wholesale",
            "subcategory":"Medical Equipment & Supplies",
            "type":"Manufacturing & Wholesale Goods"
        }
    ],
    "sg:phone":"+1 407 814 8202",
    "sg:postcode":"32703",
    "sg:province":"FL",
    "sg:tags":[
        "physician",
        "surgeon"
    ],
    "wof:name":"Mid Florida Medical",
    "wof:placetype":"venue"
},
  "geometry": {"coordinates":[-81.479265,28.674212],"type":"Point"}
}