{
  "type": "Feature",
  "properties": {
    "iso:country":"US",
    "sg:address":"11119 Corlett Rd",
    "sg:city":"Riverview",
    "sg:classifiers":[
        {
            "category":"Wholesale",
            "subcategory":"Electrical",
            "type":"Manufacturing & Wholesale Goods"
        }
    ],
    "sg:phone":"+1 813 671 3800",
    "sg:postcode":"33578",
    "sg:province":"FL",
    "sg:tags":[
        "equipment",
        "electronic"
    ],
    "sg:website":"www.audioinnovators.com",
    "wof:name":"Audio Innovators Inc",
    "wof:placetype":"venue"
},
  "geometry": {"coordinates":[-82.31731600000001,27.868046],"type":"Point"}
}