{
  "type": "Feature",
  "properties": {
    "addr:full":"190 8th St Miami Beach FL 33139",
    "addr:housenumber":"190",
    "addr:postcode":"33139",
    "addr:street":"8Th St",
    "iso:country":"US",
    "sg:address":"190 8th St",
    "sg:city":"Miami Beach",
    "sg:classifiers":[
        {
            "category":"Shopping",
            "subcategory":"Clothing, Apparel, & Fashions",
            "type":"Retail Goods"
        },
        {
            "category":"Shopping",
            "subcategory":"Shoes",
            "type":"Retail Goods"
        }
    ],
    "sg:phone":"+1 305 673 5151",
    "sg:postcode":"33139",
    "sg:province":"FL",
    "sg:tags":[
        "store",
        "sportswear"
    ],
    "sg:website":"www.kennethcole.com",
    "wof:name":"Kenneth Cole",
    "wof:placetype":"venue"
},
  "geometry": {"coordinates":[-80.13220200000001,25.778],"type":"Point"}
}