{
  "type": "Feature",
  "properties": {
    "addr:full":"5412 Provost Dr Holiday FL 34690",
    "addr:housenumber":"5412",
    "addr:postcode":"34690",
    "addr:street":"Provost Dr",
    "iso:country":"US",
    "sg:address":"5412 Provost Dr",
    "sg:city":"Holiday",
    "sg:classifiers":[
        {
            "category":"Retail",
            "subcategory":"Auto Repair",
            "type":"Services"
        }
    ],
    "sg:phone":"+1 727 945 1485",
    "sg:postcode":"34690",
    "sg:province":"FL",
    "sg:tags":[
        "repairing",
        "automobile",
        "general"
    ],
    "wof:name":"Bruce Skinner Auto",
    "wof:placetype":"venue"
},
  "geometry": {"coordinates":[-82.723349,28.198964],"type":"Point"}
}