{
  "type": "Feature",
  "properties": {
    "iso:country":"US",
    "sg:address":"8594 Palm Pkwy",
    "sg:city":"Orlando",
    "sg:classifiers":[
        {
            "category":"Restaurant",
            "type":"Food & Drink"
        }
    ],
    "sg:phone":"+1 407 238 2411",
    "sg:postcode":"32836",
    "sg:province":"FL",
    "wof:name":"Angus House Of Beef",
    "wof:placetype":"venue"
},
  "geometry": {"coordinates":[-81.50252399999999,28.385584],"type":"Point"}
}