{
  "type": "Feature",
  "properties": {
    "addr:full":"1811 Richmond Rd Lakeland FL 33803",
    "addr:housenumber":"1811",
    "addr:postcode":"33803",
    "addr:street":"Richmond Rd",
    "iso:country":"US",
    "sg:address":"1811 Richmond Rd",
    "sg:city":"Lakeland",
    "sg:classifiers":[
        {
            "category":"Social Services",
            "subcategory":"Child Care",
            "type":"Services"
        }
    ],
    "sg:phone":"+1 863 413 9890",
    "sg:postcode":"33803",
    "sg:province":"FL",
    "sg:tags":[
        "center"
    ],
    "wof:name":"Polk County School Readiness",
    "wof:placetype":"venue"
},
  "geometry": {"coordinates":[-81.923813,28.019581],"type":"Point"}
}