{
  "type": "Feature",
  "properties": {
    "iso:country":"US",
    "sg:address":"4329 Tamiami Trl N",
    "sg:city":"Naples",
    "sg:classifiers":[
        {
            "category":"Restaurant",
            "type":"Food & Drink"
        }
    ],
    "sg:phone":"+1 239 649 0909",
    "sg:postcode":"34103",
    "sg:province":"FL",
    "sg:tags":[
        "asian",
        "pan",
        "japanese"
    ],
    "wof:name":"Ichiban Japanese Restaurant",
    "wof:placetype":"venue"
},
  "geometry": {"coordinates":[-81.800361,26.201327],"type":"Point"}
}