{
  "type": "Feature",
  "properties": {
    "addr:full":"1207 S Park Ave Sanford FL 32771",
    "addr:housenumber":"1207",
    "addr:postcode":"32771",
    "addr:street":"S Park Ave",
    "iso:country":"US",
    "sg:address":"1207 S Park Ave",
    "sg:city":"Sanford",
    "sg:classifiers":[
        {
            "category":"Shopping",
            "type":"Retail Goods"
        }
    ],
    "sg:phone":"+1 407 688 0072",
    "sg:postcode":"32771",
    "sg:province":"FL",
    "sg:tags":[
        "cosmetic",
        "perfume"
    ],
    "wof:name":"It's U Beauty Supply",
    "wof:placetype":"venue"
},
  "geometry": {"coordinates":[-81.267854,28.80085],"type":"Point"}
}