{
  "type": "Feature",
  "properties": {
    "addr:full":"23422 Burlingame Ave Port Charlotte FL 33980",
    "addr:housenumber":"23422",
    "addr:postcode":"33980",
    "addr:street":"Burlingame Ave",
    "iso:country":"US",
    "sg:address":"23422 Burlingame Ave",
    "sg:city":"Port Charlotte",
    "sg:classifiers":[
        {
            "category":"Food & Beverages",
            "subcategory":"Specialty",
            "type":"Retail Goods"
        }
    ],
    "sg:phone":"+1 941 764 7587",
    "sg:postcode":"33980",
    "sg:province":"FL",
    "wof:name":"Paula Allison Nutrition",
    "wof:placetype":"venue"
},
  "geometry": {"coordinates":[-82.06288600000001,26.996835],"type":"Point"}
}