{
  "type": "Feature",
  "properties": {
    "iso:country":"US",
    "sg:address":"2 Goodlette Rd S",
    "sg:city":"Naples",
    "sg:classifiers":[
        {
            "category":"Retail",
            "subcategory":"Self-service Laundry",
            "type":"Services"
        }
    ],
    "sg:phone":"+1 239 263 3014",
    "sg:postcode":"34102",
    "sg:province":"FL",
    "sg:tags":[
        "garment",
        "coin",
        "agent"
    ],
    "wof:name":"Victoria Square Laundry",
    "wof:placetype":"venue"
},
  "geometry": {"coordinates":[-81.79084899999999,26.147775],"type":"Point"}
}