{
  "type": "Feature",
  "properties": {
    "addr:full":"26250 SW 183rd Ct Homestead FL 33031",
    "addr:housenumber":"26250",
    "addr:postcode":"33031",
    "addr:street":"Sw 183Rd Ct",
    "iso:country":"US",
    "sg:address":"26250 SW 183rd Ct",
    "sg:city":"Homestead",
    "sg:classifiers":[
        {
            "category":"Professional",
            "subcategory":"Detective & Security Services",
            "type":"Services"
        }
    ],
    "sg:phone":"+1 305 271 0068",
    "sg:postcode":"33031",
    "sg:province":"FL",
    "sg:tags":[
        "car"
    ],
    "wof:name":"Special Force K-9 Guard Dog",
    "wof:placetype":"venue"
},
  "geometry": {"coordinates":[-80.489131,25.521509],"type":"Point"}
}