{
  "type": "Feature",
  "properties": {
    "iso:country":"US",
    "sg:address":"5777 N University Dr",
    "sg:city":"Tamarac",
    "sg:classifiers":[
        {
            "category":"Shopping",
            "subcategory":"Discount & Variety Stores",
            "type":"Retail Goods"
        }
    ],
    "sg:phone":"+1 954 724 9986",
    "sg:postcode":"33321",
    "sg:province":"FL",
    "wof:name":"Dollar & Sense",
    "wof:placetype":"venue"
},
  "geometry": {"coordinates":[-80.25211400000001,26.1961],"type":"Point"}
}