{
  "type": "Feature",
  "properties": {
    "iso:country":"US",
    "sg:address":"2315 W Okeechobee Rd",
    "sg:city":"Hialeah",
    "sg:classifiers":[
        {
            "category":"Professional",
            "subcategory":"Engineering",
            "type":"Services"
        },
        {
            "category":"Wholesale",
            "subcategory":"Construction Materials",
            "type":"Manufacturing & Wholesale Goods"
        }
    ],
    "sg:phone":"+1 305 889 5336",
    "sg:postcode":"33010",
    "sg:province":"FL",
    "sg:tags":[
        "passenger-commercial",
        "industrial",
        "elevators-freight",
        "elevator"
    ],
    "wof:name":"Orlando Mendez Elevator",
    "wof:placetype":"venue"
},
  "geometry": {"coordinates":[-80.306887,25.842417],"type":"Point"}
}