{
  "type": "Feature",
  "properties": {
    "iso:country":"US",
    "sg:address":"21 S Clyde Ave",
    "sg:city":"Kissimmee",
    "sg:classifiers":[
        {
            "category":"Social Services",
            "type":"Services"
        }
    ],
    "sg:phone":"+1 407 870 8616",
    "sg:postcode":"34741",
    "sg:province":"FL",
    "sg:tags":[
        "counseling"
    ],
    "wof:name":"Shelba C Sinsel",
    "wof:placetype":"venue"
},
  "geometry": {"coordinates":[-81.413161,28.291059],"type":"Point"}
}