{
  "type": "Feature",
  "properties": {
    "addr:full":"8120 SW 183rd St Miami FL 33157",
    "addr:housenumber":"8120",
    "addr:postcode":"33157",
    "addr:street":"Sw 183Rd St",
    "iso:country":"US",
    "sg:address":"8120 SW 183rd St",
    "sg:city":"Miami",
    "sg:classifiers":[
        {
            "category":"Utilities",
            "subcategory":"Mobile Phone",
            "type":"Services"
        }
    ],
    "sg:phone":"+1 305 253 9681",
    "sg:postcode":"33157",
    "sg:province":"FL",
    "sg:tags":[
        "communication",
        "radiotelephone"
    ],
    "wof:name":"C & J Wireless",
    "wof:placetype":"venue"
},
  "geometry": {"coordinates":[-80.323145,25.600424],"type":"Point"}
}