{
  "type": "Feature",
  "properties": {
    "iso:country":"US",
    "sg:address":"5544 S Flamingo Rd",
    "sg:city":"Cooper City",
    "sg:classifiers":[
        {
            "category":"Restaurant",
            "type":"Food & Drink"
        }
    ],
    "sg:phone":"+1 954 434 2220",
    "sg:postcode":"33330",
    "sg:province":"FL",
    "wof:name":"Beverly Hills Cafe",
    "wof:placetype":"venue"
},
  "geometry": {"coordinates":[-80.31313,26.048964],"type":"Point"}
}