{
  "type": "Feature",
  "properties": {
    "iso:country":"US",
    "sg:address":"1376 Bennett Dr",
    "sg:city":"Longwood",
    "sg:classifiers":[
        {
            "category":"Home & Garden",
            "subcategory":"Furniture",
            "type":"Retail Goods"
        }
    ],
    "sg:phone":"+1 407 834 9322",
    "sg:postcode":"32750",
    "sg:province":"FL",
    "wof:name":"Wing Fat Co",
    "wof:placetype":"venue"
},
  "geometry": {"coordinates":[-81.353855,28.690428],"type":"Point"}
}