{
  "type": "Feature",
  "properties": {
    "iso:country":"US",
    "sg:address":"1739 NW Boca Raton Blvd",
    "sg:city":"Boca Raton",
    "sg:classifiers":[
        {
            "category":"Shopping",
            "subcategory":"Clothing, Apparel, & Fashions",
            "type":"Retail Goods"
        }
    ],
    "sg:phone":"+1 561 395 5001",
    "sg:postcode":"33432",
    "sg:province":"FL",
    "sg:tags":[
        "lingerie"
    ],
    "wof:name":"Lingerie Gifts",
    "wof:placetype":"venue"
},
  "geometry": {"coordinates":[-80.090317,26.36578],"type":"Point"}
}