{
  "type": "Feature",
  "properties": {
    "addr:full":"420 Bayview Ave Osprey FL 34229",
    "addr:housenumber":"420",
    "addr:postcode":"34229",
    "addr:street":"Bayview Ave Osprey",
    "iso:country":"US",
    "sg:address":"420 Bayview Ave",
    "sg:city":"Osprey",
    "sg:classifiers":[
        {
            "category":"Manufacturing",
            "subcategory":"Buildings",
            "type":"Manufacturing & Wholesale Goods"
        },
        {
            "category":"Building & Trades",
            "subcategory":"Construction",
            "type":"Services"
        }
    ],
    "sg:phone":"+1 941 966 3112",
    "sg:postcode":"34229",
    "sg:province":"FL",
    "sg:tags":[
        "home",
        "builder",
        "contractor"
    ],
    "wof:name":"Cm Builders Inc",
    "wof:placetype":"venue"
},
  "geometry": {"coordinates":[-82.488815,27.18985],"type":"Point"}
}