{
  "type": "Feature",
  "properties": {
    "addr:full":"8014 Front Beach Rd Panama City Bch FL 32407",
    "addr:housenumber":"8014",
    "addr:postcode":"32407",
    "addr:street":"Front Beach Rd",
    "iso:country":"US",
    "sg:address":"8014 Front Beach Rd",
    "sg:city":"Panama City Bch",
    "sg:classifiers":[
        {
            "category":"Professional",
            "subcategory":"Business Services",
            "type":"Services"
        }
    ],
    "sg:phone":"+1 850 235 2489",
    "sg:postcode":"32407",
    "sg:province":"FL",
    "sg:tags":[
        "auctioneer"
    ],
    "wof:name":"Jerry Slavens Auctioneer",
    "wof:placetype":"venue"
},
  "geometry": {"coordinates":[-85.774857,30.185379],"type":"Point"}
}