{
  "type": "Feature",
  "properties": {
    "addr:full":"3848 Emerson St Jacksonville FL 32207",
    "addr:housenumber":"3848",
    "addr:postcode":"32207",
    "addr:street":"Emerson St",
    "iso:country":"US",
    "sg:address":"3848 Emerson St",
    "sg:city":"Jacksonville",
    "sg:classifiers":[
        {
            "category":"Personal",
            "subcategory":"Beauty Salon",
            "type":"Services"
        }
    ],
    "sg:phone":"+1 904 399 8601",
    "sg:postcode":"32207",
    "sg:province":"FL",
    "sg:tags":[
        "shop"
    ],
    "wof:name":"Can Do Creations & Hair Salon",
    "wof:placetype":"venue"
},
  "geometry": {"coordinates":[-81.624903,30.290901],"type":"Point"}
}