{
  "type": "Feature",
  "properties": {
    "iso:country":"US",
    "sg:address":"7200 S Orange Ave Ste 101",
    "sg:city":"Orlando",
    "sg:classifiers":[
        {
            "category":"Wholesale",
            "subcategory":"Medical Equipment & Supplies",
            "type":"Manufacturing & Wholesale Goods"
        }
    ],
    "sg:phone":"+1 407 850 0398",
    "sg:postcode":"32809",
    "sg:province":"FL",
    "sg:tags":[
        "sling"
    ],
    "wof:name":"Adler Sling Certex",
    "wof:placetype":"venue"
},
  "geometry": {"coordinates":[-81.366536,28.46147],"type":"Point"}
}