{
  "type": "Feature",
  "properties": {
    "addr:full":"6713 Manatee Ave W Bradenton FL 34209",
    "addr:housenumber":"6713",
    "addr:postcode":"34209",
    "addr:street":"Manatee Ave W",
    "iso:country":"US",
    "sg:address":"6713 Manatee Ave W",
    "sg:city":"Bradenton",
    "sg:classifiers":[
        {
            "category":"Professional",
            "subcategory":"Business Services",
            "type":"Services"
        }
    ],
    "sg:phone":"+1 941 792 4335",
    "sg:postcode":"34209",
    "sg:province":"FL",
    "sg:tags":[
        "interior",
        "consultant",
        "design",
        "decorator"
    ],
    "wof:name":"Decor More",
    "wof:placetype":"venue"
},
  "geometry": {"coordinates":[-82.629306,27.495891],"type":"Point"}
}