{
  "type": "Feature",
  "properties": {
    "addr:full":"213 E Sheridan St Dania FL 33004",
    "addr:housenumber":"213",
    "addr:postcode":"33004",
    "addr:street":"E Sheridan St",
    "iso:country":"US",
    "sg:address":"213 E Sheridan St",
    "sg:city":"Dania",
    "sg:classifiers":[
        {
            "category":"Banks & Credit Unions",
            "subcategory":"Bank",
            "type":"Services"
        }
    ],
    "sg:phone":"+1 954 927 9744",
    "sg:postcode":"33004",
    "sg:province":"FL",
    "sg:tags":[
        "loan",
        "real estate"
    ],
    "wof:name":"First Capital Mortgage",
    "wof:placetype":"venue"
},
  "geometry": {"coordinates":[-80.139262,26.033805],"type":"Point"}
}