{
  "type": "Feature",
  "properties": {
    "iso:country":"US",
    "sg:address":"2490 SW 85th Ave",
    "sg:city":"Miramar",
    "sg:classifiers":[
        {
            "category":"Personal",
            "subcategory":"Beauty Salon",
            "type":"Services"
        }
    ],
    "sg:phone":"+1 954 435 9604",
    "sg:postcode":"33025",
    "sg:province":"FL",
    "wof:name":"Belle Parlor",
    "wof:placetype":"venue"
},
  "geometry": {"coordinates":[-80.256165,25.988535],"type":"Point"}
}