{
  "type": "Feature",
  "properties": {
    "iso:country":"US",
    "sg:address":"1783 W Main St",
    "sg:city":"Inverness",
    "sg:classifiers":[
        {
            "category":"Shopping",
            "type":"Retail Goods"
        },
        {
            "category":"Home & Garden",
            "subcategory":"Furniture",
            "type":"Retail Goods"
        }
    ],
    "sg:phone":"+1 352 726 2766",
    "sg:postcode":"34450",
    "sg:province":"FL",
    "sg:tags":[
        "equipment",
        "pool",
        "swimming"
    ],
    "wof:name":"Pinch-A-Penny Pool & Patio Spa",
    "wof:placetype":"venue"
},
  "geometry": {"coordinates":[-82.35156600000001,28.835906],"type":"Point"}
}