{
  "type": "Feature",
  "properties": {
    "addr:full":"701 S 50th St Tampa FL 33619",
    "addr:housenumber":"701",
    "addr:postcode":"33619",
    "addr:street":"S 50Th St",
    "iso:country":"US",
    "sg:address":"701 S 50th St",
    "sg:city":"Tampa",
    "sg:classifiers":[
        {
            "category":"Retail",
            "subcategory":"Auto Repair",
            "type":"Services"
        }
    ],
    "sg:phone":"+1 813 247 4365",
    "sg:postcode":"33619",
    "sg:province":"FL",
    "sg:tags":[
        "automotive"
    ],
    "wof:name":"Hutcherson Auto Electric",
    "wof:placetype":"venue"
},
  "geometry": {"coordinates":[-82.40191299999999,27.941167],"type":"Point"}
}