{
  "type": "Feature",
  "properties": {
    "addr:full":"400 W Cocoa Beach Cswy Cocoa Beach FL 32931",
    "addr:housenumber":"400",
    "addr:postcode":"32931",
    "addr:street":"W Cocoa;Cswy",
    "iso:country":"US",
    "sg:address":"400 W Cocoa Beach Cswy",
    "sg:city":"Cocoa Beach",
    "sg:classifiers":[
        {
            "category":"Recreation",
            "subcategory":"Marina",
            "type":"Entertainment"
        }
    ],
    "sg:phone":"+1 321 783 8349",
    "sg:postcode":"32931",
    "sg:province":"FL",
    "wof:name":"Orange Cove Marina",
    "wof:placetype":"venue"
},
  "geometry": {"coordinates":[-80.613067,28.357773],"type":"Point"}
}