{
  "type": "Feature",
  "properties": {
    "iso:country":"US",
    "sg:address":"653 La Salle Dr",
    "sg:city":"Altamonte Springs",
    "sg:classifiers":[
        {
            "category":"Building & Trades",
            "subcategory":"Construction",
            "type":"Services"
        }
    ],
    "sg:phone":"+1 407 924 9956",
    "sg:postcode":"32714",
    "sg:province":"FL",
    "sg:tags":[
        "painter",
        "contractor"
    ],
    "wof:name":"Anders Danielson Enterprises, LLC",
    "wof:placetype":"venue"
},
  "geometry": {"coordinates":[-81.40895500000001,28.657377],"type":"Point"}
}