{
  "type": "Feature",
  "properties": {
    "iso:country":"US",
    "sg:address":"4690 Terminal Dr",
    "sg:city":"Fort Myers",
    "sg:classifiers":[
        {
            "category":"Government",
            "subcategory":"Office",
            "type":"Public Place"
        }
    ],
    "sg:phone":"+1 239 936 7867",
    "sg:postcode":"33907",
    "sg:province":"FL",
    "sg:tags":[
        "federal"
    ],
    "wof:name":"US Airport Traffic Control",
    "wof:placetype":"venue"
},
  "geometry": {"coordinates":[-81.860468,26.593487],"type":"Point"}
}