{
  "type": "Feature",
  "properties": {
    "iso:country":"US",
    "sg:address":"5532 Gall Blvd",
    "sg:city":"Zephyrhills",
    "sg:classifiers":[
        {
            "category":"Wholesale",
            "subcategory":"Medical Equipment & Supplies",
            "type":"Manufacturing & Wholesale Goods"
        }
    ],
    "sg:phone":"+1 813 780 9108",
    "sg:postcode":"33542",
    "sg:province":"FL",
    "sg:tags":[
        "physician",
        "surgeon"
    ],
    "wof:name":"Suncare Respiratory Svc Inc",
    "wof:placetype":"venue"
},
  "geometry": {"coordinates":[-82.18371399999999,28.237509],"type":"Point"}
}