{
  "type": "Feature",
  "properties": {
    "iso:country":"US",
    "sg:address":"425 NW 12th Ave Ste H",
    "sg:city":"Miami",
    "sg:classifiers":[
        {
            "category":"Shopping",
            "subcategory":"Gifts & Souvenirs",
            "type":"Retail Goods"
        }
    ],
    "sg:phone":"+1 305 548 3070",
    "sg:postcode":"33128",
    "sg:province":"FL",
    "sg:tags":[
        "shop"
    ],
    "wof:name":"Discount In Chocolatazo Dollar",
    "wof:placetype":"venue"
},
  "geometry": {"coordinates":[-80.214765,25.777611],"type":"Point"}
}