{
  "type": "Feature",
  "properties": {
    "addr:full":"505 E Pleasant St Avon Park FL 33825",
    "addr:housenumber":"505",
    "addr:postcode":"33825",
    "addr:street":"E Pleasant St",
    "iso:country":"US",
    "sg:address":"505 E Pleasant St",
    "sg:city":"Avon Park",
    "sg:classifiers":[
        {
            "category":"Building & Trades",
            "subcategory":"Construction",
            "type":"Services"
        }
    ],
    "sg:phone":"+1 863 452 1698",
    "sg:postcode":"33825",
    "sg:province":"FL",
    "sg:tags":[
        "stucco",
        "contractor"
    ],
    "wof:name":"Stucco Stone By Richard Runner",
    "wof:placetype":"venue"
},
  "geometry": {"coordinates":[-81.49160500000001,27.599324],"type":"Point"}
}