{
  "type": "Feature",
  "properties": {
    "addr:full":"9723 el Clair Ranch Rd Boynton Beach FL 33437",
    "addr:housenumber":"9723",
    "addr:postcode":"33437",
    "addr:street":"El Clair Ranch Rd",
    "iso:country":"US",
    "sg:address":"9723 el Clair Ranch Rd",
    "sg:city":"Boynton Beach",
    "sg:classifiers":[
        {
            "category":"Building & Trades",
            "subcategory":"Plumbing",
            "type":"Services"
        }
    ],
    "sg:phone":"+1 561 738 2444",
    "sg:postcode":"33437",
    "sg:province":"FL",
    "sg:tags":[
        "refrigeration",
        "contractor"
    ],
    "wof:name":"Montana Cool Inc",
    "wof:placetype":"venue"
},
  "geometry": {"coordinates":[-80.13900599999999,26.53416],"type":"Point"}
}