{
  "type": "Feature",
  "properties": {
    "addr:full":"210 S Florida Ave Lakeland FL 33801",
    "addr:housenumber":"210",
    "addr:postcode":"33801",
    "addr:street":"S Florida Ave",
    "iso:country":"US",
    "sg:address":"210 S Florida Ave",
    "sg:city":"Lakeland",
    "sg:classifiers":[
        {
            "category":"Professional",
            "subcategory":"Lawyer & Legal Services",
            "type":"Services"
        }
    ],
    "sg:phone":"+1 863 688 8228",
    "sg:postcode":"33801",
    "sg:province":"FL",
    "sg:tags":[
        "attorney"
    ],
    "wof:name":"Rafool Law Office",
    "wof:placetype":"venue"
},
  "geometry": {"coordinates":[-81.95711,28.041822],"type":"Point"}
}