{
  "type": "Feature",
  "properties": {
    "iso:country":"US",
    "sg:address":"1011 Tamiami Trl",
    "sg:city":"Venice",
    "sg:classifiers":[
        {
            "category":"Shopping",
            "subcategory":"Used Merchandise",
            "type":"Retail Goods"
        }
    ],
    "sg:phone":"+1 941 484 5715",
    "sg:postcode":"34285",
    "sg:province":"FL",
    "wof:name":"Pelican Mans Thrift Shop",
    "wof:placetype":"venue"
},
  "geometry": {"coordinates":[-82.435958,27.083016],"type":"Point"}
}