{
  "type": "Feature",
  "properties": {
    "iso:country":"US",
    "sg:address":"4333 Rock Island Rd",
    "sg:city":"Fort Lauderdale",
    "sg:classifiers":[
        {
            "category":"Shopping",
            "type":"Retail Goods"
        }
    ],
    "sg:phone":"+1 954 735 3575",
    "sg:postcode":"33319",
    "sg:province":"FL",
    "sg:tags":[
        "repair",
        "merchandise"
    ],
    "wof:name":"Freeman Framing & Artwork",
    "wof:placetype":"venue"
},
  "geometry": {"coordinates":[-80.22068400000001,26.173226],"type":"Point"}
}