{
  "type": "Feature",
  "properties": {
    "addr:full":"5703 Red Bug Lake Rd Winter Springs FL 32708",
    "addr:housenumber":"5703",
    "addr:postcode":"32708",
    "addr:street":"Red Bug Lake Rd",
    "iso:country":"US",
    "sg:address":"5703 Red Bug Lake Rd",
    "sg:city":"Winter Springs",
    "sg:classifiers":[
        {
            "category":"Professional",
            "subcategory":"Business Services",
            "type":"Services"
        }
    ],
    "sg:phone":"+1 407 977 5610",
    "sg:postcode":"32708",
    "sg:province":"FL",
    "sg:tags":[
        "interior",
        "consultant",
        "design",
        "decorator"
    ],
    "wof:name":"Whimsical Creations",
    "wof:placetype":"venue"
},
  "geometry": {"coordinates":[-81.267096,28.647719],"type":"Point"}
}