{
  "type": "Feature",
  "properties": {
    "addr:full":"4309 US Hwy 1 Vero Beach FL 32967",
    "addr:housenumber":"4309",
    "addr:postcode":"32967",
    "addr:street":"Us Hwy 1",
    "iso:country":"US",
    "sg:address":"4309 US Hwy 1",
    "sg:city":"Vero Beach",
    "sg:classifiers":[
        {
            "category":"Health Services",
            "subcategory":"Clinic",
            "type":"Services"
        }
    ],
    "sg:phone":"+1 772 564 2410",
    "sg:postcode":"32967",
    "sg:province":"FL",
    "sg:tags":[
        "home"
    ],
    "wof:name":"Gentiva Health Svc",
    "wof:placetype":"venue"
},
  "geometry": {"coordinates":[-80.406387,27.670047],"type":"Point"}
}