{
  "type": "Feature",
  "properties": {
    "addr:full":"311 US Hwy 41 Ruskin FL 33570",
    "addr:housenumber":"311",
    "addr:postcode":"33570",
    "addr:street":"Us Hwy 41",
    "iso:country":"US",
    "sg:address":"311 US Hwy 41",
    "sg:city":"Ruskin",
    "sg:classifiers":[
        {
            "category":"Shopping",
            "subcategory":"Bicycles & Sporting Goods",
            "type":"Retail Goods"
        }
    ],
    "sg:phone":"+1 813 641 9337",
    "sg:postcode":"33570",
    "sg:province":"FL",
    "sg:tags":[
        "equipment",
        "soccer",
        "supply"
    ],
    "wof:name":"Rosario Cruz",
    "wof:placetype":"venue"
},
  "geometry": {"coordinates":[-82.433891,27.721424],"type":"Point"}
}