{
  "type": "Feature",
  "properties": {
    "addr:full":"918 NE 62nd St Fort Lauderdale FL 33334",
    "addr:housenumber":"918",
    "addr:postcode":"33334",
    "addr:street":"Ne 62Nd St",
    "iso:country":"US",
    "sg:address":"918 NE 62nd St",
    "sg:city":"Fort Lauderdale",
    "sg:classifiers":[
        {
            "category":"Banks & Credit Unions",
            "subcategory":"Bank",
            "type":"Services"
        }
    ],
    "sg:phone":"+1 954 958 9758",
    "sg:postcode":"33334",
    "sg:province":"FL",
    "sg:tags":[
        "money",
        "transfer"
    ],
    "wof:name":"Western Union",
    "wof:placetype":"venue"
},
  "geometry": {"coordinates":[-80.13283300000001,26.203604],"type":"Point"}
}