{
  "type": "Feature",
  "properties": {
    "iso:country":"US",
    "sg:address":"15490 NW 77th Ct",
    "sg:city":"Hialeah",
    "sg:classifiers":[
        {
            "category":"Restaurant",
            "type":"Food & Drink"
        }
    ],
    "sg:phone":"+1 305 558 6868",
    "sg:postcode":"33016",
    "sg:province":"FL",
    "sg:website":"www.outback.com",
    "wof:name":"Outback Steakhouse",
    "wof:placetype":"venue"
},
  "geometry": {"coordinates":[-80.3274,25.9139],"type":"Point"}
}