{
  "type": "Feature",
  "properties": {
    "iso:country":"US",
    "sg:address":"120 NE 2nd Ave",
    "sg:city":"Miami",
    "sg:classifiers":[
        {
            "category":"Shopping",
            "type":"Retail Goods"
        }
    ],
    "sg:phone":"+1 305 379 1170",
    "sg:postcode":"33132",
    "sg:province":"FL",
    "sg:tags":[
        "equipment",
        "parts",
        "electronic"
    ],
    "wof:name":"El Encanto De Miami 2 Inc",
    "wof:placetype":"venue"
},
  "geometry": {"coordinates":[-80.190405,25.775976],"type":"Point"}
}