{
  "type": "Feature",
  "properties": {
    "iso:country":"US",
    "sg:address":"8015 N Nebraska Ave",
    "sg:city":"Tampa",
    "sg:classifiers":[
        {
            "category":"Home & Garden",
            "subcategory":"Carpets & Floor Coverings",
            "type":"Retail Goods"
        }
    ],
    "sg:phone":"+1 813 915 9320",
    "sg:postcode":"33604",
    "sg:province":"FL",
    "wof:name":"Pro Hardwood Installations",
    "wof:placetype":"venue"
},
  "geometry": {"coordinates":[-82.45119699999999,28.021174],"type":"Point"}
}