{
  "type": "Feature",
  "properties": {
    "addr:full":"12975 SW 6th St Miami FL 33184",
    "addr:housenumber":"12975",
    "addr:postcode":"33184",
    "addr:street":"Sw 6Th St",
    "iso:country":"US",
    "sg:address":"12975 SW 6th St",
    "sg:city":"Miami",
    "sg:classifiers":[
        {
            "category":"Education",
            "subcategory":"Music School",
            "type":"Public Place"
        },
        {
            "category":"Education",
            "subcategory":"Preschool",
            "type":"Public Place"
        },
        {
            "category":"Education",
            "subcategory":"School",
            "type":"Public Place"
        }
    ],
    "sg:phone":"+1 305 424 8624",
    "sg:postcode":"33184",
    "sg:province":"FL",
    "sg:tags":[
        "kindergarten",
        "information",
        "k-",
        "private"
    ],
    "sg:website":"http://www.conchitaespinosa.com",
    "wof:name":"Conchita Espinosa Academy",
    "wof:placetype":"venue"
},
  "geometry": {"coordinates":[-80.406327,25.76199],"type":"Point"}
}