{
  "type": "Feature",
  "properties": {
    "addr:full":"1890 W State Rd 434 Longwood FL 32750",
    "addr:housenumber":"1890;434",
    "addr:postcode":"32750",
    "addr:street":"W State Rd",
    "iso:country":"US",
    "sg:address":"1890 W State Rd 434",
    "sg:city":"Longwood",
    "sg:classifiers":[
        {
            "category":"Social Services",
            "subcategory":"Child Care",
            "type":"Services"
        }
    ],
    "sg:phone":"+1 407 339 1172",
    "sg:postcode":"32750",
    "sg:province":"FL",
    "sg:tags":[
        "kindergarten",
        "academic",
        "school",
        "day"
    ],
    "sg:website":"www.scsblessings.org",
    "wof:name":"Christian Sanlando School",
    "wof:placetype":"venue"
},
  "geometry": {"coordinates":[-81.38682,28.69165],"type":"Point"}
}