{
  "type": "Feature",
  "properties": {
    "iso:country":"US",
    "sg:address":"1411 Oakfield Dr",
    "sg:city":"Brandon",
    "sg:classifiers":[
        {
            "category":"Utilities",
            "subcategory":"Telephone",
            "type":"Services"
        }
    ],
    "sg:phone":"+1 813 654 6555",
    "sg:postcode":"33511",
    "sg:province":"FL",
    "sg:tags":[
        "telecommunication"
    ],
    "wof:name":"Integrated Telecom Systems",
    "wof:placetype":"venue"
},
  "geometry": {"coordinates":[-82.30606400000001,27.934023],"type":"Point"}
}