{
  "type": "Feature",
  "properties": {
    "iso:country":"US",
    "sg:address":"995 NE 124th St",
    "sg:city":"North Miami",
    "sg:classifiers":[
        {
            "category":"Utilities",
            "subcategory":"Telephone",
            "type":"Services"
        }
    ],
    "sg:phone":"+1 305 891 9577",
    "sg:postcode":"33161",
    "sg:province":"FL",
    "sg:tags":[
        "telecommunication"
    ],
    "wof:name":"A T & T Ort",
    "wof:placetype":"venue"
},
  "geometry": {"coordinates":[-80.180094,25.88968],"type":"Point"}
}