{
  "type": "Feature",
  "properties": {
    "iso:country":"US",
    "sg:address":"2670 Placida Rd",
    "sg:city":"Grove City",
    "sg:classifiers":[
        {
            "category":"Restaurant",
            "type":"Food & Drink"
        }
    ],
    "sg:phone":"+1 941 697 8050",
    "sg:postcode":"34224",
    "sg:province":"FL",
    "wof:name":"Faull Inn",
    "wof:placetype":"venue"
},
  "geometry": {"coordinates":[-82.328784,26.917047],"type":"Point"}
}