{
  "type": "Feature",
  "properties": {
    "iso:country":"US",
    "sg:address":"6001 Kiteridge Dr",
    "sg:city":"Lithia",
    "sg:classifiers":[
        {
            "category":"Building & Trades",
            "subcategory":"Construction",
            "type":"Services"
        }
    ],
    "sg:phone":"+1 813 657 9398",
    "sg:postcode":"33547",
    "sg:province":"FL",
    "sg:tags":[
        "wallcoverings-installation",
        "wallpaper",
        "painting",
        "contractor"
    ],
    "wof:name":"Coles Painting & Pressure",
    "wof:placetype":"venue"
},
  "geometry": {"coordinates":[-82.18823999999999,27.851549],"type":"Point"}
}