{
  "type": "Feature",
  "properties": {
    "addr:full":"12791 Forest Hill Blvd Wellington FL 33414",
    "addr:housenumber":"12791",
    "addr:postcode":"33414",
    "addr:street":"Forest Hill Blvd",
    "iso:country":"US",
    "sg:address":"12791 Forest Hill Blvd",
    "sg:city":"Wellington",
    "sg:classifiers":[
        {
            "category":"Building & Trades",
            "subcategory":"Construction",
            "type":"Services"
        }
    ],
    "sg:phone":"+1 561 784 4452",
    "sg:postcode":"33414",
    "sg:province":"FL",
    "sg:tags":[
        "general",
        "contractor"
    ],
    "wof:name":"Bain Bridge Construction LLC",
    "wof:placetype":"venue"
},
  "geometry": {"coordinates":[-80.247773,26.672853],"type":"Point"}
}