{
  "type": "Feature",
  "properties": {
    "addr:full":"507 State Hwy 85 Niceville FL 32578",
    "addr:housenumber":"507",
    "addr:postcode":"32578",
    "addr:street":"State Hwy 85",
    "iso:country":"US",
    "sg:address":"507 State Hwy 85",
    "sg:city":"Niceville",
    "sg:classifiers":[
        {
            "category":"Food & Beverages",
            "subcategory":"Specialty",
            "type":"Retail Goods"
        }
    ],
    "sg:phone":"+1 850 678 8987",
    "sg:postcode":"32578",
    "sg:province":"FL",
    "sg:tags":[
        "water",
        "bulk",
        "company"
    ],
    "wof:name":"NVOC Regional Waste Water",
    "wof:placetype":"venue"
},
  "geometry": {"coordinates":[-86.49311400000001,30.532713],"type":"Point"}
}