{
  "type": "Feature",
  "properties": {
    "addr:full":"253 Driggs Dr Winter Park FL 32792",
    "addr:housenumber":"253",
    "addr:postcode":"32792",
    "addr:street":"Driggs Dr",
    "iso:country":"US",
    "sg:address":"253 Driggs Dr",
    "sg:city":"Winter Park",
    "sg:classifiers":[
        {
            "category":"Home & Garden",
            "subcategory":"Building Materials",
            "type":"Retail Goods"
        }
    ],
    "sg:phone":"+1 407 678 2555",
    "sg:postcode":"32792",
    "sg:province":"FL",
    "sg:tags":[
        "lumber"
    ],
    "sg:website":"www.84lumber.com",
    "wof:name":"84 Lumber Co",
    "wof:placetype":"venue"
},
  "geometry": {"coordinates":[-81.306966,28.599056],"type":"Point"}
}