{
  "type": "Feature",
  "properties": {
    "iso:country":"US",
    "sg:address":"11248 Isle of Waterbridge",
    "sg:city":"Orlando",
    "sg:classifiers":[
        {
            "category":"Recreation",
            "subcategory":"Amusement Park",
            "type":"Entertainment"
        }
    ],
    "sg:phone":"+1 407 934 3833",
    "sg:postcode":"32837",
    "sg:province":"FL",
    "sg:tags":[
        "park"
    ],
    "wof:name":"Cape May Resturante",
    "wof:placetype":"venue"
},
  "geometry": {"coordinates":[-81.406845,28.403338],"type":"Point"}
}