{
  "type": "Feature",
  "properties": {
    "addr:full":"16 de Luna Dr Gulf Breeze FL 32506",
    "addr:postcode":"32506",
    "addr:street":"16 De Luna Dr",
    "iso:country":"US",
    "sg:address":"16 de Luna Dr",
    "sg:city":"Gulf Breeze",
    "sg:classifiers":[
        {
            "category":"Travel",
            "subcategory":"Hotels & Motels",
            "type":"Entertainment"
        }
    ],
    "sg:phone":"+1 850 934 3300",
    "sg:postcode":"32506",
    "sg:province":"FL",
    "wof:name":"Best Western Inn",
    "wof:placetype":"venue"
},
  "geometry": {"coordinates":[-87.288065,30.419753],"type":"Point"}
}