{
  "type": "Feature",
  "properties": {
    "iso:country":"US",
    "sg:address":"840 S Bea Ave",
    "sg:city":"Inverness",
    "sg:classifiers":[
        {
            "category":"Health Services",
            "subcategory":"Doctor",
            "type":"Services"
        }
    ],
    "sg:phone":"+1 352 637 6300",
    "sg:postcode":"34452",
    "sg:province":"FL",
    "sg:tags":[
        "physician",
        "surgeon"
    ],
    "wof:name":"Vikas G Kamat MD",
    "wof:placetype":"venue"
},
  "geometry": {"coordinates":[-82.37906700000001,28.850524],"type":"Point"}
}