{
  "type": "Feature",
  "properties": {
    "iso:country":"US",
    "sg:address":"705 N Pebble Beach Blvd",
    "sg:city":"Sun City Center",
    "sg:classifiers":[
        {
            "category":"Shopping",
            "subcategory":"Pharmacy",
            "type":"Retail Goods"
        }
    ],
    "sg:phone":"+1 813 633 1389",
    "sg:postcode":"33573",
    "sg:province":"FL",
    "wof:name":"Walgreens",
    "wof:placetype":"venue"
},
  "geometry": {"coordinates":[-82.351843,27.714174],"type":"Point"}
}