{
  "type": "Feature",
  "properties": {
    "addr:full":"2824 Arapahoe Ave Jacksonville FL 32210",
    "addr:housenumber":"2824",
    "addr:postcode":"32210",
    "addr:street":"Arapahoe Ave",
    "iso:country":"US",
    "sg:address":"2824 Arapahoe Ave",
    "sg:city":"Jacksonville",
    "sg:classifiers":[
        {
            "category":"Professional",
            "type":"Services"
        }
    ],
    "sg:phone":"+1 904 384 2080",
    "sg:postcode":"32210",
    "sg:province":"FL",
    "wof:name":"Moretrench",
    "wof:placetype":"venue"
},
  "geometry": {"coordinates":[-81.706592,30.270404],"type":"Point"}
}