{
  "type": "Feature",
  "properties": {
    "addr:full":"11405 5th St E Saint Petersburg FL 33706",
    "addr:housenumber":"11405",
    "addr:postcode":"33706",
    "addr:street":"5Th St E",
    "iso:country":"US",
    "sg:address":"11405 5th St E",
    "sg:city":"Saint Petersburg",
    "sg:classifiers":[
        {
            "category":"Professional",
            "subcategory":"Business Services",
            "type":"Services"
        }
    ],
    "sg:phone":"+1 727 360 5211",
    "sg:postcode":"33706",
    "sg:province":"FL",
    "wof:name":"High CS Enterprises",
    "wof:placetype":"venue"
},
  "geometry": {"coordinates":[-82.765423,27.77506],"type":"Point"}
}