{
  "type": "Feature",
  "properties": {
    "addr:full":"4124 Southside Blvd Jacksonville FL 32216",
    "addr:housenumber":"4124",
    "addr:postcode":"32216",
    "addr:street":"Southside Blvd",
    "iso:country":"US",
    "sg:address":"4124 Southside Blvd",
    "sg:city":"Jacksonville",
    "sg:classifiers":[
        {
            "category":"Food & Beverages",
            "subcategory":"Liquor & Beverages",
            "type":"Retail Goods"
        },
        {
            "category":"Bars & Pubs",
            "type":"Food & Drink"
        }
    ],
    "sg:phone":"+1 904 641 6888",
    "sg:postcode":"32216",
    "sg:province":"FL",
    "sg:tags":[
        "drinking",
        "alcoholic"
    ],
    "wof:name":"Glenn's Liquors",
    "wof:placetype":"venue"
},
  "geometry": {"coordinates":[-81.559106,30.272716],"type":"Point"}
}