{
  "type": "Feature",
  "properties": {
    "addr:full":"4020 del Prado Blvd S Cape Coral FL 33904",
    "addr:housenumber":"4020",
    "addr:postcode":"33904",
    "addr:street":"Del Prado Blvd S",
    "iso:country":"US",
    "sg:address":"4020 del Prado Blvd S",
    "sg:city":"Cape Coral",
    "sg:classifiers":[
        {
            "category":"Retail",
            "subcategory":"Funeral Services",
            "type":"Services"
        }
    ],
    "sg:phone":"+1 239 542 9500",
    "sg:postcode":"33904",
    "sg:province":"FL",
    "sg:tags":[
        "crematory"
    ],
    "wof:name":"International Cremation Soc",
    "wof:placetype":"venue"
},
  "geometry": {"coordinates":[-81.943223,26.577004],"type":"Point"}
}