{
  "type": "Feature",
  "properties": {
    "iso:country":"US",
    "sg:address":"4155 S Atlantic Ave",
    "sg:city":"New Smyrna Beach",
    "sg:classifiers":[
        {
            "category":"Real Estate",
            "subcategory":"Real Estate Operator",
            "type":"Services"
        }
    ],
    "sg:phone":"+1 386 428 9044",
    "sg:postcode":"32169",
    "sg:province":"FL",
    "sg:tags":[
        "condominium"
    ],
    "wof:name":"Sea Coast Condominium",
    "wof:placetype":"venue"
},
  "geometry": {"coordinates":[-80.875698,29.003376],"type":"Point"}
}