{
  "type": "Feature",
  "properties": {
    "iso:country":"US",
    "sg:address":"3961 Kingston Dr",
    "sg:city":"Sarasota",
    "sg:classifiers":[
        {
            "category":"Building & Trades",
            "subcategory":"Construction",
            "type":"Services"
        }
    ],
    "sg:phone":"+1 841 927 8803",
    "sg:postcode":"34238",
    "sg:province":"FL",
    "sg:tags":[
        "contractor"
    ],
    "wof:name":"Big Dog Restoration LLC",
    "wof:placetype":"venue"
},
  "geometry": {"coordinates":[-82.48882399999999,27.261368],"type":"Point"}
}