{
  "type": "Feature",
  "properties": {
    "iso:country":"US",
    "sg:address":"2741 US Hwy 27",
    "sg:city":"Lake Placid",
    "sg:classifiers":[
        {
            "category":"Farming",
            "subcategory":"Nursery",
            "type":"Manufacturing & Wholesale Goods"
        }
    ],
    "sg:phone":"+1 863 465 1929",
    "sg:postcode":"33852",
    "sg:province":"FL",
    "sg:tags":[
        "greenhouse"
    ],
    "wof:name":"Orchid Moon",
    "wof:placetype":"venue"
},
  "geometry": {"coordinates":[-81.32874200000001,27.210855],"type":"Point"}
}