{
  "type": "Feature",
  "properties": {
    "iso:country":"US",
    "sg:address":"633 NE 167th St",
    "sg:city":"Miami",
    "sg:classifiers":[
        {
            "category":"Insurance",
            "subcategory":"Insurance Agent",
            "type":"Services"
        }
    ],
    "sg:phone":"+1 305 653 6050",
    "sg:postcode":"33162",
    "sg:province":"FL",
    "wof:name":"All Protection Insurance",
    "wof:placetype":"venue"
},
  "geometry": {"coordinates":[-80.187034,25.928709],"type":"Point"}
}