{
  "type": "Feature",
  "properties": {
    "iso:country":"US",
    "sg:address":"118 NE 39th St",
    "sg:city":"Miami",
    "sg:classifiers":[
        {
            "category":"Building & Trades",
            "subcategory":"Construction",
            "type":"Services"
        }
    ],
    "sg:phone":"+1 305 571 0170",
    "sg:postcode":"33137",
    "sg:province":"FL",
    "sg:tags":[
        "contractor"
    ],
    "wof:name":"Brodson Construction Inc",
    "wof:placetype":"venue"
},
  "geometry": {"coordinates":[-80.19299599999999,25.812607],"type":"Point"}
}