{
  "type": "Feature",
  "properties": {
    "iso:country":"US",
    "sg:address":"262 N Castleford Ct",
    "sg:city":"Longwood",
    "sg:classifiers":[
        {
            "category":"Professional",
            "type":"Services"
        }
    ],
    "sg:phone":"+1 407 869 8674",
    "sg:postcode":"32779",
    "sg:province":"FL",
    "wof:name":"Diane C Gerry PA",
    "wof:placetype":"venue"
},
  "geometry": {"coordinates":[-81.45399999999999,28.696065],"type":"Point"}
}