{
  "type": "Feature",
  "properties": {
    "iso:country":"US",
    "sg:address":"1900 Liberty Ave",
    "sg:city":"Miami Beach",
    "sg:classifiers":[
        {
            "category":"Real Estate",
            "subcategory":"Real Estate Operator",
            "type":"Services"
        }
    ],
    "sg:phone":"+1 305 534 1731",
    "sg:postcode":"33139",
    "sg:province":"FL",
    "sg:tags":[
        "apartment"
    ],
    "wof:name":"Jobrotam Development Corp",
    "wof:placetype":"venue"
},
  "geometry": {"coordinates":[-80.130501,25.795099],"type":"Point"}
}