{
  "type": "Feature",
  "properties": {
    "iso:country":"US",
    "sg:address":"260 Carib Dr",
    "sg:city":"Merritt Island",
    "sg:classifiers":[
        {
            "category":"Manufacturing",
            "subcategory":"Textiles",
            "type":"Manufacturing & Wholesale Goods"
        }
    ],
    "sg:phone":"+1 321 453 3319",
    "sg:postcode":"32952",
    "sg:province":"FL",
    "sg:tags":[
        "mill",
        "knit",
        "outerwear"
    ],
    "wof:name":"Tracy Tracys To A T",
    "wof:placetype":"venue"
},
  "geometry": {"coordinates":[-80.695538,28.351696],"type":"Point"}
}