{
  "type": "Feature",
  "properties": {
    "addr:full":"1129 Volco Rd Edgewater FL 32141",
    "addr:housenumber":"1129",
    "addr:postcode":"32141",
    "addr:street":"Volco Rd",
    "iso:country":"US",
    "sg:address":"1129 Volco Rd",
    "sg:city":"Edgewater",
    "sg:classifiers":[
        {
            "category":"Farming",
            "subcategory":"Farm",
            "type":"Manufacturing & Wholesale Goods"
        }
    ],
    "sg:phone":"+1 386 345 0453",
    "sg:postcode":"32141",
    "sg:province":"FL",
    "wof:name":"S&R Ranch",
    "wof:placetype":"venue"
},
  "geometry": {"coordinates":[-80.893889,28.916445],"type":"Point"}
}