{
  "type": "Feature",
  "properties": {
    "iso:country":"US",
    "sg:address":"540 Alpine St",
    "sg:city":"Altamonte Spgs",
    "sg:classifiers":[
        {
            "category":"Building & Trades",
            "subcategory":"Landscaping Services",
            "type":"Services"
        }
    ],
    "sg:phone":"+1 407 331 6088",
    "sg:postcode":"32701",
    "sg:province":"FL",
    "sg:tags":[
        "lawn",
        "maintenance",
        "grounds"
    ],
    "wof:name":"Sunshine Lawn & Landscaping",
    "wof:placetype":"venue"
},
  "geometry": {"coordinates":[-81.372607,28.67725],"type":"Point"}
}