{
  "type": "Feature",
  "properties": {
    "iso:country":"US",
    "sg:address":"4984 Calienta St",
    "sg:city":"Hernando Beach",
    "sg:classifiers":[
        {
            "category":"Recreation",
            "type":"Entertainment"
        }
    ],
    "sg:phone":"+1 352 592 2559",
    "sg:postcode":"34607",
    "sg:province":"FL",
    "sg:tags":[
        "guide"
    ],
    "wof:name":"Fishing Rods Bait & Tackle",
    "wof:placetype":"venue"
},
  "geometry": {"coordinates":[-82.64961099999999,28.498013],"type":"Point"}
}