{
  "type": "Feature",
  "properties": {
    "iso:country":"US",
    "sg:address":"705 S Dillard St",
    "sg:city":"Winter Garden",
    "sg:classifiers":[
        {
            "category":"Autos & Motor Vehicles",
            "subcategory":"Fuel & Gas Station",
            "type":"Retail Goods"
        }
    ],
    "sg:phone":"+1 407 654 6230",
    "sg:postcode":"34787",
    "sg:province":"FL",
    "sg:tags":[
        "oil"
    ],
    "wof:name":"Dillards Street Citgo",
    "wof:placetype":"venue"
},
  "geometry": {"coordinates":[-81.583437,28.554788],"type":"Point"}
}