{
  "type": "Feature",
  "properties": {
    "iso:country":"US",
    "sg:address":"888 SW Federal Hwy",
    "sg:city":"Stuart",
    "sg:classifiers":[
        {
            "category":"Shopping",
            "subcategory":"Musical Instruments",
            "type":"Retail Goods"
        }
    ],
    "sg:phone":"+1 772 286 7474",
    "sg:postcode":"34994",
    "sg:province":"FL",
    "sg:website":"www.schumachermusic.com",
    "wof:name":"Schumacher Music",
    "wof:placetype":"venue"
},
  "geometry": {"coordinates":[-80.25584000000001,27.1924],"type":"Point"}
}