{
  "type": "Feature",
  "properties": {
    "addr:full":"855 Darwin Dr Altamonte Spgs FL 32701",
    "addr:housenumber":"855",
    "addr:postcode":"32701",
    "addr:street":"Darwin Dr Altamonte Spgs",
    "iso:country":"US",
    "sg:address":"855 Darwin Dr",
    "sg:city":"Altamonte Spgs",
    "sg:classifiers":[
        {
            "category":"Manufacturing",
            "subcategory":"Textiles",
            "type":"Manufacturing & Wholesale Goods"
        }
    ],
    "sg:phone":"+1 407 260 9020",
    "sg:postcode":"32701",
    "sg:province":"FL",
    "sg:tags":[
        "curtain"
    ],
    "wof:name":"Ana Vazquez Seamstress",
    "wof:placetype":"venue"
},
  "geometry": {"coordinates":[-81.359326,28.658218],"type":"Point"}
}