{
  "type": "Feature",
  "properties": {
    "iso:country":"US",
    "sg:address":"9463 Benford Rd",
    "sg:city":"Orlando",
    "sg:classifiers":[
        {
            "category":"Transit Center",
            "subcategory":"Freight",
            "type":"Transportation"
        },
        {
            "category":"Airline",
            "type":"Transportation"
        }
    ],
    "sg:phone":"+1 407 855 8596",
    "sg:postcode":"32827",
    "sg:province":"FL",
    "sg:tags":[
        "air",
        "cargo",
        "express",
        "package"
    ],
    "wof:name":"Aer Lingus Cargo",
    "wof:placetype":"venue"
},
  "geometry": {"coordinates":[-81.332739,28.428368],"type":"Point"}
}