{
  "type": "Feature",
  "properties": {
    "addr:full":"6230 47th Ave E Bradenton FL 34203",
    "addr:housenumber":"6230",
    "addr:postcode":"34203",
    "addr:street":"47Th Ave E",
    "iso:country":"US",
    "sg:address":"6230 47th Ave E",
    "sg:city":"Bradenton",
    "sg:classifiers":[
        {
            "category":"Retail",
            "subcategory":"Repair Shop",
            "type":"Services"
        }
    ],
    "sg:phone":"+1 941 756 3272",
    "sg:postcode":"34203",
    "sg:province":"FL",
    "sg:tags":[
        "upholsterer"
    ],
    "wof:name":"M & M Upholstery",
    "wof:placetype":"venue"
},
  "geometry": {"coordinates":[-82.481103,27.457909],"type":"Point"}
}