{
  "type": "Feature",
  "properties": {
    "addr:full":"1319 E Cape Coral Pkwy Cape Coral FL 33904",
    "addr:housenumber":"1319",
    "addr:postcode":"33904",
    "addr:street":"E Cape Coral Pkwy",
    "iso:country":"US",
    "sg:address":"1319 E Cape Coral Pkwy",
    "sg:city":"Cape Coral",
    "sg:classifiers":[
        {
            "category":"Personal",
            "subcategory":"Beauty Salon",
            "type":"Services"
        }
    ],
    "sg:phone":"+1 239 541 9191",
    "sg:postcode":"33904",
    "sg:province":"FL",
    "wof:name":"Ooh LA LA Salon & Spa",
    "wof:placetype":"venue"
},
  "geometry": {"coordinates":[-81.947373,26.562622],"type":"Point"}
}