{
  "type": "Feature",
  "properties": {
    "iso:country":"US",
    "sg:address":"500 Flagami Blvd",
    "sg:city":"Miami",
    "sg:classifiers":[
        {
            "category":"Wholesale",
            "subcategory":"Groceries",
            "type":"Manufacturing & Wholesale Goods"
        }
    ],
    "sg:phone":"+1 305 267 8155",
    "sg:postcode":"33144",
    "sg:province":"FL",
    "sg:tags":[
        "food",
        "product"
    ],
    "wof:name":"Catalina Finest Foods",
    "wof:placetype":"venue"
},
  "geometry": {"coordinates":[-80.31585800000001,25.765513],"type":"Point"}
}