{
  "type": "Feature",
  "properties": {
    "iso:country":"US",
    "sg:address":"129 14th Ave SW",
    "sg:city":"Largo",
    "sg:classifiers":[
        {
            "category":"Professional",
            "subcategory":"Business Services",
            "type":"Services"
        }
    ],
    "sg:phone":"+1 727 348 9144",
    "sg:postcode":"33770",
    "sg:province":"FL",
    "sg:tags":[
        "consultant",
        "coach"
    ],
    "wof:name":"Central Florida Medical Training",
    "wof:placetype":"venue"
},
  "geometry": {"coordinates":[-82.79029800000001,27.903498],"type":"Point"}
}