{
  "type": "Feature",
  "properties": {
    "iso:country":"US",
    "sg:address":"4217 SW 64th Ave",
    "sg:city":"Davie",
    "sg:classifiers":[
        {
            "category":"Personal",
            "subcategory":"Beauty Salon",
            "type":"Services"
        }
    ],
    "sg:phone":"+1 954 587 6538",
    "sg:postcode":"33314",
    "sg:province":"FL",
    "wof:name":"Salon 32",
    "wof:placetype":"venue"
},
  "geometry": {"coordinates":[-80.23232,26.069558],"type":"Point"}
}