{
  "type": "Feature",
  "properties": {
    "iso:country":"US",
    "sg:address":"141 E Copeland Dr",
    "sg:city":"Orlando",
    "sg:classifiers":[
        {
            "category":"Professional",
            "subcategory":"Printing & Photocopies",
            "type":"Services"
        }
    ],
    "sg:phone":"+1 407 294 5462",
    "sg:postcode":"32806",
    "sg:province":"FL",
    "sg:tags":[
        "photographers-commercial"
    ],
    "wof:name":"Tom Hurst Photography",
    "wof:placetype":"venue"
},
  "geometry": {"coordinates":[-81.375033,28.525506],"type":"Point"}
}