{
  "type": "Feature",
  "properties": {
    "addr:full":"4400 Pga Blvd Palm Beach Gardens FL 33410",
    "addr:housenumber":"4400",
    "addr:postcode":"33410",
    "addr:street":"Pga Blvd",
    "iso:country":"US",
    "sg:address":"4400 Pga Blvd",
    "sg:city":"Palm Beach Gardens",
    "sg:classifiers":[
        {
            "category":"Real Estate",
            "subcategory":"Real Estate Agent",
            "type":"Services"
        }
    ],
    "sg:phone":"+1 561 630 4847",
    "sg:postcode":"33410",
    "sg:province":"FL",
    "wof:name":"Nancy Crown PA",
    "wof:placetype":"venue"
},
  "geometry": {"coordinates":[-80.10453699999999,26.838212],"type":"Point"}
}