{
  "type": "Feature",
  "properties": {
    "iso:country":"US",
    "sg:address":"205 S Hoover Blvd",
    "sg:city":"Tampa",
    "sg:classifiers":[
        {
            "category":"Professional",
            "subcategory":"Lawyer & Legal Services",
            "type":"Services"
        }
    ],
    "sg:phone":"+1 813 287 0802",
    "sg:postcode":"33609",
    "sg:province":"FL",
    "sg:tags":[
        "attorney"
    ],
    "wof:name":"D William Venable Pa",
    "wof:placetype":"venue"
},
  "geometry": {"coordinates":[-82.53448,27.941519],"type":"Point"}
}