{
  "type": "Feature",
  "properties": {
    "iso:country":"US",
    "sg:address":"1704 N Wickham Rd",
    "sg:city":"Melbourne",
    "sg:classifiers":[
        {
            "category":"Manufacturing",
            "subcategory":"Retail Goods",
            "type":"Manufacturing & Wholesale Goods"
        }
    ],
    "sg:phone":"+1 321 752 5700",
    "sg:postcode":"32935",
    "sg:province":"FL",
    "sg:tags":[
        "product",
        "mfg"
    ],
    "sg:website":"www.melbournemagic.com",
    "wof:name":"Melbourne Magic",
    "wof:placetype":"venue"
},
  "geometry": {"coordinates":[-80.671825,28.134793],"type":"Point"}
}