{
  "type": "Feature",
  "properties": {
    "addr:full":"2233 E Olive Rd Pensacola FL 32514",
    "addr:housenumber":"2233",
    "addr:postcode":"32514",
    "addr:street":"E Olive Rd",
    "iso:country":"US",
    "sg:address":"2233 E Olive Rd",
    "sg:city":"Pensacola",
    "sg:classifiers":[
        {
            "category":"Shopping",
            "subcategory":"Computers & Home Electronics",
            "type":"Retail Goods"
        }
    ],
    "sg:phone":"+1 850 478 2211",
    "sg:postcode":"32514",
    "sg:province":"FL",
    "sg:tags":[
        "equipment",
        "dealer"
    ],
    "sg:website":"www.computerware1.com",
    "wof:name":"Computer Ware Inc",
    "wof:placetype":"venue"
},
  "geometry": {"coordinates":[-87.21601699999999,30.510095],"type":"Point"}
}