{
  "type": "Feature",
  "properties": {
    "iso:country":"US",
    "sg:address":"2445 NE 195th St",
    "sg:city":"Miami",
    "sg:classifiers":[
        {
            "category":"Health Services",
            "subcategory":"Optometrist",
            "type":"Services"
        }
    ],
    "sg:phone":"+1 305 931 7857",
    "sg:postcode":"33180",
    "sg:province":"FL",
    "wof:name":"Paul Klein",
    "wof:placetype":"venue"
},
  "geometry": {"coordinates":[-80.153133,25.955674],"type":"Point"}
}