{
  "type": "Feature",
  "properties": {
    "iso:country":"US",
    "sg:address":"104 N Deerwood Ave",
    "sg:city":"Orlando",
    "sg:classifiers":[
        {
            "category":"Professional",
            "subcategory":"Business Services",
            "type":"Services"
        }
    ],
    "sg:phone":"+1 407 380 0605",
    "sg:postcode":"32825",
    "sg:province":"FL",
    "wof:name":"Atlantis Pool Service",
    "wof:placetype":"venue"
},
  "geometry": {"coordinates":[-81.257389,28.544022],"type":"Point"}
}