{
  "type": "Feature",
  "properties": {
    "iso:country":"US",
    "sg:address":"13937 Collins Ave",
    "sg:city":"Miami Beach",
    "sg:classifiers":[
        {
            "category":"Recreation",
            "subcategory":"Boat Charter",
            "type":"Entertainment"
        }
    ],
    "sg:phone":"+1 305 522 3942",
    "sg:postcode":"33154",
    "sg:province":"FL",
    "sg:tags":[
        "boating"
    ],
    "sg:website":"www.hauloverpointmarina.com",
    "wof:name":"Haulover Point",
    "wof:placetype":"venue"
},
  "geometry": {"coordinates":[-80.12258300000001,25.910749],"type":"Point"}
}