{
  "type": "Feature",
  "properties": {
    "iso:country":"US",
    "sg:address":"992 NE 167th St",
    "sg:city":"North Miami Bch",
    "sg:classifiers":[
        {
            "category":"Health Services",
            "subcategory":"Clinic",
            "type":"Services"
        }
    ],
    "sg:phone":"+1 305 957 7079",
    "sg:postcode":"33162",
    "sg:province":"FL",
    "sg:tags":[
        "equipment",
        "therapy",
        "oxygen"
    ],
    "wof:name":"Reliable Respiratory Care",
    "wof:placetype":"venue"
},
  "geometry": {"coordinates":[-80.181817,25.928778],"type":"Point"}
}