{
  "type": "Feature",
  "properties": {
    "addr:full":"4750 NW 179th St Opa Locka FL 33055",
    "addr:housenumber":"4750",
    "addr:postcode":"33055",
    "addr:street":"Nw 179Th St;Locka",
    "iso:country":"US",
    "sg:address":"4750 NW 179th St",
    "sg:city":"Opa Locka",
    "sg:classifiers":[
        {
            "category":"Retail",
            "subcategory":"Auto Repair",
            "type":"Services"
        }
    ],
    "sg:phone":"+1 305 620 0792",
    "sg:postcode":"33055",
    "sg:province":"FL",
    "sg:tags":[
        "automotive"
    ],
    "wof:name":"Top Cat Towing Service Inc",
    "wof:placetype":"venue"
},
  "geometry": {"coordinates":[-80.278346,25.935909],"type":"Point"}
}