{
  "type": "Feature",
  "properties": {
    "iso:country":"US",
    "sg:address":"2205 US Hwy 19",
    "sg:city":"Perry",
    "sg:classifiers":[
        {
            "category":"Food & Beverages",
            "subcategory":"Groceries & Convenience Stores",
            "type":"Retail Goods"
        }
    ],
    "sg:phone":"+1 850 584 8879",
    "sg:postcode":"32347",
    "sg:province":"FL",
    "wof:name":"Jiffy Food Store",
    "wof:placetype":"venue"
},
  "geometry": {"coordinates":[-83.608001,30.141518],"type":"Point"}
}