{
  "type": "Feature",
  "properties": {
    "addr:full":"4861 Kensington Ln Crestview FL 32539",
    "addr:housenumber":"4861",
    "addr:postcode":"32539",
    "addr:street":"Kensington Ln",
    "iso:country":"US",
    "sg:address":"4861 Kensington Ln",
    "sg:city":"Crestview",
    "sg:classifiers":[
        {
            "category":"Building & Trades",
            "subcategory":"Construction",
            "type":"Services"
        }
    ],
    "sg:phone":"+1 850 682 8883",
    "sg:postcode":"32539",
    "sg:province":"FL",
    "sg:tags":[
        "carpentry",
        "contractor"
    ],
    "wof:name":"Noah Lundy Carpentry",
    "wof:placetype":"venue"
},
  "geometry": {"coordinates":[-86.540404,30.716643],"type":"Point"}
}