{
  "type": "Feature",
  "properties": {
    "addr:full":"108 Quayside Dr Jupiter FL 33477",
    "addr:housenumber":"108",
    "addr:postcode":"33477",
    "addr:street":"Quayside Dr",
    "iso:country":"US",
    "sg:address":"108 Quayside Dr",
    "sg:city":"Jupiter",
    "sg:classifiers":[
        {
            "category":"Banks & Credit Unions",
            "subcategory":"Financial Services",
            "type":"Services"
        }
    ],
    "sg:phone":"+1 561 745 9151",
    "sg:postcode":"33477",
    "sg:province":"FL",
    "sg:tags":[
        "investor"
    ],
    "wof:name":"R & L Display Inc",
    "wof:placetype":"venue"
},
  "geometry": {"coordinates":[-80.086558,26.900566],"type":"Point"}
}