{
  "type": "Feature",
  "properties": {
    "iso:country":"US",
    "sg:address":"4109 30th Ln E",
    "sg:city":"Bradenton",
    "sg:classifiers":[
        {
            "category":"Personal",
            "type":"Services"
        }
    ],
    "sg:phone":"+1 513 671 1277",
    "sg:postcode":"34208",
    "sg:province":"FL",
    "sg:tags":[
        "party",
        "planning",
        "event"
    ],
    "wof:name":"Pope Myca Inc",
    "wof:placetype":"venue"
},
  "geometry": {"coordinates":[-82.52542200000001,27.463714],"type":"Point"}
}