{
  "type": "Feature",
  "properties": {
    "addr:full":"1477 Crane Creek Blvd Melbourne FL 32940",
    "addr:housenumber":"1477",
    "addr:postcode":"32940",
    "addr:street":"Crane Creek Blvd",
    "iso:country":"US",
    "sg:address":"1477 Crane Creek Blvd",
    "sg:city":"Melbourne",
    "sg:classifiers":[
        {
            "category":"Building & Trades",
            "subcategory":"Cleaning & Sanitation",
            "type":"Services"
        }
    ],
    "sg:phone":"+1 321 259 8954",
    "sg:postcode":"32940",
    "sg:province":"FL",
    "sg:tags":[
        "janitor"
    ],
    "wof:name":"Kristy Holbeck Cleaning",
    "wof:placetype":"venue"
},
  "geometry": {"coordinates":[-80.70911,28.241428],"type":"Point"}
}