{
  "type": "Feature",
  "properties": {
    "iso:country":"US",
    "sg:address":"277 Pinewood Dr",
    "sg:city":"Tallahassee",
    "sg:classifiers":[
        {
            "category":"Professional",
            "subcategory":"Lawyer & Legal Services",
            "type":"Services"
        }
    ],
    "sg:phone":"+1 850 681 9303",
    "sg:postcode":"32303",
    "sg:province":"FL",
    "sg:tags":[
        "attorney"
    ],
    "wof:name":"Mathews Law Firm",
    "wof:placetype":"venue"
},
  "geometry": {"coordinates":[-84.28035300000001,30.472645],"type":"Point"}
}