{
  "type": "Feature",
  "properties": {
    "iso:country":"US",
    "sg:address":"3104 River Villa Way",
    "sg:city":"Melbourne Beach",
    "sg:classifiers":[
        {
            "category":"Wholesale",
            "subcategory":"Non-durable Goods",
            "type":"Manufacturing & Wholesale Goods"
        }
    ],
    "sg:phone":"+1 321 984 7386",
    "sg:postcode":"32951",
    "sg:province":"FL",
    "wof:name":"Busy Bee",
    "wof:placetype":"venue"
},
  "geometry": {"coordinates":[-80.54604399999999,28.031461],"type":"Point"}
}