{
  "type": "Feature",
  "properties": {
    "addr:full":"2995 Burgoyne Ln West Palm Beach FL 33409",
    "addr:housenumber":"2995",
    "addr:postcode":"33409",
    "addr:street":"Burgoyne Ln",
    "iso:country":"US",
    "sg:address":"2995 Burgoyne Ln",
    "sg:city":"West Palm Beach",
    "sg:classifiers":[
        {
            "category":"Real Estate",
            "subcategory":"Real Estate Agent",
            "type":"Services"
        }
    ],
    "sg:phone":"+1 561 684 2363",
    "sg:postcode":"33409",
    "sg:province":"FL",
    "wof:name":"Rece LLC",
    "wof:placetype":"venue"
},
  "geometry": {"coordinates":[-80.100162,26.746643],"type":"Point"}
}