{
  "type": "Feature",
  "properties": {
    "addr:full":"5709 Cove Cir Naples FL 34119",
    "addr:housenumber":"5709",
    "addr:postcode":"34119",
    "addr:street":"Cove Cir",
    "iso:country":"US",
    "sg:address":"5709 Cove Cir",
    "sg:city":"Naples",
    "sg:classifiers":[
        {
            "category":"Professional",
            "subcategory":"Management & Consulting",
            "type":"Services"
        }
    ],
    "sg:phone":"+1 239 591 8577",
    "sg:postcode":"34119",
    "sg:province":"FL",
    "sg:tags":[
        "marketing",
        "program"
    ],
    "wof:name":"R-Van Marketing",
    "wof:placetype":"venue"
},
  "geometry": {"coordinates":[-81.72004099999999,26.249128],"type":"Point"}
}