{
  "type": "Feature",
  "properties": {
    "iso:country":"US",
    "sg:address":"5911 17th St E",
    "sg:city":"Bradenton",
    "sg:classifiers":[
        {
            "category":"Building & Trades",
            "subcategory":"Construction",
            "type":"Services"
        }
    ],
    "sg:phone":"+1 941 758 1240",
    "sg:postcode":"34203",
    "sg:province":"FL",
    "sg:tags":[
        "clearing",
        "land",
        "leveling"
    ],
    "wof:name":"Bradenton Land Clearing",
    "wof:placetype":"venue"
},
  "geometry": {"coordinates":[-82.543477,27.435108],"type":"Point"}
}