{
  "type": "Feature",
  "properties": {
    "addr:full":"1581 W Gulf To Lake Hwy Lecanto FL 34461",
    "addr:housenumber":"1581",
    "addr:postcode":"34461",
    "addr:street":"W Gulf To Lake Hwy",
    "iso:country":"US",
    "sg:address":"1581 W Gulf To Lake Hwy",
    "sg:city":"Lecanto",
    "sg:phone":"+1 866 302 7433",
    "sg:postcode":"34461",
    "sg:province":"FL",
    "sg:website":"http://www.citruscyclecenter.com",
    "wof:name":"Citrus Cycle Center",
    "wof:placetype":"venue"
},
  "geometry": {"coordinates":[-82.461066,28.852081],"type":"Point"}
}