{
  "type": "Feature",
  "properties": {
    "iso:country":"US",
    "sg:address":"735 Dodecanese Blvd",
    "sg:city":"Tarpon Springs",
    "sg:classifiers":[
        {
            "category":"Restaurant",
            "type":"Food & Drink"
        }
    ],
    "sg:menulink":"http://www.allmenus.com/fl/tarpon-springs/33668-mamas-greek-cuisine/menu/",
    "sg:phone":"+1 727 944 2888",
    "sg:postcode":"34689",
    "sg:province":"FL",
    "sg:tags":[
        "greek"
    ],
    "wof:name":"Mama's Greek Cuisine",
    "wof:placetype":"venue"
},
  "geometry": {"coordinates":[-82.76092300000001,28.155613],"type":"Point"}
}