{
  "type": "Feature",
  "properties": {
    "iso:country":"US",
    "sg:address":"1948 SW 8th St",
    "sg:city":"Miami",
    "sg:classifiers":[
        {
            "category":"Food & Beverages",
            "subcategory":"Groceries & Convenience Stores",
            "type":"Retail Goods"
        }
    ],
    "sg:phone":"+1 305 649 6434",
    "sg:postcode":"33135",
    "sg:province":"FL",
    "wof:name":"Kevin Dollar Store",
    "wof:placetype":"venue"
},
  "geometry": {"coordinates":[-80.22736399999999,25.765505],"type":"Point"}
}