{
  "type": "Feature",
  "properties": {
    "addr:full":"609 W Robertson St Brandon FL 33511",
    "addr:housenumber":"609",
    "addr:postcode":"33511",
    "addr:street":"W Robertson St",
    "iso:country":"US",
    "sg:address":"609 W Robertson St",
    "sg:city":"Brandon",
    "sg:classifiers":[
        {
            "category":"Retail",
            "subcategory":"Auto Repair",
            "type":"Services"
        }
    ],
    "sg:phone":"+1 813 681 3755",
    "sg:postcode":"33511",
    "sg:province":"FL",
    "sg:website":"http://midas.com",
    "wof:name":"Midas Auto Svc Experts",
    "wof:placetype":"venue"
},
  "geometry": {"coordinates":[-82.29262,27.935865],"type":"Point"}
}