{
  "type": "Feature",
  "properties": {
    "iso:country":"US",
    "sg:address":"5760 22nd Ave NW",
    "sg:city":"Naples",
    "sg:classifiers":[
        {
            "category":"Professional",
            "type":"Services"
        }
    ],
    "sg:phone":"+1 239 598 4758",
    "sg:postcode":"34119",
    "sg:province":"FL",
    "wof:name":"Vivian J Skala House Watching",
    "wof:placetype":"venue"
},
  "geometry": {"coordinates":[-81.724993,26.26809],"type":"Point"}
}