{
  "type": "Feature",
  "properties": {
    "iso:country":"US",
    "sg:address":"1106 E Colonial Dr",
    "sg:city":"Orlando",
    "sg:classifiers":[
        {
            "category":"Restaurant",
            "type":"Food & Drink"
        }
    ],
    "sg:menulink":"http://www.allmenus.com/fl/orlando/30244-little-saigon-restaurant/menu/",
    "sg:phone":"+1 407 423 8539",
    "sg:postcode":"32803",
    "sg:province":"FL",
    "sg:tags":[
        "asian",
        "vietnamese"
    ],
    "wof:name":"Little Saigon Restaurant",
    "wof:placetype":"venue"
},
  "geometry": {"coordinates":[-81.36534,28.553173],"type":"Point"}
}