{
  "type": "Feature",
  "properties": {
    "iso:country":"US",
    "sg:address":"1210 Capital Cir SE",
    "sg:city":"Tallahassee",
    "sg:classifiers":[
        {
            "category":"Insurance",
            "subcategory":"Insurance Agent",
            "type":"Services"
        },
        {
            "category":"Insurance",
            "subcategory":"Hazard Insurance",
            "type":"Services"
        }
    ],
    "sg:phone":"+1 850 270 0383",
    "sg:postcode":"32301",
    "sg:province":"FL",
    "sg:tags":[
        "auto",
        "motorcycle"
    ],
    "sg:website":"http://www.firstacceptancecorp.com/Locations.aspx",
    "wof:name":"Acceptance Auto Insurance- Tallahassee",
    "wof:placetype":"venue"
},
  "geometry": {"coordinates":[-84.22678999999999,30.430899],"type":"Point"}
}