{
  "type": "Feature",
  "properties": {
    "iso:country":"US",
    "sg:address":"2138 Miracle Mile Plz",
    "sg:city":"Vero Beach",
    "sg:classifiers":[
        {
            "category":"Restaurant",
            "type":"Food & Drink"
        }
    ],
    "sg:phone":"+1 772 778 0717",
    "sg:postcode":"32960",
    "sg:province":"FL",
    "sg:tags":[
        "parlor",
        "ice",
        "cream"
    ],
    "wof:name":"Baskin-Robbins",
    "wof:placetype":"venue"
},
  "geometry": {"coordinates":[-80.38348499999999,27.64001],"type":"Point"}
}