{
  "type": "Feature",
  "properties": {
    "iso:country":"US",
    "sg:address":"4809 W Atlantic Ave",
    "sg:city":"Delray Beach",
    "sg:classifiers":[
        {
            "category":"Cinema",
            "subcategory":"Movie Theater",
            "type":"Entertainment"
        }
    ],
    "sg:phone":"+1 561 499 9022",
    "sg:postcode":"33445",
    "sg:province":"FL",
    "wof:name":"Delray Square Cinemas",
    "wof:placetype":"venue"
},
  "geometry": {"coordinates":[-80.119193,26.457923],"type":"Point"}
}