{
  "type": "Feature",
  "properties": {
    "iso:country":"US",
    "sg:address":"142 Palm Coast Pkwy NE",
    "sg:city":"Palm Coast",
    "sg:classifiers":[
        {
            "category":"Real Estate",
            "subcategory":"Real Estate Agent",
            "type":"Services"
        }
    ],
    "sg:phone":"+1 386 445 5595",
    "sg:postcode":"32137",
    "sg:province":"FL",
    "sg:website":"www.adamscameron.com",
    "wof:name":"Adams Cameron & Co",
    "wof:placetype":"venue"
},
  "geometry": {"coordinates":[-81.192742,29.564565],"type":"Point"}
}