{
  "type": "Feature",
  "properties": {
    "iso:country":"US",
    "sg:address":"13651 Jonquil Pl",
    "sg:city":"Wellington",
    "sg:classifiers":[
        {
            "category":"Home & Garden",
            "subcategory":"Furniture",
            "type":"Retail Goods"
        }
    ],
    "sg:phone":"+1 561 383 8196",
    "sg:postcode":"33414",
    "sg:province":"FL",
    "sg:tags":[
        "store"
    ],
    "wof:name":"Jeksa Investments Inc",
    "wof:placetype":"venue"
},
  "geometry": {"coordinates":[-80.262427,26.667397],"type":"Point"}
}