{
  "type": "Feature",
  "properties": {
    "addr:full":"5558 Park Blvd Pinellas Park FL 33781",
    "addr:housenumber":"5558",
    "addr:postcode":"33781",
    "addr:street":"Park Blvd",
    "iso:country":"US",
    "sg:address":"5558 Park Blvd",
    "sg:city":"Pinellas Park",
    "sg:classifiers":[
        {
            "category":"Personal",
            "subcategory":"Beauty Salon",
            "type":"Services"
        }
    ],
    "sg:phone":"+1 727 548 7566",
    "sg:postcode":"33781",
    "sg:province":"FL",
    "sg:tags":[
        "school"
    ],
    "wof:name":"Imperial School Of Permanent",
    "wof:placetype":"venue"
},
  "geometry": {"coordinates":[-82.709467,27.83912],"type":"Point"}
}