{
  "type": "Feature",
  "properties": {
    "iso:country":"US",
    "sg:address":"2113 W Aileen St",
    "sg:city":"Tampa",
    "sg:classifiers":[
        {
            "category":"Building & Trades",
            "subcategory":"Construction",
            "type":"Services"
        }
    ],
    "sg:phone":"+1 813 874 7568",
    "sg:postcode":"33607",
    "sg:province":"FL",
    "sg:tags":[
        "residential"
    ],
    "wof:name":"CDI Construction",
    "wof:placetype":"venue"
},
  "geometry": {"coordinates":[-82.482698,27.968223],"type":"Point"}
}