{
  "type": "Feature",
  "properties": {
    "iso:country":"US",
    "sg:address":"286 NW 29th St",
    "sg:city":"Miami",
    "sg:classifiers":[
        {
            "category":"Banks & Credit Unions",
            "subcategory":"Bank",
            "type":"Services"
        }
    ],
    "sg:phone":"+1 305 576 2252",
    "sg:postcode":"33127",
    "sg:province":"FL",
    "sg:tags":[
        "broker",
        "foreign",
        "dealer",
        "exchange"
    ],
    "wof:name":"Intercredit Inc",
    "wof:placetype":"venue"
},
  "geometry": {"coordinates":[-80.19962099999999,25.803769],"type":"Point"}
}