{
  "type": "Feature",
  "properties": {
    "addr:full":"15248 S Tamiami Trl Ste 150 Fort Myers FL 33908",
    "addr:housenumber":"15248",
    "addr:postcode":"myers;33908",
    "addr:street":"S Tamiami Trl Ste 150",
    "iso:country":"US",
    "sg:address":"15248 S Tamiami Trl Ste 150",
    "sg:city":"Fort Myers",
    "sg:classifiers":[
        {
            "category":"Shopping",
            "subcategory":"Bicycles & Sporting Goods",
            "type":"Retail Goods"
        }
    ],
    "sg:phone":"+1 239 437 0373",
    "sg:postcode":"33908",
    "sg:province":"FL",
    "sg:tags":[
        "bike"
    ],
    "wof:name":"Aj Barnes Bicycle Emporium",
    "wof:placetype":"venue"
},
  "geometry": {"coordinates":[-81.869499,26.521299],"type":"Point"}
}