{
  "type": "Feature",
  "properties": {
    "iso:country":"US",
    "sg:address":"2025 N Dover Rd",
    "sg:city":"Dover",
    "sg:classifiers":[
        {
            "category":"Food & Beverages",
            "subcategory":"Fruits & Vegetables",
            "type":"Retail Goods"
        }
    ],
    "sg:phone":"+1 813 659 1965",
    "sg:postcode":"33527",
    "sg:province":"FL",
    "sg:tags":[
        "produce"
    ],
    "wof:name":"JMB Brothers Inc",
    "wof:placetype":"venue"
},
  "geometry": {"coordinates":[-82.21962499999999,27.968255],"type":"Point"}
}