{
  "type": "Feature",
  "properties": {
    "addr:full":"307 E Kennedy Blvd Maitland FL 32751",
    "addr:housenumber":"307",
    "addr:postcode":"32751",
    "addr:street":"E Kennedy Blvd",
    "iso:country":"US",
    "sg:address":"307 E Kennedy Blvd",
    "sg:city":"Maitland",
    "sg:classifiers":[
        {
            "category":"Government",
            "subcategory":"Office",
            "type":"Public Place"
        }
    ],
    "sg:phone":"+1 407 599 0350",
    "sg:postcode":"32751",
    "sg:province":"FL",
    "sg:tags":[
        "county"
    ],
    "wof:name":"Orange County Government",
    "wof:placetype":"venue"
},
  "geometry": {"coordinates":[-81.381834,28.618402],"type":"Point"}
}