{
  "type": "Feature",
  "properties": {
    "iso:country":"US",
    "sg:address":"1701 NE 5th Ave",
    "sg:city":"Pompano Beach",
    "sg:classifiers":[
        {
            "category":"Professional",
            "subcategory":"Credit Reporting & Collection",
            "type":"Services"
        }
    ],
    "sg:phone":"+1 954 781 1503",
    "sg:postcode":"33060",
    "sg:province":"FL",
    "wof:name":"McCabe Smith Reynolds & Assoc",
    "wof:placetype":"venue"
},
  "geometry": {"coordinates":[-80.116991,26.25766],"type":"Point"}
}