{
  "type": "Feature",
  "properties": {
    "addr:full":"120 NW 14th St Pompano Beach FL 33060",
    "addr:housenumber":"120",
    "addr:postcode":"33060",
    "addr:street":"Nw 14Th St",
    "iso:country":"US",
    "sg:address":"120 NW 14th St",
    "sg:city":"Pompano Beach",
    "sg:classifiers":[
        {
            "category":"Professional",
            "subcategory":"Business Services",
            "type":"Services"
        }
    ],
    "sg:phone":"+1 954 658 0498",
    "sg:postcode":"33060",
    "sg:province":"FL",
    "sg:tags":[
        "pool",
        "swimming"
    ],
    "wof:name":"Complete Pool Resurfacing",
    "wof:placetype":"venue"
},
  "geometry": {"coordinates":[-80.123544,26.245002],"type":"Point"}
}