{
  "type": "Feature",
  "properties": {
    "iso:country":"US",
    "sg:address":"1735 N Treasure Dr",
    "sg:city":"North Bay Village",
    "sg:classifiers":[
        {
            "category":"Health Services",
            "subcategory":"Health Practitioner",
            "type":"Services"
        }
    ],
    "sg:phone":"+1 305 865 2383",
    "sg:postcode":"33141",
    "sg:province":"FL",
    "sg:tags":[
        "therapy",
        "physical"
    ],
    "wof:name":"Restrepo Margarita Rpt",
    "wof:placetype":"venue"
},
  "geometry": {"coordinates":[-80.1503,25.847477],"type":"Point"}
}