{
  "type": "Feature",
  "properties": {
    "iso:country":"US",
    "sg:address":"5425 Gulfport Blvd S",
    "sg:city":"Gulfport",
    "sg:classifiers":[
        {
            "category":"Organizations",
            "subcategory":"Religious Organization",
            "type":"Services"
        }
    ],
    "sg:phone":"+1 727 322 5650",
    "sg:postcode":"33707",
    "sg:province":"FL",
    "sg:tags":[
        "church"
    ],
    "wof:name":"Church Of Jesus Christ",
    "wof:placetype":"venue"
},
  "geometry": {"coordinates":[-82.70708399999999,27.748341],"type":"Point"}
}