{
  "type": "Feature",
  "properties": {
    "iso:country":"US",
    "sg:address":"5397 Timuquana Rd",
    "sg:city":"Jacksonville",
    "sg:classifiers":[
        {
            "category":"Autos & Motor Vehicles",
            "subcategory":"Fuel & Gas Station",
            "type":"Retail Goods"
        }
    ],
    "sg:phone":"+1 904 779 9312",
    "sg:postcode":"32210",
    "sg:province":"FL",
    "sg:tags":[
        "convenience",
        "station",
        "store"
    ],
    "wof:name":"Sunshine Food Mart 71",
    "wof:placetype":"venue"
},
  "geometry": {"coordinates":[-81.72083600000001,30.247512],"type":"Point"}
}