{
  "type": "Feature",
  "properties": {
    "addr:full":"11700 NW 100th Rd Miami FL 33178",
    "addr:housenumber":"11700",
    "addr:postcode":"33178",
    "addr:street":"Nw 100Th Rd",
    "iso:country":"US",
    "sg:address":"11700 NW 100th Rd",
    "sg:city":"Miami",
    "sg:classifiers":[
        {
            "category":"Freight",
            "type":"Transportation"
        }
    ],
    "sg:phone":"+1 305 888 1600",
    "sg:postcode":"33178",
    "sg:province":"FL",
    "sg:tags":[
        "forwarders"
    ],
    "wof:name":"USFreightways",
    "wof:placetype":"venue"
},
  "geometry": {"coordinates":[-80.362357,25.875521],"type":"Point"}
}