{
  "type": "Feature",
  "properties": {
    "iso:country":"US",
    "sg:address":"2421 Biscayne Blvd",
    "sg:city":"Miami",
    "sg:classifiers":[
        {
            "category":"Banks & Credit Unions",
            "subcategory":"Financial Services",
            "type":"Services"
        }
    ],
    "sg:phone":"+1 305 573 9820",
    "sg:postcode":"33137",
    "sg:province":"FL",
    "sg:tags":[
        "cashing",
        "money",
        "check",
        "order"
    ],
    "wof:name":"Tip Top Check Cashing",
    "wof:placetype":"venue"
},
  "geometry": {"coordinates":[-80.18914700000001,25.800351],"type":"Point"}
}