{
  "type": "Feature",
  "properties": {
    "addr:full":"6758 Conroy Windermere Rd Orlando FL 32835",
    "addr:housenumber":"6758",
    "addr:postcode":"32835",
    "addr:street":"Conroy Windermere Rd",
    "iso:country":"US",
    "sg:address":"6758 Conroy Windermere Rd",
    "sg:city":"Orlando",
    "sg:classifiers":[
        {
            "category":"Food & Beverages",
            "subcategory":"Groceries & Convenience Stores",
            "type":"Retail Goods"
        }
    ],
    "sg:phone":"+1 407 294 6673",
    "sg:postcode":"32835",
    "sg:province":"FL",
    "wof:name":"7-Eleven",
    "wof:placetype":"venue"
},
  "geometry": {"coordinates":[-81.47520799999999,28.493661],"type":"Point"}
}