{
  "type": "Feature",
  "properties": {
    "addr:full":"3909 N Andrews Ave Oakland Park FL 33309",
    "addr:housenumber":"3909",
    "addr:postcode":"33309",
    "addr:street":"N Andrews Ave",
    "iso:country":"US",
    "sg:address":"3909 N Andrews Ave",
    "sg:city":"Oakland Park",
    "sg:classifiers":[
        {
            "category":"Health Services",
            "subcategory":"Doctor",
            "type":"Services"
        }
    ],
    "sg:phone":"+1 954 561 6675",
    "sg:postcode":"33309",
    "sg:province":"FL",
    "sg:tags":[
        "dentist"
    ],
    "wof:name":"Summit Dental",
    "wof:placetype":"venue"
},
  "geometry": {"coordinates":[-80.146793,26.175724],"type":"Point"}
}