{
  "type": "Feature",
  "properties": {
    "addr:full":"2363 SE Ocean Blvd Stuart FL 34996",
    "addr:housenumber":"2363",
    "addr:postcode":"34996",
    "addr:street":"Se Ocean Blvd",
    "iso:country":"US",
    "sg:address":"2363 SE Ocean Blvd",
    "sg:city":"Stuart",
    "sg:classifiers":[
        {
            "category":"Banks & Credit Unions",
            "subcategory":"Investment Brokerage",
            "type":"Services"
        }
    ],
    "sg:phone":"+1 772 219 0523",
    "sg:postcode":"34996",
    "sg:province":"FL",
    "sg:tags":[
        "advisory",
        "financial"
    ],
    "wof:name":"Financial Resource Group",
    "wof:placetype":"venue"
},
  "geometry": {"coordinates":[-80.220169,27.196623],"type":"Point"}
}