{
  "type": "Feature",
  "properties": {
    "iso:country":"US",
    "sg:address":"7425 N University Dr",
    "sg:city":"Fort Lauderdale",
    "sg:classifiers":[
        {
            "category":"Organizations",
            "subcategory":"Non-profit Organization",
            "type":"Services"
        },
        {
            "category":"Health Services",
            "subcategory":"Hospital",
            "type":"Services"
        }
    ],
    "sg:phone":"+1 954 722 9933",
    "sg:postcode":"33321",
    "sg:province":"FL",
    "sg:tags":[
        "info",
        "psychiatric",
        "abuse",
        "drug",
        "addiction",
        "treatment"
    ],
    "wof:name":"University Pavilion Hospital",
    "wof:placetype":"venue"
},
  "geometry": {"coordinates":[-80.252504,26.21362],"type":"Point"}
}