{
  "type": "Feature",
  "properties": {
    "addr:full":"283 Sterling Hill Dr Jacksonville FL 32225",
    "addr:housenumber":"283",
    "addr:postcode":"32225",
    "addr:street":"Sterling Hill Dr",
    "iso:country":"US",
    "sg:address":"283 Sterling Hill Dr",
    "sg:city":"Jacksonville",
    "sg:classifiers":[
        {
            "category":"Building & Trades",
            "subcategory":"Landscaping Services",
            "type":"Services"
        }
    ],
    "sg:phone":"+1 904 221 2334",
    "sg:postcode":"32225",
    "sg:province":"FL",
    "sg:tags":[
        "lawn",
        "maintenance",
        "grounds"
    ],
    "wof:name":"Bullseye Environmental Svc Inc",
    "wof:placetype":"venue"
},
  "geometry": {"coordinates":[-81.47922199999999,30.323758],"type":"Point"}
}