{
  "type": "Feature",
  "properties": {
    "addr:full":"12700 Automobile Blvd Clearwater FL 33762",
    "addr:postcode":"33762",
    "addr:street":"Automobile Blvd",
    "iso:country":"US",
    "sg:address":"12700 Automobile Blvd",
    "sg:city":"Clearwater",
    "sg:classifiers":[
        {
            "category":"Building & Trades",
            "subcategory":"Construction",
            "type":"Services"
        },
        {
            "category":"Wholesale",
            "subcategory":"Durable Goods & Equipment",
            "type":"Manufacturing & Wholesale Goods"
        }
    ],
    "sg:phone":"+1 727 573 0918",
    "sg:postcode":"33762",
    "sg:province":"FL",
    "sg:tags":[
        "house",
        "importer"
    ],
    "sg:website":"www.sundektampabay.com",
    "wof:name":"Sundek By Artistic Surfaces",
    "wof:placetype":"venue"
},
  "geometry": {"coordinates":[-82.696341,27.886979],"type":"Point"}
}