{
  "type": "Feature",
  "properties": {
    "iso:country":"US",
    "sg:address":"7808 Wiles Rd",
    "sg:city":"Pompano Beach",
    "sg:classifiers":[
        {
            "category":"Restaurant",
            "type":"Food & Drink"
        }
    ],
    "sg:menulink":"http://www.allmenus.com/fl/margate/71259-pizza-hut/menu/",
    "sg:phone":"+1 954 345 8333",
    "sg:postcode":"33067",
    "sg:province":"FL",
    "sg:tags":[
        "american",
        "pizza"
    ],
    "wof:name":"Pizza Hut",
    "wof:placetype":"venue"
},
  "geometry": {"coordinates":[-80.230107,26.286605],"type":"Point"}
}