{
  "type": "Feature",
  "properties": {
    "addr:full":"2119 E Fort King St Ocala FL 34471",
    "addr:housenumber":"2119",
    "addr:postcode":"34471",
    "addr:street":"E Fort King St",
    "iso:country":"US",
    "sg:address":"2119 E Fort King St",
    "sg:city":"Ocala",
    "sg:classifiers":[
        {
            "category":"Real Estate",
            "subcategory":"Real Estate Services",
            "type":"Services"
        },
        {
            "category":"Banks & Credit Unions",
            "subcategory":"Bank",
            "type":"Services"
        },
        {
            "category":"Banks & Credit Unions",
            "subcategory":"Financial Services",
            "type":"Services"
        }
    ],
    "sg:phone":"+1 352 369 5166",
    "sg:postcode":"34471",
    "sg:province":"FL",
    "sg:tags":[
        "loan"
    ],
    "wof:name":"A Aaccessible Mortgage",
    "wof:placetype":"venue"
},
  "geometry": {"coordinates":[-82.10945,29.185329],"type":"Point"}
}