{
  "type": "Feature",
  "properties": {
    "iso:country":"US",
    "sg:address":"276 Ridgedale Dr",
    "sg:city":"Lakeland",
    "sg:classifiers":[
        {
            "category":"Real Estate",
            "subcategory":"Real Estate Operator",
            "type":"Services"
        }
    ],
    "sg:phone":"+1 863 853 1833",
    "sg:postcode":"33809",
    "sg:province":"FL",
    "sg:tags":[
        "property",
        "lessor"
    ],
    "wof:name":"Crowe Properties",
    "wof:placetype":"venue"
},
  "geometry": {"coordinates":[-81.953001,28.144266],"type":"Point"}
}