{
  "type": "Feature",
  "properties": {
    "addr:full":"2985 Langley Ave Pensacola FL 32504",
    "addr:housenumber":"2985",
    "addr:postcode":"32504",
    "addr:street":"Langley Ave",
    "iso:country":"US",
    "sg:address":"2985 Langley Ave",
    "sg:city":"Pensacola",
    "sg:classifiers":[
        {
            "category":"Health Services",
            "subcategory":"Doctor",
            "type":"Services"
        }
    ],
    "sg:phone":"+1 850 478 0391",
    "sg:postcode":"32504",
    "sg:province":"FL",
    "wof:name":"Sirmans Alan G DDS PA",
    "wof:placetype":"venue"
},
  "geometry": {"coordinates":[-87.189114,30.48774],"type":"Point"}
}