{
  "type": "Feature",
  "properties": {
    "addr:full":"4110 Laguna St Coral Gables FL 33146",
    "addr:housenumber":"4110",
    "addr:postcode":"33146",
    "addr:street":"Laguna St",
    "iso:country":"US",
    "sg:address":"4110 Laguna St",
    "sg:city":"Coral Gables",
    "sg:classifiers":[
        {
            "category":"Shopping",
            "subcategory":"Stationery & Office Supplies",
            "type":"Retail Goods"
        }
    ],
    "sg:phone":"+1 305 445 3505",
    "sg:postcode":"33146",
    "sg:province":"FL",
    "sg:tags":[
        "equipment"
    ],
    "wof:name":"Camilo Muebles Inc",
    "wof:placetype":"venue"
},
  "geometry": {"coordinates":[-80.26129899999999,25.7335],"type":"Point"}
}