{
  "type": "Feature",
  "properties": {
    "iso:country":"US",
    "sg:address":"2507 W 70th St",
    "sg:city":"Hialeah",
    "sg:classifiers":[
        {
            "category":"Health Services",
            "subcategory":"Medical Lab",
            "type":"Services"
        }
    ],
    "sg:phone":"+1 305 822 8561",
    "sg:postcode":"33016",
    "sg:province":"FL",
    "sg:tags":[
        "laboratory"
    ],
    "wof:name":"Advanced Imaging Services Inc",
    "wof:placetype":"venue"
},
  "geometry": {"coordinates":[-80.336623,25.886172],"type":"Point"}
}