{
  "type": "Feature",
  "properties": {
    "addr:full":"3615 S Florida Ave Lakeland FL 33803",
    "addr:housenumber":"3615",
    "addr:postcode":"33803",
    "addr:street":"S Florida Ave",
    "iso:country":"US",
    "sg:address":"3615 S Florida Ave",
    "sg:city":"Lakeland",
    "sg:classifiers":[
        {
            "category":"Shopping",
            "subcategory":"Shoes",
            "type":"Retail Goods"
        }
    ],
    "sg:phone":"+1 863 648 2817",
    "sg:postcode":"33803",
    "sg:province":"FL",
    "wof:name":"Nine West",
    "wof:placetype":"venue"
},
  "geometry": {"coordinates":[-81.957165,27.998672],"type":"Point"}
}