{
  "type": "Feature",
  "properties": {
    "iso:country":"US",
    "sg:address":"Village of Merrick Park Mall 320 San Lorenzo Ave Ste 1225",
    "sg:city":"Coral Gables",
    "sg:classifiers":[
        {
            "category":"Shopping",
            "subcategory":"Clothing, Apparel, & Fashions",
            "type":"Retail Goods"
        }
    ],
    "sg:phone":"+1 305 442 8330",
    "sg:postcode":"33146",
    "sg:province":"FL",
    "sg:tags":[
        "children's",
        "clothing"
    ],
    "sg:website":"www.bognarpiccolini.com",
    "wof:name":"Bognar and Piccolini",
    "wof:placetype":"venue"
},
  "geometry": {"coordinates":[-80.261118,25.732148],"type":"Point"}
}