{
  "type": "Feature",
  "properties": {
    "iso:country":"US",
    "sg:address":"13952 SW 151st Ln",
    "sg:city":"Miami",
    "sg:classifiers":[
        {
            "category":"Building & Trades",
            "subcategory":"Construction",
            "type":"Services"
        }
    ],
    "sg:phone":"+1 305 300 9131",
    "sg:postcode":"33186",
    "sg:province":"FL",
    "sg:tags":[
        "roofing",
        "industrial",
        "contractors-commercial",
        "contractor"
    ],
    "wof:name":"Meraz Roofing Corp.",
    "wof:placetype":"venue"
},
  "geometry": {"coordinates":[-80.41939600000001,25.626614],"type":"Point"}
}