{
  "type": "Feature",
  "properties": {
    "iso:country":"US",
    "sg:address":"14807 N Florida Ave",
    "sg:city":"Tampa",
    "sg:classifiers":[
        {
            "category":"Professional",
            "subcategory":"Business Services",
            "type":"Services"
        },
        {
            "category":"Manufacturing",
            "subcategory":"Apparel",
            "type":"Manufacturing & Wholesale Goods"
        }
    ],
    "sg:phone":"+1 813 264 4804",
    "sg:postcode":"33613",
    "sg:province":"FL",
    "sg:tags":[
        "computerized",
        "embroidery"
    ],
    "wof:name":"We'Re In Stitches",
    "wof:placetype":"venue"
},
  "geometry": {"coordinates":[-82.459501,28.084673],"type":"Point"}
}