{
  "type": "Feature",
  "properties": {
    "iso:country":"US",
    "sg:address":"301 W 7th St",
    "sg:city":"Sanford",
    "sg:classifiers":[
        {
            "category":"Museum",
            "type":"Entertainment"
        }
    ],
    "sg:phone":"+1 407 320 0520",
    "sg:postcode":"32771",
    "sg:province":"FL",
    "sg:tags":[
        "gallery"
    ],
    "wof:name":"Student Museum",
    "wof:placetype":"venue"
},
  "geometry": {"coordinates":[-81.27109299999999,28.80623],"type":"Point"}
}