{
  "type": "Feature",
  "properties": {
    "addr:full":"499 SW Dairy Rd Port Saint Lucie FL 34953",
    "addr:housenumber":"499",
    "addr:postcode":"34953",
    "addr:street":"Sw Dairy Rd",
    "iso:country":"US",
    "sg:address":"499 SW Dairy Rd",
    "sg:city":"Port Saint Lucie",
    "sg:classifiers":[
        {
            "category":"Building & Trades",
            "subcategory":"Construction",
            "type":"Services"
        }
    ],
    "sg:phone":"+1 772 879 2027",
    "sg:postcode":"34953",
    "sg:province":"FL",
    "sg:tags":[
        "house"
    ],
    "wof:name":"Paulsen & Sons Contracting",
    "wof:placetype":"venue"
},
  "geometry": {"coordinates":[-80.362075,27.262964],"type":"Point"}
}