{
  "type": "Feature",
  "properties": {
    "iso:country":"US",
    "sg:address":"220 71st St",
    "sg:city":"Miami Beach",
    "sg:classifiers":[
        {
            "category":"Education",
            "subcategory":"Special Training",
            "type":"Public Place"
        }
    ],
    "sg:phone":"+1 305 866 6040",
    "sg:postcode":"33141",
    "sg:province":"FL",
    "sg:tags":[
        "instruction",
        "driving"
    ],
    "wof:name":"Advantage Traffic School",
    "wof:placetype":"venue"
},
  "geometry": {"coordinates":[-80.121251,25.856031],"type":"Point"}
}