{
  "type": "Feature",
  "properties": {
    "addr:full":"200 Sandestin Ln Destin FL 32550",
    "addr:housenumber":"200",
    "addr:postcode":"32550",
    "addr:street":"Sandestin Ln",
    "iso:country":"US",
    "sg:address":"200 Sandestin Ln",
    "sg:city":"Destin",
    "sg:classifiers":[
        {
            "category":"Professional",
            "type":"Services"
        }
    ],
    "sg:phone":"+1 850 622 0200",
    "sg:postcode":"32550",
    "sg:province":"FL",
    "sg:tags":[
        "establishment"
    ],
    "wof:name":"Acme Oyster House",
    "wof:placetype":"venue"
},
  "geometry": {"coordinates":[-86.30970600000001,30.379298],"type":"Point"}
}