{
  "type": "Feature",
  "properties": {
    "iso:country":"US",
    "sg:address":"2323 Lakeshore Dr",
    "sg:city":"Mount Dora",
    "sg:classifiers":[
        {
            "category":"Building & Trades",
            "subcategory":"Construction",
            "type":"Services"
        }
    ],
    "sg:phone":"+1 352 735 2433",
    "sg:postcode":"32757",
    "sg:province":"FL",
    "sg:tags":[
        "house"
    ],
    "wof:name":"West Construction Services",
    "wof:placetype":"venue"
},
  "geometry": {"coordinates":[-81.667552,28.805202],"type":"Point"}
}