{
  "type": "Feature",
  "properties": {
    "addr:full":"115 Sunwood Ct Kissimmee FL 34743",
    "addr:housenumber":"115",
    "addr:postcode":"34743",
    "addr:street":"Sunwood Ct",
    "iso:country":"US",
    "sg:address":"115 Sunwood Ct",
    "sg:city":"Kissimmee",
    "sg:classifiers":[
        {
            "category":"Real Estate",
            "subcategory":"Real Estate Agent",
            "type":"Services"
        }
    ],
    "sg:phone":"+1 407 791 8060",
    "sg:postcode":"34743",
    "sg:province":"FL",
    "wof:name":"Damon Robinson Realty",
    "wof:placetype":"venue"
},
  "geometry": {"coordinates":[-81.377893,28.341516],"type":"Point"}
}