{
  "type": "Feature",
  "properties": {
    "iso:country":"US",
    "sg:address":"12385 Rose St",
    "sg:city":"Seminole",
    "sg:classifiers":[
        {
            "category":"Manufacturing",
            "subcategory":"Retail Goods",
            "type":"Manufacturing & Wholesale Goods"
        }
    ],
    "sg:phone":"+1 727 397 9030",
    "sg:postcode":"33772",
    "sg:province":"FL",
    "sg:tags":[
        "apartment",
        "mfg",
        "game",
        "design",
        "real estate",
        "rental",
        "amusement"
    ],
    "wof:name":"Rosetree Gardens Apartments",
    "wof:placetype":"venue"
},
  "geometry": {"coordinates":[-82.810605,27.844493],"type":"Point"}
}