{
  "type": "Feature",
  "properties": {
    "iso:country":"US",
    "sg:address":"2543 Crawfordville Hwy",
    "sg:city":"Crawfordville",
    "sg:classifiers":[
        {
            "category":"Building & Trades",
            "subcategory":"Pest Control",
            "type":"Services"
        }
    ],
    "sg:phone":"+1 850 926 0011",
    "sg:postcode":"32327",
    "sg:province":"FL",
    "wof:name":"Helms Exterminating",
    "wof:placetype":"venue"
},
  "geometry": {"coordinates":[-84.370009,30.196918],"type":"Point"}
}