{
  "type": "Feature",
  "properties": {
    "iso:country":"US",
    "sg:address":"3723 W Palmetto St",
    "sg:city":"Tampa",
    "sg:classifiers":[
        {
            "category":"Retail",
            "subcategory":"Auto Repair",
            "type":"Services"
        }
    ],
    "sg:phone":"+1 813 875 5352",
    "sg:postcode":"33607",
    "sg:province":"FL",
    "sg:tags":[
        "transmission"
    ],
    "wof:name":"Martin's Transmission Svc",
    "wof:placetype":"venue"
},
  "geometry": {"coordinates":[-82.505168,27.962442],"type":"Point"}
}