{
  "type": "Feature",
  "properties": {
    "iso:country":"US",
    "sg:address":"64 Cross Creek Rd",
    "sg:city":"Destin",
    "sg:classifiers":[
        {
            "category":"Arts & Performance",
            "subcategory":"Theater",
            "type":"Entertainment"
        }
    ],
    "sg:phone":"+1 850 654 5855",
    "sg:postcode":"32550",
    "sg:province":"FL",
    "sg:tags":[
        "live",
        "music"
    ],
    "wof:name":"Rick's Sounds",
    "wof:placetype":"venue"
},
  "geometry": {"coordinates":[-86.38222399999999,30.379035],"type":"Point"}
}