{
  "type": "Feature",
  "properties": {
    "addr:full":"4122 Spring Park Rd Jacksonville FL 32207",
    "addr:housenumber":"4122",
    "addr:postcode":"32207",
    "addr:street":"Spring Park Rd",
    "iso:country":"US",
    "sg:address":"4122 Spring Park Rd",
    "sg:city":"Jacksonville",
    "sg:classifiers":[
        {
            "category":"Manufacturing",
            "subcategory":"Printing",
            "type":"Manufacturing & Wholesale Goods"
        }
    ],
    "sg:phone":"+1 904 443 0071",
    "sg:postcode":"32207",
    "sg:province":"FL",
    "sg:tags":[
        "screen"
    ],
    "wof:name":"American Screen Print Inc",
    "wof:placetype":"venue"
},
  "geometry": {"coordinates":[-81.619901,30.283281],"type":"Point"}
}