{
  "type": "Feature",
  "properties": {
    "addr:full":"1555 San Marco Blvd Jacksonville FL 32207",
    "addr:housenumber":"1555",
    "addr:postcode":"32207",
    "addr:street":"San Marco Blvd",
    "iso:country":"US",
    "sg:address":"1555 San Marco Blvd",
    "sg:city":"Jacksonville",
    "sg:classifiers":[
        {
            "category":"Health Services",
            "subcategory":"Health Practitioner",
            "type":"Services"
        }
    ],
    "sg:phone":"+1 904 396 1767",
    "sg:postcode":"32207",
    "sg:province":"FL",
    "wof:name":"Alterntive Mdicine Specialists",
    "wof:placetype":"venue"
},
  "geometry": {"coordinates":[-81.660456,30.309033],"type":"Point"}
}