{
  "type": "Feature",
  "properties": {
    "addr:full":"555 Washington Ave Ste 101 Miami Beach FL 33139",
    "addr:housenumber":"555",
    "addr:postcode":"33139",
    "addr:street":"Washington Ave Ste 101",
    "iso:country":"US",
    "sg:address":"555 Washington Ave Ste 101",
    "sg:city":"Miami Beach",
    "sg:classifiers":[
        {
            "category":"Freight",
            "type":"Transportation"
        },
        {
            "category":"Professional",
            "subcategory":"Printing & Photocopies",
            "type":"Services"
        }
    ],
    "sg:phone":"+1 305 674 4475",
    "sg:postcode":"33139",
    "sg:province":"FL",
    "sg:tags":[
        "shipping"
    ],
    "sg:website":"www.fedex.com/us/office/",
    "wof:name":"FedEx Office Print & Ship Center",
    "wof:placetype":"venue"
},
  "geometry": {"coordinates":[-80.133673,25.775114],"type":"Point"}
}