{
  "type": "Feature",
  "properties": {
    "iso:country":"US",
    "sg:address":"17 N 10th St",
    "sg:city":"Haines City",
    "sg:classifiers":[
        {
            "category":"Real Estate",
            "subcategory":"Real Estate Agent",
            "type":"Services"
        }
    ],
    "sg:phone":"+1 863 421 3400",
    "sg:postcode":"33844",
    "sg:province":"FL",
    "wof:name":"Wheeler Real Estate Services",
    "wof:placetype":"venue"
},
  "geometry": {"coordinates":[-81.623249,28.106922],"type":"Point"}
}