{
  "type": "Feature",
  "properties": {
    "addr:full":"2001 Biscayne Blvd # 3604 Miami FL 33137",
    "addr:housenumber":"2001",
    "addr:postcode":"33137",
    "addr:street":"Biscayne Blvd # 3604",
    "iso:country":"US",
    "sg:address":"2001 Biscayne Blvd # 3604",
    "sg:city":"Miami",
    "sg:classifiers":[
        {
            "category":"Professional",
            "subcategory":"Advertising",
            "type":"Services"
        }
    ],
    "sg:phone":"+1 305 479 4709",
    "sg:postcode":"33137",
    "sg:province":"FL",
    "sg:tags":[
        "marketing",
        "specialty",
        "internet"
    ],
    "wof:name":"Tropical Dimensions Media",
    "wof:placetype":"venue"
},
  "geometry": {"coordinates":[-80.189041,25.79546],"type":"Point"}
}