{
  "type": "Feature",
  "properties": {
    "iso:country":"US",
    "sg:address":"4620 NW 7th St",
    "sg:city":"Miami",
    "sg:classifiers":[
        {
            "category":"Shopping",
            "type":"Retail Goods"
        }
    ],
    "sg:phone":"+1 305 774 7610",
    "sg:postcode":"33126",
    "sg:province":"FL",
    "sg:tags":[
        "orthopedic",
        "appliance"
    ],
    "wof:name":"Advanced Tech Assoc",
    "wof:placetype":"venue"
},
  "geometry": {"coordinates":[-80.27148,25.77863],"type":"Point"}
}