{
  "type": "Feature",
  "properties": {
    "iso:country":"US",
    "sg:address":"4400 Millstone Ct",
    "sg:city":"Jacksonville",
    "sg:classifiers":[
        {
            "category":"Manufacturing",
            "subcategory":"Tools & Machinery",
            "type":"Manufacturing & Wholesale Goods"
        }
    ],
    "sg:phone":"+1 904 260 1678",
    "sg:postcode":"32257",
    "sg:province":"FL",
    "sg:tags":[
        "residential",
        "lighting",
        "fixture",
        "mfg"
    ],
    "wof:name":"After Hours Lighting",
    "wof:placetype":"venue"
},
  "geometry": {"coordinates":[-81.59896999999999,30.175297],"type":"Point"}
}