{
  "type": "Feature",
  "properties": {
    "iso:country":"US",
    "sg:address":"118 Idaho Ave",
    "sg:city":"Lakeland",
    "sg:classifiers":[
        {
            "category":"Professional",
            "subcategory":"Advertising",
            "type":"Services"
        }
    ],
    "sg:phone":"+1 863 667 3264",
    "sg:postcode":"33801",
    "sg:province":"FL",
    "sg:tags":[
        "mail",
        "direct"
    ],
    "wof:name":"Summers Woodby Tracy J",
    "wof:placetype":"venue"
},
  "geometry": {"coordinates":[-81.91245600000001,28.041207],"type":"Point"}
}