{
  "type": "Feature",
  "properties": {
    "addr:full":"10036 Sawgrass Dr E Ponte Vedra Beach FL 32082",
    "addr:housenumber":"10036",
    "addr:postcode":"32082",
    "addr:street":"Sawgrass Dr E",
    "iso:country":"US",
    "sg:address":"10036 Sawgrass Dr E",
    "sg:city":"Ponte Vedra Beach",
    "sg:classifiers":[
        {
            "category":"Organizations",
            "subcategory":"Community Association",
            "type":"Services"
        }
    ],
    "sg:phone":"+1 904 273 9832",
    "sg:postcode":"32082",
    "sg:province":"FL",
    "sg:tags":[
        "consulting",
        "business"
    ],
    "wof:name":"Sawgrass Players Club Assn",
    "wof:placetype":"venue"
},
  "geometry": {"coordinates":[-81.368543,30.188368],"type":"Point"}
}