{
  "type": "Feature",
  "properties": {
    "addr:full":"13313 Menorah Dr Punta Gorda FL 33955",
    "addr:postcode":"13313;33955",
    "addr:street":"Menorah Dr",
    "iso:country":"US",
    "sg:address":"13313 Menorah Dr",
    "sg:city":"Punta Gorda",
    "sg:classifiers":[
        {
            "category":"Building & Trades",
            "subcategory":"Construction",
            "type":"Services"
        }
    ],
    "sg:phone":"+1 941 637 5808",
    "sg:postcode":"33955",
    "sg:province":"FL",
    "sg:tags":[
        "contractor"
    ],
    "wof:name":"Hysell Roofing",
    "wof:placetype":"venue"
},
  "geometry": {"coordinates":[-81.994191,26.834247],"type":"Point"}
}