{
  "type": "Feature",
  "properties": {
    "iso:country":"US",
    "sg:address":"938 NW 135th Ct",
    "sg:city":"Miami",
    "sg:classifiers":[
        {
            "category":"Building & Trades",
            "subcategory":"Landscaping Services",
            "type":"Services"
        }
    ],
    "sg:phone":"+1 305 552 6932",
    "sg:postcode":"33182",
    "sg:province":"FL",
    "sg:tags":[
        "landscape"
    ],
    "wof:name":"Landscape R US Inc",
    "wof:placetype":"venue"
},
  "geometry": {"coordinates":[-80.414119,25.778184],"type":"Point"}
}