{
  "type": "Feature",
  "properties": {
    "iso:country":"US",
    "sg:address":"360 S Central Ave",
    "sg:city":"Lakeland",
    "sg:classifiers":[
        {
            "category":"Professional",
            "subcategory":"Lawyer & Legal Services",
            "type":"Services"
        }
    ],
    "sg:phone":"+1 863 682 3895",
    "sg:postcode":"33815",
    "sg:province":"FL",
    "wof:name":"Delvecchio & Assiociates Inc",
    "wof:placetype":"venue"
},
  "geometry": {"coordinates":[-81.973499,28.041224],"type":"Point"}
}