{
  "type": "Feature",
  "properties": {
    "addr:full":"5462 Central Ave St Petersburg FL 33707",
    "addr:housenumber":"5462",
    "addr:postcode":"33707",
    "addr:street":"Central Ave",
    "iso:country":"US",
    "sg:address":"5462 Central Ave",
    "sg:city":"St Petersburg",
    "sg:classifiers":[
        {
            "category":"Professional",
            "subcategory":"Lawyer & Legal Services",
            "type":"Services"
        }
    ],
    "sg:phone":"+1 727 323 7717",
    "sg:postcode":"33707",
    "sg:province":"FL",
    "sg:tags":[
        "attorney"
    ],
    "wof:name":"Andrew L Barauskas",
    "wof:placetype":"venue"
},
  "geometry": {"coordinates":[-82.707301,27.770838],"type":"Point"}
}