{
  "type": "Feature",
  "properties": {
    "iso:country":"US",
    "sg:address":"2242 NE 25th St",
    "sg:city":"Pompano Beach",
    "sg:classifiers":[
        {
            "category":"Professional",
            "type":"Services"
        }
    ],
    "sg:phone":"+1 954 942 8378",
    "sg:postcode":"33064",
    "sg:province":"FL",
    "wof:name":"David C Farber Inc",
    "wof:placetype":"venue"
},
  "geometry": {"coordinates":[-80.089671,26.262338],"type":"Point"}
}