{
  "type": "Feature",
  "properties": {
    "addr:full":"343 Devon Pl Lake Mary FL 32746",
    "addr:housenumber":"343",
    "addr:postcode":"32746",
    "addr:street":"Devon Pl",
    "iso:country":"US",
    "sg:address":"343 Devon Pl",
    "sg:city":"Lake Mary",
    "sg:classifiers":[
        {
            "category":"Freight",
            "type":"Transportation"
        }
    ],
    "sg:phone":"+1 407 829 6424",
    "sg:postcode":"32746",
    "sg:province":"FL",
    "wof:name":"Sbh Enterprises Inc",
    "wof:placetype":"venue"
},
  "geometry": {"coordinates":[-81.368571,28.767735],"type":"Point"}
}