{
  "type": "Feature",
  "properties": {
    "iso:country":"US",
    "sg:address":"6399 S Tex Pt",
    "sg:city":"Homosassa",
    "sg:classifiers":[
        {
            "category":"Manufacturing",
            "subcategory":"Motor Vehicles & Parts",
            "type":"Manufacturing & Wholesale Goods"
        }
    ],
    "sg:phone":"+1 352 628 4199",
    "sg:postcode":"34448",
    "sg:province":"FL",
    "sg:tags":[
        "automobile",
        "supply"
    ],
    "wof:name":"JDMADDICTIONS.COM",
    "wof:placetype":"venue"
},
  "geometry": {"coordinates":[-82.557344,28.770526],"type":"Point"}
}