{
  "type": "Feature",
  "properties": {
    "addr:full":"120 E Call St Starke FL 32091",
    "addr:housenumber":"120",
    "addr:postcode":"32091",
    "addr:street":"E Call St",
    "iso:country":"US",
    "sg:address":"120 E Call St",
    "sg:city":"Starke",
    "sg:classifiers":[
        {
            "category":"Banks & Credit Unions",
            "subcategory":"Investment Brokerage",
            "type":"Services"
        }
    ],
    "sg:phone":"+1 904 966 0002",
    "sg:postcode":"32091",
    "sg:province":"FL",
    "sg:tags":[
        "advisory"
    ],
    "wof:name":"American Express",
    "wof:placetype":"venue"
},
  "geometry": {"coordinates":[-82.109624,29.944001],"type":"Point"}
}