{
  "type": "Feature",
  "properties": {
    "iso:country":"US",
    "sg:address":"1302 Ibis Dr",
    "sg:city":"Englewood",
    "sg:classifiers":[
        {
            "category":"Building & Trades",
            "subcategory":"Landscaping Services",
            "type":"Services"
        }
    ],
    "sg:phone":"+1 941 475 0850",
    "sg:postcode":"34224",
    "sg:province":"FL",
    "wof:name":"David Hills Lawncare",
    "wof:placetype":"venue"
},
  "geometry": {"coordinates":[-82.320615,26.942202],"type":"Point"}
}