{
  "type": "Feature",
  "properties": {
    "iso:country":"US",
    "sg:address":"5301 Lookout Pass",
    "sg:city":"Zephyrhills",
    "sg:classifiers":[
        {
            "category":"Professional",
            "type":"Services"
        }
    ],
    "sg:phone":"+1 813 929 1500",
    "sg:postcode":"33544",
    "sg:province":"FL",
    "wof:name":"Red Door Inc",
    "wof:placetype":"venue"
},
  "geometry": {"coordinates":[-82.38721099999999,28.235387],"type":"Point"}
}