{
  "type": "Feature",
  "properties": {
    "iso:country":"US",
    "sg:address":"2780 N Beach Rd",
    "sg:city":"Englewood",
    "sg:classifiers":[
        {
            "category":"Building & Trades",
            "subcategory":"Construction",
            "type":"Services"
        }
    ],
    "sg:phone":"+1 941 544 4934",
    "sg:postcode":"34223",
    "sg:province":"FL",
    "sg:tags":[
        "carpentry",
        "contractor"
    ],
    "wof:name":"Burt Piccitto Carpentry",
    "wof:placetype":"venue"
},
  "geometry": {"coordinates":[-82.366483,26.934915],"type":"Point"}
}