{
  "type": "Feature",
  "properties": {
    "iso:country":"US",
    "sg:address":"5439 Micco Dr",
    "sg:city":"Orlando",
    "sg:classifiers":[
        {
            "category":"Professional",
            "subcategory":"Business Services",
            "type":"Services"
        },
        {
            "category":"Professional",
            "subcategory":"Secretarial Services",
            "type":"Services"
        }
    ],
    "sg:phone":"+1 407 240 3213",
    "sg:postcode":"32839",
    "sg:province":"FL",
    "sg:tags":[
        "transcribing",
        "disc"
    ],
    "sg:website":"www.cnctranscription.com",
    "wof:name":"C & C Transcription Inc",
    "wof:placetype":"venue"
},
  "geometry": {"coordinates":[-81.41469499999999,28.483798],"type":"Point"}
}