{
  "type": "Feature",
  "properties": {
    "iso:country":"US",
    "sg:address":"1431 S Ocean Blvd",
    "sg:city":"Pompano Beach",
    "sg:classifiers":[
        {
            "category":"Real Estate",
            "subcategory":"Real Estate Agent",
            "type":"Services"
        }
    ],
    "sg:phone":"+1 954 788 3888",
    "sg:postcode":"33062",
    "sg:province":"FL",
    "wof:name":"Patrick Nee Realty Inc",
    "wof:placetype":"venue"
},
  "geometry": {"coordinates":[-80.092563,26.214577],"type":"Point"}
}