{
  "type": "Feature",
  "properties": {
    "addr:full":"339 N Janice Ln Ormond Beach FL 32174",
    "addr:housenumber":"339",
    "addr:postcode":"32174",
    "addr:street":"N Janice Ln",
    "iso:country":"US",
    "sg:address":"339 N Janice Ln",
    "sg:city":"Ormond Beach",
    "sg:classifiers":[
        {
            "category":"Building & Trades",
            "subcategory":"Construction",
            "type":"Services"
        }
    ],
    "sg:phone":"+1 386 672 1584",
    "sg:postcode":"32174",
    "sg:province":"FL",
    "sg:tags":[
        "excavation",
        "contractor"
    ],
    "wof:name":"Td Dozer Inc",
    "wof:placetype":"venue"
},
  "geometry": {"coordinates":[-81.12598199999999,29.274539],"type":"Point"}
}