{
  "type": "Feature",
  "properties": {
    "iso:country":"US",
    "sg:address":"2720 South St",
    "sg:city":"Titusville",
    "sg:classifiers":[
        {
            "category":"Farming",
            "subcategory":"Livestock Farm",
            "type":"Manufacturing & Wholesale Goods"
        },
        {
            "category":"Recreation",
            "type":"Entertainment"
        }
    ],
    "sg:phone":"+1 321 268 5955",
    "sg:postcode":"32780",
    "sg:province":"FL",
    "sg:tags":[
        "equine",
        "stable"
    ],
    "wof:name":"Flying D Ranch Inc",
    "wof:placetype":"venue"
},
  "geometry": {"coordinates":[-80.844675,28.595923],"type":"Point"}
}