{
  "type": "Feature",
  "properties": {
    "iso:country":"US",
    "sg:address":"8603 SW 68th Street Rd",
    "sg:city":"Miami",
    "sg:classifiers":[
        {
            "category":"Professional",
            "subcategory":"Engineering",
            "type":"Services"
        },
        {
            "category":"Retail",
            "subcategory":"Repair Shop",
            "type":"Services"
        }
    ],
    "sg:phone":"+1 305 271 1899",
    "sg:postcode":"33143",
    "sg:province":"FL",
    "sg:tags":[
        "rebuilding",
        "aircraft",
        "maintenance"
    ],
    "wof:name":"Cosmos Air Inc",
    "wof:placetype":"venue"
},
  "geometry": {"coordinates":[-80.333398,25.706759],"type":"Point"}
}