{
  "type": "Feature",
  "properties": {
    "iso:country":"US",
    "sg:address":"3482 Tiffiny St",
    "sg:city":"Port Charlotte",
    "sg:classifiers":[
        {
            "category":"Real Estate",
            "subcategory":"Real Estate Agent",
            "type":"Services"
        }
    ],
    "sg:phone":"+1 941 764 7585",
    "sg:postcode":"33980",
    "sg:province":"FL",
    "wof:name":"Marianne Lilly Direct Real Est",
    "wof:placetype":"venue"
},
  "geometry": {"coordinates":[-82.058632,26.974852],"type":"Point"}
}