{
  "type": "Feature",
  "properties": {
    "iso:country":"US",
    "sg:address":"35 Lorillard Pl",
    "sg:city":"Ormond Beach",
    "sg:classifiers":[
        {
            "category":"Building & Trades",
            "subcategory":"Landscaping Services",
            "type":"Services"
        }
    ],
    "sg:phone":"+1 386 673 5886",
    "sg:postcode":"32174",
    "sg:province":"FL",
    "sg:tags":[
        "lawn"
    ],
    "wof:name":"Sarges Lawn Care",
    "wof:placetype":"venue"
},
  "geometry": {"coordinates":[-81.050164,29.270026],"type":"Point"}
}