{
  "type": "Feature",
  "properties": {
    "iso:country":"US",
    "sg:address":"2121 Lisenby Ave",
    "sg:city":"Panama City",
    "sg:classifiers":[
        {
            "category":"Social Services",
            "type":"Services"
        }
    ],
    "sg:phone":"+1 850 769 7102",
    "sg:postcode":"32405",
    "sg:province":"FL",
    "wof:name":"Anchorage Family Counseling",
    "wof:placetype":"venue"
},
  "geometry": {"coordinates":[-85.68363100000001,30.188348],"type":"Point"}
}