{
  "type": "Feature",
  "properties": {
    "addr:full":"14103 SW 51st St Miami FL 33175",
    "addr:housenumber":"14103",
    "addr:postcode":"33175",
    "addr:street":"Sw 51St St",
    "iso:country":"US",
    "sg:address":"14103 SW 51st St",
    "sg:city":"Miami",
    "sg:classifiers":[
        {
            "category":"Manufacturing",
            "subcategory":"Metals",
            "type":"Manufacturing & Wholesale Goods"
        }
    ],
    "sg:phone":"+1 305 227 2761",
    "sg:postcode":"33175",
    "sg:province":"FL",
    "sg:tags":[
        "steel",
        "distributor",
        "mill",
        "warehouse"
    ],
    "wof:name":"Blue Steel Roofing Corporation",
    "wof:placetype":"venue"
},
  "geometry": {"coordinates":[-80.422399,25.718193],"type":"Point"}
}