{
  "type": "Feature",
  "properties": {
    "iso:country":"US",
    "sg:address":"5499 NW Manville Dr",
    "sg:city":"Port Saint Lucie",
    "sg:classifiers":[
        {
            "category":"Building & Trades",
            "subcategory":"Construction",
            "type":"Services"
        }
    ],
    "sg:phone":"+1 772 465 4273",
    "sg:postcode":"34983",
    "sg:province":"FL",
    "sg:tags":[
        "house"
    ],
    "wof:name":"Willett Homebuilders Inc",
    "wof:placetype":"venue"
},
  "geometry": {"coordinates":[-80.36176399999999,27.347057],"type":"Point"}
}