{
  "type": "Feature",
  "properties": {
    "iso:country":"US",
    "sg:address":"9141 NW 40th St",
    "sg:city":"Sunrise",
    "sg:classifiers":[
        {
            "category":"Manufacturing",
            "subcategory":"Printing",
            "type":"Manufacturing & Wholesale Goods"
        }
    ],
    "sg:phone":"+1 954 258 4454",
    "sg:postcode":"33351",
    "sg:province":"FL",
    "sg:tags":[
        "printer"
    ],
    "wof:name":"Blue Line Printing",
    "wof:placetype":"venue"
},
  "geometry": {"coordinates":[-80.27220699999999,26.174159],"type":"Point"}
}