{
  "type": "Feature",
  "properties": {
    "addr:full":"9380 NW 37th Manor Fort Lauderdale FL 33351",
    "addr:housenumber":"9380",
    "addr:postcode":"33351",
    "addr:street":"Nw 37Th Manor",
    "iso:country":"US",
    "sg:address":"9380 NW 37th Manor",
    "sg:city":"Fort Lauderdale",
    "sg:classifiers":[
        {
            "category":"Shopping",
            "subcategory":"Gifts & Souvenirs",
            "type":"Retail Goods"
        }
    ],
    "sg:phone":"+1 954 749 9607",
    "sg:postcode":"33351",
    "sg:province":"FL",
    "wof:name":"Brass Gifts & Souvenirs",
    "wof:placetype":"venue"
},
  "geometry": {"coordinates":[-80.27459,26.172509],"type":"Point"}
}