{
  "type": "Feature",
  "properties": {
    "addr:full":"719 Edge St Fort Walton Beach FL 32547",
    "addr:housenumber":"719",
    "addr:postcode":"32547",
    "addr:street":"Edge St",
    "iso:country":"US",
    "sg:address":"719 Edge St",
    "sg:city":"Fort Walton Beach",
    "sg:classifiers":[
        {
            "category":"Building & Trades",
            "subcategory":"Electrical",
            "type":"Services"
        }
    ],
    "sg:phone":"+1 850 244 1318",
    "sg:postcode":"32547",
    "sg:province":"FL",
    "sg:tags":[
        "contractor",
        "electrical",
        "utility"
    ],
    "wof:name":"Daniel S Mc Clllan Elec Contrs",
    "wof:placetype":"venue"
},
  "geometry": {"coordinates":[-86.654056,30.441039],"type":"Point"}
}