{
  "type": "Feature",
  "properties": {
    "addr:full":"7550 W Waters Ave Tampa FL 33615",
    "addr:housenumber":"7550",
    "addr:postcode":"33615",
    "addr:street":"W Waters Ave",
    "iso:country":"US",
    "sg:address":"7550 W Waters Ave",
    "sg:city":"Tampa",
    "sg:classifiers":[
        {
            "category":"Freight",
            "type":"Transportation"
        }
    ],
    "sg:phone":"+1 866 320 6309",
    "sg:postcode":"33615",
    "sg:province":"FL",
    "sg:tags":[
        "commercial",
        "household",
        "storage"
    ],
    "sg:website":"http://www.unclebobs.com/stores/UB088/?source=Yellowpages.com&howheard=ISM",
    "wof:name":"Uncle Bob's Self Storage",
    "wof:placetype":"venue"
},
  "geometry": {"coordinates":[-82.564504,28.025806],"type":"Point"}
}