{
  "type": "Feature",
  "properties": {
    "addr:full":"5273 Plymouth Sorrento Rd Apopka FL 32712",
    "addr:housenumber":"5273",
    "addr:postcode":"32712",
    "addr:street":"Plymouth Sorrento Rd",
    "iso:country":"US",
    "sg:address":"5273 Plymouth Sorrento Rd",
    "sg:city":"Apopka",
    "sg:classifiers":[
        {
            "category":"Farming",
            "subcategory":"Nursery",
            "type":"Manufacturing & Wholesale Goods"
        }
    ],
    "sg:phone":"+1 407 886 6075",
    "sg:postcode":"32712",
    "sg:province":"FL",
    "sg:tags":[
        "ornamental"
    ],
    "wof:name":"Life Source Foliage",
    "wof:placetype":"venue"
},
  "geometry": {"coordinates":[-81.559724,28.758447],"type":"Point"}
}