{
  "type": "Feature",
  "properties": {
    "iso:country":"US",
    "sg:address":"302 S K St",
    "sg:city":"Lake Worth",
    "sg:classifiers":[
        {
            "category":"Real Estate",
            "subcategory":"Real Estate Operator",
            "type":"Services"
        }
    ],
    "sg:phone":"+1 561 995 2116",
    "sg:postcode":"33460",
    "sg:province":"FL",
    "sg:tags":[
        "building",
        "apartment"
    ],
    "wof:name":"Alexandra Princess Apts",
    "wof:placetype":"venue"
},
  "geometry": {"coordinates":[-80.055453,26.611008],"type":"Point"}
}