{
  "type": "Feature",
  "properties": {
    "addr:full":"7515 Harvest Village Ct Navarre FL 32566",
    "addr:housenumber":"7515",
    "addr:postcode":"32566",
    "addr:street":"Harvest Village Ct",
    "iso:country":"US",
    "sg:address":"7515 Harvest Village Ct",
    "sg:city":"Navarre",
    "sg:classifiers":[
        {
            "category":"Shopping",
            "subcategory":"Department Store",
            "type":"Retail Goods"
        },
        {
            "category":"Shopping",
            "subcategory":"Discount & Variety Stores",
            "type":"Retail Goods"
        },
        {
            "category":"Shopping",
            "type":"Retail Goods"
        },
        {
            "category":"Food & Beverages",
            "subcategory":"Groceries & Convenience Stores",
            "type":"Retail Goods"
        }
    ],
    "sg:phone":"+1 850 936 8111",
    "sg:postcode":"32566",
    "sg:province":"FL",
    "sg:tags":[
        "merchandise"
    ],
    "sg:website":"http://www.dollargeneral.com",
    "wof:name":"Dollar General",
    "wof:placetype":"venue"
},
  "geometry": {"coordinates":[-86.908495,30.40287],"type":"Point"}
}