{
  "type": "Feature",
  "properties": {
    "iso:country":"US",
    "sg:address":"206 E Howry Ave",
    "sg:city":"De Land",
    "sg:classifiers":[
        {
            "category":"Real Estate",
            "subcategory":"Real Estate Agent",
            "type":"Services"
        }
    ],
    "sg:phone":"+1 386 738 2996",
    "sg:postcode":"32724",
    "sg:province":"FL",
    "wof:name":"Mike Russo Appraisal Services",
    "wof:placetype":"venue"
},
  "geometry": {"coordinates":[-81.301053,29.026227],"type":"Point"}
}