{
  "type": "Feature",
  "properties": {
    "addr:full":"4461 Legendary Dr Destin FL 32541",
    "addr:housenumber":"4461",
    "addr:postcode":"32541",
    "addr:street":"Legendary Dr",
    "iso:country":"US",
    "sg:address":"4461 Legendary Dr",
    "sg:city":"Destin",
    "sg:classifiers":[
        {
            "category":"Building & Trades",
            "subcategory":"Construction",
            "type":"Services"
        }
    ],
    "sg:phone":"+1 850 337 8050",
    "sg:postcode":"32541",
    "sg:province":"FL",
    "sg:tags":[
        "contractor"
    ],
    "sg:website":"www.legendarybuilders.com",
    "wof:name":"Legendary Builders Inc",
    "wof:placetype":"venue"
},
  "geometry": {"coordinates":[-86.419962,30.390039],"type":"Point"}
}