{
  "type": "Feature",
  "properties": {
    "addr:full":"595 Celebration Pl Kissimmee FL 34747",
    "addr:housenumber":"595",
    "addr:postcode":"34747",
    "addr:street":"Celebration Pl",
    "iso:country":"US",
    "sg:address":"595 Celebration Pl",
    "sg:city":"Kissimmee",
    "sg:classifiers":[
        {
            "category":"Government",
            "subcategory":"Fire Station",
            "type":"Public Place"
        }
    ],
    "sg:phone":"+1 407 566 2027",
    "sg:postcode":"34747",
    "sg:province":"FL",
    "sg:tags":[
        "department"
    ],
    "wof:name":"Celebration Fire Dept",
    "wof:placetype":"venue"
},
  "geometry": {"coordinates":[-81.54709,28.326237],"type":"Point"}
}