{
  "type": "Feature",
  "properties": {
    "iso:country":"US",
    "sg:address":"3803 101st St E",
    "sg:city":"Palmetto",
    "sg:classifiers":[
        {
            "category":"Shopping",
            "subcategory":"Florist",
            "type":"Retail Goods"
        }
    ],
    "sg:phone":"+1 941 755 7673",
    "sg:postcode":"34221",
    "sg:province":"FL",
    "wof:name":"Loving Hands Bks Flowers Gifts",
    "wof:placetype":"venue"
},
  "geometry": {"coordinates":[-82.525432,27.604962],"type":"Point"}
}