{
  "type": "Feature",
  "properties": {
    "iso:country":"US",
    "sg:address":"666 W Tennessee St",
    "sg:city":"Tallahassee",
    "sg:classifiers":[
        {
            "category":"Bars & Pubs",
            "type":"Food & Drink"
        }
    ],
    "sg:phone":"+1 850 222 3043",
    "sg:postcode":"32304",
    "sg:province":"FL",
    "sg:tags":[
        "lounge",
        "drinking",
        "cocktail"
    ],
    "wof:name":"Tini's Lower Lounge",
    "wof:placetype":"venue"
},
  "geometry": {"coordinates":[-84.29329,30.444699],"type":"Point"}
}