{
  "type": "Feature",
  "properties": {
    "iso:country":"US",
    "sg:address":"1314 Indian Woman Rd",
    "sg:city":"Santa Rosa Beach",
    "sg:classifiers":[
        {
            "category":"Building & Trades",
            "subcategory":"Construction",
            "type":"Services"
        }
    ],
    "sg:phone":"+1 850 267 9449",
    "sg:postcode":"32459",
    "sg:province":"FL",
    "sg:tags":[
        "hanging",
        "contractor"
    ],
    "wof:name":"Lees Painting Plus More LLC",
    "wof:placetype":"venue"
},
  "geometry": {"coordinates":[-86.219899,30.403245],"type":"Point"}
}