{
  "type": "Feature",
  "properties": {
    "iso:country":"US",
    "sg:address":"810 SW 12th Ave",
    "sg:city":"Miami",
    "sg:classifiers":[
        {
            "category":"Real Estate",
            "subcategory":"Real Estate Services",
            "type":"Services"
        },
        {
            "category":"Insurance",
            "subcategory":"Hazard Insurance",
            "type":"Services"
        },
        {
            "category":"Insurance",
            "subcategory":"Title Insurance",
            "type":"Services"
        }
    ],
    "sg:phone":"+1 305 642 6220",
    "sg:postcode":"33130",
    "sg:province":"FL",
    "sg:tags":[
        "commercial",
        "business",
        "mortgage"
    ],
    "wof:name":"National Title Ins",
    "wof:placetype":"venue"
},
  "geometry": {"coordinates":[-80.214429,25.765759],"type":"Point"}
}