{
  "type": "Feature",
  "properties": {
    "iso:country":"US",
    "sg:address":"13552 SW 129th St",
    "sg:city":"Miami",
    "sg:classifiers":[
        {
            "category":"Shopping",
            "subcategory":"Stationery & Office Supplies",
            "type":"Retail Goods"
        },
        {
            "category":"Utilities",
            "type":"Services"
        }
    ],
    "sg:phone":"+1 305 233 7075",
    "sg:postcode":"33186",
    "sg:province":"FL",
    "sg:tags":[
        "equipment",
        "labeling",
        "label"
    ],
    "wof:name":"Flexo Concept Manufacturing Corp",
    "wof:placetype":"venue"
},
  "geometry": {"coordinates":[-80.41321600000001,25.647199],"type":"Point"}
}