{
  "type": "Feature",
  "properties": {
    "addr:full":"321 Unicorn Rd Venice FL 34293",
    "addr:housenumber":"321",
    "addr:postcode":"34293",
    "addr:street":"Unicorn Rd",
    "iso:country":"US",
    "sg:address":"321 Unicorn Rd",
    "sg:city":"Venice",
    "sg:classifiers":[
        {
            "category":"Building & Trades",
            "subcategory":"Construction",
            "type":"Services"
        }
    ],
    "sg:phone":"+1 941 493 4412",
    "sg:postcode":"34293",
    "sg:province":"FL",
    "sg:tags":[
        "personal",
        "house"
    ],
    "wof:name":"Double Duty Handyman Service",
    "wof:placetype":"venue"
},
  "geometry": {"coordinates":[-82.418115,27.059297],"type":"Point"}
}