{
  "type": "Feature",
  "properties": {
    "iso:country":"US",
    "sg:address":"6815 Dairy Rd",
    "sg:city":"Zephyrhills",
    "sg:classifiers":[
        {
            "category":"Professional",
            "subcategory":"Accounting & Tax Preparation",
            "type":"Services"
        }
    ],
    "sg:phone":"+1 813 788 2155",
    "sg:postcode":"33542",
    "sg:province":"FL",
    "wof:name":"Judson B Baggett CPA PA",
    "wof:placetype":"venue"
},
  "geometry": {"coordinates":[-82.184161,28.257391],"type":"Point"}
}