{
  "type": "Feature",
  "properties": {
    "addr:full":"11545 Osprey Landing Way Fort Myers FL 33908",
    "addr:housenumber":"11545",
    "addr:postcode":"33908",
    "addr:street":"Osprey Landing Way",
    "iso:country":"US",
    "sg:address":"11545 Osprey Landing Way",
    "sg:city":"Fort Myers",
    "sg:classifiers":[
        {
            "category":"Banks & Credit Unions",
            "subcategory":"Financial Services",
            "type":"Services"
        }
    ],
    "sg:phone":"+1 239 454 1857",
    "sg:postcode":"33908",
    "sg:province":"FL",
    "sg:tags":[
        "investor"
    ],
    "wof:name":"Second Chance Investments LLC",
    "wof:placetype":"venue"
},
  "geometry": {"coordinates":[-81.945981,26.52421],"type":"Point"}
}