{
  "type": "Feature",
  "properties": {
    "addr:full":"4315 Pompano Palmetto FL 34221",
    "addr:housenumber":"4315",
    "addr:postcode":"34221",
    "addr:street":"Pompano Palmetto",
    "iso:country":"US",
    "sg:address":"4315 Pompano",
    "sg:city":"Palmetto",
    "sg:classifiers":[
        {
            "category":"Professional",
            "type":"Services"
        }
    ],
    "sg:phone":"+1 941 722 2546",
    "sg:postcode":"34221",
    "sg:province":"FL",
    "wof:name":"Tex Min Corporation",
    "wof:placetype":"venue"
},
  "geometry": {"coordinates":[-82.610108,27.532751],"type":"Point"}
}