{
  "type": "Feature",
  "properties": {
    "iso:country":"US",
    "sg:address":"6830 SW 120th St",
    "sg:city":"Miami",
    "sg:classifiers":[
        {
            "category":"Shopping",
            "subcategory":"Photographic Equipment",
            "type":"Retail Goods"
        }
    ],
    "sg:phone":"+1 305 662 2048",
    "sg:postcode":"33156",
    "sg:province":"FL",
    "sg:tags":[
        "supply"
    ],
    "wof:name":"Rey & Rey Enterprises, Inc.",
    "wof:placetype":"venue"
},
  "geometry": {"coordinates":[-80.30515,25.659598],"type":"Point"}
}