{
  "type": "Feature",
  "properties": {
    "addr:full":"4280 SW 13th Ter Miami FL 33134",
    "addr:housenumber":"4280",
    "addr:postcode":"33134",
    "addr:street":"Sw 13Th Ter",
    "iso:country":"US",
    "sg:address":"4280 SW 13th Ter",
    "sg:city":"Miami",
    "sg:classifiers":[
        {
            "category":"Organizations",
            "subcategory":"Professional Association",
            "type":"Services"
        }
    ],
    "sg:phone":"+1 305 448 3221",
    "sg:postcode":"33134",
    "sg:province":"FL",
    "wof:name":"Orlando Gonzalez Accountant",
    "wof:placetype":"venue"
},
  "geometry": {"coordinates":[-80.263614,25.759235],"type":"Point"}
}