{
  "type": "Feature",
  "properties": {
    "iso:country":"US",
    "sg:address":"1229 18th St",
    "sg:city":"Miami Beach",
    "sg:classifiers":[
        {
            "category":"Retail",
            "subcategory":"Car Wash",
            "type":"Services"
        }
    ],
    "sg:phone":"+1 305 604 9282",
    "sg:postcode":"33139",
    "sg:province":"FL",
    "sg:website":"www.sobefinest.com",
    "wof:name":"South Beach Finest Hand Car Wash & Window Tinting",
    "wof:placetype":"venue"
},
  "geometry": {"coordinates":[-80.141926,25.793614],"type":"Point"}
}