{
  "type": "Feature",
  "properties": {
    "iso:country":"US",
    "sg:address":"1237 Ferdinand St",
    "sg:city":"Coral Gables",
    "sg:classifiers":[
        {
            "category":"Health Services",
            "subcategory":"Doctor",
            "type":"Services"
        }
    ],
    "sg:phone":"+1 305 445 5899",
    "sg:postcode":"33134",
    "sg:province":"FL",
    "sg:tags":[
        "physician",
        "surgeon"
    ],
    "wof:name":"T & T Medical Inc",
    "wof:placetype":"venue"
},
  "geometry": {"coordinates":[-80.28534000000001,25.758903],"type":"Point"}
}