{
  "type": "Feature",
  "properties": {
    "addr:full":"4330 Sawyer Rd Sarasota FL 34233",
    "addr:housenumber":"4330",
    "addr:postcode":"34233",
    "addr:street":"Sawyer Rd",
    "iso:country":"US",
    "sg:address":"4330 Sawyer Rd",
    "sg:city":"Sarasota",
    "sg:classifiers":[
        {
            "category":"Building & Trades",
            "subcategory":"Construction",
            "type":"Services"
        }
    ],
    "sg:phone":"+1 941 925 4298",
    "sg:postcode":"34233",
    "sg:province":"FL",
    "sg:tags":[
        "house"
    ],
    "wof:name":"Small Jobs Plus Inc",
    "wof:placetype":"venue"
},
  "geometry": {"coordinates":[-82.4893,27.293751],"type":"Point"}
}