{
  "type": "Feature",
  "properties": {
    "addr:full":"1025 S Fairfield Dr Pensacola FL 32506",
    "addr:housenumber":"1025",
    "addr:postcode":"32506",
    "addr:street":"S Fairfield Dr",
    "iso:country":"US",
    "sg:address":"1025 S Fairfield Dr",
    "sg:city":"Pensacola",
    "sg:classifiers":[
        {
            "category":"Organizations",
            "subcategory":"Religious Organization",
            "type":"Services"
        }
    ],
    "sg:phone":"+1 850 453 6180",
    "sg:postcode":"32506",
    "sg:province":"FL",
    "sg:tags":[
        "church"
    ],
    "wof:name":"Celebration Baptist Church",
    "wof:placetype":"venue"
},
  "geometry": {"coordinates":[-87.31226700000001,30.392863],"type":"Point"}
}