{
  "type": "Feature",
  "properties": {
    "addr:full":"9396 Lake Hickory Nut Dr Winter Garden FL 34787",
    "addr:housenumber":"9396",
    "addr:postcode":"34787",
    "addr:street":"Lake Hickory Nut Dr",
    "iso:country":"US",
    "sg:address":"9396 Lake Hickory Nut Dr",
    "sg:city":"Winter Garden",
    "sg:classifiers":[
        {
            "category":"Shopping",
            "type":"Retail Goods"
        }
    ],
    "sg:phone":"+1 407 877 3740",
    "sg:postcode":"34787",
    "sg:province":"FL",
    "sg:tags":[
        "merchandise"
    ],
    "wof:name":"Davincis Basement",
    "wof:placetype":"venue"
},
  "geometry": {"coordinates":[-81.647383,28.428925],"type":"Point"}
}