{
  "type": "Feature",
  "properties": {
    "iso:country":"US",
    "sg:address":"860 NE 158th St",
    "sg:city":"North Miami Beach",
    "sg:classifiers":[
        {
            "category":"Building & Trades",
            "subcategory":"Construction",
            "type":"Services"
        }
    ],
    "sg:phone":"+1 305 947 4033",
    "sg:postcode":"33162",
    "sg:province":"FL",
    "sg:tags":[
        "contractor"
    ],
    "wof:name":"Jvb Construction",
    "wof:placetype":"venue"
},
  "geometry": {"coordinates":[-80.182227,25.920381],"type":"Point"}
}