{
  "type": "Feature",
  "properties": {
    "iso:country":"US",
    "sg:address":"2975 Eber Blvd",
    "sg:city":"Melbourne",
    "sg:classifiers":[
        {
            "category":"Retail",
            "subcategory":"Repair Shop",
            "type":"Services"
        }
    ],
    "sg:phone":"+1 321 723 6070",
    "sg:postcode":"32904",
    "sg:province":"FL",
    "sg:tags":[
        "ironwork"
    ],
    "wof:name":"Charles Purnell Mobile Rstrtns",
    "wof:placetype":"venue"
},
  "geometry": {"coordinates":[-80.67118499999999,28.049998],"type":"Point"}
}