{
  "type": "Feature",
  "properties": {
    "addr:full":"2658 SE Erickson Dr Port Saint Lucie FL 34984",
    "addr:housenumber":"2658",
    "addr:postcode":"34984",
    "addr:street":"Se Erickson Dr",
    "iso:country":"US",
    "sg:address":"2658 SE Erickson Dr",
    "sg:city":"Port Saint Lucie",
    "sg:classifiers":[
        {
            "category":"Real Estate",
            "subcategory":"Real Estate Agent",
            "type":"Services"
        }
    ],
    "sg:phone":"+1 772 340 4000",
    "sg:postcode":"34984",
    "sg:province":"FL",
    "wof:name":"Joyce Bello",
    "wof:placetype":"venue"
},
  "geometry": {"coordinates":[-80.332961,27.262371],"type":"Point"}
}