{
  "type": "Feature",
  "properties": {
    "addr:full":"8901 Woodgate Manor Ct Fort Myers FL 33908",
    "addr:housenumber":"8901",
    "addr:postcode":"33908",
    "addr:street":"Woodgate Manor Ct",
    "iso:country":"US",
    "sg:address":"8901 Woodgate Manor Ct",
    "sg:city":"Fort Myers",
    "sg:classifiers":[
        {
            "category":"Shopping",
            "subcategory":"Optical Goods",
            "type":"Retail Goods"
        }
    ],
    "sg:phone":"+1 239 437 4595",
    "sg:postcode":"33908",
    "sg:province":"FL",
    "wof:name":"Eyes For You",
    "wof:placetype":"venue"
},
  "geometry": {"coordinates":[-81.900719,26.488609],"type":"Point"}
}