{
  "type": "Feature",
  "properties": {
    "addr:full":"203 SW 2nd St Okeechobee FL 34974",
    "addr:housenumber":"203",
    "addr:postcode":"34974",
    "addr:street":"Sw 2Nd St",
    "iso:country":"US",
    "sg:address":"203 SW 2nd St",
    "sg:city":"Okeechobee",
    "sg:classifiers":[
        {
            "category":"Food & Beverages",
            "subcategory":"Groceries & Convenience Stores",
            "type":"Retail Goods"
        }
    ],
    "sg:phone":"+1 863 467 0946",
    "sg:postcode":"34974",
    "sg:province":"FL",
    "wof:name":"Big O Drive-Thru",
    "wof:placetype":"venue"
},
  "geometry": {"coordinates":[-80.831103,27.242038],"type":"Point"}
}