{
  "type": "Feature",
  "properties": {
    "addr:full":"1312 NW 81st Ter Miami FL 33147",
    "addr:housenumber":"1312",
    "addr:postcode":"33147",
    "addr:street":"Nw 81St Ter",
    "iso:country":"US",
    "sg:address":"1312 NW 81st Ter",
    "sg:city":"Miami",
    "sg:classifiers":[
        {
            "category":"Restaurant",
            "type":"Food & Drink"
        }
    ],
    "sg:phone":"+1 786 229 7031",
    "sg:postcode":"33147",
    "sg:province":"FL",
    "sg:tags":[
        "eating"
    ],
    "wof:name":"Coops Kitchen Inc",
    "wof:placetype":"venue"
},
  "geometry": {"coordinates":[-80.22020000000001,25.849183],"type":"Point"}
}