{
  "type": "Feature",
  "properties": {
    "addr:full":"1558 S Dixie Hwy Coral Gables FL 33146",
    "addr:housenumber":"1558",
    "addr:postcode":"33146",
    "addr:street":"S Dixie Hwy",
    "iso:country":"US",
    "sg:address":"1558 S Dixie Hwy",
    "sg:city":"Coral Gables",
    "sg:classifiers":[
        {
            "category":"Building & Trades",
            "subcategory":"Locksmith",
            "type":"Services"
        }
    ],
    "sg:phone":"+1 305 755 4199",
    "sg:postcode":"33146",
    "sg:province":"FL",
    "sg:tags":[
        "key"
    ],
    "wof:name":"Emergency 24 Hour 7 Day Locksmith",
    "wof:placetype":"venue"
},
  "geometry": {"coordinates":[-80.28421899999999,25.708275],"type":"Point"}
}