{
  "type": "Feature",
  "properties": {
    "addr:full":"9060 Kimberly Blvd Boca Raton FL 33434",
    "addr:housenumber":"9060",
    "addr:postcode":"33434",
    "addr:street":"Kimberly Blvd",
    "iso:country":"US",
    "sg:address":"9060 Kimberly Blvd",
    "sg:city":"Boca Raton",
    "sg:classifiers":[
        {
            "category":"Sports & Exercise",
            "subcategory":"Gym",
            "type":"Entertainment"
        }
    ],
    "sg:phone":"+1 561 488 1492",
    "sg:postcode":"33434",
    "sg:province":"FL",
    "sg:tags":[
        "club",
        "health",
        "studio",
        "gymnasium"
    ],
    "wof:name":"Curves For Women",
    "wof:placetype":"venue"
},
  "geometry": {"coordinates":[-80.187743,26.383717],"type":"Point"}
}