{
  "type": "Feature",
  "properties": {
    "iso:country":"US",
    "sg:address":"9949 Clear Lake Cir",
    "sg:city":"Naples",
    "sg:classifiers":[
        {
            "category":"Professional",
            "subcategory":"Accounting & Tax Preparation",
            "type":"Services"
        }
    ],
    "sg:phone":"+1 239 594 1200",
    "sg:postcode":"34109",
    "sg:province":"FL",
    "sg:tags":[
        "accountant"
    ],
    "wof:name":"Arthur Rubin Ea Pa",
    "wof:placetype":"venue"
},
  "geometry": {"coordinates":[-81.74570199999999,26.255861],"type":"Point"}
}