{
  "type": "Feature",
  "properties": {
    "iso:country":"US",
    "sg:address":"114 del Prado Blvd S",
    "sg:city":"Cape Coral",
    "sg:classifiers":[
        {
            "category":"Communications",
            "subcategory":"Television Station",
            "type":"Services"
        }
    ],
    "sg:phone":"+1 239 772 1650",
    "sg:postcode":"33990",
    "sg:province":"FL",
    "sg:tags":[
        "broadcasting",
        "co"
    ],
    "wof:name":"WTPH",
    "wof:placetype":"venue"
},
  "geometry": {"coordinates":[-81.94107700000001,26.65157],"type":"Point"}
}