{
  "type": "Feature",
  "properties": {
    "iso:country":"US",
    "sg:address":"4609 Bayshore Dr",
    "sg:city":"Naples",
    "sg:classifiers":[
        {
            "category":"Building & Trades",
            "subcategory":"Construction",
            "type":"Services"
        }
    ],
    "sg:phone":"+1 239 774 1609",
    "sg:postcode":"34112",
    "sg:province":"FL",
    "sg:tags":[
        "handyman"
    ],
    "wof:name":"Friendly Fence Man",
    "wof:placetype":"venue"
},
  "geometry": {"coordinates":[-81.770307,26.113032],"type":"Point"}
}