{
  "type": "Feature",
  "properties": {
    "addr:full":"1438 Club Ln Lorida FL 33857",
    "addr:housenumber":"1438",
    "addr:postcode":"33857",
    "addr:street":"Club Ln",
    "iso:country":"US",
    "sg:address":"1438 Club Ln",
    "sg:city":"Lorida",
    "sg:classifiers":[
        {
            "category":"Building & Trades",
            "subcategory":"Construction",
            "type":"Services"
        }
    ],
    "sg:phone":"+1 863 655 2011",
    "sg:postcode":"33857",
    "sg:province":"FL",
    "sg:tags":[
        "contractor"
    ],
    "wof:name":"Mr Stucco Inc",
    "wof:placetype":"venue"
},
  "geometry": {"coordinates":[-81.24091,27.393875],"type":"Point"}
}