{
  "type": "Feature",
  "properties": {
    "iso:country":"US",
    "sg:address":"6147 Hupa Rd",
    "sg:city":"Sarasota",
    "sg:classifiers":[
        {
            "category":"Building & Trades",
            "subcategory":"Construction",
            "type":"Services"
        }
    ],
    "sg:phone":"+1 941 379 4594",
    "sg:postcode":"34241",
    "sg:province":"FL",
    "sg:tags":[
        "clearing",
        "land"
    ],
    "wof:name":"Yonkers Tractor Service Inc",
    "wof:placetype":"venue"
},
  "geometry": {"coordinates":[-82.33082899999999,27.263299],"type":"Point"}
}