{
  "type": "Feature",
  "properties": {
    "addr:full":"7000 W Palmetto Park Rd Boca Raton FL 33433",
    "addr:housenumber":"7000",
    "addr:postcode":"33433",
    "addr:street":"W Palmetto Park Rd",
    "iso:country":"US",
    "sg:address":"7000 W Palmetto Park Rd",
    "sg:city":"Boca Raton",
    "sg:classifiers":[
        {
            "category":"Professional",
            "subcategory":"Management & Consulting",
            "type":"Services"
        }
    ],
    "sg:phone":"+1 561 750 5800",
    "sg:postcode":"33433",
    "sg:province":"FL",
    "sg:tags":[
        "marketing",
        "support"
    ],
    "wof:name":"Genesis",
    "wof:placetype":"venue"
},
  "geometry": {"coordinates":[-80.153863,26.350324],"type":"Point"}
}