{
  "type": "Feature",
  "properties": {
    "addr:full":"501 1st Ave N St Petersburg FL 33705",
    "addr:housenumber":"501",
    "addr:postcode":"33705",
    "addr:street":"1St Ave N",
    "iso:country":"US",
    "sg:address":"501 1st Ave N",
    "sg:city":"St Petersburg",
    "sg:classifiers":[
        {
            "category":"Government",
            "subcategory":"Office",
            "type":"Public Place"
        }
    ],
    "sg:phone":"+1 727 562 3262",
    "sg:postcode":"33705",
    "sg:province":"FL",
    "wof:name":"Pinellas County Auto Rgstrtn",
    "wof:placetype":"venue"
},
  "geometry": {"coordinates":[-82.64174199999999,27.772074],"type":"Point"}
}