{
  "type": "Feature",
  "properties": {
    "iso:country":"US",
    "sg:address":"914 Andrews Rd",
    "sg:city":"West Palm Beach",
    "sg:classifiers":[
        {
            "category":"Real Estate",
            "subcategory":"Real Estate Agent",
            "type":"Services"
        }
    ],
    "sg:phone":"+1 561 804 9603",
    "sg:postcode":"33405",
    "sg:province":"FL",
    "wof:name":"Remax Prestige",
    "wof:placetype":"venue"
},
  "geometry": {"coordinates":[-80.06631400000001,26.687639],"type":"Point"}
}