{
  "type": "Feature",
  "properties": {
    "iso:country":"US",
    "sg:address":"1530 S Ocean Blvd",
    "sg:city":"Pompano Beach",
    "sg:classifiers":[
        {
            "category":"Real Estate",
            "subcategory":"Real Estate Operator",
            "type":"Services"
        }
    ],
    "sg:phone":"+1 954 941 8715",
    "sg:postcode":"33062",
    "sg:province":"FL",
    "sg:tags":[
        "building",
        "apartment"
    ],
    "wof:name":"Ocean East Apartment Inc",
    "wof:placetype":"venue"
},
  "geometry": {"coordinates":[-80.094111,26.207111],"type":"Point"}
}