{
  "type": "Feature",
  "properties": {
    "addr:full":"13906 Darchance Rd Windermere FL 34786",
    "addr:housenumber":"13906",
    "addr:postcode":"34786",
    "addr:street":"Darchance Rd",
    "iso:country":"US",
    "sg:address":"13906 Darchance Rd",
    "sg:city":"Windermere",
    "sg:classifiers":[
        {
            "category":"Personal",
            "subcategory":"Beauty Salon",
            "type":"Services"
        }
    ],
    "sg:phone":"+1 407 877 3657",
    "sg:postcode":"34786",
    "sg:province":"FL",
    "wof:name":"Charm And Elegance",
    "wof:placetype":"venue"
},
  "geometry": {"coordinates":[-81.584037,28.456942],"type":"Point"}
}