{
  "type": "Feature",
  "properties": {
    "iso:country":"US",
    "sg:address":"703 NE 16th Pl",
    "sg:city":"Cape Coral",
    "sg:classifiers":[
        {
            "category":"Professional",
            "subcategory":"Art Services",
            "type":"Services"
        }
    ],
    "sg:phone":"+1 239 772 0609",
    "sg:postcode":"33909",
    "sg:province":"FL",
    "sg:tags":[
        "artist"
    ],
    "wof:name":"Imaginations",
    "wof:placetype":"venue"
},
  "geometry": {"coordinates":[-81.939812,26.665909],"type":"Point"}
}