{
  "type": "Feature",
  "properties": {
    "iso:country":"US",
    "sg:address":"671 Goodlette Rd N",
    "sg:city":"Naples",
    "sg:classifiers":[
        {
            "category":"Health Services",
            "subcategory":"Doctor",
            "type":"Services"
        }
    ],
    "sg:phone":"+1 239 643 7199",
    "sg:postcode":"34102",
    "sg:province":"FL",
    "sg:tags":[
        "clinic"
    ],
    "wof:name":"Naples Injury Treatment Ctr",
    "wof:placetype":"venue"
},
  "geometry": {"coordinates":[-81.79101900000001,26.153881],"type":"Point"}
}