{
  "type": "Feature",
  "properties": {
    "iso:country":"US",
    "sg:address":"318 E Dakin Ave",
    "sg:city":"Kissimmee",
    "sg:classifiers":[
        {
            "category":"Travel",
            "subcategory":"Travel Agent",
            "type":"Entertainment"
        }
    ],
    "sg:phone":"+1 407 935 1851",
    "sg:postcode":"34741",
    "sg:province":"FL",
    "sg:tags":[
        "operator",
        "tour"
    ],
    "wof:name":"Excellence Tours Transportion",
    "wof:placetype":"venue"
},
  "geometry": {"coordinates":[-81.402683,28.291612],"type":"Point"}
}