{
  "type": "Feature",
  "properties": {
    "addr:full":"520 SE 5th Ave Fort Lauderdale FL 33301",
    "addr:housenumber":"520",
    "addr:postcode":"33301",
    "addr:street":"Se 5Th Ave",
    "iso:country":"US",
    "sg:address":"520 SE 5th Ave",
    "sg:city":"Fort Lauderdale",
    "sg:classifiers":[
        {
            "category":"Building & Trades",
            "subcategory":"Construction",
            "type":"Services"
        }
    ],
    "sg:phone":"+1 954 462 0486",
    "sg:postcode":"33301",
    "sg:province":"FL",
    "sg:tags":[
        "contractor"
    ],
    "wof:name":"Current Builders Constr Inc",
    "wof:placetype":"venue"
},
  "geometry": {"coordinates":[-80.13856,26.120645],"type":"Point"}
}