{
  "type": "Feature",
  "properties": {
    "iso:country":"US",
    "sg:address":"109 Sunflower Cir",
    "sg:city":"Royal Palm Beach",
    "sg:classifiers":[
        {
            "category":"Manufacturing",
            "subcategory":"Signs",
            "type":"Manufacturing & Wholesale Goods"
        }
    ],
    "sg:phone":"+1 561 753 2750",
    "sg:postcode":"33411",
    "sg:province":"FL",
    "wof:name":"Barefoot Designs & Signs",
    "wof:placetype":"venue"
},
  "geometry": {"coordinates":[-80.228433,26.732554],"type":"Point"}
}