{
  "type": "Feature",
  "properties": {
    "addr:full":"3691 Estepona Ave Doral FL 33178",
    "addr:housenumber":"3691",
    "addr:postcode":"33178",
    "addr:street":"Estepona Ave",
    "iso:country":"US",
    "sg:address":"3691 Estepona Ave",
    "sg:city":"Doral",
    "sg:classifiers":[
        {
            "category":"Shopping",
            "subcategory":"Hobbies, Toys, & Games",
            "type":"Retail Goods"
        }
    ],
    "sg:phone":"+1 305 477 7129",
    "sg:postcode":"33178",
    "sg:province":"FL",
    "sg:tags":[
        "coin",
        "supply"
    ],
    "wof:name":"Monroe Coin Inc",
    "wof:placetype":"venue"
},
  "geometry": {"coordinates":[-80.364114,25.80737],"type":"Point"}
}