{
  "type": "Feature",
  "properties": {
    "iso:country":"US",
    "sg:address":"12297 Hidden Hills Dr",
    "sg:city":"Jacksonville",
    "sg:classifiers":[
        {
            "category":"Real Estate",
            "subcategory":"Real Estate Agent",
            "type":"Services"
        }
    ],
    "sg:phone":"+1 904 424 3576",
    "sg:postcode":"32225",
    "sg:province":"FL",
    "wof:name":"Babs Enterprises LLC",
    "wof:placetype":"venue"
},
  "geometry": {"coordinates":[-81.510859,30.375962],"type":"Point"}
}