{
  "type": "Feature",
  "properties": {
    "iso:country":"US",
    "sg:address":"99751 Overseas Hwy",
    "sg:city":"Key Largo",
    "sg:classifiers":[
        {
            "category":"Recreation",
            "type":"Entertainment"
        }
    ],
    "sg:phone":"+1 305 453 0110",
    "sg:postcode":"33037",
    "sg:province":"FL",
    "sg:website":"www.reef-roamer.com",
    "wof:name":"Reef Roamer Inc",
    "wof:placetype":"venue"
},
  "geometry": {"coordinates":[-80.438637,25.096316],"type":"Point"}
}