{
  "type": "Feature",
  "properties": {
    "iso:country":"US",
    "sg:address":"245 SE 4th Ave",
    "sg:city":"Cape Coral",
    "sg:classifiers":[
        {
            "category":"Retail",
            "subcategory":"Repair Shop",
            "type":"Services"
        }
    ],
    "sg:phone":"+1 239 772 1818",
    "sg:postcode":"33990",
    "sg:province":"FL",
    "sg:tags":[
        "equipment",
        "commercial"
    ],
    "wof:name":"W W Scale",
    "wof:placetype":"venue"
},
  "geometry": {"coordinates":[-81.966292,26.646973],"type":"Point"}
}