{
  "type": "Feature",
  "properties": {
    "iso:country":"US",
    "sg:address":"701 N Congress Ave",
    "sg:city":"Boynton Beach",
    "sg:classifiers":[
        {
            "category":"Utilities",
            "subcategory":"Mobile Phone",
            "type":"Services"
        }
    ],
    "sg:phone":"+1 561 742 5587",
    "sg:postcode":"33426",
    "sg:province":"FL",
    "sg:tags":[
        "telephone",
        "cellular"
    ],
    "wof:name":"Metro Pcs",
    "wof:placetype":"venue"
},
  "geometry": {"coordinates":[-80.090681,26.534376],"type":"Point"}
}