{
  "type": "Feature",
  "properties": {
    "iso:country":"US",
    "sg:address":"16820 Gunn Hwy",
    "sg:city":"Odessa",
    "sg:classifiers":[
        {
            "category":"Wholesale",
            "subcategory":"Farm Supplies",
            "type":"Manufacturing & Wholesale Goods"
        }
    ],
    "sg:phone":"+1 813 920 2514",
    "sg:postcode":"33556",
    "sg:province":"FL",
    "sg:tags":[
        "feed"
    ],
    "wof:name":"Feed Depot-Fox's Corner",
    "wof:placetype":"venue"
},
  "geometry": {"coordinates":[-82.576733,28.12422],"type":"Point"}
}