{
  "type": "Feature",
  "properties": {
    "iso:country":"US",
    "sg:address":"4629 SW 74th Ave",
    "sg:city":"Miami",
    "sg:classifiers":[
        {
            "category":"Home & Garden",
            "subcategory":"Home Furnishings",
            "type":"Retail Goods"
        },
        {
            "category":"Wholesale",
            "subcategory":"Home Furnishings",
            "type":"Manufacturing & Wholesale Goods"
        }
    ],
    "sg:phone":"+1 305 266 1984",
    "sg:postcode":"33155",
    "sg:province":"FL",
    "sg:tags":[
        "draperies",
        "vertical",
        "etc-wholesale",
        "fixture",
        "blinds-venetian",
        "window",
        "treatment",
        "shades-wholesale",
        "curtain",
        "drapery",
        "manufacturer"
    ],
    "wof:name":"Le Fer Forge Drapery Hardware",
    "wof:placetype":"venue"
},
  "geometry": {"coordinates":[-80.314851,25.727251],"type":"Point"}
}