{
  "type": "Feature",
  "properties": {
    "iso:country":"US",
    "sg:address":"2668 Cape View Ln",
    "sg:city":"Melbourne",
    "sg:classifiers":[
        {
            "category":"Wholesale",
            "subcategory":"Construction Materials",
            "type":"Manufacturing & Wholesale Goods"
        },
        {
            "category":"Building & Trades",
            "subcategory":"Construction",
            "type":"Services"
        }
    ],
    "sg:phone":"+1 321 254 7836",
    "sg:postcode":"32940",
    "sg:province":"FL",
    "sg:tags":[
        "fence",
        "contractor"
    ],
    "wof:name":"Defoe's Fencing",
    "wof:placetype":"venue"
},
  "geometry": {"coordinates":[-80.666318,28.204791],"type":"Point"}
}