{
  "type": "Feature",
  "properties": {
    "iso:country":"US",
    "sg:address":"26365 Bridgewater Rd",
    "sg:city":"Punta Gorda",
    "sg:classifiers":[
        {
            "category":"Insurance",
            "subcategory":"Insurance Agent",
            "type":"Services"
        }
    ],
    "sg:phone":"+1 941 624 2100",
    "sg:postcode":"33983",
    "sg:province":"FL",
    "wof:name":"Primerica Services",
    "wof:placetype":"venue"
},
  "geometry": {"coordinates":[-82.012659,27.000971],"type":"Point"}
}