{
  "type": "Feature",
  "properties": {
    "iso:country":"US",
    "sg:address":"800 Fairway Dr",
    "sg:city":"Deerfield Beach",
    "sg:classifiers":[
        {
            "category":"Professional",
            "subcategory":"Computer Services",
            "type":"Services"
        }
    ],
    "sg:phone":"+1 954 427 4461",
    "sg:postcode":"33441",
    "sg:province":"FL",
    "sg:tags":[
        "programming",
        "related",
        "custom"
    ],
    "wof:name":"Idx Systems Corporation",
    "wof:placetype":"venue"
},
  "geometry": {"coordinates":[-80.11472500000001,26.326415],"type":"Point"}
}