{
  "type": "Feature",
  "properties": {
    "addr:full":"101 Orange Co Cir Winter Haven FL 33881",
    "addr:housenumber":"101",
    "addr:postcode":"33881",
    "addr:street":"Orange Co Cir",
    "iso:country":"US",
    "sg:address":"101 Orange Co Cir",
    "sg:city":"Winter Haven",
    "sg:classifiers":[
        {
            "category":"Manufacturing",
            "subcategory":"Printing",
            "type":"Manufacturing & Wholesale Goods"
        }
    ],
    "sg:phone":"+1 863 297 7090",
    "sg:postcode":"33881",
    "sg:province":"FL",
    "sg:tags":[
        "printer"
    ],
    "sg:website":"www.hhprint.net",
    "wof:name":"H & H Corporate Printing",
    "wof:placetype":"venue"
},
  "geometry": {"coordinates":[-81.703239,28.06986],"type":"Point"}
}