{
  "type": "Feature",
  "properties": {
    "addr:full":"126 Beal Pkwy SW Fort Walton Bch FL 32548",
    "addr:housenumber":"126",
    "addr:postcode":"32548",
    "addr:street":"Beal Pkwy Sw",
    "iso:country":"US",
    "sg:address":"126 Beal Pkwy SW",
    "sg:city":"Fort Walton Bch",
    "sg:classifiers":[
        {
            "category":"Organizations",
            "subcategory":"Membership Organization",
            "type":"Services"
        },
        {
            "category":"Social Services",
            "type":"Services"
        }
    ],
    "sg:phone":"+1 850 244 0778",
    "sg:postcode":"32548",
    "sg:province":"FL",
    "wof:name":"Sharing & Caring Inc",
    "wof:placetype":"venue"
},
  "geometry": {"coordinates":[-86.613252,30.405445],"type":"Point"}
}