{
  "type": "Feature",
  "properties": {
    "iso:country":"US",
    "sg:address":"9476 E Colonial Dr",
    "sg:city":"Orlando",
    "sg:classifiers":[
        {
            "category":"Food & Beverages",
            "subcategory":"Liquor & Beverages",
            "type":"Retail Goods"
        }
    ],
    "sg:phone":"+1 407 277 0271",
    "sg:postcode":"32817",
    "sg:province":"FL",
    "sg:tags":[
        "alcoholic"
    ],
    "wof:name":"A B C Fine Wine & Spirits 12",
    "wof:placetype":"venue"
},
  "geometry": {"coordinates":[-81.25332400000001,28.56832],"type":"Point"}
}