{
  "type": "Feature",
  "properties": {
    "addr:full":"915 Dogwood Way Panama City FL 32404",
    "addr:housenumber":"915",
    "addr:postcode":"32404",
    "addr:street":"Dogwood Way",
    "iso:country":"US",
    "sg:address":"915 Dogwood Way",
    "sg:city":"Panama City",
    "sg:classifiers":[
        {
            "category":"Utilities",
            "subcategory":"Refuse",
            "type":"Services"
        }
    ],
    "sg:phone":"+1 850 871 5716",
    "sg:postcode":"32404",
    "sg:province":"FL",
    "sg:tags":[
        "waste",
        "removal"
    ],
    "wof:name":"Kent Co Medical Svc",
    "wof:placetype":"venue"
},
  "geometry": {"coordinates":[-85.503888,30.17791],"type":"Point"}
}