{
  "type": "Feature",
  "properties": {
    "iso:country":"US",
    "sg:address":"3605 3rd St",
    "sg:city":"Vero Beach",
    "sg:classifiers":[
        {
            "category":"Building & Trades",
            "subcategory":"Construction",
            "type":"Services"
        }
    ],
    "sg:phone":"+1 772 778 2419",
    "sg:postcode":"32968",
    "sg:province":"FL",
    "sg:tags":[
        "maker",
        "cabinet"
    ],
    "wof:name":"Nick Moran Construction",
    "wof:placetype":"venue"
},
  "geometry": {"coordinates":[-80.42425,27.607576],"type":"Point"}
}