{
  "type": "Feature",
  "properties": {
    "iso:country":"US",
    "sg:address":"3877 Avalon Park East Blvd",
    "sg:city":"Orlando",
    "sg:classifiers":[
        {
            "category":"Banks & Credit Unions",
            "subcategory":"Bank",
            "type":"Services"
        }
    ],
    "sg:phone":"+1 407 381 1518",
    "sg:postcode":"32828",
    "sg:province":"FL",
    "wof:name":"First National Bank-Central Fl",
    "wof:placetype":"venue"
},
  "geometry": {"coordinates":[-81.143075,28.508427],"type":"Point"}
}