{
  "type": "Feature",
  "properties": {
    "iso:country":"US",
    "sg:address":"2305 S Orange Ave",
    "sg:city":"Orlando",
    "sg:classifiers":[
        {
            "category":"Retail",
            "subcategory":"Repair Shop",
            "type":"Services"
        }
    ],
    "sg:phone":"+1 407 841 1450",
    "sg:postcode":"32806",
    "sg:province":"FL",
    "sg:tags":[
        "machine"
    ],
    "wof:name":"Obm",
    "wof:placetype":"venue"
},
  "geometry": {"coordinates":[-81.376287,28.515759],"type":"Point"}
}