{
  "type": "Feature",
  "properties": {
    "iso:country":"US",
    "sg:address":"2205 Broadway",
    "sg:city":"Fort Myers",
    "sg:classifiers":[
        {
            "category":"Home & Garden",
            "subcategory":"Household Appliances",
            "type":"Retail Goods"
        }
    ],
    "sg:phone":"+1 239 337 2205",
    "sg:postcode":"33901",
    "sg:province":"FL",
    "sg:tags":[
        "repair"
    ],
    "wof:name":"Classic Sewing Center Inc",
    "wof:placetype":"venue"
},
  "geometry": {"coordinates":[-81.86844499999999,26.636301],"type":"Point"}
}