{
  "type": "Feature",
  "properties": {
    "iso:country":"US",
    "sg:address":"916 N State Rd 434",
    "sg:city":"Altamonte Spgs",
    "sg:classifiers":[
        {
            "category":"Building & Trades",
            "subcategory":"Plumbing",
            "type":"Services"
        }
    ],
    "sg:phone":"+1 407 788 8777",
    "sg:postcode":"32714",
    "sg:province":"FL",
    "sg:tags":[
        "conditioning",
        "air",
        "system",
        "contractor"
    ],
    "wof:name":"Air First Cooling & Heating",
    "wof:placetype":"venue"
},
  "geometry": {"coordinates":[-81.41909,28.680499],"type":"Point"}
}