{
  "type": "Feature",
  "properties": {
    "addr:full":"6915 Taft St Hollywood FL 33024",
    "addr:housenumber":"6915",
    "addr:postcode":"33024",
    "addr:street":"Taft St",
    "iso:country":"US",
    "sg:address":"6915 Taft St",
    "sg:city":"Hollywood",
    "sg:classifiers":[
        {
            "category":"Real Estate",
            "subcategory":"Real Estate Agent",
            "type":"Services"
        }
    ],
    "sg:phone":"+1 954 964 2702",
    "sg:postcode":"33024",
    "sg:province":"FL",
    "wof:name":"Act Now Realty",
    "wof:placetype":"venue"
},
  "geometry": {"coordinates":[-80.225891,26.024509],"type":"Point"}
}