{
  "type": "Feature",
  "properties": {
    "iso:country":"US",
    "sg:address":"6140 Edgewater Dr",
    "sg:city":"Orlando",
    "sg:classifiers":[
        {
            "category":"Building & Trades",
            "subcategory":"Construction",
            "type":"Services"
        }
    ],
    "sg:phone":"+1 407 290 6660",
    "sg:postcode":"32810",
    "sg:province":"FL",
    "sg:tags":[
        "contractor"
    ],
    "wof:name":"Contracting Griffith",
    "wof:placetype":"venue"
},
  "geometry": {"coordinates":[-81.418487,28.612873],"type":"Point"}
}