{
  "type": "Feature",
  "properties": {
    "iso:country":"US",
    "sg:address":"798 Port Leon Dr",
    "sg:city":"St Marks",
    "sg:classifiers":[
        {
            "category":"Recreation",
            "type":"Entertainment"
        }
    ],
    "sg:phone":"+1 850 925 4843",
    "sg:postcode":"32355",
    "sg:province":"FL",
    "sg:tags":[
        "party",
        "fishing"
    ],
    "wof:name":"Custom Charters",
    "wof:placetype":"venue"
},
  "geometry": {"coordinates":[-84.204172,30.156175],"type":"Point"}
}