{
  "type": "Feature",
  "properties": {
    "iso:country":"US",
    "sg:address":"1010 N Woodland Blvd",
    "sg:city":"Deland",
    "sg:classifiers":[
        {
            "category":"Travel",
            "subcategory":"Hotels & Motels",
            "type":"Entertainment"
        }
    ],
    "sg:phone":"+1 386 734 0670",
    "sg:postcode":"32720",
    "sg:province":"FL",
    "sg:website":"www.orangetreeinn.net",
    "wof:name":"Orange Tree Inn",
    "wof:placetype":"venue"
},
  "geometry": {"coordinates":[-81.30390199999999,29.0452],"type":"Point"}
}