{
  "type": "Feature",
  "properties": {
    "iso:country":"US",
    "sg:address":"51 Chestnut St S",
    "sg:city":"Jacksonville",
    "sg:classifiers":[
        {
            "category":"Place Of Worship",
            "subcategory":"Church",
            "type":"Public Place"
        },
        {
            "category":"Place Of Worship",
            "type":"Public Place"
        }
    ],
    "sg:phone":"+1 904 266 4964",
    "sg:postcode":"32234",
    "sg:province":"FL",
    "sg:tags":[
        "churches-united",
        "methodist",
        "churches-methodist"
    ],
    "wof:name":"Baldwin United Methodist Church",
    "wof:placetype":"venue"
},
  "geometry": {"coordinates":[-81.976421,30.302426],"type":"Point"}
}