{
  "type": "Feature",
  "properties": {
    "iso:country":"US",
    "sg:address":"5242 State Rd 54",
    "sg:city":"New Port Richey",
    "sg:classifiers":[
        {
            "category":"Building & Trades",
            "subcategory":"Pest Control",
            "type":"Services"
        }
    ],
    "sg:phone":"+1 727 815 0338",
    "sg:postcode":"34652",
    "sg:province":"FL",
    "wof:name":"Slicker Exterminator Inc",
    "wof:placetype":"venue"
},
  "geometry": {"coordinates":[-82.72343499999999,28.217004],"type":"Point"}
}