{
  "type": "Feature",
  "properties": {
    "addr:full":"871 Venetia Bay Blvd Venice FL 34285",
    "addr:housenumber":"871",
    "addr:postcode":"34285",
    "addr:street":"Venetia Bay Blvd",
    "iso:country":"US",
    "sg:address":"871 Venetia Bay Blvd",
    "sg:city":"Venice",
    "sg:classifiers":[
        {
            "category":"Insurance",
            "subcategory":"Life Insurance",
            "type":"Services"
        }
    ],
    "sg:phone":"+1 941 918 9812",
    "sg:postcode":"34285",
    "sg:province":"FL",
    "sg:tags":[
        "carrier"
    ],
    "wof:name":"Statewide Family Insur Svcs",
    "wof:placetype":"venue"
},
  "geometry": {"coordinates":[-82.444738,27.111929],"type":"Point"}
}