{
  "type": "Feature",
  "properties": {
    "iso:country":"US",
    "sg:address":"180 Treemonte Dr",
    "sg:city":"Orange City",
    "sg:classifiers":[
        {
            "category":"Health Services",
            "subcategory":"Medical Lab",
            "type":"Services"
        }
    ],
    "sg:phone":"+1 386 775 4900",
    "sg:postcode":"32763",
    "sg:province":"FL",
    "sg:tags":[
        "detection",
        "equipment",
        "drug"
    ],
    "wof:name":"Guardian Occupational Svc",
    "wof:placetype":"venue"
},
  "geometry": {"coordinates":[-81.29777900000001,28.918607],"type":"Point"}
}