{
  "type": "Feature",
  "properties": {
    "addr:full":"7752 Royal Hart Dr New Port Richey FL 34653",
    "addr:housenumber":"7752",
    "addr:postcode":"34653",
    "addr:street":"Royal Hart Dr",
    "iso:country":"US",
    "sg:address":"7752 Royal Hart Dr",
    "sg:city":"New Port Richey",
    "sg:classifiers":[
        {
            "category":"Manufacturing",
            "subcategory":"Retail Goods",
            "type":"Manufacturing & Wholesale Goods"
        }
    ],
    "sg:phone":"+1 727 372 0155",
    "sg:postcode":"34653",
    "sg:province":"FL",
    "sg:tags":[
        "product",
        "mfg"
    ],
    "wof:name":"In10did Inc",
    "wof:placetype":"venue"
},
  "geometry": {"coordinates":[-82.685204,28.231922],"type":"Point"}
}