{
  "type": "Feature",
  "properties": {
    "addr:full":"12509 SW 112th Ter Miami FL 33186",
    "addr:housenumber":"12509",
    "addr:postcode":"33186",
    "addr:street":"Sw 112Th Ter",
    "iso:country":"US",
    "sg:address":"12509 SW 112th Ter",
    "sg:city":"Miami",
    "sg:classifiers":[
        {
            "category":"Wholesale",
            "subcategory":"Machinery & Supplies",
            "type":"Manufacturing & Wholesale Goods"
        }
    ],
    "sg:phone":"+1 305 630 3332",
    "sg:postcode":"33186",
    "sg:province":"FL",
    "sg:tags":[
        "equipment",
        "establishment"
    ],
    "wof:name":"Gem Products & Systems Inc",
    "wof:placetype":"venue"
},
  "geometry": {"coordinates":[-80.398042,25.663653],"type":"Point"}
}