{
  "type": "Feature",
  "properties": {
    "addr:full":"2812 Kenilworth Blvd Sebring FL 33870",
    "addr:housenumber":"2812",
    "addr:postcode":"33870",
    "addr:street":"Kenilworth Blvd",
    "iso:country":"US",
    "sg:address":"2812 Kenilworth Blvd",
    "sg:city":"Sebring",
    "sg:classifiers":[
        {
            "category":"Organizations",
            "subcategory":"Religious Organization",
            "type":"Services"
        }
    ],
    "sg:phone":"+1 863 471 0228",
    "sg:postcode":"33870",
    "sg:province":"FL",
    "sg:tags":[
        "church"
    ],
    "wof:name":"Michael John Conner Christians",
    "wof:placetype":"venue"
},
  "geometry": {"coordinates":[-81.439205,27.485867],"type":"Point"}
}