{
  "type": "Feature",
  "properties": {
    "iso:country":"US",
    "sg:address":"6840 State Hwy 97",
    "sg:city":"Walnut Hill",
    "sg:classifiers":[
        {
            "category":"Organizations",
            "subcategory":"Religious Organization",
            "type":"Services"
        }
    ],
    "sg:phone":"+1 850 327 4406",
    "sg:postcode":"32568",
    "sg:province":"FL",
    "sg:tags":[
        "church"
    ],
    "wof:name":"Walnut Hill Mennonite Church",
    "wof:placetype":"venue"
},
  "geometry": {"coordinates":[-87.451892,30.885375],"type":"Point"}
}