{
  "type": "Feature",
  "properties": {
    "iso:country":"US",
    "sg:address":"651 NE 19th Ave",
    "sg:city":"Fort Lauderdale",
    "sg:classifiers":[
        {
            "category":"Banks & Credit Unions",
            "subcategory":"Bank",
            "type":"Services"
        }
    ],
    "sg:phone":"+1 954 772 2227",
    "sg:postcode":"33304",
    "sg:province":"FL",
    "sg:tags":[
        "loan",
        "real estate"
    ],
    "wof:name":"Chase Manhattan Lending Loans",
    "wof:placetype":"venue"
},
  "geometry": {"coordinates":[-80.121003,26.131499],"type":"Point"}
}