{
  "type": "Feature",
  "properties": {
    "iso:country":"US",
    "sg:address":"17160 Royal Palm Blvd",
    "sg:city":"Weston",
    "sg:classifiers":[
        {
            "category":"Personal",
            "subcategory":"Massage",
            "type":"Services"
        },
        {
            "category":"Health Services",
            "subcategory":"Chiropractor",
            "type":"Services"
        }
    ],
    "sg:phone":"+1 954 895 7896",
    "sg:postcode":"33326",
    "sg:province":"FL",
    "sg:tags":[
        "therapist",
        "chiropractic"
    ],
    "wof:name":"Windmill Chiropractic",
    "wof:placetype":"venue"
},
  "geometry": {"coordinates":[-80.375534,26.088023],"type":"Point"}
}