{
  "type": "Feature",
  "properties": {
    "iso:country":"US",
    "sg:address":"4095 State Hwy 7",
    "sg:city":"Lake Worth",
    "sg:classifiers":[
        {
            "category":"Retail",
            "subcategory":"Laundry & Dry Cleaning",
            "type":"Services"
        }
    ],
    "sg:phone":"+1 561 357 0818",
    "sg:postcode":"33467",
    "sg:province":"FL",
    "sg:tags":[
        "cleaners"
    ],
    "wof:name":"Dryclean USA",
    "wof:placetype":"venue"
},
  "geometry": {"coordinates":[-80.204672,26.620309],"type":"Point"}
}