{
  "type": "Feature",
  "properties": {
    "addr:full":"7140 N Miami Ave Miami FL 33150",
    "addr:housenumber":"7140",
    "addr:postcode":"33150",
    "addr:street":"N Miami Ave",
    "iso:country":"US",
    "sg:address":"7140 N Miami Ave",
    "sg:city":"Miami",
    "sg:classifiers":[
        {
            "category":"Place Of Worship",
            "subcategory":"Church",
            "type":"Public Place"
        },
        {
            "category":"Place Of Worship",
            "type":"Public Place"
        },
        {
            "category":"Organizations",
            "subcategory":"Religious Organization",
            "type":"Services"
        }
    ],
    "sg:phone":"+1 305 758 7891",
    "sg:postcode":"33150",
    "sg:province":"FL",
    "sg:tags":[
        "god",
        "churches-church",
        "churches-pentecostal"
    ],
    "wof:name":"First Haitian Church Of God",
    "wof:placetype":"venue"
},
  "geometry": {"coordinates":[-80.19655899999999,25.84007],"type":"Point"}
}