{
  "type": "Feature",
  "properties": {
    "iso:country":"US",
    "sg:address":"5654 Jason Lee Pl",
    "sg:city":"Sarasota",
    "sg:classifiers":[
        {
            "category":"Health Services",
            "subcategory":"Medical Lab",
            "type":"Services"
        }
    ],
    "sg:phone":"+1 941 923 2611",
    "sg:postcode":"34233",
    "sg:province":"FL",
    "sg:tags":[
        "laboratory"
    ],
    "wof:name":"J M Dental Designs",
    "wof:placetype":"venue"
},
  "geometry": {"coordinates":[-82.47340699999999,27.270975],"type":"Point"}
}