{
  "type": "Feature",
  "properties": {
    "iso:country":"US",
    "sg:address":"1776 Ivalea Cir",
    "sg:city":"Navarre",
    "sg:classifiers":[
        {
            "category":"Building & Trades",
            "subcategory":"Construction",
            "type":"Services"
        }
    ],
    "sg:phone":"+1 850 255 8560",
    "sg:postcode":"32566",
    "sg:province":"FL",
    "sg:tags":[
        "contractor"
    ],
    "wof:name":"Charles Read Svc",
    "wof:placetype":"venue"
},
  "geometry": {"coordinates":[-86.916872,30.399006],"type":"Point"}
}