{
  "type": "Feature",
  "properties": {
    "iso:country":"US",
    "sg:address":"507 Mercers Fernery Rd",
    "sg:city":"Deland",
    "sg:classifiers":[
        {
            "category":"Professional",
            "type":"Services"
        }
    ],
    "sg:phone":"+1 386 738 5637",
    "sg:postcode":"32720",
    "sg:province":"FL",
    "sg:tags":[
        "establishment"
    ],
    "wof:name":"Barnworks Corp",
    "wof:placetype":"venue"
},
  "geometry": {"coordinates":[-81.31447199999999,29.064565],"type":"Point"}
}