{
  "type": "Feature",
  "properties": {
    "iso:country":"US",
    "sg:address":"Dolphin Mall 11401 NW 12 th St",
    "sg:city":"Miami",
    "sg:classifiers":[
        {
            "category":"Shopping",
            "subcategory":"Clothing, Apparel, & Fashions",
            "type":"Retail Goods"
        }
    ],
    "sg:postcode":"33172",
    "sg:province":"FL",
    "sg:tags":[
        "accessory"
    ],
    "sg:website":"www.aldoshoes.com/us/accessories",
    "wof:name":"Aldo Accessories",
    "wof:placetype":"venue"
},
  "geometry": {"coordinates":[-80.377607,25.786696],"type":"Point"}
}