{
  "type": "Feature",
  "properties": {
    "iso:country":"US",
    "sg:address":"700 Euclid Ave",
    "sg:city":"Miami Beach",
    "sg:classifiers":[
        {
            "category":"Professional",
            "type":"Services"
        }
    ],
    "sg:phone":"+1 305 610 5432",
    "sg:postcode":"33139",
    "sg:province":"FL",
    "wof:name":"Desiree Nercessian",
    "wof:placetype":"venue"
},
  "geometry": {"coordinates":[-80.13505000000001,25.778309],"type":"Point"}
}