{
  "type": "Feature",
  "properties": {
    "addr:full":"601 Valle Vista Dr Brandon FL 33511",
    "addr:housenumber":"601",
    "addr:postcode":"33511",
    "addr:street":"Valle Vista Dr",
    "iso:country":"US",
    "sg:address":"601 Valle Vista Dr",
    "sg:city":"Brandon",
    "sg:classifiers":[
        {
            "category":"Shopping",
            "subcategory":"Gifts & Souvenirs",
            "type":"Retail Goods"
        }
    ],
    "sg:phone":"+1 813 685 3130",
    "sg:postcode":"33511",
    "sg:province":"FL",
    "wof:name":"Flotella 74 of Brandon",
    "wof:placetype":"venue"
},
  "geometry": {"coordinates":[-82.290385,27.89133],"type":"Point"}
}