{
  "type": "Feature",
  "properties": {
    "iso:country":"US",
    "sg:address":"915 SW 4th Ave",
    "sg:city":"Trenton",
    "sg:classifiers":[
        {
            "category":"Professional",
            "subcategory":"Detective & Security Services",
            "type":"Services"
        }
    ],
    "sg:phone":"+1 352 427 2701",
    "sg:postcode":"32693",
    "sg:province":"FL",
    "sg:tags":[
        "information",
        "bureau"
    ],
    "wof:name":"Boyette Property Services, Inc.",
    "wof:placetype":"venue"
},
  "geometry": {"coordinates":[-82.82603400000001,29.610418],"type":"Point"}
}