{
  "type": "Feature",
  "properties": {
    "iso:country":"US",
    "sg:address":"151 Regions Way",
    "sg:city":"Destin",
    "sg:classifiers":[
        {
            "category":"Building & Trades",
            "subcategory":"Construction",
            "type":"Services"
        }
    ],
    "sg:phone":"+1 850 837 9838",
    "sg:postcode":"32541",
    "sg:province":"FL",
    "sg:tags":[
        "contractor"
    ],
    "wof:name":"Pinnacle Builders",
    "wof:placetype":"venue"
},
  "geometry": {"coordinates":[-86.41989,30.38867],"type":"Point"}
}