{
  "type": "Feature",
  "properties": {
    "iso:country":"US",
    "sg:address":"3219 Cortez Blvd",
    "sg:city":"Fort Myers",
    "sg:classifiers":[
        {
            "category":"Professional",
            "type":"Services"
        }
    ],
    "sg:phone":"+1 239 275 8243",
    "sg:postcode":"33901",
    "sg:province":"FL",
    "wof:name":"Hidden Dreams Inc",
    "wof:placetype":"venue"
},
  "geometry": {"coordinates":[-81.880118,26.61811],"type":"Point"}
}