{
  "type": "Feature",
  "properties": {
    "addr:full":"11018 Old Saint Augustine Rd Jacksonville FL 32257",
    "addr:housenumber":"11018",
    "addr:postcode":"32257",
    "addr:street":"Old Saint Augustine Rd",
    "iso:country":"US",
    "sg:address":"11018 Old Saint Augustine Rd",
    "sg:city":"Jacksonville",
    "sg:classifiers":[
        {
            "category":"Restaurant",
            "type":"Food & Drink"
        }
    ],
    "sg:menulink":"http://www.allmenus.com/fl/jacksonville/106246-little-china/menu/",
    "sg:phone":"+1 904 880 6200",
    "sg:postcode":"32257",
    "sg:province":"FL",
    "sg:tags":[
        "asian",
        "chinese"
    ],
    "wof:name":"Little China",
    "wof:placetype":"venue"
},
  "geometry": {"coordinates":[-81.60389000000001,30.174626],"type":"Point"}
}