{
  "type": "Feature",
  "properties": {
    "iso:country":"US",
    "sg:address":"116 W State Road 434",
    "sg:city":"Winter Springs",
    "sg:classifiers":[
        {
            "category":"Winery",
            "type":"Food & Drink"
        }
    ],
    "sg:phone":"+1 407 327 8467",
    "sg:postcode":"32708",
    "sg:province":"FL",
    "sg:website":"www.dvinewineusa.com",
    "wof:name":"D'vine Wine Your Personal Winery",
    "wof:placetype":"venue"
},
  "geometry": {"coordinates":[-81.305852,28.698801],"type":"Point"}
}