{
  "type": "Feature",
  "properties": {
    "addr:full":"2727 N Ocean Blvd Delray Beach FL 33483",
    "addr:housenumber":"2727",
    "addr:postcode":"33483",
    "addr:street":"N Ocean Blvd",
    "iso:country":"US",
    "sg:address":"2727 N Ocean Blvd",
    "sg:city":"Delray Beach",
    "sg:classifiers":[
        {
            "category":"Real Estate",
            "subcategory":"Real Estate Agent",
            "type":"Services"
        }
    ],
    "sg:phone":"+1 561 278 1187",
    "sg:postcode":"33483",
    "sg:province":"FL",
    "wof:name":"Westminster Inc",
    "wof:placetype":"venue"
},
  "geometry": {"coordinates":[-80.05614799999999,26.481187],"type":"Point"}
}