{
  "type": "Feature",
  "properties": {
    "addr:full":"1111 96th St Miami Beach FL 33154",
    "addr:housenumber":"1111",
    "addr:postcode":"33154",
    "addr:street":"96Th St",
    "iso:country":"US",
    "sg:address":"1111 96th St",
    "sg:city":"Miami Beach",
    "sg:classifiers":[
        {
            "category":"Banks & Credit Unions",
            "subcategory":"Investment Brokerage",
            "type":"Services"
        }
    ],
    "sg:phone":"+1 305 867 4596",
    "sg:postcode":"33154",
    "sg:province":"FL",
    "sg:tags":[
        "advisory",
        "consulting",
        "management"
    ],
    "wof:name":"Raymond James Financial Svcs",
    "wof:placetype":"venue"
},
  "geometry": {"coordinates":[-80.133073,25.886755],"type":"Point"}
}