{
  "type": "Feature",
  "properties": {
    "addr:full":"7410 S Bedford Rd Floral City FL 34436",
    "addr:housenumber":"7410",
    "addr:postcode":"34436",
    "addr:street":"S Bedford Rd",
    "iso:country":"US",
    "sg:address":"7410 S Bedford Rd",
    "sg:city":"Floral City",
    "sg:classifiers":[
        {
            "category":"Wholesale",
            "subcategory":"Auto Parts",
            "type":"Manufacturing & Wholesale Goods"
        }
    ],
    "sg:phone":"+1 352 726 5847",
    "sg:postcode":"34436",
    "sg:province":"FL",
    "sg:tags":[
        "automobile",
        "rebuilt"
    ],
    "wof:name":"AOK Used Auto Parts",
    "wof:placetype":"venue"
},
  "geometry": {"coordinates":[-82.298733,28.755422],"type":"Point"}
}