{
  "type": "Feature",
  "properties": {
    "iso:country":"US",
    "sg:address":"1277 N Semoran Blvd Suite 102",
    "sg:city":"Orlando",
    "sg:classifiers":[
        {
            "category":"Real Estate",
            "subcategory":"Real Estate Services",
            "type":"Services"
        },
        {
            "category":"Personal",
            "type":"Services"
        },
        {
            "category":"Real Estate",
            "subcategory":"Real Estate Agent",
            "type":"Services"
        }
    ],
    "sg:phone":"+1 877 267 7492",
    "sg:postcode":"32807",
    "sg:province":"FL",
    "sg:tags":[
        "management",
        "consultant",
        "vacancy",
        "maintenance",
        "listing",
        "property",
        "rental"
    ],
    "sg:website":"http://local.ingenio.com/Listings/Details.aspx?NUM=a%3a10311748%3a13%3a4859924%3a14%3a0%3a7",
    "wof:name":"All County CFL Property Management",
    "wof:placetype":"venue"
},
  "geometry": {"coordinates":[-81.310867,28.563049],"type":"Point"}
}