{
  "type": "Feature",
  "properties": {
    "addr:full":"808 W Waters Ave Tampa FL 33604",
    "addr:housenumber":"808",
    "addr:postcode":"33604",
    "addr:street":"W Waters Ave",
    "iso:country":"US",
    "sg:address":"808 W Waters Ave",
    "sg:city":"Tampa",
    "sg:classifiers":[
        {
            "category":"Professional",
            "subcategory":"Management & Consulting",
            "type":"Services"
        }
    ],
    "sg:phone":"+1 813 930 8442",
    "sg:postcode":"33604",
    "sg:province":"FL",
    "sg:tags":[
        "marketing",
        "direct",
        "response"
    ],
    "wof:name":"Advantage Media Group Inc",
    "wof:placetype":"venue"
},
  "geometry": {"coordinates":[-82.46767800000001,28.025265],"type":"Point"}
}