{
  "type": "Feature",
  "properties": {
    "addr:full":"2121 Ponce de Leon Blvd Miami FL 33134",
    "addr:housenumber":"2121",
    "addr:postcode":"33134",
    "addr:street":"Ponce De Leon Blvd",
    "iso:country":"US",
    "sg:address":"2121 Ponce de Leon Blvd",
    "sg:city":"Miami",
    "sg:classifiers":[
        {
            "category":"Freight",
            "type":"Transportation"
        }
    ],
    "sg:phone":"+1 305 443 4347",
    "sg:postcode":"33134",
    "sg:province":"FL",
    "sg:tags":[
        "ship",
        "document",
        "inspection"
    ],
    "wof:name":"HINSIB Technical Office",
    "wof:placetype":"venue"
},
  "geometry": {"coordinates":[-80.25868800000001,25.753494],"type":"Point"}
}