{
  "type": "Feature",
  "properties": {
    "addr:full":"3742 SW 7th St Ocala FL 34474",
    "addr:housenumber":"3742",
    "addr:postcode":"34474",
    "addr:street":"Sw 7Th St",
    "iso:country":"US",
    "sg:address":"3742 SW 7th St",
    "sg:city":"Ocala",
    "sg:classifiers":[
        {
            "category":"Professional",
            "subcategory":"Advertising",
            "type":"Services"
        }
    ],
    "sg:phone":"+1 352 401 3678",
    "sg:postcode":"34474",
    "sg:province":"FL",
    "sg:tags":[
        "distribution"
    ],
    "wof:name":"Windshield Hps",
    "wof:placetype":"venue"
},
  "geometry": {"coordinates":[-82.18226,29.179985],"type":"Point"}
}