{
  "type": "Feature",
  "properties": {
    "addr:full":"4838 Kerry Forest Pkwy Tallahassee FL 32309",
    "addr:housenumber":"4838",
    "addr:postcode":"32309",
    "addr:street":"Kerry Forest Pkwy",
    "iso:country":"US",
    "sg:address":"4838 Kerry Forest Pkwy",
    "sg:city":"Tallahassee",
    "sg:classifiers":[
        {
            "category":"Shopping",
            "subcategory":"Gifts & Souvenirs",
            "type":"Retail Goods"
        }
    ],
    "sg:phone":"+1 850 575 2600",
    "sg:postcode":"32309",
    "sg:province":"FL",
    "sg:tags":[
        "shop"
    ],
    "wof:name":"Say Something Gifts & Embroide",
    "wof:placetype":"venue"
},
  "geometry": {"coordinates":[-84.216274,30.537971],"type":"Point"}
}