{
  "type": "Feature",
  "properties": {
    "addr:full":"11433 Lakeview Dr Pompano Beach FL 33071",
    "addr:housenumber":"11433",
    "addr:postcode":"33071",
    "addr:street":"Lakeview Dr",
    "iso:country":"US",
    "sg:address":"11433 Lakeview Dr",
    "sg:city":"Pompano Beach",
    "sg:classifiers":[
        {
            "category":"Professional",
            "type":"Services"
        }
    ],
    "sg:phone":"+1 954 346 9347",
    "sg:postcode":"33071",
    "sg:province":"FL",
    "wof:name":"Olstyn Inc",
    "wof:placetype":"venue"
},
  "geometry": {"coordinates":[-80.27711600000001,26.251035],"type":"Point"}
}