{
  "type": "Feature",
  "properties": {
    "addr:full":"452 US Hwy 41 Venice FL 34285",
    "addr:housenumber":"452",
    "addr:postcode":"34285",
    "addr:street":"Us Hwy 41",
    "iso:country":"US",
    "sg:address":"452 US Hwy 41",
    "sg:city":"Venice",
    "sg:classifiers":[
        {
            "category":"Personal",
            "subcategory":"Barber",
            "type":"Services"
        }
    ],
    "sg:phone":"+1 941 485 3131",
    "sg:postcode":"34285",
    "sg:province":"FL",
    "wof:name":"Partridge's Barber Shop",
    "wof:placetype":"venue"
},
  "geometry": {"coordinates":[-82.444413,27.093111],"type":"Point"}
}