{
  "type": "Feature",
  "properties": {
    "iso:country":"US",
    "sg:address":"10100 NW 27th Ave",
    "sg:city":"Miami",
    "sg:classifiers":[
        {
            "category":"Autos & Motor Vehicles",
            "subcategory":"Auto Supplies",
            "type":"Retail Goods"
        }
    ],
    "sg:phone":"+1 305 836 0005",
    "sg:postcode":"33147",
    "sg:province":"FL",
    "sg:tags":[
        "tire"
    ],
    "wof:name":"J & A Tires",
    "wof:placetype":"venue"
},
  "geometry": {"coordinates":[-80.242401,25.8668],"type":"Point"}
}