{
  "type": "Feature",
  "properties": {
    "addr:full":"18401 Miramar Pkwy Hollywood FL 33029",
    "addr:housenumber":"18401",
    "addr:postcode":"33029",
    "addr:street":"Miramar Pkwy",
    "iso:country":"US",
    "sg:address":"18401 Miramar Pkwy",
    "sg:city":"Hollywood",
    "sg:classifiers":[
        {
            "category":"Insurance",
            "subcategory":"Insurance Agent",
            "type":"Services"
        }
    ],
    "sg:phone":"+1 954 442 9300",
    "sg:postcode":"33029",
    "sg:province":"FL",
    "wof:name":"Gillette Insurance Agency Inc",
    "wof:placetype":"venue"
},
  "geometry": {"coordinates":[-80.39603099999999,25.979357],"type":"Point"}
}