{
  "type": "Feature",
  "properties": {
    "addr:full":"2457 S Hiawassee Rd Orlando FL 32835",
    "addr:housenumber":"2457",
    "addr:postcode":"32835",
    "addr:street":"S Hiawassee Rd",
    "iso:country":"US",
    "sg:address":"2457 S Hiawassee Rd",
    "sg:city":"Orlando",
    "sg:classifiers":[
        {
            "category":"Building & Trades",
            "subcategory":"Construction",
            "type":"Services"
        }
    ],
    "sg:phone":"+1 407 291 6740",
    "sg:postcode":"32835",
    "sg:province":"FL",
    "sg:tags":[
        "new",
        "family",
        "home"
    ],
    "wof:name":"Regal Classic Homes Inc",
    "wof:placetype":"venue"
},
  "geometry": {"coordinates":[-81.484634,28.516224],"type":"Point"}
}