{
  "type": "Feature",
  "properties": {
    "iso:country":"US",
    "sg:address":"6520 Ridge Rd",
    "sg:city":"Port Richey",
    "sg:classifiers":[
        {
            "category":"Social Services",
            "type":"Services"
        }
    ],
    "sg:phone":"+1 727 849 7794",
    "sg:postcode":"34668",
    "sg:province":"FL",
    "wof:name":"Red Cross",
    "wof:placetype":"venue"
},
  "geometry": {"coordinates":[-82.706729,28.280538],"type":"Point"}
}