{
  "type": "Feature",
  "properties": {
    "iso:country":"US",
    "sg:address":"7608 Wiltshire Park Pl",
    "sg:city":"Apollo Beach",
    "sg:classifiers":[
        {
            "category":"Wholesale",
            "subcategory":"Home Furnishings",
            "type":"Manufacturing & Wholesale Goods"
        }
    ],
    "sg:phone":"+1 813 741 1478",
    "sg:postcode":"33572",
    "sg:province":"FL",
    "wof:name":"A & P Italian Imports Inc",
    "wof:placetype":"venue"
},
  "geometry": {"coordinates":[-82.36720800000001,27.780882],"type":"Point"}
}