{
  "type": "Feature",
  "properties": {
    "addr:full":"3085 NW 57th St Miami FL 33142",
    "addr:housenumber":"3085",
    "addr:postcode":"33142",
    "addr:street":"Nw 57Th St",
    "iso:country":"US",
    "sg:address":"3085 NW 57th St",
    "sg:city":"Miami",
    "sg:classifiers":[
        {
            "category":"Building & Trades",
            "subcategory":"Locksmith",
            "type":"Services"
        }
    ],
    "sg:phone":"+1 786 718 1409",
    "sg:postcode":"33142",
    "sg:province":"FL",
    "sg:tags":[
        "key"
    ],
    "wof:name":"Emergency Locksmith",
    "wof:placetype":"venue"
},
  "geometry": {"coordinates":[-80.246695,25.826626],"type":"Point"}
}