{
  "type": "Feature",
  "properties": {
    "addr:full":"4432 Production Ct Tallahassee FL 32310",
    "addr:housenumber":"4432",
    "addr:postcode":"32310",
    "addr:street":"Production Ct",
    "iso:country":"US",
    "sg:address":"4432 Production Ct",
    "sg:city":"Tallahassee",
    "sg:classifiers":[
        {
            "category":"Building & Trades",
            "subcategory":"Plumbing",
            "type":"Services"
        }
    ],
    "sg:phone":"+1 850 574 2156",
    "sg:postcode":"32310",
    "sg:province":"FL",
    "sg:tags":[
        "septic"
    ],
    "wof:name":"Buddy's Septic Tank Svc",
    "wof:placetype":"venue"
},
  "geometry": {"coordinates":[-84.32528499999999,30.402319],"type":"Point"}
}