{
  "type": "Feature",
  "properties": {
    "iso:country":"US",
    "sg:address":"951 Bald Eagle Dr",
    "sg:city":"Marco Island",
    "sg:classifiers":[
        {
            "category":"Professional",
            "type":"Services"
        }
    ],
    "sg:phone":"+1 239 642 6600",
    "sg:postcode":"34145",
    "sg:province":"FL",
    "wof:name":"Up To Sky & Back Inc",
    "wof:placetype":"venue"
},
  "geometry": {"coordinates":[-81.728008,25.962133],"type":"Point"}
}