{
  "type": "Feature",
  "properties": {
    "addr:full":"15270 Flight Path Dr Brooksville FL 34604",
    "addr:housenumber":"15270",
    "addr:postcode":"34604",
    "addr:street":"Flight Path Dr",
    "iso:country":"US",
    "sg:address":"15270 Flight Path Dr",
    "sg:city":"Brooksville",
    "sg:classifiers":[
        {
            "category":"Manufacturing",
            "subcategory":"Tools & Machinery",
            "type":"Manufacturing & Wholesale Goods"
        }
    ],
    "sg:phone":"+1 352 754 1117",
    "sg:postcode":"34604",
    "sg:province":"FL",
    "sg:tags":[
        "wheel",
        "for",
        "tire",
        "specialty",
        "equipment",
        "manufacturer"
    ],
    "wof:name":"Esco",
    "wof:placetype":"venue"
},
  "geometry": {"coordinates":[-82.46757100000001,28.478896],"type":"Point"}
}