{
  "type": "Feature",
  "properties": {
    "addr:full":"205 Waller Way St Augustine FL 32043",
    "addr:housenumber":"205",
    "addr:postcode":"32043",
    "addr:street":"Waller Way",
    "iso:country":"US",
    "sg:address":"205 Waller Way",
    "sg:city":"St Augustine",
    "sg:classifiers":[
        {
            "category":"Restaurant",
            "type":"Food & Drink"
        }
    ],
    "sg:phone":"+1 904 824 8948",
    "sg:postcode":"32043",
    "sg:province":"FL",
    "wof:name":"Mc Donald's",
    "wof:placetype":"venue"
},
  "geometry": {"coordinates":[-81.81647,30.045942],"type":"Point"}
}