{
  "type": "Feature",
  "properties": {
    "addr:full":"1250 Andrews Cir Starke FL 32091",
    "addr:housenumber":"1250",
    "addr:postcode":"32091",
    "addr:street":"Andrews Cir",
    "iso:country":"US",
    "sg:address":"1250 Andrews Cir",
    "sg:city":"Starke",
    "sg:classifiers":[
        {
            "category":"Education",
            "subcategory":"Music School",
            "type":"Public Place"
        },
        {
            "category":"Education",
            "subcategory":"School",
            "type":"Public Place"
        }
    ],
    "sg:phone":"+1 904 966 6800",
    "sg:postcode":"32091",
    "sg:province":"FL",
    "sg:tags":[
        "high",
        "information",
        "elementary",
        "district",
        "middle"
    ],
    "wof:name":"Bradford County School Board",
    "wof:placetype":"venue"
},
  "geometry": {"coordinates":[-82.107992,29.957185],"type":"Point"}
}