{
  "type": "Feature",
  "properties": {
    "iso:country":"US",
    "sg:address":"3367 SW 1st Ave",
    "sg:city":"Miami",
    "sg:classifiers":[
        {
            "category":"Professional",
            "type":"Services"
        }
    ],
    "sg:phone":"+1 305 856 2853",
    "sg:postcode":"33145",
    "sg:province":"FL",
    "wof:name":"Religous of The Apostolate Fla",
    "wof:placetype":"venue"
},
  "geometry": {"coordinates":[-80.214035,25.749433],"type":"Point"}
}