{
  "type": "Feature",
  "properties": {
    "addr:full":"9127 Chianti Ct Boynton Beach FL 33472",
    "addr:housenumber":"9127",
    "addr:postcode":"33472",
    "addr:street":"Chianti Ct",
    "iso:country":"US",
    "sg:address":"9127 Chianti Ct",
    "sg:city":"Boynton Beach",
    "sg:classifiers":[
        {
            "category":"Professional",
            "subcategory":"Management & Consulting",
            "type":"Services"
        }
    ],
    "sg:phone":"+1 561 364 0933",
    "sg:postcode":"33472",
    "sg:province":"FL",
    "sg:tags":[
        "business"
    ],
    "wof:name":"T R P Inc",
    "wof:placetype":"venue"
},
  "geometry": {"coordinates":[-80.13460000000001,26.540811],"type":"Point"}
}