{
  "type": "Feature",
  "properties": {
    "addr:full":"4473 Comanche Trail Blvd Jacksonville FL 32259",
    "addr:housenumber":"4473",
    "addr:postcode":"32259",
    "addr:street":"Comanche Trail Blvd",
    "iso:country":"US",
    "sg:address":"4473 Comanche Trail Blvd",
    "sg:city":"Jacksonville",
    "sg:classifiers":[
        {
            "category":"Manufacturing",
            "subcategory":"Tools & Machinery",
            "type":"Manufacturing & Wholesale Goods"
        }
    ],
    "sg:phone":"+1 904 287 2484",
    "sg:postcode":"32259",
    "sg:province":"FL",
    "sg:tags":[
        "terminal",
        "computer",
        "mfg"
    ],
    "wof:name":"Stouder Enterprises",
    "wof:placetype":"venue"
},
  "geometry": {"coordinates":[-81.535934,30.064575],"type":"Point"}
}