{
  "type": "Feature",
  "properties": {
    "iso:country":"US",
    "sg:address":"18604 Gulf Blvd",
    "sg:city":"Indian Shores",
    "sg:classifiers":[
        {
            "category":"Organizations",
            "subcategory":"Community Association",
            "type":"Services"
        }
    ],
    "sg:phone":"+1 727 595 5256",
    "sg:postcode":"33785",
    "sg:province":"FL",
    "sg:tags":[
        "club"
    ],
    "wof:name":"Civitan Beach Club",
    "wof:placetype":"venue"
},
  "geometry": {"coordinates":[-82.83980099999999,27.841729],"type":"Point"}
}