{
  "type": "Feature",
  "properties": {
    "iso:country":"US",
    "sg:address":"2822 Willow Bay Ter",
    "sg:city":"Casselberry",
    "sg:classifiers":[
        {
            "category":"Professional",
            "subcategory":"Computer Services",
            "type":"Services"
        }
    ],
    "sg:phone":"+1 407 699 0000",
    "sg:postcode":"32707",
    "sg:province":"FL",
    "sg:tags":[
        "repair"
    ],
    "wof:name":"Rdsi Banking Systems",
    "wof:placetype":"venue"
},
  "geometry": {"coordinates":[-81.30921499999999,28.64529],"type":"Point"}
}