{
  "type": "Feature",
  "properties": {
    "addr:full":"1860 J and C Blvd Naples FL 34109",
    "addr:housenumber":"1860;and",
    "addr:postcode":"34109",
    "addr:street":"C Blvd",
    "iso:country":"US",
    "sg:address":"1860 J and C Blvd",
    "sg:city":"Naples",
    "sg:classifiers":[
        {
            "category":"Autos & Motor Vehicles",
            "subcategory":"Auto Supplies",
            "type":"Retail Goods"
        }
    ],
    "sg:phone":"+1 239 596 0262",
    "sg:postcode":"34109",
    "sg:province":"FL",
    "sg:tags":[
        "automobile",
        "parts"
    ],
    "wof:name":"NAPA Auto Parts",
    "wof:placetype":"venue"
},
  "geometry": {"coordinates":[-81.778791,26.223697],"type":"Point"}
}