{
  "type": "Feature",
  "properties": {
    "addr:full":"906 Park Ave Orange Park FL 32073",
    "addr:housenumber":"906",
    "addr:postcode":"32073",
    "addr:street":"Park Ave",
    "iso:country":"US",
    "sg:address":"906 Park Ave",
    "sg:city":"Orange Park",
    "sg:classifiers":[
        {
            "category":"Restaurant",
            "type":"Food & Drink"
        }
    ],
    "sg:phone":"+1 904 264 7325",
    "sg:postcode":"32073",
    "sg:province":"FL",
    "sg:tags":[
        "eating"
    ],
    "wof:name":"Sisters The",
    "wof:placetype":"venue"
},
  "geometry": {"coordinates":[-81.701725,30.177918],"type":"Point"}
}