{
  "type": "Feature",
  "properties": {
    "iso:country":"US",
    "sg:address":"123 S Ocean Ave",
    "sg:city":"West Palm Beach",
    "sg:classifiers":[
        {
            "category":"Travel",
            "subcategory":"Hotels & Motels",
            "type":"Entertainment"
        }
    ],
    "sg:phone":"+1 561 844 0233",
    "sg:postcode":"33404",
    "sg:province":"FL",
    "sg:tags":[
        "operation"
    ],
    "wof:name":"Best Western Seaspray Inn",
    "wof:placetype":"venue"
},
  "geometry": {"coordinates":[-80.03363400000001,26.779611],"type":"Point"}
}