{
  "type": "Feature",
  "properties": {
    "iso:country":"US",
    "sg:address":"1950 Lee Rd Ste 109",
    "sg:city":"Winter Park",
    "sg:classifiers":[
        {
            "category":"Health Services",
            "subcategory":"Clinic",
            "type":"Services"
        }
    ],
    "sg:phone":"+1 407 628 0504",
    "sg:postcode":"32789",
    "sg:province":"FL",
    "sg:tags":[
        "counseling",
        "mental"
    ],
    "wof:name":"Orlando Institute For Psychology and Education Inc",
    "wof:placetype":"venue"
},
  "geometry": {"coordinates":[-81.376107,28.605445],"type":"Point"}
}