{
  "type": "Feature",
  "properties": {
    "addr:full":"1101 Medford Ave Pensacola FL 32505",
    "addr:housenumber":"1101",
    "addr:postcode":"32505",
    "addr:street":"Medford Ave",
    "iso:country":"US",
    "sg:address":"1101 Medford Ave",
    "sg:city":"Pensacola",
    "sg:classifiers":[
        {
            "category":"Retail",
            "subcategory":"Auto Repair",
            "type":"Services"
        }
    ],
    "sg:phone":"+1 850 432 5948",
    "sg:postcode":"32505",
    "sg:province":"FL",
    "sg:tags":[
        "body",
        "automobile",
        "painting",
        "repairing"
    ],
    "wof:name":"Just Us 2 Body Oils",
    "wof:placetype":"venue"
},
  "geometry": {"coordinates":[-87.263519,30.460199],"type":"Point"}
}