{
  "type": "Feature",
  "properties": {
    "iso:country":"US",
    "sg:address":"440 N Orlando Ave",
    "sg:city":"Winter Park",
    "sg:classifiers":[
        {
            "category":"Shopping",
            "subcategory":"Pharmacy",
            "type":"Retail Goods"
        },
        {
            "category":"Food & Beverages",
            "subcategory":"Groceries & Convenience Stores",
            "type":"Retail Goods"
        }
    ],
    "sg:phone":"+1 407 740 0549",
    "sg:postcode":"32789",
    "sg:province":"FL",
    "sg:tags":[
        "drugstore"
    ],
    "wof:name":"Sav-On Pharmacy",
    "wof:placetype":"venue"
},
  "geometry": {"coordinates":[-81.36494399999999,28.601905],"type":"Point"}
}