{
  "type": "Feature",
  "properties": {
    "iso:country":"US",
    "sg:address":"7557 Arlington Expy",
    "sg:city":"Jacksonville",
    "sg:classifiers":[
        {
            "category":"Real Estate",
            "subcategory":"Real Estate Operator",
            "type":"Services"
        }
    ],
    "sg:phone":"+1 904 721 1257",
    "sg:postcode":"32211",
    "sg:province":"FL",
    "sg:tags":[
        "apartment",
        "complex"
    ],
    "wof:name":"Spanish Oak Apartments",
    "wof:placetype":"venue"
},
  "geometry": {"coordinates":[-81.580012,30.327874],"type":"Point"}
}