{
  "type": "Feature",
  "properties": {
    "iso:country":"US",
    "sg:address":"2161 Mc Coys Creek Blvd",
    "sg:city":"Jacksonville",
    "sg:classifiers":[
        {
            "category":"Wholesale",
            "subcategory":"Construction Materials",
            "type":"Manufacturing & Wholesale Goods"
        }
    ],
    "sg:phone":"+1 904 355 6651",
    "sg:postcode":"32204",
    "sg:province":"FL",
    "sg:tags":[
        "brick",
        "common",
        "face"
    ],
    "sg:website":"www.cashbuildingmaterial.com",
    "wof:name":"Cash Building Material Co",
    "wof:placetype":"venue"
},
  "geometry": {"coordinates":[-81.684665,30.327792],"type":"Point"}
}