{
  "type": "Feature",
  "properties": {
    "addr:full":"13142 N 22nd St Tampa FL 33612",
    "addr:housenumber":"13142",
    "addr:postcode":"33612",
    "addr:street":"N 22Nd St",
    "iso:country":"US",
    "sg:address":"13142 N 22nd St",
    "sg:city":"Tampa",
    "sg:classifiers":[
        {
            "category":"Real Estate",
            "subcategory":"Real Estate Operator",
            "type":"Services"
        }
    ],
    "sg:phone":"+1 813 971 4413",
    "sg:postcode":"33612",
    "sg:province":"FL",
    "sg:tags":[
        "apartment"
    ],
    "wof:name":"Fredericksburg Apartments",
    "wof:placetype":"venue"
},
  "geometry": {"coordinates":[-82.43462,28.066883],"type":"Point"}
}