{
  "type": "Feature",
  "properties": {
    "addr:full":"12026 Anderson Rd Tampa FL 33625",
    "addr:housenumber":"12026",
    "addr:postcode":"33625",
    "addr:street":"Anderson Rd",
    "iso:country":"US",
    "sg:address":"12026 Anderson Rd",
    "sg:city":"Tampa",
    "sg:classifiers":[
        {
            "category":"Food & Beverages",
            "subcategory":"Groceries & Convenience Stores",
            "type":"Retail Goods"
        }
    ],
    "sg:phone":"+1 813 968 2877",
    "sg:postcode":"33625",
    "sg:province":"FL",
    "sg:tags":[
        "grocer",
        "supermarket"
    ],
    "wof:name":"Publix Super Market 300",
    "wof:placetype":"venue"
},
  "geometry": {"coordinates":[-82.543604,28.056287],"type":"Point"}
}