{
  "type": "Feature",
  "properties": {
    "addr:full":"1366 18th St Sarasota FL 34234",
    "addr:housenumber":"1366",
    "addr:postcode":"34234",
    "addr:street":"18Th St",
    "iso:country":"US",
    "sg:address":"1366 18th St",
    "sg:city":"Sarasota",
    "sg:classifiers":[
        {
            "category":"Building & Trades",
            "subcategory":"Construction",
            "type":"Services"
        }
    ],
    "sg:phone":"+1 941 906 8553",
    "sg:postcode":"34234",
    "sg:province":"FL",
    "sg:tags":[
        "contractor"
    ],
    "wof:name":"Brown Abraham Sr Stucco",
    "wof:placetype":"venue"
},
  "geometry": {"coordinates":[-82.544173,27.353276],"type":"Point"}
}