{
  "type": "Feature",
  "properties": {
    "addr:full":"7733 Markham Bend Pl Sanford FL 32771",
    "addr:housenumber":"7733",
    "addr:postcode":"32771",
    "addr:street":"Markham Bend Pl",
    "iso:country":"US",
    "sg:address":"7733 Markham Bend Pl",
    "sg:city":"Sanford",
    "sg:classifiers":[
        {
            "category":"Home & Garden",
            "subcategory":"Building Materials",
            "type":"Retail Goods"
        }
    ],
    "sg:phone":"+1 407 330 0437",
    "sg:postcode":"32771",
    "sg:province":"FL",
    "wof:name":"Ply Trim South Inc",
    "wof:placetype":"venue"
},
  "geometry": {"coordinates":[-81.39715099999999,28.793915],"type":"Point"}
}