{
  "type": "Feature",
  "properties": {
    "iso:country":"US",
    "sg:address":"5041 Treiman Blvd",
    "sg:city":"Dade City",
    "sg:classifiers":[
        {
            "category":"Building & Trades",
            "subcategory":"Pest Control",
            "type":"Services"
        }
    ],
    "sg:phone":"+1 352 583 2245",
    "sg:postcode":"33523",
    "sg:province":"FL",
    "sg:tags":[
        "disinfecting"
    ],
    "wof:name":"Baloghs Pest Control",
    "wof:placetype":"venue"
},
  "geometry": {"coordinates":[-82.170531,28.507507],"type":"Point"}
}