{
  "type": "Feature",
  "properties": {
    "addr:full":"2161 N Sterling Rd Avon Park FL 33825",
    "addr:housenumber":"2161",
    "addr:postcode":"33825",
    "addr:street":"N Sterling Rd",
    "iso:country":"US",
    "sg:address":"2161 N Sterling Rd",
    "sg:city":"Avon Park",
    "sg:classifiers":[
        {
            "category":"Retail",
            "subcategory":"Car Wash",
            "type":"Services"
        }
    ],
    "sg:phone":"+1 863 453 9719",
    "sg:postcode":"33825",
    "sg:province":"FL",
    "sg:tags":[
        "carwash"
    ],
    "wof:name":"T Bay Auto Detailing",
    "wof:placetype":"venue"
},
  "geometry": {"coordinates":[-81.53658299999999,27.625719],"type":"Point"}
}