{
  "type": "Feature",
  "properties": {
    "addr:full":"3194 Old Jennings Rd Middleburg FL 32068",
    "addr:housenumber":"3194",
    "addr:postcode":"32068",
    "addr:street":"Old Jennings Rd",
    "iso:country":"US",
    "sg:address":"3194 Old Jennings Rd",
    "sg:city":"Middleburg",
    "sg:classifiers":[
        {
            "category":"Wholesale",
            "subcategory":"Home Furnishings",
            "type":"Manufacturing & Wholesale Goods"
        }
    ],
    "sg:phone":"+1 904 291 6542",
    "sg:postcode":"32068",
    "sg:province":"FL",
    "wof:name":"Heart Deco Inc",
    "wof:placetype":"venue"
},
  "geometry": {"coordinates":[-81.81620599999999,30.114675],"type":"Point"}
}