{
  "type": "Feature",
  "properties": {
    "iso:country":"US",
    "sg:address":"2325 New York St",
    "sg:city":"Melbourne",
    "sg:classifiers":[
        {
            "category":"Building & Trades",
            "subcategory":"Construction",
            "type":"Services"
        }
    ],
    "sg:phone":"+1 321 508 1154",
    "sg:postcode":"32904",
    "sg:province":"FL",
    "sg:tags":[
        "clearing",
        "land",
        "leveling"
    ],
    "wof:name":"Travis Clark Landscaping Svc",
    "wof:placetype":"venue"
},
  "geometry": {"coordinates":[-80.689123,28.068409],"type":"Point"}
}