{
  "type": "Feature",
  "properties": {
    "iso:country":"US",
    "sg:address":"12105 SW 130th St Ste 204",
    "sg:city":"Miami",
    "sg:classifiers":[
        {
            "category":"Professional",
            "subcategory":"Business Services",
            "type":"Services"
        }
    ],
    "sg:phone":"+1 305 259 7890",
    "sg:postcode":"33186",
    "sg:province":"FL",
    "sg:tags":[
        "exporter"
    ],
    "wof:name":"Blessing Angels Inc",
    "wof:placetype":"venue"
},
  "geometry": {"coordinates":[-80.39026200000001,25.647111],"type":"Point"}
}