{
  "type": "Feature",
  "properties": {
    "iso:country":"US",
    "sg:address":"2029 Melbourne Ct",
    "sg:city":"Melbourne",
    "sg:classifiers":[
        {
            "category":"Retail",
            "subcategory":"Animal Services",
            "type":"Services"
        }
    ],
    "sg:phone":"+1 321 724 9001",
    "sg:postcode":"32901",
    "sg:province":"FL",
    "sg:tags":[
        "pet",
        "grooming",
        "washing"
    ],
    "wof:name":"Animals Works",
    "wof:placetype":"venue"
},
  "geometry": {"coordinates":[-80.60542700000001,28.07702],"type":"Point"}
}