{
  "type": "Feature",
  "properties": {
    "addr:full":"8371 S Suncoast Blvd Homosassa FL 34446",
    "addr:housenumber":"8371",
    "addr:postcode":"34446",
    "addr:street":"S Suncoast Blvd",
    "iso:country":"US",
    "sg:address":"8371 S Suncoast Blvd",
    "sg:city":"Homosassa",
    "sg:classifiers":[
        {
            "category":"Building & Trades",
            "subcategory":"Construction",
            "type":"Services"
        }
    ],
    "sg:phone":"+1 352 382 7741",
    "sg:postcode":"34446",
    "sg:province":"FL",
    "sg:tags":[
        "carpet"
    ],
    "wof:name":"Duvalls Carpet & Vacuums LLC",
    "wof:placetype":"venue"
},
  "geometry": {"coordinates":[-82.552982,28.745111],"type":"Point"}
}