{
  "type": "Feature",
  "properties": {
    "iso:country":"US",
    "sg:address":"3701 NW 21st St",
    "sg:city":"Fort Lauderdale",
    "sg:classifiers":[
        {
            "category":"Building & Trades",
            "subcategory":"Landscaping Services",
            "type":"Services"
        }
    ],
    "sg:phone":"+1 954 731 4147",
    "sg:postcode":"33311",
    "sg:province":"FL",
    "wof:name":"Louis Jacques",
    "wof:placetype":"venue"
},
  "geometry": {"coordinates":[-80.197828,26.152957],"type":"Point"}
}