{
  "type": "Feature",
  "properties": {
    "iso:country":"US",
    "sg:address":"5931 Ravenswood Rd",
    "sg:city":"Fort Lauderdale",
    "sg:classifiers":[
        {
            "category":"Professional",
            "type":"Services"
        }
    ],
    "sg:phone":"+1 954 965 7170",
    "sg:postcode":"33312",
    "sg:province":"FL",
    "sg:tags":[
        "establishment"
    ],
    "wof:name":"Roxys Custom Covers",
    "wof:placetype":"venue"
},
  "geometry": {"coordinates":[-80.16820300000001,26.048838],"type":"Point"}
}