{
  "type": "Feature",
  "properties": {
    "iso:country":"US",
    "sg:address":"11350 NW 25th St",
    "sg:city":"Doral",
    "sg:classifiers":[
        {
            "category":"Manufacturing",
            "subcategory":"Tools & Machinery",
            "type":"Manufacturing & Wholesale Goods"
        }
    ],
    "sg:phone":"+1 305 639 9721",
    "sg:postcode":"33172",
    "sg:province":"FL",
    "sg:tags":[
        "computer",
        "parts",
        "supply"
    ],
    "wof:name":"Codegen USA Inc",
    "wof:placetype":"venue"
},
  "geometry": {"coordinates":[-80.383312,25.796774],"type":"Point"}
}