{
  "type": "Feature",
  "properties": {
    "iso:country":"US",
    "sg:address":"3642 NW 22nd Ave",
    "sg:city":"Miami",
    "sg:classifiers":[
        {
            "category":"Taxi",
            "type":"Transportation"
        },
        {
            "category":"Retail",
            "subcategory":"Auto Repair",
            "type":"Services"
        }
    ],
    "sg:phone":"+1 305 638 9641",
    "sg:postcode":"33142",
    "sg:province":"FL",
    "sg:tags":[
        "shop",
        "machine",
        "automobile"
    ],
    "wof:name":"Miami J M",
    "wof:placetype":"venue"
},
  "geometry": {"coordinates":[-80.23200199999999,25.8099],"type":"Point"}
}