{
  "type": "Feature",
  "properties": {
    "addr:full":"126 N Andalusia Ave Santa Rosa Beach FL 32459",
    "addr:housenumber":"126",
    "addr:postcode":"32459",
    "addr:street":"N Andalusia Ave",
    "iso:country":"US",
    "sg:address":"126 N Andalusia Ave",
    "sg:city":"Santa Rosa Beach",
    "sg:classifiers":[
        {
            "category":"Professional",
            "subcategory":"Management & Consulting",
            "type":"Services"
        }
    ],
    "sg:phone":"+1 850 231 6808",
    "sg:postcode":"32459",
    "sg:province":"FL",
    "sg:tags":[
        "retail",
        "direct",
        "sales"
    ],
    "wof:name":"Personal Preference",
    "wof:placetype":"venue"
},
  "geometry": {"coordinates":[-86.12222199999999,30.316717],"type":"Point"}
}