{
  "type": "Feature",
  "properties": {
    "addr:full":"673 Lee Ave Crestview FL 32539",
    "addr:housenumber":"673",
    "addr:postcode":"32539",
    "addr:street":"Lee Ave",
    "iso:country":"US",
    "sg:address":"673 Lee Ave",
    "sg:city":"Crestview",
    "sg:classifiers":[
        {
            "category":"Insurance",
            "subcategory":"Insurance Agent",
            "type":"Services"
        }
    ],
    "sg:phone":"+1 850 689 7676",
    "sg:postcode":"32539",
    "sg:province":"FL",
    "sg:tags":[
        "processing"
    ],
    "wof:name":"Professional Medical Billing",
    "wof:placetype":"venue"
},
  "geometry": {"coordinates":[-86.55630600000001,30.750452],"type":"Point"}
}