{
  "type": "Feature",
  "properties": {
    "iso:country":"US",
    "sg:address":"6141 Mears Ct",
    "sg:city":"Clearwater",
    "sg:classifiers":[
        {
            "category":"Retail",
            "subcategory":"Laundry & Dry Cleaning",
            "type":"Services"
        }
    ],
    "sg:phone":"+1 727 523 8914",
    "sg:postcode":"33760",
    "sg:province":"FL",
    "sg:tags":[
        "cleaner",
        "drapery",
        "curtain"
    ],
    "wof:name":"Window & Shutter Designs Corp",
    "wof:placetype":"venue"
},
  "geometry": {"coordinates":[-82.719795,27.905406],"type":"Point"}
}