{
  "type": "Feature",
  "properties": {
    "addr:full":"4826 Kerry Forest Pkwy Tallahassee FL 32309",
    "addr:housenumber":"4826",
    "addr:postcode":"32309",
    "addr:street":"Kerry Forest Pkwy",
    "iso:country":"US",
    "sg:address":"4826 Kerry Forest Pkwy",
    "sg:city":"Tallahassee",
    "sg:classifiers":[
        {
            "category":"Professional",
            "subcategory":"Accounting & Tax Preparation",
            "type":"Services"
        }
    ],
    "sg:phone":"+1 850 668 2228",
    "sg:postcode":"32309",
    "sg:province":"FL",
    "wof:name":"A Kathy Carter CPA",
    "wof:placetype":"venue"
},
  "geometry": {"coordinates":[-84.216235,30.53791],"type":"Point"}
}