{
  "type": "Feature",
  "properties": {
    "iso:country":"US",
    "sg:address":"8255 W Flagler St",
    "sg:city":"Miami",
    "sg:classifiers":[
        {
            "category":"Fast Food",
            "type":"Food & Drink"
        },
        {
            "category":"Restaurant",
            "type":"Food & Drink"
        }
    ],
    "sg:phone":"+1 305 262 9766",
    "sg:postcode":"33144",
    "sg:province":"FL",
    "sg:tags":[
        "style",
        "hamburger",
        "family",
        "house",
        "dog",
        "hot",
        "barbecue",
        "steak"
    ],
    "sg:website":"http://www.outbacksteakhouse.com",
    "wof:name":"Outback Steakhouse",
    "wof:placetype":"venue"
},
  "geometry": {"coordinates":[-80.32959700000001,25.769699],"type":"Point"}
}