{
  "type": "Feature",
  "properties": {
    "iso:country":"US",
    "sg:address":"6703 W Hwy 98",
    "sg:city":"Panama City",
    "sg:classifiers":[
        {
            "category":"Manufacturing",
            "subcategory":"Printing",
            "type":"Manufacturing & Wholesale Goods"
        }
    ],
    "sg:phone":"+1 850 234 4466",
    "sg:postcode":"32407",
    "sg:province":"FL",
    "sg:tags":[
        "lithographic",
        "commercial"
    ],
    "wof:name":"Daps",
    "wof:placetype":"venue"
},
  "geometry": {"coordinates":[-85.75349300000001,30.18824],"type":"Point"}
}