{
  "type": "Feature",
  "properties": {
    "iso:country":"US",
    "sg:address":"7622 Emerald Dr",
    "sg:city":"Melbourne",
    "sg:classifiers":[
        {
            "category":"Home & Garden",
            "subcategory":"Building Materials",
            "type":"Retail Goods"
        }
    ],
    "sg:phone":"+1 321 727 9970",
    "sg:postcode":"32904",
    "sg:province":"FL",
    "sg:tags":[
        "shutter"
    ],
    "wof:name":"East Coast Shutter",
    "wof:placetype":"venue"
},
  "geometry": {"coordinates":[-80.673061,28.103258],"type":"Point"}
}