{
  "type": "Feature",
  "properties": {
    "iso:country":"US",
    "sg:address":"4110 Ludlam Rd",
    "sg:city":"Miami",
    "sg:classifiers":[
        {
            "category":"Professional",
            "subcategory":"Advertising",
            "type":"Services"
        },
        {
            "category":"Professional",
            "subcategory":"Research",
            "type":"Services"
        }
    ],
    "sg:phone":"+1 305 740 0661",
    "sg:postcode":"33155",
    "sg:province":"FL",
    "sg:tags":[
        "agency",
        "market",
        "analysis"
    ],
    "wof:name":"Miami Market Research",
    "wof:placetype":"venue"
},
  "geometry": {"coordinates":[-80.303791,25.754169],"type":"Point"}
}