{
  "type": "Feature",
  "properties": {
    "addr:full":"811 Apricot Dr Ocoee FL 34761",
    "addr:housenumber":"811",
    "addr:postcode":"34761",
    "addr:street":"Apricot Dr",
    "iso:country":"US",
    "sg:address":"811 Apricot Dr",
    "sg:city":"Ocoee",
    "sg:classifiers":[
        {
            "category":"Building & Trades",
            "subcategory":"Construction",
            "type":"Services"
        }
    ],
    "sg:phone":"+1 407 654 9698",
    "sg:postcode":"34761",
    "sg:province":"FL",
    "sg:tags":[
        "concrete",
        "contractor"
    ],
    "wof:name":"Kati Hopper Concrete Pumping I",
    "wof:placetype":"venue"
},
  "geometry": {"coordinates":[-81.526126,28.580184],"type":"Point"}
}