{
  "type": "Feature",
  "properties": {
    "addr:full":"4186 NW 65th Ave Pompano Beach FL 33067",
    "addr:housenumber":"4186",
    "addr:postcode":"33067",
    "addr:street":"Nw 65Th Ave",
    "iso:country":"US",
    "sg:address":"4186 NW 65th Ave",
    "sg:city":"Pompano Beach",
    "sg:classifiers":[
        {
            "category":"Health Services",
            "subcategory":"Clinic",
            "type":"Services"
        }
    ],
    "sg:phone":"+1 954 757 3328",
    "sg:postcode":"33067",
    "sg:province":"FL",
    "wof:name":"Merk Medical Distributors",
    "wof:placetype":"venue"
},
  "geometry": {"coordinates":[-80.212434,26.281798],"type":"Point"}
}