{
  "type": "Feature",
  "properties": {
    "addr:full":"303 Anastasia Blvd St Augustine FL 32080",
    "addr:housenumber":"303",
    "addr:postcode":"32080",
    "addr:street":"Anastasia Blvd St",
    "iso:country":"US",
    "sg:address":"303 Anastasia Blvd",
    "sg:city":"St Augustine",
    "sg:classifiers":[
        {
            "category":"Health Services",
            "subcategory":"Doctor",
            "type":"Services"
        }
    ],
    "sg:phone":"+1 904 810 2320",
    "sg:postcode":"32080",
    "sg:province":"FL",
    "sg:tags":[
        "dentist"
    ],
    "wof:name":"Maria Z Narvaez DDS",
    "wof:placetype":"venue"
},
  "geometry": {"coordinates":[-81.299421,29.891441],"type":"Point"}
}