{
  "type": "Feature",
  "properties": {
    "iso:country":"US",
    "sg:address":"10761 NW 17th St",
    "sg:city":"Plantation",
    "sg:classifiers":[
        {
            "category":"Personal",
            "type":"Services"
        },
        {
            "category":"Professional",
            "subcategory":"Art Services",
            "type":"Services"
        }
    ],
    "sg:phone":"+1 954 472 7177",
    "sg:postcode":"33322",
    "sg:province":"FL",
    "sg:tags":[
        "photography",
        "videography",
        "wedding"
    ],
    "wof:name":"Assoc Ae Bryer",
    "wof:placetype":"venue"
},
  "geometry": {"coordinates":[-80.291141,26.144304],"type":"Point"}
}