{
  "type": "Feature",
  "properties": {
    "iso:country":"US",
    "sg:address":"16900 N Bay Rd",
    "sg:city":"Sunny Isles Beach",
    "sg:classifiers":[
        {
            "category":"Banks & Credit Unions",
            "subcategory":"Financial Services",
            "type":"Services"
        }
    ],
    "sg:phone":"+1 305 948 8155",
    "sg:postcode":"33160",
    "sg:province":"FL",
    "sg:tags":[
        "broker",
        "mortgage"
    ],
    "wof:name":"Clearwater Funding Group Inc",
    "wof:placetype":"venue"
},
  "geometry": {"coordinates":[-80.126007,25.930585],"type":"Point"}
}