{
  "type": "Feature",
  "properties": {
    "iso:country":"US",
    "sg:address":"725 Cortaro Dr",
    "sg:city":"Ruskin",
    "sg:classifiers":[
        {
            "category":"Health Services",
            "subcategory":"Medical Lab",
            "type":"Services"
        }
    ],
    "sg:phone":"+1 813 642 0887",
    "sg:postcode":"33573",
    "sg:province":"FL",
    "wof:name":"Tampa Bay Open Mri Sun Cy Ctr",
    "wof:placetype":"venue"
},
  "geometry": {"coordinates":[-82.37109599999999,27.713088],"type":"Point"}
}