{
  "type": "Feature",
  "properties": {
    "iso:country":"US",
    "sg:address":"5365 NE 3rd Ter",
    "sg:city":"Fort Lauderdale",
    "sg:classifiers":[
        {
            "category":"Building & Trades",
            "subcategory":"Construction",
            "type":"Services"
        }
    ],
    "sg:phone":"+1 954 491 1509",
    "sg:postcode":"33334",
    "sg:province":"FL",
    "sg:tags":[
        "hanging",
        "contractor"
    ],
    "wof:name":"Mark Gratz Painting",
    "wof:placetype":"venue"
},
  "geometry": {"coordinates":[-80.14237300000001,26.195079],"type":"Point"}
}