{
  "type": "Feature",
  "properties": {
    "iso:country":"US",
    "sg:address":"25225 Rancho Ln",
    "sg:city":"Paisley",
    "sg:classifiers":[
        {
            "category":"Manufacturing",
            "subcategory":"Printing",
            "type":"Manufacturing & Wholesale Goods"
        }
    ],
    "sg:phone":"+1 386 738 5333",
    "sg:postcode":"32767",
    "sg:province":"FL",
    "sg:tags":[
        "newspaper"
    ],
    "wof:name":"Town Shopper",
    "wof:placetype":"venue"
},
  "geometry": {"coordinates":[-81.540282,28.998299],"type":"Point"}
}