{
  "type": "Feature",
  "properties": {
    "iso:country":"US",
    "sg:address":"4008 W South Ave",
    "sg:city":"Tampa",
    "sg:classifiers":[
        {
            "category":"Retail",
            "subcategory":"Auto Repair",
            "type":"Services"
        }
    ],
    "sg:phone":"+1 813 875 7223",
    "sg:postcode":"33614",
    "sg:province":"FL",
    "sg:tags":[
        "automobile",
        "customizing"
    ],
    "wof:name":"Xtreme Automotive",
    "wof:placetype":"venue"
},
  "geometry": {"coordinates":[-82.509789,27.991326],"type":"Point"}
}