{
  "type": "Feature",
  "properties": {
    "iso:country":"US",
    "sg:address":"1102 N Florida Ave",
    "sg:city":"Tampa",
    "sg:classifiers":[
        {
            "category":"Shopping",
            "subcategory":"Music",
            "type":"Retail Goods"
        }
    ],
    "sg:phone":"+1 813 274 8030",
    "sg:postcode":"33602",
    "sg:province":"FL",
    "sg:tags":[
        "executive"
    ],
    "wof:name":"Tampa Archives & Records",
    "wof:placetype":"venue"
},
  "geometry": {"coordinates":[-82.459503,27.954458],"type":"Point"}
}