{
  "type": "Feature",
  "properties": {
    "addr:full":"3021 W Colonial Dr Orlando FL 32808",
    "addr:housenumber":"3021",
    "addr:postcode":"32808",
    "addr:street":"W Colonial Dr",
    "iso:country":"US",
    "sg:address":"3021 W Colonial Dr",
    "sg:city":"Orlando",
    "sg:classifiers":[
        {
            "category":"Shopping",
            "subcategory":"Shoes",
            "type":"Retail Goods"
        }
    ],
    "sg:phone":"+1 407 898 5288",
    "sg:postcode":"32808",
    "sg:province":"FL",
    "sg:tags":[
        "shoe",
        "store"
    ],
    "wof:name":"Payless Shoesource",
    "wof:placetype":"venue"
},
  "geometry": {"coordinates":[-81.416555,28.552843],"type":"Point"}
}