{
  "type": "Feature",
  "properties": {
    "addr:full":"532 Mary Ave New Smyrna Beach FL 32168",
    "addr:housenumber":"532",
    "addr:postcode":"32168",
    "addr:street":"Mary Ave",
    "iso:country":"US",
    "sg:address":"532 Mary Ave",
    "sg:city":"New Smyrna Beach",
    "sg:classifiers":[
        {
            "category":"Social Services",
            "subcategory":"Child Care",
            "type":"Services"
        }
    ],
    "sg:phone":"+1 386 427 8131",
    "sg:postcode":"32168",
    "sg:province":"FL",
    "wof:name":"Head Start Chisholm Ctr",
    "wof:placetype":"venue"
},
  "geometry": {"coordinates":[-80.931371,29.026687],"type":"Point"}
}