{
  "type": "Feature",
  "properties": {
    "iso:country":"US",
    "sg:address":"4230 New Haven Ct",
    "sg:city":"Daytona Beach",
    "sg:classifiers":[
        {
            "category":"Freight",
            "type":"Transportation"
        }
    ],
    "sg:phone":"+1 386 322 1396",
    "sg:postcode":"32127",
    "sg:province":"FL",
    "wof:name":"Alpine Jet Charters",
    "wof:placetype":"venue"
},
  "geometry": {"coordinates":[-80.99824099999999,29.134707],"type":"Point"}
}