{
  "type": "Feature",
  "properties": {
    "addr:full":"2625 NE 6th Ave Fort Lauderdale FL 33334",
    "addr:housenumber":"2625",
    "addr:postcode":"33334",
    "addr:street":"Ne 6Th Ave",
    "iso:country":"US",
    "sg:address":"2625 NE 6th Ave",
    "sg:city":"Fort Lauderdale",
    "sg:classifiers":[
        {
            "category":"Professional",
            "subcategory":"Accounting & Tax Preparation",
            "type":"Services"
        }
    ],
    "sg:phone":"+1 954 565 9173",
    "sg:postcode":"33334",
    "sg:province":"FL",
    "sg:tags":[
        "return"
    ],
    "wof:name":"Hamilton Tax Service Inc",
    "wof:placetype":"venue"
},
  "geometry": {"coordinates":[-80.138272,26.1597],"type":"Point"}
}