{
  "type": "Feature",
  "properties": {
    "iso:country":"US",
    "sg:address":"4240 S Florida Ave",
    "sg:city":"Lakeland",
    "sg:classifiers":[
        {
            "category":"Home & Garden",
            "subcategory":"Furniture",
            "type":"Retail Goods"
        }
    ],
    "sg:phone":"+1 863 646 1463",
    "sg:postcode":"33813",
    "sg:province":"FL",
    "sg:website":"www.havertys.com",
    "wof:name":"Havertys Furniture",
    "wof:placetype":"venue"
},
  "geometry": {"coordinates":[-81.956841,27.986444],"type":"Point"}
}