{
  "type": "Feature",
  "properties": {
    "iso:country":"US",
    "sg:address":"5408 S University Dr",
    "sg:city":"Davie",
    "sg:classifiers":[
        {
            "category":"Personal",
            "type":"Services"
        },
        {
            "category":"Retail",
            "subcategory":"Storage",
            "type":"Services"
        }
    ],
    "sg:phone":"+1 877 258 8230",
    "sg:postcode":"33328",
    "sg:province":"FL",
    "sg:tags":[
        "self",
        "full",
        "commercial",
        "mover",
        "household"
    ],
    "sg:website":"http://www.publicstorage.com/?pid=ypcomCPCingenio",
    "wof:name":"Public Storage",
    "wof:placetype":"venue"
},
  "geometry": {"coordinates":[-80.251758,26.052186],"type":"Point"}
}