{
  "type": "Feature",
  "properties": {
    "iso:country":"US",
    "sg:address":"5430 W Sample Rd",
    "sg:city":"Margate",
    "sg:classifiers":[
        {
            "category":"Health Services",
            "subcategory":"Doctor",
            "type":"Services"
        },
        {
            "category":"Health Services",
            "subcategory":"Clinic",
            "type":"Services"
        }
    ],
    "sg:phone":"+1 954 968 4000",
    "sg:postcode":"33073",
    "sg:province":"FL",
    "sg:tags":[
        "physician",
        "surgeon",
        "osteopathic"
    ],
    "wof:name":"Neena Gupta Do Pa",
    "wof:placetype":"venue"
},
  "geometry": {"coordinates":[-80.196972,26.274041],"type":"Point"}
}