{
  "type": "Feature",
  "properties": {
    "iso:country":"US",
    "sg:address":"29900 SW 146th Ave",
    "sg:city":"Homestead",
    "sg:classifiers":[
        {
            "category":"Retail",
            "subcategory":"Car Wash",
            "type":"Services"
        }
    ],
    "sg:phone":"+1 305 282 2068",
    "sg:postcode":"33033",
    "sg:province":"FL",
    "sg:tags":[
        "polishing",
        "washing"
    ],
    "wof:name":"Alcides Mendoza Car Wash",
    "wof:placetype":"venue"
},
  "geometry": {"coordinates":[-80.427819,25.489719],"type":"Point"}
}