{
  "type": "Feature",
  "properties": {
    "iso:country":"US",
    "sg:address":"445 Douglas Ave",
    "sg:city":"Altamonte Spgs",
    "sg:classifiers":[
        {
            "category":"Professional",
            "subcategory":"Lawyer & Legal Services",
            "type":"Services"
        }
    ],
    "sg:phone":"+1 407 261 9110",
    "sg:postcode":"32714",
    "sg:province":"FL",
    "sg:tags":[
        "attorney"
    ],
    "wof:name":"William Herrman",
    "wof:placetype":"venue"
},
  "geometry": {"coordinates":[-81.390292,28.667837],"type":"Point"}
}