{
  "type": "Feature",
  "properties": {
    "addr:full":"4 Setting Sun Trl Ormond Beach FL 32174",
    "addr:housenumber":"4",
    "addr:postcode":"32174",
    "addr:street":"Setting Sun Trl",
    "iso:country":"US",
    "sg:address":"4 Setting Sun Trl",
    "sg:city":"Ormond Beach",
    "sg:classifiers":[
        {
            "category":"Professional",
            "subcategory":"Computer Services",
            "type":"Services"
        }
    ],
    "sg:phone":"+1 386 672 5060",
    "sg:postcode":"32174",
    "sg:province":"FL",
    "sg:tags":[
        "information",
        "retrieval"
    ],
    "wof:name":"Mac Data Advantage",
    "wof:placetype":"venue"
},
  "geometry": {"coordinates":[-81.09462000000001,29.277784],"type":"Point"}
}