{
  "type": "Feature",
  "properties": {
    "addr:full":"3181 SW 14th Ct Pompano Beach FL 33069",
    "addr:housenumber":"3181",
    "addr:postcode":"33069",
    "addr:street":"Sw 14Th Ct",
    "iso:country":"US",
    "sg:address":"3181 SW 14th Ct",
    "sg:city":"Pompano Beach",
    "sg:classifiers":[
        {
            "category":"Building & Trades",
            "subcategory":"Construction",
            "type":"Services"
        }
    ],
    "sg:phone":"+1 954 935 9541",
    "sg:postcode":"33069",
    "sg:province":"FL",
    "sg:tags":[
        "carpentry",
        "contractor"
    ],
    "wof:name":"Sculptured Woodworks",
    "wof:placetype":"venue"
},
  "geometry": {"coordinates":[-80.166833,26.211295],"type":"Point"}
}