{
  "type": "Feature",
  "properties": {
    "iso:country":"US",
    "sg:address":"750 S Orange Blossom Trl",
    "sg:city":"Orlando",
    "sg:classifiers":[
        {
            "category":"Arts & Performance",
            "subcategory":"Theater",
            "type":"Entertainment"
        }
    ],
    "sg:phone":"+1 407 839 8816",
    "sg:postcode":"32805",
    "sg:province":"FL",
    "sg:tags":[
        "live",
        "music"
    ],
    "wof:name":"Mega Dj's Entertainment",
    "wof:placetype":"venue"
},
  "geometry": {"coordinates":[-81.397237,28.533842],"type":"Point"}
}