{
  "type": "Feature",
  "properties": {
    "iso:country":"US",
    "sg:address":"3073 NE 183rd Ln",
    "sg:city":"Aventura",
    "sg:classifiers":[
        {
            "category":"Retail",
            "subcategory":"Repair Shop",
            "type":"Services"
        }
    ],
    "sg:phone":"+1 305 692 7771",
    "sg:postcode":"33160",
    "sg:province":"FL",
    "sg:tags":[
        "upholsterer"
    ],
    "wof:name":"Richards Design Ctr",
    "wof:placetype":"venue"
},
  "geometry": {"coordinates":[-80.142132,25.944727],"type":"Point"}
}