{
  "type": "Feature",
  "properties": {
    "addr:full":"8903 Glades Rd  Boca Raton FL 33434",
    "addr:housenumber":"8903",
    "addr:postcode":"33434",
    "addr:street":"Glades Rd",
    "iso:country":"US",
    "sg:address":"8903 Glades Rd ",
    "sg:city":"Boca Raton",
    "sg:classifiers":[
        {
            "category":"Cafe",
            "type":"Food & Drink"
        }
    ],
    "sg:menulink":"http://www.allmenus.com/fl/sunshine-parkway/292771-china-cafe/menu/",
    "sg:phone":"561482533",
    "sg:postcode":"33434",
    "sg:province":"FL",
    "sg:tags":[
        "chinese"
    ],
    "wof:name":"China Cafe",
    "wof:placetype":"venue"
},
  "geometry": {"coordinates":[-80.185357,26.368139],"type":"Point"}
}