{
  "type": "Feature",
  "properties": {
    "addr:full":"482 Fentress Blvd Daytona Beach FL 32114",
    "addr:housenumber":"482",
    "addr:postcode":"32114",
    "addr:street":"Fentress Blvd",
    "iso:country":"US",
    "sg:address":"482 Fentress Blvd",
    "sg:city":"Daytona Beach",
    "sg:classifiers":[
        {
            "category":"Professional",
            "subcategory":"Engineering",
            "type":"Services"
        }
    ],
    "sg:phone":"+1 386 238 0072",
    "sg:postcode":"32114",
    "sg:province":"FL",
    "sg:tags":[
        "engineer"
    ],
    "sg:website":"www.mduea.com",
    "wof:name":"Infinisys",
    "wof:placetype":"venue"
},
  "geometry": {"coordinates":[-81.079063,29.192046],"type":"Point"}
}