{
  "type": "Feature",
  "properties": {
    "iso:country":"US",
    "sg:address":"13823 Sutton Park Dr N",
    "sg:city":"Jacksonville",
    "sg:classifiers":[
        {
            "category":"Retail",
            "subcategory":"Event Space",
            "type":"Services"
        },
        {
            "category":"Sports & Exercise",
            "subcategory":"Golf",
            "type":"Entertainment"
        }
    ],
    "sg:phone":"+1 904 223 4653",
    "sg:postcode":"32224",
    "sg:province":"FL",
    "sg:tags":[
        "facility",
        "banquet",
        "course",
        "courses-private",
        "reception",
        "hall"
    ],
    "sg:website":"http://www.windsorparke.com",
    "wof:name":"Windsor Park Golf Club",
    "wof:placetype":"venue"
},
  "geometry": {"coordinates":[-81.45996599999999,30.263093],"type":"Point"}
}