{
  "type": "Feature",
  "properties": {
    "addr:full":"4631 Baybrook Dr Pensacola FL 32514",
    "addr:housenumber":"4631",
    "addr:postcode":"32514",
    "addr:street":"Baybrook Dr",
    "iso:country":"US",
    "sg:address":"4631 Baybrook Dr",
    "sg:city":"Pensacola",
    "sg:classifiers":[
        {
            "category":"Farming",
            "subcategory":"Farm & Veterinary Services",
            "type":"Manufacturing & Wholesale Goods"
        }
    ],
    "sg:phone":"+1 850 857 7708",
    "sg:postcode":"32514",
    "sg:province":"FL",
    "sg:tags":[
        "preparation",
        "soil"
    ],
    "wof:name":"A+ Environmental Inc",
    "wof:placetype":"venue"
},
  "geometry": {"coordinates":[-87.166105,30.511262],"type":"Point"}
}