{
  "type": "Feature",
  "properties": {
    "iso:country":"US",
    "sg:address":"1109 Alexander Bend",
    "sg:city":"Fort Lauderdale",
    "sg:classifiers":[
        {
            "category":"Professional",
            "subcategory":"Accounting & Tax Preparation",
            "type":"Services"
        }
    ],
    "sg:phone":"+1 954 384 2034",
    "sg:postcode":"33327",
    "sg:province":"FL",
    "wof:name":"Midas Medical Billing Inc",
    "wof:placetype":"venue"
},
  "geometry": {"coordinates":[-80.411778,26.122135],"type":"Point"}
}