{
  "type": "Feature",
  "properties": {
    "iso:country":"US",
    "sg:address":"404 Pelham Rd",
    "sg:city":"Fort Walton Beach",
    "sg:classifiers":[
        {
            "category":"Manufacturing",
            "subcategory":"Textiles",
            "type":"Manufacturing & Wholesale Goods"
        }
    ],
    "sg:phone":"+1 850 621 3361",
    "sg:postcode":"32547",
    "sg:province":"FL",
    "sg:tags":[
        "mfg"
    ],
    "wof:name":"Young Alcon Inc",
    "wof:placetype":"venue"
},
  "geometry": {"coordinates":[-86.630999,30.434671],"type":"Point"}
}