{
  "type": "Feature",
  "properties": {
    "addr:full":"1673 Mason Ave Daytona Beach FL 32117",
    "addr:housenumber":"1673",
    "addr:postcode":"32117",
    "addr:street":"Mason Ave",
    "iso:country":"US",
    "sg:address":"1673 Mason Ave",
    "sg:city":"Daytona Beach",
    "sg:classifiers":[
        {
            "category":"Wholesale",
            "subcategory":"Medical Equipment & Supplies",
            "type":"Manufacturing & Wholesale Goods"
        }
    ],
    "sg:phone":"+1 386 274 4328",
    "sg:postcode":"32117",
    "sg:province":"FL",
    "sg:tags":[
        "physician",
        "surgeon"
    ],
    "wof:name":"Medical Manager Health Systems",
    "wof:placetype":"venue"
},
  "geometry": {"coordinates":[-81.065764,29.211924],"type":"Point"}
}