{
  "type": "Feature",
  "properties": {
    "iso:country":"US",
    "sg:address":"1117 NE 163rd St",
    "sg:city":"North Miami Beach",
    "sg:classifiers":[
        {
            "category":"Personal",
            "subcategory":"Beauty Salon",
            "type":"Services"
        }
    ],
    "sg:phone":"+1 305 940 1740",
    "sg:postcode":"33162",
    "sg:province":"FL",
    "sg:tags":[
        "hair",
        "shop"
    ],
    "wof:name":"Hair Magic",
    "wof:placetype":"venue"
},
  "geometry": {"coordinates":[-80.177696,25.9256],"type":"Point"}
}