{
  "type": "Feature",
  "properties": {
    "iso:country":"US",
    "sg:address":"7 Quito",
    "sg:city":"Fort Pierce",
    "sg:classifiers":[
        {
            "category":"Real Estate",
            "subcategory":"Real Estate Agent",
            "type":"Services"
        }
    ],
    "sg:phone":"+1 772 321 3554",
    "sg:postcode":"34951",
    "sg:province":"FL",
    "sg:tags":[
        "agency",
        "rental"
    ],
    "wof:name":"Hangar Sales & Rental",
    "wof:placetype":"venue"
},
  "geometry": {"coordinates":[-80.388792,27.545944],"type":"Point"}
}