{
  "type": "Feature",
  "properties": {
    "addr:full":"6680 Commonwealth Ave Jacksonville FL 32254",
    "addr:housenumber":"6680",
    "addr:postcode":"32254",
    "addr:street":"Commonwealth Ave",
    "iso:country":"US",
    "sg:address":"6680 Commonwealth Ave",
    "sg:city":"Jacksonville",
    "sg:classifiers":[
        {
            "category":"Restaurant",
            "type":"Food & Drink"
        }
    ],
    "sg:menulink":"http://www.allmenus.com/fl/jacksonville/154327-hardees/menu/",
    "sg:phone":"+1 904 783 0960",
    "sg:postcode":"32254",
    "sg:province":"FL",
    "sg:tags":[
        "burger",
        "american"
    ],
    "wof:name":"Hardee's",
    "wof:placetype":"venue"
},
  "geometry": {"coordinates":[-81.758712,30.335226],"type":"Point"}
}