{
  "type": "Feature",
  "properties": {
    "iso:country":"US",
    "sg:address":"16312 SW 45th Ter",
    "sg:city":"Miami",
    "sg:classifiers":[
        {
            "category":"Personal",
            "type":"Services"
        }
    ],
    "sg:phone":"+1 305 552 5212",
    "sg:postcode":"33185",
    "sg:province":"FL",
    "sg:tags":[
        "car",
        "loading",
        "unloading"
    ],
    "wof:name":"Chatelain Cargo Services, Inc.",
    "wof:placetype":"venue"
},
  "geometry": {"coordinates":[-80.457763,25.721843],"type":"Point"}
}