{
  "type": "Feature",
  "properties": {
    "addr:full":"730 Gardenia Dr West Palm Beach FL 33411",
    "addr:housenumber":"730",
    "addr:postcode":"33411",
    "addr:street":"Gardenia Dr",
    "iso:country":"US",
    "sg:address":"730 Gardenia Dr",
    "sg:city":"West Palm Beach",
    "sg:classifiers":[
        {
            "category":"Shopping",
            "subcategory":"Gifts & Souvenirs",
            "type":"Retail Goods"
        }
    ],
    "sg:phone":"+1 561 753 3105",
    "sg:postcode":"33411",
    "sg:province":"FL",
    "wof:name":"M&M Creations & Gifts Inc",
    "wof:placetype":"venue"
},
  "geometry": {"coordinates":[-80.22753899999999,26.685523],"type":"Point"}
}