{
  "type": "Feature",
  "properties": {
    "addr:full":"1211 de Narvaez Ave Bradenton FL 34209",
    "addr:housenumber":"1211",
    "addr:postcode":"34209",
    "addr:street":"De Narvaez Ave",
    "iso:country":"US",
    "sg:address":"1211 de Narvaez Ave",
    "sg:city":"Bradenton",
    "sg:classifiers":[
        {
            "category":"Banks & Credit Unions",
            "subcategory":"Financial Services",
            "type":"Services"
        }
    ],
    "sg:phone":"+1 941 794 5425",
    "sg:postcode":"34209",
    "sg:province":"FL",
    "sg:tags":[
        "investor"
    ],
    "wof:name":"Sorail Inc",
    "wof:placetype":"venue"
},
  "geometry": {"coordinates":[-82.639258,27.487633],"type":"Point"}
}