{
  "type": "Feature",
  "properties": {
    "addr:full":"4413 19th Street Cir W Bradenton FL 34207",
    "addr:housenumber":"4413",
    "addr:postcode":"34207",
    "addr:street":"19Th Street Cir W",
    "iso:country":"US",
    "sg:address":"4413 19th Street Cir W",
    "sg:city":"Bradenton",
    "sg:classifiers":[
        {
            "category":"Building & Trades",
            "subcategory":"Construction",
            "type":"Services"
        }
    ],
    "sg:phone":"+1 941 727 7204",
    "sg:postcode":"34207",
    "sg:province":"FL",
    "sg:tags":[
        "painter"
    ],
    "wof:name":"Raul Palma Painters",
    "wof:placetype":"venue"
},
  "geometry": {"coordinates":[-82.579735,27.459258],"type":"Point"}
}