{
  "type": "Feature",
  "properties": {
    "iso:country":"US",
    "sg:address":"4511 E Osborne Ave",
    "sg:city":"Tampa",
    "sg:classifiers":[
        {
            "category":"Manufacturing",
            "subcategory":"Retail Goods",
            "type":"Manufacturing & Wholesale Goods"
        }
    ],
    "sg:phone":"+1 813 876 3047",
    "sg:postcode":"33610",
    "sg:province":"FL",
    "sg:tags":[
        "mfg",
        "spa",
        "lumber",
        "cabinet"
    ],
    "wof:name":"Jet Stream Spas",
    "wof:placetype":"venue"
},
  "geometry": {"coordinates":[-82.406244,27.988725],"type":"Point"}
}