{
  "type": "Feature",
  "properties": {
    "addr:full":"3695 S Orlando Dr Sanford FL 32773",
    "addr:housenumber":"3695",
    "addr:postcode":"32773",
    "addr:street":"S Orlando Dr",
    "iso:country":"US",
    "sg:address":"3695 S Orlando Dr",
    "sg:city":"Sanford",
    "sg:classifiers":[
        {
            "category":"Restaurant",
            "type":"Food & Drink"
        }
    ],
    "sg:menulink":"http://www.allmenus.com/fl/sanford/63571-ci-cis-pizza/menu/",
    "sg:phone":"+1 407 330 7676",
    "sg:postcode":"32773",
    "sg:province":"FL",
    "sg:tags":[
        "american",
        "pizza"
    ],
    "wof:name":"Ci Ci's Pizza",
    "wof:placetype":"venue"
},
  "geometry": {"coordinates":[-81.285211,28.760721],"type":"Point"}
}