{
  "type": "Feature",
  "properties": {
    "iso:country":"US",
    "sg:address":"13355 Wrevham Ct",
    "sg:city":"West Palm Beach",
    "sg:classifiers":[
        {
            "category":"Building & Trades",
            "subcategory":"Construction",
            "type":"Services"
        }
    ],
    "sg:phone":"+1 561 793 8044",
    "sg:postcode":"33414",
    "sg:province":"FL",
    "sg:tags":[
        "house"
    ],
    "wof:name":"Oak Ridge Properties Inc",
    "wof:placetype":"venue"
},
  "geometry": {"coordinates":[-80.257667,26.650238],"type":"Point"}
}