{
  "type": "Feature",
  "properties": {
    "iso:country":"US",
    "sg:address":"2425 N Atlantic Ave",
    "sg:city":"Daytona Beach",
    "sg:classifiers":[
        {
            "category":"Shopping",
            "type":"Retail Goods"
        }
    ],
    "sg:phone":"+1 386 672 0501",
    "sg:postcode":"32118",
    "sg:province":"FL",
    "sg:tags":[
        "art",
        "gallery",
        "dealer"
    ],
    "wof:name":"Hawaiian Asian Art Gallery",
    "wof:placetype":"venue"
},
  "geometry": {"coordinates":[-81.024066,29.259987],"type":"Point"}
}