{
  "type": "Feature",
  "properties": {
    "iso:country":"US",
    "sg:address":"11180 Heron Bay Blvd",
    "sg:city":"Pompano Beach",
    "sg:classifiers":[
        {
            "category":"Shopping",
            "subcategory":"Gifts & Souvenirs",
            "type":"Retail Goods"
        }
    ],
    "sg:phone":"+1 954 344 4424",
    "sg:postcode":"33076",
    "sg:province":"FL",
    "wof:name":"Magnifying Connection Intl",
    "wof:placetype":"venue"
},
  "geometry": {"coordinates":[-80.278879,26.308723],"type":"Point"}
}