{
  "type": "Feature",
  "properties": {
    "iso:country":"US",
    "sg:address":"1938 Adams Ln",
    "sg:city":"Sarasota",
    "sg:classifiers":[
        {
            "category":"Professional",
            "subcategory":"Art Services",
            "type":"Services"
        }
    ],
    "sg:phone":"+1 941 955 9801",
    "sg:postcode":"34236",
    "sg:province":"FL",
    "sg:tags":[
        "graphic",
        "designer"
    ],
    "wof:name":"Origin Design",
    "wof:placetype":"venue"
},
  "geometry": {"coordinates":[-82.531543,27.334377],"type":"Point"}
}