{
  "type": "Feature",
  "properties": {
    "addr:full":"1501 NW 17th Ave Miami FL 33125",
    "addr:housenumber":"1501",
    "addr:postcode":"33125",
    "addr:street":"Nw 17Th Ave",
    "iso:country":"US",
    "sg:address":"1501 NW 17th Ave",
    "sg:city":"Miami",
    "sg:classifiers":[
        {
            "category":"Professional",
            "type":"Services"
        }
    ],
    "sg:phone":"+1 305 545 5333",
    "sg:postcode":"33125",
    "sg:province":"FL",
    "sg:tags":[
        "establishment"
    ],
    "wof:name":"C H Video",
    "wof:placetype":"venue"
},
  "geometry": {"coordinates":[-80.22313,25.78964],"type":"Point"}
}