{
  "type": "Feature",
  "properties": {
    "iso:country":"US",
    "sg:address":"2848 Birkdale Dr",
    "sg:city":"Weston",
    "sg:classifiers":[
        {
            "category":"Real Estate",
            "subcategory":"Real Estate Agent",
            "type":"Services"
        }
    ],
    "sg:phone":"+1 954 384 5332",
    "sg:postcode":"33332",
    "sg:province":"FL",
    "wof:name":"Sunshine Properties & Invstmnt",
    "wof:placetype":"venue"
},
  "geometry": {"coordinates":[-80.393597,26.084153],"type":"Point"}
}