{
  "type": "Feature",
  "properties": {
    "addr:full":"3544 SW Archer Rd Gainesville FL 32608",
    "addr:housenumber":"3544",
    "addr:postcode":"32608",
    "addr:street":"Sw Archer Rd",
    "iso:country":"US",
    "sg:address":"3544 SW Archer Rd",
    "sg:city":"Gainesville",
    "sg:classifiers":[
        {
            "category":"Shopping",
            "subcategory":"Computers & Home Electronics",
            "type":"Retail Goods"
        }
    ],
    "sg:phone":"+1 352 373 9440",
    "sg:postcode":"32608",
    "sg:province":"FL",
    "sg:tags":[
        "game",
        "video"
    ],
    "wof:name":"Rhino Video Games",
    "wof:placetype":"venue"
},
  "geometry": {"coordinates":[-82.37463,29.625307],"type":"Point"}
}