{
  "type": "Feature",
  "properties": {
    "addr:full":"3963 Orchard Hill Cir Palm Harbor FL 34684",
    "addr:housenumber":"3963",
    "addr:postcode":"34684",
    "addr:street":"Orchard Hill Cir",
    "iso:country":"US",
    "sg:address":"3963 Orchard Hill Cir",
    "sg:city":"Palm Harbor",
    "sg:classifiers":[
        {
            "category":"Food & Beverages",
            "subcategory":"Specialty",
            "type":"Retail Goods"
        }
    ],
    "sg:phone":"+1 727 785 1231",
    "sg:postcode":"34684",
    "sg:province":"FL",
    "wof:name":"Hendricks Nutrition",
    "wof:placetype":"venue"
},
  "geometry": {"coordinates":[-82.725469,28.065387],"type":"Point"}
}