{
  "type": "Feature",
  "properties": {
    "iso:country":"US",
    "sg:address":"405 SW 4 Ave",
    "sg:city":"Gainesville",
    "sg:classifiers":[
        {
            "category":"Communications",
            "subcategory":"Film & Video Production",
            "type":"Services"
        }
    ],
    "sg:phone":"+1 352 367 2646",
    "sg:postcode":"32601",
    "sg:province":"FL",
    "sg:tags":[
        "audio"
    ],
    "wof:name":"Six-O-One Records & Studio",
    "wof:placetype":"venue"
},
  "geometry": {"coordinates":[-82.32804,29.648254],"type":"Point"}
}