{
  "type": "Feature",
  "properties": {
    "addr:full":"805 Oak Rd Ocala FL 34472",
    "addr:housenumber":"805",
    "addr:postcode":"34472",
    "addr:street":"Oak Rd",
    "iso:country":"US",
    "sg:address":"805 Oak Rd",
    "sg:city":"Ocala",
    "sg:classifiers":[
        {
            "category":"Place Of Worship",
            "subcategory":"Church",
            "type":"Public Place"
        },
        {
            "category":"Place Of Worship",
            "type":"Public Place"
        }
    ],
    "sg:phone":"+1 352 687 8530",
    "sg:postcode":"34472",
    "sg:province":"FL",
    "sg:tags":[
        "churches-interdenominational",
        "denomination",
        "churches-christian",
        "churches-various",
        "churches-christian-reformed"
    ],
    "wof:name":"Silver Springs Shores Christian Church",
    "wof:placetype":"venue"
},
  "geometry": {"coordinates":[-81.98194100000001,29.089809],"type":"Point"}
}