{
  "type": "Feature",
  "properties": {
    "addr:full":"630 NE Helicon Ln Port St Lucie FL 34983",
    "addr:housenumber":"630",
    "addr:postcode":"34983",
    "addr:street":"Ne Helicon Ln",
    "iso:country":"US",
    "sg:address":"630 NE Helicon Ln",
    "sg:city":"Port St Lucie",
    "sg:classifiers":[
        {
            "category":"Retail",
            "subcategory":"Laundry & Dry Cleaning",
            "type":"Services"
        }
    ],
    "sg:phone":"+1 772 785 9141",
    "sg:postcode":"34983",
    "sg:province":"FL",
    "sg:tags":[
        "cleaners",
        "rug",
        "carpet"
    ],
    "wof:name":"Ocean Breeze",
    "wof:placetype":"venue"
},
  "geometry": {"coordinates":[-80.34745100000001,27.332123],"type":"Point"}
}