{
  "type": "Feature",
  "properties": {
    "addr:full":"2267 1st St Ste 13 Fort Myers FL 33901",
    "addr:housenumber":"2267",
    "addr:postcode":"myers fl 33901",
    "addr:street":"1St St Ste 13",
    "iso:country":"US",
    "sg:address":"2267 1st St Ste 13",
    "sg:city":"Fort Myers",
    "sg:classifiers":[
        {
            "category":"Professional",
            "subcategory":"Lawyer & Legal Services",
            "type":"Services"
        }
    ],
    "sg:phone":"+1 239 226 0121",
    "sg:postcode":"33901",
    "sg:province":"FL",
    "wof:name":"Morgan Law Firm PA",
    "wof:placetype":"venue"
},
  "geometry": {"coordinates":[-81.86944800000001,26.644577],"type":"Point"}
}