{
  "type": "Feature",
  "properties": {
    "addr:full":"1101 8th Ave W Palmetto FL 34221",
    "addr:housenumber":"1101",
    "addr:postcode":"34221",
    "addr:street":"8Th Ave W",
    "iso:country":"US",
    "sg:address":"1101 8th Ave W",
    "sg:city":"Palmetto",
    "sg:classifiers":[
        {
            "category":"Food & Beverages",
            "subcategory":"Groceries & Convenience Stores",
            "type":"Retail Goods"
        }
    ],
    "sg:phone":"+1 941 721 4406",
    "sg:postcode":"34221",
    "sg:province":"FL",
    "sg:tags":[
        "grocer"
    ],
    "wof:name":"Albertsons",
    "wof:placetype":"venue"
},
  "geometry": {"coordinates":[-82.57293199999999,27.522603],"type":"Point"}
}