{
  "type": "Feature",
  "properties": {
    "addr:full":"3956 Tamiami Trl N Naples FL 34103",
    "addr:housenumber":"3956",
    "addr:postcode":"34103",
    "addr:street":"Tamiami Trl N",
    "iso:country":"US",
    "sg:address":"3956 Tamiami Trl N",
    "sg:city":"Naples",
    "sg:classifiers":[
        {
            "category":"Retail",
            "subcategory":"Repair Shop",
            "type":"Services"
        }
    ],
    "sg:phone":"+1 239 455 8800",
    "sg:postcode":"34103",
    "sg:province":"FL",
    "wof:name":"Bb Locksmith",
    "wof:placetype":"venue"
},
  "geometry": {"coordinates":[-81.800009,26.194156],"type":"Point"}
}