{
  "type": "Feature",
  "properties": {
    "iso:country":"US",
    "sg:address":"1810 S Dixie Hwy",
    "sg:city":"Lake Worth",
    "sg:classifiers":[
        {
            "category":"Personal",
            "subcategory":"Beauty Salon",
            "type":"Services"
        }
    ],
    "sg:phone":"+1 561 493 4533",
    "sg:postcode":"33460",
    "sg:province":"FL",
    "wof:name":"Off The Chain Hair & Nail",
    "wof:placetype":"venue"
},
  "geometry": {"coordinates":[-80.053217,26.59407],"type":"Point"}
}