{
  "type": "Feature",
  "properties": {
    "iso:country":"US",
    "sg:address":"710 Pondella Rd",
    "sg:city":"Fort Myers",
    "sg:classifiers":[
        {
            "category":"Personal",
            "subcategory":"Beauty Salon",
            "type":"Services"
        }
    ],
    "sg:phone":"+1 239 997 5700",
    "sg:postcode":"33903",
    "sg:province":"FL",
    "wof:name":"Merengue Beauty Salon Inc",
    "wof:placetype":"venue"
},
  "geometry": {"coordinates":[-81.90672499999999,26.667341],"type":"Point"}
}