{
  "type": "Feature",
  "properties": {
    "addr:full":"11059 65th Ter N Seminole FL 33772",
    "addr:housenumber":"11059",
    "addr:postcode":"33772",
    "addr:street":"65Th Ter N",
    "iso:country":"US",
    "sg:address":"11059 65th Ter N",
    "sg:city":"Seminole",
    "sg:classifiers":[
        {
            "category":"Professional",
            "subcategory":"Computer Services",
            "type":"Services"
        }
    ],
    "sg:phone":"+1 727 394 1558",
    "sg:postcode":"33772",
    "sg:province":"FL",
    "sg:tags":[
        "programing",
        "custom"
    ],
    "wof:name":"Riva & Co",
    "wof:placetype":"venue"
},
  "geometry": {"coordinates":[-82.793543,27.832096],"type":"Point"}
}