{
  "type": "Feature",
  "properties": {
    "iso:country":"US",
    "sg:address":"6391 W Colonial Dr",
    "sg:city":"Orlando",
    "sg:classifiers":[
        {
            "category":"Shopping",
            "subcategory":"Clothing, Apparel, & Fashions",
            "type":"Retail Goods"
        },
        {
            "category":"Shopping",
            "subcategory":"Party Supplies",
            "type":"Retail Goods"
        }
    ],
    "sg:phone":"+1 407 298 0900",
    "sg:postcode":"32818",
    "sg:province":"FL",
    "sg:tags":[
        "decoration",
        "favors",
        "delivery",
        "balloons-retail",
        "costume"
    ],
    "sg:website":"http://www.partycity.com",
    "wof:name":"Party City",
    "wof:placetype":"venue"
},
  "geometry": {"coordinates":[-81.470489,28.552121],"type":"Point"}
}