{
  "type": "Feature",
  "properties": {
    "iso:country":"US",
    "sg:address":"12921 Oliveira St",
    "sg:city":"Dover",
    "sg:classifiers":[
        {
            "category":"Professional",
            "subcategory":"Accounting & Tax Preparation",
            "type":"Services"
        }
    ],
    "sg:phone":"+1 813 689 0852",
    "sg:postcode":"33527",
    "sg:province":"FL",
    "sg:tags":[
        "return",
        "filing"
    ],
    "wof:name":"Don Suffern Tax Svc",
    "wof:placetype":"venue"
},
  "geometry": {"coordinates":[-82.244731,27.990109],"type":"Point"}
}