{
  "type": "Feature",
  "properties": {
    "addr:full":"2341 Celery Ave Sanford FL 32771",
    "addr:housenumber":"2341",
    "addr:postcode":"32771",
    "addr:street":"Celery Ave",
    "iso:country":"US",
    "sg:address":"2341 Celery Ave",
    "sg:city":"Sanford",
    "sg:classifiers":[
        {
            "category":"Manufacturing",
            "subcategory":"Motor Vehicles & Parts",
            "type":"Manufacturing & Wholesale Goods"
        }
    ],
    "sg:phone":"+1 407 323 3547",
    "sg:postcode":"32771",
    "sg:province":"FL",
    "sg:tags":[
        "equipment",
        "transportation",
        "mfg"
    ],
    "wof:name":"Blue & Gray Trailer Mfg",
    "wof:placetype":"venue"
},
  "geometry": {"coordinates":[-81.241376,28.801261],"type":"Point"}
}