{
  "type": "Feature",
  "properties": {
    "addr:full":"107 Mott St Jacksonville FL 32254",
    "addr:housenumber":"107",
    "addr:postcode":"32254",
    "addr:street":"Mott St",
    "iso:country":"US",
    "sg:address":"107 Mott St",
    "sg:city":"Jacksonville",
    "sg:classifiers":[
        {
            "category":"Manufacturing",
            "subcategory":"Signs",
            "type":"Manufacturing & Wholesale Goods"
        }
    ],
    "sg:phone":"+1 904 388 1234",
    "sg:postcode":"32254",
    "sg:province":"FL",
    "wof:name":"Atlantic Signs",
    "wof:placetype":"venue"
},
  "geometry": {"coordinates":[-81.704649,30.328048],"type":"Point"}
}