{
  "type": "Feature",
  "properties": {
    "iso:country":"US",
    "sg:address":"3805 W Homosassa Trl",
    "sg:city":"Lecanto",
    "sg:classifiers":[
        {
            "category":"Building & Trades",
            "subcategory":"Construction",
            "type":"Services"
        }
    ],
    "sg:phone":"+1 352 746 4909",
    "sg:postcode":"34461",
    "sg:province":"FL",
    "sg:tags":[
        "roofing",
        "industrial",
        "contractors-commercial",
        "contractor"
    ],
    "wof:name":"Cj Roofing",
    "wof:placetype":"venue"
},
  "geometry": {"coordinates":[-82.497016,28.85117],"type":"Point"}
}