{
  "type": "Feature",
  "properties": {
    "iso:country":"US",
    "sg:address":"2801 SW 87th Ave",
    "sg:city":"Davie",
    "sg:classifiers":[
        {
            "category":"Health Services",
            "subcategory":"Doctor",
            "type":"Services"
        }
    ],
    "sg:phone":"+1 772 781 2473",
    "sg:postcode":"33328",
    "sg:province":"FL",
    "sg:tags":[
        "physician",
        "surgeon"
    ],
    "wof:name":"Urgent Care Networks Solutions",
    "wof:placetype":"venue"
},
  "geometry": {"coordinates":[-80.26308899999999,26.083534],"type":"Point"}
}