{
  "type": "Feature",
  "properties": {
    "iso:country":"US",
    "sg:address":"217 S J St",
    "sg:city":"Lake Worth",
    "sg:classifiers":[
        {
            "category":"Building & Trades",
            "subcategory":"Construction",
            "type":"Services"
        }
    ],
    "sg:phone":"+1 561 585 0580",
    "sg:postcode":"33460",
    "sg:province":"FL",
    "sg:tags":[
        "carpentry",
        "contractor"
    ],
    "wof:name":"Jj Trim Inc",
    "wof:placetype":"venue"
},
  "geometry": {"coordinates":[-80.056535,26.612423],"type":"Point"}
}