{
  "type": "Feature",
  "properties": {
    "addr:full":"326 Seabreeze Blvd Daytona Beach FL 32118",
    "addr:housenumber":"326",
    "addr:postcode":"32118",
    "addr:street":"Seabreeze Blvd",
    "iso:country":"US",
    "sg:address":"326 Seabreeze Blvd",
    "sg:city":"Daytona Beach",
    "sg:classifiers":[
        {
            "category":"Restaurant",
            "type":"Food & Drink"
        }
    ],
    "sg:phone":"+1 386 248 0686",
    "sg:postcode":"32118",
    "sg:province":"FL",
    "wof:name":"Larry's Giant Subs",
    "wof:placetype":"venue"
},
  "geometry": {"coordinates":[-81.01727200000001,29.233738],"type":"Point"}
}