{
  "type": "Feature",
  "properties": {
    "addr:full":"166 NW 6th Ave Webster FL 33597",
    "addr:housenumber":"166",
    "addr:postcode":"33597",
    "addr:street":"Nw 6Th Ave",
    "iso:country":"US",
    "sg:address":"166 NW 6th Ave",
    "sg:city":"Webster",
    "sg:classifiers":[
        {
            "category":"Home & Garden",
            "subcategory":"Furniture",
            "type":"Retail Goods"
        }
    ],
    "sg:phone":"+1 352 568 0200",
    "sg:postcode":"33597",
    "sg:province":"FL",
    "wof:name":"4 Seasons Oriental Arts",
    "wof:placetype":"venue"
},
  "geometry": {"coordinates":[-82.054863,28.617425],"type":"Point"}
}