{
  "type": "Feature",
  "properties": {
    "addr:full":"6576 Caroline St Milton FL 32570",
    "addr:housenumber":"6576",
    "addr:postcode":"32570",
    "addr:street":"Caroline St",
    "iso:country":"US",
    "sg:address":"6576 Caroline St",
    "sg:city":"Milton",
    "sg:classifiers":[
        {
            "category":"Social Services",
            "type":"Services"
        }
    ],
    "sg:phone":"+1 850 983 8886",
    "sg:postcode":"32570",
    "sg:province":"FL",
    "sg:tags":[
        "organization",
        "welfare"
    ],
    "wof:name":"Families Count",
    "wof:placetype":"venue"
},
  "geometry": {"coordinates":[-87.053151,30.614591],"type":"Point"}
}