{
  "type": "Feature",
  "properties": {
    "iso:country":"US",
    "sg:address":"6281 39th St N",
    "sg:city":"Pinellas Park",
    "sg:classifiers":[
        {
            "category":"Manufacturing",
            "subcategory":"Tools & Machinery",
            "type":"Manufacturing & Wholesale Goods"
        }
    ],
    "sg:phone":"+1 727 526 7833",
    "sg:postcode":"33781",
    "sg:province":"FL",
    "sg:tags":[
        "machine",
        "shop",
        "precision"
    ],
    "wof:name":"D E Farmer Machine Inc",
    "wof:placetype":"venue"
},
  "geometry": {"coordinates":[-82.68662999999999,27.829385],"type":"Point"}
}