{
  "type": "Feature",
  "properties": {
    "addr:full":"1600 Talleyrand Ave Jacksonville FL 32206",
    "addr:housenumber":"1600",
    "addr:postcode":"32206",
    "addr:street":"Talleyrand Ave",
    "iso:country":"US",
    "sg:address":"1600 Talleyrand Ave",
    "sg:city":"Jacksonville",
    "sg:classifiers":[
        {
            "category":"Wholesale",
            "subcategory":"Scrap",
            "type":"Manufacturing & Wholesale Goods"
        }
    ],
    "sg:phone":"+1 904 358 3676",
    "sg:postcode":"32206",
    "sg:province":"FL",
    "sg:tags":[
        "recycling",
        "center"
    ],
    "wof:name":"Independence Recycling-Florida",
    "wof:placetype":"venue"
},
  "geometry": {"coordinates":[-81.628193,30.343063],"type":"Point"}
}