{
  "type": "Feature",
  "properties": {
    "iso:country":"US",
    "sg:address":"4499 Rachel Blvd",
    "sg:city":"Spring Hill",
    "sg:classifiers":[
        {
            "category":"Wholesale",
            "subcategory":"Stationery",
            "type":"Manufacturing & Wholesale Goods"
        }
    ],
    "sg:phone":"+1 352 597 0492",
    "sg:postcode":"34607",
    "sg:province":"FL",
    "sg:tags":[
        "supply"
    ],
    "wof:name":"Memories By McQuarrie",
    "wof:placetype":"venue"
},
  "geometry": {"coordinates":[-82.603767,28.49881],"type":"Point"}
}