{
  "type": "Feature",
  "properties": {
    "addr:full":"2593 S State Rd 7 Miramar FL 33023",
    "addr:housenumber":"2593;7",
    "addr:postcode":"33023",
    "addr:street":"S State Rd",
    "iso:country":"US",
    "sg:address":"2593 S State Rd 7",
    "sg:city":"Miramar",
    "sg:classifiers":[
        {
            "category":"Food & Beverages",
            "subcategory":"Specialty",
            "type":"Retail Goods"
        }
    ],
    "sg:phone":"+1 954 893 5838",
    "sg:postcode":"33023",
    "sg:province":"FL",
    "sg:tags":[
        "oriental"
    ],
    "wof:name":"Thai-An Oriental Supermarket",
    "wof:placetype":"venue"
},
  "geometry": {"coordinates":[-80.206695,25.987909],"type":"Point"}
}