{
  "type": "Feature",
  "properties": {
    "addr:full":"414 N Miramar Ave Indialantic FL 32903",
    "addr:housenumber":"414",
    "addr:postcode":"32903",
    "addr:street":"N Miramar Ave",
    "iso:country":"US",
    "sg:address":"414 N Miramar Ave",
    "sg:city":"Indialantic",
    "sg:classifiers":[
        {
            "category":"Shopping",
            "subcategory":"Books",
            "type":"Retail Goods"
        }
    ],
    "sg:phone":"+1 321 729 9495",
    "sg:postcode":"32903",
    "sg:province":"FL",
    "sg:tags":[
        "dealer"
    ],
    "wof:name":"Aquarian Dreams",
    "wof:placetype":"venue"
},
  "geometry": {"coordinates":[-80.567747,28.094168],"type":"Point"}
}