{
  "type": "Feature",
  "properties": {
    "addr:full":"5095 NE 12th Ave Fort Lauderdale FL 33334",
    "addr:housenumber":"5095",
    "addr:postcode":"33334",
    "addr:street":"Ne 12Th Ave",
    "iso:country":"US",
    "sg:address":"5095 NE 12th Ave",
    "sg:city":"Fort Lauderdale",
    "sg:classifiers":[
        {
            "category":"Retail",
            "subcategory":"Auto Repair",
            "type":"Services"
        }
    ],
    "sg:phone":"+1 954 772 7780",
    "sg:postcode":"33334",
    "sg:province":"FL",
    "wof:name":"Personal Automotive Services",
    "wof:placetype":"venue"
},
  "geometry": {"coordinates":[-80.131396,26.191253],"type":"Point"}
}