{
  "type": "Feature",
  "properties": {
    "addr:full":"430 W Lancaster Rd Orlando FL 32809",
    "addr:housenumber":"430",
    "addr:postcode":"32809",
    "addr:street":"W Lancaster Rd",
    "iso:country":"US",
    "sg:address":"430 W Lancaster Rd",
    "sg:city":"Orlando",
    "sg:classifiers":[
        {
            "category":"Social Services",
            "subcategory":"Child Care",
            "type":"Services"
        }
    ],
    "sg:phone":"+1 407 856 6700",
    "sg:postcode":"32809",
    "sg:province":"FL",
    "wof:name":"Drop Of Love Daycare",
    "wof:placetype":"venue"
},
  "geometry": {"coordinates":[-81.380099,28.465359],"type":"Point"}
}