{
  "type": "Feature",
  "properties": {
    "addr:full":"836 Norfolk Pine Ln Vero Beach FL 32963",
    "addr:housenumber":"836",
    "addr:postcode":"32963",
    "addr:street":"Norfolk Pine Ln",
    "iso:country":"US",
    "sg:address":"836 Norfolk Pine Ln",
    "sg:city":"Vero Beach",
    "sg:classifiers":[
        {
            "category":"Real Estate",
            "subcategory":"Real Estate Agent",
            "type":"Services"
        }
    ],
    "sg:phone":"+1 772 234 4479",
    "sg:postcode":"32963",
    "sg:province":"FL",
    "sg:tags":[
        "inspection"
    ],
    "wof:name":"Act Home Inspection",
    "wof:placetype":"venue"
},
  "geometry": {"coordinates":[-80.332207,27.586784],"type":"Point"}
}