{
  "type": "Feature",
  "properties": {
    "iso:country":"US",
    "sg:address":"8350 NW 52nd Ter Ste 200",
    "sg:city":"Doral",
    "sg:classifiers":[
        {
            "category":"Professional",
            "subcategory":"Accounting & Tax Preparation",
            "type":"Services"
        }
    ],
    "sg:phone":"+1 305 591 8850",
    "sg:postcode":"33166",
    "sg:province":"FL",
    "sg:tags":[
        "public",
        "accountants-certified"
    ],
    "sg:website":"http://www.horwathflorida.com",
    "wof:name":"Spear Safer Pa Cpas & Advisors",
    "wof:placetype":"venue"
},
  "geometry": {"coordinates":[-80.332075,25.819851],"type":"Point"}
}