{
  "type": "Feature",
  "properties": {
    "addr:full":"921 Azalea Ln Vero Beach FL 32963",
    "addr:housenumber":"921",
    "addr:postcode":"32963",
    "addr:street":"Azalea Ln",
    "iso:country":"US",
    "sg:address":"921 Azalea Ln",
    "sg:city":"Vero Beach",
    "sg:classifiers":[
        {
            "category":"Retail",
            "subcategory":"Laundry & Dry Cleaning",
            "type":"Services"
        }
    ],
    "sg:phone":"+1 772 234 7313",
    "sg:postcode":"32963",
    "sg:province":"FL",
    "wof:name":"Studio Of Fine Tailoring",
    "wof:placetype":"venue"
},
  "geometry": {"coordinates":[-80.35653499999999,27.65247],"type":"Point"}
}