{
  "type": "Feature",
  "properties": {
    "iso:country":"US",
    "sg:address":"6257 Dowdy Ct",
    "sg:city":"Orlando",
    "sg:classifiers":[
        {
            "category":"Building & Trades",
            "subcategory":"Construction",
            "type":"Services"
        }
    ],
    "sg:phone":"+1 407 352 9822",
    "sg:postcode":"32819",
    "sg:province":"FL",
    "sg:tags":[
        "house"
    ],
    "wof:name":"Accurate Contracting Services",
    "wof:placetype":"venue"
},
  "geometry": {"coordinates":[-81.486739,28.473244],"type":"Point"}
}