{
  "type": "Feature",
  "properties": {
    "addr:full":"4001 Newberry Rd Gainesville FL 32607",
    "addr:housenumber":"4001",
    "addr:postcode":"32607",
    "addr:street":"Newberry Rd",
    "iso:country":"US",
    "sg:address":"4001 Newberry Rd",
    "sg:city":"Gainesville",
    "sg:classifiers":[
        {
            "category":"Professional",
            "subcategory":"Accounting & Tax Preparation",
            "type":"Services"
        }
    ],
    "sg:phone":"+1 352 375 7739",
    "sg:postcode":"32607",
    "sg:province":"FL",
    "sg:tags":[
        "accountant"
    ],
    "wof:name":"Pierce Deegan & Hodgin",
    "wof:placetype":"venue"
},
  "geometry": {"coordinates":[-82.385071,29.653786],"type":"Point"}
}