{
  "type": "Feature",
  "properties": {
    "iso:country":"US",
    "sg:address":"4330 NW 19th St",
    "sg:city":"Fort Lauderdale",
    "sg:classifiers":[
        {
            "category":"Autos & Motor Vehicles",
            "subcategory":"Automobile Sales",
            "type":"Retail Goods"
        }
    ],
    "sg:phone":"+1 954 677 8939",
    "sg:postcode":"33313",
    "sg:province":"FL",
    "sg:tags":[
        "used"
    ],
    "wof:name":"E&W Auto Sales & Service",
    "wof:placetype":"venue"
},
  "geometry": {"coordinates":[-80.20894800000001,26.149925],"type":"Point"}
}