{
  "type": "Feature",
  "properties": {
    "iso:country":"US",
    "sg:address":"165 S Beach Rd",
    "sg:city":"Hobe Sound",
    "sg:classifiers":[
        {
            "category":"Airline",
            "type":"Transportation"
        }
    ],
    "sg:phone":"+1 203 622 6300",
    "sg:postcode":"33455",
    "sg:province":"FL",
    "sg:tags":[
        "charter",
        "air"
    ],
    "wof:name":"Sunrise Leasing Inc",
    "wof:placetype":"venue"
},
  "geometry": {"coordinates":[-80.105921,27.044599],"type":"Point"}
}