{
  "type": "Feature",
  "properties": {
    "iso:country":"US",
    "sg:address":"1035 S Florida Ave",
    "sg:city":"Lakeland",
    "sg:classifiers":[
        {
            "category":"Professional",
            "subcategory":"Employment Agencies",
            "type":"Services"
        }
    ],
    "sg:phone":"+1 863 688 9939",
    "sg:postcode":"33803",
    "sg:province":"FL",
    "sg:tags":[
        "help",
        "supply"
    ],
    "wof:name":"Anderson Jess Prdctons Mdlling",
    "wof:placetype":"venue"
},
  "geometry": {"coordinates":[-81.957195,28.030568],"type":"Point"}
}