{
  "type": "Feature",
  "properties": {
    "iso:country":"US",
    "sg:address":"1744 12th St SE",
    "sg:city":"Largo",
    "sg:classifiers":[
        {
            "category":"Professional",
            "subcategory":"Management & Consulting",
            "type":"Services"
        }
    ],
    "sg:phone":"+1 727 559 0555",
    "sg:postcode":"33771",
    "sg:province":"FL",
    "sg:tags":[
        "consultant",
        "energy",
        "conservation"
    ],
    "wof:name":"Gold Coast Resources Inc",
    "wof:placetype":"venue"
},
  "geometry": {"coordinates":[-82.774092,27.900581],"type":"Point"}
}