{
  "type": "Feature",
  "properties": {
    "iso:country":"US",
    "sg:address":"2475 Bay St",
    "sg:city":"Sarasota",
    "sg:classifiers":[
        {
            "category":"Home & Garden",
            "subcategory":"Furniture",
            "type":"Retail Goods"
        }
    ],
    "sg:phone":"+1 941 356 5437",
    "sg:postcode":"34237",
    "sg:province":"FL",
    "wof:name":"Lance Goods Cab Installation",
    "wof:placetype":"venue"
},
  "geometry": {"coordinates":[-82.521209,27.327864],"type":"Point"}
}