{
  "type": "Feature",
  "properties": {
    "addr:full":"107 US Hwy 27 Avon Park FL 33825",
    "addr:housenumber":"107",
    "addr:postcode":"33825",
    "addr:street":"Us Hwy 27",
    "iso:country":"US",
    "sg:address":"107 US Hwy 27",
    "sg:city":"Avon Park",
    "sg:classifiers":[
        {
            "category":"Food & Beverages",
            "subcategory":"Groceries & Convenience Stores",
            "type":"Retail Goods"
        }
    ],
    "sg:phone":"+1 863 452 9844",
    "sg:postcode":"33825",
    "sg:province":"FL",
    "wof:name":"B & M Discount Beverage",
    "wof:placetype":"venue"
},
  "geometry": {"coordinates":[-81.514349,27.594579],"type":"Point"}
}