{
  "type": "Feature",
  "properties": {
    "addr:full":"6641 Hood St Hollywood FL 33024",
    "addr:housenumber":"6641",
    "addr:postcode":"33024",
    "addr:street":"Hood St",
    "iso:country":"US",
    "sg:address":"6641 Hood St",
    "sg:city":"Hollywood",
    "sg:classifiers":[
        {
            "category":"Manufacturing",
            "subcategory":"Tools & Machinery",
            "type":"Manufacturing & Wholesale Goods"
        }
    ],
    "sg:phone":"+1 954 309 5492",
    "sg:postcode":"33024",
    "sg:province":"FL",
    "sg:tags":[
        "machine",
        "shop"
    ],
    "wof:name":"P & D Technologies Inc",
    "wof:placetype":"venue"
},
  "geometry": {"coordinates":[-80.221962,26.03261],"type":"Point"}
}