{
  "type": "Feature",
  "properties": {
    "iso:country":"US",
    "sg:address":"990 W 23rd St",
    "sg:city":"Hialeah",
    "sg:classifiers":[
        {
            "category":"Shopping",
            "subcategory":"Clothing, Apparel, & Fashions",
            "type":"Retail Goods"
        }
    ],
    "sg:phone":"+1 305 888 4557",
    "sg:postcode":"33010",
    "sg:province":"FL",
    "sg:tags":[
        "wear"
    ],
    "wof:name":"Sunrise Of Miami",
    "wof:placetype":"venue"
},
  "geometry": {"coordinates":[-80.301586,25.842469],"type":"Point"}
}