{
  "type": "Feature",
  "properties": {
    "iso:country":"US",
    "sg:address":"890 Ave Central",
    "sg:city":"Lady Lake",
    "sg:classifiers":[
        {
            "category":"Restaurant",
            "type":"Food & Drink"
        }
    ],
    "sg:phone":"+1 352 753 0043",
    "sg:postcode":"32159",
    "sg:province":"FL",
    "sg:tags":[
        "eating"
    ],
    "wof:name":"Crazy Gringos",
    "wof:placetype":"venue"
},
  "geometry": {"coordinates":[-81.95124199999999,28.945889],"type":"Point"}
}