{
  "type": "Feature",
  "properties": {
    "addr:full":"25 Drennen Rd Orlando FL 32806",
    "addr:housenumber":"25",
    "addr:postcode":"32806",
    "addr:street":"Drennen Rd",
    "iso:country":"US",
    "sg:address":"25 Drennen Rd",
    "sg:city":"Orlando",
    "sg:classifiers":[
        {
            "category":"Manufacturing",
            "subcategory":"Printing",
            "type":"Manufacturing & Wholesale Goods"
        }
    ],
    "sg:phone":"+1 407 856 7137",
    "sg:postcode":"32806",
    "sg:province":"FL",
    "sg:tags":[
        "printer"
    ],
    "wof:name":"Express Press",
    "wof:placetype":"venue"
},
  "geometry": {"coordinates":[-81.37681499999999,28.503167],"type":"Point"}
}