{
  "type": "Feature",
  "properties": {
    "addr:full":"14001 Fairway Island Dr Orlando FL 32837",
    "addr:housenumber":"14001",
    "addr:postcode":"32837",
    "addr:street":"Fairway Island Dr",
    "iso:country":"US",
    "sg:address":"14001 Fairway Island Dr",
    "sg:city":"Orlando",
    "sg:classifiers":[
        {
            "category":"Restaurant",
            "type":"Food & Drink"
        }
    ],
    "sg:phone":"+1 407 852 6258",
    "sg:postcode":"32837",
    "sg:province":"FL",
    "sg:tags":[
        "eating"
    ],
    "wof:name":"Martinez Brett Oswaldo",
    "wof:placetype":"venue"
},
  "geometry": {"coordinates":[-81.40719,28.363989],"type":"Point"}
}