{
  "type": "Feature",
  "properties": {
    "addr:full":"1362 E Lombardy Dr Deltona FL 32725",
    "addr:housenumber":"1362",
    "addr:postcode":"32725",
    "addr:street":"E Lombardy Dr",
    "iso:country":"US",
    "sg:address":"1362 E Lombardy Dr",
    "sg:city":"Deltona",
    "sg:classifiers":[
        {
            "category":"Social Services",
            "type":"Services"
        },
        {
            "category":"Professional",
            "subcategory":"Employment Agencies",
            "type":"Services"
        }
    ],
    "sg:phone":"+1 386 878 8163",
    "sg:postcode":"32725",
    "sg:province":"FL",
    "sg:tags":[
        "workers'",
        "placement",
        "volunteer"
    ],
    "wof:name":"Deltona Fire Fighters Foundation, Inc.",
    "wof:placetype":"venue"
},
  "geometry": {"coordinates":[-81.255484,28.900841],"type":"Point"}
}