{
  "type": "Feature",
  "properties": {
    "iso:country":"US",
    "sg:address":"30384 Old Dixie Hwy",
    "sg:city":"Homestead",
    "sg:classifiers":[
        {
            "category":"Social Services",
            "subcategory":"Child Care",
            "type":"Services"
        }
    ],
    "sg:phone":"+1 305 246 8808",
    "sg:postcode":"33033",
    "sg:province":"FL",
    "wof:name":"Little Star Daycare",
    "wof:placetype":"venue"
},
  "geometry": {"coordinates":[-80.461341,25.485774],"type":"Point"}
}