{
  "type": "Feature",
  "properties": {
    "addr:full":"875 Elkcam Blvd Deltona FL 32725",
    "addr:housenumber":"875",
    "addr:postcode":"32725",
    "addr:street":"Elkcam Blvd",
    "iso:country":"US",
    "sg:address":"875 Elkcam Blvd",
    "sg:city":"Deltona",
    "sg:classifiers":[
        {
            "category":"Social Services",
            "subcategory":"Child Care",
            "type":"Services"
        },
        {
            "category":"Education",
            "subcategory":"Preschool",
            "type":"Public Place"
        },
        {
            "category":"Education",
            "subcategory":"School",
            "type":"Public Place"
        }
    ],
    "sg:phone":"+1 386 789 4515",
    "sg:postcode":"32725",
    "sg:province":"FL",
    "sg:tags":[
        "high",
        "middle",
        "day",
        "elementary"
    ],
    "sg:website":"www.trinitychristianacademy.com",
    "wof:name":"Trinity Christian Academy",
    "wof:placetype":"venue"
},
  "geometry": {"coordinates":[-81.252899,28.925501],"type":"Point"}
}