{
  "type": "Feature",
  "properties": {
    "addr:full":"722 N Central Ave Kissimmee FL 34741",
    "addr:housenumber":"722",
    "addr:postcode":"34741",
    "addr:street":"N Central Ave",
    "iso:country":"US",
    "sg:address":"722 N Central Ave",
    "sg:city":"Kissimmee",
    "sg:classifiers":[
        {
            "category":"Building & Trades",
            "subcategory":"Plumbing",
            "type":"Services"
        }
    ],
    "sg:phone":"+1 407 847 4421",
    "sg:postcode":"34741",
    "sg:province":"FL",
    "sg:tags":[
        "plumbing",
        "contractor"
    ],
    "wof:name":"Mikell Plumbing Inc",
    "wof:placetype":"venue"
},
  "geometry": {"coordinates":[-81.40792,28.298647],"type":"Point"}
}