{
  "type": "Feature",
  "properties": {
    "iso:country":"US",
    "sg:address":"6240 102nd Ave",
    "sg:city":"Pinellas Park",
    "sg:classifiers":[
        {
            "category":"Home & Garden",
            "subcategory":"Garden Supply",
            "type":"Retail Goods"
        },
        {
            "category":"Building & Trades",
            "subcategory":"Landscaping Services",
            "type":"Services"
        }
    ],
    "sg:phone":"+1 727 544 8046",
    "sg:postcode":"33782",
    "sg:province":"FL",
    "sg:tags":[
        "nurseryman",
        "contractor"
    ],
    "wof:name":"Southern Landscaping Service",
    "wof:placetype":"venue"
},
  "geometry": {"coordinates":[-82.722217,27.864545],"type":"Point"}
}