{
  "type": "Feature",
  "properties": {
    "iso:country":"US",
    "sg:address":"2101 Pumpkin Pl NE",
    "sg:city":"Palm Bay",
    "sg:classifiers":[
        {
            "category":"Retail",
            "subcategory":"Repair Shop",
            "type":"Services"
        }
    ],
    "sg:phone":"+1 321 726 9499",
    "sg:postcode":"32905",
    "sg:province":"FL",
    "sg:tags":[
        "lock",
        "locksmith"
    ],
    "wof:name":"A-Able Locksmiths",
    "wof:placetype":"venue"
},
  "geometry": {"coordinates":[-80.60716499999999,28.029258],"type":"Point"}
}