{
  "type": "Feature",
  "properties": {
    "addr:full":"335 Shore Dr Fort Myers FL 33905",
    "addr:housenumber":"335",
    "addr:postcode":"33905",
    "addr:street":"Shore Dr",
    "iso:country":"US",
    "sg:address":"335 Shore Dr",
    "sg:city":"Fort Myers",
    "sg:classifiers":[
        {
            "category":"Retail",
            "subcategory":"Car Wash",
            "type":"Services"
        }
    ],
    "sg:phone":"+1 239 690 0202",
    "sg:postcode":"33905",
    "sg:province":"FL",
    "sg:tags":[
        "carwash"
    ],
    "wof:name":"Car Wash Guys of SW F",
    "wof:placetype":"venue"
},
  "geometry": {"coordinates":[-81.806067,26.689086],"type":"Point"}
}