{
  "type": "Feature",
  "properties": {
    "iso:country":"US",
    "sg:address":"40 W Colonial Dr",
    "sg:city":"Orlando",
    "sg:classifiers":[
        {
            "category":"Professional",
            "subcategory":"Business Services",
            "type":"Services"
        }
    ],
    "sg:phone":"+1 407 481 1035",
    "sg:postcode":"32801",
    "sg:province":"FL",
    "sg:tags":[
        "auction",
        "gallery"
    ],
    "wof:name":"Shaias Auction House",
    "wof:placetype":"venue"
},
  "geometry": {"coordinates":[-81.380241,28.553045],"type":"Point"}
}