{
  "type": "Feature",
  "properties": {
    "iso:country":"US",
    "sg:address":"11729 Preservation Ln",
    "sg:city":"Boca Raton",
    "sg:classifiers":[
        {
            "category":"Restaurant",
            "type":"Food & Drink"
        }
    ],
    "sg:phone":"+1 561 620 3882",
    "sg:postcode":"33498",
    "sg:province":"FL",
    "sg:tags":[
        "eating"
    ],
    "wof:name":"Lindburgers",
    "wof:placetype":"venue"
},
  "geometry": {"coordinates":[-80.234638,26.391481],"type":"Point"}
}