{
  "type": "Feature",
  "properties": {
    "addr:full":"1680 NW 4th Ave Miami FL 33136",
    "addr:housenumber":"1680",
    "addr:postcode":"33136",
    "addr:street":"Nw 4Th Ave",
    "iso:country":"US",
    "sg:address":"1680 NW 4th Ave",
    "sg:city":"Miami",
    "sg:classifiers":[
        {
            "category":"Health Services",
            "subcategory":"Clinic",
            "type":"Services"
        }
    ],
    "sg:phone":"+1 305 573 9727",
    "sg:postcode":"33136",
    "sg:province":"FL",
    "sg:tags":[
        "specialty",
        "outpatient"
    ],
    "wof:name":"New Horizon Fmly Preservation",
    "wof:placetype":"venue"
},
  "geometry": {"coordinates":[-80.201753,25.791068],"type":"Point"}
}