{
  "type": "Feature",
  "properties": {
    "iso:country":"US",
    "sg:address":"7000 SW 97th Ave Ste 120",
    "sg:city":"Miami",
    "sg:classifiers":[
        {
            "category":"Professional",
            "subcategory":"Lawyer & Legal Services",
            "type":"Services"
        }
    ],
    "sg:phone":"+1 305 271 9521",
    "sg:postcode":"33173",
    "sg:province":"FL",
    "wof:name":"Contreras Paul A Atty",
    "wof:placetype":"venue"
},
  "geometry": {"coordinates":[-80.35019699999999,25.7034],"type":"Point"}
}