{
  "type": "Feature",
  "properties": {
    "iso:country":"US",
    "sg:address":"8508 SW 2 Pl",
    "sg:city":"Gainesville",
    "sg:classifiers":[
        {
            "category":"Shopping",
            "type":"Retail Goods"
        }
    ],
    "sg:phone":"+1 352 331 4708",
    "sg:postcode":"32607",
    "sg:province":"FL",
    "sg:tags":[
        "merchandise"
    ],
    "wof:name":"Silk Expressions",
    "wof:placetype":"venue"
},
  "geometry": {"coordinates":[-82.43366399999999,29.650257],"type":"Point"}
}