{
  "type": "Feature",
  "properties": {
    "iso:country":"US",
    "sg:address":"3553 NW 78th Ave",
    "sg:city":"Doral",
    "sg:classifiers":[
        {
            "category":"Wholesale",
            "subcategory":"Machinery & Supplies",
            "type":"Manufacturing & Wholesale Goods"
        }
    ],
    "sg:phone":"+1 305 477 9253",
    "sg:postcode":"33122",
    "sg:province":"FL",
    "sg:tags":[
        "compressor",
        "gas"
    ],
    "wof:name":"Atlas Copco Factory Distr",
    "wof:placetype":"venue"
},
  "geometry": {"coordinates":[-80.32328800000001,25.805658],"type":"Point"}
}