{
  "type": "Feature",
  "properties": {
    "addr:full":"13080 Metro Pkwy Fort Myers FL 33912",
    "addr:housenumber":"13080",
    "addr:postcode":"33912",
    "addr:street":"Metro Pkwy",
    "iso:country":"US",
    "sg:address":"13080 Metro Pkwy",
    "sg:city":"Fort Myers",
    "sg:classifiers":[
        {
            "category":"Wholesale",
            "subcategory":"Hardware",
            "type":"Manufacturing & Wholesale Goods"
        }
    ],
    "sg:phone":"+1 239 936 9595",
    "sg:postcode":"33912",
    "sg:province":"FL",
    "sg:tags":[
        "refrigerating"
    ],
    "wof:name":"United Refrigeration",
    "wof:placetype":"venue"
},
  "geometry": {"coordinates":[-81.852852,26.551725],"type":"Point"}
}