{
  "type": "Feature",
  "properties": {
    "iso:country":"US",
    "sg:address":"427 N Fort Lauderdale Beach Blvd",
    "sg:city":"Fort Lauderdale",
    "sg:classifiers":[
        {
            "category":"Restaurant",
            "type":"Food & Drink"
        }
    ],
    "sg:phone":"+1 954 462 1008",
    "sg:postcode":"33304",
    "sg:province":"FL",
    "wof:name":"Bierbrunnen Fort Lauderdale",
    "wof:placetype":"venue"
},
  "geometry": {"coordinates":[-80.103409,26.129606],"type":"Point"}
}