{
  "type": "Feature",
  "properties": {
    "addr:full":"14517 Billie Ln Dade City FL 33525",
    "addr:housenumber":"14517",
    "addr:postcode":"33525",
    "addr:street":"Billie Ln",
    "iso:country":"US",
    "sg:address":"14517 Billie Ln",
    "sg:city":"Dade City",
    "sg:classifiers":[
        {
            "category":"Real Estate",
            "subcategory":"Real Estate Operator",
            "type":"Services"
        }
    ],
    "sg:phone":"+1 813 285 3144",
    "sg:postcode":"33525",
    "sg:province":"FL",
    "sg:tags":[
        "building",
        "nonresidential"
    ],
    "wof:name":"Westervelt Rchard Property MGT",
    "wof:placetype":"venue"
},
  "geometry": {"coordinates":[-82.16099800000001,28.369549],"type":"Point"}
}