{
  "type": "Feature",
  "properties": {
    "iso:country":"US",
    "sg:address":"4675 E 10th Ct",
    "sg:city":"Hialeah",
    "sg:classifiers":[
        {
            "category":"Food & Beverages",
            "subcategory":"Liquor & Beverages",
            "type":"Retail Goods"
        },
        {
            "category":"Food & Beverages",
            "subcategory":"Groceries & Convenience Stores",
            "type":"Retail Goods"
        }
    ],
    "sg:phone":"+1 305 681 6031",
    "sg:postcode":"33013",
    "sg:province":"FL",
    "sg:tags":[
        "juice",
        "bottler",
        "beverages-distributors"
    ],
    "wof:name":"Kendall Juice Corp",
    "wof:placetype":"venue"
},
  "geometry": {"coordinates":[-80.262157,25.865359],"type":"Point"}
}