{
  "type": "Feature",
  "properties": {
    "addr:full":"4826 Bartelt Rd Holiday FL 34690",
    "addr:housenumber":"4826",
    "addr:postcode":"34690",
    "addr:street":"Bartelt Rd",
    "iso:country":"US",
    "sg:address":"4826 Bartelt Rd",
    "sg:city":"Holiday",
    "sg:classifiers":[
        {
            "category":"Organizations",
            "subcategory":"Religious Organization",
            "type":"Services"
        }
    ],
    "sg:phone":"+1 727 937 1520",
    "sg:postcode":"34690",
    "sg:province":"FL",
    "sg:tags":[
        "church"
    ],
    "wof:name":"Holiday United Church Christ",
    "wof:placetype":"venue"
},
  "geometry": {"coordinates":[-82.731921,28.185147],"type":"Point"}
}