{
  "type": "Feature",
  "properties": {
    "addr:full":"13935 SW 102nd Ct Miami FL 33176",
    "addr:housenumber":"13935",
    "addr:postcode":"33176",
    "addr:street":"Sw 102Nd Ct",
    "iso:country":"US",
    "sg:address":"13935 SW 102nd Ct",
    "sg:city":"Miami",
    "sg:classifiers":[
        {
            "category":"Professional",
            "subcategory":"Research",
            "type":"Services"
        }
    ],
    "sg:phone":"+1 305 232 6720",
    "sg:postcode":"33176",
    "sg:province":"FL",
    "sg:tags":[
        "analysis",
        "market"
    ],
    "wof:name":"Loretta Marketing Group",
    "wof:placetype":"venue"
},
  "geometry": {"coordinates":[-80.35945100000001,25.639974],"type":"Point"}
}