{
  "type": "Feature",
  "properties": {
    "iso:country":"US",
    "sg:address":"2496 Sylvia Ln",
    "sg:city":"Venice",
    "sg:classifiers":[
        {
            "category":"Building & Trades",
            "subcategory":"Electrical",
            "type":"Services"
        }
    ],
    "sg:phone":"+1 941 488 5672",
    "sg:postcode":"34292",
    "sg:province":"FL",
    "sg:tags":[
        "electrical",
        "contractor"
    ],
    "wof:name":"Ellis Electric",
    "wof:placetype":"venue"
},
  "geometry": {"coordinates":[-82.39569,27.098687],"type":"Point"}
}