{
  "type": "Feature",
  "properties": {
    "iso:country":"US",
    "sg:address":"4350 Bayou Blvd",
    "sg:city":"Pensacola",
    "sg:classifiers":[
        {
            "category":"Retail",
            "subcategory":"Laundry & Dry Cleaning",
            "type":"Services"
        }
    ],
    "sg:phone":"+1 850 478 9633",
    "sg:postcode":"32503",
    "sg:province":"FL",
    "sg:tags":[
        "cleaners"
    ],
    "wof:name":"Ambassador Cleaners",
    "wof:placetype":"venue"
},
  "geometry": {"coordinates":[-87.20491,30.466977],"type":"Point"}
}