{
  "type": "Feature",
  "properties": {
    "iso:country":"US",
    "sg:address":"525 Parque Dr",
    "sg:city":"Ormond Beach",
    "sg:classifiers":[
        {
            "category":"Retail",
            "subcategory":"Auto Repair",
            "type":"Services"
        }
    ],
    "sg:phone":"+1 386 672 5870",
    "sg:postcode":"32174",
    "sg:province":"FL",
    "sg:tags":[
        "repairing",
        "automobile"
    ],
    "wof:name":"Ed's Garage",
    "wof:placetype":"venue"
},
  "geometry": {"coordinates":[-81.056921,29.269881],"type":"Point"}
}