{
  "type": "Feature",
  "properties": {
    "iso:country":"US",
    "sg:address":"1165 E Blue Heron Blvd",
    "sg:city":"Riviera Beach",
    "sg:classifiers":[
        {
            "category":"Restaurant",
            "type":"Food & Drink"
        }
    ],
    "sg:phone":"+1 561 848 3560",
    "sg:postcode":"33404",
    "sg:province":"FL",
    "wof:name":"Captain Scoops",
    "wof:placetype":"venue"
},
  "geometry": {"coordinates":[-80.03739400000001,26.78359],"type":"Point"}
}