{
  "type": "Feature",
  "properties": {
    "addr:full":"2320 S Park Ave Sanford FL 32771",
    "addr:housenumber":"2320",
    "addr:postcode":"32771",
    "addr:street":"S Park Ave",
    "iso:country":"US",
    "sg:address":"2320 S Park Ave",
    "sg:city":"Sanford",
    "sg:classifiers":[
        {
            "category":"Shopping",
            "subcategory":"Computers & Home Electronics",
            "type":"Retail Goods"
        }
    ],
    "sg:phone":"+1 407 322 6723",
    "sg:postcode":"32771",
    "sg:province":"FL",
    "wof:name":"Radio Shack",
    "wof:placetype":"venue"
},
  "geometry": {"coordinates":[-81.267822,28.790485],"type":"Point"}
}