{
  "type": "Feature",
  "properties": {
    "iso:country":"US",
    "sg:address":"604 Baynard Dr",
    "sg:city":"Tarpon Springs",
    "sg:classifiers":[
        {
            "category":"Banks & Credit Unions",
            "subcategory":"Financial Services",
            "type":"Services"
        }
    ],
    "sg:phone":"+1 727 934 3774",
    "sg:postcode":"34689",
    "sg:province":"FL",
    "sg:tags":[
        "company",
        "investment",
        "holding"
    ],
    "wof:name":"Grand Commercial Center Inc",
    "wof:placetype":"venue"
},
  "geometry": {"coordinates":[-82.78380900000001,28.15293],"type":"Point"}
}