{
  "type": "Feature",
  "properties": {
    "addr:full":"4375 Maurice Dr Delray Beach FL 33445",
    "addr:housenumber":"4375",
    "addr:postcode":"33445",
    "addr:street":"Maurice Dr",
    "iso:country":"US",
    "sg:address":"4375 Maurice Dr",
    "sg:city":"Delray Beach",
    "sg:classifiers":[
        {
            "category":"Building & Trades",
            "subcategory":"Electrical",
            "type":"Services"
        }
    ],
    "sg:phone":"+1 561 499 4260",
    "sg:postcode":"33445",
    "sg:province":"FL",
    "sg:tags":[
        "installation"
    ],
    "wof:name":"All Florida Generator Instltns",
    "wof:placetype":"venue"
},
  "geometry": {"coordinates":[-80.112331,26.462378],"type":"Point"}
}