{
  "type": "Feature",
  "properties": {
    "iso:country":"US",
    "sg:address":"2090 Us 441",
    "sg:city":"Hollywood",
    "sg:classifiers":[
        {
            "category":"Restaurant",
            "type":"Food & Drink"
        }
    ],
    "sg:menulink":"http://www.allmenus.com/fl/hollywood/16051-disalvos-pizza--italian-restaurant/menu/",
    "sg:phone":"+1 954 989 7110",
    "sg:postcode":"33021",
    "sg:province":"FL",
    "sg:tags":[
        "italian"
    ],
    "wof:name":"DiSalvo's Pizza & Italian Restaurant",
    "wof:placetype":"venue"
},
  "geometry": {"coordinates":[-80.208185,26.028149],"type":"Point"}
}