{
  "type": "Feature",
  "properties": {
    "iso:country":"US",
    "sg:address":"445 Douglas Ave",
    "sg:city":"Altamonte Spgs",
    "sg:classifiers":[
        {
            "category":"Banks & Credit Unions",
            "subcategory":"Investment Brokerage",
            "type":"Services"
        }
    ],
    "sg:phone":"+1 407 862 1666",
    "sg:postcode":"32714",
    "sg:province":"FL",
    "sg:tags":[
        "advisory",
        "financial"
    ],
    "wof:name":"Financial Research Svc",
    "wof:placetype":"venue"
},
  "geometry": {"coordinates":[-81.390292,28.667837],"type":"Point"}
}