{
  "type": "Feature",
  "properties": {
    "iso:country":"US",
    "sg:address":"12647 Randolph Siding Rd",
    "sg:city":"Jupiter",
    "sg:classifiers":[
        {
            "category":"Health Services",
            "subcategory":"Health Practitioner",
            "type":"Services"
        }
    ],
    "sg:phone":"+1 561 747 6400",
    "sg:postcode":"33478",
    "sg:province":"FL",
    "sg:tags":[
        "therapist",
        "physical"
    ],
    "wof:name":"Reliable Therapy Svc Inc",
    "wof:placetype":"venue"
},
  "geometry": {"coordinates":[-80.234602,26.913079],"type":"Point"}
}