{
  "type": "Feature",
  "properties": {
    "addr:full":"3138 Laurel Grove S Jacksonville FL 32223",
    "addr:housenumber":"3138",
    "addr:postcode":"32223",
    "addr:street":"Laurel Grove S",
    "iso:country":"US",
    "sg:address":"3138 Laurel Grove S",
    "sg:city":"Jacksonville",
    "sg:classifiers":[
        {
            "category":"Utilities",
            "subcategory":"Cable",
            "type":"Services"
        }
    ],
    "sg:phone":"+1 904 683 6217",
    "sg:postcode":"32223",
    "sg:province":"FL",
    "sg:tags":[
        "television"
    ],
    "wof:name":"Cable Communications",
    "wof:placetype":"venue"
},
  "geometry": {"coordinates":[-81.621774,30.171307],"type":"Point"}
}