{
  "type": "Feature",
  "properties": {
    "iso:country":"US",
    "sg:address":"36516 Leslye Ln",
    "sg:city":"Eustis",
    "sg:classifiers":[
        {
            "category":"Retail",
            "subcategory":"Repair Shop",
            "type":"Services"
        }
    ],
    "sg:phone":"+1 352 589 6669",
    "sg:postcode":"32736",
    "sg:province":"FL",
    "sg:tags":[
        "lock",
        "locksmith"
    ],
    "wof:name":"A A American Advance Locksmith",
    "wof:placetype":"venue"
},
  "geometry": {"coordinates":[-81.52929399999999,28.88019],"type":"Point"}
}