{
  "type": "Feature",
  "properties": {
    "iso:country":"US",
    "sg:address":"5009 W Rio Vista Ave",
    "sg:city":"Tampa",
    "sg:classifiers":[
        {
            "category":"Manufacturing",
            "subcategory":"Printing",
            "type":"Manufacturing & Wholesale Goods"
        }
    ],
    "sg:phone":"+1 813 881 0887",
    "sg:postcode":"33634",
    "sg:province":"FL",
    "sg:tags":[
        "publisher"
    ],
    "wof:name":"Lightning Publications",
    "wof:placetype":"venue"
},
  "geometry": {"coordinates":[-82.526572,27.999661],"type":"Point"}
}