{
  "type": "Feature",
  "properties": {
    "addr:full":"1060 Maitland Center Cmn Maitland FL 32751",
    "addr:housenumber":"1060",
    "addr:postcode":"32751",
    "addr:street":"Maitland Center Cmn",
    "iso:country":"US",
    "sg:address":"1060 Maitland Center Cmn",
    "sg:city":"Maitland",
    "sg:classifiers":[
        {
            "category":"Insurance",
            "subcategory":"Insurance Agent",
            "type":"Services"
        }
    ],
    "sg:phone":"+1 407 667 0022",
    "sg:postcode":"32751",
    "sg:province":"FL",
    "wof:name":"Great America Insurance Co",
    "wof:placetype":"venue"
},
  "geometry": {"coordinates":[-81.397364,28.637861],"type":"Point"}
}