{
  "type": "Feature",
  "properties": {
    "addr:full":"4257 Lafayette St Marianna FL 32446",
    "addr:housenumber":"4257",
    "addr:postcode":"32446",
    "addr:street":"Lafayette St",
    "iso:country":"US",
    "sg:address":"4257 Lafayette St",
    "sg:city":"Marianna",
    "sg:classifiers":[
        {
            "category":"Health Services",
            "subcategory":"Doctor",
            "type":"Services"
        }
    ],
    "sg:phone":"+1 850 526 5500",
    "sg:postcode":"32446",
    "sg:province":"FL",
    "sg:tags":[
        "medical"
    ],
    "wof:name":"Richard Laubaugh MD",
    "wof:placetype":"venue"
},
  "geometry": {"coordinates":[-85.241545,30.780575],"type":"Point"}
}