{
  "type": "Feature",
  "properties": {
    "addr:full":"7229 SW 24th St Miami FL 33155",
    "addr:housenumber":"7229",
    "addr:postcode":"33155",
    "addr:street":"Sw 24Th St",
    "iso:country":"US",
    "sg:address":"7229 SW 24th St",
    "sg:city":"Miami",
    "sg:classifiers":[
        {
            "category":"Insurance",
            "subcategory":"Insurance Agent",
            "type":"Services"
        }
    ],
    "sg:phone":"+1 305 266 1700",
    "sg:postcode":"33155",
    "sg:province":"FL",
    "wof:name":"Equino & Assoc",
    "wof:placetype":"venue"
},
  "geometry": {"coordinates":[-80.315178,25.748176],"type":"Point"}
}