{
  "type": "Feature",
  "properties": {
    "iso:country":"US",
    "sg:address":"472 Warren Ln",
    "sg:city":"Key Biscayne",
    "sg:classifiers":[
        {
            "category":"Building & Trades",
            "subcategory":"Construction",
            "type":"Services"
        }
    ],
    "sg:phone":"+1 305 663 7307",
    "sg:postcode":"33149",
    "sg:province":"FL",
    "sg:tags":[
        "home",
        "general",
        "family",
        "contractor"
    ],
    "wof:name":"Jauregui Construction & Dev",
    "wof:placetype":"venue"
},
  "geometry": {"coordinates":[-80.168944,25.692138],"type":"Point"}
}