{
  "type": "Feature",
  "properties": {
    "iso:country":"US",
    "sg:address":"9860 W Boynton Beach Blvd",
    "sg:city":"Boynton Beach",
    "sg:classifiers":[
        {
            "category":"Building & Trades",
            "subcategory":"Landscaping Services",
            "type":"Services"
        }
    ],
    "sg:phone":"+1 561 901 1515",
    "sg:postcode":"33437",
    "sg:province":"FL",
    "sg:tags":[
        "landscape"
    ],
    "wof:name":"Pedro Santiago Landscaping",
    "wof:placetype":"venue"
},
  "geometry": {"coordinates":[-80.201083,26.527602],"type":"Point"}
}