{
  "type": "Feature",
  "properties": {
    "iso:country":"US",
    "sg:address":"12929 Buckhorn Dr",
    "sg:city":"Hudson",
    "sg:classifiers":[
        {
            "category":"Building & Trades",
            "subcategory":"Cleaning & Sanitation",
            "type":"Services"
        }
    ],
    "sg:phone":"+1 727 856 9562",
    "sg:postcode":"34669",
    "sg:province":"FL",
    "sg:tags":[
        "janitor",
        "maintenance"
    ],
    "wof:name":"Corporate Clean",
    "wof:placetype":"venue"
},
  "geometry": {"coordinates":[-82.61501,28.344238],"type":"Point"}
}