{
  "type": "Feature",
  "properties": {
    "addr:full":"3781 Commerce Loop Orlando FL 32808",
    "addr:housenumber":"3781",
    "addr:postcode":"32808",
    "addr:street":"Commerce Loop",
    "iso:country":"US",
    "sg:address":"3781 Commerce Loop",
    "sg:city":"Orlando",
    "sg:classifiers":[
        {
            "category":"Wholesale",
            "subcategory":"Construction Materials",
            "type":"Manufacturing & Wholesale Goods"
        }
    ],
    "sg:phone":"+1 407 650 8118",
    "sg:postcode":"32808",
    "sg:province":"FL",
    "sg:tags":[
        "granite"
    ],
    "wof:name":"Stone Crazy",
    "wof:placetype":"venue"
},
  "geometry": {"coordinates":[-81.427356,28.580037],"type":"Point"}
}