{
  "type": "Feature",
  "properties": {
    "addr:full":"5770 Hoffner Ave Orlando FL 32822",
    "addr:housenumber":"5770",
    "addr:postcode":"32822",
    "addr:street":"Hoffner Ave",
    "iso:country":"US",
    "sg:address":"5770 Hoffner Ave",
    "sg:city":"Orlando",
    "sg:classifiers":[
        {
            "category":"Wholesale",
            "subcategory":"Electrical",
            "type":"Manufacturing & Wholesale Goods"
        }
    ],
    "sg:phone":"+1 407 380 6020",
    "sg:postcode":"32822",
    "sg:province":"FL",
    "sg:tags":[
        "equipment",
        "electronic",
        "supply"
    ],
    "sg:website":"www.memec.com",
    "wof:name":"Insight Electronics",
    "wof:placetype":"venue"
},
  "geometry": {"coordinates":[-81.30789900000001,28.480557],"type":"Point"}
}