{
  "type": "Feature",
  "properties": {
    "iso:country":"US",
    "sg:address":"7274 Poinciana Ct",
    "sg:city":"Hialeah",
    "sg:classifiers":[
        {
            "category":"Health Services",
            "subcategory":"Clinic",
            "type":"Services"
        }
    ],
    "sg:phone":"+1 305 785 5411",
    "sg:postcode":"33014",
    "sg:province":"FL",
    "sg:tags":[
        "counselor",
        "mental"
    ],
    "wof:name":"Allen Drozd",
    "wof:placetype":"venue"
},
  "geometry": {"coordinates":[-80.31975,25.905067],"type":"Point"}
}