{
  "type": "Feature",
  "properties": {
    "addr:full":"104 Mileham Dr Orlando FL 32835",
    "addr:housenumber":"104",
    "addr:postcode":"32835",
    "addr:street":"Mileham Dr",
    "iso:country":"US",
    "sg:address":"104 Mileham Dr",
    "sg:city":"Orlando",
    "sg:classifiers":[
        {
            "category":"Building & Trades",
            "subcategory":"Plumbing",
            "type":"Services"
        }
    ],
    "sg:phone":"+1 407 299 6395",
    "sg:postcode":"32835",
    "sg:province":"FL",
    "sg:tags":[
        "plumbing",
        "contractor"
    ],
    "wof:name":"Wilder Plumbing",
    "wof:placetype":"venue"
},
  "geometry": {"coordinates":[-81.503331,28.540383],"type":"Point"}
}