{
  "type": "Feature",
  "properties": {
    "addr:full":"533 S Howard Ave Tampa FL 33606",
    "addr:housenumber":"533",
    "addr:postcode":"33606",
    "addr:street":"S Howard Ave",
    "iso:country":"US",
    "sg:address":"533 S Howard Ave",
    "sg:city":"Tampa",
    "sg:classifiers":[
        {
            "category":"Banks & Credit Unions",
            "subcategory":"Bank",
            "type":"Services"
        },
        {
            "category":"Banks & Credit Unions",
            "subcategory":"Financial Services",
            "type":"Services"
        }
    ],
    "sg:phone":"+1 239 466 7500",
    "sg:postcode":"33606",
    "sg:province":"FL",
    "sg:tags":[
        "saving",
        "loan",
        "commercial"
    ],
    "sg:website":"http://www.colonialbank.com",
    "wof:name":"Colonial Bank",
    "wof:placetype":"venue"
},
  "geometry": {"coordinates":[-82.482991,27.939448],"type":"Point"}
}