{
  "type": "Feature",
  "properties": {
    "iso:country":"US",
    "sg:address":"14965 SW 49th Ln Apt E",
    "sg:city":"Miami",
    "sg:classifiers":[
        {
            "category":"Professional",
            "subcategory":"Management & Consulting",
            "type":"Services"
        }
    ],
    "sg:phone":"+1 305 772 1354",
    "sg:postcode":"33185",
    "sg:province":"FL",
    "sg:tags":[
        "consultant",
        "educational"
    ],
    "wof:name":"Posts, Inc.",
    "wof:placetype":"venue"
},
  "geometry": {"coordinates":[-80.434712,25.718713],"type":"Point"}
}