{
  "type": "Feature",
  "properties": {
    "addr:full":"1750 E Commercial Blvd Fort Lauderdale FL 33334",
    "addr:housenumber":"1750",
    "addr:postcode":"33334",
    "addr:street":"E Commercial Blvd",
    "iso:country":"US",
    "sg:address":"1750 E Commercial Blvd",
    "sg:city":"Fort Lauderdale",
    "sg:classifiers":[
        {
            "category":"Recreation",
            "type":"Entertainment"
        }
    ],
    "sg:phone":"+1 954 771 0084",
    "sg:postcode":"33334",
    "sg:province":"FL",
    "sg:tags":[
        "martial",
        "arts",
        "instruction"
    ],
    "wof:name":"Brazilian Jiu-Jitsu Ctr",
    "wof:placetype":"venue"
},
  "geometry": {"coordinates":[-80.12316,26.18894],"type":"Point"}
}