{
  "type": "Feature",
  "properties": {
    "iso:country":"US",
    "sg:address":"1381 Sawgrass Ct",
    "sg:city":"Winter Park",
    "sg:classifiers":[
        {
            "category":"Banks & Credit Unions",
            "subcategory":"Investment Brokerage",
            "type":"Services"
        }
    ],
    "sg:phone":"+1 407 678 9970",
    "sg:postcode":"32792",
    "sg:province":"FL",
    "sg:tags":[
        "advisory"
    ],
    "wof:name":"Kiss & Company",
    "wof:placetype":"venue"
},
  "geometry": {"coordinates":[-81.313952,28.577118],"type":"Point"}
}