{
  "type": "Feature",
  "properties": {
    "iso:country":"US",
    "sg:address":"21717 SW 129th Ave",
    "sg:city":"Miami",
    "sg:classifiers":[
        {
            "category":"Sports & Exercise",
            "subcategory":"Swimming Pool",
            "type":"Entertainment"
        }
    ],
    "sg:phone":"+1 305 258 0101",
    "sg:postcode":"33170",
    "sg:province":"FL",
    "sg:tags":[
        "repair"
    ],
    "wof:name":"Pool Guardian Inc",
    "wof:placetype":"venue"
},
  "geometry": {"coordinates":[-80.40085000000001,25.564749],"type":"Point"}
}