{
  "type": "Feature",
  "properties": {
    "addr:full":"2605 W 8th Ave Hialeah FL 33010",
    "addr:housenumber":"2605",
    "addr:postcode":"33010",
    "addr:street":"W 8Th Ave",
    "iso:country":"US",
    "sg:address":"2605 W 8th Ave",
    "sg:city":"Hialeah",
    "sg:classifiers":[
        {
            "category":"Manufacturing",
            "subcategory":"Petroleum Products",
            "type":"Manufacturing & Wholesale Goods"
        }
    ],
    "sg:phone":"+1 305 887 1147",
    "sg:postcode":"33010",
    "sg:province":"FL",
    "sg:tags":[
        "contract"
    ],
    "wof:name":"Monica Manufacturing",
    "wof:placetype":"venue"
},
  "geometry": {"coordinates":[-80.29818899999999,25.845298],"type":"Point"}
}