{
  "type": "Feature",
  "properties": {
    "iso:country":"US",
    "sg:address":"1615 S Congress Ave",
    "sg:city":"Delray Beach",
    "sg:classifiers":[
        {
            "category":"Professional",
            "subcategory":"Computer Services",
            "type":"Services"
        }
    ],
    "sg:phone":"+1 561 265 2700",
    "sg:postcode":"33445",
    "sg:province":"FL",
    "sg:tags":[
        "development",
        "software"
    ],
    "wof:name":"Ecometry Corporation",
    "wof:placetype":"venue"
},
  "geometry": {"coordinates":[-80.09233500000001,26.438261],"type":"Point"}
}