{
  "type": "Feature",
  "properties": {
    "addr:full":"10500 Aviation Blvd Marathon FL 33050",
    "addr:housenumber":"10500",
    "addr:postcode":"33050",
    "addr:street":"Aviation Blvd",
    "iso:country":"US",
    "sg:address":"10500 Aviation Blvd",
    "sg:city":"Marathon",
    "sg:classifiers":[
        {
            "category":"Manufacturing",
            "subcategory":"Glass & Minerals",
            "type":"Manufacturing & Wholesale Goods"
        }
    ],
    "sg:phone":"+1 305 743 8341",
    "sg:postcode":"33050",
    "sg:province":"FL",
    "sg:tags":[
        "concrete",
        "brick",
        "prod",
        "block"
    ],
    "wof:name":"Ornamental Cast Stone",
    "wof:placetype":"venue"
},
  "geometry": {"coordinates":[-81.04040000000001,24.731949],"type":"Point"}
}