{
  "type": "Feature",
  "properties": {
    "addr:full":"3010 Apache Dr Milton FL 32571",
    "addr:housenumber":"3010",
    "addr:postcode":"32571",
    "addr:street":"Apache Dr",
    "iso:country":"US",
    "sg:address":"3010 Apache Dr",
    "sg:city":"Milton",
    "sg:classifiers":[
        {
            "category":"Building & Trades",
            "subcategory":"Construction",
            "type":"Services"
        }
    ],
    "sg:phone":"+1 850 994 8837",
    "sg:postcode":"32571",
    "sg:province":"FL",
    "sg:tags":[
        "house"
    ],
    "wof:name":"R & T Builders",
    "wof:placetype":"venue"
},
  "geometry": {"coordinates":[-87.192083,30.762719],"type":"Point"}
}