{
  "type": "Feature",
  "properties": {
    "addr:full":"11980 SW 23rd St Miramar FL 33025",
    "addr:housenumber":"11980",
    "addr:postcode":"33025",
    "addr:street":"Sw 23Rd St",
    "iso:country":"US",
    "sg:address":"11980 SW 23rd St",
    "sg:city":"Miramar",
    "sg:classifiers":[
        {
            "category":"Organizations",
            "subcategory":"Professional Association",
            "type":"Services"
        }
    ],
    "sg:phone":"+1 954 432 9179",
    "sg:postcode":"33025",
    "sg:province":"FL",
    "wof:name":"Community Association Svc",
    "wof:placetype":"venue"
},
  "geometry": {"coordinates":[-80.30615,25.987839],"type":"Point"}
}