{
  "type": "Feature",
  "properties": {
    "addr:full":"1503 Morning Dove Loop S Lakeland FL 33809",
    "addr:housenumber":"1503",
    "addr:postcode":"33809",
    "addr:street":"Morning Dove Loop S",
    "iso:country":"US",
    "sg:address":"1503 Morning Dove Loop S",
    "sg:city":"Lakeland",
    "sg:classifiers":[
        {
            "category":"Insurance",
            "subcategory":"Hazard Insurance",
            "type":"Services"
        }
    ],
    "sg:phone":"+1 863 853 3960",
    "sg:postcode":"33809",
    "sg:province":"FL",
    "wof:name":"Hanneken & Assoc",
    "wof:placetype":"venue"
},
  "geometry": {"coordinates":[-81.92488400000001,28.132999],"type":"Point"}
}