{
  "type": "Feature",
  "properties": {
    "iso:country":"US",
    "sg:address":"6691 NW 60th St",
    "sg:city":"Ocala",
    "sg:classifiers":[
        {
            "category":"Building & Trades",
            "subcategory":"Construction",
            "type":"Services"
        }
    ],
    "sg:phone":"+1 352 629 0790",
    "sg:postcode":"34482",
    "sg:province":"FL",
    "sg:tags":[
        "contractor"
    ],
    "wof:name":"David & Dayna Rescreen Svcs",
    "wof:placetype":"venue"
},
  "geometry": {"coordinates":[-82.228927,29.249522],"type":"Point"}
}