{
  "type": "Feature",
  "properties": {
    "addr:full":"1265 N 7th St Jacksonville FL 32250",
    "addr:housenumber":"1265",
    "addr:postcode":"32250",
    "addr:street":"N 7Th St",
    "iso:country":"US",
    "sg:address":"1265 N 7th St",
    "sg:city":"Jacksonville",
    "sg:classifiers":[
        {
            "category":"Communications",
            "type":"Services"
        }
    ],
    "sg:phone":"+1 904 434 2090",
    "sg:postcode":"32250",
    "sg:province":"FL",
    "sg:tags":[
        "communication"
    ],
    "wof:name":"Brightline Communications Inc",
    "wof:placetype":"venue"
},
  "geometry": {"coordinates":[-81.39890200000001,30.299815],"type":"Point"}
}