{
  "type": "Feature",
  "properties": {
    "iso:country":"US",
    "sg:address":"225 Cortez Rd",
    "sg:city":"West Palm Beach",
    "sg:classifiers":[
        {
            "category":"Professional",
            "subcategory":"Business Services",
            "type":"Services"
        }
    ],
    "sg:phone":"+1 561 585 1725",
    "sg:postcode":"33405",
    "sg:province":"FL",
    "sg:tags":[
        "interior",
        "consultant",
        "design",
        "decorator"
    ],
    "wof:name":"J Robinson Design",
    "wof:placetype":"venue"
},
  "geometry": {"coordinates":[-80.051254,26.657649],"type":"Point"}
}