{
  "type": "Feature",
  "properties": {
    "iso:country":"US",
    "sg:address":"2000 63rd Ave E",
    "sg:city":"Bradenton",
    "sg:classifiers":[
        {
            "category":"Wholesale",
            "subcategory":"Auto Parts",
            "type":"Manufacturing & Wholesale Goods"
        }
    ],
    "sg:phone":"+1 941 758 1833",
    "sg:postcode":"34203",
    "sg:province":"FL",
    "sg:tags":[
        "automobile",
        "rebuilt",
        "used",
        "accessory"
    ],
    "sg:website":"http://www.royalfl.com",
    "wof:name":"Royal Auto Recycling",
    "wof:placetype":"venue"
},
  "geometry": {"coordinates":[-82.53939200000001,27.429169],"type":"Point"}
}