{
  "type": "Feature",
  "properties": {
    "iso:country":"US",
    "sg:address":"810 E Main St",
    "sg:city":"Lakeland",
    "sg:classifiers":[
        {
            "category":"Shopping",
            "type":"Retail Goods"
        }
    ],
    "sg:phone":"+1 863 682 2886",
    "sg:postcode":"33801",
    "sg:province":"FL",
    "sg:tags":[
        "equipment"
    ],
    "wof:name":"IKON Office Solutions",
    "wof:placetype":"venue"
},
  "geometry": {"coordinates":[-81.949985,28.044326],"type":"Point"}
}