{
  "type": "Feature",
  "properties": {
    "iso:country":"US",
    "sg:address":"1760 SW 7th Ave",
    "sg:city":"Pompano Beach",
    "sg:classifiers":[
        {
            "category":"Airport",
            "type":"Transportation"
        }
    ],
    "sg:phone":"+1 954 545 1327",
    "sg:postcode":"33060",
    "sg:province":"FL",
    "sg:tags":[
        "aircraft",
        "maintenance"
    ],
    "wof:name":"Safe Flight Inc",
    "wof:placetype":"venue"
},
  "geometry": {"coordinates":[-80.131288,26.209517],"type":"Point"}
}