{
  "type": "Feature",
  "properties": {
    "iso:country":"US",
    "sg:address":"5680 SW 87th Ave",
    "sg:city":"Miami",
    "sg:classifiers":[
        {
            "category":"Government",
            "subcategory":"Office",
            "type":"Public Place"
        }
    ],
    "sg:phone":"+1 305 596 8317",
    "sg:postcode":"33173",
    "sg:province":"FL",
    "sg:tags":[
        "sector",
        "regulation",
        "commercial"
    ],
    "wof:name":"Public Works Dept",
    "wof:placetype":"venue"
},
  "geometry": {"coordinates":[-80.334934,25.715649],"type":"Point"}
}