{
  "type": "Feature",
  "properties": {
    "addr:full":"7541 W Sand Lake Rd Orlando FL 32819",
    "addr:housenumber":"7541",
    "addr:postcode":"32819",
    "addr:street":"W Sand Lake Rd",
    "iso:country":"US",
    "sg:address":"7541 W Sand Lake Rd",
    "sg:city":"Orlando",
    "sg:classifiers":[
        {
            "category":"Personal",
            "subcategory":"Beauty Salon",
            "type":"Services"
        }
    ],
    "sg:phone":"+1 407 351 9300",
    "sg:postcode":"32819",
    "sg:province":"FL",
    "wof:name":"Fountains Salon",
    "wof:placetype":"venue"
},
  "geometry": {"coordinates":[-81.48792400000001,28.450026],"type":"Point"}
}