{
  "type": "Feature",
  "properties": {
    "iso:country":"US",
    "sg:address":"19140 NW 5th Ave",
    "sg:city":"Miami",
    "sg:classifiers":[
        {
            "category":"Building & Trades",
            "subcategory":"Locksmith",
            "type":"Services"
        }
    ],
    "sg:phone":"+1 786 629 7553",
    "sg:postcode":"33169",
    "sg:province":"FL",
    "sg:tags":[
        "key"
    ],
    "wof:name":"Locksmith AAA",
    "wof:placetype":"venue"
},
  "geometry": {"coordinates":[-80.209637,25.950055],"type":"Point"}
}