{
  "type": "Feature",
  "properties": {
    "iso:country":"US",
    "sg:address":"7902 NW 64th St",
    "sg:city":"Miami",
    "sg:classifiers":[
        {
            "category":"Building & Trades",
            "subcategory":"Construction",
            "type":"Services"
        }
    ],
    "sg:phone":"+1 305 468 0092",
    "sg:postcode":"33166",
    "sg:province":"FL",
    "sg:tags":[
        "industrial"
    ],
    "wof:name":"Joule Technical Services Inc",
    "wof:placetype":"venue"
},
  "geometry": {"coordinates":[-80.32508900000001,25.831586],"type":"Point"}
}