{
  "type": "Feature",
  "properties": {
    "addr:full":"631 Bedford Way Weston FL 33326",
    "addr:housenumber":"631",
    "addr:postcode":"33326",
    "addr:street":"Bedford Way",
    "iso:country":"US",
    "sg:address":"631 Bedford Way",
    "sg:city":"Weston",
    "sg:classifiers":[
        {
            "category":"Recreation",
            "subcategory":"Picnic Area",
            "type":"Entertainment"
        }
    ],
    "sg:phone":"+1 954 557 3331",
    "sg:postcode":"33326",
    "sg:province":"FL",
    "sg:tags":[
        "place",
        "arcade",
        "amusement"
    ],
    "wof:name":"Super Arcade Systems Inc",
    "wof:placetype":"venue"
},
  "geometry": {"coordinates":[-80.38746999999999,26.113682],"type":"Point"}
}