{
  "type": "Feature",
  "properties": {
    "addr:full":"9740 Sea Turtle Dr Fort Lauderdale FL 33324",
    "addr:housenumber":"9740",
    "addr:postcode":"33324",
    "addr:street":"Sea Turtle Dr",
    "iso:country":"US",
    "sg:address":"9740 Sea Turtle Dr",
    "sg:city":"Fort Lauderdale",
    "sg:classifiers":[
        {
            "category":"Building & Trades",
            "subcategory":"Construction",
            "type":"Services"
        }
    ],
    "sg:phone":"+1 954 236 3530",
    "sg:postcode":"33324",
    "sg:province":"FL",
    "sg:tags":[
        "hanging",
        "contractor"
    ],
    "wof:name":"Elite American Inc",
    "wof:placetype":"venue"
},
  "geometry": {"coordinates":[-80.27895700000001,26.11457],"type":"Point"}
}