{
  "type": "Feature",
  "properties": {
    "addr:full":"18181 NE 31st Ave Miami FL 33160",
    "addr:housenumber":"18181",
    "addr:postcode":"33160",
    "addr:street":"Ne 31St Ave",
    "iso:country":"US",
    "sg:address":"18181 NE 31st Ave",
    "sg:city":"Miami",
    "sg:classifiers":[
        {
            "category":"Real Estate",
            "subcategory":"Real Estate Agent",
            "type":"Services"
        }
    ],
    "sg:phone":"+1 305 937 2236",
    "sg:postcode":"33160",
    "sg:province":"FL",
    "wof:name":"Shoreline Realty & Investment",
    "wof:placetype":"venue"
},
  "geometry": {"coordinates":[-80.138513,25.945407],"type":"Point"}
}