{
  "type": "Feature",
  "properties": {
    "addr:full":"2131 Andrea Ln Fort Myers FL 33912",
    "addr:housenumber":"2131",
    "addr:postcode":"33912",
    "addr:street":"Andrea Ln",
    "iso:country":"US",
    "sg:address":"2131 Andrea Ln",
    "sg:city":"Fort Myers",
    "sg:classifiers":[
        {
            "category":"Manufacturing",
            "subcategory":"Chemicals & Compounds",
            "type":"Manufacturing & Wholesale Goods"
        }
    ],
    "sg:phone":"+1 239 489 2332",
    "sg:postcode":"33912",
    "sg:province":"FL",
    "sg:tags":[
        "paint",
        "varnish",
        "allied",
        "product"
    ],
    "wof:name":"Flex Bon Paints",
    "wof:placetype":"venue"
},
  "geometry": {"coordinates":[-81.863366,26.534473],"type":"Point"}
}