{
  "type": "Feature",
  "properties": {
    "iso:country":"US",
    "sg:address":"103 W Mahoney St",
    "sg:city":"Plant City",
    "sg:classifiers":[
        {
            "category":"Real Estate",
            "subcategory":"Real Estate Operator",
            "type":"Services"
        }
    ],
    "sg:phone":"+1 813 752 5116",
    "sg:postcode":"33563",
    "sg:province":"FL",
    "sg:tags":[
        "building",
        "apartment"
    ],
    "wof:name":"Plant City Towers",
    "wof:placetype":"venue"
},
  "geometry": {"coordinates":[-82.124009,28.017073],"type":"Point"}
}