{
  "type": "Feature",
  "properties": {
    "iso:country":"US",
    "sg:address":"13 Gulf Beach Hwy",
    "sg:city":"Pensacola",
    "sg:classifiers":[
        {
            "category":"Restaurant",
            "type":"Food & Drink"
        }
    ],
    "sg:menulink":"http://www.allmenus.com/fl/pensacola/189862-kfc---kentucky-fried-chicken/menu/",
    "sg:phone":"+1 850 455 0088",
    "sg:postcode":"32507",
    "sg:province":"FL",
    "sg:tags":[
        "american",
        "chicken"
    ],
    "wof:name":"KFC - Kentucky Fried Chicken",
    "wof:placetype":"venue"
},
  "geometry": {"coordinates":[-87.278486,30.387656],"type":"Point"}
}