{
  "type": "Feature",
  "properties": {
    "iso:country":"US",
    "sg:address":"2144 NE 4th Ave",
    "sg:city":"Boca Raton",
    "sg:classifiers":[
        {
            "category":"Professional",
            "subcategory":"Business Services",
            "type":"Services"
        }
    ],
    "sg:phone":"+1 561 889 2015",
    "sg:postcode":"33431",
    "sg:province":"FL",
    "sg:tags":[
        "pool",
        "swimming"
    ],
    "wof:name":"Pacific Master Pools Inc",
    "wof:placetype":"venue"
},
  "geometry": {"coordinates":[-80.08126799999999,26.368708],"type":"Point"}
}