{
  "type": "Feature",
  "properties": {
    "iso:country":"US",
    "sg:address":"22912 Ann Miller Rd",
    "sg:city":"Panama City Bch",
    "sg:classifiers":[
        {
            "category":"Organizations",
            "subcategory":"Membership Organization",
            "type":"Services"
        }
    ],
    "sg:phone":"+1 850 234 2839",
    "sg:postcode":"32413",
    "sg:province":"FL",
    "sg:tags":[
        "athletic"
    ],
    "wof:name":"U S Fastpitch Assn",
    "wof:placetype":"venue"
},
  "geometry": {"coordinates":[-85.971002,30.267749],"type":"Point"}
}