{
  "type": "Feature",
  "properties": {
    "iso:country":"US",
    "sg:address":"9400 S Military Trl",
    "sg:city":"Boynton Beach",
    "sg:classifiers":[
        {
            "category":"Recreation",
            "type":"Entertainment"
        }
    ],
    "sg:phone":"+1 561 732 4202",
    "sg:postcode":"33436",
    "sg:province":"FL",
    "sg:tags":[
        "club",
        "country",
        "membership"
    ],
    "wof:name":"Cypress Creek Country Club",
    "wof:placetype":"venue"
},
  "geometry": {"coordinates":[-80.122742,26.535735],"type":"Point"}
}