{
  "type": "Feature",
  "properties": {
    "iso:country":"US",
    "sg:address":"420 4th Ave",
    "sg:city":"Indialantic",
    "sg:classifiers":[
        {
            "category":"Banks & Credit Unions",
            "subcategory":"Investment Brokerage",
            "type":"Services"
        }
    ],
    "sg:phone":"+1 321 723 2159",
    "sg:postcode":"32903",
    "sg:province":"FL",
    "sg:tags":[
        "advisory",
        "financial"
    ],
    "wof:name":"Chell Financial",
    "wof:placetype":"venue"
},
  "geometry": {"coordinates":[-80.574945,28.090053],"type":"Point"}
}