{
  "type": "Feature",
  "properties": {
    "iso:country":"US",
    "sg:address":"6440 Foster St",
    "sg:city":"Jupiter",
    "sg:classifiers":[
        {
            "category":"Professional",
            "subcategory":"Management & Consulting",
            "type":"Services"
        }
    ],
    "sg:phone":"+1 561 747 3953",
    "sg:postcode":"33458",
    "sg:province":"FL",
    "sg:tags":[
        "consultant",
        "nursing"
    ],
    "wof:name":"Vector Legal Nurse Consulting",
    "wof:placetype":"venue"
},
  "geometry": {"coordinates":[-80.136876,26.902608],"type":"Point"}
}