{
  "type": "Feature",
  "properties": {
    "iso:country":"US",
    "sg:address":"361 Ansin Blvd",
    "sg:city":"Hallandale Beach",
    "sg:classifiers":[
        {
            "category":"Wholesale",
            "subcategory":"Home Furnishings",
            "type":"Manufacturing & Wholesale Goods"
        }
    ],
    "sg:phone":"+1 954 458 6410",
    "sg:postcode":"33009",
    "sg:province":"FL",
    "sg:tags":[
        "equipment",
        "fireplace"
    ],
    "wof:name":"C Breines Enterprises Inc",
    "wof:placetype":"venue"
},
  "geometry": {"coordinates":[-80.16506,25.994251],"type":"Point"}
}