{
  "type": "Feature",
  "properties": {
    "iso:country":"US",
    "sg:address":"3009 Cypress Gardens Rd",
    "sg:city":"Winter Haven",
    "sg:classifiers":[
        {
            "category":"Restaurant",
            "type":"Food & Drink"
        }
    ],
    "sg:phone":"+1 863 318 8877",
    "sg:postcode":"33884",
    "sg:province":"FL",
    "sg:tags":[
        "eating"
    ],
    "sg:website":"www.sayamencafe.com",
    "wof:name":"Soul Sisters Coffee",
    "wof:placetype":"venue"
},
  "geometry": {"coordinates":[-81.685739,27.996856],"type":"Point"}
}