{
  "type": "Feature",
  "properties": {
    "iso:country":"US",
    "sg:address":"219 Edgewood Ave S",
    "sg:city":"Jacksonville",
    "sg:classifiers":[
        {
            "category":"Wholesale",
            "subcategory":"Hardware",
            "type":"Manufacturing & Wholesale Goods"
        }
    ],
    "sg:phone":"+1 904 387 0911",
    "sg:postcode":"32254",
    "sg:province":"FL",
    "sg:tags":[
        "nut",
        "bolt"
    ],
    "wof:name":"Reliance Fasteners",
    "wof:placetype":"venue"
},
  "geometry": {"coordinates":[-81.730249,30.324189],"type":"Point"}
}