{
  "type": "Feature",
  "properties": {
    "iso:country":"US",
    "sg:address":"402 N Reo St",
    "sg:city":"Tampa",
    "sg:classifiers":[
        {
            "category":"Freight",
            "type":"Transportation"
        }
    ],
    "sg:phone":"+1 813 637 8000",
    "sg:postcode":"33609",
    "sg:province":"FL",
    "sg:tags":[
        "broker",
        "trucking"
    ],
    "wof:name":"Genesis 680 AM",
    "wof:placetype":"venue"
},
  "geometry": {"coordinates":[-82.53662,27.946921],"type":"Point"}
}