{
  "type": "Feature",
  "properties": {
    "addr:full":"1453 Sunset Point Rd Clearwater FL 33755",
    "addr:housenumber":"1453",
    "addr:postcode":"33755",
    "addr:street":"Sunset Point Rd",
    "iso:country":"US",
    "sg:address":"1453 Sunset Point Rd",
    "sg:city":"Clearwater",
    "sg:classifiers":[
        {
            "category":"Retail",
            "subcategory":"Veterinary Services",
            "type":"Services"
        }
    ],
    "sg:phone":"+1 727 442 9111",
    "sg:postcode":"33755",
    "sg:province":"FL",
    "sg:tags":[
        "hospital",
        "animal"
    ],
    "wof:name":"All Pet Care Hospital",
    "wof:placetype":"venue"
},
  "geometry": {"coordinates":[-82.778654,27.989947],"type":"Point"}
}