{
  "type": "Feature",
  "properties": {
    "addr:full":"8241 Bird Rd Miami FL 33155",
    "addr:housenumber":"8241",
    "addr:postcode":"33155",
    "addr:street":"Bird Rd",
    "iso:country":"US",
    "sg:address":"8241 Bird Rd",
    "sg:city":"Miami",
    "sg:classifiers":[
        {
            "category":"Food & Beverages",
            "subcategory":"Groceries & Convenience Stores",
            "type":"Retail Goods"
        }
    ],
    "sg:phone":"+1 305 552 0991",
    "sg:postcode":"33155",
    "sg:province":"FL",
    "wof:name":"AA Tabaco Y Vinos Inc",
    "wof:placetype":"venue"
},
  "geometry": {"coordinates":[-80.32826,25.733504],"type":"Point"}
}