{
  "type": "Feature",
  "properties": {
    "iso:country":"US",
    "sg:address":"11532 Tamiami Trl",
    "sg:city":"Naples",
    "sg:classifiers":[
        {
            "category":"Real Estate",
            "subcategory":"Real Estate Agent",
            "type":"Services"
        }
    ],
    "sg:phone":"+1 239 417 4242",
    "sg:postcode":"34113",
    "sg:province":"FL",
    "wof:name":"Verona Realty",
    "wof:placetype":"venue"
},
  "geometry": {"coordinates":[-81.719357,26.076053],"type":"Point"}
}