{
  "type": "Feature",
  "properties": {
    "addr:full":"2639 Lee St Hollywood FL 33020",
    "addr:housenumber":"2639",
    "addr:postcode":"33020",
    "addr:street":"Lee St",
    "iso:country":"US",
    "sg:address":"2639 Lee St",
    "sg:city":"Hollywood",
    "sg:classifiers":[
        {
            "category":"Professional",
            "subcategory":"Computer Services",
            "type":"Services"
        }
    ],
    "sg:phone":"+1 954 925 7122",
    "sg:postcode":"33020",
    "sg:province":"FL",
    "wof:name":"Micro Tech",
    "wof:placetype":"venue"
},
  "geometry": {"coordinates":[-80.16094,26.030596],"type":"Point"}
}