{
  "type": "Feature",
  "properties": {
    "iso:country":"US",
    "sg:address":"1487 S Fairfield Dr",
    "sg:city":"Pensacola",
    "sg:classifiers":[
        {
            "category":"Wholesale",
            "subcategory":"Non-durable Goods",
            "type":"Manufacturing & Wholesale Goods"
        }
    ],
    "sg:phone":"+1 850 458 6001",
    "sg:postcode":"32507",
    "sg:province":"FL",
    "wof:name":"Panhandle Imports",
    "wof:placetype":"venue"
},
  "geometry": {"coordinates":[-87.307771,30.387708],"type":"Point"}
}