{
  "type": "Feature",
  "properties": {
    "addr:full":"1177 NW 81st St Miami FL 33150",
    "addr:housenumber":"1177",
    "addr:postcode":"33150",
    "addr:street":"Nw 81St St",
    "iso:country":"US",
    "sg:address":"1177 NW 81st St",
    "sg:city":"Miami",
    "sg:classifiers":[
        {
            "category":"Wholesale",
            "subcategory":"Meat",
            "type":"Manufacturing & Wholesale Goods"
        }
    ],
    "sg:phone":"+1 305 696 6887",
    "sg:postcode":"33150",
    "sg:province":"FL",
    "sg:tags":[
        "sausage"
    ],
    "wof:name":"Prima Sausage Co",
    "wof:placetype":"venue"
},
  "geometry": {"coordinates":[-80.216571,25.848748],"type":"Point"}
}