{
  "type": "Feature",
  "properties": {
    "addr:full":"5604 Old Cheney Hwy Orlando FL 32807",
    "addr:housenumber":"5604",
    "addr:postcode":"32807",
    "addr:street":"Old Cheney Hwy",
    "iso:country":"US",
    "sg:address":"5604 Old Cheney Hwy",
    "sg:city":"Orlando",
    "sg:classifiers":[
        {
            "category":"Food & Beverages",
            "subcategory":"Groceries & Convenience Stores",
            "type":"Retail Goods"
        }
    ],
    "sg:phone":"+1 407 273 9150",
    "sg:postcode":"32807",
    "sg:province":"FL",
    "sg:tags":[
        "station",
        "gasoline"
    ],
    "wof:name":"Circle K Store",
    "wof:placetype":"venue"
},
  "geometry": {"coordinates":[-81.31089,28.561497],"type":"Point"}
}