{
  "type": "Feature",
  "properties": {
    "addr:full":"100 Thornhill Rd Auburndale FL 33823",
    "addr:housenumber":"100",
    "addr:postcode":"33823",
    "addr:street":"Thornhill Rd",
    "iso:country":"US",
    "sg:address":"100 Thornhill Rd",
    "sg:city":"Auburndale",
    "sg:classifiers":[
        {
            "category":"Manufacturing",
            "subcategory":"Tools & Machinery",
            "type":"Manufacturing & Wholesale Goods"
        }
    ],
    "sg:phone":"+1 863 967 4191",
    "sg:postcode":"33823",
    "sg:province":"FL",
    "sg:tags":[
        "farm",
        "mfg",
        "rental",
        "trailer",
        "utility"
    ],
    "wof:name":"Agrifleet Leasing Corporation",
    "wof:placetype":"venue"
},
  "geometry": {"coordinates":[-81.813165,28.053075],"type":"Point"}
}