{
  "type": "Feature",
  "properties": {
    "iso:country":"US",
    "sg:address":"111 S Albany Ave",
    "sg:city":"Tampa",
    "sg:classifiers":[
        {
            "category":"Real Estate",
            "subcategory":"Real Estate Agent",
            "type":"Services"
        }
    ],
    "sg:phone":"+1 813 258 6555",
    "sg:postcode":"33606",
    "sg:province":"FL",
    "sg:tags":[
        "appraiser"
    ],
    "wof:name":"Hanlon Appraisal Svc",
    "wof:placetype":"venue"
},
  "geometry": {"coordinates":[-82.480993,27.943463],"type":"Point"}
}