{
  "type": "Feature",
  "properties": {
    "iso:country":"US",
    "sg:address":"1365 Hamlet Ave",
    "sg:city":"Clearwater",
    "sg:classifiers":[
        {
            "category":"Professional",
            "subcategory":"Engineering",
            "type":"Services"
        }
    ],
    "sg:phone":"+1 727 442 7196",
    "sg:postcode":"33756",
    "sg:province":"FL",
    "sg:tags":[
        "engineer"
    ],
    "sg:website":"www.mckimcreed.com",
    "wof:name":"Mc Kim & Creed",
    "wof:placetype":"venue"
},
  "geometry": {"coordinates":[-82.798458,27.946691],"type":"Point"}
}