{
  "type": "Feature",
  "properties": {
    "addr:full":"1321 NW 14th Ave Miami FL 33125",
    "addr:housenumber":"1321",
    "addr:postcode":"33125",
    "addr:street":"Nw 14Th Ave",
    "iso:country":"US",
    "sg:address":"1321 NW 14th Ave",
    "sg:city":"Miami",
    "sg:classifiers":[
        {
            "category":"Health Services",
            "subcategory":"Doctor",
            "type":"Services"
        }
    ],
    "sg:phone":"+1 305 549 6060",
    "sg:postcode":"33125",
    "sg:province":"FL",
    "sg:tags":[
        "physician",
        "surgeon"
    ],
    "wof:name":"Associated Medical Managers",
    "wof:placetype":"venue"
},
  "geometry": {"coordinates":[-80.21879800000001,25.786289],"type":"Point"}
}