{
  "type": "Feature",
  "properties": {
    "iso:country":"US",
    "sg:address":"3901 Oakwood Blvd",
    "sg:city":"Hollywood",
    "sg:classifiers":[
        {
            "category":"Shopping",
            "subcategory":"Clothing, Apparel, & Fashions",
            "type":"Retail Goods"
        },
        {
            "category":"Shopping",
            "subcategory":"Party Supplies",
            "type":"Retail Goods"
        }
    ],
    "sg:phone":"+1 954 927 0700",
    "sg:postcode":"33020",
    "sg:province":"FL",
    "sg:tags":[
        "delivery",
        "favors",
        "decoration",
        "balloons-retail",
        "costume"
    ],
    "sg:website":"http://www.partycity.com",
    "wof:name":"Party City",
    "wof:placetype":"venue"
},
  "geometry": {"coordinates":[-80.161022,26.043268],"type":"Point"}
}