{
  "type": "Feature",
  "properties": {
    "addr:full":"2311 Thonotosassa Rd Plant City FL 33563",
    "addr:housenumber":"2311",
    "addr:postcode":"33563",
    "addr:street":"Thonotosassa Rd",
    "iso:country":"US",
    "sg:address":"2311 Thonotosassa Rd",
    "sg:city":"Plant City",
    "sg:classifiers":[
        {
            "category":"Shopping",
            "subcategory":"Bicycles & Sporting Goods",
            "type":"Retail Goods"
        }
    ],
    "sg:phone":"+1 813 754 4867",
    "sg:postcode":"33563",
    "sg:province":"FL",
    "sg:tags":[
        "gun",
        "gunsmith"
    ],
    "wof:name":"Freedom Outfitters",
    "wof:placetype":"venue"
},
  "geometry": {"coordinates":[-82.14646399999999,28.023209],"type":"Point"}
}