{
  "type": "Feature",
  "properties": {
    "iso:country":"US",
    "sg:address":"4300 Alton Rd",
    "sg:city":"Miami",
    "sg:classifiers":[
        {
            "category":"Health Services",
            "subcategory":"Doctor",
            "type":"Services"
        }
    ],
    "sg:phone":"+1 305 673 9444",
    "sg:postcode":"33140",
    "sg:province":"FL",
    "sg:tags":[
        "physician",
        "surgeon"
    ],
    "wof:name":"Elizabeth Etkin-Kramer MD",
    "wof:placetype":"venue"
},
  "geometry": {"coordinates":[-80.13758799999999,25.815531],"type":"Point"}
}