{
  "type": "Feature",
  "properties": {
    "addr:full":"61 NE 43rd St Miami FL 33137",
    "addr:housenumber":"61",
    "addr:postcode":"33137",
    "addr:street":"Ne 43Rd St",
    "iso:country":"US",
    "sg:address":"61 NE 43rd St",
    "sg:city":"Miami",
    "sg:classifiers":[
        {
            "category":"Retail",
            "subcategory":"Repair Shop",
            "type":"Services"
        }
    ],
    "sg:phone":"+1 305 636 3993",
    "sg:postcode":"33137",
    "sg:province":"FL",
    "sg:tags":[
        "electrical"
    ],
    "wof:name":"Best Appliances",
    "wof:placetype":"venue"
},
  "geometry": {"coordinates":[-80.19461800000001,25.815598],"type":"Point"}
}