{
  "type": "Feature",
  "properties": {
    "addr:full":"715 Broome St Lake City FL 32034",
    "addr:housenumber":"715",
    "addr:postcode":"32034",
    "addr:street":"Broome St",
    "iso:country":"US",
    "sg:address":"715 Broome St",
    "sg:city":"Lake City",
    "sg:classifiers":[
        {
            "category":"Manufacturing",
            "subcategory":"Tools & Machinery",
            "type":"Manufacturing & Wholesale Goods"
        }
    ],
    "sg:phone":"+1 386 755 4790",
    "sg:postcode":"32034",
    "sg:province":"FL",
    "sg:tags":[
        "machine",
        "mfg"
    ],
    "wof:name":"Tracy Buck Technical Services",
    "wof:placetype":"venue"
},
  "geometry": {"coordinates":[-81.459129,30.673431],"type":"Point"}
}