{
  "type": "Feature",
  "properties": {
    "addr:full":"3501 W San Jose St Tampa FL 33629",
    "addr:housenumber":"3501",
    "addr:postcode":"33629",
    "addr:street":"W San Jose St",
    "iso:country":"US",
    "sg:address":"3501 W San Jose St",
    "sg:city":"Tampa",
    "sg:classifiers":[
        {
            "category":"Organizations",
            "subcategory":"Religious Organization",
            "type":"Services"
        }
    ],
    "sg:phone":"+1 813 253 6049",
    "sg:postcode":"33629",
    "sg:province":"FL",
    "wof:name":"Palma Ceia Presbyterian Church",
    "wof:placetype":"venue"
},
  "geometry": {"coordinates":[-82.50183,27.923202],"type":"Point"}
}