{
  "type": "Feature",
  "properties": {
    "addr:full":"243 SW 8th St Miami FL 33130",
    "addr:housenumber":"243",
    "addr:postcode":"33130",
    "addr:street":"Sw 8Th St",
    "iso:country":"US",
    "sg:address":"243 SW 8th St",
    "sg:city":"Miami",
    "sg:classifiers":[
        {
            "category":"Health Services",
            "subcategory":"Dentist",
            "type":"Services"
        }
    ],
    "sg:phone":"+1 305 854 7373",
    "sg:postcode":"33130",
    "sg:province":"FL",
    "wof:name":"South Dental At Brickell Spa Inc",
    "wof:placetype":"venue"
},
  "geometry": {"coordinates":[-80.19812400000001,25.766414],"type":"Point"}
}