{
  "type": "Feature",
  "properties": {
    "iso:country":"US",
    "sg:address":"18328 Treehaven Dr",
    "sg:city":"Hudson",
    "sg:classifiers":[
        {
            "category":"Building & Trades",
            "subcategory":"Construction",
            "type":"Services"
        }
    ],
    "sg:phone":"+1 727 819 2181",
    "sg:postcode":"34667",
    "sg:province":"FL",
    "sg:tags":[
        "home",
        "builder"
    ],
    "wof:name":"VRJ Building Contractors Inc",
    "wof:placetype":"venue"
},
  "geometry": {"coordinates":[-82.602592,28.425106],"type":"Point"}
}