{
  "type": "Feature",
  "properties": {
    "addr:full":"4584 Tamarind Dr Milton FL 32571",
    "addr:housenumber":"4584",
    "addr:postcode":"32571",
    "addr:street":"Tamarind Dr",
    "iso:country":"US",
    "sg:address":"4584 Tamarind Dr",
    "sg:city":"Milton",
    "sg:classifiers":[
        {
            "category":"Building & Trades",
            "subcategory":"Construction",
            "type":"Services"
        }
    ],
    "sg:phone":"+1 850 994 3139",
    "sg:postcode":"32571",
    "sg:province":"FL",
    "sg:tags":[
        "heavy"
    ],
    "wof:name":"FDS Construction Inc",
    "wof:placetype":"venue"
},
  "geometry": {"coordinates":[-87.101077,30.602581],"type":"Point"}
}