{
  "type": "Feature",
  "properties": {
    "iso:country":"US",
    "sg:address":"750 4th St N",
    "sg:city":"Saint Petersburg",
    "sg:classifiers":[
        {
            "category":"Restaurant",
            "type":"Food & Drink"
        }
    ],
    "sg:menulink":"http://www.allmenus.com/fl/st-petersburg/15781-weekday-gourmet/menu/",
    "sg:phone":"+1 727 388 9365",
    "sg:postcode":"33701",
    "sg:province":"FL",
    "sg:tags":[
        "american"
    ],
    "wof:name":"WeekDay Gourmet",
    "wof:placetype":"venue"
},
  "geometry": {"coordinates":[-82.63855,27.779976],"type":"Point"}
}