{
  "type": "Feature",
  "properties": {
    "iso:country":"US",
    "sg:address":"3233 Commercial Way",
    "sg:city":"Spring Hill",
    "sg:classifiers":[
        {
            "category":"Utilities",
            "subcategory":"Telephone",
            "type":"Services"
        }
    ],
    "sg:phone":"+1 352 688 7202",
    "sg:postcode":"34606",
    "sg:province":"FL",
    "sg:tags":[
        "distance",
        "long"
    ],
    "wof:name":"Skynet Telesystems",
    "wof:placetype":"venue"
},
  "geometry": {"coordinates":[-82.611647,28.478011],"type":"Point"}
}