{
  "type": "Feature",
  "properties": {
    "iso:country":"US",
    "sg:address":"1890 Lpga Blvd",
    "sg:city":"Daytona Beach",
    "sg:classifiers":[
        {
            "category":"Health Services",
            "subcategory":"Doctor",
            "type":"Services"
        }
    ],
    "sg:phone":"+1 386 672 3320",
    "sg:postcode":"32117",
    "sg:province":"FL",
    "sg:tags":[
        "physician",
        "surgeon"
    ],
    "wof:name":"Halifax Ob Gyn",
    "wof:placetype":"venue"
},
  "geometry": {"coordinates":[-81.07604600000001,29.231527],"type":"Point"}
}