{
  "type": "Feature",
  "properties": {
    "iso:country":"US",
    "sg:address":"22401 SW 184th Ave",
    "sg:city":"Miami",
    "sg:classifiers":[
        {
            "category":"Shopping",
            "subcategory":"Stationery & Office Supplies",
            "type":"Retail Goods"
        }
    ],
    "sg:phone":"+1 305 247 9700",
    "sg:postcode":"33170",
    "sg:province":"FL",
    "sg:tags":[
        "machine",
        "copy",
        "envelope",
        "store"
    ],
    "wof:name":"Copy Machine Specialists Inc",
    "wof:placetype":"venue"
},
  "geometry": {"coordinates":[-80.490334,25.55764],"type":"Point"}
}