{
  "type": "Feature",
  "properties": {
    "iso:country":"US",
    "sg:address":"530 SW 24th Rd",
    "sg:city":"Miami",
    "sg:classifiers":[
        {
            "category":"Health Services",
            "subcategory":"Health Practitioner",
            "type":"Services"
        }
    ],
    "sg:phone":"+1 305 285 7704",
    "sg:postcode":"33129",
    "sg:province":"FL",
    "sg:tags":[
        "nurse",
        "registry"
    ],
    "wof:name":"Specialty Professional Svc",
    "wof:placetype":"venue"
},
  "geometry": {"coordinates":[-80.209433,25.760033],"type":"Point"}
}