{
  "type": "Feature",
  "properties": {
    "iso:country":"US",
    "sg:address":"160 NW 24th St",
    "sg:city":"Boca Raton",
    "sg:classifiers":[
        {
            "category":"Retail",
            "subcategory":"Auto Repair",
            "type":"Services"
        }
    ],
    "sg:phone":"+1 561 750 6518",
    "sg:postcode":"33431",
    "sg:province":"FL",
    "sg:tags":[
        "general"
    ],
    "wof:name":"A & H Automotive",
    "wof:placetype":"venue"
},
  "geometry": {"coordinates":[-80.088049,26.372035],"type":"Point"}
}