{
  "type": "Feature",
  "properties": {
    "iso:country":"US",
    "sg:address":"11869 Hidden Hills Dr",
    "sg:city":"Jacksonville",
    "sg:classifiers":[
        {
            "category":"Community Center",
            "subcategory":"Senior",
            "type":"Public Place"
        }
    ],
    "sg:phone":"+1 904 642 1826",
    "sg:postcode":"32225",
    "sg:province":"FL",
    "sg:tags":[
        "citizen"
    ],
    "wof:name":"Classic Keepers",
    "wof:placetype":"venue"
},
  "geometry": {"coordinates":[-81.51073599999999,30.376226],"type":"Point"}
}