{
  "type": "Feature",
  "properties": {
    "iso:country":"US",
    "sg:address":"1777 Tamiami Trl",
    "sg:city":"Port Charlotte",
    "sg:classifiers":[
        {
            "category":"Professional",
            "subcategory":"Management & Consulting",
            "type":"Services"
        },
        {
            "category":"Social Services",
            "type":"Services"
        }
    ],
    "sg:phone":"+1 941 764 7111",
    "sg:postcode":"33948",
    "sg:province":"FL",
    "sg:tags":[
        "counselor",
        "marriage",
        "family"
    ],
    "wof:name":"Crossway Counseling & Learning",
    "wof:placetype":"venue"
},
  "geometry": {"coordinates":[-82.13638899999999,27.008276],"type":"Point"}
}