{
  "type": "Feature",
  "properties": {
    "iso:country":"US",
    "sg:address":"5171 Adams Rd",
    "sg:city":"Delray Beach",
    "sg:classifiers":[
        {
            "category":"Professional",
            "type":"Services"
        }
    ],
    "sg:phone":"+1 561 498 4930",
    "sg:postcode":"33484",
    "sg:province":"FL",
    "wof:name":"Lapaglia Studios",
    "wof:placetype":"venue"
},
  "geometry": {"coordinates":[-80.125472,26.453406],"type":"Point"}
}