{
  "type": "Feature",
  "properties": {
    "iso:country":"US",
    "sg:address":"1650 Sand Lake Rd",
    "sg:city":"Orlando",
    "sg:classifiers":[
        {
            "category":"Professional",
            "subcategory":"Employment Agencies",
            "type":"Services"
        }
    ],
    "sg:phone":"+1 407 240 0780",
    "sg:postcode":"32809",
    "sg:province":"FL",
    "sg:tags":[
        "contractor"
    ],
    "wof:name":"Hospitality Staffing Solutions",
    "wof:placetype":"venue"
},
  "geometry": {"coordinates":[-81.400229,28.450177],"type":"Point"}
}