{
  "type": "Feature",
  "properties": {
    "iso:country":"US",
    "sg:address":"8812 Moore Rd",
    "sg:city":"Lakeland",
    "sg:classifiers":[
        {
            "category":"Building & Trades",
            "subcategory":"Construction",
            "type":"Services"
        }
    ],
    "sg:phone":"+1 863 859 2359",
    "sg:postcode":"33809",
    "sg:province":"FL",
    "sg:tags":[
        "industrial"
    ],
    "wof:name":"Biometric Science",
    "wof:placetype":"venue"
},
  "geometry": {"coordinates":[-81.922161,28.160865],"type":"Point"}
}