{
  "type": "Feature",
  "properties": {
    "iso:country":"US",
    "sg:address":"5430 Proctor Rd",
    "sg:city":"Sarasota",
    "sg:classifiers":[
        {
            "category":"Wholesale",
            "subcategory":"Fruits & Vegetables",
            "type":"Manufacturing & Wholesale Goods"
        }
    ],
    "sg:phone":"+1 941 922 3456",
    "sg:postcode":"34233",
    "sg:province":"FL",
    "wof:name":"Stars & Stripes Fireworks",
    "wof:placetype":"venue"
},
  "geometry": {"coordinates":[-82.464551,27.284015],"type":"Point"}
}