{
  "type": "Feature",
  "properties": {
    "iso:country":"US",
    "sg:address":"306 Larkwood Dr",
    "sg:city":"Sanford",
    "sg:classifiers":[
        {
            "category":"Building & Trades",
            "subcategory":"Construction",
            "type":"Services"
        }
    ],
    "sg:phone":"+1 407 620 6517",
    "sg:postcode":"32771",
    "sg:province":"FL",
    "sg:tags":[
        "wallcoverings-installation",
        "wallpaper",
        "painting",
        "contractor"
    ],
    "sg:website":"http://www.ataol.com",
    "wof:name":"Landress Painting",
    "wof:placetype":"venue"
},
  "geometry": {"coordinates":[-81.314998,28.789698],"type":"Point"}
}