{
  "type": "Feature",
  "properties": {
    "iso:country":"US",
    "sg:address":"12101 SW 93rd Ave",
    "sg:city":"Miami",
    "sg:classifiers":[
        {
            "category":"Health Services",
            "subcategory":"Optometrist",
            "type":"Services"
        }
    ],
    "sg:phone":"+1 305 253 6994",
    "sg:postcode":"33176",
    "sg:province":"FL",
    "wof:name":"Askowitz Gerald N Dr Optmtrst",
    "wof:placetype":"venue"
},
  "geometry": {"coordinates":[-80.34459699999999,25.6572],"type":"Point"}
}