{
  "type": "Feature",
  "properties": {
    "iso:country":"US",
    "sg:address":"15707 Fairchild Dr",
    "sg:city":"Clearwater",
    "sg:classifiers":[
        {
            "category":"Airline",
            "type":"Transportation"
        }
    ],
    "sg:phone":"+1 727 539 7300",
    "sg:postcode":"33762",
    "sg:province":"FL",
    "sg:tags":[
        "aircraft-charter",
        "leasing",
        "rental"
    ],
    "wof:name":"Mr Exitement",
    "wof:placetype":"venue"
},
  "geometry": {"coordinates":[-82.69613099999999,27.916303],"type":"Point"}
}