{
  "type": "Feature",
  "properties": {
    "iso:country":"US",
    "sg:address":"3399 NW 72nd Ave",
    "sg:city":"Miami",
    "sg:classifiers":[
        {
            "category":"Insurance",
            "subcategory":"Insurance Agent",
            "type":"Services"
        }
    ],
    "sg:phone":"+1 305 470 0101",
    "sg:postcode":"33122",
    "sg:province":"FL",
    "wof:name":"Mutual General Insurance Group",
    "wof:placetype":"venue"
},
  "geometry": {"coordinates":[-80.31311100000001,25.804059],"type":"Point"}
}