{
  "type": "Feature",
  "properties": {
    "addr:full":"1354 Wigmore St Jacksonville FL 32206",
    "addr:housenumber":"1354",
    "addr:postcode":"32206",
    "addr:street":"Wigmore St",
    "iso:country":"US",
    "sg:address":"1354 Wigmore St",
    "sg:city":"Jacksonville",
    "sg:classifiers":[
        {
            "category":"Manufacturing",
            "subcategory":"Tools & Machinery",
            "type":"Manufacturing & Wholesale Goods"
        }
    ],
    "sg:phone":"+1 904 355 8114",
    "sg:postcode":"32206",
    "sg:province":"FL",
    "sg:tags":[
        "industrial",
        "mfg",
        "overhead",
        "traveling",
        "hoist",
        "crane"
    ],
    "wof:name":"Venco Manufacturing Inc",
    "wof:placetype":"venue"
},
  "geometry": {"coordinates":[-81.637068,30.367739],"type":"Point"}
}