{
  "type": "Feature",
  "properties": {
    "addr:full":"2302 SE Hawthorne Rd Gainesville FL 32641",
    "addr:housenumber":"2302",
    "addr:postcode":"32641",
    "addr:street":"Se Hawthorne Rd",
    "iso:country":"US",
    "sg:address":"2302 SE Hawthorne Rd",
    "sg:city":"Gainesville",
    "sg:classifiers":[
        {
            "category":"Shopping",
            "subcategory":"Florist",
            "type":"Retail Goods"
        },
        {
            "category":"Bakery",
            "type":"Food & Drink"
        },
        {
            "category":"Food & Beverages",
            "subcategory":"Supermarket",
            "type":"Retail Goods"
        },
        {
            "category":"Shopping",
            "subcategory":"Pharmacy",
            "type":"Retail Goods"
        },
        {
            "category":"Food & Beverages",
            "subcategory":"Groceries & Convenience Stores",
            "type":"Retail Goods"
        }
    ],
    "sg:phone":"+1 352 372 6106",
    "sg:postcode":"32641",
    "sg:province":"FL",
    "sg:tags":[
        "super"
    ],
    "sg:website":"http://www.foodlion.com/",
    "wof:name":"Food Lion",
    "wof:placetype":"venue"
},
  "geometry": {"coordinates":[-82.255394,29.614989],"type":"Point"}
}