{
  "type": "Feature",
  "properties": {
    "iso:country":"US",
    "sg:address":"7061 W Commercial Blvd Ste 5K",
    "sg:city":"Lauderhill",
    "sg:classifiers":[
        {
            "category":"Personal",
            "type":"Services"
        }
    ],
    "sg:phone":"+1 954 572 5444",
    "sg:postcode":"33319",
    "sg:province":"FL",
    "sg:tags":[
        "mover",
        "full",
        "storage"
    ],
    "wof:name":"Jet Movers",
    "wof:placetype":"venue"
},
  "geometry": {"coordinates":[-80.24482999999999,26.193878],"type":"Point"}
}