{
  "type": "Feature",
  "properties": {
    "iso:country":"US",
    "sg:address":"3190 Gardner Oaks Ln",
    "sg:city":"Lakeland",
    "sg:classifiers":[
        {
            "category":"Real Estate",
            "subcategory":"Real Estate Operator",
            "type":"Services"
        }
    ],
    "sg:phone":"+1 863 859 9798",
    "sg:postcode":"33810",
    "sg:province":"FL",
    "sg:tags":[
        "building",
        "nonresidential"
    ],
    "wof:name":"Gardnr Oaks Prop Ownrs Assoc",
    "wof:placetype":"venue"
},
  "geometry": {"coordinates":[-82.01638199999999,28.080441],"type":"Point"}
}