{
  "type": "Feature",
  "properties": {
    "iso:country":"US",
    "sg:address":"6647 Dolphin Cove Dr",
    "sg:city":"Apollo Beach",
    "sg:classifiers":[
        {
            "category":"Recreation",
            "subcategory":"Marina",
            "type":"Entertainment"
        }
    ],
    "sg:phone":"+1 813 956 4707",
    "sg:postcode":"33572",
    "sg:province":"FL",
    "sg:tags":[
        "repairing",
        "boat"
    ],
    "wof:name":"Tom's Marine",
    "wof:placetype":"venue"
},
  "geometry": {"coordinates":[-82.418386,27.780403],"type":"Point"}
}