{
  "type": "Feature",
  "properties": {
    "addr:full":"10423 SW 146th Ter Miami FL 33176",
    "addr:housenumber":"10423",
    "addr:postcode":"33176",
    "addr:street":"Sw 146Th Ter",
    "iso:country":"US",
    "sg:address":"10423 SW 146th Ter",
    "sg:city":"Miami",
    "sg:classifiers":[
        {
            "category":"Building & Trades",
            "subcategory":"Landscaping Services",
            "type":"Services"
        }
    ],
    "sg:phone":"+1 305 710 4613",
    "sg:postcode":"33176",
    "sg:province":"FL",
    "wof:name":"Sheldon Wynn Lawn Services",
    "wof:placetype":"venue"
},
  "geometry": {"coordinates":[-80.36299099999999,25.633425],"type":"Point"}
}