{
  "type": "Feature",
  "properties": {
    "iso:country":"US",
    "sg:address":"547 N Ridgewood Ave",
    "sg:city":"Daytona Beach",
    "sg:classifiers":[
        {
            "category":"Insurance",
            "subcategory":"Insurance Agent",
            "type":"Services"
        }
    ],
    "sg:phone":"+1 386 257 6686",
    "sg:postcode":"32114",
    "sg:province":"FL",
    "wof:name":"Singleton Insurance",
    "wof:placetype":"venue"
},
  "geometry": {"coordinates":[-81.027828,29.220256],"type":"Point"}
}