{
  "type": "Feature",
  "properties": {
    "iso:country":"US",
    "sg:address":"1945 SW 7th St",
    "sg:city":"Miami",
    "sg:classifiers":[
        {
            "category":"Shopping",
            "subcategory":"Party Supplies",
            "type":"Retail Goods"
        }
    ],
    "sg:phone":"+1 305 803 8208",
    "sg:postcode":"33135",
    "sg:province":"FL",
    "sg:tags":[
        "favors"
    ],
    "wof:name":"Chupeton Tin Ton Party Rentals",
    "wof:placetype":"venue"
},
  "geometry": {"coordinates":[-80.227163,25.766417],"type":"Point"}
}