{
  "type": "Feature",
  "properties": {
    "iso:country":"US",
    "sg:address":"16002 Lakeshore Villa Dr",
    "sg:city":"Tampa",
    "sg:classifiers":[
        {
            "category":"Health Services",
            "subcategory":"Clinic",
            "type":"Services"
        }
    ],
    "sg:phone":"+1 813 960 8153",
    "sg:postcode":"33613",
    "sg:province":"FL",
    "sg:tags":[
        "wellness",
        "program"
    ],
    "wof:name":"Lakeshore Villas Health Svc",
    "wof:placetype":"venue"
},
  "geometry": {"coordinates":[-82.454932,28.094612],"type":"Point"}
}