{
  "type": "Feature",
  "properties": {
    "addr:full":"17286 SE Galway Ct Jupiter FL 33469",
    "addr:housenumber":"17286",
    "addr:postcode":"33469",
    "addr:street":"Se Galway Ct",
    "iso:country":"US",
    "sg:address":"17286 SE Galway Ct",
    "sg:city":"Jupiter",
    "sg:classifiers":[
        {
            "category":"Arts & Performance",
            "subcategory":"Theater",
            "type":"Entertainment"
        }
    ],
    "sg:phone":"+1 561 575 4151",
    "sg:postcode":"33469",
    "sg:province":"FL",
    "sg:tags":[
        "entertainer"
    ],
    "wof:name":"Smileawhile Inc",
    "wof:placetype":"venue"
},
  "geometry": {"coordinates":[-80.095888,26.99495],"type":"Point"}
}