{
  "type": "Feature",
  "properties": {
    "iso:country":"US",
    "sg:address":"7975 NW 154th St Ste 340",
    "sg:city":"Hialeah",
    "sg:classifiers":[
        {
            "category":"Professional",
            "subcategory":"Lawyer & Legal Services",
            "type":"Services"
        }
    ],
    "sg:phone":"+1 305 828 6800",
    "sg:postcode":"33016",
    "sg:province":"FL",
    "wof:name":"Torres Richardo Jr",
    "wof:placetype":"venue"
},
  "geometry": {"coordinates":[-80.3302,25.913401],"type":"Point"}
}