{
  "type": "Feature",
  "properties": {
    "iso:country":"US",
    "sg:address":"283 Harbor Dr",
    "sg:city":"Boca Grande",
    "sg:classifiers":[
        {
            "category":"Professional",
            "type":"Services"
        }
    ],
    "sg:phone":"+1 941 964 1121",
    "sg:postcode":"33921",
    "sg:province":"FL",
    "sg:tags":[
        "establishment"
    ],
    "wof:name":"J M Corbin Enterprises Inc",
    "wof:placetype":"venue"
},
  "geometry": {"coordinates":[-82.256564,26.747354],"type":"Point"}
}