{
  "type": "Feature",
  "properties": {
    "addr:full":"621 Ohio Ave N Live Oak FL 32064",
    "addr:housenumber":"621",
    "addr:postcode":"32064",
    "addr:street":"Ohio Ave N",
    "iso:country":"US",
    "sg:address":"621 Ohio Ave N",
    "sg:city":"Live Oak",
    "sg:classifiers":[
        {
            "category":"Manufacturing",
            "subcategory":"Tools & Machinery",
            "type":"Manufacturing & Wholesale Goods"
        },
        {
            "category":"Manufacturing",
            "subcategory":"Printing",
            "type":"Manufacturing & Wholesale Goods"
        }
    ],
    "sg:phone":"+1 386 362 4044",
    "sg:postcode":"32064",
    "sg:province":"FL",
    "sg:tags":[
        "machine",
        "check",
        "mfg"
    ],
    "sg:website":"www.checksyourway.com",
    "wof:name":"Checks Your Way Inc",
    "wof:placetype":"venue"
},
  "geometry": {"coordinates":[-82.981836,30.300988],"type":"Point"}
}