{
  "type": "Feature",
  "properties": {
    "iso:country":"US",
    "sg:address":"4647 McIntosh Rd",
    "sg:city":"Dover",
    "sg:classifiers":[
        {
            "category":"Food & Beverages",
            "subcategory":"Groceries & Convenience Stores",
            "type":"Retail Goods"
        }
    ],
    "sg:phone":"+1 813 659 3990",
    "sg:postcode":"33527",
    "sg:province":"FL",
    "wof:name":"Kamboj Weena",
    "wof:placetype":"venue"
},
  "geometry": {"coordinates":[-82.24444800000001,28.003462],"type":"Point"}
}