{
  "type": "Feature",
  "properties": {
    "addr:full":"1440 Main St Sarasota FL 34236",
    "addr:housenumber":"1440",
    "addr:postcode":"34236",
    "addr:street":"Main St",
    "iso:country":"US",
    "sg:address":"1440 Main St",
    "sg:city":"Sarasota",
    "sg:classifiers":[
        {
            "category":"Wholesale",
            "subcategory":"Electrical",
            "type":"Manufacturing & Wholesale Goods"
        }
    ],
    "sg:phone":"+1 941 952 5522",
    "sg:postcode":"34236",
    "sg:province":"FL",
    "sg:tags":[
        "electric",
        "motor"
    ],
    "wof:name":"American Traveler Motor Club",
    "wof:placetype":"venue"
},
  "geometry": {"coordinates":[-82.54141300000001,27.336386],"type":"Point"}
}