{
  "type": "Feature",
  "properties": {
    "iso:country":"US",
    "sg:address":"4781 S Congress Ave",
    "sg:city":"Lake Worth",
    "sg:classifiers":[
        {
            "category":"Utilities",
            "subcategory":"Telephone",
            "type":"Services"
        }
    ],
    "sg:phone":"+1 561 434 9010",
    "sg:postcode":"33461",
    "sg:province":"FL",
    "sg:tags":[
        "information",
        "telecommunication"
    ],
    "wof:name":"Voicecom",
    "wof:placetype":"venue"
},
  "geometry": {"coordinates":[-80.089584,26.60613],"type":"Point"}
}