{
  "type": "Feature",
  "properties": {
    "addr:full":"2888 N University Dr Pompano Beach FL 33065",
    "addr:housenumber":"2888",
    "addr:postcode":"33065",
    "addr:street":"N University Dr",
    "iso:country":"US",
    "sg:address":"2888 N University Dr",
    "sg:city":"Pompano Beach",
    "sg:classifiers":[
        {
            "category":"Restaurant",
            "type":"Food & Drink"
        }
    ],
    "sg:menulink":"http://www.allmenus.com/fl/margate/122664-quiznos-sub/menu/",
    "sg:phone":"+1 954 344 4446",
    "sg:postcode":"33065",
    "sg:province":"FL",
    "sg:tags":[
        "wrap",
        "american",
        "sandwich"
    ],
    "wof:name":"Quiznos Sub",
    "wof:placetype":"venue"
},
  "geometry": {"coordinates":[-80.25015999999999,26.266057],"type":"Point"}
}