{
  "type": "Feature",
  "properties": {
    "iso:country":"US",
    "sg:address":"9134 NW 32nd Manor",
    "sg:city":"Fort Lauderdale",
    "sg:classifiers":[
        {
            "category":"Wholesale",
            "subcategory":"Non-durable Goods",
            "type":"Manufacturing & Wholesale Goods"
        }
    ],
    "sg:phone":"+1 954 771 3179",
    "sg:postcode":"33351",
    "sg:province":"FL",
    "wof:name":"Refreshment Distributors Inc",
    "wof:placetype":"venue"
},
  "geometry": {"coordinates":[-80.27212,26.166377],"type":"Point"}
}