{
  "type": "Feature",
  "properties": {
    "addr:full":"6217 S Lagoon Dr Panama City FL 32408",
    "addr:housenumber":"6217",
    "addr:postcode":"32408",
    "addr:street":"S Lagoon Dr",
    "iso:country":"US",
    "sg:address":"6217 S Lagoon Dr",
    "sg:city":"Panama City",
    "sg:classifiers":[
        {
            "category":"Building & Trades",
            "subcategory":"Construction",
            "type":"Services"
        }
    ],
    "sg:phone":"+1 850 235 4034",
    "sg:postcode":"32408",
    "sg:province":"FL",
    "sg:tags":[
        "home",
        "improvement"
    ],
    "wof:name":"North Florida Closets",
    "wof:placetype":"venue"
},
  "geometry": {"coordinates":[-85.760526,30.152335],"type":"Point"}
}