{
  "type": "Feature",
  "properties": {
    "addr:full":"7940 Porpoise Dr Marathon FL 33050",
    "addr:housenumber":"7940",
    "addr:postcode":"33050",
    "addr:street":"Porpoise Dr",
    "iso:country":"US",
    "sg:address":"7940 Porpoise Dr",
    "sg:city":"Marathon",
    "sg:classifiers":[
        {
            "category":"Building & Trades",
            "subcategory":"Construction",
            "type":"Services"
        }
    ],
    "sg:phone":"+1 305 289 0227",
    "sg:postcode":"33050",
    "sg:province":"FL",
    "sg:tags":[
        "contractor"
    ],
    "wof:name":"Jim McCabe Tile & Cabinetry In",
    "wof:placetype":"venue"
},
  "geometry": {"coordinates":[-81.06039,24.728122],"type":"Point"}
}