{
  "type": "Feature",
  "properties": {
    "iso:country":"US",
    "sg:address":"1616 W Oak St",
    "sg:city":"Kissimmee",
    "sg:classifiers":[
        {
            "category":"Organizations",
            "subcategory":"Community Association",
            "type":"Services"
        }
    ],
    "sg:phone":"+1 407 846 4210",
    "sg:postcode":"34741",
    "sg:province":"FL",
    "sg:tags":[
        "club"
    ],
    "wof:name":"Kissimmee Woman's Club",
    "wof:placetype":"venue"
},
  "geometry": {"coordinates":[-81.42101700000001,28.300807],"type":"Point"}
}