{
  "type": "Feature",
  "properties": {
    "iso:country":"US",
    "sg:address":"6500 14th St W",
    "sg:city":"Bradenton",
    "sg:classifiers":[
        {
            "category":"Recreation",
            "subcategory":"Arcade",
            "type":"Entertainment"
        }
    ],
    "sg:phone":"+1 941 751 1077",
    "sg:postcode":"34207",
    "sg:province":"FL",
    "wof:name":"Lots Of Fun",
    "wof:placetype":"venue"
},
  "geometry": {"coordinates":[-82.57557199999999,27.425327],"type":"Point"}
}