{
  "type": "Feature",
  "properties": {
    "iso:country":"US",
    "sg:address":"100 N Museum Ave",
    "sg:city":"Avon Park",
    "sg:classifiers":[
        {
            "category":"Education",
            "subcategory":"Library",
            "type":"Public Place"
        }
    ],
    "sg:phone":"+1 863 452 3803",
    "sg:postcode":"33825",
    "sg:province":"FL",
    "wof:name":"Avon Park Public Library",
    "wof:placetype":"venue"
},
  "geometry": {"coordinates":[-81.50532800000001,27.597678],"type":"Point"}
}