{
  "type": "Feature",
  "properties": {
    "iso:country":"US",
    "sg:address":"275 Tiki Dr",
    "sg:city":"Merritt Island",
    "sg:classifiers":[
        {
            "category":"Shopping",
            "subcategory":"Clothing, Apparel, & Fashions",
            "type":"Retail Goods"
        }
    ],
    "sg:phone":"+1 321 452 2007",
    "sg:postcode":"32953",
    "sg:province":"FL",
    "wof:name":"Sunnyday Clothing Inc",
    "wof:placetype":"venue"
},
  "geometry": {"coordinates":[-80.694287,28.373977],"type":"Point"}
}