{
  "type": "Feature",
  "properties": {
    "iso:country":"US",
    "sg:address":"215 W Donegan Ave",
    "sg:city":"Kissimmee",
    "sg:classifiers":[
        {
            "category":"Professional",
            "subcategory":"Engineering",
            "type":"Services"
        },
        {
            "category":"Professional",
            "subcategory":"Business Services",
            "type":"Services"
        }
    ],
    "sg:phone":"+1 407 931 3711",
    "sg:postcode":"34741",
    "sg:province":"FL",
    "sg:tags":[
        "engineer"
    ],
    "wof:name":"Collins Engineers Incorporated",
    "wof:placetype":"venue"
},
  "geometry": {"coordinates":[-81.40681600000001,28.318989],"type":"Point"}
}