{
  "type": "Feature",
  "properties": {
    "addr:full":"104 Camelot Ridge Dr Brandon FL 33511",
    "addr:housenumber":"104",
    "addr:postcode":"33511",
    "addr:street":"Camelot Ridge Dr",
    "iso:country":"US",
    "sg:address":"104 Camelot Ridge Dr",
    "sg:city":"Brandon",
    "sg:classifiers":[
        {
            "category":"Manufacturing",
            "subcategory":"Tools & Machinery",
            "type":"Manufacturing & Wholesale Goods"
        }
    ],
    "sg:phone":"+1 813 689 2533",
    "sg:postcode":"33511",
    "sg:province":"FL",
    "sg:tags":[
        "machine",
        "sales",
        "accessory"
    ],
    "wof:name":"Pyramid Machine Tool Co",
    "wof:placetype":"venue"
},
  "geometry": {"coordinates":[-82.286441,27.881663],"type":"Point"}
}