{
  "type": "Feature",
  "properties": {
    "addr:full":"1746 NE Miami Gardens Dr Miami FL 33179",
    "addr:housenumber":"1746",
    "addr:postcode":"33179",
    "addr:street":"Ne Miami Gardens Dr",
    "iso:country":"US",
    "sg:address":"1746 NE Miami Gardens Dr",
    "sg:city":"Miami",
    "sg:classifiers":[
        {
            "category":"Building & Trades",
            "subcategory":"Locksmith",
            "type":"Services"
        }
    ],
    "sg:phone":"+1 305 944 0469",
    "sg:postcode":"33179",
    "sg:province":"FL",
    "sg:tags":[
        "lock",
        "key"
    ],
    "wof:name":"Medeco",
    "wof:placetype":"venue"
},
  "geometry": {"coordinates":[-80.16590100000001,25.945801],"type":"Point"}
}