{
  "type": "Feature",
  "properties": {
    "iso:country":"US",
    "sg:address":"4424 Coquina Ridge Dr",
    "sg:city":"Melbourne",
    "sg:classifiers":[
        {
            "category":"Retail",
            "subcategory":"Repair Shop",
            "type":"Services"
        }
    ],
    "sg:phone":"+1 321 255 0799",
    "sg:postcode":"32935",
    "sg:province":"FL",
    "sg:tags":[
        "mfg",
        "refrigeration",
        "motor",
        "vehicle"
    ],
    "wof:name":"Leo W Preece",
    "wof:placetype":"venue"
},
  "geometry": {"coordinates":[-80.65116,28.181998],"type":"Point"}
}