{
  "type": "Feature",
  "properties": {
    "addr:full":"1330 N John Young Pkwy Kissimmee FL 34741",
    "addr:housenumber":"1330",
    "addr:postcode":"34741",
    "addr:street":"N John Young Pkwy",
    "iso:country":"US",
    "sg:address":"1330 N John Young Pkwy",
    "sg:city":"Kissimmee",
    "sg:classifiers":[
        {
            "category":"Banks & Credit Unions",
            "subcategory":"Bank",
            "type":"Services"
        }
    ],
    "sg:phone":"+1 407 994 0300",
    "sg:postcode":"34741",
    "sg:province":"FL",
    "sg:tags":[
        "loan",
        "real estate"
    ],
    "wof:name":"Sunshine Quest Mortgage",
    "wof:placetype":"venue"
},
  "geometry": {"coordinates":[-81.41598500000001,28.304184],"type":"Point"}
}