{
  "type": "Feature",
  "properties": {
    "iso:country":"US",
    "sg:address":"7670 International Dr Ste 100",
    "sg:city":"Orlando",
    "sg:classifiers":[
        {
            "category":"Food & Beverages",
            "subcategory":"Groceries & Convenience Stores",
            "type":"Retail Goods"
        }
    ],
    "sg:phone":"+1 407 363 1900",
    "sg:postcode":"32819",
    "sg:province":"FL",
    "wof:name":"Sand Lake Supermarket",
    "wof:placetype":"venue"
},
  "geometry": {"coordinates":[-81.47081799999999,28.451791],"type":"Point"}
}