{
  "type": "Feature",
  "properties": {
    "addr:full":"7493 W Sample Rd Coral Springs FL 33065",
    "addr:housenumber":"7493",
    "addr:postcode":"33065",
    "addr:street":"W Sample Rd",
    "iso:country":"US",
    "sg:address":"7493 W Sample Rd",
    "sg:city":"Coral Springs",
    "sg:classifiers":[
        {
            "category":"Home & Garden",
            "subcategory":"Furniture",
            "type":"Retail Goods"
        }
    ],
    "sg:phone":"+1 954 227 3446",
    "sg:postcode":"33065",
    "sg:province":"FL",
    "wof:name":"Appalachian Wood Furniture",
    "wof:placetype":"venue"
},
  "geometry": {"coordinates":[-80.22300799999999,26.272258],"type":"Point"}
}