{
  "type": "Feature",
  "properties": {
    "iso:country":"US",
    "sg:address":"425 N Florida Ave",
    "sg:city":"Tampa",
    "sg:classifiers":[
        {
            "category":"Professional",
            "subcategory":"Lawyer & Legal Services",
            "type":"Services"
        }
    ],
    "sg:phone":"+1 813 225 2500",
    "sg:postcode":"33602",
    "sg:province":"FL",
    "sg:tags":[
        "attorney"
    ],
    "wof:name":"Johnson Pope Bokor Ruppel",
    "wof:placetype":"venue"
},
  "geometry": {"coordinates":[-82.45727599999999,27.948566],"type":"Point"}
}