{
  "type": "Feature",
  "properties": {
    "addr:full":"103 King St NW Live Oak FL 32064",
    "addr:housenumber":"103",
    "addr:postcode":"32064",
    "addr:street":"King St Nw",
    "iso:country":"US",
    "sg:address":"103 King St NW",
    "sg:city":"Live Oak",
    "sg:classifiers":[
        {
            "category":"Personal",
            "subcategory":"Beauty Salon",
            "type":"Services"
        }
    ],
    "sg:phone":"+1 386 362 4836",
    "sg:postcode":"32064",
    "sg:province":"FL",
    "wof:name":"Cora's Beauty Works",
    "wof:placetype":"venue"
},
  "geometry": {"coordinates":[-82.98254,30.302056],"type":"Point"}
}