{
  "type": "Feature",
  "properties": {
    "addr:full":"1717 S US Hwy 1 Fort Pierce FL 34950",
    "addr:housenumber":"1717",
    "addr:postcode":"34950",
    "addr:street":"S Us Hwy 1",
    "iso:country":"US",
    "sg:address":"1717 S US Hwy 1",
    "sg:city":"Fort Pierce",
    "sg:classifiers":[
        {
            "category":"Wholesale",
            "subcategory":"Vending Machines",
            "type":"Manufacturing & Wholesale Goods"
        }
    ],
    "sg:phone":"+1 772 332 0892",
    "sg:postcode":"34950",
    "sg:province":"FL",
    "sg:tags":[
        "operator"
    ],
    "wof:name":"Dsl Vend",
    "wof:placetype":"venue"
},
  "geometry": {"coordinates":[-80.32599500000001,27.430984],"type":"Point"}
}