{
  "type": "Feature",
  "properties": {
    "iso:country":"US",
    "sg:address":"1490 W 68th St Ste 201",
    "sg:city":"Hialeah",
    "sg:classifiers":[
        {
            "category":"Banks & Credit Unions",
            "subcategory":"Financial Services",
            "type":"Services"
        }
    ],
    "sg:phone":"+1 305 823 5555",
    "sg:postcode":"33014",
    "sg:province":"FL",
    "sg:tags":[
        "broker",
        "mortgage"
    ],
    "wof:name":"Star of Millemium Mortgage Corp",
    "wof:placetype":"venue"
},
  "geometry": {"coordinates":[-80.31349899999999,25.884199],"type":"Point"}
}