{
  "type": "Feature",
  "properties": {
    "iso:country":"US",
    "sg:address":"1702 Cordova Rd",
    "sg:city":"Fort Lauderdale",
    "sg:classifiers":[
        {
            "category":"Professional",
            "subcategory":"Accounting & Tax Preparation",
            "type":"Services"
        }
    ],
    "sg:phone":"+1 954 525 6116",
    "sg:postcode":"33316",
    "sg:province":"FL",
    "sg:tags":[
        "accountant"
    ],
    "wof:name":"Rupp Associates",
    "wof:placetype":"venue"
},
  "geometry": {"coordinates":[-80.130652,26.099158],"type":"Point"}
}