{
  "type": "Feature",
  "properties": {
    "iso:country":"US",
    "sg:address":"4848 NW 5th St",
    "sg:city":"Delray Beach",
    "sg:classifiers":[
        {
            "category":"Building & Trades",
            "subcategory":"Plumbing",
            "type":"Services"
        }
    ],
    "sg:phone":"+1 561 495 8824",
    "sg:postcode":"33445",
    "sg:province":"FL",
    "sg:tags":[
        "plumbing",
        "contractor"
    ],
    "wof:name":"Warren Malkiel Plumbing I",
    "wof:placetype":"venue"
},
  "geometry": {"coordinates":[-80.11791100000001,26.469693],"type":"Point"}
}