{
  "type": "Feature",
  "properties": {
    "addr:full":"10490 Busch Dr N Jacksonville FL 32218",
    "addr:housenumber":"10490",
    "addr:postcode":"32218",
    "addr:street":"Busch Dr N",
    "iso:country":"US",
    "sg:address":"10490 Busch Dr N",
    "sg:city":"Jacksonville",
    "sg:classifiers":[
        {
            "category":"Wholesale",
            "subcategory":"Groceries",
            "type":"Manufacturing & Wholesale Goods"
        }
    ],
    "sg:phone":"+1 904 751 3063",
    "sg:postcode":"32218",
    "sg:province":"FL",
    "sg:tags":[
        "food",
        "distributor"
    ],
    "wof:name":"Conagra Grocery Products Co",
    "wof:placetype":"venue"
},
  "geometry": {"coordinates":[-81.635953,30.423719],"type":"Point"}
}