{
  "type": "Feature",
  "properties": {
    "iso:country":"US",
    "sg:address":"4842 Deermoss Way N",
    "sg:city":"Jacksonville",
    "sg:classifiers":[
        {
            "category":"Professional",
            "subcategory":"Business Services",
            "type":"Services"
        }
    ],
    "sg:phone":"+1 904 730 2911",
    "sg:postcode":"32217",
    "sg:province":"FL",
    "sg:tags":[
        "auctioneer"
    ],
    "wof:name":"Brancon Inc Auctioneers",
    "wof:placetype":"venue"
},
  "geometry": {"coordinates":[-81.601707,30.222486],"type":"Point"}
}