{
  "type": "Feature",
  "properties": {
    "addr:full":"6920 NE 4th Ln Ocala FL 34470",
    "addr:housenumber":"6920",
    "addr:postcode":"34470",
    "addr:street":"Ne 4Th Ln",
    "iso:country":"US",
    "sg:address":"6920 NE 4th Ln",
    "sg:city":"Ocala",
    "sg:classifiers":[
        {
            "category":"Professional",
            "subcategory":"Management & Consulting",
            "type":"Services"
        },
        {
            "category":"Travel",
            "subcategory":"Travel Agent",
            "type":"Entertainment"
        }
    ],
    "sg:phone":"+1 352 236 5669",
    "sg:postcode":"34470",
    "sg:province":"FL",
    "sg:tags":[
        "consultant",
        "marketing"
    ],
    "wof:name":"Motor Coach Marketing Int Inc",
    "wof:placetype":"venue"
},
  "geometry": {"coordinates":[-82.0394,29.190476],"type":"Point"}
}