{
  "type": "Feature",
  "properties": {
    "addr:full":"9980 N Central Park Blvd Boca Raton FL 33428",
    "addr:housenumber":"9980",
    "addr:postcode":"33428",
    "addr:street":"N Central Park Blvd",
    "iso:country":"US",
    "sg:address":"9980 N Central Park Blvd",
    "sg:city":"Boca Raton",
    "sg:classifiers":[
        {
            "category":"Health Services",
            "subcategory":"Doctor",
            "type":"Services"
        }
    ],
    "sg:phone":"+1 561 558 8898",
    "sg:postcode":"33428",
    "sg:province":"FL",
    "sg:tags":[
        "physician",
        "surgeon",
        "medical"
    ],
    "wof:name":"Howard J Gelb MD PA",
    "wof:placetype":"venue"
},
  "geometry": {"coordinates":[-80.20261600000001,26.357173],"type":"Point"}
}