{
  "type": "Feature",
  "properties": {
    "addr:full":"1680 NW 13th Ave Homestead FL 33030",
    "addr:housenumber":"1680",
    "addr:postcode":"33030",
    "addr:street":"Nw 13Th Ave",
    "iso:country":"US",
    "sg:address":"1680 NW 13th Ave",
    "sg:city":"Homestead",
    "sg:classifiers":[
        {
            "category":"Building & Trades",
            "subcategory":"Construction",
            "type":"Services"
        }
    ],
    "sg:phone":"+1 305 246 9924",
    "sg:postcode":"33030",
    "sg:province":"FL",
    "sg:tags":[
        "floor",
        "laying",
        "contractor"
    ],
    "wof:name":"Data Flooring Inc",
    "wof:placetype":"venue"
},
  "geometry": {"coordinates":[-80.492926,25.486456],"type":"Point"}
}