{
  "type": "Feature",
  "properties": {
    "iso:country":"US",
    "sg:address":"2949 Shamrock St N Apt 7",
    "sg:city":"Tallahassee",
    "sg:classifiers":[
        {
            "category":"Landmark",
            "subcategory":"Tourist Attraction",
            "type":"Public Place"
        }
    ],
    "sg:phone":"+1 850 877 8802",
    "sg:postcode":"32309",
    "sg:province":"FL",
    "sg:tags":[
        "tour",
        "sightseeing"
    ],
    "wof:name":"Egypt Golf",
    "wof:placetype":"venue"
},
  "geometry": {"coordinates":[-84.215553,30.528021],"type":"Point"}
}