{
  "type": "Feature",
  "properties": {
    "addr:full":"605 S Wickham Rd Melbourne FL 32904",
    "addr:housenumber":"605",
    "addr:postcode":"32904",
    "addr:street":"S Wickham Rd",
    "iso:country":"US",
    "sg:address":"605 S Wickham Rd",
    "sg:city":"Melbourne",
    "sg:classifiers":[
        {
            "category":"Food & Beverages",
            "subcategory":"Groceries & Convenience Stores",
            "type":"Retail Goods"
        }
    ],
    "sg:phone":"+1 321 725 8650",
    "sg:postcode":"32904",
    "sg:province":"FL",
    "wof:name":"7-Eleven",
    "wof:placetype":"venue"
},
  "geometry": {"coordinates":[-80.672563,28.097264],"type":"Point"}
}