{
  "type": "Feature",
  "properties": {
    "addr:full":"4453 Ashton Rd Sarasota FL 34233",
    "addr:housenumber":"4453",
    "addr:postcode":"34233",
    "addr:street":"Ashton Rd",
    "iso:country":"US",
    "sg:address":"4453 Ashton Rd",
    "sg:city":"Sarasota",
    "sg:classifiers":[
        {
            "category":"Building & Trades",
            "subcategory":"Construction",
            "type":"Services"
        }
    ],
    "sg:phone":"+1 941 377 2622",
    "sg:postcode":"34233",
    "sg:province":"FL",
    "sg:tags":[
        "swimming",
        "designer",
        "dealer",
        "pool",
        "contractor"
    ],
    "wof:name":"Estate Pools Inc",
    "wof:placetype":"venue"
},
  "geometry": {"coordinates":[-82.477497,27.276654],"type":"Point"}
}