{
  "type": "Feature",
  "properties": {
    "iso:country":"US",
    "sg:address":"225 5th Ave",
    "sg:city":"Indialantic",
    "sg:classifiers":[
        {
            "category":"Banks & Credit Unions",
            "subcategory":"Investment Brokerage",
            "type":"Services"
        }
    ],
    "sg:phone":"+1 321 729 9008",
    "sg:postcode":"32903",
    "sg:province":"FL",
    "sg:tags":[
        "security"
    ],
    "wof:name":"Edward Jones 09960",
    "wof:placetype":"venue"
},
  "geometry": {"coordinates":[-80.570474,28.090418],"type":"Point"}
}