{
  "type": "Feature",
  "properties": {
    "addr:full":"5923 21st St E Bradenton FL 34203",
    "addr:housenumber":"5923",
    "addr:postcode":"34203",
    "addr:street":"21St St",
    "iso:country":"US",
    "sg:address":"5923 21st St E",
    "sg:city":"Bradenton",
    "sg:classifiers":[
        {
            "category":"Home & Garden",
            "subcategory":"Furniture",
            "type":"Retail Goods"
        }
    ],
    "sg:phone":"+1 941 379 4091",
    "sg:postcode":"34203",
    "sg:province":"FL",
    "wof:name":"Bcd Concepts Inc",
    "wof:placetype":"venue"
},
  "geometry": {"coordinates":[-82.53833,27.435136],"type":"Point"}
}