{
  "type": "Feature",
  "properties": {
    "addr:full":"11301 US Hwy 19 Port Richey FL 34668",
    "addr:housenumber":"11301",
    "addr:postcode":"34668",
    "addr:street":"Us Hwy 19",
    "iso:country":"US",
    "sg:address":"11301 US Hwy 19",
    "sg:city":"Port Richey",
    "sg:classifiers":[
        {
            "category":"Retail",
            "subcategory":"Repair Shop",
            "type":"Services"
        }
    ],
    "sg:phone":"+1 727 861 1996",
    "sg:postcode":"34668",
    "sg:province":"FL",
    "sg:tags":[
        "television",
        "radio"
    ],
    "wof:name":"Ben/Glen's TV VCR Svc & Rental",
    "wof:placetype":"venue"
},
  "geometry": {"coordinates":[-82.69937899999999,28.321849],"type":"Point"}
}