{
  "type": "Feature",
  "properties": {
    "iso:country":"US",
    "sg:address":"6711 Lake Andrew Dr",
    "sg:city":"Melbourne",
    "sg:classifiers":[
        {
            "category":"Banks & Credit Unions",
            "subcategory":"Bank",
            "type":"Services"
        }
    ],
    "sg:phone":"+1 321 635 2440",
    "sg:postcode":"32940",
    "sg:province":"FL",
    "sg:website":"http://www.seacoastnational.com",
    "wof:name":"Seacoast National Bank",
    "wof:placetype":"venue"
},
  "geometry": {"coordinates":[-80.7289,28.238918],"type":"Point"}
}