{
  "type": "Feature",
  "properties": {
    "iso:country":"US",
    "sg:address":"1503 SW 1st Ave",
    "sg:city":"Fort Lauderdale",
    "sg:classifiers":[
        {
            "category":"Wholesale",
            "subcategory":"Machinery & Supplies",
            "type":"Manufacturing & Wholesale Goods"
        }
    ],
    "sg:phone":"+1 954 522 2836",
    "sg:postcode":"33315",
    "sg:province":"FL",
    "sg:tags":[
        "tool"
    ],
    "wof:name":"Solar Tool & Gage Co",
    "wof:placetype":"venue"
},
  "geometry": {"coordinates":[-80.14318900000001,26.101811],"type":"Point"}
}