{
  "type": "Feature",
  "properties": {
    "addr:full":"1725 Ridgewood Ave Daytona Beach FL 32117",
    "addr:housenumber":"1725",
    "addr:postcode":"32117",
    "addr:street":"Ridgewood Ave",
    "iso:country":"US",
    "sg:address":"1725 Ridgewood Ave",
    "sg:city":"Daytona Beach",
    "sg:classifiers":[
        {
            "category":"Organizations",
            "subcategory":"Religious Organization",
            "type":"Services"
        }
    ],
    "sg:phone":"+1 386 677 5323",
    "sg:postcode":"32117",
    "sg:province":"FL",
    "sg:tags":[
        "church"
    ],
    "wof:name":"Holly Hill Church of Christ",
    "wof:placetype":"venue"
},
  "geometry": {"coordinates":[-81.048889,29.259522],"type":"Point"}
}