{
  "type": "Feature",
  "properties": {
    "iso:country":"US",
    "sg:address":"271 SE 8th Ave",
    "sg:city":"Deerfield Beach",
    "sg:classifiers":[
        {
            "category":"Wholesale",
            "subcategory":"Durable Goods & Equipment",
            "type":"Manufacturing & Wholesale Goods"
        }
    ],
    "sg:phone":"+1 954 481 1713",
    "sg:postcode":"33441",
    "sg:province":"FL",
    "wof:name":"Greenzkeeper Wholesale Supply",
    "wof:placetype":"venue"
},
  "geometry": {"coordinates":[-80.094166,26.314673],"type":"Point"}
}