{
  "type": "Feature",
  "properties": {
    "iso:country":"US",
    "sg:address":"1380 Bolger Ave",
    "sg:city":"Spring Hill",
    "sg:classifiers":[
        {
            "category":"Manufacturing",
            "subcategory":"Signs",
            "type":"Manufacturing & Wholesale Goods"
        }
    ],
    "sg:phone":"+1 352 686 5792",
    "sg:postcode":"34609",
    "sg:province":"FL",
    "wof:name":"Aces High Signs & Graphics",
    "wof:placetype":"venue"
},
  "geometry": {"coordinates":[-82.50095399999999,28.456865],"type":"Point"}
}