{
  "type": "Feature",
  "properties": {
    "iso:country":"US",
    "sg:address":"4461 37th Ave N",
    "sg:city":"St Petersburg",
    "sg:classifiers":[
        {
            "category":"Professional",
            "subcategory":"Advertising",
            "type":"Services"
        }
    ],
    "sg:phone":"+1 727 528 4237",
    "sg:postcode":"33713",
    "sg:province":"FL",
    "sg:tags":[
        "mail"
    ],
    "wof:name":"T J Enterprises Of Florida",
    "wof:placetype":"venue"
},
  "geometry": {"coordinates":[-82.692336,27.80571],"type":"Point"}
}