{
  "type": "Feature",
  "properties": {
    "iso:country":"US",
    "sg:address":"382 Oleander Dr",
    "sg:city":"Tavernier",
    "sg:classifiers":[
        {
            "category":"Personal",
            "subcategory":"Beauty Salon",
            "type":"Services"
        }
    ],
    "sg:phone":"+1 305 684 5241",
    "sg:postcode":"33070",
    "sg:province":"FL",
    "wof:name":"Rudy And Company",
    "wof:placetype":"venue"
},
  "geometry": {"coordinates":[-80.506928,25.01488],"type":"Point"}
}