{
  "type": "Feature",
  "properties": {
    "iso:country":"US",
    "sg:address":"1617 NW 2nd St",
    "sg:city":"Miami",
    "sg:classifiers":[
        {
            "category":"Transit Center",
            "subcategory":"Freight",
            "type":"Transportation"
        },
        {
            "category":"Freight",
            "type":"Transportation"
        }
    ],
    "sg:phone":"+1 305 541 2166",
    "sg:postcode":"33125",
    "sg:province":"FL",
    "sg:tags":[
        "local",
        "trucking-motor",
        "trucking"
    ],
    "wof:name":"Uranga Trucking Inc",
    "wof:placetype":"venue"
},
  "geometry": {"coordinates":[-80.221637,25.775235],"type":"Point"}
}