{
  "type": "Feature",
  "properties": {
    "iso:country":"US",
    "sg:address":"328 Crandon Blvd",
    "sg:city":"Key Biscayne",
    "sg:classifiers":[
        {
            "category":"Shopping",
            "type":"Retail Goods"
        }
    ],
    "sg:phone":"+1 305 361 2855",
    "sg:postcode":"33149",
    "sg:province":"FL",
    "wof:name":"Pretty Boutique",
    "wof:placetype":"venue"
},
  "geometry": {"coordinates":[-80.163101,25.695299],"type":"Point"}
}