{
  "type": "Feature",
  "properties": {
    "addr:full":"1155 Cattlemen Rd Sarasota FL 34232",
    "addr:housenumber":"1155",
    "addr:postcode":"34232",
    "addr:street":"Cattlemen Rd",
    "iso:country":"US",
    "sg:address":"1155 Cattlemen Rd",
    "sg:city":"Sarasota",
    "sg:classifiers":[
        {
            "category":"Wholesale",
            "subcategory":"Electrical",
            "type":"Manufacturing & Wholesale Goods"
        }
    ],
    "sg:phone":"+1 941 377 7500",
    "sg:postcode":"34232",
    "sg:province":"FL",
    "sg:tags":[
        "light",
        "tube",
        "fixture",
        "bulb",
        "accessory"
    ],
    "wof:name":"King Lighting Supply Inc",
    "wof:placetype":"venue"
},
  "geometry": {"coordinates":[-82.45131600000001,27.324264],"type":"Point"}
}