{
  "type": "Feature",
  "properties": {
    "iso:country":"US",
    "sg:address":"7548 Municipal Dr",
    "sg:city":"Orlando",
    "sg:classifiers":[
        {
            "category":"Manufacturing",
            "subcategory":"Buildings",
            "type":"Manufacturing & Wholesale Goods"
        },
        {
            "category":"Structure",
            "subcategory":"Warehouse",
            "type":"Public Place"
        },
        {
            "category":"Building & Trades",
            "subcategory":"Construction",
            "type":"Services"
        }
    ],
    "sg:phone":"+1 407 352 0107",
    "sg:postcode":"32819",
    "sg:province":"FL",
    "sg:tags":[
        "warehouses-merchandise",
        "warehouses-public-commercial",
        "consultant",
        "builder",
        "contractor",
        "home",
        "estimate"
    ],
    "sg:website":"http://www.willisestimating.com",
    "wof:name":"Willis Construction Consulting Inc",
    "wof:placetype":"venue"
},
  "geometry": {"coordinates":[-81.452088,28.45525],"type":"Point"}
}