{
  "type": "Feature",
  "properties": {
    "addr:full":"762 NE Jordan Ter Port Saint Lucie FL 34983",
    "addr:housenumber":"762",
    "addr:postcode":"34983",
    "addr:street":"Ne Jordan Ter;Lucie",
    "iso:country":"US",
    "sg:address":"762 NE Jordan Ter",
    "sg:city":"Port Saint Lucie",
    "sg:classifiers":[
        {
            "category":"Personal",
            "type":"Services"
        }
    ],
    "sg:phone":"+1 772 468 0826",
    "sg:postcode":"34983",
    "sg:province":"FL",
    "wof:name":"B Tan",
    "wof:placetype":"venue"
},
  "geometry": {"coordinates":[-80.343903,27.336045],"type":"Point"}
}