{
  "type": "Feature",
  "properties": {
    "iso:country":"US",
    "sg:address":"607 Lake Dr",
    "sg:city":"Deland",
    "sg:classifiers":[
        {
            "category":"Building & Trades",
            "subcategory":"Construction",
            "type":"Services"
        }
    ],
    "sg:phone":"+1 386 277 2024",
    "sg:postcode":"32724",
    "sg:province":"FL",
    "sg:tags":[
        "wallcoverings-installation",
        "wallpaper",
        "painting",
        "contractor"
    ],
    "wof:name":"Indian River Painting",
    "wof:placetype":"venue"
},
  "geometry": {"coordinates":[-81.31321800000001,29.085463],"type":"Point"}
}