{
  "type": "Feature",
  "properties": {
    "addr:full":"2165 Sunnydale Blvd Clearwater FL 33765",
    "addr:housenumber":"2165",
    "addr:postcode":"33765",
    "addr:street":"Sunnydale Blvd",
    "iso:country":"US",
    "sg:address":"2165 Sunnydale Blvd",
    "sg:city":"Clearwater",
    "sg:classifiers":[
        {
            "category":"Manufacturing",
            "subcategory":"Printing",
            "type":"Manufacturing & Wholesale Goods"
        }
    ],
    "sg:phone":"+1 727 466 9111",
    "sg:postcode":"33765",
    "sg:province":"FL",
    "sg:tags":[
        "equipment",
        "scanning",
        "printer",
        "plotting",
        "supply"
    ],
    "wof:name":"Independant Printing",
    "wof:placetype":"venue"
},
  "geometry": {"coordinates":[-82.74788100000001,27.987056],"type":"Point"}
}