{
  "type": "Feature",
  "properties": {
    "iso:country":"US",
    "sg:address":"1204 N 31st Ct",
    "sg:city":"Hollywood",
    "sg:classifiers":[
        {
            "category":"Professional",
            "subcategory":"Business Services",
            "type":"Services"
        }
    ],
    "sg:phone":"+1 954 961 6750",
    "sg:postcode":"33021",
    "sg:province":"FL",
    "wof:name":"Bc Home Inspections",
    "wof:placetype":"venue"
},
  "geometry": {"coordinates":[-80.17114599999999,26.021082],"type":"Point"}
}