{
  "type": "Feature",
  "properties": {
    "iso:country":"US",
    "sg:address":"645 NW 22nd Ln",
    "sg:city":"Okeechobee",
    "sg:classifiers":[
        {
            "category":"Social Services",
            "subcategory":"Child Care",
            "type":"Services"
        }
    ],
    "sg:phone":"+1 863 357 3536",
    "sg:postcode":"34972",
    "sg:province":"FL",
    "wof:name":"Little Peoples Childcare",
    "wof:placetype":"venue"
},
  "geometry": {"coordinates":[-80.835613,27.26434],"type":"Point"}
}