{
  "type": "Feature",
  "properties": {
    "addr:full":"301 Central Ave Sarasota FL 34236",
    "addr:housenumber":"301",
    "addr:postcode":"34236",
    "addr:street":"Central Ave",
    "iso:country":"US",
    "sg:address":"301 Central Ave",
    "sg:city":"Sarasota",
    "sg:classifiers":[
        {
            "category":"Shopping",
            "type":"Retail Goods"
        }
    ],
    "sg:phone":"+1 941 366 5300",
    "sg:postcode":"34236",
    "sg:province":"FL",
    "sg:tags":[
        "color",
        "drafting",
        "graphic",
        "survey",
        "supply"
    ],
    "sg:website":"www.bluelineinc.net",
    "wof:name":"Blue Line Inc",
    "wof:placetype":"venue"
},
  "geometry": {"coordinates":[-82.542683,27.339257],"type":"Point"}
}