{
  "type": "Feature",
  "properties": {
    "iso:country":"US",
    "sg:address":"10616 Sun Villa Blvd",
    "sg:city":"Orlando",
    "sg:classifiers":[
        {
            "category":"Professional",
            "subcategory":"Engineering",
            "type":"Services"
        }
    ],
    "sg:phone":"+1 407 808 8253",
    "sg:postcode":"32817",
    "sg:province":"FL",
    "sg:tags":[
        "engineer",
        "integration",
        "system"
    ],
    "wof:name":"Taino Group Inc",
    "wof:placetype":"venue"
},
  "geometry": {"coordinates":[-81.235975,28.60049],"type":"Point"}
}