{
  "type": "Feature",
  "properties": {
    "addr:full":"615 Brandon Town Center Mall Brandon FL 33511",
    "addr:housenumber":"615",
    "addr:postcode":"33511",
    "addr:street":"Brandon Town;Mall",
    "iso:country":"US",
    "sg:address":"615 Brandon Town Center Mall",
    "sg:city":"Brandon",
    "sg:classifiers":[
        {
            "category":"Shopping",
            "subcategory":"Jewelry",
            "type":"Retail Goods"
        },
        {
            "category":"Manufacturing",
            "subcategory":"Jewelry",
            "type":"Manufacturing & Wholesale Goods"
        }
    ],
    "sg:phone":"+1 813 651 3881",
    "sg:postcode":"33511",
    "sg:province":"FL",
    "sg:tags":[
        "stone",
        "designer",
        "semi-precious",
        "precious",
        "jeweler"
    ],
    "sg:website":"http://www.zales.com",
    "wof:name":"Zales Jewelers",
    "wof:placetype":"venue"
},
  "geometry": {"coordinates":[-82.324034,27.928334],"type":"Point"}
}