{
  "type": "Feature",
  "properties": {
    "addr:full":"980 NW 10th Ave Fort Lauderdale FL 33311",
    "addr:housenumber":"980",
    "addr:postcode":"33311",
    "addr:street":"Nw 10Th Ave",
    "iso:country":"US",
    "sg:address":"980 NW 10th Ave",
    "sg:city":"Fort Lauderdale",
    "sg:classifiers":[
        {
            "category":"Freight",
            "type":"Transportation"
        }
    ],
    "sg:phone":"+1 954 712 1453",
    "sg:postcode":"33311",
    "sg:province":"FL",
    "sg:tags":[
        "operator",
        "mover",
        "local",
        "trucking"
    ],
    "wof:name":"Summit Van Lines Inc",
    "wof:placetype":"venue"
},
  "geometry": {"coordinates":[-80.154673,26.135036],"type":"Point"}
}