{
  "type": "Feature",
  "properties": {
    "iso:country":"US",
    "sg:address":"2405 SE 17th Cir",
    "sg:city":"Ocala",
    "sg:classifiers":[
        {
            "category":"Professional",
            "subcategory":"Business Services",
            "type":"Services"
        }
    ],
    "sg:phone":"+1 352 629 0165",
    "sg:postcode":"34471",
    "sg:province":"FL",
    "wof:name":"Employee Leasing Solutions",
    "wof:placetype":"venue"
},
  "geometry": {"coordinates":[-82.104049,29.169172],"type":"Point"}
}