{
  "type": "Feature",
  "properties": {
    "iso:country":"US",
    "sg:address":"777 SE 25th Ln",
    "sg:city":"Hialeah",
    "sg:classifiers":[
        {
            "category":"Health Services",
            "subcategory":"Doctor",
            "type":"Services"
        }
    ],
    "sg:phone":"+1 305 823 5730",
    "sg:postcode":"33033",
    "sg:province":"FL",
    "sg:tags":[
        "physician",
        "surgeon"
    ],
    "wof:name":"Gilda M De La Calle MD",
    "wof:placetype":"venue"
},
  "geometry": {"coordinates":[-80.440918,25.463703],"type":"Point"}
}