{
  "type": "Feature",
  "properties": {
    "addr:full":"13508 Santa Rosa Ave Port Charlotte FL 33981",
    "addr:housenumber":"13508",
    "addr:postcode":"33981",
    "addr:street":"Santa Rosa Ave",
    "iso:country":"US",
    "sg:address":"13508 Santa Rosa Ave",
    "sg:city":"Port Charlotte",
    "sg:classifiers":[
        {
            "category":"Building & Trades",
            "subcategory":"Landscaping Services",
            "type":"Services"
        }
    ],
    "sg:phone":"+1 941 697 6010",
    "sg:postcode":"33981",
    "sg:province":"FL",
    "sg:tags":[
        "landscape"
    ],
    "wof:name":"M & N Landscaping & Cnstr Corp",
    "wof:placetype":"venue"
},
  "geometry": {"coordinates":[-82.22341900000001,26.937473],"type":"Point"}
}