{
  "type": "Feature",
  "properties": {
    "addr:full":"4276 US Hwy 441 Okeechobee FL 34974",
    "addr:housenumber":"4276",
    "addr:postcode":"34974",
    "addr:street":"Us Hwy 441",
    "iso:country":"US",
    "sg:address":"4276 US Hwy 441",
    "sg:city":"Okeechobee",
    "sg:classifiers":[
        {
            "category":"Travel",
            "subcategory":"Campground",
            "type":"Entertainment"
        }
    ],
    "sg:phone":"+1 863 763 0231",
    "sg:postcode":"34974",
    "sg:province":"FL",
    "sg:tags":[
        "campsite",
        "park",
        "trailer"
    ],
    "wof:name":"Kampgrounds of America Inc",
    "wof:placetype":"venue"
},
  "geometry": {"coordinates":[-80.781814,27.206079],"type":"Point"}
}