{
  "type": "Feature",
  "properties": {
    "addr:full":"745 N Volusia Ave Orange City FL 32763",
    "addr:housenumber":"745",
    "addr:postcode":"32763",
    "addr:street":"N Volusia Ave",
    "iso:country":"US",
    "sg:address":"745 N Volusia Ave",
    "sg:city":"Orange City",
    "sg:classifiers":[
        {
            "category":"Recreation",
            "type":"Entertainment"
        }
    ],
    "sg:phone":"+1 386 774 8888",
    "sg:postcode":"32763",
    "sg:province":"FL",
    "wof:name":"Orange City Billiards",
    "wof:placetype":"venue"
},
  "geometry": {"coordinates":[-81.298935,28.956264],"type":"Point"}
}