{
  "type": "Feature",
  "properties": {
    "addr:full":"847 Waterman Rd S Jacksonville FL 32207",
    "addr:housenumber":"847",
    "addr:postcode":"32207",
    "addr:street":"Waterman Rd",
    "iso:country":"US",
    "sg:address":"847 Waterman Rd S",
    "sg:city":"Jacksonville",
    "sg:classifiers":[
        {
            "category":"Professional",
            "type":"Services"
        }
    ],
    "sg:phone":"+1 904 396 0554",
    "sg:postcode":"32207",
    "sg:province":"FL",
    "sg:tags":[
        "establishment"
    ],
    "wof:name":"Harris & Harris",
    "wof:placetype":"venue"
},
  "geometry": {"coordinates":[-81.65572,30.288038],"type":"Point"}
}