{
  "type": "Feature",
  "properties": {
    "iso:country":"US",
    "sg:address":"1112 E Donegan Ave",
    "sg:city":"Kissimmee",
    "sg:classifiers":[
        {
            "category":"Building & Trades",
            "subcategory":"Construction",
            "type":"Services"
        }
    ],
    "sg:phone":"+1 407 933 5700",
    "sg:postcode":"34744",
    "sg:province":"FL",
    "sg:tags":[
        "painter"
    ],
    "wof:name":"Roberson Decorating Co Inc",
    "wof:placetype":"venue"
},
  "geometry": {"coordinates":[-81.39157400000001,28.318893],"type":"Point"}
}