{
  "type": "Feature",
  "properties": {
    "addr:full":"803 W New York Ave De Land FL 32720",
    "addr:housenumber":"803",
    "addr:postcode":"32720",
    "addr:street":"W New York Ave",
    "iso:country":"US",
    "sg:address":"803 W New York Ave",
    "sg:city":"De Land",
    "sg:classifiers":[
        {
            "category":"Restaurant",
            "type":"Food & Drink"
        }
    ],
    "sg:phone":"+1 386 734 5705",
    "sg:postcode":"32720",
    "sg:province":"FL",
    "sg:tags":[
        "parlor",
        "pizza"
    ],
    "wof:name":"Christos & Elenis Italian Rest",
    "wof:placetype":"venue"
},
  "geometry": {"coordinates":[-81.31895900000001,29.028023],"type":"Point"}
}