{
  "type": "Feature",
  "properties": {
    "iso:country":"US",
    "sg:address":"1500 Colonial Blvd Ste 105",
    "sg:city":"Fort Myers",
    "sg:classifiers":[
        {
            "category":"Professional",
            "subcategory":"Lawyer & Legal Services",
            "type":"Services"
        }
    ],
    "sg:phone":"+1 239 334 0355",
    "sg:postcode":"33907",
    "sg:province":"FL",
    "sg:tags":[
        "personal",
        "injury"
    ],
    "wof:name":"The Law Offices of Justin G Morgan PA",
    "wof:placetype":"venue"
},
  "geometry": {"coordinates":[-81.88649700000001,26.5966],"type":"Point"}
}