{
  "type": "Feature",
  "properties": {
    "iso:country":"US",
    "sg:address":"2358 Anniston Rd",
    "sg:city":"Jacksonville",
    "sg:classifiers":[
        {
            "category":"Building & Trades",
            "subcategory":"Construction",
            "type":"Services"
        }
    ],
    "sg:phone":"+1 904 725 0583",
    "sg:postcode":"32246",
    "sg:province":"FL",
    "sg:tags":[
        "framing",
        "contractor"
    ],
    "wof:name":"Self Construction",
    "wof:placetype":"venue"
},
  "geometry": {"coordinates":[-81.54113700000001,30.30517],"type":"Point"}
}