{
  "type": "Feature",
  "properties": {
    "iso:country":"US",
    "sg:address":"30342 SW 155th Pl",
    "sg:city":"Homestead",
    "sg:classifiers":[
        {
            "category":"Wholesale",
            "subcategory":"Construction Materials",
            "type":"Manufacturing & Wholesale Goods"
        }
    ],
    "sg:phone":"+1 305 245 5974",
    "sg:postcode":"33033",
    "sg:province":"FL",
    "sg:tags":[
        "fence"
    ],
    "wof:name":"Pete's Forte Fence Corp",
    "wof:placetype":"venue"
},
  "geometry": {"coordinates":[-80.443315,25.48519],"type":"Point"}
}