{
  "type": "Feature",
  "properties": {
    "iso:country":"US",
    "sg:address":"3813 E Colonial Dr",
    "sg:city":"Orlando",
    "sg:classifiers":[
        {
            "category":"Utilities",
            "subcategory":"Mobile Phone",
            "type":"Services"
        }
    ],
    "sg:phone":"+1 407 228 7585",
    "sg:postcode":"32803",
    "sg:province":"FL",
    "sg:tags":[
        "telephone",
        "cellular"
    ],
    "wof:name":"Choice Cellular",
    "wof:placetype":"venue"
},
  "geometry": {"coordinates":[-81.336686,28.553519],"type":"Point"}
}