{
  "type": "Feature",
  "properties": {
    "iso:country":"US",
    "sg:address":"4268 King Richard Ln",
    "sg:city":"Sarasota",
    "sg:classifiers":[
        {
            "category":"Building & Trades",
            "subcategory":"Electrical",
            "type":"Services"
        }
    ],
    "sg:phone":"+1 941 371 5691",
    "sg:postcode":"34232",
    "sg:province":"FL",
    "sg:tags":[
        "electrical",
        "electric",
        "contractor"
    ],
    "wof:name":"Kochendorfer Electric Corp",
    "wof:placetype":"venue"
},
  "geometry": {"coordinates":[-82.483141,27.328772],"type":"Point"}
}