{
  "type": "Feature",
  "properties": {
    "addr:full":"1014 del Prado Blvd S Cape Coral FL 33990",
    "addr:housenumber":"1014",
    "addr:postcode":"33990",
    "addr:street":"Del Prado Blvd S",
    "iso:country":"US",
    "sg:address":"1014 del Prado Blvd S",
    "sg:city":"Cape Coral",
    "sg:classifiers":[
        {
            "category":"Utilities",
            "subcategory":"Mobile Phone",
            "type":"Services"
        }
    ],
    "sg:phone":"+1 239 458 2585",
    "sg:postcode":"33990",
    "sg:province":"FL",
    "sg:tags":[
        "repair",
        "beeper"
    ],
    "wof:name":"Beepers N Phones-South Fl",
    "wof:placetype":"venue"
},
  "geometry": {"coordinates":[-81.940821,26.633901],"type":"Point"}
}