{
  "type": "Feature",
  "properties": {
    "iso:country":"US",
    "sg:address":"3011 W Flagler St",
    "sg:city":"Miami",
    "sg:classifiers":[
        {
            "category":"Personal",
            "type":"Services"
        }
    ],
    "sg:phone":"+1 305 646 0272",
    "sg:postcode":"33135",
    "sg:province":"FL",
    "sg:tags":[
        "hair",
        "electrolysis",
        "removal"
    ],
    "wof:name":"Electrolysis & Laser of Miami",
    "wof:placetype":"venue"
},
  "geometry": {"coordinates":[-80.244102,25.7721],"type":"Point"}
}