{
  "type": "Feature",
  "properties": {
    "addr:full":"1034 E Las Olas Blvd Fort Lauderdale FL 33301",
    "addr:housenumber":"1034",
    "addr:postcode":"33301",
    "addr:street":"E Las Olas Blvd",
    "iso:country":"US",
    "sg:address":"1034 E Las Olas Blvd",
    "sg:city":"Fort Lauderdale",
    "sg:classifiers":[
        {
            "category":"Home & Garden",
            "subcategory":"Home Furnishings",
            "type":"Retail Goods"
        }
    ],
    "sg:phone":"+1 954 525 5754",
    "sg:postcode":"33301",
    "sg:province":"FL",
    "sg:tags":[
        "upholstery",
        "accessory",
        "furniture"
    ],
    "wof:name":"Elements Las Olas",
    "wof:placetype":"venue"
},
  "geometry": {"coordinates":[-80.132361,26.119242],"type":"Point"}
}