{
  "type": "Feature",
  "properties": {
    "addr:full":"5676 Washington St Hollywood FL 33023",
    "addr:housenumber":"5676",
    "addr:postcode":"33023",
    "addr:street":"Washington St",
    "iso:country":"US",
    "sg:address":"5676 Washington St",
    "sg:city":"Hollywood",
    "sg:classifiers":[
        {
            "category":"Insurance",
            "subcategory":"Insurance Agent",
            "type":"Services"
        }
    ],
    "sg:phone":"+1 954 964 8220",
    "sg:postcode":"33023",
    "sg:province":"FL",
    "wof:name":"Judy Lai",
    "wof:placetype":"venue"
},
  "geometry": {"coordinates":[-80.20169300000001,26.002567],"type":"Point"}
}