{
  "type": "Feature",
  "properties": {
    "addr:full":"2868 River Pines Way Sarasota FL 34231",
    "addr:housenumber":"2868",
    "addr:postcode":"34231",
    "addr:street":"River Pines Way",
    "iso:country":"US",
    "sg:address":"2868 River Pines Way",
    "sg:city":"Sarasota",
    "sg:classifiers":[
        {
            "category":"Restaurant",
            "type":"Food & Drink"
        }
    ],
    "sg:phone":"+1 941 951 0990",
    "sg:postcode":"34231",
    "sg:province":"FL",
    "sg:tags":[
        "eating"
    ],
    "wof:name":"Churchills Bar & Restaurant",
    "wof:placetype":"venue"
},
  "geometry": {"coordinates":[-82.513622,27.280798],"type":"Point"}
}