{
  "type": "Feature",
  "properties": {
    "iso:country":"US",
    "sg:address":"2073 Siesta Dr",
    "sg:city":"Sarasota",
    "sg:classifiers":[
        {
            "category":"Personal",
            "subcategory":"Shoe Repair & Shine",
            "type":"Services"
        }
    ],
    "sg:phone":"+1 941 365 2885",
    "sg:postcode":"34239",
    "sg:province":"FL",
    "sg:tags":[
        "repairing",
        "boot"
    ],
    "wof:name":"Town Cobbler Shoe Repair",
    "wof:placetype":"venue"
},
  "geometry": {"coordinates":[-82.527688,27.302924],"type":"Point"}
}