{
  "type": "Feature",
  "properties": {
    "addr:full":"4250 Alafaya Trl Ste 196 Oviedo FL 32765",
    "addr:postcode":"4250;32765",
    "addr:street":"Alafaya Trl Ste 196",
    "iso:country":"US",
    "sg:address":"4250 Alafaya Trl Ste 196",
    "sg:city":"Oviedo",
    "sg:classifiers":[
        {
            "category":"Personal",
            "subcategory":"Nail Salon",
            "type":"Services"
        }
    ],
    "sg:phone":"+1 407 977 0773",
    "sg:postcode":"32765",
    "sg:province":"FL",
    "wof:name":"Avenue Nails",
    "wof:placetype":"venue"
},
  "geometry": {"coordinates":[-81.207519,28.612345],"type":"Point"}
}