{
  "type": "Feature",
  "properties": {
    "addr:full":"1200 S Parrott Ave Okeechobee FL 34974",
    "addr:housenumber":"1200",
    "addr:postcode":"34974",
    "addr:street":"S Parrott Ave",
    "iso:country":"US",
    "sg:address":"1200 S Parrott Ave",
    "sg:city":"Okeechobee",
    "sg:classifiers":[
        {
            "category":"Real Estate",
            "subcategory":"Real Estate Services",
            "type":"Services"
        },
        {
            "category":"Real Estate",
            "subcategory":"Real Estate Agent",
            "type":"Services"
        }
    ],
    "sg:phone":"+1 863 763 2104",
    "sg:postcode":"34974",
    "sg:province":"FL",
    "sg:tags":[
        "buyer",
        "broker"
    ],
    "wof:name":"Century Twenty One Hazellief &",
    "wof:placetype":"venue"
},
  "geometry": {"coordinates":[-80.829964,27.232229],"type":"Point"}
}