{
  "type": "Feature",
  "properties": {
    "addr:full":"599 W Fairfield Dr Pensacola FL 32506",
    "addr:housenumber":"599",
    "addr:postcode":"32506",
    "addr:street":"W Fairfield Dr",
    "iso:country":"US",
    "sg:address":"599 W Fairfield Dr",
    "sg:city":"Pensacola",
    "sg:classifiers":[
        {
            "category":"Personal",
            "subcategory":"Beauty Salon",
            "type":"Services"
        }
    ],
    "sg:phone":"+1 850 453 2967",
    "sg:postcode":"32506",
    "sg:province":"FL",
    "sg:tags":[
        "shop"
    ],
    "wof:name":"Classic Touch Beauty Salon",
    "wof:placetype":"venue"
},
  "geometry": {"coordinates":[-87.31745100000001,30.418043],"type":"Point"}
}