{
  "type": "Feature",
  "properties": {
    "iso:country":"US",
    "sg:address":"3265 State Hwy 580",
    "sg:city":"Safety Harbor",
    "sg:classifiers":[
        {
            "category":"Organizations",
            "subcategory":"Religious Organization",
            "type":"Services"
        }
    ],
    "sg:phone":"+1 727 791 2273",
    "sg:postcode":"34695",
    "sg:province":"FL",
    "sg:tags":[
        "church"
    ],
    "wof:name":"Orthodox Chr Of Holy Trinity",
    "wof:placetype":"venue"
},
  "geometry": {"coordinates":[-82.70210299999999,28.026926],"type":"Point"}
}