{
  "type": "Feature",
  "properties": {
    "iso:country":"US",
    "sg:address":"2012 Willow Lauren Ln",
    "sg:city":"Windermere",
    "sg:classifiers":[
        {
            "category":"Wholesale",
            "subcategory":"Medical Equipment & Supplies",
            "type":"Manufacturing & Wholesale Goods"
        }
    ],
    "sg:phone":"+1 407 909 0911",
    "sg:postcode":"34786",
    "sg:province":"FL",
    "sg:tags":[
        "alarm"
    ],
    "wof:name":"Partner 24",
    "wof:placetype":"venue"
},
  "geometry": {"coordinates":[-81.551811,28.51439],"type":"Point"}
}