{
  "type": "Feature",
  "properties": {
    "iso:country":"US",
    "sg:address":"5532 Ave du Soleil",
    "sg:city":"Lutz",
    "sg:classifiers":[
        {
            "category":"Professional",
            "type":"Services"
        }
    ],
    "sg:phone":"+1 813 949 1232",
    "sg:postcode":"33558",
    "sg:province":"FL",
    "wof:name":"Take Charge Now",
    "wof:placetype":"venue"
},
  "geometry": {"coordinates":[-82.534678,28.146406],"type":"Point"}
}