{
  "type": "Feature",
  "properties": {
    "addr:full":"1401 Mason Ave Daytona Beach FL 32117",
    "addr:housenumber":"1401",
    "addr:postcode":"32117",
    "addr:street":"Mason Ave",
    "iso:country":"US",
    "sg:address":"1401 Mason Ave",
    "sg:city":"Daytona Beach",
    "sg:classifiers":[
        {
            "category":"Food & Beverages",
            "subcategory":"Groceries & Convenience Stores",
            "type":"Retail Goods"
        }
    ],
    "sg:phone":"+1 386 274 4366",
    "sg:postcode":"32117",
    "sg:province":"FL",
    "wof:name":"7-Eleven",
    "wof:placetype":"venue"
},
  "geometry": {"coordinates":[-81.06260899999999,29.213276],"type":"Point"}
}