{
  "type": "Feature",
  "properties": {
    "iso:country":"US",
    "sg:address":"6646 Angus Valley Dr",
    "sg:city":"Zephyrhills",
    "sg:classifiers":[
        {
            "category":"Building & Trades",
            "subcategory":"Plumbing",
            "type":"Services"
        }
    ],
    "sg:phone":"+1 813 991 4199",
    "sg:postcode":"33544",
    "sg:province":"FL",
    "sg:tags":[
        "contractor"
    ],
    "wof:name":"Priority Air Conditioning",
    "wof:placetype":"venue"
},
  "geometry": {"coordinates":[-82.37211499999999,28.254154],"type":"Point"}
}