{
  "type": "Feature",
  "properties": {
    "addr:full":"2124 W Elm St Tampa FL 33604",
    "addr:housenumber":"2124",
    "addr:postcode":"33604",
    "addr:street":"W Elm St",
    "iso:country":"US",
    "sg:address":"2124 W Elm St",
    "sg:city":"Tampa",
    "sg:classifiers":[
        {
            "category":"Banks & Credit Unions",
            "subcategory":"Bank",
            "type":"Services"
        }
    ],
    "sg:phone":"+1 813 935 4610",
    "sg:postcode":"33604",
    "sg:province":"FL",
    "sg:tags":[
        "mortgage"
    ],
    "wof:name":"Sound Funding",
    "wof:placetype":"venue"
},
  "geometry": {"coordinates":[-82.484118,28.00998],"type":"Point"}
}