{
  "type": "Feature",
  "properties": {
    "addr:full":"408 Highwood Cir Jupiter FL 33458",
    "addr:housenumber":"408",
    "addr:postcode":"33458",
    "addr:street":"Highwood Cir",
    "iso:country":"US",
    "sg:address":"408 Highwood Cir",
    "sg:city":"Jupiter",
    "sg:classifiers":[
        {
            "category":"Social Services",
            "subcategory":"Child Care",
            "type":"Services"
        }
    ],
    "sg:phone":"+1 561 719 7484",
    "sg:postcode":"33458",
    "sg:province":"FL",
    "sg:tags":[
        "sitting"
    ],
    "wof:name":"Sunflower Home Services",
    "wof:placetype":"venue"
},
  "geometry": {"coordinates":[-80.100842,26.928941],"type":"Point"}
}