{
  "type": "Feature",
  "properties": {
    "addr:full":"6874 81st Ave Pinellas Park FL 33781",
    "addr:housenumber":"6874",
    "addr:postcode":"33781",
    "addr:street":"81St Ave",
    "iso:country":"US",
    "sg:address":"6874 81st Ave",
    "sg:city":"Pinellas Park",
    "sg:classifiers":[
        {
            "category":"Professional",
            "type":"Services"
        }
    ],
    "sg:phone":"+1 727 546 1801",
    "sg:postcode":"33781",
    "sg:province":"FL",
    "wof:name":"Diane Walsh Inc",
    "wof:placetype":"venue"
},
  "geometry": {"coordinates":[-82.73333700000001,27.845624],"type":"Point"}
}