{
  "type": "Feature",
  "properties": {
    "addr:full":"2125 NE 17th Ter Wilton Manors FL 33305",
    "addr:housenumber":"2125",
    "addr:postcode":"33305",
    "addr:street":"Ne 17Th Ter;Manors",
    "iso:country":"US",
    "sg:address":"2125 NE 17th Ter",
    "sg:city":"Wilton Manors",
    "sg:classifiers":[
        {
            "category":"Autos & Motor Vehicles",
            "subcategory":"Boat Sales",
            "type":"Retail Goods"
        }
    ],
    "sg:phone":"+1 954 491 8688",
    "sg:postcode":"33305",
    "sg:province":"FL",
    "sg:tags":[
        "yacht",
        "broker"
    ],
    "wof:name":"Thomas C Horvath",
    "wof:placetype":"venue"
},
  "geometry": {"coordinates":[-80.12399000000001,26.157589],"type":"Point"}
}