{
  "type": "Feature",
  "properties": {
    "iso:country":"US",
    "sg:address":"18620 SW 244th St",
    "sg:city":"Homestead",
    "sg:classifiers":[
        {
            "category":"Retail",
            "subcategory":"Repair Shop",
            "type":"Services"
        }
    ],
    "sg:phone":"+1 305 245 4522",
    "sg:postcode":"33031",
    "sg:province":"FL",
    "wof:name":"Tab Service By Klema Inc",
    "wof:placetype":"venue"
},
  "geometry": {"coordinates":[-80.493037,25.539144],"type":"Point"}
}