{
  "type": "Feature",
  "properties": {
    "addr:full":"1931 Savona Pkwy Cape Coral FL 33904",
    "addr:housenumber":"1931",
    "addr:postcode":"33904",
    "addr:street":"Savona Pkwy",
    "iso:country":"US",
    "sg:address":"1931 Savona Pkwy",
    "sg:city":"Cape Coral",
    "sg:classifiers":[
        {
            "category":"Real Estate",
            "subcategory":"Real Estate Agent",
            "type":"Services"
        }
    ],
    "sg:phone":"+1 239 945 5378",
    "sg:postcode":"33904",
    "sg:province":"FL",
    "wof:name":"Richard L Tomkins Inc",
    "wof:placetype":"venue"
},
  "geometry": {"coordinates":[-81.931231,26.581344],"type":"Point"}
}