{
  "type": "Feature",
  "properties": {
    "addr:full":"8701 Hastings Blvd Hastings FL 32145",
    "addr:housenumber":"8701",
    "addr:postcode":"32145",
    "addr:street":"Hastings Blvd",
    "iso:country":"US",
    "sg:address":"8701 Hastings Blvd",
    "sg:city":"Hastings",
    "sg:classifiers":[
        {
            "category":"Autos & Motor Vehicles",
            "subcategory":"Automobile Sales",
            "type":"Retail Goods"
        }
    ],
    "sg:phone":"+1 904 692 5951",
    "sg:postcode":"32145",
    "sg:province":"FL",
    "sg:tags":[
        "equipment",
        "aircraft",
        "parts",
        "transportation",
        "supply"
    ],
    "sg:website":"www.earleaircraft.com",
    "wof:name":"Earle Aircraft Inc",
    "wof:placetype":"venue"
},
  "geometry": {"coordinates":[-81.503766,29.69464],"type":"Point"}
}