{
  "type": "Feature",
  "properties": {
    "addr:full":"468 Hickorywood Dr Crawfordville FL 32326",
    "addr:housenumber":"468",
    "addr:postcode":"32326",
    "addr:street":"Hickorywood Dr",
    "iso:country":"US",
    "sg:address":"468 Hickorywood Dr",
    "sg:city":"Crawfordville",
    "sg:classifiers":[
        {
            "category":"Manufacturing",
            "subcategory":"Printing",
            "type":"Manufacturing & Wholesale Goods"
        }
    ],
    "sg:phone":"+1 850 926 7478",
    "sg:postcode":"32326",
    "sg:province":"FL",
    "sg:tags":[
        "periodical"
    ],
    "wof:name":"Wakulla Digest",
    "wof:placetype":"venue"
},
  "geometry": {"coordinates":[-84.320747,30.17937],"type":"Point"}
}