{
  "type": "Feature",
  "properties": {
    "addr:full":"2274 Weston Rd Fort Lauderdale FL 33326",
    "addr:housenumber":"2274",
    "addr:postcode":"33326",
    "addr:street":"Weston Rd",
    "iso:country":"US",
    "sg:address":"2274 Weston Rd",
    "sg:city":"Fort Lauderdale",
    "sg:classifiers":[
        {
            "category":"Cafe",
            "type":"Food & Drink"
        }
    ],
    "sg:menulink":"http://www.allmenus.com/fl/davie/241554-offerdahls-cafe-grill/menu/",
    "sg:phone":"+1 954 384 1043",
    "sg:postcode":"33326",
    "sg:province":"FL",
    "sg:tags":[
        "american"
    ],
    "wof:name":"Offerdahl's Cafe Grill",
    "wof:placetype":"venue"
},
  "geometry": {"coordinates":[-80.371666,26.089749],"type":"Point"}
}