{
  "type": "Feature",
  "properties": {
    "addr:full":"17060 Grand Bay Dr Boca Raton FL 33496",
    "addr:housenumber":"17060",
    "addr:postcode":"33496",
    "addr:street":"Grand Bay Dr",
    "iso:country":"US",
    "sg:address":"17060 Grand Bay Dr",
    "sg:city":"Boca Raton",
    "sg:classifiers":[
        {
            "category":"Banks & Credit Unions",
            "subcategory":"Financial Services",
            "type":"Services"
        }
    ],
    "sg:phone":"+1 561 995 8685",
    "sg:postcode":"33496",
    "sg:province":"FL",
    "sg:tags":[
        "trust",
        "management"
    ],
    "wof:name":"Kaufman Foundation Inc",
    "wof:placetype":"venue"
},
  "geometry": {"coordinates":[-80.136658,26.423142],"type":"Point"}
}