{
  "type": "Feature",
  "properties": {
    "iso:country":"US",
    "sg:address":"2300 NW 17th Ave",
    "sg:city":"Miami",
    "sg:classifiers":[
        {
            "category":"Building & Trades",
            "subcategory":"Electrical",
            "type":"Services"
        }
    ],
    "sg:phone":"+1 786 360 6693",
    "sg:postcode":"33142",
    "sg:province":"FL",
    "sg:tags":[
        "electrician"
    ],
    "wof:name":"Victor Car Electric Inc",
    "wof:placetype":"venue"
},
  "geometry": {"coordinates":[-80.22341900000001,25.798441],"type":"Point"}
}