{
  "type": "Feature",
  "properties": {
    "iso:country":"US",
    "sg:address":"2312 Apalachee Pkwy",
    "sg:city":"Tallahassee",
    "sg:classifiers":[
        {
            "category":"Shopping",
            "subcategory":"Catalog Store",
            "type":"Retail Goods"
        },
        {
            "category":"Shopping",
            "subcategory":"Books",
            "type":"Retail Goods"
        }
    ],
    "sg:phone":"+1 850 580 2665",
    "sg:postcode":"32301",
    "sg:province":"FL",
    "sg:tags":[
        "mail",
        "dealer",
        "house"
    ],
    "wof:name":"Rivenoak",
    "wof:placetype":"venue"
},
  "geometry": {"coordinates":[-84.24301699999999,30.42985],"type":"Point"}
}