{
  "type": "Feature",
  "properties": {
    "iso:country":"US",
    "sg:address":"255 N Broadway Ave",
    "sg:city":"Bartow",
    "sg:classifiers":[
        {
            "category":"Government",
            "subcategory":"Office",
            "type":"Public Place"
        }
    ],
    "sg:phone":"+1 863 534 4627",
    "sg:postcode":"33830",
    "sg:province":"FL",
    "wof:name":"Honorable Charles A Davis Jr",
    "wof:placetype":"venue"
},
  "geometry": {"coordinates":[-81.843255,27.899198],"type":"Point"}
}