{
  "type": "Feature",
  "properties": {
    "iso:country":"US",
    "sg:address":"6905 NW 77th Ave",
    "sg:city":"Miami",
    "sg:classifiers":[
        {
            "category":"Wholesale",
            "subcategory":"Machinery & Supplies",
            "type":"Manufacturing & Wholesale Goods"
        }
    ],
    "sg:phone":"+1 305 883 0960",
    "sg:postcode":"33166",
    "sg:province":"FL",
    "sg:tags":[
        "equipment",
        "hydraulic"
    ],
    "wof:name":"Easy Lift Forklifts Hydraulics",
    "wof:placetype":"venue"
},
  "geometry": {"coordinates":[-80.32158200000001,25.836156],"type":"Point"}
}