{
  "type": "Feature",
  "properties": {
    "addr:full":"493 NW 27th Ave Miami FL 33125",
    "addr:housenumber":"493",
    "addr:postcode":"33125",
    "addr:street":"Nw 27Th Ave",
    "iso:country":"US",
    "sg:address":"493 NW 27th Ave",
    "sg:city":"Miami",
    "sg:classifiers":[
        {
            "category":"Professional",
            "subcategory":"Management & Consulting",
            "type":"Services"
        }
    ],
    "sg:phone":"+1 305 649 4049",
    "sg:postcode":"33125",
    "sg:province":"FL",
    "sg:tags":[
        "consultant"
    ],
    "wof:name":"NWCS Consulting Specialtly",
    "wof:placetype":"venue"
},
  "geometry": {"coordinates":[-80.239222,25.777549],"type":"Point"}
}