{
  "type": "Feature",
  "properties": {
    "addr:full":"593 E Oakland Park Blvd Fort Lauderdale FL 33334",
    "addr:housenumber":"593",
    "addr:postcode":"33334",
    "addr:street":"E Oakland Park Blvd",
    "iso:country":"US",
    "sg:address":"593 E Oakland Park Blvd",
    "sg:city":"Fort Lauderdale",
    "sg:classifiers":[
        {
            "category":"Restaurant",
            "type":"Food & Drink"
        }
    ],
    "sg:menulink":"http://www.allmenus.com/fl/fort-lauderdale/207536-taco-bell/menu/",
    "sg:phone":"+1 954 537 4913",
    "sg:postcode":"33334",
    "sg:province":"FL",
    "sg:tags":[
        "mexican"
    ],
    "wof:name":"Taco Bell",
    "wof:placetype":"venue"
},
  "geometry": {"coordinates":[-80.13853899999999,26.166731],"type":"Point"}
}