{
  "type": "Feature",
  "properties": {
    "iso:country":"US",
    "sg:address":"1779 W 37th St",
    "sg:city":"Hialeah",
    "sg:classifiers":[
        {
            "category":"Wholesale",
            "subcategory":"Medical Equipment & Supplies",
            "type":"Manufacturing & Wholesale Goods"
        }
    ],
    "sg:phone":"+1 305 827 2322",
    "sg:postcode":"33012",
    "sg:province":"FL",
    "sg:tags":[
        "physician",
        "surgeon"
    ],
    "wof:name":"Support Supply Corp",
    "wof:placetype":"venue"
},
  "geometry": {"coordinates":[-80.31531099999999,25.85535],"type":"Point"}
}