{
  "type": "Feature",
  "properties": {
    "iso:country":"US",
    "sg:address":"3631 131st Ave N",
    "sg:city":"Clearwater",
    "sg:classifiers":[
        {
            "category":"Manufacturing",
            "subcategory":"Chemicals & Compounds",
            "type":"Manufacturing & Wholesale Goods"
        }
    ],
    "sg:phone":"+1 727 592 0772",
    "sg:postcode":"33762",
    "sg:province":"FL",
    "sg:tags":[
        "preparation",
        "mfg"
    ],
    "wof:name":"Terlyn Industries Inc",
    "wof:placetype":"venue"
},
  "geometry": {"coordinates":[-82.683887,27.891388],"type":"Point"}
}