{
  "type": "Feature",
  "properties": {
    "addr:full":"4200 3rd Ave NW Bradenton FL 34209",
    "addr:housenumber":"4200",
    "addr:postcode":"34209",
    "addr:street":"3Rd Ave Nw",
    "iso:country":"US",
    "sg:address":"4200 3rd Ave NW",
    "sg:city":"Bradenton",
    "sg:classifiers":[
        {
            "category":"Retail",
            "subcategory":"Funeral Services",
            "type":"Services"
        }
    ],
    "sg:phone":"+1 941 746 1844",
    "sg:postcode":"34209",
    "sg:province":"FL",
    "sg:tags":[
        "cemetery"
    ],
    "wof:name":"Fogartyville Cemetery",
    "wof:placetype":"venue"
},
  "geometry": {"coordinates":[-82.60292800000001,27.501129],"type":"Point"}
}