{
  "type": "Feature",
  "properties": {
    "iso:country":"US",
    "sg:address":"430 Toney Penna Dr",
    "sg:city":"Jupiter",
    "sg:classifiers":[
        {
            "category":"Social Services",
            "subcategory":"Job Training",
            "type":"Services"
        }
    ],
    "sg:phone":"+1 561 748 5657",
    "sg:postcode":"33458",
    "sg:province":"FL",
    "sg:tags":[
        "rehabilitation"
    ],
    "wof:name":"Modern Rehabilitation Tech",
    "wof:placetype":"venue"
},
  "geometry": {"coordinates":[-80.10142500000001,26.926331],"type":"Point"}
}