{
  "type": "Feature",
  "properties": {
    "addr:full":"8001 SW 138th Pl Miami FL 33183",
    "addr:housenumber":"8001",
    "addr:postcode":"33183",
    "addr:street":"Sw 138Th Pl",
    "iso:country":"US",
    "sg:address":"8001 SW 138th Pl",
    "sg:city":"Miami",
    "sg:classifiers":[
        {
            "category":"Professional",
            "type":"Services"
        }
    ],
    "sg:phone":"+1 305 386 5300",
    "sg:postcode":"33183",
    "sg:province":"FL",
    "sg:tags":[
        "establishment"
    ],
    "wof:name":"Paul Virgin Inc",
    "wof:placetype":"venue"
},
  "geometry": {"coordinates":[-80.418949,25.692342],"type":"Point"}
}