{
  "type": "Feature",
  "properties": {
    "iso:country":"US",
    "sg:address":"1390 Hope Rd",
    "sg:city":"Maitland",
    "sg:classifiers":[
        {
            "category":"Professional",
            "subcategory":"Lawyer & Legal Services",
            "type":"Services"
        }
    ],
    "sg:phone":"+1 407 644 3339",
    "sg:postcode":"32751",
    "sg:province":"FL",
    "wof:name":"McElyea Santos & Barnard PA",
    "wof:placetype":"venue"
},
  "geometry": {"coordinates":[-81.384021,28.632583],"type":"Point"}
}