{
  "type": "Feature",
  "properties": {
    "addr:full":"950 Arthur Godfrey Rd Miami Beach FL 33140",
    "addr:housenumber":"950",
    "addr:postcode":"33140",
    "addr:street":"Arthur Godfrey Rd",
    "iso:country":"US",
    "sg:address":"950 Arthur Godfrey Rd",
    "sg:city":"Miami Beach",
    "sg:classifiers":[
        {
            "category":"Building & Trades",
            "subcategory":"Construction",
            "type":"Services"
        }
    ],
    "sg:phone":"+1 305 672 0293",
    "sg:postcode":"33140",
    "sg:province":"FL",
    "sg:tags":[
        "house"
    ],
    "wof:name":"Fna Builders Inc",
    "wof:placetype":"venue"
},
  "geometry": {"coordinates":[-80.135381,25.813076],"type":"Point"}
}