{
  "type": "Feature",
  "properties": {
    "iso:country":"US",
    "sg:address":"351 Hans Brinker St",
    "sg:city":"Fort Myers",
    "sg:classifiers":[
        {
            "category":"Building & Trades",
            "subcategory":"Landscaping Services",
            "type":"Services"
        }
    ],
    "sg:phone":"+1 239 997 6943",
    "sg:postcode":"33903",
    "sg:province":"FL",
    "sg:tags":[
        "lawn",
        "maintenance",
        "grounds"
    ],
    "wof:name":"Dennis W Dilley Maintenance",
    "wof:placetype":"venue"
},
  "geometry": {"coordinates":[-81.90740599999999,26.699977],"type":"Point"}
}