{
  "type": "Feature",
  "properties": {
    "addr:full":"3665 Scotch Pine Ln Ormond Beach FL 32174",
    "addr:housenumber":"3665",
    "addr:postcode":"32174",
    "addr:street":"Scotch Pine Ln",
    "iso:country":"US",
    "sg:address":"3665 Scotch Pine Ln",
    "sg:city":"Ormond Beach",
    "sg:classifiers":[
        {
            "category":"Building & Trades",
            "subcategory":"Construction",
            "type":"Services"
        }
    ],
    "sg:phone":"+1 386 547 3008",
    "sg:postcode":"32174",
    "sg:province":"FL",
    "sg:tags":[
        "clearing",
        "land",
        "leveling"
    ],
    "wof:name":"Charlies Bobcat Svc",
    "wof:placetype":"venue"
},
  "geometry": {"coordinates":[-81.23504699999999,29.231088],"type":"Point"}
}