{
  "type": "Feature",
  "properties": {
    "addr:full":"18115 Cedarhurst Rd Orlando FL 32820",
    "addr:housenumber":"18115",
    "addr:postcode":"32820",
    "addr:street":"Cedarhurst Rd",
    "iso:country":"US",
    "sg:address":"18115 Cedarhurst Rd",
    "sg:city":"Orlando",
    "sg:classifiers":[
        {
            "category":"Building & Trades",
            "subcategory":"Landscaping Services",
            "type":"Services"
        }
    ],
    "sg:phone":"+1 407 568 2749",
    "sg:postcode":"32820",
    "sg:province":"FL",
    "wof:name":"B & D Yard Care",
    "wof:placetype":"venue"
},
  "geometry": {"coordinates":[-81.10844,28.566251],"type":"Point"}
}