{
  "type": "Feature",
  "properties": {
    "iso:country":"US",
    "sg:address":"625 Ohio Ave S",
    "sg:city":"Live Oak",
    "sg:classifiers":[
        {
            "category":"Restaurant",
            "type":"Food & Drink"
        }
    ],
    "sg:menulink":"http://www.allmenus.com/fl/live-oak/71187-pizza-hut/menu/",
    "sg:phone":"+1 386 364 1123",
    "sg:postcode":"32064",
    "sg:province":"FL",
    "sg:tags":[
        "american",
        "pizza"
    ],
    "wof:name":"Pizza Hut",
    "wof:placetype":"venue"
},
  "geometry": {"coordinates":[-82.986797,30.291961],"type":"Point"}
}