{
  "type": "Feature",
  "properties": {
    "iso:country":"US",
    "sg:address":"13712 SW 84th St",
    "sg:city":"Miami",
    "sg:classifiers":[
        {
            "category":"Restaurant",
            "type":"Food & Drink"
        }
    ],
    "sg:phone":"+1 305 382 6200",
    "sg:postcode":"33183",
    "sg:province":"FL",
    "sg:tags":[
        "eating"
    ],
    "wof:name":"Mikes Pizza & Restaurant",
    "wof:placetype":"venue"
},
  "geometry": {"coordinates":[-80.416428,25.68847],"type":"Point"}
}