{
  "type": "Feature",
  "properties": {
    "addr:full":"4988 W 12th Ave Hialeah FL 33012",
    "addr:housenumber":"4988",
    "addr:postcode":"33012",
    "addr:street":"W 12Th Ave",
    "iso:country":"US",
    "sg:address":"4988 W 12th Ave",
    "sg:city":"Hialeah",
    "sg:classifiers":[
        {
            "category":"Personal",
            "subcategory":"Beauty Salon",
            "type":"Services"
        }
    ],
    "sg:phone":"+1 305 558 5243",
    "sg:postcode":"33012",
    "sg:province":"FL",
    "sg:tags":[
        "shop"
    ],
    "wof:name":"Kep's Hair & Beauty",
    "wof:placetype":"venue"
},
  "geometry": {"coordinates":[-80.306924,25.866711],"type":"Point"}
}