{
  "type": "Feature",
  "properties": {
    "addr:full":"1107 Dora Ave Tavares FL 32778",
    "addr:housenumber":"1107",
    "addr:postcode":"32778",
    "addr:street":"Dora Ave",
    "iso:country":"US",
    "sg:address":"1107 Dora Ave",
    "sg:city":"Tavares",
    "sg:classifiers":[
        {
            "category":"Building & Trades",
            "subcategory":"Landscaping Services",
            "type":"Services"
        }
    ],
    "sg:phone":"+1 352 343 6735",
    "sg:postcode":"32778",
    "sg:province":"FL",
    "wof:name":"Stricklands Lawn Maintenance",
    "wof:placetype":"venue"
},
  "geometry": {"coordinates":[-81.714254,28.813676],"type":"Point"}
}