{
  "type": "Feature",
  "properties": {
    "addr:full":"174 Semoran Commerce Pl Apopka FL 32703",
    "addr:housenumber":"174",
    "addr:postcode":"32703",
    "addr:street":"Semoran Commerce Pl",
    "iso:country":"US",
    "sg:address":"174 Semoran Commerce Pl",
    "sg:city":"Apopka",
    "sg:classifiers":[
        {
            "category":"Education",
            "subcategory":"School",
            "type":"Public Place"
        }
    ],
    "sg:phone":"+1 407 889 9661",
    "sg:postcode":"32703",
    "sg:province":"FL",
    "sg:tags":[
        "supply"
    ],
    "wof:name":"Classic School Products",
    "wof:placetype":"venue"
},
  "geometry": {"coordinates":[-81.479409,28.674676],"type":"Point"}
}