{
  "type": "Feature",
  "properties": {
    "iso:country":"US",
    "sg:address":"3119 230th St",
    "sg:city":"Lake City",
    "sg:phone":"+1 386 935 0398",
    "sg:postcode":"32024",
    "sg:province":"FL",
    "sg:tags":[
        "farm",
        "field",
        "crop"
    ],
    "wof:name":"B D & R Hay Sales",
    "wof:placetype":"venue"
},
  "geometry": {"coordinates":[-82.79951,30.03486],"type":"Point"}
}