{
  "type": "Feature",
  "properties": {
    "iso:country":"US",
    "sg:address":"1350 NW 12th Ave",
    "sg:city":"Miami",
    "sg:classifiers":[
        {
            "category":"Government",
            "subcategory":"Court House",
            "type":"Public Place"
        }
    ],
    "sg:phone":"+1 305 547 0350",
    "sg:postcode":"33136",
    "sg:province":"FL",
    "sg:tags":[
        "state",
        "counsel"
    ],
    "wof:name":"State Attorney Robbery Div",
    "wof:placetype":"venue"
},
  "geometry": {"coordinates":[-80.215052,25.786535],"type":"Point"}
}