{
  "type": "Feature",
  "properties": {
    "iso:country":"US",
    "sg:address":"19 W 33rd St",
    "sg:city":"Jacksonville",
    "sg:classifiers":[
        {
            "category":"Autos & Motor Vehicles",
            "subcategory":"Automobile Sales",
            "type":"Retail Goods"
        }
    ],
    "sg:phone":"+1 904 598 0305",
    "sg:postcode":"32206",
    "sg:province":"FL",
    "sg:tags":[
        "car",
        "used",
        "dealer"
    ],
    "wof:name":"Cathy's Auto Sales",
    "wof:placetype":"venue"
},
  "geometry": {"coordinates":[-81.655008,30.364457],"type":"Point"}
}