{
  "type": "Feature",
  "properties": {
    "addr:full":"2531 Rodman St Hollywood FL 33020",
    "addr:housenumber":"2531",
    "addr:postcode":"33020",
    "addr:street":"Rodman St",
    "iso:country":"US",
    "sg:address":"2531 Rodman St",
    "sg:city":"Hollywood",
    "sg:classifiers":[
        {
            "category":"Manufacturing",
            "subcategory":"Metals",
            "type":"Manufacturing & Wholesale Goods"
        }
    ],
    "sg:phone":"+1 954 922 7294",
    "sg:postcode":"33020",
    "sg:province":"FL",
    "sg:tags":[
        "mfg"
    ],
    "wof:name":"R & D Aluminum",
    "wof:placetype":"venue"
},
  "geometry": {"coordinates":[-80.15737300000001,26.001003],"type":"Point"}
}