{
  "type": "Feature",
  "properties": {
    "iso:country":"US",
    "sg:address":"1702 Lindsey Rd",
    "sg:city":"Jacksonville",
    "sg:classifiers":[
        {
            "category":"Personal",
            "subcategory":"Barber",
            "type":"Services"
        }
    ],
    "sg:phone":"+1 904 695 3325",
    "sg:postcode":"32221",
    "sg:province":"FL",
    "wof:name":"Cut Masters",
    "wof:placetype":"venue"
},
  "geometry": {"coordinates":[-81.785624,30.289022],"type":"Point"}
}