{
  "type": "Feature",
  "properties": {
    "iso:country":"US",
    "sg:address":"108 Bayhammock Ln",
    "sg:city":"Longwood",
    "sg:classifiers":[
        {
            "category":"Wholesale",
            "subcategory":"Electrical",
            "type":"Manufacturing & Wholesale Goods"
        }
    ],
    "sg:phone":"+1 407 788 9202",
    "sg:postcode":"32779",
    "sg:province":"FL",
    "sg:tags":[
        "electronic"
    ],
    "wof:name":"Century Automation",
    "wof:placetype":"venue"
},
  "geometry": {"coordinates":[-81.42788400000001,28.704612],"type":"Point"}
}