{
  "type": "Feature",
  "properties": {
    "iso:country":"US",
    "sg:address":"740 Tomoka Farms Rd",
    "sg:city":"New Smyrna Beach",
    "sg:classifiers":[
        {
            "category":"Organizations",
            "subcategory":"Religious Organization",
            "type":"Services"
        }
    ],
    "sg:phone":"+1 386 428 7770",
    "sg:postcode":"32168",
    "sg:province":"FL",
    "sg:tags":[
        "church"
    ],
    "wof:name":"Spruce Creek Congregation",
    "wof:placetype":"venue"
},
  "geometry": {"coordinates":[-81.068451,29.054842],"type":"Point"}
}