{
  "type": "Feature",
  "properties": {
    "iso:country":"US",
    "sg:address":"104 S 38th St",
    "sg:city":"Port Saint Joe",
    "sg:classifiers":[
        {
            "category":"Restaurant",
            "type":"Food & Drink"
        }
    ],
    "sg:phone":"+1 850 648 9134",
    "sg:postcode":"32456",
    "sg:province":"FL",
    "sg:tags":[
        "eating"
    ],
    "wof:name":"Hidden Lagoon Grill",
    "wof:placetype":"venue"
},
  "geometry": {"coordinates":[-85.42439899999999,29.950626],"type":"Point"}
}