{
  "type": "Feature",
  "properties": {
    "iso:country":"US",
    "sg:address":"5468 Hamilton Ln",
    "sg:city":"Milton",
    "sg:classifiers":[
        {
            "category":"Wholesale",
            "subcategory":"Jewelry",
            "type":"Manufacturing & Wholesale Goods"
        }
    ],
    "sg:phone":"+1 850 995 4452",
    "sg:postcode":"32571",
    "sg:province":"FL",
    "sg:tags":[
        "stone"
    ],
    "wof:name":"Take A Peek",
    "wof:placetype":"venue"
},
  "geometry": {"coordinates":[-87.15937700000001,30.633858],"type":"Point"}
}