{
  "type": "Feature",
  "properties": {
    "iso:country":"US",
    "sg:address":"1925 Old Mission Rd",
    "sg:city":"New Smyrna Beach",
    "sg:classifiers":[
        {
            "category":"Building & Trades",
            "subcategory":"Construction",
            "type":"Services"
        }
    ],
    "sg:phone":"+1 386 427 2280",
    "sg:postcode":"32168",
    "sg:province":"FL",
    "sg:tags":[
        "heavy"
    ],
    "wof:name":"Moore Marine Inc",
    "wof:placetype":"venue"
},
  "geometry": {"coordinates":[-80.94456700000001,28.987296],"type":"Point"}
}