{
  "type": "Feature",
  "properties": {
    "addr:full":"Miami Design Building 4100 NE 2nd Ave Suite 101 Miami FL 33137",
    "addr:housenumber":"4100",
    "addr:postcode":"33137",
    "addr:street":"Ne 2Nd Ave Suite 101",
    "iso:country":"US",
    "sg:address":"Miami Design Building 4100 NE 2nd Ave Suite 101",
    "sg:city":"Miami",
    "sg:classifiers":[
        {
            "category":"Home & Garden",
            "subcategory":"Home Furnishings",
            "type":"Retail Goods"
        },
        {
            "category":"Shopping",
            "subcategory":"Antiques",
            "type":"Retail Goods"
        },
        {
            "category":"Building & Trades",
            "subcategory":"Construction",
            "type":"Services"
        },
        {
            "category":"Retail",
            "subcategory":"Repair Shop",
            "type":"Services"
        },
        {
            "category":"Home & Garden",
            "subcategory":"Furniture",
            "type":"Retail Goods"
        }
    ],
    "sg:phone":"+1 305 573 2039",
    "sg:postcode":"33137",
    "sg:province":"FL",
    "sg:tags":[
        "interior",
        "decor",
        "design",
        "reupholstery",
        "store"
    ],
    "sg:website":"www.hibiscusislandhome.com",
    "wof:name":"Hibiscus Island Home",
    "wof:placetype":"venue"
},
  "geometry": {"coordinates":[-80.19167899999999,25.81459],"type":"Point"}
}