{
  "type": "Feature",
  "properties": {
    "iso:country":"US",
    "sg:address":"2155 12th St",
    "sg:city":"Sarasota",
    "sg:classifiers":[
        {
            "category":"Building & Trades",
            "subcategory":"Pest Control",
            "type":"Services"
        }
    ],
    "sg:phone":"+1 941 746 5276",
    "sg:postcode":"34237",
    "sg:province":"FL",
    "wof:name":"Fahey Professional Lawn",
    "wof:placetype":"venue"
},
  "geometry": {"coordinates":[-82.528097,27.348666],"type":"Point"}
}