{
  "type": "Feature",
  "properties": {
    "iso:country":"US",
    "sg:address":"1910 Golden Gate Blvd E",
    "sg:city":"Naples",
    "sg:classifiers":[
        {
            "category":"Building & Trades",
            "subcategory":"Construction",
            "type":"Services"
        }
    ],
    "sg:phone":"+1 239 354 3000",
    "sg:postcode":"34120",
    "sg:province":"FL",
    "sg:tags":[
        "builder",
        "operative"
    ],
    "wof:name":"V & A American Corp",
    "wof:placetype":"venue"
},
  "geometry": {"coordinates":[-81.566323,26.230277],"type":"Point"}
}