{
  "type": "Feature",
  "properties": {
    "iso:country":"US",
    "sg:address":"190 N Tessier Dr",
    "sg:city":"Saint Petersburg",
    "sg:classifiers":[
        {
            "category":"Wholesale",
            "subcategory":"Home Furnishings",
            "type":"Manufacturing & Wholesale Goods"
        }
    ],
    "sg:phone":"+1 727 367 9184",
    "sg:postcode":"33706",
    "sg:province":"FL",
    "sg:tags":[
        "wood"
    ],
    "wof:name":"Pkf Group",
    "wof:placetype":"venue"
},
  "geometry": {"coordinates":[-82.73117000000001,27.7002],"type":"Point"}
}