{
  "type": "Feature",
  "properties": {
    "iso:country":"US",
    "sg:address":"421 W Plz Real",
    "sg:city":"Boca Raton",
    "sg:classifiers":[
        {
            "category":"Shopping",
            "subcategory":"Jewelry",
            "type":"Retail Goods"
        }
    ],
    "sg:phone":"+1 561 392 7044",
    "sg:postcode":"33432",
    "sg:province":"FL",
    "sg:tags":[
        "jeweler"
    ],
    "wof:name":"Stelios Galgadas Exclusive",
    "wof:placetype":"venue"
},
  "geometry": {"coordinates":[-80.08551900000001,26.355705],"type":"Point"}
}