{
  "type": "Feature",
  "properties": {
    "iso:country":"US",
    "sg:address":"4700 Sheridan St",
    "sg:city":"Hollywood",
    "sg:classifiers":[
        {
            "category":"Insurance",
            "subcategory":"Insurance Agent",
            "type":"Services"
        }
    ],
    "sg:phone":"+1 954 962 0070",
    "sg:postcode":"33021",
    "sg:province":"FL",
    "sg:tags":[
        "broker"
    ],
    "wof:name":"Carefree Insurance Management",
    "wof:placetype":"venue"
},
  "geometry": {"coordinates":[-80.191559,26.032663],"type":"Point"}
}