{
  "type": "Feature",
  "properties": {
    "iso:country":"US",
    "sg:address":"3000 N Ponce de Leon Blvd",
    "sg:city":"St Augustine",
    "sg:classifiers":[
        {
            "category":"Insurance",
            "subcategory":"Insurance Agent",
            "type":"Services"
        }
    ],
    "sg:phone":"+1 904 826 3266",
    "sg:postcode":"32084",
    "sg:province":"FL",
    "wof:name":"Beckman Agency",
    "wof:placetype":"venue"
},
  "geometry": {"coordinates":[-81.32485699999999,29.919454],"type":"Point"}
}