{
  "type": "Feature",
  "properties": {
    "iso:country":"US",
    "sg:address":"1681 NW 97th Ave",
    "sg:city":"Doral",
    "sg:classifiers":[
        {
            "category":"Retail",
            "subcategory":"Auto Repair",
            "type":"Services"
        }
    ],
    "sg:phone":"+1 305 639 1781",
    "sg:postcode":"33172",
    "sg:province":"FL",
    "wof:name":"Forward Euro Corp",
    "wof:placetype":"venue"
},
  "geometry": {"coordinates":[-80.35271400000001,25.78959],"type":"Point"}
}