{
  "type": "Feature",
  "properties": {
    "addr:full":"1041 Harrison Ave Panama City FL 32401",
    "addr:housenumber":"1041",
    "addr:postcode":"32401",
    "addr:street":"Harrison Ave",
    "iso:country":"US",
    "sg:address":"1041 Harrison Ave",
    "sg:city":"Panama City",
    "sg:classifiers":[
        {
            "category":"Autos & Motor Vehicles",
            "subcategory":"Automobile Sales",
            "type":"Retail Goods"
        }
    ],
    "sg:phone":"+1 850 522 7172",
    "sg:postcode":"32401",
    "sg:province":"FL",
    "wof:name":"M & M Imports Auto",
    "wof:placetype":"venue"
},
  "geometry": {"coordinates":[-85.66033,30.1671],"type":"Point"}
}