{
  "type": "Feature",
  "properties": {
    "iso:country":"US",
    "sg:address":"1759 Morrill St",
    "sg:city":"Sarasota",
    "sg:classifiers":[
        {
            "category":"Shopping",
            "subcategory":"Music",
            "type":"Retail Goods"
        }
    ],
    "sg:phone":"+1 941 366 5129",
    "sg:postcode":"34236",
    "sg:province":"FL",
    "wof:name":"Paradigm Records",
    "wof:placetype":"venue"
},
  "geometry": {"coordinates":[-82.53450100000001,27.3339],"type":"Point"}
}