{
  "type": "Feature",
  "properties": {
    "addr:full":"3201 SW 129th Ave Miami FL 33175",
    "addr:housenumber":"3201",
    "addr:postcode":"33175",
    "addr:street":"Sw 129Th Ave",
    "iso:country":"US",
    "sg:address":"3201 SW 129th Ave",
    "sg:city":"Miami",
    "sg:classifiers":[
        {
            "category":"Building & Trades",
            "subcategory":"Construction",
            "type":"Services"
        }
    ],
    "sg:phone":"+1 305 220 2925",
    "sg:postcode":"33175",
    "sg:province":"FL",
    "sg:tags":[
        "concrete",
        "pumping",
        "contractor"
    ],
    "wof:name":"All Pro Concrete Pumping Corp",
    "wof:placetype":"venue"
},
  "geometry": {"coordinates":[-80.40397,25.738813],"type":"Point"}
}