{
  "type": "Feature",
  "properties": {
    "iso:country":"US",
    "sg:address":"2164 Highland Ave",
    "sg:city":"Fort Myers",
    "sg:classifiers":[
        {
            "category":"Organizations",
            "subcategory":"Religious Organization",
            "type":"Services"
        }
    ],
    "sg:phone":"+1 239 332 4011",
    "sg:postcode":"33916",
    "sg:province":"FL",
    "sg:tags":[
        "church"
    ],
    "wof:name":"House Of God Saints In Christ",
    "wof:placetype":"venue"
},
  "geometry": {"coordinates":[-81.842221,26.640337],"type":"Point"}
}