{
  "type": "Feature",
  "properties": {
    "iso:country":"US",
    "sg:address":"11380 SW 7th St",
    "sg:city":"Miami",
    "sg:classifiers":[
        {
            "category":"Personal",
            "type":"Services"
        }
    ],
    "sg:phone":"+1 305 207 5422",
    "sg:postcode":"33174",
    "sg:province":"FL",
    "sg:tags":[
        "control",
        "weight"
    ],
    "wof:name":"M M & Cosby Inc",
    "wof:placetype":"venue"
},
  "geometry": {"coordinates":[-80.37904899999999,25.762185],"type":"Point"}
}