{
  "type": "Feature",
  "properties": {
    "addr:full":"6506 36th Avenue Dr W Bradenton FL 34209",
    "addr:housenumber":"6506",
    "addr:postcode":"34209",
    "addr:street":"36Th Avenue Dr W",
    "iso:country":"US",
    "sg:address":"6506 36th Avenue Dr W",
    "sg:city":"Bradenton",
    "sg:classifiers":[
        {
            "category":"Wholesale",
            "subcategory":"Vending Machines",
            "type":"Manufacturing & Wholesale Goods"
        }
    ],
    "sg:phone":"+1 941 761 2538",
    "sg:postcode":"34209",
    "sg:province":"FL",
    "sg:tags":[
        "operator"
    ],
    "wof:name":"Blount Vending",
    "wof:placetype":"venue"
},
  "geometry": {"coordinates":[-82.62638200000001,27.469442],"type":"Point"}
}