{
  "type": "Feature",
  "properties": {
    "iso:country":"US",
    "sg:address":"610 S Albany Ave",
    "sg:city":"Tampa",
    "sg:classifiers":[
        {
            "category":"Professional",
            "subcategory":"Business Services",
            "type":"Services"
        }
    ],
    "sg:phone":"+1 813 258 2822",
    "sg:postcode":"33606",
    "sg:province":"FL",
    "wof:name":"Valmark Appraisers LLC",
    "wof:placetype":"venue"
},
  "geometry": {"coordinates":[-82.480875,27.937485],"type":"Point"}
}