{
  "type": "Feature",
  "properties": {
    "addr:full":"4317 Fortune Pl West Melbourne FL 32904",
    "addr:housenumber":"4317",
    "addr:postcode":"32904",
    "addr:street":"Fortune Pl",
    "iso:country":"US",
    "sg:address":"4317 Fortune Pl",
    "sg:city":"West Melbourne",
    "sg:classifiers":[
        {
            "category":"Freight",
            "type":"Transportation"
        }
    ],
    "sg:phone":"+1 321 676 0050",
    "sg:postcode":"32904",
    "sg:province":"FL",
    "sg:tags":[
        "mover"
    ],
    "wof:name":"Read's Moving Systems",
    "wof:placetype":"venue"
},
  "geometry": {"coordinates":[-80.697768,28.094848],"type":"Point"}
}