{
  "type": "Feature",
  "properties": {
    "iso:country":"US",
    "sg:address":"1823 Nottingham St",
    "sg:city":"Winter Haven",
    "sg:classifiers":[
        {
            "category":"Building & Trades",
            "subcategory":"Construction",
            "type":"Services"
        }
    ],
    "sg:phone":"+1 863 412 3809",
    "sg:postcode":"33880",
    "sg:province":"FL",
    "sg:tags":[
        "hanging",
        "contractor"
    ],
    "wof:name":"Sup Exter Cassidy Prssure Wash",
    "wof:placetype":"venue"
},
  "geometry": {"coordinates":[-81.747046,28.010504],"type":"Point"}
}