{
  "type": "Feature",
  "properties": {
    "addr:full":"1327 W Jefferson St Quincy FL 32351",
    "addr:housenumber":"1327",
    "addr:postcode":"32351",
    "addr:street":"W Jefferson St",
    "iso:country":"US",
    "sg:address":"1327 W Jefferson St",
    "sg:city":"Quincy",
    "sg:classifiers":[
        {
            "category":"Shopping",
            "subcategory":"Florist",
            "type":"Retail Goods"
        }
    ],
    "sg:phone":"+1 850 627 6661",
    "sg:postcode":"32351",
    "sg:province":"FL",
    "wof:name":"Ivy Shop",
    "wof:placetype":"venue"
},
  "geometry": {"coordinates":[-84.593761,30.587595],"type":"Point"}
}