{
  "type": "Feature",
  "properties": {
    "addr:full":"420 Charleswood Ave Orlando FL 32825",
    "addr:housenumber":"420",
    "addr:postcode":"32825",
    "addr:street":"Charleswood Ave",
    "iso:country":"US",
    "sg:address":"420 Charleswood Ave",
    "sg:city":"Orlando",
    "sg:classifiers":[
        {
            "category":"Building & Trades",
            "subcategory":"Construction",
            "type":"Services"
        }
    ],
    "sg:phone":"+1 407 281 3954",
    "sg:postcode":"32825",
    "sg:province":"FL",
    "wof:name":"Curtis Associate",
    "wof:placetype":"venue"
},
  "geometry": {"coordinates":[-81.25643599999999,28.537206],"type":"Point"}
}