{
  "type": "Feature",
  "properties": {
    "addr:full":"11423 SW 133rd Ter Miami FL 33176",
    "addr:housenumber":"11423",
    "addr:postcode":"33176",
    "addr:street":"Sw 133Rd Ter",
    "iso:country":"US",
    "sg:address":"11423 SW 133rd Ter",
    "sg:city":"Miami",
    "sg:classifiers":[
        {
            "category":"Shopping",
            "type":"Retail Goods"
        }
    ],
    "sg:phone":"+1 305 234 7449",
    "sg:postcode":"33176",
    "sg:province":"FL",
    "sg:tags":[
        "water",
        "equipment",
        "purification"
    ],
    "wof:name":"Vivaproducts Inc",
    "wof:placetype":"venue"
},
  "geometry": {"coordinates":[-80.379582,25.645142],"type":"Point"}
}