{
  "type": "Feature",
  "properties": {
    "iso:country":"US",
    "sg:address":"4060 Fenner Rd",
    "sg:city":"Cocoa",
    "sg:classifiers":[
        {
            "category":"Building & Trades",
            "subcategory":"Construction",
            "type":"Services"
        }
    ],
    "sg:phone":"+1 321 632 1469",
    "sg:postcode":"32926",
    "sg:province":"FL",
    "wof:name":"Huey Cox",
    "wof:placetype":"venue"
},
  "geometry": {"coordinates":[-80.78492199999999,28.367433],"type":"Point"}
}