{
  "type": "Feature",
  "properties": {
    "iso:country":"US",
    "sg:address":"11565 Tamiami Trl",
    "sg:city":"Naples",
    "sg:classifiers":[
        {
            "category":"Recreation",
            "type":"Entertainment"
        }
    ],
    "sg:phone":"+1 239 793 4414",
    "sg:postcode":"34113",
    "sg:province":"FL",
    "sg:tags":[
        "parks"
    ],
    "wof:name":"Eagle Lakes Community Park",
    "wof:placetype":"venue"
},
  "geometry": {"coordinates":[-81.71726099999999,26.074556],"type":"Point"}
}