{
  "type": "Feature",
  "properties": {
    "addr:full":"3365 Tamiami Trl Port Charlotte FL 33952",
    "addr:housenumber":"3365",
    "addr:postcode":"33952",
    "addr:street":"Tamiami Trl",
    "iso:country":"US",
    "sg:address":"3365 Tamiami Trl",
    "sg:city":"Port Charlotte",
    "sg:classifiers":[
        {
            "category":"Retail",
            "subcategory":"Laundry & Dry Cleaning",
            "type":"Services"
        }
    ],
    "sg:phone":"+1 941 629 5944",
    "sg:postcode":"33952",
    "sg:province":"FL",
    "sg:tags":[
        "cleaners"
    ],
    "wof:name":"J & J Cleaners",
    "wof:placetype":"venue"
},
  "geometry": {"coordinates":[-82.09564399999999,26.980015],"type":"Point"}
}