{
  "type": "Feature",
  "properties": {
    "iso:country":"US",
    "sg:address":"2330 NE 8th Rd",
    "sg:city":"Ocala",
    "sg:classifiers":[
        {
            "category":"Communications",
            "subcategory":"Film & Video Production",
            "type":"Services"
        }
    ],
    "sg:phone":"+1 352 620 0686",
    "sg:postcode":"34470",
    "sg:province":"FL",
    "sg:tags":[
        "taping"
    ],
    "sg:website":"www.dillonvideo.com",
    "wof:name":"Dillon Video & Film Prdctns",
    "wof:placetype":"venue"
},
  "geometry": {"coordinates":[-82.128114,29.208139],"type":"Point"}
}