{
  "type": "Feature",
  "properties": {
    "iso:country":"US",
    "sg:address":"2254 SW 182nd Way",
    "sg:city":"Miramar",
    "sg:classifiers":[
        {
            "category":"Wholesale",
            "subcategory":"Apparel",
            "type":"Manufacturing & Wholesale Goods"
        }
    ],
    "sg:phone":"+1 954 431 1796",
    "sg:postcode":"33029",
    "sg:province":"FL",
    "sg:tags":[
        "fabric"
    ],
    "wof:name":"R G Couture",
    "wof:placetype":"venue"
},
  "geometry": {"coordinates":[-80.389987,25.988669],"type":"Point"}
}