{
  "type": "Feature",
  "properties": {
    "iso:country":"US",
    "sg:address":"319 SW 12th Ter",
    "sg:city":"Cape Coral",
    "sg:classifiers":[
        {
            "category":"Professional",
            "type":"Services"
        }
    ],
    "sg:phone":"+1 239 458 2290",
    "sg:postcode":"33991",
    "sg:province":"FL",
    "sg:tags":[
        "establishment"
    ],
    "wof:name":"Step Savers",
    "wof:placetype":"venue"
},
  "geometry": {"coordinates":[-81.980591,26.63108],"type":"Point"}
}