{
  "type": "Feature",
  "properties": {
    "addr:full":"10827 NW 27th Ave Miami FL 33167",
    "addr:housenumber":"10827",
    "addr:postcode":"33167",
    "addr:street":"Nw 27Th Ave",
    "iso:country":"US",
    "sg:address":"10827 NW 27th Ave",
    "sg:city":"Miami",
    "sg:classifiers":[
        {
            "category":"Government",
            "subcategory":"Office",
            "type":"Public Place"
        }
    ],
    "sg:phone":"+1 305 693 2390",
    "sg:postcode":"33167",
    "sg:province":"FL",
    "sg:tags":[
        "state",
        "resource"
    ],
    "wof:name":"Economic Self-Sufficiency Ofc",
    "wof:placetype":"venue"
},
  "geometry": {"coordinates":[-80.24269099999999,25.874255],"type":"Point"}
}