{
  "type": "Feature",
  "properties": {
    "iso:country":"US",
    "sg:address":"3493 E Colonial Dr",
    "sg:city":"Orlando",
    "sg:classifiers":[
        {
            "category":"Shopping",
            "subcategory":"Clothing, Apparel, & Fashions",
            "type":"Retail Goods"
        }
    ],
    "sg:phone":"+1 407 896 7020",
    "sg:postcode":"32803",
    "sg:province":"FL",
    "sg:tags":[
        "sportswear"
    ],
    "wof:name":"Demo",
    "wof:placetype":"venue"
},
  "geometry": {"coordinates":[-81.338353,28.553495],"type":"Point"}
}