{
  "type": "Feature",
  "properties": {
    "addr:full":"4523 26th St W Bradenton FL 34207",
    "addr:housenumber":"4523",
    "addr:postcode":"34207",
    "addr:street":"26Th St W",
    "iso:country":"US",
    "sg:address":"4523 26th St W",
    "sg:city":"Bradenton",
    "sg:classifiers":[
        {
            "category":"Restaurant",
            "type":"Food & Drink"
        }
    ],
    "sg:phone":"+1 941 753 8971",
    "sg:postcode":"34207",
    "sg:province":"FL",
    "sg:tags":[
        "eating"
    ],
    "wof:name":"Twigys Pizza",
    "wof:placetype":"venue"
},
  "geometry": {"coordinates":[-82.587473,27.460562],"type":"Point"}
}