{
  "type": "Feature",
  "properties": {
    "iso:country":"US",
    "sg:address":"10 Arthur Dr",
    "sg:city":"Lynn Haven",
    "sg:classifiers":[
        {
            "category":"Manufacturing",
            "subcategory":"Tools & Machinery",
            "type":"Manufacturing & Wholesale Goods"
        }
    ],
    "sg:phone":"+1 850 265 3611",
    "sg:postcode":"32444",
    "sg:province":"FL",
    "sg:tags":[
        "devices"
    ],
    "sg:website":"www.merrick-inc.com",
    "wof:name":"Merrick Industries Inc",
    "wof:placetype":"venue"
},
  "geometry": {"coordinates":[-85.667023,30.243216],"type":"Point"}
}