{
  "type": "Feature",
  "properties": {
    "addr:full":"2600 N Military Trl Boca Raton FL 33431",
    "addr:housenumber":"2600",
    "addr:postcode":"33431",
    "addr:street":"N Military Trl",
    "iso:country":"US",
    "sg:address":"2600 N Military Trl",
    "sg:city":"Boca Raton",
    "sg:classifiers":[
        {
            "category":"Health Services",
            "subcategory":"Doctor",
            "type":"Services"
        }
    ],
    "sg:phone":"+1 561 997 2323",
    "sg:postcode":"33431",
    "sg:province":"FL",
    "wof:name":"Martin Polin DMD",
    "wof:placetype":"venue"
},
  "geometry": {"coordinates":[-80.120999,26.370915],"type":"Point"}
}