{
  "type": "Feature",
  "properties": {
    "iso:country":"US",
    "sg:address":"3767 Peaceful Pl",
    "sg:city":"Orlando",
    "sg:classifiers":[
        {
            "category":"Social Services",
            "subcategory":"Child Care",
            "type":"Services"
        }
    ],
    "sg:phone":"+1 407 293 8759",
    "sg:postcode":"32810",
    "sg:province":"FL",
    "sg:tags":[
        "day"
    ],
    "wof:name":"Bill S Land Care",
    "wof:placetype":"venue"
},
  "geometry": {"coordinates":[-81.42597000000001,28.634998],"type":"Point"}
}