{
  "type": "Feature",
  "properties": {
    "addr:full":"670 Glades Rd Boca Raton FL 33432",
    "addr:housenumber":"670",
    "addr:postcode":"33432",
    "addr:street":"Glades Rd",
    "iso:country":"US",
    "sg:address":"670 Glades Rd",
    "sg:city":"Boca Raton",
    "sg:classifiers":[
        {
            "category":"Professional",
            "subcategory":"Accounting & Tax Preparation",
            "type":"Services"
        }
    ],
    "sg:phone":"+1 561 391 6467",
    "sg:postcode":"33432",
    "sg:province":"FL",
    "sg:tags":[
        "billing"
    ],
    "wof:name":"Surgical Associates-Palm Beach",
    "wof:placetype":"venue"
},
  "geometry": {"coordinates":[-80.099824,26.363718],"type":"Point"}
}