{
  "type": "Feature",
  "properties": {
    "iso:country":"US",
    "sg:address":"109 Gretchen Ave S",
    "sg:city":"Lehigh Acres",
    "sg:classifiers":[
        {
            "category":"Retail",
            "subcategory":"Auto Repair",
            "type":"Services"
        }
    ],
    "sg:phone":"+1 239 369 7020",
    "sg:postcode":"33973",
    "sg:province":"FL",
    "sg:tags":[
        "repairing",
        "automobile"
    ],
    "wof:name":"M & M Automotive & Repair",
    "wof:placetype":"venue"
},
  "geometry": {"coordinates":[-81.71482899999999,26.610128],"type":"Point"}
}