{
  "type": "Feature",
  "properties": {
    "iso:country":"US",
    "sg:address":"300 E Nine Mile Rd",
    "sg:city":"Pensacola",
    "sg:classifiers":[
        {
            "category":"Autos & Motor Vehicles",
            "subcategory":"Automobile Sales",
            "type":"Retail Goods"
        }
    ],
    "sg:phone":"+1 850 475 7172",
    "sg:postcode":"32514",
    "sg:province":"FL",
    "sg:tags":[
        "car",
        "dealer"
    ],
    "wof:name":"KOOL Cruisers Auto Sales",
    "wof:placetype":"venue"
},
  "geometry": {"coordinates":[-87.26119799999999,30.532985],"type":"Point"}
}