{
  "type": "Feature",
  "properties": {
    "iso:country":"US",
    "sg:address":"12793 Maiden Cane Ln",
    "sg:city":"Bonita Springs",
    "sg:classifiers":[
        {
            "category":"Shopping",
            "subcategory":"Clothing, Apparel, & Fashions",
            "type":"Retail Goods"
        }
    ],
    "sg:phone":"+1 239 949 9386",
    "sg:postcode":"34135",
    "sg:province":"FL",
    "wof:name":"Chix With Stix Inc",
    "wof:placetype":"venue"
},
  "geometry": {"coordinates":[-81.740882,26.319299],"type":"Point"}
}