{
  "type": "Feature",
  "properties": {
    "addr:full":"1000 NW 33rd St Pompano Beach FL 33064",
    "addr:housenumber":"1000",
    "addr:postcode":"33064",
    "addr:street":"Nw 33Rd St",
    "iso:country":"US",
    "sg:address":"1000 NW 33rd St",
    "sg:city":"Pompano Beach",
    "sg:classifiers":[
        {
            "category":"Wholesale",
            "subcategory":"Electrical",
            "type":"Manufacturing & Wholesale Goods"
        }
    ],
    "sg:phone":"+1 954 977 6651",
    "sg:postcode":"33064",
    "sg:province":"FL",
    "wof:name":"GE",
    "wof:placetype":"venue"
},
  "geometry": {"coordinates":[-80.14257600000001,26.271036],"type":"Point"}
}