{
  "type": "Feature",
  "properties": {
    "addr:full":"385 W Cowles St Englewood FL 34223",
    "addr:housenumber":"385",
    "addr:postcode":"34223",
    "addr:street":"W Cowles St",
    "iso:country":"US",
    "sg:address":"385 W Cowles St",
    "sg:city":"Englewood",
    "sg:classifiers":[
        {
            "category":"Building & Trades",
            "subcategory":"Construction",
            "type":"Services"
        }
    ],
    "sg:phone":"+1 941 475 9547",
    "sg:postcode":"34223",
    "sg:province":"FL",
    "sg:tags":[
        "carpenter"
    ],
    "wof:name":"Ron Phillips Finish Carpentry",
    "wof:placetype":"venue"
},
  "geometry": {"coordinates":[-82.359725,26.958498],"type":"Point"}
}