{
  "type": "Feature",
  "properties": {
    "iso:country":"US",
    "sg:address":"3333 Tamiami Trl",
    "sg:city":"Sarasota",
    "sg:classifiers":[
        {
            "category":"Personal",
            "subcategory":"Barber",
            "type":"Services"
        }
    ],
    "sg:phone":"+1 941 355 1292",
    "sg:postcode":"34234",
    "sg:province":"FL",
    "wof:name":"His Excellency Barber Style",
    "wof:placetype":"venue"
},
  "geometry": {"coordinates":[-82.55074500000001,27.364601],"type":"Point"}
}