{
  "type": "Feature",
  "properties": {
    "addr:full":"1389 N Tamiami Trl Fort Myers FL 33903",
    "addr:housenumber":"1389",
    "addr:postcode":"fl 33903",
    "addr:street":"N Tamiami Trl",
    "iso:country":"US",
    "sg:address":"1389 N Tamiami Trl",
    "sg:city":"Fort Myers",
    "sg:classifiers":[
        {
            "category":"Travel",
            "subcategory":"Hotels & Motels",
            "type":"Entertainment"
        }
    ],
    "sg:phone":"+1 239 995 4289",
    "sg:postcode":"33903",
    "sg:province":"FL",
    "wof:name":"Courtesy Court",
    "wof:placetype":"venue"
},
  "geometry": {"coordinates":[-81.882845,26.671787],"type":"Point"}
}