{
  "type": "Feature",
  "properties": {
    "iso:country":"US",
    "sg:address":"21120 NE 18th Ct",
    "sg:city":"Miami",
    "sg:classifiers":[
        {
            "category":"Building & Trades",
            "subcategory":"Construction",
            "type":"Services"
        }
    ],
    "sg:phone":"+1 305 932 3480",
    "sg:postcode":"33179",
    "sg:province":"FL",
    "sg:tags":[
        "equipment",
        "contractor",
        "wallpaper",
        "removing",
        "hanging"
    ],
    "sg:website":"www.superiorpaperhanging.com",
    "wof:name":"Superior Paper Hanging By Steve Auerbach Inc",
    "wof:placetype":"venue"
},
  "geometry": {"coordinates":[-80.16458299999999,25.969421],"type":"Point"}
}