{
  "type": "Feature",
  "properties": {
    "addr:full":"718 Margaret Sq Winter Park FL 32789",
    "addr:housenumber":"718",
    "addr:postcode":"32789",
    "addr:street":"Margaret Sq",
    "iso:country":"US",
    "sg:address":"718 Margaret Sq",
    "sg:city":"Winter Park",
    "sg:classifiers":[
        {
            "category":"Social Services",
            "type":"Services"
        }
    ],
    "sg:phone":"+1 407 645 1193",
    "sg:postcode":"32789",
    "sg:province":"FL",
    "sg:tags":[
        "academic",
        "programming"
    ],
    "wof:name":"Esteem For Florida Youth Inc",
    "wof:placetype":"venue"
},
  "geometry": {"coordinates":[-81.373817,28.610093],"type":"Point"}
}