{
  "type": "Feature",
  "properties": {
    "addr:full":"2327 Salzedo St Coral Gables FL 33134",
    "addr:housenumber":"2327",
    "addr:postcode":"33134",
    "addr:street":"Salzedo St",
    "iso:country":"US",
    "sg:address":"2327 Salzedo St",
    "sg:city":"Coral Gables",
    "sg:classifiers":[
        {
            "category":"Government",
            "subcategory":"Office",
            "type":"Public Place"
        }
    ],
    "sg:phone":"+1 305 460 5216",
    "sg:postcode":"33134",
    "sg:province":"FL",
    "sg:tags":[
        "village"
    ],
    "wof:name":"Coral Gables Historic Restorat",
    "wof:placetype":"venue"
},
  "geometry": {"coordinates":[-80.26068600000001,25.750754],"type":"Point"}
}