{
  "type": "Feature",
  "properties": {
    "addr:full":"328 N Ocean Blvd Delray Beach FL 33483",
    "addr:housenumber":"328",
    "addr:postcode":"33483",
    "addr:street":"N Ocean Blvd",
    "iso:country":"US",
    "sg:address":"328 N Ocean Blvd",
    "sg:city":"Delray Beach",
    "sg:classifiers":[
        {
            "category":"Banks & Credit Unions",
            "subcategory":"Investment Brokerage",
            "type":"Services"
        }
    ],
    "sg:phone":"+1 561 279 7471",
    "sg:postcode":"33483",
    "sg:province":"FL",
    "sg:tags":[
        "advisory",
        "financial"
    ],
    "wof:name":"Cutler Securities",
    "wof:placetype":"venue"
},
  "geometry": {"coordinates":[-80.057363,26.467388],"type":"Point"}
}