{
  "type": "Feature",
  "properties": {
    "iso:country":"US",
    "sg:address":"1821 W Oakland Park Blvd",
    "sg:city":"Fort Lauderdale",
    "sg:classifiers":[
        {
            "category":"Banks & Credit Unions",
            "subcategory":"Bank",
            "type":"Services"
        }
    ],
    "sg:phone":"+1 954 731 7500",
    "sg:postcode":"33311",
    "sg:province":"FL",
    "sg:tags":[
        "lender",
        "correspondent"
    ],
    "wof:name":"Smart Mortgages",
    "wof:placetype":"venue"
},
  "geometry": {"coordinates":[-80.168555,26.165797],"type":"Point"}
}