{
  "type": "Feature",
  "properties": {
    "addr:full":"8143 S John Young Pkwy Orlando FL 32819",
    "addr:housenumber":"8143",
    "addr:postcode":"32819",
    "addr:street":"S John Young Pkwy",
    "iso:country":"US",
    "sg:address":"8143 S John Young Pkwy",
    "sg:city":"Orlando",
    "sg:classifiers":[
        {
            "category":"Shopping",
            "subcategory":"Jewelry",
            "type":"Retail Goods"
        }
    ],
    "sg:phone":"+1 407 345 5307",
    "sg:postcode":"32819",
    "sg:province":"FL",
    "wof:name":"Friedmans Jewelers",
    "wof:placetype":"venue"
},
  "geometry": {"coordinates":[-81.427598,28.451471],"type":"Point"}
}