{
  "type": "Feature",
  "properties": {
    "iso:country":"US",
    "sg:address":"2535 E 13th St",
    "sg:city":"Panama City",
    "sg:classifiers":[
        {
            "category":"Real Estate",
            "subcategory":"Real Estate Agent",
            "type":"Services"
        }
    ],
    "sg:phone":"+1 850 874 2844",
    "sg:postcode":"32401",
    "sg:province":"FL",
    "wof:name":"Jack H Scholder",
    "wof:placetype":"venue"
},
  "geometry": {"coordinates":[-85.62720899999999,30.171329],"type":"Point"}
}