{
  "type": "Feature",
  "properties": {
    "iso:country":"US",
    "sg:address":"724 S Pennock Ln",
    "sg:city":"Jupiter",
    "sg:classifiers":[
        {
            "category":"Building & Trades",
            "subcategory":"Construction",
            "type":"Services"
        }
    ],
    "sg:phone":"+1 561 743 8395",
    "sg:postcode":"33458",
    "sg:province":"FL",
    "sg:tags":[
        "floor",
        "laying",
        "contractor"
    ],
    "wof:name":"Surface Preparation Technology",
    "wof:placetype":"venue"
},
  "geometry": {"coordinates":[-80.110096,26.928822],"type":"Point"}
}