{
  "type": "Feature",
  "properties": {
    "iso:country":"US",
    "sg:address":"630 Old Dixie Hwy SW",
    "sg:city":"Vero Beach",
    "sg:classifiers":[
        {
            "category":"Personal",
            "subcategory":"Beauty Salon",
            "type":"Services"
        }
    ],
    "sg:phone":"+1 772 794 0703",
    "sg:postcode":"32962",
    "sg:province":"FL",
    "wof:name":"Crowning Glory",
    "wof:placetype":"venue"
},
  "geometry": {"coordinates":[-80.381057,27.591474],"type":"Point"}
}