{
  "type": "Feature",
  "properties": {
    "iso:country":"US",
    "sg:address":"8090 Mainline Pkwy",
    "sg:city":"Fort Myers",
    "sg:classifiers":[
        {
            "category":"Building & Trades",
            "subcategory":"Construction",
            "type":"Services"
        }
    ],
    "sg:phone":"+1 239 454 4877",
    "sg:postcode":"33912",
    "sg:province":"FL",
    "sg:tags":[
        "concrete",
        "contractor"
    ],
    "wof:name":"Able & Willing Pavers II Inc",
    "wof:placetype":"venue"
},
  "geometry": {"coordinates":[-81.823053,26.498166],"type":"Point"}
}