{
  "type": "Feature",
  "properties": {
    "iso:country":"US",
    "sg:address":"571 SW 71st Ct",
    "sg:city":"Miami",
    "sg:classifiers":[
        {
            "category":"Professional",
            "type":"Services"
        }
    ],
    "sg:phone":"+1 305 261 4910",
    "sg:postcode":"33144",
    "sg:province":"FL",
    "wof:name":"San Pablo Mission Inc",
    "wof:placetype":"venue"
},
  "geometry": {"coordinates":[-80.31033499999999,25.765545],"type":"Point"}
}