{
  "type": "Feature",
  "properties": {
    "addr:full":"8480 Tallahassee Dr NE Saint Petersburg FL 33702",
    "addr:housenumber":"8480",
    "addr:postcode":"33702",
    "addr:street":"Tallahassee Dr Ne",
    "iso:country":"US",
    "sg:address":"8480 Tallahassee Dr NE",
    "sg:city":"Saint Petersburg",
    "sg:classifiers":[
        {
            "category":"Health Services",
            "subcategory":"Doctor",
            "type":"Services"
        }
    ],
    "sg:phone":"+1 727 323 2505",
    "sg:postcode":"33702",
    "sg:province":"FL",
    "sg:tags":[
        "osteopathic"
    ],
    "wof:name":"John C Backe Jr MD",
    "wof:placetype":"venue"
},
  "geometry": {"coordinates":[-82.625601,27.850079],"type":"Point"}
}