{
  "type": "Feature",
  "properties": {
    "addr:full":"9822 Red Reef Ct Fort Myers FL 33919",
    "addr:housenumber":"9822",
    "addr:postcode":"33919",
    "addr:street":"Red Reef Ct",
    "iso:country":"US",
    "sg:address":"9822 Red Reef Ct",
    "sg:city":"Fort Myers",
    "sg:classifiers":[
        {
            "category":"Professional",
            "subcategory":"Management & Consulting",
            "type":"Services"
        }
    ],
    "sg:phone":"+1 239 454 0138",
    "sg:postcode":"33919",
    "sg:province":"FL",
    "sg:tags":[
        "consultant"
    ],
    "wof:name":"Jack D Adair Consultant",
    "wof:placetype":"venue"
},
  "geometry": {"coordinates":[-81.916967,26.56386],"type":"Point"}
}