{
  "type": "Feature",
  "properties": {
    "iso:country":"US",
    "sg:address":"660 Hill Rd",
    "sg:city":"Lake Placid",
    "sg:classifiers":[
        {
            "category":"Building & Trades",
            "subcategory":"Construction",
            "type":"Services"
        }
    ],
    "sg:phone":"+1 863 699 2981",
    "sg:postcode":"33852",
    "sg:province":"FL",
    "sg:tags":[
        "house"
    ],
    "wof:name":"Michael Padovano Installation",
    "wof:placetype":"venue"
},
  "geometry": {"coordinates":[-81.354972,27.31194],"type":"Point"}
}