{
  "type": "Feature",
  "properties": {
    "iso:country":"US",
    "sg:address":"1600 Central Florida Pkwy",
    "sg:city":"Orlando",
    "sg:classifiers":[
        {
            "category":"Shopping",
            "subcategory":"Stationery & Office Supplies",
            "type":"Retail Goods"
        }
    ],
    "sg:phone":"+1 407 816 5005",
    "sg:postcode":"32837",
    "sg:province":"FL",
    "sg:tags":[
        "machine",
        "copy",
        "envelope",
        "store"
    ],
    "wof:name":"Copiton USA",
    "wof:placetype":"venue"
},
  "geometry": {"coordinates":[-81.396812,28.40674],"type":"Point"}
}