{
  "type": "Feature",
  "properties": {
    "addr:full":"11077 Biscayne Blvd Miami FL 33161",
    "addr:housenumber":"11077",
    "addr:postcode":"33161",
    "addr:street":"Biscayne Blvd",
    "iso:country":"US",
    "sg:address":"11077 Biscayne Blvd",
    "sg:city":"Miami",
    "sg:classifiers":[
        {
            "category":"Health Services",
            "subcategory":"Optometrist",
            "type":"Services"
        }
    ],
    "sg:phone":"+1 305 893 9201",
    "sg:postcode":"33161",
    "sg:province":"FL",
    "wof:name":"Rainbow Eye Center PA",
    "wof:placetype":"venue"
},
  "geometry": {"coordinates":[-80.167981,25.878056],"type":"Point"}
}