{
  "type": "Feature",
  "properties": {
    "addr:full":"1136 21st Ct Vero Beach FL 32960",
    "addr:housenumber":"1136",
    "addr:postcode":"32960",
    "addr:street":"21St Ct",
    "iso:country":"US",
    "sg:address":"1136 21st Ct",
    "sg:city":"Vero Beach",
    "sg:classifiers":[
        {
            "category":"Building & Trades",
            "subcategory":"Construction",
            "type":"Services"
        }
    ],
    "sg:phone":"+1 772 567 1655",
    "sg:postcode":"32960",
    "sg:province":"FL",
    "sg:tags":[
        "paving",
        "contractor"
    ],
    "wof:name":"Trodglen Paving Inc",
    "wof:placetype":"venue"
},
  "geometry": {"coordinates":[-80.40727,27.622441],"type":"Point"}
}