{
  "type": "Feature",
  "properties": {
    "addr:full":"924 N Federal Hwy Fort Lauderdale FL 33304",
    "addr:housenumber":"924",
    "addr:postcode":"33304",
    "addr:street":"N Federal Hwy",
    "iso:country":"US",
    "sg:address":"924 N Federal Hwy",
    "sg:city":"Fort Lauderdale",
    "sg:classifiers":[
        {
            "category":"Insurance",
            "subcategory":"Insurance Agent",
            "type":"Services"
        }
    ],
    "sg:phone":"+1 954 761 1499",
    "sg:postcode":"33304",
    "sg:province":"FL",
    "sg:website":"www.victoriaparkins.com",
    "wof:name":"Allstate Insurance",
    "wof:placetype":"venue"
},
  "geometry": {"coordinates":[-80.137548,26.135529],"type":"Point"}
}