{
  "type": "Feature",
  "properties": {
    "iso:country":"US",
    "sg:address":"1107 1st Ave",
    "sg:city":"Titusville",
    "sg:classifiers":[
        {
            "category":"Banks & Credit Unions",
            "subcategory":"Investment Brokerage",
            "type":"Services"
        }
    ],
    "sg:phone":"+1 321 567 0341",
    "sg:postcode":"32780",
    "sg:province":"FL",
    "sg:tags":[
        "consultant",
        "planning",
        "financial"
    ],
    "wof:name":"Express Financial",
    "wof:placetype":"venue"
},
  "geometry": {"coordinates":[-80.81070800000001,28.605171],"type":"Point"}
}