{
  "type": "Feature",
  "properties": {
    "addr:full":"9599 SW 70th Ave Miami FL 33156",
    "addr:housenumber":"9599",
    "addr:postcode":"33156",
    "addr:street":"Sw 70Th Ave",
    "iso:country":"US",
    "sg:address":"9599 SW 70th Ave",
    "sg:city":"Miami",
    "sg:classifiers":[
        {
            "category":"Manufacturing",
            "subcategory":"Retail Goods",
            "type":"Manufacturing & Wholesale Goods"
        }
    ],
    "sg:phone":"+1 305 661 3489",
    "sg:postcode":"33156",
    "sg:province":"FL",
    "sg:tags":[
        "product",
        "contract",
        "mfg"
    ],
    "wof:name":"Sherry Mfg Far East Co In",
    "wof:placetype":"venue"
},
  "geometry": {"coordinates":[-80.308983,25.68154],"type":"Point"}
}