{
  "type": "Feature",
  "properties": {
    "iso:country":"US",
    "sg:address":"2771 Hyde Park Rd",
    "sg:city":"Jacksonville",
    "sg:classifiers":[
        {
            "category":"Retail",
            "subcategory":"Auto Repair",
            "type":"Services"
        }
    ],
    "sg:phone":"+1 904 779 1213",
    "sg:postcode":"32210",
    "sg:province":"FL",
    "sg:tags":[
        "shop"
    ],
    "wof:name":"T & D Mobile Tops",
    "wof:placetype":"venue"
},
  "geometry": {"coordinates":[-81.73624599999999,30.27247],"type":"Point"}
}