{
  "type": "Feature",
  "properties": {
    "addr:full":"15010 113th Ave N Largo FL 33774",
    "addr:housenumber":"15010",
    "addr:postcode":"33774",
    "addr:street":"113Th Ave N",
    "iso:country":"US",
    "sg:address":"15010 113th Ave N",
    "sg:city":"Largo",
    "sg:classifiers":[
        {
            "category":"Real Estate",
            "subcategory":"Developer",
            "type":"Services"
        },
        {
            "category":"Real Estate",
            "subcategory":"Real Estate Operator",
            "type":"Services"
        }
    ],
    "sg:phone":"+1 727 596 5163",
    "sg:postcode":"33774",
    "sg:province":"FL",
    "sg:tags":[
        "mobile",
        "home",
        "site"
    ],
    "wof:name":"Coquina Cove Trailer Park",
    "wof:placetype":"venue"
},
  "geometry": {"coordinates":[-82.848842,27.875667],"type":"Point"}
}