{
  "type": "Feature",
  "properties": {
    "iso:country":"US",
    "sg:address":"3627 Tyrone Blvd N",
    "sg:city":"St Petersburg",
    "sg:classifiers":[
        {
            "category":"Cinema",
            "subcategory":"Movie Rental",
            "type":"Entertainment"
        }
    ],
    "sg:phone":"+1 727 347 1866",
    "sg:postcode":"33710",
    "sg:province":"FL",
    "sg:tags":[
        "leasing",
        "video",
        "disc",
        "tape"
    ],
    "wof:name":"Good Vibrations",
    "wof:placetype":"venue"
},
  "geometry": {"coordinates":[-82.748548,27.805798],"type":"Point"}
}