{
  "type": "Feature",
  "properties": {
    "addr:full":"8450 NW 164th St Hialeah FL 33016",
    "addr:housenumber":"8450",
    "addr:postcode":"33016",
    "addr:street":"Nw 164Th St",
    "iso:country":"US",
    "sg:address":"8450 NW 164th St",
    "sg:city":"Hialeah",
    "sg:classifiers":[
        {
            "category":"Building & Trades",
            "subcategory":"Construction",
            "type":"Services"
        }
    ],
    "sg:phone":"+1 305 322 0384",
    "sg:postcode":"33016",
    "sg:province":"FL",
    "sg:tags":[
        "contractor"
    ],
    "wof:name":"One Way Striping Inc",
    "wof:placetype":"venue"
},
  "geometry": {"coordinates":[-80.338814,25.922403],"type":"Point"}
}