{
  "type": "Feature",
  "properties": {
    "iso:country":"US",
    "sg:address":"6111 Mikes Ln",
    "sg:city":"Pensacola",
    "sg:classifiers":[
        {
            "category":"Autos & Motor Vehicles",
            "subcategory":"Auto Supplies",
            "type":"Retail Goods"
        }
    ],
    "sg:phone":"+1 850 944 5081",
    "sg:postcode":"32526",
    "sg:province":"FL",
    "sg:tags":[
        "transmission",
        "automobile",
        "parts",
        "part",
        "transmissions-other",
        "accessories-wholesale",
        "manufacturer"
    ],
    "wof:name":"Speedy Transmissions",
    "wof:placetype":"venue"
},
  "geometry": {"coordinates":[-87.302134,30.463021],"type":"Point"}
}