{
  "type": "Feature",
  "properties": {
    "iso:country":"US",
    "sg:address":"1375 S Semoran Blvd",
    "sg:city":"Winter Park",
    "sg:classifiers":[
        {
            "category":"Wholesale",
            "subcategory":"Electrical",
            "type":"Manufacturing & Wholesale Goods"
        }
    ],
    "sg:phone":"+1 407 671 0440",
    "sg:postcode":"32792",
    "sg:province":"FL",
    "sg:tags":[
        "consulting",
        "business"
    ],
    "wof:name":"N E C Bus Netwrk Solutions",
    "wof:placetype":"venue"
},
  "geometry": {"coordinates":[-81.308224,28.580057],"type":"Point"}
}