{
  "type": "Feature",
  "properties": {
    "iso:country":"US",
    "sg:address":"703 Clubwood Ct",
    "sg:city":"Winter Springs",
    "sg:classifiers":[
        {
            "category":"Professional",
            "subcategory":"Management & Consulting",
            "type":"Services"
        }
    ],
    "sg:phone":"+1 407 695 4922",
    "sg:postcode":"32708",
    "sg:province":"FL",
    "sg:tags":[
        "consultant",
        "business"
    ],
    "wof:name":"J Howell & Assoc Inc",
    "wof:placetype":"venue"
},
  "geometry": {"coordinates":[-81.264567,28.682905],"type":"Point"}
}