{
  "type": "Feature",
  "properties": {
    "addr:full":"369 Blanding Blvd Orange Park FL 32073",
    "addr:housenumber":"369",
    "addr:postcode":"32073",
    "addr:street":"Blanding Blvd",
    "iso:country":"US",
    "sg:address":"369 Blanding Blvd",
    "sg:city":"Orange Park",
    "sg:classifiers":[
        {
            "category":"Retail",
            "subcategory":"Repair Shop",
            "type":"Services"
        }
    ],
    "sg:phone":"+1 904 276 1275",
    "sg:postcode":"32073",
    "sg:province":"FL",
    "sg:tags":[
        "furniture"
    ],
    "wof:name":"C & S Furniture Restoration",
    "wof:placetype":"venue"
},
  "geometry": {"coordinates":[-81.747635,30.16615],"type":"Point"}
}