{
  "type": "Feature",
  "properties": {
    "iso:country":"US",
    "sg:address":"20950 NE 27th Ct",
    "sg:city":"Miami",
    "sg:classifiers":[
        {
            "category":"Health Services",
            "subcategory":"Doctor",
            "type":"Services"
        }
    ],
    "sg:phone":"+1 305 682 2151",
    "sg:postcode":"33180",
    "sg:province":"FL",
    "sg:tags":[
        "physician",
        "oncology",
        "surgeons",
        "surgeon"
    ],
    "wof:name":"21st Century Oncology",
    "wof:placetype":"venue"
},
  "geometry": {"coordinates":[-80.146603,25.969426],"type":"Point"}
}