{
  "type": "Feature",
  "properties": {
    "iso:country":"US",
    "sg:address":"301 Marion St",
    "sg:city":"Daytona Beach",
    "sg:classifiers":[
        {
            "category":"Home & Garden",
            "subcategory":"Building Materials",
            "type":"Retail Goods"
        }
    ],
    "sg:phone":"+1 386 226 3807",
    "sg:postcode":"32114",
    "sg:province":"FL",
    "sg:tags":[
        "lumber"
    ],
    "wof:name":"Salvage Depot",
    "wof:placetype":"venue"
},
  "geometry": {"coordinates":[-81.022756,29.203912],"type":"Point"}
}