{
  "type": "Feature",
  "properties": {
    "addr:full":"10870 Harts Rd Jacksonville FL 32218",
    "addr:housenumber":"10870",
    "addr:postcode":"32218",
    "addr:street":"Harts Rd",
    "iso:country":"US",
    "sg:address":"10870 Harts Rd",
    "sg:city":"Jacksonville",
    "sg:classifiers":[
        {
            "category":"Professional",
            "subcategory":"Business Services",
            "type":"Services"
        }
    ],
    "sg:phone":"+1 904 762 7799",
    "sg:postcode":"32218",
    "sg:province":"FL",
    "sg:tags":[
        "inspection"
    ],
    "wof:name":"Recon Inspection",
    "wof:placetype":"venue"
},
  "geometry": {"coordinates":[-81.658323,30.432982],"type":"Point"}
}