{
  "type": "Feature",
  "properties": {
    "iso:country":"US",
    "sg:address":"36703 Chancey Rd",
    "sg:city":"Zephyrhills",
    "sg:classifiers":[
        {
            "category":"Wholesale",
            "subcategory":"Farm Supplies",
            "type":"Manufacturing & Wholesale Goods"
        },
        {
            "category":"Shopping",
            "type":"Retail Goods"
        }
    ],
    "sg:phone":"+1 813 782 1129",
    "sg:postcode":"33541",
    "sg:province":"FL",
    "sg:tags":[
        "feed",
        "merchandise"
    ],
    "wof:name":"Bliss Feed and Supplies",
    "wof:placetype":"venue"
},
  "geometry": {"coordinates":[-82.207307,28.207971],"type":"Point"}
}