{
  "type": "Feature",
  "properties": {
    "iso:country":"US",
    "sg:address":"1517 Ave del Rio",
    "sg:city":"Melbourne",
    "sg:classifiers":[
        {
            "category":"Organizations",
            "subcategory":"Religious Organization",
            "type":"Services"
        }
    ],
    "sg:phone":"+1 321 723 2190",
    "sg:postcode":"32901",
    "sg:province":"FL",
    "wof:name":"Brevard Hindu Mandir",
    "wof:placetype":"venue"
},
  "geometry": {"coordinates":[-80.59493999999999,28.064642],"type":"Point"}
}