{
  "type": "Feature",
  "properties": {
    "addr:full":"2802 Curry Ford Rd Orlando FL 32806",
    "addr:housenumber":"2802",
    "addr:postcode":"32806",
    "addr:street":"Curry Ford Rd",
    "iso:country":"US",
    "sg:address":"2802 Curry Ford Rd",
    "sg:city":"Orlando",
    "sg:classifiers":[
        {
            "category":"Restaurant",
            "type":"Food & Drink"
        }
    ],
    "sg:phone":"+1 407 895 6100",
    "sg:postcode":"32806",
    "sg:province":"FL",
    "sg:tags":[
        "eating"
    ],
    "wof:name":"Papa BS Inc",
    "wof:placetype":"venue"
},
  "geometry": {"coordinates":[-81.347168,28.524209],"type":"Point"}
}