{
  "type": "Feature",
  "properties": {
    "addr:full":"3898 S Osprey Ave Sarasota FL 34239",
    "addr:housenumber":"3898",
    "addr:postcode":"34239",
    "addr:street":"S Osprey Ave",
    "iso:country":"US",
    "sg:address":"3898 S Osprey Ave",
    "sg:city":"Sarasota",
    "sg:classifiers":[
        {
            "category":"Shopping",
            "subcategory":"Bicycles & Sporting Goods",
            "type":"Retail Goods"
        },
        {
            "category":"Sports & Exercise",
            "subcategory":"Bicycle Rental",
            "type":"Entertainment"
        }
    ],
    "sg:phone":"+1 941 366 7702",
    "sg:postcode":"34239",
    "sg:province":"FL",
    "sg:tags":[
        "shop",
        "bicycles-renting",
        "bicycles-repair"
    ],
    "sg:website":"http://www.villagebikes.com",
    "wof:name":"Village Bikes",
    "wof:placetype":"venue"
},
  "geometry": {"coordinates":[-82.533508,27.29899],"type":"Point"}
}