{
  "type": "Feature",
  "properties": {
    "iso:country":"US",
    "sg:address":"455 Richview Park Cir E",
    "sg:city":"Tallahassee",
    "sg:classifiers":[
        {
            "category":"Building & Trades",
            "subcategory":"Landscaping Services",
            "type":"Services"
        }
    ],
    "sg:phone":"+1 850 878 7236",
    "sg:postcode":"32301",
    "sg:province":"FL",
    "sg:tags":[
        "landscape"
    ],
    "wof:name":"Wayne Parker",
    "wof:placetype":"venue"
},
  "geometry": {"coordinates":[-84.229823,30.437119],"type":"Point"}
}