{
  "type": "Feature",
  "properties": {
    "iso:country":"US",
    "sg:address":"1605 Glenhaven Cir",
    "sg:city":"Ocoee",
    "sg:classifiers":[
        {
            "category":"Freight",
            "type":"Transportation"
        }
    ],
    "sg:phone":"+1 407 294 0892",
    "sg:postcode":"34761",
    "sg:province":"FL",
    "sg:tags":[
        "operator",
        "distance",
        "local",
        "long",
        "trucking"
    ],
    "wof:name":"RPS Trucking Company",
    "wof:placetype":"venue"
},
  "geometry": {"coordinates":[-81.51812700000001,28.576468],"type":"Point"}
}