{
  "type": "Feature",
  "properties": {
    "addr:full":"7777 N Wickham Rd Melbourne FL 32940",
    "addr:housenumber":"7777",
    "addr:postcode":"32940",
    "addr:street":"N Wickham Rd",
    "iso:country":"US",
    "sg:address":"7777 N Wickham Rd",
    "sg:city":"Melbourne",
    "sg:classifiers":[
        {
            "category":"Shopping",
            "subcategory":"Florist",
            "type":"Retail Goods"
        }
    ],
    "sg:phone":"+1 321 253 3900",
    "sg:postcode":"32940",
    "sg:province":"FL",
    "wof:name":"Silk and Such",
    "wof:placetype":"venue"
},
  "geometry": {"coordinates":[-80.69578199999999,28.230565],"type":"Point"}
}