{
  "type": "Feature",
  "properties": {
    "iso:country":"US",
    "sg:address":"1201 NW 16th St Rm B-1206",
    "sg:city":"Miami",
    "sg:classifiers":[
        {
            "category":"Education",
            "subcategory":"University",
            "type":"Public Place"
        }
    ],
    "sg:phone":"+1 305 575 3195",
    "sg:postcode":"33125",
    "sg:province":"FL",
    "sg:tags":[
        "college"
    ],
    "sg:website":"http://www.miami.edu",
    "wof:name":"Miller, Leonard M School Of Medicine",
    "wof:placetype":"venue"
},
  "geometry": {"coordinates":[-80.215149,25.790461],"type":"Point"}
}