{
  "type": "Feature",
  "properties": {
    "addr:full":"865 NW Federal Hwy Stuart FL 34994",
    "addr:housenumber":"865",
    "addr:postcode":"34994",
    "addr:street":"Nw Federal Hwy",
    "iso:country":"US",
    "sg:address":"865 NW Federal Hwy",
    "sg:city":"Stuart",
    "sg:classifiers":[
        {
            "category":"Social Services",
            "type":"Services"
        }
    ],
    "sg:phone":"+1 772 692 3679",
    "sg:postcode":"34994",
    "sg:province":"FL",
    "sg:tags":[
        "professional",
        "counselor"
    ],
    "wof:name":"Solutions Center-Personal",
    "wof:placetype":"venue"
},
  "geometry": {"coordinates":[-80.260876,27.21504],"type":"Point"}
}