{
  "type": "Feature",
  "properties": {
    "addr:full":"31333 Round Lake Rd Mount Dora FL 32757",
    "addr:housenumber":"31333",
    "addr:postcode":"32757",
    "addr:street":"Round Lake Rd",
    "iso:country":"US",
    "sg:address":"31333 Round Lake Rd",
    "sg:city":"Mount Dora",
    "sg:classifiers":[
        {
            "category":"Education",
            "subcategory":"School",
            "type":"Public Place"
        }
    ],
    "sg:phone":"+1 352 385 4399",
    "sg:postcode":"32757",
    "sg:province":"FL",
    "wof:name":"Round Lake Elementary School",
    "wof:placetype":"venue"
},
  "geometry": {"coordinates":[-81.592895,28.804744],"type":"Point"}
}