{
  "type": "Feature",
  "properties": {
    "addr:full":"1080 94th St Miami Beach FL 33154",
    "addr:housenumber":"1080",
    "addr:postcode":"33154",
    "addr:street":"94Th St",
    "iso:country":"US",
    "sg:address":"1080 94th St",
    "sg:city":"Miami Beach",
    "sg:classifiers":[
        {
            "category":"Professional",
            "subcategory":"Computer Services",
            "type":"Services"
        }
    ],
    "sg:phone":"+1 305 861 1746",
    "sg:postcode":"33154",
    "sg:province":"FL",
    "sg:tags":[
        "datum"
    ],
    "wof:name":"It Works Network Inc",
    "wof:placetype":"venue"
},
  "geometry": {"coordinates":[-80.129508,25.884761],"type":"Point"}
}