{
  "type": "Feature",
  "properties": {
    "iso:country":"US",
    "sg:address":"3606 Jacob Lois Dr",
    "sg:city":"Jacksonville",
    "sg:classifiers":[
        {
            "category":"Restaurant",
            "type":"Food & Drink"
        }
    ],
    "sg:phone":"+1 904 768 5835",
    "sg:postcode":"32218",
    "sg:province":"FL",
    "sg:tags":[
        "italian"
    ],
    "wof:name":"Mama D Academy",
    "wof:placetype":"venue"
},
  "geometry": {"coordinates":[-81.707342,30.446812],"type":"Point"}
}