{
  "type": "Feature",
  "properties": {
    "iso:country":"US",
    "sg:address":"10232 State Rd 52",
    "sg:city":"Hudson",
    "sg:classifiers":[
        {
            "category":"Retail",
            "subcategory":"Auto Repair",
            "type":"Services"
        }
    ],
    "sg:phone":"+1 727 856 3303",
    "sg:postcode":"34669",
    "sg:province":"FL",
    "sg:tags":[
        "repairing",
        "automobile"
    ],
    "wof:name":"Alternative Car Care Inc",
    "wof:placetype":"venue"
},
  "geometry": {"coordinates":[-82.648275,28.330865],"type":"Point"}
}