{
  "type": "Feature",
  "properties": {
    "iso:country":"US",
    "sg:address":"5421 Beaumont Center Blvd",
    "sg:city":"Tampa",
    "sg:classifiers":[
        {
            "category":"Professional",
            "subcategory":"Engineering",
            "type":"Services"
        }
    ],
    "sg:phone":"+1 813 885 9600",
    "sg:postcode":"33634",
    "sg:province":"FL",
    "sg:tags":[
        "engineer"
    ],
    "wof:name":"Mechanical Engineering Sltns",
    "wof:placetype":"venue"
},
  "geometry": {"coordinates":[-82.54758,27.996623],"type":"Point"}
}