{
  "type": "Feature",
  "properties": {
    "iso:country":"US",
    "sg:address":"8401 Cambria Ct",
    "sg:city":"New Port Richey",
    "sg:classifiers":[
        {
            "category":"Banks & Credit Unions",
            "subcategory":"Financial Services",
            "type":"Services"
        }
    ],
    "sg:phone":"+1 727 376 5609",
    "sg:postcode":"34653",
    "sg:province":"FL",
    "sg:tags":[
        "company",
        "holding"
    ],
    "wof:name":"Marflem Holdings Inc",
    "wof:placetype":"venue"
},
  "geometry": {"coordinates":[-82.67633600000001,28.230632],"type":"Point"}
}