{
  "type": "Feature",
  "properties": {
    "iso:country":"US",
    "sg:address":"9812 S Dixie Hwy",
    "sg:city":"Miami",
    "sg:classifiers":[
        {
            "category":"Building & Trades",
            "subcategory":"Locksmith",
            "type":"Services"
        }
    ],
    "sg:phone":"+1 786 228 5597",
    "sg:postcode":"33156",
    "sg:province":"FL",
    "sg:tags":[
        "key"
    ],
    "wof:name":"Anywhere Locksmith Service On S Dixie Hwy",
    "wof:placetype":"venue"
},
  "geometry": {"coordinates":[-80.31776600000001,25.67872],"type":"Point"}
}