{
  "type": "Feature",
  "properties": {
    "addr:full":"124 Towne Center Blvd Sanford FL 32771",
    "addr:housenumber":"124",
    "addr:postcode":"32771",
    "addr:street":"Towne Center Blvd",
    "iso:country":"US",
    "sg:address":"124 Towne Center Blvd",
    "sg:city":"Sanford",
    "sg:classifiers":[
        {
            "category":"Government",
            "subcategory":"Office",
            "type":"Public Place"
        }
    ],
    "sg:phone":"+1 407 323 6404",
    "sg:postcode":"32771",
    "sg:province":"FL",
    "sg:tags":[
        "armed",
        "force",
        "recruiting"
    ],
    "wof:name":"US Army Recruiting",
    "wof:placetype":"venue"
},
  "geometry": {"coordinates":[-81.33475300000001,28.809641],"type":"Point"}
}