{
  "type": "Feature",
  "properties": {
    "addr:full":"5906 Blue Beech Ct Fort Lauderdale FL 33319",
    "addr:housenumber":"5906",
    "addr:postcode":"33319",
    "addr:street":"Blue Beech Ct",
    "iso:country":"US",
    "sg:address":"5906 Blue Beech Ct",
    "sg:city":"Fort Lauderdale",
    "sg:classifiers":[
        {
            "category":"Real Estate",
            "subcategory":"Real Estate Agent",
            "type":"Services"
        }
    ],
    "sg:phone":"+1 954 718 6060",
    "sg:postcode":"33319",
    "sg:province":"FL",
    "wof:name":"Mli Realty",
    "wof:placetype":"venue"
},
  "geometry": {"coordinates":[-80.230262,26.193603],"type":"Point"}
}