{
  "type": "Feature",
  "properties": {
    "addr:full":"3610 NW 118th Ave Pompano Beach FL 33065",
    "addr:housenumber":"3610",
    "addr:postcode":"33065",
    "addr:street":"Nw 118Th Ave",
    "iso:country":"US",
    "sg:address":"3610 NW 118th Ave",
    "sg:city":"Pompano Beach",
    "sg:classifiers":[
        {
            "category":"Manufacturing",
            "subcategory":"Printing",
            "type":"Manufacturing & Wholesale Goods"
        }
    ],
    "sg:phone":"+1 954 341 9063",
    "sg:postcode":"33065",
    "sg:province":"FL",
    "sg:tags":[
        "lithographic",
        "commercial"
    ],
    "wof:name":"Printall II",
    "wof:placetype":"venue"
},
  "geometry": {"coordinates":[-80.283974,26.275076],"type":"Point"}
}