{
  "type": "Feature",
  "properties": {
    "iso:country":"US",
    "sg:address":"345 W Lake Mary Blvd",
    "sg:city":"Sanford",
    "sg:classifiers":[
        {
            "category":"Retail",
            "subcategory":"Laundry & Dry Cleaning",
            "type":"Services"
        }
    ],
    "sg:phone":"+1 407 321 6664",
    "sg:postcode":"32773",
    "sg:province":"FL",
    "sg:tags":[
        "cleaners"
    ],
    "wof:name":"Quality Cleaners Of Lake Mary",
    "wof:placetype":"venue"
},
  "geometry": {"coordinates":[-81.290025,28.75739],"type":"Point"}
}