{
  "type": "Feature",
  "properties": {
    "iso:country":"US",
    "sg:address":"1255 NW 102nd Way",
    "sg:city":"Pompano Beach",
    "sg:classifiers":[
        {
            "category":"Professional",
            "type":"Services"
        }
    ],
    "sg:phone":"+1 954 748 4763",
    "sg:postcode":"33071",
    "sg:province":"FL",
    "wof:name":"Mics Audio",
    "wof:placetype":"venue"
},
  "geometry": {"coordinates":[-80.26098500000001,26.246845],"type":"Point"}
}