{
  "type": "Feature",
  "properties": {
    "iso:country":"US",
    "sg:address":"521 Rebecca Dr",
    "sg:city":"Saint Cloud",
    "sg:classifiers":[
        {
            "category":"Building & Trades",
            "subcategory":"Construction",
            "type":"Services"
        }
    ],
    "sg:phone":"+1 407 891 0764",
    "sg:postcode":"34769",
    "sg:province":"FL",
    "sg:tags":[
        "carpentry",
        "contractor"
    ],
    "wof:name":"Jeff Buffington Carpentry",
    "wof:placetype":"venue"
},
  "geometry": {"coordinates":[-81.274058,28.228725],"type":"Point"}
}