{
  "type": "Feature",
  "properties": {
    "iso:country":"US",
    "sg:address":"5429 Chumuckla Hwy",
    "sg:city":"Milton",
    "sg:classifiers":[
        {
            "category":"Professional",
            "subcategory":"Business Services",
            "type":"Services"
        }
    ],
    "sg:phone":"+1 850 994 8529",
    "sg:postcode":"32571",
    "sg:province":"FL",
    "wof:name":"Mobile Attic of NW Florida",
    "wof:placetype":"venue"
},
  "geometry": {"coordinates":[-87.177222,30.639492],"type":"Point"}
}