{
  "type": "Feature",
  "properties": {
    "addr:full":"9721 SW 72 Ave Gainesville FL 32608",
    "addr:housenumber":"9721",
    "addr:postcode":"32608",
    "addr:street":"Sw 72 Ave",
    "iso:country":"US",
    "sg:address":"9721 SW 72 Ave",
    "sg:city":"Gainesville",
    "sg:classifiers":[
        {
            "category":"Education",
            "subcategory":"Special Training",
            "type":"Public Place"
        }
    ],
    "sg:phone":"+1 352 262 1122",
    "sg:postcode":"32608",
    "sg:province":"FL",
    "sg:tags":[
        "program"
    ],
    "wof:name":"American Safety In-Svc Trainer",
    "wof:placetype":"venue"
},
  "geometry": {"coordinates":[-82.44752,29.587526],"type":"Point"}
}