{
  "type": "Feature",
  "properties": {
    "iso:country":"US",
    "sg:address":"4799 Cason Cove Dr Apt 1702",
    "sg:city":"Orlando",
    "sg:classifiers":[
        {
            "category":"Travel",
            "subcategory":"Hotels & Motels",
            "type":"Entertainment"
        }
    ],
    "sg:phone":"+1 407 425 4234",
    "sg:postcode":"32811",
    "sg:province":"FL",
    "sg:tags":[
        "lodging"
    ],
    "sg:website":"http://www.theorlandowebsite.com",
    "wof:name":"Orlando Web Site Corp",
    "wof:placetype":"venue"
},
  "geometry": {"coordinates":[-81.442543,28.499451],"type":"Point"}
}