{
  "type": "Feature",
  "properties": {
    "addr:full":"7875 SW 104th St Miami FL 33156",
    "addr:housenumber":"7875",
    "addr:postcode":"33156",
    "addr:street":"Sw 104Th St",
    "iso:country":"US",
    "sg:address":"7875 SW 104th St",
    "sg:city":"Miami",
    "sg:classifiers":[
        {
            "category":"Transit Center",
            "subcategory":"Freight",
            "type":"Transportation"
        },
        {
            "category":"Professional",
            "subcategory":"Advertising",
            "type":"Services"
        }
    ],
    "sg:phone":"+1 305 595 7518",
    "sg:postcode":"33156",
    "sg:province":"FL",
    "sg:tags":[
        "outdoor"
    ],
    "wof:name":"Delta Media",
    "wof:placetype":"venue"
},
  "geometry": {"coordinates":[-80.32254399999999,25.673848],"type":"Point"}
}