{
  "type": "Feature",
  "properties": {
    "addr:full":"4627 Enterprise Ave Naples FL 34104",
    "addr:housenumber":"4627",
    "addr:postcode":"34104",
    "addr:street":"Enterprise Ave",
    "iso:country":"US",
    "sg:address":"4627 Enterprise Ave",
    "sg:city":"Naples",
    "sg:classifiers":[
        {
            "category":"Retail",
            "subcategory":"Auto Repair",
            "type":"Services"
        }
    ],
    "sg:phone":"+1 239 643 0939",
    "sg:postcode":"34104",
    "sg:province":"FL",
    "sg:tags":[
        "repairing",
        "automobile"
    ],
    "wof:name":"Clemente's Auto Care",
    "wof:placetype":"venue"
},
  "geometry": {"coordinates":[-81.757785,26.16078],"type":"Point"}
}