{
  "type": "Feature",
  "properties": {
    "addr:full":"451 E Altamonte Dr Altamonte Springs FL 32701",
    "addr:housenumber":"451",
    "addr:postcode":"32701",
    "addr:street":"E Altamonte Dr",
    "iso:country":"US",
    "sg:address":"451 E Altamonte Dr",
    "sg:city":"Altamonte Springs",
    "sg:classifiers":[
        {
            "category":"Restaurant",
            "type":"Food & Drink"
        }
    ],
    "sg:menulink":"http://www.allmenus.com/fl/casselberry-altamonte-springs/186994-mcdonalds/menu/",
    "sg:phone":"+1 407 331 6849",
    "sg:postcode":"32701",
    "sg:province":"FL",
    "sg:tags":[
        "burger",
        "american"
    ],
    "wof:name":"McDonald's",
    "wof:placetype":"venue"
},
  "geometry": {"coordinates":[-81.377211,28.664343],"type":"Point"}
}