{
  "type": "Feature",
  "properties": {
    "iso:country":"US",
    "sg:address":"21066 Escondido Way",
    "sg:city":"Boca Raton",
    "sg:classifiers":[
        {
            "category":"Building & Trades",
            "subcategory":"Construction",
            "type":"Services"
        }
    ],
    "sg:phone":"+1 561 483 8815",
    "sg:postcode":"33433",
    "sg:province":"FL",
    "sg:tags":[
        "house"
    ],
    "wof:name":"Jk Home Improvements Inc",
    "wof:placetype":"venue"
},
  "geometry": {"coordinates":[-80.182969,26.361832],"type":"Point"}
}