{
  "type": "Feature",
  "properties": {
    "addr:full":"8439 Cluster Rd Panama City FL 32404",
    "addr:housenumber":"8439",
    "addr:postcode":"32404",
    "addr:street":"Cluster Rd",
    "iso:country":"US",
    "sg:address":"8439 Cluster Rd",
    "sg:city":"Panama City",
    "sg:classifiers":[
        {
            "category":"Recreation",
            "type":"Entertainment"
        }
    ],
    "sg:phone":"+1 850 769 7766",
    "sg:postcode":"32404",
    "sg:province":"FL",
    "wof:name":"Affordable Saddles",
    "wof:placetype":"venue"
},
  "geometry": {"coordinates":[-85.502653,30.253985],"type":"Point"}
}