{
  "type": "Feature",
  "properties": {
    "addr:full":"130 Miracle Strip Pkwy Fort Walton Bch FL 32548",
    "addr:housenumber":"130",
    "addr:postcode":"32548",
    "addr:street":"Miracle Strip Pkwy Fort",
    "iso:country":"US",
    "sg:address":"130 Miracle Strip Pkwy",
    "sg:city":"Fort Walton Bch",
    "sg:classifiers":[
        {
            "category":"Shopping",
            "subcategory":"Gifts & Souvenirs",
            "type":"Retail Goods"
        }
    ],
    "sg:phone":"+1 850 243 1721",
    "sg:postcode":"32548",
    "sg:province":"FL",
    "sg:tags":[
        "shop"
    ],
    "wof:name":"Coach & Four Gifts",
    "wof:placetype":"venue"
},
  "geometry": {"coordinates":[-86.607809,30.403705],"type":"Point"}
}