{
  "type": "Feature",
  "properties": {
    "addr:full":"900 E Gregory St Pensacola FL 32502",
    "addr:housenumber":"900",
    "addr:postcode":"32502",
    "addr:street":"E Gregory St",
    "iso:country":"US",
    "sg:address":"900 E Gregory St",
    "sg:city":"Pensacola",
    "sg:classifiers":[
        {
            "category":"Food & Beverages",
            "subcategory":"Liquor & Beverages",
            "type":"Retail Goods"
        }
    ],
    "sg:phone":"+1 850 434 0807",
    "sg:postcode":"32502",
    "sg:province":"FL",
    "wof:name":"Richey's East",
    "wof:placetype":"venue"
},
  "geometry": {"coordinates":[-87.197374,30.418649],"type":"Point"}
}