{
  "type": "Feature",
  "properties": {
    "addr:full":"3562 S Osprey Ave Sarasota FL 34239",
    "addr:housenumber":"3562",
    "addr:postcode":"34239",
    "addr:street":"S Osprey Ave",
    "iso:country":"US",
    "sg:address":"3562 S Osprey Ave",
    "sg:city":"Sarasota",
    "sg:classifiers":[
        {
            "category":"Shopping",
            "subcategory":"Antiques",
            "type":"Retail Goods"
        },
        {
            "category":"Professional",
            "subcategory":"Art Services",
            "type":"Services"
        },
        {
            "category":"Home & Garden",
            "subcategory":"Furniture",
            "type":"Retail Goods"
        }
    ],
    "sg:phone":"+1 941 955 5726",
    "sg:postcode":"34239",
    "sg:province":"FL",
    "sg:tags":[
        "interior",
        "designer",
        "decorator",
        "store"
    ],
    "sg:website":"http://www.pvidesign.com",
    "wof:name":"Pedlar's Village Interior Design",
    "wof:placetype":"venue"
},
  "geometry": {"coordinates":[-82.533661,27.30151],"type":"Point"}
}