{
  "type": "Feature",
  "properties": {
    "addr:full":"6750 N Andrews Ave Exd Fort Lauderdale FL 33309",
    "addr:housenumber":"6750",
    "addr:postcode":"33309",
    "addr:street":"N Andrews Ave Exd",
    "iso:country":"US",
    "sg:address":"6750 N Andrews Ave Exd",
    "sg:city":"Fort Lauderdale",
    "sg:classifiers":[
        {
            "category":"Banks & Credit Unions",
            "subcategory":"Investment Brokerage",
            "type":"Services"
        }
    ],
    "sg:phone":"+1 954 356 0330",
    "sg:postcode":"33309",
    "sg:province":"FL",
    "sg:tags":[
        "institutional",
        "brokerage",
        "government",
        "firm",
        "bond"
    ],
    "wof:name":"Mesiro Financial Inc",
    "wof:placetype":"venue"
},
  "geometry": {"coordinates":[-80.143339,26.20936],"type":"Point"}
}