{
  "type": "Feature",
  "properties": {
    "iso:country":"US",
    "sg:address":"8241 NW 66th St",
    "sg:city":"Miami",
    "sg:classifiers":[
        {
            "category":"Manufacturing",
            "subcategory":"Electronics",
            "type":"Manufacturing & Wholesale Goods"
        }
    ],
    "sg:phone":"+1 305 592 9811",
    "sg:postcode":"33166",
    "sg:province":"FL",
    "sg:tags":[
        "equipment",
        "mfg",
        "communication"
    ],
    "wof:name":"System Indus Technologic Inc",
    "wof:placetype":"venue"
},
  "geometry": {"coordinates":[-80.330732,25.833561],"type":"Point"}
}