{
  "type": "Feature",
  "properties": {
    "iso:country":"US",
    "sg:address":"5771 Lake Victoria Dr",
    "sg:city":"Lakeland",
    "sg:classifiers":[
        {
            "category":"Professional",
            "subcategory":"Engineering",
            "type":"Services"
        }
    ],
    "sg:phone":"+1 863 646 0792",
    "sg:postcode":"33813",
    "sg:province":"FL",
    "wof:name":"Eric Jen Aviation Inc",
    "wof:placetype":"venue"
},
  "geometry": {"coordinates":[-81.954087,27.959945],"type":"Point"}
}