{
  "type": "Feature",
  "properties": {
    "addr:full":"472 NW 79th St Miami FL 33150",
    "addr:housenumber":"472",
    "addr:postcode":"33150",
    "addr:street":"Nw 79Th St",
    "iso:country":"US",
    "sg:address":"472 NW 79th St",
    "sg:city":"Miami",
    "sg:classifiers":[
        {
            "category":"Autos & Motor Vehicles",
            "subcategory":"Automobile Sales",
            "type":"Retail Goods"
        }
    ],
    "sg:phone":"+1 305 754 5599",
    "sg:postcode":"33150",
    "sg:province":"FL",
    "sg:tags":[
        "car",
        "dealer"
    ],
    "wof:name":"Jordi Auto Sales Corp",
    "wof:placetype":"venue"
},
  "geometry": {"coordinates":[-80.204911,25.847111],"type":"Point"}
}