{
  "type": "Feature",
  "properties": {
    "iso:country":"US",
    "sg:address":"1239 E Kennedy Blvd",
    "sg:city":"Tampa",
    "sg:classifiers":[
        {
            "category":"Building & Trades",
            "subcategory":"Locksmith",
            "type":"Services"
        },
        {
            "category":"Retail",
            "subcategory":"Auto Repair",
            "type":"Services"
        }
    ],
    "sg:phone":"+1 813 421 6124",
    "sg:postcode":"33602",
    "sg:province":"FL",
    "sg:tags":[
        "service-automotive",
        "locksmiths-commercial",
        "industrial",
        "road",
        "lock"
    ],
    "wof:name":"0n Time Road Service",
    "wof:placetype":"venue"
},
  "geometry": {"coordinates":[-82.446648,27.950533],"type":"Point"}
}