{
  "type": "Feature",
  "properties": {
    "iso:country":"US",
    "sg:address":"1091 Aaron Dr",
    "sg:city":"Deltona",
    "sg:classifiers":[
        {
            "category":"Autos & Motor Vehicles",
            "subcategory":"Auto Supplies",
            "type":"Retail Goods"
        }
    ],
    "sg:phone":"+1 407 575 0811",
    "sg:postcode":"32725",
    "sg:province":"FL",
    "sg:tags":[
        "automobile",
        "accessory"
    ],
    "wof:name":"La Auto Accessories",
    "wof:placetype":"venue"
},
  "geometry": {"coordinates":[-81.243004,28.884167],"type":"Point"}
}