{
  "type": "Feature",
  "properties": {
    "addr:full":"13131 NW 11th St Fort Lauderdale FL 33323",
    "addr:housenumber":"13131",
    "addr:postcode":"33323",
    "addr:street":"Nw 11Th St",
    "iso:country":"US",
    "sg:address":"13131 NW 11th St",
    "sg:city":"Fort Lauderdale",
    "sg:classifiers":[
        {
            "category":"Recreation",
            "type":"Entertainment"
        }
    ],
    "sg:phone":"+1 954 629 4200",
    "sg:postcode":"33323",
    "sg:province":"FL",
    "wof:name":"Up Front Tickets",
    "wof:placetype":"venue"
},
  "geometry": {"coordinates":[-80.322909,26.134925],"type":"Point"}
}