{
  "type": "Feature",
  "properties": {
    "iso:country":"US",
    "sg:address":"810 W 74th St",
    "sg:city":"Hialeah",
    "sg:classifiers":[
        {
            "category":"Health Services",
            "subcategory":"Nursing And Care Facility",
            "type":"Services"
        }
    ],
    "sg:phone":"+1 305 818 2082",
    "sg:postcode":"33014",
    "sg:province":"FL",
    "sg:tags":[
        "home",
        "retirement",
        "community"
    ],
    "wof:name":"Luz Home For The Elderly",
    "wof:placetype":"venue"
},
  "geometry": {"coordinates":[-80.303617,25.889686],"type":"Point"}
}