{
  "type": "Feature",
  "properties": {
    "iso:country":"US",
    "sg:address":"6201 N Dixie Hwy",
    "sg:city":"Fort Lauderdale",
    "sg:classifiers":[
        {
            "category":"Food & Beverages",
            "subcategory":"Groceries & Convenience Stores",
            "type":"Retail Goods"
        }
    ],
    "sg:phone":"+1 954 772 9033",
    "sg:postcode":"33334",
    "sg:province":"FL",
    "wof:name":"Cypress Creek",
    "wof:placetype":"venue"
},
  "geometry": {"coordinates":[-80.13271899999999,26.204197],"type":"Point"}
}