{
  "type": "Feature",
  "properties": {
    "iso:country":"US",
    "sg:address":"28331 S Tamiami Trl",
    "sg:city":"Bonita Springs",
    "sg:classifiers":[
        {
            "category":"Building & Trades",
            "subcategory":"Construction",
            "type":"Services"
        }
    ],
    "sg:phone":"+1 239 498 7400",
    "sg:postcode":"33928",
    "sg:province":"FL",
    "sg:tags":[
        "excavating",
        "contractor"
    ],
    "wof:name":"First Choice Site Development",
    "wof:placetype":"venue"
},
  "geometry": {"coordinates":[-81.805544,26.325251],"type":"Point"}
}