{
  "type": "Feature",
  "properties": {
    "addr:full":"1847 14th Ave Vero Beach FL 32960",
    "addr:housenumber":"1847",
    "addr:postcode":"32960",
    "addr:street":"14Th Ave",
    "iso:country":"US",
    "sg:address":"1847 14th Ave",
    "sg:city":"Vero Beach",
    "sg:classifiers":[
        {
            "category":"Social Services",
            "subcategory":"Adult Care",
            "type":"Services"
        }
    ],
    "sg:phone":"+1 772 564 8821",
    "sg:postcode":"32960",
    "sg:province":"FL",
    "sg:tags":[
        "residential"
    ],
    "wof:name":"Home Instead Senior Care",
    "wof:placetype":"venue"
},
  "geometry": {"coordinates":[-80.399508,27.635527],"type":"Point"}
}