{
  "type": "Feature",
  "properties": {
    "iso:country":"US",
    "sg:address":"8220 Pelican Ln",
    "sg:city":"Seminole",
    "sg:classifiers":[
        {
            "category":"Building & Trades",
            "subcategory":"Construction",
            "type":"Services"
        }
    ],
    "sg:phone":"+1 727 394 1586",
    "sg:postcode":"33777",
    "sg:province":"FL",
    "sg:tags":[
        "contractor"
    ],
    "wof:name":"Franz Tile Inc",
    "wof:placetype":"venue"
},
  "geometry": {"coordinates":[-82.760043,27.848158],"type":"Point"}
}