{
  "type": "Feature",
  "properties": {
    "iso:country":"US",
    "sg:address":"805 NW 159th Dr",
    "sg:city":"Miami",
    "sg:classifiers":[
        {
            "category":"Autos & Motor Vehicles",
            "subcategory":"Boat Sales",
            "type":"Retail Goods"
        }
    ],
    "sg:phone":"+1 305 627 9394",
    "sg:postcode":"33169",
    "sg:province":"FL",
    "sg:tags":[
        "distributor",
        "manufacturer"
    ],
    "wof:name":"Deep Impact Boats",
    "wof:placetype":"venue"
},
  "geometry": {"coordinates":[-80.218864,25.92132],"type":"Point"}
}