{
  "type": "Feature",
  "properties": {
    "iso:country":"US",
    "sg:address":"1489 Roseboro Dr",
    "sg:city":"Deltona",
    "sg:classifiers":[
        {
            "category":"Organizations",
            "subcategory":"Membership Organization",
            "type":"Services"
        }
    ],
    "sg:phone":"+1 386 532 3551",
    "sg:postcode":"32725",
    "sg:province":"FL",
    "wof:name":"Coalition Of Retired Policemen",
    "wof:placetype":"venue"
},
  "geometry": {"coordinates":[-81.23419199999999,28.933446],"type":"Point"}
}