{
  "type": "Feature",
  "properties": {
    "iso:country":"US",
    "sg:address":"1914 Tamiami Trl N",
    "sg:city":"Naples",
    "sg:classifiers":[
        {
            "category":"Shopping",
            "subcategory":"Clothing, Apparel, & Fashions",
            "type":"Retail Goods"
        }
    ],
    "sg:phone":"+1 239 213 9481",
    "sg:postcode":"34102",
    "sg:province":"FL",
    "sg:website":"www.iftheshoefitsbuyit.com",
    "wof:name":"If The Shoe Fits Buy It",
    "wof:placetype":"venue"
},
  "geometry": {"coordinates":[-81.799409,26.169547],"type":"Point"}
}