{
  "type": "Feature",
  "properties": {
    "addr:full":"1707 20th St Vero Beach FL 32960",
    "addr:housenumber":"1707",
    "addr:postcode":"32960",
    "addr:street":"20Th St",
    "iso:country":"US",
    "sg:address":"1707 20th St",
    "sg:city":"Vero Beach",
    "sg:classifiers":[
        {
            "category":"Professional",
            "subcategory":"Lawyer & Legal Services",
            "type":"Services"
        }
    ],
    "sg:phone":"+1 772 562 6262",
    "sg:postcode":"32960",
    "sg:province":"FL",
    "sg:tags":[
        "attorney"
    ],
    "wof:name":"Margaret M Anderson Pa",
    "wof:placetype":"venue"
},
  "geometry": {"coordinates":[-80.4034,27.638602],"type":"Point"}
}