{
  "type": "Feature",
  "properties": {
    "iso:country":"US",
    "sg:address":"6431 S Chickasaw Trl",
    "sg:city":"Orlando",
    "sg:classifiers":[
        {
            "category":"Health Services",
            "subcategory":"Optometrist",
            "type":"Services"
        }
    ],
    "sg:phone":"+1 407 482 4800",
    "sg:postcode":"32829",
    "sg:province":"FL",
    "wof:name":"Eye Associates Of Orlando PA",
    "wof:placetype":"venue"
},
  "geometry": {"coordinates":[-81.268022,28.469086],"type":"Point"}
}