{
  "type": "Feature",
  "properties": {
    "iso:country":"US",
    "sg:address":"4451 Enterprise Ct",
    "sg:city":"Melbourne",
    "sg:classifiers":[
        {
            "category":"Wholesale",
            "subcategory":"Auto Parts",
            "type":"Manufacturing & Wholesale Goods"
        },
        {
            "category":"Manufacturing",
            "subcategory":"Motor Vehicles & Parts",
            "type":"Manufacturing & Wholesale Goods"
        }
    ],
    "sg:phone":"+1 321 254 5810",
    "sg:postcode":"32934",
    "sg:province":"FL",
    "sg:tags":[
        "automobile",
        "supply"
    ],
    "wof:name":"Modine Aftermarket Holdings",
    "wof:placetype":"venue"
},
  "geometry": {"coordinates":[-80.700294,28.117579],"type":"Point"}
}