{
  "type": "Feature",
  "properties": {
    "addr:full":"110 Foxridge Run Longwood FL 32750",
    "addr:housenumber":"110",
    "addr:postcode":"32750",
    "addr:street":"Foxridge Run",
    "iso:country":"US",
    "sg:address":"110 Foxridge Run",
    "sg:city":"Longwood",
    "sg:classifiers":[
        {
            "category":"Restaurant",
            "type":"Food & Drink"
        }
    ],
    "sg:phone":"+1 407 339 8228",
    "sg:postcode":"32750",
    "sg:province":"FL",
    "wof:name":"As You Wish On Rye Inc",
    "wof:placetype":"venue"
},
  "geometry": {"coordinates":[-81.375507,28.708351],"type":"Point"}
}