{
  "type": "Feature",
  "properties": {
    "addr:full":"1303 Limit Ave Mt Dora FL 32757",
    "addr:housenumber":"1303",
    "addr:postcode":"32757",
    "addr:street":"Limit Ave",
    "iso:country":"US",
    "sg:address":"1303 Limit Ave",
    "sg:city":"Mt Dora",
    "sg:classifiers":[
        {
            "category":"Professional",
            "subcategory":"Accounting & Tax Preparation",
            "type":"Services"
        }
    ],
    "sg:phone":"+1 352 735 4052",
    "sg:postcode":"32757",
    "sg:province":"FL",
    "sg:tags":[
        "bookkeeping",
        "general"
    ],
    "wof:name":"Account Management Svc",
    "wof:placetype":"venue"
},
  "geometry": {"coordinates":[-81.632389,28.815272],"type":"Point"}
}