{
  "type": "Feature",
  "properties": {
    "addr:full":"6041 Kimberly Blvd Pompano Beach FL 33068",
    "addr:housenumber":"6041",
    "addr:postcode":"33068",
    "addr:street":"Kimberly Blvd",
    "iso:country":"US",
    "sg:address":"6041 Kimberly Blvd",
    "sg:city":"Pompano Beach",
    "sg:classifiers":[
        {
            "category":"Building & Trades",
            "subcategory":"Electrical",
            "type":"Services"
        }
    ],
    "sg:phone":"+1 954 970 4613",
    "sg:postcode":"33068",
    "sg:province":"FL",
    "sg:tags":[
        "electrical",
        "contractor"
    ],
    "wof:name":"Pro Tech Electrical Contrators",
    "wof:placetype":"venue"
},
  "geometry": {"coordinates":[-80.207159,26.215667],"type":"Point"}
}