{
  "type": "Feature",
  "properties": {
    "addr:full":"4279 W Lake Mary Blvd Lake Mary FL 32746",
    "addr:housenumber":"4279",
    "addr:postcode":"32746",
    "addr:street":"W Lake Mary Blvd",
    "iso:country":"US",
    "sg:address":"4279 W Lake Mary Blvd",
    "sg:city":"Lake Mary",
    "sg:classifiers":[
        {
            "category":"Shopping",
            "subcategory":"Bicycles & Sporting Goods",
            "type":"Retail Goods"
        }
    ],
    "sg:phone":"+1 407 331 5993",
    "sg:postcode":"32746",
    "sg:province":"FL",
    "sg:tags":[
        "repair"
    ],
    "wof:name":"Out Spoke N Bike Shops Inc",
    "wof:placetype":"venue"
},
  "geometry": {"coordinates":[-81.350228,28.756096],"type":"Point"}
}