{
  "type": "Feature",
  "properties": {
    "iso:country":"US",
    "sg:address":"860 Gatlin Ave",
    "sg:city":"Orlando",
    "sg:classifiers":[
        {
            "category":"Professional",
            "subcategory":"Management & Consulting",
            "type":"Services"
        }
    ],
    "sg:phone":"+1 407 852 1411",
    "sg:postcode":"32806",
    "sg:province":"FL",
    "sg:tags":[
        "house",
        "business"
    ],
    "wof:name":"Castle Consulting & Cnstr",
    "wof:placetype":"venue"
},
  "geometry": {"coordinates":[-81.36717299999999,28.494325],"type":"Point"}
}