{
  "type": "Feature",
  "properties": {
    "addr:full":"2251 NW 36th Ave Coconut Creek FL 33066",
    "addr:housenumber":"2251",
    "addr:postcode":"33066",
    "addr:street":"Nw 36Th Ave",
    "iso:country":"US",
    "sg:address":"2251 NW 36th Ave",
    "sg:city":"Coconut Creek",
    "sg:classifiers":[
        {
            "category":"Social Services",
            "subcategory":"Child Care",
            "type":"Services"
        },
        {
            "category":"Education",
            "subcategory":"School",
            "type":"Public Place"
        }
    ],
    "sg:phone":"+1 954 968 1750",
    "sg:postcode":"33066",
    "sg:province":"FL",
    "sg:tags":[
        "day"
    ],
    "wof:name":"Randazzo School",
    "wof:placetype":"venue"
},
  "geometry": {"coordinates":[-80.172663,26.25545],"type":"Point"}
}