{
  "type": "Feature",
  "properties": {
    "iso:country":"US",
    "sg:address":"16891 Jupiter Farms Rd",
    "sg:city":"Jupiter",
    "sg:classifiers":[
        {
            "category":"Restaurant",
            "type":"Food & Drink"
        }
    ],
    "sg:phone":"+1 561 747 7774",
    "sg:postcode":"33478",
    "sg:province":"FL",
    "wof:name":"Dry Dock Grille",
    "wof:placetype":"venue"
},
  "geometry": {"coordinates":[-80.191737,26.926388],"type":"Point"}
}