{
  "type": "Feature",
  "properties": {
    "addr:full":"2424 N Federal Hwy Boca Raton FL 33431",
    "addr:housenumber":"2424",
    "addr:postcode":"33431",
    "addr:street":"N Federal Hwy",
    "iso:country":"US",
    "sg:address":"2424 N Federal Hwy",
    "sg:city":"Boca Raton",
    "sg:classifiers":[
        {
            "category":"Professional",
            "subcategory":"Lawyer & Legal Services",
            "type":"Services"
        }
    ],
    "sg:phone":"+1 561 392 5354",
    "sg:postcode":"33431",
    "sg:province":"FL",
    "wof:name":"Boca Raton Title Insurance Co",
    "wof:placetype":"venue"
},
  "geometry": {"coordinates":[-80.076646,26.371375],"type":"Point"}
}