{
  "type": "Feature",
  "properties": {
    "addr:full":"3505 NW 107th Ave Doral FL 33178",
    "addr:housenumber":"3505",
    "addr:postcode":"33178",
    "addr:street":"Nw 107Th Ave",
    "iso:country":"US",
    "sg:address":"3505 NW 107th Ave",
    "sg:city":"Doral",
    "sg:classifiers":[
        {
            "category":"Freight",
            "type":"Transportation"
        },
        {
            "category":"Airline",
            "type":"Transportation"
        }
    ],
    "sg:phone":"+1 305 468 8931",
    "sg:postcode":"33178",
    "sg:province":"FL",
    "sg:tags":[
        "cargo",
        "air",
        "arrangement"
    ],
    "wof:name":"Ait Worldwide Logistics",
    "wof:placetype":"venue"
},
  "geometry": {"coordinates":[-80.385006,25.809649],"type":"Point"}
}