{
  "type": "Feature",
  "properties": {
    "iso:country":"US",
    "sg:address":"23684 US Hwy 19",
    "sg:city":"Clearwater",
    "sg:classifiers":[
        {
            "category":"Banks & Credit Unions",
            "subcategory":"Bank",
            "type":"Services"
        }
    ],
    "sg:phone":"+1 727 669 8489",
    "sg:postcode":"33765",
    "sg:province":"FL",
    "wof:name":"B B & T",
    "wof:placetype":"venue"
},
  "geometry": {"coordinates":[-82.72971099999999,27.987129],"type":"Point"}
}