{
  "type": "Feature",
  "properties": {
    "addr:full":"3930 NE 2nd Ave Miami FL 33137",
    "addr:housenumber":"3930",
    "addr:postcode":"33137",
    "addr:street":"Ne 2Nd Ave",
    "iso:country":"US",
    "sg:address":"3930 NE 2nd Ave",
    "sg:city":"Miami",
    "sg:classifiers":[
        {
            "category":"Home & Garden",
            "subcategory":"Furniture",
            "type":"Retail Goods"
        }
    ],
    "sg:phone":"+1 305 572 1182",
    "sg:postcode":"33137",
    "sg:province":"FL",
    "wof:name":"Via Solserino",
    "wof:placetype":"venue"
},
  "geometry": {"coordinates":[-80.191456,25.813244],"type":"Point"}
}