{
  "type": "Feature",
  "properties": {
    "iso:country":"US",
    "sg:address":"1430 119th Street",
    "sg:city":"Miami",
    "sg:classifiers":[
        {
            "category":"Recreation",
            "subcategory":"Dance Hall",
            "type":"Entertainment"
        }
    ],
    "sg:phone":"+1 305 600 8225",
    "sg:postcode":"33167",
    "sg:province":"FL",
    "sg:tags":[
        "club"
    ],
    "sg:website":"myspace.com/wemadeitinc",
    "wof:name":"Coco's Nightclub",
    "wof:placetype":"venue"
},
  "geometry": {"coordinates":[-80.223299,25.882987],"type":"Point"}
}