{
  "type": "Feature",
  "properties": {
    "addr:full":"2858 N Hiawassee Rd Orlando FL 32818",
    "addr:housenumber":"2858",
    "addr:postcode":"32818",
    "addr:street":"N Hiawassee Rd",
    "iso:country":"US",
    "sg:address":"2858 N Hiawassee Rd",
    "sg:city":"Orlando",
    "sg:classifiers":[
        {
            "category":"Cinema",
            "subcategory":"Movie Rental",
            "type":"Entertainment"
        }
    ],
    "sg:phone":"+1 407 299 6068",
    "sg:postcode":"32818",
    "sg:province":"FL",
    "sg:tags":[
        "video",
        "tape"
    ],
    "wof:name":"Blockbuster",
    "wof:placetype":"venue"
},
  "geometry": {"coordinates":[-81.47613800000001,28.577781],"type":"Point"}
}