{
  "type": "Feature",
  "properties": {
    "iso:country":"US",
    "sg:address":"1520 Lee St",
    "sg:city":"Fort Myers",
    "sg:classifiers":[
        {
            "category":"Organizations",
            "subcategory":"Religious Organization",
            "type":"Services"
        }
    ],
    "sg:phone":"+1 239 332 5255",
    "sg:postcode":"33901",
    "sg:province":"FL",
    "wof:name":"Mitzva TV",
    "wof:placetype":"venue"
},
  "geometry": {"coordinates":[-81.86779900000001,26.644725],"type":"Point"}
}