{
  "type": "Feature",
  "properties": {
    "iso:country":"US",
    "sg:address":"2055 NW 99th Ter",
    "sg:city":"Miami",
    "sg:classifiers":[
        {
            "category":"Food & Beverages",
            "subcategory":"Candy",
            "type":"Retail Goods"
        }
    ],
    "sg:phone":"+1 305 691 2525",
    "sg:postcode":"33147",
    "sg:province":"FL",
    "sg:tags":[
        "nut"
    ],
    "wof:name":"Rainbow Peanut Co",
    "wof:placetype":"venue"
},
  "geometry": {"coordinates":[-80.23188,25.865203],"type":"Point"}
}