{
  "type": "Feature",
  "properties": {
    "addr:full":"973 SW 8th Ct Miami FL 33130",
    "addr:housenumber":"973",
    "addr:postcode":"33130",
    "addr:street":"Sw 8Th Ct",
    "iso:country":"US",
    "sg:address":"973 SW 8th Ct",
    "sg:city":"Miami",
    "sg:classifiers":[
        {
            "category":"Professional",
            "subcategory":"Lawyer & Legal Services",
            "type":"Services"
        }
    ],
    "sg:phone":"+1 305 857 9191",
    "sg:postcode":"33130",
    "sg:province":"FL",
    "sg:tags":[
        "attorney",
        "bureau"
    ],
    "wof:name":"Terra Data Research",
    "wof:placetype":"venue"
},
  "geometry": {"coordinates":[-80.208015,25.764295],"type":"Point"}
}