{
  "type": "Feature",
  "properties": {
    "iso:country":"US",
    "sg:address":"601 King St",
    "sg:city":"Oviedo",
    "sg:classifiers":[
        {
            "category":"Education",
            "subcategory":"School",
            "type":"Public Place"
        }
    ],
    "sg:phone":"+1 407 320 4050",
    "sg:postcode":"32765",
    "sg:province":"FL",
    "sg:tags":[
        "high"
    ],
    "sg:website":"http://www.oviedohighschool.com",
    "wof:name":"Oviedo High School",
    "wof:placetype":"venue"
},
  "geometry": {"coordinates":[-81.21825699999999,28.672211],"type":"Point"}
}