{
  "type": "Feature",
  "properties": {
    "addr:full":"8827 NW 117th St Hialeah FL 33018",
    "addr:housenumber":"8827",
    "addr:postcode":"33018",
    "addr:street":"Nw 117Th St",
    "iso:country":"US",
    "sg:address":"8827 NW 117th St",
    "sg:city":"Hialeah",
    "sg:classifiers":[
        {
            "category":"Manufacturing",
            "subcategory":"Apparel",
            "type":"Manufacturing & Wholesale Goods"
        }
    ],
    "sg:phone":"+1 305 826 3400",
    "sg:postcode":"33018",
    "sg:province":"FL",
    "sg:tags":[
        "party",
        "mfg",
        "tent"
    ],
    "wof:name":"F&S Tents",
    "wof:placetype":"venue"
},
  "geometry": {"coordinates":[-80.341145,25.879832],"type":"Point"}
}