{
  "type": "Feature",
  "properties": {
    "iso:country":"US",
    "sg:address":"122 15th Ave N",
    "sg:city":"Jacksonville Bch",
    "sg:classifiers":[
        {
            "category":"Professional",
            "subcategory":"Management & Consulting",
            "type":"Services"
        }
    ],
    "sg:phone":"+1 904 242 0799",
    "sg:postcode":"32250",
    "sg:province":"FL",
    "wof:name":"Mc Cann Management",
    "wof:placetype":"venue"
},
  "geometry": {"coordinates":[-81.393354,30.303125],"type":"Point"}
}