{
  "type": "Feature",
  "properties": {
    "addr:full":"12160 Saint Andrews Pl Hollywood FL 33025",
    "addr:housenumber":"12160",
    "addr:postcode":"33025",
    "addr:street":"Saint Andrews Pl",
    "iso:country":"US",
    "sg:address":"12160 Saint Andrews Pl",
    "sg:city":"Hollywood",
    "sg:classifiers":[
        {
            "category":"Manufacturing",
            "subcategory":"Apparel",
            "type":"Manufacturing & Wholesale Goods"
        }
    ],
    "sg:phone":"+1 954 438 2875",
    "sg:postcode":"33025",
    "sg:province":"FL",
    "sg:tags":[
        "outerwear",
        "mfg"
    ],
    "wof:name":"Caramella Collection Corp",
    "wof:placetype":"venue"
},
  "geometry": {"coordinates":[-80.30731900000001,25.990734],"type":"Point"}
}