{
  "type": "Feature",
  "properties": {
    "addr:full":"205 E Granada Blvd Ormond Beach FL 32176",
    "addr:housenumber":"205",
    "addr:postcode":"32176",
    "addr:street":"E Granada Blvd",
    "iso:country":"US",
    "sg:address":"205 E Granada Blvd",
    "sg:city":"Ormond Beach",
    "sg:classifiers":[
        {
            "category":"Shopping",
            "subcategory":"Pharmacy",
            "type":"Retail Goods"
        }
    ],
    "sg:phone":"+1 386 672 1013",
    "sg:postcode":"32176",
    "sg:province":"FL",
    "sg:tags":[
        "photofinishing",
        "laboratory"
    ],
    "wof:name":"Walgreens",
    "wof:placetype":"venue"
},
  "geometry": {"coordinates":[-81.04286500000001,29.290786],"type":"Point"}
}