{
  "type": "Feature",
  "properties": {
    "addr:full":"276 S Brevard Ave Cocoa Beach FL 32931",
    "addr:housenumber":"276",
    "addr:postcode":"32931",
    "addr:street":"S Brevard Ave",
    "iso:country":"US",
    "sg:address":"276 S Brevard Ave",
    "sg:city":"Cocoa Beach",
    "sg:classifiers":[
        {
            "category":"Travel",
            "subcategory":"Travel Agent",
            "type":"Entertainment"
        }
    ],
    "sg:phone":"+1 321 799 2225",
    "sg:postcode":"32931",
    "sg:province":"FL",
    "sg:tags":[
        "agency"
    ],
    "wof:name":"American Express",
    "wof:placetype":"venue"
},
  "geometry": {"coordinates":[-80.61125199999999,28.314448],"type":"Point"}
}