{
  "type": "Feature",
  "properties": {
    "addr:full":"2210 Tamiami Trl N Naples FL 34103",
    "addr:housenumber":"2210",
    "addr:postcode":"34103",
    "addr:street":"Tamiami Trl N",
    "iso:country":"US",
    "sg:address":"2210 Tamiami Trl N",
    "sg:city":"Naples",
    "sg:classifiers":[
        {
            "category":"Wholesale",
            "subcategory":"Machinery & Supplies",
            "type":"Manufacturing & Wholesale Goods"
        }
    ],
    "sg:phone":"+1 239 262 4440",
    "sg:postcode":"34103",
    "sg:province":"FL",
    "sg:tags":[
        "beauty"
    ],
    "wof:name":"Dutchess Beauty Supply Inc",
    "wof:placetype":"venue"
},
  "geometry": {"coordinates":[-81.799696,26.174207],"type":"Point"}
}