{
  "type": "Feature",
  "properties": {
    "addr:full":"611 E Bloomingdale Ave Brandon FL 33511",
    "addr:housenumber":"611",
    "addr:postcode":"33511",
    "addr:street":"E Bloomingdale Ave",
    "iso:country":"US",
    "sg:address":"611 E Bloomingdale Ave",
    "sg:city":"Brandon",
    "sg:classifiers":[
        {
            "category":"Health Services",
            "subcategory":"Doctor",
            "type":"Services"
        }
    ],
    "sg:phone":"+1 813 684 6279",
    "sg:postcode":"33511",
    "sg:province":"FL",
    "sg:tags":[
        "dentist"
    ],
    "wof:name":"Jeffrey B Cook DDS",
    "wof:placetype":"venue"
},
  "geometry": {"coordinates":[-82.270171,27.893547],"type":"Point"}
}