{
  "type": "Feature",
  "properties": {
    "iso:country":"US",
    "sg:address":"9225 SW 158th Ln",
    "sg:city":"Miami",
    "sg:classifiers":[
        {
            "category":"Health Services",
            "subcategory":"Hospital",
            "type":"Services"
        }
    ],
    "sg:phone":"+1 305 254 1928",
    "sg:postcode":"33157",
    "sg:province":"FL",
    "sg:tags":[
        "mental"
    ],
    "wof:name":"Regis House",
    "wof:placetype":"venue"
},
  "geometry": {"coordinates":[-80.34182800000001,25.622643],"type":"Point"}
}