{
  "type": "Feature",
  "properties": {
    "iso:country":"US",
    "sg:address":"15271 Amberly Dr",
    "sg:city":"Tampa",
    "sg:classifiers":[
        {
            "category":"Insurance",
            "subcategory":"Insurance Agent",
            "type":"Services"
        }
    ],
    "sg:phone":"+1 813 978 1898",
    "sg:postcode":"33647",
    "sg:province":"FL",
    "wof:name":"State Farm Insurance",
    "wof:placetype":"venue"
},
  "geometry": {"coordinates":[-82.40330899999999,28.096715],"type":"Point"}
}