{
  "type": "Feature",
  "properties": {
    "iso:country":"US",
    "sg:address":"9917 NW 57th Manor",
    "sg:city":"Pompano Beach",
    "sg:classifiers":[
        {
            "category":"Building & Trades",
            "subcategory":"Construction",
            "type":"Services"
        }
    ],
    "sg:phone":"+1 954 796 7555",
    "sg:postcode":"33076",
    "sg:province":"FL",
    "sg:tags":[
        "contractor"
    ],
    "wof:name":"Ambrose Roofing Inc",
    "wof:placetype":"venue"
},
  "geometry": {"coordinates":[-80.256736,26.300819],"type":"Point"}
}