{
  "type": "Feature",
  "properties": {
    "addr:full":"4954 Co Rd 317 Bushnell FL 33513",
    "addr:housenumber":"4954;317",
    "addr:postcode":"33513",
    "addr:street":"Co Rd",
    "iso:country":"US",
    "sg:address":"4954 Co Rd 317",
    "sg:city":"Bushnell",
    "sg:classifiers":[
        {
            "category":"Wholesale",
            "subcategory":"Plants",
            "type":"Manufacturing & Wholesale Goods"
        }
    ],
    "sg:phone":"+1 352 303 0549",
    "sg:postcode":"33513",
    "sg:province":"FL",
    "sg:tags":[
        "nursery",
        "tree"
    ],
    "wof:name":"H & L Tree Farm By Lance",
    "wof:placetype":"venue"
},
  "geometry": {"coordinates":[-82.17015499999999,28.681162],"type":"Point"}
}