{
  "type": "Feature",
  "properties": {
    "addr:full":"3399 Pga Blvd Palm Beach Gardens FL 33410",
    "addr:housenumber":"3399",
    "addr:postcode":"33410",
    "addr:street":"Pga Blvd",
    "iso:country":"US",
    "sg:address":"3399 Pga Blvd",
    "sg:city":"Palm Beach Gardens",
    "sg:classifiers":[
        {
            "category":"Banks & Credit Unions",
            "subcategory":"Investment Brokerage",
            "type":"Services"
        }
    ],
    "sg:phone":"+1 561 630 7878",
    "sg:postcode":"33410",
    "sg:province":"FL",
    "sg:tags":[
        "security"
    ],
    "wof:name":"Northwestern Mutual Insurance",
    "wof:placetype":"venue"
},
  "geometry": {"coordinates":[-80.086491,26.845088],"type":"Point"}
}