{
  "type": "Feature",
  "properties": {
    "iso:country":"US",
    "sg:address":"641 University Blvd",
    "sg:city":"Jupiter",
    "sg:classifiers":[
        {
            "category":"Personal",
            "type":"Services"
        },
        {
            "category":"Professional",
            "subcategory":"Art Services",
            "type":"Services"
        },
        {
            "category":"Professional",
            "subcategory":"Printing & Photocopies",
            "type":"Services"
        }
    ],
    "sg:phone":"+1 561 627 1333",
    "sg:postcode":"33458",
    "sg:province":"FL",
    "sg:tags":[
        "photography",
        "videography",
        "photographers-commercial",
        "wedding"
    ],
    "wof:name":"Nancy Librizzi Photography",
    "wof:placetype":"venue"
},
  "geometry": {"coordinates":[-80.10419899999999,26.891282],"type":"Point"}
}