{
  "type": "Feature",
  "properties": {
    "iso:country":"US",
    "sg:address":"1168 E Donegan Ave",
    "sg:city":"Kissimmee",
    "sg:classifiers":[
        {
            "category":"Personal",
            "subcategory":"Barber",
            "type":"Services"
        }
    ],
    "sg:phone":"+1 407 931 0999",
    "sg:postcode":"34744",
    "sg:province":"FL",
    "wof:name":"Hot Spot",
    "wof:placetype":"venue"
},
  "geometry": {"coordinates":[-81.39242299999999,28.318881],"type":"Point"}
}