{
  "type": "Feature",
  "properties": {
    "addr:full":"9500 NW 79th Ave Ste 13 Hialeah FL 33016",
    "addr:housenumber":"9500;13",
    "addr:postcode":"33016",
    "addr:street":"Nw 79Th Ave Ste",
    "iso:country":"US",
    "sg:address":"9500 NW 79th Ave Ste 13",
    "sg:city":"Hialeah",
    "sg:classifiers":[
        {
            "category":"Food & Beverages",
            "subcategory":"Specialty",
            "type":"Retail Goods"
        }
    ],
    "sg:phone":"+1 305 823 3116",
    "sg:postcode":"33016",
    "sg:province":"FL",
    "sg:tags":[
        "product",
        "health",
        "diet"
    ],
    "wof:name":"Natural Forces Nutriproducts Corp",
    "wof:placetype":"venue"
},
  "geometry": {"coordinates":[-80.325577,25.859779],"type":"Point"}
}