{
  "type": "Feature",
  "properties": {
    "iso:country":"US",
    "sg:address":"14020 Us Highway 1",
    "sg:city":"North Palm Beach",
    "sg:classifiers":[
        {
            "category":"Restaurant",
            "type":"Food & Drink"
        }
    ],
    "sg:menulink":"http://www.allmenus.com/fl/jupiter/16340-kee-grill/menu/",
    "sg:phone":"+1 561 995 5044",
    "sg:postcode":"33408",
    "sg:province":"FL",
    "sg:tags":[
        "wrap",
        "seafood",
        "sandwich",
        "american",
        "pub"
    ],
    "wof:name":"Kee Grill",
    "wof:placetype":"venue"
},
  "geometry": {"coordinates":[-80.055447,26.882006],"type":"Point"}
}