{
  "type": "Feature",
  "properties": {
    "addr:full":"2550 26th St W Bradenton FL 34205",
    "addr:housenumber":"2550",
    "addr:postcode":"34205",
    "addr:street":"26Th St W",
    "iso:country":"US",
    "sg:address":"2550 26th St W",
    "sg:city":"Bradenton",
    "sg:classifiers":[
        {
            "category":"Professional",
            "subcategory":"Accounting & Tax Preparation",
            "type":"Services"
        }
    ],
    "sg:phone":"+1 941 753 7925",
    "sg:postcode":"34205",
    "sg:province":"FL",
    "sg:tags":[
        "payroll",
        "processing",
        "datum",
        "doe"
    ],
    "wof:name":"Paymaster Service Corp",
    "wof:placetype":"venue"
},
  "geometry": {"coordinates":[-82.587782,27.477576],"type":"Point"}
}