{
  "type": "Feature",
  "properties": {
    "iso:country":"US",
    "sg:address":"1700 Old Middleburg Rd N",
    "sg:city":"Jacksonville",
    "sg:classifiers":[
        {
            "category":"Education",
            "subcategory":"Special Training",
            "type":"Public Place"
        }
    ],
    "sg:phone":"+1 904 693 7620",
    "sg:postcode":"32210",
    "sg:province":"FL",
    "sg:tags":[
        "educational"
    ],
    "wof:name":"Ed White Njrotc",
    "wof:placetype":"venue"
},
  "geometry": {"coordinates":[-81.76511600000001,30.291899],"type":"Point"}
}