{
  "type": "Feature",
  "properties": {
    "iso:country":"US",
    "sg:address":"3276 W Scott St",
    "sg:city":"Pensacola",
    "sg:classifiers":[
        {
            "category":"Building & Trades",
            "subcategory":"Construction",
            "type":"Services"
        }
    ],
    "sg:phone":"+1 850 470 9827",
    "sg:postcode":"32505",
    "sg:province":"FL",
    "sg:tags":[
        "waterproofing",
        "contractor"
    ],
    "wof:name":"Gulf Coast Inspection",
    "wof:placetype":"venue"
},
  "geometry": {"coordinates":[-87.253811,30.438207],"type":"Point"}
}