{
  "type": "Feature",
  "properties": {
    "iso:country":"US",
    "sg:address":"2001 46th St SW",
    "sg:city":"Naples",
    "sg:classifiers":[
        {
            "category":"Personal",
            "type":"Services"
        }
    ],
    "sg:phone":"+1 239 353 5588",
    "sg:postcode":"34116",
    "sg:province":"FL",
    "sg:tags":[
        "therapist",
        "massage"
    ],
    "wof:name":"Massage Services Of Florida",
    "wof:placetype":"venue"
},
  "geometry": {"coordinates":[-81.70009400000001,26.190647],"type":"Point"}
}