{
  "type": "Feature",
  "properties": {
    "iso:country":"US",
    "sg:address":"341 N Maitland Ave",
    "sg:city":"Maitland",
    "sg:classifiers":[
        {
            "category":"Banks & Credit Unions",
            "subcategory":"Investment Brokerage",
            "type":"Services"
        }
    ],
    "sg:phone":"+1 407 774 6815",
    "sg:postcode":"32751",
    "sg:province":"FL",
    "sg:tags":[
        "consultant",
        "planning",
        "financial"
    ],
    "wof:name":"Dorman Financial Management",
    "wof:placetype":"venue"
},
  "geometry": {"coordinates":[-81.365683,28.630831],"type":"Point"}
}