{
  "type": "Feature",
  "properties": {
    "addr:full":"1481 E Wind Blvd Kissimmee FL 34746",
    "addr:housenumber":"1481",
    "addr:postcode":"34746",
    "addr:street":"E Wind Blvd",
    "iso:country":"US",
    "sg:address":"1481 E Wind Blvd",
    "sg:city":"Kissimmee",
    "sg:classifiers":[
        {
            "category":"Wholesale",
            "subcategory":"Groceries",
            "type":"Manufacturing & Wholesale Goods"
        }
    ],
    "sg:phone":"+1 321 443 9906",
    "sg:postcode":"34746",
    "sg:province":"FL",
    "wof:name":"Rick Grohosky Distributing",
    "wof:placetype":"venue"
},
  "geometry": {"coordinates":[-81.469111,28.304759],"type":"Point"}
}