{
  "type": "Feature",
  "properties": {
    "iso:country":"US",
    "sg:address":"330 W 74th Pl",
    "sg:city":"Hialeah",
    "sg:classifiers":[
        {
            "category":"Building & Trades",
            "subcategory":"Landscaping Services",
            "type":"Services"
        }
    ],
    "sg:phone":"+1 305 825 1595",
    "sg:postcode":"33014",
    "sg:province":"FL",
    "wof:name":"Gonza Landscaping Svc",
    "wof:placetype":"venue"
},
  "geometry": {"coordinates":[-80.29021400000001,25.889763],"type":"Point"}
}