{
  "type": "Feature",
  "properties": {
    "addr:full":"1882 Bellair Blvd Orange Park FL 32073",
    "addr:housenumber":"1882",
    "addr:postcode":"32073",
    "addr:street":"Bellair Blvd",
    "iso:country":"US",
    "sg:address":"1882 Bellair Blvd",
    "sg:city":"Orange Park",
    "sg:classifiers":[
        {
            "category":"Building & Trades",
            "subcategory":"Construction",
            "type":"Services"
        }
    ],
    "sg:phone":"+1 904 264 0123",
    "sg:postcode":"32073",
    "sg:province":"FL",
    "sg:tags":[
        "general",
        "contractor"
    ],
    "wof:name":"E Vaughan Rivers Inc",
    "wof:placetype":"venue"
},
  "geometry": {"coordinates":[-81.730155,30.166254],"type":"Point"}
}