{
  "type": "Feature",
  "properties": {
    "addr:full":"203 Gaffney Rd Eglin Afb FL 32542",
    "addr:housenumber":"203",
    "addr:postcode":"32542",
    "addr:street":"Gaffney Rd",
    "iso:country":"US",
    "sg:address":"203 Gaffney Rd",
    "sg:city":"Eglin Afb",
    "sg:classifiers":[
        {
            "category":"Personal",
            "subcategory":"Beauty Salon",
            "type":"Services"
        }
    ],
    "sg:phone":"+1 850 651 0935",
    "sg:postcode":"32542",
    "sg:province":"FL",
    "sg:tags":[
        "make",
        "studio"
    ],
    "wof:name":"Avon Independent Sales Rep",
    "wof:placetype":"venue"
},
  "geometry": {"coordinates":[-86.543384,30.467518],"type":"Point"}
}