{
  "type": "Feature",
  "properties": {
    "iso:country":"US",
    "sg:address":"7155 Cedar Point Dr",
    "sg:city":"New Port Richey",
    "sg:classifiers":[
        {
            "category":"Retail",
            "subcategory":"Repair Shop",
            "type":"Services"
        }
    ],
    "sg:phone":"+1 727 809 1153",
    "sg:postcode":"34653",
    "sg:province":"FL",
    "sg:tags":[
        "welding"
    ],
    "wof:name":"Kieth Strickland Welding",
    "wof:placetype":"venue"
},
  "geometry": {"coordinates":[-82.695615,28.25473],"type":"Point"}
}