{
  "type": "Feature",
  "properties": {
    "iso:country":"US",
    "sg:address":"315 S Orange Blossom Trl B",
    "sg:city":"Orlando",
    "sg:classifiers":[
        {
            "category":"Retail",
            "subcategory":"Auto Repair",
            "type":"Services"
        }
    ],
    "sg:phone":"+1 407 849 0402",
    "sg:postcode":"32805",
    "sg:province":"FL",
    "wof:name":"Best Quality Auto Repair",
    "wof:placetype":"venue"
},
  "geometry": {"coordinates":[-81.397231,28.539067],"type":"Point"}
}