{
  "type": "Feature",
  "properties": {
    "addr:full":"106 Skipper Ave Fort Walton Bch FL 32547",
    "addr:housenumber":"106",
    "addr:postcode":"32547",
    "addr:street":"Skipper Ave Fort",
    "iso:country":"US",
    "sg:address":"106 Skipper Ave",
    "sg:city":"Fort Walton Bch",
    "sg:classifiers":[
        {
            "category":"Professional",
            "subcategory":"Accounting & Tax Preparation",
            "type":"Services"
        }
    ],
    "sg:phone":"+1 850 862 2193",
    "sg:postcode":"32547",
    "sg:province":"FL",
    "sg:tags":[
        "accountant"
    ],
    "wof:name":"Ronald G Noblin CPA",
    "wof:placetype":"venue"
},
  "geometry": {"coordinates":[-86.604857,30.443515],"type":"Point"}
}