{
  "type": "Feature",
  "properties": {
    "addr:full":"429 Beville Rd South Daytona FL 32119",
    "addr:housenumber":"429",
    "addr:postcode":"32119",
    "addr:street":"Beville Rd",
    "iso:country":"US",
    "sg:address":"429 Beville Rd",
    "sg:city":"South Daytona",
    "sg:classifiers":[
        {
            "category":"Freight",
            "type":"Transportation"
        }
    ],
    "sg:phone":"+1 386 304 8694",
    "sg:postcode":"32119",
    "sg:province":"FL",
    "wof:name":"Ryder Integrated Logistics Inc",
    "wof:placetype":"venue"
},
  "geometry": {"coordinates":[-81.01334799999999,29.181491],"type":"Point"}
}