{
  "type": "Feature",
  "properties": {
    "addr:full":"41025 Thomas Boat Landing Rd Umatilla FL 32784",
    "addr:housenumber":"41025",
    "addr:postcode":"32784",
    "addr:street":"Thomas Boat Landing Rd",
    "iso:country":"US",
    "sg:address":"41025 Thomas Boat Landing Rd",
    "sg:city":"Umatilla",
    "sg:classifiers":[
        {
            "category":"Professional",
            "type":"Services"
        },
        {
            "category":"Personal",
            "type":"Services"
        },
        {
            "category":"Professional",
            "subcategory":"Lawyer & Legal Services",
            "type":"Services"
        }
    ],
    "sg:phone":"+1 352 350 5700",
    "sg:postcode":"32784",
    "sg:province":"FL",
    "sg:tags":[
        "arbitration",
        "counseling",
        "mediation"
    ],
    "sg:website":"http://www.sadles.net",
    "wof:name":"Sadles Inc",
    "wof:placetype":"venue"
},
  "geometry": {"coordinates":[-81.761641,28.946845],"type":"Point"}
}