{
  "type": "Feature",
  "properties": {
    "iso:country":"US",
    "sg:address":"4070 Co Rd 124A",
    "sg:city":"Wildwood",
    "sg:classifiers":[
        {
            "category":"Building & Trades",
            "subcategory":"Construction",
            "type":"Services"
        }
    ],
    "sg:phone":"+1 352 748 9066",
    "sg:postcode":"34785",
    "sg:province":"FL",
    "sg:tags":[
        "dry wall",
        "contractor"
    ],
    "wof:name":"Carl M Friemuth Dry Wall Inc",
    "wof:placetype":"venue"
},
  "geometry": {"coordinates":[-82.035636,28.895818],"type":"Point"}
}