{
  "type": "Feature",
  "properties": {
    "iso:country":"US",
    "sg:address":"6703 W Hwy 98",
    "sg:city":"Panama City",
    "sg:classifiers":[
        {
            "category":"Government",
            "subcategory":"Office",
            "type":"Public Place"
        }
    ],
    "sg:phone":"+1 850 234 4374",
    "sg:postcode":"32407",
    "sg:province":"FL",
    "sg:tags":[
        "navy",
        "life",
        "quality"
    ],
    "wof:name":"Morale Welfare & Recreation",
    "wof:placetype":"venue"
},
  "geometry": {"coordinates":[-85.75349300000001,30.18824],"type":"Point"}
}