{
  "type": "Feature",
  "properties": {
    "addr:full":"383 Tequesta Dr Tequesta FL 33469",
    "addr:housenumber":"383",
    "addr:postcode":"33469",
    "addr:street":"Tequesta Dr",
    "iso:country":"US",
    "sg:address":"383 Tequesta Dr",
    "sg:city":"Tequesta",
    "sg:classifiers":[
        {
            "category":"Shopping",
            "subcategory":"Jewelry",
            "type":"Retail Goods"
        }
    ],
    "sg:phone":"+1 561 744 0728",
    "sg:postcode":"33469",
    "sg:province":"FL",
    "sg:tags":[
        "jeweler"
    ],
    "wof:name":"Goldsmith",
    "wof:placetype":"venue"
},
  "geometry": {"coordinates":[-80.094336,26.9588],"type":"Point"}
}