{
  "type": "Feature",
  "properties": {
    "addr:full":"227 N Collier Blvd Marco Island FL 34145",
    "addr:housenumber":"227;collier blvd",
    "addr:postcode":"34145",
    "addr:street":"N",
    "iso:country":"US",
    "sg:address":"227 N Collier Blvd",
    "sg:city":"Marco Island",
    "sg:classifiers":[
        {
            "category":"Food & Beverages",
            "subcategory":"Groceries & Convenience Stores",
            "type":"Retail Goods"
        }
    ],
    "sg:phone":"+1 239 389 0404",
    "sg:postcode":"34145",
    "sg:province":"FL",
    "wof:name":"KWIK Stop",
    "wof:placetype":"venue"
},
  "geometry": {"coordinates":[-81.732545,25.943002],"type":"Point"}
}