{
  "type": "Feature",
  "properties": {
    "iso:country":"US",
    "sg:address":"713 SE 2nd St",
    "sg:city":"Belle Glade",
    "sg:classifiers":[
        {
            "category":"Retail",
            "subcategory":"Auto Rental",
            "type":"Services"
        }
    ],
    "sg:phone":"+1 561 993 3936",
    "sg:postcode":"33430",
    "sg:province":"FL",
    "sg:tags":[
        "truck"
    ],
    "wof:name":"Holsey Sanders",
    "wof:placetype":"venue"
},
  "geometry": {"coordinates":[-80.668145,26.678079],"type":"Point"}
}