{
  "type": "Feature",
  "properties": {
    "iso:country":"US",
    "sg:address":"9065 Saddlecreek Dr",
    "sg:city":"Boca Raton",
    "sg:classifiers":[
        {
            "category":"Building & Trades",
            "subcategory":"Cleaning & Sanitation",
            "type":"Services"
        }
    ],
    "sg:phone":"+1 561 716 7886",
    "sg:postcode":"33496",
    "sg:province":"FL",
    "sg:tags":[
        "janitor"
    ],
    "wof:name":"Imtiaze Nazamally Office Clean",
    "wof:placetype":"venue"
},
  "geometry": {"coordinates":[-80.18799,26.402928],"type":"Point"}
}