{
  "type": "Feature",
  "properties": {
    "iso:country":"US",
    "sg:address":"2477 J and C Blvd",
    "sg:city":"Naples",
    "sg:classifiers":[
        {
            "category":"Building & Trades",
            "subcategory":"Construction",
            "type":"Services"
        }
    ],
    "sg:phone":"+1 239 566 1007",
    "sg:postcode":"34109",
    "sg:province":"FL",
    "sg:tags":[
        "roofing",
        "contractor"
    ],
    "wof:name":"Crowther Roofing & Sheet",
    "wof:placetype":"venue"
},
  "geometry": {"coordinates":[-81.77698700000001,26.223883],"type":"Point"}
}