{
  "type": "Feature",
  "properties": {
    "iso:country":"US",
    "sg:address":"2100 Ponce de Leon Blvd",
    "sg:city":"Coral Gables",
    "sg:classifiers":[
        {
            "category":"Home & Garden",
            "subcategory":"Furniture",
            "type":"Retail Goods"
        }
    ],
    "sg:phone":"+1 305 476 8717",
    "sg:postcode":"33134",
    "sg:province":"FL",
    "wof:name":"Pearl Dragon Collections",
    "wof:placetype":"venue"
},
  "geometry": {"coordinates":[-80.258758,25.753033],"type":"Point"}
}