{
  "type": "Feature",
  "properties": {
    "iso:country":"US",
    "sg:address":"6844 NW 77th Ct",
    "sg:city":"Miami",
    "sg:classifiers":[
        {
            "category":"Wholesale",
            "subcategory":"Groceries",
            "type":"Manufacturing & Wholesale Goods"
        }
    ],
    "sg:phone":"+1 305 477 2256",
    "sg:postcode":"33166",
    "sg:province":"FL",
    "sg:tags":[
        "food",
        "products-wholesale"
    ],
    "wof:name":"Sim-Tex Industries",
    "wof:placetype":"venue"
},
  "geometry": {"coordinates":[-80.322383,25.835869],"type":"Point"}
}