{
  "type": "Feature",
  "properties": {
    "iso:country":"US",
    "sg:address":"100 Placid Lake Dr",
    "sg:city":"Sanford",
    "sg:classifiers":[
        {
            "category":"Education",
            "subcategory":"School",
            "type":"Public Place"
        }
    ],
    "sg:phone":"+1 407 320 1250",
    "sg:postcode":"32773",
    "sg:province":"FL",
    "wof:name":"Wicklow Elementary School",
    "wof:placetype":"venue"
},
  "geometry": {"coordinates":[-81.293139,28.778959],"type":"Point"}
}