{
  "type": "Feature",
  "properties": {
    "iso:country":"US",
    "sg:address":"2742 Elkcam Blvd",
    "sg:city":"Deltona",
    "sg:phone":"+1 386 532 4247",
    "sg:postcode":"32738",
    "sg:province":"FL",
    "wof:name":"Seabreeze Family Hair Styling",
    "wof:placetype":"venue"
},
  "geometry": {"coordinates":[-81.19092999999999,28.92595],"type":"Point"}
}