{
  "type": "Feature",
  "properties": {
    "addr:full":"133 Pembrooke Dr Palm Beach Gardens FL 33418",
    "addr:housenumber":"133",
    "addr:postcode":"33418",
    "addr:street":"Pembrooke Dr",
    "iso:country":"US",
    "sg:address":"133 Pembrooke Dr",
    "sg:city":"Palm Beach Gardens",
    "sg:classifiers":[
        {
            "category":"Real Estate",
            "subcategory":"Real Estate Operator",
            "type":"Services"
        }
    ],
    "sg:phone":"+1 561 799 0084",
    "sg:postcode":"33418",
    "sg:province":"FL",
    "sg:tags":[
        "building",
        "nonresidential"
    ],
    "wof:name":"K & D Gulf Properties LLC",
    "wof:placetype":"venue"
},
  "geometry": {"coordinates":[-80.11162400000001,26.821239],"type":"Point"}
}