{
  "type": "Feature",
  "properties": {
    "addr:full":"130 S Geronimo St Destin FL 32550",
    "addr:housenumber":"130",
    "addr:postcode":"32550",
    "addr:street":"S Geronimo St",
    "iso:country":"US",
    "sg:address":"130 S Geronimo St",
    "sg:city":"Destin",
    "sg:classifiers":[
        {
            "category":"Real Estate",
            "subcategory":"Real Estate Agent",
            "type":"Services"
        }
    ],
    "sg:phone":"+1 850 654 4010",
    "sg:postcode":"32550",
    "sg:province":"FL",
    "sg:tags":[
        "appraiser"
    ],
    "wof:name":"Sugar Sand Realty Svc",
    "wof:placetype":"venue"
},
  "geometry": {"coordinates":[-86.359617,30.377657],"type":"Point"}
}