{
  "type": "Feature",
  "properties": {
    "iso:country":"US",
    "sg:address":"401 NW 2nd Ave Ste N708",
    "sg:city":"Miami",
    "sg:classifiers":[
        {
            "category":"Professional",
            "subcategory":"Detective & Security Services",
            "type":"Services"
        },
        {
            "category":"Government",
            "subcategory":"Office",
            "type":"Public Place"
        }
    ],
    "sg:phone":"+1 305 810 1111",
    "sg:postcode":"33128",
    "sg:province":"FL",
    "sg:tags":[
        "government-state",
        "government-united",
        "state",
        "private",
        "investigator"
    ],
    "sg:website":"http://www.flofr.com",
    "wof:name":"South Florida",
    "wof:placetype":"venue"
},
  "geometry": {"coordinates":[-80.197838,25.77787],"type":"Point"}
}