{
  "type": "Feature",
  "properties": {
    "iso:country":"US",
    "sg:address":"1843 NE 185th St",
    "sg:city":"Miami",
    "sg:classifiers":[
        {
            "category":"Personal",
            "subcategory":"Beauty Salon",
            "type":"Services"
        }
    ],
    "sg:phone":"+1 305 932 8251",
    "sg:postcode":"33179",
    "sg:province":"FL",
    "sg:tags":[
        "shop"
    ],
    "wof:name":"Ultimate Hair Design Inc",
    "wof:placetype":"venue"
},
  "geometry": {"coordinates":[-80.162898,25.946068],"type":"Point"}
}