{
  "type": "Feature",
  "properties": {
    "addr:full":"2333 N Beaumont Ave Kissimmee FL 34741",
    "addr:housenumber":"2333",
    "addr:postcode":"34741",
    "addr:street":"N Beaumont Ave",
    "iso:country":"US",
    "sg:address":"2333 N Beaumont Ave",
    "sg:city":"Kissimmee",
    "sg:classifiers":[
        {
            "category":"Retail",
            "subcategory":"Repair Shop",
            "type":"Services"
        }
    ],
    "sg:phone":"+1 407 343 8500",
    "sg:postcode":"34741",
    "sg:province":"FL",
    "sg:tags":[
        "equipment",
        "industrial"
    ],
    "wof:name":"Kent Solano Pumps & Motors",
    "wof:placetype":"venue"
},
  "geometry": {"coordinates":[-81.409925,28.317466],"type":"Point"}
}