{
  "type": "Feature",
  "properties": {
    "iso:country":"US",
    "sg:address":"234 Hatteras Ave",
    "sg:city":"Clermont",
    "sg:classifiers":[
        {
            "category":"Shopping",
            "subcategory":"Party Supplies",
            "type":"Retail Goods"
        },
        {
            "category":"Building & Trades",
            "subcategory":"Equipment Rental",
            "type":"Services"
        }
    ],
    "sg:phone":"+1 352 241 0423",
    "sg:postcode":"34711",
    "sg:province":"FL",
    "sg:tags":[
        "decoration",
        "contractors'"
    ],
    "wof:name":"Jan's Party Rental",
    "wof:placetype":"venue"
},
  "geometry": {"coordinates":[-81.733299,28.565673],"type":"Point"}
}