{
  "type": "Feature",
  "properties": {
    "iso:country":"US",
    "sg:address":"210 S Pinellas Ave",
    "sg:city":"Tarpon Springs",
    "sg:classifiers":[
        {
            "category":"Professional",
            "subcategory":"Lawyer & Legal Services",
            "type":"Services"
        }
    ],
    "sg:phone":"+1 727 698 8655",
    "sg:postcode":"34689",
    "sg:province":"FL",
    "wof:name":"Dennison & King",
    "wof:placetype":"venue"
},
  "geometry": {"coordinates":[-82.756551,28.144187],"type":"Point"}
}