{
  "type": "Feature",
  "properties": {
    "addr:full":"4517 Cactus Ave Sarasota FL 34231",
    "addr:housenumber":"4517",
    "addr:postcode":"34231",
    "addr:street":"Cactus Ave",
    "iso:country":"US",
    "sg:address":"4517 Cactus Ave",
    "sg:city":"Sarasota",
    "sg:classifiers":[
        {
            "category":"Building & Trades",
            "subcategory":"Electrical",
            "type":"Services"
        }
    ],
    "sg:phone":"+1 941 923 2184",
    "sg:postcode":"34231",
    "sg:province":"FL",
    "sg:tags":[
        "electrical",
        "contractor"
    ],
    "wof:name":"Clinton Corporation",
    "wof:placetype":"venue"
},
  "geometry": {"coordinates":[-82.504705,27.289337],"type":"Point"}
}