{
  "type": "Feature",
  "properties": {
    "addr:full":"2 W Dixie Hwy Dania FL 33004",
    "addr:housenumber":"2",
    "addr:postcode":"33004",
    "addr:street":"W Dixie Hwy",
    "iso:country":"US",
    "sg:address":"2 W Dixie Hwy",
    "sg:city":"Dania",
    "sg:classifiers":[
        {
            "category":"Social Services",
            "subcategory":"Job Training",
            "type":"Services"
        }
    ],
    "sg:phone":"+1 954 921 7254",
    "sg:postcode":"33004",
    "sg:province":"FL",
    "sg:tags":[
        "research"
    ],
    "wof:name":"Starcenter",
    "wof:placetype":"venue"
},
  "geometry": {"coordinates":[-80.14529400000001,26.039534],"type":"Point"}
}