{
  "type": "Feature",
  "properties": {
    "iso:country":"US",
    "sg:address":"7035 SW 47th St",
    "sg:city":"Miami",
    "sg:classifiers":[
        {
            "category":"Building & Trades",
            "subcategory":"Electrical",
            "type":"Services"
        }
    ],
    "sg:phone":"+1 305 669 1776",
    "sg:postcode":"33155",
    "sg:province":"FL",
    "sg:tags":[
        "electrician",
        "contractor"
    ],
    "sg:website":"http://www.thunder-electric.com",
    "wof:name":"Thunder Electrical Contractors Inc",
    "wof:placetype":"venue"
},
  "geometry": {"coordinates":[-80.308401,25.72644],"type":"Point"}
}