{
  "type": "Feature",
  "properties": {
    "iso:country":"US",
    "sg:address":"6350 W Indiantown Rd",
    "sg:city":"Jupiter",
    "sg:classifiers":[
        {
            "category":"Restaurant",
            "type":"Food & Drink"
        }
    ],
    "sg:phone":"+1 561 744 8327",
    "sg:postcode":"33458",
    "sg:province":"FL",
    "sg:tags":[
        "eating"
    ],
    "wof:name":"Athenian Cafe Inc",
    "wof:placetype":"venue"
},
  "geometry": {"coordinates":[-80.132639,26.934464],"type":"Point"}
}