{
  "type": "Feature",
  "properties": {
    "iso:country":"US",
    "sg:address":"235 Hawkeye View Ln",
    "sg:city":"St Augustine",
    "sg:classifiers":[
        {
            "category":"Professional",
            "type":"Services"
        }
    ],
    "sg:phone":"+1 904 829 0121",
    "sg:postcode":"32095",
    "sg:province":"FL",
    "sg:tags":[
        "establishment"
    ],
    "wof:name":"Navesink Corp",
    "wof:placetype":"venue"
},
  "geometry": {"coordinates":[-81.344517,29.968494],"type":"Point"}
}