{
  "type": "Feature",
  "properties": {
    "iso:country":"US",
    "sg:address":"315 N Marion St",
    "sg:city":"Lake City",
    "sg:classifiers":[
        {
            "category":"Retail",
            "subcategory":"Repair Shop",
            "type":"Services"
        }
    ],
    "sg:phone":"+1 386 752 5310",
    "sg:postcode":"32055",
    "sg:province":"FL",
    "sg:tags":[
        "repairing",
        "lawn",
        "mower"
    ],
    "wof:name":"Hair's Mower Parts & Repair",
    "wof:placetype":"venue"
},
  "geometry": {"coordinates":[-82.637102,30.191949],"type":"Point"}
}