{
  "type": "Feature",
  "properties": {
    "addr:full":"3651 NE 133rd St Anthony FL 32617",
    "addr:housenumber":"3651",
    "addr:postcode":"32617",
    "addr:street":"Ne 133Rd",
    "iso:country":"US",
    "sg:address":"3651 NE 133rd St",
    "sg:city":"Anthony",
    "sg:classifiers":[
        {
            "category":"Retail",
            "subcategory":"Portrait Studio",
            "type":"Services"
        }
    ],
    "sg:phone":"+1 352 369 1191",
    "sg:postcode":"32617",
    "sg:province":"FL",
    "sg:tags":[
        "photographer"
    ],
    "wof:name":"Visions By Diane",
    "wof:placetype":"venue"
},
  "geometry": {"coordinates":[-82.085571,29.343818],"type":"Point"}
}