{
  "type": "Feature",
  "properties": {
    "iso:country":"US",
    "sg:address":"1815 Thomasville Rd",
    "sg:city":"Tallahassee",
    "sg:classifiers":[
        {
            "category":"Shopping",
            "subcategory":"Gifts & Souvenirs",
            "type":"Retail Goods"
        },
        {
            "category":"Shopping",
            "subcategory":"Books",
            "type":"Retail Goods"
        }
    ],
    "sg:phone":"+1 850 224 3320",
    "sg:postcode":"32303",
    "sg:province":"FL",
    "sg:tags":[
        "shop",
        "dealer"
    ],
    "wof:name":"Guadalupe Catholic Bks & Gifts",
    "wof:placetype":"venue"
},
  "geometry": {"coordinates":[-84.27002899999999,30.46456],"type":"Point"}
}