{
  "type": "Feature",
  "properties": {
    "addr:full":"7066 SW 4th St Miami FL 33144",
    "addr:housenumber":"7066",
    "addr:postcode":"33144",
    "addr:street":"Sw 4Th St",
    "iso:country":"US",
    "sg:address":"7066 SW 4th St",
    "sg:city":"Miami",
    "sg:classifiers":[
        {
            "category":"Shopping",
            "subcategory":"Party Supplies",
            "type":"Retail Goods"
        }
    ],
    "sg:phone":"+1 305 642 8841",
    "sg:postcode":"33144",
    "sg:province":"FL",
    "wof:name":"Casa Fiesta Party Supplies",
    "wof:placetype":"venue"
},
  "geometry": {"coordinates":[-80.309799,25.766701],"type":"Point"}
}