{
  "type": "Feature",
  "properties": {
    "iso:country":"US",
    "sg:address":"7334 Wailea Ave",
    "sg:city":"Boynton Beach",
    "sg:classifiers":[
        {
            "category":"Health Services",
            "subcategory":"Doctor",
            "type":"Services"
        }
    ],
    "sg:phone":"+1 561 752 0507",
    "sg:postcode":"33437",
    "sg:province":"FL",
    "wof:name":"Harry Rosen Dr",
    "wof:placetype":"venue"
},
  "geometry": {"coordinates":[-80.160196,26.505642],"type":"Point"}
}