{
  "type": "Feature",
  "properties": {
    "iso:country":"US",
    "sg:address":"308 Tequesta Dr",
    "sg:city":"Jupiter",
    "sg:classifiers":[
        {
            "category":"Real Estate",
            "subcategory":"Real Estate Agent",
            "type":"Services"
        }
    ],
    "sg:phone":"+1 561 743 0572",
    "sg:postcode":"33469",
    "sg:province":"FL",
    "wof:name":"Vander Waal Realty",
    "wof:placetype":"venue"
},
  "geometry": {"coordinates":[-80.09092200000001,26.958097],"type":"Point"}
}