{
  "type": "Feature",
  "properties": {
    "addr:full":"12763 Hunters Ridge Dr Bonita Springs FL 34135",
    "addr:housenumber":"12763",
    "addr:postcode":"34135",
    "addr:street":"Hunters Ridge Dr",
    "iso:country":"US",
    "sg:address":"12763 Hunters Ridge Dr",
    "sg:city":"Bonita Springs",
    "sg:classifiers":[
        {
            "category":"Real Estate",
            "subcategory":"Real Estate Agent",
            "type":"Services"
        }
    ],
    "sg:phone":"+1 239 992 8854",
    "sg:postcode":"34135",
    "sg:province":"FL",
    "wof:name":"Leslie Barreiro Realtor",
    "wof:placetype":"venue"
},
  "geometry": {"coordinates":[-81.739462,26.318944],"type":"Point"}
}