{
  "type": "Feature",
  "properties": {
    "addr:full":"840 W 84th St Hialeah FL 33014",
    "addr:housenumber":"840",
    "addr:postcode":"33014",
    "addr:street":"W 84Th St",
    "iso:country":"US",
    "sg:address":"840 W 84th St",
    "sg:city":"Hialeah",
    "sg:classifiers":[
        {
            "category":"Sports & Exercise",
            "subcategory":"Bicycle Rental",
            "type":"Entertainment"
        }
    ],
    "sg:phone":"+1 305 822 4606",
    "sg:postcode":"33014",
    "sg:province":"FL",
    "sg:tags":[
        "wear"
    ],
    "wof:name":"5th & Ocean Clothing Inc",
    "wof:placetype":"venue"
},
  "geometry": {"coordinates":[-80.301903,25.8988],"type":"Point"}
}