{
  "type": "Feature",
  "properties": {
    "iso:country":"US",
    "sg:address":"1961 Drew St",
    "sg:city":"Clearwater",
    "sg:classifiers":[
        {
            "category":"Retail",
            "subcategory":"Veterinary Services",
            "type":"Services"
        }
    ],
    "sg:phone":"+1 727 461 4960",
    "sg:postcode":"33765",
    "sg:province":"FL",
    "sg:tags":[
        "hospital",
        "animal"
    ],
    "wof:name":"Skycrest Animal Hospital Inc",
    "wof:placetype":"venue"
},
  "geometry": {"coordinates":[-82.75600300000001,27.967903],"type":"Point"}
}