{
  "type": "Feature",
  "properties": {
    "addr:full":"3210 Powers Ave Jacksonville FL 32207",
    "addr:housenumber":"3210",
    "addr:postcode":"32207",
    "addr:street":"Powers Ave",
    "iso:country":"US",
    "sg:address":"3210 Powers Ave",
    "sg:city":"Jacksonville",
    "sg:classifiers":[
        {
            "category":"Wholesale",
            "subcategory":"Machinery & Supplies",
            "type":"Manufacturing & Wholesale Goods"
        }
    ],
    "sg:phone":"+1 904 737 9919",
    "sg:postcode":"32207",
    "sg:province":"FL",
    "sg:tags":[
        "bearing",
        "industrial"
    ],
    "wof:name":"Miller Bearings Inc",
    "wof:placetype":"venue"
},
  "geometry": {"coordinates":[-81.622803,30.264479],"type":"Point"}
}