{
  "type": "Feature",
  "properties": {
    "iso:country":"US",
    "sg:address":"17550 Collins Ave",
    "sg:city":"Sunny Isl Bch",
    "sg:classifiers":[
        {
            "category":"Restaurant",
            "type":"Food & Drink"
        }
    ],
    "sg:phone":"+1 305 935 5838",
    "sg:postcode":"33160",
    "sg:province":"FL",
    "sg:website":"www.dennys.com",
    "wof:name":"Denny's Restaurant",
    "wof:placetype":"venue"
},
  "geometry": {"coordinates":[-80.121399,25.939301],"type":"Point"}
}