{
  "type": "Feature",
  "properties": {
    "iso:country":"US",
    "sg:address":"8931 W Oakland Park Blvd",
    "sg:city":"Sunrise",
    "sg:classifiers":[
        {
            "category":"Bars & Pubs",
            "type":"Food & Drink"
        }
    ],
    "sg:phone":"+1 954 749 1337",
    "sg:postcode":"33351",
    "sg:province":"FL",
    "sg:tags":[
        "lounge",
        "cocktail"
    ],
    "wof:name":"Buzz's Lounge",
    "wof:placetype":"venue"
},
  "geometry": {"coordinates":[-80.26888599999999,26.168472],"type":"Point"}
}