{
  "type": "Feature",
  "properties": {
    "addr:full":"2731 Spring Park Rd Jacksonville FL 32207",
    "addr:housenumber":"2731",
    "addr:postcode":"32207",
    "addr:street":"Spring Park Rd",
    "iso:country":"US",
    "sg:address":"2731 Spring Park Rd",
    "sg:city":"Jacksonville",
    "sg:classifiers":[
        {
            "category":"Transit Center",
            "subcategory":"Passenger",
            "type":"Transportation"
        },
        {
            "category":"Local Transit",
            "type":"Transportation"
        }
    ],
    "sg:phone":"+1 904 399 3441",
    "sg:postcode":"32207",
    "sg:province":"FL",
    "sg:tags":[
        "line",
        "public"
    ],
    "wof:name":"Atlantic Coast Shuttle",
    "wof:placetype":"venue"
},
  "geometry": {"coordinates":[-81.62923499999999,30.295751],"type":"Point"}
}