{
  "type": "Feature",
  "properties": {
    "iso:country":"US",
    "sg:address":"115 Philadelphia Blvd",
    "sg:city":"Palm Harbor",
    "sg:classifiers":[
        {
            "category":"Manufacturing",
            "subcategory":"Metals",
            "type":"Manufacturing & Wholesale Goods"
        }
    ],
    "sg:phone":"+1 727 786 8284",
    "sg:postcode":"34684",
    "sg:province":"FL",
    "sg:tags":[
        "manufacture",
        "product",
        "aluminum",
        "grail"
    ],
    "wof:name":"Dowells Aluminum Inc",
    "wof:placetype":"venue"
},
  "geometry": {"coordinates":[-82.736502,28.104083],"type":"Point"}
}