{
  "type": "Feature",
  "properties": {
    "addr:full":"7460 SW 10th St Pompano Beach FL 33068",
    "addr:housenumber":"7460",
    "addr:postcode":"33068",
    "addr:street":"Sw 10Th St",
    "iso:country":"US",
    "sg:address":"7460 SW 10th St",
    "sg:city":"Pompano Beach",
    "sg:classifiers":[
        {
            "category":"Shopping",
            "subcategory":"Music",
            "type":"Retail Goods"
        }
    ],
    "sg:phone":"+1 954 726 7491",
    "sg:postcode":"33068",
    "sg:province":"FL",
    "wof:name":"Center Forward Records Inc",
    "wof:placetype":"venue"
},
  "geometry": {"coordinates":[-80.224035,26.21639],"type":"Point"}
}