{
  "type": "Feature",
  "properties": {
    "iso:country":"US",
    "sg:address":"4964 Acorn Dr",
    "sg:city":"Boca Raton",
    "sg:classifiers":[
        {
            "category":"Restaurant",
            "type":"Food & Drink"
        }
    ],
    "sg:phone":"+1 561 999 8939",
    "sg:postcode":"33487",
    "sg:province":"FL",
    "sg:tags":[
        "eating"
    ],
    "wof:name":"Carmines Cakes",
    "wof:placetype":"venue"
},
  "geometry": {"coordinates":[-80.121003,26.412356],"type":"Point"}
}