{
  "type": "Feature",
  "properties": {
    "iso:country":"US",
    "sg:address":"2033 Eastbourne Way",
    "sg:city":"Orlando",
    "sg:classifiers":[
        {
            "category":"Wholesale",
            "subcategory":"Computers",
            "type":"Manufacturing & Wholesale Goods"
        }
    ],
    "sg:phone":"+1 407 382 0010",
    "sg:postcode":"32812",
    "sg:province":"FL",
    "sg:tags":[
        "equipment",
        "processing",
        "datum"
    ],
    "wof:name":"Storage Tek",
    "wof:placetype":"venue"
},
  "geometry": {"coordinates":[-81.317061,28.519785],"type":"Point"}
}