{
  "type": "Feature",
  "properties": {
    "addr:full":"3906 US Hwy 98 E Santa Rosa Beach FL 32459",
    "addr:housenumber":"3906",
    "addr:postcode":"32459",
    "addr:street":"Us Hwy 98 E Santa Rosa Beach",
    "iso:country":"US",
    "sg:address":"3906 US Hwy 98 E",
    "sg:city":"Santa Rosa Beach",
    "sg:classifiers":[
        {
            "category":"Restaurant",
            "type":"Food & Drink"
        }
    ],
    "sg:phone":"+1 850 622 6270",
    "sg:postcode":"32459",
    "sg:province":"FL",
    "sg:tags":[
        "caterer"
    ],
    "wof:name":"Emerald Coast Catering",
    "wof:placetype":"venue"
},
  "geometry": {"coordinates":[-86.11485,30.35708],"type":"Point"}
}