{
  "type": "Feature",
  "properties": {
    "addr:full":"11522 SW 126th Ter Miami FL 33176",
    "addr:housenumber":"11522",
    "addr:postcode":"33176",
    "addr:street":"Sw 126Th Ter",
    "iso:country":"US",
    "sg:address":"11522 SW 126th Ter",
    "sg:city":"Miami",
    "sg:classifiers":[
        {
            "category":"Building & Trades",
            "subcategory":"Plumbing",
            "type":"Services"
        }
    ],
    "sg:phone":"+1 305 233 4844",
    "sg:postcode":"33176",
    "sg:province":"FL",
    "sg:tags":[
        "plumber",
        "contractor"
    ],
    "wof:name":"All Dade Plumbing Inc",
    "wof:placetype":"venue"
},
  "geometry": {"coordinates":[-80.381433,25.651071],"type":"Point"}
}