{
  "type": "Feature",
  "properties": {
    "iso:country":"US",
    "sg:address":"626 S Miami Ave",
    "sg:city":"Miami",
    "sg:classifiers":[
        {
            "category":"Arts & Performance",
            "subcategory":"Music",
            "type":"Entertainment"
        },
        {
            "category":"Bars & Pubs",
            "subcategory":"Dive Bar",
            "type":"Food & Drink"
        }
    ],
    "sg:phone":"+1 305 374 1198",
    "sg:postcode":"33130",
    "sg:province":"FL",
    "sg:tags":[
        "venue"
    ],
    "sg:website":"www.tobacco-road.com/",
    "wof:name":"Tobacco Road",
    "wof:placetype":"venue"
},
  "geometry": {"coordinates":[-80.19450399999999,25.7679],"type":"Point"}
}