{
  "type": "Feature",
  "properties": {
    "addr:full":"10080 W Mcnab Rd Tamarac FL 33321",
    "addr:housenumber":"10080",
    "addr:postcode":"33321",
    "addr:street":"W Mcnab Rd",
    "iso:country":"US",
    "sg:address":"10080 W Mcnab Rd",
    "sg:city":"Tamarac",
    "sg:classifiers":[
        {
            "category":"Professional",
            "subcategory":"Employment Agencies",
            "type":"Services"
        }
    ],
    "sg:phone":"+1 954 709 2975",
    "sg:postcode":"33321",
    "sg:province":"FL",
    "sg:tags":[
        "opportunity"
    ],
    "wof:name":"Intl Phone Recruiters Inc",
    "wof:placetype":"venue"
},
  "geometry": {"coordinates":[-80.28648,26.208201],"type":"Point"}
}