{
  "type": "Feature",
  "properties": {
    "addr:full":"4607 Arlette Ct Lake Worth FL 33461",
    "addr:housenumber":"4607",
    "addr:postcode":"33461",
    "addr:street":"Arlette Ct",
    "iso:country":"US",
    "sg:address":"4607 Arlette Ct",
    "sg:city":"Lake Worth",
    "sg:classifiers":[
        {
            "category":"Building & Trades",
            "subcategory":"Construction",
            "type":"Services"
        }
    ],
    "sg:phone":"+1 561 254 8397",
    "sg:postcode":"33461",
    "sg:province":"FL",
    "sg:tags":[
        "heavy"
    ],
    "wof:name":"Bennie Brown",
    "wof:placetype":"venue"
},
  "geometry": {"coordinates":[-80.10744,26.613615],"type":"Point"}
}