{
  "type": "Feature",
  "properties": {
    "iso:country":"US",
    "sg:address":"6701 NW 37th Ave",
    "sg:city":"Miami",
    "sg:classifiers":[
        {
            "category":"Building & Trades",
            "subcategory":"Construction",
            "type":"Services"
        }
    ],
    "sg:phone":"+1 305 693 8186",
    "sg:postcode":"33147",
    "sg:province":"FL",
    "sg:tags":[
        "system",
        "contractor",
        "air conditioning"
    ],
    "wof:name":"Panama Ac",
    "wof:placetype":"venue"
},
  "geometry": {"coordinates":[-80.257599,25.834455],"type":"Point"}
}