{
  "type": "Feature",
  "properties": {
    "iso:country":"US",
    "sg:address":"451 S Cypress Rd",
    "sg:city":"Pompano Beach",
    "sg:classifiers":[
        {
            "category":"Shopping",
            "type":"Retail Goods"
        }
    ],
    "sg:phone":"+1 954 782 8311",
    "sg:postcode":"33060",
    "sg:province":"FL",
    "sg:tags":[
        "cosmetic",
        "perfume"
    ],
    "wof:name":"Bazzar Beauty Supply",
    "wof:placetype":"venue"
},
  "geometry": {"coordinates":[-80.123305,26.226979],"type":"Point"}
}