{
  "type": "Feature",
  "properties": {
    "iso:country":"US",
    "sg:address":"1931 Old Dixie Hwy",
    "sg:city":"Vero Beach",
    "sg:classifiers":[
        {
            "category":"Restaurant",
            "type":"Food & Drink"
        }
    ],
    "sg:menulink":"http://www.allmenus.com/fl/vero-beach/16312-undertow/menu/",
    "sg:phone":"+1 772 770 0977",
    "sg:postcode":"32960",
    "sg:province":"FL",
    "sg:tags":[
        "new",
        "american"
    ],
    "wof:name":"Undertow",
    "wof:placetype":"venue"
},
  "geometry": {"coordinates":[-80.398596,27.637082],"type":"Point"}
}