{
  "type": "Feature",
  "properties": {
    "addr:full":"2501 N Orange Ave Orlando FL 32804",
    "addr:housenumber":"2501",
    "addr:postcode":"32804",
    "addr:street":"N Orange Ave",
    "iso:country":"US",
    "sg:address":"2501 N Orange Ave",
    "sg:city":"Orlando",
    "sg:classifiers":[
        {
            "category":"Health Services",
            "subcategory":"Doctor",
            "type":"Services"
        }
    ],
    "sg:phone":"+1 407 894 4693",
    "sg:postcode":"32804",
    "sg:province":"FL",
    "sg:tags":[
        "medical"
    ],
    "wof:name":"Metzger Pins Warren Ranjit",
    "wof:placetype":"venue"
},
  "geometry": {"coordinates":[-81.37289800000001,28.574972],"type":"Point"}
}