{
  "type": "Feature",
  "properties": {
    "addr:full":"520 Navarre Ave Coral Gables FL 33134",
    "addr:housenumber":"520",
    "addr:postcode":"33134",
    "addr:street":"Navarre Ave",
    "iso:country":"US",
    "sg:address":"520 Navarre Ave",
    "sg:city":"Coral Gables",
    "sg:classifiers":[
        {
            "category":"Professional",
            "subcategory":"Computer Services",
            "type":"Services"
        }
    ],
    "sg:phone":"+1 305 476 0001",
    "sg:postcode":"33134",
    "sg:province":"FL",
    "sg:tags":[
        "repair"
    ],
    "sg:website":"www.singularnetworks.com",
    "wof:name":"Singular Networks",
    "wof:placetype":"venue"
},
  "geometry": {"coordinates":[-80.265332,25.753795],"type":"Point"}
}