{
  "type": "Feature",
  "properties": {
    "iso:country":"US",
    "sg:address":"1642 W 40th St",
    "sg:city":"Hialeah",
    "sg:classifiers":[
        {
            "category":"Retail",
            "subcategory":"Auto Repair",
            "type":"Services"
        }
    ],
    "sg:phone":"+1 305 828 2882",
    "sg:postcode":"33012",
    "sg:province":"FL",
    "wof:name":"J T Auto Center Inc",
    "wof:placetype":"venue"
},
  "geometry": {"coordinates":[-80.316399,25.8582],"type":"Point"}
}