{
  "type": "Feature",
  "properties": {
    "iso:country":"US",
    "sg:address":"1733 Mercy Dr",
    "sg:city":"Orlando",
    "sg:classifiers":[
        {
            "category":"Social Services",
            "subcategory":"Child Care",
            "type":"Services"
        }
    ],
    "sg:phone":"+1 407 295 5040",
    "sg:postcode":"32808",
    "sg:province":"FL",
    "sg:tags":[
        "day"
    ],
    "wof:name":"Future Leaders Child Care Dev",
    "wof:placetype":"venue"
},
  "geometry": {"coordinates":[-81.43047799999999,28.565199],"type":"Point"}
}