{
  "type": "Feature",
  "properties": {
    "iso:country":"US",
    "sg:address":"1015 Sunshine Ln",
    "sg:city":"Altamonte Springs",
    "sg:classifiers":[
        {
            "category":"Wholesale",
            "subcategory":"Hardware",
            "type":"Manufacturing & Wholesale Goods"
        }
    ],
    "sg:phone":"+1 407 862 4925",
    "sg:postcode":"32714",
    "sg:province":"FL",
    "sg:tags":[
        "plumbing",
        "merchandise"
    ],
    "wof:name":"G & R Plumbing Enterprises",
    "wof:placetype":"venue"
},
  "geometry": {"coordinates":[-81.42242299999999,28.655574],"type":"Point"}
}