{
  "type": "Feature",
  "properties": {
    "addr:full":"4213 Queens Ct Milton FL 32571",
    "addr:housenumber":"4213",
    "addr:postcode":"32571",
    "addr:street":"Queens Ct",
    "iso:country":"US",
    "sg:address":"4213 Queens Ct",
    "sg:city":"Milton",
    "sg:classifiers":[
        {
            "category":"Professional",
            "type":"Services"
        }
    ],
    "sg:phone":"+1 850 994 0744",
    "sg:postcode":"32571",
    "sg:province":"FL",
    "wof:name":"Caring Hearts Prof Sitter Svc",
    "wof:placetype":"venue"
},
  "geometry": {"coordinates":[-87.14816500000001,30.592997],"type":"Point"}
}