{
  "type": "Feature",
  "properties": {
    "addr:full":"5505 Hanley Rd Tampa FL 33634",
    "addr:housenumber":"5505",
    "addr:postcode":"33634",
    "addr:street":"Hanley Rd",
    "iso:country":"US",
    "sg:address":"5505 Hanley Rd",
    "sg:city":"Tampa",
    "sg:classifiers":[
        {
            "category":"Autos & Motor Vehicles",
            "subcategory":"Auto Supplies",
            "type":"Retail Goods"
        }
    ],
    "sg:phone":"+1 813 885 7651",
    "sg:postcode":"33634",
    "sg:province":"FL",
    "sg:tags":[
        "tire"
    ],
    "wof:name":"Firestone Tire & Svc Ctr",
    "wof:placetype":"venue"
},
  "geometry": {"coordinates":[-82.562724,27.999018],"type":"Point"}
}