{
  "type": "Feature",
  "properties": {
    "iso:country":"US",
    "sg:address":"2403 NW 27th Ave",
    "sg:city":"Miami",
    "sg:classifiers":[
        {
            "category":"Bakery",
            "type":"Food & Drink"
        }
    ],
    "sg:phone":"+1 305 635 3559",
    "sg:postcode":"33142",
    "sg:province":"FL",
    "wof:name":"Albe'ar Bakery",
    "wof:placetype":"venue"
},
  "geometry": {"coordinates":[-80.239998,25.799],"type":"Point"}
}