{
  "type": "Feature",
  "properties": {
    "addr:full":"883 State Hwy 20 Interlachen FL 32148",
    "addr:housenumber":"883",
    "addr:postcode":"32148",
    "addr:street":"State Hwy 20 Interlachen",
    "iso:country":"US",
    "sg:address":"883 State Hwy 20",
    "sg:city":"Interlachen",
    "sg:classifiers":[
        {
            "category":"Retail",
            "subcategory":"Veterinary Services",
            "type":"Services"
        }
    ],
    "sg:phone":"+1 386 684 4077",
    "sg:postcode":"32148",
    "sg:province":"FL",
    "sg:tags":[
        "veterinarian"
    ],
    "wof:name":"Interlachen Veterinary Clinic",
    "wof:placetype":"venue"
},
  "geometry": {"coordinates":[-81.835155,29.628374],"type":"Point"}
}