{
  "type": "Feature",
  "properties": {
    "iso:country":"US",
    "sg:address":"821 SE 16th St",
    "sg:city":"Deerfield Beach",
    "sg:classifiers":[
        {
            "category":"Building & Trades",
            "subcategory":"Construction",
            "type":"Services"
        }
    ],
    "sg:phone":"+1 954 480 9006",
    "sg:postcode":"33441",
    "sg:province":"FL",
    "sg:tags":[
        "general",
        "contractor"
    ],
    "wof:name":"Seabee Builders",
    "wof:placetype":"venue"
},
  "geometry": {"coordinates":[-80.08966599999999,26.296543],"type":"Point"}
}