{
  "type": "Feature",
  "properties": {
    "addr:full":"1685 Medical Ln Ste 200 Fort Myers FL 33907",
    "addr:housenumber":"1685",
    "addr:postcode":"myers;33907",
    "addr:street":"Medical Ln Ste 200",
    "iso:country":"US",
    "sg:address":"1685 Medical Ln Ste 200",
    "sg:city":"Fort Myers",
    "sg:classifiers":[
        {
            "category":"Education",
            "subcategory":"School",
            "type":"Public Place"
        },
        {
            "category":"Education",
            "subcategory":"University",
            "type":"Public Place"
        }
    ],
    "sg:phone":"+1 239 939 4766",
    "sg:postcode":"33907",
    "sg:province":"FL",
    "sg:tags":[
        "high",
        "middle",
        "college",
        "elementary"
    ],
    "sg:website":"www.swfc.edu",
    "wof:name":"Southwest Florida College",
    "wof:placetype":"venue"
},
  "geometry": {"coordinates":[-81.877197,26.5958],"type":"Point"}
}