{
  "type": "Feature",
  "properties": {
    "addr:full":"1900 Summit Tower Blvd Ste 140 Orlando FL 32810",
    "addr:housenumber":"1900",
    "addr:postcode":"32810",
    "addr:street":"Summit Tower Blvd Ste 140",
    "iso:country":"US",
    "sg:address":"1900 Summit Tower Blvd Ste 140",
    "sg:city":"Orlando",
    "sg:classifiers":[
        {
            "category":"Professional",
            "subcategory":"Employment Agencies",
            "type":"Services"
        }
    ],
    "sg:phone":"+1 407 875 0220",
    "sg:postcode":"32810",
    "sg:province":"FL",
    "wof:name":"Staffing Solutions by Personnel One",
    "wof:placetype":"venue"
},
  "geometry": {"coordinates":[-81.402496,28.632799],"type":"Point"}
}