{
  "type": "Feature",
  "properties": {
    "iso:country":"US",
    "sg:address":"1401 E River Dr",
    "sg:city":"Pompano Beach",
    "sg:classifiers":[
        {
            "category":"Professional",
            "subcategory":"Management & Consulting",
            "type":"Services"
        }
    ],
    "sg:phone":"+1 954 978 6152",
    "sg:postcode":"33063",
    "sg:province":"FL",
    "sg:tags":[
        "home"
    ],
    "wof:name":"A To Z Maintenance Management",
    "wof:placetype":"venue"
},
  "geometry": {"coordinates":[-80.203549,26.246356],"type":"Point"}
}