{
  "type": "Feature",
  "properties": {
    "addr:full":"14335 Collier Blvd Naples FL 34119",
    "addr:housenumber":"14335",
    "addr:postcode":"34119",
    "addr:street":"Collier Blvd",
    "iso:country":"US",
    "sg:address":"14335 Collier Blvd",
    "sg:city":"Naples",
    "sg:classifiers":[
        {
            "category":"Building & Trades",
            "subcategory":"Landscaping Services",
            "type":"Services"
        }
    ],
    "sg:phone":"+1 239 455 0000",
    "sg:postcode":"34119",
    "sg:province":"FL",
    "sg:tags":[
        "landscape"
    ],
    "wof:name":"Tru Green-Chemlawn",
    "wof:placetype":"venue"
},
  "geometry": {"coordinates":[-81.688008,26.243864],"type":"Point"}
}