{
  "type": "Feature",
  "properties": {
    "addr:full":"11754 Bruin Dr New Port Richey FL 34654",
    "addr:housenumber":"11754",
    "addr:postcode":"34654",
    "addr:street":"Bruin Dr",
    "iso:country":"US",
    "sg:address":"11754 Bruin Dr",
    "sg:city":"New Port Richey",
    "sg:classifiers":[
        {
            "category":"Building & Trades",
            "subcategory":"Construction",
            "type":"Services"
        }
    ],
    "sg:phone":"+1 727 857 0719",
    "sg:postcode":"34654",
    "sg:province":"FL",
    "sg:tags":[
        "concrete",
        "contractor"
    ],
    "wof:name":"Christopher Oneil",
    "wof:placetype":"venue"
},
  "geometry": {"coordinates":[-82.633252,28.331133],"type":"Point"}
}