{
  "type": "Feature",
  "properties": {
    "addr:full":"1628 Michigan Ave Miami Beach FL 33139",
    "addr:housenumber":"1628",
    "addr:postcode":"33139",
    "addr:street":"Michigan Ave",
    "iso:country":"US",
    "sg:address":"1628 Michigan Ave",
    "sg:city":"Miami Beach",
    "sg:classifiers":[
        {
            "category":"Arts & Performance",
            "subcategory":"Art Gallery",
            "type":"Entertainment"
        }
    ],
    "sg:phone":"+1 305 674 7076",
    "sg:postcode":"33139",
    "sg:province":"FL",
    "sg:website":"www.gdscontemporaryart.com",
    "wof:name":"Galeria Del Sol",
    "wof:placetype":"venue"
},
  "geometry": {"coordinates":[-80.138603,25.7896],"type":"Point"}
}