{
  "type": "Feature",
  "properties": {
    "addr:full":"1361 S Ocean Blvd Pompano Beach FL 33062",
    "addr:housenumber":"1361",
    "addr:postcode":"33062",
    "addr:street":"S Ocean Blvd",
    "iso:country":"US",
    "sg:address":"1361 S Ocean Blvd",
    "sg:city":"Pompano Beach",
    "sg:classifiers":[
        {
            "category":"Social Services",
            "subcategory":"Child Care",
            "type":"Services"
        }
    ],
    "sg:phone":"+1 954 784 6035",
    "sg:postcode":"33062",
    "sg:province":"FL",
    "sg:tags":[
        "day"
    ],
    "wof:name":"C W T S Day Buy Day LLC",
    "wof:placetype":"venue"
},
  "geometry": {"coordinates":[-80.09143899999999,26.220115],"type":"Point"}
}