{
  "type": "Feature",
  "properties": {
    "iso:country":"US",
    "sg:address":"512 Nokomis Ave S",
    "sg:city":"Venice",
    "sg:classifiers":[
        {
            "category":"Health Services",
            "subcategory":"Doctor",
            "type":"Services"
        }
    ],
    "sg:phone":"+1 941 488 7781",
    "sg:postcode":"34285",
    "sg:province":"FL",
    "wof:name":"Radiology Associates Of Venice",
    "wof:placetype":"venue"
},
  "geometry": {"coordinates":[-82.44560199999999,27.090183],"type":"Point"}
}