{
  "type": "Feature",
  "properties": {
    "addr:full":"128 Stillwater Cir Jupiter FL 33458",
    "addr:housenumber":"128",
    "addr:postcode":"33458",
    "addr:street":"Stillwater Cir",
    "iso:country":"US",
    "sg:address":"128 Stillwater Cir",
    "sg:city":"Jupiter",
    "sg:classifiers":[
        {
            "category":"Building & Trades",
            "subcategory":"Construction",
            "type":"Services"
        }
    ],
    "sg:phone":"+1 561 744 0991",
    "sg:postcode":"33458",
    "sg:province":"FL",
    "sg:tags":[
        "contractor"
    ],
    "wof:name":"Horgan General Contracting",
    "wof:placetype":"venue"
},
  "geometry": {"coordinates":[-80.131129,26.917424],"type":"Point"}
}