{
  "type": "Feature",
  "properties": {
    "addr:full":"4083 US Hwy 1 Rockledge FL 32955",
    "addr:housenumber":"4083",
    "addr:postcode":"32955",
    "addr:street":"Us Hwy 1",
    "iso:country":"US",
    "sg:address":"4083 US Hwy 1",
    "sg:city":"Rockledge",
    "sg:classifiers":[
        {
            "category":"Home & Garden",
            "subcategory":"Furniture",
            "type":"Retail Goods"
        }
    ],
    "sg:phone":"+1 321 632 3434",
    "sg:postcode":"32955",
    "sg:province":"FL",
    "wof:name":"Victoria's Finishing Touches",
    "wof:placetype":"venue"
},
  "geometry": {"coordinates":[-80.697025,28.28697],"type":"Point"}
}