{
  "type": "Feature",
  "properties": {
    "iso:country":"US",
    "sg:address":"140 Palm St",
    "sg:city":"Live Oak",
    "sg:classifiers":[
        {
            "category":"Freight",
            "type":"Transportation"
        }
    ],
    "sg:phone":"+1 386 362 1185",
    "sg:postcode":"32064",
    "sg:province":"FL",
    "sg:tags":[
        "trucking"
    ],
    "wof:name":"Beaver Bulk Inc",
    "wof:placetype":"venue"
},
  "geometry": {"coordinates":[-82.97413899999999,30.305919],"type":"Point"}
}