{
  "type": "Feature",
  "properties": {
    "addr:full":"420 Plumosa Ave Casselberry FL 32707",
    "addr:housenumber":"420",
    "addr:postcode":"32707",
    "addr:street":"Plumosa Ave",
    "iso:country":"US",
    "sg:address":"420 Plumosa Ave",
    "sg:city":"Casselberry",
    "sg:classifiers":[
        {
            "category":"Government",
            "subcategory":"Office",
            "type":"Public Place"
        }
    ],
    "sg:phone":"+1 407 262 7475",
    "sg:postcode":"32707",
    "sg:province":"FL",
    "sg:tags":[
        "state",
        "resource"
    ],
    "wof:name":"Economic Security Food Stamps",
    "wof:placetype":"venue"
},
  "geometry": {"coordinates":[-81.33951500000001,28.675882],"type":"Point"}
}