{
  "type": "Feature",
  "properties": {
    "addr:full":"211 E Marion Ave Punta Gorda FL 33950",
    "addr:housenumber":"211",
    "addr:postcode":"33950",
    "addr:street":"E Marion Ave",
    "iso:country":"US",
    "sg:address":"211 E Marion Ave",
    "sg:city":"Punta Gorda",
    "sg:classifiers":[
        {
            "category":"Retail",
            "subcategory":"Laundry & Dry Cleaning",
            "type":"Services"
        },
        {
            "category":"Utilities",
            "subcategory":"Fuel Oil & Lpg",
            "type":"Services"
        }
    ],
    "sg:phone":"+1 941 639 2915",
    "sg:postcode":"33950",
    "sg:province":"FL",
    "sg:tags":[
        "propane",
        "coin",
        "gas"
    ],
    "wof:name":"Punta Gorda Coin Ldry & LP Gas",
    "wof:placetype":"venue"
},
  "geometry": {"coordinates":[-82.04781199999999,26.937294],"type":"Point"}
}