{
  "type": "Feature",
  "properties": {
    "iso:country":"US",
    "sg:address":"3700 South Orlando Drive",
    "sg:city":"Sanford",
    "sg:classifiers":[
        {
            "category":"Autos & Motor Vehicles",
            "subcategory":"Automobile Sales",
            "type":"Retail Goods"
        }
    ],
    "sg:phone":"+1 407 936 2222",
    "sg:postcode":"32773",
    "sg:province":"FL",
    "sg:tags":[
        "car"
    ],
    "sg:website":"www.nationstrucks.com/",
    "wof:name":"Nations Truck",
    "wof:placetype":"venue"
},
  "geometry": {"coordinates":[-81.286569,28.762086],"type":"Point"}
}