{
  "type": "Feature",
  "properties": {
    "iso:country":"US",
    "sg:address":"101 W Kaley St",
    "sg:city":"Orlando",
    "sg:classifiers":[
        {
            "category":"Health Services",
            "subcategory":"Doctor",
            "type":"Services"
        }
    ],
    "sg:phone":"+1 407 425 7647",
    "sg:postcode":"32806",
    "sg:province":"FL",
    "sg:tags":[
        "medical"
    ],
    "wof:name":"Adams Jerome L MD PA",
    "wof:placetype":"venue"
},
  "geometry": {"coordinates":[-81.38134100000001,28.520152],"type":"Point"}
}