{
  "type": "Feature",
  "properties": {
    "iso:country":"US",
    "sg:address":"1595 W 49th St",
    "sg:city":"Hialeah",
    "sg:classifiers":[
        {
            "category":"Coffee & Tea",
            "type":"Food & Drink"
        }
    ],
    "sg:phone":"+1 305 362 7151",
    "sg:postcode":"33012",
    "sg:province":"FL",
    "sg:website":"www.starbucks.com",
    "wof:name":"Starbucks",
    "wof:placetype":"venue"
},
  "geometry": {"coordinates":[-80.313709,25.867531],"type":"Point"}
}