{
  "type": "Feature",
  "properties": {
    "iso:country":"US",
    "sg:address":"14107 SW 142nd Ave",
    "sg:city":"Miami",
    "sg:classifiers":[
        {
            "category":"Building & Trades",
            "subcategory":"Construction",
            "type":"Services"
        }
    ],
    "sg:phone":"+1 305 253 6001",
    "sg:postcode":"33186",
    "sg:province":"FL",
    "sg:tags":[
        "roofing",
        "industrial",
        "contractors-commercial",
        "contractor"
    ],
    "wof:name":"Palmer R N Roofing",
    "wof:placetype":"venue"
},
  "geometry": {"coordinates":[-80.422877,25.636201],"type":"Point"}
}