{
  "type": "Feature",
  "properties": {
    "addr:full":"824 W New York Ave De Land FL 32720",
    "addr:housenumber":"824",
    "addr:postcode":"32720",
    "addr:street":"W New York Ave",
    "iso:country":"US",
    "sg:address":"824 W New York Ave",
    "sg:city":"De Land",
    "sg:classifiers":[
        {
            "category":"Professional",
            "subcategory":"Management & Consulting",
            "type":"Services"
        }
    ],
    "sg:phone":"+1 386 736 0388",
    "sg:postcode":"32720",
    "sg:province":"FL",
    "sg:tags":[
        "business"
    ],
    "wof:name":"Excellence In Services Network",
    "wof:placetype":"venue"
},
  "geometry": {"coordinates":[-81.31799599999999,29.02795],"type":"Point"}
}