{
  "type": "Feature",
  "properties": {
    "iso:country":"US",
    "sg:address":"8353 SW 124th St Ste 201",
    "sg:city":"Miami",
    "sg:phone":"+1 305 238 9898",
    "sg:postcode":"33156",
    "sg:province":"FL",
    "wof:name":"Alan Seifer Md",
    "wof:placetype":"venue"
},
  "geometry": {"coordinates":[-80.32988,25.65513],"type":"Point"}
}