{
  "type": "Feature",
  "properties": {
    "iso:country":"US",
    "sg:address":"5011 NW 104th Ave",
    "sg:city":"Pompano Beach",
    "sg:classifiers":[
        {
            "category":"Building & Trades",
            "subcategory":"Construction",
            "type":"Services"
        }
    ],
    "sg:phone":"+1 954 341 4034",
    "sg:postcode":"33076",
    "sg:province":"FL",
    "sg:tags":[
        "house",
        "residential"
    ],
    "wof:name":"Newman Quality Construction",
    "wof:placetype":"venue"
},
  "geometry": {"coordinates":[-80.265935,26.293741],"type":"Point"}
}