{
  "type": "Feature",
  "properties": {
    "addr:full":"2400 Pga Blvd Palm Beach Gdns FL 33410",
    "addr:housenumber":"2400",
    "addr:postcode":"33410",
    "addr:street":"Pga Blvd Palm Beach Gdns",
    "iso:country":"US",
    "sg:address":"2400 Pga Blvd",
    "sg:city":"Palm Beach Gdns",
    "sg:classifiers":[
        {
            "category":"Banks & Credit Unions",
            "subcategory":"Bank",
            "type":"Services"
        }
    ],
    "sg:phone":"+1 561 622 6602",
    "sg:postcode":"33410",
    "sg:province":"FL",
    "sg:tags":[
        "loan",
        "real estate"
    ],
    "wof:name":"Premier Mortgage Funding Corp",
    "wof:placetype":"venue"
},
  "geometry": {"coordinates":[-80.070657,26.844557],"type":"Point"}
}