{
  "type": "Feature",
  "properties": {
    "addr:full":"1111 Juniper Lake Rd Defuniak Springs FL 32433",
    "addr:housenumber":"1111",
    "addr:postcode":"32433",
    "addr:street":"Juniper Lake Rd",
    "iso:country":"US",
    "sg:address":"1111 Juniper Lake Rd",
    "sg:city":"Defuniak Springs",
    "sg:classifiers":[
        {
            "category":"Professional",
            "type":"Services"
        }
    ],
    "sg:phone":"+1 850 951 1901",
    "sg:postcode":"32433",
    "sg:province":"FL",
    "sg:tags":[
        "establishment"
    ],
    "wof:name":"Conos Cleaning",
    "wof:placetype":"venue"
},
  "geometry": {"coordinates":[-86.132972,30.754783],"type":"Point"}
}