{
  "type": "Feature",
  "properties": {
    "iso:country":"US",
    "sg:address":"8206 Rose Petal Ct",
    "sg:city":"Port Richey",
    "sg:classifiers":[
        {
            "category":"Building & Trades",
            "subcategory":"Cleaning & Sanitation",
            "type":"Services"
        }
    ],
    "sg:phone":"+1 727 432 7715",
    "sg:postcode":"34668",
    "sg:province":"FL",
    "sg:tags":[
        "property",
        "maintenance"
    ],
    "wof:name":"Professional Property Mntnc",
    "wof:placetype":"venue"
},
  "geometry": {"coordinates":[-82.69367,28.276022],"type":"Point"}
}