{
  "type": "Feature",
  "properties": {
    "iso:country":"US",
    "sg:address":"4027 Vana Dr",
    "sg:city":"Sarasota",
    "sg:classifiers":[
        {
            "category":"Building & Trades",
            "subcategory":"Construction",
            "type":"Services"
        }
    ],
    "sg:phone":"+1 941 378 9789",
    "sg:postcode":"34241",
    "sg:province":"FL",
    "sg:tags":[
        "carpenter"
    ],
    "wof:name":"Terry B Engert Carpenter",
    "wof:placetype":"venue"
},
  "geometry": {"coordinates":[-82.426858,27.295575],"type":"Point"}
}