{
  "type": "Feature",
  "properties": {
    "iso:country":"US",
    "sg:address":"222 Hazard St",
    "sg:city":"Orlando",
    "sg:classifiers":[
        {
            "category":"Communications",
            "subcategory":"Radio Station",
            "type":"Services"
        }
    ],
    "sg:phone":"+1 407 423 1370",
    "sg:postcode":"32804",
    "sg:province":"FL",
    "sg:tags":[
        "company",
        "broadcasting"
    ],
    "wof:name":"U S Traffic & News",
    "wof:placetype":"venue"
},
  "geometry": {"coordinates":[-81.38163,28.586791],"type":"Point"}
}