{
  "type": "Feature",
  "properties": {
    "addr:full":"2800 NE 56th St Ocala FL 34479",
    "addr:housenumber":"2800",
    "addr:postcode":"34479",
    "addr:street":"Ne 56Th St",
    "iso:country":"US",
    "sg:address":"2800 NE 56th St",
    "sg:city":"Ocala",
    "sg:classifiers":[
        {
            "category":"Personal",
            "subcategory":"Beauty Salon",
            "type":"Services"
        }
    ],
    "sg:phone":"+1 352 622 3376",
    "sg:postcode":"34479",
    "sg:province":"FL",
    "wof:name":"Nancy Wolfe",
    "wof:placetype":"venue"
},
  "geometry": {"coordinates":[-82.099146,29.24478],"type":"Point"}
}