{
  "type": "Feature",
  "properties": {
    "iso:country":"US",
    "sg:address":"1309 W Sunrise Blvd",
    "sg:city":"Fort Lauderdale",
    "sg:classifiers":[
        {
            "category":"Autos & Motor Vehicles",
            "subcategory":"Automobile Sales",
            "type":"Retail Goods"
        }
    ],
    "sg:phone":"+1 954 768 0005",
    "sg:postcode":"33311",
    "sg:province":"FL",
    "sg:tags":[
        "car",
        "dealer"
    ],
    "wof:name":"Auto Consignment Store Inc",
    "wof:placetype":"venue"
},
  "geometry": {"coordinates":[-80.159295,26.13657],"type":"Point"}
}