{
  "type": "Feature",
  "properties": {
    "iso:country":"US",
    "sg:address":"3346 Curry Ford Rd",
    "sg:city":"Orlando",
    "sg:classifiers":[
        {
            "category":"Professional",
            "subcategory":"Accounting & Tax Preparation",
            "type":"Services"
        }
    ],
    "sg:phone":"+1 407 228 1317",
    "sg:postcode":"32806",
    "sg:province":"FL",
    "sg:tags":[
        "accountant"
    ],
    "wof:name":"Profit Keepers",
    "wof:placetype":"venue"
},
  "geometry": {"coordinates":[-81.341639,28.524105],"type":"Point"}
}