{
  "type": "Feature",
  "properties": {
    "addr:full":"74 Shoreland Dr Key Largo FL 33037",
    "addr:housenumber":"74",
    "addr:postcode":"33037",
    "addr:street":"Shoreland Dr",
    "iso:country":"US",
    "sg:address":"74 Shoreland Dr",
    "sg:city":"Key Largo",
    "sg:classifiers":[
        {
            "category":"Professional",
            "subcategory":"Advertising",
            "type":"Services"
        }
    ],
    "sg:phone":"+1 305 451 1110",
    "sg:postcode":"33037",
    "sg:province":"FL",
    "sg:tags":[
        "agency"
    ],
    "wof:name":"Fuentes & Burch Inc",
    "wof:placetype":"venue"
},
  "geometry": {"coordinates":[-80.396974,25.136288],"type":"Point"}
}