{
  "type": "Feature",
  "properties": {
    "iso:country":"US",
    "sg:address":"28051 US Hwy 19",
    "sg:city":"Clearwater",
    "sg:classifiers":[
        {
            "category":"Banks & Credit Unions",
            "subcategory":"Bank",
            "type":"Services"
        }
    ],
    "sg:phone":"+1 727 726 5551",
    "sg:postcode":"33761",
    "sg:province":"FL",
    "sg:tags":[
        "loan",
        "real estate"
    ],
    "wof:name":"First Trust Of Florida",
    "wof:placetype":"venue"
},
  "geometry": {"coordinates":[-82.738078,28.027442],"type":"Point"}
}