{
  "type": "Feature",
  "properties": {
    "iso:country":"US",
    "sg:address":"15405 State Hwy 87",
    "sg:city":"Jay",
    "sg:classifiers":[
        {
            "category":"Food & Beverages",
            "subcategory":"Groceries & Convenience Stores",
            "type":"Retail Goods"
        }
    ],
    "sg:phone":"+1 850 675 4100",
    "sg:postcode":"32565",
    "sg:province":"FL",
    "wof:name":"Tee & M State Line",
    "wof:placetype":"venue"
},
  "geometry": {"coordinates":[-87.039238,30.990325],"type":"Point"}
}