{
  "type": "Feature",
  "properties": {
    "addr:full":"4424 NW 13th St Gainesville FL 32609",
    "addr:housenumber":"4424",
    "addr:postcode":"32609",
    "addr:street":"Nw 13Th St",
    "iso:country":"US",
    "sg:address":"4424 NW 13th St",
    "sg:city":"Gainesville",
    "sg:classifiers":[
        {
            "category":"Insurance",
            "subcategory":"Insurance Agent",
            "type":"Services"
        }
    ],
    "sg:phone":"+1 352 373 3024",
    "sg:postcode":"32609",
    "sg:province":"FL",
    "wof:name":"Allstate",
    "wof:placetype":"venue"
},
  "geometry": {"coordinates":[-82.33909,29.695503],"type":"Point"}
}