{
  "type": "Feature",
  "properties": {
    "iso:country":"US",
    "sg:address":"4910 SW 150th Ter",
    "sg:city":"Hollywood",
    "sg:classifiers":[
        {
            "category":"Professional",
            "type":"Services"
        }
    ],
    "sg:phone":"+1 954 441 0060",
    "sg:postcode":"33027",
    "sg:province":"FL",
    "wof:name":"Distribumed Corp",
    "wof:placetype":"venue"
},
  "geometry": {"coordinates":[-80.346772,25.961846],"type":"Point"}
}