{
  "type": "Feature",
  "properties": {
    "iso:country":"US",
    "sg:address":"983 Creel St",
    "sg:city":"Melbourne",
    "sg:classifiers":[
        {
            "category":"Manufacturing",
            "subcategory":"Motor Vehicles & Parts",
            "type":"Manufacturing & Wholesale Goods"
        },
        {
            "category":"Wholesale",
            "subcategory":"Auto Parts",
            "type":"Manufacturing & Wholesale Goods"
        },
        {
            "category":"Retail",
            "subcategory":"Auto Repair",
            "type":"Services"
        }
    ],
    "sg:phone":"+1 321 242 7420",
    "sg:postcode":"32935",
    "sg:province":"FL",
    "sg:tags":[
        "body",
        "shop",
        "supply",
        "automobile",
        "supply-wholesale",
        "equipment",
        "service-equipment",
        "painting",
        "repairing",
        "manufacturer"
    ],
    "wof:name":"Roger & Sons Auto Refinishing & Body Repair Inc",
    "wof:placetype":"venue"
},
  "geometry": {"coordinates":[-80.634833,28.130562],"type":"Point"}
}