{
  "type": "Feature",
  "properties": {
    "addr:full":"356 N University Dr Hollywood FL 33024",
    "addr:housenumber":"356",
    "addr:postcode":"33024",
    "addr:street":"N University Dr",
    "iso:country":"US",
    "sg:address":"356 N University Dr",
    "sg:city":"Hollywood",
    "sg:classifiers":[
        {
            "category":"Shopping",
            "type":"Retail Goods"
        }
    ],
    "sg:phone":"+1 954 442 3106",
    "sg:postcode":"33024",
    "sg:province":"FL",
    "sg:tags":[
        "merchandise"
    ],
    "wof:name":"Royam LLC",
    "wof:placetype":"venue"
},
  "geometry": {"coordinates":[-80.24800999999999,26.009224],"type":"Point"}
}