{
  "type": "Feature",
  "properties": {
    "addr:full":"8151 Blaikie Ct Sarasota FL 34240",
    "addr:housenumber":"8151",
    "addr:postcode":"34240",
    "addr:street":"Blaikie Ct",
    "iso:country":"US",
    "sg:address":"8151 Blaikie Ct",
    "sg:city":"Sarasota",
    "sg:classifiers":[
        {
            "category":"Wholesale",
            "subcategory":"Construction Materials",
            "type":"Manufacturing & Wholesale Goods"
        }
    ],
    "sg:phone":"+1 941 342 1344",
    "sg:postcode":"34240",
    "sg:province":"FL",
    "sg:tags":[
        "building",
        "exterior"
    ],
    "wof:name":"Erb Supply LLC",
    "wof:placetype":"venue"
},
  "geometry": {"coordinates":[-82.404106,27.346944],"type":"Point"}
}