{
  "type": "Feature",
  "properties": {
    "addr:full":"1501 S Main St Belle Glade FL 33430",
    "addr:housenumber":"1501",
    "addr:postcode":"33430",
    "addr:street":"S Main St",
    "iso:country":"US",
    "sg:address":"1501 S Main St",
    "sg:city":"Belle Glade",
    "sg:classifiers":[
        {
            "category":"Shopping",
            "type":"Retail Goods"
        }
    ],
    "sg:phone":"+1 561 996 7710",
    "sg:postcode":"33430",
    "sg:province":"FL",
    "sg:tags":[
        "ice"
    ],
    "wof:name":"Glades Truck Ice Inc",
    "wof:placetype":"venue"
},
  "geometry": {"coordinates":[-80.67052700000001,26.669738],"type":"Point"}
}