{
  "type": "Feature",
  "properties": {
    "addr:full":"23330 Harbor View Rd Port Charlotte FL 33980",
    "addr:housenumber":"23330",
    "addr:postcode":"33980",
    "addr:street":"Harbor View Rd",
    "iso:country":"US",
    "sg:address":"23330 Harbor View Rd",
    "sg:city":"Port Charlotte",
    "sg:classifiers":[
        {
            "category":"Wholesale",
            "subcategory":"Electrical",
            "type":"Manufacturing & Wholesale Goods"
        }
    ],
    "sg:phone":"+1 941 629 0240",
    "sg:postcode":"33980",
    "sg:province":"FL",
    "sg:tags":[
        "equipment",
        "merchandise",
        "armature"
    ],
    "wof:name":"Johns Electric Motors",
    "wof:placetype":"venue"
},
  "geometry": {"coordinates":[-82.064712,26.96542],"type":"Point"}
}