{
  "type": "Feature",
  "properties": {
    "iso:country":"US",
    "sg:address":"1310 W Colonial Dr",
    "sg:city":"Orlando",
    "sg:classifiers":[
        {
            "category":"Building & Trades",
            "subcategory":"Plumbing",
            "type":"Services"
        },
        {
            "category":"Home & Garden",
            "subcategory":"Hardware",
            "type":"Retail Goods"
        }
    ],
    "sg:phone":"+1 407 872 0005",
    "sg:postcode":"32804",
    "sg:province":"FL",
    "sg:tags":[
        "filtration",
        "supply",
        "work",
        "purification",
        "water",
        "equipment"
    ],
    "wof:name":"Reps Residential Environmental Protective Systems",
    "wof:placetype":"venue"
},
  "geometry": {"coordinates":[-81.397599,28.55294],"type":"Point"}
}