{
  "type": "Feature",
  "properties": {
    "iso:country":"US",
    "sg:address":"1505 W 25th St",
    "sg:city":"Sanford",
    "sg:classifiers":[
        {
            "category":"Real Estate",
            "subcategory":"Real Estate Operator",
            "type":"Services"
        }
    ],
    "sg:phone":"+1 407 322 7304",
    "sg:postcode":"32771",
    "sg:province":"FL",
    "sg:tags":[
        "apartment"
    ],
    "wof:name":"Tropicana Apartments",
    "wof:placetype":"venue"
},
  "geometry": {"coordinates":[-81.282462,28.786634],"type":"Point"}
}