{
  "type": "Feature",
  "properties": {
    "addr:full":"2130 State Hwy 16 St Augustine FL 32084",
    "addr:housenumber":"2130",
    "addr:postcode":"32084",
    "addr:street":"State Hwy 16 St",
    "iso:country":"US",
    "sg:address":"2130 State Hwy 16",
    "sg:city":"St Augustine",
    "sg:classifiers":[
        {
            "category":"Retail",
            "subcategory":"Auto Repair",
            "type":"Services"
        }
    ],
    "sg:phone":"+1 904 824 8641",
    "sg:postcode":"32084",
    "sg:province":"FL",
    "sg:tags":[
        "automotive",
        "wrecker"
    ],
    "wof:name":"Eagle Towing & Recovery",
    "wof:placetype":"venue"
},
  "geometry": {"coordinates":[-81.39881,29.914736],"type":"Point"}
}