{
  "type": "Feature",
  "properties": {
    "iso:country":"US",
    "sg:address":"3221 W Empedrado St",
    "sg:city":"Tampa",
    "sg:classifiers":[
        {
            "category":"Real Estate",
            "subcategory":"Architect",
            "type":"Services"
        }
    ],
    "sg:phone":"+1 813 839 4750",
    "sg:postcode":"33629",
    "sg:province":"FL",
    "sg:tags":[
        "architectural"
    ],
    "wof:name":"Pando & Associates Inc",
    "wof:placetype":"venue"
},
  "geometry": {"coordinates":[-82.496731,27.920501],"type":"Point"}
}