{
  "type": "Feature",
  "properties": {
    "iso:country":"US",
    "sg:address":"7032 Cocos Dr",
    "sg:city":"Orlando",
    "sg:classifiers":[
        {
            "category":"Arts & Performance",
            "subcategory":"Theater",
            "type":"Entertainment"
        }
    ],
    "sg:phone":"+1 407 282 5222",
    "sg:postcode":"32807",
    "sg:province":"FL",
    "sg:tags":[
        "bureau",
        "agency",
        "group"
    ],
    "wof:name":"Earth Beat",
    "wof:placetype":"venue"
},
  "geometry": {"coordinates":[-81.289267,28.54236],"type":"Point"}
}