{
  "type": "Feature",
  "properties": {
    "addr:full":"8312 Monarch Cir Seminole FL 33772",
    "addr:housenumber":"8312",
    "addr:postcode":"33772",
    "addr:street":"Monarch Cir",
    "iso:country":"US",
    "sg:address":"8312 Monarch Cir",
    "sg:city":"Seminole",
    "sg:classifiers":[
        {
            "category":"Manufacturing",
            "subcategory":"Printing",
            "type":"Manufacturing & Wholesale Goods"
        }
    ],
    "sg:phone":"+1 727 399 1483",
    "sg:postcode":"33772",
    "sg:province":"FL",
    "sg:tags":[
        "periodical"
    ],
    "wof:name":"Discover Pinellas Magazine",
    "wof:placetype":"venue"
},
  "geometry": {"coordinates":[-82.80959799999999,27.850305],"type":"Point"}
}