{
  "type": "Feature",
  "properties": {
    "addr:full":"12239 SW 53rd St Fort Lauderdale FL 33330",
    "addr:housenumber":"12239",
    "addr:postcode":"33330",
    "addr:street":"Sw 53Rd St",
    "iso:country":"US",
    "sg:address":"12239 SW 53rd St",
    "sg:city":"Fort Lauderdale",
    "sg:classifiers":[
        {
            "category":"Recreation",
            "type":"Entertainment"
        }
    ],
    "sg:phone":"+1 954 434 7962",
    "sg:postcode":"33330",
    "sg:province":"FL",
    "sg:tags":[
        "legal"
    ],
    "wof:name":"Park Avenue Gymnastics",
    "wof:placetype":"venue"
},
  "geometry": {"coordinates":[-80.31129199999999,26.05146],"type":"Point"}
}