{
  "type": "Feature",
  "properties": {
    "addr:full":"18817 Sakera Rd Hudson FL 34667",
    "addr:postcode":"18817;34667",
    "addr:street":"Sakera Rd",
    "iso:country":"US",
    "sg:address":"18817 Sakera Rd",
    "sg:city":"Hudson",
    "sg:classifiers":[
        {
            "category":"Retail",
            "subcategory":"Auto Repair",
            "type":"Services"
        }
    ],
    "sg:phone":"+1 727 861 7009",
    "sg:postcode":"34667",
    "sg:province":"FL",
    "sg:tags":[
        "body",
        "automobile",
        "painting"
    ],
    "wof:name":"County Line Collision",
    "wof:placetype":"venue"
},
  "geometry": {"coordinates":[-82.611608,28.430904],"type":"Point"}
}