{
  "type": "Feature",
  "properties": {
    "addr:full":"1312 E Las Olas Blvd Fort Lauderdale FL 33301",
    "addr:housenumber":"1312",
    "addr:postcode":"33301",
    "addr:street":"E Las Olas Blvd",
    "iso:country":"US",
    "sg:address":"1312 E Las Olas Blvd",
    "sg:city":"Fort Lauderdale",
    "sg:classifiers":[
        {
            "category":"Travel",
            "subcategory":"Travel Agent",
            "type":"Entertainment"
        }
    ],
    "sg:phone":"+1 954 524 5211",
    "sg:postcode":"33301",
    "sg:province":"FL",
    "sg:tags":[
        "agency"
    ],
    "wof:name":"On The Go Travel Inc",
    "wof:placetype":"venue"
},
  "geometry": {"coordinates":[-80.12891,26.11932],"type":"Point"}
}