{
  "type": "Feature",
  "properties": {
    "iso:country":"US",
    "sg:address":"15357 Amberly Dr",
    "sg:city":"Tampa",
    "sg:classifiers":[
        {
            "category":"Personal",
            "type":"Services"
        }
    ],
    "sg:phone":"+1 813 975 1700",
    "sg:postcode":"33647",
    "sg:province":"FL",
    "sg:tags":[
        "party",
        "planning",
        "event"
    ],
    "sg:website":"http://www.youdothedishes.com",
    "wof:name":"You Do The Dishes",
    "wof:placetype":"venue"
},
  "geometry": {"coordinates":[-82.40187,28.086229],"type":"Point"}
}