{
  "type": "Feature",
  "properties": {
    "iso:country":"US",
    "sg:address":"15411 N Main St",
    "sg:city":"Jacksonville",
    "sg:classifiers":[
        {
            "category":"Food & Beverages",
            "subcategory":"Groceries & Convenience Stores",
            "type":"Retail Goods"
        }
    ],
    "sg:phone":"+1 904 757 4455",
    "sg:postcode":"32218",
    "sg:province":"FL",
    "wof:name":"Lil' Champ Food Store",
    "wof:placetype":"venue"
},
  "geometry": {"coordinates":[-81.622478,30.520126],"type":"Point"}
}