{
  "type": "Feature",
  "properties": {
    "iso:country":"US",
    "sg:address":"322 E Pine St",
    "sg:city":"Orlando",
    "sg:classifiers":[
        {
            "category":"Professional",
            "subcategory":"Advertising",
            "type":"Services"
        },
        {
            "category":"Professional",
            "subcategory":"Art Services",
            "type":"Services"
        },
        {
            "category":"Professional",
            "subcategory":"Computer Services",
            "type":"Services"
        }
    ],
    "sg:phone":"+1 407 246 1970",
    "sg:postcode":"32801",
    "sg:province":"FL",
    "sg:tags":[
        "web",
        "graphic",
        "artist",
        "commercial",
        "direct",
        "site",
        "designer",
        "design",
        "print",
        "mail"
    ],
    "sg:website":"http://www.coastlinestudios.com",
    "wof:name":"Coastline Studios",
    "wof:placetype":"venue"
},
  "geometry": {"coordinates":[-81.37358500000001,28.541322],"type":"Point"}
}