{
  "type": "Feature",
  "properties": {
    "iso:country":"US",
    "sg:address":"10910 Peachtree Dr",
    "sg:city":"Miami",
    "sg:classifiers":[
        {
            "category":"Education",
            "subcategory":"Special Training",
            "type":"Public Place"
        }
    ],
    "sg:phone":"+1 305 891 4141",
    "sg:postcode":"33161",
    "sg:province":"FL",
    "sg:tags":[
        "school",
        "language"
    ],
    "wof:name":"Spanish Solutions",
    "wof:placetype":"venue"
},
  "geometry": {"coordinates":[-80.176649,25.87651],"type":"Point"}
}