{
  "type": "Feature",
  "properties": {
    "addr:full":"3174 Gulfview Dr Spring Hill FL 34607",
    "addr:postcode":"3174;34607",
    "addr:street":"Gulfview Dr",
    "iso:country":"US",
    "sg:address":"3174 Gulfview Dr",
    "sg:city":"Spring Hill",
    "sg:classifiers":[
        {
            "category":"Professional",
            "subcategory":"Engineering",
            "type":"Services"
        }
    ],
    "sg:phone":"+1 352 796 9646",
    "sg:postcode":"34607",
    "sg:province":"FL",
    "wof:name":"Consulting Service Inc",
    "wof:placetype":"venue"
},
  "geometry": {"coordinates":[-82.66457,28.492389],"type":"Point"}
}