{
  "type": "Feature",
  "properties": {
    "addr:full":"1500 Menorca Ct Wellington FL 33414",
    "addr:housenumber":"1500",
    "addr:postcode":"33414",
    "addr:street":"Menorca Ct",
    "iso:country":"US",
    "sg:address":"1500 Menorca Ct",
    "sg:city":"Wellington",
    "sg:classifiers":[
        {
            "category":"Shopping",
            "subcategory":"Discount & Variety Stores",
            "type":"Retail Goods"
        }
    ],
    "sg:phone":"+1 561 333 5734",
    "sg:postcode":"33414",
    "sg:province":"FL",
    "sg:tags":[
        "merchandise",
        "general"
    ],
    "wof:name":"Lotus Sales",
    "wof:placetype":"venue"
},
  "geometry": {"coordinates":[-80.293476,26.6597],"type":"Point"}
}