{
  "type": "Feature",
  "properties": {
    "addr:full":"12009 S Williams St Dunnellon FL 34432",
    "addr:housenumber":"12009",
    "addr:postcode":"34432",
    "addr:street":"S Williams St",
    "iso:country":"US",
    "sg:address":"12009 S Williams St",
    "sg:city":"Dunnellon",
    "sg:classifiers":[
        {
            "category":"Building & Trades",
            "subcategory":"Plumbing",
            "type":"Services"
        }
    ],
    "sg:phone":"+1 352 489 2968",
    "sg:postcode":"34432",
    "sg:province":"FL",
    "sg:tags":[
        "plumbing",
        "contractor"
    ],
    "wof:name":"Brett's 24 Hour Pump Svc",
    "wof:placetype":"venue"
},
  "geometry": {"coordinates":[-82.462301,29.04839],"type":"Point"}
}