{
  "type": "Feature",
  "properties": {
    "iso:country":"US",
    "sg:address":"5335 Ramona Blvd",
    "sg:city":"Jacksonville",
    "sg:classifiers":[
        {
            "category":"Education",
            "subcategory":"School",
            "type":"Public Place"
        }
    ],
    "sg:phone":"+1 904 781 4411",
    "sg:postcode":"32205",
    "sg:province":"FL",
    "wof:name":"Destiny Educational Academy",
    "wof:placetype":"venue"
},
  "geometry": {"coordinates":[-81.736121,30.314205],"type":"Point"}
}