{
  "type": "Feature",
  "properties": {
    "iso:country":"US",
    "sg:address":"2530 Michigan Ave",
    "sg:city":"Kissimmee",
    "sg:classifiers":[
        {
            "category":"Building & Trades",
            "subcategory":"Pest Control",
            "type":"Services"
        }
    ],
    "sg:phone":"+1 407 846 6620",
    "sg:postcode":"34744",
    "sg:province":"FL",
    "wof:name":"Massey Services Pest & Termite",
    "wof:placetype":"venue"
},
  "geometry": {"coordinates":[-81.39131999999999,28.319476],"type":"Point"}
}