{
  "type": "Feature",
  "properties": {
    "addr:full":"8431 Casa del Rio Ln Fort Myers FL 33919",
    "addr:housenumber":"8431",
    "addr:postcode":"33919",
    "addr:street":"Casa Del Rio Ln",
    "iso:country":"US",
    "sg:address":"8431 Casa del Rio Ln",
    "sg:city":"Fort Myers",
    "sg:classifiers":[
        {
            "category":"Organizations",
            "subcategory":"Professional Association",
            "type":"Services"
        }
    ],
    "sg:phone":"+1 239 939 1952",
    "sg:postcode":"33919",
    "sg:province":"FL",
    "wof:name":"Southwest Florida Ultilities",
    "wof:placetype":"venue"
},
  "geometry": {"coordinates":[-81.89552999999999,26.592649],"type":"Point"}
}