{
  "type": "Feature",
  "properties": {
    "iso:country":"US",
    "sg:address":"25200 Pelican Creek Cir",
    "sg:city":"Bonita Springs",
    "sg:classifiers":[
        {
            "category":"Professional",
            "subcategory":"Employment Agencies",
            "type":"Services"
        }
    ],
    "sg:phone":"+1 239 498 6066",
    "sg:postcode":"34134",
    "sg:province":"FL",
    "wof:name":"OHarrow & Associates Inc",
    "wof:placetype":"venue"
},
  "geometry": {"coordinates":[-81.81241799999999,26.3721],"type":"Point"}
}