{
  "type": "Feature",
  "properties": {
    "iso:country":"US",
    "sg:address":"6959 Coral Way",
    "sg:city":"Miami",
    "sg:classifiers":[
        {
            "category":"Home & Garden",
            "subcategory":"Hardware",
            "type":"Retail Goods"
        }
    ],
    "sg:phone":"+1 305 261 7521",
    "sg:postcode":"33155",
    "sg:province":"FL",
    "sg:tags":[
        "store"
    ],
    "wof:name":"Camarioca Hardware",
    "wof:placetype":"venue"
},
  "geometry": {"coordinates":[-80.307411,25.748121],"type":"Point"}
}