{
  "type": "Feature",
  "properties": {
    "iso:country":"US",
    "sg:address":"2135 Hyde Park Cir",
    "sg:city":"Sarasota",
    "sg:classifiers":[
        {
            "category":"Building & Trades",
            "subcategory":"Construction",
            "type":"Services"
        }
    ],
    "sg:phone":"+1 941 809 3076",
    "sg:postcode":"34239",
    "sg:province":"FL",
    "sg:tags":[
        "handyman"
    ],
    "wof:name":"Timothy Haley Handyman",
    "wof:placetype":"venue"
},
  "geometry": {"coordinates":[-82.52103700000001,27.315018],"type":"Point"}
}