{
  "type": "Feature",
  "properties": {
    "addr:full":"2960 Sandridge Church Rd Sneads FL 32460",
    "addr:postcode":"2960;32460",
    "addr:street":"Church Rd",
    "iso:country":"US",
    "sg:address":"2960 Sandridge Church Rd",
    "sg:city":"Sneads",
    "sg:classifiers":[
        {
            "category":"Food & Beverages",
            "subcategory":"Groceries & Convenience Stores",
            "type":"Retail Goods"
        }
    ],
    "sg:phone":"+1 850 593 6982",
    "sg:postcode":"32460",
    "sg:province":"FL",
    "wof:name":"Baxter's Grocery",
    "wof:placetype":"venue"
},
  "geometry": {"coordinates":[-84.993279,30.77736],"type":"Point"}
}