{
  "type": "Feature",
  "properties": {
    "addr:full":"13114 S Dixie Hwy Miami FL 33156",
    "addr:housenumber":"13114",
    "addr:postcode":"33156",
    "addr:street":"S Dixie Hwy",
    "iso:country":"US",
    "sg:address":"13114 S Dixie Hwy",
    "sg:city":"Miami",
    "sg:classifiers":[
        {
            "category":"Home & Garden",
            "subcategory":"Furniture",
            "type":"Retail Goods"
        }
    ],
    "sg:phone":"+1 786 242 5656",
    "sg:postcode":"33156",
    "sg:province":"FL",
    "sg:tags":[
        "store"
    ],
    "wof:name":"South Seas Trading Company",
    "wof:placetype":"venue"
},
  "geometry": {"coordinates":[-80.332105,25.648505],"type":"Point"}
}