{
  "type": "Feature",
  "properties": {
    "iso:country":"US",
    "sg:address":"5712 W Waters Ave",
    "sg:city":"Tampa",
    "sg:classifiers":[
        {
            "category":"Food & Beverages",
            "subcategory":"Specialty",
            "type":"Retail Goods"
        }
    ],
    "sg:phone":"+1 813 849 6471",
    "sg:postcode":"33634",
    "sg:province":"FL",
    "sg:tags":[
        "oriental"
    ],
    "wof:name":"Filipino Market",
    "wof:placetype":"venue"
},
  "geometry": {"coordinates":[-82.543873,28.025456],"type":"Point"}
}