{
  "type": "Feature",
  "properties": {
    "addr:full":"1350 South Dixie Highway Coral Gables FL 33146",
    "addr:housenumber":"1350",
    "addr:postcode":"33146",
    "addr:street":"South Dixie Highway",
    "iso:country":"US",
    "sg:address":"1350 South Dixie Highway",
    "sg:city":"Coral Gables",
    "sg:classifiers":[
        {
            "category":"Travel",
            "subcategory":"Hotels & Motels",
            "type":"Entertainment"
        },
        {
            "category":"Retail",
            "subcategory":"Event Space",
            "type":"Services"
        }
    ],
    "sg:phone":"+1 305 667 5611",
    "sg:postcode":"33146",
    "sg:province":"FL",
    "sg:tags":[
        "venue"
    ],
    "sg:website":"www.holidayinn.com",
    "wof:name":"Holiday Inn Hotel Coral Gables-Univ Of Miami",
    "wof:placetype":"venue"
},
  "geometry": {"coordinates":[-80.278147,25.712693],"type":"Point"}
}