{
  "type": "Feature",
  "properties": {
    "addr:full":"1826 Lakeshore Ln Tallahassee FL 32312",
    "addr:housenumber":"1826",
    "addr:postcode":"32312",
    "addr:street":"Lakeshore Ln",
    "iso:country":"US",
    "sg:address":"1826 Lakeshore Ln",
    "sg:city":"Tallahassee",
    "sg:classifiers":[
        {
            "category":"Building & Trades",
            "subcategory":"Construction",
            "type":"Services"
        }
    ],
    "sg:phone":"+1 850 553 9222",
    "sg:postcode":"32312",
    "sg:province":"FL",
    "sg:tags":[
        "hanging",
        "contractor"
    ],
    "wof:name":"Bill Jacobus Wallcovering Inc",
    "wof:placetype":"venue"
},
  "geometry": {"coordinates":[-84.298832,30.506368],"type":"Point"}
}