{
  "type": "Feature",
  "properties": {
    "iso:country":"US",
    "sg:address":"101 S University Ave",
    "sg:city":"Archer",
    "sg:classifiers":[
        {
            "category":"Retail",
            "subcategory":"Auto Repair",
            "type":"Services"
        }
    ],
    "sg:phone":"+1 352 495 2485",
    "sg:postcode":"32618",
    "sg:province":"FL",
    "sg:tags":[
        "repairing",
        "automobile"
    ],
    "wof:name":"Archer Automotive & Tire",
    "wof:placetype":"venue"
},
  "geometry": {"coordinates":[-82.519122,29.531865],"type":"Point"}
}