{
  "type": "Feature",
  "properties": {
    "iso:country":"US",
    "sg:address":"10517 Heatherwood Dr",
    "sg:city":"Pensacola",
    "sg:classifiers":[
        {
            "category":"Building & Trades",
            "subcategory":"Construction",
            "type":"Services"
        }
    ],
    "sg:phone":"+1 850 572 5604",
    "sg:postcode":"32506",
    "sg:province":"FL",
    "sg:tags":[
        "hanging",
        "painter",
        "contractor"
    ],
    "wof:name":"Leonard B Runyon Jr Sub-Contr",
    "wof:placetype":"venue"
},
  "geometry": {"coordinates":[-87.364497,30.391911],"type":"Point"}
}