{
  "type": "Feature",
  "properties": {
    "addr:full":"14645 SW 81st Ave Miami FL 33158",
    "addr:housenumber":"14645",
    "addr:postcode":"33158",
    "addr:street":"Sw 81St Ave",
    "iso:country":"US",
    "sg:address":"14645 SW 81st Ave",
    "sg:city":"Miami",
    "sg:classifiers":[
        {
            "category":"Banks & Credit Unions",
            "subcategory":"Financial Services",
            "type":"Services"
        }
    ],
    "sg:phone":"+1 305 238 7414",
    "sg:postcode":"33158",
    "sg:province":"FL",
    "sg:tags":[
        "trust",
        "management"
    ],
    "wof:name":"Elizabeth Hissing Trust",
    "wof:placetype":"venue"
},
  "geometry": {"coordinates":[-80.32450799999999,25.635103],"type":"Point"}
}