{
  "type": "Feature",
  "properties": {
    "addr:full":"5113 W Hwy 98 Panama City FL 32401",
    "addr:housenumber":"5113",
    "addr:postcode":"32401",
    "addr:street":"W Hwy 98",
    "iso:country":"US",
    "sg:address":"5113 W Hwy 98",
    "sg:city":"Panama City",
    "sg:classifiers":[
        {
            "category":"Retail",
            "subcategory":"Auto Repair",
            "type":"Services"
        }
    ],
    "sg:phone":"+1 850 785 6737",
    "sg:postcode":"32401",
    "sg:province":"FL",
    "sg:tags":[
        "repairing",
        "automobile"
    ],
    "wof:name":"Backbeach Auto Svc Inc",
    "wof:placetype":"venue"
},
  "geometry": {"coordinates":[-85.726264,30.18293],"type":"Point"}
}