{
  "type": "Feature",
  "properties": {
    "addr:full":"360 12th Ave S Naples FL 34102",
    "addr:housenumber":"360",
    "addr:postcode":"34102",
    "addr:street":"12Th Ave S",
    "iso:country":"US",
    "sg:address":"360 12th Ave S",
    "sg:city":"Naples",
    "sg:classifiers":[
        {
            "category":"Professional",
            "subcategory":"Computer Services",
            "type":"Services"
        }
    ],
    "sg:phone":"+1 239 435 7584",
    "sg:postcode":"34102",
    "sg:province":"FL",
    "sg:tags":[
        "internet"
    ],
    "wof:name":"RJVI Inc",
    "wof:placetype":"venue"
},
  "geometry": {"coordinates":[-81.80126199999999,26.132019],"type":"Point"}
}