{
  "type": "Feature",
  "properties": {
    "iso:country":"US",
    "sg:address":"2840 Lone Pine Ln",
    "sg:city":"Naples",
    "sg:classifiers":[
        {
            "category":"Building & Trades",
            "subcategory":"Construction",
            "type":"Services"
        }
    ],
    "sg:phone":"+1 239 592 7609",
    "sg:postcode":"34119",
    "sg:province":"FL",
    "sg:tags":[
        "home",
        "builder"
    ],
    "wof:name":"Titan Custom Homes Inc",
    "wof:placetype":"venue"
},
  "geometry": {"coordinates":[-81.71054700000001,26.286334],"type":"Point"}
}