{
  "type": "Feature",
  "properties": {
    "addr:full":"1099 Shady Ln Kissimmee FL 34744",
    "addr:housenumber":"1099",
    "addr:postcode":"34744",
    "addr:street":"Shady Ln",
    "iso:country":"US",
    "sg:address":"1099 Shady Ln",
    "sg:city":"Kissimmee",
    "sg:classifiers":[
        {
            "category":"Government",
            "subcategory":"Office",
            "type":"Public Place"
        }
    ],
    "sg:phone":"+1 407 847 4357",
    "sg:postcode":"34744",
    "sg:province":"FL",
    "wof:name":"Osceola County Senior Help",
    "wof:placetype":"venue"
},
  "geometry": {"coordinates":[-81.35175599999999,28.283402],"type":"Point"}
}