{
  "type": "Feature",
  "properties": {
    "iso:country":"US",
    "sg:address":"27890 Old 41 Rd",
    "sg:city":"Bonita Springs",
    "sg:classifiers":[
        {
            "category":"Shopping",
            "subcategory":"Beauty & Cosmetics",
            "type":"Retail Goods"
        }
    ],
    "sg:phone":"+1 239 992 0567",
    "sg:postcode":"34135",
    "sg:province":"FL",
    "sg:tags":[
        "merchandise"
    ],
    "wof:name":"Mary Kay Mthes Asid Intr Dsign",
    "wof:placetype":"venue"
},
  "geometry": {"coordinates":[-81.77884899999999,26.332141],"type":"Point"}
}