{
  "type": "Feature",
  "properties": {
    "iso:country":"US",
    "sg:address":"9950 NW 29th St",
    "sg:city":"Coral Springs",
    "sg:classifiers":[
        {
            "category":"Organizations",
            "subcategory":"Religious Organization",
            "type":"Services"
        }
    ],
    "sg:phone":"+1 954 752 3950",
    "sg:postcode":"33065",
    "sg:province":"FL",
    "sg:tags":[
        "catholic",
        "church"
    ],
    "wof:name":"St Andrews Catholic Church",
    "wof:placetype":"venue"
},
  "geometry": {"coordinates":[-80.259927,26.267004],"type":"Point"}
}