{
  "type": "Feature",
  "properties": {
    "iso:country":"US",
    "sg:address":"2431 W Pensacola St",
    "sg:city":"Tallahassee",
    "sg:classifiers":[
        {
            "category":"Building & Trades",
            "subcategory":"Construction",
            "type":"Services"
        }
    ],
    "sg:phone":"+1 850 576 5416",
    "sg:postcode":"32304",
    "sg:province":"FL",
    "sg:tags":[
        "contractor"
    ],
    "wof:name":"Sullivan & Son Shtmtl Works",
    "wof:placetype":"venue"
},
  "geometry": {"coordinates":[-84.32669199999999,30.44097],"type":"Point"}
}