{
  "type": "Feature",
  "properties": {
    "addr:full":"1016 Clemons St Jupiter FL 33477",
    "addr:housenumber":"1016",
    "addr:postcode":"33477",
    "addr:street":"Clemons St",
    "iso:country":"US",
    "sg:address":"1016 Clemons St",
    "sg:city":"Jupiter",
    "sg:classifiers":[
        {
            "category":"Freight",
            "type":"Transportation"
        }
    ],
    "sg:phone":"+1 561 745 3134",
    "sg:postcode":"33477",
    "sg:province":"FL",
    "sg:tags":[
        "cargo",
        "broker",
        "agent",
        "operator",
        "shipping",
        "owner",
        "steamship"
    ],
    "sg:website":"www.wingbridge.com",
    "wof:name":"Wing Bridge Shipping Co",
    "wof:placetype":"venue"
},
  "geometry": {"coordinates":[-80.081236,26.94511],"type":"Point"}
}