{
  "type": "Feature",
  "properties": {
    "iso:country":"US",
    "sg:address":"5929 Youngquist Rd",
    "sg:city":"Fort Myers",
    "sg:classifiers":[
        {
            "category":"Professional",
            "subcategory":"Engineering",
            "type":"Services"
        }
    ],
    "sg:phone":"+1 239 454 5100",
    "sg:postcode":"33912",
    "sg:province":"FL",
    "sg:tags":[
        "engineer"
    ],
    "wof:name":"Thomas A Delnay PE",
    "wof:placetype":"venue"
},
  "geometry": {"coordinates":[-81.857629,26.511031],"type":"Point"}
}