{
  "type": "Feature",
  "properties": {
    "iso:country":"US",
    "sg:address":"1765 W Fletcher Ave",
    "sg:city":"Tampa",
    "sg:classifiers":[
        {
            "category":"Travel",
            "subcategory":"Travel Agent",
            "type":"Entertainment"
        }
    ],
    "sg:phone":"+1 813 908 1777",
    "sg:postcode":"33612",
    "sg:province":"FL",
    "sg:tags":[
        "agency",
        "bureau"
    ],
    "wof:name":"Travel Connection",
    "wof:placetype":"venue"
},
  "geometry": {"coordinates":[-82.476426,28.069463],"type":"Point"}
}