{
  "type": "Feature",
  "properties": {
    "addr:full":"212 9th St N St Petersburg FL 33705",
    "addr:housenumber":"212",
    "addr:postcode":"33705",
    "addr:street":"9Th St N",
    "iso:country":"US",
    "sg:address":"212 9th St N",
    "sg:city":"St Petersburg",
    "sg:classifiers":[
        {
            "category":"Food & Beverages",
            "subcategory":"Groceries & Convenience Stores",
            "type":"Retail Goods"
        }
    ],
    "sg:phone":"+1 727 821 4525",
    "sg:postcode":"33705",
    "sg:province":"FL",
    "sg:tags":[
        "grocer"
    ],
    "wof:name":"Downtown Food Market",
    "wof:placetype":"venue"
},
  "geometry": {"coordinates":[-82.64674599999999,27.773677],"type":"Point"}
}