{
  "type": "Feature",
  "properties": {
    "iso:country":"US",
    "sg:address":"111 Smith St",
    "sg:city":"Tallahassee",
    "sg:classifiers":[
        {
            "category":"Real Estate",
            "subcategory":"Real Estate Agent",
            "type":"Services"
        }
    ],
    "sg:phone":"+1 850 222 1100",
    "sg:postcode":"32301",
    "sg:province":"FL",
    "wof:name":"Rayner Real Estate",
    "wof:placetype":"venue"
},
  "geometry": {"coordinates":[-84.264533,30.44259],"type":"Point"}
}