{
  "type": "Feature",
  "properties": {
    "iso:country":"US",
    "sg:address":"385 SW 60th Ave",
    "sg:city":"Ocala",
    "sg:classifiers":[
        {
            "category":"Wholesale",
            "subcategory":"Medical Equipment & Supplies",
            "type":"Manufacturing & Wholesale Goods"
        },
        {
            "category":"Shopping",
            "subcategory":"Pets & Pet Supplies",
            "type":"Retail Goods"
        },
        {
            "category":"Retail",
            "subcategory":"Veterinary Services",
            "type":"Services"
        }
    ],
    "sg:phone":"+1 352 237 1755",
    "sg:postcode":"34474",
    "sg:province":"FL",
    "sg:tags":[
        "veterinarian",
        "product",
        "health",
        "animal",
        "supply-wholesale"
    ],
    "sg:website":"http://www.lextronanimalhealth.com",
    "wof:name":"Lextron Animal Health",
    "wof:placetype":"venue"
},
  "geometry": {"coordinates":[-82.21863399999999,29.182995],"type":"Point"}
}