{
  "type": "Feature",
  "properties": {
    "iso:country":"US",
    "sg:address":"312 E Boynton Beach Blvd",
    "sg:city":"Boynton Beach",
    "sg:classifiers":[
        {
            "category":"Wholesale",
            "subcategory":"Non-durable Goods",
            "type":"Manufacturing & Wholesale Goods"
        }
    ],
    "sg:phone":"+1 561 737 8478",
    "sg:postcode":"33435",
    "sg:province":"FL",
    "sg:tags":[
        "advertising"
    ],
    "wof:name":"Corporate Visibility Inc",
    "wof:placetype":"venue"
},
  "geometry": {"coordinates":[-80.061903,26.528832],"type":"Point"}
}