{
  "type": "Feature",
  "properties": {
    "iso:country":"US",
    "sg:address":"140 NE 169th St",
    "sg:city":"North Miami Bch",
    "sg:classifiers":[
        {
            "category":"Wholesale",
            "subcategory":"Construction Materials",
            "type":"Manufacturing & Wholesale Goods"
        }
    ],
    "sg:phone":"+1 305 968 4780",
    "sg:postcode":"33162",
    "sg:province":"FL",
    "sg:tags":[
        "marble"
    ],
    "wof:name":"Carlos Glass-Block Tile Instln",
    "wof:placetype":"venue"
},
  "geometry": {"coordinates":[-80.197143,25.929965],"type":"Point"}
}