{
  "type": "Feature",
  "properties": {
    "addr:full":"12081 N Okeechobee Rd Hialeah FL 33018",
    "addr:housenumber":"12081",
    "addr:postcode":"33018",
    "addr:street":"N Okeechobee Rd",
    "iso:country":"US",
    "sg:address":"12081 N Okeechobee Rd",
    "sg:city":"Hialeah",
    "sg:classifiers":[
        {
            "category":"Shopping",
            "subcategory":"Department Store",
            "type":"Retail Goods"
        }
    ],
    "sg:phone":"+1 305 825 2444",
    "sg:postcode":"33018",
    "sg:province":"FL",
    "sg:tags":[
        "shop"
    ],
    "wof:name":"S U Discount",
    "wof:placetype":"venue"
},
  "geometry": {"coordinates":[-80.360377,25.882324],"type":"Point"}
}