{
  "type": "Feature",
  "properties": {
    "iso:country":"US",
    "sg:address":"5801 SW 87th St",
    "sg:city":"Miami",
    "sg:classifiers":[
        {
            "category":"Home & Garden",
            "subcategory":"Building Materials",
            "type":"Retail Goods"
        }
    ],
    "sg:phone":"+1 305 668 5926",
    "sg:postcode":"33143",
    "sg:province":"FL",
    "sg:tags":[
        "equipment",
        "sheet",
        "metal",
        "supply"
    ],
    "sg:website":"http://www.caricom-metals.com",
    "wof:name":"Caricom Metals, Inc",
    "wof:placetype":"venue"
},
  "geometry": {"coordinates":[-80.286919,25.690769],"type":"Point"}
}