{
  "type": "Feature",
  "properties": {
    "iso:country":"US",
    "sg:address":"17760 Park Village Blvd",
    "sg:city":"Fort Myers",
    "sg:classifiers":[
        {
            "category":"Organizations",
            "subcategory":"Community Association",
            "type":"Services"
        }
    ],
    "sg:phone":"+1 239 489 3016",
    "sg:postcode":"33908",
    "sg:province":"FL",
    "sg:tags":[
        "social"
    ],
    "wof:name":"National Association Retired",
    "wof:placetype":"venue"
},
  "geometry": {"coordinates":[-81.86009300000001,26.485573],"type":"Point"}
}