{
  "type": "Feature",
  "properties": {
    "iso:country":"US",
    "sg:address":"1001 3rd Ave W",
    "sg:city":"Bradenton",
    "sg:classifiers":[
        {
            "category":"Banks & Credit Unions",
            "subcategory":"Investment Brokerage",
            "type":"Services"
        }
    ],
    "sg:phone":"+1 941 708 9449",
    "sg:postcode":"34205",
    "sg:province":"FL",
    "sg:tags":[
        "consultant",
        "planning",
        "financial"
    ],
    "wof:name":"American Express Financial Adv",
    "wof:placetype":"venue"
},
  "geometry": {"coordinates":[-82.57342199999999,27.497363],"type":"Point"}
}