{
  "type": "Feature",
  "properties": {
    "addr:full":"4161 Robin Hood Rd Jacksonville FL 32210",
    "addr:housenumber":"4161",
    "addr:postcode":"32210",
    "addr:street":"Robin Hood Rd",
    "iso:country":"US",
    "sg:address":"4161 Robin Hood Rd",
    "sg:city":"Jacksonville",
    "sg:classifiers":[
        {
            "category":"Wholesale",
            "subcategory":"Machinery & Supplies",
            "type":"Manufacturing & Wholesale Goods"
        }
    ],
    "sg:phone":"+1 904 389 8694",
    "sg:postcode":"32210",
    "sg:province":"FL",
    "sg:tags":[
        "industrial"
    ],
    "wof:name":"All Industrial Southeast Inc",
    "wof:placetype":"venue"
},
  "geometry": {"coordinates":[-81.713284,30.265532],"type":"Point"}
}