{
  "type": "Feature",
  "properties": {
    "iso:country":"US",
    "sg:address":"64 Shore Dr",
    "sg:city":"Destin",
    "sg:classifiers":[
        {
            "category":"Building & Trades",
            "subcategory":"Cleaning & Sanitation",
            "type":"Services"
        }
    ],
    "sg:phone":"+1 850 650 3139",
    "sg:postcode":"32550",
    "sg:province":"FL",
    "sg:tags":[
        "maintenance"
    ],
    "wof:name":"S&R Paint & Maintenance Servic",
    "wof:placetype":"venue"
},
  "geometry": {"coordinates":[-86.372421,30.387961],"type":"Point"}
}