{
  "type": "Feature",
  "properties": {
    "addr:full":"12638 Winfield Scott Blvd Orlando FL 32837",
    "addr:housenumber":"12638",
    "addr:postcode":"32837",
    "addr:street":"Winfield Scott Blvd",
    "iso:country":"US",
    "sg:address":"12638 Winfield Scott Blvd",
    "sg:city":"Orlando",
    "sg:classifiers":[
        {
            "category":"Shopping",
            "subcategory":"Jewelry",
            "type":"Retail Goods"
        }
    ],
    "sg:phone":"+1 407 438 6650",
    "sg:postcode":"32837",
    "sg:province":"FL",
    "sg:tags":[
        "jeweler"
    ],
    "wof:name":"Magic Rice",
    "wof:placetype":"venue"
},
  "geometry": {"coordinates":[-81.43137900000001,28.383102],"type":"Point"}
}