{
  "type": "Feature",
  "properties": {
    "iso:country":"US",
    "sg:address":"1326 SE 17th St",
    "sg:city":"Fort Lauderdale",
    "sg:classifiers":[
        {
            "category":"Autos & Motor Vehicles",
            "subcategory":"Boat Sales",
            "type":"Retail Goods"
        }
    ],
    "sg:phone":"+1 954 974 9081",
    "sg:postcode":"33316",
    "sg:province":"FL",
    "sg:tags":[
        "yacht",
        "broker"
    ],
    "wof:name":"Yacht Connection USA",
    "wof:placetype":"venue"
},
  "geometry": {"coordinates":[-80.128787,26.100408],"type":"Point"}
}