{
  "type": "Feature",
  "properties": {
    "iso:country":"US",
    "sg:address":"824 Ambassador Loop",
    "sg:city":"Tampa",
    "sg:classifiers":[
        {
            "category":"Utilities",
            "subcategory":"Water",
            "type":"Services"
        }
    ],
    "sg:phone":"+1 813 264 6715",
    "sg:postcode":"33613",
    "sg:province":"FL",
    "sg:tags":[
        "supply"
    ],
    "sg:website":"www.rain-n-save.com",
    "wof:name":"Rain N Save",
    "wof:placetype":"venue"
},
  "geometry": {"coordinates":[-82.464511,28.080086],"type":"Point"}
}