{
  "type": "Feature",
  "properties": {
    "iso:country":"US",
    "sg:address":"8001 SW 136th Ct",
    "sg:city":"Miami",
    "sg:classifiers":[
        {
            "category":"Building & Trades",
            "subcategory":"Construction",
            "type":"Services"
        }
    ],
    "sg:phone":"+1 305 380 0111",
    "sg:postcode":"33183",
    "sg:province":"FL",
    "sg:tags":[
        "roof",
        "maintenance"
    ],
    "wof:name":"Eagle Enterprises Roofing",
    "wof:placetype":"venue"
},
  "geometry": {"coordinates":[-80.41481899999999,25.69152],"type":"Point"}
}