{
  "type": "Feature",
  "properties": {
    "iso:country":"US",
    "sg:address":"3900 Park Blvd",
    "sg:city":"Pinellas Park",
    "sg:classifiers":[
        {
            "category":"Restaurant",
            "type":"Food & Drink"
        }
    ],
    "sg:menulink":"http://www.allmenus.com/fl/st-petersburg/21606-pollo-tropical/menu/",
    "sg:phone":"+1 727 362 9600",
    "sg:postcode":"33781",
    "sg:province":"FL",
    "sg:tags":[
        "american",
        "chicken"
    ],
    "wof:name":"Pollo Tropical",
    "wof:placetype":"venue"
},
  "geometry": {"coordinates":[-82.688103,27.839182],"type":"Point"}
}