{
  "type": "Feature",
  "properties": {
    "iso:country":"US",
    "sg:address":"50 NE 29th St",
    "sg:city":"Miami",
    "sg:classifiers":[
        {
            "category":"Home & Garden",
            "subcategory":"Carpets & Floor Coverings",
            "type":"Retail Goods"
        }
    ],
    "sg:phone":"+1 305 576 4845",
    "sg:postcode":"33137",
    "sg:province":"FL",
    "sg:tags":[
        "dealer",
        "rug"
    ],
    "wof:name":"Carpet Boutique Inc",
    "wof:placetype":"venue"
},
  "geometry": {"coordinates":[-80.194114,25.803927],"type":"Point"}
}