{
  "type": "Feature",
  "properties": {
    "iso:country":"US",
    "sg:address":"94 W Underwood St",
    "sg:city":"Orlando",
    "sg:classifiers":[
        {
            "category":"Health Services",
            "subcategory":"Doctor",
            "type":"Services"
        }
    ],
    "sg:phone":"+1 407 422 8873",
    "sg:postcode":"32806",
    "sg:province":"FL",
    "sg:tags":[
        "medical"
    ],
    "wof:name":"Reguero Lillian MD Faap",
    "wof:placetype":"venue"
},
  "geometry": {"coordinates":[-81.378349,28.526834],"type":"Point"}
}