{
  "type": "Feature",
  "properties": {
    "addr:full":"7261 Mobile Hwy Pensacola FL 32526",
    "addr:housenumber":"7261",
    "addr:postcode":"32526",
    "addr:street":"Mobile Hwy",
    "iso:country":"US",
    "sg:address":"7261 Mobile Hwy",
    "sg:city":"Pensacola",
    "sg:classifiers":[
        {
            "category":"Shopping",
            "subcategory":"Clothing, Apparel, & Fashions",
            "type":"Retail Goods"
        }
    ],
    "sg:phone":"+1 850 944 5163",
    "sg:postcode":"32526",
    "sg:province":"FL",
    "sg:tags":[
        "apparel",
        "women's"
    ],
    "wof:name":"B & L Inspirations",
    "wof:placetype":"venue"
},
  "geometry": {"coordinates":[-87.33963,30.499314],"type":"Point"}
}