{
  "type": "Feature",
  "properties": {
    "addr:full":"9130 S Dadeland Blvd Miami FL 33156",
    "addr:housenumber":"9130",
    "addr:postcode":"33156",
    "addr:street":"S Dadeland Blvd",
    "iso:country":"US",
    "sg:address":"9130 S Dadeland Blvd",
    "sg:city":"Miami",
    "sg:classifiers":[
        {
            "category":"Insurance",
            "subcategory":"Insurance Agent",
            "type":"Services"
        },
        {
            "category":"Insurance",
            "subcategory":"Hazard Insurance",
            "type":"Services"
        }
    ],
    "sg:phone":"+1 305 670 3135",
    "sg:postcode":"33156",
    "sg:province":"FL",
    "sg:tags":[
        "fire",
        "property",
        "casualty"
    ],
    "sg:website":"http://www.zurichna.com",
    "wof:name":"Zurich North American Insurance Company",
    "wof:placetype":"venue"
},
  "geometry": {"coordinates":[-80.31473,25.685558],"type":"Point"}
}