{
  "type": "Feature",
  "properties": {
    "iso:country":"US",
    "sg:address":"6154 11th St",
    "sg:city":"Zephyrhills",
    "sg:classifiers":[
        {
            "category":"Building & Trades",
            "subcategory":"Landscaping Services",
            "type":"Services"
        }
    ],
    "sg:phone":"+1 813 780 1072",
    "sg:postcode":"33542",
    "sg:province":"FL",
    "wof:name":"Ej Lawn Service",
    "wof:placetype":"venue"
},
  "geometry": {"coordinates":[-82.181004,28.246506],"type":"Point"}
}