{
  "type": "Feature",
  "properties": {
    "iso:country":"US",
    "sg:address":"244 Bimini Dr",
    "sg:city":"Fort Pierce",
    "sg:classifiers":[
        {
            "category":"Real Estate",
            "subcategory":"Real Estate Agent",
            "type":"Services"
        }
    ],
    "sg:phone":"+1 772 460 7979",
    "sg:postcode":"34949",
    "sg:province":"FL",
    "wof:name":"Daniel Kittrell Inc",
    "wof:placetype":"venue"
},
  "geometry": {"coordinates":[-80.30390199999999,27.486436],"type":"Point"}
}