{
  "type": "Feature",
  "properties": {
    "iso:country":"US",
    "sg:address":"301 Monument Ave",
    "sg:city":"Port St Joe",
    "sg:classifiers":[
        {
            "category":"Autos & Motor Vehicles",
            "subcategory":"Boat Sales",
            "type":"Retail Goods"
        }
    ],
    "sg:phone":"+1 850 229 6330",
    "sg:postcode":"32456",
    "sg:province":"FL",
    "sg:tags":[
        "dealer",
        "sales"
    ],
    "sg:website":"www.dalysdock.com",
    "wof:name":"Daly's Dock & Dive Ctr",
    "wof:placetype":"venue"
},
  "geometry": {"coordinates":[-85.30420599999999,29.813919],"type":"Point"}
}