{
  "type": "Feature",
  "properties": {
    "addr:full":"14103 Mc Cormick Dr Tampa FL 33626",
    "addr:housenumber":"14103",
    "addr:postcode":"33626",
    "addr:street":"Mc Cormick Dr",
    "iso:country":"US",
    "sg:address":"14103 Mc Cormick Dr",
    "sg:city":"Tampa",
    "sg:classifiers":[
        {
            "category":"Manufacturing",
            "subcategory":"Building Materials",
            "type":"Manufacturing & Wholesale Goods"
        }
    ],
    "sg:phone":"+1 813 855 7273",
    "sg:postcode":"33626",
    "sg:province":"FL",
    "sg:tags":[
        "shutter",
        "wood",
        "mfg"
    ],
    "wof:name":"Interntnal Poly/Satin Shutters",
    "wof:placetype":"venue"
},
  "geometry": {"coordinates":[-82.645675,28.06314],"type":"Point"}
}