{
  "type": "Feature",
  "properties": {
    "addr:full":"323 NE 7th Ave Delray Beach FL 33483",
    "addr:housenumber":"323",
    "addr:postcode":"33483",
    "addr:street":"Ne 7Th Ave",
    "iso:country":"US",
    "sg:address":"323 NE 7th Ave",
    "sg:city":"Delray Beach",
    "sg:classifiers":[
        {
            "category":"Professional",
            "subcategory":"Art Services",
            "type":"Services"
        }
    ],
    "sg:phone":"+1 561 272 0940",
    "sg:postcode":"33483",
    "sg:province":"FL",
    "sg:tags":[
        "graphic",
        "designer"
    ],
    "wof:name":"Nesbitt Graphics",
    "wof:placetype":"venue"
},
  "geometry": {"coordinates":[-80.06608900000001,26.46877],"type":"Point"}
}