{
  "type": "Feature",
  "properties": {
    "iso:country":"US",
    "sg:address":"133 Sanford Ave",
    "sg:city":"Debary",
    "sg:classifiers":[
        {
            "category":"Government",
            "subcategory":"Police Station",
            "type":"Public Place"
        }
    ],
    "sg:phone":"+1 386 668 0081",
    "sg:postcode":"32713",
    "sg:province":"FL",
    "sg:tags":[
        "department"
    ],
    "wof:name":"Sanford Police Dept",
    "wof:placetype":"venue"
},
  "geometry": {"coordinates":[-81.32652,28.876382],"type":"Point"}
}