{
  "type": "Feature",
  "properties": {
    "iso:country":"US",
    "sg:address":"3329 13th St",
    "sg:city":"St Cloud",
    "sg:classifiers":[
        {
            "category":"Autos & Motor Vehicles",
            "subcategory":"Boat Sales",
            "type":"Retail Goods"
        }
    ],
    "sg:phone":"+1 407 892 5166",
    "sg:postcode":"34769",
    "sg:province":"FL",
    "sg:tags":[
        "repair",
        "outboard"
    ],
    "wof:name":"Precision Marine Inc",
    "wof:placetype":"venue"
},
  "geometry": {"coordinates":[-81.307913,28.248005],"type":"Point"}
}