{
  "type": "Feature",
  "properties": {
    "addr:full":"107 US Hwy 92 Longwood FL 32750",
    "addr:housenumber":"107",
    "addr:postcode":"32750",
    "addr:street":"Us Hwy 92",
    "iso:country":"US",
    "sg:address":"107 US Hwy 92",
    "sg:city":"Longwood",
    "sg:classifiers":[
        {
            "category":"Autos & Motor Vehicles",
            "subcategory":"Fuel & Gas Station",
            "type":"Retail Goods"
        }
    ],
    "sg:phone":"+1 407 696 2413",
    "sg:postcode":"32750",
    "sg:province":"FL",
    "sg:tags":[
        "station",
        "gasoline"
    ],
    "wof:name":"Exxon",
    "wof:placetype":"venue"
},
  "geometry": {"coordinates":[-81.326798,28.700679],"type":"Point"}
}