{
  "type": "Feature",
  "properties": {
    "iso:country":"US",
    "sg:address":"12420 Golden Oak Cir",
    "sg:city":"Hudson",
    "sg:classifiers":[
        {
            "category":"Professional",
            "subcategory":"Management & Consulting",
            "type":"Services"
        }
    ],
    "sg:phone":"+1 727 856 6263",
    "sg:postcode":"34669",
    "sg:province":"FL",
    "sg:tags":[
        "home",
        "demonstration"
    ],
    "wof:name":"Amway Distributors",
    "wof:placetype":"venue"
},
  "geometry": {"coordinates":[-82.61018199999999,28.345113],"type":"Point"}
}