{
  "type": "Feature",
  "properties": {
    "addr:full":"5781 Westport Ln Naples FL 34116",
    "addr:housenumber":"5781",
    "addr:postcode":"34116",
    "addr:street":"Westport Ln",
    "iso:country":"US",
    "sg:address":"5781 Westport Ln",
    "sg:city":"Naples",
    "sg:classifiers":[
        {
            "category":"Wholesale",
            "subcategory":"Farm Supplies",
            "type":"Manufacturing & Wholesale Goods"
        }
    ],
    "sg:phone":"+1 239 352 7111",
    "sg:postcode":"34116",
    "sg:province":"FL",
    "sg:tags":[
        "horse"
    ],
    "wof:name":"Napoli Management Services Inc",
    "wof:placetype":"venue"
},
  "geometry": {"coordinates":[-81.721649,26.19267],"type":"Point"}
}