{
  "type": "Feature",
  "properties": {
    "iso:country":"US",
    "sg:address":"619 Hibiscus Dr",
    "sg:city":"Hallandale",
    "sg:classifiers":[
        {
            "category":"Building & Trades",
            "subcategory":"Electrical",
            "type":"Services"
        }
    ],
    "sg:phone":"+1 954 455 9211",
    "sg:postcode":"33009",
    "sg:province":"FL",
    "sg:tags":[
        "electrical",
        "contractor"
    ],
    "wof:name":"Smith & Hooten Electric Co",
    "wof:placetype":"venue"
},
  "geometry": {"coordinates":[-80.12532,25.97676],"type":"Point"}
}