{
  "type": "Feature",
  "properties": {
    "iso:country":"US",
    "sg:address":"14114 Riverstone Dr",
    "sg:city":"Tampa",
    "sg:classifiers":[
        {
            "category":"Banks & Credit Unions",
            "subcategory":"Investment Brokerage",
            "type":"Services"
        }
    ],
    "sg:phone":"+1 813 969 2767",
    "sg:postcode":"33624",
    "sg:province":"FL",
    "sg:tags":[
        "advisory",
        "financial"
    ],
    "wof:name":"Baybridge Financial Group",
    "wof:placetype":"venue"
},
  "geometry": {"coordinates":[-82.534696,28.081519],"type":"Point"}
}