{
  "type": "Feature",
  "properties": {
    "addr:full":"2601 Thonotosassa Rd Plant City FL 33563",
    "addr:housenumber":"2601",
    "addr:postcode":"33563",
    "addr:street":"Thonotosassa Rd",
    "iso:country":"US",
    "sg:address":"2601 Thonotosassa Rd",
    "sg:city":"Plant City",
    "sg:classifiers":[
        {
            "category":"Restaurant",
            "type":"Food & Drink"
        }
    ],
    "sg:menulink":"http://www.allmenus.com/fl/plant-city/187613-mcdonalds/menu/",
    "sg:phone":"+1 813 754 3945",
    "sg:postcode":"33563",
    "sg:province":"FL",
    "sg:tags":[
        "burger",
        "american"
    ],
    "wof:name":"McDonald's",
    "wof:placetype":"venue"
},
  "geometry": {"coordinates":[-82.14999899999999,28.025358],"type":"Point"}
}