{
  "type": "Feature",
  "properties": {
    "iso:country":"US",
    "sg:address":"9145 N Cedar Cove Rd",
    "sg:city":"Dunnellon",
    "sg:classifiers":[
        {
            "category":"Professional",
            "subcategory":"Detective & Security Services",
            "type":"Services"
        }
    ],
    "sg:phone":"+1 352 344 8006",
    "sg:postcode":"34434",
    "sg:province":"FL",
    "sg:tags":[
        "information",
        "bureau"
    ],
    "wof:name":"Window A C Svc",
    "wof:placetype":"venue"
},
  "geometry": {"coordinates":[-82.37176100000001,28.99287],"type":"Point"}
}