{
  "type": "Feature",
  "properties": {
    "iso:country":"US",
    "sg:address":"4304 Bell Shoals Rd",
    "sg:city":"Valrico",
    "sg:classifiers":[
        {
            "category":"Social Services",
            "subcategory":"Child Care",
            "type":"Services"
        }
    ],
    "sg:phone":"+1 813 654 0572",
    "sg:postcode":"33596",
    "sg:province":"FL",
    "sg:website":"www.kindercare.com",
    "wof:name":"Kinder Care Learning Ctr",
    "wof:placetype":"venue"
},
  "geometry": {"coordinates":[-82.269189,27.875739],"type":"Point"}
}