{
  "type": "Feature",
  "properties": {
    "iso:country":"US",
    "sg:address":"5100 Seminole Blvd",
    "sg:city":"St Petersburg",
    "sg:classifiers":[
        {
            "category":"Health Services",
            "subcategory":"Doctor",
            "type":"Services"
        }
    ],
    "sg:phone":"+1 727 522 6699",
    "sg:postcode":"33708",
    "sg:province":"FL",
    "sg:tags":[
        "physician",
        "surgeon"
    ],
    "wof:name":"Michelle Spuza-Milord MD",
    "wof:placetype":"venue"
},
  "geometry": {"coordinates":[-82.78703,27.818258],"type":"Point"}
}