{
  "type": "Feature",
  "properties": {
    "addr:full":"2202 W Atlantic Ave Delray Beach FL 33444",
    "addr:housenumber":"2202",
    "addr:postcode":"33444",
    "addr:street":"W Atlantic Ave",
    "iso:country":"US",
    "sg:address":"2202 W Atlantic Ave",
    "sg:city":"Delray Beach",
    "sg:classifiers":[
        {
            "category":"Health Services",
            "subcategory":"Podiatrist",
            "type":"Services"
        }
    ],
    "sg:phone":"+1 561 272 8880",
    "sg:postcode":"33444",
    "sg:province":"FL",
    "wof:name":"Delray Beach Podiatry Assoc",
    "wof:placetype":"venue"
},
  "geometry": {"coordinates":[-80.091947,26.461289],"type":"Point"}
}