{
  "type": "Feature",
  "properties": {
    "iso:country":"US",
    "sg:address":"3661 Lenox Ave",
    "sg:city":"Jacksonville",
    "sg:classifiers":[
        {
            "category":"Retail",
            "subcategory":"Auto Repair",
            "type":"Services"
        }
    ],
    "sg:phone":"+1 904 387 6915",
    "sg:postcode":"32254",
    "sg:province":"FL",
    "sg:tags":[
        "body",
        "automobile",
        "painting"
    ],
    "wof:name":"Lenox Paint and Body Shop",
    "wof:placetype":"venue"
},
  "geometry": {"coordinates":[-81.717274,30.321959],"type":"Point"}
}