{
  "type": "Feature",
  "properties": {
    "iso:country":"US",
    "sg:address":"556 SW Martin Luther King Blvd",
    "sg:city":"Belle Glade",
    "sg:classifiers":[
        {
            "category":"Shopping",
            "subcategory":"Discount & Variety Stores",
            "type":"Retail Goods"
        }
    ],
    "sg:phone":"+1 561 993 4345",
    "sg:postcode":"33430",
    "sg:province":"FL",
    "sg:tags":[
        "merchandise",
        "general"
    ],
    "wof:name":"Tiny's Package Store",
    "wof:placetype":"venue"
},
  "geometry": {"coordinates":[-80.673394,26.682173],"type":"Point"}
}