{
  "type": "Feature",
  "properties": {
    "addr:full":"597 W 11th St Panama City FL 32401",
    "addr:housenumber":"597",
    "addr:postcode":"32401",
    "addr:street":"W 11Th St",
    "iso:country":"US",
    "sg:address":"597 W 11th St",
    "sg:city":"Panama City",
    "sg:classifiers":[
        {
            "category":"Health Services",
            "subcategory":"Doctor",
            "type":"Services"
        }
    ],
    "sg:phone":"+1 850 872 4720",
    "sg:postcode":"32401",
    "sg:province":"FL",
    "sg:tags":[
        "clinic"
    ],
    "wof:name":"Primary Care Clinic",
    "wof:placetype":"venue"
},
  "geometry": {"coordinates":[-85.666374,30.167821],"type":"Point"}
}