{
  "type": "Feature",
  "properties": {
    "iso:country":"US",
    "sg:address":"6268 Via Palladium",
    "sg:city":"Boca Raton",
    "sg:classifiers":[
        {
            "category":"Manufacturing",
            "subcategory":"Tools & Machinery",
            "type":"Manufacturing & Wholesale Goods"
        }
    ],
    "sg:phone":"+1 561 367 9622",
    "sg:postcode":"33433",
    "sg:province":"FL",
    "sg:tags":[
        "surgical",
        "mfg"
    ],
    "wof:name":"Bloch Orthotics & Compression",
    "wof:placetype":"venue"
},
  "geometry": {"coordinates":[-80.142512,26.335945],"type":"Point"}
}