{
  "type": "Feature",
  "properties": {
    "addr:full":"1111 12th St Key West FL 33040",
    "addr:housenumber":"1111",
    "addr:postcode":"33040",
    "addr:street":"12Th St",
    "iso:country":"US",
    "sg:address":"1111 12th St",
    "sg:city":"Key West",
    "sg:classifiers":[
        {
            "category":"Health Services",
            "subcategory":"Doctor",
            "type":"Services"
        }
    ],
    "sg:phone":"+1 305 294 9554",
    "sg:postcode":"33040",
    "sg:province":"FL",
    "sg:tags":[
        "physician",
        "surgeon"
    ],
    "wof:name":"Island Psychiatry Inc",
    "wof:placetype":"venue"
},
  "geometry": {"coordinates":[-81.76860499999999,24.564632],"type":"Point"}
}