{
  "type": "Feature",
  "properties": {
    "iso:country":"US",
    "sg:address":"1140 Covina St",
    "sg:city":"Cocoa",
    "sg:classifiers":[
        {
            "category":"Freight",
            "type":"Transportation"
        }
    ],
    "sg:phone":"+1 321 638 3801",
    "sg:postcode":"32927",
    "sg:province":"FL",
    "sg:tags":[
        "operator",
        "local",
        "trucking"
    ],
    "wof:name":"Ricklee Trucking Inc",
    "wof:placetype":"venue"
},
  "geometry": {"coordinates":[-80.771792,28.473512],"type":"Point"}
}