{
  "type": "Feature",
  "properties": {
    "iso:country":"US",
    "sg:address":"2140 Range Rd",
    "sg:city":"Clearwater",
    "sg:classifiers":[
        {
            "category":"Manufacturing",
            "subcategory":"Metals",
            "type":"Manufacturing & Wholesale Goods"
        },
        {
            "category":"Manufacturing",
            "subcategory":"Tools & Machinery",
            "type":"Manufacturing & Wholesale Goods"
        }
    ],
    "sg:phone":"+1 727 442 4025",
    "sg:postcode":"33765",
    "sg:province":"FL",
    "sg:tags":[
        "mfg",
        "cutting",
        "hand"
    ],
    "sg:website":"www.precision.bz",
    "wof:name":"Precision Manufacturing & Sale",
    "wof:placetype":"venue"
},
  "geometry": {"coordinates":[-82.750339,27.978948],"type":"Point"}
}