{
  "type": "Feature",
  "properties": {
    "iso:country":"US",
    "sg:address":"14272 SW 121st Pl",
    "sg:city":"Miami",
    "sg:classifiers":[
        {
            "category":"Professional",
            "subcategory":"Business Services",
            "type":"Services"
        }
    ],
    "sg:phone":"+1 305 668 3010",
    "sg:postcode":"33186",
    "sg:province":"FL",
    "sg:tags":[
        "development",
        "product",
        "designers-industrial",
        "marketing",
        "commercial",
        "design"
    ],
    "wof:name":"The Ship Of The Desert Inc",
    "wof:placetype":"venue"
},
  "geometry": {"coordinates":[-80.390158,25.63493],"type":"Point"}
}