{
  "type": "Feature",
  "properties": {
    "iso:country":"US",
    "sg:address":"2601 E Henry Ave",
    "sg:city":"Tampa",
    "sg:classifiers":[
        {
            "category":"Building & Trades",
            "subcategory":"Construction",
            "type":"Services"
        }
    ],
    "sg:phone":"+1 813 232 5800",
    "sg:postcode":"33610",
    "sg:province":"FL",
    "sg:tags":[
        "cabinet",
        "carpentry",
        "maker",
        "contractor"
    ],
    "wof:name":"Roque's Cabinets",
    "wof:placetype":"venue"
},
  "geometry": {"coordinates":[-82.428268,27.999137],"type":"Point"}
}