{
  "type": "Feature",
  "properties": {
    "addr:full":"8361 NW 64th St Miami FL 33166",
    "addr:housenumber":"8361",
    "addr:postcode":"33166",
    "addr:street":"Nw 64Th St",
    "iso:country":"US",
    "sg:address":"8361 NW 64th St",
    "sg:city":"Miami",
    "sg:classifiers":[
        {
            "category":"Building & Trades",
            "subcategory":"Construction",
            "type":"Services"
        }
    ],
    "sg:phone":"+1 305 477 5118",
    "sg:postcode":"33166",
    "sg:province":"FL",
    "sg:tags":[
        "management",
        "co",
        "liquid",
        "waster",
        "general",
        "contractor"
    ],
    "wof:name":"S O S Plumbing & Envmtl Contrs",
    "wof:placetype":"venue"
},
  "geometry": {"coordinates":[-80.331042,25.83173],"type":"Point"}
}