{
  "type": "Feature",
  "properties": {
    "addr:full":"1148 Turner St Clearwater FL 33756",
    "addr:housenumber":"1148",
    "addr:postcode":"33756",
    "addr:street":"Turner St",
    "iso:country":"US",
    "sg:address":"1148 Turner St",
    "sg:city":"Clearwater",
    "sg:classifiers":[
        {
            "category":"Organizations",
            "subcategory":"Religious Organization",
            "type":"Services"
        }
    ],
    "sg:phone":"+1 727 461 1148",
    "sg:postcode":"33756",
    "sg:province":"FL",
    "sg:tags":[
        "church"
    ],
    "wof:name":"Flowing River Church",
    "wof:placetype":"venue"
},
  "geometry": {"coordinates":[-82.78793899999999,27.959514],"type":"Point"}
}