{
  "type": "Feature",
  "properties": {
    "iso:country":"US",
    "sg:address":"1734 Trade Center Way",
    "sg:city":"Naples",
    "sg:classifiers":[
        {
            "category":"Manufacturing",
            "subcategory":"Glass & Minerals",
            "type":"Manufacturing & Wholesale Goods"
        }
    ],
    "sg:phone":"+1 239 598 3004",
    "sg:postcode":"34109",
    "sg:province":"FL",
    "sg:tags":[
        "cut",
        "mfg"
    ],
    "wof:name":"Interiors Cultured Marble",
    "wof:placetype":"venue"
},
  "geometry": {"coordinates":[-81.77090699999999,26.225236],"type":"Point"}
}