{
  "type": "Feature",
  "properties": {
    "addr:full":"718 W Winter Park St Orlando FL 32804",
    "addr:housenumber":"718",
    "addr:postcode":"32804",
    "addr:street":"W Winter Park St",
    "iso:country":"US",
    "sg:address":"718 W Winter Park St",
    "sg:city":"Orlando",
    "sg:classifiers":[
        {
            "category":"Social Services",
            "subcategory":"Adult Care",
            "type":"Services"
        }
    ],
    "sg:phone":"+1 407 843 0951",
    "sg:postcode":"32804",
    "sg:province":"FL",
    "sg:tags":[
        "residential"
    ],
    "wof:name":"Battung",
    "wof:placetype":"venue"
},
  "geometry": {"coordinates":[-81.39272800000001,28.575191],"type":"Point"}
}