{
  "type": "Feature",
  "properties": {
    "iso:country":"US",
    "sg:address":"2238 Valley Dr",
    "sg:city":"Apopka",
    "sg:classifiers":[
        {
            "category":"Building & Trades",
            "subcategory":"Construction",
            "type":"Services"
        }
    ],
    "sg:phone":"+1 407 886 2907",
    "sg:postcode":"32703",
    "sg:province":"FL",
    "sg:tags":[
        "concrete",
        "contractor"
    ],
    "wof:name":"Brian W Roop",
    "wof:placetype":"venue"
},
  "geometry": {"coordinates":[-81.54743000000001,28.621523],"type":"Point"}
}