{
  "type": "Feature",
  "properties": {
    "iso:country":"US",
    "sg:address":"6080 Babcock St SE",
    "sg:city":"Palm Bay",
    "sg:classifiers":[
        {
            "category":"Banks & Credit Unions",
            "subcategory":"Bank",
            "type":"Services"
        }
    ],
    "sg:phone":"+1 321 728 8558",
    "sg:postcode":"32909",
    "sg:province":"FL",
    "sg:tags":[
        "loan",
        "real estate"
    ],
    "wof:name":"MNA Mortgage Co",
    "wof:placetype":"venue"
},
  "geometry": {"coordinates":[-80.621933,27.998245],"type":"Point"}
}