{
  "type": "Feature",
  "properties": {
    "iso:country":"US",
    "sg:address":"3621 Dahill Ct",
    "sg:city":"Casselberry",
    "sg:classifiers":[
        {
            "category":"Building & Trades",
            "subcategory":"Construction",
            "type":"Services"
        }
    ],
    "sg:phone":"+1 407 696 4878",
    "sg:postcode":"32707",
    "sg:province":"FL",
    "sg:tags":[
        "residential"
    ],
    "wof:name":"Overley Construction",
    "wof:placetype":"venue"
},
  "geometry": {"coordinates":[-81.293049,28.641737],"type":"Point"}
}