{
  "type": "Feature",
  "properties": {
    "iso:country":"US",
    "sg:address":"9485 S Dixie Hwy",
    "sg:city":"Miami",
    "sg:classifiers":[
        {
            "category":"Personal",
            "subcategory":"Hair Removal",
            "type":"Services"
        }
    ],
    "sg:phone":"+1 305 663 1246",
    "sg:postcode":"33156",
    "sg:province":"FL",
    "wof:name":"Uni-K-Wax Center",
    "wof:placetype":"venue"
},
  "geometry": {"coordinates":[-80.31449000000001,25.682583],"type":"Point"}
}