{
  "type": "Feature",
  "properties": {
    "iso:country":"US",
    "sg:address":"3188 NW 40th Ct",
    "sg:city":"Lauderdale Lakes",
    "sg:classifiers":[
        {
            "category":"Wholesale",
            "subcategory":"Durable Goods & Equipment",
            "type":"Manufacturing & Wholesale Goods"
        }
    ],
    "sg:phone":"+1 954 485 8444",
    "sg:postcode":"33309",
    "sg:province":"FL",
    "sg:tags":[
        "importer"
    ],
    "wof:name":"Williams Co",
    "wof:placetype":"venue"
},
  "geometry": {"coordinates":[-80.188383,26.176944],"type":"Point"}
}