{
  "type": "Feature",
  "properties": {
    "iso:country":"US",
    "sg:address":"1416 Fruitville Rd",
    "sg:city":"Sarasota",
    "sg:classifiers":[
        {
            "category":"Shopping",
            "subcategory":"Florist",
            "type":"Retail Goods"
        }
    ],
    "sg:phone":"+1 941 953 8223",
    "sg:postcode":"34236",
    "sg:province":"FL",
    "wof:name":"Excel Floristry Inc",
    "wof:placetype":"venue"
},
  "geometry": {"coordinates":[-82.54268399999999,27.338856],"type":"Point"}
}