{
  "type": "Feature",
  "properties": {
    "iso:country":"US",
    "sg:address":"1237 Texas Ave",
    "sg:city":"Dunedin",
    "sg:classifiers":[
        {
            "category":"Building & Trades",
            "subcategory":"Plumbing",
            "type":"Services"
        }
    ],
    "sg:phone":"+1 727 443 6714",
    "sg:postcode":"34698",
    "sg:province":"FL",
    "sg:tags":[
        "contractor"
    ],
    "wof:name":"Ellis Family Inc",
    "wof:placetype":"venue"
},
  "geometry": {"coordinates":[-82.76756899999999,28.026746],"type":"Point"}
}