{
  "type": "Feature",
  "properties": {
    "iso:country":"US",
    "sg:address":"18589 NW 27th Ave",
    "sg:city":"Opa Locka",
    "sg:classifiers":[
        {
            "category":"Shopping",
            "subcategory":"Pharmacy",
            "type":"Retail Goods"
        }
    ],
    "sg:phone":"+1 305 430 7970",
    "sg:postcode":"33054",
    "sg:province":"FL",
    "wof:name":"Great Care Pharmacy",
    "wof:placetype":"venue"
},
  "geometry": {"coordinates":[-80.245397,25.944214],"type":"Point"}
}