{
  "type": "Feature",
  "properties": {
    "addr:full":"2010 NW 21st Ave Miami FL 33142",
    "addr:housenumber":"2010",
    "addr:postcode":"33142",
    "addr:street":"Nw 21St Ave",
    "iso:country":"US",
    "sg:address":"2010 NW 21st Ave",
    "sg:city":"Miami",
    "sg:classifiers":[
        {
            "category":"Shopping",
            "subcategory":"Clothing, Apparel, & Fashions",
            "type":"Retail Goods"
        },
        {
            "category":"Shopping",
            "subcategory":"Used Merchandise",
            "type":"Retail Goods"
        }
    ],
    "sg:phone":"+1 305 325 0280",
    "sg:postcode":"33142",
    "sg:province":"FL",
    "sg:tags":[
        "shop",
        "women's",
        "resale",
        "children's",
        "apparel",
        "clothing"
    ],
    "wof:name":"Ashley Creations",
    "wof:placetype":"venue"
},
  "geometry": {"coordinates":[-80.22930100000001,25.794701],"type":"Point"}
}