{
  "type": "Feature",
  "properties": {
    "iso:country":"US",
    "sg:address":"4139 SW Archer Rd Lot 66",
    "sg:city":"Gainesville",
    "sg:classifiers":[
        {
            "category":"Professional",
            "subcategory":"Computer Services",
            "type":"Services"
        }
    ],
    "sg:phone":"+1 352 316 0290",
    "sg:postcode":"32608",
    "sg:province":"FL",
    "sg:tags":[
        "design",
        "system",
        "network"
    ],
    "wof:name":"Esbs",
    "wof:placetype":"venue"
},
  "geometry": {"coordinates":[-82.38927700000001,29.615521],"type":"Point"}
}