{
  "type": "Feature",
  "properties": {
    "iso:country":"US",
    "sg:address":"1001 E Lake Rd N",
    "sg:city":"Tarpon Springs",
    "sg:classifiers":[
        {
            "category":"Building & Trades",
            "subcategory":"Plumbing",
            "type":"Services"
        }
    ],
    "sg:phone":"+1 727 944 2794",
    "sg:postcode":"34688",
    "sg:province":"FL",
    "sg:tags":[
        "conditioning",
        "air",
        "system",
        "contractor"
    ],
    "wof:name":"Hoffman's Appliance & Air",
    "wof:placetype":"venue"
},
  "geometry": {"coordinates":[-82.69717199999999,28.160776],"type":"Point"}
}