{
  "type": "Feature",
  "properties": {
    "iso:country":"US",
    "sg:address":"2210 Grand Cayman Ct",
    "sg:city":"Kissimmee",
    "sg:classifiers":[
        {
            "category":"Arts & Performance",
            "subcategory":"Theater",
            "type":"Entertainment"
        }
    ],
    "sg:phone":"+1 407 944 9067",
    "sg:postcode":"34741",
    "sg:province":"FL",
    "sg:tags":[
        "karaoke"
    ],
    "wof:name":"Barbara Markiewicz Karaoke",
    "wof:placetype":"venue"
},
  "geometry": {"coordinates":[-81.449433,28.312116],"type":"Point"}
}