{
  "type": "Feature",
  "properties": {
    "iso:country":"US",
    "sg:address":"7712 E Chelsea St",
    "sg:city":"Tampa",
    "sg:classifiers":[
        {
            "category":"Place Of Worship",
            "subcategory":"Church",
            "type":"Public Place"
        },
        {
            "category":"Place Of Worship",
            "type":"Public Place"
        },
        {
            "category":"Organizations",
            "subcategory":"Religious Organization",
            "type":"Services"
        }
    ],
    "sg:phone":"+1 813 626 7500",
    "sg:postcode":"33610",
    "sg:province":"FL",
    "sg:tags":[
        "god",
        "churches-church",
        "churches-pentecostal"
    ],
    "wof:name":"Church Of God Southeastern",
    "wof:placetype":"venue"
},
  "geometry": {"coordinates":[-82.370925,27.985187],"type":"Point"}
}