{
  "type": "Feature",
  "properties": {
    "iso:country":"US",
    "sg:address":"845 9th Ave N",
    "sg:city":"Safety Harbor",
    "sg:classifiers":[
        {
            "category":"Building & Trades",
            "subcategory":"Construction",
            "type":"Services"
        }
    ],
    "sg:phone":"+1 727 726 1785",
    "sg:postcode":"34695",
    "sg:province":"FL",
    "sg:tags":[
        "painter"
    ],
    "wof:name":"D & J Painting & Waterproofing",
    "wof:placetype":"venue"
},
  "geometry": {"coordinates":[-82.696747,27.998861],"type":"Point"}
}