{
  "type": "Feature",
  "properties": {
    "addr:full":"799 E Oakland Park Blvd Oakland Park FL 33334",
    "addr:housenumber":"799",
    "addr:postcode":"33334",
    "addr:street":"E Oakland Park Blvd",
    "iso:country":"US",
    "sg:address":"799 E Oakland Park Blvd",
    "sg:city":"Oakland Park",
    "sg:classifiers":[
        {
            "category":"Retail",
            "subcategory":"Laundry & Dry Cleaning",
            "type":"Services"
        }
    ],
    "sg:phone":"+1 954 566 0988",
    "sg:postcode":"33334",
    "sg:province":"FL",
    "wof:name":"Sqeeky Kleen",
    "wof:placetype":"venue"
},
  "geometry": {"coordinates":[-80.136697,26.166742],"type":"Point"}
}