{
  "type": "Feature",
  "properties": {
    "iso:country":"US",
    "sg:address":"6208 Ridge Rd",
    "sg:city":"Port Richey",
    "sg:classifiers":[
        {
            "category":"Local Transit",
            "type":"Transportation"
        },
        {
            "category":"Retail",
            "subcategory":"Auto Repair",
            "type":"Services"
        }
    ],
    "sg:phone":"+1 727 845 1834",
    "sg:postcode":"34668",
    "sg:province":"FL",
    "sg:tags":[
        "limousine",
        "general"
    ],
    "wof:name":"A Silver Streak Car Service",
    "wof:placetype":"venue"
},
  "geometry": {"coordinates":[-82.711651,28.280529],"type":"Point"}
}