{
  "type": "Feature",
  "properties": {
    "iso:country":"US",
    "sg:address":"3502 N Access Rd",
    "sg:city":"Englewood",
    "sg:classifiers":[
        {
            "category":"Personal",
            "subcategory":"Beauty Salon",
            "type":"Services"
        }
    ],
    "sg:phone":"+1 941 475 2887",
    "sg:postcode":"34224",
    "sg:province":"FL",
    "wof:name":"Hairshots",
    "wof:placetype":"venue"
},
  "geometry": {"coordinates":[-82.291389,26.934389],"type":"Point"}
}