{
  "type": "Feature",
  "properties": {
    "iso:country":"US",
    "sg:address":"11300 NW 41st St",
    "sg:city":"Doral",
    "sg:classifiers":[
        {
            "category":"Wholesale",
            "subcategory":"Medical Equipment & Supplies",
            "type":"Manufacturing & Wholesale Goods"
        },
        {
            "category":"Health Services",
            "subcategory":"Hospital",
            "type":"Services"
        }
    ],
    "sg:phone":"+1 305 669 9003",
    "sg:postcode":"33178",
    "sg:province":"FL",
    "sg:tags":[
        "supplies-wholesale",
        "wheelchair",
        "appliance",
        "surgical",
        "manufacturer"
    ],
    "sg:website":"https://www.welchallyn.com",
    "wof:name":"Welch Allyn Inc",
    "wof:placetype":"venue"
},
  "geometry": {"coordinates":[-80.380757,25.811539],"type":"Point"}
}