{
  "type": "Feature",
  "properties": {
    "addr:full":"5300 SW 76th St Miami FL 33143",
    "addr:housenumber":"5300",
    "addr:postcode":"33143",
    "addr:street":"Sw 76Th St",
    "iso:country":"US",
    "sg:address":"5300 SW 76th St",
    "sg:city":"Miami",
    "sg:classifiers":[
        {
            "category":"Professional",
            "subcategory":"Lawyer & Legal Services",
            "type":"Services"
        }
    ],
    "sg:phone":"+1 305 667 1372",
    "sg:postcode":"33143",
    "sg:province":"FL",
    "sg:tags":[
        "attorney",
        "criminal",
        "law"
    ],
    "wof:name":"Edward A Carhart",
    "wof:placetype":"venue"
},
  "geometry": {"coordinates":[-80.27887,25.70085],"type":"Point"}
}