{
  "type": "Feature",
  "properties": {
    "iso:country":"US",
    "sg:address":"7964 Saddlebrook Dr",
    "sg:city":"Port Saint Lucie",
    "sg:classifiers":[
        {
            "category":"Insurance",
            "subcategory":"Insurance Agent",
            "type":"Services"
        }
    ],
    "sg:phone":"+1 772 466 8136",
    "sg:postcode":"34986",
    "sg:province":"FL",
    "wof:name":"J V Insurance Group",
    "wof:placetype":"venue"
},
  "geometry": {"coordinates":[-80.44136899999999,27.32116],"type":"Point"}
}