{
  "type": "Feature",
  "properties": {
    "addr:full":"560 NW 12th Ave Pompano Beach FL 33069",
    "addr:housenumber":"560",
    "addr:postcode":"33069",
    "addr:street":"Nw 12Th Ave",
    "iso:country":"US",
    "sg:address":"560 NW 12th Ave",
    "sg:city":"Pompano Beach",
    "sg:classifiers":[
        {
            "category":"Wholesale",
            "subcategory":"Metals & Minerals",
            "type":"Manufacturing & Wholesale Goods"
        }
    ],
    "sg:phone":"+1 954 943 1616",
    "sg:postcode":"33069",
    "sg:province":"FL",
    "sg:tags":[
        "rope",
        "wire"
    ],
    "wof:name":"Broward Machinery & Supply Inc",
    "wof:placetype":"venue"
},
  "geometry": {"coordinates":[-80.13784200000001,26.235693],"type":"Point"}
}