{
  "type": "Feature",
  "properties": {
    "addr:full":"1640 SW 61st Ave North Lauderdale FL 33068",
    "addr:housenumber":"1640",
    "addr:postcode":"33068",
    "addr:street":"Sw 61St Ave",
    "iso:country":"US",
    "sg:address":"1640 SW 61st Ave",
    "sg:city":"North Lauderdale",
    "sg:classifiers":[
        {
            "category":"Organizations",
            "subcategory":"Religious Organization",
            "type":"Services"
        }
    ],
    "sg:phone":"+1 954 972 2603",
    "sg:postcode":"33068",
    "sg:province":"FL",
    "sg:tags":[
        "church"
    ],
    "sg:website":"www.broadviewbaptistchurch.org",
    "wof:name":"Broadview Baptist Church",
    "wof:placetype":"venue"
},
  "geometry": {"coordinates":[-80.205394,26.20571],"type":"Point"}
}