{
  "type": "Feature",
  "properties": {
    "iso:country":"US",
    "sg:address":"2403 NW 47 Ter",
    "sg:city":"Gainesville",
    "sg:classifiers":[
        {
            "category":"Building & Trades",
            "subcategory":"Construction",
            "type":"Services"
        }
    ],
    "sg:phone":"+1 352 372 9705",
    "sg:postcode":"32606",
    "sg:province":"FL",
    "sg:tags":[
        "water",
        "well",
        "drilling"
    ],
    "wof:name":"Clark Well Drilling Inc",
    "wof:placetype":"venue"
},
  "geometry": {"coordinates":[-82.393601,29.6752],"type":"Point"}
}