{
  "type": "Feature",
  "properties": {
    "iso:country":"US",
    "sg:address":"25 S Magnolia Ave",
    "sg:city":"Orlando",
    "sg:classifiers":[
        {
            "category":"Professional",
            "subcategory":"Business Services",
            "type":"Services"
        }
    ],
    "sg:phone":"+1 407 649 2069",
    "sg:postcode":"32801",
    "sg:province":"FL",
    "sg:tags":[
        "translator",
        "interpreter"
    ],
    "sg:website":"www.lasch.com",
    "wof:name":"Lasch International Inc",
    "wof:placetype":"venue"
},
  "geometry": {"coordinates":[-81.37738,28.541526],"type":"Point"}
}