{
  "type": "Feature",
  "properties": {
    "iso:country":"US",
    "sg:address":"1118 S Florida Ave",
    "sg:city":"Lakeland",
    "sg:classifiers":[
        {
            "category":"Personal",
            "type":"Services"
        }
    ],
    "sg:phone":"+1 863 802 4960",
    "sg:postcode":"33803",
    "sg:province":"FL",
    "sg:tags":[
        "therapist",
        "massage"
    ],
    "wof:name":"Soothing Effects Massage Clnc",
    "wof:placetype":"venue"
},
  "geometry": {"coordinates":[-81.95704000000001,28.029419],"type":"Point"}
}