{
  "type": "Feature",
  "properties": {
    "iso:country":"US",
    "sg:address":"635 Collins Avenue",
    "sg:city":"Miami Beach",
    "sg:classifiers":[
        {
            "category":"Travel",
            "subcategory":"Hotels & Motels",
            "type":"Entertainment"
        }
    ],
    "sg:phone":"+1 305 672 0009",
    "sg:postcode":"33139",
    "sg:province":"FL",
    "sg:website":"www.metropolesouthbeach.com",
    "wof:name":"Metropole South Beach Hotel",
    "wof:placetype":"venue"
},
  "geometry": {"coordinates":[-80.132351,25.776156],"type":"Point"}
}