{
  "type": "Feature",
  "properties": {
    "addr:full":"5225 4th St N St Petersburg FL 33703",
    "addr:housenumber":"5225",
    "addr:postcode":"33703",
    "addr:street":"4Th St N",
    "iso:country":"US",
    "sg:address":"5225 4th St N",
    "sg:city":"St Petersburg",
    "sg:classifiers":[
        {
            "category":"Personal",
            "subcategory":"Beauty Salon",
            "type":"Services"
        }
    ],
    "sg:phone":"+1 727 521 1853",
    "sg:postcode":"33703",
    "sg:province":"FL",
    "sg:tags":[
        "shop",
        "manicuring"
    ],
    "wof:name":"Hong Kong Nails",
    "wof:placetype":"venue"
},
  "geometry": {"coordinates":[-82.638603,27.820078],"type":"Point"}
}