{
  "type": "Feature",
  "properties": {
    "addr:full":"20 W 4th St Atlantic Beach FL 32233",
    "addr:housenumber":"20",
    "addr:postcode":"32233",
    "addr:street":"W 4Th St",
    "iso:country":"US",
    "sg:address":"20 W 4th St",
    "sg:city":"Atlantic Beach",
    "sg:classifiers":[
        {
            "category":"Health Services",
            "subcategory":"Clinic",
            "type":"Services"
        }
    ],
    "sg:phone":"+1 904 355 6947",
    "sg:postcode":"32233",
    "sg:province":"FL",
    "sg:tags":[
        "specialty",
        "outpatient"
    ],
    "wof:name":"Alcoholic Service Center Inc",
    "wof:placetype":"venue"
},
  "geometry": {"coordinates":[-81.420023,30.328356],"type":"Point"}
}