{
  "type": "Feature",
  "properties": {
    "iso:country":"US",
    "sg:address":"15438 N Florida Ave",
    "sg:city":"Tampa",
    "sg:classifiers":[
        {
            "category":"Organizations",
            "subcategory":"Professional Association",
            "type":"Services"
        }
    ],
    "sg:phone":"+1 813 962 4448",
    "sg:postcode":"33613",
    "sg:province":"FL",
    "sg:tags":[
        "business"
    ],
    "wof:name":"American Lung Assn Gulfcoast F",
    "wof:placetype":"venue"
},
  "geometry": {"coordinates":[-82.461089,28.094769],"type":"Point"}
}