{
  "type": "Feature",
  "properties": {
    "iso:country":"US",
    "sg:address":"15293 Amberly Dr",
    "sg:city":"Tampa",
    "sg:classifiers":[
        {
            "category":"Health Services",
            "subcategory":"Doctor",
            "type":"Services"
        }
    ],
    "sg:phone":"+1 813 631 1100",
    "sg:postcode":"33647",
    "sg:province":"FL",
    "sg:tags":[
        "dentist"
    ],
    "wof:name":"Paul Duga DDS PA",
    "wof:placetype":"venue"
},
  "geometry": {"coordinates":[-82.40391200000001,28.096303],"type":"Point"}
}