{
  "type": "Feature",
  "properties": {
    "addr:full":"3455 Broken Woods Dr Pompano Beach FL 33065",
    "addr:housenumber":"3455",
    "addr:postcode":"33065",
    "addr:street":"Broken Woods Dr",
    "iso:country":"US",
    "sg:address":"3455 Broken Woods Dr",
    "sg:city":"Pompano Beach",
    "sg:classifiers":[
        {
            "category":"Professional",
            "subcategory":"Detective & Security Services",
            "type":"Services"
        }
    ],
    "sg:phone":"+1 954 752 8414",
    "sg:postcode":"33065",
    "sg:province":"FL",
    "sg:tags":[
        "car"
    ],
    "wof:name":"Bmr Investigators of Florida",
    "wof:placetype":"venue"
},
  "geometry": {"coordinates":[-80.248577,26.27366],"type":"Point"}
}