{
  "type": "Feature",
  "properties": {
    "addr:full":"220 N Sykes Creek Pkwy Ste 300 Merritt Island FL 32953",
    "addr:housenumber":"220",
    "addr:postcode":"32953",
    "addr:street":"N Sykes Creek Pkwy Ste 300",
    "iso:country":"US",
    "sg:address":"220 N Sykes Creek Pkwy Ste 300",
    "sg:city":"Merritt Island",
    "sg:classifiers":[
        {
            "category":"Health Services",
            "subcategory":"Health Practitioner",
            "type":"Services"
        }
    ],
    "sg:phone":"+1 321 459 0303",
    "sg:postcode":"32953",
    "sg:province":"FL",
    "sg:tags":[
        "therapy",
        "physical"
    ],
    "sg:website":"www.selectphysicaltherapy.com",
    "wof:name":"Select Physical Therapy",
    "wof:placetype":"venue"
},
  "geometry": {"coordinates":[-80.684141,28.359968],"type":"Point"}
}