{
  "type": "Feature",
  "properties": {
    "addr:full":"1756 Talmadge St De Land FL 32724",
    "addr:housenumber":"1756",
    "addr:postcode":"32724",
    "addr:street":"Talmadge St;Land",
    "iso:country":"US",
    "sg:address":"1756 Talmadge St",
    "sg:city":"De Land",
    "sg:classifiers":[
        {
            "category":"Organizations",
            "subcategory":"Community Association",
            "type":"Services"
        }
    ],
    "sg:phone":"+1 386 738 5952",
    "sg:postcode":"32724",
    "sg:province":"FL",
    "wof:name":"Mega Star Wars",
    "wof:placetype":"venue"
},
  "geometry": {"coordinates":[-81.26388799999999,29.066508],"type":"Point"}
}