{
  "type": "Feature",
  "properties": {
    "addr:full":"20401 NE 30th Ave Miami FL 33180",
    "addr:housenumber":"20401",
    "addr:postcode":"33180",
    "addr:street":"Ne 30Th Ave",
    "iso:country":"US",
    "sg:address":"20401 NE 30th Ave",
    "sg:city":"Miami",
    "sg:classifiers":[
        {
            "category":"Wholesale",
            "subcategory":"Apparel",
            "type":"Manufacturing & Wholesale Goods"
        }
    ],
    "sg:phone":"+1 305 932 6602",
    "sg:postcode":"33180",
    "sg:province":"FL",
    "sg:tags":[
        "commodity",
        "general"
    ],
    "wof:name":"M&J International Trading",
    "wof:placetype":"venue"
},
  "geometry": {"coordinates":[-80.141373,25.964155],"type":"Point"}
}