{
  "type": "Feature",
  "properties": {
    "iso:country":"US",
    "sg:address":"5122 Commercial Way",
    "sg:city":"Spring Hill",
    "sg:classifiers":[
        {
            "category":"Insurance",
            "subcategory":"Insurance Agent",
            "type":"Services"
        }
    ],
    "sg:phone":"+1 352 596 8186",
    "sg:postcode":"34606",
    "sg:province":"FL",
    "sg:tags":[
        "accident"
    ],
    "wof:name":"Quality Health Plans Inc",
    "wof:placetype":"venue"
},
  "geometry": {"coordinates":[-82.585117,28.505909],"type":"Point"}
}