{
  "type": "Feature",
  "properties": {
    "addr:full":"20268 NE 15th Ct Miami FL 33179",
    "addr:housenumber":"20268",
    "addr:postcode":"33179",
    "addr:street":"Ne 15Th Ct",
    "iso:country":"US",
    "sg:address":"20268 NE 15th Ct",
    "sg:city":"Miami",
    "sg:classifiers":[
        {
            "category":"Building & Trades",
            "subcategory":"Construction",
            "type":"Services"
        }
    ],
    "sg:phone":"+1 305 651 9660",
    "sg:postcode":"33179",
    "sg:province":"FL",
    "sg:tags":[
        "fire",
        "repair",
        "damage",
        "for",
        "house"
    ],
    "wof:name":"South Florida Restoration Inc",
    "wof:placetype":"venue"
},
  "geometry": {"coordinates":[-80.171104,25.960944],"type":"Point"}
}