{
  "type": "Feature",
  "properties": {
    "iso:country":"US",
    "sg:address":"15100 NW 67th Ave Suite 103",
    "sg:city":"Hialeah",
    "sg:classifiers":[
        {
            "category":"Insurance",
            "subcategory":"Hazard Insurance",
            "type":"Services"
        },
        {
            "category":"Insurance",
            "subcategory":"Insurance Agent",
            "type":"Services"
        },
        {
            "category":"Insurance",
            "subcategory":"Life Insurance",
            "type":"Services"
        }
    ],
    "sg:phone":"+1 305 424 9531",
    "sg:postcode":"33014",
    "sg:province":"FL",
    "sg:tags":[
        "auto"
    ],
    "sg:website":"http://statefarm.mqgroup.com/url.asp?usr=592643",
    "wof:name":"Ruben Sanchez Ins Agency Inc - State Farm Insurance Agent",
    "wof:placetype":"venue"
},
  "geometry": {"coordinates":[-80.30843900000001,25.909338],"type":"Point"}
}