{
  "type": "Feature",
  "properties": {
    "iso:country":"US",
    "sg:address":"2416 Vindale Rd",
    "sg:city":"Tavares",
    "sg:classifiers":[
        {
            "category":"Professional",
            "type":"Services"
        }
    ],
    "sg:phone":"+1 352 742 2682",
    "sg:postcode":"32778",
    "sg:province":"FL",
    "wof:name":"Pearl Hatmaker",
    "wof:placetype":"venue"
},
  "geometry": {"coordinates":[-81.753152,28.812791],"type":"Point"}
}