{
  "type": "Feature",
  "properties": {
    "addr:full":"8819 78th Pl Seminole FL 33777",
    "addr:housenumber":"8819",
    "addr:postcode":"33777",
    "addr:street":"78Th Pl",
    "iso:country":"US",
    "sg:address":"8819 78th Pl",
    "sg:city":"Seminole",
    "sg:classifiers":[
        {
            "category":"Retail",
            "subcategory":"Laundry & Dry Cleaning",
            "type":"Services"
        }
    ],
    "sg:phone":"+1 727 391 6694",
    "sg:postcode":"33777",
    "sg:province":"FL",
    "sg:tags":[
        "cleaner",
        "rug",
        "carpet"
    ],
    "wof:name":"Premium Carpet Cleaning",
    "wof:placetype":"venue"
},
  "geometry": {"coordinates":[-82.76173799999999,27.843748],"type":"Point"}
}