{
  "type": "Feature",
  "properties": {
    "iso:country":"US",
    "sg:address":"5931 NW 173rd Dr Unit 10",
    "sg:city":"Hialeah",
    "sg:classifiers":[
        {
            "category":"Health Services",
            "subcategory":"Clinic",
            "type":"Services"
        },
        {
            "category":"Communications",
            "type":"Services"
        },
        {
            "category":"Social Services",
            "subcategory":"Retirement Home",
            "type":"Services"
        }
    ],
    "sg:phone":"+1 305 826 7884",
    "sg:postcode":"33015",
    "sg:province":"FL",
    "sg:tags":[
        "pathologist",
        "speech-language",
        "convalescent",
        "nursing",
        "rehabilitation"
    ],
    "wof:name":"Integrated Rehabilitation Center",
    "wof:placetype":"venue"
},
  "geometry": {"coordinates":[-80.29838700000001,25.930587],"type":"Point"}
}