{
  "type": "Feature",
  "properties": {
    "iso:country":"US",
    "sg:address":"9000 SW 87th Ct",
    "sg:city":"Miami",
    "sg:classifiers":[
        {
            "category":"Real Estate",
            "subcategory":"Real Estate Agent",
            "type":"Services"
        }
    ],
    "sg:phone":"+1 305 598 6611",
    "sg:postcode":"33176",
    "sg:province":"FL",
    "wof:name":"Dolphin Properties Inc",
    "wof:placetype":"venue"
},
  "geometry": {"coordinates":[-80.335611,25.685567],"type":"Point"}
}