{
  "type": "Feature",
  "properties": {
    "addr:full":"811 E Call St Tallahassee FL 32301",
    "addr:housenumber":"811",
    "addr:postcode":"32301",
    "addr:street":"E Call St",
    "iso:country":"US",
    "sg:address":"811 E Call St",
    "sg:city":"Tallahassee",
    "sg:classifiers":[
        {
            "category":"Professional",
            "subcategory":"Management & Consulting",
            "type":"Services"
        }
    ],
    "sg:phone":"+1 850 681 8535",
    "sg:postcode":"32301",
    "sg:province":"FL",
    "sg:tags":[
        "counselor",
        "public",
        "relations"
    ],
    "wof:name":"Stephen D Hull Inc",
    "wof:placetype":"venue"
},
  "geometry": {"coordinates":[-84.267471,30.443482],"type":"Point"}
}