{
  "type": "Feature",
  "properties": {
    "iso:country":"US",
    "sg:address":"6567 Talbot Cir",
    "sg:city":"Spring Hill",
    "sg:classifiers":[
        {
            "category":"Shopping",
            "type":"Retail Goods"
        }
    ],
    "sg:phone":"+1 352 683 3666",
    "sg:postcode":"34606",
    "sg:province":"FL",
    "sg:tags":[
        "art",
        "gallery",
        "dealer"
    ],
    "wof:name":"Minds Creation",
    "wof:placetype":"venue"
},
  "geometry": {"coordinates":[-82.609708,28.449303],"type":"Point"}
}