{
  "type": "Feature",
  "properties": {
    "iso:country":"US",
    "sg:address":"883 SW 29th St",
    "sg:city":"Palm City",
    "sg:classifiers":[
        {
            "category":"Travel",
            "subcategory":"Travel Agent",
            "type":"Entertainment"
        }
    ],
    "sg:phone":"+1 772 283 4600",
    "sg:postcode":"34990",
    "sg:province":"FL",
    "sg:tags":[
        "agency",
        "bureau"
    ],
    "wof:name":"Travel Plus",
    "wof:placetype":"venue"
},
  "geometry": {"coordinates":[-80.267538,27.169935],"type":"Point"}
}