{
  "type": "Feature",
  "properties": {
    "iso:country":"US",
    "sg:address":"120 W Main St",
    "sg:city":"Lake Butler",
    "sg:classifiers":[
        {
            "category":"Retail",
            "subcategory":"Auto Repair",
            "type":"Services"
        }
    ],
    "sg:phone":"+1 386 496 3001",
    "sg:postcode":"32054",
    "sg:province":"FL",
    "sg:tags":[
        "wrecker",
        "general"
    ],
    "wof:name":"Welch's Service",
    "wof:placetype":"venue"
},
  "geometry": {"coordinates":[-82.33911500000001,30.023036],"type":"Point"}
}