{
  "type": "Feature",
  "properties": {
    "iso:country":"US",
    "sg:address":"80 S Orlando Ave",
    "sg:city":"Cocoa Beach",
    "sg:classifiers":[
        {
            "category":"Arts & Performance",
            "subcategory":"Art Gallery",
            "type":"Entertainment"
        }
    ],
    "sg:phone":"+1 321 783 7430",
    "sg:postcode":"32931",
    "sg:province":"FL",
    "wof:name":"Brigantine Gallery Florists",
    "wof:placetype":"venue"
},
  "geometry": {"coordinates":[-80.61019899999999,28.3167],"type":"Point"}
}