{
  "type": "Feature",
  "properties": {
    "iso:country":"US",
    "sg:address":"489 Bayfront Pl",
    "sg:city":"Naples",
    "sg:classifiers":[
        {
            "category":"Restaurant",
            "type":"Food & Drink"
        }
    ],
    "sg:phone":"+1 239 434 8888",
    "sg:postcode":"34102",
    "sg:province":"FL",
    "sg:tags":[
        "american",
        "seafood"
    ],
    "wof:name":"Gordon's Waterfront Grill",
    "wof:placetype":"venue"
},
  "geometry": {"coordinates":[-81.789085,26.143131],"type":"Point"}
}