{
  "type": "Feature",
  "properties": {
    "iso:country":"US",
    "sg:address":"2721 SE 174th Pl",
    "sg:city":"Summerfield",
    "sg:classifiers":[
        {
            "category":"Shopping",
            "subcategory":"Clothing, Apparel, & Fashions",
            "type":"Retail Goods"
        }
    ],
    "sg:phone":"+1 352 804 3313",
    "sg:postcode":"34491",
    "sg:province":"FL",
    "sg:tags":[
        "family"
    ],
    "wof:name":"Rafael G Obeso",
    "wof:placetype":"venue"
},
  "geometry": {"coordinates":[-82.099217,28.968372],"type":"Point"}
}