{
  "type": "Feature",
  "properties": {
    "addr:full":"1194 Hawthorne Cove Dr Winter Garden FL 34761",
    "addr:housenumber":"1194",
    "addr:postcode":"34761",
    "addr:street":"Hawthorne Cove Dr",
    "iso:country":"US",
    "sg:address":"1194 Hawthorne Cove Dr",
    "sg:city":"Winter Garden",
    "sg:classifiers":[
        {
            "category":"Professional",
            "type":"Services"
        }
    ],
    "sg:phone":"+1 407 905 9355",
    "sg:postcode":"34761",
    "sg:province":"FL",
    "sg:tags":[
        "establishment"
    ],
    "wof:name":"Circle Of Life",
    "wof:placetype":"venue"
},
  "geometry": {"coordinates":[-81.52452700000001,28.572987],"type":"Point"}
}