{
  "type": "Feature",
  "properties": {
    "addr:full":"1240 W 13th St Jacksonville FL 32209",
    "addr:housenumber":"1240",
    "addr:postcode":"32209",
    "addr:street":"W 13Th St",
    "iso:country":"US",
    "sg:address":"1240 W 13th St",
    "sg:city":"Jacksonville",
    "sg:classifiers":[
        {
            "category":"Professional",
            "type":"Services"
        }
    ],
    "sg:phone":"+1 904 768 9300",
    "sg:postcode":"32209",
    "sg:province":"FL",
    "wof:name":"Sac Corporation Jacksonville",
    "wof:placetype":"venue"
},
  "geometry": {"coordinates":[-81.675528,30.351312],"type":"Point"}
}