{
  "type": "Feature",
  "properties": {
    "addr:full":"4580 Northgate Ct Sarasota FL 34234",
    "addr:housenumber":"4580",
    "addr:postcode":"34234",
    "addr:street":"Northgate Ct",
    "iso:country":"US",
    "sg:address":"4580 Northgate Ct",
    "sg:city":"Sarasota",
    "sg:classifiers":[
        {
            "category":"Professional",
            "subcategory":"Management & Consulting",
            "type":"Services"
        }
    ],
    "sg:phone":"+1 941 359 0855",
    "sg:postcode":"34234",
    "sg:province":"FL",
    "sg:tags":[
        "business"
    ],
    "wof:name":"Hollins Tom Auction Company",
    "wof:placetype":"venue"
},
  "geometry": {"coordinates":[-82.533737,27.37245],"type":"Point"}
}