{
  "type": "Feature",
  "properties": {
    "iso:country":"US",
    "sg:address":"2699 Lee Rd",
    "sg:city":"Winter Park",
    "sg:classifiers":[
        {
            "category":"Professional",
            "subcategory":"Employment Agencies",
            "type":"Services"
        }
    ],
    "sg:phone":"+1 407 647 6478",
    "sg:postcode":"32789",
    "sg:province":"FL",
    "sg:tags":[
        "medical",
        "help"
    ],
    "wof:name":"Orlando Staffing",
    "wof:placetype":"venue"
},
  "geometry": {"coordinates":[-81.384176,28.6058],"type":"Point"}
}