{
  "type": "Feature",
  "properties": {
    "iso:country":"US",
    "sg:address":"2060 1st Ave N",
    "sg:city":"St Petersburg",
    "sg:classifiers":[
        {
            "category":"Communications",
            "subcategory":"Radio Station",
            "type":"Services"
        }
    ],
    "sg:phone":"+1 727 327 9792",
    "sg:postcode":"33713",
    "sg:province":"FL",
    "sg:tags":[
        "company",
        "broadcasting"
    ],
    "wof:name":"WRXB",
    "wof:placetype":"venue"
},
  "geometry": {"coordinates":[-82.660905,27.771893],"type":"Point"}
}