{
  "type": "Feature",
  "properties": {
    "iso:country":"US",
    "sg:address":"9588 NW 41st St",
    "sg:city":"Miami",
    "sg:classifiers":[
        {
            "category":"Home & Garden",
            "subcategory":"Hardware",
            "type":"Retail Goods"
        }
    ],
    "sg:phone":"+1 305 718 4595",
    "sg:postcode":"33178",
    "sg:province":"FL",
    "wof:name":"Ace Hardware",
    "wof:placetype":"venue"
},
  "geometry": {"coordinates":[-80.35257799999999,25.811582],"type":"Point"}
}