{
  "type": "Feature",
  "properties": {
    "iso:country":"US",
    "sg:address":"718 Westwood Dr",
    "sg:city":"Brandon",
    "sg:classifiers":[
        {
            "category":"Retail",
            "subcategory":"Auto Repair",
            "type":"Services"
        }
    ],
    "sg:phone":"+1 813 681 1649",
    "sg:postcode":"33511",
    "sg:province":"FL",
    "sg:tags":[
        "body",
        "painting",
        "repairing",
        "automobile"
    ],
    "wof:name":"Kim Inc",
    "wof:placetype":"venue"
},
  "geometry": {"coordinates":[-82.294624,27.930031],"type":"Point"}
}