{
  "type": "Feature",
  "properties": {
    "iso:country":"US",
    "sg:address":"8700 E Colonial Dr",
    "sg:city":"Orlando",
    "sg:classifiers":[
        {
            "category":"Food & Beverages",
            "subcategory":"Groceries & Convenience Stores",
            "type":"Retail Goods"
        }
    ],
    "sg:phone":"+1 407 273 7086",
    "sg:postcode":"32817",
    "sg:province":"FL",
    "wof:name":"KWIK Stop Store",
    "wof:placetype":"venue"
},
  "geometry": {"coordinates":[-81.267793,28.568371],"type":"Point"}
}