{
  "type": "Feature",
  "properties": {
    "iso:country":"US",
    "sg:address":"11970 NW 12th St",
    "sg:city":"Pembroke Pines",
    "sg:classifiers":[
        {
            "category":"Building & Trades",
            "subcategory":"Pest Control",
            "type":"Services"
        }
    ],
    "sg:phone":"+1 954 435 5917",
    "sg:postcode":"33026",
    "sg:province":"FL",
    "wof:name":"Statewide Pest Control Inc",
    "wof:placetype":"venue"
},
  "geometry": {"coordinates":[-80.307345,26.01585],"type":"Point"}
}