{
  "type": "Feature",
  "properties": {
    "iso:country":"US",
    "sg:address":"1325 W Broadway St",
    "sg:city":"Oviedo",
    "sg:classifiers":[
        {
            "category":"Personal",
            "subcategory":"Beauty Salon",
            "type":"Services"
        },
        {
            "category":"Personal",
            "subcategory":"Barber",
            "type":"Services"
        }
    ],
    "sg:phone":"+1 407 365 2832",
    "sg:postcode":"32765",
    "sg:province":"FL",
    "sg:tags":[
        "shop"
    ],
    "wof:name":"Venci's Barber Shop",
    "wof:placetype":"venue"
},
  "geometry": {"coordinates":[-81.224531,28.664367],"type":"Point"}
}