{
  "type": "Feature",
  "properties": {
    "iso:country":"US",
    "sg:address":"3523 Reid St",
    "sg:city":"Palatka",
    "sg:classifiers":[
        {
            "category":"Autos & Motor Vehicles",
            "subcategory":"Automobile Sales",
            "type":"Retail Goods"
        }
    ],
    "sg:phone":"+1 386 326 9069",
    "sg:postcode":"32177",
    "sg:province":"FL",
    "sg:tags":[
        "car",
        "dealer"
    ],
    "sg:website":"www.a1usedcarsinc.com",
    "wof:name":"Used Cars Inc",
    "wof:placetype":"venue"
},
  "geometry": {"coordinates":[-81.666287,29.657391],"type":"Point"}
}