{
  "type": "Feature",
  "properties": {
    "iso:country":"US",
    "sg:address":"6700 SW 92nd St",
    "sg:city":"Miami",
    "sg:classifiers":[
        {
            "category":"Real Estate",
            "subcategory":"Real Estate Agent",
            "type":"Services"
        }
    ],
    "sg:phone":"+1 305 595 2855",
    "sg:postcode":"33156",
    "sg:province":"FL",
    "wof:name":"Acropolis Realty LLC",
    "wof:placetype":"venue"
},
  "geometry": {"coordinates":[-80.305013,25.685304],"type":"Point"}
}