{
  "type": "Feature",
  "properties": {
    "iso:country":"US",
    "sg:address":"790 Harbour Dr",
    "sg:city":"Naples",
    "sg:classifiers":[
        {
            "category":"Professional",
            "subcategory":"Accounting & Tax Preparation",
            "type":"Services"
        }
    ],
    "sg:phone":"+1 239 263 5010",
    "sg:postcode":"34103",
    "sg:province":"FL",
    "sg:tags":[
        "accountant"
    ],
    "wof:name":"Hayes & Galati PA CPA",
    "wof:placetype":"venue"
},
  "geometry": {"coordinates":[-81.801748,26.180376],"type":"Point"}
}