{
  "type": "Feature",
  "properties": {
    "iso:country":"US",
    "sg:address":"7786 W Sand Lake Rd",
    "sg:city":"Orlando",
    "sg:classifiers":[
        {
            "category":"Restaurant",
            "type":"Food & Drink"
        }
    ],
    "sg:menulink":"http://www.allmenus.com/fl/southwest-orange/276980-amura-japanese-restaurant/menu/",
    "sg:phone":"+1 407 370 0007",
    "sg:postcode":"32819",
    "sg:province":"FL",
    "sg:tags":[
        "japanese",
        "asian"
    ],
    "wof:name":"Amura Japanese Restaurant",
    "wof:placetype":"venue"
},
  "geometry": {"coordinates":[-81.48908,28.449852],"type":"Point"}
}