{
  "type": "Feature",
  "properties": {
    "addr:full":"1435 NW 3rd Ave Miami FL 33136",
    "addr:housenumber":"1435",
    "addr:postcode":"33136",
    "addr:street":"Nw 3Rd Ave",
    "iso:country":"US",
    "sg:address":"1435 NW 3rd Ave",
    "sg:city":"Miami",
    "sg:classifiers":[
        {
            "category":"Recreation",
            "subcategory":"Arcade",
            "type":"Entertainment"
        }
    ],
    "sg:phone":"+1 305 442 1007",
    "sg:postcode":"33136",
    "sg:province":"FL",
    "sg:tags":[
        "device",
        "operator",
        "amusement"
    ],
    "wof:name":"Fun Land USA Corp",
    "wof:placetype":"venue"
},
  "geometry": {"coordinates":[-80.19989700000001,25.789464],"type":"Point"}
}