{
  "type": "Feature",
  "properties": {
    "iso:country":"US",
    "sg:address":"336 Bob McCaskill Dr",
    "sg:city":"De Funiak Springs",
    "sg:classifiers":[
        {
            "category":"Building & Trades",
            "subcategory":"Construction",
            "type":"Services"
        }
    ],
    "sg:phone":"+1 850 892 6629",
    "sg:postcode":"32433",
    "sg:province":"FL",
    "sg:tags":[
        "house"
    ],
    "wof:name":"Wilson Homes of Seagrove Inc",
    "wof:placetype":"venue"
},
  "geometry": {"coordinates":[-86.14483799999999,30.758858],"type":"Point"}
}