{
  "type": "Feature",
  "properties": {
    "addr:full":"502 E 2nd Ave Crestview FL 32536",
    "addr:housenumber":"502",
    "addr:postcode":"32536",
    "addr:street":"E 2Nd Ave",
    "iso:country":"US",
    "sg:address":"502 E 2nd Ave",
    "sg:city":"Crestview",
    "sg:classifiers":[
        {
            "category":"Building & Trades",
            "subcategory":"Construction",
            "type":"Services"
        }
    ],
    "sg:phone":"+1 850 682 3793",
    "sg:postcode":"32536",
    "sg:province":"FL",
    "sg:tags":[
        "contractor"
    ],
    "wof:name":"Superior Exteriors",
    "wof:placetype":"venue"
},
  "geometry": {"coordinates":[-86.56867800000001,30.766806],"type":"Point"}
}