{
  "type": "Feature",
  "properties": {
    "iso:country":"US",
    "sg:address":"218 Ash St",
    "sg:city":"Fernandina Beach",
    "sg:classifiers":[
        {
            "category":"Shopping",
            "type":"Retail Goods"
        }
    ],
    "sg:phone":"+1 904 277 1147",
    "sg:postcode":"32034",
    "sg:province":"FL",
    "sg:tags":[
        "art",
        "gallery",
        "dealer"
    ],
    "wof:name":"Susan's Slightly Off Centre",
    "wof:placetype":"venue"
},
  "geometry": {"coordinates":[-81.463943,30.669943],"type":"Point"}
}