{
  "type": "Feature",
  "properties": {
    "addr:full":"7360 Coral Way Ste 29 Miami FL 33155",
    "addr:housenumber":"7360",
    "addr:postcode":"33155",
    "addr:street":"Coral Way Ste 29",
    "iso:country":"US",
    "sg:address":"7360 Coral Way Ste 29",
    "sg:city":"Miami",
    "sg:classifiers":[
        {
            "category":"Education",
            "subcategory":"School",
            "type":"Public Place"
        }
    ],
    "sg:phone":"+1 305 261 0742",
    "sg:postcode":"33155",
    "sg:province":"FL",
    "wof:name":"International Institute of Fine Arts",
    "wof:placetype":"venue"
},
  "geometry": {"coordinates":[-80.314729,25.747863],"type":"Point"}
}