{
  "type": "Feature",
  "properties": {
    "iso:country":"US",
    "sg:address":"3505 Schooner Dr",
    "sg:city":"Parrish",
    "sg:classifiers":[
        {
            "category":"Real Estate",
            "subcategory":"Real Estate Operator",
            "type":"Services"
        }
    ],
    "sg:phone":"+1 941 776 0098",
    "sg:postcode":"34219",
    "sg:province":"FL",
    "sg:tags":[
        "mobile",
        "home",
        "site"
    ],
    "wof:name":"Sandy Vollmer Inc",
    "wof:placetype":"venue"
},
  "geometry": {"coordinates":[-82.462801,27.543178],"type":"Point"}
}