{
  "type": "Feature",
  "properties": {
    "iso:country":"US",
    "sg:address":"2109 Tuscarora Trl",
    "sg:city":"Maitland",
    "sg:classifiers":[
        {
            "category":"Mining & Drilling",
            "type":"Manufacturing & Wholesale Goods"
        }
    ],
    "sg:phone":"+1 407 644 4666",
    "sg:postcode":"32751",
    "sg:province":"FL",
    "sg:tags":[
        "development",
        "gas",
        "oil",
        "exploration"
    ],
    "wof:name":"FORB Corp",
    "wof:placetype":"venue"
},
  "geometry": {"coordinates":[-81.33586099999999,28.633156],"type":"Point"}
}