{
  "type": "Feature",
  "properties": {
    "iso:country":"US",
    "sg:address":"5104 N Orange Blossom Trl",
    "sg:city":"Orlando",
    "sg:classifiers":[
        {
            "category":"Organizations",
            "subcategory":"Professional Association",
            "type":"Services"
        }
    ],
    "sg:phone":"+1 407 291 9415",
    "sg:postcode":"32810",
    "sg:province":"FL",
    "wof:name":"Florida Turfgrass Assn",
    "wof:placetype":"venue"
},
  "geometry": {"coordinates":[-81.42148299999999,28.605373],"type":"Point"}
}