{
  "type": "Feature",
  "properties": {
    "iso:country":"US",
    "sg:address":"4790 SW 72nd Ave.",
    "sg:city":"Miami",
    "sg:classifiers":[
        {
            "category":"Shopping",
            "subcategory":"Clothing, Apparel, & Fashions",
            "type":"Retail Goods"
        }
    ],
    "sg:phone":"+1 305 282 4749",
    "sg:postcode":"33155",
    "sg:province":"FL",
    "wof:name":"Eccentricity",
    "wof:placetype":"venue"
},
  "geometry": {"coordinates":[-80.310751,25.726036],"type":"Point"}
}