{
  "type": "Feature",
  "properties": {
    "iso:country":"US",
    "sg:address":"410 S John Sims Pkwy",
    "sg:city":"Valparaiso",
    "sg:classifiers":[
        {
            "category":"Retail",
            "subcategory":"Auto Repair",
            "type":"Services"
        }
    ],
    "sg:phone":"+1 850 678 1789",
    "sg:postcode":"32580",
    "sg:province":"FL",
    "sg:tags":[
        "automotive"
    ],
    "wof:name":"Quik Center Lube",
    "wof:placetype":"venue"
},
  "geometry": {"coordinates":[-86.49398100000001,30.497561],"type":"Point"}
}