{
  "type": "Feature",
  "properties": {
    "iso:country":"US",
    "sg:address":"104 W 5th Ave",
    "sg:city":"Tallahassee",
    "sg:classifiers":[
        {
            "category":"Professional",
            "subcategory":"Detective & Security Services",
            "type":"Services"
        }
    ],
    "sg:phone":"+1 850 562 2530",
    "sg:postcode":"32303",
    "sg:province":"FL",
    "sg:tags":[
        "private",
        "investigator"
    ],
    "wof:name":"Investgations Info Specialists",
    "wof:placetype":"venue"
},
  "geometry": {"coordinates":[-84.28194000000001,30.45471],"type":"Point"}
}