{
  "type": "Feature",
  "properties": {
    "iso:country":"US",
    "sg:address":"71 Azure Pl",
    "sg:city":"Destin",
    "sg:classifiers":[
        {
            "category":"Real Estate",
            "subcategory":"Real Estate Operator",
            "type":"Services"
        }
    ],
    "sg:phone":"+1 850 654 1911",
    "sg:postcode":"32550",
    "sg:province":"FL",
    "sg:tags":[
        "building",
        "nonresidential"
    ],
    "wof:name":"R & K Properties LLC",
    "wof:placetype":"venue"
},
  "geometry": {"coordinates":[-86.395049,30.388931],"type":"Point"}
}