{
  "type": "Feature",
  "properties": {
    "addr:full":"635 N 12th St Tampa FL 33602",
    "addr:housenumber":"635",
    "addr:postcode":"33602",
    "addr:street":"N 12Th St",
    "iso:country":"US",
    "sg:address":"635 N 12th St",
    "sg:city":"Tampa",
    "sg:classifiers":[
        {
            "category":"Wholesale",
            "subcategory":"Electrical",
            "type":"Manufacturing & Wholesale Goods"
        }
    ],
    "sg:phone":"+1 813 229 9486",
    "sg:postcode":"33602",
    "sg:province":"FL",
    "wof:name":"Professional Hermetics",
    "wof:placetype":"venue"
},
  "geometry": {"coordinates":[-82.446782,27.954615],"type":"Point"}
}