{
  "type": "Feature",
  "properties": {
    "iso:country":"US",
    "sg:address":"9483 Country Rd",
    "sg:city":"Brooksville",
    "sg:classifiers":[
        {
            "category":"Building & Trades",
            "subcategory":"Construction",
            "type":"Services"
        }
    ],
    "sg:phone":"+1 352 596 6078",
    "sg:postcode":"34613",
    "sg:province":"FL",
    "sg:tags":[
        "roofing",
        "contractor"
    ],
    "wof:name":"S & F Roofing Inc",
    "wof:placetype":"venue"
},
  "geometry": {"coordinates":[-82.56221600000001,28.537758],"type":"Point"}
}