{
  "type": "Feature",
  "properties": {
    "iso:country":"US",
    "sg:address":"7320 Lake Underhill Rd",
    "sg:city":"Orlando",
    "sg:classifiers":[
        {
            "category":"Wholesale",
            "subcategory":"Durable Goods & Equipment",
            "type":"Manufacturing & Wholesale Goods"
        }
    ],
    "sg:phone":"+1 407 207 5747",
    "sg:postcode":"32822",
    "sg:province":"FL",
    "sg:tags":[
        "exporter"
    ],
    "wof:name":"Glass America",
    "wof:placetype":"venue"
},
  "geometry": {"coordinates":[-81.28616599999999,28.539074],"type":"Point"}
}