{
  "type": "Feature",
  "properties": {
    "iso:country":"US",
    "sg:address":"705 27th Ave SW",
    "sg:city":"Vero Beach",
    "sg:classifiers":[
        {
            "category":"Professional",
            "subcategory":"Research",
            "type":"Services"
        }
    ],
    "sg:phone":"+1 772 770 0602",
    "sg:postcode":"32968",
    "sg:province":"FL",
    "sg:tags":[
        "chemical",
        "development"
    ],
    "wof:name":"Sea Ag Inc",
    "wof:placetype":"venue"
},
  "geometry": {"coordinates":[-80.41424499999999,27.590675],"type":"Point"}
}