{
  "type": "Feature",
  "properties": {
    "addr:full":"7825 SW 40th St Miami FL 33155",
    "addr:housenumber":"7825",
    "addr:postcode":"33155",
    "addr:street":"Sw 40Th St",
    "iso:country":"US",
    "sg:address":"7825 SW 40th St",
    "sg:city":"Miami",
    "sg:classifiers":[
        {
            "category":"Building & Trades",
            "subcategory":"Construction",
            "type":"Services"
        }
    ],
    "sg:phone":"+1 305 262 2456",
    "sg:postcode":"33155",
    "sg:province":"FL",
    "sg:tags":[
        "contractor"
    ],
    "wof:name":"Ceramic Tiles Gallery Inc",
    "wof:placetype":"venue"
},
  "geometry": {"coordinates":[-80.319616,25.733038],"type":"Point"}
}