{
  "type": "Feature",
  "properties": {
    "addr:full":"1857 SW Dreyfuss Blvd Port Saint Lucie FL 34953",
    "addr:housenumber":"1857",
    "addr:postcode":"34953",
    "addr:street":"Sw Dreyfuss Blvd",
    "iso:country":"US",
    "sg:address":"1857 SW Dreyfuss Blvd",
    "sg:city":"Port Saint Lucie",
    "sg:classifiers":[
        {
            "category":"Real Estate",
            "subcategory":"Real Estate Agent",
            "type":"Services"
        }
    ],
    "sg:phone":"+1 772 344 4747",
    "sg:postcode":"34953",
    "sg:province":"FL",
    "sg:tags":[
        "residential",
        "construction"
    ],
    "wof:name":"Smartwise Homes",
    "wof:placetype":"venue"
},
  "geometry": {"coordinates":[-80.40543700000001,27.248984],"type":"Point"}
}