{
  "type": "Feature",
  "properties": {
    "iso:country":"US",
    "sg:address":"3015 NW 79th St",
    "sg:city":"Miami",
    "sg:classifiers":[
        {
            "category":"Shopping Center",
            "type":"Public Place"
        }
    ],
    "sg:phone":"+1 305 836 3677",
    "sg:postcode":"33147",
    "sg:province":"FL",
    "sg:tags":[
        "flea",
        "market"
    ],
    "wof:name":"Flea Market USA",
    "wof:placetype":"venue"
},
  "geometry": {"coordinates":[-80.246126,25.84597],"type":"Point"}
}