{
  "type": "Feature",
  "properties": {
    "iso:country":"US",
    "sg:address":"17101 SW 79th Ct",
    "sg:city":"Palmetto Bay",
    "sg:classifiers":[
        {
            "category":"Professional",
            "type":"Services"
        }
    ],
    "sg:phone":"+1 305 232 8555",
    "sg:postcode":"33157",
    "sg:province":"FL",
    "sg:tags":[
        "establishment"
    ],
    "wof:name":"Sacks Group",
    "wof:placetype":"venue"
},
  "geometry": {"coordinates":[-80.320818,25.610515],"type":"Point"}
}