{
  "type": "Feature",
  "properties": {
    "iso:country":"US",
    "sg:address":"8802 NW 112th St",
    "sg:city":"Hialeah",
    "sg:classifiers":[
        {
            "category":"Manufacturing",
            "subcategory":"Metals",
            "type":"Manufacturing & Wholesale Goods"
        }
    ],
    "sg:phone":"+1 305 512 9558",
    "sg:postcode":"33018",
    "sg:province":"FL",
    "sg:tags":[
        "aluminum",
        "primary",
        "producer"
    ],
    "wof:name":"NFC Aluminum Inc",
    "wof:placetype":"venue"
},
  "geometry": {"coordinates":[-80.34328600000001,25.875121],"type":"Point"}
}