{
  "type": "Feature",
  "properties": {
    "addr:full":"10880 SW 4th St Miami FL 33174",
    "addr:housenumber":"10880",
    "addr:postcode":"33174",
    "addr:street":"Sw 4Th St",
    "iso:country":"US",
    "sg:address":"10880 SW 4th St",
    "sg:city":"Miami",
    "sg:classifiers":[
        {
            "category":"Autos & Motor Vehicles",
            "subcategory":"Auto Supplies",
            "type":"Retail Goods"
        }
    ],
    "sg:phone":"+1 305 274 6652",
    "sg:postcode":"33174",
    "sg:province":"FL",
    "sg:tags":[
        "tire"
    ],
    "wof:name":"R & R Firestone",
    "wof:placetype":"venue"
},
  "geometry": {"coordinates":[-80.37129899999999,25.764761],"type":"Point"}
}