{
  "type": "Feature",
  "properties": {
    "iso:country":"US",
    "sg:address":"2226 N Temple Ave",
    "sg:city":"Starke",
    "sg:classifiers":[
        {
            "category":"Wholesale",
            "subcategory":"Farm Supplies",
            "type":"Manufacturing & Wholesale Goods"
        }
    ],
    "sg:phone":"+1 904 964 7871",
    "sg:postcode":"32091",
    "sg:province":"FL",
    "wof:name":"Gold Key Farm & Western Store",
    "wof:placetype":"venue"
},
  "geometry": {"coordinates":[-82.10281999999999,29.96801],"type":"Point"}
}