{
  "type": "Feature",
  "properties": {
    "iso:country":"US",
    "sg:address":"4719 N Thatcher Ave",
    "sg:city":"Tampa",
    "sg:classifiers":[
        {
            "category":"Freight",
            "type":"Transportation"
        }
    ],
    "sg:phone":"+1 813 931 4411",
    "sg:postcode":"33614",
    "sg:province":"FL",
    "sg:tags":[
        "operator",
        "mover",
        "local",
        "special",
        "trucking"
    ],
    "wof:name":"Bayside Moving & Storage",
    "wof:placetype":"venue"
},
  "geometry": {"coordinates":[-82.51437300000001,27.988508],"type":"Point"}
}