{
  "type": "Feature",
  "properties": {
    "iso:country":"US",
    "sg:address":"4506 Mercantile Ave",
    "sg:city":"Naples",
    "sg:classifiers":[
        {
            "category":"Manufacturing",
            "subcategory":"Rubber & Plastics",
            "type":"Manufacturing & Wholesale Goods"
        }
    ],
    "sg:phone":"+1 239 403 0755",
    "sg:postcode":"34104",
    "sg:province":"FL",
    "sg:tags":[
        "trim",
        "architectural",
        "mfg"
    ],
    "wof:name":"Foam Masters Inc",
    "wof:placetype":"venue"
},
  "geometry": {"coordinates":[-81.757097,26.16608],"type":"Point"}
}