{
  "type": "Feature",
  "properties": {
    "addr:full":"12660 NE 3rd Ave Miami FL 33161",
    "addr:housenumber":"12660",
    "addr:postcode":"33161",
    "addr:street":"Ne 3Rd Ave",
    "iso:country":"US",
    "sg:address":"12660 NE 3rd Ave",
    "sg:city":"Miami",
    "sg:classifiers":[
        {
            "category":"Shopping",
            "subcategory":"Used Merchandise",
            "type":"Retail Goods"
        }
    ],
    "sg:phone":"+1 305 895 0251",
    "sg:postcode":"33161",
    "sg:province":"FL",
    "wof:name":"Claudia B Bailey Antiques",
    "wof:placetype":"venue"
},
  "geometry": {"coordinates":[-80.19250599999999,25.89],"type":"Point"}
}