{
  "type": "Feature",
  "properties": {
    "addr:full":"2306 McGee Rd Plant City FL 33565",
    "addr:housenumber":"2306",
    "addr:postcode":"33565",
    "addr:street":"Mcgee Rd",
    "iso:country":"US",
    "sg:address":"2306 McGee Rd",
    "sg:city":"Plant City",
    "sg:classifiers":[
        {
            "category":"Building & Trades",
            "subcategory":"Plumbing",
            "type":"Services"
        }
    ],
    "sg:phone":"+1 813 659 0297",
    "sg:postcode":"33565",
    "sg:province":"FL",
    "sg:tags":[
        "contractor"
    ],
    "wof:name":"Rite Flo Plumbing Co",
    "wof:placetype":"venue"
},
  "geometry": {"coordinates":[-82.150627,28.058292],"type":"Point"}
}