{
  "type": "Feature",
  "properties": {
    "addr:full":"420 Wisteria Rd Daytona Beach FL 32118",
    "addr:housenumber":"420",
    "addr:postcode":"32118",
    "addr:street":"Wisteria Rd",
    "iso:country":"US",
    "sg:address":"420 Wisteria Rd",
    "sg:city":"Daytona Beach",
    "sg:classifiers":[
        {
            "category":"Manufacturing",
            "subcategory":"Paper Products",
            "type":"Manufacturing & Wholesale Goods"
        }
    ],
    "sg:phone":"+1 386 253 9439",
    "sg:postcode":"32118",
    "sg:province":"FL",
    "sg:tags":[
        "wallpaper",
        "painting",
        "contractor"
    ],
    "wof:name":"Jane Ellen Harkness",
    "wof:placetype":"venue"
},
  "geometry": {"coordinates":[-81.000642,29.208783],"type":"Point"}
}