{
  "type": "Feature",
  "properties": {
    "iso:country":"US",
    "sg:address":"46 SW 1st St",
    "sg:city":"Miami",
    "sg:classifiers":[
        {
            "category":"Professional",
            "subcategory":"Lawyer & Legal Services",
            "type":"Services"
        }
    ],
    "sg:phone":"+1 305 374 7750",
    "sg:postcode":"33130",
    "sg:province":"FL",
    "sg:tags":[
        "attorney"
    ],
    "wof:name":"Druckman Fee & Chait",
    "wof:placetype":"venue"
},
  "geometry": {"coordinates":[-80.19473000000001,25.773211],"type":"Point"}
}