{
  "type": "Feature",
  "properties": {
    "iso:country":"US",
    "sg:address":"655 W Fulton St Ste 3",
    "sg:city":"Sanford",
    "sg:classifiers":[
        {
            "category":"Organizations",
            "subcategory":"Membership Organization",
            "type":"Services"
        }
    ],
    "sg:phone":"+1 321 277 8572",
    "sg:postcode":"32771",
    "sg:province":"FL",
    "sg:tags":[
        "military",
        "veteran"
    ],
    "wof:name":"Your Central Supply Source",
    "wof:placetype":"venue"
},
  "geometry": {"coordinates":[-81.273758,28.81337],"type":"Point"}
}