{
  "type": "Feature",
  "properties": {
    "iso:country":"US",
    "sg:address":"1358 NW 78th Ave",
    "sg:city":"Doral",
    "sg:classifiers":[
        {
            "category":"Freight",
            "type":"Transportation"
        }
    ],
    "sg:phone":"+1 305 716 1119",
    "sg:postcode":"33126",
    "sg:province":"FL",
    "sg:tags":[
        "forwarding"
    ],
    "wof:name":"Amber Worldwide Logistics Inc",
    "wof:placetype":"venue"
},
  "geometry": {"coordinates":[-80.322712,25.783888],"type":"Point"}
}