{
  "type": "Feature",
  "properties": {
    "iso:country":"US",
    "sg:address":"2274 Rose St",
    "sg:city":"Sarasota",
    "sg:classifiers":[
        {
            "category":"Building & Trades",
            "subcategory":"Construction",
            "type":"Services"
        }
    ],
    "sg:phone":"+1 941 685 1760",
    "sg:postcode":"34239",
    "sg:province":"FL",
    "sg:tags":[
        "house"
    ],
    "wof:name":"Chameleon Improvements",
    "wof:placetype":"venue"
},
  "geometry": {"coordinates":[-82.523039,27.306386],"type":"Point"}
}