{
  "type": "Feature",
  "properties": {
    "iso:country":"US",
    "sg:address":"17487 Spring Hill Dr",
    "sg:city":"Brooksville",
    "sg:classifiers":[
        {
            "category":"Personal",
            "subcategory":"Beauty Salon",
            "type":"Services"
        }
    ],
    "sg:phone":"+1 352 796 6411",
    "sg:postcode":"34604",
    "sg:province":"FL",
    "wof:name":"Aquarius Beauty Salon & Btq",
    "wof:placetype":"venue"
},
  "geometry": {"coordinates":[-82.441543,28.481105],"type":"Point"}
}