{
  "type": "Feature",
  "properties": {
    "iso:country":"US",
    "sg:address":"284 E Eau Gallie Blvd",
    "sg:city":"Satellite Beach",
    "sg:classifiers":[
        {
            "category":"Home & Garden",
            "subcategory":"Furniture",
            "type":"Retail Goods"
        }
    ],
    "sg:phone":"+1 321 777 7237",
    "sg:postcode":"32937",
    "sg:province":"FL",
    "sg:tags":[
        "swimming",
        "pool",
        "supply"
    ],
    "wof:name":"Pinch A Penny",
    "wof:placetype":"venue"
},
  "geometry": {"coordinates":[-80.598524,28.138482],"type":"Point"}
}