{
  "type": "Feature",
  "properties": {
    "iso:country":"US",
    "sg:address":"1950 Thomasville Rd",
    "sg:city":"Tallahassee",
    "sg:classifiers":[
        {
            "category":"Home & Garden",
            "subcategory":"Home Furnishings",
            "type":"Retail Goods"
        }
    ],
    "sg:phone":"+1 850 222 1393",
    "sg:postcode":"32303",
    "sg:province":"FL",
    "sg:tags":[
        "curtain",
        "made",
        "drapery"
    ],
    "wof:name":"Frances Drapery",
    "wof:placetype":"venue"
},
  "geometry": {"coordinates":[-84.268018,30.467472],"type":"Point"}
}