{
  "type": "Feature",
  "properties": {
    "iso:country":"US",
    "sg:address":"1675 SE Lake Legacy Way",
    "sg:city":"Stuart",
    "sg:classifiers":[
        {
            "category":"Shopping",
            "subcategory":"Gifts & Souvenirs",
            "type":"Retail Goods"
        }
    ],
    "sg:phone":"+1 772 260 6070",
    "sg:postcode":"34997",
    "sg:province":"FL",
    "sg:tags":[
        "shop"
    ],
    "wof:name":"Treasure Coast Hardwoods",
    "wof:placetype":"venue"
},
  "geometry": {"coordinates":[-80.233509,27.125574],"type":"Point"}
}