{
  "type": "Feature",
  "properties": {
    "iso:country":"US",
    "sg:address":"6702 Benjamin Rd",
    "sg:city":"Tampa",
    "sg:classifiers":[
        {
            "category":"Manufacturing",
            "subcategory":"Tools & Machinery",
            "type":"Manufacturing & Wholesale Goods"
        }
    ],
    "sg:phone":"+1 813 890 0920",
    "sg:postcode":"33634",
    "sg:province":"FL",
    "sg:tags":[
        "lens",
        "optical",
        "manufacturer"
    ],
    "wof:name":"Instant Optical",
    "wof:placetype":"venue"
},
  "geometry": {"coordinates":[-82.542025,28.010934],"type":"Point"}
}