{
  "type": "Feature",
  "properties": {
    "addr:full":"1336 Orange Cir S Orange Park FL 32073",
    "addr:housenumber":"1336",
    "addr:postcode":"32073",
    "addr:street":"Orange Cir S Orange Park",
    "iso:country":"US",
    "sg:address":"1336 Orange Cir S",
    "sg:city":"Orange Park",
    "sg:classifiers":[
        {
            "category":"Banks & Credit Unions",
            "subcategory":"Bank",
            "type":"Services"
        }
    ],
    "sg:phone":"+1 904 278 8123",
    "sg:postcode":"32073",
    "sg:province":"FL",
    "sg:tags":[
        "mortgage"
    ],
    "wof:name":"Florida Mortgage Funding",
    "wof:placetype":"venue"
},
  "geometry": {"coordinates":[-81.69970499999999,30.173103],"type":"Point"}
}