{
  "type": "Feature",
  "properties": {
    "iso:country":"US",
    "sg:address":"143 Guadalajara Dr",
    "sg:city":"Kissimmee",
    "sg:classifiers":[
        {
            "category":"Local Transit",
            "type":"Transportation"
        }
    ],
    "sg:phone":"+1 407 348 2470",
    "sg:postcode":"34743",
    "sg:province":"FL",
    "sg:tags":[
        "airport"
    ],
    "wof:name":"Florida Van Pool Trnsptn",
    "wof:placetype":"venue"
},
  "geometry": {"coordinates":[-81.353837,28.324746],"type":"Point"}
}