{
  "type": "Feature",
  "properties": {
    "iso:country":"US",
    "sg:address":"1660 N Monroe St",
    "sg:city":"Tallahassee",
    "sg:classifiers":[
        {
            "category":"Retail",
            "subcategory":"Laundry & Dry Cleaning",
            "type":"Services"
        }
    ],
    "sg:phone":"+1 850 561 3830",
    "sg:postcode":"32303",
    "sg:province":"FL",
    "sg:tags":[
        "cleaners"
    ],
    "wof:name":"Blue Ribbon Cleaners",
    "wof:placetype":"venue"
},
  "geometry": {"coordinates":[-84.281036,30.459905],"type":"Point"}
}