{
  "type": "Feature",
  "properties": {
    "iso:country":"US",
    "sg:address":"7748 Wiles Rd",
    "sg:city":"Coral Springs",
    "sg:classifiers":[
        {
            "category":"Retail",
            "subcategory":"Repair Shop",
            "type":"Services"
        },
        {
            "category":"Shopping",
            "type":"Retail Goods"
        }
    ],
    "sg:phone":"+1 954 340 8830",
    "sg:postcode":"33067",
    "sg:province":"FL",
    "sg:tags":[
        "picture",
        "frame",
        "merchandise"
    ],
    "wof:name":"Design Crafters Inc",
    "wof:placetype":"venue"
},
  "geometry": {"coordinates":[-80.229793,26.286676],"type":"Point"}
}