{
  "type": "Feature",
  "properties": {
    "addr:full":"1111 Fairfield Dr West Palm Beach FL 33407",
    "addr:housenumber":"1111",
    "addr:postcode":"33407",
    "addr:street":"Fairfield Dr",
    "iso:country":"US",
    "sg:address":"1111 Fairfield Dr",
    "sg:city":"West Palm Beach",
    "sg:classifiers":[
        {
            "category":"Organizations",
            "subcategory":"Religious Organization",
            "type":"Services"
        }
    ],
    "sg:phone":"+1 561 881 9095",
    "sg:postcode":"33407",
    "sg:province":"FL",
    "sg:tags":[
        "church"
    ],
    "wof:name":"Central New Testament Chr-God",
    "wof:placetype":"venue"
},
  "geometry": {"coordinates":[-80.069727,26.762496],"type":"Point"}
}