{
  "type": "Feature",
  "properties": {
    "iso:country":"US",
    "sg:address":"200 NE 30th St",
    "sg:city":"Miami",
    "sg:classifiers":[
        {
            "category":"Manufacturing",
            "subcategory":"Textiles",
            "type":"Manufacturing & Wholesale Goods"
        },
        {
            "category":"Shopping",
            "subcategory":"Crafts & Fabrics",
            "type":"Retail Goods"
        }
    ],
    "sg:phone":"+1 305 573 3033",
    "sg:postcode":"33137",
    "sg:province":"FL",
    "sg:tags":[
        "shop",
        "fabrics-wholesale",
        "store",
        "manufacturer"
    ],
    "sg:website":"www.isacouturefabrics.com",
    "wof:name":"Isa Couture Fabrics",
    "wof:placetype":"venue"
},
  "geometry": {"coordinates":[-80.191002,25.805201],"type":"Point"}
}