{
  "type": "Feature",
  "properties": {
    "iso:country":"US",
    "sg:address":"7823 Clark Moody Blvd",
    "sg:city":"Port Richey",
    "sg:classifiers":[
        {
            "category":"Wholesale",
            "subcategory":"Metals & Minerals",
            "type":"Manufacturing & Wholesale Goods"
        }
    ],
    "sg:phone":"+1 727 849 9519",
    "sg:postcode":"34668",
    "sg:province":"FL",
    "sg:tags":[
        "heavy",
        "construction",
        "center"
    ],
    "wof:name":"Suiters Aluminum Inc",
    "wof:placetype":"venue"
},
  "geometry": {"coordinates":[-82.714884,28.272882],"type":"Point"}
}