{
  "type": "Feature",
  "properties": {
    "addr:full":"2335 NW 107th Ave Doral FL 33172",
    "addr:housenumber":"2335",
    "addr:postcode":"33172",
    "addr:street":"Nw 107Th Ave",
    "iso:country":"US",
    "sg:address":"2335 NW 107th Ave",
    "sg:city":"Doral",
    "sg:classifiers":[
        {
            "category":"Freight",
            "type":"Transportation"
        }
    ],
    "sg:phone":"+1 305 477 7393",
    "sg:postcode":"33172",
    "sg:province":"FL",
    "sg:tags":[
        "consultant"
    ],
    "wof:name":"Metrics Freight Systems Inc",
    "wof:placetype":"venue"
},
  "geometry": {"coordinates":[-80.36899,25.795796],"type":"Point"}
}