{
  "type": "Feature",
  "properties": {
    "iso:country":"US",
    "sg:address":"1002 E Duval St",
    "sg:city":"Lake City",
    "sg:classifiers":[
        {
            "category":"Personal",
            "subcategory":"Beauty Salon",
            "type":"Services"
        }
    ],
    "sg:phone":"+1 386 758 9336",
    "sg:postcode":"32055",
    "sg:province":"FL",
    "wof:name":"Cutting Edge",
    "wof:placetype":"venue"
},
  "geometry": {"coordinates":[-82.629662,30.189245],"type":"Point"}
}