{
  "type": "Feature",
  "properties": {
    "addr:full":"8773 Laredo St Navarre FL 32566",
    "addr:housenumber":"8773",
    "addr:postcode":"32566",
    "addr:street":"Laredo St",
    "iso:country":"US",
    "sg:address":"8773 Laredo St",
    "sg:city":"Navarre",
    "sg:classifiers":[
        {
            "category":"Shopping",
            "subcategory":"Bicycles & Sporting Goods",
            "type":"Retail Goods"
        }
    ],
    "sg:phone":"+1 850 543 7988",
    "sg:postcode":"32566",
    "sg:province":"FL",
    "sg:tags":[
        "equipment",
        "golf",
        "supply"
    ],
    "wof:name":"Jean Doane Landscaping",
    "wof:placetype":"venue"
},
  "geometry": {"coordinates":[-86.856449,30.409523],"type":"Point"}
}