{
  "type": "Feature",
  "properties": {
    "iso:country":"US",
    "sg:address":"212 Yacht Club Dr",
    "sg:city":"St Augustine",
    "sg:classifiers":[
        {
            "category":"Manufacturing",
            "subcategory":"Tools & Machinery",
            "type":"Manufacturing & Wholesale Goods"
        },
        {
            "category":"Manufacturing",
            "subcategory":"Watercraft",
            "type":"Manufacturing & Wholesale Goods"
        }
    ],
    "sg:phone":"+1 904 829 2125",
    "sg:postcode":"32084",
    "sg:province":"FL",
    "sg:tags":[
        "supply",
        "equipment",
        "accessory",
        "marine",
        "mfg"
    ],
    "wof:name":"Advanced Marine Technologies",
    "wof:placetype":"venue"
},
  "geometry": {"coordinates":[-81.306945,29.915536],"type":"Point"}
}