{
  "type": "Feature",
  "properties": {
    "addr:full":"151 NW 11th St Ste 102 Homestead FL 33030",
    "addr:housenumber":"151",
    "addr:postcode":"33030",
    "addr:street":"Nw 11Th St Ste 102",
    "iso:country":"US",
    "sg:address":"151 NW 11th St Ste 102",
    "sg:city":"Homestead",
    "sg:classifiers":[
        {
            "category":"Health Services",
            "subcategory":"Doctor",
            "type":"Services"
        }
    ],
    "sg:phone":"+1 305 245 5881",
    "sg:postcode":"33030",
    "sg:province":"FL",
    "sg:tags":[
        "physician",
        "pediatrics-otorhinolaryngology",
        "surgeons",
        "otorhinolaryngology",
        "nose",
        "throat",
        "surgeon",
        "ear"
    ],
    "wof:name":"South Florida Ent Associates",
    "wof:placetype":"venue"
},
  "geometry": {"coordinates":[-80.480577,25.480784],"type":"Point"}
}