{
  "type": "Feature",
  "properties": {
    "addr:full":"1490 NW 43rd Ave Fort Lauderdale FL 33313",
    "addr:housenumber":"1490",
    "addr:postcode":"33313",
    "addr:street":"Nw 43Rd Ave",
    "iso:country":"US",
    "sg:address":"1490 NW 43rd Ave",
    "sg:city":"Fort Lauderdale",
    "sg:classifiers":[
        {
            "category":"Organizations",
            "subcategory":"Community Association",
            "type":"Services"
        }
    ],
    "sg:phone":"+1 954 484 5162",
    "sg:postcode":"33313",
    "sg:province":"FL",
    "wof:name":"Park So 7 Condos Inc",
    "wof:placetype":"venue"
},
  "geometry": {"coordinates":[-80.20692699999999,26.144373],"type":"Point"}
}