{
  "type": "Feature",
  "properties": {
    "addr:full":"212 Marion St Satellite Beach FL 32937",
    "addr:housenumber":"212",
    "addr:postcode":"32937",
    "addr:street":"Marion St",
    "iso:country":"US",
    "sg:address":"212 Marion St",
    "sg:city":"Satellite Beach",
    "sg:classifiers":[
        {
            "category":"Retail",
            "subcategory":"Repair Shop",
            "type":"Services"
        }
    ],
    "sg:phone":"+1 321 777 6471",
    "sg:postcode":"32937",
    "sg:province":"FL",
    "wof:name":"R & D Repair & Remodeling",
    "wof:placetype":"venue"
},
  "geometry": {"coordinates":[-80.588584,28.146203],"type":"Point"}
}