{
  "type": "Feature",
  "properties": {
    "iso:country":"US",
    "sg:address":"1707 W 23rd St",
    "sg:city":"Panama City",
    "sg:classifiers":[
        {
            "category":"Health Services",
            "subcategory":"Optometrist",
            "type":"Services"
        }
    ],
    "sg:phone":"+1 850 873 8134",
    "sg:postcode":"32405",
    "sg:province":"FL",
    "wof:name":"Brenda Wainwright OD Pa",
    "wof:placetype":"venue"
},
  "geometry": {"coordinates":[-85.688377,30.189755],"type":"Point"}
}