{
  "type": "Feature",
  "properties": {
    "addr:full":"3003 Brooks St Lakeland FL 33803",
    "addr:housenumber":"3003",
    "addr:postcode":"33803",
    "addr:street":"Brooks St",
    "iso:country":"US",
    "sg:address":"3003 Brooks St",
    "sg:city":"Lakeland",
    "sg:classifiers":[
        {
            "category":"Building & Trades",
            "subcategory":"Construction",
            "type":"Services"
        }
    ],
    "sg:phone":"+1 863 667 4800",
    "sg:postcode":"33803",
    "sg:province":"FL",
    "sg:tags":[
        "painter"
    ],
    "wof:name":"Sharrett Decorating",
    "wof:placetype":"venue"
},
  "geometry": {"coordinates":[-81.898444,28.004041],"type":"Point"}
}