{
  "type": "Feature",
  "properties": {
    "iso:country":"US",
    "sg:address":"18825 Biscayne Blvd",
    "sg:city":"Miami",
    "sg:phone":"+1 305 937 4401",
    "sg:postcode":"33180",
    "sg:province":"FL",
    "wof:name":"Via Moda",
    "wof:placetype":"venue"
},
  "geometry": {"coordinates":[-80.14657200000001,25.949975],"type":"Point"}
}