{
  "type": "Feature",
  "properties": {
    "iso:country":"US",
    "sg:address":"400 N Hiatus Rd",
    "sg:city":"Pembroke Pines",
    "sg:classifiers":[
        {
            "category":"Real Estate",
            "subcategory":"Real Estate Agent",
            "type":"Services"
        }
    ],
    "sg:phone":"+1 954 499 6000",
    "sg:postcode":"33026",
    "sg:province":"FL",
    "wof:name":"Revier Real Estate",
    "wof:placetype":"venue"
},
  "geometry": {"coordinates":[-80.29644,26.01093],"type":"Point"}
}