{
  "type": "Feature",
  "properties": {
    "iso:country":"US",
    "sg:address":"8630 Saddlebrook Cir",
    "sg:city":"Naples",
    "sg:classifiers":[
        {
            "category":"Real Estate",
            "subcategory":"Real Estate Operator",
            "type":"Services"
        }
    ],
    "sg:phone":"+1 239 348 7421",
    "sg:postcode":"34104",
    "sg:province":"FL",
    "sg:tags":[
        "apartment"
    ],
    "wof:name":"Saddlebrook Village Apts",
    "wof:placetype":"venue"
},
  "geometry": {"coordinates":[-81.69339100000001,26.155309],"type":"Point"}
}