{
  "type": "Feature",
  "properties": {
    "addr:full":"95 Marina Ave Key Largo FL 33037",
    "addr:housenumber":"95",
    "addr:postcode":"33037",
    "addr:street":"Marina Ave",
    "iso:country":"US",
    "sg:address":"95 Marina Ave",
    "sg:city":"Key Largo",
    "sg:classifiers":[
        {
            "category":"Social Services",
            "type":"Services"
        }
    ],
    "sg:phone":"+1 305 451 4181",
    "sg:postcode":"33037",
    "sg:province":"FL",
    "wof:name":"Adams Counseling",
    "wof:placetype":"venue"
},
  "geometry": {"coordinates":[-80.43784100000001,25.089823],"type":"Point"}
}