{
  "type": "Feature",
  "properties": {
    "iso:country":"US",
    "sg:address":"1024 State Hwy 60",
    "sg:city":"Lake Wales",
    "sg:classifiers":[
        {
            "category":"Taxi",
            "type":"Transportation"
        }
    ],
    "sg:phone":"+1 863 676 1089",
    "sg:postcode":"33853",
    "sg:province":"FL",
    "sg:tags":[
        "taxicab"
    ],
    "wof:name":"Lake Wales Cab Co",
    "wof:placetype":"venue"
},
  "geometry": {"coordinates":[-81.570061,27.893932],"type":"Point"}
}