{
  "type": "Feature",
  "properties": {
    "addr:full":"1190 Homestead Rd N Lehigh Acres FL 33936",
    "addr:housenumber":"1190",
    "addr:postcode":"33936",
    "addr:street":"Homestead Rd N",
    "iso:country":"US",
    "sg:address":"1190 Homestead Rd N",
    "sg:city":"Lehigh Acres",
    "sg:classifiers":[
        {
            "category":"Banks & Credit Unions",
            "subcategory":"Bank",
            "type":"Services"
        }
    ],
    "sg:phone":"+1 239 303 9599",
    "sg:postcode":"33936",
    "sg:province":"FL",
    "sg:tags":[
        "state",
        "commercial"
    ],
    "wof:name":"Premier Community Bank SW Fla",
    "wof:placetype":"venue"
},
  "geometry": {"coordinates":[-81.64715099999999,26.604361],"type":"Point"}
}