{
  "type": "Feature",
  "properties": {
    "iso:country":"US",
    "sg:address":"8269 SW 100th Lane Rd",
    "sg:city":"Ocala",
    "sg:classifiers":[
        {
            "category":"Real Estate",
            "subcategory":"Real Estate Services",
            "type":"Services"
        },
        {
            "category":"Building & Trades",
            "subcategory":"Cleaning & Sanitation",
            "type":"Services"
        }
    ],
    "sg:phone":"+1 352 861 2705",
    "sg:postcode":"34481",
    "sg:province":"FL",
    "sg:tags":[
        "maintenance",
        "cleaners-interior"
    ],
    "wof:name":"M H Michaels Maintenance",
    "wof:placetype":"venue"
},
  "geometry": {"coordinates":[-82.256567,29.075432],"type":"Point"}
}