{
  "type": "Feature",
  "properties": {
    "iso:country":"US",
    "sg:address":"504 Reo Dr",
    "sg:city":"Jupiter",
    "sg:classifiers":[
        {
            "category":"Professional",
            "subcategory":"Business Services",
            "type":"Services"
        }
    ],
    "sg:phone":"+1 561 744 5999",
    "sg:postcode":"33458",
    "sg:province":"FL",
    "sg:tags":[
        "pool",
        "swimming"
    ],
    "wof:name":"Mike Small Pool Svc",
    "wof:placetype":"venue"
},
  "geometry": {"coordinates":[-80.107114,26.937678],"type":"Point"}
}