{
  "type": "Feature",
  "properties": {
    "iso:country":"US",
    "sg:address":"2680 S Ferdon Blvd",
    "sg:city":"Crestview",
    "sg:classifiers":[
        {
            "category":"Bars & Pubs",
            "type":"Food & Drink"
        }
    ],
    "sg:menulink":"http://www.allmenus.com/fl/crestview/101366-sonnys-bar-b-q/menu/",
    "sg:phone":"+1 850 683 0572",
    "sg:postcode":"32536",
    "sg:province":"FL",
    "sg:tags":[
        "barbecue",
        "american"
    ],
    "wof:name":"Sonny's Bar-B-Q",
    "wof:placetype":"venue"
},
  "geometry": {"coordinates":[-86.56677500000001,30.732189],"type":"Point"}
}