{
  "type": "Feature",
  "properties": {
    "iso:country":"US",
    "sg:address":"6013 Eleanor Dr",
    "sg:city":"Tampa",
    "sg:classifiers":[
        {
            "category":"Restaurant",
            "type":"Food & Drink"
        }
    ],
    "sg:phone":"+1 813 963 2676",
    "sg:postcode":"33634",
    "sg:province":"FL",
    "sg:tags":[
        "eating"
    ],
    "wof:name":"Ice Cube Inc",
    "wof:placetype":"venue"
},
  "geometry": {"coordinates":[-82.548247,27.984734],"type":"Point"}
}