{
  "type": "Feature",
  "properties": {
    "iso:country":"US",
    "sg:address":"8602 SW 5th Pl",
    "sg:city":"Gainesville",
    "sg:classifiers":[
        {
            "category":"Professional",
            "subcategory":"Accounting & Tax Preparation",
            "type":"Services"
        },
        {
            "category":"Professional",
            "subcategory":"Business Services",
            "type":"Services"
        }
    ],
    "sg:phone":"+1 352 332 0618",
    "sg:postcode":"32607",
    "sg:province":"FL",
    "sg:tags":[
        "consultant",
        "coach",
        "public",
        "accountants-certified"
    ],
    "wof:name":"Helen K Gyllstrom Cpa",
    "wof:placetype":"venue"
},
  "geometry": {"coordinates":[-82.434409,29.646924],"type":"Point"}
}