{
  "type": "Feature",
  "properties": {
    "addr:full":"10810 72nd St N Largo FL 33777",
    "addr:housenumber":"10810",
    "addr:postcode":"33777",
    "addr:street":"72Nd St N",
    "iso:country":"US",
    "sg:address":"10810 72nd St N",
    "sg:city":"Largo",
    "sg:classifiers":[
        {
            "category":"Professional",
            "subcategory":"Management & Consulting",
            "type":"Services"
        }
    ],
    "sg:phone":"+1 727 545 4185",
    "sg:postcode":"33777",
    "sg:province":"FL",
    "sg:tags":[
        "consultant",
        "broker"
    ],
    "sg:website":"www.terrikabachnick.com",
    "wof:name":"Kabachnick Group",
    "wof:placetype":"venue"
},
  "geometry": {"coordinates":[-82.738535,27.870501],"type":"Point"}
}