{
  "type": "Feature",
  "properties": {
    "iso:country":"US",
    "sg:address":"6600 E Hwy 22",
    "sg:city":"Panama City",
    "sg:classifiers":[
        {
            "category":"Building & Trades",
            "subcategory":"Electrical",
            "type":"Services"
        }
    ],
    "sg:phone":"+1 850 871 5613",
    "sg:postcode":"32404",
    "sg:province":"FL",
    "sg:tags":[
        "electric",
        "contractor"
    ],
    "wof:name":"Dave Pybus Electric",
    "wof:placetype":"venue"
},
  "geometry": {"coordinates":[-85.57758200000001,30.152956],"type":"Point"}
}