{
  "type": "Feature",
  "properties": {
    "iso:country":"US",
    "sg:address":"1707 E Cape Coral Pkwy",
    "sg:city":"Cape Coral",
    "sg:classifiers":[
        {
            "category":"Professional",
            "subcategory":"Management & Consulting",
            "type":"Services"
        }
    ],
    "sg:phone":"+1 239 549 9696",
    "sg:postcode":"33904",
    "sg:province":"FL",
    "sg:tags":[
        "business"
    ],
    "wof:name":"Coastland Homes Inc",
    "wof:placetype":"venue"
},
  "geometry": {"coordinates":[-81.940712,26.562733],"type":"Point"}
}