{
  "type": "Feature",
  "properties": {
    "iso:country":"US",
    "sg:address":"166 W 3rd Ave",
    "sg:city":"Pierson",
    "sg:classifiers":[
        {
            "category":"Place Of Worship",
            "subcategory":"Church",
            "type":"Public Place"
        },
        {
            "category":"Place Of Worship",
            "type":"Public Place"
        }
    ],
    "sg:phone":"+1 386 749 2204",
    "sg:postcode":"32180",
    "sg:province":"FL",
    "sg:tags":[
        "churches-baptist-general",
        "churches-baptist-southern",
        "churches-baptist"
    ],
    "wof:name":"First Baptist Church Of Pierson",
    "wof:placetype":"venue"
},
  "geometry": {"coordinates":[-81.46563500000001,29.235777],"type":"Point"}
}