{
  "type": "Feature",
  "properties": {
    "iso:country":"US",
    "sg:address":"1470 NW 107th Ave Ste K",
    "sg:city":"Doral",
    "sg:classifiers":[
        {
            "category":"Building & Trades",
            "subcategory":"Construction",
            "type":"Services"
        }
    ],
    "sg:phone":"+1 305 599 8186",
    "sg:postcode":"33172",
    "sg:province":"FL",
    "sg:tags":[
        "contractor"
    ],
    "wof:name":"Reliable Contractors",
    "wof:placetype":"venue"
},
  "geometry": {"coordinates":[-80.36889600000001,25.7876],"type":"Point"}
}