{
  "type": "Feature",
  "properties": {
    "iso:country":"US",
    "sg:address":"DBA Tourico Holiday, Inc. 220 East Central Parkway Suite 400",
    "sg:city":"Altamonte Springs",
    "sg:classifiers":[
        {
            "category":"Travel",
            "subcategory":"Hotels & Motels",
            "type":"Entertainment"
        }
    ],
    "sg:phone":"+1 800 442 0568",
    "sg:postcode":"32701",
    "sg:province":"FL",
    "sg:website":"www.LastMinuteTravel.com",
    "wof:name":"LastMinuteTravel.com",
    "wof:placetype":"venue"
},
  "geometry": {"coordinates":[-81.383489,28.669103],"type":"Point"}
}