{
  "type": "Feature",
  "properties": {
    "addr:full":"5821 SW 5th Ter Miami FL 33144",
    "addr:housenumber":"5821",
    "addr:postcode":"33144",
    "addr:street":"Sw 5Th Ter",
    "iso:country":"US",
    "sg:address":"5821 SW 5th Ter",
    "sg:city":"Miami",
    "sg:classifiers":[
        {
            "category":"Manufacturing",
            "subcategory":"Chemicals & Compounds",
            "type":"Manufacturing & Wholesale Goods"
        }
    ],
    "sg:phone":"+1 305 261 0369",
    "sg:postcode":"33144",
    "sg:province":"FL",
    "sg:tags":[
        "preparation",
        "mfg"
    ],
    "wof:name":"Tsi Aquatics Inc",
    "wof:placetype":"venue"
},
  "geometry": {"coordinates":[-80.29102,25.765584],"type":"Point"}
}