{
  "type": "Feature",
  "properties": {
    "iso:country":"US",
    "sg:address":"2307 Orange Point Ave",
    "sg:city":"Palm Harbor",
    "sg:classifiers":[
        {
            "category":"Shopping",
            "subcategory":"Used Merchandise",
            "type":"Retail Goods"
        }
    ],
    "sg:phone":"+1 727 781 1806",
    "sg:postcode":"34683",
    "sg:province":"FL",
    "sg:tags":[
        "shop",
        "consignment"
    ],
    "wof:name":"Second Debut Consignment Btq",
    "wof:placetype":"venue"
},
  "geometry": {"coordinates":[-82.745096,28.09092],"type":"Point"}
}