{
  "type": "Feature",
  "properties": {
    "iso:country":"US",
    "sg:address":"2401 1st St",
    "sg:city":"Fort Myers",
    "sg:classifiers":[
        {
            "category":"Communications",
            "type":"Services"
        }
    ],
    "sg:phone":"+1 239 333 0000",
    "sg:postcode":"33901",
    "sg:province":"FL",
    "wof:name":"T 3 Communications LLC",
    "wof:placetype":"venue"
},
  "geometry": {"coordinates":[-81.868099,26.645321],"type":"Point"}
}