{
  "type": "Feature",
  "properties": {
    "addr:full":"6785 SW 8th St Miami FL 33144",
    "addr:housenumber":"6785",
    "addr:postcode":"33144",
    "addr:street":"Sw 8Th St",
    "iso:country":"US",
    "sg:address":"6785 SW 8th St",
    "sg:city":"Miami",
    "sg:classifiers":[
        {
            "category":"Professional",
            "subcategory":"Secretarial Services",
            "type":"Services"
        },
        {
            "category":"Professional",
            "subcategory":"Employment Agencies",
            "type":"Services"
        },
        {
            "category":"Professional",
            "subcategory":"Business Services",
            "type":"Services"
        },
        {
            "category":"Professional",
            "subcategory":"Lawyer & Legal Services",
            "type":"Services"
        }
    ],
    "sg:phone":"+1 305 266 9117",
    "sg:postcode":"33144",
    "sg:province":"FL",
    "sg:tags":[
        "notary",
        "public",
        "typing"
    ],
    "wof:name":"Rosy's Service",
    "wof:placetype":"venue"
},
  "geometry": {"coordinates":[-80.305566,25.763298],"type":"Point"}
}