{
  "type": "Feature",
  "properties": {
    "iso:country":"US",
    "sg:address":"836 Prudential Dr",
    "sg:city":"Jacksonville",
    "sg:classifiers":[
        {
            "category":"Health Services",
            "subcategory":"Health Practitioner",
            "type":"Services"
        }
    ],
    "sg:phone":"+1 904 399 0350",
    "sg:postcode":"32207",
    "sg:province":"FL",
    "sg:tags":[
        "audiologists"
    ],
    "wof:name":"Jacksonville Hearing & Balance",
    "wof:placetype":"venue"
},
  "geometry": {"coordinates":[-81.662886,30.316222],"type":"Point"}
}