{
  "type": "Feature",
  "properties": {
    "addr:full":"3440 Hollywood Blvd Hollywood FL 33021",
    "addr:housenumber":"3440",
    "addr:postcode":"33021",
    "addr:street":"Hollywood Blvd",
    "iso:country":"US",
    "sg:address":"3440 Hollywood Blvd",
    "sg:city":"Hollywood",
    "sg:classifiers":[
        {
            "category":"Professional",
            "subcategory":"Lawyer & Legal Services",
            "type":"Services"
        }
    ],
    "sg:phone":"+1 954 961 1400",
    "sg:postcode":"33021",
    "sg:province":"FL",
    "sg:tags":[
        "litigation",
        "attorney",
        "law",
        "personal",
        "tort",
        "injury"
    ],
    "wof:name":"Blaker , Jeffrey A. - Conroy, Simberg, G",
    "wof:placetype":"venue"
},
  "geometry": {"coordinates":[-80.178392,26.010582],"type":"Point"}
}