{
  "type": "Feature",
  "properties": {
    "iso:country":"US",
    "sg:address":"601 Collins Ave Ste 3",
    "sg:city":"Miami Beach",
    "sg:classifiers":[
        {
            "category":"Food & Beverages",
            "subcategory":"Groceries & Convenience Stores",
            "type":"Retail Goods"
        }
    ],
    "sg:phone":"+1 305 673 3386",
    "sg:postcode":"33139",
    "sg:province":"FL",
    "wof:name":"Loco Food Market",
    "wof:placetype":"venue"
},
  "geometry": {"coordinates":[-80.132464,25.775663],"type":"Point"}
}