{
  "type": "Feature",
  "properties": {
    "iso:country":"US",
    "sg:address":"216 Jackson St",
    "sg:city":"Black",
    "sg:classifiers":[
        {
            "category":"Wholesale",
            "subcategory":"Stationery",
            "type":"Manufacturing & Wholesale Goods"
        }
    ],
    "sg:phone":"+1 334 684 6237",
    "sg:postcode":"36314",
    "sg:province":"FL",
    "sg:tags":[
        "supply"
    ],
    "wof:name":"Danny Stewart",
    "wof:placetype":"venue"
},
  "geometry": {"coordinates":[-85.742462,31.012993],"type":"Point"}
}