{
  "type": "Feature",
  "properties": {
    "addr:full":"330 W 9th St Hialeah FL 33010",
    "addr:housenumber":"330",
    "addr:postcode":"33010",
    "addr:street":"W 9Th St",
    "iso:country":"US",
    "sg:address":"330 W 9th St",
    "sg:city":"Hialeah",
    "sg:classifiers":[
        {
            "category":"Personal",
            "subcategory":"Beauty Salon",
            "type":"Services"
        }
    ],
    "sg:phone":"+1 305 883 5111",
    "sg:postcode":"33010",
    "sg:province":"FL",
    "wof:name":"Iraida Unisex",
    "wof:placetype":"venue"
},
  "geometry": {"coordinates":[-80.289118,25.829628],"type":"Point"}
}