{
  "type": "Feature",
  "properties": {
    "addr:full":"9100 SW 86th St Miami FL 33173",
    "addr:housenumber":"9100",
    "addr:postcode":"33173",
    "addr:street":"Sw 86Th St",
    "iso:country":"US",
    "sg:address":"9100 SW 86th St",
    "sg:city":"Miami",
    "sg:classifiers":[
        {
            "category":"Cinema",
            "subcategory":"Movie Theater",
            "type":"Entertainment"
        }
    ],
    "sg:phone":"+1 305 271 0506",
    "sg:postcode":"33173",
    "sg:province":"FL",
    "sg:tags":[
        "motion",
        "picture"
    ],
    "wof:name":"Florence C Boss",
    "wof:placetype":"venue"
},
  "geometry": {"coordinates":[-80.341251,25.689406],"type":"Point"}
}