{
  "type": "Feature",
  "properties": {
    "iso:country":"US",
    "sg:address":"6110 Powers Ave",
    "sg:city":"Jacksonville",
    "sg:classifiers":[
        {
            "category":"Building & Trades",
            "subcategory":"Construction",
            "type":"Services"
        }
    ],
    "sg:phone":"+1 904 733 9343",
    "sg:postcode":"32217",
    "sg:province":"FL",
    "sg:tags":[
        "marble",
        "terrazzo"
    ],
    "wof:name":"Florida Stone & Marble",
    "wof:placetype":"venue"
},
  "geometry": {"coordinates":[-81.62103399999999,30.261998],"type":"Point"}
}