{
  "type": "Feature",
  "properties": {
    "addr:full":"4710 50th Ave Vero Beach FL 32967",
    "addr:housenumber":"4710",
    "addr:postcode":"32967",
    "addr:street":"50Th Ave",
    "iso:country":"US",
    "sg:address":"4710 50th Ave",
    "sg:city":"Vero Beach",
    "sg:classifiers":[
        {
            "category":"Shopping",
            "subcategory":"Clothing, Apparel, & Fashions",
            "type":"Retail Goods"
        }
    ],
    "sg:phone":"+1 772 567 4383",
    "sg:postcode":"32967",
    "sg:province":"FL",
    "wof:name":"Veronica A Domani",
    "wof:placetype":"venue"
},
  "geometry": {"coordinates":[-80.43772,27.67936],"type":"Point"}
}