{
  "type": "Feature",
  "properties": {
    "addr:full":"1410 E Fern Rd Lakeland FL 33801",
    "addr:housenumber":"1410",
    "addr:postcode":"33801",
    "addr:street":"E Fern Rd",
    "iso:country":"US",
    "sg:address":"1410 E Fern Rd",
    "sg:city":"Lakeland",
    "sg:classifiers":[
        {
            "category":"Banks & Credit Unions",
            "subcategory":"Investment Brokerage",
            "type":"Services"
        }
    ],
    "sg:phone":"+1 863 682 5839",
    "sg:postcode":"33801",
    "sg:province":"FL",
    "sg:tags":[
        "tape",
        "video",
        "sale",
        "dvds-rental"
    ],
    "wof:name":"Village Video",
    "wof:placetype":"venue"
},
  "geometry": {"coordinates":[-81.935804,28.04795],"type":"Point"}
}