{
  "type": "Feature",
  "properties": {
    "iso:country":"US",
    "sg:address":"5352 NW 201st St",
    "sg:city":"Hialeah",
    "sg:classifiers":[
        {
            "category":"Health Services",
            "subcategory":"Medical Lab",
            "type":"Services"
        }
    ],
    "sg:phone":"+1 305 974 4994",
    "sg:postcode":"33015",
    "sg:province":"FL",
    "sg:tags":[
        "record"
    ],
    "wof:name":"Jeanette Rojas",
    "wof:placetype":"venue"
},
  "geometry": {"coordinates":[-80.31049,25.95487],"type":"Point"}
}