{
  "type": "Feature",
  "properties": {
    "iso:country":"US",
    "sg:address":"1691 94th Dr",
    "sg:city":"Vero Beach",
    "sg:classifiers":[
        {
            "category":"Shopping",
            "subcategory":"Books",
            "type":"Retail Goods"
        }
    ],
    "sg:phone":"+1 772 794 2494",
    "sg:postcode":"32966",
    "sg:province":"FL",
    "sg:tags":[
        "dealer"
    ],
    "wof:name":"Book Warehouse",
    "wof:placetype":"venue"
},
  "geometry": {"coordinates":[-80.522541,27.637233],"type":"Point"}
}