{
  "type": "Feature",
  "properties": {
    "iso:country":"US",
    "sg:address":"959 Periwinkle Way",
    "sg:city":"Sanibel",
    "sg:classifiers":[
        {
            "category":"Real Estate",
            "subcategory":"Real Estate Agent",
            "type":"Services"
        }
    ],
    "sg:phone":"+1 239 472 3535",
    "sg:postcode":"33957",
    "sg:province":"FL",
    "wof:name":"Frey Realty Group",
    "wof:placetype":"venue"
},
  "geometry": {"coordinates":[-82.039806,26.446859],"type":"Point"}
}