{
  "type": "Feature",
  "properties": {
    "iso:country":"US",
    "sg:address":"601 E Chaminade Dr",
    "sg:city":"Hollywood",
    "sg:classifiers":[
        {
            "category":"Real Estate",
            "subcategory":"Real Estate Agent",
            "type":"Services"
        }
    ],
    "sg:phone":"+1 954 962 1524",
    "sg:postcode":"33021",
    "sg:province":"FL",
    "sg:tags":[
        "sales"
    ],
    "wof:name":"Jhs Property Marketing Corp",
    "wof:placetype":"venue"
},
  "geometry": {"coordinates":[-80.19492099999999,26.016046],"type":"Point"}
}