{
  "type": "Feature",
  "properties": {
    "iso:country":"US",
    "sg:address":"7580 E Irlo Bronson Memorial Hwy",
    "sg:city":"Saint Cloud",
    "sg:classifiers":[
        {
            "category":"Farming",
            "subcategory":"Aquatic Farm",
            "type":"Manufacturing & Wholesale Goods"
        }
    ],
    "sg:phone":"+1 407 957 3203",
    "sg:postcode":"34771",
    "sg:province":"FL",
    "sg:tags":[
        "tropical",
        "fish"
    ],
    "wof:name":"Castelli Farms",
    "wof:placetype":"venue"
},
  "geometry": {"coordinates":[-81.119519,28.163493],"type":"Point"}
}