{
  "type": "Feature",
  "properties": {
    "iso:country":"US",
    "sg:address":"1224 E Fowler Ave",
    "sg:city":"Tampa",
    "sg:classifiers":[
        {
            "category":"Personal",
            "subcategory":"Beauty Salon",
            "type":"Services"
        }
    ],
    "sg:phone":"+1 813 910 2600",
    "sg:postcode":"33612",
    "sg:province":"FL",
    "wof:name":"Wicked Stylzz",
    "wof:placetype":"venue"
},
  "geometry": {"coordinates":[-82.445393,28.054587],"type":"Point"}
}