{
  "type": "Feature",
  "properties": {
    "addr:full":"820 SE 8th Ave Deerfield Beach FL 33441",
    "addr:housenumber":"820",
    "addr:postcode":"33441",
    "addr:street":"Se 8Th Ave",
    "iso:country":"US",
    "sg:address":"820 SE 8th Ave",
    "sg:city":"Deerfield Beach",
    "sg:classifiers":[
        {
            "category":"Organizations",
            "subcategory":"Community Association",
            "type":"Services"
        }
    ],
    "sg:phone":"+1 954 421 6097",
    "sg:postcode":"33441",
    "sg:province":"FL",
    "sg:tags":[
        "military"
    ],
    "wof:name":"American Legion",
    "wof:placetype":"venue"
},
  "geometry": {"coordinates":[-80.093856,26.306258],"type":"Point"}
}