{
  "type": "Feature",
  "properties": {
    "addr:full":"1469 Fairway Dr Perry FL 32347",
    "addr:housenumber":"1469",
    "addr:postcode":"32347",
    "addr:street":"Fairway Dr",
    "iso:country":"US",
    "sg:address":"1469 Fairway Dr",
    "sg:city":"Perry",
    "sg:classifiers":[
        {
            "category":"Professional",
            "subcategory":"Business Services",
            "type":"Services"
        }
    ],
    "sg:phone":"+1 850 584 3535",
    "sg:postcode":"32347",
    "sg:province":"FL",
    "wof:name":"A Family Affair",
    "wof:placetype":"venue"
},
  "geometry": {"coordinates":[-83.610815,30.132227],"type":"Point"}
}