{
  "type": "Feature",
  "properties": {
    "iso:country":"US",
    "sg:address":"5925 NW 167th Street",
    "sg:city":"Hialeah",
    "sg:classifiers":[
        {
            "category":"Autos & Motor Vehicles",
            "subcategory":"Automobile Sales",
            "type":"Retail Goods"
        }
    ],
    "sg:phone":"+1 305 816 1810",
    "sg:postcode":"33015",
    "sg:province":"FL",
    "sg:tags":[
        "car"
    ],
    "wof:name":"Maroone Honda of Miami",
    "wof:placetype":"venue"
},
  "geometry": {"coordinates":[-80.298135,25.926439],"type":"Point"}
}