{
  "type": "Feature",
  "properties": {
    "iso:country":"US",
    "sg:address":"370 N Beaumont Ave",
    "sg:city":"Kissimmee",
    "sg:classifiers":[
        {
            "category":"Building & Trades",
            "subcategory":"Electrical",
            "type":"Services"
        }
    ],
    "sg:phone":"+1 407 343 3000",
    "sg:postcode":"34741",
    "sg:province":"FL",
    "sg:tags":[
        "electrician",
        "contractor"
    ],
    "wof:name":"Mike Morgan Electric",
    "wof:placetype":"venue"
},
  "geometry": {"coordinates":[-81.40994499999999,28.29564],"type":"Point"}
}