{
  "type": "Feature",
  "properties": {
    "iso:country":"US",
    "sg:address":"3200 Trout River Blvd",
    "sg:city":"Jacksonville",
    "sg:classifiers":[
        {
            "category":"Shopping",
            "subcategory":"Gifts & Souvenirs",
            "type":"Retail Goods"
        }
    ],
    "sg:phone":"+1 904 764 0828",
    "sg:postcode":"32208",
    "sg:province":"FL",
    "wof:name":"Unique Creations",
    "wof:placetype":"venue"
},
  "geometry": {"coordinates":[-81.70052,30.415034],"type":"Point"}
}