{
  "type": "Feature",
  "properties": {
    "addr:full":"8027 Ridgegreen Dr Lakeland FL 33809",
    "addr:housenumber":"8027",
    "addr:postcode":"33809",
    "addr:street":"Ridgegreen Dr",
    "iso:country":"US",
    "sg:address":"8027 Ridgegreen Dr",
    "sg:city":"Lakeland",
    "sg:classifiers":[
        {
            "category":"Building & Trades",
            "subcategory":"Construction",
            "type":"Services"
        }
    ],
    "sg:phone":"+1 863 698 4365",
    "sg:postcode":"33809",
    "sg:province":"FL",
    "sg:tags":[
        "paving",
        "asphalt",
        "contractor"
    ],
    "wof:name":"Spiker's Asphalt Maintenance",
    "wof:placetype":"venue"
},
  "geometry": {"coordinates":[-81.935166,28.146151],"type":"Point"}
}