{
  "type": "Feature",
  "properties": {
    "addr:full":"3301 Cherry St Panama City FL 32401",
    "addr:housenumber":"3301",
    "addr:postcode":"32401",
    "addr:street":"Cherry St",
    "iso:country":"US",
    "sg:address":"3301 Cherry St",
    "sg:city":"Panama City",
    "sg:classifiers":[
        {
            "category":"Wholesale",
            "subcategory":"Machinery & Supplies",
            "type":"Manufacturing & Wholesale Goods"
        }
    ],
    "sg:phone":"+1 850 767 8833",
    "sg:postcode":"32401",
    "sg:province":"FL",
    "sg:tags":[
        "cleaning",
        "vacuum"
    ],
    "wof:name":"Smith Industrial Svc",
    "wof:placetype":"venue"
},
  "geometry": {"coordinates":[-85.61799499999999,30.145746],"type":"Point"}
}