{
  "type": "Feature",
  "properties": {
    "addr:full":"2111 N Federal Hwy Hollywood FL 33020",
    "addr:housenumber":"2111",
    "addr:postcode":"33020",
    "addr:street":"N Federal Hwy",
    "iso:country":"US",
    "sg:address":"2111 N Federal Hwy",
    "sg:city":"Hollywood",
    "sg:classifiers":[
        {
            "category":"Shopping",
            "type":"Retail Goods"
        }
    ],
    "sg:phone":"+1 954 925 1466",
    "sg:postcode":"33020",
    "sg:province":"FL",
    "sg:tags":[
        "pet",
        "shop"
    ],
    "wof:name":"Quality Tropicals",
    "wof:placetype":"venue"
},
  "geometry": {"coordinates":[-80.143202,26.030824],"type":"Point"}
}