{
  "type": "Feature",
  "properties": {
    "iso:country":"US",
    "sg:address":"1895 M L King Blvd",
    "sg:city":"Midway",
    "sg:classifiers":[
        {
            "category":"Personal",
            "subcategory":"Beauty Salon",
            "type":"Services"
        }
    ],
    "sg:phone":"+1 850 391 9153",
    "sg:postcode":"32343",
    "sg:province":"FL",
    "wof:name":"Oneal, Lashanda",
    "wof:placetype":"venue"
},
  "geometry": {"coordinates":[-84.463081,30.497969],"type":"Point"}
}