{
  "type": "Feature",
  "properties": {
    "iso:country":"US",
    "sg:address":"2236 1st St",
    "sg:city":"Fort Myers",
    "sg:classifiers":[
        {
            "category":"Restaurant",
            "type":"Food & Drink"
        }
    ],
    "sg:phone":"+1 239 461 0444",
    "sg:postcode":"33901",
    "sg:province":"FL",
    "sg:tags":[
        "eating"
    ],
    "wof:name":"Liquid Cafe Co Inc",
    "wof:placetype":"venue"
},
  "geometry": {"coordinates":[-81.8704,26.643952],"type":"Point"}
}