{
  "type": "Feature",
  "properties": {
    "addr:full":"21029 Cortez Blvd Brooksville FL 34601",
    "addr:housenumber":"21029",
    "addr:postcode":"34601",
    "addr:street":"Cortez Blvd",
    "iso:country":"US",
    "sg:address":"21029 Cortez Blvd",
    "sg:city":"Brooksville",
    "sg:classifiers":[
        {
            "category":"Wholesale",
            "subcategory":"Farm Supplies",
            "type":"Manufacturing & Wholesale Goods"
        }
    ],
    "sg:phone":"+1 352 796 4186",
    "sg:postcode":"34601",
    "sg:province":"FL",
    "sg:tags":[
        "feed",
        "pet",
        "garden"
    ],
    "wof:name":"Ranch Hand Seed Depot",
    "wof:placetype":"venue"
},
  "geometry": {"coordinates":[-82.38854499999999,28.538433],"type":"Point"}
}