{
  "type": "Feature",
  "properties": {
    "iso:country":"US",
    "sg:address":"800 Hunting Lodge Dr",
    "sg:city":"Miami",
    "sg:classifiers":[
        {
            "category":"Wholesale",
            "subcategory":"Books, Periodicals, & Newspapers",
            "type":"Manufacturing & Wholesale Goods"
        }
    ],
    "sg:phone":"+1 305 888 3921",
    "sg:postcode":"33166",
    "sg:province":"FL",
    "wof:name":"Soloutions 4 Inc",
    "wof:placetype":"venue"
},
  "geometry": {"coordinates":[-80.297281,25.812628],"type":"Point"}
}