{
  "type": "Feature",
  "properties": {
    "addr:full":"14054 NW 82nd Ave Hialeah FL 33016",
    "addr:housenumber":"14054",
    "addr:postcode":"33016",
    "addr:street":"Nw 82Nd Ave",
    "iso:country":"US",
    "sg:address":"14054 NW 82nd Ave",
    "sg:city":"Hialeah",
    "sg:classifiers":[
        {
            "category":"Real Estate",
            "subcategory":"Real Estate Services",
            "type":"Services"
        },
        {
            "category":"Banks & Credit Unions",
            "subcategory":"Financial Services",
            "type":"Services"
        }
    ],
    "sg:phone":"+1 305 827 2532",
    "sg:postcode":"33016",
    "sg:province":"FL",
    "sg:tags":[
        "loan",
        "processing"
    ],
    "wof:name":"Fembi Mortgage Bankers",
    "wof:placetype":"venue"
},
  "geometry": {"coordinates":[-80.332381,25.900064],"type":"Point"}
}