{
  "type": "Feature",
  "properties": {
    "iso:country":"US",
    "sg:address":"4300 McCarty Rd",
    "sg:city":"Fort Pierce",
    "sg:classifiers":[
        {
            "category":"Wholesale",
            "subcategory":"Farm Supplies",
            "type":"Manufacturing & Wholesale Goods"
        }
    ],
    "sg:phone":"+1 772 461 3035",
    "sg:postcode":"34945",
    "sg:province":"FL",
    "sg:tags":[
        "fertilizer"
    ],
    "wof:name":"Southeastern Spreader Svc Inc",
    "wof:placetype":"venue"
},
  "geometry": {"coordinates":[-80.448222,27.390101],"type":"Point"}
}