{
  "type": "Feature",
  "properties": {
    "iso:country":"US",
    "sg:address":"4505 Varsity Lakes Ct",
    "sg:city":"Lehigh Acres",
    "sg:classifiers":[
        {
            "category":"Building & Trades",
            "subcategory":"Construction",
            "type":"Services"
        }
    ],
    "sg:phone":"+1 239 690 1093",
    "sg:postcode":"33971",
    "sg:province":"FL",
    "sg:tags":[
        "house"
    ],
    "wof:name":"Eurotrace Construction Corp",
    "wof:placetype":"venue"
},
  "geometry": {"coordinates":[-81.724,26.626173],"type":"Point"}
}