{
  "type": "Feature",
  "properties": {
    "iso:country":"US",
    "sg:address":"5990 Walt Loop Rd",
    "sg:city":"Lakeland",
    "sg:classifiers":[
        {
            "category":"Freight",
            "type":"Transportation"
        }
    ],
    "sg:phone":"+1 863 858 8770",
    "sg:postcode":"33809",
    "sg:province":"FL",
    "sg:tags":[
        "general"
    ],
    "wof:name":"Sandpiper Self Storage",
    "wof:placetype":"venue"
},
  "geometry": {"coordinates":[-81.93919099999999,28.116422],"type":"Point"}
}