{
  "type": "Feature",
  "properties": {
    "addr:full":"17320 NW 18th Ave Opa Locka FL 33056",
    "addr:housenumber":"17320",
    "addr:postcode":"33056",
    "addr:street":"Nw 18Th Ave;Locka",
    "iso:country":"US",
    "sg:address":"17320 NW 18th Ave",
    "sg:city":"Opa Locka",
    "sg:classifiers":[
        {
            "category":"Wholesale",
            "subcategory":"Vending Machines",
            "type":"Manufacturing & Wholesale Goods"
        }
    ],
    "sg:phone":"+1 305 625 4376",
    "sg:postcode":"33056",
    "sg:province":"FL",
    "wof:name":"H & Z Vending",
    "wof:placetype":"venue"
},
  "geometry": {"coordinates":[-80.23094,25.933956],"type":"Point"}
}