{
  "type": "Feature",
  "properties": {
    "iso:country":"US",
    "sg:address":"1115 Cherokee St",
    "sg:city":"Jupiter",
    "sg:classifiers":[
        {
            "category":"Building & Trades",
            "subcategory":"Construction",
            "type":"Services"
        }
    ],
    "sg:phone":"+1 561 252 6764",
    "sg:postcode":"33458",
    "sg:province":"FL",
    "sg:tags":[
        "carpenter"
    ],
    "wof:name":"John A Dysard Carpentry",
    "wof:placetype":"venue"
},
  "geometry": {"coordinates":[-80.115129,26.932438],"type":"Point"}
}