{
  "type": "Feature",
  "properties": {
    "addr:full":"949 Crestview Cir Fort Lauderdale FL 33327",
    "addr:housenumber":"949",
    "addr:postcode":"33327",
    "addr:street":"Crestview Cir",
    "iso:country":"US",
    "sg:address":"949 Crestview Cir",
    "sg:city":"Fort Lauderdale",
    "sg:classifiers":[
        {
            "category":"Professional",
            "type":"Services"
        }
    ],
    "sg:phone":"+1 954 217 2036",
    "sg:postcode":"33327",
    "sg:province":"FL",
    "sg:tags":[
        "author"
    ],
    "wof:name":"Micrium Inc",
    "wof:placetype":"venue"
},
  "geometry": {"coordinates":[-80.41873,26.130315],"type":"Point"}
}