{
  "type": "Feature",
  "properties": {
    "iso:country":"US",
    "sg:address":"5719 Granada Dr",
    "sg:city":"Sarasota",
    "sg:classifiers":[
        {
            "category":"Real Estate",
            "subcategory":"Real Estate Operator",
            "type":"Services"
        }
    ],
    "sg:phone":"+1 941 921 7555",
    "sg:postcode":"34231",
    "sg:province":"FL",
    "sg:tags":[
        "specializing",
        "management",
        "apart"
    ],
    "wof:name":"Sugartree Village Apartments",
    "wof:placetype":"venue"
},
  "geometry": {"coordinates":[-82.50581699999999,27.270979],"type":"Point"}
}