{
  "type": "Feature",
  "properties": {
    "addr:full":"6384 66th St Pinellas Park FL 33781",
    "addr:housenumber":"6384",
    "addr:postcode":"33781",
    "addr:street":"66Th St",
    "iso:country":"US",
    "sg:address":"6384 66th St",
    "sg:city":"Pinellas Park",
    "sg:classifiers":[
        {
            "category":"Cinema",
            "subcategory":"Movie Rental",
            "type":"Entertainment"
        }
    ],
    "sg:phone":"+1 727 546 8717",
    "sg:postcode":"33781",
    "sg:province":"FL",
    "sg:tags":[
        "video",
        "tape"
    ],
    "sg:website":"www.hollywoodvideo.com",
    "wof:name":"Hollywood Video",
    "wof:placetype":"venue"
},
  "geometry": {"coordinates":[-82.728548,27.829948],"type":"Point"}
}