{
  "type": "Feature",
  "properties": {
    "iso:country":"US",
    "sg:address":"4545 Pleasant Hill Rd",
    "sg:city":"Kissimmee",
    "sg:classifiers":[
        {
            "category":"Health Services",
            "subcategory":"Doctor",
            "type":"Services"
        }
    ],
    "sg:phone":"+1 407 933 7900",
    "sg:postcode":"34759",
    "sg:province":"FL",
    "sg:tags":[
        "medical"
    ],
    "wof:name":"Torres-Ruiz Cecilio MD",
    "wof:placetype":"venue"
},
  "geometry": {"coordinates":[-81.440692,28.151689],"type":"Point"}
}