{
  "type": "Feature",
  "properties": {
    "iso:country":"US",
    "sg:address":"6400 Park Blvd",
    "sg:city":"Pinellas Park",
    "sg:classifiers":[
        {
            "category":"Restaurant",
            "type":"Food & Drink"
        }
    ],
    "sg:phone":"+1 727 541 2121",
    "sg:postcode":"33781",
    "sg:province":"FL",
    "sg:tags":[
        "eating"
    ],
    "wof:name":"Shang Hai Express",
    "wof:placetype":"venue"
},
  "geometry": {"coordinates":[-82.724887,27.839156],"type":"Point"}
}