{
  "type": "Feature",
  "properties": {
    "addr:full":"34918 US Hwy 19 N Palm Harbor FL 34684",
    "addr:housenumber":"34918",
    "addr:postcode":"34684",
    "addr:street":"Us Hwy 19 N",
    "iso:country":"US",
    "sg:address":"34918 US Hwy 19 N",
    "sg:city":"Palm Harbor",
    "sg:classifiers":[
        {
            "category":"Health Services",
            "subcategory":"Doctor",
            "type":"Services"
        }
    ],
    "sg:phone":"+1 727 787 7077",
    "sg:postcode":"34684",
    "sg:province":"FL",
    "sg:tags":[
        "medical"
    ],
    "wof:name":"Allan Spiegel MD PA",
    "wof:placetype":"venue"
},
  "geometry": {"coordinates":[-82.73941000000001,28.086277],"type":"Point"}
}