{
  "type": "Feature",
  "properties": {
    "iso:country":"US",
    "sg:address":"142 Stockton St",
    "sg:city":"Jacksonville",
    "sg:classifiers":[
        {
            "category":"Professional",
            "subcategory":"Business Services",
            "type":"Services"
        }
    ],
    "sg:phone":"+1 904 353 4006",
    "sg:postcode":"32204",
    "sg:province":"FL",
    "wof:name":"Auto Security Co",
    "wof:placetype":"venue"
},
  "geometry": {"coordinates":[-81.69147,30.329371],"type":"Point"}
}