{
  "type": "Feature",
  "properties": {
    "addr:full":"9908 NW 1st Ct Pompano Beach FL 33071",
    "addr:housenumber":"9908",
    "addr:postcode":"33071",
    "addr:street":"Nw 1St Ct",
    "iso:country":"US",
    "sg:address":"9908 NW 1st Ct",
    "sg:city":"Pompano Beach",
    "sg:classifiers":[
        {
            "category":"Professional",
            "subcategory":"Management & Consulting",
            "type":"Services"
        }
    ],
    "sg:phone":"+1 954 344 0855",
    "sg:postcode":"33071",
    "sg:province":"FL",
    "sg:tags":[
        "business"
    ],
    "wof:name":"Donaway & Associates Inc",
    "wof:placetype":"venue"
},
  "geometry": {"coordinates":[-80.257653,26.231618],"type":"Point"}
}