{
  "type": "Feature",
  "properties": {
    "addr:full":"251 5th St SW Winter Haven FL 33880",
    "addr:housenumber":"251",
    "addr:postcode":"33880",
    "addr:street":"5Th St Sw",
    "iso:country":"US",
    "sg:address":"251 5th St SW",
    "sg:city":"Winter Haven",
    "sg:classifiers":[
        {
            "category":"Freight",
            "type":"Transportation"
        }
    ],
    "sg:phone":"+1 863 293 0507",
    "sg:postcode":"33880",
    "sg:province":"FL",
    "sg:tags":[
        "good",
        "warehousing",
        "commercial",
        "household",
        "storage",
        "furniture"
    ],
    "wof:name":"Extra Closet",
    "wof:placetype":"venue"
},
  "geometry": {"coordinates":[-81.732164,28.020307],"type":"Point"}
}