{
  "type": "Feature",
  "properties": {
    "iso:country":"US",
    "sg:address":"3675 W 16th Ave",
    "sg:city":"Hialeah",
    "sg:classifiers":[
        {
            "category":"Shopping",
            "subcategory":"Bicycles & Sporting Goods",
            "type":"Retail Goods"
        }
    ],
    "sg:phone":"+1 305 827 5656",
    "sg:postcode":"33012",
    "sg:province":"FL",
    "wof:name":"Paintballs R US",
    "wof:placetype":"venue"
},
  "geometry": {"coordinates":[-80.314697,25.855101],"type":"Point"}
}