{
  "type": "Feature",
  "properties": {
    "addr:full":"615 S Orange Ave Sarasota FL 34236",
    "addr:housenumber":"615",
    "addr:postcode":"34236",
    "addr:street":"S Orange Ave",
    "iso:country":"US",
    "sg:address":"615 S Orange Ave",
    "sg:city":"Sarasota",
    "sg:classifiers":[
        {
            "category":"Health Services",
            "subcategory":"Optometrist",
            "type":"Services"
        }
    ],
    "sg:phone":"+1 941 366 2892",
    "sg:postcode":"34236",
    "sg:province":"FL",
    "wof:name":"Camp & Sinclair",
    "wof:placetype":"venue"
},
  "geometry": {"coordinates":[-82.538566,27.331105],"type":"Point"}
}