{
  "type": "Feature",
  "properties": {
    "addr:full":"425 N Park Ave Orange City FL 32763",
    "addr:housenumber":"425",
    "addr:postcode":"32763",
    "addr:street":"N Park Ave",
    "iso:country":"US",
    "sg:address":"425 N Park Ave",
    "sg:city":"Orange City",
    "sg:classifiers":[
        {
            "category":"Building & Trades",
            "subcategory":"Construction",
            "type":"Services"
        }
    ],
    "sg:phone":"+1 386 717 1675",
    "sg:postcode":"32763",
    "sg:province":"FL",
    "sg:tags":[
        "concrete",
        "contractor"
    ],
    "wof:name":"BBG Concrete",
    "wof:placetype":"venue"
},
  "geometry": {"coordinates":[-81.301047,28.951836],"type":"Point"}
}