{
  "type": "Feature",
  "properties": {
    "addr:full":"2873 Roxbury Rd Winter Park FL 32789",
    "addr:housenumber":"2873",
    "addr:postcode":"32789",
    "addr:street":"Roxbury Rd",
    "iso:country":"US",
    "sg:address":"2873 Roxbury Rd",
    "sg:city":"Winter Park",
    "sg:classifiers":[
        {
            "category":"Professional",
            "subcategory":"Business Services",
            "type":"Services"
        }
    ],
    "sg:phone":"+1 407 629 6339",
    "sg:postcode":"32789",
    "sg:province":"FL",
    "wof:name":"Design Tech",
    "wof:placetype":"venue"
},
  "geometry": {"coordinates":[-81.38736900000001,28.59732],"type":"Point"}
}