{
  "type": "Feature",
  "properties": {
    "addr:full":"720 Nathan Hale Rd West Palm Beach FL 33405",
    "addr:housenumber":"720",
    "addr:postcode":"33405",
    "addr:street":"Nathan Hale Rd",
    "iso:country":"US",
    "sg:address":"720 Nathan Hale Rd",
    "sg:city":"West Palm Beach",
    "sg:classifiers":[
        {
            "category":"Retail",
            "subcategory":"Repair Shop",
            "type":"Services"
        }
    ],
    "sg:phone":"+1 561 493 4007",
    "sg:postcode":"33405",
    "sg:province":"FL",
    "sg:tags":[
        "appliance"
    ],
    "wof:name":"Blast Air Conditioning",
    "wof:placetype":"venue"
},
  "geometry": {"coordinates":[-80.06168700000001,26.658868],"type":"Point"}
}