{
  "type": "Feature",
  "properties": {
    "iso:country":"US",
    "sg:address":"7225 Hallock St",
    "sg:city":"Jacksonville",
    "sg:classifiers":[
        {
            "category":"Food & Beverages",
            "subcategory":"Groceries & Convenience Stores",
            "type":"Retail Goods"
        }
    ],
    "sg:phone":"+1 904 396 4662",
    "sg:postcode":"32211",
    "sg:province":"FL",
    "wof:name":"Annie Food Mart",
    "wof:placetype":"venue"
},
  "geometry": {"coordinates":[-81.582211,30.316534],"type":"Point"}
}