{
  "type": "Feature",
  "properties": {
    "iso:country":"US",
    "sg:address":"801 Edgehill Dr",
    "sg:city":"Palm Harbor",
    "sg:classifiers":[
        {
            "category":"Building & Trades",
            "subcategory":"Construction",
            "type":"Services"
        }
    ],
    "sg:phone":"+1 727 787 7710",
    "sg:postcode":"34684",
    "sg:province":"FL",
    "sg:tags":[
        "contractor"
    ],
    "wof:name":"Pride Pressure Washing",
    "wof:placetype":"venue"
},
  "geometry": {"coordinates":[-82.729033,28.0563],"type":"Point"}
}