{
  "type": "Feature",
  "properties": {
    "addr:full":"1099 NE 45th St Fort Lauderdale FL 33334",
    "addr:housenumber":"1099",
    "addr:postcode":"33334",
    "addr:street":"Ne 45Th St",
    "iso:country":"US",
    "sg:address":"1099 NE 45th St",
    "sg:city":"Fort Lauderdale",
    "sg:classifiers":[
        {
            "category":"Retail",
            "subcategory":"Repair Shop",
            "type":"Services"
        }
    ],
    "sg:phone":"+1 954 229 1953",
    "sg:postcode":"33334",
    "sg:province":"FL",
    "sg:tags":[
        "supply"
    ],
    "wof:name":"Oakland Park Mower Repair",
    "wof:placetype":"venue"
},
  "geometry": {"coordinates":[-80.133349,26.183187],"type":"Point"}
}