{
  "type": "Feature",
  "properties": {
    "iso:country":"US",
    "sg:address":"8043 Causeway Blvd S",
    "sg:city":"Saint Petersburg",
    "sg:classifiers":[
        {
            "category":"Real Estate",
            "subcategory":"Real Estate Agent",
            "type":"Services"
        }
    ],
    "sg:phone":"+1 727 347 4149",
    "sg:postcode":"33707",
    "sg:province":"FL",
    "wof:name":"Skempris Corp",
    "wof:placetype":"venue"
},
  "geometry": {"coordinates":[-82.752,27.768359],"type":"Point"}
}