{
  "type": "Feature",
  "properties": {
    "addr:full":"2480 Hwy 71 Marianna FL 32448",
    "addr:housenumber":"2480",
    "addr:postcode":"32448",
    "addr:street":"Hwy 71",
    "iso:country":"US",
    "sg:address":"2480 Hwy 71",
    "sg:city":"Marianna",
    "sg:classifiers":[
        {
            "category":"Home & Garden",
            "subcategory":"Building Materials",
            "type":"Retail Goods"
        },
        {
            "category":"Retail",
            "subcategory":"Auto Repair",
            "type":"Services"
        }
    ],
    "sg:phone":"+1 850 482 4724",
    "sg:postcode":"32448",
    "sg:province":"FL",
    "sg:tags":[
        "plate",
        "automotive",
        "commercial",
        "glass",
        "window",
        "residential"
    ],
    "wof:name":"Tommy's Auto Glass",
    "wof:placetype":"venue"
},
  "geometry": {"coordinates":[-85.186708,30.744664],"type":"Point"}
}