{
  "type": "Feature",
  "properties": {
    "iso:country":"US",
    "sg:address":"1817 SW 102nd Pl",
    "sg:city":"Miami",
    "sg:classifiers":[
        {
            "category":"Communications",
            "subcategory":"Film & Video Production",
            "type":"Services"
        }
    ],
    "sg:phone":"+1 305 228 0825",
    "sg:postcode":"33165",
    "sg:province":"FL",
    "sg:tags":[
        "motion",
        "tv",
        "radio",
        "companies-film"
    ],
    "wof:name":"Ed Filomia Productions Inc",
    "wof:placetype":"venue"
},
  "geometry": {"coordinates":[-80.361519,25.752525],"type":"Point"}
}