{
  "type": "Feature",
  "properties": {
    "iso:country":"US",
    "sg:address":"3600 S State Rd 7",
    "sg:city":"Miramar",
    "sg:classifiers":[
        {
            "category":"Banks & Credit Unions",
            "subcategory":"Bank",
            "type":"Services"
        }
    ],
    "sg:phone":"+1 954 964 3982",
    "sg:postcode":"33023",
    "sg:province":"FL",
    "sg:tags":[
        "loan",
        "real estate"
    ],
    "wof:name":"Shaheed Agency",
    "wof:placetype":"venue"
},
  "geometry": {"coordinates":[-80.206305,25.97654],"type":"Point"}
}