{
  "type": "Feature",
  "properties": {
    "addr:full":"5752 Okeechobee Rd West Palm Beach FL 33417",
    "addr:housenumber":"5752",
    "addr:postcode":"33417",
    "addr:street":"Okeechobee Rd",
    "iso:country":"US",
    "sg:address":"5752 Okeechobee Rd",
    "sg:city":"West Palm Beach",
    "sg:classifiers":[
        {
            "category":"Insurance",
            "subcategory":"Insurance Agent",
            "type":"Services"
        }
    ],
    "sg:phone":"+1 561 296 4141",
    "sg:postcode":"33417",
    "sg:province":"FL",
    "wof:name":"America's Insurance",
    "wof:placetype":"venue"
},
  "geometry": {"coordinates":[-80.131647,26.707214],"type":"Point"}
}