{
  "type": "Feature",
  "properties": {
    "addr:full":"18021 Biscayne Blvd Miami FL 33160",
    "addr:housenumber":"18021",
    "addr:postcode":"33160",
    "addr:street":"Biscayne Blvd",
    "iso:country":"US",
    "sg:address":"18021 Biscayne Blvd",
    "sg:city":"Miami",
    "sg:classifiers":[
        {
            "category":"Banks & Credit Unions",
            "subcategory":"Financial Services",
            "type":"Services"
        }
    ],
    "sg:phone":"+1 305 792 5152",
    "sg:postcode":"33160",
    "sg:province":"FL",
    "sg:tags":[
        "investor"
    ],
    "wof:name":"Wanderlust Investments Inc",
    "wof:placetype":"venue"
},
  "geometry": {"coordinates":[-80.148769,25.941446],"type":"Point"}
}