{
  "type": "Feature",
  "properties": {
    "iso:country":"US",
    "sg:address":"4001 Smith Ryals Rd",
    "sg:city":"Plant City",
    "sg:classifiers":[
        {
            "category":"Wholesale",
            "subcategory":"Plants",
            "type":"Manufacturing & Wholesale Goods"
        },
        {
            "category":"Home & Garden",
            "subcategory":"Garden Supply",
            "type":"Retail Goods"
        }
    ],
    "sg:phone":"+1 813 737 1909",
    "sg:postcode":"33567",
    "sg:province":"FL",
    "sg:tags":[
        "nurseryman"
    ],
    "wof:name":"Forte Nursery Inc",
    "wof:placetype":"venue"
},
  "geometry": {"coordinates":[-82.088589,27.957545],"type":"Point"}
}