{
  "type": "Feature",
  "properties": {
    "iso:country":"US",
    "sg:address":"1359 NE 95th St",
    "sg:city":"Ocala",
    "sg:classifiers":[
        {
            "category":"Building & Trades",
            "subcategory":"Cleaning & Sanitation",
            "type":"Services"
        }
    ],
    "sg:phone":"+1 352 690 6627",
    "sg:postcode":"34479",
    "sg:province":"FL",
    "sg:tags":[
        "janitor"
    ],
    "wof:name":"Courtney Sapp Cleaning Svc",
    "wof:placetype":"venue"
},
  "geometry": {"coordinates":[-82.11965600000001,29.28858],"type":"Point"}
}