{
  "type": "Feature",
  "properties": {
    "iso:country":"US",
    "sg:address":"11231 NW 20th St",
    "sg:city":"Miami",
    "sg:classifiers":[
        {
            "category":"Food & Beverages",
            "subcategory":"Groceries & Convenience Stores",
            "type":"Retail Goods"
        }
    ],
    "sg:phone":"+1 305 591 9115",
    "sg:postcode":"33172",
    "sg:province":"FL",
    "wof:name":"Food Innovations",
    "wof:placetype":"venue"
},
  "geometry": {"coordinates":[-80.37794100000001,25.792749],"type":"Point"}
}