{
  "type": "Feature",
  "properties": {
    "iso:country":"US",
    "sg:address":"2479 State Hwy 207",
    "sg:city":"St Augustine",
    "sg:classifiers":[
        {
            "category":"Autos & Motor Vehicles",
            "subcategory":"Automobile Sales",
            "type":"Retail Goods"
        }
    ],
    "sg:phone":"+1 904 827 0089",
    "sg:postcode":"32086",
    "sg:province":"FL",
    "sg:tags":[
        "truck"
    ],
    "sg:website":"www.trksrus.com",
    "wof:name":"Shaw Hallman Enterprises Inc",
    "wof:placetype":"venue"
},
  "geometry": {"coordinates":[-81.37657,29.828726],"type":"Point"}
}