{
  "type": "Feature",
  "properties": {
    "addr:full":"1255 Commerce Blvd Midway FL 32343",
    "addr:housenumber":"1255",
    "addr:postcode":"32343",
    "addr:street":"Commerce Blvd",
    "iso:country":"US",
    "sg:address":"1255 Commerce Blvd",
    "sg:city":"Midway",
    "sg:classifiers":[
        {
            "category":"Building & Trades",
            "subcategory":"Construction",
            "type":"Services"
        }
    ],
    "sg:phone":"+1 850 514 1006",
    "sg:postcode":"32343",
    "sg:province":"FL",
    "sg:tags":[
        "commercial"
    ],
    "sg:website":"www.cookbrothersinc.com",
    "wof:name":"Cook Brothers Inc",
    "wof:placetype":"venue"
},
  "geometry": {"coordinates":[-84.418477,30.493657],"type":"Point"}
}