{
  "type": "Feature",
  "properties": {
    "addr:full":"1501 Lutterloh Rd Tallahassee FL 32305",
    "addr:housenumber":"1501",
    "addr:postcode":"32305",
    "addr:street":"Lutterloh Rd",
    "iso:country":"US",
    "sg:address":"1501 Lutterloh Rd",
    "sg:city":"Tallahassee",
    "sg:classifiers":[
        {
            "category":"Organizations",
            "subcategory":"Religious Organization",
            "type":"Services"
        }
    ],
    "sg:phone":"+1 850 421 1444",
    "sg:postcode":"32305",
    "sg:province":"FL",
    "sg:tags":[
        "place",
        "worship",
        "church"
    ],
    "wof:name":"Galilee Ame Church",
    "wof:placetype":"venue"
},
  "geometry": {"coordinates":[-84.25289100000001,30.329831],"type":"Point"}
}