{
  "type": "Feature",
  "properties": {
    "addr:full":"1209 Calhoun Ave Panama City FL 32401",
    "addr:housenumber":"1209",
    "addr:postcode":"32401",
    "addr:street":"Calhoun Ave",
    "iso:country":"US",
    "sg:address":"1209 Calhoun Ave",
    "sg:city":"Panama City",
    "sg:classifiers":[
        {
            "category":"Real Estate",
            "subcategory":"Real Estate Operator",
            "type":"Services"
        }
    ],
    "sg:phone":"+1 850 785 6761",
    "sg:postcode":"32401",
    "sg:province":"FL",
    "sg:tags":[
        "apartment"
    ],
    "wof:name":"Fred Anderson Rental Apartment",
    "wof:placetype":"venue"
},
  "geometry": {"coordinates":[-85.69431899999999,30.171621],"type":"Point"}
}