{
  "type": "Feature",
  "properties": {
    "iso:country":"US",
    "sg:address":"11862 Anchorage Way",
    "sg:city":"Boca Raton",
    "sg:classifiers":[
        {
            "category":"Building & Trades",
            "subcategory":"Construction",
            "type":"Services"
        }
    ],
    "sg:phone":"+1 561 477 0794",
    "sg:postcode":"33428",
    "sg:province":"FL",
    "wof:name":"D & O Topping Inc",
    "wof:placetype":"venue"
},
  "geometry": {"coordinates":[-80.217169,26.334028],"type":"Point"}
}