{
  "type": "Feature",
  "properties": {
    "iso:country":"US",
    "sg:address":"1920 Atwood Dr",
    "sg:city":"Pensacola",
    "sg:classifiers":[
        {
            "category":"Building & Trades",
            "subcategory":"Equipment Rental",
            "type":"Services"
        }
    ],
    "sg:phone":"+1 850 477 1899",
    "sg:postcode":"32514",
    "sg:province":"FL",
    "wof:name":"Adams Rentals",
    "wof:placetype":"venue"
},
  "geometry": {"coordinates":[-87.21986200000001,30.506349],"type":"Point"}
}