{
  "type": "Feature",
  "properties": {
    "addr:full":"11875 High Tech Ave Orlando FL 32817",
    "addr:housenumber":"11875",
    "addr:postcode":"32817",
    "addr:street":"High Tech Ave",
    "iso:country":"US",
    "sg:address":"11875 High Tech Ave",
    "sg:city":"Orlando",
    "sg:classifiers":[
        {
            "category":"Professional",
            "subcategory":"Research",
            "type":"Services"
        }
    ],
    "sg:phone":"+1 407 381 8255",
    "sg:postcode":"32817",
    "sg:province":"FL",
    "sg:tags":[
        "automobile",
        "commercial",
        "physical"
    ],
    "wof:name":"S R G",
    "wof:placetype":"venue"
},
  "geometry": {"coordinates":[-81.21354700000001,28.599312],"type":"Point"}
}