{
  "type": "Feature",
  "properties": {
    "iso:country":"US",
    "sg:address":"1231 Kindel Ave",
    "sg:city":"Winter Park",
    "sg:classifiers":[
        {
            "category":"Building & Trades",
            "subcategory":"Construction",
            "type":"Services"
        }
    ],
    "sg:phone":"+1 407 647 2334",
    "sg:postcode":"32789",
    "sg:province":"FL",
    "sg:tags":[
        "contractor"
    ],
    "wof:name":"Vanson Enterprises Inc",
    "wof:placetype":"venue"
},
  "geometry": {"coordinates":[-81.365402,28.6073],"type":"Point"}
}