{
  "type": "Feature",
  "properties": {
    "addr:full":"2027 US Hwy 27 Sebring FL 33870",
    "addr:housenumber":"2027",
    "addr:postcode":"33870",
    "addr:street":"Us Hwy 27",
    "iso:country":"US",
    "sg:address":"2027 US Hwy 27",
    "sg:city":"Sebring",
    "sg:classifiers":[
        {
            "category":"Insurance",
            "subcategory":"Insurance Agent",
            "type":"Services"
        }
    ],
    "sg:phone":"+1 863 385 3936",
    "sg:postcode":"33870",
    "sg:province":"FL",
    "wof:name":"Allstate",
    "wof:placetype":"venue"
},
  "geometry": {"coordinates":[-81.45310499999999,27.471578],"type":"Point"}
}