{
  "type": "Feature",
  "properties": {
    "addr:full":"116 S Pinellas Ave Tarpon Springs FL 34689",
    "addr:housenumber":"116",
    "addr:postcode":"34689",
    "addr:street":"S Pinellas Ave",
    "iso:country":"US",
    "sg:address":"116 S Pinellas Ave",
    "sg:city":"Tarpon Springs",
    "sg:classifiers":[
        {
            "category":"Banks & Credit Unions",
            "subcategory":"Bank",
            "type":"Services"
        }
    ],
    "sg:phone":"+1 727 934 4638",
    "sg:postcode":"34689",
    "sg:province":"FL",
    "sg:tags":[
        "national",
        "commercial"
    ],
    "wof:name":"Bank Of America",
    "wof:placetype":"venue"
},
  "geometry": {"coordinates":[-82.75662699999999,28.144993],"type":"Point"}
}