{
  "type": "Feature",
  "properties": {
    "addr:full":"2135 Margarita Dr Lady Lake FL 32159",
    "addr:postcode":"2135;32159",
    "addr:street":"Margarita Dr",
    "iso:country":"US",
    "sg:address":"2135 Margarita Dr",
    "sg:city":"Lady Lake",
    "sg:classifiers":[
        {
            "category":"Shopping",
            "subcategory":"Shoes",
            "type":"Retail Goods"
        }
    ],
    "sg:phone":"+1 352 750 9965",
    "sg:postcode":"32159",
    "sg:province":"FL",
    "sg:tags":[
        "shoe",
        "store"
    ],
    "wof:name":"Red Wing Shoe Store",
    "wof:placetype":"venue"
},
  "geometry": {"coordinates":[-81.980835,28.949392],"type":"Point"}
}