{
  "type": "Feature",
  "properties": {
    "iso:country":"US",
    "sg:address":"1041 NW 33rd Ave",
    "sg:city":"Miami",
    "sg:classifiers":[
        {
            "category":"Organizations",
            "subcategory":"Community Association",
            "type":"Services"
        }
    ],
    "sg:phone":"+1 305 642 0096",
    "sg:postcode":"33125",
    "sg:province":"FL",
    "wof:name":"Hispanic Fighters Assoc Hfa In",
    "wof:placetype":"venue"
},
  "geometry": {"coordinates":[-80.250114,25.780003],"type":"Point"}
}