{
  "type": "Feature",
  "properties": {
    "iso:country":"US",
    "sg:address":"1754 NE 58th St",
    "sg:city":"Fort Lauderdale",
    "sg:phone":"+1 954 491 1793",
    "sg:postcode":"33334",
    "sg:province":"FL",
    "sg:tags":[
        "equipment",
        "commercial"
    ],
    "wof:name":"AB Fire Equipment Inc",
    "wof:placetype":"venue"
},
  "geometry": {"coordinates":[-80.123206,26.199308],"type":"Point"}
}