{
  "type": "Feature",
  "properties": {
    "iso:country":"US",
    "sg:address":"8416 Sheldon Rd",
    "sg:city":"Tampa",
    "sg:classifiers":[
        {
            "category":"Personal",
            "subcategory":"Beauty Salon",
            "type":"Services"
        }
    ],
    "sg:phone":"+1 813 806 9404",
    "sg:postcode":"33615",
    "sg:province":"FL",
    "wof:name":"First Choice Haircutters",
    "wof:placetype":"venue"
},
  "geometry": {"coordinates":[-82.583079,28.028081],"type":"Point"}
}