{
  "type": "Feature",
  "properties": {
    "iso:country":"US",
    "sg:address":"34106 State Rd 54",
    "sg:city":"Zephyrhills",
    "sg:classifiers":[
        {
            "category":"Social Services",
            "subcategory":"Child Care",
            "type":"Services"
        }
    ],
    "sg:phone":"+1 813 779 2767",
    "sg:postcode":"33543",
    "sg:province":"FL",
    "sg:tags":[
        "center"
    ],
    "wof:name":"Little People Christian Day",
    "wof:placetype":"venue"
},
  "geometry": {"coordinates":[-82.252182,28.218711],"type":"Point"}
}