{
  "type": "Feature",
  "properties": {
    "iso:country":"US",
    "sg:address":"15669 60th Pl N",
    "sg:city":"Loxahatchee",
    "sg:classifiers":[
        {
            "category":"Banks & Credit Unions",
            "subcategory":"Investment Brokerage",
            "type":"Services"
        }
    ],
    "sg:phone":"+1 239 565 0741",
    "sg:postcode":"33470",
    "sg:province":"FL",
    "sg:tags":[
        "advisory"
    ],
    "wof:name":"Rrim Investments",
    "wof:placetype":"venue"
},
  "geometry": {"coordinates":[-80.28993,26.766587],"type":"Point"}
}