{
  "type": "Feature",
  "properties": {
    "addr:full":"1903 S Monroe St Tallahassee FL 32301",
    "addr:housenumber":"1903",
    "addr:postcode":"32301",
    "addr:street":"S Monroe St",
    "iso:country":"US",
    "sg:address":"1903 S Monroe St",
    "sg:city":"Tallahassee",
    "sg:classifiers":[
        {
            "category":"Retail",
            "subcategory":"Auto Repair",
            "type":"Services"
        }
    ],
    "sg:phone":"+1 850 681 7569",
    "sg:postcode":"32301",
    "sg:province":"FL",
    "sg:tags":[
        "body",
        "automobile",
        "painting"
    ],
    "wof:name":"Frank Odom Auto Body",
    "wof:placetype":"venue"
},
  "geometry": {"coordinates":[-84.280575,30.426074],"type":"Point"}
}