{
  "type": "Feature",
  "properties": {
    "addr:full":"3000 Old Chemstrand Rd Cantonment FL 32533",
    "addr:housenumber":"3000",
    "addr:postcode":"32533",
    "addr:street":"Old Chemstrand Rd",
    "iso:country":"US",
    "sg:address":"3000 Old Chemstrand Rd",
    "sg:city":"Cantonment",
    "sg:classifiers":[
        {
            "category":"Wholesale",
            "subcategory":"Hardware",
            "type":"Manufacturing & Wholesale Goods"
        }
    ],
    "sg:phone":"+1 850 968 2333",
    "sg:postcode":"32533",
    "sg:province":"FL",
    "sg:tags":[
        "used",
        "boiler"
    ],
    "wof:name":"National Boiler",
    "wof:placetype":"venue"
},
  "geometry": {"coordinates":[-87.262415,30.589126],"type":"Point"}
}