{
  "type": "Feature",
  "properties": {
    "addr:full":"13346 Lincoln Rd Riverview FL 33578",
    "addr:housenumber":"13346",
    "addr:postcode":"33578",
    "addr:street":"Lincoln Rd",
    "iso:country":"US",
    "sg:address":"13346 Lincoln Rd",
    "sg:city":"Riverview",
    "sg:classifiers":[
        {
            "category":"Shopping",
            "subcategory":"Hobbies, Toys, & Games",
            "type":"Retail Goods"
        }
    ],
    "sg:phone":"+1 813 234 0899",
    "sg:postcode":"33578",
    "sg:province":"FL",
    "sg:tags":[
        "shop",
        "hobby",
        "model",
        "supply"
    ],
    "wof:name":"Hobby Zone",
    "wof:placetype":"venue"
},
  "geometry": {"coordinates":[-82.34175,27.790312],"type":"Point"}
}