{
  "type": "Feature",
  "properties": {
    "addr:full":"588 Floral Dr Kissimmee FL 34743",
    "addr:housenumber":"588",
    "addr:postcode":"34743",
    "addr:street":"Floral Dr",
    "iso:country":"US",
    "sg:address":"588 Floral Dr",
    "sg:city":"Kissimmee",
    "sg:classifiers":[
        {
            "category":"Retail",
            "subcategory":"Repair Shop",
            "type":"Services"
        }
    ],
    "sg:phone":"+1 407 348 4139",
    "sg:postcode":"34743",
    "sg:province":"FL",
    "wof:name":"Victoria M Tejada Cleanin",
    "wof:placetype":"venue"
},
  "geometry": {"coordinates":[-81.36078500000001,28.320004],"type":"Point"}
}