{
  "type": "Feature",
  "properties": {
    "iso:country":"US",
    "sg:address":"2828 Coral Way",
    "sg:city":"Coral Gables",
    "sg:classifiers":[
        {
            "category":"Real Estate",
            "subcategory":"Real Estate Services",
            "type":"Services"
        }
    ],
    "sg:phone":"+1 305 445 4032",
    "sg:postcode":"33145",
    "sg:province":"FL",
    "sg:tags":[
        "management",
        "property"
    ],
    "wof:name":"Jag Ventures",
    "wof:placetype":"venue"
},
  "geometry": {"coordinates":[-80.239875,25.750052],"type":"Point"}
}