{
  "type": "Feature",
  "properties": {
    "addr:full":"24181 S Tamiami Trl Bonita Springs FL 34134",
    "addr:housenumber":"24181",
    "addr:postcode":"34134",
    "addr:street":"S Tamiami Trl",
    "iso:country":"US",
    "sg:address":"24181 S Tamiami Trl",
    "sg:city":"Bonita Springs",
    "sg:classifiers":[
        {
            "category":"Wholesale",
            "subcategory":"Sporting Goods",
            "type":"Manufacturing & Wholesale Goods"
        }
    ],
    "sg:phone":"+1 239 948 9840",
    "sg:postcode":"34134",
    "sg:province":"FL",
    "sg:tags":[
        "equipment",
        "retail",
        "golf"
    ],
    "wof:name":"Golf Ball Warehouse Inc",
    "wof:placetype":"venue"
},
  "geometry": {"coordinates":[-81.809809,26.390475],"type":"Point"}
}