{
  "type": "Feature",
  "properties": {
    "iso:country":"US",
    "sg:address":"2133 Broadway",
    "sg:city":"Fort Myers",
    "sg:classifiers":[
        {
            "category":"Manufacturing",
            "subcategory":"Printing",
            "type":"Manufacturing & Wholesale Goods"
        }
    ],
    "sg:phone":"+1 239 334 1118",
    "sg:postcode":"33901",
    "sg:province":"FL",
    "sg:tags":[
        "commercial"
    ],
    "wof:name":"Ace Press Inc",
    "wof:placetype":"venue"
},
  "geometry": {"coordinates":[-81.868459,26.637293],"type":"Point"}
}