{
  "type": "Feature",
  "properties": {
    "addr:full":"1140 NE Dixie Hwy Jensen Beach FL 34957",
    "addr:housenumber":"1140",
    "addr:postcode":"34957",
    "addr:street":"Ne Dixie Hwy",
    "iso:country":"US",
    "sg:address":"1140 NE Dixie Hwy",
    "sg:city":"Jensen Beach",
    "sg:classifiers":[
        {
            "category":"Retail",
            "subcategory":"Auto Repair",
            "type":"Services"
        }
    ],
    "sg:phone":"+1 772 232 2668",
    "sg:postcode":"34957",
    "sg:province":"FL",
    "sg:tags":[
        "general"
    ],
    "wof:name":"Boot & The Bonnet",
    "wof:placetype":"venue"
},
  "geometry": {"coordinates":[-80.237037,27.219503],"type":"Point"}
}