{
  "type": "Feature",
  "properties": {
    "iso:country":"US",
    "sg:address":"317 E Nine Mile Rd",
    "sg:city":"Pensacola",
    "sg:classifiers":[
        {
            "category":"Autos & Motor Vehicles",
            "subcategory":"Auto Supplies",
            "type":"Retail Goods"
        }
    ],
    "sg:phone":"+1 850 476 6530",
    "sg:postcode":"32514",
    "sg:province":"FL",
    "sg:tags":[
        "automotive",
        "tire",
        "repair"
    ],
    "wof:name":"Big 10 Tires 2",
    "wof:placetype":"venue"
},
  "geometry": {"coordinates":[-87.25914400000001,30.532858],"type":"Point"}
}