{
  "type": "Feature",
  "properties": {
    "iso:country":"US",
    "sg:address":"1866 Buford Blvd",
    "sg:city":"Tallahassee",
    "sg:classifiers":[
        {
            "category":"Health Services",
            "subcategory":"Podiatrist",
            "type":"Services"
        }
    ],
    "sg:phone":"+1 850 878 6998",
    "sg:postcode":"32308",
    "sg:province":"FL",
    "sg:website":"www.tallahasseepodiatry.com",
    "wof:name":"Tallahassee Podiatry Assoc",
    "wof:placetype":"venue"
},
  "geometry": {"coordinates":[-84.232544,30.474866],"type":"Point"}
}