{
  "type": "Feature",
  "properties": {
    "addr:full":"6409 Manatee Ave W Bradenton FL 34209",
    "addr:housenumber":"6409",
    "addr:postcode":"34209",
    "addr:street":"Manatee Ave W",
    "iso:country":"US",
    "sg:address":"6409 Manatee Ave W",
    "sg:city":"Bradenton",
    "sg:classifiers":[
        {
            "category":"Restaurant",
            "type":"Food & Drink"
        }
    ],
    "sg:phone":"+1 941 792 4997",
    "sg:postcode":"34209",
    "sg:province":"FL",
    "sg:tags":[
        "caterer"
    ],
    "wof:name":"Broadway Catering",
    "wof:placetype":"venue"
},
  "geometry": {"coordinates":[-82.630261,27.4959],"type":"Point"}
}