{
  "type": "Feature",
  "properties": {
    "addr:full":"4735 Brady Ln Palm Beach Gardens FL 33418",
    "addr:housenumber":"4735",
    "addr:postcode":"33418",
    "addr:street":"Brady Ln",
    "iso:country":"US",
    "sg:address":"4735 Brady Ln",
    "sg:city":"Palm Beach Gardens",
    "sg:classifiers":[
        {
            "category":"Banks & Credit Unions",
            "subcategory":"Investment Brokerage",
            "type":"Services"
        }
    ],
    "sg:phone":"+1 561 775 7174",
    "sg:postcode":"33418",
    "sg:province":"FL",
    "sg:tags":[
        "brokerage",
        "firm",
        "real estate"
    ],
    "wof:name":"Rlf Realty Inc",
    "wof:placetype":"venue"
},
  "geometry": {"coordinates":[-80.107867,26.813979],"type":"Point"}
}