{
  "type": "Feature",
  "properties": {
    "addr:full":"15821 Beachcomber Ave Fort Myers FL 33908",
    "addr:housenumber":"15821",
    "addr:postcode":"33908",
    "addr:street":"Beachcomber Ave",
    "iso:country":"US",
    "sg:address":"15821 Beachcomber Ave",
    "sg:city":"Fort Myers",
    "sg:classifiers":[
        {
            "category":"Wholesale",
            "subcategory":"Electrical",
            "type":"Manufacturing & Wholesale Goods"
        }
    ],
    "sg:phone":"+1 239 489 1148",
    "sg:postcode":"33908",
    "sg:province":"FL",
    "sg:tags":[
        "electronic"
    ],
    "wof:name":"Marconi Communications Inc",
    "wof:placetype":"venue"
},
  "geometry": {"coordinates":[-81.941851,26.511827],"type":"Point"}
}