{
  "type": "Feature",
  "properties": {
    "addr:full":"1106 W Pine St Orlando FL 32805",
    "addr:housenumber":"1106",
    "addr:postcode":"32805",
    "addr:street":"W Pine St",
    "iso:country":"US",
    "sg:address":"1106 W Pine St",
    "sg:city":"Orlando",
    "sg:classifiers":[
        {
            "category":"Autos & Motor Vehicles",
            "subcategory":"Auto Supplies",
            "type":"Retail Goods"
        },
        {
            "category":"Wholesale",
            "subcategory":"Electrical",
            "type":"Manufacturing & Wholesale Goods"
        },
        {
            "category":"Wholesale",
            "subcategory":"Auto Parts",
            "type":"Manufacturing & Wholesale Goods"
        }
    ],
    "sg:phone":"+1 407 423 5157",
    "sg:postcode":"32805",
    "sg:province":"FL",
    "sg:tags":[
        "battery",
        "automobile",
        "accessory",
        "equipment",
        "truck",
        "engines-supplies"
    ],
    "sg:website":"http://ad.doubleclick.net/clk;221862232;45455595;j?http://www.carquest.com/carquest/store_locator.html",
    "wof:name":"CARQUEST Auto Parts",
    "wof:placetype":"venue"
},
  "geometry": {"coordinates":[-81.394611,28.541059],"type":"Point"}
}