{
  "type": "Feature",
  "properties": {
    "iso:country":"US",
    "sg:address":"2118 Bay St",
    "sg:city":"Fort Myers",
    "sg:classifiers":[
        {
            "category":"Parking",
            "type":"Transportation"
        }
    ],
    "sg:phone":"+1 239 337 1990",
    "sg:postcode":"33901",
    "sg:province":"FL",
    "sg:tags":[
        "garage"
    ],
    "wof:name":"Standard Parking",
    "wof:placetype":"venue"
},
  "geometry": {"coordinates":[-81.871718,26.644068],"type":"Point"}
}