{
  "type": "Feature",
  "properties": {
    "addr:full":"4018 W Vine St Kissimmee FL 34741",
    "addr:housenumber":"4018",
    "addr:postcode":"34741",
    "addr:street":"W Vine St",
    "iso:country":"US",
    "sg:address":"4018 W Vine St",
    "sg:city":"Kissimmee",
    "sg:classifiers":[
        {
            "category":"Travel",
            "subcategory":"Hotels & Motels",
            "type":"Entertainment"
        }
    ],
    "sg:phone":"+1 407 870 2000",
    "sg:postcode":"34741",
    "sg:province":"FL",
    "wof:name":"Best Western",
    "wof:placetype":"venue"
},
  "geometry": {"coordinates":[-81.444101,28.304326],"type":"Point"}
}