{
  "type": "Feature",
  "properties": {
    "addr:full":"6206 N 17th St Tampa FL 33610",
    "addr:housenumber":"6206",
    "addr:postcode":"33610",
    "addr:street":"N 17Th St",
    "iso:country":"US",
    "sg:address":"6206 N 17th St",
    "sg:city":"Tampa",
    "sg:classifiers":[
        {
            "category":"Building & Trades",
            "subcategory":"Construction",
            "type":"Services"
        }
    ],
    "sg:phone":"+1 813 234 3729",
    "sg:postcode":"33610",
    "sg:province":"FL",
    "sg:tags":[
        "general",
        "contractor"
    ],
    "wof:name":"Dangelo Constructions",
    "wof:placetype":"venue"
},
  "geometry": {"coordinates":[-82.44098,28.004132],"type":"Point"}
}