{
  "type": "Feature",
  "properties": {
    "addr:full":"38924 C Ave Zephyrhills FL 33542",
    "addr:housenumber":"38924",
    "addr:postcode":"33542",
    "addr:street":"C Ave",
    "iso:country":"US",
    "sg:address":"38924 C Ave",
    "sg:city":"Zephyrhills",
    "sg:classifiers":[
        {
            "category":"Organizations",
            "subcategory":"Religious Organization",
            "type":"Services"
        }
    ],
    "sg:phone":"+1 813 782 7510",
    "sg:postcode":"33542",
    "sg:province":"FL",
    "sg:website":"www.zhillswesleyan.org",
    "wof:name":"Zephyrhills Wesleyan Church",
    "wof:placetype":"venue"
},
  "geometry": {"coordinates":[-82.170557,28.226412],"type":"Point"}
}