{
  "type": "Feature",
  "properties": {
    "iso:country":"US",
    "sg:address":"262 Parkland Ave",
    "sg:city":"Sarasota",
    "sg:classifiers":[
        {
            "category":"Building & Trades",
            "subcategory":"Construction",
            "type":"Services"
        }
    ],
    "sg:phone":"+1 941 371 6372",
    "sg:postcode":"34232",
    "sg:province":"FL",
    "sg:tags":[
        "carpentry",
        "contractor"
    ],
    "wof:name":"MRM Carpentry Inc",
    "wof:placetype":"venue"
},
  "geometry": {"coordinates":[-82.49606799999999,27.33298],"type":"Point"}
}