{
  "type": "Feature",
  "properties": {
    "addr:full":"7500 Dr Phillips Blvd Orlando FL 32819",
    "addr:housenumber":"7500",
    "addr:postcode":"32819",
    "addr:street":"Dr Phillips Blvd",
    "iso:country":"US",
    "sg:address":"7500 Dr Phillips Blvd",
    "sg:city":"Orlando",
    "sg:classifiers":[
        {
            "category":"Local Transit",
            "type":"Transportation"
        }
    ],
    "sg:phone":"+1 407 295 2667",
    "sg:postcode":"32819",
    "sg:province":"FL",
    "sg:tags":[
        "limousine"
    ],
    "wof:name":"Executive Transportation",
    "wof:placetype":"venue"
},
  "geometry": {"coordinates":[-81.48815999999999,28.453669],"type":"Point"}
}