{
  "type": "Feature",
  "properties": {
    "addr:full":"9000 SW 50th Pl Cooper City FL 33328",
    "addr:housenumber":"9000",
    "addr:postcode":"33328",
    "addr:street":"Sw 50Th Pl",
    "iso:country":"US",
    "sg:address":"9000 SW 50th Pl",
    "sg:city":"Cooper City",
    "sg:classifiers":[
        {
            "category":"Government",
            "subcategory":"Office",
            "type":"Public Place"
        }
    ],
    "sg:phone":"+1 954 252 9069",
    "sg:postcode":"33328",
    "sg:province":"FL",
    "sg:tags":[
        "county"
    ],
    "wof:name":"Broward County Supervisor",
    "wof:placetype":"venue"
},
  "geometry": {"coordinates":[-80.271496,26.058895],"type":"Point"}
}