{
  "type": "Feature",
  "properties": {
    "addr:full":"1443 del Prado Blvd S Cape Coral FL 33990",
    "addr:housenumber":"1443",
    "addr:postcode":"33990",
    "addr:street":"Del Prado Blvd S",
    "iso:country":"US",
    "sg:address":"1443 del Prado Blvd S",
    "sg:city":"Cape Coral",
    "sg:classifiers":[
        {
            "category":"Building & Trades",
            "subcategory":"Construction",
            "type":"Services"
        }
    ],
    "sg:phone":"+1 239 549 7877",
    "sg:postcode":"33990",
    "sg:province":"FL",
    "sg:tags":[
        "home",
        "builder"
    ],
    "wof:name":"Carousel Home Builders",
    "wof:placetype":"venue"
},
  "geometry": {"coordinates":[-81.940624,26.624869],"type":"Point"}
}