{
  "type": "Feature",
  "properties": {
    "iso:country":"US",
    "sg:address":"507 S Waukesha St",
    "sg:city":"Bonifay",
    "sg:classifiers":[
        {
            "category":"Insurance",
            "subcategory":"Insurance Agent",
            "type":"Services"
        }
    ],
    "sg:phone":"+1 850 547 4222",
    "sg:postcode":"32425",
    "sg:province":"FL",
    "wof:name":"Durant Insurance Inc",
    "wof:placetype":"venue"
},
  "geometry": {"coordinates":[-85.67996100000001,30.785464],"type":"Point"}
}