{
  "type": "Feature",
  "properties": {
    "iso:country":"US",
    "sg:address":"7376 W 20th Ave Ste 148",
    "sg:city":"Hialeah",
    "sg:classifiers":[
        {
            "category":"Shopping",
            "subcategory":"Clothing, Apparel, & Fashions",
            "type":"Retail Goods"
        }
    ],
    "sg:phone":"+1 305 556 6906",
    "sg:postcode":"33016",
    "sg:province":"FL",
    "sg:tags":[
        "children's",
        "clothing"
    ],
    "wof:name":"Designs by Ana M",
    "wof:placetype":"venue"
},
  "geometry": {"coordinates":[-80.32454199999999,25.889498],"type":"Point"}
}