{
  "type": "Feature",
  "properties": {
    "iso:country":"US",
    "sg:address":"6814 46th Ave N",
    "sg:city":"St Petersburg",
    "sg:classifiers":[
        {
            "category":"Retail",
            "subcategory":"Repair Shop",
            "type":"Services"
        }
    ],
    "sg:phone":"+1 727 541 3158",
    "sg:postcode":"33709",
    "sg:province":"FL",
    "sg:tags":[
        "scooter",
        "motorcycle",
        "motor"
    ],
    "wof:name":"Westcoast Motorcycle Sales",
    "wof:placetype":"venue"
},
  "geometry": {"coordinates":[-82.733378,27.813639],"type":"Point"}
}