{
  "type": "Feature",
  "properties": {
    "addr:full":"205 Montgomery Ave Sarasota FL 34243",
    "addr:housenumber":"205",
    "addr:postcode":"34243",
    "addr:street":"Montgomery Ave",
    "iso:country":"US",
    "sg:address":"205 Montgomery Ave",
    "sg:city":"Sarasota",
    "sg:classifiers":[
        {
            "category":"Manufacturing",
            "subcategory":"Tools & Machinery",
            "type":"Manufacturing & Wholesale Goods"
        }
    ],
    "sg:phone":"+1 941 359 9990",
    "sg:postcode":"34243",
    "sg:province":"FL",
    "sg:tags":[
        "physician",
        "surgeon"
    ],
    "sg:website":"www.soundparts.com",
    "wof:name":"Sound Parts",
    "wof:placetype":"venue"
},
  "geometry": {"coordinates":[-82.57289299999999,27.413575],"type":"Point"}
}