{
  "type": "Feature",
  "properties": {
    "iso:country":"US",
    "sg:address":"1620 Tay Ct",
    "sg:city":"Palm Harbor",
    "sg:classifiers":[
        {
            "category":"Professional",
            "subcategory":"Management & Consulting",
            "type":"Services"
        }
    ],
    "sg:phone":"+1 727 785 3994",
    "sg:postcode":"34684",
    "sg:province":"FL",
    "sg:tags":[
        "import",
        "marketing"
    ],
    "wof:name":"T Amazon Inc",
    "wof:placetype":"venue"
},
  "geometry": {"coordinates":[-82.720085,28.082728],"type":"Point"}
}