{
  "type": "Feature",
  "properties": {
    "addr:full":"5297 Shoffner Blvd Crestview FL 32539",
    "addr:housenumber":"5297",
    "addr:postcode":"32539",
    "addr:street":"Shoffner Blvd",
    "iso:country":"US",
    "sg:address":"5297 Shoffner Blvd",
    "sg:city":"Crestview",
    "sg:classifiers":[
        {
            "category":"Organizations",
            "subcategory":"Religious Organization",
            "type":"Services"
        }
    ],
    "sg:phone":"+1 850 682 8811",
    "sg:postcode":"32539",
    "sg:province":"FL",
    "sg:tags":[
        "church"
    ],
    "wof:name":"Oakridge Assembly Of God Chr",
    "wof:placetype":"venue"
},
  "geometry": {"coordinates":[-86.528322,30.756828],"type":"Point"}
}