{
  "type": "Feature",
  "properties": {
    "iso:country":"US",
    "sg:address":"1572 Osowaw Blvd",
    "sg:city":"Spring Hill",
    "sg:classifiers":[
        {
            "category":"Building & Trades",
            "subcategory":"Landscaping Services",
            "type":"Services"
        }
    ],
    "sg:phone":"+1 352 232 7711",
    "sg:postcode":"34607",
    "sg:province":"FL",
    "sg:tags":[
        "landscape",
        "contractor"
    ],
    "wof:name":"Robert Vance Landscaping",
    "wof:placetype":"venue"
},
  "geometry": {"coordinates":[-82.655242,28.451819],"type":"Point"}
}