{
  "type": "Feature",
  "properties": {
    "addr:full":"7608 Yachtsman Dr Port Richey FL 34667",
    "addr:housenumber":"7608",
    "addr:postcode":"34667",
    "addr:street":"Yachtsman Dr",
    "iso:country":"US",
    "sg:address":"7608 Yachtsman Dr",
    "sg:city":"Port Richey",
    "sg:classifiers":[
        {
            "category":"Shopping",
            "subcategory":"Clothing, Apparel, & Fashions",
            "type":"Retail Goods"
        }
    ],
    "sg:phone":"+1 727 863 7462",
    "sg:postcode":"34667",
    "sg:province":"FL",
    "wof:name":"Gloria Rogoff",
    "wof:placetype":"venue"
},
  "geometry": {"coordinates":[-82.692443,28.384596],"type":"Point"}
}