{
  "type": "Feature",
  "properties": {
    "iso:country":"US",
    "sg:address":"1255 Jeffords St",
    "sg:city":"Clearwater",
    "sg:classifiers":[
        {
            "category":"Real Estate",
            "subcategory":"Real Estate Operator",
            "type":"Services"
        }
    ],
    "sg:phone":"+1 727 447 2040",
    "sg:postcode":"33756",
    "sg:province":"FL",
    "sg:tags":[
        "apartment"
    ],
    "wof:name":"El Camino Rental Apartments",
    "wof:placetype":"venue"
},
  "geometry": {"coordinates":[-82.785093,27.953429],"type":"Point"}
}