{
  "type": "Feature",
  "properties": {
    "iso:country":"US",
    "sg:address":"395 Ospery Landing Way",
    "sg:city":"Lakeland",
    "sg:classifiers":[
        {
            "category":"Shopping",
            "subcategory":"Clothing, Apparel, & Fashions",
            "type":"Retail Goods"
        }
    ],
    "sg:phone":"+1 863 682 5619",
    "sg:postcode":"33813",
    "sg:province":"FL",
    "sg:tags":[
        "uniform"
    ],
    "wof:name":"Polk Professional Uniforms",
    "wof:placetype":"venue"
},
  "geometry": {"coordinates":[-81.952438,27.931794],"type":"Point"}
}