{
  "type": "Feature",
  "properties": {
    "addr:full":"680 Palm Dr Satellite Beach FL 32937",
    "addr:housenumber":"680",
    "addr:postcode":"32937",
    "addr:street":"Palm Dr",
    "iso:country":"US",
    "sg:address":"680 Palm Dr",
    "sg:city":"Satellite Beach",
    "sg:classifiers":[
        {
            "category":"Restaurant",
            "type":"Food & Drink"
        }
    ],
    "sg:phone":"+1 321 777 8425",
    "sg:postcode":"32937",
    "sg:province":"FL",
    "wof:name":"Johnson-D'Arpa Inc",
    "wof:placetype":"venue"
},
  "geometry": {"coordinates":[-80.58856,28.162261],"type":"Point"}
}