{
  "type": "Feature",
  "properties": {
    "iso:country":"US",
    "sg:address":"3402 Technological Ave",
    "sg:city":"Orlando",
    "sg:classifiers":[
        {
            "category":"Restaurant",
            "type":"Food & Drink"
        },
        {
            "category":"Food & Beverages",
            "subcategory":"Dairy",
            "type":"Retail Goods"
        }
    ],
    "sg:phone":"+1 407 658 4112",
    "sg:postcode":"32817",
    "sg:province":"FL",
    "sg:tags":[
        "yogurt",
        "dessert"
    ],
    "wof:name":"Freshberry Frozen Yogurt",
    "wof:placetype":"venue"
},
  "geometry": {"coordinates":[-81.220337,28.597719],"type":"Point"}
}