{
  "type": "Feature",
  "properties": {
    "iso:country":"US",
    "sg:address":"3316 SW 35th Blvd",
    "sg:city":"Gainesville",
    "sg:classifiers":[
        {
            "category":"Restaurant",
            "type":"Food & Drink"
        }
    ],
    "sg:menulink":"http://www.allmenus.com/fl/gainesville/63013-subway/menu/",
    "sg:phone":"+1 352 373 4465",
    "sg:postcode":"32608",
    "sg:province":"FL",
    "sg:tags":[
        "american",
        "sandwich"
    ],
    "wof:name":"Subway",
    "wof:placetype":"venue"
},
  "geometry": {"coordinates":[-82.377657,29.624602],"type":"Point"}
}