{
  "type": "Feature",
  "properties": {
    "iso:country":"US",
    "sg:address":"4423 N Monroe St",
    "sg:city":"Tallahassee",
    "sg:classifiers":[
        {
            "category":"Organizations",
            "subcategory":"Religious Organization",
            "type":"Services"
        }
    ],
    "sg:phone":"+1 850 562 1759",
    "sg:postcode":"32303",
    "sg:province":"FL",
    "sg:tags":[
        "church"
    ],
    "wof:name":"Lake Jackson United Methodist",
    "wof:placetype":"venue"
},
  "geometry": {"coordinates":[-84.346009,30.515409],"type":"Point"}
}