{
  "type": "Feature",
  "properties": {
    "iso:country":"US",
    "sg:address":"1100 17th St",
    "sg:city":"Miami Beach",
    "sg:classifiers":[
        {
            "category":"Professional",
            "subcategory":"Advertising",
            "type":"Services"
        }
    ],
    "sg:phone":"+1 305 534 0589",
    "sg:postcode":"33139",
    "sg:province":"FL",
    "sg:tags":[
        "counselor"
    ],
    "wof:name":"Accountable Inc",
    "wof:placetype":"venue"
},
  "geometry": {"coordinates":[-80.141278,25.79204],"type":"Point"}
}