{
  "type": "Feature",
  "properties": {
    "addr:full":"3343 E Oakland Park Blvd Fort Lauderdale FL 33308",
    "addr:housenumber":"3343",
    "addr:postcode":"33308",
    "addr:street":"E Oakland Park Blvd",
    "iso:country":"US",
    "sg:address":"3343 E Oakland Park Blvd",
    "sg:city":"Fort Lauderdale",
    "sg:classifiers":[
        {
            "category":"Restaurant",
            "type":"Food & Drink"
        }
    ],
    "sg:phone":"+1 954 561 2554",
    "sg:postcode":"33308",
    "sg:province":"FL",
    "wof:name":"Cafe Martorano",
    "wof:placetype":"venue"
},
  "geometry": {"coordinates":[-80.10190799999999,26.167562],"type":"Point"}
}