{
  "type": "Feature",
  "properties": {
    "iso:country":"US",
    "sg:address":"10850 SW 113th Pl Ste 104",
    "sg:city":"Miami",
    "sg:classifiers":[
        {
            "category":"Insurance",
            "subcategory":"Insurance Agent",
            "type":"Services"
        },
        {
            "category":"Banks & Credit Unions",
            "subcategory":"Financial Services",
            "type":"Services"
        }
    ],
    "sg:phone":"+1 407 599 0057",
    "sg:postcode":"33176",
    "sg:province":"FL",
    "sg:tags":[
        "counseling",
        "debt",
        "adjuster"
    ],
    "sg:website":"http://www.consumerdebtcounselors.com",
    "wof:name":"Consumer Debt Counselors Inc",
    "wof:placetype":"venue"
},
  "geometry": {"coordinates":[-80.37782900000001,25.668235],"type":"Point"}
}