{
  "type": "Feature",
  "properties": {
    "addr:full":"14175 Beach Blvd Jacksonville Beach FL 32250",
    "addr:housenumber":"14175",
    "addr:postcode":"32250",
    "addr:street":"Beach Blvd",
    "iso:country":"US",
    "sg:address":"14175 Beach Blvd",
    "sg:city":"Jacksonville Beach",
    "sg:classifiers":[
        {
            "category":"Autos & Motor Vehicles",
            "subcategory":"Auto Supplies",
            "type":"Retail Goods"
        }
    ],
    "sg:phone":"+1 904 992 8228",
    "sg:postcode":"32250",
    "sg:province":"FL",
    "wof:name":"Sun Tire",
    "wof:placetype":"venue"
},
  "geometry": {"coordinates":[-81.444597,30.287893],"type":"Point"}
}