{
  "type": "Feature",
  "properties": {
    "iso:country":"US",
    "sg:address":"1655 W 44th Pl",
    "sg:city":"Hialeah",
    "sg:classifiers":[
        {
            "category":"Freight",
            "type":"Transportation"
        }
    ],
    "sg:phone":"+1 305 362 6374",
    "sg:postcode":"33012",
    "sg:province":"FL",
    "wof:name":"Quality Transport Corp",
    "wof:placetype":"venue"
},
  "geometry": {"coordinates":[-80.316311,25.862513],"type":"Point"}
}