{
  "type": "Feature",
  "properties": {
    "iso:country":"US",
    "sg:address":"3357 Sheridan St",
    "sg:city":"Hollywood",
    "sg:classifiers":[
        {
            "category":"Restaurant",
            "type":"Food & Drink"
        }
    ],
    "sg:phone":"+1 954 983 2825",
    "sg:postcode":"33021",
    "sg:province":"FL",
    "sg:tags":[
        "grocery",
        "store"
    ],
    "wof:name":"Levys Kosher of Hollywood",
    "wof:placetype":"venue"
},
  "geometry": {"coordinates":[-80.176315,26.033156],"type":"Point"}
}