{
  "type": "Feature",
  "properties": {
    "iso:country":"US",
    "sg:address":"1778 Imperial Palm Dr",
    "sg:city":"Apopka",
    "sg:classifiers":[
        {
            "category":"Wholesale",
            "subcategory":"Sporting Goods",
            "type":"Manufacturing & Wholesale Goods"
        }
    ],
    "sg:phone":"+1 407 831 5967",
    "sg:postcode":"32712",
    "sg:province":"FL",
    "sg:tags":[
        "equipment",
        "pool",
        "swimming"
    ],
    "wof:name":"Aqua Tech",
    "wof:placetype":"venue"
},
  "geometry": {"coordinates":[-81.478606,28.701889],"type":"Point"}
}