{
  "type": "Feature",
  "properties": {
    "addr:full":"701 S Federal Hwy Pompano Beach FL 33062",
    "addr:housenumber":"701",
    "addr:postcode":"33062",
    "addr:street":"S Federal Hwy",
    "iso:country":"US",
    "sg:address":"701 S Federal Hwy",
    "sg:city":"Pompano Beach",
    "sg:classifiers":[
        {
            "category":"Recreation",
            "subcategory":"Marina",
            "type":"Entertainment"
        }
    ],
    "sg:phone":"+1 954 946 1450",
    "sg:postcode":"33062",
    "sg:province":"FL",
    "sg:tags":[
        "operation",
        "boat"
    ],
    "wof:name":"Pompano Beach Marine Center",
    "wof:placetype":"venue"
},
  "geometry": {"coordinates":[-80.103391,26.22347],"type":"Point"}
}