{
  "type": "Feature",
  "properties": {
    "iso:country":"US",
    "sg:address":"6800 Aloma Ave",
    "sg:city":"Winter Park",
    "sg:classifiers":[
        {
            "category":"Shopping",
            "subcategory":"Used Merchandise",
            "type":"Retail Goods"
        }
    ],
    "sg:phone":"+1 407 679 4010",
    "sg:postcode":"32792",
    "sg:province":"FL",
    "sg:tags":[
        "shop",
        "thrift"
    ],
    "wof:name":"Primrose Thrift Store",
    "wof:placetype":"venue"
},
  "geometry": {"coordinates":[-81.297873,28.606504],"type":"Point"}
}