{
  "type": "Feature",
  "properties": {
    "iso:country":"US",
    "sg:address":"2206 53rd Ave E",
    "sg:city":"Bradenton",
    "sg:classifiers":[
        {
            "category":"Social Services",
            "subcategory":"Child Care",
            "type":"Services"
        }
    ],
    "sg:phone":"+1 941 758 0277",
    "sg:postcode":"34203",
    "sg:province":"FL",
    "sg:tags":[
        "day"
    ],
    "wof:name":"Jer-Care",
    "wof:placetype":"venue"
},
  "geometry": {"coordinates":[-82.5365,27.447333],"type":"Point"}
}