{
  "type": "Feature",
  "properties": {
    "iso:country":"US",
    "sg:address":"7537 Tallowtree Dr",
    "sg:city":"Wesley Chapel",
    "sg:classifiers":[
        {
            "category":"Building & Trades",
            "subcategory":"Pest Control",
            "type":"Services"
        }
    ],
    "sg:phone":"+1 813 713 4044",
    "sg:postcode":"33544",
    "sg:province":"FL",
    "wof:name":"Apple Pest Control",
    "wof:placetype":"venue"
},
  "geometry": {"coordinates":[-82.34779399999999,28.268721],"type":"Point"}
}