{
  "type": "Feature",
  "properties": {
    "addr:full":"12900 44th St N Clearwater FL 33762",
    "addr:housenumber":"12900",
    "addr:postcode":"33762",
    "addr:street":"44Th St N",
    "iso:country":"US",
    "sg:address":"12900 44th St N",
    "sg:city":"Clearwater",
    "sg:classifiers":[
        {
            "category":"Manufacturing",
            "subcategory":"Tools & Machinery",
            "type":"Manufacturing & Wholesale Goods"
        }
    ],
    "sg:phone":"+1 727 561 9292",
    "sg:postcode":"33762",
    "sg:province":"FL",
    "sg:tags":[
        "furnishing",
        "mfg"
    ],
    "wof:name":"Boyd Industries Inc",
    "wof:placetype":"venue"
},
  "geometry": {"coordinates":[-82.693259,27.889304],"type":"Point"}
}