{
  "type": "Feature",
  "properties": {
    "addr:full":"10466 W Yulee Dr Homosassa FL 34448",
    "addr:housenumber":"10466",
    "addr:postcode":"34448",
    "addr:street":"W Yulee Dr",
    "iso:country":"US",
    "sg:address":"10466 W Yulee Dr",
    "sg:city":"Homosassa",
    "sg:classifiers":[
        {
            "category":"Museum",
            "type":"Entertainment"
        }
    ],
    "sg:phone":"+1 352 628 9411",
    "sg:postcode":"34448",
    "sg:province":"FL",
    "wof:name":"Olde Mill House Gallery",
    "wof:placetype":"venue"
},
  "geometry": {"coordinates":[-82.60723,28.784729],"type":"Point"}
}