{
  "type": "Feature",
  "properties": {
    "iso:country":"US",
    "sg:address":"21251 Marsh Hawk Dr",
    "sg:city":"Land O Lakes",
    "sg:classifiers":[
        {
            "category":"Professional",
            "subcategory":"Computer Services",
            "type":"Services"
        }
    ],
    "sg:phone":"+1 813 235 6666",
    "sg:postcode":"34638",
    "sg:province":"FL",
    "sg:tags":[
        "related"
    ],
    "wof:name":"Interscience Technologies Inc",
    "wof:placetype":"venue"
},
  "geometry": {"coordinates":[-82.46499900000001,28.243552],"type":"Point"}
}