{
  "type": "Feature",
  "properties": {
    "iso:country":"US",
    "sg:address":"4200 NW 16th St",
    "sg:city":"Fort Lauderdale",
    "sg:classifiers":[
        {
            "category":"Government",
            "subcategory":"Office",
            "type":"Public Place"
        }
    ],
    "sg:phone":"+1 954 535 2375",
    "sg:postcode":"33313",
    "sg:province":"FL",
    "sg:tags":[
        "administrative",
        "program",
        "health"
    ],
    "wof:name":"Substance Abuse and Health",
    "wof:placetype":"venue"
},
  "geometry": {"coordinates":[-80.206053,26.145982],"type":"Point"}
}