{
  "type": "Feature",
  "properties": {
    "iso:country":"US",
    "sg:address":"11387 S US Hwy 301",
    "sg:city":"Webster",
    "sg:classifiers":[
        {
            "category":"Professional",
            "subcategory":"Computer Services",
            "type":"Services"
        }
    ],
    "sg:phone":"+1 352 568 0918",
    "sg:postcode":"33597",
    "sg:province":"FL",
    "sg:tags":[
        "programing",
        "custom"
    ],
    "wof:name":"K & L Enterprises",
    "wof:placetype":"venue"
},
  "geometry": {"coordinates":[-82.146585,28.593073],"type":"Point"}
}