{
  "type": "Feature",
  "properties": {
    "iso:country":"US",
    "sg:address":"6232 Osprey Ter",
    "sg:city":"Pompano Beach",
    "sg:classifiers":[
        {
            "category":"Wholesale",
            "subcategory":"Chemicals & Plastics",
            "type":"Manufacturing & Wholesale Goods"
        }
    ],
    "sg:phone":"+1 954 426 4888",
    "sg:postcode":"33073",
    "sg:province":"FL",
    "sg:tags":[
        "raw",
        "material",
        "recycling"
    ],
    "wof:name":"Responsible Envmtl Solutions",
    "wof:placetype":"venue"
},
  "geometry": {"coordinates":[-80.196062,26.304275],"type":"Point"}
}