{
  "type": "Feature",
  "properties": {
    "iso:country":"US",
    "sg:address":"814 Cape Coral Pkwy E",
    "sg:city":"Cape Coral",
    "sg:classifiers":[
        {
            "category":"Restaurant",
            "type":"Food & Drink"
        }
    ],
    "sg:phone":"+1 239 945 1700",
    "sg:postcode":"33904",
    "sg:province":"FL",
    "sg:tags":[
        "pizza"
    ],
    "wof:name":"Papa Joe's Italian Restaurant & Pizzeria",
    "wof:placetype":"venue"
},
  "geometry": {"coordinates":[-81.9571,26.562599],"type":"Point"}
}