{
  "type": "Feature",
  "properties": {
    "iso:country":"US",
    "sg:address":"1015 N 12th Ave",
    "sg:city":"Pensacola",
    "sg:classifiers":[
        {
            "category":"Professional",
            "subcategory":"Lawyer & Legal Services",
            "type":"Services"
        }
    ],
    "sg:phone":"+1 850 434 9999",
    "sg:postcode":"32501",
    "sg:province":"FL",
    "sg:tags":[
        "attorney"
    ],
    "wof:name":"James M Corrigan",
    "wof:placetype":"venue"
},
  "geometry": {"coordinates":[-87.203343,30.426523],"type":"Point"}
}