{
  "type": "Feature",
  "properties": {
    "iso:country":"US",
    "sg:address":"4455 Sunbeam Rd",
    "sg:city":"Jacksonville",
    "sg:classifiers":[
        {
            "category":"Retail",
            "subcategory":"Auto Repair",
            "type":"Services"
        }
    ],
    "sg:phone":"+1 904 448 3786",
    "sg:postcode":"32257",
    "sg:province":"FL",
    "sg:tags":[
        "repairing",
        "tire"
    ],
    "wof:name":"National Tire Solutions Inc",
    "wof:placetype":"venue"
},
  "geometry": {"coordinates":[-81.596367,30.206063],"type":"Point"}
}