{
  "type": "Feature",
  "properties": {
    "iso:country":"US",
    "sg:address":"1203 NW 12th Ave",
    "sg:city":"Gainesville",
    "sg:classifiers":[
        {
            "category":"Health Services",
            "subcategory":"Clinic",
            "type":"Services"
        }
    ],
    "sg:phone":"+1 352 338 1114",
    "sg:postcode":"32601",
    "sg:province":"FL",
    "sg:tags":[
        "welfare"
    ],
    "wof:name":"Health Perspectives Pa",
    "wof:placetype":"venue"
},
  "geometry": {"coordinates":[-82.33722,29.66306],"type":"Point"}
}