{
  "type": "Feature",
  "properties": {
    "addr:full":"2398 US Hwy 98 Okeechobee FL 34972",
    "addr:housenumber":"2398",
    "addr:postcode":"34972",
    "addr:street":"Us Hwy 98",
    "iso:country":"US",
    "sg:address":"2398 US Hwy 98",
    "sg:city":"Okeechobee",
    "sg:classifiers":[
        {
            "category":"Retail",
            "subcategory":"Auto Repair",
            "type":"Services"
        }
    ],
    "sg:phone":"+1 863 357 0890",
    "sg:postcode":"34972",
    "sg:province":"FL",
    "sg:tags":[
        "general"
    ],
    "wof:name":"C&D Automotive Repair & Transm",
    "wof:placetype":"venue"
},
  "geometry": {"coordinates":[-80.869339,27.270782],"type":"Point"}
}