{
  "type": "Feature",
  "properties": {
    "iso:country":"US",
    "sg:address":"1306 E Cervantes St",
    "sg:city":"Pensacola",
    "sg:classifiers":[
        {
            "category":"Professional",
            "subcategory":"Computer Services",
            "type":"Services"
        }
    ],
    "sg:phone":"+1 850 470 8496",
    "sg:postcode":"32501",
    "sg:province":"FL",
    "sg:tags":[
        "prepackaged",
        "software"
    ],
    "wof:name":"J P Micro Corporation",
    "wof:placetype":"venue"
},
  "geometry": {"coordinates":[-87.199781,30.424404],"type":"Point"}
}