{
  "type": "Feature",
  "properties": {
    "iso:country":"US",
    "sg:address":"2557 Tulip St",
    "sg:city":"Sarasota",
    "sg:classifiers":[
        {
            "category":"Building & Trades",
            "subcategory":"Construction",
            "type":"Services"
        }
    ],
    "sg:phone":"+1 941 377 2641",
    "sg:postcode":"34239",
    "sg:province":"FL",
    "sg:tags":[
        "paving",
        "asphalt",
        "contractor"
    ],
    "wof:name":"Sarasota Sealcoating Inc",
    "wof:placetype":"venue"
},
  "geometry": {"coordinates":[-82.518939,27.303549],"type":"Point"}
}