{
  "type": "Feature",
  "properties": {
    "addr:full":"2307 Industrial Dr Panama City FL 32405",
    "addr:housenumber":"2307",
    "addr:postcode":"32405",
    "addr:street":"Industrial Dr",
    "iso:country":"US",
    "sg:address":"2307 Industrial Dr",
    "sg:city":"Panama City",
    "sg:classifiers":[
        {
            "category":"Manufacturing",
            "subcategory":"Tools & Machinery",
            "type":"Manufacturing & Wholesale Goods"
        }
    ],
    "sg:phone":"+1 850 769 9080",
    "sg:postcode":"32405",
    "sg:province":"FL",
    "sg:tags":[
        "machined",
        "parts",
        "defense",
        "precision",
        "contractor"
    ],
    "wof:name":"K & K Precision Manufacturing",
    "wof:placetype":"venue"
},
  "geometry": {"coordinates":[-85.632932,30.187291],"type":"Point"}
}