{
  "type": "Feature",
  "properties": {
    "iso:country":"US",
    "sg:address":"1501 Biscayne Blvd",
    "sg:city":"Miami",
    "sg:classifiers":[
        {
            "category":"Shopping Center",
            "type":"Public Place"
        }
    ],
    "sg:phone":"+1 305 375 9410",
    "sg:postcode":"33132",
    "sg:province":"FL",
    "wof:name":"Downtown Mall",
    "wof:placetype":"venue"
},
  "geometry": {"coordinates":[-80.188928,25.789531],"type":"Point"}
}