{
  "type": "Feature",
  "properties": {
    "addr:full":"18446 Greensboro St Brooksville FL 34610",
    "addr:housenumber":"18446",
    "addr:postcode":"34610",
    "addr:street":"Greensboro St",
    "iso:country":"US",
    "sg:address":"18446 Greensboro St",
    "sg:city":"Brooksville",
    "sg:classifiers":[
        {
            "category":"Home & Garden",
            "subcategory":"Building Materials",
            "type":"Retail Goods"
        },
        {
            "category":"Building & Trades",
            "subcategory":"Construction",
            "type":"Services"
        }
    ],
    "sg:phone":"+1 727 857 9256",
    "sg:postcode":"34610",
    "sg:province":"FL",
    "sg:tags":[
        "screen",
        "enclosure"
    ],
    "wof:name":"Screen Services",
    "wof:placetype":"venue"
},
  "geometry": {"coordinates":[-82.529928,28.431319],"type":"Point"}
}