{
  "type": "Feature",
  "properties": {
    "iso:country":"US",
    "sg:address":"16999 Dixie Hwy",
    "sg:city":"Miami",
    "sg:classifiers":[
        {
            "category":"Restaurant",
            "type":"Food & Drink"
        }
    ],
    "sg:phone":"+1 305 253 5300",
    "sg:postcode":"33157",
    "sg:province":"FL",
    "wof:name":"IL Pappagallo",
    "wof:placetype":"venue"
},
  "geometry": {"coordinates":[-80.34749600000001,25.61322],"type":"Point"}
}