{
  "type": "Feature",
  "properties": {
    "addr:full":"6107 W Harwood Ave Orlando FL 32835",
    "addr:housenumber":"6107",
    "addr:postcode":"32835",
    "addr:street":"W Harwood Ave",
    "iso:country":"US",
    "sg:address":"6107 W Harwood Ave",
    "sg:city":"Orlando",
    "sg:classifiers":[
        {
            "category":"Building & Trades",
            "subcategory":"Construction",
            "type":"Services"
        }
    ],
    "sg:phone":"+1 407 299 0097",
    "sg:postcode":"32835",
    "sg:province":"FL",
    "sg:tags":[
        "floor",
        "laying",
        "contractor"
    ],
    "wof:name":"Matthew I Hart",
    "wof:placetype":"venue"
},
  "geometry": {"coordinates":[-81.46624,28.547889],"type":"Point"}
}