{
  "type": "Feature",
  "properties": {
    "addr:full":"10120 Southern Pride Pl Wellington FL 33449",
    "addr:housenumber":"10120",
    "addr:postcode":"33449",
    "addr:street":"Southern Pride Pl",
    "iso:country":"US",
    "sg:address":"10120 Southern Pride Pl",
    "sg:city":"Wellington",
    "sg:classifiers":[
        {
            "category":"Building & Trades",
            "subcategory":"Cleaning & Sanitation",
            "type":"Services"
        }
    ],
    "sg:phone":"+1 561 383 5070",
    "sg:postcode":"33449",
    "sg:province":"FL",
    "sg:tags":[
        "janitor"
    ],
    "wof:name":"K C Cleaning Svc",
    "wof:placetype":"venue"
},
  "geometry": {"coordinates":[-80.207982,26.630312],"type":"Point"}
}