{
  "type": "Feature",
  "properties": {
    "addr:full":"5471 Commercial Way Spring Hill FL 34606",
    "addr:housenumber":"5471",
    "addr:postcode":"34606",
    "addr:street":"Commercial Way",
    "iso:country":"US",
    "sg:address":"5471 Commercial Way",
    "sg:city":"Spring Hill",
    "sg:classifiers":[
        {
            "category":"Professional",
            "subcategory":"Lawyer & Legal Services",
            "type":"Services"
        }
    ],
    "sg:phone":"+1 352 597 3888",
    "sg:postcode":"34606",
    "sg:province":"FL",
    "wof:name":"Gregory G Gay PA",
    "wof:placetype":"venue"
},
  "geometry": {"coordinates":[-82.58269300000001,28.508104],"type":"Point"}
}