{
  "type": "Feature",
  "properties": {
    "addr:full":"2115 Palm Bay Rd NE Palm Bay FL 32905",
    "addr:housenumber":"2115",
    "addr:postcode":"32905",
    "addr:street":"Palm Bay Rd Ne",
    "iso:country":"US",
    "sg:address":"2115 Palm Bay Rd NE",
    "sg:city":"Palm Bay",
    "sg:classifiers":[
        {
            "category":"Professional",
            "subcategory":"Lawyer & Legal Services",
            "type":"Services"
        }
    ],
    "sg:phone":"+1 321 727 0222",
    "sg:postcode":"32905",
    "sg:province":"FL",
    "wof:name":"Roy A Alterman PA",
    "wof:placetype":"venue"
},
  "geometry": {"coordinates":[-80.611051,28.034962],"type":"Point"}
}