{
  "type": "Feature",
  "properties": {
    "iso:country":"US",
    "sg:address":"1340 NW Ave L",
    "sg:city":"Belle Glade",
    "sg:classifiers":[
        {
            "category":"Government",
            "subcategory":"Post Office",
            "type":"Public Place"
        }
    ],
    "sg:phone":"+1 561 996 3145",
    "sg:postcode":"33430",
    "sg:province":"FL",
    "sg:tags":[
        "postal",
        "us"
    ],
    "wof:name":"Belle Glade Main Office",
    "wof:placetype":"venue"
},
  "geometry": {"coordinates":[-80.680654,26.696727],"type":"Point"}
}