{
  "type": "Feature",
  "properties": {
    "iso:country":"US",
    "sg:address":"4038 NW 59 Ave",
    "sg:city":"Gainesville",
    "sg:classifiers":[
        {
            "category":"Restaurant",
            "type":"Food & Drink"
        }
    ],
    "sg:phone":"+1 352 271 0810",
    "sg:postcode":"32653",
    "sg:province":"FL",
    "sg:tags":[
        "eating"
    ],
    "wof:name":"Chef Brothers Inc",
    "wof:placetype":"venue"
},
  "geometry": {"coordinates":[-82.384119,29.70903],"type":"Point"}
}