{
  "type": "Feature",
  "properties": {
    "addr:full":"2813 SW 32nd Ave Ocala FL 34474",
    "addr:housenumber":"2813",
    "addr:postcode":"34474",
    "addr:street":"Sw 32Nd Ave",
    "iso:country":"US",
    "sg:address":"2813 SW 32nd Ave",
    "sg:city":"Ocala",
    "sg:classifiers":[
        {
            "category":"Manufacturing",
            "subcategory":"Glass & Minerals",
            "type":"Manufacturing & Wholesale Goods"
        }
    ],
    "sg:phone":"+1 352 291 2557",
    "sg:postcode":"34474",
    "sg:province":"FL",
    "sg:tags":[
        "concrete",
        "product"
    ],
    "wof:name":"Hi-Tech Structures Levy LLC",
    "wof:placetype":"venue"
},
  "geometry": {"coordinates":[-82.17651499999999,29.158654],"type":"Point"}
}