{
  "type": "Feature",
  "properties": {
    "iso:country":"US",
    "sg:address":"3960 S Babcock St",
    "sg:city":"Melbourne",
    "sg:classifiers":[
        {
            "category":"Recreation",
            "subcategory":"Amusement Park",
            "type":"Entertainment"
        }
    ],
    "sg:phone":"+1 321 956 6706",
    "sg:postcode":"32901",
    "sg:province":"FL",
    "sg:tags":[
        "operation",
        "park"
    ],
    "wof:name":"Andretti Thrill Park",
    "wof:placetype":"venue"
},
  "geometry": {"coordinates":[-80.62157000000001,28.053196],"type":"Point"}
}