{
  "type": "Feature",
  "properties": {
    "addr:full":"1531 Belvedere Rd West Palm Beach FL 33406",
    "addr:housenumber":"1531",
    "addr:postcode":"33406",
    "addr:street":"Belvedere Rd",
    "iso:country":"US",
    "sg:address":"1531 Belvedere Rd",
    "sg:city":"West Palm Beach",
    "sg:classifiers":[
        {
            "category":"Restaurant",
            "type":"Food & Drink"
        }
    ],
    "sg:menulink":"http://www.allmenus.com/fl/west-palm-beach/169289-wendys/menu/",
    "sg:phone":"+1 561 471 9554",
    "sg:postcode":"33406",
    "sg:province":"FL",
    "sg:tags":[
        "burger",
        "american",
        "soup"
    ],
    "wof:name":"Wendy's",
    "wof:placetype":"venue"
},
  "geometry": {"coordinates":[-80.07382699999999,26.691296],"type":"Point"}
}