{
  "type": "Feature",
  "properties": {
    "iso:country":"US",
    "sg:address":"1010 Beverly Dr",
    "sg:city":"Rockledge",
    "sg:classifiers":[
        {
            "category":"Sports & Exercise",
            "subcategory":"Gym",
            "type":"Entertainment"
        }
    ],
    "sg:phone":"+1 321 632 0011",
    "sg:postcode":"32955",
    "sg:province":"FL",
    "sg:tags":[
        "fitness",
        "physical",
        "facility"
    ],
    "wof:name":"Fitness Plus",
    "wof:placetype":"venue"
},
  "geometry": {"coordinates":[-80.724543,28.336001],"type":"Point"}
}