{
  "type": "Feature",
  "properties": {
    "iso:country":"US",
    "sg:address":"326 W Pine St",
    "sg:city":"Lake Worth",
    "sg:classifiers":[
        {
            "category":"Professional",
            "type":"Services"
        }
    ],
    "sg:phone":"+1 561 547 6011",
    "sg:postcode":"33462",
    "sg:province":"FL",
    "wof:name":"Cadle Leavy Inc",
    "wof:placetype":"venue"
},
  "geometry": {"coordinates":[-80.05427299999999,26.582855],"type":"Point"}
}