{
  "type": "Feature",
  "properties": {
    "addr:full":"2108 N 19th Ave Hollywood FL 33020",
    "addr:housenumber":"2108",
    "addr:postcode":"33020",
    "addr:street":"N 19Th Ave",
    "iso:country":"US",
    "sg:address":"2108 N 19th Ave",
    "sg:city":"Hollywood",
    "sg:classifiers":[
        {
            "category":"Building & Trades",
            "subcategory":"Landscaping Services",
            "type":"Services"
        }
    ],
    "sg:phone":"+1 954 925 8806",
    "sg:postcode":"33020",
    "sg:province":"FL",
    "sg:tags":[
        "landscape"
    ],
    "wof:name":"Backyard Landscape",
    "wof:placetype":"venue"
},
  "geometry": {"coordinates":[-80.145376,26.030726],"type":"Point"}
}