{
  "type": "Feature",
  "properties": {
    "iso:country":"US",
    "sg:address":"615 Catalina St",
    "sg:city":"Vero Beach",
    "sg:classifiers":[
        {
            "category":"Travel",
            "subcategory":"Travel Agent",
            "type":"Entertainment"
        }
    ],
    "sg:phone":"+1 772 770 2222",
    "sg:postcode":"32960",
    "sg:province":"FL",
    "sg:tags":[
        "agency"
    ],
    "wof:name":"Holbrook Golf Travel",
    "wof:placetype":"venue"
},
  "geometry": {"coordinates":[-80.38564,27.64672],"type":"Point"}
}