{
  "type": "Feature",
  "properties": {
    "addr:full":"787 S Washington Blvd Sarasota FL 34236",
    "addr:housenumber":"787",
    "addr:postcode":"34236",
    "addr:street":"S Washington Blvd",
    "iso:country":"US",
    "sg:address":"787 S Washington Blvd",
    "sg:city":"Sarasota",
    "sg:classifiers":[
        {
            "category":"Restaurant",
            "type":"Food & Drink"
        }
    ],
    "sg:menulink":"http://www.allmenus.com/fl/sarasota/187680-mcdonalds/menu/",
    "sg:phone":"+1 941 365 3030",
    "sg:postcode":"34236",
    "sg:province":"FL",
    "sg:tags":[
        "burger",
        "american"
    ],
    "wof:name":"McDonald's",
    "wof:placetype":"venue"
},
  "geometry": {"coordinates":[-82.53046999999999,27.328711],"type":"Point"}
}