{
  "type": "Feature",
  "properties": {
    "iso:country":"US",
    "sg:address":"531 US Hwy 92",
    "sg:city":"Longwood",
    "sg:classifiers":[
        {
            "category":"Shopping",
            "subcategory":"Books",
            "type":"Retail Goods"
        }
    ],
    "sg:phone":"+1 407 388 1034",
    "sg:postcode":"32750",
    "sg:province":"FL",
    "sg:tags":[
        "dealer"
    ],
    "wof:name":"Jehova Jireh Christian Bkstr",
    "wof:placetype":"venue"
},
  "geometry": {"coordinates":[-81.326446,28.70583],"type":"Point"}
}