{
  "type": "Feature",
  "properties": {
    "iso:country":"US",
    "sg:address":"1401 Miccosukee Rd",
    "sg:city":"Tallahassee",
    "sg:classifiers":[
        {
            "category":"Banks & Credit Unions",
            "subcategory":"Bank",
            "type":"Services"
        }
    ],
    "sg:phone":"+1 850 907 5000",
    "sg:postcode":"32308",
    "sg:province":"FL",
    "wof:name":"Sun Trust Bank",
    "wof:placetype":"venue"
},
  "geometry": {"coordinates":[-84.26051699999999,30.456163],"type":"Point"}
}