{
  "type": "Feature",
  "properties": {
    "iso:country":"US",
    "sg:address":"24631 Leonard Way",
    "sg:city":"Eustis",
    "sg:classifiers":[
        {
            "category":"Education",
            "subcategory":"School",
            "type":"Public Place"
        }
    ],
    "sg:phone":"+1 352 357 1849",
    "sg:postcode":"32736",
    "sg:province":"FL",
    "sg:tags":[
        "supply"
    ],
    "wof:name":"Teachers Educational Resource Center",
    "wof:placetype":"venue"
},
  "geometry": {"coordinates":[-81.548641,28.869591],"type":"Point"}
}