{
  "type": "Feature",
  "properties": {
    "iso:country":"US",
    "sg:address":"4625 Mobile Hwy",
    "sg:city":"Pensacola",
    "sg:classifiers":[
        {
            "category":"Restaurant",
            "type":"Food & Drink"
        }
    ],
    "sg:phone":"+1 850 456 0014",
    "sg:postcode":"32506",
    "sg:province":"FL",
    "sg:tags":[
        "style",
        "family",
        "lunch",
        "american",
        "brunch",
        "breakfast"
    ],
    "sg:website":"http://www.dennys.com",
    "wof:name":"Denny's",
    "wof:placetype":"venue"
},
  "geometry": {"coordinates":[-87.278564,30.436704],"type":"Point"}
}