{
  "type": "Feature",
  "properties": {
    "iso:country":"US",
    "sg:address":"11650 Munson Hwy",
    "sg:city":"Milton",
    "sg:classifiers":[
        {
            "category":"Government",
            "subcategory":"Office",
            "type":"Public Place"
        }
    ],
    "sg:phone":"+1 850 957 6140",
    "sg:postcode":"32570",
    "sg:province":"FL",
    "sg:tags":[
        "conservation"
    ],
    "wof:name":"Division of Forestry/Dist 1",
    "wof:placetype":"venue"
},
  "geometry": {"coordinates":[-86.870936,30.860778],"type":"Point"}
}