{
  "type": "Feature",
  "properties": {
    "iso:country":"US",
    "sg:address":"12334 Summerwood Dr",
    "sg:city":"Fort Myers",
    "sg:classifiers":[
        {
            "category":"Building & Trades",
            "subcategory":"Plumbing",
            "type":"Services"
        }
    ],
    "sg:phone":"+1 239 466 9669",
    "sg:postcode":"33908",
    "sg:province":"FL",
    "sg:tags":[
        "contractor"
    ],
    "wof:name":"Royal Flush Plumbing",
    "wof:placetype":"venue"
},
  "geometry": {"coordinates":[-81.958912,26.514866],"type":"Point"}
}