{
  "type": "Feature",
  "properties": {
    "iso:country":"US",
    "sg:address":"6577 Waterford Cir",
    "sg:city":"Sarasota",
    "sg:classifiers":[
        {
            "category":"Manufacturing",
            "subcategory":"Printing",
            "type":"Manufacturing & Wholesale Goods"
        }
    ],
    "sg:phone":"+1 941 926 0266",
    "sg:postcode":"34238",
    "sg:province":"FL",
    "sg:tags":[
        "periodical"
    ],
    "wof:name":"Bride Groom Publications",
    "wof:placetype":"venue"
},
  "geometry": {"coordinates":[-82.494856,27.257908],"type":"Point"}
}