{
  "type": "Feature",
  "properties": {
    "iso:country":"US",
    "sg:address":"309 NE 1st St",
    "sg:city":"Gainesville",
    "sg:classifiers":[
        {
            "category":"Professional",
            "subcategory":"Lawyer & Legal Services",
            "type":"Services"
        }
    ],
    "sg:phone":"+1 352 375 2414",
    "sg:postcode":"32601",
    "sg:province":"FL",
    "sg:tags":[
        "attorney",
        "practice",
        "elder",
        "real estate",
        "law"
    ],
    "wof:name":"Sellers Ernest A Jr",
    "wof:placetype":"venue"
},
  "geometry": {"coordinates":[-82.323989,29.654066],"type":"Point"}
}