{
  "type": "Feature",
  "properties": {
    "iso:country":"US",
    "sg:address":"438 N Fletcher Ave",
    "sg:city":"Fernandina Beach",
    "sg:classifiers":[
        {
            "category":"Building & Trades",
            "subcategory":"Construction",
            "type":"Services"
        }
    ],
    "sg:phone":"+1 904 321 0626",
    "sg:postcode":"32034",
    "sg:province":"FL",
    "sg:tags":[
        "general",
        "contractor"
    ],
    "wof:name":"Domestic Designs Inc",
    "wof:placetype":"venue"
},
  "geometry": {"coordinates":[-81.430836,30.67248],"type":"Point"}
}