{
  "type": "Feature",
  "properties": {
    "iso:country":"US",
    "sg:address":"2541 Cameron Ave",
    "sg:city":"Sanford",
    "sg:classifiers":[
        {
            "category":"Building & Trades",
            "subcategory":"Construction",
            "type":"Services"
        }
    ],
    "sg:phone":"+1 407 322 9154",
    "sg:postcode":"32773",
    "sg:province":"FL",
    "sg:tags":[
        "contractor"
    ],
    "wof:name":"B-Con Site Development",
    "wof:placetype":"venue"
},
  "geometry": {"coordinates":[-81.21430599999999,28.783943],"type":"Point"}
}