{
  "type": "Feature",
  "properties": {
    "iso:country":"US",
    "sg:address":"12612 NW South River Dr",
    "sg:city":"Miami",
    "sg:classifiers":[
        {
            "category":"Banks & Credit Unions",
            "subcategory":"Financial Services",
            "type":"Services"
        }
    ],
    "sg:phone":"+1 305 829 2027",
    "sg:postcode":"33178",
    "sg:province":"FL",
    "sg:tags":[
        "investor"
    ],
    "wof:name":"In Machin Property Investments",
    "wof:placetype":"venue"
},
  "geometry": {"coordinates":[-80.368889,25.887983],"type":"Point"}
}