{
  "type": "Feature",
  "properties": {
    "iso:country":"US",
    "sg:address":"510 Douglas Ave",
    "sg:city":"Altamonte Spgs",
    "sg:classifiers":[
        {
            "category":"Wholesale",
            "subcategory":"Medical Equipment & Supplies",
            "type":"Manufacturing & Wholesale Goods"
        }
    ],
    "sg:phone":"+1 407 339 3968",
    "sg:postcode":"32714",
    "sg:province":"FL",
    "sg:tags":[
        "x",
        "apparatus"
    ],
    "wof:name":"Rads Mobil X-Ray",
    "wof:placetype":"venue"
},
  "geometry": {"coordinates":[-81.390424,28.671495],"type":"Point"}
}