{
  "type": "Feature",
  "properties": {
    "addr:full":"6536 Beach Blvd Jacksonville FL 32216",
    "addr:housenumber":"6536",
    "addr:postcode":"32216",
    "addr:street":"Beach Blvd",
    "iso:country":"US",
    "sg:address":"6536 Beach Blvd",
    "sg:city":"Jacksonville",
    "sg:classifiers":[
        {
            "category":"Autos & Motor Vehicles",
            "subcategory":"Automobile Sales",
            "type":"Retail Goods"
        }
    ],
    "sg:phone":"+1 904 721 7444",
    "sg:postcode":"32216",
    "sg:province":"FL",
    "sg:tags":[
        "car",
        "dealer"
    ],
    "wof:name":"Florida Import Export",
    "wof:placetype":"venue"
},
  "geometry": {"coordinates":[-81.593019,30.290212],"type":"Point"}
}