{
  "type": "Feature",
  "properties": {
    "iso:country":"US",
    "sg:address":"529 N Atlantic Ave",
    "sg:city":"Daytona Beach",
    "sg:classifiers":[
        {
            "category":"Personal",
            "subcategory":"Beauty Salon",
            "type":"Services"
        }
    ],
    "sg:phone":"+1 386 255 6067",
    "sg:postcode":"32118",
    "sg:province":"FL",
    "wof:name":"Hot Braids",
    "wof:placetype":"venue"
},
  "geometry": {"coordinates":[-81.012321,29.235061],"type":"Point"}
}