{
  "type": "Feature",
  "properties": {
    "addr:full":"630 S Miami Ave Miami FL 33130",
    "addr:housenumber":"630",
    "addr:postcode":"33130",
    "addr:street":"S Miami Ave",
    "iso:country":"US",
    "sg:address":"630 S Miami Ave",
    "sg:city":"Miami",
    "sg:classifiers":[
        {
            "category":"Shopping",
            "subcategory":"News",
            "type":"Retail Goods"
        }
    ],
    "sg:phone":"+1 305 373 3810",
    "sg:postcode":"33130",
    "sg:province":"FL",
    "sg:tags":[
        "stand"
    ],
    "wof:name":"Brickell Village News",
    "wof:placetype":"venue"
},
  "geometry": {"coordinates":[-80.19343600000001,25.767658],"type":"Point"}
}