{
  "type": "Feature",
  "properties": {
    "addr:full":"14171 SW 139th Ct Miami FL 33186",
    "addr:housenumber":"14171",
    "addr:postcode":"33186",
    "addr:street":"Sw 139Th Ct",
    "iso:country":"US",
    "sg:address":"14171 SW 139th Ct",
    "sg:city":"Miami",
    "sg:classifiers":[
        {
            "category":"Wholesale",
            "subcategory":"Medical Equipment & Supplies",
            "type":"Manufacturing & Wholesale Goods"
        }
    ],
    "sg:phone":"+1 305 251 5049",
    "sg:postcode":"33186",
    "sg:province":"FL",
    "wof:name":"W&M Care Svcs Inc",
    "wof:placetype":"venue"
},
  "geometry": {"coordinates":[-80.419754,25.636236],"type":"Point"}
}