{
  "type": "Feature",
  "properties": {
    "iso:country":"US",
    "sg:address":"3911 Jog Rd",
    "sg:city":"Greenacres",
    "sg:classifiers":[
        {
            "category":"Shopping",
            "type":"Retail Goods"
        },
        {
            "category":"Shopping",
            "subcategory":"Florist",
            "type":"Retail Goods"
        }
    ],
    "sg:phone":"+1 561 965 6335",
    "sg:postcode":"33467",
    "sg:province":"FL",
    "sg:tags":[
        "plant",
        "flower",
        "tree",
        "artificial"
    ],
    "wof:name":"Amanda's Floral Design",
    "wof:placetype":"venue"
},
  "geometry": {"coordinates":[-80.146779,26.619222],"type":"Point"}
}