{
  "type": "Feature",
  "properties": {
    "addr:full":"894 Palm Bay Rd NE Palm Bay FL 32905",
    "addr:housenumber":"894",
    "addr:postcode":"32905",
    "addr:street":"Palm Bay Rd Ne",
    "iso:country":"US",
    "sg:address":"894 Palm Bay Rd NE",
    "sg:city":"Palm Bay",
    "sg:classifiers":[
        {
            "category":"Retail",
            "subcategory":"Auto Rental",
            "type":"Services"
        }
    ],
    "sg:phone":"+1 321 724 1960",
    "sg:postcode":"32905",
    "sg:province":"FL",
    "sg:tags":[
        "renting",
        "truck",
        "leasing"
    ],
    "wof:name":"U-Haul Co",
    "wof:placetype":"venue"
},
  "geometry": {"coordinates":[-80.64928399999999,28.035158],"type":"Point"}
}