{
  "type": "Feature",
  "properties": {
    "iso:country":"US",
    "sg:address":"11854 W Dixie Hwy",
    "sg:city":"Miami",
    "sg:classifiers":[
        {
            "category":"Communications",
            "subcategory":"Film & Video Production",
            "type":"Services"
        },
        {
            "category":"Shopping",
            "subcategory":"Music",
            "type":"Retail Goods"
        }
    ],
    "sg:phone":"+1 305 895 8006",
    "sg:postcode":"33161",
    "sg:province":"FL",
    "sg:tags":[
        "record",
        "tapes-wholesale",
        "cd's",
        "dvd's",
        "store",
        "manufacturer"
    ],
    "wof:name":"Maxi Sound Music Hall",
    "wof:placetype":"venue"
},
  "geometry": {"coordinates":[-80.193298,25.8839],"type":"Point"}
}