{
  "type": "Feature",
  "properties": {
    "iso:country":"US",
    "sg:address":"13651 Hays Rd",
    "sg:city":"Brooksville",
    "sg:classifiers":[
        {
            "category":"Organizations",
            "subcategory":"Religious Organization",
            "type":"Services"
        }
    ],
    "sg:phone":"+1 727 857 2600",
    "sg:postcode":"34610",
    "sg:province":"FL",
    "sg:website":"www.bmchs.com",
    "wof:name":"Bishop Mc Laughlin Catholic",
    "wof:placetype":"venue"
},
  "geometry": {"coordinates":[-82.569068,28.329905],"type":"Point"}
}