{
  "type": "Feature",
  "properties": {
    "addr:full":"35 Edward Higgins Ter Sanford FL 32771",
    "addr:housenumber":"35",
    "addr:postcode":"32771",
    "addr:street":"Edward Higgins Ter",
    "iso:country":"US",
    "sg:address":"35 Edward Higgins Ter",
    "sg:city":"Sanford",
    "sg:classifiers":[
        {
            "category":"Education",
            "subcategory":"School",
            "type":"Public Place"
        }
    ],
    "sg:phone":"+1 407 322 1034",
    "sg:postcode":"32771",
    "sg:province":"FL",
    "wof:name":"Harbor School",
    "wof:placetype":"venue"
},
  "geometry": {"coordinates":[-81.28024600000001,28.80975],"type":"Point"}
}