{
  "type": "Feature",
  "properties": {
    "iso:country":"US",
    "sg:address":"3755 Tenoroc Mine Rd",
    "sg:city":"Lakeland",
    "sg:classifiers":[
        {
            "category":"Shopping",
            "subcategory":"Bicycles & Sporting Goods",
            "type":"Retail Goods"
        }
    ],
    "sg:phone":"+1 863 666 2500",
    "sg:postcode":"33805",
    "sg:province":"FL",
    "sg:tags":[
        "gun",
        "gunsmith"
    ],
    "sg:website":"www.tenoroc.us",
    "wof:name":"Tenoroc Shooting Sports",
    "wof:placetype":"venue"
},
  "geometry": {"coordinates":[-81.86897,28.104227],"type":"Point"}
}