{
  "type": "Feature",
  "properties": {
    "addr:full":"211 NE Olive Ave Port St Lucie FL 34952",
    "addr:housenumber":"211",
    "addr:postcode":"34952",
    "addr:street":"Ne Olive Ave",
    "iso:country":"US",
    "sg:address":"211 NE Olive Ave",
    "sg:city":"Port St Lucie",
    "sg:classifiers":[
        {
            "category":"Professional",
            "subcategory":"Business Services",
            "type":"Services"
        }
    ],
    "sg:phone":"+1 772 344 0563",
    "sg:postcode":"34952",
    "sg:province":"FL",
    "sg:tags":[
        "record",
        "document"
    ],
    "wof:name":"Terry L Deangelis Records Mgmt",
    "wof:placetype":"venue"
},
  "geometry": {"coordinates":[-80.329778,27.330843],"type":"Point"}
}