{
  "type": "Feature",
  "properties": {
    "iso:country":"US",
    "sg:address":"55 S Main St",
    "sg:city":"Williston",
    "sg:classifiers":[
        {
            "category":"Government",
            "subcategory":"Office",
            "type":"Public Place"
        }
    ],
    "sg:phone":"+1 352 528 6091",
    "sg:postcode":"32696",
    "sg:province":"FL",
    "sg:tags":[
        "policy"
    ],
    "wof:name":"Levy County Tax Collector",
    "wof:placetype":"venue"
},
  "geometry": {"coordinates":[-82.44714,29.387233],"type":"Point"}
}