{
  "type": "Feature",
  "properties": {
    "addr:full":"7811 Lawrence Rd Boynton Beach FL 33436",
    "addr:housenumber":"7811",
    "addr:postcode":"33436",
    "addr:street":"Lawrence Rd",
    "iso:country":"US",
    "sg:address":"7811 Lawrence Rd",
    "sg:city":"Boynton Beach",
    "sg:classifiers":[
        {
            "category":"Building & Trades",
            "subcategory":"Landscaping Services",
            "type":"Services"
        }
    ],
    "sg:phone":"+1 561 965 0547",
    "sg:postcode":"33436",
    "sg:province":"FL",
    "wof:name":"Lawngreen Landscaping Inc",
    "wof:placetype":"venue"
},
  "geometry": {"coordinates":[-80.105774,26.558715],"type":"Point"}
}