{
  "type": "Feature",
  "properties": {
    "iso:country":"US",
    "sg:address":"1640 Miller Ave Unit Bb",
    "sg:city":"Clearwater",
    "sg:classifiers":[
        {
            "category":"Home & Garden",
            "subcategory":"Furniture",
            "type":"Retail Goods"
        },
        {
            "category":"Home & Garden",
            "subcategory":"Home Furnishings",
            "type":"Retail Goods"
        },
        {
            "category":"Building & Trades",
            "subcategory":"Construction",
            "type":"Services"
        },
        {
            "category":"Wholesale",
            "subcategory":"Home Furnishings",
            "type":"Manufacturing & Wholesale Goods"
        }
    ],
    "sg:phone":"+1 727 585 4406",
    "sg:postcode":"33756",
    "sg:province":"FL",
    "sg:tags":[
        "equipment-wholesale",
        "kitchen",
        "cabinet",
        "refacing",
        "resurfacing",
        "equipment-household",
        "maker",
        "cabinets-refinishing",
        "manufacturer"
    ],
    "wof:name":"Buis Custom Cabinets Inc",
    "wof:placetype":"venue"
},
  "geometry": {"coordinates":[-82.793164,27.938201],"type":"Point"}
}