{
  "type": "Feature",
  "properties": {
    "addr:full":"700 Maguire Blvd Orlando FL 32803",
    "addr:housenumber":"700",
    "addr:postcode":"32803",
    "addr:street":"Maguire Blvd",
    "iso:country":"US",
    "sg:address":"700 Maguire Blvd",
    "sg:city":"Orlando",
    "sg:classifiers":[
        {
            "category":"Professional",
            "type":"Services"
        },
        {
            "category":"Restaurant",
            "type":"Food & Drink"
        },
        {
            "category":"Fast Food",
            "type":"Food & Drink"
        }
    ],
    "sg:phone":"+1 407 898 2960",
    "sg:postcode":"32803",
    "sg:province":"FL",
    "sg:tags":[
        "delivery",
        "take",
        "pizza"
    ],
    "sg:website":"http://www.pizzahut.com",
    "wof:name":"Pizza Hut",
    "wof:placetype":"venue"
},
  "geometry": {"coordinates":[-81.344711,28.5534],"type":"Point"}
}