{
  "type": "Feature",
  "properties": {
    "iso:country":"US",
    "sg:address":"3636 Blanding Blvd",
    "sg:city":"Jacksonville",
    "sg:classifiers":[
        {
            "category":"Shopping",
            "subcategory":"Crafts & Fabrics",
            "type":"Retail Goods"
        }
    ],
    "sg:phone":"+1 904 771 6535",
    "sg:postcode":"32210",
    "sg:province":"FL",
    "sg:tags":[
        "sewing"
    ],
    "sg:website":"www.joann.com",
    "wof:name":"Jo-Ann Fabrics & Crafts",
    "wof:placetype":"venue"
},
  "geometry": {"coordinates":[-81.73711,30.268279],"type":"Point"}
}