{
  "type": "Feature",
  "properties": {
    "iso:country":"US",
    "sg:address":"5500 Military Tr.  Suite 22-105",
    "sg:city":"Jupiter",
    "sg:classifiers":[
        {
            "category":"Professional",
            "subcategory":"Business Services",
            "type":"Services"
        }
    ],
    "sg:phone":"+1 800 928 2086",
    "sg:postcode":"33458",
    "sg:province":"FL",
    "sg:tags":[
        "voice-broadcasting",
        "group-call",
        "mass-text-message"
    ],
    "sg:website":"http://www.dialmycalls.com",
    "wof:name":"DialMyCalls.com",
    "wof:placetype":"venue"
},
  "geometry": {"coordinates":[-80.103526,26.886488],"type":"Point"}
}