{
  "type": "Feature",
  "properties": {
    "iso:country":"US",
    "sg:address":"6482 Lake Worth Rd",
    "sg:city":"Lake Worth",
    "sg:classifiers":[
        {
            "category":"Wholesale",
            "subcategory":"Machinery & Supplies",
            "type":"Manufacturing & Wholesale Goods"
        }
    ],
    "sg:phone":"+1 561 439 4050",
    "sg:postcode":"33463",
    "sg:province":"FL",
    "sg:tags":[
        "equipment",
        "establishment"
    ],
    "wof:name":"Nail City Inc",
    "wof:placetype":"venue"
},
  "geometry": {"coordinates":[-80.146558,26.618881],"type":"Point"}
}