{
  "type": "Feature",
  "properties": {
    "iso:country":"US",
    "sg:address":"5542 High St",
    "sg:city":"New Port Richey",
    "sg:classifiers":[
        {
            "category":"Health Services",
            "subcategory":"Doctor",
            "type":"Services"
        }
    ],
    "sg:phone":"+1 727 845 9168",
    "sg:postcode":"34652",
    "sg:province":"FL",
    "sg:tags":[
        "clinic"
    ],
    "wof:name":"Memory Diagnostic Ctr",
    "wof:placetype":"venue"
},
  "geometry": {"coordinates":[-82.721407,28.236094],"type":"Point"}
}