{
  "type": "Feature",
  "properties": {
    "iso:country":"US",
    "sg:address":"1954 Park Meadows Dr",
    "sg:city":"Fort Myers",
    "sg:classifiers":[
        {
            "category":"Manufacturing",
            "subcategory":"Apparel",
            "type":"Manufacturing & Wholesale Goods"
        }
    ],
    "sg:phone":"+1 239 939 3300",
    "sg:postcode":"33907",
    "sg:province":"FL",
    "sg:tags":[
        "product",
        "merchandise",
        "mfg"
    ],
    "wof:name":"Riverside Covers",
    "wof:placetype":"venue"
},
  "geometry": {"coordinates":[-81.882825,26.56697],"type":"Point"}
}