{
  "type": "Feature",
  "properties": {
    "iso:country":"US",
    "sg:address":"302 W Pine St",
    "sg:city":"Lantana",
    "sg:classifiers":[
        {
            "category":"Shopping",
            "subcategory":"Used Merchandise",
            "type":"Retail Goods"
        }
    ],
    "sg:phone":"+1 561 547 9771",
    "sg:postcode":"33462",
    "sg:province":"FL",
    "sg:tags":[
        "antique"
    ],
    "wof:name":"Barefoot Mailman Antiques",
    "wof:placetype":"venue"
},
  "geometry": {"coordinates":[-80.052296,26.582814],"type":"Point"}
}