{
  "type": "Feature",
  "properties": {
    "addr:full":"7075 W 20th Ave Hialeah FL 33014",
    "addr:housenumber":"7075",
    "addr:postcode":"33014",
    "addr:street":"W 20Th Ave",
    "iso:country":"US",
    "sg:address":"7075 W 20th Ave",
    "sg:city":"Hialeah",
    "sg:classifiers":[
        {
            "category":"Manufacturing",
            "subcategory":"Furniture",
            "type":"Manufacturing & Wholesale Goods"
        }
    ],
    "sg:phone":"+1 305 231 8840",
    "sg:postcode":"33014",
    "sg:province":"FL",
    "sg:tags":[
        "manufacture",
        "storage",
        "rack",
        "merchandise",
        "display"
    ],
    "wof:name":"T X L Mezzanine Systems",
    "wof:placetype":"venue"
},
  "geometry": {"coordinates":[-80.32324699999999,25.885657],"type":"Point"}
}