{
  "type": "Feature",
  "properties": {
    "addr:full":"1210 NW 27th Ave Pompano Beach FL 33069",
    "addr:housenumber":"1210",
    "addr:postcode":"33069",
    "addr:street":"Nw 27Th Ave",
    "iso:country":"US",
    "sg:address":"1210 NW 27th Ave",
    "sg:city":"Pompano Beach",
    "sg:classifiers":[
        {
            "category":"Organizations",
            "subcategory":"Religious Organization",
            "type":"Services"
        }
    ],
    "sg:phone":"+1 954 957 2693",
    "sg:postcode":"33069",
    "sg:province":"FL",
    "sg:tags":[
        "church"
    ],
    "wof:name":"Ebenezer Sda Church",
    "wof:placetype":"venue"
},
  "geometry": {"coordinates":[-80.159488,26.246934],"type":"Point"}
}