{
  "type": "Feature",
  "properties": {
    "iso:country":"US",
    "sg:address":"13501 SW 128th St",
    "sg:city":"Miami",
    "sg:classifiers":[
        {
            "category":"Wholesale",
            "subcategory":"Computers",
            "type":"Manufacturing & Wholesale Goods"
        },
        {
            "category":"Wholesale",
            "subcategory":"Durable Goods & Equipment",
            "type":"Manufacturing & Wholesale Goods"
        }
    ],
    "sg:phone":"+1 305 254 9050",
    "sg:postcode":"33186",
    "sg:province":"FL",
    "sg:tags":[
        "software",
        "exporter",
        "furniture"
    ],
    "sg:website":"www.panintertrade.com",
    "wof:name":"Panintertrade Inc",
    "wof:placetype":"venue"
},
  "geometry": {"coordinates":[-80.41451600000001,25.648403],"type":"Point"}
}