{
  "type": "Feature",
  "properties": {
    "iso:country":"US",
    "sg:address":"6537 NW 13th Ct",
    "sg:city":"Plantation",
    "sg:classifiers":[
        {
            "category":"Wholesale",
            "subcategory":"Auto Parts",
            "type":"Manufacturing & Wholesale Goods"
        }
    ],
    "sg:phone":"+1 954 583 6440",
    "sg:postcode":"33313",
    "sg:province":"FL",
    "sg:tags":[
        "body",
        "shop",
        "equipment",
        "automobile",
        "supply"
    ],
    "wof:name":"Auto Clip & Body Supply",
    "wof:placetype":"venue"
},
  "geometry": {"coordinates":[-80.236453,26.141409],"type":"Point"}
}