{
  "type": "Feature",
  "properties": {
    "addr:full":"16150 Jog Rd Delray Beach FL 33446",
    "addr:postcode":"16150;33446",
    "addr:street":"Jog Rd",
    "iso:country":"US",
    "sg:address":"16150 Jog Rd",
    "sg:city":"Delray Beach",
    "sg:classifiers":[
        {
            "category":"Social Services",
            "subcategory":"Adult Care",
            "type":"Services"
        }
    ],
    "sg:phone":"+1 561 498 5552",
    "sg:postcode":"33446",
    "sg:province":"FL",
    "sg:tags":[
        "home",
        "residential"
    ],
    "wof:name":"Arden Courts",
    "wof:placetype":"venue"
},
  "geometry": {"coordinates":[-80.14648200000001,26.435792],"type":"Point"}
}