{
  "type": "Feature",
  "properties": {
    "addr:full":"3400 57th St N Saint Petersburg FL 33710",
    "addr:housenumber":"3400",
    "addr:postcode":"33710",
    "addr:street":"57Th St N",
    "iso:country":"US",
    "sg:address":"3400 57th St N",
    "sg:city":"Saint Petersburg",
    "sg:classifiers":[
        {
            "category":"Building & Trades",
            "subcategory":"Construction",
            "type":"Services"
        }
    ],
    "sg:phone":"+1 727 347 6352",
    "sg:postcode":"33710",
    "sg:province":"FL",
    "wof:name":"Professional Highway Main",
    "wof:placetype":"venue"
},
  "geometry": {"coordinates":[-82.71134499999999,27.803832],"type":"Point"}
}