{
  "type": "Feature",
  "properties": {
    "addr:full":"6600 NW 27th Ave Ste 110 Miami FL 33147",
    "addr:housenumber":"6600",
    "addr:postcode":"33147",
    "addr:street":"Nw 27Th Ave Ste 110",
    "iso:country":"US",
    "sg:address":"6600 NW 27th Ave Ste 110",
    "sg:city":"Miami",
    "sg:classifiers":[
        {
            "category":"Building & Trades",
            "subcategory":"Construction",
            "type":"Services"
        },
        {
            "category":"Military Area",
            "subcategory":"Armory",
            "type":"Public Place"
        }
    ],
    "sg:phone":"+1 305 406 2116",
    "sg:postcode":"33147",
    "sg:province":"FL",
    "sg:tags":[
        "repair",
        "fence-sales",
        "fence",
        "contractor"
    ],
    "wof:name":"Bell & Son Fence Co Inc",
    "wof:placetype":"venue"
},
  "geometry": {"coordinates":[-80.241371,25.834419],"type":"Point"}
}