{
  "type": "Feature",
  "properties": {
    "iso:country":"US",
    "sg:address":"13700 Sutton Park Dr N",
    "sg:city":"Jacksonville",
    "sg:classifiers":[
        {
            "category":"Real Estate",
            "subcategory":"Real Estate Operator",
            "type":"Services"
        }
    ],
    "sg:phone":"+1 904 223 1171",
    "sg:postcode":"32224",
    "sg:province":"FL",
    "sg:tags":[
        "building",
        "apartment"
    ],
    "wof:name":"Links At Windsor Parke",
    "wof:placetype":"venue"
},
  "geometry": {"coordinates":[-81.462969,30.265529],"type":"Point"}
}