{
  "type": "Feature",
  "properties": {
    "addr:full":"11100 Astronaut Blvd Orlando FL 32837",
    "addr:postcode":"11100;32837",
    "addr:street":"Astronaut Blvd",
    "iso:country":"US",
    "sg:address":"11100 Astronaut Blvd",
    "sg:city":"Orlando",
    "sg:classifiers":[
        {
            "category":"Wholesale",
            "subcategory":"Electrical",
            "type":"Manufacturing & Wholesale Goods"
        }
    ],
    "sg:phone":"+1 407 851 7830",
    "sg:postcode":"32837",
    "sg:province":"FL",
    "sg:tags":[
        "equipment",
        "outdoor",
        "lighting",
        "rent"
    ],
    "wof:name":"Airstar Florida Ltg Ballons",
    "wof:placetype":"venue"
},
  "geometry": {"coordinates":[-81.39918900000001,28.404636],"type":"Point"}
}