{
  "type": "Feature",
  "properties": {
    "addr:full":"1764 Branchwater Trl Orlando FL 32825",
    "addr:housenumber":"1764",
    "addr:postcode":"32825",
    "addr:street":"Branchwater Trl",
    "iso:country":"US",
    "sg:address":"1764 Branchwater Trl",
    "sg:city":"Orlando",
    "sg:classifiers":[
        {
            "category":"Building & Trades",
            "subcategory":"Electrical",
            "type":"Services"
        }
    ],
    "sg:phone":"+1 407 275 2973",
    "sg:postcode":"32825",
    "sg:province":"FL",
    "sg:tags":[
        "electrician"
    ],
    "wof:name":"Bjm Electric Company",
    "wof:placetype":"venue"
},
  "geometry": {"coordinates":[-81.22699900000001,28.51883],"type":"Point"}
}