{
  "type": "Feature",
  "properties": {
    "iso:country":"US",
    "sg:address":"37234 Florida Ave",
    "sg:city":"Dade City",
    "sg:classifiers":[
        {
            "category":"Professional",
            "type":"Services"
        }
    ],
    "sg:phone":"+1 352 518 8076",
    "sg:postcode":"33525",
    "sg:province":"FL",
    "wof:name":"Stained Glass Excellence",
    "wof:placetype":"venue"
},
  "geometry": {"coordinates":[-82.199428,28.359576],"type":"Point"}
}