{
  "type": "Feature",
  "properties": {
    "iso:country":"US",
    "sg:address":"11095 Hearth Rd",
    "sg:city":"Spring Hill",
    "sg:classifiers":[
        {
            "category":"Real Estate",
            "subcategory":"Real Estate Agent",
            "type":"Services"
        }
    ],
    "sg:phone":"+1 352 686 9110",
    "sg:postcode":"34608",
    "sg:province":"FL",
    "wof:name":"Florida Homeland Realty",
    "wof:placetype":"venue"
},
  "geometry": {"coordinates":[-82.541909,28.49473],"type":"Point"}
}