{
  "type": "Feature",
  "properties": {
    "addr:full":"9695 Delegates Dr Orlando FL 32837",
    "addr:housenumber":"9695",
    "addr:postcode":"32837",
    "addr:street":"Delegates Dr",
    "iso:country":"US",
    "sg:address":"9695 Delegates Dr",
    "sg:city":"Orlando",
    "sg:classifiers":[
        {
            "category":"Wholesale",
            "subcategory":"Medical Equipment & Supplies",
            "type":"Manufacturing & Wholesale Goods"
        }
    ],
    "sg:phone":"+1 407 563 5770",
    "sg:postcode":"32837",
    "sg:province":"FL",
    "sg:tags":[
        "pharmaceutical",
        "surgical"
    ],
    "wof:name":"Physician Sales & Service",
    "wof:placetype":"venue"
},
  "geometry": {"coordinates":[-81.407848,28.42959],"type":"Point"}
}