{
  "type": "Feature",
  "properties": {
    "iso:country":"US",
    "sg:address":"1253 Cricket Dr NE",
    "sg:city":"Palm Bay",
    "sg:classifiers":[
        {
            "category":"Building & Trades",
            "subcategory":"Construction",
            "type":"Services"
        }
    ],
    "sg:phone":"+1 321 536 0827",
    "sg:postcode":"32907",
    "sg:province":"FL",
    "sg:tags":[
        "contractor"
    ],
    "wof:name":"Vicente Jose & T Fence Co",
    "wof:placetype":"venue"
},
  "geometry": {"coordinates":[-80.634468,28.011118],"type":"Point"}
}