{
  "type": "Feature",
  "properties": {
    "iso:country":"US",
    "sg:address":"7781 Maclean Rd",
    "sg:city":"Tallahassee",
    "sg:classifiers":[
        {
            "category":"Professional",
            "subcategory":"Engineering",
            "type":"Services"
        }
    ],
    "sg:phone":"+1 850 894 0741",
    "sg:postcode":"32312",
    "sg:province":"FL",
    "sg:tags":[
        "engineer"
    ],
    "wof:name":"Cathers Consulting",
    "wof:placetype":"venue"
},
  "geometry": {"coordinates":[-84.243218,30.571084],"type":"Point"}
}