{
  "type": "Feature",
  "properties": {
    "iso:country":"US",
    "sg:address":"2000 Corporate Blvd NW",
    "sg:city":"Boca Raton",
    "sg:classifiers":[
        {
            "category":"Manufacturing",
            "subcategory":"Printing",
            "type":"Manufacturing & Wholesale Goods"
        }
    ],
    "sg:phone":"+1 561 994 0555",
    "sg:postcode":"33431",
    "sg:province":"FL",
    "sg:tags":[
        "publisher"
    ],
    "sg:website":"www.crcpress.com",
    "wof:name":"CRC Press Inc",
    "wof:placetype":"venue"
},
  "geometry": {"coordinates":[-80.12538499999999,26.37076],"type":"Point"}
}