{
  "type": "Feature",
  "properties": {
    "iso:country":"US",
    "sg:address":"4601 Edgemoor St",
    "sg:city":"Orlando",
    "sg:classifiers":[
        {
            "category":"Real Estate",
            "subcategory":"Real Estate Operator",
            "type":"Services"
        }
    ],
    "sg:phone":"+1 407 291 3083",
    "sg:postcode":"32811",
    "sg:province":"FL",
    "sg:tags":[
        "apartment"
    ],
    "wof:name":"Ivey Lane Resident Assn",
    "wof:placetype":"venue"
},
  "geometry": {"coordinates":[-81.437866,28.542354],"type":"Point"}
}