{
  "type": "Feature",
  "properties": {
    "addr:full":"6095 W 19th Ave Apt 401 Hialeah FL 33012",
    "addr:housenumber":"6095;401",
    "addr:postcode":"33012",
    "addr:street":"W 19Th Ave Apt",
    "iso:country":"US",
    "sg:address":"6095 W 19th Ave Apt 401",
    "sg:city":"Hialeah",
    "sg:classifiers":[
        {
            "category":"Banks & Credit Unions",
            "subcategory":"Investment Brokerage",
            "type":"Services"
        },
        {
            "category":"Manufacturing",
            "subcategory":"Petroleum Products",
            "type":"Manufacturing & Wholesale Goods"
        }
    ],
    "sg:phone":"+1 305 827 2912",
    "sg:postcode":"33012",
    "sg:province":"FL",
    "sg:tags":[
        "luminous",
        "chain"
    ],
    "wof:name":"Link Supply Chain Services Inc",
    "wof:placetype":"venue"
},
  "geometry": {"coordinates":[-80.321302,25.878097],"type":"Point"}
}