{
  "type": "Feature",
  "properties": {
    "iso:country":"US",
    "sg:address":"2095 Siesta Dr",
    "sg:city":"Sarasota",
    "sg:classifiers":[
        {
            "category":"Personal",
            "subcategory":"Beauty Salon",
            "type":"Services"
        }
    ],
    "sg:phone":"+1 941 954 5584",
    "sg:postcode":"34239",
    "sg:province":"FL",
    "sg:tags":[
        "shop"
    ],
    "wof:name":"Fancy Nails",
    "wof:placetype":"venue"
},
  "geometry": {"coordinates":[-82.528068,27.302924],"type":"Point"}
}