{
  "type": "Feature",
  "properties": {
    "addr:full":"4314 S Hale Ave Tampa FL 33611",
    "addr:housenumber":"4314",
    "addr:postcode":"33611",
    "addr:street":"S Hale Ave",
    "iso:country":"US",
    "sg:address":"4314 S Hale Ave",
    "sg:city":"Tampa",
    "sg:classifiers":[
        {
            "category":"Building & Trades",
            "subcategory":"Landscaping Services",
            "type":"Services"
        }
    ],
    "sg:phone":"+1 813 837 9077",
    "sg:postcode":"33611",
    "sg:province":"FL",
    "wof:name":"Lawns Limbs & Landscape",
    "wof:placetype":"venue"
},
  "geometry": {"coordinates":[-82.511426,27.901864],"type":"Point"}
}