{
  "type": "Feature",
  "properties": {
    "iso:country":"US",
    "sg:address":"15924 SW 92nd Ave",
    "sg:city":"Miami",
    "sg:classifiers":[
        {
            "category":"Sports & Exercise",
            "subcategory":"Gym",
            "type":"Entertainment"
        }
    ],
    "sg:phone":"+1 305 256 0065",
    "sg:postcode":"33157",
    "sg:province":"FL",
    "sg:tags":[
        "club",
        "health",
        "studio",
        "gymnasium"
    ],
    "sg:website":"www.goldgym.com",
    "wof:name":"Gold's Gym",
    "wof:placetype":"venue"
},
  "geometry": {"coordinates":[-80.342168,25.622747],"type":"Point"}
}