{
  "type": "Feature",
  "properties": {
    "iso:country":"US",
    "sg:address":"7976 Lasalle Blvd",
    "sg:city":"Hollywood",
    "sg:classifiers":[
        {
            "category":"Building & Trades",
            "subcategory":"Construction",
            "type":"Services"
        }
    ],
    "sg:phone":"+1 954 989 4533",
    "sg:postcode":"33023",
    "sg:province":"FL",
    "sg:tags":[
        "contractor"
    ],
    "wof:name":"Two Kids Enterprises",
    "wof:placetype":"venue"
},
  "geometry": {"coordinates":[-80.245642,25.984281],"type":"Point"}
}