{
  "type": "Feature",
  "properties": {
    "iso:country":"US",
    "sg:address":"4270 Aloma Ave Ste 142",
    "sg:city":"Winter Park",
    "sg:classifiers":[
        {
            "category":"Personal",
            "subcategory":"Tanning Parlor",
            "type":"Services"
        }
    ],
    "sg:phone":"+1 407 678 7773",
    "sg:postcode":"32792",
    "sg:province":"FL",
    "sg:website":"www.thesuntancenter.com",
    "wof:name":"Sun Tan Center",
    "wof:placetype":"venue"
},
  "geometry": {"coordinates":[-81.2985,28.6064],"type":"Point"}
}