{
  "type": "Feature",
  "properties": {
    "iso:country":"US",
    "sg:address":"5644 Cypress Cir",
    "sg:city":"Tallahassee",
    "sg:classifiers":[
        {
            "category":"Building & Trades",
            "subcategory":"Construction",
            "type":"Services"
        }
    ],
    "sg:phone":"+1 850 514 3755",
    "sg:postcode":"32303",
    "sg:province":"FL",
    "sg:tags":[
        "floor",
        "laying",
        "contractor"
    ],
    "wof:name":"Jim H Wilson Sr Carpet Install",
    "wof:placetype":"venue"
},
  "geometry": {"coordinates":[-84.374256,30.516421],"type":"Point"}
}