{
  "type": "Feature",
  "properties": {
    "iso:country":"US",
    "sg:address":"3807 Grand Ave",
    "sg:city":"Miami",
    "sg:classifiers":[
        {
            "category":"Personal",
            "subcategory":"Beauty Salon",
            "type":"Services"
        }
    ],
    "sg:phone":"+1 305 448 9239",
    "sg:postcode":"33133",
    "sg:province":"FL",
    "sg:tags":[
        "shop",
        "equipment",
        "salons-equipment",
        "supply"
    ],
    "wof:name":"Discount Beauty & Barber Supl",
    "wof:placetype":"venue"
},
  "geometry": {"coordinates":[-80.25466900000001,25.727604],"type":"Point"}
}