{
  "type": "Feature",
  "properties": {
    "iso:country":"US",
    "sg:address":"3853 Coconut Rd",
    "sg:city":"Lake Worth",
    "sg:classifiers":[
        {
            "category":"Wholesale",
            "subcategory":"Hardware",
            "type":"Manufacturing & Wholesale Goods"
        }
    ],
    "sg:phone":"+1 954 938 2090",
    "sg:postcode":"33461",
    "sg:province":"FL",
    "sg:tags":[
        "construction",
        "marine"
    ],
    "wof:name":"Marine Hardware Specialties",
    "wof:placetype":"venue"
},
  "geometry": {"coordinates":[-80.09931,26.619116],"type":"Point"}
}