{
  "type": "Feature",
  "properties": {
    "iso:country":"US",
    "sg:address":"601 Cyprus Ave",
    "sg:city":"Clearwater",
    "sg:classifiers":[
        {
            "category":"Building & Trades",
            "subcategory":"Construction",
            "type":"Services"
        }
    ],
    "sg:phone":"+1 727 449 8746",
    "sg:postcode":"33767",
    "sg:province":"FL",
    "sg:tags":[
        "concrete",
        "contractor"
    ],
    "wof:name":"S L G Concrete",
    "wof:placetype":"venue"
},
  "geometry": {"coordinates":[-82.82503699999999,27.985876],"type":"Point"}
}