{
  "type": "Feature",
  "properties": {
    "addr:full":"1322 US Hwy 1 Sebastian FL 32958",
    "addr:housenumber":"1322",
    "addr:postcode":"32958",
    "addr:street":"Us Hwy 1",
    "iso:country":"US",
    "sg:address":"1322 US Hwy 1",
    "sg:city":"Sebastian",
    "sg:classifiers":[
        {
            "category":"Marine",
            "type":"Transportation"
        },
        {
            "category":"Museum",
            "type":"Entertainment"
        }
    ],
    "sg:phone":"+1 772 589 0435",
    "sg:postcode":"32958",
    "sg:province":"FL",
    "sg:tags":[
        "water",
        "gallery",
        "transport"
    ],
    "sg:website":"www.melfisher.com",
    "wof:name":"Mell Fischers Treasure Museum",
    "wof:placetype":"venue"
},
  "geometry": {"coordinates":[-80.46969900000001,27.818336],"type":"Point"}
}