{
  "type": "Feature",
  "properties": {
    "iso:country":"US",
    "sg:address":"2097 Trade Center Way",
    "sg:city":"Naples",
    "sg:classifiers":[
        {
            "category":"Wholesale",
            "subcategory":"Construction Materials",
            "type":"Manufacturing & Wholesale Goods"
        }
    ],
    "sg:phone":"+1 239 591 1433",
    "sg:postcode":"34109",
    "sg:province":"FL",
    "sg:tags":[
        "stone",
        "italian"
    ],
    "wof:name":"Porphyry USA Inc",
    "wof:placetype":"venue"
},
  "geometry": {"coordinates":[-81.777165,26.225262],"type":"Point"}
}