{
  "type": "Feature",
  "properties": {
    "addr:full":"419 Santa Barbara Blvd Cape Coral FL 33991",
    "addr:housenumber":"419",
    "addr:postcode":"33991",
    "addr:street":"Santa Barbara Blvd",
    "iso:country":"US",
    "sg:address":"419 Santa Barbara Blvd",
    "sg:city":"Cape Coral",
    "sg:classifiers":[
        {
            "category":"Retail",
            "subcategory":"Portrait Studio",
            "type":"Services"
        },
        {
            "category":"Professional",
            "subcategory":"Art Services",
            "type":"Services"
        }
    ],
    "sg:phone":"+1 239 458 5100",
    "sg:postcode":"33991",
    "sg:province":"FL",
    "sg:tags":[
        "photographer",
        "photography",
        "commercial"
    ],
    "wof:name":"Nocera Photographics",
    "wof:placetype":"venue"
},
  "geometry": {"coordinates":[-81.974097,26.642742],"type":"Point"}
}