{
  "type": "Feature",
  "properties": {
    "iso:country":"US",
    "sg:address":"19075 SW 49th Pl",
    "sg:city":"Dunnellon",
    "sg:classifiers":[
        {
            "category":"Building & Trades",
            "subcategory":"Construction",
            "type":"Services"
        }
    ],
    "sg:phone":"+1 352 465 3264",
    "sg:postcode":"34432",
    "sg:province":"FL",
    "sg:tags":[
        "hanging",
        "contractor"
    ],
    "wof:name":"Other World Painting Corp",
    "wof:placetype":"venue"
},
  "geometry": {"coordinates":[-82.441726,29.13871],"type":"Point"}
}