{
  "type": "Feature",
  "properties": {
    "addr:full":"2756 W Atlantic Blvd Pompano Beach FL 33069",
    "addr:housenumber":"2756",
    "addr:postcode":"33069",
    "addr:street":"W Atlantic Blvd",
    "iso:country":"US",
    "sg:address":"2756 W Atlantic Blvd",
    "sg:city":"Pompano Beach",
    "sg:classifiers":[
        {
            "category":"Education",
            "subcategory":"Vocational School",
            "type":"Public Place"
        }
    ],
    "sg:phone":"+1 954 975 5566",
    "sg:postcode":"33069",
    "sg:province":"FL",
    "sg:tags":[
        "technical",
        "trade"
    ],
    "wof:name":"American Intl Language School",
    "wof:placetype":"venue"
},
  "geometry": {"coordinates":[-80.160315,26.231167],"type":"Point"}
}