{
  "type": "Feature",
  "properties": {
    "addr:full":"6670 SW 12th St Miami FL 33144",
    "addr:housenumber":"6670",
    "addr:postcode":"33144",
    "addr:street":"Sw 12Th St",
    "iso:country":"US",
    "sg:address":"6670 SW 12th St",
    "sg:city":"Miami",
    "sg:classifiers":[
        {
            "category":"Food & Beverages",
            "subcategory":"Groceries & Convenience Stores",
            "type":"Retail Goods"
        }
    ],
    "sg:phone":"+1 305 265 2031",
    "sg:postcode":"33144",
    "sg:province":"FL",
    "wof:name":"Marielas Nica Grocery Store",
    "wof:placetype":"venue"
},
  "geometry": {"coordinates":[-80.302988,25.759437],"type":"Point"}
}