{
  "type": "Feature",
  "properties": {
    "addr:full":"25 McLeod St Merritt Island FL 32953",
    "addr:housenumber":"25",
    "addr:postcode":"32953",
    "addr:street":"Mcleod St",
    "iso:country":"US",
    "sg:address":"25 McLeod St",
    "sg:city":"Merritt Island",
    "sg:classifiers":[
        {
            "category":"Banks & Credit Unions",
            "subcategory":"Atm",
            "type":"Services"
        }
    ],
    "sg:phone":"+1 321 452 1580",
    "sg:postcode":"32953",
    "sg:province":"FL",
    "sg:tags":[
        "bankruptcy"
    ],
    "wof:name":"Ovletrea Shirley W PA",
    "wof:placetype":"venue"
},
  "geometry": {"coordinates":[-80.701531,28.357536],"type":"Point"}
}