{
  "type": "Feature",
  "properties": {
    "addr:full":"600 W New Nolte Rd St Cloud FL 34769",
    "addr:housenumber":"600",
    "addr:postcode":"34769",
    "addr:street":"W New Nolte Rd",
    "iso:country":"US",
    "sg:address":"600 W New Nolte Rd",
    "sg:city":"St Cloud",
    "sg:classifiers":[
        {
            "category":"Manufacturing",
            "subcategory":"Glass & Minerals",
            "type":"Manufacturing & Wholesale Goods"
        }
    ],
    "sg:phone":"+1 407 891 9183",
    "sg:postcode":"34769",
    "sg:province":"FL",
    "sg:tags":[
        "stucco"
    ],
    "wof:name":"Your Kind Of Stucco",
    "wof:placetype":"venue"
},
  "geometry": {"coordinates":[-81.27927099999999,28.224187],"type":"Point"}
}