{
  "type": "Feature",
  "properties": {
    "addr:full":"7350 Linton Blvd Delray Beach FL 33484",
    "addr:housenumber":"7350",
    "addr:postcode":"33484",
    "addr:street":"Linton Blvd",
    "iso:country":"US",
    "sg:address":"7350 Linton Blvd",
    "sg:city":"Delray Beach",
    "sg:classifiers":[
        {
            "category":"Sports & Exercise",
            "subcategory":"Golf",
            "type":"Entertainment"
        }
    ],
    "sg:phone":"+1 561 637 8806",
    "sg:postcode":"33484",
    "sg:province":"FL",
    "sg:tags":[
        "course",
        "maintenance"
    ],
    "wof:name":"Adison Reserve",
    "wof:placetype":"venue"
},
  "geometry": {"coordinates":[-80.15814399999999,26.439108],"type":"Point"}
}