{
  "type": "Feature",
  "properties": {
    "addr:full":"16002 Bay Vista Dr Clearwater FL 33760",
    "addr:housenumber":"16002",
    "addr:postcode":"33760",
    "addr:street":"Bay Vista Dr",
    "iso:country":"US",
    "sg:address":"16002 Bay Vista Dr",
    "sg:city":"Clearwater",
    "sg:classifiers":[
        {
            "category":"Social Services",
            "subcategory":"Job Training",
            "type":"Services"
        }
    ],
    "sg:phone":"+1 727 524 1757",
    "sg:postcode":"33760",
    "sg:province":"FL",
    "sg:tags":[
        "center"
    ],
    "wof:name":"Tech Data Training Center",
    "wof:placetype":"venue"
},
  "geometry": {"coordinates":[-82.708613,27.919398],"type":"Point"}
}