{
  "type": "Feature",
  "properties": {
    "addr:full":"6020 N Federal Hwy Boca Raton FL 33487",
    "addr:housenumber":"6020",
    "addr:postcode":"33487",
    "addr:street":"N Federal Hwy",
    "iso:country":"US",
    "sg:address":"6020 N Federal Hwy",
    "sg:city":"Boca Raton",
    "sg:classifiers":[
        {
            "category":"Professional",
            "subcategory":"Accounting & Tax Preparation",
            "type":"Services"
        }
    ],
    "sg:phone":"+1 561 862 0003",
    "sg:postcode":"33487",
    "sg:province":"FL",
    "sg:tags":[
        "accountant"
    ],
    "wof:name":"Globe Parcel",
    "wof:placetype":"venue"
},
  "geometry": {"coordinates":[-80.076173,26.403572],"type":"Point"}
}