{
  "type": "Feature",
  "properties": {
    "iso:country":"US",
    "sg:address":"8841 Park Blvd",
    "sg:city":"Seminole",
    "sg:classifiers":[
        {
            "category":"Bakery",
            "type":"Food & Drink"
        }
    ],
    "sg:menulink":"http://www.allmenus.com/fl/st-petersburg/102006-perkins-restaurant--bakery/menu/",
    "sg:phone":"+1 863 676 0991",
    "sg:postcode":"33777",
    "sg:province":"FL",
    "sg:tags":[
        "sandwich",
        "salad",
        "soup",
        "american",
        "pastry",
        "wrap"
    ],
    "wof:name":"Perkins Restaurant & Bakery",
    "wof:placetype":"venue"
},
  "geometry": {"coordinates":[-82.761442,27.840652],"type":"Point"}
}