{
  "type": "Feature",
  "properties": {
    "iso:country":"US",
    "sg:address":"3525 SW 130th Ave",
    "sg:city":"Miami",
    "sg:classifiers":[
        {
            "category":"Community Center",
            "subcategory":"Senior",
            "type":"Public Place"
        }
    ],
    "sg:phone":"+1 305 220 1041",
    "sg:postcode":"33175",
    "sg:province":"FL",
    "sg:tags":[
        "citizen"
    ],
    "wof:name":"Salome Residensia",
    "wof:placetype":"venue"
},
  "geometry": {"coordinates":[-80.40586500000001,25.735689],"type":"Point"}
}