{
  "type": "Feature",
  "properties": {
    "iso:country":"US",
    "sg:address":"6519 27th Way N",
    "sg:city":"Saint Petersburg",
    "sg:classifiers":[
        {
            "category":"Real Estate",
            "subcategory":"Real Estate Operator",
            "type":"Services"
        }
    ],
    "sg:phone":"+1 727 527 4097",
    "sg:postcode":"33702",
    "sg:province":"FL",
    "sg:tags":[
        "building",
        "nonresidential"
    ],
    "wof:name":"Jlf Properties Inc",
    "wof:placetype":"venue"
},
  "geometry": {"coordinates":[-82.670858,27.832179],"type":"Point"}
}