{
  "type": "Feature",
  "properties": {
    "addr:full":"6121 US Hwy 98 Lakeland FL 33809",
    "addr:housenumber":"6121",
    "addr:postcode":"33809",
    "addr:street":"Us Hwy 98",
    "iso:country":"US",
    "sg:address":"6121 US Hwy 98",
    "sg:city":"Lakeland",
    "sg:classifiers":[
        {
            "category":"Building & Trades",
            "subcategory":"Construction",
            "type":"Services"
        }
    ],
    "sg:phone":"+1 863 816 1328",
    "sg:postcode":"33809",
    "sg:province":"FL",
    "sg:tags":[
        "material",
        "contractor"
    ],
    "wof:name":"Custom Coatings",
    "wof:placetype":"venue"
},
  "geometry": {"coordinates":[-81.982145,28.171566],"type":"Point"}
}