{
  "type": "Feature",
  "properties": {
    "addr:full":"5770 W Irlo Bronson Memorial Hwy Kissimmee FL 34746",
    "addr:housenumber":"5770",
    "addr:postcode":"34746",
    "addr:street":"W Irlo Bronson Memorial Hwy",
    "iso:country":"US",
    "sg:address":"5770 W Irlo Bronson Memorial Hwy",
    "sg:city":"Kissimmee",
    "sg:classifiers":[
        {
            "category":"Shopping",
            "subcategory":"Hobbies, Toys, & Games",
            "type":"Retail Goods"
        }
    ],
    "sg:phone":"+1 407 396 7999",
    "sg:postcode":"34746",
    "sg:province":"FL",
    "sg:tags":[
        "toy",
        "store"
    ],
    "wof:name":"M G Men's Wear Brands Inc",
    "wof:placetype":"venue"
},
  "geometry": {"coordinates":[-81.51558,28.332373],"type":"Point"}
}