{
  "type": "Feature",
  "properties": {
    "addr:full":"5503 W Waters Ave Tampa FL 33634",
    "addr:housenumber":"5503",
    "addr:postcode":"33634",
    "addr:street":"W Waters Ave",
    "iso:country":"US",
    "sg:address":"5503 W Waters Ave",
    "sg:city":"Tampa",
    "sg:classifiers":[
        {
            "category":"Building & Trades",
            "subcategory":"Construction",
            "type":"Services"
        }
    ],
    "sg:phone":"+1 813 888 7961",
    "sg:postcode":"33634",
    "sg:province":"FL",
    "sg:tags":[
        "house"
    ],
    "wof:name":"Bay Craft Construction Inc",
    "wof:placetype":"venue"
},
  "geometry": {"coordinates":[-82.5348,28.025641],"type":"Point"}
}