{
  "type": "Feature",
  "properties": {
    "iso:country":"US",
    "sg:address":"531 W State Rd 436",
    "sg:city":"Altamonte Springs",
    "sg:classifiers":[
        {
            "category":"Recreation",
            "type":"Entertainment"
        }
    ],
    "sg:phone":"+1 407 682 4077",
    "sg:postcode":"32714",
    "sg:province":"FL",
    "sg:tags":[
        "course",
        "golf",
        "arcade"
    ],
    "wof:name":"Congo River Golf & Exploration Co",
    "wof:placetype":"venue"
},
  "geometry": {"coordinates":[-81.403637,28.662247],"type":"Point"}
}