{
  "type": "Feature",
  "properties": {
    "addr:full":"1003 Seagull Ln Lynn Haven FL 32444",
    "addr:housenumber":"1003",
    "addr:postcode":"32444",
    "addr:street":"Seagull Ln",
    "iso:country":"US",
    "sg:address":"1003 Seagull Ln",
    "sg:city":"Lynn Haven",
    "sg:classifiers":[
        {
            "category":"Wholesale",
            "subcategory":"Machinery & Supplies",
            "type":"Manufacturing & Wholesale Goods"
        }
    ],
    "sg:phone":"+1 850 265 6302",
    "sg:postcode":"32444",
    "sg:province":"FL",
    "sg:tags":[
        "heat",
        "mate",
        "representative",
        "processing"
    ],
    "wof:name":"Mark Design & Sales",
    "wof:placetype":"venue"
},
  "geometry": {"coordinates":[-85.678156,30.230888],"type":"Point"}
}