{
  "type": "Feature",
  "properties": {
    "iso:country":"US",
    "sg:address":"13851 S John Young Pkwy",
    "sg:city":"Orlando",
    "sg:classifiers":[
        {
            "category":"Personal",
            "subcategory":"Beauty Salon",
            "type":"Services"
        }
    ],
    "sg:phone":"+1 407 240 1339",
    "sg:postcode":"32837",
    "sg:province":"FL",
    "sg:tags":[
        "shop"
    ],
    "wof:name":"Supercuts",
    "wof:placetype":"venue"
},
  "geometry": {"coordinates":[-81.422225,28.361089],"type":"Point"}
}