{
  "type": "Feature",
  "properties": {
    "addr:full":"3328 W Columbus Dr Tampa FL 33607",
    "addr:housenumber":"3328",
    "addr:postcode":"33607",
    "addr:street":"W Columbus Dr",
    "iso:country":"US",
    "sg:address":"3328 W Columbus Dr",
    "sg:city":"Tampa",
    "sg:classifiers":[
        {
            "category":"Restaurant",
            "type":"Food & Drink"
        }
    ],
    "sg:phone":"+1 813 879 1357",
    "sg:postcode":"33607",
    "sg:province":"FL",
    "sg:tags":[
        "eating"
    ],
    "wof:name":"Arco-Iris Restaurant Inc",
    "wof:placetype":"venue"
},
  "geometry": {"coordinates":[-82.49884900000001,27.966647],"type":"Point"}
}