{
  "type": "Feature",
  "properties": {
    "addr:full":"11435 N Dale Mabry Hwy Tampa FL 33618",
    "addr:housenumber":"11435",
    "addr:postcode":"33618",
    "addr:street":"N Dale Mabry Hwy",
    "iso:country":"US",
    "sg:address":"11435 N Dale Mabry Hwy",
    "sg:city":"Tampa",
    "sg:phone":"+1 813 265 9844",
    "sg:postcode":"33618",
    "sg:province":"FL",
    "sg:website":"http://www.carrabbas.com/",
    "wof:name":"Carrabba's Italian Grill",
    "wof:placetype":"venue"
},
  "geometry": {"coordinates":[-82.504054,28.052443],"type":"Point"}
}