{
  "type": "Feature",
  "properties": {
    "iso:country":"US",
    "sg:address":"8730 Thomas Dr",
    "sg:city":"Panama City Bch",
    "sg:classifiers":[
        {
            "category":"Manufacturing",
            "subcategory":"Food",
            "type":"Manufacturing & Wholesale Goods"
        }
    ],
    "sg:phone":"+1 850 233 5950",
    "sg:postcode":"32408",
    "sg:province":"FL",
    "sg:tags":[
        "winery",
        "mfg"
    ],
    "wof:name":"Panama City Beach Winery",
    "wof:placetype":"venue"
},
  "geometry": {"coordinates":[-85.789581,30.16812],"type":"Point"}
}