{
  "type": "Feature",
  "properties": {
    "iso:country":"US",
    "sg:address":"2901 W Saint Isabell St",
    "sg:city":"Tampa",
    "sg:classifiers":[
        {
            "category":"Health Services",
            "subcategory":"Doctor",
            "type":"Services"
        }
    ],
    "sg:phone":"+1 813 875 2866",
    "sg:postcode":"33607",
    "sg:province":"FL",
    "sg:tags":[
        "medical"
    ],
    "wof:name":"Dennis D Jungerberg MD",
    "wof:placetype":"venue"
},
  "geometry": {"coordinates":[-82.493022,27.978799],"type":"Point"}
}