{
  "type": "Feature",
  "properties": {
    "addr:full":"655 Old Hwy 50 W Clermont FL 34711",
    "addr:housenumber":"655",
    "addr:postcode":"34711",
    "addr:street":"Old Hwy 50 W",
    "iso:country":"US",
    "sg:address":"655 Old Hwy 50 W",
    "sg:city":"Clermont",
    "sg:classifiers":[
        {
            "category":"Professional",
            "subcategory":"Lawyer & Legal Services",
            "type":"Services"
        }
    ],
    "sg:phone":"+1 352 243 9991",
    "sg:postcode":"34711",
    "sg:province":"FL",
    "wof:name":"Pamela J Helton PA",
    "wof:placetype":"venue"
},
  "geometry": {"coordinates":[-81.698324,28.565006],"type":"Point"}
}