{
  "type": "Feature",
  "properties": {
    "iso:country":"US",
    "sg:address":"33 Park Dr",
    "sg:city":"Lake Placid",
    "sg:classifiers":[
        {
            "category":"Restaurant",
            "type":"Food & Drink"
        }
    ],
    "sg:phone":"+1 863 465 0876",
    "sg:postcode":"33852",
    "sg:province":"FL",
    "sg:tags":[
        "eating"
    ],
    "wof:name":"Platters",
    "wof:placetype":"venue"
},
  "geometry": {"coordinates":[-81.369128,27.298211],"type":"Point"}
}