{
  "type": "Feature",
  "properties": {
    "addr:full":"17505 S Dixie Hwy Miami FL 33157",
    "addr:housenumber":"17505",
    "addr:postcode":"33157",
    "addr:street":"S Dixie Hwy",
    "iso:country":"US",
    "sg:address":"17505 S Dixie Hwy",
    "sg:city":"Miami",
    "sg:classifiers":[
        {
            "category":"Structure",
            "subcategory":"Office Building",
            "type":"Public Place"
        }
    ],
    "sg:phone":"+1 305 232 2326",
    "sg:postcode":"33157",
    "sg:province":"FL",
    "sg:tags":[
        "park"
    ],
    "wof:name":"Wp Properties",
    "wof:placetype":"venue"
},
  "geometry": {"coordinates":[-80.348203,25.607053],"type":"Point"}
}