{
  "type": "Feature",
  "properties": {
    "addr:full":"731 7th St W Palmetto FL 34221",
    "addr:housenumber":"731",
    "addr:postcode":"34221",
    "addr:street":"7Th St W",
    "iso:country":"US",
    "sg:address":"731 7th St W",
    "sg:city":"Palmetto",
    "sg:classifiers":[
        {
            "category":"Retail",
            "subcategory":"Repair Shop",
            "type":"Services"
        }
    ],
    "sg:phone":"+1 941 723 1487",
    "sg:postcode":"34221",
    "sg:province":"FL",
    "sg:tags":[
        "picture",
        "framing"
    ],
    "wof:name":"Framing By Robin",
    "wof:placetype":"venue"
},
  "geometry": {"coordinates":[-82.572,27.517507],"type":"Point"}
}