{
  "type": "Feature",
  "properties": {
    "addr:full":"10700 SW 109th Ct Miami FL 33176",
    "addr:housenumber":"10700",
    "addr:postcode":"33176",
    "addr:street":"Sw 109Th Ct",
    "iso:country":"US",
    "sg:address":"10700 SW 109th Ct",
    "sg:city":"Miami",
    "sg:classifiers":[
        {
            "category":"Building & Trades",
            "subcategory":"Construction",
            "type":"Services"
        }
    ],
    "sg:phone":"+1 305 596 5278",
    "sg:postcode":"33176",
    "sg:province":"FL",
    "sg:tags":[
        "contractor"
    ],
    "wof:name":"Felix Toral Garage Door Svc",
    "wof:placetype":"venue"
},
  "geometry": {"coordinates":[-80.37197500000001,25.670175],"type":"Point"}
}