{
  "type": "Feature",
  "properties": {
    "iso:country":"US",
    "sg:address":"11401 NW 12th St Ste 152",
    "sg:city":"Miami",
    "sg:classifiers":[
        {
            "category":"Shopping",
            "subcategory":"Shoes",
            "type":"Retail Goods"
        }
    ],
    "sg:phone":"+1 305 406 2174",
    "sg:postcode":"33172",
    "sg:province":"FL",
    "sg:tags":[
        "store"
    ],
    "wof:name":"Sole Leather Inc",
    "wof:placetype":"venue"
},
  "geometry": {"coordinates":[-80.37976999999999,25.782897],"type":"Point"}
}