{
  "type": "Feature",
  "properties": {
    "iso:country":"US",
    "sg:address":"230 E Interlake Blvd",
    "sg:city":"Lake Placid",
    "sg:classifiers":[
        {
            "category":"Health Services",
            "subcategory":"Podiatrist",
            "type":"Services"
        }
    ],
    "sg:phone":"+1 863 699 6001",
    "sg:postcode":"33852",
    "sg:province":"FL",
    "wof:name":"Foot Doctor",
    "wof:placetype":"venue"
},
  "geometry": {"coordinates":[-81.36364,27.297098],"type":"Point"}
}