{
  "type": "Feature",
  "properties": {
    "addr:full":"11310 Andy Dr Riverview FL 33569",
    "addr:housenumber":"11310",
    "addr:postcode":"33569",
    "addr:street":"Andy Dr",
    "iso:country":"US",
    "sg:address":"11310 Andy Dr",
    "sg:city":"Riverview",
    "sg:classifiers":[
        {
            "category":"Manufacturing",
            "subcategory":"Metals",
            "type":"Manufacturing & Wholesale Goods"
        }
    ],
    "sg:phone":"+1 305 968 4205",
    "sg:postcode":"33569",
    "sg:province":"FL",
    "sg:tags":[
        "steel",
        "distributor",
        "mill",
        "warehouse"
    ],
    "wof:name":"Peak Steel",
    "wof:placetype":"venue"
},
  "geometry": {"coordinates":[-82.31492799999999,27.858717],"type":"Point"}
}