{
  "type": "Feature",
  "properties": {
    "addr:full":"4765 Capital Cir NW Tallahassee FL 32303",
    "addr:housenumber":"4765",
    "addr:postcode":"32303",
    "addr:street":"Capital Cir Nw",
    "iso:country":"US",
    "sg:address":"4765 Capital Cir NW",
    "sg:city":"Tallahassee",
    "sg:classifiers":[
        {
            "category":"Autos & Motor Vehicles",
            "subcategory":"Automobile Sales",
            "type":"Retail Goods"
        },
        {
            "category":"Freight",
            "type":"Transportation"
        },
        {
            "category":"Retail",
            "subcategory":"Auto Rental",
            "type":"Services"
        },
        {
            "category":"Retail",
            "subcategory":"Auto Repair",
            "type":"Services"
        }
    ],
    "sg:phone":"+1 850 701 0163",
    "sg:postcode":"32303",
    "sg:province":"FL",
    "sg:tags":[
        "new",
        "truck",
        "trucking"
    ],
    "sg:website":"http://www.fourstarfreightliner.com",
    "wof:name":"Four Star Freightliner",
    "wof:placetype":"venue"
},
  "geometry": {"coordinates":[-84.36602000000001,30.518193],"type":"Point"}
}