{
  "type": "Feature",
  "properties": {
    "iso:country":"US",
    "sg:address":"1208 N Parsons Ave",
    "sg:city":"Brandon",
    "sg:classifiers":[
        {
            "category":"Food & Beverages",
            "subcategory":"Groceries & Convenience Stores",
            "type":"Retail Goods"
        }
    ],
    "sg:phone":"+1 813 657 9675",
    "sg:postcode":"33510",
    "sg:province":"FL",
    "wof:name":"Beverage Castle",
    "wof:placetype":"venue"
},
  "geometry": {"coordinates":[-82.285966,27.958162],"type":"Point"}
}