{
  "type": "Feature",
  "properties": {
    "iso:country":"US",
    "sg:address":"3483 Phillips Hwy",
    "sg:city":"Jacksonville",
    "sg:classifiers":[
        {
            "category":"Autos & Motor Vehicles",
            "subcategory":"Auto Supplies",
            "type":"Retail Goods"
        }
    ],
    "sg:phone":"+1 904 398 4545",
    "sg:postcode":"32207",
    "sg:province":"FL",
    "sg:tags":[
        "tire"
    ],
    "wof:name":"Tubel's Goodyear Svc Ctr",
    "wof:placetype":"venue"
},
  "geometry": {"coordinates":[-81.63512299999999,30.289803],"type":"Point"}
}