{
  "type": "Feature",
  "properties": {
    "iso:country":"US",
    "sg:address":"2545 NW 74th Ave",
    "sg:city":"Miami",
    "sg:classifiers":[
        {
            "category":"Wholesale",
            "subcategory":"Hardware",
            "type":"Manufacturing & Wholesale Goods"
        }
    ],
    "sg:phone":"+1 305 499 9300",
    "sg:postcode":"33122",
    "sg:province":"FL",
    "sg:tags":[
        "tool"
    ],
    "wof:name":"M C Equipment & Tool",
    "wof:placetype":"venue"
},
  "geometry": {"coordinates":[-80.316964,25.797521],"type":"Point"}
}