{
  "type": "Feature",
  "properties": {
    "addr:full":"2259 Bee Ridge Rd Sarasota FL 34239",
    "addr:housenumber":"2259",
    "addr:postcode":"34239",
    "addr:street":"Bee Ridge Rd",
    "iso:country":"US",
    "sg:address":"2259 Bee Ridge Rd",
    "sg:city":"Sarasota",
    "sg:classifiers":[
        {
            "category":"Retail",
            "subcategory":"Animal Services",
            "type":"Services"
        }
    ],
    "sg:phone":"+1 941 929 7297",
    "sg:postcode":"34239",
    "sg:province":"FL",
    "sg:tags":[
        "pet",
        "grooming",
        "washing"
    ],
    "wof:name":"Lucylocks Grooming Studio",
    "wof:placetype":"venue"
},
  "geometry": {"coordinates":[-82.524337,27.298916],"type":"Point"}
}