{
  "type": "Feature",
  "properties": {
    "addr:full":"15117 NW 1st St Hollywood FL 33028",
    "addr:housenumber":"15117",
    "addr:postcode":"33028",
    "addr:street":"Nw 1St St",
    "iso:country":"US",
    "sg:address":"15117 NW 1st St",
    "sg:city":"Hollywood",
    "sg:classifiers":[
        {
            "category":"Wholesale",
            "subcategory":"Durable Goods & Equipment",
            "type":"Manufacturing & Wholesale Goods"
        }
    ],
    "sg:phone":"+1 954 704 3628",
    "sg:postcode":"33028",
    "sg:province":"FL",
    "wof:name":"Cali Party Supplies Inc",
    "wof:placetype":"venue"
},
  "geometry": {"coordinates":[-80.363437,26.008907],"type":"Point"}
}