{
  "type": "Feature",
  "properties": {
    "addr:full":"2336 14th Ave Vero Beach FL 32960",
    "addr:housenumber":"2336",
    "addr:postcode":"32960",
    "addr:street":"14Th Ave",
    "iso:country":"US",
    "sg:address":"2336 14th Ave",
    "sg:city":"Vero Beach",
    "sg:classifiers":[
        {
            "category":"Museum",
            "type":"Entertainment"
        }
    ],
    "sg:phone":"+1 772 778 3435",
    "sg:postcode":"32960",
    "sg:province":"FL",
    "wof:name":"Indian River Historical Soc",
    "wof:placetype":"venue"
},
  "geometry": {"coordinates":[-80.39921200000001,27.642087],"type":"Point"}
}