{
  "type": "Feature",
  "properties": {
    "addr:city":"Vero Beach",
    "addr:full":"2336 14Th Ave Vero Beach, Fl 32960-3302",
    "addr:house_number":"2336",
    "addr:housenumber":"2336",
    "addr:phone":"+1 772-778-3435",
    "addr:postcode":"32960-3302",
    "addr:road":"14Th Ave",
    "addr:state":"FL",
    "addr:street":"14Th Ave",
    "iso:country":"US",
    "sg:address":"2336 14th Ave",
    "sg:city":"Vero Beach",
    "sg:classifiers":[
        {
            "category":"Museum",
            "type":"Entertainment"
        }
    ],
    "sg:phone":"+1 772 778 3435",
    "sg:postcode":"32960",
    "sg:province":"FL",
    "wof:airports":[
        102527921
    ],
    "wof:name":"Indian River County Historical Society",
    "wof:placetype":"venue"
},
  "geometry": {"coordinates":[-80.39901,27.64251],"type":"Point"}
}