{
  "type": "Feature",
  "properties": {
    "addr:full":"1449 S Nova Rd Daytona Beach FL 32114",
    "addr:housenumber":"1449",
    "addr:postcode":"32114",
    "addr:street":"S Nova Rd",
    "iso:country":"US",
    "sg:address":"1449 S Nova Rd",
    "sg:city":"Daytona Beach",
    "sg:classifiers":[
        {
            "category":"Professional",
            "subcategory":"Business Services",
            "type":"Services"
        }
    ],
    "sg:phone":"+1 386 258 2400",
    "sg:postcode":"32114",
    "sg:province":"FL",
    "sg:tags":[
        "consulting",
        "telemarketing"
    ],
    "wof:name":"Evergreen Sales & Mktg Svcs",
    "wof:placetype":"venue"
},
  "geometry": {"coordinates":[-81.029135,29.179905],"type":"Point"}
}