{
  "type": "Feature",
  "properties": {
    "iso:country":"US",
    "sg:address":"2823 S Orange Ave",
    "sg:city":"Orlando",
    "sg:classifiers":[
        {
            "category":"Cinema",
            "subcategory":"Movie Rental",
            "type":"Entertainment"
        }
    ],
    "sg:phone":"+1 407 839 3885",
    "sg:postcode":"32806",
    "sg:province":"FL",
    "sg:tags":[
        "video",
        "store"
    ],
    "wof:name":"Blockbuster",
    "wof:placetype":"venue"
},
  "geometry": {"coordinates":[-81.376232,28.511923],"type":"Point"}
}