{
  "type": "Feature",
  "properties": {
    "iso:country":"US",
    "sg:address":"8440 Ulmerton Rd",
    "sg:city":"Largo",
    "sg:classifiers":[
        {
            "category":"Shopping",
            "subcategory":"Bicycles & Sporting Goods",
            "type":"Retail Goods"
        }
    ],
    "sg:phone":"+1 727 535 9803",
    "sg:postcode":"33771",
    "sg:province":"FL",
    "sg:tags":[
        "gun",
        "gunsmith"
    ],
    "sg:website":"www.surplusfirearms.com",
    "wof:name":"Mark Kubes Firearms Specs",
    "wof:placetype":"venue"
},
  "geometry": {"coordinates":[-82.75675,27.894329],"type":"Point"}
}