{
  "type": "Feature",
  "properties": {
    "addr:full":"6143 Massachusetts Ave New Port Richey FL 34653",
    "addr:housenumber":"6143",
    "addr:postcode":"34653",
    "addr:street":"Massachusetts Ave",
    "iso:country":"US",
    "sg:address":"6143 Massachusetts Ave",
    "sg:city":"New Port Richey",
    "sg:classifiers":[
        {
            "category":"Bars & Pubs",
            "type":"Food & Drink"
        }
    ],
    "sg:phone":"+1 727 848 5443",
    "sg:postcode":"34653",
    "sg:province":"FL",
    "sg:tags":[
        "drinking"
    ],
    "wof:name":"Sail Inn Tavern",
    "wof:placetype":"venue"
},
  "geometry": {"coordinates":[-82.712597,28.258799],"type":"Point"}
}