{
  "type": "Feature",
  "properties": {
    "addr:full":"7074 Barrancas Ave Bokeelia FL 33922",
    "addr:housenumber":"7074",
    "addr:postcode":"33922",
    "addr:street":"Barrancas Ave",
    "iso:country":"US",
    "sg:address":"7074 Barrancas Ave",
    "sg:city":"Bokeelia",
    "sg:classifiers":[
        {
            "category":"Marine",
            "type":"Transportation"
        }
    ],
    "sg:phone":"+1 239 283 4948",
    "sg:postcode":"33922",
    "sg:province":"FL",
    "sg:tags":[
        "towing"
    ],
    "wof:name":"Maclean's Marine Towing & Slvg",
    "wof:placetype":"venue"
},
  "geometry": {"coordinates":[-82.142269,26.693763],"type":"Point"}
}