{
  "type": "Feature",
  "properties": {
    "iso:country":"US",
    "sg:address":"25 SW Linden St",
    "sg:city":"Stuart",
    "sg:classifiers":[
        {
            "category":"Building & Trades",
            "subcategory":"Landscaping Services",
            "type":"Services"
        }
    ],
    "sg:phone":"+1 772 288 3440",
    "sg:postcode":"34997",
    "sg:province":"FL",
    "sg:tags":[
        "topsoil",
        "sod",
        "sodding"
    ],
    "sg:website":"http://www.stuartsod.com",
    "wof:name":"Stuart Sod Inc",
    "wof:placetype":"venue"
},
  "geometry": {"coordinates":[-80.25034599999999,27.136743],"type":"Point"}
}