{
  "type": "Feature",
  "properties": {
    "addr:full":"1028 Del Prado Blvd S Cape Coral FL 33990",
    "addr:housenumber":"1028",
    "addr:postcode":"33990",
    "addr:street":"Del Prado Blvd S",
    "iso:country":"US",
    "sg:address":"1028 Del Prado Blvd S",
    "sg:city":"Cape Coral",
    "sg:classifiers":[
        {
            "category":"Autos & Motor Vehicles",
            "subcategory":"Auto Supplies",
            "type":"Retail Goods"
        },
        {
            "category":"Retail",
            "subcategory":"Auto Repair",
            "type":"Services"
        }
    ],
    "sg:phone":"+1 239 772 1868",
    "sg:postcode":"33990",
    "sg:province":"FL",
    "sg:tags":[
        "tire"
    ],
    "sg:website":"www.tirekingdom.com",
    "wof:name":"Tire Kingdom",
    "wof:placetype":"venue"
},
  "geometry": {"coordinates":[-81.941002,26.632099],"type":"Point"}
}