{
  "type": "Feature",
  "properties": {
    "addr:full":"3415 4th Ave S St Petersburg FL 33711",
    "addr:housenumber":"3415",
    "addr:postcode":"33711",
    "addr:street":"4Th Ave S",
    "iso:country":"US",
    "sg:address":"3415 4th Ave S",
    "sg:city":"St Petersburg",
    "sg:classifiers":[
        {
            "category":"Insurance",
            "subcategory":"Hazard Insurance",
            "type":"Services"
        }
    ],
    "sg:phone":"+1 727 323 1089",
    "sg:postcode":"33711",
    "sg:province":"FL",
    "sg:tags":[
        "bond"
    ],
    "wof:name":"Bail Bond Information",
    "wof:placetype":"venue"
},
  "geometry": {"coordinates":[-82.680615,27.76744],"type":"Point"}
}