{
  "type": "Feature",
  "properties": {
    "iso:country":"US",
    "sg:address":"2534 Forfarshire Dr",
    "sg:city":"Winter Park",
    "sg:classifiers":[
        {
            "category":"Building & Trades",
            "subcategory":"Construction",
            "type":"Services"
        }
    ],
    "sg:phone":"+1 407 695 6576",
    "sg:postcode":"32792",
    "sg:province":"FL",
    "sg:tags":[
        "house"
    ],
    "wof:name":"Jenkins Roberts Construction I",
    "wof:placetype":"venue"
},
  "geometry": {"coordinates":[-81.318573,28.588219],"type":"Point"}
}