{
  "type": "Feature",
  "properties": {
    "iso:country":"US",
    "sg:address":"10790 NE 6th Ave",
    "sg:city":"Miami",
    "sg:classifiers":[
        {
            "category":"Retail",
            "subcategory":"Auto Repair",
            "type":"Services"
        }
    ],
    "sg:phone":"+1 305 759 9244",
    "sg:postcode":"33161",
    "sg:province":"FL",
    "sg:tags":[
        "shop",
        "automotive"
    ],
    "wof:name":"Tristate Auto Electric",
    "wof:placetype":"venue"
},
  "geometry": {"coordinates":[-80.18582499999999,25.873757],"type":"Point"}
}