{
  "type": "Feature",
  "properties": {
    "addr:full":"2014 Tamiami Trl N Naples FL 34102",
    "addr:housenumber":"2014",
    "addr:postcode":"34102",
    "addr:street":"Tamiami Trl N",
    "iso:country":"US",
    "sg:address":"2014 Tamiami Trl N",
    "sg:city":"Naples",
    "sg:classifiers":[
        {
            "category":"Shopping",
            "subcategory":"Shoes",
            "type":"Retail Goods"
        }
    ],
    "sg:phone":"+1 239 261 2292",
    "sg:postcode":"34102",
    "sg:province":"FL",
    "wof:name":"Foot Locker",
    "wof:placetype":"venue"
},
  "geometry": {"coordinates":[-81.79908399999999,26.167637],"type":"Point"}
}