{
  "type": "Feature",
  "properties": {
    "iso:country":"US",
    "sg:address":"7114 N Habana Ave",
    "sg:city":"Tampa",
    "sg:classifiers":[
        {
            "category":"Retail",
            "subcategory":"Repair Shop",
            "type":"Services"
        }
    ],
    "sg:phone":"+1 813 972 8996",
    "sg:postcode":"33614",
    "sg:province":"FL",
    "sg:tags":[
        "refrigeration"
    ],
    "wof:name":"Wagners Heating & AC",
    "wof:placetype":"venue"
},
  "geometry": {"coordinates":[-82.488552,28.012628],"type":"Point"}
}