{
  "type": "Feature",
  "properties": {
    "addr:full":"3960 Rca Blvd Palm Beach Gdns FL 33410",
    "addr:postcode":"3960;33410",
    "addr:street":"Rca Blvd Palm Beach Gdns",
    "iso:country":"US",
    "sg:address":"3960 Rca Blvd",
    "sg:city":"Palm Beach Gdns",
    "sg:classifiers":[
        {
            "category":"Banks & Credit Unions",
            "subcategory":"Bank",
            "type":"Services"
        }
    ],
    "sg:phone":"+1 561 352 2450",
    "sg:postcode":"33410",
    "sg:province":"FL",
    "sg:tags":[
        "loan",
        "real estate"
    ],
    "wof:name":"Clayton",
    "wof:placetype":"venue"
},
  "geometry": {"coordinates":[-80.09661800000001,26.837914],"type":"Point"}
}