{
  "type": "Feature",
  "properties": {
    "addr:full":"8232 State Rd 52 Port Richey FL 34669",
    "addr:housenumber":"8232;52",
    "addr:postcode":"34669",
    "addr:street":"State Rd",
    "iso:country":"US",
    "sg:address":"8232 State Rd 52",
    "sg:city":"Port Richey",
    "sg:classifiers":[
        {
            "category":"Restaurant",
            "type":"Food & Drink"
        }
    ],
    "sg:phone":"+1 727 697 1988",
    "sg:postcode":"34669",
    "sg:province":"FL",
    "sg:tags":[
        "eating"
    ],
    "wof:name":"Buffet Good Fortune",
    "wof:placetype":"venue"
},
  "geometry": {"coordinates":[-82.678833,28.330919],"type":"Point"}
}