{
  "type": "Feature",
  "properties": {
    "addr:full":"5029 Edgewater Dr Orlando FL 32810",
    "addr:housenumber":"5029",
    "addr:postcode":"32810",
    "addr:street":"Edgewater Dr",
    "iso:country":"US",
    "sg:address":"5029 Edgewater Dr",
    "sg:city":"Orlando",
    "sg:classifiers":[
        {
            "category":"Education",
            "subcategory":"Vocational School",
            "type":"Public Place"
        }
    ],
    "sg:phone":"+1 407 571 2449",
    "sg:postcode":"32810",
    "sg:province":"FL",
    "sg:tags":[
        "broker",
        "mortgage"
    ],
    "sg:website":"www.kambuck.com",
    "wof:name":"Kambuck Resources Llc",
    "wof:placetype":"venue"
},
  "geometry": {"coordinates":[-81.40860000000001,28.6049],"type":"Point"}
}