{
  "type": "Feature",
  "properties": {
    "iso:country":"US",
    "sg:address":"925 Camelot Ln",
    "sg:city":"Lakeland",
    "sg:classifiers":[
        {
            "category":"Health Services",
            "subcategory":"Doctor",
            "type":"Services"
        }
    ],
    "sg:phone":"+1 863 646 4080",
    "sg:postcode":"33813",
    "sg:province":"FL",
    "sg:tags":[
        "physician",
        "family",
        "practice",
        "surgeons",
        "medicine"
    ],
    "wof:name":"John M Lafferty Md Pa",
    "wof:placetype":"venue"
},
  "geometry": {"coordinates":[-81.94925499999999,27.970678],"type":"Point"}
}