{
  "type": "Feature",
  "properties": {
    "addr:full":"3149 N Ponce de Leon Blvd St Augustine FL 32084",
    "addr:housenumber":"3149",
    "addr:postcode":"32084",
    "addr:street":"N Ponce De Leon Blvd St",
    "iso:country":"US",
    "sg:address":"3149 N Ponce de Leon Blvd",
    "sg:city":"St Augustine",
    "sg:classifiers":[
        {
            "category":"Professional",
            "subcategory":"Lawyer & Legal Services",
            "type":"Services"
        }
    ],
    "sg:phone":"+1 904 825 1770",
    "sg:postcode":"32084",
    "sg:province":"FL",
    "sg:tags":[
        "attorney"
    ],
    "wof:name":"Patricia Brosnan",
    "wof:placetype":"venue"
},
  "geometry": {"coordinates":[-81.325129,29.920823],"type":"Point"}
}