{
  "type": "Feature",
  "properties": {
    "iso:country":"US",
    "sg:address":"2010 Mckee Rd",
    "sg:city":"Tallahassee",
    "sg:classifiers":[
        {
            "category":"Manufacturing",
            "subcategory":"Buildings",
            "type":"Manufacturing & Wholesale Goods"
        },
        {
            "category":"Real Estate",
            "subcategory":"Real Estate Services",
            "type":"Services"
        },
        {
            "category":"Building & Trades",
            "subcategory":"Cleaning & Sanitation",
            "type":"Services"
        },
        {
            "category":"Building & Trades",
            "subcategory":"Construction",
            "type":"Services"
        }
    ],
    "sg:phone":"+1 850 536 9150",
    "sg:postcode":"32303",
    "sg:province":"FL",
    "sg:tags":[
        "industrial",
        "cleaners-interior",
        "builder",
        "system",
        "specialty",
        "heating",
        "contractor",
        "maintenance",
        "home",
        "air conditioning",
        "contractors-commercial"
    ],
    "wof:name":"Panhandle Building Services",
    "wof:placetype":"venue"
},
  "geometry": {"coordinates":[-84.327715,30.498932],"type":"Point"}
}