{
  "type": "Feature",
  "properties": {
    "addr:full":"2214 N Flamingo Rd Pembroke Pines FL 33028",
    "addr:housenumber":"2214",
    "addr:postcode":"33028",
    "addr:street":"N Flamingo Rd",
    "iso:country":"US",
    "sg:address":"2214 N Flamingo Rd",
    "sg:city":"Pembroke Pines",
    "sg:classifiers":[
        {
            "category":"Shopping",
            "subcategory":"Gifts & Souvenirs",
            "type":"Retail Goods"
        }
    ],
    "sg:phone":"+1 954 704 0666",
    "sg:postcode":"33028",
    "sg:province":"FL",
    "sg:tags":[
        "shop"
    ],
    "wof:name":"Sincerely Yours Cards & Gifts",
    "wof:placetype":"venue"
},
  "geometry": {"coordinates":[-80.312613,26.027231],"type":"Point"}
}