{
  "type": "Feature",
  "properties": {
    "iso:country":"US",
    "sg:address":"13315 Provence Dr",
    "sg:city":"Palm Beach Gardens",
    "sg:classifiers":[
        {
            "category":"Real Estate",
            "subcategory":"Real Estate Agent",
            "type":"Services"
        }
    ],
    "sg:phone":"+1 561 775 1220",
    "sg:postcode":"33410",
    "sg:province":"FL",
    "wof:name":"Hh Realty Co LLC",
    "wof:placetype":"venue"
},
  "geometry": {"coordinates":[-80.091503,26.87192],"type":"Point"}
}