{
  "type": "Feature",
  "properties": {
    "iso:country":"US",
    "sg:address":"4305 Quando Dr",
    "sg:city":"Orlando",
    "sg:classifiers":[
        {
            "category":"Autos & Motor Vehicles",
            "subcategory":"Automobile Sales",
            "type":"Retail Goods"
        }
    ],
    "sg:phone":"+1 407 854 0739",
    "sg:postcode":"32812",
    "sg:province":"FL",
    "wof:name":"Satellite Motors",
    "wof:placetype":"venue"
},
  "geometry": {"coordinates":[-81.330862,28.470849],"type":"Point"}
}