{
  "type": "Feature",
  "properties": {
    "addr:full":"1936 Michigan Ave NE Saint Petersburg FL 33703",
    "addr:housenumber":"1936",
    "addr:postcode":"33703",
    "addr:street":"Michigan Ave Ne",
    "iso:country":"US",
    "sg:address":"1936 Michigan Ave NE",
    "sg:city":"Saint Petersburg",
    "sg:classifiers":[
        {
            "category":"Professional",
            "subcategory":"Management & Consulting",
            "type":"Services"
        }
    ],
    "sg:phone":"+1 727 528 2984",
    "sg:postcode":"33703",
    "sg:province":"FL",
    "sg:tags":[
        "insurance"
    ],
    "wof:name":"US Integrity Incorporated",
    "wof:placetype":"venue"
},
  "geometry": {"coordinates":[-82.598947,27.818991],"type":"Point"}
}