{
  "type": "Feature",
  "properties": {
    "addr:full":"373 Colony Dr Naples FL 34108",
    "addr:housenumber":"373",
    "addr:postcode":"34108",
    "addr:street":"Colony Dr",
    "iso:country":"US",
    "sg:address":"373 Colony Dr",
    "sg:city":"Naples",
    "sg:classifiers":[
        {
            "category":"Building & Trades",
            "subcategory":"Construction",
            "type":"Services"
        }
    ],
    "sg:phone":"+1 239 594 5856",
    "sg:postcode":"34108",
    "sg:province":"FL",
    "sg:tags":[
        "builder",
        "operative"
    ],
    "wof:name":"International Business",
    "wof:placetype":"venue"
},
  "geometry": {"coordinates":[-81.812714,26.250301],"type":"Point"}
}