{
  "type": "Feature",
  "properties": {
    "addr:full":"36 SW 1st St Miami FL 33130",
    "addr:housenumber":"36",
    "addr:postcode":"33130",
    "addr:street":"Sw 1St St",
    "iso:country":"US",
    "sg:address":"36 SW 1st St",
    "sg:city":"Miami",
    "sg:classifiers":[
        {
            "category":"Restaurant",
            "type":"Food & Drink"
        }
    ],
    "sg:phone":"+1 305 372 5205",
    "sg:postcode":"33130",
    "sg:province":"FL",
    "sg:tags":[
        "seafood",
        "latin",
        "american"
    ],
    "wof:name":"Latitude Zero",
    "wof:placetype":"venue"
},
  "geometry": {"coordinates":[-80.19448300000001,25.773286],"type":"Point"}
}