{
  "type": "Feature",
  "properties": {
    "addr:full":"10501 67th Ave Seminole FL 33772",
    "addr:housenumber":"10501",
    "addr:postcode":"33772",
    "addr:street":"67Th Ave",
    "iso:country":"US",
    "sg:address":"10501 67th Ave",
    "sg:city":"Seminole",
    "sg:classifiers":[
        {
            "category":"Real Estate",
            "subcategory":"Real Estate Operator",
            "type":"Services"
        }
    ],
    "sg:phone":"+1 727 392 6559",
    "sg:postcode":"33772",
    "sg:province":"FL",
    "sg:tags":[
        "apartment"
    ],
    "wof:name":"Triple's S Apartments",
    "wof:placetype":"venue"
},
  "geometry": {"coordinates":[-82.783928,27.833191],"type":"Point"}
}