{
  "type": "Feature",
  "properties": {
    "addr:full":"11454 175th Rd N Jupiter FL 33478",
    "addr:housenumber":"11454",
    "addr:postcode":"33478",
    "addr:street":"175Th Rd N",
    "iso:country":"US",
    "sg:address":"11454 175th Rd N",
    "sg:city":"Jupiter",
    "sg:classifiers":[
        {
            "category":"Manufacturing",
            "subcategory":"Toys & Sporting Goods",
            "type":"Manufacturing & Wholesale Goods"
        }
    ],
    "sg:phone":"+1 561 248 4608",
    "sg:postcode":"33478",
    "sg:province":"FL",
    "sg:tags":[
        "mfg"
    ],
    "wof:name":"Brookside & Moss",
    "wof:placetype":"venue"
},
  "geometry": {"coordinates":[-80.214519,26.935707],"type":"Point"}
}