{
  "type": "Feature",
  "properties": {
    "iso:country":"US",
    "sg:address":"222 N Lakeview Dr",
    "sg:city":"Lake Helen",
    "sg:classifiers":[
        {
            "category":"Real Estate",
            "subcategory":"Real Estate Agent",
            "type":"Services"
        }
    ],
    "sg:phone":"+1 386 228 9866",
    "sg:postcode":"32744",
    "sg:province":"FL",
    "wof:name":"AAA Appraisal Services",
    "wof:placetype":"venue"
},
  "geometry": {"coordinates":[-81.23192,28.986129],"type":"Point"}
}