{
  "type": "Feature",
  "properties": {
    "addr:full":"1248 Edgewood Ave W Jacksonville FL 32208",
    "addr:housenumber":"1248",
    "addr:postcode":"32208",
    "addr:street":"Edgewood Ave W",
    "iso:country":"US",
    "sg:address":"1248 Edgewood Ave W",
    "sg:city":"Jacksonville",
    "sg:classifiers":[
        {
            "category":"Banks & Credit Unions",
            "subcategory":"Bank",
            "type":"Services"
        }
    ],
    "sg:phone":"+1 904 924 7731",
    "sg:postcode":"32208",
    "sg:province":"FL",
    "sg:tags":[
        "broker",
        "mortgage"
    ],
    "wof:name":"Green Light Mortgage Inc",
    "wof:placetype":"venue"
},
  "geometry": {"coordinates":[-81.677514,30.39185],"type":"Point"}
}