{
  "type": "Feature",
  "properties": {
    "iso:country":"US",
    "sg:address":"1901 S Andrews Ave",
    "sg:city":"Fort Lauderdale",
    "sg:classifiers":[
        {
            "category":"Professional",
            "subcategory":"Lawyer & Legal Services",
            "type":"Services"
        }
    ],
    "sg:phone":"+1 954 927 5330",
    "sg:postcode":"33316",
    "sg:province":"FL",
    "sg:tags":[
        "attorney"
    ],
    "sg:website":"www.national-law.com",
    "wof:name":"Vernis & Bowling Of Broward",
    "wof:placetype":"venue"
},
  "geometry": {"coordinates":[-80.141144,26.096456],"type":"Point"}
}