{
  "type": "Feature",
  "properties": {
    "iso:country":"US",
    "sg:address":"2565 Westgate Ave",
    "sg:city":"West Palm Beach",
    "sg:classifiers":[
        {
            "category":"Food & Beverages",
            "subcategory":"Groceries & Convenience Stores",
            "type":"Retail Goods"
        }
    ],
    "sg:phone":"+1 561 640 8887",
    "sg:postcode":"33409",
    "sg:province":"FL",
    "sg:tags":[
        "market"
    ],
    "wof:name":"LA Gran Familia Food Market",
    "wof:placetype":"venue"
},
  "geometry": {"coordinates":[-80.091407,26.703057],"type":"Point"}
}