{
  "type": "Feature",
  "properties": {
    "addr:full":"5997 Francine Dr Jacksonville FL 32234",
    "addr:housenumber":"5997",
    "addr:postcode":"32234",
    "addr:street":"Francine Dr",
    "iso:country":"US",
    "sg:address":"5997 Francine Dr",
    "sg:city":"Jacksonville",
    "sg:classifiers":[
        {
            "category":"Retail",
            "subcategory":"Auto Repair",
            "type":"Services"
        }
    ],
    "sg:phone":"+1 904 289 7485",
    "sg:postcode":"32234",
    "sg:province":"FL",
    "sg:tags":[
        "automotive"
    ],
    "wof:name":"Kents Mobile Rv Generator Serv",
    "wof:placetype":"venue"
},
  "geometry": {"coordinates":[-81.994455,30.180613],"type":"Point"}
}