{
  "type": "Feature",
  "properties": {
    "addr:full":"5181 NW 109th Ave Fort Lauderdale FL 33351",
    "addr:housenumber":"5181",
    "addr:postcode":"33351",
    "addr:street":"Nw 109Th Ave",
    "iso:country":"US",
    "sg:address":"5181 NW 109th Ave",
    "sg:city":"Fort Lauderdale",
    "sg:classifiers":[
        {
            "category":"Building & Trades",
            "subcategory":"Plumbing",
            "type":"Services"
        }
    ],
    "sg:phone":"+1 954 747 9199",
    "sg:postcode":"33351",
    "sg:province":"FL",
    "sg:tags":[
        "contractor"
    ],
    "wof:name":"Hvac Mechanical Inc",
    "wof:placetype":"venue"
},
  "geometry": {"coordinates":[-80.296043,26.188018],"type":"Point"}
}