{
  "type": "Feature",
  "properties": {
    "addr:full":"3906 Exchange Ave Naples FL 34104",
    "addr:housenumber":"3906",
    "addr:postcode":"34104",
    "addr:street":"Exchange Ave",
    "iso:country":"US",
    "sg:address":"3906 Exchange Ave",
    "sg:city":"Naples",
    "sg:classifiers":[
        {
            "category":"Autos & Motor Vehicles",
            "subcategory":"Auto Supplies",
            "type":"Retail Goods"
        }
    ],
    "sg:phone":"+1 239 643 7676",
    "sg:postcode":"34104",
    "sg:province":"FL",
    "wof:name":"Collier Tires & Auto Repairs",
    "wof:placetype":"venue"
},
  "geometry": {"coordinates":[-81.76569600000001,26.158611],"type":"Point"}
}