{
  "type": "Feature",
  "properties": {
    "iso:country":"US",
    "sg:address":"18024 SW 29th Ct",
    "sg:city":"Miramar",
    "sg:classifiers":[
        {
            "category":"Wholesale",
            "subcategory":"Chemicals & Plastics",
            "type":"Manufacturing & Wholesale Goods"
        }
    ],
    "sg:phone":"+1 954 704 8179",
    "sg:postcode":"33029",
    "sg:province":"FL",
    "sg:tags":[
        "bag"
    ],
    "wof:name":"Bags For Bags By Andrea",
    "wof:placetype":"venue"
},
  "geometry": {"coordinates":[-80.38526299999999,25.980724],"type":"Point"}
}