{
  "type": "Feature",
  "properties": {
    "iso:country":"US",
    "sg:address":"8814 Rocky Creek Dr",
    "sg:city":"Tampa",
    "sg:classifiers":[
        {
            "category":"Professional",
            "subcategory":"Lawyer & Legal Services",
            "type":"Services"
        }
    ],
    "sg:phone":"+1 813 932 5297",
    "sg:postcode":"33615",
    "sg:province":"FL",
    "sg:tags":[
        "attorney"
    ],
    "wof:name":"Rothman Law Offices",
    "wof:placetype":"venue"
},
  "geometry": {"coordinates":[-82.58838299999999,27.995908],"type":"Point"}
}