{
  "type": "Feature",
  "properties": {
    "iso:country":"US",
    "sg:address":"35248 US Hwy 19 N",
    "sg:city":"Palm Harbor",
    "sg:classifiers":[
        {
            "category":"Professional",
            "subcategory":"Management & Consulting",
            "type":"Services"
        }
    ],
    "sg:phone":"+1 508 359 1792",
    "sg:postcode":"34684",
    "sg:province":"FL",
    "sg:tags":[
        "development",
        "leadership",
        "team"
    ],
    "wof:name":"Teambuilders",
    "wof:placetype":"venue"
},
  "geometry": {"coordinates":[-82.73945999999999,28.088666],"type":"Point"}
}