{
  "type": "Feature",
  "properties": {
    "iso:country":"US",
    "sg:address":"8565 Coral Way",
    "sg:city":"Miami",
    "sg:classifiers":[
        {
            "category":"Ice Cream",
            "type":"Food & Drink"
        }
    ],
    "sg:menulink":"http://www.allmenus.com/fl/south-westside/221392-carvel/menu/",
    "sg:phone":"+1 305 261 5577",
    "sg:postcode":"33155",
    "sg:province":"FL",
    "sg:tags":[
        "american"
    ],
    "wof:name":"Carvel",
    "wof:placetype":"venue"
},
  "geometry": {"coordinates":[-80.333168,25.747758],"type":"Point"}
}