{
  "type": "Feature",
  "properties": {
    "iso:country":"US",
    "sg:address":"725 E Main St",
    "sg:city":"Pahokee",
    "sg:classifiers":[
        {
            "category":"Home & Garden",
            "subcategory":"Carpets & Floor Coverings",
            "type":"Retail Goods"
        }
    ],
    "sg:phone":"+1 561 924 7049",
    "sg:postcode":"33476",
    "sg:province":"FL",
    "sg:tags":[
        "dealer",
        "rug"
    ],
    "wof:name":"Nelson Lopez Carpet & Vinyl",
    "wof:placetype":"venue"
},
  "geometry": {"coordinates":[-80.64480399999999,26.843306],"type":"Point"}
}