{
  "type": "Feature",
  "properties": {
    "addr:full":"3207 Margaret Oaks Ln Orlando FL 32806",
    "addr:housenumber":"3207",
    "addr:postcode":"32806",
    "addr:street":"Margaret Oaks Ln",
    "iso:country":"US",
    "sg:address":"3207 Margaret Oaks Ln",
    "sg:city":"Orlando",
    "sg:phone":"+1 407 856 1564",
    "sg:postcode":"32806",
    "sg:province":"FL",
    "sg:tags":[
        "oil"
    ],
    "wof:name":"Amsoil Synthetic Lubricants",
    "wof:placetype":"venue"
},
  "geometry": {"coordinates":[-81.34726000000001,28.50566],"type":"Point"}
}