{
  "type": "Feature",
  "properties": {
    "addr:full":"5064 W Atlantic Ave Delray Beach FL 33484",
    "addr:housenumber":"5064",
    "addr:postcode":"33484",
    "addr:street":"W Atlantic Ave",
    "iso:country":"US",
    "sg:address":"5064 W Atlantic Ave",
    "sg:city":"Delray Beach",
    "sg:classifiers":[
        {
            "category":"Shopping",
            "subcategory":"Florist",
            "type":"Retail Goods"
        }
    ],
    "sg:phone":"+1 561 495 0114",
    "sg:postcode":"33484",
    "sg:province":"FL",
    "wof:name":"Crystal Rose",
    "wof:placetype":"venue"
},
  "geometry": {"coordinates":[-80.123378,26.457761],"type":"Point"}
}