{
  "type": "Feature",
  "properties": {
    "addr:full":"2712 26th Ave E Bradenton FL 34208",
    "addr:housenumber":"2712",
    "addr:postcode":"34208",
    "addr:street":"26Th Ave E",
    "iso:country":"US",
    "sg:address":"2712 26th Ave E",
    "sg:city":"Bradenton",
    "sg:classifiers":[
        {
            "category":"Wholesale",
            "subcategory":"Fruits & Vegetables",
            "type":"Manufacturing & Wholesale Goods"
        }
    ],
    "sg:phone":"+1 941 748 5829",
    "sg:postcode":"34208",
    "sg:province":"FL",
    "sg:tags":[
        "citrus"
    ],
    "sg:website":"www.mixon.com",
    "wof:name":"Mixon Fruit Farms Inc",
    "wof:placetype":"venue"
},
  "geometry": {"coordinates":[-82.52786,27.476672],"type":"Point"}
}