{
  "type": "Feature",
  "properties": {
    "iso:country":"US",
    "sg:address":"1219 Dunn Ave",
    "sg:city":"Daytona Beach",
    "sg:classifiers":[
        {
            "category":"Professional",
            "subcategory":"Business Services",
            "type":"Services"
        }
    ],
    "sg:phone":"+1 386 255 4568",
    "sg:postcode":"32114",
    "sg:province":"FL",
    "sg:tags":[
        "child",
        "day",
        "care"
    ],
    "wof:name":"Easter Seals",
    "wof:placetype":"venue"
},
  "geometry": {"coordinates":[-81.054799,29.207231],"type":"Point"}
}