{
  "type": "Feature",
  "properties": {
    "iso:country":"US",
    "sg:address":"403 4th Ave S",
    "sg:city":"Lake Worth",
    "sg:classifiers":[
        {
            "category":"Building & Trades",
            "subcategory":"Construction",
            "type":"Services"
        }
    ],
    "sg:phone":"+1 561 533 8700",
    "sg:postcode":"33460",
    "sg:province":"FL",
    "sg:tags":[
        "hanging",
        "contractor"
    ],
    "wof:name":"Edwin Stone Painting",
    "wof:placetype":"venue"
},
  "geometry": {"coordinates":[-80.053557,26.610856],"type":"Point"}
}