{
  "type": "Feature",
  "properties": {
    "addr:full":"6150 14th St W Bradenton FL 34207",
    "addr:housenumber":"6150",
    "addr:postcode":"34207",
    "addr:street":"14Th St W",
    "iso:country":"US",
    "sg:address":"6150 14th St W",
    "sg:city":"Bradenton",
    "sg:classifiers":[
        {
            "category":"Shopping",
            "type":"Retail Goods"
        }
    ],
    "sg:phone":"+1 941 756 2700",
    "sg:postcode":"34207",
    "sg:province":"FL",
    "sg:tags":[
        "merchandise"
    ],
    "sg:website":"http://www.target.com",
    "wof:name":"Target",
    "wof:placetype":"venue"
},
  "geometry": {"coordinates":[-82.575453,27.432108],"type":"Point"}
}