{
  "type": "Feature",
  "properties": {
    "addr:full":"3108 N F St Pensacola FL 32501",
    "addr:housenumber":"3108",
    "addr:postcode":"32501",
    "addr:street":"N F St",
    "iso:country":"US",
    "sg:address":"3108 N F St",
    "sg:city":"Pensacola",
    "sg:classifiers":[
        {
            "category":"Building & Trades",
            "subcategory":"Plumbing",
            "type":"Services"
        }
    ],
    "sg:phone":"+1 850 433 4521",
    "sg:postcode":"32501",
    "sg:province":"FL",
    "sg:tags":[
        "plumbing",
        "contractor"
    ],
    "wof:name":"High Tech Plumbing & Heating",
    "wof:placetype":"venue"
},
  "geometry": {"coordinates":[-87.229702,30.444252],"type":"Point"}
}