{
  "type": "Feature",
  "properties": {
    "iso:country":"US",
    "sg:address":"2212 N Pearl St",
    "sg:city":"Jacksonville",
    "sg:classifiers":[
        {
            "category":"Manufacturing",
            "subcategory":"Paper Products",
            "type":"Manufacturing & Wholesale Goods"
        }
    ],
    "sg:phone":"+1 904 356 6063",
    "sg:postcode":"32206",
    "sg:province":"FL",
    "sg:tags":[
        "boxes-corrugated",
        "fiber"
    ],
    "sg:website":"http://www.kandgbox.com",
    "wof:name":"K & G Box Co Inc",
    "wof:placetype":"venue"
},
  "geometry": {"coordinates":[-81.65836400000001,30.350802],"type":"Point"}
}