{
  "type": "Feature",
  "properties": {
    "iso:country":"US",
    "sg:address":"13711 Gulf Blvd",
    "sg:city":"Madeira Beach",
    "sg:classifiers":[
        {
            "category":"Restaurant",
            "type":"Food & Drink"
        }
    ],
    "sg:phone":"+1 727 395 0052",
    "sg:postcode":"33708",
    "sg:province":"FL",
    "wof:name":"Cordello Pizza & Subs",
    "wof:placetype":"venue"
},
  "geometry": {"coordinates":[-82.790431,27.792461],"type":"Point"}
}