{
  "type": "Feature",
  "properties": {
    "addr:full":"12169 Dixie Hwy Miami FL 33156",
    "addr:housenumber":"12169",
    "addr:postcode":"33156",
    "addr:street":"Dixie Hwy",
    "iso:country":"US",
    "sg:address":"12169 Dixie Hwy",
    "sg:city":"Miami",
    "sg:classifiers":[
        {
            "category":"Professional",
            "subcategory":"Engineering",
            "type":"Services"
        }
    ],
    "sg:phone":"+1 305 251 8372",
    "sg:postcode":"33156",
    "sg:province":"FL",
    "sg:tags":[
        "engineer"
    ],
    "wof:name":"Alfredo Carbonell Inc",
    "wof:placetype":"venue"
},
  "geometry": {"coordinates":[-80.327652,25.657751],"type":"Point"}
}