{
  "type": "Feature",
  "properties": {
    "iso:country":"US",
    "sg:address":"812 NW 24th Ct",
    "sg:city":"Miami",
    "sg:classifiers":[
        {
            "category":"Building & Trades",
            "subcategory":"Plumbing",
            "type":"Services"
        }
    ],
    "sg:phone":"+1 305 541 4875",
    "sg:postcode":"33125",
    "sg:province":"FL",
    "sg:tags":[
        "contractor"
    ],
    "wof:name":"Mendez General Service Co",
    "wof:placetype":"venue"
},
  "geometry": {"coordinates":[-80.236496,25.780271],"type":"Point"}
}