{
  "type": "Feature",
  "properties": {
    "addr:full":"5859 NW 37th St Virginia Gardens FL 33166",
    "addr:housenumber":"5859",
    "addr:postcode":"33166",
    "addr:street":"Nw 37Th St",
    "iso:country":"US",
    "sg:address":"5859 NW 37th St",
    "sg:city":"Virginia Gardens",
    "sg:classifiers":[
        {
            "category":"Organizations",
            "subcategory":"Non-profit Organization",
            "type":"Services"
        }
    ],
    "sg:phone":"+1 786 265 9116",
    "sg:postcode":"33166",
    "sg:province":"FL",
    "sg:tags":[
        "info",
        "addiction",
        "abuse",
        "treatment",
        "drug"
    ],
    "wof:name":"Nueva Vida Ministerio Catolico",
    "wof:placetype":"venue"
},
  "geometry": {"coordinates":[-80.292097,25.808159],"type":"Point"}
}