{
  "type": "Feature",
  "properties": {
    "iso:country":"US",
    "sg:address":"9201 Cypress Lake Dr",
    "sg:city":"Fort Myers",
    "sg:classifiers":[
        {
            "category":"Shopping",
            "subcategory":"Optical Goods",
            "type":"Retail Goods"
        }
    ],
    "sg:phone":"+1 239 481 8171",
    "sg:postcode":"33919",
    "sg:province":"FL",
    "sg:tags":[
        "optician",
        "eyewear"
    ],
    "wof:name":"Cypress Lake Eyewear",
    "wof:placetype":"venue"
},
  "geometry": {"coordinates":[-81.906502,26.545601],"type":"Point"}
}