{
  "type": "Feature",
  "properties": {
    "iso:country":"US",
    "sg:address":"169 Eglin Pkwy S",
    "sg:city":"Fort Walton Beach",
    "sg:classifiers":[
        {
            "category":"Wholesale",
            "subcategory":"Durable Goods & Equipment",
            "type":"Manufacturing & Wholesale Goods"
        }
    ],
    "sg:phone":"+1 850 243 4991",
    "sg:postcode":"32548",
    "sg:province":"FL",
    "wof:name":"Marilyn and Company",
    "wof:placetype":"venue"
},
  "geometry": {"coordinates":[-86.60633,30.40529],"type":"Point"}
}