{
  "type": "Feature",
  "properties": {
    "iso:country":"US",
    "sg:address":"2633 Mercy Dr",
    "sg:city":"Orlando",
    "sg:classifiers":[
        {
            "category":"Wholesale",
            "subcategory":"Machinery & Supplies",
            "type":"Manufacturing & Wholesale Goods"
        }
    ],
    "sg:phone":"+1 407 578 5633",
    "sg:postcode":"32808",
    "sg:province":"FL",
    "sg:tags":[
        "dry",
        "equipment",
        "mfg",
        "cleaning",
        "representative"
    ],
    "wof:name":"Coastal Equipment Company",
    "wof:placetype":"venue"
},
  "geometry": {"coordinates":[-81.430742,28.578441],"type":"Point"}
}