{
  "type": "Feature",
  "properties": {
    "iso:country":"US",
    "sg:address":"1025 S Semoran Blvd",
    "sg:city":"Winter Park",
    "sg:classifiers":[
        {
            "category":"Professional",
            "subcategory":"Accounting & Tax Preparation",
            "type":"Services"
        }
    ],
    "sg:phone":"+1 407 671 1477",
    "sg:postcode":"32792",
    "sg:province":"FL",
    "sg:tags":[
        "consultant"
    ],
    "wof:name":"Marvin F Poer & Co",
    "wof:placetype":"venue"
},
  "geometry": {"coordinates":[-81.30767,28.581095],"type":"Point"}
}