{
  "type": "Feature",
  "properties": {
    "addr:full":"18867 Big Cypress Dr Jupiter FL 33458",
    "addr:housenumber":"18867",
    "addr:postcode":"33458",
    "addr:street":"Big Cypress Dr",
    "iso:country":"US",
    "sg:address":"18867 Big Cypress Dr",
    "sg:city":"Jupiter",
    "sg:classifiers":[
        {
            "category":"Wholesale",
            "subcategory":"Chemicals & Plastics",
            "type":"Manufacturing & Wholesale Goods"
        }
    ],
    "sg:phone":"+1 561 747 4484",
    "sg:postcode":"33458",
    "sg:province":"FL",
    "sg:tags":[
        "water",
        "treating"
    ],
    "wof:name":"Hercules Incorporated",
    "wof:placetype":"venue"
},
  "geometry": {"coordinates":[-80.138445,26.954454],"type":"Point"}
}