{
  "type": "Feature",
  "properties": {
    "addr:full":"1342 Champion Dr Lakeland FL 33801",
    "addr:housenumber":"1342",
    "addr:postcode":"33801",
    "addr:street":"Champion Dr",
    "iso:country":"US",
    "sg:address":"1342 Champion Dr",
    "sg:city":"Lakeland",
    "sg:classifiers":[
        {
            "category":"Organizations",
            "subcategory":"Membership Organization",
            "type":"Services"
        }
    ],
    "sg:phone":"+1 863 667 4779",
    "sg:postcode":"33801",
    "sg:province":"FL",
    "wof:name":"Nabi of Florida",
    "wof:placetype":"venue"
},
  "geometry": {"coordinates":[-81.86359,28.062026],"type":"Point"}
}