{
  "type": "Feature",
  "properties": {
    "iso:country":"US",
    "sg:address":"2607 Springhill Rd",
    "sg:city":"Tallahassee",
    "sg:classifiers":[
        {
            "category":"Building & Trades",
            "subcategory":"Construction",
            "type":"Services"
        }
    ],
    "sg:phone":"+1 850 576 2606",
    "sg:postcode":"32305",
    "sg:province":"FL",
    "sg:tags":[
        "paving",
        "asphalt",
        "contractor"
    ],
    "wof:name":"Cox Asphalt Maintenance Inc",
    "wof:placetype":"venue"
},
  "geometry": {"coordinates":[-84.30399199999999,30.411261],"type":"Point"}
}