{
  "type": "Feature",
  "properties": {
    "iso:country":"US",
    "sg:address":"1311 24th Ave SW",
    "sg:city":"Vero Beach",
    "sg:classifiers":[
        {
            "category":"Building & Trades",
            "subcategory":"Construction",
            "type":"Services"
        }
    ],
    "sg:phone":"+1 772 562 8480",
    "sg:postcode":"32962",
    "sg:province":"FL",
    "sg:tags":[
        "contractor"
    ],
    "wof:name":"Brian Tarry Rescreening",
    "wof:placetype":"venue"
},
  "geometry": {"coordinates":[-80.410284,27.5794],"type":"Point"}
}