{
  "type": "Feature",
  "properties": {
    "iso:country":"US",
    "sg:address":"3553 Industrial Park Dr",
    "sg:city":"Marianna",
    "sg:classifiers":[
        {
            "category":"Professional",
            "subcategory":"Detective & Security Services",
            "type":"Services"
        }
    ],
    "sg:phone":"+1 850 526 1400",
    "sg:postcode":"32446",
    "sg:province":"FL",
    "sg:tags":[
        "information",
        "bureau"
    ],
    "wof:name":"Gilmore Services Of Marianna",
    "wof:placetype":"venue"
},
  "geometry": {"coordinates":[-85.17156900000001,30.823099],"type":"Point"}
}