{
  "type": "Feature",
  "properties": {
    "iso:country":"US",
    "sg:address":"3930 SW 2 Ave",
    "sg:city":"Gainesville",
    "sg:classifiers":[
        {
            "category":"Retail",
            "subcategory":"Laundry & Dry Cleaning",
            "type":"Services"
        }
    ],
    "sg:phone":"+1 352 336 2238",
    "sg:postcode":"32607",
    "sg:province":"FL",
    "sg:tags":[
        "cleaners",
        "rug",
        "carpet"
    ],
    "wof:name":"Absolute Clean",
    "wof:placetype":"venue"
},
  "geometry": {"coordinates":[-82.382429,29.650572],"type":"Point"}
}