{
  "type": "Feature",
  "properties": {
    "addr:full":"1330 Central Florida Pkwy Orlando FL 32837",
    "addr:housenumber":"1330",
    "addr:postcode":"32837",
    "addr:street":"Central Florida Pkwy",
    "iso:country":"US",
    "sg:address":"1330 Central Florida Pkwy",
    "sg:city":"Orlando",
    "sg:classifiers":[
        {
            "category":"Manufacturing",
            "subcategory":"Paper Products",
            "type":"Manufacturing & Wholesale Goods"
        }
    ],
    "sg:phone":"+1 407 855 5120",
    "sg:postcode":"32837",
    "sg:province":"FL",
    "sg:tags":[
        "corrugated",
        "box",
        "mfg",
        "point",
        "purchase",
        "display"
    ],
    "wof:name":"Dusobox Creative Packg Group",
    "wof:placetype":"venue"
},
  "geometry": {"coordinates":[-81.397001,28.406671],"type":"Point"}
}