{
  "type": "Feature",
  "properties": {
    "addr:full":"2535 Wild Wood Dr Melbourne FL 32935",
    "addr:housenumber":"2535",
    "addr:postcode":"32935",
    "addr:street":"Wild Wood Dr",
    "iso:country":"US",
    "sg:address":"2535 Wild Wood Dr",
    "sg:city":"Melbourne",
    "sg:classifiers":[
        {
            "category":"Professional",
            "subcategory":"Computer Services",
            "type":"Services"
        }
    ],
    "sg:phone":"+1 321 508 3791",
    "sg:postcode":"32935",
    "sg:province":"FL",
    "sg:tags":[
        "wiring"
    ],
    "wof:name":"Structured Concepts",
    "wof:placetype":"venue"
},
  "geometry": {"coordinates":[-80.663814,28.179595],"type":"Point"}
}