{
  "type": "Feature",
  "properties": {
    "iso:country":"US",
    "sg:address":"4445 N US Hwy 17",
    "sg:city":"Deland",
    "sg:classifiers":[
        {
            "category":"Autos & Motor Vehicles",
            "subcategory":"Automobile Sales",
            "type":"Retail Goods"
        }
    ],
    "sg:phone":"+1 386 985 2286",
    "sg:postcode":"32720",
    "sg:province":"FL",
    "sg:tags":[
        "car",
        "used",
        "dealer"
    ],
    "wof:name":"Vaughn Used Cars",
    "wof:placetype":"venue"
},
  "geometry": {"coordinates":[-81.33969399999999,29.102719],"type":"Point"}
}