{
  "type": "Feature",
  "properties": {
    "addr:full":"7820 SW 55th Ave Miami FL 33143",
    "addr:housenumber":"7820",
    "addr:postcode":"33143",
    "addr:street":"Sw 55Th Ave",
    "iso:country":"US",
    "sg:address":"7820 SW 55th Ave",
    "sg:city":"Miami",
    "sg:classifiers":[
        {
            "category":"Manufacturing",
            "subcategory":"Printing",
            "type":"Manufacturing & Wholesale Goods"
        }
    ],
    "sg:phone":"+1 305 382 8819",
    "sg:postcode":"33143",
    "sg:province":"FL",
    "sg:tags":[
        "book"
    ],
    "wof:name":"Shone Holding Inc",
    "wof:placetype":"venue"
},
  "geometry": {"coordinates":[-80.28338599999999,25.697275],"type":"Point"}
}