{
  "type": "Feature",
  "properties": {
    "addr:full":"3379 E Lake Shore Ln Clearwater FL 33761",
    "addr:housenumber":"3379",
    "addr:postcode":"33761",
    "addr:street":"E Lake Shore Ln",
    "iso:country":"US",
    "sg:address":"3379 E Lake Shore Ln",
    "sg:city":"Clearwater",
    "sg:classifiers":[
        {
            "category":"Building & Trades",
            "subcategory":"Construction",
            "type":"Services"
        }
    ],
    "sg:phone":"+1 727 787 9859",
    "sg:postcode":"33761",
    "sg:province":"FL",
    "sg:tags":[
        "tile",
        "dealer"
    ],
    "wof:name":"Affordable Concepts Inc",
    "wof:placetype":"venue"
},
  "geometry": {"coordinates":[-82.728202,28.04473],"type":"Point"}
}