{
  "type": "Feature",
  "properties": {
    "iso:country":"US",
    "sg:address":"2700 W Atlantic Blvd",
    "sg:city":"Pompano Beach",
    "sg:classifiers":[
        {
            "category":"Banks & Credit Unions",
            "subcategory":"Bank",
            "type":"Services"
        }
    ],
    "sg:phone":"+1 954 957 8225",
    "sg:postcode":"33069",
    "sg:province":"FL",
    "sg:tags":[
        "other",
        "plan",
        "card"
    ],
    "wof:name":"Bankcard Brokers MSP Inc",
    "wof:placetype":"venue"
},
  "geometry": {"coordinates":[-80.161389,26.23123],"type":"Point"}
}