{
  "type": "Feature",
  "properties": {
    "iso:country":"US",
    "sg:address":"3210 W Cypress St",
    "sg:city":"Tampa",
    "sg:classifiers":[
        {
            "category":"Professional",
            "subcategory":"Lawyer & Legal Services",
            "type":"Services"
        }
    ],
    "sg:phone":"+1 813 281 2897",
    "sg:postcode":"33607",
    "sg:province":"FL",
    "sg:tags":[
        "attorney",
        "criminal",
        "family",
        "duo",
        "personal",
        "injury",
        "dwi",
        "law"
    ],
    "sg:website":"http://www.TheAdvocateForYou.com",
    "wof:name":"Taracks, Gomez & Associates",
    "wof:placetype":"venue"
},
  "geometry": {"coordinates":[-82.49633799999999,27.95207],"type":"Point"}
}