{
  "type": "Feature",
  "properties": {
    "addr:full":"5598 Commercial Way Spring Hill FL 34606",
    "addr:housenumber":"5598",
    "addr:postcode":"34606",
    "addr:street":"Commercial Way",
    "iso:country":"US",
    "sg:address":"5598 Commercial Way",
    "sg:city":"Spring Hill",
    "sg:classifiers":[
        {
            "category":"Restaurant",
            "type":"Food & Drink"
        }
    ],
    "sg:phone":"+1 352 686 8806",
    "sg:postcode":"34606",
    "sg:province":"FL",
    "sg:tags":[
        "eating"
    ],
    "wof:name":"Don Ramon's Cafe",
    "wof:placetype":"venue"
},
  "geometry": {"coordinates":[-82.580361,28.509797],"type":"Point"}
}