{
  "type": "Feature",
  "properties": {
    "iso:country":"US",
    "sg:address":"2045 N 12th Ave",
    "sg:city":"Pensacola",
    "sg:classifiers":[
        {
            "category":"Health Services",
            "subcategory":"Chiropractor",
            "type":"Services"
        }
    ],
    "sg:phone":"+1 850 437 1056",
    "sg:postcode":"32503",
    "sg:province":"FL",
    "sg:tags":[
        "chiropractic"
    ],
    "wof:name":"Progressive Family Chiropractic",
    "wof:placetype":"venue"
},
  "geometry": {"coordinates":[-87.205305,30.435591],"type":"Point"}
}