{
  "type": "Feature",
  "properties": {
    "iso:country":"US",
    "sg:address":"1800 W 49th St Ste 405",
    "sg:city":"Hialeah",
    "sg:classifiers":[
        {
            "category":"Health Services",
            "subcategory":"Doctor",
            "type":"Services"
        }
    ],
    "sg:phone":"+1 305 823 6045",
    "sg:postcode":"33012",
    "sg:province":"FL",
    "sg:tags":[
        "dermatologist"
    ],
    "wof:name":"Brahmatewari Just MD",
    "wof:placetype":"venue"
},
  "geometry": {"coordinates":[-80.31905,25.866393],"type":"Point"}
}