{
  "type": "Feature",
  "properties": {
    "addr:full":"1005 Trask Ln Bartow FL 33830",
    "addr:housenumber":"1005",
    "addr:postcode":"33830",
    "addr:street":"Trask Ln",
    "iso:country":"US",
    "sg:address":"1005 Trask Ln",
    "sg:city":"Bartow",
    "sg:classifiers":[
        {
            "category":"Real Estate",
            "subcategory":"Real Estate Services",
            "type":"Services"
        },
        {
            "category":"Real Estate",
            "subcategory":"Real Estate Agent",
            "type":"Services"
        }
    ],
    "sg:phone":"+1 863 533 3938",
    "sg:postcode":"33830",
    "sg:province":"FL",
    "sg:tags":[
        "management"
    ],
    "wof:name":"Rosie Thornburg",
    "wof:placetype":"venue"
},
  "geometry": {"coordinates":[-81.853604,27.911487],"type":"Point"}
}