{
  "type": "Feature",
  "properties": {
    "iso:country":"US",
    "sg:address":"6292 Tower Ln",
    "sg:city":"Sarasota",
    "sg:classifiers":[
        {
            "category":"Wholesale",
            "subcategory":"Chemicals & Plastics",
            "type":"Manufacturing & Wholesale Goods"
        }
    ],
    "sg:phone":"+1 941 343 9343",
    "sg:postcode":"34240",
    "sg:province":"FL",
    "wof:name":"Chemnet Sarasota",
    "wof:placetype":"venue"
},
  "geometry": {"coordinates":[-82.445465,27.329853],"type":"Point"}
}