{
  "type": "Feature",
  "properties": {
    "iso:country":"US",
    "sg:address":"2484 W State Rd 434",
    "sg:city":"Longwood",
    "sg:classifiers":[
        {
            "category":"Museum",
            "type":"Entertainment"
        }
    ],
    "sg:phone":"+1 407 682 0220",
    "sg:postcode":"32779",
    "sg:province":"FL",
    "sg:tags":[
        "organization",
        "arts",
        "information"
    ],
    "wof:name":"Whitman School For Performing",
    "wof:placetype":"venue"
},
  "geometry": {"coordinates":[-81.403057,28.687138],"type":"Point"}
}