{
  "type": "Feature",
  "properties": {
    "iso:country":"US",
    "sg:address":"6737 Tower Dr",
    "sg:city":"Hudson",
    "sg:classifiers":[
        {
            "category":"Home & Garden",
            "subcategory":"Building Materials",
            "type":"Retail Goods"
        }
    ],
    "sg:phone":"+1 727 868 2161",
    "sg:postcode":"34667",
    "sg:province":"FL",
    "sg:tags":[
        "plasterboard",
        "wallboard"
    ],
    "sg:website":"www.rinker.com",
    "wof:name":"Rinker Materials Gypsum Supply",
    "wof:placetype":"venue"
},
  "geometry": {"coordinates":[-82.703575,28.346083],"type":"Point"}
}