{
  "type": "Feature",
  "properties": {
    "iso:country":"US",
    "sg:address":"1340 NE 140th St",
    "sg:city":"Citra",
    "sg:classifiers":[
        {
            "category":"Building & Trades",
            "subcategory":"Construction",
            "type":"Services"
        }
    ],
    "sg:phone":"+1 352 622 8050",
    "sg:postcode":"32192",
    "sg:province":"FL",
    "sg:tags":[
        "dry wall",
        "contractor"
    ],
    "wof:name":"Dennis W Young Repair Svc",
    "wof:placetype":"venue"
},
  "geometry": {"coordinates":[-82.121965,29.35289],"type":"Point"}
}