{
  "type": "Feature",
  "properties": {
    "iso:country":"US",
    "sg:address":"1845 SW 3rd St",
    "sg:city":"Miami",
    "sg:classifiers":[
        {
            "category":"Building & Trades",
            "subcategory":"Electrical",
            "type":"Services"
        }
    ],
    "sg:phone":"+1 305 541 7498",
    "sg:postcode":"33135",
    "sg:province":"FL",
    "sg:tags":[
        "electrical",
        "contractor"
    ],
    "wof:name":"Llanes Electric Inc",
    "wof:placetype":"venue"
},
  "geometry": {"coordinates":[-80.225244,25.769795],"type":"Point"}
}