{
  "type": "Feature",
  "properties": {
    "addr:full":"20764 W Dixie Hwy Miami FL 33180",
    "addr:housenumber":"20764",
    "addr:postcode":"33180",
    "addr:street":"W Dixie Hwy",
    "iso:country":"US",
    "sg:address":"20764 W Dixie Hwy",
    "sg:city":"Miami",
    "sg:classifiers":[
        {
            "category":"Professional",
            "subcategory":"Accounting & Tax Preparation",
            "type":"Services"
        }
    ],
    "sg:phone":"+1 305 931 9844",
    "sg:postcode":"33180",
    "sg:province":"FL",
    "sg:tags":[
        "accountant",
        "public",
        "certified"
    ],
    "wof:name":"CBA Associates Pa",
    "wof:placetype":"venue"
},
  "geometry": {"coordinates":[-80.147926,25.968205],"type":"Point"}
}