{
  "type": "Feature",
  "properties": {
    "addr:full":"9632 Ilex Cir S Palm Beach Gardens FL 33410",
    "addr:housenumber":"9632",
    "addr:postcode":"33410",
    "addr:street":"Ilex Cir S Palm Beach Gardens",
    "iso:country":"US",
    "sg:address":"9632 Ilex Cir S",
    "sg:city":"Palm Beach Gardens",
    "sg:classifiers":[
        {
            "category":"Building & Trades",
            "subcategory":"Plumbing",
            "type":"Services"
        }
    ],
    "sg:phone":"+1 561 848 7231",
    "sg:postcode":"33410",
    "sg:province":"FL",
    "sg:tags":[
        "contractor"
    ],
    "wof:name":"North County Cooling Inc",
    "wof:placetype":"venue"
},
  "geometry": {"coordinates":[-80.098744,26.8184],"type":"Point"}
}