{
  "type": "Feature",
  "properties": {
    "iso:country":"US",
    "sg:address":"10050 Griffin Rd",
    "sg:city":"Cooper City",
    "sg:classifiers":[
        {
            "category":"Manufacturing",
            "subcategory":"Printing",
            "type":"Manufacturing & Wholesale Goods"
        }
    ],
    "sg:phone":"+1 954 680 8496",
    "sg:postcode":"33328",
    "sg:province":"FL",
    "sg:tags":[
        "screen"
    ],
    "wof:name":"Select Screenprinting Inc",
    "wof:placetype":"venue"
},
  "geometry": {"coordinates":[-80.280362,26.064062],"type":"Point"}
}