{
  "type": "Feature",
  "properties": {
    "iso:country":"US",
    "sg:address":"1100 S Missouri Ave",
    "sg:city":"Clearwater",
    "sg:classifiers":[
        {
            "category":"Government",
            "subcategory":"Office",
            "type":"Public Place"
        },
        {
            "category":"Real Estate",
            "subcategory":"Real Estate Operator",
            "type":"Services"
        }
    ],
    "sg:phone":"+1 727 443 3399",
    "sg:postcode":"33756",
    "sg:province":"FL",
    "sg:tags":[
        "housing",
        "apartment",
        "authority"
    ],
    "wof:name":"Main Street Apartments",
    "wof:placetype":"venue"
},
  "geometry": {"coordinates":[-82.787582,27.954091],"type":"Point"}
}