{
  "type": "Feature",
  "properties": {
    "iso:country":"US",
    "sg:address":"7700 N Kendall Drive, Suite 408",
    "sg:city":"Miami",
    "sg:classifiers":[
        {
            "category":"Real Estate",
            "subcategory":"Real Estate Services",
            "type":"Services"
        }
    ],
    "sg:phone":"+1 305 595 5500",
    "sg:postcode":"33156",
    "sg:province":"FL",
    "sg:tags":[
        "commercial"
    ],
    "sg:website":"http://www.412iplansinc.net",
    "wof:name":"HealthSpectrum, Inc.",
    "wof:placetype":"venue"
},
  "geometry": {"coordinates":[-80.319389,25.688398],"type":"Point"}
}