{
  "type": "Feature",
  "properties": {
    "addr:full":"9420 Griffin Rd Cooper City FL 33328",
    "addr:housenumber":"9420",
    "addr:postcode":"33328",
    "addr:street":"Griffin Rd",
    "iso:country":"US",
    "sg:address":"9420 Griffin Rd",
    "sg:city":"Cooper City",
    "sg:classifiers":[
        {
            "category":"Shopping",
            "subcategory":"Jewelry",
            "type":"Retail Goods"
        }
    ],
    "sg:phone":"+1 954 434 1840",
    "sg:postcode":"33328",
    "sg:province":"FL",
    "sg:tags":[
        "jeweler"
    ],
    "wof:name":"Cooper City Jewelry",
    "wof:placetype":"venue"
},
  "geometry": {"coordinates":[-80.27157699999999,26.064299],"type":"Point"}
}