{
  "type": "Feature",
  "properties": {
    "iso:country":"US",
    "sg:address":"10912 N 56th St",
    "sg:city":"Tampa",
    "sg:classifiers":[
        {
            "category":"Professional",
            "subcategory":"Accounting & Tax Preparation",
            "type":"Services"
        }
    ],
    "sg:phone":"+1 813 980 2734",
    "sg:postcode":"33617",
    "sg:province":"FL",
    "wof:name":"Dollars Snse Cmptrzed Accnting",
    "wof:placetype":"venue"
},
  "geometry": {"coordinates":[-82.393753,28.048858],"type":"Point"}
}