{
  "type": "Feature",
  "properties": {
    "addr:full":"4315 NW 93rd Doral FL 33178",
    "addr:housenumber":"4315",
    "addr:postcode":"33178",
    "addr:street":"Nw 93Rd",
    "iso:country":"US",
    "sg:address":"4315 NW 93rd",
    "sg:city":"Doral",
    "sg:classifiers":[
        {
            "category":"Building & Trades",
            "subcategory":"Cleaning & Sanitation",
            "type":"Services"
        }
    ],
    "sg:phone":"+1 786 472 9471",
    "sg:postcode":"33178",
    "sg:province":"FL",
    "sg:tags":[
        "carpet"
    ],
    "sg:website":"www.doralcarpetcleaning.net/",
    "wof:name":"Doral Carpet Cleaning",
    "wof:placetype":"venue"
},
  "geometry": {"coordinates":[-80.345068,25.814072],"type":"Point"}
}