{
  "type": "Feature",
  "properties": {
    "iso:country":"US",
    "sg:address":"1511 N Mission Rd",
    "sg:city":"Tallahassee",
    "sg:classifiers":[
        {
            "category":"Communications",
            "subcategory":"Film & Video Production",
            "type":"Services"
        }
    ],
    "sg:phone":"+1 850 386 2818",
    "sg:postcode":"32304",
    "sg:province":"FL",
    "sg:tags":[
        "taping"
    ],
    "wof:name":"Tallytown Productions",
    "wof:placetype":"venue"
},
  "geometry": {"coordinates":[-84.343648,30.463503],"type":"Point"}
}