{
  "type": "Feature",
  "properties": {
    "addr:full":"10310 S Ocean Dr Jensen Beach FL 34957",
    "addr:housenumber":"10310",
    "addr:postcode":"34957",
    "addr:street":"S Ocean Dr",
    "iso:country":"US",
    "sg:address":"10310 S Ocean Dr",
    "sg:city":"Jensen Beach",
    "sg:classifiers":[
        {
            "category":"Freight",
            "type":"Transportation"
        }
    ],
    "sg:phone":"+1 772 229 9212",
    "sg:postcode":"34957",
    "sg:province":"FL",
    "wof:name":"Jensen Movers Inc",
    "wof:placetype":"venue"
},
  "geometry": {"coordinates":[-80.20659999999999,27.27405],"type":"Point"}
}