{
  "type": "Feature",
  "properties": {
    "iso:country":"US",
    "sg:address":"495 Carswell Ave",
    "sg:city":"Daytona Beach",
    "sg:classifiers":[
        {
            "category":"Professional",
            "subcategory":"Business Services",
            "type":"Services"
        },
        {
            "category":"Building & Trades",
            "subcategory":"Construction",
            "type":"Services"
        }
    ],
    "sg:phone":"+1 386 255 2523",
    "sg:postcode":"32117",
    "sg:province":"FL",
    "sg:tags":[
        "plastering",
        "coping",
        "contractor",
        "tiling",
        "pool",
        "swimming"
    ],
    "wof:name":"Aquasol Commercial Chemical",
    "wof:placetype":"venue"
},
  "geometry": {"coordinates":[-81.036356,29.232309],"type":"Point"}
}