{
  "type": "Feature",
  "properties": {
    "iso:country":"US",
    "sg:address":"10 NE 3rd St",
    "sg:city":"Miami",
    "sg:classifiers":[
        {
            "category":"Arts & Performance",
            "subcategory":"Art Gallery",
            "type":"Entertainment"
        }
    ],
    "sg:phone":"+1 305 579 0069",
    "sg:postcode":"33132",
    "sg:province":"FL",
    "wof:name":"Wallflower Gallery",
    "wof:placetype":"venue"
},
  "geometry": {"coordinates":[-80.19360399999999,25.776899],"type":"Point"}
}