{
  "type": "Feature",
  "properties": {
    "iso:country":"US",
    "sg:address":"5650 S Florida Ave",
    "sg:city":"Lakeland",
    "sg:classifiers":[
        {
            "category":"Restaurant",
            "type":"Food & Drink"
        }
    ],
    "sg:phone":"+1 863 709 9262",
    "sg:postcode":"33813",
    "sg:province":"FL",
    "sg:tags":[
        "menu"
    ],
    "wof:name":"Lakeland Ale House",
    "wof:placetype":"venue"
},
  "geometry": {"coordinates":[-81.96570699999999,27.963918],"type":"Point"}
}