{
  "type": "Feature",
  "properties": {
    "addr:full":"7820 Peters Rd Fort Lauderdale FL 33317",
    "addr:housenumber":"7820",
    "addr:postcode":"33317",
    "addr:street":"Peters Rd",
    "iso:country":"US",
    "sg:address":"7820 Peters Rd",
    "sg:city":"Fort Lauderdale",
    "sg:classifiers":[
        {
            "category":"Wholesale",
            "subcategory":"Drugs",
            "type":"Manufacturing & Wholesale Goods"
        }
    ],
    "sg:phone":"+1 954 474 8174",
    "sg:postcode":"33317",
    "sg:province":"FL",
    "wof:name":"Leo Pharma Inc",
    "wof:placetype":"venue"
},
  "geometry": {"coordinates":[-80.253276,26.105308],"type":"Point"}
}