{
  "type": "Feature",
  "properties": {
    "iso:country":"US",
    "sg:address":"8340 NW 25th Ct",
    "sg:city":"Fort Lauderdale",
    "sg:classifiers":[
        {
            "category":"Professional",
            "subcategory":"Business Services",
            "type":"Services"
        }
    ],
    "sg:phone":"+1 954 914 0692",
    "sg:postcode":"33322",
    "sg:province":"FL",
    "sg:tags":[
        "marketing",
        "corporate"
    ],
    "wof:name":"JKG Resources Inc",
    "wof:placetype":"venue"
},
  "geometry": {"coordinates":[-80.26128799999999,26.156597],"type":"Point"}
}