{
  "type": "Feature",
  "properties": {
    "iso:country":"US",
    "sg:address":"30214 US Hwy 19",
    "sg:city":"Clearwater",
    "sg:classifiers":[
        {
            "category":"Shopping",
            "subcategory":"Hobbies, Toys, & Games",
            "type":"Retail Goods"
        }
    ],
    "sg:phone":"+1 727 773 1600",
    "sg:postcode":"33761",
    "sg:province":"FL",
    "sg:tags":[
        "equipment",
        "ceramic",
        "supply"
    ],
    "wof:name":"Florida Ceramic Sales Inc",
    "wof:placetype":"venue"
},
  "geometry": {"coordinates":[-82.73858,28.046677],"type":"Point"}
}