{
  "type": "Feature",
  "properties": {
    "addr:full":"450 W 4th Ave Tallahassee FL 32303",
    "addr:housenumber":"450",
    "addr:postcode":"32303",
    "addr:street":"W 4Th Ave",
    "iso:country":"US",
    "sg:address":"450 W 4th Ave",
    "sg:city":"Tallahassee",
    "sg:classifiers":[
        {
            "category":"Recreation",
            "type":"Entertainment"
        },
        {
            "category":"Organizations",
            "subcategory":"Professional Association",
            "type":"Services"
        }
    ],
    "sg:phone":"+1 850 891 3930",
    "sg:postcode":"32303",
    "sg:province":"FL",
    "sg:tags":[
        "hall",
        "business",
        "auditorium"
    ],
    "wof:name":"Fourth Ave Community Center",
    "wof:placetype":"venue"
},
  "geometry": {"coordinates":[-84.286826,30.453702],"type":"Point"}
}