{
  "type": "Feature",
  "properties": {
    "iso:country":"US",
    "sg:address":"645 Sebastian Blvd Eastbound",
    "sg:city":"Sebastian",
    "sg:classifiers":[
        {
            "category":"Building & Trades",
            "subcategory":"Construction",
            "type":"Services"
        }
    ],
    "sg:phone":"+1 772 299 1085",
    "sg:postcode":"32958",
    "sg:province":"FL",
    "sg:tags":[
        "mobile",
        "home"
    ],
    "wof:name":"East Coast Mobile Home Svc",
    "wof:placetype":"venue"
},
  "geometry": {"coordinates":[-80.48203100000001,27.796296],"type":"Point"}
}