{
  "type": "Feature",
  "properties": {
    "iso:country":"US",
    "sg:address":"3443 Segovia St",
    "sg:city":"Coral Gables",
    "sg:classifiers":[
        {
            "category":"Education",
            "subcategory":"Library",
            "type":"Public Place"
        }
    ],
    "sg:phone":"+1 305 442 8706",
    "sg:postcode":"33134",
    "sg:province":"FL",
    "wof:name":"Coral Gables Public Library",
    "wof:placetype":"venue"
},
  "geometry": {"coordinates":[-80.26619700000001,25.739799],"type":"Point"}
}