{
  "type": "Feature",
  "properties": {
    "iso:country":"US",
    "sg:address":"108 Beal Pkwy SW",
    "sg:city":"Fort Walton Bch",
    "sg:classifiers":[
        {
            "category":"Professional",
            "subcategory":"Accounting & Tax Preparation",
            "type":"Services"
        }
    ],
    "sg:phone":"+1 850 244 4108",
    "sg:postcode":"32548",
    "sg:province":"FL",
    "sg:tags":[
        "accountant"
    ],
    "wof:name":"Susan M Surber CPA",
    "wof:placetype":"venue"
},
  "geometry": {"coordinates":[-86.613073,30.408894],"type":"Point"}
}