{
  "type": "Feature",
  "properties": {
    "addr:full":"28153 Lindenhurst Dr Zephyrhills FL 33544",
    "addr:housenumber":"28153",
    "addr:postcode":"33544",
    "addr:street":"Lindenhurst Dr",
    "iso:country":"US",
    "sg:address":"28153 Lindenhurst Dr",
    "sg:city":"Zephyrhills",
    "sg:classifiers":[
        {
            "category":"Building & Trades",
            "subcategory":"Landscaping Services",
            "type":"Services"
        }
    ],
    "sg:phone":"+1 813 973 4778",
    "sg:postcode":"33544",
    "sg:province":"FL",
    "sg:tags":[
        "landscape",
        "contractor"
    ],
    "wof:name":"Lawns By Les",
    "wof:placetype":"venue"
},
  "geometry": {"coordinates":[-82.351302,28.265023],"type":"Point"}
}