{
  "type": "Feature",
  "properties": {
    "addr:full":"133 E 14th St Hialeah FL 33010",
    "addr:housenumber":"133",
    "addr:postcode":"33010",
    "addr:street":"E 14Th St",
    "iso:country":"US",
    "sg:address":"133 E 14th St",
    "sg:city":"Hialeah",
    "sg:classifiers":[
        {
            "category":"Professional",
            "subcategory":"Art Services",
            "type":"Services"
        }
    ],
    "sg:phone":"+1 305 888 3405",
    "sg:postcode":"33010",
    "sg:province":"FL",
    "sg:tags":[
        "graphic",
        "designer"
    ],
    "wof:name":"J Dm Graphics",
    "wof:placetype":"venue"
},
  "geometry": {"coordinates":[-80.278385,25.834643],"type":"Point"}
}