{
  "type": "Feature",
  "properties": {
    "iso:country":"US",
    "sg:address":"3431 N 22nd St",
    "sg:city":"Tampa",
    "sg:classifiers":[
        {
            "category":"Recreation",
            "subcategory":"Arcade",
            "type":"Entertainment"
        }
    ],
    "sg:phone":"+1 813 241 0115",
    "sg:postcode":"33605",
    "sg:province":"FL",
    "wof:name":"Classic Hair Salon",
    "wof:placetype":"venue"
},
  "geometry": {"coordinates":[-82.43468900000001,27.975302],"type":"Point"}
}