{
  "type": "Feature",
  "properties": {
    "addr:full":"14300 60th St N Clearwater FL 33760",
    "addr:housenumber":"14300",
    "addr:postcode":"33760",
    "addr:street":"60Th St N",
    "iso:country":"US",
    "sg:address":"14300 60th St N",
    "sg:city":"Clearwater",
    "sg:classifiers":[
        {
            "category":"Wholesale",
            "subcategory":"Machinery & Supplies",
            "type":"Manufacturing & Wholesale Goods"
        }
    ],
    "sg:phone":"+1 727 535 3200",
    "sg:postcode":"33760",
    "sg:province":"FL",
    "sg:tags":[
        "equipment",
        "rep",
        "industrial",
        "mfg"
    ],
    "wof:name":"Pennington and Associates Inc",
    "wof:placetype":"venue"
},
  "geometry": {"coordinates":[-82.718446,27.903683],"type":"Point"}
}