{
  "type": "Feature",
  "properties": {
    "addr:full":"650 E Findley Ave Eagle Lake FL 33839",
    "addr:housenumber":"650",
    "addr:postcode":"33839",
    "addr:street":"E Findley Ave",
    "iso:country":"US",
    "sg:address":"650 E Findley Ave",
    "sg:city":"Eagle Lake",
    "sg:classifiers":[
        {
            "category":"Building & Trades",
            "subcategory":"Construction",
            "type":"Services"
        }
    ],
    "sg:phone":"+1 863 295 9478",
    "sg:postcode":"33839",
    "sg:province":"FL",
    "sg:tags":[
        "contractor"
    ],
    "wof:name":"Loyd Lath & Metal Framing",
    "wof:placetype":"venue"
},
  "geometry": {"coordinates":[-81.752956,27.979744],"type":"Point"}
}