{
  "type": "Feature",
  "properties": {
    "iso:country":"US",
    "sg:address":"3313 N Federal Hwy",
    "sg:city":"Pompano Beach",
    "sg:classifiers":[
        {
            "category":"Personal",
            "subcategory":"Beauty Salon",
            "type":"Services"
        }
    ],
    "sg:phone":"+1 954 785 0305",
    "sg:postcode":"33064",
    "sg:province":"FL",
    "sg:tags":[
        "shop"
    ],
    "wof:name":"Angel Nail",
    "wof:placetype":"venue"
},
  "geometry": {"coordinates":[-80.09793000000001,26.273034],"type":"Point"}
}