{
  "type": "Feature",
  "properties": {
    "addr:full":"1275 Bennett Dr Longwood FL 32750",
    "addr:housenumber":"1275",
    "addr:postcode":"32750",
    "addr:street":"Bennett Dr",
    "iso:country":"US",
    "sg:address":"1275 Bennett Dr",
    "sg:city":"Longwood",
    "sg:classifiers":[
        {
            "category":"Manufacturing",
            "subcategory":"Textiles",
            "type":"Manufacturing & Wholesale Goods"
        },
        {
            "category":"Manufacturing",
            "subcategory":"Retail Goods",
            "type":"Manufacturing & Wholesale Goods"
        }
    ],
    "sg:phone":"+1 407 834 2999",
    "sg:postcode":"32750",
    "sg:province":"FL",
    "sg:tags":[
        "repair",
        "assembly",
        "mfg",
        "fiberglass",
        "tape",
        "fabricating"
    ],
    "sg:website":"www.pow-rwrap.com",
    "wof:name":"Access-Able Technologies Inc",
    "wof:placetype":"venue"
},
  "geometry": {"coordinates":[-81.352818,28.689888],"type":"Point"}
}