{
  "type": "Feature",
  "properties": {
    "addr:full":"401 Carpenters Way Lakeland FL 33809",
    "addr:housenumber":"401",
    "addr:postcode":"33809",
    "addr:street":"Carpenters Way",
    "iso:country":"US",
    "sg:address":"401 Carpenters Way",
    "sg:city":"Lakeland",
    "sg:classifiers":[
        {
            "category":"Recreation",
            "type":"Entertainment"
        }
    ],
    "sg:phone":"+1 863 858 4451",
    "sg:postcode":"33809",
    "sg:province":"FL",
    "sg:tags":[
        "club"
    ],
    "sg:website":"www.golfwedgewood.com",
    "wof:name":"Wedgewood Golf & Country Club",
    "wof:placetype":"venue"
},
  "geometry": {"coordinates":[-81.958513,28.093732],"type":"Point"}
}