{
  "type": "Feature",
  "properties": {
    "addr:full":"2721 N HIAWASSEE RD ORLANDO FL 32818",
    "addr:housenumber":"2721",
    "addr:postcode":"32818",
    "addr:street":"N Hiawassee Rd",
    "iso:country":"US",
    "sg:address":"2721 N HIAWASSEE RD",
    "sg:city":"ORLANDO",
    "sg:classifiers":[
        {
            "category":"Home & Garden",
            "subcategory":"Household Appliances",
            "type":"Retail Goods"
        },
        {
            "category":"Communications",
            "subcategory":"Radio Station",
            "type":"Services"
        },
        {
            "category":"Shopping",
            "subcategory":"Computers & Home Electronics",
            "type":"Retail Goods"
        },
        {
            "category":"Home & Garden",
            "subcategory":"Furniture",
            "type":"Retail Goods"
        }
    ],
    "sg:phone":"+1 407 291 8683",
    "sg:postcode":"32818",
    "sg:province":"FL",
    "sg:tags":[
        "renting",
        "television",
        "leasing",
        "radio-renting",
        "equipment",
        "rental"
    ],
    "sg:website":"http://www.rentacenter.com/",
    "wof:name":"Rent-A-Center",
    "wof:placetype":"venue"
},
  "geometry": {"coordinates":[-81.47599,28.580784],"type":"Point"}
}