{
  "type": "Feature",
  "properties": {
    "iso:country":"US",
    "sg:address":"8480 SW 66th St",
    "sg:city":"Miami",
    "sg:classifiers":[
        {
            "category":"Professional",
            "subcategory":"Management & Consulting",
            "type":"Services"
        }
    ],
    "sg:phone":"+1 305 595 6375",
    "sg:postcode":"33143",
    "sg:province":"FL",
    "sg:tags":[
        "consultant",
        "business"
    ],
    "wof:name":"L & L Assoc Intl",
    "wof:placetype":"venue"
},
  "geometry": {"coordinates":[-80.330822,25.70783],"type":"Point"}
}