{
  "type": "Feature",
  "properties": {
    "addr:full":"6923 Bottle Brush Dr Port Richey FL 34668",
    "addr:housenumber":"6923",
    "addr:postcode":"34668",
    "addr:street":"Bottle Brush Dr",
    "iso:country":"US",
    "sg:address":"6923 Bottle Brush Dr",
    "sg:city":"Port Richey",
    "sg:classifiers":[
        {
            "category":"Building & Trades",
            "subcategory":"Landscaping Services",
            "type":"Services"
        }
    ],
    "sg:phone":"+1 727 847 7560",
    "sg:postcode":"34668",
    "sg:province":"FL",
    "sg:tags":[
        "lawn",
        "maintenance",
        "grounds"
    ],
    "wof:name":"Lawn Tech Prof Ground Mntnc",
    "wof:placetype":"venue"
},
  "geometry": {"coordinates":[-82.699793,28.274739],"type":"Point"}
}