{
  "type": "Feature",
  "properties": {
    "iso:country":"US",
    "sg:address":"5720 SW 17th St",
    "sg:city":"Miami",
    "sg:classifiers":[
        {
            "category":"Organizations",
            "subcategory":"Religious Organization",
            "type":"Services"
        }
    ],
    "sg:phone":"+1 305 264 5454",
    "sg:postcode":"33155",
    "sg:province":"FL",
    "wof:name":"Templo De La Biblia Abierta",
    "wof:placetype":"venue"
},
  "geometry": {"coordinates":[-80.28780399999999,25.7551],"type":"Point"}
}