{
  "type": "Feature",
  "properties": {
    "addr:full":"180 Crandon Blvd Ste 111 Key Biscayne FL 33149",
    "addr:housenumber":"180",
    "addr:postcode":"33149",
    "addr:street":"Crandon Blvd Ste 111",
    "iso:country":"US",
    "sg:address":"180 Crandon Blvd Ste 111",
    "sg:city":"Key Biscayne",
    "sg:classifiers":[
        {
            "category":"Social Services",
            "subcategory":"Child Care",
            "type":"Services"
        }
    ],
    "sg:phone":"+1 305 365 7888",
    "sg:postcode":"33149",
    "sg:province":"FL",
    "sg:tags":[
        "day"
    ],
    "sg:website":"www.champssports.com",
    "wof:name":"Champs",
    "wof:placetype":"venue"
},
  "geometry": {"coordinates":[-80.16303499999999,25.697832],"type":"Point"}
}