{
  "type": "Feature",
  "properties": {
    "iso:country":"US",
    "sg:address":"514 Via De Palmas",
    "sg:city":"Boca Raton",
    "sg:classifiers":[
        {
            "category":"Restaurant",
            "type":"Food & Drink"
        }
    ],
    "sg:menulink":"http://www.allmenus.com/fl/boca-raton/283765-jakes-stone-crab/menu/",
    "sg:phone":"+1 561 347 1055",
    "sg:postcode":"33432",
    "sg:province":"FL",
    "sg:tags":[
        "seafood",
        "american"
    ],
    "wof:name":"Jakes Stone Crab",
    "wof:placetype":"venue"
},
  "geometry": {"coordinates":[-80.08516400000001,26.347013],"type":"Point"}
}