{
  "type": "Feature",
  "properties": {
    "addr:full":"1052 E 43rd St Hialeah FL 33013",
    "addr:housenumber":"1052",
    "addr:postcode":"33013",
    "addr:street":"E 43Rd St",
    "iso:country":"US",
    "sg:address":"1052 E 43rd St",
    "sg:city":"Hialeah",
    "sg:classifiers":[
        {
            "category":"Retail",
            "subcategory":"Auto Repair",
            "type":"Services"
        }
    ],
    "sg:phone":"+1 305 685 2277",
    "sg:postcode":"33013",
    "sg:province":"FL",
    "sg:tags":[
        "body",
        "automobile",
        "painting"
    ],
    "wof:name":"LA Chispa Body Shop",
    "wof:placetype":"venue"
},
  "geometry": {"coordinates":[-80.261782,25.861878],"type":"Point"}
}