{
  "type": "Feature",
  "properties": {
    "iso:country":"US",
    "sg:address":"514 Gulf Shore Dr # 304",
    "sg:city":"Destin",
    "sg:classifiers":[
        {
            "category":"Professional",
            "subcategory":"Lawyer & Legal Services",
            "type":"Services"
        }
    ],
    "sg:phone":"+1 850 650 5611",
    "sg:postcode":"32541",
    "sg:province":"FL",
    "sg:tags":[
        "attorney",
        "practice"
    ],
    "wof:name":"John Jordan Attny",
    "wof:placetype":"venue"
},
  "geometry": {"coordinates":[-86.499571,30.384696],"type":"Point"}
}