{
  "type": "Feature",
  "properties": {
    "addr:full":"263 S US Hwy 1 Tequesta FL 33469",
    "addr:housenumber":"263",
    "addr:postcode":"33469",
    "addr:street":"S Us Hwy 1",
    "iso:country":"US",
    "sg:address":"263 S US Hwy 1",
    "sg:city":"Tequesta",
    "sg:classifiers":[
        {
            "category":"Shopping",
            "subcategory":"Gifts & Souvenirs",
            "type":"Retail Goods"
        }
    ],
    "sg:phone":"+1 561 744 6743",
    "sg:postcode":"33469",
    "sg:province":"FL",
    "sg:tags":[
        "cards",
        "greeting"
    ],
    "wof:name":"Sand Dollar Cards & Gifts",
    "wof:placetype":"venue"
},
  "geometry": {"coordinates":[-80.084918,26.956006],"type":"Point"}
}