{
  "type": "Feature",
  "properties": {
    "addr:full":"854 SE Stafford Dr Stuart FL 34996",
    "addr:housenumber":"854",
    "addr:postcode":"34996",
    "addr:street":"Se Stafford Dr",
    "iso:country":"US",
    "sg:address":"854 SE Stafford Dr",
    "sg:city":"Stuart",
    "sg:classifiers":[
        {
            "category":"Building & Trades",
            "subcategory":"Construction",
            "type":"Services"
        }
    ],
    "sg:phone":"+1 772 286 9120",
    "sg:postcode":"34996",
    "sg:province":"FL",
    "sg:tags":[
        "masonry",
        "contractor"
    ],
    "wof:name":"Castle Brick & Stone Inc",
    "wof:placetype":"venue"
},
  "geometry": {"coordinates":[-80.23137800000001,27.19169],"type":"Point"}
}