{
  "type": "Feature",
  "properties": {
    "addr:full":"2971 NW 98th Pl Miami FL 33172",
    "addr:housenumber":"2971",
    "addr:postcode":"33172",
    "addr:street":"Nw 98Th Pl",
    "iso:country":"US",
    "sg:address":"2971 NW 98th Pl",
    "sg:city":"Miami",
    "sg:classifiers":[
        {
            "category":"Restaurant",
            "type":"Food & Drink"
        }
    ],
    "sg:phone":"+1 305 477 5802",
    "sg:postcode":"33172",
    "sg:province":"FL",
    "sg:tags":[
        "eating"
    ],
    "wof:name":"Coffee Cup Franchise USA LLC",
    "wof:placetype":"venue"
},
  "geometry": {"coordinates":[-80.355919,25.801469],"type":"Point"}
}