{
  "type": "Feature",
  "properties": {
    "addr:full":"16889 W Secretariat Dr Loxahatchee FL 33470",
    "addr:housenumber":"16889",
    "addr:postcode":"33470",
    "addr:street":"W Secretariat Dr",
    "iso:country":"US",
    "sg:address":"16889 W Secretariat Dr",
    "sg:city":"Loxahatchee",
    "sg:classifiers":[
        {
            "category":"Professional",
            "subcategory":"Art Services",
            "type":"Services"
        },
        {
            "category":"Home & Garden",
            "subcategory":"Building Materials",
            "type":"Retail Goods"
        },
        {
            "category":"Building & Trades",
            "subcategory":"Construction",
            "type":"Services"
        }
    ],
    "sg:phone":"+1 561 792 0300",
    "sg:postcode":"33470",
    "sg:province":"FL",
    "sg:tags":[
        "designer",
        "altering",
        "improvement",
        "interior",
        "contractor",
        "remodeling",
        "decorator"
    ],
    "wof:name":"Moore Unique Interiors Inc",
    "wof:placetype":"venue"
},
  "geometry": {"coordinates":[-80.312642,26.714546],"type":"Point"}
}