{
  "type": "Feature",
  "properties": {
    "addr:full":"2916 Wilder Park Dr Plant City FL 33566",
    "addr:housenumber":"2916",
    "addr:postcode":"33566",
    "addr:street":"Wilder Park Dr",
    "iso:country":"US",
    "sg:address":"2916 Wilder Park Dr",
    "sg:city":"Plant City",
    "sg:classifiers":[
        {
            "category":"Insurance",
            "subcategory":"Hazard Insurance",
            "type":"Services"
        }
    ],
    "sg:phone":"+1 813 763 3926",
    "sg:postcode":"33566",
    "sg:province":"FL",
    "sg:tags":[
        "bond"
    ],
    "wof:name":"Perez Bail Bonds",
    "wof:placetype":"venue"
},
  "geometry": {"coordinates":[-82.091508,28.02893],"type":"Point"}
}