{
  "type": "Feature",
  "properties": {
    "iso:country":"US",
    "sg:address":"3785 NE 25th Ave",
    "sg:city":"Ocala",
    "sg:classifiers":[
        {
            "category":"Restaurant",
            "type":"Food & Drink"
        }
    ],
    "sg:phone":"+1 352 401 0900",
    "sg:postcode":"34479",
    "sg:province":"FL",
    "wof:name":"Northgate Diner",
    "wof:placetype":"venue"
},
  "geometry": {"coordinates":[-82.103509,29.225489],"type":"Point"}
}