{
  "type": "Feature",
  "properties": {
    "iso:country":"US",
    "sg:address":"511 E Fairfield Dr",
    "sg:city":"Pensacola",
    "sg:classifiers":[
        {
            "category":"Professional",
            "subcategory":"Accounting & Tax Preparation",
            "type":"Services"
        }
    ],
    "sg:phone":"+1 850 470 9702",
    "sg:postcode":"32503",
    "sg:province":"FL",
    "sg:tags":[
        "return",
        "filing"
    ],
    "wof:name":"Jackson Hewitt Tax Svc",
    "wof:placetype":"venue"
},
  "geometry": {"coordinates":[-87.219514,30.453231],"type":"Point"}
}