{
  "type": "Feature",
  "properties": {
    "addr:full":"6270 Coral Lake Dr Miami FL 33155",
    "addr:housenumber":"6270",
    "addr:postcode":"33155",
    "addr:street":"Coral Lake Dr",
    "iso:country":"US",
    "sg:address":"6270 Coral Lake Dr",
    "sg:city":"Miami",
    "sg:classifiers":[
        {
            "category":"Professional",
            "subcategory":"Business Services",
            "type":"Services"
        }
    ],
    "sg:phone":"+1 305 667 7208",
    "sg:postcode":"33155",
    "sg:province":"FL",
    "wof:name":"Anderson Molina & Associates",
    "wof:placetype":"venue"
},
  "geometry": {"coordinates":[-80.29596600000001,25.726532],"type":"Point"}
}