{
  "type": "Feature",
  "properties": {
    "addr:full":"4520 NE Jacksonville Rd Ocala FL 34479",
    "addr:housenumber":"4520",
    "addr:postcode":"34479",
    "addr:street":"Ne Jacksonville Rd",
    "iso:country":"US",
    "sg:address":"4520 NE Jacksonville Rd",
    "sg:city":"Ocala",
    "sg:classifiers":[
        {
            "category":"Building & Trades",
            "subcategory":"Construction",
            "type":"Services"
        }
    ],
    "sg:phone":"+1 352 286 4018",
    "sg:postcode":"34479",
    "sg:province":"FL",
    "sg:tags":[
        "restoration",
        "cleaning",
        "patio",
        "deck"
    ],
    "wof:name":"Anthony's Pressure Cleaning",
    "wof:placetype":"venue"
},
  "geometry": {"coordinates":[-82.119862,29.237545],"type":"Point"}
}