{
  "type": "Feature",
  "properties": {
    "iso:country":"US",
    "sg:address":"226 N Chestnut Rd",
    "sg:city":"Lakeland",
    "sg:classifiers":[
        {
            "category":"Manufacturing",
            "subcategory":"Furniture",
            "type":"Manufacturing & Wholesale Goods"
        }
    ],
    "sg:phone":"+1 863 701 8338",
    "sg:postcode":"33815",
    "sg:province":"FL",
    "sg:tags":[
        "mfg"
    ],
    "wof:name":"Antiques of Tomorrow",
    "wof:placetype":"venue"
},
  "geometry": {"coordinates":[-81.99413800000001,28.046303],"type":"Point"}
}