{
  "type": "Feature",
  "properties": {
    "iso:country":"US",
    "sg:address":"12723 NW 99th Pl",
    "sg:city":"Hialeah",
    "sg:classifiers":[
        {
            "category":"Building & Trades",
            "subcategory":"Landscaping Services",
            "type":"Services"
        }
    ],
    "sg:phone":"+1 305 826 4600",
    "sg:postcode":"33018",
    "sg:province":"FL",
    "sg:tags":[
        "lawn"
    ],
    "wof:name":"Jose R Noriega",
    "wof:placetype":"venue"
},
  "geometry": {"coordinates":[-80.36098699999999,25.889842],"type":"Point"}
}