{
  "type": "Feature",
  "properties": {
    "iso:country":"US",
    "sg:address":"3229 Audrey Dr",
    "sg:city":"Crestview",
    "sg:classifiers":[
        {
            "category":"Insurance",
            "subcategory":"Hazard Insurance",
            "type":"Services"
        }
    ],
    "sg:phone":"+1 850 682 5399",
    "sg:postcode":"32539",
    "sg:province":"FL",
    "wof:name":"Thomas G Moody",
    "wof:placetype":"venue"
},
  "geometry": {"coordinates":[-86.527653,30.827029],"type":"Point"}
}