{
  "type": "Feature",
  "properties": {
    "addr:full":"1744 Gulf Winds Ct Apopka FL 32712",
    "addr:housenumber":"1744",
    "addr:postcode":"32712",
    "addr:street":"Gulf Winds Ct",
    "iso:country":"US",
    "sg:address":"1744 Gulf Winds Ct",
    "sg:city":"Apopka",
    "sg:classifiers":[
        {
            "category":"Real Estate",
            "subcategory":"Real Estate Services",
            "type":"Services"
        },
        {
            "category":"Real Estate",
            "subcategory":"Real Estate Agent",
            "type":"Services"
        }
    ],
    "sg:phone":"+1 321 948 6884",
    "sg:postcode":"32712",
    "sg:province":"FL",
    "sg:tags":[
        "buyer",
        "broker"
    ],
    "wof:name":"Ponce Inlet Realty, Inc.",
    "wof:placetype":"venue"
},
  "geometry": {"coordinates":[-81.504728,28.709212],"type":"Point"}
}