{
  "type": "Feature",
  "properties": {
    "iso:country":"US",
    "sg:address":"5150 December Ln",
    "sg:city":"Brooksville",
    "sg:classifiers":[
        {
            "category":"Professional",
            "subcategory":"Computer Services",
            "type":"Services"
        }
    ],
    "sg:phone":"+1 352 796 5716",
    "sg:postcode":"34604",
    "sg:province":"FL",
    "sg:tags":[
        "datum"
    ],
    "wof:name":"Unlimited Images Inc",
    "wof:placetype":"venue"
},
  "geometry": {"coordinates":[-82.45907099999999,28.504723],"type":"Point"}
}