{
  "type": "Feature",
  "properties": {
    "iso:country":"US",
    "sg:address":"5068 Bottlebrush St",
    "sg:city":"Delray Beach",
    "sg:classifiers":[
        {
            "category":"Building & Trades",
            "subcategory":"Construction",
            "type":"Services"
        }
    ],
    "sg:phone":"+1 561 495 5257",
    "sg:postcode":"33484",
    "sg:province":"FL",
    "sg:tags":[
        "house"
    ],
    "wof:name":"Paradise Management & Cnstr",
    "wof:placetype":"venue"
},
  "geometry": {"coordinates":[-80.12361,26.444992],"type":"Point"}
}