{
  "type": "Feature",
  "properties": {
    "iso:country":"US",
    "sg:address":"218 SW 7th Ave",
    "sg:city":"Boynton Beach",
    "sg:classifiers":[
        {
            "category":"Banks & Credit Unions",
            "subcategory":"Financial Services",
            "type":"Services"
        }
    ],
    "sg:phone":"+1 561 374 9437",
    "sg:postcode":"33435",
    "sg:province":"FL",
    "sg:tags":[
        "investor"
    ],
    "wof:name":"Freedom Investors Team LLC",
    "wof:placetype":"venue"
},
  "geometry": {"coordinates":[-80.06770899999999,26.520853],"type":"Point"}
}