{
  "type": "Feature",
  "properties": {
    "iso:country":"US",
    "sg:address":"8305 Fairway Rd",
    "sg:city":"Sunrise",
    "sg:classifiers":[
        {
            "category":"Building & Trades",
            "subcategory":"Construction",
            "type":"Services"
        }
    ],
    "sg:phone":"+1 954 741 0221",
    "sg:postcode":"33351",
    "sg:province":"FL",
    "sg:tags":[
        "wallcoverings-installation",
        "wallpaper",
        "painting",
        "contractor"
    ],
    "wof:name":"Squires Painting Inc",
    "wof:placetype":"venue"
},
  "geometry": {"coordinates":[-80.260599,26.174078],"type":"Point"}
}