{
  "type": "Feature",
  "properties": {
    "addr:full":"6300 University Pkwy Sarasota FL 34240",
    "addr:housenumber":"6300",
    "addr:postcode":"34240",
    "addr:street":"University Pkwy",
    "iso:country":"US",
    "sg:address":"6300 University Pkwy",
    "sg:city":"Sarasota",
    "sg:classifiers":[
        {
            "category":"Professional",
            "subcategory":"Business Services",
            "type":"Services"
        }
    ],
    "sg:phone":"+1 941 907 3224",
    "sg:postcode":"34240",
    "sg:province":"FL",
    "sg:tags":[
        "labeling"
    ],
    "wof:name":"Fcci Agency, Inc",
    "wof:placetype":"venue"
},
  "geometry": {"coordinates":[-82.439313,27.387451],"type":"Point"}
}