{
  "type": "Feature",
  "properties": {
    "addr:full":"457 Wildwood Ave SW Palm Bay FL 32908",
    "addr:housenumber":"457",
    "addr:postcode":"32908",
    "addr:street":"Wildwood Ave Sw",
    "iso:country":"US",
    "sg:address":"457 Wildwood Ave SW",
    "sg:city":"Palm Bay",
    "sg:classifiers":[
        {
            "category":"Shopping",
            "subcategory":"Hobbies, Toys, & Games",
            "type":"Retail Goods"
        }
    ],
    "sg:phone":"+1 321 952 3660",
    "sg:postcode":"32908",
    "sg:province":"FL",
    "wof:name":"Ceramic Patch",
    "wof:placetype":"venue"
},
  "geometry": {"coordinates":[-80.701131,27.988173],"type":"Point"}
}