{
  "type": "Feature",
  "properties": {
    "iso:country":"US",
    "sg:address":"18318 Coral Chase Dr",
    "sg:city":"Boca Raton",
    "sg:classifiers":[
        {
            "category":"Real Estate",
            "subcategory":"Real Estate Agent",
            "type":"Services"
        }
    ],
    "sg:phone":"+1 561 218 2072",
    "sg:postcode":"33498",
    "sg:province":"FL",
    "wof:name":"M&M Holdings of South Florida",
    "wof:placetype":"venue"
},
  "geometry": {"coordinates":[-80.223607,26.402638],"type":"Point"}
}