{
  "type": "Feature",
  "properties": {
    "addr:full":"7332 Office Park Pl Melbourne FL 32940",
    "addr:housenumber":"7332",
    "addr:postcode":"32940",
    "addr:street":"Office Park Pl",
    "iso:country":"US",
    "sg:address":"7332 Office Park Pl",
    "sg:city":"Melbourne",
    "sg:classifiers":[
        {
            "category":"Health Services",
            "subcategory":"Doctor",
            "type":"Services"
        }
    ],
    "sg:phone":"+1 321 255 7740",
    "sg:postcode":"32940",
    "sg:province":"FL",
    "sg:tags":[
        "dentist"
    ],
    "wof:name":"Claudia Pryszlak DDS",
    "wof:placetype":"venue"
},
  "geometry": {"coordinates":[-80.710701,28.231252],"type":"Point"}
}