{
  "type": "Feature",
  "properties": {
    "addr:full":"4569 Wadita Ka Way West Palm Beach FL 33417",
    "addr:housenumber":"4569",
    "addr:postcode":"33417",
    "addr:street":"Wadita Ka Way",
    "iso:country":"US",
    "sg:address":"4569 Wadita Ka Way",
    "sg:city":"West Palm Beach",
    "sg:classifiers":[
        {
            "category":"Health Services",
            "subcategory":"Health Practitioner",
            "type":"Services"
        }
    ],
    "sg:phone":"+1 561 478 0964",
    "sg:postcode":"33417",
    "sg:province":"FL",
    "sg:tags":[
        "therapist",
        "physical"
    ],
    "wof:name":"Tracy P Garrett",
    "wof:placetype":"venue"
},
  "geometry": {"coordinates":[-80.113415,26.746573],"type":"Point"}
}