{
  "type": "Feature",
  "properties": {
    "addr:full":"1319 Johns Ave Lehigh Acres FL 33972",
    "addr:housenumber":"1319",
    "addr:postcode":"33972",
    "addr:street":"Johns Ave",
    "iso:country":"US",
    "sg:address":"1319 Johns Ave",
    "sg:city":"Lehigh Acres",
    "sg:classifiers":[
        {
            "category":"Freight",
            "type":"Transportation"
        }
    ],
    "sg:phone":"+1 239 369 6470",
    "sg:postcode":"33972",
    "sg:province":"FL",
    "sg:tags":[
        "operator",
        "local",
        "trucking"
    ],
    "wof:name":"Alcyn Trucking Inc",
    "wof:placetype":"venue"
},
  "geometry": {"coordinates":[-81.580592,26.650923],"type":"Point"}
}