{
  "type": "Feature",
  "properties": {
    "addr:full":"605 Yorktown Dr Leesburg FL 34748",
    "addr:housenumber":"605",
    "addr:postcode":"34748",
    "addr:street":"Yorktown Dr",
    "iso:country":"US",
    "sg:address":"605 Yorktown Dr",
    "sg:city":"Leesburg",
    "sg:classifiers":[
        {
            "category":"Professional",
            "subcategory":"Employment Agencies",
            "type":"Services"
        }
    ],
    "sg:phone":"+1 352 787 7004",
    "sg:postcode":"34748",
    "sg:province":"FL",
    "sg:tags":[
        "modeling"
    ],
    "wof:name":"Stella's Talent Agency",
    "wof:placetype":"venue"
},
  "geometry": {"coordinates":[-81.85710899999999,28.821076],"type":"Point"}
}