{
  "type": "Feature",
  "properties": {
    "addr:full":"790 Dunlawton Ave Daytona Beach FL 32127",
    "addr:housenumber":"790",
    "addr:postcode":"32127",
    "addr:street":"Dunlawton Ave",
    "iso:country":"US",
    "sg:address":"790 Dunlawton Ave",
    "sg:city":"Daytona Beach",
    "sg:classifiers":[
        {
            "category":"Recreation",
            "type":"Entertainment"
        }
    ],
    "sg:phone":"+1 386 763 0223",
    "sg:postcode":"32127",
    "sg:province":"FL",
    "wof:name":"Healing Sprit Thrputic Massage",
    "wof:placetype":"venue"
},
  "geometry": {"coordinates":[-80.997463,29.138194],"type":"Point"}
}