{
  "type": "Feature",
  "properties": {
    "iso:country":"US",
    "sg:address":"1200 7th Ave N",
    "sg:city":"Saint Petersburg",
    "sg:phone":"+1 727 825 1766",
    "sg:postcode":"33705",
    "sg:province":"FL",
    "sg:tags":[
        "equipment",
        "commercial"
    ],
    "wof:name":"Mediq Equipment & Maintenance",
    "wof:placetype":"venue"
},
  "geometry": {"coordinates":[-82.65173,27.779328],"type":"Point"}
}