{
  "type": "Feature",
  "properties": {
    "addr:full":"112 Debarry Ave Orange Park FL 32073",
    "addr:housenumber":"112",
    "addr:postcode":"32073",
    "addr:street":"Debarry Ave",
    "iso:country":"US",
    "sg:address":"112 Debarry Ave",
    "sg:city":"Orange Park",
    "sg:classifiers":[
        {
            "category":"Wholesale",
            "subcategory":"Sporting Goods",
            "type":"Manufacturing & Wholesale Goods"
        }
    ],
    "sg:phone":"+1 904 264 4744",
    "sg:postcode":"32073",
    "sg:province":"FL",
    "sg:tags":[
        "s"
    ],
    "wof:name":"Scuba Tiger LLC",
    "wof:placetype":"venue"
},
  "geometry": {"coordinates":[-81.72410600000001,30.185404],"type":"Point"}
}