{
  "type": "Feature",
  "properties": {
    "addr:full":"12917 Water Point Blvd Windermere FL 34786",
    "addr:housenumber":"12917",
    "addr:postcode":"34786",
    "addr:street":"Water Point Blvd",
    "iso:country":"US",
    "sg:address":"12917 Water Point Blvd",
    "sg:city":"Windermere",
    "sg:classifiers":[
        {
            "category":"Professional",
            "subcategory":"Advertising",
            "type":"Services"
        }
    ],
    "sg:phone":"+1 407 909 1286",
    "sg:postcode":"34786",
    "sg:province":"FL",
    "sg:tags":[
        "mailing",
        "shipping"
    ],
    "wof:name":"G S Marketing",
    "wof:placetype":"venue"
},
  "geometry": {"coordinates":[-81.576257,28.515239],"type":"Point"}
}