{
  "type": "Feature",
  "properties": {
    "addr:full":"1401 W Gore St Orlando FL 32805",
    "addr:housenumber":"1401",
    "addr:postcode":"32805",
    "addr:street":"W Gore St",
    "iso:country":"US",
    "sg:address":"1401 W Gore St",
    "sg:city":"Orlando",
    "sg:classifiers":[
        {
            "category":"Wholesale",
            "subcategory":"Groceries",
            "type":"Manufacturing & Wholesale Goods"
        }
    ],
    "sg:phone":"+1 407 236 0507",
    "sg:postcode":"32805",
    "sg:province":"FL",
    "sg:tags":[
        "tea",
        "coffee"
    ],
    "wof:name":"Orlando Coffee Roaster",
    "wof:placetype":"venue"
},
  "geometry": {"coordinates":[-81.397228,28.531192],"type":"Point"}
}