{
  "type": "Feature",
  "properties": {
    "addr:full":"4920 NW 54th Ct Tamarac FL 33319",
    "addr:housenumber":"4920",
    "addr:postcode":"33319",
    "addr:street":"Nw 54Th Ct",
    "iso:country":"US",
    "sg:address":"4920 NW 54th Ct",
    "sg:city":"Tamarac",
    "sg:classifiers":[
        {
            "category":"Home & Garden",
            "subcategory":"Home Furnishings",
            "type":"Retail Goods"
        }
    ],
    "sg:phone":"+1 954 486 8456",
    "sg:postcode":"33319",
    "sg:province":"FL",
    "sg:tags":[
        "pottery"
    ],
    "wof:name":"Ruby's Pottery",
    "wof:placetype":"venue"
},
  "geometry": {"coordinates":[-80.216887,26.191609],"type":"Point"}
}