{
  "type": "Feature",
  "properties": {
    "addr:full":"1690 Alcazar Way S Saint Petersburg FL 33712",
    "addr:housenumber":"1690",
    "addr:postcode":"33712",
    "addr:street":"Alcazar Way S",
    "iso:country":"US",
    "sg:address":"1690 Alcazar Way S",
    "sg:city":"Saint Petersburg",
    "sg:classifiers":[
        {
            "category":"Shopping",
            "subcategory":"Music",
            "type":"Retail Goods"
        }
    ],
    "sg:phone":"+1 727 867 6195",
    "sg:postcode":"33712",
    "sg:province":"FL",
    "wof:name":"Fat Toe Records Inc",
    "wof:placetype":"venue"
},
  "geometry": {"coordinates":[-82.656841,27.72123],"type":"Point"}
}