{
  "type": "Feature",
  "properties": {
    "iso:country":"US",
    "sg:address":"850 Teague Trl",
    "sg:city":"Lady Lake",
    "sg:classifiers":[
        {
            "category":"Government",
            "subcategory":"Post Office",
            "type":"Public Place"
        }
    ],
    "sg:phone":"+1 352 000 1111",
    "sg:postcode":"32159",
    "sg:province":"FL",
    "wof:name":"US Post Office",
    "wof:placetype":"venue"
},
  "geometry": {"coordinates":[-81.92324499999999,28.915919],"type":"Point"}
}