{
  "type": "Feature",
  "properties": {
    "iso:country":"US",
    "sg:address":"400 N US Hwy 1",
    "sg:city":"Ormond Beach",
    "sg:classifiers":[
        {
            "category":"Building & Trades",
            "subcategory":"Plumbing",
            "type":"Services"
        }
    ],
    "sg:phone":"+1 386 734 8064",
    "sg:postcode":"32174",
    "sg:province":"FL",
    "sg:tags":[
        "conditioning",
        "air",
        "system",
        "contractor"
    ],
    "sg:website":"www.totalcomfortfl.com",
    "wof:name":"Total Comfort Heat & Air Cond",
    "wof:placetype":"venue"
},
  "geometry": {"coordinates":[-81.069581,29.290589],"type":"Point"}
}