{
  "type": "Feature",
  "properties": {
    "iso:country":"US",
    "sg:address":"2002 S 31st St",
    "sg:city":"Fort Pierce",
    "sg:classifiers":[
        {
            "category":"Building & Trades",
            "subcategory":"Construction",
            "type":"Services"
        }
    ],
    "sg:phone":"+1 772 465 7477",
    "sg:postcode":"34947",
    "sg:province":"FL",
    "sg:tags":[
        "house"
    ],
    "wof:name":"Tom Black Construction",
    "wof:placetype":"venue"
},
  "geometry": {"coordinates":[-80.35633900000001,27.428461],"type":"Point"}
}