{
  "type": "Feature",
  "properties": {
    "iso:country":"US",
    "sg:address":"1590 NW 10th Ave",
    "sg:city":"Boca Raton",
    "sg:classifiers":[
        {
            "category":"Health Services",
            "subcategory":"Doctor",
            "type":"Services"
        }
    ],
    "sg:phone":"+1 561 395 3503",
    "sg:postcode":"33486",
    "sg:province":"FL",
    "sg:tags":[
        "dentist"
    ],
    "wof:name":"Robert E Lane DDS",
    "wof:placetype":"venue"
},
  "geometry": {"coordinates":[-80.106055,26.364914],"type":"Point"}
}