{
  "type": "Feature",
  "properties": {
    "iso:country":"US",
    "sg:address":"W Volusia Regional Sho",
    "sg:city":"Deland",
    "sg:classifiers":[
        {
            "category":"Shopping",
            "subcategory":"Jewelry",
            "type":"Retail Goods"
        }
    ],
    "sg:phone":"+1 386 738 2113",
    "sg:postcode":"32720",
    "sg:province":"FL",
    "sg:website":"www.kay.com",
    "wof:name":"Kay Jewelers",
    "wof:placetype":"venue"
},
  "geometry": {"coordinates":[-81.329399,29.027901],"type":"Point"}
}