{
  "type": "Feature",
  "properties": {
    "addr:full":"11503 Ayala Rd Jacksonville FL 32258",
    "addr:housenumber":"11503",
    "addr:postcode":"32258",
    "addr:street":"Ayala Rd",
    "iso:country":"US",
    "sg:address":"11503 Ayala Rd",
    "sg:city":"Jacksonville",
    "sg:classifiers":[
        {
            "category":"Professional",
            "type":"Services"
        }
    ],
    "sg:phone":"+1 904 262 7891",
    "sg:postcode":"32258",
    "sg:province":"FL",
    "sg:tags":[
        "establishment"
    ],
    "wof:name":"C J Sak",
    "wof:placetype":"venue"
},
  "geometry": {"coordinates":[-81.549869,30.163505],"type":"Point"}
}