{
  "type": "Feature",
  "properties": {
    "iso:country":"US",
    "sg:address":"6340 W Indiantown Rd",
    "sg:city":"Jupiter",
    "sg:classifiers":[
        {
            "category":"Real Estate",
            "subcategory":"Real Estate Agent",
            "type":"Services"
        }
    ],
    "sg:phone":"+1 561 575 3586",
    "sg:postcode":"33458",
    "sg:province":"FL",
    "wof:name":"Regency Realty",
    "wof:placetype":"venue"
},
  "geometry": {"coordinates":[-80.13255100000001,26.934465],"type":"Point"}
}