{
  "type": "Feature",
  "properties": {
    "addr:full":"96000 Overseas Hwy Key Largo FL 33037",
    "addr:housenumber":"96000",
    "addr:postcode":"33037",
    "addr:street":"Overseas Hwy",
    "iso:country":"US",
    "sg:address":"96000 Overseas Hwy",
    "sg:city":"Key Largo",
    "sg:classifiers":[
        {
            "category":"Insurance",
            "subcategory":"Insurance Agent",
            "type":"Services"
        }
    ],
    "sg:phone":"+1 305 852 5604",
    "sg:postcode":"33037",
    "sg:province":"FL",
    "wof:name":"Scs & Associates Inc",
    "wof:placetype":"venue"
},
  "geometry": {"coordinates":[-80.484144,25.05211],"type":"Point"}
}