{
  "type": "Feature",
  "properties": {
    "addr:full":"254 Vilano Rd St Augustine FL 32084",
    "addr:housenumber":"254",
    "addr:postcode":"32084",
    "addr:street":"Vilano Rd St",
    "iso:country":"US",
    "sg:address":"254 Vilano Rd",
    "sg:city":"St Augustine",
    "sg:classifiers":[
        {
            "category":"Restaurant",
            "type":"Food & Drink"
        }
    ],
    "sg:phone":"+1 904 824 6844",
    "sg:postcode":"32084",
    "sg:province":"FL",
    "wof:name":"Pointe",
    "wof:placetype":"venue"
},
  "geometry": {"coordinates":[-81.297808,29.916683],"type":"Point"}
}