{
  "type": "Feature",
  "properties": {
    "addr:full":"12401 SW 134th Ct Suite 12 Miami FL 33186",
    "addr:housenumber":"12401;12",
    "addr:postcode":"33186",
    "addr:street":"Sw 134Th Ct Suite",
    "iso:country":"US",
    "sg:address":"12401 SW 134th Ct Suite 12",
    "sg:city":"Miami",
    "sg:phone":"+1 305 379 3600",
    "sg:postcode":"33186",
    "sg:province":"FL",
    "wof:name":"A Deposition Reporter",
    "wof:placetype":"venue"
},
  "geometry": {"coordinates":[-80.41239899999999,25.652361],"type":"Point"}
}