{
  "type": "Feature",
  "properties": {
    "iso:country":"US",
    "sg:address":"9172 Blind Pass Rd",
    "sg:city":"Saint Petersburg",
    "sg:classifiers":[
        {
            "category":"Wholesale",
            "subcategory":"Machinery & Supplies",
            "type":"Manufacturing & Wholesale Goods"
        }
    ],
    "sg:phone":"+1 727 363 3166",
    "sg:postcode":"33706",
    "sg:province":"FL",
    "sg:tags":[
        "equipment",
        "grocery",
        "establishment"
    ],
    "wof:name":"Helton Enterprises Inc",
    "wof:placetype":"venue"
},
  "geometry": {"coordinates":[-82.757499,27.753269],"type":"Point"}
}