{
  "type": "Feature",
  "properties": {
    "iso:country":"US",
    "sg:address":"3092 Gulf Breeze Pkwy",
    "sg:city":"Gulf Breeze",
    "sg:classifiers":[
        {
            "category":"Wholesale",
            "subcategory":"Tobacco Products",
            "type":"Manufacturing & Wholesale Goods"
        }
    ],
    "sg:phone":"+1 850 932 4366",
    "sg:postcode":"32563",
    "sg:province":"FL",
    "sg:tags":[
        "cigarette",
        "cigar",
        "dealer"
    ],
    "wof:name":"Tobacco Place",
    "wof:placetype":"venue"
},
  "geometry": {"coordinates":[-87.090948,30.386203],"type":"Point"}
}