{
  "type": "Feature",
  "properties": {
    "iso:country":"US",
    "sg:address":"3573 Enterprise Ave",
    "sg:city":"Naples",
    "sg:classifiers":[
        {
            "category":"Home & Garden",
            "subcategory":"Furniture",
            "type":"Retail Goods"
        }
    ],
    "sg:phone":"+1 239 304 0800",
    "sg:postcode":"34104",
    "sg:province":"FL",
    "sg:tags":[
        "top",
        "counter"
    ],
    "wof:name":"All Professional Glass",
    "wof:placetype":"venue"
},
  "geometry": {"coordinates":[-81.76156,26.160733],"type":"Point"}
}