{
  "type": "Feature",
  "properties": {
    "addr:full":"11120 S Cleveland Ave Fort Myers FL 33907",
    "addr:housenumber":"11120",
    "addr:postcode":"33907",
    "addr:street":"S Cleveland Ave",
    "iso:country":"US",
    "sg:address":"11120 S Cleveland Ave",
    "sg:city":"Fort Myers",
    "sg:classifiers":[
        {
            "category":"Home & Garden",
            "subcategory":"Furniture",
            "type":"Retail Goods"
        }
    ],
    "sg:phone":"+1 239 939 7656",
    "sg:postcode":"33907",
    "sg:province":"FL",
    "sg:tags":[
        "store"
    ],
    "sg:website":"www.thepatiocorner.com",
    "wof:name":"Patio Corner In Ft Myers",
    "wof:placetype":"venue"
},
  "geometry": {"coordinates":[-81.872101,26.577999],"type":"Point"}
}