{
  "type": "Feature",
  "properties": {
    "addr:full":"2932 Bardahl Ct Deltona FL 32738",
    "addr:housenumber":"2932",
    "addr:postcode":"32738",
    "addr:street":"Bardahl Ct",
    "iso:country":"US",
    "sg:address":"2932 Bardahl Ct",
    "sg:city":"Deltona",
    "sg:classifiers":[
        {
            "category":"Personal",
            "type":"Services"
        },
        {
            "category":"Professional",
            "subcategory":"Art Services",
            "type":"Services"
        }
    ],
    "sg:phone":"+1 386 747 6846",
    "sg:postcode":"32738",
    "sg:province":"FL",
    "sg:tags":[
        "photography",
        "videography",
        "wedding"
    ],
    "wof:name":"Pictures Of You Photography",
    "wof:placetype":"venue"
},
  "geometry": {"coordinates":[-81.183668,28.882159],"type":"Point"}
}