{
  "type": "Feature",
  "properties": {
    "addr:full":"28100 Dovewood Ct Bonita Springs FL 34135",
    "addr:housenumber":"28100",
    "addr:postcode":"34135",
    "addr:street":"Dovewood Ct",
    "iso:country":"US",
    "sg:address":"28100 Dovewood Ct",
    "sg:city":"Bonita Springs",
    "sg:classifiers":[
        {
            "category":"Building & Trades",
            "subcategory":"Cleaning & Sanitation",
            "type":"Services"
        }
    ],
    "sg:phone":"+1 239 405 0725",
    "sg:postcode":"34135",
    "sg:province":"FL",
    "sg:tags":[
        "janitor"
    ],
    "wof:name":"Steven Sanchez Cleaning Svc",
    "wof:placetype":"venue"
},
  "geometry": {"coordinates":[-81.78443900000001,26.330698],"type":"Point"}
}