{
  "type": "Feature",
  "properties": {
    "addr:full":"12991 NW 1st St Hollywood FL 33028",
    "addr:housenumber":"12991",
    "addr:postcode":"33028",
    "addr:street":"Nw 1St St",
    "iso:country":"US",
    "sg:address":"12991 NW 1st St",
    "sg:city":"Hollywood",
    "sg:classifiers":[
        {
            "category":"Professional",
            "type":"Services"
        }
    ],
    "sg:phone":"+1 954 442 2441",
    "sg:postcode":"33028",
    "sg:province":"FL",
    "wof:name":"In Gods Co",
    "wof:placetype":"venue"
},
  "geometry": {"coordinates":[-80.323047,26.00838],"type":"Point"}
}