{
  "type": "Feature",
  "properties": {
    "iso:country":"US",
    "sg:address":"56 N Halifax Dr",
    "sg:city":"Ormond Beach",
    "sg:classifiers":[
        {
            "category":"Organizations",
            "subcategory":"Religious Organization",
            "type":"Services"
        }
    ],
    "sg:phone":"+1 386 677 6172",
    "sg:postcode":"32176",
    "sg:province":"FL",
    "sg:tags":[
        "church"
    ],
    "sg:website":"www.uuormond.org",
    "wof:name":"Unitarian Universalist Society",
    "wof:placetype":"venue"
},
  "geometry": {"coordinates":[-81.047461,29.293996],"type":"Point"}
}