{
  "type": "Feature",
  "properties": {
    "iso:country":"US",
    "sg:address":"4017 Sawyer Ct",
    "sg:city":"Sarasota",
    "sg:classifiers":[
        {
            "category":"Autos & Motor Vehicles",
            "subcategory":"Auto Supplies",
            "type":"Retail Goods"
        }
    ],
    "sg:phone":"+1 941 924 2604",
    "sg:postcode":"34233",
    "sg:province":"FL",
    "sg:tags":[
        "automobile",
        "top",
        "upholstery",
        "covers",
        "seat"
    ],
    "wof:name":"Don's Custom & Vintage At Hoyt's",
    "wof:placetype":"venue"
},
  "geometry": {"coordinates":[-82.487904,27.296026],"type":"Point"}
}