{
  "type": "Feature",
  "properties": {
    "addr:full":"1338 S Killian Dr Lake Park FL 33403",
    "addr:housenumber":"1338",
    "addr:postcode":"33403",
    "addr:street":"S Killian Dr",
    "iso:country":"US",
    "sg:address":"1338 S Killian Dr",
    "sg:city":"Lake Park",
    "sg:classifiers":[
        {
            "category":"Wholesale",
            "subcategory":"Machinery & Supplies",
            "type":"Manufacturing & Wholesale Goods"
        }
    ],
    "sg:phone":"+1 561 863 9343",
    "sg:postcode":"33403",
    "sg:province":"FL",
    "sg:tags":[
        "equipment",
        "system",
        "vacuum"
    ],
    "wof:name":"San-Tek Enterprises Inc",
    "wof:placetype":"venue"
},
  "geometry": {"coordinates":[-80.081287,26.804292],"type":"Point"}
}