{
  "type": "Feature",
  "properties": {
    "iso:country":"US",
    "sg:address":"5633 SW 26th St",
    "sg:city":"Hollywood",
    "sg:classifiers":[
        {
            "category":"Building & Trades",
            "subcategory":"Construction",
            "type":"Services"
        }
    ],
    "sg:phone":"+1 954 987 4968",
    "sg:postcode":"33023",
    "sg:province":"FL",
    "sg:tags":[
        "contractor"
    ],
    "wof:name":"Chivers James",
    "wof:placetype":"venue"
},
  "geometry": {"coordinates":[-80.20201,25.986842],"type":"Point"}
}