{
  "type": "Feature",
  "properties": {
    "iso:country":"US",
    "sg:address":"705 1st St N",
    "sg:city":"Indian Rocks Bch",
    "sg:classifiers":[
        {
            "category":"Shopping",
            "type":"Retail Goods"
        }
    ],
    "sg:phone":"+1 727 593 7821",
    "sg:postcode":"33785",
    "sg:province":"FL",
    "sg:tags":[
        "wheel",
        "chair",
        "scooter"
    ],
    "wof:name":"Rent Me",
    "wof:placetype":"venue"
},
  "geometry": {"coordinates":[-82.84907800000001,27.887783],"type":"Point"}
}