{
  "type": "Feature",
  "properties": {
    "iso:country":"US",
    "sg:address":"3663 Webber St",
    "sg:city":"Sarasota",
    "sg:classifiers":[
        {
            "category":"Shopping",
            "subcategory":"Clothing, Apparel, & Fashions",
            "type":"Retail Goods"
        }
    ],
    "sg:phone":"+1 941 921 1944",
    "sg:postcode":"34232",
    "sg:province":"FL",
    "wof:name":"My Best Friends Closet Etc",
    "wof:placetype":"venue"
},
  "geometry": {"coordinates":[-82.495073,27.308339],"type":"Point"}
}