{
  "type": "Feature",
  "properties": {
    "iso:country":"US",
    "sg:address":"3621 NE 1st Ct",
    "sg:city":"Miami",
    "sg:classifiers":[
        {
            "category":"Shopping",
            "subcategory":"Stationery & Office Supplies",
            "type":"Retail Goods"
        }
    ],
    "sg:phone":"+1 305 576 7550",
    "sg:postcode":"33137",
    "sg:province":"FL",
    "sg:tags":[
        "equipment"
    ],
    "sg:website":"www.officedimensionsinc.com",
    "wof:name":"Office Dimensions Inc",
    "wof:placetype":"venue"
},
  "geometry": {"coordinates":[-80.19199399999999,25.810722],"type":"Point"}
}