{
  "type": "Feature",
  "properties": {
    "addr:full":"444 Brickell Ave Miami FL 33131",
    "addr:housenumber":"444",
    "addr:postcode":"33131",
    "addr:street":"Brickell Ave",
    "iso:country":"US",
    "sg:address":"444 Brickell Ave",
    "sg:city":"Miami",
    "sg:classifiers":[
        {
            "category":"Professional",
            "subcategory":"Art Services",
            "type":"Services"
        }
    ],
    "sg:phone":"+1 305 992 7946",
    "sg:postcode":"33131",
    "sg:province":"FL",
    "sg:tags":[
        "photographer"
    ],
    "sg:website":"www.justateaseportraits.com",
    "wof:name":"Just A Tease Portraits",
    "wof:placetype":"venue"
},
  "geometry": {"coordinates":[-80.190004,25.769086],"type":"Point"}
}