{
  "type": "Feature",
  "properties": {
    "iso:country":"US",
    "sg:address":"1580 Bay Dr",
    "sg:city":"Miami Beach",
    "sg:classifiers":[
        {
            "category":"Ferry",
            "type":"Transportation"
        }
    ],
    "sg:phone":"+1 305 861 0709",
    "sg:postcode":"33141",
    "sg:province":"FL",
    "sg:tags":[
        "boat"
    ],
    "wof:name":"Fast Cats Ferry Svc",
    "wof:placetype":"venue"
},
  "geometry": {"coordinates":[-80.134056,25.851045],"type":"Point"}
}