{
  "type": "Feature",
  "properties": {
    "addr:full":"16681 SW 78th Ave Palmetto Bay FL 33157",
    "addr:housenumber":"16681",
    "addr:postcode":"33157",
    "addr:street":"Sw 78Th Ave",
    "iso:country":"US",
    "sg:address":"16681 SW 78th Ave",
    "sg:city":"Palmetto Bay",
    "sg:classifiers":[
        {
            "category":"Professional",
            "type":"Services"
        }
    ],
    "sg:phone":"+1 305 971 2470",
    "sg:postcode":"33157",
    "sg:province":"FL",
    "sg:tags":[
        "establishment"
    ],
    "wof:name":"G & G Interterra Inc",
    "wof:placetype":"venue"
},
  "geometry": {"coordinates":[-80.318456,25.616459],"type":"Point"}
}