{
  "type": "Feature",
  "properties": {
    "addr:full":"10987 SE 95th Avenue Rd Belleview FL 34420",
    "addr:housenumber":"10987",
    "addr:postcode":"34420",
    "addr:street":"Se 95Th Avenue Rd",
    "iso:country":"US",
    "sg:address":"10987 SE 95th Avenue Rd",
    "sg:city":"Belleview",
    "sg:classifiers":[
        {
            "category":"Shopping",
            "subcategory":"Discount & Variety Stores",
            "type":"Retail Goods"
        }
    ],
    "sg:phone":"+1 352 687 2687",
    "sg:postcode":"34420",
    "sg:province":"FL",
    "sg:tags":[
        "merchandise",
        "general"
    ],
    "wof:name":"P H Jones Opportunities Unltd",
    "wof:placetype":"venue"
},
  "geometry": {"coordinates":[-81.99572499999999,29.062234],"type":"Point"}
}