{
  "type": "Feature",
  "properties": {
    "iso:country":"US",
    "sg:address":"1350 S Washington Ave",
    "sg:city":"Titusville",
    "sg:classifiers":[
        {
            "category":"Autos & Motor Vehicles",
            "subcategory":"Automobile Sales",
            "type":"Retail Goods"
        }
    ],
    "sg:phone":"+1 321 269 2011",
    "sg:postcode":"32780",
    "sg:province":"FL",
    "wof:name":"Norris Ron Honda-Buick-Gmc",
    "wof:placetype":"venue"
},
  "geometry": {"coordinates":[-80.806878,28.598736],"type":"Point"}
}