{
  "type": "Feature",
  "properties": {
    "iso:country":"US",
    "sg:address":"1616 NE 205th Ter",
    "sg:city":"Miami",
    "sg:classifiers":[
        {
            "category":"Wholesale",
            "subcategory":"Painting Supplies",
            "type":"Manufacturing & Wholesale Goods"
        },
        {
            "category":"Home & Garden",
            "subcategory":"Building Materials",
            "type":"Retail Goods"
        },
        {
            "category":"Building & Trades",
            "subcategory":"Construction",
            "type":"Services"
        }
    ],
    "sg:phone":"+1 305 653 1712",
    "sg:postcode":"33179",
    "sg:province":"FL",
    "sg:tags":[
        "wall",
        "wallcoverings-installation",
        "wallpaper",
        "coating",
        "wallcoverings"
    ],
    "sg:website":"http://www.brambiers.com",
    "wof:name":"Brambier's Windows & Walls",
    "wof:placetype":"venue"
},
  "geometry": {"coordinates":[-80.169949,25.964187],"type":"Point"}
}