{
  "type": "Feature",
  "properties": {
    "addr:full":"6584 50th Ave N St Petersburg FL 33709",
    "addr:housenumber":"6584",
    "addr:postcode":"33709",
    "addr:street":"50Th Ave N",
    "iso:country":"US",
    "sg:address":"6584 50th Ave N",
    "sg:city":"St Petersburg",
    "sg:classifiers":[
        {
            "category":"Autos & Motor Vehicles",
            "subcategory":"Auto Supplies",
            "type":"Retail Goods"
        }
    ],
    "sg:phone":"+1 727 546 3541",
    "sg:postcode":"33709",
    "sg:province":"FL",
    "sg:tags":[
        "automotive",
        "parts",
        "equipment",
        "race",
        "automobile",
        "fuel",
        "racing",
        "car"
    ],
    "wof:name":"Hole Shot Engineering Inc",
    "wof:placetype":"venue"
},
  "geometry": {"coordinates":[-82.727872,27.817215],"type":"Point"}
}