{
  "type": "Feature",
  "properties": {
    "addr:full":"1995 NE 150th St Ste 107 North Miami FL 33181",
    "addr:housenumber":"1995",
    "addr:postcode":"33181",
    "addr:street":"Ne 150Th St Ste 107",
    "iso:country":"US",
    "sg:address":"1995 NE 150th St Ste 107",
    "sg:city":"North Miami",
    "sg:classifiers":[
        {
            "category":"Communications",
            "subcategory":"Newspaper",
            "type":"Services"
        }
    ],
    "sg:phone":"+1 305 945 7403",
    "sg:postcode":"33181",
    "sg:province":"FL",
    "sg:tags":[
        "print",
        "medium"
    ],
    "wof:name":"Caribbean Resort Directory",
    "wof:placetype":"venue"
},
  "geometry": {"coordinates":[-80.159599,25.914101],"type":"Point"}
}