{
  "type": "Feature",
  "properties": {
    "iso:country":"US",
    "sg:address":"1139 NE Krome Ter",
    "sg:city":"Homestead",
    "sg:classifiers":[
        {
            "category":"Health Services",
            "subcategory":"Doctor",
            "type":"Services"
        }
    ],
    "sg:phone":"+1 305 245 5070",
    "sg:postcode":"33030",
    "sg:province":"FL",
    "sg:tags":[
        "medical"
    ],
    "wof:name":"Coral Reef Medical Associates",
    "wof:placetype":"venue"
},
  "geometry": {"coordinates":[-80.475784,25.481384],"type":"Point"}
}