{
  "type": "Feature",
  "properties": {
    "addr:full":"355 W Main St Apopka FL 32712",
    "addr:housenumber":"355",
    "addr:postcode":"32712",
    "addr:street":"W Main St",
    "iso:country":"US",
    "sg:address":"355 W Main St",
    "sg:city":"Apopka",
    "sg:classifiers":[
        {
            "category":"Retail",
            "subcategory":"Repair Shop",
            "type":"Services"
        }
    ],
    "sg:phone":"+1 407 880 0606",
    "sg:postcode":"32712",
    "sg:province":"FL",
    "wof:name":"Motorcycles of Apopka Inc",
    "wof:placetype":"venue"
},
  "geometry": {"coordinates":[-81.518792,28.677334],"type":"Point"}
}