{
  "type": "Feature",
  "properties": {
    "iso:country":"US",
    "sg:address":"3333 Timberwood Cir",
    "sg:city":"Naples",
    "sg:classifiers":[
        {
            "category":"Shopping",
            "subcategory":"Crafts & Fabrics",
            "type":"Retail Goods"
        }
    ],
    "sg:phone":"+1 239 434 2610",
    "sg:postcode":"34105",
    "sg:province":"FL",
    "sg:tags":[
        "material",
        "needlework"
    ],
    "wof:name":"Jane Nichols",
    "wof:placetype":"venue"
},
  "geometry": {"coordinates":[-81.76661900000001,26.202285],"type":"Point"}
}