{
  "type": "Feature",
  "properties": {
    "iso:country":"US",
    "sg:address":"810 Columbia St",
    "sg:city":"Orlando",
    "sg:classifiers":[
        {
            "category":"Real Estate",
            "subcategory":"Real Estate Agent",
            "type":"Services"
        }
    ],
    "sg:phone":"+1 407 380 6082",
    "sg:postcode":"32805",
    "sg:province":"FL",
    "sg:tags":[
        "periodical"
    ],
    "wof:name":"Alixander Group",
    "wof:placetype":"venue"
},
  "geometry": {"coordinates":[-81.38985099999999,28.527385],"type":"Point"}
}