{
  "type": "Feature",
  "properties": {
    "addr:full":"8897 Fontainebleau Blvd Miami FL 33172",
    "addr:housenumber":"8897",
    "addr:postcode":"33172",
    "addr:street":"Fontainebleau Blvd",
    "iso:country":"US",
    "sg:address":"8897 Fontainebleau Blvd",
    "sg:city":"Miami",
    "sg:classifiers":[
        {
            "category":"Professional",
            "subcategory":"Management & Consulting",
            "type":"Services"
        }
    ],
    "sg:phone":"+1 786 853 9913",
    "sg:postcode":"33172",
    "sg:province":"FL",
    "sg:tags":[
        "consultant"
    ],
    "wof:name":"Emperor Maritime Corp",
    "wof:placetype":"venue"
},
  "geometry": {"coordinates":[-80.342412,25.773715],"type":"Point"}
}