{
  "type": "Feature",
  "properties": {
    "iso:country":"US",
    "sg:address":"2190 State Hwy 70",
    "sg:city":"Okeechobee",
    "sg:classifiers":[
        {
            "category":"Retail",
            "subcategory":"Auto Rental",
            "type":"Services"
        }
    ],
    "sg:phone":"+1 863 467 8344",
    "sg:postcode":"34972",
    "sg:province":"FL",
    "sg:tags":[
        "renting",
        "truck",
        "leasing"
    ],
    "wof:name":"U-Haul Co",
    "wof:placetype":"venue"
},
  "geometry": {"coordinates":[-80.850836,27.243441],"type":"Point"}
}