{
  "type": "Feature",
  "properties": {
    "iso:country":"US",
    "sg:address":"1149 S Volusia Ave",
    "sg:city":"Orange City",
    "sg:classifiers":[
        {
            "category":"Shopping",
            "type":"Retail Goods"
        }
    ],
    "sg:phone":"+1 386 774 4474",
    "sg:postcode":"32763",
    "sg:province":"FL",
    "sg:tags":[
        "pet",
        "boarding/pet",
        "animal",
        "merchandise",
        "sitting"
    ],
    "wof:name":"Clip N Dip",
    "wof:placetype":"venue"
},
  "geometry": {"coordinates":[-81.298698,28.935301],"type":"Point"}
}