{
  "type": "Feature",
  "properties": {
    "iso:country":"US",
    "sg:address":"6348 Walk Cir",
    "sg:city":"Boca Raton",
    "sg:classifiers":[
        {
            "category":"Wholesale",
            "subcategory":"Non-durable Goods",
            "type":"Manufacturing & Wholesale Goods"
        }
    ],
    "sg:phone":"+1 561 750 2449",
    "sg:postcode":"33433",
    "sg:province":"FL",
    "wof:name":"Usabraz Trading Corp",
    "wof:placetype":"venue"
},
  "geometry": {"coordinates":[-80.14272099999999,26.351461],"type":"Point"}
}