{
  "type": "Feature",
  "properties": {
    "addr:full":"5007 49th St N Saint Petersburg FL 33709",
    "addr:housenumber":"5007",
    "addr:postcode":"33709",
    "addr:street":"49Th St N",
    "iso:country":"US",
    "sg:address":"5007 49th St N",
    "sg:city":"Saint Petersburg",
    "sg:classifiers":[
        {
            "category":"Shopping",
            "subcategory":"Clothing, Apparel, & Fashions",
            "type":"Retail Goods"
        }
    ],
    "sg:phone":"+1 727 323 0363",
    "sg:postcode":"33709",
    "sg:province":"FL",
    "wof:name":"Yes Fashions",
    "wof:placetype":"venue"
},
  "geometry": {"coordinates":[-82.699898,27.819077],"type":"Point"}
}