{
  "type": "Feature",
  "properties": {
    "iso:country":"US",
    "sg:address":"4300 Clarcona Ocoee Rd",
    "sg:city":"Orlando",
    "sg:classifiers":[
        {
            "category":"Health Services",
            "subcategory":"Doctor",
            "type":"Services"
        }
    ],
    "sg:phone":"+1 407 292 0292",
    "sg:postcode":"32810",
    "sg:province":"FL",
    "sg:tags":[
        "medicine",
        "physician",
        "practice",
        "surgeons",
        "family"
    ],
    "wof:name":"Rosemont Family Medical Center",
    "wof:placetype":"venue"
},
  "geometry": {"coordinates":[-81.43311300000001,28.6127],"type":"Point"}
}