{
  "type": "Feature",
  "properties": {
    "iso:country":"US",
    "sg:address":"19511 SW 118th Ave",
    "sg:city":"Miami",
    "sg:classifiers":[
        {
            "category":"Manufacturing",
            "subcategory":"Apparel",
            "type":"Manufacturing & Wholesale Goods"
        }
    ],
    "sg:phone":"+1 305 234 9486",
    "sg:postcode":"33177",
    "sg:province":"FL",
    "sg:tags":[
        "retail",
        "embroidery"
    ],
    "wof:name":"T Solutions",
    "wof:placetype":"venue"
},
  "geometry": {"coordinates":[-80.382745,25.585651],"type":"Point"}
}