{
  "type": "Feature",
  "properties": {
    "iso:country":"US",
    "sg:address":"1215 S Eustis St",
    "sg:city":"Eustis",
    "sg:classifiers":[
        {
            "category":"Place Of Worship",
            "subcategory":"Church",
            "type":"Public Place"
        },
        {
            "category":"Place Of Worship",
            "type":"Public Place"
        },
        {
            "category":"Organizations",
            "subcategory":"Religious Organization",
            "type":"Services"
        }
    ],
    "sg:phone":"+1 352 589 1558",
    "sg:postcode":"32726",
    "sg:province":"FL",
    "sg:tags":[
        "god",
        "churches-church",
        "churches-pentecostal"
    ],
    "wof:name":"Mills Street Church Of God",
    "wof:placetype":"venue"
},
  "geometry": {"coordinates":[-81.684532,28.841751],"type":"Point"}
}