{
  "type": "Feature",
  "properties": {
    "iso:country":"US",
    "sg:address":"426 Privateer Rd",
    "sg:city":"North Palm Beach",
    "sg:classifiers":[
        {
            "category":"Manufacturing",
            "subcategory":"Tools & Machinery",
            "type":"Manufacturing & Wholesale Goods"
        }
    ],
    "sg:phone":"+1 561 845 8166",
    "sg:postcode":"33408",
    "sg:province":"FL",
    "sg:tags":[
        "construction"
    ],
    "wof:name":"Sklubak & Assoc Inc",
    "wof:placetype":"venue"
},
  "geometry": {"coordinates":[-80.062724,26.819368],"type":"Point"}
}