{
  "type": "Feature",
  "properties": {
    "iso:country":"US",
    "sg:address":"13370 Douglas Rd",
    "sg:city":"Dade City",
    "sg:classifiers":[
        {
            "category":"Building & Trades",
            "subcategory":"Cleaning & Sanitation",
            "type":"Services"
        }
    ],
    "sg:phone":"+1 352 588 3063",
    "sg:postcode":"33525",
    "sg:province":"FL",
    "sg:tags":[
        "house"
    ],
    "wof:name":"Yvonne Sloop Cleaning Business",
    "wof:placetype":"venue"
},
  "geometry": {"coordinates":[-82.357232,28.352118],"type":"Point"}
}