{
  "type": "Feature",
  "properties": {
    "iso:country":"US",
    "sg:address":"1627 E 8th St",
    "sg:city":"Jacksonville",
    "sg:classifiers":[
        {
            "category":"Social Services",
            "subcategory":"Adult Care",
            "type":"Services"
        },
        {
            "category":"Real Estate",
            "subcategory":"Real Estate Operator",
            "type":"Services"
        }
    ],
    "sg:phone":"+1 904 355 9731",
    "sg:postcode":"32206",
    "sg:province":"FL",
    "sg:tags":[
        "boarding",
        "house",
        "residential"
    ],
    "wof:name":"Christian Bishop Home",
    "wof:placetype":"venue"
},
  "geometry": {"coordinates":[-81.63207800000001,30.345291],"type":"Point"}
}