{
  "type": "Feature",
  "properties": {
    "iso:country":"US",
    "sg:address":"4125 NE 174th Ter",
    "sg:city":"Silver Springs",
    "sg:classifiers":[
        {
            "category":"Building & Trades",
            "subcategory":"Construction",
            "type":"Services"
        }
    ],
    "sg:phone":"+1 352 817 5854",
    "sg:postcode":"34488",
    "sg:province":"FL",
    "sg:tags":[
        "plastering",
        "contractor"
    ],
    "wof:name":"Chris Reeves Plastering",
    "wof:placetype":"venue"
},
  "geometry": {"coordinates":[-81.864115,29.228374],"type":"Point"}
}