{
  "type": "Feature",
  "properties": {
    "iso:country":"US",
    "sg:address":"15971 Mellen Ln",
    "sg:city":"Jupiter",
    "sg:classifiers":[
        {
            "category":"Marine",
            "type":"Transportation"
        }
    ],
    "sg:phone":"+1 561 845 7171",
    "sg:postcode":"33478",
    "sg:province":"FL",
    "sg:tags":[
        "surveyor"
    ],
    "wof:name":"Stetler Marine Surveys",
    "wof:placetype":"venue"
},
  "geometry": {"coordinates":[-80.232829,26.910369],"type":"Point"}
}