{
  "type": "Feature",
  "properties": {
    "addr:full":"336 W Bay St Jacksonville FL 32202",
    "addr:housenumber":"336",
    "addr:postcode":"32202",
    "addr:street":"W Bay St",
    "iso:country":"US",
    "sg:address":"336 W Bay St",
    "sg:city":"Jacksonville",
    "sg:classifiers":[
        {
            "category":"Parking",
            "type":"Transportation"
        }
    ],
    "sg:phone":"+1 904 355 5129",
    "sg:postcode":"32202",
    "sg:province":"FL",
    "sg:tags":[
        "garage"
    ],
    "wof:name":"Central Parking System",
    "wof:placetype":"venue"
},
  "geometry": {"coordinates":[-81.662621,30.327175],"type":"Point"}
}