{
  "type": "Feature",
  "properties": {
    "iso:country":"US",
    "sg:address":"4980 W 10th Ave Ste 102",
    "sg:city":"Hialeah",
    "sg:classifiers":[
        {
            "category":"Professional",
            "subcategory":"Testing Lab",
            "type":"Services"
        }
    ],
    "sg:phone":"+1 305 558 4140",
    "sg:postcode":"33012",
    "sg:province":"FL",
    "sg:tags":[
        "laboratory"
    ],
    "wof:name":"Breast & Ultrasound Diagnostic Services, Inc",
    "wof:placetype":"venue"
},
  "geometry": {"coordinates":[-80.30342,25.867453],"type":"Point"}
}