{
  "type": "Feature",
  "properties": {
    "addr:full":"2300 NE 38th St Ocala FL 34479",
    "addr:housenumber":"2300",
    "addr:postcode":"34479",
    "addr:street":"Ne 38Th St",
    "iso:country":"US",
    "sg:address":"2300 NE 38th St",
    "sg:city":"Ocala",
    "sg:classifiers":[
        {
            "category":"Shopping",
            "subcategory":"Used Merchandise",
            "type":"Retail Goods"
        }
    ],
    "sg:phone":"+1 352 867 8222",
    "sg:postcode":"34479",
    "sg:province":"FL",
    "wof:name":"L&J Life Is A Jrney Thrift Str",
    "wof:placetype":"venue"
},
  "geometry": {"coordinates":[-82.105784,29.226141],"type":"Point"}
}