{
  "type": "Feature",
  "properties": {
    "iso:country":"US",
    "sg:address":"14275 SW 232nd St",
    "sg:city":"Miami",
    "sg:classifiers":[
        {
            "category":"Building & Trades",
            "subcategory":"Landscaping Services",
            "type":"Services"
        }
    ],
    "sg:phone":"+1 305 257 0034",
    "sg:postcode":"33170",
    "sg:province":"FL",
    "sg:tags":[
        "landscape",
        "contractor"
    ],
    "wof:name":"Colorful Forest Landscaping",
    "wof:placetype":"venue"
},
  "geometry": {"coordinates":[-80.421722,25.551214],"type":"Point"}
}