{
  "type": "Feature",
  "properties": {
    "addr:full":"10136 W Indiantown Rd Jupiter FL 33478",
    "addr:housenumber":"10136",
    "addr:postcode":"33478",
    "addr:street":"W Indiantown Rd",
    "iso:country":"US",
    "sg:address":"10136 W Indiantown Rd",
    "sg:city":"Jupiter",
    "sg:classifiers":[
        {
            "category":"Retail",
            "subcategory":"Repair Shop",
            "type":"Services"
        }
    ],
    "sg:phone":"+1 561 953 2037",
    "sg:postcode":"33478",
    "sg:province":"FL",
    "sg:tags":[
        "lock",
        "locksmith"
    ],
    "wof:name":"24 Hour 7 Day Emrgncy Lcksmth",
    "wof:placetype":"venue"
},
  "geometry": {"coordinates":[-80.197911,26.942159],"type":"Point"}
}