{
  "type": "Feature",
  "properties": {
    "iso:country":"US",
    "sg:address":"3354 Lake Shore Blvd",
    "sg:city":"Jacksonville",
    "sg:classifiers":[
        {
            "category":"Professional",
            "subcategory":"Management & Consulting",
            "type":"Services"
        }
    ],
    "sg:phone":"+1 904 389 9922",
    "sg:postcode":"32210",
    "sg:province":"FL",
    "sg:tags":[
        "roofing",
        "consultant"
    ],
    "wof:name":"Jodie Marchman Roof Conslnts",
    "wof:placetype":"venue"
},
  "geometry": {"coordinates":[-81.72183,30.272663],"type":"Point"}
}