{
  "type": "Feature",
  "properties": {
    "addr:full":"2853 Foxwood Ct Clearwater FL 33761",
    "addr:housenumber":"2853",
    "addr:postcode":"33761",
    "addr:street":"Foxwood Ct",
    "iso:country":"US",
    "sg:address":"2853 Foxwood Ct",
    "sg:city":"Clearwater",
    "sg:classifiers":[
        {
            "category":"Building & Trades",
            "subcategory":"Construction",
            "type":"Services"
        }
    ],
    "sg:phone":"+1 727 725 0531",
    "sg:postcode":"33761",
    "sg:province":"FL",
    "sg:tags":[
        "floor",
        "laying",
        "contractor"
    ],
    "wof:name":"Kms Broadloom Inc",
    "wof:placetype":"venue"
},
  "geometry": {"coordinates":[-82.71909100000001,28.028021],"type":"Point"}
}