{
  "type": "Feature",
  "properties": {
    "iso:country":"US",
    "sg:address":"2515 NW 166th St",
    "sg:city":"Opa Locka",
    "sg:classifiers":[
        {
            "category":"Social Services",
            "type":"Services"
        }
    ],
    "sg:phone":"+1 305 430 9802",
    "sg:postcode":"33054",
    "sg:province":"FL",
    "wof:name":"Petashleys",
    "wof:placetype":"venue"
},
  "geometry": {"coordinates":[-80.24445799999999,25.925695],"type":"Point"}
}