{
  "type": "Feature",
  "properties": {
    "iso:country":"US",
    "sg:address":"10442 SW 21st St",
    "sg:city":"Miami",
    "sg:classifiers":[
        {
            "category":"Health Services",
            "subcategory":"Doctor",
            "type":"Services"
        }
    ],
    "sg:phone":"+1 305 553 2920",
    "sg:postcode":"33165",
    "sg:province":"FL",
    "wof:name":"Arencibia Fernando MD",
    "wof:placetype":"venue"
},
  "geometry": {"coordinates":[-80.36460099999999,25.75],"type":"Point"}
}