{
  "type": "Feature",
  "properties": {
    "addr:full":"1405 S Orange Ave Orlando FL 32806",
    "addr:housenumber":"1405",
    "addr:postcode":"32806",
    "addr:street":"S Orange Ave",
    "iso:country":"US",
    "sg:address":"1405 S Orange Ave",
    "sg:city":"Orlando",
    "sg:classifiers":[
        {
            "category":"Health Services",
            "subcategory":"Doctor",
            "type":"Services"
        }
    ],
    "sg:phone":"+1 407 425 6226",
    "sg:postcode":"32806",
    "sg:province":"FL",
    "sg:tags":[
        "physician",
        "surgeon"
    ],
    "wof:name":"Outpatient Cardiovascular Ctr",
    "wof:placetype":"venue"
},
  "geometry": {"coordinates":[-81.37639299999999,28.525818],"type":"Point"}
}