{
  "type": "Feature",
  "properties": {
    "addr:full":"9518 Lakeview Ct Spring Hill FL 34608",
    "addr:housenumber":"9518",
    "addr:postcode":"34608",
    "addr:street":"Lakeview Ct",
    "iso:country":"US",
    "sg:address":"9518 Lakeview Ct",
    "sg:city":"Spring Hill",
    "sg:classifiers":[
        {
            "category":"Building & Trades",
            "subcategory":"Landscaping Services",
            "type":"Services"
        }
    ],
    "sg:phone":"+1 352 688 1852",
    "sg:postcode":"34608",
    "sg:province":"FL",
    "sg:tags":[
        "lawn",
        "maintenance",
        "grounds"
    ],
    "wof:name":"Michael Smith Lawn Svc",
    "wof:placetype":"venue"
},
  "geometry": {"coordinates":[-82.560064,28.492368],"type":"Point"}
}