{
  "type": "Feature",
  "properties": {
    "iso:country":"US",
    "sg:address":"7326 Miami Lakeway S",
    "sg:city":"Hialeah",
    "sg:classifiers":[
        {
            "category":"Shopping",
            "subcategory":"Catalog Store",
            "type":"Retail Goods"
        }
    ],
    "sg:phone":"+1 786 210 7640",
    "sg:postcode":"33014",
    "sg:province":"FL",
    "sg:tags":[
        "mail",
        "order",
        "merchandise",
        "general"
    ],
    "wof:name":"Buddha Wear",
    "wof:placetype":"venue"
},
  "geometry": {"coordinates":[-80.31862099999999,25.909685],"type":"Point"}
}