{
  "type": "Feature",
  "properties": {
    "iso:country":"US",
    "sg:address":"105 South St",
    "sg:city":"Daytona Beach",
    "sg:classifiers":[
        {
            "category":"Social Services",
            "type":"Services"
        }
    ],
    "sg:phone":"+1 386 258 5993",
    "sg:postcode":"32114",
    "sg:province":"FL",
    "sg:tags":[
        "info",
        "program",
        "referral"
    ],
    "wof:name":"Family Renew Community",
    "wof:placetype":"venue"
},
  "geometry": {"coordinates":[-81.01555399999999,29.199837],"type":"Point"}
}