{
  "type": "Feature",
  "properties": {
    "addr:full":"17646 Temple Blvd Loxahatchee FL 33470",
    "addr:housenumber":"17646",
    "addr:postcode":"33470",
    "addr:street":"Temple Blvd",
    "iso:country":"US",
    "sg:address":"17646 Temple Blvd",
    "sg:city":"Loxahatchee",
    "sg:classifiers":[
        {
            "category":"Building & Trades",
            "subcategory":"Cleaning & Sanitation",
            "type":"Services"
        }
    ],
    "sg:phone":"+1 561 790 7343",
    "sg:postcode":"33470",
    "sg:province":"FL",
    "sg:tags":[
        "house"
    ],
    "wof:name":"Heshee Cleaning Svc",
    "wof:placetype":"venue"
},
  "geometry": {"coordinates":[-80.321653,26.794654],"type":"Point"}
}