{
  "type": "Feature",
  "properties": {
    "iso:country":"US",
    "sg:address":"5884 NW 79th Way",
    "sg:city":"Parkland",
    "sg:classifiers":[
        {
            "category":"Retail",
            "subcategory":"Portrait Studio",
            "type":"Services"
        }
    ],
    "sg:phone":"+1 954 753 3686",
    "sg:postcode":"33067",
    "sg:province":"FL",
    "sg:tags":[
        "photographer",
        "photography",
        "commercial",
        "photo"
    ],
    "wof:name":"Creative Focus Photography",
    "wof:placetype":"venue"
},
  "geometry": {"coordinates":[-80.231387,26.307914],"type":"Point"}
}