{
  "type": "Feature",
  "properties": {
    "addr:full":"933 E Bloomingdale Ave Brandon FL 33511",
    "addr:housenumber":"933",
    "addr:postcode":"33511",
    "addr:street":"E Bloomingdale Ave",
    "iso:country":"US",
    "sg:address":"933 E Bloomingdale Ave",
    "sg:city":"Brandon",
    "sg:classifiers":[
        {
            "category":"Shopping",
            "subcategory":"Shoes",
            "type":"Retail Goods"
        }
    ],
    "sg:phone":"+1 813 684 6677",
    "sg:postcode":"33511",
    "sg:province":"FL",
    "wof:name":"Payless Shoe Source",
    "wof:placetype":"venue"
},
  "geometry": {"coordinates":[-82.272851,27.893569],"type":"Point"}
}