{
  "type": "Feature",
  "properties": {
    "addr:full":"300 Woodette Dr Apt 505 Dunedin FL 34698",
    "addr:housenumber":"300;505",
    "addr:postcode":"34698",
    "addr:street":"Woodette Dr Apt",
    "iso:country":"US",
    "sg:address":"300 Woodette Dr Apt 505",
    "sg:city":"Dunedin",
    "sg:classifiers":[
        {
            "category":"Professional",
            "subcategory":"Art Services",
            "type":"Services"
        }
    ],
    "sg:phone":"+1 727 474 3497",
    "sg:postcode":"34698",
    "sg:province":"FL",
    "sg:tags":[
        "designer",
        "display",
        "producer"
    ],
    "wof:name":"Creative Design",
    "wof:placetype":"venue"
},
  "geometry": {"coordinates":[-82.787727,28.05196],"type":"Point"}
}