{
  "type": "Feature",
  "properties": {
    "iso:country":"US",
    "sg:address":"8030 Whispering Palm Dr",
    "sg:city":"Boca Raton",
    "sg:classifiers":[
        {
            "category":"Real Estate",
            "subcategory":"Real Estate Agent",
            "type":"Services"
        }
    ],
    "sg:phone":"+1 561 451 0660",
    "sg:postcode":"33496",
    "sg:province":"FL",
    "wof:name":"Whisper Walk Section D Assn",
    "wof:placetype":"venue"
},
  "geometry": {"coordinates":[-80.17264,26.400827],"type":"Point"}
}