{
  "type": "Feature",
  "properties": {
    "addr:full":"1510 NW 22nd St Crystal River FL 34428",
    "addr:housenumber":"1510",
    "addr:postcode":"34428",
    "addr:street":"Nw 22Nd St",
    "iso:country":"US",
    "sg:address":"1510 NW 22nd St",
    "sg:city":"Crystal River",
    "sg:classifiers":[
        {
            "category":"Shopping",
            "type":"Retail Goods"
        }
    ],
    "sg:phone":"+1 352 795 9026",
    "sg:postcode":"34428",
    "sg:province":"FL",
    "sg:tags":[
        "art",
        "gallery",
        "dealer"
    ],
    "wof:name":"Glen Haven Gallery II Pictr",
    "wof:placetype":"venue"
},
  "geometry": {"coordinates":[-82.61274,28.916578],"type":"Point"}
}