{
  "type": "Feature",
  "properties": {
    "iso:country":"US",
    "sg:address":"7959 NW 21st St",
    "sg:city":"Doral",
    "sg:classifiers":[
        {
            "category":"Professional",
            "type":"Services"
        }
    ],
    "sg:phone":"+1 305 640 9876",
    "sg:postcode":"33122",
    "sg:province":"FL",
    "sg:tags":[
        "establishment"
    ],
    "wof:name":"Antarctica Products",
    "wof:placetype":"venue"
},
  "geometry": {"coordinates":[-80.328452,25.793492],"type":"Point"}
}