{
  "type": "Feature",
  "properties": {
    "iso:country":"US",
    "sg:address":"Detrick Ave",
    "sg:city":"Deland",
    "sg:classifiers":[
        {
            "category":"Building & Trades",
            "subcategory":"Construction",
            "type":"Services"
        }
    ],
    "sg:phone":"+1 386 736 8880",
    "sg:postcode":"32720",
    "sg:province":"FL",
    "sg:tags":[
        "contractor"
    ],
    "wof:name":"McMahan Construction Inc",
    "wof:placetype":"venue"
},
  "geometry": {"coordinates":[-81.329399,29.027901],"type":"Point"}
}