{
  "type": "Feature",
  "properties": {
    "addr:full":"3720 S Dixie Hwy West Palm Beach FL 33405",
    "addr:housenumber":"3720",
    "addr:postcode":"33405",
    "addr:street":"S Dixie Hwy",
    "iso:country":"US",
    "sg:address":"3720 S Dixie Hwy",
    "sg:city":"West Palm Beach",
    "sg:classifiers":[
        {
            "category":"Banks & Credit Unions",
            "subcategory":"Bank",
            "type":"Services"
        }
    ],
    "sg:phone":"+1 561 659 0062",
    "sg:postcode":"33405",
    "sg:province":"FL",
    "sg:tags":[
        "loan",
        "real estate"
    ],
    "wof:name":"Zurich Mortgage Solutions",
    "wof:placetype":"venue"
},
  "geometry": {"coordinates":[-80.054625,26.677146],"type":"Point"}
}