{
  "type": "Feature",
  "properties": {
    "iso:country":"US",
    "sg:address":"1559 Shady Lake Ter",
    "sg:city":"Palm City",
    "sg:classifiers":[
        {
            "category":"Local Transit",
            "type":"Transportation"
        }
    ],
    "sg:phone":"+1 561 684 1512",
    "sg:postcode":"34990",
    "sg:province":"FL",
    "sg:tags":[
        "limousine"
    ],
    "wof:name":"Brazilian Limousine Svc",
    "wof:placetype":"venue"
},
  "geometry": {"coordinates":[-80.276979,27.176638],"type":"Point"}
}