{
  "type": "Feature",
  "properties": {
    "iso:country":"US",
    "sg:address":"4728 Frontier Rd",
    "sg:city":"Milton",
    "sg:classifiers":[
        {
            "category":"Home & Garden",
            "subcategory":"Building Materials",
            "type":"Retail Goods"
        },
        {
            "category":"Building & Trades",
            "subcategory":"Construction",
            "type":"Services"
        }
    ],
    "sg:phone":"+1 850 982 2363",
    "sg:postcode":"32571",
    "sg:province":"FL",
    "sg:tags":[
        "fence-sales",
        "fence",
        "contractor"
    ],
    "wof:name":"Luttigs Fencing Inc",
    "wof:placetype":"venue"
},
  "geometry": {"coordinates":[-87.13566299999999,30.608227],"type":"Point"}
}