{
  "type": "Feature",
  "properties": {
    "iso:country":"US",
    "sg:address":"9950 NW 17th St",
    "sg:city":"Doral",
    "sg:classifiers":[
        {
            "category":"Professional",
            "type":"Services"
        }
    ],
    "sg:phone":"+1 305 463 4800",
    "sg:postcode":"33172",
    "sg:province":"FL",
    "sg:tags":[
        "establishment"
    ],
    "wof:name":"Crowley Maritime Corp",
    "wof:placetype":"venue"
},
  "geometry": {"coordinates":[-80.357416,25.789917],"type":"Point"}
}