{
  "type": "Feature",
  "properties": {
    "iso:country":"US",
    "sg:address":"300 Bayou Blvd Apt 103",
    "sg:city":"Pensacola",
    "sg:classifiers":[
        {
            "category":"Real Estate",
            "subcategory":"Real Estate Services",
            "type":"Services"
        },
        {
            "category":"Real Estate",
            "subcategory":"Real Estate Operator",
            "type":"Services"
        }
    ],
    "sg:phone":"+1 850 438 7542",
    "sg:postcode":"32503",
    "sg:province":"FL",
    "sg:tags":[
        "apartment",
        "condominium",
        "vacancy",
        "management",
        "listing",
        "rental",
        "finder"
    ],
    "wof:name":"Bayou Breeze Condominiums",
    "wof:placetype":"venue"
},
  "geometry": {"coordinates":[-87.18598900000001,30.42448],"type":"Point"}
}