{
  "type": "Feature",
  "properties": {
    "iso:country":"US",
    "sg:address":"21790 160th St",
    "sg:city":"Live Oak",
    "sg:classifiers":[
        {
            "category":"Social Services",
            "type":"Services"
        }
    ],
    "sg:phone":"+1 386 776 1877",
    "sg:postcode":"32060",
    "sg:province":"FL",
    "sg:tags":[
        "counseling"
    ],
    "wof:name":"Christian Family Counseling",
    "wof:placetype":"venue"
},
  "geometry": {"coordinates":[-83.20146099999999,30.158493],"type":"Point"}
}