{
  "type": "Feature",
  "properties": {
    "addr:full":"4197 Avalon Blvd Milton FL 32583",
    "addr:housenumber":"4197",
    "addr:postcode":"32583",
    "addr:street":"Avalon Blvd",
    "iso:country":"US",
    "sg:address":"4197 Avalon Blvd",
    "sg:city":"Milton",
    "sg:classifiers":[
        {
            "category":"Building & Trades",
            "subcategory":"Plumbing",
            "type":"Services"
        }
    ],
    "sg:phone":"+1 850 623 2636",
    "sg:postcode":"32583",
    "sg:province":"FL",
    "sg:tags":[
        "repair",
        "electrical"
    ],
    "wof:name":"Avalon Plumbing",
    "wof:placetype":"venue"
},
  "geometry": {"coordinates":[-87.086078,30.58372],"type":"Point"}
}