{
  "type": "Feature",
  "properties": {
    "iso:country":"US",
    "sg:address":"6789 Phillips Industrial Blvd",
    "sg:city":"Jacksonville",
    "sg:classifiers":[
        {
            "category":"Wholesale",
            "subcategory":"Construction Materials",
            "type":"Manufacturing & Wholesale Goods"
        }
    ],
    "sg:phone":"+1 904 268 7511",
    "sg:postcode":"32256",
    "sg:province":"FL",
    "wof:name":"Construction Materials Limited",
    "wof:placetype":"venue"
},
  "geometry": {"coordinates":[-81.531716,30.159269],"type":"Point"}
}