{
  "type": "Feature",
  "properties": {
    "addr:full":"2020 Oakley Seaver Dr, Ste 1 Clermont FL 34711",
    "addr:housenumber":"2020",
    "addr:postcode":"34711",
    "addr:street":"Oakley Seaver Dr Ste 1",
    "iso:country":"US",
    "sg:address":"2020 Oakley Seaver Dr, Ste 1",
    "sg:city":"Clermont",
    "sg:classifiers":[
        {
            "category":"Health Services",
            "subcategory":"Doctor",
            "type":"Services"
        }
    ],
    "sg:phone":"+1 352 404 6959",
    "sg:postcode":"34711",
    "sg:province":"FL",
    "sg:tags":[
        "physician",
        "management",
        "pediatrics",
        "surgeons",
        "medicine",
        "pain",
        "surgeon",
        "rehabilitation",
        "physical"
    ],
    "sg:website":"http://www.physmedi.com",
    "wof:name":"Margarita Correa MD",
    "wof:placetype":"venue"
},
  "geometry": {"coordinates":[-81.719976,28.553694],"type":"Point"}
}