{
  "type": "Feature",
  "properties": {
    "iso:country":"US",
    "sg:address":"3939 Webber St",
    "sg:city":"Sarasota",
    "sg:classifiers":[
        {
            "category":"Organizations",
            "subcategory":"Religious Organization",
            "type":"Services"
        }
    ],
    "sg:phone":"+1 941 924 4050",
    "sg:postcode":"34232",
    "sg:province":"FL",
    "sg:tags":[
        "church"
    ],
    "wof:name":"Trinity Chapel",
    "wof:placetype":"venue"
},
  "geometry": {"coordinates":[-82.4901,27.308345],"type":"Point"}
}