{
  "type": "Feature",
  "properties": {
    "addr:full":"3221 W Hallandale Beach Blvd Pembroke Pines FL 33023",
    "addr:housenumber":"3221",
    "addr:postcode":"33023",
    "addr:street":"W Hallandale Beach Blvd",
    "iso:country":"US",
    "sg:address":"3221 W Hallandale Beach Blvd",
    "sg:city":"Pembroke Pines",
    "sg:classifiers":[
        {
            "category":"Real Estate",
            "subcategory":"Developer",
            "type":"Services"
        }
    ],
    "sg:phone":"+1 954 964 2292",
    "sg:postcode":"33023",
    "sg:province":"FL",
    "wof:name":"Southern Facilities",
    "wof:placetype":"venue"
},
  "geometry": {"coordinates":[-80.17537400000001,25.984819],"type":"Point"}
}