{
  "type": "Feature",
  "properties": {
    "iso:country":"US",
    "sg:address":"6014 W Linebaugh Ave",
    "sg:city":"Tampa",
    "sg:classifiers":[
        {
            "category":"Manufacturing",
            "subcategory":"Metals",
            "type":"Manufacturing & Wholesale Goods"
        }
    ],
    "sg:phone":"+1 813 961 7893",
    "sg:postcode":"33625",
    "sg:province":"FL",
    "sg:tags":[
        "mfg",
        "furniture"
    ],
    "wof:name":"Design Specialties",
    "wof:placetype":"venue"
},
  "geometry": {"coordinates":[-82.54266699999999,28.040298],"type":"Point"}
}