{
  "type": "Feature",
  "properties": {
    "addr:full":"385 N Elizabeth Ave Bartow FL 33830",
    "addr:housenumber":"385",
    "addr:postcode":"33830",
    "addr:street":"N Elizabeth Ave",
    "iso:country":"US",
    "sg:address":"385 N Elizabeth Ave",
    "sg:city":"Bartow",
    "sg:classifiers":[
        {
            "category":"Building & Trades",
            "subcategory":"Plumbing",
            "type":"Services"
        }
    ],
    "sg:phone":"+1 863 533 3584",
    "sg:postcode":"33830",
    "sg:province":"FL",
    "sg:tags":[
        "plumbing",
        "contractor"
    ],
    "wof:name":"Harry A Morgan Plumbing",
    "wof:placetype":"venue"
},
  "geometry": {"coordinates":[-81.829774,27.89866],"type":"Point"}
}