{
  "type": "Feature",
  "properties": {
    "iso:country":"US",
    "sg:address":"9409 W Atlantic Blvd",
    "sg:city":"Pompano Beach",
    "sg:classifiers":[
        {
            "category":"Restaurant",
            "type":"Food & Drink"
        }
    ],
    "sg:menulink":"http://www.allmenus.com/fl/margate/179685-chick-fil-a/menu/",
    "sg:phone":"+1 954 753 7767",
    "sg:postcode":"33071",
    "sg:province":"FL",
    "sg:tags":[
        "wrap",
        "soup",
        "american",
        "sandwich",
        "salad"
    ],
    "wof:name":"Chick-fil-A",
    "wof:placetype":"venue"
},
  "geometry": {"coordinates":[-80.254536,26.240415],"type":"Point"}
}