{
  "type": "Feature",
  "properties": {
    "addr:full":"15090 Lakeside View Dr Fort Myers FL 33919",
    "addr:housenumber":"15090",
    "addr:postcode":"33919",
    "addr:street":"Lakeside View Dr",
    "iso:country":"US",
    "sg:address":"15090 Lakeside View Dr",
    "sg:city":"Fort Myers",
    "sg:classifiers":[
        {
            "category":"Professional",
            "subcategory":"Lawyer & Legal Services",
            "type":"Services"
        }
    ],
    "sg:phone":"+1 239 433 4505",
    "sg:postcode":"33919",
    "sg:province":"FL",
    "wof:name":"Harrison Simon M Atty",
    "wof:placetype":"venue"
},
  "geometry": {"coordinates":[-81.90920300000001,26.5226],"type":"Point"}
}