{
  "type": "Feature",
  "properties": {
    "iso:country":"US",
    "sg:address":"6720 Coral Way",
    "sg:city":"Miami",
    "sg:classifiers":[
        {
            "category":"Restaurant",
            "type":"Food & Drink"
        }
    ],
    "sg:phone":"+1 305 661 4281",
    "sg:postcode":"33155",
    "sg:province":"FL",
    "sg:tags":[
        "pizza"
    ],
    "sg:website":"http://www.pizzaleos.com/",
    "wof:name":"Leo's Pizza",
    "wof:placetype":"venue"
},
  "geometry": {"coordinates":[-80.304298,25.7481],"type":"Point"}
}