{
  "type": "Feature",
  "properties": {
    "iso:country":"US",
    "sg:address":"902 Carter Rd",
    "sg:city":"Winter Garden",
    "sg:classifiers":[
        {
            "category":"Retail",
            "subcategory":"Auto Repair",
            "type":"Services"
        },
        {
            "category":"Wholesale",
            "subcategory":"Auto Parts",
            "type":"Manufacturing & Wholesale Goods"
        }
    ],
    "sg:phone":"+1 407 654 3456",
    "sg:postcode":"34787",
    "sg:province":"FL",
    "sg:tags":[
        "repairing",
        "automobile",
        "retailer",
        "radiator"
    ],
    "wof:name":"Eskimo Radiators",
    "wof:placetype":"venue"
},
  "geometry": {"coordinates":[-81.56479899999999,28.553614],"type":"Point"}
}