{
  "type": "Feature",
  "properties": {
    "addr:full":"575 N Ridgewood Ave Ormond Beach FL 32174",
    "addr:housenumber":"575",
    "addr:postcode":"32174",
    "addr:street":"N Ridgewood Ave",
    "iso:country":"US",
    "sg:address":"575 N Ridgewood Ave",
    "sg:city":"Ormond Beach",
    "sg:classifiers":[
        {
            "category":"Shopping",
            "subcategory":"Catalog Store",
            "type":"Retail Goods"
        }
    ],
    "sg:phone":"+1 386 615 4555",
    "sg:postcode":"32174",
    "sg:province":"FL",
    "sg:tags":[
        "mail",
        "order"
    ],
    "wof:name":"Access D Design",
    "wof:placetype":"venue"
},
  "geometry": {"coordinates":[-81.065558,29.298555],"type":"Point"}
}