{
  "type": "Feature",
  "properties": {
    "addr:full":"824 W 69th St Hialeah FL 33014",
    "addr:housenumber":"824",
    "addr:postcode":"33014",
    "addr:street":"W 69Th St",
    "iso:country":"US",
    "sg:address":"824 W 69th St",
    "sg:city":"Hialeah",
    "sg:classifiers":[
        {
            "category":"Communications",
            "subcategory":"Film & Video Production",
            "type":"Services"
        }
    ],
    "sg:phone":"+1 305 558 7814",
    "sg:postcode":"33014",
    "sg:province":"FL",
    "sg:tags":[
        "motion"
    ],
    "wof:name":"Earth Tone Productions Inc",
    "wof:placetype":"venue"
},
  "geometry": {"coordinates":[-80.30190399999999,25.885104],"type":"Point"}
}