{
  "type": "Feature",
  "properties": {
    "addr:full":"15 S Orange Ave Orlando FL 32801",
    "addr:housenumber":"15",
    "addr:postcode":"32801",
    "addr:street":"S Orange Ave",
    "iso:country":"US",
    "sg:address":"15 S Orange Ave",
    "sg:city":"Orlando",
    "sg:classifiers":[
        {
            "category":"Bars & Pubs",
            "type":"Food & Drink"
        }
    ],
    "sg:phone":"+1 407 649 6496",
    "sg:postcode":"32801",
    "sg:province":"FL",
    "sg:tags":[
        "club",
        "night"
    ],
    "sg:website":"www.icon-nightclub.com",
    "wof:name":"Icon",
    "wof:placetype":"venue"
},
  "geometry": {"coordinates":[-81.378955,28.541428],"type":"Point"}
}