{
  "type": "Feature",
  "properties": {
    "iso:country":"US",
    "sg:address":"2161 Shadowlawn Dr",
    "sg:city":"Naples",
    "sg:classifiers":[
        {
            "category":"Education",
            "subcategory":"School",
            "type":"Public Place"
        }
    ],
    "sg:phone":"+1 239 417 3737",
    "sg:postcode":"34112",
    "sg:province":"FL",
    "sg:website":"www.collier.k12.fl.us",
    "wof:name":"Shadowlawn Elementary School",
    "wof:placetype":"venue"
},
  "geometry": {"coordinates":[-81.77055,26.134358],"type":"Point"}
}