{
  "type": "Feature",
  "properties": {
    "iso:country":"US",
    "sg:address":"5225 SW 112th Ct",
    "sg:city":"Miami",
    "sg:classifiers":[
        {
            "category":"Health Services",
            "subcategory":"Doctor",
            "type":"Services"
        }
    ],
    "sg:phone":"+1 561 416 9771",
    "sg:postcode":"33165",
    "sg:province":"FL",
    "sg:tags":[
        "dentist"
    ],
    "wof:name":"Pablo E Miranda DDS",
    "wof:placetype":"venue"
},
  "geometry": {"coordinates":[-80.376085,25.719603],"type":"Point"}
}