{
  "type": "Feature",
  "properties": {
    "addr:full":"3370 Capital Cir NE Tallahassee FL 32308",
    "addr:postcode":"3370;32308",
    "addr:street":"Capital Cir Ne",
    "iso:country":"US",
    "sg:address":"3370 Capital Cir NE",
    "sg:city":"Tallahassee",
    "sg:classifiers":[
        {
            "category":"Organizations",
            "subcategory":"Professional Association",
            "type":"Services"
        }
    ],
    "sg:phone":"+1 850 531 8344",
    "sg:postcode":"32308",
    "sg:province":"FL",
    "sg:tags":[
        "medical"
    ],
    "wof:name":"Florida Society of Dermatology",
    "wof:placetype":"venue"
},
  "geometry": {"coordinates":[-84.247522,30.499851],"type":"Point"}
}