{
  "type": "Feature",
  "properties": {
    "iso:country":"US",
    "sg:address":"929 Shipwatch Dr E",
    "sg:city":"Jacksonville",
    "sg:classifiers":[
        {
            "category":"Professional",
            "subcategory":"Lawyer & Legal Services",
            "type":"Services"
        }
    ],
    "sg:phone":"+1 904 220 9680",
    "sg:postcode":"32225",
    "sg:province":"FL",
    "wof:name":"Purcell Flangan & Hay",
    "wof:placetype":"venue"
},
  "geometry": {"coordinates":[-81.443904,30.349646],"type":"Point"}
}