{
  "type": "Feature",
  "properties": {
    "iso:country":"US",
    "sg:address":"2007 Harrison Ave",
    "sg:city":"Panama City",
    "sg:classifiers":[
        {
            "category":"Health Services",
            "subcategory":"Doctor",
            "type":"Services"
        },
        {
            "category":"Health Services",
            "subcategory":"Medical Lab",
            "type":"Services"
        }
    ],
    "sg:phone":"+1 850 769 5224",
    "sg:postcode":"32405",
    "sg:province":"FL",
    "sg:tags":[
        "laboratory",
        "surgeon",
        "physician"
    ],
    "wof:name":"Dzung Nguyen MD",
    "wof:placetype":"venue"
},
  "geometry": {"coordinates":[-85.65934900000001,30.1843],"type":"Point"}
}