{
  "type": "Feature",
  "properties": {
    "iso:country":"US",
    "sg:address":"600 King St",
    "sg:city":"Cocoa",
    "sg:classifiers":[
        {
            "category":"Autos & Motor Vehicles",
            "subcategory":"Auto Supplies",
            "type":"Retail Goods"
        }
    ],
    "sg:phone":"+1 321 633 6870",
    "sg:postcode":"32922",
    "sg:province":"FL",
    "sg:tags":[
        "automobile",
        "part",
        "accessory"
    ],
    "sg:website":"http://www.autozone.com",
    "wof:name":"AutoZone",
    "wof:placetype":"venue"
},
  "geometry": {"coordinates":[-80.736267,28.355761],"type":"Point"}
}