{
  "type": "Feature",
  "properties": {
    "iso:country":"US",
    "sg:address":"120 New Warrington Rd",
    "sg:city":"Pensacola",
    "sg:classifiers":[
        {
            "category":"Restaurant",
            "type":"Food & Drink"
        }
    ],
    "sg:phone":"+1 850 202 7827",
    "sg:postcode":"32506",
    "sg:province":"FL",
    "wof:name":"Miami Subs Grill",
    "wof:placetype":"venue"
},
  "geometry": {"coordinates":[-87.276242,30.410245],"type":"Point"}
}