{
  "type": "Feature",
  "properties": {
    "iso:country":"US",
    "sg:address":"912 S 62nd Ave",
    "sg:city":"Hollywood",
    "sg:classifiers":[
        {
            "category":"Retail",
            "subcategory":"Auto Repair",
            "type":"Services"
        }
    ],
    "sg:phone":"+1 954 983 9878",
    "sg:postcode":"33023",
    "sg:province":"FL",
    "sg:tags":[
        "general"
    ],
    "wof:name":"Moggio Auto Repair Service",
    "wof:placetype":"venue"
},
  "geometry": {"coordinates":[-80.211399,26.001998],"type":"Point"}
}