{
  "type": "Feature",
  "properties": {
    "addr:full":"1616 Rodman St Hollywood FL 33020",
    "addr:housenumber":"1616",
    "addr:postcode":"33020",
    "addr:street":"Rodman St",
    "iso:country":"US",
    "sg:address":"1616 Rodman St",
    "sg:city":"Hollywood",
    "sg:classifiers":[
        {
            "category":"Wholesale",
            "subcategory":"Auto Parts",
            "type":"Manufacturing & Wholesale Goods"
        }
    ],
    "sg:phone":"+1 954 922 0271",
    "sg:postcode":"33020",
    "sg:province":"FL",
    "wof:name":"Equipment Specialties",
    "wof:placetype":"venue"
},
  "geometry": {"coordinates":[-80.140451,26.001375],"type":"Point"}
}