{
  "type": "Feature",
  "properties": {
    "iso:country":"US",
    "sg:address":"385 W 49th St",
    "sg:city":"Hialeah",
    "sg:classifiers":[
        {
            "category":"Professional",
            "subcategory":"Lawyer & Legal Services",
            "type":"Services"
        }
    ],
    "sg:phone":"+1 305 817 2669",
    "sg:postcode":"33012",
    "sg:province":"FL",
    "wof:name":"Law Office of Cambo & Zaldivar",
    "wof:placetype":"venue"
},
  "geometry": {"coordinates":[-80.290505,25.866847],"type":"Point"}
}