{
  "type": "Feature",
  "properties": {
    "addr:full":"13741 Downing Ln Fort Myers FL 33919",
    "addr:housenumber":"13741",
    "addr:postcode":"33919",
    "addr:street":"Downing Ln",
    "iso:country":"US",
    "sg:address":"13741 Downing Ln",
    "sg:city":"Fort Myers",
    "sg:classifiers":[
        {
            "category":"Marine",
            "type":"Transportation"
        }
    ],
    "sg:phone":"+1 239 481 9423",
    "sg:postcode":"33919",
    "sg:province":"FL",
    "sg:tags":[
        "water",
        "transport"
    ],
    "wof:name":"T J Fish",
    "wof:placetype":"venue"
},
  "geometry": {"coordinates":[-81.908483,26.541814],"type":"Point"}
}