{
  "type": "Feature",
  "properties": {
    "addr:full":"8550 NW 33rd Ave Miami FL 33147",
    "addr:housenumber":"8550",
    "addr:postcode":"33147",
    "addr:street":"Nw 33Rd Ave",
    "iso:country":"US",
    "sg:address":"8550 NW 33rd Ave",
    "sg:city":"Miami",
    "sg:classifiers":[
        {
            "category":"Banks & Credit Unions",
            "subcategory":"Financial Services",
            "type":"Services"
        }
    ],
    "sg:phone":"+1 305 559 7707",
    "sg:postcode":"33147",
    "sg:province":"FL",
    "sg:tags":[
        "broker",
        "mortgage"
    ],
    "wof:name":"Continental Trust Mortgage",
    "wof:placetype":"venue"
},
  "geometry": {"coordinates":[-80.252053,25.852403],"type":"Point"}
}