{
  "type": "Feature",
  "properties": {
    "iso:country":"US",
    "sg:address":"4655 Hwy 90",
    "sg:city":"Marianna",
    "sg:classifiers":[
        {
            "category":"Travel",
            "subcategory":"Hotels & Motels",
            "type":"Entertainment"
        }
    ],
    "sg:phone":"+1 850 526 3251",
    "sg:postcode":"32446",
    "sg:province":"FL",
    "sg:tags":[
        "operation"
    ],
    "wof:name":"Ramada Inn",
    "wof:placetype":"venue"
},
  "geometry": {"coordinates":[-85.20743299999999,30.770281],"type":"Point"}
}