{
  "type": "Feature",
  "properties": {
    "iso:country":"US",
    "sg:address":"44 Lake Beauty Dr",
    "sg:city":"Orlando",
    "sg:classifiers":[
        {
            "category":"Health Services",
            "subcategory":"Doctor",
            "type":"Services"
        }
    ],
    "sg:phone":"+1 407 425 7188",
    "sg:postcode":"32806",
    "sg:province":"FL",
    "sg:tags":[
        "physician",
        "surgeon"
    ],
    "sg:website":"www.centralfloridaretina.com",
    "wof:name":"Central Florida Retina",
    "wof:placetype":"venue"
},
  "geometry": {"coordinates":[-81.377408,28.522641],"type":"Point"}
}