{
  "type": "Feature",
  "properties": {
    "addr:full":"1700 W International Speedway Blvd Daytona Beach FL 32114",
    "addr:housenumber":"1700",
    "addr:postcode":"32114",
    "addr:street":"W International Speedway Blvd",
    "iso:country":"US",
    "sg:address":"1700 W International Speedway Blvd",
    "sg:city":"Daytona Beach",
    "sg:classifiers":[
        {
            "category":"Personal",
            "subcategory":"Beauty Salon",
            "type":"Services"
        }
    ],
    "sg:phone":"+1 386 257 9007",
    "sg:postcode":"32114",
    "sg:province":"FL",
    "sg:tags":[
        "treatment",
        "skin"
    ],
    "wof:name":"Skin Deep",
    "wof:placetype":"venue"
},
  "geometry": {"coordinates":[-81.065101,29.193743],"type":"Point"}
}