{
  "type": "Feature",
  "properties": {
    "iso:country":"US",
    "sg:address":"8045 N.W. 36 St. Ste. 506-A",
    "sg:city":"Doral",
    "sg:classifiers":[
        {
            "category":"Education",
            "subcategory":"Junior College",
            "type":"Public Place"
        },
        {
            "category":"Education",
            "subcategory":"University",
            "type":"Public Place"
        }
    ],
    "sg:phone":"+1 786 287 4843",
    "sg:postcode":"33166",
    "sg:province":"FL",
    "sg:tags":[
        "school",
        "real estate"
    ],
    "sg:website":"http://www.jmrealtyschool.com",
    "wof:name":"Abi International",
    "wof:placetype":"venue"
},
  "geometry": {"coordinates":[-80.32624300000001,25.809524],"type":"Point"}
}