{
  "type": "Feature",
  "properties": {
    "iso:country":"US",
    "sg:address":"1681 E Hinson Ave",
    "sg:city":"Haines City",
    "sg:classifiers":[
        {
            "category":"Restaurant",
            "type":"Food & Drink"
        }
    ],
    "sg:phone":"+1 863 422 5522",
    "sg:postcode":"33844",
    "sg:province":"FL",
    "wof:name":"Bird Of Paradise",
    "wof:placetype":"venue"
},
  "geometry": {"coordinates":[-81.61863,28.106623],"type":"Point"}
}