{
  "type": "Feature",
  "properties": {
    "iso:country":"US",
    "sg:address":"4602 N Himes Ave",
    "sg:city":"Tampa",
    "sg:classifiers":[
        {
            "category":"Government",
            "subcategory":"Office",
            "type":"Public Place"
        }
    ],
    "sg:phone":"+1 813 348 1172",
    "sg:postcode":"33614",
    "sg:province":"FL",
    "sg:tags":[
        "township",
        "government-city",
        "village"
    ],
    "wof:name":"Cordelia B Hunt Ctr",
    "wof:placetype":"venue"
},
  "geometry": {"coordinates":[-82.501211,27.986219],"type":"Point"}
}