{
  "type": "Feature",
  "properties": {
    "addr:full":"2245 Old Gunn Hwy Odessa FL 33556",
    "addr:housenumber":"2245",
    "addr:postcode":"33556",
    "addr:street":"Old Gunn Hwy",
    "iso:country":"US",
    "sg:address":"2245 Old Gunn Hwy",
    "sg:city":"Odessa",
    "sg:classifiers":[
        {
            "category":"Place Of Worship",
            "type":"Public Place"
        }
    ],
    "sg:phone":"+1 813 951 2288",
    "sg:postcode":"33556",
    "sg:province":"FL",
    "sg:tags":[
        "church"
    ],
    "wof:name":"St Judes Church",
    "wof:placetype":"venue"
},
  "geometry": {"coordinates":[-82.594382,28.191363],"type":"Point"}
}