{
  "type": "Feature",
  "properties": {
    "iso:country":"US",
    "sg:address":"202 Pontotoc St",
    "sg:city":"Auburndale",
    "sg:classifiers":[
        {
            "category":"Place Of Worship",
            "subcategory":"Church",
            "type":"Public Place"
        },
        {
            "category":"Place Of Worship",
            "type":"Public Place"
        }
    ],
    "sg:phone":"+1 863 967 2130",
    "sg:postcode":"33823",
    "sg:province":"FL",
    "sg:tags":[
        "churches-episcopal-anglican",
        "churches-episcopal"
    ],
    "wof:name":"St Alban's Episcopal Church",
    "wof:placetype":"venue"
},
  "geometry": {"coordinates":[-81.78831,28.064611],"type":"Point"}
}