{
  "type": "Feature",
  "properties": {
    "addr:full":"2225 NE 123rd St North Miami FL 33181",
    "addr:housenumber":"2225",
    "addr:postcode":"33181",
    "addr:street":"Ne 123Rd St",
    "iso:country":"US",
    "sg:address":"2225 NE 123rd St",
    "sg:city":"North Miami",
    "sg:classifiers":[
        {
            "category":"Professional",
            "type":"Services"
        }
    ],
    "sg:phone":"+1 305 891 3100",
    "sg:postcode":"33181",
    "sg:province":"FL",
    "sg:tags":[
        "establishment"
    ],
    "wof:name":"Drain Defender",
    "wof:placetype":"venue"
},
  "geometry": {"coordinates":[-80.157448,25.889464],"type":"Point"}
}