{
  "type": "Feature",
  "properties": {
    "iso:country":"US",
    "sg:address":"300 1st St NW",
    "sg:city":"Largo",
    "sg:classifiers":[
        {
            "category":"Retail",
            "subcategory":"Repair Shop",
            "type":"Services"
        }
    ],
    "sg:phone":"+1 727 584 2016",
    "sg:postcode":"33770",
    "sg:province":"FL",
    "sg:tags":[
        "supply"
    ],
    "wof:name":"American Lawnmower",
    "wof:placetype":"venue"
},
  "geometry": {"coordinates":[-82.789975,27.919093],"type":"Point"}
}