{
  "type": "Feature",
  "properties": {
    "iso:country":"US",
    "sg:address":"2901 4th St N",
    "sg:city":"St Petersburg",
    "sg:classifiers":[
        {
            "category":"Health Services",
            "subcategory":"Health Practitioner",
            "type":"Services"
        }
    ],
    "sg:phone":"+1 727 821 8300",
    "sg:postcode":"33704",
    "sg:province":"FL",
    "sg:tags":[
        "acupuncture"
    ],
    "wof:name":"White Lotus Natural Medicine",
    "wof:placetype":"venue"
},
  "geometry": {"coordinates":[-82.63856199999999,27.799422],"type":"Point"}
}