{
  "type": "Feature",
  "properties": {
    "iso:country":"US",
    "sg:address":"4081 Forest Hill Dr",
    "sg:city":"Hollywood",
    "sg:classifiers":[
        {
            "category":"Freight",
            "type":"Transportation"
        }
    ],
    "sg:phone":"+1 954 431 6675",
    "sg:postcode":"33026",
    "sg:province":"FL",
    "sg:tags":[
        "arrangement"
    ],
    "wof:name":"Satcom Transport Inc",
    "wof:placetype":"venue"
},
  "geometry": {"coordinates":[-80.30073400000001,26.042598],"type":"Point"}
}