{
  "type": "Feature",
  "properties": {
    "iso:country":"US",
    "sg:address":"1941 NE 34th Ct",
    "sg:city":"Pompano Beach",
    "sg:classifiers":[
        {
            "category":"Retail",
            "subcategory":"Auto Repair",
            "type":"Services"
        }
    ],
    "sg:phone":"+1 954 942 4950",
    "sg:postcode":"33064",
    "sg:province":"FL",
    "sg:tags":[
        "automotive"
    ],
    "wof:name":"Lighthouse Auto Repair Center",
    "wof:placetype":"venue"
},
  "geometry": {"coordinates":[-80.097425,26.273214],"type":"Point"}
}