{
  "type": "Feature",
  "properties": {
    "addr:full":"8363 Ramona Blvd W Jacksonville FL 32221",
    "addr:housenumber":"8363",
    "addr:postcode":"32221",
    "addr:street":"Ramona Blvd W",
    "iso:country":"US",
    "sg:address":"8363 Ramona Blvd W",
    "sg:city":"Jacksonville",
    "sg:classifiers":[
        {
            "category":"Food & Beverages",
            "subcategory":"Groceries & Convenience Stores",
            "type":"Retail Goods"
        }
    ],
    "sg:phone":"+1 904 781 6996",
    "sg:postcode":"32221",
    "sg:province":"FL",
    "wof:name":"Normans Food Mart",
    "wof:placetype":"venue"
},
  "geometry": {"coordinates":[-81.788111,30.31356],"type":"Point"}
}