{
  "type": "Feature",
  "properties": {
    "iso:country":"US",
    "sg:address":"5900 SW 42nd Pl",
    "sg:city":"Davie",
    "sg:classifiers":[
        {
            "category":"Retail",
            "subcategory":"Auto Repair",
            "type":"Services"
        }
    ],
    "sg:phone":"+1 954 727 1690",
    "sg:postcode":"33314",
    "sg:province":"FL",
    "sg:tags":[
        "repairing",
        "automobile",
        "service-equipment",
        "supply"
    ],
    "wof:name":"Custom Parts Enterprises",
    "wof:placetype":"venue"
},
  "geometry": {"coordinates":[-80.225182,26.0688],"type":"Point"}
}