{
  "type": "Feature",
  "properties": {
    "iso:country":"US",
    "sg:address":"4430 E Hwy 316",
    "sg:city":"Citra",
    "sg:classifiers":[
        {
            "category":"Building & Trades",
            "subcategory":"Construction",
            "type":"Services"
        }
    ],
    "sg:phone":"+1 352 595 5624",
    "sg:postcode":"32113",
    "sg:province":"FL",
    "sg:tags":[
        "general",
        "contractor"
    ],
    "wof:name":"Greg Watson Building & Contr",
    "wof:placetype":"venue"
},
  "geometry": {"coordinates":[-82.07219000000001,29.361151],"type":"Point"}
}