{
  "type": "Feature",
  "properties": {
    "iso:country":"US",
    "sg:address":"5130 Main St",
    "sg:city":"New Port Richey",
    "sg:classifiers":[
        {
            "category":"Home & Garden",
            "subcategory":"Building Materials",
            "type":"Retail Goods"
        }
    ],
    "sg:phone":"+1 727 848 1499",
    "sg:postcode":"34652",
    "sg:province":"FL",
    "sg:tags":[
        "builder",
        "cabinet"
    ],
    "wof:name":"Prime Mica & Wood Design Ctr",
    "wof:placetype":"venue"
},
  "geometry": {"coordinates":[-82.73021300000001,28.249874],"type":"Point"}
}