{
  "type": "Feature",
  "properties": {
    "iso:country":"US",
    "sg:address":"197 S Federal Hwy",
    "sg:city":"Boca Raton",
    "sg:classifiers":[
        {
            "category":"Restaurant",
            "type":"Food & Drink"
        }
    ],
    "sg:menulink":"http://www.allmenus.com/fl/boca-raton/21521-salad-creations/menu/",
    "sg:phone":"+1 561 417 6996",
    "sg:postcode":"33432",
    "sg:province":"FL",
    "sg:tags":[
        "soup",
        "american",
        "salad"
    ],
    "wof:name":"Salad Creations",
    "wof:placetype":"venue"
},
  "geometry": {"coordinates":[-80.08645799999999,26.348034],"type":"Point"}
}