{
  "type": "Feature",
  "properties": {
    "iso:country":"US",
    "sg:address":"4986 73rd Ave N",
    "sg:city":"Pinellas Park",
    "sg:classifiers":[
        {
            "category":"Manufacturing",
            "subcategory":"Metals",
            "type":"Manufacturing & Wholesale Goods"
        }
    ],
    "sg:phone":"+1 727 527 0224",
    "sg:postcode":"33781",
    "sg:province":"FL",
    "sg:tags":[
        "coating"
    ],
    "wof:name":"Refurbit",
    "wof:placetype":"venue"
},
  "geometry": {"coordinates":[-82.700322,27.838215],"type":"Point"}
}