{
  "type": "Feature",
  "properties": {
    "iso:country":"US",
    "sg:address":"8080 NW 10th St Apt 5",
    "sg:city":"Miami",
    "sg:classifiers":[
        {
            "category":"Building & Trades",
            "subcategory":"Equipment Rental",
            "type":"Services"
        }
    ],
    "sg:phone":"+1 305 260 0506",
    "sg:postcode":"33126",
    "sg:province":"FL",
    "sg:tags":[
        "contractors'"
    ],
    "wof:name":"Horsepower Service",
    "wof:placetype":"venue"
},
  "geometry": {"coordinates":[-80.324082,25.780284],"type":"Point"}
}