{
  "type": "Feature",
  "properties": {
    "iso:country":"US",
    "sg:address":"6610 Riverview Blvd",
    "sg:city":"Bradenton",
    "sg:classifiers":[
        {
            "category":"Communications",
            "subcategory":"Film & Video Production",
            "type":"Services"
        }
    ],
    "sg:phone":"+1 941 792 1292",
    "sg:postcode":"34209",
    "sg:province":"FL",
    "sg:tags":[
        "motion"
    ],
    "wof:name":"Bandon Enterprises Inc",
    "wof:placetype":"venue"
},
  "geometry": {"coordinates":[-82.628877,27.512314],"type":"Point"}
}