{
  "type": "Feature",
  "properties": {
    "iso:country":"US",
    "sg:address":"140 Piper Blvd",
    "sg:city":"Port Orange",
    "sg:classifiers":[
        {
            "category":"Health Services",
            "subcategory":"Doctor",
            "type":"Services"
        }
    ],
    "sg:phone":"+1 386 322 8767",
    "sg:postcode":"32128",
    "sg:province":"FL",
    "sg:tags":[
        "physician",
        "surgeon"
    ],
    "wof:name":"Spruce Creek Flight Physicals",
    "wof:placetype":"venue"
},
  "geometry": {"coordinates":[-81.046845,29.079083],"type":"Point"}
}