{
  "type": "Feature",
  "properties": {
    "iso:country":"US",
    "sg:address":"4549 Courtney Rd",
    "sg:city":"Saint James City",
    "sg:classifiers":[
        {
            "category":"Building & Trades",
            "subcategory":"Landscaping Services",
            "type":"Services"
        }
    ],
    "sg:phone":"+1 239 282 9244",
    "sg:postcode":"33956",
    "sg:province":"FL",
    "wof:name":"Mike Nabors Lawn Service",
    "wof:placetype":"venue"
},
  "geometry": {"coordinates":[-82.10190299999999,26.579669],"type":"Point"}
}