{
  "type": "Feature",
  "properties": {
    "iso:country":"US",
    "sg:address":"2240 N University Dr",
    "sg:city":"Sunrise",
    "sg:classifiers":[
        {
            "category":"Shopping",
            "subcategory":"Jewelry",
            "type":"Retail Goods"
        },
        {
            "category":"Manufacturing",
            "subcategory":"Jewelry",
            "type":"Manufacturing & Wholesale Goods"
        }
    ],
    "sg:phone":"+1 954 741 4555",
    "sg:postcode":"33322",
    "sg:province":"FL",
    "sg:tags":[
        "stone",
        "designer",
        "semi-precious",
        "precious",
        "jeweler"
    ],
    "wof:name":"American School Of Jewelry",
    "wof:placetype":"venue"
},
  "geometry": {"coordinates":[-80.257048,26.152277],"type":"Point"}
}