{
  "type": "Feature",
  "properties": {
    "iso:country":"US",
    "sg:address":"4302 Gall Blvd",
    "sg:city":"Zephyrhills",
    "sg:classifiers":[
        {
            "category":"Autos & Motor Vehicles",
            "subcategory":"Recreational Vehicle Sales",
            "type":"Retail Goods"
        }
    ],
    "sg:phone":"+1 813 788 6385",
    "sg:postcode":"33542",
    "sg:province":"FL",
    "wof:name":"First Rv & Trailer Supplies",
    "wof:placetype":"venue"
},
  "geometry": {"coordinates":[-82.179861,28.220015],"type":"Point"}
}