{
  "type": "Feature",
  "properties": {
    "addr:full":"1681 SE 4th Ct Deerfield Beach FL 33441",
    "addr:housenumber":"1681",
    "addr:postcode":"33441",
    "addr:street":"Se 4Th Ct",
    "iso:country":"US",
    "sg:address":"1681 SE 4th Ct",
    "sg:city":"Deerfield Beach",
    "sg:classifiers":[
        {
            "category":"Retail",
            "subcategory":"Repair Shop",
            "type":"Services"
        }
    ],
    "sg:phone":"+1 954 974 8557",
    "sg:postcode":"33441",
    "sg:province":"FL",
    "sg:tags":[
        "refrigeration",
        "contractor"
    ],
    "wof:name":"Constructair Technologies",
    "wof:placetype":"venue"
},
  "geometry": {"coordinates":[-80.083961,26.312211],"type":"Point"}
}