{
  "type": "Feature",
  "properties": {
    "iso:country":"US",
    "sg:address":"1701 Ringling Blvd",
    "sg:city":"Sarasota",
    "sg:classifiers":[
        {
            "category":"Building & Trades",
            "subcategory":"Construction",
            "type":"Services"
        }
    ],
    "sg:phone":"+1 941 955 5253",
    "sg:postcode":"34236",
    "sg:province":"FL",
    "sg:tags":[
        "paving",
        "contractor"
    ],
    "wof:name":"Semington Pavers LLC",
    "wof:placetype":"venue"
},
  "geometry": {"coordinates":[-82.535455,27.335051],"type":"Point"}
}