{
  "type": "Feature",
  "properties": {
    "addr:full":"3650 NW 82nd Ave Ste 307 Doral FL 33166",
    "addr:housenumber":"3650",
    "addr:postcode":"33166",
    "addr:street":"Nw 82Nd Ave Ste 307",
    "iso:country":"US",
    "sg:address":"3650 NW 82nd Ave Ste 307",
    "sg:city":"Doral",
    "sg:classifiers":[
        {
            "category":"Personal",
            "subcategory":"Psychics & Astrologers",
            "type":"Services"
        }
    ],
    "sg:phone":"+1 305 718 8811",
    "sg:postcode":"33166",
    "sg:province":"FL",
    "sg:tags":[
        "therapist",
        "respiratory"
    ],
    "wof:name":"Scj Enterprises Inc",
    "wof:placetype":"venue"
},
  "geometry": {"coordinates":[-80.329334,25.808474],"type":"Point"}
}