{
  "type": "Feature",
  "properties": {
    "addr:full":"558 Genius Dr Winter Park FL 32789",
    "addr:housenumber":"558",
    "addr:postcode":"32789",
    "addr:street":"Genius Dr",
    "iso:country":"US",
    "sg:address":"558 Genius Dr",
    "sg:city":"Winter Park",
    "sg:classifiers":[
        {
            "category":"Shopping",
            "subcategory":"Gifts & Souvenirs",
            "type":"Retail Goods"
        }
    ],
    "sg:phone":"+1 407 644 1545",
    "sg:postcode":"32789",
    "sg:province":"FL",
    "sg:tags":[
        "shop"
    ],
    "wof:name":"Park Avenue Gallery",
    "wof:placetype":"venue"
},
  "geometry": {"coordinates":[-81.33248,28.589163],"type":"Point"}
}