{
  "type": "Feature",
  "properties": {
    "iso:country":"US",
    "sg:address":"1609 SW 5th Ct",
    "sg:city":"Fort Lauderdale",
    "sg:classifiers":[
        {
            "category":"Home & Garden",
            "subcategory":"Building Materials",
            "type":"Retail Goods"
        }
    ],
    "sg:phone":"+1 954 527 5053",
    "sg:postcode":"33312",
    "sg:province":"FL",
    "wof:name":"Group Contracting Services",
    "wof:placetype":"venue"
},
  "geometry": {"coordinates":[-80.163983,26.115521],"type":"Point"}
}