{
  "type": "Feature",
  "properties": {
    "iso:country":"US",
    "sg:address":"14657 SW 56th St",
    "sg:city":"Miami",
    "sg:classifiers":[
        {
            "category":"Food & Beverages",
            "subcategory":"Liquor & Beverages",
            "type":"Retail Goods"
        }
    ],
    "sg:phone":"+1 305 221 5151",
    "sg:postcode":"33175",
    "sg:province":"FL",
    "sg:tags":[
        "alcoholic"
    ],
    "wof:name":"Mega Discount Liquors #1",
    "wof:placetype":"venue"
},
  "geometry": {"coordinates":[-80.43024699999999,25.713958],"type":"Point"}
}