{
  "type": "Feature",
  "properties": {
    "iso:country":"US",
    "sg:address":"1424 Old Dixie Hwy",
    "sg:city":"Vero Beach",
    "sg:classifiers":[
        {
            "category":"Professional",
            "type":"Services"
        }
    ],
    "sg:phone":"+1 772 770 1333",
    "sg:postcode":"32960",
    "sg:province":"FL",
    "sg:tags":[
        "establishment"
    ],
    "wof:name":"Vero Pavillion LLC",
    "wof:placetype":"venue"
},
  "geometry": {"coordinates":[-80.39600299999999,27.628998],"type":"Point"}
}