{
  "type": "Feature",
  "properties": {
    "iso:country":"US",
    "sg:address":"506 Enka Ave",
    "sg:city":"Orlando",
    "sg:classifiers":[
        {
            "category":"Arts & Performance",
            "subcategory":"Theater",
            "type":"Entertainment"
        }
    ],
    "sg:phone":"+1 407 578 1109",
    "sg:postcode":"32835",
    "sg:province":"FL",
    "sg:tags":[
        "entertainer"
    ],
    "sg:website":"www.506crew.com",
    "wof:name":"506 Crew",
    "wof:placetype":"venue"
},
  "geometry": {"coordinates":[-81.472206,28.536505],"type":"Point"}
}