{
  "type": "Feature",
  "properties": {
    "addr:full":"5925 6th St E Bradenton FL 34203",
    "addr:housenumber":"5925",
    "addr:postcode":"34203",
    "addr:street":"6Th St",
    "iso:country":"US",
    "sg:address":"5925 6th St E",
    "sg:city":"Bradenton",
    "sg:classifiers":[
        {
            "category":"Social Services",
            "subcategory":"Child Care",
            "type":"Services"
        }
    ],
    "sg:phone":"+1 941 753 9104",
    "sg:postcode":"34203",
    "sg:province":"FL",
    "wof:name":"Maria's Daycare",
    "wof:placetype":"venue"
},
  "geometry": {"coordinates":[-82.558097,27.435018],"type":"Point"}
}