{
  "type": "Feature",
  "properties": {
    "iso:country":"US",
    "sg:address":"100 Tennessee Ave",
    "sg:city":"St Cloud",
    "sg:classifiers":[
        {
            "category":"Building & Trades",
            "subcategory":"Landscaping Services",
            "type":"Services"
        }
    ],
    "sg:phone":"+1 407 957 4142",
    "sg:postcode":"34769",
    "sg:province":"FL",
    "sg:tags":[
        "lawn",
        "maintenance",
        "grounds"
    ],
    "wof:name":"Kissimmee Valley Lawn Care",
    "wof:placetype":"venue"
},
  "geometry": {"coordinates":[-81.296998,28.258349],"type":"Point"}
}