{
  "type": "Feature",
  "properties": {
    "addr:full":"5441 Caurus Ct Orlando FL 32808",
    "addr:housenumber":"5441",
    "addr:postcode":"32808",
    "addr:street":"Caurus Ct",
    "iso:country":"US",
    "sg:address":"5441 Caurus Ct",
    "sg:city":"Orlando",
    "sg:classifiers":[
        {
            "category":"Building & Trades",
            "subcategory":"Construction",
            "type":"Services"
        }
    ],
    "sg:phone":"+1 407 296 6258",
    "sg:postcode":"32808",
    "sg:province":"FL",
    "sg:tags":[
        "hanging",
        "contractor"
    ],
    "wof:name":"Thomas Murray Painting",
    "wof:placetype":"venue"
},
  "geometry": {"coordinates":[-81.448339,28.610007],"type":"Point"}
}