{
  "type": "Feature",
  "properties": {
    "iso:country":"US",
    "sg:address":"1801 Scirocco Loop",
    "sg:city":"Fort Walton Bch",
    "sg:classifiers":[
        {
            "category":"Building & Trades",
            "subcategory":"Construction",
            "type":"Services"
        }
    ],
    "sg:phone":"+1 850 863 4330",
    "sg:postcode":"32547",
    "sg:province":"FL",
    "sg:tags":[
        "home",
        "improvement"
    ],
    "wof:name":"Jim Davis Home Mntnc & Rprs",
    "wof:placetype":"venue"
},
  "geometry": {"coordinates":[-86.635243,30.461782],"type":"Point"}
}