{
  "type": "Feature",
  "properties": {
    "iso:country":"US",
    "sg:address":"11718 White Bluff Dr",
    "sg:city":"Jacksonville",
    "sg:classifiers":[
        {
            "category":"Retail",
            "subcategory":"Auto Repair",
            "type":"Services"
        }
    ],
    "sg:phone":"+1 904 642 0160",
    "sg:postcode":"32225",
    "sg:province":"FL",
    "sg:tags":[
        "repairing",
        "automobile"
    ],
    "wof:name":"Tailored Mobile Auto Svc",
    "wof:placetype":"venue"
},
  "geometry": {"coordinates":[-81.50616100000001,30.385533],"type":"Point"}
}