{
  "type": "Feature",
  "properties": {
    "iso:country":"US",
    "sg:address":"9973 SE 58th Ave",
    "sg:city":"Belleview",
    "sg:classifiers":[
        {
            "category":"Real Estate",
            "subcategory":"Real Estate Agent",
            "type":"Services"
        }
    ],
    "sg:phone":"+1 352 347 0275",
    "sg:postcode":"34420",
    "sg:province":"FL",
    "wof:name":"Haywood Realty & Auction Co",
    "wof:placetype":"venue"
},
  "geometry": {"coordinates":[-82.053455,29.078344],"type":"Point"}
}