{
  "type": "Feature",
  "properties": {
    "iso:country":"US",
    "sg:address":"508 North Dr",
    "sg:city":"Melbourne",
    "sg:classifiers":[
        {
            "category":"Shopping",
            "type":"Retail Goods"
        }
    ],
    "sg:phone":"+1 321 255 9800",
    "sg:postcode":"32931",
    "sg:province":"FL",
    "sg:tags":[
        "medical",
        "supply"
    ],
    "wof:name":"Lake Diabetes Supply Inc",
    "wof:placetype":"venue"
},
  "geometry": {"coordinates":[-80.690093,28.115334],"type":"Point"}
}