{
  "type": "Feature",
  "properties": {
    "iso:country":"US",
    "sg:address":"923 del Prado Blvd S",
    "sg:city":"Cape Coral",
    "sg:classifiers":[
        {
            "category":"Insurance",
            "subcategory":"Insurance Agent",
            "type":"Services"
        }
    ],
    "sg:phone":"+1 239 573 7332",
    "sg:postcode":"33990",
    "sg:province":"FL",
    "wof:name":"Lutheran Brotherhood",
    "wof:placetype":"venue"
},
  "geometry": {"coordinates":[-81.940765,26.636104],"type":"Point"}
}