{
  "type": "Feature",
  "properties": {
    "iso:country":"US",
    "sg:address":"933 Lee Rd",
    "sg:city":"Orlando",
    "sg:classifiers":[
        {
            "category":"Real Estate",
            "subcategory":"Real Estate Services",
            "type":"Services"
        },
        {
            "category":"Real Estate",
            "subcategory":"Real Estate Agent",
            "type":"Services"
        }
    ],
    "sg:phone":"+1 407 294 9959",
    "sg:postcode":"32810",
    "sg:province":"FL",
    "sg:tags":[
        "buyer",
        "broker"
    ],
    "wof:name":"Residential Real Estate Law",
    "wof:placetype":"venue"
},
  "geometry": {"coordinates":[-81.39409999999999,28.606496],"type":"Point"}
}