{
  "type": "Feature",
  "properties": {
    "iso:country":"US",
    "sg:address":"3960 Old Sunbeam Rd",
    "sg:city":"Jacksonville",
    "sg:classifiers":[
        {
            "category":"Real Estate",
            "subcategory":"Real Estate Operator",
            "type":"Services"
        }
    ],
    "sg:phone":"+1 904 262 3454",
    "sg:postcode":"32257",
    "sg:province":"FL",
    "sg:tags":[
        "apartment"
    ],
    "wof:name":"Mandarin Trace Apartments",
    "wof:placetype":"venue"
},
  "geometry": {"coordinates":[-81.612871,30.20531],"type":"Point"}
}