{
  "type": "Feature",
  "properties": {
    "iso:country":"US",
    "sg:address":"1101 Brickell Ave # 313",
    "sg:city":"Miami",
    "sg:classifiers":[
        {
            "category":"Professional",
            "subcategory":"Computer Services",
            "type":"Services"
        }
    ],
    "sg:phone":"+1 305 731 2433",
    "sg:postcode":"33131",
    "sg:province":"FL",
    "sg:tags":[
        "repair",
        "equipment-service"
    ],
    "wof:name":"Computer Repair Miami FL - Geeks Mobile",
    "wof:placetype":"venue"
},
  "geometry": {"coordinates":[-80.191351,25.763338],"type":"Point"}
}