{
  "type": "Feature",
  "properties": {
    "iso:country":"US",
    "sg:address":"611 Minnesota St",
    "sg:city":"Lake Worth",
    "sg:classifiers":[
        {
            "category":"Real Estate",
            "subcategory":"Real Estate Operator",
            "type":"Services"
        }
    ],
    "sg:phone":"+1 561 588 5422",
    "sg:postcode":"33462",
    "sg:province":"FL",
    "sg:tags":[
        "building",
        "nonresidential"
    ],
    "wof:name":"Florida Properties LLC",
    "wof:placetype":"venue"
},
  "geometry": {"coordinates":[-80.057438,26.586217],"type":"Point"}
}