{
  "type": "Feature",
  "properties": {
    "iso:country":"US",
    "sg:address":"10877 SW 132nd Circle Ct",
    "sg:city":"Miami",
    "sg:classifiers":[
        {
            "category":"Wholesale",
            "subcategory":"Durable Goods & Equipment",
            "type":"Manufacturing & Wholesale Goods"
        }
    ],
    "sg:phone":"+1 305 207 6058",
    "sg:postcode":"33186",
    "sg:province":"FL",
    "sg:tags":[
        "exporter"
    ],
    "wof:name":"Osorio Brothers Corp",
    "wof:placetype":"venue"
},
  "geometry": {"coordinates":[-80.409049,25.666637],"type":"Point"}
}