{
  "type": "Feature",
  "properties": {
    "iso:country":"US",
    "sg:address":"19910 Jodi Dr",
    "sg:city":"Lutz",
    "sg:classifiers":[
        {
            "category":"Building & Trades",
            "subcategory":"Construction",
            "type":"Services"
        }
    ],
    "sg:phone":"+1 813 948 2217",
    "sg:postcode":"33558",
    "sg:province":"FL",
    "sg:tags":[
        "house"
    ],
    "wof:name":"Fields Construction",
    "wof:placetype":"venue"
},
  "geometry": {"coordinates":[-82.47864800000001,28.169923],"type":"Point"}
}