{
  "type": "Feature",
  "properties": {
    "iso:country":"US",
    "sg:address":"2125 SE Aneci St",
    "sg:city":"Port Saint Lucie",
    "sg:classifiers":[
        {
            "category":"Shopping",
            "subcategory":"Pharmacy",
            "type":"Retail Goods"
        }
    ],
    "sg:phone":"+1 772 878 8583",
    "sg:postcode":"34984",
    "sg:province":"FL",
    "wof:name":"Rexall Showcase Intl",
    "wof:placetype":"venue"
},
  "geometry": {"coordinates":[-80.335837,27.277908],"type":"Point"}
}