{
  "type": "Feature",
  "properties": {
    "iso:country":"US",
    "sg:address":"2404 Oak Landing Dr",
    "sg:city":"Brandon",
    "sg:classifiers":[
        {
            "category":"Banks & Credit Unions",
            "subcategory":"Investment Brokerage",
            "type":"Services"
        }
    ],
    "sg:phone":"+1 813 685 6315",
    "sg:postcode":"33511",
    "sg:province":"FL",
    "sg:tags":[
        "security"
    ],
    "wof:name":"Housevestors Inc",
    "wof:placetype":"venue"
},
  "geometry": {"coordinates":[-82.26764300000001,27.909517],"type":"Point"}
}