{
  "type": "Feature",
  "properties": {
    "addr:full":"7106 Berrywood Ln Jacksonville FL 32277",
    "addr:housenumber":"7106",
    "addr:postcode":"32277",
    "addr:street":"Berrywood Ln",
    "iso:country":"US",
    "sg:address":"7106 Berrywood Ln",
    "sg:city":"Jacksonville",
    "sg:classifiers":[
        {
            "category":"Home & Garden",
            "subcategory":"Carpets & Floor Coverings",
            "type":"Retail Goods"
        }
    ],
    "sg:phone":"+1 904 762 0534",
    "sg:postcode":"32277",
    "sg:province":"FL",
    "wof:name":"Ben & Jack Majic Floor",
    "wof:placetype":"venue"
},
  "geometry": {"coordinates":[-81.57817900000001,30.354391],"type":"Point"}
}