{
  "type": "Feature",
  "properties": {
    "addr:full":"5401 Southern Comfort Blvd Tampa FL 33634",
    "addr:housenumber":"5401",
    "addr:postcode":"33634",
    "addr:street":"Southern Comfort Blvd",
    "iso:country":"US",
    "sg:address":"5401 Southern Comfort Blvd",
    "sg:city":"Tampa",
    "sg:classifiers":[
        {
            "category":"Freight",
            "type":"Transportation"
        }
    ],
    "sg:phone":"+1 813 882 8466",
    "sg:postcode":"33634",
    "sg:province":"FL",
    "sg:tags":[
        "warehouse"
    ],
    "wof:name":"Ecuamerica International Trnsp",
    "wof:placetype":"venue"
},
  "geometry": {"coordinates":[-82.54222300000001,27.996748],"type":"Point"}
}