{
  "type": "Feature",
  "properties": {
    "iso:country":"US",
    "sg:address":"1333 Osprey Ave",
    "sg:city":"Naples",
    "sg:classifiers":[
        {
            "category":"Building & Trades",
            "subcategory":"Landscaping Services",
            "type":"Services"
        }
    ],
    "sg:phone":"+1 239 775 5332",
    "sg:postcode":"34102",
    "sg:province":"FL",
    "sg:tags":[
        "tree"
    ],
    "wof:name":"Stumps R Us",
    "wof:placetype":"venue"
},
  "geometry": {"coordinates":[-81.784622,26.136504],"type":"Point"}
}