{
  "type": "Feature",
  "properties": {
    "iso:country":"US",
    "sg:address":"250 Brent Ln",
    "sg:city":"Pensacola",
    "sg:classifiers":[
        {
            "category":"Organizations",
            "subcategory":"Religious Organization",
            "type":"Services"
        }
    ],
    "sg:phone":"+1 850 479 6575",
    "sg:postcode":"32503",
    "sg:province":"FL",
    "wof:name":"Campus Church",
    "wof:placetype":"venue"
},
  "geometry": {"coordinates":[-87.231453,30.471057],"type":"Point"}
}