{
  "type": "Feature",
  "properties": {
    "iso:country":"US",
    "sg:address":"413 Dixie Hwy",
    "sg:city":"Auburndale",
    "sg:classifiers":[
        {
            "category":"Building & Trades",
            "subcategory":"Construction",
            "type":"Services"
        }
    ],
    "sg:phone":"+1 863 967 2763",
    "sg:postcode":"33823",
    "sg:province":"FL",
    "sg:tags":[
        "roofing",
        "contractor"
    ],
    "wof:name":"Quality Roofing Co",
    "wof:placetype":"venue"
},
  "geometry": {"coordinates":[-81.818879,28.073516],"type":"Point"}
}