{
  "type": "Feature",
  "properties": {
    "iso:country":"US",
    "sg:address":"1308 Drexel Ave",
    "sg:city":"Miami Beach",
    "sg:classifiers":[
        {
            "category":"Real Estate",
            "subcategory":"Real Estate Agent",
            "type":"Services"
        }
    ],
    "sg:phone":"+1 305 674 4495",
    "sg:postcode":"33139",
    "sg:province":"FL",
    "sg:tags":[
        "management"
    ],
    "wof:name":"Dejavu Property",
    "wof:placetype":"venue"
},
  "geometry": {"coordinates":[-80.133028,25.785285],"type":"Point"}
}