{
  "type": "Feature",
  "properties": {
    "addr:full":"5283 Neff Lake Rd Brooksville FL 34601",
    "addr:housenumber":"5283",
    "addr:postcode":"34601",
    "addr:street":"Neff Lake Rd",
    "iso:country":"US",
    "sg:address":"5283 Neff Lake Rd",
    "sg:city":"Brooksville",
    "sg:classifiers":[
        {
            "category":"Social Services",
            "type":"Services"
        }
    ],
    "sg:phone":"+1 352 544 2322",
    "sg:postcode":"34601",
    "sg:province":"FL",
    "sg:tags":[
        "human"
    ],
    "wof:name":"ARC  The",
    "wof:placetype":"venue"
},
  "geometry": {"coordinates":[-82.319693,28.509667],"type":"Point"}
}