{
  "type": "Feature",
  "properties": {
    "addr:full":"148 N Parsons Ave Brandon FL 33510",
    "addr:housenumber":"148",
    "addr:postcode":"33510",
    "addr:street":"N Parsons Ave",
    "iso:country":"US",
    "sg:address":"148 N Parsons Ave",
    "sg:city":"Brandon",
    "sg:classifiers":[
        {
            "category":"Retail",
            "subcategory":"Repair Shop",
            "type":"Services"
        }
    ],
    "sg:phone":"+1 813 685 1664",
    "sg:postcode":"33510",
    "sg:province":"FL",
    "sg:tags":[
        "electronic"
    ],
    "wof:name":"Video Exchange Unlimited",
    "wof:placetype":"venue"
},
  "geometry": {"coordinates":[-82.28588499999999,27.93979],"type":"Point"}
}