{
  "type": "Feature",
  "properties": {
    "addr:full":"1855 Wilbur Ave Vero Beach FL 32960",
    "addr:housenumber":"1855",
    "addr:postcode":"32960",
    "addr:street":"Wilbur Ave",
    "iso:country":"US",
    "sg:address":"1855 Wilbur Ave",
    "sg:city":"Vero Beach",
    "sg:classifiers":[
        {
            "category":"Building & Trades",
            "subcategory":"Electrical",
            "type":"Services"
        }
    ],
    "sg:phone":"+1 772 569 9909",
    "sg:postcode":"32960",
    "sg:province":"FL",
    "sg:tags":[
        "electric",
        "contractor"
    ],
    "wof:name":"Daniel Electrical Contractors",
    "wof:placetype":"venue"
},
  "geometry": {"coordinates":[-80.39487200000001,27.635627],"type":"Point"}
}