{
  "type": "Feature",
  "properties": {
    "iso:country":"US",
    "sg:address":"20 Cathedral Pl",
    "sg:city":"St Augustine",
    "sg:classifiers":[
        {
            "category":"Shopping",
            "subcategory":"Clothing, Apparel, & Fashions",
            "type":"Retail Goods"
        }
    ],
    "sg:phone":"+1 904 823 0709",
    "sg:postcode":"32084",
    "sg:province":"FL",
    "sg:tags":[
        "t"
    ],
    "wof:name":"Old City Gift Shop",
    "wof:placetype":"venue"
},
  "geometry": {"coordinates":[-81.311065,29.892668],"type":"Point"}
}