{
  "type": "Feature",
  "properties": {
    "addr:full":"140 S Elm Ave Pahokee FL 33476",
    "addr:housenumber":"140",
    "addr:postcode":"33476",
    "addr:street":"S Elm Ave",
    "iso:country":"US",
    "sg:address":"140 S Elm Ave",
    "sg:city":"Pahokee",
    "sg:classifiers":[
        {
            "category":"Building & Trades",
            "subcategory":"Construction",
            "type":"Services"
        }
    ],
    "sg:phone":"+1 561 924 7767",
    "sg:postcode":"33476",
    "sg:province":"FL",
    "sg:tags":[
        "house"
    ],
    "wof:name":"Mark Lewis",
    "wof:placetype":"venue"
},
  "geometry": {"coordinates":[-80.660059,26.823463],"type":"Point"}
}