{
  "type": "Feature",
  "properties": {
    "iso:country":"US",
    "sg:address":"2470 S Parkview Ave",
    "sg:city":"Orange City",
    "sg:classifiers":[
        {
            "category":"Insurance",
            "subcategory":"Insurance Agent",
            "type":"Services"
        }
    ],
    "sg:phone":"+1 386 775 4705",
    "sg:postcode":"32763",
    "sg:province":"FL",
    "wof:name":"Mid Florida Crop Insurance Ser",
    "wof:placetype":"venue"
},
  "geometry": {"coordinates":[-81.294287,28.921341],"type":"Point"}
}