{
  "type": "Feature",
  "properties": {
    "iso:country":"US",
    "sg:address":"6677 Old Bagdad Hwy",
    "sg:city":"Milton",
    "sg:classifiers":[
        {
            "category":"Building & Trades",
            "subcategory":"Construction",
            "type":"Services"
        }
    ],
    "sg:phone":"+1 850 626 1941",
    "sg:postcode":"32583",
    "sg:province":"FL",
    "sg:tags":[
        "contractor"
    ],
    "wof:name":"Surfside Pools",
    "wof:placetype":"venue"
},
  "geometry": {"coordinates":[-87.044703,30.59968],"type":"Point"}
}