{
  "type": "Feature",
  "properties": {
    "iso:country":"US",
    "sg:address":"2032 John Anderson Dr",
    "sg:city":"Ormond Beach",
    "sg:classifiers":[
        {
            "category":"Health Services",
            "subcategory":"Clinic",
            "type":"Services"
        }
    ],
    "sg:phone":"+1 386 290 8424",
    "sg:postcode":"32176",
    "sg:province":"FL",
    "wof:name":"Alvin E Smith",
    "wof:placetype":"venue"
},
  "geometry": {"coordinates":[-81.071155,29.342518],"type":"Point"}
}