{
  "type": "Feature",
  "properties": {
    "addr:full":"14810 Griffin Rd Fort Lauderdale FL 33331",
    "addr:housenumber":"14810",
    "addr:postcode":"33331",
    "addr:street":"Griffin Rd",
    "iso:country":"US",
    "sg:address":"14810 Griffin Rd",
    "sg:city":"Fort Lauderdale",
    "sg:classifiers":[
        {
            "category":"Autos & Motor Vehicles",
            "subcategory":"Fuel & Gas Station",
            "type":"Retail Goods"
        }
    ],
    "sg:phone":"+1 954 252 0100",
    "sg:postcode":"33331",
    "sg:province":"FL",
    "sg:tags":[
        "station",
        "gasoline"
    ],
    "wof:name":"Shell",
    "wof:placetype":"venue"
},
  "geometry": {"coordinates":[-80.346166,26.062864],"type":"Point"}
}