{
  "type": "Feature",
  "properties": {
    "iso:country":"US",
    "sg:address":"5726 Deer Hollow Trl",
    "sg:city":"Sarasota",
    "sg:classifiers":[
        {
            "category":"Building & Trades",
            "subcategory":"Construction",
            "type":"Services"
        }
    ],
    "sg:phone":"+1 941 377 8161",
    "sg:postcode":"34232",
    "sg:province":"FL",
    "sg:tags":[
        "hanging",
        "contractor"
    ],
    "wof:name":"Donna Flanagan",
    "wof:placetype":"venue"
},
  "geometry": {"coordinates":[-82.453565,27.348301],"type":"Point"}
}