{
  "type": "Feature",
  "properties": {
    "addr:full":"2450 NW 6th Ct Pompano Beach FL 33069",
    "addr:housenumber":"2450",
    "addr:postcode":"33069",
    "addr:street":"Nw 6Th Ct",
    "iso:country":"US",
    "sg:address":"2450 NW 6th Ct",
    "sg:city":"Pompano Beach",
    "sg:classifiers":[
        {
            "category":"Building & Trades",
            "subcategory":"Construction",
            "type":"Services"
        }
    ],
    "sg:phone":"+1 954 975 7575",
    "sg:postcode":"33069",
    "sg:province":"FL",
    "wof:name":"Goodrum Paving",
    "wof:placetype":"venue"
},
  "geometry": {"coordinates":[-80.158863,26.237492],"type":"Point"}
}