{
  "type": "Feature",
  "properties": {
    "iso:country":"US",
    "sg:address":"11812 Classic Lake Way",
    "sg:city":"Tampa",
    "sg:classifiers":[
        {
            "category":"Personal",
            "type":"Services"
        }
    ],
    "sg:phone":"+1 813 770 4502",
    "sg:postcode":"33635",
    "sg:province":"FL",
    "sg:tags":[
        "mover"
    ],
    "sg:website":"http://www.thesmoothestmove.com",
    "wof:name":"THE SMOOTHER MOVER L.L.C",
    "wof:placetype":"venue"
},
  "geometry": {"coordinates":[-82.61485,28.031509],"type":"Point"}
}