{
  "type": "Feature",
  "properties": {
    "iso:country":"US",
    "sg:address":"3684 N Wickham Rd",
    "sg:city":"Melbourne",
    "sg:classifiers":[
        {
            "category":"Professional",
            "subcategory":"Lawyer & Legal Services",
            "type":"Services"
        }
    ],
    "sg:phone":"+1 321 751 8110",
    "sg:postcode":"32935",
    "sg:province":"FL",
    "sg:tags":[
        "attorney"
    ],
    "wof:name":"Joan Berry Nassar Pa Attorney",
    "wof:placetype":"venue"
},
  "geometry": {"coordinates":[-80.672033,28.163022],"type":"Point"}
}