{
  "type": "Feature",
  "properties": {
    "iso:country":"US",
    "sg:address":"3385 Pan American Dr",
    "sg:city":"Miami",
    "sg:classifiers":[
        {
            "category":"Retail",
            "subcategory":"Repair Shop",
            "type":"Services"
        }
    ],
    "sg:phone":"+1 305 858 7375",
    "sg:postcode":"33133",
    "sg:province":"FL",
    "wof:name":"Alex Acosta Marine Repair",
    "wof:placetype":"venue"
},
  "geometry": {"coordinates":[-80.23446800000001,25.728253],"type":"Point"}
}