{
  "type": "Feature",
  "properties": {
    "addr:full":"10801 NW 33rd St Doral FL 33172",
    "addr:housenumber":"10801",
    "addr:postcode":"33172",
    "addr:street":"Nw 33Rd St",
    "iso:country":"US",
    "sg:address":"10801 NW 33rd St",
    "sg:city":"Doral",
    "sg:classifiers":[
        {
            "category":"Professional",
            "subcategory":"Management & Consulting",
            "type":"Services"
        }
    ],
    "sg:phone":"+1 305 599 8955",
    "sg:postcode":"33172",
    "sg:province":"FL",
    "sg:tags":[
        "consultant",
        "safety",
        "shoe",
        "store"
    ],
    "wof:name":"Abaco Industrial Safety",
    "wof:placetype":"venue"
},
  "geometry": {"coordinates":[-80.371498,25.8041],"type":"Point"}
}