{
  "type": "Feature",
  "properties": {
    "iso:country":"US",
    "sg:address":"1660 Malcolm Pointe Dr",
    "sg:city":"Winter Garden",
    "sg:classifiers":[
        {
            "category":"Building & Trades",
            "subcategory":"Construction",
            "type":"Services"
        }
    ],
    "sg:phone":"+1 407 877 8083",
    "sg:postcode":"34787",
    "sg:province":"FL",
    "sg:tags":[
        "home",
        "builder"
    ],
    "wof:name":"Adams Homes",
    "wof:placetype":"venue"
},
  "geometry": {"coordinates":[-81.56210799999999,28.588996],"type":"Point"}
}