{
  "type": "Feature",
  "properties": {
    "addr:full":"6861 SW 196th Ave Fort Lauderdale FL 33332",
    "addr:housenumber":"6861",
    "addr:postcode":"33332",
    "addr:street":"Sw 196Th Ave",
    "iso:country":"US",
    "sg:address":"6861 SW 196th Ave",
    "sg:city":"Fort Lauderdale",
    "sg:classifiers":[
        {
            "category":"Professional",
            "type":"Services"
        }
    ],
    "sg:phone":"+1 954 252 5245",
    "sg:postcode":"33332",
    "sg:province":"FL",
    "wof:name":"Recol Aluminum Products Inc",
    "wof:placetype":"venue"
},
  "geometry": {"coordinates":[-80.409429,26.031568],"type":"Point"}
}