{
  "type": "Feature",
  "properties": {
    "addr:full":"3255 Cypress Gardens Rd Winter Haven FL 33884",
    "addr:housenumber":"3255",
    "addr:postcode":"33884",
    "addr:street":"Cypress Gardens Rd",
    "iso:country":"US",
    "sg:address":"3255 Cypress Gardens Rd",
    "sg:city":"Winter Haven",
    "sg:classifiers":[
        {
            "category":"Home & Garden",
            "subcategory":"Furniture",
            "type":"Retail Goods"
        }
    ],
    "sg:phone":"+1 863 324 3810",
    "sg:postcode":"33884",
    "sg:province":"FL",
    "sg:tags":[
        "patio",
        "accessory"
    ],
    "wof:name":"Leisure Wrld Outdoor Furn More",
    "wof:placetype":"venue"
},
  "geometry": {"coordinates":[-81.68198099999999,27.996805],"type":"Point"}
}