{
  "type": "Feature",
  "properties": {
    "addr:full":"8501 W Miss Maggie Dr Homosassa FL 34448",
    "addr:housenumber":"8501",
    "addr:postcode":"34448",
    "addr:street":"W Miss Maggie Dr",
    "iso:country":"US",
    "sg:address":"8501 W Miss Maggie Dr",
    "sg:city":"Homosassa",
    "sg:classifiers":[
        {
            "category":"Travel",
            "subcategory":"Campground",
            "type":"Entertainment"
        },
        {
            "category":"Shopping",
            "subcategory":"Bicycles & Sporting Goods",
            "type":"Retail Goods"
        }
    ],
    "sg:phone":"+1 352 382 2081",
    "sg:postcode":"34448",
    "sg:province":"FL",
    "sg:tags":[
        "camp",
        "mari",
        "trailer",
        "fishing"
    ],
    "wof:name":"Chassahowitzka River Lodge",
    "wof:placetype":"venue"
},
  "geometry": {"coordinates":[-82.57401299999999,28.71387],"type":"Point"}
}