{
  "type": "Feature",
  "properties": {
    "iso:country":"US",
    "sg:address":"6901 US Hwy 192",
    "sg:city":"Melbourne",
    "sg:classifiers":[
        {
            "category":"Shopping",
            "subcategory":"Bicycles & Sporting Goods",
            "type":"Retail Goods"
        }
    ],
    "sg:phone":"+1 321 723 2179",
    "sg:postcode":"32904",
    "sg:province":"FL",
    "wof:name":"Holly Camp Fishing",
    "wof:placetype":"venue"
},
  "geometry": {"coordinates":[-80.73792899999999,28.078856],"type":"Point"}
}