{
  "type": "Feature",
  "properties": {
    "addr:full":"8641 Baypine Rd Jacksonville FL 32256",
    "addr:housenumber":"8641",
    "addr:postcode":"32256",
    "addr:street":"Baypine Rd",
    "iso:country":"US",
    "sg:address":"8641 Baypine Rd",
    "sg:city":"Jacksonville",
    "sg:classifiers":[
        {
            "category":"Professional",
            "subcategory":"Management & Consulting",
            "type":"Services"
        }
    ],
    "sg:phone":"+1 904 737 6411",
    "sg:postcode":"32256",
    "sg:province":"FL",
    "sg:tags":[
        "communications",
        "consultant"
    ],
    "wof:name":"Lighthouse Telecommunications",
    "wof:placetype":"venue"
},
  "geometry": {"coordinates":[-81.577855,30.227694],"type":"Point"}
}