{
  "type": "Feature",
  "properties": {
    "iso:country":"US",
    "sg:address":"3950 NW 62nd Ave",
    "sg:city":"Gainesville",
    "sg:classifiers":[
        {
            "category":"Real Estate",
            "subcategory":"Real Estate Services",
            "type":"Services"
        },
        {
            "category":"Real Estate",
            "subcategory":"Real Estate Agent",
            "type":"Services"
        }
    ],
    "sg:phone":"+1 352 494 2969",
    "sg:postcode":"32653",
    "sg:province":"FL",
    "sg:tags":[
        "management"
    ],
    "wof:name":"Bagby Real Estate",
    "wof:placetype":"venue"
},
  "geometry": {"coordinates":[-82.382437,29.710978],"type":"Point"}
}