{
  "type": "Feature",
  "properties": {
    "addr:full":"505 D St Saint Augustine FL 32080",
    "addr:housenumber":"505",
    "addr:postcode":"32080",
    "addr:street":"D St",
    "iso:country":"US",
    "sg:address":"505 D St",
    "sg:city":"Saint Augustine",
    "sg:classifiers":[
        {
            "category":"Professional",
            "subcategory":"Engineering",
            "type":"Services"
        }
    ],
    "sg:phone":"+1 904 471 3295",
    "sg:postcode":"32080",
    "sg:province":"FL",
    "wof:name":"DK Designs Inc",
    "wof:placetype":"venue"
},
  "geometry": {"coordinates":[-81.27301,29.842575],"type":"Point"}
}