{
  "type": "Feature",
  "properties": {
    "addr:full":"104 E Fletcher Ave Tampa FL 33612",
    "addr:housenumber":"104",
    "addr:postcode":"33612",
    "addr:street":"E Fletcher Ave",
    "iso:country":"US",
    "sg:address":"104 E Fletcher Ave",
    "sg:city":"Tampa",
    "sg:classifiers":[
        {
            "category":"Health Services",
            "subcategory":"Doctor",
            "type":"Services"
        }
    ],
    "sg:phone":"+1 813 968 4998",
    "sg:postcode":"33612",
    "sg:province":"FL",
    "sg:tags":[
        "dentist"
    ],
    "wof:name":"Michael L Vacher DDS Inc",
    "wof:placetype":"venue"
},
  "geometry": {"coordinates":[-82.456722,28.06937],"type":"Point"}
}