{
  "type": "Feature",
  "properties": {
    "iso:country":"US",
    "sg:address":"1100 NW 54th St",
    "sg:city":"Miami",
    "sg:classifiers":[
        {
            "category":"Restaurant",
            "type":"Food & Drink"
        }
    ],
    "sg:menulink":"http://www.allmenus.com/fl/miami/169223-wendys/menu/",
    "sg:phone":"+1 305 756 1511",
    "sg:postcode":"33127",
    "sg:province":"FL",
    "sg:tags":[
        "burger",
        "american",
        "soup"
    ],
    "wof:name":"Wendy's",
    "wof:placetype":"venue"
},
  "geometry": {"coordinates":[-80.21517299999999,25.823828],"type":"Point"}
}