{
  "type": "Feature",
  "properties": {
    "iso:country":"US",
    "sg:address":"880 NW 13th St",
    "sg:city":"Boca Raton",
    "sg:classifiers":[
        {
            "category":"Retail",
            "subcategory":"Auto Repair",
            "type":"Services"
        }
    ],
    "sg:phone":"+1 561 391 4026",
    "sg:postcode":"33486",
    "sg:province":"FL",
    "sg:tags":[
        "body",
        "automobile",
        "painting"
    ],
    "wof:name":"Pilates-Method Of Body Condi",
    "wof:placetype":"venue"
},
  "geometry": {"coordinates":[-80.10286499999999,26.361291],"type":"Point"}
}