{
  "type": "Feature",
  "properties": {
    "iso:country":"US",
    "sg:address":"1455 Rockledge Dr",
    "sg:city":"Rockledge",
    "sg:classifiers":[
        {
            "category":"Building & Trades",
            "subcategory":"Construction",
            "type":"Services"
        }
    ],
    "sg:phone":"+1 321 631 6647",
    "sg:postcode":"32955",
    "sg:province":"FL",
    "sg:tags":[
        "carpentry",
        "contractor"
    ],
    "wof:name":"Thomas Hastings Carpentry",
    "wof:placetype":"venue"
},
  "geometry": {"coordinates":[-80.709751,28.31829],"type":"Point"}
}