{
  "type": "Feature",
  "properties": {
    "iso:country":"US",
    "sg:address":"604 43rd St W",
    "sg:city":"Bradenton",
    "sg:classifiers":[
        {
            "category":"Retail",
            "subcategory":"Funeral Services",
            "type":"Services"
        }
    ],
    "sg:phone":"+1 941 758 7788",
    "sg:postcode":"34209",
    "sg:province":"FL",
    "sg:tags":[
        "director"
    ],
    "wof:name":"Brown & Sons Funeral Home",
    "wof:placetype":"venue"
},
  "geometry": {"coordinates":[-82.603953,27.494909],"type":"Point"}
}