{
  "type": "Feature",
  "properties": {
    "addr:full":"1339 E Vine St Kissimmee FL 34744",
    "addr:housenumber":"1339",
    "addr:postcode":"34744",
    "addr:street":"E Vine St",
    "iso:country":"US",
    "sg:address":"1339 E Vine St",
    "sg:city":"Kissimmee",
    "sg:classifiers":[
        {
            "category":"Home & Garden",
            "subcategory":"Carpets & Floor Coverings",
            "type":"Retail Goods"
        }
    ],
    "sg:phone":"+1 407 931 2630",
    "sg:postcode":"34744",
    "sg:province":"FL",
    "sg:tags":[
        "dealer",
        "rug"
    ],
    "wof:name":"Valencia Tile & Carpet Inc",
    "wof:placetype":"venue"
},
  "geometry": {"coordinates":[-81.387327,28.304255],"type":"Point"}
}