{
  "type": "Feature",
  "properties": {
    "addr:full":"4910 14th St W Bradenton FL 34207",
    "addr:housenumber":"4910",
    "addr:postcode":"34207",
    "addr:street":"14Th St W",
    "iso:country":"US",
    "sg:address":"4910 14th St W",
    "sg:city":"Bradenton",
    "sg:classifiers":[
        {
            "category":"Banks & Credit Unions",
            "subcategory":"Bank",
            "type":"Services"
        }
    ],
    "sg:phone":"+1 941 756 9999",
    "sg:postcode":"34207",
    "sg:province":"FL",
    "sg:tags":[
        "loan",
        "real estate"
    ],
    "wof:name":"AAAA Mortgage Loans",
    "wof:placetype":"venue"
},
  "geometry": {"coordinates":[-82.57546600000001,27.453438],"type":"Point"}
}