{
  "type": "Feature",
  "properties": {
    "iso:country":"US",
    "sg:address":"16160 Mount Abbey Way",
    "sg:city":"Fort Myers",
    "sg:classifiers":[
        {
            "category":"Real Estate",
            "subcategory":"Real Estate Agent",
            "type":"Services"
        }
    ],
    "sg:phone":"+1 239 454 6283",
    "sg:postcode":"33908",
    "sg:province":"FL",
    "wof:name":"Sheila Finn-Bouchard",
    "wof:placetype":"venue"
},
  "geometry": {"coordinates":[-81.89083599999999,26.507292],"type":"Point"}
}