{
  "type": "Feature",
  "properties": {
    "addr:full":"7483 NW 4th St Fort Lauderdale FL 33317",
    "addr:housenumber":"7483",
    "addr:postcode":"33317",
    "addr:street":"Nw 4Th St",
    "iso:country":"US",
    "sg:address":"7483 NW 4th St",
    "sg:city":"Fort Lauderdale",
    "sg:classifiers":[
        {
            "category":"Professional",
            "subcategory":"Detective & Security Services",
            "type":"Services"
        }
    ],
    "sg:phone":"+1 954 327 3427",
    "sg:postcode":"33317",
    "sg:province":"FL",
    "sg:tags":[
        "system"
    ],
    "wof:name":"Guardsmark Llc",
    "wof:placetype":"venue"
},
  "geometry": {"coordinates":[-80.249751,26.126932],"type":"Point"}
}