{
  "type": "Feature",
  "properties": {
    "iso:country":"US",
    "sg:address":"500 SW 6th Ct",
    "sg:city":"Pompano Beach",
    "sg:classifiers":[
        {
            "category":"Retail",
            "subcategory":"Auto Repair",
            "type":"Services"
        }
    ],
    "sg:phone":"+1 954 783 4335",
    "sg:postcode":"33060",
    "sg:province":"FL",
    "sg:tags":[
        "repairing",
        "automobile"
    ],
    "wof:name":"Zack & Tino's Auto Ctr Corp",
    "wof:placetype":"venue"
},
  "geometry": {"coordinates":[-80.133612,26.221632],"type":"Point"}
}