{
  "type": "Feature",
  "properties": {
    "addr:full":"1238 S US Hwy 1 Vero Beach FL 32962",
    "addr:housenumber":"1238",
    "addr:postcode":"32962",
    "addr:street":"S Us Hwy 1",
    "iso:country":"US",
    "sg:address":"1238 S US Hwy 1",
    "sg:city":"Vero Beach",
    "sg:classifiers":[
        {
            "category":"Banks & Credit Unions",
            "subcategory":"Bank",
            "type":"Services"
        }
    ],
    "sg:phone":"+1 772 770 3737",
    "sg:postcode":"32962",
    "sg:province":"FL",
    "wof:name":"Riverside National Bank",
    "wof:placetype":"venue"
},
  "geometry": {"coordinates":[-80.375456,27.578607],"type":"Point"}
}