{
  "type": "Feature",
  "properties": {
    "iso:country":"US",
    "sg:address":"1714 W 68th St",
    "sg:city":"Hialeah",
    "sg:classifiers":[
        {
            "category":"Shopping",
            "subcategory":"Crafts & Fabrics",
            "type":"Retail Goods"
        }
    ],
    "sg:phone":"+1 305 362 8300",
    "sg:postcode":"33014",
    "sg:province":"FL",
    "sg:tags":[
        "shop"
    ],
    "wof:name":"Popular Fabrics",
    "wof:placetype":"venue"
},
  "geometry": {"coordinates":[-80.31654,25.884077],"type":"Point"}
}