{
  "type": "Feature",
  "properties": {
    "addr:full":"1108 Solana Ave Winter Park FL 32789",
    "addr:housenumber":"1108",
    "addr:postcode":"32789",
    "addr:street":"Solana Ave",
    "iso:country":"US",
    "sg:address":"1108 Solana Ave",
    "sg:city":"Winter Park",
    "sg:classifiers":[
        {
            "category":"Home & Garden",
            "subcategory":"Building Materials",
            "type":"Retail Goods"
        },
        {
            "category":"Building & Trades",
            "subcategory":"Construction",
            "type":"Services"
        }
    ],
    "sg:phone":"+1 407 645 1613",
    "sg:postcode":"32789",
    "sg:province":"FL",
    "sg:tags":[
        "refinishing",
        "flooring",
        "floor",
        "laying",
        "resurfacing",
        "wood",
        "stairs"
    ],
    "wof:name":"Southeast Hardwood Flr & Stair",
    "wof:placetype":"venue"
},
  "geometry": {"coordinates":[-81.362511,28.607989],"type":"Point"}
}