{
  "type": "Feature",
  "properties": {
    "iso:country":"US",
    "sg:address":"5881 Shalimar Dr",
    "sg:city":"Punta Gorda",
    "sg:classifiers":[
        {
            "category":"Organizations",
            "subcategory":"Religious Organization",
            "type":"Services"
        }
    ],
    "sg:phone":"+1 941 575 4144",
    "sg:postcode":"33982",
    "sg:province":"FL",
    "sg:tags":[
        "church"
    ],
    "wof:name":"Spirit Of Life Christian",
    "wof:placetype":"venue"
},
  "geometry": {"coordinates":[-81.982354,26.948022],"type":"Point"}
}