{
  "type": "Feature",
  "properties": {
    "iso:country":"US",
    "sg:address":"7277 N Atlantic Ave",
    "sg:city":"Cape Canaveral",
    "sg:classifiers":[
        {
            "category":"Manufacturing",
            "subcategory":"Electronics",
            "type":"Manufacturing & Wholesale Goods"
        }
    ],
    "sg:phone":"+1 321 784 4427",
    "sg:postcode":"32920",
    "sg:province":"FL",
    "sg:tags":[
        "picture",
        "television",
        "mfg",
        "communication",
        "tube",
        "equipment",
        "electron"
    ],
    "wof:name":"Vdc Display Systems",
    "wof:placetype":"venue"
},
  "geometry": {"coordinates":[-80.605654,28.382384],"type":"Point"}
}