{
  "type": "Feature",
  "properties": {
    "addr:full":"6701 38th Ave N Saint Petersburg FL 33710",
    "addr:housenumber":"6701",
    "addr:postcode":"33710",
    "addr:street":"38Th Ave N",
    "iso:country":"US",
    "sg:address":"6701 38th Ave N",
    "sg:city":"Saint Petersburg",
    "sg:classifiers":[
        {
            "category":"Health Services",
            "subcategory":"Health Practitioner",
            "type":"Services"
        }
    ],
    "sg:phone":"+1 727 344 8690",
    "sg:postcode":"33710",
    "sg:province":"FL",
    "wof:name":"Jade Tree Wellness Center Inc",
    "wof:placetype":"venue"
},
  "geometry": {"coordinates":[-82.730204,27.806421],"type":"Point"}
}