{
  "type": "Feature",
  "properties": {
    "addr:full":"115 Palm Dr East Palatka FL 32131",
    "addr:housenumber":"115",
    "addr:postcode":"32131",
    "addr:street":"Palm Dr East",
    "iso:country":"US",
    "sg:address":"115 Palm Dr",
    "sg:city":"East Palatka",
    "sg:classifiers":[
        {
            "category":"Professional",
            "subcategory":"Employment Agencies",
            "type":"Services"
        }
    ],
    "sg:phone":"+1 386 325 1200",
    "sg:postcode":"32131",
    "sg:province":"FL",
    "wof:name":"Elite Bartending",
    "wof:placetype":"venue"
},
  "geometry": {"coordinates":[-81.62490099999999,29.681446],"type":"Point"}
}