{
  "type": "Feature",
  "properties": {
    "iso:country":"US",
    "sg:address":"801 3rd St S",
    "sg:city":"St Petersburg",
    "sg:classifiers":[
        {
            "category":"Education",
            "subcategory":"Vocational School",
            "type":"Public Place"
        }
    ],
    "sg:phone":"+1 727 821 9494",
    "sg:postcode":"33701",
    "sg:province":"FL",
    "sg:tags":[
        "specialized",
        "television",
        "medium",
        "radio",
        "broadcasting"
    ],
    "sg:website":"www.poynter.org",
    "wof:name":"Poynter Institute For Media St",
    "wof:placetype":"venue"
},
  "geometry": {"coordinates":[-82.636995,27.761715],"type":"Point"}
}