{
  "type": "Feature",
  "properties": {
    "iso:country":"US",
    "sg:address":"4537 Edison Ave",
    "sg:city":"Jacksonville",
    "sg:classifiers":[
        {
            "category":"Professional",
            "subcategory":"Computer Services",
            "type":"Services"
        }
    ],
    "sg:phone":"+1 904 379 0075",
    "sg:postcode":"32254",
    "sg:province":"FL",
    "sg:tags":[
        "home",
        "consulting",
        "page",
        "dev",
        "internet"
    ],
    "wof:name":"Jacksonvilles Web Source",
    "wof:placetype":"venue"
},
  "geometry": {"coordinates":[-81.72357,30.322567],"type":"Point"}
}