{
  "type": "Feature",
  "properties": {
    "iso:country":"US",
    "sg:address":"19814 SW 80th Ct",
    "sg:city":"Miami",
    "sg:classifiers":[
        {
            "category":"Professional",
            "subcategory":"Management & Consulting",
            "type":"Services"
        }
    ],
    "sg:phone":"+1 305 252 7882",
    "sg:postcode":"33189",
    "sg:province":"FL",
    "sg:tags":[
        "party",
        "planning"
    ],
    "wof:name":"Preferred Palate",
    "wof:placetype":"venue"
},
  "geometry": {"coordinates":[-80.32209899999999,25.581667],"type":"Point"}
}