{
  "type": "Feature",
  "properties": {
    "iso:country":"US",
    "sg:address":"9737 Variety Tree Rd",
    "sg:city":"Leesburg",
    "sg:classifiers":[
        {
            "category":"Building & Trades",
            "subcategory":"Landscaping Services",
            "type":"Services"
        }
    ],
    "sg:phone":"+1 352 326 8251",
    "sg:postcode":"34788",
    "sg:province":"FL",
    "wof:name":"Patrick Miller Enterprises",
    "wof:placetype":"venue"
},
  "geometry": {"coordinates":[-81.794146,28.868177],"type":"Point"}
}