{
  "type": "Feature",
  "properties": {
    "iso:country":"US",
    "sg:address":"18100 Royal Tree Pkwy",
    "sg:city":"Naples",
    "sg:classifiers":[
        {
            "category":"Sports & Exercise",
            "subcategory":"Golf",
            "type":"Entertainment"
        }
    ],
    "sg:phone":"+1 239 732 0034",
    "sg:postcode":"34114",
    "sg:province":"FL",
    "sg:tags":[
        "course",
        "public"
    ],
    "wof:name":"Naples Golf Club South",
    "wof:placetype":"venue"
},
  "geometry": {"coordinates":[-81.628738,26.01502],"type":"Point"}
}