{
  "type": "Feature",
  "properties": {
    "iso:country":"US",
    "sg:address":"9833 SW 117th Pl",
    "sg:city":"Miami",
    "sg:classifiers":[
        {
            "category":"Professional",
            "subcategory":"Computer Services",
            "type":"Services"
        }
    ],
    "sg:phone":"+1 305 274 7942",
    "sg:postcode":"33186",
    "sg:province":"FL",
    "sg:tags":[
        "internet"
    ],
    "wof:name":"Millennium Publishing Inc",
    "wof:placetype":"venue"
},
  "geometry": {"coordinates":[-80.385265,25.676293],"type":"Point"}
}