{
  "type": "Feature",
  "properties": {
    "iso:country":"US",
    "sg:address":"678 NW 112th St",
    "sg:city":"Miami",
    "sg:classifiers":[
        {
            "category":"Communications",
            "subcategory":"Film & Video Production",
            "type":"Services"
        }
    ],
    "sg:phone":"+1 305 758 9200",
    "sg:postcode":"33168",
    "sg:province":"FL",
    "sg:tags":[
        "recording",
        "service-sound"
    ],
    "wof:name":"Keep It Hundred Records",
    "wof:placetype":"venue"
},
  "geometry": {"coordinates":[-80.21002799999999,25.87739],"type":"Point"}
}