{
  "type": "Feature",
  "properties": {
    "iso:country":"US",
    "sg:address":"8700 N Kendall Dr",
    "sg:city":"Miami",
    "sg:classifiers":[
        {
            "category":"Health Services",
            "subcategory":"Doctor",
            "type":"Services"
        }
    ],
    "sg:phone":"+1 305 271 5189",
    "sg:postcode":"33176",
    "sg:province":"FL",
    "sg:tags":[
        "physician",
        "family",
        "reconstructive",
        "practice",
        "surgeons",
        "cosmetic",
        "plastic",
        "medicine",
        "surgery",
        "hand",
        "surgeon"
    ],
    "sg:website":"http://www.drjoellevin.com",
    "wof:name":"Levin, Joel M MD",
    "wof:placetype":"venue"
},
  "geometry": {"coordinates":[-80.333549,25.68796],"type":"Point"}
}