{
  "type": "Feature",
  "properties": {
    "iso:country":"US",
    "sg:address":"39410 Co Rd 54",
    "sg:city":"Zephyrhills",
    "sg:classifiers":[
        {
            "category":"Building & Trades",
            "subcategory":"Landscaping Services",
            "type":"Services"
        }
    ],
    "sg:phone":"+1 813 783 2025",
    "sg:postcode":"33542",
    "sg:province":"FL",
    "sg:tags":[
        "tree"
    ],
    "wof:name":"Bushwackers",
    "wof:placetype":"venue"
},
  "geometry": {"coordinates":[-82.16386300000001,28.251813],"type":"Point"}
}