{
  "type": "Feature",
  "properties": {
    "iso:country":"US",
    "sg:address":"3550 49th St",
    "sg:city":"Vero Beach",
    "sg:classifiers":[
        {
            "category":"Building & Trades",
            "subcategory":"Construction",
            "type":"Services"
        }
    ],
    "sg:phone":"+1 772 770 5244",
    "sg:postcode":"32967",
    "sg:province":"FL",
    "sg:tags":[
        "heavy"
    ],
    "wof:name":"Utility Services",
    "wof:placetype":"venue"
},
  "geometry": {"coordinates":[-80.42155,27.68242],"type":"Point"}
}