{
  "type": "Feature",
  "properties": {
    "addr:full":"3800 Acline Rd Punta Gorda FL 33950",
    "addr:housenumber":"3800",
    "addr:postcode":"33950",
    "addr:street":"Acline Rd",
    "iso:country":"US",
    "sg:address":"3800 Acline Rd",
    "sg:city":"Punta Gorda",
    "sg:classifiers":[
        {
            "category":"Building & Trades",
            "subcategory":"Construction",
            "type":"Services"
        }
    ],
    "sg:phone":"+1 941 639 1818",
    "sg:postcode":"33950",
    "sg:province":"FL",
    "sg:tags":[
        "contractor"
    ],
    "wof:name":"Dale R Baker Construction",
    "wof:placetype":"venue"
},
  "geometry": {"coordinates":[-82.006186,26.884046],"type":"Point"}
}