{
  "type": "Feature",
  "properties": {
    "iso:country":"US",
    "sg:address":"1481 NW North River Dr",
    "sg:city":"Miami",
    "sg:classifiers":[
        {
            "category":"Professional",
            "subcategory":"Lawyer & Legal Services",
            "type":"Services"
        }
    ],
    "sg:phone":"+1 305 324 6020",
    "sg:postcode":"33125",
    "sg:province":"FL",
    "wof:name":"Masztal Carl L Atty",
    "wof:placetype":"venue"
},
  "geometry": {"coordinates":[-80.22020000000001,25.785999],"type":"Point"}
}