{
  "type": "Feature",
  "properties": {
    "addr:full":"2983 Vineland Rd Kissimmee FL 34746",
    "addr:housenumber":"2983",
    "addr:postcode":"34746",
    "addr:street":"Vineland Rd",
    "iso:country":"US",
    "sg:address":"2983 Vineland Rd",
    "sg:city":"Kissimmee",
    "sg:classifiers":[
        {
            "category":"Building & Trades",
            "subcategory":"Landscaping Services",
            "type":"Services"
        }
    ],
    "sg:phone":"+1 407 284 9481",
    "sg:postcode":"34746",
    "sg:province":"FL",
    "sg:tags":[
        "lawn",
        "tree",
        "arborist"
    ],
    "wof:name":"Arbor Quest Group Inc",
    "wof:placetype":"venue"
},
  "geometry": {"coordinates":[-81.479647,28.336388],"type":"Point"}
}