{
  "type": "Feature",
  "properties": {
    "iso:country":"US",
    "sg:address":"333 Racetrack Rd NW",
    "sg:city":"Fort Walton Bch",
    "sg:classifiers":[
        {
            "category":"Professional",
            "subcategory":"Employment Agencies",
            "type":"Services"
        }
    ],
    "sg:phone":"+1 850 862 1466",
    "sg:postcode":"32547",
    "sg:province":"FL",
    "sg:tags":[
        "opportunity"
    ],
    "sg:website":"www.erperp.com",
    "wof:name":"ERPERP.COM",
    "wof:placetype":"venue"
},
  "geometry": {"coordinates":[-86.628112,30.449274],"type":"Point"}
}