{
  "type": "Feature",
  "properties": {
    "iso:country":"US",
    "sg:address":"7800 SW 87th Ave",
    "sg:city":"Miami",
    "sg:classifiers":[
        {
            "category":"Health Services",
            "subcategory":"Doctor",
            "type":"Services"
        },
        {
            "category":"Health Services",
            "subcategory":"Dentist",
            "type":"Services"
        }
    ],
    "sg:phone":"+1 305 274 7474",
    "sg:postcode":"33173",
    "sg:province":"FL",
    "sg:tags":[
        "dentists-oral",
        "physician",
        "maxillofacial",
        "surgeons",
        "surgery",
        "oral"
    ],
    "wof:name":"Diamond Andrea DMD",
    "wof:placetype":"venue"
},
  "geometry": {"coordinates":[-80.334,25.696899],"type":"Point"}
}