{
  "type": "Feature",
  "properties": {
    "addr:full":"8561 NW 54th Ct Lauderhill FL 33351",
    "addr:housenumber":"8561",
    "addr:postcode":"33351",
    "addr:street":"Nw 54Th Ct",
    "iso:country":"US",
    "sg:address":"8561 NW 54th Ct",
    "sg:city":"Lauderhill",
    "sg:classifiers":[
        {
            "category":"Coffee & Tea",
            "type":"Food & Drink"
        },
        {
            "category":"Restaurant",
            "type":"Food & Drink"
        }
    ],
    "sg:phone":"+1 954 749 9888",
    "sg:postcode":"33351",
    "sg:province":"FL",
    "sg:tags":[
        "espresso"
    ],
    "wof:name":"Ivis Cuban Cafe",
    "wof:placetype":"venue"
},
  "geometry": {"coordinates":[-80.263936,26.192209],"type":"Point"}
}