{
  "type": "Feature",
  "properties": {
    "iso:country":"US",
    "sg:address":"508 Dr Martin Luther King Jr Blvd",
    "sg:city":"Seffner",
    "sg:classifiers":[
        {
            "category":"Retail",
            "subcategory":"Auto Repair",
            "type":"Services"
        }
    ],
    "sg:phone":"+1 813 571 5870",
    "sg:postcode":"33584",
    "sg:province":"FL",
    "sg:tags":[
        "repairing",
        "automobile"
    ],
    "wof:name":"Bullet Auto Svc",
    "wof:placetype":"venue"
},
  "geometry": {"coordinates":[-82.282082,27.98149],"type":"Point"}
}