{
  "type": "Feature",
  "properties": {
    "addr:full":"524 E College Ave Tallahassee FL 32301",
    "addr:housenumber":"524",
    "addr:postcode":"32301",
    "addr:street":"E College Ave",
    "iso:country":"US",
    "sg:address":"524 E College Ave",
    "sg:city":"Tallahassee",
    "sg:classifiers":[
        {
            "category":"Professional",
            "subcategory":"Lawyer & Legal Services",
            "type":"Services"
        }
    ],
    "sg:phone":"+1 850 222 1961",
    "sg:postcode":"32301",
    "sg:province":"FL",
    "wof:name":"Gievers PA",
    "wof:placetype":"venue"
},
  "geometry": {"coordinates":[-84.275854,30.440817],"type":"Point"}
}