{
  "type": "Feature",
  "properties": {
    "iso:country":"US",
    "sg:address":"1607 N Cove Blvd",
    "sg:city":"Panama City",
    "sg:classifiers":[
        {
            "category":"Autos & Motor Vehicles",
            "subcategory":"Auto Supplies",
            "type":"Retail Goods"
        }
    ],
    "sg:phone":"+1 850 215 1777",
    "sg:postcode":"32405",
    "sg:province":"FL",
    "sg:tags":[
        "automobile",
        "stereo",
        "radio"
    ],
    "wof:name":"Walker's Audio & Security",
    "wof:placetype":"venue"
},
  "geometry": {"coordinates":[-85.65020800000001,30.178592],"type":"Point"}
}