{
  "type": "Feature",
  "properties": {
    "addr:full":"6835 Caroline St Milton FL 32570",
    "addr:housenumber":"6835",
    "addr:postcode":"32570",
    "addr:street":"Caroline St",
    "iso:country":"US",
    "sg:address":"6835 Caroline St",
    "sg:city":"Milton",
    "sg:classifiers":[
        {
            "category":"Shopping",
            "subcategory":"Computers & Home Electronics",
            "type":"Retail Goods"
        }
    ],
    "sg:phone":"+1 850 983 2270",
    "sg:postcode":"32570",
    "sg:province":"FL",
    "sg:tags":[
        "equipment",
        "dealer"
    ],
    "wof:name":"Panther Computers",
    "wof:placetype":"venue"
},
  "geometry": {"coordinates":[-87.03828799999999,30.622102],"type":"Point"}
}