{
  "type": "Feature",
  "properties": {
    "iso:country":"US",
    "sg:address":"202 Royal Palm Beach Blvd",
    "sg:city":"Royal Palm Beach",
    "sg:classifiers":[
        {
            "category":"Insurance",
            "subcategory":"Insurance Agent",
            "type":"Services"
        }
    ],
    "sg:phone":"+1 561 798 8203",
    "sg:postcode":"33411",
    "sg:province":"FL",
    "wof:name":"Allstate Insurance",
    "wof:placetype":"venue"
},
  "geometry": {"coordinates":[-80.230039,26.683271],"type":"Point"}
}