{
  "type": "Feature",
  "properties": {
    "iso:country":"US",
    "sg:address":"500 SW 10th Pl",
    "sg:city":"Ocala",
    "sg:classifiers":[
        {
            "category":"Recreation",
            "type":"Entertainment"
        }
    ],
    "sg:phone":"+1 352 732 9779",
    "sg:postcode":"34474",
    "sg:province":"FL",
    "sg:tags":[
        "diving",
        "instruction"
    ],
    "wof:name":"Ocala Dive Ctr Inc",
    "wof:placetype":"venue"
},
  "geometry": {"coordinates":[-82.142664,29.178255],"type":"Point"}
}