{
  "type": "Feature",
  "properties": {
    "addr:full":"4209 W Santiago St Tampa FL 33629",
    "addr:housenumber":"4209",
    "addr:postcode":"33629",
    "addr:street":"W Santiago St",
    "iso:country":"US",
    "sg:address":"4209 W Santiago St",
    "sg:city":"Tampa",
    "sg:classifiers":[
        {
            "category":"Building & Trades",
            "subcategory":"Cleaning & Sanitation",
            "type":"Services"
        }
    ],
    "sg:phone":"+1 813 831 4535",
    "sg:postcode":"33629",
    "sg:province":"FL",
    "sg:tags":[
        "janitor"
    ],
    "wof:name":"Fine Tooth Comb Cleaning Co",
    "wof:placetype":"venue"
},
  "geometry": {"coordinates":[-82.51609000000001,27.919226],"type":"Point"}
}