{
  "type": "Feature",
  "properties": {
    "iso:country":"US",
    "sg:address":"7217 Antoinette Cir",
    "sg:city":"Navarre",
    "sg:classifiers":[
        {
            "category":"Home & Garden",
            "subcategory":"Furniture",
            "type":"Retail Goods"
        }
    ],
    "sg:phone":"+1 850 336 0185",
    "sg:postcode":"32566",
    "sg:province":"FL",
    "sg:tags":[
        "cabinet"
    ],
    "wof:name":"MRH Cabinetry & Woodworks",
    "wof:placetype":"venue"
},
  "geometry": {"coordinates":[-86.920725,30.405205],"type":"Point"}
}