{
  "type": "Feature",
  "properties": {
    "iso:country":"US",
    "sg:address":"593 E Sample Rd",
    "sg:city":"Pompano Beach",
    "sg:classifiers":[
        {
            "category":"Banks & Credit Unions",
            "subcategory":"Bank",
            "type":"Services"
        }
    ],
    "sg:phone":"+1 954 781 1886",
    "sg:postcode":"33064",
    "sg:province":"FL",
    "sg:tags":[
        "money",
        "transfer"
    ],
    "wof:name":"Real Transfer LLC",
    "wof:placetype":"venue"
},
  "geometry": {"coordinates":[-80.11478099999999,26.275307],"type":"Point"}
}