{
  "type": "Feature",
  "properties": {
    "iso:country":"US",
    "sg:address":"4914 Lake Underhill Rd",
    "sg:city":"Orlando",
    "sg:classifiers":[
        {
            "category":"Professional",
            "subcategory":"Lawyer & Legal Services",
            "type":"Services"
        }
    ],
    "sg:phone":"+1 407 306 9442",
    "sg:postcode":"32807",
    "sg:province":"FL",
    "sg:tags":[
        "attorney"
    ],
    "wof:name":"Ameri Legal",
    "wof:placetype":"venue"
},
  "geometry": {"coordinates":[-81.324395,28.538817],"type":"Point"}
}