{
  "type": "Feature",
  "properties": {
    "iso:country":"US",
    "sg:address":"282 Winchester Way",
    "sg:city":"Palm Harbor",
    "sg:classifiers":[
        {
            "category":"Building & Trades",
            "subcategory":"Construction",
            "type":"Services"
        }
    ],
    "sg:phone":"+1 727 786 4433",
    "sg:postcode":"34684",
    "sg:province":"FL",
    "sg:tags":[
        "house"
    ],
    "wof:name":"Christopher Michaels Cnstr",
    "wof:placetype":"venue"
},
  "geometry": {"coordinates":[-82.73410800000001,28.069391],"type":"Point"}
}