{
  "type": "Feature",
  "properties": {
    "iso:country":"US",
    "sg:address":"515 E Main St",
    "sg:city":"Bartow",
    "sg:classifiers":[
        {
            "category":"Professional",
            "subcategory":"Lawyer & Legal Services",
            "type":"Services"
        }
    ],
    "sg:phone":"+1 863 534 3617",
    "sg:postcode":"33830",
    "sg:province":"FL",
    "sg:tags":[
        "attorney",
        "law",
        "family",
        "divorce",
        "practice",
        "criminal"
    ],
    "wof:name":"White Nathaniel Attorney At Law",
    "wof:placetype":"venue"
},
  "geometry": {"coordinates":[-81.83975700000001,27.896451],"type":"Point"}
}