{
  "type": "Feature",
  "properties": {
    "addr:full":"4289 Cypress Ln West Palm Beach FL 33406",
    "addr:housenumber":"4289",
    "addr:postcode":"33406",
    "addr:street":"Cypress Ln",
    "iso:country":"US",
    "sg:address":"4289 Cypress Ln",
    "sg:city":"West Palm Beach",
    "sg:classifiers":[
        {
            "category":"Building & Trades",
            "subcategory":"Electrical",
            "type":"Services"
        }
    ],
    "sg:phone":"+1 561 965 9355",
    "sg:postcode":"33406",
    "sg:province":"FL",
    "sg:tags":[
        "electrical",
        "contractor"
    ],
    "wof:name":"David O Naylor Electric",
    "wof:placetype":"venue"
},
  "geometry": {"coordinates":[-80.109611,26.641664],"type":"Point"}
}