{
  "type": "Feature",
  "properties": {
    "iso:country":"US",
    "sg:address":"2895 Tampa Rd",
    "sg:city":"Palm Harbor",
    "sg:classifiers":[
        {
            "category":"Social Services",
            "subcategory":"Adult Care",
            "type":"Services"
        }
    ],
    "sg:phone":"+1 727 771 1600",
    "sg:postcode":"34684",
    "sg:province":"FL",
    "sg:tags":[
        "home",
        "residential"
    ],
    "wof:name":"Arden Courts",
    "wof:placetype":"venue"
},
  "geometry": {"coordinates":[-82.731255,28.06738],"type":"Point"}
}