{
  "type": "Feature",
  "properties": {
    "addr:full":"5600 Mariner St Ste 122 Tampa FL 33609",
    "addr:housenumber":"5600",
    "addr:postcode":"33609",
    "addr:street":"Mariner St Ste 122",
    "iso:country":"US",
    "sg:address":"5600 Mariner St Ste 122",
    "sg:city":"Tampa",
    "sg:classifiers":[
        {
            "category":"Wholesale",
            "subcategory":"Office Equipment",
            "type":"Manufacturing & Wholesale Goods"
        }
    ],
    "sg:phone":"+1 813 286 2900",
    "sg:postcode":"33609",
    "sg:province":"FL",
    "sg:tags":[
        "dictating",
        "machine",
        "supply"
    ],
    "sg:website":"http://www.powerscribe.com",
    "wof:name":"Dictaphone Corporation",
    "wof:placetype":"venue"
},
  "geometry": {"coordinates":[-82.537086,27.942949],"type":"Point"}
}