{
  "type": "Feature",
  "properties": {
    "iso:country":"US",
    "sg:address":"3349 King George Dr",
    "sg:city":"Orlando",
    "sg:classifiers":[
        {
            "category":"Home & Garden",
            "subcategory":"Building Materials",
            "type":"Retail Goods"
        },
        {
            "category":"Building & Trades",
            "subcategory":"Construction",
            "type":"Services"
        }
    ],
    "sg:phone":"+1 407 470 0571",
    "sg:postcode":"32835",
    "sg:province":"FL",
    "sg:tags":[
        "concrete",
        "staining",
        "contractor"
    ],
    "wof:name":"Elite Custom Concrete Coatings Inc.",
    "wof:placetype":"venue"
},
  "geometry": {"coordinates":[-81.504974,28.505853],"type":"Point"}
}