{
  "type": "Feature",
  "properties": {
    "iso:country":"US",
    "sg:address":"10344 Autumn Valley",
    "sg:city":"Jacksonville",
    "sg:classifiers":[
        {
            "category":"Shopping",
            "type":"Retail Goods"
        }
    ],
    "sg:phone":"+1 904 262 6788",
    "sg:postcode":"32257",
    "sg:province":"FL",
    "sg:tags":[
        "cosmetic",
        "perfume"
    ],
    "wof:name":"Mary Kay Cosmetics",
    "wof:placetype":"venue"
},
  "geometry": {"coordinates":[-81.616793,30.189778],"type":"Point"}
}