{
  "type": "Feature",
  "properties": {
    "addr:full":"636 W Yale St Orlando FL 32804",
    "addr:housenumber":"636",
    "addr:postcode":"32804",
    "addr:street":"W Yale St",
    "iso:country":"US",
    "sg:address":"636 W Yale St",
    "sg:city":"Orlando",
    "sg:classifiers":[
        {
            "category":"Professional",
            "subcategory":"Lawyer & Legal Services",
            "type":"Services"
        }
    ],
    "sg:phone":"+1 407 472 0595",
    "sg:postcode":"32804",
    "sg:province":"FL",
    "sg:tags":[
        "attorney"
    ],
    "wof:name":"Anita L Barber PA",
    "wof:placetype":"venue"
},
  "geometry": {"coordinates":[-81.38713799999999,28.569465],"type":"Point"}
}