{
  "type": "Feature",
  "properties": {
    "addr:full":"661 E Altamonte Dr Ste 120 Altamonte Springs FL 32701",
    "addr:housenumber":"661",
    "addr:postcode":"32701",
    "addr:street":"E Altamonte Dr Ste 120",
    "iso:country":"US",
    "sg:address":"661 E Altamonte Dr Ste 120",
    "sg:city":"Altamonte Springs",
    "sg:classifiers":[
        {
            "category":"Health Services",
            "subcategory":"Doctor",
            "type":"Services"
        }
    ],
    "sg:phone":"+1 407 331 9595",
    "sg:postcode":"32701",
    "sg:province":"FL",
    "wof:name":"Ruskin Craig J MD",
    "wof:placetype":"venue"
},
  "geometry": {"coordinates":[-81.368797,28.664],"type":"Point"}
}