{
  "type": "Feature",
  "properties": {
    "addr:full":"4532 SW 71st Ave Miami FL 33155",
    "addr:housenumber":"4532",
    "addr:postcode":"33155",
    "addr:street":"Sw 71St Ave",
    "iso:country":"US",
    "sg:address":"4532 SW 71st Ave",
    "sg:city":"Miami",
    "sg:classifiers":[
        {
            "category":"Building & Trades",
            "subcategory":"Construction",
            "type":"Services"
        }
    ],
    "sg:phone":"+1 305 662 2214",
    "sg:postcode":"33155",
    "sg:province":"FL",
    "sg:tags":[
        "general",
        "contractor"
    ],
    "wof:name":"Hayden Enterprises Inc",
    "wof:placetype":"venue"
},
  "geometry": {"coordinates":[-80.308864,25.728459],"type":"Point"}
}