{
  "type": "Feature",
  "properties": {
    "iso:country":"US",
    "sg:address":"3220 S US Hwy 1",
    "sg:city":"Fort Pierce",
    "sg:classifiers":[
        {
            "category":"Organizations",
            "subcategory":"Religious Organization",
            "type":"Services"
        }
    ],
    "sg:phone":"+1 772 489 4046",
    "sg:postcode":"34982",
    "sg:province":"FL",
    "wof:name":"End Prophetic Deliverance",
    "wof:placetype":"venue"
},
  "geometry": {"coordinates":[-80.32581999999999,27.408221],"type":"Point"}
}