{
  "type": "Feature",
  "properties": {
    "addr:full":"9941 SW 7th St Pembroke Pines FL 33025",
    "addr:housenumber":"9941",
    "addr:postcode":"33025",
    "addr:street":"Sw 7Th St",
    "iso:country":"US",
    "sg:address":"9941 SW 7th St",
    "sg:city":"Pembroke Pines",
    "sg:classifiers":[
        {
            "category":"Arts & Performance",
            "subcategory":"Theater",
            "type":"Entertainment"
        }
    ],
    "sg:phone":"+1 954 437 6261",
    "sg:postcode":"33025",
    "sg:province":"FL",
    "sg:tags":[
        "live",
        "music"
    ],
    "wof:name":"Darryl Gilbert DJ Retro",
    "wof:placetype":"venue"
},
  "geometry": {"coordinates":[-80.276627,26.002704],"type":"Point"}
}