{
  "type": "Feature",
  "properties": {
    "addr:full":"2460 W 1st Ave Hialeah FL 33010",
    "addr:housenumber":"2460",
    "addr:postcode":"33010",
    "addr:street":"W 1St Ave",
    "iso:country":"US",
    "sg:address":"2460 W 1st Ave",
    "sg:city":"Hialeah",
    "sg:classifiers":[
        {
            "category":"Food & Beverages",
            "subcategory":"Bakery",
            "type":"Retail Goods"
        }
    ],
    "sg:phone":"+1 305 888 8431",
    "sg:postcode":"33010",
    "sg:province":"FL",
    "sg:tags":[
        "baker"
    ],
    "wof:name":"Lisa's Bakery",
    "wof:placetype":"venue"
},
  "geometry": {"coordinates":[-80.284227,25.844056],"type":"Point"}
}