{
  "type": "Feature",
  "properties": {
    "iso:country":"US",
    "sg:address":"6240 N Lockwood Ridge Rd",
    "sg:city":"Sarasota",
    "sg:classifiers":[
        {
            "category":"Restaurant",
            "type":"Food & Drink"
        }
    ],
    "sg:phone":"+1 941 358 1353",
    "sg:postcode":"34243",
    "sg:province":"FL",
    "sg:tags":[
        "eating"
    ],
    "wof:name":"Coach & Horses Brit Pub & Rest",
    "wof:placetype":"venue"
},
  "geometry": {"coordinates":[-82.50554700000001,27.388421],"type":"Point"}
}