{
  "type": "Feature",
  "properties": {
    "iso:country":"US",
    "sg:address":"210 S Kings Ave",
    "sg:city":"Brandon",
    "sg:classifiers":[
        {
            "category":"Shopping",
            "subcategory":"Shoes",
            "type":"Retail Goods"
        }
    ],
    "sg:phone":"+1 813 681 9523",
    "sg:postcode":"33511",
    "sg:province":"FL",
    "wof:name":"Dyeable Shoes Etc",
    "wof:placetype":"venue"
},
  "geometry": {"coordinates":[-82.294011,27.934464],"type":"Point"}
}