{
  "type": "Feature",
  "properties": {
    "addr:full":"1859 Joyce St Sarasota FL 34231",
    "addr:housenumber":"1859",
    "addr:postcode":"34231",
    "addr:street":"Joyce St",
    "iso:country":"US",
    "sg:address":"1859 Joyce St",
    "sg:city":"Sarasota",
    "sg:classifiers":[
        {
            "category":"Sports & Exercise",
            "subcategory":"Race Track",
            "type":"Entertainment"
        }
    ],
    "sg:phone":"+1 941 320 8867",
    "sg:postcode":"34231",
    "sg:province":"FL",
    "sg:tags":[
        "operation",
        "racing",
        "or"
    ],
    "wof:name":"Dont Blink Racing",
    "wof:placetype":"venue"
},
  "geometry": {"coordinates":[-82.494857,27.222916],"type":"Point"}
}