{
  "type": "Feature",
  "properties": {
    "iso:country":"US",
    "sg:address":"2117 Faulk Dr",
    "sg:city":"Tallahassee",
    "sg:classifiers":[
        {
            "category":"Retail",
            "subcategory":"Repair Shop",
            "type":"Services"
        },
        {
            "category":"Building & Trades",
            "subcategory":"Construction",
            "type":"Services"
        }
    ],
    "sg:phone":"+1 850 562 0183",
    "sg:postcode":"32303",
    "sg:province":"FL",
    "sg:tags":[
        "cabinet",
        "carpentry",
        "refinishing",
        "contractor"
    ],
    "wof:name":"A & K Cabinet Restoration",
    "wof:placetype":"venue"
},
  "geometry": {"coordinates":[-84.341853,30.51204],"type":"Point"}
}