{
  "type": "Feature",
  "properties": {
    "iso:country":"US",
    "sg:address":"1002 SW 142nd Ct",
    "sg:city":"Miami",
    "sg:classifiers":[
        {
            "category":"Shopping",
            "type":"Retail Goods"
        }
    ],
    "sg:phone":"+1 305 551 2492",
    "sg:postcode":"33184",
    "sg:province":"FL",
    "sg:tags":[
        "merchandising"
    ],
    "sg:website":"http://www.hectormolina.net",
    "wof:name":"Hector E Molina",
    "wof:placetype":"venue"
},
  "geometry": {"coordinates":[-80.42559,25.757715],"type":"Point"}
}