{
  "type": "Feature",
  "properties": {
    "addr:full":"20510 Marlin Rd Miami FL 33189",
    "addr:housenumber":"20510",
    "addr:postcode":"33189",
    "addr:street":"Marlin Rd",
    "iso:country":"US",
    "sg:address":"20510 Marlin Rd",
    "sg:city":"Miami",
    "sg:classifiers":[
        {
            "category":"Retail",
            "subcategory":"Auto Repair",
            "type":"Services"
        }
    ],
    "sg:phone":"+1 305 253 9223",
    "sg:postcode":"33189",
    "sg:province":"FL",
    "sg:tags":[
        "repairing",
        "automobile"
    ],
    "wof:name":"Neway Auto Svc",
    "wof:placetype":"venue"
},
  "geometry": {"coordinates":[-80.34446800000001,25.574855],"type":"Point"}
}