{
  "type": "Feature",
  "properties": {
    "iso:country":"US",
    "sg:address":"3390 Mary St",
    "sg:city":"Miami",
    "sg:classifiers":[
        {
            "category":"Arts & Performance",
            "subcategory":"Art Gallery",
            "type":"Entertainment"
        },
        {
            "category":"Professional",
            "subcategory":"Art Services",
            "type":"Services"
        }
    ],
    "sg:phone":"+1 305 569 3097",
    "sg:postcode":"33133",
    "sg:province":"FL",
    "sg:tags":[
        "fine",
        "commercial",
        "artist"
    ],
    "wof:name":"Grovehouse Artist",
    "wof:placetype":"venue"
},
  "geometry": {"coordinates":[-80.239418,25.72823],"type":"Point"}
}