{
  "type": "Feature",
  "properties": {
    "iso:country":"US",
    "sg:address":"5386 Broad St",
    "sg:city":"Milton",
    "sg:classifiers":[
        {
            "category":"Health Services",
            "subcategory":"Nursing And Care Facility",
            "type":"Services"
        }
    ],
    "sg:phone":"+1 850 623 4661",
    "sg:postcode":"32570",
    "sg:province":"FL",
    "sg:tags":[
        "skilled"
    ],
    "wof:name":"Santa Rosa Convalescent Center",
    "wof:placetype":"venue"
},
  "geometry": {"coordinates":[-87.03751800000001,30.629496],"type":"Point"}
}