{
  "type": "Feature",
  "properties": {
    "addr:full":"2218 N Dixie Hwy Boca Raton FL 33431",
    "addr:housenumber":"2218",
    "addr:postcode":"33431",
    "addr:street":"N Dixie Hwy",
    "iso:country":"US",
    "sg:address":"2218 N Dixie Hwy",
    "sg:city":"Boca Raton",
    "sg:classifiers":[
        {
            "category":"Professional",
            "subcategory":"Engineering",
            "type":"Services"
        }
    ],
    "sg:phone":"+1 561 417 3996",
    "sg:postcode":"33431",
    "sg:province":"FL",
    "sg:tags":[
        "engineer"
    ],
    "wof:name":"Cornerstone Engineering",
    "wof:placetype":"venue"
},
  "geometry": {"coordinates":[-80.08456700000001,26.369247],"type":"Point"}
}