{
  "type": "Feature",
  "properties": {
    "iso:country":"US",
    "sg:address":"42 Barkley Cir",
    "sg:city":"Fort Myers",
    "sg:classifiers":[
        {
            "category":"Social Services",
            "type":"Services"
        }
    ],
    "sg:phone":"+1 239 277 0646",
    "sg:postcode":"33907",
    "sg:province":"FL",
    "sg:tags":[
        "counselor",
        "marriage",
        "family"
    ],
    "wof:name":"Mary Robinson",
    "wof:placetype":"venue"
},
  "geometry": {"coordinates":[-81.88268100000001,26.587279],"type":"Point"}
}