{
  "type": "Feature",
  "properties": {
    "iso:country":"US",
    "sg:address":"2375 N Canoe Creek Rd",
    "sg:city":"St Cloud",
    "sg:classifiers":[
        {
            "category":"Social Services",
            "subcategory":"Child Care",
            "type":"Services"
        }
    ],
    "sg:phone":"+1 407 891 0353",
    "sg:postcode":"34769",
    "sg:province":"FL",
    "wof:name":"Academy For Kids",
    "wof:placetype":"venue"
},
  "geometry": {"coordinates":[-81.293042,28.233621],"type":"Point"}
}