{
  "type": "Feature",
  "properties": {
    "iso:country":"US",
    "sg:address":"8130 NW 58th St",
    "sg:city":"Doral",
    "sg:classifiers":[
        {
            "category":"Professional",
            "subcategory":"Accounting & Tax Preparation",
            "type":"Services"
        }
    ],
    "sg:phone":"+1 786 336 0683",
    "sg:postcode":"33166",
    "sg:province":"FL",
    "sg:tags":[
        "accountant"
    ],
    "wof:name":"Garcias",
    "wof:placetype":"venue"
},
  "geometry": {"coordinates":[-80.326993,25.826299],"type":"Point"}
}