{
  "type": "Feature",
  "properties": {
    "addr:full":"11562 SW 69th Cir Ocala FL 34476",
    "addr:housenumber":"11562",
    "addr:postcode":"34476",
    "addr:street":"Sw 69Th Cir",
    "iso:country":"US",
    "sg:address":"11562 SW 69th Cir",
    "sg:city":"Ocala",
    "sg:classifiers":[
        {
            "category":"Building & Trades",
            "subcategory":"Construction",
            "type":"Services"
        }
    ],
    "sg:phone":"+1 352 873 6041",
    "sg:postcode":"34476",
    "sg:province":"FL",
    "sg:tags":[
        "concrete",
        "contractor"
    ],
    "wof:name":"Ballard L Smith Clear Coating",
    "wof:placetype":"venue"
},
  "geometry": {"coordinates":[-82.233602,29.057581],"type":"Point"}
}