{
  "type": "Feature",
  "properties": {
    "iso:country":"US",
    "sg:address":"6801 NW 77th Ave",
    "sg:city":"Miami",
    "sg:classifiers":[
        {
            "category":"Manufacturing",
            "subcategory":"Textiles",
            "type":"Manufacturing & Wholesale Goods"
        }
    ],
    "sg:phone":"+1 305 471 5830",
    "sg:postcode":"33166",
    "sg:province":"FL",
    "sg:tags":[
        "tile-wholesale",
        "manufacturer"
    ],
    "wof:name":"Integres Clay Forever",
    "wof:placetype":"venue"
},
  "geometry": {"coordinates":[-80.32163199999999,25.83527],"type":"Point"}
}