{
  "type": "Feature",
  "properties": {
    "iso:country":"US",
    "sg:address":"8299 W Beaver St",
    "sg:city":"Jacksonville",
    "sg:classifiers":[
        {
            "category":"Restaurant",
            "type":"Food & Drink"
        }
    ],
    "sg:phone":"+1 904 695 2133",
    "sg:postcode":"32220",
    "sg:province":"FL",
    "sg:tags":[
        "eating",
        "caterer"
    ],
    "wof:name":"Melissa's Sandwich Shop",
    "wof:placetype":"venue"
},
  "geometry": {"coordinates":[-81.785853,30.322585],"type":"Point"}
}