{
  "type": "Feature",
  "properties": {
    "addr:full":"1341 NW 52nd St Miami FL 33142",
    "addr:housenumber":"1341",
    "addr:postcode":"33142",
    "addr:street":"Nw 52Nd St",
    "iso:country":"US",
    "sg:address":"1341 NW 52nd St",
    "sg:city":"Miami",
    "sg:classifiers":[
        {
            "category":"Building & Trades",
            "subcategory":"Construction",
            "type":"Services"
        }
    ],
    "sg:phone":"+1 305 758 9057",
    "sg:postcode":"33142",
    "sg:province":"FL",
    "sg:tags":[
        "home",
        "improvement"
    ],
    "wof:name":"Luther B Taylor Painting",
    "wof:placetype":"venue"
},
  "geometry": {"coordinates":[-80.21959200000001,25.823183],"type":"Point"}
}