{
  "type": "Feature",
  "properties": {
    "addr:full":"8891 Old Pine Rd Boca Raton FL 33433",
    "addr:housenumber":"8891",
    "addr:postcode":"33433",
    "addr:street":"Old Pine Rd",
    "iso:country":"US",
    "sg:address":"8891 Old Pine Rd",
    "sg:city":"Boca Raton",
    "sg:classifiers":[
        {
            "category":"Shopping",
            "type":"Retail Goods"
        }
    ],
    "sg:phone":"+1 561 451 4218",
    "sg:postcode":"33433",
    "sg:province":"FL",
    "sg:tags":[
        "product",
        "wood"
    ],
    "wof:name":"Donna Wood",
    "wof:placetype":"venue"
},
  "geometry": {"coordinates":[-80.186053,26.350617],"type":"Point"}
}