{
  "type": "Feature",
  "properties": {
    "iso:country":"US",
    "sg:address":"114 Corporation Way",
    "sg:city":"Venice",
    "sg:classifiers":[
        {
            "category":"Wholesale",
            "subcategory":"Construction Materials",
            "type":"Manufacturing & Wholesale Goods"
        }
    ],
    "sg:phone":"+1 941 412 0359",
    "sg:postcode":"34285",
    "sg:province":"FL",
    "wof:name":"Construction Wholesale Inc",
    "wof:placetype":"venue"
},
  "geometry": {"coordinates":[-82.42254699999999,27.085637],"type":"Point"}
}