{
  "type": "Feature",
  "properties": {
    "iso:country":"US",
    "sg:address":"830 Canal St",
    "sg:city":"New Smyrna Beach",
    "sg:classifiers":[
        {
            "category":"Building & Trades",
            "subcategory":"Plumbing",
            "type":"Services"
        }
    ],
    "sg:phone":"+1 386 428 4746",
    "sg:postcode":"32168",
    "sg:province":"FL",
    "sg:tags":[
        "plumbing",
        "contractor"
    ],
    "wof:name":"Lutz Plumbing",
    "wof:placetype":"venue"
},
  "geometry": {"coordinates":[-80.930673,29.021867],"type":"Point"}
}