{
  "type": "Feature",
  "properties": {
    "iso:country":"US",
    "sg:address":"1510 Lakeview Rd",
    "sg:city":"Clearwater",
    "sg:classifiers":[
        {
            "category":"Restaurant",
            "type":"Food & Drink"
        }
    ],
    "sg:phone":"+1 727 443 3738",
    "sg:postcode":"33756",
    "sg:province":"FL",
    "wof:name":"Lakeview Grill & Restaurant",
    "wof:placetype":"venue"
},
  "geometry": {"coordinates":[-82.774503,27.949769],"type":"Point"}
}