{
  "type": "Feature",
  "properties": {
    "addr:full":"4600 W Cypress St Tampa FL 33607",
    "addr:housenumber":"4600",
    "addr:postcode":"33607",
    "addr:street":"W Cypress St",
    "iso:country":"US",
    "sg:address":"4600 W Cypress St",
    "sg:city":"Tampa",
    "sg:classifiers":[
        {
            "category":"Social Services",
            "subcategory":"Adult Care",
            "type":"Services"
        }
    ],
    "sg:phone":"+1 813 978 8500",
    "sg:postcode":"33607",
    "sg:province":"FL",
    "sg:tags":[
        "foster"
    ],
    "wof:name":"National Mentor Healthcare",
    "wof:placetype":"venue"
},
  "geometry": {"coordinates":[-82.523152,27.952285],"type":"Point"}
}