{
  "type": "Feature",
  "properties": {
    "iso:country":"US",
    "sg:address":"3177 W US-90",
    "sg:city":"Lake City",
    "sg:classifiers":[
        {
            "category":"Bars & Pubs",
            "type":"Food & Drink"
        },
        {
            "category":"Bakery",
            "type":"Food & Drink"
        }
    ],
    "sg:menulink":"http://www.allmenus.com/fl/lake-city/49401-sonnys-bar-b-q/menu/",
    "sg:phone":"+1 386 752 1117",
    "sg:postcode":"32055",
    "sg:province":"FL",
    "sg:tags":[
        "barbecue",
        "american",
        "pastry"
    ],
    "wof:name":"Sonny's Bar-B-Q",
    "wof:placetype":"venue"
},
  "geometry": {"coordinates":[-82.679485,30.18],"type":"Point"}
}