{
  "type": "Feature",
  "properties": {
    "addr:full":"11440 N Kendall Dr Miami FL 33176",
    "addr:housenumber":"11440",
    "addr:postcode":"33176",
    "addr:street":"N Kendall Dr",
    "iso:country":"US",
    "sg:address":"11440 N Kendall Dr",
    "sg:city":"Miami",
    "sg:classifiers":[
        {
            "category":"Building & Trades",
            "subcategory":"Construction",
            "type":"Services"
        }
    ],
    "sg:phone":"+1 305 595 1772",
    "sg:postcode":"33176",
    "sg:province":"FL",
    "sg:tags":[
        "contractor"
    ],
    "wof:name":"Kendall Summit",
    "wof:placetype":"venue"
},
  "geometry": {"coordinates":[-80.3629,25.659401],"type":"Point"}
}