{
  "type": "Feature",
  "properties": {
    "iso:country":"US",
    "sg:address":"451 Dixie Hwy",
    "sg:city":"Coral Gables",
    "sg:classifiers":[
        {
            "category":"Banks & Credit Unions",
            "subcategory":"Bank",
            "type":"Services"
        }
    ],
    "sg:phone":"+1 305 668 9727",
    "sg:postcode":"33133",
    "sg:province":"FL",
    "sg:tags":[
        "cashing",
        "check"
    ],
    "wof:name":"South Dixie Check Cashiers Inc",
    "wof:placetype":"venue"
},
  "geometry": {"coordinates":[-80.26223400000001,25.726311],"type":"Point"}
}