{
  "type": "Feature",
  "properties": {
    "iso:country":"US",
    "sg:address":"7355 W Colonial Dr",
    "sg:city":"Orlando",
    "sg:classifiers":[
        {
            "category":"Shopping",
            "type":"Retail Goods"
        }
    ],
    "sg:phone":"+1 407 692 2623",
    "sg:postcode":"32818",
    "sg:province":"FL",
    "sg:tags":[
        "merchandise"
    ],
    "wof:name":"Puppy Country & Grooming",
    "wof:placetype":"venue"
},
  "geometry": {"coordinates":[-81.481736,28.552097],"type":"Point"}
}