{
  "type": "Feature",
  "properties": {
    "addr:full":"6832 Forest Hill Blvd Greenacres FL 33413",
    "addr:housenumber":"6832",
    "addr:postcode":"33413",
    "addr:street":"Forest Hill Blvd",
    "iso:country":"US",
    "sg:address":"6832 Forest Hill Blvd",
    "sg:city":"Greenacres",
    "sg:classifiers":[
        {
            "category":"Sports & Exercise",
            "subcategory":"Gym",
            "type":"Entertainment"
        }
    ],
    "sg:phone":"+1 561 966 4653",
    "sg:postcode":"33413",
    "sg:province":"FL",
    "sg:tags":[
        "center",
        "club",
        "gymnasium",
        "health",
        "fitness",
        "studio",
        "physical"
    ],
    "wof:name":"World Gym Fitness Centers",
    "wof:placetype":"venue"
},
  "geometry": {"coordinates":[-80.149653,26.651078],"type":"Point"}
}