{
  "type": "Feature",
  "properties": {
    "addr:full":"1531 Winthrop St Jacksonville FL 32206",
    "addr:housenumber":"1531",
    "addr:postcode":"32206",
    "addr:street":"Winthrop St",
    "iso:country":"US",
    "sg:address":"1531 Winthrop St",
    "sg:city":"Jacksonville",
    "sg:classifiers":[
        {
            "category":"Education",
            "subcategory":"School",
            "type":"Public Place"
        }
    ],
    "sg:phone":"+1 904 630 6790",
    "sg:postcode":"32206",
    "sg:province":"FL",
    "wof:name":"John Love Elementary School",
    "wof:placetype":"venue"
},
  "geometry": {"coordinates":[-81.63575299999999,30.347534],"type":"Point"}
}