{
  "type": "Feature",
  "properties": {
    "iso:country":"US",
    "sg:address":"2605 Tamiami Trl",
    "sg:city":"Port Charlotte",
    "sg:classifiers":[
        {
            "category":"Personal",
            "subcategory":"Beauty Salon",
            "type":"Services"
        }
    ],
    "sg:phone":"+1 941 629 6464",
    "sg:postcode":"33952",
    "sg:province":"FL",
    "wof:name":"Hair & Co",
    "wof:placetype":"venue"
},
  "geometry": {"coordinates":[-82.114096,26.992839],"type":"Point"}
}