{
  "type": "Feature",
  "properties": {
    "addr:full":"2732 SW 32nd Ave Miami FL 33133",
    "addr:housenumber":"2732",
    "addr:postcode":"33133",
    "addr:street":"Sw 32Nd Ave",
    "iso:country":"US",
    "sg:address":"2732 SW 32nd Ave",
    "sg:city":"Miami",
    "sg:classifiers":[
        {
            "category":"Place Of Worship",
            "subcategory":"Church",
            "type":"Public Place"
        },
        {
            "category":"Place Of Worship",
            "type":"Public Place"
        }
    ],
    "sg:phone":"+1 305 445 3631",
    "sg:postcode":"33133",
    "sg:province":"FL",
    "sg:tags":[
        "churches-baptist-general",
        "churches-baptist-southern",
        "churches-baptist"
    ],
    "wof:name":"Coral Baptist Church",
    "wof:placetype":"venue"
},
  "geometry": {"coordinates":[-80.24606300000001,25.74078],"type":"Point"}
}