{
  "type": "Feature",
  "properties": {
    "addr:full":"8711 Bryan Dairy Rd Largo FL 33777",
    "addr:housenumber":"8711",
    "addr:postcode":"33777",
    "addr:street":"Bryan Dairy Rd",
    "iso:country":"US",
    "sg:address":"8711 Bryan Dairy Rd",
    "sg:city":"Largo",
    "sg:classifiers":[
        {
            "category":"Health Services",
            "subcategory":"Doctor",
            "type":"Services"
        }
    ],
    "sg:phone":"+1 727 394 5700",
    "sg:postcode":"33777",
    "sg:province":"FL",
    "sg:tags":[
        "clinic"
    ],
    "wof:name":"Morton Plant Immediate Care",
    "wof:placetype":"venue"
},
  "geometry": {"coordinates":[-82.759934,27.872365],"type":"Point"}
}