{
  "type": "Feature",
  "properties": {
    "iso:country":"US",
    "sg:address":"8320 Inverness Dr",
    "sg:city":"Tallahassee",
    "sg:classifiers":[
        {
            "category":"Professional",
            "subcategory":"Business Services",
            "type":"Services"
        }
    ],
    "sg:phone":"+1 850 668 1559",
    "sg:postcode":"32312",
    "sg:province":"FL",
    "wof:name":"Tc Chason Enterprises LLC",
    "wof:placetype":"venue"
},
  "geometry": {"coordinates":[-84.235491,30.589139],"type":"Point"}
}