{
  "type": "Feature",
  "properties": {
    "iso:country":"US",
    "sg:address":"3131 NW 13th St",
    "sg:city":"Gainesville",
    "sg:classifiers":[
        {
            "category":"Real Estate",
            "subcategory":"Real Estate Agent",
            "type":"Services"
        },
        {
            "category":"Banks & Credit Unions",
            "subcategory":"Financial Services",
            "type":"Services"
        }
    ],
    "sg:phone":"+1 352 376 4400",
    "sg:postcode":"32609",
    "sg:province":"FL",
    "sg:tags":[
        "investor"
    ],
    "wof:name":"Florida Homes Inc",
    "wof:placetype":"venue"
},
  "geometry": {"coordinates":[-82.338995,29.681858],"type":"Point"}
}