{
  "type": "Feature",
  "properties": {
    "addr:full":"167 Delmar Ave Fort Myers Beach FL 33931",
    "addr:housenumber":"167",
    "addr:postcode":"33931",
    "addr:street":"Delmar Ave",
    "iso:country":"US",
    "sg:address":"167 Delmar Ave",
    "sg:city":"Fort Myers Beach",
    "sg:classifiers":[
        {
            "category":"Real Estate",
            "subcategory":"Real Estate Agent",
            "type":"Services"
        }
    ],
    "sg:phone":"+1 239 770 5910",
    "sg:postcode":"33931",
    "sg:province":"FL",
    "wof:name":"Weniger Real Estate Services",
    "wof:placetype":"venue"
},
  "geometry": {"coordinates":[-81.94558000000001,26.451907],"type":"Point"}
}