{
  "type": "Feature",
  "properties": {
    "iso:country":"US",
    "sg:address":"520 Cranes Way",
    "sg:city":"Altamonte Spgs",
    "sg:classifiers":[
        {
            "category":"Professional",
            "subcategory":"Art Services",
            "type":"Services"
        }
    ],
    "sg:phone":"+1 407 865 6282",
    "sg:postcode":"32701",
    "sg:province":"FL",
    "sg:tags":[
        "artist"
    ],
    "wof:name":"Celia Pinero Artist",
    "wof:placetype":"venue"
},
  "geometry": {"coordinates":[-81.378235,28.670833],"type":"Point"}
}