{
  "type": "Feature",
  "properties": {
    "addr:full":"2064 W Indiantown Rd Jupiter FL 33478",
    "addr:housenumber":"2064",
    "addr:postcode":"33478",
    "addr:street":"W Indiantown Rd",
    "iso:country":"US",
    "sg:address":"2064 W Indiantown Rd",
    "sg:city":"Jupiter",
    "sg:classifiers":[
        {
            "category":"Autos & Motor Vehicles",
            "subcategory":"Auto Supplies",
            "type":"Retail Goods"
        }
    ],
    "sg:phone":"+1 561 748 9444",
    "sg:postcode":"33478",
    "sg:province":"FL",
    "wof:name":"Pep Boys",
    "wof:placetype":"venue"
},
  "geometry": {"coordinates":[-80.127931,26.934333],"type":"Point"}
}