{
  "type": "Feature",
  "properties": {
    "iso:country":"US",
    "sg:address":"105 E Jefferson St",
    "sg:city":"Quincy",
    "sg:classifiers":[
        {
            "category":"Shopping",
            "subcategory":"Shoes",
            "type":"Retail Goods"
        }
    ],
    "sg:phone":"+1 850 875 2700",
    "sg:postcode":"32351",
    "sg:province":"FL",
    "wof:name":"C J's Shoes & Fashions",
    "wof:placetype":"venue"
},
  "geometry": {"coordinates":[-84.575552,30.588094],"type":"Point"}
}