{
  "type": "Feature",
  "properties": {
    "addr:full":"18911 Still Lake Dr Jupiter FL 33458",
    "addr:housenumber":"18911",
    "addr:postcode":"33458",
    "addr:street":"Still Lake Dr",
    "iso:country":"US",
    "sg:address":"18911 Still Lake Dr",
    "sg:city":"Jupiter",
    "sg:classifiers":[
        {
            "category":"Shopping",
            "subcategory":"Hobbies, Toys, & Games",
            "type":"Retail Goods"
        }
    ],
    "sg:phone":"+1 561 707 0213",
    "sg:postcode":"33458",
    "sg:province":"FL",
    "wof:name":"Edvinas Budzinauskas",
    "wof:placetype":"venue"
},
  "geometry": {"coordinates":[-80.136233,26.955369],"type":"Point"}
}