{
  "type": "Feature",
  "properties": {
    "addr:full":"723 Lincoln Ln N Miami Beach FL 33139",
    "addr:housenumber":"723",
    "addr:postcode":"33139",
    "addr:street":"Lincoln Ln N",
    "iso:country":"US",
    "sg:address":"723 Lincoln Ln N",
    "sg:city":"Miami Beach",
    "sg:classifiers":[
        {
            "category":"Shopping",
            "subcategory":"Luggage & Leather Goods",
            "type":"Retail Goods"
        }
    ],
    "sg:phone":"+1 305 672 0110",
    "sg:postcode":"33139",
    "sg:province":"FL",
    "wof:name":"Heavy Duty Goods Inc",
    "wof:placetype":"venue"
},
  "geometry": {"coordinates":[-80.136393,25.791245],"type":"Point"}
}