{
  "type": "Feature",
  "properties": {
    "iso:country":"US",
    "sg:address":"1301 NW 89th Ct Ste 219",
    "sg:city":"Doral",
    "sg:classifiers":[
        {
            "category":"Food & Beverages",
            "subcategory":"Meat & Fish",
            "type":"Retail Goods"
        }
    ],
    "sg:phone":"+1 305 418 9674",
    "sg:postcode":"33172",
    "sg:province":"FL",
    "sg:tags":[
        "seafood",
        "market"
    ],
    "wof:name":"A B C Seafood Distributors",
    "wof:placetype":"venue"
},
  "geometry": {"coordinates":[-80.341083,25.785117],"type":"Point"}
}