{
  "type": "Feature",
  "properties": {
    "addr:full":"8330 SW 51st Ln Gainesville FL 32608",
    "addr:housenumber":"8330",
    "addr:postcode":"32608",
    "addr:street":"Sw 51St Ln",
    "iso:country":"US",
    "sg:address":"8330 SW 51st Ln",
    "sg:city":"Gainesville",
    "sg:classifiers":[
        {
            "category":"Professional",
            "subcategory":"Detective & Security Services",
            "type":"Services"
        }
    ],
    "sg:phone":"+1 352 384 9136",
    "sg:postcode":"32608",
    "sg:province":"FL",
    "sg:tags":[
        "information",
        "bureau"
    ],
    "wof:name":"1st Class Home Services",
    "wof:placetype":"venue"
},
  "geometry": {"coordinates":[-82.431811,29.605887],"type":"Point"}
}