{
  "type": "Feature",
  "properties": {
    "addr:full":"4207 S Dale Mabry Hwy Tampa FL 33611",
    "addr:housenumber":"4207",
    "addr:postcode":"33611",
    "addr:street":"S Dale Mabry Hwy",
    "iso:country":"US",
    "sg:address":"4207 S Dale Mabry Hwy",
    "sg:city":"Tampa",
    "sg:classifiers":[
        {
            "category":"Real Estate",
            "subcategory":"Real Estate Agent",
            "type":"Services"
        }
    ],
    "sg:phone":"+1 813 839 4060",
    "sg:postcode":"33611",
    "sg:province":"FL",
    "wof:name":"C H Realty II TAMPA Key LLC",
    "wof:placetype":"venue"
},
  "geometry": {"coordinates":[-82.50626699999999,27.903672],"type":"Point"}
}