{
  "type": "Feature",
  "properties": {
    "iso:country":"US",
    "sg:address":"250 Westshore Plz",
    "sg:city":"Tampa",
    "sg:classifiers":[
        {
            "category":"Coffee & Tea",
            "type":"Food & Drink"
        },
        {
            "category":"Cafe",
            "type":"Food & Drink"
        },
        {
            "category":"Bakery",
            "type":"Food & Drink"
        }
    ],
    "sg:menulink":"http://www.allmenus.com/fl/tampa/234024-nestle-toll-house-cafe/menu/",
    "sg:phone":"+1 813 202 8257",
    "sg:postcode":"33609",
    "sg:province":"FL",
    "sg:tags":[
        "american",
        "pastry"
    ],
    "wof:name":"Nestle Toll House Cafe",
    "wof:placetype":"venue"
},
  "geometry": {"coordinates":[-82.52728999999999,27.94597],"type":"Point"}
}