{
  "type": "Feature",
  "properties": {
    "addr:full":"106 Myrtle Ridge Rd Lutz FL 33549",
    "addr:housenumber":"106",
    "addr:postcode":"33549",
    "addr:street":"Myrtle Ridge Rd",
    "iso:country":"US",
    "sg:address":"106 Myrtle Ridge Rd",
    "sg:city":"Lutz",
    "sg:classifiers":[
        {
            "category":"Health Services",
            "subcategory":"Hospital",
            "type":"Services"
        }
    ],
    "sg:phone":"+1 813 949 1185",
    "sg:postcode":"33549",
    "sg:province":"FL",
    "sg:tags":[
        "center",
        "birth"
    ],
    "wof:name":"Labor Love Birth Ctr For Tampa",
    "wof:placetype":"venue"
},
  "geometry": {"coordinates":[-82.46195400000001,28.123145],"type":"Point"}
}