{
  "type": "Feature",
  "properties": {
    "iso:country":"US",
    "sg:address":"910 Adelphi Ct",
    "sg:city":"Fort Myers",
    "sg:classifiers":[
        {
            "category":"Building & Trades",
            "subcategory":"Landscaping Services",
            "type":"Services"
        }
    ],
    "sg:phone":"+1 239 437 7973",
    "sg:postcode":"33919",
    "sg:province":"FL",
    "sg:tags":[
        "landscape",
        "contractor"
    ],
    "wof:name":"Shoreline Landscape Design Inc",
    "wof:placetype":"venue"
},
  "geometry": {"coordinates":[-81.899164,26.552002],"type":"Point"}
}