{
  "type": "Feature",
  "properties": {
    "iso:country":"US",
    "sg:address":"2937 SW 27th Ave Ste 202",
    "sg:city":"Miami",
    "sg:classifiers":[
        {
            "category":"Professional",
            "subcategory":"Lawyer & Legal Services",
            "type":"Services"
        }
    ],
    "sg:phone":"+1 305 858 2383",
    "sg:postcode":"33133",
    "sg:province":"FL",
    "wof:name":"Arroyave Oscar Law Office of",
    "wof:placetype":"venue"
},
  "geometry": {"coordinates":[-80.237548,25.73699],"type":"Point"}
}