{
  "type": "Feature",
  "properties": {
    "iso:country":"US",
    "sg:address":"125 Datura St",
    "sg:city":"West Palm Beach",
    "sg:classifiers":[
        {
            "category":"Restaurant",
            "type":"Food & Drink"
        }
    ],
    "sg:phone":"+1 561 835 1828",
    "sg:postcode":"33401",
    "sg:province":"FL",
    "sg:website":"www.spotosoysterbar.com",
    "wof:name":"Spoto's Oyster Bar",
    "wof:placetype":"venue"
},
  "geometry": {"coordinates":[-80.050372,26.712306],"type":"Point"}
}