{
  "type": "Feature",
  "properties": {
    "iso:country":"US",
    "sg:address":"8110 Cortez Rd W",
    "sg:city":"Bradenton",
    "sg:classifiers":[
        {
            "category":"Personal",
            "subcategory":"Tanning Parlor",
            "type":"Services"
        }
    ],
    "sg:phone":"+1 941 795 6040",
    "sg:postcode":"34210",
    "sg:province":"FL",
    "sg:tags":[
        "salon"
    ],
    "wof:name":"Bronzers Sun Spa LLC",
    "wof:placetype":"venue"
},
  "geometry": {"coordinates":[-82.643423,27.462151],"type":"Point"}
}