{
  "type": "Feature",
  "properties": {
    "iso:country":"US",
    "sg:address":"14626 NE 248th Ter",
    "sg:city":"Salt Springs",
    "sg:classifiers":[
        {
            "category":"Travel",
            "subcategory":"Hotels & Motels",
            "type":"Entertainment"
        }
    ],
    "sg:phone":"+1 352 685 2330",
    "sg:postcode":"32134",
    "sg:province":"FL",
    "wof:name":"Anchor Inn Cottages",
    "wof:placetype":"venue"
},
  "geometry": {"coordinates":[-81.74344600000001,29.365488],"type":"Point"}
}