{
  "type": "Feature",
  "properties": {
    "addr:full":"929 W Cypress Creek Rd Fort Lauderdale FL 33309",
    "addr:housenumber":"929",
    "addr:postcode":"33309",
    "addr:street":"W Cypress Creek Rd",
    "iso:country":"US",
    "sg:address":"929 W Cypress Creek Rd",
    "sg:city":"Fort Lauderdale",
    "sg:classifiers":[
        {
            "category":"Restaurant",
            "type":"Food & Drink"
        }
    ],
    "sg:menulink":"http://www.allmenus.com/fl/fort-lauderdale/187155-mcdonalds/menu/",
    "sg:phone":"+1 954 491 6363",
    "sg:postcode":"33309",
    "sg:province":"FL",
    "sg:tags":[
        "burger",
        "american"
    ],
    "wof:name":"McDonald's",
    "wof:placetype":"venue"
},
  "geometry": {"coordinates":[-80.15642,26.203284],"type":"Point"}
}