{
  "type": "Feature",
  "properties": {
    "addr:full":"23002 Sandalfoot Plaza Dr Boca Raton FL 33428",
    "addr:postcode":"23002;33428",
    "addr:street":"Sandalfoot Plaza Dr",
    "iso:country":"US",
    "sg:address":"23002 Sandalfoot Plaza Dr",
    "sg:city":"Boca Raton",
    "sg:classifiers":[
        {
            "category":"Retail",
            "subcategory":"Laundry & Dry Cleaning",
            "type":"Services"
        }
    ],
    "sg:phone":"+1 561 483 2100",
    "sg:postcode":"33428",
    "sg:province":"FL",
    "sg:tags":[
        "cleaner"
    ],
    "wof:name":"Dryclean USA",
    "wof:placetype":"venue"
},
  "geometry": {"coordinates":[-80.201716,26.334818],"type":"Point"}
}