{
  "type": "Feature",
  "properties": {
    "addr:full":"9628 NE 2nd Ave Miami FL 33138",
    "addr:housenumber":"9628",
    "addr:postcode":"33138",
    "addr:street":"Ne 2Nd Ave",
    "iso:country":"US",
    "sg:address":"9628 NE 2nd Ave",
    "sg:city":"Miami",
    "sg:classifiers":[
        {
            "category":"Professional",
            "subcategory":"Management & Consulting",
            "type":"Services"
        }
    ],
    "sg:phone":"+1 305 751 4873",
    "sg:postcode":"33138",
    "sg:province":"FL",
    "sg:tags":[
        "technical",
        "consultant",
        "marine",
        "diver",
        "for"
    ],
    "wof:name":"Internatl Assoc of Nitrox",
    "wof:placetype":"venue"
},
  "geometry": {"coordinates":[-80.19352000000001,25.864165],"type":"Point"}
}