{
  "type": "Feature",
  "properties": {
    "iso:country":"US",
    "sg:address":"1724 W University Ave",
    "sg:city":"Gainesville",
    "sg:classifiers":[
        {
            "category":"Fast Food",
            "type":"Food & Drink"
        },
        {
            "category":"Restaurant",
            "type":"Food & Drink"
        },
        {
            "category":"Food & Beverages",
            "subcategory":"Groceries & Convenience Stores",
            "type":"Retail Goods"
        }
    ],
    "sg:phone":"+1 352 375 7222",
    "sg:postcode":"32603",
    "sg:province":"FL",
    "sg:tags":[
        "shop",
        "sandwich",
        "take"
    ],
    "sg:website":"http://www.jimmyjohns.com",
    "wof:name":"Jimmy John's",
    "wof:placetype":"venue"
},
  "geometry": {"coordinates":[-82.34515,29.652108],"type":"Point"}
}