{
  "type": "Feature",
  "properties": {
    "addr:full":"361 S County Rd Palm Beach FL 33480",
    "addr:housenumber":"361",
    "addr:postcode":"33480",
    "addr:street":"S County Rd",
    "iso:country":"US",
    "sg:address":"361 S County Rd",
    "sg:city":"Palm Beach",
    "sg:classifiers":[
        {
            "category":"Building & Trades",
            "subcategory":"Construction",
            "type":"Services"
        }
    ],
    "sg:phone":"+1 561 837 9820",
    "sg:postcode":"33480",
    "sg:province":"FL",
    "sg:tags":[
        "residential",
        "general",
        "contractor"
    ],
    "wof:name":"Alonso & Associates",
    "wof:placetype":"venue"
},
  "geometry": {"coordinates":[-80.036525,26.702842],"type":"Point"}
}