{
  "type": "Feature",
  "properties": {
    "iso:country":"US",
    "sg:address":"503 S Dixie Dr",
    "sg:city":"Howey In The Hills",
    "sg:classifiers":[
        {
            "category":"Retail",
            "subcategory":"Laundry & Dry Cleaning",
            "type":"Services"
        }
    ],
    "sg:phone":"+1 352 324 2593",
    "sg:postcode":"34737",
    "sg:province":"FL",
    "sg:tags":[
        "carpet"
    ],
    "wof:name":"A-1 Apollo Carpet Cleaning",
    "wof:placetype":"venue"
},
  "geometry": {"coordinates":[-81.772682,28.709655],"type":"Point"}
}