{
  "type": "Feature",
  "properties": {
    "addr:full":"9385 N 56th St Tampa FL 33617",
    "addr:housenumber":"9385",
    "addr:postcode":"33617",
    "addr:street":"N 56Th St",
    "iso:country":"US",
    "sg:address":"9385 N 56th St",
    "sg:city":"Tampa",
    "sg:classifiers":[
        {
            "category":"Professional",
            "subcategory":"Lawyer & Legal Services",
            "type":"Services"
        }
    ],
    "sg:phone":"+1 813 988 5135",
    "sg:postcode":"33617",
    "sg:province":"FL",
    "sg:tags":[
        "attorney"
    ],
    "wof:name":"John E Mc Millan",
    "wof:placetype":"venue"
},
  "geometry": {"coordinates":[-82.393379,28.035878],"type":"Point"}
}