{
  "type": "Feature",
  "properties": {
    "addr:full":"7331 Office Park Pl Melbourne FL 32940",
    "addr:housenumber":"7331",
    "addr:postcode":"32940",
    "addr:street":"Office Park Pl",
    "iso:country":"US",
    "sg:address":"7331 Office Park Pl",
    "sg:city":"Melbourne",
    "sg:classifiers":[
        {
            "category":"Banks & Credit Unions",
            "subcategory":"Investment Brokerage",
            "type":"Services"
        }
    ],
    "sg:phone":"+1 321 254 6404",
    "sg:postcode":"32940",
    "sg:province":"FL",
    "sg:tags":[
        "consultant",
        "planning",
        "financial"
    ],
    "wof:name":"Linsco Private Ledger Fncl Svc",
    "wof:placetype":"venue"
},
  "geometry": {"coordinates":[-80.71078799999999,28.231246],"type":"Point"}
}