{
  "type": "Feature",
  "properties": {
    "addr:full":"1811 NW Boca Raton Blvd Boca Raton FL 33432",
    "addr:housenumber":"1811",
    "addr:postcode":"33432",
    "addr:street":"Nw Boca Raton Blvd",
    "iso:country":"US",
    "sg:address":"1811 NW Boca Raton Blvd",
    "sg:city":"Boca Raton",
    "sg:classifiers":[
        {
            "category":"Retail",
            "subcategory":"Repair Shop",
            "type":"Services"
        }
    ],
    "sg:phone":"+1 561 395 4383",
    "sg:postcode":"33432",
    "sg:province":"FL",
    "sg:tags":[
        "lock",
        "locksmith"
    ],
    "wof:name":"Boca Locksmith",
    "wof:placetype":"venue"
},
  "geometry": {"coordinates":[-80.090301,26.36522],"type":"Point"}
}