{
  "type": "Feature",
  "properties": {
    "addr:full":"6432 River Point Dr Green Cove Springs FL 32043",
    "addr:housenumber":"6432",
    "addr:postcode":"32043",
    "addr:street":"River Point Dr",
    "iso:country":"US",
    "sg:address":"6432 River Point Dr",
    "sg:city":"Green Cove Springs",
    "sg:classifiers":[
        {
            "category":"Home & Garden",
            "subcategory":"Mobile Homes",
            "type":"Retail Goods"
        }
    ],
    "sg:phone":"+1 904 284 1196",
    "sg:postcode":"32043",
    "sg:province":"FL",
    "wof:name":"Land & Home Sales Inc",
    "wof:placetype":"venue"
},
  "geometry": {"coordinates":[-81.696361,30.076966],"type":"Point"}
}