{
  "type": "Feature",
  "properties": {
    "addr:full":"10080 Jeno Rd Milton FL 32583",
    "addr:housenumber":"10080",
    "addr:postcode":"32583",
    "addr:street":"Jeno Rd",
    "iso:country":"US",
    "sg:address":"10080 Jeno Rd",
    "sg:city":"Milton",
    "sg:classifiers":[
        {
            "category":"Building & Trades",
            "subcategory":"Cleaning & Sanitation",
            "type":"Services"
        }
    ],
    "sg:phone":"+1 850 983 9981",
    "sg:postcode":"32583",
    "sg:province":"FL",
    "sg:tags":[
        "maintenance"
    ],
    "wof:name":"Dome Wright Janitorial Service",
    "wof:placetype":"venue"
},
  "geometry": {"coordinates":[-86.911483,30.626203],"type":"Point"}
}