{
  "type": "Feature",
  "properties": {
    "iso:country":"US",
    "sg:address":"1595 N Broadway Ave",
    "sg:city":"Bartow",
    "sg:classifiers":[
        {
            "category":"Restaurant",
            "type":"Food & Drink"
        }
    ],
    "sg:menulink":"http://www.allmenus.com/fl/bartow/240631-checkers/menu/",
    "sg:phone":"+1 863 533 2700",
    "sg:postcode":"33830",
    "sg:province":"FL",
    "sg:tags":[
        "burger",
        "american",
        "hot",
        "dog"
    ],
    "wof:name":"Checkers",
    "wof:placetype":"venue"
},
  "geometry": {"coordinates":[-81.843732,27.910154],"type":"Point"}
}