{
  "type": "Feature",
  "properties": {
    "iso:country":"US",
    "sg:address":"8617 NW 43rd Ct",
    "sg:city":"Pompano Beach",
    "sg:classifiers":[
        {
            "category":"Wholesale",
            "subcategory":"Drugs",
            "type":"Manufacturing & Wholesale Goods"
        }
    ],
    "sg:phone":"+1 954 753 1051",
    "sg:postcode":"33065",
    "sg:province":"FL",
    "wof:name":"Eli Lilly and Company",
    "wof:placetype":"venue"
},
  "geometry": {"coordinates":[-80.240362,26.28373],"type":"Point"}
}