{
  "type": "Feature",
  "properties": {
    "addr:full":"7256 E Horse Hammock Rd Avon Park FL 33825",
    "addr:housenumber":"7256",
    "addr:postcode":"33825",
    "addr:street":"E Horse Hammock Rd",
    "iso:country":"US",
    "sg:address":"7256 E Horse Hammock Rd",
    "sg:city":"Avon Park",
    "sg:classifiers":[
        {
            "category":"Building & Trades",
            "subcategory":"Cleaning & Sanitation",
            "type":"Services"
        }
    ],
    "sg:phone":"+1 863 452 5934",
    "sg:postcode":"33825",
    "sg:province":"FL",
    "sg:tags":[
        "janitor"
    ],
    "wof:name":"Delphia Rucker Cleaning Svc",
    "wof:placetype":"venue"
},
  "geometry": {"coordinates":[-81.381034,27.632035],"type":"Point"}
}