{
  "type": "Feature",
  "properties": {
    "addr:full":"2765 Leeward Ln Naples FL 34103",
    "addr:housenumber":"2765",
    "addr:postcode":"34103",
    "addr:street":"Leeward Ln",
    "iso:country":"US",
    "sg:address":"2765 Leeward Ln",
    "sg:city":"Naples",
    "sg:classifiers":[
        {
            "category":"Professional",
            "subcategory":"Accounting & Tax Preparation",
            "type":"Services"
        }
    ],
    "sg:phone":"+1 239 263 7982",
    "sg:postcode":"34103",
    "sg:province":"FL",
    "wof:name":"Cjk Consultants Inc",
    "wof:placetype":"venue"
},
  "geometry": {"coordinates":[-81.808638,26.180412],"type":"Point"}
}