{
  "type": "Feature",
  "properties": {
    "iso:country":"US",
    "sg:address":"4801 Ann Dr",
    "sg:city":"Holiday",
    "sg:classifiers":[
        {
            "category":"Organizations",
            "subcategory":"Religious Organization",
            "type":"Services"
        }
    ],
    "sg:phone":"+1 727 942 1442",
    "sg:postcode":"34690",
    "sg:province":"FL",
    "sg:tags":[
        "church"
    ],
    "wof:name":"Holiday Community Fellowship",
    "wof:placetype":"venue"
},
  "geometry": {"coordinates":[-82.734557,28.191326],"type":"Point"}
}