{
  "type": "Feature",
  "properties": {
    "addr:full":"1660 NW 3rd St Deerfield Beach FL 33442",
    "addr:housenumber":"1660",
    "addr:postcode":"33442",
    "addr:street":"Nw 3Rd St",
    "iso:country":"US",
    "sg:address":"1660 NW 3rd St",
    "sg:city":"Deerfield Beach",
    "sg:classifiers":[
        {
            "category":"Manufacturing",
            "subcategory":"Metals",
            "type":"Manufacturing & Wholesale Goods"
        }
    ],
    "sg:phone":"+1 954 428 9810",
    "sg:postcode":"33442",
    "sg:province":"FL",
    "sg:tags":[
        "die",
        "aluminum",
        "mfg"
    ],
    "wof:name":"Stanley Tool & Die",
    "wof:placetype":"venue"
},
  "geometry": {"coordinates":[-80.123462,26.321241],"type":"Point"}
}