{
  "type": "Feature",
  "properties": {
    "iso:country":"US",
    "sg:address":"12525 SW 33rd St",
    "sg:city":"Miami",
    "sg:classifiers":[
        {
            "category":"Professional",
            "type":"Services"
        }
    ],
    "sg:phone":"+1 305 554 1913",
    "sg:postcode":"33175",
    "sg:province":"FL",
    "wof:name":"Stargas Inc",
    "wof:placetype":"venue"
},
  "geometry": {"coordinates":[-80.397621,25.737642],"type":"Point"}
}