{
  "type": "Feature",
  "properties": {
    "addr:full":"1519 NE 153rd Ter Miami FL 33162",
    "addr:housenumber":"1519",
    "addr:postcode":"33162",
    "addr:street":"Ne 153Rd Ter",
    "iso:country":"US",
    "sg:address":"1519 NE 153rd Ter",
    "sg:city":"Miami",
    "sg:classifiers":[
        {
            "category":"Food & Beverages",
            "subcategory":"Groceries & Convenience Stores",
            "type":"Retail Goods"
        }
    ],
    "sg:phone":"+1 305 945 1832",
    "sg:postcode":"33162",
    "sg:province":"FL",
    "wof:name":"G T Groceries Inc",
    "wof:placetype":"venue"
},
  "geometry": {"coordinates":[-80.169955,25.916752],"type":"Point"}
}