{
  "type": "Feature",
  "properties": {
    "iso:country":"US",
    "sg:address":"3245 NW Federal Hwy",
    "sg:city":"Jensen Beach",
    "sg:classifiers":[
        {
            "category":"Shopping",
            "subcategory":"Department Store",
            "type":"Retail Goods"
        }
    ],
    "sg:phone":"+1 772 692 2210",
    "sg:postcode":"34957",
    "sg:province":"FL",
    "sg:website":"www.marshallsonline.com",
    "wof:name":"Marshalls",
    "wof:placetype":"venue"
},
  "geometry": {"coordinates":[-80.270167,27.239721],"type":"Point"}
}