{
  "type": "Feature",
  "properties": {
    "iso:country":"US",
    "sg:address":"6681 Overseas Hwy",
    "sg:city":"Marathon",
    "sg:classifiers":[
        {
            "category":"Home & Garden",
            "subcategory":"Building Materials",
            "type":"Retail Goods"
        }
    ],
    "sg:phone":"+1 305 743 5342",
    "sg:postcode":"33050",
    "sg:province":"FL",
    "sg:tags":[
        "carpet",
        "covering",
        "rug",
        "floor"
    ],
    "wof:name":"Handley",
    "wof:placetype":"venue"
},
  "geometry": {"coordinates":[-81.06635900000001,24.718679],"type":"Point"}
}