{
  "type": "Feature",
  "properties": {
    "iso:country":"US",
    "sg:address":"685 Royal Palm Beach Blvd",
    "sg:city":"Royal Palm Beach",
    "sg:classifiers":[
        {
            "category":"Real Estate",
            "subcategory":"Real Estate Services",
            "type":"Services"
        }
    ],
    "sg:phone":"+1 561 793 2000",
    "sg:postcode":"33411",
    "sg:province":"FL",
    "sg:tags":[
        "company",
        "title"
    ],
    "wof:name":"Boulevard Title Co",
    "wof:placetype":"venue"
},
  "geometry": {"coordinates":[-80.230155,26.684669],"type":"Point"}
}