{
  "type": "Feature",
  "properties": {
    "iso:country":"US",
    "sg:address":"1321 Eastport Rd",
    "sg:city":"Jacksonville",
    "sg:classifiers":[
        {
            "category":"Government",
            "subcategory":"Office",
            "type":"Public Place"
        }
    ],
    "sg:phone":"+1 904 630 2489",
    "sg:postcode":"32218",
    "sg:province":"FL",
    "sg:tags":[
        "village"
    ],
    "wof:name":"Jacksonville Mosquito Control",
    "wof:placetype":"venue"
},
  "geometry": {"coordinates":[-81.608413,30.44294],"type":"Point"}
}