{
  "type": "Feature",
  "properties": {
    "iso:country":"US",
    "sg:address":"110 SW Martin Luther King Blvd",
    "sg:city":"Belle Glade",
    "sg:classifiers":[
        {
            "category":"Sports & Exercise",
            "subcategory":"Golf",
            "type":"Entertainment"
        }
    ],
    "sg:phone":"+1 561 996 4049",
    "sg:postcode":"33430",
    "sg:province":"FL",
    "sg:tags":[
        "course"
    ],
    "wof:name":"Miniature Golf Course",
    "wof:placetype":"venue"
},
  "geometry": {"coordinates":[-80.669004,26.682184],"type":"Point"}
}