{
  "type": "Feature",
  "properties": {
    "iso:country":"US",
    "sg:address":"999 Ponce De Leon Blvd",
    "sg:city":"Coral Gables",
    "sg:classifiers":[
        {
            "category":"Professional",
            "subcategory":"Lawyer & Legal Services",
            "type":"Services"
        }
    ],
    "sg:phone":"+1 305 442 0606",
    "sg:postcode":"33134",
    "sg:province":"FL",
    "sg:tags":[
        "personal",
        "injury"
    ],
    "wof:name":"Bofill Jose Atty",
    "wof:placetype":"venue"
},
  "geometry": {"coordinates":[-80.259102,25.762199],"type":"Point"}
}