{
  "type": "Feature",
  "properties": {
    "iso:country":"US",
    "sg:address":"4903 W Hanna Ave",
    "sg:city":"Tampa",
    "sg:classifiers":[
        {
            "category":"Home & Garden",
            "subcategory":"Building Materials",
            "type":"Retail Goods"
        }
    ],
    "sg:phone":"+1 813 249 9323",
    "sg:postcode":"33634",
    "sg:province":"FL",
    "sg:tags":[
        "granite",
        "marble"
    ],
    "wof:name":"Elegant Marble & Granite Inc",
    "wof:placetype":"venue"
},
  "geometry": {"coordinates":[-82.526602,28.00365],"type":"Point"}
}