{
  "type": "Feature",
  "properties": {
    "iso:country":"US",
    "sg:address":"485 Lakeview Dr",
    "sg:city":"Palm Harbor",
    "sg:classifiers":[
        {
            "category":"Wholesale",
            "subcategory":"Construction Materials",
            "type":"Manufacturing & Wholesale Goods"
        }
    ],
    "sg:phone":"+1 727 789 3555",
    "sg:postcode":"34683",
    "sg:province":"FL",
    "sg:tags":[
        "building",
        "product",
        "representative",
        "architectural",
        "mfg"
    ],
    "wof:name":"Builders Choice Southeast Inc",
    "wof:placetype":"venue"
},
  "geometry": {"coordinates":[-82.751564,28.08487],"type":"Point"}
}