{
  "type": "Feature",
  "properties": {
    "addr:full":"7510 Thomas Dr Panama City Bch FL 32408",
    "addr:housenumber":"7510",
    "addr:postcode":"32408",
    "addr:street":"Thomas Dr",
    "iso:country":"US",
    "sg:address":"7510 Thomas Dr",
    "sg:city":"Panama City Bch",
    "sg:classifiers":[
        {
            "category":"Shopping",
            "subcategory":"Tobacco",
            "type":"Retail Goods"
        },
        {
            "category":"Shopping",
            "subcategory":"Gifts & Souvenirs",
            "type":"Retail Goods"
        }
    ],
    "sg:phone":"+1 850 230 3961",
    "sg:postcode":"32408",
    "sg:province":"FL",
    "sg:tags":[
        "novelty",
        "condom"
    ],
    "wof:name":"Condom Knowledge Inc",
    "wof:placetype":"venue"
},
  "geometry": {"coordinates":[-85.778373,30.160734],"type":"Point"}
}