{
  "type": "Feature",
  "properties": {
    "addr:full":"2500 N McMullen Booth Rd Clearwater FL 33761",
    "addr:housenumber":"2500",
    "addr:postcode":"33761",
    "addr:street":"N Mcmullen Booth Rd",
    "iso:country":"US",
    "sg:address":"2500 N McMullen Booth Rd",
    "sg:city":"Clearwater",
    "sg:classifiers":[
        {
            "category":"Banks & Credit Unions",
            "subcategory":"Bank",
            "type":"Services"
        }
    ],
    "sg:phone":"+1 727 823 4181",
    "sg:postcode":"33761",
    "sg:province":"FL",
    "wof:name":"Sun Trust Bank",
    "wof:placetype":"venue"
},
  "geometry": {"coordinates":[-82.708911,28.01504],"type":"Point"}
}