{
  "type": "Feature",
  "properties": {
    "addr:full":"8291 Hampton Wood Dr Boca Raton FL 33433",
    "addr:housenumber":"8291",
    "addr:postcode":"33433",
    "addr:street":"Hampton Wood Dr",
    "iso:country":"US",
    "sg:address":"8291 Hampton Wood Dr",
    "sg:city":"Boca Raton",
    "sg:classifiers":[
        {
            "category":"Retail",
            "subcategory":"Auto Repair",
            "type":"Services"
        }
    ],
    "sg:phone":"+1 561 883 0411",
    "sg:postcode":"33433",
    "sg:province":"FL",
    "sg:tags":[
        "glass",
        "coating",
        "tinting"
    ],
    "wof:name":"Do It Yourself Window Tinting",
    "wof:placetype":"venue"
},
  "geometry": {"coordinates":[-80.173379,26.352689],"type":"Point"}
}