{
  "type": "Feature",
  "properties": {
    "addr:full":"399 Circle Dr Deland FL 32724",
    "addr:housenumber":"399",
    "addr:postcode":"32724",
    "addr:street":"Circle Dr",
    "iso:country":"US",
    "sg:address":"399 Circle Dr",
    "sg:city":"Deland",
    "sg:classifiers":[
        {
            "category":"Real Estate",
            "subcategory":"Real Estate Operator",
            "type":"Services"
        }
    ],
    "sg:phone":"+1 386 736 1183",
    "sg:postcode":"32724",
    "sg:province":"FL",
    "sg:tags":[
        "mobile",
        "home",
        "site",
        "community"
    ],
    "wof:name":"Applegate Estates Inc",
    "wof:placetype":"venue"
},
  "geometry": {"coordinates":[-81.30481899999999,29.078025],"type":"Point"}
}