{
  "type": "Feature",
  "properties": {
    "addr:full":"2801 Coastal Hwy St Augustine FL 32084",
    "addr:housenumber":"2801",
    "addr:postcode":"32084",
    "addr:street":"Coastal Hwy St",
    "iso:country":"US",
    "sg:address":"2801 Coastal Hwy",
    "sg:city":"St Augustine",
    "sg:classifiers":[
        {
            "category":"Restaurant",
            "type":"Food & Drink"
        }
    ],
    "sg:phone":"+1 904 824 6466",
    "sg:postcode":"32084",
    "sg:province":"FL",
    "sg:tags":[
        "caterer"
    ],
    "wof:name":"Amazing Grace Catering Co",
    "wof:placetype":"venue"
},
  "geometry": {"coordinates":[-81.29239099999999,29.91678],"type":"Point"}
}