{
  "type": "Feature",
  "properties": {
    "addr:full":"330 SW 27th Ave Ste 701 Miami FL 33135",
    "addr:housenumber":"330",
    "addr:postcode":"33135",
    "addr:street":"Sw 27Th Ave Ste 701",
    "iso:country":"US",
    "sg:address":"330 SW 27th Ave Ste 701",
    "sg:city":"Miami",
    "sg:classifiers":[
        {
            "category":"Health Services",
            "subcategory":"Doctor",
            "type":"Services"
        }
    ],
    "sg:phone":"+1 305 642 7186",
    "sg:postcode":"33135",
    "sg:province":"FL",
    "wof:name":"Morlote Medical Group Dr",
    "wof:placetype":"venue"
},
  "geometry": {"coordinates":[-80.239098,25.7691],"type":"Point"}
}