{
  "type": "Feature",
  "properties": {
    "iso:country":"US",
    "sg:address":"5365 Brosche Rd",
    "sg:city":"Orlando",
    "sg:classifiers":[
        {
            "category":"Personal",
            "type":"Services"
        }
    ],
    "sg:phone":"+1 407 263 7600",
    "sg:postcode":"32807",
    "sg:province":"FL",
    "sg:tags":[
        "therapist",
        "massage"
    ],
    "wof:name":"Therapeutic Hands Of Steele",
    "wof:placetype":"venue"
},
  "geometry": {"coordinates":[-81.315386,28.546798],"type":"Point"}
}