{
  "type": "Feature",
  "properties": {
    "iso:country":"US",
    "sg:address":"2009 W Vine St",
    "sg:city":"Kissimmee",
    "sg:classifiers":[
        {
            "category":"Travel",
            "subcategory":"Hotels & Motels",
            "type":"Entertainment"
        }
    ],
    "sg:phone":"+1 407 846 2713",
    "sg:postcode":"34741",
    "sg:province":"FL",
    "sg:tags":[
        "lodging"
    ],
    "sg:website":"http://www.ramada.com",
    "wof:name":"Ramada Inn Kissimmee",
    "wof:placetype":"venue"
},
  "geometry": {"coordinates":[-81.424295,28.30456],"type":"Point"}
}