{
  "type": "Feature",
  "properties": {
    "iso:country":"US",
    "sg:address":"6856 McLane Rd",
    "sg:city":"Grand Ridge",
    "sg:classifiers":[
        {
            "category":"Freight",
            "type":"Transportation"
        }
    ],
    "sg:phone":"+1 850 592 8494",
    "sg:postcode":"32442",
    "sg:province":"FL",
    "sg:tags":[
        "operator",
        "trucking"
    ],
    "wof:name":"Southern Contract Carriers",
    "wof:placetype":"venue"
},
  "geometry": {"coordinates":[-85.024939,30.754745],"type":"Point"}
}