{
  "type": "Feature",
  "properties": {
    "iso:country":"US",
    "sg:address":"601 E Dixie Ave Ste 301",
    "sg:city":"Leesburg",
    "sg:classifiers":[
        {
            "category":"Health Services",
            "subcategory":"Doctor",
            "type":"Services"
        }
    ],
    "sg:phone":"+1 352 787 1001",
    "sg:postcode":"34748",
    "sg:province":"FL",
    "sg:tags":[
        "gynecology",
        "physician",
        "surgeon",
        "surgeons",
        "obstetrics"
    ],
    "wof:name":"Lakeside Center For Women",
    "wof:placetype":"venue"
},
  "geometry": {"coordinates":[-81.86938000000001,28.806591],"type":"Point"}
}