{
  "type": "Feature",
  "properties": {
    "iso:country":"US",
    "sg:address":"2256 NW 26th Ave",
    "sg:city":"Miami",
    "sg:classifiers":[
        {
            "category":"Autos & Motor Vehicles",
            "subcategory":"Automobile Sales",
            "type":"Retail Goods"
        }
    ],
    "sg:phone":"+1 305 638 8084",
    "sg:postcode":"33142",
    "sg:province":"FL",
    "sg:tags":[
        "car",
        "dealer"
    ],
    "wof:name":"Happy Star Auto",
    "wof:placetype":"venue"
},
  "geometry": {"coordinates":[-80.23892600000001,25.797957],"type":"Point"}
}