{
  "type": "Feature",
  "properties": {
    "iso:country":"US",
    "sg:address":"640 NW 133rd St",
    "sg:city":"Miami",
    "sg:classifiers":[
        {
            "category":"Building & Trades",
            "subcategory":"Construction",
            "type":"Services"
        }
    ],
    "sg:phone":"+1 305 685 2149",
    "sg:postcode":"33168",
    "sg:province":"FL",
    "sg:tags":[
        "a",
        "family",
        "residential",
        "general",
        "home",
        "contractor"
    ],
    "wof:name":"Space Builders and Planners",
    "wof:placetype":"venue"
},
  "geometry": {"coordinates":[-80.21118800000001,25.896447],"type":"Point"}
}