{
  "type": "Feature",
  "properties": {
    "iso:country":"US",
    "sg:address":"545 State Hwy 190",
    "sg:city":"Valparaiso",
    "sg:classifiers":[
        {
            "category":"Freight",
            "type":"Transportation"
        }
    ],
    "sg:phone":"+1 850 678 8885",
    "sg:postcode":"32580",
    "sg:province":"FL",
    "sg:tags":[
        "commercial",
        "storage"
    ],
    "wof:name":"Charlie Brown Climatic Control",
    "wof:placetype":"venue"
},
  "geometry": {"coordinates":[-86.50419599999999,30.511205],"type":"Point"}
}