{
  "type": "Feature",
  "properties": {
    "iso:country":"US",
    "sg:address":"3001 Aloma Ave",
    "sg:city":"Winter Park",
    "sg:classifiers":[
        {
            "category":"Wholesale",
            "subcategory":"Non-durable Goods",
            "type":"Manufacturing & Wholesale Goods"
        }
    ],
    "sg:phone":"+1 407 672 1270",
    "sg:postcode":"32792",
    "sg:province":"FL",
    "wof:name":"APT Video Guide By Brenda",
    "wof:placetype":"venue"
},
  "geometry": {"coordinates":[-81.311336,28.603604],"type":"Point"}
}