{
  "type": "Feature",
  "properties": {
    "addr:full":"257 S Spoonbill Ln Jupiter FL 33458",
    "addr:housenumber":"257",
    "addr:postcode":"33458",
    "addr:street":"S Spoonbill Ln",
    "iso:country":"US",
    "sg:address":"257 S Spoonbill Ln",
    "sg:city":"Jupiter",
    "sg:classifiers":[
        {
            "category":"Banks & Credit Unions",
            "subcategory":"Financial Services",
            "type":"Services"
        }
    ],
    "sg:phone":"+1 561 748 7741",
    "sg:postcode":"33458",
    "sg:province":"FL",
    "sg:tags":[
        "money",
        "manager",
        "private"
    ],
    "wof:name":"Tequesta Capital Investments",
    "wof:placetype":"venue"
},
  "geometry": {"coordinates":[-80.134119,26.908074],"type":"Point"}
}