{
  "type": "Feature",
  "properties": {
    "addr:full":"9140 Madison Ave Jacksonville FL 32208",
    "addr:housenumber":"9140",
    "addr:postcode":"32208",
    "addr:street":"Madison Ave",
    "iso:country":"US",
    "sg:address":"9140 Madison Ave",
    "sg:city":"Jacksonville",
    "sg:classifiers":[
        {
            "category":"Manufacturing",
            "subcategory":"Building Materials",
            "type":"Manufacturing & Wholesale Goods"
        }
    ],
    "sg:phone":"+1 904 768 6817",
    "sg:postcode":"32208",
    "sg:province":"FL",
    "sg:tags":[
        "mfg",
        "wood",
        "kitchen",
        "cabinet"
    ],
    "wof:name":"O L Hancock Cab Installation",
    "wof:placetype":"venue"
},
  "geometry": {"coordinates":[-81.684253,30.40844],"type":"Point"}
}