{
  "type": "Feature",
  "properties": {
    "iso:country":"US",
    "sg:address":"522 Rutile Dr",
    "sg:city":"Ponte Vedra Bch",
    "sg:classifiers":[
        {
            "category":"Communications",
            "type":"Services"
        }
    ],
    "sg:phone":"+1 904 543 8198",
    "sg:postcode":"32082",
    "sg:province":"FL",
    "wof:name":"Applied Data Communications",
    "wof:placetype":"venue"
},
  "geometry": {"coordinates":[-81.37633700000001,30.227732],"type":"Point"}
}