{
  "type": "Feature",
  "properties": {
    "iso:country":"US",
    "sg:address":"8642 SW Riviera Dr",
    "sg:city":"Arcadia",
    "sg:classifiers":[
        {
            "category":"Utilities",
            "subcategory":"Telephone",
            "type":"Services"
        }
    ],
    "sg:phone":"+1 863 993 2113",
    "sg:postcode":"34269",
    "sg:province":"FL",
    "sg:tags":[
        "equipment",
        "communications",
        "web",
        "provider"
    ],
    "wof:name":"Netliner Communications",
    "wof:placetype":"venue"
},
  "geometry": {"coordinates":[-81.98535,27.04543],"type":"Point"}
}