{
  "type": "Feature",
  "properties": {
    "addr:full":"3520 3rd St S Jacksonville Bch FL 32250",
    "addr:housenumber":"3520",
    "addr:postcode":"32250",
    "addr:street":"3Rd St S",
    "iso:country":"US",
    "sg:address":"3520 3rd St S",
    "sg:city":"Jacksonville Bch",
    "sg:classifiers":[
        {
            "category":"Insurance",
            "subcategory":"Insurance Agent",
            "type":"Services"
        }
    ],
    "sg:phone":"+1 904 249 3382",
    "sg:postcode":"32250",
    "sg:province":"FL",
    "wof:name":"State Farm Insurance",
    "wof:placetype":"venue"
},
  "geometry": {"coordinates":[-81.387075,30.261097],"type":"Point"}
}