{
  "type": "Feature",
  "properties": {
    "iso:country":"US",
    "sg:address":"1234 Rawls Dr",
    "sg:city":"Lakeland",
    "sg:classifiers":[
        {
            "category":"Professional",
            "type":"Services"
        },
        {
            "category":"Personal",
            "type":"Services"
        }
    ],
    "sg:phone":"+1 863 968 0972",
    "sg:postcode":"33801",
    "sg:province":"FL",
    "sg:tags":[
        "full",
        "material",
        "storage",
        "moving",
        "services-labor",
        "mover"
    ],
    "wof:name":"Doug's Moving & Delivery Service",
    "wof:placetype":"venue"
},
  "geometry": {"coordinates":[-81.903746,28.059007],"type":"Point"}
}