{
  "type": "Feature",
  "properties": {
    "iso:country":"US",
    "sg:address":"South Beach",
    "sg:city":"Miami",
    "sg:classifiers":[
        {
            "category":"Sports & Exercise",
            "subcategory":"Playing Field",
            "type":"Entertainment"
        }
    ],
    "sg:phone":"+1 310 507 5602",
    "sg:postcode":"33139",
    "sg:province":"FL",
    "sg:tags":[
        "instruction",
        "fitness"
    ],
    "sg:website":"www.freewebs.com/sobeshape",
    "wof:name":"The WOW Booty Camp",
    "wof:placetype":"venue"
},
  "geometry": {"coordinates":[-80.136948,25.855766],"type":"Point"}
}