{
  "type": "Feature",
  "properties": {
    "addr:full":"17240 Oleander Ln Sugarloaf Shores FL 33042",
    "addr:housenumber":"17240",
    "addr:postcode":"33042",
    "addr:street":"Oleander Ln",
    "iso:country":"US",
    "sg:address":"17240 Oleander Ln",
    "sg:city":"Sugarloaf Shores",
    "sg:classifiers":[
        {
            "category":"Recreation",
            "type":"Entertainment"
        }
    ],
    "sg:phone":"+1 305 745 3304",
    "sg:postcode":"33042",
    "sg:province":"FL",
    "sg:tags":[
        "guide"
    ],
    "wof:name":"Capt Dexter Simmons",
    "wof:placetype":"venue"
},
  "geometry": {"coordinates":[-81.55087899999999,24.634978],"type":"Point"}
}