{
  "type": "Feature",
  "properties": {
    "iso:country":"US",
    "sg:address":"984 NE 79th St",
    "sg:city":"Miami",
    "sg:classifiers":[
        {
            "category":"Wholesale",
            "subcategory":"Medical Equipment & Supplies",
            "type":"Manufacturing & Wholesale Goods"
        }
    ],
    "sg:phone":"+1 305 757 0607",
    "sg:postcode":"33138",
    "sg:province":"FL",
    "wof:name":"Arap Medical Equipment",
    "wof:placetype":"venue"
},
  "geometry": {"coordinates":[-80.1788,25.84791],"type":"Point"}
}