{
  "type": "Feature",
  "properties": {
    "addr:full":"302 Racetrack Rd NW Fort Walton Beach FL 32547",
    "addr:housenumber":"302",
    "addr:postcode":"32547",
    "addr:street":"Racetrack Rd Nw",
    "iso:country":"US",
    "sg:address":"302 Racetrack Rd NW",
    "sg:city":"Fort Walton Beach",
    "sg:classifiers":[
        {
            "category":"Restaurant",
            "type":"Food & Drink"
        }
    ],
    "sg:menulink":"http://www.allmenus.com/fl/fort-walton-beach/160262-burger-king/menu/",
    "sg:phone":"+1 850 315 8841",
    "sg:postcode":"32547",
    "sg:province":"FL",
    "sg:tags":[
        "burger",
        "american"
    ],
    "wof:name":"Burger King",
    "wof:placetype":"venue"
},
  "geometry": {"coordinates":[-86.625517,30.449364],"type":"Point"}
}