{
  "type": "Feature",
  "properties": {
    "iso:country":"US",
    "sg:address":"4349 SW Port Way",
    "sg:city":"Palm City",
    "sg:classifiers":[
        {
            "category":"Wholesale",
            "subcategory":"Drugs",
            "type":"Manufacturing & Wholesale Goods"
        }
    ],
    "sg:phone":"+1 772 781 7278",
    "sg:postcode":"34990",
    "sg:province":"FL",
    "sg:tags":[
        "pet",
        "supplement",
        "nutritional",
        "for"
    ],
    "wof:name":"Healthypetnet",
    "wof:placetype":"venue"
},
  "geometry": {"coordinates":[-80.31158499999999,27.165264],"type":"Point"}
}