{
  "type": "Feature",
  "properties": {
    "iso:country":"US",
    "sg:address":"410 E Hallandale Beach Blvd",
    "sg:city":"Hallandale Beach",
    "sg:classifiers":[
        {
            "category":"Cinema",
            "subcategory":"Movie Rental",
            "type":"Entertainment"
        }
    ],
    "sg:phone":"+1 954 458 7453",
    "sg:postcode":"33009",
    "sg:province":"FL",
    "sg:tags":[
        "leasing",
        "video",
        "disc",
        "tape"
    ],
    "wof:name":"Video Coral",
    "wof:placetype":"venue"
},
  "geometry": {"coordinates":[-80.14334100000001,25.985655],"type":"Point"}
}