{
  "type": "Feature",
  "properties": {
    "addr:full":"13665 Automobile Blvd Clearwater FL 33762",
    "addr:postcode":"33762",
    "addr:street":"Automobile Blvd",
    "iso:country":"US",
    "sg:address":"13665 Automobile Blvd",
    "sg:city":"Clearwater",
    "sg:classifiers":[
        {
            "category":"Manufacturing",
            "subcategory":"Metals",
            "type":"Manufacturing & Wholesale Goods"
        }
    ],
    "sg:phone":"+1 727 572 9202",
    "sg:postcode":"33762",
    "sg:province":"FL",
    "sg:tags":[
        "mfg",
        "marine",
        "hardware",
        "equipment",
        "distributor",
        "supplies-wholesale"
    ],
    "sg:website":"http://www.acconmarine.com",
    "wof:name":"Accon Marine Inc",
    "wof:placetype":"venue"
},
  "geometry": {"coordinates":[-82.696381,27.896559],"type":"Point"}
}