{
  "type": "Feature",
  "properties": {
    "addr:full":"244 San Juan Cir Melbourne FL 32935",
    "addr:housenumber":"244",
    "addr:postcode":"32935",
    "addr:street":"San Juan Cir",
    "iso:country":"US",
    "sg:address":"244 San Juan Cir",
    "sg:city":"Melbourne",
    "sg:classifiers":[
        {
            "category":"Building & Trades",
            "subcategory":"Construction",
            "type":"Services"
        }
    ],
    "sg:phone":"+1 321 751 8748",
    "sg:postcode":"32935",
    "sg:province":"FL",
    "sg:tags":[
        "coping",
        "plastering",
        "tiling",
        "pool",
        "swimming"
    ],
    "wof:name":"Brothers Leak Masters",
    "wof:placetype":"venue"
},
  "geometry": {"coordinates":[-80.646614,28.137148],"type":"Point"}
}