{
  "type": "Feature",
  "properties": {
    "iso:country":"US",
    "sg:address":"13882 US Hwy 1",
    "sg:city":"Juno Beach",
    "sg:classifiers":[
        {
            "category":"Professional",
            "subcategory":"Business Services",
            "type":"Services"
        },
        {
            "category":"Building & Trades",
            "subcategory":"Construction",
            "type":"Services"
        }
    ],
    "sg:phone":"+1 561 624 7766",
    "sg:postcode":"33408",
    "sg:province":"FL",
    "sg:tags":[
        "consultant",
        "contractor",
        "design",
        "interior",
        "decorator",
        "carpentry"
    ],
    "sg:website":"www.kitchensoftheworld.com",
    "wof:name":"Hallmark Kitchens Inc",
    "wof:placetype":"venue"
},
  "geometry": {"coordinates":[-80.05583799999999,26.879776],"type":"Point"}
}