{
  "type": "Feature",
  "properties": {
    "addr:full":"18 Triangle Park Lake Placid FL 33852",
    "addr:housenumber":"18",
    "addr:postcode":"33852",
    "addr:street":"Triangle Park;Placid",
    "iso:country":"US",
    "sg:address":"18 Triangle Park",
    "sg:city":"Lake Placid",
    "sg:classifiers":[
        {
            "category":"Retail",
            "subcategory":"Repair Shop",
            "type":"Services"
        }
    ],
    "sg:phone":"+1 863 465 1716",
    "sg:postcode":"33852",
    "sg:province":"FL",
    "sg:tags":[
        "lock",
        "locksmith"
    ],
    "wof:name":"Taylor's Locksmith Svc",
    "wof:placetype":"venue"
},
  "geometry": {"coordinates":[-81.354618,27.298831],"type":"Point"}
}