{
  "type": "Feature",
  "properties": {
    "iso:country":"US",
    "sg:address":"3400 NE 12th Ave",
    "sg:city":"Oakland Park",
    "sg:classifiers":[
        {
            "category":"Manufacturing",
            "subcategory":"Printing",
            "type":"Manufacturing & Wholesale Goods"
        }
    ],
    "sg:phone":"+1 954 537 9590",
    "sg:postcode":"33334",
    "sg:province":"FL",
    "sg:tags":[
        "printer"
    ],
    "sg:website":"www.allegraftl.com",
    "wof:name":"Allegra Print & Imaging",
    "wof:placetype":"venue"
},
  "geometry": {"coordinates":[-80.131165,26.170484],"type":"Point"}
}