{
  "type": "Feature",
  "properties": {
    "iso:country":"US",
    "sg:address":"2715 27th Avenue Dr W",
    "sg:city":"Bradenton",
    "sg:classifiers":[
        {
            "category":"Professional",
            "subcategory":"Business Services",
            "type":"Services"
        }
    ],
    "sg:phone":"+1 941 753 7608",
    "sg:postcode":"34205",
    "sg:province":"FL",
    "sg:tags":[
        "notary"
    ],
    "wof:name":"Marriage Place",
    "wof:placetype":"venue"
},
  "geometry": {"coordinates":[-82.590636,27.475793],"type":"Point"}
}