{
  "type": "Feature",
  "properties": {
    "iso:country":"US",
    "sg:address":"8794 SW 8th St",
    "sg:city":"Miami",
    "sg:classifiers":[
        {
            "category":"Professional",
            "subcategory":"Business Services",
            "type":"Services"
        }
    ],
    "sg:phone":"+1 305 551 9440",
    "sg:postcode":"33174",
    "sg:province":"FL",
    "sg:tags":[
        "import",
        "importer",
        "representative"
    ],
    "wof:name":"Unique Import Usa",
    "wof:placetype":"venue"
},
  "geometry": {"coordinates":[-80.338078,25.761812],"type":"Point"}
}