{
  "type": "Feature",
  "properties": {
    "iso:country":"US",
    "sg:address":"1324 E Vine St",
    "sg:city":"Kissimmee",
    "sg:classifiers":[
        {
            "category":"Shopping",
            "subcategory":"Used Merchandise",
            "type":"Retail Goods"
        }
    ],
    "sg:phone":"+1 407 931 0001",
    "sg:postcode":"34744",
    "sg:province":"FL",
    "sg:tags":[
        "shop",
        "thrift"
    ],
    "wof:name":"Helping Kids Thrift & Gifts",
    "wof:placetype":"venue"
},
  "geometry": {"coordinates":[-81.386616,28.304092],"type":"Point"}
}