{
  "type": "Feature",
  "properties": {
    "iso:country":"US",
    "sg:address":"3181 S Ocean Dr",
    "sg:city":"Hallandale",
    "sg:classifiers":[
        {
            "category":"Professional",
            "type":"Services"
        }
    ],
    "sg:phone":"+1 954 454 8654",
    "sg:postcode":"33009",
    "sg:province":"FL",
    "wof:name":"Harry Italiener Dr",
    "wof:placetype":"venue"
},
  "geometry": {"coordinates":[-80.119378,25.98548],"type":"Point"}
}