{
  "type": "Feature",
  "properties": {
    "iso:country":"US",
    "sg:address":"3575 Bennington Dr",
    "sg:city":"Fort Myers",
    "sg:classifiers":[
        {
            "category":"Real Estate",
            "subcategory":"Real Estate Agent",
            "type":"Services"
        },
        {
            "category":"Real Estate",
            "subcategory":"Real Estate Operator",
            "type":"Services"
        }
    ],
    "sg:phone":"+1 239 277 0718",
    "sg:postcode":"33919",
    "sg:province":"FL",
    "sg:tags":[
        "condominium"
    ],
    "wof:name":"Cypress Lake Gardens Condomini",
    "wof:placetype":"venue"
},
  "geometry": {"coordinates":[-81.889687,26.544342],"type":"Point"}
}