{
  "type": "Feature",
  "properties": {
    "iso:country":"US",
    "sg:address":"4388 Real Ct",
    "sg:city":"Orlando",
    "sg:classifiers":[
        {
            "category":"Place Of Worship",
            "type":"Public Place"
        }
    ],
    "sg:phone":"+1 407 296 4768",
    "sg:postcode":"32808",
    "sg:province":"FL",
    "sg:tags":[
        "church"
    ],
    "wof:name":"The Rock Center Inc",
    "wof:placetype":"venue"
},
  "geometry": {"coordinates":[-81.43497600000001,28.590706],"type":"Point"}
}