{
  "type": "Feature",
  "properties": {
    "addr:full":"1407 Edmundshire Ln Orlando FL 32806",
    "addr:housenumber":"1407",
    "addr:postcode":"32806",
    "addr:street":"Edmundshire Ln",
    "iso:country":"US",
    "sg:address":"1407 Edmundshire Ln",
    "sg:city":"Orlando",
    "sg:classifiers":[
        {
            "category":"Professional",
            "subcategory":"Secretarial Services",
            "type":"Services"
        }
    ],
    "sg:phone":"+1 407 898 7282",
    "sg:postcode":"32806",
    "sg:province":"FL",
    "sg:tags":[
        "reporting"
    ],
    "sg:website":"www.pepperboxinc.com",
    "wof:name":"Pepper Box Inc",
    "wof:placetype":"venue"
},
  "geometry": {"coordinates":[-81.33296,28.525794],"type":"Point"}
}