{
  "type": "Feature",
  "properties": {
    "addr:full":"1337 Long Horn Rd Middleburg FL 32068",
    "addr:housenumber":"1337",
    "addr:postcode":"32068",
    "addr:street":"Long Horn Rd",
    "iso:country":"US",
    "sg:address":"1337 Long Horn Rd",
    "sg:city":"Middleburg",
    "sg:classifiers":[
        {
            "category":"Government",
            "subcategory":"Office",
            "type":"Public Place"
        }
    ],
    "sg:phone":"+1 904 291 5530",
    "sg:postcode":"32068",
    "sg:province":"FL",
    "wof:name":"Jennings State Forest",
    "wof:placetype":"venue"
},
  "geometry": {"coordinates":[-81.962203,30.12647],"type":"Point"}
}