{
  "type": "Feature",
  "properties": {
    "iso:country":"US",
    "sg:address":"877 Executive Center Dr W",
    "sg:city":"St Petersburg",
    "sg:classifiers":[
        {
            "category":"Professional",
            "subcategory":"Advertising",
            "type":"Services"
        }
    ],
    "sg:phone":"+1 727 573 2575",
    "sg:postcode":"33702",
    "sg:province":"FL",
    "sg:tags":[
        "counselor"
    ],
    "wof:name":"Devine Communications Corp",
    "wof:placetype":"venue"
},
  "geometry": {"coordinates":[-82.643027,27.860872],"type":"Point"}
}