{
  "type": "Feature",
  "properties": {
    "addr:full":"104 Monterey Pointe Dr Palm Beach Gardens FL 33418",
    "addr:housenumber":"104",
    "addr:postcode":"33418",
    "addr:street":"Monterey Pointe Dr",
    "iso:country":"US",
    "sg:address":"104 Monterey Pointe Dr",
    "sg:city":"Palm Beach Gardens",
    "sg:classifiers":[
        {
            "category":"Professional",
            "subcategory":"Management & Consulting",
            "type":"Services"
        }
    ],
    "sg:phone":"+1 561 776 8622",
    "sg:postcode":"33418",
    "sg:province":"FL",
    "wof:name":"Wmi Advisors",
    "wof:placetype":"venue"
},
  "geometry": {"coordinates":[-80.138368,26.8218],"type":"Point"}
}