{
  "type": "Feature",
  "properties": {
    "iso:country":"US",
    "sg:address":"160 Blountstown Hwy",
    "sg:city":"Tallahassee",
    "sg:classifiers":[
        {
            "category":"Food & Beverages",
            "subcategory":"Specialty",
            "type":"Retail Goods"
        }
    ],
    "sg:phone":"+1 850 574 9277",
    "sg:postcode":"32304",
    "sg:province":"FL",
    "wof:name":"D & A Nutrition Inc",
    "wof:placetype":"venue"
},
  "geometry": {"coordinates":[-84.349974,30.437534],"type":"Point"}
}