{
  "type": "Feature",
  "properties": {
    "addr:full":"5740 10th Ave SW Naples FL 34116",
    "addr:housenumber":"5740",
    "addr:postcode":"34116",
    "addr:street":"10Th Ave Sw",
    "iso:country":"US",
    "sg:address":"5740 10th Ave SW",
    "sg:city":"Naples",
    "sg:classifiers":[
        {
            "category":"Building & Trades",
            "subcategory":"Construction",
            "type":"Services"
        }
    ],
    "sg:phone":"+1 239 352 2648",
    "sg:postcode":"34116",
    "sg:province":"FL",
    "sg:tags":[
        "carpenter"
    ],
    "wof:name":"Millennium Trim",
    "wof:placetype":"venue"
},
  "geometry": {"coordinates":[-81.723508,26.210002],"type":"Point"}
}