{
  "type": "Feature",
  "properties": {
    "iso:country":"US",
    "sg:address":"118 W Cervantes St",
    "sg:city":"Pensacola",
    "sg:classifiers":[
        {
            "category":"Real Estate",
            "subcategory":"Real Estate Agent",
            "type":"Services"
        }
    ],
    "sg:phone":"+1 850 432 1526",
    "sg:postcode":"32501",
    "sg:province":"FL",
    "wof:name":"JBN Realty",
    "wof:placetype":"venue"
},
  "geometry": {"coordinates":[-87.219905,30.420973],"type":"Point"}
}