{
  "type": "Feature",
  "properties": {
    "addr:full":"13661 44th Pl N West Palm Beach FL 33411",
    "addr:housenumber":"13661",
    "addr:postcode":"33411",
    "addr:street":"44Th Pl N",
    "iso:country":"US",
    "sg:address":"13661 44th Pl N",
    "sg:city":"West Palm Beach",
    "sg:classifiers":[
        {
            "category":"Building & Trades",
            "subcategory":"Construction",
            "type":"Services"
        }
    ],
    "sg:phone":"+1 561 798 1739",
    "sg:postcode":"33411",
    "sg:province":"FL",
    "sg:tags":[
        "contractor"
    ],
    "wof:name":"Jims Welding",
    "wof:placetype":"venue"
},
  "geometry": {"coordinates":[-80.257462,26.742301],"type":"Point"}
}