{
  "type": "Feature",
  "properties": {
    "iso:country":"US",
    "sg:address":"569 Peck Ave",
    "sg:city":"Fort Myers",
    "sg:classifiers":[
        {
            "category":"Professional",
            "subcategory":"Business Services",
            "type":"Services"
        }
    ],
    "sg:phone":"+1 239 218 7599",
    "sg:postcode":"33919",
    "sg:province":"FL",
    "wof:name":"A W Restorations Inc",
    "wof:placetype":"venue"
},
  "geometry": {"coordinates":[-81.90867,26.563737],"type":"Point"}
}