{
  "type": "Feature",
  "properties": {
    "addr:full":"3184 NW 170th St Opa Locka FL 33056",
    "addr:housenumber":"3184",
    "addr:postcode":"33056",
    "addr:street":"Nw 170Th St;Locka",
    "iso:country":"US",
    "sg:address":"3184 NW 170th St",
    "sg:city":"Opa Locka",
    "sg:classifiers":[
        {
            "category":"Building & Trades",
            "subcategory":"Cleaning & Sanitation",
            "type":"Services"
        }
    ],
    "sg:phone":"+1 305 624 3754",
    "sg:postcode":"33056",
    "sg:province":"FL",
    "sg:tags":[
        "maintenance"
    ],
    "wof:name":"Dan Rohen Maintenance",
    "wof:placetype":"venue"
},
  "geometry": {"coordinates":[-80.25108299999999,25.929002],"type":"Point"}
}