{
  "type": "Feature",
  "properties": {
    "iso:country":"US",
    "sg:address":"4833 Lamar Dr",
    "sg:city":"Milton",
    "sg:classifiers":[
        {
            "category":"Retail",
            "subcategory":"Repair Shop",
            "type":"Services"
        }
    ],
    "sg:phone":"+1 850 995 1156",
    "sg:postcode":"32571",
    "sg:province":"FL",
    "sg:tags":[
        "sharpening"
    ],
    "wof:name":"Southern Sharpening",
    "wof:placetype":"venue"
},
  "geometry": {"coordinates":[-87.146574,30.611074],"type":"Point"}
}