{
  "type": "Feature",
  "properties": {
    "addr:full":"3301 SW 13th Ave Fort Lauderdale FL 33315",
    "addr:housenumber":"3301",
    "addr:postcode":"33315",
    "addr:street":"Sw 13Th Ave",
    "iso:country":"US",
    "sg:address":"3301 SW 13th Ave",
    "sg:city":"Fort Lauderdale",
    "sg:classifiers":[
        {
            "category":"Retail",
            "subcategory":"Repair Shop",
            "type":"Services"
        },
        {
            "category":"Airport",
            "type":"Transportation"
        }
    ],
    "sg:phone":"+1 954 764 2616",
    "sg:postcode":"33315",
    "sg:province":"FL",
    "sg:tags":[
        "engine",
        "aircraft",
        "station",
        "maintenance"
    ],
    "wof:name":"Complete Turbine Service LLC",
    "wof:placetype":"venue"
},
  "geometry": {"coordinates":[-80.158568,26.081484],"type":"Point"}
}