{
  "type": "Feature",
  "properties": {
    "addr:full":"1650 Cypress Dr Jupiter FL 33469",
    "addr:housenumber":"1650",
    "addr:postcode":"33469",
    "addr:street":"Cypress Dr",
    "iso:country":"US",
    "sg:address":"1650 Cypress Dr",
    "sg:city":"Jupiter",
    "sg:classifiers":[
        {
            "category":"Shopping",
            "subcategory":"Jewelry",
            "type":"Retail Goods"
        }
    ],
    "sg:phone":"+1 561 748 4552",
    "sg:postcode":"33469",
    "sg:province":"FL",
    "sg:tags":[
        "clocks"
    ],
    "wof:name":"It's About Time Clocks & Crsts",
    "wof:placetype":"venue"
},
  "geometry": {"coordinates":[-80.092456,26.965027],"type":"Point"}
}