{
  "type": "Feature",
  "properties": {
    "addr:full":"6900 SW 21st Ct Davie FL 33317",
    "addr:housenumber":"6900",
    "addr:postcode":"33317",
    "addr:street":"Sw 21St Ct",
    "iso:country":"US",
    "sg:address":"6900 SW 21st Ct",
    "sg:city":"Davie",
    "sg:classifiers":[
        {
            "category":"Shopping",
            "subcategory":"Computers & Home Electronics",
            "type":"Retail Goods"
        }
    ],
    "sg:phone":"+1 954 563 0438",
    "sg:postcode":"33317",
    "sg:province":"FL",
    "sg:tags":[
        "parts",
        "supply"
    ],
    "wof:name":"Universal Office Solutions",
    "wof:placetype":"venue"
},
  "geometry": {"coordinates":[-80.237747,26.092191],"type":"Point"}
}