{
  "type": "Feature",
  "properties": {
    "iso:country":"US",
    "sg:address":"8006 NW 90th St",
    "sg:city":"Medley",
    "sg:classifiers":[
        {
            "category":"Shopping",
            "subcategory":"Clothing, Apparel, & Fashions",
            "type":"Retail Goods"
        },
        {
            "category":"Shopping",
            "subcategory":"Crafts & Fabrics",
            "type":"Retail Goods"
        },
        {
            "category":"Professional",
            "subcategory":"Printing & Photocopies",
            "type":"Services"
        }
    ],
    "sg:phone":"+1 786 514 5578",
    "sg:postcode":"33166",
    "sg:province":"FL",
    "sg:tags":[
        "shop",
        "clothing",
        "screen",
        "services-commercial",
        "store"
    ],
    "sg:website":"http://www.topteezprinting.com",
    "wof:name":"A Top Teez Screen Printin",
    "wof:placetype":"venue"
},
  "geometry": {"coordinates":[-80.326025,25.855144],"type":"Point"}
}