{
  "type": "Feature",
  "properties": {
    "iso:country":"US",
    "sg:address":"19421 SW 119th Ave",
    "sg:city":"Miami",
    "sg:classifiers":[
        {
            "category":"Building & Trades",
            "subcategory":"Construction",
            "type":"Services"
        }
    ],
    "sg:phone":"+1 786 242 6614",
    "sg:postcode":"33177",
    "sg:province":"FL",
    "sg:tags":[
        "concrete",
        "contractor"
    ],
    "wof:name":"Palma Concrete Inc",
    "wof:placetype":"venue"
},
  "geometry": {"coordinates":[-80.38463,25.586787],"type":"Point"}
}