{
  "type": "Feature",
  "properties": {
    "iso:country":"US",
    "sg:address":"515 S Market Ave",
    "sg:city":"Fort Pierce",
    "sg:classifiers":[
        {
            "category":"Autos & Motor Vehicles",
            "subcategory":"Automobile Sales",
            "type":"Retail Goods"
        }
    ],
    "sg:phone":"+1 772 464 1566",
    "sg:postcode":"34982",
    "sg:province":"FL",
    "sg:tags":[
        "car",
        "dealer"
    ],
    "wof:name":"Ralph's Place",
    "wof:placetype":"venue"
},
  "geometry": {"coordinates":[-80.32959099999999,27.392405],"type":"Point"}
}