{
  "type": "Feature",
  "properties": {
    "iso:country":"US",
    "sg:address":"5320 Babcock St NE",
    "sg:city":"Palm Bay",
    "sg:classifiers":[
        {
            "category":"Education",
            "subcategory":"School",
            "type":"Public Place"
        }
    ],
    "sg:phone":"+1 321 723 8866",
    "sg:postcode":"32905",
    "sg:province":"FL",
    "sg:website":"www.st-joe.org",
    "wof:name":"St Joseph's Catholic School",
    "wof:placetype":"venue"
},
  "geometry": {"coordinates":[-80.622249,28.01488],"type":"Point"}
}