{
  "type": "Feature",
  "properties": {
    "iso:country":"US",
    "sg:address":"19715 NW 37th Ave",
    "sg:city":"Opa Locka",
    "sg:classifiers":[
        {
            "category":"Education",
            "subcategory":"Special Training",
            "type":"Public Place"
        }
    ],
    "sg:phone":"+1 305 621 1929",
    "sg:postcode":"33056",
    "sg:province":"FL",
    "wof:name":"Childrens Village The",
    "wof:placetype":"venue"
},
  "geometry": {"coordinates":[-80.26191300000001,25.953584],"type":"Point"}
}