{
  "type": "Feature",
  "properties": {
    "iso:country":"US",
    "sg:address":"4071 Laguna St",
    "sg:city":"Coral Gables",
    "sg:classifiers":[
        {
            "category":"Professional",
            "type":"Services"
        }
    ],
    "sg:phone":"+1 305 445 3291",
    "sg:postcode":"33146",
    "sg:province":"FL",
    "sg:tags":[
        "establishment"
    ],
    "wof:name":"Knowledge In Motion Inc",
    "wof:placetype":"venue"
},
  "geometry": {"coordinates":[-80.261092,25.733721],"type":"Point"}
}