{
  "type": "Feature",
  "properties": {
    "iso:country":"US",
    "sg:address":"9245 Lazy Ln",
    "sg:city":"Tampa",
    "sg:classifiers":[
        {
            "category":"Manufacturing",
            "subcategory":"Tools & Machinery",
            "type":"Manufacturing & Wholesale Goods"
        }
    ],
    "sg:phone":"+1 813 935 1841",
    "sg:postcode":"33614",
    "sg:province":"FL",
    "sg:tags":[
        "physician",
        "surgeon",
        "surgical",
        "mfg"
    ],
    "wof:name":"Blake Manufacturing Inc",
    "wof:placetype":"venue"
},
  "geometry": {"coordinates":[-82.506241,28.035048],"type":"Point"}
}