{
  "type": "Feature",
  "properties": {
    "iso:country":"US",
    "sg:address":"1061 Meyer Way",
    "sg:city":"Pensacola",
    "sg:classifiers":[
        {
            "category":"Building & Trades",
            "subcategory":"Construction",
            "type":"Services"
        }
    ],
    "sg:phone":"+1 850 469 0977",
    "sg:postcode":"32514",
    "sg:province":"FL",
    "sg:tags":[
        "home",
        "builder"
    ],
    "wof:name":"Adams Homes Of Nw Fl Inc",
    "wof:placetype":"venue"
},
  "geometry": {"coordinates":[-87.239278,30.512052],"type":"Point"}
}