{
  "type": "Feature",
  "properties": {
    "iso:country":"US",
    "sg:address":"4501 Howell Branch Rd",
    "sg:city":"Winter Park",
    "sg:classifiers":[
        {
            "category":"Recreation",
            "type":"Entertainment"
        }
    ],
    "sg:phone":"+1 407 671 5888",
    "sg:postcode":"32792",
    "sg:province":"FL",
    "sg:tags":[
        "stable"
    ],
    "wof:name":"Winter Park Farm",
    "wof:placetype":"venue"
},
  "geometry": {"coordinates":[-81.293656,28.623745],"type":"Point"}
}