{
  "type": "Feature",
  "properties": {
    "iso:country":"US",
    "sg:address":"2006 Cherokee Dr",
    "sg:city":"Neptune Beach",
    "sg:classifiers":[
        {
            "category":"Wholesale",
            "subcategory":"Sporting Goods",
            "type":"Manufacturing & Wholesale Goods"
        }
    ],
    "sg:phone":"+1 904 246 1667",
    "sg:postcode":"32266",
    "sg:province":"FL",
    "wof:name":"Sls of North Florida Inc",
    "wof:placetype":"venue"
},
  "geometry": {"coordinates":[-81.41861299999999,30.313014],"type":"Point"}
}