{
  "type": "Feature",
  "properties": {
    "addr:full":"615 N Old Corry Field Rd Pensacola FL 32506",
    "addr:housenumber":"615",
    "addr:postcode":"32506",
    "addr:street":"N Old Corry Field Rd",
    "iso:country":"US",
    "sg:address":"615 N Old Corry Field Rd",
    "sg:city":"Pensacola",
    "sg:classifiers":[
        {
            "category":"Building & Trades",
            "subcategory":"Cleaning & Sanitation",
            "type":"Services"
        }
    ],
    "sg:phone":"+1 850 453 8799",
    "sg:postcode":"32506",
    "sg:province":"FL",
    "sg:tags":[
        "janitor"
    ],
    "wof:name":"Clean Up Crew",
    "wof:placetype":"venue"
},
  "geometry": {"coordinates":[-87.272065,30.419474],"type":"Point"}
}