{
  "type": "Feature",
  "properties": {
    "iso:country":"US",
    "sg:address":"8836 N 56th St",
    "sg:city":"Tampa",
    "sg:classifiers":[
        {
            "category":"Banks & Credit Unions",
            "subcategory":"Bank",
            "type":"Services"
        }
    ],
    "sg:phone":"+1 813 984 7233",
    "sg:postcode":"33617",
    "sg:province":"FL",
    "sg:tags":[
        "depository",
        "banking"
    ],
    "wof:name":"Vimaheisas Multi Services",
    "wof:placetype":"venue"
},
  "geometry": {"coordinates":[-82.393541,28.032157],"type":"Point"}
}