{
  "type": "Feature",
  "properties": {
    "iso:country":"US",
    "sg:address":"17 Palmira Rd",
    "sg:city":"Debary",
    "sg:phone":"+1 386 668 6652",
    "sg:postcode":"32713",
    "sg:province":"FL",
    "wof:name":"Whitaker Air Conditioning",
    "wof:placetype":"venue"
},
  "geometry": {"coordinates":[-81.309123,28.880875],"type":"Point"}
}