{
  "type": "Feature",
  "properties": {
    "iso:country":"US",
    "sg:address":"311 E Highway 50",
    "sg:city":"Clermont",
    "sg:classifiers":[
        {
            "category":"Professional",
            "subcategory":"Accounting & Tax Preparation",
            "type":"Services"
        }
    ],
    "sg:phone":"+1 352 429 3254",
    "sg:postcode":"34711",
    "sg:province":"FL",
    "sg:tags":[
        "bookkeeping",
        "return",
        "billing",
        "preparation-business"
    ],
    "sg:website":"http://www.canii.com",
    "wof:name":"Can Ii Inc",
    "wof:placetype":"venue"
},
  "geometry": {"coordinates":[-81.751165,28.550388],"type":"Point"}
}