{
  "type": "Feature",
  "properties": {
    "iso:country":"US",
    "sg:address":"2131 S Terrace Blvd",
    "sg:city":"Longwood",
    "sg:classifiers":[
        {
            "category":"Banks & Credit Unions",
            "subcategory":"Financial Services",
            "type":"Services"
        }
    ],
    "sg:phone":"+1 407 869 5436",
    "sg:postcode":"32779",
    "sg:province":"FL",
    "sg:tags":[
        "company",
        "holding"
    ],
    "wof:name":"John Pirillo Holdings Inc",
    "wof:placetype":"venue"
},
  "geometry": {"coordinates":[-81.426267,28.69008],"type":"Point"}
}