{
  "type": "Feature",
  "properties": {
    "addr:full":"3611 Tamiami Trl N Naples FL 34103",
    "addr:housenumber":"3611",
    "addr:postcode":"34103",
    "addr:street":"Tamiami Trl N",
    "iso:country":"US",
    "sg:address":"3611 Tamiami Trl N",
    "sg:city":"Naples",
    "sg:classifiers":[
        {
            "category":"Home & Garden",
            "subcategory":"Building Materials",
            "type":"Retail Goods"
        }
    ],
    "sg:phone":"+1 239 275 5775",
    "sg:postcode":"34103",
    "sg:province":"FL",
    "sg:tags":[
        "door"
    ],
    "wof:name":"Robert Hunt Corp",
    "wof:placetype":"venue"
},
  "geometry": {"coordinates":[-81.80004700000001,26.190444],"type":"Point"}
}