{
  "type": "Feature",
  "properties": {
    "iso:country":"US",
    "sg:address":"444 Brickell Ave Ste 809",
    "sg:city":"Miami",
    "sg:classifiers":[
        {
            "category":"Parking",
            "type":"Transportation"
        }
    ],
    "sg:phone":"+1 305 374 8328",
    "sg:postcode":"33131",
    "sg:province":"FL",
    "wof:name":"Park America Inc",
    "wof:placetype":"venue"
},
  "geometry": {"coordinates":[-80.19010900000001,25.769374],"type":"Point"}
}