{
  "type": "Feature",
  "properties": {
    "addr:full":"440 Sawgrass Corporate Pkwy Fort Lauderdale FL 33325",
    "addr:housenumber":"440",
    "addr:postcode":"33325",
    "addr:street":"Sawgrass Corporate Pkwy",
    "iso:country":"US",
    "sg:address":"440 Sawgrass Corporate Pkwy",
    "sg:city":"Fort Lauderdale",
    "sg:classifiers":[
        {
            "category":"Health Services",
            "subcategory":"Doctor",
            "type":"Services"
        }
    ],
    "sg:phone":"+1 954 846 8202",
    "sg:postcode":"33325",
    "sg:province":"FL",
    "sg:tags":[
        "medical"
    ],
    "wof:name":"Gill Paredes MD",
    "wof:placetype":"venue"
},
  "geometry": {"coordinates":[-80.330961,26.125564],"type":"Point"}
}