{
  "type": "Feature",
  "properties": {
    "addr:full":"3581 1st St Bradenton FL 34208",
    "addr:housenumber":"3581",
    "addr:postcode":"34208",
    "addr:street":"1St St",
    "iso:country":"US",
    "sg:address":"3581 1st St",
    "sg:city":"Bradenton",
    "sg:classifiers":[
        {
            "category":"Shopping",
            "subcategory":"Optical Goods",
            "type":"Retail Goods"
        }
    ],
    "sg:phone":"+1 941 746 4300",
    "sg:postcode":"34208",
    "sg:province":"FL",
    "wof:name":"Lens Crafters",
    "wof:placetype":"venue"
},
  "geometry": {"coordinates":[-82.562854,27.469316],"type":"Point"}
}