{
  "type": "Feature",
  "properties": {
    "iso:country":"US",
    "sg:address":"829 S Main St",
    "sg:city":"Bell",
    "sg:classifiers":[
        {
            "category":"Food & Beverages",
            "subcategory":"Groceries & Convenience Stores",
            "type":"Retail Goods"
        }
    ],
    "sg:phone":"+1 352 463 7478",
    "sg:postcode":"32619",
    "sg:province":"FL",
    "wof:name":"Country Quick Stop Inc",
    "wof:placetype":"venue"
},
  "geometry": {"coordinates":[-82.860336,29.750001],"type":"Point"}
}