{
  "type": "Feature",
  "properties": {
    "iso:country":"US",
    "sg:address":"4061 Pittman Dr",
    "sg:city":"Jacksonville",
    "sg:classifiers":[
        {
            "category":"Building & Trades",
            "subcategory":"Landscaping Services",
            "type":"Services"
        }
    ],
    "sg:phone":"+1 904 733 8021",
    "sg:postcode":"32207",
    "sg:province":"FL",
    "sg:tags":[
        "landscape"
    ],
    "wof:name":"Broughton Landscape",
    "wof:placetype":"venue"
},
  "geometry": {"coordinates":[-81.606526,30.283138],"type":"Point"}
}