{
  "type": "Feature",
  "properties": {
    "addr:full":"4343 W Flagler St Coral Gables FL 33134",
    "addr:housenumber":"4343",
    "addr:postcode":"33134",
    "addr:street":"W Flagler St",
    "iso:country":"US",
    "sg:address":"4343 W Flagler St",
    "sg:city":"Coral Gables",
    "sg:classifiers":[
        {
            "category":"Education",
            "subcategory":"Special Training",
            "type":"Public Place"
        }
    ],
    "sg:phone":"+1 305 442 9223",
    "sg:postcode":"33134",
    "sg:province":"FL",
    "sg:tags":[
        "management"
    ],
    "wof:name":"Management Resources Inc",
    "wof:placetype":"venue"
},
  "geometry": {"coordinates":[-80.266417,25.77169],"type":"Point"}
}