{
  "type": "Feature",
  "properties": {
    "iso:country":"US",
    "sg:address":"2540 Skif Dr",
    "sg:city":"Orlando",
    "sg:classifiers":[
        {
            "category":"Home & Garden",
            "subcategory":"Carpets & Floor Coverings",
            "type":"Retail Goods"
        }
    ],
    "sg:phone":"+1 407 384 5742",
    "sg:postcode":"32812",
    "sg:province":"FL",
    "sg:tags":[
        "material"
    ],
    "wof:name":"Morton's Carpet Service",
    "wof:placetype":"venue"
},
  "geometry": {"coordinates":[-81.32420399999999,28.515802],"type":"Point"}
}