{
  "type": "Feature",
  "properties": {
    "iso:country":"US",
    "sg:address":"510 N Parramore Ave",
    "sg:city":"Orlando",
    "sg:classifiers":[
        {
            "category":"Retail",
            "subcategory":"Repair Shop",
            "type":"Services"
        },
        {
            "category":"Wholesale",
            "subcategory":"Electrical",
            "type":"Manufacturing & Wholesale Goods"
        }
    ],
    "sg:phone":"+1 407 841 8824",
    "sg:postcode":"32801",
    "sg:province":"FL",
    "sg:tags":[
        "r",
        "appliance",
        "parts",
        "accessory"
    ],
    "wof:name":"Southern Electric Co",
    "wof:placetype":"venue"
},
  "geometry": {"coordinates":[-81.38915,28.550122],"type":"Point"}
}