{
  "type": "Feature",
  "properties": {
    "addr:full":"611 Pine St Tarpon Springs FL 34689",
    "addr:housenumber":"611",
    "addr:postcode":"34689",
    "addr:street":"Pine St",
    "iso:country":"US",
    "sg:address":"611 Pine St",
    "sg:city":"Tarpon Springs",
    "sg:classifiers":[
        {
            "category":"Shopping",
            "subcategory":"Gifts & Souvenirs",
            "type":"Retail Goods"
        }
    ],
    "sg:phone":"+1 727 937 2134",
    "sg:postcode":"34689",
    "sg:province":"FL",
    "sg:tags":[
        "shop"
    ],
    "wof:name":"Nick's Sponges & Sharks Teeth",
    "wof:placetype":"venue"
},
  "geometry": {"coordinates":[-82.74655,28.150918],"type":"Point"}
}