{
  "type": "Feature",
  "properties": {
    "addr:full":"1011 N Pebble Beach Blvd Sun City Center FL 33573",
    "addr:housenumber":"1011",
    "addr:postcode":"33573",
    "addr:street":"N Pebble Beach Blvd",
    "iso:country":"US",
    "sg:address":"1011 N Pebble Beach Blvd",
    "sg:city":"Sun City Center",
    "sg:classifiers":[
        {
            "category":"Education",
            "subcategory":"Library",
            "type":"Public Place"
        }
    ],
    "sg:phone":"+1 813 634 1315",
    "sg:postcode":"33573",
    "sg:province":"FL",
    "wof:name":"Sun City Center Library",
    "wof:placetype":"venue"
},
  "geometry": {"coordinates":[-82.35278099999999,27.715684],"type":"Point"}
}