{
  "type": "Feature",
  "properties": {
    "iso:country":"US",
    "sg:address":"3725 SE Ocean Blvd",
    "sg:city":"Stuart",
    "sg:classifiers":[
        {
            "category":"Real Estate",
            "subcategory":"Real Estate Agent",
            "type":"Services"
        }
    ],
    "sg:phone":"+1 772 287 7676",
    "sg:postcode":"34996",
    "sg:province":"FL",
    "wof:name":"Waterfront Properties",
    "wof:placetype":"venue"
},
  "geometry": {"coordinates":[-80.200564,27.202818],"type":"Point"}
}