{
  "type": "Feature",
  "properties": {
    "iso:country":"US",
    "sg:address":"101 Margo Ln",
    "sg:city":"Longwood",
    "sg:phone":"+1 407 767 0440",
    "sg:postcode":"32750",
    "sg:province":"FL",
    "sg:tags":[
        "machine",
        "operator",
        "vending",
        "equipment"
    ],
    "wof:name":"Automatic Vending Enterprises",
    "wof:placetype":"venue"
},
  "geometry": {"coordinates":[-81.36742,28.715384],"type":"Point"}
}