{
  "type": "Feature",
  "properties": {
    "iso:country":"US",
    "sg:address":"601 Mac Ln",
    "sg:city":"Sebring",
    "sg:classifiers":[
        {
            "category":"Building & Trades",
            "subcategory":"Construction",
            "type":"Services"
        }
    ],
    "sg:phone":"+1 863 471 6594",
    "sg:postcode":"33875",
    "sg:province":"FL",
    "sg:tags":[
        "designer",
        "marine",
        "contractor"
    ],
    "wof:name":"JMS Marine Svc Inc",
    "wof:placetype":"venue"
},
  "geometry": {"coordinates":[-81.47211299999999,27.456303],"type":"Point"}
}