{
  "type": "Feature",
  "properties": {
    "addr:full":"940 NE Dixie Hwy Jensen Beach FL 34957",
    "addr:housenumber":"940",
    "addr:postcode":"34957",
    "addr:street":"Ne Dixie Hwy",
    "iso:country":"US",
    "sg:address":"940 NE Dixie Hwy",
    "sg:city":"Jensen Beach",
    "sg:classifiers":[
        {
            "category":"Building & Trades",
            "subcategory":"Plumbing",
            "type":"Services"
        }
    ],
    "sg:phone":"+1 772 334 3200",
    "sg:postcode":"34957",
    "sg:province":"FL",
    "sg:tags":[
        "conditioning",
        "air",
        "heating",
        "contractor"
    ],
    "wof:name":"Jensen Beach Air Conditioning",
    "wof:placetype":"venue"
},
  "geometry": {"coordinates":[-80.239818,27.219593],"type":"Point"}
}