{
  "type": "Feature",
  "properties": {
    "iso:country":"US",
    "sg:address":"3015 Ridgevale Cir",
    "sg:city":"Valrico",
    "sg:classifiers":[
        {
            "category":"Professional",
            "type":"Services"
        }
    ],
    "sg:phone":"+1 813 689 6199",
    "sg:postcode":"33594",
    "sg:province":"FL",
    "wof:name":"Raymond & Joycelyn L L C",
    "wof:placetype":"venue"
},
  "geometry": {"coordinates":[-82.25936299999999,27.898893],"type":"Point"}
}