{
  "type": "Feature",
  "properties": {
    "addr:full":"1919 NW 19th St Fort Lauderdale FL 33311",
    "addr:housenumber":"1919",
    "addr:postcode":"33311",
    "addr:street":"Nw 19Th St",
    "iso:country":"US",
    "sg:address":"1919 NW 19th St",
    "sg:city":"Fort Lauderdale",
    "sg:classifiers":[
        {
            "category":"Manufacturing",
            "subcategory":"Leather Goods",
            "type":"Manufacturing & Wholesale Goods"
        },
        {
            "category":"Wholesale",
            "subcategory":"Non-durable Goods",
            "type":"Manufacturing & Wholesale Goods"
        }
    ],
    "sg:phone":"+1 954 462 0800",
    "sg:postcode":"33311",
    "sg:province":"FL",
    "sg:tags":[
        "mfg",
        "motor",
        "vehicle"
    ],
    "wof:name":"Classic Soft Trim Inc",
    "wof:placetype":"venue"
},
  "geometry": {"coordinates":[-80.167748,26.151368],"type":"Point"}
}