{
  "type": "Feature",
  "properties": {
    "iso:country":"US",
    "sg:address":"29663 Richard Rd",
    "sg:city":"Big Pine Key",
    "sg:classifiers":[
        {
            "category":"Building & Trades",
            "subcategory":"Construction",
            "type":"Services"
        }
    ],
    "sg:phone":"+1 305 872 4659",
    "sg:postcode":"33043",
    "sg:province":"FL",
    "sg:tags":[
        "house"
    ],
    "wof:name":"Ob1 Builders Inc",
    "wof:placetype":"venue"
},
  "geometry": {"coordinates":[-81.368582,24.659766],"type":"Point"}
}