{
  "type": "Feature",
  "properties": {
    "addr:full":"1168 Eagles Watch Trl Winter Springs FL 32708",
    "addr:housenumber":"1168",
    "addr:postcode":"32708",
    "addr:street":"Eagles Watch Trl",
    "iso:country":"US",
    "sg:address":"1168 Eagles Watch Trl",
    "sg:city":"Winter Springs",
    "sg:classifiers":[
        {
            "category":"Professional",
            "subcategory":"Detective & Security Services",
            "type":"Services"
        }
    ],
    "sg:phone":"+1 407 671 6120",
    "sg:postcode":"32708",
    "sg:province":"FL",
    "sg:tags":[
        "car"
    ],
    "wof:name":"Contemporary Services Corp",
    "wof:placetype":"venue"
},
  "geometry": {"coordinates":[-81.27051899999999,28.653562],"type":"Point"}
}