{
  "type": "Feature",
  "properties": {
    "iso:country":"US",
    "sg:address":"6807 S Orange Ave",
    "sg:city":"Orlando",
    "sg:classifiers":[
        {
            "category":"Restaurant",
            "type":"Food & Drink"
        },
        {
            "category":"Food & Beverages",
            "subcategory":"Groceries & Convenience Stores",
            "type":"Retail Goods"
        }
    ],
    "sg:phone":"+1 407 859 4999",
    "sg:postcode":"32809",
    "sg:province":"FL",
    "sg:tags":[
        "delicatessen"
    ],
    "wof:name":"European Deli",
    "wof:placetype":"venue"
},
  "geometry": {"coordinates":[-81.36741000000001,28.464527],"type":"Point"}
}