{
  "type": "Feature",
  "properties": {
    "iso:country":"US",
    "sg:address":"4800 Palm Ave",
    "sg:city":"Hialeah",
    "sg:classifiers":[
        {
            "category":"Shopping",
            "subcategory":"Computers & Home Electronics",
            "type":"Retail Goods"
        }
    ],
    "sg:phone":"+1 305 819 8430",
    "sg:postcode":"33012",
    "sg:province":"FL",
    "sg:tags":[
        "television",
        "radio"
    ],
    "wof:name":"MJA For Radio Klaridad",
    "wof:placetype":"venue"
},
  "geometry": {"coordinates":[-80.283063,25.865189],"type":"Point"}
}