{
  "type": "Feature",
  "properties": {
    "iso:country":"US",
    "sg:address":"14914 SW 42nd Ter",
    "sg:city":"Miami",
    "sg:classifiers":[
        {
            "category":"Real Estate",
            "subcategory":"Real Estate Agent",
            "type":"Services"
        }
    ],
    "sg:phone":"+1 305 559 5291",
    "sg:postcode":"33185",
    "sg:province":"FL",
    "sg:tags":[
        "appraiser"
    ],
    "wof:name":"Mds Group Inc",
    "wof:placetype":"venue"
},
  "geometry": {"coordinates":[-80.435452,25.727484],"type":"Point"}
}