{
  "type": "Feature",
  "properties": {
    "iso:country":"US",
    "sg:address":"7255 Della Dr",
    "sg:city":"Orlando",
    "sg:classifiers":[
        {
            "category":"Education",
            "subcategory":"Library",
            "type":"Public Place"
        }
    ],
    "sg:phone":"+1 407 355 7400",
    "sg:postcode":"32819",
    "sg:province":"FL",
    "wof:name":"Orange County Library",
    "wof:placetype":"venue"
},
  "geometry": {"coordinates":[-81.489999,28.457777],"type":"Point"}
}