{
  "type": "Feature",
  "properties": {
    "addr:full":"9214 Tivoli Pl Boca Raton FL 33434",
    "addr:housenumber":"9214",
    "addr:postcode":"33434",
    "addr:street":"Tivoli Pl",
    "iso:country":"US",
    "sg:address":"9214 Tivoli Pl",
    "sg:city":"Boca Raton",
    "sg:classifiers":[
        {
            "category":"Professional",
            "subcategory":"Engineering",
            "type":"Services"
        }
    ],
    "sg:phone":"+1 561 488 2445",
    "sg:postcode":"33434",
    "sg:province":"FL",
    "wof:name":"Dr Inventech Inc",
    "wof:placetype":"venue"
},
  "geometry": {"coordinates":[-80.19027199999999,26.381236],"type":"Point"}
}