{
  "type": "Feature",
  "properties": {
    "addr:full":"545 Bayview Pkwy Nokomis FL 34275",
    "addr:housenumber":"545",
    "addr:postcode":"34275",
    "addr:street":"Bayview Pkwy",
    "iso:country":"US",
    "sg:address":"545 Bayview Pkwy",
    "sg:city":"Nokomis",
    "sg:classifiers":[
        {
            "category":"Wholesale",
            "subcategory":"Hardware",
            "type":"Manufacturing & Wholesale Goods"
        },
        {
            "category":"Home & Garden",
            "subcategory":"Hardware",
            "type":"Retail Goods"
        }
    ],
    "sg:phone":"+1 941 488 5390",
    "sg:postcode":"34275",
    "sg:province":"FL",
    "sg:tags":[
        "hardware-builders",
        "store"
    ],
    "wof:name":"Spring Cook Co",
    "wof:placetype":"venue"
},
  "geometry": {"coordinates":[-82.46170600000001,27.115442],"type":"Point"}
}