{
  "type": "Feature",
  "properties": {
    "addr:full":"7619 San Sebastian Way Naples FL 34109",
    "addr:housenumber":"7619",
    "addr:postcode":"34109",
    "addr:street":"San Sebastian Way",
    "iso:country":"US",
    "sg:address":"7619 San Sebastian Way",
    "sg:city":"Naples",
    "sg:classifiers":[
        {
            "category":"Professional",
            "subcategory":"Computer Services",
            "type":"Services"
        }
    ],
    "sg:phone":"+1 239 596 3760",
    "sg:postcode":"34109",
    "sg:province":"FL",
    "sg:tags":[
        "related"
    ],
    "wof:name":"Wspincom",
    "wof:placetype":"venue"
},
  "geometry": {"coordinates":[-81.784235,26.240479],"type":"Point"}
}