{
  "type": "Feature",
  "properties": {
    "iso:country":"US",
    "sg:address":"660 14th Ave",
    "sg:city":"Vero Beach",
    "sg:classifiers":[
        {
            "category":"Manufacturing",
            "subcategory":"Apparel",
            "type":"Manufacturing & Wholesale Goods"
        }
    ],
    "sg:phone":"+1 772 770 3235",
    "sg:postcode":"32962",
    "sg:province":"FL",
    "wof:name":"Creative Stitches",
    "wof:placetype":"venue"
},
  "geometry": {"coordinates":[-80.399551,27.613197],"type":"Point"}
}