{
  "type": "Feature",
  "properties": {
    "addr:full":"1819 Riverview Dr NE Melbourne FL 32901",
    "addr:housenumber":"1819",
    "addr:postcode":"32901",
    "addr:street":"Riverview Dr Ne",
    "iso:country":"US",
    "sg:address":"1819 Riverview Dr NE",
    "sg:city":"Melbourne",
    "sg:classifiers":[
        {
            "category":"Real Estate",
            "subcategory":"Real Estate Agent",
            "type":"Services"
        }
    ],
    "sg:phone":"+1 321 733 0800",
    "sg:postcode":"32901",
    "sg:province":"FL",
    "wof:name":"Brevards Best Realty Inc",
    "wof:placetype":"venue"
},
  "geometry": {"coordinates":[-80.602318,28.080423],"type":"Point"}
}