{
  "type": "Feature",
  "properties": {
    "addr:full":"15115 Race Track Rd Odessa FL 33556",
    "addr:housenumber":"15115",
    "addr:postcode":"33556",
    "addr:street":"Race Track Rd",
    "iso:country":"US",
    "sg:address":"15115 Race Track Rd",
    "sg:city":"Odessa",
    "sg:classifiers":[
        {
            "category":"Manufacturing",
            "subcategory":"Lumber",
            "type":"Manufacturing & Wholesale Goods"
        }
    ],
    "sg:phone":"+1 727 410 7776",
    "sg:postcode":"33556",
    "sg:province":"FL",
    "sg:tags":[
        "hardwood",
        "mill"
    ],
    "wof:name":"Roorda Buiders Inc",
    "wof:placetype":"venue"
},
  "geometry": {"coordinates":[-82.611926,28.088393],"type":"Point"}
}