{
  "type": "Feature",
  "properties": {
    "addr:full":"1132 NW 133rd Ct Miami FL 33182",
    "addr:housenumber":"1132",
    "addr:postcode":"33182",
    "addr:street":"Nw 133Rd Ct",
    "iso:country":"US",
    "sg:address":"1132 NW 133rd Ct",
    "sg:city":"Miami",
    "sg:classifiers":[
        {
            "category":"Shopping",
            "subcategory":"Party Supplies",
            "type":"Retail Goods"
        }
    ],
    "sg:phone":"+1 305 227 0111",
    "sg:postcode":"33182",
    "sg:province":"FL",
    "sg:tags":[
        "decoration",
        "favors"
    ],
    "wof:name":"Space Walk Of Miami",
    "wof:placetype":"venue"
},
  "geometry": {"coordinates":[-80.411581,25.781097],"type":"Point"}
}