{
  "type": "Feature",
  "properties": {
    "addr:full":"7540 S Federal Hwy Lantana FL 33462",
    "addr:housenumber":"7540",
    "addr:postcode":"33462",
    "addr:street":"S Federal Hwy",
    "iso:country":"US",
    "sg:address":"7540 S Federal Hwy",
    "sg:city":"Lantana",
    "sg:classifiers":[
        {
            "category":"Professional",
            "subcategory":"Accounting & Tax Preparation",
            "type":"Services"
        }
    ],
    "sg:phone":"+1 561 582 3046",
    "sg:postcode":"33462",
    "sg:province":"FL",
    "sg:tags":[
        "accountant"
    ],
    "wof:name":"Melendez & Assoc",
    "wof:placetype":"venue"
},
  "geometry": {"coordinates":[-80.05378,26.564862],"type":"Point"}
}