{
  "type": "Feature",
  "properties": {
    "iso:country":"US",
    "sg:address":"7351 Shoppes Dr",
    "sg:city":"Melbourne",
    "sg:classifiers":[
        {
            "category":"Utilities",
            "subcategory":"Mobile Phone",
            "type":"Services"
        },
        {
            "category":"Coffee & Tea",
            "type":"Food & Drink"
        }
    ],
    "sg:phone":"+1 321 254 0312",
    "sg:postcode":"32940",
    "sg:province":"FL",
    "sg:tags":[
        "shop",
        "wi-fi",
        "espresso",
        "hotspot",
        "restaurant"
    ],
    "sg:website":"http://www.starbuckscoffee.com",
    "wof:name":"Starbucks Coffee",
    "wof:placetype":"venue"
},
  "geometry": {"coordinates":[-80.72215799999999,28.230751],"type":"Point"}
}