{
  "type": "Feature",
  "properties": {
    "iso:country":"US",
    "sg:address":"5825 Derek Ave",
    "sg:city":"Sarasota",
    "sg:classifiers":[
        {
            "category":"Restaurant",
            "type":"Food & Drink"
        }
    ],
    "sg:menulink":"http://www.allmenus.com/fl/gulf-gate-osprey/189660-kfc---kentucky-fried-chicken/menu/",
    "sg:phone":"+1 941 926 3095",
    "sg:postcode":"34238",
    "sg:province":"FL",
    "sg:tags":[
        "american",
        "chicken"
    ],
    "wof:name":"KFC - Kentucky Fried Chicken",
    "wof:placetype":"venue"
},
  "geometry": {"coordinates":[-82.483535,27.268399],"type":"Point"}
}