{
  "type": "Feature",
  "properties": {
    "iso:country":"US",
    "sg:address":"511 Bayshore Dr",
    "sg:city":"Fort Lauderdale",
    "sg:classifiers":[
        {
            "category":"Organizations",
            "subcategory":"Non-profit Organization",
            "type":"Services"
        }
    ],
    "sg:phone":"+1 954 566 3748",
    "sg:postcode":"33304",
    "sg:province":"FL",
    "sg:tags":[
        "house",
        "construction",
        "social"
    ],
    "wof:name":"Davis Development Group Inc",
    "wof:placetype":"venue"
},
  "geometry": {"coordinates":[-80.105862,26.128],"type":"Point"}
}