{
  "type": "Feature",
  "properties": {
    "addr:full":"6235 Massachusetts Ave New Port Richey FL 34653",
    "addr:housenumber":"6235",
    "addr:postcode":"34653",
    "addr:street":"Massachusetts Ave",
    "iso:country":"US",
    "sg:address":"6235 Massachusetts Ave",
    "sg:city":"New Port Richey",
    "sg:classifiers":[
        {
            "category":"Building & Trades",
            "subcategory":"Plumbing",
            "type":"Services"
        }
    ],
    "sg:phone":"+1 727 848 2561",
    "sg:postcode":"34653",
    "sg:province":"FL",
    "sg:tags":[
        "conditioning",
        "air",
        "system",
        "contractor"
    ],
    "wof:name":"A & J Heating & Air Cond",
    "wof:placetype":"venue"
},
  "geometry": {"coordinates":[-82.711769,28.258795],"type":"Point"}
}