{
  "type": "Feature",
  "properties": {
    "iso:country":"US",
    "sg:address":"2390 Francis Ave",
    "sg:city":"Naples",
    "sg:classifiers":[
        {
            "category":"Wholesale",
            "subcategory":"Groceries",
            "type":"Manufacturing & Wholesale Goods"
        }
    ],
    "sg:phone":"+1 239 417 3500",
    "sg:postcode":"34112",
    "sg:province":"FL",
    "sg:tags":[
        "grocer"
    ],
    "wof:name":"Henry Lee Co",
    "wof:placetype":"venue"
},
  "geometry": {"coordinates":[-81.777306,26.136077],"type":"Point"}
}