{
  "type": "Feature",
  "properties": {
    "iso:country":"US",
    "sg:address":"8600 Bird Rd",
    "sg:city":"Miami",
    "sg:classifiers":[
        {
            "category":"Wholesale",
            "subcategory":"Plants",
            "type":"Manufacturing & Wholesale Goods"
        },
        {
            "category":"Shopping",
            "subcategory":"Crafts & Fabrics",
            "type":"Retail Goods"
        }
    ],
    "sg:phone":"+1 305 666 2121",
    "sg:postcode":"33155",
    "sg:province":"FL",
    "sg:tags":[
        "florists'",
        "supply",
        "florist",
        "supplies-wholesale",
        "plants-wholesale",
        "manufacturer"
    ],
    "wof:name":"Pineland Preserve Center Condominium Association",
    "wof:placetype":"venue"
},
  "geometry": {"coordinates":[-80.335263,25.733004],"type":"Point"}
}