{
  "type": "Feature",
  "properties": {
    "addr:full":"2108 Orchid St Sarasota FL 34239",
    "addr:housenumber":"2108",
    "addr:postcode":"34239",
    "addr:street":"Orchid St",
    "iso:country":"US",
    "sg:address":"2108 Orchid St",
    "sg:city":"Sarasota",
    "sg:classifiers":[
        {
            "category":"Building & Trades",
            "subcategory":"Construction",
            "type":"Services"
        }
    ],
    "sg:phone":"+1 941 362 7719",
    "sg:postcode":"34239",
    "sg:province":"FL",
    "sg:tags":[
        "tile",
        "dealer"
    ],
    "wof:name":"Imaginative Marble",
    "wof:placetype":"venue"
},
  "geometry": {"coordinates":[-82.52653599999999,27.303708],"type":"Point"}
}