{
  "type": "Feature",
  "properties": {
    "iso:country":"US",
    "sg:address":"4414 Ginny Dr",
    "sg:city":"Lakeland",
    "sg:classifiers":[
        {
            "category":"Professional",
            "subcategory":"Secretarial Services",
            "type":"Services"
        }
    ],
    "sg:phone":"+1 863 701 7028",
    "sg:postcode":"33811",
    "sg:province":"FL",
    "sg:tags":[
        "reporting"
    ],
    "wof:name":"R & R Processing Inc",
    "wof:placetype":"venue"
},
  "geometry": {"coordinates":[-81.99276,27.982718],"type":"Point"}
}