{
  "type": "Feature",
  "properties": {
    "addr:full":"7661 NW 68th St Miami FL 33166",
    "addr:housenumber":"7661",
    "addr:postcode":"33166",
    "addr:street":"Nw 68Th St",
    "iso:country":"US",
    "sg:address":"7661 NW 68th St",
    "sg:city":"Miami",
    "sg:classifiers":[
        {
            "category":"Professional",
            "subcategory":"Lawyer & Legal Services",
            "type":"Services"
        }
    ],
    "sg:phone":"+1 305 883 8585",
    "sg:postcode":"33166",
    "sg:province":"FL",
    "sg:tags":[
        "case"
    ],
    "sg:website":"http://www.dijaro.com",
    "wof:name":"Kar Fix Inc",
    "wof:placetype":"venue"
},
  "geometry": {"coordinates":[-80.32116600000001,25.83527],"type":"Point"}
}