{
  "type": "Feature",
  "properties": {
    "iso:country":"US",
    "sg:address":"407 Pomont Ave",
    "sg:city":"St Augustine",
    "sg:classifiers":[
        {
            "category":"Building & Trades",
            "subcategory":"Construction",
            "type":"Services"
        }
    ],
    "sg:phone":"+1 904 824 6619",
    "sg:postcode":"32084",
    "sg:province":"FL",
    "sg:tags":[
        "general",
        "contractor"
    ],
    "wof:name":"Thurston Brothers Construction",
    "wof:placetype":"venue"
},
  "geometry": {"coordinates":[-81.343763,29.911015],"type":"Point"}
}