{
  "type": "Feature",
  "properties": {
    "iso:country":"US",
    "sg:address":"1740 Main St NE",
    "sg:city":"Palm Bay",
    "sg:classifiers":[
        {
            "category":"Retail",
            "subcategory":"Auto Repair",
            "type":"Services"
        }
    ],
    "sg:phone":"+1 321 728 7800",
    "sg:postcode":"32905",
    "sg:province":"FL",
    "sg:tags":[
        "machine",
        "automobile",
        "shop",
        "automotive"
    ],
    "wof:name":"Alan's Automotive Machine",
    "wof:placetype":"venue"
},
  "geometry": {"coordinates":[-80.58801099999999,28.042372],"type":"Point"}
}