{
  "type": "Feature",
  "properties": {
    "addr:full":"5864 5th Ave S St Petersburg FL 33707",
    "addr:housenumber":"5864",
    "addr:postcode":"33707",
    "addr:street":"5Th Ave S",
    "iso:country":"US",
    "sg:address":"5864 5th Ave S",
    "sg:city":"St Petersburg",
    "sg:classifiers":[
        {
            "category":"Building & Trades",
            "subcategory":"Landscaping Services",
            "type":"Services"
        }
    ],
    "sg:phone":"+1 727 449 9191",
    "sg:postcode":"33707",
    "sg:province":"FL",
    "sg:tags":[
        "tree"
    ],
    "wof:name":"Tree Dudes",
    "wof:placetype":"venue"
},
  "geometry": {"coordinates":[-82.71301800000001,27.76635],"type":"Point"}
}