{
  "type": "Feature",
  "properties": {
    "addr:full":"2088 W Busch Blvd Tampa FL 33612",
    "addr:housenumber":"2088",
    "addr:postcode":"33612",
    "addr:street":"W Busch Blvd",
    "iso:country":"US",
    "sg:address":"2088 W Busch Blvd",
    "sg:city":"Tampa",
    "sg:classifiers":[
        {
            "category":"Personal",
            "subcategory":"Beauty Salon",
            "type":"Services"
        }
    ],
    "sg:phone":"+1 813 933 4356",
    "sg:postcode":"33612",
    "sg:province":"FL",
    "sg:tags":[
        "shop"
    ],
    "wof:name":"Head's Up Styling Salon",
    "wof:placetype":"venue"
},
  "geometry": {"coordinates":[-82.479263,28.033356],"type":"Point"}
}