{
  "type": "Feature",
  "properties": {
    "iso:country":"US",
    "sg:address":"66 W Flagler St Ste 300",
    "sg:city":"Miami",
    "sg:classifiers":[
        {
            "category":"Professional",
            "subcategory":"Lawyer & Legal Services",
            "type":"Services"
        }
    ],
    "sg:phone":"+1 305 374 9099",
    "sg:postcode":"33130",
    "sg:province":"FL",
    "wof:name":"Ayala Julio J PA",
    "wof:placetype":"venue"
},
  "geometry": {"coordinates":[-80.194996,25.774072],"type":"Point"}
}