{
  "type": "Feature",
  "properties": {
    "addr:full":"2523 Cedar Ln Panama City FL 32405",
    "addr:housenumber":"2523",
    "addr:postcode":"32405",
    "addr:street":"Cedar Ln",
    "iso:country":"US",
    "sg:address":"2523 Cedar Ln",
    "sg:city":"Panama City",
    "sg:classifiers":[
        {
            "category":"Wholesale",
            "subcategory":"Machinery & Supplies",
            "type":"Manufacturing & Wholesale Goods"
        }
    ],
    "sg:phone":"+1 850 769 5990",
    "sg:postcode":"32405",
    "sg:province":"FL",
    "sg:tags":[
        "car"
    ],
    "wof:name":"Ken's Auto Care",
    "wof:placetype":"venue"
},
  "geometry": {"coordinates":[-85.62849900000001,30.181379],"type":"Point"}
}