{
  "type": "Feature",
  "properties": {
    "iso:country":"US",
    "sg:address":"122 W Palm Ave",
    "sg:city":"Tampa",
    "sg:classifiers":[
        {
            "category":"Restaurant",
            "type":"Food & Drink"
        }
    ],
    "sg:phone":"+1 813 228 8227",
    "sg:postcode":"33602",
    "sg:province":"FL",
    "sg:tags":[
        "eating"
    ],
    "wof:name":"Eve Catering Service",
    "wof:placetype":"venue"
},
  "geometry": {"coordinates":[-82.46207699999999,27.962205],"type":"Point"}
}