{
  "type": "Feature",
  "properties": {
    "iso:country":"US",
    "sg:address":"7431 W Atlantic Ave",
    "sg:city":"Delray Beach",
    "sg:classifiers":[
        {
            "category":"Shopping",
            "subcategory":"Department Store",
            "type":"Retail Goods"
        }
    ],
    "sg:phone":"+1 561 638 3660",
    "sg:postcode":"33446",
    "sg:province":"FL",
    "sg:tags":[
        "shop"
    ],
    "wof:name":"Dollar Tree",
    "wof:placetype":"venue"
},
  "geometry": {"coordinates":[-80.162251,26.45379],"type":"Point"}
}