{
  "type": "Feature",
  "properties": {
    "iso:country":"US",
    "sg:address":"555 S Federal Hwy",
    "sg:city":"Boca Raton",
    "sg:classifiers":[
        {
            "category":"Professional",
            "subcategory":"Management & Consulting",
            "type":"Services"
        },
        {
            "category":"Professional",
            "subcategory":"Advertising",
            "type":"Services"
        }
    ],
    "sg:phone":"+1 561 620 3880",
    "sg:postcode":"33432",
    "sg:province":"FL",
    "sg:tags":[
        "marketing",
        "program"
    ],
    "wof:name":"Radiate Group Inc",
    "wof:placetype":"venue"
},
  "geometry": {"coordinates":[-80.086378,26.344932],"type":"Point"}
}