{
  "type": "Feature",
  "properties": {
    "iso:country":"US",
    "sg:address":"2909 Barrett Rd",
    "sg:city":"Jacksonville",
    "sg:classifiers":[
        {
            "category":"Building & Trades",
            "subcategory":"Cleaning & Sanitation",
            "type":"Services"
        }
    ],
    "sg:phone":"+1 904 646 0963",
    "sg:postcode":"32246",
    "sg:province":"FL",
    "sg:tags":[
        "house"
    ],
    "wof:name":"Brenda Faith Volpe Cleaning",
    "wof:placetype":"venue"
},
  "geometry": {"coordinates":[-81.54779000000001,30.293584],"type":"Point"}
}