{
  "type": "Feature",
  "properties": {
    "addr:full":"4186 NW 6th Ct Deerfield Beach FL 33442",
    "addr:housenumber":"4186",
    "addr:postcode":"33442",
    "addr:street":"Nw 6Th Ct",
    "iso:country":"US",
    "sg:address":"4186 NW 6th Ct",
    "sg:city":"Deerfield Beach",
    "sg:classifiers":[
        {
            "category":"Home & Garden",
            "subcategory":"Hardware",
            "type":"Retail Goods"
        }
    ],
    "sg:phone":"+1 754 264 3204",
    "sg:postcode":"33442",
    "sg:province":"FL",
    "wof:name":"M Kaposi Tools Inc",
    "wof:placetype":"venue"
},
  "geometry": {"coordinates":[-80.161919,26.324795],"type":"Point"}
}