{
  "type": "Feature",
  "properties": {
    "addr:full":"4552 Eagle Key Cir Naples FL 34112",
    "addr:housenumber":"4552",
    "addr:postcode":"34112",
    "addr:street":"Eagle Key Cir",
    "iso:country":"US",
    "sg:address":"4552 Eagle Key Cir",
    "sg:city":"Naples",
    "sg:classifiers":[
        {
            "category":"Professional",
            "subcategory":"Business Services",
            "type":"Services"
        }
    ],
    "sg:phone":"+1 239 649 7768",
    "sg:postcode":"34112",
    "sg:province":"FL",
    "sg:tags":[
        "interior",
        "consultant",
        "design",
        "decorator"
    ],
    "wof:name":"Vander Zee Interiors",
    "wof:placetype":"venue"
},
  "geometry": {"coordinates":[-81.75145999999999,26.128832],"type":"Point"}
}