{
  "type": "Feature",
  "properties": {
    "iso:country":"US",
    "sg:address":"3527 Cocoplum Cir",
    "sg:city":"Pompano Beach",
    "sg:classifiers":[
        {
            "category":"Communications",
            "subcategory":"Film & Video Production",
            "type":"Services"
        }
    ],
    "sg:phone":"+1 954 977 8970",
    "sg:postcode":"33063",
    "sg:province":"FL",
    "sg:tags":[
        "motion"
    ],
    "wof:name":"9546462969",
    "wof:placetype":"venue"
},
  "geometry": {"coordinates":[-80.189651,26.26714],"type":"Point"}
}