{
  "type": "Feature",
  "properties": {
    "iso:country":"US",
    "sg:address":"4825 NW 103rd Way",
    "sg:city":"Pompano Beach",
    "sg:classifiers":[
        {
            "category":"Recreation",
            "type":"Entertainment"
        }
    ],
    "sg:phone":"+1 954 978 6169",
    "sg:postcode":"33076",
    "sg:province":"FL",
    "wof:name":"Dan Daley Stables",
    "wof:placetype":"venue"
},
  "geometry": {"coordinates":[-80.26262199999999,26.290059],"type":"Point"}
}