{
  "type": "Feature",
  "properties": {
    "iso:country":"US",
    "sg:address":"2305 Killearn Center Blvd",
    "sg:city":"Tallahassee",
    "sg:classifiers":[
        {
            "category":"Building & Trades",
            "subcategory":"Construction",
            "type":"Services"
        }
    ],
    "sg:phone":"+1 850 284 6854",
    "sg:postcode":"32309",
    "sg:province":"FL",
    "sg:tags":[
        "painter"
    ],
    "wof:name":"David Hendrix Painting Inc",
    "wof:placetype":"venue"
},
  "geometry": {"coordinates":[-84.245198,30.505914],"type":"Point"}
}