{
  "type": "Feature",
  "properties": {
    "addr:full":"13249 Glacier National Dr Orlando FL 32837",
    "addr:housenumber":"13249",
    "addr:postcode":"32837",
    "addr:street":"Glacier National Dr",
    "iso:country":"US",
    "sg:address":"13249 Glacier National Dr",
    "sg:city":"Orlando",
    "sg:classifiers":[
        {
            "category":"Manufacturing",
            "subcategory":"Chemicals & Compounds",
            "type":"Manufacturing & Wholesale Goods"
        }
    ],
    "sg:phone":"+1 407 816 3680",
    "sg:postcode":"32837",
    "sg:province":"FL",
    "sg:tags":[
        "preparation",
        "mfg"
    ],
    "wof:name":"Friendly Inks Systems",
    "wof:placetype":"venue"
},
  "geometry": {"coordinates":[-81.42455099999999,28.371704],"type":"Point"}
}