{
  "type": "Feature",
  "properties": {
    "addr:full":"2816 Annette Cir Jacksonville FL 32216",
    "addr:housenumber":"2816",
    "addr:postcode":"32216",
    "addr:street":"Annette Cir",
    "iso:country":"US",
    "sg:address":"2816 Annette Cir",
    "sg:city":"Jacksonville",
    "sg:classifiers":[
        {
            "category":"Professional",
            "type":"Services"
        }
    ],
    "sg:phone":"+1 904 724 0302",
    "sg:postcode":"32216",
    "sg:province":"FL",
    "wof:name":"Pumpkin Hill Inc",
    "wof:placetype":"venue"
},
  "geometry": {"coordinates":[-81.58837699999999,30.275823],"type":"Point"}
}