{
  "type": "Feature",
  "properties": {
    "iso:country":"US",
    "sg:address":"5702 Green Island Dr",
    "sg:city":"Lake Worth",
    "sg:classifiers":[
        {
            "category":"Retail",
            "subcategory":"Repair Shop",
            "type":"Services"
        }
    ],
    "sg:phone":"+1 561 689 9715",
    "sg:postcode":"33463",
    "sg:province":"FL",
    "sg:tags":[
        "refrigerator",
        "freezer"
    ],
    "wof:name":"Temp Tech Svc",
    "wof:placetype":"venue"
},
  "geometry": {"coordinates":[-80.13258,26.573071],"type":"Point"}
}