{
  "type": "Feature",
  "properties": {
    "iso:country":"US",
    "sg:address":"5330 N Pine Hills Rd",
    "sg:city":"Orlando",
    "sg:classifiers":[
        {
            "category":"Professional",
            "subcategory":"Secretarial Services",
            "type":"Services"
        }
    ],
    "sg:phone":"+1 407 295 3774",
    "sg:postcode":"32808",
    "sg:province":"FL",
    "sg:tags":[
        "reporting",
        "court"
    ],
    "wof:name":"Invisible Secretary",
    "wof:placetype":"venue"
},
  "geometry": {"coordinates":[-81.451493,28.607577],"type":"Point"}
}