{
  "type": "Feature",
  "properties": {
    "iso:country":"US",
    "sg:address":"8001 Woodland Center Blvd",
    "sg:city":"Tampa",
    "sg:classifiers":[
        {
            "category":"Real Estate",
            "subcategory":"Real Estate Agent",
            "type":"Services"
        }
    ],
    "sg:phone":"+1 813 887 4200",
    "sg:postcode":"33614",
    "sg:province":"FL",
    "sg:tags":[
        "management"
    ],
    "wof:name":"Greystar Management Services",
    "wof:placetype":"venue"
},
  "geometry": {"coordinates":[-82.524141,28.02547],"type":"Point"}
}