{
  "type": "Feature",
  "properties": {
    "iso:country":"US",
    "sg:address":"9672 Pines Blvd",
    "sg:city":"Pembroke Pines",
    "sg:classifiers":[
        {
            "category":"Banks & Credit Unions",
            "subcategory":"Bank",
            "type":"Services"
        }
    ],
    "sg:phone":"+1 954 392 1155",
    "sg:postcode":"33024",
    "sg:province":"FL",
    "sg:tags":[
        "loan",
        "real estate"
    ],
    "wof:name":"Transam Lending Group Inc",
    "wof:placetype":"venue"
},
  "geometry": {"coordinates":[-80.274047,26.008405],"type":"Point"}
}