{
  "type": "Feature",
  "properties": {
    "iso:country":"US",
    "sg:address":"8912 Hannigan Ct",
    "sg:city":"Tampa",
    "sg:classifiers":[
        {
            "category":"Shopping",
            "subcategory":"Gifts & Souvenirs",
            "type":"Retail Goods"
        }
    ],
    "sg:phone":"+1 813 926 0877",
    "sg:postcode":"33626",
    "sg:province":"FL",
    "wof:name":"Premier Baskets",
    "wof:placetype":"venue"
},
  "geometry": {"coordinates":[-82.58650400000001,28.064802],"type":"Point"}
}