{
  "type": "Feature",
  "properties": {
    "addr:full":"122 Seminole Ln Boca Raton FL 33487",
    "addr:housenumber":"122",
    "addr:postcode":"33487",
    "addr:street":"Seminole Ln",
    "iso:country":"US",
    "sg:address":"122 Seminole Ln",
    "sg:city":"Boca Raton",
    "sg:classifiers":[
        {
            "category":"Wholesale",
            "subcategory":"Durable Goods & Equipment",
            "type":"Manufacturing & Wholesale Goods"
        }
    ],
    "sg:phone":"+1 561 988 7090",
    "sg:postcode":"33487",
    "sg:province":"FL",
    "sg:tags":[
        "exporter"
    ],
    "wof:name":"Pet Labs",
    "wof:placetype":"venue"
},
  "geometry": {"coordinates":[-80.08034499999999,26.422267],"type":"Point"}
}