{
  "type": "Feature",
  "properties": {
    "addr:full":"34 US Hwy 92 Debary FL 32713",
    "addr:housenumber":"34",
    "addr:postcode":"32713",
    "addr:street":"Us Hwy 92",
    "iso:country":"US",
    "sg:address":"34 US Hwy 92",
    "sg:city":"Debary",
    "sg:classifiers":[
        {
            "category":"Restaurant",
            "type":"Food & Drink"
        }
    ],
    "sg:phone":"+1 386 668 9307",
    "sg:postcode":"32713",
    "sg:province":"FL",
    "wof:name":"Gentili's Pizza",
    "wof:placetype":"venue"
},
  "geometry": {"coordinates":[-81.30842,28.884205],"type":"Point"}
}