{
  "type": "Feature",
  "properties": {
    "addr:full":"2381 Hillcreek Cir E Clearwater FL 33759",
    "addr:housenumber":"2381",
    "addr:postcode":"33759",
    "addr:street":"Hillcreek Cir E",
    "iso:country":"US",
    "sg:address":"2381 Hillcreek Cir E",
    "sg:city":"Clearwater",
    "sg:classifiers":[
        {
            "category":"Health Services",
            "subcategory":"Doctor",
            "type":"Services"
        }
    ],
    "sg:phone":"+1 727 791 0101",
    "sg:postcode":"33759",
    "sg:province":"FL",
    "wof:name":"Ernest Rillman DMD",
    "wof:placetype":"venue"
},
  "geometry": {"coordinates":[-82.713646,28.008466],"type":"Point"}
}