{
  "type": "Feature",
  "properties": {
    "iso:country":"US",
    "sg:address":"660 Azalea Ct",
    "sg:city":"Fort Lauderdale",
    "sg:classifiers":[
        {
            "category":"Professional",
            "type":"Services"
        }
    ],
    "sg:phone":"+1 954 791 5713",
    "sg:postcode":"33317",
    "sg:province":"FL",
    "wof:name":"Leveritt & Sons Inc",
    "wof:placetype":"venue"
},
  "geometry": {"coordinates":[-80.228959,26.131289],"type":"Point"}
}