{
  "type": "Feature",
  "properties": {
    "iso:country":"US",
    "sg:address":"7205 NW 68th St",
    "sg:city":"Miami",
    "sg:classifiers":[
        {
            "category":"Wholesale",
            "subcategory":"Durable Goods & Equipment",
            "type":"Manufacturing & Wholesale Goods"
        }
    ],
    "sg:phone":"+1 305 887 2279",
    "sg:postcode":"33166",
    "sg:province":"FL",
    "sg:tags":[
        "exporter"
    ],
    "wof:name":"Miam Transworld Co",
    "wof:placetype":"venue"
},
  "geometry": {"coordinates":[-80.31505900000001,25.83532],"type":"Point"}
}