{
  "type": "Feature",
  "properties": {
    "addr:full":"5736 US Hwy 19 New Port Richey FL 34652",
    "addr:housenumber":"5736",
    "addr:postcode":"34652",
    "addr:street":"Us Hwy 19",
    "iso:country":"US",
    "sg:address":"5736 US Hwy 19",
    "sg:city":"New Port Richey",
    "sg:classifiers":[
        {
            "category":"Autos & Motor Vehicles",
            "subcategory":"Fuel & Gas Station",
            "type":"Retail Goods"
        }
    ],
    "sg:phone":"+1 727 841 8040",
    "sg:postcode":"34652",
    "sg:province":"FL",
    "sg:tags":[
        "grocery",
        "station",
        "gasoline"
    ],
    "wof:name":"Sunoco",
    "wof:placetype":"venue"
},
  "geometry": {"coordinates":[-82.727681,28.243583],"type":"Point"}
}