{
  "type": "Feature",
  "properties": {
    "iso:country":"US",
    "sg:address":"20205 NE 15th Ct",
    "sg:city":"Miami",
    "sg:classifiers":[
        {
            "category":"Communications",
            "subcategory":"Film & Video Production",
            "type":"Services"
        }
    ],
    "sg:phone":"+1 305 493 7635",
    "sg:postcode":"33179",
    "sg:province":"FL",
    "sg:tags":[
        "picture",
        "companies-film",
        "producer",
        "tv",
        "services-commercial",
        "motion",
        "studio",
        "radio"
    ],
    "wof:name":"Steve Procko Productions",
    "wof:placetype":"venue"
},
  "geometry": {"coordinates":[-80.171048,25.959546],"type":"Point"}
}