{
  "type": "Feature",
  "properties": {
    "addr:full":"14306 Kids Ln Panama City FL 32409",
    "addr:postcode":"32409",
    "addr:street":"Kids Ln",
    "iso:country":"US",
    "sg:address":"14306 Kids Ln",
    "sg:city":"Panama City",
    "sg:classifiers":[
        {
            "category":"Building & Trades",
            "subcategory":"Plumbing",
            "type":"Services"
        }
    ],
    "sg:phone":"+1 850 265 6393",
    "sg:postcode":"32409",
    "sg:province":"FL",
    "sg:tags":[
        "contractor"
    ],
    "wof:name":"Donn Air Conditioning",
    "wof:placetype":"venue"
},
  "geometry": {"coordinates":[-85.666765,30.41115],"type":"Point"}
}