{
  "type": "Feature",
  "properties": {
    "iso:country":"US",
    "sg:address":"5848 Bee Ridge Rd",
    "sg:city":"Sarasota",
    "sg:classifiers":[
        {
            "category":"Deli",
            "type":"Food & Drink"
        },
        {
            "category":"Restaurant",
            "type":"Food & Drink"
        }
    ],
    "sg:phone":"+1 941 378 0545",
    "sg:postcode":"34233",
    "sg:province":"FL",
    "sg:tags":[
        "delicatessen"
    ],
    "wof:name":"Big City",
    "wof:placetype":"venue"
},
  "geometry": {"coordinates":[-82.452684,27.298771],"type":"Point"}
}