{
  "type": "Feature",
  "properties": {
    "iso:country":"US",
    "sg:address":"2973 W State Rd 434",
    "sg:city":"Longwood",
    "sg:classifiers":[
        {
            "category":"Banks & Credit Unions",
            "subcategory":"Bank",
            "type":"Services"
        }
    ],
    "sg:phone":"+1 407 869 8288",
    "sg:postcode":"32779",
    "sg:province":"FL",
    "sg:tags":[
        "loan",
        "broker",
        "real estate"
    ],
    "wof:name":"Custom Funding and Investments",
    "wof:placetype":"venue"
},
  "geometry": {"coordinates":[-81.412898,28.687106],"type":"Point"}
}