{
  "type": "Feature",
  "properties": {
    "addr:full":"909 SE 1st Ave Ste 100 Miami FL 33131",
    "addr:housenumber":"909",
    "addr:postcode":"33131",
    "addr:street":"Se 1St Ave Ste 100",
    "iso:country":"US",
    "sg:address":"909 SE 1st Ave Ste 100",
    "sg:city":"Miami",
    "sg:classifiers":[
        {
            "category":"Banks & Credit Unions",
            "subcategory":"Bank",
            "type":"Services"
        },
        {
            "category":"Banks & Credit Unions",
            "subcategory":"Financial Services",
            "type":"Services"
        }
    ],
    "sg:phone":"+1 888 842 6328",
    "sg:postcode":"33131",
    "sg:province":"FL",
    "sg:tags":[
        "broker",
        "mortgage"
    ],
    "wof:name":"Navy Federal Credit Union",
    "wof:placetype":"venue"
},
  "geometry": {"coordinates":[-80.192325,25.764537],"type":"Point"}
}