{
  "type": "Feature",
  "properties": {
    "addr:full":"5111 Crill Ave Palatka FL 32177",
    "addr:housenumber":"5111",
    "addr:postcode":"32177",
    "addr:street":"Crill Ave",
    "iso:country":"US",
    "sg:address":"5111 Crill Ave",
    "sg:city":"Palatka",
    "sg:classifiers":[
        {
            "category":"Insurance",
            "subcategory":"Insurance Agent",
            "type":"Services"
        }
    ],
    "sg:phone":"+1 386 328 4898",
    "sg:postcode":"32177",
    "sg:province":"FL",
    "wof:name":"Business & Auto Insurance Spec",
    "wof:placetype":"venue"
},
  "geometry": {"coordinates":[-81.67894099999999,29.641313],"type":"Point"}
}