{
  "type": "Feature",
  "properties": {
    "addr:full":"7429 NW 50th St Miami FL 33166",
    "addr:housenumber":"7429",
    "addr:postcode":"33166",
    "addr:street":"Nw 50Th St",
    "iso:country":"US",
    "sg:address":"7429 NW 50th St",
    "sg:city":"Miami",
    "sg:classifiers":[
        {
            "category":"Professional",
            "subcategory":"Management & Consulting",
            "type":"Services"
        }
    ],
    "sg:phone":"+1 305 591 2611",
    "sg:postcode":"33166",
    "sg:province":"FL",
    "sg:tags":[
        "aviation",
        "consultant"
    ],
    "wof:name":"International Technical Inc",
    "wof:placetype":"venue"
},
  "geometry": {"coordinates":[-80.318006,25.819051],"type":"Point"}
}