{
  "type": "Feature",
  "properties": {
    "addr:full":"6400 N US Hwy 1 Melbourne FL 32940",
    "addr:housenumber":"6400",
    "addr:postcode":"32940",
    "addr:street":"N Us Hwy 1",
    "iso:country":"US",
    "sg:address":"6400 N US Hwy 1",
    "sg:city":"Melbourne",
    "sg:classifiers":[
        {
            "category":"Shopping",
            "subcategory":"Used Merchandise",
            "type":"Retail Goods"
        }
    ],
    "sg:phone":"+1 321 752 6161",
    "sg:postcode":"32940",
    "sg:province":"FL",
    "wof:name":"Pack Rat S Mini",
    "wof:placetype":"venue"
},
  "geometry": {"coordinates":[-80.66775800000001,28.216846],"type":"Point"}
}