{
  "type": "Feature",
  "properties": {
    "iso:country":"US",
    "sg:address":"6300 Shirley St",
    "sg:city":"Naples",
    "sg:classifiers":[
        {
            "category":"Wholesale",
            "subcategory":"Construction Materials",
            "type":"Manufacturing & Wholesale Goods"
        }
    ],
    "sg:phone":"+1 239 598 3166",
    "sg:postcode":"34109",
    "sg:province":"FL",
    "sg:tags":[
        "concrete",
        "product"
    ],
    "wof:name":"Schwab Ready-Mix Inc",
    "wof:placetype":"venue"
},
  "geometry": {"coordinates":[-81.781538,26.220401],"type":"Point"}
}