{
  "type": "Feature",
  "properties": {
    "iso:country":"US",
    "sg:address":"2675 Yellowtail Dr",
    "sg:city":"Marathon",
    "sg:classifiers":[
        {
            "category":"Building & Trades",
            "subcategory":"Construction",
            "type":"Services"
        }
    ],
    "sg:phone":"+1 305 743 3536",
    "sg:postcode":"33050",
    "sg:province":"FL",
    "sg:tags":[
        "house",
        "residential"
    ],
    "wof:name":"Bowers Construction Co Inc",
    "wof:placetype":"venue"
},
  "geometry": {"coordinates":[-81.056262,24.730492],"type":"Point"}
}