{
  "type": "Feature",
  "properties": {
    "iso:country":"US",
    "sg:address":"9650 Atlantic Blvd",
    "sg:city":"Jacksonville",
    "sg:classifiers":[
        {
            "category":"Autos & Motor Vehicles",
            "subcategory":"Automobile Sales",
            "type":"Retail Goods"
        }
    ],
    "sg:phone":"+1 800 755 3219",
    "sg:postcode":"32225",
    "sg:province":"FL",
    "sg:tags":[
        "body",
        "repairing",
        "painting",
        "car"
    ],
    "sg:website":"http://www.mikedavidson.com",
    "wof:name":"Mike Davidson Ford",
    "wof:placetype":"venue"
},
  "geometry": {"coordinates":[-81.547577,30.3218],"type":"Point"}
}