{
  "type": "Feature",
  "properties": {
    "iso:country":"US",
    "sg:address":"137 Willow Pond Ln",
    "sg:city":"Ponte Vedra Beach",
    "sg:classifiers":[
        {
            "category":"Building & Trades",
            "subcategory":"Landscaping Services",
            "type":"Services"
        }
    ],
    "sg:phone":"+1 904 234 7700",
    "sg:postcode":"32082",
    "sg:province":"FL",
    "sg:tags":[
        "landscape"
    ],
    "wof:name":"Kathi Hollands Garden Arch",
    "wof:placetype":"venue"
},
  "geometry": {"coordinates":[-81.377622,30.188942],"type":"Point"}
}