{
  "type": "Feature",
  "properties": {
    "addr:full":"4459 Woodmere St Jacksonville FL 32210",
    "addr:housenumber":"4459",
    "addr:postcode":"32210",
    "addr:street":"Woodmere St",
    "iso:country":"US",
    "sg:address":"4459 Woodmere St",
    "sg:city":"Jacksonville",
    "sg:classifiers":[
        {
            "category":"Health Services",
            "subcategory":"Doctor",
            "type":"Services"
        }
    ],
    "sg:phone":"+1 904 384 1601",
    "sg:postcode":"32210",
    "sg:province":"FL",
    "sg:tags":[
        "physician",
        "surgeon"
    ],
    "wof:name":"Dr C & Linda Marie",
    "wof:placetype":"venue"
},
  "geometry": {"coordinates":[-81.71884799999999,30.289334],"type":"Point"}
}