{
  "type": "Feature",
  "properties": {
    "iso:country":"US",
    "sg:address":"6017 Pine Ridge Rd",
    "sg:city":"Naples",
    "sg:classifiers":[
        {
            "category":"Wholesale",
            "subcategory":"Non-durable Goods",
            "type":"Manufacturing & Wholesale Goods"
        }
    ],
    "sg:phone":"+1 239 514 3117",
    "sg:postcode":"34119",
    "sg:province":"FL",
    "sg:tags":[
        "advertising"
    ],
    "wof:name":"Double Exposure Promotions Inc",
    "wof:placetype":"venue"
},
  "geometry": {"coordinates":[-81.71680600000001,26.211911],"type":"Point"}
}