{
  "type": "Feature",
  "properties": {
    "addr:full":"1917 NE 19th Pl Cape Coral FL 33909",
    "addr:housenumber":"1917",
    "addr:postcode":"33909",
    "addr:street":"Ne 19Th Pl",
    "iso:country":"US",
    "sg:address":"1917 NE 19th Pl",
    "sg:city":"Cape Coral",
    "sg:classifiers":[
        {
            "category":"Building & Trades",
            "subcategory":"Construction",
            "type":"Services"
        }
    ],
    "sg:phone":"+1 239 823 7412",
    "sg:postcode":"33909",
    "sg:province":"FL",
    "sg:tags":[
        "contractor"
    ],
    "wof:name":"Victor Zayas Maintenance Svc",
    "wof:placetype":"venue"
},
  "geometry": {"coordinates":[-81.934882,26.688437],"type":"Point"}
}