{
  "type": "Feature",
  "properties": {
    "iso:country":"US",
    "sg:address":"215 West Dr",
    "sg:city":"Melbourne",
    "sg:classifiers":[
        {
            "category":"Government",
            "subcategory":"Fire Station",
            "type":"Public Place"
        },
        {
            "category":"Professional",
            "subcategory":"Detective & Security Services",
            "type":"Services"
        },
        {
            "category":"Home & Garden",
            "subcategory":"Hardware",
            "type":"Retail Goods"
        },
        {
            "category":"Conference Center",
            "type":"Public Place"
        }
    ],
    "sg:phone":"+1 321 725 1009",
    "sg:postcode":"32904",
    "sg:province":"FL",
    "sg:tags":[
        "extinguisher",
        "industrial",
        "backflow",
        "supply",
        "commercial",
        "alarm",
        "sprinklers-residential",
        "system",
        "equipment",
        "protection",
        "device",
        "automatic",
        "prevention"
    ],
    "sg:website":"http://www.universalfireprotection.net",
    "wof:name":"Universal Fire Protection",
    "wof:placetype":"venue"
},
  "geometry": {"coordinates":[-80.69098700000001,28.104271],"type":"Point"}
}