{
  "type": "Feature",
  "properties": {
    "addr:full":"593 SE Nome Dr Port Saint Lucie FL 34984",
    "addr:housenumber":"593",
    "addr:postcode":"34984",
    "addr:street":"Se Nome Dr",
    "iso:country":"US",
    "sg:address":"593 SE Nome Dr",
    "sg:city":"Port Saint Lucie",
    "sg:classifiers":[
        {
            "category":"Social Services",
            "subcategory":"Child Care",
            "type":"Services"
        }
    ],
    "sg:phone":"+1 772 344 7231",
    "sg:postcode":"34984",
    "sg:province":"FL",
    "sg:tags":[
        "day"
    ],
    "wof:name":"Palacios Mrcedes Fmly Day Care",
    "wof:placetype":"venue"
},
  "geometry": {"coordinates":[-80.336741,27.260305],"type":"Point"}
}