{
  "type": "Feature",
  "properties": {
    "iso:country":"US",
    "sg:address":"8301 Joliet St",
    "sg:city":"Port Richey",
    "sg:classifiers":[
        {
            "category":"Education",
            "subcategory":"Vocational School",
            "type":"Public Place"
        }
    ],
    "sg:phone":"+1 727 863 5147",
    "sg:postcode":"34667",
    "sg:province":"FL",
    "sg:tags":[
        "contractor"
    ],
    "wof:name":"Koning Contractors Library",
    "wof:placetype":"venue"
},
  "geometry": {"coordinates":[-82.67840700000001,28.381999],"type":"Point"}
}