{
  "type": "Feature",
  "properties": {
    "iso:country":"US",
    "sg:address":"4035 Joy Rd",
    "sg:city":"Cocoa",
    "sg:classifiers":[
        {
            "category":"Building & Trades",
            "subcategory":"Landscaping Services",
            "type":"Services"
        }
    ],
    "sg:phone":"+1 321 631 9148",
    "sg:postcode":"32927",
    "sg:province":"FL",
    "wof:name":"Chiefs Lawn Care Service",
    "wof:placetype":"venue"
},
  "geometry": {"coordinates":[-80.76246399999999,28.434054],"type":"Point"}
}