{
  "type": "Feature",
  "properties": {
    "iso:country":"US",
    "sg:address":"19870 NW 27th Ave",
    "sg:city":"Miami Gardens",
    "sg:classifiers":[
        {
            "category":"Shopping",
            "subcategory":"Mobile Phones",
            "type":"Retail Goods"
        }
    ],
    "sg:phone":"+1 305 423 1242",
    "sg:postcode":"33056",
    "sg:province":"FL",
    "wof:name":"Toyz Wireless",
    "wof:placetype":"venue"
},
  "geometry": {"coordinates":[-80.24621,25.955102],"type":"Point"}
}