{
  "type": "Feature",
  "properties": {
    "addr:full":"1515 S Washington Ave Titusville FL 32780",
    "addr:housenumber":"1515",
    "addr:postcode":"32780",
    "addr:street":"S Washington Ave",
    "iso:country":"US",
    "sg:address":"1515 S Washington Ave",
    "sg:city":"Titusville",
    "sg:classifiers":[
        {
            "category":"Restaurant",
            "type":"Food & Drink"
        }
    ],
    "sg:menulink":"http://www.allmenus.com/fl/titusville/171534-moonlight-drive-in-restaurant/menu/",
    "sg:phone":"+1 321 267 8222",
    "sg:postcode":"32780",
    "sg:province":"FL",
    "sg:tags":[
        "american"
    ],
    "wof:name":"Moonlight Drive In Restaurant",
    "wof:placetype":"venue"
},
  "geometry": {"coordinates":[-80.80564099999999,28.597312],"type":"Point"}
}