{
  "type": "Feature",
  "properties": {
    "iso:country":"US",
    "sg:address":"2669 Holly Point Rd E",
    "sg:city":"Orange Park",
    "sg:classifiers":[
        {
            "category":"Building & Trades",
            "subcategory":"Construction",
            "type":"Services"
        }
    ],
    "sg:phone":"+1 904 215 7622",
    "sg:postcode":"32073",
    "sg:province":"FL",
    "sg:tags":[
        "contractor"
    ],
    "wof:name":"Cronk Duch & Miller",
    "wof:placetype":"venue"
},
  "geometry": {"coordinates":[-81.698094,30.156219],"type":"Point"}
}