{
  "type": "Feature",
  "properties": {
    "iso:country":"US",
    "sg:address":"8410 US Hwy 19",
    "sg:city":"Port Richey",
    "sg:classifiers":[
        {
            "category":"Insurance",
            "subcategory":"Title Insurance",
            "type":"Services"
        }
    ],
    "sg:phone":"+1 727 845 1084",
    "sg:postcode":"34668",
    "sg:province":"FL",
    "sg:tags":[
        "carrier"
    ],
    "wof:name":"Keystone Title Agency",
    "wof:placetype":"venue"
},
  "geometry": {"coordinates":[-82.717324,28.280436],"type":"Point"}
}