{
  "type": "Feature",
  "properties": {
    "addr:full":"7731 SW 80th St Ocala FL 34476",
    "addr:housenumber":"7731",
    "addr:postcode":"34476",
    "addr:street":"Sw 80Th St",
    "iso:country":"US",
    "sg:address":"7731 SW 80th St",
    "sg:city":"Ocala",
    "sg:classifiers":[
        {
            "category":"Retail",
            "subcategory":"Repair Shop",
            "type":"Services"
        }
    ],
    "sg:phone":"+1 352 812 5858",
    "sg:postcode":"34476",
    "sg:province":"FL",
    "sg:tags":[
        "related"
    ],
    "wof:name":"Patrick J Orrell Personal Prop",
    "wof:placetype":"venue"
},
  "geometry": {"coordinates":[-82.245028,29.106692],"type":"Point"}
}