{
  "type": "Feature",
  "properties": {
    "iso:country":"US",
    "sg:address":"2302 S Macdill Ave",
    "sg:city":"Tampa",
    "sg:classifiers":[
        {
            "category":"Banks & Credit Unions",
            "subcategory":"Bank",
            "type":"Services"
        }
    ],
    "sg:phone":"+1 813 250 3838",
    "sg:postcode":"33629",
    "sg:province":"FL",
    "sg:website":"www.thepalmbank.com",
    "wof:name":"Palm Bank",
    "wof:placetype":"venue"
},
  "geometry": {"coordinates":[-82.493487,27.923865],"type":"Point"}
}