{
  "type": "Feature",
  "properties": {
    "addr:full":"224 NW 106th Ave Hollywood FL 33026",
    "addr:housenumber":"224",
    "addr:postcode":"33026",
    "addr:street":"Nw 106Th Ave",
    "iso:country":"US",
    "sg:address":"224 NW 106th Ave",
    "sg:city":"Hollywood",
    "sg:classifiers":[
        {
            "category":"Professional",
            "type":"Services"
        }
    ],
    "sg:phone":"+1 954 450 4972",
    "sg:postcode":"33026",
    "sg:province":"FL",
    "wof:name":"Wahoo Sports Corp",
    "wof:placetype":"venue"
},
  "geometry": {"coordinates":[-80.28730899999999,26.008103],"type":"Point"}
}