{
  "type": "Feature",
  "properties": {
    "iso:country":"US",
    "sg:address":"13415 SW 56th St",
    "sg:city":"Miami",
    "sg:classifiers":[
        {
            "category":"Government",
            "subcategory":"Office",
            "type":"Public Place"
        }
    ],
    "sg:phone":"+1 305 207 6020",
    "sg:postcode":"33175",
    "sg:province":"FL",
    "sg:tags":[
        "government-state"
    ],
    "wof:name":"All Service & Comm",
    "wof:placetype":"venue"
},
  "geometry": {"coordinates":[-80.41134099999999,25.714695],"type":"Point"}
}