{
  "type": "Feature",
  "properties": {
    "iso:country":"US",
    "sg:address":"520 Lake Powell Dr",
    "sg:city":"Panama City",
    "sg:classifiers":[
        {
            "category":"Manufacturing",
            "subcategory":"Printing",
            "type":"Manufacturing & Wholesale Goods"
        }
    ],
    "sg:phone":"+1 850 236 8895",
    "sg:postcode":"32413",
    "sg:province":"FL",
    "sg:tags":[
        "lithographic",
        "commercial"
    ],
    "wof:name":"Adams Professional Graphi",
    "wof:placetype":"venue"
},
  "geometry": {"coordinates":[-85.970558,30.266845],"type":"Point"}
}