{
  "type": "Feature",
  "properties": {
    "iso:country":"US",
    "sg:address":"615 Corwood Dr",
    "sg:city":"Sarasota",
    "sg:classifiers":[
        {
            "category":"Real Estate",
            "subcategory":"Architect",
            "type":"Services"
        }
    ],
    "sg:phone":"+1 941 358 1731",
    "sg:postcode":"34234",
    "sg:province":"FL",
    "sg:tags":[
        "model",
        "architectural"
    ],
    "sg:website":"www.brainwork.com",
    "wof:name":"Sightline",
    "wof:placetype":"venue"
},
  "geometry": {"coordinates":[-82.55527600000001,27.372105],"type":"Point"}
}