{
  "type": "Feature",
  "properties": {
    "addr:full":"19542 Aztec St Summerland Key FL 33042",
    "addr:housenumber":"19542",
    "addr:postcode":"33042",
    "addr:street":"Aztec St",
    "iso:country":"US",
    "sg:address":"19542 Aztec St",
    "sg:city":"Summerland Key",
    "sg:classifiers":[
        {
            "category":"Building & Trades",
            "subcategory":"Construction",
            "type":"Services"
        }
    ],
    "sg:phone":"+1 305 744 9707",
    "sg:postcode":"33042",
    "sg:province":"FL",
    "sg:tags":[
        "dry wall",
        "contractor"
    ],
    "wof:name":"Hansen S Drywall Inc",
    "wof:placetype":"venue"
},
  "geometry": {"coordinates":[-81.527855,24.667692],"type":"Point"}
}