{
  "type": "Feature",
  "properties": {
    "iso:country":"US",
    "sg:address":"1570 Pitch Pine Ave",
    "sg:city":"Jacksonville",
    "sg:classifiers":[
        {
            "category":"Retail",
            "subcategory":"Laundry & Dry Cleaning",
            "type":"Services"
        }
    ],
    "sg:phone":"+1 904 287 9386",
    "sg:postcode":"32259",
    "sg:province":"FL",
    "wof:name":"Danson Carpet Care",
    "wof:placetype":"venue"
},
  "geometry": {"coordinates":[-81.625314,30.096156],"type":"Point"}
}