{
  "type": "Feature",
  "properties": {
    "iso:country":"US",
    "sg:address":"500 NE 48th St",
    "sg:city":"Boca Raton",
    "sg:classifiers":[
        {
            "category":"Freight",
            "type":"Transportation"
        }
    ],
    "sg:phone":"+1 561 416 2309",
    "sg:postcode":"33431",
    "sg:province":"FL",
    "sg:tags":[
        "commercial",
        "storage"
    ],
    "wof:name":"Storage Express II Inc",
    "wof:placetype":"venue"
},
  "geometry": {"coordinates":[-80.076584,26.39226],"type":"Point"}
}