{
  "type": "Feature",
  "properties": {
    "iso:country":"US",
    "sg:address":"808 Hastings Dr",
    "sg:city":"Kissimmee",
    "sg:classifiers":[
        {
            "category":"Education",
            "subcategory":"Special Training",
            "type":"Public Place"
        },
        {
            "category":"Professional",
            "subcategory":"Business Services",
            "type":"Services"
        }
    ],
    "sg:phone":"+1 407 847 8816",
    "sg:postcode":"34744",
    "sg:province":"FL",
    "sg:tags":[
        "testing",
        "tutoring"
    ],
    "wof:name":"Jablon E G Eductl Specialist",
    "wof:placetype":"venue"
},
  "geometry": {"coordinates":[-81.391277,28.292062],"type":"Point"}
}