{
  "type": "Feature",
  "properties": {
    "iso:country":"US",
    "sg:address":"1505 NW 167th St",
    "sg:city":"Miami",
    "sg:classifiers":[
        {
            "category":"Health Services",
            "subcategory":"Doctor",
            "type":"Services"
        }
    ],
    "sg:phone":"+1 305 625 5400",
    "sg:postcode":"33169",
    "sg:province":"FL",
    "sg:tags":[
        "surgeon",
        "oral"
    ],
    "wof:name":"Dollinger Howard DDS",
    "wof:placetype":"venue"
},
  "geometry": {"coordinates":[-80.225522,25.927986],"type":"Point"}
}