{
  "type": "Feature",
  "properties": {
    "iso:country":"US",
    "sg:address":"2551 Princess Way",
    "sg:city":"Kissimmee",
    "sg:phone":"+1 407 862 6981",
    "sg:postcode":"34746",
    "sg:province":"FL",
    "sg:tags":[
        "equipment",
        "commercial"
    ],
    "wof:name":"Pv Suppliers To The Hospitalit",
    "wof:placetype":"venue"
},
  "geometry": {"coordinates":[-81.462389,28.32184],"type":"Point"}
}