{
  "type": "Feature",
  "properties": {
    "iso:country":"US",
    "sg:address":"4728 NW 114th Ave # 202",
    "sg:city":"Doral",
    "sg:classifiers":[
        {
            "category":"Manufacturing",
            "subcategory":"Electronics",
            "type":"Manufacturing & Wholesale Goods"
        },
        {
            "category":"Shopping",
            "subcategory":"Computers & Home Electronics",
            "type":"Retail Goods"
        }
    ],
    "sg:phone":"+1 305 495 5521",
    "sg:postcode":"33178",
    "sg:province":"FL",
    "sg:tags":[
        "printers-equipment",
        "printer",
        "supply"
    ],
    "sg:website":"http://www.suninkjet.com",
    "wof:name":"Concord Associates",
    "wof:placetype":"venue"
},
  "geometry": {"coordinates":[-80.38166699999999,25.816198],"type":"Point"}
}