{
  "type": "Feature",
  "properties": {
    "addr:full":"147 Sioux St Tavernier FL 33070",
    "addr:housenumber":"147",
    "addr:postcode":"33070",
    "addr:street":"Sioux St",
    "iso:country":"US",
    "sg:address":"147 Sioux St",
    "sg:city":"Tavernier",
    "sg:classifiers":[
        {
            "category":"Building & Trades",
            "subcategory":"Landscaping Services",
            "type":"Services"
        }
    ],
    "sg:phone":"+1 305 852 2684",
    "sg:postcode":"33070",
    "sg:province":"FL",
    "wof:name":"Family Tree Ldscpg & Tree Svc",
    "wof:placetype":"venue"
},
  "geometry": {"coordinates":[-80.54879099999999,24.984483],"type":"Point"}
}