{
  "type": "Feature",
  "properties": {
    "iso:country":"US",
    "sg:address":"220 E Bay St",
    "sg:city":"Jacksonville",
    "sg:classifiers":[
        {
            "category":"Government",
            "subcategory":"Office",
            "type":"Public Place"
        }
    ],
    "sg:phone":"+1 904 630 1341",
    "sg:postcode":"32202",
    "sg:province":"FL",
    "sg:tags":[
        "village"
    ],
    "sg:website":"www.coj.net",
    "wof:name":"Jacksonville Streets & Drain",
    "wof:placetype":"venue"
},
  "geometry": {"coordinates":[-81.654594,30.325426],"type":"Point"}
}