{
  "type": "Feature",
  "properties": {
    "addr:full":"716 SW Lake Charles Cir Port Saint Lucie FL 34986",
    "addr:housenumber":"716",
    "addr:postcode":"34986",
    "addr:street":"Sw Lake Charles Cir",
    "iso:country":"US",
    "sg:address":"716 SW Lake Charles Cir",
    "sg:city":"Port Saint Lucie",
    "sg:classifiers":[
        {
            "category":"Professional",
            "type":"Services"
        }
    ],
    "sg:phone":"+1 772 336 3650",
    "sg:postcode":"34986",
    "sg:province":"FL",
    "wof:name":"Peter A Dargen Company",
    "wof:placetype":"venue"
},
  "geometry": {"coordinates":[-80.410408,27.298693],"type":"Point"}
}