{
  "type": "Feature",
  "properties": {
    "iso:country":"US",
    "sg:address":"2158 Gerard Ct",
    "sg:city":"Port Charlotte",
    "sg:classifiers":[
        {
            "category":"Arts & Performance",
            "subcategory":"Theater",
            "type":"Entertainment"
        }
    ],
    "sg:phone":"+1 941 627 8922",
    "sg:postcode":"33952",
    "sg:province":"FL",
    "sg:tags":[
        "musician"
    ],
    "wof:name":"Third Street Exit",
    "wof:placetype":"venue"
},
  "geometry": {"coordinates":[-82.08552899999999,26.997793],"type":"Point"}
}