{
  "type": "Feature",
  "properties": {
    "iso:country":"US",
    "sg:address":"1503 Main St",
    "sg:city":"Sarasota",
    "sg:classifiers":[
        {
            "category":"Shopping",
            "subcategory":"Florist",
            "type":"Retail Goods"
        }
    ],
    "sg:phone":"+1 941 366 5566",
    "sg:postcode":"34236",
    "sg:province":"FL",
    "wof:name":"Tiger Lily",
    "wof:placetype":"venue"
},
  "geometry": {"coordinates":[-82.538642,27.336541],"type":"Point"}
}