{
  "type": "Feature",
  "properties": {
    "addr:full":"4855 N Dixie Hwy Pompano Beach FL 33064",
    "addr:housenumber":"4855",
    "addr:postcode":"33064",
    "addr:street":"N Dixie Hwy",
    "iso:country":"US",
    "sg:address":"4855 N Dixie Hwy",
    "sg:city":"Pompano Beach",
    "sg:classifiers":[
        {
            "category":"Utilities",
            "subcategory":"Mobile Phone",
            "type":"Services"
        }
    ],
    "sg:phone":"+1 954 481 1560",
    "sg:postcode":"33064",
    "sg:province":"FL",
    "sg:tags":[
        "telephone",
        "cellular"
    ],
    "wof:name":"Cellular Zone",
    "wof:placetype":"venue"
},
  "geometry": {"coordinates":[-80.109162,26.291783],"type":"Point"}
}