{
  "type": "Feature",
  "properties": {
    "addr:full":"4021 N Dixie Hwy Pompano Beach FL 33064",
    "addr:housenumber":"4021",
    "addr:postcode":"33064",
    "addr:street":"N Dixie Hwy",
    "iso:country":"US",
    "sg:address":"4021 N Dixie Hwy",
    "sg:city":"Pompano Beach",
    "sg:classifiers":[
        {
            "category":"Insurance",
            "subcategory":"Insurance Agent",
            "type":"Services"
        }
    ],
    "sg:phone":"+1 954 784 6212",
    "sg:postcode":"33064",
    "sg:province":"FL",
    "wof:name":"Ultimate Insurance Associates",
    "wof:placetype":"venue"
},
  "geometry": {"coordinates":[-80.111999,26.281767],"type":"Point"}
}