{
  "type": "Feature",
  "properties": {
    "addr:full":"805 Bayside Ln Fort Lauderdale FL 33326",
    "addr:housenumber":"805",
    "addr:postcode":"33326",
    "addr:street":"Bayside Ln",
    "iso:country":"US",
    "sg:address":"805 Bayside Ln",
    "sg:city":"Fort Lauderdale",
    "sg:classifiers":[
        {
            "category":"Professional",
            "subcategory":"Management & Consulting",
            "type":"Services"
        }
    ],
    "sg:phone":"+1 954 292 3679",
    "sg:postcode":"33326",
    "sg:province":"FL",
    "sg:tags":[
        "technical",
        "consultant"
    ],
    "wof:name":"Be One Inc",
    "wof:placetype":"venue"
},
  "geometry": {"coordinates":[-80.397704,26.108119],"type":"Point"}
}