{
  "type": "Feature",
  "properties": {
    "addr:full":"2200 Monroe St Hollywood FL 33020",
    "addr:housenumber":"2200",
    "addr:postcode":"33020",
    "addr:street":"Monroe St",
    "iso:country":"US",
    "sg:address":"2200 Monroe St",
    "sg:city":"Hollywood",
    "sg:classifiers":[
        {
            "category":"Food & Beverages",
            "subcategory":"Groceries & Convenience Stores",
            "type":"Retail Goods"
        }
    ],
    "sg:phone":"+1 954 923 5347",
    "sg:postcode":"33020",
    "sg:province":"FL",
    "wof:name":"Jovanna Quinones",
    "wof:placetype":"venue"
},
  "geometry": {"coordinates":[-80.152666,26.007485],"type":"Point"}
}