{
  "type": "Feature",
  "properties": {
    "iso:country":"US",
    "sg:address":"600 SW 22nd Ave",
    "sg:city":"Miami",
    "sg:classifiers":[
        {
            "category":"Retail",
            "subcategory":"Auto Repair",
            "type":"Services"
        }
    ],
    "sg:phone":"+1 305 649 0025",
    "sg:postcode":"33135",
    "sg:province":"FL",
    "wof:name":"Discount Cv Joint Inc",
    "wof:placetype":"venue"
},
  "geometry": {"coordinates":[-80.230904,25.767099],"type":"Point"}
}