{
  "type": "Feature",
  "properties": {
    "addr:full":"375 Sunnyside Dr Venice FL 34293",
    "addr:housenumber":"375",
    "addr:postcode":"34293",
    "addr:street":"Sunnyside Dr",
    "iso:country":"US",
    "sg:address":"375 Sunnyside Dr",
    "sg:city":"Venice",
    "sg:classifiers":[
        {
            "category":"Manufacturing",
            "subcategory":"Soap",
            "type":"Manufacturing & Wholesale Goods"
        }
    ],
    "sg:phone":"+1 941 493 5830",
    "sg:postcode":"34293",
    "sg:province":"FL",
    "sg:tags":[
        "detergent"
    ],
    "wof:name":"Olivia Centore Flea Market",
    "wof:placetype":"venue"
},
  "geometry": {"coordinates":[-82.38578099999999,27.056598],"type":"Point"}
}