{
  "type": "Feature",
  "properties": {
    "iso:country":"US",
    "sg:address":"2201 Cantu Ct",
    "sg:city":"Sarasota",
    "sg:classifiers":[
        {
            "category":"Insurance",
            "subcategory":"Hazard Insurance",
            "type":"Services"
        }
    ],
    "sg:phone":"+1 941 377 4842",
    "sg:postcode":"34232",
    "sg:province":"FL",
    "sg:tags":[
        "chemical",
        "underwriting",
        "specialized"
    ],
    "wof:name":"Chemplan",
    "wof:placetype":"venue"
},
  "geometry": {"coordinates":[-82.44944700000001,27.310458],"type":"Point"}
}