{
  "type": "Feature",
  "properties": {
    "iso:country":"US",
    "sg:address":"1500 N Broadwalk",
    "sg:city":"Hollywood",
    "sg:classifiers":[
        {
            "category":"Professional",
            "subcategory":"Business Services",
            "type":"Services"
        }
    ],
    "sg:phone":"+1 954 757 9500",
    "sg:postcode":"33019",
    "sg:province":"FL",
    "sg:tags":[
        "personal",
        "bureau",
        "broker",
        "agent"
    ],
    "wof:name":"Sun & Fun Cycles",
    "wof:placetype":"venue"
},
  "geometry": {"coordinates":[-80.115025,26.022367],"type":"Point"}
}