{
  "type": "Feature",
  "properties": {
    "iso:country":"US",
    "sg:address":"1006 SE 4th Pl",
    "sg:city":"Cape Coral",
    "sg:classifiers":[
        {
            "category":"Sports & Exercise",
            "subcategory":"Golf",
            "type":"Entertainment"
        }
    ],
    "sg:phone":"+1 239 574 4454",
    "sg:postcode":"33990",
    "sg:province":"FL",
    "wof:name":"Hunters Run",
    "wof:placetype":"venue"
},
  "geometry": {"coordinates":[-81.96566300000001,26.633079],"type":"Point"}
}