{
  "type": "Feature",
  "properties": {
    "iso:country":"US",
    "sg:address":"9222 Arlington Expy",
    "sg:city":"Jacksonville",
    "sg:classifiers":[
        {
            "category":"Shopping",
            "subcategory":"Clothing, Apparel, & Fashions",
            "type":"Retail Goods"
        }
    ],
    "sg:phone":"+1 904 724 8802",
    "sg:postcode":"32225",
    "sg:province":"FL",
    "sg:tags":[
        "baby",
        "accessory"
    ],
    "sg:website":"www.usababy.com",
    "wof:name":"USA Baby",
    "wof:placetype":"venue"
},
  "geometry": {"coordinates":[-81.558555,30.322267],"type":"Point"}
}