{
  "type": "Feature",
  "properties": {
    "addr:full":"13722 SW 84th St Miami FL 33183",
    "addr:housenumber":"13722",
    "addr:postcode":"33183",
    "addr:street":"Sw 84Th St",
    "iso:country":"US",
    "sg:address":"13722 SW 84th St",
    "sg:city":"Miami",
    "sg:classifiers":[
        {
            "category":"Health Services",
            "subcategory":"Doctor",
            "type":"Services"
        },
        {
            "category":"Health Services",
            "subcategory":"Dentist",
            "type":"Services"
        }
    ],
    "sg:phone":"+1 305 385 5555",
    "sg:postcode":"33183",
    "sg:province":"FL",
    "sg:tags":[
        "dentists-oral",
        "physician",
        "maxillofacial",
        "surgeons",
        "surgery",
        "oral"
    ],
    "wof:name":"Bloch, Jonathan T Dmd",
    "wof:placetype":"venue"
},
  "geometry": {"coordinates":[-80.41631700000001,25.688446],"type":"Point"}
}