{
  "type": "Feature",
  "properties": {
    "iso:country":"US",
    "sg:address":"1113 Edgehill Ave",
    "sg:city":"Spring Hill",
    "sg:classifiers":[
        {
            "category":"Building & Trades",
            "subcategory":"Construction",
            "type":"Services"
        }
    ],
    "sg:phone":"+1 352 688 8420",
    "sg:postcode":"34606",
    "sg:province":"FL",
    "sg:tags":[
        "contractor"
    ],
    "wof:name":"Walker Drywall",
    "wof:placetype":"venue"
},
  "geometry": {"coordinates":[-82.60555600000001,28.447473],"type":"Point"}
}