{
  "type": "Feature",
  "properties": {
    "iso:country":"US",
    "sg:address":"3900 Military Trl",
    "sg:city":"Jupiter",
    "sg:classifiers":[
        {
            "category":"Insurance",
            "subcategory":"Insurance Agent",
            "type":"Services"
        }
    ],
    "sg:phone":"+1 561 622 1412",
    "sg:postcode":"33458",
    "sg:province":"FL",
    "wof:name":"Steven Muller Insurance Inc",
    "wof:placetype":"venue"
},
  "geometry": {"coordinates":[-80.102627,26.90721],"type":"Point"}
}