{
  "type": "Feature",
  "properties": {
    "iso:country":"US",
    "sg:address":"20283 State Rd 7",
    "sg:city":"Boca Raton",
    "sg:classifiers":[
        {
            "category":"Professional",
            "subcategory":"Research",
            "type":"Services"
        }
    ],
    "sg:phone":"+1 561 479 3525",
    "sg:postcode":"33498",
    "sg:province":"FL",
    "sg:tags":[
        "development",
        "human",
        "factor"
    ],
    "wof:name":"Mempa Research Assoc",
    "wof:placetype":"venue"
},
  "geometry": {"coordinates":[-80.20361,26.378614],"type":"Point"}
}