{
  "type": "Feature",
  "properties": {
    "iso:country":"US",
    "sg:address":"644 2nd Ln",
    "sg:city":"Vero Beach",
    "sg:classifiers":[
        {
            "category":"Real Estate",
            "subcategory":"Real Estate Agent",
            "type":"Services"
        }
    ],
    "sg:phone":"+1 772 567 0040",
    "sg:postcode":"32962",
    "sg:province":"FL",
    "wof:name":"Thomas M Beckley Realtor",
    "wof:placetype":"venue"
},
  "geometry": {"coordinates":[-80.38658100000001,27.606355],"type":"Point"}
}