{
  "type": "Feature",
  "properties": {
    "addr:full":"331 SE 10th St Pompano Beach FL 33060",
    "addr:housenumber":"331",
    "addr:postcode":"33060",
    "addr:street":"Se 10Th St",
    "iso:country":"US",
    "sg:address":"331 SE 10th St",
    "sg:city":"Pompano Beach",
    "sg:classifiers":[
        {
            "category":"Building & Trades",
            "subcategory":"Construction",
            "type":"Services"
        }
    ],
    "sg:phone":"+1 954 786 1738",
    "sg:postcode":"33060",
    "sg:province":"FL",
    "sg:tags":[
        "residential"
    ],
    "wof:name":"JR Construction Company",
    "wof:placetype":"venue"
},
  "geometry": {"coordinates":[-80.119534,26.216858],"type":"Point"}
}