{
  "type": "Feature",
  "properties": {
    "iso:country":"US",
    "sg:address":"7737 NW 79th Ave Apt 107",
    "sg:city":"Tamarac",
    "sg:classifiers":[
        {
            "category":"Manufacturing",
            "subcategory":"Petroleum Products",
            "type":"Manufacturing & Wholesale Goods"
        }
    ],
    "sg:phone":"+1 954 721 9461",
    "sg:postcode":"33321",
    "sg:province":"FL",
    "sg:tags":[
        "contract"
    ],
    "wof:name":"Mhk Industries",
    "wof:placetype":"venue"
},
  "geometry": {"coordinates":[-80.257957,26.217908],"type":"Point"}
}