{
  "type": "Feature",
  "properties": {
    "addr:full":"42 Madeore St Saint Augustine FL 32084",
    "addr:housenumber":"42",
    "addr:postcode":"32084",
    "addr:street":"Madeore St",
    "iso:country":"US",
    "sg:address":"42 Madeore St",
    "sg:city":"Saint Augustine",
    "sg:classifiers":[
        {
            "category":"Building & Trades",
            "subcategory":"Construction",
            "type":"Services"
        }
    ],
    "sg:phone":"+1 904 829 5405",
    "sg:postcode":"32084",
    "sg:province":"FL",
    "sg:tags":[
        "carpentry",
        "contractor"
    ],
    "wof:name":"Ryan Freeman Carpentry Inc",
    "wof:placetype":"venue"
},
  "geometry": {"coordinates":[-81.331399,29.886094],"type":"Point"}
}