{
  "type": "Feature",
  "properties": {
    "iso:country":"US",
    "sg:address":"1812 Hazelwood Dr",
    "sg:city":"Fort Pierce",
    "sg:classifiers":[
        {
            "category":"Shopping",
            "subcategory":"Gifts & Souvenirs",
            "type":"Retail Goods"
        }
    ],
    "sg:phone":"+1 772 465 1919",
    "sg:postcode":"34982",
    "sg:province":"FL",
    "wof:name":"Third World Acquisition Corp",
    "wof:placetype":"venue"
},
  "geometry": {"coordinates":[-80.34275599999999,27.394331],"type":"Point"}
}