{
  "type": "Feature",
  "properties": {
    "iso:country":"US",
    "sg:address":"3171 NW 12th Ter",
    "sg:city":"Gainesville",
    "sg:classifiers":[
        {
            "category":"Retail",
            "subcategory":"Laundry & Dry Cleaning",
            "type":"Services"
        }
    ],
    "sg:phone":"+1 352 373 5930",
    "sg:postcode":"32609",
    "sg:province":"FL",
    "sg:tags":[
        "cleaners",
        "rug",
        "carpet"
    ],
    "wof:name":"Advanced Carpet Systems",
    "wof:placetype":"venue"
},
  "geometry": {"coordinates":[-82.337577,29.68128],"type":"Point"}
}