{
  "type": "Feature",
  "properties": {
    "iso:country":"US",
    "sg:address":"150 Brandy Ln",
    "sg:city":"Tallahassee",
    "sg:classifiers":[
        {
            "category":"Building & Trades",
            "subcategory":"Construction",
            "type":"Services"
        }
    ],
    "sg:phone":"+1 850 298 2224",
    "sg:postcode":"32317",
    "sg:province":"FL",
    "sg:tags":[
        "carpenter"
    ],
    "wof:name":"Brian Markley Carpentry",
    "wof:placetype":"venue"
},
  "geometry": {"coordinates":[-84.138193,30.460422],"type":"Point"}
}