{
  "type": "Feature",
  "properties": {
    "iso:country":"US",
    "sg:address":"7232 SW 8th St",
    "sg:city":"Miami",
    "sg:classifiers":[
        {
            "category":"Recreation",
            "subcategory":"Gun Range",
            "type":"Entertainment"
        },
        {
            "category":"Community Center",
            "type":"Public Place"
        }
    ],
    "sg:phone":"+1 305 267 1122",
    "sg:postcode":"33144",
    "sg:province":"FL",
    "sg:tags":[
        "paintball"
    ],
    "wof:name":"Rage Paintball",
    "wof:placetype":"venue"
},
  "geometry": {"coordinates":[-80.312471,25.7628],"type":"Point"}
}