{
  "type": "Feature",
  "properties": {
    "iso:country":"US",
    "sg:address":"13746 Waggle Ct",
    "sg:city":"Hudson",
    "sg:classifiers":[
        {
            "category":"Building & Trades",
            "subcategory":"Construction",
            "type":"Services"
        }
    ],
    "sg:phone":"+1 727 869 4304",
    "sg:postcode":"34669",
    "sg:province":"FL",
    "sg:tags":[
        "handyman"
    ],
    "wof:name":"General Home Svc",
    "wof:placetype":"venue"
},
  "geometry": {"coordinates":[-82.655894,28.357029],"type":"Point"}
}