{
  "type": "Feature",
  "properties": {
    "addr:full":"4316 New River Hills Pkwy Valrico FL 33596",
    "addr:housenumber":"4316",
    "addr:postcode":"33596",
    "addr:street":"New River Hills Pkwy",
    "iso:country":"US",
    "sg:address":"4316 New River Hills Pkwy",
    "sg:city":"Valrico",
    "sg:classifiers":[
        {
            "category":"Professional",
            "subcategory":"Employment Agencies",
            "type":"Services"
        }
    ],
    "sg:phone":"+1 813 571 2000",
    "sg:postcode":"33596",
    "sg:province":"FL",
    "sg:tags":[
        "consultant",
        "search",
        "executive"
    ],
    "wof:name":"Jim Adams",
    "wof:placetype":"venue"
},
  "geometry": {"coordinates":[-82.218487,27.878246],"type":"Point"}
}