{
  "type": "Feature",
  "properties": {
    "iso:country":"US",
    "sg:address":"4601 SE 5th Ave",
    "sg:city":"Cape Coral",
    "sg:classifiers":[
        {
            "category":"Travel",
            "subcategory":"Hotels & Motels",
            "type":"Entertainment"
        }
    ],
    "sg:phone":"+1 239 542 5812",
    "sg:postcode":"33904",
    "sg:province":"FL",
    "sg:website":"www.hideawayflorida.com",
    "wof:name":"Hideaway Waterfront Resort",
    "wof:placetype":"venue"
},
  "geometry": {"coordinates":[-81.96409300000001,26.566643],"type":"Point"}
}