{
  "type": "Feature",
  "properties": {
    "addr:full":"900 N Fort Harrison Ave Clearwater FL 33755",
    "addr:housenumber":"900",
    "addr:postcode":"33755",
    "addr:street":"N Fort Harrison Ave",
    "iso:country":"US",
    "sg:address":"900 N Fort Harrison Ave",
    "sg:city":"Clearwater",
    "sg:classifiers":[
        {
            "category":"Education",
            "subcategory":"School",
            "type":"Public Place"
        }
    ],
    "sg:phone":"+1 727 469 5982",
    "sg:postcode":"33755",
    "sg:province":"FL",
    "wof:name":"Northward Elementary School",
    "wof:placetype":"venue"
},
  "geometry": {"coordinates":[-82.798675,27.97573],"type":"Point"}
}