{
  "type": "Feature",
  "properties": {
    "addr:full":"728 Virginia Dr Orlando FL 32803",
    "addr:housenumber":"728",
    "addr:postcode":"32803",
    "addr:street":"Virginia Dr",
    "iso:country":"US",
    "sg:address":"728 Virginia Dr",
    "sg:city":"Orlando",
    "sg:classifiers":[
        {
            "category":"Recreation",
            "type":"Entertainment"
        }
    ],
    "sg:phone":"+1 407 894 6683",
    "sg:postcode":"32803",
    "sg:province":"FL",
    "wof:name":"Manor Gallery Inc",
    "wof:placetype":"venue"
},
  "geometry": {"coordinates":[-81.366226,28.563986],"type":"Point"}
}