{
  "type": "Feature",
  "properties": {
    "iso:country":"US",
    "sg:address":"3498 E Semoran Blvd",
    "sg:city":"Apopka",
    "sg:classifiers":[
        {
            "category":"Autos & Motor Vehicles",
            "subcategory":"Fuel & Gas Station",
            "type":"Retail Goods"
        }
    ],
    "sg:phone":"+1 407 774 4339",
    "sg:postcode":"32703",
    "sg:province":"FL",
    "sg:tags":[
        "oil"
    ],
    "wof:name":"Maverick Management",
    "wof:placetype":"venue"
},
  "geometry": {"coordinates":[-81.456502,28.672316],"type":"Point"}
}