{
  "type": "Feature",
  "properties": {
    "addr:full":"6553 Stirling Rd Davie FL 33314",
    "addr:housenumber":"6553",
    "addr:postcode":"33314",
    "addr:street":"Stirling Rd",
    "iso:country":"US",
    "sg:address":"6553 Stirling Rd",
    "sg:city":"Davie",
    "sg:classifiers":[
        {
            "category":"Insurance",
            "subcategory":"Hazard Insurance",
            "type":"Services"
        }
    ],
    "sg:phone":"+1 954 583 5900",
    "sg:postcode":"33314",
    "sg:province":"FL",
    "sg:tags":[
        "commercial",
        "business"
    ],
    "wof:name":"Roroga Enterprises, Inc",
    "wof:placetype":"venue"
},
  "geometry": {"coordinates":[-80.233515,26.046004],"type":"Point"}
}