{
  "type": "Feature",
  "properties": {
    "iso:country":"US",
    "sg:address":"14444 Beach Blvd",
    "sg:city":"Jacksonville Beach",
    "sg:classifiers":[
        {
            "category":"Health Services",
            "subcategory":"Doctor",
            "type":"Services"
        }
    ],
    "sg:phone":"+1 904 992 8900",
    "sg:postcode":"32250",
    "sg:province":"FL",
    "wof:name":"Reza Azari",
    "wof:placetype":"venue"
},
  "geometry": {"coordinates":[-81.435918,30.287855],"type":"Point"}
}