{
  "type": "Feature",
  "properties": {
    "iso:country":"US",
    "sg:address":"3115 NE Loquat Ln",
    "sg:city":"Jensen Beach",
    "sg:classifiers":[
        {
            "category":"Building & Trades",
            "subcategory":"Construction",
            "type":"Services"
        }
    ],
    "sg:phone":"+1 772 334 4511",
    "sg:postcode":"34957",
    "sg:province":"FL",
    "sg:tags":[
        "painter"
    ],
    "wof:name":"Extra Service Painting",
    "wof:placetype":"venue"
},
  "geometry": {"coordinates":[-80.238924,27.233952],"type":"Point"}
}