{
  "type": "Feature",
  "properties": {
    "iso:country":"US",
    "sg:address":"619 SE 9th Pl",
    "sg:city":"Cape Coral",
    "sg:classifiers":[
        {
            "category":"Building & Trades",
            "subcategory":"Construction",
            "type":"Services"
        }
    ],
    "sg:phone":"+1 239 242 0051",
    "sg:postcode":"33990",
    "sg:province":"FL",
    "sg:tags":[
        "floor",
        "laying",
        "contractor"
    ],
    "wof:name":"Cantrells Flooring Inc",
    "wof:placetype":"venue"
},
  "geometry": {"coordinates":[-81.955431,26.63815],"type":"Point"}
}