{
  "type": "Feature",
  "properties": {
    "addr:full":"1700 S Red Rd Ste 201 Miami FL 33155",
    "addr:housenumber":"1700",
    "addr:postcode":"33155",
    "addr:street":"S Red Rd Ste 201",
    "iso:country":"US",
    "sg:address":"1700 S Red Rd Ste 201",
    "sg:city":"Miami",
    "sg:classifiers":[
        {
            "category":"Real Estate",
            "subcategory":"Surveying",
            "type":"Services"
        }
    ],
    "sg:phone":"+1 305 262 1925",
    "sg:postcode":"33155",
    "sg:province":"FL",
    "sg:tags":[
        "surveyor",
        "land"
    ],
    "sg:website":"http://WWW.CLSURVEYORS.COM",
    "wof:name":"Continental Land Surveyors",
    "wof:placetype":"venue"
},
  "geometry": {"coordinates":[-80.287567,25.755613],"type":"Point"}
}