{
  "type": "Feature",
  "properties": {
    "iso:country":"US",
    "sg:address":"8487 Via Serena",
    "sg:city":"Boca Raton",
    "sg:classifiers":[
        {
            "category":"Professional",
            "subcategory":"Business Services",
            "type":"Services"
        }
    ],
    "sg:phone":"+1 561 883 5200",
    "sg:postcode":"33433",
    "sg:province":"FL",
    "sg:tags":[
        "arbitration"
    ],
    "wof:name":"Affordable Mediation Solutions",
    "wof:placetype":"venue"
},
  "geometry": {"coordinates":[-80.17932399999999,26.363711],"type":"Point"}
}