{
  "type": "Feature",
  "properties": {
    "addr:full":"2018 Shamrock Ln Lynn Haven FL 32444",
    "addr:housenumber":"2018",
    "addr:postcode":"32444",
    "addr:street":"Shamrock Ln",
    "iso:country":"US",
    "sg:address":"2018 Shamrock Ln",
    "sg:city":"Lynn Haven",
    "sg:classifiers":[
        {
            "category":"Building & Trades",
            "subcategory":"Plumbing",
            "type":"Services"
        }
    ],
    "sg:phone":"+1 850 265 4329",
    "sg:postcode":"32444",
    "sg:province":"FL",
    "sg:tags":[
        "contractor"
    ],
    "wof:name":"Arctic Air & Heat",
    "wof:placetype":"venue"
},
  "geometry": {"coordinates":[-85.62106,30.236711],"type":"Point"}
}