{
  "type": "Feature",
  "properties": {
    "addr:full":"13501 Icot Blvd Clearwater FL 33760",
    "addr:housenumber":"13501",
    "addr:postcode":"33760",
    "addr:street":"Icot Blvd",
    "iso:country":"US",
    "sg:address":"13501 Icot Blvd",
    "sg:city":"Clearwater",
    "sg:classifiers":[
        {
            "category":"Shopping",
            "subcategory":"Jewelry",
            "type":"Retail Goods"
        },
        {
            "category":"Shopping",
            "subcategory":"Antiques",
            "type":"Retail Goods"
        },
        {
            "category":"Shopping",
            "subcategory":"Pawn Shop",
            "type":"Retail Goods"
        }
    ],
    "sg:phone":"+1 727 535 3333",
    "sg:postcode":"33760",
    "sg:province":"FL",
    "sg:tags":[
        "buyer",
        "pawnbroker"
    ],
    "sg:website":"http://www.sellgoldformore.com",
    "wof:name":"A W D C - sellgoldformore.com",
    "wof:placetype":"venue"
},
  "geometry": {"coordinates":[-82.71520200000001,27.895069],"type":"Point"}
}