{
  "type": "Feature",
  "properties": {
    "iso:country":"US",
    "sg:address":"3025 SW 105th Ave",
    "sg:city":"Miami",
    "sg:classifiers":[
        {
            "category":"Freight",
            "type":"Transportation"
        }
    ],
    "sg:phone":"+1 305 594 2629",
    "sg:postcode":"33165",
    "sg:province":"FL",
    "wof:name":"Freight Control Inc",
    "wof:placetype":"venue"
},
  "geometry": {"coordinates":[-80.365109,25.739856],"type":"Point"}
}