{
  "type": "Feature",
  "properties": {
    "iso:country":"US",
    "sg:address":"1655 Lakeshore Cir",
    "sg:city":"Fort Lauderdale",
    "sg:classifiers":[
        {
            "category":"Wholesale",
            "subcategory":"Durable Goods & Equipment",
            "type":"Manufacturing & Wholesale Goods"
        },
        {
            "category":"Wholesale",
            "subcategory":"Non-durable Goods",
            "type":"Manufacturing & Wholesale Goods"
        }
    ],
    "sg:phone":"+1 954 384 4834",
    "sg:postcode":"33326",
    "sg:province":"FL",
    "sg:tags":[
        "exporter"
    ],
    "wof:name":"Silver Bird Corp",
    "wof:placetype":"venue"
},
  "geometry": {"coordinates":[-80.369748,26.099559],"type":"Point"}
}