{
  "type": "Feature",
  "properties": {
    "iso:country":"US",
    "sg:address":"208 Lakeside Ln",
    "sg:city":"Mary Esther",
    "sg:classifiers":[
        {
            "category":"Building & Trades",
            "subcategory":"Landscaping Services",
            "type":"Services"
        }
    ],
    "sg:phone":"+1 850 581 0439",
    "sg:postcode":"32569",
    "sg:province":"FL",
    "wof:name":"James Wortham Lawn Care",
    "wof:placetype":"venue"
},
  "geometry": {"coordinates":[-86.747499,30.412851],"type":"Point"}
}