{
  "type": "Feature",
  "properties": {
    "iso:country":"US",
    "sg:address":"4611 SW 75th Ave",
    "sg:city":"Miami",
    "sg:classifiers":[
        {
            "category":"Banks & Credit Unions",
            "subcategory":"Financial Services",
            "type":"Services"
        }
    ],
    "sg:phone":"+1 305 262 3913",
    "sg:postcode":"33155",
    "sg:province":"FL",
    "sg:tags":[
        "broker",
        "mortgage"
    ],
    "wof:name":"Mortgage Consultants Inc",
    "wof:placetype":"venue"
},
  "geometry": {"coordinates":[-80.316697,25.726739],"type":"Point"}
}