{
  "type": "Feature",
  "properties": {
    "addr:full":"7489 NW 4th St Fort Lauderdale FL 33317",
    "addr:housenumber":"7489",
    "addr:postcode":"33317",
    "addr:street":"Nw 4Th St",
    "iso:country":"US",
    "sg:address":"7489 NW 4th St",
    "sg:city":"Fort Lauderdale",
    "sg:classifiers":[
        {
            "category":"Building & Trades",
            "subcategory":"Construction",
            "type":"Services"
        }
    ],
    "sg:phone":"+1 954 581 8600",
    "sg:postcode":"33317",
    "sg:province":"FL",
    "sg:tags":[
        "specializing",
        "residential",
        "general",
        "contractor"
    ],
    "wof:name":"Donovan Construction Inc",
    "wof:placetype":"venue"
},
  "geometry": {"coordinates":[-80.249657,26.126931],"type":"Point"}
}