{
  "type": "Feature",
  "properties": {
    "addr:full":"5251 110th Ave N Clearwater FL 33760",
    "addr:housenumber":"5251",
    "addr:postcode":"33760",
    "addr:street":"110Th Ave N",
    "iso:country":"US",
    "sg:address":"5251 110th Ave N",
    "sg:city":"Clearwater",
    "sg:classifiers":[
        {
            "category":"Restaurant",
            "type":"Food & Drink"
        }
    ],
    "sg:phone":"+1 727 561 7311",
    "sg:postcode":"33760",
    "sg:province":"FL",
    "wof:name":"KOZY Korner",
    "wof:placetype":"venue"
},
  "geometry": {"coordinates":[-82.706001,27.872012],"type":"Point"}
}