{
  "type": "Feature",
  "properties": {
    "addr:full":"7628 N 56th St Tampa FL 33617",
    "addr:housenumber":"7628",
    "addr:postcode":"33617",
    "addr:street":"N 56Th St",
    "iso:country":"US",
    "sg:address":"7628 N 56th St",
    "sg:city":"Tampa",
    "sg:classifiers":[
        {
            "category":"Professional",
            "subcategory":"Business Services",
            "type":"Services"
        }
    ],
    "sg:phone":"+1 813 980 1560",
    "sg:postcode":"33617",
    "sg:province":"FL",
    "sg:tags":[
        "paralegal"
    ],
    "wof:name":"Assistance Program",
    "wof:placetype":"venue"
},
  "geometry": {"coordinates":[-82.39351600000001,28.017791],"type":"Point"}
}