{
  "type": "Feature",
  "properties": {
    "addr:full":"16002 Lakeshore Villa Dr Tampa FL 33613",
    "addr:housenumber":"16002",
    "addr:postcode":"33613",
    "addr:street":"Lakeshore Villa Dr",
    "iso:country":"US",
    "sg:address":"16002 Lakeshore Villa Dr",
    "sg:city":"Tampa",
    "sg:classifiers":[
        {
            "category":"Health Services",
            "subcategory":"Nursing And Care Facility",
            "type":"Services"
        }
    ],
    "sg:phone":"+1 813 968 5093",
    "sg:postcode":"33613",
    "sg:province":"FL",
    "sg:tags":[
        "skilled"
    ],
    "wof:name":"Senior Care Group Inc",
    "wof:placetype":"venue"
},
  "geometry": {"coordinates":[-82.454932,28.094612],"type":"Point"}
}