{
  "type": "Feature",
  "properties": {
    "iso:country":"US",
    "sg:address":"5501 W Spruce St",
    "sg:city":"Tampa",
    "sg:classifiers":[
        {
            "category":"Health Services",
            "subcategory":"Chiropractor",
            "type":"Services"
        }
    ],
    "sg:phone":"+1 813 873 2225",
    "sg:postcode":"33607",
    "sg:province":"FL",
    "wof:name":"Natl Corp Wellness Cnsltnts",
    "wof:placetype":"venue"
},
  "geometry": {"coordinates":[-82.538708,27.960016],"type":"Point"}
}