{
  "type": "Feature",
  "properties": {
    "addr:full":"8110 S Orange Blossom Trl Orlando FL 32809",
    "addr:housenumber":"8110",
    "addr:postcode":"32809",
    "addr:street":"S Orange Blossom Trl",
    "iso:country":"US",
    "sg:address":"8110 S Orange Blossom Trl",
    "sg:city":"Orlando",
    "sg:classifiers":[
        {
            "category":"Shopping",
            "subcategory":"Books",
            "type":"Retail Goods"
        }
    ],
    "sg:phone":"+1 407 859 3422",
    "sg:postcode":"32809",
    "sg:province":"FL",
    "sg:tags":[
        "comic"
    ],
    "wof:name":"A Ace Comics Inc",
    "wof:placetype":"venue"
},
  "geometry": {"coordinates":[-81.401053,28.449928],"type":"Point"}
}