{
  "type": "Feature",
  "properties": {
    "iso:country":"US",
    "sg:address":"305 NW 72nd Ave",
    "sg:city":"Miami",
    "sg:classifiers":[
        {
            "category":"Real Estate",
            "subcategory":"Real Estate Operator",
            "type":"Services"
        }
    ],
    "sg:phone":"+1 305 266 7821",
    "sg:postcode":"33126",
    "sg:province":"FL",
    "sg:tags":[
        "apartment"
    ],
    "wof:name":"Montecarlos Apt Inc",
    "wof:placetype":"venue"
},
  "geometry": {"coordinates":[-80.31202399999999,25.77335],"type":"Point"}
}