{
  "type": "Feature",
  "properties": {
    "iso:country":"US",
    "sg:address":"325 Nassauville Rd",
    "sg:city":"Fernandina Beach",
    "sg:classifiers":[
        {
            "category":"Organizations",
            "subcategory":"Religious Organization",
            "type":"Services"
        }
    ],
    "sg:phone":"+1 904 261 6553",
    "sg:postcode":"32034",
    "sg:province":"FL",
    "sg:tags":[
        "church"
    ],
    "wof:name":"Jehovah's Witnesses",
    "wof:placetype":"venue"
},
  "geometry": {"coordinates":[-81.51757499999999,30.60955],"type":"Point"}
}