{
  "type": "Feature",
  "properties": {
    "addr:full":"2000 E Oakland Park Blvd Fort Lauderdale FL 33306",
    "addr:housenumber":"2000",
    "addr:postcode":"33306",
    "addr:street":"E Oakland Park Blvd",
    "iso:country":"US",
    "sg:address":"2000 E Oakland Park Blvd",
    "sg:city":"Fort Lauderdale",
    "sg:classifiers":[
        {
            "category":"Manufacturing",
            "subcategory":"Apparel",
            "type":"Manufacturing & Wholesale Goods"
        }
    ],
    "sg:phone":"+1 954 565 2711",
    "sg:postcode":"33306",
    "sg:province":"FL",
    "sg:tags":[
        "prom",
        "custom",
        "corporate",
        "imprinted",
        "embroidered"
    ],
    "sg:website":"www.sharpmarketing.com",
    "wof:name":"Sharp Marketing",
    "wof:placetype":"venue"
},
  "geometry": {"coordinates":[-80.120014,26.167181],"type":"Point"}
}