{
  "type": "Feature",
  "properties": {
    "iso:country":"US",
    "sg:address":"7119 Poller Ave",
    "sg:city":"Tampa",
    "sg:classifiers":[
        {
            "category":"Shopping",
            "subcategory":"Bicycles & Sporting Goods",
            "type":"Retail Goods"
        }
    ],
    "sg:phone":"+1 813 932 2034",
    "sg:postcode":"33614",
    "sg:province":"FL",
    "sg:tags":[
        "equipment",
        "diver",
        "supply"
    ],
    "wof:name":"Hill Marine Supply",
    "wof:placetype":"venue"
},
  "geometry": {"coordinates":[-82.487494,28.013556],"type":"Point"}
}