{
  "type": "Feature",
  "properties": {
    "addr:full":"991 E 27th St Hialeah FL 33013",
    "addr:housenumber":"991",
    "addr:postcode":"33013",
    "addr:street":"E 27Th St",
    "iso:country":"US",
    "sg:address":"991 E 27th St",
    "sg:city":"Hialeah",
    "sg:classifiers":[
        {
            "category":"Retail",
            "subcategory":"Repair Shop",
            "type":"Services"
        }
    ],
    "sg:phone":"+1 305 693 9100",
    "sg:postcode":"33013",
    "sg:province":"FL",
    "sg:tags":[
        "key"
    ],
    "wof:name":"A Fajardo Locksmith",
    "wof:placetype":"venue"
},
  "geometry": {"coordinates":[-80.26391700000001,25.847237],"type":"Point"}
}