{
  "type": "Feature",
  "properties": {
    "iso:country":"US",
    "sg:address":"1009 Falcon St",
    "sg:city":"Deltona",
    "sg:classifiers":[
        {
            "category":"Retail",
            "subcategory":"Repair Shop",
            "type":"Services"
        }
    ],
    "sg:phone":"+1 386 574 7703",
    "sg:postcode":"32725",
    "sg:province":"FL",
    "sg:tags":[
        "sharpening"
    ],
    "wof:name":"J & L Sharp All",
    "wof:placetype":"venue"
},
  "geometry": {"coordinates":[-81.247659,28.882397],"type":"Point"}
}