{
  "type": "Feature",
  "properties": {
    "iso:country":"US",
    "sg:address":"4819 E Busch Blvd",
    "sg:city":"Tampa",
    "sg:classifiers":[
        {
            "category":"Banks & Credit Unions",
            "subcategory":"Bank",
            "type":"Services"
        }
    ],
    "sg:phone":"+1 813 988 1776",
    "sg:postcode":"33617",
    "sg:province":"FL",
    "sg:tags":[
        "loan",
        "real estate"
    ],
    "sg:website":"www.homemortgagelender.com",
    "wof:name":"Home Mortgage Lender Inc",
    "wof:placetype":"venue"
},
  "geometry": {"coordinates":[-82.407174,28.03256],"type":"Point"}
}