{
  "type": "Feature",
  "properties": {
    "iso:country":"US",
    "sg:address":"7101 SW 139th St",
    "sg:city":"Miami",
    "sg:classifiers":[
        {
            "category":"Professional",
            "subcategory":"Business Services",
            "type":"Services"
        }
    ],
    "sg:phone":"+1 305 256 0880",
    "sg:postcode":"33158",
    "sg:province":"FL",
    "wof:name":"Vendi Enterprises LLC",
    "wof:placetype":"venue"
},
  "geometry": {"coordinates":[-80.30865900000001,25.64193],"type":"Point"}
}