{
  "type": "Feature",
  "properties": {
    "iso:country":"US",
    "sg:address":"440 W New York Ave",
    "sg:city":"Deland",
    "sg:classifiers":[
        {
            "category":"Banks & Credit Unions",
            "subcategory":"Bank",
            "type":"Services"
        }
    ],
    "sg:phone":"+1 386 822 4744",
    "sg:postcode":"32720",
    "sg:province":"FL",
    "sg:tags":[
        "loan",
        "real estate"
    ],
    "wof:name":"Abraham Mortgage",
    "wof:placetype":"venue"
},
  "geometry": {"coordinates":[-81.310318,29.027955],"type":"Point"}
}