{
  "type": "Feature",
  "properties": {
    "iso:country":"US",
    "sg:address":"16540 Daeza Dr",
    "sg:city":"Winter Garden",
    "sg:classifiers":[
        {
            "category":"Real Estate",
            "subcategory":"Developer",
            "type":"Services"
        }
    ],
    "sg:phone":"+1 407 239 6970",
    "sg:postcode":"34787",
    "sg:province":"FL",
    "wof:name":"Woodmede Developers Inc",
    "wof:placetype":"venue"
},
  "geometry": {"coordinates":[-81.632954,28.354442],"type":"Point"}
}