{
  "type": "Feature",
  "properties": {
    "iso:country":"US",
    "sg:address":"2825 Lockwood Meadows Blvd",
    "sg:city":"Sarasota",
    "sg:classifiers":[
        {
            "category":"Manufacturing",
            "subcategory":"Retail Goods",
            "type":"Manufacturing & Wholesale Goods"
        }
    ],
    "sg:phone":"+1 941 957 3773",
    "sg:postcode":"34234",
    "sg:province":"FL",
    "sg:tags":[
        "product",
        "mfg"
    ],
    "wof:name":"Russells Screen Service",
    "wof:placetype":"venue"
},
  "geometry": {"coordinates":[-82.51121000000001,27.357797],"type":"Point"}
}