{
  "type": "Feature",
  "properties": {
    "iso:country":"US",
    "sg:address":"11259 Bus Park Blvd",
    "sg:city":"Jacksonville",
    "sg:classifiers":[
        {
            "category":"Wholesale",
            "subcategory":"Metals & Minerals",
            "type":"Manufacturing & Wholesale Goods"
        }
    ],
    "sg:phone":"+1 904 370 1360",
    "sg:postcode":"32256",
    "sg:province":"FL",
    "sg:tags":[
        "aluminum"
    ],
    "wof:name":"Aluminum Products",
    "wof:placetype":"venue"
},
  "geometry": {"coordinates":[-81.53302100000001,30.164194],"type":"Point"}
}