{
  "type": "Feature",
  "properties": {
    "addr:full":"4236 53rd Ave W Apt 2606 Bradenton FL 34210",
    "addr:housenumber":"4236",
    "addr:postcode":"2606;34210",
    "addr:street":"53Rd Ave W Apt",
    "iso:country":"US",
    "sg:address":"4236 53rd Ave W Apt 2606",
    "sg:city":"Bradenton",
    "sg:classifiers":[
        {
            "category":"Retail",
            "subcategory":"Auto Repair",
            "type":"Services"
        }
    ],
    "sg:phone":"+1 941 752 6875",
    "sg:postcode":"34210",
    "sg:province":"FL",
    "sg:tags":[
        "windshield"
    ],
    "wof:name":"Clear View Glassworks",
    "wof:placetype":"venue"
},
  "geometry": {"coordinates":[-82.60454799999999,27.447701],"type":"Point"}
}