{
  "type": "Feature",
  "properties": {
    "addr:full":"92 W 2nd St Atlantic Beach FL 32233",
    "addr:housenumber":"92",
    "addr:postcode":"32233",
    "addr:street":"W 2Nd St",
    "iso:country":"US",
    "sg:address":"92 W 2nd St",
    "sg:city":"Atlantic Beach",
    "sg:classifiers":[
        {
            "category":"Freight",
            "type":"Transportation"
        }
    ],
    "sg:phone":"+1 904 246 4014",
    "sg:postcode":"32233",
    "sg:province":"FL",
    "sg:tags":[
        "commercial",
        "storage"
    ],
    "wof:name":"Caribbean Cold Storage",
    "wof:placetype":"venue"
},
  "geometry": {"coordinates":[-81.421543,30.326718],"type":"Point"}
}