{
  "type": "Feature",
  "properties": {
    "iso:country":"US",
    "sg:address":"501 Wade St",
    "sg:city":"Winter Springs",
    "sg:classifiers":[
        {
            "category":"Building & Trades",
            "subcategory":"Electrical",
            "type":"Services"
        }
    ],
    "sg:phone":"+1 407 327 3848",
    "sg:postcode":"32708",
    "sg:province":"FL",
    "sg:tags":[
        "electrical",
        "contractor"
    ],
    "wof:name":"H L Pruitt Corp",
    "wof:placetype":"venue"
},
  "geometry": {"coordinates":[-81.296623,28.704604],"type":"Point"}
}