{
  "type": "Feature",
  "properties": {
    "iso:country":"US",
    "sg:address":"2197 Josey Rd",
    "sg:city":"Bonifay",
    "sg:classifiers":[
        {
            "category":"Professional",
            "subcategory":"Management & Consulting",
            "type":"Services"
        }
    ],
    "sg:phone":"+1 850 547 5888",
    "sg:postcode":"32425",
    "sg:province":"FL",
    "sg:tags":[
        "consultant",
        "recreation",
        "program"
    ],
    "wof:name":"Homes County Dixie Youth Bsbll",
    "wof:placetype":"venue"
},
  "geometry": {"coordinates":[-85.75761199999999,30.805714],"type":"Point"}
}