{
  "type": "Feature",
  "properties": {
    "iso:country":"US",
    "sg:address":"43 Skyline Dr",
    "sg:city":"Lake Mary",
    "sg:classifiers":[
        {
            "category":"Insurance",
            "subcategory":"Insurance Agent",
            "type":"Services"
        }
    ],
    "sg:phone":"+1 321 257 1300",
    "sg:postcode":"32746",
    "sg:province":"FL",
    "wof:name":"Guarantee Insurance Co",
    "wof:placetype":"venue"
},
  "geometry": {"coordinates":[-81.368206,28.738981],"type":"Point"}
}