{
  "type": "Feature",
  "properties": {
    "addr:full":"6835 Honeysuckle Trl Bradenton FL 34202",
    "addr:housenumber":"6835",
    "addr:postcode":"34202",
    "addr:street":"Honeysuckle Trl",
    "iso:country":"US",
    "sg:address":"6835 Honeysuckle Trl",
    "sg:city":"Bradenton",
    "sg:classifiers":[
        {
            "category":"Professional",
            "subcategory":"Management & Consulting",
            "type":"Services"
        }
    ],
    "sg:phone":"+1 941 907 4783",
    "sg:postcode":"34202",
    "sg:province":"FL",
    "sg:tags":[
        "business"
    ],
    "wof:name":"Wolf Market & Consulting",
    "wof:placetype":"venue"
},
  "geometry": {"coordinates":[-82.42021800000001,27.417293],"type":"Point"}
}