{
  "type": "Feature",
  "properties": {
    "addr:full":"1000 SW 84th Ave Miramar FL 33025",
    "addr:housenumber":"1000",
    "addr:postcode":"33025",
    "addr:street":"Sw 84Th Ave",
    "iso:country":"US",
    "sg:address":"1000 SW 84th Ave",
    "sg:city":"Miramar",
    "sg:classifiers":[
        {
            "category":"Health Services",
            "subcategory":"Clinic",
            "type":"Services"
        }
    ],
    "sg:phone":"+1 954 966 7375",
    "sg:postcode":"33025",
    "sg:province":"FL",
    "sg:tags":[
        "information",
        "mental"
    ],
    "wof:name":"Short-Term Rsdntial Trtmnt Ctr",
    "wof:placetype":"venue"
},
  "geometry": {"coordinates":[-80.25461199999999,25.993916],"type":"Point"}
}