{
  "type": "Feature",
  "properties": {
    "iso:country":"US",
    "sg:address":"831 SE 9th St",
    "sg:city":"Deerfield Beach",
    "sg:classifiers":[
        {
            "category":"Organizations",
            "subcategory":"Religious Organization",
            "type":"Services"
        }
    ],
    "sg:phone":"+1 954 420 0908",
    "sg:postcode":"33441",
    "sg:province":"FL",
    "sg:tags":[
        "church"
    ],
    "wof:name":"Theosophical Society",
    "wof:placetype":"venue"
},
  "geometry": {"coordinates":[-80.093108,26.306278],"type":"Point"}
}