{
  "type": "Feature",
  "properties": {
    "iso:country":"US",
    "sg:address":"9150 SW 87th Ave",
    "sg:city":"Miami",
    "sg:classifiers":[
        {
            "category":"Social Services",
            "type":"Services"
        }
    ],
    "sg:phone":"+1 305 274 0018",
    "sg:postcode":"33176",
    "sg:province":"FL",
    "sg:tags":[
        "worker"
    ],
    "wof:name":"Hartog Jill A LCSW PA",
    "wof:placetype":"venue"
},
  "geometry": {"coordinates":[-80.335436,25.684624],"type":"Point"}
}