{
  "type": "Feature",
  "properties": {
    "iso:country":"US",
    "sg:address":"13109 SW 122nd Ave",
    "sg:city":"Miami",
    "sg:classifiers":[
        {
            "category":"Building & Trades",
            "subcategory":"Construction",
            "type":"Services"
        }
    ],
    "sg:phone":"+1 305 235 1993",
    "sg:postcode":"33186",
    "sg:province":"FL",
    "sg:tags":[
        "maker",
        "cabinet"
    ],
    "sg:website":"http://www.craftmastercabinet.com",
    "wof:name":"Craft Master Custom Cabinets Inc",
    "wof:placetype":"venue"
},
  "geometry": {"coordinates":[-80.391513,25.64536],"type":"Point"}
}