{
  "type": "Feature",
  "properties": {
    "addr:full":"4101 SW 61st Ave Davie FL 33314",
    "addr:housenumber":"4101",
    "addr:postcode":"33314",
    "addr:street":"Sw 61St Ave",
    "iso:country":"US",
    "sg:address":"4101 SW 61st Ave",
    "sg:city":"Davie",
    "sg:classifiers":[
        {
            "category":"Place Of Worship",
            "type":"Public Place"
        }
    ],
    "sg:phone":"+1 954 583 4718",
    "sg:postcode":"33314",
    "sg:province":"FL",
    "sg:tags":[
        "church"
    ],
    "wof:name":"T C C Children's Academy",
    "wof:placetype":"venue"
},
  "geometry": {"coordinates":[-80.22825400000001,26.071481],"type":"Point"}
}