{
  "type": "Feature",
  "properties": {
    "iso:country":"US",
    "sg:address":"1520 Broadway Ste 107",
    "sg:city":"Fort Myers",
    "sg:classifiers":[
        {
            "category":"Banks & Credit Unions",
            "subcategory":"Bank",
            "type":"Services"
        },
        {
            "category":"Banks & Credit Unions",
            "subcategory":"Financial Services",
            "type":"Services"
        }
    ],
    "sg:phone":"+1 239 332 5115",
    "sg:postcode":"33901",
    "sg:province":"FL",
    "sg:tags":[
        "broker",
        "mortgage"
    ],
    "wof:name":"Southwest Capital Bank",
    "wof:placetype":"venue"
},
  "geometry": {"coordinates":[-81.87070900000001,26.643597],"type":"Point"}
}