{
  "type": "Feature",
  "properties": {
    "addr:full":"2325 NE 145th Avenue Rd Silver Springs FL 34488",
    "addr:housenumber":"2325",
    "addr:postcode":"34488",
    "addr:street":"Ne 145Th Avenue Rd",
    "iso:country":"US",
    "sg:address":"2325 NE 145th Avenue Rd",
    "sg:city":"Silver Springs",
    "sg:classifiers":[
        {
            "category":"Shopping",
            "subcategory":"Used Merchandise",
            "type":"Retail Goods"
        }
    ],
    "sg:phone":"+1 352 625 2178",
    "sg:postcode":"34488",
    "sg:province":"FL",
    "wof:name":"Troy Stigall Discount Mdse",
    "wof:placetype":"venue"
},
  "geometry": {"coordinates":[-81.913156,29.215086],"type":"Point"}
}