{
  "type": "Feature",
  "properties": {
    "addr:full":"6223 N 9th Ave Pensacola FL 32504",
    "addr:housenumber":"6223",
    "addr:postcode":"32504",
    "addr:street":"N 9Th Ave",
    "iso:country":"US",
    "sg:address":"6223 N 9th Ave",
    "sg:city":"Pensacola",
    "sg:classifiers":[
        {
            "category":"Restaurant",
            "type":"Food & Drink"
        }
    ],
    "sg:phone":"+1 850 478 0563",
    "sg:postcode":"32504",
    "sg:province":"FL",
    "sg:tags":[
        "fast"
    ],
    "wof:name":"Whataburger",
    "wof:placetype":"venue"
},
  "geometry": {"coordinates":[-87.197602,30.488028],"type":"Point"}
}