{
  "type": "Feature",
  "properties": {
    "iso:country":"US",
    "sg:address":"3293 S US Hwy 1",
    "sg:city":"Fort Pierce",
    "sg:classifiers":[
        {
            "category":"Professional",
            "subcategory":"Accounting & Tax Preparation",
            "type":"Services"
        }
    ],
    "sg:phone":"+1 772 462 4010",
    "sg:postcode":"34982",
    "sg:province":"FL",
    "sg:tags":[
        "return",
        "filing"
    ],
    "wof:name":"Taxes & Svc By Noe Gomez",
    "wof:placetype":"venue"
},
  "geometry": {"coordinates":[-80.32581500000001,27.40392],"type":"Point"}
}