{
  "type": "Feature",
  "properties": {
    "addr:full":"20810 W Dixie Hwy Miami FL 33180",
    "addr:housenumber":"20810",
    "addr:postcode":"33180",
    "addr:street":"W Dixie Hwy",
    "iso:country":"US",
    "sg:address":"20810 W Dixie Hwy",
    "sg:city":"Miami",
    "sg:classifiers":[
        {
            "category":"Professional",
            "subcategory":"Accounting & Tax Preparation",
            "type":"Services"
        }
    ],
    "sg:phone":"+1 305 466 4502",
    "sg:postcode":"33180",
    "sg:province":"FL",
    "wof:name":"American Accounting Inc",
    "wof:placetype":"venue"
},
  "geometry": {"coordinates":[-80.147916,25.967843],"type":"Point"}
}