{
  "type": "Feature",
  "properties": {
    "iso:country":"US",
    "sg:address":"4310 23rd Pl SW",
    "sg:city":"Naples",
    "sg:classifiers":[
        {
            "category":"Building & Trades",
            "subcategory":"Construction",
            "type":"Services"
        }
    ],
    "sg:phone":"+1 239 455 1148",
    "sg:postcode":"34116",
    "sg:province":"FL",
    "sg:tags":[
        "clearing",
        "land",
        "leveling"
    ],
    "wof:name":"J R's Lawn & Tractor Svc",
    "wof:placetype":"venue"
},
  "geometry": {"coordinates":[-81.69387,26.185312],"type":"Point"}
}