{
  "type": "Feature",
  "properties": {
    "iso:country":"US",
    "sg:address":"330 North St",
    "sg:city":"Daytona Beach",
    "sg:classifiers":[
        {
            "category":"Organizations",
            "subcategory":"Non-profit Organization",
            "type":"Services"
        }
    ],
    "sg:phone":"+1 386 252 7200",
    "sg:postcode":"32114",
    "sg:province":"FL",
    "sg:website":"www.mfhp.org",
    "wof:name":"Mid Flordia Housing Partnershi",
    "wof:placetype":"venue"
},
  "geometry": {"coordinates":[-81.02983500000001,29.221367],"type":"Point"}
}