{
  "type": "Feature",
  "properties": {
    "addr:full":"2951 E Stonebrook Cir Fort Lauderdale FL 33330",
    "addr:housenumber":"2951",
    "addr:postcode":"33330",
    "addr:street":"E Stonebrook Cir",
    "iso:country":"US",
    "sg:address":"2951 E Stonebrook Cir",
    "sg:city":"Fort Lauderdale",
    "sg:classifiers":[
        {
            "category":"Professional",
            "subcategory":"Detective & Security Services",
            "type":"Services"
        }
    ],
    "sg:phone":"+1 954 424 4342",
    "sg:postcode":"33330",
    "sg:province":"FL",
    "sg:tags":[
        "system"
    ],
    "wof:name":"Nor Seg Security Services Inc",
    "wof:placetype":"venue"
},
  "geometry": {"coordinates":[-80.314606,26.082363],"type":"Point"}
}