{
  "type": "Feature",
  "properties": {
    "iso:country":"US",
    "sg:address":"102 Hammocks Ct",
    "sg:city":"Greenacres",
    "sg:classifiers":[
        {
            "category":"Retail",
            "subcategory":"Portrait Studio",
            "type":"Services"
        }
    ],
    "sg:phone":"+1 561 969 0262",
    "sg:postcode":"33413",
    "sg:province":"FL",
    "sg:tags":[
        "photographer"
    ],
    "wof:name":"Hayes Photography",
    "wof:placetype":"venue"
},
  "geometry": {"coordinates":[-80.149586,26.645936],"type":"Point"}
}