{
  "type": "Feature",
  "properties": {
    "addr:full":"2479 NW 63rd St Boca Raton FL 33496",
    "addr:housenumber":"2479",
    "addr:postcode":"33496",
    "addr:street":"Nw 63Rd St",
    "iso:country":"US",
    "sg:address":"2479 NW 63rd St",
    "sg:city":"Boca Raton",
    "sg:classifiers":[
        {
            "category":"Professional",
            "subcategory":"Business Services",
            "type":"Services"
        }
    ],
    "sg:phone":"+1 561 998 0697",
    "sg:postcode":"33496",
    "sg:province":"FL",
    "wof:name":"Coastal Financial Group Inc",
    "wof:placetype":"venue"
},
  "geometry": {"coordinates":[-80.13731799999999,26.405361],"type":"Point"}
}