{
  "type": "Feature",
  "properties": {
    "iso:country":"US",
    "sg:address":"505 S Conway Rd",
    "sg:city":"Orlando",
    "sg:classifiers":[
        {
            "category":"Food & Beverages",
            "subcategory":"Groceries & Convenience Stores",
            "type":"Retail Goods"
        }
    ],
    "sg:phone":"+1 407 275 1210",
    "sg:postcode":"32807",
    "sg:province":"FL",
    "wof:name":"Maverick",
    "wof:placetype":"venue"
},
  "geometry": {"coordinates":[-81.331121,28.536714],"type":"Point"}
}