{
  "type": "Feature",
  "properties": {
    "iso:country":"US",
    "sg:address":"200 S Park Rd",
    "sg:city":"Hollywood",
    "sg:classifiers":[
        {
            "category":"Health Services",
            "subcategory":"Doctor",
            "type":"Services"
        }
    ],
    "sg:phone":"+1 954 981 3330",
    "sg:postcode":"33021",
    "sg:province":"FL",
    "sg:tags":[
        "medical"
    ],
    "wof:name":"Behan Hektner & Miller PA",
    "wof:placetype":"venue"
},
  "geometry": {"coordinates":[-80.17555,26.009708],"type":"Point"}
}