{
  "type": "Feature",
  "properties": {
    "iso:country":"US",
    "sg:address":"5339 Mile Stretch Dr",
    "sg:city":"Holiday",
    "sg:classifiers":[
        {
            "category":"Social Services",
            "subcategory":"Child Care",
            "type":"Services"
        },
        {
            "category":"Education",
            "subcategory":"Preschool",
            "type":"Public Place"
        }
    ],
    "sg:phone":"+1 727 934 3739",
    "sg:postcode":"34690",
    "sg:province":"FL",
    "sg:tags":[
        "kindergarten",
        "school",
        "nursery",
        "day"
    ],
    "wof:name":"Kids Stop-N-Play",
    "wof:placetype":"venue"
},
  "geometry": {"coordinates":[-82.725444,28.188021],"type":"Point"}
}