{
  "type": "Feature",
  "properties": {
    "iso:country":"US",
    "sg:address":"8479 Walden Rd",
    "sg:city":"Jacksonville",
    "sg:classifiers":[
        {
            "category":"Retail",
            "subcategory":"Repair Shop",
            "type":"Services"
        }
    ],
    "sg:phone":"+1 904 778 1518",
    "sg:postcode":"32244",
    "sg:province":"FL",
    "sg:tags":[
        "hardware"
    ],
    "wof:name":"Walts Pumps",
    "wof:placetype":"venue"
},
  "geometry": {"coordinates":[-81.789424,30.205614],"type":"Point"}
}