{
  "type": "Feature",
  "properties": {
    "addr:full":"1283 Co Rd 463 Lake Panasoffkee FL 33538",
    "addr:housenumber":"1283",
    "addr:postcode":"33538",
    "addr:street":"Co Rd 463",
    "iso:country":"US",
    "sg:address":"1283 Co Rd 463",
    "sg:city":"Lake Panasoffkee",
    "sg:classifiers":[
        {
            "category":"Wholesale",
            "subcategory":"Machinery & Supplies",
            "type":"Manufacturing & Wholesale Goods"
        }
    ],
    "sg:phone":"+1 352 793 1809",
    "sg:postcode":"33538",
    "sg:province":"FL",
    "sg:tags":[
        "equipment",
        "establishment"
    ],
    "wof:name":"Beautician Louise Tuberville",
    "wof:placetype":"venue"
},
  "geometry": {"coordinates":[-82.12328599999999,28.780892],"type":"Point"}
}