{
  "type": "Feature",
  "properties": {
    "addr:full":"81197 Overseas Hwy Islamorada FL 33036",
    "addr:housenumber":"81197",
    "addr:postcode":"33036",
    "addr:street":"Overseas Hwy",
    "iso:country":"US",
    "sg:address":"81197 Overseas Hwy",
    "sg:city":"Islamorada",
    "sg:classifiers":[
        {
            "category":"Home & Garden",
            "subcategory":"Garden Supply",
            "type":"Retail Goods"
        }
    ],
    "sg:phone":"+1 305 664 3433",
    "sg:postcode":"33036",
    "sg:province":"FL",
    "wof:name":"Banyan Tree",
    "wof:placetype":"venue"
},
  "geometry": {"coordinates":[-80.643109,24.911202],"type":"Point"}
}