{
  "type": "Feature",
  "properties": {
    "addr:full":"5620 Sheridan St Hollywood FL 33021",
    "addr:housenumber":"5620",
    "addr:postcode":"33021",
    "addr:street":"Sheridan St",
    "iso:country":"US",
    "sg:address":"5620 Sheridan St",
    "sg:city":"Hollywood",
    "sg:classifiers":[
        {
            "category":"Health Services",
            "subcategory":"Medical Lab",
            "type":"Services"
        }
    ],
    "sg:phone":"+1 954 963 0003",
    "sg:postcode":"33021",
    "sg:province":"FL",
    "sg:tags":[
        "laboratory",
        "dental"
    ],
    "wof:name":"Kcd Dental Lab",
    "wof:placetype":"venue"
},
  "geometry": {"coordinates":[-80.20034699999999,26.03238],"type":"Point"}
}