{
  "type": "Feature",
  "properties": {
    "addr:full":"1900 S Goldenrod Rd Orlando FL 32822",
    "addr:housenumber":"1900",
    "addr:postcode":"32822",
    "addr:street":"S Goldenrod Rd",
    "iso:country":"US",
    "sg:address":"1900 S Goldenrod Rd",
    "sg:city":"Orlando",
    "sg:classifiers":[
        {
            "category":"Organizations",
            "subcategory":"Community Association",
            "type":"Services"
        }
    ],
    "sg:phone":"+1 407 273 5480",
    "sg:postcode":"32822",
    "sg:province":"FL",
    "sg:tags":[
        "fraternal"
    ],
    "wof:name":"Fraternal Order Of Eagles",
    "wof:placetype":"venue"
},
  "geometry": {"coordinates":[-81.28566600000001,28.52422],"type":"Point"}
}