{
  "type": "Feature",
  "properties": {
    "iso:country":"US",
    "sg:address":"624 Cave Hollow Ln",
    "sg:city":"Orlando",
    "sg:classifiers":[
        {
            "category":"Professional",
            "subcategory":"Accounting & Tax Preparation",
            "type":"Services"
        }
    ],
    "sg:phone":"+1 407 382 6198",
    "sg:postcode":"32828",
    "sg:province":"FL",
    "wof:name":"Diane M Porath CPA",
    "wof:placetype":"venue"
},
  "geometry": {"coordinates":[-81.20457,28.53922],"type":"Point"}
}