{
  "type": "Feature",
  "properties": {
    "iso:country":"US",
    "sg:address":"5150 Volunteer Rd",
    "sg:city":"Southwest Rnchs",
    "sg:classifiers":[
        {
            "category":"Retail",
            "subcategory":"Car Wash",
            "type":"Services"
        }
    ],
    "sg:phone":"+1 954 680 9721",
    "sg:postcode":"33330",
    "sg:province":"FL",
    "sg:tags":[
        "polishing",
        "washing"
    ],
    "wof:name":"Unlimited Car Washing",
    "wof:placetype":"venue"
},
  "geometry": {"coordinates":[-80.34595400000001,26.054887],"type":"Point"}
}