{
  "type": "Feature",
  "properties": {
    "iso:country":"US",
    "sg:address":"6491 Fairchild Ave",
    "sg:city":"Cocoa",
    "sg:classifiers":[
        {
            "category":"Shopping",
            "subcategory":"Hobbies, Toys, & Games",
            "type":"Retail Goods"
        }
    ],
    "sg:phone":"+1 321 433 3655",
    "sg:postcode":"32927",
    "sg:province":"FL",
    "sg:tags":[
        "doll"
    ],
    "wof:name":"Space Coast Doll Works",
    "wof:placetype":"venue"
},
  "geometry": {"coordinates":[-80.811387,28.471929],"type":"Point"}
}