{
  "type": "Feature",
  "properties": {
    "addr:full":"621 Lakeview Rd Clearwater FL 33756",
    "addr:housenumber":"621",
    "addr:postcode":"33756",
    "addr:street":"Lakeview Rd",
    "iso:country":"US",
    "sg:address":"621 Lakeview Rd",
    "sg:city":"Clearwater",
    "sg:classifiers":[
        {
            "category":"Manufacturing",
            "subcategory":"Apparel",
            "type":"Manufacturing & Wholesale Goods"
        }
    ],
    "sg:phone":"+1 727 442 1477",
    "sg:postcode":"33756",
    "sg:province":"FL",
    "sg:tags":[
        "mfg"
    ],
    "wof:name":"Weezee Wear Inc",
    "wof:placetype":"venue"
},
  "geometry": {"coordinates":[-82.797855,27.94809],"type":"Point"}
}