{
  "type": "Feature",
  "properties": {
    "iso:country":"US",
    "sg:address":"14286 Beach Blvd",
    "sg:city":"Jacksonville Beach",
    "sg:classifiers":[
        {
            "category":"Banks & Credit Unions",
            "subcategory":"Bank",
            "type":"Services"
        }
    ],
    "sg:phone":"+1 904 992 8171",
    "sg:postcode":"32250",
    "sg:province":"FL",
    "sg:tags":[
        "national",
        "commercial"
    ],
    "wof:name":"Bank of America",
    "wof:placetype":"venue"
},
  "geometry": {"coordinates":[-81.441652,30.287774],"type":"Point"}
}