{
  "type": "Feature",
  "properties": {
    "addr:full":"1251 Taylor Ln Exd Lehigh Acres FL 33936",
    "addr:housenumber":"1251",
    "addr:postcode":"33936",
    "addr:street":"Taylor Ln Exd",
    "iso:country":"US",
    "sg:address":"1251 Taylor Ln Exd",
    "sg:city":"Lehigh Acres",
    "sg:classifiers":[
        {
            "category":"Restaurant",
            "type":"Food & Drink"
        }
    ],
    "sg:phone":"+1 239 368 3139",
    "sg:postcode":"33936",
    "sg:province":"FL",
    "wof:name":"L A Pizza",
    "wof:placetype":"venue"
},
  "geometry": {"coordinates":[-81.64707300000001,26.60815],"type":"Point"}
}