{
  "type": "Feature",
  "properties": {
    "iso:country":"US",
    "sg:address":"7131 W Gator Ln",
    "sg:city":"Crystal River",
    "sg:classifiers":[
        {
            "category":"Personal",
            "type":"Services"
        }
    ],
    "sg:phone":"+1 352 563 0748",
    "sg:postcode":"34428",
    "sg:province":"FL",
    "wof:name":"Bernard D Mulligan Inc",
    "wof:placetype":"venue"
},
  "geometry": {"coordinates":[-82.551939,28.905898],"type":"Point"}
}