{
  "type": "Feature",
  "properties": {
    "addr:full":"12976 SW 89th Ave Miami FL 33176",
    "addr:housenumber":"12976",
    "addr:postcode":"33176",
    "addr:street":"Sw 89Th Ave",
    "iso:country":"US",
    "sg:address":"12976 SW 89th Ave",
    "sg:city":"Miami",
    "sg:classifiers":[
        {
            "category":"Building & Trades",
            "subcategory":"Construction",
            "type":"Services"
        }
    ],
    "sg:phone":"+1 305 232 8800",
    "sg:postcode":"33176",
    "sg:province":"FL",
    "sg:tags":[
        "shed",
        "utility"
    ],
    "wof:name":"Certified Buildings",
    "wof:placetype":"venue"
},
  "geometry": {"coordinates":[-80.338476,25.64946],"type":"Point"}
}