{
  "type": "Feature",
  "properties": {
    "iso:country":"US",
    "sg:address":"1810 E Busch Blvd",
    "sg:city":"Tampa",
    "sg:classifiers":[
        {
            "category":"Travel",
            "subcategory":"Hotels & Motels",
            "type":"Entertainment"
        }
    ],
    "sg:phone":"+1 813 933 2665",
    "sg:postcode":"33612",
    "sg:province":"FL",
    "wof:name":"Economy Inn",
    "wof:placetype":"venue"
},
  "geometry": {"coordinates":[-82.437607,28.032636],"type":"Point"}
}