{
  "type": "Feature",
  "properties": {
    "addr:full":"7427 State Rd 21 Keystone Heights FL 32656",
    "addr:housenumber":"7427;21",
    "addr:postcode":"32656",
    "addr:street":"State Rd;Heights",
    "iso:country":"US",
    "sg:address":"7427 State Rd 21",
    "sg:city":"Keystone Heights",
    "sg:classifiers":[
        {
            "category":"Food & Beverages",
            "subcategory":"Groceries & Convenience Stores",
            "type":"Retail Goods"
        }
    ],
    "sg:phone":"+1 352 473 9197",
    "sg:postcode":"32656",
    "sg:province":"FL",
    "wof:name":"B & M Food Mart",
    "wof:placetype":"venue"
},
  "geometry": {"coordinates":[-82.02773000000001,29.79023],"type":"Point"}
}