{
  "type": "Feature",
  "properties": {
    "addr:full":"9330 Fountainbleau Blvd Miami FL 33172",
    "addr:housenumber":"9330",
    "addr:postcode":"33172",
    "addr:street":"Fountainbleau Blvd",
    "iso:country":"US",
    "sg:address":"9330 Fountainbleau Blvd",
    "sg:city":"Miami",
    "sg:classifiers":[
        {
            "category":"Professional",
            "subcategory":"Management & Consulting",
            "type":"Services"
        }
    ],
    "sg:phone":"+1 305 992 3331",
    "sg:postcode":"33172",
    "sg:province":"FL",
    "wof:name":"J Martin Inc",
    "wof:placetype":"venue"
},
  "geometry": {"coordinates":[-80.349615,25.774532],"type":"Point"}
}