{
  "type": "Feature",
  "properties": {
    "iso:country":"US",
    "sg:address":"645 S Federal Hwy",
    "sg:city":"Dania",
    "sg:classifiers":[
        {
            "category":"Restaurant",
            "type":"Food & Drink"
        }
    ],
    "sg:menulink":"http://www.allmenus.com/fl/hollywood/163551-rallys/menu/",
    "sg:phone":"+1 954 925 4729",
    "sg:postcode":"33004",
    "sg:province":"FL",
    "sg:tags":[
        "sandwich",
        "dog",
        "burger",
        "hot",
        "wrap",
        "american"
    ],
    "wof:name":"Rally's",
    "wof:placetype":"venue"
},
  "geometry": {"coordinates":[-80.143366,26.041339],"type":"Point"}
}