{
  "type": "Feature",
  "properties": {
    "iso:country":"US",
    "sg:address":"9498 NW 17th Ave",
    "sg:city":"Miami",
    "sg:classifiers":[
        {
            "category":"Retail",
            "subcategory":"Auto Repair",
            "type":"Services"
        }
    ],
    "sg:phone":"+1 305 691 6698",
    "sg:postcode":"33147",
    "sg:province":"FL",
    "sg:tags":[
        "repairing",
        "tire"
    ],
    "wof:name":"Chris Tires & Rims",
    "wof:placetype":"venue"
},
  "geometry": {"coordinates":[-80.22585599999999,25.860445],"type":"Point"}
}