{
  "type": "Feature",
  "properties": {
    "iso:country":"US",
    "sg:address":"851 Seminola Blvd",
    "sg:city":"Casselberry",
    "sg:classifiers":[
        {
            "category":"Building & Trades",
            "subcategory":"Landscaping Services",
            "type":"Services"
        }
    ],
    "sg:phone":"+1 407 695 1174",
    "sg:postcode":"32707",
    "sg:province":"FL",
    "sg:tags":[
        "landscape",
        "contractor"
    ],
    "wof:name":"Ground Werks",
    "wof:placetype":"venue"
},
  "geometry": {"coordinates":[-81.319226,28.675944],"type":"Point"}
}