{
  "type": "Feature",
  "properties": {
    "addr:full":"338 Bartow Blvd Bartow FL 33830",
    "addr:housenumber":"338",
    "addr:postcode":"33830",
    "addr:street":"Bartow Blvd",
    "iso:country":"US",
    "sg:address":"338 Bartow Blvd",
    "sg:city":"Bartow",
    "sg:classifiers":[
        {
            "category":"Retail",
            "subcategory":"Auto Repair",
            "type":"Services"
        }
    ],
    "sg:phone":"+1 863 533 3722",
    "sg:postcode":"33830",
    "sg:province":"FL",
    "sg:tags":[
        "automobile",
        "restoration",
        "classic"
    ],
    "wof:name":"Lloyd's Auto Restorations",
    "wof:placetype":"venue"
},
  "geometry": {"coordinates":[-81.845398,27.87947],"type":"Point"}
}