{
  "type": "Feature",
  "properties": {
    "iso:country":"US",
    "sg:address":"4000 Hollywood Blvd",
    "sg:city":"Hollywood",
    "sg:classifiers":[
        {
            "category":"Professional",
            "subcategory":"Management & Consulting",
            "type":"Services"
        }
    ],
    "sg:phone":"+1 305 530 3534",
    "sg:postcode":"33021",
    "sg:province":"FL",
    "sg:tags":[
        "specializing",
        "consultant",
        "benefit",
        "business",
        "employee"
    ],
    "wof:name":"F D R Financial Group Inc",
    "wof:placetype":"venue"
},
  "geometry": {"coordinates":[-80.184861,26.010731],"type":"Point"}
}