{
  "type": "Feature",
  "properties": {
    "iso:country":"US",
    "sg:address":"1713 Haverhill Dr",
    "sg:city":"Deltona",
    "sg:classifiers":[
        {
            "category":"Retail",
            "subcategory":"Repair Shop",
            "type":"Services"
        }
    ],
    "sg:phone":"+1 386 574 1610",
    "sg:postcode":"32725",
    "sg:province":"FL",
    "sg:tags":[
        "related"
    ],
    "wof:name":"Andrew's Inc",
    "wof:placetype":"venue"
},
  "geometry": {"coordinates":[-81.22557,28.904332],"type":"Point"}
}