{
  "type": "Feature",
  "properties": {
    "iso:country":"US",
    "sg:address":"340 12th Ave",
    "sg:city":"Indian Rocks Beach",
    "sg:classifiers":[
        {
            "category":"Building & Trades",
            "subcategory":"Landscaping Services",
            "type":"Services"
        }
    ],
    "sg:phone":"+1 727 596 6764",
    "sg:postcode":"33785",
    "sg:province":"FL",
    "wof:name":"Sunshine Lawn & Landscapi",
    "wof:placetype":"venue"
},
  "geometry": {"coordinates":[-82.84243499999999,27.895614],"type":"Point"}
}