{
  "type": "Feature",
  "properties": {
    "iso:country":"US",
    "sg:address":"216 28th St S",
    "sg:city":"St Petersburg",
    "sg:classifiers":[
        {
            "category":"Retail",
            "subcategory":"Car Wash",
            "type":"Services"
        }
    ],
    "sg:phone":"+1 727 648 3060",
    "sg:postcode":"33712",
    "sg:province":"FL",
    "sg:tags":[
        "polishing",
        "washing"
    ],
    "wof:name":"K & D Car Wash",
    "wof:placetype":"venue"
},
  "geometry": {"coordinates":[-82.671156,27.768453],"type":"Point"}
}