{
  "type": "Feature",
  "properties": {
    "addr:full":"9220 Rainbow Ln Port Richey FL 34668",
    "addr:housenumber":"9220",
    "addr:postcode":"34668",
    "addr:street":"Rainbow Ln",
    "iso:country":"US",
    "sg:address":"9220 Rainbow Ln",
    "sg:city":"Port Richey",
    "sg:classifiers":[
        {
            "category":"Professional",
            "subcategory":"Advertising",
            "type":"Services"
        }
    ],
    "sg:phone":"+1 727 815 9619",
    "sg:postcode":"34668",
    "sg:province":"FL",
    "wof:name":"Crossroads Advertising",
    "wof:placetype":"venue"
},
  "geometry": {"coordinates":[-82.683611,28.291579],"type":"Point"}
}