{
  "type": "Feature",
  "properties": {
    "iso:country":"US",
    "sg:address":"3832 S Lake Dr",
    "sg:city":"Boynton Beach",
    "sg:classifiers":[
        {
            "category":"Freight",
            "type":"Transportation"
        }
    ],
    "sg:phone":"+1 561 824 8326",
    "sg:postcode":"33435",
    "sg:province":"FL",
    "wof:name":"Tag Team Movers Inc",
    "wof:placetype":"venue"
},
  "geometry": {"coordinates":[-80.079736,26.488822],"type":"Point"}
}