{
  "type": "Feature",
  "properties": {
    "iso:country":"US",
    "sg:address":"504 E del Monte Ave",
    "sg:city":"Clewiston",
    "sg:classifiers":[
        {
            "category":"Building & Trades",
            "subcategory":"Landscaping Services",
            "type":"Services"
        }
    ],
    "sg:phone":"+1 863 983 8526",
    "sg:postcode":"33440",
    "sg:province":"FL",
    "wof:name":"Ladies of Lawn",
    "wof:placetype":"venue"
},
  "geometry": {"coordinates":[-80.924785,26.759043],"type":"Point"}
}