{
  "type": "Feature",
  "properties": {
    "iso:country":"US",
    "sg:address":"1656 NW 35th St",
    "sg:city":"Miami",
    "sg:classifiers":[
        {
            "category":"Transit Center",
            "subcategory":"Freight",
            "type":"Transportation"
        }
    ],
    "sg:phone":"+1 305 403 4010",
    "sg:postcode":"33142",
    "sg:province":"FL",
    "sg:tags":[
        "cargo",
        "air",
        "express",
        "package"
    ],
    "wof:name":"Martinez Cargo Express",
    "wof:placetype":"venue"
},
  "geometry": {"coordinates":[-80.223415,25.808614],"type":"Point"}
}