{
  "type": "Feature",
  "properties": {
    "iso:country":"US",
    "sg:address":"4315 Highland Park Blvd",
    "sg:city":"Lakeland",
    "sg:classifiers":[
        {
            "category":"Professional",
            "subcategory":"Accounting & Tax Preparation",
            "type":"Services"
        }
    ],
    "sg:phone":"+1 863 644 6688",
    "sg:postcode":"33813",
    "sg:province":"FL",
    "sg:tags":[
        "accountant"
    ],
    "wof:name":"Brokaw Investment Advisors",
    "wof:placetype":"venue"
},
  "geometry": {"coordinates":[-81.95423599999999,27.986874],"type":"Point"}
}