{
  "type": "Feature",
  "properties": {
    "addr:full":"9309 S Orange Blossom Trl Orlando FL 32837",
    "addr:housenumber":"9309",
    "addr:postcode":"32837",
    "addr:street":"S Orange Blossom Trl",
    "iso:country":"US",
    "sg:address":"9309 S Orange Blossom Trl",
    "sg:city":"Orlando",
    "sg:classifiers":[
        {
            "category":"Health Services",
            "subcategory":"Nursing And Care Facility",
            "type":"Services"
        }
    ],
    "sg:phone":"+1 407 851 8969",
    "sg:postcode":"32837",
    "sg:province":"FL",
    "sg:tags":[
        "home",
        "retirement",
        "community"
    ],
    "wof:name":"Alliance Care Of America",
    "wof:placetype":"venue"
},
  "geometry": {"coordinates":[-81.404651,28.428815],"type":"Point"}
}