{
  "type": "Feature",
  "properties": {
    "iso:country":"US",
    "sg:address":"6500 NW 12th Ave",
    "sg:city":"Fort Lauderdale",
    "sg:classifiers":[
        {
            "category":"Wholesale",
            "subcategory":"Office Equipment",
            "type":"Manufacturing & Wholesale Goods"
        }
    ],
    "sg:phone":"+1 954 489 0050",
    "sg:postcode":"33309",
    "sg:province":"FL",
    "sg:tags":[
        "machine",
        "mailing"
    ],
    "wof:name":"East Coast Mailing Systems Inc",
    "wof:placetype":"venue"
},
  "geometry": {"coordinates":[-80.15984899999999,26.207773],"type":"Point"}
}