{
  "type": "Feature",
  "properties": {
    "iso:country":"US",
    "sg:address":"6041 SE Earp Rd",
    "sg:city":"Belleview",
    "sg:classifiers":[
        {
            "category":"Professional",
            "subcategory":"Management & Consulting",
            "type":"Services"
        }
    ],
    "sg:phone":"+1 352 347 1165",
    "sg:postcode":"34420",
    "sg:province":"FL",
    "sg:tags":[
        "consultant",
        "business"
    ],
    "wof:name":"Wallace Manufacturing",
    "wof:placetype":"venue"
},
  "geometry": {"coordinates":[-82.050522,29.06179],"type":"Point"}
}