{
  "type": "Feature",
  "properties": {
    "iso:country":"US",
    "sg:address":"1899 State Rd 44",
    "sg:city":"New Smyrna Beach",
    "sg:classifiers":[
        {
            "category":"Autos & Motor Vehicles",
            "subcategory":"Motorcycle Sales",
            "type":"Retail Goods"
        }
    ],
    "sg:phone":"+1 386 409 3034",
    "sg:postcode":"32168",
    "sg:province":"FL",
    "sg:tags":[
        "scooter"
    ],
    "wof:name":"New Smyrna Beach Harley",
    "wof:placetype":"venue"
},
  "geometry": {"coordinates":[-80.94478599999999,29.013861],"type":"Point"}
}