{
  "type": "Feature",
  "properties": {
    "iso:country":"US",
    "sg:address":"1422 US Hwy 19",
    "sg:city":"Holiday",
    "sg:classifiers":[
        {
            "category":"Building & Trades",
            "subcategory":"Landscaping Services",
            "type":"Services"
        }
    ],
    "sg:phone":"+1 727 938 0747",
    "sg:postcode":"34691",
    "sg:province":"FL",
    "wof:name":"First Choice Services",
    "wof:placetype":"venue"
},
  "geometry": {"coordinates":[-82.740533,28.178902],"type":"Point"}
}