{
  "type": "Feature",
  "properties": {
    "addr:full":"1925 Mizell Ave Winter Park FL 32792",
    "addr:housenumber":"1925",
    "addr:postcode":"32792",
    "addr:street":"Mizell Ave",
    "iso:country":"US",
    "sg:address":"1925 Mizell Ave",
    "sg:city":"Winter Park",
    "sg:classifiers":[
        {
            "category":"Health Services",
            "subcategory":"Optometrist",
            "type":"Services"
        }
    ],
    "sg:phone":"+1 407 629 6646",
    "sg:postcode":"32792",
    "sg:province":"FL",
    "sg:tags":[
        "ophthalmologist"
    ],
    "sg:website":"www.chriss.eyemd.org",
    "wof:name":"Truchelut Tracy A MD",
    "wof:placetype":"venue"
},
  "geometry": {"coordinates":[-81.32669799999999,28.596201],"type":"Point"}
}