{
  "type": "Feature",
  "properties": {
    "iso:country":"US",
    "sg:address":"100 S 10th St",
    "sg:city":"Haines City",
    "sg:classifiers":[
        {
            "category":"Insurance",
            "subcategory":"Insurance Agent",
            "type":"Services"
        }
    ],
    "sg:phone":"+1 863 422 2345",
    "sg:postcode":"33844",
    "sg:province":"FL",
    "sg:tags":[
        "agency"
    ],
    "wof:name":"Ewing Black Welder Duce Insur",
    "wof:placetype":"venue"
},
  "geometry": {"coordinates":[-81.623328,28.104405],"type":"Point"}
}