{
  "type": "Feature",
  "properties": {
    "iso:country":"US",
    "sg:address":"2609 65th St E",
    "sg:city":"Bradenton",
    "sg:classifiers":[
        {
            "category":"Recreation",
            "type":"Entertainment"
        }
    ],
    "sg:phone":"+1 941 747 7679",
    "sg:postcode":"34208",
    "sg:province":"FL",
    "wof:name":"Within Rach Indoor Clmbing Gym",
    "wof:placetype":"venue"
},
  "geometry": {"coordinates":[-82.480199,27.475406],"type":"Point"}
}