{
  "type": "Feature",
  "properties": {
    "addr:full":"9790 66th St N Pinellas Park FL 33782",
    "addr:housenumber":"9790",
    "addr:postcode":"33782",
    "addr:street":"66Th St N",
    "iso:country":"US",
    "sg:address":"9790 66th St N",
    "sg:city":"Pinellas Park",
    "sg:classifiers":[
        {
            "category":"Wholesale",
            "subcategory":"Motor Vehicles",
            "type":"Manufacturing & Wholesale Goods"
        }
    ],
    "sg:phone":"+1 727 546 2455",
    "sg:postcode":"33782",
    "sg:province":"FL",
    "wof:name":"AA Auto Brokers Pinellas Park",
    "wof:placetype":"venue"
},
  "geometry": {"coordinates":[-82.728915,27.860229],"type":"Point"}
}