{
  "type": "Feature",
  "properties": {
    "addr:full":"301 NW 9th St Miami FL 33136",
    "addr:housenumber":"301",
    "addr:postcode":"33136",
    "addr:street":"Nw 9Th St",
    "iso:country":"US",
    "sg:address":"301 NW 9th St",
    "sg:city":"Miami",
    "sg:classifiers":[
        {
            "category":"Place Of Worship",
            "subcategory":"Church",
            "type":"Public Place"
        },
        {
            "category":"Landmark",
            "subcategory":"Historic",
            "type":"Public Place"
        }
    ],
    "sg:phone":"+1 305 379 4147",
    "sg:postcode":"33136",
    "sg:province":"FL",
    "sg:tags":[
        "building",
        "historical"
    ],
    "wof:name":"Mount Zion Baptist Church",
    "wof:placetype":"venue"
},
  "geometry": {"coordinates":[-80.199699,25.782499],"type":"Point"}
}