{
  "type": "Feature",
  "properties": {
    "addr:full":"7225 Ridge Rd Port Richey FL 34668",
    "addr:housenumber":"7225",
    "addr:postcode":"34668",
    "addr:street":"Ridge Rd",
    "iso:country":"US",
    "sg:address":"7225 Ridge Rd",
    "sg:city":"Port Richey",
    "sg:classifiers":[
        {
            "category":"Banks & Credit Unions",
            "subcategory":"Bank",
            "type":"Services"
        }
    ],
    "sg:phone":"+1 727 847 1786",
    "sg:postcode":"34668",
    "sg:province":"FL",
    "sg:tags":[
        "federal"
    ],
    "wof:name":"Suncoast Schools Federal Cr Un",
    "wof:placetype":"venue"
},
  "geometry": {"coordinates":[-82.688242,28.280586],"type":"Point"}
}