{
  "type": "Feature",
  "properties": {
    "addr:full":"25000 Harborside Blvd Punta Gorda FL 33955",
    "addr:postcode":"25000;33955",
    "addr:street":"Harborside Blvd",
    "iso:country":"US",
    "sg:address":"25000 Harborside Blvd",
    "sg:city":"Punta Gorda",
    "sg:classifiers":[
        {
            "category":"Real Estate",
            "subcategory":"Real Estate Agent",
            "type":"Services"
        }
    ],
    "sg:phone":"+1 941 637 9884",
    "sg:postcode":"33955",
    "sg:province":"FL",
    "wof:name":"Coldwell Banker Residential",
    "wof:placetype":"venue"
},
  "geometry": {"coordinates":[-82.035658,26.786296],"type":"Point"}
}