{
  "type": "Feature",
  "properties": {
    "addr:full":"611 NW 60 St Gainesville FL 32607",
    "addr:housenumber":"611",
    "addr:postcode":"32607",
    "addr:street":"Nw 60 St",
    "iso:country":"US",
    "sg:address":"611 NW 60 St",
    "sg:city":"Gainesville",
    "sg:classifiers":[
        {
            "category":"Insurance",
            "subcategory":"Insurance Agent",
            "type":"Services"
        }
    ],
    "sg:phone":"+1 352 331 3000",
    "sg:postcode":"32607",
    "sg:province":"FL",
    "wof:name":"Wendy LA Pointe Insurance",
    "wof:placetype":"venue"
},
  "geometry": {"coordinates":[-82.406395,29.658244],"type":"Point"}
}