{
  "type": "Feature",
  "properties": {
    "addr:full":"5099 Industry Dr Melbourne FL 32940",
    "addr:housenumber":"5099",
    "addr:postcode":"32940",
    "addr:street":"Industry Dr",
    "iso:country":"US",
    "sg:address":"5099 Industry Dr",
    "sg:city":"Melbourne",
    "sg:classifiers":[
        {
            "category":"Building & Trades",
            "subcategory":"Electrical",
            "type":"Services"
        }
    ],
    "sg:phone":"+1 321 259 6902",
    "sg:postcode":"32940",
    "sg:province":"FL",
    "sg:tags":[
        "electric",
        "contractor"
    ],
    "wof:name":"Harding's Electric & AC",
    "wof:placetype":"venue"
},
  "geometry": {"coordinates":[-80.66381,28.19373],"type":"Point"}
}