{
  "type": "Feature",
  "properties": {
    "addr:full":"12067 Indian Rocks Rd Largo FL 33774",
    "addr:housenumber":"12067",
    "addr:postcode":"33774",
    "addr:street":"Indian Rocks Rd",
    "iso:country":"US",
    "sg:address":"12067 Indian Rocks Rd",
    "sg:city":"Largo",
    "sg:classifiers":[
        {
            "category":"Shopping",
            "subcategory":"Bicycles & Sporting Goods",
            "type":"Retail Goods"
        }
    ],
    "sg:phone":"+1 727 595 6235",
    "sg:postcode":"33774",
    "sg:province":"FL",
    "sg:tags":[
        "repair"
    ],
    "wof:name":"Marlowe S Bike Shop",
    "wof:placetype":"venue"
},
  "geometry": {"coordinates":[-82.832307,27.880906],"type":"Point"}
}