{
  "type": "Feature",
  "properties": {
    "addr:full":"3863 Kingston Oaks Cove Oviedo FL 32765",
    "addr:housenumber":"3863",
    "addr:postcode":"32765",
    "addr:street":"Kingston Oaks Cove",
    "iso:country":"US",
    "sg:address":"3863 Kingston Oaks Cove",
    "sg:city":"Oviedo",
    "sg:classifiers":[
        {
            "category":"Wholesale",
            "subcategory":"Electrical",
            "type":"Manufacturing & Wholesale Goods"
        }
    ],
    "sg:phone":"+1 407 971 8094",
    "sg:postcode":"32765",
    "sg:province":"FL",
    "sg:tags":[
        "parts",
        "electronic"
    ],
    "wof:name":"Diversified Electronics",
    "wof:placetype":"venue"
},
  "geometry": {"coordinates":[-81.21113699999999,28.614383],"type":"Point"}
}