{
  "type": "Feature",
  "properties": {
    "iso:country":"US",
    "sg:address":"6118 SW 32nd St",
    "sg:city":"Hollywood",
    "sg:classifiers":[
        {
            "category":"Building & Trades",
            "subcategory":"Construction",
            "type":"Services"
        }
    ],
    "sg:phone":"+1 954 987 7897",
    "sg:postcode":"33023",
    "sg:province":"FL",
    "sg:tags":[
        "carpentry",
        "contractor"
    ],
    "wof:name":"Lenny Mac Inc",
    "wof:placetype":"venue"
},
  "geometry": {"coordinates":[-80.210216,25.981775],"type":"Point"}
}