{
  "type": "Feature",
  "properties": {
    "iso:country":"US",
    "sg:address":"780 Rellim Ln",
    "sg:city":"Sarasota",
    "sg:classifiers":[
        {
            "category":"Building & Trades",
            "subcategory":"Construction",
            "type":"Services"
        }
    ],
    "sg:phone":"+1 941 371 2878",
    "sg:postcode":"34232",
    "sg:province":"FL",
    "sg:tags":[
        "contractor"
    ],
    "wof:name":"A Touch of Tile",
    "wof:placetype":"venue"
},
  "geometry": {"coordinates":[-82.460348,27.342045],"type":"Point"}
}