{
  "type": "Feature",
  "properties": {
    "iso:country":"US",
    "sg:address":"642 NW 3rd St",
    "sg:city":"Miami",
    "sg:classifiers":[
        {
            "category":"Real Estate",
            "subcategory":"Real Estate Operator",
            "type":"Services"
        }
    ],
    "sg:phone":"+1 305 548 4150",
    "sg:postcode":"33128",
    "sg:province":"FL",
    "sg:tags":[
        "boarding",
        "house",
        "lodging"
    ],
    "wof:name":"Spanish River Inn",
    "wof:placetype":"venue"
},
  "geometry": {"coordinates":[-80.205305,25.776708],"type":"Point"}
}