{
  "type": "Feature",
  "properties": {
    "addr:full":"698 NW 47th Ter Miami FL 33127",
    "addr:housenumber":"698",
    "addr:postcode":"33127",
    "addr:street":"Nw 47Th Ter",
    "iso:country":"US",
    "sg:address":"698 NW 47th Ter",
    "sg:city":"Miami",
    "sg:classifiers":[
        {
            "category":"Organizations",
            "subcategory":"Religious Organization",
            "type":"Services"
        }
    ],
    "sg:phone":"+1 305 751 5846",
    "sg:postcode":"33127",
    "sg:province":"FL",
    "wof:name":"Mt Sinai Baptist Church",
    "wof:placetype":"venue"
},
  "geometry": {"coordinates":[-80.20760300000001,25.819099],"type":"Point"}
}