{
  "type": "Feature",
  "properties": {
    "addr:full":"3401 SW 160th Ave Hollywood FL 33027",
    "addr:housenumber":"3401",
    "addr:postcode":"33027",
    "addr:street":"Sw 160Th Ave",
    "iso:country":"US",
    "sg:address":"3401 SW 160th Ave",
    "sg:city":"Hollywood",
    "sg:classifiers":[
        {
            "category":"Wholesale",
            "subcategory":"Toys & Hobbies",
            "type":"Manufacturing & Wholesale Goods"
        }
    ],
    "sg:phone":"+1 954 364 1360",
    "sg:postcode":"33027",
    "sg:province":"FL",
    "wof:name":"Mattel Inc Latin America",
    "wof:placetype":"venue"
},
  "geometry": {"coordinates":[-80.359382,25.968449],"type":"Point"}
}