{
  "type": "Feature",
  "properties": {
    "addr:full":"7515 Ilex Dr Port Richey FL 34668",
    "addr:housenumber":"7515",
    "addr:postcode":"34668",
    "addr:street":"Ilex Dr",
    "iso:country":"US",
    "sg:address":"7515 Ilex Dr",
    "sg:city":"Port Richey",
    "sg:classifiers":[
        {
            "category":"Building & Trades",
            "subcategory":"Landscaping Services",
            "type":"Services"
        }
    ],
    "sg:phone":"+1 727 819 1174",
    "sg:postcode":"34668",
    "sg:province":"FL",
    "sg:tags":[
        "landscape",
        "contractor"
    ],
    "wof:name":"All Turf Lawn & Landscape",
    "wof:placetype":"venue"
},
  "geometry": {"coordinates":[-82.69041,28.318498],"type":"Point"}
}