{
  "type": "Feature",
  "properties": {
    "iso:country":"US",
    "sg:address":"1907 E 7th Ave",
    "sg:city":"Tampa",
    "sg:classifiers":[
        {
            "category":"Shopping",
            "type":"Retail Goods"
        }
    ],
    "sg:phone":"+1 813 247 2000",
    "sg:postcode":"33605",
    "sg:province":"FL",
    "sg:tags":[
        "art",
        "gallery",
        "dealer"
    ],
    "wof:name":"Hoffman Porges Gallery",
    "wof:placetype":"venue"
},
  "geometry": {"coordinates":[-82.43681599999999,27.960176],"type":"Point"}
}