{
  "type": "Feature",
  "properties": {
    "addr:full":"212 W Marion Ave Punta Gorda FL 33950",
    "addr:housenumber":"212",
    "addr:postcode":"33950",
    "addr:street":"W Marion Ave",
    "iso:country":"US",
    "sg:address":"212 W Marion Ave",
    "sg:city":"Punta Gorda",
    "sg:classifiers":[
        {
            "category":"Shopping",
            "subcategory":"Florist",
            "type":"Retail Goods"
        }
    ],
    "sg:phone":"+1 941 639 3944",
    "sg:postcode":"33950",
    "sg:province":"FL",
    "sg:tags":[
        "shop"
    ],
    "wof:name":"Blossom Shop The",
    "wof:placetype":"venue"
},
  "geometry": {"coordinates":[-82.051356,26.935192],"type":"Point"}
}