{
  "type": "Feature",
  "properties": {
    "iso:country":"US",
    "sg:address":"12120 NW 10th St",
    "sg:city":"Pompano Beach",
    "sg:classifiers":[
        {
            "category":"Wholesale",
            "subcategory":"Non-durable Goods",
            "type":"Manufacturing & Wholesale Goods"
        }
    ],
    "sg:phone":"+1 954 345 2808",
    "sg:postcode":"33071",
    "sg:province":"FL",
    "sg:tags":[
        "merchandise",
        "general"
    ],
    "wof:name":"Gss",
    "wof:placetype":"venue"
},
  "geometry": {"coordinates":[-80.288083,26.243466],"type":"Point"}
}