{
  "type": "Feature",
  "properties": {
    "iso:country":"US",
    "sg:address":"7820 Peters Rd",
    "sg:city":"Fort Lauderdale",
    "sg:classifiers":[
        {
            "category":"Professional",
            "subcategory":"Accounting & Tax Preparation",
            "type":"Services"
        }
    ],
    "sg:phone":"+1 954 452 5151",
    "sg:postcode":"33317",
    "sg:province":"FL",
    "sg:tags":[
        "firm"
    ],
    "wof:name":"M and M Financial Advisors",
    "wof:placetype":"venue"
},
  "geometry": {"coordinates":[-80.253276,26.105308],"type":"Point"}
}