{
  "type": "Feature",
  "properties": {
    "iso:country":"US",
    "sg:address":"33626 Verda Ave",
    "sg:city":"Leesburg",
    "sg:classifiers":[
        {
            "category":"Building & Trades",
            "subcategory":"Construction",
            "type":"Services"
        }
    ],
    "sg:phone":"+1 352 343 6810",
    "sg:postcode":"34788",
    "sg:province":"FL",
    "sg:tags":[
        "handyman"
    ],
    "wof:name":"Terri Davis Handyman",
    "wof:placetype":"venue"
},
  "geometry": {"coordinates":[-81.768422,28.839813],"type":"Point"}
}