{
  "type": "Feature",
  "properties": {
    "iso:country":"US",
    "sg:address":"3221 NE 9th Ter",
    "sg:city":"Pompano Beach",
    "sg:classifiers":[
        {
            "category":"Building & Trades",
            "subcategory":"Construction",
            "type":"Services"
        }
    ],
    "sg:phone":"+1 954 786 5280",
    "sg:postcode":"33064",
    "sg:province":"FL",
    "sg:tags":[
        "hanging",
        "contractor"
    ],
    "wof:name":"Brasmerica Painting Inc",
    "wof:placetype":"venue"
},
  "geometry": {"coordinates":[-80.11018300000001,26.269049],"type":"Point"}
}