{
  "type": "Feature",
  "properties": {
    "iso:country":"US",
    "sg:address":"340 N Cswy",
    "sg:city":"New Smyrna Beach",
    "sg:classifiers":[
        {
            "category":"Professional",
            "subcategory":"Lawyer & Legal Services",
            "type":"Services"
        }
    ],
    "sg:phone":"+1 386 428 3311",
    "sg:postcode":"32169",
    "sg:province":"FL",
    "sg:tags":[
        "attorney"
    ],
    "wof:name":"Thomas D Wright",
    "wof:placetype":"venue"
},
  "geometry": {"coordinates":[-80.91238800000001,29.035351],"type":"Point"}
}