{
  "type": "Feature",
  "properties": {
    "addr:full":"4370 NW 68th St Pompano Beach FL 33073",
    "addr:housenumber":"4370",
    "addr:postcode":"33073",
    "addr:street":"Nw 68Th St",
    "iso:country":"US",
    "sg:address":"4370 NW 68th St",
    "sg:city":"Pompano Beach",
    "sg:classifiers":[
        {
            "category":"Shopping",
            "subcategory":"Hobbies, Toys, & Games",
            "type":"Retail Goods"
        }
    ],
    "sg:phone":"+1 954 426 3626",
    "sg:postcode":"33073",
    "sg:province":"FL",
    "sg:tags":[
        "model"
    ],
    "wof:name":"Minature Dream Models Inc",
    "wof:placetype":"venue"
},
  "geometry": {"coordinates":[-80.18458,26.314003],"type":"Point"}
}