{
  "type": "Feature",
  "properties": {
    "addr:full":"2015 E Main St Lakeland FL 33801",
    "addr:housenumber":"2015",
    "addr:postcode":"33801",
    "addr:street":"E Main St",
    "iso:country":"US",
    "sg:address":"2015 E Main St",
    "sg:city":"Lakeland",
    "sg:classifiers":[
        {
            "category":"Social Services",
            "subcategory":"Child Care",
            "type":"Services"
        }
    ],
    "sg:phone":"+1 863 510 0606",
    "sg:postcode":"33801",
    "sg:province":"FL",
    "wof:name":"Big Wheels Child Care",
    "wof:placetype":"venue"
},
  "geometry": {"coordinates":[-81.924289,28.045913],"type":"Point"}
}