{
  "type": "Feature",
  "properties": {
    "iso:country":"US",
    "sg:address":"1951 Royal Fern Dr",
    "sg:city":"Wellington",
    "sg:classifiers":[
        {
            "category":"Education",
            "subcategory":"Library",
            "type":"Public Place"
        }
    ],
    "sg:phone":"+1 561 790 6070",
    "sg:postcode":"33414",
    "sg:province":"FL",
    "sg:website":"http://www.pbcountyclerk.com",
    "wof:name":"Wellington Branch Library",
    "wof:placetype":"venue"
},
  "geometry": {"coordinates":[-80.224739,26.652151],"type":"Point"}
}