{
  "type": "Feature",
  "properties": {
    "iso:country":"US",
    "sg:address":"4868 Whistler Dr",
    "sg:city":"Orlando",
    "sg:classifiers":[
        {
            "category":"Building & Trades",
            "subcategory":"Landscaping Services",
            "type":"Services"
        }
    ],
    "sg:phone":"+1 321 228 7399",
    "sg:postcode":"32812",
    "sg:province":"FL",
    "sg:tags":[
        "tree",
        "arborist",
        "stump",
        "grinding",
        "removal"
    ],
    "wof:name":"Davidsons Environmental",
    "wof:placetype":"venue"
},
  "geometry": {"coordinates":[-81.326082,28.505552],"type":"Point"}
}