{
  "type": "Feature",
  "properties": {
    "iso:country":"US",
    "sg:address":"1328 SW 5th St",
    "sg:city":"Miami",
    "sg:classifiers":[
        {
            "category":"Personal",
            "subcategory":"Beauty Salon",
            "type":"Services"
        }
    ],
    "sg:phone":"+1 305 631 0131",
    "sg:postcode":"33135",
    "sg:province":"FL",
    "sg:tags":[
        "hair"
    ],
    "wof:name":"Kuky Estillo Barber Shop 1",
    "wof:placetype":"venue"
},
  "geometry": {"coordinates":[-80.216662,25.768466],"type":"Point"}
}