{
  "type": "Feature",
  "properties": {
    "addr:full":"515 N Dollins Ave Orlando FL 32805",
    "addr:housenumber":"515",
    "addr:postcode":"32805",
    "addr:street":"N Dollins Ave",
    "iso:country":"US",
    "sg:address":"515 N Dollins Ave",
    "sg:city":"Orlando",
    "sg:classifiers":[
        {
            "category":"Building & Trades",
            "subcategory":"Construction",
            "type":"Services"
        }
    ],
    "sg:phone":"+1 407 481 2529",
    "sg:postcode":"32805",
    "sg:province":"FL",
    "sg:tags":[
        "contractor"
    ],
    "wof:name":"Raymond Pittman Inc",
    "wof:placetype":"venue"
},
  "geometry": {"coordinates":[-81.407338,28.551133],"type":"Point"}
}