{
  "type": "Feature",
  "properties": {
    "iso:country":"US",
    "sg:address":"10591 SW 56th Ter",
    "sg:city":"Miami",
    "sg:classifiers":[
        {
            "category":"Banks & Credit Unions",
            "subcategory":"Financial Services",
            "type":"Services"
        }
    ],
    "sg:phone":"+1 305 275 6066",
    "sg:postcode":"33173",
    "sg:province":"FL",
    "sg:tags":[
        "investor"
    ],
    "wof:name":"Multi World Investments Inc",
    "wof:placetype":"venue"
},
  "geometry": {"coordinates":[-80.365106,25.715084],"type":"Point"}
}