{
  "type": "Feature",
  "properties": {
    "iso:country":"US",
    "sg:address":"12002 US Hwy 41",
    "sg:city":"Gibsonton",
    "sg:classifiers":[
        {
            "category":"Recreation",
            "type":"Entertainment"
        }
    ],
    "sg:phone":"+1 813 741 3448",
    "sg:postcode":"33534",
    "sg:province":"FL",
    "sg:tags":[
        "aquarium"
    ],
    "wof:name":"Aquatic Sensation",
    "wof:placetype":"venue"
},
  "geometry": {"coordinates":[-82.381871,27.824531],"type":"Point"}
}