{
  "type": "Feature",
  "properties": {
    "iso:country":"US",
    "sg:address":"8530 Amber Oak Dr",
    "sg:city":"Orlando",
    "sg:classifiers":[
        {
            "category":"Education",
            "subcategory":"Special Training",
            "type":"Public Place"
        }
    ],
    "sg:phone":"+1 407 679 7280",
    "sg:postcode":"32817",
    "sg:province":"FL",
    "sg:tags":[
        "management"
    ],
    "sg:website":"www.listeningleader.com",
    "wof:name":"Leadership & Listening",
    "wof:placetype":"venue"
},
  "geometry": {"coordinates":[-81.27011299999999,28.605059],"type":"Point"}
}