{
  "type": "Feature",
  "properties": {
    "addr:full":"1901 S Congress Ave Boynton Beach FL 33426",
    "addr:housenumber":"1901",
    "addr:postcode":"33426",
    "addr:street":"S Congress Ave",
    "iso:country":"US",
    "sg:address":"1901 S Congress Ave",
    "sg:city":"Boynton Beach",
    "sg:classifiers":[
        {
            "category":"Banks & Credit Unions",
            "subcategory":"Bank",
            "type":"Services"
        }
    ],
    "sg:phone":"+1 561 369 8889",
    "sg:postcode":"33426",
    "sg:province":"FL",
    "sg:tags":[
        "financing"
    ],
    "wof:name":"Bibby Financial Svc",
    "wof:placetype":"venue"
},
  "geometry": {"coordinates":[-80.090104,26.506681],"type":"Point"}
}