{
  "type": "Feature",
  "properties": {
    "addr:full":"7300 Manatee Ave W Bradenton FL 34209",
    "addr:housenumber":"7300",
    "addr:postcode":"34209",
    "addr:street":"Manatee Ave W",
    "iso:country":"US",
    "sg:address":"7300 Manatee Ave W",
    "sg:city":"Bradenton",
    "sg:classifiers":[
        {
            "category":"Shopping",
            "subcategory":"Department Store",
            "type":"Retail Goods"
        }
    ],
    "sg:phone":"+1 941 794 0981",
    "sg:postcode":"34209",
    "sg:province":"FL",
    "sg:tags":[
        "shop"
    ],
    "wof:name":"Beall's Outlet",
    "wof:placetype":"venue"
},
  "geometry": {"coordinates":[-82.635418,27.496143],"type":"Point"}
}