{
  "type": "Feature",
  "properties": {
    "iso:country":"US",
    "sg:address":"2486 Running Oak Ct",
    "sg:city":"Spring Hill",
    "sg:classifiers":[
        {
            "category":"Professional",
            "type":"Services"
        }
    ],
    "sg:phone":"+1 352 683 8081",
    "sg:postcode":"34608",
    "sg:province":"FL",
    "wof:name":"Ann Elona Inc",
    "wof:placetype":"venue"
},
  "geometry": {"coordinates":[-82.56023500000001,28.476197],"type":"Point"}
}