{
  "type": "Feature",
  "properties": {
    "addr:full":"9201 W Sample Rd Coral Springs FL 33065",
    "addr:housenumber":"9201",
    "addr:postcode":"33065",
    "addr:street":"W Sample Rd",
    "iso:country":"US",
    "sg:address":"9201 W Sample Rd",
    "sg:city":"Coral Springs",
    "sg:classifiers":[
        {
            "category":"Utilities",
            "subcategory":"Mobile Phone",
            "type":"Services"
        }
    ],
    "sg:phone":"+1 954 753 4114",
    "sg:postcode":"33065",
    "sg:province":"FL",
    "sg:tags":[
        "telephone",
        "cellular"
    ],
    "wof:name":"Cingular Wireless",
    "wof:placetype":"venue"
},
  "geometry": {"coordinates":[-80.24923699999999,26.272518],"type":"Point"}
}