{
  "type": "Feature",
  "properties": {
    "iso:country":"US",
    "sg:address":"13616 SW 142nd Ave",
    "sg:city":"Miami",
    "sg:classifiers":[
        {
            "category":"Wholesale",
            "subcategory":"Jewelry",
            "type":"Manufacturing & Wholesale Goods"
        }
    ],
    "sg:phone":"+1 305 971 4110",
    "sg:postcode":"33186",
    "sg:province":"FL",
    "sg:tags":[
        "jeweler"
    ],
    "wof:name":"Mirevi Jewelry",
    "wof:placetype":"venue"
},
  "geometry": {"coordinates":[-80.42297600000001,25.637422],"type":"Point"}
}