{
  "type": "Feature",
  "properties": {
    "iso:country":"US",
    "sg:address":"2356 NW 7th St",
    "sg:city":"Miami",
    "sg:classifiers":[
        {
            "category":"Shopping",
            "subcategory":"Pharmacy",
            "type":"Retail Goods"
        }
    ],
    "sg:phone":"+1 305 643 4722",
    "sg:postcode":"33125",
    "sg:province":"FL",
    "sg:tags":[
        "drugstore"
    ],
    "wof:name":"V H Pharmacy",
    "wof:placetype":"venue"
},
  "geometry": {"coordinates":[-80.234703,25.779699],"type":"Point"}
}