{
  "type": "Feature",
  "properties": {
    "iso:country":"US",
    "sg:address":"12565 Research Pkwy",
    "sg:city":"Orlando",
    "sg:classifiers":[
        {
            "category":"Professional",
            "type":"Services"
        }
    ],
    "sg:phone":"+1 407 277 5411",
    "sg:postcode":"32826",
    "sg:province":"FL",
    "sg:tags":[
        "establishment"
    ],
    "sg:website":"www.cfic.org",
    "wof:name":"Central Florida Innovation",
    "wof:placetype":"venue"
},
  "geometry": {"coordinates":[-81.19596300000001,28.58742],"type":"Point"}
}