{
  "type": "Feature",
  "properties": {
    "iso:country":"US",
    "sg:address":"795 Apollo Cir NE",
    "sg:city":"Palm Bay",
    "sg:classifiers":[
        {
            "category":"Health Services",
            "subcategory":"Chiropractor",
            "type":"Services"
        }
    ],
    "sg:phone":"+1 321 733 3756",
    "sg:postcode":"32905",
    "sg:province":"FL",
    "wof:name":"Hodal Family Chiropractic",
    "wof:placetype":"venue"
},
  "geometry": {"coordinates":[-80.591583,28.015228],"type":"Point"}
}