{
  "type": "Feature",
  "properties": {
    "iso:country":"US",
    "sg:address":"301 Buenaventura Blvd",
    "sg:city":"Kissimmee",
    "sg:classifiers":[
        {
            "category":"Sports & Exercise",
            "subcategory":"Golf",
            "type":"Entertainment"
        }
    ],
    "sg:phone":"+1 407 348 9555",
    "sg:postcode":"34743",
    "sg:province":"FL",
    "sg:tags":[
        "course"
    ],
    "wof:name":"Walk-In Sticks Golf Club",
    "wof:placetype":"venue"
},
  "geometry": {"coordinates":[-81.34858699999999,28.325737],"type":"Point"}
}