{
  "type": "Feature",
  "properties": {
    "iso:country":"US",
    "sg:address":"44 NE 16th St",
    "sg:city":"Homestead",
    "sg:classifiers":[
        {
            "category":"Professional",
            "subcategory":"Computer Services",
            "type":"Services"
        }
    ],
    "sg:phone":"+1 305 247 2227",
    "sg:postcode":"33030",
    "sg:province":"FL",
    "sg:tags":[
        "datum"
    ],
    "wof:name":"Saint Aubin Technologies Inc",
    "wof:placetype":"venue"
},
  "geometry": {"coordinates":[-80.476803,25.485304],"type":"Point"}
}