{
  "type": "Feature",
  "properties": {
    "iso:country":"US",
    "sg:address":"1831 Azalea Ave",
    "sg:city":"Winter Park",
    "sg:classifiers":[
        {
            "category":"Building & Trades",
            "subcategory":"Construction",
            "type":"Services"
        }
    ],
    "sg:phone":"+1 407 628 8029",
    "sg:postcode":"32789",
    "sg:province":"FL",
    "sg:tags":[
        "contractor"
    ],
    "wof:name":"Florida Builders Network",
    "wof:placetype":"venue"
},
  "geometry": {"coordinates":[-81.3293,28.6231],"type":"Point"}
}