{
  "type": "Feature",
  "properties": {
    "iso:country":"US",
    "sg:address":"500 E Airport Blvd",
    "sg:city":"Sanford",
    "sg:classifiers":[
        {
            "category":"Retail",
            "subcategory":"Funeral Services",
            "type":"Services"
        }
    ],
    "sg:phone":"+1 407 322 3213",
    "sg:postcode":"32773",
    "sg:province":"FL",
    "sg:tags":[
        "director"
    ],
    "wof:name":"Gramkow Funeral Home",
    "wof:placetype":"venue"
},
  "geometry": {"coordinates":[-81.27310199999999,28.770192],"type":"Point"}
}