{
  "type": "Feature",
  "properties": {
    "addr:full":"3701 N University Dr Pompano Beach FL 33065",
    "addr:housenumber":"3701",
    "addr:postcode":"33065",
    "addr:street":"N University Dr",
    "iso:country":"US",
    "sg:address":"3701 N University Dr",
    "sg:city":"Pompano Beach",
    "sg:classifiers":[
        {
            "category":"Retail",
            "subcategory":"Auto Rental",
            "type":"Services"
        }
    ],
    "sg:phone":"+1 954 345 6225",
    "sg:postcode":"33065",
    "sg:province":"FL",
    "sg:tags":[
        "passenger",
        "car"
    ],
    "wof:name":"Marlin Rent A Car",
    "wof:placetype":"venue"
},
  "geometry": {"coordinates":[-80.25021,26.276108],"type":"Point"}
}