{
  "type": "Feature",
  "properties": {
    "iso:country":"US",
    "sg:address":"10730 SW 190th St",
    "sg:city":"Miami",
    "sg:classifiers":[
        {
            "category":"Manufacturing",
            "subcategory":"Furniture",
            "type":"Manufacturing & Wholesale Goods"
        },
        {
            "category":"Building & Trades",
            "subcategory":"Construction",
            "type":"Services"
        }
    ],
    "sg:phone":"+1 305 256 7267",
    "sg:postcode":"33157",
    "sg:province":"FL",
    "sg:tags":[
        "upholstered",
        "household",
        "mfg",
        "woodworker"
    ],
    "wof:name":"Biscayne Woodworks Inc",
    "wof:placetype":"venue"
},
  "geometry": {"coordinates":[-80.365459,25.590633],"type":"Point"}
}