{
  "type": "Feature",
  "properties": {
    "iso:country":"US",
    "sg:address":"856 Wren Rd",
    "sg:city":"Jacksonville",
    "sg:classifiers":[
        {
            "category":"Building & Trades",
            "subcategory":"Construction",
            "type":"Services"
        }
    ],
    "sg:phone":"+1 904 725 4084",
    "sg:postcode":"32216",
    "sg:province":"FL",
    "sg:tags":[
        "concrete",
        "contractor"
    ],
    "wof:name":"D&B Concrete Pumping",
    "wof:placetype":"venue"
},
  "geometry": {"coordinates":[-81.593069,30.302489],"type":"Point"}
}