{
  "type": "Feature",
  "properties": {
    "iso:country":"US",
    "sg:address":"17450 SE 11th St",
    "sg:city":"Silver Springs",
    "sg:classifiers":[
        {
            "category":"Building & Trades",
            "subcategory":"Construction",
            "type":"Services"
        }
    ],
    "sg:phone":"+1 352 625 1076",
    "sg:postcode":"34488",
    "sg:province":"FL",
    "sg:tags":[
        "contractor"
    ],
    "wof:name":"Grant M Hermening & Associates",
    "wof:placetype":"venue"
},
  "geometry": {"coordinates":[-81.863299,29.175779],"type":"Point"}
}