{
  "type": "Feature",
  "properties": {
    "addr:full":"6920 NW 84th Ave Miami FL 33166",
    "addr:housenumber":"6920",
    "addr:postcode":"33166",
    "addr:street":"Nw 84Th Ave",
    "iso:country":"US",
    "sg:address":"6920 NW 84th Ave",
    "sg:city":"Miami",
    "sg:classifiers":[
        {
            "category":"Wholesale",
            "subcategory":"Non-durable Goods",
            "type":"Manufacturing & Wholesale Goods"
        },
        {
            "category":"Wholesale",
            "subcategory":"Groceries",
            "type":"Manufacturing & Wholesale Goods"
        }
    ],
    "sg:phone":"+1 305 597 0640",
    "sg:postcode":"33166",
    "sg:province":"FL",
    "sg:tags":[
        "pet",
        "bird",
        "supply"
    ],
    "wof:name":"All Bird Supply Inc",
    "wof:placetype":"venue"
},
  "geometry": {"coordinates":[-80.33415100000001,25.835985],"type":"Point"}
}