{
  "type": "Feature",
  "properties": {
    "addr:full":"101 S McCall Rd Englewood FL 34223",
    "addr:housenumber":"101",
    "addr:postcode":"34223",
    "addr:street":"S Mccall Rd",
    "iso:country":"US",
    "sg:address":"101 S McCall Rd",
    "sg:city":"Englewood",
    "sg:classifiers":[
        {
            "category":"Manufacturing",
            "subcategory":"Apparel",
            "type":"Manufacturing & Wholesale Goods"
        }
    ],
    "sg:phone":"+1 941 474 0223",
    "sg:postcode":"34223",
    "sg:province":"FL",
    "sg:tags":[
        "awning",
        "mfg",
        "dist",
        "display",
        "sign"
    ],
    "sg:website":"www.millikenindustries.com",
    "wof:name":"Milliken Industries",
    "wof:placetype":"venue"
},
  "geometry": {"coordinates":[-82.35714900000001,26.959383],"type":"Point"}
}