{
  "type": "Feature",
  "properties": {
    "addr:full":"6119 Park Blvd Pinellas Park FL 33781",
    "addr:housenumber":"6119",
    "addr:postcode":"33781",
    "addr:street":"Park Blvd",
    "iso:country":"US",
    "sg:address":"6119 Park Blvd",
    "sg:city":"Pinellas Park",
    "sg:classifiers":[
        {
            "category":"Social Services",
            "type":"Services"
        }
    ],
    "sg:phone":"+1 727 549 9784",
    "sg:postcode":"33781",
    "sg:province":"FL",
    "wof:name":"Ancs Wic Store",
    "wof:placetype":"venue"
},
  "geometry": {"coordinates":[-82.719539,27.83925],"type":"Point"}
}