{
  "type": "Feature",
  "properties": {
    "iso:country":"US",
    "sg:address":"1820 E Johnson Ave",
    "sg:city":"Haines City",
    "sg:classifiers":[
        {
            "category":"Education",
            "subcategory":"School",
            "type":"Public Place"
        }
    ],
    "sg:phone":"+1 863 421 3254",
    "sg:postcode":"33844",
    "sg:province":"FL",
    "sg:tags":[
        "elementary"
    ],
    "wof:name":"Eastside Elementary School",
    "wof:placetype":"venue"
},
  "geometry": {"coordinates":[-81.61624999999999,28.114079],"type":"Point"}
}