{
  "type": "Feature",
  "properties": {
    "addr:full":"3200 N Andrews Ave Fort Lauderdale FL 33309",
    "addr:housenumber":"3200",
    "addr:postcode":"33309",
    "addr:street":"N Andrews Ave",
    "iso:country":"US",
    "sg:address":"3200 N Andrews Ave",
    "sg:city":"Fort Lauderdale",
    "sg:classifiers":[
        {
            "category":"Freight",
            "type":"Transportation"
        }
    ],
    "sg:phone":"+1 954 463 8400",
    "sg:postcode":"33309",
    "sg:province":"FL",
    "wof:name":"Medics Transport Service",
    "wof:placetype":"venue"
},
  "geometry": {"coordinates":[-80.14651499999999,26.168884],"type":"Point"}
}