{
  "type": "Feature",
  "properties": {
    "iso:country":"US",
    "sg:address":"257 Cownie Ave SE",
    "sg:city":"Palm Bay",
    "sg:classifiers":[
        {
            "category":"Building & Trades",
            "subcategory":"Construction",
            "type":"Services"
        }
    ],
    "sg:phone":"+1 321 676 0237",
    "sg:postcode":"32909",
    "sg:province":"FL",
    "sg:tags":[
        "painter"
    ],
    "wof:name":"R A Laudato Painting Contract",
    "wof:placetype":"venue"
},
  "geometry": {"coordinates":[-80.655187,27.995029],"type":"Point"}
}