{
  "type": "Feature",
  "properties": {
    "addr:full":"5900 State Hwy 70 Bradenton FL 34203",
    "addr:housenumber":"5900",
    "addr:postcode":"34203",
    "addr:street":"State Hwy 70",
    "iso:country":"US",
    "sg:address":"5900 State Hwy 70",
    "sg:city":"Bradenton",
    "sg:classifiers":[
        {
            "category":"Retail",
            "subcategory":"Auto Repair",
            "type":"Services"
        }
    ],
    "sg:phone":"+1 941 751 1818",
    "sg:postcode":"34203",
    "sg:province":"FL",
    "sg:tags":[
        "repairing",
        "automobile"
    ],
    "wof:name":"Tuffy Auto Svc Ctr",
    "wof:placetype":"venue"
},
  "geometry": {"coordinates":[-82.490668,27.446263],"type":"Point"}
}