{
  "type": "Feature",
  "properties": {
    "iso:country":"US",
    "sg:address":"4104 Ponce de Leon Blvd",
    "sg:city":"Coral Gables",
    "sg:classifiers":[
        {
            "category":"Shopping",
            "subcategory":"Musical Instruments",
            "type":"Retail Goods"
        }
    ],
    "sg:phone":"+1 305 774 5848",
    "sg:postcode":"33146",
    "sg:province":"FL",
    "sg:tags":[
        "piano"
    ],
    "wof:name":"Steinway & Sons",
    "wof:placetype":"venue"
},
  "geometry": {"coordinates":[-80.258599,25.734085],"type":"Point"}
}