{
  "type": "Feature",
  "properties": {
    "iso:country":"US",
    "sg:address":"9015 Fowler Ave",
    "sg:city":"Pensacola",
    "sg:classifiers":[
        {
            "category":"Autos & Motor Vehicles",
            "subcategory":"Automobile Sales",
            "type":"Retail Goods"
        }
    ],
    "sg:phone":"+1 850 857 1550",
    "sg:postcode":"32534",
    "sg:province":"FL",
    "sg:tags":[
        "car",
        "used"
    ],
    "wof:name":"Sunrise Wholesale",
    "wof:placetype":"venue"
},
  "geometry": {"coordinates":[-87.283857,30.528195],"type":"Point"}
}