{
  "type": "Feature",
  "properties": {
    "addr:full":"12140 Race Track Rd Tampa FL 33626",
    "addr:housenumber":"12140",
    "addr:postcode":"33626",
    "addr:street":"Race Track Rd",
    "iso:country":"US",
    "sg:address":"12140 Race Track Rd",
    "sg:city":"Tampa",
    "sg:classifiers":[
        {
            "category":"Building & Trades",
            "subcategory":"Construction",
            "type":"Services"
        }
    ],
    "sg:phone":"+1 813 891 0550",
    "sg:postcode":"33626",
    "sg:province":"FL",
    "sg:tags":[
        "contractor"
    ],
    "wof:name":"Pepper Contracting Svc",
    "wof:placetype":"venue"
},
  "geometry": {"coordinates":[-82.642967,28.061673],"type":"Point"}
}