{
  "type": "Feature",
  "properties": {
    "addr:full":"5355 E Colonial Dr Orlando FL 32807",
    "addr:housenumber":"5355",
    "addr:postcode":"32807",
    "addr:street":"E Colonial Dr",
    "iso:country":"US",
    "sg:address":"5355 E Colonial Dr",
    "sg:city":"Orlando",
    "sg:classifiers":[
        {
            "category":"Restaurant",
            "type":"Food & Drink"
        }
    ],
    "sg:menulink":"http://www.allmenus.com/fl/orlando/30268-hot-dog-heaven/menu/",
    "sg:phone":"+1 407 282 5746",
    "sg:postcode":"32807",
    "sg:province":"FL",
    "sg:tags":[
        "american"
    ],
    "wof:name":"Hot Dog Heaven",
    "wof:placetype":"venue"
},
  "geometry": {"coordinates":[-81.316078,28.554846],"type":"Point"}
}