{
  "type": "Feature",
  "properties": {
    "addr:full":"118 Miracle Strip Pkwy Fort Walton Beach FL 32548",
    "addr:housenumber":"118",
    "addr:postcode":"32548",
    "addr:street":"Miracle Strip Pkwy",
    "iso:country":"US",
    "sg:address":"118 Miracle Strip Pkwy",
    "sg:city":"Fort Walton Beach",
    "sg:classifiers":[
        {
            "category":"Shopping",
            "subcategory":"Clothing, Apparel, & Fashions",
            "type":"Retail Goods"
        }
    ],
    "sg:phone":"+1 850 244 4994",
    "sg:postcode":"32548",
    "sg:province":"FL",
    "wof:name":"Sun Fashion & Gifts",
    "wof:placetype":"venue"
},
  "geometry": {"coordinates":[-86.607378,30.403676],"type":"Point"}
}