{
  "type": "Feature",
  "properties": {
    "addr:full":"4141 NE 2nd Ave Ste 201 Miami FL 33137",
    "addr:housenumber":"4141",
    "addr:postcode":"33137",
    "addr:street":"Ne 2Nd Ave Ste 201",
    "iso:country":"US",
    "sg:address":"4141 NE 2nd Ave Ste 201",
    "sg:city":"Miami",
    "sg:classifiers":[
        {
            "category":"Professional",
            "subcategory":"Lawyer & Legal Services",
            "type":"Services"
        }
    ],
    "sg:phone":"+1 305 571 8550",
    "sg:postcode":"33137",
    "sg:province":"FL",
    "wof:name":"Alters Jeremy W",
    "wof:placetype":"venue"
},
  "geometry": {"coordinates":[-80.19126199999999,25.814638],"type":"Point"}
}