{
  "type": "Feature",
  "properties": {
    "addr:full":"2098 E Edgewood Dr Lakeland FL 33803",
    "addr:housenumber":"2098",
    "addr:postcode":"33803",
    "addr:street":"E Edgewood Dr",
    "iso:country":"US",
    "sg:address":"2098 E Edgewood Dr",
    "sg:city":"Lakeland",
    "sg:classifiers":[
        {
            "category":"Personal",
            "subcategory":"Beauty Salon",
            "type":"Services"
        }
    ],
    "sg:phone":"+1 863 665 3777",
    "sg:postcode":"33803",
    "sg:province":"FL",
    "wof:name":"Looksmart Family Hair Care",
    "wof:placetype":"venue"
},
  "geometry": {"coordinates":[-81.921297,28.013312],"type":"Point"}
}