{
  "type": "Feature",
  "properties": {
    "addr:full":"115 S Mercury Ave Clearwater FL 33765",
    "addr:housenumber":"115",
    "addr:postcode":"33765",
    "addr:street":"S Mercury Ave",
    "iso:country":"US",
    "sg:address":"115 S Mercury Ave",
    "sg:city":"Clearwater",
    "sg:classifiers":[
        {
            "category":"Health Services",
            "subcategory":"Clinic",
            "type":"Services"
        }
    ],
    "sg:phone":"+1 727 239 0571",
    "sg:postcode":"33765",
    "sg:province":"FL",
    "wof:name":"Clearwater Healthcare",
    "wof:placetype":"venue"
},
  "geometry": {"coordinates":[-82.751879,27.96379],"type":"Point"}
}