{
  "type": "Feature",
  "properties": {
    "addr:full":"1335 Twin Oaks Cir Oviedo FL 32765",
    "addr:housenumber":"1335",
    "addr:postcode":"32765",
    "addr:street":"Twin Oaks Cir",
    "iso:country":"US",
    "sg:address":"1335 Twin Oaks Cir",
    "sg:city":"Oviedo",
    "sg:classifiers":[
        {
            "category":"Health Services",
            "subcategory":"Doctor",
            "type":"Services"
        }
    ],
    "sg:phone":"+1 407 325 9384",
    "sg:postcode":"32765",
    "sg:province":"FL",
    "sg:tags":[
        "medical"
    ],
    "wof:name":"Halfway Medical",
    "wof:placetype":"venue"
},
  "geometry": {"coordinates":[-81.205634,28.687409],"type":"Point"}
}