{
  "type": "Feature",
  "properties": {
    "iso:country":"US",
    "sg:address":"16607 NW 73rd Ct",
    "sg:city":"Hialeah",
    "sg:classifiers":[
        {
            "category":"Travel",
            "subcategory":"Travel Agent",
            "type":"Entertainment"
        }
    ],
    "sg:phone":"+1 305 819 3959",
    "sg:postcode":"33014",
    "sg:province":"FL",
    "sg:tags":[
        "agency",
        "bureau"
    ],
    "wof:name":"Great Deals Travel",
    "wof:placetype":"venue"
},
  "geometry": {"coordinates":[-80.31992200000001,25.923915],"type":"Point"}
}