{
  "type": "Feature",
  "properties": {
    "iso:country":"US",
    "sg:address":"1288 N Tamiami Trl",
    "sg:city":"Fort Myers",
    "sg:classifiers":[
        {
            "category":"Shopping",
            "subcategory":"Used Merchandise",
            "type":"Retail Goods"
        }
    ],
    "sg:phone":"+1 239 652 0388",
    "sg:postcode":"33903",
    "sg:province":"FL",
    "sg:tags":[
        "shop",
        "thrift"
    ],
    "sg:website":"www.habitat4humanity.org",
    "wof:name":"Habitat For Humanity",
    "wof:placetype":"venue"
},
  "geometry": {"coordinates":[-81.880695,26.667752],"type":"Point"}
}