{
  "type": "Feature",
  "properties": {
    "addr:full":"1870 Grove Ct Kissimmee FL 34746",
    "addr:housenumber":"1870",
    "addr:postcode":"34746",
    "addr:street":"Grove Ct",
    "iso:country":"US",
    "sg:address":"1870 Grove Ct",
    "sg:city":"Kissimmee",
    "sg:classifiers":[
        {
            "category":"Real Estate",
            "subcategory":"Real Estate Agent",
            "type":"Services"
        }
    ],
    "sg:phone":"+1 407 931 1757",
    "sg:postcode":"34746",
    "sg:province":"FL",
    "sg:tags":[
        "inspection"
    ],
    "wof:name":"WHIT Mart Corp",
    "wof:placetype":"venue"
},
  "geometry": {"coordinates":[-81.445649,28.249499],"type":"Point"}
}