{
  "type": "Feature",
  "properties": {
    "addr:full":"3009 US Hwy 92 Winter Haven FL 33881",
    "addr:housenumber":"3009",
    "addr:postcode":"33881",
    "addr:street":"Us Hwy 92",
    "iso:country":"US",
    "sg:address":"3009 US Hwy 92",
    "sg:city":"Winter Haven",
    "sg:classifiers":[
        {
            "category":"Personal",
            "type":"Services"
        },
        {
            "category":"Personal",
            "subcategory":"Tattoo Parlor",
            "type":"Services"
        }
    ],
    "sg:phone":"+1 863 956 4668",
    "sg:postcode":"33881",
    "sg:province":"FL",
    "sg:tags":[
        "tattooing"
    ],
    "wof:name":"Ground Zero Tattoos",
    "wof:placetype":"venue"
},
  "geometry": {"coordinates":[-81.765424,28.064672],"type":"Point"}
}