{
  "type": "Feature",
  "properties": {
    "iso:country":"US",
    "sg:address":"104 E Nine Mile Rd",
    "sg:city":"Pensacola",
    "sg:classifiers":[
        {
            "category":"Professional",
            "subcategory":"Accounting & Tax Preparation",
            "type":"Services"
        }
    ],
    "sg:phone":"+1 850 292 2911",
    "sg:postcode":"32534",
    "sg:province":"FL",
    "sg:tags":[
        "bookkeeping",
        "general"
    ],
    "wof:name":"Donna The Title Specialists",
    "wof:placetype":"venue"
},
  "geometry": {"coordinates":[-87.269488,30.533269],"type":"Point"}
}