{
  "type": "Feature",
  "properties": {
    "iso:country":"US",
    "sg:address":"9134 Eden Ave",
    "sg:city":"Hudson",
    "sg:classifiers":[
        {
            "category":"Retail",
            "subcategory":"Auto Repair",
            "type":"Services"
        }
    ],
    "sg:phone":"+1 727 869 9577",
    "sg:postcode":"34667",
    "sg:province":"FL",
    "sg:tags":[
        "body",
        "automobile",
        "used",
        "restoration",
        "classic"
    ],
    "wof:name":"Time Machines Inc",
    "wof:placetype":"venue"
},
  "geometry": {"coordinates":[-82.664278,28.393258],"type":"Point"}
}