{
  "type": "Feature",
  "properties": {
    "addr:full":"6621 NW 84th Ave Miami FL 33166",
    "addr:housenumber":"6621",
    "addr:postcode":"33166",
    "addr:street":"Nw 84Th Ave",
    "iso:country":"US",
    "sg:address":"6621 NW 84th Ave",
    "sg:city":"Miami",
    "sg:classifiers":[
        {
            "category":"Professional",
            "subcategory":"Computer Services",
            "type":"Services"
        },
        {
            "category":"Shopping",
            "subcategory":"Computers & Home Electronics",
            "type":"Retail Goods"
        },
        {
            "category":"Wholesale",
            "subcategory":"Computers",
            "type":"Manufacturing & Wholesale Goods"
        }
    ],
    "sg:phone":"+1 305 463 9393",
    "sg:postcode":"33166",
    "sg:province":"FL",
    "sg:tags":[
        "supply",
        "hardware",
        "equipment",
        "computer-wholesale",
        "manufacturer",
        "software"
    ],
    "wof:name":"J & C Miami Trading Group",
    "wof:placetype":"venue"
},
  "geometry": {"coordinates":[-80.334014,25.833662],"type":"Point"}
}