{
  "type": "Feature",
  "properties": {
    "addr:full":"1 Wilderness Blvd Parrish FL 34219",
    "addr:housenumber":"1",
    "addr:postcode":"34219",
    "addr:street":"Wilderness Blvd",
    "iso:country":"US",
    "sg:address":"1 Wilderness Blvd",
    "sg:city":"Parrish",
    "sg:classifiers":[
        {
            "category":"Organizations",
            "subcategory":"Community Association",
            "type":"Services"
        }
    ],
    "sg:phone":"+1 941 776 1729",
    "sg:postcode":"34219",
    "sg:province":"FL",
    "sg:tags":[
        "club"
    ],
    "wof:name":"River Wilderness Golf & Countr",
    "wof:placetype":"venue"
},
  "geometry": {"coordinates":[-82.437015,27.548482],"type":"Point"}
}