{
  "type": "Feature",
  "properties": {
    "iso:country":"US",
    "sg:address":"1715 Woodridge Dr",
    "sg:city":"Clearwater",
    "sg:classifiers":[
        {
            "category":"Professional",
            "subcategory":"Engineering",
            "type":"Services"
        },
        {
            "category":"Real Estate",
            "subcategory":"Architect",
            "type":"Services"
        }
    ],
    "sg:phone":"+1 727 585 2446",
    "sg:postcode":"33756",
    "sg:province":"FL",
    "sg:tags":[
        "architects'",
        "consulting",
        "specification",
        "builders'",
        "construction",
        "architectural",
        "engineer"
    ],
    "wof:name":"Shelter Design & Planning",
    "wof:placetype":"venue"
},
  "geometry": {"coordinates":[-82.767053,27.934527],"type":"Point"}
}