{
  "type": "Feature",
  "properties": {
    "addr:full":"745 N Alafaya Trl Orlando FL 32828",
    "addr:housenumber":"745",
    "addr:postcode":"32828",
    "addr:street":"N Alafaya Trl",
    "iso:country":"US",
    "sg:address":"745 N Alafaya Trl",
    "sg:city":"Orlando",
    "sg:classifiers":[
        {
            "category":"Shopping",
            "subcategory":"Books",
            "type":"Retail Goods"
        }
    ],
    "sg:phone":"+1 407 482 9421",
    "sg:postcode":"32828",
    "sg:province":"FL",
    "sg:tags":[
        "dealer"
    ],
    "sg:website":"www.familychristian.com",
    "wof:name":"Family Christian Book Store",
    "wof:placetype":"venue"
},
  "geometry": {"coordinates":[-81.206211,28.554079],"type":"Point"}
}