{
  "type": "Feature",
  "properties": {
    "iso:country":"US",
    "sg:address":"2190 NW 95th St",
    "sg:city":"Miami",
    "sg:classifiers":[
        {
            "category":"Retail",
            "subcategory":"Car Wash",
            "type":"Services"
        }
    ],
    "sg:phone":"+1 305 333 1844",
    "sg:postcode":"33147",
    "sg:province":"FL",
    "sg:tags":[
        "carwash"
    ],
    "wof:name":"Clean & Correct",
    "wof:placetype":"venue"
},
  "geometry": {"coordinates":[-80.232388,25.860923],"type":"Point"}
}