{
  "type": "Feature",
  "properties": {
    "iso:country":"US",
    "sg:address":"3110 Ambassador Ave",
    "sg:city":"Spring Hill",
    "sg:classifiers":[
        {
            "category":"Autos & Motor Vehicles",
            "subcategory":"Auto Supplies",
            "type":"Retail Goods"
        }
    ],
    "sg:phone":"+1 352 688 8703",
    "sg:postcode":"34609",
    "sg:province":"FL",
    "wof:name":"Sic Sounds & Performance",
    "wof:placetype":"venue"
},
  "geometry": {"coordinates":[-82.49446399999999,28.477039],"type":"Point"}
}