{
  "type": "Feature",
  "properties": {
    "iso:country":"US",
    "sg:address":"2494 Blanding Blvd",
    "sg:city":"Middleburg",
    "sg:classifiers":[
        {
            "category":"Shopping",
            "subcategory":"Clothing, Apparel, & Fashions",
            "type":"Retail Goods"
        }
    ],
    "sg:phone":"+1 904 214 9112",
    "sg:postcode":"32068",
    "sg:province":"FL",
    "sg:tags":[
        "infant",
        "wear"
    ],
    "wof:name":"A 2nd Childhood",
    "wof:placetype":"venue"
},
  "geometry": {"coordinates":[-81.863505,30.07553],"type":"Point"}
}