{
  "type": "Feature",
  "properties": {
    "iso:country":"US",
    "sg:address":"60 McLeod St",
    "sg:city":"Merritt Island",
    "sg:classifiers":[
        {
            "category":"Communications",
            "type":"Services"
        }
    ],
    "sg:phone":"+1 321 259 0024",
    "sg:postcode":"32953",
    "sg:province":"FL",
    "sg:tags":[
        "web",
        "design"
    ],
    "sg:website":"www.brc60.com",
    "wof:name":"Brandt Ronat & Company",
    "wof:placetype":"venue"
},
  "geometry": {"coordinates":[-80.70103,28.357934],"type":"Point"}
}