{
  "type": "Feature",
  "properties": {
    "addr:full":"5174 NW 26 St Ocala FL 34482",
    "addr:housenumber":"5174",
    "addr:postcode":"34482",
    "addr:street":"Nw 26",
    "iso:country":"US",
    "sg:address":"5174 NW 26 St",
    "sg:city":"Ocala",
    "sg:classifiers":[
        {
            "category":"Sports & Exercise",
            "subcategory":"Golf",
            "type":"Entertainment"
        }
    ],
    "sg:phone":"+1 352 732 4653",
    "sg:postcode":"34482",
    "sg:province":"FL",
    "sg:tags":[
        "course"
    ],
    "wof:name":"Ocala Palms Golf Country Club",
    "wof:placetype":"venue"
},
  "geometry": {"coordinates":[-82.206209,29.212435],"type":"Point"}
}