{
  "type": "Feature",
  "properties": {
    "iso:country":"US",
    "sg:address":"15675 96th St N",
    "sg:city":"Jupiter",
    "sg:classifiers":[
        {
            "category":"Building & Trades",
            "subcategory":"Construction",
            "type":"Services"
        }
    ],
    "sg:phone":"+1 561 743 8453",
    "sg:postcode":"33478",
    "sg:province":"FL",
    "sg:tags":[
        "tile",
        "dealer"
    ],
    "wof:name":"Mcginness Tile & Marble",
    "wof:placetype":"venue"
},
  "geometry": {"coordinates":[-80.186086,26.908457],"type":"Point"}
}