{
  "type": "Feature",
  "properties": {
    "addr:full":"4916 Fleetwood St New Port Richey FL 34653",
    "addr:housenumber":"4916",
    "addr:postcode":"34653",
    "addr:street":"Fleetwood St",
    "iso:country":"US",
    "sg:address":"4916 Fleetwood St",
    "sg:city":"New Port Richey",
    "sg:classifiers":[
        {
            "category":"Organizations",
            "subcategory":"Religious Organization",
            "type":"Services"
        }
    ],
    "sg:phone":"+1 727 846 1024",
    "sg:postcode":"34653",
    "sg:province":"FL",
    "sg:tags":[
        "clergy"
    ],
    "wof:name":"Ellis E Bond",
    "wof:placetype":"venue"
},
  "geometry": {"coordinates":[-82.71149800000001,28.230915],"type":"Point"}
}