{
  "type": "Feature",
  "properties": {
    "addr:full":"323 E Kennedy Blvd Ste A Maitland FL 32751",
    "addr:housenumber":"323",
    "addr:postcode":"32751",
    "addr:street":"E Kennedy Blvd Ste A",
    "iso:country":"US",
    "sg:address":"323 E Kennedy Blvd Ste A",
    "sg:city":"Maitland",
    "sg:classifiers":[
        {
            "category":"Personal",
            "subcategory":"Beauty Salon",
            "type":"Services"
        }
    ],
    "sg:phone":"+1 407 645 1366",
    "sg:postcode":"32751",
    "sg:province":"FL",
    "wof:name":"Euro Design Of Central Florida Inc",
    "wof:placetype":"venue"
},
  "geometry": {"coordinates":[-81.380765,28.61846],"type":"Point"}
}