{
  "type": "Feature",
  "properties": {
    "addr:full":"3253 McDonald St Miami FL 33133",
    "addr:housenumber":"3253",
    "addr:postcode":"33133",
    "addr:street":"Mcdonald St",
    "iso:country":"US",
    "sg:address":"3253 McDonald St",
    "sg:city":"Miami",
    "sg:classifiers":[
        {
            "category":"Building & Trades",
            "subcategory":"Landscaping Services",
            "type":"Services"
        }
    ],
    "sg:phone":"+1 305 448 4768",
    "sg:postcode":"33133",
    "sg:province":"FL",
    "sg:tags":[
        "lawn",
        "maintenance",
        "grounds"
    ],
    "wof:name":"Grove Grass Inc",
    "wof:placetype":"venue"
},
  "geometry": {"coordinates":[-80.245515,25.730032],"type":"Point"}
}