{
  "type": "Feature",
  "properties": {
    "iso:country":"US",
    "sg:address":"1760 N Congress Ave",
    "sg:city":"Boynton Beach",
    "sg:classifiers":[
        {
            "category":"Real Estate",
            "subcategory":"Real Estate Agent",
            "type":"Services"
        }
    ],
    "sg:phone":"+1 561 738 2361",
    "sg:postcode":"33426",
    "sg:province":"FL",
    "wof:name":"Compson Associates",
    "wof:placetype":"venue"
},
  "geometry": {"coordinates":[-80.090639,26.546039],"type":"Point"}
}