{
  "type": "Feature",
  "properties": {
    "iso:country":"US",
    "sg:address":"1063 SW Blue Water Way",
    "sg:city":"Stuart",
    "sg:classifiers":[
        {
            "category":"Marine",
            "type":"Transportation"
        }
    ],
    "sg:phone":"+1 772 781 9068",
    "sg:postcode":"34997",
    "sg:province":"FL",
    "sg:tags":[
        "surveyor"
    ],
    "wof:name":"Birely Marine Surveying",
    "wof:placetype":"venue"
},
  "geometry": {"coordinates":[-80.26993,27.118629],"type":"Point"}
}