{
  "type": "Feature",
  "properties": {
    "addr:full":"3008 Kiwi Pl Ellenton FL 34222",
    "addr:housenumber":"3008",
    "addr:postcode":"34222",
    "addr:street":"Kiwi Pl",
    "iso:country":"US",
    "sg:address":"3008 Kiwi Pl",
    "sg:city":"Ellenton",
    "sg:classifiers":[
        {
            "category":"Organizations",
            "subcategory":"Community Association",
            "type":"Services"
        }
    ],
    "sg:phone":"+1 941 722 1124",
    "sg:postcode":"34222",
    "sg:province":"FL",
    "wof:name":"Order of Eastern Star of",
    "wof:placetype":"venue"
},
  "geometry": {"coordinates":[-82.497179,27.541414],"type":"Point"}
}