{
  "type": "Feature",
  "properties": {
    "addr:full":"6312 S 78th St Riverview FL 33569",
    "addr:housenumber":"6312",
    "addr:postcode":"33569",
    "addr:street":"S 78Th St",
    "iso:country":"US",
    "sg:address":"6312 S 78th St",
    "sg:city":"Riverview",
    "sg:classifiers":[
        {
            "category":"Manufacturing",
            "subcategory":"Electronics",
            "type":"Manufacturing & Wholesale Goods"
        }
    ],
    "sg:phone":"+1 813 671 2218",
    "sg:postcode":"33569",
    "sg:province":"FL",
    "wof:name":"Emerson Network Power",
    "wof:placetype":"venue"
},
  "geometry": {"coordinates":[-82.36893600000001,27.886059],"type":"Point"}
}