{
  "type": "Feature",
  "properties": {
    "iso:country":"US",
    "sg:address":"4078 S Ridgewood Ave",
    "sg:city":"Daytona Beach",
    "sg:classifiers":[
        {
            "category":"Personal",
            "subcategory":"Beauty Salon",
            "type":"Services"
        }
    ],
    "sg:phone":"+1 386 756 7765",
    "sg:postcode":"32127",
    "sg:province":"FL",
    "sg:tags":[
        "shop",
        "manicuring"
    ],
    "wof:name":"Lina's Nails",
    "wof:placetype":"venue"
},
  "geometry": {"coordinates":[-80.98688199999999,29.142224],"type":"Point"}
}