{
  "type": "Feature",
  "properties": {
    "addr:full":"7448 Lake Worth Rd Lake Worth FL 33467",
    "addr:housenumber":"7448",
    "addr:postcode":"33467",
    "addr:street":"Lake Worth Rd",
    "iso:country":"US",
    "sg:address":"7448 Lake Worth Rd",
    "sg:city":"Lake Worth",
    "sg:classifiers":[
        {
            "category":"Professional",
            "type":"Services"
        }
    ],
    "sg:phone":"+1 561 965 6610",
    "sg:postcode":"33467",
    "sg:province":"FL",
    "wof:name":"Sumar Inc",
    "wof:placetype":"venue"
},
  "geometry": {"coordinates":[-80.162491,26.617493],"type":"Point"}
}