{
  "type": "Feature",
  "properties": {
    "iso:country":"US",
    "sg:address":"2905 NW 9th St",
    "sg:city":"Miami",
    "sg:classifiers":[
        {
            "category":"Travel",
            "subcategory":"Travel Agent",
            "type":"Entertainment"
        }
    ],
    "sg:phone":"+1 305 649 2249",
    "sg:postcode":"33125",
    "sg:province":"FL",
    "sg:tags":[
        "agency"
    ],
    "wof:name":"Viaje Services USA",
    "wof:placetype":"venue"
},
  "geometry": {"coordinates":[-80.242474,25.781369],"type":"Point"}
}