{
  "type": "Feature",
  "properties": {
    "iso:country":"US",
    "sg:address":"8875 Orange Blossom Dr",
    "sg:city":"Seminole",
    "sg:classifiers":[
        {
            "category":"Wholesale",
            "subcategory":"Durable Goods & Equipment",
            "type":"Manufacturing & Wholesale Goods"
        }
    ],
    "sg:phone":"+1 727 399 8052",
    "sg:postcode":"33772",
    "sg:province":"FL",
    "sg:tags":[
        "professional"
    ],
    "wof:name":"David R Grove Inc",
    "wof:placetype":"venue"
},
  "geometry": {"coordinates":[-82.804012,27.850977],"type":"Point"}
}