{
  "type": "Feature",
  "properties": {
    "iso:country":"US",
    "sg:address":"2320 W Bay Dr",
    "sg:city":"Largo",
    "sg:classifiers":[
        {
            "category":"Health Services",
            "subcategory":"Doctor",
            "type":"Services"
        }
    ],
    "sg:phone":"+1 727 581 3726",
    "sg:postcode":"33770",
    "sg:province":"FL",
    "sg:tags":[
        "physician",
        "surgery",
        "oral",
        "dentist",
        "surgeons"
    ],
    "wof:name":"Terry L Hamblen Dmd",
    "wof:placetype":"venue"
},
  "geometry": {"coordinates":[-82.812225,27.916771],"type":"Point"}
}