{
  "type": "Feature",
  "properties": {
    "addr:full":"1130-D SW 8th St Miami FL 33125",
    "addr:housenumber":"1130-d",
    "addr:postcode":"33125",
    "addr:street":"Sw 8Th St",
    "iso:country":"US",
    "sg:address":"1130-D SW 8th St",
    "sg:city":"Miami",
    "sg:classifiers":[
        {
            "category":"Personal",
            "subcategory":"Barber",
            "type":"Services"
        }
    ],
    "sg:postcode":"33125",
    "sg:province":"FL",
    "wof:name":"La Esquina Barber Shop",
    "wof:placetype":"venue"
},
  "geometry": {"coordinates":[-80.213521,25.765618],"type":"Point"}
}