{
  "type": "Feature",
  "properties": {
    "iso:country":"US",
    "sg:address":"1515 Riverside Ave",
    "sg:city":"Jacksonville",
    "sg:classifiers":[
        {
            "category":"Professional",
            "subcategory":"Lawyer & Legal Services",
            "type":"Services"
        }
    ],
    "sg:phone":"+1 904 353 5616",
    "sg:postcode":"32204",
    "sg:province":"FL",
    "sg:tags":[
        "attorney"
    ],
    "wof:name":"Frazier & Frazier",
    "wof:placetype":"venue"
},
  "geometry": {"coordinates":[-81.678586,30.312433],"type":"Point"}
}