{
  "type": "Feature",
  "properties": {
    "addr:full":"1954 N Main St Gainesville FL 32609",
    "addr:housenumber":"1954",
    "addr:postcode":"32609",
    "addr:street":"N Main St",
    "iso:country":"US",
    "sg:address":"1954 N Main St",
    "sg:city":"Gainesville",
    "sg:classifiers":[
        {
            "category":"Retail",
            "subcategory":"Auto Repair",
            "type":"Services"
        }
    ],
    "sg:phone":"+1 352 377 5500",
    "sg:postcode":"32609",
    "sg:province":"FL",
    "sg:tags":[
        "glass",
        "coating",
        "tinting"
    ],
    "wof:name":"Premier Glass Tinting",
    "wof:placetype":"venue"
},
  "geometry": {"coordinates":[-82.323928,29.669739],"type":"Point"}
}