{
  "type": "Feature",
  "properties": {
    "iso:country":"US",
    "sg:address":"1708 Hermosa Cir",
    "sg:city":"Milton",
    "sg:phone":"+1 850 623 9639",
    "sg:postcode":"32583",
    "sg:province":"FL",
    "wof:name":"Kyser Siding & Construction Inc",
    "wof:placetype":"venue"
},
  "geometry": {"coordinates":[-87.05641199999999,30.496519],"type":"Point"}
}