{
  "type": "Feature",
  "properties": {
    "iso:country":"US",
    "sg:address":"262 Almeria Ave",
    "sg:city":"Coral Gables",
    "sg:classifiers":[
        {
            "category":"Building & Trades",
            "subcategory":"Construction",
            "type":"Services"
        }
    ],
    "sg:phone":"+1 305 445 0040",
    "sg:postcode":"33134",
    "sg:province":"FL",
    "sg:tags":[
        "interior",
        "design"
    ],
    "wof:name":"Ackermann Gail S Int Desingr",
    "wof:placetype":"venue"
},
  "geometry": {"coordinates":[-80.260201,25.747101],"type":"Point"}
}