{
  "type": "Feature",
  "properties": {
    "iso:country":"US",
    "sg:address":"1903 NW 29th St",
    "sg:city":"Fort Lauderdale",
    "sg:classifiers":[
        {
            "category":"Building & Trades",
            "subcategory":"Cleaning & Sanitation",
            "type":"Services"
        }
    ],
    "sg:phone":"+1 954 486 3880",
    "sg:postcode":"33311",
    "sg:province":"FL",
    "sg:tags":[
        "maintenance"
    ],
    "wof:name":"Dry Mist",
    "wof:placetype":"venue"
},
  "geometry": {"coordinates":[-80.168747,26.1626],"type":"Point"}
}