{
  "type": "Feature",
  "properties": {
    "addr:full":"1520 S Highland Ave Clearwater FL 33756",
    "addr:housenumber":"1520",
    "addr:postcode":"33756",
    "addr:street":"S Highland Ave",
    "iso:country":"US",
    "sg:address":"1520 S Highland Ave",
    "sg:city":"Clearwater",
    "sg:classifiers":[
        {
            "category":"Building & Trades",
            "subcategory":"Plumbing",
            "type":"Services"
        }
    ],
    "sg:phone":"+1 727 449 2699",
    "sg:postcode":"33756",
    "sg:province":"FL",
    "sg:tags":[
        "conditioning",
        "contractor",
        "system",
        "air"
    ],
    "wof:name":"Air Care Heating & Air Cond",
    "wof:placetype":"venue"
},
  "geometry": {"coordinates":[-82.77509999999999,27.940296],"type":"Point"}
}