{
  "type": "Feature",
  "properties": {
    "iso:country":"US",
    "sg:address":"28878 Marsh Elder Ct",
    "sg:city":"Bonita Springs",
    "sg:classifiers":[
        {
            "category":"Health Services",
            "subcategory":"Doctor",
            "type":"Services"
        }
    ],
    "sg:phone":"+1 239 992 2011",
    "sg:postcode":"34135",
    "sg:province":"FL",
    "sg:tags":[
        "dentist"
    ],
    "wof:name":"R E Grant DDS",
    "wof:placetype":"venue"
},
  "geometry": {"coordinates":[-81.74530300000001,26.319413],"type":"Point"}
}