{
  "type": "Feature",
  "properties": {
    "iso:country":"US",
    "sg:address":"20450 NW 2nd Ct",
    "sg:city":"Miami",
    "sg:classifiers":[
        {
            "category":"Building & Trades",
            "subcategory":"Construction",
            "type":"Services"
        }
    ],
    "sg:phone":"+1 305 651 4841",
    "sg:postcode":"33169",
    "sg:province":"FL",
    "sg:tags":[
        "nonresidential",
        "contractor"
    ],
    "wof:name":"Williams & Williams Assoc Inc",
    "wof:placetype":"venue"
},
  "geometry": {"coordinates":[-80.207037,25.965508],"type":"Point"}
}