{
  "type": "Feature",
  "properties": {
    "iso:country":"US",
    "sg:address":"9031 9th St N",
    "sg:city":"St Petersburg",
    "sg:classifiers":[
        {
            "category":"Restaurant",
            "type":"Food & Drink"
        }
    ],
    "sg:phone":"+1 727 578 8848",
    "sg:postcode":"33702",
    "sg:province":"FL",
    "sg:tags":[
        "shop",
        "coffee"
    ],
    "wof:name":"Blue Lagoon",
    "wof:placetype":"venue"
},
  "geometry": {"coordinates":[-82.64689,27.854951],"type":"Point"}
}