{
  "type": "Feature",
  "properties": {
    "addr:full":"3125 SE Creekwood Ter Arcadia FL 34266",
    "addr:housenumber":"3125",
    "addr:postcode":"34266",
    "addr:street":"Se Creekwood Ter",
    "iso:country":"US",
    "sg:address":"3125 SE Creekwood Ter",
    "sg:city":"Arcadia",
    "sg:classifiers":[
        {
            "category":"Building & Trades",
            "subcategory":"Construction",
            "type":"Services"
        }
    ],
    "sg:phone":"+1 863 491 0909",
    "sg:postcode":"34266",
    "sg:province":"FL",
    "sg:tags":[
        "contractor"
    ],
    "wof:name":"Gary McHugh Masonry Inc",
    "wof:placetype":"venue"
},
  "geometry": {"coordinates":[-81.815744,27.182587],"type":"Point"}
}