{
  "type": "Feature",
  "properties": {
    "addr:full":"1800 NE 114th St Apt 809 Miami FL 33181",
    "addr:housenumber":"1800;809",
    "addr:postcode":"33181",
    "addr:street":"Ne 114Th St Apt",
    "iso:country":"US",
    "sg:address":"1800 NE 114th St Apt 809",
    "sg:city":"Miami",
    "sg:classifiers":[
        {
            "category":"Professional",
            "subcategory":"Accounting & Tax Preparation",
            "type":"Services"
        }
    ],
    "sg:phone":"+1 305 892 2536",
    "sg:postcode":"33181",
    "sg:province":"FL",
    "sg:tags":[
        "bookkeeping",
        "billing"
    ],
    "wof:name":"Co Pay Funding",
    "wof:placetype":"venue"
},
  "geometry": {"coordinates":[-80.16486999999999,25.880896],"type":"Point"}
}