{
  "type": "Feature",
  "properties": {
    "addr:full":"3205 SE 19th Ave Ocala FL 34471",
    "addr:housenumber":"3205",
    "addr:postcode":"34471",
    "addr:street":"Se 19Th Ave",
    "iso:country":"US",
    "sg:address":"3205 SE 19th Ave",
    "sg:city":"Ocala",
    "sg:classifiers":[
        {
            "category":"Wholesale",
            "subcategory":"Groceries",
            "type":"Manufacturing & Wholesale Goods"
        }
    ],
    "sg:phone":"+1 954 764 1781",
    "sg:postcode":"34471",
    "sg:province":"FL",
    "sg:tags":[
        "food",
        "product"
    ],
    "wof:name":"Colorado Boxed Beef",
    "wof:placetype":"venue"
},
  "geometry": {"coordinates":[-82.111593,29.155414],"type":"Point"}
}