{
  "type": "Feature",
  "properties": {
    "addr:full":"10 Sarasota Center Blvd Sarasota FL 34240",
    "addr:housenumber":"10",
    "addr:postcode":"34240",
    "addr:street":"Sarasota Center Blvd",
    "iso:country":"US",
    "sg:address":"10 Sarasota Center Blvd",
    "sg:city":"Sarasota",
    "sg:classifiers":[
        {
            "category":"Professional",
            "subcategory":"Computer Services",
            "type":"Services"
        }
    ],
    "sg:phone":"+1 941 351 8279",
    "sg:postcode":"34240",
    "sg:province":"FL",
    "sg:tags":[
        "consultant"
    ],
    "sg:website":"www.pcmnetworking.com",
    "wof:name":"PCM Networking",
    "wof:placetype":"venue"
},
  "geometry": {"coordinates":[-82.40561700000001,27.342743],"type":"Point"}
}