{
  "type": "Feature",
  "properties": {
    "addr:full":"9350 SW 22nd Ter Miami FL 33165",
    "addr:housenumber":"9350",
    "addr:postcode":"33165",
    "addr:street":"Sw 22Nd Ter",
    "iso:country":"US",
    "sg:address":"9350 SW 22nd Ter",
    "sg:city":"Miami",
    "sg:classifiers":[
        {
            "category":"Real Estate",
            "subcategory":"Surveying",
            "type":"Services"
        }
    ],
    "sg:phone":"+1 305 220 0073",
    "sg:postcode":"33165",
    "sg:province":"FL",
    "wof:name":"Gunter Group Inc",
    "wof:placetype":"venue"
},
  "geometry": {"coordinates":[-80.34639799999999,25.748743],"type":"Point"}
}