{
  "type": "Feature",
  "properties": {
    "addr:full":"502 Pasadena Ave S St Petersburg FL 33707",
    "addr:housenumber":"502",
    "addr:postcode":"33707",
    "addr:street":"Pasadena Ave S",
    "iso:country":"US",
    "sg:address":"502 Pasadena Ave S",
    "sg:city":"St Petersburg",
    "sg:classifiers":[
        {
            "category":"Health Services",
            "subcategory":"Podiatrist",
            "type":"Services"
        }
    ],
    "sg:phone":"+1 727 343 9400",
    "sg:postcode":"33707",
    "sg:province":"FL",
    "wof:name":"Pasadena & Gulf Beach Podiatry",
    "wof:placetype":"venue"
},
  "geometry": {"coordinates":[-82.734101,27.764782],"type":"Point"}
}