{
  "type": "Feature",
  "properties": {
    "addr:full":"390 W State Road 434 Ste 100 Longwood FL 32750",
    "addr:housenumber":"390",
    "addr:postcode":"32750",
    "addr:street":"W State Road 434 Ste 100",
    "iso:country":"US",
    "sg:address":"390 W State Road 434 Ste 100",
    "sg:city":"Longwood",
    "sg:classifiers":[
        {
            "category":"Banks & Credit Unions",
            "subcategory":"Bank",
            "type":"Services"
        },
        {
            "category":"Banks & Credit Unions",
            "subcategory":"Financial Services",
            "type":"Services"
        }
    ],
    "sg:phone":"+1 407 834 1924",
    "sg:postcode":"32750",
    "sg:province":"FL",
    "sg:tags":[
        "saving",
        "mortgage",
        "loan",
        "commercial",
        "broker",
        "banking",
        "internet"
    ],
    "sg:website":"www.bankofamerica.com",
    "wof:name":"Bank of America",
    "wof:placetype":"venue"
},
  "geometry": {"coordinates":[-81.352743,28.69772],"type":"Point"}
}