{
  "type": "Feature",
  "properties": {
    "iso:country":"US",
    "sg:address":"8245 Co Rd 44",
    "sg:city":"Leesburg",
    "sg:classifiers":[
        {
            "category":"Health Services",
            "subcategory":"Doctor",
            "type":"Services"
        }
    ],
    "sg:phone":"+1 352 326 3366",
    "sg:postcode":"34788",
    "sg:province":"FL",
    "sg:tags":[
        "medical"
    ],
    "wof:name":"Eugene P Tan MD",
    "wof:placetype":"venue"
},
  "geometry": {"coordinates":[-81.818697,28.835937],"type":"Point"}
}