{
  "type": "Feature",
  "properties": {
    "iso:country":"US",
    "sg:address":"7667 W Beaver St Lot 5",
    "sg:city":"Jacksonville",
    "sg:classifiers":[
        {
            "category":"Health Services",
            "subcategory":"Nursing And Care Facility",
            "type":"Services"
        }
    ],
    "sg:phone":"+1 904 781 3938",
    "sg:postcode":"32220",
    "sg:province":"FL",
    "sg:tags":[
        "residential"
    ],
    "wof:name":"Wng Enterprises",
    "wof:placetype":"venue"
},
  "geometry": {"coordinates":[-81.77493800000001,30.322794],"type":"Point"}
}