{
  "type": "Feature",
  "properties": {
    "iso:country":"US",
    "sg:address":"175 S Lawrence Blvd",
    "sg:city":"Keystone Heights",
    "sg:classifiers":[
        {
            "category":"Professional",
            "subcategory":"Engineering",
            "type":"Services"
        }
    ],
    "sg:phone":"+1 352 473 6464",
    "sg:postcode":"32656",
    "sg:province":"FL",
    "sg:tags":[
        "engineer"
    ],
    "wof:name":"Robert E Jones",
    "wof:placetype":"venue"
},
  "geometry": {"coordinates":[-82.03112299999999,29.78475],"type":"Point"}
}