{
  "type": "Feature",
  "properties": {
    "iso:country":"US",
    "sg:address":"3380 NW 114th St",
    "sg:city":"Miami",
    "sg:classifiers":[
        {
            "category":"Manufacturing",
            "subcategory":"Wood Products",
            "type":"Manufacturing & Wholesale Goods"
        },
        {
            "category":"Manufacturing",
            "subcategory":"Paper Products",
            "type":"Manufacturing & Wholesale Goods"
        }
    ],
    "sg:phone":"+1 305 403 1523",
    "sg:postcode":"33167",
    "sg:province":"FL",
    "sg:tags":[
        "fiber-wholesale",
        "fiber",
        "boxes-corrugated",
        "boxes-folding-manufacturers",
        "manufacturer"
    ],
    "wof:name":"U - Boxes",
    "wof:placetype":"venue"
},
  "geometry": {"coordinates":[-80.254363,25.878279],"type":"Point"}
}