{
  "type": "Feature",
  "properties": {
    "addr:full":"491 18th Ave NE Naples FL 34120",
    "addr:housenumber":"491",
    "addr:postcode":"34120",
    "addr:street":"18Th Ave Ne",
    "iso:country":"US",
    "sg:address":"491 18th Ave NE",
    "sg:city":"Naples",
    "sg:classifiers":[
        {
            "category":"Social Services",
            "type":"Services"
        }
    ],
    "sg:phone":"+1 239 352 9320",
    "sg:postcode":"34120",
    "sg:province":"FL",
    "sg:tags":[
        "counseling"
    ],
    "wof:name":"WEIC",
    "wof:placetype":"venue"
},
  "geometry": {"coordinates":[-81.592528,26.262921],"type":"Point"}
}