{
  "type": "Feature",
  "properties": {
    "addr:full":"4551 N Washington Blvd Sarasota FL 34234",
    "addr:housenumber":"4551",
    "addr:postcode":"34234",
    "addr:street":"N Washington Blvd",
    "iso:country":"US",
    "sg:address":"4551 N Washington Blvd",
    "sg:city":"Sarasota",
    "sg:classifiers":[
        {
            "category":"Home & Garden",
            "subcategory":"Carpets & Floor Coverings",
            "type":"Retail Goods"
        }
    ],
    "sg:phone":"+1 941 355 8437",
    "sg:postcode":"34234",
    "sg:province":"FL",
    "sg:tags":[
        "tile",
        "dealer",
        "rug"
    ],
    "wof:name":"Manasota Flooring Inc",
    "wof:placetype":"venue"
},
  "geometry": {"coordinates":[-82.530946,27.372858],"type":"Point"}
}