{
  "type": "Feature",
  "properties": {
    "iso:country":"US",
    "sg:address":"16250 NW 48th Ave",
    "sg:city":"Hialeah",
    "sg:classifiers":[
        {
            "category":"Manufacturing",
            "subcategory":"Furniture",
            "type":"Manufacturing & Wholesale Goods"
        }
    ],
    "sg:phone":"+1 305 624 2333",
    "sg:postcode":"33014",
    "sg:province":"FL",
    "sg:tags":[
        "material",
        "fixture",
        "display"
    ],
    "sg:website":"www.art-phyl.com",
    "wof:name":"Art-Phyl CREATIONS-Apc",
    "wof:placetype":"venue"
},
  "geometry": {"coordinates":[-80.278689,25.920154],"type":"Point"}
}