{
  "type": "Feature",
  "properties": {
    "addr:full":"801 Playground Rd Fort Walton Bch FL 32547",
    "addr:housenumber":"801",
    "addr:postcode":"32547",
    "addr:street":"Playground Rd",
    "iso:country":"US",
    "sg:address":"801 Playground Rd",
    "sg:city":"Fort Walton Bch",
    "sg:classifiers":[
        {
            "category":"Professional",
            "subcategory":"Business Services",
            "type":"Services"
        },
        {
            "category":"Building & Trades",
            "subcategory":"Construction",
            "type":"Services"
        }
    ],
    "sg:phone":"+1 850 862 5677",
    "sg:postcode":"32547",
    "sg:province":"FL",
    "sg:tags":[
        "television",
        "electrical",
        "telephone",
        "cable",
        "contractor"
    ],
    "wof:name":"Aerial and Underground Telecom",
    "wof:placetype":"venue"
},
  "geometry": {"coordinates":[-86.621685,30.449215],"type":"Point"}
}