{
  "type": "Feature",
  "properties": {
    "iso:country":"US",
    "sg:address":"2553 N Atlantic Ave",
    "sg:city":"Daytona Beach",
    "sg:classifiers":[
        {
            "category":"Shopping",
            "type":"Retail Goods"
        }
    ],
    "sg:phone":"+1 386 671 2905",
    "sg:postcode":"32118",
    "sg:province":"FL",
    "sg:tags":[
        "cosmetic",
        "perfume"
    ],
    "wof:name":"KATH & Steph Avon & Acces",
    "wof:placetype":"venue"
},
  "geometry": {"coordinates":[-81.025915,29.2626],"type":"Point"}
}