{
  "type": "Feature",
  "properties": {
    "iso:country":"US",
    "sg:address":"3324 Tamiami Trl",
    "sg:city":"Naples",
    "sg:classifiers":[
        {
            "category":"Shopping",
            "subcategory":"Department Store",
            "type":"Retail Goods"
        }
    ],
    "sg:phone":"+1 239 793 2877",
    "sg:postcode":"34112",
    "sg:province":"FL",
    "sg:tags":[
        "shop"
    ],
    "wof:name":"Celia's Dollar Value",
    "wof:placetype":"venue"
},
  "geometry": {"coordinates":[-81.764529,26.125355],"type":"Point"}
}