{
  "type": "Feature",
  "properties": {
    "iso:country":"US",
    "sg:address":"1910 S Monroe St",
    "sg:city":"Tallahassee",
    "sg:classifiers":[
        {
            "category":"Manufacturing",
            "subcategory":"Glass & Minerals",
            "type":"Manufacturing & Wholesale Goods"
        },
        {
            "category":"Retail",
            "subcategory":"Auto Repair",
            "type":"Services"
        }
    ],
    "sg:phone":"+1 877 350 2675",
    "sg:postcode":"32301",
    "sg:province":"FL",
    "sg:tags":[
        "plate",
        "window",
        "windshield",
        "glass-auto"
    ],
    "sg:website":"http://local.ingenio.com/Listings/Details.aspx?NUM=a%3a9825363%3a13%3a4859924%3a14%3a0%3a7",
    "wof:name":"A-Z Wakulla Glass",
    "wof:placetype":"venue"
},
  "geometry": {"coordinates":[-84.28061700000001,30.42334],"type":"Point"}
}