{
  "type": "Feature",
  "properties": {
    "iso:country":"US",
    "sg:address":"8518 Eagles Loop Cir",
    "sg:city":"Windermere",
    "sg:phone":"+1 407 217 5701",
    "sg:postcode":"34786",
    "sg:province":"FL",
    "wof:name":"Ross, John",
    "wof:placetype":"venue"
},
  "geometry": {"coordinates":[-81.546255,28.443648],"type":"Point"}
}