{
  "type": "Feature",
  "properties": {
    "addr:full":"3835 Saint Valentine Way Orlando FL 32811",
    "addr:housenumber":"3835",
    "addr:postcode":"32811",
    "addr:street":"Saint Valentine Way",
    "iso:country":"US",
    "sg:address":"3835 Saint Valentine Way",
    "sg:city":"Orlando",
    "sg:classifiers":[
        {
            "category":"Autos & Motor Vehicles",
            "subcategory":"Auto Supplies",
            "type":"Retail Goods"
        }
    ],
    "sg:phone":"+1 407 843 9130",
    "sg:postcode":"32811",
    "sg:province":"FL",
    "sg:tags":[
        "automobile",
        "part"
    ],
    "sg:website":"http://www.mytinytiger.com",
    "wof:name":"Vista-Pro Automotive",
    "wof:placetype":"venue"
},
  "geometry": {"coordinates":[-81.43264000000001,28.503048],"type":"Point"}
}