{
  "type": "Feature",
  "properties": {
    "addr:full":"1501 8th St SE Miami FL 33135",
    "addr:housenumber":"1501",
    "addr:postcode":"33135",
    "addr:street":"8Th St Se",
    "iso:country":"US",
    "sg:address":"1501 8th St SE",
    "sg:city":"Miami",
    "sg:classifiers":[
        {
            "category":"Professional",
            "subcategory":"Management & Consulting",
            "type":"Services"
        }
    ],
    "sg:phone":"+1 305 643 6823",
    "sg:postcode":"33135",
    "sg:province":"FL",
    "sg:tags":[
        "fuel"
    ],
    "wof:name":"C E Management Corp",
    "wof:placetype":"venue"
},
  "geometry": {"coordinates":[-80.220536,25.765684],"type":"Point"}
}