{
  "type": "Feature",
  "properties": {
    "iso:country":"US",
    "sg:address":"5330 NW 17th Ave",
    "sg:city":"Miami",
    "sg:classifiers":[
        {
            "category":"Restaurant",
            "type":"Food & Drink"
        }
    ],
    "sg:phone":"+1 305 693 6033",
    "sg:postcode":"33142",
    "sg:province":"FL",
    "wof:name":"Shaker's Conch House",
    "wof:placetype":"venue"
},
  "geometry": {"coordinates":[-80.22460700000001,25.823428],"type":"Point"}
}