{
  "type": "Feature",
  "properties": {
    "addr:full":"15400 Biscayne Blvd Ste 103 Aventura FL 33160",
    "addr:housenumber":"15400",
    "addr:postcode":"33160",
    "addr:street":"Biscayne Blvd Ste 103",
    "iso:country":"US",
    "sg:address":"15400 Biscayne Blvd Ste 103",
    "sg:city":"Aventura",
    "sg:classifiers":[
        {
            "category":"Health Services",
            "subcategory":"Doctor",
            "type":"Services"
        }
    ],
    "sg:phone":"+1 305 947 0751",
    "sg:postcode":"33160",
    "sg:province":"FL",
    "wof:name":"Pascual Amaryllis MD",
    "wof:placetype":"venue"
},
  "geometry": {"coordinates":[-80.156334,25.918367],"type":"Point"}
}