{
  "type": "Feature",
  "properties": {
    "addr:full":"3810 W Osborne Ave Tampa FL 33614",
    "addr:housenumber":"3810",
    "addr:postcode":"33614",
    "addr:street":"W Osborne Ave",
    "iso:country":"US",
    "sg:address":"3810 W Osborne Ave",
    "sg:city":"Tampa",
    "sg:classifiers":[
        {
            "category":"Retail",
            "subcategory":"Auto Repair",
            "type":"Services"
        }
    ],
    "sg:phone":"+1 813 876 6438",
    "sg:postcode":"33614",
    "sg:province":"FL",
    "sg:tags":[
        "body",
        "general"
    ],
    "wof:name":"Classic Corvettes Inc",
    "wof:placetype":"venue"
},
  "geometry": {"coordinates":[-82.50640799999999,27.98884],"type":"Point"}
}