{
  "type": "Feature",
  "properties": {
    "addr:full":"6117 Kurt St Brooksville FL 34604",
    "addr:housenumber":"6117",
    "addr:postcode":"34604",
    "addr:street":"Kurt St",
    "iso:country":"US",
    "sg:address":"6117 Kurt St",
    "sg:city":"Brooksville",
    "sg:classifiers":[
        {
            "category":"Building & Trades",
            "subcategory":"Construction",
            "type":"Services"
        }
    ],
    "sg:phone":"+1 352 754 2813",
    "sg:postcode":"34604",
    "sg:province":"FL",
    "sg:tags":[
        "contractor"
    ],
    "wof:name":"Herbert J Denney",
    "wof:placetype":"venue"
},
  "geometry": {"coordinates":[-82.465211,28.515998],"type":"Point"}
}