{
  "type": "Feature",
  "properties": {
    "iso:country":"US",
    "sg:address":"7014 University Blvd",
    "sg:city":"Winter Park",
    "sg:classifiers":[
        {
            "category":"Restaurant",
            "type":"Food & Drink"
        }
    ],
    "sg:phone":"+1 407 671 3578",
    "sg:postcode":"32792",
    "sg:province":"FL",
    "wof:name":"Heshgen Food Svc",
    "wof:placetype":"venue"
},
  "geometry": {"coordinates":[-81.293997,28.597451],"type":"Point"}
}