{
  "type": "Feature",
  "properties": {
    "iso:country":"US",
    "sg:address":"1355 W Palmetto Park Rd",
    "sg:city":"Boca Raton",
    "sg:classifiers":[
        {
            "category":"Professional",
            "subcategory":"Advertising",
            "type":"Services"
        }
    ],
    "sg:phone":"+1 561 697 0440",
    "sg:postcode":"33486",
    "sg:province":"FL",
    "sg:tags":[
        "agency"
    ],
    "wof:name":"AAA Attorney Refferal Service",
    "wof:placetype":"venue"
},
  "geometry": {"coordinates":[-80.113979,26.350824],"type":"Point"}
}