{
  "type": "Feature",
  "properties": {
    "iso:country":"US",
    "sg:address":"1201 58th Ave S",
    "sg:city":"St Petersburg",
    "sg:classifiers":[
        {
            "category":"Organizations",
            "subcategory":"Community Association",
            "type":"Services"
        }
    ],
    "sg:phone":"+1 727 866 2500",
    "sg:postcode":"33705",
    "sg:province":"FL",
    "sg:tags":[
        "club"
    ],
    "wof:name":"Baypoint Little League",
    "wof:placetype":"venue"
},
  "geometry": {"coordinates":[-82.654635,27.715719],"type":"Point"}
}