{
  "type": "Feature",
  "properties": {
    "iso:country":"US",
    "sg:address":"1820 SW 11th Ct",
    "sg:city":"Fort Lauderdale",
    "sg:classifiers":[
        {
            "category":"Professional",
            "subcategory":"Business Services",
            "type":"Services"
        }
    ],
    "sg:phone":"+1 954 294 5504",
    "sg:postcode":"33312",
    "sg:province":"FL",
    "wof:name":"Mulheron Group Inc",
    "wof:placetype":"venue"
},
  "geometry": {"coordinates":[-80.166157,26.107745],"type":"Point"}
}