{
  "type": "Feature",
  "properties": {
    "iso:country":"US",
    "sg:address":"4701 NW 7th Manor",
    "sg:city":"Coconut Creek",
    "sg:classifiers":[
        {
            "category":"Banks & Credit Unions",
            "subcategory":"Bank",
            "type":"Services"
        }
    ],
    "sg:phone":"+1 954 974 5229",
    "sg:postcode":"33063",
    "sg:province":"FL",
    "sg:tags":[
        "financing"
    ],
    "wof:name":"Wells Fargo Business Credit",
    "wof:placetype":"venue"
},
  "geometry": {"coordinates":[-80.190275,26.238087],"type":"Point"}
}