{
  "type": "Feature",
  "properties": {
    "addr:full":"4711 Wakulla Way Orlando FL 32822",
    "addr:housenumber":"4711",
    "addr:postcode":"32822",
    "addr:street":"Wakulla Way",
    "iso:country":"US",
    "sg:address":"4711 Wakulla Way",
    "sg:city":"Orlando",
    "sg:classifiers":[
        {
            "category":"Building & Trades",
            "subcategory":"Construction",
            "type":"Services"
        }
    ],
    "sg:phone":"+1 407 277 5193",
    "sg:postcode":"32822",
    "sg:province":"FL",
    "sg:tags":[
        "dry wall",
        "contractor"
    ],
    "wof:name":"Z's Drywall Svc",
    "wof:placetype":"venue"
},
  "geometry": {"coordinates":[-81.281262,28.479795],"type":"Point"}
}