{
  "type": "Feature",
  "properties": {
    "iso:country":"US",
    "sg:address":"6365 Taft St",
    "sg:city":"Hollywood",
    "sg:classifiers":[
        {
            "category":"Real Estate",
            "subcategory":"Real Estate Agent",
            "type":"Services"
        }
    ],
    "sg:phone":"+1 954 964 3717",
    "sg:postcode":"33024",
    "sg:province":"FL",
    "sg:website":"www.americanhomeguides.com",
    "wof:name":"American Home Guides Inc",
    "wof:placetype":"venue"
},
  "geometry": {"coordinates":[-80.21403100000001,26.024863],"type":"Point"}
}