{
  "type": "Feature",
  "properties": {
    "addr:full":"2021 E Commercial Blvd Fort Lauderdale FL 33308",
    "addr:housenumber":"2021",
    "addr:postcode":"33308",
    "addr:street":"E Commercial Blvd",
    "iso:country":"US",
    "sg:address":"2021 E Commercial Blvd",
    "sg:city":"Fort Lauderdale",
    "sg:classifiers":[
        {
            "category":"Health Services",
            "subcategory":"Doctor",
            "type":"Services"
        }
    ],
    "sg:phone":"+1 954 202 7850",
    "sg:postcode":"33308",
    "sg:province":"FL",
    "sg:tags":[
        "medical"
    ],
    "wof:name":"Gastrntrlogy Inst Fort Ldrdale",
    "wof:placetype":"venue"
},
  "geometry": {"coordinates":[-80.121039,26.189058],"type":"Point"}
}