{
  "type": "Feature",
  "properties": {
    "addr:full":"4350 NE 170th Ave Silver Springs FL 34488",
    "addr:housenumber":"4350",
    "addr:postcode":"34488",
    "addr:street":"Ne 170Th Ave",
    "iso:country":"US",
    "sg:address":"4350 NE 170th Ave",
    "sg:city":"Silver Springs",
    "sg:classifiers":[
        {
            "category":"Retail",
            "subcategory":"Auto Rental",
            "type":"Services"
        }
    ],
    "sg:phone":"+1 352 528 0841",
    "sg:postcode":"34488",
    "sg:province":"FL",
    "sg:tags":[
        "renting",
        "truck",
        "leasing"
    ],
    "wof:name":"U-Haul Co",
    "wof:placetype":"venue"
},
  "geometry": {"coordinates":[-81.871752,29.232111],"type":"Point"}
}