{
  "type": "Feature",
  "properties": {
    "addr:full":"87 Bay Bridge Dr Gulf Breeze FL 32561",
    "addr:housenumber":"87",
    "addr:postcode":"32561",
    "addr:street":"Bay Bridge Dr",
    "iso:country":"US",
    "sg:address":"87 Bay Bridge Dr",
    "sg:city":"Gulf Breeze",
    "sg:classifiers":[
        {
            "category":"Insurance",
            "subcategory":"Insurance Agent",
            "type":"Services"
        }
    ],
    "sg:phone":"+1 850 934 2997",
    "sg:postcode":"32561",
    "sg:province":"FL",
    "wof:name":"Prudential",
    "wof:placetype":"venue"
},
  "geometry": {"coordinates":[-87.17545,30.370929],"type":"Point"}
}