{
  "type": "Feature",
  "properties": {
    "iso:country":"US",
    "sg:address":"200 Douglas Ave",
    "sg:city":"Dunedin",
    "sg:classifiers":[
        {
            "category":"Retail",
            "subcategory":"Auto Repair",
            "type":"Services"
        }
    ],
    "sg:phone":"+1 727 736 6788",
    "sg:postcode":"34698",
    "sg:province":"FL",
    "sg:tags":[
        "shop",
        "automobile",
        "tire"
    ],
    "wof:name":"Dick Carroll Inc",
    "wof:placetype":"venue"
},
  "geometry": {"coordinates":[-82.787897,28.001642],"type":"Point"}
}