{
  "type": "Feature",
  "properties": {
    "addr:full":"623 Beechwood St Jacksonville FL 32206",
    "addr:housenumber":"623",
    "addr:postcode":"32206",
    "addr:street":"Beechwood St",
    "iso:country":"US",
    "sg:address":"623 Beechwood St",
    "sg:city":"Jacksonville",
    "sg:classifiers":[
        {
            "category":"Local Transit",
            "type":"Transportation"
        }
    ],
    "sg:phone":"+1 904 358 1211",
    "sg:postcode":"32206",
    "sg:province":"FL",
    "sg:tags":[
        "public"
    ],
    "sg:website":"http://www.communityrehabcenter.org",
    "wof:name":"Crct",
    "wof:placetype":"venue"
},
  "geometry": {"coordinates":[-81.659167,30.369212],"type":"Point"}
}