{
  "type": "Feature",
  "properties": {
    "iso:country":"US",
    "sg:address":"1 Ellington Dr",
    "sg:city":"Palm Coast",
    "sg:classifiers":[
        {
            "category":"Wholesale",
            "subcategory":"Vending Machines",
            "type":"Manufacturing & Wholesale Goods"
        }
    ],
    "sg:phone":"+1 386 793 9203",
    "sg:postcode":"32164",
    "sg:province":"FL",
    "sg:tags":[
        "operator"
    ],
    "wof:name":"Liberty Snack & Vending",
    "wof:placetype":"venue"
},
  "geometry": {"coordinates":[-81.22729,29.489849],"type":"Point"}
}