{
  "type": "Feature",
  "properties": {
    "addr:full":"1661 Peregrine Falcons Way Orlando FL 32837",
    "addr:housenumber":"1661",
    "addr:postcode":"32837",
    "addr:street":"Peregrine Falcons Way",
    "iso:country":"US",
    "sg:address":"1661 Peregrine Falcons Way",
    "sg:city":"Orlando",
    "sg:classifiers":[
        {
            "category":"Banks & Credit Unions",
            "subcategory":"Financial Services",
            "type":"Services"
        }
    ],
    "sg:phone":"+1 407 850 0564",
    "sg:postcode":"32837",
    "sg:province":"FL",
    "sg:tags":[
        "investor"
    ],
    "wof:name":"Smart Investments Orlando I",
    "wof:placetype":"venue"
},
  "geometry": {"coordinates":[-81.402624,28.362681],"type":"Point"}
}