{
  "type": "Feature",
  "properties": {
    "addr:full":"2910 Sammonds Rd Plant City FL 33563",
    "addr:housenumber":"2910",
    "addr:postcode":"33563",
    "addr:street":"Sammonds Rd",
    "iso:country":"US",
    "sg:address":"2910 Sammonds Rd",
    "sg:city":"Plant City",
    "sg:classifiers":[
        {
            "category":"Manufacturing",
            "subcategory":"Metals",
            "type":"Manufacturing & Wholesale Goods"
        },
        {
            "category":"Wholesale",
            "subcategory":"Metals & Minerals",
            "type":"Manufacturing & Wholesale Goods"
        }
    ],
    "sg:phone":"+1 813 752 6521",
    "sg:postcode":"33563",
    "sg:province":"FL",
    "sg:tags":[
        "pipe",
        "foundry",
        "center",
        "iron"
    ],
    "wof:name":"American Cast Iron Pipe Co",
    "wof:placetype":"venue"
},
  "geometry": {"coordinates":[-82.146918,28.007277],"type":"Point"}
}