{
  "type": "Feature",
  "properties": {
    "iso:country":"US",
    "sg:address":"3846 S Tuttle Ave",
    "sg:city":"Sarasota",
    "sg:classifiers":[
        {
            "category":"Restaurant",
            "type":"Food & Drink"
        }
    ],
    "sg:menulink":"http://www.allmenus.com/fl/sarasota/81383-papa-johns-pizza/menu/",
    "sg:phone":"+1 941 922 7272",
    "sg:postcode":"34239",
    "sg:province":"FL",
    "sg:tags":[
        "american",
        "pizza"
    ],
    "wof:name":"Papa John's Pizza",
    "wof:placetype":"venue"
},
  "geometry": {"coordinates":[-82.51420400000001,27.301456],"type":"Point"}
}