{
  "type": "Feature",
  "properties": {
    "iso:country":"US",
    "sg:address":"1290 SW Biltmore St",
    "sg:city":"Port St Lucie",
    "sg:classifiers":[
        {
            "category":"Building & Trades",
            "subcategory":"Construction",
            "type":"Services"
        }
    ],
    "sg:phone":"+1 772 370 9770",
    "sg:postcode":"34983",
    "sg:province":"FL",
    "sg:tags":[
        "roofing",
        "contractor"
    ],
    "wof:name":"Treasure Coast Roofing",
    "wof:placetype":"venue"
},
  "geometry": {"coordinates":[-80.370915,27.304078],"type":"Point"}
}