{
  "type": "Feature",
  "properties": {
    "iso:country":"US",
    "sg:address":"7297 NW 36th St",
    "sg:city":"Miami",
    "sg:classifiers":[
        {
            "category":"Sports & Exercise",
            "subcategory":"Gym",
            "type":"Entertainment"
        }
    ],
    "sg:phone":"+1 305 594 4223",
    "sg:postcode":"33166",
    "sg:province":"FL",
    "sg:tags":[
        "club",
        "health",
        "studio",
        "gymnasium"
    ],
    "wof:name":"Body 2000",
    "wof:placetype":"venue"
},
  "geometry": {"coordinates":[-80.31552499999999,25.809362],"type":"Point"}
}