{
  "type": "Feature",
  "properties": {
    "addr:full":"13011 US Hwy 19 Port Richey FL 34667",
    "addr:housenumber":"13011",
    "addr:postcode":"34667",
    "addr:street":"Us Hwy 19",
    "iso:country":"US",
    "sg:address":"13011 US Hwy 19",
    "sg:city":"Port Richey",
    "sg:classifiers":[
        {
            "category":"Retail",
            "subcategory":"Funeral Services",
            "type":"Services"
        }
    ],
    "sg:phone":"+1 727 863 1000",
    "sg:postcode":"34667",
    "sg:province":"FL",
    "sg:tags":[
        "home"
    ],
    "wof:name":"SCI",
    "wof:placetype":"venue"
},
  "geometry": {"coordinates":[-82.69929399999999,28.347325],"type":"Point"}
}