{
  "type": "Feature",
  "properties": {
    "iso:country":"US",
    "sg:address":"1713 Penman Rd",
    "sg:city":"Jacksonville Beach",
    "sg:classifiers":[
        {
            "category":"Professional",
            "subcategory":"Computer Services",
            "type":"Services"
        }
    ],
    "sg:phone":"+1 904 247 7220",
    "sg:postcode":"32250",
    "sg:province":"FL",
    "sg:tags":[
        "programing",
        "custom"
    ],
    "wof:name":"Laser Check Specialists",
    "wof:placetype":"venue"
},
  "geometry": {"coordinates":[-81.406448,30.302987],"type":"Point"}
}