{
  "type": "Feature",
  "properties": {
    "addr:full":"4101 Oakwood Blvd Hollywood FL 33020",
    "addr:housenumber":"4101",
    "addr:postcode":"33020",
    "addr:street":"Oakwood Blvd",
    "iso:country":"US",
    "sg:address":"4101 Oakwood Blvd",
    "sg:city":"Hollywood",
    "sg:classifiers":[
        {
            "category":"Shopping",
            "type":"Retail Goods"
        }
    ],
    "sg:phone":"+1 954 920 7658",
    "sg:postcode":"33020",
    "sg:province":"FL",
    "sg:tags":[
        "merchandise",
        "animal"
    ],
    "wof:name":"Petsmart",
    "wof:placetype":"venue"
},
  "geometry": {"coordinates":[-80.15997299999999,26.047836],"type":"Point"}
}