{
  "type": "Feature",
  "properties": {
    "iso:country":"US",
    "sg:address":"8320 Lillian Hwy",
    "sg:city":"Pensacola",
    "sg:classifiers":[
        {
            "category":"Building & Trades",
            "subcategory":"Construction",
            "type":"Services"
        }
    ],
    "sg:phone":"+1 850 453 6177",
    "sg:postcode":"32506",
    "sg:province":"FL",
    "sg:tags":[
        "work",
        "carpentry"
    ],
    "wof:name":"Dream Craft Woodworking Inc",
    "wof:placetype":"venue"
},
  "geometry": {"coordinates":[-87.32457100000001,30.421065],"type":"Point"}
}