{
  "type": "Feature",
  "properties": {
    "addr:full":"4040 SW 69th Ave Miramar FL 33023",
    "addr:housenumber":"4040",
    "addr:postcode":"33023",
    "addr:street":"Sw 69Th Ave",
    "iso:country":"US",
    "sg:address":"4040 SW 69th Ave",
    "sg:city":"Miramar",
    "sg:classifiers":[
        {
            "category":"Restaurant",
            "type":"Food & Drink"
        }
    ],
    "sg:phone":"+1 954 963 7007",
    "sg:postcode":"33023",
    "sg:province":"FL",
    "sg:tags":[
        "continental"
    ],
    "wof:name":"Family Caribbean Cuisine",
    "wof:placetype":"venue"
},
  "geometry": {"coordinates":[-80.225735,25.973257],"type":"Point"}
}