{
  "type": "Feature",
  "properties": {
    "iso:country":"US",
    "sg:address":"207 SW 12th Ct",
    "sg:city":"Fort Lauderdale",
    "sg:classifiers":[
        {
            "category":"Professional",
            "subcategory":"Lawyer & Legal Services",
            "type":"Services"
        }
    ],
    "sg:phone":"+1 954 523 6225",
    "sg:postcode":"33315",
    "sg:province":"FL",
    "wof:name":"Mary Catherine Bonner",
    "wof:placetype":"venue"
},
  "geometry": {"coordinates":[-80.14554099999999,26.106644],"type":"Point"}
}