{
  "type": "Feature",
  "properties": {
    "iso:country":"US",
    "sg:address":"908 Savannas Point Dr",
    "sg:city":"Fort Pierce",
    "sg:classifiers":[
        {
            "category":"Building & Trades",
            "subcategory":"Construction",
            "type":"Services"
        }
    ],
    "sg:phone":"+1 772 464 9670",
    "sg:postcode":"34982",
    "sg:province":"FL",
    "sg:tags":[
        "house"
    ],
    "wof:name":"General Cnstr Rnovation By Nel",
    "wof:placetype":"venue"
},
  "geometry": {"coordinates":[-80.3181,27.402089],"type":"Point"}
}