{
  "type": "Feature",
  "properties": {
    "iso:country":"US",
    "sg:address":"1334 SE Macarthur Blvd",
    "sg:city":"Stuart",
    "sg:classifiers":[
        {
            "category":"Professional",
            "subcategory":"Lawyer & Legal Services",
            "type":"Services"
        }
    ],
    "sg:phone":"+1 772 225 5400",
    "sg:postcode":"34996",
    "sg:province":"FL",
    "sg:tags":[
        "attorney"
    ],
    "wof:name":"Richard A Zambo P A",
    "wof:placetype":"venue"
},
  "geometry": {"coordinates":[-80.16095799999999,27.187964],"type":"Point"}
}