{
  "type": "Feature",
  "properties": {
    "iso:country":"US",
    "sg:address":"10731 NW 4th St",
    "sg:city":"Plantation",
    "sg:classifiers":[
        {
            "category":"Autos & Motor Vehicles",
            "subcategory":"Automobile Sales",
            "type":"Retail Goods"
        }
    ],
    "sg:phone":"+1 954 370 8886",
    "sg:postcode":"33324",
    "sg:province":"FL",
    "sg:tags":[
        "car",
        "dealer"
    ],
    "wof:name":"Auto Shoppers Inc",
    "wof:placetype":"venue"
},
  "geometry": {"coordinates":[-80.292823,26.124436],"type":"Point"}
}