{
  "type": "Feature",
  "properties": {
    "addr:full":"2324 SE 14th St Ocala FL 34471",
    "addr:housenumber":"2324",
    "addr:postcode":"34471",
    "addr:street":"Se 14Th St",
    "iso:country":"US",
    "sg:address":"2324 SE 14th St",
    "sg:city":"Ocala",
    "sg:classifiers":[
        {
            "category":"Utilities",
            "subcategory":"Telephone",
            "type":"Services"
        }
    ],
    "sg:phone":"+1 352 368 1060",
    "sg:postcode":"34471",
    "sg:province":"FL",
    "sg:tags":[
        "communications"
    ],
    "wof:name":"Michell Enterprises",
    "wof:placetype":"venue"
},
  "geometry": {"coordinates":[-82.10693000000001,29.174298],"type":"Point"}
}