{
  "type": "Feature",
  "properties": {
    "iso:country":"US",
    "sg:address":"1900 Tamiami Trl",
    "sg:city":"Port Charlotte",
    "sg:classifiers":[
        {
            "category":"Organizations",
            "subcategory":"Membership Organization",
            "type":"Services"
        }
    ],
    "sg:phone":"+1 941 625 0455",
    "sg:postcode":"33948",
    "sg:province":"FL",
    "sg:tags":[
        "science",
        "reading",
        "christian",
        "rooms"
    ],
    "wof:name":"Christian Science Reading Room",
    "wof:placetype":"venue"
},
  "geometry": {"coordinates":[-82.130887,27.005332],"type":"Point"}
}