{
  "type": "Feature",
  "properties": {
    "addr:full":"612 Fernwood St Panama City Bch FL 32407",
    "addr:housenumber":"612",
    "addr:postcode":"32407",
    "addr:street":"Fernwood St",
    "iso:country":"US",
    "sg:address":"612 Fernwood St",
    "sg:city":"Panama City Bch",
    "sg:classifiers":[
        {
            "category":"Building & Trades",
            "subcategory":"Plumbing",
            "type":"Services"
        }
    ],
    "sg:phone":"+1 850 258 7907",
    "sg:postcode":"32407",
    "sg:province":"FL",
    "sg:tags":[
        "plumbing",
        "contractor"
    ],
    "wof:name":"Green's Plumbing Co LLC",
    "wof:placetype":"venue"
},
  "geometry": {"coordinates":[-85.839984,30.197088],"type":"Point"}
}