{
  "type": "Feature",
  "properties": {
    "addr:full":"5115 N Socrum Loop Rd Lakeland FL 33809",
    "addr:housenumber":"5115",
    "addr:postcode":"33809",
    "addr:street":"N Socrum Loop Rd",
    "iso:country":"US",
    "sg:address":"5115 N Socrum Loop Rd",
    "sg:city":"Lakeland",
    "sg:classifiers":[
        {
            "category":"Utilities",
            "subcategory":"Cable",
            "type":"Services"
        }
    ],
    "sg:phone":"+1 863 858 7379",
    "sg:postcode":"33809",
    "sg:province":"FL",
    "sg:tags":[
        "television"
    ],
    "wof:name":"Cable Dude Inc",
    "wof:placetype":"venue"
},
  "geometry": {"coordinates":[-81.94731400000001,28.10911],"type":"Point"}
}