{
  "type": "Feature",
  "properties": {
    "addr:full":"734 Co Rd 485 Lake Panasoffkee FL 33538",
    "addr:housenumber":"734;485",
    "addr:postcode":"33538",
    "addr:street":"Co Rd",
    "iso:country":"US",
    "sg:address":"734 Co Rd 485",
    "sg:city":"Lake Panasoffkee",
    "sg:classifiers":[
        {
            "category":"Manufacturing",
            "subcategory":"Retail Goods",
            "type":"Manufacturing & Wholesale Goods"
        }
    ],
    "sg:phone":"+1 352 569 0833",
    "sg:postcode":"33538",
    "sg:province":"FL",
    "sg:tags":[
        "product",
        "mfg"
    ],
    "wof:name":"Yelorose Crafts & Silk Creat",
    "wof:placetype":"venue"
},
  "geometry": {"coordinates":[-82.11671200000001,28.76817],"type":"Point"}
}