{
  "type": "Feature",
  "properties": {
    "iso:country":"US",
    "sg:address":"300 Hollywood Blvd SE",
    "sg:city":"Fort Walton Bch",
    "sg:classifiers":[
        {
            "category":"Health Services",
            "subcategory":"Doctor",
            "type":"Services"
        }
    ],
    "sg:phone":"+1 850 243 4723",
    "sg:postcode":"32548",
    "sg:province":"FL",
    "sg:tags":[
        "dentist"
    ],
    "wof:name":"A B Dental Assoc",
    "wof:placetype":"venue"
},
  "geometry": {"coordinates":[-86.595843,30.412125],"type":"Point"}
}