{
  "type": "Feature",
  "properties": {
    "iso:country":"US",
    "sg:address":"17100 Collins Ave",
    "sg:city":"Sunny Isles Bch",
    "sg:classifiers":[
        {
            "category":"Professional",
            "subcategory":"Computer Services",
            "type":"Services"
        }
    ],
    "sg:phone":"+1 305 945 6900",
    "sg:postcode":"33160",
    "sg:province":"FL",
    "sg:tags":[
        "internet"
    ],
    "wof:name":"AHEARTBREAKERS.COM",
    "wof:placetype":"venue"
},
  "geometry": {"coordinates":[-80.121771,25.934951],"type":"Point"}
}