{
  "type": "Feature",
  "properties": {
    "addr:full":"1150 Red John Dr Daytona Beach FL 32124",
    "addr:housenumber":"1150",
    "addr:postcode":"32124",
    "addr:street":"Red John Dr",
    "iso:country":"US",
    "sg:address":"1150 Red John Dr",
    "sg:city":"Daytona Beach",
    "sg:classifiers":[
        {
            "category":"Education",
            "subcategory":"School",
            "type":"Public Place"
        }
    ],
    "sg:phone":"+1 386 947 5904",
    "sg:postcode":"32124",
    "sg:province":"FL",
    "wof:name":"Discovery Center",
    "wof:placetype":"venue"
},
  "geometry": {"coordinates":[-81.14916100000001,29.138679],"type":"Point"}
}