{
  "type": "Feature",
  "properties": {
    "iso:country":"US",
    "sg:address":"3429 SW Archer Rd",
    "sg:city":"Gainesville",
    "sg:classifiers":[
        {
            "category":"Home & Garden",
            "subcategory":"Furniture",
            "type":"Retail Goods"
        }
    ],
    "sg:phone":"+1 352 378 3415",
    "sg:postcode":"32608",
    "sg:province":"FL",
    "sg:tags":[
        "bed",
        "mattress"
    ],
    "wof:name":"Buds 1/2 Price Beds",
    "wof:placetype":"venue"
},
  "geometry": {"coordinates":[-82.375196,29.624641],"type":"Point"}
}