{
  "type": "Feature",
  "properties": {
    "iso:country":"US",
    "sg:address":"5775 Lake Lizzie Dr",
    "sg:city":"Saint Cloud",
    "sg:classifiers":[
        {
            "category":"Arts & Performance",
            "subcategory":"Theater",
            "type":"Entertainment"
        }
    ],
    "sg:phone":"+1 407 892 7753",
    "sg:postcode":"34771",
    "sg:province":"FL",
    "sg:tags":[
        "group"
    ],
    "wof:name":"S Go Jump N Slide Inc",
    "wof:placetype":"venue"
},
  "geometry": {"coordinates":[-81.206791,28.246959],"type":"Point"}
}