{
  "type": "Feature",
  "properties": {
    "addr:full":"11830 Lancashire Dr Tampa FL 33626",
    "addr:housenumber":"11830",
    "addr:postcode":"33626",
    "addr:street":"Lancashire Dr",
    "iso:country":"US",
    "sg:address":"11830 Lancashire Dr",
    "sg:city":"Tampa",
    "sg:classifiers":[
        {
            "category":"Professional",
            "subcategory":"Computer Services",
            "type":"Services"
        }
    ],
    "sg:phone":"+1 813 854 4990",
    "sg:postcode":"33626",
    "sg:province":"FL",
    "sg:tags":[
        "datum"
    ],
    "wof:name":"Forbes Design Group Inc",
    "wof:placetype":"venue"
},
  "geometry": {"coordinates":[-82.61849100000001,28.059302],"type":"Point"}
}