{
  "type": "Feature",
  "properties": {
    "iso:country":"US",
    "sg:address":"1713 Palm Rd",
    "sg:city":"Ormond Beach",
    "sg:classifiers":[
        {
            "category":"Building & Trades",
            "subcategory":"Construction",
            "type":"Services"
        }
    ],
    "sg:phone":"+1 386 672 1147",
    "sg:postcode":"32174",
    "sg:province":"FL",
    "sg:tags":[
        "handyman"
    ],
    "wof:name":"Richard E Howell Handyman",
    "wof:placetype":"venue"
},
  "geometry": {"coordinates":[-81.069147,29.252606],"type":"Point"}
}