{
  "type": "Feature",
  "properties": {
    "iso:country":"US",
    "sg:address":"700 Armenia Dr",
    "sg:city":"Pensacola",
    "sg:classifiers":[
        {
            "category":"Retail",
            "subcategory":"Portrait Studio",
            "type":"Services"
        }
    ],
    "sg:phone":"+1 850 433 1199",
    "sg:postcode":"32505",
    "sg:province":"FL",
    "sg:tags":[
        "photographer"
    ],
    "wof:name":"C L Whitmore Photography",
    "wof:placetype":"venue"
},
  "geometry": {"coordinates":[-87.248,30.465127],"type":"Point"}
}