{
  "type": "Feature",
  "properties": {
    "iso:country":"US",
    "sg:address":"5539 US Hwy 29",
    "sg:city":"Molino",
    "sg:classifiers":[
        {
            "category":"Restaurant",
            "type":"Food & Drink"
        }
    ],
    "sg:phone":"+1 850 587 2803",
    "sg:postcode":"32577",
    "sg:province":"FL",
    "sg:tags":[
        "eating"
    ],
    "wof:name":"Fran's Country Grill",
    "wof:placetype":"venue"
},
  "geometry": {"coordinates":[-87.350853,30.694931],"type":"Point"}
}