{
  "type": "Feature",
  "properties": {
    "addr:full":"2001 E Robinson St Orlando FL 32803",
    "addr:housenumber":"2001",
    "addr:postcode":"32803",
    "addr:street":"E Robinson St",
    "iso:country":"US",
    "sg:address":"2001 E Robinson St",
    "sg:city":"Orlando",
    "sg:classifiers":[
        {
            "category":"Real Estate",
            "subcategory":"Real Estate Services",
            "type":"Services"
        },
        {
            "category":"Real Estate",
            "subcategory":"Real Estate Agent",
            "type":"Services"
        }
    ],
    "sg:phone":"+1 407 377 0850",
    "sg:postcode":"32803",
    "sg:province":"FL",
    "sg:tags":[
        "buyer",
        "loan",
        "broker"
    ],
    "wof:name":"Brokers Real Estate Group",
    "wof:placetype":"venue"
},
  "geometry": {"coordinates":[-81.356056,28.545891],"type":"Point"}
}