{
  "type": "Feature",
  "properties": {
    "iso:country":"US",
    "sg:address":"633 SE 4th Pl",
    "sg:city":"Hialeah",
    "sg:classifiers":[
        {
            "category":"Farming",
            "subcategory":"Poultry Farm",
            "type":"Manufacturing & Wholesale Goods"
        }
    ],
    "sg:phone":"+1 305 888 9891",
    "sg:postcode":"33010",
    "sg:province":"FL",
    "sg:tags":[
        "poultry-wholesale"
    ],
    "wof:name":"Emilio Produce",
    "wof:placetype":"venue"
},
  "geometry": {"coordinates":[-80.26838499999999,25.818622],"type":"Point"}
}