{
  "type": "Feature",
  "properties": {
    "addr:full":"9101 NW 7th Ave Miami FL 33150",
    "addr:housenumber":"9101",
    "addr:postcode":"33150",
    "addr:street":"Nw 7Th Ave",
    "iso:country":"US",
    "sg:address":"9101 NW 7th Ave",
    "sg:city":"Miami",
    "sg:classifiers":[
        {
            "category":"Real Estate",
            "subcategory":"Developer",
            "type":"Services"
        }
    ],
    "sg:phone":"+1 954 732 2833",
    "sg:postcode":"33150",
    "sg:province":"FL",
    "wof:name":"Tarco Properties LLC",
    "wof:placetype":"venue"
},
  "geometry": {"coordinates":[-80.209666,25.860948],"type":"Point"}
}