{
  "type": "Feature",
  "properties": {
    "addr:full":"1259 W 22nd St Jacksonville FL 32209",
    "addr:housenumber":"1259",
    "addr:postcode":"32209",
    "addr:street":"W 22Nd St",
    "iso:country":"US",
    "sg:address":"1259 W 22nd St",
    "sg:city":"Jacksonville",
    "sg:classifiers":[
        {
            "category":"Personal",
            "subcategory":"Beauty Salon",
            "type":"Services"
        }
    ],
    "sg:phone":"+1 904 475 1420",
    "sg:postcode":"32209",
    "sg:province":"FL",
    "wof:name":"Kiwi Hair",
    "wof:placetype":"venue"
},
  "geometry": {"coordinates":[-81.674311,30.357491],"type":"Point"}
}