{
  "type": "Feature",
  "properties": {
    "addr:full":"5205 NW 39th Ave Gainesville FL 32606",
    "addr:housenumber":"5205",
    "addr:postcode":"32606",
    "addr:street":"Nw 39Th Ave",
    "iso:country":"US",
    "sg:address":"5205 NW 39th Ave",
    "sg:city":"Gainesville",
    "sg:classifiers":[
        {
            "category":"Food & Beverages",
            "subcategory":"Bakery",
            "type":"Retail Goods"
        }
    ],
    "sg:phone":"+1 352 375 0376",
    "sg:postcode":"32606",
    "sg:province":"FL",
    "sg:tags":[
        "doughnut"
    ],
    "sg:website":"www.donutconnection.com",
    "wof:name":"Donut Connection",
    "wof:placetype":"venue"
},
  "geometry": {"coordinates":[-82.39791700000001,29.688597],"type":"Point"}
}