{
  "type": "Feature",
  "properties": {
    "addr:full":"675 E 45th St Hialeah FL 33013",
    "addr:housenumber":"675",
    "addr:postcode":"33013",
    "addr:street":"E 45Th St",
    "iso:country":"US",
    "sg:address":"675 E 45th St",
    "sg:city":"Hialeah",
    "sg:classifiers":[
        {
            "category":"Professional",
            "type":"Services"
        }
    ],
    "sg:phone":"+1 305 688 4622",
    "sg:postcode":"33013",
    "sg:province":"FL",
    "wof:name":"R Montenegro Inc",
    "wof:placetype":"venue"
},
  "geometry": {"coordinates":[-80.270054,25.863624],"type":"Point"}
}