{
  "type": "Feature",
  "properties": {
    "addr:full":"12351 49th St N Clearwater FL 33762",
    "addr:housenumber":"12351",
    "addr:postcode":"33762",
    "addr:street":"49Th St N",
    "iso:country":"US",
    "sg:address":"12351 49th St N",
    "sg:city":"Clearwater",
    "sg:classifiers":[
        {
            "category":"Autos & Motor Vehicles",
            "subcategory":"Automobile Sales",
            "type":"Retail Goods"
        }
    ],
    "sg:phone":"+1 727 556 0335",
    "sg:postcode":"33762",
    "sg:province":"FL",
    "sg:tags":[
        "used"
    ],
    "sg:website":"www.autoxtc.com",
    "wof:name":"Auto XTC",
    "wof:placetype":"venue"
},
  "geometry": {"coordinates":[-82.700245,27.883216],"type":"Point"}
}