{
  "type": "Feature",
  "properties": {
    "addr:full":"4344 Peters Rd Plantation FL 33317",
    "addr:housenumber":"4344",
    "addr:postcode":"33317",
    "addr:street":"Peters Rd",
    "iso:country":"US",
    "sg:address":"4344 Peters Rd",
    "sg:city":"Plantation",
    "sg:classifiers":[
        {
            "category":"Retail",
            "subcategory":"Auto Repair",
            "type":"Services"
        }
    ],
    "sg:phone":"+1 954 583 2277",
    "sg:postcode":"33317",
    "sg:province":"FL",
    "sg:tags":[
        "repairing",
        "automobile"
    ],
    "wof:name":"Certified Automotive Repair",
    "wof:placetype":"venue"
},
  "geometry": {"coordinates":[-80.20637600000001,26.104284],"type":"Point"}
}