{
  "type": "Feature",
  "properties": {
    "addr:full":"1401 E Gary Rd Lakeland FL 33801",
    "addr:housenumber":"1401",
    "addr:postcode":"33801",
    "addr:street":"E Gary Rd",
    "iso:country":"US",
    "sg:address":"1401 E Gary Rd",
    "sg:city":"Lakeland",
    "sg:classifiers":[
        {
            "category":"Bars & Pubs",
            "type":"Food & Drink"
        }
    ],
    "sg:phone":"+1 863 687 1733",
    "sg:postcode":"33801",
    "sg:province":"FL",
    "sg:tags":[
        "drinking"
    ],
    "wof:name":"Buds Place",
    "wof:placetype":"venue"
},
  "geometry": {"coordinates":[-81.93647,28.049593],"type":"Point"}
}