{
  "type": "Feature",
  "properties": {
    "iso:country":"US",
    "sg:address":"836 W 18th St",
    "sg:city":"Hialeah",
    "sg:classifiers":[
        {
            "category":"Home & Garden",
            "subcategory":"Building Materials",
            "type":"Retail Goods"
        },
        {
            "category":"Manufacturing",
            "subcategory":"Building Materials",
            "type":"Manufacturing & Wholesale Goods"
        }
    ],
    "sg:phone":"+1 305 863 9444",
    "sg:postcode":"33010",
    "sg:province":"FL",
    "sg:tags":[
        "solid",
        "top",
        "counter",
        "surface"
    ],
    "wof:name":"Veloz Counter Top & Granite",
    "wof:placetype":"venue"
},
  "geometry": {"coordinates":[-80.300178,25.838001],"type":"Point"}
}