{
  "type": "Feature",
  "properties": {
    "iso:country":"US",
    "sg:address":"2462 SW 27th Ln",
    "sg:city":"Miami",
    "sg:classifiers":[
        {
            "category":"Professional",
            "subcategory":"Accounting & Tax Preparation",
            "type":"Services"
        }
    ],
    "sg:phone":"+1 305 860 4805",
    "sg:postcode":"33133",
    "sg:province":"FL",
    "wof:name":"San Juan Accounting Services",
    "wof:placetype":"venue"
},
  "geometry": {"coordinates":[-80.235884,25.739917],"type":"Point"}
}