{
  "type": "Feature",
  "properties": {
    "addr:full":"1635 US Hwy 1 S St Augustine FL 32084",
    "addr:housenumber":"1635",
    "addr:postcode":"32084",
    "addr:street":"Us Hwy 1 S St",
    "iso:country":"US",
    "sg:address":"1635 US Hwy 1 S",
    "sg:city":"St Augustine",
    "sg:classifiers":[
        {
            "category":"Real Estate",
            "subcategory":"Developer",
            "type":"Services"
        }
    ],
    "sg:phone":"+1 904 824 6680",
    "sg:postcode":"32084",
    "sg:province":"FL",
    "sg:tags":[
        "cemetery"
    ],
    "wof:name":"San Lorenzo Cemetery",
    "wof:placetype":"venue"
},
  "geometry": {"coordinates":[-81.323345,29.872109],"type":"Point"}
}