{
  "type": "Feature",
  "properties": {
    "iso:country":"US",
    "sg:address":"3225 Hickory Creek Ln",
    "sg:city":"Brooksville",
    "sg:classifiers":[
        {
            "category":"Freight",
            "type":"Transportation"
        }
    ],
    "sg:phone":"+1 352 540 9992",
    "sg:postcode":"34602",
    "sg:province":"FL",
    "sg:tags":[
        "local",
        "storage",
        "trucking"
    ],
    "wof:name":"Sears Transportation Inc",
    "wof:placetype":"venue"
},
  "geometry": {"coordinates":[-82.300444,28.480036],"type":"Point"}
}