{
  "type": "Feature",
  "properties": {
    "iso:country":"US",
    "sg:address":"4622 Siesta Cir",
    "sg:city":"Fort Myers",
    "sg:classifiers":[
        {
            "category":"Building & Trades",
            "subcategory":"Plumbing",
            "type":"Services"
        }
    ],
    "sg:phone":"+1 239 931 4433",
    "sg:postcode":"33901",
    "sg:province":"FL",
    "sg:tags":[
        "contractor"
    ],
    "wof:name":"Extreme Plumbing Inc",
    "wof:placetype":"venue"
},
  "geometry": {"coordinates":[-81.887068,26.599887],"type":"Point"}
}