{
  "type": "Feature",
  "properties": {
    "addr:full":"1676 Anne Dr Middleburg FL 32068",
    "addr:housenumber":"1676",
    "addr:postcode":"32068",
    "addr:street":"Anne Dr",
    "iso:country":"US",
    "sg:address":"1676 Anne Dr",
    "sg:city":"Middleburg",
    "sg:classifiers":[
        {
            "category":"Building & Trades",
            "subcategory":"Construction",
            "type":"Services"
        }
    ],
    "sg:phone":"+1 904 375 0127",
    "sg:postcode":"32068",
    "sg:province":"FL",
    "sg:tags":[
        "general",
        "contractor"
    ],
    "wof:name":"Herman E Ricks Concrete Constr",
    "wof:placetype":"venue"
},
  "geometry": {"coordinates":[-81.78657,30.10767],"type":"Point"}
}