{
  "type": "Feature",
  "properties": {
    "addr:full":"2135 NW 93rd Ter Miami FL 33147",
    "addr:housenumber":"2135",
    "addr:postcode":"33147",
    "addr:street":"Nw 93Rd Ter",
    "iso:country":"US",
    "sg:address":"2135 NW 93rd Ter",
    "sg:city":"Miami",
    "sg:classifiers":[
        {
            "category":"Freight",
            "type":"Transportation"
        }
    ],
    "sg:phone":"+1 305 693 3626",
    "sg:postcode":"33147",
    "sg:province":"FL",
    "sg:tags":[
        "operator",
        "local",
        "trucking"
    ],
    "wof:name":"N & P Backhoe & Hauling",
    "wof:placetype":"venue"
},
  "geometry": {"coordinates":[-80.233405,25.859552],"type":"Point"}
}