{
  "type": "Feature",
  "properties": {
    "addr:full":"209 Thompson Ave Cocoa FL 32922",
    "addr:housenumber":"209",
    "addr:postcode":"32922",
    "addr:street":"Thompson Ave",
    "iso:country":"US",
    "sg:address":"209 Thompson Ave",
    "sg:city":"Cocoa",
    "sg:classifiers":[
        {
            "category":"Building & Trades",
            "subcategory":"Plumbing",
            "type":"Services"
        }
    ],
    "sg:phone":"+1 321 690 1242",
    "sg:postcode":"32922",
    "sg:province":"FL",
    "sg:tags":[
        "mechanical",
        "contractor"
    ],
    "wof:name":"RMC",
    "wof:placetype":"venue"
},
  "geometry": {"coordinates":[-80.752864,28.359654],"type":"Point"}
}