{
  "type": "Feature",
  "properties": {
    "addr:full":"901 N Pompano Ave Sarasota FL 34237",
    "addr:housenumber":"901",
    "addr:postcode":"34237",
    "addr:street":"N Pompano Ave",
    "iso:country":"US",
    "sg:address":"901 N Pompano Ave",
    "sg:city":"Sarasota",
    "sg:classifiers":[
        {
            "category":"Recreation",
            "type":"Entertainment"
        }
    ],
    "sg:phone":"+1 941 953 5925",
    "sg:postcode":"34237",
    "sg:province":"FL",
    "sg:tags":[
        "club",
        "membership"
    ],
    "wof:name":"Sarasota Babe Ruth League",
    "wof:placetype":"venue"
},
  "geometry": {"coordinates":[-82.507875,27.343731],"type":"Point"}
}