{
  "type": "Feature",
  "properties": {
    "iso:country":"US",
    "sg:address":"1714 State Hwy 13",
    "sg:city":"Jacksonville",
    "sg:classifiers":[
        {
            "category":"Professional",
            "subcategory":"Business Services",
            "type":"Services"
        }
    ],
    "sg:phone":"+1 904 287 2525",
    "sg:postcode":"32259",
    "sg:province":"FL",
    "sg:tags":[
        "conference",
        "coordinator",
        "seminar"
    ],
    "sg:website":"www.marywoodcenter.org",
    "wof:name":"Marywood Retreat Ctr",
    "wof:placetype":"venue"
},
  "geometry": {"coordinates":[-81.63633,30.084604],"type":"Point"}
}