{
  "type": "Feature",
  "properties": {
    "iso:country":"US",
    "sg:address":"5001 N University Dr",
    "sg:city":"Fort Lauderdale",
    "sg:classifiers":[
        {
            "category":"Restaurant",
            "type":"Food & Drink"
        }
    ],
    "sg:menulink":"http://www.allmenus.com/fl/plantation/209856-miami-subs-grill/menu/",
    "sg:phone":"+1 954 748 0900",
    "sg:postcode":"33351",
    "sg:province":"FL",
    "sg:tags":[
        "wrap",
        "american",
        "sandwich"
    ],
    "wof:name":"Miami Subs Grill",
    "wof:placetype":"venue"
},
  "geometry": {"coordinates":[-80.25202299999999,26.188169],"type":"Point"}
}