{
  "type": "Feature",
  "properties": {
    "iso:country":"US",
    "sg:address":"4732 Dolphin Cay Ln",
    "sg:city":"St Petersburg",
    "sg:classifiers":[
        {
            "category":"Real Estate",
            "subcategory":"Real Estate Operator",
            "type":"Services"
        }
    ],
    "sg:phone":"+1 727 864 1186",
    "sg:postcode":"33711",
    "sg:province":"FL",
    "sg:tags":[
        "condominium"
    ],
    "sg:website":"www.dolphincay.com",
    "wof:name":"Dolphin Cay Property Owners",
    "wof:placetype":"venue"
},
  "geometry": {"coordinates":[-82.692819,27.723842],"type":"Point"}
}