{
  "type": "Feature",
  "properties": {
    "addr:full":"4939 Erin Ln Melbourne FL 32940",
    "addr:housenumber":"4939",
    "addr:postcode":"32940",
    "addr:street":"Erin Ln",
    "iso:country":"US",
    "sg:address":"4939 Erin Ln",
    "sg:city":"Melbourne",
    "sg:classifiers":[
        {
            "category":"Professional",
            "type":"Services"
        }
    ],
    "sg:phone":"+1 321 259 5265",
    "sg:postcode":"32940",
    "sg:province":"FL",
    "wof:name":"Triple JM Corporation",
    "wof:placetype":"venue"
},
  "geometry": {"coordinates":[-80.66495999999999,28.190771],"type":"Point"}
}