{
  "type": "Feature",
  "properties": {
    "iso:country":"US",
    "sg:address":"5836 92nd Ter N",
    "sg:city":"Pinellas Park",
    "sg:classifiers":[
        {
            "category":"Building & Trades",
            "subcategory":"Construction",
            "type":"Services"
        }
    ],
    "sg:phone":"+1 727 546 4961",
    "sg:postcode":"33782",
    "sg:province":"FL",
    "sg:tags":[
        "hanging",
        "contractor"
    ],
    "wof:name":"Kellys Painting",
    "wof:placetype":"venue"
},
  "geometry": {"coordinates":[-82.71379899999999,27.856026],"type":"Point"}
}