{
  "type": "Feature",
  "properties": {
    "addr:full":"10 SE 1st Ave Delray Beach FL 33444",
    "addr:housenumber":"10",
    "addr:postcode":"33444",
    "addr:street":"Se 1St Ave",
    "iso:country":"US",
    "sg:address":"10 SE 1st Ave",
    "sg:city":"Delray Beach",
    "sg:classifiers":[
        {
            "category":"Professional",
            "type":"Services"
        }
    ],
    "sg:phone":"+1 561 243 3121",
    "sg:postcode":"33444",
    "sg:province":"FL",
    "sg:tags":[
        "establishment"
    ],
    "wof:name":"Fund Development Assoc",
    "wof:placetype":"venue"
},
  "geometry": {"coordinates":[-80.072132,26.459969],"type":"Point"}
}