{
  "type": "Feature",
  "properties": {
    "addr:full":"7022 NW 10th Pl Gainesville FL 32605",
    "addr:housenumber":"7022",
    "addr:postcode":"32605",
    "addr:street":"Nw 10Th Pl",
    "iso:country":"US",
    "sg:address":"7022 NW 10th Pl",
    "sg:city":"Gainesville",
    "sg:classifiers":[
        {
            "category":"Government",
            "subcategory":"Office",
            "type":"Public Place"
        }
    ],
    "sg:phone":"+1 352 331 3990",
    "sg:postcode":"32605",
    "sg:province":"FL",
    "sg:tags":[
        "federal",
        "program"
    ],
    "wof:name":"US Agricultural Dept",
    "wof:placetype":"venue"
},
  "geometry": {"coordinates":[-82.417671,29.662166],"type":"Point"}
}