{
  "type": "Feature",
  "properties": {
    "addr:full":"4186 Kings Hwy Port Charlotte FL 33980",
    "addr:housenumber":"4186",
    "addr:postcode":"33980",
    "addr:street":"Kings Hwy",
    "iso:country":"US",
    "sg:address":"4186 Kings Hwy",
    "sg:city":"Port Charlotte",
    "sg:classifiers":[
        {
            "category":"Home & Garden",
            "subcategory":"Carpets & Floor Coverings",
            "type":"Retail Goods"
        }
    ],
    "sg:phone":"+1 941 625 1115",
    "sg:postcode":"33980",
    "sg:province":"FL",
    "sg:tags":[
        "dealer",
        "rug"
    ],
    "wof:name":"Accent Carpets",
    "wof:placetype":"venue"
},
  "geometry": {"coordinates":[-82.06662300000001,26.972167],"type":"Point"}
}