{
  "type": "Feature",
  "properties": {
    "addr:full":"1820 SE 39 Ter Gainesville FL 32641",
    "addr:housenumber":"1820;39 ter",
    "addr:postcode":"32641",
    "addr:street":"Se",
    "iso:country":"US",
    "sg:address":"1820 SE 39 Ter",
    "sg:city":"Gainesville",
    "sg:classifiers":[
        {
            "category":"Professional",
            "subcategory":"Business Services",
            "type":"Services"
        }
    ],
    "sg:phone":"+1 352 336 4548",
    "sg:postcode":"32641",
    "sg:province":"FL",
    "sg:tags":[
        "sales"
    ],
    "wof:name":"Stuffin Shop  The",
    "wof:placetype":"venue"
},
  "geometry": {"coordinates":[-82.27621000000001,29.634421],"type":"Point"}
}