{
  "type": "Feature",
  "properties": {
    "iso:country":"US",
    "sg:address":"759 University Blvd N",
    "sg:city":"Jacksonville",
    "sg:classifiers":[
        {
            "category":"Personal",
            "subcategory":"Beauty Salon",
            "type":"Services"
        }
    ],
    "sg:phone":"+1 904 743 7878",
    "sg:postcode":"32211",
    "sg:province":"FL",
    "wof:name":"Me & Mc Ghee Beauty Salon",
    "wof:placetype":"venue"
},
  "geometry": {"coordinates":[-81.60453200000001,30.326788],"type":"Point"}
}