{
  "type": "Feature",
  "properties": {
    "addr:full":"103 St James St Carrabelle FL 32346",
    "addr:housenumber":"103",
    "addr:postcode":"32346",
    "addr:street":"St James St",
    "iso:country":"US",
    "sg:address":"103 St James St",
    "sg:city":"Carrabelle",
    "sg:classifiers":[
        {
            "category":"Shopping",
            "subcategory":"Bicycles & Sporting Goods",
            "type":"Retail Goods"
        }
    ],
    "sg:phone":"+1 850 697 9232",
    "sg:postcode":"32346",
    "sg:province":"FL",
    "sg:tags":[
        "tackle",
        "fishing"
    ],
    "wof:name":"Frank's Bait & Tackle",
    "wof:placetype":"venue"
},
  "geometry": {"coordinates":[-84.42128200000001,29.986903],"type":"Point"}
}