{
  "type": "Feature",
  "properties": {
    "iso:country":"US",
    "sg:address":"11903 Turkey Rd",
    "sg:city":"Jacksonville",
    "sg:classifiers":[
        {
            "category":"Home & Garden",
            "subcategory":"Building Materials",
            "type":"Retail Goods"
        }
    ],
    "sg:phone":"+1 904 781 7602",
    "sg:postcode":"32221",
    "sg:province":"FL",
    "sg:tags":[
        "screen",
        "window"
    ],
    "wof:name":"Safari Screens Of Jacksonville",
    "wof:placetype":"venue"
},
  "geometry": {"coordinates":[-81.869536,30.296304],"type":"Point"}
}