{
  "type": "Feature",
  "properties": {
    "iso:country":"US",
    "sg:address":"3350 Commercial Way",
    "sg:city":"Spring Hill",
    "sg:classifiers":[
        {
            "category":"Organizations",
            "subcategory":"Religious Organization",
            "type":"Services"
        }
    ],
    "sg:phone":"+1 352 686 8880",
    "sg:postcode":"34606",
    "sg:province":"FL",
    "sg:tags":[
        "church"
    ],
    "sg:website":"www.nblc.org",
    "wof:name":"New Beginning Life Ctr",
    "wof:placetype":"venue"
},
  "geometry": {"coordinates":[-82.608762,28.480827],"type":"Point"}
}