{
  "type": "Feature",
  "properties": {
    "addr:full":"204 McLean Pt Winter Haven FL 33884",
    "addr:housenumber":"204",
    "addr:postcode":"33884",
    "addr:street":"Mclean Pt",
    "iso:country":"US",
    "sg:address":"204 McLean Pt",
    "sg:city":"Winter Haven",
    "sg:classifiers":[
        {
            "category":"Banks & Credit Unions",
            "subcategory":"Financial Services",
            "type":"Services"
        }
    ],
    "sg:phone":"+1 863 875 1775",
    "sg:postcode":"33884",
    "sg:province":"FL",
    "sg:tags":[
        "investment",
        "closed"
    ],
    "wof:name":"Wintou R Robert A",
    "wof:placetype":"venue"
},
  "geometry": {"coordinates":[-81.683539,27.966405],"type":"Point"}
}