{
  "type": "Feature",
  "properties": {
    "addr:full":"11112 San Jose Blvd Jacksonville FL 32223",
    "addr:housenumber":"11112",
    "addr:postcode":"32223",
    "addr:street":"San Jose Blvd",
    "iso:country":"US",
    "sg:address":"11112 San Jose Blvd",
    "sg:city":"Jacksonville",
    "sg:classifiers":[
        {
            "category":"Shopping",
            "subcategory":"Used Merchandise",
            "type":"Retail Goods"
        },
        {
            "category":"Shopping",
            "subcategory":"Clothing, Apparel, & Fashions",
            "type":"Retail Goods"
        }
    ],
    "sg:phone":"+1 904 886 7071",
    "sg:postcode":"32223",
    "sg:province":"FL",
    "sg:tags":[
        "new",
        "infant",
        "furnishing",
        "wear"
    ],
    "wof:name":"Once Upon A Child",
    "wof:placetype":"venue"
},
  "geometry": {"coordinates":[-81.628529,30.173664],"type":"Point"}
}