{
  "type": "Feature",
  "properties": {
    "iso:country":"US",
    "sg:address":"1442 SE 13th St",
    "sg:city":"Fort Lauderdale",
    "sg:classifiers":[
        {
            "category":"Freight",
            "type":"Transportation"
        }
    ],
    "sg:phone":"+1 772 546 2912",
    "sg:postcode":"33316",
    "sg:province":"FL",
    "sg:tags":[
        "shipping",
        "agent",
        "purchasing"
    ],
    "wof:name":"Tamarind Consolidated & Assoc",
    "wof:placetype":"venue"
},
  "geometry": {"coordinates":[-80.128748,26.105629],"type":"Point"}
}