{
  "type": "Feature",
  "properties": {
    "addr:full":"2530 W 2nd Ave Hialeah FL 33010",
    "addr:housenumber":"2530",
    "addr:postcode":"33010",
    "addr:street":"W 2Nd Ave",
    "iso:country":"US",
    "sg:address":"2530 W 2nd Ave",
    "sg:city":"Hialeah",
    "sg:classifiers":[
        {
            "category":"Recreation",
            "subcategory":"Dog Park",
            "type":"Entertainment"
        },
        {
            "category":"Shopping",
            "subcategory":"Pets & Pet Supplies",
            "type":"Retail Goods"
        },
        {
            "category":"Retail",
            "subcategory":"Pet Boarding",
            "type":"Services"
        }
    ],
    "sg:phone":"+1 305 885 3623",
    "sg:postcode":"33010",
    "sg:province":"FL",
    "sg:tags":[
        "training",
        "sitting",
        "specialty",
        "kennel",
        "boarding/pet",
        "day",
        "care"
    ],
    "sg:website":"http://WWW.WOLFFSKENNELINC.COM",
    "wof:name":"WOLLF'S KENNEL INC . K-9 Boarding & Training Center",
    "wof:placetype":"venue"
},
  "geometry": {"coordinates":[-80.28600299999999,25.8449],"type":"Point"}
}