{
  "type": "Feature",
  "properties": {
    "iso:country":"US",
    "sg:address":"985 S Mill Ave",
    "sg:city":"Bartow",
    "sg:classifiers":[
        {
            "category":"Building & Trades",
            "subcategory":"Landscaping Services",
            "type":"Services"
        }
    ],
    "sg:phone":"+1 863 533 5253",
    "sg:postcode":"33830",
    "sg:province":"FL",
    "wof:name":"Double N Grassing",
    "wof:placetype":"venue"
},
  "geometry": {"coordinates":[-81.846531,27.888022],"type":"Point"}
}