{
  "type": "Feature",
  "properties": {
    "iso:country":"US",
    "sg:address":"12751 el Clair Ranch Rd",
    "sg:city":"Boynton Beach",
    "sg:classifiers":[
        {
            "category":"Organizations",
            "subcategory":"Community Association",
            "type":"Services"
        }
    ],
    "sg:phone":"+1 561 637 4315",
    "sg:postcode":"33437",
    "sg:province":"FL",
    "wof:name":"Coral Lakes Club",
    "wof:placetype":"venue"
},
  "geometry": {"coordinates":[-80.139081,26.489024],"type":"Point"}
}