{
  "type": "Feature",
  "properties": {
    "iso:country":"US",
    "sg:address":"2225 Carib Cir",
    "sg:city":"Palm Beach Gardens",
    "sg:classifiers":[
        {
            "category":"Sports & Exercise",
            "subcategory":"Gym",
            "type":"Entertainment"
        }
    ],
    "sg:phone":"+1 561 627 9052",
    "sg:postcode":"33410",
    "sg:province":"FL",
    "sg:tags":[
        "fitness",
        "physical",
        "facility"
    ],
    "wof:name":"True Fitness Technology Inc",
    "wof:placetype":"venue"
},
  "geometry": {"coordinates":[-80.07142399999999,26.856462],"type":"Point"}
}