{
  "type": "Feature",
  "properties": {
    "iso:country":"US",
    "sg:address":"699 Beal Pkwy NW",
    "sg:city":"Fort Walton Beach",
    "sg:classifiers":[
        {
            "category":"Shopping",
            "type":"Retail Goods"
        }
    ],
    "sg:phone":"+1 850 864 3640",
    "sg:postcode":"32547",
    "sg:province":"FL",
    "sg:tags":[
        "pool",
        "swimming"
    ],
    "wof:name":"Pinch A Penny 109",
    "wof:placetype":"venue"
},
  "geometry": {"coordinates":[-86.639122,30.434893],"type":"Point"}
}