{
  "type": "Feature",
  "properties": {
    "addr:full":"1808 Garvin St Orlando FL 32803",
    "addr:housenumber":"1808",
    "addr:postcode":"32803",
    "addr:street":"Garvin St",
    "iso:country":"US",
    "sg:address":"1808 Garvin St",
    "sg:city":"Orlando",
    "sg:classifiers":[
        {
            "category":"Retail",
            "subcategory":"Portrait Studio",
            "type":"Services"
        }
    ],
    "sg:phone":"+1 407 895 8488",
    "sg:postcode":"32803",
    "sg:province":"FL",
    "sg:tags":[
        "photographer"
    ],
    "wof:name":"Joanne Carole Photography",
    "wof:placetype":"venue"
},
  "geometry": {"coordinates":[-81.356314,28.557637],"type":"Point"}
}