{
  "type": "Feature",
  "properties": {
    "addr:full":"8040 Tatum Waterway Dr Miami Beach FL 33141",
    "addr:housenumber":"8040",
    "addr:postcode":"33141",
    "addr:street":"Tatum Waterway Dr",
    "iso:country":"US",
    "sg:address":"8040 Tatum Waterway Dr",
    "sg:city":"Miami Beach",
    "sg:classifiers":[
        {
            "category":"Building & Trades",
            "subcategory":"Construction",
            "type":"Services"
        }
    ],
    "sg:phone":"+1 305 864 9444",
    "sg:postcode":"33141",
    "sg:province":"FL",
    "sg:tags":[
        "roofing",
        "contractor"
    ],
    "wof:name":"Campbell Roofing & Constr",
    "wof:placetype":"venue"
},
  "geometry": {"coordinates":[-80.124692,25.865376],"type":"Point"}
}