{
  "type": "Feature",
  "properties": {
    "addr:full":"14426 Middle Fairway Dr Spring Hill FL 34609",
    "addr:housenumber":"14426",
    "addr:postcode":"34609",
    "addr:street":"Middle Fairway Dr",
    "iso:country":"US",
    "sg:address":"14426 Middle Fairway Dr",
    "sg:city":"Spring Hill",
    "sg:classifiers":[
        {
            "category":"Real Estate",
            "subcategory":"Real Estate Agent",
            "type":"Services"
        }
    ],
    "sg:phone":"+1 352 754 9797",
    "sg:postcode":"34609",
    "sg:province":"FL",
    "wof:name":"Schickedanz Bros Inc",
    "wof:placetype":"venue"
},
  "geometry": {"coordinates":[-82.48377499999999,28.496403],"type":"Point"}
}