{
  "type": "Feature",
  "properties": {
    "iso:country":"US",
    "sg:address":"143 S Cypress Rd",
    "sg:city":"Pompano Beach",
    "sg:classifiers":[
        {
            "category":"Restaurant",
            "type":"Food & Drink"
        }
    ],
    "sg:phone":"+1 954 942 8778",
    "sg:postcode":"33060",
    "sg:province":"FL",
    "wof:name":"Sub Spot",
    "wof:placetype":"venue"
},
  "geometry": {"coordinates":[-80.123187,26.229371],"type":"Point"}
}