{
  "type": "Feature",
  "properties": {
    "addr:full":"2255 Southwind Ln Largo FL 33771",
    "addr:housenumber":"2255",
    "addr:postcode":"33771",
    "addr:street":"Southwind Ln",
    "iso:country":"US",
    "sg:address":"2255 Southwind Ln",
    "sg:city":"Largo",
    "sg:classifiers":[
        {
            "category":"Retail",
            "subcategory":"Auto Repair",
            "type":"Services"
        }
    ],
    "sg:phone":"+1 727 584 6472",
    "sg:postcode":"33771",
    "sg:province":"FL",
    "sg:tags":[
        "repairing",
        "automobile"
    ],
    "wof:name":"Barnes & Barnes Automotive",
    "wof:placetype":"venue"
},
  "geometry": {"coordinates":[-82.768958,27.896191],"type":"Point"}
}