{
  "type": "Feature",
  "properties": {
    "addr:full":"4759 Bocaire Blvd Boca Raton FL 33487",
    "addr:housenumber":"4759",
    "addr:postcode":"33487",
    "addr:street":"Bocaire Blvd",
    "iso:country":"US",
    "sg:address":"4759 Bocaire Blvd",
    "sg:city":"Boca Raton",
    "sg:classifiers":[
        {
            "category":"Banks & Credit Unions",
            "subcategory":"Financial Services",
            "type":"Services"
        }
    ],
    "sg:phone":"+1 561 995 9280",
    "sg:postcode":"33487",
    "sg:province":"FL",
    "sg:tags":[
        "company",
        "holding"
    ],
    "wof:name":"Tulgan Associates LP",
    "wof:placetype":"venue"
},
  "geometry": {"coordinates":[-80.120143,26.420912],"type":"Point"}
}