{
  "type": "Feature",
  "properties": {
    "iso:country":"US",
    "sg:address":"1244 Taylor St",
    "sg:city":"Auburndale",
    "sg:classifiers":[
        {
            "category":"Freight",
            "type":"Transportation"
        }
    ],
    "sg:phone":"+1 863 666 2470",
    "sg:postcode":"33823",
    "sg:province":"FL",
    "sg:tags":[
        "concrete",
        "haul",
        "co",
        "hauling"
    ],
    "wof:name":"R & D Transport",
    "wof:placetype":"venue"
},
  "geometry": {"coordinates":[-81.846221,28.04683],"type":"Point"}
}