{
  "type": "Feature",
  "properties": {
    "addr:full":"759 NE 69th St Miami FL 33138",
    "addr:housenumber":"759",
    "addr:postcode":"33138",
    "addr:street":"Ne 69Th St",
    "iso:country":"US",
    "sg:address":"759 NE 69th St",
    "sg:city":"Miami",
    "sg:classifiers":[
        {
            "category":"Professional",
            "subcategory":"Business Services",
            "type":"Services"
        }
    ],
    "sg:phone":"+1 305 759 0001",
    "sg:postcode":"33138",
    "sg:province":"FL",
    "sg:tags":[
        "event"
    ],
    "wof:name":"Arena Eagle Events LLC",
    "wof:placetype":"venue"
},
  "geometry": {"coordinates":[-80.18028200000001,25.839367],"type":"Point"}
}