{
  "type": "Feature",
  "properties": {
    "addr:full":"1235 Ariana St Lakeland FL 33803",
    "addr:housenumber":"1235",
    "addr:postcode":"33803",
    "addr:street":"Ariana St",
    "iso:country":"US",
    "sg:address":"1235 Ariana St",
    "sg:city":"Lakeland",
    "sg:classifiers":[
        {
            "category":"Banks & Credit Unions",
            "subcategory":"Bank",
            "type":"Services"
        }
    ],
    "sg:phone":"+1 863 687 4166",
    "sg:postcode":"33803",
    "sg:province":"FL",
    "sg:tags":[
        "federal"
    ],
    "wof:name":"Florida Central Credit Union",
    "wof:placetype":"venue"
},
  "geometry": {"coordinates":[-81.97493799999999,28.025893],"type":"Point"}
}