{
  "type": "Feature",
  "properties": {
    "addr:full":"1670 Daniels Dr Fort Myers FL 33917",
    "addr:housenumber":"1670",
    "addr:postcode":"33917",
    "addr:street":"Daniels Dr",
    "iso:country":"US",
    "sg:address":"1670 Daniels Dr",
    "sg:city":"Fort Myers",
    "sg:classifiers":[
        {
            "category":"Building & Trades",
            "subcategory":"Construction",
            "type":"Services"
        }
    ],
    "sg:phone":"+1 239 995 3900",
    "sg:postcode":"33917",
    "sg:province":"FL",
    "sg:tags":[
        "tile",
        "dealer"
    ],
    "wof:name":"Wood's Constrution & Tile Inc",
    "wof:placetype":"venue"
},
  "geometry": {"coordinates":[-81.876986,26.680952],"type":"Point"}
}