{
  "type": "Feature",
  "properties": {
    "addr:full":"11456 Peachstone Ln Orlando FL 32821",
    "addr:housenumber":"11456",
    "addr:postcode":"32821",
    "addr:street":"Peachstone Ln",
    "iso:country":"US",
    "sg:address":"11456 Peachstone Ln",
    "sg:city":"Orlando",
    "sg:classifiers":[
        {
            "category":"Manufacturing",
            "subcategory":"Toys & Sporting Goods",
            "type":"Manufacturing & Wholesale Goods"
        }
    ],
    "sg:phone":"+1 407 823 6579",
    "sg:postcode":"32821",
    "sg:province":"FL",
    "sg:tags":[
        "mfg"
    ],
    "wof:name":"Roboflex Inc",
    "wof:placetype":"venue"
},
  "geometry": {"coordinates":[-81.44681199999999,28.398728],"type":"Point"}
}