{
  "type": "Feature",
  "properties": {
    "iso:country":"US",
    "sg:address":"6130 Florence St",
    "sg:city":"Gibsonton",
    "sg:classifiers":[
        {
            "category":"Social Services",
            "subcategory":"Child Care",
            "type":"Services"
        }
    ],
    "sg:phone":"+1 813 677 1598",
    "sg:postcode":"33534",
    "sg:province":"FL",
    "sg:tags":[
        "day"
    ],
    "wof:name":"Pre-School Academy Inc",
    "wof:placetype":"venue"
},
  "geometry": {"coordinates":[-82.383089,27.830062],"type":"Point"}
}