{
  "type": "Feature",
  "properties": {
    "addr:full":"11612 SW 127th Ter Miami FL 33176",
    "addr:housenumber":"11612",
    "addr:postcode":"33176",
    "addr:street":"Sw 127Th Ter",
    "iso:country":"US",
    "sg:address":"11612 SW 127th Ter",
    "sg:city":"Miami",
    "sg:classifiers":[
        {
            "category":"Professional",
            "subcategory":"Engineering",
            "type":"Services"
        }
    ],
    "sg:phone":"+1 305 254 0568",
    "sg:postcode":"33176",
    "sg:province":"FL",
    "wof:name":"Jem Engineering Svcs",
    "wof:placetype":"venue"
},
  "geometry": {"coordinates":[-80.381912,25.648964],"type":"Point"}
}