{
  "type": "Feature",
  "properties": {
    "iso:country":"US",
    "sg:address":"2754 Navigator Ave",
    "sg:city":"Sanford",
    "sg:classifiers":[
        {
            "category":"Building & Trades",
            "subcategory":"Construction",
            "type":"Services"
        }
    ],
    "sg:phone":"+1 407 322 8008",
    "sg:postcode":"32773",
    "sg:province":"FL",
    "sg:tags":[
        "maker",
        "cabinet"
    ],
    "wof:name":"Richard Leatherman Woodshop",
    "wof:placetype":"venue"
},
  "geometry": {"coordinates":[-81.254081,28.777469],"type":"Point"}
}