{
  "type": "Feature",
  "properties": {
    "addr:full":"13309 SW 124th St Miami FL 33186",
    "addr:housenumber":"13309",
    "addr:postcode":"33186",
    "addr:street":"Sw 124Th St",
    "iso:country":"US",
    "sg:address":"13309 SW 124th St",
    "sg:city":"Miami",
    "sg:classifiers":[
        {
            "category":"Professional",
            "subcategory":"Engineering",
            "type":"Services"
        }
    ],
    "sg:phone":"+1 305 760 6196",
    "sg:postcode":"33186",
    "sg:province":"FL",
    "sg:tags":[
        "consulting",
        "engineer"
    ],
    "wof:name":"Al Brizuela Engineering Inc",
    "wof:placetype":"venue"
},
  "geometry": {"coordinates":[-80.41057600000001,25.652488],"type":"Point"}
}