{
  "type": "Feature",
  "properties": {
    "addr:full":"1216 Golden Pond Ln Rockledge FL 32955",
    "addr:housenumber":"1216",
    "addr:postcode":"32955",
    "addr:street":"Golden Pond Ln",
    "iso:country":"US",
    "sg:address":"1216 Golden Pond Ln",
    "sg:city":"Rockledge",
    "sg:classifiers":[
        {
            "category":"Banks & Credit Unions",
            "subcategory":"Financial Services",
            "type":"Services"
        }
    ],
    "sg:phone":"+1 321 433 1182",
    "sg:postcode":"32955",
    "sg:province":"FL",
    "sg:tags":[
        "property",
        "investor"
    ],
    "wof:name":"Southast Inv Prpts Brevard Inc",
    "wof:placetype":"venue"
},
  "geometry": {"coordinates":[-80.73019499999999,28.300476],"type":"Point"}
}