{
  "type": "Feature",
  "properties": {
    "addr:full":"433 NE 191st St Miami FL 33179",
    "addr:housenumber":"433",
    "addr:postcode":"33179",
    "addr:street":"Ne 191St St",
    "iso:country":"US",
    "sg:address":"433 NE 191st St",
    "sg:city":"Miami",
    "sg:classifiers":[
        {
            "category":"Wholesale",
            "subcategory":"Non-durable Goods",
            "type":"Manufacturing & Wholesale Goods"
        }
    ],
    "sg:phone":"+1 305 249 0936",
    "sg:postcode":"33179",
    "sg:province":"FL",
    "wof:name":"Blessed Imports",
    "wof:placetype":"venue"
},
  "geometry": {"coordinates":[-80.190309,25.950514],"type":"Point"}
}