{
  "type": "Feature",
  "properties": {
    "addr:full":"257 S Cypress Rd Pompano Beach FL 33060",
    "addr:housenumber":"257",
    "addr:postcode":"33060",
    "addr:street":"S Cypress Rd",
    "iso:country":"US",
    "sg:address":"257 S Cypress Rd",
    "sg:city":"Pompano Beach",
    "sg:classifiers":[
        {
            "category":"Wholesale",
            "subcategory":"Construction Materials",
            "type":"Manufacturing & Wholesale Goods"
        },
        {
            "category":"Building & Trades",
            "subcategory":"Construction",
            "type":"Services"
        }
    ],
    "sg:phone":"+1 954 536 8483",
    "sg:postcode":"33060",
    "sg:province":"FL",
    "sg:tags":[
        "marble",
        "contractor"
    ],
    "wof:name":"S W Marble Restoration Inc",
    "wof:placetype":"venue"
},
  "geometry": {"coordinates":[-80.12327999999999,26.228434],"type":"Point"}
}