{
  "type": "Feature",
  "properties": {
    "iso:country":"US",
    "sg:address":"1324 E International Speedway Blvd Ste 7",
    "sg:city":"Deland",
    "sg:classifiers":[
        {
            "category":"Home & Garden",
            "subcategory":"Furniture",
            "type":"Retail Goods"
        }
    ],
    "sg:phone":"+1 386 736 6984",
    "sg:postcode":"32724",
    "sg:province":"FL",
    "sg:tags":[
        "store"
    ],
    "wof:name":"Childress John",
    "wof:placetype":"venue"
},
  "geometry": {"coordinates":[-81.278982,29.055954],"type":"Point"}
}