{
  "type": "Feature",
  "properties": {
    "iso:country":"US",
    "sg:address":"3940 B Rd",
    "sg:city":"Loxahatchee",
    "sg:classifiers":[
        {
            "category":"Retail",
            "subcategory":"Auto Repair",
            "type":"Services"
        }
    ],
    "sg:phone":"+1 561 640 0709",
    "sg:postcode":"33470",
    "sg:province":"FL",
    "sg:tags":[
        "towing"
    ],
    "wof:name":"J & B Towing",
    "wof:placetype":"venue"
},
  "geometry": {"coordinates":[-80.288425,26.734516],"type":"Point"}
}