{
  "type": "Feature",
  "properties": {
    "iso:country":"US",
    "sg:address":"819 Deltona Blvd",
    "sg:city":"Deltona",
    "sg:classifiers":[
        {
            "category":"Food & Beverages",
            "subcategory":"Groceries & Convenience Stores",
            "type":"Retail Goods"
        }
    ],
    "sg:phone":"+1 386 574 0327",
    "sg:postcode":"32725",
    "sg:province":"FL",
    "sg:tags":[
        "station",
        "gasoline"
    ],
    "wof:name":"Circle K Store",
    "wof:placetype":"venue"
},
  "geometry": {"coordinates":[-81.276039,28.888406],"type":"Point"}
}