{
  "type": "Feature",
  "properties": {
    "iso:country":"US",
    "sg:address":"1200 North Federal Highway Suite 200",
    "sg:city":"Boca Raton",
    "sg:classifiers":[
        {
            "category":"Professional",
            "subcategory":"Computer Services",
            "type":"Services"
        }
    ],
    "sg:phone":"+1 866 297 5070",
    "sg:postcode":"33432",
    "sg:province":"FL",
    "wof:name":"Safe Technologies International",
    "wof:placetype":"venue"
},
  "geometry": {"coordinates":[-80.077923,26.368022],"type":"Point"}
}