{
  "type": "Feature",
  "properties": {
    "iso:country":"US",
    "sg:address":"1221 SE 9th Ter",
    "sg:city":"Cape Coral",
    "sg:classifiers":[
        {
            "category":"Home & Garden",
            "subcategory":"Furniture",
            "type":"Retail Goods"
        }
    ],
    "sg:phone":"+1 239 573 8882",
    "sg:postcode":"33990",
    "sg:province":"FL",
    "sg:tags":[
        "store"
    ],
    "wof:name":"Fti Fine Home Interiors",
    "wof:placetype":"venue"
},
  "geometry": {"coordinates":[-81.947712,26.635205],"type":"Point"}
}