{
  "type": "Feature",
  "properties": {
    "iso:country":"US",
    "sg:address":"2619 5th St W",
    "sg:city":"Lehigh Acres",
    "sg:classifiers":[
        {
            "category":"Local Transit",
            "type":"Transportation"
        }
    ],
    "sg:phone":"+1 239 303 2427",
    "sg:postcode":"33971",
    "sg:province":"FL",
    "sg:tags":[
        "passenger"
    ],
    "wof:name":"Lerey Limosine Service",
    "wof:placetype":"venue"
},
  "geometry": {"coordinates":[-81.66485,26.616231],"type":"Point"}
}