{
  "type": "Feature",
  "properties": {
    "addr:full":"3970 S Pipkin Rd Lakeland FL 33811",
    "addr:housenumber":"3970",
    "addr:postcode":"33811",
    "addr:street":"S Pipkin Rd",
    "iso:country":"US",
    "sg:address":"3970 S Pipkin Rd",
    "sg:city":"Lakeland",
    "sg:classifiers":[
        {
            "category":"Professional",
            "subcategory":"Detective & Security Services",
            "type":"Services"
        },
        {
            "category":"Shopping",
            "subcategory":"Computers & Home Electronics",
            "type":"Retail Goods"
        }
    ],
    "sg:phone":"+1 863 583 3343",
    "sg:postcode":"33811",
    "sg:province":"FL",
    "sg:tags":[
        "control",
        "television",
        "monitoring",
        "system",
        "radio",
        "store"
    ],
    "sg:website":"http://www.camconn.com",
    "wof:name":"Cam Connections, Inc.",
    "wof:placetype":"venue"
},
  "geometry": {"coordinates":[-81.995971,27.993335],"type":"Point"}
}