{
  "type": "Feature",
  "properties": {
    "iso:country":"US",
    "sg:address":"11865 SW 24th Ter",
    "sg:city":"Miami",
    "sg:classifiers":[
        {
            "category":"Retail",
            "subcategory":"Repair Shop",
            "type":"Services"
        }
    ],
    "sg:phone":"+1 305 357 3665",
    "sg:postcode":"33175",
    "sg:province":"FL",
    "sg:tags":[
        "lock",
        "locksmith"
    ],
    "wof:name":"24 All Day Emergency Locksmith",
    "wof:placetype":"venue"
},
  "geometry": {"coordinates":[-80.386162,25.745744],"type":"Point"}
}