{
  "type": "Feature",
  "properties": {
    "iso:country":"US",
    "sg:address":"2851 E 8th Ave",
    "sg:city":"Hialeah",
    "sg:classifiers":[
        {
            "category":"Organizations",
            "subcategory":"Religious Organization",
            "type":"Services"
        }
    ],
    "sg:phone":"+1 305 693 0484",
    "sg:postcode":"33013",
    "sg:province":"FL",
    "wof:name":"Elim Exodus 15 27 Ciie",
    "wof:placetype":"venue"
},
  "geometry": {"coordinates":[-80.266066,25.848677],"type":"Point"}
}