{
  "type": "Feature",
  "properties": {
    "iso:country":"US",
    "sg:address":"33 N Garden Ave",
    "sg:city":"Clearwater",
    "sg:phone":"+1 727 584 8128",
    "sg:postcode":"33755",
    "sg:province":"FL",
    "wof:name":"Wakely & Associates",
    "wof:placetype":"venue"
},
  "geometry": {"coordinates":[-82.798686,27.96606],"type":"Point"}
}