{
  "type": "Feature",
  "properties": {
    "addr:full":"2869 Wood St Sarasota FL 34237",
    "addr:housenumber":"2869",
    "addr:postcode":"34237",
    "addr:street":"Wood St",
    "iso:country":"US",
    "sg:address":"2869 Wood St",
    "sg:city":"Sarasota",
    "sg:classifiers":[
        {
            "category":"Building & Trades",
            "subcategory":"Construction",
            "type":"Services"
        }
    ],
    "sg:phone":"+1 941 955 7112",
    "sg:postcode":"34237",
    "sg:province":"FL",
    "sg:tags":[
        "contractor"
    ],
    "wof:name":"Mullett Brothers",
    "wof:placetype":"venue"
},
  "geometry": {"coordinates":[-82.511169,27.328356],"type":"Point"}
}