{
  "type": "Feature",
  "properties": {
    "iso:country":"US",
    "sg:address":"3507 Plantation Dr",
    "sg:city":"Sarasota",
    "sg:classifiers":[
        {
            "category":"Retail",
            "subcategory":"Repair Shop",
            "type":"Services"
        }
    ],
    "sg:phone":"+1 941 362 4365",
    "sg:postcode":"34231",
    "sg:province":"FL",
    "wof:name":"Gold Works",
    "wof:placetype":"venue"
},
  "geometry": {"coordinates":[-82.498609,27.283589],"type":"Point"}
}