{
  "type": "Feature",
  "properties": {
    "iso:country":"US",
    "sg:address":"1090 NW 23rd St",
    "sg:city":"Miami",
    "sg:classifiers":[
        {
            "category":"Wholesale",
            "subcategory":"Medical Equipment & Supplies",
            "type":"Manufacturing & Wholesale Goods"
        },
        {
            "category":"Shopping",
            "subcategory":"Pharmacy",
            "type":"Retail Goods"
        }
    ],
    "sg:phone":"+1 305 633 6650",
    "sg:postcode":"33127",
    "sg:province":"FL",
    "sg:tags":[
        "pharmaceutical",
        "drugstore",
        "products-wholesale",
        "manufacturer"
    ],
    "wof:name":"Rex Discount Wholesale",
    "wof:placetype":"venue"
},
  "geometry": {"coordinates":[-80.212592,25.798736],"type":"Point"}
}