{
  "type": "Feature",
  "properties": {
    "iso:country":"US",
    "sg:address":"1701 3rd Ave S",
    "sg:city":"St Petersburg",
    "sg:classifiers":[
        {
            "category":"Professional",
            "subcategory":"Advertising",
            "type":"Services"
        }
    ],
    "sg:phone":"+1 727 329 1517",
    "sg:postcode":"33712",
    "sg:province":"FL",
    "sg:tags":[
        "mailing",
        "shipping"
    ],
    "sg:website":"www.jaggedpeak.com",
    "wof:name":"Jagged Peak",
    "wof:placetype":"venue"
},
  "geometry": {"coordinates":[-82.657656,27.768402],"type":"Point"}
}