{
  "type": "Feature",
  "properties": {
    "iso:country":"US",
    "sg:address":"2848 Natural Bridge Rd",
    "sg:city":"Tallahassee",
    "sg:classifiers":[
        {
            "category":"Building & Trades",
            "subcategory":"Construction",
            "type":"Services"
        }
    ],
    "sg:phone":"+1 850 210 1254",
    "sg:postcode":"32305",
    "sg:province":"FL",
    "sg:tags":[
        "carpentry",
        "carpenter",
        "contractor"
    ],
    "wof:name":"Smith's Custom Interior Trim",
    "wof:placetype":"venue"
},
  "geometry": {"coordinates":[-84.226781,30.307291],"type":"Point"}
}