{
  "type": "Feature",
  "properties": {
    "addr:full":"1950 NW 18th St Pompano Beach FL 33069",
    "addr:housenumber":"1950",
    "addr:postcode":"33069",
    "addr:street":"Nw 18Th St",
    "iso:country":"US",
    "sg:address":"1950 NW 18th St",
    "sg:city":"Pompano Beach",
    "sg:classifiers":[
        {
            "category":"Manufacturing",
            "subcategory":"Metals",
            "type":"Manufacturing & Wholesale Goods"
        }
    ],
    "sg:phone":"+1 954 968 3100",
    "sg:postcode":"33069",
    "sg:province":"FL",
    "sg:tags":[
        "fabricator",
        "sheet"
    ],
    "wof:name":"Copper Sales Inc",
    "wof:placetype":"venue"
},
  "geometry": {"coordinates":[-80.151528,26.252753],"type":"Point"}
}