{
  "type": "Feature",
  "properties": {
    "iso:country":"US",
    "sg:address":"1321 NE 163rd St",
    "sg:city":"North Miami Beach",
    "sg:classifiers":[
        {
            "category":"Shopping",
            "subcategory":"Clothing, Apparel, & Fashions",
            "type":"Retail Goods"
        }
    ],
    "sg:phone":"+1 305 354 2211",
    "sg:postcode":"33162",
    "sg:province":"FL",
    "sg:tags":[
        "accessory",
        "clothing",
        "women's"
    ],
    "wof:name":"Linen N More",
    "wof:placetype":"venue"
},
  "geometry": {"coordinates":[-80.173967,25.925583],"type":"Point"}
}