{
  "type": "Feature",
  "properties": {
    "addr:full":"7640 NW 186th St Hialeah FL 33015",
    "addr:housenumber":"7640",
    "addr:postcode":"33015",
    "addr:street":"Nw 186Th St",
    "iso:country":"US",
    "sg:address":"7640 NW 186th St",
    "sg:city":"Hialeah",
    "sg:classifiers":[
        {
            "category":"Social Services",
            "subcategory":"Child Care",
            "type":"Services"
        }
    ],
    "sg:phone":"+1 305 362 8222",
    "sg:postcode":"33015",
    "sg:province":"FL",
    "sg:tags":[
        "day"
    ],
    "wof:name":"Kiddie Corner Academy",
    "wof:placetype":"venue"
},
  "geometry": {"coordinates":[-80.32550000000001,25.9424],"type":"Point"}
}