{
  "type": "Feature",
  "properties": {
    "iso:country":"US",
    "sg:address":"5941 S University Dr",
    "sg:city":"Fort Lauderdale",
    "sg:classifiers":[
        {
            "category":"Restaurant",
            "type":"Food & Drink"
        }
    ],
    "sg:phone":"+1 954 252 5418",
    "sg:postcode":"33328",
    "sg:province":"FL",
    "sg:tags":[
        "eating"
    ],
    "wof:name":"Gran Chimu",
    "wof:placetype":"venue"
},
  "geometry": {"coordinates":[-80.251974,26.057776],"type":"Point"}
}