{
  "type": "Feature",
  "properties": {
    "addr:full":"17401 NE 114th Ave Waldo FL 32694",
    "addr:housenumber":"17401",
    "addr:postcode":"32694",
    "addr:street":"Ne 114Th Ave",
    "iso:country":"US",
    "sg:address":"17401 NE 114th Ave",
    "sg:city":"Waldo",
    "sg:classifiers":[
        {
            "category":"Professional",
            "subcategory":"Management & Consulting",
            "type":"Services"
        }
    ],
    "sg:phone":"+1 352 468 2003",
    "sg:postcode":"32694",
    "sg:province":"FL",
    "wof:name":"M & D Hanke Enterprises Inc",
    "wof:placetype":"venue"
},
  "geometry": {"coordinates":[-82.139572,29.76052],"type":"Point"}
}