{
  "type": "Feature",
  "properties": {
    "addr:full":"12 Waynel Cir SE Fort Walton Bch FL 32548",
    "addr:housenumber":"12",
    "addr:postcode":"32548",
    "addr:street":"Waynel Cir Se Fort",
    "iso:country":"US",
    "sg:address":"12 Waynel Cir SE",
    "sg:city":"Fort Walton Bch",
    "sg:classifiers":[
        {
            "category":"Real Estate",
            "subcategory":"Real Estate Agent",
            "type":"Services"
        }
    ],
    "sg:phone":"+1 850 243 1115",
    "sg:postcode":"32548",
    "sg:province":"FL",
    "sg:website":"www.whitesandsrealty.com",
    "wof:name":"White Sands Realty",
    "wof:placetype":"venue"
},
  "geometry": {"coordinates":[-86.59345999999999,30.40909],"type":"Point"}
}