{
  "type": "Feature",
  "properties": {
    "addr:full":"5356 McIntosh Rd Sarasota FL 34233",
    "addr:housenumber":"5356",
    "addr:postcode":"34233",
    "addr:street":"Mcintosh Rd",
    "iso:country":"US",
    "sg:address":"5356 McIntosh Rd",
    "sg:city":"Sarasota",
    "sg:classifiers":[
        {
            "category":"Retail",
            "subcategory":"Auto Repair",
            "type":"Services"
        }
    ],
    "sg:phone":"+1 941 925 2767",
    "sg:postcode":"34233",
    "sg:province":"FL",
    "sg:tags":[
        "repairing",
        "automobile"
    ],
    "wof:name":"Barrett's Auto Repair",
    "wof:placetype":"venue"
},
  "geometry": {"coordinates":[-82.481055,27.276571],"type":"Point"}
}