{
  "type": "Feature",
  "properties": {
    "addr:full":"4385 SE 58th Ave Ocala FL 34480",
    "addr:housenumber":"4385",
    "addr:postcode":"34480",
    "addr:street":"Se 58Th Ave",
    "iso:country":"US",
    "sg:address":"4385 SE 58th Ave",
    "sg:city":"Ocala",
    "sg:classifiers":[
        {
            "category":"Manufacturing",
            "subcategory":"Lumber",
            "type":"Manufacturing & Wholesale Goods"
        }
    ],
    "sg:phone":"+1 352 620 0993",
    "sg:postcode":"34480",
    "sg:province":"FL",
    "sg:tags":[
        "logging"
    ],
    "wof:name":"R&M Pulpwood Inc",
    "wof:placetype":"venue"
},
  "geometry": {"coordinates":[-82.053591,29.143727],"type":"Point"}
}