{
  "type": "Feature",
  "properties": {
    "addr:full":"937 W State Rd 436 Altamonte Springs FL 32714",
    "addr:housenumber":"937;436",
    "addr:postcode":"32714",
    "addr:street":"W State Rd",
    "iso:country":"US",
    "sg:address":"937 W State Rd 436",
    "sg:city":"Altamonte Springs",
    "sg:classifiers":[
        {
            "category":"Shopping",
            "subcategory":"Clothing, Apparel, & Fashions",
            "type":"Retail Goods"
        }
    ],
    "sg:phone":"+1 407 772 8193",
    "sg:postcode":"32714",
    "sg:province":"FL",
    "sg:tags":[
        "costume"
    ],
    "sg:website":"www.spirithalloween.com",
    "wof:name":"Spirit",
    "wof:placetype":"venue"
},
  "geometry": {"coordinates":[-81.42161400000001,28.66545],"type":"Point"}
}