{
  "type": "Feature",
  "properties": {
    "addr:full":"1400 N 29th Ct Hollywood FL 33020",
    "addr:housenumber":"1400",
    "addr:postcode":"33020",
    "addr:street":"N 29Th Ct",
    "iso:country":"US",
    "sg:address":"1400 N 29th Ct",
    "sg:city":"Hollywood",
    "sg:classifiers":[
        {
            "category":"Building & Trades",
            "subcategory":"Construction",
            "type":"Services"
        }
    ],
    "sg:phone":"+1 954 923 7600",
    "sg:postcode":"33020",
    "sg:province":"FL",
    "sg:tags":[
        "general",
        "contractor"
    ],
    "wof:name":"Super Diversified Inc",
    "wof:placetype":"venue"
},
  "geometry": {"coordinates":[-80.166448,26.02337],"type":"Point"}
}