{
  "type": "Feature",
  "properties": {
    "iso:country":"US",
    "sg:address":"506 Pine St",
    "sg:city":"Orlando",
    "sg:classifiers":[
        {
            "category":"Autos & Motor Vehicles",
            "subcategory":"Automobile Sales",
            "type":"Retail Goods"
        },
        {
            "category":"Autos & Motor Vehicles",
            "subcategory":"Recreational Vehicle Sales",
            "type":"Retail Goods"
        }
    ],
    "sg:phone":"+1 407 428 0116",
    "sg:postcode":"32824",
    "sg:province":"FL",
    "sg:tags":[
        "antique",
        "new",
        "car",
        "classic"
    ],
    "wof:name":"Orlando Classic Cars",
    "wof:placetype":"venue"
},
  "geometry": {"coordinates":[-81.37042700000001,28.43259],"type":"Point"}
}