{
  "type": "Feature",
  "properties": {
    "addr:full":"13173 Irwin Dr Port Charlotte FL 33953",
    "addr:housenumber":"13173",
    "addr:postcode":"33953",
    "addr:street":"Irwin Dr",
    "iso:country":"US",
    "sg:address":"13173 Irwin Dr",
    "sg:city":"Port Charlotte",
    "sg:classifiers":[
        {
            "category":"Building & Trades",
            "subcategory":"Landscaping Services",
            "type":"Services"
        }
    ],
    "sg:phone":"+1 941 624 3640",
    "sg:postcode":"33953",
    "sg:province":"FL",
    "sg:tags":[
        "landscape"
    ],
    "wof:name":"Lawnscapes",
    "wof:placetype":"venue"
},
  "geometry": {"coordinates":[-82.235675,27.00764],"type":"Point"}
}