{
  "type": "Feature",
  "properties": {
    "iso:country":"US",
    "sg:address":"5320 SW 5th St",
    "sg:city":"Coral Gables",
    "sg:classifiers":[
        {
            "category":"Building & Trades",
            "subcategory":"Construction",
            "type":"Services"
        }
    ],
    "sg:phone":"+1 305 642 7545",
    "sg:postcode":"33134",
    "sg:province":"FL",
    "sg:tags":[
        "painter"
    ],
    "wof:name":"5 Star Painting",
    "wof:placetype":"venue"
},
  "geometry": {"coordinates":[-80.28368500000001,25.766555],"type":"Point"}
}