{
  "type": "Feature",
  "properties": {
    "addr:full":"6545 Nova Dr Davie FL 33317",
    "addr:housenumber":"6545",
    "addr:postcode":"33317",
    "addr:street":"Nova Dr",
    "iso:country":"US",
    "sg:address":"6545 Nova Dr",
    "sg:city":"Davie",
    "sg:classifiers":[
        {
            "category":"Wholesale",
            "subcategory":"Office Equipment",
            "type":"Manufacturing & Wholesale Goods"
        }
    ],
    "sg:phone":"+1 954 974 6456",
    "sg:postcode":"33317",
    "sg:province":"FL",
    "sg:tags":[
        "register",
        "cash",
        "supply"
    ],
    "wof:name":"Rhino Paper Products",
    "wof:placetype":"venue"
},
  "geometry": {"coordinates":[-80.229474,26.085912],"type":"Point"}
}