{
  "type": "Feature",
  "properties": {
    "addr:full":"420 Snug Harbor Dr Merritt Island FL 32953",
    "addr:housenumber":"420",
    "addr:postcode":"32953",
    "addr:street":"Snug Harbor Dr",
    "iso:country":"US",
    "sg:address":"420 Snug Harbor Dr",
    "sg:city":"Merritt Island",
    "sg:classifiers":[
        {
            "category":"Wholesale",
            "subcategory":"Motor Vehicles",
            "type":"Manufacturing & Wholesale Goods"
        }
    ],
    "sg:phone":"+1 321 452 1997",
    "sg:postcode":"32953",
    "sg:province":"FL",
    "wof:name":"Cavin Matthew D&David H",
    "wof:placetype":"venue"
},
  "geometry": {"coordinates":[-80.709962,28.366959],"type":"Point"}
}