{
  "type": "Feature",
  "properties": {
    "addr:full":"3111 Cardinal Dr Vero Beach FL 32963",
    "addr:housenumber":"3111",
    "addr:postcode":"32963",
    "addr:street":"Cardinal Dr",
    "iso:country":"US",
    "sg:address":"3111 Cardinal Dr",
    "sg:city":"Vero Beach",
    "sg:classifiers":[
        {
            "category":"Professional",
            "subcategory":"Lawyer & Legal Services",
            "type":"Services"
        }
    ],
    "sg:phone":"+1 772 231 6900",
    "sg:postcode":"32963",
    "sg:province":"FL",
    "sg:tags":[
        "attorney"
    ],
    "wof:name":"O'Haire Quinn Candler Casalino",
    "wof:placetype":"venue"
},
  "geometry": {"coordinates":[-80.35723,27.651388],"type":"Point"}
}