{
  "type": "Feature",
  "properties": {
    "addr:full":"3507 Connon Dr New Port Richey FL 34652",
    "addr:housenumber":"3507",
    "addr:postcode":"34652",
    "addr:street":"Connon Dr",
    "iso:country":"US",
    "sg:address":"3507 Connon Dr",
    "sg:city":"New Port Richey",
    "sg:classifiers":[
        {
            "category":"Building & Trades",
            "subcategory":"Cleaning & Sanitation",
            "type":"Services"
        }
    ],
    "sg:phone":"+1 727 847 2885",
    "sg:postcode":"34652",
    "sg:province":"FL",
    "sg:tags":[
        "property",
        "maintenance"
    ],
    "wof:name":"Phillips Maintenance",
    "wof:placetype":"venue"
},
  "geometry": {"coordinates":[-82.737651,28.212225],"type":"Point"}
}