{
  "type": "Feature",
  "properties": {
    "addr:full":"4814 S Florida Ave Lakeland FL 33813",
    "addr:housenumber":"4814",
    "addr:postcode":"33813",
    "addr:street":"S Florida Ave",
    "iso:country":"US",
    "sg:address":"4814 S Florida Ave",
    "sg:city":"Lakeland",
    "sg:classifiers":[
        {
            "category":"Retail",
            "subcategory":"Portrait Studio",
            "type":"Services"
        }
    ],
    "sg:phone":"+1 863 646 2275",
    "sg:postcode":"33813",
    "sg:province":"FL",
    "sg:tags":[
        "photo",
        "animal"
    ],
    "wof:name":"Wags To Whiskers",
    "wof:placetype":"venue"
},
  "geometry": {"coordinates":[-81.957961,27.978624],"type":"Point"}
}