{
  "type": "Feature",
  "properties": {
    "iso:country":"US",
    "sg:address":"1237 US Hwy 41",
    "sg:city":"Venice",
    "sg:classifiers":[
        {
            "category":"Shopping",
            "subcategory":"Clothing, Apparel, & Fashions",
            "type":"Retail Goods"
        }
    ],
    "sg:phone":"+1 941 483 3775",
    "sg:postcode":"34285",
    "sg:province":"FL",
    "wof:name":"Champagne Threads",
    "wof:placetype":"venue"
},
  "geometry": {"coordinates":[-82.431104,27.079004],"type":"Point"}
}