{
  "type": "Feature",
  "properties": {
    "addr:full":"213 Carolyn Ave Panama City Bch FL 32407",
    "addr:housenumber":"213",
    "addr:postcode":"32407",
    "addr:street":"Carolyn Ave",
    "iso:country":"US",
    "sg:address":"213 Carolyn Ave",
    "sg:city":"Panama City Bch",
    "sg:classifiers":[
        {
            "category":"Social Services",
            "subcategory":"Child Care",
            "type":"Services"
        }
    ],
    "sg:phone":"+1 850 235 3100",
    "sg:postcode":"32407",
    "sg:province":"FL",
    "wof:name":"Academy Of Early Learners",
    "wof:placetype":"venue"
},
  "geometry": {"coordinates":[-85.757121,30.193126],"type":"Point"}
}