{
  "type": "Feature",
  "properties": {
    "iso:country":"US",
    "sg:address":"338 E Lyman Ave",
    "sg:city":"Winter Park",
    "sg:classifiers":[
        {
            "category":"Social Services",
            "subcategory":"Child Care",
            "type":"Services"
        },
        {
            "category":"Organizations",
            "subcategory":"Religious Organization",
            "type":"Services"
        }
    ],
    "sg:phone":"+1 407 644 1737",
    "sg:postcode":"32789",
    "sg:province":"FL",
    "sg:tags":[
        "day"
    ],
    "wof:name":"All Saints Episcopal Church",
    "wof:placetype":"venue"
},
  "geometry": {"coordinates":[-81.348099,28.5949],"type":"Point"}
}