{
  "type": "Feature",
  "properties": {
    "addr:full":"303 US Hwy 27 Minneola FL 34715",
    "addr:housenumber":"303",
    "addr:postcode":"34715",
    "addr:street":"Us Hwy 27",
    "iso:country":"US",
    "sg:address":"303 US Hwy 27",
    "sg:city":"Minneola",
    "sg:classifiers":[
        {
            "category":"Home & Garden",
            "subcategory":"Carpets & Floor Coverings",
            "type":"Retail Goods"
        }
    ],
    "sg:phone":"+1 352 242 0000",
    "sg:postcode":"34715",
    "sg:province":"FL",
    "sg:tags":[
        "dealer",
        "rug"
    ],
    "wof:name":"Warehouse Carpets",
    "wof:placetype":"venue"
},
  "geometry": {"coordinates":[-81.751758,28.583149],"type":"Point"}
}