{
  "type": "Feature",
  "properties": {
    "iso:country":"US",
    "sg:address":"9883 NW 51st Ter",
    "sg:city":"Doral",
    "sg:classifiers":[
        {
            "category":"Professional",
            "subcategory":"Employment Agencies",
            "type":"Services"
        }
    ],
    "sg:phone":"+1 305 436 9598",
    "sg:postcode":"33178",
    "sg:province":"FL",
    "sg:tags":[
        "consultant",
        "search",
        "executive"
    ],
    "wof:name":"Chico Moises",
    "wof:placetype":"venue"
},
  "geometry": {"coordinates":[-80.355363,25.819995],"type":"Point"}
}