{
  "type": "Feature",
  "properties": {
    "addr:full":"3161 W Oakland Park Blvd Fort Lauderdale FL 33311",
    "addr:housenumber":"3161",
    "addr:postcode":"33311",
    "addr:street":"W Oakland Park Blvd",
    "iso:country":"US",
    "sg:address":"3161 W Oakland Park Blvd",
    "sg:city":"Fort Lauderdale",
    "sg:classifiers":[
        {
            "category":"Shopping",
            "subcategory":"Jewelry",
            "type":"Retail Goods"
        }
    ],
    "sg:phone":"+1 954 733 6375",
    "sg:postcode":"33311",
    "sg:province":"FL",
    "wof:name":"Williams 14k Jewelry Inc",
    "wof:placetype":"venue"
},
  "geometry": {"coordinates":[-80.188654,26.165432],"type":"Point"}
}