{
  "type": "Feature",
  "properties": {
    "iso:country":"US",
    "sg:address":"3300 Santa Barbara Blvd",
    "sg:city":"Naples",
    "sg:classifiers":[
        {
            "category":"Recreation",
            "type":"Entertainment"
        }
    ],
    "sg:phone":"+1 239 353 0404",
    "sg:postcode":"34116",
    "sg:province":"FL",
    "sg:tags":[
        "parks"
    ],
    "sg:website":"www.colliergov.net",
    "wof:name":"Golden Gate Community Park",
    "wof:placetype":"venue"
},
  "geometry": {"coordinates":[-81.718801,26.166673],"type":"Point"}
}