{
  "type": "Feature",
  "properties": {
    "iso:country":"US",
    "sg:address":"3785 N Federal Hwy",
    "sg:city":"Boca Raton",
    "sg:classifiers":[
        {
            "category":"Professional",
            "subcategory":"Management & Consulting",
            "type":"Services"
        }
    ],
    "sg:phone":"+1 561 955 8840",
    "sg:postcode":"33431",
    "sg:province":"FL",
    "sg:tags":[
        "consultant",
        "business"
    ],
    "wof:name":"Signature Consulting",
    "wof:placetype":"venue"
},
  "geometry": {"coordinates":[-80.076564,26.383805],"type":"Point"}
}