{
  "type": "Feature",
  "properties": {
    "iso:country":"US",
    "sg:address":"181 Normandy Road",
    "sg:city":"Orlando",
    "sg:classifiers":[
        {
            "category":"Professional",
            "subcategory":"Art Services",
            "type":"Services"
        }
    ],
    "sg:phone":"+1 407 928 7640",
    "sg:postcode":"32807",
    "sg:province":"FL",
    "sg:tags":[
        "photographer"
    ],
    "sg:website":"www.marcharmonphoto.com",
    "wof:name":"Marc Harmon Photography Inc.",
    "wof:placetype":"venue"
},
  "geometry": {"coordinates":[-81.341583,28.667137],"type":"Point"}
}