{
  "type": "Feature",
  "properties": {
    "iso:country":"US",
    "sg:address":"1975 Tamiami Trl S",
    "sg:city":"Venice",
    "sg:classifiers":[
        {
            "category":"Shopping",
            "subcategory":"Jewelry",
            "type":"Retail Goods"
        }
    ],
    "sg:phone":"+1 941 493 1911",
    "sg:postcode":"34293",
    "sg:province":"FL",
    "sg:tags":[
        "stone",
        "diamond",
        "semi-precious",
        "precious",
        "jeweler"
    ],
    "sg:website":"http://www.reflectionsingold.com/",
    "wof:name":"Reflections in Gold",
    "wof:placetype":"venue"
},
  "geometry": {"coordinates":[-82.414552,27.059679],"type":"Point"}
}