{
  "type": "Feature",
  "properties": {
    "iso:country":"US",
    "sg:address":"2304 Bottega Ln",
    "sg:city":"Brandon",
    "sg:classifiers":[
        {
            "category":"Banks & Credit Unions",
            "subcategory":"Bank",
            "type":"Services"
        }
    ],
    "sg:phone":"+1 813 643 9559",
    "sg:postcode":"33511",
    "sg:province":"FL",
    "sg:tags":[
        "loan",
        "real estate"
    ],
    "wof:name":"Molton Allen & Williams Mtg",
    "wof:placetype":"venue"
},
  "geometry": {"coordinates":[-82.324888,27.91194],"type":"Point"}
}