{
  "type": "Feature",
  "properties": {
    "addr:full":"750 NE 12th Ter Crystal River FL 34428",
    "addr:housenumber":"750",
    "addr:postcode":"34428",
    "addr:street":"Ne 12Th Ter",
    "iso:country":"US",
    "sg:address":"750 NE 12th Ter",
    "sg:city":"Crystal River",
    "sg:classifiers":[
        {
            "category":"Education",
            "subcategory":"Special Training",
            "type":"Public Place"
        }
    ],
    "sg:phone":"+1 352 795 8019",
    "sg:postcode":"34428",
    "sg:province":"FL",
    "sg:tags":[
        "tutoring"
    ],
    "wof:name":"A Learner's Connection",
    "wof:placetype":"venue"
},
  "geometry": {"coordinates":[-82.581548,28.906899],"type":"Point"}
}