{
  "type": "Feature",
  "properties": {
    "addr:full":"1234 Germain St Pensacola FL 32534",
    "addr:housenumber":"1234",
    "addr:postcode":"32534",
    "addr:street":"Germain St",
    "iso:country":"US",
    "sg:address":"1234 Germain St",
    "sg:city":"Pensacola",
    "sg:classifiers":[
        {
            "category":"Personal",
            "subcategory":"Beauty Salon",
            "type":"Services"
        }
    ],
    "sg:phone":"+1 850 474 3516",
    "sg:postcode":"32534",
    "sg:province":"FL",
    "sg:tags":[
        "shop"
    ],
    "wof:name":"Be Lov Lee Beauty Salon",
    "wof:placetype":"venue"
},
  "geometry": {"coordinates":[-87.282883,30.514616],"type":"Point"}
}