{
  "type": "Feature",
  "properties": {
    "iso:country":"US",
    "sg:address":"6505 Thomas Dr",
    "sg:city":"Panama City Bch",
    "sg:classifiers":[
        {
            "category":"Real Estate",
            "subcategory":"Real Estate Operator",
            "type":"Services"
        }
    ],
    "sg:phone":"+1 850 230 2100",
    "sg:postcode":"32408",
    "sg:province":"FL",
    "sg:tags":[
        "condominium"
    ],
    "sg:website":"www.summerhousepc.com",
    "wof:name":"Summerhouse",
    "wof:placetype":"venue"
},
  "geometry": {"coordinates":[-85.766715,30.152127],"type":"Point"}
}