{
  "type": "Feature",
  "properties": {
    "iso:country":"US",
    "sg:address":"6910 Odoniel Loop W",
    "sg:city":"Lakeland",
    "sg:classifiers":[
        {
            "category":"Wholesale",
            "subcategory":"Electrical",
            "type":"Manufacturing & Wholesale Goods"
        }
    ],
    "sg:phone":"+1 863 815 0937",
    "sg:postcode":"33809",
    "sg:province":"FL",
    "sg:tags":[
        "distributes",
        "computer",
        "parts"
    ],
    "wof:name":"Allnet USA",
    "wof:placetype":"venue"
},
  "geometry": {"coordinates":[-81.933741,28.130737],"type":"Point"}
}