{
  "type": "Feature",
  "properties": {
    "iso:country":"US",
    "sg:address":"701 SW 27th Ave Ste 500",
    "sg:city":"Miami",
    "sg:classifiers":[
        {
            "category":"Professional",
            "subcategory":"Business Services",
            "type":"Services"
        }
    ],
    "sg:phone":"+1 305 637 4275",
    "sg:postcode":"33135",
    "sg:province":"FL",
    "sg:tags":[
        "medical",
        "administration"
    ],
    "sg:website":"http://www.seminolecohealth.com",
    "wof:name":"Children & Families Department",
    "wof:placetype":"venue"
},
  "geometry": {"coordinates":[-80.2388,25.766081],"type":"Point"}
}