{
  "type": "Feature",
  "properties": {
    "iso:country":"US",
    "sg:address":"10371 W Sample Rd",
    "sg:city":"Coral Springs",
    "sg:classifiers":[
        {
            "category":"Health Services",
            "subcategory":"Health Practitioner",
            "type":"Services"
        }
    ],
    "sg:phone":"+1 954 341 0090",
    "sg:postcode":"33065",
    "sg:province":"FL",
    "sg:tags":[
        "pathologist",
        "speech"
    ],
    "wof:name":"Children's Therapy Svc",
    "wof:placetype":"venue"
},
  "geometry": {"coordinates":[-80.260912,26.272667],"type":"Point"}
}