{
  "type": "Feature",
  "properties": {
    "iso:country":"US",
    "sg:address":"900 SW 26th Rd",
    "sg:city":"Miami",
    "sg:classifiers":[
        {
            "category":"Organizations",
            "subcategory":"Religious Organization",
            "type":"Services"
        }
    ],
    "sg:phone":"+1 305 858 2621",
    "sg:postcode":"33129",
    "sg:province":"FL",
    "sg:tags":[
        "church"
    ],
    "wof:name":"St Peter & Paul Catholic Church",
    "wof:placetype":"venue"
},
  "geometry": {"coordinates":[-80.21230300000001,25.7605],"type":"Point"}
}