{
  "type": "Feature",
  "properties": {
    "iso:country":"US",
    "sg:address":"830 Indus Rd",
    "sg:city":"Venice",
    "sg:classifiers":[
        {
            "category":"Professional",
            "type":"Services"
        }
    ],
    "sg:phone":"+1 941 497 4262",
    "sg:postcode":"34293",
    "sg:province":"FL",
    "wof:name":"Ellen of Venice Inc",
    "wof:placetype":"venue"
},
  "geometry": {"coordinates":[-82.423818,27.054806],"type":"Point"}
}