{
  "type": "Feature",
  "properties": {
    "iso:country":"US",
    "sg:address":"9485 SW 72nd St Ste A222",
    "sg:city":"Miami",
    "sg:classifiers":[
        {
            "category":"Health Services",
            "subcategory":"Clinic",
            "type":"Services"
        }
    ],
    "sg:phone":"+1 305 279 0007",
    "sg:postcode":"33173",
    "sg:province":"FL",
    "sg:tags":[
        "osteopathic"
    ],
    "wof:name":"South Florida Clinical & Consulting Group",
    "wof:placetype":"venue"
},
  "geometry": {"coordinates":[-80.34699500000001,25.701825],"type":"Point"}
}