{
  "type": "Feature",
  "properties": {
    "iso:country":"US",
    "sg:address":"4995 Cleveland Ave",
    "sg:city":"Fort Myers",
    "sg:classifiers":[
        {
            "category":"Shopping",
            "subcategory":"Clothing, Apparel, & Fashions",
            "type":"Retail Goods"
        }
    ],
    "sg:phone":"+1 239 931 3000",
    "sg:postcode":"33907",
    "sg:province":"FL",
    "wof:name":"Old Navy",
    "wof:placetype":"venue"
},
  "geometry": {"coordinates":[-81.8719,26.58709],"type":"Point"}
}