{
  "type": "Feature",
  "properties": {
    "iso:country":"US",
    "sg:address":"1320 Alligator Dr",
    "sg:city":"Panacea",
    "sg:classifiers":[
        {
            "category":"Travel",
            "subcategory":"Campground",
            "type":"Entertainment"
        }
    ],
    "sg:phone":"+1 850 349 2065",
    "sg:postcode":"32346",
    "sg:province":"FL",
    "wof:name":"D & E Enterprises",
    "wof:placetype":"venue"
},
  "geometry": {"coordinates":[-84.37376999999999,29.893839],"type":"Point"}
}