{
  "type": "Feature",
  "properties": {
    "iso:country":"US",
    "sg:address":"14900 NE 6th Ave",
    "sg:city":"Miami",
    "sg:classifiers":[
        {
            "category":"Food & Beverages",
            "subcategory":"Specialty",
            "type":"Retail Goods"
        },
        {
            "category":"Food & Beverages",
            "subcategory":"Groceries & Convenience Stores",
            "type":"Retail Goods"
        }
    ],
    "sg:phone":"+1 305 917 0232",
    "sg:postcode":"33161",
    "sg:province":"FL",
    "wof:name":"Business Management USA Inc",
    "wof:placetype":"venue"
},
  "geometry": {"coordinates":[-80.187622,25.912115],"type":"Point"}
}