{
  "type": "Feature",
  "properties": {
    "addr:full":"8036 NW 10th Ct Miami FL 33150",
    "addr:housenumber":"8036",
    "addr:postcode":"33150",
    "addr:street":"Nw 10Th Ct",
    "iso:country":"US",
    "sg:address":"8036 NW 10th Ct",
    "sg:city":"Miami",
    "sg:classifiers":[
        {
            "category":"Organizations",
            "subcategory":"Religious Organization",
            "type":"Services"
        }
    ],
    "sg:phone":"+1 305 694 1471",
    "sg:postcode":"33150",
    "sg:province":"FL",
    "sg:tags":[
        "church"
    ],
    "wof:name":"Believers Temple Of Christ",
    "wof:placetype":"venue"
},
  "geometry": {"coordinates":[-80.214095,25.847476],"type":"Point"}
}