{
  "type": "Feature",
  "properties": {
    "iso:country":"US",
    "sg:address":"8718 Pawnee Ave",
    "sg:city":"Tampa",
    "sg:classifiers":[
        {
            "category":"Social Services",
            "subcategory":"Child Care",
            "type":"Services"
        }
    ],
    "sg:phone":"+1 813 985 2118",
    "sg:postcode":"33617",
    "sg:province":"FL",
    "sg:tags":[
        "day"
    ],
    "wof:name":"Rogers Family Daycare",
    "wof:placetype":"venue"
},
  "geometry": {"coordinates":[-82.406384,28.031941],"type":"Point"}
}