{
  "type": "Feature",
  "properties": {
    "iso:country":"US",
    "sg:address":"4125 Cleveland Ave",
    "sg:city":"Fort Myers",
    "sg:classifiers":[
        {
            "category":"Shopping",
            "subcategory":"Luggage & Leather Goods",
            "type":"Retail Goods"
        }
    ],
    "sg:phone":"+1 239 226 1122",
    "sg:postcode":"33901",
    "sg:province":"FL",
    "wof:name":"Freeman's Luggage",
    "wof:placetype":"venue"
},
  "geometry": {"coordinates":[-81.87179399999999,26.602732],"type":"Point"}
}