{
  "type": "Feature",
  "properties": {
    "iso:country":"US",
    "sg:address":"3915 NW 4th Ter",
    "sg:city":"Miami",
    "sg:classifiers":[
        {
            "category":"Banks & Credit Unions",
            "subcategory":"Investment Brokerage",
            "type":"Services"
        }
    ],
    "sg:phone":"+1 305 649 0075",
    "sg:postcode":"33126",
    "sg:province":"FL",
    "wof:name":"Rama & M Investment",
    "wof:placetype":"venue"
},
  "geometry": {"coordinates":[-80.262051,25.776713],"type":"Point"}
}