{
  "type": "Feature",
  "properties": {
    "addr:full":"2717 Zorno Way Delray Beach FL 33445",
    "addr:housenumber":"2717",
    "addr:postcode":"33445",
    "addr:street":"Zorno Way",
    "iso:country":"US",
    "sg:address":"2717 Zorno Way",
    "sg:city":"Delray Beach",
    "sg:classifiers":[
        {
            "category":"Building & Trades",
            "subcategory":"Construction",
            "type":"Services"
        }
    ],
    "sg:phone":"+1 561 278 7886",
    "sg:postcode":"33445",
    "sg:province":"FL",
    "sg:tags":[
        "planning",
        "remodeling",
        "kitchen"
    ],
    "wof:name":"Attention To Detail Kitchen",
    "wof:placetype":"venue"
},
  "geometry": {"coordinates":[-80.102783,26.446311],"type":"Point"}
}