{
  "type": "Feature",
  "properties": {
    "iso:country":"US",
    "sg:address":"4350 Oakes Rd",
    "sg:city":"Fort Lauderdale",
    "sg:classifiers":[
        {
            "category":"Professional",
            "subcategory":"Business Services",
            "type":"Services"
        }
    ],
    "sg:phone":"+1 954 584 2151",
    "sg:postcode":"33314",
    "sg:province":"FL",
    "sg:tags":[
        "benefit",
        "provider"
    ],
    "wof:name":"National Companies",
    "wof:placetype":"venue"
},
  "geometry": {"coordinates":[-80.206137,26.0764],"type":"Point"}
}