{
  "type": "Feature",
  "properties": {
    "iso:country":"US",
    "sg:address":"13551 SW 8th St",
    "sg:city":"Fort Lauderdale",
    "sg:classifiers":[
        {
            "category":"Building & Trades",
            "subcategory":"Landscaping Services",
            "type":"Services"
        }
    ],
    "sg:phone":"+1 954 472 3246",
    "sg:postcode":"33325",
    "sg:province":"FL",
    "wof:name":"Mark Fanuccis Landscaping",
    "wof:placetype":"venue"
},
  "geometry": {"coordinates":[-80.329628,26.109559],"type":"Point"}
}