{
  "type": "Feature",
  "properties": {
    "iso:country":"US",
    "sg:address":"7921 NW 21st St",
    "sg:city":"Doral",
    "sg:classifiers":[
        {
            "category":"Professional",
            "subcategory":"Lawyer & Legal Services",
            "type":"Services"
        }
    ],
    "sg:phone":"+1 305 599 9225",
    "sg:postcode":"33122",
    "sg:province":"FL",
    "sg:tags":[
        "paralegal"
    ],
    "wof:name":"Infinate Herbs",
    "wof:placetype":"venue"
},
  "geometry": {"coordinates":[-80.324223,25.793391],"type":"Point"}
}