{
  "type": "Feature",
  "properties": {
    "iso:country":"US",
    "sg:address":"3443 Hi St",
    "sg:city":"Lake Worth",
    "sg:classifiers":[
        {
            "category":"Taxi",
            "type":"Transportation"
        }
    ],
    "sg:phone":"+1 561 964 4777",
    "sg:postcode":"33461",
    "sg:province":"FL",
    "sg:tags":[
        "taxicab"
    ],
    "wof:name":"Guatemex Corp",
    "wof:placetype":"venue"
},
  "geometry": {"coordinates":[-80.086215,26.628211],"type":"Point"}
}