{
  "type": "Feature",
  "properties": {
    "iso:country":"US",
    "sg:address":"5004 Fremont St",
    "sg:city":"Jacksonville",
    "sg:classifiers":[
        {
            "category":"Personal",
            "subcategory":"Beauty Salon",
            "type":"Services"
        }
    ],
    "sg:phone":"+1 904 384 3411",
    "sg:postcode":"32210",
    "sg:province":"FL",
    "wof:name":"Khariss Beauty Salon",
    "wof:placetype":"venue"
},
  "geometry": {"coordinates":[-81.732342,30.278725],"type":"Point"}
}