{
  "type": "Feature",
  "properties": {
    "addr:full":"964 Schumann Dr Sebastian FL 32958",
    "addr:housenumber":"964",
    "addr:postcode":"32958",
    "addr:street":"Schumann Dr",
    "iso:country":"US",
    "sg:address":"964 Schumann Dr",
    "sg:city":"Sebastian",
    "sg:classifiers":[
        {
            "category":"Insurance",
            "subcategory":"Hazard Insurance",
            "type":"Services"
        }
    ],
    "sg:phone":"+1 772 589 5657",
    "sg:postcode":"32958",
    "sg:province":"FL",
    "sg:tags":[
        "commercial",
        "business"
    ],
    "wof:name":"Roseland Insurance",
    "wof:placetype":"venue"
},
  "geometry": {"coordinates":[-80.462789,27.781901],"type":"Point"}
}