{
  "type": "Feature",
  "properties": {
    "iso:country":"US",
    "sg:address":"1901 Convention Center Dr",
    "sg:city":"Miami Beach",
    "sg:classifiers":[
        {
            "category":"Retail",
            "subcategory":"Event Space",
            "type":"Services"
        }
    ],
    "sg:phone":"+1 305 412 3976",
    "sg:postcode":"33139",
    "sg:province":"FL",
    "sg:tags":[
        "venue"
    ],
    "wof:name":"MiaGreen Expo & Conference",
    "wof:placetype":"venue"
},
  "geometry": {"coordinates":[-80.134699,25.794796],"type":"Point"}
}