{
  "type": "Feature",
  "properties": {
    "iso:country":"US",
    "sg:address":"1755 Luten Rd",
    "sg:city":"Gretna",
    "sg:classifiers":[
        {
            "category":"Building & Trades",
            "subcategory":"Plumbing",
            "type":"Services"
        }
    ],
    "sg:phone":"+1 850 856 8000",
    "sg:postcode":"32352",
    "sg:province":"FL",
    "sg:tags":[
        "conditioning",
        "air",
        "system",
        "contractor"
    ],
    "wof:name":"Climate Control",
    "wof:placetype":"venue"
},
  "geometry": {"coordinates":[-84.62923499999999,30.606234],"type":"Point"}
}