{
  "type": "Feature",
  "properties": {
    "addr:full":"1131 NE 170th St Miami FL 33162",
    "addr:housenumber":"1131",
    "addr:postcode":"33162",
    "addr:street":"Ne 170Th St",
    "iso:country":"US",
    "sg:address":"1131 NE 170th St",
    "sg:city":"Miami",
    "sg:classifiers":[
        {
            "category":"Professional",
            "type":"Services"
        }
    ],
    "sg:phone":"+1 305 770 3701",
    "sg:postcode":"33162",
    "sg:province":"FL",
    "wof:name":"Qi Rong Wu Inc",
    "wof:placetype":"venue"
},
  "geometry": {"coordinates":[-80.176851,25.932118],"type":"Point"}
}