{
  "type": "Feature",
  "properties": {
    "addr:full":"15880 Summerlin Rd Fort Myers FL 33908",
    "addr:housenumber":"15880",
    "addr:postcode":"33908",
    "addr:street":"Summerlin Rd",
    "iso:country":"US",
    "sg:address":"15880 Summerlin Rd",
    "sg:city":"Fort Myers",
    "sg:classifiers":[
        {
            "category":"Building & Trades",
            "subcategory":"Plumbing",
            "type":"Services"
        }
    ],
    "sg:phone":"+1 239 995 9071",
    "sg:postcode":"33908",
    "sg:province":"FL",
    "sg:tags":[
        "plumbing",
        "contractor"
    ],
    "wof:name":"All City Plumbing",
    "wof:placetype":"venue"
},
  "geometry": {"coordinates":[-81.898741,26.514239],"type":"Point"}
}