{
  "type": "Feature",
  "properties": {
    "addr:full":"18780 Dixie Hwy Miami FL 33157",
    "addr:housenumber":"18780",
    "addr:postcode":"33157",
    "addr:street":"Dixie Hwy",
    "iso:country":"US",
    "sg:address":"18780 Dixie Hwy",
    "sg:city":"Miami",
    "sg:classifiers":[
        {
            "category":"Home & Garden",
            "subcategory":"Furniture",
            "type":"Retail Goods"
        }
    ],
    "sg:phone":"+1 305 255 3538",
    "sg:postcode":"33157",
    "sg:province":"FL",
    "wof:name":"City Furniture",
    "wof:placetype":"venue"
},
  "geometry": {"coordinates":[-80.357253,25.592243],"type":"Point"}
}