{
  "type": "Feature",
  "properties": {
    "addr:full":"9598 SW 114th St Unit 16 Ocala FL 34481",
    "addr:housenumber":"9598;16",
    "addr:postcode":"34481",
    "addr:street":"Sw 114Th St Unit",
    "iso:country":"US",
    "sg:address":"9598 SW 114th St Unit 16",
    "sg:city":"Ocala",
    "sg:classifiers":[
        {
            "category":"Wholesale",
            "subcategory":"Painting Supplies",
            "type":"Manufacturing & Wholesale Goods"
        },
        {
            "category":"Manufacturing",
            "subcategory":"Tools & Machinery",
            "type":"Manufacturing & Wholesale Goods"
        },
        {
            "category":"Building & Trades",
            "subcategory":"Construction",
            "type":"Services"
        },
        {
            "category":"Home & Garden",
            "subcategory":"Building Materials",
            "type":"Retail Goods"
        },
        {
            "category":"Manufacturing",
            "subcategory":"Chemicals & Compounds",
            "type":"Manufacturing & Wholesale Goods"
        },
        {
            "category":"Autos & Motor Vehicles",
            "subcategory":"Auto Supplies",
            "type":"Retail Goods"
        },
        {
            "category":"Building & Trades",
            "subcategory":"Equipment Rental",
            "type":"Services"
        },
        {
            "category":"Manufacturing",
            "subcategory":"Building Materials",
            "type":"Manufacturing & Wholesale Goods"
        }
    ],
    "sg:phone":"+1 352 237 0293",
    "sg:postcode":"34481",
    "sg:province":"FL",
    "sg:tags":[
        "shop",
        "body",
        "spraying",
        "wall",
        "automobile",
        "wallpaper",
        "coating",
        "improvement",
        "paint-wholesale",
        "paint",
        "wallcoverings-installation",
        "wallcoverings",
        "contractor",
        "equipment-renting",
        "painter",
        "manufacturer"
    ],
    "sg:website":"http://national.citysearch.com/profile/external/47167250/ocala_fl/sherwin_williams_company.html?publisher=yellowpages&reference_id=1&placement=ypwebsitemip",
    "wof:name":"Sherwin-Williams Company",
    "wof:placetype":"venue"
},
  "geometry": {"coordinates":[-82.278053,29.055217],"type":"Point"}
}