{
  "type": "Feature",
  "properties": {
    "iso:country":"US",
    "sg:address":"1524 Fruitville Rd",
    "sg:city":"Sarasota",
    "sg:classifiers":[
        {
            "category":"Shopping",
            "subcategory":"Used Merchandise",
            "type":"Retail Goods"
        }
    ],
    "sg:phone":"+1 941 373 0300",
    "sg:postcode":"34236",
    "sg:province":"FL",
    "sg:tags":[
        "antique"
    ],
    "wof:name":"Point West Designs",
    "wof:placetype":"venue"
},
  "geometry": {"coordinates":[-82.53904900000001,27.338798],"type":"Point"}
}