{
  "type": "Feature",
  "properties": {
    "iso:country":"US",
    "sg:address":"4950 W Kennedy Blvd",
    "sg:city":"Tampa",
    "sg:classifiers":[
        {
            "category":"Health Services",
            "subcategory":"Doctor",
            "type":"Services"
        }
    ],
    "sg:phone":"+1 813 287 1150",
    "sg:postcode":"33609",
    "sg:province":"FL",
    "sg:tags":[
        "physician",
        "medical",
        "surgeon"
    ],
    "wof:name":"Dr Rawlings Joseph E Jr MD",
    "wof:placetype":"venue"
},
  "geometry": {"coordinates":[-82.528352,27.944855],"type":"Point"}
}