{
  "type": "Feature",
  "properties": {
    "addr:full":"16050 S Tamiami Trl Fort Myers FL 33908",
    "addr:housenumber":"16050",
    "addr:postcode":"fl 33908",
    "addr:street":"S Tamiami Trl",
    "iso:country":"US",
    "sg:address":"16050 S Tamiami Trl",
    "sg:city":"Fort Myers",
    "sg:classifiers":[
        {
            "category":"Professional",
            "type":"Services"
        }
    ],
    "sg:phone":"+1 239 437 6664",
    "sg:postcode":"33908",
    "sg:province":"FL",
    "sg:tags":[
        "establishment"
    ],
    "wof:name":"Omni Group",
    "wof:placetype":"venue"
},
  "geometry": {"coordinates":[-81.86098200000001,26.508817],"type":"Point"}
}