{
  "type": "Feature",
  "properties": {
    "addr:full":"710 NE 6th Ave Crystal River FL 34428",
    "addr:housenumber":"710",
    "addr:postcode":"34428",
    "addr:street":"Ne 6Th Ave",
    "iso:country":"US",
    "sg:address":"710 NE 6th Ave",
    "sg:city":"Crystal River",
    "sg:classifiers":[
        {
            "category":"Education",
            "subcategory":"School",
            "type":"Public Place"
        }
    ],
    "sg:phone":"+1 352 746 0681",
    "sg:postcode":"34428",
    "sg:province":"FL",
    "wof:name":"Citrus Ct School Board Trnsprt",
    "wof:placetype":"venue"
},
  "geometry": {"coordinates":[-82.58489400000001,28.902326],"type":"Point"}
}