{
  "type": "Feature",
  "properties": {
    "iso:country":"US",
    "sg:address":"557 Little River Loop",
    "sg:city":"Altamonte Springs",
    "sg:classifiers":[
        {
            "category":"Freight",
            "type":"Transportation"
        }
    ],
    "sg:phone":"+1 407 822 9187",
    "sg:postcode":"32714",
    "sg:province":"FL",
    "sg:tags":[
        "operator",
        "trucking"
    ],
    "wof:name":"Pierce K Guevara",
    "wof:placetype":"venue"
},
  "geometry": {"coordinates":[-81.41748200000001,28.650802],"type":"Point"}
}