{
  "type": "Feature",
  "properties": {
    "iso:country":"US",
    "sg:address":"2626 NW 72nd Ave",
    "sg:city":"Miami",
    "sg:classifiers":[
        {
            "category":"Shopping",
            "subcategory":"Florist",
            "type":"Retail Goods"
        }
    ],
    "sg:phone":"+1 305 597 0441",
    "sg:postcode":"33122",
    "sg:province":"FL",
    "wof:name":"United Floral Farms",
    "wof:placetype":"venue"
},
  "geometry": {"coordinates":[-80.31304900000001,25.798142],"type":"Point"}
}