{
  "type": "Feature",
  "properties": {
    "addr:full":"4432 W Hwy 98 Panama City FL 32401",
    "addr:housenumber":"4432",
    "addr:postcode":"32401",
    "addr:street":"W Hwy 98",
    "iso:country":"US",
    "sg:address":"4432 W Hwy 98",
    "sg:city":"Panama City",
    "sg:classifiers":[
        {
            "category":"Restaurant",
            "type":"Food & Drink"
        }
    ],
    "sg:phone":"+1 850 769 1283",
    "sg:postcode":"32401",
    "sg:province":"FL",
    "sg:tags":[
        "eating",
        "pizza"
    ],
    "wof:name":"Chuck E Cheese's",
    "wof:placetype":"venue"
},
  "geometry": {"coordinates":[-85.717336,30.180825],"type":"Point"}
}