{
  "type": "Feature",
  "properties": {
    "addr:full":"975 W 49th St Hialeah FL 33012",
    "addr:housenumber":"975",
    "addr:postcode":"33012",
    "addr:street":"W 49Th St",
    "iso:country":"US",
    "sg:address":"975 W 49th St",
    "sg:city":"Hialeah",
    "sg:classifiers":[
        {
            "category":"Health Services",
            "subcategory":"Hospital",
            "type":"Services"
        }
    ],
    "sg:phone":"+1 305 512 9381",
    "sg:postcode":"33012",
    "sg:province":"FL",
    "sg:tags":[
        "medical",
        "surgical",
        "hospitalization",
        "plan"
    ],
    "sg:website":"http://www.humanaventures.com",
    "wof:name":"Humana",
    "wof:placetype":"venue"
},
  "geometry": {"coordinates":[-80.302847,25.866711],"type":"Point"}
}