{
  "type": "Feature",
  "properties": {
    "iso:country":"US",
    "sg:address":"14450 Landfill Rd",
    "sg:city":"Brooksville",
    "sg:classifiers":[
        {
            "category":"Government",
            "subcategory":"Office",
            "type":"Public Place"
        }
    ],
    "sg:phone":"+1 352 754 4112",
    "sg:postcode":"34614",
    "sg:province":"FL",
    "wof:name":"Northwest Landfill",
    "wof:placetype":"venue"
},
  "geometry": {"coordinates":[-82.482952,28.67296],"type":"Point"}
}