{
  "type": "Feature",
  "properties": {
    "addr:full":"18452 Deep Passage Ln Fort Myers Beach FL 33931",
    "addr:housenumber":"18452",
    "addr:postcode":"33931",
    "addr:street":"Deep Passage Ln",
    "iso:country":"US",
    "sg:address":"18452 Deep Passage Ln",
    "sg:city":"Fort Myers Beach",
    "sg:classifiers":[
        {
            "category":"Restaurant",
            "type":"Food & Drink"
        }
    ],
    "sg:phone":"+1 239 395 1142",
    "sg:postcode":"33931",
    "sg:province":"FL",
    "sg:tags":[
        "eating"
    ],
    "wof:name":"RC Otter Inc",
    "wof:placetype":"venue"
},
  "geometry": {"coordinates":[-81.95477099999999,26.476773],"type":"Point"}
}