{
  "type": "Feature",
  "properties": {
    "addr:full":"9550 NW 79th Ave Hialeah FL 33016",
    "addr:housenumber":"9550",
    "addr:postcode":"33016",
    "addr:street":"Nw 79Th Ave",
    "iso:country":"US",
    "sg:address":"9550 NW 79th Ave",
    "sg:city":"Hialeah",
    "sg:classifiers":[
        {
            "category":"Retail",
            "subcategory":"Auto Repair",
            "type":"Services"
        }
    ],
    "sg:phone":"+1 305 558 8080",
    "sg:postcode":"33016",
    "sg:province":"FL",
    "sg:tags":[
        "automobile",
        "wrecker",
        "towing"
    ],
    "wof:name":"American Towing Inc",
    "wof:placetype":"venue"
},
  "geometry": {"coordinates":[-80.32566,25.860105],"type":"Point"}
}