{
  "type": "Feature",
  "properties": {
    "iso:country":"US",
    "sg:address":"7195 Pembroke Rd",
    "sg:city":"Pembroke Pines",
    "sg:classifiers":[
        {
            "category":"Shopping",
            "subcategory":"Clothing, Apparel, & Fashions",
            "type":"Retail Goods"
        }
    ],
    "sg:phone":"+1 954 518 0093",
    "sg:postcode":"33023",
    "sg:province":"FL",
    "sg:tags":[
        "alteration"
    ],
    "wof:name":"Designer Alterations Plus",
    "wof:placetype":"venue"
},
  "geometry": {"coordinates":[-80.230177,25.995049],"type":"Point"}
}