{
  "type": "Feature",
  "properties": {
    "iso:country":"US",
    "sg:address":"207 Clematis St",
    "sg:city":"West Palm Beach",
    "sg:classifiers":[
        {
            "category":"Restaurant",
            "type":"Food & Drink"
        }
    ],
    "sg:menulink":"http://www.allmenus.com/fl/west-palm-beach/278393-maison-carlos/menu/",
    "sg:phone":"+1 561 659 6524",
    "sg:postcode":"33401",
    "sg:province":"FL",
    "sg:tags":[
        "french",
        "italian"
    ],
    "wof:name":"Maison Carlos",
    "wof:placetype":"venue"
},
  "geometry": {"coordinates":[-80.05087899999999,26.713434],"type":"Point"}
}