{
  "type": "Feature",
  "properties": {
    "addr:full":"1897 W Shores Rd Indialantic FL 32935",
    "addr:housenumber":"1897",
    "addr:postcode":"32935",
    "addr:street":"W Shores Rd",
    "iso:country":"US",
    "sg:address":"1897 W Shores Rd",
    "sg:city":"Indialantic",
    "sg:classifiers":[
        {
            "category":"Social Services",
            "type":"Services"
        }
    ],
    "sg:phone":"+1 321 591 3510",
    "sg:postcode":"32935",
    "sg:province":"FL",
    "sg:tags":[
        "specialist",
        "video",
        "legal"
    ],
    "wof:name":"Videolog LLC",
    "wof:placetype":"venue"
},
  "geometry": {"coordinates":[-80.650262,28.149462],"type":"Point"}
}