{
  "type": "Feature",
  "properties": {
    "addr:full":"5624 Dewey St Hollywood FL 33023",
    "addr:housenumber":"5624",
    "addr:postcode":"33023",
    "addr:street":"Dewey St",
    "iso:country":"US",
    "sg:address":"5624 Dewey St",
    "sg:city":"Hollywood",
    "sg:classifiers":[
        {
            "category":"Retail",
            "subcategory":"Repair Shop",
            "type":"Services"
        },
        {
            "category":"Home & Garden",
            "subcategory":"Furniture",
            "type":"Retail Goods"
        }
    ],
    "sg:phone":"+1 954 962 0028",
    "sg:postcode":"33023",
    "sg:province":"FL",
    "sg:tags":[
        "store",
        "upholsterer"
    ],
    "wof:name":"Bishop Furniture Repair",
    "wof:placetype":"venue"
},
  "geometry": {"coordinates":[-80.19958699999999,26.001766],"type":"Point"}
}