{
  "type": "Feature",
  "properties": {
    "iso:country":"US",
    "sg:address":"6573 Marissa Loop",
    "sg:city":"Naples",
    "sg:classifiers":[
        {
            "category":"Real Estate",
            "subcategory":"Real Estate Operator",
            "type":"Services"
        }
    ],
    "sg:phone":"+1 239 592 5311",
    "sg:postcode":"34108",
    "sg:province":"FL",
    "sg:tags":[
        "condominium"
    ],
    "wof:name":"St Marissa Condominium",
    "wof:placetype":"venue"
},
  "geometry": {"coordinates":[-81.81165900000001,26.228676],"type":"Point"}
}