{
  "type": "Feature",
  "properties": {
    "addr:full":"7171 N Davis Hwy Pensacola FL 32504",
    "addr:housenumber":"7171",
    "addr:postcode":"32504",
    "addr:street":"N Davis Hwy",
    "iso:country":"US",
    "sg:address":"7171 N Davis Hwy",
    "sg:city":"Pensacola",
    "sg:classifiers":[
        {
            "category":"Shopping",
            "subcategory":"Clothing, Apparel, & Fashions",
            "type":"Retail Goods"
        },
        {
            "category":"Shopping",
            "subcategory":"Shoes",
            "type":"Retail Goods"
        }
    ],
    "sg:phone":"+1 850 479 4813",
    "sg:postcode":"32504",
    "sg:province":"FL",
    "sg:tags":[
        "sportswear",
        "store"
    ],
    "sg:website":"http://www.footlocker.com",
    "wof:name":"Foot Locker",
    "wof:placetype":"venue"
},
  "geometry": {"coordinates":[-87.221752,30.498986],"type":"Point"}
}