{
  "type": "Feature",
  "properties": {
    "iso:country":"US",
    "sg:address":"3620 NW 59th St",
    "sg:city":"Miami",
    "sg:classifiers":[
        {
            "category":"Wholesale",
            "subcategory":"Non-durable Goods",
            "type":"Manufacturing & Wholesale Goods"
        }
    ],
    "sg:phone":"+1 305 638 7700",
    "sg:postcode":"33142",
    "sg:province":"FL",
    "sg:tags":[
        "export",
        "used",
        "clothing"
    ],
    "sg:website":"www.petitas.com",
    "wof:name":"Petitas Trading Corp",
    "wof:placetype":"venue"
},
  "geometry": {"coordinates":[-80.25503999999999,25.828009],"type":"Point"}
}