{
  "type": "Feature",
  "properties": {
    "addr:full":"2390 80th Ct Vero Beach FL 32966",
    "addr:housenumber":"2390",
    "addr:postcode":"32966",
    "addr:street":"80Th Ct",
    "iso:country":"US",
    "sg:address":"2390 80th Ct",
    "sg:city":"Vero Beach",
    "sg:classifiers":[
        {
            "category":"Home & Garden",
            "subcategory":"Garden Supply",
            "type":"Retail Goods"
        }
    ],
    "sg:phone":"+1 772 299 0572",
    "sg:postcode":"32966",
    "sg:province":"FL",
    "sg:tags":[
        "bulb",
        "seed"
    ],
    "wof:name":"Delta & Pine Land Co",
    "wof:placetype":"venue"
},
  "geometry": {"coordinates":[-80.49268499999999,27.644147],"type":"Point"}
}