{
  "type": "Feature",
  "properties": {
    "addr:full":"8925 SW 126th Ter Miami FL 33176",
    "addr:housenumber":"8925",
    "addr:postcode":"33176",
    "addr:street":"Sw 126Th Ter",
    "iso:country":"US",
    "sg:address":"8925 SW 126th Ter",
    "sg:city":"Miami",
    "sg:classifiers":[
        {
            "category":"Professional",
            "type":"Services"
        }
    ],
    "sg:phone":"+1 305 238 9340",
    "sg:postcode":"33176",
    "sg:province":"FL",
    "wof:name":"Lytelcommunications Corp",
    "wof:placetype":"venue"
},
  "geometry": {"coordinates":[-80.340062,25.652618],"type":"Point"}
}