{
  "type": "Feature",
  "properties": {
    "addr:full":"10135 US Hwy 441 Leesburg FL 34788",
    "addr:postcode":"10135;34788",
    "addr:street":"Us Hwy 441",
    "iso:country":"US",
    "sg:address":"10135 US Hwy 441",
    "sg:city":"Leesburg",
    "sg:classifiers":[
        {
            "category":"Restaurant",
            "type":"Food & Drink"
        }
    ],
    "sg:phone":"+1 352 326 3234",
    "sg:postcode":"34788",
    "sg:province":"FL",
    "wof:name":"Subway Sandwiches & Salads",
    "wof:placetype":"venue"
},
  "geometry": {"coordinates":[-81.78942600000001,28.824029],"type":"Point"}
}