{
  "type": "Feature",
  "properties": {
    "addr:full":"1859 Capital Cir NE Tallahassee FL 32308",
    "addr:housenumber":"1859",
    "addr:postcode":"32308",
    "addr:street":"Capital Cir Ne",
    "iso:country":"US",
    "sg:address":"1859 Capital Cir NE",
    "sg:city":"Tallahassee",
    "sg:classifiers":[
        {
            "category":"Banks & Credit Unions",
            "subcategory":"Bank",
            "type":"Services"
        }
    ],
    "sg:phone":"+1 850 671 4449",
    "sg:postcode":"32308",
    "sg:province":"FL",
    "sg:tags":[
        "banker",
        "mortgage"
    ],
    "wof:name":"AmSouth",
    "wof:placetype":"venue"
},
  "geometry": {"coordinates":[-84.232062,30.471668],"type":"Point"}
}