{
  "type": "Feature",
  "properties": {
    "iso:country":"US",
    "sg:address":"1533 Commercial Way",
    "sg:city":"Spring Hill",
    "sg:classifiers":[
        {
            "category":"Shopping",
            "subcategory":"Shoes",
            "type":"Retail Goods"
        }
    ],
    "sg:phone":"+1 352 683 2800",
    "sg:postcode":"34606",
    "sg:province":"FL",
    "wof:name":"Payless Shoe Source",
    "wof:placetype":"venue"
},
  "geometry": {"coordinates":[-82.628997,28.456403],"type":"Point"}
}