{
  "type": "Feature",
  "properties": {
    "addr:full":"800 E Twiggs St Tampa FL 33602",
    "addr:housenumber":"800",
    "addr:postcode":"33602",
    "addr:street":"E Twiggs St",
    "iso:country":"US",
    "sg:address":"800 E Twiggs St",
    "sg:city":"Tampa",
    "sg:classifiers":[
        {
            "category":"Government",
            "subcategory":"Office",
            "type":"Public Place"
        }
    ],
    "sg:phone":"+1 813 272 6423",
    "sg:postcode":"33602",
    "sg:province":"FL",
    "sg:tags":[
        "parish",
        "government-county"
    ],
    "wof:name":"Hillsborough County Victim Assistance Program",
    "wof:placetype":"venue"
},
  "geometry": {"coordinates":[-82.454391,27.95063],"type":"Point"}
}