{
  "type": "Feature",
  "properties": {
    "addr:full":"11204 NW 2nd Ter Miami FL 33172",
    "addr:housenumber":"11204",
    "addr:postcode":"33172",
    "addr:street":"Nw 2Nd Ter",
    "iso:country":"US",
    "sg:address":"11204 NW 2nd Ter",
    "sg:city":"Miami",
    "sg:classifiers":[
        {
            "category":"Professional",
            "subcategory":"Detective & Security Services",
            "type":"Services"
        }
    ],
    "sg:phone":"+1 305 480 0058",
    "sg:postcode":"33172",
    "sg:province":"FL",
    "sg:tags":[
        "guard",
        "patrol"
    ],
    "wof:name":"K 9 Security Guard Dogs",
    "wof:placetype":"venue"
},
  "geometry": {"coordinates":[-80.377304,25.77098],"type":"Point"}
}