{
  "type": "Feature",
  "properties": {
    "iso:country":"US",
    "sg:address":"12314 SW 132nd Ct",
    "sg:city":"Miami",
    "sg:classifiers":[
        {
            "category":"Freight",
            "type":"Transportation"
        }
    ],
    "sg:phone":"+1 305 278 7288",
    "sg:postcode":"33186",
    "sg:province":"FL",
    "sg:tags":[
        "truck",
        "dump",
        "trucking"
    ],
    "wof:name":"C & C Carriers Inc",
    "wof:placetype":"venue"
},
  "geometry": {"coordinates":[-80.408457,25.65336],"type":"Point"}
}