{
  "type": "Feature",
  "properties": {
    "addr:full":"1580 N University Dr Pompano Beach FL 33071",
    "addr:housenumber":"1580",
    "addr:postcode":"33071",
    "addr:street":"N University Dr",
    "iso:country":"US",
    "sg:address":"1580 N University Dr",
    "sg:city":"Pompano Beach",
    "sg:classifiers":[
        {
            "category":"Restaurant",
            "type":"Food & Drink"
        }
    ],
    "sg:menulink":"http://www.allmenus.com/fl/margate/16267-black-angus-steakhouse/menu/",
    "sg:phone":"+1 954 346 6344",
    "sg:postcode":"33071",
    "sg:province":"FL",
    "sg:tags":[
        "american",
        "steakhouse"
    ],
    "wof:name":"Black Angus Steakhouse",
    "wof:placetype":"venue"
},
  "geometry": {"coordinates":[-80.25332,26.250643],"type":"Point"}
}