{
  "type": "Feature",
  "properties": {
    "addr:full":"350 Crossing Blvd Orange Park FL 32073",
    "addr:housenumber":"350",
    "addr:postcode":"32073",
    "addr:street":"Crossing Blvd",
    "iso:country":"US",
    "sg:address":"350 Crossing Blvd",
    "sg:city":"Orange Park",
    "sg:classifiers":[
        {
            "category":"Real Estate",
            "subcategory":"Real Estate Agent",
            "type":"Services"
        }
    ],
    "sg:phone":"+1 904 269 6669",
    "sg:postcode":"32073",
    "sg:province":"FL",
    "sg:tags":[
        "management"
    ],
    "wof:name":"Equity Residential Properties",
    "wof:placetype":"venue"
},
  "geometry": {"coordinates":[-81.71827999999999,30.18479],"type":"Point"}
}