{
  "type": "Feature",
  "properties": {
    "addr:full":"517 Enderby Rd Oviedo FL 32766",
    "addr:housenumber":"517",
    "addr:postcode":"32766",
    "addr:street":"Enderby Rd",
    "iso:country":"US",
    "sg:address":"517 Enderby Rd",
    "sg:city":"Oviedo",
    "sg:classifiers":[
        {
            "category":"Building & Trades",
            "subcategory":"Landscaping Services",
            "type":"Services"
        }
    ],
    "sg:phone":"+1 407 365 1197",
    "sg:postcode":"32766",
    "sg:province":"FL",
    "wof:name":"Patrick Smiths Lawn Service",
    "wof:placetype":"venue"
},
  "geometry": {"coordinates":[-81.103769,28.656844],"type":"Point"}
}