{
  "type": "Feature",
  "properties": {
    "iso:country":"US",
    "sg:address":"2695 Pinewood Blvd N",
    "sg:city":"Middleburg",
    "sg:classifiers":[
        {
            "category":"Building & Trades",
            "subcategory":"Construction",
            "type":"Services"
        }
    ],
    "sg:phone":"+1 904 272 5205",
    "sg:postcode":"32068",
    "sg:province":"FL",
    "sg:tags":[
        "general",
        "contractor"
    ],
    "wof:name":"Home Repair Specialist",
    "wof:placetype":"venue"
},
  "geometry": {"coordinates":[-81.786376,30.10871],"type":"Point"}
}