{
  "type": "Feature",
  "properties": {
    "iso:country":"US",
    "sg:address":"975 Gateway Blvd Suites 101 - 105",
    "sg:city":"Boynton Beach",
    "sg:classifiers":[
        {
            "category":"Professional",
            "subcategory":"Computer Services",
            "type":"Services"
        }
    ],
    "sg:phone":"+1 561 288 0552",
    "sg:postcode":"33426",
    "sg:province":"FL",
    "sg:website":"http://CoworkingFlorida.com",
    "wof:name":"Coworking Florida",
    "wof:placetype":"venue"
},
  "geometry": {"coordinates":[-80.07834699999999,26.550188],"type":"Point"}
}