{
  "type": "Feature",
  "properties": {
    "iso:country":"US",
    "sg:address":"7600 Southland Blvd",
    "sg:city":"Orlando",
    "sg:classifiers":[
        {
            "category":"Home & Garden",
            "subcategory":"Building Materials",
            "type":"Retail Goods"
        }
    ],
    "sg:phone":"+1 407 396 0997",
    "sg:postcode":"32809",
    "sg:province":"FL",
    "sg:tags":[
        "door"
    ],
    "wof:name":"First American Overhead Doors",
    "wof:placetype":"venue"
},
  "geometry": {"coordinates":[-81.40706900000001,28.452235],"type":"Point"}
}