{
  "type": "Feature",
  "properties": {
    "iso:country":"US",
    "sg:address":"2111 NW 13th St",
    "sg:city":"Gainesville",
    "sg:classifiers":[
        {
            "category":"Restaurant",
            "type":"Food & Drink"
        }
    ],
    "sg:menulink":"http://www.allmenus.com/fl/gainesville/62269-adams-rib-co/menu/",
    "sg:phone":"+1 352 373 8886",
    "sg:postcode":"32609",
    "sg:province":"FL",
    "sg:tags":[
        "barbecue",
        "american"
    ],
    "wof:name":"Adam's Rib Co.",
    "wof:placetype":"venue"
},
  "geometry": {"coordinates":[-82.33898499999999,29.672388],"type":"Point"}
}