{
  "type": "Feature",
  "properties": {
    "iso:country":"US",
    "sg:address":"4933 Tamiami Trl N",
    "sg:city":"Naples",
    "sg:classifiers":[
        {
            "category":"Professional",
            "subcategory":"Business Services",
            "type":"Services"
        }
    ],
    "sg:phone":"+1 239 403 9417",
    "sg:postcode":"34103",
    "sg:province":"FL",
    "sg:tags":[
        "interior",
        "consultant",
        "design",
        "decorator"
    ],
    "wof:name":"Lani D Designs Inc",
    "wof:placetype":"venue"
},
  "geometry": {"coordinates":[-81.80043000000001,26.207548],"type":"Point"}
}