{
  "type": "Feature",
  "properties": {
    "iso:country":"US",
    "sg:address":"28405 SW 185th Ave",
    "sg:city":"Homestead",
    "sg:classifiers":[
        {
            "category":"Wholesale",
            "subcategory":"Plants",
            "type":"Manufacturing & Wholesale Goods"
        },
        {
            "category":"Farming",
            "subcategory":"Nursery",
            "type":"Manufacturing & Wholesale Goods"
        }
    ],
    "sg:phone":"+1 305 242 0930",
    "sg:postcode":"33030",
    "sg:province":"FL",
    "sg:tags":[
        "tree",
        "grower"
    ],
    "wof:name":"Danny's Nursery Inc",
    "wof:placetype":"venue"
},
  "geometry": {"coordinates":[-80.491831,25.502625],"type":"Point"}
}