{
  "type": "Feature",
  "properties": {
    "iso:country":"US",
    "sg:address":"2309 27th St S",
    "sg:city":"Saint Petersburg",
    "sg:classifiers":[
        {
            "category":"Shopping",
            "subcategory":"Discount & Variety Stores",
            "type":"Retail Goods"
        }
    ],
    "sg:phone":"+1 727 385 9739",
    "sg:postcode":"33712",
    "sg:province":"FL",
    "sg:tags":[
        "merchandise",
        "general"
    ],
    "wof:name":"Richard Copeland",
    "wof:placetype":"venue"
},
  "geometry": {"coordinates":[-82.670366,27.747555],"type":"Point"}
}