{
  "type": "Feature",
  "properties": {
    "addr:full":"17976 Temple Blvd Loxahatchee FL 33470",
    "addr:housenumber":"17976",
    "addr:postcode":"33470",
    "addr:street":"Temple Blvd",
    "iso:country":"US",
    "sg:address":"17976 Temple Blvd",
    "sg:city":"Loxahatchee",
    "sg:classifiers":[
        {
            "category":"Wholesale",
            "subcategory":"Home Furnishings",
            "type":"Manufacturing & Wholesale Goods"
        }
    ],
    "sg:phone":"+1 561 753 7825",
    "sg:postcode":"33470",
    "sg:province":"FL",
    "wof:name":"Peek A Boo Home Parties",
    "wof:placetype":"venue"
},
  "geometry": {"coordinates":[-80.326638,26.794754],"type":"Point"}
}