{
  "type": "Feature",
  "properties": {
    "iso:country":"US",
    "sg:address":"2453 NW 7th Ave",
    "sg:city":"Miami",
    "sg:classifiers":[
        {
            "category":"Bus Charters",
            "type":"Transportation"
        }
    ],
    "sg:phone":"+1 786 621 5443",
    "sg:postcode":"33127",
    "sg:province":"FL",
    "sg:tags":[
        "buses-charter",
        "rental"
    ],
    "wof:name":"Mr Auto Bus International Corp",
    "wof:placetype":"venue"
},
  "geometry": {"coordinates":[-80.207185,25.800328],"type":"Point"}
}