{
  "type": "Feature",
  "properties": {
    "addr:full":"3184 S Congress Ave Lake Worth FL 33461",
    "addr:housenumber":"3184",
    "addr:postcode":"33461",
    "addr:street":"S Congress Ave",
    "iso:country":"US",
    "sg:address":"3184 S Congress Ave",
    "sg:city":"Lake Worth",
    "sg:classifiers":[
        {
            "category":"Shopping",
            "subcategory":"Pharmacy",
            "type":"Retail Goods"
        }
    ],
    "sg:phone":"+1 561 968 6206",
    "sg:postcode":"33461",
    "sg:province":"FL",
    "wof:name":"Walgreens",
    "wof:placetype":"venue"
},
  "geometry": {"coordinates":[-80.088528,26.631484],"type":"Point"}
}