{
  "type": "Feature",
  "properties": {
    "iso:country":"US",
    "sg:address":"2469 W US Hwy 90",
    "sg:city":"Lake City",
    "sg:classifiers":[
        {
            "category":"Food & Beverages",
            "subcategory":"Specialty",
            "type":"Retail Goods"
        }
    ],
    "sg:phone":"+1 386 758 0031",
    "sg:postcode":"32055",
    "sg:province":"FL",
    "sg:tags":[
        "tea",
        "coffee"
    ],
    "wof:name":"Coffee House",
    "wof:placetype":"venue"
},
  "geometry": {"coordinates":[-82.656346,30.183338],"type":"Point"}
}