{
  "type": "Feature",
  "properties": {
    "addr:full":"5470 Highway Ave Jacksonville FL 32254",
    "addr:housenumber":"5470",
    "addr:postcode":"32254",
    "addr:street":"Highway Ave",
    "iso:country":"US",
    "sg:address":"5470 Highway Ave",
    "sg:city":"Jacksonville",
    "sg:classifiers":[
        {
            "category":"Retail",
            "subcategory":"Auto Repair",
            "type":"Services"
        }
    ],
    "sg:phone":"+1 904 693 2627",
    "sg:postcode":"32254",
    "sg:province":"FL",
    "sg:tags":[
        "wrecker"
    ],
    "wof:name":"Bob's Towing & Recovery Inc",
    "wof:placetype":"venue"
},
  "geometry": {"coordinates":[-81.740808,30.321312],"type":"Point"}
}