{
  "type": "Feature",
  "properties": {
    "iso:country":"US",
    "sg:address":"860 N Federal Hwy",
    "sg:city":"Pompano Beach",
    "sg:classifiers":[
        {
            "category":"Food & Beverages",
            "subcategory":"Bakery",
            "type":"Retail Goods"
        }
    ],
    "sg:phone":"+1 954 782 3331",
    "sg:postcode":"33062",
    "sg:province":"FL",
    "wof:name":"Ferraros Italian Bakery",
    "wof:placetype":"venue"
},
  "geometry": {"coordinates":[-80.102486,26.239598],"type":"Point"}
}