{
  "type": "Feature",
  "properties": {
    "iso:country":"US",
    "sg:address":"3225 Mason Rd",
    "sg:city":"Pensacola",
    "sg:classifiers":[
        {
            "category":"Building & Trades",
            "subcategory":"Construction",
            "type":"Services"
        }
    ],
    "sg:phone":"+1 850 944 3032",
    "sg:postcode":"32568",
    "sg:province":"FL",
    "sg:tags":[
        "contractor"
    ],
    "wof:name":"Celebrity Home Builders Inc",
    "wof:placetype":"venue"
},
  "geometry": {"coordinates":[-87.42179400000001,30.846326],"type":"Point"}
}