{
  "type": "Feature",
  "properties": {
    "iso:country":"US",
    "sg:address":"14707 Laurel Lake Ln",
    "sg:city":"Lutz",
    "sg:classifiers":[
        {
            "category":"Building & Trades",
            "subcategory":"Construction",
            "type":"Services"
        }
    ],
    "sg:phone":"+1 813 263 4220",
    "sg:postcode":"33559",
    "sg:province":"FL",
    "sg:tags":[
        "handyman"
    ],
    "wof:name":"Ronjon Maintenance Inc",
    "wof:placetype":"venue"
},
  "geometry": {"coordinates":[-82.422907,28.082982],"type":"Point"}
}