{
  "type": "Feature",
  "properties": {
    "iso:country":"US",
    "sg:address":"6240 Shirley St",
    "sg:city":"Naples",
    "sg:classifiers":[
        {
            "category":"Building & Trades",
            "subcategory":"Construction",
            "type":"Services"
        }
    ],
    "sg:phone":"+1 239 591 4999",
    "sg:postcode":"34109",
    "sg:province":"FL",
    "sg:tags":[
        "tile",
        "dealer"
    ],
    "wof:name":"Treasure Tile Inc",
    "wof:placetype":"venue"
},
  "geometry": {"coordinates":[-81.781558,26.221067],"type":"Point"}
}