{
  "type": "Feature",
  "properties": {
    "iso:country":"US",
    "sg:address":"5312 Cliff St",
    "sg:city":"Graceville",
    "sg:classifiers":[
        {
            "category":"Government",
            "subcategory":"Office",
            "type":"Public Place"
        }
    ],
    "sg:phone":"+1 850 263 3204",
    "sg:postcode":"32440",
    "sg:province":"FL",
    "sg:tags":[
        "government-state"
    ],
    "wof:name":"State of Florida",
    "wof:placetype":"venue"
},
  "geometry": {"coordinates":[-85.51401300000001,30.955073],"type":"Point"}
}