{
  "type": "Feature",
  "properties": {
    "iso:country":"US",
    "sg:address":"11571 San Jose Blvd",
    "sg:city":"Jacksonville",
    "sg:classifiers":[
        {
            "category":"Health Services",
            "subcategory":"Doctor",
            "type":"Services"
        }
    ],
    "sg:phone":"+1 904 268 1285",
    "sg:postcode":"32223",
    "sg:province":"FL",
    "sg:tags":[
        "dentist"
    ],
    "wof:name":"Brace Place",
    "wof:placetype":"venue"
},
  "geometry": {"coordinates":[-81.632575,30.16141],"type":"Point"}
}