{
  "type": "Feature",
  "properties": {
    "addr:full":"4535 S Florida Ave Lakeland FL 33813",
    "addr:housenumber":"4535",
    "addr:postcode":"33813",
    "addr:street":"S Florida Ave",
    "iso:country":"US",
    "sg:address":"4535 S Florida Ave",
    "sg:city":"Lakeland",
    "sg:classifiers":[
        {
            "category":"Banks & Credit Unions",
            "subcategory":"Bank",
            "type":"Services"
        }
    ],
    "sg:phone":"+1 863 644 6618",
    "sg:postcode":"33813",
    "sg:province":"FL",
    "wof:name":"Amsouth Bank",
    "wof:placetype":"venue"
},
  "geometry": {"coordinates":[-81.95696700000001,27.983363],"type":"Point"}
}