{
  "type": "Feature",
  "properties": {
    "addr:full":"17889 SE 158th Ct Weirsdale FL 32195",
    "addr:postcode":"17889;32195",
    "addr:street":"Se 158Th Ct",
    "iso:country":"US",
    "sg:address":"17889 SE 158th Ct",
    "sg:city":"Weirsdale",
    "sg:classifiers":[
        {
            "category":"Shopping",
            "subcategory":"Books",
            "type":"Retail Goods"
        }
    ],
    "sg:phone":"+1 352 821 2828",
    "sg:postcode":"32195",
    "sg:province":"FL",
    "wof:name":"Fly-Write Books",
    "wof:placetype":"venue"
},
  "geometry": {"coordinates":[-81.89021,28.963222],"type":"Point"}
}