{
  "type": "Feature",
  "properties": {
    "addr:full":"8234 NW 14th St Doral FL 33126",
    "addr:housenumber":"8234",
    "addr:postcode":"33126",
    "addr:street":"Nw 14Th St",
    "iso:country":"US",
    "sg:address":"8234 NW 14th St",
    "sg:city":"Doral",
    "sg:classifiers":[
        {
            "category":"Restaurant",
            "type":"Food & Drink"
        }
    ],
    "sg:phone":"+1 305 591 7539",
    "sg:postcode":"33126",
    "sg:province":"FL",
    "sg:tags":[
        "pizza",
        "italian"
    ],
    "sg:website":"www.dominos.com",
    "wof:name":"Domino's Pizza",
    "wof:placetype":"venue"
},
  "geometry": {"coordinates":[-80.329201,25.7864],"type":"Point"}
}