{
  "type": "Feature",
  "properties": {
    "iso:country":"US",
    "sg:address":"2357 Tamiami Trl S # 3-229",
    "sg:city":"Venice",
    "sg:classifiers":[
        {
            "category":"Professional",
            "subcategory":"Detective & Security Services",
            "type":"Services"
        }
    ],
    "sg:phone":"+1 941 375 2891",
    "sg:postcode":"34293",
    "sg:province":"FL",
    "sg:tags":[
        "private",
        "investigator"
    ],
    "wof:name":"Tr Vst Investigations",
    "wof:placetype":"venue"
},
  "geometry": {"coordinates":[-82.406249,27.050207],"type":"Point"}
}