{
  "type": "Feature",
  "properties": {
    "iso:country":"US",
    "sg:address":"400 Lake Blvd",
    "sg:city":"Sanford",
    "sg:classifiers":[
        {
            "category":"Education",
            "subcategory":"School",
            "type":"Public Place"
        }
    ],
    "sg:phone":"+1 407 320 0238",
    "sg:postcode":"32773",
    "sg:province":"FL",
    "wof:name":"John Polk Alternative School",
    "wof:placetype":"venue"
},
  "geometry": {"coordinates":[-81.31199599999999,28.782869],"type":"Point"}
}