{
  "type": "Feature",
  "properties": {
    "iso:country":"US",
    "sg:address":"11610 SE US Hwy 301",
    "sg:city":"Belleview",
    "sg:classifiers":[
        {
            "category":"Building & Trades",
            "subcategory":"Construction",
            "type":"Services"
        }
    ],
    "sg:phone":"+1 352 347 8397",
    "sg:postcode":"34420",
    "sg:province":"FL",
    "sg:tags":[
        "masonry",
        "contractor"
    ],
    "wof:name":"Jason Ross Masonry",
    "wof:placetype":"venue"
},
  "geometry": {"coordinates":[-82.04709,29.053907],"type":"Point"}
}