{
  "type": "Feature",
  "properties": {
    "addr:full":"8228 W Charmaine Dr Homosassa FL 34448",
    "addr:housenumber":"8228",
    "addr:postcode":"34448",
    "addr:street":"W Charmaine Dr",
    "iso:country":"US",
    "sg:address":"8228 W Charmaine Dr",
    "sg:city":"Homosassa",
    "sg:classifiers":[
        {
            "category":"Real Estate",
            "subcategory":"Real Estate Operator",
            "type":"Services"
        }
    ],
    "sg:phone":"+1 352 628 4304",
    "sg:postcode":"34448",
    "sg:province":"FL",
    "sg:tags":[
        "mobile",
        "home",
        "community"
    ],
    "wof:name":"Stonebrook Park",
    "wof:placetype":"venue"
},
  "geometry": {"coordinates":[-82.570522,28.823916],"type":"Point"}
}