{
  "type": "Feature",
  "properties": {
    "iso:country":"US",
    "sg:address":"1121 E Commercial Blvd",
    "sg:city":"Oakland Park",
    "sg:classifiers":[
        {
            "category":"Building & Trades",
            "subcategory":"Landscaping Services",
            "type":"Services"
        }
    ],
    "sg:phone":"+1 954 771 6123",
    "sg:postcode":"33334",
    "sg:province":"FL",
    "sg:tags":[
        "designer",
        "landscape"
    ],
    "wof:name":"Supreme Nursery",
    "wof:placetype":"venue"
},
  "geometry": {"coordinates":[-80.13212900000001,26.188947],"type":"Point"}
}