{
  "type": "Feature",
  "properties": {
    "iso:country":"US",
    "sg:address":"5805 Saufley Field Rd",
    "sg:city":"Pensacola",
    "sg:classifiers":[
        {
            "category":"Building & Trades",
            "subcategory":"Construction",
            "type":"Services"
        }
    ],
    "sg:phone":"+1 850 453 1253",
    "sg:postcode":"32526",
    "sg:province":"FL",
    "sg:tags":[
        "paving",
        "contractor"
    ],
    "wof:name":"Heaton Brothers Construction",
    "wof:placetype":"venue"
},
  "geometry": {"coordinates":[-87.331444,30.461725],"type":"Point"}
}