{
  "type": "Feature",
  "properties": {
    "iso:country":"US",
    "sg:address":"1642 N Volusia Ave",
    "sg:city":"Orange City",
    "sg:classifiers":[
        {
            "category":"Real Estate",
            "subcategory":"Surveying",
            "type":"Services"
        }
    ],
    "sg:phone":"+1 386 775 1616",
    "sg:postcode":"32763",
    "sg:province":"FL",
    "wof:name":"Keith and Schnars PA",
    "wof:placetype":"venue"
},
  "geometry": {"coordinates":[-81.298683,28.962495],"type":"Point"}
}