{
  "type": "Feature",
  "properties": {
    "iso:country":"US",
    "sg:address":"3157 W International Speedway Blvd",
    "sg:city":"Daytona Beach",
    "sg:classifiers":[
        {
            "category":"Wholesale",
            "subcategory":"Auto Parts",
            "type":"Manufacturing & Wholesale Goods"
        }
    ],
    "sg:phone":"+1 386 255 8485",
    "sg:postcode":"32124",
    "sg:province":"FL",
    "sg:tags":[
        "automobile",
        "rebuilt"
    ],
    "wof:name":"Speedway Pull & Save Auto Prts",
    "wof:placetype":"venue"
},
  "geometry": {"coordinates":[-81.10383400000001,29.154862],"type":"Point"}
}