{
  "type": "Feature",
  "properties": {
    "addr:full":"1561 W 13th St West Palm Beach FL 33404",
    "addr:housenumber":"1561",
    "addr:postcode":"33404",
    "addr:street":"W 13Th St",
    "iso:country":"US",
    "sg:address":"1561 W 13th St",
    "sg:city":"West Palm Beach",
    "sg:classifiers":[
        {
            "category":"Travel",
            "subcategory":"Travel Agent",
            "type":"Entertainment"
        }
    ],
    "sg:phone":"+1 561 842 5669",
    "sg:postcode":"33404",
    "sg:province":"FL",
    "sg:tags":[
        "agency"
    ],
    "wof:name":"Ram & Rime LLC",
    "wof:placetype":"venue"
},
  "geometry": {"coordinates":[-80.082309,26.774242],"type":"Point"}
}