{
  "type": "Feature",
  "properties": {
    "addr:full":"311 SW 17th St Fort Lauderdale FL 33315",
    "addr:housenumber":"311",
    "addr:postcode":"33315",
    "addr:street":"Sw 17Th St",
    "iso:country":"US",
    "sg:address":"311 SW 17th St",
    "sg:city":"Fort Lauderdale",
    "sg:classifiers":[
        {
            "category":"Retail",
            "subcategory":"Repair Shop",
            "type":"Services"
        }
    ],
    "sg:phone":"+1 954 467 3716",
    "sg:postcode":"33315",
    "sg:province":"FL",
    "sg:tags":[
        "repairing",
        "piano",
        "refinishing"
    ],
    "wof:name":"Zehme Uwe RTT",
    "wof:placetype":"venue"
},
  "geometry": {"coordinates":[-80.14672400000001,26.100212],"type":"Point"}
}