{
  "type": "Feature",
  "properties": {
    "addr:full":"7000 Pine Forest Rd Pensacola FL 32526",
    "addr:housenumber":"7000",
    "addr:postcode":"32526",
    "addr:street":"Pine Forest Rd",
    "iso:country":"US",
    "sg:address":"7000 Pine Forest Rd",
    "sg:city":"Pensacola",
    "sg:classifiers":[
        {
            "category":"Wholesale",
            "subcategory":"Metals & Minerals",
            "type":"Manufacturing & Wholesale Goods"
        }
    ],
    "sg:phone":"+1 850 944 7757",
    "sg:postcode":"32526",
    "sg:province":"FL",
    "sg:tags":[
        "pipe"
    ],
    "wof:name":"Hanson Pipe & Prod Southeast",
    "wof:placetype":"venue"
},
  "geometry": {"coordinates":[-87.30607500000001,30.490077],"type":"Point"}
}