{
  "type": "Feature",
  "properties": {
    "iso:country":"US",
    "sg:address":"27870 Old 41 Rd",
    "sg:city":"Bonita Springs",
    "sg:classifiers":[
        {
            "category":"Home & Garden",
            "subcategory":"Furniture",
            "type":"Retail Goods"
        }
    ],
    "sg:phone":"+1 239 992 2255",
    "sg:postcode":"34135",
    "sg:province":"FL",
    "sg:tags":[
        "major",
        "floor",
        "covering"
    ],
    "wof:name":"Badcock Furniture Bonita Sprng",
    "wof:placetype":"venue"
},
  "geometry": {"coordinates":[-81.778907,26.332778],"type":"Point"}
}