{
  "type": "Feature",
  "properties": {
    "addr:full":"601 N Primrose Dr Orlando FL 32803",
    "addr:housenumber":"601",
    "addr:postcode":"32803",
    "addr:street":"N Primrose Dr",
    "iso:country":"US",
    "sg:address":"601 N Primrose Dr",
    "sg:city":"Orlando",
    "sg:classifiers":[
        {
            "category":"Real Estate",
            "subcategory":"Real Estate Agent",
            "type":"Services"
        }
    ],
    "sg:phone":"+1 407 898 7001",
    "sg:postcode":"32803",
    "sg:province":"FL",
    "sg:tags":[
        "broker"
    ],
    "wof:name":"Century 21",
    "wof:placetype":"venue"
},
  "geometry": {"coordinates":[-81.34790700000001,28.553255],"type":"Point"}
}