{
  "type": "Feature",
  "properties": {
    "iso:country":"US",
    "sg:address":"11440 SW 88th St",
    "sg:city":"Miami",
    "sg:classifiers":[
        {
            "category":"Banks & Credit Unions",
            "subcategory":"Bank",
            "type":"Services"
        }
    ],
    "sg:phone":"+1 305 596 5880",
    "sg:postcode":"33176",
    "sg:province":"FL",
    "sg:tags":[
        "loan",
        "real estate"
    ],
    "wof:name":"Premiere Mortgage Corp",
    "wof:placetype":"venue"
},
  "geometry": {"coordinates":[-80.378344,25.68667],"type":"Point"}
}