{
  "type": "Feature",
  "properties": {
    "iso:country":"US",
    "sg:address":"6005 Silver Star Rd",
    "sg:city":"Orlando",
    "sg:classifiers":[
        {
            "category":"Shopping",
            "type":"Retail Goods"
        }
    ],
    "sg:phone":"+1 407 298 7834",
    "sg:postcode":"32808",
    "sg:province":"FL",
    "sg:tags":[
        "equipment",
        "clothing",
        "safety"
    ],
    "wof:name":"SafeRidge USA",
    "wof:placetype":"venue"
},
  "geometry": {"coordinates":[-81.464375,28.577907],"type":"Point"}
}