{
  "type": "Feature",
  "properties": {
    "addr:full":"2049 NW 141st St Opa Locka FL 33054",
    "addr:housenumber":"2049",
    "addr:postcode":"33054",
    "addr:street":"Nw 141St St;Locka",
    "iso:country":"US",
    "sg:address":"2049 NW 141st St",
    "sg:city":"Opa Locka",
    "sg:classifiers":[
        {
            "category":"Wholesale",
            "subcategory":"Auto Parts",
            "type":"Manufacturing & Wholesale Goods"
        }
    ],
    "sg:phone":"+1 305 685 6815",
    "sg:postcode":"33054",
    "sg:province":"FL",
    "sg:tags":[
        "turbochargers"
    ],
    "wof:name":"Almar Diesel Svc",
    "wof:placetype":"venue"
},
  "geometry": {"coordinates":[-80.23290900000001,25.903064],"type":"Point"}
}