{
  "type": "Feature",
  "properties": {
    "iso:country":"US",
    "sg:address":"20423 State Rd 7",
    "sg:city":"Boca Raton",
    "sg:classifiers":[
        {
            "category":"Real Estate",
            "subcategory":"Real Estate Agent",
            "type":"Services"
        }
    ],
    "sg:phone":"+1 561 488 3012",
    "sg:postcode":"33498",
    "sg:province":"FL",
    "sg:tags":[
        "property",
        "appraisal"
    ],
    "wof:name":"Frazer J R Reserves Appraisal",
    "wof:placetype":"venue"
},
  "geometry": {"coordinates":[-80.20355499999999,26.370032],"type":"Point"}
}