{
  "type": "Feature",
  "properties": {
    "iso:country":"US",
    "sg:address":"608 S US Hwy 1",
    "sg:city":"Fort Pierce",
    "sg:classifiers":[
        {
            "category":"Professional",
            "subcategory":"Employment Agencies",
            "type":"Services"
        }
    ],
    "sg:phone":"+1 772 467 9993",
    "sg:postcode":"34950",
    "sg:province":"FL",
    "sg:tags":[
        "opportunity"
    ],
    "wof:name":"Able Body Labor",
    "wof:placetype":"venue"
},
  "geometry": {"coordinates":[-80.325835,27.442005],"type":"Point"}
}