{
  "type": "Feature",
  "properties": {
    "iso:country":"US",
    "sg:address":"801 NW 3rd St",
    "sg:city":"Mulberry",
    "sg:classifiers":[
        {
            "category":"Social Services",
            "subcategory":"Child Care",
            "type":"Services"
        },
        {
            "category":"Education",
            "subcategory":"Preschool",
            "type":"Public Place"
        }
    ],
    "sg:phone":"+1 863 869 9624",
    "sg:postcode":"33860",
    "sg:province":"FL",
    "sg:tags":[
        "kindergarten"
    ],
    "wof:name":"Just 4 Kids Preschool",
    "wof:placetype":"venue"
},
  "geometry": {"coordinates":[-81.98056,27.897511],"type":"Point"}
}