{
  "type": "Feature",
  "properties": {
    "addr:full":"1451 Idlewild Ct Sarasota FL 34243",
    "addr:housenumber":"1451",
    "addr:postcode":"34243",
    "addr:street":"Idlewild Ct",
    "iso:country":"US",
    "sg:address":"1451 Idlewild Ct",
    "sg:city":"Sarasota",
    "sg:classifiers":[
        {
            "category":"Building & Trades",
            "subcategory":"Construction",
            "type":"Services"
        }
    ],
    "sg:phone":"+1 941 758 7370",
    "sg:postcode":"34243",
    "sg:province":"FL",
    "sg:tags":[
        "masonry",
        "contractor"
    ],
    "wof:name":"Mc Bride's Concrete Constr",
    "wof:placetype":"venue"
},
  "geometry": {"coordinates":[-82.55001300000001,27.417021],"type":"Point"}
}