{
  "type": "Feature",
  "properties": {
    "addr:full":"2431 NW 41 St Gainesville FL 32606",
    "addr:housenumber":"2431",
    "addr:postcode":"32606",
    "addr:street":"Nw 41 St",
    "iso:country":"US",
    "sg:address":"2431 NW 41 St",
    "sg:city":"Gainesville",
    "sg:classifiers":[
        {
            "category":"Real Estate",
            "subcategory":"Real Estate Operator",
            "type":"Services"
        }
    ],
    "sg:phone":"+1 352 378 0773",
    "sg:postcode":"32606",
    "sg:province":"FL",
    "sg:tags":[
        "building",
        "apartment"
    ],
    "wof:name":"Atrium Retirement Residence",
    "wof:placetype":"venue"
},
  "geometry": {"coordinates":[-82.38633400000001,29.673256],"type":"Point"}
}