{
  "type": "Feature",
  "properties": {
    "addr:full":"1412 Rupp Ln Lake Worth FL 33460",
    "addr:housenumber":"1412",
    "addr:postcode":"33460",
    "addr:street":"Rupp Ln",
    "iso:country":"US",
    "sg:address":"1412 Rupp Ln",
    "sg:city":"Lake Worth",
    "sg:classifiers":[
        {
            "category":"Home & Garden",
            "subcategory":"Building Materials",
            "type":"Retail Goods"
        }
    ],
    "sg:phone":"+1 561 585 9511",
    "sg:postcode":"33460",
    "sg:province":"FL",
    "sg:tags":[
        "door"
    ],
    "sg:website":"www.bikerswebsite.com",
    "wof:name":"Carl Salvo Inc",
    "wof:placetype":"venue"
},
  "geometry": {"coordinates":[-80.06131600000001,26.644209],"type":"Point"}
}