{
  "type": "Feature",
  "properties": {
    "addr:full":"10800 US Hwy 301 Dade City FL 33525",
    "addr:housenumber":"10800",
    "addr:postcode":"33525",
    "addr:street":"Us Hwy 301",
    "iso:country":"US",
    "sg:address":"10800 US Hwy 301",
    "sg:city":"Dade City",
    "sg:classifiers":[
        {
            "category":"Wholesale",
            "subcategory":"Electrical",
            "type":"Manufacturing & Wholesale Goods"
        }
    ],
    "sg:phone":"+1 352 567 6146",
    "sg:postcode":"33525",
    "sg:province":"FL",
    "sg:tags":[
        "communication",
        "radio",
        "system"
    ],
    "wof:name":"Electronics & Communications",
    "wof:placetype":"venue"
},
  "geometry": {"coordinates":[-82.187656,28.31429],"type":"Point"}
}