{
  "type": "Feature",
  "properties": {
    "addr:full":"4421 NW 70th Ave Fort Lauderdale FL 33319",
    "addr:housenumber":"4421",
    "addr:postcode":"33319",
    "addr:street":"Nw 70Th Ave",
    "iso:country":"US",
    "sg:address":"4421 NW 70th Ave",
    "sg:city":"Fort Lauderdale",
    "sg:classifiers":[
        {
            "category":"Professional",
            "subcategory":"Business Services",
            "type":"Services"
        }
    ],
    "sg:phone":"+1 954 747 5411",
    "sg:postcode":"33319",
    "sg:province":"FL",
    "wof:name":"Dwyer Design Group Inc",
    "wof:placetype":"venue"
},
  "geometry": {"coordinates":[-80.24354,26.180311],"type":"Point"}
}