{
  "type": "Feature",
  "properties": {
    "addr:full":"1816 US Hwy 19 Holiday FL 34691",
    "addr:housenumber":"1816",
    "addr:postcode":"34691",
    "addr:street":"Us Hwy 19",
    "iso:country":"US",
    "sg:address":"1816 US Hwy 19",
    "sg:city":"Holiday",
    "sg:classifiers":[
        {
            "category":"Farming",
            "subcategory":"Orchard",
            "type":"Manufacturing & Wholesale Goods"
        }
    ],
    "sg:phone":"+1 727 934 0566",
    "sg:postcode":"34691",
    "sg:province":"FL",
    "sg:tags":[
        "grove",
        "management"
    ],
    "wof:name":"Citrus Country Groves",
    "wof:placetype":"venue"
},
  "geometry": {"coordinates":[-82.740003,28.187651],"type":"Point"}
}