{
  "type": "Feature",
  "properties": {
    "iso:country":"US",
    "sg:address":"517 S 33rd St",
    "sg:city":"Fort Pierce",
    "sg:classifiers":[
        {
            "category":"Building & Trades",
            "subcategory":"Equipment Rental",
            "type":"Services"
        }
    ],
    "sg:phone":"+1 772 461 6604",
    "sg:postcode":"34947",
    "sg:province":"FL",
    "sg:tags":[
        "yard"
    ],
    "wof:name":"Chandler Equipment Co Inc",
    "wof:placetype":"venue"
},
  "geometry": {"coordinates":[-80.358152,27.443222],"type":"Point"}
}