{
  "type": "Feature",
  "properties": {
    "iso:country":"US",
    "sg:address":"1717 N Bayshore Dr Ste 127",
    "sg:city":"Miami",
    "sg:classifiers":[
        {
            "category":"Parking",
            "type":"Transportation"
        }
    ],
    "sg:phone":"+1 305 932 8600",
    "sg:postcode":"33132",
    "sg:province":"FL",
    "wof:name":"Double Park Llc",
    "wof:placetype":"venue"
},
  "geometry": {"coordinates":[-80.186938,25.791995],"type":"Point"}
}