{
  "type": "Feature",
  "properties": {
    "iso:country":"US",
    "sg:address":"7162 Phillips Hwy",
    "sg:city":"Jacksonville",
    "sg:classifiers":[
        {
            "category":"Utilities",
            "subcategory":"Fuel Oil & Lpg",
            "type":"Services"
        }
    ],
    "sg:phone":"+1 904 296 1029",
    "sg:postcode":"32256",
    "sg:province":"FL",
    "sg:tags":[
        "propane",
        "gas"
    ],
    "wof:name":"Sawco Propane",
    "wof:placetype":"venue"
},
  "geometry": {"coordinates":[-81.59991599999999,30.243676],"type":"Point"}
}