{
  "type": "Feature",
  "properties": {
    "addr:full":"647 Lincoln Rd Miami Beach FL 33139",
    "addr:housenumber":"647",
    "addr:postcode":"33139",
    "addr:street":"Lincoln Rd",
    "iso:country":"US",
    "sg:address":"647 Lincoln Rd",
    "sg:city":"Miami Beach",
    "sg:classifiers":[
        {
            "category":"Restaurant",
            "type":"Food & Drink"
        }
    ],
    "sg:phone":"+1 305 672 7112",
    "sg:postcode":"33139",
    "sg:province":"FL",
    "sg:tags":[
        "thai",
        "sushi",
        "bar"
    ],
    "wof:name":"Sushi Siam",
    "wof:placetype":"venue"
},
  "geometry": {"coordinates":[-80.135201,25.790501],"type":"Point"}
}