{
  "type": "Feature",
  "properties": {
    "addr:full":"115 Deerpath Dr Oldsmar FL 34677",
    "addr:housenumber":"115",
    "addr:postcode":"34677",
    "addr:street":"Deerpath Dr",
    "iso:country":"US",
    "sg:address":"115 Deerpath Dr",
    "sg:city":"Oldsmar",
    "sg:classifiers":[
        {
            "category":"Shopping",
            "subcategory":"Pharmacy",
            "type":"Retail Goods"
        }
    ],
    "sg:phone":"+1 727 773 9849",
    "sg:postcode":"34677",
    "sg:province":"FL",
    "wof:name":"Pharm Advantage Inc",
    "wof:placetype":"venue"
},
  "geometry": {"coordinates":[-82.69932,28.073112],"type":"Point"}
}