{
  "type": "Feature",
  "properties": {
    "addr:full":"1241 Gulf of Mexico Dr Longboat Key FL 34228",
    "addr:housenumber":"1241",
    "addr:postcode":"34228",
    "addr:street":"Gulf",
    "iso:country":"US",
    "sg:address":"1241 Gulf of Mexico Dr",
    "sg:city":"Longboat Key",
    "sg:classifiers":[
        {
            "category":"Professional",
            "subcategory":"Business Services",
            "type":"Services"
        }
    ],
    "sg:phone":"+1 941 387 0706",
    "sg:postcode":"34228",
    "sg:province":"FL",
    "sg:tags":[
        "interior",
        "consultant",
        "design",
        "decorator"
    ],
    "wof:name":"Interiors By Marilyn Bezner",
    "wof:placetype":"venue"
},
  "geometry": {"coordinates":[-82.608622,27.351041],"type":"Point"}
}