{
  "type": "Feature",
  "properties": {
    "iso:country":"US",
    "sg:address":"855 Golfview Ave",
    "sg:city":"Bartow",
    "sg:classifiers":[
        {
            "category":"Building & Trades",
            "subcategory":"Construction",
            "type":"Services"
        }
    ],
    "sg:phone":"+1 863 533 6533",
    "sg:postcode":"33830",
    "sg:province":"FL",
    "sg:tags":[
        "general",
        "contractor"
    ],
    "wof:name":"E G & S Builds",
    "wof:placetype":"venue"
},
  "geometry": {"coordinates":[-81.822529,27.886767],"type":"Point"}
}