{
  "type": "Feature",
  "properties": {
    "iso:country":"US",
    "sg:address":"4510 W State Road 46",
    "sg:city":"Sanford",
    "sg:classifiers":[
        {
            "category":"Bakery",
            "type":"Food & Drink"
        },
        {
            "category":"Coffee & Tea",
            "type":"Food & Drink"
        },
        {
            "category":"Bagels",
            "type":"Food & Drink"
        },
        {
            "category":"Donuts",
            "type":"Food & Drink"
        }
    ],
    "sg:menulink":"http://www.allmenus.com/fl/sanford/138121-dunkin-donuts/menu/",
    "sg:phone":"+1 407 320 0855",
    "sg:postcode":"32771",
    "sg:province":"FL",
    "sg:tags":[
        "american",
        "pastry"
    ],
    "wof:name":"Dunkin' Donuts",
    "wof:placetype":"venue"
},
  "geometry": {"coordinates":[-81.328418,28.811839],"type":"Point"}
}