{
  "type": "Feature",
  "properties": {
    "addr:full":"218 W Michigan St Orlando FL 32806",
    "addr:housenumber":"218",
    "addr:postcode":"32806",
    "addr:street":"W Michigan St",
    "iso:country":"US",
    "sg:address":"218 W Michigan St",
    "sg:city":"Orlando",
    "sg:classifiers":[
        {
            "category":"Personal",
            "subcategory":"Barber",
            "type":"Services"
        }
    ],
    "sg:phone":"+1 407 841 8981",
    "sg:postcode":"32806",
    "sg:province":"FL",
    "wof:name":"Mug'n Brush Hair Design Ctr",
    "wof:placetype":"venue"
},
  "geometry": {"coordinates":[-81.38280399999999,28.512785],"type":"Point"}
}