{
  "type": "Feature",
  "properties": {
    "iso:country":"US",
    "sg:address":"7226 N Cortez Ave",
    "sg:city":"Tampa",
    "sg:classifiers":[
        {
            "category":"Organizations",
            "subcategory":"Religious Organization",
            "type":"Services"
        }
    ],
    "sg:phone":"+1 813 885 3977",
    "sg:postcode":"33614",
    "sg:province":"FL",
    "sg:tags":[
        "church"
    ],
    "wof:name":"Basilio Scientific School Assn",
    "wof:placetype":"venue"
},
  "geometry": {"coordinates":[-82.507445,28.016321],"type":"Point"}
}