{
  "type": "Feature",
  "properties": {
    "addr:full":"2946 NE 19th Dr Gainesville FL 32609",
    "addr:housenumber":"2946",
    "addr:postcode":"32609",
    "addr:street":"Ne 19Th Dr",
    "iso:country":"US",
    "sg:address":"2946 NE 19th Dr",
    "sg:city":"Gainesville",
    "sg:classifiers":[
        {
            "category":"Retail",
            "subcategory":"Auto Repair",
            "type":"Services"
        }
    ],
    "sg:phone":"+1 352 376 7315",
    "sg:postcode":"32609",
    "sg:province":"FL",
    "sg:tags":[
        "body"
    ],
    "wof:name":"Gator and Body Shop",
    "wof:placetype":"venue"
},
  "geometry": {"coordinates":[-82.298599,29.679697],"type":"Point"}
}