{
  "type": "Feature",
  "properties": {
    "iso:country":"US",
    "sg:address":"7636 Atlantic Blvd",
    "sg:city":"Jacksonville",
    "sg:classifiers":[
        {
            "category":"Manufacturing",
            "subcategory":"Motor Vehicles & Parts",
            "type":"Manufacturing & Wholesale Goods"
        }
    ],
    "sg:phone":"+1 904 727 9915",
    "sg:postcode":"32211",
    "sg:province":"FL",
    "sg:tags":[
        "repair",
        "axle"
    ],
    "wof:name":"Cv Specialist Auto Repair",
    "wof:placetype":"venue"
},
  "geometry": {"coordinates":[-81.57832500000001,30.313374],"type":"Point"}
}