{
  "type": "Feature",
  "properties": {
    "addr:full":"2207 N Harbour Dr Lynn Haven FL 32444",
    "addr:housenumber":"2207",
    "addr:postcode":"32444",
    "addr:street":"N Harbour Dr",
    "iso:country":"US",
    "sg:address":"2207 N Harbour Dr",
    "sg:city":"Lynn Haven",
    "sg:classifiers":[
        {
            "category":"Shopping",
            "type":"Retail Goods"
        }
    ],
    "sg:phone":"+1 850 265 5346",
    "sg:postcode":"32444",
    "sg:province":"FL",
    "sg:tags":[
        "merchandise"
    ],
    "wof:name":"Pinch A Penny 94",
    "wof:placetype":"venue"
},
  "geometry": {"coordinates":[-85.671976,30.237576],"type":"Point"}
}