{
  "type": "Feature",
  "properties": {
    "iso:country":"US",
    "sg:address":"8234 NW 103rd St",
    "sg:city":"Hialeah",
    "sg:classifiers":[
        {
            "category":"Shopping",
            "subcategory":"Pawn Shop",
            "type":"Retail Goods"
        }
    ],
    "sg:phone":"+1 305 558 7446",
    "sg:postcode":"33016",
    "sg:province":"FL",
    "wof:name":"Daniel Pawn Shop",
    "wof:placetype":"venue"
},
  "geometry": {"coordinates":[-80.330803,25.8694],"type":"Point"}
}