{
  "type": "Feature",
  "properties": {
    "iso:country":"US",
    "sg:address":"12098 W Sample Rd",
    "sg:city":"Coral Springs",
    "sg:classifiers":[
        {
            "category":"Shopping",
            "subcategory":"Clothing, Apparel, & Fashions",
            "type":"Retail Goods"
        }
    ],
    "sg:phone":"+1 954 323 2155",
    "sg:postcode":"33065",
    "sg:province":"FL",
    "sg:tags":[
        "garment"
    ],
    "wof:name":"Beneiora Clothing Co Inc",
    "wof:placetype":"venue"
},
  "geometry": {"coordinates":[-80.288207,26.272865],"type":"Point"}
}