{
  "type": "Feature",
  "properties": {
    "iso:country":"US",
    "sg:address":"2591 Edmond Cir",
    "sg:city":"Auburndale",
    "sg:classifiers":[
        {
            "category":"Building & Trades",
            "subcategory":"Construction",
            "type":"Services"
        }
    ],
    "sg:phone":"+1 863 967 3099",
    "sg:postcode":"33823",
    "sg:province":"FL",
    "sg:tags":[
        "welder"
    ],
    "wof:name":"Cadwalader Sr Richard J",
    "wof:placetype":"venue"
},
  "geometry": {"coordinates":[-81.825018,28.035551],"type":"Point"}
}