{
  "type": "Feature",
  "properties": {
    "iso:country":"US",
    "sg:address":"102 State Hwy 13",
    "sg:city":"Jacksonville",
    "sg:classifiers":[
        {
            "category":"Restaurant",
            "type":"Food & Drink"
        }
    ],
    "sg:phone":"+1 904 287 1787",
    "sg:postcode":"32259",
    "sg:province":"FL",
    "wof:name":"Lori's Gourmet Cafe",
    "wof:placetype":"venue"
},
  "geometry": {"coordinates":[-81.625433,30.12715],"type":"Point"}
}