{
  "type": "Feature",
  "properties": {
    "iso:country":"US",
    "sg:address":"1000 Lincoln Rd",
    "sg:city":"Miami Beach",
    "sg:classifiers":[
        {
            "category":"Building & Trades",
            "subcategory":"Electrical",
            "type":"Services"
        }
    ],
    "sg:phone":"+1 305 531 5800",
    "sg:postcode":"33139",
    "sg:province":"FL",
    "sg:tags":[
        "quality",
        "indoor",
        "inspection",
        "air"
    ],
    "wof:name":"Armor Inspection Services Corp",
    "wof:placetype":"venue"
},
  "geometry": {"coordinates":[-80.139988,25.790471],"type":"Point"}
}