{
  "type": "Feature",
  "properties": {
    "iso:country":"US",
    "sg:address":"1600 Pennsylvania Ave",
    "sg:city":"Miami Beach",
    "sg:classifiers":[
        {
            "category":"Arts & Performance",
            "subcategory":"Arts Center",
            "type":"Entertainment"
        },
        {
            "category":"Arts & Performance",
            "subcategory":"Dance",
            "type":"Entertainment"
        }
    ],
    "sg:phone":"+1 305 600 4360",
    "sg:postcode":"33139",
    "sg:province":"FL",
    "sg:tags":[
        "school",
        "performing"
    ],
    "sg:website":"www.studiotangovida.com",
    "wof:name":"Studio TangoVida",
    "wof:placetype":"venue"
},
  "geometry": {"coordinates":[-80.13459,25.789236],"type":"Point"}
}