{
  "type": "Feature",
  "properties": {
    "iso:country":"US",
    "sg:address":"12022 Gandy Blvd N",
    "sg:city":"St Petersburg",
    "sg:classifiers":[
        {
            "category":"Organizations",
            "subcategory":"Non-profit Organization",
            "type":"Services"
        },
        {
            "category":"Organizations",
            "subcategory":"Membership Organization",
            "type":"Services"
        }
    ],
    "sg:phone":"+1 727 579 1365",
    "sg:postcode":"33702",
    "sg:province":"FL",
    "wof:name":"Associated Marine Institute",
    "wof:placetype":"venue"
},
  "geometry": {"coordinates":[-82.593453,27.876327],"type":"Point"}
}