{
  "type": "Feature",
  "properties": {
    "iso:country":"US",
    "sg:address":"30 NE 40th St",
    "sg:city":"Miami",
    "sg:classifiers":[
        {
            "category":"Wholesale",
            "subcategory":"Furniture",
            "type":"Manufacturing & Wholesale Goods"
        }
    ],
    "sg:phone":"+1 305 573 9797",
    "sg:postcode":"33137",
    "sg:province":"FL",
    "sg:tags":[
        "furniture-wholesale",
        "manufacturer"
    ],
    "sg:website":"http://www.johnprotomaster.com",
    "wof:name":"Protomaster & Company",
    "wof:placetype":"venue"
},
  "geometry": {"coordinates":[-80.194856,25.813365],"type":"Point"}
}