{
  "type": "Feature",
  "properties": {
    "iso:country":"US",
    "sg:address":"2724 SW 34 St",
    "sg:city":"Gainesville",
    "sg:classifiers":[
        {
            "category":"Autos & Motor Vehicles",
            "subcategory":"Motorcycle Sales",
            "type":"Retail Goods"
        }
    ],
    "sg:phone":"+1 352 367 0665",
    "sg:postcode":"32608",
    "sg:province":"FL",
    "sg:tags":[
        "scooter"
    ],
    "wof:name":"New Scooters 4 Less",
    "wof:placetype":"venue"
},
  "geometry": {"coordinates":[-82.36827700000001,29.600657],"type":"Point"}
}