{
  "type": "Feature",
  "properties": {
    "addr:full":"1129 N Courtenay Pkwy Merritt Island FL 32953",
    "addr:housenumber":"1129",
    "addr:postcode":"32953",
    "addr:street":"N Courtenay Pkwy",
    "iso:country":"US",
    "sg:address":"1129 N Courtenay Pkwy",
    "sg:city":"Merritt Island",
    "sg:classifiers":[
        {
            "category":"Personal",
            "subcategory":"Barber",
            "type":"Services"
        }
    ],
    "sg:phone":"+1 321 452 0920",
    "sg:postcode":"32953",
    "sg:province":"FL",
    "wof:name":"Barber Shop",
    "wof:placetype":"venue"
},
  "geometry": {"coordinates":[-80.702544,28.379158],"type":"Point"}
}