{
  "type": "Feature",
  "properties": {
    "iso:country":"US",
    "sg:address":"6400 8th St SW",
    "sg:city":"West Miami",
    "sg:classifiers":[
        {
            "category":"Banks & Credit Unions",
            "subcategory":"Bank",
            "type":"Services"
        }
    ],
    "sg:phone":"+1 305 264 7211",
    "sg:postcode":"33144",
    "sg:province":"FL",
    "sg:website":"www.intercreditbank.com",
    "wof:name":"Intercredit Bank",
    "wof:placetype":"venue"
},
  "geometry": {"coordinates":[-80.300889,25.763192],"type":"Point"}
}