{
  "type": "Feature",
  "properties": {
    "iso:country":"US",
    "sg:address":"1465 NE 123rd St",
    "sg:city":"Miami",
    "sg:classifiers":[
        {
            "category":"Local Transit",
            "type":"Transportation"
        }
    ],
    "sg:phone":"+1 305 891 2389",
    "sg:postcode":"33161",
    "sg:province":"FL",
    "sg:tags":[
        "passenger"
    ],
    "wof:name":"Miamis Finest Inc",
    "wof:placetype":"venue"
},
  "geometry": {"coordinates":[-80.170272,25.890601],"type":"Point"}
}