{
  "type": "Feature",
  "properties": {
    "iso:country":"US",
    "sg:address":"8011 Thomas Dr",
    "sg:city":"Panama City",
    "sg:classifiers":[
        {
            "category":"Bars & Pubs",
            "type":"Food & Drink"
        }
    ],
    "sg:phone":"+1 850 235 1243",
    "sg:postcode":"32408",
    "sg:province":"FL",
    "wof:name":"Foghorn's Liquors",
    "wof:placetype":"venue"
},
  "geometry": {"coordinates":[-85.782585,30.163169],"type":"Point"}
}