{
  "type": "Feature",
  "properties": {
    "iso:country":"US",
    "sg:address":"1965 Schnoor Rd",
    "sg:city":"Jay",
    "sg:classifiers":[
        {
            "category":"Building & Trades",
            "subcategory":"Construction",
            "type":"Services"
        }
    ],
    "sg:phone":"+1 850 995 8582",
    "sg:postcode":"32565",
    "sg:province":"FL",
    "sg:tags":[
        "equipment",
        "supply",
        "drywall",
        "contractor"
    ],
    "wof:name":"Mitch Smith Drywall",
    "wof:placetype":"venue"
},
  "geometry": {"coordinates":[-87.237156,30.792989],"type":"Point"}
}