{
  "type": "Feature",
  "properties": {
    "iso:country":"US",
    "sg:address":"10026 W McNab Rd",
    "sg:city":"Fort Lauderdale",
    "sg:classifiers":[
        {
            "category":"Bars & Pubs",
            "type":"Food & Drink"
        }
    ],
    "sg:phone":"+1 954 720 7560",
    "sg:postcode":"33321",
    "sg:province":"FL",
    "sg:tags":[
        "drinking"
    ],
    "wof:name":"Calico Jack",
    "wof:placetype":"venue"
},
  "geometry": {"coordinates":[-80.291377,26.208241],"type":"Point"}
}