{
  "type": "Feature",
  "properties": {
    "addr:full":"205 Albert Ln Port Charlotte FL 33954",
    "addr:housenumber":"205",
    "addr:postcode":"33954",
    "addr:street":"Albert Ln",
    "iso:country":"US",
    "sg:address":"205 Albert Ln",
    "sg:city":"Port Charlotte",
    "sg:classifiers":[
        {
            "category":"Building & Trades",
            "subcategory":"Construction",
            "type":"Services"
        }
    ],
    "sg:phone":"+1 941 625 7618",
    "sg:postcode":"33954",
    "sg:province":"FL",
    "sg:tags":[
        "residential",
        "designer"
    ],
    "wof:name":"Thomas Adamo Designer",
    "wof:placetype":"venue"
},
  "geometry": {"coordinates":[-82.059074,27.026441],"type":"Point"}
}