{
  "type": "Feature",
  "properties": {
    "addr:full":"1504 N Nebraska Ave Tampa FL 33602",
    "addr:housenumber":"1504",
    "addr:postcode":"33602",
    "addr:street":"N Nebraska Ave",
    "iso:country":"US",
    "sg:address":"1504 N Nebraska Ave",
    "sg:city":"Tampa",
    "sg:classifiers":[
        {
            "category":"Bars & Pubs",
            "type":"Food & Drink"
        }
    ],
    "sg:phone":"+1 813 221 3777",
    "sg:postcode":"33602",
    "sg:province":"FL",
    "sg:tags":[
        "drinking"
    ],
    "wof:name":"Lucky Lounge",
    "wof:placetype":"venue"
},
  "geometry": {"coordinates":[-82.45133300000001,27.957092],"type":"Point"}
}