{
  "type": "Feature",
  "properties": {
    "addr:full":"301 S Monroe St Tallahassee FL 32301",
    "addr:housenumber":"301",
    "addr:postcode":"32301",
    "addr:street":"S Monroe St",
    "iso:country":"US",
    "sg:address":"301 S Monroe St",
    "sg:city":"Tallahassee",
    "sg:classifiers":[
        {
            "category":"Government",
            "subcategory":"Office",
            "type":"Public Place"
        }
    ],
    "sg:phone":"+1 850 488 6102",
    "sg:postcode":"32301",
    "sg:province":"FL",
    "wof:name":"Leon County Property Appraiser",
    "wof:placetype":"venue"
},
  "geometry": {"coordinates":[-84.280664,30.439593],"type":"Point"}
}