{
  "type": "Feature",
  "properties": {
    "addr:full":"10231 Timberland Point Dr Tampa FL 33647",
    "addr:housenumber":"10231",
    "addr:postcode":"33647",
    "addr:street":"Timberland Point Dr",
    "iso:country":"US",
    "sg:address":"10231 Timberland Point Dr",
    "sg:city":"Tampa",
    "sg:classifiers":[
        {
            "category":"Wholesale",
            "subcategory":"Vending Machines",
            "type":"Manufacturing & Wholesale Goods"
        }
    ],
    "sg:phone":"+1 813 973 2122",
    "sg:postcode":"33647",
    "sg:province":"FL",
    "sg:tags":[
        "operator"
    ],
    "wof:name":"Divine Choice Vending",
    "wof:placetype":"venue"
},
  "geometry": {"coordinates":[-82.313603,28.13738],"type":"Point"}
}