{
  "type": "Feature",
  "properties": {
    "iso:country":"US",
    "sg:address":"241 Worth Ave",
    "sg:city":"Palm Beach",
    "sg:classifiers":[
        {
            "category":"Shopping",
            "subcategory":"Jewelry",
            "type":"Retail Goods"
        }
    ],
    "sg:phone":"+1 561 655 5441",
    "sg:postcode":"33480",
    "sg:province":"FL",
    "sg:tags":[
        "stone",
        "art",
        "metal",
        "also",
        "precious",
        "dealer"
    ],
    "wof:name":"Maison Maurice Jewerly",
    "wof:placetype":"venue"
},
  "geometry": {"coordinates":[-80.03731999999999,26.700755],"type":"Point"}
}