{
  "type": "Feature",
  "properties": {
    "iso:country":"US",
    "sg:address":"2301 NE 17th Ter",
    "sg:city":"Ocala",
    "sg:classifiers":[
        {
            "category":"Building & Trades",
            "subcategory":"Plumbing",
            "type":"Services"
        }
    ],
    "sg:phone":"+1 352 622 6564",
    "sg:postcode":"34470",
    "sg:province":"FL",
    "sg:tags":[
        "contractor"
    ],
    "wof:name":"Ocala Plumbing Co Inc",
    "wof:placetype":"venue"
},
  "geometry": {"coordinates":[-82.11515,29.20257],"type":"Point"}
}