{
  "type": "Feature",
  "properties": {
    "addr:full":"9201 E Calusa Club Dr Miami FL 33186",
    "addr:housenumber":"9201",
    "addr:postcode":"33186",
    "addr:street":"E Calusa Club Dr",
    "iso:country":"US",
    "sg:address":"9201 E Calusa Club Dr",
    "sg:city":"Miami",
    "sg:classifiers":[
        {
            "category":"Farming",
            "subcategory":"Livestock Farm",
            "type":"Manufacturing & Wholesale Goods"
        },
        {
            "category":"Farming",
            "subcategory":"Farm",
            "type":"Manufacturing & Wholesale Goods"
        }
    ],
    "sg:phone":"+1 305 408 3810",
    "sg:postcode":"33186",
    "sg:province":"FL",
    "wof:name":"Hog Tales Oak Farms",
    "wof:placetype":"venue"
},
  "geometry": {"coordinates":[-80.401668,25.681728],"type":"Point"}
}