{
  "type": "Feature",
  "properties": {
    "addr:full":"1800 Mountain Lake Cutoff Rd Lake Wales FL 33859",
    "addr:housenumber":"1800",
    "addr:postcode":"33859",
    "addr:street":"Mountain Lake Cutoff Rd",
    "iso:country":"US",
    "sg:address":"1800 Mountain Lake Cutoff Rd",
    "sg:city":"Lake Wales",
    "sg:classifiers":[
        {
            "category":"Freight",
            "type":"Transportation"
        },
        {
            "category":"Professional",
            "type":"Services"
        }
    ],
    "sg:phone":"+1 863 676 7718",
    "sg:postcode":"33859",
    "sg:province":"FL",
    "sg:tags":[
        "cargo",
        "loading"
    ],
    "wof:name":"B & B Loading Service Inc",
    "wof:placetype":"venue"
},
  "geometry": {"coordinates":[-81.616691,27.924781],"type":"Point"}
}