{
  "type": "Feature",
  "properties": {
    "iso:country":"US",
    "sg:address":"2539 Gary Cir Apt 201",
    "sg:city":"Dunedin",
    "sg:classifiers":[
        {
            "category":"Military Area",
            "subcategory":"Coast Guard Base",
            "type":"Public Place"
        }
    ],
    "sg:phone":"+1 727 736 0533",
    "sg:postcode":"34698",
    "sg:province":"FL",
    "sg:tags":[
        "meter"
    ],
    "sg:website":"http://www.fewtek.com",
    "wof:name":"Fewtek Inc",
    "wof:placetype":"venue"
},
  "geometry": {"coordinates":[-82.78826599999999,28.049581],"type":"Point"}
}