{
  "type": "Feature",
  "properties": {
    "addr:full":"5440 Beaumont Center Blvd Tampa FL 33634",
    "addr:housenumber":"5440",
    "addr:postcode":"33634",
    "addr:street":"Beaumont Center Blvd",
    "iso:country":"US",
    "sg:address":"5440 Beaumont Center Blvd",
    "sg:city":"Tampa",
    "sg:classifiers":[
        {
            "category":"Professional",
            "subcategory":"Computer Services",
            "type":"Services"
        }
    ],
    "sg:phone":"+1 813 249 7468",
    "sg:postcode":"33634",
    "sg:province":"FL",
    "sg:tags":[
        "repair"
    ],
    "wof:name":"Decision One",
    "wof:placetype":"venue"
},
  "geometry": {"coordinates":[-82.547191,27.997713],"type":"Point"}
}