{
  "type": "Feature",
  "properties": {
    "addr:full":"36828 Chestnut Ln Zephyrhills FL 33541",
    "addr:housenumber":"36828",
    "addr:postcode":"33541",
    "addr:street":"Chestnut Ln",
    "iso:country":"US",
    "sg:address":"36828 Chestnut Ln",
    "sg:city":"Zephyrhills",
    "sg:classifiers":[
        {
            "category":"Building & Trades",
            "subcategory":"Landscaping Services",
            "type":"Services"
        }
    ],
    "sg:phone":"+1 813 782 4996",
    "sg:postcode":"33541",
    "sg:province":"FL",
    "wof:name":"Cindy Farringtons Maintenance",
    "wof:placetype":"venue"
},
  "geometry": {"coordinates":[-82.20823300000001,28.231709],"type":"Point"}
}