{
  "type": "Feature",
  "properties": {
    "iso:country":"US",
    "sg:address":"6217 Wood Lake Rd",
    "sg:city":"Jupiter",
    "sg:classifiers":[
        {
            "category":"Personal",
            "subcategory":"Beauty Salon",
            "type":"Services"
        }
    ],
    "sg:phone":"+1 561 575 3500",
    "sg:postcode":"33458",
    "sg:province":"FL",
    "sg:tags":[
        "treatment",
        "skin"
    ],
    "sg:website":"www.phsolutions.net",
    "wof:name":"P H Solutions",
    "wof:placetype":"venue"
},
  "geometry": {"coordinates":[-80.1309,26.961173],"type":"Point"}
}