{
  "type": "Feature",
  "properties": {
    "addr:full":"7900 NW 27th Ave Miami FL 33147",
    "addr:housenumber":"7900",
    "addr:postcode":"33147",
    "addr:street":"Nw 27Th Ave",
    "iso:country":"US",
    "sg:address":"7900 NW 27th Ave",
    "sg:city":"Miami",
    "sg:classifiers":[
        {
            "category":"Shopping",
            "subcategory":"Jewelry",
            "type":"Retail Goods"
        }
    ],
    "sg:phone":"+1 305 836 3524",
    "sg:postcode":"33147",
    "sg:province":"FL",
    "sg:tags":[
        "jeweler"
    ],
    "wof:name":"Katie Collection",
    "wof:placetype":"venue"
},
  "geometry": {"coordinates":[-80.241753,25.846677],"type":"Point"}
}