{
  "type": "Feature",
  "properties": {
    "iso:country":"US",
    "sg:address":"8540 Co Rd 561",
    "sg:city":"Clermont",
    "sg:classifiers":[
        {
            "category":"Building & Trades",
            "subcategory":"Plumbing",
            "type":"Services"
        }
    ],
    "sg:phone":"+1 352 394 4291",
    "sg:postcode":"34711",
    "sg:province":"FL",
    "sg:tags":[
        "contractor"
    ],
    "wof:name":"R L Vail",
    "wof:placetype":"venue"
},
  "geometry": {"coordinates":[-81.793271,28.472917],"type":"Point"}
}