{
  "type": "Feature",
  "properties": {
    "addr:full":"12046 Collegiate Way Orlando FL 32817",
    "addr:housenumber":"12046",
    "addr:postcode":"32817",
    "addr:street":"Collegiate Way",
    "iso:country":"US",
    "sg:address":"12046 Collegiate Way",
    "sg:city":"Orlando",
    "sg:classifiers":[
        {
            "category":"Education",
            "subcategory":"Special Training",
            "type":"Public Place"
        },
        {
            "category":"Social Services",
            "subcategory":"Child Care",
            "type":"Services"
        },
        {
            "category":"Education",
            "subcategory":"School",
            "type":"Public Place"
        },
        {
            "category":"Communications",
            "type":"Services"
        }
    ],
    "sg:phone":"+1 407 281 0441",
    "sg:postcode":"32817",
    "sg:province":"FL",
    "sg:tags":[
        "educational",
        "pathologist",
        "speech-language",
        "middle",
        "elementary"
    ],
    "wof:name":"United Cerebral Palsy",
    "wof:placetype":"venue"
},
  "geometry": {"coordinates":[-81.21147499999999,28.59693],"type":"Point"}
}