{
  "type": "Feature",
  "properties": {
    "iso:country":"US",
    "sg:address":"3615 Dupont Ave",
    "sg:city":"Jacksonville",
    "sg:classifiers":[
        {
            "category":"Restaurant",
            "type":"Food & Drink"
        }
    ],
    "sg:menulink":"http://www.allmenus.com/fl/jacksonville/106239-pizza-stella/menu/",
    "sg:phone":"+1 904 828 4002",
    "sg:postcode":"32217",
    "sg:province":"FL",
    "sg:tags":[
        "italian"
    ],
    "wof:name":"Pizza Stella",
    "wof:placetype":"venue"
},
  "geometry": {"coordinates":[-81.624776,30.255319],"type":"Point"}
}