{
  "type": "Feature",
  "properties": {
    "addr:full":"101 Fairview Ave Daytona Beach FL 32114",
    "addr:housenumber":"101",
    "addr:postcode":"32114",
    "addr:street":"Fairview Ave",
    "iso:country":"US",
    "sg:address":"101 Fairview Ave",
    "sg:city":"Daytona Beach",
    "sg:classifiers":[
        {
            "category":"Retail",
            "subcategory":"Repair Shop",
            "type":"Services"
        }
    ],
    "sg:phone":"+1 386 253 1703",
    "sg:postcode":"32114",
    "sg:province":"FL",
    "sg:tags":[
        "scooter",
        "motorcycle",
        "motor"
    ],
    "wof:name":"Strokerz",
    "wof:placetype":"venue"
},
  "geometry": {"coordinates":[-81.024457,29.220726],"type":"Point"}
}