{
  "type": "Feature",
  "properties": {
    "addr:full":"10585 NW 110th St Reddick FL 32686",
    "addr:housenumber":"10585",
    "addr:postcode":"32686",
    "addr:street":"Nw 110Th St",
    "iso:country":"US",
    "sg:address":"10585 NW 110th St",
    "sg:city":"Reddick",
    "sg:classifiers":[
        {
            "category":"Farming",
            "subcategory":"Livestock Farm",
            "type":"Manufacturing & Wholesale Goods"
        }
    ],
    "sg:phone":"+1 352 351 1982",
    "sg:postcode":"32686",
    "sg:province":"FL",
    "sg:tags":[
        "hog",
        "or",
        "feedlot"
    ],
    "wof:name":"McMahon Livestock",
    "wof:placetype":"venue"
},
  "geometry": {"coordinates":[-82.301058,29.305646],"type":"Point"}
}