{
  "type": "Feature",
  "properties": {
    "iso:country":"US",
    "sg:address":"3008 State Hwy 95A",
    "sg:city":"Cantonment",
    "sg:classifiers":[
        {
            "category":"Manufacturing",
            "subcategory":"Glass & Minerals",
            "type":"Manufacturing & Wholesale Goods"
        }
    ],
    "sg:phone":"+1 850 477 0343",
    "sg:postcode":"32533",
    "sg:province":"FL",
    "sg:tags":[
        "ready"
    ],
    "wof:name":"Pensacola Ready Mix USA",
    "wof:placetype":"venue"
},
  "geometry": {"coordinates":[-87.321849,30.659323],"type":"Point"}
}