{
  "type": "Feature",
  "properties": {
    "addr:full":"970 N Cocoa Blvd Cocoa FL 32922",
    "addr:housenumber":"970",
    "addr:postcode":"32922",
    "addr:street":"N Cocoa Blvd",
    "iso:country":"US",
    "sg:address":"970 N Cocoa Blvd",
    "sg:city":"Cocoa",
    "sg:classifiers":[
        {
            "category":"Personal",
            "subcategory":"Barber",
            "type":"Services"
        }
    ],
    "sg:phone":"+1 321 504 0603",
    "sg:postcode":"32922",
    "sg:province":"FL",
    "wof:name":"Sharon's Barber Shop",
    "wof:placetype":"venue"
},
  "geometry": {"coordinates":[-80.737521,28.376001],"type":"Point"}
}