{
  "type": "Feature",
  "properties": {
    "iso:country":"US",
    "sg:address":"5008 W Linebaugh Ave",
    "sg:city":"Tampa",
    "sg:classifiers":[
        {
            "category":"Wholesale",
            "subcategory":"Hardware",
            "type":"Manufacturing & Wholesale Goods"
        }
    ],
    "sg:phone":"+1 813 968 7933",
    "sg:postcode":"33624",
    "sg:province":"FL",
    "sg:tags":[
        "plumbing",
        "fixture",
        "supply"
    ],
    "wof:name":"Independent Contractors Supply",
    "wof:placetype":"venue"
},
  "geometry": {"coordinates":[-82.526921,28.04014],"type":"Point"}
}