{
  "type": "Feature",
  "properties": {
    "addr:full":"2741 SW 84th Ct Miami FL 33155",
    "addr:housenumber":"2741",
    "addr:postcode":"33155",
    "addr:street":"Sw 84Th Ct",
    "iso:country":"US",
    "sg:address":"2741 SW 84th Ct",
    "sg:city":"Miami",
    "sg:classifiers":[
        {
            "category":"Professional",
            "subcategory":"Accounting & Tax Preparation",
            "type":"Services"
        }
    ],
    "sg:phone":"+1 305 439 8819",
    "sg:postcode":"33155",
    "sg:province":"FL",
    "sg:tags":[
        "bookkeeping",
        "billing"
    ],
    "wof:name":"C G Billing Inc",
    "wof:placetype":"venue"
},
  "geometry": {"coordinates":[-80.332272,25.744326],"type":"Point"}
}