{
  "type": "Feature",
  "properties": {
    "addr:full":"1704 Lakeside Ave St Augustine FL 32084",
    "addr:housenumber":"1704",
    "addr:postcode":"32084",
    "addr:street":"Lakeside Ave St",
    "iso:country":"US",
    "sg:address":"1704 Lakeside Ave",
    "sg:city":"St Augustine",
    "sg:classifiers":[
        {
            "category":"Building & Trades",
            "subcategory":"Construction",
            "type":"Services"
        }
    ],
    "sg:phone":"+1 904 826 0222",
    "sg:postcode":"32084",
    "sg:province":"FL",
    "sg:tags":[
        "steel",
        "erection",
        "business",
        "structural"
    ],
    "wof:name":"Southeastern Structural Detlrs",
    "wof:placetype":"venue"
},
  "geometry": {"coordinates":[-81.33111599999999,29.869947],"type":"Point"}
}