{
  "type": "Feature",
  "properties": {
    "iso:country":"US",
    "sg:address":"1110 Old Dixie Hwy",
    "sg:city":"Vero Beach",
    "sg:phone":"+1 772 567 5320",
    "sg:postcode":"32960",
    "sg:province":"FL",
    "sg:tags":[
        "gasoline",
        "product",
        "oil",
        "petroleum"
    ],
    "wof:name":"Paradise Petroleum Inc",
    "wof:placetype":"venue"
},
  "geometry": {"coordinates":[-80.392961,27.619936],"type":"Point"}
}