{
  "type": "Feature",
  "properties": {
    "addr:full":"5457 Lake Margaret Dr Orlando FL 32812",
    "addr:housenumber":"5457",
    "addr:postcode":"32812",
    "addr:street":"Lake Margaret Dr",
    "iso:country":"US",
    "sg:address":"5457 Lake Margaret Dr",
    "sg:city":"Orlando",
    "sg:classifiers":[
        {
            "category":"Professional",
            "subcategory":"Computer Services",
            "type":"Services"
        }
    ],
    "sg:phone":"+1 407 281 0585",
    "sg:postcode":"32812",
    "sg:province":"FL",
    "sg:tags":[
        "related"
    ],
    "wof:name":"Apctechguy",
    "wof:placetype":"venue"
},
  "geometry": {"coordinates":[-81.316517,28.506226],"type":"Point"}
}