{
  "type": "Feature",
  "properties": {
    "addr:full":"5425 Park Central Ct Naples FL 34109",
    "addr:housenumber":"5425",
    "addr:postcode":"34109",
    "addr:street":"Park Central Ct",
    "iso:country":"US",
    "sg:address":"5425 Park Central Ct",
    "sg:city":"Naples",
    "sg:classifiers":[
        {
            "category":"Banks & Credit Unions",
            "subcategory":"Investment Brokerage",
            "type":"Services"
        }
    ],
    "sg:phone":"+1 239 513 0007",
    "sg:postcode":"34109",
    "sg:province":"FL",
    "sg:tags":[
        "consultant",
        "planning",
        "financial"
    ],
    "wof:name":"Nye Financial Group",
    "wof:placetype":"venue"
},
  "geometry": {"coordinates":[-81.76735600000001,26.214102],"type":"Point"}
}