{
  "type": "Feature",
  "properties": {
    "addr:full":"7264 8th St SW Miami FL 33144",
    "addr:housenumber":"7264",
    "addr:postcode":"33144",
    "addr:street":"8Th St Sw",
    "iso:country":"US",
    "sg:address":"7264 8th St SW",
    "sg:city":"Miami",
    "sg:classifiers":[
        {
            "category":"Social Services",
            "subcategory":"Job Training",
            "type":"Services"
        }
    ],
    "sg:phone":"+1 305 262 8100",
    "sg:postcode":"33144",
    "sg:province":"FL",
    "sg:tags":[
        "rehabilitation"
    ],
    "wof:name":"Rehabilitation Institute",
    "wof:placetype":"venue"
},
  "geometry": {"coordinates":[-80.312667,25.762738],"type":"Point"}
}