{
  "type": "Feature",
  "properties": {
    "iso:country":"US",
    "sg:address":"1844 Montclair Rd",
    "sg:city":"Clearwater",
    "sg:classifiers":[
        {
            "category":"Personal",
            "subcategory":"Nail Salon",
            "type":"Services"
        }
    ],
    "sg:phone":"+1 727 442 4927",
    "sg:postcode":"33763",
    "sg:province":"FL",
    "wof:name":"Fancy Sumner",
    "wof:placetype":"venue"
},
  "geometry": {"coordinates":[-82.761544,27.993275],"type":"Point"}
}