{
  "type": "Feature",
  "properties": {
    "iso:country":"US",
    "sg:address":"234 S Federal Hwy",
    "sg:city":"Boca Raton",
    "sg:classifiers":[
        {
            "category":"Autos & Motor Vehicles",
            "subcategory":"Boat Sales",
            "type":"Retail Goods"
        }
    ],
    "sg:phone":"+1 954 943 6900",
    "sg:postcode":"33432",
    "sg:province":"FL",
    "wof:name":"Boats 4 Less",
    "wof:placetype":"venue"
},
  "geometry": {"coordinates":[-80.08631200000001,26.347302],"type":"Point"}
}