{
  "type": "Feature",
  "properties": {
    "addr:full":"9201 Nelson Park Cir Orlando FL 32817",
    "addr:housenumber":"9201",
    "addr:postcode":"32817",
    "addr:street":"Nelson Park Cir",
    "iso:country":"US",
    "sg:address":"9201 Nelson Park Cir",
    "sg:city":"Orlando",
    "sg:classifiers":[
        {
            "category":"Real Estate",
            "subcategory":"Real Estate Operator",
            "type":"Services"
        }
    ],
    "sg:phone":"+1 407 207 1488",
    "sg:postcode":"32817",
    "sg:province":"FL",
    "sg:tags":[
        "building",
        "apartment"
    ],
    "sg:website":"www.riverfrontequities.com",
    "wof:name":"Riverfront Apartments Inc",
    "wof:placetype":"venue"
},
  "geometry": {"coordinates":[-81.25696000000001,28.574503],"type":"Point"}
}