{
  "type": "Feature",
  "properties": {
    "addr:full":"6350 Presidential Ct Fort Myers FL 33919",
    "addr:housenumber":"6350",
    "addr:postcode":"33919",
    "addr:street":"Presidential Ct",
    "iso:country":"US",
    "sg:address":"6350 Presidential Ct",
    "sg:city":"Fort Myers",
    "sg:classifiers":[
        {
            "category":"Health Services",
            "subcategory":"Doctor",
            "type":"Services"
        }
    ],
    "sg:phone":"+1 239 437 5500",
    "sg:postcode":"33919",
    "sg:province":"FL",
    "sg:tags":[
        "medical"
    ],
    "wof:name":"Specialists of Childrens",
    "wof:placetype":"venue"
},
  "geometry": {"coordinates":[-81.886993,26.557687],"type":"Point"}
}