{
  "type": "Feature",
  "properties": {
    "iso:country":"US",
    "sg:address":"1798 W International Speedway Blvd",
    "sg:city":"Daytona Beach",
    "sg:classifiers":[
        {
            "category":"Travel",
            "subcategory":"Hotels & Motels",
            "type":"Entertainment"
        }
    ],
    "sg:phone":"+1 386 255 2422",
    "sg:postcode":"32114",
    "sg:province":"FL",
    "sg:website":"www.ramadainn.com",
    "wof:name":"Ramada Inn",
    "wof:placetype":"venue"
},
  "geometry": {"coordinates":[-81.062933,29.194402],"type":"Point"}
}