{
  "type": "Feature",
  "properties": {
    "addr:full":"7370 NW 36th St Miami FL 33166",
    "addr:housenumber":"7370",
    "addr:postcode":"33166",
    "addr:street":"Nw 36Th St",
    "iso:country":"US",
    "sg:address":"7370 NW 36th St",
    "sg:city":"Miami",
    "sg:classifiers":[
        {
            "category":"Shopping",
            "type":"Retail Goods"
        }
    ],
    "sg:phone":"+1 954 429 9998",
    "sg:postcode":"33166",
    "sg:province":"FL",
    "sg:tags":[
        "repair",
        "electrical",
        "merchandise"
    ],
    "wof:name":"Advanced Comm Solutions",
    "wof:placetype":"venue"
},
  "geometry": {"coordinates":[-80.31417500000001,25.809224],"type":"Point"}
}