{
  "type": "Feature",
  "properties": {
    "iso:country":"US",
    "sg:address":"2801 Herschel St",
    "sg:city":"Jacksonville",
    "sg:classifiers":[
        {
            "category":"Education",
            "subcategory":"School",
            "type":"Public Place"
        }
    ],
    "sg:phone":"+1 904 381 3900",
    "sg:postcode":"32205",
    "sg:province":"FL",
    "wof:name":"West Riverside Elementary Schl",
    "wof:placetype":"venue"
},
  "geometry": {"coordinates":[-81.696637,30.306979],"type":"Point"}
}