{
  "type": "Feature",
  "properties": {
    "iso:country":"US",
    "sg:address":"4061 Navigator Way",
    "sg:city":"Kissimmee",
    "sg:classifiers":[
        {
            "category":"Wholesale",
            "subcategory":"Machinery & Supplies",
            "type":"Manufacturing & Wholesale Goods"
        }
    ],
    "sg:phone":"+1 321 442 2901",
    "sg:postcode":"34746",
    "sg:province":"FL",
    "sg:tags":[
        "equipment",
        "industrial"
    ],
    "wof:name":"Guestroom Equipment Inc.",
    "wof:placetype":"venue"
},
  "geometry": {"coordinates":[-81.452653,28.181039],"type":"Point"}
}