{
  "type": "Feature",
  "properties": {
    "iso:country":"US",
    "sg:address":"1120 Romney St",
    "sg:city":"Jacksonville",
    "sg:classifiers":[
        {
            "category":"Wholesale",
            "subcategory":"Electrical",
            "type":"Manufacturing & Wholesale Goods"
        }
    ],
    "sg:phone":"+1 904 745 1111",
    "sg:postcode":"32211",
    "sg:province":"FL",
    "sg:tags":[
        "electric",
        "motor"
    ],
    "wof:name":"Butler's Pump & Tool Repair",
    "wof:placetype":"venue"
},
  "geometry": {"coordinates":[-81.60024900000001,30.333373],"type":"Point"}
}