{
  "type": "Feature",
  "properties": {
    "addr:full":"4724 NW 57 Dr Gainesville FL 32606",
    "addr:housenumber":"4724",
    "addr:postcode":"32606",
    "addr:street":"Nw 57 Dr",
    "iso:country":"US",
    "sg:address":"4724 NW 57 Dr",
    "sg:city":"Gainesville",
    "sg:classifiers":[
        {
            "category":"Professional",
            "subcategory":"Management & Consulting",
            "type":"Services"
        }
    ],
    "sg:phone":"+1 352 377 9333",
    "sg:postcode":"32606",
    "sg:province":"FL",
    "sg:tags":[
        "environmental",
        "consultant"
    ],
    "wof:name":"Florida Vector Services Inc",
    "wof:placetype":"venue"
},
  "geometry": {"coordinates":[-82.403423,29.697494],"type":"Point"}
}