{
  "type": "Feature",
  "properties": {
    "iso:country":"US",
    "sg:address":"524 Orange Dr",
    "sg:city":"Altamonte Springs",
    "sg:classifiers":[
        {
            "category":"Retail",
            "subcategory":"Car Wash",
            "type":"Services"
        }
    ],
    "sg:phone":"+1 407 830 9111",
    "sg:postcode":"32701",
    "sg:province":"FL",
    "sg:tags":[
        "carwash"
    ],
    "wof:name":"Bg Whisonant",
    "wof:placetype":"venue"
},
  "geometry": {"coordinates":[-81.37561599999999,28.660759],"type":"Point"}
}