{
  "type": "Feature",
  "properties": {
    "addr:full":"6130 NW 54 Way Gainesville FL 32653",
    "addr:housenumber":"6130",
    "addr:postcode":"32653",
    "addr:street":"Nw 54 Way",
    "iso:country":"US",
    "sg:address":"6130 NW 54 Way",
    "sg:city":"Gainesville",
    "sg:classifiers":[
        {
            "category":"Professional",
            "subcategory":"Engineering",
            "type":"Services"
        }
    ],
    "sg:phone":"+1 352 375 4628",
    "sg:postcode":"32653",
    "sg:province":"FL",
    "wof:name":"Jr Ambrose PHD Pe",
    "wof:placetype":"venue"
},
  "geometry": {"coordinates":[-82.401217,29.70871],"type":"Point"}
}