{
  "type": "Feature",
  "properties": {
    "iso:country":"US",
    "sg:address":"14951 113th Ave",
    "sg:city":"Largo",
    "sg:classifiers":[
        {
            "category":"Retail",
            "subcategory":"Auto Repair",
            "type":"Services"
        },
        {
            "category":"Shopping",
            "subcategory":"Mobile Phones",
            "type":"Retail Goods"
        },
        {
            "category":"Building & Trades",
            "subcategory":"Construction",
            "type":"Services"
        },
        {
            "category":"Home & Garden",
            "subcategory":"Mobile Homes",
            "type":"Retail Goods"
        }
    ],
    "sg:phone":"+1 727 596 9929",
    "sg:postcode":"33774",
    "sg:province":"FL",
    "sg:tags":[
        "manufactured",
        "housing-communities",
        "recreational",
        "transporting",
        "vehicle",
        "homes-repair",
        "campers-repair"
    ],
    "wof:name":"Lehman's Mobile Home Service Inc",
    "wof:placetype":"venue"
},
  "geometry": {"coordinates":[-82.846891,27.875795],"type":"Point"}
}