{
  "type": "Feature",
  "properties": {
    "iso:country":"US",
    "sg:address":"175 Fontainebleau Blvd",
    "sg:city":"Miami",
    "sg:classifiers":[
        {
            "category":"Wholesale",
            "subcategory":"Durable Goods & Equipment",
            "type":"Manufacturing & Wholesale Goods"
        }
    ],
    "sg:phone":"+1 305 226 5260",
    "sg:postcode":"33172",
    "sg:province":"FL",
    "sg:tags":[
        "exporter"
    ],
    "wof:name":"Jonsan Group Investment & Mgmt",
    "wof:placetype":"venue"
},
  "geometry": {"coordinates":[-80.337261,25.771506],"type":"Point"}
}