{
  "type": "Feature",
  "properties": {
    "iso:country":"US",
    "sg:address":"6770 Indian Creek Dr",
    "sg:city":"Miami Beach",
    "sg:classifiers":[
        {
            "category":"Wholesale",
            "subcategory":"Durable Goods & Equipment",
            "type":"Manufacturing & Wholesale Goods"
        }
    ],
    "sg:phone":"+1 305 867 0243",
    "sg:postcode":"33141",
    "sg:province":"FL",
    "sg:tags":[
        "exporter"
    ],
    "wof:name":"Hema Oragnostics Systems LLC",
    "wof:placetype":"venue"
},
  "geometry": {"coordinates":[-80.122294,25.851692],"type":"Point"}
}