{
  "type": "Feature",
  "properties": {
    "iso:country":"US",
    "sg:address":"881 E Elkcam Cir",
    "sg:city":"Marco Island",
    "sg:classifiers":[
        {
            "category":"Building & Trades",
            "subcategory":"Plumbing",
            "type":"Services"
        }
    ],
    "sg:phone":"+1 239 394 1668",
    "sg:postcode":"34145",
    "sg:province":"FL",
    "sg:tags":[
        "specializing",
        "work",
        "plumb",
        "contractor",
        "also",
        "plumbing"
    ],
    "wof:name":"Prouts Plumbing & Supply Inc",
    "wof:placetype":"venue"
},
  "geometry": {"coordinates":[-81.72434,25.958554],"type":"Point"}
}