{
  "type": "Feature",
  "properties": {
    "iso:country":"US",
    "sg:address":"2155 Oceanview Dr",
    "sg:city":"Saint Petersburg",
    "sg:classifiers":[
        {
            "category":"Shopping",
            "subcategory":"Shoes",
            "type":"Retail Goods"
        }
    ],
    "sg:phone":"+1 727 906 8024",
    "sg:postcode":"33715",
    "sg:province":"FL",
    "wof:name":"Sports Ventures America I",
    "wof:placetype":"venue"
},
  "geometry": {"coordinates":[-82.726343,27.663812],"type":"Point"}
}