{
  "type": "Feature",
  "properties": {
    "iso:country":"US",
    "sg:address":"5144 Bradenton Rd",
    "sg:city":"Sarasota",
    "sg:classifiers":[
        {
            "category":"Shopping",
            "subcategory":"Clothing, Apparel, & Fashions",
            "type":"Retail Goods"
        }
    ],
    "sg:phone":"+1 941 358 5108",
    "sg:postcode":"34234",
    "sg:province":"FL",
    "wof:name":"Underground For Originals By B",
    "wof:placetype":"venue"
},
  "geometry": {"coordinates":[-82.546903,27.378178],"type":"Point"}
}