{
  "type": "Feature",
  "properties": {
    "iso:country":"US",
    "sg:address":"8903 Hammock Loop",
    "sg:city":"Polk City",
    "sg:classifiers":[
        {
            "category":"Building & Trades",
            "subcategory":"Construction",
            "type":"Services"
        }
    ],
    "sg:phone":"+1 863 661 2535",
    "sg:postcode":"33868",
    "sg:province":"FL",
    "sg:tags":[
        "resurfacing",
        "laying",
        "refinishing",
        "floor"
    ],
    "wof:name":"B & D Floor Covering",
    "wof:placetype":"venue"
},
  "geometry": {"coordinates":[-81.86502,28.160208],"type":"Point"}
}