{
  "type": "Feature",
  "properties": {
    "addr:full":"1290 Buckeye Rd Ormond Beach FL 32174",
    "addr:housenumber":"1290",
    "addr:postcode":"32174",
    "addr:street":"Buckeye Rd",
    "iso:country":"US",
    "sg:address":"1290 Buckeye Rd",
    "sg:city":"Ormond Beach",
    "sg:classifiers":[
        {
            "category":"Building & Trades",
            "subcategory":"Construction",
            "type":"Services"
        }
    ],
    "sg:phone":"+1 386 290 5461",
    "sg:postcode":"32174",
    "sg:province":"FL",
    "sg:tags":[
        "house"
    ],
    "wof:name":"Richs Residential Services",
    "wof:placetype":"venue"
},
  "geometry": {"coordinates":[-81.085846,29.26923],"type":"Point"}
}