{
  "type": "Feature",
  "properties": {
    "iso:country":"US",
    "sg:address":"225 W New York Ave",
    "sg:city":"Deland",
    "sg:classifiers":[
        {
            "category":"Travel",
            "subcategory":"Hotels & Motels",
            "type":"Entertainment"
        },
        {
            "category":"Bars & Pubs",
            "subcategory":"Nightclub",
            "type":"Food & Drink"
        },
        {
            "category":"Real Estate",
            "subcategory":"Real Estate Operator",
            "type":"Services"
        }
    ],
    "sg:phone":"+1 386 734 4411",
    "sg:postcode":"32720",
    "sg:province":"FL",
    "sg:tags":[
        "apartment",
        "nightlife"
    ],
    "wof:name":"Putnam Hotel & Apartments",
    "wof:placetype":"venue"
},
  "geometry": {"coordinates":[-81.307098,29.028],"type":"Point"}
}