{
  "type": "Feature",
  "properties": {
    "iso:country":"US",
    "sg:address":"1544 Big Bass Dr",
    "sg:city":"Tarpon Springs",
    "sg:classifiers":[
        {
            "category":"Shopping",
            "subcategory":"Clothing, Apparel, & Fashions",
            "type":"Retail Goods"
        }
    ],
    "sg:phone":"+1 727 733 6950",
    "sg:postcode":"34689",
    "sg:province":"FL",
    "wof:name":"Simply Dara's",
    "wof:placetype":"venue"
},
  "geometry": {"coordinates":[-82.732078,28.138947],"type":"Point"}
}