{
  "type": "Feature",
  "properties": {
    "iso:country":"US",
    "sg:address":"Miami International Airport",
    "sg:city":"Miami",
    "sg:classifiers":[
        {
            "category":"Shopping",
            "subcategory":"Department Store",
            "type":"Retail Goods"
        }
    ],
    "sg:phone":"+1 305 871 1069",
    "sg:postcode":"33166",
    "sg:province":"FL",
    "sg:website":"www.brookstone.com",
    "wof:name":"Brookstone Company",
    "wof:placetype":"venue"
},
  "geometry": {"coordinates":[-80.275614,25.796549],"type":"Point"}
}