{
  "type": "Feature",
  "properties": {
    "iso:country":"US",
    "sg:address":"6800 SW 81st Ter",
    "sg:city":"Miami",
    "sg:classifiers":[
        {
            "category":"Wholesale",
            "subcategory":"Home Furnishings",
            "type":"Manufacturing & Wholesale Goods"
        }
    ],
    "sg:phone":"+1 305 668 3161",
    "sg:postcode":"33143",
    "sg:province":"FL",
    "sg:tags":[
        "floor",
        "marble",
        "covering"
    ],
    "wof:name":"Gultas Inc",
    "wof:placetype":"venue"
},
  "geometry": {"coordinates":[-80.30354699999999,25.694648],"type":"Point"}
}