{
  "type": "Feature",
  "properties": {
    "addr:full":"1200 Clare Ave West Palm Beach FL 33401",
    "addr:housenumber":"1200",
    "addr:postcode":"33401",
    "addr:street":"Clare Ave",
    "iso:country":"US",
    "sg:address":"1200 Clare Ave",
    "sg:city":"West Palm Beach",
    "sg:classifiers":[
        {
            "category":"Restaurant",
            "type":"Food & Drink"
        }
    ],
    "sg:phone":"+1 561 835 0066",
    "sg:postcode":"33401",
    "sg:province":"FL",
    "sg:tags":[
        "eating"
    ],
    "wof:name":"Christafaros Inc",
    "wof:placetype":"venue"
},
  "geometry": {"coordinates":[-80.062622,26.700249],"type":"Point"}
}