{
  "type": "Feature",
  "properties": {
    "addr:full":"965 NE 12th Ave Homestead FL 33030",
    "addr:housenumber":"965",
    "addr:postcode":"33030",
    "addr:street":"Ne 12Th Ave",
    "iso:country":"US",
    "sg:address":"965 NE 12th Ave",
    "sg:city":"Homestead",
    "sg:classifiers":[
        {
            "category":"Autos & Motor Vehicles",
            "subcategory":"Automobile Sales",
            "type":"Retail Goods"
        }
    ],
    "sg:phone":"+1 305 242 0550",
    "sg:postcode":"33030",
    "sg:province":"FL",
    "sg:tags":[
        "used"
    ],
    "wof:name":"Homestead Motors Inc",
    "wof:placetype":"venue"
},
  "geometry": {"coordinates":[-80.460868,25.480404],"type":"Point"}
}