{
  "type": "Feature",
  "properties": {
    "iso:country":"US",
    "sg:address":"6241 SW 138th Ct",
    "sg:city":"Miami",
    "sg:classifiers":[
        {
            "category":"Wholesale",
            "subcategory":"Durable Goods & Equipment",
            "type":"Manufacturing & Wholesale Goods"
        }
    ],
    "sg:phone":"+1 305 388 7711",
    "sg:postcode":"33183",
    "sg:province":"FL",
    "sg:tags":[
        "engineering",
        "supply"
    ],
    "wof:name":"Bluepoint Technologies LLC",
    "wof:placetype":"venue"
},
  "geometry": {"coordinates":[-80.417227,25.708334],"type":"Point"}
}