{
  "type": "Feature",
  "properties": {
    "addr:full":"7452 W Grover Cleveland Blvd Homosassa FL 34446",
    "addr:housenumber":"7452",
    "addr:postcode":"34446",
    "addr:street":"W;Cleveland Blvd",
    "iso:country":"US",
    "sg:address":"7452 W Grover Cleveland Blvd",
    "sg:city":"Homosassa",
    "sg:classifiers":[
        {
            "category":"Restaurant",
            "type":"Food & Drink"
        }
    ],
    "sg:phone":"+1 352 628 3220",
    "sg:postcode":"34446",
    "sg:province":"FL",
    "wof:name":"Augie's Nut House",
    "wof:placetype":"venue"
},
  "geometry": {"coordinates":[-82.55857899999999,28.803741],"type":"Point"}
}