{
  "type": "Feature",
  "properties": {
    "addr:full":"622 N 9th Plz Panama City FL 32404",
    "addr:housenumber":"622",
    "addr:postcode":"32404",
    "addr:street":"N 9Th Plz",
    "iso:country":"US",
    "sg:address":"622 N 9th Plz",
    "sg:city":"Panama City",
    "sg:classifiers":[
        {
            "category":"Retail",
            "subcategory":"Repair Shop",
            "type":"Services"
        }
    ],
    "sg:phone":"+1 850 763 9290",
    "sg:postcode":"32404",
    "sg:province":"FL",
    "sg:tags":[
        "appliance"
    ],
    "wof:name":"PDQ Technical Svc",
    "wof:placetype":"venue"
},
  "geometry": {"coordinates":[-85.603262,30.135406],"type":"Point"}
}