{
  "type": "Feature",
  "properties": {
    "addr:full":"913 Gulf Breeze Pkwy Gulf Breeze FL 32561",
    "addr:housenumber":"913",
    "addr:postcode":"32561",
    "addr:street":"Gulf Breeze Pkwy",
    "iso:country":"US",
    "sg:address":"913 Gulf Breeze Pkwy",
    "sg:city":"Gulf Breeze",
    "sg:classifiers":[
        {
            "category":"Professional",
            "subcategory":"Accounting & Tax Preparation",
            "type":"Services"
        }
    ],
    "sg:phone":"+1 850 932 9685",
    "sg:postcode":"32561",
    "sg:province":"FL",
    "sg:tags":[
        "return"
    ],
    "wof:name":"H & R Block",
    "wof:placetype":"venue"
},
  "geometry": {"coordinates":[-87.16238800000001,30.357301],"type":"Point"}
}