{
  "type": "Feature",
  "properties": {
    "addr:full":"9409 W Highway 98 Pensacola FL 32506",
    "addr:housenumber":"9409",
    "addr:postcode":"32506",
    "addr:street":"W Highway 98",
    "iso:country":"US",
    "sg:address":"9409 W Highway 98",
    "sg:city":"Pensacola",
    "sg:classifiers":[
        {
            "category":"Arena",
            "subcategory":"Sports Club",
            "type":"Entertainment"
        }
    ],
    "sg:phone":"+1 850 453 8400",
    "sg:postcode":"32506",
    "sg:province":"FL",
    "sg:tags":[
        "martial art",
        "instruction"
    ],
    "wof:name":"Abercrombie's TaeKwonDo Academy",
    "wof:placetype":"venue"
},
  "geometry": {"coordinates":[-87.3471,30.403441],"type":"Point"}
}