{
  "type": "Feature",
  "properties": {
    "addr:full":"4350 NW 8th Ave Miami FL 33127",
    "addr:housenumber":"4350",
    "addr:postcode":"33127",
    "addr:street":"Nw 8Th Ave",
    "iso:country":"US",
    "sg:address":"4350 NW 8th Ave",
    "sg:city":"Miami",
    "sg:classifiers":[
        {
            "category":"Travel",
            "subcategory":"Hotels & Motels",
            "type":"Entertainment"
        }
    ],
    "sg:phone":"+1 305 443 8464",
    "sg:postcode":"33127",
    "sg:province":"FL",
    "wof:name":"Miami Executive Hotel",
    "wof:placetype":"venue"
},
  "geometry": {"coordinates":[-80.210167,25.81555],"type":"Point"}
}