{
  "type": "Feature",
  "properties": {
    "iso:country":"US",
    "sg:address":"8411 NW 74th St",
    "sg:city":"Miami",
    "sg:classifiers":[
        {
            "category":"Wholesale",
            "subcategory":"Medical Equipment & Supplies",
            "type":"Manufacturing & Wholesale Goods"
        }
    ],
    "sg:phone":"+1 305 322 2781",
    "sg:postcode":"33166",
    "sg:province":"FL",
    "sg:tags":[
        "respiratory"
    ],
    "wof:name":"Oxymaster",
    "wof:placetype":"venue"
},
  "geometry": {"coordinates":[-80.33792699999999,25.84081],"type":"Point"}
}