{
  "type": "Feature",
  "properties": {
    "iso:country":"US",
    "sg:address":"8525 NW 53rd Ter Ste 110",
    "sg:city":"Miami",
    "sg:classifiers":[
        {
            "category":"Real Estate",
            "subcategory":"Real Estate Services",
            "type":"Services"
        },
        {
            "category":"Professional",
            "subcategory":"Business Services",
            "type":"Services"
        },
        {
            "category":"Real Estate",
            "subcategory":"Surveying",
            "type":"Services"
        }
    ],
    "sg:phone":"+1 305 470 2100",
    "sg:postcode":"33166",
    "sg:province":"FL",
    "sg:tags":[
        "appraisers-business",
        "industrial",
        "appraisers-commercial",
        "commercial",
        "appraiser"
    ],
    "sg:website":"http://www.appraisalfirstinc.com",
    "wof:name":"Appraisalfirst Inc",
    "wof:placetype":"venue"
},
  "geometry": {"coordinates":[-80.334915,25.821512],"type":"Point"}
}