{
  "type": "Feature",
  "properties": {
    "iso:country":"US",
    "sg:address":"2690 Babbitt Ave",
    "sg:city":"Orlando",
    "sg:classifiers":[
        {
            "category":"Organizations",
            "subcategory":"Professional Association",
            "type":"Services"
        }
    ],
    "sg:phone":"+1 407 568 3295",
    "sg:postcode":"32833",
    "sg:province":"FL",
    "wof:name":"Bowling Centers Assn-Florida",
    "wof:placetype":"venue"
},
  "geometry": {"coordinates":[-81.07461600000001,28.506962],"type":"Point"}
}