{
  "type": "Feature",
  "properties": {
    "iso:country":"US",
    "sg:address":"1 US Hwy 92",
    "sg:city":"De Bary",
    "sg:classifiers":[
        {
            "category":"Food & Beverages",
            "subcategory":"Groceries & Convenience Stores",
            "type":"Retail Goods"
        }
    ],
    "sg:phone":"+1 386 668 9365",
    "sg:postcode":"32713",
    "sg:province":"FL",
    "wof:name":"Shell Oil Products U S",
    "wof:placetype":"venue"
},
  "geometry": {"coordinates":[-81.306817,28.890212],"type":"Point"}
}