{
  "type": "Feature",
  "properties": {
    "iso:country":"US",
    "sg:address":"3510 NW 83rd St",
    "sg:city":"Miami",
    "sg:classifiers":[
        {
            "category":"Building & Trades",
            "subcategory":"Locksmith",
            "type":"Services"
        }
    ],
    "sg:phone":"+1 786 718 1395",
    "sg:postcode":"33147",
    "sg:province":"FL",
    "sg:tags":[
        "key"
    ],
    "wof:name":"A Express Locksmith",
    "wof:placetype":"venue"
},
  "geometry": {"coordinates":[-80.25506799999999,25.849177],"type":"Point"}
}