{
  "type": "Feature",
  "properties": {
    "addr:full":"3279 SW 14th Pl Boynton Beach FL 33426",
    "addr:housenumber":"3279",
    "addr:postcode":"33426",
    "addr:street":"Sw 14Th Pl",
    "iso:country":"US",
    "sg:address":"3279 SW 14th Pl",
    "sg:city":"Boynton Beach",
    "sg:classifiers":[
        {
            "category":"Wholesale",
            "subcategory":"Drugs",
            "type":"Manufacturing & Wholesale Goods"
        }
    ],
    "sg:phone":"+1 561 364 0886",
    "sg:postcode":"33426",
    "sg:province":"FL",
    "sg:tags":[
        "vitamin"
    ],
    "wof:name":"Dynamic Nutrition of Florida",
    "wof:placetype":"venue"
},
  "geometry": {"coordinates":[-80.08818599999999,26.495637],"type":"Point"}
}