{
  "type": "Feature",
  "properties": {
    "addr:full":"12644 Shoreline Dr Wellington FL 33414",
    "addr:housenumber":"12644",
    "addr:postcode":"33414",
    "addr:street":"Shoreline Dr",
    "iso:country":"US",
    "sg:address":"12644 Shoreline Dr",
    "sg:city":"Wellington",
    "sg:classifiers":[
        {
            "category":"Shopping",
            "type":"Retail Goods"
        }
    ],
    "sg:phone":"+1 561 333 7598",
    "sg:postcode":"33414",
    "sg:province":"FL",
    "sg:tags":[
        "miscellaneous",
        "store"
    ],
    "wof:name":"Queen Bead Inc",
    "wof:placetype":"venue"
},
  "geometry": {"coordinates":[-80.246949,26.653701],"type":"Point"}
}