{
  "type": "Feature",
  "properties": {
    "iso:country":"US",
    "sg:address":"4645 S Old Floral City Rd",
    "sg:city":"Inverness",
    "sg:classifiers":[
        {
            "category":"Retail",
            "subcategory":"Auto Repair",
            "type":"Services"
        }
    ],
    "sg:phone":"+1 352 563 4000",
    "sg:postcode":"34450",
    "sg:province":"FL",
    "sg:tags":[
        "repairing",
        "automobile"
    ],
    "wof:name":"Earl Lou Reed Repairs",
    "wof:placetype":"venue"
},
  "geometry": {"coordinates":[-82.295039,28.796228],"type":"Point"}
}