{
  "type": "Feature",
  "properties": {
    "iso:country":"US",
    "sg:address":"19317 Lake Pickett Rd",
    "sg:city":"Orlando",
    "sg:classifiers":[
        {
            "category":"Building & Trades",
            "subcategory":"Construction",
            "type":"Services"
        }
    ],
    "sg:phone":"+1 407 568 4400",
    "sg:postcode":"32820",
    "sg:province":"FL",
    "sg:tags":[
        "heavy",
        "general",
        "contractor"
    ],
    "wof:name":"B L Woods Construction Inc",
    "wof:placetype":"venue"
},
  "geometry": {"coordinates":[-81.091683,28.59625],"type":"Point"}
}