{
  "type": "Feature",
  "properties": {
    "iso:country":"US",
    "sg:address":"3735 W Neptune St",
    "sg:city":"Tampa",
    "sg:classifiers":[
        {
            "category":"Health Services",
            "subcategory":"Doctor",
            "type":"Services"
        }
    ],
    "sg:phone":"+1 813 253 3815",
    "sg:postcode":"33629",
    "sg:province":"FL",
    "sg:tags":[
        "dentist"
    ],
    "wof:name":"Facial & Reconstructive Surg",
    "wof:placetype":"venue"
},
  "geometry": {"coordinates":[-82.505675,27.930292],"type":"Point"}
}