{
  "type": "Feature",
  "properties": {
    "iso:country":"US",
    "sg:address":"810 S State Rd 7",
    "sg:city":"Fort Lauderdale",
    "sg:classifiers":[
        {
            "category":"Professional",
            "subcategory":"Lawyer & Legal Services",
            "type":"Services"
        }
    ],
    "sg:phone":"+1 954 321 9979",
    "sg:postcode":"33317",
    "sg:province":"FL",
    "sg:tags":[
        "law"
    ],
    "wof:name":"Mettellus-Hood & Associates PA",
    "wof:placetype":"venue"
},
  "geometry": {"coordinates":[-80.20162999999999,26.11069],"type":"Point"}
}