{
  "type": "Feature",
  "properties": {
    "addr:full":"1540 S John Rodes Blvd Melbourne FL 32904",
    "addr:housenumber":"1540",
    "addr:postcode":"32904",
    "addr:street":"S John Rodes Blvd",
    "iso:country":"US",
    "sg:address":"1540 S John Rodes Blvd",
    "sg:city":"Melbourne",
    "sg:classifiers":[
        {
            "category":"Sports & Exercise",
            "subcategory":"Gym",
            "type":"Entertainment"
        }
    ],
    "sg:phone":"+1 321 728 0300",
    "sg:postcode":"32904",
    "sg:province":"FL",
    "sg:tags":[
        "club",
        "health",
        "studio",
        "gymnasium"
    ],
    "wof:name":"Yoga Center",
    "wof:placetype":"venue"
},
  "geometry": {"coordinates":[-80.700244,28.079617],"type":"Point"}
}