{
  "type": "Feature",
  "properties": {
    "addr:full":"20250 Juniper St Blountstown FL 32424",
    "addr:housenumber":"20250",
    "addr:postcode":"32424",
    "addr:street":"Juniper St",
    "iso:country":"US",
    "sg:address":"20250 Juniper St",
    "sg:city":"Blountstown",
    "sg:classifiers":[
        {
            "category":"Food & Beverages",
            "subcategory":"Groceries & Convenience Stores",
            "type":"Retail Goods"
        }
    ],
    "sg:phone":"+1 850 674 4959",
    "sg:postcode":"32424",
    "sg:province":"FL",
    "wof:name":"Mom and Pops Deli and Fd Mart",
    "wof:placetype":"venue"
},
  "geometry": {"coordinates":[-85.049909,30.44124],"type":"Point"}
}