{
  "type": "Feature",
  "properties": {
    "iso:country":"US",
    "sg:address":"1787 E Washington Ave",
    "sg:city":"Eustis",
    "sg:classifiers":[
        {
            "category":"Building & Trades",
            "subcategory":"Construction",
            "type":"Services"
        }
    ],
    "sg:phone":"+1 352 589 1481",
    "sg:postcode":"32726",
    "sg:province":"FL",
    "sg:tags":[
        "contractor"
    ],
    "wof:name":"Manganiello Daniel Tile &",
    "wof:placetype":"venue"
},
  "geometry": {"coordinates":[-81.66677900000001,28.847498],"type":"Point"}
}