{
  "type": "Feature",
  "properties": {
    "addr:full":"975 3rd St S Jacksonville Beach FL 32250",
    "addr:housenumber":"975",
    "addr:postcode":"32250",
    "addr:street":"3Rd St S",
    "iso:country":"US",
    "sg:address":"975 3rd St S",
    "sg:city":"Jacksonville Beach",
    "sg:classifiers":[
        {
            "category":"Restaurant",
            "type":"Food & Drink"
        }
    ],
    "sg:menulink":"http://www.allmenus.com/fl/jacksonville/189719-kfc---kentucky-fried-chicken/menu/",
    "sg:phone":"+1 904 246 2882",
    "sg:postcode":"32250",
    "sg:province":"FL",
    "sg:tags":[
        "american",
        "chicken"
    ],
    "wof:name":"KFC - Kentucky Fried Chicken",
    "wof:placetype":"venue"
},
  "geometry": {"coordinates":[-81.389713,30.279132],"type":"Point"}
}