{
  "type": "Feature",
  "properties": {
    "iso:country":"US",
    "sg:address":"5279 Ehrlich Rd",
    "sg:city":"Tampa",
    "sg:classifiers":[
        {
            "category":"Insurance",
            "subcategory":"Insurance Agent",
            "type":"Services"
        },
        {
            "category":"Insurance",
            "subcategory":"Hazard Insurance",
            "type":"Services"
        },
        {
            "category":"Insurance",
            "subcategory":"Title Insurance",
            "type":"Services"
        },
        {
            "category":"Insurance",
            "subcategory":"Life Insurance",
            "type":"Services"
        }
    ],
    "sg:phone":"+1 813 936 2236",
    "sg:postcode":"33624",
    "sg:province":"FL",
    "sg:tags":[
        "business",
        "auto",
        "commercial",
        "homeowner",
        "motorcycle",
        "renter"
    ],
    "wof:name":"Allstate Insurance Company - Calvin Ruff",
    "wof:placetype":"venue"
},
  "geometry": {"coordinates":[-82.539035,28.084625],"type":"Point"}
}