{
  "type": "Feature",
  "properties": {
    "addr:full":"3102 E Cervantes St Pensacola FL 32503",
    "addr:housenumber":"3102",
    "addr:postcode":"32503",
    "addr:street":"E Cervantes St",
    "iso:country":"US",
    "sg:address":"3102 E Cervantes St",
    "sg:city":"Pensacola",
    "sg:classifiers":[
        {
            "category":"Restaurant",
            "type":"Food & Drink"
        }
    ],
    "sg:phone":"+1 850 438 4787",
    "sg:postcode":"32503",
    "sg:province":"FL",
    "wof:name":"Hunan Chinese Restaurant",
    "wof:placetype":"venue"
},
  "geometry": {"coordinates":[-87.17968999999999,30.425181],"type":"Point"}
}