{
  "type": "Feature",
  "properties": {
    "iso:country":"US",
    "sg:address":"2138 Hollywood Blvd",
    "sg:city":"Hollywood",
    "sg:classifiers":[
        {
            "category":"Professional",
            "subcategory":"Lawyer & Legal Services",
            "type":"Services"
        }
    ],
    "sg:phone":"+1 954 925 3538",
    "sg:postcode":"33020",
    "sg:province":"FL",
    "wof:name":"Law Offices Bornstein & Smith",
    "wof:placetype":"venue"
},
  "geometry": {"coordinates":[-80.15034300000001,26.011314],"type":"Point"}
}