{
  "type": "Feature",
  "properties": {
    "iso:country":"US",
    "sg:address":"1033 E Oakland Park Blvd",
    "sg:city":"Fort Lauderdale",
    "sg:classifiers":[
        {
            "category":"Shopping",
            "type":"Retail Goods"
        }
    ],
    "sg:phone":"+1 954 564 5700",
    "sg:postcode":"33334",
    "sg:province":"FL",
    "sg:tags":[
        "craft",
        "art",
        "supply"
    ],
    "wof:name":"Design Images",
    "wof:placetype":"venue"
},
  "geometry": {"coordinates":[-80.131894,26.166923],"type":"Point"}
}