{
  "type": "Feature",
  "properties": {
    "addr:full":"218 E Floral Ave Eustis FL 32726",
    "addr:housenumber":"218",
    "addr:postcode":"32726",
    "addr:street":"E Floral Ave",
    "iso:country":"US",
    "sg:address":"218 E Floral Ave",
    "sg:city":"Eustis",
    "sg:classifiers":[
        {
            "category":"Shopping",
            "subcategory":"Gifts & Souvenirs",
            "type":"Retail Goods"
        }
    ],
    "sg:phone":"+1 352 483 2400",
    "sg:postcode":"32726",
    "sg:province":"FL",
    "sg:tags":[
        "shop"
    ],
    "wof:name":"Across The Border Gift Shop",
    "wof:placetype":"venue"
},
  "geometry": {"coordinates":[-81.68177300000001,28.859244],"type":"Point"}
}