{
  "type": "Feature",
  "properties": {
    "iso:country":"US",
    "sg:address":"16970 San Carlos Blvd",
    "sg:city":"Fort Myers",
    "sg:classifiers":[
        {
            "category":"Health Services",
            "subcategory":"Doctor",
            "type":"Services"
        }
    ],
    "sg:phone":"+1 239 454 6868",
    "sg:postcode":"33908",
    "sg:province":"FL",
    "sg:tags":[
        "physician",
        "surgeon"
    ],
    "wof:name":"Phillip G Davis MD",
    "wof:placetype":"venue"
},
  "geometry": {"coordinates":[-81.943378,26.494307],"type":"Point"}
}