{
  "type": "Feature",
  "properties": {
    "addr:full":"503 SE 25th Ave Ocala FL 34471",
    "addr:housenumber":"503",
    "addr:postcode":"34471",
    "addr:street":"Se 25Th Ave",
    "iso:country":"US",
    "sg:address":"503 SE 25th Ave",
    "sg:city":"Ocala",
    "sg:classifiers":[
        {
            "category":"Government",
            "subcategory":"Office",
            "type":"Public Place"
        }
    ],
    "sg:phone":"+1 352 368 8213",
    "sg:postcode":"34471",
    "sg:province":"FL",
    "sg:website":"www.tc.co.marion.fl.us",
    "wof:name":"Marion County Occupational",
    "wof:placetype":"venue"
},
  "geometry": {"coordinates":[-82.103184,29.18245],"type":"Point"}
}