{
  "type": "Feature",
  "properties": {
    "addr:full":"250 N Atlantic Ave Daytona Beach FL 32118",
    "addr:housenumber":"250",
    "addr:postcode":"32118",
    "addr:street":"N Atlantic Ave",
    "iso:country":"US",
    "sg:address":"250 N Atlantic Ave",
    "sg:city":"Daytona Beach",
    "sg:classifiers":[
        {
            "category":"Restaurant",
            "type":"Food & Drink"
        }
    ],
    "sg:menulink":"http://www.allmenus.com/fl/north-peninsula/183044-planet-smoothie/menu/",
    "sg:phone":"+1 336 226 2002",
    "sg:postcode":"32118",
    "sg:province":"FL",
    "sg:tags":[
        "smoothy",
        "juice",
        "american"
    ],
    "wof:name":"Planet Smoothie",
    "wof:placetype":"venue"
},
  "geometry": {"coordinates":[-81.009832,29.231037],"type":"Point"}
}