{
  "type": "Feature",
  "properties": {
    "iso:country":"US",
    "sg:address":"1315 Lee Rd",
    "sg:city":"Winter Park",
    "sg:classifiers":[
        {
            "category":"Retail",
            "subcategory":"Auto Repair",
            "type":"Services"
        }
    ],
    "sg:phone":"+1 407 647 2711",
    "sg:postcode":"32789",
    "sg:province":"FL",
    "sg:tags":[
        "automotive"
    ],
    "wof:name":"Tuffy Auto Service Centers",
    "wof:placetype":"venue"
},
  "geometry": {"coordinates":[-81.36626,28.605945],"type":"Point"}
}