{
  "type": "Feature",
  "properties": {
    "addr:full":"16182 126th Ter N Jupiter FL 33478",
    "addr:housenumber":"16182",
    "addr:postcode":"33478",
    "addr:street":"126Th Ter N",
    "iso:country":"US",
    "sg:address":"16182 126th Ter N",
    "sg:city":"Jupiter",
    "sg:classifiers":[
        {
            "category":"Shopping",
            "subcategory":"Computers & Home Electronics",
            "type":"Retail Goods"
        }
    ],
    "sg:phone":"+1 561 386 3063",
    "sg:postcode":"33478",
    "sg:province":"FL",
    "sg:tags":[
        "software"
    ],
    "wof:name":"Feedback Technologies",
    "wof:placetype":"venue"
},
  "geometry": {"coordinates":[-80.233653,26.916996],"type":"Point"}
}