{
  "type": "Feature",
  "properties": {
    "iso:country":"US",
    "sg:address":"3597 Cosmos St",
    "sg:city":"Palm Beach Gdns",
    "sg:classifiers":[
        {
            "category":"Building & Trades",
            "subcategory":"Construction",
            "type":"Services"
        },
        {
            "category":"Wholesale",
            "subcategory":"Painting Supplies",
            "type":"Manufacturing & Wholesale Goods"
        }
    ],
    "sg:phone":"+1 561 626 7037",
    "sg:postcode":"33410",
    "sg:province":"FL",
    "sg:tags":[
        "painter"
    ],
    "wof:name":"Lavo Ladasic Custom Painting",
    "wof:placetype":"venue"
},
  "geometry": {"coordinates":[-80.092579,26.819129],"type":"Point"}
}