{
  "type": "Feature",
  "properties": {
    "iso:country":"US",
    "sg:address":"1460 SW 3rd St",
    "sg:city":"Pompano Beach",
    "sg:classifiers":[
        {
            "category":"Building & Trades",
            "subcategory":"Construction",
            "type":"Services"
        }
    ],
    "sg:phone":"+1 954 527 5885",
    "sg:postcode":"33069",
    "sg:province":"FL",
    "sg:tags":[
        "house"
    ],
    "wof:name":"Florida Restoration Specialist",
    "wof:placetype":"venue"
},
  "geometry": {"coordinates":[-80.143923,26.226514],"type":"Point"}
}