{
  "type": "Feature",
  "properties": {
    "addr:full":"782 Neapolitan Way Naples FL 34103",
    "addr:housenumber":"782",
    "addr:postcode":"34103",
    "addr:street":"Neapolitan Way",
    "iso:country":"US",
    "sg:address":"782 Neapolitan Way",
    "sg:city":"Naples",
    "sg:classifiers":[
        {
            "category":"Home & Garden",
            "subcategory":"Household Appliances",
            "type":"Retail Goods"
        }
    ],
    "sg:phone":"+1 239 261 8158",
    "sg:postcode":"34103",
    "sg:province":"FL",
    "wof:name":"Smith Bill Appliances",
    "wof:placetype":"venue"
},
  "geometry": {"coordinates":[-81.801802,26.202869],"type":"Point"}
}