{
  "type": "Feature",
  "properties": {
    "addr:full":"1170 S Broad St Brooksville FL 34601",
    "addr:housenumber":"1170",
    "addr:postcode":"34601",
    "addr:street":"S Broad St",
    "iso:country":"US",
    "sg:address":"1170 S Broad St",
    "sg:city":"Brooksville",
    "sg:classifiers":[
        {
            "category":"Restaurant",
            "type":"Food & Drink"
        }
    ],
    "sg:menulink":"http://www.allmenus.com/fl/brooksville/71015-pizza-hut/menu/",
    "sg:phone":"+1 352 796 4040",
    "sg:postcode":"34601",
    "sg:province":"FL",
    "sg:tags":[
        "american",
        "pizza"
    ],
    "wof:name":"Pizza Hut",
    "wof:placetype":"venue"
},
  "geometry": {"coordinates":[-82.402404,28.543673],"type":"Point"}
}