{
  "type": "Feature",
  "properties": {
    "iso:country":"US",
    "sg:address":"3631 Hedrick St",
    "sg:city":"Jacksonville",
    "sg:classifiers":[
        {
            "category":"Shopping",
            "subcategory":"Gifts & Souvenirs",
            "type":"Retail Goods"
        }
    ],
    "sg:phone":"+1 904 384 4633",
    "sg:postcode":"32205",
    "sg:province":"FL",
    "sg:tags":[
        "shop"
    ],
    "wof:name":"Peeramid Inc",
    "wof:placetype":"venue"
},
  "geometry": {"coordinates":[-81.703394,30.294717],"type":"Point"}
}