{
  "type": "Feature",
  "properties": {
    "iso:country":"US",
    "sg:address":"1 W Oakland Ave",
    "sg:city":"Ocoee",
    "sg:classifiers":[
        {
            "category":"Social Services",
            "subcategory":"Child Care",
            "type":"Services"
        }
    ],
    "sg:phone":"+1 407 877 3332",
    "sg:postcode":"34761",
    "sg:province":"FL",
    "sg:tags":[
        "day"
    ],
    "wof:name":"First Steps Academy Inc",
    "wof:placetype":"venue"
},
  "geometry": {"coordinates":[-81.545333,28.570535],"type":"Point"}
}