{
  "type": "Feature",
  "properties": {
    "iso:country":"US",
    "sg:address":"243 Mateo Way NE",
    "sg:city":"St Petersburg",
    "sg:classifiers":[
        {
            "category":"Shopping",
            "subcategory":"Books",
            "type":"Retail Goods"
        }
    ],
    "sg:phone":"+1 727 894 1565",
    "sg:postcode":"33704",
    "sg:province":"FL",
    "sg:tags":[
        "dealer"
    ],
    "wof:name":"Micklersmith Florida Booktrade",
    "wof:placetype":"venue"
},
  "geometry": {"coordinates":[-82.624444,27.795266],"type":"Point"}
}