{
  "type": "Feature",
  "properties": {
    "addr:full":"7750 W McNab Rd Fort Lauderdale FL 33321",
    "addr:housenumber":"7750",
    "addr:postcode":"33321",
    "addr:street":"W Mcnab Rd",
    "iso:country":"US",
    "sg:address":"7750 W McNab Rd",
    "sg:city":"Fort Lauderdale",
    "sg:classifiers":[
        {
            "category":"Shopping",
            "type":"Retail Goods"
        }
    ],
    "sg:phone":"+1 954 597 2720",
    "sg:postcode":"33321",
    "sg:province":"FL",
    "sg:tags":[
        "merchandise"
    ],
    "wof:name":"Dragons Paintball Shop Corp",
    "wof:placetype":"venue"
},
  "geometry": {"coordinates":[-80.23115199999999,26.208503],"type":"Point"}
}