{
  "type": "Feature",
  "properties": {
    "iso:country":"US",
    "sg:address":"15920 SW 99th Ct",
    "sg:city":"Miami",
    "sg:classifiers":[
        {
            "category":"Recreation",
            "type":"Entertainment"
        }
    ],
    "sg:phone":"+1 305 235 8450",
    "sg:postcode":"33157",
    "sg:province":"FL",
    "sg:tags":[
        "entertainers-family",
        "business"
    ],
    "wof:name":"Str 8 Clownin Entertainment Inc",
    "wof:placetype":"venue"
},
  "geometry": {"coordinates":[-80.354421,25.621708],"type":"Point"}
}