{
  "type": "Feature",
  "properties": {
    "iso:country":"US",
    "sg:address":"1131 Cherokee Ave",
    "sg:city":"Lehigh Acres",
    "sg:classifiers":[
        {
            "category":"Building & Trades",
            "subcategory":"Cleaning & Sanitation",
            "type":"Services"
        }
    ],
    "sg:phone":"+1 239 303 0372",
    "sg:postcode":"33936",
    "sg:province":"FL",
    "sg:tags":[
        "janitor"
    ],
    "wof:name":"Margaret's House Cleaning",
    "wof:placetype":"venue"
},
  "geometry": {"coordinates":[-81.649485,26.597437],"type":"Point"}
}