{
  "type": "Feature",
  "properties": {
    "iso:country":"US",
    "sg:address":"7400 Baymeadows Cir E",
    "sg:city":"Jacksonville",
    "sg:classifiers":[
        {
            "category":"Wholesale",
            "subcategory":"Computers",
            "type":"Manufacturing & Wholesale Goods"
        }
    ],
    "sg:phone":"+1 904 737 5554",
    "sg:postcode":"32256",
    "sg:province":"FL",
    "sg:tags":[
        "prepackaged",
        "software"
    ],
    "wof:name":"American Medical Systems",
    "wof:placetype":"venue"
},
  "geometry": {"coordinates":[-81.56578399999999,30.229929],"type":"Point"}
}