{
  "type": "Feature",
  "properties": {
    "addr:full":"6102 Saint Remy Way Lutz FL 33558",
    "addr:housenumber":"6102",
    "addr:postcode":"33558",
    "addr:street":"Saint Remy Way",
    "iso:country":"US",
    "sg:address":"6102 Saint Remy Way",
    "sg:city":"Lutz",
    "sg:classifiers":[
        {
            "category":"Utilities",
            "subcategory":"Mobile Phone",
            "type":"Services"
        }
    ],
    "sg:phone":"+1 813 383 6637",
    "sg:postcode":"33558",
    "sg:province":"FL",
    "sg:tags":[
        "telephone",
        "cellular"
    ],
    "wof:name":"Quality Data Source",
    "wof:placetype":"venue"
},
  "geometry": {"coordinates":[-82.54995700000001,28.149953],"type":"Point"}
}