{
  "type": "Feature",
  "properties": {
    "iso:country":"US",
    "sg:address":"247 SW 33rd Ct",
    "sg:city":"Fort Lauderdale",
    "sg:classifiers":[
        {
            "category":"Retail",
            "subcategory":"Repair Shop",
            "type":"Services"
        }
    ],
    "sg:phone":"+1 954 764 4770",
    "sg:postcode":"33315",
    "sg:province":"FL",
    "sg:tags":[
        "boat"
    ],
    "wof:name":"Leftlane Preformance & Sales",
    "wof:placetype":"venue"
},
  "geometry": {"coordinates":[-80.14272800000001,26.082644],"type":"Point"}
}