{
  "type": "Feature",
  "properties": {
    "addr:full":"11852 Bruce B Downs Blvd Tampa FL 33612",
    "addr:housenumber":"11852",
    "addr:postcode":"33612",
    "addr:street":"Bruce B Downs Blvd",
    "iso:country":"US",
    "sg:address":"11852 Bruce B Downs Blvd",
    "sg:city":"Tampa",
    "sg:classifiers":[
        {
            "category":"Utilities",
            "subcategory":"Mobile Phone",
            "type":"Services"
        }
    ],
    "sg:phone":"+1 813 910 1007",
    "sg:postcode":"33612",
    "sg:province":"FL",
    "sg:tags":[
        "communication",
        "radiotelephone"
    ],
    "wof:name":"City Beepers",
    "wof:placetype":"venue"
},
  "geometry": {"coordinates":[-82.42614500000001,28.056465],"type":"Point"}
}