{
  "type": "Feature",
  "properties": {
    "addr:full":"15296 Briarcrest Cir Fort Myers FL 33912",
    "addr:housenumber":"15296",
    "addr:postcode":"33912",
    "addr:street":"Briarcrest Cir",
    "iso:country":"US",
    "sg:address":"15296 Briarcrest Cir",
    "sg:city":"Fort Myers",
    "sg:classifiers":[
        {
            "category":"Organizations",
            "subcategory":"Religious Organization",
            "type":"Services"
        }
    ],
    "sg:phone":"+1 239 454 4254",
    "sg:postcode":"33912",
    "sg:province":"FL",
    "wof:name":"First Brazilian Baptist",
    "wof:placetype":"venue"
},
  "geometry": {"coordinates":[-81.84765400000001,26.519414],"type":"Point"}
}