{
  "type": "Feature",
  "properties": {
    "iso:country":"US",
    "sg:address":"7523 Aloma Ave",
    "sg:city":"Winter Park",
    "sg:classifiers":[
        {
            "category":"Banks & Credit Unions",
            "subcategory":"Bank",
            "type":"Services"
        }
    ],
    "sg:phone":"+1 407 677 7325",
    "sg:postcode":"32792",
    "sg:province":"FL",
    "sg:tags":[
        "loan"
    ],
    "wof:name":"Mortgage Executives LLC",
    "wof:placetype":"venue"
},
  "geometry": {"coordinates":[-81.286401,28.609835],"type":"Point"}
}