{
  "type": "Feature",
  "properties": {
    "iso:country":"US",
    "sg:address":"163 Fairway Cir",
    "sg:city":"Naples",
    "sg:classifiers":[
        {
            "category":"Building & Trades",
            "subcategory":"Construction",
            "type":"Services"
        }
    ],
    "sg:phone":"+1 239 596 4473",
    "sg:postcode":"34110",
    "sg:province":"FL",
    "sg:tags":[
        "contractor"
    ],
    "wof:name":"Down Island Pools Inc",
    "wof:placetype":"venue"
},
  "geometry": {"coordinates":[-81.78131399999999,26.280883],"type":"Point"}
}