{
  "type": "Feature",
  "properties": {
    "iso:country":"US",
    "sg:address":"316 Cherry St",
    "sg:city":"Panama City",
    "sg:classifiers":[
        {
            "category":"Real Estate",
            "subcategory":"Real Estate Operator",
            "type":"Services"
        }
    ],
    "sg:phone":"+1 850 769 4666",
    "sg:postcode":"32401",
    "sg:province":"FL",
    "sg:tags":[
        "condominium"
    ],
    "wof:name":"Bay Club Condominiums",
    "wof:placetype":"venue"
},
  "geometry": {"coordinates":[-85.654805,30.145847],"type":"Point"}
}