{
  "type": "Feature",
  "properties": {
    "addr:full":"1500 Timbercrest Dr Deltona FL 32738",
    "addr:housenumber":"1500",
    "addr:postcode":"32738",
    "addr:street":"Timbercrest Dr",
    "iso:country":"US",
    "sg:address":"1500 Timbercrest Dr",
    "sg:city":"Deltona",
    "sg:classifiers":[
        {
            "category":"Shopping",
            "subcategory":"Bicycles & Sporting Goods",
            "type":"Retail Goods"
        }
    ],
    "sg:phone":"+1 386 789 8601",
    "sg:postcode":"32738",
    "sg:province":"FL",
    "sg:tags":[
        "equipment",
        "camping"
    ],
    "wof:name":"Website 199",
    "wof:placetype":"venue"
},
  "geometry": {"coordinates":[-81.19629399999999,28.905644],"type":"Point"}
}