{
  "type": "Feature",
  "properties": {
    "iso:country":"US",
    "sg:address":"1311 Hollywood Blvd",
    "sg:city":"Hollywood",
    "sg:classifiers":[
        {
            "category":"Home & Garden",
            "subcategory":"Home Furnishings",
            "type":"Retail Goods"
        }
    ],
    "sg:phone":"+1 954 920 9859",
    "sg:postcode":"33019",
    "sg:province":"FL",
    "sg:tags":[
        "house"
    ],
    "sg:website":"http://fidowalks.com",
    "wof:name":"Fido Walks",
    "wof:placetype":"venue"
},
  "geometry": {"coordinates":[-80.132885,26.011813],"type":"Point"}
}