{
  "type": "Feature",
  "properties": {
    "addr:full":"229 Pasadena Dr Tampa FL 33615",
    "addr:housenumber":"229",
    "addr:postcode":"33615",
    "addr:street":"Pasadena Dr",
    "iso:country":"US",
    "sg:address":"229 Pasadena Dr",
    "sg:city":"Tampa",
    "sg:classifiers":[
        {
            "category":"Building & Trades",
            "subcategory":"Cleaning & Sanitation",
            "type":"Services"
        }
    ],
    "sg:phone":"+1 813 885 7772",
    "sg:postcode":"33615",
    "sg:province":"FL",
    "sg:tags":[
        "janitor"
    ],
    "wof:name":"Divinity Cleaning Svc Inc",
    "wof:placetype":"venue"
},
  "geometry": {"coordinates":[-82.590191,28.007517],"type":"Point"}
}