{
  "type": "Feature",
  "properties": {
    "addr:full":"3401 River Gardens Cir Pensacola FL 32514",
    "addr:housenumber":"3401",
    "addr:postcode":"32514",
    "addr:street":"River Gardens Cir",
    "iso:country":"US",
    "sg:address":"3401 River Gardens Cir",
    "sg:city":"Pensacola",
    "sg:classifiers":[
        {
            "category":"Real Estate",
            "subcategory":"Real Estate Agent",
            "type":"Services"
        }
    ],
    "sg:phone":"+1 850 478 5530",
    "sg:postcode":"32514",
    "sg:province":"FL",
    "wof:name":"Flannigan Real Estate Inc",
    "wof:placetype":"venue"
},
  "geometry": {"coordinates":[-87.195054,30.533831],"type":"Point"}
}