{
  "type": "Feature",
  "properties": {
    "iso:country":"US",
    "sg:address":"465 Bay Front Pl",
    "sg:city":"Naples",
    "sg:classifiers":[
        {
            "category":"Real Estate",
            "subcategory":"Real Estate Agent",
            "type":"Services"
        }
    ],
    "sg:phone":"+1 239 434 8770",
    "sg:postcode":"34102",
    "sg:province":"FL",
    "wof:name":"Premier Properties-Sw Fl Inc",
    "wof:placetype":"venue"
},
  "geometry": {"coordinates":[-81.789407,26.143204],"type":"Point"}
}