{
  "type": "Feature",
  "properties": {
    "addr:full":"922 Jackson Way Fort Pierce FL 34949",
    "addr:housenumber":"922",
    "addr:postcode":"34949",
    "addr:street":"Jackson Way",
    "iso:country":"US",
    "sg:address":"922 Jackson Way",
    "sg:city":"Fort Pierce",
    "sg:classifiers":[
        {
            "category":"Professional",
            "subcategory":"Management & Consulting",
            "type":"Services"
        }
    ],
    "sg:phone":"+1 772 595 6069",
    "sg:postcode":"34949",
    "sg:province":"FL",
    "wof:name":"Green Machine Management Corp",
    "wof:placetype":"venue"
},
  "geometry": {"coordinates":[-80.30619900000001,27.499175],"type":"Point"}
}