{
  "type": "Feature",
  "properties": {
    "iso:country":"US",
    "sg:address":"185 S Jackson Rd",
    "sg:city":"Venice",
    "sg:classifiers":[
        {
            "category":"Building & Trades",
            "subcategory":"Plumbing",
            "type":"Services"
        }
    ],
    "sg:phone":"+1 941 484 9787",
    "sg:postcode":"34292",
    "sg:province":"FL",
    "sg:tags":[
        "sheet",
        "work",
        "metal",
        "contractor"
    ],
    "wof:name":"All Tin Sheet Metal & Roofing",
    "wof:placetype":"venue"
},
  "geometry": {"coordinates":[-82.36017200000001,27.097943],"type":"Point"}
}