{
  "type": "Feature",
  "properties": {
    "addr:full":"1501 Regal Oak Dr Kissimmee FL 34744",
    "addr:housenumber":"1501",
    "addr:postcode":"34744",
    "addr:street":"Regal Oak Dr",
    "iso:country":"US",
    "sg:address":"1501 Regal Oak Dr",
    "sg:city":"Kissimmee",
    "sg:classifiers":[
        {
            "category":"Professional",
            "subcategory":"Business Services",
            "type":"Services"
        }
    ],
    "sg:phone":"+1 407 933 6766",
    "sg:postcode":"34744",
    "sg:province":"FL",
    "wof:name":"Power Line Solutions Inc",
    "wof:placetype":"venue"
},
  "geometry": {"coordinates":[-81.37943199999999,28.252247],"type":"Point"}
}