{
  "type": "Feature",
  "properties": {
    "iso:country":"US",
    "sg:address":"8445 Butternut Rd",
    "sg:city":"Fort Myers",
    "sg:classifiers":[
        {
            "category":"Building & Trades",
            "subcategory":"Landscaping Services",
            "type":"Services"
        }
    ],
    "sg:phone":"+1 239 267 6049",
    "sg:postcode":"33967",
    "sg:province":"FL",
    "sg:tags":[
        "tree"
    ],
    "wof:name":"D & D Tree & Landscape Svc",
    "wof:placetype":"venue"
},
  "geometry": {"coordinates":[-81.80774099999999,26.468869],"type":"Point"}
}