{
  "type": "Feature",
  "properties": {
    "addr:full":"2519 N McMullen Booth Rd Clearwater FL 33761",
    "addr:housenumber":"2519",
    "addr:postcode":"33761",
    "addr:street":"N Mcmullen Booth Rd",
    "iso:country":"US",
    "sg:address":"2519 N McMullen Booth Rd",
    "sg:city":"Clearwater",
    "sg:classifiers":[
        {
            "category":"Health Services",
            "subcategory":"Clinic",
            "type":"Services"
        }
    ],
    "sg:phone":"+1 813 662 7999",
    "sg:postcode":"33761",
    "sg:province":"FL",
    "sg:tags":[
        "screening",
        "cancer"
    ],
    "wof:name":"Labpass",
    "wof:placetype":"venue"
},
  "geometry": {"coordinates":[-82.70898800000001,28.01439],"type":"Point"}
}