{
  "type": "Feature",
  "properties": {
    "addr:full":"6308 Newtown Cir Tampa FL 33615",
    "addr:housenumber":"6308",
    "addr:postcode":"33615",
    "addr:street":"Newtown Cir",
    "iso:country":"US",
    "sg:address":"6308 Newtown Cir",
    "sg:city":"Tampa",
    "sg:classifiers":[
        {
            "category":"Building & Trades",
            "subcategory":"Construction",
            "type":"Services"
        }
    ],
    "sg:phone":"+1 813 505 3109",
    "sg:postcode":"33615",
    "sg:province":"FL",
    "sg:tags":[
        "house"
    ],
    "wof:name":"Evan Devoe Homes Inc",
    "wof:placetype":"venue"
},
  "geometry": {"coordinates":[-82.600486,28.005025],"type":"Point"}
}