{
  "type": "Feature",
  "properties": {
    "addr:full":"660 Venice Ln Sarasota FL 34242",
    "addr:housenumber":"660",
    "addr:postcode":"34242",
    "addr:street":"Venice Ln",
    "iso:country":"US",
    "sg:address":"660 Venice Ln",
    "sg:city":"Sarasota",
    "sg:classifiers":[
        {
            "category":"Professional",
            "type":"Services"
        }
    ],
    "sg:phone":"+1 941 349 3673",
    "sg:postcode":"34242",
    "sg:province":"FL",
    "sg:tags":[
        "establishment"
    ],
    "wof:name":"Robert Schey Inc",
    "wof:placetype":"venue"
},
  "geometry": {"coordinates":[-82.554367,27.282865],"type":"Point"}
}