{
  "type": "Feature",
  "properties": {
    "iso:country":"US",
    "sg:address":"1641 Land O Lakes Blvd",
    "sg:city":"Lutz",
    "sg:classifiers":[
        {
            "category":"Retail",
            "subcategory":"Auto Repair",
            "type":"Services"
        }
    ],
    "sg:phone":"+1 813 949 0271",
    "sg:postcode":"33549",
    "sg:province":"FL",
    "sg:tags":[
        "body",
        "automobile",
        "painting"
    ],
    "wof:name":"Lutz Land O'Lakes Auto Body",
    "wof:placetype":"venue"
},
  "geometry": {"coordinates":[-82.46386800000001,28.176759],"type":"Point"}
}