{
  "type": "Feature",
  "properties": {
    "addr:full":"1555 E 8th St Jacksonville FL 32206",
    "addr:housenumber":"1555",
    "addr:postcode":"32206",
    "addr:street":"E 8Th St",
    "iso:country":"US",
    "sg:address":"1555 E 8th St",
    "sg:city":"Jacksonville",
    "sg:classifiers":[
        {
            "category":"Banks & Credit Unions",
            "subcategory":"Financial Services",
            "type":"Services"
        }
    ],
    "sg:phone":"+1 904 634 1204",
    "sg:postcode":"32206",
    "sg:province":"FL",
    "sg:tags":[
        "investor"
    ],
    "wof:name":"Cash Depot USA Licata Investme",
    "wof:placetype":"venue"
},
  "geometry": {"coordinates":[-81.633899,30.345375],"type":"Point"}
}