{
  "type": "Feature",
  "properties": {
    "iso:country":"US",
    "sg:address":"137 Live Oak Ave",
    "sg:city":"Daytona Beach",
    "sg:classifiers":[
        {
            "category":"Organizations",
            "subcategory":"Religious Organization",
            "type":"Services"
        }
    ],
    "sg:phone":"+1 386 252 4540",
    "sg:postcode":"32114",
    "sg:province":"FL",
    "sg:tags":[
        "church"
    ],
    "wof:name":"First Church Of Christ Scntst",
    "wof:placetype":"venue"
},
  "geometry": {"coordinates":[-81.017842,29.205848],"type":"Point"}
}