{
  "type": "Feature",
  "properties": {
    "iso:country":"US",
    "sg:address":"606 W Main St",
    "sg:city":"Leesburg",
    "sg:classifiers":[
        {
            "category":"Shopping",
            "subcategory":"Used Merchandise",
            "type":"Retail Goods"
        }
    ],
    "sg:phone":"+1 352 360 0091",
    "sg:postcode":"34748",
    "sg:province":"FL",
    "sg:tags":[
        "antique"
    ],
    "wof:name":"Corner Nook Antiques",
    "wof:placetype":"venue"
},
  "geometry": {"coordinates":[-81.87844,28.811205],"type":"Point"}
}