{
  "type": "Feature",
  "properties": {
    "iso:country":"US",
    "sg:address":"11941 Bostick St",
    "sg:city":"Dunnellon",
    "sg:classifiers":[
        {
            "category":"Shopping",
            "subcategory":"Gifts & Souvenirs",
            "type":"Retail Goods"
        },
        {
            "category":"Shopping",
            "subcategory":"Books",
            "type":"Retail Goods"
        }
    ],
    "sg:phone":"+1 352 489 7555",
    "sg:postcode":"34432",
    "sg:province":"FL",
    "sg:tags":[
        "comic"
    ],
    "wof:name":"7th Inning Stretch",
    "wof:placetype":"venue"
},
  "geometry": {"coordinates":[-82.457927,29.051479],"type":"Point"}
}