{
  "type": "Feature",
  "properties": {
    "iso:country":"US",
    "sg:address":"925 Macco Rd",
    "sg:city":"Port St John",
    "sg:classifiers":[
        {
            "category":"Organizations",
            "subcategory":"Professional Association",
            "type":"Services"
        }
    ],
    "sg:phone":"+1 321 632 6158",
    "sg:postcode":"32927",
    "sg:province":"FL",
    "wof:name":"Woods Of Port St John",
    "wof:placetype":"venue"
},
  "geometry": {"coordinates":[-80.779467,28.482708],"type":"Point"}
}