{
  "type": "Feature",
  "properties": {
    "iso:country":"US",
    "sg:address":"8403 NW 20th Pl",
    "sg:city":"Coral Springs",
    "sg:classifiers":[
        {
            "category":"Retail",
            "subcategory":"Repair Shop",
            "type":"Services"
        },
        {
            "category":"Retail",
            "subcategory":"Auto Repair",
            "type":"Services"
        }
    ],
    "sg:phone":"+1 561 392 3133",
    "sg:postcode":"33071",
    "sg:province":"FL",
    "sg:tags":[
        "repairing",
        "automobile"
    ],
    "wof:name":"All Sprinkler Pump & Repair",
    "wof:placetype":"venue"
},
  "geometry": {"coordinates":[-80.238302,26.255591],"type":"Point"}
}