{
  "type": "Feature",
  "properties": {
    "addr:full":"21 SE 10th St Deerfield Beach FL 33441",
    "addr:housenumber":"21",
    "addr:postcode":"33441",
    "addr:street":"Se 10Th St",
    "iso:country":"US",
    "sg:address":"21 SE 10th St",
    "sg:city":"Deerfield Beach",
    "sg:classifiers":[
        {
            "category":"Wholesale",
            "subcategory":"Non-durable Goods",
            "type":"Manufacturing & Wholesale Goods"
        }
    ],
    "sg:phone":"+1 954 596 2095",
    "sg:postcode":"33441",
    "sg:province":"FL",
    "sg:tags":[
        "merchandise",
        "general"
    ],
    "wof:name":"Global Bridges Corp",
    "wof:placetype":"venue"
},
  "geometry": {"coordinates":[-80.10188100000001,26.305004],"type":"Point"}
}