{
  "type": "Feature",
  "properties": {
    "iso:country":"US",
    "sg:address":"2900 NW 36th St",
    "sg:city":"Miami",
    "sg:classifiers":[
        {
            "category":"Autos & Motor Vehicles",
            "subcategory":"Automobile Sales",
            "type":"Retail Goods"
        },
        {
            "category":"Autos & Motor Vehicles",
            "subcategory":"Auto Supplies",
            "type":"Retail Goods"
        },
        {
            "category":"Retail",
            "subcategory":"Auto Repair",
            "type":"Services"
        }
    ],
    "sg:phone":"+1 305 635 8000",
    "sg:postcode":"33142",
    "sg:province":"FL",
    "sg:tags":[
        "body",
        "repairing",
        "car",
        "accessory",
        "part",
        "new",
        "painting"
    ],
    "sg:website":"http://www.billseidlekia.com",
    "wof:name":"Nissan",
    "wof:placetype":"venue"
},
  "geometry": {"coordinates":[-80.24226400000001,25.80904],"type":"Point"}
}