{
  "type": "Feature",
  "properties": {
    "iso:country":"US",
    "sg:address":"1615 Harrison St",
    "sg:city":"Hollywood",
    "sg:classifiers":[
        {
            "category":"Real Estate",
            "subcategory":"Real Estate Agent",
            "type":"Services"
        }
    ],
    "sg:phone":"+1 954 929 6428",
    "sg:postcode":"33020",
    "sg:province":"FL",
    "wof:name":"Marjorie S Korf PA",
    "wof:placetype":"venue"
},
  "geometry": {"coordinates":[-80.14045400000001,26.010739],"type":"Point"}
}