{
  "type": "Feature",
  "properties": {
    "addr:full":"11853 47th Rd N West Palm Beach FL 33411",
    "addr:housenumber":"11853",
    "addr:postcode":"33411",
    "addr:street":"47Th Rd N",
    "iso:country":"US",
    "sg:address":"11853 47th Rd N",
    "sg:city":"West Palm Beach",
    "sg:classifiers":[
        {
            "category":"Professional",
            "subcategory":"Business Services",
            "type":"Services"
        }
    ],
    "sg:phone":"+1 561 793 5098",
    "sg:postcode":"33411",
    "sg:province":"FL",
    "sg:tags":[
        "drafting"
    ],
    "wof:name":"Charles Franklin",
    "wof:placetype":"venue"
},
  "geometry": {"coordinates":[-80.230171,26.747551],"type":"Point"}
}