{
  "type": "Feature",
  "properties": {
    "iso:country":"US",
    "sg:address":"2031 NE 33rd St",
    "sg:city":"Pompano Beach",
    "sg:classifiers":[
        {
            "category":"Professional",
            "subcategory":"Accounting & Tax Preparation",
            "type":"Services"
        }
    ],
    "sg:phone":"+1 954 784 9675",
    "sg:postcode":"33064",
    "sg:province":"FL",
    "sg:tags":[
        "return"
    ],
    "wof:name":"Jf Tax Service",
    "wof:placetype":"venue"
},
  "geometry": {"coordinates":[-80.096036,26.272175],"type":"Point"}
}