{
  "type": "Feature",
  "properties": {
    "addr:full":"22465 Pasture Ln Brooksville FL 34601",
    "addr:housenumber":"22465",
    "addr:postcode":"34601",
    "addr:street":"Pasture Ln",
    "iso:country":"US",
    "sg:address":"22465 Pasture Ln",
    "sg:city":"Brooksville",
    "sg:classifiers":[
        {
            "category":"Building & Trades",
            "subcategory":"Landscaping Services",
            "type":"Services"
        }
    ],
    "sg:phone":"+1 352 799 0886",
    "sg:postcode":"34601",
    "sg:province":"FL",
    "sg:tags":[
        "landscape",
        "contractor"
    ],
    "wof:name":"G E Landscaping Inc",
    "wof:placetype":"venue"
},
  "geometry": {"coordinates":[-82.358437,28.544638],"type":"Point"}
}