{
  "type": "Feature",
  "properties": {
    "addr:full":"7511 Abbey Glen Bradenton FL 34202",
    "addr:housenumber":"7511",
    "addr:postcode":"34202",
    "addr:street":"Abbey Glen",
    "iso:country":"US",
    "sg:address":"7511 Abbey Glen",
    "sg:city":"Bradenton",
    "sg:classifiers":[
        {
            "category":"Real Estate",
            "subcategory":"Real Estate Operator",
            "type":"Services"
        }
    ],
    "sg:phone":"+1 941 907 9512",
    "sg:postcode":"34202",
    "sg:province":"FL",
    "sg:tags":[
        "building",
        "nonresidential"
    ],
    "wof:name":"Wildcat Properties LLC",
    "wof:placetype":"venue"
},
  "geometry": {"coordinates":[-82.404279,27.40483],"type":"Point"}
}