{
  "type": "Feature",
  "properties": {
    "addr:full":"1155 NW 64th Ter Gainesville FL 32605",
    "addr:housenumber":"1155",
    "addr:postcode":"32605",
    "addr:street":"Nw 64Th Ter",
    "iso:country":"US",
    "sg:address":"1155 NW 64th Ter",
    "sg:city":"Gainesville",
    "sg:classifiers":[
        {
            "category":"Health Services",
            "subcategory":"Doctor",
            "type":"Services"
        }
    ],
    "sg:phone":"+1 352 331 6736",
    "sg:postcode":"32605",
    "sg:province":"FL",
    "sg:tags":[
        "physician",
        "surgeon"
    ],
    "wof:name":"Dean C Kramer MD",
    "wof:placetype":"venue"
},
  "geometry": {"coordinates":[-82.410871,29.661934],"type":"Point"}
}