{
  "type": "Feature",
  "properties": {
    "iso:country":"US",
    "sg:address":"855 Elizabeth St",
    "sg:city":"Punta Gorda",
    "sg:classifiers":[
        {
            "category":"Professional",
            "subcategory":"Advertising",
            "type":"Services"
        }
    ],
    "sg:phone":"+1 941 639 6393",
    "sg:postcode":"33950",
    "sg:province":"FL",
    "sg:tags":[
        "distribution"
    ],
    "wof:name":"West Florida Distributors",
    "wof:placetype":"venue"
},
  "geometry": {"coordinates":[-82.044101,26.931169],"type":"Point"}
}