{
  "type": "Feature",
  "properties": {
    "addr:full":"3412 W 84th St Hialeah FL 33018",
    "addr:housenumber":"3412",
    "addr:postcode":"33018",
    "addr:street":"W 84Th St",
    "iso:country":"US",
    "sg:address":"3412 W 84th St",
    "sg:city":"Hialeah",
    "sg:classifiers":[
        {
            "category":"Health Services",
            "subcategory":"Health Practitioner",
            "type":"Services"
        }
    ],
    "sg:phone":"+1 305 821 8889",
    "sg:postcode":"33018",
    "sg:province":"FL",
    "sg:tags":[
        "gambling",
        "addiction-information",
        "treatment"
    ],
    "wof:name":"T & R Rehab Inc",
    "wof:placetype":"venue"
},
  "geometry": {"coordinates":[-80.35209999999999,25.898549],"type":"Point"}
}