{
  "type": "Feature",
  "properties": {
    "iso:country":"US",
    "sg:address":"1102 George Jenkins Blvd",
    "sg:city":"Lakeland",
    "sg:classifiers":[
        {
            "category":"Banks & Credit Unions",
            "subcategory":"Bank",
            "type":"Services"
        }
    ],
    "sg:phone":"+1 863 687 3981",
    "sg:postcode":"33815",
    "sg:province":"FL",
    "wof:name":"Tampa Scl Employee Fed Cu",
    "wof:placetype":"venue"
},
  "geometry": {"coordinates":[-81.97011999999999,28.042768],"type":"Point"}
}