{
  "type": "Feature",
  "properties": {
    "addr:full":"5743 NW 112th Pl Doral FL 33178",
    "addr:housenumber":"5743",
    "addr:postcode":"33178",
    "addr:street":"Nw 112Th Pl",
    "iso:country":"US",
    "sg:address":"5743 NW 112th Pl",
    "sg:city":"Doral",
    "sg:classifiers":[
        {
            "category":"Organizations",
            "subcategory":"Membership Organization",
            "type":"Services"
        }
    ],
    "sg:phone":"+1 305 592 6192",
    "sg:postcode":"33178",
    "sg:province":"FL",
    "sg:tags":[
        "military",
        "veteran"
    ],
    "wof:name":"Foreign Aviation Specialist, Inc.",
    "wof:placetype":"venue"
},
  "geometry": {"coordinates":[-80.378979,25.825299],"type":"Point"}
}