{
  "type": "Feature",
  "properties": {
    "iso:country":"US",
    "sg:address":"644 Clearlake Rd",
    "sg:city":"Cocoa",
    "sg:classifiers":[
        {
            "category":"Building & Trades",
            "subcategory":"Electrical",
            "type":"Services"
        }
    ],
    "sg:phone":"+1 321 632 7169",
    "sg:postcode":"32922",
    "sg:province":"FL",
    "sg:tags":[
        "electrical",
        "electric",
        "contractor"
    ],
    "wof:name":"Sun Kraft Electrical Contrs",
    "wof:placetype":"venue"
},
  "geometry": {"coordinates":[-80.754915,28.363496],"type":"Point"}
}