{
  "type": "Feature",
  "properties": {
    "addr:full":"8439 NW 72nd St Miami FL 33166",
    "addr:housenumber":"8439",
    "addr:postcode":"33166",
    "addr:street":"Nw 72Nd St",
    "iso:country":"US",
    "sg:address":"8439 NW 72nd St",
    "sg:city":"Miami",
    "sg:classifiers":[
        {
            "category":"Wholesale",
            "subcategory":"Office Equipment",
            "type":"Manufacturing & Wholesale Goods"
        }
    ],
    "sg:phone":"+1 305 477 5336",
    "sg:postcode":"33166",
    "sg:province":"FL",
    "sg:tags":[
        "machine",
        "duplicating",
        "copying"
    ],
    "wof:name":"Repo Depot S",
    "wof:placetype":"venue"
},
  "geometry": {"coordinates":[-80.3381,25.839011],"type":"Point"}
}