{
  "type": "Feature",
  "properties": {
    "addr:full":"1194 S Broad St Brooksville FL 34601",
    "addr:housenumber":"1194",
    "addr:postcode":"34601",
    "addr:street":"S Broad St",
    "iso:country":"US",
    "sg:address":"1194 S Broad St",
    "sg:city":"Brooksville",
    "sg:classifiers":[
        {
            "category":"Retail",
            "subcategory":"Laundry & Dry Cleaning",
            "type":"Services"
        }
    ],
    "sg:phone":"+1 352 796 7965",
    "sg:postcode":"34601",
    "sg:province":"FL",
    "sg:tags":[
        "cleaners"
    ],
    "wof:name":"Touch Of Quality Cleaners",
    "wof:placetype":"venue"
},
  "geometry": {"coordinates":[-82.402725,28.542388],"type":"Point"}
}