{
  "type": "Feature",
  "properties": {
    "addr:full":"5488 58th St N Kenneth City FL 33709",
    "addr:housenumber":"5488",
    "addr:postcode":"33709",
    "addr:street":"58Th St N",
    "iso:country":"US",
    "sg:address":"5488 58th St N",
    "sg:city":"Kenneth City",
    "sg:classifiers":[
        {
            "category":"Bars & Pubs",
            "type":"Food & Drink"
        }
    ],
    "sg:phone":"+1 727 545 1992",
    "sg:postcode":"33709",
    "sg:province":"FL",
    "wof:name":"Where-Else Tavern",
    "wof:placetype":"venue"
},
  "geometry": {"coordinates":[-82.71235,27.821108],"type":"Point"}
}