{
  "type": "Feature",
  "properties": {
    "addr:full":"1801 Capital Cir SE Tallahassee FL 32301",
    "addr:housenumber":"1801",
    "addr:postcode":"32301",
    "addr:street":"Capital Cir Se",
    "iso:country":"US",
    "sg:address":"1801 Capital Cir SE",
    "sg:city":"Tallahassee",
    "sg:classifiers":[
        {
            "category":"Government",
            "subcategory":"Office",
            "type":"Public Place"
        }
    ],
    "sg:phone":"+1 850 488 7522",
    "sg:postcode":"32301",
    "sg:province":"FL",
    "sg:tags":[
        "sector",
        "regulation",
        "commercial"
    ],
    "wof:name":"Bureau of Notaries",
    "wof:placetype":"venue"
},
  "geometry": {"coordinates":[-84.227728,30.421682],"type":"Point"}
}