{
  "type": "Feature",
  "properties": {
    "addr:full":"14365 SW 285th St Homestead FL 33033",
    "addr:housenumber":"14365",
    "addr:postcode":"33033",
    "addr:street":"Sw 285Th St",
    "iso:country":"US",
    "sg:address":"14365 SW 285th St",
    "sg:city":"Homestead",
    "sg:classifiers":[
        {
            "category":"Building & Trades",
            "subcategory":"Landscaping Services",
            "type":"Services"
        }
    ],
    "sg:phone":"+1 305 248 5554",
    "sg:postcode":"33033",
    "sg:province":"FL",
    "wof:name":"Noel Mondragon Lawn Care",
    "wof:placetype":"venue"
},
  "geometry": {"coordinates":[-80.424503,25.502549],"type":"Point"}
}