{
  "type": "Feature",
  "properties": {
    "iso:country":"US",
    "sg:address":"7106 Fairway Dr",
    "sg:city":"Palm Beach Gdns",
    "sg:classifiers":[
        {
            "category":"Banks & Credit Unions",
            "subcategory":"Bank",
            "type":"Services"
        }
    ],
    "sg:phone":"+1 561 624 4002",
    "sg:postcode":"33418",
    "sg:province":"FL",
    "sg:tags":[
        "federal",
        "savings",
        "institution"
    ],
    "wof:name":"Washington Mutual Bank",
    "wof:placetype":"venue"
},
  "geometry": {"coordinates":[-80.133565,26.836686],"type":"Point"}
}