{
  "type": "Feature",
  "properties": {
    "iso:country":"US",
    "sg:address":"212 Briny Ave",
    "sg:city":"Pompano Beach",
    "sg:classifiers":[
        {
            "category":"Real Estate",
            "subcategory":"Real Estate Services",
            "type":"Services"
        }
    ],
    "sg:phone":"+1 954 785 4440",
    "sg:postcode":"33062",
    "sg:province":"FL",
    "sg:tags":[
        "research"
    ],
    "wof:name":"Real Estate Marketing/Research",
    "wof:placetype":"venue"
},
  "geometry": {"coordinates":[-80.090029,26.228868],"type":"Point"}
}