{
  "type": "Feature",
  "properties": {
    "addr:full":"775 W 49th St Ste 1 Hialeah FL 33012",
    "addr:housenumber":"775",
    "addr:postcode":"33012",
    "addr:street":"W 49Th St Ste 1",
    "iso:country":"US",
    "sg:address":"775 W 49th St Ste 1",
    "sg:city":"Hialeah",
    "sg:classifiers":[
        {
            "category":"Shopping",
            "subcategory":"Pharmacy",
            "type":"Retail Goods"
        }
    ],
    "sg:phone":"+1 305 823 0823",
    "sg:postcode":"33012",
    "sg:province":"FL",
    "sg:tags":[
        "drugstore"
    ],
    "sg:website":"www.navarropharmacies.com",
    "wof:name":"Navarro Discount Pharmacies",
    "wof:placetype":"venue"
},
  "geometry": {"coordinates":[-80.298486,25.866837],"type":"Point"}
}