{
  "type": "Feature",
  "properties": {
    "addr:full":"3866 Reid St Palatka FL 32177",
    "addr:housenumber":"3866",
    "addr:postcode":"32177",
    "addr:street":"Reid St",
    "iso:country":"US",
    "sg:address":"3866 Reid St",
    "sg:city":"Palatka",
    "sg:classifiers":[
        {
            "category":"Retail",
            "subcategory":"Auto Repair",
            "type":"Services"
        }
    ],
    "sg:phone":"+1 386 329 9970",
    "sg:postcode":"32177",
    "sg:province":"FL",
    "sg:tags":[
        "repairing",
        "automobile"
    ],
    "wof:name":"United Auto Repairs",
    "wof:placetype":"venue"
},
  "geometry": {"coordinates":[-81.673863,29.65987],"type":"Point"}
}