{
  "type": "Feature",
  "properties": {
    "iso:country":"US",
    "sg:address":"2010 NE 7th Ave",
    "sg:city":"Dania",
    "sg:classifiers":[
        {
            "category":"Building & Trades",
            "subcategory":"Construction",
            "type":"Services"
        }
    ],
    "sg:phone":"+1 954 763 5488",
    "sg:postcode":"33004",
    "sg:province":"FL",
    "sg:tags":[
        "development",
        "composite",
        "research"
    ],
    "wof:name":"Rosewood Government Svcs LLC",
    "wof:placetype":"venue"
},
  "geometry": {"coordinates":[-80.13202800000001,26.07097],"type":"Point"}
}