{
  "type": "Feature",
  "properties": {
    "iso:country":"US",
    "sg:address":"1027 Town Center Dr",
    "sg:city":"Orange City",
    "sg:classifiers":[
        {
            "category":"Health Services",
            "subcategory":"Doctor",
            "type":"Services"
        }
    ],
    "sg:phone":"+1 386 456 1200",
    "sg:postcode":"32763",
    "sg:province":"FL",
    "sg:tags":[
        "practice",
        "family"
    ],
    "wof:name":"Gonzalez Aimee MD PA",
    "wof:placetype":"venue"
},
  "geometry": {"coordinates":[-81.286795,28.906368],"type":"Point"}
}