{
  "type": "Feature",
  "properties": {
    "addr:full":"9855 Crotty Ave Hastings FL 32145",
    "addr:housenumber":"9855",
    "addr:postcode":"32145",
    "addr:street":"Crotty Ave",
    "iso:country":"US",
    "sg:address":"9855 Crotty Ave",
    "sg:city":"Hastings",
    "sg:classifiers":[
        {
            "category":"Health Services",
            "subcategory":"Clinic",
            "type":"Services"
        }
    ],
    "sg:phone":"+1 904 692 1129",
    "sg:postcode":"32145",
    "sg:province":"FL",
    "sg:tags":[
        "home"
    ],
    "wof:name":"Dewaysha's Home Care Svc",
    "wof:placetype":"venue"
},
  "geometry": {"coordinates":[-81.42801799999999,29.664274],"type":"Point"}
}