{
  "type": "Feature",
  "properties": {
    "iso:country":"US",
    "sg:address":"20910 SW 85th Ave",
    "sg:city":"Miami",
    "sg:classifiers":[
        {
            "category":"Organizations",
            "subcategory":"Professional Association",
            "type":"Services"
        }
    ],
    "sg:phone":"+1 786 242 1636",
    "sg:postcode":"33189",
    "sg:province":"FL",
    "wof:name":"Centennial Home Owners Assn",
    "wof:placetype":"venue"
},
  "geometry": {"coordinates":[-80.326605,25.573333],"type":"Point"}
}