{
  "type": "Feature",
  "properties": {
    "addr:full":"5407 Boran Dr Tampa FL 33610",
    "addr:housenumber":"5407",
    "addr:postcode":"33610",
    "addr:street":"Boran Dr",
    "iso:country":"US",
    "sg:address":"5407 Boran Dr",
    "sg:city":"Tampa",
    "sg:classifiers":[
        {
            "category":"Building & Trades",
            "subcategory":"Construction",
            "type":"Services"
        }
    ],
    "sg:phone":"+1 813 628 4811",
    "sg:postcode":"33610",
    "sg:province":"FL",
    "sg:tags":[
        "new",
        "general",
        "commercial",
        "contractor"
    ],
    "sg:website":"www.cancogencon.com",
    "wof:name":"Canco General Contractors Inc",
    "wof:placetype":"venue"
},
  "geometry": {"coordinates":[-82.388103,27.998548],"type":"Point"}
}