{
  "type": "Feature",
  "properties": {
    "addr:full":"3720 NW 43 St Gainesville FL 32606",
    "addr:housenumber":"3720",
    "addr:postcode":"32606",
    "addr:street":"Nw 43 St",
    "iso:country":"US",
    "sg:address":"3720 NW 43 St",
    "sg:city":"Gainesville",
    "sg:classifiers":[
        {
            "category":"Shopping",
            "subcategory":"Optical Goods",
            "type":"Retail Goods"
        }
    ],
    "sg:phone":"+1 352 367 0077",
    "sg:postcode":"32606",
    "sg:province":"FL",
    "wof:name":"Adonis Optical Inc",
    "wof:placetype":"venue"
},
  "geometry": {"coordinates":[-82.388999,29.688468],"type":"Point"}
}