{
  "type": "Feature",
  "properties": {
    "iso:country":"US",
    "sg:address":"900 Meridian Ave",
    "sg:city":"Miami Beach",
    "sg:classifiers":[
        {
            "category":"Professional",
            "subcategory":"Engineering",
            "type":"Services"
        }
    ],
    "sg:phone":"+1 305 674 0844",
    "sg:postcode":"33139",
    "sg:province":"FL",
    "sg:tags":[
        "engineer"
    ],
    "wof:name":"Southern Power Resources Inc",
    "wof:placetype":"venue"
},
  "geometry": {"coordinates":[-80.136235,25.780628],"type":"Point"}
}