{
  "type": "Feature",
  "properties": {
    "iso:country":"US",
    "sg:address":"932 NW 128th Pl",
    "sg:city":"Miami",
    "sg:classifiers":[
        {
            "category":"Professional",
            "subcategory":"Engineering",
            "type":"Services"
        }
    ],
    "sg:phone":"+1 305 216 9561",
    "sg:postcode":"33182",
    "sg:province":"FL",
    "sg:tags":[
        "civil",
        "engineer"
    ],
    "wof:name":"Joseph P Chi & Associates Inc",
    "wof:placetype":"venue"
},
  "geometry": {"coordinates":[-80.40440599999999,25.77836],"type":"Point"}
}