{
  "type": "Feature",
  "properties": {
    "iso:country":"US",
    "sg:address":"2940 Kerry Forest Pkwy",
    "sg:city":"Tallahassee",
    "sg:classifiers":[
        {
            "category":"Professional",
            "subcategory":"Lawyer & Legal Services",
            "type":"Services"
        }
    ],
    "sg:phone":"+1 850 425 2855",
    "sg:postcode":"32309",
    "sg:province":"FL",
    "sg:tags":[
        "attorney"
    ],
    "wof:name":"Claire A Duchemin Pa",
    "wof:placetype":"venue"
},
  "geometry": {"coordinates":[-84.22386,30.540433],"type":"Point"}
}