{
  "type": "Feature",
  "properties": {
    "addr:full":"135 King St St Augustine FL 32084",
    "addr:housenumber":"135",
    "addr:postcode":"32084",
    "addr:street":"King St",
    "iso:country":"US",
    "sg:address":"135 King St",
    "sg:city":"St Augustine",
    "sg:classifiers":[
        {
            "category":"Shopping",
            "subcategory":"Florist",
            "type":"Retail Goods"
        }
    ],
    "sg:phone":"+1 904 824 9332",
    "sg:postcode":"32084",
    "sg:province":"FL",
    "sg:website":"www.abasketofluv.com",
    "wof:name":"Flowers By Shirley",
    "wof:placetype":"venue"
},
  "geometry": {"coordinates":[-81.31912699999999,29.891367],"type":"Point"}
}