{
  "type": "Feature",
  "properties": {
    "addr:full":"166 9th Ave Vero Beach FL 32962",
    "addr:housenumber":"166",
    "addr:postcode":"32962",
    "addr:street":"9Th Ave",
    "iso:country":"US",
    "sg:address":"166 9th Ave",
    "sg:city":"Vero Beach",
    "sg:classifiers":[
        {
            "category":"Building & Trades",
            "subcategory":"Construction",
            "type":"Services"
        }
    ],
    "sg:phone":"+1 772 567 7343",
    "sg:postcode":"32962",
    "sg:province":"FL",
    "sg:tags":[
        "tile",
        "dealer",
        "contractor"
    ],
    "wof:name":"Geno's Ceramic Tile",
    "wof:placetype":"venue"
},
  "geometry": {"coordinates":[-80.391402,27.604074],"type":"Point"}
}