{
  "type": "Feature",
  "properties": {
    "iso:country":"US",
    "sg:address":"2030 Murrell Rd",
    "sg:city":"Rockledge",
    "sg:classifiers":[
        {
            "category":"Food & Beverages",
            "subcategory":"Bakery",
            "type":"Retail Goods"
        }
    ],
    "sg:phone":"+1 321 639 0100",
    "sg:postcode":"32955",
    "sg:province":"FL",
    "wof:name":"George Westen",
    "wof:placetype":"venue"
},
  "geometry": {"coordinates":[-80.721976,28.315815],"type":"Point"}
}