{
  "type": "Feature",
  "properties": {
    "addr:full":"4822 SW 159th Ave Hollywood FL 33027",
    "addr:housenumber":"4822",
    "addr:postcode":"33027",
    "addr:street":"Sw 159Th Ave",
    "iso:country":"US",
    "sg:address":"4822 SW 159th Ave",
    "sg:city":"Hollywood",
    "sg:classifiers":[
        {
            "category":"Building & Trades",
            "subcategory":"Construction",
            "type":"Services"
        }
    ],
    "sg:phone":"+1 954 517 0508",
    "sg:postcode":"33027",
    "sg:province":"FL",
    "sg:tags":[
        "new",
        "dwelling"
    ],
    "wof:name":"Erm Building Corp",
    "wof:placetype":"venue"
},
  "geometry": {"coordinates":[-80.358851,25.966961],"type":"Point"}
}