{
  "type": "Feature",
  "properties": {
    "addr:full":"5336 Ashton Ct Sarasota FL 34233",
    "addr:housenumber":"5336",
    "addr:postcode":"34233",
    "addr:street":"Ashton Ct",
    "iso:country":"US",
    "sg:address":"5336 Ashton Ct",
    "sg:city":"Sarasota",
    "sg:classifiers":[
        {
            "category":"Manufacturing",
            "subcategory":"Glass & Minerals",
            "type":"Manufacturing & Wholesale Goods"
        }
    ],
    "sg:phone":"+1 941 924 1663",
    "sg:postcode":"34233",
    "sg:province":"FL",
    "sg:tags":[
        "fabricator",
        "fiber"
    ],
    "wof:name":"Reliable Fiberglass",
    "wof:placetype":"venue"
},
  "geometry": {"coordinates":[-82.476028,27.27392],"type":"Point"}
}