{
  "type": "Feature",
  "properties": {
    "iso:country":"US",
    "sg:address":"2721 Forsyth Rd",
    "sg:city":"Winter Park",
    "sg:classifiers":[
        {
            "category":"Manufacturing",
            "subcategory":"Printing",
            "type":"Manufacturing & Wholesale Goods"
        }
    ],
    "sg:phone":"+1 407 671 0600",
    "sg:postcode":"32792",
    "sg:province":"FL",
    "sg:tags":[
        "commercial",
        "offset"
    ],
    "wof:name":"Impact Printing Co",
    "wof:placetype":"venue"
},
  "geometry": {"coordinates":[-81.294568,28.586615],"type":"Point"}
}