{
  "type": "Feature",
  "properties": {
    "iso:country":"US",
    "sg:address":"1011 S Federal Hwy",
    "sg:city":"Hollywood",
    "sg:classifiers":[
        {
            "category":"Professional",
            "subcategory":"Lawyer & Legal Services",
            "type":"Services"
        }
    ],
    "sg:phone":"+1 954 920 1571",
    "sg:postcode":"33020",
    "sg:province":"FL",
    "sg:tags":[
        "litigation",
        "attorney",
        "injury",
        "personal",
        "civil",
        "practice",
        "trial",
        "law"
    ],
    "sg:website":"http://www.1800askfree.com",
    "wof:name":"David W Singer & Assoc Pa",
    "wof:placetype":"venue"
},
  "geometry": {"coordinates":[-80.142752,26.003109],"type":"Point"}
}