{
  "type": "Feature",
  "properties": {
    "iso:country":"US",
    "sg:address":"237 Foxtail Dr",
    "sg:city":"West Palm Beach",
    "sg:classifiers":[
        {
            "category":"Organizations",
            "subcategory":"Community Association",
            "type":"Services"
        }
    ],
    "sg:phone":"+1 561 968 7766",
    "sg:postcode":"33415",
    "sg:province":"FL",
    "sg:tags":[
        "business"
    ],
    "wof:name":"Charter CLB Palm Bch Hmeowners",
    "wof:placetype":"venue"
},
  "geometry": {"coordinates":[-80.143282,26.645142],"type":"Point"}
}