{
  "type": "Feature",
  "properties": {
    "iso:country":"US",
    "sg:address":"1559 Cesery Blvd",
    "sg:city":"Jacksonville",
    "sg:classifiers":[
        {
            "category":"Arts & Performance",
            "subcategory":"Theater",
            "type":"Entertainment"
        }
    ],
    "sg:phone":"+1 904 744 9011",
    "sg:postcode":"32211",
    "sg:province":"FL",
    "sg:tags":[
        "dance",
        "company"
    ],
    "wof:name":"Beyond Dance",
    "wof:placetype":"venue"
},
  "geometry": {"coordinates":[-81.59697300000001,30.336419],"type":"Point"}
}