{
  "type": "Feature",
  "properties": {
    "addr:full":"4880 Placida Rd Englewood FL 34224",
    "addr:postcode":"4880;34224",
    "addr:street":"Placida Rd",
    "iso:country":"US",
    "sg:address":"4880 Placida Rd",
    "sg:city":"Englewood",
    "sg:classifiers":[
        {
            "category":"Real Estate",
            "subcategory":"Architect",
            "type":"Services"
        }
    ],
    "sg:phone":"+1 941 697 6474",
    "sg:postcode":"34224",
    "sg:province":"FL",
    "wof:name":"Rossa FV Architect & Planner",
    "wof:placetype":"venue"
},
  "geometry": {"coordinates":[-82.311774,26.89916],"type":"Point"}
}