{
  "type": "Feature",
  "properties": {
    "iso:country":"US",
    "sg:address":"2100 Tamiami Trl N",
    "sg:city":"Naples",
    "sg:classifiers":[
        {
            "category":"Banks & Credit Unions",
            "subcategory":"Investment Brokerage",
            "type":"Services"
        }
    ],
    "sg:phone":"+1 239 262 3333",
    "sg:postcode":"34102",
    "sg:province":"FL",
    "sg:tags":[
        "dealer"
    ],
    "wof:name":"Fifth Third Securities Inc",
    "wof:placetype":"venue"
},
  "geometry": {"coordinates":[-81.799601,26.173115],"type":"Point"}
}