{
  "type": "Feature",
  "properties": {
    "iso:country":"US",
    "sg:address":"3113 Old Farmhouse Dr",
    "sg:city":"Fort Myers",
    "sg:classifiers":[
        {
            "category":"Real Estate",
            "subcategory":"Real Estate Agent",
            "type":"Services"
        }
    ],
    "sg:phone":"+1 239 656 6654",
    "sg:postcode":"33917",
    "sg:province":"FL",
    "wof:name":"Henry Dilling",
    "wof:placetype":"venue"
},
  "geometry": {"coordinates":[-81.895673,26.70889],"type":"Point"}
}