{
  "type": "Feature",
  "properties": {
    "iso:country":"US",
    "sg:address":"3442 W Sunview Ln",
    "sg:city":"Dunnellon",
    "sg:classifiers":[
        {
            "category":"Building & Trades",
            "subcategory":"Electrical",
            "type":"Services"
        }
    ],
    "sg:phone":"+1 352 489 7734",
    "sg:postcode":"34433",
    "sg:province":"FL",
    "sg:tags":[
        "electric",
        "contractor"
    ],
    "wof:name":"Barr/None Electric",
    "wof:placetype":"venue"
},
  "geometry": {"coordinates":[-82.492964,29.035651],"type":"Point"}
}