{
  "type": "Feature",
  "properties": {
    "addr:full":"226 Clematis St West Palm Beach FL 33401",
    "addr:housenumber":"226",
    "addr:postcode":"33401",
    "addr:street":"Clematis St",
    "iso:country":"US",
    "sg:address":"226 Clematis St",
    "sg:city":"West Palm Beach",
    "sg:classifiers":[
        {
            "category":"Coffee & Tea",
            "type":"Food & Drink"
        }
    ],
    "sg:menulink":"http://www.allmenus.com/fl/west-palm-beach/116841-starbucks-coffee/menu/",
    "sg:phone":"+1 561 655 9933",
    "sg:postcode":"33401",
    "sg:province":"FL",
    "sg:tags":[
        "american"
    ],
    "wof:name":"Starbucks Coffee",
    "wof:placetype":"venue"
},
  "geometry": {"coordinates":[-80.051517,26.713312],"type":"Point"}
}