{
  "type": "Feature",
  "properties": {
    "iso:country":"US",
    "sg:address":"1138 Milan Ave",
    "sg:city":"Miami",
    "sg:classifiers":[
        {
            "category":"Building & Trades",
            "subcategory":"Plumbing",
            "type":"Services"
        }
    ],
    "sg:phone":"+1 305 441 1318",
    "sg:postcode":"33134",
    "sg:province":"FL",
    "sg:tags":[
        "plumbing",
        "repair",
        "contractor"
    ],
    "wof:name":"Fernando Alicot Inc",
    "wof:placetype":"venue"
},
  "geometry": {"coordinates":[-80.277957,25.756917],"type":"Point"}
}