{
  "type": "Feature",
  "properties": {
    "iso:country":"US",
    "sg:address":"506 Edgewater Dr",
    "sg:city":"Pensacola",
    "sg:classifiers":[
        {
            "category":"Building & Trades",
            "subcategory":"Construction",
            "type":"Services"
        }
    ],
    "sg:phone":"+1 850 455 2013",
    "sg:postcode":"32507",
    "sg:province":"FL",
    "sg:tags":[
        "contractor"
    ],
    "wof:name":"Raincarrier Inc",
    "wof:placetype":"venue"
},
  "geometry": {"coordinates":[-87.27261,30.401216],"type":"Point"}
}