{
  "type": "Feature",
  "properties": {
    "addr:full":"14269 83rd Ln N Loxahatchee FL 33470",
    "addr:housenumber":"14269",
    "addr:postcode":"33470",
    "addr:street":"83Rd Ln N",
    "iso:country":"US",
    "sg:address":"14269 83rd Ln N",
    "sg:city":"Loxahatchee",
    "sg:classifiers":[
        {
            "category":"Retail",
            "subcategory":"Auto Repair",
            "type":"Services"
        }
    ],
    "sg:phone":"+1 561 644 1286",
    "sg:postcode":"33470",
    "sg:province":"FL",
    "sg:tags":[
        "repairing",
        "automobile"
    ],
    "wof:name":"Len's Mobile Auto Repair",
    "wof:placetype":"venue"
},
  "geometry": {"coordinates":[-80.265463,26.800806],"type":"Point"}
}