{
  "type": "Feature",
  "properties": {
    "iso:country":"US",
    "sg:address":"230 Sandyhook Ln",
    "sg:city":"De Land",
    "sg:classifiers":[
        {
            "category":"Shopping",
            "subcategory":"Bicycles & Sporting Goods",
            "type":"Retail Goods"
        }
    ],
    "sg:phone":"+1 386 738 5826",
    "sg:postcode":"32724",
    "sg:province":"FL",
    "wof:name":"Western Shooters Emporium of",
    "wof:placetype":"venue"
},
  "geometry": {"coordinates":[-81.315808,29.083125],"type":"Point"}
}