{
  "type": "Feature",
  "properties": {
    "iso:country":"US",
    "sg:address":"15275 Collier Blvd",
    "sg:city":"Naples",
    "sg:classifiers":[
        {
            "category":"Building & Trades",
            "subcategory":"Construction",
            "type":"Services"
        }
    ],
    "sg:phone":"+1 239 289 0330",
    "sg:postcode":"34119",
    "sg:province":"FL",
    "sg:tags":[
        "remodeling"
    ],
    "wof:name":"Dreamworks Cnstr & Rmdlg LLC",
    "wof:placetype":"venue"
},
  "geometry": {"coordinates":[-81.689184,26.267898],"type":"Point"}
}