{
  "type": "Feature",
  "properties": {
    "iso:country":"US",
    "sg:address":"15919 Brenda St",
    "sg:city":"Hudson",
    "sg:classifiers":[
        {
            "category":"Professional",
            "type":"Services"
        }
    ],
    "sg:phone":"+1 727 863 9700",
    "sg:postcode":"34667",
    "sg:province":"FL",
    "sg:tags":[
        "establishment"
    ],
    "wof:name":"West Florida Docks",
    "wof:placetype":"venue"
},
  "geometry": {"coordinates":[-82.652744,28.386648],"type":"Point"}
}