{
  "type": "Feature",
  "properties": {
    "iso:country":"US",
    "sg:address":"120 Petty Cir",
    "sg:city":"Titusville",
    "sg:classifiers":[
        {
            "category":"Building & Trades",
            "subcategory":"Landscaping Services",
            "type":"Services"
        }
    ],
    "sg:phone":"+1 321 268 2459",
    "sg:postcode":"32796",
    "sg:province":"FL",
    "sg:tags":[
        "sod",
        "sodding"
    ],
    "wof:name":"Merritt Island Sod & Landscpg",
    "wof:placetype":"venue"
},
  "geometry": {"coordinates":[-80.822213,28.616411],"type":"Point"}
}