{
  "type": "Feature",
  "properties": {
    "addr:full":"311 Lake Proctor Ct Geneva FL 32732",
    "addr:housenumber":"311",
    "addr:postcode":"32732",
    "addr:street":"Lake Proctor Ct",
    "iso:country":"US",
    "sg:address":"311 Lake Proctor Ct",
    "sg:city":"Geneva",
    "sg:classifiers":[
        {
            "category":"Building & Trades",
            "subcategory":"Construction",
            "type":"Services"
        }
    ],
    "sg:phone":"+1 407 349 3831",
    "sg:postcode":"32732",
    "sg:province":"FL",
    "sg:tags":[
        "development",
        "cite"
    ],
    "wof:name":"George Griffin & Sons Inc",
    "wof:placetype":"venue"
},
  "geometry": {"coordinates":[-81.10580400000001,28.726915],"type":"Point"}
}