{
  "type": "Feature",
  "properties": {
    "addr:full":"331 Virginia Ave Orange City FL 32750",
    "addr:housenumber":"331",
    "addr:postcode":"32750",
    "addr:street":"Virginia Ave",
    "iso:country":"US",
    "sg:address":"331 Virginia Ave",
    "sg:city":"Orange City",
    "sg:classifiers":[
        {
            "category":"Building & Trades",
            "subcategory":"Electrical",
            "type":"Services"
        }
    ],
    "sg:phone":"+1 386 775 3303",
    "sg:postcode":"32750",
    "sg:province":"FL",
    "sg:tags":[
        "electrical",
        "contractor"
    ],
    "wof:name":"Lee Sarver Electric",
    "wof:placetype":"venue"
},
  "geometry": {"coordinates":[-81.38194799999999,28.688496],"type":"Point"}
}