{
  "type": "Feature",
  "properties": {
    "addr:full":"15450 SW 75th Circle Ln Miami FL 33193",
    "addr:housenumber":"15450",
    "addr:postcode":"33193",
    "addr:street":"Sw 75Th Circle Ln",
    "iso:country":"US",
    "sg:address":"15450 SW 75th Circle Ln",
    "sg:city":"Miami",
    "sg:classifiers":[
        {
            "category":"Building & Trades",
            "subcategory":"Landscaping Services",
            "type":"Services"
        }
    ],
    "sg:phone":"+1 305 383 3518",
    "sg:postcode":"33193",
    "sg:province":"FL",
    "sg:tags":[
        "lawn",
        "maintenance",
        "grounds"
    ],
    "wof:name":"Genaro Martinez Lawn Svc",
    "wof:placetype":"venue"
},
  "geometry": {"coordinates":[-80.443242,25.695629],"type":"Point"}
}