{
  "type": "Feature",
  "properties": {
    "iso:country":"US",
    "sg:address":"3020 Waterfield Ln",
    "sg:city":"Lakeland",
    "sg:classifiers":[
        {
            "category":"Wholesale",
            "subcategory":"Vending Machines",
            "type":"Manufacturing & Wholesale Goods"
        }
    ],
    "sg:phone":"+1 863 665 3152",
    "sg:postcode":"33803",
    "sg:province":"FL",
    "sg:tags":[
        "machines-parts",
        "merchandise",
        "supply"
    ],
    "wof:name":"Canteen Fl",
    "wof:placetype":"venue"
},
  "geometry": {"coordinates":[-81.898568,28.000373],"type":"Point"}
}