{
  "type": "Feature",
  "properties": {
    "addr:full":"3942 Co Rd 315A Green Cove Springs FL 32043",
    "addr:housenumber":"3942;315a",
    "addr:postcode":"32043",
    "addr:street":"Co Rd",
    "iso:country":"US",
    "sg:address":"3942 Co Rd 315A",
    "sg:city":"Green Cove Springs",
    "sg:classifiers":[
        {
            "category":"Shopping",
            "subcategory":"Gifts & Souvenirs",
            "type":"Retail Goods"
        }
    ],
    "sg:phone":"+1 904 284 9731",
    "sg:postcode":"32043",
    "sg:province":"FL",
    "wof:name":"Samuels Fine Gifts",
    "wof:placetype":"venue"
},
  "geometry": {"coordinates":[-81.718654,29.986416],"type":"Point"}
}