{
  "type": "Feature",
  "properties": {
    "iso:country":"US",
    "sg:address":"291 NE Hwy 41",
    "sg:city":"Williston",
    "sg:classifiers":[
        {
            "category":"Retail",
            "subcategory":"Repair Shop",
            "type":"Services"
        }
    ],
    "sg:phone":"+1 352 528 6684",
    "sg:postcode":"32696",
    "sg:province":"FL",
    "sg:tags":[
        "scooter",
        "motorcycle",
        "motor"
    ],
    "wof:name":"Midnight Cycle",
    "wof:placetype":"venue"
},
  "geometry": {"coordinates":[-82.45511999999999,29.33223],"type":"Point"}
}