{
  "type": "Feature",
  "properties": {
    "addr:full":"3326 Parazine St Pensacola FL 32514",
    "addr:housenumber":"3326",
    "addr:postcode":"32514",
    "addr:street":"Parazine St",
    "iso:country":"US",
    "sg:address":"3326 Parazine St",
    "sg:city":"Pensacola",
    "sg:classifiers":[
        {
            "category":"Building & Trades",
            "subcategory":"Landscaping Services",
            "type":"Services"
        }
    ],
    "sg:phone":"+1 850 479 4326",
    "sg:postcode":"32514",
    "sg:province":"FL",
    "wof:name":"Palms Plus Landscaping",
    "wof:placetype":"venue"
},
  "geometry": {"coordinates":[-87.194351,30.514384],"type":"Point"}
}