{
  "type": "Feature",
  "properties": {
    "iso:country":"US",
    "sg:address":"1660 W 42nd St",
    "sg:city":"Hialeah",
    "sg:classifiers":[
        {
            "category":"Retail",
            "subcategory":"Auto Repair",
            "type":"Services"
        }
    ],
    "sg:phone":"+1 305 827 6015",
    "sg:postcode":"33012",
    "sg:province":"FL",
    "sg:tags":[
        "automotive",
        "general"
    ],
    "wof:name":"Marreros Auto Repair Corp",
    "wof:placetype":"venue"
},
  "geometry": {"coordinates":[-80.31578,25.859662],"type":"Point"}
}