{
  "type": "Feature",
  "properties": {
    "addr:full":"179 W Airport Blvd Pensacola FL 32505",
    "addr:housenumber":"179",
    "addr:postcode":"32505",
    "addr:street":"W Airport Blvd",
    "iso:country":"US",
    "sg:address":"179 W Airport Blvd",
    "sg:city":"Pensacola",
    "sg:classifiers":[
        {
            "category":"Retail",
            "subcategory":"Auto Repair",
            "type":"Services"
        }
    ],
    "sg:phone":"+1 850 484 9776",
    "sg:postcode":"32505",
    "sg:province":"FL",
    "sg:tags":[
        "automobile",
        "glass",
        "replacement"
    ],
    "wof:name":"Guardian Auto Glass",
    "wof:placetype":"venue"
},
  "geometry": {"coordinates":[-87.25214099999999,30.472361],"type":"Point"}
}