{
  "type": "Feature",
  "properties": {
    "addr:full":"2184 James Dr Saint Cloud FL 34771",
    "addr:housenumber":"2184",
    "addr:postcode":"34771",
    "addr:street":"James Dr",
    "iso:country":"US",
    "sg:address":"2184 James Dr",
    "sg:city":"Saint Cloud",
    "sg:classifiers":[
        {
            "category":"Building & Trades",
            "subcategory":"Construction",
            "type":"Services"
        }
    ],
    "sg:phone":"+1 407 892 3913",
    "sg:postcode":"34771",
    "sg:province":"FL",
    "sg:tags":[
        "house"
    ],
    "wof:name":"Walter Dunn",
    "wof:placetype":"venue"
},
  "geometry": {"coordinates":[-81.206368,28.238635],"type":"Point"}
}