{
  "type": "Feature",
  "properties": {
    "iso:country":"US",
    "sg:address":"1474 W 84th St",
    "sg:city":"Hialeah",
    "sg:classifiers":[
        {
            "category":"Professional",
            "subcategory":"Lawyer & Legal Services",
            "type":"Services"
        }
    ],
    "sg:phone":"+1 305 823 1401",
    "sg:postcode":"33014",
    "sg:province":"FL",
    "sg:tags":[
        "attorney"
    ],
    "wof:name":"L Michael Osman",
    "wof:placetype":"venue"
},
  "geometry": {"coordinates":[-80.313469,25.898492],"type":"Point"}
}