{
  "type": "Feature",
  "properties": {
    "iso:country":"US",
    "sg:address":"313 5th St",
    "sg:city":"West Palm Beach",
    "sg:classifiers":[
        {
            "category":"Building & Trades",
            "subcategory":"Construction",
            "type":"Services"
        }
    ],
    "sg:phone":"+1 561 820 1400",
    "sg:postcode":"33401",
    "sg:province":"FL",
    "sg:tags":[
        "new",
        "general",
        "renovation",
        "contractor"
    ],
    "wof:name":"Davis General Contracting Corp",
    "wof:placetype":"venue"
},
  "geometry": {"coordinates":[-80.053236,26.717993],"type":"Point"}
}