{
  "type": "Feature",
  "properties": {
    "iso:country":"US",
    "sg:address":"400 W Industrial Ave",
    "sg:city":"Boynton Beach",
    "sg:classifiers":[
        {
            "category":"Retail",
            "subcategory":"Auto Repair",
            "type":"Services"
        }
    ],
    "sg:phone":"+1 561 736 1007",
    "sg:postcode":"33426",
    "sg:province":"FL",
    "sg:tags":[
        "body",
        "shop",
        "automobile",
        "paint",
        "automotive",
        "painting"
    ],
    "wof:name":"Precision Auto Body Works Inc",
    "wof:placetype":"venue"
},
  "geometry": {"coordinates":[-80.076432,26.537428],"type":"Point"}
}