{
  "type": "Feature",
  "properties": {
    "iso:country":"US",
    "sg:address":"35 Almeria Ave",
    "sg:city":"Coral Gables",
    "sg:classifiers":[
        {
            "category":"Professional",
            "subcategory":"Lawyer & Legal Services",
            "type":"Services"
        }
    ],
    "sg:phone":"+1 305 461 9223",
    "sg:postcode":"33134",
    "sg:province":"FL",
    "wof:name":"Arriola Velez Maria C Atty",
    "wof:placetype":"venue"
},
  "geometry": {"coordinates":[-80.25569900000001,25.7472],"type":"Point"}
}