{
  "type": "Feature",
  "properties": {
    "iso:country":"US",
    "sg:address":"9425 SW 80th St",
    "sg:city":"Miami",
    "sg:classifiers":[
        {
            "category":"Autos & Motor Vehicles",
            "subcategory":"Auto Supplies",
            "type":"Retail Goods"
        }
    ],
    "sg:phone":"+1 305 387 4365",
    "sg:postcode":"33173",
    "sg:province":"FL",
    "sg:tags":[
        "automobile",
        "alarm"
    ],
    "sg:website":"www.autoalarmspecialists.com",
    "wof:name":"Auto Alarm Spec",
    "wof:placetype":"venue"
},
  "geometry": {"coordinates":[-80.34670699999999,25.69476],"type":"Point"}
}