{
  "type": "Feature",
  "properties": {
    "iso:country":"US",
    "sg:address":"9541 April Rd",
    "sg:city":"Miami",
    "sg:classifiers":[
        {
            "category":"Building & Trades",
            "subcategory":"Landscaping Services",
            "type":"Services"
        }
    ],
    "sg:phone":"+1 305 235 5693",
    "sg:postcode":"33157",
    "sg:province":"FL",
    "wof:name":"Lawns By George Maintenance Co",
    "wof:placetype":"venue"
},
  "geometry": {"coordinates":[-80.34766399999999,25.585609],"type":"Point"}
}