{
  "type": "Feature",
  "properties": {
    "iso:country":"US",
    "sg:address":"651 Fort Smith Blvd",
    "sg:city":"Deltona",
    "sg:classifiers":[
        {
            "category":"Personal",
            "subcategory":"Beauty Salon",
            "type":"Services"
        }
    ],
    "sg:phone":"+1 386 748 6989",
    "sg:postcode":"32738",
    "sg:province":"FL",
    "wof:name":"Shower Of Blessings Event",
    "wof:placetype":"venue"
},
  "geometry": {"coordinates":[-81.203987,28.879129],"type":"Point"}
}