{
  "type": "Feature",
  "properties": {
    "iso:country":"US",
    "sg:address":"321 S Missouri Ave",
    "sg:city":"Clearwater",
    "sg:classifiers":[
        {
            "category":"Professional",
            "subcategory":"Management & Consulting",
            "type":"Services"
        }
    ],
    "sg:phone":"+1 727 461 4901",
    "sg:postcode":"33756",
    "sg:province":"FL",
    "sg:tags":[
        "consultant",
        "broker"
    ],
    "wof:name":"Art Glass Studios & Co Inc",
    "wof:placetype":"venue"
},
  "geometry": {"coordinates":[-82.787544,27.962467],"type":"Point"}
}