{
  "type": "Feature",
  "properties": {
    "iso:country":"US",
    "sg:address":"4370 Mount Vernon Ave",
    "sg:city":"Titusville",
    "sg:classifiers":[
        {
            "category":"Professional",
            "subcategory":"Business Services",
            "type":"Services"
        }
    ],
    "sg:phone":"+1 321 268 9988",
    "sg:postcode":"32780",
    "sg:province":"FL",
    "wof:name":"Flamingo Express of Titusville",
    "wof:placetype":"venue"
},
  "geometry": {"coordinates":[-80.799476,28.561267],"type":"Point"}
}