{
  "type": "Feature",
  "properties": {
    "iso:country":"US",
    "sg:address":"1 S Front St",
    "sg:city":"Fernandina Beach",
    "sg:classifiers":[
        {
            "category":"Travel",
            "subcategory":"Travel Agent",
            "type":"Entertainment"
        }
    ],
    "sg:phone":"+1 904 261 9972",
    "sg:postcode":"32034",
    "sg:province":"FL",
    "sg:tags":[
        "tours",
        "promoter"
    ],
    "wof:name":"Amelia River Cruises & Charter",
    "wof:placetype":"venue"
},
  "geometry": {"coordinates":[-81.46486899999999,30.671419],"type":"Point"}
}