{
  "type": "Feature",
  "properties": {
    "iso:country":"US",
    "sg:address":"7144 SW 47th St",
    "sg:city":"Miami",
    "sg:classifiers":[
        {
            "category":"Professional",
            "type":"Services"
        }
    ],
    "sg:phone":"+1 305 667 3212",
    "sg:postcode":"33155",
    "sg:province":"FL",
    "sg:tags":[
        "establishment"
    ],
    "wof:name":"Fortune Diversified",
    "wof:placetype":"venue"
},
  "geometry": {"coordinates":[-80.309122,25.726334],"type":"Point"}
}