{
  "type": "Feature",
  "properties": {
    "addr:full":"3940 Riverland Rd Fort Lauderdale FL 33312",
    "addr:housenumber":"3940",
    "addr:postcode":"33312",
    "addr:street":"Riverland Rd",
    "iso:country":"US",
    "sg:address":"3940 Riverland Rd",
    "sg:city":"Fort Lauderdale",
    "sg:classifiers":[
        {
            "category":"Food & Beverages",
            "subcategory":"Groceries & Convenience Stores",
            "type":"Retail Goods"
        }
    ],
    "sg:phone":"+1 954 584 7661",
    "sg:postcode":"33312",
    "sg:province":"FL",
    "wof:name":"Riverland Food Store Inc",
    "wof:placetype":"venue"
},
  "geometry": {"coordinates":[-80.19969500000001,26.091591],"type":"Point"}
}