{
  "type": "Feature",
  "properties": {
    "addr:full":"4646 Ashton Rd Sarasota FL 34233",
    "addr:housenumber":"4646",
    "addr:postcode":"34233",
    "addr:street":"Ashton Rd",
    "iso:country":"US",
    "sg:address":"4646 Ashton Rd",
    "sg:city":"Sarasota",
    "sg:classifiers":[
        {
            "category":"Shopping",
            "type":"Retail Goods"
        },
        {
            "category":"Manufacturing",
            "subcategory":"Electronics",
            "type":"Manufacturing & Wholesale Goods"
        }
    ],
    "sg:phone":"+1 941 342 0000",
    "sg:postcode":"34233",
    "sg:province":"FL",
    "sg:tags":[
        "sound",
        "system",
        "equipment",
        "video",
        "audio",
        "religious"
    ],
    "wof:name":"Worship Media Solutions LLC",
    "wof:placetype":"venue"
},
  "geometry": {"coordinates":[-82.479398,27.276494],"type":"Point"}
}