{
  "type": "Feature",
  "properties": {
    "addr:full":"879 E Prima Vista Blvd Port St Lucie FL 34952",
    "addr:housenumber":"879",
    "addr:postcode":"34952",
    "addr:street":"E Prima Vista Blvd",
    "iso:country":"US",
    "sg:address":"879 E Prima Vista Blvd",
    "sg:city":"Port St Lucie",
    "sg:classifiers":[
        {
            "category":"Retail",
            "subcategory":"Portrait Studio",
            "type":"Services"
        },
        {
            "category":"Professional",
            "subcategory":"Art Services",
            "type":"Services"
        }
    ],
    "sg:phone":"+1 772 344 4656",
    "sg:postcode":"34952",
    "sg:province":"FL",
    "sg:tags":[
        "photographer",
        "photography",
        "commercial"
    ],
    "wof:name":"Memories By Mark",
    "wof:placetype":"venue"
},
  "geometry": {"coordinates":[-80.3241,27.326124],"type":"Point"}
}