{
  "type": "Feature",
  "properties": {
    "iso:country":"US",
    "sg:address":"8201 W Sunrise Blvd",
    "sg:city":"Fort Lauderdale",
    "sg:classifiers":[
        {
            "category":"Restaurant",
            "type":"Food & Drink"
        },
        {
            "category":"Food & Beverages",
            "subcategory":"Bakery",
            "type":"Retail Goods"
        }
    ],
    "sg:phone":"+1 954 475 1511",
    "sg:postcode":"33322",
    "sg:province":"FL",
    "sg:tags":[
        "bagel",
        "eating"
    ],
    "wof:name":"Strathmore Bagels & Deli",
    "wof:placetype":"venue"
},
  "geometry": {"coordinates":[-80.25769200000001,26.148542],"type":"Point"}
}