{
  "type": "Feature",
  "properties": {
    "iso:country":"US",
    "sg:address":"10850 Quail Roost Dr",
    "sg:city":"Miami",
    "sg:classifiers":[
        {
            "category":"Organizations",
            "subcategory":"Religious Organization",
            "type":"Services"
        }
    ],
    "sg:phone":"+1 305 238 7333",
    "sg:postcode":"33157",
    "sg:province":"FL",
    "wof:name":"South Dade Christian Church",
    "wof:placetype":"venue"
},
  "geometry": {"coordinates":[-80.36640199999999,25.5959],"type":"Point"}
}