{
  "type": "Feature",
  "properties": {
    "iso:country":"US",
    "sg:address":"1155 NE 126th St",
    "sg:city":"Miami",
    "sg:classifiers":[
        {
            "category":"Professional",
            "subcategory":"Management & Consulting",
            "type":"Services"
        }
    ],
    "sg:phone":"+1 305 895 0540",
    "sg:postcode":"33161",
    "sg:province":"FL",
    "wof:name":"Quality Financial Consultants",
    "wof:placetype":"venue"
},
  "geometry": {"coordinates":[-80.17540200000001,25.891649],"type":"Point"}
}