{
  "type": "Feature",
  "properties": {
    "iso:country":"US",
    "sg:address":"12355 Roseland Rd",
    "sg:city":"Sebastian",
    "sg:classifiers":[
        {
            "category":"Retail",
            "subcategory":"Veterinary Services",
            "type":"Services"
        }
    ],
    "sg:phone":"+1 772 589 1970",
    "sg:postcode":"32958",
    "sg:province":"FL",
    "sg:tags":[
        "veterinarian",
        "specialty"
    ],
    "wof:name":"Roseland Equine Inc",
    "wof:placetype":"venue"
},
  "geometry": {"coordinates":[-80.50424,27.818967],"type":"Point"}
}