{
  "type": "Feature",
  "properties": {
    "addr:full":"8010 NW 154th St Hialeah FL 33016",
    "addr:housenumber":"8010",
    "addr:postcode":"33016",
    "addr:street":"Nw 154Th St",
    "iso:country":"US",
    "sg:address":"8010 NW 154th St",
    "sg:city":"Hialeah",
    "sg:classifiers":[
        {
            "category":"Real Estate",
            "subcategory":"Real Estate Services",
            "type":"Services"
        }
    ],
    "sg:phone":"+1 305 556 1111",
    "sg:postcode":"33016",
    "sg:province":"FL",
    "sg:tags":[
        "management",
        "property"
    ],
    "wof:name":"Real Estate Teammates",
    "wof:placetype":"venue"
},
  "geometry": {"coordinates":[-80.330597,25.9133],"type":"Point"}
}