{
  "type": "Feature",
  "properties": {
    "addr:full":"1381 Market Cir Port Charlotte FL 33953",
    "addr:housenumber":"1381",
    "addr:postcode":"33953",
    "addr:street":"Market Cir",
    "iso:country":"US",
    "sg:address":"1381 Market Cir",
    "sg:city":"Port Charlotte",
    "sg:classifiers":[
        {
            "category":"Freight",
            "type":"Transportation"
        }
    ],
    "sg:phone":"+1 941 624 2250",
    "sg:postcode":"33953",
    "sg:province":"FL",
    "sg:tags":[
        "commercial",
        "storage"
    ],
    "wof:name":"Murdock Self Storage",
    "wof:placetype":"venue"
},
  "geometry": {"coordinates":[-82.154065,27.011534],"type":"Point"}
}