{
  "type": "Feature",
  "properties": {
    "addr:full":"4614 Taray Ln Holiday FL 34690",
    "addr:housenumber":"4614",
    "addr:postcode":"34690",
    "addr:street":"Taray Ln",
    "iso:country":"US",
    "sg:address":"4614 Taray Ln",
    "sg:city":"Holiday",
    "sg:classifiers":[
        {
            "category":"Shopping",
            "subcategory":"Catalog Store",
            "type":"Retail Goods"
        }
    ],
    "sg:phone":"+1 727 938 7749",
    "sg:postcode":"34690",
    "sg:province":"FL",
    "sg:tags":[
        "mail",
        "house"
    ],
    "wof:name":"Trinkets N Treasures",
    "wof:placetype":"venue"
},
  "geometry": {"coordinates":[-82.737043,28.196381],"type":"Point"}
}