{
  "type": "Feature",
  "properties": {
    "addr:full":"6002 S Dale Mabry Hwy Tampa FL 33611",
    "addr:housenumber":"6002",
    "addr:postcode":"33611",
    "addr:street":"S Dale Mabry Hwy",
    "iso:country":"US",
    "sg:address":"6002 S Dale Mabry Hwy",
    "sg:city":"Tampa",
    "sg:classifiers":[
        {
            "category":"Food & Beverages",
            "subcategory":"Specialty",
            "type":"Retail Goods"
        }
    ],
    "sg:phone":"+1 813 832 4455",
    "sg:postcode":"33611",
    "sg:province":"FL",
    "sg:tags":[
        "product",
        "oriental"
    ],
    "wof:name":"Dobond Farmer Market Inc",
    "wof:placetype":"venue"
},
  "geometry": {"coordinates":[-82.50643599999999,27.880614],"type":"Point"}
}