{
  "type": "Feature",
  "properties": {
    "addr:full":"2840 E Irlo Bronson Memorial Hwy Kissimmee FL 34744",
    "addr:housenumber":"2840",
    "addr:postcode":"34744",
    "addr:street":"E Irlo Bronson Memorial Hwy",
    "iso:country":"US",
    "sg:address":"2840 E Irlo Bronson Memorial Hwy",
    "sg:city":"Kissimmee",
    "sg:classifiers":[
        {
            "category":"Retail",
            "subcategory":"Veterinary Services",
            "type":"Services"
        }
    ],
    "sg:phone":"+1 407 847 4472",
    "sg:postcode":"34744",
    "sg:province":"FL",
    "sg:tags":[
        "veterinarian"
    ],
    "wof:name":"Animal Clinic 192",
    "wof:placetype":"venue"
},
  "geometry": {"coordinates":[-81.328587,28.261347],"type":"Point"}
}