{
  "type": "Feature",
  "properties": {
    "addr:full":"642 N Wickham Rd Melbourne FL 32935",
    "addr:housenumber":"642",
    "addr:postcode":"32935",
    "addr:street":"N Wickham Rd",
    "iso:country":"US",
    "sg:address":"642 N Wickham Rd",
    "sg:city":"Melbourne",
    "sg:classifiers":[
        {
            "category":"Personal",
            "subcategory":"Beauty Salon",
            "type":"Services"
        },
        {
            "category":"Personal",
            "subcategory":"Nail Salon",
            "type":"Services"
        }
    ],
    "sg:phone":"+1 321 253 0904",
    "sg:postcode":"32935",
    "sg:province":"FL",
    "sg:tags":[
        "hair",
        "stylist"
    ],
    "wof:name":"Hair Matters",
    "wof:placetype":"venue"
},
  "geometry": {"coordinates":[-80.6726,28.117228],"type":"Point"}
}