{
  "type": "Feature",
  "properties": {
    "addr:full":"9160 Bonita Beach Rd Bonita Springs FL 34135",
    "addr:housenumber":"9160",
    "addr:postcode":"34135",
    "addr:street":"Bonita Beach Rd",
    "iso:country":"US",
    "sg:address":"9160 Bonita Beach Rd",
    "sg:city":"Bonita Springs",
    "sg:classifiers":[
        {
            "category":"Health Services",
            "subcategory":"Doctor",
            "type":"Services"
        }
    ],
    "sg:phone":"+1 239 992 0555",
    "sg:postcode":"34135",
    "sg:province":"FL",
    "sg:tags":[
        "medical"
    ],
    "wof:name":"Bonita Healthcare Center",
    "wof:placetype":"venue"
},
  "geometry": {"coordinates":[-81.799908,26.330661],"type":"Point"}
}