{
  "type": "Feature",
  "properties": {
    "iso:country":"US",
    "sg:address":"1199 N Lombardo Ave",
    "sg:city":"Lecanto",
    "sg:classifiers":[
        {
            "category":"Building & Trades",
            "subcategory":"Construction",
            "type":"Services"
        }
    ],
    "sg:phone":"+1 352 746 4039",
    "sg:postcode":"34461",
    "sg:province":"FL",
    "sg:tags":[
        "roofing",
        "contractor"
    ],
    "wof:name":"James N Robertson",
    "wof:placetype":"venue"
},
  "geometry": {"coordinates":[-82.474846,28.881601],"type":"Point"}
}