{
  "type": "Feature",
  "properties": {
    "addr:full":"3165 Phillips Hwy Jacksonville FL 32207",
    "addr:housenumber":"3165",
    "addr:postcode":"32207",
    "addr:street":"Phillips Hwy",
    "iso:country":"US",
    "sg:address":"3165 Phillips Hwy",
    "sg:city":"Jacksonville",
    "sg:classifiers":[
        {
            "category":"Restaurant",
            "type":"Food & Drink"
        }
    ],
    "sg:phone":"+1 904 398 6193",
    "sg:postcode":"32207",
    "sg:province":"FL",
    "sg:tags":[
        "eating"
    ],
    "wof:name":"JRS Sandwichshop",
    "wof:placetype":"venue"
},
  "geometry": {"coordinates":[-81.640356,30.296824],"type":"Point"}
}