{
  "type": "Feature",
  "properties": {
    "iso:country":"US",
    "sg:address":"1209 SE 26th St",
    "sg:city":"Cape Coral",
    "sg:classifiers":[
        {
            "category":"Banks & Credit Unions",
            "subcategory":"Bank",
            "type":"Services"
        }
    ],
    "sg:phone":"+1 239 458 3507",
    "sg:postcode":"33904",
    "sg:province":"FL",
    "sg:tags":[
        "mortgage"
    ],
    "wof:name":"A2z Mortgage Processing Inc",
    "wof:placetype":"venue"
},
  "geometry": {"coordinates":[-81.94708,26.603988],"type":"Point"}
}