{
  "type": "Feature",
  "properties": {
    "iso:country":"US",
    "sg:address":"2308 Larsen Rd",
    "sg:city":"Jacksonville",
    "sg:classifiers":[
        {
            "category":"Home & Garden",
            "subcategory":"Carpets & Floor Coverings",
            "type":"Retail Goods"
        }
    ],
    "sg:phone":"+1 904 737 8988",
    "sg:postcode":"32207",
    "sg:province":"FL",
    "wof:name":"Professional Floors",
    "wof:placetype":"venue"
},
  "geometry": {"coordinates":[-81.635606,30.275426],"type":"Point"}
}