{
  "type": "Feature",
  "properties": {
    "addr:full":"1121 NE 1st Ave Pompano Beach FL 33060",
    "addr:housenumber":"1121",
    "addr:postcode":"33060",
    "addr:street":"Ne 1St Ave",
    "iso:country":"US",
    "sg:address":"1121 NE 1st Ave",
    "sg:city":"Pompano Beach",
    "sg:classifiers":[
        {
            "category":"Wholesale",
            "subcategory":"Machinery & Supplies",
            "type":"Manufacturing & Wholesale Goods"
        }
    ],
    "sg:phone":"+1 954 785 6585",
    "sg:postcode":"33060",
    "sg:province":"FL",
    "sg:tags":[
        "truck"
    ],
    "wof:name":"South Florida Trucks",
    "wof:placetype":"venue"
},
  "geometry": {"coordinates":[-80.122162,26.241312],"type":"Point"}
}