{
  "type": "Feature",
  "properties": {
    "iso:country":"US",
    "sg:address":"16005 E Hwy 40",
    "sg:city":"Silver Springs",
    "sg:classifiers":[
        {
            "category":"Shopping",
            "subcategory":"Gifts & Souvenirs",
            "type":"Retail Goods"
        }
    ],
    "sg:phone":"+1 352 625 7773",
    "sg:postcode":"34488",
    "sg:province":"FL",
    "sg:tags":[
        "party",
        "supply"
    ],
    "wof:name":"Saven Haven",
    "wof:placetype":"venue"
},
  "geometry": {"coordinates":[-81.89039699999999,29.183196],"type":"Point"}
}