{
  "type": "Feature",
  "properties": {
    "iso:country":"US",
    "sg:address":"1648 Alligator Dr",
    "sg:city":"Panacea",
    "sg:classifiers":[
        {
            "category":"Government",
            "subcategory":"Office",
            "type":"Public Place"
        }
    ],
    "sg:phone":"+1 850 349 2833",
    "sg:postcode":"32346",
    "sg:province":"FL",
    "sg:tags":[
        "federal",
        "security"
    ],
    "wof:name":"Coast Guard Auxiliary Inc",
    "wof:placetype":"venue"
},
  "geometry": {"coordinates":[-84.414621,29.903264],"type":"Point"}
}