{
  "type": "Feature",
  "properties": {
    "iso:country":"US",
    "sg:address":"1776 W 49th St",
    "sg:city":"Hialeah",
    "sg:classifiers":[
        {
            "category":"Education",
            "subcategory":"Junior College",
            "type":"Public Place"
        }
    ],
    "sg:phone":"+1 305 237 8710",
    "sg:postcode":"33012",
    "sg:province":"FL",
    "sg:tags":[
        "technical",
        "institute"
    ],
    "sg:website":"www.mdc.edu",
    "wof:name":"Miami-Dade Community College",
    "wof:placetype":"venue"
},
  "geometry": {"coordinates":[-80.318415,25.866507],"type":"Point"}
}