{
  "type": "Feature",
  "properties": {
    "addr:full":"1809 Smith Dr Titusville FL 32780",
    "addr:housenumber":"1809",
    "addr:postcode":"32780",
    "addr:street":"Smith Dr",
    "iso:country":"US",
    "sg:address":"1809 Smith Dr",
    "sg:city":"Titusville",
    "sg:classifiers":[
        {
            "category":"Building & Trades",
            "subcategory":"Construction",
            "type":"Services"
        }
    ],
    "sg:phone":"+1 321 268 4550",
    "sg:postcode":"32780",
    "sg:province":"FL",
    "sg:tags":[
        "house"
    ],
    "wof:name":"Top Shelf Construction",
    "wof:placetype":"venue"
},
  "geometry": {"coordinates":[-80.82340499999999,28.603078],"type":"Point"}
}