{
  "type": "Feature",
  "properties": {
    "iso:country":"US",
    "sg:address":"30 S Magnolia Ave",
    "sg:city":"Ocala",
    "sg:classifiers":[
        {
            "category":"Restaurant",
            "type":"Food & Drink"
        }
    ],
    "sg:menulink":"http://www.allmenus.com/fl/ocala/158114-renos-on-the-square/menu/",
    "sg:phone":"+1 352 402 0097",
    "sg:postcode":"34471",
    "sg:province":"FL",
    "sg:tags":[
        "new",
        "american"
    ],
    "wof:name":"Reno's On The Square",
    "wof:placetype":"venue"
},
  "geometry": {"coordinates":[-82.136944,29.186379],"type":"Point"}
}