{
  "type": "Feature",
  "properties": {
    "addr:full":"906 NW 10th St Boynton Beach FL 33426",
    "addr:housenumber":"906",
    "addr:postcode":"33426",
    "addr:street":"Nw 10Th St",
    "iso:country":"US",
    "sg:address":"906 NW 10th St",
    "sg:city":"Boynton Beach",
    "sg:classifiers":[
        {
            "category":"Building & Trades",
            "subcategory":"Pest Control",
            "type":"Services"
        }
    ],
    "sg:phone":"+1 561 735 0085",
    "sg:postcode":"33426",
    "sg:province":"FL",
    "wof:name":"Excellent Environmental Svcs",
    "wof:placetype":"venue"
},
  "geometry": {"coordinates":[-80.081425,26.537822],"type":"Point"}
}