{
  "type": "Feature",
  "properties": {
    "addr:full":"1321 NW 13th St Miami FL 33125",
    "addr:housenumber":"1321",
    "addr:postcode":"33125",
    "addr:street":"Nw 13Th St",
    "iso:country":"US",
    "sg:address":"1321 NW 13th St",
    "sg:city":"Miami",
    "sg:classifiers":[
        {
            "category":"Government",
            "subcategory":"Jail",
            "type":"Public Place"
        }
    ],
    "sg:phone":"+1 786 263 4100",
    "sg:postcode":"33125",
    "sg:province":"FL",
    "sg:tags":[
        "correctional",
        "institution"
    ],
    "wof:name":"Corrections Dept",
    "wof:placetype":"venue"
},
  "geometry": {"coordinates":[-80.216998,25.786353],"type":"Point"}
}