{
  "type": "Feature",
  "properties": {
    "addr:full":"5342 Moon Shadow Ln Greenacres FL 33463",
    "addr:housenumber":"5342",
    "addr:postcode":"33463",
    "addr:street":"Moon Shadow Ln",
    "iso:country":"US",
    "sg:address":"5342 Moon Shadow Ln",
    "sg:city":"Greenacres",
    "sg:classifiers":[
        {
            "category":"Arts & Performance",
            "subcategory":"Dance",
            "type":"Entertainment"
        }
    ],
    "sg:phone":"+1 561 868 5611",
    "sg:postcode":"33463",
    "sg:province":"FL",
    "sg:tags":[
        "instruction",
        "dancing"
    ],
    "wof:name":"Bailey Academy Of Dance Inc",
    "wof:placetype":"venue"
},
  "geometry": {"coordinates":[-80.128193,26.602679],"type":"Point"}
}