{
  "type": "Feature",
  "properties": {
    "addr:full":"1866 94th Dr Vero Beach FL 32966",
    "addr:housenumber":"1866",
    "addr:postcode":"32966",
    "addr:street":"94Th Dr",
    "iso:country":"US",
    "sg:address":"1866 94th Dr",
    "sg:city":"Vero Beach",
    "sg:classifiers":[
        {
            "category":"Shopping",
            "subcategory":"Clothing, Apparel, & Fashions",
            "type":"Retail Goods"
        }
    ],
    "sg:phone":"+1 772 794 7622",
    "sg:postcode":"32966",
    "sg:province":"FL",
    "wof:name":"Versace Co Store",
    "wof:placetype":"venue"
},
  "geometry": {"coordinates":[-80.524512,27.635386],"type":"Point"}
}