{
  "type": "Feature",
  "properties": {
    "iso:country":"US",
    "sg:address":"2731 Elsie Rd",
    "sg:city":"St Augustine",
    "sg:classifiers":[
        {
            "category":"Building & Trades",
            "subcategory":"Landscaping Services",
            "type":"Services"
        }
    ],
    "sg:phone":"+1 904 797 5472",
    "sg:postcode":"32086",
    "sg:province":"FL",
    "sg:tags":[
        "lawn",
        "maintenance",
        "grounds"
    ],
    "wof:name":"Robin Hall's Lawn Care",
    "wof:placetype":"venue"
},
  "geometry": {"coordinates":[-81.34751,29.844919],"type":"Point"}
}