{
  "type": "Feature",
  "properties": {
    "iso:country":"US",
    "sg:address":"5925 Benjamin Center Dr",
    "sg:city":"Tampa",
    "sg:classifiers":[
        {
            "category":"Restaurant",
            "type":"Food & Drink"
        }
    ],
    "sg:phone":"+1 813 882 4499",
    "sg:postcode":"33634",
    "sg:province":"FL",
    "wof:name":"Moxies Too Cafe & Deli",
    "wof:placetype":"venue"
},
  "geometry": {"coordinates":[-82.539903,28.006478],"type":"Point"}
}