{
  "type": "Feature",
  "properties": {
    "iso:country":"US",
    "sg:address":"2927 Hatteras Way",
    "sg:city":"Naples",
    "sg:classifiers":[
        {
            "category":"Home & Garden",
            "subcategory":"Building Materials",
            "type":"Retail Goods"
        }
    ],
    "sg:phone":"+1 239 593 0806",
    "sg:postcode":"34119",
    "sg:province":"FL",
    "sg:tags":[
        "windows"
    ],
    "wof:name":"Architectural Resources & Dsgn",
    "wof:placetype":"venue"
},
  "geometry": {"coordinates":[-81.709581,26.247543],"type":"Point"}
}