{
  "type": "Feature",
  "properties": {
    "addr:full":"26740 Pine Ave Bonita Springs FL 34135",
    "addr:housenumber":"26740",
    "addr:postcode":"34135",
    "addr:street":"Pine Ave",
    "iso:country":"US",
    "sg:address":"26740 Pine Ave",
    "sg:city":"Bonita Springs",
    "sg:classifiers":[
        {
            "category":"Recreation",
            "type":"Entertainment"
        }
    ],
    "sg:phone":"+1 239 992 2556",
    "sg:postcode":"34135",
    "sg:province":"FL",
    "sg:tags":[
        "executive",
        "parks"
    ],
    "wof:name":"Bonita Springs Recreation Ctr",
    "wof:placetype":"venue"
},
  "geometry": {"coordinates":[-81.783306,26.348952],"type":"Point"}
}