{
  "type": "Feature",
  "properties": {
    "iso:country":"US",
    "sg:address":"5016 Blanding Blvd",
    "sg:city":"Jacksonville",
    "sg:classifiers":[
        {
            "category":"Bars & Pubs",
            "type":"Food & Drink"
        }
    ],
    "sg:phone":"+1 904 777 6373",
    "sg:postcode":"32210",
    "sg:province":"FL",
    "sg:tags":[
        "club",
        "night"
    ],
    "wof:name":"Sampaguita Club & Cuisine",
    "wof:placetype":"venue"
},
  "geometry": {"coordinates":[-81.743144,30.251304],"type":"Point"}
}