{
  "type": "Feature",
  "properties": {
    "addr:full":"16121 NW 57th Ave Hialeah FL 33014",
    "addr:housenumber":"16121",
    "addr:postcode":"33014",
    "addr:street":"Nw 57Th Ave",
    "iso:country":"US",
    "sg:address":"16121 NW 57th Ave",
    "sg:city":"Hialeah",
    "sg:classifiers":[
        {
            "category":"Communications",
            "type":"Services"
        }
    ],
    "sg:phone":"+1 305 623 1929",
    "sg:postcode":"33014",
    "sg:province":"FL",
    "sg:tags":[
        "consultant"
    ],
    "wof:name":"T S I Communications",
    "wof:placetype":"venue"
},
  "geometry": {"coordinates":[-80.29291499999999,25.919646],"type":"Point"}
}