{
  "type": "Feature",
  "properties": {
    "addr:full":"365 3rd St NW Winter Haven FL 33881",
    "addr:housenumber":"365",
    "addr:postcode":"33881",
    "addr:street":"3Rd St Nw",
    "iso:country":"US",
    "sg:address":"365 3rd St NW",
    "sg:city":"Winter Haven",
    "sg:classifiers":[
        {
            "category":"Personal",
            "subcategory":"Beauty Salon",
            "type":"Services"
        }
    ],
    "sg:phone":"+1 863 293 5800",
    "sg:postcode":"33881",
    "sg:province":"FL",
    "wof:name":"Altered Ego Image Design",
    "wof:placetype":"venue"
},
  "geometry": {"coordinates":[-81.73027999999999,28.025668],"type":"Point"}
}