{
  "type": "Feature",
  "properties": {
    "addr:full":"700 Pleasantdale Dr Wildwood FL 34785",
    "addr:housenumber":"700",
    "addr:postcode":"34785",
    "addr:street":"Pleasantdale Dr",
    "iso:country":"US",
    "sg:address":"700 Pleasantdale Dr",
    "sg:city":"Wildwood",
    "sg:classifiers":[
        {
            "category":"Building & Trades",
            "subcategory":"Cleaning & Sanitation",
            "type":"Services"
        }
    ],
    "sg:phone":"+1 352 330 0240",
    "sg:postcode":"34785",
    "sg:province":"FL",
    "sg:tags":[
        "house"
    ],
    "wof:name":"Top To Bottom House Cleaning",
    "wof:placetype":"venue"
},
  "geometry": {"coordinates":[-82.028407,28.867204],"type":"Point"}
}