{
  "type": "Feature",
  "properties": {
    "addr:full":"240 Lakeview Ave Titusville FL 32796",
    "addr:housenumber":"240",
    "addr:postcode":"32796",
    "addr:street":"Lakeview Ave",
    "iso:country":"US",
    "sg:address":"240 Lakeview Ave",
    "sg:city":"Titusville",
    "sg:classifiers":[
        {
            "category":"Shopping",
            "subcategory":"Computers & Home Electronics",
            "type":"Retail Goods"
        }
    ],
    "sg:phone":"+1 321 783 8447",
    "sg:postcode":"32796",
    "sg:province":"FL",
    "sg:tags":[
        "equipment",
        "satellite",
        "system"
    ],
    "wof:name":"Gene Hereford Installation",
    "wof:placetype":"venue"
},
  "geometry": {"coordinates":[-80.857724,28.618108],"type":"Point"}
}