{
  "type": "Feature",
  "properties": {
    "iso:country":"US",
    "sg:address":"6400 Abisco Rd",
    "sg:city":"Cocoa",
    "sg:classifiers":[
        {
            "category":"Retail",
            "subcategory":"Repair Shop",
            "type":"Services"
        }
    ],
    "sg:phone":"+1 321 269 9616",
    "sg:postcode":"32927",
    "sg:province":"FL",
    "sg:tags":[
        "appliance"
    ],
    "wof:name":"Appliance Enterprises Inc",
    "wof:placetype":"venue"
},
  "geometry": {"coordinates":[-80.808543,28.470826],"type":"Point"}
}