{
  "type": "Feature",
  "properties": {
    "iso:country":"US",
    "sg:address":"5753 Bird Rd Ste B",
    "sg:city":"Miami",
    "sg:classifiers":[
        {
            "category":"Retail",
            "subcategory":"Veterinary Services",
            "type":"Services"
        }
    ],
    "sg:phone":"+1 305 661 6466",
    "sg:postcode":"33155",
    "sg:province":"FL",
    "sg:tags":[
        "veterinarian"
    ],
    "wof:name":"Red Bird Animal Clinic",
    "wof:placetype":"venue"
},
  "geometry": {"coordinates":[-80.288101,25.733999],"type":"Point"}
}