{
  "type": "Feature",
  "properties": {
    "iso:country":"US",
    "sg:address":"801 Lincoln Rd",
    "sg:city":"Miami Beach",
    "sg:classifiers":[
        {
            "category":"Food & Beverages",
            "subcategory":"Chocolate",
            "type":"Retail Goods"
        }
    ],
    "sg:postcode":"33119",
    "sg:province":"FL",
    "sg:tags":[
        "shop",
        "chocolatiers"
    ],
    "wof:name":"Ghiradelli Chocolate Company",
    "wof:placetype":"venue"
},
  "geometry": {"coordinates":[-80.136658,25.79055],"type":"Point"}
}