{
  "type": "Feature",
  "properties": {
    "iso:country":"US",
    "sg:address":"14690 SW 248th St",
    "sg:city":"Homestead",
    "sg:classifiers":[
        {
            "category":"Home & Garden",
            "subcategory":"Garden Supply",
            "type":"Retail Goods"
        }
    ],
    "sg:phone":"+1 305 257 3296",
    "sg:postcode":"33032",
    "sg:province":"FL",
    "wof:name":"All Green Landscape",
    "wof:placetype":"venue"
},
  "geometry": {"coordinates":[-80.42547500000001,25.536257],"type":"Point"}
}