{
  "type": "Feature",
  "properties": {
    "iso:country":"US",
    "sg:address":"5435 Balsam Ave",
    "sg:city":"Melbourne",
    "sg:classifiers":[
        {
            "category":"Real Estate",
            "subcategory":"Real Estate Agent",
            "type":"Services"
        }
    ],
    "sg:phone":"+1 321 223 1135",
    "sg:postcode":"32904",
    "sg:province":"FL",
    "sg:tags":[
        "inspection"
    ],
    "wof:name":"John Washburn Home Inspections",
    "wof:placetype":"venue"
},
  "geometry": {"coordinates":[-80.655924,28.086783],"type":"Point"}
}