{
  "type": "Feature",
  "properties": {
    "iso:country":"US",
    "sg:address":"295 SW 2nd St",
    "sg:city":"Boca Raton",
    "sg:classifiers":[
        {
            "category":"Building & Trades",
            "subcategory":"Plumbing",
            "type":"Services"
        }
    ],
    "sg:phone":"+1 561 362 1173",
    "sg:postcode":"33432",
    "sg:province":"FL",
    "sg:tags":[
        "conditioning",
        "air",
        "system",
        "contractor"
    ],
    "wof:name":"RNC Heating & Air Cond Inc",
    "wof:placetype":"venue"
},
  "geometry": {"coordinates":[-80.09002700000001,26.34782],"type":"Point"}
}