{
  "type": "Feature",
  "properties": {
    "iso:country":"US",
    "sg:address":"5200 Old Cheney Hwy",
    "sg:city":"Orlando",
    "sg:classifiers":[
        {
            "category":"Organizations",
            "subcategory":"Religious Organization",
            "type":"Services"
        }
    ],
    "sg:phone":"+1 407 273 4650",
    "sg:postcode":"32807",
    "sg:province":"FL",
    "sg:tags":[
        "church"
    ],
    "wof:name":"Primera Iglesia Bautista",
    "wof:placetype":"venue"
},
  "geometry": {"coordinates":[-81.31847399999999,28.558298],"type":"Point"}
}