{
  "type": "Feature",
  "properties": {
    "iso:country":"US",
    "sg:address":"1632 Bell Ave",
    "sg:city":"Port St Lucie",
    "sg:classifiers":[
        {
            "category":"Professional",
            "subcategory":"Business Services",
            "type":"Services"
        }
    ],
    "sg:phone":"+1 772 621 8926",
    "sg:postcode":"34982",
    "sg:province":"FL",
    "sg:tags":[
        "paging",
        "answering"
    ],
    "wof:name":"A Line Answering Svc",
    "wof:placetype":"venue"
},
  "geometry": {"coordinates":[-80.338533,27.39655],"type":"Point"}
}