{
  "type": "Feature",
  "properties": {
    "iso:country":"US",
    "sg:address":"1905 W Vine St",
    "sg:city":"Kissimmee",
    "sg:classifiers":[
        {
            "category":"Retail",
            "subcategory":"Laundry & Dry Cleaning",
            "type":"Services"
        }
    ],
    "sg:phone":"+1 407 518 0636",
    "sg:postcode":"34741",
    "sg:province":"FL",
    "wof:name":"Colonial Coin Laundry",
    "wof:placetype":"venue"
},
  "geometry": {"coordinates":[-81.42421299999999,28.304598],"type":"Point"}
}