{
  "type": "Feature",
  "properties": {
    "addr:full":"1760 NW 28th Ave Fort Lauderdale FL 33311",
    "addr:housenumber":"1760",
    "addr:postcode":"33311",
    "addr:street":"Nw 28Th Ave",
    "iso:country":"US",
    "sg:address":"1760 NW 28th Ave",
    "sg:city":"Fort Lauderdale",
    "sg:classifiers":[
        {
            "category":"Building & Trades",
            "subcategory":"Plumbing",
            "type":"Services"
        }
    ],
    "sg:phone":"+1 954 485 0806",
    "sg:postcode":"33311",
    "sg:province":"FL",
    "sg:tags":[
        "contractor"
    ],
    "wof:name":"Wins Plumbing Repair",
    "wof:placetype":"venue"
},
  "geometry": {"coordinates":[-80.18024,26.149194],"type":"Point"}
}