{
  "type": "Feature",
  "properties": {
    "addr:full":"1113 Abagail Dr Deltona FL 32725",
    "addr:housenumber":"1113",
    "addr:postcode":"32725",
    "addr:street":"Abagail Dr",
    "iso:country":"US",
    "sg:address":"1113 Abagail Dr",
    "sg:city":"Deltona",
    "sg:classifiers":[
        {
            "category":"Building & Trades",
            "subcategory":"Cleaning & Sanitation",
            "type":"Services"
        },
        {
            "category":"Home & Garden",
            "subcategory":"Carpets & Floor Coverings",
            "type":"Retail Goods"
        }
    ],
    "sg:phone":"+1 386 774 7441",
    "sg:postcode":"32725",
    "sg:province":"FL",
    "sg:tags":[
        "carpeting"
    ],
    "wof:name":"All Pro Carpet Cleaners",
    "wof:placetype":"venue"
},
  "geometry": {"coordinates":[-81.245481,28.886859],"type":"Point"}
}