{
  "type": "Feature",
  "properties": {
    "addr:full":"5870 Venisota Rd Venice FL 34293",
    "addr:housenumber":"5870",
    "addr:postcode":"34293",
    "addr:street":"Venisota Rd",
    "iso:country":"US",
    "sg:address":"5870 Venisota Rd",
    "sg:city":"Venice",
    "sg:classifiers":[
        {
            "category":"Professional",
            "subcategory":"Art Services",
            "type":"Services"
        }
    ],
    "sg:phone":"+1 941 375 8901",
    "sg:postcode":"34293",
    "sg:province":"FL",
    "sg:tags":[
        "designer",
        "display",
        "producer"
    ],
    "wof:name":"Creative Window Designs By Janis Inc",
    "wof:placetype":"venue"
},
  "geometry": {"coordinates":[-82.399933,27.02619],"type":"Point"}
}