{
  "type": "Feature",
  "properties": {
    "iso:country":"US",
    "sg:address":"522 McIntosh Rd",
    "sg:city":"Ormond Beach",
    "sg:classifiers":[
        {
            "category":"Building & Trades",
            "subcategory":"Landscaping Services",
            "type":"Services"
        }
    ],
    "sg:phone":"+1 386 676 7583",
    "sg:postcode":"32174",
    "sg:province":"FL",
    "sg:tags":[
        "lawn",
        "garden"
    ],
    "wof:name":"C & S Lawn Maintenance",
    "wof:placetype":"venue"
},
  "geometry": {"coordinates":[-81.066963,29.296502],"type":"Point"}
}