{
  "type": "Feature",
  "properties": {
    "iso:country":"US",
    "sg:address":"3724 SW 266th St",
    "sg:city":"Newberry",
    "sg:classifiers":[
        {
            "category":"Farming",
            "subcategory":"Orchard",
            "type":"Manufacturing & Wholesale Goods"
        },
        {
            "category":"Farming",
            "subcategory":"Farm",
            "type":"Manufacturing & Wholesale Goods"
        }
    ],
    "sg:phone":"+1 352 472 7257",
    "sg:postcode":"32669",
    "sg:province":"FL",
    "wof:name":"Wayne Bass Farms",
    "wof:placetype":"venue"
},
  "geometry": {"coordinates":[-82.62278999999999,29.613337],"type":"Point"}
}