{
  "type": "Feature",
  "properties": {
    "iso:country":"US",
    "sg:address":"3501 Jackson St",
    "sg:city":"Hollywood",
    "sg:classifiers":[
        {
            "category":"Professional",
            "subcategory":"Business Services",
            "type":"Services"
        }
    ],
    "sg:phone":"+1 954 322 8551",
    "sg:postcode":"33021",
    "sg:province":"FL",
    "wof:name":"Art Space",
    "wof:placetype":"venue"
},
  "geometry": {"coordinates":[-80.180905,26.007921],"type":"Point"}
}