{
  "type": "Feature",
  "properties": {
    "iso:country":"US",
    "sg:address":"2824 Conway Gardens Rd",
    "sg:city":"Orlando",
    "sg:classifiers":[
        {
            "category":"Recreation",
            "type":"Entertainment"
        }
    ],
    "sg:phone":"+1 407 856 7961",
    "sg:postcode":"32806",
    "sg:province":"FL",
    "sg:tags":[
        "guide"
    ],
    "sg:website":"www.gatorbass.com",
    "wof:name":"Gators Big Bass Guide Svc",
    "wof:placetype":"venue"
},
  "geometry": {"coordinates":[-81.339252,28.5072],"type":"Point"}
}