{
  "type": "Feature",
  "properties": {
    "iso:country":"US",
    "sg:address":"2225 Curry Ford Rd",
    "sg:city":"Orlando",
    "sg:classifiers":[
        {
            "category":"Personal",
            "subcategory":"Beauty Salon",
            "type":"Services"
        }
    ],
    "sg:phone":"+1 407 895 9933",
    "sg:postcode":"32806",
    "sg:province":"FL",
    "wof:name":"A Beautiful You",
    "wof:placetype":"venue"
},
  "geometry": {"coordinates":[-81.35293799999999,28.524163],"type":"Point"}
}