{
  "type": "Feature",
  "properties": {
    "iso:country":"US",
    "sg:address":"5466 Catts St",
    "sg:city":"Naples",
    "sg:classifiers":[
        {
            "category":"Building & Trades",
            "subcategory":"Cleaning & Sanitation",
            "type":"Services"
        }
    ],
    "sg:phone":"+1 239 732 0896",
    "sg:postcode":"34113",
    "sg:province":"FL",
    "sg:tags":[
        "janitor"
    ],
    "wof:name":"Tracy L Tribley Janitorial Svc",
    "wof:placetype":"venue"
},
  "geometry": {"coordinates":[-81.71951199999999,26.09048],"type":"Point"}
}