{
  "type": "Feature",
  "properties": {
    "addr:full":"44 Veterans Ave Brooksville FL 34601",
    "addr:housenumber":"44",
    "addr:postcode":"34601",
    "addr:street":"Veterans Ave",
    "iso:country":"US",
    "sg:address":"44 Veterans Ave",
    "sg:city":"Brooksville",
    "sg:classifiers":[
        {
            "category":"Health Services",
            "subcategory":"Doctor",
            "type":"Services"
        }
    ],
    "sg:phone":"+1 352 797 3500",
    "sg:postcode":"34601",
    "sg:province":"FL",
    "sg:tags":[
        "physician",
        "surgeon"
    ],
    "wof:name":"Dennis Gonzalez MD",
    "wof:placetype":"venue"
},
  "geometry": {"coordinates":[-82.399382,28.550099],"type":"Point"}
}