{
  "type": "Feature",
  "properties": {
    "addr:full":"263 Commercial Blvd Fort Lauderdale FL 33308",
    "addr:housenumber":"263",
    "addr:postcode":"33308",
    "addr:street":"Commercial Blvd",
    "iso:country":"US",
    "sg:address":"263 Commercial Blvd",
    "sg:city":"Fort Lauderdale",
    "sg:classifiers":[
        {
            "category":"Shopping",
            "type":"Retail Goods"
        }
    ],
    "sg:phone":"+1 954 267 9202",
    "sg:postcode":"33308",
    "sg:province":"FL",
    "sg:tags":[
        "picture",
        "frame",
        "merchandise"
    ],
    "wof:name":"Budget Framer",
    "wof:placetype":"venue"
},
  "geometry": {"coordinates":[-80.10229,26.189932],"type":"Point"}
}