{
  "type": "Feature",
  "properties": {
    "addr:full":"15331 Allen Way Fort Myers FL 33908",
    "addr:housenumber":"15331",
    "addr:postcode":"33908",
    "addr:street":"Allen Way",
    "iso:country":"US",
    "sg:address":"15331 Allen Way",
    "sg:city":"Fort Myers",
    "sg:classifiers":[
        {
            "category":"Travel",
            "subcategory":"Hotels & Motels",
            "type":"Entertainment"
        }
    ],
    "sg:phone":"+1 239 466 7925",
    "sg:postcode":"33908",
    "sg:province":"FL",
    "sg:tags":[
        "operation"
    ],
    "wof:name":"Resort Vacation Concepts Inc",
    "wof:placetype":"venue"
},
  "geometry": {"coordinates":[-81.96848199999999,26.516724],"type":"Point"}
}