{
  "type": "Feature",
  "properties": {
    "iso:country":"US",
    "sg:address":"2909 22nd Ave N",
    "sg:city":"Saint Petersburg",
    "sg:classifiers":[
        {
            "category":"Food & Beverages",
            "subcategory":"Specialty",
            "type":"Retail Goods"
        }
    ],
    "sg:phone":"+1 727 321 2400",
    "sg:postcode":"33713",
    "sg:province":"FL",
    "sg:tags":[
        "coffee"
    ],
    "wof:name":"Mazzaro Italian Market",
    "wof:placetype":"venue"
},
  "geometry": {"coordinates":[-82.675318,27.791966],"type":"Point"}
}