{
  "type": "Feature",
  "properties": {
    "iso:country":"US",
    "sg:address":"507 E Fort King St",
    "sg:city":"Ocala",
    "sg:classifiers":[
        {
            "category":"Shopping",
            "subcategory":"Used Merchandise",
            "type":"Retail Goods"
        },
        {
            "category":"Wholesale",
            "subcategory":"Durable Goods & Equipment",
            "type":"Manufacturing & Wholesale Goods"
        }
    ],
    "sg:phone":"+1 352 732 8880",
    "sg:postcode":"34471",
    "sg:province":"FL",
    "sg:tags":[
        "antique"
    ],
    "wof:name":"Occasional Shoppe Inc",
    "wof:placetype":"venue"
},
  "geometry": {"coordinates":[-82.133229,29.185549],"type":"Point"}
}