{
  "type": "Feature",
  "properties": {
    "addr:full":"4965 W Nine Mile Rd Pensacola FL 32526",
    "addr:housenumber":"4965",
    "addr:postcode":"32526",
    "addr:street":"W Nine Mile Rd",
    "iso:country":"US",
    "sg:address":"4965 W Nine Mile Rd",
    "sg:city":"Pensacola",
    "sg:classifiers":[
        {
            "category":"Building & Trades",
            "subcategory":"Construction",
            "type":"Services"
        },
        {
            "category":"Utilities",
            "type":"Services"
        }
    ],
    "sg:phone":"+1 850 944 0065",
    "sg:postcode":"32526",
    "sg:province":"FL",
    "sg:tags":[
        "control",
        "testing",
        "water",
        "sanitary",
        "laboratory",
        "pollution"
    ],
    "wof:name":"Professional Certified Svcs",
    "wof:placetype":"venue"
},
  "geometry": {"coordinates":[-87.36776500000001,30.535267],"type":"Point"}
}