{
  "type": "Feature",
  "properties": {
    "iso:country":"US",
    "sg:address":"15865 Assembly Loop",
    "sg:city":"Jupiter",
    "sg:classifiers":[
        {
            "category":"Building & Trades",
            "subcategory":"Construction",
            "type":"Services"
        }
    ],
    "sg:phone":"+1 561 624 1108",
    "sg:postcode":"33478",
    "sg:province":"FL",
    "sg:tags":[
        "excavating",
        "contractor"
    ],
    "wof:name":"Russell Trucking Inc",
    "wof:placetype":"venue"
},
  "geometry": {"coordinates":[-80.28229899999999,26.909522],"type":"Point"}
}