{
  "type": "Feature",
  "properties": {
    "addr:full":"326 W Central Ave Winter Haven FL 33880",
    "addr:housenumber":"326",
    "addr:postcode":"33880",
    "addr:street":"W Central Ave",
    "iso:country":"US",
    "sg:address":"326 W Central Ave",
    "sg:city":"Winter Haven",
    "sg:classifiers":[
        {
            "category":"Shopping",
            "subcategory":"Hobbies, Toys, & Games",
            "type":"Retail Goods"
        }
    ],
    "sg:phone":"+1 863 292 0810",
    "sg:postcode":"33880",
    "sg:province":"FL",
    "wof:name":"Gaylords Specialty Crafts",
    "wof:placetype":"venue"
},
  "geometry": {"coordinates":[-81.73097,28.022168],"type":"Point"}
}