{
  "type": "Feature",
  "properties": {
    "iso:country":"US",
    "sg:address":"3637 Havendale Blvd NW",
    "sg:city":"Winter Haven",
    "sg:classifiers":[
        {
            "category":"Shopping",
            "type":"Retail Goods"
        }
    ],
    "sg:phone":"+1 863 967 1898",
    "sg:postcode":"33881",
    "sg:province":"FL",
    "sg:tags":[
        "merchandise"
    ],
    "wof:name":"Pet World",
    "wof:placetype":"venue"
},
  "geometry": {"coordinates":[-81.755256,28.046349],"type":"Point"}
}