{
  "type": "Feature",
  "properties": {
    "addr:full":"1004 W Church St Avon Park FL 33825",
    "addr:housenumber":"1004",
    "addr:postcode":"33825",
    "addr:street":"W Church St",
    "iso:country":"US",
    "sg:address":"1004 W Church St",
    "sg:city":"Avon Park",
    "sg:classifiers":[
        {
            "category":"Building & Trades",
            "subcategory":"Landscaping Services",
            "type":"Services"
        }
    ],
    "sg:phone":"+1 863 452 6635",
    "sg:postcode":"33825",
    "sg:province":"FL",
    "sg:tags":[
        "lawn",
        "maintenance",
        "grounds"
    ],
    "wof:name":"D C Yard Care & Landscaping",
    "wof:placetype":"venue"
},
  "geometry": {"coordinates":[-81.512528,27.597482],"type":"Point"}
}