{
  "type": "Feature",
  "properties": {
    "iso:country":"US",
    "sg:address":"13161 Cleveland Ave",
    "sg:city":"Fort Myers",
    "sg:classifiers":[
        {
            "category":"Real Estate",
            "subcategory":"Real Estate Services",
            "type":"Services"
        }
    ],
    "sg:phone":"+1 239 997 4100",
    "sg:postcode":"33903",
    "sg:province":"FL",
    "sg:tags":[
        "company",
        "title"
    ],
    "wof:name":"Southern States Abstract-Title",
    "wof:placetype":"venue"
},
  "geometry": {"coordinates":[-81.88511,26.661541],"type":"Point"}
}