{
  "type": "Feature",
  "properties": {
    "iso:country":"US",
    "sg:address":"1 Alhambra Plz",
    "sg:city":"Coral Gables",
    "sg:classifiers":[
        {
            "category":"Professional",
            "subcategory":"Lawyer & Legal Services",
            "type":"Services"
        }
    ],
    "sg:phone":"+1 305 774 6220",
    "sg:postcode":"33134",
    "sg:province":"FL",
    "wof:name":"Ferguson Troy D & Associates",
    "wof:placetype":"venue"
},
  "geometry": {"coordinates":[-80.254672,25.752686],"type":"Point"}
}