{
  "type": "Feature",
  "properties": {
    "addr:full":"8900 SW 107th Ave Miami FL 33176",
    "addr:housenumber":"8900",
    "addr:postcode":"33176",
    "addr:street":"Sw 107Th Ave",
    "iso:country":"US",
    "sg:address":"8900 SW 107th Ave",
    "sg:city":"Miami",
    "sg:classifiers":[
        {
            "category":"Professional",
            "subcategory":"Lawyer & Legal Services",
            "type":"Services"
        }
    ],
    "sg:phone":"+1 305 443 0732",
    "sg:postcode":"33176",
    "sg:province":"FL",
    "sg:tags":[
        "attorney"
    ],
    "sg:website":"www.divecubascuba.com",
    "wof:name":"Robert L Feldman",
    "wof:placetype":"venue"
},
  "geometry": {"coordinates":[-80.366901,25.684433],"type":"Point"}
}