{
  "type": "Feature",
  "properties": {
    "addr:full":"3933 Jean St Jacksonville FL 32205",
    "addr:housenumber":"3933",
    "addr:postcode":"32205",
    "addr:street":"Jean St",
    "iso:country":"US",
    "sg:address":"3933 Jean St",
    "sg:city":"Jacksonville",
    "sg:classifiers":[
        {
            "category":"Building & Trades",
            "subcategory":"Construction",
            "type":"Services"
        }
    ],
    "sg:phone":"+1 904 388 7301",
    "sg:postcode":"32205",
    "sg:province":"FL",
    "sg:tags":[
        "residential"
    ],
    "wof:name":"Joseph M Knoy",
    "wof:placetype":"venue"
},
  "geometry": {"coordinates":[-81.716843,30.295695],"type":"Point"}
}