{
  "type": "Feature",
  "properties": {
    "iso:country":"US",
    "sg:address":"1924 Ayrshier Pl",
    "sg:city":"Oviedo",
    "sg:classifiers":[
        {
            "category":"Landmark",
            "subcategory":"Tourist Information",
            "type":"Public Place"
        }
    ],
    "sg:phone":"+1 407 929 4811",
    "sg:postcode":"32765",
    "sg:province":"FL",
    "sg:tags":[
        "promoter",
        "tours-operators"
    ],
    "wof:name":"Red Scarf Travel",
    "wof:placetype":"venue"
},
  "geometry": {"coordinates":[-81.213669,28.642897],"type":"Point"}
}