{
  "type": "Feature",
  "properties": {
    "addr:full":"9014 SR-52 Hudson FL 34667",
    "addr:housenumber":"9014",
    "addr:postcode":"34667",
    "addr:street":"Sr-52",
    "iso:country":"US",
    "sg:address":"9014 SR-52",
    "sg:city":"Hudson",
    "sg:classifiers":[
        {
            "category":"Restaurant",
            "type":"Food & Drink"
        }
    ],
    "sg:menulink":"http://www.allmenus.com/fl/port-richey/163576-rallys/menu/",
    "sg:phone":"+1 727 868 4181",
    "sg:postcode":"34667",
    "sg:province":"FL",
    "sg:tags":[
        "sandwich",
        "dog",
        "burger",
        "hot",
        "wrap",
        "american"
    ],
    "wof:name":"Rally's",
    "wof:placetype":"venue"
},
  "geometry": {"coordinates":[-82.665594,28.33101],"type":"Point"}
}