{
  "type": "Feature",
  "properties": {
    "addr:full":"223 W Adams St Jacksonville FL 32202",
    "addr:housenumber":"223",
    "addr:postcode":"32202",
    "addr:street":"W Adams St",
    "iso:country":"US",
    "sg:address":"223 W Adams St",
    "sg:city":"Jacksonville",
    "sg:classifiers":[
        {
            "category":"Health Services",
            "subcategory":"Doctor",
            "type":"Services"
        }
    ],
    "sg:phone":"+1 904 356 0072",
    "sg:postcode":"32202",
    "sg:province":"FL",
    "sg:tags":[
        "dentist"
    ],
    "sg:website":"www.wittendental.com",
    "wof:name":"A Downtown Dental",
    "wof:placetype":"venue"
},
  "geometry": {"coordinates":[-81.661147,30.328601],"type":"Point"}
}