{
  "type": "Feature",
  "properties": {
    "addr:full":"13680 NW 19th Ave Opa Locka FL 33054",
    "addr:housenumber":"13680",
    "addr:postcode":"33054",
    "addr:street":"Nw 19Th Ave;Locka",
    "iso:country":"US",
    "sg:address":"13680 NW 19th Ave",
    "sg:city":"Opa Locka",
    "sg:classifiers":[
        {
            "category":"Retail",
            "subcategory":"Auto Repair",
            "type":"Services"
        }
    ],
    "sg:phone":"+1 305 681 8387",
    "sg:postcode":"33054",
    "sg:province":"FL",
    "wof:name":"Integrated Motors",
    "wof:placetype":"venue"
},
  "geometry": {"coordinates":[-80.231632,25.899075],"type":"Point"}
}