{
  "type": "Feature",
  "properties": {
    "iso:country":"US",
    "sg:address":"1208 Georgia St",
    "sg:city":"Delray Beach",
    "sg:classifiers":[
        {
            "category":"Retail",
            "subcategory":"Auto Repair",
            "type":"Services"
        }
    ],
    "sg:phone":"+1 561 265 2227",
    "sg:postcode":"33444",
    "sg:province":"FL",
    "sg:tags":[
        "repairing",
        "automobile"
    ],
    "wof:name":"Black Horse Motor Cars",
    "wof:placetype":"venue"
},
  "geometry": {"coordinates":[-80.086637,26.443174],"type":"Point"}
}