{
  "type": "Feature",
  "properties": {
    "addr:full":"344 Morgan Ln Mary Esther FL 32569",
    "addr:housenumber":"344",
    "addr:postcode":"32569",
    "addr:street":"Morgan Ln",
    "iso:country":"US",
    "sg:address":"344 Morgan Ln",
    "sg:city":"Mary Esther",
    "sg:classifiers":[
        {
            "category":"Building & Trades",
            "subcategory":"Construction",
            "type":"Services"
        }
    ],
    "sg:phone":"+1 850 585 0346",
    "sg:postcode":"32569",
    "sg:province":"FL",
    "sg:tags":[
        "concrete",
        "contractor"
    ],
    "wof:name":"Robert M Charron Contractor",
    "wof:placetype":"venue"
},
  "geometry": {"coordinates":[-86.78479299999999,30.412901],"type":"Point"}
}