{
  "type": "Feature",
  "properties": {
    "iso:country":"US",
    "sg:address":"2888 Mahan Dr",
    "sg:city":"Tallahassee",
    "sg:classifiers":[
        {
            "category":"Health Services",
            "subcategory":"Doctor",
            "type":"Services"
        }
    ],
    "sg:phone":"+1 850 656 2926",
    "sg:postcode":"32308",
    "sg:province":"FL",
    "sg:tags":[
        "physician",
        "surgeon"
    ],
    "wof:name":"Tallahassee Community Surgery",
    "wof:placetype":"venue"
},
  "geometry": {"coordinates":[-84.229437,30.459565],"type":"Point"}
}