{
  "type": "Feature",
  "properties": {
    "iso:country":"US",
    "sg:address":"228 Adair Ave",
    "sg:city":"Longwood",
    "sg:classifiers":[
        {
            "category":"Shopping",
            "subcategory":"Discount & Variety Stores",
            "type":"Retail Goods"
        }
    ],
    "sg:phone":"+1 407 332 7552",
    "sg:postcode":"32750",
    "sg:province":"FL",
    "sg:tags":[
        "merchandise",
        "general"
    ],
    "wof:name":"RMC Specialty Products Inc",
    "wof:placetype":"venue"
},
  "geometry": {"coordinates":[-81.373915,28.691719],"type":"Point"}
}