{
  "type": "Feature",
  "properties": {
    "iso:country":"US",
    "sg:address":"16604 Avila Blvd",
    "sg:city":"Tampa",
    "sg:classifiers":[
        {
            "category":"Recreation",
            "type":"Entertainment"
        }
    ],
    "sg:phone":"+1 813 962 2472",
    "sg:postcode":"33613",
    "sg:province":"FL",
    "sg:tags":[
        "course",
        "golf"
    ],
    "wof:name":"Avila Golf & Country Club",
    "wof:placetype":"venue"
},
  "geometry": {"coordinates":[-82.47308,28.107702],"type":"Point"}
}