{
  "type": "Feature",
  "properties": {
    "iso:country":"US",
    "sg:address":"5000 N Wickham Rd",
    "sg:city":"Melbourne",
    "sg:classifiers":[
        {
            "category":"Personal",
            "subcategory":"Beauty Salon",
            "type":"Services"
        }
    ],
    "sg:phone":"+1 321 622 5962",
    "sg:postcode":"32940",
    "sg:province":"FL",
    "sg:tags":[
        "hair",
        "stylist"
    ],
    "wof:name":"Unique Hair Salon",
    "wof:placetype":"venue"
},
  "geometry": {"coordinates":[-80.672119,28.18947],"type":"Point"}
}