{
  "type": "Feature",
  "properties": {
    "addr:full":"1918 7th Ave N Lake Worth FL 33461",
    "addr:housenumber":"1918",
    "addr:postcode":"33461",
    "addr:street":"7Th Ave N",
    "iso:country":"US",
    "sg:address":"1918 7th Ave N",
    "sg:city":"Lake Worth",
    "sg:classifiers":[
        {
            "category":"Home & Garden",
            "subcategory":"Furniture",
            "type":"Retail Goods"
        }
    ],
    "sg:phone":"+1 561 547 5749",
    "sg:postcode":"33461",
    "sg:province":"FL",
    "sg:tags":[
        "builder",
        "custom"
    ],
    "wof:name":"Morel's Fine Wood Furnishing",
    "wof:placetype":"venue"
},
  "geometry": {"coordinates":[-80.071033,26.624288],"type":"Point"}
}