{
  "type": "Feature",
  "properties": {
    "iso:country":"US",
    "sg:address":"7910 SW 16th St",
    "sg:city":"Miami",
    "sg:classifiers":[
        {
            "category":"Home & Garden",
            "subcategory":"Building Materials",
            "type":"Retail Goods"
        },
        {
            "category":"Building & Trades",
            "subcategory":"Construction",
            "type":"Services"
        }
    ],
    "sg:phone":"+1 786 220 7980",
    "sg:postcode":"33155",
    "sg:province":"FL",
    "sg:tags":[
        "concrete",
        "staining",
        "contractor"
    ],
    "wof:name":"Miamicrete, Inc.",
    "wof:placetype":"venue"
},
  "geometry": {"coordinates":[-80.32486,25.755209],"type":"Point"}
}