{
  "type": "Feature",
  "properties": {
    "iso:country":"US",
    "sg:address":"10404 W Flagler St Ste 12",
    "sg:city":"Miami",
    "sg:classifiers":[
        {
            "category":"Food & Beverages",
            "subcategory":"Groceries & Convenience Stores",
            "type":"Retail Goods"
        }
    ],
    "sg:phone":"+1 305 221 7234",
    "sg:postcode":"33174",
    "sg:province":"FL",
    "wof:name":"El Mercadito Nicaraguense",
    "wof:placetype":"venue"
},
  "geometry": {"coordinates":[-80.364304,25.768499],"type":"Point"}
}