{
  "type": "Feature",
  "properties": {
    "iso:country":"US",
    "sg:address":"3755 Tamiami Trl",
    "sg:city":"Port Charlotte",
    "sg:classifiers":[
        {
            "category":"Recreation",
            "type":"Entertainment"
        }
    ],
    "sg:phone":"+1 941 585 6506",
    "sg:postcode":"33952",
    "sg:province":"FL",
    "sg:tags":[
        "bicycle"
    ],
    "wof:name":"Bicycle Center-Port Charlotte",
    "wof:placetype":"venue"
},
  "geometry": {"coordinates":[-82.08932900000001,26.974463],"type":"Point"}
}