{
  "type": "Feature",
  "properties": {
    "iso:country":"US",
    "sg:address":"10760 W Flagler St Ste 4",
    "sg:city":"Miami",
    "sg:classifiers":[
        {
            "category":"Personal",
            "subcategory":"Barber",
            "type":"Services"
        }
    ],
    "sg:phone":"+1 305 551 9177",
    "sg:postcode":"33174",
    "sg:province":"FL",
    "wof:name":"Pepe's Barber Shop Unisex",
    "wof:placetype":"venue"
},
  "geometry": {"coordinates":[-80.37039900000001,25.7684],"type":"Point"}
}