{
  "type": "Feature",
  "properties": {
    "iso:country":"US",
    "sg:address":"857 E Klosterman Rd",
    "sg:city":"Tarpon Springs",
    "sg:classifiers":[
        {
            "category":"Restaurant",
            "type":"Food & Drink"
        }
    ],
    "sg:phone":"+1 727 944 5788",
    "sg:postcode":"34684",
    "sg:province":"FL",
    "wof:name":"Nana's Restaurant",
    "wof:placetype":"venue"
},
  "geometry": {"coordinates":[-82.738006,28.122994],"type":"Point"}
}