{
  "type": "Feature",
  "properties": {
    "addr:full":"2310 Hammondville Rd Pompano Beach FL 33069",
    "addr:housenumber":"2310",
    "addr:postcode":"33069",
    "addr:street":"Hammondville Rd",
    "iso:country":"US",
    "sg:address":"2310 Hammondville Rd",
    "sg:city":"Pompano Beach",
    "sg:classifiers":[
        {
            "category":"Organizations",
            "subcategory":"Religious Organization",
            "type":"Services"
        }
    ],
    "sg:phone":"+1 954 971 8780",
    "sg:postcode":"33069",
    "sg:province":"FL",
    "sg:tags":[
        "catholic",
        "church"
    ],
    "wof:name":"San Isidros Catholic Church",
    "wof:placetype":"venue"
},
  "geometry": {"coordinates":[-80.15159800000001,26.243568],"type":"Point"}
}