{
  "type": "Feature",
  "properties": {
    "iso:country":"US",
    "sg:address":"120 NW 44th St",
    "sg:city":"Miami",
    "sg:classifiers":[
        {
            "category":"Cinema",
            "subcategory":"Movie Rental",
            "type":"Entertainment"
        }
    ],
    "sg:phone":"+1 954 695 2925",
    "sg:postcode":"33127",
    "sg:province":"FL",
    "sg:tags":[
        "slide",
        "film",
        "strip"
    ],
    "wof:name":"Blackjack Pictures, Inc.",
    "wof:placetype":"venue"
},
  "geometry": {"coordinates":[-80.197997,25.815942],"type":"Point"}
}