{
  "type": "Feature",
  "properties": {
    "addr:full":"1189 SW 26th Ave Fort Lauderdale FL 33312",
    "addr:housenumber":"1189",
    "addr:postcode":"33312",
    "addr:street":"Sw 26Th Ave",
    "iso:country":"US",
    "sg:address":"1189 SW 26th Ave",
    "sg:city":"Fort Lauderdale",
    "sg:classifiers":[
        {
            "category":"Health Services",
            "subcategory":"Chiropractor",
            "type":"Services"
        }
    ],
    "sg:phone":"+1 954 791 4848",
    "sg:postcode":"33312",
    "sg:province":"FL",
    "wof:name":"Buhlinger Chiropractic Ctr",
    "wof:placetype":"venue"
},
  "geometry": {"coordinates":[-80.175979,26.107866],"type":"Point"}
}