{
  "type": "Feature",
  "properties": {
    "addr:full":"2373 NW 149th St Opa Locka FL 33054",
    "addr:housenumber":"2373",
    "addr:postcode":"33054",
    "addr:street":"Nw 149Th St;Locka",
    "iso:country":"US",
    "sg:address":"2373 NW 149th St",
    "sg:city":"Opa Locka",
    "sg:classifiers":[
        {
            "category":"Manufacturing",
            "subcategory":"Furniture",
            "type":"Manufacturing & Wholesale Goods"
        }
    ],
    "sg:phone":"+1 305 687 9091",
    "sg:postcode":"33054",
    "sg:province":"FL",
    "sg:tags":[
        "mfg"
    ],
    "wof:name":"Art Form Collection Inc",
    "wof:placetype":"venue"
},
  "geometry": {"coordinates":[-80.23856499999999,25.910182],"type":"Point"}
}