{
  "type": "Feature",
  "properties": {
    "iso:country":"US",
    "sg:address":"45 Bahia Trace Cir",
    "sg:city":"Ocala",
    "sg:classifiers":[
        {
            "category":"Professional",
            "subcategory":"Management & Consulting",
            "type":"Services"
        }
    ],
    "sg:phone":"+1 352 687 2362",
    "sg:postcode":"34472",
    "sg:province":"FL",
    "sg:tags":[
        "business"
    ],
    "wof:name":"McAfee Business Solutions",
    "wof:placetype":"venue"
},
  "geometry": {"coordinates":[-82.011196,29.138121],"type":"Point"}
}