{
  "type": "Feature",
  "properties": {
    "iso:country":"US",
    "sg:address":"3310 E Fort King St",
    "sg:city":"Ocala",
    "sg:classifiers":[
        {
            "category":"Shopping",
            "subcategory":"Gifts & Souvenirs",
            "type":"Retail Goods"
        }
    ],
    "sg:phone":"+1 352 622 3737",
    "sg:postcode":"34470",
    "sg:province":"FL",
    "sg:tags":[
        "shop"
    ],
    "wof:name":"Your Hearts Desire",
    "wof:placetype":"venue"
},
  "geometry": {"coordinates":[-82.086866,29.1861],"type":"Point"}
}