{
  "type": "Feature",
  "properties": {
    "addr:full":"10442 N Dale Mabry Hwy Tampa FL 33618",
    "addr:housenumber":"10442",
    "addr:postcode":"33618",
    "addr:street":"N Dale Mabry Hwy",
    "iso:country":"US",
    "sg:address":"10442 N Dale Mabry Hwy",
    "sg:city":"Tampa",
    "sg:classifiers":[
        {
            "category":"Restaurant",
            "type":"Food & Drink"
        }
    ],
    "sg:phone":"+1 813 961 7588",
    "sg:postcode":"33618",
    "sg:province":"FL",
    "wof:name":"MEI Wah Chinese Restaurant",
    "wof:placetype":"venue"
},
  "geometry": {"coordinates":[-82.504572,28.045649],"type":"Point"}
}