{
  "type": "Feature",
  "properties": {
    "addr:full":"301 Maple Crst Haines City FL 33844",
    "addr:housenumber":"301",
    "addr:postcode":"33844",
    "addr:street":"Maple Crst",
    "iso:country":"US",
    "sg:address":"301 Maple Crst",
    "sg:city":"Haines City",
    "sg:classifiers":[
        {
            "category":"Travel",
            "subcategory":"Hotels & Motels",
            "type":"Entertainment"
        }
    ],
    "sg:phone":"+1 863 422 0941",
    "sg:postcode":"33844",
    "sg:province":"FL",
    "wof:name":"Hotel Bed & Breakfast",
    "wof:placetype":"venue"
},
  "geometry": {"coordinates":[-81.66349599999999,28.099617],"type":"Point"}
}