{
  "type": "Feature",
  "properties": {
    "iso:country":"US",
    "sg:address":"3036 Stratton Ln",
    "sg:city":"Jacksonville",
    "sg:classifiers":[
        {
            "category":"Building & Trades",
            "subcategory":"Landscaping Services",
            "type":"Services"
        }
    ],
    "sg:phone":"+1 904 786 4253",
    "sg:postcode":"32221",
    "sg:province":"FL",
    "wof:name":"Raymond Johnsons Lawn Service",
    "wof:placetype":"venue"
},
  "geometry": {"coordinates":[-81.831492,30.259876],"type":"Point"}
}