{
  "type": "Feature",
  "properties": {
    "iso:country":"US",
    "sg:address":"1310 Poplar Ave",
    "sg:city":"Venice",
    "sg:classifiers":[
        {
            "category":"Building & Trades",
            "subcategory":"Landscaping Services",
            "type":"Services"
        }
    ],
    "sg:phone":"+1 941 488 6258",
    "sg:postcode":"34285",
    "sg:province":"FL",
    "wof:name":"Lawns USA",
    "wof:placetype":"venue"
},
  "geometry": {"coordinates":[-82.418136,27.096478],"type":"Point"}
}