{
  "type": "Feature",
  "properties": {
    "iso:country":"US",
    "sg:address":"918 Edgewood Ave S",
    "sg:city":"Jacksonville",
    "sg:classifiers":[
        {
            "category":"Government",
            "subcategory":"Office",
            "type":"Public Place"
        }
    ],
    "sg:phone":"+1 904 384 2665",
    "sg:postcode":"32205",
    "sg:province":"FL",
    "sg:tags":[
        "educational",
        "program",
        "administrative"
    ],
    "wof:name":"Public Library",
    "wof:placetype":"venue"
},
  "geometry": {"coordinates":[-81.719388,30.313347],"type":"Point"}
}