{
  "type": "Feature",
  "properties": {
    "addr:full":"1701 S 50th St Tampa FL 33619",
    "addr:housenumber":"1701",
    "addr:postcode":"33619",
    "addr:street":"S 50Th St",
    "iso:country":"US",
    "sg:address":"1701 S 50th St",
    "sg:city":"Tampa",
    "sg:classifiers":[
        {
            "category":"Home & Garden",
            "subcategory":"Garden Supply",
            "type":"Retail Goods"
        }
    ],
    "sg:phone":"+1 813 247 5796",
    "sg:postcode":"33619",
    "sg:province":"FL",
    "sg:tags":[
        "statuary"
    ],
    "wof:name":"Pla Statuary",
    "wof:placetype":"venue"
},
  "geometry": {"coordinates":[-82.40192399999999,27.931206],"type":"Point"}
}