{
  "type": "Feature",
  "properties": {
    "addr:full":"2541 Bay Leaf Dr Orlando FL 32837",
    "addr:housenumber":"2541",
    "addr:postcode":"32837",
    "addr:street":"Bay Leaf Dr",
    "iso:country":"US",
    "sg:address":"2541 Bay Leaf Dr",
    "sg:city":"Orlando",
    "sg:classifiers":[
        {
            "category":"Shopping",
            "subcategory":"Computers & Home Electronics",
            "type":"Retail Goods"
        }
    ],
    "sg:phone":"+1 407 858 9105",
    "sg:postcode":"32837",
    "sg:province":"FL",
    "sg:tags":[
        "development",
        "software"
    ],
    "wof:name":"First Financial Software Inc",
    "wof:placetype":"venue"
},
  "geometry": {"coordinates":[-81.415622,28.392716],"type":"Point"}
}