{
  "type": "Feature",
  "properties": {
    "iso:country":"US",
    "sg:address":"3922 Coconut Palm Dr",
    "sg:city":"Tampa",
    "sg:classifiers":[
        {
            "category":"Manufacturing",
            "subcategory":"Printing",
            "type":"Manufacturing & Wholesale Goods"
        }
    ],
    "sg:phone":"+1 813 627 6700",
    "sg:postcode":"33619",
    "sg:province":"FL",
    "sg:tags":[
        "publisher"
    ],
    "sg:website":"www.csgis.com",
    "wof:name":"Chain Store Guide",
    "wof:placetype":"venue"
},
  "geometry": {"coordinates":[-82.34962,27.980369],"type":"Point"}
}