{
  "type": "Feature",
  "properties": {
    "addr:full":"10919 N Dale Mabry Hwy Tampa FL 33614",
    "addr:housenumber":"10919",
    "addr:postcode":"33614",
    "addr:street":"N Dale Mabry Hwy",
    "iso:country":"US",
    "sg:address":"10919 N Dale Mabry Hwy",
    "sg:city":"Tampa",
    "sg:classifiers":[
        {
            "category":"Shopping",
            "type":"Retail Goods"
        }
    ],
    "sg:phone":"+1 813 908 7678",
    "sg:postcode":"33614",
    "sg:province":"FL",
    "sg:tags":[
        "hearing",
        "equipment",
        "supply",
        "impaired"
    ],
    "wof:name":"Bell Hearing Factory Direct",
    "wof:placetype":"venue"
},
  "geometry": {"coordinates":[-82.50413,28.049038],"type":"Point"}
}