{
  "type": "Feature",
  "properties": {
    "addr:full":"301 W Oakland Park Blvd Wilton Manors FL 33311",
    "addr:housenumber":"301",
    "addr:postcode":"33311",
    "addr:street":"W Oakland Park Blvd",
    "iso:country":"US",
    "sg:address":"301 W Oakland Park Blvd",
    "sg:city":"Wilton Manors",
    "sg:classifiers":[
        {
            "category":"Retail",
            "subcategory":"Repair Shop",
            "type":"Services"
        }
    ],
    "sg:phone":"+1 954 446 7137",
    "sg:postcode":"33311",
    "sg:province":"FL",
    "sg:tags":[
        "lock",
        "locksmith"
    ],
    "wof:name":"1 Hour All Day Emergency",
    "wof:placetype":"venue"
},
  "geometry": {"coordinates":[-80.15049399999999,26.166425],"type":"Point"}
}