{
  "type": "Feature",
  "properties": {
    "iso:country":"US",
    "sg:address":"2223 S Goldenrod Rd",
    "sg:city":"Orlando",
    "sg:classifiers":[
        {
            "category":"Restaurant",
            "type":"Food & Drink"
        }
    ],
    "sg:menulink":"http://www.allmenus.com/fl/union-park/81347-papa-johns-pizza/menu/",
    "sg:phone":"+1 407 275 7272",
    "sg:postcode":"32822",
    "sg:province":"FL",
    "sg:tags":[
        "american",
        "pizza"
    ],
    "wof:name":"Papa John's Pizza",
    "wof:placetype":"venue"
},
  "geometry": {"coordinates":[-81.28854699999999,28.516679],"type":"Point"}
}