{
  "type": "Feature",
  "properties": {
    "iso:country":"US",
    "sg:address":"300 US Hwy 98",
    "sg:city":"Destin",
    "sg:classifiers":[
        {
            "category":"Food & Beverages",
            "subcategory":"Specialty",
            "type":"Retail Goods"
        }
    ],
    "sg:phone":"+1 850 654 1005",
    "sg:postcode":"32541",
    "sg:province":"FL",
    "sg:tags":[
        "health",
        "diet"
    ],
    "wof:name":"Feelin' Good Health Foods",
    "wof:placetype":"venue"
},
  "geometry": {"coordinates":[-86.499752,30.393001],"type":"Point"}
}