{
  "type": "Feature",
  "properties": {
    "iso:country":"US",
    "sg:address":"1127 Sterling Rd",
    "sg:city":"Inverness",
    "sg:classifiers":[
        {
            "category":"Real Estate",
            "subcategory":"Surveying",
            "type":"Services"
        }
    ],
    "sg:phone":"+1 352 344 8502",
    "sg:postcode":"34450",
    "sg:province":"FL",
    "sg:tags":[
        "surveyor"
    ],
    "wof:name":"Bobby J Goodman Inc",
    "wof:placetype":"venue"
},
  "geometry": {"coordinates":[-82.343694,28.838418],"type":"Point"}
}