{
  "type": "Feature",
  "properties": {
    "iso:country":"US",
    "sg:address":"7341 SW 6th Ct",
    "sg:city":"Fort Lauderdale",
    "sg:classifiers":[
        {
            "category":"Professional",
            "subcategory":"Business Services",
            "type":"Services"
        }
    ],
    "sg:phone":"+1 954 581 9744",
    "sg:postcode":"33317",
    "sg:province":"FL",
    "wof:name":"Sunshine Hosts",
    "wof:placetype":"venue"
},
  "geometry": {"coordinates":[-80.24560099999999,26.112316],"type":"Point"}
}