{
  "type": "Feature",
  "properties": {
    "iso:country":"US",
    "sg:address":"4971 NW Blitchton Rd",
    "sg:city":"Ocala",
    "sg:classifiers":[
        {
            "category":"Shopping",
            "subcategory":"Florist",
            "type":"Retail Goods"
        }
    ],
    "sg:phone":"+1 352 840 0377",
    "sg:postcode":"34482",
    "sg:province":"FL",
    "wof:name":"Northwest Florist",
    "wof:placetype":"venue"
},
  "geometry": {"coordinates":[-82.200468,29.214133],"type":"Point"}
}