{
  "type": "Feature",
  "properties": {
    "addr:full":"1981 SW 133rd Ave Miramar FL 33027",
    "addr:housenumber":"1981",
    "addr:postcode":"33027",
    "addr:street":"Sw 133Rd Ave",
    "iso:country":"US",
    "sg:address":"1981 SW 133rd Ave",
    "sg:city":"Miramar",
    "sg:classifiers":[
        {
            "category":"Social Services",
            "subcategory":"Child Care",
            "type":"Services"
        }
    ],
    "sg:phone":"+1 954 430 9919",
    "sg:postcode":"33027",
    "sg:province":"FL",
    "wof:name":"America Ahmed Child Care",
    "wof:placetype":"venue"
},
  "geometry": {"coordinates":[-80.323865,25.99093],"type":"Point"}
}