{
  "type": "Feature",
  "properties": {
    "iso:country":"US",
    "sg:address":"3200 N Federal Hwy",
    "sg:city":"Boca Raton",
    "sg:classifiers":[
        {
            "category":"Banks & Credit Unions",
            "subcategory":"Bank",
            "type":"Services"
        }
    ],
    "sg:phone":"+1 561 392 1997",
    "sg:postcode":"33431",
    "sg:province":"FL",
    "sg:tags":[
        "mortgage",
        "loan",
        "broker",
        "licensed",
        "real estate"
    ],
    "wof:name":"Park Place Financial Inc",
    "wof:placetype":"venue"
},
  "geometry": {"coordinates":[-80.07647799999999,26.382925],"type":"Point"}
}