{
  "type": "Feature",
  "properties": {
    "iso:country":"US",
    "sg:address":"11755 SW 90th St",
    "sg:city":"Miami",
    "sg:classifiers":[
        {
            "category":"Education",
            "subcategory":"School",
            "type":"Public Place"
        }
    ],
    "sg:phone":"+1 305 598 3882",
    "sg:postcode":"33186",
    "sg:province":"FL",
    "sg:tags":[
        "elementary",
        "academic",
        "special",
        "private",
        "secondary"
    ],
    "wof:name":"Paladin Academy",
    "wof:placetype":"venue"
},
  "geometry": {"coordinates":[-80.38550600000001,25.684591],"type":"Point"}
}