{
  "type": "Feature",
  "properties": {
    "iso:country":"US",
    "sg:address":"14515 Walsingham Rd",
    "sg:city":"Largo",
    "sg:classifiers":[
        {
            "category":"Real Estate",
            "subcategory":"Real Estate Agent",
            "type":"Services"
        }
    ],
    "sg:phone":"+1 727 596 6508",
    "sg:postcode":"33774",
    "sg:province":"FL",
    "wof:name":"Shipwatch Realty Inc",
    "wof:placetype":"venue"
},
  "geometry": {"coordinates":[-82.838804,27.880486],"type":"Point"}
}