{
  "type": "Feature",
  "properties": {
    "iso:country":"US",
    "sg:address":"2725 Sundance St",
    "sg:city":"Naples",
    "sg:classifiers":[
        {
            "category":"Building & Trades",
            "subcategory":"Landscaping Services",
            "type":"Services"
        }
    ],
    "sg:phone":"+1 239 455 8948",
    "sg:postcode":"34120",
    "sg:province":"FL",
    "wof:name":"Ja Tree Farm",
    "wof:placetype":"venue"
},
  "geometry": {"coordinates":[-81.657178,26.266015],"type":"Point"}
}