{
  "type": "Feature",
  "properties": {
    "addr:full":"5600 W Highway 98 Pensacola FL 32507",
    "addr:housenumber":"5600",
    "addr:postcode":"32507",
    "addr:street":"W Highway 98",
    "iso:country":"US",
    "sg:address":"5600 W Highway 98",
    "sg:city":"Pensacola",
    "sg:classifiers":[
        {
            "category":"Utilities",
            "subcategory":"Mobile Phone",
            "type":"Services"
        },
        {
            "category":"Utilities",
            "subcategory":"Telephone",
            "type":"Services"
        },
        {
            "category":"Shopping",
            "subcategory":"Mobile Phones",
            "type":"Retail Goods"
        },
        {
            "category":"Manufacturing",
            "subcategory":"Electronics",
            "type":"Manufacturing & Wholesale Goods"
        },
        {
            "category":"Communications",
            "type":"Services"
        }
    ],
    "sg:phone":"+1 850 457 7044",
    "sg:postcode":"32507",
    "sg:province":"FL",
    "sg:tags":[
        "equipment",
        "telecommunications-equipment",
        "system",
        "cellular",
        "supply"
    ],
    "sg:website":"http://www.alltel.com",
    "wof:name":"Alltel Wireless",
    "wof:placetype":"venue"
},
  "geometry": {"coordinates":[-87.289574,30.396669],"type":"Point"}
}