{
  "type": "Feature",
  "properties": {
    "addr:full":"2250 NW 24th Ave Gainesville FL 32605",
    "addr:housenumber":"2250",
    "addr:postcode":"32605",
    "addr:street":"Nw 24Th Ave",
    "iso:country":"US",
    "sg:address":"2250 NW 24th Ave",
    "sg:city":"Gainesville",
    "sg:classifiers":[
        {
            "category":"Professional",
            "subcategory":"Research",
            "type":"Services"
        }
    ],
    "sg:phone":"+1 352 372 9061",
    "sg:postcode":"32605",
    "sg:province":"FL",
    "sg:tags":[
        "information",
        "medical"
    ],
    "sg:website":"http://www.apt-pharmatox.com",
    "wof:name":"Applied Pharmacology & Toxicology Inc",
    "wof:placetype":"venue"
},
  "geometry": {"coordinates":[-82.353551,29.674931],"type":"Point"}
}