{
  "type": "Feature",
  "properties": {
    "addr:full":"133 SW Wiregrass Ct Palm City FL 34990",
    "addr:housenumber":"133",
    "addr:postcode":"34990",
    "addr:street":"Sw Wiregrass Ct",
    "iso:country":"US",
    "sg:address":"133 SW Wiregrass Ct",
    "sg:city":"Palm City",
    "sg:classifiers":[
        {
            "category":"Building & Trades",
            "subcategory":"Construction",
            "type":"Services"
        }
    ],
    "sg:phone":"+1 772 220 8627",
    "sg:postcode":"34990",
    "sg:province":"FL",
    "sg:tags":[
        "house"
    ],
    "wof:name":"Martin Homes Inc",
    "wof:placetype":"venue"
},
  "geometry": {"coordinates":[-80.299363,27.203967],"type":"Point"}
}