{
  "type": "Feature",
  "properties": {
    "addr:full":"3895 NW 183rd St Opa Locka FL 33055",
    "addr:housenumber":"3895",
    "addr:postcode":"33055",
    "addr:street":"Nw 183Rd St;Locka",
    "iso:country":"US",
    "sg:address":"3895 NW 183rd St",
    "sg:city":"Opa Locka",
    "sg:classifiers":[
        {
            "category":"Building & Trades",
            "subcategory":"Cleaning & Sanitation",
            "type":"Services"
        }
    ],
    "sg:phone":"+1 305 622 3361",
    "sg:postcode":"33055",
    "sg:province":"FL",
    "sg:tags":[
        "janitor"
    ],
    "wof:name":"Daryl Professional Svc Inc",
    "wof:placetype":"venue"
},
  "geometry": {"coordinates":[-80.264257,25.940303],"type":"Point"}
}