{
  "type": "Feature",
  "properties": {
    "iso:country":"US",
    "sg:address":"1825 Old Moultrie Rd",
    "sg:city":"St Augustine",
    "sg:classifiers":[
        {
            "category":"Retail",
            "subcategory":"Car Wash",
            "type":"Services"
        }
    ],
    "sg:phone":"+1 904 824 6588",
    "sg:postcode":"32084",
    "sg:province":"FL",
    "sg:tags":[
        "polishing",
        "washing"
    ],
    "wof:name":"Salt 'n Sand Car Wash",
    "wof:placetype":"venue"
},
  "geometry": {"coordinates":[-81.326196,29.870251],"type":"Point"}
}