{
  "type": "Feature",
  "properties": {
    "addr:full":"8701 NW 91st St Medley FL 33178",
    "addr:housenumber":"8701",
    "addr:postcode":"33178",
    "addr:street":"Nw 91St St",
    "iso:country":"US",
    "sg:address":"8701 NW 91st St",
    "sg:city":"Medley",
    "sg:classifiers":[
        {
            "category":"Building & Trades",
            "subcategory":"Landscaping Services",
            "type":"Services"
        }
    ],
    "sg:phone":"+1 305 887 8377",
    "sg:postcode":"33178",
    "sg:province":"FL",
    "sg:tags":[
        "gardener"
    ],
    "wof:name":"Keystone Garden Inc",
    "wof:placetype":"venue"
},
  "geometry": {"coordinates":[-80.34056699999999,25.856654],"type":"Point"}
}