{
  "type": "Feature",
  "properties": {
    "addr:full":"3750 W 16th Ave Hialeah FL 33012",
    "addr:housenumber":"3750",
    "addr:postcode":"33012",
    "addr:street":"W 16Th Ave",
    "iso:country":"US",
    "sg:address":"3750 W 16th Ave",
    "sg:city":"Hialeah",
    "sg:classifiers":[
        {
            "category":"Health Services",
            "subcategory":"Clinic",
            "type":"Services"
        }
    ],
    "sg:phone":"+1 305 826 9796",
    "sg:postcode":"33012",
    "sg:province":"FL",
    "wof:name":"Golden Therapy Ctr Inc",
    "wof:placetype":"venue"
},
  "geometry": {"coordinates":[-80.314481,25.855777],"type":"Point"}
}