{
  "type": "Feature",
  "properties": {
    "iso:country":"US",
    "sg:address":"330 S State Road 7",
    "sg:city":"Hollywood",
    "sg:classifiers":[
        {
            "category":"Banks & Credit Unions",
            "subcategory":"Bank",
            "type":"Services"
        },
        {
            "category":"Shopping",
            "subcategory":"Thrift Store",
            "type":"Retail Goods"
        }
    ],
    "sg:phone":"+1 954 962 4983",
    "sg:postcode":"33023",
    "sg:province":"FL",
    "sg:tags":[
        "shop",
        "second",
        "hand"
    ],
    "wof:name":"Mattrob Inc",
    "wof:placetype":"venue"
},
  "geometry": {"coordinates":[-80.207429,26.004395],"type":"Point"}
}