{
  "type": "Feature",
  "properties": {
    "iso:country":"US",
    "sg:address":"704 N 74th Ave",
    "sg:city":"Pensacola",
    "sg:classifiers":[
        {
            "category":"Real Estate",
            "subcategory":"Real Estate Services",
            "type":"Services"
        },
        {
            "category":"Real Estate",
            "subcategory":"Real Estate Agent",
            "type":"Services"
        }
    ],
    "sg:phone":"+1 850 455 2389",
    "sg:postcode":"32506",
    "sg:province":"FL",
    "sg:tags":[
        "buyer",
        "broker"
    ],
    "wof:name":"John D Fayard",
    "wof:placetype":"venue"
},
  "geometry": {"coordinates":[-87.309676,30.419267],"type":"Point"}
}