{
  "type": "Feature",
  "properties": {
    "iso:country":"US",
    "sg:address":"2500 Airport Pulling Rd S",
    "sg:city":"Naples",
    "sg:classifiers":[
        {
            "category":"Professional",
            "subcategory":"Employment Agencies",
            "type":"Services"
        }
    ],
    "sg:phone":"+1 239 417 2301",
    "sg:postcode":"34112",
    "sg:province":"FL",
    "sg:tags":[
        "temporary"
    ],
    "wof:name":"Coastal Staffing Services",
    "wof:placetype":"venue"
},
  "geometry": {"coordinates":[-81.76649999999999,26.128973],"type":"Point"}
}