{
  "type": "Feature",
  "properties": {
    "iso:country":"US",
    "sg:address":"3900 Creighton Rd",
    "sg:city":"Pensacola",
    "sg:classifiers":[
        {
            "category":"Restaurant",
            "type":"Food & Drink"
        }
    ],
    "sg:menulink":"http://www.allmenus.com/fl/pensacola/71343-pizza-hut/menu/",
    "sg:phone":"+1 850 478 2966",
    "sg:postcode":"32504",
    "sg:province":"FL",
    "sg:tags":[
        "american",
        "pizza"
    ],
    "wof:name":"Pizza Hut",
    "wof:placetype":"venue"
},
  "geometry": {"coordinates":[-87.17269899999999,30.498067],"type":"Point"}
}