{
  "type": "Feature",
  "properties": {
    "iso:country":"US",
    "sg:address":"21681 Tuckahoe Rd",
    "sg:city":"Alva",
    "sg:classifiers":[
        {
            "category":"Building & Trades",
            "subcategory":"Construction",
            "type":"Services"
        }
    ],
    "sg:phone":"+1 239 728 3447",
    "sg:postcode":"33920",
    "sg:province":"FL",
    "sg:tags":[
        "contractor",
        "carpenter",
        "carpentry"
    ],
    "wof:name":"Marvin Pigott Carpentry",
    "wof:placetype":"venue"
},
  "geometry": {"coordinates":[-81.604157,26.697861],"type":"Point"}
}