{
  "type": "Feature",
  "properties": {
    "iso:country":"US",
    "sg:address":"14 Neptune Rd",
    "sg:city":"Kissimmee",
    "sg:classifiers":[
        {
            "category":"Railroad",
            "type":"Transportation"
        }
    ],
    "sg:phone":"+1 407 933 8598",
    "sg:postcode":"34744",
    "sg:province":"FL",
    "wof:name":"CSX Transportation Inc",
    "wof:placetype":"venue"
},
  "geometry": {"coordinates":[-81.402289,28.294639],"type":"Point"}
}