{
  "type": "Feature",
  "properties": {
    "iso:country":"US",
    "sg:address":"1675 S John Rodes Blvd",
    "sg:city":"Melbourne",
    "sg:classifiers":[
        {
            "category":"Shopping",
            "type":"Retail Goods"
        }
    ],
    "sg:phone":"+1 321 728 1009",
    "sg:postcode":"32904",
    "sg:province":"FL",
    "sg:tags":[
        "trophy",
        "medal",
        "merchandise",
        "award"
    ],
    "wof:name":"Flordia Trophies",
    "wof:placetype":"venue"
},
  "geometry": {"coordinates":[-80.700254,28.079347],"type":"Point"}
}