{
  "type": "Feature",
  "properties": {
    "iso:country":"US",
    "sg:address":"6781 Park St",
    "sg:city":"Hollywood",
    "sg:classifiers":[
        {
            "category":"Building & Trades",
            "subcategory":"Landscaping Services",
            "type":"Services"
        }
    ],
    "sg:phone":"+1 954 989 0792",
    "sg:postcode":"33024",
    "sg:province":"FL",
    "wof:name":"Karen Helms Lawn Mntnce",
    "wof:placetype":"venue"
},
  "geometry": {"coordinates":[-80.222793,26.028208],"type":"Point"}
}