{
  "type": "Feature",
  "properties": {
    "addr:full":"480 W 84th St Ste 109 Hialeah FL 33014",
    "addr:housenumber":"480",
    "addr:postcode":"33014",
    "addr:street":"W 84Th St Ste 109",
    "iso:country":"US",
    "sg:address":"480 W 84th St Ste 109",
    "sg:city":"Hialeah",
    "sg:classifiers":[
        {
            "category":"Wholesale",
            "subcategory":"Medical Equipment & Supplies",
            "type":"Manufacturing & Wholesale Goods"
        },
        {
            "category":"Shopping",
            "subcategory":"Pharmacy",
            "type":"Retail Goods"
        }
    ],
    "sg:phone":"+1 305 698 1118",
    "sg:postcode":"33014",
    "sg:province":"FL",
    "sg:tags":[
        "home",
        "health",
        "care"
    ],
    "wof:name":"Marrero Home Service",
    "wof:placetype":"venue"
},
  "geometry": {"coordinates":[-80.29347199999999,25.898661],"type":"Point"}
}