{
  "type": "Feature",
  "properties": {
    "iso:country":"US",
    "sg:address":"4245 Homewood Ln",
    "sg:city":"Lakeland",
    "sg:classifiers":[
        {
            "category":"Real Estate",
            "subcategory":"Real Estate Agent",
            "type":"Services"
        }
    ],
    "sg:phone":"+1 863 698 4491",
    "sg:postcode":"33811",
    "sg:province":"FL",
    "wof:name":"Merritt Realty",
    "wof:placetype":"venue"
},
  "geometry": {"coordinates":[-82.03343,27.940956],"type":"Point"}
}