{
  "type": "Feature",
  "properties": {
    "addr:full":"3131 Palm Rd West Palm Beach FL 33409",
    "addr:housenumber":"3131",
    "addr:postcode":"33409",
    "addr:street":"Palm Rd",
    "iso:country":"US",
    "sg:address":"3131 Palm Rd",
    "sg:city":"West Palm Beach",
    "sg:classifiers":[
        {
            "category":"Professional",
            "subcategory":"Computer Services",
            "type":"Services"
        }
    ],
    "sg:phone":"+1 561 689 2549",
    "sg:postcode":"33409",
    "sg:province":"FL",
    "sg:tags":[
        "communications",
        "datum",
        "telephone"
    ],
    "wof:name":"Snakeye Designs",
    "wof:placetype":"venue"
},
  "geometry": {"coordinates":[-80.102414,26.72178],"type":"Point"}
}