{
  "type": "Feature",
  "properties": {
    "iso:country":"US",
    "sg:address":"2435 S Okeechobee Rd",
    "sg:city":"Hialeah",
    "sg:classifiers":[
        {
            "category":"Wholesale",
            "subcategory":"Groceries",
            "type":"Manufacturing & Wholesale Goods"
        }
    ],
    "sg:phone":"+1 305 883 5282",
    "sg:postcode":"33010",
    "sg:province":"FL",
    "wof:name":"Sopresa Bakery",
    "wof:placetype":"venue"
},
  "geometry": {"coordinates":[-80.309348,25.844274],"type":"Point"}
}