{
  "type": "Feature",
  "properties": {
    "iso:country":"US",
    "sg:address":"6774 Bakersfield Dr",
    "sg:city":"Jacksonville",
    "sg:classifiers":[
        {
            "category":"Real Estate",
            "subcategory":"Real Estate Operator",
            "type":"Services"
        }
    ],
    "sg:phone":"+1 904 786 7808",
    "sg:postcode":"32210",
    "sg:province":"FL",
    "sg:tags":[
        "property",
        "lessor"
    ],
    "wof:name":"Brymec L P",
    "wof:placetype":"venue"
},
  "geometry": {"coordinates":[-81.757418,30.288828],"type":"Point"}
}