{
  "type": "Feature",
  "properties": {
    "iso:country":"US",
    "sg:address":"1519 Yale Dr",
    "sg:city":"Hollywood",
    "sg:classifiers":[
        {
            "category":"Communications",
            "subcategory":"Film & Video Production",
            "type":"Services"
        },
        {
            "category":"Communications",
            "subcategory":"Television Station",
            "type":"Services"
        }
    ],
    "sg:phone":"+1 954 961 4715",
    "sg:postcode":"33021",
    "sg:province":"FL",
    "sg:tags":[
        "tv",
        "commercials-radio",
        "radio",
        "companies-film"
    ],
    "sg:website":"http://www.hdsuite.com",
    "wof:name":"Horizon Productions Inc",
    "wof:placetype":"venue"
},
  "geometry": {"coordinates":[-80.185057,26.023624],"type":"Point"}
}