{
  "type": "Feature",
  "properties": {
    "iso:country":"US",
    "sg:address":"484 Capri K",
    "sg:city":"Delray Beach",
    "sg:classifiers":[
        {
            "category":"Shopping",
            "subcategory":"Gifts & Souvenirs",
            "type":"Retail Goods"
        }
    ],
    "sg:phone":"+1 561 495 4733",
    "sg:postcode":"33484",
    "sg:province":"FL",
    "wof:name":"Gifts By Bernard",
    "wof:placetype":"venue"
},
  "geometry": {"coordinates":[-80.134608,26.439521],"type":"Point"}
}