{
  "type": "Feature",
  "properties": {
    "iso:country":"US",
    "sg:address":"223 Durango Rd",
    "sg:city":"Destin",
    "sg:classifiers":[
        {
            "category":"Government",
            "subcategory":"Office",
            "type":"Public Place"
        }
    ],
    "sg:phone":"+1 850 598 7777",
    "sg:postcode":"32541",
    "sg:province":"FL",
    "sg:tags":[
        "development"
    ],
    "wof:name":"Apollo Development",
    "wof:placetype":"venue"
},
  "geometry": {"coordinates":[-86.499099,30.38812],"type":"Point"}
}