{
  "type": "Feature",
  "properties": {
    "iso:country":"US",
    "sg:address":"1532 Stevenson Dr",
    "sg:city":"Clearwater",
    "sg:classifiers":[
        {
            "category":"Social Services",
            "subcategory":"Child Care",
            "type":"Services"
        }
    ],
    "sg:phone":"+1 727 461 4280",
    "sg:postcode":"33755",
    "sg:province":"FL",
    "wof:name":"Audrey Stolzer Inc",
    "wof:placetype":"venue"
},
  "geometry": {"coordinates":[-82.784902,27.981059],"type":"Point"}
}