{
  "type": "Feature",
  "properties": {
    "addr:full":"1488 Grove St Clearwater FL 33755",
    "addr:housenumber":"1488",
    "addr:postcode":"33755",
    "addr:street":"Grove St",
    "iso:country":"US",
    "sg:address":"1488 Grove St",
    "sg:city":"Clearwater",
    "sg:classifiers":[
        {
            "category":"Building & Trades",
            "subcategory":"Construction",
            "type":"Services"
        }
    ],
    "sg:phone":"+1 727 447 8160",
    "sg:postcode":"33755",
    "sg:province":"FL",
    "sg:tags":[
        "house"
    ],
    "wof:name":"Philip Geisler Services",
    "wof:placetype":"venue"
},
  "geometry": {"coordinates":[-82.77691299999999,27.967338],"type":"Point"}
}