{
  "type": "Feature",
  "properties": {
    "addr:full":"522 Garland Cir Indian Rocks Beach FL 33785",
    "addr:housenumber":"522",
    "addr:postcode":"33785",
    "addr:street":"Garland Cir",
    "iso:country":"US",
    "sg:address":"522 Garland Cir",
    "sg:city":"Indian Rocks Beach",
    "sg:classifiers":[
        {
            "category":"Banks & Credit Unions",
            "subcategory":"Bank",
            "type":"Services"
        }
    ],
    "sg:phone":"+1 727 518 9077",
    "sg:postcode":"33785",
    "sg:province":"FL",
    "sg:tags":[
        "broker",
        "mortgage"
    ],
    "wof:name":"All Family Financial LLC",
    "wof:placetype":"venue"
},
  "geometry": {"coordinates":[-82.84789000000001,27.88746],"type":"Point"}
}