{
  "type": "Feature",
  "properties": {
    "addr:full":"5311 NW 35th Ter Fort Lauderdale FL 33309",
    "addr:housenumber":"5311",
    "addr:postcode":"33309",
    "addr:street":"Nw 35Th Ter",
    "iso:country":"US",
    "sg:address":"5311 NW 35th Ter",
    "sg:city":"Fort Lauderdale",
    "sg:classifiers":[
        {
            "category":"Shopping",
            "subcategory":"Clothing, Apparel, & Fashions",
            "type":"Retail Goods"
        }
    ],
    "sg:phone":"+1 954 730 8189",
    "sg:postcode":"33309",
    "sg:province":"FL",
    "sg:tags":[
        "lingerie"
    ],
    "sg:website":"www.anita.com",
    "wof:name":"Anita International Corp",
    "wof:placetype":"venue"
},
  "geometry": {"coordinates":[-80.198268,26.190938],"type":"Point"}
}