{
  "type": "Feature",
  "properties": {
    "iso:country":"US",
    "sg:address":"4313 W Beach Park Dr",
    "sg:city":"Tampa",
    "sg:classifiers":[
        {
            "category":"Wholesale",
            "subcategory":"Machinery & Supplies",
            "type":"Manufacturing & Wholesale Goods"
        }
    ],
    "sg:phone":"+1 813 286 8634",
    "sg:postcode":"33609",
    "sg:province":"FL",
    "sg:tags":[
        "equipment",
        "industrial"
    ],
    "wof:name":"Indoff 171",
    "wof:placetype":"venue"
},
  "geometry": {"coordinates":[-82.517954,27.938735],"type":"Point"}
}