{
  "type": "Feature",
  "properties": {
    "addr:full":"3483 NE Indian Ct Jensen Beach FL 34957",
    "addr:housenumber":"3483",
    "addr:postcode":"34957",
    "addr:street":"Ne Indian Ct",
    "iso:country":"US",
    "sg:address":"3483 NE Indian Ct",
    "sg:city":"Jensen Beach",
    "sg:classifiers":[
        {
            "category":"Building & Trades",
            "subcategory":"Construction",
            "type":"Services"
        }
    ],
    "sg:phone":"+1 772 334 8909",
    "sg:postcode":"34957",
    "sg:province":"FL",
    "sg:tags":[
        "carpentry",
        "contractor"
    ],
    "wof:name":"Kents Karpentry & Painting",
    "wof:placetype":"venue"
},
  "geometry": {"coordinates":[-80.231408,27.247279],"type":"Point"}
}