{
  "type": "Feature",
  "properties": {
    "addr:full":"5807 Breckenridge Pkwy Tampa FL 33610",
    "addr:housenumber":"5807",
    "addr:postcode":"33610",
    "addr:street":"Breckenridge Pkwy",
    "iso:country":"US",
    "sg:address":"5807 Breckenridge Pkwy",
    "sg:city":"Tampa",
    "sg:classifiers":[
        {
            "category":"Building & Trades",
            "subcategory":"Construction",
            "type":"Services"
        }
    ],
    "sg:phone":"+1 813 635 9007",
    "sg:postcode":"33610",
    "sg:province":"FL",
    "sg:tags":[
        "development",
        "contractor"
    ],
    "wof:name":"W Jackson & Son Construction",
    "wof:placetype":"venue"
},
  "geometry": {"coordinates":[-82.357907,28.006326],"type":"Point"}
}