{
  "type": "Feature",
  "properties": {
    "addr:full":"902 S US Hwy 1 Jupiter FL 33477",
    "addr:housenumber":"902",
    "addr:postcode":"33477",
    "addr:street":"S Us Hwy 1",
    "iso:country":"US",
    "sg:address":"902 S US Hwy 1",
    "sg:city":"Jupiter",
    "sg:classifiers":[
        {
            "category":"Banks & Credit Unions",
            "subcategory":"Bank",
            "type":"Services"
        }
    ],
    "sg:phone":"+1 561 575 9161",
    "sg:postcode":"33477",
    "sg:province":"FL",
    "sg:tags":[
        "broker",
        "mortgage"
    ],
    "wof:name":"Preferred Florida Mortgages",
    "wof:placetype":"venue"
},
  "geometry": {"coordinates":[-80.076294,26.925069],"type":"Point"}
}