{
  "type": "Feature",
  "properties": {
    "addr:full":"2928 Avon Rd Panama City FL 32405",
    "addr:housenumber":"2928",
    "addr:postcode":"32405",
    "addr:street":"Avon Rd",
    "iso:country":"US",
    "sg:address":"2928 Avon Rd",
    "sg:city":"Panama City",
    "sg:classifiers":[
        {
            "category":"Organizations",
            "subcategory":"Community Association",
            "type":"Services"
        }
    ],
    "sg:phone":"+1 850 785 5264",
    "sg:postcode":"32405",
    "sg:province":"FL",
    "wof:name":"Military Order of Cootie",
    "wof:placetype":"venue"
},
  "geometry": {"coordinates":[-85.61965499999999,30.196763],"type":"Point"}
}