{
  "type": "Feature",
  "properties": {
    "addr:full":"8479 15th Way N St Petersburg FL 33702",
    "addr:housenumber":"8479",
    "addr:postcode":"33702",
    "addr:street":"15Th Way N",
    "iso:country":"US",
    "sg:address":"8479 15th Way N",
    "sg:city":"St Petersburg",
    "sg:classifiers":[
        {
            "category":"Professional",
            "type":"Services"
        }
    ],
    "sg:phone":"+1 727 209 0751",
    "sg:postcode":"33702",
    "sg:province":"FL",
    "sg:tags":[
        "establishment"
    ],
    "wof:name":"Mark Manning",
    "wof:placetype":"venue"
},
  "geometry": {"coordinates":[-82.654487,27.848722],"type":"Point"}
}