{
  "type": "Feature",
  "properties": {
    "iso:country":"US",
    "sg:address":"3520 N Monroe St",
    "sg:city":"Tallahassee",
    "sg:classifiers":[
        {
            "category":"Health Services",
            "subcategory":"Medical Lab",
            "type":"Services"
        }
    ],
    "sg:phone":"+1 850 562 7774",
    "sg:postcode":"32303",
    "sg:province":"FL",
    "sg:tags":[
        "detection",
        "equipment",
        "drug"
    ],
    "wof:name":"Paramedical Services Inc",
    "wof:placetype":"venue"
},
  "geometry": {"coordinates":[-84.32576400000001,30.495505],"type":"Point"}
}