{
  "type": "Feature",
  "properties": {
    "iso:country":"US",
    "sg:address":"7114 SW 117th Ave",
    "sg:city":"Miami",
    "sg:classifiers":[
        {
            "category":"Personal",
            "subcategory":"Beauty Salon",
            "type":"Services"
        },
        {
            "category":"Personal",
            "subcategory":"Day Spa",
            "type":"Services"
        }
    ],
    "sg:phone":"+1 305 274 1805",
    "sg:postcode":"33183",
    "sg:province":"FL",
    "sg:website":"www.mayrasartandspa.com",
    "wof:name":"Mayra's Art Spa",
    "wof:placetype":"venue"
},
  "geometry": {"coordinates":[-80.382434,25.701338],"type":"Point"}
}