{
  "type": "Feature",
  "properties": {
    "iso:country":"US",
    "sg:address":"2416 US Hwy 301",
    "sg:city":"Ellenton",
    "sg:classifiers":[
        {
            "category":"Building & Trades",
            "subcategory":"Construction",
            "type":"Services"
        }
    ],
    "sg:phone":"+1 941 722 3565",
    "sg:postcode":"34222",
    "sg:province":"FL",
    "sg:tags":[
        "heavy"
    ],
    "wof:name":"Collier Marine Development",
    "wof:placetype":"venue"
},
  "geometry": {"coordinates":[-82.539177,27.521773],"type":"Point"}
}