{
  "type": "Feature",
  "properties": {
    "addr:full":"1790 SW 22nd St Coral Gables FL 33145",
    "addr:housenumber":"1790",
    "addr:postcode":"33145",
    "addr:street":"Sw 22Nd St",
    "iso:country":"US",
    "sg:address":"1790 SW 22nd St",
    "sg:city":"Coral Gables",
    "sg:classifiers":[
        {
            "category":"Wholesale",
            "subcategory":"Computers",
            "type":"Manufacturing & Wholesale Goods"
        }
    ],
    "sg:phone":"+1 305 285 1380",
    "sg:postcode":"33145",
    "sg:province":"FL",
    "sg:tags":[
        "information",
        "retrieval"
    ],
    "wof:name":"Netting Solutions",
    "wof:placetype":"venue"
},
  "geometry": {"coordinates":[-80.222336,25.750785],"type":"Point"}
}