{
  "type": "Feature",
  "properties": {
    "iso:country":"US",
    "sg:address":"321 E New Haven Ave",
    "sg:city":"Melbourne",
    "sg:classifiers":[
        {
            "category":"Retail",
            "subcategory":"Auto Repair",
            "type":"Services"
        }
    ],
    "sg:phone":"+1 321 723 3229",
    "sg:postcode":"32901",
    "sg:province":"FL",
    "sg:tags":[
        "automobile",
        "accessory",
        "truck",
        "glass"
    ],
    "wof:name":"Auto One of Melbourne",
    "wof:placetype":"venue"
},
  "geometry": {"coordinates":[-80.61497300000001,28.078514],"type":"Point"}
}