{
  "type": "Feature",
  "properties": {
    "iso:country":"US",
    "sg:address":"845 NE 79th St",
    "sg:city":"Miami",
    "sg:classifiers":[
        {
            "category":"Professional",
            "subcategory":"Lawyer & Legal Services",
            "type":"Services"
        }
    ],
    "sg:phone":"+1 305 759 8262",
    "sg:postcode":"33138",
    "sg:province":"FL",
    "sg:tags":[
        "attorney",
        "practice",
        "immigration",
        "law"
    ],
    "sg:website":"http://www.accesslawyer.com",
    "wof:name":"Access USA Lawyer Inc",
    "wof:placetype":"venue"
},
  "geometry": {"coordinates":[-80.179157,25.847999],"type":"Point"}
}