{
  "type": "Feature",
  "properties": {
    "addr:full":"1039 N Paul Dr Inverness FL 34453",
    "addr:housenumber":"1039",
    "addr:postcode":"34453",
    "addr:street":"N Paul Dr",
    "iso:country":"US",
    "sg:address":"1039 N Paul Dr",
    "sg:city":"Inverness",
    "sg:classifiers":[
        {
            "category":"Organizations",
            "subcategory":"Community Association",
            "type":"Services"
        }
    ],
    "sg:phone":"+1 352 341 6875",
    "sg:postcode":"34453",
    "sg:province":"FL",
    "wof:name":"Disabled American Veterans",
    "wof:placetype":"venue"
},
  "geometry": {"coordinates":[-82.364386,28.877951],"type":"Point"}
}