{
  "type": "Feature",
  "properties": {
    "addr:full":"1626 Riggins Rd Tallahassee FL 32308",
    "addr:housenumber":"1626",
    "addr:postcode":"32308",
    "addr:street":"Riggins Rd",
    "iso:country":"US",
    "sg:address":"1626 Riggins Rd",
    "sg:city":"Tallahassee",
    "sg:classifiers":[
        {
            "category":"Health Services",
            "subcategory":"Doctor",
            "type":"Services"
        }
    ],
    "sg:phone":"+1 850 877 2787",
    "sg:postcode":"32308",
    "sg:province":"FL",
    "sg:tags":[
        "clinic"
    ],
    "sg:website":"www.medisyn.com",
    "wof:name":"Medi Syn Inc",
    "wof:placetype":"venue"
},
  "geometry": {"coordinates":[-84.23760900000001,30.45852],"type":"Point"}
}