{
  "type": "Feature",
  "properties": {
    "addr:full":"181 Library Rd Jacksonville FL 32225",
    "addr:housenumber":"181",
    "addr:postcode":"32225",
    "addr:street":"Library Rd",
    "iso:country":"US",
    "sg:address":"181 Library Rd",
    "sg:city":"Jacksonville",
    "sg:classifiers":[
        {
            "category":"Retail",
            "subcategory":"Auto Repair",
            "type":"Services"
        }
    ],
    "sg:phone":"+1 904 721 3664",
    "sg:postcode":"32225",
    "sg:province":"FL",
    "sg:tags":[
        "lubricating"
    ],
    "wof:name":"Prolube",
    "wof:placetype":"venue"
},
  "geometry": {"coordinates":[-81.543374,30.325134],"type":"Point"}
}