{
  "type": "Feature",
  "properties": {
    "iso:country":"US",
    "sg:address":"13015 Middlefield Rd",
    "sg:city":"Tallahassee",
    "sg:classifiers":[
        {
            "category":"Shopping",
            "subcategory":"Florist",
            "type":"Retail Goods"
        }
    ],
    "sg:phone":"+1 850 893 6856",
    "sg:postcode":"32309",
    "sg:province":"FL",
    "wof:name":"Vicki D Cureton Florist",
    "wof:placetype":"venue"
},
  "geometry": {"coordinates":[-84.045446,30.54406],"type":"Point"}
}