{
  "type": "Feature",
  "properties": {
    "iso:country":"US",
    "sg:address":"3218 Button Wood Dr",
    "sg:city":"Middleburg",
    "sg:classifiers":[
        {
            "category":"Building & Trades",
            "subcategory":"Construction",
            "type":"Services"
        }
    ],
    "sg:phone":"+1 904 213 0123",
    "sg:postcode":"32068",
    "sg:province":"FL",
    "sg:tags":[
        "house"
    ],
    "wof:name":"Kjs Construction Inc",
    "wof:placetype":"venue"
},
  "geometry": {"coordinates":[-81.78815899999999,30.106345],"type":"Point"}
}