{
  "type": "Feature",
  "properties": {
    "iso:country":"US",
    "sg:address":"6135 NW 167th St",
    "sg:city":"Hialeah",
    "sg:classifiers":[
        {
            "category":"Real Estate",
            "subcategory":"Architect",
            "type":"Services"
        }
    ],
    "sg:phone":"+1 305 826 6600",
    "sg:postcode":"33015",
    "sg:province":"FL",
    "sg:tags":[
        "building",
        "construction"
    ],
    "wof:name":"Engineered Construction-S Fl",
    "wof:placetype":"venue"
},
  "geometry": {"coordinates":[-80.304569,25.925209],"type":"Point"}
}