{
  "type": "Feature",
  "properties": {
    "addr:full":"13970 SE 47th Street Rd Ocklawaha FL 32179",
    "addr:housenumber":"13970",
    "addr:postcode":"32179",
    "addr:street":"Se 47Th Street Rd",
    "iso:country":"US",
    "sg:address":"13970 SE 47th Street Rd",
    "sg:city":"Ocklawaha",
    "sg:classifiers":[
        {
            "category":"Professional",
            "type":"Services"
        }
    ],
    "sg:phone":"+1 352 625 8877",
    "sg:postcode":"32179",
    "sg:province":"FL",
    "wof:name":"Jam Envrnmntal Svcs Consulting",
    "wof:placetype":"venue"
},
  "geometry": {"coordinates":[-81.918668,29.13879],"type":"Point"}
}