{
  "type": "Feature",
  "properties": {
    "iso:country":"US",
    "sg:address":"8370 W Flagler St Ste 246",
    "sg:city":"Miami",
    "sg:classifiers":[
        {
            "category":"Personal",
            "subcategory":"Skin Care",
            "type":"Services"
        }
    ],
    "sg:phone":"+1 305 552 7507",
    "sg:postcode":"33144",
    "sg:province":"FL",
    "wof:name":"Siluetas",
    "wof:placetype":"venue"
},
  "geometry": {"coordinates":[-80.331344,25.769614],"type":"Point"}
}