{
  "type": "Feature",
  "properties": {
    "iso:country":"US",
    "sg:address":"1489 Meadowbrook Rd NE",
    "sg:city":"Melbourne",
    "sg:classifiers":[
        {
            "category":"Home & Garden",
            "subcategory":"Garden Supply",
            "type":"Retail Goods"
        }
    ],
    "sg:phone":"+1 321 676 4769",
    "sg:postcode":"32905",
    "sg:province":"FL",
    "sg:tags":[
        "sprinkler"
    ],
    "wof:name":"All Brevard Irrigation",
    "wof:placetype":"venue"
},
  "geometry": {"coordinates":[-80.62932000000001,28.014132],"type":"Point"}
}