{
  "type": "Feature",
  "properties": {
    "addr:full":"1712 NW 82nd Ave Doral FL 33126",
    "addr:housenumber":"1712",
    "addr:postcode":"33126",
    "addr:street":"Nw 82Nd Ave",
    "iso:country":"US",
    "sg:address":"1712 NW 82nd Ave",
    "sg:city":"Doral",
    "sg:classifiers":[
        {
            "category":"Professional",
            "subcategory":"Detective & Security Services",
            "type":"Services"
        },
        {
            "category":"Manufacturing",
            "subcategory":"Electronics",
            "type":"Manufacturing & Wholesale Goods"
        }
    ],
    "sg:phone":"+1 305 639 2454",
    "sg:postcode":"33126",
    "sg:province":"FL",
    "sg:tags":[
        "control",
        "monitoring",
        "equipment-wholesale",
        "consultant",
        "system",
        "equipment",
        "manufacturer"
    ],
    "wof:name":"A1 Security Supply Inc",
    "wof:placetype":"venue"
},
  "geometry": {"coordinates":[-80.32883,25.789965],"type":"Point"}
}