{
  "type": "Feature",
  "properties": {
    "addr:full":"2332 E 16th St Panama City FL 32405",
    "addr:housenumber":"2332",
    "addr:postcode":"32405",
    "addr:street":"E 16Th St",
    "iso:country":"US",
    "sg:address":"2332 E 16th St",
    "sg:city":"Panama City",
    "sg:classifiers":[
        {
            "category":"Building & Trades",
            "subcategory":"Construction",
            "type":"Services"
        }
    ],
    "sg:phone":"+1 850 763 4784",
    "sg:postcode":"32405",
    "sg:province":"FL",
    "sg:tags":[
        "home",
        "improvement"
    ],
    "wof:name":"Fresh Quality Painting",
    "wof:placetype":"venue"
},
  "geometry": {"coordinates":[-85.63,30.176201],"type":"Point"}
}