{
  "type": "Feature",
  "properties": {
    "addr:full":"6432 US Hwy 27 Sebring FL 33876",
    "addr:housenumber":"6432",
    "addr:postcode":"33876",
    "addr:street":"Us Hwy 27",
    "iso:country":"US",
    "sg:address":"6432 US Hwy 27",
    "sg:city":"Sebring",
    "sg:classifiers":[
        {
            "category":"Insurance",
            "subcategory":"Insurance Agent",
            "type":"Services"
        }
    ],
    "sg:phone":"+1 863 382 0131",
    "sg:postcode":"33876",
    "sg:province":"FL",
    "wof:name":"Advanced Insur Underwriters",
    "wof:placetype":"venue"
},
  "geometry": {"coordinates":[-81.41986300000001,27.448837],"type":"Point"}
}