{
  "type": "Feature",
  "properties": {
    "addr:full":"10961 SW 120th St Miami FL 33176",
    "addr:housenumber":"10961",
    "addr:postcode":"33176",
    "addr:street":"Sw 120Th St",
    "iso:country":"US",
    "sg:address":"10961 SW 120th St",
    "sg:city":"Miami",
    "sg:classifiers":[
        {
            "category":"Food & Beverages",
            "subcategory":"Groceries & Convenience Stores",
            "type":"Retail Goods"
        }
    ],
    "sg:phone":"+1 305 233 9442",
    "sg:postcode":"33176",
    "sg:province":"FL",
    "sg:tags":[
        "natural"
    ],
    "wof:name":"Naturavit Inc",
    "wof:placetype":"venue"
},
  "geometry": {"coordinates":[-80.372274,25.657272],"type":"Point"}
}