{
  "type": "Feature",
  "properties": {
    "iso:country":"US",
    "sg:address":"2840 Ave of the Americas",
    "sg:city":"Englewood",
    "sg:classifiers":[
        {
            "category":"Home & Garden",
            "subcategory":"Building Materials",
            "type":"Retail Goods"
        },
        {
            "category":"Building & Trades",
            "subcategory":"Construction",
            "type":"Services"
        }
    ],
    "sg:phone":"+1 941 475 1281",
    "sg:postcode":"34224",
    "sg:province":"FL",
    "sg:tags":[
        "plate",
        "installation",
        "contractor",
        "glass",
        "window",
        "mirror"
    ],
    "wof:name":"Lemon Bay Glass & Mirror",
    "wof:placetype":"venue"
},
  "geometry": {"coordinates":[-82.310925,26.91882],"type":"Point"}
}