{
  "type": "Feature",
  "properties": {
    "iso:country":"US",
    "sg:address":"5887 NW 25th Ct",
    "sg:city":"Boca Raton",
    "sg:classifiers":[
        {
            "category":"Professional",
            "type":"Services"
        }
    ],
    "sg:phone":"+1 561 997 9082",
    "sg:postcode":"33496",
    "sg:province":"FL",
    "wof:name":"Mark Florine",
    "wof:placetype":"venue"
},
  "geometry": {"coordinates":[-80.140939,26.401204],"type":"Point"}
}