{
  "type": "Feature",
  "properties": {
    "iso:country":"US",
    "sg:address":"3075 NW 56th St",
    "sg:city":"Miami",
    "sg:classifiers":[
        {
            "category":"Recreation",
            "type":"Entertainment"
        }
    ],
    "sg:phone":"+1 305 635 1912",
    "sg:postcode":"33142",
    "sg:province":"FL",
    "sg:tags":[
        "entertainers-family",
        "business"
    ],
    "wof:name":"Kahmeleon Entertainments",
    "wof:placetype":"venue"
},
  "geometry": {"coordinates":[-80.24646300000001,25.825567],"type":"Point"}
}