{
  "type": "Feature",
  "properties": {
    "iso:country":"US",
    "sg:address":"575 North St",
    "sg:city":"Longwood",
    "sg:classifiers":[
        {
            "category":"Professional",
            "subcategory":"Research",
            "type":"Services"
        }
    ],
    "sg:phone":"+1 407 834 2828",
    "sg:postcode":"32750",
    "sg:province":"FL",
    "sg:tags":[
        "development",
        "laboratory"
    ],
    "sg:website":"www.rdc-inc.com",
    "wof:name":"Research & Development Ind Inc",
    "wof:placetype":"venue"
},
  "geometry": {"coordinates":[-81.35830300000001,28.683146],"type":"Point"}
}