{
  "type": "Feature",
  "properties": {
    "iso:country":"US",
    "sg:address":"6432 Edgewater Dr",
    "sg:city":"Orlando",
    "sg:classifiers":[
        {
            "category":"Home & Garden",
            "subcategory":"Carpets & Floor Coverings",
            "type":"Retail Goods"
        }
    ],
    "sg:phone":"+1 407 290 2493",
    "sg:postcode":"32810",
    "sg:province":"FL",
    "sg:tags":[
        "mattress"
    ],
    "wof:name":"Buy Rite Furniture",
    "wof:placetype":"venue"
},
  "geometry": {"coordinates":[-81.425797,28.6154],"type":"Point"}
}