{
  "type": "Feature",
  "properties": {
    "addr:full":"106 Alhambra Ave Altamonte Spgs FL 32714",
    "addr:housenumber":"106",
    "addr:postcode":"32714",
    "addr:street":"Alhambra Ave;Spgs",
    "iso:country":"US",
    "sg:address":"106 Alhambra Ave",
    "sg:city":"Altamonte Spgs",
    "sg:classifiers":[
        {
            "category":"Building & Trades",
            "subcategory":"Construction",
            "type":"Services"
        }
    ],
    "sg:phone":"+1 407 389 0476",
    "sg:postcode":"32714",
    "sg:province":"FL",
    "sg:tags":[
        "general",
        "contractor"
    ],
    "wof:name":"GGNR Contractors Inc",
    "wof:placetype":"venue"
},
  "geometry": {"coordinates":[-81.42652,28.668389],"type":"Point"}
}