{
  "type": "Feature",
  "properties": {
    "iso:country":"US",
    "sg:address":"5202 S Macdill Ave",
    "sg:city":"Tampa",
    "sg:classifiers":[
        {
            "category":"Building & Trades",
            "subcategory":"Construction",
            "type":"Services"
        }
    ],
    "sg:phone":"+1 813 837 6272",
    "sg:postcode":"33611",
    "sg:province":"FL",
    "sg:tags":[
        "carpentry",
        "contractor"
    ],
    "wof:name":"Beveled Edge",
    "wof:placetype":"venue"
},
  "geometry": {"coordinates":[-82.493825,27.889229],"type":"Point"}
}