{
  "type": "Feature",
  "properties": {
    "iso:country":"US",
    "sg:address":"9716 Pines Blvd",
    "sg:city":"Hollywood",
    "sg:classifiers":[
        {
            "category":"Banks & Credit Unions",
            "subcategory":"Bank",
            "type":"Services"
        }
    ],
    "sg:phone":"+1 954 538 9042",
    "sg:postcode":"33024",
    "sg:province":"FL",
    "sg:tags":[
        "mortgage"
    ],
    "wof:name":"Peoples Mortgage Funding Group",
    "wof:placetype":"venue"
},
  "geometry": {"coordinates":[-80.27446999999999,26.008468],"type":"Point"}
}