{
  "type": "Feature",
  "properties": {
    "addr:full":"3310 SW Pine Island Rd Cape Coral FL 33991",
    "addr:housenumber":"3310",
    "addr:postcode":"33991",
    "addr:street":"Sw Pine Island Rd",
    "iso:country":"US",
    "sg:address":"3310 SW Pine Island Rd",
    "sg:city":"Cape Coral",
    "sg:classifiers":[
        {
            "category":"Organizations",
            "subcategory":"Religious Organization",
            "type":"Services"
        }
    ],
    "sg:phone":"+1 239 283 2446",
    "sg:postcode":"33991",
    "sg:province":"FL",
    "sg:tags":[
        "church"
    ],
    "wof:name":"First Baptist Church-Matlacha",
    "wof:placetype":"venue"
},
  "geometry": {"coordinates":[-82.062338,26.637249],"type":"Point"}
}