{
  "type": "Feature",
  "properties": {
    "addr:full":"930 Mar Walt Dr Fort Walton Beach FL 32547",
    "addr:housenumber":"930",
    "addr:postcode":"32547",
    "addr:street":"Mar Walt Dr",
    "iso:country":"US",
    "sg:address":"930 Mar Walt Dr",
    "sg:city":"Fort Walton Beach",
    "sg:classifiers":[
        {
            "category":"Shopping",
            "type":"Retail Goods"
        }
    ],
    "sg:phone":"+1 850 863 5959",
    "sg:postcode":"32547",
    "sg:province":"FL",
    "sg:tags":[
        "merchandise"
    ],
    "wof:name":"Bay Prosthetic Center",
    "wof:placetype":"venue"
},
  "geometry": {"coordinates":[-86.632192,30.452089],"type":"Point"}
}