{
  "type": "Feature",
  "properties": {
    "iso:country":"US",
    "sg:address":"1724 S Woodland Blvd",
    "sg:city":"Deland",
    "sg:classifiers":[
        {
            "category":"Shopping",
            "subcategory":"Beauty & Cosmetics",
            "type":"Retail Goods"
        },
        {
            "category":"Personal",
            "subcategory":"Barber",
            "type":"Services"
        },
        {
            "category":"Personal",
            "subcategory":"Beauty Salon",
            "type":"Services"
        }
    ],
    "sg:phone":"+1 386 740 8480",
    "sg:postcode":"32720",
    "sg:province":"FL",
    "sg:tags":[
        "equipment",
        "perfume",
        "salons-equipment",
        "supply"
    ],
    "wof:name":"Deland Beauty Care",
    "wof:placetype":"venue"
},
  "geometry": {"coordinates":[-81.302803,28.998501],"type":"Point"}
}