{
  "type": "Feature",
  "properties": {
    "addr:full":"220 S Holly Ave Sanford FL 32771",
    "addr:housenumber":"220",
    "addr:postcode":"32771",
    "addr:street":"S Holly Ave",
    "iso:country":"US",
    "sg:address":"220 S Holly Ave",
    "sg:city":"Sanford",
    "sg:classifiers":[
        {
            "category":"Autos & Motor Vehicles",
            "subcategory":"Automobile Sales",
            "type":"Retail Goods"
        }
    ],
    "sg:phone":"+1 407 323 1209",
    "sg:postcode":"32771",
    "sg:province":"FL",
    "sg:tags":[
        "used"
    ],
    "wof:name":"GM Auto Sales Inc",
    "wof:placetype":"venue"
},
  "geometry": {"coordinates":[-81.2753,28.810047],"type":"Point"}
}