{
  "type": "Feature",
  "properties": {
    "addr:full":"6914 N Clark Ave Tampa FL 33614",
    "addr:housenumber":"6914",
    "addr:postcode":"33614",
    "addr:street":"N Clark Ave",
    "iso:country":"US",
    "sg:address":"6914 N Clark Ave",
    "sg:city":"Tampa",
    "sg:classifiers":[
        {
            "category":"Retail",
            "subcategory":"Car Wash",
            "type":"Services"
        }
    ],
    "sg:phone":"+1 813 885 1886",
    "sg:postcode":"33614",
    "sg:province":"FL",
    "sg:tags":[
        "carwash"
    ],
    "wof:name":"Kiwkie Wash",
    "wof:placetype":"venue"
},
  "geometry": {"coordinates":[-82.511821,28.012354],"type":"Point"}
}