{
  "type": "Feature",
  "properties": {
    "addr:full":"13623 Rhodine Rd Riverview FL 33579",
    "addr:housenumber":"13623",
    "addr:postcode":"33579",
    "addr:street":"Rhodine Rd",
    "iso:country":"US",
    "sg:address":"13623 Rhodine Rd",
    "sg:city":"Riverview",
    "sg:classifiers":[
        {
            "category":"Shopping",
            "subcategory":"Computers & Home Electronics",
            "type":"Retail Goods"
        }
    ],
    "sg:phone":"+1 813 657 7460",
    "sg:postcode":"33579",
    "sg:province":"FL",
    "sg:tags":[
        "television",
        "radio"
    ],
    "wof:name":"Lotus TV Of Tampa LLC",
    "wof:placetype":"venue"
},
  "geometry": {"coordinates":[-81.68732,30.406072],"type":"Point"}
}