{
  "type": "Feature",
  "properties": {
    "iso:country":"US",
    "sg:address":"37 Skyline Dr",
    "sg:city":"Lake Mary",
    "sg:classifiers":[
        {
            "category":"Wholesale",
            "subcategory":"Hardware",
            "type":"Manufacturing & Wholesale Goods"
        }
    ],
    "sg:phone":"+1 407 444 2261",
    "sg:postcode":"32746",
    "sg:province":"FL",
    "sg:tags":[
        "conditioner",
        "air"
    ],
    "wof:name":"York International Sls & Svcs",
    "wof:placetype":"venue"
},
  "geometry": {"coordinates":[-81.368201,28.739414],"type":"Point"}
}