{
  "type": "Feature",
  "properties": {
    "iso:country":"US",
    "sg:address":"541 S Scott St",
    "sg:city":"Bainbridge",
    "sg:classifiers":[
        {
            "category":"Banks & Credit Unions",
            "subcategory":"Bank",
            "type":"Services"
        }
    ],
    "sg:phone":"+1 229 243 7007",
    "sg:postcode":"39819",
    "sg:province":"FL",
    "sg:tags":[
        "cashing",
        "check"
    ],
    "wof:name":"Cash Two You",
    "wof:placetype":"venue"
},
  "geometry": {"coordinates":[-84.56785000000001,30.901351],"type":"Point"}
}