{
  "type": "Feature",
  "properties": {
    "addr:full":"300 Gatlin Ave Orlando FL 32806",
    "addr:housenumber":"300",
    "addr:postcode":"32806",
    "addr:street":"Gatlin Ave",
    "iso:country":"US",
    "sg:address":"300 Gatlin Ave",
    "sg:city":"Orlando",
    "sg:classifiers":[
        {
            "category":"Health Services",
            "subcategory":"Doctor",
            "type":"Services"
        }
    ],
    "sg:phone":"+1 407 438 3777",
    "sg:postcode":"32806",
    "sg:province":"FL",
    "sg:tags":[
        "dentist"
    ],
    "wof:name":"Ignacio A Baez DDS",
    "wof:placetype":"venue"
},
  "geometry": {"coordinates":[-81.37382100000001,28.493718],"type":"Point"}
}