{
  "type": "Feature",
  "properties": {
    "iso:country":"US",
    "sg:address":"2719 SW 1st Pl",
    "sg:city":"Cape Coral",
    "sg:classifiers":[
        {
            "category":"Personal",
            "type":"Services"
        }
    ],
    "sg:phone":"+1 239 573 6872",
    "sg:postcode":"33914",
    "sg:province":"FL",
    "sg:tags":[
        "wedding",
        "chapel"
    ],
    "wof:name":"USA Wedding Directory Inc",
    "wof:placetype":"venue"
},
  "geometry": {"coordinates":[-81.977101,26.602595],"type":"Point"}
}