{
  "type": "Feature",
  "properties": {
    "iso:country":"US",
    "sg:address":"2779 Peters Rd",
    "sg:city":"Fort Pierce",
    "sg:classifiers":[
        {
            "category":"Shopping",
            "subcategory":"Shoes",
            "type":"Retail Goods"
        }
    ],
    "sg:phone":"+1 772 489 0301",
    "sg:postcode":"34945",
    "sg:province":"FL",
    "wof:name":"Bass Shoe Factory Outlet 253",
    "wof:placetype":"venue"
},
  "geometry": {"coordinates":[-80.391711,27.415825],"type":"Point"}
}