{
  "type": "Feature",
  "properties": {
    "iso:country":"US",
    "sg:address":"8646 NW 54th St",
    "sg:city":"Pompano Beach",
    "sg:classifiers":[
        {
            "category":"Organizations",
            "subcategory":"Professional Association",
            "type":"Services"
        }
    ],
    "sg:phone":"+1 954 796 4447",
    "sg:postcode":"33067",
    "sg:province":"FL",
    "sg:tags":[
        "business"
    ],
    "wof:name":"Helms Briscoe",
    "wof:placetype":"venue"
},
  "geometry": {"coordinates":[-80.24193,26.296506],"type":"Point"}
}