{
  "type": "Feature",
  "properties": {
    "addr:full":"1400 N Hercules Ave Clearwater FL 33765",
    "addr:housenumber":"1400",
    "addr:postcode":"33765",
    "addr:street":"N Hercules Ave",
    "iso:country":"US",
    "sg:address":"1400 N Hercules Ave",
    "sg:city":"Clearwater",
    "sg:classifiers":[
        {
            "category":"Food & Beverages",
            "subcategory":"Groceries & Convenience Stores",
            "type":"Retail Goods"
        }
    ],
    "sg:phone":"+1 727 442 2562",
    "sg:postcode":"33765",
    "sg:province":"FL",
    "wof:name":"Dokken Racing",
    "wof:placetype":"venue"
},
  "geometry": {"coordinates":[-82.75462,27.979516],"type":"Point"}
}