{
  "type": "Feature",
  "properties": {
    "addr:full":"138 Palm Coast Pkwy NE Palm Coast FL 32137",
    "addr:housenumber":"138",
    "addr:postcode":"32137",
    "addr:street":"Palm Coast Pkwy Ne",
    "iso:country":"US",
    "sg:address":"138 Palm Coast Pkwy NE",
    "sg:city":"Palm Coast",
    "sg:classifiers":[
        {
            "category":"Education",
            "subcategory":"Special Training",
            "type":"Public Place"
        }
    ],
    "sg:phone":"+1 386 446 8008",
    "sg:postcode":"32137",
    "sg:province":"FL",
    "wof:name":"Corperate Cntributions Academy",
    "wof:placetype":"venue"
},
  "geometry": {"coordinates":[-81.19271999999999,29.564608],"type":"Point"}
}