{
  "type": "Feature",
  "properties": {
    "iso:country":"US",
    "sg:address":"3551 Bluebird Ave",
    "sg:city":"Lake Placid",
    "sg:classifiers":[
        {
            "category":"Building & Trades",
            "subcategory":"Landscaping Services",
            "type":"Services"
        }
    ],
    "sg:phone":"+1 863 465 4334",
    "sg:postcode":"33852",
    "sg:province":"FL",
    "wof:name":"Aquatic Plus Inc",
    "wof:placetype":"venue"
},
  "geometry": {"coordinates":[-81.46278100000001,27.340908],"type":"Point"}
}