{
  "type": "Feature",
  "properties": {
    "iso:country":"US",
    "sg:address":"1260 NE 115th St",
    "sg:city":"Miami",
    "sg:classifiers":[
        {
            "category":"Real Estate",
            "subcategory":"Real Estate Operator",
            "type":"Services"
        }
    ],
    "sg:phone":"+1 305 895 0533",
    "sg:postcode":"33161",
    "sg:province":"FL",
    "sg:tags":[
        "building",
        "apartment"
    ],
    "wof:name":"Miami Heights Apartments",
    "wof:placetype":"venue"
},
  "geometry": {"coordinates":[-80.172952,25.881535],"type":"Point"}
}