{
  "type": "Feature",
  "properties": {
    "addr:full":"334 49th Ave N Saint Petersburg FL 33703",
    "addr:housenumber":"334",
    "addr:postcode":"33703",
    "addr:street":"49Th Ave N",
    "iso:country":"US",
    "sg:address":"334 49th Ave N",
    "sg:city":"Saint Petersburg",
    "sg:classifiers":[
        {
            "category":"Professional",
            "subcategory":"Detective & Security Services",
            "type":"Services"
        }
    ],
    "sg:phone":"+1 727 527 5589",
    "sg:postcode":"33703",
    "sg:province":"FL",
    "sg:tags":[
        "car"
    ],
    "wof:name":"Bay Investigations",
    "wof:placetype":"venue"
},
  "geometry": {"coordinates":[-82.638004,27.8166],"type":"Point"}
}