{
  "type": "Feature",
  "properties": {
    "addr:full":"1300 NE 8 Ave Gainesville FL 32601",
    "addr:housenumber":"1300",
    "addr:postcode":"32601",
    "addr:street":"Ne 8 Ave",
    "iso:country":"US",
    "sg:address":"1300 NE 8 Ave",
    "sg:city":"Gainesville",
    "sg:classifiers":[
        {
            "category":"Government",
            "subcategory":"Office",
            "type":"Public Place"
        }
    ],
    "sg:phone":"+1 352 334 4117",
    "sg:postcode":"32601",
    "sg:province":"FL",
    "sg:tags":[
        "federal",
        "security"
    ],
    "wof:name":"US Army Reserve",
    "wof:placetype":"venue"
},
  "geometry": {"coordinates":[-82.30912499999999,29.659388],"type":"Point"}
}