{
  "type": "Feature",
  "properties": {
    "iso:country":"US",
    "sg:address":"10 Toreador",
    "sg:city":"Port Saint Lucie",
    "sg:classifiers":[
        {
            "category":"Real Estate",
            "subcategory":"Real Estate Agent",
            "type":"Services"
        }
    ],
    "sg:phone":"+1 772 359 4044",
    "sg:postcode":"34952",
    "sg:province":"FL",
    "wof:name":"Homes of Treasure Coast",
    "wof:placetype":"venue"
},
  "geometry": {"coordinates":[-80.29003,27.30465],"type":"Point"}
}