{
  "type": "Feature",
  "properties": {
    "addr:full":"7103 Landmark Dr Spring Hill FL 34606",
    "addr:housenumber":"7103",
    "addr:postcode":"34606",
    "addr:street":"Landmark Dr",
    "iso:country":"US",
    "sg:address":"7103 Landmark Dr",
    "sg:city":"Spring Hill",
    "sg:classifiers":[
        {
            "category":"Professional",
            "type":"Services"
        }
    ],
    "sg:phone":"+1 352 686 6625",
    "sg:postcode":"34606",
    "sg:province":"FL",
    "sg:tags":[
        "establishment"
    ],
    "wof:name":"Design It Ctr Intl",
    "wof:placetype":"venue"
},
  "geometry": {"coordinates":[-82.604176,28.439153],"type":"Point"}
}