{
  "type": "Feature",
  "properties": {
    "addr:full":"4350 Oakes Rd Fort Lauderdale FL 33314",
    "addr:housenumber":"4350",
    "addr:postcode":"33314",
    "addr:street":"Oakes Rd",
    "iso:country":"US",
    "sg:address":"4350 Oakes Rd",
    "sg:city":"Fort Lauderdale",
    "sg:classifiers":[
        {
            "category":"Professional",
            "subcategory":"Business Services",
            "type":"Services"
        }
    ],
    "sg:phone":"+1 954 327 3097",
    "sg:postcode":"33314",
    "sg:province":"FL",
    "sg:tags":[
        "management",
        "co",
        "project",
        "design",
        "interior",
        "carpet"
    ],
    "wof:name":"Global Mar & Ht Interiors Inc",
    "wof:placetype":"venue"
},
  "geometry": {"coordinates":[-80.206137,26.0764],"type":"Point"}
}