{
  "type": "Feature",
  "properties": {
    "iso:country":"US",
    "sg:address":"13861 SW 36th St",
    "sg:city":"Miami",
    "sg:classifiers":[
        {
            "category":"Utilities",
            "subcategory":"Water",
            "type":"Services"
        }
    ],
    "sg:phone":"+1 305 551 0624",
    "sg:postcode":"33175",
    "sg:province":"FL",
    "sg:tags":[
        "bulk",
        "companies-bottled"
    ],
    "wof:name":"Supreme Tankless Water Heater Inc",
    "wof:placetype":"venue"
},
  "geometry": {"coordinates":[-80.419113,25.734329],"type":"Point"}
}