{
  "type": "Feature",
  "properties": {
    "iso:country":"US",
    "sg:address":"748 W 9th St",
    "sg:city":"Riviera Beach",
    "sg:classifiers":[
        {
            "category":"Organizations",
            "subcategory":"Religious Organization",
            "type":"Services"
        }
    ],
    "sg:phone":"+1 561 842 8068",
    "sg:postcode":"33404",
    "sg:province":"FL",
    "sg:tags":[
        "church"
    ],
    "wof:name":"New Macedonia Missionary",
    "wof:placetype":"venue"
},
  "geometry": {"coordinates":[-80.064418,26.770213],"type":"Point"}
}