{
  "type": "Feature",
  "properties": {
    "addr:full":"212 New Market Rd E Immokalee FL 34142",
    "addr:housenumber":"212",
    "addr:postcode":"34142",
    "addr:street":"New Market Rd E",
    "iso:country":"US",
    "sg:address":"212 New Market Rd E",
    "sg:city":"Immokalee",
    "sg:classifiers":[
        {
            "category":"Restaurant",
            "type":"Food & Drink"
        }
    ],
    "sg:phone":"+1 239 657 7898",
    "sg:postcode":"34142",
    "sg:province":"FL",
    "sg:tags":[
        "mexican"
    ],
    "wof:name":"Taquito 2 El",
    "wof:placetype":"venue"
},
  "geometry": {"coordinates":[-81.415004,26.425474],"type":"Point"}
}