{
  "type": "Feature",
  "properties": {
    "addr:full":"5716 Georgia Ave West Palm Beach FL 33405",
    "addr:housenumber":"5716",
    "addr:postcode":"33405",
    "addr:street":"Georgia Ave",
    "iso:country":"US",
    "sg:address":"5716 Georgia Ave",
    "sg:city":"West Palm Beach",
    "sg:classifiers":[
        {
            "category":"Shopping",
            "subcategory":"Clothing, Apparel, & Fashions",
            "type":"Retail Goods"
        }
    ],
    "sg:phone":"+1 561 582 2224",
    "sg:postcode":"33405",
    "sg:province":"FL",
    "sg:tags":[
        "salvage",
        "surplus",
        "merchandise"
    ],
    "wof:name":"Allison's Architectural Antq",
    "wof:placetype":"venue"
},
  "geometry": {"coordinates":[-80.05879,26.662623],"type":"Point"}
}