{
  "type": "Feature",
  "properties": {
    "addr:full":"10091 Koa Rd Sanderson FL 32095",
    "addr:housenumber":"10091",
    "addr:postcode":"32095",
    "addr:street":"Koa Rd",
    "iso:country":"US",
    "sg:address":"10091 Koa Rd",
    "sg:city":"Sanderson",
    "sg:classifiers":[
        {
            "category":"Building & Trades",
            "subcategory":"Construction",
            "type":"Services"
        }
    ],
    "sg:phone":"+1 904 259 2048",
    "sg:postcode":"32095",
    "sg:province":"FL",
    "sg:tags":[
        "contractor"
    ],
    "wof:name":"Faith Texturing",
    "wof:placetype":"venue"
},
  "geometry": {"coordinates":[-81.49613100000001,30.064816],"type":"Point"}
}