{
  "type": "Feature",
  "properties": {
    "addr:full":"3100 SW 62nd Ave Miami FL 33155",
    "addr:housenumber":"3100",
    "addr:postcode":"33155",
    "addr:street":"Sw 62Nd Ave",
    "iso:country":"US",
    "sg:address":"3100 SW 62nd Ave",
    "sg:city":"Miami",
    "sg:classifiers":[
        {
            "category":"Health Services",
            "subcategory":"Doctor",
            "type":"Services"
        }
    ],
    "sg:phone":"+1 305 662 8316",
    "sg:postcode":"33155",
    "sg:province":"FL",
    "sg:tags":[
        "throat",
        "ear",
        "nose"
    ],
    "wof:name":"Villalonga Pedro J MD",
    "wof:placetype":"venue"
},
  "geometry": {"coordinates":[-80.295197,25.7414],"type":"Point"}
}