{
  "type": "Feature",
  "properties": {
    "addr:full":"15901 Collins Ave Sunny Isles Bch FL 33160",
    "addr:housenumber":"15901",
    "addr:postcode":"33160",
    "addr:street":"Collins Ave",
    "iso:country":"US",
    "sg:address":"15901 Collins Ave",
    "sg:city":"Sunny Isles Bch",
    "sg:classifiers":[
        {
            "category":"Personal",
            "subcategory":"Adult",
            "type":"Services"
        }
    ],
    "sg:phone":"+1 305 940 1828",
    "sg:postcode":"33160",
    "sg:province":"FL",
    "sg:tags":[
        "escort"
    ],
    "wof:name":"Connected Escort",
    "wof:placetype":"venue"
},
  "geometry": {"coordinates":[-80.122302,25.923312],"type":"Point"}
}