{
  "type": "Feature",
  "properties": {
    "iso:country":"US",
    "sg:address":"5959 NW 7th St",
    "sg:city":"Miami",
    "sg:classifiers":[
        {
            "category":"Health Services",
            "subcategory":"Hospital",
            "type":"Services"
        }
    ],
    "sg:phone":"+1 305 264 1000",
    "sg:postcode":"33126",
    "sg:province":"FL",
    "sg:tags":[
        "general"
    ],
    "wof:name":"Pan American Hospital",
    "wof:placetype":"venue"
},
  "geometry": {"coordinates":[-80.29356300000001,25.777888],"type":"Point"}
}