{
  "type": "Feature",
  "properties": {
    "addr:full":"4375 Wheatland Way Palm Harbor FL 34685",
    "addr:housenumber":"4375",
    "addr:postcode":"34685",
    "addr:street":"Wheatland Way",
    "iso:country":"US",
    "sg:address":"4375 Wheatland Way",
    "sg:city":"Palm Harbor",
    "sg:classifiers":[
        {
            "category":"Professional",
            "type":"Services"
        }
    ],
    "sg:phone":"+1 727 934 5905",
    "sg:postcode":"34685",
    "sg:province":"FL",
    "sg:tags":[
        "writer"
    ],
    "wof:name":"Doug Eadie",
    "wof:placetype":"venue"
},
  "geometry": {"coordinates":[-82.720659,28.11377],"type":"Point"}
}