{
  "type": "Feature",
  "properties": {
    "iso:country":"US",
    "sg:address":"4021 W Waters Ave",
    "sg:city":"Tampa",
    "sg:classifiers":[
        {
            "category":"Banks & Credit Unions",
            "subcategory":"Bank",
            "type":"Services"
        }
    ],
    "sg:phone":"+1 813 244 6390",
    "sg:postcode":"33614",
    "sg:province":"FL",
    "sg:tags":[
        "loan",
        "broker",
        "custom",
        "real estate"
    ],
    "wof:name":"Allstate Funding Corp.",
    "wof:placetype":"venue"
},
  "geometry": {"coordinates":[-82.51029200000001,28.02553],"type":"Point"}
}