{
  "type": "Feature",
  "properties": {
    "iso:country":"US",
    "sg:address":"2260 Orion Lake Dr",
    "sg:city":"Navarre",
    "sg:classifiers":[
        {
            "category":"Building & Trades",
            "subcategory":"Construction",
            "type":"Services"
        }
    ],
    "sg:phone":"+1 850 939 8181",
    "sg:postcode":"32566",
    "sg:province":"FL",
    "sg:tags":[
        "repairing",
        "remodeling",
        "contractor"
    ],
    "wof:name":"A Best Restoration",
    "wof:placetype":"venue"
},
  "geometry": {"coordinates":[-86.81148899999999,30.41321],"type":"Point"}
}