{
  "type": "Feature",
  "properties": {
    "iso:country":"US",
    "sg:address":"2201 Cantu Ct",
    "sg:city":"Sarasota",
    "sg:classifiers":[
        {
            "category":"Health Services",
            "subcategory":"Clinic",
            "type":"Services"
        }
    ],
    "sg:phone":"+1 941 379 4900",
    "sg:postcode":"34232",
    "sg:province":"FL",
    "sg:tags":[
        "home"
    ],
    "wof:name":"Housecall Home Healthcare",
    "wof:placetype":"venue"
},
  "geometry": {"coordinates":[-82.44944700000001,27.310458],"type":"Point"}
}