{
  "type": "Feature",
  "properties": {
    "addr:full":"1124 Trotwood Blvd Winter Springs FL 32708",
    "addr:housenumber":"1124",
    "addr:postcode":"32708",
    "addr:street":"Trotwood Blvd",
    "iso:country":"US",
    "sg:address":"1124 Trotwood Blvd",
    "sg:city":"Winter Springs",
    "sg:classifiers":[
        {
            "category":"Insurance",
            "subcategory":"Insurance Agent",
            "type":"Services"
        }
    ],
    "sg:phone":"+1 407 695 4478",
    "sg:postcode":"32708",
    "sg:province":"FL",
    "wof:name":"Claims Incorporated Corporate",
    "wof:placetype":"venue"
},
  "geometry": {"coordinates":[-81.27479599999999,28.686559],"type":"Point"}
}