{
  "type": "Feature",
  "properties": {
    "iso:country":"US",
    "sg:address":"5975 NW 18th St Bldg 716F",
    "sg:city":"Miami",
    "sg:classifiers":[
        {
            "category":"Professional",
            "subcategory":"Business Services",
            "type":"Services"
        }
    ],
    "sg:phone":"+1 305 871 2865",
    "sg:postcode":"33126",
    "sg:province":"FL",
    "sg:tags":[
        "organizing",
        "services-household"
    ],
    "wof:name":"D H L Purchase Manager",
    "wof:placetype":"venue"
},
  "geometry": {"coordinates":[-80.293705,25.790959],"type":"Point"}
}