{
  "type": "Feature",
  "properties": {
    "iso:country":"US",
    "sg:address":"105 S Ridgewood Dr",
    "sg:city":"Sebring",
    "sg:classifiers":[
        {
            "category":"Personal",
            "type":"Services"
        }
    ],
    "sg:phone":"+1 863 471 0995",
    "sg:postcode":"33870",
    "sg:province":"FL",
    "sg:tags":[
        "therapist",
        "massage"
    ],
    "wof:name":"Art Of Massage",
    "wof:placetype":"venue"
},
  "geometry": {"coordinates":[-81.441226,27.495407],"type":"Point"}
}