{
  "type": "Feature",
  "properties": {
    "iso:country":"US",
    "sg:address":"2710 Rew Cir",
    "sg:city":"Ocoee",
    "sg:classifiers":[
        {
            "category":"Professional",
            "subcategory":"Management & Consulting",
            "type":"Services"
        },
        {
            "category":"Education",
            "subcategory":"Special Training",
            "type":"Public Place"
        }
    ],
    "sg:phone":"+1 407 656 3906",
    "sg:postcode":"34761",
    "sg:province":"FL",
    "sg:tags":[
        "distance",
        "s",
        "provider",
        "specialized",
        "organization"
    ],
    "wof:name":"Compass Knowledge Holdings",
    "wof:placetype":"venue"
},
  "geometry": {"coordinates":[-81.536902,28.549874],"type":"Point"}
}