{
  "type": "Feature",
  "properties": {
    "iso:country":"US",
    "sg:address":"937 E Gulf Dr",
    "sg:city":"Sanibel",
    "sg:classifiers":[
        {
            "category":"Bars & Pubs",
            "type":"Food & Drink"
        },
        {
            "category":"Restaurant",
            "type":"Food & Drink"
        }
    ],
    "sg:menulink":"http://www.allmenus.com/fl/sanibel-island/49868-ellingtons-jazz-bar--restaurant/menu/",
    "sg:phone":"+1 239 472 0497",
    "sg:postcode":"33957",
    "sg:province":"FL",
    "sg:tags":[
        "american"
    ],
    "wof:name":"Ellington's Jazz Bar & Restaurant",
    "wof:placetype":"venue"
},
  "geometry": {"coordinates":[-82.0406,26.440093],"type":"Point"}
}