{
  "type": "Feature",
  "properties": {
    "iso:country":"US",
    "sg:address":"1712 N Dale Mabry Hwy",
    "sg:city":"Tampa",
    "sg:classifiers":[
        {
            "category":"Home & Garden",
            "subcategory":"Building Materials",
            "type":"Retail Goods"
        }
    ],
    "sg:phone":"+1 813 879 1000",
    "sg:postcode":"33607",
    "sg:province":"FL",
    "sg:tags":[
        "supply"
    ],
    "sg:website":"www.homedepot.com",
    "wof:name":"Home Depot",
    "wof:placetype":"venue"
},
  "geometry": {"coordinates":[-82.505656,27.956628],"type":"Point"}
}