{
  "type": "Feature",
  "properties": {
    "iso:country":"US",
    "sg:address":"6100 Griffin Rd",
    "sg:city":"Fort Lauderdale",
    "sg:classifiers":[
        {
            "category":"Education",
            "subcategory":"College",
            "type":"Public Place"
        }
    ],
    "sg:phone":"+1 954 262 2031",
    "sg:postcode":"33314",
    "sg:province":"FL",
    "wof:name":"PH D Program Office",
    "wof:placetype":"venue"
},
  "geometry": {"coordinates":[-80.229146,26.065165],"type":"Point"}
}