{
  "type": "Feature",
  "properties": {
    "iso:country":"US",
    "sg:address":"156 Mill Creek Rd",
    "sg:city":"Jacksonville",
    "sg:classifiers":[
        {
            "category":"Retail",
            "subcategory":"Auto Repair",
            "type":"Services"
        }
    ],
    "sg:phone":"+1 904 727 0937",
    "sg:postcode":"32211",
    "sg:province":"FL",
    "sg:tags":[
        "repairing",
        "automobile"
    ],
    "wof:name":"Al's Automotive",
    "wof:placetype":"venue"
},
  "geometry": {"coordinates":[-81.56021699999999,30.317267],"type":"Point"}
}