{
  "type": "Feature",
  "properties": {
    "iso:country":"US",
    "sg:address":"227 SE Sims Cir",
    "sg:city":"Port Saint Lucie",
    "sg:classifiers":[
        {
            "category":"Banks & Credit Unions",
            "subcategory":"Financial Services",
            "type":"Services"
        }
    ],
    "sg:phone":"+1 772 344 9274",
    "sg:postcode":"34984",
    "sg:province":"FL",
    "sg:tags":[
        "trust",
        "investment",
        "real estate"
    ],
    "wof:name":"R&D Management Inc",
    "wof:placetype":"venue"
},
  "geometry": {"coordinates":[-80.34611,27.248163],"type":"Point"}
}