{
  "type": "Feature",
  "properties": {
    "addr:full":"212 Frisco Rd Pensacola FL 32507",
    "addr:housenumber":"212",
    "addr:postcode":"32507",
    "addr:street":"Frisco Rd",
    "iso:country":"US",
    "sg:address":"212 Frisco Rd",
    "sg:city":"Pensacola",
    "sg:classifiers":[
        {
            "category":"Building & Trades",
            "subcategory":"Landscaping Services",
            "type":"Services"
        }
    ],
    "sg:phone":"+1 850 456 2980",
    "sg:postcode":"32507",
    "sg:province":"FL",
    "wof:name":"Landscape Services",
    "wof:placetype":"venue"
},
  "geometry": {"coordinates":[-87.264003,30.407786],"type":"Point"}
}