{
  "type": "Feature",
  "properties": {
    "addr:full":"5720 Charleston St Hollywood FL 33021",
    "addr:housenumber":"5720",
    "addr:postcode":"33021",
    "addr:street":"Charleston St",
    "iso:country":"US",
    "sg:address":"5720 Charleston St",
    "sg:city":"Hollywood",
    "sg:classifiers":[
        {
            "category":"Personal",
            "subcategory":"Beauty Salon",
            "type":"Services"
        }
    ],
    "sg:phone":"+1 954 961 9712",
    "sg:postcode":"33021",
    "sg:province":"FL",
    "sg:tags":[
        "shop"
    ],
    "wof:name":"Ginos Studio of Hair Design",
    "wof:placetype":"venue"
},
  "geometry": {"coordinates":[-80.20392,26.039348],"type":"Point"}
}