{
  "type": "Feature",
  "properties": {
    "addr:full":"40 Spring Loop Cir Ocala FL 34472",
    "addr:housenumber":"40",
    "addr:postcode":"34472",
    "addr:street":"Spring Loop Cir",
    "iso:country":"US",
    "sg:address":"40 Spring Loop Cir",
    "sg:city":"Ocala",
    "sg:classifiers":[
        {
            "category":"Social Services",
            "subcategory":"Adult Care",
            "type":"Services"
        }
    ],
    "sg:phone":"+1 352 687 8727",
    "sg:postcode":"34472",
    "sg:province":"FL",
    "sg:tags":[
        "residential"
    ],
    "wof:name":"Hope Garden Als Inc",
    "wof:placetype":"venue"
},
  "geometry": {"coordinates":[-82.015902,29.100514],"type":"Point"}
}