{
  "type": "Feature",
  "properties": {
    "addr:full":"2601 Longleaf Dr Pensacola FL 32526",
    "addr:housenumber":"2601",
    "addr:postcode":"32526",
    "addr:street":"Longleaf Dr",
    "iso:country":"US",
    "sg:address":"2601 Longleaf Dr",
    "sg:city":"Pensacola",
    "sg:classifiers":[
        {
            "category":"Building & Trades",
            "subcategory":"Construction",
            "type":"Services"
        }
    ],
    "sg:phone":"+1 850 944 9604",
    "sg:postcode":"32526",
    "sg:province":"FL",
    "sg:tags":[
        "acoustical",
        "contractor"
    ],
    "wof:name":"Foster-Keller Construction Inc",
    "wof:placetype":"venue"
},
  "geometry": {"coordinates":[-87.29672100000001,30.486428],"type":"Point"}
}