{
  "type": "Feature",
  "properties": {
    "addr:full":"10995 Metro Pkwy Fort Myers FL 33966",
    "addr:housenumber":"10995",
    "addr:postcode":"33966",
    "addr:street":"Metro Pkwy",
    "iso:country":"US",
    "sg:address":"10995 Metro Pkwy",
    "sg:city":"Fort Myers",
    "sg:classifiers":[
        {
            "category":"Wholesale",
            "subcategory":"Construction Materials",
            "type":"Manufacturing & Wholesale Goods"
        }
    ],
    "sg:phone":"+1 239 275 6433",
    "sg:postcode":"33966",
    "sg:province":"FL",
    "sg:tags":[
        "equipment",
        "roofing",
        "supply"
    ],
    "wof:name":"Suncoast Roofers Supply Inc",
    "wof:placetype":"venue"
},
  "geometry": {"coordinates":[-81.85315,26.58293],"type":"Point"}
}