{
  "type": "Feature",
  "properties": {
    "iso:country":"US",
    "sg:address":"16985 SW 153rd Pl",
    "sg:city":"Miami",
    "sg:classifiers":[
        {
            "category":"Cinema",
            "subcategory":"Movie Rental",
            "type":"Entertainment"
        }
    ],
    "sg:phone":"+1 305 232 0562",
    "sg:postcode":"33187",
    "sg:province":"FL",
    "sg:tags":[
        "video",
        "tape"
    ],
    "wof:name":"Fan Digital Video Services",
    "wof:placetype":"venue"
},
  "geometry": {"coordinates":[-80.44148800000001,25.608836],"type":"Point"}
}