{
  "type": "Feature",
  "properties": {
    "iso:country":"US",
    "sg:address":"14375 S Tamiami Trl",
    "sg:city":"Fort Myers",
    "sg:classifiers":[
        {
            "category":"Retail",
            "subcategory":"Auto Rental",
            "type":"Services"
        }
    ],
    "sg:phone":"+1 239 466 0053",
    "sg:postcode":"33912",
    "sg:province":"FL",
    "sg:tags":[
        "car"
    ],
    "sg:website":"www.enterprise.com",
    "wof:name":"Enterprise Rent-A-Car",
    "wof:placetype":"venue"
},
  "geometry": {"coordinates":[-81.870716,26.533347],"type":"Point"}
}