{
  "type": "Feature",
  "properties": {
    "iso:country":"US",
    "sg:address":"1725 N Dale Mabry Hwy",
    "sg:city":"Tampa",
    "sg:classifiers":[
        {
            "category":"Home & Garden",
            "subcategory":"Household Appliances",
            "type":"Retail Goods"
        }
    ],
    "sg:phone":"+1 813 874 8814",
    "sg:postcode":"33607",
    "sg:province":"FL",
    "sg:tags":[
        "electronics"
    ],
    "wof:name":"Best Buy",
    "wof:placetype":"venue"
},
  "geometry": {"coordinates":[-82.50550699999999,27.956515],"type":"Point"}
}