{
  "type": "Feature",
  "properties": {
    "iso:country":"US",
    "sg:address":"8361 SW 91st Ter",
    "sg:city":"Miami",
    "sg:classifiers":[
        {
            "category":"Communications",
            "subcategory":"Film & Video Production",
            "type":"Services"
        }
    ],
    "sg:phone":"+1 305 596 1011",
    "sg:postcode":"33156",
    "sg:province":"FL",
    "sg:tags":[
        "taping"
    ],
    "wof:name":"Pro Cam Intl Inc",
    "wof:placetype":"venue"
},
  "geometry": {"coordinates":[-80.330326,25.684957],"type":"Point"}
}