{
  "type": "Feature",
  "properties": {
    "iso:country":"US",
    "sg:address":"804 W Jefferson St",
    "sg:city":"Quincy",
    "sg:classifiers":[
        {
            "category":"Autos & Motor Vehicles",
            "subcategory":"Auto Supplies",
            "type":"Retail Goods"
        }
    ],
    "sg:phone":"+1 850 875 2444",
    "sg:postcode":"32351",
    "sg:province":"FL",
    "sg:tags":[
        "tire"
    ],
    "wof:name":"Quincy Alignment & Tires",
    "wof:placetype":"venue"
},
  "geometry": {"coordinates":[-84.586702,30.588174],"type":"Point"}
}