{
  "type": "Feature",
  "properties": {
    "iso:country":"US",
    "sg:address":"2108 Gilliam Ln",
    "sg:city":"Tallahassee",
    "sg:classifiers":[
        {
            "category":"Building & Trades",
            "subcategory":"Construction",
            "type":"Services"
        }
    ],
    "sg:phone":"+1 850 385 5869",
    "sg:postcode":"32308",
    "sg:province":"FL",
    "sg:tags":[
        "contractor"
    ],
    "wof:name":"Super Daves Win Tinting & ACC",
    "wof:placetype":"venue"
},
  "geometry": {"coordinates":[-84.24108699999999,30.492193],"type":"Point"}
}