{
  "type": "Feature",
  "properties": {
    "iso:country":"US",
    "sg:address":"3501 Martin Hurst Rd",
    "sg:city":"Tallahassee",
    "sg:classifiers":[
        {
            "category":"Building & Trades",
            "subcategory":"Construction",
            "type":"Services"
        }
    ],
    "sg:phone":"+1 850 893 0168",
    "sg:postcode":"32312",
    "sg:province":"FL",
    "sg:tags":[
        "house",
        "c",
        "hanging",
        "contractor"
    ],
    "wof:name":"Riverking Custom Painting",
    "wof:placetype":"venue"
},
  "geometry": {"coordinates":[-84.254767,30.506894],"type":"Point"}
}