{
  "type": "Feature",
  "properties": {
    "iso:country":"US",
    "sg:address":"460 W 84th St",
    "sg:city":"Hialeah",
    "sg:classifiers":[
        {
            "category":"Organizations",
            "subcategory":"Professional Association",
            "type":"Services"
        }
    ],
    "sg:phone":"+1 305 558 6667",
    "sg:postcode":"33014",
    "sg:province":"FL",
    "sg:tags":[
        "representative",
        "agent",
        "manufacturers'"
    ],
    "sg:website":"http://www.thefidlergroup.com",
    "wof:name":"The Fidler Group Inc",
    "wof:placetype":"venue"
},
  "geometry": {"coordinates":[-80.293359,25.898661],"type":"Point"}
}