{
  "type": "Feature",
  "properties": {
    "addr:full":"1717 Main St Weston FL 33326",
    "addr:housenumber":"1717",
    "addr:postcode":"33326",
    "addr:street":"Main St",
    "iso:country":"US",
    "sg:address":"1717 Main St",
    "sg:city":"Weston",
    "sg:classifiers":[
        {
            "category":"Shopping",
            "subcategory":"Clothing, Apparel, & Fashions",
            "type":"Retail Goods"
        }
    ],
    "sg:phone":"+1 954 217 7515",
    "sg:postcode":"33326",
    "sg:province":"FL",
    "wof:name":"Zucco Boutique Inc",
    "wof:placetype":"venue"
},
  "geometry": {"coordinates":[-80.381322,26.097199],"type":"Point"}
}