{
  "type": "Feature",
  "properties": {
    "iso:country":"US",
    "sg:address":"62 NE 27th St",
    "sg:city":"Miami",
    "sg:classifiers":[
        {
            "category":"Arts & Performance",
            "subcategory":"Art Gallery",
            "type":"Entertainment"
        },
        {
            "category":"Shopping",
            "subcategory":"Crafts & Fabrics",
            "type":"Retail Goods"
        }
    ],
    "sg:phone":"+1 305 576 0256",
    "sg:postcode":"33137",
    "sg:province":"FL",
    "sg:tags":[
        "consultant",
        "galleries",
        "instruction"
    ],
    "wof:name":"Nader's Art Gallery",
    "wof:placetype":"venue"
},
  "geometry": {"coordinates":[-80.19364899999999,25.802467],"type":"Point"}
}