{
  "type": "Feature",
  "properties": {
    "iso:country":"US",
    "sg:address":"2125 Queen Palm Dr",
    "sg:city":"Edgewater",
    "sg:classifiers":[
        {
            "category":"Building & Trades",
            "subcategory":"Construction",
            "type":"Services"
        }
    ],
    "sg:phone":"+1 386 426 0842",
    "sg:postcode":"32141",
    "sg:province":"FL",
    "sg:tags":[
        "concrete",
        "contractor"
    ],
    "wof:name":"Tyler Concrete Construction",
    "wof:placetype":"venue"
},
  "geometry": {"coordinates":[-80.90762100000001,28.960236],"type":"Point"}
}