{
  "type": "Feature",
  "properties": {
    "iso:country":"US",
    "sg:address":"5311 N Dixie Hwy",
    "sg:city":"Fort Lauderdale",
    "sg:classifiers":[
        {
            "category":"Manufacturing",
            "subcategory":"Printing",
            "type":"Manufacturing & Wholesale Goods"
        }
    ],
    "sg:phone":"+1 954 491 1661",
    "sg:postcode":"33334",
    "sg:province":"FL",
    "sg:tags":[
        "lithographic",
        "commercial"
    ],
    "wof:name":"Sunrise Press Inc",
    "wof:placetype":"venue"
},
  "geometry": {"coordinates":[-80.132464,26.194667],"type":"Point"}
}