{
  "type": "Feature",
  "properties": {
    "iso:country":"US",
    "sg:address":"2751 Van Buren St",
    "sg:city":"Hollywood",
    "sg:classifiers":[
        {
            "category":"Education",
            "subcategory":"School",
            "type":"Public Place"
        }
    ],
    "sg:phone":"+1 954 920 2008",
    "sg:postcode":"33020",
    "sg:province":"FL",
    "sg:tags":[
        "disabled",
        "for",
        "learning"
    ],
    "wof:name":"Paladin Academy",
    "wof:placetype":"venue"
},
  "geometry": {"coordinates":[-80.160363,26.009882],"type":"Point"}
}