{
  "type": "Feature",
  "properties": {
    "addr:full":"3230 Stirling Rd Hollywood FL 33021",
    "addr:housenumber":"3230",
    "addr:postcode":"33021",
    "addr:street":"Stirling Rd",
    "iso:country":"US",
    "sg:address":"3230 Stirling Rd",
    "sg:city":"Hollywood",
    "sg:classifiers":[
        {
            "category":"Communications",
            "type":"Services"
        }
    ],
    "sg:phone":"+1 954 966 4743",
    "sg:postcode":"33021",
    "sg:province":"FL",
    "sg:tags":[
        "communication"
    ],
    "wof:name":"Tri County Mediation",
    "wof:placetype":"venue"
},
  "geometry": {"coordinates":[-80.174943,26.047732],"type":"Point"}
}