{
  "type": "Feature",
  "properties": {
    "iso:country":"US",
    "sg:address":"2012 Whitfield Park Dr",
    "sg:city":"Sarasota",
    "sg:classifiers":[
        {
            "category":"Autos & Motor Vehicles",
            "subcategory":"Motorcycle Sales",
            "type":"Retail Goods"
        }
    ],
    "sg:phone":"+1 941 756 8674",
    "sg:postcode":"34243",
    "sg:province":"FL",
    "sg:tags":[
        "classic"
    ],
    "wof:name":"Reko's British Restorations",
    "wof:placetype":"venue"
},
  "geometry": {"coordinates":[-82.535374,27.41886],"type":"Point"}
}