{
  "type": "Feature",
  "properties": {
    "iso:country":"US",
    "sg:address":"519 Cleveland St",
    "sg:city":"Clearwater",
    "sg:classifiers":[
        {
            "category":"Shopping",
            "subcategory":"Computers & Home Electronics",
            "type":"Retail Goods"
        }
    ],
    "sg:phone":"+1 727 466 9477",
    "sg:postcode":"33755",
    "sg:province":"FL",
    "sg:tags":[
        "software"
    ],
    "sg:website":"www.reportmaster.com",
    "wof:name":"Report Master",
    "wof:placetype":"venue"
},
  "geometry": {"coordinates":[-82.79875699999999,27.965559],"type":"Point"}
}