{
  "type": "Feature",
  "properties": {
    "iso:country":"US",
    "sg:address":"17440 Slater Rd",
    "sg:city":"Fort Myers",
    "sg:classifiers":[
        {
            "category":"Building & Trades",
            "subcategory":"Construction",
            "type":"Services"
        }
    ],
    "sg:phone":"+1 239 543 2372",
    "sg:postcode":"33917",
    "sg:province":"FL",
    "sg:tags":[
        "concrete",
        "contractor"
    ],
    "wof:name":"Ken Hines Concrete",
    "wof:placetype":"venue"
},
  "geometry": {"coordinates":[-81.85352,26.720444],"type":"Point"}
}