{
  "type": "Feature",
  "properties": {
    "addr:full":"6831 N Military Trl West Palm Beach FL 33407",
    "addr:housenumber":"6831",
    "addr:postcode":"33407",
    "addr:street":"N Military Trl",
    "iso:country":"US",
    "sg:address":"6831 N Military Trl",
    "sg:city":"West Palm Beach",
    "sg:classifiers":[
        {
            "category":"Home & Garden",
            "subcategory":"Furniture",
            "type":"Retail Goods"
        }
    ],
    "sg:phone":"+1 561 841 7702",
    "sg:postcode":"33407",
    "sg:province":"FL",
    "wof:name":"Skeffingtons Furniture",
    "wof:placetype":"venue"
},
  "geometry": {"coordinates":[-80.107693,26.774839],"type":"Point"}
}