{
  "type": "Feature",
  "properties": {
    "addr:full":"244 NE 33rd St Fort Lauderdale FL 33334",
    "addr:housenumber":"244",
    "addr:postcode":"33334",
    "addr:street":"Ne 33Rd St",
    "iso:country":"US",
    "sg:address":"244 NE 33rd St",
    "sg:city":"Fort Lauderdale",
    "sg:classifiers":[
        {
            "category":"Manufacturing",
            "subcategory":"Electronics",
            "type":"Manufacturing & Wholesale Goods"
        }
    ],
    "sg:phone":"+1 786 859 1336",
    "sg:postcode":"33334",
    "sg:province":"FL",
    "sg:tags":[
        "wireless",
        "application",
        "protocol"
    ],
    "wof:name":"Ocean Communication",
    "wof:placetype":"venue"
},
  "geometry": {"coordinates":[-80.144132,26.168847],"type":"Point"}
}