{
  "type": "Feature",
  "properties": {
    "iso:country":"US",
    "sg:address":"1732 Cornwallis Pkwy",
    "sg:city":"Cape Coral",
    "sg:classifiers":[
        {
            "category":"Shopping",
            "subcategory":"Gifts & Souvenirs",
            "type":"Retail Goods"
        }
    ],
    "sg:phone":"+1 239 549 8486",
    "sg:postcode":"33904",
    "sg:province":"FL",
    "wof:name":"Ty Ingles Gifts & Collectibles",
    "wof:placetype":"venue"
},
  "geometry": {"coordinates":[-81.93686,26.595904],"type":"Point"}
}