{
  "type": "Feature",
  "properties": {
    "addr:full":"497 S Chickasaw Trl Orlando FL 32825",
    "addr:housenumber":"497",
    "addr:postcode":"32825",
    "addr:street":"S Chickasaw Trl",
    "iso:country":"US",
    "sg:address":"497 S Chickasaw Trl",
    "sg:city":"Orlando",
    "sg:classifiers":[
        {
            "category":"Shopping",
            "subcategory":"Clothing, Apparel, & Fashions",
            "type":"Retail Goods"
        }
    ],
    "sg:phone":"+1 407 277 4632",
    "sg:postcode":"32825",
    "sg:province":"FL",
    "sg:tags":[
        "handbag"
    ],
    "sg:website":"http://www.catofashions.com/",
    "wof:name":"Cato",
    "wof:placetype":"venue"
},
  "geometry": {"coordinates":[-81.27538699999999,28.537746],"type":"Point"}
}