{
  "type": "Feature",
  "properties": {
    "iso:country":"US",
    "sg:address":"440 Grant Rd",
    "sg:city":"Venice",
    "sg:classifiers":[
        {
            "category":"Building & Trades",
            "subcategory":"Electrical",
            "type":"Services"
        }
    ],
    "sg:phone":"+1 941 408 7707",
    "sg:postcode":"34293",
    "sg:province":"FL",
    "sg:tags":[
        "electrical",
        "contractor"
    ],
    "wof:name":"Night Scape By Mike",
    "wof:placetype":"venue"
},
  "geometry": {"coordinates":[-82.42139899999999,27.061011],"type":"Point"}
}