{
  "type": "Feature",
  "properties": {
    "addr:full":"4320 SE Federal Hwy Stuart FL 34997",
    "addr:housenumber":"4320",
    "addr:postcode":"34997",
    "addr:street":"Se Federal Hwy",
    "iso:country":"US",
    "sg:address":"4320 SE Federal Hwy",
    "sg:city":"Stuart",
    "sg:classifiers":[
        {
            "category":"Shopping",
            "subcategory":"Tobacco",
            "type":"Retail Goods"
        }
    ],
    "sg:phone":"+1 772 287 5060",
    "sg:postcode":"34997",
    "sg:province":"FL",
    "sg:tags":[
        "product"
    ],
    "wof:name":"Coffmans Pipe and Tobacco",
    "wof:placetype":"venue"
},
  "geometry": {"coordinates":[-80.21794300000001,27.151092],"type":"Point"}
}