{
  "type": "Feature",
  "properties": {
    "addr:full":"124 US Hwy 1 North Palm Beach FL 33408",
    "addr:housenumber":"124",
    "addr:postcode":"33408",
    "addr:street":"Us Hwy 1 North",
    "iso:country":"US",
    "sg:address":"124 US Hwy 1",
    "sg:city":"North Palm Beach",
    "sg:classifiers":[
        {
            "category":"Professional",
            "subcategory":"Management & Consulting",
            "type":"Services"
        }
    ],
    "sg:phone":"+1 561 848 4501",
    "sg:postcode":"33408",
    "sg:province":"FL",
    "sg:tags":[
        "party",
        "planning"
    ],
    "sg:website":"www.christopherscreativedesigns.com",
    "wof:name":"Christopher's Christmas Shop",
    "wof:placetype":"venue"
},
  "geometry": {"coordinates":[-80.05423500000001,26.793398],"type":"Point"}
}