{
  "type": "Feature",
  "properties": {
    "addr:full":"308 Tequesta Dr Tequesta FL 33469",
    "addr:housenumber":"308",
    "addr:postcode":"33469",
    "addr:street":"Tequesta Dr",
    "iso:country":"US",
    "sg:address":"308 Tequesta Dr",
    "sg:city":"Tequesta",
    "sg:classifiers":[
        {
            "category":"Social Services",
            "type":"Services"
        }
    ],
    "sg:phone":"+1 561 745 1750",
    "sg:postcode":"33469",
    "sg:province":"FL",
    "sg:tags":[
        "counselor",
        "health",
        "mental"
    ],
    "wof:name":"Bettina Fiessinger",
    "wof:placetype":"venue"
},
  "geometry": {"coordinates":[-80.09092200000001,26.958097],"type":"Point"}
}