{
  "type": "Feature",
  "properties": {
    "iso:country":"US",
    "sg:address":"2638 Albion Ave",
    "sg:city":"Orlando",
    "sg:classifiers":[
        {
            "category":"Professional",
            "subcategory":"Business Services",
            "type":"Services"
        }
    ],
    "sg:phone":"+1 407 568 2826",
    "sg:postcode":"32833",
    "sg:province":"FL",
    "wof:name":"Ertan Enterprises",
    "wof:placetype":"venue"
},
  "geometry": {"coordinates":[-81.069057,28.510213],"type":"Point"}
}