{
  "type": "Feature",
  "properties": {
    "iso:country":"US",
    "sg:address":"9875 SW 73rd St",
    "sg:city":"Miami",
    "sg:classifiers":[
        {
            "category":"Professional",
            "subcategory":"Accounting & Tax Preparation",
            "type":"Services"
        }
    ],
    "sg:phone":"+1 305 271 2867",
    "sg:postcode":"33173",
    "sg:province":"FL",
    "wof:name":"Herman Siegall",
    "wof:placetype":"venue"
},
  "geometry": {"coordinates":[-80.355368,25.700356],"type":"Point"}
}