{
  "type": "Feature",
  "properties": {
    "iso:country":"US",
    "sg:address":"2041 NW 12th Ave",
    "sg:city":"Miami",
    "sg:classifiers":[
        {
            "category":"Wholesale",
            "subcategory":"Groceries",
            "type":"Manufacturing & Wholesale Goods"
        }
    ],
    "sg:phone":"+1 305 324 4414",
    "sg:postcode":"33127",
    "sg:province":"FL",
    "sg:tags":[
        "meat",
        "frozen",
        "beer",
        "candy",
        "food",
        "grocer",
        "fresh",
        "store"
    ],
    "wof:name":"Jetro Cash & Carry",
    "wof:placetype":"venue"
},
  "geometry": {"coordinates":[-80.214996,25.7955],"type":"Point"}
}