{
  "type": "Feature",
  "properties": {
    "iso:country":"US",
    "sg:address":"5515 46th St E",
    "sg:city":"Bradenton",
    "sg:classifiers":[
        {
            "category":"Transit Center",
            "subcategory":"Freight",
            "type":"Transportation"
        },
        {
            "category":"Freight",
            "type":"Transportation"
        }
    ],
    "sg:phone":"+1 941 739 3560",
    "sg:postcode":"34203",
    "sg:province":"FL",
    "sg:tags":[
        "local",
        "trucking-motor",
        "trucking"
    ],
    "wof:name":"Luis Trucking",
    "wof:placetype":"venue"
},
  "geometry": {"coordinates":[-82.504777,27.442247],"type":"Point"}
}