{
  "type": "Feature",
  "properties": {
    "iso:country":"US",
    "sg:address":"3475 SW 17th St",
    "sg:city":"Miami",
    "sg:classifiers":[
        {
            "category":"Place Of Worship",
            "subcategory":"Church",
            "type":"Public Place"
        }
    ],
    "sg:phone":"+1 305 446 2427",
    "sg:postcode":"33145",
    "sg:province":"FL",
    "sg:website":"www.straymond.info",
    "wof:name":"St Raymond Catholic Church",
    "wof:placetype":"venue"
},
  "geometry": {"coordinates":[-80.251701,25.755199],"type":"Point"}
}