{
  "type": "Feature",
  "properties": {
    "addr:full":"112 Ocean Dr Miami Beach FL 33139",
    "addr:housenumber":"112",
    "addr:postcode":"33139",
    "addr:street":"Ocean Dr",
    "iso:country":"US",
    "sg:address":"112 Ocean Dr",
    "sg:city":"Miami Beach",
    "sg:classifiers":[
        {
            "category":"Restaurant",
            "type":"Food & Drink"
        }
    ],
    "sg:menulink":"http://www.allmenus.com/fl/miami-beach/15920-prime-112/menu/",
    "sg:phone":"+1 305 532 8112",
    "sg:postcode":"33139",
    "sg:province":"FL",
    "sg:tags":[
        "american",
        "steakhouse"
    ],
    "wof:name":"Prime 112",
    "wof:placetype":"venue"
},
  "geometry": {"coordinates":[-80.13296699999999,25.769794],"type":"Point"}
}