{
  "type": "Feature",
  "properties": {
    "iso:country":"US",
    "sg:address":"30 Pecan St",
    "sg:city":"Jacksonville",
    "sg:classifiers":[
        {
            "category":"Retail",
            "subcategory":"Auto Repair",
            "type":"Services"
        }
    ],
    "sg:phone":"+1 904 805 0808",
    "sg:postcode":"32211",
    "sg:province":"FL",
    "sg:tags":[
        "repairing",
        "automobile"
    ],
    "wof:name":"All Tune & Lube",
    "wof:placetype":"venue"
},
  "geometry": {"coordinates":[-81.575879,30.315413],"type":"Point"}
}