{
  "type": "Feature",
  "properties": {
    "iso:country":"US",
    "sg:address":"1765 W State Road 434",
    "sg:city":"Longwood",
    "sg:classifiers":[
        {
            "category":"Social Services",
            "subcategory":"Child Care",
            "type":"Services"
        },
        {
            "category":"Education",
            "subcategory":"School",
            "type":"Public Place"
        }
    ],
    "sg:phone":"+1 407 998 5530",
    "sg:postcode":"32750",
    "sg:province":"FL",
    "sg:tags":[
        "day"
    ],
    "sg:website":"www.gracekidsacademy.com",
    "wof:name":"Gracekids Academy",
    "wof:placetype":"venue"
},
  "geometry": {"coordinates":[-81.384771,28.693203],"type":"Point"}
}