{
  "type": "Feature",
  "properties": {
    "iso:country":"US",
    "sg:address":"208 N Oceanshore Blvd",
    "sg:city":"Flagler Beach",
    "sg:classifiers":[
        {
            "category":"Restaurant",
            "type":"Food & Drink"
        }
    ],
    "sg:phone":"+1 386 439 0380",
    "sg:postcode":"32136",
    "sg:province":"FL",
    "sg:tags":[
        "eating"
    ],
    "wof:name":"Kings Oceanshore Cafe Inc",
    "wof:placetype":"venue"
},
  "geometry": {"coordinates":[-81.12805,29.482186],"type":"Point"}
}