{
  "type": "Feature",
  "properties": {
    "iso:country":"US",
    "sg:address":"8615 SW 124th Ave",
    "sg:city":"Miami",
    "sg:classifiers":[
        {
            "category":"Shopping",
            "subcategory":"Department Store",
            "type":"Retail Goods"
        }
    ],
    "sg:phone":"+1 305 412 7831",
    "sg:postcode":"33183",
    "sg:province":"FL",
    "sg:tags":[
        "shop"
    ],
    "wof:name":"Pier 1 Imports",
    "wof:placetype":"venue"
},
  "geometry": {"coordinates":[-80.393851,25.687165],"type":"Point"}
}