{
  "type": "Feature",
  "properties": {
    "iso:country":"US",
    "sg:address":"4707 140th Ave N",
    "sg:city":"Clearwater",
    "sg:classifiers":[
        {
            "category":"Insurance",
            "subcategory":"Insurance Agent",
            "type":"Services"
        }
    ],
    "sg:phone":"+1 727 599 2109",
    "sg:postcode":"33762",
    "sg:province":"FL",
    "wof:name":"AFLAC",
    "wof:placetype":"venue"
},
  "geometry": {"coordinates":[-82.698019,27.899242],"type":"Point"}
}