{
  "type": "Feature",
  "properties": {
    "iso:country":"US",
    "sg:address":"1542 Scotch Pine Dr",
    "sg:city":"Brandon",
    "sg:classifiers":[
        {
            "category":"Banks & Credit Unions",
            "subcategory":"Investment Brokerage",
            "type":"Services"
        }
    ],
    "sg:phone":"+1 813 661 8765",
    "sg:postcode":"33511",
    "sg:province":"FL",
    "sg:tags":[
        "advisory"
    ],
    "wof:name":"Jtc Investments",
    "wof:placetype":"venue"
},
  "geometry": {"coordinates":[-82.312798,27.911223],"type":"Point"}
}