{
  "type": "Feature",
  "properties": {
    "addr:full":"1621 E Vine St Ste A Kissimmee FL 34744",
    "addr:housenumber":"1621",
    "addr:postcode":"34744",
    "addr:street":"E Vine St Ste A",
    "iso:country":"US",
    "sg:address":"1621 E Vine St Ste A",
    "sg:city":"Kissimmee",
    "sg:classifiers":[
        {
            "category":"Health Services",
            "subcategory":"Chiropractor",
            "type":"Services"
        }
    ],
    "sg:phone":"+1 407 847 2898",
    "sg:postcode":"34744",
    "sg:province":"FL",
    "sg:tags":[
        "chiropractic"
    ],
    "wof:name":"Arvant & Reis Pa",
    "wof:placetype":"venue"
},
  "geometry": {"coordinates":[-81.38482999999999,28.3041],"type":"Point"}
}