{
  "type": "Feature",
  "properties": {
    "iso:country":"US",
    "sg:address":"5720 Lawton Dr",
    "sg:city":"Sarasota",
    "sg:classifiers":[
        {
            "category":"Freight",
            "type":"Transportation"
        }
    ],
    "sg:phone":"+1 941 921 4222",
    "sg:postcode":"34233",
    "sg:province":"FL",
    "sg:tags":[
        "recreational",
        "vehicle"
    ],
    "wof:name":"Extra Closet",
    "wof:placetype":"venue"
},
  "geometry": {"coordinates":[-82.486818,27.2723],"type":"Point"}
}