{
  "type": "Feature",
  "properties": {
    "addr:full":"5350 6th Ave N St Petersburg FL 33710",
    "addr:housenumber":"5350",
    "addr:postcode":"33710",
    "addr:street":"6Th Ave N",
    "iso:country":"US",
    "sg:address":"5350 6th Ave N",
    "sg:city":"St Petersburg",
    "sg:classifiers":[
        {
            "category":"Manufacturing",
            "subcategory":"Printing",
            "type":"Manufacturing & Wholesale Goods"
        }
    ],
    "sg:phone":"+1 727 323 3002",
    "sg:postcode":"33710",
    "sg:province":"FL",
    "sg:tags":[
        "screen",
        "commercial"
    ],
    "wof:name":"Ramey Enterprises",
    "wof:placetype":"venue"
},
  "geometry": {"coordinates":[-82.70612,27.778054],"type":"Point"}
}