{
  "type": "Feature",
  "properties": {
    "iso:country":"US",
    "sg:address":"11 Cone Rd",
    "sg:city":"Ormond Beach",
    "sg:classifiers":[
        {
            "category":"Organizations",
            "subcategory":"Religious Organization",
            "type":"Services"
        }
    ],
    "sg:phone":"+1 386 672 3644",
    "sg:postcode":"32174",
    "sg:province":"FL",
    "sg:tags":[
        "church"
    ],
    "sg:website":"www.rimaridgebaptist.org",
    "wof:name":"Rima Ridge Baptist Church",
    "wof:placetype":"venue"
},
  "geometry": {"coordinates":[-81.211977,29.253974],"type":"Point"}
}