{
  "type": "Feature",
  "properties": {
    "addr:full":"1550 SW 27th Ave Miami FL 33145",
    "addr:housenumber":"1550",
    "addr:postcode":"33145",
    "addr:street":"Sw 27Th Ave",
    "iso:country":"US",
    "sg:address":"1550 SW 27th Ave",
    "sg:city":"Miami",
    "sg:classifiers":[
        {
            "category":"Shopping",
            "subcategory":"Discount & Variety Stores",
            "type":"Retail Goods"
        }
    ],
    "sg:phone":"+1 305 244 9549",
    "sg:postcode":"33145",
    "sg:province":"FL",
    "wof:name":"Crazy Dollar Store",
    "wof:placetype":"venue"
},
  "geometry": {"coordinates":[-80.238653,25.758245],"type":"Point"}
}