{
  "type": "Feature",
  "properties": {
    "iso:country":"US",
    "sg:address":"27064 Church Rd",
    "sg:city":"Brooksville",
    "sg:classifiers":[
        {
            "category":"Organizations",
            "subcategory":"Religious Organization",
            "type":"Services"
        }
    ],
    "sg:phone":"+1 352 799 4133",
    "sg:postcode":"34602",
    "sg:province":"FL",
    "sg:tags":[
        "church"
    ],
    "wof:name":"Mt Pleasant Missionary Church",
    "wof:placetype":"venue"
},
  "geometry": {"coordinates":[-82.29292700000001,28.44945],"type":"Point"}
}