{
  "type": "Feature",
  "properties": {
    "addr:full":"9401 NW 42nd St Pompano Beach FL 33065",
    "addr:housenumber":"9401",
    "addr:postcode":"33065",
    "addr:street":"Nw 42Nd St",
    "iso:country":"US",
    "sg:address":"9401 NW 42nd St",
    "sg:city":"Pompano Beach",
    "sg:classifiers":[
        {
            "category":"Manufacturing",
            "subcategory":"Printing",
            "type":"Manufacturing & Wholesale Goods"
        }
    ],
    "sg:phone":"+1 954 752 8229",
    "sg:postcode":"33065",
    "sg:province":"FL",
    "sg:tags":[
        "lithographic",
        "commercial"
    ],
    "wof:name":"Larry Kunken Enterprises",
    "wof:placetype":"venue"
},
  "geometry": {"coordinates":[-80.25196099999999,26.28371],"type":"Point"}
}