{
  "type": "Feature",
  "properties": {
    "addr:full":"1140 Seabreeze Blvd Fort Lauderdale FL 33316",
    "addr:housenumber":"1140",
    "addr:postcode":"33316",
    "addr:street":"Seabreeze Blvd",
    "iso:country":"US",
    "sg:address":"1140 Seabreeze Blvd",
    "sg:city":"Fort Lauderdale",
    "sg:classifiers":[
        {
            "category":"Shopping",
            "subcategory":"Gifts & Souvenirs",
            "type":"Retail Goods"
        }
    ],
    "sg:phone":"+1 954 763 7227",
    "sg:postcode":"33316",
    "sg:province":"FL",
    "sg:tags":[
        "shop"
    ],
    "wof:name":"W H Smith",
    "wof:placetype":"venue"
},
  "geometry": {"coordinates":[-80.106583,26.108955],"type":"Point"}
}