{
  "type": "Feature",
  "properties": {
    "addr:full":"1003 del Prado Blvd S Cape Coral FL 33990",
    "addr:housenumber":"1003",
    "addr:postcode":"33990",
    "addr:street":"Del Prado Blvd S",
    "iso:country":"US",
    "sg:address":"1003 del Prado Blvd S",
    "sg:city":"Cape Coral",
    "sg:classifiers":[
        {
            "category":"Professional",
            "subcategory":"Lawyer & Legal Services",
            "type":"Services"
        }
    ],
    "sg:phone":"+1 239 514 7600",
    "sg:postcode":"33990",
    "sg:province":"FL",
    "wof:name":"Berke and Lubell PA",
    "wof:placetype":"venue"
},
  "geometry": {"coordinates":[-81.940743,26.632908],"type":"Point"}
}