{
  "type": "Feature",
  "properties": {
    "addr:full":"3040 Egret Ter Safety Harbor FL 34695",
    "addr:housenumber":"3040",
    "addr:postcode":"34695",
    "addr:street":"Egret Ter",
    "iso:country":"US",
    "sg:address":"3040 Egret Ter",
    "sg:city":"Safety Harbor",
    "sg:classifiers":[
        {
            "category":"Building & Trades",
            "subcategory":"Construction",
            "type":"Services"
        }
    ],
    "sg:phone":"+1 727 791 8323",
    "sg:postcode":"34695",
    "sg:province":"FL",
    "sg:tags":[
        "kitchen",
        "remodels",
        "cabinet"
    ],
    "wof:name":"North Bay Remodeling",
    "wof:placetype":"venue"
},
  "geometry": {"coordinates":[-82.70016200000001,28.019041],"type":"Point"}
}