{
  "type": "Feature",
  "properties": {
    "addr:full":"1181 Mary Lou Ln Gulf Breeze FL 32563",
    "addr:housenumber":"1181",
    "addr:postcode":"32563",
    "addr:street":"Mary Lou Ln",
    "iso:country":"US",
    "sg:address":"1181 Mary Lou Ln",
    "sg:city":"Gulf Breeze",
    "sg:classifiers":[
        {
            "category":"Shopping",
            "subcategory":"Optical Goods",
            "type":"Retail Goods"
        }
    ],
    "sg:phone":"+1 850 934 1954",
    "sg:postcode":"32563",
    "sg:province":"FL",
    "wof:name":"Eye Care of Gulf Breeze",
    "wof:placetype":"venue"
},
  "geometry": {"coordinates":[-87.115793,30.384005],"type":"Point"}
}