{
  "type": "Feature",
  "properties": {
    "iso:country":"US",
    "sg:address":"4904 S Kirkman Rd",
    "sg:city":"Orlando",
    "sg:classifiers":[
        {
            "category":"Restaurant",
            "type":"Food & Drink"
        }
    ],
    "sg:phone":"+1 407 293 0752",
    "sg:postcode":"32811",
    "sg:province":"FL",
    "sg:tags":[
        "eating"
    ],
    "wof:name":"Kim Wu Chinese Restaurant",
    "wof:placetype":"venue"
},
  "geometry": {"coordinates":[-81.45899199999999,28.491018],"type":"Point"}
}