{
  "type": "Feature",
  "properties": {
    "addr:full":"4547 French St Jacksonville FL 32205",
    "addr:housenumber":"4547",
    "addr:postcode":"32205",
    "addr:street":"French St",
    "iso:country":"US",
    "sg:address":"4547 French St",
    "sg:city":"Jacksonville",
    "sg:classifiers":[
        {
            "category":"Shopping",
            "subcategory":"Beauty & Cosmetics",
            "type":"Retail Goods"
        }
    ],
    "sg:phone":"+1 904 384 9337",
    "sg:postcode":"32205",
    "sg:province":"FL",
    "sg:tags":[
        "merchandise"
    ],
    "wof:name":"Elizabeth M Ziemba",
    "wof:placetype":"venue"
},
  "geometry": {"coordinates":[-81.723488,30.310625],"type":"Point"}
}