{
  "type": "Feature",
  "properties": {
    "addr:full":"316 Glenwood Rd De Land FL 32720",
    "addr:housenumber":"316",
    "addr:postcode":"32720",
    "addr:street":"Glenwood Rd De Land",
    "iso:country":"US",
    "sg:address":"316 Glenwood Rd",
    "sg:city":"De Land",
    "sg:classifiers":[
        {
            "category":"Building & Trades",
            "subcategory":"Construction",
            "type":"Services"
        }
    ],
    "sg:phone":"+1 386 738 1166",
    "sg:postcode":"32720",
    "sg:province":"FL",
    "sg:tags":[
        "carpentry",
        "contractor"
    ],
    "wof:name":"Regency Custom Designs",
    "wof:placetype":"venue"
},
  "geometry": {"coordinates":[-81.310275,29.07197],"type":"Point"}
}