{
  "type": "Feature",
  "properties": {
    "iso:country":"US",
    "sg:address":"495 NE 24th Ave",
    "sg:city":"Pompano Beach",
    "sg:classifiers":[
        {
            "category":"Retail",
            "subcategory":"Auto Repair",
            "type":"Services"
        }
    ],
    "sg:phone":"+1 954 946 7566",
    "sg:postcode":"33062",
    "sg:province":"FL",
    "sg:tags":[
        "general"
    ],
    "wof:name":"Performance Car of Pompano",
    "wof:placetype":"venue"
},
  "geometry": {"coordinates":[-80.100114,26.236428],"type":"Point"}
}