{
  "type": "Feature",
  "properties": {
    "addr:full":"311 Cloverdale Blvd Fort Walton Beach FL 32547",
    "addr:housenumber":"311",
    "addr:postcode":"32547",
    "addr:street":"Cloverdale Blvd",
    "iso:country":"US",
    "sg:address":"311 Cloverdale Blvd",
    "sg:city":"Fort Walton Beach",
    "sg:classifiers":[
        {
            "category":"Wholesale",
            "subcategory":"Machinery & Supplies",
            "type":"Manufacturing & Wholesale Goods"
        }
    ],
    "sg:phone":"+1 850 862 7970",
    "sg:postcode":"32547",
    "sg:province":"FL",
    "sg:tags":[
        "equipment",
        "establishment"
    ],
    "wof:name":"Missco",
    "wof:placetype":"venue"
},
  "geometry": {"coordinates":[-86.643428,30.450764],"type":"Point"}
}