{
  "type": "Feature",
  "properties": {
    "iso:country":"US",
    "sg:address":"2832 NW 79th Ave",
    "sg:city":"Doral",
    "sg:classifiers":[
        {
            "category":"Manufacturing",
            "subcategory":"Tobacco Products",
            "type":"Manufacturing & Wholesale Goods"
        }
    ],
    "sg:phone":"+1 305 592 2684",
    "sg:postcode":"33122",
    "sg:province":"FL",
    "sg:tags":[
        "cigarette",
        "cigar",
        "tobacco-wholesale",
        "manufacturer"
    ],
    "wof:name":"Lorillard Company",
    "wof:placetype":"venue"
},
  "geometry": {"coordinates":[-80.325003,25.79777],"type":"Point"}
}