{
  "type": "Feature",
  "properties": {
    "addr:full":"2510 NW 99th Ave Coral Springs FL 33065",
    "addr:housenumber":"2510",
    "addr:postcode":"33065",
    "addr:street":"Nw 99Th Ave",
    "iso:country":"US",
    "sg:address":"2510 NW 99th Ave",
    "sg:city":"Coral Springs",
    "sg:classifiers":[
        {
            "category":"Banks & Credit Unions",
            "subcategory":"Investment Brokerage",
            "type":"Services"
        }
    ],
    "sg:phone":"+1 954 757 7696",
    "sg:postcode":"33065",
    "sg:province":"FL",
    "sg:tags":[
        "consultant",
        "financing"
    ],
    "wof:name":"Christian Financial Advisors",
    "wof:placetype":"venue"
},
  "geometry": {"coordinates":[-80.25815,26.262923],"type":"Point"}
}