{
  "type": "Feature",
  "properties": {
    "iso:country":"US",
    "sg:address":"51 S Main Ave",
    "sg:city":"Clearwater",
    "sg:classifiers":[
        {
            "category":"Travel",
            "subcategory":"Travel Agent",
            "type":"Entertainment"
        }
    ],
    "sg:phone":"+1 727 449 8334",
    "sg:postcode":"33765",
    "sg:province":"FL",
    "sg:tags":[
        "agency",
        "bureau"
    ],
    "sg:website":"www.diamondholidaystravel.com",
    "wof:name":"Diamond Holidays",
    "wof:placetype":"venue"
},
  "geometry": {"coordinates":[-82.74805000000001,27.962904],"type":"Point"}
}