{
  "type": "Feature",
  "properties": {
    "addr:full":"801 Pike Rd West Palm Beach FL 33411",
    "addr:housenumber":"801",
    "addr:postcode":"33411",
    "addr:street":"Pike Rd",
    "iso:country":"US",
    "sg:address":"801 Pike Rd",
    "sg:city":"West Palm Beach",
    "sg:classifiers":[
        {
            "category":"Building & Trades",
            "subcategory":"Electrical",
            "type":"Services"
        }
    ],
    "sg:phone":"+1 561 689 7644",
    "sg:postcode":"33411",
    "sg:province":"FL",
    "sg:tags":[
        "electric",
        "contractor"
    ],
    "wof:name":"G King Electric",
    "wof:placetype":"venue"
},
  "geometry": {"coordinates":[-80.165935,26.689581],"type":"Point"}
}