{
  "type": "Feature",
  "properties": {
    "iso:country":"US",
    "sg:address":"7631 Gall Blvd",
    "sg:city":"Zephyrhills",
    "sg:classifiers":[
        {
            "category":"Shopping",
            "subcategory":"Department Store",
            "type":"Retail Goods"
        }
    ],
    "sg:phone":"+1 813 782 1957",
    "sg:postcode":"33541",
    "sg:province":"FL",
    "wof:name":"Wal-Mart Supercenter",
    "wof:placetype":"venue"
},
  "geometry": {"coordinates":[-82.188329,28.268513],"type":"Point"}
}