{
  "type": "Feature",
  "properties": {
    "iso:country":"US",
    "sg:address":"2928 Ashton Ter",
    "sg:city":"Oviedo",
    "sg:classifiers":[
        {
            "category":"Building & Trades",
            "subcategory":"Construction",
            "type":"Services"
        }
    ],
    "sg:phone":"+1 407 366 3939",
    "sg:postcode":"32765",
    "sg:province":"FL",
    "sg:tags":[
        "contractor"
    ],
    "wof:name":"Sun-TEC Builders Inc",
    "wof:placetype":"venue"
},
  "geometry": {"coordinates":[-81.236249,28.633911],"type":"Point"}
}