{
  "type": "Feature",
  "properties": {
    "iso:country":"US",
    "sg:address":"1358 Linda Ann Dr",
    "sg:city":"Tallahassee",
    "sg:classifiers":[
        {
            "category":"Building & Trades",
            "subcategory":"Construction",
            "type":"Services"
        }
    ],
    "sg:phone":"+1 850 627 2661",
    "sg:postcode":"32301",
    "sg:province":"FL",
    "sg:tags":[
        "carpentry",
        "contractor"
    ],
    "wof:name":"Klein Malcolm Carpenter",
    "wof:placetype":"venue"
},
  "geometry": {"coordinates":[-84.245137,30.428803],"type":"Point"}
}