{
  "type": "Feature",
  "properties": {
    "addr:full":"13659 59th Ct N West Palm Beach FL 33411",
    "addr:housenumber":"13659",
    "addr:postcode":"33411",
    "addr:street":"59Th Ct N",
    "iso:country":"US",
    "sg:address":"13659 59th Ct N",
    "sg:city":"West Palm Beach",
    "sg:classifiers":[
        {
            "category":"Professional",
            "subcategory":"Business Services",
            "type":"Services"
        }
    ],
    "sg:phone":"+1 561 432 9529",
    "sg:postcode":"33411",
    "sg:province":"FL",
    "sg:tags":[
        "water",
        "treatment"
    ],
    "wof:name":"Affordable Water Syst",
    "wof:placetype":"venue"
},
  "geometry": {"coordinates":[-80.257274,26.764578],"type":"Point"}
}