{
  "type": "Feature",
  "properties": {
    "iso:country":"US",
    "sg:address":"2253 Bayview Ln",
    "sg:city":"North Miami",
    "sg:classifiers":[
        {
            "category":"Professional",
            "subcategory":"Business Services",
            "type":"Services"
        }
    ],
    "sg:phone":"+1 954 791 7913",
    "sg:postcode":"33181",
    "sg:province":"FL",
    "sg:tags":[
        "fund",
        "promotion",
        "raising"
    ],
    "wof:name":"Cross Promotional Svc Inc",
    "wof:placetype":"venue"
},
  "geometry": {"coordinates":[-80.149732,25.894501],"type":"Point"}
}