{
  "type": "Feature",
  "properties": {
    "addr:full":"1767 NW Palmetto Ter Stuart FL 34994",
    "addr:housenumber":"1767",
    "addr:postcode":"34994",
    "addr:street":"Nw Palmetto Ter",
    "iso:country":"US",
    "sg:address":"1767 NW Palmetto Ter",
    "sg:city":"Stuart",
    "sg:classifiers":[
        {
            "category":"Health Services",
            "subcategory":"Doctor",
            "type":"Services"
        }
    ],
    "sg:phone":"+1 772 692 5727",
    "sg:postcode":"34994",
    "sg:province":"FL",
    "sg:tags":[
        "clinic"
    ],
    "wof:name":"Physician's Choice Respiratory",
    "wof:placetype":"venue"
},
  "geometry": {"coordinates":[-80.27667,27.227369],"type":"Point"}
}