{
  "type": "Feature",
  "properties": {
    "addr:full":"4380 SW 112th Ave Miami FL 33165",
    "addr:housenumber":"4380",
    "addr:postcode":"33165",
    "addr:street":"Sw 112Th Ave",
    "iso:country":"US",
    "sg:address":"4380 SW 112th Ave",
    "sg:city":"Miami",
    "sg:classifiers":[
        {
            "category":"Freight",
            "type":"Transportation"
        }
    ],
    "sg:phone":"+1 305 485 8338",
    "sg:postcode":"33165",
    "sg:province":"FL",
    "wof:name":"A & J Transport Inc",
    "wof:placetype":"venue"
},
  "geometry": {"coordinates":[-80.375523,25.726541],"type":"Point"}
}