{
  "type": "Feature",
  "properties": {
    "iso:country":"US",
    "sg:address":"1710 E 7th Ave",
    "sg:city":"Tampa",
    "sg:classifiers":[
        {
            "category":"Professional",
            "subcategory":"Lawyer & Legal Services",
            "type":"Services"
        }
    ],
    "sg:phone":"+1 813 241 6111",
    "sg:postcode":"33605",
    "sg:province":"FL",
    "sg:tags":[
        "attorney"
    ],
    "wof:name":"Herce & Herce PA",
    "wof:placetype":"venue"
},
  "geometry": {"coordinates":[-82.439342,27.960338],"type":"Point"}
}