{
  "type": "Feature",
  "properties": {
    "iso:country":"US",
    "sg:address":"916 N Young Blvd",
    "sg:city":"Chiefland",
    "sg:classifiers":[
        {
            "category":"Autos & Motor Vehicles",
            "subcategory":"Automobile Sales",
            "type":"Retail Goods"
        },
        {
            "category":"Retail",
            "subcategory":"Auto Repair",
            "type":"Services"
        }
    ],
    "sg:phone":"+1 888 761 4477",
    "sg:postcode":"32626",
    "sg:province":"FL",
    "sg:tags":[
        "car",
        "used",
        "new"
    ],
    "sg:website":"http://www.whitefordco.com/",
    "wof:name":"White Ford Company",
    "wof:placetype":"venue"
},
  "geometry": {"coordinates":[-82.848596,29.477113],"type":"Point"}
}