{
  "type": "Feature",
  "properties": {
    "addr:full":"18351 NE 19th Ave North Miami Beach FL 33179",
    "addr:housenumber":"18351",
    "addr:postcode":"33179",
    "addr:street":"Ne 19Th Ave",
    "iso:country":"US",
    "sg:address":"18351 NE 19th Ave",
    "sg:city":"North Miami Beach",
    "sg:classifiers":[
        {
            "category":"Shopping",
            "subcategory":"Beauty & Cosmetics",
            "type":"Retail Goods"
        }
    ],
    "sg:phone":"+1 305 935 9094",
    "sg:postcode":"33179",
    "sg:province":"FL",
    "sg:tags":[
        "supply"
    ],
    "wof:name":"Aventura Beauty Center",
    "wof:placetype":"venue"
},
  "geometry": {"coordinates":[-80.162903,25.945101],"type":"Point"}
}