{
  "type": "Feature",
  "properties": {
    "addr:full":"100 Kings Point Dr Miami FL 33160",
    "addr:housenumber":"100",
    "addr:postcode":"33160",
    "addr:street":"Kings Point Dr",
    "iso:country":"US",
    "sg:address":"100 Kings Point Dr",
    "sg:city":"Miami",
    "sg:classifiers":[
        {
            "category":"Home & Garden",
            "subcategory":"Furniture",
            "type":"Retail Goods"
        }
    ],
    "sg:phone":"+1 305 302 1460",
    "sg:postcode":"33160",
    "sg:province":"FL",
    "sg:tags":[
        "furnishing"
    ],
    "wof:name":"Terrick Designs LLC",
    "wof:placetype":"venue"
},
  "geometry": {"coordinates":[-80.122984,25.923726],"type":"Point"}
}