{
  "type": "Feature",
  "properties": {
    "iso:country":"US",
    "sg:address":"10450 SE Jupiter Narrows Dr",
    "sg:city":"Hobe Sound",
    "sg:classifiers":[
        {
            "category":"Real Estate",
            "subcategory":"Real Estate Agent",
            "type":"Services"
        }
    ],
    "sg:phone":"+1 772 545 9983",
    "sg:postcode":"33455",
    "sg:province":"FL",
    "wof:name":"Jackie Brown Real Est Closing",
    "wof:placetype":"venue"
},
  "geometry": {"coordinates":[-80.133466,27.07472],"type":"Point"}
}