{
  "type": "Feature",
  "properties": {
    "addr:full":"9615 Thomas Dr Panama City FL 32408",
    "addr:housenumber":"9615",
    "addr:postcode":"32408",
    "addr:street":"Thomas Dr",
    "iso:country":"US",
    "sg:address":"9615 Thomas Dr",
    "sg:city":"Panama City",
    "sg:classifiers":[
        {
            "category":"Sports & Exercise",
            "subcategory":"Golf",
            "type":"Entertainment"
        }
    ],
    "sg:phone":"+1 850 234 5051",
    "sg:postcode":"32408",
    "sg:province":"FL",
    "sg:tags":[
        "course"
    ],
    "wof:name":"Signal Hill Golf Course",
    "wof:placetype":"venue"
},
  "geometry": {"coordinates":[-85.795513,30.174785],"type":"Point"}
}