{
  "type": "Feature",
  "properties": {
    "iso:country":"US",
    "sg:address":"2090 Palmetto St",
    "sg:city":"Clearwater",
    "sg:classifiers":[
        {
            "category":"Home & Garden",
            "subcategory":"Home Furnishings",
            "type":"Retail Goods"
        },
        {
            "category":"Home & Garden",
            "subcategory":"Hardware",
            "type":"Retail Goods"
        }
    ],
    "sg:phone":"+1 727 447 7676",
    "sg:postcode":"33765",
    "sg:province":"FL",
    "sg:tags":[
        "equipment",
        "fixture",
        "lighting",
        "system"
    ],
    "sg:website":"http://www.frontierlighting.com/showroom.jsp",
    "wof:name":"Frontier Lighting",
    "wof:placetype":"venue"
},
  "geometry": {"coordinates":[-82.75072299999999,27.975263],"type":"Point"}
}