{
  "type": "Feature",
  "properties": {
    "iso:country":"US",
    "sg:address":"150 Woodland Ave",
    "sg:city":"Cocoa Beach",
    "sg:classifiers":[
        {
            "category":"Wholesale",
            "subcategory":"Non-durable Goods",
            "type":"Manufacturing & Wholesale Goods"
        },
        {
            "category":"Wholesale",
            "subcategory":"Durable Goods & Equipment",
            "type":"Manufacturing & Wholesale Goods"
        }
    ],
    "sg:phone":"+1 321 783 4430",
    "sg:postcode":"32931",
    "sg:province":"FL",
    "sg:tags":[
        "souvenir"
    ],
    "wof:name":"Cape Kennedy Mint",
    "wof:placetype":"venue"
},
  "geometry": {"coordinates":[-80.61210800000001,28.321092],"type":"Point"}
}