{
  "type": "Feature",
  "properties": {
    "iso:country":"US",
    "sg:address":"16401 US Hwy 301",
    "sg:city":"Dade City",
    "sg:classifiers":[
        {
            "category":"Retail",
            "subcategory":"Repair Shop",
            "type":"Services"
        }
    ],
    "sg:phone":"+1 352 523 2234",
    "sg:postcode":"33523",
    "sg:province":"FL",
    "sg:tags":[
        "television",
        "radio"
    ],
    "wof:name":"Raymer's Electronics",
    "wof:placetype":"venue"
},
  "geometry": {"coordinates":[-82.19539399999999,28.39434],"type":"Point"}
}