{
  "type": "Feature",
  "properties": {
    "addr:full":"6690 20th St Vero Beach FL 32966",
    "addr:housenumber":"6690",
    "addr:postcode":"32966",
    "addr:street":"20Th St",
    "iso:country":"US",
    "sg:address":"6690 20th St",
    "sg:city":"Vero Beach",
    "sg:classifiers":[
        {
            "category":"Restaurant",
            "type":"Food & Drink"
        }
    ],
    "sg:phone":"+1 772 562 2210",
    "sg:postcode":"32966",
    "sg:province":"FL",
    "wof:name":"Mamma Mia's Pizza & Subs",
    "wof:placetype":"venue"
},
  "geometry": {"coordinates":[-80.46356299999999,27.639045],"type":"Point"}
}