{
  "type": "Feature",
  "properties": {
    "iso:country":"US",
    "sg:address":"2357 Edgewood Ave N",
    "sg:city":"Jacksonville",
    "sg:classifiers":[
        {
            "category":"Professional",
            "subcategory":"Management & Consulting",
            "type":"Services"
        }
    ],
    "sg:phone":"+1 904 378 3900",
    "sg:postcode":"32254",
    "sg:province":"FL",
    "wof:name":"Quality Lake Management Inc",
    "wof:placetype":"venue"
},
  "geometry": {"coordinates":[-81.73113499999999,30.351112],"type":"Point"}
}