{
  "type": "Feature",
  "properties": {
    "iso:country":"US",
    "sg:address":"1771 Riviera Cir",
    "sg:city":"Sarasota",
    "sg:classifiers":[
        {
            "category":"Professional",
            "subcategory":"Business Services",
            "type":"Services"
        }
    ],
    "sg:phone":"+1 941 921 5315",
    "sg:postcode":"34232",
    "sg:province":"FL",
    "sg:tags":[
        "sportswear"
    ],
    "wof:name":"Richard Harff Inc",
    "wof:placetype":"venue"
},
  "geometry": {"coordinates":[-82.495041,27.316339],"type":"Point"}
}