{
  "type": "Feature",
  "properties": {
    "iso:country":"US",
    "sg:address":"1405 NE Indian River Dr",
    "sg:city":"Jensen Beach",
    "sg:classifiers":[
        {
            "category":"Autos & Motor Vehicles",
            "subcategory":"Boat Sales",
            "type":"Retail Goods"
        }
    ],
    "sg:phone":"+1 772 219 8122",
    "sg:postcode":"34957",
    "sg:province":"FL",
    "sg:tags":[
        "dealer",
        "sales"
    ],
    "wof:name":"HMY Yachts",
    "wof:placetype":"venue"
},
  "geometry": {"coordinates":[-80.21328699999999,27.224646],"type":"Point"}
}