{
  "type": "Feature",
  "properties": {
    "addr:full":"1220 NW 4th Ave Ocala FL 34475",
    "addr:housenumber":"1220",
    "addr:postcode":"34475",
    "addr:street":"Nw 4Th Ave",
    "iso:country":"US",
    "sg:address":"1220 NW 4th Ave",
    "sg:city":"Ocala",
    "sg:classifiers":[
        {
            "category":"Government",
            "subcategory":"Office",
            "type":"Public Place"
        }
    ],
    "sg:phone":"+1 352 629 4827",
    "sg:postcode":"34475",
    "sg:province":"FL",
    "sg:tags":[
        "village"
    ],
    "wof:name":"Ocala Water Reclamation",
    "wof:placetype":"venue"
},
  "geometry": {"coordinates":[-82.14044199999999,29.198206],"type":"Point"}
}