{
  "type": "Feature",
  "properties": {
    "addr:full":"2011 SW 97th Ave Hollywood FL 33025",
    "addr:housenumber":"2011",
    "addr:postcode":"33025",
    "addr:street":"Sw 97Th Ave",
    "iso:country":"US",
    "sg:address":"2011 SW 97th Ave",
    "sg:city":"Hollywood",
    "sg:classifiers":[
        {
            "category":"Wholesale",
            "subcategory":"Non-durable Goods",
            "type":"Manufacturing & Wholesale Goods"
        }
    ],
    "sg:phone":"+1 954 436 5134",
    "sg:postcode":"33025",
    "sg:province":"FL",
    "wof:name":"Amex World Trade Corp",
    "wof:placetype":"venue"
},
  "geometry": {"coordinates":[-80.27359,25.993122],"type":"Point"}
}