{
  "type": "Feature",
  "properties": {
    "addr:full":"16220 Indian Trce Fort Lauderdale FL 33326",
    "addr:housenumber":"16220",
    "addr:postcode":"33326",
    "addr:street":"Indian Trce",
    "iso:country":"US",
    "sg:address":"16220 Indian Trce",
    "sg:city":"Fort Lauderdale",
    "sg:classifiers":[
        {
            "category":"Bakery",
            "type":"Food & Drink"
        },
        {
            "category":"Coffee & Tea",
            "type":"Food & Drink"
        },
        {
            "category":"Bagels",
            "type":"Food & Drink"
        },
        {
            "category":"Donuts",
            "type":"Food & Drink"
        }
    ],
    "sg:menulink":"http://www.allmenus.com/fl/davie/138146-dunkin-donuts/menu/",
    "sg:phone":"+1 954 349 9775",
    "sg:postcode":"33326",
    "sg:province":"FL",
    "sg:tags":[
        "american",
        "pastry"
    ],
    "wof:name":"Dunkin' Donuts",
    "wof:placetype":"venue"
},
  "geometry": {"coordinates":[-80.365728,26.10249],"type":"Point"}
}