{
  "type": "Feature",
  "properties": {
    "addr:full":"2484 Caring Way Port Charlotte FL 33952",
    "addr:housenumber":"2484",
    "addr:postcode":"33952",
    "addr:street":"Caring Way",
    "iso:country":"US",
    "sg:address":"2484 Caring Way",
    "sg:city":"Port Charlotte",
    "sg:classifiers":[
        {
            "category":"Health Services",
            "subcategory":"Doctor",
            "type":"Services"
        }
    ],
    "sg:phone":"+1 941 625 1999",
    "sg:postcode":"33952",
    "sg:province":"FL",
    "sg:tags":[
        "physician",
        "surgeon"
    ],
    "wof:name":"My Children's Doctor",
    "wof:placetype":"venue"
},
  "geometry": {"coordinates":[-82.102717,26.990142],"type":"Point"}
}