{
  "type": "Feature",
  "properties": {
    "addr:full":"1541 N Cocoa Blvd Cocoa FL 32922",
    "addr:housenumber":"1541",
    "addr:postcode":"32922",
    "addr:street":"N Cocoa Blvd",
    "iso:country":"US",
    "sg:address":"1541 N Cocoa Blvd",
    "sg:city":"Cocoa",
    "sg:classifiers":[
        {
            "category":"Social Services",
            "type":"Services"
        }
    ],
    "sg:phone":"+1 321 634 5939",
    "sg:postcode":"32922",
    "sg:province":"FL",
    "sg:tags":[
        "senior",
        "citizen"
    ],
    "wof:name":"Embers",
    "wof:placetype":"venue"
},
  "geometry": {"coordinates":[-80.74277600000001,28.384396],"type":"Point"}
}