{
  "type": "Feature",
  "properties": {
    "iso:country":"US",
    "sg:address":"15660 SE 86th Ct",
    "sg:city":"Summerfield",
    "sg:classifiers":[
        {
            "category":"Health Services",
            "subcategory":"Nursing And Care Facility",
            "type":"Services"
        },
        {
            "category":"Social Services",
            "subcategory":"Adult Care",
            "type":"Services"
        }
    ],
    "sg:phone":"+1 352 347 3484",
    "sg:postcode":"34491",
    "sg:province":"FL",
    "sg:tags":[
        "living",
        "assisted",
        "homes-elderly",
        "elder",
        "people"
    ],
    "wof:name":"Crystels Place Adult Fam",
    "wof:placetype":"venue"
},
  "geometry": {"coordinates":[-82.01007799999999,28.994428],"type":"Point"}
}