{
  "type": "Feature",
  "properties": {
    "addr:full":"6122 SW Hwy 200 Ocala FL 34476",
    "addr:housenumber":"6122",
    "addr:postcode":"34476",
    "addr:street":"Sw Hwy 200",
    "iso:country":"US",
    "sg:address":"6122 SW Hwy 200",
    "sg:city":"Ocala",
    "sg:classifiers":[
        {
            "category":"Wholesale",
            "subcategory":"Drugs",
            "type":"Manufacturing & Wholesale Goods"
        }
    ],
    "sg:phone":"+1 352 861 6323",
    "sg:postcode":"34476",
    "sg:province":"FL",
    "wof:name":"American Drug Club Ocala Fla",
    "wof:placetype":"venue"
},
  "geometry": {"coordinates":[-82.221599,29.114207],"type":"Point"}
}