{
  "type": "Feature",
  "properties": {
    "addr:full":"850 Carswell Ave Holly Hill FL 32117",
    "addr:housenumber":"850",
    "addr:postcode":"32117",
    "addr:street":"Carswell Ave",
    "iso:country":"US",
    "sg:address":"850 Carswell Ave",
    "sg:city":"Holly Hill",
    "sg:classifiers":[
        {
            "category":"Manufacturing",
            "subcategory":"Metals",
            "type":"Manufacturing & Wholesale Goods"
        }
    ],
    "sg:phone":"+1 386 253 5151",
    "sg:postcode":"32117",
    "sg:province":"FL",
    "sg:tags":[
        "coating",
        "powder"
    ],
    "wof:name":"Like Nu Inc",
    "wof:placetype":"venue"
},
  "geometry": {"coordinates":[-81.041489,29.240858],"type":"Point"}
}