{
  "type": "Feature",
  "properties": {
    "iso:country":"US",
    "sg:address":"1055 3rd St",
    "sg:city":"Daytona Beach",
    "sg:classifiers":[
        {
            "category":"Health Services",
            "subcategory":"Nursing And Care Facility",
            "type":"Services"
        }
    ],
    "sg:phone":"+1 386 252 3686",
    "sg:postcode":"32117",
    "sg:province":"FL",
    "sg:tags":[
        "skilled"
    ],
    "wof:name":"Daytona Bch Hlthcare Rhblttion",
    "wof:placetype":"venue"
},
  "geometry": {"coordinates":[-81.05260800000001,29.223382],"type":"Point"}
}