{
  "type": "Feature",
  "properties": {
    "addr:full":"6467 SW 10th St West Miami FL 33144",
    "addr:housenumber":"6467",
    "addr:postcode":"33144",
    "addr:street":"Sw 10Th St",
    "iso:country":"US",
    "sg:address":"6467 SW 10th St",
    "sg:city":"West Miami",
    "sg:classifiers":[
        {
            "category":"Utilities",
            "subcategory":"Cable",
            "type":"Services"
        }
    ],
    "sg:phone":"+1 786 275 8625",
    "sg:postcode":"33144",
    "sg:province":"FL",
    "sg:tags":[
        "television"
    ],
    "wof:name":"Custom Cable TV Corp",
    "wof:placetype":"venue"
},
  "geometry": {"coordinates":[-80.300622,25.761593],"type":"Point"}
}