{
  "type": "Feature",
  "properties": {
    "addr:full":"325 S Orlando Ave Winter Park FL 32789",
    "addr:housenumber":"325",
    "addr:postcode":"32789",
    "addr:street":"S Orlando Ave",
    "iso:country":"US",
    "sg:address":"325 S Orlando Ave",
    "sg:city":"Winter Park",
    "sg:classifiers":[
        {
            "category":"Manufacturing",
            "subcategory":"Printing",
            "type":"Manufacturing & Wholesale Goods"
        }
    ],
    "sg:phone":"+1 407 628 3833",
    "sg:postcode":"32789",
    "sg:province":"FL",
    "sg:tags":[
        "lithographic",
        "commercial"
    ],
    "wof:name":"Laser Print",
    "wof:placetype":"venue"
},
  "geometry": {"coordinates":[-81.36503500000001,28.595608],"type":"Point"}
}