{
  "type": "Feature",
  "properties": {
    "addr:full":"6698 Lana Ln Jacksonville FL 32244",
    "addr:housenumber":"6698",
    "addr:postcode":"32244",
    "addr:street":"Lana Ln",
    "iso:country":"US",
    "sg:address":"6698 Lana Ln",
    "sg:city":"Jacksonville",
    "sg:classifiers":[
        {
            "category":"Building & Trades",
            "subcategory":"Construction",
            "type":"Services"
        }
    ],
    "sg:phone":"+1 904 779 2892",
    "sg:postcode":"32244",
    "sg:province":"FL",
    "sg:tags":[
        "house"
    ],
    "wof:name":"Steins Home Improvement",
    "wof:placetype":"venue"
},
  "geometry": {"coordinates":[-81.776472,30.22779],"type":"Point"}
}