{
  "type": "Feature",
  "properties": {
    "addr:full":"365 S Calhoun St Labelle FL 33935",
    "addr:housenumber":"365",
    "addr:postcode":"33935",
    "addr:street":"S Calhoun St",
    "iso:country":"US",
    "sg:address":"365 S Calhoun St",
    "sg:city":"Labelle",
    "sg:classifiers":[
        {
            "category":"Building & Trades",
            "subcategory":"Construction",
            "type":"Services"
        }
    ],
    "sg:phone":"+1 863 675 0730",
    "sg:postcode":"33935",
    "sg:province":"FL",
    "sg:tags":[
        "handyman"
    ],
    "wof:name":"Tony's Handyman Svc",
    "wof:placetype":"venue"
},
  "geometry": {"coordinates":[-81.42706200000001,26.754797],"type":"Point"}
}