{
  "type": "Feature",
  "properties": {
    "addr:full":"1875 Boggy Creek Rd Kissimmee FL 34744",
    "addr:housenumber":"1875",
    "addr:postcode":"34744",
    "addr:street":"Boggy Creek Rd",
    "iso:country":"US",
    "sg:address":"1875 Boggy Creek Rd",
    "sg:city":"Kissimmee",
    "sg:classifiers":[
        {
            "category":"Social Services",
            "type":"Services"
        }
    ],
    "sg:phone":"+1 407 943 7010",
    "sg:postcode":"34744",
    "sg:province":"FL",
    "sg:tags":[
        "human"
    ],
    "wof:name":"Community Coalition Of Osceola Water Safety",
    "wof:placetype":"venue"
},
  "geometry": {"coordinates":[-81.368487,28.304211],"type":"Point"}
}