{
  "type": "Feature",
  "properties": {
    "iso:country":"US",
    "sg:address":"2 N Atlantic Ave",
    "sg:city":"Cocoa Beach",
    "sg:classifiers":[
        {
            "category":"Restaurant",
            "type":"Food & Drink"
        }
    ],
    "sg:phone":"+1 321 783 9512",
    "sg:postcode":"32931",
    "sg:province":"FL",
    "sg:tags":[
        "chinese"
    ],
    "wof:name":"Yen Yen Chinese Restaurant",
    "wof:placetype":"venue"
},
  "geometry": {"coordinates":[-80.60880299999999,28.319],"type":"Point"}
}