{
  "type": "Feature",
  "properties": {
    "iso:country":"US",
    "sg:address":"1320 Dixie Hwy",
    "sg:city":"Miami",
    "sg:classifiers":[
        {
            "category":"Professional",
            "subcategory":"Business Services",
            "type":"Services"
        }
    ],
    "sg:phone":"+1 305 665 0557",
    "sg:postcode":"33146",
    "sg:province":"FL",
    "sg:tags":[
        "information",
        "tourist",
        "travel",
        "agency",
        "board",
        "operator"
    ],
    "wof:name":"Jamaican Tourist Board",
    "wof:placetype":"venue"
},
  "geometry": {"coordinates":[-80.27675600000001,25.714751],"type":"Point"}
}