{
  "type": "Feature",
  "properties": {
    "iso:country":"US",
    "sg:address":"5811 Pinetree Dr",
    "sg:city":"Fort Pierce",
    "sg:classifiers":[
        {
            "category":"Recreation",
            "subcategory":"Marina",
            "type":"Entertainment"
        }
    ],
    "sg:phone":"+1 772 216 4089",
    "sg:postcode":"34982",
    "sg:province":"FL",
    "sg:tags":[
        "repairing",
        "boat"
    ],
    "wof:name":"Sisco Marine",
    "wof:placetype":"venue"
},
  "geometry": {"coordinates":[-80.31475500000001,27.360625],"type":"Point"}
}