{
  "type": "Feature",
  "properties": {
    "addr:full":"14881 SW 40 Terrace Miami FL 33185",
    "addr:housenumber":"14881",
    "addr:postcode":"33185",
    "addr:street":"Sw 40 Terrace",
    "iso:country":"US",
    "sg:address":"14881 SW 40 Terrace",
    "sg:city":"Miami",
    "sg:classifiers":[
        {
            "category":"Arts & Performance",
            "subcategory":"Music",
            "type":"Entertainment"
        }
    ],
    "sg:phone":"+1 786 277 7808",
    "sg:postcode":"33185",
    "sg:province":"FL",
    "sg:tags":[
        "jockey",
        "disc"
    ],
    "sg:website":"http://www.spinpartydj.com",
    "wof:name":"SpinPartyDJ",
    "wof:placetype":"venue"
},
  "geometry": {"coordinates":[-80.435278,25.729742],"type":"Point"}
}