{
  "type": "Feature",
  "properties": {
    "addr:full":"815 S Main St Jacksonville FL 32207",
    "addr:housenumber":"815",
    "addr:postcode":"32207",
    "addr:street":"S Main St",
    "iso:country":"US",
    "sg:address":"815 S Main St",
    "sg:city":"Jacksonville",
    "sg:classifiers":[
        {
            "category":"Travel",
            "subcategory":"Hotels & Motels",
            "type":"Entertainment"
        }
    ],
    "sg:phone":"+1 904 858 1255",
    "sg:postcode":"32207",
    "sg:province":"FL",
    "sg:tags":[
        "operation"
    ],
    "wof:name":"Temporary Lodging Corp",
    "wof:placetype":"venue"
},
  "geometry": {"coordinates":[-81.658767,30.317374],"type":"Point"}
}