{
  "type": "Feature",
  "properties": {
    "addr:full":"5250 S US Hwy 17-92 Casselberry FL 32707",
    "addr:housenumber":"5250",
    "addr:postcode":"17-92;32707",
    "addr:street":"S Us Hwy",
    "iso:country":"US",
    "sg:address":"5250 S US Hwy 17-92",
    "sg:city":"Casselberry",
    "sg:classifiers":[
        {
            "category":"Professional",
            "subcategory":"Lawyer & Legal Services",
            "type":"Services"
        }
    ],
    "sg:phone":"+1 866 831 5465",
    "sg:postcode":"32707",
    "sg:province":"FL",
    "sg:tags":[
        "personal",
        "injury"
    ],
    "wof:name":"Faddis & Warner - Attorneys at Law",
    "wof:placetype":"venue"
},
  "geometry": {"coordinates":[-81.339944,28.666051],"type":"Point"}
}