{
  "type": "Feature",
  "properties": {
    "addr:full":"150 Park Ave Orange Park FL 32073",
    "addr:housenumber":"150",
    "addr:postcode":"32073",
    "addr:street":"Park Ave",
    "iso:country":"US",
    "sg:address":"150 Park Ave",
    "sg:city":"Orange Park",
    "sg:classifiers":[
        {
            "category":"Travel",
            "subcategory":"Hotels & Motels",
            "type":"Entertainment"
        }
    ],
    "sg:phone":"+1 904 264 9513",
    "sg:postcode":"32073",
    "sg:province":"FL",
    "wof:name":"Holiday Inn Jacksonville",
    "wof:placetype":"venue"
},
  "geometry": {"coordinates":[-81.70242399999999,30.186881],"type":"Point"}
}