{
  "type": "Feature",
  "properties": {
    "addr:full":"721 E 11th St Panama City FL 32401",
    "addr:housenumber":"721",
    "addr:postcode":"32401",
    "addr:street":"E 11Th St",
    "iso:country":"US",
    "sg:address":"721 E 11th St",
    "sg:city":"Panama City",
    "sg:classifiers":[
        {
            "category":"Insurance",
            "subcategory":"Hazard Insurance",
            "type":"Services"
        }
    ],
    "sg:phone":"+1 850 522 4240",
    "sg:postcode":"32401",
    "sg:province":"FL",
    "sg:tags":[
        "bond"
    ],
    "wof:name":"I Bond Inc",
    "wof:placetype":"venue"
},
  "geometry": {"coordinates":[-85.649755,30.16785],"type":"Point"}
}