{
  "type": "Feature",
  "properties": {
    "iso:country":"US",
    "sg:address":"440 Edgewood Ave S",
    "sg:city":"Jacksonville",
    "sg:classifiers":[
        {
            "category":"Manufacturing",
            "subcategory":"Printing",
            "type":"Manufacturing & Wholesale Goods"
        }
    ],
    "sg:phone":"+1 904 384 4284",
    "sg:postcode":"32254",
    "sg:province":"FL",
    "sg:tags":[
        "newspaper"
    ],
    "wof:name":"Bullseye Marketing",
    "wof:placetype":"venue"
},
  "geometry": {"coordinates":[-81.725702,30.319201],"type":"Point"}
}