{
  "type": "Feature",
  "properties": {
    "iso:country":"US",
    "sg:address":"9890 N Loop Rd",
    "sg:city":"Pensacola",
    "sg:classifiers":[
        {
            "category":"Professional",
            "subcategory":"Management & Consulting",
            "type":"Services"
        }
    ],
    "sg:phone":"+1 850 492 1860",
    "sg:postcode":"32507",
    "sg:province":"FL",
    "sg:tags":[
        "consultant",
        "business"
    ],
    "wof:name":"JRC Business Offices",
    "wof:placetype":"venue"
},
  "geometry": {"coordinates":[-87.35433399999999,30.353733],"type":"Point"}
}