{
  "type": "Feature",
  "properties": {
    "addr:full":"935 S Atlantic Ave Daytona Beach FL 32118",
    "addr:housenumber":"935",
    "addr:postcode":"32118",
    "addr:street":"S Atlantic Ave",
    "iso:country":"US",
    "sg:address":"935 S Atlantic Ave",
    "sg:city":"Daytona Beach",
    "sg:classifiers":[
        {
            "category":"Professional",
            "subcategory":"Management & Consulting",
            "type":"Services"
        }
    ],
    "sg:phone":"+1 386 257 9868",
    "sg:postcode":"32118",
    "sg:province":"FL",
    "sg:tags":[
        "distributor",
        "material",
        "handling"
    ],
    "wof:name":"Nexus Management Group Lc",
    "wof:placetype":"venue"
},
  "geometry": {"coordinates":[-81.00197799999999,29.213509],"type":"Point"}
}