{
  "type": "Feature",
  "properties": {
    "iso:country":"US",
    "sg:address":"3431 Bonita Beach Rd SW",
    "sg:city":"Bonita Springs",
    "sg:classifiers":[
        {
            "category":"Freight",
            "type":"Transportation"
        }
    ],
    "sg:phone":"+1 239 947 4445",
    "sg:postcode":"34134",
    "sg:province":"FL",
    "sg:tags":[
        "forwarding"
    ],
    "wof:name":"Pak-N-Ship",
    "wof:placetype":"venue"
},
  "geometry": {"coordinates":[-81.809511,26.330585],"type":"Point"}
}