{
  "type": "Feature",
  "properties": {
    "addr:full":"3505 Queen St N St Petersburg FL 33713",
    "addr:housenumber":"3505",
    "addr:postcode":"33713",
    "addr:street":"Queen St N",
    "iso:country":"US",
    "sg:address":"3505 Queen St N",
    "sg:city":"St Petersburg",
    "sg:classifiers":[
        {
            "category":"Building & Trades",
            "subcategory":"Construction",
            "type":"Services"
        }
    ],
    "sg:phone":"+1 727 384 2333",
    "sg:postcode":"33713",
    "sg:province":"FL",
    "sg:tags":[
        "handyman"
    ],
    "wof:name":"Scott C Benke's Handyman Svc",
    "wof:placetype":"venue"
},
  "geometry": {"coordinates":[-82.65737300000001,27.803825],"type":"Point"}
}