{
  "type": "Feature",
  "properties": {
    "iso:country":"US",
    "sg:address":"20 Sea Winds Ln N",
    "sg:city":"Ponte Vedra Beach",
    "sg:classifiers":[
        {
            "category":"Travel",
            "subcategory":"Travel Agent",
            "type":"Entertainment"
        }
    ],
    "sg:phone":"+1 904 285 3922",
    "sg:postcode":"32082",
    "sg:province":"FL",
    "sg:tags":[
        "agency"
    ],
    "wof:name":"Mabry & Mabry Travel LLC",
    "wof:placetype":"venue"
},
  "geometry": {"coordinates":[-81.375905,30.217572],"type":"Point"}
}