{
  "type": "Feature",
  "properties": {
    "iso:country":"US",
    "sg:address":"5170 Riverwood Ave",
    "sg:city":"Sarasota",
    "sg:classifiers":[
        {
            "category":"Personal",
            "type":"Services"
        }
    ],
    "sg:phone":"+1 941 921 4305",
    "sg:postcode":"34231",
    "sg:province":"FL",
    "sg:tags":[
        "miscellaneous"
    ],
    "wof:name":"Greenwood Home Svc",
    "wof:placetype":"venue"
},
  "geometry": {"coordinates":[-82.524795,27.278826],"type":"Point"}
}