{
  "type": "Feature",
  "properties": {
    "iso:country":"US",
    "sg:address":"144 Beach Dr NE",
    "sg:city":"St Petersburg",
    "sg:classifiers":[
        {
            "category":"Shopping",
            "subcategory":"Jewelry",
            "type":"Retail Goods"
        }
    ],
    "sg:phone":"+1 727 823 2000",
    "sg:postcode":"33701",
    "sg:province":"FL",
    "sg:tags":[
        "jeweler"
    ],
    "wof:name":"Bernie's & Son Jewelers",
    "wof:placetype":"venue"
},
  "geometry": {"coordinates":[-82.632758,27.773542],"type":"Point"}
}