{
  "type": "Feature",
  "properties": {
    "iso:country":"US",
    "sg:address":"522 Hogan Dr",
    "sg:city":"Fort Myers",
    "sg:classifiers":[
        {
            "category":"Real Estate",
            "subcategory":"Real Estate Agent",
            "type":"Services"
        }
    ],
    "sg:phone":"+1 239 995 7629",
    "sg:postcode":"33903",
    "sg:province":"FL",
    "wof:name":"Walter W Hutchison Real Estate",
    "wof:placetype":"venue"
},
  "geometry": {"coordinates":[-81.91145299999999,26.691677],"type":"Point"}
}