{
  "type": "Feature",
  "properties": {
    "iso:country":"US",
    "sg:address":"322 S Iowa Ave",
    "sg:city":"Lakeland",
    "sg:classifiers":[
        {
            "category":"Food & Beverages",
            "subcategory":"Groceries & Convenience Stores",
            "type":"Retail Goods"
        }
    ],
    "sg:phone":"+1 863 413 0860",
    "sg:postcode":"33801",
    "sg:province":"FL",
    "sg:tags":[
        "story"
    ],
    "wof:name":"Lake Beulah Food Mart",
    "wof:placetype":"venue"
},
  "geometry": {"coordinates":[-81.953041,28.040558],"type":"Point"}
}