{
  "type": "Feature",
  "properties": {
    "iso:country":"US",
    "sg:address":"8160 W Broward Blvd",
    "sg:city":"Fort Lauderdale",
    "sg:classifiers":[
        {
            "category":"Home & Garden",
            "subcategory":"Furniture",
            "type":"Retail Goods"
        },
        {
            "category":"Shopping",
            "subcategory":"Clothing, Apparel, & Fashions",
            "type":"Retail Goods"
        }
    ],
    "sg:phone":"+1 954 423 6644",
    "sg:postcode":"33317",
    "sg:province":"FL",
    "sg:tags":[
        "baby",
        "accessory"
    ],
    "wof:name":"Crib & Teen City Expo Fla LLC",
    "wof:placetype":"venue"
},
  "geometry": {"coordinates":[-80.258849,26.120673],"type":"Point"}
}