{
  "type": "Feature",
  "properties": {
    "addr:full":"2142 Reynolds St Sarasota FL 34231",
    "addr:housenumber":"2142",
    "addr:postcode":"34231",
    "addr:street":"Reynolds St",
    "iso:country":"US",
    "sg:address":"2142 Reynolds St",
    "sg:city":"Sarasota",
    "sg:classifiers":[
        {
            "category":"Social Services",
            "subcategory":"Child Care",
            "type":"Services"
        }
    ],
    "sg:phone":"+1 941 925 3791",
    "sg:postcode":"34231",
    "sg:province":"FL",
    "sg:tags":[
        "day"
    ],
    "wof:name":"Momma Sstos Preschool Day Schl",
    "wof:placetype":"venue"
},
  "geometry": {"coordinates":[-82.517551,27.255903],"type":"Point"}
}