{
  "type": "Feature",
  "properties": {
    "iso:country":"US",
    "sg:address":"1204 S Broad St",
    "sg:city":"Brooksville",
    "sg:classifiers":[
        {
            "category":"Shopping",
            "type":"Retail Goods"
        }
    ],
    "sg:phone":"+1 352 544 0620",
    "sg:postcode":"34601",
    "sg:province":"FL",
    "sg:tags":[
        "telephone",
        "cellular"
    ],
    "wof:name":"Cellular Safari",
    "wof:placetype":"venue"
},
  "geometry": {"coordinates":[-82.402818,28.542187],"type":"Point"}
}