{
  "type": "Feature",
  "properties": {
    "iso:country":"US",
    "sg:address":"22237 Laver Ln",
    "sg:city":"Land O Lakes",
    "sg:classifiers":[
        {
            "category":"Building & Trades",
            "subcategory":"Construction",
            "type":"Services"
        }
    ],
    "sg:phone":"+1 813 996 1070",
    "sg:postcode":"34639",
    "sg:province":"FL",
    "sg:tags":[
        "painter"
    ],
    "wof:name":"Anderson Painting LL",
    "wof:placetype":"venue"
},
  "geometry": {"coordinates":[-82.44949200000001,28.214532],"type":"Point"}
}