{
  "type": "Feature",
  "properties": {
    "addr:full":"11740 SW 178th Ter Miami FL 33177",
    "addr:housenumber":"11740",
    "addr:postcode":"33177",
    "addr:street":"Sw 178Th Ter",
    "iso:country":"US",
    "sg:address":"11740 SW 178th Ter",
    "sg:city":"Miami",
    "sg:classifiers":[
        {
            "category":"Building & Trades",
            "subcategory":"Landscaping Services",
            "type":"Services"
        }
    ],
    "sg:phone":"+1 305 233 5126",
    "sg:postcode":"33177",
    "sg:province":"FL",
    "sg:tags":[
        "tree"
    ],
    "wof:name":"Alex Carmenate Landscaping",
    "wof:placetype":"venue"
},
  "geometry": {"coordinates":[-80.382098,25.602755],"type":"Point"}
}