{
  "type": "Feature",
  "properties": {
    "iso:country":"US",
    "sg:address":"1178 NW 54th St",
    "sg:city":"Miami",
    "sg:classifiers":[
        {
            "category":"Personal",
            "subcategory":"Beauty Salon",
            "type":"Services"
        }
    ],
    "sg:phone":"+1 305 757 1222",
    "sg:postcode":"33127",
    "sg:province":"FL",
    "wof:name":"Miami Hair & Nail Studio",
    "wof:placetype":"venue"
},
  "geometry": {"coordinates":[-80.21479100000001,25.824664],"type":"Point"}
}