{
  "type": "Feature",
  "properties": {
    "iso:country":"US",
    "sg:address":"107 NE 1st Ave",
    "sg:city":"Ocala",
    "sg:classifiers":[
        {
            "category":"Professional",
            "subcategory":"Accounting & Tax Preparation",
            "type":"Services"
        }
    ],
    "sg:phone":"+1 352 274 9535",
    "sg:postcode":"34470",
    "sg:province":"FL",
    "sg:tags":[
        "payroll",
        "public",
        "accountants-certified"
    ],
    "wof:name":"Berryhill Hoffman & Getsee PA",
    "wof:placetype":"venue"
},
  "geometry": {"coordinates":[-82.135947,29.18785],"type":"Point"}
}