{
  "type": "Feature",
  "properties": {
    "iso:country":"US",
    "sg:address":"6400 International Dr",
    "sg:city":"Orlando",
    "sg:classifiers":[
        {
            "category":"Shopping",
            "subcategory":"Gifts & Souvenirs",
            "type":"Retail Goods"
        }
    ],
    "sg:phone":"+1 407 264 9559",
    "sg:postcode":"32819",
    "sg:province":"FL",
    "sg:tags":[
        "shop"
    ],
    "wof:name":"Gold Castle Inc",
    "wof:placetype":"venue"
},
  "geometry": {"coordinates":[-81.465062,28.462268],"type":"Point"}
}