{
  "type": "Feature",
  "properties": {
    "iso:country":"US",
    "sg:address":"10600 Crimson Ln",
    "sg:city":"New Port Richey",
    "sg:classifiers":[
        {
            "category":"Professional",
            "type":"Services"
        }
    ],
    "sg:phone":"+1 727 372 3585",
    "sg:postcode":"34655",
    "sg:province":"FL",
    "wof:name":"Franklin L Wotring",
    "wof:placetype":"venue"
},
  "geometry": {"coordinates":[-82.63902400000001,28.198406],"type":"Point"}
}