{
  "type": "Feature",
  "properties": {
    "iso:country":"US",
    "sg:address":"3379 E Colonial Dr",
    "sg:city":"Orlando",
    "sg:classifiers":[
        {
            "category":"Shopping",
            "subcategory":"Jewelry",
            "type":"Retail Goods"
        }
    ],
    "sg:phone":"+1 407 895 1114",
    "sg:postcode":"32803",
    "sg:province":"FL",
    "sg:tags":[
        "jeweler"
    ],
    "wof:name":"Lundstrom Jewelers",
    "wof:placetype":"venue"
},
  "geometry": {"coordinates":[-81.341086,28.553454],"type":"Point"}
}