{
  "type": "Feature",
  "properties": {
    "iso:country":"US",
    "sg:address":"8127 NW 29th St",
    "sg:city":"Doral",
    "sg:classifiers":[
        {
            "category":"Freight",
            "type":"Transportation"
        },
        {
            "category":"Retail",
            "subcategory":"Storage",
            "type":"Services"
        }
    ],
    "sg:phone":"+1 305 640 0550",
    "sg:postcode":"33122",
    "sg:province":"FL",
    "sg:tags":[
        "cargo",
        "container"
    ],
    "wof:name":"Frogs Cargo Corp",
    "wof:placetype":"venue"
},
  "geometry": {"coordinates":[-80.32811100000001,25.800742],"type":"Point"}
}