{
  "type": "Feature",
  "properties": {
    "addr:full":"1034 Woodland Dr Lakeland FL 33809",
    "addr:housenumber":"1034",
    "addr:postcode":"33809",
    "addr:street":"Woodland Dr",
    "iso:country":"US",
    "sg:address":"1034 Woodland Dr",
    "sg:city":"Lakeland",
    "sg:classifiers":[
        {
            "category":"Building & Trades",
            "subcategory":"Construction",
            "type":"Services"
        },
        {
            "category":"Insurance",
            "subcategory":"Insurance Agent",
            "type":"Services"
        }
    ],
    "sg:phone":"+1 863 859 3066",
    "sg:postcode":"33809",
    "sg:province":"FL",
    "sg:tags":[
        "apartment",
        "family",
        "insured",
        "home",
        "property",
        "remodeling",
        "replacement"
    ],
    "wof:name":"David Brothers Construction",
    "wof:placetype":"venue"
},
  "geometry": {"coordinates":[-81.97218100000001,28.088867],"type":"Point"}
}