{
  "type": "Feature",
  "properties": {
    "addr:full":"5925 Imperial Pkwy Mulberry FL 33860",
    "addr:housenumber":"5925",
    "addr:postcode":"33860",
    "addr:street":"Imperial Pkwy",
    "iso:country":"US",
    "sg:address":"5925 Imperial Pkwy",
    "sg:city":"Mulberry",
    "sg:classifiers":[
        {
            "category":"Restaurant",
            "type":"Food & Drink"
        }
    ],
    "sg:phone":"+1 863 644 7447",
    "sg:postcode":"33860",
    "sg:province":"FL",
    "wof:name":"Imperial Pizza",
    "wof:placetype":"venue"
},
  "geometry": {"coordinates":[-81.986711,27.937017],"type":"Point"}
}