{
  "type": "Feature",
  "properties": {
    "iso:country":"US",
    "sg:address":"4797 NW 72nd Ave",
    "sg:city":"Miami",
    "sg:classifiers":[
        {
            "category":"Wholesale",
            "subcategory":"Groceries",
            "type":"Manufacturing & Wholesale Goods"
        },
        {
            "category":"Food & Beverages",
            "subcategory":"Groceries & Convenience Stores",
            "type":"Retail Goods"
        }
    ],
    "sg:phone":"+1 305 482 9818",
    "sg:postcode":"33166",
    "sg:province":"FL",
    "sg:tags":[
        "products-wholesale"
    ],
    "wof:name":"Sabanero Inc",
    "wof:placetype":"venue"
},
  "geometry": {"coordinates":[-80.31339199999999,25.817046],"type":"Point"}
}