{
  "type": "Feature",
  "properties": {
    "iso:country":"US",
    "sg:address":"1629 W 33rd Pl",
    "sg:city":"Hialeah",
    "sg:classifiers":[
        {
            "category":"Home & Garden",
            "subcategory":"Building Materials",
            "type":"Retail Goods"
        }
    ],
    "sg:phone":"+1 305 556 7289",
    "sg:postcode":"33012",
    "sg:province":"FL",
    "sg:tags":[
        "windows"
    ],
    "wof:name":"Sunshine Windows",
    "wof:placetype":"venue"
},
  "geometry": {"coordinates":[-80.317241,25.852145],"type":"Point"}
}