{
  "type": "Feature",
  "properties": {
    "iso:country":"US",
    "sg:address":"733 Palm Ave",
    "sg:city":"Hialeah",
    "sg:classifiers":[
        {
            "category":"Personal",
            "subcategory":"Barber",
            "type":"Services"
        }
    ],
    "sg:phone":"+1 305 888 6955",
    "sg:postcode":"33010",
    "sg:province":"FL",
    "wof:name":"Perfection Barber Shop",
    "wof:placetype":"venue"
},
  "geometry": {"coordinates":[-80.281403,25.828413],"type":"Point"}
}