{
  "type": "Feature",
  "properties": {
    "addr:full":"1890 N University Dr Pompano Beach FL 33071",
    "addr:housenumber":"1890",
    "addr:postcode":"33071",
    "addr:street":"N University Dr",
    "iso:country":"US",
    "sg:address":"1890 N University Dr",
    "sg:city":"Pompano Beach",
    "sg:classifiers":[
        {
            "category":"Social Services",
            "type":"Services"
        }
    ],
    "sg:phone":"+1 954 227 2700",
    "sg:postcode":"33071",
    "sg:province":"FL",
    "wof:name":"Siegel Judith Lcsw",
    "wof:placetype":"venue"
},
  "geometry": {"coordinates":[-80.25308699999999,26.251107],"type":"Point"}
}