{
  "type": "Feature",
  "properties": {
    "addr:full":"1 Corporate Center Tampa FL 33607",
    "addr:housenumber":"1",
    "addr:postcode":"33607",
    "iso:country":"US",
    "sg:address":"1 Corporate Center",
    "sg:city":"Tampa",
    "sg:classifiers":[
        {
            "category":"Professional",
            "subcategory":"Research",
            "type":"Services"
        }
    ],
    "sg:phone":"+1 813 639 7530",
    "sg:postcode":"33607",
    "sg:province":"FL",
    "sg:website":"http://www.spectralimage.com",
    "wof:name":"Spectral Image",
    "wof:placetype":"venue"
},
  "geometry": {"coordinates":[-82.542582,28.001185],"type":"Point"}
}