{
  "type": "Feature",
  "properties": {
    "addr:full":"3030 Hartley Rd Jacksonville FL 32257",
    "addr:housenumber":"3030",
    "addr:postcode":"32257",
    "addr:street":"Hartley Rd",
    "iso:country":"US",
    "sg:address":"3030 Hartley Rd",
    "sg:city":"Jacksonville",
    "sg:classifiers":[
        {
            "category":"Banks & Credit Unions",
            "subcategory":"Bank",
            "type":"Services"
        }
    ],
    "sg:phone":"+1 904 880 6445",
    "sg:postcode":"32257",
    "sg:province":"FL",
    "sg:tags":[
        "loan",
        "real estate"
    ],
    "wof:name":"Countrywide Home Loans",
    "wof:placetype":"venue"
},
  "geometry": {"coordinates":[-81.631045,30.185027],"type":"Point"}
}