{
  "type": "Feature",
  "properties": {
    "iso:country":"US",
    "sg:address":"430 Cove Tower Dr",
    "sg:city":"Naples",
    "sg:classifiers":[
        {
            "category":"Autos & Motor Vehicles",
            "subcategory":"Auto Supplies",
            "type":"Retail Goods"
        }
    ],
    "sg:phone":"+1 239 598 4812",
    "sg:postcode":"34110",
    "sg:province":"FL",
    "wof:name":"Ralph W Firestone",
    "wof:placetype":"venue"
},
  "geometry": {"coordinates":[-81.813104,26.290995],"type":"Point"}
}