{
  "type": "Feature",
  "properties": {
    "iso:country":"US",
    "sg:address":"8325 NE 2nd Ave",
    "sg:city":"Miami",
    "sg:classifiers":[
        {
            "category":"Education",
            "subcategory":"Vocational School",
            "type":"Public Place"
        }
    ],
    "sg:phone":"+1 305 754 9000",
    "sg:postcode":"33138",
    "sg:province":"FL",
    "sg:tags":[
        "nurse"
    ],
    "wof:name":"Christine Geanbaci",
    "wof:placetype":"venue"
},
  "geometry": {"coordinates":[-80.19281599999999,25.850363],"type":"Point"}
}