{
  "type": "Feature",
  "properties": {
    "iso:country":"US",
    "sg:address":"11125 Laxton St",
    "sg:city":"Orlando",
    "sg:classifiers":[
        {
            "category":"Freight",
            "type":"Transportation"
        }
    ],
    "sg:phone":"+1 407 855 2383",
    "sg:postcode":"32824",
    "sg:province":"FL",
    "sg:tags":[
        "hauling",
        "trucking"
    ],
    "wof:name":"JLS Hauling",
    "wof:placetype":"venue"
},
  "geometry": {"coordinates":[-81.357349,28.396058],"type":"Point"}
}