{
  "type": "Feature",
  "properties": {
    "addr:full":"355 NW 170th St Miami FL 33169",
    "addr:housenumber":"355",
    "addr:postcode":"33169",
    "addr:street":"Nw 170Th St",
    "iso:country":"US",
    "sg:address":"355 NW 170th St",
    "sg:city":"Miami",
    "sg:classifiers":[
        {
            "category":"Retail",
            "subcategory":"Auto Repair",
            "type":"Services"
        }
    ],
    "sg:phone":"+1 305 653 5588",
    "sg:postcode":"33169",
    "sg:province":"FL",
    "sg:tags":[
        "general"
    ],
    "wof:name":"Swedish Motors Inc",
    "wof:placetype":"venue"
},
  "geometry": {"coordinates":[-80.208156,25.930612],"type":"Point"}
}