{
  "type": "Feature",
  "properties": {
    "addr:full":"16510 N Dale Mabry Hwy Tampa FL 33618",
    "addr:housenumber":"16510",
    "addr:postcode":"33618",
    "addr:street":"N Dale Mabry Hwy",
    "iso:country":"US",
    "sg:address":"16510 N Dale Mabry Hwy",
    "sg:city":"Tampa",
    "sg:classifiers":[
        {
            "category":"Communications",
            "subcategory":"Film & Video Production",
            "type":"Services"
        }
    ],
    "sg:phone":"+1 813 948 9595",
    "sg:postcode":"33618",
    "sg:province":"FL",
    "sg:tags":[
        "editing",
        "tape"
    ],
    "wof:name":"C W Craig Productions",
    "wof:placetype":"venue"
},
  "geometry": {"coordinates":[-82.50242,28.108097],"type":"Point"}
}