{
  "type": "Feature",
  "properties": {
    "iso:country":"US",
    "sg:address":"56 NW 180 St",
    "sg:city":"Cross City",
    "sg:classifiers":[
        {
            "category":"Wholesale",
            "subcategory":"Auto Parts",
            "type":"Manufacturing & Wholesale Goods"
        }
    ],
    "sg:phone":"+1 352 498 2528",
    "sg:postcode":"32669",
    "sg:province":"FL",
    "sg:tags":[
        "automobile",
        "rebuilt"
    ],
    "wof:name":"Cross City Cars & Parts",
    "wof:placetype":"venue"
},
  "geometry": {"coordinates":[-82.53395,29.655824],"type":"Point"}
}