{
  "type": "Feature",
  "properties": {
    "addr:full":"1782 W 68th St Hialeah FL 33014",
    "addr:housenumber":"1782",
    "addr:postcode":"33014",
    "addr:street":"W 68Th St",
    "iso:country":"US",
    "sg:address":"1782 W 68th St",
    "sg:city":"Hialeah",
    "sg:classifiers":[
        {
            "category":"Restaurant",
            "type":"Food & Drink"
        }
    ],
    "sg:phone":"+1 305 698 6800",
    "sg:postcode":"33014",
    "sg:province":"FL",
    "sg:tags":[
        "parlor",
        "ice",
        "cream"
    ],
    "wof:name":"Party Ice Cream",
    "wof:placetype":"venue"
},
  "geometry": {"coordinates":[-80.319154,25.884025],"type":"Point"}
}