{
  "type": "Feature",
  "properties": {
    "addr:full":"11076 Spring Hill Dr Spring Hill FL 34608",
    "addr:housenumber":"11076",
    "addr:postcode":"34608",
    "addr:street":"Spring Hill Dr",
    "iso:country":"US",
    "sg:address":"11076 Spring Hill Dr",
    "sg:city":"Spring Hill",
    "sg:classifiers":[
        {
            "category":"Sports & Exercise",
            "subcategory":"Gym",
            "type":"Entertainment"
        }
    ],
    "sg:phone":"+1 352 666 0665",
    "sg:postcode":"34608",
    "sg:province":"FL",
    "sg:tags":[
        "facility"
    ],
    "wof:name":"Curves of Spring Hills SW",
    "wof:placetype":"venue"
},
  "geometry": {"coordinates":[-82.54202100000001,28.460991],"type":"Point"}
}