{
  "type": "Feature",
  "properties": {
    "iso:country":"US",
    "sg:address":"4801 NW 36th St",
    "sg:city":"Miami Springs",
    "sg:classifiers":[
        {
            "category":"Retail",
            "subcategory":"Auto Rental",
            "type":"Services"
        }
    ],
    "sg:phone":"+1 305 888 8448",
    "sg:postcode":"33166",
    "sg:province":"FL",
    "sg:tags":[
        "renting",
        "automobile"
    ],
    "wof:name":"Exotic Toys Car Rental",
    "wof:placetype":"venue"
},
  "geometry": {"coordinates":[-80.27647399999999,25.808035],"type":"Point"}
}