{
  "type": "Feature",
  "properties": {
    "addr:full":"5505 N Atlantic Ave Ste 101 Cocoa Beach FL 32931",
    "addr:housenumber":"5505",
    "addr:postcode":"32931",
    "addr:street":"N Atlantic Ave Ste 101",
    "iso:country":"US",
    "sg:address":"5505 N Atlantic Ave Ste 101",
    "sg:city":"Cocoa Beach",
    "sg:classifiers":[
        {
            "category":"Personal",
            "subcategory":"Nail Salon",
            "type":"Services"
        }
    ],
    "sg:phone":"+1 321 784 2148",
    "sg:postcode":"32931",
    "sg:province":"FL",
    "wof:name":"Stylz",
    "wof:placetype":"venue"
},
  "geometry": {"coordinates":[-80.6082,28.368106],"type":"Point"}
}