{
  "type": "Feature",
  "properties": {
    "iso:country":"US",
    "sg:address":"12160 NW 46th St",
    "sg:city":"Pompano Beach",
    "sg:classifiers":[
        {
            "category":"Real Estate",
            "subcategory":"Real Estate Agent",
            "type":"Services"
        }
    ],
    "sg:phone":"+1 954 227 3605",
    "sg:postcode":"33076",
    "sg:province":"FL",
    "wof:name":"Ali Abbas Dhanji PA",
    "wof:placetype":"venue"
},
  "geometry": {"coordinates":[-80.289805,26.288164],"type":"Point"}
}