{
  "type": "Feature",
  "properties": {
    "iso:country":"US",
    "sg:address":"618 S Commerce Ave",
    "sg:city":"Sebring",
    "sg:classifiers":[
        {
            "category":"Building & Trades",
            "subcategory":"Pest Control",
            "type":"Services"
        }
    ],
    "sg:phone":"+1 863 385 2283",
    "sg:postcode":"33870",
    "sg:province":"FL",
    "wof:name":"Helen Havery Pest Control",
    "wof:placetype":"venue"
},
  "geometry": {"coordinates":[-81.435788,27.491282],"type":"Point"}
}