{
  "type": "Feature",
  "properties": {
    "addr:full":"1565 Forest Ave Winter Park FL 32789",
    "addr:housenumber":"1565",
    "addr:postcode":"32789",
    "addr:street":"Forest Ave",
    "iso:country":"US",
    "sg:address":"1565 Forest Ave",
    "sg:city":"Winter Park",
    "sg:classifiers":[
        {
            "category":"Restaurant",
            "type":"Food & Drink"
        }
    ],
    "sg:phone":"+1 407 645 5210",
    "sg:postcode":"32789",
    "sg:province":"FL",
    "sg:tags":[
        "eating"
    ],
    "wof:name":"Ultimate Bagel Inc",
    "wof:placetype":"venue"
},
  "geometry": {"coordinates":[-81.34693300000001,28.582798],"type":"Point"}
}