{
  "type": "Feature",
  "properties": {
    "addr:full":"9010 Unicorn Ave Port Richey FL 34668",
    "addr:housenumber":"9010",
    "addr:postcode":"34668",
    "addr:street":"Unicorn Ave",
    "iso:country":"US",
    "sg:address":"9010 Unicorn Ave",
    "sg:city":"Port Richey",
    "sg:classifiers":[
        {
            "category":"Personal",
            "subcategory":"Beauty Salon",
            "type":"Services"
        }
    ],
    "sg:phone":"+1 727 848 6476",
    "sg:postcode":"34668",
    "sg:province":"FL",
    "wof:name":"Sandy's Beauty Shop",
    "wof:placetype":"venue"
},
  "geometry": {"coordinates":[-82.707508,28.288419],"type":"Point"}
}