{
  "type": "Feature",
  "properties": {
    "iso:country":"US",
    "sg:address":"298 N Lawrence Blvd",
    "sg:city":"Keystone Heights",
    "sg:classifiers":[
        {
            "category":"Banks & Credit Unions",
            "subcategory":"Bank",
            "type":"Services"
        }
    ],
    "sg:phone":"+1 352 473 5522",
    "sg:postcode":"32656",
    "sg:province":"FL",
    "sg:tags":[
        "loan",
        "real estate"
    ],
    "wof:name":"Market Street Mortgage Corp",
    "wof:placetype":"venue"
},
  "geometry": {"coordinates":[-82.03130899999999,29.785729],"type":"Point"}
}