{
  "type": "Feature",
  "properties": {
    "addr:full":"174 Clinton Cemetery Rd Edgewater FL 32141",
    "addr:housenumber":"174",
    "addr:postcode":"32141",
    "addr:street":"Clinton Cemetery Rd",
    "iso:country":"US",
    "sg:address":"174 Clinton Cemetery Rd",
    "sg:city":"Edgewater",
    "sg:classifiers":[
        {
            "category":"Retail",
            "subcategory":"Veterinary Services",
            "type":"Services"
        }
    ],
    "sg:phone":"+1 386 345 3909",
    "sg:postcode":"32141",
    "sg:province":"FL",
    "wof:name":"Kitten Jones Lighthouse Animal",
    "wof:placetype":"venue"
},
  "geometry": {"coordinates":[-80.877143,28.915507],"type":"Point"}
}