{
  "type": "Feature",
  "properties": {
    "iso:country":"US",
    "sg:address":"6051 16th Ave N",
    "sg:city":"St Petersburg",
    "sg:classifiers":[
        {
            "category":"Retail",
            "subcategory":"Repair Shop",
            "type":"Services"
        }
    ],
    "sg:phone":"+1 727 344 2240",
    "sg:postcode":"33710",
    "sg:province":"FL",
    "sg:tags":[
        "lock",
        "locksmith"
    ],
    "wof:name":"A Kline & Son Locksmith",
    "wof:placetype":"venue"
},
  "geometry": {"coordinates":[-82.715692,27.78739],"type":"Point"}
}