{
  "type": "Feature",
  "properties": {
    "addr:full":"238 Pine Hov Cir Greenacres FL 33463",
    "addr:housenumber":"238",
    "addr:postcode":"33463",
    "addr:street":"Pine Hov Cir",
    "iso:country":"US",
    "sg:address":"238 Pine Hov Cir",
    "sg:city":"Greenacres",
    "sg:classifiers":[
        {
            "category":"Building & Trades",
            "subcategory":"Electrical",
            "type":"Services"
        },
        {
            "category":"Professional",
            "subcategory":"Management & Consulting",
            "type":"Services"
        }
    ],
    "sg:phone":"+1 561 735 4475",
    "sg:postcode":"33463",
    "sg:province":"FL",
    "sg:tags":[
        "consultant",
        "lighting",
        "electrical",
        "contractor"
    ],
    "wof:name":"Security Illuminations Inc",
    "wof:placetype":"venue"
},
  "geometry": {"coordinates":[-80.13378899999999,26.610908],"type":"Point"}
}