{
  "type": "Feature",
  "properties": {
    "iso:country":"US",
    "sg:address":"1001 NW 31 Dr",
    "sg:city":"Gainesville",
    "sg:classifiers":[
        {
            "category":"Recreation",
            "type":"Entertainment"
        }
    ],
    "sg:phone":"+1 352 334 2187",
    "sg:postcode":"32605",
    "sg:province":"FL",
    "sg:tags":[
        "pool",
        "swimming"
    ],
    "wof:name":"H Spurgeon Cherry Pool",
    "wof:placetype":"venue"
},
  "geometry": {"coordinates":[-82.369379,29.661171],"type":"Point"}
}