{
  "type": "Feature",
  "properties": {
    "iso:country":"US",
    "sg:address":"1611 Wood Duck Dr",
    "sg:city":"Winter Springs",
    "sg:classifiers":[
        {
            "category":"Professional",
            "subcategory":"Engineering",
            "type":"Services"
        }
    ],
    "sg:phone":"+1 407 365 4468",
    "sg:postcode":"32708",
    "sg:province":"FL",
    "wof:name":"Mitzo Engineering Inc",
    "wof:placetype":"venue"
},
  "geometry": {"coordinates":[-81.233738,28.673184],"type":"Point"}
}