{
  "type": "Feature",
  "properties": {
    "addr:full":"7451 Riviero Blvd Hollywood FL 33023",
    "addr:housenumber":"7451",
    "addr:postcode":"33023",
    "addr:street":"Riviero Blvd",
    "iso:country":"US",
    "sg:address":"7451 Riviero Blvd",
    "sg:city":"Hollywood",
    "sg:classifiers":[
        {
            "category":"Education",
            "subcategory":"Special Training",
            "type":"Public Place"
        }
    ],
    "sg:phone":"+1 954 961 2911",
    "sg:postcode":"33023",
    "sg:province":"FL",
    "sg:tags":[
        "school"
    ],
    "wof:name":"Parkway Acdemy Chrtr High Schl",
    "wof:placetype":"venue"
},
  "geometry": {"coordinates":[-80.23827300000001,25.973377],"type":"Point"}
}