{
  "type": "Feature",
  "properties": {
    "iso:country":"US",
    "sg:address":"1951 SW 172nd Ave",
    "sg:city":"Miramar",
    "sg:classifiers":[
        {
            "category":"Health Services",
            "subcategory":"Doctor",
            "type":"Services"
        }
    ],
    "sg:phone":"+1 305 823 6270",
    "sg:postcode":"33029",
    "sg:province":"FL",
    "sg:tags":[
        "physician",
        "surgeon"
    ],
    "wof:name":"Castillo-Plaza & Assoc Inc",
    "wof:placetype":"venue"
},
  "geometry": {"coordinates":[-80.375585,25.989838],"type":"Point"}
}