{
  "type": "Feature",
  "properties": {
    "iso:country":"US",
    "sg:address":"3800 N Nebraska Ave",
    "sg:city":"Tampa",
    "sg:classifiers":[
        {
            "category":"Organizations",
            "subcategory":"Religious Organization",
            "type":"Services"
        }
    ],
    "sg:phone":"+1 813 224 0098",
    "sg:postcode":"33603",
    "sg:province":"FL",
    "wof:name":"Harvest Fellowship Bb Church",
    "wof:placetype":"venue"
},
  "geometry": {"coordinates":[-82.45115699999999,27.979668],"type":"Point"}
}