{
  "type": "Feature",
  "properties": {
    "addr:full":"1559 E Merritt Island Cswy Merritt Island FL 32952",
    "addr:housenumber":"1559",
    "addr:postcode":"32952",
    "addr:street":"E",
    "iso:country":"US",
    "sg:address":"1559 E Merritt Island Cswy",
    "sg:city":"Merritt Island",
    "sg:classifiers":[
        {
            "category":"Retail",
            "subcategory":"Auto Repair",
            "type":"Services"
        }
    ],
    "sg:phone":"+1 321 452 7111",
    "sg:postcode":"32952",
    "sg:province":"FL",
    "sg:tags":[
        "body",
        "shop"
    ],
    "wof:name":"Buddyboys Auto Painting & Body Works",
    "wof:placetype":"venue"
},
  "geometry": {"coordinates":[-80.668404,28.357201],"type":"Point"}
}