{
  "type": "Feature",
  "properties": {
    "iso:country":"US",
    "sg:address":"7033 Commonwealth Ave",
    "sg:city":"Jacksonville",
    "sg:classifiers":[
        {
            "category":"Professional",
            "subcategory":"Employment Agencies",
            "type":"Services"
        }
    ],
    "sg:phone":"+1 904 693 3686",
    "sg:postcode":"32220",
    "sg:province":"FL",
    "sg:tags":[
        "opportunity"
    ],
    "wof:name":"Resource MFG",
    "wof:placetype":"venue"
},
  "geometry": {"coordinates":[-81.76393899999999,30.335699],"type":"Point"}
}