{
  "type": "Feature",
  "properties": {
    "iso:country":"US",
    "sg:address":"1150 N 28th St",
    "sg:city":"Tampa",
    "sg:classifiers":[
        {
            "category":"Freight",
            "type":"Transportation"
        }
    ],
    "sg:phone":"+1 813 248 1551",
    "sg:postcode":"33605",
    "sg:province":"FL",
    "sg:tags":[
        "warehouse",
        "public"
    ],
    "wof:name":"Global Warehousing",
    "wof:placetype":"venue"
},
  "geometry": {"coordinates":[-82.428139,27.955438],"type":"Point"}
}