{
  "type": "Feature",
  "properties": {
    "iso:country":"US",
    "sg:address":"11400 NW 32nd Ave",
    "sg:city":"Miami",
    "sg:classifiers":[
        {
            "category":"Freight",
            "type":"Transportation"
        }
    ],
    "sg:phone":"+1 305 769 1442",
    "sg:postcode":"33147",
    "sg:province":"FL",
    "sg:tags":[
        "distance",
        "trucking",
        "storage",
        "long",
        "local"
    ],
    "wof:name":"FMI International LLC",
    "wof:placetype":"venue"
},
  "geometry": {"coordinates":[-80.25124099999999,25.879875],"type":"Point"}
}