{
  "type": "Feature",
  "properties": {
    "addr:full":"120 Park St Lake Placid FL 33852",
    "addr:housenumber":"120",
    "addr:postcode":"33852",
    "addr:street":"Park St",
    "iso:country":"US",
    "sg:address":"120 Park St",
    "sg:city":"Lake Placid",
    "sg:classifiers":[
        {
            "category":"Organizations",
            "subcategory":"Religious Organization",
            "type":"Services"
        }
    ],
    "sg:phone":"+1 863 699 0032",
    "sg:postcode":"33852",
    "sg:province":"FL",
    "sg:tags":[
        "church"
    ],
    "wof:name":"Bethel AME Church",
    "wof:placetype":"venue"
},
  "geometry": {"coordinates":[-81.35215100000001,27.279194],"type":"Point"}
}