{
  "type": "Feature",
  "properties": {
    "iso:country":"US",
    "sg:address":"1481 S Prescott Ave",
    "sg:city":"Clearwater",
    "sg:classifiers":[
        {
            "category":"Building & Trades",
            "subcategory":"Landscaping Services",
            "type":"Services"
        }
    ],
    "sg:phone":"+1 727 447 7613",
    "sg:postcode":"33756",
    "sg:province":"FL",
    "wof:name":"L&G Lawn Service",
    "wof:placetype":"venue"
},
  "geometry": {"coordinates":[-82.78430899999999,27.944033],"type":"Point"}
}