{
  "type": "Feature",
  "properties": {
    "addr:full":"6821 Heritage Dr Port St Lucie FL 34952",
    "addr:housenumber":"6821",
    "addr:postcode":"34952",
    "addr:street":"Heritage Dr",
    "iso:country":"US",
    "sg:address":"6821 Heritage Dr",
    "sg:city":"Port St Lucie",
    "sg:classifiers":[
        {
            "category":"Retail",
            "subcategory":"Auto Repair",
            "type":"Services"
        }
    ],
    "sg:phone":"+1 772 464 7182",
    "sg:postcode":"34952",
    "sg:province":"FL",
    "sg:tags":[
        "repairing",
        "automobile"
    ],
    "wof:name":"F & M Auto Repair",
    "wof:placetype":"venue"
},
  "geometry": {"coordinates":[-80.327799,27.34052],"type":"Point"}
}