{
  "type": "Feature",
  "properties": {
    "iso:country":"US",
    "sg:address":"8224 Biscayne Blvd",
    "sg:city":"Miami",
    "sg:classifiers":[
        {
            "category":"Personal",
            "subcategory":"Beauty Salon",
            "type":"Services"
        }
    ],
    "sg:phone":"+1 305 754 0205",
    "sg:postcode":"33138",
    "sg:province":"FL",
    "wof:name":"Suprize Barber & Beauty Salon",
    "wof:placetype":"venue"
},
  "geometry": {"coordinates":[-80.184798,25.850499],"type":"Point"}
}