{
  "type": "Feature",
  "properties": {
    "iso:country":"US",
    "sg:address":"151 NW 2nd Ave Nr",
    "sg:city":"Miami",
    "sg:classifiers":[
        {
            "category":"Food & Beverages",
            "subcategory":"Groceries & Convenience Stores",
            "type":"Retail Goods"
        }
    ],
    "sg:phone":"+1 305 945 7452",
    "sg:postcode":"33169",
    "sg:province":"FL",
    "wof:name":"R M K Son E W Indian Grocery",
    "wof:placetype":"venue"
},
  "geometry": {"coordinates":[-80.20536,25.949435],"type":"Point"}
}