{
  "type": "Feature",
  "properties": {
    "addr:full":"4783 23rd Pl N West Palm Beach FL 33417",
    "addr:housenumber":"4783",
    "addr:postcode":"33417",
    "addr:street":"23Rd Pl N",
    "iso:country":"US",
    "sg:address":"4783 23rd Pl N",
    "sg:city":"West Palm Beach",
    "sg:classifiers":[
        {
            "category":"Shopping",
            "subcategory":"Gifts & Souvenirs",
            "type":"Retail Goods"
        }
    ],
    "sg:phone":"+1 561 697 4465",
    "sg:postcode":"33417",
    "sg:province":"FL",
    "sg:tags":[
        "shop",
        "novelty"
    ],
    "wof:name":"Stained Glass Nite Lites",
    "wof:placetype":"venue"
},
  "geometry": {"coordinates":[-80.117486,26.712017],"type":"Point"}
}