{
  "type": "Feature",
  "properties": {
    "addr:full":"13899 SW 142nd Ave Miami FL 33186",
    "addr:housenumber":"13899",
    "addr:postcode":"33186",
    "addr:street":"Sw 142Nd Ave",
    "iso:country":"US",
    "sg:address":"13899 SW 142nd Ave",
    "sg:city":"Miami",
    "sg:classifiers":[
        {
            "category":"Building & Trades",
            "subcategory":"Construction",
            "type":"Services"
        }
    ],
    "sg:phone":"+1 786 242 6300",
    "sg:postcode":"33186",
    "sg:province":"FL",
    "sg:tags":[
        "windows"
    ],
    "wof:name":"American Boys Inc",
    "wof:placetype":"venue"
},
  "geometry": {"coordinates":[-80.42281199999999,25.639908],"type":"Point"}
}