{
  "type": "Feature",
  "properties": {
    "iso:country":"US",
    "sg:address":"4505 Webster St",
    "sg:city":"Tampa",
    "sg:classifiers":[
        {
            "category":"Professional",
            "subcategory":"Management & Consulting",
            "type":"Services"
        }
    ],
    "sg:phone":"+1 813 663 3709",
    "sg:postcode":"33610",
    "sg:province":"FL",
    "wof:name":"Hazel Conyers",
    "wof:placetype":"venue"
},
  "geometry": {"coordinates":[-82.420934,27.986911],"type":"Point"}
}