{
  "type": "Feature",
  "properties": {
    "iso:country":"US",
    "sg:address":"9100 Baldridge Rd",
    "sg:city":"Pensacola",
    "sg:classifiers":[
        {
            "category":"Real Estate",
            "subcategory":"Real Estate Operator",
            "type":"Services"
        }
    ],
    "sg:phone":"+1 850 475 2153",
    "sg:postcode":"32514",
    "sg:province":"FL",
    "sg:tags":[
        "apartment"
    ],
    "wof:name":"Homecorp",
    "wof:placetype":"venue"
},
  "geometry": {"coordinates":[-87.225533,30.527241],"type":"Point"}
}