{
  "type": "Feature",
  "properties": {
    "iso:country":"US",
    "sg:address":"1877 Edge St",
    "sg:city":"Niceville",
    "sg:classifiers":[
        {
            "category":"Utilities",
            "subcategory":"Refuse",
            "type":"Services"
        }
    ],
    "sg:phone":"+1 850 678 5800",
    "sg:postcode":"32578",
    "sg:province":"FL",
    "sg:tags":[
        "garbage",
        "collection"
    ],
    "wof:name":"Weekend Hauling",
    "wof:placetype":"venue"
},
  "geometry": {"coordinates":[-86.450458,30.511142],"type":"Point"}
}