{
  "type": "Feature",
  "properties": {
    "iso:country":"US",
    "sg:address":"7102 Causeway Blvd",
    "sg:city":"Tampa",
    "sg:classifiers":[
        {
            "category":"Transit Center",
            "subcategory":"Freight",
            "type":"Transportation"
        },
        {
            "category":"Freight",
            "type":"Transportation"
        }
    ],
    "sg:phone":"+1 813 620 1990",
    "sg:postcode":"33619",
    "sg:province":"FL",
    "sg:tags":[
        "local",
        "trucking-motor",
        "trucking"
    ],
    "wof:name":"Uti",
    "wof:placetype":"venue"
},
  "geometry": {"coordinates":[-82.375789,27.922791],"type":"Point"}
}