{
  "type": "Feature",
  "properties": {
    "addr:full":"211 Hancock Bridge Pkwy Cape Coral FL 33990",
    "addr:housenumber":"211",
    "addr:postcode":"33990",
    "addr:street":"Hancock Bridge Pkwy",
    "iso:country":"US",
    "sg:address":"211 Hancock Bridge Pkwy",
    "sg:city":"Cape Coral",
    "sg:classifiers":[
        {
            "category":"Arena",
            "subcategory":"Sports Club",
            "type":"Entertainment"
        }
    ],
    "sg:phone":"+1 239 574 5437",
    "sg:postcode":"33990",
    "sg:province":"FL",
    "sg:tags":[
        "martial art"
    ],
    "wof:name":"Ata Shuman's Black Belt Academy",
    "wof:placetype":"venue"
},
  "geometry": {"coordinates":[-81.969984,26.652027],"type":"Point"}
}