{
  "type": "Feature",
  "properties": {
    "addr:full":"161 N Cypress Way Casselberry FL 32707",
    "addr:housenumber":"161",
    "addr:postcode":"32707",
    "addr:street":"N Cypress Way",
    "iso:country":"US",
    "sg:address":"161 N Cypress Way",
    "sg:city":"Casselberry",
    "sg:classifiers":[
        {
            "category":"Building & Trades",
            "subcategory":"Construction",
            "type":"Services"
        }
    ],
    "sg:phone":"+1 407 830 7778",
    "sg:postcode":"32707",
    "sg:province":"FL",
    "sg:tags":[
        "siding",
        "contractor"
    ],
    "wof:name":"Sun State Siding Inc",
    "wof:placetype":"venue"
},
  "geometry": {"coordinates":[-81.34171000000001,28.674275],"type":"Point"}
}