{
  "type": "Feature",
  "properties": {
    "addr:full":"808 Ellicott Cir NW Port Charlotte FL 33952",
    "addr:housenumber":"808",
    "addr:postcode":"33952",
    "addr:street":"Ellicott Cir Nw",
    "iso:country":"US",
    "sg:address":"808 Ellicott Cir NW",
    "sg:city":"Port Charlotte",
    "sg:classifiers":[
        {
            "category":"Freight",
            "type":"Transportation"
        }
    ],
    "sg:phone":"+1 941 627 1985",
    "sg:postcode":"33952",
    "sg:province":"FL",
    "sg:tags":[
        "operator",
        "local",
        "trucking"
    ],
    "wof:name":"Steven Hesson Trucking Inc",
    "wof:placetype":"venue"
},
  "geometry": {"coordinates":[-82.122292,26.997815],"type":"Point"}
}