{
  "type": "Feature",
  "properties": {
    "iso:country":"US",
    "sg:address":"7660 SE 59th Ct Unit 104",
    "sg:city":"Ocala",
    "sg:classifiers":[
        {
            "category":"Professional",
            "subcategory":"Art Services",
            "type":"Services"
        }
    ],
    "sg:phone":"+1 352 427 0833",
    "sg:postcode":"34472",
    "sg:province":"FL",
    "sg:tags":[
        "designer",
        "display",
        "producer"
    ],
    "wof:name":"R A M Design",
    "wof:placetype":"venue"
},
  "geometry": {"coordinates":[-82.05122299999999,29.108963],"type":"Point"}
}