{
  "type": "Feature",
  "properties": {
    "addr:full":"891 Vanderbilt Beach Rd Naples FL 34108",
    "addr:housenumber":"891",
    "addr:postcode":"34108",
    "addr:street":"Vanderbilt Beach Rd",
    "iso:country":"US",
    "sg:address":"891 Vanderbilt Beach Rd",
    "sg:city":"Naples",
    "sg:classifiers":[
        {
            "category":"Wholesale",
            "subcategory":"Machinery & Supplies",
            "type":"Manufacturing & Wholesale Goods"
        }
    ],
    "sg:phone":"+1 239 254 8901",
    "sg:postcode":"34108",
    "sg:province":"FL",
    "wof:name":"Florida Distilled H2owater",
    "wof:placetype":"venue"
},
  "geometry": {"coordinates":[-81.816733,26.252892],"type":"Point"}
}