{
  "type": "Feature",
  "properties": {
    "iso:country":"US",
    "sg:address":"4050 Marlberry Ln",
    "sg:city":"Melbourne",
    "sg:classifiers":[
        {
            "category":"Arts & Performance",
            "subcategory":"Theater",
            "type":"Entertainment"
        }
    ],
    "sg:phone":"+1 321 733 0278",
    "sg:postcode":"32901",
    "sg:province":"FL",
    "sg:tags":[
        "musician"
    ],
    "wof:name":"Arts Of Praise Academy",
    "wof:placetype":"venue"
},
  "geometry": {"coordinates":[-80.631488,28.049229],"type":"Point"}
}