{
  "type": "Feature",
  "properties": {
    "addr:full":"7154 W Colonial Dr Orlando FL 32818",
    "addr:housenumber":"7154",
    "addr:postcode":"32818",
    "addr:street":"W Colonial Dr",
    "iso:country":"US",
    "sg:address":"7154 W Colonial Dr",
    "sg:city":"Orlando",
    "sg:classifiers":[
        {
            "category":"Home & Garden",
            "subcategory":"Garden Supply",
            "type":"Retail Goods"
        }
    ],
    "sg:phone":"+1 407 522 1234",
    "sg:postcode":"32818",
    "sg:province":"FL",
    "sg:tags":[
        "center"
    ],
    "wof:name":"Pots N Planters",
    "wof:placetype":"venue"
},
  "geometry": {"coordinates":[-81.478487,28.551996],"type":"Point"}
}