{
  "type": "Feature",
  "properties": {
    "iso:country":"US",
    "sg:address":"23 Cove Rd",
    "sg:city":"Lake Placid",
    "sg:classifiers":[
        {
            "category":"Wholesale",
            "subcategory":"Motor Vehicles",
            "type":"Manufacturing & Wholesale Goods"
        }
    ],
    "sg:phone":"+1 863 443 1960",
    "sg:postcode":"33852",
    "sg:province":"FL",
    "wof:name":"Euromax Inc",
    "wof:placetype":"venue"
},
  "geometry": {"coordinates":[-81.414294,27.321924],"type":"Point"}
}