{
  "type": "Feature",
  "properties": {
    "addr:full":"715 Apricot Ave Sarasota FL 34237",
    "addr:housenumber":"715",
    "addr:postcode":"34237",
    "addr:street":"Apricot Ave",
    "iso:country":"US",
    "sg:address":"715 Apricot Ave",
    "sg:city":"Sarasota",
    "sg:classifiers":[
        {
            "category":"Building & Trades",
            "subcategory":"Construction",
            "type":"Services"
        }
    ],
    "sg:phone":"+1 941 954 1555",
    "sg:postcode":"34237",
    "sg:province":"FL",
    "sg:tags":[
        "heavy",
        "manufacture",
        "metal",
        "dock",
        "prefabricated"
    ],
    "wof:name":"Duncan Seawall Dock & Boat Lft",
    "wof:placetype":"venue"
},
  "geometry": {"coordinates":[-82.52490400000001,27.341951],"type":"Point"}
}