{
  "type": "Feature",
  "properties": {
    "iso:country":"US",
    "sg:address":"275 NW 2nd St",
    "sg:city":"Miami",
    "sg:classifiers":[
        {
            "category":"Government",
            "subcategory":"Office",
            "type":"Public Place"
        }
    ],
    "sg:phone":"+1 305 755 6215",
    "sg:postcode":"33128",
    "sg:province":"FL",
    "sg:tags":[
        "government-state"
    ],
    "wof:name":"Florida State Of",
    "wof:placetype":"venue"
},
  "geometry": {"coordinates":[-80.19891,25.775905],"type":"Point"}
}