{
  "type": "Feature",
  "properties": {
    "iso:country":"US",
    "sg:address":"5406 Co Rd 218",
    "sg:city":"Middleburg",
    "sg:classifiers":[
        {
            "category":"Bars & Pubs",
            "type":"Food & Drink"
        }
    ],
    "sg:phone":"+1 904 282 7085",
    "sg:postcode":"32068",
    "sg:province":"FL",
    "wof:name":"Old Rooster Rest & Bar Inc",
    "wof:placetype":"venue"
},
  "geometry": {"coordinates":[-81.95161899999999,30.096655],"type":"Point"}
}