{
  "type": "Feature",
  "properties": {
    "iso:country":"US",
    "sg:address":"341 Forest Park Cir",
    "sg:city":"Longwood",
    "sg:classifiers":[
        {
            "category":"Professional",
            "subcategory":"Management & Consulting",
            "type":"Services"
        }
    ],
    "sg:phone":"+1 407 862 7124",
    "sg:postcode":"32779",
    "sg:province":"FL",
    "wof:name":"Certaint Management",
    "wof:placetype":"venue"
},
  "geometry": {"coordinates":[-81.443926,28.682211],"type":"Point"}
}