{
  "type": "Feature",
  "properties": {
    "iso:country":"US",
    "sg:address":"1200 Garvey Rd SW",
    "sg:city":"Palm Bay",
    "sg:phone":"+1 321 727 1075",
    "sg:postcode":"32908",
    "sg:province":"FL",
    "sg:tags":[
        "heavy",
        "fee",
        "beef",
        "farm",
        "construction",
        "cattle"
    ],
    "wof:name":"Wilbro Land Clearing",
    "wof:placetype":"venue"
},
  "geometry": {"coordinates":[-80.68858299999999,27.957866],"type":"Point"}
}