{
  "type": "Feature",
  "properties": {
    "addr:full":"2750 Michigan Ave Kissimmee FL 34744",
    "addr:housenumber":"2750",
    "addr:postcode":"34744",
    "addr:street":"Michigan Ave",
    "iso:country":"US",
    "sg:address":"2750 Michigan Ave",
    "sg:city":"Kissimmee",
    "sg:classifiers":[
        {
            "category":"Professional",
            "subcategory":"Business Services",
            "type":"Services"
        }
    ],
    "sg:phone":"+1 407 908 6665",
    "sg:postcode":"34744",
    "sg:province":"FL",
    "wof:name":"JM Maquinaria USA LLC",
    "wof:placetype":"venue"
},
  "geometry": {"coordinates":[-81.39133200000001,28.328134],"type":"Point"}
}