{
  "type": "Feature",
  "properties": {
    "iso:country":"US",
    "sg:address":"7509 Grant St",
    "sg:city":"Hollywood",
    "sg:classifiers":[
        {
            "category":"Professional",
            "subcategory":"Management & Consulting",
            "type":"Services"
        }
    ],
    "sg:phone":"+1 954 966 1231",
    "sg:postcode":"33024",
    "sg:province":"FL",
    "wof:name":"Jaj Energy Management Systems",
    "wof:placetype":"venue"
},
  "geometry": {"coordinates":[-80.24003999999999,26.017463],"type":"Point"}
}