{
  "type": "Feature",
  "properties": {
    "iso:country":"US",
    "sg:address":"21097 NE 27th Ct",
    "sg:city":"Miami",
    "sg:classifiers":[
        {
            "category":"Personal",
            "subcategory":"Hair Removal",
            "type":"Services"
        }
    ],
    "sg:phone":"+1 866 494 4348",
    "sg:postcode":"33180",
    "sg:province":"FL",
    "sg:website":"http://www.filitrac.com/Click.aspx?tid=B812D3B64AE5D4A16F1E6E18E307A35AC9798167DE606D32&FiliAff=15016&sid=Local%20Store&mwpid=YellowPages&cpag=YellowPages&cpca=YellowPages&cpao=123&bannerid=2678",
    "wof:name":"American Laser Center",
    "wof:placetype":"venue"
},
  "geometry": {"coordinates":[-80.146659,25.970761],"type":"Point"}
}