{
  "type": "Feature",
  "properties": {
    "iso:country":"US",
    "sg:address":"5917 Clydesdale Pl",
    "sg:city":"Orlando",
    "sg:classifiers":[
        {
            "category":"Professional",
            "subcategory":"Computer Services",
            "type":"Services"
        }
    ],
    "sg:phone":"+1 877 514 9484",
    "sg:postcode":"32822",
    "sg:province":"FL",
    "sg:tags":[
        "repair",
        "parts",
        "networking",
        "retail"
    ],
    "wof:name":"TDS Technology Partners",
    "wof:placetype":"venue"
},
  "geometry": {"coordinates":[-81.304633,28.522331],"type":"Point"}
}