{
  "type": "Feature",
  "properties": {
    "addr:full":"1410 NW 13th St Gainesville FL 32601",
    "addr:housenumber":"1410",
    "addr:postcode":"32601",
    "addr:street":"Nw 13Th St",
    "iso:country":"US",
    "sg:address":"1410 NW 13th St",
    "sg:city":"Gainesville",
    "sg:classifiers":[
        {
            "category":"Personal",
            "subcategory":"Beauty Salon",
            "type":"Services"
        }
    ],
    "sg:phone":"+1 352 384 1215",
    "sg:postcode":"32601",
    "sg:province":"FL",
    "sg:tags":[
        "shop"
    ],
    "wof:name":"Accent Styling Salon",
    "wof:placetype":"venue"
},
  "geometry": {"coordinates":[-82.339232,29.666598],"type":"Point"}
}