{
  "type": "Feature",
  "properties": {
    "iso:country":"US",
    "sg:address":"5895 NW 167th St",
    "sg:city":"Hialeah",
    "sg:classifiers":[
        {
            "category":"Restaurant",
            "type":"Food & Drink"
        }
    ],
    "sg:phone":"+1 305 823 2330",
    "sg:postcode":"33015",
    "sg:province":"FL",
    "sg:tags":[
        "eating"
    ],
    "wof:name":"Express Cafe",
    "wof:placetype":"venue"
},
  "geometry": {"coordinates":[-80.295655,25.925255],"type":"Point"}
}