{
  "type": "Feature",
  "properties": {
    "iso:country":"US",
    "sg:address":"664 Azalea Ln",
    "sg:city":"Vero Beach",
    "sg:classifiers":[
        {
            "category":"Travel",
            "subcategory":"Travel Agent",
            "type":"Entertainment"
        }
    ],
    "sg:phone":"+1 772 231 3408",
    "sg:postcode":"32963",
    "sg:province":"FL",
    "sg:tags":[
        "bureau",
        "passenger",
        "agency",
        "transportation",
        "arrangement"
    ],
    "wof:name":"Jean Wainwright Travel Inc",
    "wof:placetype":"venue"
},
  "geometry": {"coordinates":[-80.361688,27.652302],"type":"Point"}
}