{
  "type": "Feature",
  "properties": {
    "addr:full":"604 Lithia Pinecrest Rd Brandon FL 33511",
    "addr:housenumber":"604",
    "addr:postcode":"33511",
    "addr:street":"Lithia Pinecrest Rd",
    "iso:country":"US",
    "sg:address":"604 Lithia Pinecrest Rd",
    "sg:city":"Brandon",
    "sg:classifiers":[
        {
            "category":"Personal",
            "subcategory":"Beauty Salon",
            "type":"Services"
        }
    ],
    "sg:phone":"+1 813 657 9590",
    "sg:postcode":"33511",
    "sg:province":"FL",
    "sg:tags":[
        "spa",
        "day"
    ],
    "wof:name":"Imperial Massage",
    "wof:placetype":"venue"
},
  "geometry": {"coordinates":[-82.273957,27.927402],"type":"Point"}
}