{
  "type": "Feature",
  "properties": {
    "iso:country":"US",
    "sg:address":"4222 W 16th Ave",
    "sg:city":"Hialeah",
    "sg:classifiers":[
        {
            "category":"Retail",
            "subcategory":"Laundry & Dry Cleaning",
            "type":"Services"
        }
    ],
    "sg:phone":"+1 305 557 5565",
    "sg:postcode":"33012",
    "sg:province":"FL",
    "sg:tags":[
        "cleaner"
    ],
    "wof:name":"Los Pinos Dry Cleaners",
    "wof:placetype":"venue"
},
  "geometry": {"coordinates":[-80.314598,25.860001],"type":"Point"}
}