{
  "type": "Feature",
  "properties": {
    "addr:full":"5849 NE 4th Ln Okeechobee FL 34974",
    "addr:housenumber":"5849",
    "addr:postcode":"34974",
    "addr:street":"Ne 4Th Ln",
    "iso:country":"US",
    "sg:address":"5849 NE 4th Ln",
    "sg:city":"Okeechobee",
    "sg:classifiers":[
        {
            "category":"Wholesale",
            "subcategory":"Vending Machines",
            "type":"Manufacturing & Wholesale Goods"
        }
    ],
    "sg:phone":"+1 863 763 1519",
    "sg:postcode":"34974",
    "sg:province":"FL",
    "sg:tags":[
        "operator"
    ],
    "wof:name":"Mobile Munchies",
    "wof:placetype":"venue"
},
  "geometry": {"coordinates":[-80.765503,27.248777],"type":"Point"}
}