{
  "type": "Feature",
  "properties": {
    "iso:country":"US",
    "sg:address":"14623 Perdido Key Dr",
    "sg:city":"Pensacola",
    "sg:classifiers":[
        {
            "category":"Building & Trades",
            "subcategory":"Construction",
            "type":"Services"
        }
    ],
    "sg:phone":"+1 850 497 8300",
    "sg:postcode":"32507",
    "sg:province":"FL",
    "sg:tags":[
        "general",
        "contractor"
    ],
    "wof:name":"White Construction Co",
    "wof:placetype":"venue"
},
  "geometry": {"coordinates":[-87.45056099999999,30.29414],"type":"Point"}
}