{
  "type": "Feature",
  "properties": {
    "addr:full":"6826 Liberty St Gulf Breeze FL 32566",
    "addr:housenumber":"6826",
    "addr:postcode":"32566",
    "addr:street":"Liberty St",
    "iso:country":"US",
    "sg:address":"6826 Liberty St",
    "sg:city":"Gulf Breeze",
    "sg:classifiers":[
        {
            "category":"Shopping",
            "subcategory":"Used Merchandise",
            "type":"Retail Goods"
        }
    ],
    "sg:phone":"+1 850 936 9544",
    "sg:postcode":"32566",
    "sg:province":"FL",
    "wof:name":"Mary Hope Service Antique",
    "wof:placetype":"venue"
},
  "geometry": {"coordinates":[-86.93925900000001,30.418544],"type":"Point"}
}