{
  "type": "Feature",
  "properties": {
    "iso:country":"US",
    "sg:address":"324 Seaboard Ave",
    "sg:city":"Venice",
    "sg:classifiers":[
        {
            "category":"Building & Trades",
            "subcategory":"Plumbing",
            "type":"Services"
        }
    ],
    "sg:phone":"+1 941 764 7102",
    "sg:postcode":"34285",
    "sg:province":"FL",
    "sg:tags":[
        "conditioning",
        "air",
        "system",
        "contractor"
    ],
    "wof:name":"Acme/Charlotte Air & Refrig",
    "wof:placetype":"venue"
},
  "geometry": {"coordinates":[-82.435074,27.093493],"type":"Point"}
}