{
  "type": "Feature",
  "properties": {
    "iso:country":"US",
    "sg:address":"3525 Manassas Ave",
    "sg:city":"Melbourne",
    "sg:classifiers":[
        {
            "category":"Retail",
            "subcategory":"Animal Services",
            "type":"Services"
        }
    ],
    "sg:phone":"+1 321 242 9010",
    "sg:postcode":"32934",
    "sg:province":"FL",
    "wof:name":"Greyhound Pets of America",
    "wof:placetype":"venue"
},
  "geometry": {"coordinates":[-80.68380500000001,28.170567],"type":"Point"}
}