{
  "type": "Feature",
  "properties": {
    "addr:full":"5190 NW 167th St Hialeah FL 33014",
    "addr:housenumber":"5190",
    "addr:postcode":"33014",
    "addr:street":"Nw 167Th St",
    "iso:country":"US",
    "sg:address":"5190 NW 167th St",
    "sg:city":"Hialeah",
    "sg:classifiers":[
        {
            "category":"Arts & Performance",
            "subcategory":"Theater",
            "type":"Entertainment"
        }
    ],
    "sg:phone":"+1 305 474 0076",
    "sg:postcode":"33014",
    "sg:province":"FL",
    "sg:tags":[
        "bureau"
    ],
    "wof:name":"Golden Touch",
    "wof:placetype":"venue"
},
  "geometry": {"coordinates":[-80.281302,25.924927],"type":"Point"}
}