{
  "type": "Feature",
  "properties": {
    "iso:country":"US",
    "sg:address":"125 Baywood Ave",
    "sg:city":"Longwood",
    "sg:classifiers":[
        {
            "category":"Wholesale",
            "subcategory":"Motor Vehicles",
            "type":"Manufacturing & Wholesale Goods"
        }
    ],
    "sg:phone":"+1 407 699 1399",
    "sg:postcode":"32750",
    "sg:province":"FL",
    "wof:name":"Wing Plus",
    "wof:placetype":"venue"
},
  "geometry": {"coordinates":[-81.341752,28.718404],"type":"Point"}
}