{
  "type": "Feature",
  "properties": {
    "addr:full":"1600 NW 59th St Miami FL 33142",
    "addr:housenumber":"1600",
    "addr:postcode":"33142",
    "addr:street":"Nw 59Th St",
    "iso:country":"US",
    "sg:address":"1600 NW 59th St",
    "sg:city":"Miami",
    "sg:classifiers":[
        {
            "category":"Building & Trades",
            "subcategory":"Locksmith",
            "type":"Services"
        }
    ],
    "sg:phone":"+1 786 718 1392",
    "sg:postcode":"33142",
    "sg:province":"FL",
    "sg:tags":[
        "key"
    ],
    "wof:name":"A Plus Locksmith",
    "wof:placetype":"venue"
},
  "geometry": {"coordinates":[-80.22378500000001,25.829429],"type":"Point"}
}