{
  "type": "Feature",
  "properties": {
    "addr:full":"580 Reed Canal Rd Daytona Beach FL 32119",
    "addr:housenumber":"580",
    "addr:postcode":"32119",
    "addr:street":"Reed Canal Rd",
    "iso:country":"US",
    "sg:address":"580 Reed Canal Rd",
    "sg:city":"Daytona Beach",
    "sg:classifiers":[
        {
            "category":"Real Estate",
            "subcategory":"Real Estate Operator",
            "type":"Services"
        }
    ],
    "sg:phone":"+1 386 788 2381",
    "sg:postcode":"32119",
    "sg:province":"FL",
    "sg:tags":[
        "mini",
        "apartment",
        "storage",
        "unit"
    ],
    "wof:name":"Marcell Garden Apartments",
    "wof:placetype":"venue"
},
  "geometry": {"coordinates":[-81.00111,29.158672],"type":"Point"}
}