{
  "type": "Feature",
  "properties": {
    "iso:country":"US",
    "sg:address":"822 Sterling Oaks Blvd",
    "sg:city":"Naples",
    "sg:classifiers":[
        {
            "category":"Restaurant",
            "type":"Food & Drink"
        }
    ],
    "sg:phone":"+1 239 598 1084",
    "sg:postcode":"34110",
    "sg:province":"FL",
    "wof:name":"Club House & Restaurant",
    "wof:placetype":"venue"
},
  "geometry": {"coordinates":[-81.802682,26.313864],"type":"Point"}
}