{
  "type": "Feature",
  "properties": {
    "addr:full":"13494 W Colonial Dr Winter Garden FL 34787",
    "addr:housenumber":"13494",
    "addr:postcode":"34787",
    "addr:street":"W Colonial Dr",
    "iso:country":"US",
    "sg:address":"13494 W Colonial Dr",
    "sg:city":"Winter Garden",
    "sg:classifiers":[
        {
            "category":"Restaurant",
            "type":"Food & Drink"
        }
    ],
    "sg:menulink":"http://www.allmenus.com/fl/winter-garden-ocoee/187806-mcdonalds/menu/",
    "sg:phone":"+1 407 656 5550",
    "sg:postcode":"34787",
    "sg:province":"FL",
    "sg:tags":[
        "burger",
        "american"
    ],
    "wof:name":"McDonald's",
    "wof:placetype":"venue"
},
  "geometry": {"coordinates":[-81.583105,28.550577],"type":"Point"}
}