{
  "type": "Feature",
  "properties": {
    "iso:country":"US",
    "sg:address":"1678 Sarno Rd",
    "sg:city":"Melbourne",
    "sg:classifiers":[
        {
            "category":"Building & Trades",
            "subcategory":"Cleaning & Sanitation",
            "type":"Services"
        }
    ],
    "sg:phone":"+1 321 409 9322",
    "sg:postcode":"32935",
    "sg:province":"FL",
    "sg:tags":[
        "janitor"
    ],
    "wof:name":"Beverly Macky Cleaning Svc",
    "wof:placetype":"venue"
},
  "geometry": {"coordinates":[-80.64787800000001,28.121711],"type":"Point"}
}