{
  "type": "Feature",
  "properties": {
    "addr:full":"2187 Egret Dr Clearwater FL 33764",
    "addr:housenumber":"2187",
    "addr:postcode":"33764",
    "addr:street":"Egret Dr",
    "iso:country":"US",
    "sg:address":"2187 Egret Dr",
    "sg:city":"Clearwater",
    "sg:classifiers":[
        {
            "category":"Shopping",
            "subcategory":"Clothing, Apparel, & Fashions",
            "type":"Retail Goods"
        }
    ],
    "sg:phone":"+1 727 599 2341",
    "sg:postcode":"33764",
    "sg:province":"FL",
    "wof:name":"Gem of A Kind LLC",
    "wof:placetype":"venue"
},
  "geometry": {"coordinates":[-82.746876,27.927729],"type":"Point"}
}