{
  "type": "Feature",
  "properties": {
    "addr:full":"10078 NW 1st Ct Fort Lauderdale FL 33324",
    "addr:housenumber":"10078",
    "addr:postcode":"33324",
    "addr:street":"Nw 1St Ct",
    "iso:country":"US",
    "sg:address":"10078 NW 1st Ct",
    "sg:city":"Fort Lauderdale",
    "sg:classifiers":[
        {
            "category":"Health Services",
            "subcategory":"Chiropractor",
            "type":"Services"
        }
    ],
    "sg:phone":"+1 954 472 7975",
    "sg:postcode":"33324",
    "sg:province":"FL",
    "wof:name":"Markson Chriropractic Inc",
    "wof:placetype":"venue"
},
  "geometry": {"coordinates":[-80.283584,26.122541],"type":"Point"}
}