{
  "type": "Feature",
  "properties": {
    "iso:country":"US",
    "sg:address":"10381 Cypress Lakes Dr",
    "sg:city":"Jacksonville",
    "sg:classifiers":[
        {
            "category":"Museum",
            "type":"Entertainment"
        }
    ],
    "sg:phone":"+1 904 519 1004",
    "sg:postcode":"32256",
    "sg:province":"FL",
    "wof:name":"Korean American Cultural Cente",
    "wof:placetype":"venue"
},
  "geometry": {"coordinates":[-81.529698,30.174426],"type":"Point"}
}