{
  "type": "Feature",
  "properties": {
    "iso:country":"US",
    "sg:address":"4810 Mc Elroy Ave",
    "sg:city":"Tampa",
    "sg:classifiers":[
        {
            "category":"Autos & Motor Vehicles",
            "subcategory":"Boat Sales",
            "type":"Retail Goods"
        }
    ],
    "sg:phone":"+1 813 831 3000",
    "sg:postcode":"33611",
    "sg:province":"FL",
    "sg:tags":[
        "dealer",
        "sales"
    ],
    "wof:name":"Jack's Interbay Marine",
    "wof:placetype":"venue"
},
  "geometry": {"coordinates":[-82.529708,27.892331],"type":"Point"}
}