{
  "type": "Feature",
  "properties": {
    "iso:country":"US",
    "sg:address":"1500 Monza Ave Ste 350",
    "sg:city":"Coral Gables",
    "sg:classifiers":[
        {
            "category":"Sports & Exercise",
            "subcategory":"Gym",
            "type":"Entertainment"
        },
        {
            "category":"Health Services",
            "subcategory":"Health Practitioner",
            "type":"Services"
        }
    ],
    "sg:phone":"+1 305 740 6001",
    "sg:postcode":"33146",
    "sg:province":"FL",
    "sg:tags":[
        "pilate",
        "therapy",
        "physical"
    ],
    "sg:website":"www.polestarmiami.com",
    "wof:name":"Polestar Physical Therapy and Pilates Center",
    "wof:placetype":"venue"
},
  "geometry": {"coordinates":[-80.283528,25.707218],"type":"Point"}
}