{
  "type": "Feature",
  "properties": {
    "addr:full":"4022 SW Sand Trl Palm City FL 34990",
    "addr:housenumber":"4022",
    "addr:postcode":"34990",
    "addr:street":"Sw Sand Trl",
    "iso:country":"US",
    "sg:address":"4022 SW Sand Trl",
    "sg:city":"Palm City",
    "sg:classifiers":[
        {
            "category":"Retail",
            "subcategory":"Repair Shop",
            "type":"Services"
        }
    ],
    "sg:phone":"+1 772 220 7707",
    "sg:postcode":"34990",
    "sg:province":"FL",
    "wof:name":"Domestic Boutique",
    "wof:placetype":"venue"
},
  "geometry": {"coordinates":[-80.31086000000001,27.171295],"type":"Point"}
}