{
  "type": "Feature",
  "properties": {
    "addr:full":"8392 Pinto Dr Lake Worth FL 33467",
    "addr:housenumber":"8392",
    "addr:postcode":"33467",
    "addr:street":"Pinto Dr",
    "iso:country":"US",
    "sg:address":"8392 Pinto Dr",
    "sg:city":"Lake Worth",
    "sg:classifiers":[
        {
            "category":"Retail",
            "subcategory":"Animal Services",
            "type":"Services"
        }
    ],
    "sg:phone":"+1 561 674 1617",
    "sg:postcode":"33467",
    "sg:province":"FL",
    "sg:tags":[
        "pet",
        "grooming",
        "washing"
    ],
    "wof:name":"Paradise Palms Pet Resort",
    "wof:placetype":"venue"
},
  "geometry": {"coordinates":[-80.17922799999999,26.625993],"type":"Point"}
}