{
  "type": "Feature",
  "properties": {
    "iso:country":"US",
    "sg:address":"334 Center Crest Blvd",
    "sg:city":"Davenport",
    "sg:classifiers":[
        {
            "category":"Organizations",
            "subcategory":"Professional Association",
            "type":"Services"
        }
    ],
    "sg:phone":"+1 863 421 6320",
    "sg:postcode":"33837",
    "sg:province":"FL",
    "wof:name":"Center Crest Lot Owners Assn",
    "wof:placetype":"venue"
},
  "geometry": {"coordinates":[-81.616229,28.160202],"type":"Point"}
}