{
  "type": "Feature",
  "properties": {
    "iso:country":"US",
    "sg:address":"9831 NW 58th St 144",
    "sg:city":"Doral",
    "sg:classifiers":[
        {
            "category":"Insurance",
            "subcategory":"Hazard Insurance",
            "type":"Services"
        }
    ],
    "sg:phone":"+1 786 464 1651",
    "sg:postcode":"33178",
    "sg:province":"FL",
    "sg:website":"www.michaelrodriguezallstate.com/",
    "wof:name":"Michael Rodriguez - Allstate Insurance",
    "wof:placetype":"venue"
},
  "geometry": {"coordinates":[-80.355463,25.826192],"type":"Point"}
}