{
  "type": "Feature",
  "properties": {
    "iso:country":"US",
    "sg:address":"11 Westwood Ave",
    "sg:city":"Jupiter",
    "sg:classifiers":[
        {
            "category":"Manufacturing",
            "subcategory":"Chemicals & Compounds",
            "type":"Manufacturing & Wholesale Goods"
        }
    ],
    "sg:phone":"+1 561 575 1193",
    "sg:postcode":"33469",
    "sg:province":"FL",
    "sg:tags":[
        "preparation",
        "mfg"
    ],
    "wof:name":"Kasko Industries Inc",
    "wof:placetype":"venue"
},
  "geometry": {"coordinates":[-80.09548599999999,26.96133],"type":"Point"}
}