{
  "type": "Feature",
  "properties": {
    "iso:country":"US",
    "sg:address":"2701 W 27th St",
    "sg:city":"Panama City",
    "sg:classifiers":[
        {
            "category":"Professional",
            "subcategory":"Computer Services",
            "type":"Services"
        }
    ],
    "sg:phone":"+1 850 763 2439",
    "sg:postcode":"32405",
    "sg:province":"FL",
    "sg:tags":[
        "consulting",
        "datum",
        "dev",
        "internet",
        "home",
        "page"
    ],
    "wof:name":"T 3 Web Design Inc",
    "wof:placetype":"venue"
},
  "geometry": {"coordinates":[-85.697577,30.196927],"type":"Point"}
}