{
  "type": "Feature",
  "properties": {
    "addr:full":"1218 E Robinson St Orlando FL 32801",
    "addr:housenumber":"1218",
    "addr:postcode":"32801",
    "addr:street":"E Robinson St",
    "iso:country":"US",
    "sg:address":"1218 E Robinson St",
    "sg:city":"Orlando",
    "sg:classifiers":[
        {
            "category":"Professional",
            "subcategory":"Lawyer & Legal Services",
            "type":"Services"
        }
    ],
    "sg:phone":"+1 407 246 7040",
    "sg:postcode":"32801",
    "sg:province":"FL",
    "sg:tags":[
        "attorney",
        "employment",
        "litigation",
        "death",
        "personal",
        "automobile",
        "damage",
        "labor",
        "tort",
        "employee",
        "injury",
        "compensation",
        "product",
        "practice",
        "worker",
        "liability",
        "plan",
        "law",
        "accident",
        "medical",
        "wrongful",
        "benefit",
        "malpractice",
        "property"
    ],
    "sg:website":"http://www.oneofficeonepurpose.com",
    "wof:name":"Law Office Of Piercy J Stakelum Esq",
    "wof:placetype":"venue"
},
  "geometry": {"coordinates":[-81.36344099999999,28.545799],"type":"Point"}
}