{
  "type": "Feature",
  "properties": {
    "addr:full":"8635 Blanding Blvd Jacksonville FL 32244",
    "addr:housenumber":"8635",
    "addr:postcode":"32244",
    "addr:street":"Blanding Blvd",
    "iso:country":"US",
    "sg:address":"8635 Blanding Blvd",
    "sg:city":"Jacksonville",
    "sg:classifiers":[
        {
            "category":"Coffee & Tea",
            "type":"Food & Drink"
        }
    ],
    "sg:menulink":"http://www.allmenus.com/fl/jacksonville/117087-starbucks-coffee/menu/",
    "sg:phone":"+1 904 771 0655",
    "sg:postcode":"32244",
    "sg:province":"FL",
    "sg:tags":[
        "american"
    ],
    "wof:name":"Starbucks Coffee",
    "wof:placetype":"venue"
},
  "geometry": {"coordinates":[-81.737577,30.193712],"type":"Point"}
}