{
  "type": "Feature",
  "properties": {
    "addr:full":"1200 NW 76 Blvd Gainesville FL 32606",
    "addr:housenumber":"1200",
    "addr:postcode":"32606",
    "addr:street":"Nw 76 Blvd",
    "iso:country":"US",
    "sg:address":"1200 NW 76 Blvd",
    "sg:city":"Gainesville",
    "sg:classifiers":[
        {
            "category":"Food & Beverages",
            "subcategory":"Groceries & Convenience Stores",
            "type":"Retail Goods"
        }
    ],
    "sg:phone":"+1 352 332 0661",
    "sg:postcode":"32606",
    "sg:province":"FL",
    "sg:tags":[
        "grocer"
    ],
    "wof:name":"Publix Super Market",
    "wof:placetype":"venue"
},
  "geometry": {"coordinates":[-82.42413999999999,29.661154],"type":"Point"}
}