{
  "type": "Feature",
  "properties": {
    "addr:full":"11989 Co Rd 223 Oxford FL 34484",
    "addr:housenumber":"11989;223",
    "addr:postcode":"34484",
    "addr:street":"Co Rd",
    "iso:country":"US",
    "sg:address":"11989 Co Rd 223",
    "sg:city":"Oxford",
    "sg:classifiers":[
        {
            "category":"Building & Trades",
            "subcategory":"Construction",
            "type":"Services"
        }
    ],
    "sg:phone":"+1 352 750 5700",
    "sg:postcode":"34484",
    "sg:province":"FL",
    "sg:tags":[
        "dock"
    ],
    "wof:name":"Sands Construction",
    "wof:placetype":"venue"
},
  "geometry": {"coordinates":[-82.07024699999999,28.929353],"type":"Point"}
}