{
  "type": "Feature",
  "properties": {
    "iso:country":"US",
    "sg:address":"1550 S Highland Ave",
    "sg:city":"Clearwater",
    "sg:classifiers":[
        {
            "category":"Restaurant",
            "type":"Food & Drink"
        }
    ],
    "sg:phone":"+1 727 320 8838",
    "sg:postcode":"33756",
    "sg:province":"FL",
    "wof:name":"Sportsmen Bar & Grill",
    "wof:placetype":"venue"
},
  "geometry": {"coordinates":[-82.77510599999999,27.940656],"type":"Point"}
}