{
  "type": "Feature",
  "properties": {
    "iso:country":"US",
    "sg:address":"10202 Chiltern Garden Dr",
    "sg:city":"Orlando",
    "sg:classifiers":[
        {
            "category":"Professional",
            "type":"Services"
        }
    ],
    "sg:phone":"+1 407 856 3705",
    "sg:postcode":"32827",
    "sg:province":"FL",
    "sg:tags":[
        "establishment"
    ],
    "wof:name":"CYLI",
    "wof:placetype":"venue"
},
  "geometry": {"coordinates":[-81.260818,28.418853],"type":"Point"}
}