{
  "type": "Feature",
  "properties": {
    "addr:full":"27008 W Dixie Hwy Homestead FL 33032",
    "addr:housenumber":"27008",
    "addr:postcode":"33032",
    "addr:street":"W Dixie Hwy",
    "iso:country":"US",
    "sg:address":"27008 W Dixie Hwy",
    "sg:city":"Homestead",
    "sg:classifiers":[
        {
            "category":"Retail",
            "subcategory":"Veterinary Services",
            "type":"Services"
        }
    ],
    "sg:phone":"+1 305 247 1777",
    "sg:postcode":"33032",
    "sg:province":"FL",
    "sg:tags":[
        "animal"
    ],
    "wof:name":"Gilley Animal Clinic Inc",
    "wof:placetype":"venue"
},
  "geometry": {"coordinates":[-80.433528,25.514289],"type":"Point"}
}