{
  "type": "Feature",
  "properties": {
    "addr:full":"5474 SE 52nd Ave Stuart FL 34997",
    "addr:housenumber":"5474",
    "addr:postcode":"34997",
    "addr:street":"Se 52Nd Ave",
    "iso:country":"US",
    "sg:address":"5474 SE 52nd Ave",
    "sg:city":"Stuart",
    "sg:classifiers":[
        {
            "category":"Professional",
            "type":"Services"
        }
    ],
    "sg:phone":"+1 772 283 1953",
    "sg:postcode":"34997",
    "sg:province":"FL",
    "wof:name":"Aquatics Plus By",
    "wof:placetype":"venue"
},
  "geometry": {"coordinates":[-80.184094,27.138014],"type":"Point"}
}