{
  "type": "Feature",
  "properties": {
    "iso:country":"US",
    "sg:address":"5712 Drummand Way",
    "sg:city":"Naples",
    "sg:classifiers":[
        {
            "category":"Wholesale",
            "subcategory":"Home Furnishings",
            "type":"Manufacturing & Wholesale Goods"
        }
    ],
    "sg:phone":"+1 239 593 0061",
    "sg:postcode":"34119",
    "sg:province":"FL",
    "wof:name":"Aardvark Inc",
    "wof:placetype":"venue"
},
  "geometry": {"coordinates":[-81.716112,26.246219],"type":"Point"}
}