{
  "type": "Feature",
  "properties": {
    "addr:full":"2305 Minton Rd Melbourne FL 32904",
    "addr:housenumber":"2305",
    "addr:postcode":"32904",
    "addr:street":"Minton Rd",
    "iso:country":"US",
    "sg:address":"2305 Minton Rd",
    "sg:city":"Melbourne",
    "sg:classifiers":[
        {
            "category":"Banks & Credit Unions",
            "subcategory":"Bank",
            "type":"Services"
        }
    ],
    "sg:phone":"+1 321 726 1983",
    "sg:postcode":"32904",
    "sg:province":"FL",
    "sg:tags":[
        "state",
        "chartered"
    ],
    "wof:name":"Central Florida Postal Cr Un",
    "wof:placetype":"venue"
},
  "geometry": {"coordinates":[-80.670806,28.070346],"type":"Point"}
}