{
  "type": "Feature",
  "properties": {
    "iso:country":"US",
    "sg:address":"465 21st St",
    "sg:city":"Vero Beach",
    "sg:classifiers":[
        {
            "category":"Restaurant",
            "type":"Food & Drink"
        }
    ],
    "sg:phone":"+1 772 778 8489",
    "sg:postcode":"32960",
    "sg:province":"FL",
    "sg:tags":[
        "eating"
    ],
    "wof:name":"Los Amigos Mexican Cafe",
    "wof:placetype":"venue"
},
  "geometry": {"coordinates":[-80.382903,27.63965],"type":"Point"}
}