{
  "type": "Feature",
  "properties": {
    "iso:country":"US",
    "sg:address":"5515 5th Ave",
    "sg:city":"Key West",
    "sg:classifiers":[
        {
            "category":"Food & Beverages",
            "subcategory":"Groceries & Convenience Stores",
            "type":"Retail Goods"
        }
    ],
    "sg:phone":"+1 305 295 0305",
    "sg:postcode":"33040",
    "sg:province":"FL",
    "sg:tags":[
        "grocer"
    ],
    "wof:name":"LA Curva Luis Cafe",
    "wof:placetype":"venue"
},
  "geometry": {"coordinates":[-81.73782799999999,24.568569],"type":"Point"}
}