{
  "type": "Feature",
  "properties": {
    "iso:country":"US",
    "sg:address":"9411 SW 4th St",
    "sg:city":"Miami",
    "sg:classifiers":[
        {
            "category":"Retail",
            "subcategory":"Laundry & Dry Cleaning",
            "type":"Services"
        }
    ],
    "sg:phone":"+1 954 322 2477",
    "sg:postcode":"33174",
    "sg:province":"FL",
    "sg:tags":[
        "cleaners",
        "rug",
        "carpet"
    ],
    "wof:name":"A-1 Chemical Dry System",
    "wof:placetype":"venue"
},
  "geometry": {"coordinates":[-80.34855,25.7656],"type":"Point"}
}