{
  "type": "Feature",
  "properties": {
    "addr:full":"5524 W Flagler St Miami FL 33134",
    "addr:housenumber":"5524",
    "addr:postcode":"33134",
    "addr:street":"W Flagler St",
    "iso:country":"US",
    "sg:address":"5524 W Flagler St",
    "sg:city":"Miami",
    "sg:classifiers":[
        {
            "category":"Wholesale",
            "subcategory":"Medical Equipment & Supplies",
            "type":"Manufacturing & Wholesale Goods"
        }
    ],
    "sg:phone":"+1 305 265 8838",
    "sg:postcode":"33134",
    "sg:province":"FL",
    "wof:name":"B N S Equipment",
    "wof:placetype":"venue"
},
  "geometry": {"coordinates":[-80.28516500000001,25.770835],"type":"Point"}
}