{
  "type": "Feature",
  "properties": {
    "iso:country":"US",
    "sg:address":"11401 NW 12th St",
    "sg:city":"Miami",
    "sg:classifiers":[
        {
            "category":"Shopping",
            "subcategory":"Jewelry",
            "type":"Retail Goods"
        }
    ],
    "sg:phone":"+1 305 468 1975",
    "sg:postcode":"33172",
    "sg:province":"FL",
    "wof:name":"Silver & Gold Connection",
    "wof:placetype":"venue"
},
  "geometry": {"coordinates":[-80.376503,25.782801],"type":"Point"}
}