{
  "type": "Feature",
  "properties": {
    "iso:country":"US",
    "sg:address":"10439 Utopia Cir E",
    "sg:city":"Boynton Beach",
    "sg:classifiers":[
        {
            "category":"Health Services",
            "subcategory":"Doctor",
            "type":"Services"
        }
    ],
    "sg:phone":"+1 561 736 2753",
    "sg:postcode":"33437",
    "sg:province":"FL",
    "wof:name":"Ivan E Roseff DDS & Assoc",
    "wof:placetype":"venue"
},
  "geometry": {"coordinates":[-80.144549,26.523516],"type":"Point"}
}