{
  "type": "Feature",
  "properties": {
    "iso:country":"US",
    "sg:address":"13200 Crowell Rd",
    "sg:city":"Brooksville",
    "sg:classifiers":[
        {
            "category":"Building & Trades",
            "subcategory":"Plumbing",
            "type":"Services"
        }
    ],
    "sg:phone":"+1 352 596 9797",
    "sg:postcode":"34613",
    "sg:province":"FL",
    "sg:tags":[
        "plumber",
        "industrial",
        "contractors-commercial"
    ],
    "wof:name":"J & J Plumbing Of Florida Inc",
    "wof:placetype":"venue"
},
  "geometry": {"coordinates":[-82.504859,28.571894],"type":"Point"}
}