{
  "type": "Feature",
  "properties": {
    "iso:country":"US",
    "sg:address":"1124 N Lake Reedy Blvd",
    "sg:city":"Frostproof",
    "sg:classifiers":[
        {
            "category":"Wholesale",
            "subcategory":"Farm Supplies",
            "type":"Manufacturing & Wholesale Goods"
        }
    ],
    "sg:phone":"+1 863 678 0060",
    "sg:postcode":"33843",
    "sg:province":"FL",
    "sg:tags":[
        "feed"
    ],
    "wof:name":"Mitchell's Feed & Tack",
    "wof:placetype":"venue"
},
  "geometry": {"coordinates":[-81.508313,27.756638],"type":"Point"}
}