{
  "type": "Feature",
  "properties": {
    "iso:country":"US",
    "sg:address":"110 21st St SW",
    "sg:city":"Naples",
    "sg:classifiers":[
        {
            "category":"Building & Trades",
            "subcategory":"Landscaping Services",
            "type":"Services"
        }
    ],
    "sg:phone":"+1 239 353 1011",
    "sg:postcode":"34117",
    "sg:province":"FL",
    "sg:tags":[
        "landscape",
        "contractor"
    ],
    "wof:name":"Jukins Landscaping",
    "wof:placetype":"venue"
},
  "geometry": {"coordinates":[-81.64897000000001,26.229216],"type":"Point"}
}