{
  "type": "Feature",
  "properties": {
    "iso:country":"US",
    "sg:address":"16701 Collins Ave",
    "sg:city":"North Miami Beach",
    "sg:classifiers":[
        {
            "category":"Restaurant",
            "type":"Food & Drink"
        }
    ],
    "sg:menulink":"http://www.allmenus.com/fl/miami-beach/292619-pelicans-on-the-pier/menu/",
    "sg:phone":"+1 305 945 9228",
    "sg:postcode":"33160",
    "sg:province":"FL",
    "sg:tags":[
        "seafood"
    ],
    "wof:name":"Pelicans on the Pier",
    "wof:placetype":"venue"
},
  "geometry": {"coordinates":[-80.12187400000001,25.930283],"type":"Point"}
}