{
  "type": "Feature",
  "properties": {
    "iso:country":"US",
    "sg:address":"29524 Crossland Dr",
    "sg:city":"Zephyrhills",
    "sg:classifiers":[
        {
            "category":"Shopping",
            "subcategory":"Clothing, Apparel, & Fashions",
            "type":"Retail Goods"
        }
    ],
    "sg:phone":"+1 813 355 2068",
    "sg:postcode":"33543",
    "sg:province":"FL",
    "sg:tags":[
        "tape",
        "magazine",
        "music"
    ],
    "wof:name":"Low End Hip Hop Shop The",
    "wof:placetype":"venue"
},
  "geometry": {"coordinates":[-82.33116099999999,28.172233],"type":"Point"}
}