{
  "type": "Feature",
  "properties": {
    "addr:full":"5051 Club Rd West Palm Beach FL 33415",
    "addr:housenumber":"5051",
    "addr:postcode":"33415",
    "addr:street":"Club Rd",
    "iso:country":"US",
    "sg:address":"5051 Club Rd",
    "sg:city":"West Palm Beach",
    "sg:classifiers":[
        {
            "category":"Building & Trades",
            "subcategory":"Construction",
            "type":"Services"
        }
    ],
    "sg:phone":"+1 561 478 2806",
    "sg:postcode":"33415",
    "sg:province":"FL",
    "sg:tags":[
        "tile",
        "marble",
        "contractor"
    ],
    "wof:name":"Featherstone Tile & Marble Inc",
    "wof:placetype":"venue"
},
  "geometry": {"coordinates":[-80.12217200000001,26.687764],"type":"Point"}
}