{
  "type": "Feature",
  "properties": {
    "iso:country":"US",
    "sg:address":"6809 State Hwy 70",
    "sg:city":"Bradenton",
    "sg:classifiers":[
        {
            "category":"Professional",
            "subcategory":"Computer Services",
            "type":"Services"
        }
    ],
    "sg:phone":"+1 941 753 6240",
    "sg:postcode":"34203",
    "sg:province":"FL",
    "sg:tags":[
        "web",
        "design",
        "site"
    ],
    "wof:name":"Net Effect Inc",
    "wof:placetype":"venue"
},
  "geometry": {"coordinates":[-82.471918,27.44493],"type":"Point"}
}