{
  "type": "Feature",
  "properties": {
    "addr:full":"212 N Moon Ave Brandon FL 33510",
    "addr:housenumber":"212",
    "addr:postcode":"33510",
    "addr:street":"N Moon Ave",
    "iso:country":"US",
    "sg:address":"212 N Moon Ave",
    "sg:city":"Brandon",
    "sg:classifiers":[
        {
            "category":"Health Services",
            "subcategory":"Doctor",
            "type":"Services"
        }
    ],
    "sg:phone":"+1 813 689 5928",
    "sg:postcode":"33510",
    "sg:province":"FL",
    "wof:name":"Raynal Eric C DMD",
    "wof:placetype":"venue"
},
  "geometry": {"coordinates":[-82.288287,27.940222],"type":"Point"}
}