{
  "type": "Feature",
  "properties": {
    "iso:country":"US",
    "sg:address":"2570 20th Ave N",
    "sg:city":"St Petersburg",
    "sg:classifiers":[
        {
            "category":"Building & Trades",
            "subcategory":"Electrical",
            "type":"Services"
        }
    ],
    "sg:phone":"+1 727 321 5299",
    "sg:postcode":"33713",
    "sg:province":"FL",
    "sg:tags":[
        "electrical",
        "electric",
        "contractor"
    ],
    "wof:name":"Frank F Lowry Electric Inc",
    "wof:placetype":"venue"
},
  "geometry": {"coordinates":[-82.667991,27.790042],"type":"Point"}
}