{
  "type": "Feature",
  "properties": {
    "addr:full":"4880 Coconut Ave Cocoa FL 32926",
    "addr:housenumber":"4880",
    "addr:postcode":"32926",
    "addr:street":"Coconut Ave",
    "iso:country":"US",
    "sg:address":"4880 Coconut Ave",
    "sg:city":"Cocoa",
    "sg:classifiers":[
        {
            "category":"Building & Trades",
            "subcategory":"Landscaping Services",
            "type":"Services"
        }
    ],
    "sg:phone":"+1 321 631 7323",
    "sg:postcode":"32926",
    "sg:province":"FL",
    "sg:tags":[
        "lawn",
        "maintenance",
        "grounds"
    ],
    "wof:name":"Propper Cuts",
    "wof:placetype":"venue"
},
  "geometry": {"coordinates":[-80.826115,28.404053],"type":"Point"}
}