{
  "type": "Feature",
  "properties": {
    "iso:country":"US",
    "sg:address":"1599 SW 159th Ter",
    "sg:city":"Hollywood",
    "sg:classifiers":[
        {
            "category":"Shopping",
            "subcategory":"Florist",
            "type":"Retail Goods"
        }
    ],
    "sg:phone":"+1 954 450 9700",
    "sg:postcode":"33027",
    "sg:province":"FL",
    "wof:name":"Floral Arrangements Inc",
    "wof:placetype":"venue"
},
  "geometry": {"coordinates":[-80.35863500000001,25.993781],"type":"Point"}
}