{
  "type": "Feature",
  "properties": {
    "iso:country":"US",
    "sg:address":"2229 NW 27th Ave",
    "sg:city":"Miami",
    "sg:classifiers":[
        {
            "category":"Real Estate",
            "subcategory":"Real Estate Operator",
            "type":"Services"
        }
    ],
    "sg:phone":"+1 305 634 1530",
    "sg:postcode":"33142",
    "sg:province":"FL",
    "sg:tags":[
        "building",
        "mall",
        "shopping",
        "center",
        "nonresidential"
    ],
    "wof:name":"R M Financial Partnership",
    "wof:placetype":"venue"
},
  "geometry": {"coordinates":[-80.239814,25.797327],"type":"Point"}
}