{
  "type": "Feature",
  "properties": {
    "iso:country":"US",
    "sg:address":"2101 N Nebraska Ave",
    "sg:city":"Tampa",
    "sg:classifiers":[
        {
            "category":"Autos & Motor Vehicles",
            "subcategory":"Automobile Sales",
            "type":"Retail Goods"
        }
    ],
    "sg:phone":"+1 813 975 0966",
    "sg:postcode":"33602",
    "sg:province":"FL",
    "sg:tags":[
        "used"
    ],
    "wof:name":"Bayridge Auto Sales",
    "wof:placetype":"venue"
},
  "geometry": {"coordinates":[-82.451228,27.96406],"type":"Point"}
}