{
  "type": "Feature",
  "properties": {
    "iso:country":"US",
    "sg:address":"1870 Miami Dr",
    "sg:city":"North Miami Bch",
    "sg:classifiers":[
        {
            "category":"Real Estate",
            "subcategory":"Real Estate Agent",
            "type":"Services"
        }
    ],
    "sg:phone":"+1 305 949 9493",
    "sg:postcode":"33162",
    "sg:province":"FL",
    "wof:name":"Belt-One Properties Inc",
    "wof:placetype":"venue"
},
  "geometry": {"coordinates":[-80.162184,25.930379],"type":"Point"}
}