{
  "type": "Feature",
  "properties": {
    "addr:full":"7161 Ulmerton Rd Largo FL 33771",
    "addr:housenumber":"7161",
    "addr:postcode":"33771",
    "addr:street":"Ulmerton Rd",
    "iso:country":"US",
    "sg:address":"7161 Ulmerton Rd",
    "sg:city":"Largo",
    "sg:classifiers":[
        {
            "category":"Restaurant",
            "type":"Food & Drink"
        }
    ],
    "sg:phone":"+1 727 531 6297",
    "sg:postcode":"33771",
    "sg:province":"FL",
    "wof:name":"Canas Chinese Restaurant",
    "wof:placetype":"venue"
},
  "geometry": {"coordinates":[-82.736862,27.894059],"type":"Point"}
}