{
  "type": "Feature",
  "properties": {
    "addr:full":"1025 W Hallandale Beach Blvd Hallandale FL 33009",
    "addr:housenumber":"1025",
    "addr:postcode":"33009",
    "addr:street":"W Hallandale Beach Blvd",
    "iso:country":"US",
    "sg:address":"1025 W Hallandale Beach Blvd",
    "sg:city":"Hallandale",
    "sg:classifiers":[
        {
            "category":"Restaurant",
            "type":"Food & Drink"
        }
    ],
    "sg:phone":"+1 954 458 0306",
    "sg:postcode":"33009",
    "sg:province":"FL",
    "sg:tags":[
        "eating"
    ],
    "wof:name":"Dennys",
    "wof:placetype":"venue"
},
  "geometry": {"coordinates":[-80.164056,25.985024],"type":"Point"}
}