{
  "type": "Feature",
  "properties": {
    "iso:country":"US",
    "sg:address":"2300 E Robinson St",
    "sg:city":"Orlando",
    "sg:classifiers":[
        {
            "category":"Shopping",
            "subcategory":"Books",
            "type":"Retail Goods"
        }
    ],
    "sg:phone":"+1 407 896 3866",
    "sg:postcode":"32803",
    "sg:province":"FL",
    "sg:tags":[
        "religious",
        "gift"
    ],
    "wof:name":"Abbey The",
    "wof:placetype":"venue"
},
  "geometry": {"coordinates":[-81.35193599999999,28.545942],"type":"Point"}
}