{
  "type": "Feature",
  "properties": {
    "iso:country":"US",
    "sg:address":"9236 Spring Run Blvd",
    "sg:city":"Bonita Springs",
    "sg:classifiers":[
        {
            "category":"Real Estate",
            "subcategory":"Real Estate Agent",
            "type":"Services"
        }
    ],
    "sg:phone":"+1 239 498 0034",
    "sg:postcode":"34135",
    "sg:province":"FL",
    "sg:tags":[
        "management"
    ],
    "wof:name":"Rainbows End Property Mgmt Crp",
    "wof:placetype":"venue"
},
  "geometry": {"coordinates":[-81.80270400000001,26.397471],"type":"Point"}
}