{
  "type": "Feature",
  "properties": {
    "addr:full":"503 Cherrywood Dr Ormond Beach FL 32174",
    "addr:housenumber":"503",
    "addr:postcode":"32174",
    "addr:street":"Cherrywood Dr",
    "iso:country":"US",
    "sg:address":"503 Cherrywood Dr",
    "sg:city":"Ormond Beach",
    "sg:classifiers":[
        {
            "category":"Manufacturing",
            "subcategory":"Food",
            "type":"Manufacturing & Wholesale Goods"
        }
    ],
    "sg:phone":"+1 386 676 5477",
    "sg:postcode":"32174",
    "sg:province":"FL",
    "sg:tags":[
        "flavor",
        "mfg"
    ],
    "wof:name":"Deising",
    "wof:placetype":"venue"
},
  "geometry": {"coordinates":[-81.06663500000001,29.273104],"type":"Point"}
}