{
  "type": "Feature",
  "properties": {
    "iso:country":"US",
    "sg:address":"8200 NW 30th Ter",
    "sg:city":"Miami",
    "sg:classifiers":[
        {
            "category":"Shopping",
            "subcategory":"Florist",
            "type":"Retail Goods"
        }
    ],
    "sg:phone":"+1 305 994 7760",
    "sg:postcode":"33122",
    "sg:province":"FL",
    "wof:name":"1 800 Flowerscom",
    "wof:placetype":"venue"
},
  "geometry": {"coordinates":[-80.333209,25.801713],"type":"Point"}
}