{
  "type": "Feature",
  "properties": {
    "addr:full":"14400 NW 77th Ct Ste 204 Hialeah FL 33016",
    "addr:housenumber":"14400",
    "addr:postcode":"33016",
    "addr:street":"Nw 77Th Ct Ste 204",
    "iso:country":"US",
    "sg:address":"14400 NW 77th Ct Ste 204",
    "sg:city":"Hialeah",
    "sg:classifiers":[
        {
            "category":"Wholesale",
            "subcategory":"Office Equipment",
            "type":"Manufacturing & Wholesale Goods"
        }
    ],
    "sg:phone":"+1 305 821 2039",
    "sg:postcode":"33016",
    "sg:province":"FL",
    "sg:tags":[
        "equipment-wholesale",
        "manufacturer",
        "furniture"
    ],
    "sg:website":"http://www.ricohusa.net",
    "wof:name":"Ricoh Americas Corporation",
    "wof:placetype":"venue"
},
  "geometry": {"coordinates":[-80.325171,25.905092],"type":"Point"}
}