{
  "type": "Feature",
  "properties": {
    "addr:full":"2112 S Old Mill Dr Deltona FL 32725",
    "addr:housenumber":"2112",
    "addr:postcode":"32725",
    "addr:street":"S Old Mill Dr",
    "iso:country":"US",
    "sg:address":"2112 S Old Mill Dr",
    "sg:city":"Deltona",
    "sg:classifiers":[
        {
            "category":"Health Services",
            "subcategory":"Dentist",
            "type":"Services"
        }
    ],
    "sg:phone":"+1 386 789 5976",
    "sg:postcode":"32725",
    "sg:province":"FL",
    "wof:name":"Zuch John",
    "wof:placetype":"venue"
},
  "geometry": {"coordinates":[-81.23406199999999,28.92222],"type":"Point"}
}