{
  "type": "Feature",
  "properties": {
    "addr:full":"1306 Wallwood Dr Brandon FL 33510",
    "addr:housenumber":"1306",
    "addr:postcode":"33510",
    "addr:street":"Wallwood Dr",
    "iso:country":"US",
    "sg:address":"1306 Wallwood Dr",
    "sg:city":"Brandon",
    "sg:classifiers":[
        {
            "category":"Building & Trades",
            "subcategory":"Electrical",
            "type":"Services"
        }
    ],
    "sg:phone":"+1 813 681 3223",
    "sg:postcode":"33510",
    "sg:province":"FL",
    "sg:tags":[
        "electric",
        "contractor"
    ],
    "wof:name":"Tutko Electric",
    "wof:placetype":"venue"
},
  "geometry": {"coordinates":[-82.32107499999999,27.961504],"type":"Point"}
}