{
  "type": "Feature",
  "properties": {
    "iso:country":"US",
    "sg:address":"5687 Naples Blvd",
    "sg:city":"Naples",
    "sg:classifiers":[
        {
            "category":"Social Services",
            "type":"Services"
        }
    ],
    "sg:phone":"+1 239 597 7070",
    "sg:postcode":"34109",
    "sg:province":"FL",
    "sg:tags":[
        "organization",
        "welfare"
    ],
    "wof:name":"Liberty Youth Ranch",
    "wof:placetype":"venue"
},
  "geometry": {"coordinates":[-81.76995100000001,26.219141],"type":"Point"}
}