{
  "type": "Feature",
  "properties": {
    "addr:full":"17107 SW 82nd Ct Miami FL 33157",
    "addr:housenumber":"17107",
    "addr:postcode":"33157",
    "addr:street":"Sw 82Nd Ct",
    "iso:country":"US",
    "sg:address":"17107 SW 82nd Ct",
    "sg:city":"Miami",
    "sg:classifiers":[
        {
            "category":"Insurance",
            "subcategory":"Insurance Agent",
            "type":"Services"
        }
    ],
    "sg:phone":"+1 786 242 2536",
    "sg:postcode":"33157",
    "sg:province":"FL",
    "wof:name":"Northwestern Mutual",
    "wof:placetype":"venue"
},
  "geometry": {"coordinates":[-80.325739,25.611883],"type":"Point"}
}