{
  "type": "Feature",
  "properties": {
    "iso:country":"US",
    "sg:address":"7 E Silver Springs Blvd",
    "sg:city":"Ocala",
    "sg:classifiers":[
        {
            "category":"Professional",
            "subcategory":"Advertising",
            "type":"Services"
        },
        {
            "category":"Professional",
            "subcategory":"Computer Services",
            "type":"Services"
        }
    ],
    "sg:phone":"+1 352 369 9607",
    "sg:postcode":"34470",
    "sg:province":"FL",
    "sg:tags":[
        "web",
        "agency",
        "site",
        "hosting",
        "design",
        "software"
    ],
    "sg:website":"http://www.blackkatstudio.com",
    "wof:name":"Black Kat Studio Inc",
    "wof:placetype":"venue"
},
  "geometry": {"coordinates":[-82.13694099999999,29.187091],"type":"Point"}
}