{
  "type": "Feature",
  "properties": {
    "iso:country":"US",
    "sg:address":"413 Oak Pl",
    "sg:city":"Port Orange",
    "sg:classifiers":[
        {
            "category":"Retail",
            "subcategory":"Repair Shop",
            "type":"Services"
        }
    ],
    "sg:phone":"+1 386 756 1226",
    "sg:postcode":"32127",
    "sg:province":"FL",
    "sg:tags":[
        "high",
        "fidelity",
        "stereophonic"
    ],
    "wof:name":"A J Electronic's",
    "wof:placetype":"venue"
},
  "geometry": {"coordinates":[-80.99144800000001,29.13619],"type":"Point"}
}