{
  "type": "Feature",
  "properties": {
    "iso:country":"US",
    "sg:address":"3222 Bellingham Dr",
    "sg:city":"Orlando",
    "sg:classifiers":[
        {
            "category":"Building & Trades",
            "subcategory":"Cleaning & Sanitation",
            "type":"Services"
        }
    ],
    "sg:phone":"+1 407 282 3857",
    "sg:postcode":"32825",
    "sg:province":"FL",
    "sg:tags":[
        "janitor"
    ],
    "wof:name":"Julio A Vega Janitorial",
    "wof:placetype":"venue"
},
  "geometry": {"coordinates":[-81.23620099999999,28.50743],"type":"Point"}
}