{
  "type": "Feature",
  "properties": {
    "iso:country":"US",
    "sg:address":"1620 Adamo Dr",
    "sg:city":"Tampa",
    "sg:classifiers":[
        {
            "category":"Insurance",
            "subcategory":"Insurance Agent",
            "type":"Services"
        }
    ],
    "sg:phone":"+1 813 248 1135",
    "sg:postcode":"33605",
    "sg:province":"FL",
    "sg:tags":[
        "agency"
    ],
    "wof:name":"Lord & Co PLC",
    "wof:placetype":"venue"
},
  "geometry": {"coordinates":[-82.441435,27.955887],"type":"Point"}
}