{
  "type": "Feature",
  "properties": {
    "iso:country":"US",
    "sg:address":"1320 Carrick Ave",
    "sg:city":"Pensacola",
    "sg:classifiers":[
        {
            "category":"Professional",
            "subcategory":"Business Services",
            "type":"Services"
        }
    ],
    "sg:phone":"+1 850 453 3714",
    "sg:postcode":"32506",
    "sg:province":"FL",
    "sg:tags":[
        "production",
        "video",
        "duplication"
    ],
    "wof:name":"Your Out Door Productions",
    "wof:placetype":"venue"
},
  "geometry": {"coordinates":[-87.316997,30.389057],"type":"Point"}
}