{
  "type": "Feature",
  "properties": {
    "iso:country":"US",
    "sg:address":"594 Benjamin Franklin Pl",
    "sg:city":"Orlando",
    "sg:classifiers":[
        {
            "category":"Professional",
            "subcategory":"Detective & Security Services",
            "type":"Services"
        }
    ],
    "sg:phone":"+1 407 415 8122",
    "sg:postcode":"32809",
    "sg:province":"FL",
    "sg:tags":[
        "information",
        "bureau"
    ],
    "wof:name":"Spotless Cleanig Services",
    "wof:placetype":"venue"
},
  "geometry": {"coordinates":[-81.381463,28.457003],"type":"Point"}
}