{
  "type": "Feature",
  "properties": {
    "iso:country":"US",
    "sg:address":"4208 N Renellie Dr",
    "sg:city":"Tampa",
    "sg:classifiers":[
        {
            "category":"Building & Trades",
            "subcategory":"Construction",
            "type":"Services"
        }
    ],
    "sg:phone":"+1 813 873 9394",
    "sg:postcode":"33614",
    "sg:province":"FL",
    "sg:tags":[
        "waterproofing",
        "contractor"
    ],
    "sg:website":"www.fiber-deck.com",
    "wof:name":"Fiber Deck Inc",
    "wof:placetype":"venue"
},
  "geometry": {"coordinates":[-82.52285000000001,27.980513],"type":"Point"}
}