{
  "type": "Feature",
  "properties": {
    "iso:country":"US",
    "sg:address":"2589 Parkway Dr",
    "sg:city":"De Land",
    "sg:classifiers":[
        {
            "category":"Building & Trades",
            "subcategory":"Construction",
            "type":"Services"
        }
    ],
    "sg:phone":"+1 386 734 8427",
    "sg:postcode":"32720",
    "sg:province":"FL",
    "sg:tags":[
        "carpentry",
        "contractor"
    ],
    "wof:name":"Alfies Custom Woodwork",
    "wof:placetype":"venue"
},
  "geometry": {"coordinates":[-81.321393,29.073032],"type":"Point"}
}