{
  "type": "Feature",
  "properties": {
    "iso:country":"US",
    "sg:address":"3190 Belle Christiane Cir",
    "sg:city":"Pensacola",
    "sg:classifiers":[
        {
            "category":"Wholesale",
            "subcategory":"Books, Periodicals, & Newspapers",
            "type":"Manufacturing & Wholesale Goods"
        }
    ],
    "sg:phone":"+1 850 433 1358",
    "sg:postcode":"32503",
    "sg:province":"FL",
    "wof:name":"Sandford Baines Publishin",
    "wof:placetype":"venue"
},
  "geometry": {"coordinates":[-87.17810900000001,30.447903],"type":"Point"}
}