{
  "type": "Feature",
  "properties": {
    "addr:full":"2500 N Forsyth Rd Orlando FL 32807",
    "addr:housenumber":"2500",
    "addr:postcode":"32807",
    "addr:street":"N Forsyth Rd",
    "iso:country":"US",
    "sg:address":"2500 N Forsyth Rd",
    "sg:city":"Orlando",
    "sg:classifiers":[
        {
            "category":"Real Estate",
            "subcategory":"Real Estate Operator",
            "type":"Services"
        }
    ],
    "sg:phone":"+1 407 678 0507",
    "sg:postcode":"32807",
    "sg:province":"FL",
    "sg:tags":[
        "building",
        "nonresidential"
    ],
    "wof:name":"A&H Industrial Park",
    "wof:placetype":"venue"
},
  "geometry": {"coordinates":[-81.29458700000001,28.583482],"type":"Point"}
}