{
  "type": "Feature",
  "properties": {
    "addr:full":"16080 SW 138th Pl Miami FL 33177",
    "addr:housenumber":"16080",
    "addr:postcode":"33177",
    "addr:street":"Sw 138Th Pl",
    "iso:country":"US",
    "sg:address":"16080 SW 138th Pl",
    "sg:city":"Miami",
    "sg:classifiers":[
        {
            "category":"Professional",
            "type":"Services"
        }
    ],
    "sg:phone":"+1 305 278 8120",
    "sg:postcode":"33177",
    "sg:province":"FL",
    "wof:name":"Regency Sound Station Inc",
    "wof:placetype":"venue"
},
  "geometry": {"coordinates":[-80.417912,25.617218],"type":"Point"}
}