{
  "type": "Feature",
  "properties": {
    "iso:country":"US",
    "sg:address":"660 N Dixie Hwy",
    "sg:city":"Hollywood",
    "sg:classifiers":[
        {
            "category":"Health Services",
            "subcategory":"Doctor",
            "type":"Services"
        }
    ],
    "sg:phone":"+1 954 923 0399",
    "sg:postcode":"33020",
    "sg:province":"FL",
    "sg:tags":[
        "dentist"
    ],
    "wof:name":"Sr & Jr Dental",
    "wof:placetype":"venue"
},
  "geometry": {"coordinates":[-80.149569,26.017062],"type":"Point"}
}