{
  "type": "Feature",
  "properties": {
    "addr:full":"927 NE 125th Street North Miami FL 33161",
    "addr:housenumber":"927",
    "addr:postcode":"33161",
    "addr:street":"Ne 125Th Street",
    "iso:country":"US",
    "sg:address":"927 NE 125th Street",
    "sg:city":"North Miami",
    "sg:classifiers":[
        {
            "category":"Restaurant",
            "type":"Food & Drink"
        }
    ],
    "sg:phone":"+1 305 873 6444",
    "sg:postcode":"33161",
    "sg:province":"FL",
    "sg:tags":[
        "new",
        "american"
    ],
    "wof:name":"Grateful Bread",
    "wof:placetype":"venue"
},
  "geometry": {"coordinates":[-80.179838,25.890566],"type":"Point"}
}