{
  "type": "Feature",
  "properties": {
    "iso:country":"US",
    "sg:address":"1017 North Blvd E",
    "sg:city":"Leesburg",
    "sg:classifiers":[
        {
            "category":"Health Services",
            "subcategory":"Health Practitioner",
            "type":"Services"
        }
    ],
    "sg:phone":"+1 352 315 9006",
    "sg:postcode":"34748",
    "sg:province":"FL",
    "sg:tags":[
        "therapy",
        "physical"
    ],
    "wof:name":"P T Centers of Florida",
    "wof:placetype":"venue"
},
  "geometry": {"coordinates":[-81.86213600000001,28.813334],"type":"Point"}
}