{
  "type": "Feature",
  "properties": {
    "iso:country":"US",
    "sg:address":"4618 Bartelt Rd",
    "sg:city":"Holiday",
    "sg:classifiers":[
        {
            "category":"Retail",
            "subcategory":"Repair Shop",
            "type":"Services"
        },
        {
            "category":"Building & Trades",
            "subcategory":"Plumbing",
            "type":"Services"
        }
    ],
    "sg:phone":"+1 727 849 6142",
    "sg:postcode":"34690",
    "sg:province":"FL",
    "sg:tags":[
        "plumbing",
        "drain",
        "cleaning",
        "sewer",
        "contractor"
    ],
    "wof:name":"Ed Hauck Master Plumbers Inc",
    "wof:placetype":"venue"
},
  "geometry": {"coordinates":[-82.73847000000001,28.184745],"type":"Point"}
}