{
  "type": "Feature",
  "properties": {
    "iso:country":"US",
    "sg:address":"8578 NW 56th St",
    "sg:city":"Doral",
    "sg:classifiers":[
        {
            "category":"Transit Center",
            "subcategory":"Freight",
            "type":"Transportation"
        },
        {
            "category":"Professional",
            "subcategory":"Business Services",
            "type":"Services"
        }
    ],
    "sg:phone":"+1 305 471 7970",
    "sg:postcode":"33166",
    "sg:province":"FL",
    "sg:tags":[
        "container",
        "broker",
        "shipping"
    ],
    "sg:website":"http://www.lifegp.us",
    "wof:name":"Life Cargo",
    "wof:placetype":"venue"
},
  "geometry": {"coordinates":[-80.336122,25.824381],"type":"Point"}
}