{
  "type": "Feature",
  "properties": {
    "iso:country":"US",
    "sg:address":"4775 State Hwy 305",
    "sg:city":"Elkton",
    "sg:classifiers":[
        {
            "category":"Home & Garden",
            "subcategory":"Garden Supply",
            "type":"Retail Goods"
        }
    ],
    "sg:phone":"+1 904 692 2016",
    "sg:postcode":"32033",
    "sg:province":"FL",
    "sg:tags":[
        "nurseryman"
    ],
    "wof:name":"Green Wave Nursery",
    "wof:placetype":"venue"
},
  "geometry": {"coordinates":[-81.426002,29.787264],"type":"Point"}
}