{
  "type": "Feature",
  "properties": {
    "iso:country":"US",
    "sg:address":"4646 W Irlo Bronson Memorial Hwy",
    "sg:city":"Kissimmee",
    "sg:classifiers":[
        {
            "category":"Professional",
            "type":"Services"
        }
    ],
    "sg:phone":"+1 407 396 7744",
    "sg:postcode":"34746",
    "sg:province":"FL",
    "sg:tags":[
        "establishment"
    ],
    "wof:name":"Vocational Corp",
    "wof:placetype":"venue"
},
  "geometry": {"coordinates":[-81.467191,28.312622],"type":"Point"}
}