{
  "type": "Feature",
  "properties": {
    "iso:country":"US",
    "sg:address":"599 W 49th St",
    "sg:city":"Hialeah",
    "sg:classifiers":[
        {
            "category":"Shopping",
            "type":"Retail Goods"
        }
    ],
    "sg:phone":"+1 305 557 3360",
    "sg:postcode":"33012",
    "sg:province":"FL",
    "sg:tags":[
        "outdoor",
        "lighting",
        "specialty"
    ],
    "sg:website":"www.fabulousdiamonds.com",
    "wof:name":"Diamonds Fabulous",
    "wof:placetype":"venue"
},
  "geometry": {"coordinates":[-80.291099,25.866664],"type":"Point"}
}