{
  "type": "Feature",
  "properties": {
    "addr:full":"6192 Elliott St Punta Gorda FL 33950",
    "addr:housenumber":"6192",
    "addr:postcode":"33950",
    "addr:street":"Elliott St",
    "iso:country":"US",
    "sg:address":"6192 Elliott St",
    "sg:city":"Punta Gorda",
    "sg:classifiers":[
        {
            "category":"Shopping",
            "subcategory":"Used Merchandise",
            "type":"Retail Goods"
        }
    ],
    "sg:phone":"+1 941 255 9700",
    "sg:postcode":"33950",
    "sg:province":"FL",
    "sg:tags":[
        "shop",
        "consignment"
    ],
    "wof:name":"Consigning Woman Enterprises",
    "wof:placetype":"venue"
},
  "geometry": {"coordinates":[-82.037257,26.94258],"type":"Point"}
}