{
  "type": "Feature",
  "properties": {
    "addr:full":"272 Lytton Cir Orlando FL 32824",
    "addr:housenumber":"272",
    "addr:postcode":"32824",
    "addr:street":"Lytton Cir",
    "iso:country":"US",
    "sg:address":"272 Lytton Cir",
    "sg:city":"Orlando",
    "sg:classifiers":[
        {
            "category":"Professional",
            "subcategory":"Research",
            "type":"Services"
        }
    ],
    "sg:phone":"+1 407 353 4192",
    "sg:postcode":"32824",
    "sg:province":"FL",
    "sg:tags":[
        "development",
        "material",
        "advanced"
    ],
    "wof:name":"NTI",
    "wof:placetype":"venue"
},
  "geometry": {"coordinates":[-81.38665399999999,28.396051],"type":"Point"}
}