{
  "type": "Feature",
  "properties": {
    "addr:full":"9390 Lem Turner Rd Jacksonville FL 32208",
    "addr:postcode":"9390;32208",
    "addr:street":"Turner Rd",
    "iso:country":"US",
    "sg:address":"9390 Lem Turner Rd",
    "sg:city":"Jacksonville",
    "sg:classifiers":[
        {
            "category":"Health Services",
            "subcategory":"Doctor",
            "type":"Services"
        }
    ],
    "sg:phone":"+1 904 766 2992",
    "sg:postcode":"32208",
    "sg:province":"FL",
    "sg:tags":[
        "physician",
        "family",
        "practice",
        "surgeons",
        "medicine"
    ],
    "wof:name":"Lem Turner Family Medical",
    "wof:placetype":"venue"
},
  "geometry": {"coordinates":[-81.68897200000001,30.41057],"type":"Point"}
}