{
  "type": "Feature",
  "properties": {
    "iso:country":"US",
    "sg:address":"909 S Ridgewood Ave",
    "sg:city":"Edgewater",
    "sg:classifiers":[
        {
            "category":"Retail",
            "subcategory":"Veterinary Services",
            "type":"Services"
        }
    ],
    "sg:phone":"+1 386 427 8339",
    "sg:postcode":"32132",
    "sg:province":"FL",
    "wof:name":"Indian River Animal Clinic",
    "wof:placetype":"venue"
},
  "geometry": {"coordinates":[-80.902444,28.983195],"type":"Point"}
}