{
  "type": "Feature",
  "properties": {
    "iso:country":"US",
    "sg:address":"150 W Jessup Ave",
    "sg:city":"Longwood",
    "sg:classifiers":[
        {
            "category":"Building & Trades",
            "subcategory":"Landscaping Services",
            "type":"Services"
        }
    ],
    "sg:phone":"+1 407 667 1777",
    "sg:postcode":"32750",
    "sg:province":"FL",
    "sg:tags":[
        "design"
    ],
    "wof:name":"Dix Lathrop Inc",
    "wof:placetype":"venue"
},
  "geometry": {"coordinates":[-81.348158,28.701429],"type":"Point"}
}