{
  "type": "Feature",
  "properties": {
    "iso:country":"US",
    "sg:address":"10875 SW 45th Ave",
    "sg:city":"Ocala",
    "sg:classifiers":[
        {
            "category":"Building & Trades",
            "subcategory":"Construction",
            "type":"Services"
        }
    ],
    "sg:phone":"+1 352 216 0688",
    "sg:postcode":"34476",
    "sg:province":"FL",
    "sg:tags":[
        "painter"
    ],
    "wof:name":"Steven Wood's Coatings",
    "wof:placetype":"venue"
},
  "geometry": {"coordinates":[-82.193882,29.064248],"type":"Point"}
}