{
  "type": "Feature",
  "properties": {
    "addr:full":"3625 S Florida Ave Lakeland FL 33803",
    "addr:housenumber":"3625",
    "addr:postcode":"33803",
    "addr:street":"S Florida Ave",
    "iso:country":"US",
    "sg:address":"3625 S Florida Ave",
    "sg:city":"Lakeland",
    "sg:classifiers":[
        {
            "category":"Recreation",
            "type":"Entertainment"
        }
    ],
    "sg:phone":"+1 863 648 5355",
    "sg:postcode":"33803",
    "sg:province":"FL",
    "sg:tags":[
        "martial",
        "arts",
        "instruction"
    ],
    "wof:name":"World Oyama Karate",
    "wof:placetype":"venue"
},
  "geometry": {"coordinates":[-81.957166,27.998754],"type":"Point"}
}