{
  "type": "Feature",
  "properties": {
    "addr:full":"4908 Creekside Dr Clearwater FL 33760",
    "addr:housenumber":"4908",
    "addr:postcode":"33760",
    "addr:street":"Creekside Dr",
    "iso:country":"US",
    "sg:address":"4908 Creekside Dr",
    "sg:city":"Clearwater",
    "sg:classifiers":[
        {
            "category":"Arts & Performance",
            "subcategory":"Theater",
            "type":"Entertainment"
        }
    ],
    "sg:phone":"+1 727 572 0400",
    "sg:postcode":"33760",
    "sg:province":"FL",
    "sg:tags":[
        "program",
        "radio",
        "producer"
    ],
    "wof:name":"Medical Broadcasting Corp",
    "wof:placetype":"venue"
},
  "geometry": {"coordinates":[-82.701536,27.891241],"type":"Point"}
}