{
  "type": "Feature",
  "properties": {
    "iso:country":"US",
    "sg:address":"3480 W 84th St",
    "sg:city":"Hialeah",
    "sg:classifiers":[
        {
            "category":"Utilities",
            "subcategory":"Telephone",
            "type":"Services"
        },
        {
            "category":"Manufacturing",
            "subcategory":"Electronics",
            "type":"Manufacturing & Wholesale Goods"
        }
    ],
    "sg:phone":"+1 305 512 9451",
    "sg:postcode":"33018",
    "sg:province":"FL",
    "sg:tags":[
        "equipment",
        "telecommunications-equipment",
        "system",
        "supply"
    ],
    "wof:name":"Access Datacom",
    "wof:placetype":"venue"
},
  "geometry": {"coordinates":[-80.354009,25.898626],"type":"Point"}
}