{
  "type": "Feature",
  "properties": {
    "iso:country":"US",
    "sg:address":"9040 SW 152nd St",
    "sg:city":"Palmetto Bay",
    "sg:classifiers":[
        {
            "category":"Health Services",
            "subcategory":"Chiropractor",
            "type":"Services"
        }
    ],
    "sg:phone":"+1 305 663 6678",
    "sg:postcode":"33157",
    "sg:province":"FL",
    "wof:name":"Accurso Joseph W DC",
    "wof:placetype":"venue"
},
  "geometry": {"coordinates":[-80.34011,25.628823],"type":"Point"}
}