{
  "type": "Feature",
  "properties": {
    "iso:country":"US",
    "sg:address":"730 Thomas Ln",
    "sg:city":"Cocoa",
    "sg:classifiers":[
        {
            "category":"Personal",
            "subcategory":"Beauty Salon",
            "type":"Services"
        }
    ],
    "sg:phone":"+1 321 636 6403",
    "sg:postcode":"32922",
    "sg:province":"FL",
    "wof:name":"Mary's Beauty Nook",
    "wof:placetype":"venue"
},
  "geometry": {"coordinates":[-80.739797,28.352694],"type":"Point"}
}