{
  "type": "Feature",
  "properties": {
    "addr:full":"10631 NW 88th Ave Hialeah FL 33018",
    "addr:housenumber":"10631",
    "addr:postcode":"33018",
    "addr:street":"Nw 88Th Ave",
    "iso:country":"US",
    "sg:address":"10631 NW 88th Ave",
    "sg:city":"Hialeah",
    "sg:classifiers":[
        {
            "category":"Health Services",
            "subcategory":"Clinic",
            "type":"Services"
        },
        {
            "category":"Health Services",
            "subcategory":"Health Practitioner",
            "type":"Services"
        }
    ],
    "sg:phone":"+1 305 274 1641",
    "sg:postcode":"33018",
    "sg:province":"FL",
    "sg:tags":[
        "information",
        "mental",
        "drug",
        "abuse",
        "treatment",
        "addiction",
        "alcoholism"
    ],
    "wof:name":"Professional Health Network Inc",
    "wof:placetype":"venue"
},
  "geometry": {"coordinates":[-80.340807,25.870021],"type":"Point"}
}