{
  "type": "Feature",
  "properties": {
    "iso:country":"US",
    "sg:address":"4970 SW 52nd St # 315",
    "sg:city":"Davie",
    "sg:classifiers":[
        {
            "category":"Building & Trades",
            "subcategory":"Locksmith",
            "type":"Services"
        }
    ],
    "sg:phone":"+1 954 321 8272",
    "sg:postcode":"33314",
    "sg:province":"FL",
    "sg:tags":[
        "locksmiths-commercial",
        "industrial",
        "key",
        "lock"
    ],
    "wof:name":"Skylex Lock & Safe",
    "wof:placetype":"venue"
},
  "geometry": {"coordinates":[-80.210109,26.057223],"type":"Point"}
}