{
  "type": "Feature",
  "properties": {
    "iso:country":"US",
    "sg:address":"19907 Front Beach Rd",
    "sg:city":"Panama City",
    "sg:classifiers":[
        {
            "category":"Real Estate",
            "subcategory":"Real Estate Agent",
            "type":"Services"
        }
    ],
    "sg:phone":"+1 850 249 9020",
    "sg:postcode":"32413",
    "sg:province":"FL",
    "wof:name":"Luxury Vacation Rentals",
    "wof:placetype":"venue"
},
  "geometry": {"coordinates":[-85.940326,30.246808],"type":"Point"}
}