{
  "type": "Feature",
  "properties": {
    "iso:country":"US",
    "sg:address":"1086 Masterson St",
    "sg:city":"Melbourne",
    "sg:classifiers":[
        {
            "category":"Banks & Credit Unions",
            "subcategory":"Investment Brokerage",
            "type":"Services"
        }
    ],
    "sg:phone":"+1 321 243 5775",
    "sg:postcode":"32935",
    "sg:province":"FL",
    "sg:tags":[
        "advisory",
        "financial"
    ],
    "wof:name":"Alyse Wright Enterprises",
    "wof:placetype":"venue"
},
  "geometry": {"coordinates":[-80.635949,28.139],"type":"Point"}
}