{
  "type": "Feature",
  "properties": {
    "iso:country":"US",
    "sg:address":"201 W 23rd St",
    "sg:city":"Hialeah",
    "sg:classifiers":[
        {
            "category":"Wholesale",
            "subcategory":"Construction Materials",
            "type":"Manufacturing & Wholesale Goods"
        },
        {
            "category":"Home & Garden",
            "subcategory":"Building Materials",
            "type":"Retail Goods"
        }
    ],
    "sg:phone":"+1 305 888 8783",
    "sg:postcode":"33010",
    "sg:province":"FL",
    "sg:tags":[
        "systems-wholesale",
        "equipment",
        "heating",
        "system"
    ],
    "wof:name":"Boiler And Oil Service Corp",
    "wof:placetype":"venue"
},
  "geometry": {"coordinates":[-80.28610999999999,25.84272],"type":"Point"}
}