{
  "type": "Feature",
  "properties": {
    "iso:country":"US",
    "sg:address":"915 Vineland Pl",
    "sg:city":"Lake Mary",
    "sg:classifiers":[
        {
            "category":"Building & Trades",
            "subcategory":"Cleaning & Sanitation",
            "type":"Services"
        }
    ],
    "sg:phone":"+1 407 268 3310",
    "sg:postcode":"32746",
    "sg:province":"FL",
    "sg:tags":[
        "house"
    ],
    "wof:name":"Home Services At Heathrow",
    "wof:placetype":"venue"
},
  "geometry": {"coordinates":[-81.305288,28.775166],"type":"Point"}
}