{
  "type": "Feature",
  "properties": {
    "addr:full":"6741 Land O Lakes Blvd Land O Lakes FL 34638",
    "addr:housenumber":"6741",
    "addr:postcode":"34638",
    "addr:street":"Land O Lakes Blvd Land",
    "iso:country":"US",
    "sg:address":"6741 Land O Lakes Blvd",
    "sg:city":"Land O Lakes",
    "sg:classifiers":[
        {
            "category":"Organizations",
            "subcategory":"Non-profit Organization",
            "type":"Services"
        }
    ],
    "sg:phone":"+1 813 996 0205",
    "sg:postcode":"34638",
    "sg:province":"FL",
    "sg:tags":[
        "information",
        "alcoholism",
        "treatment"
    ],
    "wof:name":"Alpha Counseling Svc",
    "wof:placetype":"venue"
},
  "geometry": {"coordinates":[-82.472902,28.256119],"type":"Point"}
}