{
  "type": "Feature",
  "properties": {
    "iso:country":"US",
    "sg:address":"1131 SE 3rd Ave",
    "sg:city":"Fort Lauderdale",
    "sg:classifiers":[
        {
            "category":"Real Estate",
            "subcategory":"Real Estate Agent",
            "type":"Services"
        }
    ],
    "sg:phone":"+1 954 763 8033",
    "sg:postcode":"33316",
    "sg:province":"FL",
    "sg:tags":[
        "consultant",
        "appraiser"
    ],
    "wof:name":"Roe Minor Realty Consultants",
    "wof:placetype":"venue"
},
  "geometry": {"coordinates":[-80.14016599999999,26.108139],"type":"Point"}
}