{
  "type": "Feature",
  "properties": {
    "iso:country":"US",
    "sg:address":"699 Manatee Ave",
    "sg:city":"Bradenton Beach",
    "sg:classifiers":[
        {
            "category":"Banks & Credit Unions",
            "subcategory":"Bank",
            "type":"Services"
        }
    ],
    "sg:phone":"+1 941 778 4566",
    "sg:postcode":"34217",
    "sg:province":"FL",
    "sg:tags":[
        "national"
    ],
    "wof:name":"Bank of America NA",
    "wof:placetype":"venue"
},
  "geometry": {"coordinates":[-82.69988600000001,27.496911],"type":"Point"}
}