{
  "type": "Feature",
  "properties": {
    "iso:country":"US",
    "sg:address":"1470 NW 107th Ave",
    "sg:city":"Doral",
    "sg:classifiers":[
        {
            "category":"Retail",
            "subcategory":"Auto Repair",
            "type":"Services"
        }
    ],
    "sg:phone":"+1 305 470 9393",
    "sg:postcode":"33172",
    "sg:province":"FL",
    "sg:tags":[
        "glass",
        "coating",
        "tinting"
    ],
    "wof:name":"Confianza Window Tinting",
    "wof:placetype":"venue"
},
  "geometry": {"coordinates":[-80.368893,25.78738],"type":"Point"}
}