{
  "type": "Feature",
  "properties": {
    "addr:full":"601 E Mallory St Pensacola FL 32503",
    "addr:housenumber":"601",
    "addr:postcode":"32503",
    "addr:street":"E Mallory St",
    "iso:country":"US",
    "sg:address":"601 E Mallory St",
    "sg:city":"Pensacola",
    "sg:classifiers":[
        {
            "category":"Place Of Worship",
            "type":"Public Place"
        }
    ],
    "sg:phone":"+1 850 266 3369",
    "sg:postcode":"32503",
    "sg:province":"FL",
    "sg:tags":[
        "church"
    ],
    "wof:name":"Mt Moriah Faith Deliverance Holiness Church, Inc.",
    "wof:placetype":"venue"
},
  "geometry": {"coordinates":[-87.21167,30.43112],"type":"Point"}
}