{
  "type": "Feature",
  "properties": {
    "iso:country":"US",
    "sg:address":"9322 Front Beach Rd",
    "sg:city":"Panama City",
    "sg:classifiers":[
        {
            "category":"Travel",
            "subcategory":"Hotels & Motels",
            "type":"Entertainment"
        }
    ],
    "sg:phone":"+1 850 234 2278",
    "sg:postcode":"32407",
    "sg:province":"FL",
    "sg:tags":[
        "operation",
        "trailer"
    ],
    "wof:name":"Park Place Campground & Motel",
    "wof:placetype":"venue"
},
  "geometry": {"coordinates":[-85.792333,30.180702],"type":"Point"}
}