{
  "type": "Feature",
  "properties": {
    "addr:full":"2500 SW 107th Ave Miami FL 33165",
    "addr:housenumber":"2500",
    "addr:postcode":"33165",
    "addr:street":"Sw 107Th Ave",
    "iso:country":"US",
    "sg:address":"2500 SW 107th Ave",
    "sg:city":"Miami",
    "sg:classifiers":[
        {
            "category":"Professional",
            "subcategory":"Engineering",
            "type":"Services"
        },
        {
            "category":"Professional",
            "subcategory":"Computer Services",
            "type":"Services"
        }
    ],
    "sg:phone":"+1 305 480 0738",
    "sg:postcode":"33165",
    "sg:province":"FL",
    "sg:tags":[
        "custom",
        "management",
        "programing",
        "engineer"
    ],
    "wof:name":"Southernmost Systems Inc",
    "wof:placetype":"venue"
},
  "geometry": {"coordinates":[-80.367705,25.745331],"type":"Point"}
}