{
  "type": "Feature",
  "properties": {
    "addr:full":"307 Johnson St Hollywood FL 33019",
    "addr:housenumber":"307",
    "addr:postcode":"33019",
    "addr:street":"Johnson St",
    "iso:country":"US",
    "sg:address":"307 Johnson St",
    "sg:city":"Hollywood",
    "sg:classifiers":[
        {
            "category":"Shopping",
            "subcategory":"Clothing, Apparel, & Fashions",
            "type":"Retail Goods"
        }
    ],
    "sg:phone":"+1 954 922 9194",
    "sg:postcode":"33019",
    "sg:province":"FL",
    "sg:tags":[
        "sport"
    ],
    "wof:name":"Swim N Jog",
    "wof:placetype":"venue"
},
  "geometry": {"coordinates":[-80.116916,26.019565],"type":"Point"}
}