{
  "type": "Feature",
  "properties": {
    "iso:country":"US",
    "sg:address":"301 Balfour Dr",
    "sg:city":"Winter Park",
    "sg:classifiers":[
        {
            "category":"Shopping",
            "subcategory":"Discount & Variety Stores",
            "type":"Retail Goods"
        }
    ],
    "sg:phone":"+1 407 677 1386",
    "sg:postcode":"32792",
    "sg:province":"FL",
    "sg:tags":[
        "merchandise",
        "general"
    ],
    "wof:name":"Jesus Gonzalez Enterprises",
    "wof:placetype":"venue"
},
  "geometry": {"coordinates":[-81.317015,28.60006],"type":"Point"}
}