{
  "type": "Feature",
  "properties": {
    "iso:country":"US",
    "sg:address":"3039 Forest Dr",
    "sg:city":"Lakeland",
    "sg:classifiers":[
        {
            "category":"Wholesale",
            "subcategory":"Auto Parts",
            "type":"Manufacturing & Wholesale Goods"
        }
    ],
    "sg:phone":"+1 863 648 5920",
    "sg:postcode":"33811",
    "sg:province":"FL",
    "wof:name":"Suncoast Automotive",
    "wof:placetype":"venue"
},
  "geometry": {"coordinates":[-82.00839000000001,27.969398],"type":"Point"}
}