{
  "type": "Feature",
  "properties": {
    "iso:country":"US",
    "sg:address":"1343 W 72nd St",
    "sg:city":"Hialeah",
    "sg:classifiers":[
        {
            "category":"Professional",
            "type":"Services"
        }
    ],
    "sg:phone":"+1 305 823 8390",
    "sg:postcode":"33014",
    "sg:province":"FL",
    "sg:tags":[
        "establishment"
    ],
    "wof:name":"Tc Corp",
    "wof:placetype":"venue"
},
  "geometry": {"coordinates":[-80.311522,25.887981],"type":"Point"}
}