{
  "type": "Feature",
  "properties": {
    "iso:country":"US",
    "sg:address":"310 S Dale Mabry Hwy",
    "sg:city":"Tampa",
    "sg:classifiers":[
        {
            "category":"Professional",
            "subcategory":"Lawyer & Legal Services",
            "type":"Services"
        }
    ],
    "sg:phone":"+1 813 765 9464",
    "sg:postcode":"33609",
    "sg:province":"FL",
    "sg:tags":[
        "attorney"
    ],
    "wof:name":"David A Fontes",
    "wof:placetype":"venue"
},
  "geometry": {"coordinates":[-82.505647,27.941316],"type":"Point"}
}