{
  "type": "Feature",
  "properties": {
    "addr:full":"28059 US Hwy 19 Clearwater FL 33761",
    "addr:postcode":"28059;33761",
    "addr:street":"Us Hwy 19",
    "iso:country":"US",
    "sg:address":"28059 US Hwy 19",
    "sg:city":"Clearwater",
    "sg:classifiers":[
        {
            "category":"Banks & Credit Unions",
            "subcategory":"Bank",
            "type":"Services"
        }
    ],
    "sg:phone":"+1 727 796 2900",
    "sg:postcode":"33761",
    "sg:province":"FL",
    "wof:name":"Republic Bank",
    "wof:placetype":"venue"
},
  "geometry": {"coordinates":[-82.738079,28.027331],"type":"Point"}
}