{
  "type": "Feature",
  "properties": {
    "iso:country":"US",
    "sg:address":"4815 Manatee Ave W",
    "sg:city":"Bradenton",
    "sg:classifiers":[
        {
            "category":"Wholesale",
            "subcategory":"Medical Equipment & Supplies",
            "type":"Manufacturing & Wholesale Goods"
        }
    ],
    "sg:phone":"+1 941 745 9297",
    "sg:postcode":"34209",
    "sg:province":"FL",
    "wof:name":"OXY-Med Pulmonary HM Care Svc",
    "wof:placetype":"venue"
},
  "geometry": {"coordinates":[-82.609297,27.495947],"type":"Point"}
}