{
  "type": "Feature",
  "properties": {
    "addr:full":"2200 Bee Ridge Rd Sarasota FL 34239",
    "addr:housenumber":"2200",
    "addr:postcode":"34239",
    "addr:street":"Bee Ridge Rd",
    "iso:country":"US",
    "sg:address":"2200 Bee Ridge Rd",
    "sg:city":"Sarasota",
    "sg:classifiers":[
        {
            "category":"Autos & Motor Vehicles",
            "subcategory":"Automobile Sales",
            "type":"Retail Goods"
        }
    ],
    "sg:phone":"+1 941 922 1571",
    "sg:postcode":"34239",
    "sg:province":"FL",
    "sg:tags":[
        "car",
        "dealer"
    ],
    "wof:name":"Coast Cadillac Co",
    "wof:placetype":"venue"
},
  "geometry": {"coordinates":[-82.526903,27.298768],"type":"Point"}
}