{
  "type": "Feature",
  "properties": {
    "addr:full":"8603 S Dixie Hwy Miami FL 33143",
    "addr:housenumber":"8603",
    "addr:postcode":"33143",
    "addr:street":"S Dixie Hwy",
    "iso:country":"US",
    "sg:address":"8603 S Dixie Hwy",
    "sg:city":"Miami",
    "sg:classifiers":[
        {
            "category":"Banks & Credit Unions",
            "subcategory":"Financial Services",
            "type":"Services"
        }
    ],
    "sg:phone":"+1 305 667 0111",
    "sg:postcode":"33143",
    "sg:province":"FL",
    "sg:tags":[
        "broker",
        "mortgage"
    ],
    "wof:name":"First Choice Mortgage of South Florida",
    "wof:placetype":"venue"
},
  "geometry": {"coordinates":[-80.305892,25.690566],"type":"Point"}
}