{
  "type": "Feature",
  "properties": {
    "iso:country":"US",
    "sg:address":"5231 Cornell St",
    "sg:city":"Lakeland",
    "sg:classifiers":[
        {
            "category":"Building & Trades",
            "subcategory":"Construction",
            "type":"Services"
        }
    ],
    "sg:phone":"+1 863 853 9808",
    "sg:postcode":"33810",
    "sg:province":"FL",
    "sg:tags":[
        "maintenance",
        "contractor"
    ],
    "wof:name":"Certified Maintenance & Mech",
    "wof:placetype":"venue"
},
  "geometry": {"coordinates":[-81.974901,28.107987],"type":"Point"}
}