{
  "type": "Feature",
  "properties": {
    "iso:country":"US",
    "sg:address":"5468 Williamsburg Dr",
    "sg:city":"Punta Gorda",
    "sg:classifiers":[
        {
            "category":"Manufacturing",
            "subcategory":"Signs",
            "type":"Manufacturing & Wholesale Goods"
        }
    ],
    "sg:phone":"+1 941 637 1114",
    "sg:postcode":"33982",
    "sg:province":"FL",
    "sg:tags":[
        "body",
        "auto",
        "specialty",
        "mfg"
    ],
    "wof:name":"Sign Zone",
    "wof:placetype":"venue"
},
  "geometry": {"coordinates":[-81.99857799999999,26.95324],"type":"Point"}
}