{
  "type": "Feature",
  "properties": {
    "iso:country":"US",
    "sg:address":"530 Gus Hipp Blvd",
    "sg:city":"Rockledge",
    "sg:classifiers":[
        {
            "category":"Wholesale",
            "subcategory":"Electrical",
            "type":"Manufacturing & Wholesale Goods"
        }
    ],
    "sg:phone":"+1 321 639 2161",
    "sg:postcode":"32955",
    "sg:province":"FL",
    "sg:tags":[
        "equipment"
    ],
    "wof:name":"City Electric Supply Co",
    "wof:placetype":"venue"
},
  "geometry": {"coordinates":[-80.719669,28.304174],"type":"Point"}
}