{
  "type": "Feature",
  "properties": {
    "iso:country":"US",
    "sg:address":"1150 Campo Sano Ave Ste 420",
    "sg:city":"Miami",
    "sg:classifiers":[
        {
            "category":"Health Services",
            "subcategory":"Doctor",
            "type":"Services"
        },
        {
            "category":"Personal",
            "subcategory":"Beauty Salon",
            "type":"Services"
        },
        {
            "category":"Personal",
            "subcategory":"Hair Removal",
            "type":"Services"
        },
        {
            "category":"Personal",
            "subcategory":"Skin Care",
            "type":"Services"
        }
    ],
    "sg:phone":"+1 305 669 2799",
    "sg:postcode":"33146",
    "sg:province":"FL",
    "sg:tags":[
        "physician",
        "surgeons",
        "cosmetic",
        "dermatologist",
        "dermatology",
        "surgery",
        "surgeon"
    ],
    "sg:website":"http://www.cosmeticdermatologyofmiami.com",
    "wof:name":"Perez-Quintairos Ileana MD",
    "wof:placetype":"venue"
},
  "geometry": {"coordinates":[-80.274494,25.724662],"type":"Point"}
}