{
  "type": "Feature",
  "properties": {
    "addr:full":"900 South Miami Ave #121 Miami FL 33130",
    "addr:housenumber":"900",
    "addr:postcode":"33130",
    "addr:street":"South Miami Ave # 121",
    "iso:country":"US",
    "sg:address":"900 South Miami Ave #121",
    "sg:city":"Miami",
    "sg:classifiers":[
        {
            "category":"Shopping",
            "subcategory":"Clothing, Apparel, & Fashions",
            "type":"Retail Goods"
        }
    ],
    "sg:phone":"+1 305 415 9600",
    "sg:postcode":"33130",
    "sg:province":"FL",
    "sg:tags":[
        "clothing",
        "women's"
    ],
    "sg:website":"www.grouplx.com/",
    "wof:name":"Studio LX",
    "wof:placetype":"venue"
},
  "geometry": {"coordinates":[-80.193516,25.765224],"type":"Point"}
}