{
  "type": "Feature",
  "properties": {
    "iso:country":"US",
    "sg:address":"23133 Sandalfoot Plaza Dr",
    "sg:city":"Boca Raton",
    "sg:classifiers":[
        {
            "category":"Insurance",
            "subcategory":"Insurance Agent",
            "type":"Services"
        }
    ],
    "sg:phone":"+1 561 488 3333",
    "sg:postcode":"33428",
    "sg:province":"FL",
    "sg:website":"www.bocabay.com",
    "wof:name":"Boca Bay Insurance",
    "wof:placetype":"venue"
},
  "geometry": {"coordinates":[-80.20182200000001,26.332511],"type":"Point"}
}