{
  "type": "Feature",
  "properties": {
    "iso:country":"US",
    "sg:address":"106 SW Grand St",
    "sg:city":"Greenville",
    "sg:classifiers":[
        {
            "category":"Shopping",
            "subcategory":"Pharmacy",
            "type":"Retail Goods"
        }
    ],
    "sg:phone":"+1 850 948 3011",
    "sg:postcode":"32331",
    "sg:province":"FL",
    "sg:website":"http://www.jacksonsdrugstore.com",
    "wof:name":"Jackson Drug Store Greenville",
    "wof:placetype":"venue"
},
  "geometry": {"coordinates":[-83.611844,30.471211],"type":"Point"}
}