{
  "type": "Feature",
  "properties": {
    "iso:country":"US",
    "sg:address":"236 Grand Ave",
    "sg:city":"Coral Gables",
    "sg:classifiers":[
        {
            "category":"Social Services",
            "type":"Services"
        }
    ],
    "sg:phone":"+1 305 569 9926",
    "sg:postcode":"33133",
    "sg:province":"FL",
    "sg:tags":[
        "youth",
        "organization",
        "center"
    ],
    "wof:name":"Boys and Girls Clubs of Miami",
    "wof:placetype":"venue"
},
  "geometry": {"coordinates":[-80.259342,25.727501],"type":"Point"}
}