{
  "type": "Feature",
  "properties": {
    "addr:full":"1123 Crestwood Blvd Lake Worth FL 33460",
    "addr:housenumber":"1123",
    "addr:postcode":"33460",
    "addr:street":"Crestwood Blvd",
    "iso:country":"US",
    "sg:address":"1123 Crestwood Blvd",
    "sg:city":"Lake Worth",
    "sg:classifiers":[
        {
            "category":"Professional",
            "subcategory":"Accounting & Tax Preparation",
            "type":"Services"
        }
    ],
    "sg:phone":"+1 561 721 0028",
    "sg:postcode":"33460",
    "sg:province":"FL",
    "wof:name":"R B W & Associates",
    "wof:placetype":"venue"
},
  "geometry": {"coordinates":[-80.05767899999999,26.631895],"type":"Point"}
}