{
  "type": "Feature",
  "properties": {
    "addr:full":"1599 NW 43rd Ave Lauderhill FL 33313",
    "addr:housenumber":"1599",
    "addr:postcode":"33313",
    "addr:street":"Nw 43Rd Ave",
    "iso:country":"US",
    "sg:address":"1599 NW 43rd Ave",
    "sg:city":"Lauderhill",
    "sg:classifiers":[
        {
            "category":"Shopping",
            "subcategory":"Computers & Home Electronics",
            "type":"Retail Goods"
        }
    ],
    "sg:phone":"+1 954 484 1266",
    "sg:postcode":"33313",
    "sg:province":"FL",
    "sg:tags":[
        "equipment",
        "dealer"
    ],
    "wof:name":"Computer Guy TV",
    "wof:placetype":"venue"
},
  "geometry": {"coordinates":[-80.207016,26.144962],"type":"Point"}
}