{
  "type": "Feature",
  "properties": {
    "iso:country":"US",
    "sg:address":"14141 SW 240th St",
    "sg:city":"Homestead",
    "sg:classifiers":[
        {
            "category":"Building & Trades",
            "subcategory":"Landscaping Services",
            "type":"Services"
        }
    ],
    "sg:phone":"+1 305 258 1028",
    "sg:postcode":"33032",
    "sg:province":"FL",
    "wof:name":"Myers & Son Backhoe",
    "wof:placetype":"venue"
},
  "geometry": {"coordinates":[-80.419719,25.543936],"type":"Point"}
}