{
  "type": "Feature",
  "properties": {
    "addr:full":"12836 Key Lime Blvd West Palm Beach FL 33412",
    "addr:housenumber":"12836",
    "addr:postcode":"33412",
    "addr:street":"Key Lime Blvd",
    "iso:country":"US",
    "sg:address":"12836 Key Lime Blvd",
    "sg:city":"West Palm Beach",
    "sg:classifiers":[
        {
            "category":"Retail",
            "subcategory":"Portrait Studio",
            "type":"Services"
        }
    ],
    "sg:phone":"+1 561 793 7239",
    "sg:postcode":"33412",
    "sg:province":"FL",
    "sg:tags":[
        "photographer"
    ],
    "wof:name":"Tom's Back Yard",
    "wof:placetype":"venue"
},
  "geometry": {"coordinates":[-80.24294399999999,26.787192],"type":"Point"}
}