{
  "type": "Feature",
  "properties": {
    "iso:country":"US",
    "sg:address":"15337 Parete Rd",
    "sg:city":"Jacksonville",
    "sg:classifiers":[
        {
            "category":"Building & Trades",
            "subcategory":"Landscaping Services",
            "type":"Services"
        }
    ],
    "sg:phone":"+1 904 764 8583",
    "sg:postcode":"32218",
    "sg:province":"FL",
    "wof:name":"Glenda Miller & Sons",
    "wof:placetype":"venue"
},
  "geometry": {"coordinates":[-81.732512,30.515066],"type":"Point"}
}