{
  "type": "Feature",
  "properties": {
    "addr:full":"1461 SW 159th Ave Hollywood FL 33027",
    "addr:housenumber":"1461",
    "addr:postcode":"33027",
    "addr:street":"Sw 159Th Ave",
    "iso:country":"US",
    "sg:address":"1461 SW 159th Ave",
    "sg:city":"Hollywood",
    "sg:classifiers":[
        {
            "category":"Restaurant",
            "type":"Food & Drink"
        }
    ],
    "sg:phone":"+1 954 437 8246",
    "sg:postcode":"33027",
    "sg:province":"FL",
    "sg:tags":[
        "eating"
    ],
    "wof:name":"Mama LLC",
    "wof:placetype":"venue"
},
  "geometry": {"coordinates":[-80.356993,25.996656],"type":"Point"}
}