{
  "type": "Feature",
  "properties": {
    "iso:country":"US",
    "sg:address":"4027 Bessent Rd",
    "sg:city":"Jacksonville",
    "sg:classifiers":[
        {
            "category":"School Buses",
            "type":"Transportation"
        }
    ],
    "sg:phone":"+1 904 764 1160",
    "sg:postcode":"32218",
    "sg:province":"FL",
    "wof:name":"C W Harris Bus Company",
    "wof:placetype":"venue"
},
  "geometry": {"coordinates":[-81.713841,30.423789],"type":"Point"}
}