{
  "type": "Feature",
  "properties": {
    "iso:country":"US",
    "sg:address":"7440 Kalani St",
    "sg:city":"Orlando",
    "sg:classifiers":[
        {
            "category":"Building & Trades",
            "subcategory":"Landscaping Services",
            "type":"Services"
        },
        {
            "category":"Farming",
            "subcategory":"Nursery",
            "type":"Manufacturing & Wholesale Goods"
        }
    ],
    "sg:phone":"+1 407 247 6081",
    "sg:postcode":"32822",
    "sg:province":"FL",
    "sg:tags":[
        "arborist",
        "tree",
        "nurseries-plants"
    ],
    "wof:name":"Williams Tree Service",
    "wof:placetype":"venue"
},
  "geometry": {"coordinates":[-81.288078,28.490061],"type":"Point"}
}