{
  "type": "Feature",
  "properties": {
    "iso:country":"US",
    "sg:address":"11910 Race Track Rd",
    "sg:city":"Tampa",
    "sg:classifiers":[
        {
            "category":"Professional",
            "subcategory":"Business Services",
            "type":"Services"
        }
    ],
    "sg:phone":"+1 813 243 5415",
    "sg:postcode":"33626",
    "sg:province":"FL",
    "wof:name":"I T Resources",
    "wof:placetype":"venue"
},
  "geometry": {"coordinates":[-82.64471399999999,28.060149],"type":"Point"}
}