{
  "type": "Feature",
  "properties": {
    "iso:country":"US",
    "sg:address":"1623 Patton Ave",
    "sg:city":"Apopka",
    "sg:classifiers":[
        {
            "category":"Building & Trades",
            "subcategory":"Construction",
            "type":"Services"
        }
    ],
    "sg:phone":"+1 407 886 4267",
    "sg:postcode":"32703",
    "sg:province":"FL",
    "sg:tags":[
        "home",
        "contractor",
        "general",
        "family",
        "new"
    ],
    "wof:name":"Prominent Construction Company",
    "wof:placetype":"venue"
},
  "geometry": {"coordinates":[-81.46230799999999,28.654753],"type":"Point"}
}