{
  "type": "Feature",
  "properties": {
    "iso:country":"US",
    "sg:address":"1917 Taft St",
    "sg:city":"Hollywood",
    "sg:classifiers":[
        {
            "category":"Real Estate",
            "subcategory":"Real Estate Operator",
            "type":"Services"
        }
    ],
    "sg:phone":"+1 954 922 2572",
    "sg:postcode":"33020",
    "sg:province":"FL",
    "sg:tags":[
        "apartment"
    ],
    "wof:name":"Chaloult Apartments",
    "wof:placetype":"venue"
},
  "geometry": {"coordinates":[-80.147063,26.026258],"type":"Point"}
}