{
  "type": "Feature",
  "properties": {
    "iso:country":"US",
    "sg:address":"5725 Lakeland Highlands Rd",
    "sg:city":"Lakeland",
    "sg:classifiers":[
        {
            "category":"Manufacturing",
            "subcategory":"Buildings",
            "type":"Manufacturing & Wholesale Goods"
        },
        {
            "category":"Building & Trades",
            "subcategory":"Construction",
            "type":"Services"
        }
    ],
    "sg:phone":"+1 863 619 8448",
    "sg:postcode":"33813",
    "sg:province":"FL",
    "sg:tags":[
        "home",
        "builder",
        "contractor"
    ],
    "wof:name":"Cap Homes",
    "wof:placetype":"venue"
},
  "geometry": {"coordinates":[-81.923705,27.961195],"type":"Point"}
}