{
  "type": "Feature",
  "properties": {
    "addr:full":"14221 SW 286th St Homestead FL 33033",
    "addr:housenumber":"14221",
    "addr:postcode":"33033",
    "addr:street":"Sw 286Th St",
    "iso:country":"US",
    "sg:address":"14221 SW 286th St",
    "sg:city":"Homestead",
    "sg:classifiers":[
        {
            "category":"Personal",
            "subcategory":"Beauty Salon",
            "type":"Services"
        }
    ],
    "sg:phone":"+1 786 243 3039",
    "sg:postcode":"33033",
    "sg:province":"FL",
    "sg:tags":[
        "manicuring"
    ],
    "wof:name":"Sophia's Nail Shop",
    "wof:placetype":"venue"
},
  "geometry": {"coordinates":[-80.423706,25.501112],"type":"Point"}
}