{
  "type": "Feature",
  "properties": {
    "iso:country":"US",
    "sg:address":"6955 NW 52nd St",
    "sg:city":"Miami",
    "sg:classifiers":[
        {
            "category":"Professional",
            "subcategory":"Management & Consulting",
            "type":"Services"
        }
    ],
    "sg:phone":"+1 305 406 0113",
    "sg:postcode":"33166",
    "sg:province":"FL",
    "sg:tags":[
        "logistics"
    ],
    "wof:name":"Logistic Cargo Ctr",
    "wof:placetype":"venue"
},
  "geometry": {"coordinates":[-80.310452,25.820772],"type":"Point"}
}