{
  "type": "Feature",
  "properties": {
    "addr:full":"50 Squanto Pl Palm Coast FL 32164",
    "addr:housenumber":"50",
    "addr:postcode":"32164",
    "addr:street":"Squanto Pl",
    "iso:country":"US",
    "sg:address":"50 Squanto Pl",
    "sg:city":"Palm Coast",
    "sg:classifiers":[
        {
            "category":"Health Services",
            "subcategory":"Doctor",
            "type":"Services"
        }
    ],
    "sg:phone":"+1 386 246 6289",
    "sg:postcode":"32164",
    "sg:province":"FL",
    "sg:tags":[
        "physician",
        "surgeon"
    ],
    "wof:name":"Palm Coast Eye Physicians",
    "wof:placetype":"venue"
},
  "geometry": {"coordinates":[-81.206796,29.418325],"type":"Point"}
}