{
  "type": "Feature",
  "properties": {
    "addr:full":"1917 W Flagler St Miami FL 33135",
    "addr:housenumber":"1917",
    "addr:postcode":"33135",
    "addr:street":"W Flagler St",
    "iso:country":"US",
    "sg:address":"1917 W Flagler St",
    "sg:city":"Miami",
    "sg:classifiers":[
        {
            "category":"Retail",
            "subcategory":"Auto Repair",
            "type":"Services"
        }
    ],
    "sg:phone":"+1 305 649 3292",
    "sg:postcode":"33135",
    "sg:province":"FL",
    "sg:tags":[
        "body",
        "shop"
    ],
    "wof:name":"Ok Auto Glass",
    "wof:placetype":"venue"
},
  "geometry": {"coordinates":[-80.227097,25.7726],"type":"Point"}
}