{
  "type": "Feature",
  "properties": {
    "iso:country":"US",
    "sg:address":"1100 Crystal Bowl Cir",
    "sg:city":"Casselberry",
    "sg:classifiers":[
        {
            "category":"Manufacturing",
            "subcategory":"Building Materials",
            "type":"Manufacturing & Wholesale Goods"
        }
    ],
    "sg:phone":"+1 407 699 6994",
    "sg:postcode":"32707",
    "sg:province":"FL",
    "sg:tags":[
        "mfg"
    ],
    "wof:name":"Guglielmello Investments Inc",
    "wof:placetype":"venue"
},
  "geometry": {"coordinates":[-81.313982,28.661984],"type":"Point"}
}