{
  "type": "Feature",
  "properties": {
    "addr:full":"12725 SW 122nd Ave Miami FL 33155",
    "addr:housenumber":"12725",
    "addr:postcode":"33155",
    "addr:street":"Sw 122Nd Ave",
    "iso:country":"US",
    "sg:address":"12725 SW 122nd Ave",
    "sg:city":"Miami",
    "sg:classifiers":[
        {
            "category":"Arts & Performance",
            "subcategory":"Music",
            "type":"Entertainment"
        }
    ],
    "sg:phone":"+1 305 232 0987",
    "sg:postcode":"33155",
    "sg:province":"FL",
    "sg:tags":[
        "dj"
    ],
    "sg:website":"www.visiondjs.com",
    "wof:name":"Vision DJs",
    "wof:placetype":"venue"
},
  "geometry": {"coordinates":[-80.389894,25.649868],"type":"Point"}
}