{
  "type": "Feature",
  "properties": {
    "iso:country":"US",
    "sg:address":"330 Kon Tiki Dr",
    "sg:city":"Naples",
    "sg:classifiers":[
        {
            "category":"Real Estate",
            "subcategory":"Real Estate Operator",
            "type":"Services"
        }
    ],
    "sg:phone":"+1 239 389 0643",
    "sg:postcode":"34113",
    "sg:province":"FL",
    "sg:tags":[
        "building",
        "apartment"
    ],
    "wof:name":"Tarpon Vlg Apartments Condo As",
    "wof:placetype":"venue"
},
  "geometry": {"coordinates":[-81.722803,25.984652],"type":"Point"}
}