{
  "type": "Feature",
  "properties": {
    "iso:country":"US",
    "sg:address":"6491 SE Federal Hwy",
    "sg:city":"Stuart",
    "sg:classifiers":[
        {
            "category":"Retail",
            "subcategory":"Auto Rental",
            "type":"Services"
        }
    ],
    "sg:phone":"+1 772 220 4911",
    "sg:postcode":"34997",
    "sg:province":"FL",
    "sg:tags":[
        "passenger",
        "car"
    ],
    "wof:name":"Rent-A-Wreck",
    "wof:placetype":"venue"
},
  "geometry": {"coordinates":[-80.194233,27.12607],"type":"Point"}
}