{
  "type": "Feature",
  "properties": {
    "iso:country":"US",
    "sg:address":"1606 NW 84th Ave",
    "sg:city":"Doral",
    "sg:classifiers":[
        {
            "category":"Wholesale",
            "subcategory":"Computers",
            "type":"Manufacturing & Wholesale Goods"
        }
    ],
    "sg:phone":"+1 305 599 6810",
    "sg:postcode":"33126",
    "sg:province":"FL",
    "wof:name":"Qbex Electronics Corp",
    "wof:placetype":"venue"
},
  "geometry": {"coordinates":[-80.332466,25.788137],"type":"Point"}
}