{
  "type": "Feature",
  "properties": {
    "addr:full":"3054 Beach Blvd S Gulfport FL 33707",
    "addr:housenumber":"3054",
    "addr:postcode":"33707",
    "addr:street":"Beach Blvd S",
    "iso:country":"US",
    "sg:address":"3054 Beach Blvd S",
    "sg:city":"Gulfport",
    "sg:classifiers":[
        {
            "category":"Restaurant",
            "type":"Food & Drink"
        }
    ],
    "sg:phone":"+1 727 323 3533",
    "sg:postcode":"33707",
    "sg:province":"FL",
    "sg:tags":[
        "delicatessen"
    ],
    "wof:name":"Leaky Tiki Hut",
    "wof:placetype":"venue"
},
  "geometry": {"coordinates":[-82.707741,27.738933],"type":"Point"}
}