{
  "type": "Feature",
  "properties": {
    "addr:full":"11540 N Kayak Pt Inglis FL 34449",
    "addr:housenumber":"11540",
    "addr:postcode":"34449",
    "addr:street":"N Kayak Pt",
    "iso:country":"US",
    "sg:address":"11540 N Kayak Pt",
    "sg:city":"Inglis",
    "sg:classifiers":[
        {
            "category":"Real Estate",
            "subcategory":"Developer",
            "type":"Services"
        }
    ],
    "sg:phone":"+1 352 447 3067",
    "sg:postcode":"34449",
    "sg:province":"FL",
    "wof:name":"Oak Forest Inc",
    "wof:placetype":"venue"
},
  "geometry": {"coordinates":[-82.710775,29.030425],"type":"Point"}
}