{
  "type": "Feature",
  "properties": {
    "iso:country":"US",
    "sg:address":"2241 Lake Vilma Dr",
    "sg:city":"Orlando",
    "sg:classifiers":[
        {
            "category":"Professional",
            "subcategory":"Management & Consulting",
            "type":"Services"
        }
    ],
    "sg:phone":"+1 407 292 2813",
    "sg:postcode":"32835",
    "sg:province":"FL",
    "sg:tags":[
        "information",
        "construction",
        "system"
    ],
    "wof:name":"Tri-M Associates Consulting",
    "wof:placetype":"venue"
},
  "geometry": {"coordinates":[-81.49442000000001,28.517218],"type":"Point"}
}