{
  "type": "Feature",
  "properties": {
    "addr:full":"31001 Cortez Blvd Brooksville FL 34602",
    "addr:housenumber":"31001",
    "addr:postcode":"34602",
    "addr:street":"Cortez Blvd",
    "iso:country":"US",
    "sg:address":"31001 Cortez Blvd",
    "sg:city":"Brooksville",
    "sg:classifiers":[
        {
            "category":"Autos & Motor Vehicles",
            "subcategory":"Fuel & Gas Station",
            "type":"Retail Goods"
        }
    ],
    "sg:phone":"+1 352 544 5535",
    "sg:postcode":"34602",
    "sg:province":"FL",
    "sg:tags":[
        "oil"
    ],
    "wof:name":"M & M Marketing Amoco",
    "wof:placetype":"venue"
},
  "geometry": {"coordinates":[-82.233699,28.52313],"type":"Point"}
}