{
  "type": "Feature",
  "properties": {
    "addr:full":"1010 Bunnell Rd Altamonte Springs FL 32714",
    "addr:housenumber":"1010",
    "addr:postcode":"32714",
    "addr:street":"Bunnell Rd",
    "iso:country":"US",
    "sg:address":"1010 Bunnell Rd",
    "sg:city":"Altamonte Springs",
    "sg:classifiers":[
        {
            "category":"Home & Garden",
            "subcategory":"Building Materials",
            "type":"Retail Goods"
        }
    ],
    "sg:phone":"+1 407 788 7419",
    "sg:postcode":"32714",
    "sg:province":"FL",
    "wof:name":"Screen Doctor of Central Fla",
    "wof:placetype":"venue"
},
  "geometry": {"coordinates":[-81.42357,28.657857],"type":"Point"}
}