{
  "type": "Feature",
  "properties": {
    "addr:full":"18515 NE 18th Ave Miami FL 33179",
    "addr:housenumber":"18515",
    "addr:postcode":"33179",
    "addr:street":"Ne 18Th Ave",
    "iso:country":"US",
    "sg:address":"18515 NE 18th Ave",
    "sg:city":"Miami",
    "sg:classifiers":[
        {
            "category":"Deli",
            "type":"Food & Drink"
        }
    ],
    "sg:phone":"+1 305 830 3354",
    "sg:postcode":"33179",
    "sg:province":"FL",
    "sg:tags":[
        "delicatessen"
    ],
    "wof:name":"Skylake Deli",
    "wof:placetype":"venue"
},
  "geometry": {"coordinates":[-80.165083,25.946095],"type":"Point"}
}