{
  "type": "Feature",
  "properties": {
    "addr:full":"7344 SW 48th St Ste 203 Miami FL 33155",
    "addr:housenumber":"7344",
    "addr:postcode":"33155",
    "addr:street":"Sw 48Th St Ste 203",
    "iso:country":"US",
    "sg:address":"7344 SW 48th St Ste 203",
    "sg:city":"Miami",
    "sg:classifiers":[
        {
            "category":"Professional",
            "subcategory":"Lawyer & Legal Services",
            "type":"Services"
        }
    ],
    "sg:phone":"+1 305 667 5919",
    "sg:postcode":"33155",
    "sg:province":"FL",
    "wof:name":"Davis Jessica PA",
    "wof:placetype":"venue"
},
  "geometry": {"coordinates":[-80.313283,25.725387],"type":"Point"}
}