{
  "type": "Feature",
  "properties": {
    "iso:country":"US",
    "sg:address":"9019 Biscayne Blvd",
    "sg:city":"Miami Shores",
    "sg:classifiers":[
        {
            "category":"Insurance",
            "subcategory":"Insurance Agent",
            "type":"Services"
        }
    ],
    "sg:phone":"+1 305 751 0330",
    "sg:postcode":"33138",
    "sg:province":"FL",
    "wof:name":"Express TAX",
    "wof:placetype":"venue"
},
  "geometry": {"coordinates":[-80.183378,25.858708],"type":"Point"}
}