{
  "type": "Feature",
  "properties": {
    "addr:full":"6524 Swissco Dr Orlando FL 32822",
    "addr:housenumber":"6524",
    "addr:postcode":"32822",
    "addr:street":"Swissco Dr",
    "iso:country":"US",
    "sg:address":"6524 Swissco Dr",
    "sg:city":"Orlando",
    "sg:classifiers":[
        {
            "category":"Building & Trades",
            "subcategory":"Construction",
            "type":"Services"
        }
    ],
    "sg:phone":"+1 407 582 0127",
    "sg:postcode":"32822",
    "sg:province":"FL",
    "sg:tags":[
        "hanging",
        "contractor"
    ],
    "wof:name":"Masster Decorating",
    "wof:placetype":"venue"
},
  "geometry": {"coordinates":[-81.30019,28.467467],"type":"Point"}
}