{
  "type": "Feature",
  "properties": {
    "iso:country":"US",
    "sg:address":"606 W Madison St",
    "sg:city":"Starke",
    "sg:classifiers":[
        {
            "category":"Banks & Credit Unions",
            "subcategory":"Bank",
            "type":"Services"
        }
    ],
    "sg:phone":"+1 904 964 9696",
    "sg:postcode":"32091",
    "sg:province":"FL",
    "sg:tags":[
        "national",
        "commercial"
    ],
    "sg:website":"www.bankmercantile.com",
    "wof:name":"Mercantile Bank",
    "wof:placetype":"venue"
},
  "geometry": {"coordinates":[-82.116246,29.944682],"type":"Point"}
}