{
  "type": "Feature",
  "properties": {
    "iso:country":"US",
    "sg:address":"3120 Purple Martin Ln",
    "sg:city":"Indialantic",
    "sg:classifiers":[
        {
            "category":"Shopping",
            "subcategory":"Catalog Store",
            "type":"Retail Goods"
        }
    ],
    "sg:phone":"+1 321 773 4380",
    "sg:postcode":"32903",
    "sg:province":"FL",
    "sg:tags":[
        "house",
        "mail"
    ],
    "wof:name":"B & B Sales Force",
    "wof:placetype":"venue"
},
  "geometry": {"coordinates":[-80.584081,28.134152],"type":"Point"}
}