{
  "type": "Feature",
  "properties": {
    "addr:full":"1633 Acme St Orlando FL 32805",
    "addr:housenumber":"1633",
    "addr:postcode":"32805",
    "addr:street":"Acme St",
    "iso:country":"US",
    "sg:address":"1633 Acme St",
    "sg:city":"Orlando",
    "sg:classifiers":[
        {
            "category":"Organizations",
            "subcategory":"Labor Organization",
            "type":"Services"
        }
    ],
    "sg:phone":"+1 407 841 2065",
    "sg:postcode":"32805",
    "sg:province":"FL",
    "wof:name":"International Association",
    "wof:placetype":"venue"
},
  "geometry": {"coordinates":[-81.404464,28.527926],"type":"Point"}
}