{
  "type": "Feature",
  "properties": {
    "addr:full":"4002 SE 1st Ct Cape Coral FL 33904",
    "addr:housenumber":"4002",
    "addr:postcode":"33904",
    "addr:street":"Se 1St Ct",
    "iso:country":"US",
    "sg:address":"4002 SE 1st Ct",
    "sg:city":"Cape Coral",
    "sg:classifiers":[
        {
            "category":"Building & Trades",
            "subcategory":"Construction",
            "type":"Services"
        }
    ],
    "sg:phone":"+1 239 542 5807",
    "sg:postcode":"33904",
    "sg:province":"FL",
    "sg:tags":[
        "sewer",
        "contractor"
    ],
    "wof:name":"Mainline USA",
    "wof:placetype":"venue"
},
  "geometry": {"coordinates":[-81.969582,26.574294],"type":"Point"}
}