{
  "type": "Feature",
  "properties": {
    "iso:country":"US",
    "sg:address":"1921 Waldemere St",
    "sg:city":"Sarasota",
    "sg:classifiers":[
        {
            "category":"Health Services",
            "subcategory":"Doctor",
            "type":"Services"
        }
    ],
    "sg:phone":"+1 941 917 8565",
    "sg:postcode":"34239",
    "sg:province":"FL",
    "sg:tags":[
        "physician",
        "surgeon",
        "medical"
    ],
    "wof:name":"Michael S Finazzo MD",
    "wof:placetype":"venue"
},
  "geometry": {"coordinates":[-82.530832,27.319241],"type":"Point"}
}