{
  "type": "Feature",
  "properties": {
    "addr:full":"320 N Magnolia Ave Orlando FL 32801",
    "addr:housenumber":"320",
    "addr:postcode":"32801",
    "addr:street":"N Magnolia Ave",
    "iso:country":"US",
    "sg:address":"320 N Magnolia Ave",
    "sg:city":"Orlando",
    "sg:classifiers":[
        {
            "category":"Professional",
            "subcategory":"Lawyer & Legal Services",
            "type":"Services"
        }
    ],
    "sg:phone":"+1 407 648 7499",
    "sg:postcode":"32801",
    "sg:province":"FL",
    "wof:name":"Crowell Patrick C",
    "wof:placetype":"venue"
},
  "geometry": {"coordinates":[-81.37759699999999,28.546278],"type":"Point"}
}