{
  "type": "Feature",
  "properties": {
    "addr:full":"1465 Bayshore Dr Cocoa Beach FL 32931",
    "addr:housenumber":"1465",
    "addr:postcode":"32931",
    "addr:street":"Bayshore Dr",
    "iso:country":"US",
    "sg:address":"1465 Bayshore Dr",
    "sg:city":"Cocoa Beach",
    "sg:classifiers":[
        {
            "category":"Building & Trades",
            "subcategory":"Landscaping Services",
            "type":"Services"
        }
    ],
    "sg:phone":"+1 321 783 3837",
    "sg:postcode":"32931",
    "sg:province":"FL",
    "sg:tags":[
        "lawn",
        "garden"
    ],
    "wof:name":"Coastal Lawn & Tree Service",
    "wof:placetype":"venue"
},
  "geometry": {"coordinates":[-80.610266,28.292437],"type":"Point"}
}