{
  "type": "Feature",
  "properties": {
    "iso:country":"US",
    "sg:address":"295 W 23rd St",
    "sg:city":"Hialeah",
    "sg:classifiers":[
        {
            "category":"Manufacturing",
            "subcategory":"Metals",
            "type":"Manufacturing & Wholesale Goods"
        }
    ],
    "sg:phone":"+1 305 885 3493",
    "sg:postcode":"33010",
    "sg:province":"FL",
    "sg:tags":[
        "manufacture",
        "hardware",
        "marine"
    ],
    "wof:name":"Marine Manufacturing Inc",
    "wof:placetype":"venue"
},
  "geometry": {"coordinates":[-80.286376,25.842792],"type":"Point"}
}