{
  "type": "Feature",
  "properties": {
    "addr:full":"8055 SW 89th Ct Miami FL 33173",
    "addr:housenumber":"8055",
    "addr:postcode":"33173",
    "addr:street":"Sw 89Th Ct",
    "iso:country":"US",
    "sg:address":"8055 SW 89th Ct",
    "sg:city":"Miami",
    "sg:classifiers":[
        {
            "category":"Autos & Motor Vehicles",
            "subcategory":"Automobile Sales",
            "type":"Retail Goods"
        }
    ],
    "sg:phone":"+1 305 986 9665",
    "sg:postcode":"33173",
    "sg:province":"FL",
    "sg:tags":[
        "used",
        "o",
        "trucking",
        "truck",
        "tractor",
        "trailer"
    ],
    "wof:name":"Mega Trucks & Equipment Inc",
    "wof:placetype":"venue"
},
  "geometry": {"coordinates":[-80.339156,25.6938],"type":"Point"}
}