{
  "type": "Feature",
  "properties": {
    "addr:full":"11112 Taeda Dr Orlando FL 32832",
    "addr:housenumber":"11112",
    "addr:postcode":"32832",
    "addr:street":"Taeda Dr",
    "iso:country":"US",
    "sg:address":"11112 Taeda Dr",
    "sg:city":"Orlando",
    "sg:classifiers":[
        {
            "category":"Organizations",
            "subcategory":"Non-profit Organization",
            "type":"Services"
        }
    ],
    "sg:phone":"+1 407 207 5545",
    "sg:postcode":"32832",
    "sg:province":"FL",
    "sg:website":"www.nacd.org",
    "wof:name":"National Academy For Child Dev",
    "wof:placetype":"venue"
},
  "geometry": {"coordinates":[-81.211309,28.413732],"type":"Point"}
}