{
  "type": "Feature",
  "properties": {
    "addr:full":"1813 J and C Blvd Naples FL 34109",
    "addr:housenumber":"1813;and",
    "addr:postcode":"34109",
    "addr:street":"C Blvd",
    "iso:country":"US",
    "sg:address":"1813 J and C Blvd",
    "sg:city":"Naples",
    "sg:classifiers":[
        {
            "category":"Professional",
            "subcategory":"Printing & Photocopies",
            "type":"Services"
        },
        {
            "category":"Manufacturing",
            "subcategory":"Printing",
            "type":"Manufacturing & Wholesale Goods"
        }
    ],
    "sg:phone":"+1 239 592 0404",
    "sg:postcode":"34109",
    "sg:province":"FL",
    "sg:tags":[
        "photocopying",
        "printer"
    ],
    "wof:name":"Colortec Digital Inc",
    "wof:placetype":"venue"
},
  "geometry": {"coordinates":[-81.77828,26.223858],"type":"Point"}
}