{
  "type": "Feature",
  "properties": {
    "addr:full":"1228 N Pinellas Ave Tarpon Springs FL 34689",
    "addr:housenumber":"1228",
    "addr:postcode":"34689",
    "addr:street":"N Pinellas Ave",
    "iso:country":"US",
    "sg:address":"1228 N Pinellas Ave",
    "sg:city":"Tarpon Springs",
    "sg:classifiers":[
        {
            "category":"Real Estate",
            "subcategory":"Real Estate Operator",
            "type":"Services"
        }
    ],
    "sg:phone":"+1 727 938 8444",
    "sg:postcode":"34689",
    "sg:province":"FL",
    "sg:tags":[
        "building",
        "parks"
    ],
    "wof:name":"Anclote River Plaza Inc",
    "wof:placetype":"venue"
},
  "geometry": {"coordinates":[-82.75677399999999,28.160226],"type":"Point"}
}