{
  "type": "Feature",
  "properties": {
    "iso:country":"US",
    "sg:address":"4205 W Atlantic Ave",
    "sg:city":"Delray Beach",
    "sg:classifiers":[
        {
            "category":"Health Services",
            "subcategory":"Chiropractor",
            "type":"Services"
        }
    ],
    "sg:phone":"+1 561 819 2225",
    "sg:postcode":"33445",
    "sg:province":"FL",
    "wof:name":"Weber Chiropractic",
    "wof:placetype":"venue"
},
  "geometry": {"coordinates":[-80.10911400000001,26.457922],"type":"Point"}
}