{
  "type": "Feature",
  "properties": {
    "addr:full":"8191 N Tamiami Trl Sarasota FL 34243",
    "addr:housenumber":"8191",
    "addr:postcode":"34243",
    "addr:street":"N Tamiami Trl",
    "iso:country":"US",
    "sg:address":"8191 N Tamiami Trl",
    "sg:city":"Sarasota",
    "sg:classifiers":[
        {
            "category":"Autos & Motor Vehicles",
            "subcategory":"Automobile Sales",
            "type":"Retail Goods"
        }
    ],
    "sg:phone":"+1 941 355 9585",
    "sg:postcode":"34243",
    "sg:province":"FL",
    "sg:tags":[
        "equipment",
        "transportation"
    ],
    "wof:name":"Flight Source International",
    "wof:placetype":"venue"
},
  "geometry": {"coordinates":[-82.560974,27.392597],"type":"Point"}
}