{
  "type": "Feature",
  "properties": {
    "iso:country":"US",
    "sg:address":"1500 Posner Blvd",
    "sg:city":"Davenport",
    "sg:classifiers":[
        {
            "category":"Shopping",
            "subcategory":"Shoes",
            "type":"Retail Goods"
        }
    ],
    "sg:phone":"+1 863 424 8972",
    "sg:postcode":"33837",
    "sg:province":"FL",
    "sg:tags":[
        "store"
    ],
    "sg:website":"www.payless.com",
    "wof:name":"Payless Shoesource #1921",
    "wof:placetype":"venue"
},
  "geometry": {"coordinates":[-81.64433200000001,28.225526],"type":"Point"}
}