{
  "type": "Feature",
  "properties": {
    "iso:country":"US",
    "sg:address":"764 Grand Parke Dr",
    "sg:city":"Jacksonville",
    "sg:classifiers":[
        {
            "category":"Restaurant",
            "type":"Food & Drink"
        }
    ],
    "sg:phone":"+1 904 230 0830",
    "sg:postcode":"32259",
    "sg:province":"FL",
    "sg:tags":[
        "eating"
    ],
    "wof:name":"Strategic Restaurant Concepts",
    "wof:placetype":"venue"
},
  "geometry": {"coordinates":[-81.614974,30.126262],"type":"Point"}
}