{
  "type": "Feature",
  "properties": {
    "iso:country":"US",
    "sg:address":"2170 Serpentine Cir S",
    "sg:city":"Saint Petersburg",
    "sg:classifiers":[
        {
            "category":"Manufacturing",
            "subcategory":"Watercraft",
            "type":"Manufacturing & Wholesale Goods"
        }
    ],
    "sg:phone":"+1 727 866 2678",
    "sg:postcode":"33712",
    "sg:province":"FL",
    "sg:tags":[
        "repair"
    ],
    "wof:name":"Bristol Yacht Service",
    "wof:placetype":"venue"
},
  "geometry": {"coordinates":[-82.662244,27.70298],"type":"Point"}
}