{
  "type": "Feature",
  "properties": {
    "addr:full":"1305 SE 14th St Cape Coral FL 33990",
    "addr:housenumber":"1305",
    "addr:postcode":"33990",
    "addr:street":"Se 14Th St",
    "iso:country":"US",
    "sg:address":"1305 SE 14th St",
    "sg:city":"Cape Coral",
    "sg:classifiers":[
        {
            "category":"Banks & Credit Unions",
            "subcategory":"Financial Services",
            "type":"Services"
        }
    ],
    "sg:phone":"+1 239 458 7159",
    "sg:postcode":"33990",
    "sg:province":"FL",
    "sg:tags":[
        "broker",
        "mortgage"
    ],
    "wof:name":"Streamline Title Services of Alabama",
    "wof:placetype":"venue"
},
  "geometry": {"coordinates":[-81.947591,26.626687],"type":"Point"}
}