{
  "type": "Feature",
  "properties": {
    "addr:full":"103 Sanderling Dr Winter Haven FL 33881",
    "addr:housenumber":"103",
    "addr:postcode":"33881",
    "addr:street":"Sanderling Dr",
    "iso:country":"US",
    "sg:address":"103 Sanderling Dr",
    "sg:city":"Winter Haven",
    "sg:classifiers":[
        {
            "category":"Building & Trades",
            "subcategory":"Construction",
            "type":"Services"
        }
    ],
    "sg:phone":"+1 863 299 1788",
    "sg:postcode":"33881",
    "sg:province":"FL",
    "sg:tags":[
        "home",
        "builder"
    ],
    "wof:name":"Holiday Builders",
    "wof:placetype":"venue"
},
  "geometry": {"coordinates":[-81.67585200000001,28.048403],"type":"Point"}
}