{
  "type": "Feature",
  "properties": {
    "iso:country":"US",
    "sg:address":"621 SW 21st Ter",
    "sg:city":"Fort Lauderdale",
    "sg:classifiers":[
        {
            "category":"Real Estate",
            "subcategory":"Real Estate Agent",
            "type":"Services"
        }
    ],
    "sg:phone":"+1 954 587 7988",
    "sg:postcode":"33312",
    "sg:province":"FL",
    "wof:name":"Paul J Sepancy",
    "wof:placetype":"venue"
},
  "geometry": {"coordinates":[-80.170661,26.120917],"type":"Point"}
}