{
  "type": "Feature",
  "properties": {
    "addr:full":"5410 Edgewater Ct Cocoa FL 32927",
    "addr:housenumber":"5410",
    "addr:postcode":"32927",
    "addr:street":"Edgewater Ct",
    "iso:country":"US",
    "sg:address":"5410 Edgewater Ct",
    "sg:city":"Cocoa",
    "sg:classifiers":[
        {
            "category":"Personal",
            "subcategory":"Beauty Salon",
            "type":"Services"
        }
    ],
    "sg:phone":"+1 321 631 2866",
    "sg:postcode":"32927",
    "sg:province":"FL",
    "wof:name":"Helen Collura Beauty Salon",
    "wof:placetype":"venue"
},
  "geometry": {"coordinates":[-80.762843,28.460364],"type":"Point"}
}