{
  "type": "Feature",
  "properties": {
    "addr:full":"2811 Dunhill Dr Cocoa FL 32926",
    "addr:housenumber":"2811",
    "addr:postcode":"32926",
    "addr:street":"Dunhill Dr",
    "iso:country":"US",
    "sg:address":"2811 Dunhill Dr",
    "sg:city":"Cocoa",
    "sg:classifiers":[
        {
            "category":"Restaurant",
            "type":"Food & Drink"
        }
    ],
    "sg:phone":"+1 321 631 4617",
    "sg:postcode":"32926",
    "sg:province":"FL",
    "sg:tags":[
        "eating"
    ],
    "wof:name":"Dolce Gelato Inc",
    "wof:placetype":"venue"
},
  "geometry": {"coordinates":[-80.77090800000001,28.398198],"type":"Point"}
}