{
  "type": "Feature",
  "properties": {
    "addr:full":"5334 Mile Stretch Dr Holiday FL 34690",
    "addr:housenumber":"5334",
    "addr:postcode":"34690",
    "addr:street":"Mile Stretch Dr",
    "iso:country":"US",
    "sg:address":"5334 Mile Stretch Dr",
    "sg:city":"Holiday",
    "sg:classifiers":[
        {
            "category":"Retail",
            "subcategory":"Auto Repair",
            "type":"Services"
        }
    ],
    "sg:phone":"+1 727 943 0046",
    "sg:postcode":"34690",
    "sg:province":"FL",
    "sg:tags":[
        "automotive"
    ],
    "wof:name":"Cox & Wood Inc",
    "wof:placetype":"venue"
},
  "geometry": {"coordinates":[-82.727262,28.187946],"type":"Point"}
}