{
  "type": "Feature",
  "properties": {
    "iso:country":"US",
    "sg:address":"4204 N Lois Ave",
    "sg:city":"Tampa",
    "sg:classifiers":[
        {
            "category":"Shopping",
            "subcategory":"Crafts & Fabrics",
            "type":"Retail Goods"
        }
    ],
    "sg:phone":"+1 813 876 3052",
    "sg:postcode":"33614",
    "sg:province":"FL",
    "sg:tags":[
        "sewing"
    ],
    "wof:name":"All Fabric Dry Clnrs",
    "wof:placetype":"venue"
},
  "geometry": {"coordinates":[-82.513746,27.978014],"type":"Point"}
}