{
  "type": "Feature",
  "properties": {
    "iso:country":"US",
    "sg:address":"59 SW 12th Ave Ste 105",
    "sg:city":"Dania",
    "sg:classifiers":[
        {
            "category":"Autos & Motor Vehicles",
            "subcategory":"Auto Supplies",
            "type":"Retail Goods"
        }
    ],
    "sg:phone":"+1 954 239 4561",
    "sg:postcode":"33004",
    "sg:province":"FL",
    "sg:tags":[
        "automobile",
        "part",
        "engines-supplies",
        "equipment"
    ],
    "sg:website":"http://www.erwparts.com",
    "wof:name":"Fast Engine Parts",
    "wof:placetype":"venue"
},
  "geometry": {"coordinates":[-80.15186300000001,26.049559],"type":"Point"}
}