{
  "type": "Feature",
  "properties": {
    "addr:full":"3445 Sanibel-Captiva Rd Sanibel FL 33957",
    "addr:housenumber":"3445",
    "addr:postcode":"33957",
    "addr:street":"Sanibel-Captiva Rd",
    "iso:country":"US",
    "sg:address":"3445 Sanibel-Captiva Rd",
    "sg:city":"Sanibel",
    "sg:classifiers":[
        {
            "category":"Wholesale",
            "subcategory":"Electrical",
            "type":"Manufacturing & Wholesale Goods"
        }
    ],
    "sg:phone":"+1 239 472 1231",
    "sg:postcode":"33957",
    "sg:province":"FL",
    "sg:tags":[
        "alarm",
        "burglar",
        "system"
    ],
    "wof:name":"Sentry Security Systems",
    "wof:placetype":"venue"
},
  "geometry": {"coordinates":[-82.096221,26.439198],"type":"Point"}
}