{
  "type": "Feature",
  "properties": {
    "iso:country":"US",
    "sg:address":"1520 Travelers Palm Dr",
    "sg:city":"Edgewater",
    "sg:classifiers":[
        {
            "category":"Professional",
            "subcategory":"Employment Agencies",
            "type":"Services"
        }
    ],
    "sg:phone":"+1 386 427 0103",
    "sg:postcode":"32132",
    "sg:province":"FL",
    "sg:tags":[
        "opportunity"
    ],
    "wof:name":"Key Source Associates Inc",
    "wof:placetype":"venue"
},
  "geometry": {"coordinates":[-80.91626100000001,28.972809],"type":"Point"}
}