{
  "type": "Feature",
  "properties": {
    "addr:full":"5324 S John Young Pkwy Orlando FL 32839",
    "addr:housenumber":"5324",
    "addr:postcode":"32839",
    "addr:street":"S John Young Pkwy",
    "iso:country":"US",
    "sg:address":"5324 S John Young Pkwy",
    "sg:city":"Orlando",
    "sg:classifiers":[
        {
            "category":"Restaurant",
            "type":"Food & Drink"
        }
    ],
    "sg:menulink":"http://www.allmenus.com/fl/orlando/160367-burger-king/menu/",
    "sg:phone":"+1 407 370 4510",
    "sg:postcode":"32839",
    "sg:province":"FL",
    "sg:tags":[
        "burger",
        "american"
    ],
    "wof:name":"Burger King",
    "wof:placetype":"venue"
},
  "geometry": {"coordinates":[-81.418137,28.485828],"type":"Point"}
}