{
  "type": "Feature",
  "properties": {
    "addr:full":"1310 SW Eagleglen Pl Stuart FL 34997",
    "addr:housenumber":"1310",
    "addr:postcode":"34997",
    "addr:street":"Sw Eagleglen Pl",
    "iso:country":"US",
    "sg:address":"1310 SW Eagleglen Pl",
    "sg:city":"Stuart",
    "sg:classifiers":[
        {
            "category":"Arts & Performance",
            "subcategory":"Theater",
            "type":"Entertainment"
        }
    ],
    "sg:phone":"+1 772 219 1000",
    "sg:postcode":"34997",
    "sg:province":"FL",
    "sg:tags":[
        "group"
    ],
    "sg:website":"www.michaelroseorchestra.com",
    "wof:name":"Michael Rose Orchestra",
    "wof:placetype":"venue"
},
  "geometry": {"coordinates":[-80.27267000000001,27.092866],"type":"Point"}
}