{
  "type": "Feature",
  "properties": {
    "iso:country":"US",
    "sg:address":"2406 SE 28th St",
    "sg:city":"Ocala",
    "sg:classifiers":[
        {
            "category":"Professional",
            "subcategory":"Management & Consulting",
            "type":"Services"
        }
    ],
    "sg:phone":"+1 352 622 3127",
    "sg:postcode":"34471",
    "sg:province":"FL",
    "sg:tags":[
        "business"
    ],
    "wof:name":"A Corner of Yesterday",
    "wof:placetype":"venue"
},
  "geometry": {"coordinates":[-82.100019,29.160169],"type":"Point"}
}