{
  "type": "Feature",
  "properties": {
    "iso:country":"US",
    "sg:address":"4995 NW 79th Ave Ste 110",
    "sg:city":"Doral",
    "sg:classifiers":[
        {
            "category":"Shopping",
            "subcategory":"Stationery & Office Supplies",
            "type":"Retail Goods"
        }
    ],
    "sg:phone":"+1 305 261 3736",
    "sg:postcode":"33166",
    "sg:province":"FL",
    "sg:tags":[
        "envelope",
        "store"
    ],
    "wof:name":"Murray Shields Co",
    "wof:placetype":"venue"
},
  "geometry": {"coordinates":[-80.32556,25.818865],"type":"Point"}
}