{
  "type": "Feature",
  "properties": {
    "iso:country":"US",
    "sg:address":"1907 State Road 524",
    "sg:city":"Cocoa",
    "sg:classifiers":[
        {
            "category":"Food & Beverages",
            "subcategory":"Supermarket",
            "type":"Retail Goods"
        },
        {
            "category":"Food & Beverages",
            "subcategory":"Groceries & Convenience Stores",
            "type":"Retail Goods"
        }
    ],
    "sg:phone":"+1 321 504 7880",
    "sg:postcode":"32926",
    "sg:province":"FL",
    "sg:tags":[
        "super"
    ],
    "wof:name":"Sunshine Food Mart 121",
    "wof:placetype":"venue"
},
  "geometry": {"coordinates":[-80.75538,28.397014],"type":"Point"}
}