{
  "type": "Feature",
  "properties": {
    "iso:country":"US",
    "sg:address":"4921 72nd Ave",
    "sg:city":"Pinellas Park",
    "sg:classifiers":[
        {
            "category":"Home & Garden",
            "subcategory":"Building Materials",
            "type":"Retail Goods"
        }
    ],
    "sg:phone":"+1 727 544 1333",
    "sg:postcode":"33781",
    "sg:province":"FL",
    "sg:tags":[
        "repair"
    ],
    "wof:name":"Paint House",
    "wof:placetype":"venue"
},
  "geometry": {"coordinates":[-82.700723,27.837458],"type":"Point"}
}