{
  "type": "Feature",
  "properties": {
    "iso:country":"US",
    "sg:address":"14610 SW 103rd Ave",
    "sg:city":"Miami",
    "sg:classifiers":[
        {
            "category":"Organizations",
            "subcategory":"Professional Association",
            "type":"Services"
        }
    ],
    "sg:phone":"+1 305 238 4513",
    "sg:postcode":"33176",
    "sg:province":"FL",
    "sg:tags":[
        "sale"
    ],
    "wof:name":"Isaac Robinson",
    "wof:placetype":"venue"
},
  "geometry": {"coordinates":[-80.360257,25.63335],"type":"Point"}
}