{
  "type": "Feature",
  "properties": {
    "iso:country":"US",
    "sg:address":"18291 US Hwy 331 S",
    "sg:city":"Freeport",
    "sg:classifiers":[
        {
            "category":"Autos & Motor Vehicles",
            "subcategory":"Motorcycle Sales",
            "type":"Retail Goods"
        }
    ],
    "sg:phone":"+1 850 835 5400",
    "sg:postcode":"32439",
    "sg:province":"FL",
    "sg:tags":[
        "all",
        "terrain"
    ],
    "wof:name":"Distinctive Cycles Inc",
    "wof:placetype":"venue"
},
  "geometry": {"coordinates":[-86.130972,30.458623],"type":"Point"}
}