{
  "type": "Feature",
  "properties": {
    "addr:full":"221 W 27th St Hialeah FL 33010",
    "addr:housenumber":"221",
    "addr:postcode":"33010",
    "addr:street":"W 27Th St",
    "iso:country":"US",
    "sg:address":"221 W 27th St",
    "sg:city":"Hialeah",
    "sg:classifiers":[
        {
            "category":"Home & Garden",
            "subcategory":"Furniture",
            "type":"Retail Goods"
        }
    ],
    "sg:phone":"+1 305 882 0102",
    "sg:postcode":"33010",
    "sg:province":"FL",
    "sg:tags":[
        "material"
    ],
    "wof:name":"Aparicio Kitchen Cabinets",
    "wof:placetype":"venue"
},
  "geometry": {"coordinates":[-80.287869,25.84636],"type":"Point"}
}