{
  "type": "Feature",
  "properties": {
    "iso:country":"US",
    "sg:address":"7060 Beach Blvd",
    "sg:city":"Jacksonville",
    "sg:classifiers":[
        {
            "category":"Wholesale",
            "subcategory":"Construction Materials",
            "type":"Manufacturing & Wholesale Goods"
        }
    ],
    "sg:phone":"+1 904 724 0350",
    "sg:postcode":"32216",
    "sg:province":"FL",
    "sg:tags":[
        "concrete",
        "product"
    ],
    "wof:name":"Jarmon's",
    "wof:placetype":"venue"
},
  "geometry": {"coordinates":[-81.58698,30.2895],"type":"Point"}
}