{
  "type": "Feature",
  "properties": {
    "addr:full":"1703 E 5th St Panama City FL 32401",
    "addr:housenumber":"1703",
    "addr:postcode":"32401",
    "addr:street":"E 5Th St",
    "iso:country":"US",
    "sg:address":"1703 E 5th St",
    "sg:city":"Panama City",
    "sg:classifiers":[
        {
            "category":"Home & Garden",
            "subcategory":"Carpets & Floor Coverings",
            "type":"Retail Goods"
        }
    ],
    "sg:phone":"+1 850 785 1561",
    "sg:postcode":"32401",
    "sg:province":"FL",
    "sg:tags":[
        "dealer",
        "rug"
    ],
    "wof:name":"Surplus & Salvage Sales Inc",
    "wof:placetype":"venue"
},
  "geometry": {"coordinates":[-85.63772,30.156878],"type":"Point"}
}