{
  "type": "Feature",
  "properties": {
    "iso:country":"US",
    "sg:address":"8100 SW 81st Dr",
    "sg:city":"Miami",
    "sg:classifiers":[
        {
            "category":"Personal",
            "subcategory":"Massage",
            "type":"Services"
        }
    ],
    "sg:phone":"+1 305 596 6644",
    "sg:postcode":"33143",
    "sg:province":"FL",
    "sg:tags":[
        "therapist"
    ],
    "wof:name":"Pain Relief Center",
    "wof:placetype":"venue"
},
  "geometry": {"coordinates":[-80.32501999999999,25.69492],"type":"Point"}
}