{
  "type": "Feature",
  "properties": {
    "iso:country":"US",
    "sg:address":"1500 Weston Rd",
    "sg:city":"Weston",
    "sg:classifiers":[
        {
            "category":"Retail",
            "subcategory":"Portrait Studio",
            "type":"Services"
        }
    ],
    "sg:phone":"+1 954 385 5666",
    "sg:postcode":"33326",
    "sg:province":"FL",
    "sg:tags":[
        "photographer"
    ],
    "wof:name":"Brett Tyler Photography",
    "wof:placetype":"venue"
},
  "geometry": {"coordinates":[-80.366984,26.100956],"type":"Point"}
}