{
  "type": "Feature",
  "properties": {
    "addr:full":"920 Lincoln Rd Miami Beach FL 33139",
    "addr:housenumber":"920",
    "addr:postcode":"33139",
    "addr:street":"Lincoln Rd",
    "iso:country":"US",
    "sg:address":"920 Lincoln Rd",
    "sg:city":"Miami Beach",
    "sg:classifiers":[
        {
            "category":"Shopping",
            "subcategory":"Clothing, Apparel, & Fashions",
            "type":"Retail Goods"
        }
    ],
    "sg:phone":"+1 305 695 8808",
    "sg:postcode":"33139",
    "sg:province":"FL",
    "sg:tags":[
        "clothes",
        "retailer",
        "accessory"
    ],
    "wof:name":"Chroma",
    "wof:placetype":"venue"
},
  "geometry": {"coordinates":[-80.138593,25.790425],"type":"Point"}
}