{
  "type": "Feature",
  "properties": {
    "iso:country":"US",
    "sg:address":"1817 NW 13th St",
    "sg:city":"Gainesville",
    "sg:classifiers":[
        {
            "category":"Insurance",
            "subcategory":"Insurance Agent",
            "type":"Services"
        }
    ],
    "sg:phone":"+1 352 377 5511",
    "sg:postcode":"32609",
    "sg:province":"FL",
    "wof:name":"Allstate",
    "wof:placetype":"venue"
},
  "geometry": {"coordinates":[-82.33907600000001,29.670107],"type":"Point"}
}