{
  "type": "Feature",
  "properties": {
    "iso:country":"US",
    "sg:address":"13135 Fort King Rd",
    "sg:city":"Dade City",
    "sg:classifiers":[
        {
            "category":"Government",
            "subcategory":"Office",
            "type":"Public Place"
        }
    ],
    "sg:phone":"+1 352 567 5567",
    "sg:postcode":"33525",
    "sg:province":"FL",
    "sg:tags":[
        "county",
        "program"
    ],
    "wof:name":"Pasco County School Bus Garage",
    "wof:placetype":"venue"
},
  "geometry": {"coordinates":[-82.20348199999999,28.336932],"type":"Point"}
}