{
  "type": "Feature",
  "properties": {
    "addr:full":"317 Polk St Hollywood FL 33019",
    "addr:housenumber":"317",
    "addr:postcode":"33019",
    "addr:street":"Polk St",
    "iso:country":"US",
    "sg:address":"317 Polk St",
    "sg:city":"Hollywood",
    "sg:classifiers":[
        {
            "category":"Travel",
            "subcategory":"Hotels & Motels",
            "type":"Entertainment"
        },
        {
            "category":"Travel",
            "subcategory":"Bed & Breakfast",
            "type":"Entertainment"
        }
    ],
    "sg:phone":"+1 954 450 0000",
    "sg:postcode":"33019",
    "sg:province":"FL",
    "sg:tags":[
        "inn",
        "corporate",
        "lodging"
    ],
    "sg:website":"http://www.villa-sinclair.com",
    "wof:name":"Villa Sinclair",
    "wof:placetype":"venue"
},
  "geometry": {"coordinates":[-80.11611000000001,26.013886],"type":"Point"}
}