{
  "type": "Feature",
  "properties": {
    "iso:country":"US",
    "sg:address":"3040 NW 6th St",
    "sg:city":"Miami",
    "sg:classifiers":[
        {
            "category":"Professional",
            "subcategory":"Printing & Photocopies",
            "type":"Services"
        }
    ],
    "sg:phone":"+1 305 264 8766",
    "sg:postcode":"33125",
    "sg:province":"FL",
    "sg:tags":[
        "consultant"
    ],
    "wof:name":"Network Lucidity Inc",
    "wof:placetype":"venue"
},
  "geometry": {"coordinates":[-80.245099,25.778471],"type":"Point"}
}