{
  "type": "Feature",
  "properties": {
    "addr:full":"235 SW 6th Ave Boynton Beach FL 33435",
    "addr:housenumber":"235",
    "addr:postcode":"33435",
    "addr:street":"Sw 6Th Ave",
    "iso:country":"US",
    "sg:address":"235 SW 6th Ave",
    "sg:city":"Boynton Beach",
    "sg:classifiers":[
        {
            "category":"Organizations",
            "subcategory":"Religious Organization",
            "type":"Services"
        }
    ],
    "sg:phone":"+1 561 732 3774",
    "sg:postcode":"33435",
    "sg:province":"FL",
    "wof:name":"First Presb Chur Boyntn Bch",
    "wof:placetype":"venue"
},
  "geometry": {"coordinates":[-80.067455,26.521806],"type":"Point"}
}