{
  "type": "Feature",
  "properties": {
    "addr:full":"1395 Brickell Ave Miami FL 33129",
    "addr:housenumber":"1395",
    "addr:postcode":"33129",
    "addr:street":"Brickell Ave",
    "iso:country":"US",
    "sg:address":"1395 Brickell Ave",
    "sg:city":"Miami",
    "sg:classifiers":[
        {
            "category":"Government",
            "subcategory":"Office",
            "type":"Public Place"
        }
    ],
    "sg:phone":"+1 305 372 9799",
    "sg:postcode":"33129",
    "sg:province":"FL",
    "sg:tags":[
        "federal",
        "affairs"
    ],
    "wof:name":"Consulate General De France",
    "wof:placetype":"venue"
},
  "geometry": {"coordinates":[-80.192027,25.760755],"type":"Point"}
}