{
  "type": "Feature",
  "properties": {
    "iso:country":"US",
    "sg:address":"110 Farrier Ln",
    "sg:city":"Crawfordville",
    "sg:classifiers":[
        {
            "category":"Professional",
            "subcategory":"Business Services",
            "type":"Services"
        }
    ],
    "sg:phone":"+1 850 294 2252",
    "sg:postcode":"32327",
    "sg:province":"FL",
    "sg:tags":[
        "consultant",
        "coach"
    ],
    "wof:name":"Steve Paris Consulting",
    "wof:placetype":"venue"
},
  "geometry": {"coordinates":[-84.339443,30.184967],"type":"Point"}
}