{
  "type": "Feature",
  "properties": {
    "iso:country":"US",
    "sg:address":"1900 Scott St",
    "sg:city":"Hollywood",
    "sg:classifiers":[
        {
            "category":"Building & Trades",
            "subcategory":"Construction",
            "type":"Services"
        }
    ],
    "sg:phone":"+1 954 920 5353",
    "sg:postcode":"33020",
    "sg:province":"FL",
    "sg:tags":[
        "floor",
        "laying",
        "contractor"
    ],
    "wof:name":"Robert Swartz",
    "wof:placetype":"venue"
},
  "geometry": {"coordinates":[-80.147488,26.02984],"type":"Point"}
}