{
  "type": "Feature",
  "properties": {
    "iso:country":"US",
    "sg:address":"859 River Oak W",
    "sg:city":"Ormond Beach",
    "sg:classifiers":[
        {
            "category":"Wholesale",
            "subcategory":"Electrical",
            "type":"Manufacturing & Wholesale Goods"
        }
    ],
    "sg:phone":"+1 386 677 8161",
    "sg:postcode":"32174",
    "sg:province":"FL",
    "sg:tags":[
        "electronic"
    ],
    "wof:name":"Vla Studios",
    "wof:placetype":"venue"
},
  "geometry": {"coordinates":[-81.06785000000001,29.304376],"type":"Point"}
}