{
  "type": "Feature",
  "properties": {
    "addr:full":"1136 Old Dixie Hwy Vero Beach FL 32960",
    "addr:housenumber":"1136",
    "addr:postcode":"32960",
    "addr:street":"Old Dixie Hwy",
    "iso:country":"US",
    "sg:address":"1136 Old Dixie Hwy",
    "sg:city":"Vero Beach",
    "sg:classifiers":[
        {
            "category":"Home & Garden",
            "subcategory":"Carpets & Floor Coverings",
            "type":"Retail Goods"
        }
    ],
    "sg:phone":"+1 772 569 9113",
    "sg:postcode":"32960",
    "sg:province":"FL",
    "sg:tags":[
        "tile",
        "wholesale",
        "marble"
    ],
    "sg:website":"www.creativetile.net",
    "wof:name":"Creative Tile & Marble",
    "wof:placetype":"venue"
},
  "geometry": {"coordinates":[-80.39288000000001,27.619756],"type":"Point"}
}