{
  "type": "Feature",
  "properties": {
    "iso:country":"US",
    "sg:address":"38137 Ricker Dr",
    "sg:city":"Lady Lake",
    "sg:classifiers":[
        {
            "category":"Home & Garden",
            "subcategory":"Garden Supply",
            "type":"Retail Goods"
        }
    ],
    "sg:phone":"+1 352 753 8711",
    "sg:postcode":"32159",
    "sg:province":"FL",
    "sg:tags":[
        "sprinkler"
    ],
    "wof:name":"David Jenzen's Handyman Svc",
    "wof:placetype":"venue"
},
  "geometry": {"coordinates":[-81.86448799999999,28.898191],"type":"Point"}
}