{
  "type": "Feature",
  "properties": {
    "addr:full":"18810 W Dixie Hwy Miami FL 33180",
    "addr:housenumber":"18810",
    "addr:postcode":"33180",
    "addr:street":"W Dixie Hwy",
    "iso:country":"US",
    "sg:address":"18810 W Dixie Hwy",
    "sg:city":"Miami",
    "sg:classifiers":[
        {
            "category":"Personal",
            "subcategory":"Beauty Salon",
            "type":"Services"
        },
        {
            "category":"Personal",
            "subcategory":"Barber",
            "type":"Services"
        },
        {
            "category":"Shopping",
            "subcategory":"Beauty & Cosmetics",
            "type":"Retail Goods"
        }
    ],
    "sg:phone":"+1 305 278 7010",
    "sg:postcode":"33180",
    "sg:province":"FL",
    "sg:tags":[
        "equipment",
        "salons-equipment",
        "supply"
    ],
    "sg:website":"http://www.acebeauty.com",
    "wof:name":"Beauty Alliance",
    "wof:placetype":"venue"
},
  "geometry": {"coordinates":[-80.148809,25.949407],"type":"Point"}
}