{
  "type": "Feature",
  "properties": {
    "addr:full":"2750 Haines Bayshore Rd Clearwater FL 33760",
    "addr:housenumber":"2750",
    "addr:postcode":"33760",
    "addr:street":"Haines Bayshore Rd",
    "iso:country":"US",
    "sg:address":"2750 Haines Bayshore Rd",
    "sg:city":"Clearwater",
    "sg:classifiers":[
        {
            "category":"Education",
            "subcategory":"School",
            "type":"Public Place"
        }
    ],
    "sg:phone":"+1 727 531 1449",
    "sg:postcode":"33760",
    "sg:province":"FL",
    "wof:name":"CLEARWATER Central Catholic Hs",
    "wof:placetype":"venue"
},
  "geometry": {"coordinates":[-82.721279,27.930994],"type":"Point"}
}