{
  "type": "Feature",
  "properties": {
    "iso:country":"US",
    "sg:address":"4960 SW 72nd Ave Ste 301",
    "sg:city":"Miami",
    "sg:classifiers":[
        {
            "category":"Professional",
            "subcategory":"Computer Services",
            "type":"Services"
        }
    ],
    "sg:phone":"+1 305 665 3379",
    "sg:postcode":"33155",
    "sg:province":"FL",
    "sg:tags":[
        "repair"
    ],
    "wof:name":"Compuwin",
    "wof:placetype":"venue"
},
  "geometry": {"coordinates":[-80.312986,25.724043],"type":"Point"}
}