{
  "type": "Feature",
  "properties": {
    "iso:country":"US",
    "sg:address":"425 North Rd",
    "sg:city":"Naples",
    "sg:classifiers":[
        {
            "category":"Autos & Motor Vehicles",
            "subcategory":"Boat Sales",
            "type":"Retail Goods"
        }
    ],
    "sg:phone":"+1 239 643 0232",
    "sg:postcode":"34104",
    "sg:province":"FL",
    "sg:tags":[
        "dealer",
        "sales"
    ],
    "sg:website":"www.naplesmarina.com",
    "wof:name":"Naples Marina & Boating Ctr",
    "wof:placetype":"venue"
},
  "geometry": {"coordinates":[-81.782918,26.152269],"type":"Point"}
}