{
  "type": "Feature",
  "properties": {
    "addr:full":"12670 Wildrose Ave New Port Richey FL 34654",
    "addr:housenumber":"12670",
    "addr:postcode":"34654",
    "addr:street":"Wildrose Ave",
    "iso:country":"US",
    "sg:address":"12670 Wildrose Ave",
    "sg:city":"New Port Richey",
    "sg:classifiers":[
        {
            "category":"Building & Trades",
            "subcategory":"Construction",
            "type":"Services"
        }
    ],
    "sg:phone":"+1 727 856 1399",
    "sg:postcode":"34654",
    "sg:province":"FL",
    "sg:tags":[
        "restoration",
        "cleaning",
        "patio",
        "deck"
    ],
    "wof:name":"P Marquis Pressure Cleaning",
    "wof:placetype":"venue"
},
  "geometry": {"coordinates":[-82.605243,28.28284],"type":"Point"}
}