{
  "type": "Feature",
  "properties": {
    "iso:country":"US",
    "sg:address":"10530 NW 26th St Ste F203",
    "sg:city":"Doral",
    "sg:classifiers":[
        {
            "category":"Personal",
            "subcategory":"Tanning Parlor",
            "type":"Services"
        }
    ],
    "sg:phone":"+1 305 463 7366",
    "sg:postcode":"33172",
    "sg:province":"FL",
    "sg:tags":[
        "salon"
    ],
    "wof:name":"Tans Maritima Usa",
    "wof:placetype":"venue"
},
  "geometry": {"coordinates":[-80.36693,25.798019],"type":"Point"}
}