{
  "type": "Feature",
  "properties": {
    "addr:full":"2716 NE 28th St Fort Lauderdale FL 33306",
    "addr:housenumber":"2716",
    "addr:postcode":"33306",
    "addr:street":"Ne 28Th St",
    "iso:country":"US",
    "sg:address":"2716 NE 28th St",
    "sg:city":"Fort Lauderdale",
    "sg:classifiers":[
        {
            "category":"Retail",
            "subcategory":"Repair Shop",
            "type":"Services"
        }
    ],
    "sg:phone":"+1 954 564 5433",
    "sg:postcode":"33306",
    "sg:province":"FL",
    "sg:tags":[
        "equipment",
        "conditioning",
        "air"
    ],
    "wof:name":"A C Abraham",
    "wof:placetype":"venue"
},
  "geometry": {"coordinates":[-80.111614,26.163698],"type":"Point"}
}