{
  "type": "Feature",
  "properties": {
    "iso:country":"US",
    "sg:address":"1037 S Florida Ave",
    "sg:city":"Lakeland",
    "sg:classifiers":[
        {
            "category":"Professional",
            "subcategory":"Advertising",
            "type":"Services"
        }
    ],
    "sg:phone":"+1 863 688 7078",
    "sg:postcode":"33803",
    "sg:province":"FL",
    "sg:tags":[
        "agency",
        "public",
        "relations"
    ],
    "wof:name":"Nissen Advertising Inc",
    "wof:placetype":"venue"
},
  "geometry": {"coordinates":[-81.957195,28.030627],"type":"Point"}
}