{
  "type": "Feature",
  "properties": {
    "iso:country":"US",
    "sg:address":"1929 Directors Row",
    "sg:city":"Orlando",
    "sg:phone":"+1 407 852 1970",
    "sg:postcode":"32809",
    "sg:province":"FL",
    "sg:tags":[
        "oil"
    ],
    "sg:website":"www.ashland.com",
    "wof:name":"Valvoline Co",
    "wof:placetype":"venue"
},
  "geometry": {"coordinates":[-81.40033099999999,28.459052],"type":"Point"}
}