{
  "type": "Feature",
  "properties": {
    "iso:country":"US",
    "sg:address":"10018 W McNab Rd",
    "sg:city":"Fort Lauderdale",
    "sg:classifiers":[
        {
            "category":"Retail",
            "subcategory":"Laundry & Dry Cleaning",
            "type":"Services"
        }
    ],
    "sg:phone":"+1 954 741 0048",
    "sg:postcode":"33321",
    "sg:province":"FL",
    "wof:name":"Image Floors Interiors",
    "wof:placetype":"venue"
},
  "geometry": {"coordinates":[-80.29113599999999,26.208318],"type":"Point"}
}