{
  "type": "Feature",
  "properties": {
    "addr:full":"2025 E Atlantic Blvd Pompano Beach FL 33060",
    "addr:housenumber":"2025",
    "addr:postcode":"33060",
    "addr:street":"E Atlantic Blvd",
    "iso:country":"US",
    "sg:address":"2025 E Atlantic Blvd",
    "sg:city":"Pompano Beach",
    "sg:classifiers":[
        {
            "category":"Restaurant",
            "type":"Food & Drink"
        }
    ],
    "sg:menulink":"http://www.allmenus.com/fl/pompano-beach/187618-mcdonalds/menu/",
    "sg:phone":"+1 954 781 1920",
    "sg:postcode":"33060",
    "sg:province":"FL",
    "sg:tags":[
        "burger",
        "american"
    ],
    "wof:name":"McDonald's",
    "wof:placetype":"venue"
},
  "geometry": {"coordinates":[-80.103633,26.231822],"type":"Point"}
}