{
  "type": "Feature",
  "properties": {
    "iso:country":"US",
    "sg:address":"1168 SW Ithaca St",
    "sg:city":"Port Saint Lucie",
    "sg:classifiers":[
        {
            "category":"Building & Trades",
            "subcategory":"Construction",
            "type":"Services"
        }
    ],
    "sg:phone":"+1 772 834 6394",
    "sg:postcode":"34983",
    "sg:province":"FL",
    "sg:tags":[
        "hanging",
        "contractor"
    ],
    "wof:name":"Carrie Dequattro",
    "wof:placetype":"venue"
},
  "geometry": {"coordinates":[-80.351634,27.305906],"type":"Point"}
}