{
  "type": "Feature",
  "properties": {
    "iso:country":"US",
    "sg:address":"207 N A St",
    "sg:city":"Lake Worth",
    "sg:classifiers":[
        {
            "category":"Food & Beverages",
            "subcategory":"Meat & Fish",
            "type":"Retail Goods"
        }
    ],
    "sg:phone":"+1 561 588 8688",
    "sg:postcode":"33460",
    "sg:province":"FL",
    "wof:name":"Papa's Meat Market",
    "wof:placetype":"venue"
},
  "geometry": {"coordinates":[-80.065062,26.619218],"type":"Point"}
}