{
  "type": "Feature",
  "properties": {
    "addr:full":"2800 Mahan Dr Tallahassee FL 32308",
    "addr:housenumber":"2800",
    "addr:postcode":"32308",
    "addr:street":"Mahan Dr",
    "iso:country":"US",
    "sg:address":"2800 Mahan Dr",
    "sg:city":"Tallahassee",
    "sg:classifiers":[
        {
            "category":"Restaurant",
            "type":"Food & Drink"
        }
    ],
    "sg:phone":"+1 850 878 6472",
    "sg:postcode":"32308",
    "sg:province":"FL",
    "sg:tags":[
        "eating"
    ],
    "wof:name":"Ryan S Steak House",
    "wof:placetype":"venue"
},
  "geometry": {"coordinates":[-84.22799500000001,30.460089],"type":"Point"}
}