{
  "type": "Feature",
  "properties": {
    "iso:country":"US",
    "sg:address":"305 Kingston Ave",
    "sg:city":"Daytona Beach",
    "sg:classifiers":[
        {
            "category":"Taxi",
            "type":"Transportation"
        }
    ],
    "sg:phone":"+1 386 254 3400",
    "sg:postcode":"32114",
    "sg:province":"FL",
    "sg:tags":[
        "taxicab"
    ],
    "wof:name":"All Florida Cab",
    "wof:placetype":"venue"
},
  "geometry": {"coordinates":[-81.030997,29.224667],"type":"Point"}
}