{
  "type": "Feature",
  "properties": {
    "iso:country":"US",
    "sg:address":"5008 Manatee Ave W",
    "sg:city":"Bradenton",
    "sg:classifiers":[
        {
            "category":"Real Estate",
            "subcategory":"Developer",
            "type":"Services"
        },
        {
            "category":"Real Estate",
            "subcategory":"Real Estate Agent",
            "type":"Services"
        }
    ],
    "sg:phone":"+1 941 748 4098",
    "sg:postcode":"34209",
    "sg:province":"FL",
    "wof:name":"All Florida Realty & Auctn Co",
    "wof:placetype":"venue"
},
  "geometry": {"coordinates":[-82.61149,27.495972],"type":"Point"}
}