{
  "type": "Feature",
  "properties": {
    "addr:full":"100 S Myrtle Ave Clearwater FL 33756",
    "addr:housenumber":"100",
    "addr:postcode":"33756",
    "addr:street":"S Myrtle Ave",
    "iso:country":"US",
    "sg:address":"100 S Myrtle Ave",
    "sg:city":"Clearwater",
    "sg:classifiers":[
        {
            "category":"Banks & Credit Unions",
            "subcategory":"Investment Brokerage",
            "type":"Services"
        },
        {
            "category":"Professional",
            "subcategory":"Business Services",
            "type":"Services"
        }
    ],
    "sg:phone":"+1 727 562 4554",
    "sg:postcode":"33756",
    "sg:province":"FL",
    "sg:tags":[
        "development",
        "councils",
        "economic",
        "authorities",
        "commissions"
    ],
    "wof:name":"Development Neighborhood Svcs",
    "wof:placetype":"venue"
},
  "geometry": {"coordinates":[-82.79589799999999,27.964781],"type":"Point"}
}