{
  "type": "Feature",
  "properties": {
    "addr:full":"10937 NW 33 Pl Gainesville FL 32606",
    "addr:housenumber":"10937",
    "addr:postcode":"32606",
    "addr:street":"Nw 33 Pl",
    "iso:country":"US",
    "sg:address":"10937 NW 33 Pl",
    "sg:city":"Gainesville",
    "sg:classifiers":[
        {
            "category":"Professional",
            "subcategory":"Accounting & Tax Preparation",
            "type":"Services"
        }
    ],
    "sg:phone":"+1 352 331 8923",
    "sg:postcode":"32606",
    "sg:province":"FL",
    "wof:name":"Medical Billing Mgt Gainesvill",
    "wof:placetype":"venue"
},
  "geometry": {"coordinates":[-82.45755200000001,29.684317],"type":"Point"}
}