{
  "type": "Feature",
  "properties": {
    "addr:full":"205 US Hwy 27 Lake Placid FL 33852",
    "addr:housenumber":"205",
    "addr:postcode":"33852",
    "addr:street":"Us Hwy 27",
    "iso:country":"US",
    "sg:address":"205 US Hwy 27",
    "sg:city":"Lake Placid",
    "sg:classifiers":[
        {
            "category":"Building & Trades",
            "subcategory":"Electrical",
            "type":"Services"
        }
    ],
    "sg:phone":"+1 863 465 3352",
    "sg:postcode":"33852",
    "sg:province":"FL",
    "sg:tags":[
        "installs",
        "security",
        "alarm",
        "system"
    ],
    "wof:name":"Central Security & Electronics",
    "wof:placetype":"venue"
},
  "geometry": {"coordinates":[-81.358485,27.301139],"type":"Point"}
}