{
  "type": "Feature",
  "properties": {
    "addr:full":"333 SE 32nd St Cape Coral FL 33904",
    "addr:housenumber":"333",
    "addr:postcode":"33904",
    "addr:street":"Se 32Nd St",
    "iso:country":"US",
    "sg:address":"333 SE 32nd St",
    "sg:city":"Cape Coral",
    "sg:classifiers":[
        {
            "category":"Building & Trades",
            "subcategory":"Landscaping Services",
            "type":"Services"
        }
    ],
    "sg:phone":"+1 239 458 0224",
    "sg:postcode":"33904",
    "sg:province":"FL",
    "sg:tags":[
        "tree"
    ],
    "wof:name":"All Coast Tree Svc",
    "wof:placetype":"venue"
},
  "geometry": {"coordinates":[-81.967264,26.592623],"type":"Point"}
}