{
  "type": "Feature",
  "properties": {
    "iso:country":"US",
    "sg:address":"14901 Park Lake Dr",
    "sg:city":"Fort Myers",
    "sg:classifiers":[
        {
            "category":"Professional",
            "type":"Services"
        }
    ],
    "sg:phone":"+1 239 489 4977",
    "sg:postcode":"33919",
    "sg:province":"FL",
    "wof:name":"Waranty Services",
    "wof:placetype":"venue"
},
  "geometry": {"coordinates":[-81.89085900000001,26.526596],"type":"Point"}
}