{
  "type": "Feature",
  "properties": {
    "iso:country":"US",
    "sg:address":"337 Bay Arbor Blvd",
    "sg:city":"Oldsmar",
    "sg:classifiers":[
        {
            "category":"Building & Trades",
            "subcategory":"Construction",
            "type":"Services"
        }
    ],
    "sg:phone":"+1 813 907 9693",
    "sg:postcode":"34677",
    "sg:province":"FL",
    "sg:tags":[
        "home",
        "builder"
    ],
    "wof:name":"Lennar Homes",
    "wof:placetype":"venue"
},
  "geometry": {"coordinates":[-82.68187399999999,28.049664],"type":"Point"}
}