{
  "type": "Feature",
  "properties": {
    "iso:country":"US",
    "sg:address":"8905 Regents Park Dr",
    "sg:city":"Tampa",
    "sg:classifiers":[
        {
            "category":"Real Estate",
            "subcategory":"Real Estate Services",
            "type":"Services"
        }
    ],
    "sg:phone":"+1 813 907 5073",
    "sg:postcode":"33647",
    "sg:province":"FL",
    "sg:tags":[
        "company",
        "title"
    ],
    "wof:name":"First American Title Ins Co",
    "wof:placetype":"venue"
},
  "geometry": {"coordinates":[-82.350853,28.146578],"type":"Point"}
}