{
  "type": "Feature",
  "properties": {
    "iso:country":"US",
    "sg:address":"706 1st Ave N",
    "sg:city":"Safety Harbor",
    "sg:classifiers":[
        {
            "category":"Building & Trades",
            "subcategory":"Construction",
            "type":"Services"
        }
    ],
    "sg:phone":"+1 727 726 0581",
    "sg:postcode":"34695",
    "sg:province":"FL",
    "sg:tags":[
        "contractor"
    ],
    "wof:name":"Palmer Building Contractors In",
    "wof:placetype":"venue"
},
  "geometry": {"coordinates":[-82.688001,27.998748],"type":"Point"}
}