{
  "type": "Feature",
  "properties": {
    "iso:country":"US",
    "sg:address":"2225 Carter Rd",
    "sg:city":"St Augustine",
    "sg:classifiers":[
        {
            "category":"Utilities",
            "type":"Services"
        },
        {
            "category":"Building & Trades",
            "subcategory":"Landscaping Services",
            "type":"Services"
        }
    ],
    "sg:phone":"+1 904 824 5245",
    "sg:postcode":"32084",
    "sg:province":"FL",
    "sg:tags":[
        "sweeping"
    ],
    "wof:name":"Joiner Sweeping & Lawn Service",
    "wof:placetype":"venue"
},
  "geometry": {"coordinates":[-81.380698,29.890476],"type":"Point"}
}