{
  "type": "Feature",
  "properties": {
    "iso:country":"US",
    "sg:address":"2870 Harper Rd",
    "sg:city":"Melbourne",
    "sg:classifiers":[
        {
            "category":"Professional",
            "subcategory":"Business Services",
            "type":"Services"
        }
    ],
    "sg:phone":"+1 321 676 6336",
    "sg:postcode":"32904",
    "sg:province":"FL",
    "wof:name":"Omni Business Solutions Inc",
    "wof:placetype":"venue"
},
  "geometry": {"coordinates":[-80.668701,28.10582],"type":"Point"}
}