{
  "type": "Feature",
  "properties": {
    "addr:full":"1937 George Jenkins Blvd Lakeland FL 33815",
    "addr:housenumber":"1937",
    "addr:postcode":"33815",
    "addr:street":"George Jenkins Blvd",
    "iso:country":"US",
    "sg:address":"1937 George Jenkins Blvd",
    "sg:city":"Lakeland",
    "sg:classifiers":[
        {
            "category":"Restaurant",
            "type":"Food & Drink"
        }
    ],
    "sg:phone":"+1 863 688 6623",
    "sg:postcode":"33815",
    "sg:province":"FL",
    "sg:tags":[
        "fast"
    ],
    "wof:name":"McDonalds",
    "wof:placetype":"venue"
},
  "geometry": {"coordinates":[-81.987377,28.041995],"type":"Point"}
}