{
  "type": "Feature",
  "properties": {
    "iso:country":"US",
    "sg:address":"707 Debra Lynne Dr",
    "sg:city":"Brandon",
    "sg:classifiers":[
        {
            "category":"Professional",
            "subcategory":"Business Services",
            "type":"Services"
        }
    ],
    "sg:phone":"+1 813 654 4573",
    "sg:postcode":"33511",
    "sg:province":"FL",
    "wof:name":"Professional By Design",
    "wof:placetype":"venue"
},
  "geometry": {"coordinates":[-82.29689399999999,27.929077],"type":"Point"}
}