{
  "type": "Feature",
  "properties": {
    "iso:country":"US",
    "sg:address":"800 S Delaney Ave",
    "sg:city":"Avon Park",
    "sg:classifiers":[
        {
            "category":"Social Services",
            "subcategory":"Child Care",
            "type":"Services"
        }
    ],
    "sg:phone":"+1 863 452 1069",
    "sg:postcode":"33825",
    "sg:province":"FL",
    "wof:name":"Avon Park Community Child Care",
    "wof:placetype":"venue"
},
  "geometry": {"coordinates":[-81.498114,27.588289],"type":"Point"}
}