{
  "type": "Feature",
  "properties": {
    "addr:full":"824 Spring Garden Ranch Rd De Leon Springs FL 32130",
    "addr:housenumber":"824",
    "addr:postcode":"32130",
    "addr:street":"Spring Garden Ranch Rd De Leon",
    "iso:country":"US",
    "sg:address":"824 Spring Garden Ranch Rd",
    "sg:city":"De Leon Springs",
    "sg:classifiers":[
        {
            "category":"Manufacturing",
            "subcategory":"Wood Products",
            "type":"Manufacturing & Wholesale Goods"
        }
    ],
    "sg:phone":"+1 386 985 5315",
    "sg:postcode":"32130",
    "sg:province":"FL",
    "sg:tags":[
        "mfg"
    ],
    "wof:name":"Dan Sue",
    "wof:placetype":"venue"
},
  "geometry": {"coordinates":[-81.341364,29.136948],"type":"Point"}
}