{
  "type": "Feature",
  "properties": {
    "addr:full":"1256 Vinetree Dr Brandon FL 33510",
    "addr:housenumber":"1256",
    "addr:postcode":"33510",
    "addr:street":"Vinetree Dr",
    "iso:country":"US",
    "sg:address":"1256 Vinetree Dr",
    "sg:city":"Brandon",
    "sg:classifiers":[
        {
            "category":"Health Services",
            "subcategory":"Clinic",
            "type":"Services"
        }
    ],
    "sg:phone":"+1 813 972 1141",
    "sg:postcode":"33510",
    "sg:province":"FL",
    "sg:tags":[
        "blood",
        "bank"
    ],
    "wof:name":"Electronic Medical Recors",
    "wof:placetype":"venue"
},
  "geometry": {"coordinates":[-82.30101000000001,27.972238],"type":"Point"}
}