{
  "type": "Feature",
  "properties": {
    "addr:full":"335 W Highbanks Rd Debary FL 32713",
    "addr:housenumber":"335",
    "addr:postcode":"32713",
    "addr:street":"W Highbanks Rd",
    "iso:country":"US",
    "sg:address":"335 W Highbanks Rd",
    "sg:city":"Debary",
    "sg:classifiers":[
        {
            "category":"Building & Trades",
            "subcategory":"Construction",
            "type":"Services"
        }
    ],
    "sg:phone":"+1 386 753 0098",
    "sg:postcode":"32713",
    "sg:province":"FL",
    "sg:tags":[
        "contractor"
    ],
    "wof:name":"Camry Homes Inc Residential & Commercial Constuctn",
    "wof:placetype":"venue"
},
  "geometry": {"coordinates":[-81.338402,28.8901],"type":"Point"}
}