{
  "type": "Feature",
  "properties": {
    "addr:full":"1802 N Alafaya Trl Orlando FL 32826",
    "addr:housenumber":"1802",
    "addr:postcode":"32826",
    "addr:street":"N Alafaya Trl",
    "iso:country":"US",
    "sg:address":"1802 N Alafaya Trl",
    "sg:city":"Orlando",
    "sg:classifiers":[
        {
            "category":"Insurance",
            "subcategory":"Hazard Insurance",
            "type":"Services"
        },
        {
            "category":"Insurance",
            "subcategory":"Health Insurance",
            "type":"Services"
        }
    ],
    "sg:phone":"+1 407 992 4420",
    "sg:postcode":"32826",
    "sg:province":"FL",
    "wof:name":"Peo Pros",
    "wof:placetype":"venue"
},
  "geometry": {"coordinates":[-81.20784,28.569271],"type":"Point"}
}