{
  "type": "Feature",
  "properties": {
    "iso:country":"US",
    "sg:address":"2782 Florida Plaza Blvd",
    "sg:city":"Kissimmee",
    "sg:classifiers":[
        {
            "category":"Building & Trades",
            "subcategory":"Construction",
            "type":"Services"
        }
    ],
    "sg:phone":"+1 407 933 2768",
    "sg:postcode":"34746",
    "sg:province":"FL",
    "sg:tags":[
        "home",
        "builder"
    ],
    "wof:name":"ICI Homes",
    "wof:placetype":"venue"
},
  "geometry": {"coordinates":[-81.51570700000001,28.329069],"type":"Point"}
}