{
  "type": "Feature",
  "properties": {
    "addr:full":"4471 NW 36th Ave Miami FL 33142",
    "addr:housenumber":"4471",
    "addr:postcode":"33142",
    "addr:street":"Nw 36Th Ave",
    "iso:country":"US",
    "sg:address":"4471 NW 36th Ave",
    "sg:city":"Miami",
    "sg:classifiers":[
        {
            "category":"Transit Center",
            "subcategory":"Freight",
            "type":"Transportation"
        }
    ],
    "sg:phone":"+1 305 885 4959",
    "sg:postcode":"33142",
    "sg:province":"FL",
    "sg:tags":[
        "cargo",
        "air",
        "express",
        "package"
    ],
    "wof:name":"International Cargo Express",
    "wof:placetype":"venue"
},
  "geometry": {"coordinates":[-80.254689,25.815106],"type":"Point"}
}