{
  "type": "Feature",
  "properties": {
    "iso:country":"US",
    "sg:address":"826 W University Ave",
    "sg:city":"Gainesville",
    "sg:classifiers":[
        {
            "category":"Restaurant",
            "type":"Food & Drink"
        }
    ],
    "sg:menulink":"http://www.allmenus.com/fl/gainesville/207462-taco-bell/menu/",
    "sg:phone":"+1 352 373 2949",
    "sg:postcode":"32601",
    "sg:province":"FL",
    "sg:tags":[
        "mexican"
    ],
    "wof:name":"Taco Bell",
    "wof:placetype":"venue"
},
  "geometry": {"coordinates":[-82.333303,29.652081],"type":"Point"}
}