{
  "type": "Feature",
  "properties": {
    "iso:country":"US",
    "sg:address":"233 NW 20th Ter",
    "sg:city":"Miami",
    "sg:classifiers":[
        {
            "category":"Real Estate",
            "subcategory":"Real Estate Operator",
            "type":"Services"
        }
    ],
    "sg:phone":"+1 305 573 4539",
    "sg:postcode":"33127",
    "sg:province":"FL",
    "sg:tags":[
        "apartment"
    ],
    "wof:name":"Winwood Apartments",
    "wof:placetype":"venue"
},
  "geometry": {"coordinates":[-80.19940200000001,25.796],"type":"Point"}
}