{
  "type": "Feature",
  "properties": {
    "iso:country":"US",
    "sg:address":"1335 Bender Ave",
    "sg:city":"Daytona Beach",
    "sg:classifiers":[
        {
            "category":"Airport",
            "type":"Transportation"
        }
    ],
    "sg:phone":"+1 386 253 8487",
    "sg:postcode":"32117",
    "sg:province":"FL",
    "wof:name":"Daniel A Torlucci",
    "wof:placetype":"venue"
},
  "geometry": {"coordinates":[-81.051573,29.2483],"type":"Point"}
}