{
  "type": "Feature",
  "properties": {
    "iso:country":"US",
    "sg:address":"4237 Bee Ridge Rd",
    "sg:city":"Sarasota",
    "sg:classifiers":[
        {
            "category":"Personal",
            "subcategory":"Beauty Salon",
            "type":"Services"
        }
    ],
    "sg:phone":"+1 941 371 1661",
    "sg:postcode":"34239",
    "sg:province":"FL",
    "wof:name":"Heads Up Hair Co",
    "wof:placetype":"venue"
},
  "geometry": {"coordinates":[-82.480964,27.298731],"type":"Point"}
}