{
  "type": "Feature",
  "properties": {
    "iso:country":"US",
    "sg:address":"504 SE Parkway Dr",
    "sg:city":"Stuart",
    "sg:classifiers":[
        {
            "category":"Building & Trades",
            "subcategory":"Landscaping Services",
            "type":"Services"
        }
    ],
    "sg:phone":"+1 772 220 1765",
    "sg:postcode":"34996",
    "sg:province":"FL",
    "sg:tags":[
        "lawn"
    ],
    "wof:name":"Final Touch Landscape",
    "wof:placetype":"venue"
},
  "geometry": {"coordinates":[-80.22957599999999,27.194399],"type":"Point"}
}