{
  "type": "Feature",
  "properties": {
    "addr:full":"131 W Blue Heron Blvd Riviera Beach FL 33404",
    "addr:housenumber":"131",
    "addr:postcode":"33404",
    "addr:street":"W Blue Heron Blvd",
    "iso:country":"US",
    "sg:address":"131 W Blue Heron Blvd",
    "sg:city":"Riviera Beach",
    "sg:classifiers":[
        {
            "category":"Social Services",
            "subcategory":"Adult Care",
            "type":"Services"
        }
    ],
    "sg:phone":"+1 561 848 0047",
    "sg:postcode":"33404",
    "sg:province":"FL",
    "sg:tags":[
        "home",
        "residential"
    ],
    "wof:name":"Howard House",
    "wof:placetype":"venue"
},
  "geometry": {"coordinates":[-80.057852,26.783415],"type":"Point"}
}