{
  "type": "Feature",
  "properties": {
    "iso:country":"US",
    "sg:address":"3870 Palm Beach Blvd",
    "sg:city":"Fort Myers",
    "sg:classifiers":[
        {
            "category":"Shopping",
            "subcategory":"Clothing, Apparel, & Fashions",
            "type":"Retail Goods"
        }
    ],
    "sg:phone":"+1 239 694 2017",
    "sg:postcode":"33916",
    "sg:province":"FL",
    "sg:tags":[
        "sportswear"
    ],
    "wof:name":"Fiesta Deportes",
    "wof:placetype":"venue"
},
  "geometry": {"coordinates":[-81.83404899999999,26.66419],"type":"Point"}
}