{
  "type": "Feature",
  "properties": {
    "iso:country":"US",
    "sg:address":"276 Alhambra Cir",
    "sg:city":"Coral Gables",
    "sg:classifiers":[
        {
            "category":"Restaurant",
            "type":"Food & Drink"
        }
    ],
    "sg:phone":"+1 305 446 4545",
    "sg:postcode":"33134",
    "sg:province":"FL",
    "wof:name":"Crepes & Co",
    "wof:placetype":"venue"
},
  "geometry": {"coordinates":[-80.259338,25.75203],"type":"Point"}
}