{
  "type": "Feature",
  "properties": {
    "addr:full":"20137 Saraceno Dr Estero FL 33928",
    "addr:postcode":"20137;33928",
    "addr:street":"Saraceno Dr",
    "iso:country":"US",
    "sg:address":"20137 Saraceno Dr",
    "sg:city":"Estero",
    "sg:classifiers":[
        {
            "category":"Professional",
            "type":"Services"
        }
    ],
    "sg:phone":"+1 239 948 7660",
    "sg:postcode":"33928",
    "sg:province":"FL",
    "sg:tags":[
        "establishment"
    ],
    "wof:name":"Grandezza Development",
    "wof:placetype":"venue"
},
  "geometry": {"coordinates":[-81.768265,26.446682],"type":"Point"}
}