{
  "type": "Feature",
  "properties": {
    "iso:country":"US",
    "sg:address":"2125 NW 8th Ave",
    "sg:city":"Miami",
    "sg:classifiers":[
        {
            "category":"Manufacturing",
            "subcategory":"Food",
            "type":"Manufacturing & Wholesale Goods"
        }
    ],
    "sg:phone":"+1 305 545 9993",
    "sg:postcode":"33127",
    "sg:province":"FL",
    "sg:tags":[
        "manufacture",
        "dry",
        "bakery",
        "processing",
        "product"
    ],
    "wof:name":"Bingo Bakery Inc",
    "wof:placetype":"venue"
},
  "geometry": {"coordinates":[-80.209198,25.796301],"type":"Point"}
}