{
  "type": "Feature",
  "properties": {
    "iso:country":"US",
    "sg:address":"1300 W Hillsboro Blvd",
    "sg:city":"Deerfield Beach",
    "sg:classifiers":[
        {
            "category":"Railroad",
            "type":"Transportation"
        }
    ],
    "sg:phone":"+1 954 421 1155",
    "sg:postcode":"33073",
    "sg:province":"FL",
    "sg:tags":[
        "operator",
        "government"
    ],
    "wof:name":"Amtrak Passenger Station",
    "wof:placetype":"venue"
},
  "geometry": {"coordinates":[-80.12138,26.318084],"type":"Point"}
}