{
  "type": "Feature",
  "properties": {
    "iso:country":"US",
    "sg:address":"1601 Collins Ave",
    "sg:city":"Miami Beach",
    "sg:classifiers":[
        {
            "category":"Restaurant",
            "type":"Food & Drink"
        }
    ],
    "sg:menulink":"http://www.allmenus.com/fl/miami-beach/52076-prestons/menu/",
    "sg:phone":"+1 305 604 5442",
    "sg:postcode":"33139",
    "sg:province":"FL",
    "sg:tags":[
        "american"
    ],
    "wof:name":"Preston's",
    "wof:placetype":"venue"
},
  "geometry": {"coordinates":[-80.130171,25.78927],"type":"Point"}
}