{
  "type": "Feature",
  "properties": {
    "iso:country":"US",
    "sg:address":"216 15th St",
    "sg:city":"Panama City",
    "sg:classifiers":[
        {
            "category":"Food & Beverages",
            "subcategory":"Bakery",
            "type":"Retail Goods"
        }
    ],
    "sg:phone":"+1 850 234 8347",
    "sg:postcode":"32413",
    "sg:province":"FL",
    "wof:name":"Moores Distributors Inc",
    "wof:placetype":"venue"
},
  "geometry": {"coordinates":[-85.93283099999999,30.247836],"type":"Point"}
}