{
  "type": "Feature",
  "properties": {
    "iso:country":"US",
    "sg:address":"2509 Coconut Dr",
    "sg:city":"Cocoa",
    "sg:classifiers":[
        {
            "category":"Real Estate",
            "subcategory":"Real Estate Services",
            "type":"Services"
        },
        {
            "category":"Real Estate",
            "subcategory":"Real Estate Agent",
            "type":"Services"
        }
    ],
    "sg:phone":"+1 321 698 8072",
    "sg:postcode":"32926",
    "sg:province":"FL",
    "sg:tags":[
        "buyer",
        "broker"
    ],
    "wof:name":"Aladdin Era Real Estate",
    "wof:placetype":"venue"
},
  "geometry": {"coordinates":[-80.771762,28.367889],"type":"Point"}
}