{
  "type": "Feature",
  "properties": {
    "addr:full":"3471 Olin Baxley Rd Middleburg FL 32068",
    "addr:housenumber":"3471",
    "addr:postcode":"32068",
    "addr:street":"Olin Baxley Rd",
    "iso:country":"US",
    "sg:address":"3471 Olin Baxley Rd",
    "sg:city":"Middleburg",
    "sg:classifiers":[
        {
            "category":"Building & Trades",
            "subcategory":"Construction",
            "type":"Services"
        }
    ],
    "sg:phone":"+1 904 282 1043",
    "sg:postcode":"32068",
    "sg:province":"FL",
    "wof:name":"Ivey Construction Co",
    "wof:placetype":"venue"
},
  "geometry": {"coordinates":[-81.833811,30.088425],"type":"Point"}
}