{
  "type": "Feature",
  "properties": {
    "iso:country":"US",
    "sg:address":"260 Citrus Tower Blvd Suite A",
    "sg:city":"Clermont",
    "sg:classifiers":[
        {
            "category":"Professional",
            "subcategory":"Computer Services",
            "type":"Services"
        },
        {
            "category":"Utilities",
            "subcategory":"Telephone",
            "type":"Services"
        },
        {
            "category":"Communications",
            "type":"Services"
        },
        {
            "category":"Communications",
            "subcategory":"Television Station",
            "type":"Services"
        }
    ],
    "sg:phone":"+1 352 536 6160",
    "sg:postcode":"34711",
    "sg:province":"FL",
    "sg:tags":[
        "satellite",
        "cable",
        "tv",
        "isp",
        "system",
        "equipment",
        "internet",
        "data",
        "provider"
    ],
    "sg:website":"http://CenturyLink.com",
    "wof:name":"Clermont CenturyLink Store",
    "wof:placetype":"venue"
},
  "geometry": {"coordinates":[-81.740996,28.564836],"type":"Point"}
}