{
  "type": "Feature",
  "properties": {
    "iso:country":"US",
    "sg:address":"9897 Gulf Blvd",
    "sg:city":"Saint Petersburg",
    "sg:classifiers":[
        {
            "category":"Home & Garden",
            "subcategory":"Furniture",
            "type":"Retail Goods"
        }
    ],
    "sg:phone":"+1 727 360 4841",
    "sg:postcode":"33706",
    "sg:province":"FL",
    "wof:name":"Bay Pines Furniture",
    "wof:placetype":"venue"
},
  "geometry": {"coordinates":[-82.764644,27.756256],"type":"Point"}
}