{
  "type": "Feature",
  "properties": {
    "addr:full":"8392 Bird Rd Miami FL 33155",
    "addr:housenumber":"8392",
    "addr:postcode":"33155",
    "addr:street":"Bird Rd",
    "iso:country":"US",
    "sg:address":"8392 Bird Rd",
    "sg:city":"Miami",
    "sg:classifiers":[
        {
            "category":"Personal",
            "subcategory":"Nail Salon",
            "type":"Services"
        }
    ],
    "sg:phone":"+1 305 226 0282",
    "sg:postcode":"33155",
    "sg:province":"FL",
    "wof:name":"Florida Hollywood Nail Supply Inc",
    "wof:placetype":"venue"
},
  "geometry": {"coordinates":[-80.331596,25.7332],"type":"Point"}
}