{
  "type": "Feature",
  "properties": {
    "iso:country":"US",
    "sg:address":"2914 Jog Rd",
    "sg:city":"Lake Worth",
    "sg:classifiers":[
        {
            "category":"Health Services",
            "subcategory":"Health Practitioner",
            "type":"Services"
        }
    ],
    "sg:phone":"+1 561 969 1519",
    "sg:postcode":"33467",
    "sg:province":"FL",
    "sg:tags":[
        "therapy",
        "outpatient",
        "physical"
    ],
    "wof:name":"English English Physcl Therapy",
    "wof:placetype":"venue"
},
  "geometry": {"coordinates":[-80.146002,26.632129],"type":"Point"}
}