{
  "type": "Feature",
  "properties": {
    "addr:full":"6602 Causeway Blvd Tampa FL 33619",
    "addr:housenumber":"6602",
    "addr:postcode":"33619",
    "addr:street":"Causeway Blvd",
    "iso:country":"US",
    "sg:address":"6602 Causeway Blvd",
    "sg:city":"Tampa",
    "sg:classifiers":[
        {
            "category":"Professional",
            "subcategory":"Detective & Security Services",
            "type":"Services"
        }
    ],
    "sg:phone":"+1 813 630 5656",
    "sg:postcode":"33619",
    "sg:province":"FL",
    "sg:tags":[
        "system"
    ],
    "sg:website":"www.sheppardsecurity.com",
    "wof:name":"Sheppard Security & Comm",
    "wof:placetype":"venue"
},
  "geometry": {"coordinates":[-82.379948,27.92282],"type":"Point"}
}