{
  "type": "Feature",
  "properties": {
    "iso:country":"US",
    "sg:address":"14910 Casey Rd",
    "sg:city":"Tampa",
    "sg:classifiers":[
        {
            "category":"Banks & Credit Unions",
            "subcategory":"Bank",
            "type":"Services"
        }
    ],
    "sg:phone":"+1 813 962 4202",
    "sg:postcode":"33624",
    "sg:province":"FL",
    "sg:tags":[
        "loan",
        "real estate"
    ],
    "wof:name":"Challenge Mortgage-Carrollwood",
    "wof:placetype":"venue"
},
  "geometry": {"coordinates":[-82.517313,28.085154],"type":"Point"}
}