{
  "type": "Feature",
  "properties": {
    "iso:country":"US",
    "sg:address":"755 S Palm Ave",
    "sg:city":"Sarasota",
    "sg:classifiers":[
        {
            "category":"Professional",
            "subcategory":"Secretarial Services",
            "type":"Services"
        }
    ],
    "sg:phone":"+1 941 504 7208",
    "sg:postcode":"34236",
    "sg:province":"FL",
    "sg:tags":[
        "reporting",
        "court"
    ],
    "wof:name":"Administrative Services On Lin",
    "wof:placetype":"venue"
},
  "geometry": {"coordinates":[-82.539717,27.3294],"type":"Point"}
}