{
  "type": "Feature",
  "properties": {
    "iso:country":"US",
    "sg:address":"1545 49th St N",
    "sg:city":"Saint Petersburg",
    "sg:classifiers":[
        {
            "category":"Bars & Pubs",
            "type":"Food & Drink"
        }
    ],
    "sg:phone":"+1 727 322 1199",
    "sg:postcode":"33710",
    "sg:province":"FL",
    "sg:tags":[
        "drinking"
    ],
    "wof:name":"Platinum Vault",
    "wof:placetype":"venue"
},
  "geometry": {"coordinates":[-82.69988499999999,27.786393],"type":"Point"}
}