{
  "type": "Feature",
  "properties": {
    "iso:country":"US",
    "sg:address":"149 Hampton Way",
    "sg:city":"Jupiter",
    "sg:classifiers":[
        {
            "category":"Professional",
            "subcategory":"Management & Consulting",
            "type":"Services"
        }
    ],
    "sg:phone":"+1 561 747 2277",
    "sg:postcode":"33458",
    "sg:province":"FL",
    "sg:tags":[
        "consultant",
        "safety"
    ],
    "wof:name":"Technical Safety Assoc",
    "wof:placetype":"venue"
},
  "geometry": {"coordinates":[-80.111457,26.914151],"type":"Point"}
}