{
  "type": "Feature",
  "properties": {
    "iso:country":"US",
    "sg:address":"765 SW Dalton Cir",
    "sg:city":"Port Saint Lucie",
    "sg:classifiers":[
        {
            "category":"Organizations",
            "subcategory":"Community Association",
            "type":"Services"
        }
    ],
    "sg:phone":"+1 772 336 4343",
    "sg:postcode":"34953",
    "sg:province":"FL",
    "wof:name":"PSL Sons of Italy Number 2594",
    "wof:placetype":"venue"
},
  "geometry": {"coordinates":[-80.37060099999999,27.26301],"type":"Point"}
}