{
  "type": "Feature",
  "properties": {
    "iso:country":"US",
    "sg:address":"3373 NW 107th St",
    "sg:city":"Miami",
    "sg:classifiers":[
        {
            "category":"Professional",
            "subcategory":"Engineering",
            "type":"Services"
        },
        {
            "category":"Retail",
            "subcategory":"Repair Shop",
            "type":"Services"
        }
    ],
    "sg:phone":"+1 305 681 7356",
    "sg:postcode":"33167",
    "sg:province":"FL",
    "sg:tags":[
        "rebuilding",
        "aircraft",
        "maintenance"
    ],
    "sg:website":"http://www.jas-inc.com",
    "wof:name":"Jet Aviation Specialists Inc",
    "wof:placetype":"venue"
},
  "geometry": {"coordinates":[-80.253047,25.871259],"type":"Point"}
}