{
  "type": "Feature",
  "properties": {
    "addr:full":"2218 Thomasville Rd Tallahassee FL 32308",
    "addr:housenumber":"2218",
    "addr:postcode":"32308",
    "addr:street":"Thomasville Rd",
    "iso:country":"US",
    "sg:address":"2218 Thomasville Rd",
    "sg:city":"Tallahassee",
    "sg:classifiers":[
        {
            "category":"Professional",
            "type":"Services"
        }
    ],
    "sg:phone":"+1 850 443 3928",
    "sg:postcode":"32308",
    "sg:province":"FL",
    "wof:name":"Riffraff Culinary Svc",
    "wof:placetype":"venue"
},
  "geometry": {"coordinates":[-84.264111,30.474386],"type":"Point"}
}