{
  "type": "Feature",
  "properties": {
    "iso:country":"US",
    "sg:address":"1715 W International Speedway Blvd",
    "sg:city":"Daytona Beach",
    "sg:classifiers":[
        {
            "category":"Travel",
            "subcategory":"Hotels & Motels",
            "type":"Entertainment"
        }
    ],
    "sg:phone":"+1 386 257 4030",
    "sg:postcode":"32114",
    "sg:province":"FL",
    "sg:website":"www.hoteldaytona.com",
    "wof:name":"Hampton Inn",
    "wof:placetype":"venue"
},
  "geometry": {"coordinates":[-81.066604,29.192993],"type":"Point"}
}