{
  "type": "Feature",
  "properties": {
    "iso:country":"US",
    "sg:address":"212 Admiral Ln",
    "sg:city":"Debary",
    "sg:classifiers":[
        {
            "category":"Professional",
            "type":"Services"
        }
    ],
    "sg:phone":"+1 386 668 6835",
    "sg:postcode":"32713",
    "sg:province":"FL",
    "sg:tags":[
        "establishment"
    ],
    "wof:name":"White & White",
    "wof:placetype":"venue"
},
  "geometry": {"coordinates":[-81.353916,28.883571],"type":"Point"}
}