{
  "type": "Feature",
  "properties": {
    "addr:full":"2374 W Oak Ridge Rd Orlando FL 32809",
    "addr:housenumber":"2374",
    "addr:postcode":"32809",
    "addr:street":"W Oak Ridge Rd",
    "iso:country":"US",
    "sg:address":"2374 W Oak Ridge Rd",
    "sg:city":"Orlando",
    "sg:classifiers":[
        {
            "category":"Shopping",
            "subcategory":"Music",
            "type":"Retail Goods"
        }
    ],
    "sg:phone":"+1 407 854 0707",
    "sg:postcode":"32809",
    "sg:province":"FL",
    "wof:name":"Sonyvan Music",
    "wof:placetype":"venue"
},
  "geometry": {"coordinates":[-81.409147,28.472334],"type":"Point"}
}