{
  "type": "Feature",
  "properties": {
    "iso:country":"US",
    "sg:address":"6501 Arlington Expy",
    "sg:city":"Jacksonville",
    "sg:classifiers":[
        {
            "category":"Manufacturing",
            "subcategory":"Chemicals & Compounds",
            "type":"Manufacturing & Wholesale Goods"
        }
    ],
    "sg:phone":"+1 904 398 8655",
    "sg:postcode":"32211",
    "sg:province":"FL",
    "wof:name":"Vi-Da Laboratory Inc",
    "wof:placetype":"venue"
},
  "geometry": {"coordinates":[-81.58936199999999,30.327776],"type":"Point"}
}