{
  "type": "Feature",
  "properties": {
    "iso:country":"US",
    "sg:address":"5460 Lyons Rd",
    "sg:city":"Pompano Beach",
    "sg:classifiers":[
        {
            "category":"Local Transit",
            "type":"Transportation"
        }
    ],
    "sg:phone":"+1 954 725 6368",
    "sg:postcode":"33073",
    "sg:province":"FL",
    "sg:tags":[
        "passenger"
    ],
    "wof:name":"VIP Limousine Service",
    "wof:placetype":"venue"
},
  "geometry": {"coordinates":[-80.186493,26.296813],"type":"Point"}
}