{
  "type": "Feature",
  "properties": {
    "addr:full":"4401 NW 7th Ave Miami FL 33127",
    "addr:housenumber":"4401",
    "addr:postcode":"33127",
    "addr:street":"Nw 7Th Ave",
    "iso:country":"US",
    "sg:address":"4401 NW 7th Ave",
    "sg:city":"Miami",
    "sg:classifiers":[
        {
            "category":"Place Of Worship",
            "type":"Public Place"
        }
    ],
    "sg:phone":"+1 305 757 1225",
    "sg:postcode":"33127",
    "sg:province":"FL",
    "sg:tags":[
        "church"
    ],
    "wof:name":"Solid Rock Deliverance Center",
    "wof:placetype":"venue"
},
  "geometry": {"coordinates":[-80.207787,25.816035],"type":"Point"}
}