{
  "type": "Feature",
  "properties": {
    "iso:country":"US",
    "sg:address":"3590 Mistletoe Ln",
    "sg:city":"Longboat Key",
    "sg:classifiers":[
        {
            "category":"Real Estate",
            "subcategory":"Developer",
            "type":"Services"
        }
    ],
    "sg:phone":"+1 941 383 7988",
    "sg:postcode":"34228",
    "sg:province":"FL",
    "wof:name":"Fedder Company",
    "wof:placetype":"venue"
},
  "geometry": {"coordinates":[-82.62241299999999,27.381524],"type":"Point"}
}