{
  "type": "Feature",
  "properties": {
    "iso:country":"US",
    "sg:address":"3240 Lipscomb Pl",
    "sg:city":"Orlando",
    "sg:classifiers":[
        {
            "category":"Real Estate",
            "subcategory":"Real Estate Services",
            "type":"Services"
        }
    ],
    "sg:phone":"+1 407 290 9199",
    "sg:postcode":"32805",
    "sg:province":"FL",
    "sg:tags":[
        "management"
    ],
    "wof:name":"Jackson Hudson Corporation",
    "wof:placetype":"venue"
},
  "geometry": {"coordinates":[-81.41954200000001,28.540327],"type":"Point"}
}