{
  "type": "Feature",
  "properties": {
    "addr:full":"217 Azalea Dr Edgewater FL 32141",
    "addr:housenumber":"217",
    "addr:postcode":"32141",
    "addr:street":"Azalea Dr",
    "iso:country":"US",
    "sg:address":"217 Azalea Dr",
    "sg:city":"Edgewater",
    "sg:classifiers":[
        {
            "category":"Utilities",
            "subcategory":"Refuse",
            "type":"Services"
        }
    ],
    "sg:phone":"+1 386 427 2525",
    "sg:postcode":"32141",
    "sg:province":"FL",
    "sg:tags":[
        "truck",
        "dump"
    ],
    "wof:name":"Fbi Florida",
    "wof:placetype":"venue"
},
  "geometry": {"coordinates":[-80.89629499999999,28.969713],"type":"Point"}
}