{
  "type": "Feature",
  "properties": {
    "iso:country":"US",
    "sg:address":"13422 77th Pl N",
    "sg:city":"West Palm Beach",
    "sg:classifiers":[
        {
            "category":"Building & Trades",
            "subcategory":"Landscaping Services",
            "type":"Services"
        }
    ],
    "sg:phone":"+1 561 753 1189",
    "sg:postcode":"33412",
    "sg:province":"FL",
    "sg:tags":[
        "lawn",
        "maintenance",
        "grounds"
    ],
    "wof:name":"Jeff Hauger Enterprises",
    "wof:placetype":"venue"
},
  "geometry": {"coordinates":[-80.2517,26.791112],"type":"Point"}
}