{
  "type": "Feature",
  "properties": {
    "addr:full":"4851 Dairy Rd Melbourne FL 32904",
    "addr:housenumber":"4851",
    "addr:postcode":"32904",
    "addr:street":"Dairy Rd",
    "iso:country":"US",
    "sg:address":"4851 Dairy Rd",
    "sg:city":"Melbourne",
    "sg:classifiers":[
        {
            "category":"Professional",
            "type":"Services"
        }
    ],
    "sg:phone":"+1 321 723 2222",
    "sg:postcode":"32904",
    "sg:province":"FL",
    "sg:tags":[
        "establishment"
    ],
    "wof:name":"City Limits",
    "wof:placetype":"venue"
},
  "geometry": {"coordinates":[-80.638013,28.040508],"type":"Point"}
}