{
  "type": "Feature",
  "properties": {
    "iso:country":"US",
    "sg:address":"2670 S Flamingo Rd",
    "sg:city":"Davie",
    "sg:classifiers":[
        {
            "category":"Retail",
            "subcategory":"Veterinary Services",
            "type":"Services"
        }
    ],
    "sg:phone":"+1 954 916 4903",
    "sg:postcode":"33330",
    "sg:province":"FL",
    "sg:tags":[
        "hospital",
        "animal"
    ],
    "wof:name":"Animal Recreation & Rehab Ctr",
    "wof:placetype":"venue"
},
  "geometry": {"coordinates":[-80.314036,26.075727],"type":"Point"}
}