{
  "type": "Feature",
  "properties": {
    "addr:full":"10698 SW 24th St Miami FL 33165",
    "addr:housenumber":"10698",
    "addr:postcode":"33165",
    "addr:street":"Sw 24Th St",
    "iso:country":"US",
    "sg:address":"10698 SW 24th St",
    "sg:city":"Miami",
    "sg:classifiers":[
        {
            "category":"Autos & Motor Vehicles",
            "subcategory":"Fuel & Gas Station",
            "type":"Retail Goods"
        }
    ],
    "sg:phone":"+1 305 559 2417",
    "sg:postcode":"33165",
    "sg:province":"FL",
    "wof:name":"Ruth Hernandez",
    "wof:placetype":"venue"
},
  "geometry": {"coordinates":[-80.367695,25.746493],"type":"Point"}
}