{
  "type": "Feature",
  "properties": {
    "addr:full":"10381 NW 62nd Dr Pompano Beach FL 33076",
    "addr:housenumber":"10381",
    "addr:postcode":"33076",
    "addr:street":"Nw 62Nd Dr",
    "iso:country":"US",
    "sg:address":"10381 NW 62nd Dr",
    "sg:city":"Pompano Beach",
    "sg:classifiers":[
        {
            "category":"Personal",
            "subcategory":"Beauty Salon",
            "type":"Services"
        }
    ],
    "sg:phone":"+1 954 753 9009",
    "sg:postcode":"33076",
    "sg:province":"FL",
    "sg:tags":[
        "shop"
    ],
    "wof:name":"A Lite Affair Inc",
    "wof:placetype":"venue"
},
  "geometry": {"coordinates":[-80.264966,26.307162],"type":"Point"}
}