{
  "type": "Feature",
  "properties": {
    "addr:full":"901 US Hwy 27 Sebring FL 33870",
    "addr:housenumber":"901",
    "addr:postcode":"33870",
    "addr:street":"Us Hwy 27",
    "iso:country":"US",
    "sg:address":"901 US Hwy 27",
    "sg:city":"Sebring",
    "sg:classifiers":[
        {
            "category":"Shopping",
            "subcategory":"Gifts & Souvenirs",
            "type":"Retail Goods"
        }
    ],
    "sg:phone":"+1 863 471 6006",
    "sg:postcode":"33870",
    "sg:province":"FL",
    "sg:tags":[
        "cards",
        "greeting"
    ],
    "wof:name":"Cindys Hallmark Shop",
    "wof:placetype":"venue"
},
  "geometry": {"coordinates":[-81.472081,27.475337],"type":"Point"}
}