{
  "type": "Feature",
  "properties": {
    "addr:full":"10649 Brighton Hill Cir N Jacksonville FL 32256",
    "addr:housenumber":"10649",
    "addr:postcode":"32256",
    "addr:street":"Brighton Hill Cir N",
    "iso:country":"US",
    "sg:address":"10649 Brighton Hill Cir N",
    "sg:city":"Jacksonville",
    "sg:classifiers":[
        {
            "category":"Wholesale",
            "subcategory":"Construction Materials",
            "type":"Manufacturing & Wholesale Goods"
        }
    ],
    "sg:phone":"+1 904 519 5505",
    "sg:postcode":"32256",
    "sg:province":"FL",
    "sg:tags":[
        "marble"
    ],
    "wof:name":"Mirror Magic",
    "wof:placetype":"venue"
},
  "geometry": {"coordinates":[-81.52392399999999,30.210319],"type":"Point"}
}