{
  "type": "Feature",
  "properties": {
    "iso:country":"US",
    "sg:address":"7526 Banner St",
    "sg:city":"New Port Richey",
    "sg:classifiers":[
        {
            "category":"Arts & Performance",
            "subcategory":"Theater",
            "type":"Entertainment"
        }
    ],
    "sg:phone":"+1 727 842 2101",
    "sg:postcode":"34653",
    "sg:province":"FL",
    "sg:tags":[
        "group"
    ],
    "wof:name":"West Coast Mummers",
    "wof:placetype":"venue"
},
  "geometry": {"coordinates":[-82.689932,28.25552],"type":"Point"}
}