{
  "type": "Feature",
  "properties": {
    "addr:full":"2424 W Oakland Park Blvd Oakland Park FL 33311",
    "addr:housenumber":"2424",
    "addr:postcode":"33311",
    "addr:street":"W Oakland Park Blvd",
    "iso:country":"US",
    "sg:address":"2424 W Oakland Park Blvd",
    "sg:city":"Oakland Park",
    "sg:classifiers":[
        {
            "category":"Professional",
            "subcategory":"Credit Reporting & Collection",
            "type":"Services"
        }
    ],
    "sg:phone":"+1 954 485 4000",
    "sg:postcode":"33311",
    "sg:province":"FL",
    "sg:tags":[
        "agency"
    ],
    "sg:website":"www.usb-inc.com",
    "wof:name":"United Service Bureau",
    "wof:placetype":"venue"
},
  "geometry": {"coordinates":[-80.178871,26.165426],"type":"Point"}
}