{
  "type": "Feature",
  "properties": {
    "iso:country":"US",
    "sg:address":"8505 NW 74th St",
    "sg:city":"Miami",
    "sg:classifiers":[
        {
            "category":"Home & Garden",
            "subcategory":"Household Appliances",
            "type":"Retail Goods"
        },
        {
            "category":"Wholesale",
            "subcategory":"Drugs",
            "type":"Manufacturing & Wholesale Goods"
        },
        {
            "category":"Wholesale",
            "subcategory":"Durable Goods & Equipment",
            "type":"Manufacturing & Wholesale Goods"
        },
        {
            "category":"Organizations",
            "subcategory":"Community Association",
            "type":"Services"
        },
        {
            "category":"Professional",
            "subcategory":"Credit Reporting & Collection",
            "type":"Services"
        }
    ],
    "sg:phone":"+1 305 513 8540",
    "sg:postcode":"33166",
    "sg:province":"FL",
    "sg:tags":[
        "major",
        "industrial",
        "garbage",
        "disposal",
        "commercial",
        "compactors-waste-industrial",
        "appliances-major-wholesale",
        "compactors-waste-household",
        "manufacturer"
    ],
    "sg:website":"http://www.equipcomfg.com",
    "wof:name":"Equipco Manufacturing, Inc.",
    "wof:placetype":"venue"
},
  "geometry": {"coordinates":[-80.337413,25.840737],"type":"Point"}
}