{
  "type": "Feature",
  "properties": {
    "iso:country":"US",
    "sg:address":"221 US Hwy 27",
    "sg:city":"Clermont",
    "sg:classifiers":[
        {
            "category":"Professional",
            "subcategory":"Engineering",
            "type":"Services"
        }
    ],
    "sg:phone":"+1 352 394 8514",
    "sg:postcode":"34711",
    "sg:province":"FL",
    "wof:name":"Knight Engineering Inc",
    "wof:placetype":"venue"
},
  "geometry": {"coordinates":[-81.678697,28.359363],"type":"Point"}
}