{
  "type": "Feature",
  "properties": {
    "iso:country":"US",
    "sg:address":"301 S Monroe St",
    "sg:city":"Tallahassee",
    "sg:classifiers":[
        {
            "category":"Manufacturing",
            "subcategory":"Tools & Machinery",
            "type":"Manufacturing & Wholesale Goods"
        }
    ],
    "sg:phone":"+1 850 488 1350",
    "sg:postcode":"32301",
    "sg:province":"FL",
    "sg:tags":[
        "machine",
        "mfg",
        "general",
        "government"
    ],
    "wof:name":"State Florida Department of",
    "wof:placetype":"venue"
},
  "geometry": {"coordinates":[-84.280664,30.439593],"type":"Point"}
}