{
  "type": "Feature",
  "properties": {
    "iso:country":"US",
    "sg:address":"8841 W Flagler St Ste 113",
    "sg:city":"Miami",
    "sg:classifiers":[
        {
            "category":"Building & Trades",
            "subcategory":"Construction",
            "type":"Services"
        }
    ],
    "sg:phone":"+1 305 968 1311",
    "sg:postcode":"33174",
    "sg:province":"FL",
    "sg:tags":[
        "handyman"
    ],
    "wof:name":"All In One Inspections & Rpr",
    "wof:placetype":"venue"
},
  "geometry": {"coordinates":[-80.339856,25.769557],"type":"Point"}
}