{
  "type": "Feature",
  "properties": {
    "iso:country":"US",
    "sg:address":"530 NE 199th Ter",
    "sg:city":"Miami",
    "sg:classifiers":[
        {
            "category":"Professional",
            "subcategory":"Computer Services",
            "type":"Services"
        }
    ],
    "sg:phone":"+1 305 573 4734",
    "sg:postcode":"33179",
    "sg:province":"FL",
    "sg:tags":[
        "consultant",
        "designer"
    ],
    "wof:name":"Sync Consulting Inc",
    "wof:placetype":"venue"
},
  "geometry": {"coordinates":[-80.189336,25.95832],"type":"Point"}
}