{
  "type": "Feature",
  "properties": {
    "iso:country":"US",
    "sg:address":"7985 113th St N",
    "sg:city":"Seminole",
    "sg:classifiers":[
        {
            "category":"Professional",
            "subcategory":"Lawyer & Legal Services",
            "type":"Services"
        }
    ],
    "sg:phone":"+1 727 398 0086",
    "sg:postcode":"33772",
    "sg:province":"FL",
    "sg:tags":[
        "attorney"
    ],
    "wof:name":"Bryan K Mc Lachlan",
    "wof:placetype":"venue"
},
  "geometry": {"coordinates":[-82.795252,27.845145],"type":"Point"}
}