{
  "type": "Feature",
  "properties": {
    "addr:full":"23 Old Mission Ave St Augustine FL 32084",
    "addr:housenumber":"23",
    "addr:postcode":"32084",
    "addr:street":"Old Mission Ave St",
    "iso:country":"US",
    "sg:address":"23 Old Mission Ave",
    "sg:city":"St Augustine",
    "sg:classifiers":[
        {
            "category":"Personal",
            "type":"Services"
        }
    ],
    "sg:phone":"+1 904 825 3665",
    "sg:postcode":"32084",
    "sg:province":"FL",
    "sg:tags":[
        "therapist",
        "massage"
    ],
    "wof:name":"Melissa Devlin",
    "wof:placetype":"venue"
},
  "geometry": {"coordinates":[-81.319177,29.903886],"type":"Point"}
}