{
  "type": "Feature",
  "properties": {
    "iso:country":"US",
    "sg:address":"6563 Taylor Rd",
    "sg:city":"Naples",
    "sg:classifiers":[
        {
            "category":"Shopping",
            "type":"Retail Goods"
        }
    ],
    "sg:phone":"+1 239 597 9100",
    "sg:postcode":"34109",
    "sg:province":"FL",
    "sg:tags":[
        "product",
        "merchandise",
        "mfg"
    ],
    "wof:name":"Awnings By Naples Awning",
    "wof:placetype":"venue"
},
  "geometry": {"coordinates":[-81.783826,26.224173],"type":"Point"}
}