{
  "type": "Feature",
  "properties": {
    "addr:full":"576 Ave A Satellite Beach FL 32951",
    "addr:housenumber":"576",
    "addr:postcode":"32951",
    "addr:street":"Ave A Satellite Beach",
    "iso:country":"US",
    "sg:address":"576 Ave A",
    "sg:city":"Satellite Beach",
    "sg:classifiers":[
        {
            "category":"Real Estate",
            "subcategory":"Real Estate Agent",
            "type":"Services"
        }
    ],
    "sg:phone":"+1 321 773 4114",
    "sg:postcode":"32951",
    "sg:province":"FL",
    "sg:tags":[
        "appraiser"
    ],
    "wof:name":"Southast Real Prprty Apprisers",
    "wof:placetype":"venue"
},
  "geometry": {"coordinates":[-80.564018,28.069496],"type":"Point"}
}