{
  "type": "Feature",
  "properties": {
    "iso:country":"US",
    "sg:address":"2048 SW 57th Ave",
    "sg:city":"Miami",
    "sg:classifiers":[
        {
            "category":"Shopping",
            "subcategory":"Bicycles & Sporting Goods",
            "type":"Retail Goods"
        },
        {
            "category":"Wholesale",
            "subcategory":"Chemicals & Plastics",
            "type":"Manufacturing & Wholesale Goods"
        },
        {
            "category":"Personal",
            "subcategory":"Sauna",
            "type":"Services"
        }
    ],
    "sg:phone":"+1 305 262 3411",
    "sg:postcode":"33155",
    "sg:province":"FL",
    "sg:tags":[
        "supply",
        "equipment",
        "swimming",
        "supplies-wholesale",
        "pool",
        "manufacturer"
    ],
    "wof:name":"Freddy's Pool Supply",
    "wof:placetype":"venue"
},
  "geometry": {"coordinates":[-80.288427,25.75221],"type":"Point"}
}