{
  "type": "Feature",
  "properties": {
    "addr:full":"1824 Canova St SE Melbourne FL 32909",
    "addr:housenumber":"1824",
    "addr:postcode":"32909",
    "addr:street":"Canova St Se",
    "iso:country":"US",
    "sg:address":"1824 Canova St SE",
    "sg:city":"Melbourne",
    "sg:classifiers":[
        {
            "category":"Home & Garden",
            "subcategory":"Household Appliances",
            "type":"Retail Goods"
        }
    ],
    "sg:phone":"+1 321 984 9865",
    "sg:postcode":"32909",
    "sg:province":"FL",
    "sg:tags":[
        "cleaners",
        "vacuum"
    ],
    "wof:name":"Rainbow Sales & Svc",
    "wof:placetype":"venue"
},
  "geometry": {"coordinates":[-80.616388,27.997292],"type":"Point"}
}