{
  "type": "Feature",
  "properties": {
    "addr:full":"2 E Collins St Umatilla FL 32784",
    "addr:housenumber":"2",
    "addr:postcode":"32784",
    "addr:street":"E Collins St",
    "iso:country":"US",
    "sg:address":"2 E Collins St",
    "sg:city":"Umatilla",
    "sg:classifiers":[
        {
            "category":"Organizations",
            "subcategory":"Religious Organization",
            "type":"Services"
        }
    ],
    "sg:phone":"+1 352 669 2881",
    "sg:postcode":"32784",
    "sg:province":"FL",
    "sg:tags":[
        "church"
    ],
    "wof:name":"Anointed House Of Prayer",
    "wof:placetype":"venue"
},
  "geometry": {"coordinates":[-81.66467900000001,28.934841],"type":"Point"}
}