{
  "type": "Feature",
  "properties": {
    "addr:full":"4747 J P Hall Blvd Green Cove Spgs FL 32043",
    "addr:housenumber":"4747",
    "addr:postcode":"32043",
    "addr:street":"J P Hall Blvd Green Cove Spgs",
    "iso:country":"US",
    "sg:address":"4747 J P Hall Blvd",
    "sg:city":"Green Cove Spgs",
    "sg:classifiers":[
        {
            "category":"Home & Garden",
            "subcategory":"Building Materials",
            "type":"Retail Goods"
        }
    ],
    "sg:phone":"+1 904 284 8464",
    "sg:postcode":"32043",
    "sg:province":"FL",
    "sg:tags":[
        "lumber"
    ],
    "wof:name":"Us Lumber",
    "wof:placetype":"venue"
},
  "geometry": {"coordinates":[-81.67088200000001,29.937403],"type":"Point"}
}