{
  "type": "Feature",
  "properties": {
    "addr:full":"14600 Kendale Lakes Blvd Miami FL 33183",
    "addr:housenumber":"14600",
    "addr:postcode":"33183",
    "addr:street":"Kendale Lakes Blvd",
    "iso:country":"US",
    "sg:address":"14600 Kendale Lakes Blvd",
    "sg:city":"Miami",
    "sg:classifiers":[
        {
            "category":"Education",
            "subcategory":"University",
            "type":"Public Place"
        }
    ],
    "sg:phone":"+1 305 382 2872",
    "sg:postcode":"33183",
    "sg:province":"FL",
    "sg:tags":[
        "college"
    ],
    "wof:name":"South Florida College",
    "wof:placetype":"venue"
},
  "geometry": {"coordinates":[-80.429751,25.690951],"type":"Point"}
}