{
  "type": "Feature",
  "properties": {
    "iso:country":"US",
    "sg:address":"10233 130th St",
    "sg:city":"Largo",
    "sg:classifiers":[
        {
            "category":"Wholesale",
            "subcategory":"Sporting Goods",
            "type":"Manufacturing & Wholesale Goods"
        }
    ],
    "sg:phone":"+1 727 593 5183",
    "sg:postcode":"33774",
    "sg:province":"FL",
    "sg:website":"www.mysporthut.com",
    "wof:name":"MYSPORTHUT.COM",
    "wof:placetype":"venue"
},
  "geometry": {"coordinates":[-82.818397,27.866025],"type":"Point"}
}