{
  "type": "Feature",
  "properties": {
    "addr:full":"385 Nieuport Dr Vero Beach FL 32968",
    "addr:housenumber":"385",
    "addr:postcode":"32968",
    "addr:street":"Nieuport Dr",
    "iso:country":"US",
    "sg:address":"385 Nieuport Dr",
    "sg:city":"Vero Beach",
    "sg:classifiers":[
        {
            "category":"Building & Trades",
            "subcategory":"Electrical",
            "type":"Services"
        }
    ],
    "sg:phone":"+1 772 778 0707",
    "sg:postcode":"32968",
    "sg:province":"FL",
    "sg:tags":[
        "electrical",
        "contractor"
    ],
    "wof:name":"Roys Electrical Services Inc",
    "wof:placetype":"venue"
},
  "geometry": {"coordinates":[-80.498987,27.598382],"type":"Point"}
}