{
  "type": "Feature",
  "properties": {
    "addr:full":"13450 SE 120th St Dunnellon FL 34431",
    "addr:postcode":"13450;34431",
    "addr:street":"Se 120Th St",
    "iso:country":"US",
    "sg:address":"13450 SE 120th St",
    "sg:city":"Dunnellon",
    "sg:classifiers":[
        {
            "category":"Farming",
            "subcategory":"Farm & Veterinary Services",
            "type":"Manufacturing & Wholesale Goods"
        }
    ],
    "sg:phone":"+1 352 489 0013",
    "sg:postcode":"34431",
    "sg:province":"FL",
    "sg:tags":[
        "livestock"
    ],
    "wof:name":"Windy Hills Farm",
    "wof:placetype":"venue"
},
  "geometry": {"coordinates":[-82.541971,29.156265],"type":"Point"}
}