{
  "type": "Feature",
  "properties": {
    "addr:full":"4063 Salisbury Rd Jacksonville FL 32216",
    "addr:housenumber":"4063",
    "addr:postcode":"32216",
    "addr:street":"Salisbury Rd",
    "iso:country":"US",
    "sg:address":"4063 Salisbury Rd",
    "sg:city":"Jacksonville",
    "sg:classifiers":[
        {
            "category":"Health Services",
            "subcategory":"Doctor",
            "type":"Services"
        }
    ],
    "sg:phone":"+1 904 281 0870",
    "sg:postcode":"32216",
    "sg:province":"FL",
    "sg:tags":[
        "physician",
        "radiology",
        "surgeons"
    ],
    "wof:name":"Comprehensive Medical Imaging",
    "wof:placetype":"venue"
},
  "geometry": {"coordinates":[-81.595597,30.255738],"type":"Point"}
}