{
  "type": "Feature",
  "properties": {
    "iso:country":"US",
    "sg:address":"11 Tupelo Ave SE",
    "sg:city":"Fort Walton Bch",
    "sg:classifiers":[
        {
            "category":"Autos & Motor Vehicles",
            "subcategory":"Automobile Sales",
            "type":"Retail Goods"
        }
    ],
    "sg:phone":"+1 850 244 8657",
    "sg:postcode":"32548",
    "sg:province":"FL",
    "sg:tags":[
        "limousine"
    ],
    "wof:name":"City Limousine FWB Inc",
    "wof:placetype":"venue"
},
  "geometry": {"coordinates":[-86.605304,30.411393],"type":"Point"}
}