{
  "type": "Feature",
  "properties": {
    "iso:country":"US",
    "sg:address":"15841 SW 97th Ave",
    "sg:city":"Miami",
    "sg:classifiers":[
        {
            "category":"Personal",
            "type":"Services"
        }
    ],
    "sg:phone":"+1 305 281 9404",
    "sg:postcode":"33157",
    "sg:province":"FL",
    "sg:tags":[
        "local"
    ],
    "wof:name":"Global Lifestyles Inc.",
    "wof:placetype":"venue"
},
  "geometry": {"coordinates":[-80.348287,25.621485],"type":"Point"}
}