{
  "type": "Feature",
  "properties": {
    "iso:country":"US",
    "sg:address":"6001 Argyle Forest Blvd",
    "sg:city":"Jacksonville",
    "sg:classifiers":[
        {
            "category":"Restaurant",
            "type":"Food & Drink"
        }
    ],
    "sg:menulink":"http://www.allmenus.com/fl/jacksonville/155672-philly-connection/menu/",
    "sg:phone":"+1 904 908 0890",
    "sg:postcode":"32244",
    "sg:province":"FL",
    "sg:tags":[
        "cheesesteaks",
        "sandwich",
        "american"
    ],
    "wof:name":"Philly Connection",
    "wof:placetype":"venue"
},
  "geometry": {"coordinates":[-81.742893,30.193578],"type":"Point"}
}