{
  "type": "Feature",
  "properties": {
    "addr:full":"6225 State Hwy 64 Bradenton FL 34208",
    "addr:housenumber":"6225",
    "addr:postcode":"34208",
    "addr:street":"State Hwy 64",
    "iso:country":"US",
    "sg:address":"6225 State Hwy 64",
    "sg:city":"Bradenton",
    "sg:classifiers":[
        {
            "category":"Shopping",
            "type":"Retail Goods"
        }
    ],
    "sg:phone":"+1 941 744 5756",
    "sg:postcode":"34208",
    "sg:province":"FL",
    "sg:tags":[
        "wheel",
        "chair",
        "scooter"
    ],
    "wof:name":"Scooter Store",
    "wof:placetype":"venue"
},
  "geometry": {"coordinates":[-82.489569,27.494186],"type":"Point"}
}