{
  "type": "Feature",
  "properties": {
    "addr:full":"425 Selkirk Dr Winter Park FL 32792",
    "addr:housenumber":"425",
    "addr:postcode":"32792",
    "addr:street":"Selkirk Dr",
    "iso:country":"US",
    "sg:address":"425 Selkirk Dr",
    "sg:city":"Winter Park",
    "sg:classifiers":[
        {
            "category":"Professional",
            "type":"Services"
        }
    ],
    "sg:phone":"+1 407 644 1696",
    "sg:postcode":"32792",
    "sg:province":"FL",
    "sg:tags":[
        "establishment"
    ],
    "wof:name":"Outreach Program Inc",
    "wof:placetype":"venue"
},
  "geometry": {"coordinates":[-81.32426700000001,28.59009],"type":"Point"}
}