{
  "type": "Feature",
  "properties": {
    "iso:country":"US",
    "sg:address":"10670 SW 186th St",
    "sg:city":"Miami",
    "sg:classifiers":[
        {
            "category":"Home & Garden",
            "subcategory":"Furniture",
            "type":"Retail Goods"
        }
    ],
    "sg:phone":"+1 305 251 8516",
    "sg:postcode":"33157",
    "sg:province":"FL",
    "sg:tags":[
        "store"
    ],
    "wof:name":"Marlin Furniture Inc",
    "wof:placetype":"venue"
},
  "geometry": {"coordinates":[-80.364998,25.596001],"type":"Point"}
}