{
  "type": "Feature",
  "properties": {
    "iso:country":"US",
    "sg:address":"9101 Ely St",
    "sg:city":"Pensacola",
    "sg:classifiers":[
        {
            "category":"Manufacturing",
            "subcategory":"Motor Vehicles & Parts",
            "type":"Manufacturing & Wholesale Goods"
        }
    ],
    "sg:phone":"+1 850 476 0907",
    "sg:postcode":"32514",
    "sg:province":"FL",
    "sg:tags":[
        "manufacture",
        "automobile",
        "industrial",
        "component",
        "supply"
    ],
    "wof:name":"Dana Coupled Products",
    "wof:placetype":"venue"
},
  "geometry": {"coordinates":[-87.201641,30.525726],"type":"Point"}
}