{
  "type": "Feature",
  "properties": {
    "iso:country":"US",
    "sg:address":"1505 Henley Rd NW",
    "sg:city":"Palm Bay",
    "sg:classifiers":[
        {
            "category":"Building & Trades",
            "subcategory":"Plumbing",
            "type":"Services"
        }
    ],
    "sg:phone":"+1 321 952 4318",
    "sg:postcode":"32907",
    "sg:province":"FL",
    "sg:tags":[
        "contractor"
    ],
    "wof:name":"National Plumbing Service",
    "wof:placetype":"venue"
},
  "geometry": {"coordinates":[-80.703976,28.03485],"type":"Point"}
}