{
  "type": "Feature",
  "properties": {
    "iso:country":"US",
    "sg:address":"154 Treasure Palm Dr",
    "sg:city":"Panama City Bch",
    "sg:classifiers":[
        {
            "category":"Building & Trades",
            "subcategory":"Pest Control",
            "type":"Services"
        }
    ],
    "sg:phone":"+1 850 596 5306",
    "sg:postcode":"32408",
    "sg:province":"FL",
    "sg:tags":[
        "trapper",
        "animal"
    ],
    "wof:name":"A & H Trapping",
    "wof:placetype":"venue"
},
  "geometry": {"coordinates":[-85.773826,30.175528],"type":"Point"}
}