{
  "type": "Feature",
  "properties": {
    "addr:full":"4332 Boat Club Dr Jacksonville FL 32277",
    "addr:housenumber":"4332",
    "addr:postcode":"32277",
    "addr:street":"Boat Club Dr",
    "iso:country":"US",
    "sg:address":"4332 Boat Club Dr",
    "sg:city":"Jacksonville",
    "sg:classifiers":[
        {
            "category":"Wholesale",
            "subcategory":"Electrical",
            "type":"Manufacturing & Wholesale Goods"
        }
    ],
    "sg:phone":"+1 904 745 1523",
    "sg:postcode":"32277",
    "sg:province":"FL",
    "sg:tags":[
        "telephone"
    ],
    "wof:name":"XETA Technologies Inc",
    "wof:placetype":"venue"
},
  "geometry": {"coordinates":[-81.59594,30.381261],"type":"Point"}
}