{
  "type": "Feature",
  "properties": {
    "addr:full":"20121 SW 91st Ave Miami FL 33189",
    "addr:housenumber":"20121",
    "addr:postcode":"33189",
    "addr:street":"Sw 91St Ave",
    "iso:country":"US",
    "sg:address":"20121 SW 91st Ave",
    "sg:city":"Miami",
    "sg:classifiers":[
        {
            "category":"Real Estate",
            "subcategory":"Real Estate Agent",
            "type":"Services"
        }
    ],
    "sg:phone":"+1 305 234 8887",
    "sg:postcode":"33189",
    "sg:province":"FL",
    "wof:name":"Alpha Omega Intl Realtors",
    "wof:placetype":"venue"
},
  "geometry": {"coordinates":[-80.338813,25.57989],"type":"Point"}
}