{
  "type": "Feature",
  "properties": {
    "addr:full":"1431 Davis Dr Fort Myers FL 33919",
    "addr:housenumber":"1431",
    "addr:postcode":"33919",
    "addr:street":"Davis Dr",
    "iso:country":"US",
    "sg:address":"1431 Davis Dr",
    "sg:city":"Fort Myers",
    "sg:classifiers":[
        {
            "category":"Real Estate",
            "subcategory":"Real Estate Agent",
            "type":"Services"
        }
    ],
    "sg:phone":"+1 239 229 8772",
    "sg:postcode":"33919",
    "sg:province":"FL",
    "sg:tags":[
        "inspection"
    ],
    "wof:name":"Dyron Johnson Home Inspections",
    "wof:placetype":"venue"
},
  "geometry": {"coordinates":[-81.88504399999999,26.592997],"type":"Point"}
}