{
  "type": "Feature",
  "properties": {
    "addr:full":"4456 Inland Ln Orlando FL 32817",
    "addr:housenumber":"4456",
    "addr:postcode":"32817",
    "addr:street":"Inland Ln",
    "iso:country":"US",
    "sg:address":"4456 Inland Ln",
    "sg:city":"Orlando",
    "sg:classifiers":[
        {
            "category":"Professional",
            "subcategory":"Engineering",
            "type":"Services"
        }
    ],
    "sg:phone":"+1 321 972 1355",
    "sg:postcode":"32817",
    "sg:province":"FL",
    "sg:tags":[
        "engineer",
        "structural"
    ],
    "wof:name":"Robelo, Edgard",
    "wof:placetype":"venue"
},
  "geometry": {"coordinates":[-81.27055,28.602647],"type":"Point"}
}