{
  "type": "Feature",
  "properties": {
    "addr:full":"3665 E Bay Dr Ste 176 Largo FL 33771",
    "addr:housenumber":"3665",
    "addr:postcode":"33771",
    "addr:street":"E Bay Dr Ste 176",
    "iso:country":"US",
    "sg:address":"3665 E Bay Dr Ste 176",
    "sg:city":"Largo",
    "sg:classifiers":[
        {
            "category":"Personal",
            "subcategory":"Beauty Salon",
            "type":"Services"
        },
        {
            "category":"Personal",
            "subcategory":"Nail Salon",
            "type":"Services"
        }
    ],
    "sg:phone":"+1 727 530 3262",
    "sg:postcode":"33771",
    "sg:province":"FL",
    "sg:tags":[
        "hair",
        "stylist"
    ],
    "wof:name":"A Fine Hair Studio",
    "wof:placetype":"venue"
},
  "geometry": {"coordinates":[-82.748752,27.916382],"type":"Point"}
}