{
  "type": "Feature",
  "properties": {
    "iso:country":"US",
    "sg:address":"135 Baywood Ave",
    "sg:city":"Longwood",
    "sg:classifiers":[
        {
            "category":"Manufacturing",
            "subcategory":"Apparel",
            "type":"Manufacturing & Wholesale Goods"
        },
        {
            "category":"Shopping",
            "subcategory":"Clothing, Apparel, & Fashions",
            "type":"Retail Goods"
        }
    ],
    "sg:phone":"+1 407 695 0900",
    "sg:postcode":"32750",
    "sg:province":"FL",
    "sg:tags":[
        "mfg",
        "swimwear",
        "outerwear",
        "accessory"
    ],
    "sg:website":"www.ultimateswimwear.com",
    "wof:name":"Ultimate Swimwear Inc",
    "wof:placetype":"venue"
},
  "geometry": {"coordinates":[-81.341078,28.718404],"type":"Point"}
}