{
  "type": "Feature",
  "properties": {
    "iso:country":"US",
    "sg:address":"280 Westshore Plz",
    "sg:city":"Tampa",
    "sg:classifiers":[
        {
            "category":"Shopping",
            "subcategory":"Hobbies, Toys, & Games",
            "type":"Retail Goods"
        }
    ],
    "sg:phone":"+1 813 287 9521",
    "sg:postcode":"33609",
    "sg:province":"FL",
    "wof:name":"Kay Bee Toys",
    "wof:placetype":"venue"
},
  "geometry": {"coordinates":[-82.5274,27.946636],"type":"Point"}
}