{
  "type": "Feature",
  "properties": {
    "addr:full":"8170 Bayshore Rd Fort Myers FL 33917",
    "addr:housenumber":"8170",
    "addr:postcode":"33917",
    "addr:street":"Bayshore Rd",
    "iso:country":"US",
    "sg:address":"8170 Bayshore Rd",
    "sg:city":"Fort Myers",
    "sg:classifiers":[
        {
            "category":"Building & Trades",
            "subcategory":"Construction",
            "type":"Services"
        }
    ],
    "sg:phone":"+1 239 543 0890",
    "sg:postcode":"33917",
    "sg:province":"FL",
    "sg:tags":[
        "water",
        "well",
        "drilling"
    ],
    "wof:name":"Parker & Sons Well Drilling",
    "wof:placetype":"venue"
},
  "geometry": {"coordinates":[-81.822328,26.715001],"type":"Point"}
}