{
  "type": "Feature",
  "properties": {
    "iso:country":"US",
    "sg:address":"4209 NW 20th Ter",
    "sg:city":"Cape Coral",
    "sg:classifiers":[
        {
            "category":"Banks & Credit Unions",
            "subcategory":"Financial Services",
            "type":"Services"
        }
    ],
    "sg:phone":"+1 239 282 8280",
    "sg:postcode":"33993",
    "sg:province":"FL",
    "sg:tags":[
        "investor"
    ],
    "wof:name":"A&G Investments & Rentals Inc",
    "wof:placetype":"venue"
},
  "geometry": {"coordinates":[-82.06098799999999,26.691619],"type":"Point"}
}