{
  "type": "Feature",
  "properties": {
    "iso:country":"US",
    "sg:address":"160 Heron Dr",
    "sg:city":"Melbourne Beach",
    "sg:classifiers":[
        {
            "category":"Building & Trades",
            "subcategory":"Construction",
            "type":"Services"
        }
    ],
    "sg:phone":"+1 321 728 9909",
    "sg:postcode":"32951",
    "sg:province":"FL",
    "sg:tags":[
        "carpenter"
    ],
    "wof:name":"Clyde Hippchen Carpentry",
    "wof:placetype":"venue"
},
  "geometry": {"coordinates":[-80.508076,27.964411],"type":"Point"}
}