{
  "type": "Feature",
  "properties": {
    "addr:full":"4656 Millenia Plaza Way Orlando FL 32839",
    "addr:housenumber":"4656",
    "addr:postcode":"32839",
    "addr:street":"Millenia Plaza Way",
    "iso:country":"US",
    "sg:address":"4656 Millenia Plaza Way",
    "sg:city":"Orlando",
    "sg:classifiers":[
        {
            "category":"Shopping",
            "subcategory":"Bicycles & Sporting Goods",
            "type":"Retail Goods"
        }
    ],
    "sg:phone":"+1 407 345 8288",
    "sg:postcode":"32839",
    "sg:province":"FL",
    "sg:tags":[
        "equipment",
        "golf",
        "supply"
    ],
    "wof:name":"Golfsmith",
    "wof:placetype":"venue"
},
  "geometry": {"coordinates":[-81.428102,28.493501],"type":"Point"}
}