{
  "type": "Feature",
  "properties": {
    "iso:country":"US",
    "sg:address":"1074 W Sample Rd",
    "sg:city":"Pompano Beach",
    "sg:classifiers":[
        {
            "category":"Shopping",
            "subcategory":"Clothing, Apparel, & Fashions",
            "type":"Retail Goods"
        }
    ],
    "sg:phone":"+1 954 785 9785",
    "sg:postcode":"33064",
    "sg:province":"FL",
    "wof:name":"Color Of Brazil",
    "wof:placetype":"venue"
},
  "geometry": {"coordinates":[-80.138295,26.27484],"type":"Point"}
}