{
  "type": "Feature",
  "properties": {
    "iso:country":"US",
    "sg:address":"6024 15th St E",
    "sg:city":"Bradenton",
    "sg:classifiers":[
        {
            "category":"Autos & Motor Vehicles",
            "subcategory":"Automobile Sales",
            "type":"Retail Goods"
        }
    ],
    "sg:phone":"+1 941 756 6171",
    "sg:postcode":"34203",
    "sg:province":"FL",
    "sg:tags":[
        "car",
        "dealer"
    ],
    "wof:name":"M & S Autos Classic Cars",
    "wof:placetype":"venue"
},
  "geometry": {"coordinates":[-82.546755,27.43304],"type":"Point"}
}