{
  "type": "Feature",
  "properties": {
    "addr:full":"740 Pitt St Clermont FL 34711",
    "addr:housenumber":"740",
    "addr:postcode":"34711",
    "addr:street":"Pitt St",
    "iso:country":"US",
    "sg:address":"740 Pitt St",
    "sg:city":"Clermont",
    "sg:classifiers":[
        {
            "category":"Real Estate",
            "subcategory":"Real Estate Services",
            "type":"Services"
        },
        {
            "category":"Real Estate",
            "subcategory":"Real Estate Agent",
            "type":"Services"
        }
    ],
    "sg:phone":"+1 352 978 8506",
    "sg:postcode":"34711",
    "sg:province":"FL",
    "sg:tags":[
        "buyer",
        "broker"
    ],
    "wof:name":"Real Estate Notefinder",
    "wof:placetype":"venue"
},
  "geometry": {"coordinates":[-81.743797,28.5576],"type":"Point"}
}