{
  "type": "Feature",
  "properties": {
    "addr:full":"940 Giant Oak Rd Lakeland FL 33810",
    "addr:housenumber":"940",
    "addr:postcode":"33810",
    "addr:street":"Giant Oak Rd",
    "iso:country":"US",
    "sg:address":"940 Giant Oak Rd",
    "sg:city":"Lakeland",
    "sg:classifiers":[
        {
            "category":"Health Services",
            "subcategory":"Doctor",
            "type":"Services"
        }
    ],
    "sg:phone":"+1 863 683 1516",
    "sg:postcode":"33810",
    "sg:province":"FL",
    "sg:tags":[
        "medical"
    ],
    "wof:name":"Hundley J Roderick MD",
    "wof:placetype":"venue"
},
  "geometry": {"coordinates":[-82.048925,28.050457],"type":"Point"}
}