{
  "type": "Feature",
  "properties": {
    "addr:full":"3304 NW 52 Pl Gainesville FL 32605",
    "addr:housenumber":"3304",
    "addr:postcode":"32605",
    "addr:street":"Nw 52 Pl",
    "iso:country":"US",
    "sg:address":"3304 NW 52 Pl",
    "sg:city":"Gainesville",
    "sg:classifiers":[
        {
            "category":"Building & Trades",
            "subcategory":"Construction",
            "type":"Services"
        }
    ],
    "sg:phone":"+1 352 377 0034",
    "sg:postcode":"32605",
    "sg:province":"FL",
    "sg:tags":[
        "hanging",
        "contractor"
    ],
    "wof:name":"Revitalized Painting",
    "wof:placetype":"venue"
},
  "geometry": {"coordinates":[-82.370266,29.702458],"type":"Point"}
}