{
  "type": "Feature",
  "properties": {
    "iso:country":"US",
    "sg:address":"9400 E Colonial Dr",
    "sg:city":"Orlando",
    "sg:classifiers":[
        {
            "category":"Autos & Motor Vehicles",
            "subcategory":"Fuel & Gas Station",
            "type":"Retail Goods"
        },
        {
            "category":"Food & Beverages",
            "subcategory":"Groceries & Convenience Stores",
            "type":"Retail Goods"
        }
    ],
    "sg:phone":"+1 407 658 2580",
    "sg:postcode":"32817",
    "sg:province":"FL",
    "sg:website":"http://www.sunocoinc.com",
    "wof:name":"Speedway/Sunoco",
    "wof:placetype":"venue"
},
  "geometry": {"coordinates":[-81.257244,28.56831],"type":"Point"}
}