{
  "type": "Feature",
  "properties": {
    "iso:country":"US",
    "sg:address":"438 N Beach St",
    "sg:city":"Daytona Beach",
    "sg:classifiers":[
        {
            "category":"Manufacturing",
            "subcategory":"Apparel",
            "type":"Manufacturing & Wholesale Goods"
        }
    ],
    "sg:phone":"+1 386 252 7770",
    "sg:postcode":"32114",
    "sg:province":"FL",
    "sg:tags":[
        "leather"
    ],
    "sg:website":"www.barneysleather.com",
    "wof:name":"Barney's Leather",
    "wof:placetype":"venue"
},
  "geometry": {"coordinates":[-81.023329,29.221109],"type":"Point"}
}