{
  "type": "Feature",
  "properties": {
    "iso:country":"US",
    "sg:address":"118 Lake Hollingsworth Dr",
    "sg:city":"Lakeland",
    "sg:classifiers":[
        {
            "category":"Farming",
            "subcategory":"Orchard",
            "type":"Manufacturing & Wholesale Goods"
        }
    ],
    "sg:phone":"+1 863 683 4742",
    "sg:postcode":"33801",
    "sg:province":"FL",
    "wof:name":"Rocker Farms Inc",
    "wof:placetype":"venue"
},
  "geometry": {"coordinates":[-81.943337,28.029909],"type":"Point"}
}