{
  "type": "Feature",
  "properties": {
    "addr:full":"17436 Spring Valley Rd Dade City FL 33523",
    "addr:housenumber":"17436",
    "addr:postcode":"33523",
    "addr:street":"Spring Valley Rd",
    "iso:country":"US",
    "sg:address":"17436 Spring Valley Rd",
    "sg:city":"Dade City",
    "sg:classifiers":[
        {
            "category":"Building & Trades",
            "subcategory":"Landscaping Services",
            "type":"Services"
        }
    ],
    "sg:phone":"+1 352 521 3936",
    "sg:postcode":"33523",
    "sg:province":"FL",
    "sg:tags":[
        "lawn",
        "maintenance",
        "grounds"
    ],
    "wof:name":"Renigade Lawn Svc",
    "wof:placetype":"venue"
},
  "geometry": {"coordinates":[-82.24627099999999,28.411571],"type":"Point"}
}