{
  "type": "Feature",
  "properties": {
    "addr:full":"3881 W 16th Ave Hialeah FL 33012",
    "addr:housenumber":"3881",
    "addr:postcode":"33012",
    "addr:street":"W 16Th Ave",
    "iso:country":"US",
    "sg:address":"3881 W 16th Ave",
    "sg:city":"Hialeah",
    "sg:classifiers":[
        {
            "category":"Autos & Motor Vehicles",
            "subcategory":"Auto Supplies",
            "type":"Retail Goods"
        }
    ],
    "sg:phone":"+1 786 313 0066",
    "sg:postcode":"33012",
    "sg:province":"FL",
    "sg:tags":[
        "tire"
    ],
    "wof:name":"Cash & Carry Rims & Tires Inc",
    "wof:placetype":"venue"
},
  "geometry": {"coordinates":[-80.314531,25.857154],"type":"Point"}
}