{
  "type": "Feature",
  "properties": {
    "iso:country":"US",
    "sg:address":"41 NE 1st Ct",
    "sg:city":"Dania",
    "sg:classifiers":[
        {
            "category":"Organizations",
            "subcategory":"Community Association",
            "type":"Services"
        }
    ],
    "sg:phone":"+1 954 921 7532",
    "sg:postcode":"33004",
    "sg:province":"FL",
    "sg:tags":[
        "teachers'",
        "agency"
    ],
    "wof:name":"Marshall Libre",
    "wof:placetype":"venue"
},
  "geometry": {"coordinates":[-80.14214,26.053137],"type":"Point"}
}