{
  "type": "Feature",
  "properties": {
    "iso:country":"US",
    "sg:address":"4462 Lafayette St",
    "sg:city":"Marianna",
    "sg:classifiers":[
        {
            "category":"Autos & Motor Vehicles",
            "subcategory":"Auto Supplies",
            "type":"Retail Goods"
        },
        {
            "category":"Retail",
            "subcategory":"Auto Repair",
            "type":"Services"
        }
    ],
    "sg:phone":"+1 850 482 3230",
    "sg:postcode":"32446",
    "sg:province":"FL",
    "sg:tags":[
        "wheel",
        "brake",
        "tire"
    ],
    "wof:name":"Marianna Tire Pros",
    "wof:placetype":"venue"
},
  "geometry": {"coordinates":[-85.22374000000001,30.773991],"type":"Point"}
}