{
  "type": "Feature",
  "properties": {
    "iso:country":"US",
    "sg:address":"2850 Tigertail Ave",
    "sg:city":"Miami",
    "sg:classifiers":[
        {
            "category":"Professional",
            "type":"Services"
        }
    ],
    "sg:phone":"+1 305 856 7995",
    "sg:postcode":"33133",
    "sg:province":"FL",
    "sg:tags":[
        "establishment"
    ],
    "wof:name":"Dg Systems Inc",
    "wof:placetype":"venue"
},
  "geometry": {"coordinates":[-80.239383,25.730036],"type":"Point"}
}