{
  "type": "Feature",
  "properties": {
    "addr:full":"3721 W Tacon St Tampa FL 33629",
    "addr:housenumber":"3721",
    "addr:postcode":"33629",
    "addr:street":"W Tacon St",
    "iso:country":"US",
    "sg:address":"3721 W Tacon St",
    "sg:city":"Tampa",
    "sg:classifiers":[
        {
            "category":"Organizations",
            "subcategory":"Religious Organization",
            "type":"Services"
        }
    ],
    "sg:phone":"+1 813 832 3018",
    "sg:postcode":"33629",
    "sg:province":"FL",
    "sg:tags":[
        "synagogue"
    ],
    "wof:name":"Young Isreal of Tampa Inc",
    "wof:placetype":"venue"
},
  "geometry": {"coordinates":[-82.50564799999999,27.916403],"type":"Point"}
}