{
  "type": "Feature",
  "properties": {
    "iso:country":"US",
    "sg:address":"4273 Cavehill Rd",
    "sg:city":"Spring Hill",
    "sg:classifiers":[
        {
            "category":"Professional",
            "subcategory":"Research",
            "type":"Services"
        }
    ],
    "sg:phone":"+1 352 596 2090",
    "sg:postcode":"34606",
    "sg:province":"FL",
    "sg:tags":[
        "development",
        "laboratory"
    ],
    "wof:name":"Qax Intl Systems",
    "wof:placetype":"venue"
},
  "geometry": {"coordinates":[-82.594285,28.492462],"type":"Point"}
}