{
  "type": "Feature",
  "properties": {
    "addr:full":"11210 Cortez Blvd Brooksville FL 34613",
    "addr:housenumber":"11210",
    "addr:postcode":"34613",
    "addr:street":"Cortez Blvd",
    "iso:country":"US",
    "sg:address":"11210 Cortez Blvd",
    "sg:city":"Brooksville",
    "sg:classifiers":[
        {
            "category":"Travel",
            "subcategory":"Campground",
            "type":"Entertainment"
        }
    ],
    "sg:phone":"+1 352 596 6082",
    "sg:postcode":"34613",
    "sg:province":"FL",
    "sg:tags":[
        "camp"
    ],
    "wof:name":"Sand Hill Scout Reservation",
    "wof:placetype":"venue"
},
  "geometry": {"coordinates":[-82.511771,28.533586],"type":"Point"}
}