{
  "type": "Feature",
  "properties": {
    "iso:country":"US",
    "sg:address":"10433 Co Rd 39",
    "sg:city":"Lithia",
    "sg:classifiers":[
        {
            "category":"Professional",
            "subcategory":"Management & Consulting",
            "type":"Services"
        }
    ],
    "sg:phone":"+1 813 677 1303",
    "sg:postcode":"33547",
    "sg:province":"FL",
    "sg:tags":[
        "retail",
        "direct",
        "sales"
    ],
    "wof:name":"Katie Jeans Ice Cream & Deli",
    "wof:placetype":"venue"
},
  "geometry": {"coordinates":[-82.14559800000001,27.85664],"type":"Point"}
}