{
  "type": "Feature",
  "properties": {
    "addr:full":"5751 NW 151st St Hialeah FL 33014",
    "addr:housenumber":"5751",
    "addr:postcode":"33014",
    "addr:street":"Nw 151St St",
    "iso:country":"US",
    "sg:address":"5751 NW 151st St",
    "sg:city":"Hialeah",
    "sg:classifiers":[
        {
            "category":"Professional",
            "subcategory":"Management & Consulting",
            "type":"Services"
        }
    ],
    "sg:phone":"+1 305 821 4500",
    "sg:postcode":"33014",
    "sg:province":"FL",
    "sg:tags":[
        "consultant",
        "security",
        "system"
    ],
    "sg:website":"www.crowlatinamerica.com",
    "wof:name":"Celltronic Corp",
    "wof:placetype":"venue"
},
  "geometry": {"coordinates":[-80.29694499999999,25.910836],"type":"Point"}
}