{
  "type": "Feature",
  "properties": {
    "iso:country":"US",
    "sg:address":"1434 Ridge St",
    "sg:city":"Kissimmee",
    "sg:classifiers":[
        {
            "category":"Professional",
            "subcategory":"Advertising",
            "type":"Services"
        }
    ],
    "sg:phone":"+1 407 290 6600",
    "sg:postcode":"34744",
    "sg:province":"FL",
    "wof:name":"Alpine Productions",
    "wof:placetype":"venue"
},
  "geometry": {"coordinates":[-81.38723299999999,28.339693],"type":"Point"}
}