{
  "type": "Feature",
  "properties": {
    "iso:country":"US",
    "sg:address":"5900 American Way",
    "sg:city":"Orlando",
    "sg:classifiers":[
        {
            "category":"Travel",
            "subcategory":"Travel Agent",
            "type":"Entertainment"
        }
    ],
    "sg:phone":"+1 407 352 8687",
    "sg:postcode":"32819",
    "sg:province":"FL",
    "sg:tags":[
        "tours",
        "promoter"
    ],
    "wof:name":"Abner Tours",
    "wof:placetype":"venue"
},
  "geometry": {"coordinates":[-81.462535,28.462286],"type":"Point"}
}