{
  "type": "Feature",
  "properties": {
    "iso:country":"US",
    "sg:address":"1536 Cypress Ave",
    "sg:city":"Melbourne",
    "sg:classifiers":[
        {
            "category":"Wholesale",
            "subcategory":"Medical Equipment & Supplies",
            "type":"Manufacturing & Wholesale Goods"
        }
    ],
    "sg:phone":"+1 321 255 5549",
    "sg:postcode":"32935",
    "sg:province":"FL",
    "sg:tags":[
        "physician",
        "surgeon"
    ],
    "sg:website":"http://www.nationwidewheelchairlift.com",
    "wof:name":"Nationwide Wheelchair",
    "wof:placetype":"venue"
},
  "geometry": {"coordinates":[-80.63271400000001,28.132064],"type":"Point"}
}