{
  "type": "Feature",
  "properties": {
    "iso:country":"US",
    "sg:address":"3386 S Douglas Rd",
    "sg:city":"Miami",
    "sg:classifiers":[
        {
            "category":"Professional",
            "subcategory":"Accounting & Tax Preparation",
            "type":"Services"
        }
    ],
    "sg:phone":"+1 786 552 1064",
    "sg:postcode":"33133",
    "sg:province":"FL",
    "sg:tags":[
        "bookkeeping",
        "return",
        "representative",
        "preparation-business",
        "taxes-consultants"
    ],
    "sg:website":"http://www.jacksonhewitt.com/",
    "wof:name":"Jackson Hewitt Tax Service",
    "wof:placetype":"venue"
},
  "geometry": {"coordinates":[-80.253591,25.727938],"type":"Point"}
}