{
  "type": "Feature",
  "properties": {
    "addr:full":"390 W Sample Rd Pompano Beach FL 33064",
    "addr:housenumber":"390",
    "addr:postcode":"33064",
    "addr:street":"W Sample Rd",
    "iso:country":"US",
    "sg:address":"390 W Sample Rd",
    "sg:city":"Pompano Beach",
    "sg:classifiers":[
        {
            "category":"Autos & Motor Vehicles",
            "subcategory":"Fuel & Gas Station",
            "type":"Retail Goods"
        }
    ],
    "sg:phone":"+1 954 785 0810",
    "sg:postcode":"33064",
    "sg:province":"FL",
    "sg:tags":[
        "station",
        "gasoline"
    ],
    "wof:name":"Crystal Lake Chevron",
    "wof:placetype":"venue"
},
  "geometry": {"coordinates":[-80.129012,26.274865],"type":"Point"}
}