{
  "type": "Feature",
  "properties": {
    "addr:full":"250 Terry Dr Pensacola FL 32503",
    "addr:housenumber":"250",
    "addr:postcode":"32503",
    "addr:street":"Terry Dr",
    "iso:country":"US",
    "sg:address":"250 Terry Dr",
    "sg:city":"Pensacola",
    "sg:classifiers":[
        {
            "category":"Building & Trades",
            "subcategory":"Construction",
            "type":"Services"
        }
    ],
    "sg:phone":"+1 850 478 4761",
    "sg:postcode":"32503",
    "sg:province":"FL",
    "sg:tags":[
        "contractor"
    ],
    "wof:name":"Total Construction",
    "wof:placetype":"venue"
},
  "geometry": {"coordinates":[-87.260462,30.501642],"type":"Point"}
}