{
  "type": "Feature",
  "properties": {
    "addr:full":"6720 Winkler Rd Fort Myers FL 33919",
    "addr:housenumber":"6720",
    "addr:postcode":"33919",
    "addr:street":"Winkler Rd",
    "iso:country":"US",
    "sg:address":"6720 Winkler Rd",
    "sg:city":"Fort Myers",
    "sg:classifiers":[
        {
            "category":"Building & Trades",
            "subcategory":"Construction",
            "type":"Services"
        }
    ],
    "sg:phone":"+1 239 433 1112",
    "sg:postcode":"33919",
    "sg:province":"FL",
    "sg:tags":[
        "contractor"
    ],
    "sg:website":"www.marvin-homes.com",
    "wof:name":"Marvin Development Corp",
    "wof:placetype":"venue"
},
  "geometry": {"coordinates":[-81.898399,26.5443],"type":"Point"}
}