{
  "type": "Feature",
  "properties": {
    "iso:country":"US",
    "sg:address":"251 N Congress Ave",
    "sg:city":"Delray Beach",
    "sg:classifiers":[
        {
            "category":"Home & Garden",
            "subcategory":"Building Materials",
            "type":"Retail Goods"
        }
    ],
    "sg:phone":"+1 561 278 6855",
    "sg:postcode":"33445",
    "sg:province":"FL",
    "sg:tags":[
        "plumbing",
        "fixture",
        "supply"
    ],
    "sg:website":"www.noland.com",
    "wof:name":"Noland Co",
    "wof:placetype":"venue"
},
  "geometry": {"coordinates":[-80.093498,26.467792],"type":"Point"}
}