{
  "type": "Feature",
  "properties": {
    "iso:country":"US",
    "sg:address":"7532 NW 86th Ter",
    "sg:city":"Fort Lauderdale",
    "sg:classifiers":[
        {
            "category":"Professional",
            "type":"Services"
        }
    ],
    "sg:phone":"+1 954 341 4575",
    "sg:postcode":"33321",
    "sg:province":"FL",
    "wof:name":"David G Cardona Inc",
    "wof:placetype":"venue"
},
  "geometry": {"coordinates":[-80.269711,26.218339],"type":"Point"}
}