{
  "type": "Feature",
  "properties": {
    "addr:full":"3326 N Miami Ave Miami FL 33127",
    "addr:housenumber":"3326",
    "addr:postcode":"33127",
    "addr:street":"N Miami Ave",
    "iso:country":"US",
    "sg:address":"3326 N Miami Ave",
    "sg:city":"Miami",
    "sg:classifiers":[
        {
            "category":"Arts & Performance",
            "subcategory":"Art Gallery",
            "type":"Entertainment"
        }
    ],
    "sg:phone":"+1 305 576 1645",
    "sg:postcode":"33127",
    "sg:province":"FL",
    "wof:name":"More Than Decor",
    "wof:placetype":"venue"
},
  "geometry": {"coordinates":[-80.19538799999999,25.807663],"type":"Point"}
}