{
  "type": "Feature",
  "properties": {
    "addr:full":"6943 Gall Blvd Zephyrhills FL 33542",
    "addr:housenumber":"6943",
    "addr:postcode":"33542",
    "addr:street":"Gall Blvd",
    "iso:country":"US",
    "sg:address":"6943 Gall Blvd",
    "sg:city":"Zephyrhills",
    "sg:classifiers":[
        {
            "category":"Shopping",
            "subcategory":"Florist",
            "type":"Retail Goods"
        }
    ],
    "sg:phone":"+1 813 788 0221",
    "sg:postcode":"33542",
    "sg:province":"FL",
    "wof:name":"Flowers & More",
    "wof:placetype":"venue"
},
  "geometry": {"coordinates":[-82.188256,28.257758],"type":"Point"}
}