{
  "type": "Feature",
  "properties": {
    "iso:country":"US",
    "sg:address":"10356 NW 55th St",
    "sg:city":"Fort Lauderdale",
    "sg:classifiers":[
        {
            "category":"Health Services",
            "subcategory":"Clinic",
            "type":"Services"
        }
    ],
    "sg:phone":"+1 954 572 8164",
    "sg:postcode":"33351",
    "sg:province":"FL",
    "sg:tags":[
        "repair"
    ],
    "wof:name":"Morgan Screening Inc",
    "wof:placetype":"venue"
},
  "geometry": {"coordinates":[-80.287237,26.192544],"type":"Point"}
}