{
  "type": "Feature",
  "properties": {
    "iso:country":"US",
    "sg:address":"2326 N University Dr",
    "sg:city":"Pompano Beach",
    "sg:classifiers":[
        {
            "category":"Shopping",
            "subcategory":"Clothing, Apparel, & Fashions",
            "type":"Retail Goods"
        }
    ],
    "sg:phone":"+1 954 753 0538",
    "sg:postcode":"33065",
    "sg:province":"FL",
    "sg:tags":[
        "family"
    ],
    "wof:name":"Sewinn Inn",
    "wof:placetype":"venue"
},
  "geometry": {"coordinates":[-80.24992399999999,26.262206],"type":"Point"}
}