{
  "type": "Feature",
  "properties": {
    "iso:country":"US",
    "sg:address":"541 E State Road 434",
    "sg:city":"Winter Springs",
    "sg:classifiers":[
        {
            "category":"Restaurant",
            "type":"Food & Drink"
        }
    ],
    "sg:phone":"+1 407 327 5155",
    "sg:postcode":"32708",
    "sg:province":"FL",
    "sg:tags":[
        "italian"
    ],
    "sg:website":"www.papatonysrestaurant.com",
    "wof:name":"Papa Tony's Italian Restaurant",
    "wof:placetype":"venue"
},
  "geometry": {"coordinates":[-81.297203,28.701],"type":"Point"}
}