{
  "type": "Feature",
  "properties": {
    "iso:country":"US",
    "sg:address":"2109 W Memorial Blvd",
    "sg:city":"Lakeland",
    "sg:phone":"+1 863 412 9326",
    "sg:postcode":"33815",
    "sg:province":"FL",
    "sg:tags":[
        "equipment",
        "commercial"
    ],
    "wof:name":"Carmen Padilla",
    "wof:placetype":"venue"
},
  "geometry": {"coordinates":[-81.99100199999999,28.054867],"type":"Point"}
}