{
  "type": "Feature",
  "properties": {
    "iso:country":"US",
    "sg:address":"3304 Soutel Dr",
    "sg:city":"Jacksonville",
    "sg:classifiers":[
        {
            "category":"Social Services",
            "subcategory":"Child Care",
            "type":"Services"
        }
    ],
    "sg:phone":"+1 904 713 0879",
    "sg:postcode":"32208",
    "sg:province":"FL",
    "wof:name":"Kreative Kidz Day Care",
    "wof:placetype":"venue"
},
  "geometry": {"coordinates":[-81.70336500000001,30.404488],"type":"Point"}
}