{
  "type": "Feature",
  "properties": {
    "addr:full":"1551 Global Ct Sarasota FL 34240",
    "addr:housenumber":"1551",
    "addr:postcode":"34240",
    "addr:street":"Global Ct",
    "iso:country":"US",
    "sg:address":"1551 Global Ct",
    "sg:city":"Sarasota",
    "sg:classifiers":[
        {
            "category":"Professional",
            "subcategory":"Research",
            "type":"Services"
        }
    ],
    "sg:phone":"+1 941 371 9858",
    "sg:postcode":"34240",
    "sg:province":"FL",
    "sg:tags":[
        "environmental",
        "ecological"
    ],
    "wof:name":"Geo Environmental",
    "wof:placetype":"venue"
},
  "geometry": {"coordinates":[-82.40606699999999,27.353205],"type":"Point"}
}