{
  "type": "Feature",
  "properties": {
    "iso:country":"US",
    "sg:address":"2444 S Nova Rd",
    "sg:city":"Daytona Beach",
    "sg:classifiers":[
        {
            "category":"Retail",
            "subcategory":"Auto Repair",
            "type":"Services"
        }
    ],
    "sg:phone":"+1 386 788 0012",
    "sg:postcode":"32119",
    "sg:province":"FL",
    "sg:tags":[
        "marina",
        "automotive",
        "general",
        "op"
    ],
    "wof:name":"Nova Rv Sales & Storage",
    "wof:placetype":"venue"
},
  "geometry": {"coordinates":[-81.022189,29.1589],"type":"Point"}
}