{
  "type": "Feature",
  "properties": {
    "iso:country":"US",
    "sg:address":"10358 S Hwy 71",
    "sg:city":"Wewahitchka",
    "sg:classifiers":[
        {
            "category":"Recreation",
            "type":"Entertainment"
        }
    ],
    "sg:phone":"+1 850 827 4299",
    "sg:postcode":"32465",
    "sg:province":"FL",
    "sg:tags":[
        "guide"
    ],
    "wof:name":"Broke-A-Toe Outdoor Guide Svc",
    "wof:placetype":"venue"
},
  "geometry": {"coordinates":[-85.18438999999999,29.946021],"type":"Point"}
}