{
  "type": "Feature",
  "properties": {
    "iso:country":"US",
    "sg:address":"5956 NE 4th Ave",
    "sg:city":"Miami",
    "sg:classifiers":[
        {
            "category":"Retail",
            "subcategory":"Repair Shop",
            "type":"Services"
        }
    ],
    "sg:phone":"+1 305 759 6951",
    "sg:postcode":"33137",
    "sg:province":"FL",
    "sg:tags":[
        "furniture"
    ],
    "wof:name":"Genes Furniture Service",
    "wof:placetype":"venue"
},
  "geometry": {"coordinates":[-80.188233,25.831478],"type":"Point"}
}