{
  "type": "Feature",
  "properties": {
    "addr:full":"6425 NW 109th Ave Miami FL 33178",
    "addr:housenumber":"6425",
    "addr:postcode":"33178",
    "addr:street":"Nw 109Th Ave",
    "iso:country":"US",
    "sg:address":"6425 NW 109th Ave",
    "sg:city":"Miami",
    "sg:classifiers":[
        {
            "category":"Wholesale",
            "subcategory":"Electrical",
            "type":"Manufacturing & Wholesale Goods"
        }
    ],
    "sg:phone":"+1 305 594 3711",
    "sg:postcode":"33178",
    "sg:province":"FL",
    "sg:tags":[
        "electronic"
    ],
    "wof:name":"Blue Laser Corp",
    "wof:placetype":"venue"
},
  "geometry": {"coordinates":[-80.373419,25.831359],"type":"Point"}
}