{
  "type": "Feature",
  "properties": {
    "addr:full":"9317 Sacramento Dr New Port Richey FL 34655",
    "addr:housenumber":"9317",
    "addr:postcode":"34655",
    "addr:street":"Sacramento Dr",
    "iso:country":"US",
    "sg:address":"9317 Sacramento Dr",
    "sg:city":"New Port Richey",
    "sg:classifiers":[
        {
            "category":"Building & Trades",
            "subcategory":"Equipment Rental",
            "type":"Services"
        }
    ],
    "sg:phone":"+1 727 376 5965",
    "sg:postcode":"34655",
    "sg:province":"FL",
    "wof:name":"Sacramento Leasing Inc",
    "wof:placetype":"venue"
},
  "geometry": {"coordinates":[-82.660781,28.222661],"type":"Point"}
}