{
  "type": "Feature",
  "properties": {
    "iso:country":"US",
    "sg:address":"3854 SE Fairway E",
    "sg:city":"Stuart",
    "sg:classifiers":[
        {
            "category":"Health Services",
            "subcategory":"Clinic",
            "type":"Services"
        }
    ],
    "sg:phone":"+1 772 287 2100",
    "sg:postcode":"34997",
    "sg:province":"FL",
    "sg:tags":[
        "hypnotherapy"
    ],
    "wof:name":"Adventures In Recovery",
    "wof:placetype":"venue"
},
  "geometry": {"coordinates":[-80.19894600000001,27.159482],"type":"Point"}
}