{
  "type": "Feature",
  "properties": {
    "addr:full":"2906 Santa Barbara Blvd Naples FL 34116",
    "addr:housenumber":"2906",
    "addr:postcode":"34116",
    "addr:street":"Santa Barbara Blvd",
    "iso:country":"US",
    "sg:address":"2906 Santa Barbara Blvd",
    "sg:city":"Naples",
    "sg:classifiers":[
        {
            "category":"Personal",
            "subcategory":"Beauty Salon",
            "type":"Services"
        }
    ],
    "sg:phone":"+1 239 455 2944",
    "sg:postcode":"34116",
    "sg:province":"FL",
    "sg:tags":[
        "shop",
        "barber",
        "combined"
    ],
    "wof:name":"A Cut Above of Naples Inc",
    "wof:placetype":"venue"
},
  "geometry": {"coordinates":[-81.718756,26.173322],"type":"Point"}
}