{
  "type": "Feature",
  "properties": {
    "addr:full":"409 Cresap St Lakeland FL 33815",
    "addr:housenumber":"409",
    "addr:postcode":"33815",
    "addr:street":"Cresap St",
    "iso:country":"US",
    "sg:address":"409 Cresap St",
    "sg:city":"Lakeland",
    "sg:classifiers":[
        {
            "category":"Shopping",
            "subcategory":"Beauty & Cosmetics",
            "type":"Retail Goods"
        }
    ],
    "sg:phone":"+1 863 682 4072",
    "sg:postcode":"33815",
    "sg:province":"FL",
    "sg:tags":[
        "merchandise"
    ],
    "wof:name":"Joyce L Brennan",
    "wof:placetype":"venue"
},
  "geometry": {"coordinates":[-81.96111000000001,28.033305],"type":"Point"}
}