{
  "type": "Feature",
  "properties": {
    "addr:full":"330 S Jefferson St Pensacola FL 32502",
    "addr:housenumber":"330",
    "addr:postcode":"32502",
    "addr:street":"S Jefferson St",
    "iso:country":"US",
    "sg:address":"330 S Jefferson St",
    "sg:city":"Pensacola",
    "sg:classifiers":[
        {
            "category":"Government",
            "subcategory":"Office",
            "type":"Public Place"
        }
    ],
    "sg:phone":"+1 850 595 5990",
    "sg:postcode":"32502",
    "sg:province":"FL",
    "wof:name":"T T Wentworth Museum",
    "wof:placetype":"venue"
},
  "geometry": {"coordinates":[-87.213583,30.410219],"type":"Point"}
}