{
  "type": "Feature",
  "properties": {
    "iso:country":"US",
    "sg:address":"4415 N Armenia Ave",
    "sg:city":"Tampa",
    "sg:classifiers":[
        {
            "category":"Professional",
            "subcategory":"Accounting & Tax Preparation",
            "type":"Services"
        }
    ],
    "sg:phone":"+1 813 348 0834",
    "sg:postcode":"33603",
    "sg:province":"FL",
    "sg:tags":[
        "consultant"
    ],
    "wof:name":"Diaz & Diaz Svc",
    "wof:placetype":"venue"
},
  "geometry": {"coordinates":[-82.484593,27.98154],"type":"Point"}
}