{
  "type": "Feature",
  "properties": {
    "iso:country":"US",
    "sg:address":"4533 Ponce De Leon Blvd",
    "sg:city":"Coral Gables",
    "sg:classifiers":[
        {
            "category":"Real Estate",
            "subcategory":"Architect",
            "type":"Services"
        }
    ],
    "sg:phone":"+1 305 740 5442",
    "sg:postcode":"33146",
    "sg:province":"FL",
    "wof:name":"Behar Font & Partners",
    "wof:placetype":"venue"
},
  "geometry": {"coordinates":[-80.258499,25.73],"type":"Point"}
}