{
  "type": "Feature",
  "properties": {
    "addr:full":"4501 N Ocean Blvd Boca Raton FL 33431",
    "addr:housenumber":"4501",
    "addr:postcode":"33431",
    "addr:street":"N Ocean Blvd",
    "iso:country":"US",
    "sg:address":"4501 N Ocean Blvd",
    "sg:city":"Boca Raton",
    "sg:classifiers":[
        {
            "category":"Shopping",
            "subcategory":"Pharmacy",
            "type":"Retail Goods"
        }
    ],
    "sg:phone":"+1 561 367 0544",
    "sg:postcode":"33431",
    "sg:province":"FL",
    "wof:name":"Body Rx Naples & Boca Raton",
    "wof:placetype":"venue"
},
  "geometry": {"coordinates":[-80.06730399999999,26.387168],"type":"Point"}
}