{
  "type": "Feature",
  "properties": {
    "addr:full":"504 NE 19th St Fort Lauderdale FL 33305",
    "addr:housenumber":"504",
    "addr:postcode":"33305",
    "addr:street":"Ne 19Th St",
    "iso:country":"US",
    "sg:address":"504 NE 19th St",
    "sg:city":"Fort Lauderdale",
    "sg:classifiers":[
        {
            "category":"Building & Trades",
            "subcategory":"Construction",
            "type":"Services"
        }
    ],
    "sg:phone":"+1 954 566 8724",
    "sg:postcode":"33305",
    "sg:province":"FL",
    "sg:tags":[
        "house"
    ],
    "wof:name":"Ji Dial Construction",
    "wof:placetype":"venue"
},
  "geometry": {"coordinates":[-80.138164,26.151962],"type":"Point"}
}