{
  "type": "Feature",
  "properties": {
    "iso:country":"US",
    "sg:address":"1615 N Federal Hwy",
    "sg:city":"Fort Lauderdale",
    "sg:classifiers":[
        {
            "category":"Coffee & Tea",
            "type":"Food & Drink"
        }
    ],
    "sg:menulink":"http://www.allmenus.com/fl/fort-lauderdale/116784-starbucks-coffee/menu/",
    "sg:phone":"+1 954 564 9775",
    "sg:postcode":"33305",
    "sg:province":"FL",
    "sg:tags":[
        "american"
    ],
    "wof:name":"Starbucks Coffee",
    "wof:placetype":"venue"
},
  "geometry": {"coordinates":[-80.11984200000001,26.149331],"type":"Point"}
}