{
  "type": "Feature",
  "properties": {
    "iso:country":"US",
    "sg:address":"8105 SW 16 Pl",
    "sg:city":"Gainesville",
    "sg:classifiers":[
        {
            "category":"Travel",
            "subcategory":"Hotels & Motels",
            "type":"Entertainment"
        }
    ],
    "sg:phone":"+1 352 331 6272",
    "sg:postcode":"32607",
    "sg:province":"FL",
    "sg:tags":[
        "operation"
    ],
    "wof:name":"Florida Motel",
    "wof:placetype":"venue"
},
  "geometry": {"coordinates":[-82.427661,29.637339],"type":"Point"}
}