{
  "type": "Feature",
  "properties": {
    "addr:full":"1595 Greens Dairy Rd Deland FL 32720",
    "addr:housenumber":"1595",
    "addr:postcode":"32720",
    "addr:street":"Greens Dairy Rd",
    "iso:country":"US",
    "sg:address":"1595 Greens Dairy Rd",
    "sg:city":"Deland",
    "sg:classifiers":[
        {
            "category":"Building & Trades",
            "subcategory":"Construction",
            "type":"Services"
        }
    ],
    "sg:phone":"+1 386 561 0301",
    "sg:postcode":"32720",
    "sg:province":"FL",
    "sg:tags":[
        "excavation",
        "grading",
        "contractor"
    ],
    "wof:name":"Clifton Groundworks, Inc.",
    "wof:placetype":"venue"
},
  "geometry": {"coordinates":[-81.335337,29.056966],"type":"Point"}
}