{
  "type": "Feature",
  "properties": {
    "addr:full":"127 NW 20th St Miami FL 33127",
    "addr:housenumber":"127",
    "addr:postcode":"33127",
    "addr:street":"Nw 20Th St",
    "iso:country":"US",
    "sg:address":"127 NW 20th St",
    "sg:city":"Miami",
    "sg:classifiers":[
        {
            "category":"Food & Beverages",
            "subcategory":"Groceries & Convenience Stores",
            "type":"Retail Goods"
        }
    ],
    "sg:phone":"+1 305 576 7093",
    "sg:postcode":"33127",
    "sg:province":"FL",
    "wof:name":"Dt Super Star",
    "wof:placetype":"venue"
},
  "geometry": {"coordinates":[-80.197256,25.795495],"type":"Point"}
}