{
  "type": "Feature",
  "properties": {
    "iso:country":"US",
    "sg:address":"492 20th Ave N",
    "sg:city":"Indian Rocks Bch",
    "sg:classifiers":[
        {
            "category":"Real Estate",
            "subcategory":"Real Estate Agent",
            "type":"Services"
        }
    ],
    "sg:phone":"+1 727 595 4211",
    "sg:postcode":"33785",
    "sg:province":"FL",
    "sg:tags":[
        "inspection"
    ],
    "wof:name":"Mark Cramer Inspection Svc Inc",
    "wof:placetype":"venue"
},
  "geometry": {"coordinates":[-82.837643,27.90022],"type":"Point"}
}