{
  "type": "Feature",
  "properties": {
    "addr:full":"825 S Grandview Ave Daytona Beach FL 32118",
    "addr:housenumber":"825",
    "addr:postcode":"32118",
    "addr:street":"S Grandview Ave",
    "iso:country":"US",
    "sg:address":"825 S Grandview Ave",
    "sg:city":"Daytona Beach",
    "sg:classifiers":[
        {
            "category":"Government",
            "subcategory":"Office",
            "type":"Public Place"
        }
    ],
    "sg:phone":"+1 386 239 6573",
    "sg:postcode":"32118",
    "sg:province":"FL",
    "sg:tags":[
        "village"
    ],
    "wof:name":"Daytona Beach Lenox Playground",
    "wof:placetype":"venue"
},
  "geometry": {"coordinates":[-81.005562,29.216314],"type":"Point"}
}