{
  "type": "Feature",
  "properties": {
    "iso:country":"US",
    "sg:address":"6708 N 54th St",
    "sg:city":"Tampa",
    "sg:classifiers":[
        {
            "category":"Building & Trades",
            "subcategory":"Construction",
            "type":"Services"
        }
    ],
    "sg:phone":"+1 813 621 9632",
    "sg:postcode":"33610",
    "sg:province":"FL",
    "sg:tags":[
        "insulation",
        "heat",
        "contractor"
    ],
    "sg:website":"www.31w.com",
    "wof:name":"31-W Insulation Co Inc",
    "wof:placetype":"venue"
},
  "geometry": {"coordinates":[-82.395791,28.008783],"type":"Point"}
}