{
  "type": "Feature",
  "properties": {
    "iso:country":"US",
    "sg:address":"10059 NW 45th Ave",
    "sg:city":"Ocala",
    "sg:classifiers":[
        {
            "category":"Retail",
            "subcategory":"Animal Services",
            "type":"Services"
        }
    ],
    "sg:phone":"+1 352 732 3798",
    "sg:postcode":"34482",
    "sg:province":"FL",
    "sg:tags":[
        "pet",
        "boarding",
        "sitting"
    ],
    "wof:name":"Mother Daughter Home Svc Inc",
    "wof:placetype":"venue"
},
  "geometry": {"coordinates":[-82.19584999999999,29.293977],"type":"Point"}
}