{
  "type": "Feature",
  "properties": {
    "addr:full":"81 Solee Rd Palm Coast FL 32137",
    "addr:housenumber":"81",
    "addr:postcode":"32137",
    "addr:street":"Solee Rd",
    "iso:country":"US",
    "sg:address":"81 Solee Rd",
    "sg:city":"Palm Coast",
    "sg:classifiers":[
        {
            "category":"Manufacturing",
            "subcategory":"Electronics",
            "type":"Manufacturing & Wholesale Goods"
        }
    ],
    "sg:phone":"+1 386 447 6735",
    "sg:postcode":"32137",
    "sg:province":"FL",
    "sg:tags":[
        "apparatus",
        "mfg"
    ],
    "wof:name":"Wilmar Industries Inc",
    "wof:placetype":"venue"
},
  "geometry": {"coordinates":[-81.19371700000001,29.619817],"type":"Point"}
}