{
  "type": "Feature",
  "properties": {
    "iso:country":"US",
    "sg:address":"19800 SW 110th Ct",
    "sg:city":"Miami",
    "sg:classifiers":[
        {
            "category":"Building & Trades",
            "subcategory":"Landscaping Services",
            "type":"Services"
        }
    ],
    "sg:phone":"+1 305 378 4458",
    "sg:postcode":"33157",
    "sg:province":"FL",
    "sg:tags":[
        "lawn"
    ],
    "wof:name":"Eidam Eraldo Lawn Service",
    "wof:placetype":"venue"
},
  "geometry": {"coordinates":[-80.37107,25.581266],"type":"Point"}
}