{
  "type": "Feature",
  "properties": {
    "iso:country":"US",
    "sg:address":"1653 Jess Parrish Ct",
    "sg:city":"Titusville",
    "sg:classifiers":[
        {
            "category":"Health Services",
            "subcategory":"Doctor",
            "type":"Services"
        }
    ],
    "sg:phone":"+1 321 264 0199",
    "sg:postcode":"32796",
    "sg:province":"FL",
    "sg:tags":[
        "physician",
        "surgeon"
    ],
    "wof:name":"Rashid, Ayesha I MD FAAP",
    "wof:placetype":"venue"
},
  "geometry": {"coordinates":[-80.82077,28.627541],"type":"Point"}
}