{
  "type": "Feature",
  "properties": {
    "addr:full":"3100 S Florida Ave Inverness FL 34450",
    "addr:housenumber":"3100",
    "addr:postcode":"34450",
    "addr:street":"S Florida Ave",
    "iso:country":"US",
    "sg:address":"3100 S Florida Ave",
    "sg:city":"Inverness",
    "sg:classifiers":[
        {
            "category":"Retail",
            "subcategory":"Car Wash",
            "type":"Services"
        }
    ],
    "sg:phone":"+1 352 344 2732",
    "sg:postcode":"34450",
    "sg:province":"FL",
    "sg:tags":[
        "polishing",
        "washing"
    ],
    "wof:name":"Luvbugs Car Wash",
    "wof:placetype":"venue"
},
  "geometry": {"coordinates":[-82.315569,28.816993],"type":"Point"}
}