{
  "type": "Feature",
  "properties": {
    "addr:full":"5131 Losco Rd Jacksonville FL 32257",
    "addr:housenumber":"5131",
    "addr:postcode":"32257",
    "addr:street":"Losco Rd",
    "iso:country":"US",
    "sg:address":"5131 Losco Rd",
    "sg:city":"Jacksonville",
    "sg:classifiers":[
        {
            "category":"Building & Trades",
            "subcategory":"Construction",
            "type":"Services"
        }
    ],
    "sg:phone":"+1 904 292 1203",
    "sg:postcode":"32257",
    "sg:province":"FL",
    "sg:tags":[
        "nonresidential"
    ],
    "wof:name":"Mmm of Jacksonville",
    "wof:placetype":"venue"
},
  "geometry": {"coordinates":[-81.576313,30.172457],"type":"Point"}
}