{
  "type": "Feature",
  "properties": {
    "iso:country":"US",
    "sg:address":"129 Dayton Rd",
    "sg:city":"Lake Worth",
    "sg:classifiers":[
        {
            "category":"Building & Trades",
            "subcategory":"Landscaping Services",
            "type":"Services"
        }
    ],
    "sg:phone":"+1 561 434 1343",
    "sg:postcode":"33467",
    "sg:province":"FL",
    "sg:tags":[
        "designer",
        "landscape"
    ],
    "wof:name":"JBD Designs Inc",
    "wof:placetype":"venue"
},
  "geometry": {"coordinates":[-80.16622099999999,26.610991],"type":"Point"}
}