{
  "type": "Feature",
  "properties": {
    "iso:country":"US",
    "sg:address":"210 Adams Dr",
    "sg:city":"Maitland",
    "sg:classifiers":[
        {
            "category":"Professional",
            "subcategory":"Management & Consulting",
            "type":"Services"
        }
    ],
    "sg:phone":"+1 407 644 4116",
    "sg:postcode":"32751",
    "sg:province":"FL",
    "sg:tags":[
        "business"
    ],
    "wof:name":"Keyinsites",
    "wof:placetype":"venue"
},
  "geometry": {"coordinates":[-81.35082199999999,28.626359],"type":"Point"}
}