{
  "type": "Feature",
  "properties": {
    "addr:full":"2307 Covington Creek Cir E Jacksonville FL 32224",
    "addr:housenumber":"2307",
    "addr:postcode":"32224",
    "addr:street":"Covington Creek Cir E",
    "iso:country":"US",
    "sg:address":"2307 Covington Creek Cir E",
    "sg:city":"Jacksonville",
    "sg:classifiers":[
        {
            "category":"Professional",
            "subcategory":"Business Services",
            "type":"Services"
        }
    ],
    "sg:phone":"+1 904 220 7946",
    "sg:postcode":"32224",
    "sg:province":"FL",
    "wof:name":"Rick Arsenault Certified Inc",
    "wof:placetype":"venue"
},
  "geometry": {"coordinates":[-81.44542199999999,30.305727],"type":"Point"}
}