{
  "type": "Feature",
  "properties": {
    "addr:full":"3352 SE Fairway W Stuart FL 34997",
    "addr:housenumber":"3352",
    "addr:postcode":"34997",
    "addr:street":"Se Fairway W",
    "iso:country":"US",
    "sg:address":"3352 SE Fairway W",
    "sg:city":"Stuart",
    "sg:classifiers":[
        {
            "category":"Real Estate",
            "subcategory":"Real Estate Agent",
            "type":"Services"
        }
    ],
    "sg:phone":"+1 772 463 7577",
    "sg:postcode":"34997",
    "sg:province":"FL",
    "wof:name":"201 Colorado Ave LLC",
    "wof:placetype":"venue"
},
  "geometry": {"coordinates":[-80.205512,27.159441],"type":"Point"}
}