{
  "type": "Feature",
  "properties": {
    "addr:full":"999 Brickell Ave Miami FL 33131",
    "addr:housenumber":"999",
    "addr:postcode":"33131",
    "addr:street":"Brickell Ave",
    "iso:country":"US",
    "sg:address":"999 Brickell Ave",
    "sg:city":"Miami",
    "sg:classifiers":[
        {
            "category":"Real Estate",
            "subcategory":"Real Estate Services",
            "type":"Services"
        },
        {
            "category":"Real Estate",
            "subcategory":"Real Estate Agent",
            "type":"Services"
        }
    ],
    "sg:phone":"+1 305 993 5055",
    "sg:postcode":"33131",
    "sg:province":"FL",
    "sg:tags":[
        "buyer",
        "broker"
    ],
    "wof:name":"Diverse Realty Services",
    "wof:placetype":"venue"
},
  "geometry": {"coordinates":[-80.19111599999999,25.764191],"type":"Point"}
}