{
  "type": "Feature",
  "properties": {
    "addr:full":"2526 22nd St N St Petersburg FL 33713",
    "addr:housenumber":"2526",
    "addr:postcode":"33713",
    "addr:street":"22Nd St N",
    "iso:country":"US",
    "sg:address":"2526 22nd St N",
    "sg:city":"St Petersburg",
    "sg:classifiers":[
        {
            "category":"Building & Trades",
            "subcategory":"Construction",
            "type":"Services"
        }
    ],
    "sg:phone":"+1 727 521 2500",
    "sg:postcode":"33713",
    "sg:province":"FL",
    "sg:tags":[
        "painter"
    ],
    "wof:name":"Caravan Contractors",
    "wof:placetype":"venue"
},
  "geometry": {"coordinates":[-82.66324,27.795411],"type":"Point"}
}