{
  "type": "Feature",
  "properties": {
    "addr:full":"4741 NE 13th Ave Oakland Park FL 33334",
    "addr:housenumber":"4741",
    "addr:postcode":"33334",
    "addr:street":"Ne 13Th Ave",
    "iso:country":"US",
    "sg:address":"4741 NE 13th Ave",
    "sg:city":"Oakland Park",
    "sg:classifiers":[
        {
            "category":"Building & Trades",
            "subcategory":"Construction",
            "type":"Services"
        }
    ],
    "sg:phone":"+1 954 491 9042",
    "sg:postcode":"33334",
    "sg:province":"FL",
    "sg:tags":[
        "sandblasting"
    ],
    "wof:name":"A-1 Don's Sandblasting",
    "wof:placetype":"venue"
},
  "geometry": {"coordinates":[-80.13029400000001,26.18683],"type":"Point"}
}