{
  "type": "Feature",
  "properties": {
    "addr:full":"10 Corrie Pl Boynton Beach FL 33426",
    "addr:housenumber":"10",
    "addr:postcode":"33426",
    "addr:street":"Corrie Pl",
    "iso:country":"US",
    "sg:address":"10 Corrie Pl",
    "sg:city":"Boynton Beach",
    "sg:classifiers":[
        {
            "category":"Professional",
            "type":"Services"
        }
    ],
    "sg:phone":"+1 561 966 3904",
    "sg:postcode":"33426",
    "sg:province":"FL",
    "wof:name":"My Baby Place Inc",
    "wof:placetype":"venue"
},
  "geometry": {"coordinates":[-80.08292,26.568449],"type":"Point"}
}