{
  "type": "Feature",
  "properties": {
    "iso:country":"US",
    "sg:address":"6525 NW 187th Ter",
    "sg:city":"Alachua",
    "sg:classifiers":[
        {
            "category":"Professional",
            "subcategory":"Computer Services",
            "type":"Services"
        }
    ],
    "sg:phone":"+1 386 462 2154",
    "sg:postcode":"32615",
    "sg:province":"FL",
    "sg:tags":[
        "graphic"
    ],
    "wof:name":"Digital Designs",
    "wof:placetype":"venue"
},
  "geometry": {"coordinates":[-82.541802,29.715515],"type":"Point"}
}