{
  "type": "Feature",
  "properties": {
    "addr:full":"675 E Wisconsin Ave Orange City FL 32763",
    "addr:housenumber":"675",
    "addr:postcode":"32763",
    "addr:street":"E Wisconsin Ave",
    "iso:country":"US",
    "sg:address":"675 E Wisconsin Ave",
    "sg:city":"Orange City",
    "sg:classifiers":[
        {
            "category":"Building & Trades",
            "subcategory":"Construction",
            "type":"Services"
        }
    ],
    "sg:phone":"+1 386 775 3831",
    "sg:postcode":"32763",
    "sg:province":"FL",
    "sg:tags":[
        "contractor"
    ],
    "wof:name":"Alan Pryde Ceramic Tile",
    "wof:placetype":"venue"
},
  "geometry": {"coordinates":[-81.29238599999999,28.959654],"type":"Point"}
}