{
  "type": "Feature",
  "properties": {
    "iso:country":"US",
    "sg:address":"7520 Red Road, Suite E",
    "sg:city":"Miami",
    "sg:classifiers":[
        {
            "category":"Real Estate",
            "subcategory":"Real Estate Services",
            "type":"Services"
        },
        {
            "category":"Real Estate",
            "subcategory":"Real Estate Agent",
            "type":"Services"
        }
    ],
    "sg:phone":"+1 305 338 3809",
    "sg:postcode":"33143",
    "sg:province":"FL",
    "sg:tags":[
        "apartment",
        "rental",
        "finder"
    ],
    "sg:website":"http://www.marketwatchmiami.com",
    "wof:name":"Village Realty of South Florida",
    "wof:placetype":"venue"
},
  "geometry": {"coordinates":[-80.285276,25.701388],"type":"Point"}
}