{
  "type": "Feature",
  "properties": {
    "iso:country":"US",
    "sg:address":"1041 SE 17th St",
    "sg:city":"Fort Lauderdale",
    "sg:classifiers":[
        {
            "category":"Professional",
            "subcategory":"Lawyer & Legal Services",
            "type":"Services"
        }
    ],
    "sg:phone":"+1 954 463 8322",
    "sg:postcode":"33316",
    "sg:province":"FL",
    "wof:name":"Lorna Brownburton",
    "wof:placetype":"venue"
},
  "geometry": {"coordinates":[-80.13262400000001,26.100485],"type":"Point"}
}