{
  "type": "Feature",
  "properties": {
    "addr:full":"20 E Martin Luther King Jr Blvd Brooksville FL 34601",
    "addr:housenumber":"20",
    "addr:postcode":"34601",
    "addr:street":"E Martin Luther King Jr Blvd",
    "iso:country":"US",
    "sg:address":"20 E Martin Luther King Jr Blvd",
    "sg:city":"Brooksville",
    "sg:classifiers":[
        {
            "category":"Home & Garden",
            "subcategory":"Building Materials",
            "type":"Retail Goods"
        }
    ],
    "sg:phone":"+1 352 796 0013",
    "sg:postcode":"34601",
    "sg:province":"FL",
    "sg:tags":[
        "mixed",
        "concrete"
    ],
    "wof:name":"Cemex",
    "wof:placetype":"venue"
},
  "geometry": {"coordinates":[-82.38787499999999,28.545403],"type":"Point"}
}