{
  "type": "Feature",
  "properties": {
    "iso:country":"US",
    "sg:address":"615 Mariposa St",
    "sg:city":"Orlando",
    "sg:classifiers":[
        {
            "category":"Real Estate",
            "subcategory":"Real Estate Services",
            "type":"Services"
        },
        {
            "category":"Real Estate",
            "subcategory":"Real Estate Agent",
            "type":"Services"
        }
    ],
    "sg:phone":"+1 407 872 8501",
    "sg:postcode":"32801",
    "sg:province":"FL",
    "sg:tags":[
        "management"
    ],
    "wof:name":"Success Universal Inc",
    "wof:placetype":"venue"
},
  "geometry": {"coordinates":[-81.369654,28.539851],"type":"Point"}
}