{
  "type": "Feature",
  "properties": {
    "addr:full":"5955 Longbow Ln West Palm Beach FL 33415",
    "addr:housenumber":"5955",
    "addr:postcode":"33415",
    "addr:street":"Longbow Ln",
    "iso:country":"US",
    "sg:address":"5955 Longbow Ln",
    "sg:city":"West Palm Beach",
    "sg:classifiers":[
        {
            "category":"Building & Trades",
            "subcategory":"Construction",
            "type":"Services"
        }
    ],
    "sg:phone":"+1 561 723 7106",
    "sg:postcode":"33415",
    "sg:province":"FL",
    "sg:tags":[
        "contractor"
    ],
    "wof:name":"Jacqueline Ferreira",
    "wof:placetype":"venue"
},
  "geometry": {"coordinates":[-80.13569099999999,26.647555],"type":"Point"}
}