{
  "type": "Feature",
  "properties": {
    "addr:full":"2400 W 8th Ln Hialeah FL 33010",
    "addr:housenumber":"2400",
    "addr:postcode":"33010",
    "addr:street":"W 8Th Ln",
    "iso:country":"US",
    "sg:address":"2400 W 8th Ln",
    "sg:city":"Hialeah",
    "sg:classifiers":[
        {
            "category":"Manufacturing",
            "subcategory":"Petroleum Products",
            "type":"Manufacturing & Wholesale Goods"
        }
    ],
    "sg:phone":"+1 305 885 2116",
    "sg:postcode":"33010",
    "sg:province":"FL",
    "sg:tags":[
        "sheets",
        "etc-producers",
        "plastics-fabrics",
        "rods",
        "film"
    ],
    "wof:name":"Global Plastics Machinary Inc",
    "wof:placetype":"venue"
},
  "geometry": {"coordinates":[-80.299755,25.843455],"type":"Point"}
}