{
  "type": "Feature",
  "properties": {
    "addr:full":"1801 N Military Trl Boca Raton FL 33431",
    "addr:housenumber":"1801",
    "addr:postcode":"33431",
    "addr:street":"N Military Trl",
    "iso:country":"US",
    "sg:address":"1801 N Military Trl",
    "sg:city":"Boca Raton",
    "sg:classifiers":[
        {
            "category":"Banks & Credit Unions",
            "subcategory":"Investment Brokerage",
            "type":"Services"
        }
    ],
    "sg:phone":"+1 561 620 5000",
    "sg:postcode":"33431",
    "sg:province":"FL",
    "sg:tags":[
        "stock",
        "bond"
    ],
    "wof:name":"Smith Barney",
    "wof:placetype":"venue"
},
  "geometry": {"coordinates":[-80.12159699999999,26.365803],"type":"Point"}
}