{
  "type": "Feature",
  "properties": {
    "iso:country":"US",
    "sg:address":"123 Flagship Dr",
    "sg:city":"Lutz",
    "sg:classifiers":[
        {
            "category":"Wholesale",
            "subcategory":"Non-durable Goods",
            "type":"Manufacturing & Wholesale Goods"
        }
    ],
    "sg:phone":"+1 813 909 2088",
    "sg:postcode":"33549",
    "sg:province":"FL",
    "wof:name":"World Capital Trading Inc",
    "wof:placetype":"venue"
},
  "geometry": {"coordinates":[-82.462705,28.134849],"type":"Point"}
}