{
  "type": "Feature",
  "properties": {
    "iso:country":"US",
    "sg:address":"10271 Sorrento Rd",
    "sg:city":"Pensacola",
    "sg:classifiers":[
        {
            "category":"Social Services",
            "subcategory":"Child Care",
            "type":"Services"
        }
    ],
    "sg:phone":"+1 850 456 9501",
    "sg:postcode":"32507",
    "sg:province":"FL",
    "sg:tags":[
        "day"
    ],
    "wof:name":"Blue Angel Early Learning Ctr",
    "wof:placetype":"venue"
},
  "geometry": {"coordinates":[-87.35823600000001,30.360677],"type":"Point"}
}