{
  "type": "Feature",
  "properties": {
    "iso:country":"US",
    "sg:address":"3606 Old Winter Garden Rd",
    "sg:city":"Orlando",
    "sg:classifiers":[
        {
            "category":"Autos & Motor Vehicles",
            "subcategory":"Automobile Sales",
            "type":"Retail Goods"
        }
    ],
    "sg:phone":"+1 407 822 7372",
    "sg:postcode":"32805",
    "sg:province":"FL",
    "sg:tags":[
        "used"
    ],
    "wof:name":"Charlot Used Auto Sales Inc",
    "wof:placetype":"venue"
},
  "geometry": {"coordinates":[-81.421402,28.54721],"type":"Point"}
}