{
  "type": "Feature",
  "properties": {
    "iso:country":"US",
    "sg:address":"15130 S Tamiami Trl",
    "sg:city":"Fort Myers",
    "sg:classifiers":[
        {
            "category":"Autos & Motor Vehicles",
            "subcategory":"Automobile Sales",
            "type":"Retail Goods"
        }
    ],
    "sg:phone":"+1 239 489 1203",
    "sg:postcode":"33908",
    "sg:province":"FL",
    "sg:tags":[
        "automotive"
    ],
    "wof:name":"Beverly Hills Tinting Inc",
    "wof:placetype":"venue"
},
  "geometry": {"coordinates":[-81.87031899999999,26.522676],"type":"Point"}
}