{
  "type": "Feature",
  "properties": {
    "iso:country":"US",
    "sg:address":"6404 Sagewood Dr",
    "sg:city":"Orlando",
    "sg:classifiers":[
        {
            "category":"Building & Trades",
            "subcategory":"Pest Control",
            "type":"Services"
        }
    ],
    "sg:phone":"+1 407 298 1327",
    "sg:postcode":"32818",
    "sg:province":"FL",
    "wof:name":"DNA Pest Svc",
    "wof:placetype":"venue"
},
  "geometry": {"coordinates":[-81.470225,28.5626],"type":"Point"}
}