{
  "type": "Feature",
  "properties": {
    "iso:country":"US",
    "sg:address":"5210 Londonderry Ln",
    "sg:city":"Zephyrhills",
    "sg:classifiers":[
        {
            "category":"Real Estate",
            "subcategory":"Real Estate Agent",
            "type":"Services"
        }
    ],
    "sg:phone":"+1 813 907 9708",
    "sg:postcode":"33543",
    "sg:province":"FL",
    "sg:tags":[
        "inspection"
    ],
    "wof:name":"Jeff James Dupont Inspection",
    "wof:placetype":"venue"
},
  "geometry": {"coordinates":[-82.328701,28.232766],"type":"Point"}
}