{
  "type": "Feature",
  "properties": {
    "iso:country":"US",
    "sg:address":"361 20th Ave NE",
    "sg:city":"Naples",
    "sg:classifiers":[
        {
            "category":"Retail",
            "subcategory":"Auto Repair",
            "type":"Services"
        }
    ],
    "sg:phone":"+1 239 352 0414",
    "sg:postcode":"34120",
    "sg:province":"FL",
    "sg:tags":[
        "repairing",
        "automobile"
    ],
    "wof:name":"Affordable Mobile Mechanic",
    "wof:placetype":"venue"
},
  "geometry": {"coordinates":[-81.60636700000001,26.266398],"type":"Point"}
}