{
  "type": "Feature",
  "properties": {
    "iso:country":"US",
    "sg:address":"819 5th St",
    "sg:city":"Miami Beach",
    "sg:classifiers":[
        {
            "category":"Professional",
            "type":"Services"
        }
    ],
    "sg:phone":"+1 305 538 0816",
    "sg:postcode":"33139",
    "sg:province":"FL",
    "wof:name":"819 Fifth Street Corporation",
    "wof:placetype":"venue"
},
  "geometry": {"coordinates":[-80.137005,25.774511],"type":"Point"}
}