{
  "type": "Feature",
  "properties": {
    "iso:country":"US",
    "sg:address":"3206 Buckingham Ln",
    "sg:city":"Cocoa",
    "sg:classifiers":[
        {
            "category":"Professional",
            "subcategory":"Lawyer & Legal Services",
            "type":"Services"
        }
    ],
    "sg:phone":"+1 321 634 5080",
    "sg:postcode":"32926",
    "sg:province":"FL",
    "wof:name":"Thomas E Thoburn PA",
    "wof:placetype":"venue"
},
  "geometry": {"coordinates":[-80.74902,28.403697],"type":"Point"}
}