{
  "type": "Feature",
  "properties": {
    "iso:country":"US",
    "sg:address":"1212 N 39th St",
    "sg:city":"Tampa",
    "sg:classifiers":[
        {
            "category":"Manufacturing",
            "subcategory":"Tools & Machinery",
            "type":"Manufacturing & Wholesale Goods"
        }
    ],
    "sg:phone":"+1 813 248 5707",
    "sg:postcode":"33605",
    "sg:province":"FL",
    "sg:tags":[
        "equipment",
        "petroleum"
    ],
    "sg:website":"www.guardianfueltech.com",
    "wof:name":"Guardian Fueling Technologies",
    "wof:placetype":"venue"
},
  "geometry": {"coordinates":[-82.41564,27.95733],"type":"Point"}
}