{
  "type": "Feature",
  "properties": {
    "iso:country":"US",
    "sg:address":"2361 Cortez Rd",
    "sg:city":"Jacksonville",
    "sg:classifiers":[
        {
            "category":"Education",
            "subcategory":"School",
            "type":"Public Place"
        }
    ],
    "sg:phone":"+1 904 641 7874",
    "sg:postcode":"32246",
    "sg:province":"FL",
    "wof:name":"Jesus Jubiland Day School",
    "wof:placetype":"venue"
},
  "geometry": {"coordinates":[-81.53120199999999,30.306833],"type":"Point"}
}