{
  "type": "Feature",
  "properties": {
    "iso:country":"US",
    "sg:address":"200 SE 1st St",
    "sg:city":"Miami",
    "sg:classifiers":[
        {
            "category":"Professional",
            "subcategory":"Management & Consulting",
            "type":"Services"
        }
    ],
    "sg:phone":"+1 305 374 8922",
    "sg:postcode":"33131",
    "sg:province":"FL",
    "sg:tags":[
        "business"
    ],
    "wof:name":"Imageworks Consulting Firm",
    "wof:placetype":"venue"
},
  "geometry": {"coordinates":[-80.188964,25.773439],"type":"Point"}
}