{
  "type": "Feature",
  "properties": {
    "addr:full":"4414 NE 6th Ter Oakland Park FL 33334",
    "addr:housenumber":"4414",
    "addr:postcode":"33334",
    "addr:street":"Ne 6Th Ter;Park",
    "iso:country":"US",
    "sg:address":"4414 NE 6th Ter",
    "sg:city":"Oakland Park",
    "sg:classifiers":[
        {
            "category":"Manufacturing",
            "subcategory":"Tools & Machinery",
            "type":"Manufacturing & Wholesale Goods"
        }
    ],
    "sg:phone":"+1 954 938 6228",
    "sg:postcode":"33334",
    "sg:province":"FL",
    "sg:tags":[
        "machine",
        "shop"
    ],
    "wof:name":"Atlantic Coast Mfg Inc",
    "wof:placetype":"venue"
},
  "geometry": {"coordinates":[-80.138136,26.182557],"type":"Point"}
}