{
  "type": "Feature",
  "properties": {
    "iso:country":"US",
    "sg:address":"120 NE 8th St",
    "sg:city":"Homestead",
    "sg:classifiers":[
        {
            "category":"Shopping",
            "subcategory":"Department Store",
            "type":"Retail Goods"
        }
    ],
    "sg:phone":"+1 305 242 7455",
    "sg:postcode":"33030",
    "sg:province":"FL",
    "wof:name":"Sears",
    "wof:placetype":"venue"
},
  "geometry": {"coordinates":[-80.475438,25.477062],"type":"Point"}
}