{
  "type": "Feature",
  "properties": {
    "iso:country":"US",
    "sg:address":"11675 N Main St",
    "sg:city":"Jacksonville",
    "sg:classifiers":[
        {
            "category":"Home & Garden",
            "subcategory":"Building Materials",
            "type":"Retail Goods"
        },
        {
            "category":"Home & Garden",
            "subcategory":"Hardware",
            "type":"Retail Goods"
        }
    ],
    "sg:phone":"+1 904 757 3404",
    "sg:postcode":"32218",
    "sg:province":"FL",
    "wof:name":"Shuman Cash Supply Inc",
    "wof:placetype":"venue"
},
  "geometry": {"coordinates":[-81.639098,30.447586],"type":"Point"}
}