{
  "type": "Feature",
  "properties": {
    "iso:country":"US",
    "sg:address":"332 W Boynton Beach Blvd",
    "sg:city":"Boynton Beach",
    "sg:classifiers":[
        {
            "category":"Manufacturing",
            "subcategory":"Signs",
            "type":"Manufacturing & Wholesale Goods"
        }
    ],
    "sg:phone":"+1 561 736 3712",
    "sg:postcode":"33435",
    "sg:province":"FL",
    "sg:tags":[
        "specialty",
        "mfg"
    ],
    "wof:name":"Signature Signs & Graphics",
    "wof:placetype":"venue"
},
  "geometry": {"coordinates":[-80.06775399999999,26.52885],"type":"Point"}
}