{
  "type": "Feature",
  "properties": {
    "iso:country":"US",
    "sg:address":"5603 3rd Rd",
    "sg:city":"Lake Worth",
    "sg:classifiers":[
        {
            "category":"Building & Trades",
            "subcategory":"Construction",
            "type":"Services"
        }
    ],
    "sg:phone":"+1 561 641 6029",
    "sg:postcode":"33467",
    "sg:province":"FL",
    "sg:tags":[
        "carpentry",
        "contractor"
    ],
    "wof:name":"Scotts Trim Carpentry",
    "wof:placetype":"venue"
},
  "geometry": {"coordinates":[-80.1669,26.594151],"type":"Point"}
}