{
  "type": "Feature",
  "properties": {
    "iso:country":"US",
    "sg:address":"201 N Franklin St # 2000",
    "sg:city":"Tampa",
    "sg:classifiers":[
        {
            "category":"Professional",
            "subcategory":"Lawyer & Legal Services",
            "type":"Services"
        }
    ],
    "sg:phone":"+1 813 273 4200",
    "sg:postcode":"33602",
    "sg:province":"FL",
    "sg:tags":[
        "attorney",
        "practice",
        "plan"
    ],
    "sg:website":"http://www.ausley.com",
    "wof:name":"Mcfarland Ferguson & Mcmullen",
    "wof:placetype":"venue"
},
  "geometry": {"coordinates":[-82.45760300000001,27.94696],"type":"Point"}
}