{
  "type": "Feature",
  "properties": {
    "iso:country":"US",
    "sg:address":"1150 NW 14th St",
    "sg:city":"Miami",
    "sg:classifiers":[
        {
            "category":"Health Services",
            "subcategory":"Doctor",
            "type":"Services"
        }
    ],
    "sg:phone":"+1 305 324 1645",
    "sg:postcode":"33136",
    "sg:province":"FL",
    "sg:tags":[
        "physician",
        "cardiology",
        "thoracic",
        "surgeons",
        "surgeon",
        "surgery",
        "cardiovascular"
    ],
    "wof:name":"Arthur Kaufman Md",
    "wof:placetype":"venue"
},
  "geometry": {"coordinates":[-80.21405799999999,25.78763],"type":"Point"}
}