{
  "type": "Feature",
  "properties": {
    "iso:country":"US",
    "sg:address":"12265 W Indiantown Rd",
    "sg:city":"Jupiter",
    "sg:classifiers":[
        {
            "category":"Organizations",
            "subcategory":"Religious Organization",
            "type":"Services"
        }
    ],
    "sg:phone":"+1 561 748 8680",
    "sg:postcode":"33478",
    "sg:province":"FL",
    "sg:tags":[
        "church"
    ],
    "wof:name":"Christian Missionary Alliance",
    "wof:placetype":"venue"
},
  "geometry": {"coordinates":[-80.22735400000001,26.942532],"type":"Point"}
}