{
  "type": "Feature",
  "properties": {
    "addr:full":"140 W Flagler St Miami FL 33130",
    "addr:housenumber":"140",
    "addr:postcode":"33130",
    "addr:street":"W Flagler St",
    "iso:country":"US",
    "sg:address":"140 W Flagler St",
    "sg:city":"Miami",
    "sg:classifiers":[
        {
            "category":"Government",
            "subcategory":"Court House",
            "type":"Public Place"
        }
    ],
    "sg:phone":"+1 305 375 2901",
    "sg:postcode":"33130",
    "sg:province":"FL",
    "wof:name":"County Clerk",
    "wof:placetype":"venue"
},
  "geometry": {"coordinates":[-80.19717799999999,25.773973],"type":"Point"}
}