{
  "type": "Feature",
  "properties": {
    "iso:country":"US",
    "sg:address":"5018 Spring Park Rd",
    "sg:city":"Jacksonville",
    "sg:classifiers":[
        {
            "category":"Wholesale",
            "subcategory":"Electrical",
            "type":"Manufacturing & Wholesale Goods"
        }
    ],
    "sg:phone":"+1 904 737 6706",
    "sg:postcode":"32207",
    "sg:province":"FL",
    "sg:tags":[
        "control",
        "security",
        "system"
    ],
    "sg:website":"www.semcorp.com",
    "wof:name":"Best Access Systems",
    "wof:placetype":"venue"
},
  "geometry": {"coordinates":[-81.611856,30.271312],"type":"Point"}
}