{
  "type": "Feature",
  "properties": {
    "iso:country":"US",
    "sg:address":"5008 Manatee Ave W",
    "sg:city":"Bradenton",
    "sg:classifiers":[
        {
            "category":"Travel",
            "subcategory":"Travel Agent",
            "type":"Entertainment"
        }
    ],
    "sg:phone":"+1 941 745 1880",
    "sg:postcode":"34209",
    "sg:province":"FL",
    "sg:tags":[
        "agency"
    ],
    "wof:name":"Eddas Travel Corner Inc",
    "wof:placetype":"venue"
},
  "geometry": {"coordinates":[-82.61149,27.495972],"type":"Point"}
}