{
  "type": "Feature",
  "properties": {
    "addr:full":"3785 NE 17th Ave Ocala FL 34479",
    "addr:housenumber":"3785",
    "addr:postcode":"34479",
    "addr:street":"Ne 17Th Ave",
    "iso:country":"US",
    "sg:address":"3785 NE 17th Ave",
    "sg:city":"Ocala",
    "sg:classifiers":[
        {
            "category":"Building & Trades",
            "subcategory":"Construction",
            "type":"Services"
        }
    ],
    "sg:phone":"+1 352 622 4766",
    "sg:postcode":"34479",
    "sg:province":"FL",
    "sg:tags":[
        "restoration",
        "cleaning",
        "patio",
        "deck"
    ],
    "wof:name":"Top To Bottom Pressure Clean",
    "wof:placetype":"venue"
},
  "geometry": {"coordinates":[-82.115173,29.225765],"type":"Point"}
}