{
  "type": "Feature",
  "properties": {
    "addr:full":"6768 Aloma Ave Winter Park FL 32792",
    "addr:housenumber":"6768",
    "addr:postcode":"32792",
    "addr:street":"Aloma Ave",
    "iso:country":"US",
    "sg:address":"6768 Aloma Ave",
    "sg:city":"Winter Park",
    "sg:classifiers":[
        {
            "category":"Food & Beverages",
            "subcategory":"Groceries & Convenience Stores",
            "type":"Retail Goods"
        }
    ],
    "sg:phone":"+1 407 644 5510",
    "sg:postcode":"32792",
    "sg:province":"FL",
    "wof:name":"Winn-Dixie",
    "wof:placetype":"venue"
},
  "geometry": {"coordinates":[-81.297573,28.606556],"type":"Point"}
}