{
  "type": "Feature",
  "properties": {
    "addr:full":"218 S US Hwy 1 Jupiter FL 33469",
    "addr:housenumber":"218",
    "addr:postcode":"33469",
    "addr:street":"S Us Hwy 1",
    "iso:country":"US",
    "sg:address":"218 S US Hwy 1",
    "sg:city":"Jupiter",
    "sg:classifiers":[
        {
            "category":"Banks & Credit Unions",
            "subcategory":"Investment Brokerage",
            "type":"Services"
        }
    ],
    "sg:phone":"+1 772 220 1071",
    "sg:postcode":"33469",
    "sg:province":"FL",
    "sg:tags":[
        "commodity",
        "contract"
    ],
    "wof:name":"Beddows Commodities Inc",
    "wof:placetype":"venue"
},
  "geometry": {"coordinates":[-80.085042,26.956396],"type":"Point"}
}