{
  "type": "Feature",
  "properties": {
    "iso:country":"US",
    "sg:address":"10409 SW 186th Ave",
    "sg:city":"Miami",
    "sg:classifiers":[
        {
            "category":"Home & Garden",
            "subcategory":"Furniture",
            "type":"Retail Goods"
        }
    ],
    "sg:phone":"+1 305 233 5358",
    "sg:postcode":"33196",
    "sg:province":"FL",
    "sg:tags":[
        "store"
    ],
    "wof:name":"Husaini Anayat",
    "wof:placetype":"venue"
},
  "geometry": {"coordinates":[-80.360494,25.594519],"type":"Point"}
}