{
  "type": "Feature",
  "properties": {
    "iso:country":"US",
    "sg:address":"407 Wekiva Springs Rd",
    "sg:city":"Longwood",
    "sg:classifiers":[
        {
            "category":"Real Estate",
            "subcategory":"Real Estate Agent",
            "type":"Services"
        }
    ],
    "sg:phone":"+1 407 862 9200",
    "sg:postcode":"32779",
    "sg:province":"FL",
    "sg:website":"www.bettebutzrealty.com",
    "wof:name":"Bette Butz Realty Inc",
    "wof:placetype":"venue"
},
  "geometry": {"coordinates":[-81.40962399999999,28.692062],"type":"Point"}
}