{
  "type": "Feature",
  "properties": {
    "iso:country":"US",
    "sg:address":"424 W 23rd St",
    "sg:city":"Panama City",
    "sg:classifiers":[
        {
            "category":"Real Estate",
            "subcategory":"Real Estate Agent",
            "type":"Services"
        }
    ],
    "sg:phone":"+1 850 249 4669",
    "sg:postcode":"32405",
    "sg:province":"FL",
    "wof:name":"Cornerstone Realty",
    "wof:placetype":"venue"
},
  "geometry": {"coordinates":[-85.667852,30.189785],"type":"Point"}
}