{
  "type": "Feature",
  "properties": {
    "addr:full":"9501 State Hwy 64 Bradenton FL 34212",
    "addr:housenumber":"9501",
    "addr:postcode":"34212",
    "addr:street":"State Hwy 64",
    "iso:country":"US",
    "sg:address":"9501 State Hwy 64",
    "sg:city":"Bradenton",
    "sg:classifiers":[
        {
            "category":"Education",
            "subcategory":"School",
            "type":"Public Place"
        }
    ],
    "sg:phone":"+1 941 714 7240",
    "sg:postcode":"34212",
    "sg:province":"FL",
    "wof:name":"Carlos E Haile Middle School",
    "wof:placetype":"venue"
},
  "geometry": {"coordinates":[-82.447155,27.485758],"type":"Point"}
}