{
  "type": "Feature",
  "properties": {
    "iso:country":"US",
    "sg:address":"5155 S University Dr",
    "sg:city":"Davie",
    "sg:classifiers":[
        {
            "category":"Home & Garden",
            "subcategory":"Furniture",
            "type":"Retail Goods"
        },
        {
            "category":"Shopping",
            "subcategory":"Gifts & Souvenirs",
            "type":"Retail Goods"
        }
    ],
    "sg:phone":"+1 954 472 6958",
    "sg:postcode":"33328",
    "sg:province":"FL",
    "sg:tags":[
        "handcraft",
        "drapery"
    ],
    "wof:name":"Country Connection Inc",
    "wof:placetype":"venue"
},
  "geometry": {"coordinates":[-80.251696,26.047692],"type":"Point"}
}