{
  "type": "Feature",
  "properties": {
    "iso:country":"US",
    "sg:address":"13121 Doubletree Cir",
    "sg:city":"Wellington",
    "sg:classifiers":[
        {
            "category":"Professional",
            "subcategory":"Management & Consulting",
            "type":"Services"
        }
    ],
    "sg:phone":"+1 561 204 2658",
    "sg:postcode":"33414",
    "sg:province":"FL",
    "sg:tags":[
        "fuel"
    ],
    "wof:name":"Mondial Expatriate Svc Inc",
    "wof:placetype":"venue"
},
  "geometry": {"coordinates":[-80.25467,26.67832],"type":"Point"}
}