{
  "type": "Feature",
  "properties": {
    "iso:country":"US",
    "sg:address":"8101 Dr Martin Luther King Jr St N",
    "sg:city":"Saint Petersburg",
    "sg:classifiers":[
        {
            "category":"Restaurant",
            "type":"Food & Drink"
        },
        {
            "category":"Ice Cream",
            "type":"Food & Drink"
        }
    ],
    "sg:menulink":"http://www.allmenus.com/fl/st-petersburg/92387-steak-n-shake/menu/",
    "sg:phone":"+1 727 568 9169",
    "sg:postcode":"33702",
    "sg:province":"FL",
    "sg:tags":[
        "american",
        "ice",
        "cream"
    ],
    "wof:name":"Steak 'n Shake",
    "wof:placetype":"venue"
},
  "geometry": {"coordinates":[-82.64690400000001,27.846412],"type":"Point"}
}