{
  "type": "Feature",
  "properties": {
    "iso:country":"US",
    "sg:address":"411 W Belt Ave",
    "sg:city":"Bushnell",
    "sg:classifiers":[
        {
            "category":"Personal",
            "subcategory":"Beauty Salon",
            "type":"Services"
        }
    ],
    "sg:phone":"+1 352 793 5453",
    "sg:postcode":"33513",
    "sg:province":"FL",
    "sg:tags":[
        "manicuring"
    ],
    "wof:name":"U/Got/Nails",
    "wof:placetype":"venue"
},
  "geometry": {"coordinates":[-82.119103,28.668506],"type":"Point"}
}