{
  "type": "Feature",
  "properties": {
    "iso:country":"US",
    "sg:address":"2335 NW 8th Ave",
    "sg:city":"Miami",
    "sg:classifiers":[
        {
            "category":"Building & Trades",
            "subcategory":"Construction",
            "type":"Services"
        }
    ],
    "sg:phone":"+1 305 635 0332",
    "sg:postcode":"33127",
    "sg:province":"FL",
    "sg:tags":[
        "roofing",
        "contractor"
    ],
    "wof:name":"Kingtech Roofing Inc",
    "wof:placetype":"venue"
},
  "geometry": {"coordinates":[-80.209135,25.799475],"type":"Point"}
}