{
  "type": "Feature",
  "properties": {
    "iso:country":"US",
    "sg:address":"2801 NW 13th St",
    "sg:city":"Gainesville",
    "sg:classifiers":[
        {
            "category":"Shopping",
            "type":"Retail Goods"
        }
    ],
    "sg:phone":"+1 352 375 6600",
    "sg:postcode":"32609",
    "sg:province":"FL",
    "sg:tags":[
        "merchandise"
    ],
    "wof:name":"Wireless Retail",
    "wof:placetype":"venue"
},
  "geometry": {"coordinates":[-82.33902,29.678691],"type":"Point"}
}