{
  "type": "Feature",
  "properties": {
    "iso:country":"US",
    "sg:address":"6880 S Grande Dr",
    "sg:city":"Boca Raton",
    "sg:classifiers":[
        {
            "category":"Professional",
            "type":"Services"
        }
    ],
    "sg:phone":"+1 561 487 5475",
    "sg:postcode":"33433",
    "sg:province":"FL",
    "wof:name":"Joan A Shaouy",
    "wof:placetype":"venue"
},
  "geometry": {"coordinates":[-80.15083300000001,26.365426],"type":"Point"}
}