{
  "type": "Feature",
  "properties": {
    "iso:country":"US",
    "sg:address":"1555 1st St S",
    "sg:city":"Winter Haven",
    "sg:classifiers":[
        {
            "category":"Autos & Motor Vehicles",
            "subcategory":"Automobile Sales",
            "type":"Retail Goods"
        }
    ],
    "sg:phone":"+1 863 299 1221",
    "sg:postcode":"33880",
    "sg:province":"FL",
    "sg:tags":[
        "car",
        "dealership",
        "dealer"
    ],
    "wof:name":"Central Pontiac Buick G M C",
    "wof:placetype":"venue"
},
  "geometry": {"coordinates":[-81.726823,28.006226],"type":"Point"}
}