{
  "type": "Feature",
  "properties": {
    "iso:country":"US",
    "sg:address":"7402 N Branch Ave",
    "sg:city":"Tampa",
    "sg:classifiers":[
        {
            "category":"Building & Trades",
            "subcategory":"Landscaping Services",
            "type":"Services"
        }
    ],
    "sg:phone":"+1 813 986 5867",
    "sg:postcode":"33604",
    "sg:province":"FL",
    "wof:name":"Chains Stump Removal",
    "wof:placetype":"venue"
},
  "geometry": {"coordinates":[-82.457928,28.01614],"type":"Point"}
}