{
  "type": "Feature",
  "properties": {
    "iso:country":"US",
    "sg:address":"5000 S Clyde Morris Blvd",
    "sg:city":"Port Orange",
    "sg:classifiers":[
        {
            "category":"Cafe",
            "type":"Food & Drink"
        }
    ],
    "sg:menulink":"http://www.allmenus.com/fl/port-orange/29975-joy-luck-cafe/menu/",
    "sg:phone":"+1 386 322 1800",
    "sg:postcode":"32127",
    "sg:province":"FL",
    "sg:tags":[
        "asian",
        "chinese"
    ],
    "wof:name":"Joy Luck Cafe",
    "wof:placetype":"venue"
},
  "geometry": {"coordinates":[-81.023106,29.11666],"type":"Point"}
}