{
  "type": "Feature",
  "properties": {
    "addr:full":"8936 N Military Trl Palm Beach Gardens FL 33410",
    "addr:housenumber":"8936",
    "addr:postcode":"33410",
    "addr:street":"N Military Trl",
    "iso:country":"US",
    "sg:address":"8936 N Military Trl",
    "sg:city":"Palm Beach Gardens",
    "sg:classifiers":[
        {
            "category":"Personal",
            "type":"Services"
        }
    ],
    "sg:phone":"+1 561 622 9101",
    "sg:postcode":"33410",
    "sg:province":"FL",
    "wof:name":"La Weight Loss Centers Inc",
    "wof:placetype":"venue"
},
  "geometry": {"coordinates":[-80.106455,26.805752],"type":"Point"}
}