{
  "type": "Feature",
  "properties": {
    "addr:full":"333 Croton Dr Maitland FL 32751",
    "addr:housenumber":"333",
    "addr:postcode":"32751",
    "addr:street":"Croton Dr",
    "iso:country":"US",
    "sg:address":"333 Croton Dr",
    "sg:city":"Maitland",
    "sg:classifiers":[
        {
            "category":"Professional",
            "subcategory":"Advertising",
            "type":"Services"
        }
    ],
    "sg:phone":"+1 407 339 1736",
    "sg:postcode":"32751",
    "sg:province":"FL",
    "sg:tags":[
        "counselor"
    ],
    "wof:name":"G A & Co",
    "wof:placetype":"venue"
},
  "geometry": {"coordinates":[-81.38199899999999,28.641122],"type":"Point"}
}