{
  "type": "Feature",
  "properties": {
    "iso:country":"US",
    "sg:address":"6985 Seminole Blvd",
    "sg:city":"Seminole",
    "sg:classifiers":[
        {
            "category":"Real Estate",
            "subcategory":"Developer",
            "type":"Services"
        },
        {
            "category":"Real Estate",
            "subcategory":"Real Estate Operator",
            "type":"Services"
        }
    ],
    "sg:phone":"+1 727 392 6774",
    "sg:postcode":"33772",
    "sg:province":"FL",
    "sg:tags":[
        "mobile",
        "home",
        "site"
    ],
    "wof:name":"Gulf Crest Home Owners Assoc",
    "wof:placetype":"venue"
},
  "geometry": {"coordinates":[-82.786964,27.835198],"type":"Point"}
}