{
  "type": "Feature",
  "properties": {
    "addr:full":"6958 SW 47th St Miami FL 33155",
    "addr:housenumber":"6958",
    "addr:postcode":"33155",
    "addr:street":"Sw 47Th St",
    "iso:country":"US",
    "sg:address":"6958 SW 47th St",
    "sg:city":"Miami",
    "sg:classifiers":[
        {
            "category":"Building & Trades",
            "subcategory":"Construction",
            "type":"Services"
        }
    ],
    "sg:phone":"+1 305 661 9269",
    "sg:postcode":"33155",
    "sg:province":"FL",
    "sg:tags":[
        "general",
        "contractor"
    ],
    "wof:name":"K D Construction",
    "wof:placetype":"venue"
},
  "geometry": {"coordinates":[-80.30820900000001,25.726366],"type":"Point"}
}