{
  "type": "Feature",
  "properties": {
    "addr:full":"5135 Adanson St Orlando FL 32804",
    "addr:postcode":"5135;32804",
    "addr:street":"Adanson St",
    "iso:country":"US",
    "sg:address":"5135 Adanson St",
    "sg:city":"Orlando",
    "sg:classifiers":[
        {
            "category":"Professional",
            "subcategory":"Employment Agencies",
            "type":"Services"
        }
    ],
    "sg:phone":"+1 407 629 2046",
    "sg:postcode":"32804",
    "sg:province":"FL",
    "wof:name":"Clp Resources Inc",
    "wof:placetype":"venue"
},
  "geometry": {"coordinates":[-81.39336400000001,28.604293],"type":"Point"}
}