{
  "type": "Feature",
  "properties": {
    "addr:full":"1645 Barber Rd Sarasota FL 34240",
    "addr:housenumber":"1645",
    "addr:postcode":"34240",
    "addr:street":"Barber Rd",
    "iso:country":"US",
    "sg:address":"1645 Barber Rd",
    "sg:city":"Sarasota",
    "sg:classifiers":[
        {
            "category":"Government",
            "subcategory":"Office",
            "type":"Public Place"
        }
    ],
    "sg:phone":"+1 941 316 1776",
    "sg:postcode":"34240",
    "sg:province":"FL",
    "sg:tags":[
        "management"
    ],
    "wof:name":"Peace River Manasota Regl Wter",
    "wof:placetype":"venue"
},
  "geometry": {"coordinates":[-82.445356,27.319686],"type":"Point"}
}