{
  "type": "Feature",
  "properties": {
    "iso:country":"US",
    "sg:address":"920 E Eau Gallie Blvd",
    "sg:city":"Indian Hrbr Bch",
    "sg:classifiers":[
        {
            "category":"Home & Garden",
            "subcategory":"Garden Supply",
            "type":"Retail Goods"
        }
    ],
    "sg:phone":"+1 321 773 1375",
    "sg:postcode":"32937",
    "sg:province":"FL",
    "sg:tags":[
        "plant",
        "landscaping",
        "nurseryman",
        "nursery",
        "counseling",
        "silk"
    ],
    "wof:name":"Sun Harbor Nursery",
    "wof:placetype":"venue"
},
  "geometry": {"coordinates":[-80.583462,28.13872],"type":"Point"}
}