{
  "type": "Feature",
  "properties": {
    "iso:country":"US",
    "sg:address":"4609 Gallagher Rd",
    "sg:city":"Plant City",
    "sg:classifiers":[
        {
            "category":"Building & Trades",
            "subcategory":"Landscaping Services",
            "type":"Services"
        }
    ],
    "sg:phone":"+1 813 986 0555",
    "sg:postcode":"33565",
    "sg:province":"FL",
    "sg:tags":[
        "landscape",
        "contractor"
    ],
    "wof:name":"Prestige Lawn Design",
    "wof:placetype":"venue"
},
  "geometry": {"coordinates":[-82.236744,28.065491],"type":"Point"}
}