{
  "type": "Feature",
  "properties": {
    "addr:full":"867 Kell Aire Dr Destin FL 32541",
    "addr:housenumber":"867",
    "addr:postcode":"32541",
    "addr:street":"Kell Aire Dr",
    "iso:country":"US",
    "sg:address":"867 Kell Aire Dr",
    "sg:city":"Destin",
    "sg:classifiers":[
        {
            "category":"Building & Trades",
            "subcategory":"Construction",
            "type":"Services"
        }
    ],
    "sg:phone":"+1 850 243 9330",
    "sg:postcode":"32541",
    "sg:province":"FL",
    "sg:tags":[
        "contractor"
    ],
    "wof:name":"Bryla Construction Inc",
    "wof:placetype":"venue"
},
  "geometry": {"coordinates":[-86.47813600000001,30.401182],"type":"Point"}
}