{
  "type": "Feature",
  "properties": {
    "iso:country":"US",
    "sg:address":"812 SE 8th St",
    "sg:city":"Hialeah",
    "sg:classifiers":[
        {
            "category":"Shopping",
            "subcategory":"Used Merchandise",
            "type":"Retail Goods"
        }
    ],
    "sg:phone":"+1 305 885 9800",
    "sg:postcode":"33010",
    "sg:province":"FL",
    "sg:tags":[
        "shop",
        "pawnbroker",
        "pawn"
    ],
    "wof:name":"A G Cash Corp",
    "wof:placetype":"venue"
},
  "geometry": {"coordinates":[-80.264297,25.815701],"type":"Point"}
}