{
  "type": "Feature",
  "properties": {
    "iso:country":"US",
    "sg:address":"5043 Timothy Ln",
    "sg:city":"Jacksonville",
    "sg:classifiers":[
        {
            "category":"Retail",
            "subcategory":"Auto Repair",
            "type":"Services"
        }
    ],
    "sg:phone":"+1 904 381 9444",
    "sg:postcode":"32210",
    "sg:province":"FL",
    "sg:tags":[
        "automobile",
        "top",
        "upholstery"
    ],
    "wof:name":"Car Concepts Customized Auto",
    "wof:placetype":"venue"
},
  "geometry": {"coordinates":[-81.731697,30.275593],"type":"Point"}
}