{
  "type": "Feature",
  "properties": {
    "addr:full":"7457 103rd St Jacksonville FL 32210",
    "addr:housenumber":"7457",
    "addr:postcode":"32210",
    "addr:street":"103Rd St",
    "iso:country":"US",
    "sg:address":"7457 103rd St",
    "sg:city":"Jacksonville",
    "sg:classifiers":[
        {
            "category":"Professional",
            "type":"Services"
        }
    ],
    "sg:phone":"+1 904 772 8271",
    "sg:postcode":"32210",
    "sg:province":"FL",
    "sg:tags":[
        "establishment"
    ],
    "wof:name":"One Stop Merchants",
    "wof:placetype":"venue"
},
  "geometry": {"coordinates":[-81.769559,30.24837],"type":"Point"}
}