{
  "type": "Feature",
  "properties": {
    "addr:full":"8236 Glades Rd Boca Raton FL 33432",
    "addr:housenumber":"8236",
    "addr:postcode":"33432",
    "addr:street":"Glades Rd",
    "iso:country":"US",
    "sg:address":"8236 Glades Rd",
    "sg:city":"Boca Raton",
    "sg:classifiers":[
        {
            "category":"Shopping",
            "subcategory":"Hobbies, Toys, & Games",
            "type":"Retail Goods"
        },
        {
            "category":"Shopping",
            "subcategory":"Musical Instruments",
            "type":"Retail Goods"
        }
    ],
    "sg:phone":"+1 561 483 9991",
    "sg:postcode":"33432",
    "sg:province":"FL",
    "sg:tags":[
        "table",
        "supply",
        "accessory"
    ],
    "wof:name":"Billiard Tables and More",
    "wof:placetype":"venue"
},
  "geometry": {"coordinates":[-80.17469199999999,26.367819],"type":"Point"}
}