{
  "type": "Feature",
  "properties": {
    "iso:country":"US",
    "sg:address":"2712 N 58th St",
    "sg:city":"Tampa",
    "sg:classifiers":[
        {
            "category":"Home & Garden",
            "subcategory":"Building Materials",
            "type":"Retail Goods"
        }
    ],
    "sg:phone":"+1 813 635 9695",
    "sg:postcode":"33619",
    "sg:province":"FL",
    "sg:tags":[
        "door"
    ],
    "wof:name":"Commercial Door Int'l Inc",
    "wof:placetype":"venue"
},
  "geometry": {"coordinates":[-82.389426,27.968426],"type":"Point"}
}