{
  "type": "Feature",
  "properties": {
    "iso:country":"US",
    "sg:address":"2206 N West Shore Blvd",
    "sg:city":"Tampa",
    "sg:classifiers":[
        {
            "category":"Professional",
            "type":"Services"
        }
    ],
    "sg:phone":"+1 813 639 4235",
    "sg:postcode":"33607",
    "sg:province":"FL",
    "sg:tags":[
        "establishment"
    ],
    "wof:name":"Tartan Wealth Management",
    "wof:placetype":"venue"
},
  "geometry": {"coordinates":[-82.5241,27.963003],"type":"Point"}
}