{
  "type": "Feature",
  "properties": {
    "iso:country":"US",
    "sg:address":"928 N Federal Hwy",
    "sg:city":"Hollywood",
    "sg:phone":"+1 954 925 4287",
    "sg:postcode":"33020",
    "sg:province":"FL",
    "sg:tags":[
        "video",
        "conferencing"
    ],
    "sg:website":"www.4avs.com",
    "wof:name":"Audio Visual Solutions Corp",
    "wof:placetype":"venue"
},
  "geometry": {"coordinates":[-80.143304,26.020535],"type":"Point"}
}