{
  "type": "Feature",
  "properties": {
    "iso:country":"US",
    "sg:address":"102 SE 10 Ave",
    "sg:city":"Gainesville",
    "sg:classifiers":[
        {
            "category":"Insurance",
            "subcategory":"Hazard Insurance",
            "type":"Services"
        }
    ],
    "sg:phone":"+1 352 377 7135",
    "sg:postcode":"32601",
    "sg:province":"FL",
    "sg:tags":[
        "bond"
    ],
    "wof:name":"Agency Bail Bonds",
    "wof:placetype":"venue"
},
  "geometry": {"coordinates":[-82.32124,29.641085],"type":"Point"}
}