{
  "type": "Feature",
  "properties": {
    "iso:country":"US",
    "sg:address":"2363 Blanding Blvd",
    "sg:city":"Jacksonville",
    "sg:classifiers":[
        {
            "category":"Organizations",
            "subcategory":"Religious Organization",
            "type":"Services"
        }
    ],
    "sg:phone":"+1 904 388 6578",
    "sg:postcode":"32210",
    "sg:province":"FL",
    "wof:name":"Lakeshore Baptist Church Inc",
    "wof:placetype":"venue"
},
  "geometry": {"coordinates":[-81.730698,30.275582],"type":"Point"}
}