{
  "type": "Feature",
  "properties": {
    "iso:country":"US",
    "sg:address":"1523 SE 42nd Ter",
    "sg:city":"Cape Coral",
    "sg:classifiers":[
        {
            "category":"Building & Trades",
            "subcategory":"Cleaning & Sanitation",
            "type":"Services"
        }
    ],
    "sg:phone":"+1 239 540 1640",
    "sg:postcode":"33904",
    "sg:province":"FL",
    "sg:tags":[
        "maintenance"
    ],
    "wof:name":"A1 Merola Services",
    "wof:placetype":"venue"
},
  "geometry": {"coordinates":[-81.944495,26.573197],"type":"Point"}
}