{
  "type": "Feature",
  "properties": {
    "iso:country":"US",
    "sg:address":"4000 Newberry Rd",
    "sg:city":"Gainesville",
    "sg:classifiers":[
        {
            "category":"Personal",
            "type":"Services"
        }
    ],
    "sg:phone":"+1 352 367 2541",
    "sg:postcode":"32607",
    "sg:province":"FL",
    "sg:tags":[
        "consulting",
        "management",
        "program",
        "fitness",
        "r",
        "exercise",
        "physical"
    ],
    "wof:name":"Solo Pro",
    "wof:placetype":"venue"
},
  "geometry": {"coordinates":[-82.384158,29.65362],"type":"Point"}
}