{
  "type": "Feature",
  "properties": {
    "iso:country":"US",
    "sg:address":"632 86th St",
    "sg:city":"Miami Beach",
    "sg:classifiers":[
        {
            "category":"Wholesale",
            "subcategory":"Jewelry",
            "type":"Manufacturing & Wholesale Goods"
        }
    ],
    "sg:phone":"+1 305 861 2639",
    "sg:postcode":"33141",
    "sg:province":"FL",
    "sg:tags":[
        "stone"
    ],
    "wof:name":"Marcela C Paredes",
    "wof:placetype":"venue"
},
  "geometry": {"coordinates":[-80.128432,25.870313],"type":"Point"}
}