{
  "type": "Feature",
  "properties": {
    "iso:country":"US",
    "sg:address":"4925 Webb Rd",
    "sg:city":"Tampa",
    "sg:classifiers":[
        {
            "category":"Education",
            "subcategory":"School",
            "type":"Public Place"
        }
    ],
    "sg:phone":"+1 813 872 5382",
    "sg:postcode":"33615",
    "sg:province":"FL",
    "sg:tags":[
        "elementary"
    ],
    "wof:name":"Bay Crest Elementary School",
    "wof:placetype":"venue"
},
  "geometry": {"coordinates":[-82.575056,27.99296],"type":"Point"}
}