{
  "type": "Feature",
  "properties": {
    "addr:full":"2101 N University Dr Fort Lauderdale FL 33322",
    "addr:housenumber":"2101",
    "addr:postcode":"33322",
    "addr:street":"N University Dr",
    "iso:country":"US",
    "sg:address":"2101 N University Dr",
    "sg:city":"Fort Lauderdale",
    "sg:classifiers":[
        {
            "category":"Personal",
            "type":"Services"
        }
    ],
    "sg:phone":"+1 954 747 9826",
    "sg:postcode":"33322",
    "sg:province":"FL",
    "wof:name":"Atomic Tan Inc",
    "wof:placetype":"venue"
},
  "geometry": {"coordinates":[-80.257114,26.151475],"type":"Point"}
}