{
  "type": "Feature",
  "properties": {
    "addr:full":"7051 Dr Phillips Blvd Orlando FL 32819",
    "addr:housenumber":"7051",
    "addr:postcode":"32819",
    "addr:street":"Dr Phillips Blvd",
    "iso:country":"US",
    "sg:address":"7051 Dr Phillips Blvd",
    "sg:city":"Orlando",
    "sg:classifiers":[
        {
            "category":"Health Services",
            "subcategory":"Doctor",
            "type":"Services"
        }
    ],
    "sg:phone":"+1 407 345 0005",
    "sg:postcode":"32819",
    "sg:province":"FL",
    "sg:tags":[
        "physician",
        "surgeon"
    ],
    "wof:name":"Southwest Internal Medicine",
    "wof:placetype":"venue"
},
  "geometry": {"coordinates":[-81.491433,28.459255],"type":"Point"}
}