{
  "type": "Feature",
  "properties": {
    "iso:country":"US",
    "sg:address":"20851 Hammock Greens Ln",
    "sg:city":"Estero",
    "sg:classifiers":[
        {
            "category":"Real Estate",
            "subcategory":"Real Estate Agent",
            "type":"Services"
        }
    ],
    "sg:phone":"+1 239 948 7650",
    "sg:postcode":"33928",
    "sg:province":"FL",
    "wof:name":"Olympus State",
    "wof:placetype":"venue"
},
  "geometry": {"coordinates":[-81.827445,26.431986],"type":"Point"}
}