{
  "type": "Feature",
  "properties": {
    "addr:full":"5743 NW 100th Way Coral Springs FL 33076",
    "addr:housenumber":"5743",
    "addr:postcode":"33076",
    "addr:street":"Nw 100Th Way",
    "iso:country":"US",
    "sg:address":"5743 NW 100th Way",
    "sg:city":"Coral Springs",
    "sg:classifiers":[
        {
            "category":"Professional",
            "subcategory":"Computer Services",
            "type":"Services"
        }
    ],
    "sg:phone":"+1 954 757 2682",
    "sg:postcode":"33076",
    "sg:province":"FL",
    "sg:tags":[
        "consultant",
        "designer",
        "related"
    ],
    "wof:name":"Real Time Alliances Inc",
    "wof:placetype":"venue"
},
  "geometry": {"coordinates":[-80.25992100000001,26.300627],"type":"Point"}
}