{
  "type": "Feature",
  "properties": {
    "addr:full":"2814 NW 79th Ave Miami FL 33122",
    "addr:housenumber":"2814",
    "addr:postcode":"33122",
    "addr:street":"Nw 79Th Ave",
    "iso:country":"US",
    "sg:address":"2814 NW 79th Ave",
    "sg:city":"Miami",
    "sg:classifiers":[
        {
            "category":"Wholesale",
            "subcategory":"Home Furnishings",
            "type":"Manufacturing & Wholesale Goods"
        }
    ],
    "sg:phone":"+1 305 592 9295",
    "sg:postcode":"33122",
    "sg:province":"FL",
    "sg:tags":[
        "floor",
        "covering"
    ],
    "wof:name":"Wholesale Flooring Source",
    "wof:placetype":"venue"
},
  "geometry": {"coordinates":[-80.325073,25.798089],"type":"Point"}
}