{
  "type": "Feature",
  "properties": {
    "iso:country":"US",
    "sg:address":"6000 Coral Way",
    "sg:city":"Bradenton",
    "sg:classifiers":[
        {
            "category":"Real Estate",
            "subcategory":"Real Estate Operator",
            "type":"Services"
        }
    ],
    "sg:phone":"+1 941 753 4697",
    "sg:postcode":"34207",
    "sg:province":"FL",
    "sg:tags":[
        "condominium"
    ],
    "wof:name":"Parkway Villas Condominium",
    "wof:placetype":"venue"
},
  "geometry": {"coordinates":[-82.583556,27.433317],"type":"Point"}
}