{
  "type": "Feature",
  "properties": {
    "iso:country":"US",
    "sg:address":"298 W 2nd St",
    "sg:city":"Chuluota",
    "sg:classifiers":[
        {
            "category":"Building & Trades",
            "subcategory":"Landscaping Services",
            "type":"Services"
        }
    ],
    "sg:phone":"+1 407 359 1050",
    "sg:postcode":"32766",
    "sg:province":"FL",
    "sg:tags":[
        "landscape",
        "contractor"
    ],
    "wof:name":"Victor's Landscaping",
    "wof:placetype":"venue"
},
  "geometry": {"coordinates":[-81.13381200000001,28.644901],"type":"Point"}
}