{
  "type": "Feature",
  "properties": {
    "iso:country":"US",
    "sg:address":"1784 NW Madrid Way",
    "sg:city":"Boca Raton",
    "sg:classifiers":[
        {
            "category":"Building & Trades",
            "subcategory":"Construction",
            "type":"Services"
        }
    ],
    "sg:phone":"+1 561 447 6655",
    "sg:postcode":"33432",
    "sg:province":"FL",
    "sg:tags":[
        "home",
        "builder"
    ],
    "wof:name":"Dream Homes",
    "wof:placetype":"venue"
},
  "geometry": {"coordinates":[-80.08757300000001,26.366123],"type":"Point"}
}