{
  "type": "Feature",
  "properties": {
    "iso:country":"US",
    "sg:address":"8963 103rd St",
    "sg:city":"Jacksonville",
    "sg:classifiers":[
        {
            "category":"Building & Trades",
            "subcategory":"Landscaping Services",
            "type":"Services"
        }
    ],
    "sg:phone":"+1 904 772 8847",
    "sg:postcode":"32210",
    "sg:province":"FL",
    "sg:tags":[
        "sod",
        "sodding"
    ],
    "sg:website":"www.sodserviceofjax.com",
    "wof:name":"Sod Service Of Jacksonville",
    "wof:placetype":"venue"
},
  "geometry": {"coordinates":[-81.801464,30.247685],"type":"Point"}
}