{
  "type": "Feature",
  "properties": {
    "iso:country":"US",
    "sg:address":"7977 W 12th Ave",
    "sg:city":"Hialeah",
    "sg:classifiers":[
        {
            "category":"Banks & Credit Unions",
            "subcategory":"Financial Services",
            "type":"Services"
        }
    ],
    "sg:phone":"+1 305 809 7595",
    "sg:postcode":"33014",
    "sg:province":"FL",
    "sg:tags":[
        "advising"
    ],
    "wof:name":"Hialeah Merchant Accounts Processing",
    "wof:placetype":"venue"
},
  "geometry": {"coordinates":[-80.30570899999999,25.896292],"type":"Point"}
}