{
  "type": "Feature",
  "properties": {
    "iso:country":"US",
    "sg:address":"7530 Argyle Forest Blvd",
    "sg:city":"Jacksonville",
    "sg:classifiers":[
        {
            "category":"Autos & Motor Vehicles",
            "subcategory":"Auto Supplies",
            "type":"Retail Goods"
        }
    ],
    "sg:phone":"+1 904 777 3250",
    "sg:postcode":"32244",
    "sg:province":"FL",
    "sg:website":"www.stage6motorsports.com",
    "wof:name":"Stage 6 Motor Sports",
    "wof:placetype":"venue"
},
  "geometry": {"coordinates":[-81.769862,30.196395],"type":"Point"}
}