{
  "type": "Feature",
  "properties": {
    "iso:country":"US",
    "sg:address":"14680 118th Ave N",
    "sg:city":"Largo",
    "sg:classifiers":[
        {
            "category":"Professional",
            "type":"Services"
        }
    ],
    "sg:phone":"+1 727 596 2540",
    "sg:postcode":"33774",
    "sg:province":"FL",
    "sg:tags":[
        "establishment"
    ],
    "wof:name":"Cyberstainless Corp",
    "wof:placetype":"venue"
},
  "geometry": {"coordinates":[-82.841183,27.880412],"type":"Point"}
}