{
  "type": "Feature",
  "properties": {
    "addr:full":"8714 Mahogany Ave Fort Lauderdale FL 33324",
    "addr:housenumber":"8714",
    "addr:postcode":"33324",
    "addr:street":"Mahogany Ave",
    "iso:country":"US",
    "sg:address":"8714 Mahogany Ave",
    "sg:city":"Fort Lauderdale",
    "sg:classifiers":[
        {
            "category":"Professional",
            "subcategory":"Management & Consulting",
            "type":"Services"
        }
    ],
    "sg:phone":"+1 954 476 2323",
    "sg:postcode":"33324",
    "sg:province":"FL",
    "wof:name":"OSI Systems Inc",
    "wof:placetype":"venue"
},
  "geometry": {"coordinates":[-80.265778,26.115272],"type":"Point"}
}