{
  "type": "Feature",
  "properties": {
    "iso:country":"US",
    "sg:address":"3905 Wekiva Springs Rd",
    "sg:city":"Longwood",
    "sg:classifiers":[
        {
            "category":"Shopping",
            "subcategory":"Pharmacy",
            "type":"Retail Goods"
        }
    ],
    "sg:phone":"+1 407 862 8086",
    "sg:postcode":"32779",
    "sg:province":"FL",
    "sg:tags":[
        "drug",
        "store"
    ],
    "wof:name":"CVS",
    "wof:placetype":"venue"
},
  "geometry": {"coordinates":[-81.443298,28.707347],"type":"Point"}
}