{
  "type": "Feature",
  "properties": {
    "addr:full":"14925 Bruce B Downs Blvd Tampa FL 33613",
    "addr:housenumber":"14925",
    "addr:postcode":"33613",
    "addr:street":"Bruce B Downs Blvd",
    "iso:country":"US",
    "sg:address":"14925 Bruce B Downs Blvd",
    "sg:city":"Tampa",
    "sg:classifiers":[
        {
            "category":"Restaurant",
            "type":"Food & Drink"
        }
    ],
    "sg:menulink":"http://www.allmenus.com/fl/tampa/46474-jersey-mikes/menu/",
    "sg:phone":"+1 813 910 1118",
    "sg:postcode":"33613",
    "sg:province":"FL",
    "sg:tags":[
        "american",
        "sandwich"
    ],
    "wof:name":"Jersey Mike's",
    "wof:placetype":"venue"
},
  "geometry": {"coordinates":[-82.412266,28.083774],"type":"Point"}
}