{
  "type": "Feature",
  "properties": {
    "iso:country":"US",
    "sg:address":"2421 S State Rd 7",
    "sg:city":"Hollywood",
    "sg:classifiers":[
        {
            "category":"Wholesale",
            "subcategory":"Furniture",
            "type":"Manufacturing & Wholesale Goods"
        }
    ],
    "sg:phone":"+1 954 894 1402",
    "sg:postcode":"33023",
    "sg:province":"FL",
    "wof:name":"Half Price Mattress Inc",
    "wof:placetype":"venue"
},
  "geometry": {"coordinates":[-80.20674,25.989099],"type":"Point"}
}