{
  "type": "Feature",
  "properties": {
    "iso:country":"US",
    "sg:address":"6051 Sun Blvd W",
    "sg:city":"Saint Petersburg",
    "sg:classifiers":[
        {
            "category":"Manufacturing",
            "subcategory":"Furniture",
            "type":"Manufacturing & Wholesale Goods"
        }
    ],
    "sg:phone":"+1 727 867 5774",
    "sg:postcode":"33715",
    "sg:province":"FL",
    "sg:tags":[
        "household",
        "wood",
        "mfg"
    ],
    "wof:name":"McLagan Mfg",
    "wof:placetype":"venue"
},
  "geometry": {"coordinates":[-82.717945,27.713429],"type":"Point"}
}