{
  "type": "Feature",
  "properties": {
    "iso:country":"US",
    "sg:address":"8339 W Flagler St",
    "sg:city":"Miami",
    "sg:classifiers":[
        {
            "category":"Shopping",
            "subcategory":"Jewelry",
            "type":"Retail Goods"
        }
    ],
    "sg:phone":"+1 305 264 4686",
    "sg:postcode":"33144",
    "sg:province":"FL",
    "wof:name":"Luany Jewelers IV",
    "wof:placetype":"venue"
},
  "geometry": {"coordinates":[-80.330803,25.769699],"type":"Point"}
}