{
  "type": "Feature",
  "properties": {
    "iso:country":"US",
    "sg:address":"9887 4th St N",
    "sg:city":"St Petersburg",
    "sg:classifiers":[
        {
            "category":"Wholesale",
            "subcategory":"Sporting Goods",
            "type":"Manufacturing & Wholesale Goods"
        }
    ],
    "sg:phone":"+1 727 577 5944",
    "sg:postcode":"33702",
    "sg:province":"FL",
    "sg:tags":[
        "salon",
        "tanning",
        "supply"
    ],
    "sg:website":"www.millenniumtanning.com",
    "wof:name":"Millennium Tanning Products",
    "wof:placetype":"venue"
},
  "geometry": {"coordinates":[-82.63873599999999,27.860881],"type":"Point"}
}