{
  "type": "Feature",
  "properties": {
    "addr:full":"3285 Conway Blvd Port Charlotte FL 33952",
    "addr:housenumber":"3285",
    "addr:postcode":"33952",
    "addr:street":"Conway Blvd",
    "iso:country":"US",
    "sg:address":"3285 Conway Blvd",
    "sg:city":"Port Charlotte",
    "sg:classifiers":[
        {
            "category":"Building & Trades",
            "subcategory":"Electrical",
            "type":"Services"
        }
    ],
    "sg:phone":"+1 941 625 7493",
    "sg:postcode":"33952",
    "sg:province":"FL",
    "sg:tags":[
        "electrical",
        "electric",
        "contractor"
    ],
    "wof:name":"Karl's Electric Co",
    "wof:placetype":"venue"
},
  "geometry": {"coordinates":[-82.08842,26.98058],"type":"Point"}
}