{
  "type": "Feature",
  "properties": {
    "iso:country":"US",
    "sg:address":"1715 E Young Cir",
    "sg:city":"Hollywood",
    "sg:classifiers":[
        {
            "category":"Arena",
            "subcategory":"Sports Club",
            "type":"Entertainment"
        }
    ],
    "sg:phone":"+1 954 920 5824",
    "sg:postcode":"33020",
    "sg:province":"FL",
    "sg:tags":[
        "health"
    ],
    "wof:name":"Anytime Fitness Of Hollywood",
    "wof:placetype":"venue"
},
  "geometry": {"coordinates":[-80.141734,26.011334],"type":"Point"}
}