{
  "type": "Feature",
  "properties": {
    "addr:full":"16500 Slater Rd Fort Myers FL 33917",
    "addr:housenumber":"16500",
    "addr:postcode":"33917",
    "addr:street":"Slater Rd",
    "iso:country":"US",
    "sg:address":"16500 Slater Rd",
    "sg:city":"Fort Myers",
    "sg:classifiers":[
        {
            "category":"Real Estate",
            "subcategory":"Real Estate Operator",
            "type":"Services"
        }
    ],
    "sg:phone":"+1 239 543 4701",
    "sg:postcode":"33917",
    "sg:province":"FL",
    "sg:tags":[
        "mobile",
        "home",
        "site"
    ],
    "wof:name":"Julia & Siesta Parks",
    "wof:placetype":"venue"
},
  "geometry": {"coordinates":[-81.853004,26.703402],"type":"Point"}
}