{
  "type": "Feature",
  "properties": {
    "iso:country":"US",
    "sg:address":"4573 Phipps Dr",
    "sg:city":"Daytona Beach",
    "sg:classifiers":[
        {
            "category":"Building & Trades",
            "subcategory":"Construction",
            "type":"Services"
        }
    ],
    "sg:phone":"+1 386 756 4715",
    "sg:postcode":"32129",
    "sg:province":"FL",
    "sg:tags":[
        "acoustical",
        "contractor"
    ],
    "wof:name":"K B Sargent Enterprises",
    "wof:placetype":"venue"
},
  "geometry": {"coordinates":[-81.02674500000001,29.134637],"type":"Point"}
}