{
  "type": "Feature",
  "properties": {
    "addr:full":"177 Park Land Dr Lake Placid FL 33852",
    "addr:housenumber":"177",
    "addr:postcode":"33852",
    "addr:street":"Park Land Dr",
    "iso:country":"US",
    "sg:address":"177 Park Land Dr",
    "sg:city":"Lake Placid",
    "sg:classifiers":[
        {
            "category":"Building & Trades",
            "subcategory":"Construction",
            "type":"Services"
        }
    ],
    "sg:phone":"+1 863 699 1442",
    "sg:postcode":"33852",
    "sg:province":"FL",
    "sg:tags":[
        "drainage",
        "contractor"
    ],
    "wof:name":"Dallas E Duppenthaler Jr",
    "wof:placetype":"venue"
},
  "geometry": {"coordinates":[-81.392348,27.190202],"type":"Point"}
}