{
  "type": "Feature",
  "properties": {
    "addr:full":"5515 Roosevelt Blvd Jacksonville FL 32244",
    "addr:housenumber":"5515",
    "addr:postcode":"32244",
    "addr:street":"Roosevelt Blvd",
    "iso:country":"US",
    "sg:address":"5515 Roosevelt Blvd",
    "sg:city":"Jacksonville",
    "sg:classifiers":[
        {
            "category":"Banks & Credit Unions",
            "subcategory":"Bank",
            "type":"Services"
        }
    ],
    "sg:phone":"+1 904 389 3688",
    "sg:postcode":"32244",
    "sg:province":"FL",
    "sg:tags":[
        "depository",
        "banking"
    ],
    "wof:name":"Cash Advance",
    "wof:placetype":"venue"
},
  "geometry": {"coordinates":[-81.697079,30.24513],"type":"Point"}
}