{
  "type": "Feature",
  "properties": {
    "iso:country":"US",
    "sg:address":"8700 Cortez Rd W",
    "sg:city":"Bradenton",
    "sg:phone":"+1 888 701 9482",
    "sg:postcode":"34210",
    "sg:province":"FL",
    "wof:name":"Planet Stone Marble & Granite",
    "wof:placetype":"venue"
},
  "geometry": {"coordinates":[-82.649866,27.461679],"type":"Point"}
}