{
  "type": "Feature",
  "properties": {
    "iso:country":"US",
    "sg:address":"3405 Warren Park Rd",
    "sg:city":"Belle Isle",
    "sg:classifiers":[
        {
            "category":"Building & Trades",
            "subcategory":"Plumbing",
            "type":"Services"
        }
    ],
    "sg:phone":"+1 407 888 3344",
    "sg:postcode":"32812",
    "sg:province":"FL",
    "sg:tags":[
        "conditioning",
        "air",
        "system",
        "contractor"
    ],
    "wof:name":"Chill Air Inc",
    "wof:placetype":"venue"
},
  "geometry": {"coordinates":[-81.33893999999999,28.463071],"type":"Point"}
}