{
  "type": "Feature",
  "properties": {
    "addr:full":"3750 Gunn Hwy Tampa FL 33618",
    "addr:housenumber":"3750",
    "addr:postcode":"33618",
    "addr:street":"Gunn Hwy",
    "iso:country":"US",
    "sg:address":"3750 Gunn Hwy",
    "sg:city":"Tampa",
    "sg:classifiers":[
        {
            "category":"Professional",
            "subcategory":"Management & Consulting",
            "type":"Services"
        }
    ],
    "sg:phone":"+1 813 514 1470",
    "sg:postcode":"33618",
    "sg:province":"FL",
    "sg:tags":[
        "personnel",
        "consultant"
    ],
    "wof:name":"Food Team",
    "wof:placetype":"venue"
},
  "geometry": {"coordinates":[-82.50797900000001,28.038092],"type":"Point"}
}