{
  "type": "Feature",
  "properties": {
    "addr:full":"834 Damek Ter SW Palm Bay FL 32908",
    "addr:housenumber":"834",
    "addr:postcode":"32908",
    "addr:street":"Damek Ter Sw",
    "iso:country":"US",
    "sg:address":"834 Damek Ter SW",
    "sg:city":"Palm Bay",
    "sg:classifiers":[
        {
            "category":"Autos & Motor Vehicles",
            "subcategory":"Motorcycle Sales",
            "type":"Retail Goods"
        }
    ],
    "sg:phone":"+1 321 956 7807",
    "sg:postcode":"32908",
    "sg:province":"FL",
    "wof:name":"A & A Performance",
    "wof:placetype":"venue"
},
  "geometry": {"coordinates":[-80.68571,27.979784],"type":"Point"}
}