{
  "type": "Feature",
  "properties": {
    "iso:country":"US",
    "sg:address":"15701 NW 2nd Ave",
    "sg:city":"Miami",
    "sg:classifiers":[
        {
            "category":"Building & Trades",
            "subcategory":"Construction",
            "type":"Services"
        }
    ],
    "sg:phone":"+1 305 837 7669",
    "sg:postcode":"33169",
    "sg:province":"FL",
    "sg:tags":[
        "contractor"
    ],
    "wof:name":"C&C Carpet Installer",
    "wof:placetype":"venue"
},
  "geometry": {"coordinates":[-80.203822,25.917949],"type":"Point"}
}