{
  "type": "Feature",
  "properties": {
    "addr:full":"1822 Nantucket Dr Sun City Center FL 33573",
    "addr:housenumber":"1822",
    "addr:postcode":"33573",
    "addr:street":"Nantucket Dr",
    "iso:country":"US",
    "sg:address":"1822 Nantucket Dr",
    "sg:city":"Sun City Center",
    "sg:classifiers":[
        {
            "category":"Banks & Credit Unions",
            "subcategory":"Financial Services",
            "type":"Services"
        }
    ],
    "sg:phone":"+1 813 633 8074",
    "sg:postcode":"33573",
    "sg:province":"FL",
    "sg:tags":[
        "trust",
        "management"
    ],
    "wof:name":"Joyce B Aspland Trust",
    "wof:placetype":"venue"
},
  "geometry": {"coordinates":[-82.384073,27.700836],"type":"Point"}
}