{
  "type": "Feature",
  "properties": {
    "iso:country":"US",
    "sg:address":"1514 SE Port St Lucie Blvd",
    "sg:city":"Port St Lucie",
    "sg:classifiers":[
        {
            "category":"Real Estate",
            "subcategory":"Real Estate Services",
            "type":"Services"
        }
    ],
    "sg:phone":"+1 772 337 1009",
    "sg:postcode":"34952",
    "sg:province":"FL",
    "sg:tags":[
        "company",
        "title"
    ],
    "wof:name":"Martin St Lucie Title Inc",
    "wof:placetype":"venue"
},
  "geometry": {"coordinates":[-80.306482,27.271193],"type":"Point"}
}