{
  "type": "Feature",
  "properties": {
    "addr:full":"3153 22nd Ave N Saint Petersburg FL 33713",
    "addr:housenumber":"3153",
    "addr:postcode":"33713",
    "addr:street":"22Nd Ave N",
    "iso:country":"US",
    "sg:address":"3153 22nd Ave N",
    "sg:city":"Saint Petersburg",
    "sg:classifiers":[
        {
            "category":"Retail",
            "subcategory":"Auto Repair",
            "type":"Services"
        }
    ],
    "sg:phone":"+1 727 321 6737",
    "sg:postcode":"33713",
    "sg:province":"FL",
    "sg:tags":[
        "general"
    ],
    "wof:name":"Daves Suncoast Chevron",
    "wof:placetype":"venue"
},
  "geometry": {"coordinates":[-82.676486,27.791959],"type":"Point"}
}