{
  "type": "Feature",
  "properties": {
    "iso:country":"US",
    "sg:address":"1465 Compass Ct",
    "sg:city":"Kissimmee",
    "sg:classifiers":[
        {
            "category":"Utilities",
            "subcategory":"Telephone",
            "type":"Services"
        }
    ],
    "sg:phone":"+1 407 846 1460",
    "sg:postcode":"34744",
    "sg:province":"FL",
    "sg:tags":[
        "communications"
    ],
    "wof:name":"Jays Cee Collectibles",
    "wof:placetype":"venue"
},
  "geometry": {"coordinates":[-81.379825,28.254525],"type":"Point"}
}