{
  "type": "Feature",
  "properties": {
    "addr:full":"1339 W Granada Blvd Ormond Beach FL 32174",
    "addr:housenumber":"1339",
    "addr:postcode":"32174",
    "addr:street":"W Granada Blvd",
    "iso:country":"US",
    "sg:address":"1339 W Granada Blvd",
    "sg:city":"Ormond Beach",
    "sg:classifiers":[
        {
            "category":"Banks & Credit Unions",
            "subcategory":"Bank",
            "type":"Services"
        }
    ],
    "sg:phone":"+1 386 673 0500",
    "sg:postcode":"32174",
    "sg:province":"FL",
    "sg:tags":[
        "loan",
        "real estate"
    ],
    "wof:name":"First Pacific Mortgage",
    "wof:placetype":"venue"
},
  "geometry": {"coordinates":[-81.105626,29.264455],"type":"Point"}
}