{
  "type": "Feature",
  "properties": {
    "iso:country":"US",
    "sg:address":"3800 Town Center Blvd",
    "sg:city":"Orlando",
    "sg:classifiers":[
        {
            "category":"Social Services",
            "subcategory":"Adult Care",
            "type":"Services"
        }
    ],
    "sg:phone":"+1 407 251 8088",
    "sg:postcode":"32837",
    "sg:province":"FL",
    "sg:tags":[
        "home",
        "residential"
    ],
    "wof:name":"Gables At Hunter's Creek",
    "wof:placetype":"venue"
},
  "geometry": {"coordinates":[-81.42406699999999,28.364268],"type":"Point"}
}