{
  "type": "Feature",
  "properties": {
    "iso:country":"US",
    "sg:address":"4125 Tamiami Trl",
    "sg:city":"Naples",
    "sg:classifiers":[
        {
            "category":"Personal",
            "subcategory":"Beauty Salon",
            "type":"Services"
        }
    ],
    "sg:phone":"+1 239 649 4443",
    "sg:postcode":"34112",
    "sg:province":"FL",
    "sg:tags":[
        "hair"
    ],
    "wof:name":"First Choice Haircutter Ltd",
    "wof:placetype":"venue"
},
  "geometry": {"coordinates":[-81.75555199999999,26.115647],"type":"Point"}
}