{
  "type": "Feature",
  "properties": {
    "addr:full":"48 Fairway Cir New Smyrna Beach FL 32168",
    "addr:housenumber":"48",
    "addr:postcode":"32168",
    "addr:street":"Fairway Cir",
    "iso:country":"US",
    "sg:address":"48 Fairway Cir",
    "sg:city":"New Smyrna Beach",
    "sg:classifiers":[
        {
            "category":"Building & Trades",
            "subcategory":"Plumbing",
            "type":"Services"
        }
    ],
    "sg:phone":"+1 386 423 4239",
    "sg:postcode":"32168",
    "sg:province":"FL",
    "sg:tags":[
        "conditioning",
        "air",
        "heating",
        "contractor"
    ],
    "wof:name":"Moonlighting AC & Heatin",
    "wof:placetype":"venue"
},
  "geometry": {"coordinates":[-80.94055,29.033645],"type":"Point"}
}