{
  "type": "Feature",
  "properties": {
    "addr:full":"2641 Sunset Point Rd Clearwater FL 33759",
    "addr:housenumber":"2641",
    "addr:postcode":"33759",
    "addr:street":"Sunset Point Rd",
    "iso:country":"US",
    "sg:address":"2641 Sunset Point Rd",
    "sg:city":"Clearwater",
    "sg:classifiers":[
        {
            "category":"Real Estate",
            "subcategory":"Architect",
            "type":"Services"
        }
    ],
    "sg:phone":"+1 727 725 0111",
    "sg:postcode":"33759",
    "sg:province":"FL",
    "wof:name":"Bacon Group Inc",
    "wof:placetype":"venue"
},
  "geometry": {"coordinates":[-82.72800700000001,27.990749],"type":"Point"}
}