{
  "type": "Feature",
  "properties": {
    "iso:country":"US",
    "sg:address":"118 W Orange St",
    "sg:city":"Altamonte Springs",
    "sg:classifiers":[
        {
            "category":"Professional",
            "subcategory":"Accounting & Tax Preparation",
            "type":"Services"
        }
    ],
    "sg:phone":"+1 407 862 0305",
    "sg:postcode":"32714",
    "sg:province":"FL",
    "sg:tags":[
        "accountant"
    ],
    "wof:name":"Kelley & Goldberg Cpa's",
    "wof:placetype":"venue"
},
  "geometry": {"coordinates":[-81.389297,28.6738],"type":"Point"}
}