{
  "type": "Feature",
  "properties": {
    "iso:country":"US",
    "sg:address":"324 W Strong St",
    "sg:city":"Pensacola",
    "sg:classifiers":[
        {
            "category":"Shopping",
            "subcategory":"Gifts & Souvenirs",
            "type":"Retail Goods"
        }
    ],
    "sg:phone":"+1 850 434 6048",
    "sg:postcode":"32501",
    "sg:province":"FL",
    "wof:name":"Elberts Imports/Gift",
    "wof:placetype":"venue"
},
  "geometry": {"coordinates":[-87.222393,30.42153],"type":"Point"}
}