{
  "type": "Feature",
  "properties": {
    "iso:country":"US",
    "sg:address":"1707 Blanding Blvd",
    "sg:city":"Middleburg",
    "sg:classifiers":[
        {
            "category":"Building & Trades",
            "subcategory":"Construction",
            "type":"Services"
        }
    ],
    "sg:phone":"+1 904 282 7590",
    "sg:postcode":"32068",
    "sg:province":"FL",
    "sg:tags":[
        "home",
        "builder"
    ],
    "wof:name":"Clay County Habitat For Hmnty",
    "wof:placetype":"venue"
},
  "geometry": {"coordinates":[-81.822582,30.108248],"type":"Point"}
}