{
  "type": "Feature",
  "properties": {
    "addr:full":"722 E Elkcam Cir Marco Island FL 34145",
    "addr:housenumber":"722",
    "addr:postcode":"34145",
    "addr:street":"E Elkcam Cir",
    "iso:country":"US",
    "sg:address":"722 E Elkcam Cir",
    "sg:city":"Marco Island",
    "sg:classifiers":[
        {
            "category":"Retail",
            "subcategory":"Repair Shop",
            "type":"Services"
        }
    ],
    "sg:phone":"+1 239 394 1464",
    "sg:postcode":"34145",
    "sg:province":"FL",
    "sg:tags":[
        "welding"
    ],
    "wof:name":"Jerry Ammons Welding Svc",
    "wof:placetype":"venue"
},
  "geometry": {"coordinates":[-81.72189400000001,25.955577],"type":"Point"}
}