{
  "type": "Feature",
  "properties": {
    "addr:full":"2955 NW 73rd St Miami FL 33147",
    "addr:housenumber":"2955",
    "addr:postcode":"33147",
    "addr:street":"Nw 73Rd St",
    "iso:country":"US",
    "sg:address":"2955 NW 73rd St",
    "sg:city":"Miami",
    "sg:classifiers":[
        {
            "category":"Building & Trades",
            "subcategory":"Construction",
            "type":"Services"
        }
    ],
    "sg:phone":"+1 305 969 3644",
    "sg:postcode":"33147",
    "sg:province":"FL",
    "sg:tags":[
        "contractor"
    ],
    "wof:name":"Absolute Demolition Inc",
    "wof:placetype":"venue"
},
  "geometry": {"coordinates":[-80.24554500000001,25.840437],"type":"Point"}
}