{
  "type": "Feature",
  "properties": {
    "addr:full":"6216 28th St E Bradenton FL 34203",
    "addr:housenumber":"6216",
    "addr:postcode":"34203",
    "addr:street":"28Th St",
    "iso:country":"US",
    "sg:address":"6216 28th St E",
    "sg:city":"Bradenton",
    "sg:classifiers":[
        {
            "category":"Wholesale",
            "subcategory":"Medical Equipment & Supplies",
            "type":"Manufacturing & Wholesale Goods"
        }
    ],
    "sg:phone":"+1 941 752 5811",
    "sg:postcode":"34203",
    "sg:province":"FL",
    "sg:tags":[
        "optical",
        "machinery"
    ],
    "sg:website":"http://www.americanphotonics.com",
    "wof:name":"American Photonics Co",
    "wof:placetype":"venue"
},
  "geometry": {"coordinates":[-82.528992,27.431194],"type":"Point"}
}