{
  "type": "Feature",
  "properties": {
    "iso:country":"US",
    "sg:address":"8203 Cooper Creek Blvd",
    "sg:city":"University Park",
    "sg:classifiers":[
        {
            "category":"Building & Trades",
            "subcategory":"Construction",
            "type":"Services"
        }
    ],
    "sg:phone":"+1 941 351 2854",
    "sg:postcode":"34201",
    "sg:province":"FL",
    "sg:tags":[
        "designer",
        "dealer",
        "pool",
        "swimming"
    ],
    "wof:name":"Splash Pools",
    "wof:placetype":"venue"
},
  "geometry": {"coordinates":[-82.45410800000001,27.39199],"type":"Point"}
}