{
  "type": "Feature",
  "properties": {
    "addr:full":"1673 Pine Bay Dr Lake Mary FL 32746",
    "addr:housenumber":"1673",
    "addr:postcode":"32746",
    "addr:street":"Pine Bay Dr",
    "iso:country":"US",
    "sg:address":"1673 Pine Bay Dr",
    "sg:city":"Lake Mary",
    "sg:classifiers":[
        {
            "category":"Real Estate",
            "subcategory":"Real Estate Operator",
            "type":"Services"
        }
    ],
    "sg:phone":"+1 407 833 0405",
    "sg:postcode":"32746",
    "sg:province":"FL",
    "sg:tags":[
        "property",
        "lessor"
    ],
    "wof:name":"Saz Development Inc",
    "wof:placetype":"venue"
},
  "geometry": {"coordinates":[-81.367205,28.730531],"type":"Point"}
}