{
  "type": "Feature",
  "properties": {
    "iso:country":"US",
    "sg:address":"700 Riveroak E",
    "sg:city":"Ormond Beach",
    "sg:classifiers":[
        {
            "category":"Manufacturing",
            "subcategory":"Tools & Machinery",
            "type":"Manufacturing & Wholesale Goods"
        }
    ],
    "sg:phone":"+1 386 671 7758",
    "sg:postcode":"32174",
    "sg:province":"FL",
    "sg:tags":[
        "machine",
        "mfg",
        "attachment",
        "accessory"
    ],
    "wof:name":"Pharmaceutika International",
    "wof:placetype":"venue"
},
  "geometry": {"coordinates":[-81.06615600000001,29.304831],"type":"Point"}
}