{
  "type": "Feature",
  "properties": {
    "iso:country":"US",
    "sg:address":"5584 Cortez Rd W",
    "sg:city":"Bradenton",
    "sg:classifiers":[
        {
            "category":"Food & Beverages",
            "subcategory":"Groceries & Convenience Stores",
            "type":"Retail Goods"
        }
    ],
    "sg:phone":"+1 941 794 1718",
    "sg:postcode":"34210",
    "sg:province":"FL",
    "sg:tags":[
        "product",
        "mfg"
    ],
    "wof:name":"Publix",
    "wof:placetype":"venue"
},
  "geometry": {"coordinates":[-82.618087,27.462392],"type":"Point"}
}