{
  "type": "Feature",
  "properties": {
    "iso:country":"US",
    "sg:address":"845 Morningview Ct",
    "sg:city":"Lakeland",
    "sg:classifiers":[
        {
            "category":"Food & Beverages",
            "subcategory":"Groceries & Convenience Stores",
            "type":"Retail Goods"
        }
    ],
    "sg:phone":"+1 941 379 5109",
    "sg:postcode":"33813",
    "sg:province":"FL",
    "sg:tags":[
        "market"
    ],
    "wof:name":"Radiant Food Store",
    "wof:placetype":"venue"
},
  "geometry": {"coordinates":[-81.951166,27.953584],"type":"Point"}
}