{
  "type": "Feature",
  "properties": {
    "iso:country":"US",
    "sg:address":"203 Royal Poinciana Way",
    "sg:city":"Palm Beach",
    "sg:classifiers":[
        {
            "category":"Health Services",
            "subcategory":"Health Practitioner",
            "type":"Services"
        }
    ],
    "sg:phone":"+1 561 832 6133",
    "sg:postcode":"33480",
    "sg:province":"FL",
    "wof:name":"Elizabeth Strnberg Shulman PHD",
    "wof:placetype":"venue"
},
  "geometry": {"coordinates":[-80.03844599999999,26.718434],"type":"Point"}
}