{
  "type": "Feature",
  "properties": {
    "addr:full":"24150 Tiseo Blvd Port Charlotte FL 33980",
    "addr:postcode":"24150;33980",
    "addr:street":"Tiseo Blvd",
    "iso:country":"US",
    "sg:address":"24150 Tiseo Blvd",
    "sg:city":"Port Charlotte",
    "sg:classifiers":[
        {
            "category":"Education",
            "subcategory":"Special Training",
            "type":"Public Place"
        }
    ],
    "sg:phone":"+1 941 764 7890",
    "sg:postcode":"33980",
    "sg:province":"FL",
    "sg:tags":[
        "tutoring"
    ],
    "wof:name":"Kumon Math & Reading Ctr",
    "wof:placetype":"venue"
},
  "geometry": {"coordinates":[-82.05440900000001,27.011928],"type":"Point"}
}