{
  "type": "Feature",
  "properties": {
    "iso:country":"US",
    "sg:address":"930 E Sunrise Blvd",
    "sg:city":"Fort Lauderdale",
    "sg:classifiers":[
        {
            "category":"Retail",
            "subcategory":"Laundry & Dry Cleaning",
            "type":"Services"
        }
    ],
    "sg:phone":"+1 954 522 2100",
    "sg:postcode":"33304",
    "sg:province":"FL",
    "sg:tags":[
        "diaper"
    ],
    "wof:name":"Diapers Etc Factory Outlet",
    "wof:placetype":"venue"
},
  "geometry": {"coordinates":[-80.133707,26.136977],"type":"Point"}
}