{
  "type": "Feature",
  "properties": {
    "iso:country":"US",
    "sg:address":"1743 N University Dr",
    "sg:city":"Fort Lauderdale",
    "sg:classifiers":[
        {
            "category":"Shopping",
            "type":"Retail Goods"
        },
        {
            "category":"Wholesale",
            "subcategory":"Home Furnishings",
            "type":"Manufacturing & Wholesale Goods"
        }
    ],
    "sg:phone":"+1 954 472 6699",
    "sg:postcode":"33322",
    "sg:province":"FL",
    "sg:tags":[
        "picture",
        "frame"
    ],
    "wof:name":"Create-A-Frame",
    "wof:placetype":"venue"
},
  "geometry": {"coordinates":[-80.256861,26.147007],"type":"Point"}
}