{
  "type": "Feature",
  "properties": {
    "iso:country":"US",
    "sg:address":"1725 28th St N",
    "sg:city":"St Petersburg",
    "sg:classifiers":[
        {
            "category":"Building & Trades",
            "subcategory":"Construction",
            "type":"Services"
        }
    ],
    "sg:phone":"+1 727 321 1120",
    "sg:postcode":"33713",
    "sg:province":"FL",
    "sg:tags":[
        "paving",
        "contractor"
    ],
    "wof:name":"Florida Precision Pavers",
    "wof:placetype":"venue"
},
  "geometry": {"coordinates":[-82.671244,27.78896],"type":"Point"}
}