{
  "type": "Feature",
  "properties": {
    "iso:country":"US",
    "sg:address":"8251 Crewsville Rd",
    "sg:city":"Zolfo Springs",
    "sg:classifiers":[
        {
            "category":"Organizations",
            "subcategory":"Religious Organization",
            "type":"Services"
        }
    ],
    "sg:phone":"+1 863 735 0871",
    "sg:postcode":"33890",
    "sg:province":"FL",
    "sg:tags":[
        "church"
    ],
    "wof:name":"Crewsville Bethel Baptist Chr",
    "wof:placetype":"venue"
},
  "geometry": {"coordinates":[-81.584853,27.41753],"type":"Point"}
}