{
  "type": "Feature",
  "properties": {
    "iso:country":"US",
    "sg:address":"12811 Kenwood Ln",
    "sg:city":"Fort Myers",
    "sg:classifiers":[
        {
            "category":"Professional",
            "subcategory":"Accounting & Tax Preparation",
            "type":"Services"
        }
    ],
    "sg:phone":"+1 239 275 3405",
    "sg:postcode":"33907",
    "sg:province":"FL",
    "sg:tags":[
        "auditing",
        "bookkeeping"
    ],
    "wof:name":"V A Judah CPA PA",
    "wof:placetype":"venue"
},
  "geometry": {"coordinates":[-81.871983,26.554375],"type":"Point"}
}