{
  "type": "Feature",
  "properties": {
    "addr:full":"1444 W Busch Blvd Tampa FL 33612",
    "addr:housenumber":"1444",
    "addr:postcode":"33612",
    "addr:street":"W Busch Blvd",
    "iso:country":"US",
    "sg:address":"1444 W Busch Blvd",
    "sg:city":"Tampa",
    "sg:classifiers":[
        {
            "category":"Health Services",
            "subcategory":"Doctor",
            "type":"Services"
        },
        {
            "category":"Health Services",
            "subcategory":"Clinic",
            "type":"Services"
        }
    ],
    "sg:phone":"+1 813 931 9094",
    "sg:postcode":"33612",
    "sg:province":"FL",
    "sg:tags":[
        "physician",
        "family",
        "medical",
        "practice",
        "surgeons",
        "medicine"
    ],
    "wof:name":"Phelps, Jan, Md - Abbey Medical Clinic",
    "wof:placetype":"venue"
},
  "geometry": {"coordinates":[-82.474563,28.033434],"type":"Point"}
}