{
  "type": "Feature",
  "properties": {
    "addr:full":"43 SE Seminole St Stuart FL 34994",
    "addr:housenumber":"43",
    "addr:postcode":"34994",
    "addr:street":"Se Seminole St",
    "iso:country":"US",
    "sg:address":"43 SE Seminole St",
    "sg:city":"Stuart",
    "sg:classifiers":[
        {
            "category":"Professional",
            "subcategory":"Lawyer & Legal Services",
            "type":"Services"
        }
    ],
    "sg:phone":"+1 772 283 3051",
    "sg:postcode":"34994",
    "sg:province":"FL",
    "sg:tags":[
        "attorney"
    ],
    "wof:name":"Jeffrey M Kirsch",
    "wof:placetype":"venue"
},
  "geometry": {"coordinates":[-80.251671,27.199316],"type":"Point"}
}