{
  "type": "Feature",
  "properties": {
    "addr:full":"3870 Westgate Ave West Palm Beach FL 33409",
    "addr:housenumber":"3870",
    "addr:postcode":"33409",
    "addr:street":"Westgate Ave",
    "iso:country":"US",
    "sg:address":"3870 Westgate Ave",
    "sg:city":"West Palm Beach",
    "sg:classifiers":[
        {
            "category":"Food & Beverages",
            "subcategory":"Groceries & Convenience Stores",
            "type":"Retail Goods"
        }
    ],
    "sg:phone":"+1 561 640 4423",
    "sg:postcode":"33409",
    "sg:province":"FL",
    "wof:name":"Stop & Shop",
    "wof:placetype":"venue"
},
  "geometry": {"coordinates":[-80.106449,26.702947],"type":"Point"}
}