{
  "type": "Feature",
  "properties": {
    "iso:country":"US",
    "sg:address":"10104 Hawthorne Place Dr",
    "sg:city":"Riverview",
    "sg:classifiers":[
        {
            "category":"Manufacturing",
            "subcategory":"Printing",
            "type":"Manufacturing & Wholesale Goods"
        }
    ],
    "sg:phone":"+1 813 630 4232",
    "sg:postcode":"33511",
    "sg:province":"FL",
    "sg:tags":[
        "printer",
        "commercial",
        "offset"
    ],
    "wof:name":"Aj Envelope",
    "wof:placetype":"venue"
},
  "geometry": {"coordinates":[-82.343002,27.921508],"type":"Point"}
}