{
  "type": "Feature",
  "properties": {
    "addr:full":"3820 W Florentine Dr Citrus Springs FL 34433",
    "addr:housenumber":"3820",
    "addr:postcode":"34433",
    "addr:street":"W Florentine Dr",
    "iso:country":"US",
    "sg:address":"3820 W Florentine Dr",
    "sg:city":"Citrus Springs",
    "sg:classifiers":[
        {
            "category":"Building & Trades",
            "subcategory":"Construction",
            "type":"Services"
        }
    ],
    "sg:phone":"+1 352 489 1838",
    "sg:postcode":"34433",
    "sg:province":"FL",
    "sg:tags":[
        "masonry",
        "contractor"
    ],
    "wof:name":"Michael L Brussell Masonry",
    "wof:placetype":"venue"
},
  "geometry": {"coordinates":[-82.49830900000001,28.967951],"type":"Point"}
}