{
  "type": "Feature",
  "properties": {
    "iso:country":"US",
    "sg:address":"6536 Gentle Ben Cir",
    "sg:city":"Zephyrhills",
    "sg:classifiers":[
        {
            "category":"Wholesale",
            "subcategory":"Construction Materials",
            "type":"Manufacturing & Wholesale Goods"
        }
    ],
    "sg:phone":"+1 813 907 8270",
    "sg:postcode":"33544",
    "sg:province":"FL",
    "wof:name":"Speciality Southern Products",
    "wof:placetype":"venue"
},
  "geometry": {"coordinates":[-82.359679,28.250302],"type":"Point"}
}