{
  "type": "Feature",
  "properties": {
    "iso:country":"US",
    "sg:address":"8115 Vineland Ave",
    "sg:city":"Orlando",
    "sg:classifiers":[
        {
            "category":"Food & Beverages",
            "subcategory":"Liquor & Beverages",
            "type":"Retail Goods"
        }
    ],
    "sg:phone":"+1 407 239 9999",
    "sg:postcode":"32821",
    "sg:province":"FL",
    "wof:name":"Empire Liquor",
    "wof:placetype":"venue"
},
  "geometry": {"coordinates":[-81.48697900000001,28.385087],"type":"Point"}
}