{
  "type": "Feature",
  "properties": {
    "addr:full":"5020 Lee Blvd Lehigh Acres FL 33971",
    "addr:housenumber":"5020",
    "addr:postcode":"33971",
    "addr:street":"Lee Blvd",
    "iso:country":"US",
    "sg:address":"5020 Lee Blvd",
    "sg:city":"Lehigh Acres",
    "sg:classifiers":[
        {
            "category":"Building & Trades",
            "subcategory":"Construction",
            "type":"Services"
        }
    ],
    "sg:phone":"+1 239 303 1382",
    "sg:postcode":"33971",
    "sg:province":"FL",
    "sg:tags":[
        "general",
        "contractor"
    ],
    "wof:name":"Mayor Construction-Naples Corp",
    "wof:placetype":"venue"
},
  "geometry": {"coordinates":[-81.73018399999999,26.617589],"type":"Point"}
}