{
  "type": "Feature",
  "properties": {
    "iso:country":"US",
    "sg:address":"3000 Broadway",
    "sg:city":"Riviera Beach",
    "sg:classifiers":[
        {
            "category":"Food & Beverages",
            "subcategory":"Groceries & Convenience Stores",
            "type":"Retail Goods"
        }
    ],
    "sg:phone":"+1 561 881 1212",
    "sg:postcode":"33404",
    "sg:province":"FL",
    "sg:tags":[
        "grocer"
    ],
    "sg:website":"www.savealot.com",
    "wof:name":"Save-A-Lot",
    "wof:placetype":"venue"
},
  "geometry": {"coordinates":[-80.05472399999999,26.786534],"type":"Point"}
}