{
  "type": "Feature",
  "properties": {
    "addr:full":"11900 Biscayne Blvd North Miami FL 33181",
    "addr:housenumber":"11900",
    "addr:postcode":"33181",
    "addr:street":"Biscayne Blvd",
    "iso:country":"US",
    "sg:address":"11900 Biscayne Blvd",
    "sg:city":"North Miami",
    "sg:classifiers":[
        {
            "category":"Professional",
            "subcategory":"Accounting & Tax Preparation",
            "type":"Services"
        }
    ],
    "sg:phone":"+1 305 891 8646",
    "sg:postcode":"33181",
    "sg:province":"FL",
    "sg:tags":[
        "billing"
    ],
    "wof:name":"Billing Methods Inc",
    "wof:placetype":"venue"
},
  "geometry": {"coordinates":[-80.16459999999999,25.886546],"type":"Point"}
}