{
  "type": "Feature",
  "properties": {
    "addr:full":"1111 Sorrento Dr Fort Lauderdale FL 33326",
    "addr:housenumber":"1111",
    "addr:postcode":"33326",
    "addr:street":"Sorrento Dr",
    "iso:country":"US",
    "sg:address":"1111 Sorrento Dr",
    "sg:city":"Fort Lauderdale",
    "sg:classifiers":[
        {
            "category":"Real Estate",
            "subcategory":"Real Estate Operator",
            "type":"Services"
        }
    ],
    "sg:phone":"+1 954 385 0347",
    "sg:postcode":"33326",
    "sg:province":"FL",
    "sg:tags":[
        "building",
        "nonresidential"
    ],
    "wof:name":"That Shopping Thing",
    "wof:placetype":"venue"
},
  "geometry": {"coordinates":[-80.399593,26.133996],"type":"Point"}
}