{
  "type": "Feature",
  "properties": {
    "iso:country":"US",
    "sg:address":"231 Normandy Rd",
    "sg:city":"Casselberry",
    "sg:classifiers":[
        {
            "category":"Building & Trades",
            "subcategory":"Construction",
            "type":"Services"
        }
    ],
    "sg:phone":"+1 407 831 9677",
    "sg:postcode":"32707",
    "sg:province":"FL",
    "sg:tags":[
        "contractor"
    ],
    "wof:name":"Dun Rite Drywall Inc",
    "wof:placetype":"venue"
},
  "geometry": {"coordinates":[-81.343159,28.666959],"type":"Point"}
}