{
  "type": "Feature",
  "properties": {
    "addr:full":"400 Gran Bahama Blvd Davenport FL 33897",
    "addr:housenumber":"400",
    "addr:postcode":"33897",
    "addr:street":"Gran Bahama Blvd",
    "iso:country":"US",
    "sg:address":"400 Gran Bahama Blvd",
    "sg:city":"Davenport",
    "sg:classifiers":[
        {
            "category":"Travel",
            "subcategory":"Hotels & Motels",
            "type":"Entertainment"
        }
    ],
    "sg:phone":"+1 863 547 1200",
    "sg:postcode":"33897",
    "sg:province":"FL",
    "sg:website":"www.bahamabayresort.com",
    "wof:name":"Bahama Bay Resort",
    "wof:placetype":"venue"
},
  "geometry": {"coordinates":[-81.66390199999999,28.318199],"type":"Point"}
}