{
  "type": "Feature",
  "properties": {
    "addr:full":"2701 Gateway Dr Pompano Beach FL 33069",
    "addr:housenumber":"2701",
    "addr:postcode":"33069",
    "addr:street":"Gateway Dr",
    "iso:country":"US",
    "sg:address":"2701 Gateway Dr",
    "sg:city":"Pompano Beach",
    "sg:classifiers":[
        {
            "category":"Building & Trades",
            "subcategory":"Equipment Rental",
            "type":"Services"
        }
    ],
    "sg:phone":"+1 954 956 9003",
    "sg:postcode":"33069",
    "sg:province":"FL",
    "sg:tags":[
        "medical",
        "merchandise"
    ],
    "wof:name":"American Homepatient",
    "wof:placetype":"venue"
},
  "geometry": {"coordinates":[-80.160207,26.213027],"type":"Point"}
}