{
  "type": "Feature",
  "properties": {
    "iso:country":"US",
    "sg:address":"2023 Wilson St",
    "sg:city":"Hollywood",
    "sg:classifiers":[
        {
            "category":"Shopping",
            "type":"Retail Goods"
        },
        {
            "category":"Manufacturing",
            "subcategory":"Signs",
            "type":"Manufacturing & Wholesale Goods"
        }
    ],
    "sg:phone":"+1 954 920 4262",
    "sg:postcode":"33020",
    "sg:province":"FL",
    "sg:tags":[
        "banner",
        "specialty",
        "mfg"
    ],
    "wof:name":"Bob's Signs & Designs",
    "wof:placetype":"venue"
},
  "geometry": {"coordinates":[-80.14783300000001,26.027168],"type":"Point"}
}