{
  "type": "Feature",
  "properties": {
    "addr:full":"4400 N Federal Hwy Boca Raton FL 33431",
    "addr:housenumber":"4400",
    "addr:postcode":"33431",
    "addr:street":"N Federal Hwy",
    "iso:country":"US",
    "sg:address":"4400 N Federal Hwy",
    "sg:city":"Boca Raton",
    "sg:classifiers":[
        {
            "category":"Real Estate",
            "subcategory":"Real Estate Agent",
            "type":"Services"
        }
    ],
    "sg:phone":"+1 561 750 2426",
    "sg:postcode":"33431",
    "sg:province":"FL",
    "wof:name":"Sam Mina",
    "wof:placetype":"venue"
},
  "geometry": {"coordinates":[-80.07655699999999,26.389948],"type":"Point"}
}