{
  "type": "Feature",
  "properties": {
    "addr:full":"14540 Cortez Blvd Brooksville FL 34613",
    "addr:housenumber":"14540",
    "addr:postcode":"34613",
    "addr:street":"Cortez Blvd",
    "iso:country":"US",
    "sg:address":"14540 Cortez Blvd",
    "sg:city":"Brooksville",
    "sg:classifiers":[
        {
            "category":"Health Services",
            "subcategory":"Doctor",
            "type":"Services"
        }
    ],
    "sg:phone":"+1 727 726 8871",
    "sg:postcode":"34613",
    "sg:province":"FL",
    "sg:tags":[
        "medical"
    ],
    "wof:name":"Anjali Singh MD",
    "wof:placetype":"venue"
},
  "geometry": {"coordinates":[-82.484228,28.533956],"type":"Point"}
}