{
  "type": "Feature",
  "properties": {
    "iso:country":"US",
    "sg:address":"24450 SW 152nd Ave",
    "sg:city":"Homestead",
    "sg:classifiers":[
        {
            "category":"Wholesale",
            "subcategory":"Plants",
            "type":"Manufacturing & Wholesale Goods"
        }
    ],
    "sg:phone":"+1 305 248 4463",
    "sg:postcode":"33032",
    "sg:province":"FL",
    "sg:tags":[
        "supply"
    ],
    "wof:name":"Oscar D Dominguez",
    "wof:placetype":"venue"
},
  "geometry": {"coordinates":[-80.437203,25.539959],"type":"Point"}
}