{
  "type": "Feature",
  "properties": {
    "iso:country":"US",
    "sg:address":"2089 Tamiami Trl",
    "sg:city":"Venice",
    "sg:classifiers":[
        {
            "category":"Building & Trades",
            "subcategory":"Construction",
            "type":"Services"
        }
    ],
    "sg:phone":"+1 941 492 4494",
    "sg:postcode":"34293",
    "sg:province":"FL",
    "sg:tags":[
        "general",
        "contractor"
    ],
    "wof:name":"Home Masters Construction",
    "wof:placetype":"venue"
},
  "geometry": {"coordinates":[-82.412699,27.057342],"type":"Point"}
}