{
  "type": "Feature",
  "properties": {
    "iso:country":"US",
    "sg:address":"1126 Ave J",
    "sg:city":"Ormond Beach",
    "sg:classifiers":[
        {
            "category":"Professional",
            "subcategory":"Business Services",
            "type":"Services"
        }
    ],
    "sg:phone":"+1 386 672 2424",
    "sg:postcode":"32174",
    "sg:province":"FL",
    "wof:name":"Younger Business Svc",
    "wof:placetype":"venue"
},
  "geometry": {"coordinates":[-81.084929,29.253697],"type":"Point"}
}