{
  "type": "Feature",
  "properties": {
    "iso:country":"US",
    "sg:address":"1415 Gilchrist St",
    "sg:city":"Quincy",
    "sg:classifiers":[
        {
            "category":"Organizations",
            "subcategory":"Membership Organization",
            "type":"Services"
        }
    ],
    "sg:phone":"+1 850 627 2736",
    "sg:postcode":"32351",
    "sg:province":"FL",
    "sg:tags":[
        "charity"
    ],
    "wof:name":"Free & Accepted Masons Of Florida",
    "wof:placetype":"venue"
},
  "geometry": {"coordinates":[-84.59375900000001,30.571125],"type":"Point"}
}