{
  "type": "Feature",
  "properties": {
    "addr:full":"1900 SW 27th Ter Cape Coral FL 33914",
    "addr:housenumber":"1900",
    "addr:postcode":"33914",
    "addr:street":"Sw 27Th Ter",
    "iso:country":"US",
    "sg:address":"1900 SW 27th Ter",
    "sg:city":"Cape Coral",
    "sg:classifiers":[
        {
            "category":"Building & Trades",
            "subcategory":"Cleaning & Sanitation",
            "type":"Services"
        }
    ],
    "sg:phone":"+1 239 549 1662",
    "sg:postcode":"33914",
    "sg:province":"FL",
    "sg:tags":[
        "maintenance"
    ],
    "wof:name":"Diorio Cleaning Serv",
    "wof:placetype":"venue"
},
  "geometry": {"coordinates":[-82.01396699999999,26.601722],"type":"Point"}
}