{
  "type": "Feature",
  "properties": {
    "iso:country":"US",
    "sg:address":"6752 Collins Ave",
    "sg:city":"Miami Beach",
    "sg:classifiers":[
        {
            "category":"Bars & Pubs",
            "type":"Food & Drink"
        }
    ],
    "sg:phone":"+1 305 865 1752",
    "sg:postcode":"33141",
    "sg:province":"FL",
    "sg:tags":[
        "lounge",
        "drinking",
        "cocktail"
    ],
    "wof:name":"Sandbar Lounge",
    "wof:placetype":"venue"
},
  "geometry": {"coordinates":[-80.120375,25.851675],"type":"Point"}
}