{
  "type": "Feature",
  "properties": {
    "addr:full":"342 Raleigh Pl Oviedo FL 32765",
    "addr:housenumber":"342",
    "addr:postcode":"32765",
    "addr:street":"Raleigh Pl",
    "iso:country":"US",
    "sg:address":"342 Raleigh Pl",
    "sg:city":"Oviedo",
    "sg:classifiers":[
        {
            "category":"Health Services",
            "subcategory":"Doctor",
            "type":"Services"
        }
    ],
    "sg:phone":"+1 407 971 8216",
    "sg:postcode":"32765",
    "sg:province":"FL",
    "sg:tags":[
        "physician",
        "surgeon"
    ],
    "wof:name":"Synergy Healthcare Services",
    "wof:placetype":"venue"
},
  "geometry": {"coordinates":[-81.21461499999999,28.632101],"type":"Point"}
}