{
  "type": "Feature",
  "properties": {
    "addr:full":"9442 Courtney Ln Tallahassee FL 32305",
    "addr:housenumber":"9442",
    "addr:postcode":"32305",
    "addr:street":"Courtney Ln",
    "iso:country":"US",
    "sg:address":"9442 Courtney Ln",
    "sg:city":"Tallahassee",
    "sg:classifiers":[
        {
            "category":"Home & Garden",
            "subcategory":"Building Materials",
            "type":"Retail Goods"
        }
    ],
    "sg:phone":"+1 850 566 0867",
    "sg:postcode":"32305",
    "sg:province":"FL",
    "sg:tags":[
        "door"
    ],
    "wof:name":"Alot Moore Garage Doors",
    "wof:placetype":"venue"
},
  "geometry": {"coordinates":[-84.31674599999999,30.311283],"type":"Point"}
}