{
  "type": "Feature",
  "properties": {
    "addr:full":"14837 N Florida Ave Tampa FL 33613",
    "addr:housenumber":"14837",
    "addr:postcode":"33613",
    "addr:street":"N Florida Ave",
    "iso:country":"US",
    "sg:address":"14837 N Florida Ave",
    "sg:city":"Tampa",
    "sg:classifiers":[
        {
            "category":"Shopping",
            "subcategory":"Clothing, Apparel, & Fashions",
            "type":"Retail Goods"
        }
    ],
    "sg:phone":"+1 813 453 9335",
    "sg:postcode":"33613",
    "sg:province":"FL",
    "wof:name":"Renegade Classics",
    "wof:placetype":"venue"
},
  "geometry": {"coordinates":[-82.45949299999999,28.083876],"type":"Point"}
}