{
  "type": "Feature",
  "properties": {
    "iso:country":"US",
    "sg:address":"4459 Gulf Breeze Pkwy",
    "sg:city":"Gulf Breeze",
    "sg:classifiers":[
        {
            "category":"Professional",
            "subcategory":"Advertising",
            "type":"Services"
        }
    ],
    "sg:phone":"+1 850 934 7225",
    "sg:postcode":"32563",
    "sg:province":"FL",
    "sg:tags":[
        "mailing",
        "shipping"
    ],
    "wof:name":"Breeze Packing Moving & Shppng",
    "wof:placetype":"venue"
},
  "geometry": {"coordinates":[-87.039703,30.393772],"type":"Point"}
}