{
  "type": "Feature",
  "properties": {
    "iso:country":"US",
    "sg:address":"5401 W Oak Ridge Rd",
    "sg:city":"Orlando",
    "sg:classifiers":[
        {
            "category":"Manufacturing",
            "subcategory":"Pottery",
            "type":"Manufacturing & Wholesale Goods"
        }
    ],
    "sg:phone":"+1 407 345 9313",
    "sg:postcode":"32819",
    "sg:province":"FL",
    "sg:tags":[
        "product",
        "mfg"
    ],
    "wof:name":"Pfaltzgraff 37",
    "wof:placetype":"venue"
},
  "geometry": {"coordinates":[-81.44777499999999,28.472135],"type":"Point"}
}