{
  "type": "Feature",
  "properties": {
    "iso:country":"US",
    "sg:address":"2811 N Albany Ave",
    "sg:city":"Tampa",
    "sg:classifiers":[
        {
            "category":"Building & Trades",
            "subcategory":"Construction",
            "type":"Services"
        }
    ],
    "sg:phone":"+1 813 254 0542",
    "sg:postcode":"33607",
    "sg:province":"FL",
    "sg:tags":[
        "carpentry",
        "material",
        "contractor"
    ],
    "wof:name":"Scaglione Cabinets Inc",
    "wof:placetype":"venue"
},
  "geometry": {"coordinates":[-82.480656,27.965852],"type":"Point"}
}