{
  "type": "Feature",
  "properties": {
    "addr:full":"1491 Main St Dunedin FL 34698",
    "addr:housenumber":"1491",
    "addr:postcode":"34698",
    "addr:street":"Main St",
    "iso:country":"US",
    "sg:address":"1491 Main St",
    "sg:city":"Dunedin",
    "sg:classifiers":[
        {
            "category":"Food & Beverages",
            "subcategory":"Groceries & Convenience Stores",
            "type":"Retail Goods"
        }
    ],
    "sg:phone":"+1 727 736 5681",
    "sg:postcode":"34698",
    "sg:province":"FL",
    "sg:tags":[
        "grocer",
        "supermarket"
    ],
    "wof:name":"Publix Super Market 270",
    "wof:placetype":"venue"
},
  "geometry": {"coordinates":[-82.766841,28.019413],"type":"Point"}
}