{
  "type": "Feature",
  "properties": {
    "iso:country":"US",
    "sg:address":"11777 24th St",
    "sg:city":"Live Oak",
    "sg:classifiers":[
        {
            "category":"Building & Trades",
            "subcategory":"Construction",
            "type":"Services"
        }
    ],
    "sg:phone":"+1 386 842 5146",
    "sg:postcode":"32060",
    "sg:province":"FL",
    "sg:tags":[
        "contractor"
    ],
    "wof:name":"Suwannee Masonry Inc",
    "wof:placetype":"venue"
},
  "geometry": {"coordinates":[-82.989403,30.40762],"type":"Point"}
}