{
  "type": "Feature",
  "properties": {
    "iso:country":"US",
    "sg:address":"5761 NW 37th Ave",
    "sg:city":"Miami",
    "sg:classifiers":[
        {
            "category":"Shopping",
            "subcategory":"Used Merchandise",
            "type":"Retail Goods"
        }
    ],
    "sg:phone":"+1 305 634 1377",
    "sg:postcode":"33142",
    "sg:province":"FL",
    "sg:tags":[
        "vintage",
        "consignment"
    ],
    "wof:name":"Florida Rags",
    "wof:placetype":"venue"
},
  "geometry": {"coordinates":[-80.25700999999999,25.826756],"type":"Point"}
}