{
  "type": "Feature",
  "properties": {
    "iso:country":"US",
    "sg:address":"330 E 9th St",
    "sg:city":"Hialeah",
    "sg:classifiers":[
        {
            "category":"Shopping",
            "subcategory":"Pawn Shop",
            "type":"Retail Goods"
        }
    ],
    "sg:phone":"+1 305 887 0330",
    "sg:postcode":"33010",
    "sg:province":"FL",
    "wof:name":"Treasure Jewelry & Pawn Shop",
    "wof:placetype":"venue"
},
  "geometry": {"coordinates":[-80.275002,25.830099],"type":"Point"}
}