{
  "type": "Feature",
  "properties": {
    "addr:full":"3830 S Tuttle Ave Sarasota FL 34239",
    "addr:housenumber":"3830",
    "addr:postcode":"34239",
    "addr:street":"S Tuttle Ave",
    "iso:country":"US",
    "sg:address":"3830 S Tuttle Ave",
    "sg:city":"Sarasota",
    "sg:classifiers":[
        {
            "category":"Shopping",
            "subcategory":"Clothing, Apparel, & Fashions",
            "type":"Retail Goods"
        },
        {
            "category":"Banks & Credit Unions",
            "subcategory":"Bank",
            "type":"Services"
        },
        {
            "category":"Shopping",
            "subcategory":"Used Merchandise",
            "type":"Retail Goods"
        }
    ],
    "sg:phone":"+1 941 922 5535",
    "sg:postcode":"34239",
    "sg:province":"FL",
    "sg:tags":[
        "shop",
        "resale",
        "second",
        "consignment",
        "hand"
    ],
    "wof:name":"Laura Jean's",
    "wof:placetype":"venue"
},
  "geometry": {"coordinates":[-82.514197,27.299437],"type":"Point"}
}