{
  "type": "Feature",
  "properties": {
    "iso:country":"US",
    "sg:address":"7671 SW 132nd Pl",
    "sg:city":"Miami",
    "sg:classifiers":[
        {
            "category":"Arts & Performance",
            "subcategory":"Theater",
            "type":"Entertainment"
        }
    ],
    "sg:phone":"+1 305 382 9460",
    "sg:postcode":"33183",
    "sg:province":"FL",
    "sg:tags":[
        "musician",
        "group"
    ],
    "sg:website":"http://www.mixtura.biz",
    "wof:name":"Mixtura Inc",
    "wof:placetype":"venue"
},
  "geometry": {"coordinates":[-80.40762599999999,25.69679],"type":"Point"}
}