{
  "type": "Feature",
  "properties": {
    "iso:country":"US",
    "sg:address":"120 Co Rd 305",
    "sg:city":"Seville",
    "sg:classifiers":[
        {
            "category":"Government",
            "subcategory":"Post Office",
            "type":"Public Place"
        }
    ],
    "sg:phone":"+1 386 749 2884",
    "sg:postcode":"32190",
    "sg:province":"FL",
    "wof:name":"US Post Office",
    "wof:placetype":"venue"
},
  "geometry": {"coordinates":[-81.49439,29.317064],"type":"Point"}
}