{
  "type": "Feature",
  "properties": {
    "iso:country":"US",
    "sg:address":"8363 Pines Blvd",
    "sg:city":"Hollywood",
    "sg:classifiers":[
        {
            "category":"Banks & Credit Unions",
            "subcategory":"Bank",
            "type":"Services"
        }
    ],
    "sg:phone":"+1 954 450 9099",
    "sg:postcode":"33024",
    "sg:province":"FL",
    "sg:tags":[
        "broker",
        "mortgage"
    ],
    "wof:name":"Allstate Mrtg Investments Inc",
    "wof:placetype":"venue"
},
  "geometry": {"coordinates":[-80.254501,26.009156],"type":"Point"}
}