{
  "type": "Feature",
  "properties": {
    "addr:full":"760 8th Ct Vero Beach FL 32962",
    "addr:housenumber":"760",
    "addr:postcode":"32962",
    "addr:street":"8Th Ct",
    "iso:country":"US",
    "sg:address":"760 8th Ct",
    "sg:city":"Vero Beach",
    "sg:classifiers":[
        {
            "category":"Bars & Pubs",
            "type":"Food & Drink"
        }
    ],
    "sg:phone":"+1 772 794 0144",
    "sg:postcode":"32962",
    "sg:province":"FL",
    "sg:tags":[
        "lounge",
        "cocktail"
    ],
    "wof:name":"Uptown Speakeasy Pub & Package",
    "wof:placetype":"venue"
},
  "geometry": {"coordinates":[-80.389653,27.615277],"type":"Point"}
}