{
  "type": "Feature",
  "properties": {
    "iso:country":"US",
    "sg:address":"3201 SW 34th Ave",
    "sg:city":"Ocala",
    "sg:classifiers":[
        {
            "category":"Travel",
            "subcategory":"Travel Agent",
            "type":"Entertainment"
        }
    ],
    "sg:phone":"+1 352 237 2881",
    "sg:postcode":"34474",
    "sg:province":"FL",
    "sg:tags":[
        "agency"
    ],
    "wof:name":"Joli Tour Cruises",
    "wof:placetype":"venue"
},
  "geometry": {"coordinates":[-82.177684,29.154715],"type":"Point"}
}