{
  "type": "Feature",
  "properties": {
    "addr:full":"10302 NW 9th Street Cir Miami FL 33172",
    "addr:housenumber":"10302",
    "addr:postcode":"33172",
    "addr:street":"Nw 9Th Street Cir",
    "iso:country":"US",
    "sg:address":"10302 NW 9th Street Cir",
    "sg:city":"Miami",
    "sg:classifiers":[
        {
            "category":"Food & Beverages",
            "subcategory":"Groceries & Convenience Stores",
            "type":"Retail Goods"
        }
    ],
    "sg:phone":"+1 305 480 9468",
    "sg:postcode":"33172",
    "sg:province":"FL",
    "wof:name":"Arf All Market Inc",
    "wof:placetype":"venue"
},
  "geometry": {"coordinates":[-80.364085,25.775157],"type":"Point"}
}