{
  "type": "Feature",
  "properties": {
    "addr:full":"2120 Barcelona Way S Saint Petersburg FL 33712",
    "addr:housenumber":"2120",
    "addr:postcode":"33712",
    "addr:street":"Barcelona Way S",
    "iso:country":"US",
    "sg:address":"2120 Barcelona Way S",
    "sg:city":"Saint Petersburg",
    "sg:classifiers":[
        {
            "category":"Food & Beverages",
            "subcategory":"Specialty",
            "type":"Retail Goods"
        }
    ],
    "sg:phone":"+1 727 867 0340",
    "sg:postcode":"33712",
    "sg:province":"FL",
    "wof:name":"Ajh & Innovations",
    "wof:placetype":"venue"
},
  "geometry": {"coordinates":[-82.66303000000001,27.723112],"type":"Point"}
}