{
  "type": "Feature",
  "properties": {
    "iso:country":"US",
    "sg:address":"950 N Courtenay Pkwy Ste 19",
    "sg:city":"Merritt Island",
    "sg:classifiers":[
        {
            "category":"Shopping",
            "subcategory":"Clothing, Apparel, & Fashions",
            "type":"Retail Goods"
        }
    ],
    "sg:phone":"+1 321 452 7001",
    "sg:postcode":"32953",
    "sg:province":"FL",
    "sg:tags":[
        "children's",
        "clothing"
    ],
    "wof:name":"Play It Again Baby",
    "wof:placetype":"venue"
},
  "geometry": {"coordinates":[-80.70029599999999,28.372138],"type":"Point"}
}