{
  "type": "Feature",
  "properties": {
    "iso:country":"US",
    "sg:address":"7630 Ardwick Dr",
    "sg:city":"Lake Worth",
    "sg:classifiers":[
        {
            "category":"Building & Trades",
            "subcategory":"Construction",
            "type":"Services"
        }
    ],
    "sg:phone":"+1 561 439 0064",
    "sg:postcode":"33467",
    "sg:province":"FL",
    "sg:tags":[
        "house"
    ],
    "wof:name":"William Floyd Anders",
    "wof:placetype":"venue"
},
  "geometry": {"coordinates":[-80.165605,26.565126],"type":"Point"}
}