{
  "type": "Feature",
  "properties": {
    "iso:country":"US",
    "sg:address":"1665 Wp Ball Blvd",
    "sg:city":"Sanford",
    "sg:classifiers":[
        {
            "category":"Restaurant",
            "type":"Food & Drink"
        }
    ],
    "sg:phone":"+1 407 531 1151",
    "sg:postcode":"32771",
    "sg:province":"FL",
    "sg:tags":[
        "pizza"
    ],
    "wof:name":"Caffe Positano",
    "wof:placetype":"venue"
},
  "geometry": {"coordinates":[-81.33573800000001,28.80002],"type":"Point"}
}