{
  "type": "Feature",
  "properties": {
    "iso:country":"US",
    "sg:address":"17776 Toledo Blade Blvd",
    "sg:city":"Port Charlotte",
    "sg:classifiers":[
        {
            "category":"Wholesale",
            "subcategory":"Electrical",
            "type":"Manufacturing & Wholesale Goods"
        }
    ],
    "sg:phone":"+1 941 625 9700",
    "sg:postcode":"33948",
    "sg:province":"FL",
    "sg:tags":[
        "alarm",
        "burglar",
        "system"
    ],
    "sg:website":"www.securityalarmcorp.com",
    "wof:name":"Security Alarm Corp",
    "wof:placetype":"venue"
},
  "geometry": {"coordinates":[-82.16206,27.005446],"type":"Point"}
}