{
  "type": "Feature",
  "properties": {
    "iso:country":"US",
    "sg:address":"939 Blanding Blvd",
    "sg:city":"Orange Park",
    "sg:classifiers":[
        {
            "category":"Social Services",
            "subcategory":"Child Care",
            "type":"Services"
        }
    ],
    "sg:phone":"+1 904 276 2644",
    "sg:postcode":"32065",
    "sg:province":"FL",
    "sg:tags":[
        "kindergarten",
        "academic",
        "school"
    ],
    "wof:name":"First Class Learning Ctr",
    "wof:placetype":"venue"
},
  "geometry": {"coordinates":[-81.77284,30.1387],"type":"Point"}
}