{
  "type": "Feature",
  "properties": {
    "iso:country":"US",
    "sg:address":"6815 Farragut Ln",
    "sg:city":"Boynton Beach",
    "sg:classifiers":[
        {
            "category":"Professional",
            "subcategory":"Lawyer & Legal Services",
            "type":"Services"
        }
    ],
    "sg:phone":"+1 561 738 1731",
    "sg:postcode":"33437",
    "sg:province":"FL",
    "wof:name":"Martin & Pickett P A",
    "wof:placetype":"venue"
},
  "geometry": {"coordinates":[-80.152196,26.529805],"type":"Point"}
}