{
  "type": "Feature",
  "properties": {
    "iso:country":"US",
    "sg:address":"4340 Montalvo Ct",
    "sg:city":"Naples",
    "sg:classifiers":[
        {
            "category":"Professional",
            "subcategory":"Detective & Security Services",
            "type":"Services"
        }
    ],
    "sg:phone":"+1 239 514 4871",
    "sg:postcode":"34109",
    "sg:province":"FL",
    "sg:tags":[
        "investigation",
        "clearance"
    ],
    "wof:name":"Edward Motedew",
    "wof:placetype":"venue"
},
  "geometry": {"coordinates":[-81.742722,26.23585],"type":"Point"}
}