{
  "type": "Feature",
  "properties": {
    "iso:country":"US",
    "sg:address":"55 NW 27th Ave",
    "sg:city":"Miami",
    "sg:classifiers":[
        {
            "category":"Science Facility",
            "type":"Public Place"
        }
    ],
    "sg:phone":"+1 305 967 8360",
    "sg:postcode":"33125",
    "sg:province":"FL",
    "sg:tags":[
        "rodeo"
    ],
    "wof:name":"Safety First Riding Florida",
    "wof:placetype":"venue"
},
  "geometry": {"coordinates":[-80.23905499999999,25.773194],"type":"Point"}
}