{
  "type": "Feature",
  "properties": {
    "iso:country":"US",
    "sg:address":"400 N Navy Blvd",
    "sg:city":"Pensacola",
    "sg:classifiers":[
        {
            "category":"Food & Beverages",
            "subcategory":"Groceries & Convenience Stores",
            "type":"Retail Goods"
        }
    ],
    "sg:phone":"+1 850 453 2806",
    "sg:postcode":"32507",
    "sg:province":"FL",
    "wof:name":"Winn-Dixie",
    "wof:placetype":"venue"
},
  "geometry": {"coordinates":[-87.278026,30.393981],"type":"Point"}
}