{
  "type": "Feature",
  "properties": {
    "addr:full":"2690 S Ponte Vedra Blvd Ponte Vedra Beach FL 32082",
    "addr:housenumber":"2690",
    "addr:postcode":"32082",
    "addr:street":"S Ponte Vedra Blvd",
    "iso:country":"US",
    "sg:address":"2690 S Ponte Vedra Blvd",
    "sg:city":"Ponte Vedra Beach",
    "sg:classifiers":[
        {
            "category":"Government",
            "subcategory":"Office",
            "type":"Public Place"
        }
    ],
    "sg:phone":"+1 904 825 6877",
    "sg:postcode":"32082",
    "sg:province":"FL",
    "sg:tags":[
        "conservation"
    ],
    "wof:name":"Florida Fsh Wld Life Cons Comm",
    "wof:placetype":"venue"
},
  "geometry": {"coordinates":[-81.32428400000001,30.026017],"type":"Point"}
}