{
  "type": "Feature",
  "properties": {
    "iso:country":"US",
    "sg:address":"1143 38th Ave SW",
    "sg:city":"Vero Beach",
    "sg:classifiers":[
        {
            "category":"Retail",
            "subcategory":"Repair Shop",
            "type":"Services"
        }
    ],
    "sg:phone":"+1 772 978 5870",
    "sg:postcode":"32968",
    "sg:province":"FL",
    "sg:tags":[
        "spa",
        "hot",
        "tub"
    ],
    "wof:name":"Aqua Blue Pool",
    "wof:placetype":"venue"
},
  "geometry": {"coordinates":[-80.42565500000001,27.5827],"type":"Point"}
}