{
  "type": "Feature",
  "properties": {
    "addr:full":"474 5th St SW Vero Beach FL 32962",
    "addr:housenumber":"474",
    "addr:postcode":"32962",
    "addr:street":"5Th St Sw",
    "iso:country":"US",
    "sg:address":"474 5th St SW",
    "sg:city":"Vero Beach",
    "sg:classifiers":[
        {
            "category":"Freight",
            "type":"Transportation"
        }
    ],
    "sg:phone":"+1 772 340 2626",
    "sg:postcode":"32962",
    "sg:province":"FL",
    "sg:tags":[
        "general"
    ],
    "wof:name":"K A Verderber Inc",
    "wof:placetype":"venue"
},
  "geometry": {"coordinates":[-80.38078,27.594099],"type":"Point"}
}