{
  "type": "Feature",
  "properties": {
    "iso:country":"US",
    "sg:address":"4899 W Waters Ave",
    "sg:city":"Tampa",
    "sg:classifiers":[
        {
            "category":"Shopping",
            "type":"Retail Goods"
        }
    ],
    "sg:phone":"+1 813 880 0411",
    "sg:postcode":"33634",
    "sg:province":"FL",
    "sg:tags":[
        "typewriter"
    ],
    "sg:website":"www.sunstateoffice.copystardealers.com",
    "wof:name":"Sun State Office Equipment",
    "wof:placetype":"venue"
},
  "geometry": {"coordinates":[-82.52742000000001,28.02556],"type":"Point"}
}