{
  "type": "Feature",
  "properties": {
    "iso:country":"US",
    "sg:address":"6400 S US Highway 17/92",
    "sg:city":"Fern Park",
    "sg:classifiers":[
        {
            "category":"Education",
            "subcategory":"School",
            "type":"Public Place"
        }
    ],
    "sg:phone":"+1 407 831 9805",
    "sg:postcode":"32730",
    "sg:province":"FL",
    "wof:name":"Top Cat",
    "wof:placetype":"venue"
},
  "geometry": {"coordinates":[-81.34308299999999,28.658815],"type":"Point"}
}