{
  "type": "Feature",
  "properties": {
    "iso:country":"US",
    "sg:address":"4817 N Florida Ave",
    "sg:city":"Tampa",
    "sg:classifiers":[
        {
            "category":"Education",
            "subcategory":"School",
            "type":"Public Place"
        }
    ],
    "sg:phone":"+1 813 231 9272",
    "sg:postcode":"33603",
    "sg:province":"FL",
    "sg:website":"http://www.sdhc.k12.fl.us",
    "wof:name":"Walton Academy For The Perform",
    "wof:placetype":"venue"
},
  "geometry": {"coordinates":[-82.459389,27.98958],"type":"Point"}
}