{
  "type": "Feature",
  "properties": {
    "addr:full":"10358 Ireland St Spring Hill FL 34608",
    "addr:housenumber":"10358",
    "addr:postcode":"34608",
    "addr:street":"Ireland St",
    "iso:country":"US",
    "sg:address":"10358 Ireland St",
    "sg:city":"Spring Hill",
    "sg:classifiers":[
        {
            "category":"Education",
            "subcategory":"Special Training",
            "type":"Public Place"
        }
    ],
    "sg:phone":"+1 352 688 8720",
    "sg:postcode":"34608",
    "sg:province":"FL",
    "wof:name":"Superscore",
    "wof:placetype":"venue"
},
  "geometry": {"coordinates":[-82.548687,28.480308],"type":"Point"}
}