{
  "type": "Feature",
  "properties": {
    "addr:full":"205 W Alexander St Plant City FL 33563",
    "addr:housenumber":"205",
    "addr:postcode":"33563",
    "addr:street":"W Alexander St",
    "iso:country":"US",
    "sg:address":"205 W Alexander St",
    "sg:city":"Plant City",
    "sg:classifiers":[
        {
            "category":"Farming",
            "subcategory":"Orchard",
            "type":"Manufacturing & Wholesale Goods"
        }
    ],
    "sg:phone":"+1 813 754 9449",
    "sg:postcode":"33563",
    "sg:province":"FL",
    "sg:tags":[
        "citrus",
        "grove",
        "fruit"
    ],
    "wof:name":"Cash & Carry Pharmacy",
    "wof:placetype":"venue"
},
  "geometry": {"coordinates":[-82.12520000000001,27.988059],"type":"Point"}
}