{
  "type": "Feature",
  "properties": {
    "iso:country":"US",
    "sg:address":"3891 Stirling Rd",
    "sg:city":"Fort Lauderdale",
    "sg:classifiers":[
        {
            "category":"Communications",
            "subcategory":"Film & Video Production",
            "type":"Services"
        }
    ],
    "sg:phone":"+1 954 983 5580",
    "sg:postcode":"33312",
    "sg:province":"FL",
    "sg:tags":[
        "motion"
    ],
    "wof:name":"KTI Video Resources",
    "wof:placetype":"venue"
},
  "geometry": {"coordinates":[-80.197194,26.047034],"type":"Point"}
}