{
  "type": "Feature",
  "properties": {
    "iso:country":"US",
    "sg:address":"16674 Mellen Ln",
    "sg:city":"Jupiter",
    "sg:classifiers":[
        {
            "category":"Professional",
            "subcategory":"Business Services",
            "type":"Services"
        }
    ],
    "sg:phone":"+1 561 744 2594",
    "sg:postcode":"33478",
    "sg:province":"FL",
    "sg:tags":[
        "consultant",
        "coach"
    ],
    "wof:name":"Support Life Consultants",
    "wof:placetype":"venue"
},
  "geometry": {"coordinates":[-80.23170399999999,26.92287],"type":"Point"}
}