{
  "type": "Feature",
  "properties": {
    "addr:full":"2104 NW 99th Ave Doral FL 33172",
    "addr:housenumber":"2104",
    "addr:postcode":"33172",
    "addr:street":"Nw 99Th Ave",
    "iso:country":"US",
    "sg:address":"2104 NW 99th Ave",
    "sg:city":"Doral",
    "sg:classifiers":[
        {
            "category":"Wholesale",
            "subcategory":"Medical Equipment & Supplies",
            "type":"Manufacturing & Wholesale Goods"
        }
    ],
    "sg:phone":"+1 786 464 1184",
    "sg:postcode":"33172",
    "sg:province":"FL",
    "sg:tags":[
        "physician",
        "surgeon"
    ],
    "wof:name":"J & B Medical Supply",
    "wof:placetype":"venue"
},
  "geometry": {"coordinates":[-80.357129,25.793484],"type":"Point"}
}