{
  "type": "Feature",
  "properties": {
    "addr:full":"13270 SW 131st St Miami FL 33186",
    "addr:housenumber":"13270",
    "addr:postcode":"33186",
    "addr:street":"Sw 131St St",
    "iso:country":"US",
    "sg:address":"13270 SW 131st St",
    "sg:city":"Miami",
    "sg:classifiers":[
        {
            "category":"Home & Garden",
            "subcategory":"Furniture",
            "type":"Retail Goods"
        },
        {
            "category":"Wholesale",
            "subcategory":"Home Furnishings",
            "type":"Manufacturing & Wholesale Goods"
        }
    ],
    "sg:phone":"+1 305 969 0330",
    "sg:postcode":"33186",
    "sg:province":"FL",
    "sg:tags":[
        "equipment-wholesale",
        "kitchen",
        "equipment-household",
        "manufacturer",
        "cabinet"
    ],
    "wof:name":"Beyond Renovation",
    "wof:placetype":"venue"
},
  "geometry": {"coordinates":[-80.409159,25.645739],"type":"Point"}
}