{
  "type": "Feature",
  "properties": {
    "iso:country":"US",
    "sg:address":"230 NW 53rd Ct",
    "sg:city":"Fort Lauderdale",
    "sg:classifiers":[
        {
            "category":"Building & Trades",
            "subcategory":"Landscaping Services",
            "type":"Services"
        }
    ],
    "sg:phone":"+1 954 229 9472",
    "sg:postcode":"33309",
    "sg:province":"FL",
    "sg:tags":[
        "landscape"
    ],
    "wof:name":"Carlos Land Service",
    "wof:placetype":"venue"
},
  "geometry": {"coordinates":[-80.149929,26.192964],"type":"Point"}
}