{
  "type": "Feature",
  "properties": {
    "addr:full":"3385 S Us Highway 17/92 Casselberry FL 32707",
    "addr:housenumber":"3385;92",
    "addr:postcode":"32707",
    "addr:street":"S Us Highway 17 /",
    "iso:country":"US",
    "sg:address":"3385 S Us Highway 17/92",
    "sg:city":"Casselberry",
    "sg:classifiers":[
        {
            "category":"Ice Cream",
            "type":"Food & Drink"
        }
    ],
    "sg:phone":"+1 407 339 2689",
    "sg:postcode":"32707",
    "sg:province":"FL",
    "sg:tags":[
        "frozen",
        "yogurt"
    ],
    "sg:website":"www.hersheyicecreamfl.com",
    "wof:name":"Hershey's Ice Cream of Casselberry",
    "wof:placetype":"venue"
},
  "geometry": {"coordinates":[-81.334459,28.678727],"type":"Point"}
}