{
  "type": "Feature",
  "properties": {
    "iso:country":"US",
    "sg:address":"870 Cypress Gardens Blvd",
    "sg:city":"Winter Haven",
    "sg:classifiers":[
        {
            "category":"Restaurant",
            "type":"Food & Drink"
        }
    ],
    "sg:menulink":"http://www.allmenus.com/fl/winter-haven-auburndale/181211-imperial-buffet/menu/",
    "sg:phone":"+1 863 292 9296",
    "sg:postcode":"33880",
    "sg:province":"FL",
    "sg:tags":[
        "asian",
        "chinese"
    ],
    "wof:name":"Imperial Buffet",
    "wof:placetype":"venue"
},
  "geometry": {"coordinates":[-81.71529099999999,28.004054],"type":"Point"}
}