{
  "type": "Feature",
  "properties": {
    "addr:full":"3090 Winter Lake Rd Lakeland FL 33803",
    "addr:housenumber":"3090",
    "addr:postcode":"33803",
    "addr:street":"Winter Lake Rd",
    "iso:country":"US",
    "sg:address":"3090 Winter Lake Rd",
    "sg:city":"Lakeland",
    "sg:classifiers":[
        {
            "category":"Home & Garden",
            "subcategory":"Building Materials",
            "type":"Retail Goods"
        }
    ],
    "sg:phone":"+1 863 667 1768",
    "sg:postcode":"33803",
    "sg:province":"FL",
    "wof:name":"Clark Screen N Closures Inc",
    "wof:placetype":"venue"
},
  "geometry": {"coordinates":[-81.897779,27.996865],"type":"Point"}
}