{
  "type": "Feature",
  "properties": {
    "iso:country":"US",
    "sg:address":"3120 Helms Farm Rd",
    "sg:city":"Laurel Hill",
    "sg:classifiers":[
        {
            "category":"Building & Trades",
            "subcategory":"Construction",
            "type":"Services"
        }
    ],
    "sg:phone":"+1 850 689 7540",
    "sg:postcode":"32567",
    "sg:province":"FL",
    "sg:tags":[
        "carpentry",
        "contractor"
    ],
    "wof:name":"Bess Robert Trim Carpentry",
    "wof:placetype":"venue"
},
  "geometry": {"coordinates":[-86.525158,30.866998],"type":"Point"}
}