{
  "type": "Feature",
  "properties": {
    "addr:full":"2221 14th St W Bradenton FL 34205",
    "addr:housenumber":"2221",
    "addr:postcode":"34205",
    "addr:street":"14Th St W",
    "iso:country":"US",
    "sg:address":"2221 14th St W",
    "sg:city":"Bradenton",
    "sg:classifiers":[
        {
            "category":"Wholesale",
            "subcategory":"Auto Parts",
            "type":"Manufacturing & Wholesale Goods"
        }
    ],
    "sg:phone":"+1 941 371 4366",
    "sg:postcode":"34205",
    "sg:province":"FL",
    "wof:name":"A C P Automotive Warehouse",
    "wof:placetype":"venue"
},
  "geometry": {"coordinates":[-82.575277,27.479231],"type":"Point"}
}