{
  "type": "Feature",
  "properties": {
    "iso:country":"US",
    "sg:address":"4260 SW 72nd Way",
    "sg:city":"Fort Lauderdale",
    "sg:classifiers":[
        {
            "category":"Shopping",
            "type":"Retail Goods"
        }
    ],
    "sg:phone":"+1 954 474 7387",
    "sg:postcode":"33314",
    "sg:province":"FL",
    "sg:tags":[
        "merchandise"
    ],
    "wof:name":"Groom Waggin Mobile Pet",
    "wof:placetype":"venue"
},
  "geometry": {"coordinates":[-80.24267,26.066885],"type":"Point"}
}