{
  "type": "Feature",
  "properties": {
    "iso:country":"US",
    "sg:address":"6658 James St",
    "sg:city":"Milton",
    "sg:classifiers":[
        {
            "category":"Place Of Worship",
            "subcategory":"Church",
            "type":"Public Place"
        },
        {
            "category":"Place Of Worship",
            "type":"Public Place"
        }
    ],
    "sg:phone":"+1 850 623 4398",
    "sg:postcode":"32570",
    "sg:province":"FL",
    "sg:tags":[
        "churches-baptist-general",
        "churches-baptist-southern",
        "churches-baptist"
    ],
    "wof:name":"James Street Baptist Church",
    "wof:placetype":"venue"
},
  "geometry": {"coordinates":[-87.044709,30.641775],"type":"Point"}
}