{
  "type": "Feature",
  "properties": {
    "iso:country":"US",
    "sg:address":"7921 Flower Ave",
    "sg:city":"Tampa",
    "sg:classifiers":[
        {
            "category":"Organizations",
            "subcategory":"Non-profit Organization",
            "type":"Services"
        }
    ],
    "sg:phone":"+1 813 672 9298",
    "sg:postcode":"33619",
    "sg:province":"FL",
    "sg:tags":[
        "action",
        "agency",
        "community",
        "social"
    ],
    "wof:name":"Progress Village Community Dev",
    "wof:placetype":"venue"
},
  "geometry": {"coordinates":[-82.36635099999999,27.894893],"type":"Point"}
}