{
  "type": "Feature",
  "properties": {
    "addr:full":"106 Angelfish Ln Jupiter FL 33477",
    "addr:housenumber":"106",
    "addr:postcode":"33477",
    "addr:street":"Angelfish Ln",
    "iso:country":"US",
    "sg:address":"106 Angelfish Ln",
    "sg:city":"Jupiter",
    "sg:classifiers":[
        {
            "category":"Building & Trades",
            "subcategory":"Landscaping Services",
            "type":"Services"
        }
    ],
    "sg:phone":"+1 561 741 4744",
    "sg:postcode":"33477",
    "sg:province":"FL",
    "wof:name":"Boynton Lawn Services Inc",
    "wof:placetype":"venue"
},
  "geometry": {"coordinates":[-80.072104,26.922821],"type":"Point"}
}