{
  "type": "Feature",
  "properties": {
    "iso:country":"US",
    "sg:address":"2340 Sunderland Rd",
    "sg:city":"Maitland",
    "sg:classifiers":[
        {
            "category":"Shopping",
            "subcategory":"Stationery & Office Supplies",
            "type":"Retail Goods"
        }
    ],
    "sg:phone":"+1 407 677 5900",
    "sg:postcode":"32751",
    "sg:province":"FL",
    "sg:tags":[
        "equipment"
    ],
    "sg:website":"www.indoff.com",
    "wof:name":"Indoff Inc",
    "wof:placetype":"venue"
},
  "geometry": {"coordinates":[-81.338881,28.641481],"type":"Point"}
}