{
  "type": "Feature",
  "properties": {
    "iso:country":"US",
    "sg:address":"324 N Dale Mabry Hwy",
    "sg:city":"Tampa",
    "sg:classifiers":[
        {
            "category":"Government",
            "subcategory":"Jail",
            "type":"Public Place"
        }
    ],
    "sg:phone":"+1 813 873 4800",
    "sg:postcode":"33609",
    "sg:province":"FL",
    "sg:tags":[
        "correctional",
        "institution"
    ],
    "wof:name":"Tampa South Probation Office",
    "wof:placetype":"venue"
},
  "geometry": {"coordinates":[-82.505746,27.948292],"type":"Point"}
}