{
  "type": "Feature",
  "properties": {
    "iso:country":"US",
    "sg:address":"2012 E Robinson St",
    "sg:city":"Orlando",
    "sg:classifiers":[
        {
            "category":"Real Estate",
            "subcategory":"Surveying",
            "type":"Services"
        }
    ],
    "sg:phone":"+1 407 894 6314",
    "sg:postcode":"32803",
    "sg:province":"FL",
    "wof:name":"Accuright Surveys Of Orlando",
    "wof:placetype":"venue"
},
  "geometry": {"coordinates":[-81.355632,28.545822],"type":"Point"}
}