{
  "type": "Feature",
  "properties": {
    "addr:full":"4407 Kelly Rd Tampa FL 33615",
    "addr:housenumber":"4407",
    "addr:postcode":"33615",
    "addr:street":"Kelly Rd",
    "iso:country":"US",
    "sg:address":"4407 Kelly Rd",
    "sg:city":"Tampa",
    "sg:classifiers":[
        {
            "category":"Health Services",
            "subcategory":"Chiropractor",
            "type":"Services"
        }
    ],
    "sg:phone":"+1 813 887 5560",
    "sg:postcode":"33615",
    "sg:province":"FL",
    "sg:tags":[
        "chiropractic"
    ],
    "wof:name":"Town & Country Chiropractic",
    "wof:placetype":"venue"
},
  "geometry": {"coordinates":[-82.564998,27.982037],"type":"Point"}
}