{
  "type": "Feature",
  "properties": {
    "iso:country":"US",
    "sg:address":"7770 W Irlo Bronson Memorial Hwy",
    "sg:city":"Kissimmee",
    "sg:classifiers":[
        {
            "category":"Travel",
            "subcategory":"Hotels & Motels",
            "type":"Entertainment"
        }
    ],
    "sg:phone":"+1 407 396 3000",
    "sg:postcode":"34747",
    "sg:province":"FL",
    "sg:tags":[
        "resort"
    ],
    "sg:website":"www.dailymanagementresorts.com",
    "wof:name":"Grand Lake Resort Ltd",
    "wof:placetype":"venue"
},
  "geometry": {"coordinates":[-81.596709,28.339769],"type":"Point"}
}