{
  "type": "Feature",
  "properties": {
    "addr:full":"45 NW 14th Ave Dania FL 33004",
    "addr:housenumber":"45",
    "addr:postcode":"33004",
    "addr:street":"Nw 14Th Ave",
    "iso:country":"US",
    "sg:address":"45 NW 14th Ave",
    "sg:city":"Dania",
    "sg:classifiers":[
        {
            "category":"Social Services",
            "subcategory":"Child Care",
            "type":"Services"
        }
    ],
    "sg:phone":"+1 954 929 9468",
    "sg:postcode":"33004",
    "sg:province":"FL",
    "sg:tags":[
        "day"
    ],
    "wof:name":"Camp Blanding Child Care Ctr",
    "wof:placetype":"venue"
},
  "geometry": {"coordinates":[-80.153661,26.053051],"type":"Point"}
}