{
  "type": "Feature",
  "properties": {
    "iso:country":"US",
    "sg:address":"412 Old Village Way",
    "sg:city":"Oldsmar",
    "sg:classifiers":[
        {
            "category":"Professional",
            "subcategory":"Detective & Security Services",
            "type":"Services"
        }
    ],
    "sg:phone":"+1 727 657 2777",
    "sg:postcode":"34677",
    "sg:province":"FL",
    "sg:tags":[
        "information",
        "bureau"
    ],
    "wof:name":"Gage's Janitorial Service",
    "wof:placetype":"venue"
},
  "geometry": {"coordinates":[-82.680188,28.039149],"type":"Point"}
}