{
  "type": "Feature",
  "properties": {
    "iso:country":"US",
    "sg:address":"1931 W Copans Rd",
    "sg:city":"Pompano Beach",
    "sg:classifiers":[
        {
            "category":"Autos & Motor Vehicles",
            "subcategory":"Auto Supplies",
            "type":"Retail Goods"
        }
    ],
    "sg:phone":"+1 954 979 4244",
    "sg:postcode":"33064",
    "sg:province":"FL",
    "sg:tags":[
        "automobile",
        "parts"
    ],
    "wof:name":"Bumper To Bumper",
    "wof:placetype":"venue"
},
  "geometry": {"coordinates":[-80.146377,26.260485],"type":"Point"}
}