{
  "type": "Feature",
  "properties": {
    "addr:full":"631 Park St Jacksonville FL 32204",
    "addr:housenumber":"631",
    "addr:postcode":"32204",
    "addr:street":"Park St",
    "iso:country":"US",
    "sg:address":"631 Park St",
    "sg:city":"Jacksonville",
    "sg:classifiers":[
        {
            "category":"Organizations",
            "subcategory":"Labor Organization",
            "type":"Services"
        }
    ],
    "sg:phone":"+1 904 354 8500",
    "sg:postcode":"32204",
    "sg:province":"FL",
    "wof:name":"National Assn-Letter Carriers",
    "wof:placetype":"venue"
},
  "geometry": {"coordinates":[-81.679036,30.318764],"type":"Point"}
}