{
  "type": "Feature",
  "properties": {
    "addr:full":"710 Oakfield Dr Brandon FL 33511",
    "addr:housenumber":"710",
    "addr:postcode":"33511",
    "addr:street":"Oakfield Dr",
    "iso:country":"US",
    "sg:address":"710 Oakfield Dr",
    "sg:city":"Brandon",
    "sg:classifiers":[
        {
            "category":"Health Services",
            "subcategory":"Clinic",
            "type":"Services"
        }
    ],
    "sg:phone":"+1 813 681 9455",
    "sg:postcode":"33511",
    "sg:province":"FL",
    "sg:tags":[
        "home",
        "agency",
        "employment",
        "care"
    ],
    "wof:name":"Columbia Health Care",
    "wof:placetype":"venue"
},
  "geometry": {"coordinates":[-82.296339,27.93423],"type":"Point"}
}