{
  "type": "Feature",
  "properties": {
    "addr:full":"13981 US Hwy 1 Juno Beach FL 33408",
    "addr:housenumber":"13981",
    "addr:postcode":"33408",
    "addr:street":"Us Hwy 1 Juno Beach",
    "iso:country":"US",
    "sg:address":"13981 US Hwy 1",
    "sg:city":"Juno Beach",
    "sg:classifiers":[
        {
            "category":"Home & Garden",
            "subcategory":"Garden Supply",
            "type":"Retail Goods"
        }
    ],
    "sg:phone":"+1 561 624 3776",
    "sg:postcode":"33408",
    "sg:province":"FL",
    "sg:tags":[
        "tree",
        "christmas"
    ],
    "wof:name":"North Pole Christmas Trees",
    "wof:placetype":"venue"
},
  "geometry": {"coordinates":[-80.056229,26.880527],"type":"Point"}
}