{
  "type": "Feature",
  "properties": {
    "iso:country":"US",
    "sg:address":"8664 N Atlantic Ave",
    "sg:city":"Cape Canaveral",
    "sg:classifiers":[
        {
            "category":"Building & Trades",
            "subcategory":"Cleaning & Sanitation",
            "type":"Services"
        }
    ],
    "sg:phone":"+1 321 868 0300",
    "sg:postcode":"32920",
    "sg:province":"FL",
    "sg:tags":[
        "janitor"
    ],
    "wof:name":"Ultra Clean Svc",
    "wof:placetype":"venue"
},
  "geometry": {"coordinates":[-80.604602,28.39789],"type":"Point"}
}