{
  "type": "Feature",
  "properties": {
    "addr:full":"1878 Dr Andres Way Delray Beach FL 33445",
    "addr:housenumber":"1878",
    "addr:postcode":"33445",
    "addr:street":"Dr Andres Way",
    "iso:country":"US",
    "sg:address":"1878 Dr Andres Way",
    "sg:city":"Delray Beach",
    "sg:classifiers":[
        {
            "category":"Retail",
            "subcategory":"Auto Repair",
            "type":"Services"
        }
    ],
    "sg:phone":"+1 561 272 7196",
    "sg:postcode":"33445",
    "sg:province":"FL",
    "sg:tags":[
        "glass",
        "coating",
        "tinting"
    ],
    "wof:name":"Crystal Clear Automotive",
    "wof:placetype":"venue"
},
  "geometry": {"coordinates":[-80.09290300000001,26.458667],"type":"Point"}
}