{
  "type": "Feature",
  "properties": {
    "iso:country":"US",
    "sg:address":"6020 Diana Rd",
    "sg:city":"Venice",
    "sg:classifiers":[
        {
            "category":"Manufacturing",
            "subcategory":"Metals",
            "type":"Manufacturing & Wholesale Goods"
        }
    ],
    "sg:phone":"+1 941 497 5297",
    "sg:postcode":"34293",
    "sg:province":"FL",
    "sg:tags":[
        "aluminum",
        "primary",
        "producer"
    ],
    "wof:name":"Mark Calvert Aluminum LLC",
    "wof:placetype":"venue"
},
  "geometry": {"coordinates":[-82.40775499999999,27.02723],"type":"Point"}
}