{
  "type": "Feature",
  "properties": {
    "iso:country":"US",
    "sg:address":"9307 N 56th St",
    "sg:city":"Tampa",
    "sg:classifiers":[
        {
            "category":"Restaurant",
            "type":"Food & Drink"
        }
    ],
    "sg:menulink":"http://www.allmenus.com/fl/tampa/81409-papa-johns-pizza/menu/",
    "sg:phone":"+1 813 985 7272",
    "sg:postcode":"33617",
    "sg:province":"FL",
    "sg:tags":[
        "american",
        "pizza"
    ],
    "wof:name":"Papa John's Pizza",
    "wof:placetype":"venue"
},
  "geometry": {"coordinates":[-82.393412,28.034505],"type":"Point"}
}