{
  "type": "Feature",
  "properties": {
    "iso:country":"US",
    "sg:address":"15423 Lake Magdalene Blvd",
    "sg:city":"Tampa",
    "sg:classifiers":[
        {
            "category":"Retail",
            "subcategory":"Repair Shop",
            "type":"Services"
        }
    ],
    "sg:phone":"+1 813 269 9492",
    "sg:postcode":"33613",
    "sg:province":"FL",
    "sg:tags":[
        "water",
        "equipment",
        "softening"
    ],
    "wof:name":"AWS",
    "wof:placetype":"venue"
},
  "geometry": {"coordinates":[-82.4808,28.098983],"type":"Point"}
}