{
  "type": "Feature",
  "properties": {
    "addr:full":"5410 SW 130th Ave Fort Lauderdale FL 33330",
    "addr:housenumber":"5410",
    "addr:postcode":"33330",
    "addr:street":"Sw 130Th Ave",
    "iso:country":"US",
    "sg:address":"5410 SW 130th Ave",
    "sg:city":"Fort Lauderdale",
    "sg:classifiers":[
        {
            "category":"Recreation",
            "type":"Entertainment"
        }
    ],
    "sg:phone":"+1 954 442 8863",
    "sg:postcode":"33330",
    "sg:province":"FL",
    "sg:tags":[
        "travel",
        "agency"
    ],
    "wof:name":"Eco Destination Mgt Svcs",
    "wof:placetype":"venue"
},
  "geometry": {"coordinates":[-80.321529,26.054712],"type":"Point"}
}