{
  "type": "Feature",
  "properties": {
    "addr:full":"4447 Land O Lakes Blvd Land O Lakes FL 34639",
    "addr:housenumber":"4447",
    "addr:postcode":"34639",
    "addr:street":"Land O Lakes Blvd Land",
    "iso:country":"US",
    "sg:address":"4447 Land O Lakes Blvd",
    "sg:city":"Land O Lakes",
    "sg:classifiers":[
        {
            "category":"Autos & Motor Vehicles",
            "subcategory":"Automobile Sales",
            "type":"Retail Goods"
        }
    ],
    "sg:phone":"+1 813 995 9020",
    "sg:postcode":"34639",
    "sg:province":"FL",
    "sg:website":"www.teecarts.biz",
    "wof:name":"Teecarts LLC",
    "wof:placetype":"venue"
},
  "geometry": {"coordinates":[-82.45779400000001,28.224773],"type":"Point"}
}