{
  "type": "Feature",
  "properties": {
    "iso:country":"US",
    "sg:address":"21 Blue Gulf Dr",
    "sg:city":"Santa Rosa Beach",
    "sg:classifiers":[
        {
            "category":"Shopping",
            "type":"Retail Goods"
        }
    ],
    "sg:phone":"+1 850 267 0228",
    "sg:postcode":"32459",
    "sg:province":"FL",
    "sg:tags":[
        "merchandise"
    ],
    "wof:name":"Gaffrey Art Gallery",
    "wof:placetype":"venue"
},
  "geometry": {"coordinates":[-86.21075999999999,30.349949],"type":"Point"}
}