{
  "type": "Feature",
  "properties": {
    "addr:full":"11522 State Hwy 84 Fort Lauderdale FL 33325",
    "addr:housenumber":"11522",
    "addr:postcode":"33325",
    "addr:street":"State Hwy 84",
    "iso:country":"US",
    "sg:address":"11522 State Hwy 84",
    "sg:city":"Fort Lauderdale",
    "sg:classifiers":[
        {
            "category":"Personal",
            "subcategory":"Barber",
            "type":"Services"
        }
    ],
    "sg:phone":"+1 954 472 9447",
    "sg:postcode":"33325",
    "sg:province":"FL",
    "sg:tags":[
        "shop"
    ],
    "wof:name":"Micks Barber Shop",
    "wof:placetype":"venue"
},
  "geometry": {"coordinates":[-80.30415499999999,26.112561],"type":"Point"}
}