{
  "type": "Feature",
  "properties": {
    "addr:full":"5933 S Congress Ave Lantana FL 33462",
    "addr:housenumber":"5933",
    "addr:postcode":"33462",
    "addr:street":"S Congress Ave",
    "iso:country":"US",
    "sg:address":"5933 S Congress Ave",
    "sg:city":"Lantana",
    "sg:classifiers":[
        {
            "category":"Restaurant",
            "type":"Food & Drink"
        }
    ],
    "sg:phone":"+1 561 965 0010",
    "sg:postcode":"33462",
    "sg:province":"FL",
    "sg:tags":[
        "parlor",
        "ice",
        "cream"
    ],
    "wof:name":"Peppermint Patti's Ice Cream",
    "wof:placetype":"venue"
},
  "geometry": {"coordinates":[-80.093493,26.593409],"type":"Point"}
}