{
  "type": "Feature",
  "properties": {
    "iso:country":"US",
    "sg:address":"10241 Metro Pkwy",
    "sg:city":"Fort Myers",
    "sg:classifiers":[
        {
            "category":"Professional",
            "subcategory":"Management & Consulting",
            "type":"Services"
        }
    ],
    "sg:phone":"+1 239 936 4874",
    "sg:postcode":"33966",
    "sg:province":"FL",
    "sg:tags":[
        "consultant",
        "medical"
    ],
    "wof:name":"Kinetic Concepts Inc",
    "wof:placetype":"venue"
},
  "geometry": {"coordinates":[-81.851445,26.591106],"type":"Point"}
}