{
  "type": "Feature",
  "properties": {
    "iso:country":"US",
    "sg:address":"9117 SW 72nd Ave Ste E3",
    "sg:city":"Miami",
    "sg:classifiers":[
        {
            "category":"Real Estate",
            "subcategory":"Real Estate Operator",
            "type":"Services"
        }
    ],
    "sg:phone":"+1 305 665 5276",
    "sg:postcode":"33156",
    "sg:province":"FL",
    "sg:tags":[
        "apartment"
    ],
    "sg:website":"www.kendallhouseapartments.com",
    "wof:name":"Kendall House Apartments",
    "wof:placetype":"venue"
},
  "geometry": {"coordinates":[-80.310997,25.6861],"type":"Point"}
}