{
  "type": "Feature",
  "properties": {
    "iso:country":"US",
    "sg:address":"10741 SW 139th Ave",
    "sg:city":"Miami",
    "sg:classifiers":[
        {
            "category":"Shopping",
            "subcategory":"Clothing, Apparel, & Fashions",
            "type":"Retail Goods"
        }
    ],
    "sg:phone":"+1 305 382 7604",
    "sg:postcode":"33186",
    "sg:province":"FL",
    "sg:tags":[
        "consulting",
        "management"
    ],
    "wof:name":"G P In & Out",
    "wof:placetype":"venue"
},
  "geometry": {"coordinates":[-80.420188,25.668482],"type":"Point"}
}