{
  "type": "Feature",
  "properties": {
    "iso:country":"US",
    "sg:address":"303 N 4th St",
    "sg:city":"Lake Worth",
    "sg:classifiers":[
        {
            "category":"Food & Beverages",
            "subcategory":"Groceries & Convenience Stores",
            "type":"Retail Goods"
        }
    ],
    "sg:phone":"+1 561 740 3949",
    "sg:postcode":"33462",
    "sg:province":"FL",
    "wof:name":"Marie C Georges Food Market",
    "wof:placetype":"venue"
},
  "geometry": {"coordinates":[-80.054303,26.5868],"type":"Point"}
}