{
  "type": "Feature",
  "properties": {
    "iso:country":"US",
    "sg:address":"1149 Lake Dr",
    "sg:city":"Cocoa",
    "sg:classifiers":[
        {
            "category":"Shopping",
            "subcategory":"Clothing, Apparel, & Fashions",
            "type":"Retail Goods"
        }
    ],
    "sg:phone":"+1 321 636 8114",
    "sg:postcode":"32922",
    "sg:province":"FL",
    "sg:tags":[
        "youth",
        "organization"
    ],
    "wof:name":"Fcaa Brevard County Family",
    "wof:placetype":"venue"
},
  "geometry": {"coordinates":[-80.746816,28.357251],"type":"Point"}
}