{
  "type": "Feature",
  "properties": {
    "iso:country":"US",
    "sg:address":"17212 US Hwy 19",
    "sg:city":"Hudson",
    "sg:classifiers":[
        {
            "category":"Building & Trades",
            "subcategory":"Landscaping Services",
            "type":"Services"
        }
    ],
    "sg:phone":"+1 727 869 7447",
    "sg:postcode":"34667",
    "sg:province":"FL",
    "sg:tags":[
        "landscape",
        "contractor"
    ],
    "wof:name":"Garden World Nursery",
    "wof:placetype":"venue"
},
  "geometry": {"coordinates":[-82.651785,28.409098],"type":"Point"}
}