{
  "type": "Feature",
  "properties": {
    "addr:full":"3332 Southside Blvd Jacksonville FL 32216",
    "addr:housenumber":"3332",
    "addr:postcode":"32216",
    "addr:street":"Southside Blvd",
    "iso:country":"US",
    "sg:address":"3332 Southside Blvd",
    "sg:city":"Jacksonville",
    "sg:classifiers":[
        {
            "category":"Building & Trades",
            "subcategory":"Plumbing",
            "type":"Services"
        }
    ],
    "sg:phone":"+1 904 388 1900",
    "sg:postcode":"32216",
    "sg:province":"FL",
    "sg:tags":[
        "conditioning",
        "air",
        "heating",
        "contractor"
    ],
    "wof:name":"Elder Heating & Cooling Inc",
    "wof:placetype":"venue"
},
  "geometry": {"coordinates":[-81.559296,30.286314],"type":"Point"}
}