{
  "type": "Feature",
  "properties": {
    "addr:full":"7230 US Hwy 301 Riverview FL 33569",
    "addr:housenumber":"7230",
    "addr:postcode":"33569",
    "addr:street":"Us Hwy 301",
    "iso:country":"US",
    "sg:address":"7230 US Hwy 301",
    "sg:city":"Riverview",
    "sg:classifiers":[
        {
            "category":"Insurance",
            "subcategory":"Insurance Agent",
            "type":"Services"
        }
    ],
    "sg:phone":"+1 813 677 0782",
    "sg:postcode":"33569",
    "sg:province":"FL",
    "wof:name":"Great Florida Ins Of Riverview",
    "wof:placetype":"venue"
},
  "geometry": {"coordinates":[-82.32665299999999,27.877873],"type":"Point"}
}