{
  "type": "Feature",
  "properties": {
    "addr:full":"6316 Autumn Chase Ln Orlando FL 32818",
    "addr:housenumber":"6316",
    "addr:postcode":"32818",
    "addr:street":"Autumn Chase Ln",
    "iso:country":"US",
    "sg:address":"6316 Autumn Chase Ln",
    "sg:city":"Orlando",
    "sg:classifiers":[
        {
            "category":"Building & Trades",
            "subcategory":"Plumbing",
            "type":"Services"
        }
    ],
    "sg:phone":"+1 407 814 9547",
    "sg:postcode":"32818",
    "sg:province":"FL",
    "sg:tags":[
        "conditioning",
        "air",
        "system",
        "contractor"
    ],
    "wof:name":"Elite Air Conditioning & Htg",
    "wof:placetype":"venue"
},
  "geometry": {"coordinates":[-81.484571,28.629708],"type":"Point"}
}