{
  "type": "Feature",
  "properties": {
    "iso:country":"US",
    "sg:address":"1126 N Fletcher Ave",
    "sg:city":"Fernandina Beach",
    "sg:classifiers":[
        {
            "category":"Restaurant",
            "type":"Food & Drink"
        }
    ],
    "sg:phone":"+1 904 261 3636",
    "sg:postcode":"32034",
    "sg:province":"FL",
    "sg:tags":[
        "eating"
    ],
    "wof:name":"Blue Seas Restaurant",
    "wof:placetype":"venue"
},
  "geometry": {"coordinates":[-81.429717,30.681366],"type":"Point"}
}