{
  "type": "Feature",
  "properties": {
    "iso:country":"US",
    "sg:address":"896 S Dixie Hwy",
    "sg:city":"Coral Gables",
    "sg:classifiers":[
        {
            "category":"Health Services",
            "subcategory":"Dentist",
            "type":"Services"
        }
    ],
    "sg:phone":"+1 305 661 9798",
    "sg:postcode":"33146",
    "sg:province":"FL",
    "sg:tags":[
        "orthodontist"
    ],
    "wof:name":"Coro Jorge C Ms DMD",
    "wof:placetype":"venue"
},
  "geometry": {"coordinates":[-80.270798,25.719299],"type":"Point"}
}