{
  "type": "Feature",
  "properties": {
    "addr:full":"310 Egan Dr Crestview FL 32536",
    "addr:housenumber":"310",
    "addr:postcode":"32536",
    "addr:street":"Egan Dr",
    "iso:country":"US",
    "sg:address":"310 Egan Dr",
    "sg:city":"Crestview",
    "sg:classifiers":[
        {
            "category":"Real Estate",
            "subcategory":"Real Estate Operator",
            "type":"Services"
        }
    ],
    "sg:phone":"+1 850 689 2246",
    "sg:postcode":"32536",
    "sg:province":"FL",
    "sg:tags":[
        "building",
        "nonresidential"
    ],
    "wof:name":"Abstan Properties",
    "wof:placetype":"venue"
},
  "geometry": {"coordinates":[-86.61308099999999,30.718135],"type":"Point"}
}