{
  "type": "Feature",
  "properties": {
    "addr:full":"10108 Hatteras Ct Fort Myers FL 33919",
    "addr:housenumber":"10108",
    "addr:postcode":"33919",
    "addr:street":"Hatteras Ct",
    "iso:country":"US",
    "sg:address":"10108 Hatteras Ct",
    "sg:city":"Fort Myers",
    "sg:classifiers":[
        {
            "category":"Professional",
            "type":"Services"
        }
    ],
    "sg:phone":"+1 239 454 4263",
    "sg:postcode":"33919",
    "sg:province":"FL",
    "sg:tags":[
        "establishment"
    ],
    "wof:name":"Giordano International Corp",
    "wof:placetype":"venue"
},
  "geometry": {"coordinates":[-81.92165199999999,26.554557],"type":"Point"}
}