{
  "type": "Feature",
  "properties": {
    "addr:full":"4561 W 10th Ave Hialeah FL 33012",
    "addr:housenumber":"4561",
    "addr:postcode":"33012",
    "addr:street":"W 10Th Ave",
    "iso:country":"US",
    "sg:address":"4561 W 10th Ave",
    "sg:city":"Hialeah",
    "sg:classifiers":[
        {
            "category":"Real Estate",
            "subcategory":"Real Estate Services",
            "type":"Services"
        }
    ],
    "sg:phone":"+1 305 824 0007",
    "sg:postcode":"33012",
    "sg:province":"FL",
    "sg:tags":[
        "abstract",
        "title"
    ],
    "wof:name":"Es Title Services Inc",
    "wof:placetype":"venue"
},
  "geometry": {"coordinates":[-80.303235,25.863586],"type":"Point"}
}