{
  "type": "Feature",
  "properties": {
    "iso:country":"US",
    "sg:address":"6460 126th Ave",
    "sg:city":"Largo",
    "sg:classifiers":[
        {
            "category":"Autos & Motor Vehicles",
            "subcategory":"Auto Supplies",
            "type":"Retail Goods"
        }
    ],
    "sg:phone":"+1 727 531 7701",
    "sg:postcode":"33773",
    "sg:province":"FL",
    "sg:tags":[
        "body",
        "shop",
        "equipment",
        "automobile"
    ],
    "sg:website":"http://www.ipaindustrial.com",
    "wof:name":"Finishmaster, Inc.",
    "wof:placetype":"venue"
},
  "geometry": {"coordinates":[-82.72631199999999,27.886431],"type":"Point"}
}