{
  "type": "Feature",
  "properties": {
    "iso:country":"US",
    "sg:address":"2150 Spencer Rd",
    "sg:city":"Orange Park",
    "sg:classifiers":[
        {
            "category":"Real Estate",
            "subcategory":"Real Estate Operator",
            "type":"Services"
        }
    ],
    "sg:phone":"+1 904 272 2282",
    "sg:postcode":"32073",
    "sg:province":"FL",
    "sg:tags":[
        "apartment"
    ],
    "sg:website":"www.forrent.com",
    "wof:name":"Four Winds Apartments",
    "wof:placetype":"venue"
},
  "geometry": {"coordinates":[-81.749571,30.167161],"type":"Point"}
}