{
  "type": "Feature",
  "properties": {
    "iso:country":"US",
    "sg:address":"1464 SW 48th Ave",
    "sg:city":"Fort Lauderdale",
    "sg:classifiers":[
        {
            "category":"Building & Trades",
            "subcategory":"Construction",
            "type":"Services"
        }
    ],
    "sg:phone":"+1 954 583 8704",
    "sg:postcode":"33317",
    "sg:province":"FL",
    "sg:tags":[
        "contractor"
    ],
    "wof:name":"S&L Fence Inc",
    "wof:placetype":"venue"
},
  "geometry": {"coordinates":[-80.21264499999999,26.104298],"type":"Point"}
}