{
  "type": "Feature",
  "properties": {
    "addr:full":"741 S Orlando Ave Winter Park FL 32789",
    "addr:housenumber":"741",
    "addr:postcode":"32789",
    "addr:street":"S Orlando Ave",
    "iso:country":"US",
    "sg:address":"741 S Orlando Ave",
    "sg:city":"Winter Park",
    "sg:classifiers":[
        {
            "category":"Shopping",
            "subcategory":"Pharmacy",
            "type":"Retail Goods"
        }
    ],
    "sg:phone":"+1 407 647 0346",
    "sg:postcode":"32789",
    "sg:province":"FL",
    "sg:tags":[
        "drugstore"
    ],
    "wof:name":"Publix Pharmacy",
    "wof:placetype":"venue"
},
  "geometry": {"coordinates":[-81.36489899999999,28.591499],"type":"Point"}
}