{
  "type": "Feature",
  "properties": {
    "addr:full":"2202 N 38th St Tampa FL 33605",
    "addr:housenumber":"2202",
    "addr:postcode":"33605",
    "addr:street":"N 38Th St",
    "iso:country":"US",
    "sg:address":"2202 N 38th St",
    "sg:city":"Tampa",
    "sg:classifiers":[
        {
            "category":"Shopping",
            "type":"Retail Goods"
        }
    ],
    "sg:phone":"+1 813 223 9538",
    "sg:postcode":"33605",
    "sg:province":"FL",
    "sg:tags":[
        "corporate",
        "event"
    ],
    "wof:name":"Modern Display",
    "wof:placetype":"venue"
},
  "geometry": {"coordinates":[-82.41727899999999,27.963099],"type":"Point"}
}