{
  "type": "Feature",
  "properties": {
    "iso:country":"US",
    "sg:address":"1950 NW 15th St",
    "sg:city":"Pompano Beach",
    "sg:classifiers":[
        {
            "category":"Wholesale",
            "subcategory":"Plants",
            "type":"Manufacturing & Wholesale Goods"
        }
    ],
    "sg:phone":"+1 954 979 0600",
    "sg:postcode":"33069",
    "sg:province":"FL",
    "sg:tags":[
        "nursery",
        "landscape",
        "supply"
    ],
    "wof:name":"Universal Enterprises Supply",
    "wof:placetype":"venue"
},
  "geometry": {"coordinates":[-80.150655,26.2454],"type":"Point"}
}