{
  "type": "Feature",
  "properties": {
    "iso:country":"US",
    "sg:address":"19498 E Country Club Dr",
    "sg:city":"Miami",
    "sg:classifiers":[
        {
            "category":"Health Services",
            "subcategory":"Podiatrist",
            "type":"Services"
        }
    ],
    "sg:phone":"+1 305 974 4534",
    "sg:postcode":"33180",
    "sg:province":"FL",
    "sg:tags":[
        "physician",
        "surgeons"
    ],
    "wof:name":"Podiatry 2013, Inc.",
    "wof:placetype":"venue"
},
  "geometry": {"coordinates":[-80.132008,25.957631],"type":"Point"}
}