{
  "type": "Feature",
  "properties": {
    "addr:full":"721 N Lincoln Ln Miami Beach FL 33139",
    "addr:housenumber":"721",
    "addr:postcode":"33139",
    "addr:street":"N Lincoln Ln",
    "iso:country":"US",
    "sg:address":"721 N Lincoln Ln",
    "sg:city":"Miami Beach",
    "sg:classifiers":[
        {
            "category":"Shopping",
            "subcategory":"Used Merchandise",
            "type":"Retail Goods"
        }
    ],
    "sg:phone":"+1 305 333 5675",
    "sg:postcode":"33139",
    "sg:province":"FL",
    "sg:tags":[
        "vintage",
        "consignment"
    ],
    "wof:name":"ShopBar",
    "wof:placetype":"venue"
},
  "geometry": {"coordinates":[-80.135837,25.791196],"type":"Point"}
}