{
  "type": "Feature",
  "properties": {
    "iso:country":"US",
    "sg:address":"8432 Juniper Ave",
    "sg:city":"Pensacola",
    "sg:classifiers":[
        {
            "category":"Wholesale",
            "subcategory":"Auto Parts",
            "type":"Manufacturing & Wholesale Goods"
        }
    ],
    "sg:phone":"+1 850 477 6850",
    "sg:postcode":"32534",
    "sg:province":"FL",
    "wof:name":"Dps",
    "wof:placetype":"venue"
},
  "geometry": {"coordinates":[-87.271388,30.519556],"type":"Point"}
}