{
  "type": "Feature",
  "properties": {
    "iso:country":"US",
    "sg:address":"5014 Damsen Cir",
    "sg:city":"New Port Richey",
    "sg:classifiers":[
        {
            "category":"Shopping",
            "subcategory":"Catalog Store",
            "type":"Retail Goods"
        },
        {
            "category":"Shopping",
            "subcategory":"Clothing, Apparel, & Fashions",
            "type":"Retail Goods"
        }
    ],
    "sg:phone":"+1 727 847 6471",
    "sg:postcode":"34653",
    "sg:province":"FL",
    "sg:tags":[
        "house",
        "boutique",
        "item",
        "mail"
    ],
    "wof:name":"Sue's Birdie Boutique",
    "wof:placetype":"venue"
},
  "geometry": {"coordinates":[-82.702493,28.233202],"type":"Point"}
}