{
  "type": "Feature",
  "properties": {
    "addr:full":"1585 E 11th Ave Hialeah FL 33010",
    "addr:housenumber":"1585",
    "addr:postcode":"33010",
    "addr:street":"E 11Th Ave",
    "iso:country":"US",
    "sg:address":"1585 E 11th Ave",
    "sg:city":"Hialeah",
    "sg:classifiers":[
        {
            "category":"Home & Garden",
            "subcategory":"Building Materials",
            "type":"Retail Goods"
        }
    ],
    "sg:phone":"+1 305 887 9199",
    "sg:postcode":"33010",
    "sg:province":"FL",
    "sg:tags":[
        "carpentry",
        "contractor"
    ],
    "wof:name":"Stefanini Millwork Inc",
    "wof:placetype":"venue"
},
  "geometry": {"coordinates":[-80.259919,25.83657],"type":"Point"}
}