{
  "type": "Feature",
  "properties": {
    "addr:full":"19730 SW 12th St Hollywood FL 33029",
    "addr:housenumber":"19730",
    "addr:postcode":"33029",
    "addr:street":"Sw 12Th St",
    "iso:country":"US",
    "sg:address":"19730 SW 12th St",
    "sg:city":"Hollywood",
    "sg:classifiers":[
        {
            "category":"Building & Trades",
            "subcategory":"Construction",
            "type":"Services"
        }
    ],
    "sg:phone":"+1 954 431 7193",
    "sg:postcode":"33029",
    "sg:province":"FL",
    "sg:tags":[
        "contractor"
    ],
    "wof:name":"Taurus Residential Bldg Contrs",
    "wof:placetype":"venue"
},
  "geometry": {"coordinates":[-80.40973200000001,25.997583],"type":"Point"}
}