{
  "type": "Feature",
  "properties": {
    "addr:full":"816 US Hwy 98 Destin FL 32541",
    "addr:housenumber":"816",
    "addr:postcode":"32541",
    "addr:street":"Us Hwy 98",
    "iso:country":"US",
    "sg:address":"816 US Hwy 98",
    "sg:city":"Destin",
    "sg:classifiers":[
        {
            "category":"Real Estate",
            "subcategory":"Real Estate Agent",
            "type":"Services"
        }
    ],
    "sg:phone":"+1 850 837 9950",
    "sg:postcode":"32541",
    "sg:province":"FL",
    "wof:name":"Monica T Bozeman Real Estate",
    "wof:placetype":"venue"
},
  "geometry": {"coordinates":[-86.48097,30.38894],"type":"Point"}
}