{
  "type": "Feature",
  "properties": {
    "addr:full":"3785 NW 82nd Ave Miami FL 33166",
    "addr:housenumber":"3785",
    "addr:postcode":"33166",
    "addr:street":"Nw 82Nd Ave",
    "iso:country":"US",
    "sg:address":"3785 NW 82nd Ave",
    "sg:city":"Miami",
    "sg:classifiers":[
        {
            "category":"Utilities",
            "subcategory":"Telephone",
            "type":"Services"
        }
    ],
    "sg:phone":"+1 305 255 9782",
    "sg:postcode":"33166",
    "sg:province":"FL",
    "sg:tags":[
        "communications"
    ],
    "wof:name":"Web Monster Inc",
    "wof:placetype":"venue"
},
  "geometry": {"coordinates":[-80.329295,25.809727],"type":"Point"}
}