{
  "type": "Feature",
  "properties": {
    "addr:full":"201 N Federal Hwy Hollywood FL 33020",
    "addr:housenumber":"201",
    "addr:postcode":"33020",
    "addr:street":"N Federal Hwy",
    "iso:country":"US",
    "sg:address":"201 N Federal Hwy",
    "sg:city":"Hollywood",
    "sg:classifiers":[
        {
            "category":"Bakery",
            "type":"Food & Drink"
        },
        {
            "category":"Coffee & Tea",
            "type":"Food & Drink"
        },
        {
            "category":"Bagels",
            "type":"Food & Drink"
        },
        {
            "category":"Donuts",
            "type":"Food & Drink"
        }
    ],
    "sg:menulink":"http://www.allmenus.com/fl/hollywood/137971-dunkin-donuts/menu/",
    "sg:phone":"+1 954 457 9918",
    "sg:postcode":"33020",
    "sg:province":"FL",
    "sg:tags":[
        "american",
        "pastry"
    ],
    "wof:name":"Dunkin' Donuts",
    "wof:placetype":"venue"
},
  "geometry": {"coordinates":[-80.142929,26.012756],"type":"Point"}
}