{
  "type": "Feature",
  "properties": {
    "iso:country":"US",
    "sg:address":"8211 NW 64th St",
    "sg:city":"Miami",
    "sg:classifiers":[
        {
            "category":"Shopping",
            "type":"Retail Goods"
        }
    ],
    "sg:phone":"+1 305 639 6766",
    "sg:postcode":"33166",
    "sg:province":"FL",
    "sg:tags":[
        "equipment",
        "care",
        "health",
        "home"
    ],
    "wof:name":"Home Medical Svc",
    "wof:placetype":"venue"
},
  "geometry": {"coordinates":[-80.33376,25.831778],"type":"Point"}
}