{
  "type": "Feature",
  "properties": {
    "iso:country":"US",
    "sg:address":"3850 SW 87 Ave",
    "sg:city":"Miami",
    "sg:classifiers":[
        {
            "category":"Health Services",
            "subcategory":"Dentist",
            "type":"Services"
        }
    ],
    "sg:phone":"+1 786 228 7420",
    "sg:postcode":"33165",
    "sg:province":"FL",
    "wof:name":"The Oaks Dental",
    "wof:placetype":"venue"
},
  "geometry": {"coordinates":[-80.33609800000001,25.734123],"type":"Point"}
}