{
  "type": "Feature",
  "properties": {
    "iso:country":"US",
    "sg:address":"1523 NW 16th Ave",
    "sg:city":"Gainesville",
    "sg:classifiers":[
        {
            "category":"Professional",
            "subcategory":"Engineering",
            "type":"Services"
        }
    ],
    "sg:phone":"+1 352 335 6100",
    "sg:postcode":"32605",
    "sg:province":"FL",
    "sg:tags":[
        "civil",
        "contractor",
        "engineer"
    ],
    "wof:name":"Structural Dimensions Inc",
    "wof:placetype":"venue"
},
  "geometry": {"coordinates":[-82.342175,29.666724],"type":"Point"}
}