{
  "type": "Feature",
  "properties": {
    "iso:country":"US",
    "sg:address":"7333 NW 54th St",
    "sg:city":"Miami",
    "sg:classifiers":[
        {
            "category":"Building & Trades",
            "subcategory":"Construction",
            "type":"Services"
        }
    ],
    "sg:phone":"+1 305 805 5385",
    "sg:postcode":"33166",
    "sg:province":"FL",
    "sg:tags":[
        "contractor"
    ],
    "wof:name":"Mr Grout Tile & Grout",
    "wof:placetype":"venue"
},
  "geometry": {"coordinates":[-80.31632,25.822634],"type":"Point"}
}