{
  "type": "Feature",
  "properties": {
    "iso:country":"US",
    "sg:address":"2986 Ocean Shore Blvd",
    "sg:city":"Ormond Beach",
    "sg:classifiers":[
        {
            "category":"Restaurant",
            "type":"Food & Drink"
        }
    ],
    "sg:phone":"+1 386 441 4554",
    "sg:postcode":"32176",
    "sg:province":"FL",
    "wof:name":"Stella's At The Beach",
    "wof:placetype":"venue"
},
  "geometry": {"coordinates":[-81.075363,29.36759],"type":"Point"}
}