{
  "type": "Feature",
  "properties": {
    "iso:country":"US",
    "sg:address":"1366 Co Rd 29",
    "sg:city":"Lake Placid",
    "sg:classifiers":[
        {
            "category":"Farming",
            "subcategory":"Farm",
            "type":"Manufacturing & Wholesale Goods"
        },
        {
            "category":"Farming",
            "subcategory":"Nursery",
            "type":"Manufacturing & Wholesale Goods"
        }
    ],
    "sg:phone":"+1 863 465 2580",
    "sg:postcode":"33852",
    "sg:province":"FL",
    "sg:tags":[
        "ornamental"
    ],
    "wof:name":"Parker Island Bulb Co Inc",
    "wof:placetype":"venue"
},
  "geometry": {"coordinates":[-81.283659,27.231324],"type":"Point"}
}