{
  "type": "Feature",
  "properties": {
    "iso:country":"US",
    "sg:address":"2065 E Duval St",
    "sg:city":"Lake City",
    "sg:classifiers":[
        {
            "category":"Restaurant",
            "type":"Food & Drink"
        }
    ],
    "sg:phone":"+1 386 755 5058",
    "sg:postcode":"32055",
    "sg:province":"FL",
    "wof:name":"Crossroads Cafe",
    "wof:placetype":"venue"
},
  "geometry": {"coordinates":[-82.620588,30.189538],"type":"Point"}
}