{
  "type": "Feature",
  "properties": {
    "addr:full":"4136 Pembroke Rd Hollywood FL 33021",
    "addr:housenumber":"4136",
    "addr:postcode":"33021",
    "addr:street":"Pembroke Rd",
    "iso:country":"US",
    "sg:address":"4136 Pembroke Rd",
    "sg:city":"Hollywood",
    "sg:classifiers":[
        {
            "category":"Retail",
            "subcategory":"Auto Repair",
            "type":"Services"
        }
    ],
    "sg:phone":"+1 954 962 5081",
    "sg:postcode":"33021",
    "sg:province":"FL",
    "sg:tags":[
        "automotive"
    ],
    "wof:name":"Lous Super Service",
    "wof:placetype":"venue"
},
  "geometry": {"coordinates":[-80.184135,25.99554],"type":"Point"}
}