{
  "type": "Feature",
  "properties": {
    "addr:full":"16800 Collins Ave Sunny Isles Beach FL 33160",
    "addr:housenumber":"16800",
    "addr:postcode":"33160",
    "addr:street":"Collins Ave",
    "iso:country":"US",
    "sg:address":"16800 Collins Ave",
    "sg:city":"Sunny Isles Beach",
    "sg:classifiers":[
        {
            "category":"Autos & Motor Vehicles",
            "subcategory":"Fuel & Gas Station",
            "type":"Retail Goods"
        }
    ],
    "sg:phone":"+1 305 945 0322",
    "sg:postcode":"33160",
    "sg:province":"FL",
    "sg:website":"www.shell.com",
    "wof:name":"North Beach Shell",
    "wof:placetype":"venue"
},
  "geometry": {"coordinates":[-80.121803,25.9319],"type":"Point"}
}