{
  "type": "Feature",
  "properties": {
    "iso:country":"US",
    "sg:address":"133 E Flagler St",
    "sg:city":"Miami",
    "sg:classifiers":[
        {
            "category":"Shopping",
            "subcategory":"Computers & Home Electronics",
            "type":"Retail Goods"
        }
    ],
    "sg:phone":"+1 305 375 8044",
    "sg:postcode":"33131",
    "sg:province":"FL",
    "sg:tags":[
        "consumer",
        "electronic",
        "equipment"
    ],
    "wof:name":"Osmar Electronics",
    "wof:placetype":"venue"
},
  "geometry": {"coordinates":[-80.19076200000001,25.7743],"type":"Point"}
}