{
  "type": "Feature",
  "properties": {
    "iso:country":"US",
    "sg:address":"1246 17th Ave N",
    "sg:city":"Lake Worth",
    "sg:classifiers":[
        {
            "category":"Real Estate",
            "subcategory":"Real Estate Agent",
            "type":"Services"
        }
    ],
    "sg:phone":"+1 561 445 8346",
    "sg:postcode":"33460",
    "sg:province":"FL",
    "wof:name":"Dennis Edie Rl Est Properties",
    "wof:placetype":"venue"
},
  "geometry": {"coordinates":[-80.061131,26.63607],"type":"Point"}
}