{
  "type": "Feature",
  "properties": {
    "addr:full":"7423 US Hwy 27 Sebring FL 33876",
    "addr:housenumber":"7423",
    "addr:postcode":"33876",
    "addr:street":"Us Hwy 27",
    "iso:country":"US",
    "sg:address":"7423 US Hwy 27",
    "sg:city":"Sebring",
    "sg:classifiers":[
        {
            "category":"Restaurant",
            "type":"Food & Drink"
        }
    ],
    "sg:phone":"+1 863 314 9919",
    "sg:postcode":"33876",
    "sg:province":"FL",
    "sg:tags":[
        "italian"
    ],
    "wof:name":"Tony's Italian Restaurant",
    "wof:placetype":"venue"
},
  "geometry": {"coordinates":[-81.41872600000001,27.436031],"type":"Point"}
}