{
  "type": "Feature",
  "properties": {
    "iso:country":"US",
    "sg:address":"803 North St",
    "sg:city":"Jacksonville",
    "sg:classifiers":[
        {
            "category":"Manufacturing",
            "subcategory":"Printing",
            "type":"Manufacturing & Wholesale Goods"
        }
    ],
    "sg:phone":"+1 904 722 0196",
    "sg:postcode":"32211",
    "sg:province":"FL",
    "sg:tags":[
        "screen"
    ],
    "sg:website":"www.greatatlantictshirt.com",
    "wof:name":"Great Atlantic Outfitters",
    "wof:placetype":"venue"
},
  "geometry": {"coordinates":[-81.594421,30.330686],"type":"Point"}
}