{
  "type": "Feature",
  "properties": {
    "addr:full":"8299 W Beaver St Jacksonville FL 32220",
    "addr:housenumber":"8299",
    "addr:postcode":"32220",
    "addr:street":"W Beaver St",
    "iso:country":"US",
    "sg:address":"8299 W Beaver St",
    "sg:city":"Jacksonville",
    "sg:classifiers":[
        {
            "category":"Retail",
            "subcategory":"Laundry & Dry Cleaning",
            "type":"Services"
        }
    ],
    "sg:phone":"+1 904 786 7440",
    "sg:postcode":"32220",
    "sg:province":"FL",
    "sg:tags":[
        "cleaners"
    ],
    "wof:name":"Jet Dry Cleaners",
    "wof:placetype":"venue"
},
  "geometry": {"coordinates":[-81.785853,30.322585],"type":"Point"}
}