{
  "type": "Feature",
  "properties": {
    "addr:full":"3218 Stonehurst Cir Kissimmee FL 34741",
    "addr:housenumber":"3218",
    "addr:postcode":"34741",
    "addr:street":"Stonehurst Cir",
    "iso:country":"US",
    "sg:address":"3218 Stonehurst Cir",
    "sg:city":"Kissimmee",
    "sg:classifiers":[
        {
            "category":"Restaurant",
            "type":"Food & Drink"
        }
    ],
    "sg:phone":"+1 407 846 2962",
    "sg:postcode":"34741",
    "sg:province":"FL",
    "sg:tags":[
        "eating"
    ],
    "wof:name":"John Schaefer Kitchen Consulta",
    "wof:placetype":"venue"
},
  "geometry": {"coordinates":[-81.44345300000001,28.345699],"type":"Point"}
}