{
  "type": "Feature",
  "properties": {
    "addr:full":"3361 Co Rd 220 Middleburg FL 32068",
    "addr:housenumber":"3361;220",
    "addr:postcode":"32068",
    "addr:street":"Co Rd",
    "iso:country":"US",
    "sg:address":"3361 Co Rd 220",
    "sg:city":"Middleburg",
    "sg:classifiers":[
        {
            "category":"Farming",
            "subcategory":"Livestock Farm",
            "type":"Manufacturing & Wholesale Goods"
        }
    ],
    "sg:phone":"+1 904 214 9119",
    "sg:postcode":"32068",
    "sg:province":"FL",
    "sg:tags":[
        "ranch"
    ],
    "wof:name":"North Florida Equine Ranch",
    "wof:placetype":"venue"
},
  "geometry": {"coordinates":[-81.827091,30.095971],"type":"Point"}
}