{
  "type": "Feature",
  "properties": {
    "addr:full":"1123 N Combee Rd Lakeland FL 33801",
    "addr:housenumber":"1123",
    "addr:postcode":"33801",
    "addr:street":"N Combee Rd",
    "iso:country":"US",
    "sg:address":"1123 N Combee Rd",
    "sg:city":"Lakeland",
    "sg:classifiers":[
        {
            "category":"Home & Garden",
            "subcategory":"Home Furnishings",
            "type":"Retail Goods"
        }
    ],
    "sg:phone":"+1 863 668 9325",
    "sg:postcode":"33801",
    "sg:province":"FL",
    "sg:tags":[
        "decorating",
        "chinaware",
        "instruction"
    ],
    "wof:name":"Porcelain Art",
    "wof:placetype":"venue"
},
  "geometry": {"coordinates":[-81.90795300000001,28.057374],"type":"Point"}
}