{
  "type": "Feature",
  "properties": {
    "addr:full":"1300 Pinehurst Dr Spring Hill FL 34606",
    "addr:housenumber":"1300",
    "addr:postcode":"34606",
    "addr:street":"Pinehurst Dr",
    "iso:country":"US",
    "sg:address":"1300 Pinehurst Dr",
    "sg:city":"Spring Hill",
    "sg:classifiers":[
        {
            "category":"Banks & Credit Unions",
            "subcategory":"Bank",
            "type":"Services"
        }
    ],
    "sg:phone":"+1 352 666 5200",
    "sg:postcode":"34606",
    "sg:province":"FL",
    "sg:tags":[
        "commercial"
    ],
    "sg:website":"www.1stkensington.com",
    "wof:name":"First Kensington Bank",
    "wof:placetype":"venue"
},
  "geometry": {"coordinates":[-82.625124,28.460805],"type":"Point"}
}