{
  "type": "Feature",
  "properties": {
    "iso:country":"US",
    "sg:address":"19800 Veterans Blvd",
    "sg:city":"Port Charlotte",
    "sg:classifiers":[
        {
            "category":"Building & Trades",
            "subcategory":"Plumbing",
            "type":"Services"
        }
    ],
    "sg:phone":"+1 941 629 2845",
    "sg:postcode":"33954",
    "sg:province":"FL",
    "sg:tags":[
        "conditioning",
        "air",
        "heating",
        "contractor"
    ],
    "wof:name":"Cardwells AC & Htg",
    "wof:placetype":"venue"
},
  "geometry": {"coordinates":[-82.053344,27.018165],"type":"Point"}
}