{
  "type": "Feature",
  "properties": {
    "addr:full":"9110 Ellis Rd Melbourne FL 32904",
    "addr:housenumber":"9110",
    "addr:postcode":"32904",
    "addr:street":"Ellis Rd",
    "iso:country":"US",
    "sg:address":"9110 Ellis Rd",
    "sg:city":"Melbourne",
    "sg:classifiers":[
        {
            "category":"Building & Trades",
            "subcategory":"Construction",
            "type":"Services"
        }
    ],
    "sg:phone":"+1 321 729 9064",
    "sg:postcode":"32904",
    "sg:province":"FL",
    "sg:tags":[
        "insulation",
        "heat",
        "contractor"
    ],
    "wof:name":"Pruett Insulation Inc",
    "wof:placetype":"venue"
},
  "geometry": {"coordinates":[-80.700187,28.099013],"type":"Point"}
}