{
  "type": "Feature",
  "properties": {
    "iso:country":"US",
    "sg:address":"535 Hialeah Dr",
    "sg:city":"Hialeah",
    "sg:classifiers":[
        {
            "category":"Restaurant",
            "type":"Food & Drink"
        }
    ],
    "sg:phone":"+1 305 888 6298",
    "sg:postcode":"33010",
    "sg:province":"FL",
    "wof:name":"Dunkin Donuts",
    "wof:placetype":"venue"
},
  "geometry": {"coordinates":[-80.27089700000001,25.823099],"type":"Point"}
}