{
  "type": "Feature",
  "properties": {
    "iso:country":"US",
    "sg:address":"940 12th St",
    "sg:city":"Vero Beach",
    "sg:classifiers":[
        {
            "category":"Professional",
            "subcategory":"Computer Services",
            "type":"Services"
        }
    ],
    "sg:phone":"+1 772 388 9387",
    "sg:postcode":"32960",
    "sg:province":"FL",
    "sg:tags":[
        "internet"
    ],
    "wof:name":"Comcast High Speed Internet",
    "wof:placetype":"venue"
},
  "geometry": {"coordinates":[-80.392335,27.623444],"type":"Point"}
}