{
  "type": "Feature",
  "properties": {
    "iso:country":"US",
    "sg:address":"250 Price Ct",
    "sg:city":"Satellite Beach",
    "sg:classifiers":[
        {
            "category":"Building & Trades",
            "subcategory":"Construction",
            "type":"Services"
        }
    ],
    "sg:phone":"+1 321 777 5678",
    "sg:postcode":"32937",
    "sg:province":"FL",
    "sg:tags":[
        "concrete",
        "contractor"
    ],
    "wof:name":"Acj Concrete Inc",
    "wof:placetype":"venue"
},
  "geometry": {"coordinates":[-80.59504099999999,28.179213],"type":"Point"}
}