{
  "type": "Feature",
  "properties": {
    "iso:country":"US",
    "sg:address":"102 Drennen Rd",
    "sg:city":"Orlando",
    "sg:classifiers":[
        {
            "category":"Building & Trades",
            "subcategory":"Construction",
            "type":"Services"
        }
    ],
    "sg:phone":"+1 407 816 5582",
    "sg:postcode":"32806",
    "sg:province":"FL",
    "sg:tags":[
        "residential",
        "contractor",
        "nonresidential"
    ],
    "wof:name":"Kevin Barnes Construction",
    "wof:placetype":"venue"
},
  "geometry": {"coordinates":[-81.37925,28.502994],"type":"Point"}
}