{
  "type": "Feature",
  "properties": {
    "iso:country":"US",
    "sg:address":"299 N Orlando Ave",
    "sg:city":"Cocoa Beach",
    "sg:classifiers":[
        {
            "category":"Health Services",
            "subcategory":"Chiropractor",
            "type":"Services"
        }
    ],
    "sg:phone":"+1 321 783 9400",
    "sg:postcode":"32931",
    "sg:province":"FL",
    "wof:name":"Sickel's Clinic of Chiropractic",
    "wof:placetype":"venue"
},
  "geometry": {"coordinates":[-80.6101,28.323601],"type":"Point"}
}