{
  "type": "Feature",
  "properties": {
    "iso:country":"US",
    "sg:address":"435 Citrus St",
    "sg:city":"Melbourne",
    "sg:classifiers":[
        {
            "category":"Building & Trades",
            "subcategory":"Construction",
            "type":"Services"
        }
    ],
    "sg:phone":"+1 321 757 5202",
    "sg:postcode":"32935",
    "sg:province":"FL",
    "sg:tags":[
        "carpentry",
        "contractor"
    ],
    "wof:name":"Jerrys Installation LLC",
    "wof:placetype":"venue"
},
  "geometry": {"coordinates":[-80.670462,28.136526],"type":"Point"}
}