{
  "type": "Feature",
  "properties": {
    "addr:full":"22 Pine Ash Ln Palm Coast FL 32164",
    "addr:housenumber":"22",
    "addr:postcode":"32164",
    "addr:street":"Pine Ash Ln",
    "iso:country":"US",
    "sg:address":"22 Pine Ash Ln",
    "sg:city":"Palm Coast",
    "sg:classifiers":[
        {
            "category":"Restaurant",
            "type":"Food & Drink"
        }
    ],
    "sg:phone":"+1 386 437 7661",
    "sg:postcode":"32164",
    "sg:province":"FL",
    "sg:tags":[
        "eating"
    ],
    "wof:name":"Cafe Latino",
    "wof:placetype":"venue"
},
  "geometry": {"coordinates":[-81.20569399999999,29.513398],"type":"Point"}
}