{
  "type": "Feature",
  "properties": {
    "iso:country":"US",
    "sg:address":"823 SW 8th Ave",
    "sg:city":"Miami",
    "sg:classifiers":[
        {
            "category":"Wholesale",
            "subcategory":"Motor Vehicles",
            "type":"Manufacturing & Wholesale Goods"
        }
    ],
    "sg:phone":"+1 305 856 2379",
    "sg:postcode":"33130",
    "sg:province":"FL",
    "sg:tags":[
        "automobile",
        "truck",
        "broker"
    ],
    "wof:name":"C A Mega Trucking",
    "wof:placetype":"venue"
},
  "geometry": {"coordinates":[-80.20733,25.765249],"type":"Point"}
}