{
  "type": "Feature",
  "properties": {
    "iso:country":"US",
    "sg:address":"87 N Clarke Rd",
    "sg:city":"Ocoee",
    "sg:classifiers":[
        {
            "category":"Education",
            "subcategory":"School",
            "type":"Public Place"
        }
    ],
    "sg:phone":"+1 407 445 5475",
    "sg:postcode":"34761",
    "sg:province":"FL",
    "sg:tags":[
        "elementary"
    ],
    "sg:website":"http://www.ocps.k12.fl.us",
    "wof:name":"Citrus Elementary School",
    "wof:placetype":"venue"
},
  "geometry": {"coordinates":[-81.517319,28.571053],"type":"Point"}
}