{
  "type": "Feature",
  "properties": {
    "addr:full":"1100 W Oakland Park Blvd Wilton Manors FL 33311",
    "addr:housenumber":"1100",
    "addr:postcode":"33311",
    "addr:street":"W Oakland Park Blvd",
    "iso:country":"US",
    "sg:address":"1100 W Oakland Park Blvd",
    "sg:city":"Wilton Manors",
    "sg:classifiers":[
        {
            "category":"Retail",
            "subcategory":"Auto Rental",
            "type":"Services"
        }
    ],
    "sg:phone":"+1 954 390 0222",
    "sg:postcode":"33311",
    "sg:province":"FL",
    "sg:tags":[
        "renting",
        "automobile"
    ],
    "wof:name":"Enterprise Rent-A-Car",
    "wof:placetype":"venue"
},
  "geometry": {"coordinates":[-80.15696199999999,26.166119],"type":"Point"}
}