{
  "type": "Feature",
  "properties": {
    "addr:full":"302 Rachelle Ave Sanford FL 32771",
    "addr:housenumber":"302",
    "addr:postcode":"32771",
    "addr:street":"Rachelle Ave",
    "iso:country":"US",
    "sg:address":"302 Rachelle Ave",
    "sg:city":"Sanford",
    "sg:classifiers":[
        {
            "category":"Shopping",
            "subcategory":"Gifts & Souvenirs",
            "type":"Retail Goods"
        }
    ],
    "sg:phone":"+1 407 324 9983",
    "sg:postcode":"32771",
    "sg:province":"FL",
    "wof:name":"Common Scents",
    "wof:placetype":"venue"
},
  "geometry": {"coordinates":[-81.29036000000001,28.816449],"type":"Point"}
}