{
  "type": "Feature",
  "properties": {
    "iso:country":"US",
    "sg:address":"1799 N State Road 7",
    "sg:city":"Margate",
    "sg:classifiers":[
        {
            "category":"Professional",
            "subcategory":"Accounting & Tax Preparation",
            "type":"Services"
        }
    ],
    "sg:phone":"+1 954 972 3776",
    "sg:postcode":"33063",
    "sg:province":"FL",
    "sg:tags":[
        "bookkeeping",
        "return",
        "preparation-business",
        "billing"
    ],
    "wof:name":"Babio J & Associates",
    "wof:placetype":"venue"
},
  "geometry": {"coordinates":[-80.201538,26.249954],"type":"Point"}
}