{
  "type": "Feature",
  "properties": {
    "iso:country":"US",
    "sg:address":"1134 State Ave",
    "sg:city":"Daytona Beach",
    "sg:classifiers":[
        {
            "category":"Wholesale",
            "subcategory":"Construction Materials",
            "type":"Manufacturing & Wholesale Goods"
        },
        {
            "category":"Manufacturing",
            "subcategory":"Glass & Minerals",
            "type":"Manufacturing & Wholesale Goods"
        }
    ],
    "sg:phone":"+1 386 238 4430",
    "sg:postcode":"32117",
    "sg:province":"FL",
    "sg:tags":[
        "concrete",
        "product",
        "marble",
        "mfg"
    ],
    "wof:name":"Daytona Marble",
    "wof:placetype":"venue"
},
  "geometry": {"coordinates":[-81.04451299999999,29.24797],"type":"Point"}
}