{
  "type": "Feature",
  "properties": {
    "iso:country":"US",
    "sg:address":"314 N Duss St",
    "sg:city":"New Smyrna Beach",
    "sg:classifiers":[
        {
            "category":"Recreation",
            "type":"Entertainment"
        }
    ],
    "sg:phone":"+1 386 478 1934",
    "sg:postcode":"32168",
    "sg:province":"FL",
    "sg:tags":[
        "carnival"
    ],
    "wof:name":"Black Heritage Festival Inc",
    "wof:placetype":"venue"
},
  "geometry": {"coordinates":[-80.932908,29.024761],"type":"Point"}
}