{
  "type": "Feature",
  "properties": {
    "iso:country":"US",
    "sg:address":"2530 N Washington Blvd",
    "sg:city":"Sarasota",
    "sg:classifiers":[
        {
            "category":"Autos & Motor Vehicles",
            "subcategory":"Fuel & Gas Station",
            "type":"Retail Goods"
        }
    ],
    "sg:phone":"+1 941 330 9188",
    "sg:postcode":"34234",
    "sg:province":"FL",
    "sg:tags":[
        "station",
        "gasoline"
    ],
    "wof:name":"New Town Snappy",
    "wof:placetype":"venue"
},
  "geometry": {"coordinates":[-82.53043,27.359085],"type":"Point"}
}