{
  "type": "Feature",
  "properties": {
    "addr:full":"2838 Hollywood Blvd Hollywood FL 33020",
    "addr:housenumber":"2838",
    "addr:postcode":"33020",
    "addr:street":"Hollywood Blvd",
    "iso:country":"US",
    "sg:address":"2838 Hollywood Blvd",
    "sg:city":"Hollywood",
    "sg:classifiers":[
        {
            "category":"Retail",
            "subcategory":"Veterinary Services",
            "type":"Services"
        }
    ],
    "sg:phone":"+1 954 923 9840",
    "sg:postcode":"33020",
    "sg:province":"FL",
    "sg:tags":[
        "clinic",
        "hospital",
        "specialty"
    ],
    "wof:name":"All-State Technical Svc",
    "wof:placetype":"venue"
},
  "geometry": {"coordinates":[-80.16378,26.01092],"type":"Point"}
}