{
  "type": "Feature",
  "properties": {
    "addr:full":"204 N Texas Ave Tavares FL 32778",
    "addr:housenumber":"204",
    "addr:postcode":"32778",
    "addr:street":"N Texas Ave",
    "iso:country":"US",
    "sg:address":"204 N Texas Ave",
    "sg:city":"Tavares",
    "sg:classifiers":[
        {
            "category":"Organizations",
            "subcategory":"Non-profit Organization",
            "type":"Services"
        }
    ],
    "sg:phone":"+1 352 343 3200",
    "sg:postcode":"32778",
    "sg:province":"FL",
    "sg:tags":[
        "social"
    ],
    "wof:name":"Comprehensive Addictions",
    "wof:placetype":"venue"
},
  "geometry": {"coordinates":[-81.730071,28.804114],"type":"Point"}
}