{
  "type": "Feature",
  "properties": {
    "addr:full":"1428 SE 33rd St Cape Coral FL 33904",
    "addr:housenumber":"1428",
    "addr:postcode":"33904",
    "addr:street":"Se 33Rd St",
    "iso:country":"US",
    "sg:address":"1428 SE 33rd St",
    "sg:city":"Cape Coral",
    "sg:classifiers":[
        {
            "category":"Building & Trades",
            "subcategory":"Cleaning & Sanitation",
            "type":"Services"
        }
    ],
    "sg:phone":"+1 239 945 8464",
    "sg:postcode":"33904",
    "sg:province":"FL",
    "sg:tags":[
        "janitor"
    ],
    "wof:name":"Absolute Professional Cleaning",
    "wof:placetype":"venue"
},
  "geometry": {"coordinates":[-81.943291,26.590927],"type":"Point"}
}