{
  "type": "Feature",
  "properties": {
    "addr:full":"3927 Crawfordville Rd Tallahassee FL 32305",
    "addr:housenumber":"3927",
    "addr:postcode":"32305",
    "addr:street":"Crawfordville Rd",
    "iso:country":"US",
    "sg:address":"3927 Crawfordville Rd",
    "sg:city":"Tallahassee",
    "sg:classifiers":[
        {
            "category":"Manufacturing",
            "subcategory":"Printing",
            "type":"Manufacturing & Wholesale Goods"
        }
    ],
    "sg:phone":"+1 850 656 7627",
    "sg:postcode":"32305",
    "sg:province":"FL",
    "sg:tags":[
        "newspaper"
    ],
    "wof:name":"Leon County News",
    "wof:placetype":"venue"
},
  "geometry": {"coordinates":[-84.28242299999999,30.395969],"type":"Point"}
}