{
  "type": "Feature",
  "properties": {
    "iso:country":"US",
    "sg:address":"351 W Avery St",
    "sg:city":"Pensacola",
    "sg:classifiers":[
        {
            "category":"Restaurant",
            "type":"Food & Drink"
        }
    ],
    "sg:phone":"+1 850 438 3806",
    "sg:postcode":"32501",
    "sg:province":"FL",
    "sg:tags":[
        "eating"
    ],
    "wof:name":"A Gourmet Occasion",
    "wof:placetype":"venue"
},
  "geometry": {"coordinates":[-87.224047,30.42993],"type":"Point"}
}