{
  "type": "Feature",
  "properties": {
    "iso:country":"US",
    "sg:address":"2501 Oleander Blvd",
    "sg:city":"Fort Pierce",
    "sg:classifiers":[
        {
            "category":"Retail",
            "subcategory":"Repair Shop",
            "type":"Services"
        },
        {
            "category":"Home & Garden",
            "subcategory":"Household Appliances",
            "type":"Retail Goods"
        }
    ],
    "sg:phone":"+1 772 467 2032",
    "sg:postcode":"34982",
    "sg:province":"FL",
    "sg:tags":[
        "machine",
        "sewing"
    ],
    "wof:name":"Terry's Sewing Machine Repair",
    "wof:placetype":"venue"
},
  "geometry": {"coordinates":[-80.33201,27.42346],"type":"Point"}
}