{
  "type": "Feature",
  "properties": {
    "iso:country":"US",
    "sg:address":"1314 N East Ave",
    "sg:city":"Sarasota",
    "sg:classifiers":[
        {
            "category":"Manufacturing",
            "subcategory":"Signs",
            "type":"Manufacturing & Wholesale Goods"
        }
    ],
    "sg:phone":"+1 941 364 9457",
    "sg:postcode":"34237",
    "sg:province":"FL",
    "wof:name":"Artistic Neon Sign Co",
    "wof:placetype":"venue"
},
  "geometry": {"coordinates":[-82.528267,27.350335],"type":"Point"}
}