{
  "type": "Feature",
  "properties": {
    "iso:country":"US",
    "sg:address":"836 NE 76th St",
    "sg:city":"Boca Raton",
    "sg:classifiers":[
        {
            "category":"Professional",
            "subcategory":"Management & Consulting",
            "type":"Services"
        }
    ],
    "sg:phone":"+1 561 997 8656",
    "sg:postcode":"33487",
    "sg:province":"FL",
    "sg:tags":[
        "business"
    ],
    "wof:name":"Sandlers Consulting Corp",
    "wof:placetype":"venue"
},
  "geometry": {"coordinates":[-80.070268,26.417201],"type":"Point"}
}