{
  "type": "Feature",
  "properties": {
    "addr:full":"3615 Thomasson Dr Naples FL 34112",
    "addr:housenumber":"3615",
    "addr:postcode":"34112",
    "addr:street":"Thomasson Dr",
    "iso:country":"US",
    "sg:address":"3615 Thomasson Dr",
    "sg:city":"Naples",
    "sg:classifiers":[
        {
            "category":"Retail",
            "subcategory":"Laundry & Dry Cleaning",
            "type":"Services"
        }
    ],
    "sg:phone":"+1 239 417 0511",
    "sg:postcode":"34112",
    "sg:province":"FL",
    "sg:tags":[
        "cleaners",
        "rug",
        "carpet"
    ],
    "wof:name":"Dial's Carpet & Upholstery",
    "wof:placetype":"venue"
},
  "geometry": {"coordinates":[-81.761101,26.109237],"type":"Point"}
}