{
  "type": "Feature",
  "properties": {
    "iso:country":"US",
    "sg:address":"3709 72nd Ter E",
    "sg:city":"Sarasota",
    "sg:classifiers":[
        {
            "category":"Internet Cafe",
            "subcategory":"None",
            "type":"Food & Drink"
        }
    ],
    "sg:phone":"+1 941 360 0233",
    "sg:postcode":"34243",
    "sg:province":"FL",
    "sg:tags":[
        "directory",
        "product"
    ],
    "wof:name":"Cpufix.Com",
    "wof:placetype":"venue"
},
  "geometry": {"coordinates":[-82.51531799999999,27.411189],"type":"Point"}
}