{
  "type": "Feature",
  "properties": {
    "iso:country":"US",
    "sg:address":"1092 US Hwy 17",
    "sg:city":"Palatka",
    "sg:classifiers":[
        {
            "category":"Shopping",
            "subcategory":"Computers & Home Electronics",
            "type":"Retail Goods"
        }
    ],
    "sg:phone":"+1 386 328 5422",
    "sg:postcode":"32177",
    "sg:province":"FL",
    "sg:tags":[
        "equipment",
        "electronic",
        "supply"
    ],
    "wof:name":"D C Electronics",
    "wof:placetype":"venue"
},
  "geometry": {"coordinates":[-81.638779,29.648822],"type":"Point"}
}