{
  "type": "Feature",
  "properties": {
    "addr:full":"1584 Owl Hollow Ln Jacksonville FL 32223",
    "addr:housenumber":"1584",
    "addr:postcode":"32223",
    "addr:street":"Owl Hollow Ln",
    "iso:country":"US",
    "sg:address":"1584 Owl Hollow Ln",
    "sg:city":"Jacksonville",
    "sg:classifiers":[
        {
            "category":"Professional",
            "subcategory":"Management & Consulting",
            "type":"Services"
        }
    ],
    "sg:phone":"+1 904 262 5666",
    "sg:postcode":"32223",
    "sg:province":"FL",
    "sg:tags":[
        "consultant"
    ],
    "wof:name":"Bill David & Associates Inc",
    "wof:placetype":"venue"
},
  "geometry": {"coordinates":[-81.66928900000001,30.142466],"type":"Point"}
}