{
  "type": "Feature",
  "properties": {
    "iso:country":"US",
    "sg:address":"800 Virginia Ave",
    "sg:city":"Fort Pierce",
    "sg:classifiers":[
        {
            "category":"Shopping",
            "subcategory":"Bicycles & Sporting Goods",
            "type":"Retail Goods"
        }
    ],
    "sg:phone":"+1 772 465 1162",
    "sg:postcode":"34982",
    "sg:province":"FL",
    "sg:tags":[
        "skating",
        "equipment",
        "supply"
    ],
    "wof:name":"Skate Sales Intl",
    "wof:placetype":"venue"
},
  "geometry": {"coordinates":[-80.330968,27.425468],"type":"Point"}
}