{
  "type": "Feature",
  "properties": {
    "addr:full":"4953 Windward Pl Fernandina Beach FL 32034",
    "addr:housenumber":"4953",
    "addr:postcode":"32034",
    "addr:street":"Windward Pl",
    "iso:country":"US",
    "sg:address":"4953 Windward Pl",
    "sg:city":"Fernandina Beach",
    "sg:classifiers":[
        {
            "category":"Wholesale",
            "subcategory":"Durable Goods & Equipment",
            "type":"Manufacturing & Wholesale Goods"
        }
    ],
    "sg:phone":"+1 904 277 3630",
    "sg:postcode":"32034",
    "sg:province":"FL",
    "wof:name":"Langford Antiques",
    "wof:placetype":"venue"
},
  "geometry": {"coordinates":[-81.453457,30.586579],"type":"Point"}
}