{
  "type": "Feature",
  "properties": {
    "addr:full":"821 NE Patterson Ave Lake City FL 32055",
    "addr:housenumber":"821",
    "addr:postcode":"32055",
    "addr:street":"Ne Patterson Ave",
    "iso:country":"US",
    "sg:address":"821 NE Patterson Ave",
    "sg:city":"Lake City",
    "sg:classifiers":[
        {
            "category":"Organizations",
            "subcategory":"Religious Organization",
            "type":"Services"
        }
    ],
    "sg:phone":"+1 386 752 5710",
    "sg:postcode":"32055",
    "sg:province":"FL",
    "wof:name":"Church of True Believers",
    "wof:placetype":"venue"
},
  "geometry": {"coordinates":[-82.625604,30.195018],"type":"Point"}
}