{
  "type": "Feature",
  "properties": {
    "iso:country":"US",
    "sg:address":"223 S Main St",
    "sg:city":"Gainesville",
    "sg:classifiers":[
        {
            "category":"Bakery",
            "type":"Food & Drink"
        }
    ],
    "sg:menulink":"http://www.allmenus.com/fl/gainesville/62972-metropolitan-bagel-bakery/menu/",
    "sg:phone":"+1 352 381 9494",
    "sg:postcode":"32601",
    "sg:province":"FL",
    "sg:tags":[
        "american",
        "pastry"
    ],
    "wof:name":"Metropolitan Bagel Bakery",
    "wof:placetype":"venue"
},
  "geometry": {"coordinates":[-82.32486,29.648947],"type":"Point"}
}