{
  "type": "Feature",
  "properties": {
    "addr:full":"1009 Bond Ave Jacksonville FL 32206",
    "addr:housenumber":"1009",
    "addr:postcode":"32206",
    "addr:street":"Bond Ave",
    "iso:country":"US",
    "sg:address":"1009 Bond Ave",
    "sg:city":"Jacksonville",
    "sg:classifiers":[
        {
            "category":"Building & Trades",
            "subcategory":"Plumbing",
            "type":"Services"
        }
    ],
    "sg:phone":"+1 850 575 2088",
    "sg:postcode":"32206",
    "sg:province":"FL",
    "sg:tags":[
        "contractor"
    ],
    "wof:name":"Howard Services Heating and A",
    "wof:placetype":"venue"
},
  "geometry": {"coordinates":[-81.628438,30.333082],"type":"Point"}
}