{
  "type": "Feature",
  "properties": {
    "addr:full":"2156 NW 61st St Miami FL 33142",
    "addr:housenumber":"2156",
    "addr:postcode":"33142",
    "addr:street":"Nw 61St St",
    "iso:country":"US",
    "sg:address":"2156 NW 61st St",
    "sg:city":"Miami",
    "sg:classifiers":[
        {
            "category":"Personal",
            "subcategory":"Barber",
            "type":"Services"
        }
    ],
    "sg:phone":"+1 305 633 1300",
    "sg:postcode":"33142",
    "sg:province":"FL",
    "wof:name":"Marco Barber Shop",
    "wof:placetype":"venue"
},
  "geometry": {"coordinates":[-80.232049,25.830586],"type":"Point"}
}