{
  "type": "Feature",
  "properties": {
    "iso:country":"US",
    "sg:address":"1770 Loon Ct",
    "sg:city":"Middleburg",
    "sg:classifiers":[
        {
            "category":"Personal",
            "type":"Services"
        }
    ],
    "sg:phone":"+1 904 214 9617",
    "sg:postcode":"32068",
    "sg:province":"FL",
    "sg:tags":[
        "credit",
        "debt",
        "counseling"
    ],
    "wof:name":"Guardian Debt Svc",
    "wof:placetype":"venue"
},
  "geometry": {"coordinates":[-81.942695,30.091357],"type":"Point"}
}