{
  "type": "Feature",
  "properties": {
    "addr:full":"1527 Old Dixie Hwy Jupiter FL 33469",
    "addr:housenumber":"1527",
    "addr:postcode":"33469",
    "addr:street":"Old Dixie Hwy",
    "iso:country":"US",
    "sg:address":"1527 Old Dixie Hwy",
    "sg:city":"Jupiter",
    "sg:classifiers":[
        {
            "category":"Shopping",
            "subcategory":"Used Merchandise",
            "type":"Retail Goods"
        }
    ],
    "sg:phone":"+1 561 747 2770",
    "sg:postcode":"33469",
    "sg:province":"FL",
    "sg:tags":[
        "shop",
        "consignment"
    ],
    "wof:name":"Island Interiors Consignments",
    "wof:placetype":"venue"
},
  "geometry": {"coordinates":[-80.093701,26.970438],"type":"Point"}
}