{
  "type": "Feature",
  "properties": {
    "iso:country":"US",
    "sg:address":"232 SE 1st St",
    "sg:city":"Gainesville",
    "sg:classifiers":[
        {
            "category":"Cafe",
            "type":"Food & Drink"
        }
    ],
    "sg:menulink":"http://www.allmenus.com/fl/gainesville/260738-thai-fusion-cafe/menu/",
    "sg:phone":"+1 352 373 3004",
    "sg:postcode":"32601",
    "sg:province":"FL",
    "sg:tags":[
        "thai",
        "asian"
    ],
    "wof:name":"Thai Fusion Cafe",
    "wof:placetype":"venue"
},
  "geometry": {"coordinates":[-82.324084,29.650058],"type":"Point"}
}