{
  "type": "Feature",
  "properties": {
    "iso:country":"US",
    "sg:address":"2720 E Atlantic Blvd",
    "sg:city":"Pompano Beach",
    "sg:classifiers":[
        {
            "category":"Real Estate",
            "subcategory":"Real Estate Agent",
            "type":"Services"
        }
    ],
    "sg:phone":"+1 954 782 9562",
    "sg:postcode":"33062",
    "sg:province":"FL",
    "sg:tags":[
        "management"
    ],
    "wof:name":"Atlantic Square Properties",
    "wof:placetype":"venue"
},
  "geometry": {"coordinates":[-80.095195,26.231829],"type":"Point"}
}