{
  "type": "Feature",
  "properties": {
    "iso:country":"US",
    "sg:address":"7001 Lake Ellenor Dr",
    "sg:city":"Orlando",
    "sg:classifiers":[
        {
            "category":"Organizations",
            "subcategory":"Labor Organization",
            "type":"Services"
        }
    ],
    "sg:phone":"+1 407 856 5828",
    "sg:postcode":"32809",
    "sg:province":"FL",
    "wof:name":"Seiu Local 8",
    "wof:placetype":"venue"
},
  "geometry": {"coordinates":[-81.401099,28.463918],"type":"Point"}
}