{
  "type": "Feature",
  "properties": {
    "iso:country":"US",
    "sg:address":"1908 Chestnut Ave",
    "sg:city":"Panama City",
    "sg:classifiers":[
        {
            "category":"Arts & Performance",
            "subcategory":"Theater",
            "type":"Entertainment"
        }
    ],
    "sg:phone":"+1 850 747 0915",
    "sg:postcode":"32405",
    "sg:province":"FL",
    "sg:tags":[
        "karaoke"
    ],
    "wof:name":"Music Makers",
    "wof:placetype":"venue"
},
  "geometry": {"coordinates":[-85.70027,30.184789],"type":"Point"}
}