{
  "type": "Feature",
  "properties": {
    "iso:country":"US",
    "sg:address":"213 N Federal Hwy",
    "sg:city":"Hallandale Beach",
    "sg:classifiers":[
        {
            "category":"Health Services",
            "subcategory":"Clinic",
            "type":"Services"
        }
    ],
    "sg:phone":"+1 954 454 8800",
    "sg:postcode":"33009",
    "sg:province":"FL",
    "sg:tags":[
        "medical",
        "emergency",
        "minor"
    ],
    "wof:name":"E R Urgent Care Ctr",
    "wof:placetype":"venue"
},
  "geometry": {"coordinates":[-80.142448,25.988137],"type":"Point"}
}