{
  "type": "Feature",
  "properties": {
    "iso:country":"US",
    "sg:address":"8740 N Kendall Dr",
    "sg:city":"Miami",
    "sg:classifiers":[
        {
            "category":"Health Services",
            "subcategory":"Dentist",
            "type":"Services"
        }
    ],
    "sg:phone":"+1 305 274 3113",
    "sg:postcode":"33176",
    "sg:province":"FL",
    "sg:tags":[
        "orthodontist"
    ],
    "sg:website":"www.4braces.com",
    "wof:name":"Orthodontic Specialists of South Florida DDS",
    "wof:placetype":"venue"
},
  "geometry": {"coordinates":[-80.33440299999999,25.687783],"type":"Point"}
}