{
  "type": "Feature",
  "properties": {
    "addr:full":"1801 SE 10th Ave Fort Lauderdale FL 33316",
    "addr:housenumber":"1801",
    "addr:postcode":"33316",
    "addr:street":"Se 10Th Ave",
    "iso:country":"US",
    "sg:address":"1801 SE 10th Ave",
    "sg:city":"Fort Lauderdale",
    "sg:classifiers":[
        {
            "category":"Restaurant",
            "type":"Food & Drink"
        }
    ],
    "sg:menulink":"http://www.allmenus.com/fl/fort-lauderdale/39766-outback-steakhouse/menu/",
    "sg:phone":"+1 954 523 5600",
    "sg:postcode":"33316",
    "sg:province":"FL",
    "sg:tags":[
        "american",
        "steakhouse"
    ],
    "wof:name":"Outback Steakhouse",
    "wof:placetype":"venue"
},
  "geometry": {"coordinates":[-80.13267500000001,26.099243],"type":"Point"}
}