{
  "type": "Feature",
  "properties": {
    "iso:country":"US",
    "sg:address":"2500 E Busch Blvd",
    "sg:city":"Tampa",
    "sg:classifiers":[
        {
            "category":"Shopping",
            "subcategory":"Clothing, Apparel, & Fashions",
            "type":"Retail Goods"
        }
    ],
    "sg:phone":"+1 813 984 7166",
    "sg:postcode":"33612",
    "sg:province":"FL",
    "wof:name":"Alico Fashions",
    "wof:placetype":"venue"
},
  "geometry": {"coordinates":[-82.433251,28.032633],"type":"Point"}
}