{
  "type": "Feature",
  "properties": {
    "addr:full":"35 E Prospect Rd Fort Lauderdale FL 33334",
    "addr:housenumber":"35",
    "addr:postcode":"33334",
    "addr:street":"E Prospect Rd",
    "iso:country":"US",
    "sg:address":"35 E Prospect Rd",
    "sg:city":"Fort Lauderdale",
    "sg:classifiers":[
        {
            "category":"Personal",
            "subcategory":"Beauty Salon",
            "type":"Services"
        }
    ],
    "sg:phone":"+1 954 928 0766",
    "sg:postcode":"33334",
    "sg:province":"FL",
    "sg:tags":[
        "shop",
        "metal",
        "center"
    ],
    "wof:name":"Garden Nail Salon",
    "wof:placetype":"venue"
},
  "geometry": {"coordinates":[-80.14521000000001,26.181414],"type":"Point"}
}