{
  "type": "Feature",
  "properties": {
    "addr:full":"245 NW 25th St Miami FL 33127",
    "addr:housenumber":"245",
    "addr:postcode":"33127",
    "addr:street":"Nw 25Th St",
    "iso:country":"US",
    "sg:address":"245 NW 25th St",
    "sg:city":"Miami",
    "sg:classifiers":[
        {
            "category":"Wholesale",
            "subcategory":"Groceries",
            "type":"Manufacturing & Wholesale Goods"
        }
    ],
    "sg:phone":"+1 305 571 8690",
    "sg:postcode":"33127",
    "sg:province":"FL",
    "sg:tags":[
        "frozen",
        "food"
    ],
    "wof:name":"RLL Trading",
    "wof:placetype":"venue"
},
  "geometry": {"coordinates":[-80.200289,25.800778],"type":"Point"}
}