{
  "type": "Feature",
  "properties": {
    "iso:country":"US",
    "sg:address":"1106 S Scott Ave",
    "sg:city":"Sanford",
    "sg:classifiers":[
        {
            "category":"Building & Trades",
            "subcategory":"Construction",
            "type":"Services"
        }
    ],
    "sg:phone":"+1 407 323 9715",
    "sg:postcode":"32771",
    "sg:province":"FL",
    "sg:tags":[
        "house"
    ],
    "wof:name":"Miller Construction Services L",
    "wof:placetype":"venue"
},
  "geometry": {"coordinates":[-81.251361,28.803856],"type":"Point"}
}