{
  "type": "Feature",
  "properties": {
    "iso:country":"US",
    "sg:address":"13717 E Citrus Dr",
    "sg:city":"Loxahatchee",
    "sg:classifiers":[
        {
            "category":"Manufacturing",
            "subcategory":"Glass & Minerals",
            "type":"Manufacturing & Wholesale Goods"
        }
    ],
    "sg:phone":"+1 561 791 2461",
    "sg:postcode":"33470",
    "sg:province":"FL",
    "sg:tags":[
        "cut",
        "mfg"
    ],
    "wof:name":"B & B Marble Inc",
    "wof:placetype":"venue"
},
  "geometry": {"coordinates":[-80.258776,26.683989],"type":"Point"}
}