{
  "type": "Feature",
  "properties": {
    "iso:country":"US",
    "sg:address":"14 Marina Ter",
    "sg:city":"Saint Petersburg",
    "sg:classifiers":[
        {
            "category":"Professional",
            "subcategory":"Business Services",
            "type":"Services"
        }
    ],
    "sg:phone":"+1 727 367 3653",
    "sg:postcode":"33706",
    "sg:province":"FL",
    "wof:name":"Bentley Group Enterprises Inc",
    "wof:placetype":"venue"
},
  "geometry": {"coordinates":[-82.76007799999999,27.762438],"type":"Point"}
}