{
  "type": "Feature",
  "properties": {
    "iso:country":"US",
    "sg:address":"8338 US Hwy 19",
    "sg:city":"Port Richey",
    "sg:classifiers":[
        {
            "category":"Autos & Motor Vehicles",
            "subcategory":"Auto Supplies",
            "type":"Retail Goods"
        }
    ],
    "sg:phone":"+1 727 841 9100",
    "sg:postcode":"34668",
    "sg:province":"FL",
    "sg:tags":[
        "truck",
        "accessory"
    ],
    "wof:name":"West Coast Truck Accessories",
    "wof:placetype":"venue"
},
  "geometry": {"coordinates":[-82.717915,28.279496],"type":"Point"}
}