{
  "type": "Feature",
  "properties": {
    "addr:full":"15025 Peach Orchard Rd Brooksville FL 34614",
    "addr:housenumber":"15025",
    "addr:postcode":"34614",
    "addr:street":"Peach Orchard Rd",
    "iso:country":"US",
    "sg:address":"15025 Peach Orchard Rd",
    "sg:city":"Brooksville",
    "sg:classifiers":[
        {
            "category":"Wholesale",
            "subcategory":"Scrap",
            "type":"Manufacturing & Wholesale Goods"
        }
    ],
    "sg:phone":"+1 352 799 1982",
    "sg:postcode":"34614",
    "sg:province":"FL",
    "sg:tags":[
        "automobile",
        "rebuilt",
        "part",
        "supplies-used",
        "material"
    ],
    "wof:name":"T T Auto Wrecking Salvage",
    "wof:placetype":"venue"
},
  "geometry": {"coordinates":[-82.48302700000001,28.592084],"type":"Point"}
}