{
  "type": "Feature",
  "properties": {
    "addr:full":"3812 Skyline Blvd Cape Coral FL 33914",
    "addr:housenumber":"3812",
    "addr:postcode":"33914",
    "addr:street":"Skyline Blvd",
    "iso:country":"US",
    "sg:address":"3812 Skyline Blvd",
    "sg:city":"Cape Coral",
    "sg:classifiers":[
        {
            "category":"Personal",
            "subcategory":"Beauty Salon",
            "type":"Services"
        }
    ],
    "sg:phone":"+1 239 549 1139",
    "sg:postcode":"33914",
    "sg:province":"FL",
    "wof:name":"Hair FX Studio & Full Svc Sln",
    "wof:placetype":"venue"
},
  "geometry": {"coordinates":[-81.99099099999999,26.581433],"type":"Point"}
}