{
  "type": "Feature",
  "properties": {
    "iso:country":"US",
    "sg:address":"321 W Holly Dr",
    "sg:city":"Orange City",
    "sg:classifiers":[
        {
            "category":"Retail",
            "subcategory":"Laundry & Dry Cleaning",
            "type":"Services"
        }
    ],
    "sg:phone":"+1 386 774 9007",
    "sg:postcode":"32763",
    "sg:province":"FL",
    "wof:name":"Genesis Carpet Cleaning",
    "wof:placetype":"venue"
},
  "geometry": {"coordinates":[-81.305504,28.927345],"type":"Point"}
}