{
  "type": "Feature",
  "properties": {
    "iso:country":"US",
    "sg:address":"12000 4th St N",
    "sg:city":"St Petersburg",
    "sg:classifiers":[
        {
            "category":"Retail",
            "subcategory":"Portrait Studio",
            "type":"Services"
        }
    ],
    "sg:phone":"+1 727 578 0564",
    "sg:postcode":"33716",
    "sg:province":"FL",
    "sg:tags":[
        "photographer"
    ],
    "wof:name":"Good Memories",
    "wof:placetype":"venue"
},
  "geometry": {"coordinates":[-82.638802,27.877519],"type":"Point"}
}