{
  "type": "Feature",
  "properties": {
    "addr:full":"2317 Rochelle Ave Kissimmee FL 34746",
    "addr:housenumber":"2317",
    "addr:postcode":"34746",
    "addr:street":"Rochelle Ave",
    "iso:country":"US",
    "sg:address":"2317 Rochelle Ave",
    "sg:city":"Kissimmee",
    "sg:classifiers":[
        {
            "category":"Shopping",
            "subcategory":"Shoes",
            "type":"Retail Goods"
        }
    ],
    "sg:phone":"+1 407 397 7430",
    "sg:postcode":"34746",
    "sg:province":"FL",
    "wof:name":"A&M Footwear Outlet Inc",
    "wof:placetype":"venue"
},
  "geometry": {"coordinates":[-81.483636,28.315801],"type":"Point"}
}