{
  "type": "Feature",
  "properties": {
    "iso:country":"US",
    "sg:address":"8283 US Hwy 1",
    "sg:city":"Port St Lucie",
    "sg:classifiers":[
        {
            "category":"Professional",
            "type":"Services"
        }
    ],
    "sg:phone":"+1 772 340 7777",
    "sg:postcode":"34982",
    "sg:province":"FL",
    "sg:tags":[
        "establishment"
    ],
    "wof:name":"Rebar",
    "wof:placetype":"venue"
},
  "geometry": {"coordinates":[-80.314368,27.31577],"type":"Point"}
}