{
  "type": "Feature",
  "properties": {
    "addr:full":"560 NW 27th St Miami FL 33127",
    "addr:housenumber":"560",
    "addr:postcode":"33127",
    "addr:street":"Nw 27Th St",
    "iso:country":"US",
    "sg:address":"560 NW 27th St",
    "sg:city":"Miami",
    "sg:classifiers":[
        {
            "category":"Personal",
            "subcategory":"Beauty Salon",
            "type":"Services"
        }
    ],
    "sg:phone":"+1 305 576 3525",
    "sg:postcode":"33127",
    "sg:province":"FL",
    "sg:tags":[
        "wig",
        "hair",
        "piece"
    ],
    "wof:name":"Human Hair Supplies",
    "wof:placetype":"venue"
},
  "geometry": {"coordinates":[-80.20445100000001,25.801797],"type":"Point"}
}