{
  "type": "Feature",
  "properties": {
    "iso:country":"US",
    "sg:address":"2117 Arcadia Rd",
    "sg:city":"Holiday",
    "sg:classifiers":[
        {
            "category":"Professional",
            "subcategory":"Detective & Security Services",
            "type":"Services"
        }
    ],
    "sg:phone":"+1 727 376 8746",
    "sg:postcode":"34690",
    "sg:province":"FL",
    "sg:tags":[
        "information",
        "bureau"
    ],
    "wof:name":"Mike Chubres Tree Service",
    "wof:placetype":"venue"
},
  "geometry": {"coordinates":[-82.73168800000001,28.190157],"type":"Point"}
}