{
  "type": "Feature",
  "properties": {
    "iso:country":"US",
    "sg:address":"10955 SW 15th St",
    "sg:city":"Hollywood",
    "sg:classifiers":[
        {
            "category":"Wholesale",
            "subcategory":"Auto Parts",
            "type":"Manufacturing & Wholesale Goods"
        }
    ],
    "sg:phone":"+1 954 704 1205",
    "sg:postcode":"33025",
    "sg:province":"FL",
    "wof:name":"A Parts",
    "wof:placetype":"venue"
},
  "geometry": {"coordinates":[-80.29494099999999,25.994774],"type":"Point"}
}