{
  "type": "Feature",
  "properties": {
    "addr:full":"345 Duval St Fort Walton Bch FL 32547",
    "addr:housenumber":"345",
    "addr:postcode":"32547",
    "addr:street":"Duval St",
    "iso:country":"US",
    "sg:address":"345 Duval St",
    "sg:city":"Fort Walton Bch",
    "sg:classifiers":[
        {
            "category":"Professional",
            "subcategory":"Art Services",
            "type":"Services"
        }
    ],
    "sg:phone":"+1 850 830 4564",
    "sg:postcode":"32547",
    "sg:province":"FL",
    "sg:tags":[
        "graphic",
        "designer"
    ],
    "wof:name":"T C Graphics",
    "wof:placetype":"venue"
},
  "geometry": {"coordinates":[-86.60800999999999,30.445311],"type":"Point"}
}