{
  "type": "Feature",
  "properties": {
    "iso:country":"US",
    "sg:address":"3081 NW 123rd Ave",
    "sg:city":"Fort Lauderdale",
    "sg:classifiers":[
        {
            "category":"Wholesale",
            "subcategory":"Groceries",
            "type":"Manufacturing & Wholesale Goods"
        }
    ],
    "sg:phone":"+1 954 749 9368",
    "sg:postcode":"33323",
    "sg:province":"FL",
    "wof:name":"Jamaican Roasters Inc",
    "wof:placetype":"venue"
},
  "geometry": {"coordinates":[-80.312757,26.165206],"type":"Point"}
}