{
  "type": "Feature",
  "properties": {
    "addr:full":"976 Somerset Ln Melbourne FL 32940",
    "addr:housenumber":"976",
    "addr:postcode":"32940",
    "addr:street":"Somerset Ln",
    "iso:country":"US",
    "sg:address":"976 Somerset Ln",
    "sg:city":"Melbourne",
    "sg:classifiers":[
        {
            "category":"Insurance",
            "subcategory":"Insurance Agent",
            "type":"Services"
        }
    ],
    "sg:phone":"+1 321 752 7363",
    "sg:postcode":"32940",
    "sg:province":"FL",
    "wof:name":"Risk Excellence",
    "wof:placetype":"venue"
},
  "geometry": {"coordinates":[-80.692527,28.207897],"type":"Point"}
}