{
  "type": "Feature",
  "properties": {
    "iso:country":"US",
    "sg:address":"13901 US Hwy 1",
    "sg:city":"Juno Beach",
    "sg:classifiers":[
        {
            "category":"Health Services",
            "subcategory":"Doctor",
            "type":"Services"
        }
    ],
    "sg:phone":"+1 561 630 0840",
    "sg:postcode":"33408",
    "sg:province":"FL",
    "sg:tags":[
        "physician",
        "surgeon"
    ],
    "wof:name":"Healthy Women",
    "wof:placetype":"venue"
},
  "geometry": {"coordinates":[-80.05589500000001,26.879405],"type":"Point"}
}