{
  "type": "Feature",
  "properties": {
    "iso:country":"US",
    "sg:address":"28341 S Tamiami Trl",
    "sg:city":"Bonita Springs",
    "sg:classifiers":[
        {
            "category":"Recreation",
            "type":"Entertainment"
        }
    ],
    "sg:phone":"+1 239 948 0008",
    "sg:postcode":"33928",
    "sg:province":"FL",
    "sg:tags":[
        "tours"
    ],
    "wof:name":"Caribbean Duck Tours",
    "wof:placetype":"venue"
},
  "geometry": {"coordinates":[-81.805538,26.325096],"type":"Point"}
}