{
  "type": "Feature",
  "properties": {
    "iso:country":"US",
    "sg:address":"339 S Deerwood Ave",
    "sg:city":"Orlando",
    "sg:classifiers":[
        {
            "category":"Real Estate",
            "subcategory":"Real Estate Agent",
            "type":"Services"
        }
    ],
    "sg:phone":"+1 407 493 3511",
    "sg:postcode":"32825",
    "sg:province":"FL",
    "sg:tags":[
        "inspection"
    ],
    "wof:name":"Intuitive Home Inspection Inc",
    "wof:placetype":"venue"
},
  "geometry": {"coordinates":[-81.257175,28.539384],"type":"Point"}
}