{
  "type": "Feature",
  "properties": {
    "iso:country":"US",
    "sg:address":"845 NE 6th Ave",
    "sg:city":"Delray Beach",
    "sg:classifiers":[
        {
            "category":"Health Services",
            "subcategory":"Doctor",
            "type":"Services"
        }
    ],
    "sg:phone":"+1 561 272 0040",
    "sg:postcode":"33483",
    "sg:province":"FL",
    "sg:tags":[
        "dentist"
    ],
    "wof:name":"Julian R Chapman DDS",
    "wof:placetype":"venue"
},
  "geometry": {"coordinates":[-80.06711900000001,26.476114],"type":"Point"}
}