{
  "type": "Feature",
  "properties": {
    "addr:full":"8836 NW 149th Ter Hialeah FL 33018",
    "addr:housenumber":"8836",
    "addr:postcode":"33018",
    "addr:street":"Nw 149Th Ter",
    "iso:country":"US",
    "sg:address":"8836 NW 149th Ter",
    "sg:city":"Hialeah",
    "sg:classifiers":[
        {
            "category":"Retail",
            "subcategory":"Repair Shop",
            "type":"Services"
        }
    ],
    "sg:phone":"+1 305 556 5941",
    "sg:postcode":"33018",
    "sg:province":"FL",
    "sg:tags":[
        "equipment",
        "electronic",
        "supply"
    ],
    "wof:name":"Carlos' Sound Systems",
    "wof:placetype":"venue"
},
  "geometry": {"coordinates":[-80.342449,25.909105],"type":"Point"}
}