{
  "type": "Feature",
  "properties": {
    "iso:country":"US",
    "sg:address":"1702 Grange Cir",
    "sg:city":"Longwood",
    "sg:classifiers":[
        {
            "category":"Communications",
            "subcategory":"Film & Video Production",
            "type":"Services"
        }
    ],
    "sg:phone":"+1 407 260 0449",
    "sg:postcode":"32750",
    "sg:province":"FL",
    "sg:tags":[
        "motion"
    ],
    "sg:website":"http://www.aimvideoproductions.com",
    "wof:name":"AIM Video Productions",
    "wof:placetype":"venue"
},
  "geometry": {"coordinates":[-81.357071,28.719231],"type":"Point"}
}