{
  "type": "Feature",
  "properties": {
    "iso:country":"US",
    "sg:address":"6970 130th Ave N",
    "sg:city":"West Palm Beach",
    "sg:classifiers":[
        {
            "category":"Building & Trades",
            "subcategory":"Construction",
            "type":"Services"
        }
    ],
    "sg:phone":"+1 561 795 6982",
    "sg:postcode":"33412",
    "sg:province":"FL",
    "sg:tags":[
        "dry wall",
        "contractor"
    ],
    "wof:name":"Coastal Drywall Systems Inc",
    "wof:placetype":"venue"
},
  "geometry": {"coordinates":[-80.245966,26.779311],"type":"Point"}
}