{
  "type": "Feature",
  "properties": {
    "iso:country":"US",
    "sg:address":"6633 S Dixie Hwy",
    "sg:city":"Miami",
    "sg:classifiers":[
        {
            "category":"Shopping",
            "subcategory":"Clothing, Apparel, & Fashions",
            "type":"Retail Goods"
        }
    ],
    "sg:phone":"+1 786 268 0678",
    "sg:postcode":"33143",
    "sg:province":"FL",
    "sg:tags":[
        "accessory",
        "clothing",
        "women's"
    ],
    "wof:name":"Blush",
    "wof:placetype":"venue"
},
  "geometry": {"coordinates":[-80.300499,25.695299],"type":"Point"}
}