{
  "type": "Feature",
  "properties": {
    "iso:country":"US",
    "sg:address":"2700 Maritime Blvd",
    "sg:city":"Tampa",
    "sg:classifiers":[
        {
            "category":"Home & Garden",
            "subcategory":"Garden Supply",
            "type":"Retail Goods"
        }
    ],
    "sg:phone":"+1 813 248 0712",
    "sg:postcode":"33605",
    "sg:province":"FL",
    "sg:tags":[
        "fertilizer"
    ],
    "wof:name":"Vital-Cycle",
    "wof:placetype":"venue"
},
  "geometry": {"coordinates":[-82.440879,27.919857],"type":"Point"}
}