{
  "type": "Feature",
  "properties": {
    "iso:country":"US",
    "sg:address":"4921 Tangerine Ave S",
    "sg:city":"Gulfport",
    "sg:classifiers":[
        {
            "category":"Retail",
            "subcategory":"Repair Shop",
            "type":"Services"
        }
    ],
    "sg:phone":"+1 727 321 7381",
    "sg:postcode":"33707",
    "sg:province":"FL",
    "sg:tags":[
        "clocks",
        "parts"
    ],
    "wof:name":"Gulfport Watch & Clock Hosp",
    "wof:placetype":"venue"
},
  "geometry": {"coordinates":[-82.701722,27.752192],"type":"Point"}
}