{
  "type": "Feature",
  "properties": {
    "iso:country":"US",
    "sg:address":"103 E Canal St",
    "sg:city":"Mulberry",
    "sg:classifiers":[
        {
            "category":"Education",
            "subcategory":"Library",
            "type":"Public Place"
        },
        {
            "category":"Government",
            "subcategory":"Office",
            "type":"Public Place"
        }
    ],
    "sg:phone":"+1 863 425 3246",
    "sg:postcode":"33860",
    "sg:province":"FL",
    "sg:tags":[
        "township",
        "government-city",
        "village"
    ],
    "wof:name":"Dr. C.C. Pearce Municipal Library",
    "wof:placetype":"venue"
},
  "geometry": {"coordinates":[-81.973105,27.89489],"type":"Point"}
}