{
  "type": "Feature",
  "properties": {
    "addr:full":"3111 Spring Park Rd Jacksonville FL 32207",
    "addr:housenumber":"3111",
    "addr:postcode":"32207",
    "addr:street":"Spring Park Rd",
    "iso:country":"US",
    "sg:address":"3111 Spring Park Rd",
    "sg:city":"Jacksonville",
    "sg:classifiers":[
        {
            "category":"Professional",
            "subcategory":"Detective & Security Services",
            "type":"Services"
        }
    ],
    "sg:phone":"+1 904 398 2090",
    "sg:postcode":"32207",
    "sg:province":"FL",
    "sg:tags":[
        "car",
        "armored"
    ],
    "sg:website":"www.loomisfargo.com",
    "wof:name":"Loomis Fargo & Co",
    "wof:placetype":"venue"
},
  "geometry": {"coordinates":[-81.62572299999999,30.291139],"type":"Point"}
}