{
  "type": "Feature",
  "properties": {
    "addr:full":"13050 NW 30th Ave Opa Locka FL 33054",
    "addr:housenumber":"13050",
    "addr:postcode":"33054",
    "addr:street":"Nw 30Th Ave;Locka",
    "iso:country":"US",
    "sg:address":"13050 NW 30th Ave",
    "sg:city":"Opa Locka",
    "sg:classifiers":[
        {
            "category":"Professional",
            "type":"Services"
        }
    ],
    "sg:phone":"+1 305 681 3844",
    "sg:postcode":"33054",
    "sg:province":"FL",
    "wof:name":"Greff International Inc",
    "wof:placetype":"venue"
},
  "geometry": {"coordinates":[-80.247584,25.892494],"type":"Point"}
}