{
  "type": "Feature",
  "properties": {
    "iso:country":"US",
    "sg:address":"600 76th St Unit 2",
    "sg:city":"Miami Beach",
    "sg:classifiers":[
        {
            "category":"Professional",
            "subcategory":"Advertising",
            "type":"Services"
        },
        {
            "category":"Professional",
            "subcategory":"Art Services",
            "type":"Services"
        },
        {
            "category":"Communications",
            "type":"Services"
        }
    ],
    "sg:phone":"+1 786 361 8710",
    "sg:postcode":"33141",
    "sg:province":"FL",
    "sg:tags":[
        "marketing",
        "graphic",
        "design",
        "web"
    ],
    "sg:website":"www.webdesignmiamira.com",
    "wof:name":"Rafael Anazco",
    "wof:placetype":"venue"
},
  "geometry": {"coordinates":[-80.12466000000001,25.861101],"type":"Point"}
}