{
  "type": "Feature",
  "properties": {
    "iso:country":"US",
    "sg:address":"5303 NW 7th St",
    "sg:city":"Miami",
    "sg:classifiers":[
        {
            "category":"Retail",
            "subcategory":"Auto Repair",
            "type":"Services"
        }
    ],
    "sg:phone":"+1 305 529 6495",
    "sg:postcode":"33126",
    "sg:province":"FL",
    "sg:tags":[
        "repairing",
        "automobile"
    ],
    "wof:name":"Hermes Auto Svc",
    "wof:placetype":"venue"
},
  "geometry": {"coordinates":[-80.28282900000001,25.7783],"type":"Point"}
}