{
  "type": "Feature",
  "properties": {
    "iso:country":"US",
    "sg:address":"196 W 25th St",
    "sg:city":"Hialeah",
    "sg:classifiers":[
        {
            "category":"Restaurant",
            "type":"Food & Drink"
        },
        {
            "category":"Food & Beverages",
            "subcategory":"Bakery",
            "type":"Retail Goods"
        }
    ],
    "sg:phone":"+1 305 883 5188",
    "sg:postcode":"33010",
    "sg:province":"FL",
    "sg:tags":[
        "baker",
        "eating"
    ],
    "wof:name":"Catering Express",
    "wof:placetype":"venue"
},
  "geometry": {"coordinates":[-80.28440999999999,25.844543],"type":"Point"}
}