{
  "type": "Feature",
  "properties": {
    "iso:country":"US",
    "sg:address":"10355 Hammocks Blvd",
    "sg:city":"Miami",
    "sg:classifiers":[
        {
            "category":"Recreation",
            "type":"Entertainment"
        }
    ],
    "sg:phone":"+1 305 388 1129",
    "sg:postcode":"33196",
    "sg:province":"FL",
    "sg:tags":[
        "boxing",
        "instruction"
    ],
    "wof:name":"Knock Out Boxing Club",
    "wof:placetype":"venue"
},
  "geometry": {"coordinates":[-80.443772,25.67029],"type":"Point"}
}