{
  "type": "Feature",
  "properties": {
    "iso:country":"US",
    "sg:address":"8054 Washington St",
    "sg:city":"Port Richey",
    "sg:classifiers":[
        {
            "category":"Banks & Credit Unions",
            "subcategory":"Bank",
            "type":"Services"
        }
    ],
    "sg:phone":"+1 727 815 8515",
    "sg:postcode":"34668",
    "sg:province":"FL",
    "sg:tags":[
        "machine",
        "wholesale",
        "teller",
        "card",
        "automated"
    ],
    "wof:name":"Amer-E-Com Digital Corporation",
    "wof:placetype":"venue"
},
  "geometry": {"coordinates":[-82.719628,28.27507],"type":"Point"}
}