{
  "type": "Feature",
  "properties": {
    "addr:full":"134 SW 5th Ave Miami FL 33130",
    "addr:housenumber":"134",
    "addr:postcode":"33130",
    "addr:street":"Sw 5Th Ave",
    "iso:country":"US",
    "sg:address":"134 SW 5th Ave",
    "sg:city":"Miami",
    "sg:classifiers":[
        {
            "category":"Shopping",
            "subcategory":"Party Supplies",
            "type":"Retail Goods"
        }
    ],
    "sg:phone":"+1 305 325 8444",
    "sg:postcode":"33130",
    "sg:province":"FL",
    "sg:tags":[
        "decoration",
        "rental"
    ],
    "wof:name":"A Party Connection",
    "wof:placetype":"venue"
},
  "geometry": {"coordinates":[-80.20264899999999,25.77254],"type":"Point"}
}