{
  "type": "Feature",
  "properties": {
    "iso:country":"US",
    "sg:address":"3440 Ocean Pkwy",
    "sg:city":"Boynton Beach",
    "sg:classifiers":[
        {
            "category":"Retail",
            "subcategory":"Repair Shop",
            "type":"Services"
        }
    ],
    "sg:phone":"+1 561 667 1823",
    "sg:postcode":"33435",
    "sg:province":"FL",
    "sg:tags":[
        "equipment",
        "conditioning",
        "air"
    ],
    "wof:name":"Evans Air",
    "wof:placetype":"venue"
},
  "geometry": {"coordinates":[-80.063748,26.564414],"type":"Point"}
}