{
  "type": "Feature",
  "properties": {
    "iso:country":"US",
    "sg:address":"2669 Enterprise Rd",
    "sg:city":"Orange City",
    "sg:classifiers":[
        {
            "category":"Health Services",
            "subcategory":"Doctor",
            "type":"Services"
        }
    ],
    "sg:phone":"+1 386 774 0491",
    "sg:postcode":"32763",
    "sg:province":"FL",
    "sg:tags":[
        "physician",
        "surgeon",
        "medical"
    ],
    "wof:name":"Elder Health Care of Volusia",
    "wof:placetype":"venue"
},
  "geometry": {"coordinates":[-81.29164,28.910847],"type":"Point"}
}