{
  "type": "Feature",
  "properties": {
    "addr:full":"3231 Union St N St Petersburg FL 33713",
    "addr:housenumber":"3231",
    "addr:postcode":"33713",
    "addr:street":"Union St N",
    "iso:country":"US",
    "sg:address":"3231 Union St N",
    "sg:city":"St Petersburg",
    "sg:classifiers":[
        {
            "category":"Building & Trades",
            "subcategory":"Landscaping Services",
            "type":"Services"
        }
    ],
    "sg:phone":"+1 727 894 5704",
    "sg:postcode":"33713",
    "sg:province":"FL",
    "sg:tags":[
        "lawn",
        "maintenance",
        "grounds"
    ],
    "wof:name":"Bennett's Tractor Mowing",
    "wof:placetype":"venue"
},
  "geometry": {"coordinates":[-82.662046,27.80242],"type":"Point"}
}