{
  "type": "Feature",
  "properties": {
    "addr:full":"1885 US Hwy 19 Tarpon Springs FL 34691",
    "addr:housenumber":"1885",
    "addr:postcode":"34691",
    "addr:street":"Us Hwy 19",
    "iso:country":"US",
    "sg:address":"1885 US Hwy 19",
    "sg:city":"Tarpon Springs",
    "sg:classifiers":[
        {
            "category":"Food & Beverages",
            "subcategory":"Fruits & Vegetables",
            "type":"Retail Goods"
        }
    ],
    "sg:phone":"+1 727 942 4894",
    "sg:postcode":"34691",
    "sg:province":"FL",
    "sg:tags":[
        "produce"
    ],
    "wof:name":"Johnny's Produce II",
    "wof:placetype":"venue"
},
  "geometry": {"coordinates":[-82.740179,28.186571],"type":"Point"}
}