{
  "type": "Feature",
  "properties": {
    "addr:full":"4824 N Meridian Rd Tallahassee FL 32312",
    "addr:housenumber":"4824",
    "addr:postcode":"32312",
    "addr:street":"N Meridian Rd",
    "iso:country":"US",
    "sg:address":"4824 N Meridian Rd",
    "sg:city":"Tallahassee",
    "sg:classifiers":[
        {
            "category":"Organizations",
            "subcategory":"Religious Organization",
            "type":"Services"
        }
    ],
    "sg:phone":"+1 850 893 2268",
    "sg:postcode":"32312",
    "sg:province":"FL",
    "sg:tags":[
        "church"
    ],
    "wof:name":"Elizabeth Popular Spring Chr",
    "wof:placetype":"venue"
},
  "geometry": {"coordinates":[-84.277564,30.535449],"type":"Point"}
}