{
  "type": "Feature",
  "properties": {
    "iso:country":"US",
    "sg:address":"545 Pine Island Rd",
    "sg:city":"Fort Myers",
    "sg:classifiers":[
        {
            "category":"Professional",
            "subcategory":"Accounting & Tax Preparation",
            "type":"Services"
        }
    ],
    "sg:phone":"+1 239 997 3278",
    "sg:postcode":"33903",
    "sg:province":"FL",
    "sg:tags":[
        "return",
        "filing"
    ],
    "wof:name":"Jackson Hewitt Tax Svc",
    "wof:placetype":"venue"
},
  "geometry": {"coordinates":[-81.899829,26.681912],"type":"Point"}
}