{
  "type": "Feature",
  "properties": {
    "iso:country":"US",
    "sg:address":"82 SW Irwin Ave",
    "sg:city":"Melbourne",
    "sg:classifiers":[
        {
            "category":"Building & Trades",
            "subcategory":"Plumbing",
            "type":"Services"
        },
        {
            "category":"Wholesale",
            "subcategory":"Machinery & Supplies",
            "type":"Manufacturing & Wholesale Goods"
        }
    ],
    "sg:phone":"+1 321 724 6473",
    "sg:postcode":"32904",
    "sg:province":"FL",
    "sg:tags":[
        "lawn",
        "installation",
        "system",
        "sprinklers-garden",
        "irrigation",
        "contractor",
        "equipment"
    ],
    "wof:name":"Indian River Irrigation Systems",
    "wof:placetype":"venue"
},
  "geometry": {"coordinates":[-80.64128700000001,28.078379],"type":"Point"}
}