{
  "type": "Feature",
  "properties": {
    "addr:full":"6190 SE Bridge Rd Hobe Sound FL 33455",
    "addr:housenumber":"6190",
    "addr:postcode":"33455",
    "addr:street":"Se Bridge Rd",
    "iso:country":"US",
    "sg:address":"6190 SE Bridge Rd",
    "sg:city":"Hobe Sound",
    "sg:classifiers":[
        {
            "category":"Building & Trades",
            "subcategory":"Construction",
            "type":"Services"
        }
    ],
    "sg:phone":"+1 772 546 1949",
    "sg:postcode":"33455",
    "sg:province":"FL",
    "sg:tags":[
        "house"
    ],
    "wof:name":"Thomas Dickerson Construction",
    "wof:placetype":"venue"
},
  "geometry": {"coordinates":[-80.169675,27.043631],"type":"Point"}
}