{
  "type": "Feature",
  "properties": {
    "iso:country":"US",
    "sg:address":"1886 40th Ter SW",
    "sg:city":"Naples",
    "sg:classifiers":[
        {
            "category":"Restaurant",
            "type":"Food & Drink"
        }
    ],
    "sg:phone":"+1 239 304 1396",
    "sg:postcode":"34116",
    "sg:province":"FL",
    "wof:name":"Tropical Restaurant",
    "wof:placetype":"venue"
},
  "geometry": {"coordinates":[-81.68843699999999,26.193997],"type":"Point"}
}