{
  "type": "Feature",
  "properties": {
    "addr:full":"8520 NW 46th Dr Pompano Beach FL 33067",
    "addr:housenumber":"8520",
    "addr:postcode":"33067",
    "addr:street":"Nw 46Th Dr",
    "iso:country":"US",
    "sg:address":"8520 NW 46th Dr",
    "sg:city":"Pompano Beach",
    "sg:classifiers":[
        {
            "category":"Building & Trades",
            "subcategory":"Electrical",
            "type":"Services"
        }
    ],
    "sg:phone":"+1 954 341 9823",
    "sg:postcode":"33067",
    "sg:province":"FL",
    "sg:tags":[
        "electrical",
        "contractor"
    ],
    "wof:name":"Drew Laurenzano Electric Inc",
    "wof:placetype":"venue"
},
  "geometry": {"coordinates":[-80.241304,26.287281],"type":"Point"}
}