{
  "type": "Feature",
  "properties": {
    "addr:full":"1702 Minnesota Ave Lynn Haven FL 32444",
    "addr:housenumber":"1702",
    "addr:postcode":"32444",
    "addr:street":"Minnesota Ave",
    "iso:country":"US",
    "sg:address":"1702 Minnesota Ave",
    "sg:city":"Lynn Haven",
    "sg:classifiers":[
        {
            "category":"Building & Trades",
            "subcategory":"Construction",
            "type":"Services"
        }
    ],
    "sg:phone":"+1 850 265 5402",
    "sg:postcode":"32444",
    "sg:province":"FL",
    "sg:tags":[
        "contractor"
    ],
    "wof:name":"Scott Dalys Tile Installation",
    "wof:placetype":"venue"
},
  "geometry": {"coordinates":[-85.64441600000001,30.232909],"type":"Point"}
}