{
  "type": "Feature",
  "properties": {
    "addr:full":"4158 Okeechobee Rd Fort Pierce FL 34947",
    "addr:housenumber":"4158",
    "addr:postcode":"34947",
    "addr:street":"Okeechobee Rd",
    "iso:country":"US",
    "sg:address":"4158 Okeechobee Rd",
    "sg:city":"Fort Pierce",
    "sg:classifiers":[
        {
            "category":"Autos & Motor Vehicles",
            "subcategory":"Auto Supplies",
            "type":"Retail Goods"
        }
    ],
    "sg:phone":"+1 772 489 2428",
    "sg:postcode":"34947",
    "sg:province":"FL",
    "sg:tags":[
        "automobile",
        "parts"
    ],
    "wof:name":"Advance Auto Parts Inc",
    "wof:placetype":"venue"
},
  "geometry": {"coordinates":[-80.36776399999999,27.425818],"type":"Point"}
}