{
  "type": "Feature",
  "properties": {
    "iso:country":"US",
    "sg:address":"7270 SW 12th St",
    "sg:city":"Miami",
    "sg:classifiers":[
        {
            "category":"Manufacturing",
            "subcategory":"Tools & Machinery",
            "type":"Manufacturing & Wholesale Goods"
        }
    ],
    "sg:phone":"+1 305 593 9749",
    "sg:postcode":"33144",
    "sg:province":"FL",
    "sg:tags":[
        "equipment",
        "pump",
        "pumping"
    ],
    "wof:name":"ITT Industries Inc",
    "wof:placetype":"venue"
},
  "geometry": {"coordinates":[-80.31409600000001,25.759047],"type":"Point"}
}