{
  "type": "Feature",
  "properties": {
    "iso:country":"US",
    "sg:address":"2800 SW 4th Ave",
    "sg:city":"Fort Lauderdale",
    "sg:classifiers":[
        {
            "category":"Airline",
            "type":"Transportation"
        },
        {
            "category":"Building & Trades",
            "subcategory":"Equipment Rental",
            "type":"Services"
        }
    ],
    "sg:phone":"+1 954 761 3131",
    "sg:postcode":"33315",
    "sg:province":"FL",
    "sg:tags":[
        "aircraft",
        "charter",
        "leasing",
        "nonscheduled",
        "air"
    ],
    "wof:name":"Reggie Express Services Inc",
    "wof:placetype":"venue"
},
  "geometry": {"coordinates":[-80.146542,26.085316],"type":"Point"}
}