{
  "type": "Feature",
  "properties": {
    "addr:full":"23358 Water Cir Boca Raton FL 33486",
    "addr:housenumber":"23358",
    "addr:postcode":"33486",
    "addr:street":"Water Cir",
    "iso:country":"US",
    "sg:address":"23358 Water Cir",
    "sg:city":"Boca Raton",
    "sg:classifiers":[
        {
            "category":"Insurance",
            "subcategory":"Insurance Agent",
            "type":"Services"
        }
    ],
    "sg:phone":"+1 561 750 8653",
    "sg:postcode":"33486",
    "sg:province":"FL",
    "wof:name":"American Insurance & Financial",
    "wof:placetype":"venue"
},
  "geometry": {"coordinates":[-80.124742,26.330695],"type":"Point"}
}