{
  "type": "Feature",
  "properties": {
    "addr:full":"413 Islamorada Blvd Punta Gorda FL 33955",
    "addr:housenumber":"413",
    "addr:postcode":"33955",
    "addr:street":"Islamorada Blvd",
    "iso:country":"US",
    "sg:address":"413 Islamorada Blvd",
    "sg:city":"Punta Gorda",
    "sg:classifiers":[
        {
            "category":"Shopping",
            "type":"Retail Goods"
        }
    ],
    "sg:phone":"+1 941 575 0233",
    "sg:postcode":"33955",
    "sg:province":"FL",
    "sg:tags":[
        "merchandise"
    ],
    "wof:name":"Minta A Williquiett Pet S",
    "wof:placetype":"venue"
},
  "geometry": {"coordinates":[-82.051355,26.762309],"type":"Point"}
}