{
  "type": "Feature",
  "properties": {
    "iso:country":"US",
    "sg:address":"568 Gainsboro St",
    "sg:city":"Deltona",
    "sg:classifiers":[
        {
            "category":"Professional",
            "subcategory":"Art Services",
            "type":"Services"
        }
    ],
    "sg:phone":"+1 386 562 0728",
    "sg:postcode":"32725",
    "sg:province":"FL",
    "sg:tags":[
        "designer",
        "display",
        "producer"
    ],
    "wof:name":"Entertainment Designs And Marketing",
    "wof:placetype":"venue"
},
  "geometry": {"coordinates":[-81.263869,28.918238],"type":"Point"}
}