{
  "type": "Feature",
  "properties": {
    "addr:full":"2334 Westminster Ter Oviedo FL 32765",
    "addr:housenumber":"2334",
    "addr:postcode":"32765",
    "addr:street":"Westminster Ter",
    "iso:country":"US",
    "sg:address":"2334 Westminster Ter",
    "sg:city":"Oviedo",
    "sg:classifiers":[
        {
            "category":"Insurance",
            "subcategory":"Insurance Agent",
            "type":"Services"
        }
    ],
    "sg:phone":"+1 407 359 8214",
    "sg:postcode":"32765",
    "sg:province":"FL",
    "wof:name":"Rick Gatlin Glaxo Srvs",
    "wof:placetype":"venue"
},
  "geometry": {"coordinates":[-81.21888,28.635437],"type":"Point"}
}