{
  "type": "Feature",
  "properties": {
    "iso:country":"US",
    "sg:address":"724 Versailles Ln",
    "sg:city":"Kissimmee",
    "sg:classifiers":[
        {
            "category":"Shopping",
            "subcategory":"Books",
            "type":"Retail Goods"
        }
    ],
    "sg:phone":"+1 407 931 2077",
    "sg:postcode":"34759",
    "sg:province":"FL",
    "sg:tags":[
        "bible"
    ],
    "wof:name":"Sociedad Biblica Valera",
    "wof:placetype":"venue"
},
  "geometry": {"coordinates":[-81.436672,28.110316],"type":"Point"}
}