{
  "type": "Feature",
  "properties": {
    "iso:country":"US",
    "sg:address":"250 N Atlantic Ave",
    "sg:city":"Daytona Beach",
    "sg:classifiers":[
        {
            "category":"Recreation",
            "type":"Entertainment"
        }
    ],
    "sg:phone":"+1 386 258 3040",
    "sg:postcode":"32118",
    "sg:province":"FL",
    "sg:tags":[
        "charter",
        "boat"
    ],
    "wof:name":"Short Money Jet Ski Rentals",
    "wof:placetype":"venue"
},
  "geometry": {"coordinates":[-81.01003799999999,29.230661],"type":"Point"}
}