{
  "type": "Feature",
  "properties": {
    "iso:country":"US",
    "sg:address":"5523 W Cypress St",
    "sg:city":"Tampa",
    "sg:classifiers":[
        {
            "category":"Building & Trades",
            "subcategory":"Construction",
            "type":"Services"
        },
        {
            "category":"Professional",
            "subcategory":"Management & Consulting",
            "type":"Services"
        }
    ],
    "sg:phone":"+1 813 282 1179",
    "sg:postcode":"33607",
    "sg:province":"FL",
    "sg:tags":[
        "general",
        "commercial",
        "contractor"
    ],
    "wof:name":"Wichman Construction",
    "wof:placetype":"venue"
},
  "geometry": {"coordinates":[-82.54212699999999,27.952571],"type":"Point"}
}