{
  "type": "Feature",
  "properties": {
    "addr:full":"675 Tamiami Trl N Naples FL 34102",
    "addr:housenumber":"675",
    "addr:postcode":"34102",
    "addr:street":"Tamiami Trl N",
    "iso:country":"US",
    "sg:address":"675 Tamiami Trl N",
    "sg:city":"Naples",
    "sg:classifiers":[
        {
            "category":"Restaurant",
            "type":"Food & Drink"
        }
    ],
    "sg:phone":"+1 239 261 8818",
    "sg:postcode":"34102",
    "sg:province":"FL",
    "wof:name":"Pizza Hut",
    "wof:placetype":"venue"
},
  "geometry": {"coordinates":[-81.79665900000001,26.154602],"type":"Point"}
}