{
  "type": "Feature",
  "properties": {
    "iso:country":"US",
    "sg:address":"4615 Santa Maria St",
    "sg:city":"Miami",
    "sg:classifiers":[
        {
            "category":"Professional",
            "subcategory":"Lawyer & Legal Services",
            "type":"Services"
        }
    ],
    "sg:phone":"+1 305 661 2452",
    "sg:postcode":"33146",
    "sg:province":"FL",
    "wof:name":"Walker H William Jr Atty",
    "wof:placetype":"venue"
},
  "geometry": {"coordinates":[-80.277901,25.728701],"type":"Point"}
}