{
  "type": "Feature",
  "properties": {
    "addr:full":"318 S Copeland St Tallahassee FL 32304",
    "addr:housenumber":"318",
    "addr:postcode":"32304",
    "addr:street":"S Copeland St",
    "iso:country":"US",
    "sg:address":"318 S Copeland St",
    "sg:city":"Tallahassee",
    "sg:classifiers":[
        {
            "category":"Organizations",
            "subcategory":"Community Association",
            "type":"Services"
        }
    ],
    "sg:phone":"+1 850 224 7764",
    "sg:postcode":"32304",
    "sg:province":"FL",
    "sg:tags":[
        "sorority",
        "fraternity"
    ],
    "wof:name":"Delta Tau Delta Fraternity",
    "wof:placetype":"venue"
},
  "geometry": {"coordinates":[-84.290863,30.438907],"type":"Point"}
}