{
  "type": "Feature",
  "properties": {
    "addr:full":"205 Cook St Brandon FL 33511",
    "addr:housenumber":"205",
    "addr:postcode":"33511",
    "addr:street":"Cook St",
    "iso:country":"US",
    "sg:address":"205 Cook St",
    "sg:city":"Brandon",
    "sg:classifiers":[
        {
            "category":"Autos & Motor Vehicles",
            "subcategory":"Auto Supplies",
            "type":"Retail Goods"
        }
    ],
    "sg:phone":"+1 813 685 3040",
    "sg:postcode":"33511",
    "sg:province":"FL",
    "sg:tags":[
        "equipment",
        "racing",
        "car",
        "automobile"
    ],
    "wof:name":"Jeffs Auto & Speed Supply Inc",
    "wof:placetype":"venue"
},
  "geometry": {"coordinates":[-82.282291,27.936612],"type":"Point"}
}