{
  "type": "Feature",
  "properties": {
    "addr:full":"175 NW 31st St Miami FL 33127",
    "addr:housenumber":"175",
    "addr:postcode":"33127",
    "addr:street":"Nw 31St St",
    "iso:country":"US",
    "sg:address":"175 NW 31st St",
    "sg:city":"Miami",
    "sg:classifiers":[
        {
            "category":"Organizations",
            "subcategory":"Religious Organization",
            "type":"Services"
        }
    ],
    "sg:phone":"+1 305 634 5774",
    "sg:postcode":"33127",
    "sg:province":"FL",
    "wof:name":"Victory Outreach",
    "wof:placetype":"venue"
},
  "geometry": {"coordinates":[-80.197924,25.805807],"type":"Point"}
}