{
  "type": "Feature",
  "properties": {
    "iso:country":"US",
    "sg:address":"3641 10th St N",
    "sg:city":"Naples",
    "sg:classifiers":[
        {
            "category":"Building & Trades",
            "subcategory":"Construction",
            "type":"Services"
        }
    ],
    "sg:phone":"+1 239 262 5775",
    "sg:postcode":"34103",
    "sg:province":"FL",
    "sg:tags":[
        "residential",
        "designer"
    ],
    "wof:name":"Nicolle Swanson Designs",
    "wof:placetype":"venue"
},
  "geometry": {"coordinates":[-81.798586,26.190615],"type":"Point"}
}