{
  "type": "Feature",
  "properties": {
    "addr:full":"5 E Lucy St Homestead FL 33034",
    "addr:housenumber":"5",
    "addr:postcode":"33034",
    "addr:street":"E Lucy St",
    "iso:country":"US",
    "sg:address":"5 E Lucy St",
    "sg:city":"Homestead",
    "sg:classifiers":[
        {
            "category":"Communications",
            "type":"Services"
        },
        {
            "category":"Shopping",
            "subcategory":"Computers & Home Electronics",
            "type":"Retail Goods"
        }
    ],
    "sg:phone":"+1 305 248 2990",
    "sg:postcode":"33034",
    "sg:province":"FL",
    "sg:tags":[
        "sound",
        "television",
        "system",
        "equipment",
        "radio",
        "consumer",
        "store"
    ],
    "wof:name":"Noe Electronics",
    "wof:placetype":"venue"
},
  "geometry": {"coordinates":[-80.477188,25.462495],"type":"Point"}
}