{
  "type": "Feature",
  "properties": {
    "iso:country":"US",
    "sg:address":"701 W John Sims Pkwy",
    "sg:city":"Valparaiso",
    "sg:classifiers":[
        {
            "category":"Banks & Credit Unions",
            "subcategory":"Bank",
            "type":"Services"
        }
    ],
    "sg:phone":"+1 850 729 4174",
    "sg:postcode":"32580",
    "sg:province":"FL",
    "sg:tags":[
        "personal",
        "institution"
    ],
    "wof:name":"Bank of America",
    "wof:placetype":"venue"
},
  "geometry": {"coordinates":[-86.501496,30.519814],"type":"Point"}
}