{
  "type": "Feature",
  "properties": {
    "iso:country":"US",
    "sg:address":"861 N Venetian Dr",
    "sg:city":"Miami",
    "sg:classifiers":[
        {
            "category":"Health Services",
            "subcategory":"Doctor",
            "type":"Services"
        }
    ],
    "sg:phone":"+1 305 374 8240",
    "sg:postcode":"33139",
    "sg:province":"FL",
    "sg:website":"dotfleishermiamicolonics.com/",
    "wof:name":"Dot Fleisher Miami Colonics Center",
    "wof:placetype":"venue"
},
  "geometry": {"coordinates":[-80.177796,25.790803],"type":"Point"}
}