{
  "type": "Feature",
  "properties": {
    "iso:country":"US",
    "sg:address":"299 Alhambra Cir",
    "sg:city":"Coral Gables",
    "sg:classifiers":[
        {
            "category":"Insurance",
            "subcategory":"Title Insurance",
            "type":"Services"
        },
        {
            "category":"Real Estate",
            "subcategory":"Real Estate Services",
            "type":"Services"
        }
    ],
    "sg:phone":"+1 305 443 4147",
    "sg:postcode":"33134",
    "sg:province":"FL",
    "sg:tags":[
        "company",
        "carrier"
    ],
    "wof:name":"South Florida Title Associates",
    "wof:placetype":"venue"
},
  "geometry": {"coordinates":[-80.25872699999999,25.752142],"type":"Point"}
}