{
  "type": "Feature",
  "properties": {
    "iso:country":"US",
    "sg:address":"17554 Front Beach Rd",
    "sg:city":"Panama City",
    "sg:classifiers":[
        {
            "category":"Restaurant",
            "type":"Food & Drink"
        }
    ],
    "sg:phone":"+1 850 234 1942",
    "sg:postcode":"32413",
    "sg:province":"FL",
    "wof:name":"Mike's Diner",
    "wof:placetype":"venue"
},
  "geometry": {"coordinates":[-85.914146,30.234565],"type":"Point"}
}