{
  "type": "Feature",
  "properties": {
    "iso:country":"US",
    "sg:address":"615 E Princeton St",
    "sg:city":"Orlando",
    "sg:classifiers":[
        {
            "category":"Health Services",
            "subcategory":"Doctor",
            "type":"Services"
        }
    ],
    "sg:phone":"+1 407 894 1645",
    "sg:postcode":"32803",
    "sg:province":"FL",
    "sg:tags":[
        "physician",
        "surgeon",
        "neurology",
        "surgeons"
    ],
    "sg:website":"http://www.neurosurgeons4kids.com",
    "wof:name":"Trumble, Eric MD",
    "wof:placetype":"venue"
},
  "geometry": {"coordinates":[-81.370205,28.571727],"type":"Point"}
}