{
  "type": "Feature",
  "properties": {
    "iso:country":"US",
    "sg:address":"4747 N Nob Hill Rd",
    "sg:city":"Sunrise",
    "sg:classifiers":[
        {
            "category":"Insurance",
            "subcategory":"Insurance Agent",
            "type":"Services"
        }
    ],
    "sg:phone":"+1 954 749 8443",
    "sg:postcode":"33351",
    "sg:province":"FL",
    "wof:name":"All State Insurance",
    "wof:placetype":"venue"
},
  "geometry": {"coordinates":[-80.284209,26.182979],"type":"Point"}
}