{
  "type": "Feature",
  "properties": {
    "iso:country":"US",
    "sg:address":"917 Sago Palm Way",
    "sg:city":"Apollo Beach",
    "sg:classifiers":[
        {
            "category":"Real Estate",
            "subcategory":"Real Estate Agent",
            "type":"Services"
        }
    ],
    "sg:phone":"+1 813 645 8438",
    "sg:postcode":"33572",
    "sg:province":"FL",
    "wof:name":"Brandon Villas",
    "wof:placetype":"venue"
},
  "geometry": {"coordinates":[-82.414777,27.778632],"type":"Point"}
}