{
  "type": "Feature",
  "properties": {
    "iso:country":"US",
    "sg:address":"22102 Blue Creek Lodge Rd",
    "sg:city":"Astor",
    "sg:classifiers":[
        {
            "category":"Shopping",
            "type":"Retail Goods"
        }
    ],
    "sg:phone":"+1 352 759 2063",
    "sg:postcode":"32102",
    "sg:province":"FL",
    "sg:tags":[
        "merchandise"
    ],
    "wof:name":"Suffield Philatelics",
    "wof:placetype":"venue"
},
  "geometry": {"coordinates":[-81.57629300000001,29.186555],"type":"Point"}
}