{
  "type": "Feature",
  "properties": {
    "iso:country":"US",
    "sg:address":"10875 154th Rd N",
    "sg:city":"Jupiter",
    "sg:classifiers":[
        {
            "category":"Professional",
            "subcategory":"Art Services",
            "type":"Services"
        },
        {
            "category":"Building & Trades",
            "subcategory":"Construction",
            "type":"Services"
        }
    ],
    "sg:phone":"+1 561 747 3622",
    "sg:postcode":"33478",
    "sg:province":"FL",
    "sg:tags":[
        "bathroom",
        "designer",
        "installation",
        "windows-repair",
        "contractor",
        "siding",
        "planning",
        "interior",
        "replacement",
        "remodeling",
        "decorator",
        "kitchen"
    ],
    "wof:name":"Tri-County Enterprises",
    "wof:placetype":"venue"
},
  "geometry": {"coordinates":[-80.20840699999999,26.904501],"type":"Point"}
}