{
  "type": "Feature",
  "properties": {
    "addr:full":"8801 Industrial Dr Tampa FL 33637",
    "addr:housenumber":"8801",
    "addr:postcode":"33637",
    "addr:street":"Industrial Dr",
    "iso:country":"US",
    "sg:address":"8801 Industrial Dr",
    "sg:city":"Tampa",
    "sg:classifiers":[
        {
            "category":"Professional",
            "subcategory":"Engineering",
            "type":"Services"
        }
    ],
    "sg:phone":"+1 813 988 7425",
    "sg:postcode":"33637",
    "sg:province":"FL",
    "sg:tags":[
        "engineer"
    ],
    "wof:name":"Production & Process",
    "wof:placetype":"venue"
},
  "geometry": {"coordinates":[-82.35946800000001,28.016737],"type":"Point"}
}