{
  "type": "Feature",
  "properties": {
    "addr:full":"1681 Algonquin Trl Maitland FL 32751",
    "addr:housenumber":"1681",
    "addr:postcode":"32751",
    "addr:street":"Algonquin Trl",
    "iso:country":"US",
    "sg:address":"1681 Algonquin Trl",
    "sg:city":"Maitland",
    "sg:classifiers":[
        {
            "category":"Restaurant",
            "type":"Food & Drink"
        }
    ],
    "sg:phone":"+1 407 628 8364",
    "sg:postcode":"32751",
    "sg:province":"FL",
    "sg:tags":[
        "eating"
    ],
    "wof:name":"Quiznos Subs",
    "wof:placetype":"venue"
},
  "geometry": {"coordinates":[-81.350982,28.629484],"type":"Point"}
}