{
  "type": "Feature",
  "properties": {
    "iso:country":"US",
    "sg:address":"2265 E Dana Dr",
    "sg:city":"Deltona",
    "sg:classifiers":[
        {
            "category":"Retail",
            "subcategory":"Auto Repair",
            "type":"Services"
        }
    ],
    "sg:phone":"+1 386 789 1043",
    "sg:postcode":"32738",
    "sg:province":"FL",
    "sg:tags":[
        "automotive"
    ],
    "wof:name":"Greggs Wrecker Service",
    "wof:placetype":"venue"
},
  "geometry": {"coordinates":[-81.19069500000001,28.928023],"type":"Point"}
}