{
  "type": "Feature",
  "properties": {
    "iso:country":"US",
    "sg:address":"2913 Maldive Ct",
    "sg:city":"Deltona",
    "sg:classifiers":[
        {
            "category":"Building & Trades",
            "subcategory":"Construction",
            "type":"Services"
        }
    ],
    "sg:phone":"+1 386 860 4977",
    "sg:postcode":"32738",
    "sg:province":"FL",
    "sg:tags":[
        "carpentry",
        "contractor"
    ],
    "wof:name":"Uniquely Unlimited Inc",
    "wof:placetype":"venue"
},
  "geometry": {"coordinates":[-81.18480700000001,28.885677],"type":"Point"}
}