{
  "type": "Feature",
  "properties": {
    "addr:full":"400 Meravan Ct Palm Harbor FL 34683",
    "addr:housenumber":"400",
    "addr:postcode":"34683",
    "addr:street":"Meravan Ct",
    "iso:country":"US",
    "sg:address":"400 Meravan Ct",
    "sg:city":"Palm Harbor",
    "sg:classifiers":[
        {
            "category":"Restaurant",
            "type":"Food & Drink"
        }
    ],
    "sg:phone":"+1 727 785 7080",
    "sg:postcode":"34683",
    "sg:province":"FL",
    "sg:tags":[
        "eating"
    ],
    "wof:name":"Marriott Micro Corp Inc",
    "wof:placetype":"venue"
},
  "geometry": {"coordinates":[-82.76530099999999,28.06262],"type":"Point"}
}