{
  "type": "Feature",
  "properties": {
    "addr:full":"1129 Royal Palm Beach Blvd Royal Palm Beach FL 33411",
    "addr:housenumber":"1129",
    "addr:postcode":"33411",
    "addr:street":"Royal Palm Beach Blvd",
    "iso:country":"US",
    "sg:address":"1129 Royal Palm Beach Blvd",
    "sg:city":"Royal Palm Beach",
    "sg:classifiers":[
        {
            "category":"Professional",
            "subcategory":"Business Services",
            "type":"Services"
        }
    ],
    "sg:phone":"+1 561 753 3777",
    "sg:postcode":"33411",
    "sg:province":"FL",
    "sg:tags":[
        "packaging",
        "center"
    ],
    "wof:name":"Postal Center Ix Inc",
    "wof:placetype":"venue"
},
  "geometry": {"coordinates":[-80.22900799999999,26.711183],"type":"Point"}
}