{
  "type": "Feature",
  "properties": {
    "addr:full":"133 E Bay St Jacksonville FL 32202",
    "addr:housenumber":"133",
    "addr:postcode":"32202",
    "addr:street":"E Bay St",
    "iso:country":"US",
    "sg:address":"133 E Bay St",
    "sg:city":"Jacksonville",
    "sg:classifiers":[
        {
            "category":"Banks & Credit Unions",
            "subcategory":"Bank",
            "type":"Services"
        }
    ],
    "sg:phone":"+1 904 353 0201",
    "sg:postcode":"32202",
    "sg:province":"FL",
    "sg:tags":[
        "loan"
    ],
    "wof:name":"Florida Investor Loans",
    "wof:placetype":"venue"
},
  "geometry": {"coordinates":[-81.6558,30.325846],"type":"Point"}
}