{
  "type": "Feature",
  "properties": {
    "iso:country":"US",
    "sg:address":"283 Cranes Roost Blvd Ste 111",
    "sg:city":"Altamonte Springs",
    "sg:classifiers":[
        {
            "category":"Personal",
            "type":"Services"
        }
    ],
    "sg:phone":"+1 407 218 5841",
    "sg:postcode":"32701",
    "sg:province":"FL",
    "sg:tags":[
        "local"
    ],
    "sg:website":"www.elitesingleprofessionals.com/",
    "wof:name":"Elite Introductions and Matchmaking",
    "wof:placetype":"venue"
},
  "geometry": {"coordinates":[-81.38387400000001,28.664964],"type":"Point"}
}