{
  "type": "Feature",
  "properties": {
    "addr:full":"928 Porter Dr Largo FL 33771",
    "addr:housenumber":"928",
    "addr:postcode":"33771",
    "addr:street":"Porter Dr",
    "iso:country":"US",
    "sg:address":"928 Porter Dr",
    "sg:city":"Largo",
    "sg:classifiers":[
        {
            "category":"Building & Trades",
            "subcategory":"Construction",
            "type":"Services"
        }
    ],
    "sg:phone":"+1 727 538 4963",
    "sg:postcode":"33771",
    "sg:province":"FL",
    "sg:tags":[
        "house"
    ],
    "wof:name":"Aldrich Construction and Dev",
    "wof:placetype":"venue"
},
  "geometry": {"coordinates":[-82.75787699999999,27.924514],"type":"Point"}
}