{
  "type": "Feature",
  "properties": {
    "addr:full":"8701 S Orange Ave Orlando FL 32824",
    "addr:housenumber":"8701",
    "addr:postcode":"32824",
    "addr:street":"S Orange Ave",
    "iso:country":"US",
    "sg:address":"8701 S Orange Ave",
    "sg:city":"Orlando",
    "sg:classifiers":[
        {
            "category":"Restaurant",
            "type":"Food & Drink"
        }
    ],
    "sg:phone":"+1 407 858 9800",
    "sg:postcode":"32824",
    "sg:province":"FL",
    "sg:tags":[
        "house",
        "steak"
    ],
    "wof:name":"Gentlemans Club & Steakhouse",
    "wof:placetype":"venue"
},
  "geometry": {"coordinates":[-81.383511,28.365479],"type":"Point"}
}