{
  "type": "Feature",
  "properties": {
    "addr:full":"4429 Basswood St Milton FL 32583",
    "addr:housenumber":"4429",
    "addr:postcode":"32583",
    "addr:street":"Basswood St",
    "iso:country":"US",
    "sg:address":"4429 Basswood St",
    "sg:city":"Milton",
    "sg:classifiers":[
        {
            "category":"Bars & Pubs",
            "type":"Food & Drink"
        }
    ],
    "sg:phone":"+1 850 623 2672",
    "sg:postcode":"32583",
    "sg:province":"FL",
    "sg:tags":[
        "drinking"
    ],
    "wof:name":"Mickeys",
    "wof:placetype":"venue"
},
  "geometry": {"coordinates":[-87.058755,30.597416],"type":"Point"}
}