{
  "type": "Feature",
  "properties": {
    "iso:country":"US",
    "sg:address":"8340 Holly Hill Cove",
    "sg:city":"Jacksonville",
    "sg:classifiers":[
        {
            "category":"Freight",
            "type":"Transportation"
        }
    ],
    "sg:phone":"+1 904 783 0931",
    "sg:postcode":"32221",
    "sg:province":"FL",
    "sg:tags":[
        "operator",
        "trucking"
    ],
    "wof:name":"Merello Trucking Inc",
    "wof:placetype":"venue"
},
  "geometry": {"coordinates":[-81.78917199999999,30.310666],"type":"Point"}
}