{
  "type": "Feature",
  "properties": {
    "iso:country":"US",
    "sg:address":"1028 Bluejack Oak Dr",
    "sg:city":"Oviedo",
    "sg:classifiers":[
        {
            "category":"Building & Trades",
            "subcategory":"Construction",
            "type":"Services"
        }
    ],
    "sg:phone":"+1 407 977 3845",
    "sg:postcode":"32765",
    "sg:province":"FL",
    "sg:tags":[
        "home",
        "improvement"
    ],
    "wof:name":"Home Improvements Will Castend",
    "wof:placetype":"venue"
},
  "geometry": {"coordinates":[-81.19438599999999,28.649762],"type":"Point"}
}