{
  "type": "Feature",
  "properties": {
    "iso:country":"US",
    "sg:address":"410 S Lincoln Ave",
    "sg:city":"Clearwater",
    "sg:classifiers":[
        {
            "category":"Real Estate",
            "subcategory":"Architect",
            "type":"Services"
        }
    ],
    "sg:phone":"+1 727 461 2402",
    "sg:postcode":"33756",
    "sg:province":"FL",
    "sg:tags":[
        "architectural"
    ],
    "wof:name":"Peter Marich Architect Inc",
    "wof:placetype":"venue"
},
  "geometry": {"coordinates":[-82.785884,27.960921],"type":"Point"}
}