{
  "type": "Feature",
  "properties": {
    "iso:country":"US",
    "sg:address":"1596 Old Titusville Rd",
    "sg:city":"Deltona",
    "sg:classifiers":[
        {
            "category":"Professional",
            "type":"Services"
        }
    ],
    "sg:phone":"+1 386 860 2240",
    "sg:postcode":"32725",
    "sg:province":"FL",
    "sg:tags":[
        "transportation"
    ],
    "wof:name":"Clr Logistics Inc",
    "wof:placetype":"venue"
},
  "geometry": {"coordinates":[-81.227834,28.86363],"type":"Point"}
}