{
  "type": "Feature",
  "properties": {
    "addr:full":"11422 SW 87th Ter Miami FL 33173",
    "addr:housenumber":"11422",
    "addr:postcode":"33173",
    "addr:street":"Sw 87Th Ter",
    "iso:country":"US",
    "sg:address":"11422 SW 87th Ter",
    "sg:city":"Miami",
    "sg:classifiers":[
        {
            "category":"Wholesale",
            "subcategory":"Non-durable Goods",
            "type":"Manufacturing & Wholesale Goods"
        }
    ],
    "sg:phone":"+1 305 275 0090",
    "sg:postcode":"33173",
    "sg:province":"FL",
    "wof:name":"Freebird Enterprises Inc",
    "wof:placetype":"venue"
},
  "geometry": {"coordinates":[-80.377972,25.687061],"type":"Point"}
}