{
  "type": "Feature",
  "properties": {
    "iso:country":"US",
    "sg:address":"3945 Fiscal Ct",
    "sg:city":"Riviera Beach",
    "sg:classifiers":[
        {
            "category":"Retail",
            "subcategory":"Auto Repair",
            "type":"Services"
        }
    ],
    "sg:phone":"+1 561 840 1066",
    "sg:postcode":"33404",
    "sg:province":"FL",
    "sg:tags":[
        "truck"
    ],
    "wof:name":"Freightliner Trucks-Florida",
    "wof:placetype":"venue"
},
  "geometry": {"coordinates":[-80.096929,26.796221],"type":"Point"}
}