{
  "type": "Feature",
  "properties": {
    "iso:country":"US",
    "sg:address":"8320 NW 10th St",
    "sg:city":"Miami",
    "sg:classifiers":[
        {
            "category":"Building & Trades",
            "subcategory":"Construction",
            "type":"Services"
        }
    ],
    "sg:phone":"+1 786 271 2092",
    "sg:postcode":"33126",
    "sg:province":"FL",
    "sg:tags":[
        "floor",
        "laying",
        "contractor"
    ],
    "wof:name":"A and B Wood Floors LLC",
    "wof:placetype":"venue"
},
  "geometry": {"coordinates":[-80.32981700000001,25.780462],"type":"Point"}
}