{
  "type": "Feature",
  "properties": {
    "addr:full":"22214 Co Rd 561 Astatula FL 34705",
    "addr:housenumber":"22214",
    "addr:postcode":"34705",
    "addr:street":"Co Rd 561",
    "iso:country":"US",
    "sg:address":"22214 Co Rd 561",
    "sg:city":"Astatula",
    "sg:classifiers":[
        {
            "category":"Wholesale",
            "subcategory":"Machinery & Supplies",
            "type":"Manufacturing & Wholesale Goods"
        }
    ],
    "sg:phone":"+1 352 394 2017",
    "sg:postcode":"34705",
    "sg:province":"FL",
    "sg:tags":[
        "equipment",
        "industrial"
    ],
    "wof:name":"Dougs Paint and Pressure Wshg",
    "wof:placetype":"venue"
},
  "geometry": {"coordinates":[-81.737408,28.666856],"type":"Point"}
}