{
  "type": "Feature",
  "properties": {
    "iso:country":"US",
    "sg:address":"2499 Founder St",
    "sg:city":"Deltona",
    "sg:classifiers":[
        {
            "category":"Shopping",
            "subcategory":"Computers & Home Electronics",
            "type":"Retail Goods"
        }
    ],
    "sg:phone":"+1 386 789 5406",
    "sg:postcode":"32738",
    "sg:province":"FL",
    "wof:name":"Macarthurs Computer Works",
    "wof:placetype":"venue"
},
  "geometry": {"coordinates":[-81.19946,28.946977],"type":"Point"}
}