{
  "type": "Feature",
  "properties": {
    "iso:country":"US",
    "sg:address":"1661 Cheyenne Trl",
    "sg:city":"Maitland",
    "sg:classifiers":[
        {
            "category":"Shopping",
            "type":"Retail Goods"
        }
    ],
    "sg:phone":"+1 407 645 5123",
    "sg:postcode":"32751",
    "sg:province":"FL",
    "sg:tags":[
        "merchandise"
    ],
    "wof:name":"Lynette Gray",
    "wof:placetype":"venue"
},
  "geometry": {"coordinates":[-81.34974099999999,28.631191],"type":"Point"}
}