{
  "type": "Feature",
  "properties": {
    "iso:country":"US",
    "sg:address":"695 E 9th St",
    "sg:city":"Hialeah",
    "sg:classifiers":[
        {
            "category":"Retail",
            "subcategory":"Veterinary Services",
            "type":"Services"
        }
    ],
    "sg:phone":"+1 305 884 8973",
    "sg:postcode":"33010",
    "sg:province":"FL",
    "wof:name":"Perfecto Q Vidal",
    "wof:placetype":"venue"
},
  "geometry": {"coordinates":[-80.26678800000001,25.830564],"type":"Point"}
}