{
  "type": "Feature",
  "properties": {
    "addr:full":"8238 NW South River Dr Medley FL 33166",
    "addr:housenumber":"8238",
    "addr:postcode":"33166",
    "addr:street":"Nw South River Dr",
    "iso:country":"US",
    "sg:address":"8238 NW South River Dr",
    "sg:city":"Medley",
    "sg:classifiers":[
        {
            "category":"Wholesale",
            "subcategory":"Medical Equipment & Supplies",
            "type":"Manufacturing & Wholesale Goods"
        }
    ],
    "sg:phone":"+1 305 883 8244",
    "sg:postcode":"33166",
    "sg:province":"FL",
    "sg:tags":[
        "physician",
        "surgeon"
    ],
    "wof:name":"Canaan Medical Supply Inc",
    "wof:placetype":"venue"
},
  "geometry": {"coordinates":[-80.317612,25.849425],"type":"Point"}
}