{
  "type": "Feature",
  "properties": {
    "addr:full":"3407 N W St Pensacola FL 32505",
    "addr:housenumber":"3407",
    "addr:postcode":"32505",
    "addr:street":"N W St",
    "iso:country":"US",
    "sg:address":"3407 N W St",
    "sg:city":"Pensacola",
    "sg:classifiers":[
        {
            "category":"Building & Trades",
            "subcategory":"Construction",
            "type":"Services"
        }
    ],
    "sg:phone":"+1 850 430 4307",
    "sg:postcode":"32505",
    "sg:province":"FL",
    "sg:tags":[
        "general",
        "contractor"
    ],
    "wof:name":"Biggs Green Constr Svc Inc",
    "wof:placetype":"venue"
},
  "geometry": {"coordinates":[-87.249376,30.447202],"type":"Point"}
}