{
  "type": "Feature",
  "properties": {
    "addr:full":"450 N Pine Island Rd Plantation FL 33324",
    "addr:housenumber":"450",
    "addr:postcode":"33324",
    "addr:street":"N Pine Island Rd",
    "iso:country":"US",
    "sg:address":"450 N Pine Island Rd",
    "sg:city":"Plantation",
    "sg:classifiers":[
        {
            "category":"Banks & Credit Unions",
            "subcategory":"Bank",
            "type":"Services"
        },
        {
            "category":"Banks & Credit Unions",
            "subcategory":"Financial Services",
            "type":"Services"
        }
    ],
    "sg:phone":"+1 954 693 9277",
    "sg:postcode":"33324",
    "sg:province":"FL",
    "sg:tags":[
        "commercial",
        "financing",
        "saving",
        "loan"
    ],
    "sg:website":"http://www.colonialbank.com",
    "wof:name":"BB&T",
    "wof:placetype":"venue"
},
  "geometry": {"coordinates":[-80.262756,26.125774],"type":"Point"}
}