{
  "type": "Feature",
  "properties": {
    "addr:full":"12506 Maverick Ct Tampa FL 33626",
    "addr:housenumber":"12506",
    "addr:postcode":"33626",
    "addr:street":"Maverick Ct",
    "iso:country":"US",
    "sg:address":"12506 Maverick Ct",
    "sg:city":"Tampa",
    "sg:classifiers":[
        {
            "category":"Professional",
            "subcategory":"Engineering",
            "type":"Services"
        }
    ],
    "sg:phone":"+1 727 804 5316",
    "sg:postcode":"33626",
    "sg:province":"FL",
    "sg:tags":[
        "engineer"
    ],
    "wof:name":"MSW Syst & Consulting Inc",
    "wof:placetype":"venue"
},
  "geometry": {"coordinates":[-82.635059,28.045581],"type":"Point"}
}