{
  "type": "Feature",
  "properties": {
    "addr:full":"2301 Maitland Center Pkwy Maitland FL 32751",
    "addr:housenumber":"2301",
    "addr:postcode":"32751",
    "addr:street":"Maitland Center Pkwy",
    "iso:country":"US",
    "sg:address":"2301 Maitland Center Pkwy",
    "sg:city":"Maitland",
    "sg:classifiers":[
        {
            "category":"Deli",
            "type":"Food & Drink"
        },
        {
            "category":"Food & Beverages",
            "subcategory":"Bakery",
            "type":"Retail Goods"
        }
    ],
    "sg:phone":"+1 407 660 3108",
    "sg:postcode":"32751",
    "sg:province":"FL",
    "sg:tags":[
        "sandwich"
    ],
    "wof:name":"New York Deli",
    "wof:placetype":"venue"
},
  "geometry": {"coordinates":[-81.391413,28.634368],"type":"Point"}
}