{
  "type": "Feature",
  "properties": {
    "iso:country":"US",
    "sg:address":"4400 NW 19th Ave",
    "sg:city":"Pompano Beach",
    "sg:classifiers":[
        {
            "category":"Professional",
            "subcategory":"Computer Services",
            "type":"Services"
        }
    ],
    "sg:phone":"+1 954 979 5077",
    "sg:postcode":"33064",
    "sg:province":"FL",
    "sg:tags":[
        "internet"
    ],
    "wof:name":"Sniper Marketing",
    "wof:placetype":"venue"
},
  "geometry": {"coordinates":[-80.149754,26.284506],"type":"Point"}
}