{
  "type": "Feature",
  "properties": {
    "iso:country":"US",
    "sg:address":"2783 Fitzgerald St",
    "sg:city":"Jacksonville",
    "sg:classifiers":[
        {
            "category":"Social Services",
            "subcategory":"Child Care",
            "type":"Services"
        }
    ],
    "sg:phone":"+1 904 387 3082",
    "sg:postcode":"32254",
    "sg:province":"FL",
    "wof:name":"Marcia's Daycare",
    "wof:placetype":"venue"
},
  "geometry": {"coordinates":[-81.698111,30.325502],"type":"Point"}
}