{
  "type": "Feature",
  "properties": {
    "iso:country":"US",
    "sg:address":"5917 Manatee Ave W",
    "sg:city":"Bradenton",
    "sg:classifiers":[
        {
            "category":"Food & Beverages",
            "subcategory":"Bakery",
            "type":"Retail Goods"
        }
    ],
    "sg:phone":"+1 941 794 0336",
    "sg:postcode":"34209",
    "sg:province":"FL",
    "sg:tags":[
        "bagel"
    ],
    "wof:name":"Manhattan Bagel",
    "wof:placetype":"venue"
},
  "geometry": {"coordinates":[-82.621255,27.496073],"type":"Point"}
}