{
  "type": "Feature",
  "properties": {
    "iso:country":"US",
    "sg:address":"3701 SW 47th Ave",
    "sg:city":"Davie",
    "sg:classifiers":[
        {
            "category":"Wholesale",
            "subcategory":"Durable Goods & Equipment",
            "type":"Manufacturing & Wholesale Goods"
        }
    ],
    "sg:phone":"+1 954 581 3677",
    "sg:postcode":"33314",
    "sg:province":"FL",
    "sg:tags":[
        "exporter"
    ],
    "wof:name":"Biomedical Unlimited",
    "wof:placetype":"venue"
},
  "geometry": {"coordinates":[-80.210114,26.067693],"type":"Point"}
}