{
  "type": "Feature",
  "properties": {
    "iso:country":"US",
    "sg:address":"205 Julia St",
    "sg:city":"Jacksonville",
    "sg:classifiers":[
        {
            "category":"Personal",
            "subcategory":"Barber",
            "type":"Services"
        }
    ],
    "sg:phone":"+1 904 356 5385",
    "sg:postcode":"32202",
    "sg:province":"FL",
    "sg:tags":[
        "shop"
    ],
    "wof:name":"Bank Barber Shop",
    "wof:placetype":"venue"
},
  "geometry": {"coordinates":[-81.661117,30.329302],"type":"Point"}
}