{
  "type": "Feature",
  "properties": {
    "iso:country":"US",
    "sg:address":"8050 Glenridge Loop W",
    "sg:city":"Lakeland",
    "sg:classifiers":[
        {
            "category":"Building & Trades",
            "subcategory":"Construction",
            "type":"Services"
        }
    ],
    "sg:phone":"+1 863 853 9862",
    "sg:postcode":"33809",
    "sg:province":"FL",
    "sg:tags":[
        "floor",
        "laying",
        "contractor"
    ],
    "wof:name":"Sircy Flooring Inc",
    "wof:placetype":"venue"
},
  "geometry": {"coordinates":[-81.953762,28.145065],"type":"Point"}
}