{
  "type": "Feature",
  "properties": {
    "iso:country":"US",
    "sg:address":"4813 Barbara Rd",
    "sg:city":"Tampa",
    "sg:classifiers":[
        {
            "category":"Building & Trades",
            "subcategory":"Construction",
            "type":"Services"
        }
    ],
    "sg:phone":"+1 813 635 9738",
    "sg:postcode":"33610",
    "sg:province":"FL",
    "sg:tags":[
        "carpentry",
        "contractor"
    ],
    "wof:name":"Wld Carpentry",
    "wof:placetype":"venue"
},
  "geometry": {"coordinates":[-82.343898,27.989185],"type":"Point"}
}