{
  "type": "Feature",
  "properties": {
    "iso:country":"US",
    "sg:address":"7534 University Blvd",
    "sg:city":"Winter Park",
    "sg:classifiers":[
        {
            "category":"Health Services",
            "subcategory":"Dentist",
            "type":"Services"
        }
    ],
    "sg:phone":"+1 407 672 0030",
    "sg:postcode":"32792",
    "sg:province":"FL",
    "sg:tags":[
        "orthodontist"
    ],
    "wof:name":"Central Florida Orthodontic Specialists",
    "wof:placetype":"venue"
},
  "geometry": {"coordinates":[-81.285301,28.5972],"type":"Point"}
}