{
  "type": "Feature",
  "properties": {
    "addr:full":"2505 NE 9 St Gainesville FL 32609",
    "addr:housenumber":"2505;9",
    "addr:postcode":"32609",
    "addr:street":"Ne",
    "iso:country":"US",
    "sg:address":"2505 NE 9 St",
    "sg:city":"Gainesville",
    "sg:classifiers":[
        {
            "category":"Organizations",
            "subcategory":"Community Association",
            "type":"Services"
        }
    ],
    "sg:phone":"+1 352 372 9200",
    "sg:postcode":"32609",
    "sg:province":"FL",
    "sg:tags":[
        "fraternal"
    ],
    "wof:name":"Masonic Lodge",
    "wof:placetype":"venue"
},
  "geometry": {"coordinates":[-82.314716,29.676061],"type":"Point"}
}