{
  "type": "Feature",
  "properties": {
    "iso:country":"US",
    "sg:address":"1525 51st Ave E",
    "sg:city":"Ellenton",
    "sg:classifiers":[
        {
            "category":"Bars & Pubs",
            "type":"Food & Drink"
        }
    ],
    "sg:menulink":"http://www.allmenus.com/fl/bradenton/36392-anna-maria-oyster-bar/menu/",
    "sg:phone":"+1 941 721 7773",
    "sg:postcode":"34222",
    "sg:province":"FL",
    "sg:tags":[
        "seafood",
        "american"
    ],
    "wof:name":"Anna Maria Oyster Bar",
    "wof:placetype":"venue"
},
  "geometry": {"coordinates":[-82.51309999999999,27.526954],"type":"Point"}
}