{
  "type": "Feature",
  "properties": {
    "addr:full":"705 Art Center Ave New Smyrna Beach FL 32168",
    "addr:housenumber":"705",
    "addr:postcode":"32168",
    "addr:street":"Art Center Ave",
    "iso:country":"US",
    "sg:address":"705 Art Center Ave",
    "sg:city":"New Smyrna Beach",
    "sg:classifiers":[
        {
            "category":"Manufacturing",
            "subcategory":"Signs",
            "type":"Manufacturing & Wholesale Goods"
        }
    ],
    "sg:phone":"+1 386 427 1278",
    "sg:postcode":"32168",
    "sg:province":"FL",
    "sg:tags":[
        "specialty",
        "mfg"
    ],
    "wof:name":"Coastline Whl Signs & Svcs LLC",
    "wof:placetype":"venue"
},
  "geometry": {"coordinates":[-80.959194,29.070363],"type":"Point"}
}