{
  "type": "Feature",
  "properties": {
    "addr:full":"6601 Lyons Rd Coconut Creek FL 33073",
    "addr:housenumber":"6601",
    "addr:postcode":"33073",
    "addr:street":"Lyons Rd",
    "iso:country":"US",
    "sg:address":"6601 Lyons Rd",
    "sg:city":"Coconut Creek",
    "sg:classifiers":[
        {
            "category":"Wholesale",
            "subcategory":"Non-durable Goods",
            "type":"Manufacturing & Wholesale Goods"
        }
    ],
    "sg:phone":"+1 954 570 6165",
    "sg:postcode":"33073",
    "sg:province":"FL",
    "sg:tags":[
        "merchandise",
        "general"
    ],
    "wof:name":"Richardson Co",
    "wof:placetype":"venue"
},
  "geometry": {"coordinates":[-80.18662,26.311832],"type":"Point"}
}