{
  "type": "Feature",
  "properties": {
    "iso:country":"US",
    "sg:address":"3661 NW 19th Ter",
    "sg:city":"Miami",
    "sg:classifiers":[
        {
            "category":"Local Transit",
            "type":"Transportation"
        }
    ],
    "sg:phone":"+1 305 634 4905",
    "sg:postcode":"33125",
    "sg:province":"FL",
    "sg:tags":[
        "suburban"
    ],
    "wof:name":"I & M Peraza Inc",
    "wof:placetype":"venue"
},
  "geometry": {"coordinates":[-80.25487,25.793232],"type":"Point"}
}