{
  "type": "Feature",
  "properties": {
    "addr:full":"17107 Pines Blvd Hollywood FL 33027",
    "addr:housenumber":"17107",
    "addr:postcode":"33027",
    "addr:street":"Pines Blvd",
    "iso:country":"US",
    "sg:address":"17107 Pines Blvd",
    "sg:city":"Hollywood",
    "sg:classifiers":[
        {
            "category":"Real Estate",
            "subcategory":"Real Estate Agent",
            "type":"Services"
        }
    ],
    "sg:phone":"+1 954 432 0222",
    "sg:postcode":"33027",
    "sg:province":"FL",
    "sg:tags":[
        "realtor"
    ],
    "wof:name":"Re/Max",
    "wof:placetype":"venue"
},
  "geometry": {"coordinates":[-80.37472,26.007806],"type":"Point"}
}