{
  "type": "Feature",
  "properties": {
    "addr:full":"4223 US Hwy 90 Milton FL 32571",
    "addr:housenumber":"4223",
    "addr:postcode":"32571",
    "addr:street":"Us Hwy 90",
    "iso:country":"US",
    "sg:address":"4223 US Hwy 90",
    "sg:city":"Milton",
    "sg:classifiers":[
        {
            "category":"Government",
            "subcategory":"Police Station",
            "type":"Public Place"
        }
    ],
    "sg:phone":"+1 850 995 1985",
    "sg:postcode":"32571",
    "sg:province":"FL",
    "sg:tags":[
        "sheriff"
    ],
    "wof:name":"Santa Rosa County Sheriff",
    "wof:placetype":"venue"
},
  "geometry": {"coordinates":[-87.15232399999999,30.602639],"type":"Point"}
}