{
  "type": "Feature",
  "properties": {
    "addr:full":"12241 S Dixie Hwy Miami FL 33156",
    "addr:housenumber":"12241",
    "addr:postcode":"33156",
    "addr:street":"S Dixie Hwy",
    "iso:country":"US",
    "sg:address":"12241 S Dixie Hwy",
    "sg:city":"Miami",
    "sg:classifiers":[
        {
            "category":"Real Estate",
            "subcategory":"Real Estate Services",
            "type":"Services"
        }
    ],
    "sg:phone":"+1 305 251 2484",
    "sg:postcode":"33156",
    "sg:province":"FL",
    "wof:name":"Smith Realty Rl Est",
    "wof:placetype":"venue"
},
  "geometry": {"coordinates":[-80.327904,25.6567],"type":"Point"}
}