{
  "type": "Feature",
  "properties": {
    "addr:full":"12031 US Hwy 19 Hudson FL 34667",
    "addr:housenumber":"12031",
    "addr:postcode":"34667",
    "addr:street":"Us Hwy 19",
    "iso:country":"US",
    "sg:address":"12031 US Hwy 19",
    "sg:city":"Hudson",
    "sg:classifiers":[
        {
            "category":"Food & Beverages",
            "subcategory":"Groceries & Convenience Stores",
            "type":"Retail Goods"
        }
    ],
    "sg:phone":"+1 727 863 3173",
    "sg:postcode":"34667",
    "sg:province":"FL",
    "sg:tags":[
        "florist",
        "bakery",
        "grocer"
    ],
    "wof:name":"Publix Super Market 295",
    "wof:placetype":"venue"
},
  "geometry": {"coordinates":[-82.699376,28.335167],"type":"Point"}
}