{
  "type": "Feature",
  "properties": {
    "addr:full":"7819 Graves Rd Pensacola FL 32514",
    "addr:housenumber":"7819",
    "addr:postcode":"32514",
    "addr:street":"Graves Rd",
    "iso:country":"US",
    "sg:address":"7819 Graves Rd",
    "sg:city":"Pensacola",
    "sg:classifiers":[
        {
            "category":"Wholesale",
            "subcategory":"Non-durable Goods",
            "type":"Manufacturing & Wholesale Goods"
        }
    ],
    "sg:phone":"+1 850 479 3094",
    "sg:postcode":"32514",
    "sg:province":"FL",
    "sg:website":"www.lifeforceonline.com",
    "wof:name":"Lifeforce Glass Inc",
    "wof:placetype":"venue"
},
  "geometry": {"coordinates":[-87.214521,30.507344],"type":"Point"}
}