{
  "type": "Feature",
  "properties": {
    "addr:full":"5716 S Bayberry Ln Fort Lauderdale FL 33319",
    "addr:housenumber":"5716",
    "addr:postcode":"33319",
    "addr:street":"S Bayberry Ln",
    "iso:country":"US",
    "sg:address":"5716 S Bayberry Ln",
    "sg:city":"Fort Lauderdale",
    "sg:classifiers":[
        {
            "category":"Organizations",
            "subcategory":"Membership Organization",
            "type":"Services"
        }
    ],
    "sg:phone":"+1 954 730 3250",
    "sg:postcode":"33319",
    "sg:province":"FL",
    "wof:name":"Stan Sudler & Assn",
    "wof:placetype":"venue"
},
  "geometry": {"coordinates":[-80.228099,26.188856],"type":"Point"}
}