{
  "type": "Feature",
  "properties": {
    "iso:country":"US",
    "sg:address":"21 Suntree Pl",
    "sg:city":"Melbourne",
    "sg:classifiers":[
        {
            "category":"Health Services",
            "subcategory":"Hospital",
            "type":"Services"
        },
        {
            "category":"Health Services",
            "subcategory":"Doctor",
            "type":"Services"
        }
    ],
    "sg:phone":"+1 321 757 0577",
    "sg:postcode":"32940",
    "sg:province":"FL",
    "sg:tags":[
        "physician",
        "surgeon"
    ],
    "wof:name":"Brevard Pain Management Inc",
    "wof:placetype":"venue"
},
  "geometry": {"coordinates":[-80.68002,28.228462],"type":"Point"}
}