{
  "type": "Feature",
  "properties": {
    "iso:country":"US",
    "sg:address":"2000 E Oakland Park Blvd",
    "sg:city":"Fort Lauderdale",
    "sg:classifiers":[
        {
            "category":"Professional",
            "subcategory":"Advertising",
            "type":"Services"
        }
    ],
    "sg:phone":"+1 954 565 3379",
    "sg:postcode":"33306",
    "sg:province":"FL",
    "sg:tags":[
        "agency"
    ],
    "wof:name":"Leftfield Advertising LLC",
    "wof:placetype":"venue"
},
  "geometry": {"coordinates":[-80.120014,26.167181],"type":"Point"}
}