{
  "type": "Feature",
  "properties": {
    "iso:country":"US",
    "sg:address":"6380 S Dixie Hwy",
    "sg:city":"South Miami",
    "sg:classifiers":[
        {
            "category":"Retail",
            "subcategory":"Veterinary Services",
            "type":"Services"
        }
    ],
    "sg:phone":"+1 305 666 7387",
    "sg:postcode":"33143",
    "sg:province":"FL",
    "sg:tags":[
        "veterinarian"
    ],
    "wof:name":"South Dade Animal Hospital",
    "wof:placetype":"venue"
},
  "geometry": {"coordinates":[-80.2967,25.698601],"type":"Point"}
}