{
  "type": "Feature",
  "properties": {
    "addr:full":"7527 NW 22nd Ave Miami FL 33147",
    "addr:housenumber":"7527",
    "addr:postcode":"33147",
    "addr:street":"Nw 22Nd Ave",
    "iso:country":"US",
    "sg:address":"7527 NW 22nd Ave",
    "sg:city":"Miami",
    "sg:classifiers":[
        {
            "category":"Personal",
            "subcategory":"Barber",
            "type":"Services"
        }
    ],
    "sg:phone":"+1 305 691 4046",
    "sg:postcode":"33147",
    "sg:province":"FL",
    "wof:name":"Family Unisex Barber Shop",
    "wof:placetype":"venue"
},
  "geometry": {"coordinates":[-80.233411,25.843728],"type":"Point"}
}