{
  "type": "Feature",
  "properties": {
    "addr:full":"17479 Sapp Pl Jupiter FL 33458",
    "addr:housenumber":"17479",
    "addr:postcode":"33458",
    "addr:street":"Sapp Pl",
    "iso:country":"US",
    "sg:address":"17479 Sapp Pl",
    "sg:city":"Jupiter",
    "sg:classifiers":[
        {
            "category":"Food & Beverages",
            "subcategory":"Specialty",
            "type":"Retail Goods"
        }
    ],
    "sg:phone":"+1 561 747 9078",
    "sg:postcode":"33458",
    "sg:province":"FL",
    "wof:name":"Diamite Herbal Products",
    "wof:placetype":"venue"
},
  "geometry": {"coordinates":[-80.137001,26.932878],"type":"Point"}
}