{
  "type": "Feature",
  "properties": {
    "addr:full":"670 N Orlando Ave Ste 201 Maitland FL 32751",
    "addr:housenumber":"670",
    "addr:postcode":"32751",
    "addr:street":"N Orlando Ave Ste 201",
    "iso:country":"US",
    "sg:address":"670 N Orlando Ave Ste 201",
    "sg:city":"Maitland",
    "sg:classifiers":[
        {
            "category":"Personal",
            "subcategory":"Beauty Salon",
            "type":"Services"
        }
    ],
    "sg:phone":"+1 407 629 5000",
    "sg:postcode":"32751",
    "sg:province":"FL",
    "sg:tags":[
        "hair"
    ],
    "wof:name":"Heads Salon Edward T",
    "wof:placetype":"venue"
},
  "geometry": {"coordinates":[-81.362396,28.6327],"type":"Point"}
}