{
  "type": "Feature",
  "properties": {
    "addr:full":"705 E 9th St Hialeah FL 33010",
    "addr:housenumber":"705",
    "addr:postcode":"33010",
    "addr:street":"E 9Th St",
    "iso:country":"US",
    "sg:address":"705 E 9th St",
    "sg:city":"Hialeah",
    "sg:classifiers":[
        {
            "category":"Restaurant",
            "type":"Food & Drink"
        }
    ],
    "sg:phone":"+1 305 884 1846",
    "sg:postcode":"33010",
    "sg:province":"FL",
    "wof:name":"Cafeteria Restaurant LA Esprtn",
    "wof:placetype":"venue"
},
  "geometry": {"coordinates":[-80.266869,25.830562],"type":"Point"}
}