{
  "type": "Feature",
  "properties": {
    "iso:country":"US",
    "sg:address":"6316 Willow St",
    "sg:city":"Zellwood",
    "sg:classifiers":[
        {
            "category":"Organizations",
            "subcategory":"Religious Organization",
            "type":"Services"
        }
    ],
    "sg:phone":"+1 352 383 9400",
    "sg:postcode":"32757",
    "sg:province":"FL",
    "sg:tags":[
        "church"
    ],
    "wof:name":"First John Holiness",
    "wof:placetype":"venue"
},
  "geometry": {"coordinates":[-81.614042,28.736249],"type":"Point"}
}