{
  "type": "Feature",
  "properties": {
    "iso:country":"US",
    "sg:address":"4003 Broadway",
    "sg:city":"West Palm Beach",
    "sg:classifiers":[
        {
            "category":"Food & Beverages",
            "subcategory":"Groceries & Convenience Stores",
            "type":"Retail Goods"
        }
    ],
    "sg:phone":"+1 561 845 6772",
    "sg:postcode":"33407",
    "sg:province":"FL",
    "sg:tags":[
        "grocer"
    ],
    "wof:name":"Cheers Supermarket",
    "wof:placetype":"venue"
},
  "geometry": {"coordinates":[-80.056605,26.748925],"type":"Point"}
}