{
  "type": "Feature",
  "properties": {
    "addr:full":"13309 41st Ln N West Palm Beach FL 33411",
    "addr:housenumber":"13309",
    "addr:postcode":"33411",
    "addr:street":"41St Ln N",
    "iso:country":"US",
    "sg:address":"13309 41st Ln N",
    "sg:city":"West Palm Beach",
    "sg:classifiers":[
        {
            "category":"Building & Trades",
            "subcategory":"Construction",
            "type":"Services"
        }
    ],
    "sg:phone":"+1 561 793 0476",
    "sg:postcode":"33411",
    "sg:province":"FL",
    "sg:tags":[
        "contractor"
    ],
    "wof:name":"All Phase Inc",
    "wof:placetype":"venue"
},
  "geometry": {"coordinates":[-80.25006500000001,26.738383],"type":"Point"}
}