{
  "type": "Feature",
  "properties": {
    "iso:country":"US",
    "sg:address":"2192 NW 21st St",
    "sg:city":"Miami",
    "sg:classifiers":[
        {
            "category":"Manufacturing",
            "subcategory":"Apparel",
            "type":"Manufacturing & Wholesale Goods"
        }
    ],
    "sg:phone":"+1 305 325 0147",
    "sg:postcode":"33142",
    "sg:province":"FL",
    "sg:tags":[
        "clothing-men's-wholesale",
        "manufacturer"
    ],
    "wof:name":"Jenda Corp",
    "wof:placetype":"venue"
},
  "geometry": {"coordinates":[-80.231381,25.795444],"type":"Point"}
}