{
  "type": "Feature",
  "properties": {
    "addr:full":"5845 SW 26th St Miami FL 33155",
    "addr:housenumber":"5845",
    "addr:postcode":"33155",
    "addr:street":"Sw 26Th St",
    "iso:country":"US",
    "sg:address":"5845 SW 26th St",
    "sg:city":"Miami",
    "sg:classifiers":[
        {
            "category":"Professional",
            "subcategory":"Lawyer & Legal Services",
            "type":"Services"
        }
    ],
    "sg:phone":"+1 305 663 3009",
    "sg:postcode":"33155",
    "sg:province":"FL",
    "sg:tags":[
        "notary"
    ],
    "wof:name":"Associate Interpreters Inc",
    "wof:placetype":"venue"
},
  "geometry": {"coordinates":[-80.29021400000001,25.746633],"type":"Point"}
}