{
  "type": "Feature",
  "properties": {
    "addr:full":"315 Citrona Dr Fernandina Beach FL 32034",
    "addr:housenumber":"315",
    "addr:postcode":"32034",
    "addr:street":"Citrona Dr",
    "iso:country":"US",
    "sg:address":"315 Citrona Dr",
    "sg:city":"Fernandina Beach",
    "sg:classifiers":[
        {
            "category":"Education",
            "subcategory":"School",
            "type":"Public Place"
        }
    ],
    "sg:phone":"+1 904 321 5865",
    "sg:postcode":"32034",
    "sg:province":"FL",
    "sg:tags":[
        "middle"
    ],
    "wof:name":"Fernandina Beach Middle School",
    "wof:placetype":"venue"
},
  "geometry": {"coordinates":[-81.444073,30.66508],"type":"Point"}
}