{
  "type": "Feature",
  "properties": {
    "addr:full":"3950 W Newberry Rd Gainesville FL 32607",
    "addr:housenumber":"3950",
    "addr:postcode":"32607",
    "addr:street":"W Newberry Rd",
    "iso:country":"US",
    "sg:address":"3950 W Newberry Rd",
    "sg:city":"Gainesville",
    "sg:classifiers":[
        {
            "category":"Autos & Motor Vehicles",
            "subcategory":"Auto Supplies",
            "type":"Retail Goods"
        },
        {
            "category":"Retail",
            "subcategory":"Auto Repair",
            "type":"Services"
        }
    ],
    "sg:phone":"+1 352 371 1771",
    "sg:postcode":"32607",
    "sg:province":"FL",
    "sg:tags":[
        "wheel",
        "tire",
        "retread",
        "balancing",
        "wheels-aligning",
        "recap",
        "brake"
    ],
    "sg:website":"http://www.tirekingdom.com",
    "wof:name":"Tire Kingdom",
    "wof:placetype":"venue"
},
  "geometry": {"coordinates":[-82.36444899999999,29.650435],"type":"Point"}
}