{
  "type": "Feature",
  "properties": {
    "iso:country":"US",
    "sg:address":"3750 US Hwy 27",
    "sg:city":"Sebring",
    "sg:classifiers":[
        {
            "category":"Restaurant",
            "type":"Food & Drink"
        }
    ],
    "sg:phone":"+1 863 386 1328",
    "sg:postcode":"33870",
    "sg:province":"FL",
    "wof:name":"Thai House",
    "wof:placetype":"venue"
},
  "geometry": {"coordinates":[-81.43499,27.465112],"type":"Point"}
}