{
  "type": "Feature",
  "properties": {
    "iso:country":"US",
    "sg:address":"150 SW 13th Ave",
    "sg:city":"Miami",
    "sg:classifiers":[
        {
            "category":"Place Of Worship",
            "subcategory":"Church",
            "type":"Public Place"
        },
        {
            "category":"Organizations",
            "subcategory":"Religious Organization",
            "type":"Services"
        }
    ],
    "sg:phone":"+1 305 643 2711",
    "sg:postcode":"33135",
    "sg:province":"FL",
    "sg:tags":[
        "churches-episcopal"
    ],
    "wof:name":"Holy Comforter Episcopal Church",
    "wof:placetype":"venue"
},
  "geometry": {"coordinates":[-80.21639999999999,25.7721],"type":"Point"}
}