{
  "type": "Feature",
  "properties": {
    "addr:full":"19575 State Rd 7 Boca Raton FL 33498",
    "addr:housenumber":"19575",
    "addr:postcode":"33498",
    "addr:street":"State Rd 7",
    "iso:country":"US",
    "sg:address":"19575 State Rd 7",
    "sg:city":"Boca Raton",
    "sg:classifiers":[
        {
            "category":"Professional",
            "subcategory":"Business Services",
            "type":"Services"
        }
    ],
    "sg:phone":"+1 561 883 7777",
    "sg:postcode":"33498",
    "sg:province":"FL",
    "sg:tags":[
        "embroidery"
    ],
    "wof:name":"Embroidme",
    "wof:placetype":"venue"
},
  "geometry": {"coordinates":[-80.203715,26.387176],"type":"Point"}
}