{
  "type": "Feature",
  "properties": {
    "iso:country":"US",
    "sg:address":"10099 Seminole Blvd # A3",
    "sg:city":"Seminole",
    "sg:classifiers":[
        {
            "category":"Health Services",
            "subcategory":"Doctor",
            "type":"Services"
        }
    ],
    "sg:phone":"+1 727 391 0158",
    "sg:postcode":"33772",
    "sg:province":"FL",
    "sg:tags":[
        "physician",
        "pediatrics-emergency",
        "pediatrics",
        "surgeons",
        "medicine",
        "surgeon"
    ],
    "wof:name":"Pediatric Health Alliance",
    "wof:placetype":"venue"
},
  "geometry": {"coordinates":[-82.786942,27.864177],"type":"Point"}
}