{
  "type": "Feature",
  "properties": {
    "addr:full":"8850 SW 14 Ave Gainesville FL 32607",
    "addr:housenumber":"8850",
    "addr:postcode":"32607",
    "addr:street":"Sw 14 Ave",
    "iso:country":"US",
    "sg:address":"8850 SW 14 Ave",
    "sg:city":"Gainesville",
    "sg:classifiers":[
        {
            "category":"Professional",
            "subcategory":"Art Services",
            "type":"Services"
        }
    ],
    "sg:phone":"+1 352 335 0038",
    "sg:postcode":"32607",
    "sg:province":"FL",
    "sg:tags":[
        "photographer"
    ],
    "wof:name":"T J Morrissey Photography",
    "wof:placetype":"venue"
},
  "geometry": {"coordinates":[-82.440404,29.63954],"type":"Point"}
}