{
  "type": "Feature",
  "properties": {
    "addr:full":"1145 Washington Ave Miami FL 33139",
    "addr:housenumber":"1145",
    "addr:postcode":"33139",
    "addr:street":"Washington Ave",
    "iso:country":"US",
    "sg:address":"1145 Washington Ave",
    "sg:city":"Miami",
    "sg:classifiers":[
        {
            "category":"Shopping",
            "subcategory":"Optical Goods",
            "type":"Retail Goods"
        }
    ],
    "sg:phone":"+1 305 534 4500",
    "sg:postcode":"33139",
    "sg:province":"FL",
    "wof:name":"Eyemax Inc",
    "wof:placetype":"venue"
},
  "geometry": {"coordinates":[-80.132338,25.782487],"type":"Point"}
}