{
  "type": "Feature",
  "properties": {
    "iso:country":"US",
    "sg:address":"119 S Indiana Ave",
    "sg:city":"Englewood",
    "sg:classifiers":[
        {
            "category":"Personal",
            "subcategory":"Beauty Salon",
            "type":"Services"
        }
    ],
    "sg:phone":"+1 941 460 0526",
    "sg:postcode":"34223",
    "sg:province":"FL",
    "sg:tags":[
        "manicuring"
    ],
    "wof:name":"Tj Nails",
    "wof:placetype":"venue"
},
  "geometry": {"coordinates":[-82.352981,26.95966],"type":"Point"}
}