{
  "type": "Feature",
  "properties": {
    "iso:country":"US",
    "sg:address":"6901 Collins Ave",
    "sg:city":"Miami Beach",
    "sg:classifiers":[
        {
            "category":"Building & Trades",
            "subcategory":"Construction",
            "type":"Services"
        }
    ],
    "sg:phone":"+1 305 993 0030",
    "sg:postcode":"33141",
    "sg:province":"FL",
    "sg:tags":[
        "contractor"
    ],
    "wof:name":"W Sg Developement Company",
    "wof:placetype":"venue"
},
  "geometry": {"coordinates":[-80.12025800000001,25.854286],"type":"Point"}
}