{
  "type": "Feature",
  "properties": {
    "iso:country":"US",
    "sg:address":"777 Main St",
    "sg:city":"Daytona Beach",
    "sg:classifiers":[
        {
            "category":"Wholesale",
            "subcategory":"Durable Goods & Equipment",
            "type":"Manufacturing & Wholesale Goods"
        }
    ],
    "sg:phone":"+1 386 252 6434",
    "sg:postcode":"32118",
    "sg:province":"FL",
    "sg:tags":[
        "exporter"
    ],
    "sg:website":"www.bikerdesign.com",
    "wof:name":"Biker Design Inc",
    "wof:placetype":"venue"
},
  "geometry": {"coordinates":[-81.00967,29.22624],"type":"Point"}
}