{
  "type": "Feature",
  "properties": {
    "addr:full":"8950 State Road 52 Hudson FL 34667",
    "addr:housenumber":"8950",
    "addr:postcode":"34667",
    "addr:street":"State Road 52",
    "iso:country":"US",
    "sg:address":"8950 State Road 52",
    "sg:city":"Hudson",
    "sg:phone":"+1 727 863 2771",
    "sg:postcode":"34667",
    "sg:province":"FL",
    "wof:name":"Dr Musgrave's Acupet Veterinary Services",
    "wof:placetype":"venue"
},
  "geometry": {"coordinates":[-82.667552,28.331027],"type":"Point"}
}