{
  "type": "Feature",
  "properties": {
    "addr:full":"9684 Pines Blvd Pembroke Pines FL 33024",
    "addr:housenumber":"9684",
    "addr:postcode":"33024",
    "addr:street":"Pines Blvd",
    "iso:country":"US",
    "sg:address":"9684 Pines Blvd",
    "sg:city":"Pembroke Pines",
    "sg:classifiers":[
        {
            "category":"Health Services",
            "subcategory":"Chiropractor",
            "type":"Services"
        }
    ],
    "sg:phone":"+1 954 438 1212",
    "sg:postcode":"33024",
    "sg:province":"FL",
    "wof:name":"Driano Family Chiro & Natural",
    "wof:placetype":"venue"
},
  "geometry": {"coordinates":[-80.274147,26.008402],"type":"Point"}
}