{
  "type": "Feature",
  "properties": {
    "iso:country":"US",
    "sg:address":"1311 N Orange Ave",
    "sg:city":"Orlando",
    "sg:classifiers":[
        {
            "category":"Retail",
            "subcategory":"Auto Repair",
            "type":"Services"
        }
    ],
    "sg:phone":"+1 407 898 2351",
    "sg:postcode":"32804",
    "sg:province":"FL",
    "sg:tags":[
        "body",
        "automobile",
        "top",
        "upholstery"
    ],
    "wof:name":"Orlando Auto Upholstery Inc",
    "wof:placetype":"venue"
},
  "geometry": {"coordinates":[-81.37294,28.562678],"type":"Point"}
}