{
  "type": "Feature",
  "properties": {
    "addr:full":"2240 Alton Rd Deltona FL 32738",
    "addr:housenumber":"2240",
    "addr:postcode":"32738",
    "addr:street":"Alton Rd",
    "iso:country":"US",
    "sg:address":"2240 Alton Rd",
    "sg:city":"Deltona",
    "sg:classifiers":[
        {
            "category":"Building & Trades",
            "subcategory":"Construction",
            "type":"Services"
        }
    ],
    "sg:phone":"+1 386 532 5256",
    "sg:postcode":"32738",
    "sg:province":"FL",
    "sg:tags":[
        "house"
    ],
    "wof:name":"Budget Home Repair & Imprvs",
    "wof:placetype":"venue"
},
  "geometry": {"coordinates":[-81.206593,28.916019],"type":"Point"}
}