{
  "type": "Feature",
  "properties": {
    "addr:full":"4641 SW 42nd Ter Fort Lauderdale FL 33314",
    "addr:housenumber":"4641",
    "addr:postcode":"33314",
    "addr:street":"Sw 42Nd Ter",
    "iso:country":"US",
    "sg:address":"4641 SW 42nd Ter",
    "sg:city":"Fort Lauderdale",
    "sg:classifiers":[
        {
            "category":"Autos & Motor Vehicles",
            "subcategory":"Boat Sales",
            "type":"Retail Goods"
        }
    ],
    "sg:phone":"+1 954 581 5255",
    "sg:postcode":"33314",
    "sg:province":"FL",
    "wof:name":"Kaiwahine Marine Services Inc",
    "wof:placetype":"venue"
},
  "geometry": {"coordinates":[-80.203058,26.065892],"type":"Point"}
}