{
  "type": "Feature",
  "properties": {
    "addr:full":"6366 SW 22nd St Miami FL 33155",
    "addr:housenumber":"6366",
    "addr:postcode":"33155",
    "addr:street":"Sw 22Nd St",
    "iso:country":"US",
    "sg:address":"6366 SW 22nd St",
    "sg:city":"Miami",
    "sg:classifiers":[
        {
            "category":"Recreation",
            "type":"Entertainment"
        }
    ],
    "sg:phone":"+1 786 399 4027",
    "sg:postcode":"33155",
    "sg:province":"FL",
    "sg:tags":[
        "entertainers-family",
        "business"
    ],
    "wof:name":"Revive Entretainment Corp",
    "wof:placetype":"venue"
},
  "geometry": {"coordinates":[-80.298815,25.750079],"type":"Point"}
}