{
  "type": "Feature",
  "properties": {
    "iso:country":"US",
    "sg:address":"308 W Highland Dr",
    "sg:city":"Lakeland",
    "sg:classifiers":[
        {
            "category":"Personal",
            "type":"Services"
        }
    ],
    "sg:phone":"+1 863 644 0550",
    "sg:postcode":"33813",
    "sg:province":"FL",
    "sg:tags":[
        "therapist",
        "massage"
    ],
    "wof:name":"Body Balancing By Lisa",
    "wof:placetype":"venue"
},
  "geometry": {"coordinates":[-81.959515,27.985722],"type":"Point"}
}