{
  "type": "Feature",
  "properties": {
    "iso:country":"US",
    "sg:address":"6419 Parkland Dr",
    "sg:city":"Sarasota",
    "sg:classifiers":[
        {
            "category":"Professional",
            "subcategory":"Research",
            "type":"Services"
        },
        {
            "category":"Health Services",
            "subcategory":"Medical Lab",
            "type":"Services"
        }
    ],
    "sg:phone":"+1 941 756 0000",
    "sg:postcode":"34243",
    "sg:province":"FL",
    "sg:tags":[
        "laboratory"
    ],
    "wof:name":"International Medical Lab Inc",
    "wof:placetype":"venue"
},
  "geometry": {"coordinates":[-82.536187,27.428738],"type":"Point"}
}