{
  "type": "Feature",
  "properties": {
    "addr:full":"1200 3rd St West Palm Beach FL 33403",
    "addr:housenumber":"1200",
    "addr:postcode":"33403",
    "addr:street":"3Rd St",
    "iso:country":"US",
    "sg:address":"1200 3rd St",
    "sg:city":"West Palm Beach",
    "sg:classifiers":[
        {
            "category":"Retail",
            "subcategory":"Repair Shop",
            "type":"Services"
        }
    ],
    "sg:phone":"+1 561 848 7720",
    "sg:postcode":"33403",
    "sg:province":"FL",
    "wof:name":"Lake Park Stained Glass Inc",
    "wof:placetype":"venue"
},
  "geometry": {"coordinates":[-80.058702,26.803948],"type":"Point"}
}