{
  "type": "Feature",
  "properties": {
    "iso:country":"US",
    "sg:address":"13327 Highland Chase Pl",
    "sg:city":"Fort Myers",
    "sg:classifiers":[
        {
            "category":"Real Estate",
            "subcategory":"Real Estate Agent",
            "type":"Services"
        }
    ],
    "sg:phone":"+1 239 561 6241",
    "sg:postcode":"33913",
    "sg:province":"FL",
    "wof:name":"Watermark Real Estate",
    "wof:placetype":"venue"
},
  "geometry": {"coordinates":[-81.7351,26.585018],"type":"Point"}
}