{
  "type": "Feature",
  "properties": {
    "addr:full":"2145 Sunnydale Blvd Clearwater FL 33765",
    "addr:housenumber":"2145",
    "addr:postcode":"33765",
    "addr:street":"Sunnydale Blvd",
    "iso:country":"US",
    "sg:address":"2145 Sunnydale Blvd",
    "sg:city":"Clearwater",
    "sg:classifiers":[
        {
            "category":"Professional",
            "subcategory":"Advertising",
            "type":"Services"
        }
    ],
    "sg:phone":"+1 727 442 6440",
    "sg:postcode":"33765",
    "sg:province":"FL",
    "sg:tags":[
        "mailing",
        "shipping"
    ],
    "wof:name":"Joy Rockwell Enterprises",
    "wof:placetype":"venue"
},
  "geometry": {"coordinates":[-82.748822,27.986989],"type":"Point"}
}