{
  "type": "Feature",
  "properties": {
    "addr:full":"14640 Mustang Trl Southwest Rnchs FL 33330",
    "addr:housenumber":"14640",
    "addr:postcode":"33330",
    "addr:street":"Mustang Trl Southwest Rnchs",
    "iso:country":"US",
    "sg:address":"14640 Mustang Trl",
    "sg:city":"Southwest Rnchs",
    "sg:classifiers":[
        {
            "category":"Professional",
            "subcategory":"Art Services",
            "type":"Services"
        }
    ],
    "sg:phone":"+1 954 880 0757",
    "sg:postcode":"33330",
    "sg:province":"FL",
    "sg:tags":[
        "graphic",
        "designer"
    ],
    "sg:website":"www.designworkshopgroup.com",
    "wof:name":"Design Workshop Group Inc",
    "wof:placetype":"venue"
},
  "geometry": {"coordinates":[-80.339727,26.033149],"type":"Point"}
}