{
  "type": "Feature",
  "properties": {
    "addr:full":"6363 Taft St Hollywood FL 33024",
    "addr:housenumber":"6363",
    "addr:postcode":"33024",
    "addr:street":"Taft St",
    "iso:country":"US",
    "sg:address":"6363 Taft St",
    "sg:city":"Hollywood",
    "sg:classifiers":[
        {
            "category":"Real Estate",
            "subcategory":"Real Estate Agent",
            "type":"Services"
        }
    ],
    "sg:phone":"+1 954 966 9919",
    "sg:postcode":"33024",
    "sg:province":"FL",
    "wof:name":"Real Estate USA",
    "wof:placetype":"venue"
},
  "geometry": {"coordinates":[-80.21405799999999,26.024862],"type":"Point"}
}