{
  "type": "Feature",
  "properties": {
    "iso:country":"US",
    "sg:address":"31734 State Road 44",
    "sg:city":"Eustis",
    "sg:classifiers":[
        {
            "category":"Food & Beverages",
            "subcategory":"Groceries & Convenience Stores",
            "type":"Retail Goods"
        }
    ],
    "sg:phone":"+1 352 589 2010",
    "sg:postcode":"32736",
    "sg:province":"FL",
    "sg:website":"http://www.circlek.com",
    "wof:name":"Circle K",
    "wof:placetype":"venue"
},
  "geometry": {"coordinates":[-81.432213,28.938712],"type":"Point"}
}