{
  "type": "Feature",
  "properties": {
    "iso:country":"US",
    "sg:address":"20750 Six Ls Farm Rd",
    "sg:city":"Estero",
    "sg:classifiers":[
        {
            "category":"Real Estate",
            "subcategory":"Real Estate Services",
            "type":"Services"
        },
        {
            "category":"Real Estate",
            "subcategory":"Real Estate Agent",
            "type":"Services"
        }
    ],
    "sg:phone":"+1 239 947 5887",
    "sg:postcode":"33928",
    "sg:province":"FL",
    "sg:tags":[
        "management"
    ],
    "wof:name":"Kelly Youngquist Inc",
    "wof:placetype":"venue"
},
  "geometry": {"coordinates":[-81.65969800000001,26.437856],"type":"Point"}
}