{
  "type": "Feature",
  "properties": {
    "iso:country":"US",
    "sg:address":"3123 W 23rd St",
    "sg:city":"Panama City",
    "sg:classifiers":[
        {
            "category":"Banks & Credit Unions",
            "subcategory":"Bank",
            "type":"Services"
        }
    ],
    "sg:phone":"+1 850 770 7000",
    "sg:postcode":"32405",
    "sg:province":"FL",
    "wof:name":"Peoples First Community Bank",
    "wof:placetype":"venue"
},
  "geometry": {"coordinates":[-85.70195699999999,30.1896],"type":"Point"}
}