{
  "type": "Feature",
  "properties": {
    "addr:full":"20165 NE 39th Pl Miami FL 33180",
    "addr:housenumber":"20165",
    "addr:postcode":"33180",
    "addr:street":"Ne 39Th Pl",
    "iso:country":"US",
    "sg:address":"20165 NE 39th Pl",
    "sg:city":"Miami",
    "sg:classifiers":[
        {
            "category":"Professional",
            "subcategory":"Lawyer & Legal Services",
            "type":"Services"
        }
    ],
    "sg:phone":"+1 954 695 4451",
    "sg:postcode":"33180",
    "sg:province":"FL",
    "sg:tags":[
        "arbitration"
    ],
    "wof:name":"Mediation.Com",
    "wof:placetype":"venue"
},
  "geometry": {"coordinates":[-80.124971,25.962011],"type":"Point"}
}