{
  "type": "Feature",
  "properties": {
    "addr:full":"6307 Ridge Rd Port Richey FL 34668",
    "addr:housenumber":"6307",
    "addr:postcode":"34668",
    "addr:street":"Ridge Rd",
    "iso:country":"US",
    "sg:address":"6307 Ridge Rd",
    "sg:city":"Port Richey",
    "sg:classifiers":[
        {
            "category":"Shopping",
            "type":"Retail Goods"
        }
    ],
    "sg:phone":"+1 727 843 0777",
    "sg:postcode":"34668",
    "sg:province":"FL",
    "sg:tags":[
        "merchandise"
    ],
    "wof:name":"Slippery When Wet Jantr Sup",
    "wof:placetype":"venue"
},
  "geometry": {"coordinates":[-82.71028,28.280685],"type":"Point"}
}