{
  "type": "Feature",
  "properties": {
    "iso:country":"US",
    "sg:address":"7188 Southport Dr",
    "sg:city":"Boynton Beach",
    "sg:classifiers":[
        {
            "category":"Banks & Credit Unions",
            "subcategory":"Investment Brokerage",
            "type":"Services"
        }
    ],
    "sg:phone":"+1 561 364 0151",
    "sg:postcode":"33472",
    "sg:province":"FL",
    "sg:tags":[
        "advisory",
        "financial"
    ],
    "wof:name":"Lawrence M Wolberg Financial",
    "wof:placetype":"venue"
},
  "geometry": {"coordinates":[-80.159189,26.546214],"type":"Point"}
}