{
  "type": "Feature",
  "properties": {
    "addr:full":"1051 Port Malabar Blvd NE Palm Bay FL 32905",
    "addr:housenumber":"1051",
    "addr:postcode":"32905",
    "addr:street":"Port Malabar Blvd Ne",
    "iso:country":"US",
    "sg:address":"1051 Port Malabar Blvd NE",
    "sg:city":"Palm Bay",
    "sg:classifiers":[
        {
            "category":"Health Services",
            "subcategory":"Doctor",
            "type":"Services"
        }
    ],
    "sg:phone":"+1 321 729 6060",
    "sg:postcode":"32905",
    "sg:province":"FL",
    "sg:tags":[
        "dentist"
    ],
    "wof:name":"United Dental Group",
    "wof:placetype":"venue"
},
  "geometry": {"coordinates":[-80.621377,28.019277],"type":"Point"}
}