{
  "type": "Feature",
  "properties": {
    "addr:full":"290 SW 97th Ter Hollywood FL 33025",
    "addr:housenumber":"290",
    "addr:postcode":"33025",
    "addr:street":"Sw 97Th Ter",
    "iso:country":"US",
    "sg:address":"290 SW 97th Ter",
    "sg:city":"Hollywood",
    "sg:classifiers":[
        {
            "category":"Retail",
            "subcategory":"Veterinary Services",
            "type":"Services"
        }
    ],
    "sg:phone":"+1 954 436 9195",
    "sg:postcode":"33025",
    "sg:province":"FL",
    "wof:name":"Furry Animal Lady",
    "wof:placetype":"venue"
},
  "geometry": {"coordinates":[-80.275469,26.006126],"type":"Point"}
}