{
  "type": "Feature",
  "properties": {
    "addr:full":"1615 N Harbor City Blvd Melbourne FL 32935",
    "addr:housenumber":"1615",
    "addr:postcode":"32935",
    "addr:street":"N Harbor City Blvd",
    "iso:country":"US",
    "sg:address":"1615 N Harbor City Blvd",
    "sg:city":"Melbourne",
    "sg:classifiers":[
        {
            "category":"Professional",
            "subcategory":"Employment Agencies",
            "type":"Services"
        }
    ],
    "sg:phone":"+1 321 253 9449",
    "sg:postcode":"32935",
    "sg:province":"FL",
    "sg:tags":[
        "help",
        "contractor"
    ],
    "wof:name":"Workers Temporary Staffing Inc",
    "wof:placetype":"venue"
},
  "geometry": {"coordinates":[-80.63155399999999,28.132275],"type":"Point"}
}