{
  "type": "Feature",
  "properties": {
    "addr:full":"5030 Champion Blvd Boca Raton FL 33496",
    "addr:housenumber":"5030",
    "addr:postcode":"33496",
    "addr:street":"Champion Blvd",
    "iso:country":"US",
    "sg:address":"5030 Champion Blvd",
    "sg:city":"Boca Raton",
    "sg:classifiers":[
        {
            "category":"Deli",
            "type":"Food & Drink"
        }
    ],
    "sg:menulink":"http://www.allmenus.com/fl/boca-raton/36032-too-jays/menu/",
    "sg:phone":"+1 561 241 5903",
    "sg:postcode":"33496",
    "sg:province":"FL",
    "sg:tags":[
        "american"
    ],
    "wof:name":"Too Jay's",
    "wof:placetype":"venue"
},
  "geometry": {"coordinates":[-80.12226800000001,26.411852],"type":"Point"}
}