{
  "type": "Feature",
  "properties": {
    "addr:full":"109 N 9th St Haines City FL 33844",
    "addr:housenumber":"109",
    "addr:postcode":"33844",
    "addr:street":"N 9Th St",
    "iso:country":"US",
    "sg:address":"109 N 9th St",
    "sg:city":"Haines City",
    "sg:classifiers":[
        {
            "category":"Government",
            "subcategory":"Office",
            "type":"Public Place"
        }
    ],
    "sg:phone":"+1 863 206 2224",
    "sg:postcode":"33844",
    "sg:province":"FL",
    "sg:tags":[
        "urban",
        "outreach"
    ],
    "wof:name":"Kings Kids Worldwide Outreach",
    "wof:placetype":"venue"
},
  "geometry": {"coordinates":[-81.624067,28.108273],"type":"Point"}
}