{
  "type": "Feature",
  "properties": {
    "iso:country":"US",
    "sg:address":"1600 SW 2nd Ave",
    "sg:city":"Miami",
    "sg:classifiers":[
        {
            "category":"Wholesale",
            "subcategory":"Apparel",
            "type":"Manufacturing & Wholesale Goods"
        }
    ],
    "sg:phone":"+1 305 854 6620",
    "sg:postcode":"33129",
    "sg:province":"FL",
    "sg:tags":[
        "swimwear"
    ],
    "wof:name":"Onda De Mar Blu",
    "wof:placetype":"venue"
},
  "geometry": {"coordinates":[-80.197857,25.760107],"type":"Point"}
}