{
  "type": "Feature",
  "properties": {
    "addr:full":"2221 SW 60th Way Miramar FL 33023",
    "addr:housenumber":"2221",
    "addr:postcode":"33023",
    "addr:street":"Sw 60Th Way",
    "iso:country":"US",
    "sg:address":"2221 SW 60th Way",
    "sg:city":"Miramar",
    "sg:classifiers":[
        {
            "category":"Freight",
            "type":"Transportation"
        }
    ],
    "sg:phone":"+1 954 322 7771",
    "sg:postcode":"33023",
    "sg:province":"FL",
    "sg:tags":[
        "shipping",
        "agent"
    ],
    "wof:name":"Caraballo Cargo Inc",
    "wof:placetype":"venue"
},
  "geometry": {"coordinates":[-80.208448,25.99095],"type":"Point"}
}