{
  "type": "Feature",
  "properties": {
    "addr:full":"6500 W 21st Ct Hialeah FL 33016",
    "addr:housenumber":"6500",
    "addr:postcode":"33016",
    "addr:street":"W 21St Ct",
    "iso:country":"US",
    "sg:address":"6500 W 21st Ct",
    "sg:city":"Hialeah",
    "sg:classifiers":[
        {
            "category":"Professional",
            "subcategory":"Lawyer & Legal Services",
            "type":"Services"
        }
    ],
    "sg:phone":"+1 305 639 1732",
    "sg:postcode":"33016",
    "sg:province":"FL",
    "wof:name":"A Attorney At Law Paul Buechele",
    "wof:placetype":"venue"
},
  "geometry": {"coordinates":[-80.326661,25.881541],"type":"Point"}
}