{
  "type": "Feature",
  "properties": {
    "addr:full":"2784 S Ocean Blvd Palm Beach FL 33480",
    "addr:housenumber":"2784",
    "addr:postcode":"33480",
    "addr:street":"S Ocean Blvd",
    "iso:country":"US",
    "sg:address":"2784 S Ocean Blvd",
    "sg:city":"Palm Beach",
    "sg:classifiers":[
        {
            "category":"Real Estate",
            "subcategory":"Real Estate Operator",
            "type":"Services"
        }
    ],
    "sg:phone":"+1 561 585 6060",
    "sg:postcode":"33480",
    "sg:province":"FL",
    "sg:tags":[
        "condominium"
    ],
    "wof:name":"Cove Condominium North",
    "wof:placetype":"venue"
},
  "geometry": {"coordinates":[-80.03865999999999,26.619337],"type":"Point"}
}