{
  "type": "Feature",
  "properties": {
    "addr:full":"1615 W Blue Springs Ave Orange City FL 32763",
    "addr:housenumber":"1615",
    "addr:postcode":"32763",
    "addr:street":"W Blue Springs Ave",
    "iso:country":"US",
    "sg:address":"1615 W Blue Springs Ave",
    "sg:city":"Orange City",
    "sg:classifiers":[
        {
            "category":"Professional",
            "subcategory":"Business Services",
            "type":"Services"
        }
    ],
    "sg:phone":"+1 386 774 8282",
    "sg:postcode":"32763",
    "sg:province":"FL",
    "sg:tags":[
        "paralegal"
    ],
    "wof:name":"Offical Document Svc",
    "wof:placetype":"venue"
},
  "geometry": {"coordinates":[-81.325896,28.943405],"type":"Point"}
}