{
  "type": "Feature",
  "properties": {
    "iso:country":"US",
    "sg:address":"5310 McIntosh Rd",
    "sg:city":"Sarasota",
    "sg:classifiers":[
        {
            "category":"Autos & Motor Vehicles",
            "subcategory":"Auto Supplies",
            "type":"Retail Goods"
        }
    ],
    "sg:phone":"+1 941 922 9049",
    "sg:postcode":"34233",
    "sg:province":"FL",
    "sg:tags":[
        "tire"
    ],
    "wof:name":"Superior Auto Ctr Inc",
    "wof:placetype":"venue"
},
  "geometry": {"coordinates":[-82.481134,27.275599],"type":"Point"}
}