{
  "type": "Feature",
  "properties": {
    "addr:full":"3412 Ave G NW Winter Haven FL 33880",
    "addr:housenumber":"3412",
    "addr:postcode":"33880",
    "addr:street":"Ave G Nw",
    "iso:country":"US",
    "sg:address":"3412 Ave G NW",
    "sg:city":"Winter Haven",
    "sg:classifiers":[
        {
            "category":"Banks & Credit Unions",
            "subcategory":"Bank",
            "type":"Services"
        }
    ],
    "sg:phone":"+1 863 293 3797",
    "sg:postcode":"33880",
    "sg:province":"FL",
    "sg:tags":[
        "cashing",
        "check"
    ],
    "wof:name":"All Knids Cashed Check Cashing",
    "wof:placetype":"venue"
},
  "geometry": {"coordinates":[-81.77095300000001,28.02937],"type":"Point"}
}