{
  "type": "Feature",
  "properties": {
    "iso:country":"US",
    "sg:address":"93 Orange St",
    "sg:city":"St Augustine",
    "sg:classifiers":[
        {
            "category":"Real Estate",
            "subcategory":"Surveying",
            "type":"Services"
        }
    ],
    "sg:phone":"+1 904 823 3600",
    "sg:postcode":"32084",
    "sg:province":"FL",
    "sg:tags":[
        "surveyor"
    ],
    "wof:name":"Devino & Assoc Inc",
    "wof:placetype":"venue"
},
  "geometry": {"coordinates":[-81.319288,29.897287],"type":"Point"}
}