{
  "type": "Feature",
  "properties": {
    "iso:country":"US",
    "sg:address":"2548 NW 36th St",
    "sg:city":"Miami",
    "sg:classifiers":[
        {
            "category":"Recreation",
            "type":"Entertainment"
        }
    ],
    "sg:phone":"+1 305 642 7600",
    "sg:postcode":"33142",
    "sg:province":"FL",
    "sg:tags":[
        "hall",
        "auditorium"
    ],
    "wof:name":"Regis House Community Ctr",
    "wof:placetype":"venue"
},
  "geometry": {"coordinates":[-80.239788,25.80903],"type":"Point"}
}