{
  "type": "Feature",
  "properties": {
    "iso:country":"US",
    "sg:address":"2350 SW 97th Ave",
    "sg:city":"Miami",
    "sg:classifiers":[
        {
            "category":"Real Estate",
            "subcategory":"Real Estate Operator",
            "type":"Services"
        }
    ],
    "sg:phone":"+1 305 223 1025",
    "sg:postcode":"33165",
    "sg:province":"FL",
    "sg:tags":[
        "apartment"
    ],
    "wof:name":"Westbrook Gardens Apts",
    "wof:placetype":"venue"
},
  "geometry": {"coordinates":[-80.357399,25.735399],"type":"Point"}
}