{
  "type": "Feature",
  "properties": {
    "iso:country":"US",
    "sg:address":"1925 NW 81st St",
    "sg:city":"Miami",
    "sg:classifiers":[
        {
            "category":"Travel",
            "subcategory":"Travel Agent",
            "type":"Entertainment"
        }
    ],
    "sg:phone":"+1 786 306 6936",
    "sg:postcode":"33147",
    "sg:province":"FL",
    "sg:tags":[
        "agency",
        "services-commercial"
    ],
    "wof:name":"Bmh Travels",
    "wof:placetype":"venue"
},
  "geometry": {"coordinates":[-80.22980800000001,25.848262],"type":"Point"}
}