{
  "type": "Feature",
  "properties": {
    "iso:country":"US",
    "sg:address":"2400 S Ridgewood Ave",
    "sg:city":"Daytona Beach",
    "sg:classifiers":[
        {
            "category":"Professional",
            "subcategory":"Detective & Security Services",
            "type":"Services"
        }
    ],
    "sg:phone":"+1 386 322 0052",
    "sg:postcode":"32119",
    "sg:province":"FL",
    "sg:tags":[
        "protective"
    ],
    "wof:name":"Wells Fargo Guard Services",
    "wof:placetype":"venue"
},
  "geometry": {"coordinates":[-80.998042,29.164451],"type":"Point"}
}