{
  "type": "Feature",
  "properties": {
    "addr:full":"1342 NE 118th St Miami FL 33161",
    "addr:housenumber":"1342",
    "addr:postcode":"33161",
    "addr:street":"Ne 118Th St",
    "iso:country":"US",
    "sg:address":"1342 NE 118th St",
    "sg:city":"Miami",
    "sg:classifiers":[
        {
            "category":"Building & Trades",
            "subcategory":"Cleaning & Sanitation",
            "type":"Services"
        }
    ],
    "sg:phone":"+1 305 893 1126",
    "sg:postcode":"33161",
    "sg:province":"FL",
    "sg:tags":[
        "janitor"
    ],
    "wof:name":"Fifth Avenue Janitorial Contr",
    "wof:placetype":"venue"
},
  "geometry": {"coordinates":[-80.17075,25.884418],"type":"Point"}
}