{
  "type": "Feature",
  "properties": {
    "addr:full":"140 E Miracle Strip Pkwy Mary Esther FL 32569",
    "addr:housenumber":"140",
    "addr:postcode":"32569",
    "addr:street":"E Miracle Strip Pkwy",
    "iso:country":"US",
    "sg:address":"140 E Miracle Strip Pkwy",
    "sg:city":"Mary Esther",
    "sg:classifiers":[
        {
            "category":"Restaurant",
            "type":"Food & Drink"
        }
    ],
    "sg:phone":"+1 850 244 3445",
    "sg:postcode":"32569",
    "sg:province":"FL",
    "sg:tags":[
        "eating"
    ],
    "wof:name":"Daddys Place For Ribs",
    "wof:placetype":"venue"
},
  "geometry": {"coordinates":[-86.66231399999999,30.409697],"type":"Point"}
}