{
  "type": "Feature",
  "properties": {
    "iso:country":"US",
    "sg:address":"3920 NW 4th Ct",
    "sg:city":"Deerfield Beach",
    "sg:classifiers":[
        {
            "category":"Shopping",
            "subcategory":"Gifts & Souvenirs",
            "type":"Retail Goods"
        }
    ],
    "sg:phone":"+1 954 428 9591",
    "sg:postcode":"33442",
    "sg:province":"FL",
    "wof:name":"Dotty Plaut PC",
    "wof:placetype":"venue"
},
  "geometry": {"coordinates":[-80.15722700000001,26.323426],"type":"Point"}
}