{
  "type": "Feature",
  "properties": {
    "iso:country":"US",
    "sg:address":"12378 SW 127 Ave",
    "sg:city":"Miami",
    "sg:classifiers":[
        {
            "category":"Personal",
            "subcategory":"Beauty Salon",
            "type":"Services"
        }
    ],
    "sg:phone":"+1 305 969 9501",
    "sg:postcode":"33186",
    "sg:province":"FL",
    "sg:tags":[
        "hair"
    ],
    "wof:name":"Kendall Discount Beauty Supply",
    "wof:placetype":"venue"
},
  "geometry": {"coordinates":[-80.39925100000001,25.653238],"type":"Point"}
}