{
  "type": "Feature",
  "properties": {
    "iso:country":"US",
    "sg:address":"1300 E Bay Dr Ste B",
    "sg:city":"Largo",
    "sg:classifiers":[
        {
            "category":"Personal",
            "subcategory":"Nail Salon",
            "type":"Services"
        }
    ],
    "sg:phone":"+1 727 585 6652",
    "sg:postcode":"33771",
    "sg:province":"FL",
    "wof:name":"Abracadabra Industies",
    "wof:placetype":"venue"
},
  "geometry": {"coordinates":[-82.77341199999999,27.916725],"type":"Point"}
}