{
  "type": "Feature",
  "properties": {
    "iso:country":"US",
    "sg:address":"13318 Moran Dr",
    "sg:city":"Tampa",
    "sg:classifiers":[
        {
            "category":"Place Of Worship",
            "type":"Public Place"
        }
    ],
    "sg:phone":"+1 813 963 2366",
    "sg:postcode":"33618",
    "sg:province":"FL",
    "sg:tags":[
        "church"
    ],
    "wof:name":"Tampa Bay Community Church",
    "wof:placetype":"venue"
},
  "geometry": {"coordinates":[-82.490701,28.068872],"type":"Point"}
}