{
  "type": "Feature",
  "properties": {
    "iso:country":"US",
    "sg:address":"501 Centre St",
    "sg:city":"Fernandina Beach",
    "sg:classifiers":[
        {
            "category":"Professional",
            "subcategory":"Detective & Security Services",
            "type":"Services"
        }
    ],
    "sg:phone":"+1 904 491 5545",
    "sg:postcode":"32034",
    "sg:province":"FL",
    "wof:name":"Hines Investigations",
    "wof:placetype":"venue"
},
  "geometry": {"coordinates":[-81.46125000000001,30.67102],"type":"Point"}
}