{
  "type": "Feature",
  "properties": {
    "addr:full":"1380 N Krome Ave Homestead FL 33030",
    "addr:housenumber":"1380",
    "addr:postcode":"33030",
    "addr:street":"N Krome Ave",
    "iso:country":"US",
    "sg:address":"1380 N Krome Ave",
    "sg:city":"Homestead",
    "sg:classifiers":[
        {
            "category":"Real Estate",
            "subcategory":"Real Estate Agent",
            "type":"Services"
        }
    ],
    "sg:phone":"+1 786 349 5698",
    "sg:postcode":"33030",
    "sg:province":"FL",
    "wof:name":"Guillen And Associates",
    "wof:placetype":"venue"
},
  "geometry": {"coordinates":[-80.47749,25.483355],"type":"Point"}
}