{
  "type": "Feature",
  "properties": {
    "iso:country":"US",
    "sg:address":"1825 12th St SE",
    "sg:city":"Largo",
    "sg:classifiers":[
        {
            "category":"Retail",
            "subcategory":"Auto Repair",
            "type":"Services"
        }
    ],
    "sg:phone":"+1 727 559 0607",
    "sg:postcode":"33771",
    "sg:province":"FL",
    "sg:tags":[
        "body",
        "automobile",
        "painting"
    ],
    "wof:name":"Floyd's Auto Body & Paint",
    "wof:placetype":"venue"
},
  "geometry": {"coordinates":[-82.774444,27.901662],"type":"Point"}
}