{
  "type": "Feature",
  "properties": {
    "addr:full":"90800 Overseas Hwy Tavernier FL 33070",
    "addr:housenumber":"90800",
    "addr:postcode":"33070",
    "addr:street":"Overseas Hwy",
    "iso:country":"US",
    "sg:address":"90800 Overseas Hwy",
    "sg:city":"Tavernier",
    "sg:classifiers":[
        {
            "category":"Sports & Exercise",
            "subcategory":"Sports Center",
            "type":"Entertainment"
        },
        {
            "category":"Community Center",
            "type":"Public Place"
        }
    ],
    "sg:phone":"+1 305 766 6893",
    "sg:postcode":"33070",
    "sg:province":"FL",
    "sg:tags":[
        "recreation"
    ],
    "wof:name":"Catch Me If You Can Fishing Charters",
    "wof:placetype":"venue"
},
  "geometry": {"coordinates":[-80.53191099999999,25.002791],"type":"Point"}
}