{
  "type": "Feature",
  "properties": {
    "iso:country":"US",
    "sg:address":"1800 Collins Ave # 16B",
    "sg:city":"Miami Beach",
    "sg:classifiers":[
        {
            "category":"Travel",
            "subcategory":"Hotels & Motels",
            "type":"Entertainment"
        }
    ],
    "sg:phone":"+1 786 999 8537",
    "sg:postcode":"33139",
    "sg:province":"FL",
    "sg:website":"www.vacationaptsinmiami.com",
    "wof:name":"Vacation Apartments in Miami",
    "wof:placetype":"venue"
},
  "geometry": {"coordinates":[-80.12984899999999,25.79422],"type":"Point"}
}