{
  "type": "Feature",
  "properties": {
    "addr:full":"9183 August Cir Saint Augustine FL 32080",
    "addr:housenumber":"9183",
    "addr:postcode":"32080",
    "addr:street":"August Cir",
    "iso:country":"US",
    "sg:address":"9183 August Cir",
    "sg:city":"Saint Augustine",
    "sg:classifiers":[
        {
            "category":"Retail",
            "subcategory":"Self-service Laundry",
            "type":"Services"
        }
    ],
    "sg:phone":"+1 904 461 5664",
    "sg:postcode":"32080",
    "sg:province":"FL",
    "sg:tags":[
        "coin"
    ],
    "wof:name":"Alto Laundry Systems Inc",
    "wof:placetype":"venue"
},
  "geometry": {"coordinates":[-81.225908,29.694149],"type":"Point"}
}