{
  "type": "Feature",
  "properties": {
    "addr:full":"100 Glenview Pl Naples FL 34108",
    "addr:housenumber":"100",
    "addr:postcode":"34108",
    "addr:street":"Glenview Pl",
    "iso:country":"US",
    "sg:address":"100 Glenview Pl",
    "sg:city":"Naples",
    "sg:classifiers":[
        {
            "category":"Personal",
            "subcategory":"Beauty Salon",
            "type":"Services"
        }
    ],
    "sg:phone":"+1 239 594 1707",
    "sg:postcode":"34108",
    "sg:province":"FL",
    "sg:tags":[
        "shop"
    ],
    "wof:name":"Salon At Glenview Caring",
    "wof:placetype":"venue"
},
  "geometry": {"coordinates":[-81.809528,26.218199],"type":"Point"}
}