{
  "type": "Feature",
  "properties": {
    "addr:full":"175 Cloud Dr De Funiak Springs FL 32433",
    "addr:housenumber":"175",
    "addr:postcode":"32433",
    "addr:street":"Cloud Dr De Funiak Springs",
    "iso:country":"US",
    "sg:address":"175 Cloud Dr",
    "sg:city":"De Funiak Springs",
    "sg:classifiers":[
        {
            "category":"Professional",
            "type":"Services"
        }
    ],
    "sg:phone":"+1 850 259 9348",
    "sg:postcode":"32433",
    "sg:province":"FL",
    "wof:name":"Frankie Lamb Framing",
    "wof:placetype":"venue"
},
  "geometry": {"coordinates":[-86.37537,30.762901],"type":"Point"}
}