{
  "type": "Feature",
  "properties": {
    "addr:full":"2610 Northbrooke Dr Naples FL 34119",
    "addr:housenumber":"2610",
    "addr:postcode":"34119",
    "addr:street":"Northbrooke Dr",
    "iso:country":"US",
    "sg:address":"2610 Northbrooke Dr",
    "sg:city":"Naples",
    "sg:classifiers":[
        {
            "category":"Social Services",
            "type":"Services"
        }
    ],
    "sg:phone":"+1 239 596 6868",
    "sg:postcode":"34119",
    "sg:province":"FL",
    "sg:tags":[
        "organization",
        "welfare"
    ],
    "wof:name":"American Red Cross",
    "wof:placetype":"venue"
},
  "geometry": {"coordinates":[-81.737734,26.279428],"type":"Point"}
}