{
  "type": "Feature",
  "properties": {
    "addr:full":"19188 Punta Gorda Ct Port Charlotte FL 33948",
    "addr:housenumber":"19188",
    "addr:postcode":"33948",
    "addr:street":"Punta Gorda Ct",
    "iso:country":"US",
    "sg:address":"19188 Punta Gorda Ct",
    "sg:city":"Port Charlotte",
    "sg:classifiers":[
        {
            "category":"Building & Trades",
            "subcategory":"Construction",
            "type":"Services"
        }
    ],
    "sg:phone":"+1 941 766 6139",
    "sg:postcode":"33948",
    "sg:province":"FL",
    "sg:tags":[
        "house"
    ],
    "wof:name":"Keller Express Construction",
    "wof:placetype":"venue"
},
  "geometry": {"coordinates":[-82.135366,26.954873],"type":"Point"}
}