{
  "type": "Feature",
  "properties": {
    "addr:full":"517 Vera Cruz Dr Destin FL 32541",
    "addr:housenumber":"517",
    "addr:postcode":"32541",
    "addr:street":"Vera Cruz Dr",
    "iso:country":"US",
    "sg:address":"517 Vera Cruz Dr",
    "sg:city":"Destin",
    "sg:classifiers":[
        {
            "category":"Building & Trades",
            "subcategory":"Construction",
            "type":"Services"
        }
    ],
    "sg:phone":"+1 850 830 0454",
    "sg:postcode":"32541",
    "sg:province":"FL",
    "sg:tags":[
        "heavy"
    ],
    "wof:name":"Shirah Construction",
    "wof:placetype":"venue"
},
  "geometry": {"coordinates":[-86.495908,30.385735],"type":"Point"}
}