{
  "type": "Feature",
  "properties": {
    "iso:country":"US",
    "sg:address":"4946 Westchester Ct",
    "sg:city":"Naples",
    "sg:classifiers":[
        {
            "category":"Professional",
            "type":"Services"
        }
    ],
    "sg:phone":"+1 239 263 8104",
    "sg:postcode":"34105",
    "sg:province":"FL",
    "wof:name":"Peggy D & John R Gates",
    "wof:placetype":"venue"
},
  "geometry": {"coordinates":[-81.761489,26.198542],"type":"Point"}
}