{
  "type": "Feature",
  "properties": {
    "iso:country":"US",
    "sg:address":"2749 Yarmouth Dr",
    "sg:city":"Wellington",
    "sg:classifiers":[
        {
            "category":"Building & Trades",
            "subcategory":"Plumbing",
            "type":"Services"
        }
    ],
    "sg:phone":"+1 561 795 3990",
    "sg:postcode":"33414",
    "sg:province":"FL",
    "sg:tags":[
        "plumber",
        "industrial",
        "contractors-commercial"
    ],
    "wof:name":"Port Stlucie Plumbing",
    "wof:placetype":"venue"
},
  "geometry": {"coordinates":[-80.268089,26.64307],"type":"Point"}
}