{
  "type": "Feature",
  "properties": {
    "addr:full":"440 W 24th St West Palm Beach FL 33404",
    "addr:housenumber":"440",
    "addr:postcode":"33404",
    "addr:street":"W 24Th St",
    "iso:country":"US",
    "sg:address":"440 W 24th St",
    "sg:city":"West Palm Beach",
    "sg:classifiers":[
        {
            "category":"Autos & Motor Vehicles",
            "subcategory":"Automobile Sales",
            "type":"Retail Goods"
        }
    ],
    "sg:phone":"+1 561 882 9261",
    "sg:postcode":"33404",
    "sg:province":"FL",
    "wof:name":"Staley Rodney R & B Car Sales",
    "wof:placetype":"venue"
},
  "geometry": {"coordinates":[-80.060396,26.782031],"type":"Point"}
}