{
  "type": "Feature",
  "properties": {
    "addr:full":"223 Miramar Rd Lakeland FL 33803",
    "addr:housenumber":"223",
    "addr:postcode":"33803",
    "addr:street":"Miramar Rd",
    "iso:country":"US",
    "sg:address":"223 Miramar Rd",
    "sg:city":"Lakeland",
    "sg:classifiers":[
        {
            "category":"Manufacturing",
            "subcategory":"Paper Products",
            "type":"Manufacturing & Wholesale Goods"
        }
    ],
    "sg:phone":"+1 863 683 0500",
    "sg:postcode":"33803",
    "sg:province":"FL",
    "sg:tags":[
        "bamboo"
    ],
    "wof:name":"Mid Florida Nurseries",
    "wof:placetype":"venue"
},
  "geometry": {"coordinates":[-81.956039,28.02031],"type":"Point"}
}