{
  "type": "Feature",
  "properties": {
    "addr:full":"1319 Glenview Ln Lakeland FL 33813",
    "addr:housenumber":"1319",
    "addr:postcode":"33813",
    "addr:street":"Glenview Ln",
    "iso:country":"US",
    "sg:address":"1319 Glenview Ln",
    "sg:city":"Lakeland",
    "sg:classifiers":[
        {
            "category":"Social Services",
            "type":"Services"
        }
    ],
    "sg:phone":"+1 863 644 4828",
    "sg:postcode":"33813",
    "sg:province":"FL",
    "wof:name":"Heart Florida Autism Society",
    "wof:placetype":"venue"
},
  "geometry": {"coordinates":[-81.936877,27.984834],"type":"Point"}
}