{
  "type": "Feature",
  "properties": {
    "addr:full":"7892 Sailboat Key Blvd South Pasadena FL 33707",
    "addr:housenumber":"7892",
    "addr:postcode":"33707",
    "addr:street":"Sailboat Key Blvd",
    "iso:country":"US",
    "sg:address":"7892 Sailboat Key Blvd",
    "sg:city":"South Pasadena",
    "sg:classifiers":[
        {
            "category":"Professional",
            "type":"Services"
        }
    ],
    "sg:phone":"+1 727 360 1671",
    "sg:postcode":"33707",
    "sg:province":"FL",
    "sg:tags":[
        "establishment"
    ],
    "wof:name":"Harbourside Press",
    "wof:placetype":"venue"
},
  "geometry": {"coordinates":[-82.750097,27.753478],"type":"Point"}
}