{
  "type": "Feature",
  "properties": {
    "iso:country":"US",
    "sg:address":"3650 NE 70th Ave",
    "sg:city":"Silver Springs",
    "sg:classifiers":[
        {
            "category":"Building & Trades",
            "subcategory":"Landscaping Services",
            "type":"Services"
        }
    ],
    "sg:phone":"+1 352 236 1385",
    "sg:postcode":"34488",
    "sg:province":"FL",
    "sg:tags":[
        "landscape",
        "contractor"
    ],
    "wof:name":"William Leslie Landscaping",
    "wof:placetype":"venue"
},
  "geometry": {"coordinates":[-82.038479,29.225113],"type":"Point"}
}