{
  "type": "Feature",
  "properties": {
    "iso:country":"US",
    "sg:address":"6703 Mott Ave",
    "sg:city":"Orlando",
    "sg:classifiers":[
        {
            "category":"Building & Trades",
            "subcategory":"Construction",
            "type":"Services"
        }
    ],
    "sg:phone":"+1 407 846 8828",
    "sg:postcode":"32810",
    "sg:province":"FL",
    "sg:tags":[
        "water",
        "restoration",
        "damage"
    ],
    "sg:website":"www.eirsinc.com",
    "wof:name":"EIRS Inc",
    "wof:placetype":"venue"
},
  "geometry": {"coordinates":[-81.438912,28.621206],"type":"Point"}
}