{
  "type": "Feature",
  "properties": {
    "addr:full":"11360 Fortune Cir Wellington FL 33414",
    "addr:housenumber":"11360",
    "addr:postcode":"33414",
    "addr:street":"Fortune Cir",
    "iso:country":"US",
    "sg:address":"11360 Fortune Cir",
    "sg:city":"Wellington",
    "sg:classifiers":[
        {
            "category":"Wholesale",
            "subcategory":"Durable Goods & Equipment",
            "type":"Manufacturing & Wholesale Goods"
        }
    ],
    "sg:phone":"+1 561 383 5583",
    "sg:postcode":"33414",
    "sg:province":"FL",
    "sg:tags":[
        "exporter"
    ],
    "wof:name":"Kiss Caribbean Distributors",
    "wof:placetype":"venue"
},
  "geometry": {"coordinates":[-80.225122,26.635135],"type":"Point"}
}