{
  "type": "Feature",
  "properties": {
    "addr:full":"125 Morningstar Dr Punta Gorda FL 33950",
    "addr:housenumber":"125",
    "addr:postcode":"33950",
    "addr:street":"Morningstar Dr",
    "iso:country":"US",
    "sg:address":"125 Morningstar Dr",
    "sg:city":"Punta Gorda",
    "sg:classifiers":[
        {
            "category":"Professional",
            "type":"Services"
        }
    ],
    "sg:phone":"+1 941 575 0465",
    "sg:postcode":"33950",
    "sg:province":"FL",
    "sg:tags":[
        "establishment"
    ],
    "wof:name":"Roofus Studios",
    "wof:placetype":"venue"
},
  "geometry": {"coordinates":[-82.01740100000001,26.946655],"type":"Point"}
}