{
  "type": "Feature",
  "properties": {
    "iso:country":"US",
    "sg:address":"6100 9th St N",
    "sg:city":"St Petersburg",
    "sg:classifiers":[
        {
            "category":"Insurance",
            "subcategory":"Insurance Agent",
            "type":"Services"
        }
    ],
    "sg:phone":"+1 727 528 7800",
    "sg:postcode":"33703",
    "sg:province":"FL",
    "wof:name":"Prudential Insurance Co",
    "wof:placetype":"venue"
},
  "geometry": {"coordinates":[-82.646925,27.828483],"type":"Point"}
}