{
  "type": "Feature",
  "properties": {
    "addr:full":"1900 S State Road 7 Miramar FL 33023",
    "addr:housenumber":"1900",
    "addr:postcode":"33023",
    "addr:street":"S State Road 7",
    "iso:country":"US",
    "sg:address":"1900 S State Road 7",
    "sg:city":"Miramar",
    "sg:classifiers":[
        {
            "category":"Fast Food",
            "type":"Food & Drink"
        },
        {
            "category":"Manufacturing",
            "subcategory":"Food",
            "type":"Manufacturing & Wholesale Goods"
        },
        {
            "category":"Restaurant",
            "type":"Food & Drink"
        },
        {
            "category":"Ice Cream",
            "type":"Food & Drink"
        }
    ],
    "sg:phone":"+1 954 989 4272",
    "sg:postcode":"33023",
    "sg:province":"FL",
    "sg:tags":[
        "frozen",
        "dessert",
        "desserts-manufacturers",
        "distributor",
        "take"
    ],
    "sg:website":"http://www.dairyqueen.com",
    "wof:name":"Dairy Queen",
    "wof:placetype":"venue"
},
  "geometry": {"coordinates":[-80.206985,25.993874],"type":"Point"}
}