{
  "type": "Feature",
  "properties": {
    "addr:full":"265 College Dr Orange Park FL 32065",
    "addr:housenumber":"265",
    "addr:postcode":"32065",
    "addr:street":"College Dr",
    "iso:country":"US",
    "sg:address":"265 College Dr",
    "sg:city":"Orange Park",
    "sg:classifiers":[
        {
            "category":"Recreation",
            "type":"Entertainment"
        }
    ],
    "sg:phone":"+1 904 710 4900",
    "sg:postcode":"32065",
    "sg:province":"FL",
    "sg:tags":[
        "martial",
        "arts",
        "instruction"
    ],
    "wof:name":"Vovinam Martial Arts",
    "wof:placetype":"venue"
},
  "geometry": {"coordinates":[-81.776492,30.119192],"type":"Point"}
}