{
  "type": "Feature",
  "properties": {
    "iso:country":"US",
    "sg:address":"1672 S Ridgewood Ave",
    "sg:city":"South Daytona",
    "sg:classifiers":[
        {
            "category":"Government",
            "subcategory":"Office",
            "type":"Public Place"
        }
    ],
    "sg:phone":"+1 386 322 3010",
    "sg:postcode":"32119",
    "sg:province":"FL",
    "sg:tags":[
        "city"
    ],
    "wof:name":"City Manager",
    "wof:placetype":"venue"
},
  "geometry": {"coordinates":[-81.007425,29.181606],"type":"Point"}
}