{
  "type": "Feature",
  "properties": {
    "addr:full":"2620 Creighton Rd Pensacola FL 32504",
    "addr:housenumber":"2620",
    "addr:postcode":"32504",
    "addr:street":"Creighton Rd",
    "iso:country":"US",
    "sg:address":"2620 Creighton Rd",
    "sg:city":"Pensacola",
    "sg:classifiers":[
        {
            "category":"Banks & Credit Unions",
            "subcategory":"Bank",
            "type":"Services"
        }
    ],
    "sg:phone":"+1 850 478 8144",
    "sg:postcode":"32504",
    "sg:province":"FL",
    "sg:tags":[
        "financing",
        "loan"
    ],
    "sg:website":"http://citi.bridgetrack.com/citifi/_redir.htm?BTData=302177C736961705A55424AB8BEBEABA298948493FBFBF6E9EAC5C2DECE67BE2&BT_TRF=10467&RedirectID=YLLWPGS_US_CTGRY_TRD_LNK_FNCL_SRVCS_CPC&creativeID=YP_Link",
    "wof:name":"CitiFinancial",
    "wof:placetype":"venue"
},
  "geometry": {"coordinates":[-87.192656,30.495168],"type":"Point"}
}