{
  "type": "Feature",
  "properties": {
    "iso:country":"US",
    "sg:address":"7310 SW 17th Ter",
    "sg:city":"Miami",
    "sg:classifiers":[
        {
            "category":"Building & Trades",
            "subcategory":"Cleaning & Sanitation",
            "type":"Services"
        }
    ],
    "sg:phone":"+1 305 267 3305",
    "sg:postcode":"33155",
    "sg:province":"FL",
    "sg:tags":[
        "janitor"
    ],
    "wof:name":"All Cleaning Restoration Inc",
    "wof:placetype":"venue"
},
  "geometry": {"coordinates":[-80.31399500000001,25.754038],"type":"Point"}
}