{
  "type": "Feature",
  "properties": {
    "iso:country":"US",
    "sg:address":"1343 Lane Ave S",
    "sg:city":"Jacksonville",
    "sg:classifiers":[
        {
            "category":"Retail",
            "subcategory":"Auto Repair",
            "type":"Services"
        }
    ],
    "sg:phone":"+1 904 781 8222",
    "sg:postcode":"32205",
    "sg:province":"FL",
    "sg:tags":[
        "repairing",
        "automobile"
    ],
    "wof:name":"Paul's Auto Care",
    "wof:placetype":"venue"
},
  "geometry": {"coordinates":[-81.75182599999999,30.298153],"type":"Point"}
}