{
  "type": "Feature",
  "properties": {
    "addr:full":"1283 S Tamiami Trl Sarasota FL 34239",
    "addr:housenumber":"1283",
    "addr:postcode":"34239",
    "addr:street":"S Tamiami Trl",
    "iso:country":"US",
    "sg:address":"1283 S Tamiami Trl",
    "sg:city":"Sarasota",
    "sg:classifiers":[
        {
            "category":"Professional",
            "subcategory":"Management & Consulting",
            "type":"Services"
        }
    ],
    "sg:phone":"+1 941 955 2675",
    "sg:postcode":"34239",
    "sg:province":"FL",
    "sg:tags":[
        "consultant",
        "wine"
    ],
    "wof:name":"Michael's Wine Cellar",
    "wof:placetype":"venue"
},
  "geometry": {"coordinates":[-82.52964900000001,27.322592],"type":"Point"}
}