{
  "type": "Feature",
  "properties": {
    "iso:country":"US",
    "sg:address":"9141 Lake Park Cir N",
    "sg:city":"Fort Lauderdale",
    "sg:classifiers":[
        {
            "category":"Wholesale",
            "subcategory":"Home Furnishings",
            "type":"Manufacturing & Wholesale Goods"
        }
    ],
    "sg:phone":"+1 954 236 6858",
    "sg:postcode":"33328",
    "sg:province":"FL",
    "wof:name":"Decor-N-More",
    "wof:placetype":"venue"
},
  "geometry": {"coordinates":[-80.27088000000001,26.089653],"type":"Point"}
}