{
  "type": "Feature",
  "properties": {
    "addr:full":"16502 N Dale Mabry Hwy Tampa FL 33618",
    "addr:housenumber":"16502",
    "addr:postcode":"33618",
    "addr:street":"N Dale Mabry Hwy",
    "iso:country":"US",
    "sg:address":"16502 N Dale Mabry Hwy",
    "sg:city":"Tampa",
    "sg:classifiers":[
        {
            "category":"Banks & Credit Unions",
            "subcategory":"Investment Brokerage",
            "type":"Services"
        }
    ],
    "sg:phone":"+1 813 936 0222",
    "sg:postcode":"33618",
    "sg:province":"FL",
    "sg:tags":[
        "consultant",
        "planning",
        "financial"
    ],
    "wof:name":"Taylor & Williams Inc",
    "wof:placetype":"venue"
},
  "geometry": {"coordinates":[-82.502422,28.108236],"type":"Point"}
}