{
  "type": "Feature",
  "properties": {
    "addr:full":"4600 SW 46th Ave Ocala FL 34474",
    "addr:housenumber":"4600",
    "addr:postcode":"34474",
    "addr:street":"Sw 46Th Ave",
    "iso:country":"US",
    "sg:address":"4600 SW 46th Ave",
    "sg:city":"Ocala",
    "sg:classifiers":[
        {
            "category":"Health Services",
            "subcategory":"Doctor",
            "type":"Services"
        }
    ],
    "sg:phone":"+1 352 732 6500",
    "sg:postcode":"34474",
    "sg:province":"FL",
    "sg:tags":[
        "physician",
        "surgeon"
    ],
    "wof:name":"James B Dolan MD",
    "wof:placetype":"venue"
},
  "geometry": {"coordinates":[-82.197625,29.142281],"type":"Point"}
}