{
  "type": "Feature",
  "properties": {
    "addr:full":"159 Coralwood Cir Kissimmee FL 34743",
    "addr:housenumber":"159",
    "addr:postcode":"34743",
    "addr:street":"Coralwood Cir",
    "iso:country":"US",
    "sg:address":"159 Coralwood Cir",
    "sg:city":"Kissimmee",
    "sg:classifiers":[
        {
            "category":"Home & Garden",
            "subcategory":"Furniture",
            "type":"Retail Goods"
        }
    ],
    "sg:phone":"+1 407 348 3293",
    "sg:postcode":"34743",
    "sg:province":"FL",
    "wof:name":"Ambiance Furniture Inc",
    "wof:placetype":"venue"
},
  "geometry": {"coordinates":[-81.37643,28.344031],"type":"Point"}
}