{
  "type": "Feature",
  "properties": {
    "iso:country":"US",
    "sg:address":"9558 NW 41st St",
    "sg:city":"Doral",
    "sg:classifiers":[
        {
            "category":"Insurance",
            "subcategory":"Insurance Agent",
            "type":"Services"
        },
        {
            "category":"Insurance",
            "subcategory":"Hazard Insurance",
            "type":"Services"
        },
        {
            "category":"Insurance",
            "subcategory":"Title Insurance",
            "type":"Services"
        },
        {
            "category":"Insurance",
            "subcategory":"Life Insurance",
            "type":"Services"
        }
    ],
    "sg:phone":"+1 305 477 4864",
    "sg:postcode":"33178",
    "sg:province":"FL",
    "sg:tags":[
        "business",
        "auto",
        "commercial",
        "homeowner",
        "motorcycle",
        "renter"
    ],
    "wof:name":"Allstate Insurance Company - Fernando Oyarzun",
    "wof:placetype":"venue"
},
  "geometry": {"coordinates":[-80.348969,25.811544],"type":"Point"}
}