{
  "type": "Feature",
  "properties": {
    "addr:full":"1120 Andalusia Ave Coral Gables FL 33134",
    "addr:housenumber":"1120",
    "addr:postcode":"33134",
    "addr:street":"Andalusia Ave",
    "iso:country":"US",
    "sg:address":"1120 Andalusia Ave",
    "sg:city":"Coral Gables",
    "sg:classifiers":[
        {
            "category":"Recreation",
            "subcategory":"Playground",
            "type":"Entertainment"
        },
        {
            "category":"Sports & Exercise",
            "subcategory":"Tennis Court",
            "type":"Entertainment"
        }
    ],
    "sg:phone":"+1 305 460 5333",
    "sg:postcode":"33134",
    "sg:province":"FL",
    "wof:name":"Salvadore Park",
    "wof:placetype":"venue"
},
  "geometry": {"coordinates":[-80.27807900000001,25.747304],"type":"Point"}
}