{
  "type": "Feature",
  "properties": {
    "iso:country":"US",
    "sg:address":"1788 NW 23rd St",
    "sg:city":"Miami",
    "sg:classifiers":[
        {
            "category":"Building & Trades",
            "subcategory":"Plumbing",
            "type":"Services"
        }
    ],
    "sg:phone":"+1 305 633 8917",
    "sg:postcode":"33142",
    "sg:province":"FL",
    "sg:tags":[
        "contractor"
    ],
    "wof:name":"P & R Smith Corp",
    "wof:placetype":"venue"
},
  "geometry": {"coordinates":[-80.22380699999999,25.798351],"type":"Point"}
}