{
  "type": "Feature",
  "properties": {
    "iso:country":"US",
    "sg:address":"1446 Windjammer Loop",
    "sg:city":"Lutz",
    "sg:classifiers":[
        {
            "category":"Manufacturing",
            "subcategory":"Apparel",
            "type":"Manufacturing & Wholesale Goods"
        }
    ],
    "sg:phone":"+1 813 949 6213",
    "sg:postcode":"33559",
    "sg:province":"FL",
    "sg:tags":[
        "dress",
        "mfg"
    ],
    "wof:name":"Crystal Shamrocks LLC",
    "wof:placetype":"venue"
},
  "geometry": {"coordinates":[-82.42146200000001,28.178091],"type":"Point"}
}