{
  "type": "Feature",
  "properties": {
    "iso:country":"US",
    "sg:address":"12465 2nd St E",
    "sg:city":"Treasure Island",
    "sg:classifiers":[
        {
            "category":"Professional",
            "subcategory":"Lawyer & Legal Services",
            "type":"Services"
        }
    ],
    "sg:phone":"+1 727 363 1103",
    "sg:postcode":"33706",
    "sg:province":"FL",
    "sg:tags":[
        "attorney"
    ],
    "wof:name":"Otto Halboth",
    "wof:placetype":"venue"
},
  "geometry": {"coordinates":[-82.776527,27.781034],"type":"Point"}
}