{
  "type": "Feature",
  "properties": {
    "addr:full":"1902 7th Ct N Lake Worth FL 33461",
    "addr:housenumber":"1902",
    "addr:postcode":"33461",
    "addr:street":"7Th Ct N",
    "iso:country":"US",
    "sg:address":"1902 7th Ct N",
    "sg:city":"Lake Worth",
    "sg:classifiers":[
        {
            "category":"Manufacturing",
            "subcategory":"Metals",
            "type":"Manufacturing & Wholesale Goods"
        }
    ],
    "sg:phone":"+1 561 547 4613",
    "sg:postcode":"33461",
    "sg:province":"FL",
    "sg:tags":[
        "door",
        "mfg"
    ],
    "wof:name":"International Door",
    "wof:placetype":"venue"
},
  "geometry": {"coordinates":[-80.07249299999999,26.62479],"type":"Point"}
}