{
  "type": "Feature",
  "properties": {
    "iso:country":"US",
    "sg:address":"2060 Biscayne Blvd",
    "sg:city":"Miami",
    "sg:classifiers":[
        {
            "category":"Autos & Motor Vehicles",
            "subcategory":"Automobile Sales",
            "type":"Retail Goods"
        }
    ],
    "sg:phone":"+1 877 215 1576",
    "sg:postcode":"33137",
    "sg:province":"FL",
    "sg:tags":[
        "car"
    ],
    "sg:website":"www.bramanminiofmiami.com",
    "wof:name":"Braman BMW/Mini",
    "wof:placetype":"venue"
},
  "geometry": {"coordinates":[-80.18997899999999,25.796831],"type":"Point"}
}