{
  "type": "Feature",
  "properties": {
    "addr:full":"7936 Rutillio Ct New Port Richey FL 34653",
    "addr:housenumber":"7936",
    "addr:postcode":"34653",
    "addr:street":"Rutillio Ct",
    "iso:country":"US",
    "sg:address":"7936 Rutillio Ct",
    "sg:city":"New Port Richey",
    "sg:classifiers":[
        {
            "category":"Banks & Credit Unions",
            "subcategory":"Investment Brokerage",
            "type":"Services"
        }
    ],
    "sg:phone":"+1 727 848 4009",
    "sg:postcode":"34653",
    "sg:province":"FL",
    "sg:tags":[
        "consultant",
        "planning",
        "financial"
    ],
    "wof:name":"CCM Investments",
    "wof:placetype":"venue"
},
  "geometry": {"coordinates":[-82.70447799999999,28.271731],"type":"Point"}
}