{
  "type": "Feature",
  "properties": {
    "iso:country":"US",
    "sg:address":"111 SW 107th Ave",
    "sg:city":"Miami",
    "sg:classifiers":[
        {
            "category":"Professional",
            "subcategory":"Accounting & Tax Preparation",
            "type":"Services"
        }
    ],
    "sg:phone":"+1 305 225 6743",
    "sg:postcode":"33174",
    "sg:province":"FL",
    "sg:tags":[
        "accountant"
    ],
    "wof:name":"Jose Espinales CPA",
    "wof:placetype":"venue"
},
  "geometry": {"coordinates":[-80.368842,25.767674],"type":"Point"}
}