{
  "type": "Feature",
  "properties": {
    "addr:full":"1307 Central Park Dr Sanford FL 32771",
    "addr:housenumber":"1307",
    "addr:postcode":"32771",
    "addr:street":"Central Park Dr",
    "iso:country":"US",
    "sg:address":"1307 Central Park Dr",
    "sg:city":"Sanford",
    "sg:classifiers":[
        {
            "category":"Retail",
            "subcategory":"Auto Repair",
            "type":"Services"
        }
    ],
    "sg:phone":"+1 407 302 0117",
    "sg:postcode":"32771",
    "sg:province":"FL",
    "sg:tags":[
        "body"
    ],
    "wof:name":"Scratchmaster",
    "wof:placetype":"venue"
},
  "geometry": {"coordinates":[-81.316405,28.800886],"type":"Point"}
}