{
  "type": "Feature",
  "properties": {
    "iso:country":"US",
    "sg:address":"3033 Hartley Rd",
    "sg:city":"Jacksonville",
    "sg:classifiers":[
        {
            "category":"Banks & Credit Unions",
            "subcategory":"Bank",
            "type":"Services"
        }
    ],
    "sg:phone":"+1 904 880 3199",
    "sg:postcode":"32257",
    "sg:province":"FL",
    "sg:tags":[
        "broker",
        "mortgage"
    ],
    "wof:name":"Diversfied Mrtg Assoc of N Fla",
    "wof:placetype":"venue"
},
  "geometry": {"coordinates":[-81.631196,30.184987],"type":"Point"}
}