{
  "type": "Feature",
  "properties": {
    "addr:full":"818 4th St N Saint Petersburg FL 33701",
    "addr:housenumber":"818",
    "addr:postcode":"33701",
    "addr:street":"4Th St N",
    "iso:country":"US",
    "sg:address":"818 4th St N",
    "sg:city":"Saint Petersburg",
    "sg:classifiers":[
        {
            "category":"Social Services",
            "type":"Services"
        }
    ],
    "sg:phone":"+1 727 898 3111",
    "sg:postcode":"33701",
    "sg:province":"FL",
    "wof:name":"Red Cross",
    "wof:placetype":"venue"
},
  "geometry": {"coordinates":[-82.638639,27.78106],"type":"Point"}
}