{
  "type": "Feature",
  "properties": {
    "iso:country":"US",
    "sg:address":"7929 Atlantic Wy",
    "sg:city":"Miami Beach",
    "sg:classifiers":[
        {
            "category":"Recreation",
            "subcategory":"Water Park",
            "type":"Entertainment"
        },
        {
            "category":"Restaurant",
            "type":"Food & Drink"
        },
        {
            "category":"Park",
            "type":"Public Place"
        }
    ],
    "sg:phone":"+1 305 993 2032",
    "sg:postcode":"33141",
    "sg:province":"FL",
    "sg:tags":[
        "local",
        "flavor",
        "beach"
    ],
    "wof:name":"North Shore State Recreation Area",
    "wof:placetype":"venue"
},
  "geometry": {"coordinates":[-80.120165,25.864745],"type":"Point"}
}