{
  "type": "Feature",
  "properties": {
    "iso:country":"US",
    "sg:address":"18750 S River Rd",
    "sg:city":"Alva",
    "sg:classifiers":[
        {
            "category":"Building & Trades",
            "subcategory":"Construction",
            "type":"Services"
        }
    ],
    "sg:phone":"+1 239 728 2763",
    "sg:postcode":"33920",
    "sg:province":"FL",
    "sg:tags":[
        "specializing",
        "home",
        "comm",
        "contractor"
    ],
    "wof:name":"Carl A Mellquist General Contr",
    "wof:placetype":"venue"
},
  "geometry": {"coordinates":[-81.64224299999999,26.7157],"type":"Point"}
}