{
  "type": "Feature",
  "properties": {
    "addr:full":"6511 Cay Cir Orlando FL 32809",
    "addr:housenumber":"6511",
    "addr:postcode":"32809",
    "addr:street":"Cay Cir",
    "iso:country":"US",
    "sg:address":"6511 Cay Cir",
    "sg:city":"Orlando",
    "sg:classifiers":[
        {
            "category":"Shopping",
            "subcategory":"Used Merchandise",
            "type":"Retail Goods"
        }
    ],
    "sg:phone":"+1 407 240 2705",
    "sg:postcode":"32809",
    "sg:province":"FL",
    "wof:name":"Chloes Collection Inc",
    "wof:placetype":"venue"
},
  "geometry": {"coordinates":[-81.360467,28.466755],"type":"Point"}
}