{
  "type": "Feature",
  "properties": {
    "iso:country":"US",
    "sg:address":"1450 Madruga Ave Ste 302",
    "sg:city":"Coral Gables",
    "sg:classifiers":[
        {
            "category":"Professional",
            "subcategory":"Lawyer & Legal Services",
            "type":"Services"
        }
    ],
    "sg:phone":"+1 305 670 1188",
    "sg:postcode":"33146",
    "sg:province":"FL",
    "sg:tags":[
        "litigation"
    ],
    "sg:website":"www.deeblaw.com",
    "wof:name":"Deeb Kevin L Law Office",
    "wof:placetype":"venue"
},
  "geometry": {"coordinates":[-80.28223300000001,25.708928],"type":"Point"}
}