{
  "type": "Feature",
  "properties": {
    "addr:full":"4352 Avalon Blvd Milton FL 32583",
    "addr:housenumber":"4352",
    "addr:postcode":"32583",
    "addr:street":"Avalon Blvd",
    "iso:country":"US",
    "sg:address":"4352 Avalon Blvd",
    "sg:city":"Milton",
    "sg:classifiers":[
        {
            "category":"Retail",
            "subcategory":"Car Wash",
            "type":"Services"
        }
    ],
    "sg:phone":"+1 850 981 9115",
    "sg:postcode":"32583",
    "sg:province":"FL",
    "sg:tags":[
        "automobile",
        "detail",
        "clean"
    ],
    "wof:name":"Carewash Auto Club",
    "wof:placetype":"venue"
},
  "geometry": {"coordinates":[-87.081064,30.592968],"type":"Point"}
}