{
  "type": "Feature",
  "properties": {
    "addr:full":"30750 Watson Blvd Big Pine Key FL 33043",
    "addr:housenumber":"30750",
    "addr:postcode":"33043",
    "addr:street":"Watson Blvd",
    "iso:country":"US",
    "sg:address":"30750 Watson Blvd",
    "sg:city":"Big Pine Key",
    "sg:classifiers":[
        {
            "category":"Building & Trades",
            "subcategory":"Construction",
            "type":"Services"
        }
    ],
    "sg:phone":"+1 305 872 2052",
    "sg:postcode":"33043",
    "sg:province":"FL",
    "sg:tags":[
        "marine"
    ],
    "wof:name":"Muddobbers Inc",
    "wof:placetype":"venue"
},
  "geometry": {"coordinates":[-81.356768,24.6964],"type":"Point"}
}