{
  "type": "Feature",
  "properties": {
    "addr:full":"4545 Mariotti Ct Sarasota FL 34233",
    "addr:housenumber":"4545",
    "addr:postcode":"34233",
    "addr:street":"Mariotti Ct",
    "iso:country":"US",
    "sg:address":"4545 Mariotti Ct",
    "sg:city":"Sarasota",
    "sg:classifiers":[
        {
            "category":"Building & Trades",
            "subcategory":"Construction",
            "type":"Services"
        }
    ],
    "sg:phone":"+1 941 922 6184",
    "sg:postcode":"34233",
    "sg:province":"FL",
    "sg:tags":[
        "special",
        "contractor"
    ],
    "wof:name":"Ken White Paving Inc",
    "wof:placetype":"venue"
},
  "geometry": {"coordinates":[-82.480266,27.275471],"type":"Point"}
}