{
  "type": "Feature",
  "properties": {
    "iso:country":"US",
    "sg:address":"3015 SW 54th Ave",
    "sg:city":"Davie",
    "sg:classifiers":[
        {
            "category":"Home & Garden",
            "subcategory":"Building Materials",
            "type":"Retail Goods"
        }
    ],
    "sg:phone":"+1 954 587 8833",
    "sg:postcode":"33314",
    "sg:province":"FL",
    "sg:tags":[
        "water",
        "waste",
        "treatment"
    ],
    "wof:name":"Tindall Hammock Soil Coins",
    "wof:placetype":"venue"
},
  "geometry": {"coordinates":[-80.222155,26.082591],"type":"Point"}
}