{
  "type": "Feature",
  "properties": {
    "iso:country":"US",
    "sg:address":"12600 SW 120th St Ste 107",
    "sg:city":"Miami",
    "sg:classifiers":[
        {
            "category":"Health Services",
            "subcategory":"Doctor",
            "type":"Services"
        }
    ],
    "sg:phone":"+1 305 969 6954",
    "sg:postcode":"33186",
    "sg:province":"FL",
    "sg:tags":[
        "dermatologist"
    ],
    "sg:website":"www.drkarenkade.com",
    "wof:name":"Karen R Kade, MD",
    "wof:placetype":"venue"
},
  "geometry": {"coordinates":[-80.398584,25.656791],"type":"Point"}
}