{
  "type": "Feature",
  "properties": {
    "iso:country":"US",
    "sg:address":"2939 S Florida Ave",
    "sg:city":"Lakeland",
    "sg:classifiers":[
        {
            "category":"Health Services",
            "subcategory":"Podiatrist",
            "type":"Services"
        }
    ],
    "sg:phone":"+1 863 687 3404",
    "sg:postcode":"33803",
    "sg:province":"FL",
    "wof:name":"Fazekas Edward A DPM",
    "wof:placetype":"venue"
},
  "geometry": {"coordinates":[-81.957099,28.010445],"type":"Point"}
}