{
  "type": "Feature",
  "properties": {
    "iso:country":"US",
    "sg:address":"4024 Pembroke Rd",
    "sg:city":"Hollywood",
    "sg:classifiers":[
        {
            "category":"Personal",
            "subcategory":"Barber",
            "type":"Services"
        }
    ],
    "sg:phone":"+1 954 963 9314",
    "sg:postcode":"33021",
    "sg:province":"FL",
    "wof:name":"Sam's Barber Shop",
    "wof:placetype":"venue"
},
  "geometry": {"coordinates":[-80.185174,25.995512],"type":"Point"}
}