{
  "type": "Feature",
  "properties": {
    "addr:full":"10327 NW 27th Ave Miami FL 33147",
    "addr:housenumber":"10327",
    "addr:postcode":"33147",
    "addr:street":"Nw 27Th Ave",
    "iso:country":"US",
    "sg:address":"10327 NW 27th Ave",
    "sg:city":"Miami",
    "sg:classifiers":[
        {
            "category":"Building & Trades",
            "subcategory":"Locksmith",
            "type":"Services"
        }
    ],
    "sg:phone":"+1 305 351 8011",
    "sg:postcode":"33147",
    "sg:province":"FL",
    "sg:tags":[
        "key"
    ],
    "wof:name":"A 1 24 Hour 7 Day Emerg Locksmith",
    "wof:placetype":"venue"
},
  "geometry": {"coordinates":[-80.24225199999999,25.868447],"type":"Point"}
}