{
  "type": "Feature",
  "properties": {
    "addr:full":"6905 W 12th Ct Hialeah FL 33014",
    "addr:housenumber":"6905",
    "addr:postcode":"33014",
    "addr:street":"W 12Th Ct",
    "iso:country":"US",
    "sg:address":"6905 W 12th Ct",
    "sg:city":"Hialeah",
    "sg:classifiers":[
        {
            "category":"Shopping",
            "subcategory":"Optical Goods",
            "type":"Retail Goods"
        }
    ],
    "sg:phone":"+1 305 823 5525",
    "sg:postcode":"33014",
    "sg:province":"FL",
    "wof:name":"Owl Optacal 305 823 2020",
    "wof:placetype":"venue"
},
  "geometry": {"coordinates":[-80.308429,25.887933],"type":"Point"}
}