{
  "type": "Feature",
  "properties": {
    "iso:country":"US",
    "sg:address":"1791 Boy Scout Dr",
    "sg:city":"Fort Myers",
    "sg:classifiers":[
        {
            "category":"Health Services",
            "subcategory":"Clinic",
            "type":"Services"
        }
    ],
    "sg:phone":"+1 239 931 6777",
    "sg:postcode":"33907",
    "sg:province":"FL",
    "sg:tags":[
        "home"
    ],
    "wof:name":"Maxim Healthcare Svc",
    "wof:placetype":"venue"
},
  "geometry": {"coordinates":[-81.878378,26.581711],"type":"Point"}
}