{
  "type": "Feature",
  "properties": {
    "iso:country":"US",
    "sg:address":"131 Flamingo Rd",
    "sg:city":"Venice",
    "sg:classifiers":[
        {
            "category":"Food & Beverages",
            "subcategory":"Groceries & Convenience Stores",
            "type":"Retail Goods"
        }
    ],
    "sg:phone":"+1 941 408 0013",
    "sg:postcode":"34293",
    "sg:province":"FL",
    "wof:name":"Bolams Mobil Mart",
    "wof:placetype":"venue"
},
  "geometry": {"coordinates":[-82.405942,27.045676],"type":"Point"}
}