{
  "type": "Feature",
  "properties": {
    "iso:country":"US",
    "sg:address":"7109 N Armenia Ave",
    "sg:city":"Tampa",
    "sg:classifiers":[
        {
            "category":"Health Services",
            "subcategory":"Chiropractor",
            "type":"Services"
        }
    ],
    "sg:phone":"+1 813 933 5370",
    "sg:postcode":"33604",
    "sg:province":"FL",
    "wof:name":"Omar Inaty DC",
    "wof:placetype":"venue"
},
  "geometry": {"coordinates":[-82.48516100000001,28.014175],"type":"Point"}
}