{
  "type": "Feature",
  "properties": {
    "iso:country":"US",
    "sg:address":"425 Mary Esther Cutoff",
    "sg:city":"Fort Walton Beach",
    "sg:classifiers":[
        {
            "category":"Freight",
            "type":"Transportation"
        }
    ],
    "sg:phone":"+1 850 243 1346",
    "sg:postcode":"32548",
    "sg:province":"FL",
    "sg:tags":[
        "warehouse"
    ],
    "wof:name":"Life Style",
    "wof:placetype":"venue"
},
  "geometry": {"coordinates":[-86.644093,30.425262],"type":"Point"}
}