{
  "type": "Feature",
  "properties": {
    "iso:country":"US",
    "sg:address":"11985 US Hwy 1",
    "sg:city":"Juno Beach",
    "sg:classifiers":[
        {
            "category":"Restaurant",
            "type":"Food & Drink"
        }
    ],
    "sg:phone":"+1 561 625 3708",
    "sg:postcode":"33408",
    "sg:province":"FL",
    "sg:tags":[
        "grocery",
        "eating"
    ],
    "wof:name":"Crazy Cuban",
    "wof:placetype":"venue"
},
  "geometry": {"coordinates":[-80.05870299999999,26.851996],"type":"Point"}
}