{
  "type": "Feature",
  "properties": {
    "addr:full":"1548 NE 4th Ave Fort Lauderdale FL 33304",
    "addr:housenumber":"1548",
    "addr:postcode":"33304",
    "addr:street":"Ne 4Th Ave",
    "iso:country":"US",
    "sg:address":"1548 NE 4th Ave",
    "sg:city":"Fort Lauderdale",
    "sg:classifiers":[
        {
            "category":"Real Estate",
            "subcategory":"Real Estate Agent",
            "type":"Services"
        }
    ],
    "sg:phone":"+1 954 728 9563",
    "sg:postcode":"33304",
    "sg:province":"FL",
    "wof:name":"Dependable Realty Inc",
    "wof:placetype":"venue"
},
  "geometry": {"coordinates":[-80.140666,26.146686],"type":"Point"}
}