{
  "type": "Feature",
  "properties": {
    "iso:country":"US",
    "sg:address":"826 N John St",
    "sg:city":"Orlando",
    "sg:classifiers":[
        {
            "category":"Professional",
            "subcategory":"Computer Services",
            "type":"Services"
        }
    ],
    "sg:phone":"+1 800 668 7325",
    "sg:postcode":"32808",
    "sg:province":"FL",
    "sg:tags":[
        "prepackaged",
        "software",
        "custom"
    ],
    "wof:name":"Cartit Corporation",
    "wof:placetype":"venue"
},
  "geometry": {"coordinates":[-81.46259000000001,28.552892],"type":"Point"}
}