{
  "type": "Feature",
  "properties": {
    "addr:full":"2103 Sylvester Ct Lakeland FL 33803",
    "addr:housenumber":"2103",
    "addr:postcode":"33803",
    "addr:street":"Sylvester Ct",
    "iso:country":"US",
    "sg:address":"2103 Sylvester Ct",
    "sg:city":"Lakeland",
    "sg:classifiers":[
        {
            "category":"Building & Trades",
            "subcategory":"Construction",
            "type":"Services"
        }
    ],
    "sg:phone":"+1 863 687 2222",
    "sg:postcode":"33803",
    "sg:province":"FL",
    "sg:tags":[
        "residential"
    ],
    "wof:name":"Jonathan Conner",
    "wof:placetype":"venue"
},
  "geometry": {"coordinates":[-81.923784,28.018527],"type":"Point"}
}