{
  "type": "Feature",
  "properties": {
    "iso:country":"US",
    "sg:address":"5550 Lakewood Cir S Apt H",
    "sg:city":"Margate",
    "sg:classifiers":[
        {
            "category":"Building & Trades",
            "subcategory":"Construction",
            "type":"Services"
        }
    ],
    "sg:phone":"+1 954 957 8282",
    "sg:postcode":"33063",
    "sg:province":"FL",
    "sg:tags":[
        "system",
        "specialty",
        "heating",
        "contractor",
        "air conditioning"
    ],
    "wof:name":"Air Electric Inc",
    "wof:placetype":"venue"
},
  "geometry": {"coordinates":[-80.199742,26.231964],"type":"Point"}
}