{
  "type": "Feature",
  "properties": {
    "iso:country":"US",
    "sg:address":"280 24th Ave",
    "sg:city":"Apalachicola",
    "sg:classifiers":[
        {
            "category":"Building & Trades",
            "subcategory":"Plumbing",
            "type":"Services"
        }
    ],
    "sg:phone":"+1 850 670 8168",
    "sg:postcode":"32320",
    "sg:province":"FL",
    "sg:tags":[
        "contractor"
    ],
    "wof:name":"B & K Plumbing",
    "wof:placetype":"venue"
},
  "geometry": {"coordinates":[-85.003164,29.724949],"type":"Point"}
}