{
  "type": "Feature",
  "properties": {
    "iso:country":"US",
    "sg:address":"1931 SW 52nd Ave",
    "sg:city":"Fort Lauderdale",
    "sg:classifiers":[
        {
            "category":"Professional",
            "subcategory":"Management & Consulting",
            "type":"Services"
        }
    ],
    "sg:phone":"+1 954 321 8532",
    "sg:postcode":"33317",
    "sg:province":"FL",
    "wof:name":"Zuzu Blue Inc",
    "wof:placetype":"venue"
},
  "geometry": {"coordinates":[-80.22034499999999,26.096362],"type":"Point"}
}