{
  "type": "Feature",
  "properties": {
    "iso:country":"US",
    "sg:address":"71 Miramar Beach Dr",
    "sg:city":"Destin",
    "sg:classifiers":[
        {
            "category":"Utilities",
            "subcategory":"Water",
            "type":"Services"
        }
    ],
    "sg:phone":"+1 850 654 1242",
    "sg:postcode":"32550",
    "sg:province":"FL",
    "sg:tags":[
        "company",
        "sewage"
    ],
    "wof:name":"South Walton Utility Co Inc",
    "wof:placetype":"venue"
},
  "geometry": {"coordinates":[-86.358422,30.38122],"type":"Point"}
}