{
  "type": "Feature",
  "properties": {
    "iso:country":"US",
    "sg:address":"922 Pine Shadow Dr",
    "sg:city":"Apopka",
    "sg:classifiers":[
        {
            "category":"Shopping",
            "subcategory":"Clothing, Apparel, & Fashions",
            "type":"Retail Goods"
        }
    ],
    "sg:phone":"+1 407 880 1299",
    "sg:postcode":"32712",
    "sg:province":"FL",
    "wof:name":"Proline Uniform & Accessorie",
    "wof:placetype":"venue"
},
  "geometry": {"coordinates":[-81.497202,28.710378],"type":"Point"}
}