{
  "type": "Feature",
  "properties": {
    "addr:full":"255 Minorca Ave Miami FL 33134",
    "addr:housenumber":"255",
    "addr:postcode":"33134",
    "addr:street":"Minorca Ave",
    "iso:country":"US",
    "sg:address":"255 Minorca Ave",
    "sg:city":"Miami",
    "sg:classifiers":[
        {
            "category":"Professional",
            "type":"Services"
        }
    ],
    "sg:phone":"+1 305 446 9509",
    "sg:postcode":"33134",
    "sg:province":"FL",
    "wof:name":"Caravelas USA LLC",
    "wof:placetype":"venue"
},
  "geometry": {"coordinates":[-80.259823,25.753782],"type":"Point"}
}