{
  "type": "Feature",
  "properties": {
    "iso:country":"US",
    "sg:address":"11571 Beach Blvd",
    "sg:city":"Jacksonville",
    "sg:classifiers":[
        {
            "category":"Taxi",
            "type":"Transportation"
        },
        {
            "category":"Retail",
            "subcategory":"Auto Rental",
            "type":"Services"
        }
    ],
    "sg:phone":"+1 904 265 5466",
    "sg:postcode":"32246",
    "sg:province":"FL",
    "sg:tags":[
        "limousine"
    ],
    "wof:name":"Vip Limousine Inc",
    "wof:placetype":"venue"
},
  "geometry": {"coordinates":[-81.520233,30.287081],"type":"Point"}
}