{
  "type": "Feature",
  "properties": {
    "addr:full":"7250 NW 58th St Miami FL 33166",
    "addr:housenumber":"7250",
    "addr:postcode":"33166",
    "addr:street":"Nw 58Th St",
    "iso:country":"US",
    "sg:address":"7250 NW 58th St",
    "sg:city":"Miami",
    "sg:classifiers":[
        {
            "category":"Communications",
            "subcategory":"Radio Station",
            "type":"Services"
        }
    ],
    "sg:phone":"+1 786 497 3410",
    "sg:postcode":"33166",
    "sg:province":"FL",
    "sg:tags":[
        "broadcast"
    ],
    "wof:name":"Wnma",
    "wof:placetype":"venue"
},
  "geometry": {"coordinates":[-80.316303,25.8262],"type":"Point"}
}