{
  "type": "Feature",
  "properties": {
    "iso:country":"US",
    "sg:address":"8025 SW 62nd Pl",
    "sg:city":"Miami",
    "sg:classifiers":[
        {
            "category":"Professional",
            "type":"Services"
        }
    ],
    "sg:phone":"+1 305 667 6921",
    "sg:postcode":"33143",
    "sg:province":"FL",
    "wof:name":"Gail Satz PA",
    "wof:placetype":"venue"
},
  "geometry": {"coordinates":[-80.294617,25.695046],"type":"Point"}
}