{
  "type": "Feature",
  "properties": {
    "iso:country":"US",
    "sg:address":"422 SW 2nd Ter Ste 110",
    "sg:city":"Cape Coral",
    "sg:classifiers":[
        {
            "category":"Shopping",
            "subcategory":"Used Merchandise",
            "type":"Retail Goods"
        }
    ],
    "sg:phone":"+1 239 458 7773",
    "sg:postcode":"33991",
    "sg:province":"FL",
    "sg:tags":[
        "vintage",
        "consignment"
    ],
    "sg:website":"www.guysanddollsnewtoyou.com",
    "wof:name":"Guys & Dolls New To You",
    "wof:placetype":"venue"
},
  "geometry": {"coordinates":[-81.983749,26.645184],"type":"Point"}
}