{
  "type": "Feature",
  "properties": {
    "addr:full":"11200 Woodland Waters Blvd Weeki Wachee FL 34613",
    "addr:housenumber":"11200",
    "addr:postcode":"34613",
    "addr:street":"Woodland Waters Blvd",
    "iso:country":"US",
    "sg:address":"11200 Woodland Waters Blvd",
    "sg:city":"Weeki Wachee",
    "sg:classifiers":[
        {
            "category":"Professional",
            "subcategory":"Management & Consulting",
            "type":"Services"
        }
    ],
    "sg:phone":"+1 352 597 3769",
    "sg:postcode":"34613",
    "sg:province":"FL",
    "sg:tags":[
        "consultant",
        "educational"
    ],
    "wof:name":"Cenapas Corp",
    "wof:placetype":"venue"
},
  "geometry": {"coordinates":[-82.540491,28.563673],"type":"Point"}
}