{
  "type": "Feature",
  "properties": {
    "addr:full":"400 Ederington Dr Brooksville FL 34601",
    "addr:housenumber":"400",
    "addr:postcode":"34601",
    "addr:street":"Ederington Dr",
    "iso:country":"US",
    "sg:address":"400 Ederington Dr",
    "sg:city":"Brooksville",
    "sg:classifiers":[
        {
            "category":"Building & Trades",
            "subcategory":"Landscaping Services",
            "type":"Services"
        }
    ],
    "sg:phone":"+1 352 754 9408",
    "sg:postcode":"34601",
    "sg:province":"FL",
    "sg:tags":[
        "landscape"
    ],
    "wof:name":"Jerry Landscaping",
    "wof:placetype":"venue"
},
  "geometry": {"coordinates":[-82.392032,28.568106],"type":"Point"}
}