{
  "type": "Feature",
  "properties": {
    "addr:full":"7360 SW 48th St Miami FL 33155",
    "addr:housenumber":"7360",
    "addr:postcode":"33155",
    "addr:street":"Sw 48Th St",
    "iso:country":"US",
    "sg:address":"7360 SW 48th St",
    "sg:city":"Miami",
    "sg:classifiers":[
        {
            "category":"Manufacturing",
            "subcategory":"Electronics",
            "type":"Manufacturing & Wholesale Goods"
        }
    ],
    "sg:phone":"+1 786 206 3966",
    "sg:postcode":"33155",
    "sg:province":"FL",
    "sg:tags":[
        "printers-equipment",
        "supply"
    ],
    "sg:website":"http://www.microgeo-usa.com",
    "wof:name":"Microgeo Usa",
    "wof:placetype":"venue"
},
  "geometry": {"coordinates":[-80.314294,25.725466],"type":"Point"}
}