{
  "type": "Feature",
  "properties": {
    "iso:country":"US",
    "sg:address":"4931 NW 54th St",
    "sg:city":"Coconut Creek",
    "sg:classifiers":[
        {
            "category":"Building & Trades",
            "subcategory":"Cleaning & Sanitation",
            "type":"Services"
        }
    ],
    "sg:phone":"+1 954 421 4770",
    "sg:postcode":"33073",
    "sg:province":"FL",
    "sg:tags":[
        "janitor"
    ],
    "wof:name":"Bill's Building Maintenance",
    "wof:placetype":"venue"
},
  "geometry": {"coordinates":[-80.19049699999999,26.297579],"type":"Point"}
}