{
  "type": "Feature",
  "properties": {
    "addr:full":"5110 Bayshore Blvd Tampa FL 33611",
    "addr:housenumber":"5110",
    "addr:postcode":"33611",
    "addr:street":"Bayshore Blvd",
    "iso:country":"US",
    "sg:address":"5110 Bayshore Blvd",
    "sg:city":"Tampa",
    "sg:classifiers":[
        {
            "category":"Building & Trades",
            "subcategory":"Construction",
            "type":"Services"
        }
    ],
    "sg:phone":"+1 813 835 5080",
    "sg:postcode":"33611",
    "sg:province":"FL",
    "sg:tags":[
        "house"
    ],
    "wof:name":"Robert H Delafield Inc",
    "wof:placetype":"venue"
},
  "geometry": {"coordinates":[-82.485649,27.889823],"type":"Point"}
}