{
  "type": "Feature",
  "properties": {
    "addr:full":"1041 Plateau Ave Lakeland FL 33815",
    "addr:housenumber":"1041",
    "addr:postcode":"33815",
    "addr:street":"Plateau Ave",
    "iso:country":"US",
    "sg:address":"1041 Plateau Ave",
    "sg:city":"Lakeland",
    "sg:classifiers":[
        {
            "category":"Building & Trades",
            "subcategory":"Construction",
            "type":"Services"
        }
    ],
    "sg:phone":"+1 863 682 9681",
    "sg:postcode":"33815",
    "sg:province":"FL",
    "sg:tags":[
        "house"
    ],
    "wof:name":"Meloney Painting & Remodeling",
    "wof:placetype":"venue"
},
  "geometry": {"coordinates":[-81.988017,28.029642],"type":"Point"}
}