{
  "type": "Feature",
  "properties": {
    "iso:country":"US",
    "sg:address":"230 SE Mizner Blvd",
    "sg:city":"Boca Raton",
    "sg:classifiers":[
        {
            "category":"Professional",
            "type":"Services"
        }
    ],
    "sg:phone":"+1 561 361 1384",
    "sg:postcode":"33432",
    "sg:province":"FL",
    "wof:name":"Camrose Ventures Ltd",
    "wof:placetype":"venue"
},
  "geometry": {"coordinates":[-80.084497,26.346045],"type":"Point"}
}