{
  "type": "Feature",
  "properties": {
    "addr:full":"2332 Riverside Ave Jacksonville FL 32204",
    "addr:housenumber":"2332",
    "addr:postcode":"32204",
    "addr:street":"Riverside Ave",
    "iso:country":"US",
    "sg:address":"2332 Riverside Ave",
    "sg:city":"Jacksonville",
    "sg:classifiers":[
        {
            "category":"Health Services",
            "subcategory":"Doctor",
            "type":"Services"
        }
    ],
    "sg:phone":"+1 904 388 2540",
    "sg:postcode":"32204",
    "sg:province":"FL",
    "sg:tags":[
        "physician",
        "family",
        "practice",
        "surgeons",
        "medicine",
        "surgeon"
    ],
    "wof:name":"Rajesh Patel Md",
    "wof:placetype":"venue"
},
  "geometry": {"coordinates":[-81.686184,30.309965],"type":"Point"}
}