{
  "type": "Feature",
  "properties": {
    "addr:full":"1403 Goldtree Dr Port Saint Lucie FL 34952",
    "addr:housenumber":"1403",
    "addr:postcode":"34952",
    "addr:street":"Goldtree Dr",
    "iso:country":"US",
    "sg:address":"1403 Goldtree Dr",
    "sg:city":"Port Saint Lucie",
    "sg:classifiers":[
        {
            "category":"Health Services",
            "subcategory":"Doctor",
            "type":"Services"
        }
    ],
    "sg:phone":"+1 772 335 3550",
    "sg:postcode":"34952",
    "sg:province":"FL",
    "sg:tags":[
        "medical"
    ],
    "wof:name":"Ted M Schiff",
    "wof:placetype":"venue"
},
  "geometry": {"coordinates":[-80.295648,27.286674],"type":"Point"}
}