{
  "type": "Feature",
  "properties": {
    "addr:full":"13520 S Apopka Vineland Rd Orlando FL 32821",
    "addr:housenumber":"13520",
    "addr:postcode":"32821",
    "addr:street":"S Apopka Vineland Rd",
    "iso:country":"US",
    "sg:address":"13520 S Apopka Vineland Rd",
    "sg:city":"Orlando",
    "sg:classifiers":[
        {
            "category":"Restaurant",
            "type":"Food & Drink"
        }
    ],
    "sg:menulink":"http://www.allmenus.com/fl/southwest-orange/91532-bennigans-grill--tavern/menu/",
    "sg:phone":"+1 407 938 9090",
    "sg:postcode":"32821",
    "sg:province":"FL",
    "sg:tags":[
        "sandwich",
        "salad",
        "burger",
        "pub",
        "soup",
        "american",
        "wrap"
    ],
    "wof:name":"Bennigan's Grill & Tavern",
    "wof:placetype":"venue"
},
  "geometry": {"coordinates":[-81.50348200000001,28.370246],"type":"Point"}
}