{
  "type": "Feature",
  "properties": {
    "iso:country":"US",
    "sg:address":"9624 SW 12th Ct",
    "sg:city":"Boca Raton",
    "sg:classifiers":[
        {
            "category":"Building & Trades",
            "subcategory":"Plumbing",
            "type":"Services"
        }
    ],
    "sg:phone":"+1 561 482 9870",
    "sg:postcode":"33428",
    "sg:province":"FL",
    "sg:tags":[
        "contractor"
    ],
    "wof:name":"K & P Mechanical",
    "wof:placetype":"venue"
},
  "geometry": {"coordinates":[-80.197389,26.337012],"type":"Point"}
}