{
  "type": "Feature",
  "properties": {
    "addr:full":"5850 Charloma Dr Lakeland FL 33812",
    "addr:housenumber":"5850",
    "addr:postcode":"33812",
    "addr:street":"Charloma Dr",
    "iso:country":"US",
    "sg:address":"5850 Charloma Dr",
    "sg:city":"Lakeland",
    "sg:classifiers":[
        {
            "category":"Building & Trades",
            "subcategory":"Construction",
            "type":"Services"
        }
    ],
    "sg:phone":"+1 863 648 5022",
    "sg:postcode":"33812",
    "sg:province":"FL",
    "sg:tags":[
        "contractor"
    ],
    "wof:name":"Haynes Finishing",
    "wof:placetype":"venue"
},
  "geometry": {"coordinates":[-81.908874,27.957474],"type":"Point"}
}