{
  "type": "Feature",
  "properties": {
    "iso:country":"US",
    "sg:address":"4447 Commons Dr E",
    "sg:city":"Destin",
    "sg:classifiers":[
        {
            "category":"Restaurant",
            "type":"Food & Drink"
        }
    ],
    "sg:menulink":"http://www.allmenus.com/fl/fort-walton-beach/122718-quiznos-sub/menu/",
    "sg:phone":"+1 850 837 5222",
    "sg:postcode":"32541",
    "sg:province":"FL",
    "sg:tags":[
        "wrap",
        "american",
        "sandwich"
    ],
    "wof:name":"Quiznos Sub",
    "wof:placetype":"venue"
},
  "geometry": {"coordinates":[-86.432833,30.38873],"type":"Point"}
}