{
  "type": "Feature",
  "properties": {
    "addr:full":"2519 NW 95th St Miami FL 33147",
    "addr:housenumber":"2519",
    "addr:postcode":"33147",
    "addr:street":"Nw 95Th St",
    "iso:country":"US",
    "sg:address":"2519 NW 95th St",
    "sg:city":"Miami",
    "sg:classifiers":[
        {
            "category":"Organizations",
            "subcategory":"Religious Organization",
            "type":"Services"
        }
    ],
    "sg:phone":"+1 305 693 8228",
    "sg:postcode":"33147",
    "sg:province":"FL",
    "wof:name":"Freedom Temple of Miami Inc",
    "wof:placetype":"venue"
},
  "geometry": {"coordinates":[-80.24037800000001,25.860902],"type":"Point"}
}