{
  "type": "Feature",
  "properties": {
    "addr:full":"16600 Media Rd Minneola FL 34711",
    "addr:postcode":"16600;34711",
    "addr:street":"Media Rd",
    "iso:country":"US",
    "sg:address":"16600 Media Rd",
    "sg:city":"Minneola",
    "sg:classifiers":[
        {
            "category":"Health Services",
            "subcategory":"Nursing And Care Facility",
            "type":"Services"
        }
    ],
    "sg:phone":"+1 352 394 3518",
    "sg:postcode":"34711",
    "sg:province":"FL",
    "sg:tags":[
        "home",
        "retirement",
        "community"
    ],
    "wof:name":"Africa Inland Mission Rtrmnt",
    "wof:placetype":"venue"
},
  "geometry": {"coordinates":[-81.76313399999999,28.590801],"type":"Point"}
}