{
  "type": "Feature",
  "properties": {
    "addr:full":"12790 S Dixie Hwy Miami FL 33156",
    "addr:housenumber":"12790",
    "addr:postcode":"33156",
    "addr:street":"S Dixie Hwy",
    "iso:country":"US",
    "sg:address":"12790 S Dixie Hwy",
    "sg:city":"Miami",
    "sg:classifiers":[
        {
            "category":"Banks & Credit Unions",
            "subcategory":"Financial Services",
            "type":"Services"
        }
    ],
    "sg:phone":"+1 305 259 7510",
    "sg:postcode":"33156",
    "sg:province":"FL",
    "sg:tags":[
        "broker",
        "mortgage"
    ],
    "wof:name":"Paramount Mortgage Co",
    "wof:placetype":"venue"
},
  "geometry": {"coordinates":[-80.330299,25.6523],"type":"Point"}
}