{
  "type": "Feature",
  "properties": {
    "iso:country":"US",
    "sg:address":"196 Linda Sue Dr",
    "sg:city":"Lake Helen",
    "sg:classifiers":[
        {
            "category":"Building & Trades",
            "subcategory":"Construction",
            "type":"Services"
        }
    ],
    "sg:phone":"+1 386 228 1005",
    "sg:postcode":"32744",
    "sg:province":"FL",
    "sg:tags":[
        "general",
        "contractor"
    ],
    "wof:name":"J H Construction",
    "wof:placetype":"venue"
},
  "geometry": {"coordinates":[-81.239206,29.00879],"type":"Point"}
}