{
  "type": "Feature",
  "properties": {
    "iso:country":"US",
    "sg:address":"794 Sanders Rd",
    "sg:city":"Daytona Beach",
    "sg:classifiers":[
        {
            "category":"Building & Trades",
            "subcategory":"Construction",
            "type":"Services"
        }
    ],
    "sg:phone":"+1 386 788 7102",
    "sg:postcode":"32127",
    "sg:province":"FL",
    "sg:tags":[
        "plastering",
        "business",
        "coping",
        "contractor",
        "pool",
        "tiling",
        "merchandise",
        "swimming"
    ],
    "wof:name":"Fiberglass Plus",
    "wof:placetype":"venue"
},
  "geometry": {"coordinates":[-80.99181299999999,29.125729],"type":"Point"}
}