{
  "type": "Feature",
  "properties": {
    "addr:full":"1504 41st Ave Vero Beach FL 32960",
    "addr:housenumber":"1504",
    "addr:postcode":"32960",
    "addr:street":"41St Ave",
    "iso:country":"US",
    "sg:address":"1504 41st Ave",
    "sg:city":"Vero Beach",
    "sg:classifiers":[
        {
            "category":"Retail",
            "subcategory":"Repair Shop",
            "type":"Services"
        }
    ],
    "sg:phone":"+1 772 569 2280",
    "sg:postcode":"32960",
    "sg:province":"FL",
    "sg:tags":[
        "refrigerator",
        "freezer"
    ],
    "wof:name":"A 1 Home Refrigeration Svc",
    "wof:placetype":"venue"
},
  "geometry": {"coordinates":[-80.427508,27.630973],"type":"Point"}
}