{
  "type": "Feature",
  "properties": {
    "iso:country":"US",
    "sg:address":"700 W Granada Blvd",
    "sg:city":"Ormond Beach",
    "sg:classifiers":[
        {
            "category":"Professional",
            "subcategory":"Lawyer & Legal Services",
            "type":"Services"
        }
    ],
    "sg:phone":"+1 386 677 9339",
    "sg:postcode":"32174",
    "sg:province":"FL",
    "sg:tags":[
        "attorney"
    ],
    "wof:name":"Florida Venture Title Svc",
    "wof:placetype":"venue"
},
  "geometry": {"coordinates":[-81.079472,29.278922],"type":"Point"}
}