{
  "type": "Feature",
  "properties": {
    "addr:full":"17521 N Tamiami Trl Fort Myers FL 33903",
    "addr:housenumber":"17521",
    "addr:postcode":"fl 33903",
    "addr:street":"N Tamiami Trl",
    "iso:country":"US",
    "sg:address":"17521 N Tamiami Trl",
    "sg:city":"Fort Myers",
    "sg:classifiers":[
        {
            "category":"Retail",
            "subcategory":"Auto Rental",
            "type":"Services"
        }
    ],
    "sg:phone":"+1 239 731 3417",
    "sg:postcode":"33903",
    "sg:province":"FL",
    "sg:tags":[
        "renting",
        "leasing",
        "trailer"
    ],
    "wof:name":"U-Haul Co",
    "wof:placetype":"venue"
},
  "geometry": {"coordinates":[-81.904771,26.719397],"type":"Point"}
}