{
  "type": "Feature",
  "properties": {
    "addr:full":"5707 Emerald Ridge Blvd Lakeland FL 33813",
    "addr:housenumber":"5707",
    "addr:postcode":"33813",
    "addr:street":"Emerald Ridge Blvd",
    "iso:country":"US",
    "sg:address":"5707 Emerald Ridge Blvd",
    "sg:city":"Lakeland",
    "sg:classifiers":[
        {
            "category":"Building & Trades",
            "subcategory":"Construction",
            "type":"Services"
        }
    ],
    "sg:phone":"+1 863 644 1972",
    "sg:postcode":"33813",
    "sg:province":"FL",
    "sg:tags":[
        "house"
    ],
    "wof:name":"Rhoton Construction Group Inc",
    "wof:placetype":"venue"
},
  "geometry": {"coordinates":[-81.927092,27.961755],"type":"Point"}
}