{
  "type": "Feature",
  "properties": {
    "addr:full":"4797 NE 11th Ave Fort Lauderdale FL 33334",
    "addr:housenumber":"4797",
    "addr:postcode":"33334",
    "addr:street":"Ne 11Th Ave",
    "iso:country":"US",
    "sg:address":"4797 NE 11th Ave",
    "sg:city":"Fort Lauderdale",
    "sg:classifiers":[
        {
            "category":"Building & Trades",
            "subcategory":"Electrical",
            "type":"Services"
        }
    ],
    "sg:phone":"+1 954 493 9411",
    "sg:postcode":"33334",
    "sg:province":"FL",
    "sg:tags":[
        "electrical",
        "electric",
        "contractor"
    ],
    "wof:name":"Al Siefert Electric",
    "wof:placetype":"venue"
},
  "geometry": {"coordinates":[-80.13275899999999,26.185301],"type":"Point"}
}