{
  "type": "Feature",
  "properties": {
    "addr:full":"5700 Memorial Hwy Tampa FL 33615",
    "addr:housenumber":"5700",
    "addr:postcode":"33615",
    "addr:street":"Memorial Hwy",
    "iso:country":"US",
    "sg:address":"5700 Memorial Hwy",
    "sg:city":"Tampa",
    "sg:classifiers":[
        {
            "category":"Professional",
            "subcategory":"Lawyer & Legal Services",
            "type":"Services"
        }
    ],
    "sg:phone":"+1 813 290 9999",
    "sg:postcode":"33615",
    "sg:province":"FL",
    "sg:tags":[
        "attorney"
    ],
    "wof:name":"Joel Treauhaft",
    "wof:placetype":"venue"
},
  "geometry": {"coordinates":[-82.56633600000001,27.982211],"type":"Point"}
}