{
  "type": "Feature",
  "properties": {
    "iso:country":"US",
    "sg:address":"1316 Wicklow Ln",
    "sg:city":"Ormond Beach",
    "sg:classifiers":[
        {
            "category":"Professional",
            "subcategory":"Management & Consulting",
            "type":"Services"
        }
    ],
    "sg:phone":"+1 386 672 0470",
    "sg:postcode":"32174",
    "sg:province":"FL",
    "wof:name":"Halifax Capital Management LLC",
    "wof:placetype":"venue"
},
  "geometry": {"coordinates":[-81.14060600000001,29.403022],"type":"Point"}
}