{
  "type": "Feature",
  "properties": {
    "addr:full":"6863 Stirling Rd Davie FL 33314",
    "addr:housenumber":"6863",
    "addr:postcode":"33314",
    "addr:street":"Stirling Rd",
    "iso:country":"US",
    "sg:address":"6863 Stirling Rd",
    "sg:city":"Davie",
    "sg:classifiers":[
        {
            "category":"Shopping",
            "subcategory":"Optical Goods",
            "type":"Retail Goods"
        }
    ],
    "sg:phone":"+1 954 583 6700",
    "sg:postcode":"33314",
    "sg:province":"FL",
    "wof:name":"Sterling Optical",
    "wof:placetype":"venue"
},
  "geometry": {"coordinates":[-80.226403,26.046291],"type":"Point"}
}