{
  "type": "Feature",
  "properties": {
    "iso:country":"US",
    "sg:address":"712 Ponte Vedra Blvd",
    "sg:city":"Ponte Vedra Beach",
    "sg:classifiers":[
        {
            "category":"Shopping",
            "subcategory":"Books",
            "type":"Retail Goods"
        }
    ],
    "sg:phone":"+1 904 285 1114",
    "sg:postcode":"32082",
    "sg:province":"FL",
    "wof:name":"Compleat Books",
    "wof:placetype":"venue"
},
  "geometry": {"coordinates":[-81.36979100000001,30.210076],"type":"Point"}
}