{
  "type": "Feature",
  "properties": {
    "iso:country":"US",
    "sg:address":"13007 Cortez Blvd",
    "sg:city":"Brooksville",
    "sg:classifiers":[
        {
            "category":"Food & Beverages",
            "subcategory":"Specialty",
            "type":"Retail Goods"
        }
    ],
    "sg:phone":"+1 352 592 0717",
    "sg:postcode":"34613",
    "sg:province":"FL",
    "wof:name":"Goto Health Inc",
    "wof:placetype":"venue"
},
  "geometry": {"coordinates":[-82.515371,28.533709],"type":"Point"}
}