{
  "type": "Feature",
  "properties": {
    "addr:full":"9920 SW 74th St Miami FL 33173",
    "addr:housenumber":"9920",
    "addr:postcode":"33173",
    "addr:street":"Sw 74Th St",
    "iso:country":"US",
    "sg:address":"9920 SW 74th St",
    "sg:city":"Miami",
    "sg:classifiers":[
        {
            "category":"Freight",
            "type":"Transportation"
        }
    ],
    "sg:phone":"+1 305 279 5927",
    "sg:postcode":"33173",
    "sg:province":"FL",
    "sg:tags":[
        "operator",
        "local",
        "trucking"
    ],
    "wof:name":"Deco Delivery Inc",
    "wof:placetype":"venue"
},
  "geometry": {"coordinates":[-80.354635,25.699381],"type":"Point"}
}