{
  "type": "Feature",
  "properties": {
    "addr:full":"741 SW 49th Ter Pompano Beach FL 33068",
    "addr:housenumber":"741",
    "addr:postcode":"33068",
    "addr:street":"Sw 49Th Ter",
    "iso:country":"US",
    "sg:address":"741 SW 49th Ter",
    "sg:city":"Pompano Beach",
    "sg:classifiers":[
        {
            "category":"Building & Trades",
            "subcategory":"Landscaping Services",
            "type":"Services"
        }
    ],
    "sg:phone":"+1 954 972 5577",
    "sg:postcode":"33068",
    "sg:province":"FL",
    "sg:tags":[
        "landscape"
    ],
    "wof:name":"Dreamscape Landscaping",
    "wof:placetype":"venue"
},
  "geometry": {"coordinates":[-80.192599,26.221166],"type":"Point"}
}