{
  "type": "Feature",
  "properties": {
    "addr:full":"1404 Seminole Blvd Largo FL 33770",
    "addr:housenumber":"1404",
    "addr:postcode":"33770",
    "addr:street":"Seminole Blvd",
    "iso:country":"US",
    "sg:address":"1404 Seminole Blvd",
    "sg:city":"Largo",
    "sg:classifiers":[
        {
            "category":"Shopping",
            "subcategory":"Gifts & Souvenirs",
            "type":"Retail Goods"
        }
    ],
    "sg:phone":"+1 727 586 5561",
    "sg:postcode":"33770",
    "sg:province":"FL",
    "sg:tags":[
        "item",
        "plant",
        "racing"
    ],
    "wof:name":"Start To Finish",
    "wof:placetype":"venue"
},
  "geometry": {"coordinates":[-82.787212,27.902092],"type":"Point"}
}