{
  "type": "Feature",
  "properties": {
    "addr:full":"700 Armenia Dr Pensacola FL 32505",
    "addr:housenumber":"700",
    "addr:postcode":"32505",
    "addr:street":"Armenia Dr",
    "iso:country":"US",
    "sg:address":"700 Armenia Dr",
    "sg:city":"Pensacola",
    "sg:classifiers":[
        {
            "category":"Professional",
            "subcategory":"Art Services",
            "type":"Services"
        }
    ],
    "sg:phone":"+1 850 434 1489",
    "sg:postcode":"32505",
    "sg:province":"FL",
    "sg:tags":[
        "studio",
        "photographer",
        "commercial",
        "design",
        "photo",
        "portrait"
    ],
    "sg:website":"www.asaphoto.com",
    "wof:name":"Asa Photo Graphics Corp",
    "wof:placetype":"venue"
},
  "geometry": {"coordinates":[-87.248,30.465127],"type":"Point"}
}