{
  "type": "Feature",
  "properties": {
    "addr:full":"201 Toney Penna Dr Jupiter FL 33458",
    "addr:housenumber":"201",
    "addr:postcode":"33458",
    "addr:street":"Toney Penna Dr",
    "iso:country":"US",
    "sg:address":"201 Toney Penna Dr",
    "sg:city":"Jupiter",
    "sg:classifiers":[
        {
            "category":"Building & Trades",
            "subcategory":"Construction",
            "type":"Services"
        }
    ],
    "sg:phone":"+1 561 743 6505",
    "sg:postcode":"33458",
    "sg:province":"FL",
    "sg:tags":[
        "home",
        "improvement"
    ],
    "wof:name":"Home Connection",
    "wof:placetype":"venue"
},
  "geometry": {"coordinates":[-80.09791800000001,26.926282],"type":"Point"}
}