{
  "type": "Feature",
  "properties": {
    "addr:full":"8851 SW 132nd St Miami FL 33176",
    "addr:housenumber":"8851",
    "addr:postcode":"33176",
    "addr:street":"Sw 132Nd St",
    "iso:country":"US",
    "sg:address":"8851 SW 132nd St",
    "sg:city":"Miami",
    "sg:classifiers":[
        {
            "category":"Shopping",
            "type":"Retail Goods"
        }
    ],
    "sg:phone":"+1 786 293 3474",
    "sg:postcode":"33176",
    "sg:province":"FL",
    "sg:tags":[
        "miscellaneous",
        "store"
    ],
    "wof:name":"House Of Fins",
    "wof:placetype":"venue"
},
  "geometry": {"coordinates":[-80.337064,25.647565],"type":"Point"}
}