{
  "type": "Feature",
  "properties": {
    "addr:full":"726 Arthur Godfrey Rd Miami Beach FL 33140",
    "addr:housenumber":"726",
    "addr:postcode":"33140",
    "addr:street":"Arthur Godfrey Rd",
    "iso:country":"US",
    "sg:address":"726 Arthur Godfrey Rd",
    "sg:city":"Miami Beach",
    "sg:classifiers":[
        {
            "category":"Banks & Credit Unions",
            "subcategory":"Bank",
            "type":"Services"
        }
    ],
    "sg:phone":"+1 305 674 8805",
    "sg:postcode":"33140",
    "sg:province":"FL",
    "sg:tags":[
        "loan",
        "real estate"
    ],
    "wof:name":"First Prudential Mtg Svc Inc",
    "wof:placetype":"venue"
},
  "geometry": {"coordinates":[-80.13113,25.813773],"type":"Point"}
}