{
  "type": "Feature",
  "properties": {
    "iso:country":"US",
    "sg:address":"4715 S Congress Ave",
    "sg:city":"Lake Worth",
    "sg:classifiers":[
        {
            "category":"Health Services",
            "subcategory":"Doctor",
            "type":"Services"
        }
    ],
    "sg:phone":"+1 561 798 6600",
    "sg:postcode":"33461",
    "sg:province":"FL",
    "sg:tags":[
        "physician",
        "surgeon"
    ],
    "wof:name":"Harvey Montijo MD",
    "wof:placetype":"venue"
},
  "geometry": {"coordinates":[-80.089602,26.605627],"type":"Point"}
}