{
  "type": "Feature",
  "properties": {
    "addr:full":"1235 Providence Blvd Ste J Deltona FL 32725",
    "addr:housenumber":"1235",
    "addr:postcode":"32725",
    "addr:street":"Providence Blvd Ste J",
    "iso:country":"US",
    "sg:address":"1235 Providence Blvd Ste J",
    "sg:city":"Deltona",
    "sg:classifiers":[
        {
            "category":"Restaurant",
            "type":"Food & Drink"
        }
    ],
    "sg:phone":"+1 386 860 2698",
    "sg:postcode":"32725",
    "sg:province":"FL",
    "sg:tags":[
        "chinese"
    ],
    "wof:name":"China King",
    "wof:placetype":"venue"
},
  "geometry": {"coordinates":[-81.2397,28.899401],"type":"Point"}
}