{
  "type": "Feature",
  "properties": {
    "addr:full":"4415 Metro Pkwy Fort Myers FL 33916",
    "addr:housenumber":"4415",
    "addr:postcode":"33916",
    "addr:street":"Metro Pkwy",
    "iso:country":"US",
    "sg:address":"4415 Metro Pkwy",
    "sg:city":"Fort Myers",
    "sg:classifiers":[
        {
            "category":"Professional",
            "subcategory":"Engineering",
            "type":"Services"
        }
    ],
    "sg:phone":"+1 239 278 7996",
    "sg:postcode":"33916",
    "sg:province":"FL",
    "sg:tags":[
        "engineer"
    ],
    "wof:name":"Boyle Engineering Corporation",
    "wof:placetype":"venue"
},
  "geometry": {"coordinates":[-81.850371,26.601426],"type":"Point"}
}