{
  "type": "Feature",
  "properties": {
    "iso:country":"US",
    "sg:address":"3531 15th Ave SW",
    "sg:city":"Naples",
    "sg:classifiers":[
        {
            "category":"Wholesale",
            "subcategory":"Machinery & Supplies",
            "type":"Manufacturing & Wholesale Goods"
        }
    ],
    "sg:phone":"+1 239 455 9642",
    "sg:postcode":"34117",
    "sg:province":"FL",
    "sg:tags":[
        "cleaning"
    ],
    "wof:name":"Pelican Pressure Cleaning",
    "wof:placetype":"venue"
},
  "geometry": {"coordinates":[-81.677279,26.201645],"type":"Point"}
}