{
  "type": "Feature",
  "properties": {
    "addr:full":"919 W Center St Avon Park FL 33825",
    "addr:housenumber":"919",
    "addr:postcode":"33825",
    "addr:street":"W Center St",
    "iso:country":"US",
    "sg:address":"919 W Center St",
    "sg:city":"Avon Park",
    "sg:classifiers":[
        {
            "category":"Organizations",
            "subcategory":"Religious Organization",
            "type":"Services"
        }
    ],
    "sg:phone":"+1 863 452 5400",
    "sg:postcode":"33825",
    "sg:province":"FL",
    "sg:tags":[
        "church"
    ],
    "wof:name":"Iglesia De Dios Pentecostal",
    "wof:placetype":"venue"
},
  "geometry": {"coordinates":[-81.51071899999999,27.587325],"type":"Point"}
}