{
  "type": "Feature",
  "properties": {
    "iso:country":"US",
    "sg:address":"3551 NE 5th Ave",
    "sg:city":"Oakland Park",
    "sg:classifiers":[
        {
            "category":"Wholesale",
            "subcategory":"Auto Parts",
            "type":"Manufacturing & Wholesale Goods"
        }
    ],
    "sg:phone":"+1 954 714 0404",
    "sg:postcode":"33334",
    "sg:province":"FL",
    "sg:tags":[
        "automobile",
        "rebuilt"
    ],
    "sg:website":"www.raysautoparts.com",
    "wof:name":"Ray's Auto Storage",
    "wof:placetype":"venue"
},
  "geometry": {"coordinates":[-80.140631,26.172],"type":"Point"}
}