{
  "type": "Feature",
  "properties": {
    "iso:country":"US",
    "sg:address":"3442 Swanee Rd",
    "sg:city":"Port Charlotte",
    "sg:classifiers":[
        {
            "category":"Real Estate",
            "subcategory":"Developer",
            "type":"Services"
        }
    ],
    "sg:phone":"+1 941 629 2120",
    "sg:postcode":"33980",
    "sg:province":"FL",
    "wof:name":"Daffron Development Inc",
    "wof:placetype":"venue"
},
  "geometry": {"coordinates":[-82.063953,26.97729],"type":"Point"}
}