{
  "type": "Feature",
  "properties": {
    "iso:country":"US",
    "sg:address":"1820 Royal Fern Ln",
    "sg:city":"Jacksonville Beach",
    "sg:classifiers":[
        {
            "category":"Professional",
            "subcategory":"Business Services",
            "type":"Services"
        }
    ],
    "sg:phone":"+1 904 246 6765",
    "sg:postcode":"32250",
    "sg:province":"FL",
    "wof:name":"Lori Rourk Interiors Inc",
    "wof:placetype":"venue"
},
  "geometry": {"coordinates":[-81.40446799999999,30.264388],"type":"Point"}
}