{
  "type": "Feature",
  "properties": {
    "addr:full":"3501 2nd Ave S St Petersburg FL 33711",
    "addr:housenumber":"3501",
    "addr:postcode":"33711",
    "addr:street":"2Nd Ave S",
    "iso:country":"US",
    "sg:address":"3501 2nd Ave S",
    "sg:city":"St Petersburg",
    "sg:classifiers":[
        {
            "category":"Manufacturing",
            "subcategory":"Printing",
            "type":"Manufacturing & Wholesale Goods"
        }
    ],
    "sg:phone":"+1 727 323 5204",
    "sg:postcode":"33711",
    "sg:province":"FL",
    "sg:tags":[
        "printer"
    ],
    "wof:name":"It's The Word Printing Etc",
    "wof:placetype":"venue"
},
  "geometry": {"coordinates":[-82.68210500000001,27.769161],"type":"Point"}
}