{
  "type": "Feature",
  "properties": {
    "addr:full":"288 S Arnold Rd Panama City Bch FL 32413",
    "addr:housenumber":"288",
    "addr:postcode":"32413",
    "addr:street":"S Arnold Rd",
    "iso:country":"US",
    "sg:address":"288 S Arnold Rd",
    "sg:city":"Panama City Bch",
    "sg:classifiers":[
        {
            "category":"Autos & Motor Vehicles",
            "subcategory":"Motorcycle Sales",
            "type":"Retail Goods"
        }
    ],
    "sg:phone":"+1 850 249 2453",
    "sg:postcode":"32413",
    "sg:province":"FL",
    "sg:tags":[
        "scooter"
    ],
    "wof:name":"American Thunder",
    "wof:placetype":"venue"
},
  "geometry": {"coordinates":[-85.890221,30.224571],"type":"Point"}
}