{
  "type": "Feature",
  "properties": {
    "iso:country":"US",
    "sg:address":"778 S Federal Hwy",
    "sg:city":"Deerfield Beach",
    "sg:classifiers":[
        {
            "category":"Retail",
            "subcategory":"Repair Shop",
            "type":"Services"
        }
    ],
    "sg:phone":"+1 954 427 9161",
    "sg:postcode":"33443",
    "sg:province":"FL",
    "sg:tags":[
        "lock",
        "locksmith"
    ],
    "wof:name":"A & 1 Locksmith",
    "wof:placetype":"venue"
},
  "geometry": {"coordinates":[-80.09250900000001,26.307295],"type":"Point"}
}