{
  "type": "Feature",
  "properties": {
    "iso:country":"US",
    "sg:address":"4010 E Hillsborough Ave",
    "sg:city":"Tampa",
    "sg:classifiers":[
        {
            "category":"Shopping",
            "type":"Retail Goods"
        }
    ],
    "sg:phone":"+1 813 246 9116",
    "sg:postcode":"33610",
    "sg:province":"FL",
    "sg:tags":[
        "miscellaneous",
        "store"
    ],
    "wof:name":"Mobility Trnsp Systems",
    "wof:placetype":"venue"
},
  "geometry": {"coordinates":[-82.41233699999999,27.996177],"type":"Point"}
}