{
  "type": "Feature",
  "properties": {
    "addr:full":"106 S Babcock St Melbourne FL 32901",
    "addr:housenumber":"106",
    "addr:postcode":"32901",
    "addr:street":"S Babcock St",
    "iso:country":"US",
    "sg:address":"106 S Babcock St",
    "sg:city":"Melbourne",
    "sg:classifiers":[
        {
            "category":"Food & Beverages",
            "subcategory":"Specialty",
            "type":"Retail Goods"
        }
    ],
    "sg:phone":"+1 321 723 1803",
    "sg:postcode":"32901",
    "sg:province":"FL",
    "wof:name":"Land Of Spice",
    "wof:placetype":"venue"
},
  "geometry": {"coordinates":[-80.621888,28.105421],"type":"Point"}
}