{
  "type": "Feature",
  "properties": {
    "iso:country":"US",
    "sg:address":"4776 New Broad St",
    "sg:city":"Orlando",
    "sg:classifiers":[
        {
            "category":"Real Estate",
            "subcategory":"Architect",
            "type":"Services"
        }
    ],
    "sg:phone":"+1 407 425 2500",
    "sg:postcode":"32814",
    "sg:province":"FL",
    "sg:tags":[
        "architectural",
        "business"
    ],
    "wof:name":"Voa Associates Incorporated",
    "wof:placetype":"venue"
},
  "geometry": {"coordinates":[-81.328501,28.565889],"type":"Point"}
}