{
  "type": "Feature",
  "properties": {
    "iso:country":"US",
    "sg:address":"12201 SW 92nd Ave",
    "sg:city":"Miami",
    "sg:classifiers":[
        {
            "category":"Shopping",
            "type":"Retail Goods"
        }
    ],
    "sg:phone":"+1 305 598 5357",
    "sg:postcode":"33176",
    "sg:province":"FL",
    "sg:tags":[
        "enforcement",
        "law",
        "supply"
    ],
    "sg:website":"www.nightline-inc.com",
    "wof:name":"Nightline Inc",
    "wof:placetype":"venue"
},
  "geometry": {"coordinates":[-80.342647,25.65826],"type":"Point"}
}