{
  "type": "Feature",
  "properties": {
    "iso:country":"US",
    "sg:address":"1500 University Blvd W",
    "sg:city":"Jacksonville",
    "sg:classifiers":[
        {
            "category":"Restaurant",
            "type":"Food & Drink"
        }
    ],
    "sg:menulink":"http://www.allmenus.com/fl/jacksonville/43265-the-healthy-bagel-company/menu/",
    "sg:phone":"+1 904 737 7896",
    "sg:postcode":"32217",
    "sg:province":"FL",
    "sg:tags":[
        "american"
    ],
    "wof:name":"The Healthy Bagel Company",
    "wof:placetype":"venue"
},
  "geometry": {"coordinates":[-81.645196,30.260752],"type":"Point"}
}