{
  "type": "Feature",
  "properties": {
    "iso:country":"US",
    "sg:address":"3671 8th Ave SE",
    "sg:city":"Naples",
    "sg:classifiers":[
        {
            "category":"Building & Trades",
            "subcategory":"Landscaping Services",
            "type":"Services"
        }
    ],
    "sg:phone":"+1 239 353 3243",
    "sg:postcode":"34117",
    "sg:province":"FL",
    "sg:tags":[
        "landscape",
        "contractor"
    ],
    "wof:name":"Angel Ruiz Landscaping",
    "wof:placetype":"venue"
},
  "geometry": {"coordinates":[-81.536931,26.216058],"type":"Point"}
}