{
  "type": "Feature",
  "properties": {
    "iso:country":"US",
    "sg:address":"2121 Blount Rd",
    "sg:city":"Pompano Beach",
    "sg:classifiers":[
        {
            "category":"Wholesale",
            "subcategory":"Auto Parts",
            "type":"Manufacturing & Wholesale Goods"
        }
    ],
    "sg:phone":"+1 954 782 0604",
    "sg:postcode":"33069",
    "sg:province":"FL",
    "sg:tags":[
        "wholesaler",
        "automotive",
        "supply"
    ],
    "wof:name":"Mile Marker International Inc",
    "wof:placetype":"venue"
},
  "geometry": {"coordinates":[-80.16400899999999,26.255349],"type":"Point"}
}