{
  "type": "Feature",
  "properties": {
    "iso:country":"US",
    "sg:address":"47 New Florida Ave",
    "sg:city":"Beverly Hills",
    "sg:classifiers":[
        {
            "category":"Shopping",
            "type":"Retail Goods"
        }
    ],
    "sg:phone":"+1 352 527 8529",
    "sg:postcode":"34465",
    "sg:province":"FL",
    "sg:tags":[
        "cosmetic",
        "perfume"
    ],
    "wof:name":"Colleen Carters Faceprint",
    "wof:placetype":"venue"
},
  "geometry": {"coordinates":[-82.467625,28.904124],"type":"Point"}
}