{
  "type": "Feature",
  "properties": {
    "addr:full":"5590 NW 113th Pl Miami FL 33178",
    "addr:housenumber":"5590",
    "addr:postcode":"33178",
    "addr:street":"Nw 113Th Pl",
    "iso:country":"US",
    "sg:address":"5590 NW 113th Pl",
    "sg:city":"Miami",
    "sg:classifiers":[
        {
            "category":"Autos & Motor Vehicles",
            "subcategory":"Automobile Sales",
            "type":"Retail Goods"
        }
    ],
    "sg:phone":"+1 305 392 6788",
    "sg:postcode":"33178",
    "sg:province":"FL",
    "sg:tags":[
        "used"
    ],
    "wof:name":"Used & Repair Cell Corp",
    "wof:placetype":"venue"
},
  "geometry": {"coordinates":[-80.38148700000001,25.823846],"type":"Point"}
}