{
  "type": "Feature",
  "properties": {
    "iso:country":"US",
    "sg:address":"1594 NE 24th St",
    "sg:city":"Jensen Beach",
    "sg:classifiers":[
        {
            "category":"Building & Trades",
            "subcategory":"Construction",
            "type":"Services"
        }
    ],
    "sg:phone":"+1 772 334 3781",
    "sg:postcode":"34957",
    "sg:province":"FL",
    "sg:tags":[
        "carpentry",
        "contractor"
    ],
    "wof:name":"Rich Pryzygoda Interior Trim",
    "wof:placetype":"venue"
},
  "geometry": {"coordinates":[-80.22850099999999,27.231451],"type":"Point"}
}