{
  "type": "Feature",
  "properties": {
    "iso:country":"US",
    "sg:address":"151 Graham Ave",
    "sg:city":"Oviedo",
    "sg:classifiers":[
        {
            "category":"Education",
            "subcategory":"School",
            "type":"Public Place"
        }
    ],
    "sg:phone":"+1 407 320 6350",
    "sg:postcode":"32765",
    "sg:province":"FL",
    "wof:name":"Lawton Elementary School",
    "wof:placetype":"venue"
},
  "geometry": {"coordinates":[-81.209405,28.666757],"type":"Point"}
}