{
  "type": "Feature",
  "properties": {
    "iso:country":"US",
    "sg:address":"15395 Gulf Blvd",
    "sg:city":"Madeira Beach",
    "sg:classifiers":[
        {
            "category":"Recreation",
            "type":"Entertainment"
        }
    ],
    "sg:phone":"+1 727 398 7008",
    "sg:postcode":"33708",
    "sg:province":"FL",
    "sg:tags":[
        "course",
        "golf"
    ],
    "wof:name":"Smugglers Cove Adventure Golf",
    "wof:placetype":"venue"
},
  "geometry": {"coordinates":[-82.804002,27.80332],"type":"Point"}
}