{
  "type": "Feature",
  "properties": {
    "iso:country":"US",
    "sg:address":"218 S Atlantic Dr",
    "sg:city":"Lake Worth",
    "sg:classifiers":[
        {
            "category":"Food & Beverages",
            "subcategory":"Meat & Fish",
            "type":"Retail Goods"
        }
    ],
    "sg:phone":"+1 561 582 1939",
    "sg:postcode":"33462",
    "sg:province":"FL",
    "wof:name":"Rockfish Farms",
    "wof:placetype":"venue"
},
  "geometry": {"coordinates":[-80.043814,26.581277],"type":"Point"}
}