{
  "type": "Feature",
  "properties": {
    "iso:country":"US",
    "sg:address":"4112 Mobile Hwy",
    "sg:city":"Pensacola",
    "sg:classifiers":[
        {
            "category":"Home & Garden",
            "subcategory":"Furniture",
            "type":"Retail Goods"
        }
    ],
    "sg:phone":"+1 850 456 2115",
    "sg:postcode":"32506",
    "sg:province":"FL",
    "wof:name":"Plaza Furniture",
    "wof:placetype":"venue"
},
  "geometry": {"coordinates":[-87.26983799999999,30.428233],"type":"Point"}
}