{
  "type": "Feature",
  "properties": {
    "iso:country":"US",
    "sg:address":"12394 SW 82nd Ave",
    "sg:city":"Miami",
    "sg:classifiers":[
        {
            "category":"Professional",
            "subcategory":"Lawyer & Legal Services",
            "type":"Services"
        }
    ],
    "sg:phone":"+1 305 233 9066",
    "sg:postcode":"33156",
    "sg:province":"FL",
    "wof:name":"Vasallo & Vasallo PA",
    "wof:placetype":"venue"
},
  "geometry": {"coordinates":[-80.326453,25.655263],"type":"Point"}
}