{
  "type": "Feature",
  "properties": {
    "addr:full":"3659 Maguire Blvd Orlando FL 32803",
    "addr:housenumber":"3659",
    "addr:postcode":"32803",
    "addr:street":"Maguire Blvd",
    "iso:country":"US",
    "sg:address":"3659 Maguire Blvd",
    "sg:city":"Orlando",
    "sg:classifiers":[
        {
            "category":"Social Services",
            "type":"Services"
        }
    ],
    "sg:phone":"+1 407 896 3873",
    "sg:postcode":"32803",
    "sg:province":"FL",
    "sg:tags":[
        "organization",
        "welfare"
    ],
    "wof:name":"National Multiple Sclerosis",
    "wof:placetype":"venue"
},
  "geometry": {"coordinates":[-81.33379600000001,28.560947],"type":"Point"}
}