{
  "type": "Feature",
  "properties": {
    "addr:full":"3411 W Oakland Park Blvd Lauderdale Lakes FL 33311",
    "addr:housenumber":"3411",
    "addr:postcode":"33311",
    "addr:street":"W Oakland Park Blvd",
    "iso:country":"US",
    "sg:address":"3411 W Oakland Park Blvd",
    "sg:city":"Lauderdale Lakes",
    "sg:classifiers":[
        {
            "category":"Personal",
            "subcategory":"Beauty Salon",
            "type":"Services"
        }
    ],
    "sg:phone":"+1 954 484 4406",
    "sg:postcode":"33311",
    "sg:province":"FL",
    "wof:name":"Up A KUT Unisex Salon",
    "wof:placetype":"venue"
},
  "geometry": {"coordinates":[-80.19292,26.165426],"type":"Point"}
}