{
  "type": "Feature",
  "properties": {
    "iso:country":"US",
    "sg:address":"135 12th St",
    "sg:city":"Daytona Beach",
    "sg:classifiers":[
        {
            "category":"Home & Garden",
            "subcategory":"Furniture",
            "type":"Retail Goods"
        }
    ],
    "sg:phone":"+1 386 255 6436",
    "sg:postcode":"32117",
    "sg:province":"FL",
    "wof:name":"Barrios & Hanley",
    "wof:placetype":"venue"
},
  "geometry": {"coordinates":[-81.038721,29.248985],"type":"Point"}
}