{
  "type": "Feature",
  "properties": {
    "iso:country":"US",
    "sg:address":"12640 NW South River Dr",
    "sg:city":"Medley",
    "sg:classifiers":[
        {
            "category":"Wholesale",
            "subcategory":"Motor Vehicles",
            "type":"Manufacturing & Wholesale Goods"
        }
    ],
    "sg:phone":"+1 305 889 1880",
    "sg:postcode":"33178",
    "sg:province":"FL",
    "sg:tags":[
        "automobile",
        "truck",
        "broker"
    ],
    "wof:name":"K International Auto Brokers",
    "wof:placetype":"venue"
},
  "geometry": {"coordinates":[-80.36919899999999,25.888241],"type":"Point"}
}