{
  "type": "Feature",
  "properties": {
    "iso:country":"US",
    "sg:address":"1321 NE 23rd Ave",
    "sg:city":"Pompano Beach",
    "sg:classifiers":[
        {
            "category":"Food & Beverages",
            "subcategory":"Groceries & Convenience Stores",
            "type":"Retail Goods"
        }
    ],
    "sg:phone":"+1 954 785 1080",
    "sg:postcode":"33062",
    "sg:province":"FL",
    "wof:name":"Circle K",
    "wof:placetype":"venue"
},
  "geometry": {"coordinates":[-80.09960599999999,26.248358],"type":"Point"}
}