{
  "type": "Feature",
  "properties": {
    "iso:country":"US",
    "sg:address":"1836 Capital Cir NE",
    "sg:city":"Tallahassee",
    "sg:classifiers":[
        {
            "category":"Retail",
            "subcategory":"Auto Repair",
            "type":"Services"
        }
    ],
    "sg:phone":"+1 850 942 2886",
    "sg:postcode":"32308",
    "sg:province":"FL",
    "sg:tags":[
        "repairing",
        "automobile"
    ],
    "wof:name":"Bass Tire & Napa Autocare Rpr",
    "wof:placetype":"venue"
},
  "geometry": {"coordinates":[-84.23261100000001,30.472283],"type":"Point"}
}