{
  "type": "Feature",
  "properties": {
    "iso:country":"US",
    "sg:address":"305 Acorn Dr",
    "sg:city":"Titusville",
    "sg:classifiers":[
        {
            "category":"Social Services",
            "subcategory":"Child Care",
            "type":"Services"
        }
    ],
    "sg:phone":"+1 321 383 9568",
    "sg:postcode":"32780",
    "sg:province":"FL",
    "sg:tags":[
        "day"
    ],
    "wof:name":"Jack & Jills Play Schl & Nurs",
    "wof:placetype":"venue"
},
  "geometry": {"coordinates":[-80.80428000000001,28.56009],"type":"Point"}
}