{
  "type": "Feature",
  "properties": {
    "addr:full":"7988 Plummer Rd Jacksonville FL 32219",
    "addr:housenumber":"7988",
    "addr:postcode":"32219",
    "addr:street":"Plummer Rd",
    "iso:country":"US",
    "sg:address":"7988 Plummer Rd",
    "sg:city":"Jacksonville",
    "sg:classifiers":[
        {
            "category":"Arts & Performance",
            "subcategory":"Theater",
            "type":"Entertainment"
        }
    ],
    "sg:phone":"+1 904 766 3677",
    "sg:postcode":"32219",
    "sg:province":"FL",
    "sg:tags":[
        "bureau"
    ],
    "wof:name":"Peak Productions",
    "wof:placetype":"venue"
},
  "geometry": {"coordinates":[-81.775578,30.437502],"type":"Point"}
}