{
  "type": "Feature",
  "properties": {
    "iso:country":"US",
    "sg:address":"6475 Minton Rd SE",
    "sg:city":"Palm Bay",
    "sg:classifiers":[
        {
            "category":"Education",
            "subcategory":"Library",
            "type":"Public Place"
        }
    ],
    "sg:phone":"+1 321 952 6317",
    "sg:postcode":"32908",
    "sg:province":"FL",
    "wof:name":"Brevard County Library Systems",
    "wof:placetype":"venue"
},
  "geometry": {"coordinates":[-80.671953,27.993764],"type":"Point"}
}