{
  "type": "Feature",
  "properties": {
    "iso:country":"US",
    "sg:address":"5650 66th St N",
    "sg:city":"Saint Petersburg",
    "sg:classifiers":[
        {
            "category":"Building & Trades",
            "subcategory":"Construction",
            "type":"Services"
        }
    ],
    "sg:phone":"+1 727 541 4486",
    "sg:postcode":"33709",
    "sg:province":"FL",
    "sg:tags":[
        "contractor"
    ],
    "wof:name":"Film King",
    "wof:placetype":"venue"
},
  "geometry": {"coordinates":[-82.72856299999999,27.823999],"type":"Point"}
}