{
  "type": "Feature",
  "properties": {
    "addr:full":"4021 S Peninsula Dr Daytona Beach FL 32127",
    "addr:housenumber":"4021",
    "addr:postcode":"32127",
    "addr:street":"S Peninsula Dr",
    "iso:country":"US",
    "sg:address":"4021 S Peninsula Dr",
    "sg:city":"Daytona Beach",
    "sg:classifiers":[
        {
            "category":"Building & Trades",
            "subcategory":"Landscaping Services",
            "type":"Services"
        }
    ],
    "sg:phone":"+1 386 760 0552",
    "sg:postcode":"32127",
    "sg:province":"FL",
    "wof:name":"Terra Firma",
    "wof:placetype":"venue"
},
  "geometry": {"coordinates":[-80.960572,29.132184],"type":"Point"}
}