{
  "type": "Feature",
  "properties": {
    "iso:country":"US",
    "sg:address":"1843 S Federal Hwy",
    "sg:city":"Fort Lauderdale",
    "sg:classifiers":[
        {
            "category":"Restaurant",
            "type":"Food & Drink"
        }
    ],
    "sg:phone":"+1 954 523 8636",
    "sg:postcode":"33316",
    "sg:province":"FL",
    "sg:tags":[
        "drinking",
        "eating"
    ],
    "wof:name":"Ernies Booze and Bar-B-Que",
    "wof:placetype":"venue"
},
  "geometry": {"coordinates":[-80.136695,26.097723],"type":"Point"}
}