{
  "type": "Feature",
  "properties": {
    "addr:full":"4827 N Lois Ave Tampa FL 33614",
    "addr:housenumber":"4827",
    "addr:postcode":"33614",
    "addr:street":"N Lois Ave",
    "iso:country":"US",
    "sg:address":"4827 N Lois Ave",
    "sg:city":"Tampa",
    "sg:classifiers":[
        {
            "category":"Wholesale",
            "subcategory":"Medical Equipment & Supplies",
            "type":"Manufacturing & Wholesale Goods"
        }
    ],
    "sg:phone":"+1 813 877 7581",
    "sg:postcode":"33614",
    "sg:province":"FL",
    "sg:tags":[
        "optical"
    ],
    "wof:name":"Frame Fashions Inc",
    "wof:placetype":"venue"
},
  "geometry": {"coordinates":[-82.513447,27.990806],"type":"Point"}
}