{
  "type": "Feature",
  "properties": {
    "addr:full":"19595-D NE 10th Ave Miami FL 33179",
    "addr:housenumber":"19595-d",
    "addr:postcode":"33179",
    "addr:street":"Ne 10Th Ave",
    "iso:country":"US",
    "sg:address":"19595-D NE 10th Ave",
    "sg:city":"Miami",
    "sg:classifiers":[
        {
            "category":"Professional",
            "subcategory":"Art Services",
            "type":"Services"
        },
        {
            "category":"Building & Trades",
            "subcategory":"Construction",
            "type":"Services"
        },
        {
            "category":"Home & Garden",
            "subcategory":"Furniture",
            "type":"Retail Goods"
        }
    ],
    "sg:phone":"+1 305 999 9921",
    "sg:postcode":"33179",
    "sg:province":"FL",
    "sg:tags":[
        "interior",
        "designer",
        "design",
        "decorator",
        "store"
    ],
    "wof:name":"Helene Weissner Designs, Inc.",
    "wof:placetype":"venue"
},
  "geometry": {"coordinates":[-80.182034,25.95552],"type":"Point"}
}