{
  "type": "Feature",
  "properties": {
    "iso:country":"US",
    "sg:address":"1007 Catalpa Ln",
    "sg:city":"Orlando",
    "sg:classifiers":[
        {
            "category":"Real Estate",
            "subcategory":"Architect",
            "type":"Services"
        }
    ],
    "sg:phone":"+1 407 894 5213",
    "sg:postcode":"32806",
    "sg:province":"FL",
    "sg:tags":[
        "architectural"
    ],
    "wof:name":"Thomas Horas Designer",
    "wof:placetype":"venue"
},
  "geometry": {"coordinates":[-81.337749,28.527738],"type":"Point"}
}