{
  "type": "Feature",
  "properties": {
    "iso:country":"US",
    "sg:address":"2021 Park St",
    "sg:city":"Jacksonville",
    "sg:classifiers":[
        {
            "category":"Real Estate",
            "subcategory":"Real Estate Services",
            "type":"Services"
        },
        {
            "category":"Real Estate",
            "subcategory":"Real Estate Agent",
            "type":"Services"
        }
    ],
    "sg:phone":"+1 904 683 5230",
    "sg:postcode":"32204",
    "sg:province":"FL",
    "sg:tags":[
        "buyer",
        "management",
        "broker"
    ],
    "wof:name":"Traditions Realty",
    "wof:placetype":"venue"
},
  "geometry": {"coordinates":[-81.681712,30.313752],"type":"Point"}
}