{
  "type": "Feature",
  "properties": {
    "iso:country":"US",
    "sg:address":"2219 S Woodland Blvd",
    "sg:city":"Deland",
    "sg:classifiers":[
        {
            "category":"Education",
            "subcategory":"Preschool",
            "type":"Public Place"
        },
        {
            "category":"Education",
            "subcategory":"School",
            "type":"Public Place"
        }
    ],
    "sg:phone":"+1 386 736 9849",
    "sg:postcode":"32720",
    "sg:province":"FL",
    "sg:tags":[
        "elementary"
    ],
    "wof:name":"Easter Seals Child Development Ctr",
    "wof:placetype":"venue"
},
  "geometry": {"coordinates":[-81.30090300000001,28.9897],"type":"Point"}
}