{
  "type": "Feature",
  "properties": {
    "iso:country":"US",
    "sg:address":"9791 NW 30th St",
    "sg:city":"Doral",
    "sg:classifiers":[
        {
            "category":"Food & Beverages",
            "subcategory":"Groceries & Convenience Stores",
            "type":"Retail Goods"
        }
    ],
    "sg:phone":"+1 305 592 4560",
    "sg:postcode":"33172",
    "sg:province":"FL",
    "sg:tags":[
        "market"
    ],
    "wof:name":"I-Markets Inc",
    "wof:placetype":"venue"
},
  "geometry": {"coordinates":[-80.35546600000001,25.80253],"type":"Point"}
}