{
  "type": "Feature",
  "properties": {
    "addr:full":"13057 SW 215th Ter Miami FL 33177",
    "addr:housenumber":"13057",
    "addr:postcode":"33177",
    "addr:street":"Sw 215Th Ter",
    "iso:country":"US",
    "sg:address":"13057 SW 215th Ter",
    "sg:city":"Miami",
    "sg:classifiers":[
        {
            "category":"Professional",
            "subcategory":"Detective & Security Services",
            "type":"Services"
        }
    ],
    "sg:phone":"+1 305 388 8441",
    "sg:postcode":"33177",
    "sg:province":"FL",
    "sg:tags":[
        "consultant",
        "system",
        "equipment"
    ],
    "wof:name":"Global Security And Fire, Inc.",
    "wof:placetype":"venue"
},
  "geometry": {"coordinates":[-80.403218,25.566604],"type":"Point"}
}