{
  "type": "Feature",
  "properties": {
    "iso:country":"US",
    "sg:address":"103 Ambersweet Way",
    "sg:city":"Davenport",
    "sg:classifiers":[
        {
            "category":"Restaurant",
            "type":"Food & Drink"
        }
    ],
    "sg:phone":"+1 863 424 6199",
    "sg:postcode":"33897",
    "sg:province":"FL",
    "wof:name":"Spice Of Life",
    "wof:placetype":"venue"
},
  "geometry": {"coordinates":[-81.669167,28.311942],"type":"Point"}
}