{
  "type": "Feature",
  "properties": {
    "iso:country":"US",
    "sg:address":"6091 W 14th Ct",
    "sg:city":"Hialeah",
    "sg:classifiers":[
        {
            "category":"Building & Trades",
            "subcategory":"Plumbing",
            "type":"Services"
        }
    ],
    "sg:phone":"+1 305 456 3025",
    "sg:postcode":"33012",
    "sg:province":"FL",
    "sg:tags":[
        "contractor"
    ],
    "wof:name":"Mj Air Conditioning Pipefiters",
    "wof:placetype":"venue"
},
  "geometry": {"coordinates":[-80.31209699999999,25.878527],"type":"Point"}
}