{
  "type": "Feature",
  "properties": {
    "iso:country":"US",
    "sg:address":"650 S Barracks St",
    "sg:city":"Pensacola",
    "sg:classifiers":[
        {
            "category":"Wholesale",
            "subcategory":"Construction Materials",
            "type":"Manufacturing & Wholesale Goods"
        }
    ],
    "sg:phone":"+1 850 455 1321",
    "sg:postcode":"32502",
    "sg:province":"FL",
    "sg:tags":[
        "sand",
        "gravel",
        "lime"
    ],
    "wof:name":"Martin Marietta Aggregates",
    "wof:placetype":"venue"
},
  "geometry": {"coordinates":[-87.210836,30.407579],"type":"Point"}
}