{
  "type": "Feature",
  "properties": {
    "addr:full":"897 Orange Hill Rd Chipley FL 32428",
    "addr:housenumber":"897",
    "addr:postcode":"32428",
    "addr:street":"Orange Hill Rd",
    "iso:country":"US",
    "sg:address":"897 Orange Hill Rd",
    "sg:city":"Chipley",
    "sg:classifiers":[
        {
            "category":"Freight",
            "type":"Transportation"
        }
    ],
    "sg:phone":"+1 850 638 0089",
    "sg:postcode":"32428",
    "sg:province":"FL",
    "sg:tags":[
        "general"
    ],
    "wof:name":"Dorsey Storage & Woodwork",
    "wof:placetype":"venue"
},
  "geometry": {"coordinates":[-85.525536,30.765009],"type":"Point"}
}