{
  "type": "Feature",
  "properties": {
    "addr:full":"701 Pennsylvania Ave Wauchula FL 33873",
    "addr:housenumber":"701",
    "addr:postcode":"33873",
    "addr:street":"Pennsylvania Ave",
    "iso:country":"US",
    "sg:address":"701 Pennsylvania Ave",
    "sg:city":"Wauchula",
    "sg:classifiers":[
        {
            "category":"Organizations",
            "subcategory":"Religious Organization",
            "type":"Services"
        }
    ],
    "sg:phone":"+1 863 773 3753",
    "sg:postcode":"33873",
    "sg:province":"FL",
    "sg:tags":[
        "church"
    ],
    "wof:name":"Gospel Tabernacle",
    "wof:placetype":"venue"
},
  "geometry": {"coordinates":[-81.81961,27.554088],"type":"Point"}
}