{
  "type": "Feature",
  "properties": {
    "iso:country":"US",
    "sg:address":"607 W University Ave ",
    "sg:city":"Gainesville",
    "sg:classifiers":[
        {
            "category":"Restaurant",
            "type":"Food & Drink"
        }
    ],
    "sg:menulink":"http://www.allmenus.com/fl/gainesville/282819-lucas-pasta/menu/",
    "sg:phone":"+1 352 338 1700",
    "sg:postcode":"32601",
    "sg:province":"FL",
    "sg:tags":[
        "italian"
    ],
    "wof:name":"Lucas Pasta",
    "wof:placetype":"venue"
},
  "geometry": {"coordinates":[-82.33087399999999,29.652044],"type":"Point"}
}