{
  "type": "Feature",
  "properties": {
    "iso:country":"US",
    "sg:address":"3215 15th St E",
    "sg:city":"Bradenton",
    "sg:classifiers":[
        {
            "category":"Building & Trades",
            "subcategory":"Construction",
            "type":"Services"
        }
    ],
    "sg:phone":"+1 941 746 9362",
    "sg:postcode":"34208",
    "sg:province":"FL",
    "sg:tags":[
        "roofing",
        "contractor"
    ],
    "wof:name":"White Peterman Roofing Inc",
    "wof:placetype":"venue"
},
  "geometry": {"coordinates":[-82.546566,27.470626],"type":"Point"}
}