{
  "type": "Feature",
  "properties": {
    "addr:full":"3462 NE 12th Ter Fort Lauderdale FL 33334",
    "addr:housenumber":"3462",
    "addr:postcode":"33334",
    "addr:street":"Ne 12Th Ter",
    "iso:country":"US",
    "sg:address":"3462 NE 12th Ter",
    "sg:city":"Fort Lauderdale",
    "sg:classifiers":[
        {
            "category":"Building & Trades",
            "subcategory":"Construction",
            "type":"Services"
        }
    ],
    "sg:phone":"+1 954 566 5761",
    "sg:postcode":"33334",
    "sg:province":"FL",
    "sg:tags":[
        "hanging",
        "contractor"
    ],
    "wof:name":"Painting & Pressure Cleaning B",
    "wof:placetype":"venue"
},
  "geometry": {"coordinates":[-80.130346,26.171338],"type":"Point"}
}