{
  "type": "Feature",
  "properties": {
    "iso:country":"US",
    "sg:address":"2303 Phoenix Ave",
    "sg:city":"Jacksonville",
    "sg:classifiers":[
        {
            "category":"Retail",
            "subcategory":"Repair Shop",
            "type":"Services"
        }
    ],
    "sg:phone":"+1 904 632 1818",
    "sg:postcode":"32206",
    "sg:province":"FL",
    "sg:tags":[
        "welding"
    ],
    "wof:name":"Ironman Fabrication & Welding",
    "wof:placetype":"venue"
},
  "geometry": {"coordinates":[-81.641034,30.352188],"type":"Point"}
}