{
  "type": "Feature",
  "properties": {
    "addr:full":"5730 Tamarack Dr Orlando FL 32819",
    "addr:housenumber":"5730",
    "addr:postcode":"32819",
    "addr:street":"Tamarack Dr",
    "iso:country":"US",
    "sg:address":"5730 Tamarack Dr",
    "sg:city":"Orlando",
    "sg:classifiers":[
        {
            "category":"Organizations",
            "subcategory":"Professional Association",
            "type":"Services"
        }
    ],
    "sg:phone":"+1 407 354 0104",
    "sg:postcode":"32819",
    "sg:province":"FL",
    "sg:tags":[
        "business",
        "trade"
    ],
    "wof:name":"Commerce Quest Inc.",
    "wof:placetype":"venue"
},
  "geometry": {"coordinates":[-81.488921,28.482404],"type":"Point"}
}