{
  "type": "Feature",
  "properties": {
    "iso:country":"US",
    "sg:address":"3000 NW 48th St",
    "sg:city":"Coconut Creek",
    "sg:classifiers":[
        {
            "category":"Utilities",
            "subcategory":"Refuse",
            "type":"Services"
        }
    ],
    "sg:phone":"+1 954 968 6173",
    "sg:postcode":"33073",
    "sg:province":"FL",
    "sg:tags":[
        "garbage",
        "collection"
    ],
    "wof:name":"Central Sanitary Landfill",
    "wof:placetype":"venue"
},
  "geometry": {"coordinates":[-80.166149,26.28856],"type":"Point"}
}