{
  "type": "Feature",
  "properties": {
    "iso:country":"US",
    "sg:address":"1144 W State Road 436",
    "sg:city":"Altamonte Springs",
    "sg:classifiers":[
        {
            "category":"Personal",
            "subcategory":"Tattoo Parlor",
            "type":"Services"
        }
    ],
    "sg:phone":"+1 407 260 2266",
    "sg:postcode":"32714",
    "sg:province":"FL",
    "sg:website":"www.besttattoosinc.com",
    "wof:name":"Best Tattoos",
    "wof:placetype":"venue"
},
  "geometry": {"coordinates":[-81.42980900000001,28.666395],"type":"Point"}
}