{
  "type": "Feature",
  "properties": {
    "addr:full":"7513 W Sand Lake Rd Orlando FL 32819",
    "addr:housenumber":"7513",
    "addr:postcode":"32819",
    "addr:street":"W Sand Lake Rd",
    "iso:country":"US",
    "sg:address":"7513 W Sand Lake Rd",
    "sg:city":"Orlando",
    "sg:classifiers":[
        {
            "category":"Banks & Credit Unions",
            "subcategory":"Investment Brokerage",
            "type":"Services"
        }
    ],
    "sg:phone":"+1 407 352 8808",
    "sg:postcode":"32819",
    "sg:province":"FL",
    "sg:tags":[
        "advisory",
        "financial"
    ],
    "wof:name":"Phillip Roy Financial Svc",
    "wof:placetype":"venue"
},
  "geometry": {"coordinates":[-81.478149,28.450072],"type":"Point"}
}