{
  "type": "Feature",
  "properties": {
    "iso:country":"US",
    "sg:address":"42 N 7th St",
    "sg:city":"Haines City",
    "sg:classifiers":[
        {
            "category":"Banks & Credit Unions",
            "subcategory":"Bank",
            "type":"Services"
        }
    ],
    "sg:phone":"+1 863 421 0678",
    "sg:postcode":"33844",
    "sg:province":"FL",
    "sg:tags":[
        "loan",
        "real estate"
    ],
    "wof:name":"Tropical Mortgage Businesses",
    "wof:placetype":"venue"
},
  "geometry": {"coordinates":[-81.62585,28.107302],"type":"Point"}
}