{
  "type": "Feature",
  "properties": {
    "addr:full":"14089 SW 144th Avenue Rd Miami FL 33186",
    "addr:housenumber":"14089",
    "addr:postcode":"33186",
    "addr:street":"Sw 144Th Avenue Rd",
    "iso:country":"US",
    "sg:address":"14089 SW 144th Avenue Rd",
    "sg:city":"Miami",
    "sg:classifiers":[
        {
            "category":"Manufacturing",
            "subcategory":"Building Materials",
            "type":"Manufacturing & Wholesale Goods"
        }
    ],
    "sg:phone":"+1 305 251 3220",
    "sg:postcode":"33186",
    "sg:province":"FL",
    "sg:tags":[
        "communication",
        "tower"
    ],
    "sg:website":"http://www.ccu.com",
    "wof:name":"C C U Inc",
    "wof:placetype":"venue"
},
  "geometry": {"coordinates":[-80.42897000000001,25.636024],"type":"Point"}
}