{
  "type": "Feature",
  "properties": {
    "addr:full":"3600 University Blvd W Jacksonville FL 32217",
    "addr:housenumber":"3600",
    "addr:postcode":"32217",
    "addr:street":"University Blvd W",
    "iso:country":"US",
    "sg:address":"3600 University Blvd W",
    "sg:city":"Jacksonville",
    "sg:classifiers":[
        {
            "category":"Shopping",
            "subcategory":"Beauty & Cosmetics",
            "type":"Retail Goods"
        },
        {
            "category":"Retail",
            "subcategory":"Photofinishing",
            "type":"Services"
        },
        {
            "category":"Shopping",
            "subcategory":"Gifts & Souvenirs",
            "type":"Retail Goods"
        },
        {
            "category":"Retail",
            "subcategory":"Storage",
            "type":"Services"
        },
        {
            "category":"Shopping",
            "subcategory":"Pharmacy",
            "type":"Retail Goods"
        }
    ],
    "sg:phone":"+1 904 733 7600",
    "sg:postcode":"32217",
    "sg:province":"FL",
    "sg:tags":[
        "supply",
        "photo",
        "sundries",
        "perfume",
        "card",
        "aid",
        "finishing",
        "first",
        "store",
        "greeting"
    ],
    "wof:name":"Cvs Pharmacy",
    "wof:placetype":"venue"
},
  "geometry": {"coordinates":[-81.625522,30.261551],"type":"Point"}
}