{
  "type": "Feature",
  "properties": {
    "iso:country":"US",
    "sg:address":"8192 College Pkwy",
    "sg:city":"Fort Myers",
    "sg:classifiers":[
        {
            "category":"Insurance",
            "subcategory":"Insurance Agent",
            "type":"Services"
        }
    ],
    "sg:phone":"+1 239 481 2030",
    "sg:postcode":"33919",
    "sg:province":"FL",
    "wof:name":"All Care Insurance",
    "wof:placetype":"venue"
},
  "geometry": {"coordinates":[-81.893856,26.556877],"type":"Point"}
}