{
  "type": "Feature",
  "properties": {
    "iso:country":"US",
    "sg:address":"4515 SW 29th Ave",
    "sg:city":"Gainesville",
    "sg:classifiers":[
        {
            "category":"Retail",
            "subcategory":"Auto Rental",
            "type":"Services"
        },
        {
            "category":"Building & Trades",
            "subcategory":"Equipment Rental",
            "type":"Services"
        },
        {
            "category":"Retail",
            "subcategory":"Storage",
            "type":"Services"
        }
    ],
    "sg:phone":"+1 352 332 4647",
    "sg:postcode":"32608",
    "sg:province":"FL",
    "sg:tags":[
        "renting",
        "moving-self",
        "leasing",
        "truck",
        "van",
        "moving",
        "trailer"
    ],
    "sg:website":"http://www.ryder.com/",
    "wof:name":"Ryder",
    "wof:placetype":"venue"
},
  "geometry": {"coordinates":[-82.392228,29.627368],"type":"Point"}
}