{
  "type": "Feature",
  "properties": {
    "addr:full":"1223 12th Ln Palm Beach Gdns FL 33418",
    "addr:housenumber":"1223",
    "addr:postcode":"33418",
    "addr:street":"12Th Ln",
    "iso:country":"US",
    "sg:address":"1223 12th Ln",
    "sg:city":"Palm Beach Gdns",
    "sg:classifiers":[
        {
            "category":"Professional",
            "subcategory":"Business Services",
            "type":"Services"
        }
    ],
    "sg:phone":"+1 561 776 9200",
    "sg:postcode":"33418",
    "sg:province":"FL",
    "sg:tags":[
        "fund",
        "promotion",
        "raising"
    ],
    "wof:name":"World Stage Promotions LLC",
    "wof:placetype":"venue"
},
  "geometry": {"coordinates":[-80.110467,26.84513],"type":"Point"}
}