{
  "type": "Feature",
  "properties": {
    "iso:country":"US",
    "sg:address":"4160 NW 21st St",
    "sg:city":"Fort Lauderdale",
    "sg:classifiers":[
        {
            "category":"Shopping",
            "subcategory":"Clothing, Apparel, & Fashions",
            "type":"Retail Goods"
        }
    ],
    "sg:phone":"+1 954 295 6712",
    "sg:postcode":"33313",
    "sg:province":"FL",
    "wof:name":"C & L Designer T Shirts",
    "wof:placetype":"venue"
},
  "geometry": {"coordinates":[-80.205275,26.153688],"type":"Point"}
}