{
  "type": "Feature",
  "properties": {
    "iso:country":"US",
    "sg:address":"800 NE 8th St",
    "sg:city":"Fort Lauderdale",
    "sg:classifiers":[
        {
            "category":"Cinema",
            "subcategory":"Movie Theater",
            "type":"Entertainment"
        }
    ],
    "sg:phone":"+1 954 828 5381",
    "sg:postcode":"33304",
    "sg:province":"FL",
    "wof:name":"War Memorial Auditorium",
    "wof:placetype":"venue"
},
  "geometry": {"coordinates":[-80.13615299999999,26.133588],"type":"Point"}
}