{
  "type": "Feature",
  "properties": {
    "iso:country":"US",
    "sg:address":"10260 W Sample Rd",
    "sg:city":"Coral Springs",
    "sg:classifiers":[
        {
            "category":"Shopping",
            "subcategory":"Gifts & Souvenirs",
            "type":"Retail Goods"
        }
    ],
    "sg:phone":"+1 954 255 5353",
    "sg:postcode":"33065",
    "sg:province":"FL",
    "sg:tags":[
        "shop"
    ],
    "wof:name":"Cottage Rose Accents",
    "wof:placetype":"venue"
},
  "geometry": {"coordinates":[-80.26267,26.272537],"type":"Point"}
}