{
  "type": "Feature",
  "properties": {
    "iso:country":"US",
    "sg:address":"950 SW 87th Ave",
    "sg:city":"Miami",
    "sg:classifiers":[
        {
            "category":"Building & Trades",
            "subcategory":"Locksmith",
            "type":"Services"
        }
    ],
    "sg:phone":"+1 305 423 0992",
    "sg:postcode":"33174",
    "sg:province":"FL",
    "sg:tags":[
        "key"
    ],
    "wof:name":"0 Waiting Time Locksmith Service",
    "wof:placetype":"venue"
},
  "geometry": {"coordinates":[-80.336319,25.760442],"type":"Point"}
}