{
  "type": "Feature",
  "properties": {
    "iso:country":"US",
    "sg:address":"1228 Deleon Way",
    "sg:city":"Lakeland",
    "sg:classifiers":[
        {
            "category":"Retail",
            "subcategory":"Auto Repair",
            "type":"Services"
        }
    ],
    "sg:phone":"+1 863 698 3389",
    "sg:postcode":"33805",
    "sg:province":"FL",
    "sg:tags":[
        "automotive"
    ],
    "wof:name":"Road Rangers",
    "wof:placetype":"venue"
},
  "geometry": {"coordinates":[-81.949679,28.05976],"type":"Point"}
}