{
  "type": "Feature",
  "properties": {
    "addr:full":"3911 Oakwood Blvd Hollywood FL 33020",
    "addr:housenumber":"3911",
    "addr:postcode":"33020",
    "addr:street":"Oakwood Blvd",
    "iso:country":"US",
    "sg:address":"3911 Oakwood Blvd",
    "sg:city":"Hollywood",
    "sg:classifiers":[
        {
            "category":"Shopping",
            "subcategory":"Hobbies, Toys, & Games",
            "type":"Retail Goods"
        }
    ],
    "sg:phone":"+1 954 922 2646",
    "sg:postcode":"33020",
    "sg:province":"FL",
    "sg:tags":[
        "craft",
        "supply"
    ],
    "wof:name":"Rag Shop",
    "wof:placetype":"venue"
},
  "geometry": {"coordinates":[-80.15992199999999,26.047126],"type":"Point"}
}