{
  "type": "Feature",
  "properties": {
    "iso:country":"US",
    "sg:address":"659 Murphy Rd",
    "sg:city":"Winter Springs",
    "sg:classifiers":[
        {
            "category":"Building & Trades",
            "subcategory":"Landscaping Services",
            "type":"Services"
        }
    ],
    "sg:phone":"+1 407 696 8620",
    "sg:postcode":"32708",
    "sg:province":"FL",
    "wof:name":"Swanson Lawn Care & Press",
    "wof:placetype":"venue"
},
  "geometry": {"coordinates":[-81.309755,28.681638],"type":"Point"}
}