{
  "type": "Feature",
  "properties": {
    "addr:full":"13680 NW 19th Ave Opa Locka FL 33054",
    "addr:housenumber":"13680",
    "addr:postcode":"33054",
    "addr:street":"Nw 19Th Ave;Locka",
    "iso:country":"US",
    "sg:address":"13680 NW 19th Ave",
    "sg:city":"Opa Locka",
    "sg:classifiers":[
        {
            "category":"Retail",
            "subcategory":"Auto Repair",
            "type":"Services"
        }
    ],
    "sg:phone":"+1 786 413 0922",
    "sg:postcode":"33054",
    "sg:province":"FL",
    "sg:tags":[
        "repairing",
        "automobile"
    ],
    "wof:name":"Arrocha Auto Repair",
    "wof:placetype":"venue"
},
  "geometry": {"coordinates":[-80.23161899999999,25.900401],"type":"Point"}
}