{
  "type": "Feature",
  "properties": {
    "addr:full":"5183 NW 15th St Margate FL 33063",
    "addr:housenumber":"5183",
    "addr:postcode":"33063",
    "addr:street":"Nw 15Th St Margate",
    "iso:country":"US",
    "sg:address":"5183 NW 15th St",
    "sg:city":"Margate",
    "sg:classifiers":[
        {
            "category":"Retail",
            "subcategory":"Auto Repair",
            "type":"Services"
        }
    ],
    "sg:phone":"+1 954 969 9977",
    "sg:postcode":"33063",
    "sg:province":"FL",
    "sg:tags":[
        "repairing",
        "automobile"
    ],
    "wof:name":"Ruff Racing",
    "wof:placetype":"venue"
},
  "geometry": {"coordinates":[-80.19349800000001,26.248675],"type":"Point"}
}