{
  "type": "Feature",
  "properties": {
    "iso:country":"US",
    "sg:address":"33050 Professional Dr",
    "sg:city":"Leesburg",
    "sg:classifiers":[
        {
            "category":"Health Services",
            "subcategory":"Doctor",
            "type":"Services"
        }
    ],
    "sg:phone":"+1 352 787 6800",
    "sg:postcode":"34788",
    "sg:province":"FL",
    "sg:tags":[
        "dentist"
    ],
    "wof:name":"Dave Wollenschlaeger Orthdntcs",
    "wof:placetype":"venue"
},
  "geometry": {"coordinates":[-81.82363700000001,28.832821],"type":"Point"}
}