{
  "type": "Feature",
  "properties": {
    "iso:country":"US",
    "sg:address":"17970 NE 31st Ct",
    "sg:city":"Aventura",
    "sg:classifiers":[
        {
            "category":"Shopping",
            "subcategory":"Shoes",
            "type":"Retail Goods"
        }
    ],
    "sg:phone":"+1 305 944 6347",
    "sg:postcode":"33160",
    "sg:province":"FL",
    "sg:tags":[
        "store"
    ],
    "wof:name":"S A Cavalini",
    "wof:placetype":"venue"
},
  "geometry": {"coordinates":[-80.13809999999999,25.944099],"type":"Point"}
}