{
  "type": "Feature",
  "properties": {
    "iso:country":"US",
    "sg:address":"998 Douglas Ave",
    "sg:city":"Dunedin",
    "sg:classifiers":[
        {
            "category":"Autos & Motor Vehicles",
            "subcategory":"Auto Supplies",
            "type":"Retail Goods"
        }
    ],
    "sg:phone":"+1 727 734 3914",
    "sg:postcode":"34698",
    "sg:province":"FL",
    "sg:tags":[
        "automobile",
        "part",
        "accessory"
    ],
    "wof:name":"Bay Shore Auto Parts",
    "wof:placetype":"venue"
},
  "geometry": {"coordinates":[-82.787941,28.015779],"type":"Point"}
}