{
  "type": "Feature",
  "properties": {
    "addr:full":"1284 Creekside St Naples FL 34108",
    "addr:housenumber":"1284",
    "addr:postcode":"34108",
    "addr:street":"Creekside St",
    "iso:country":"US",
    "sg:address":"1284 Creekside St",
    "sg:city":"Naples",
    "sg:classifiers":[
        {
            "category":"Health Services",
            "subcategory":"Doctor",
            "type":"Services"
        }
    ],
    "sg:phone":"+1 239 254 8884",
    "sg:postcode":"34108",
    "sg:province":"FL",
    "sg:tags":[
        "physician",
        "family",
        "gynecology",
        "practice",
        "surgeons",
        "obstetrics",
        "medicine"
    ],
    "sg:website":"http://www.mfmswfl.com",
    "wof:name":"Maternal Fetal Medicine of SW Florida",
    "wof:placetype":"venue"
},
  "geometry": {"coordinates":[-81.791293,26.270994],"type":"Point"}
}