{
  "type": "Feature",
  "properties": {
    "addr:full":"4707 14th Ave N St Petersburg FL 33713",
    "addr:housenumber":"4707",
    "addr:postcode":"33713",
    "addr:street":"14Th Ave N",
    "iso:country":"US",
    "sg:address":"4707 14th Ave N",
    "sg:city":"St Petersburg",
    "sg:classifiers":[
        {
            "category":"Real Estate",
            "subcategory":"Real Estate Agent",
            "type":"Services"
        }
    ],
    "sg:phone":"+1 727 898 7227",
    "sg:postcode":"33713",
    "sg:province":"FL",
    "wof:name":"KLH Perferred Properties Inc",
    "wof:placetype":"venue"
},
  "geometry": {"coordinates":[-82.698498,27.785528],"type":"Point"}
}