{
  "type": "Feature",
  "properties": {
    "addr:full":"125 Main St Destin FL 32541",
    "addr:housenumber":"125",
    "addr:postcode":"32541",
    "addr:street":"Main St",
    "iso:country":"US",
    "sg:address":"125 Main St",
    "sg:city":"Destin",
    "sg:classifiers":[
        {
            "category":"Building & Trades",
            "subcategory":"Construction",
            "type":"Services"
        }
    ],
    "sg:phone":"+1 850 269 1705",
    "sg:postcode":"32541",
    "sg:province":"FL",
    "sg:tags":[
        "general",
        "contractor"
    ],
    "wof:name":"Opus Construction & Dev Inc",
    "wof:placetype":"venue"
},
  "geometry": {"coordinates":[-86.483503,30.391298],"type":"Point"}
}