{
  "type": "Feature",
  "properties": {
    "iso:country":"US",
    "sg:address":"5699 34th St N",
    "sg:city":"St Petersburg",
    "sg:classifiers":[
        {
            "category":"Manufacturing",
            "subcategory":"Printing",
            "type":"Manufacturing & Wholesale Goods"
        }
    ],
    "sg:phone":"+1 727 527 5871",
    "sg:postcode":"33714",
    "sg:province":"FL",
    "sg:tags":[
        "printer"
    ],
    "wof:name":"Sterling Printers",
    "wof:placetype":"venue"
},
  "geometry": {"coordinates":[-82.679542,27.822896],"type":"Point"}
}