{
  "type": "Feature",
  "properties": {
    "addr:full":"11570 State Hwy 84 Davie FL 33325",
    "addr:housenumber":"11570",
    "addr:postcode":"33325",
    "addr:street":"State Hwy 84",
    "iso:country":"US",
    "sg:address":"11570 State Hwy 84",
    "sg:city":"Davie",
    "sg:classifiers":[
        {
            "category":"Health Services",
            "subcategory":"Clinic",
            "type":"Services"
        }
    ],
    "sg:phone":"+1 954 727 9100",
    "sg:postcode":"33325",
    "sg:province":"FL",
    "sg:tags":[
        "dialysis"
    ],
    "wof:name":"Universal Kidney Ctr-Davie",
    "wof:placetype":"venue"
},
  "geometry": {"coordinates":[-80.30354699999999,26.112438],"type":"Point"}
}