{
  "type": "Feature",
  "properties": {
    "addr:full":"1819 Main St Sarasota FL 34236",
    "addr:housenumber":"1819",
    "addr:postcode":"34236",
    "addr:street":"Main St",
    "iso:country":"US",
    "sg:address":"1819 Main St",
    "sg:city":"Sarasota",
    "sg:classifiers":[
        {
            "category":"Professional",
            "subcategory":"Detective & Security Services",
            "type":"Services"
        }
    ],
    "sg:phone":"+1 941 957 1444",
    "sg:postcode":"34236",
    "sg:province":"FL",
    "sg:tags":[
        "employee",
        "company",
        "leasing"
    ],
    "wof:name":"Wackenhut Corporation",
    "wof:placetype":"venue"
},
  "geometry": {"coordinates":[-82.53324000000001,27.336538],"type":"Point"}
}