{
  "type": "Feature",
  "properties": {
    "iso:country":"US",
    "sg:address":"5373 Ehrlich Rd",
    "sg:city":"Tampa",
    "sg:classifiers":[
        {
            "category":"Utilities",
            "subcategory":"Telephone",
            "type":"Services"
        }
    ],
    "sg:phone":"+1 813 962 4604",
    "sg:postcode":"33625",
    "sg:province":"FL",
    "wof:name":"JMR Telecom",
    "wof:placetype":"venue"
},
  "geometry": {"coordinates":[-82.54266699999999,28.082908],"type":"Point"}
}