{
  "type": "Feature",
  "properties": {
    "addr:full":"2080 N Monroe St Tallahassee FL 32303",
    "addr:housenumber":"2080",
    "addr:postcode":"32303",
    "addr:street":"N Monroe St",
    "iso:country":"US",
    "sg:address":"2080 N Monroe St",
    "sg:city":"Tallahassee",
    "sg:classifiers":[
        {
            "category":"Retail",
            "subcategory":"Auto Repair",
            "type":"Services"
        }
    ],
    "sg:phone":"+1 850 386 1912",
    "sg:postcode":"32303",
    "sg:province":"FL",
    "sg:tags":[
        "general"
    ],
    "wof:name":"Precision Tune Auto Care",
    "wof:placetype":"venue"
},
  "geometry": {"coordinates":[-84.28743,30.46925],"type":"Point"}
}