{
  "type": "Feature",
  "properties": {
    "addr:full":"6645 Vineland Rd Orlando FL 32819",
    "addr:housenumber":"6645",
    "addr:postcode":"32819",
    "addr:street":"Vineland Rd",
    "iso:country":"US",
    "sg:address":"6645 Vineland Rd",
    "sg:city":"Orlando",
    "sg:classifiers":[
        {
            "category":"Real Estate",
            "subcategory":"Real Estate Services",
            "type":"Services"
        }
    ],
    "sg:phone":"+1 407 903 0334",
    "sg:postcode":"32819",
    "sg:province":"FL",
    "sg:tags":[
        "company",
        "title"
    ],
    "wof:name":"Preferred Alliance Title LTD",
    "wof:placetype":"venue"
},
  "geometry": {"coordinates":[-81.474428,28.480637],"type":"Point"}
}