{
  "type": "Feature",
  "properties": {
    "iso:country":"US",
    "sg:address":"9460 NW 12th St",
    "sg:city":"Doral",
    "sg:classifiers":[
        {
            "category":"Shopping",
            "subcategory":"Florist",
            "type":"Retail Goods"
        }
    ],
    "sg:phone":"+1 305 629 2720",
    "sg:postcode":"33172",
    "sg:province":"FL",
    "wof:name":"Jazmine Flower Corp",
    "wof:placetype":"venue"
},
  "geometry": {"coordinates":[-80.35007,25.78335],"type":"Point"}
}