{
  "type": "Feature",
  "properties": {
    "iso:country":"US",
    "sg:address":"4700 SW Country Pl",
    "sg:city":"Palm City",
    "sg:classifiers":[
        {
            "category":"Professional",
            "type":"Services"
        }
    ],
    "sg:phone":"+1 772 223 8658",
    "sg:postcode":"34990",
    "sg:province":"FL",
    "wof:name":"Colean Services Inc",
    "wof:placetype":"venue"
},
  "geometry": {"coordinates":[-80.311852,27.118806],"type":"Point"}
}