{
  "type": "Feature",
  "properties": {
    "addr:full":"5518 Dunn Ave Jacksonville FL 32218",
    "addr:housenumber":"5518",
    "addr:postcode":"32218",
    "addr:street":"Dunn Ave",
    "iso:country":"US",
    "sg:address":"5518 Dunn Ave",
    "sg:city":"Jacksonville",
    "sg:classifiers":[
        {
            "category":"Organizations",
            "subcategory":"Religious Organization",
            "type":"Services"
        }
    ],
    "sg:phone":"+1 904 768 0970",
    "sg:postcode":"32218",
    "sg:province":"FL",
    "sg:tags":[
        "church"
    ],
    "wof:name":"Cornerstone Pentecostal Church",
    "wof:placetype":"venue"
},
  "geometry": {"coordinates":[-81.734843,30.438036],"type":"Point"}
}