{
  "type": "Feature",
  "properties": {
    "iso:country":"US",
    "sg:address":"1879 SW 31st Ave",
    "sg:city":"Hallandale",
    "sg:classifiers":[
        {
            "category":"Shopping",
            "subcategory":"Party Supplies",
            "type":"Retail Goods"
        }
    ],
    "sg:phone":"+1 954 966 6955",
    "sg:postcode":"33009",
    "sg:province":"FL",
    "sg:tags":[
        "rental"
    ],
    "wof:name":"Event Rentals",
    "wof:placetype":"venue"
},
  "geometry": {"coordinates":[-80.168723,25.994653],"type":"Point"}
}