{
  "type": "Feature",
  "properties": {
    "iso:country":"US",
    "sg:address":"221 Wetherby St",
    "sg:city":"Venice",
    "sg:classifiers":[
        {
            "category":"Health Services",
            "subcategory":"Podiatrist",
            "type":"Services"
        }
    ],
    "sg:phone":"+1 941 497 7051",
    "sg:postcode":"34293",
    "sg:province":"FL",
    "sg:tags":[
        "physician",
        "surgeons"
    ],
    "wof:name":"Jonathan Chabra",
    "wof:placetype":"venue"
},
  "geometry": {"coordinates":[-82.362938,27.050393],"type":"Point"}
}