{
  "type": "Feature",
  "properties": {
    "iso:country":"US",
    "sg:address":"3802 E Colonial Dr",
    "sg:city":"Orlando",
    "sg:classifiers":[
        {
            "category":"Personal",
            "subcategory":"Beauty Salon",
            "type":"Services"
        }
    ],
    "sg:phone":"+1 407 895 0440",
    "sg:postcode":"32803",
    "sg:province":"FL",
    "sg:tags":[
        "manicuring"
    ],
    "wof:name":"M Z Nails",
    "wof:placetype":"venue"
},
  "geometry": {"coordinates":[-81.336603,28.553372],"type":"Point"}
}