{
  "type": "Feature",
  "properties": {
    "addr:full":"936 14th St W Bradenton FL 34205",
    "addr:housenumber":"936",
    "addr:postcode":"34205",
    "addr:street":"14Th St W",
    "iso:country":"US",
    "sg:address":"936 14th St W",
    "sg:city":"Bradenton",
    "sg:classifiers":[
        {
            "category":"Organizations",
            "subcategory":"Non-profit Organization",
            "type":"Services"
        }
    ],
    "sg:phone":"+1 941 747 5757",
    "sg:postcode":"34205",
    "sg:province":"FL",
    "wof:name":"Manatee County Girl's Club Inc",
    "wof:placetype":"venue"
},
  "geometry": {"coordinates":[-82.575337,27.490987],"type":"Point"}
}