{
  "type": "Feature",
  "properties": {
    "iso:country":"US",
    "sg:address":"2812 N Orange Blossom Trl",
    "sg:city":"Orlando",
    "sg:classifiers":[
        {
            "category":"Retail",
            "subcategory":"Auto Repair",
            "type":"Services"
        }
    ],
    "sg:phone":"+1 407 421 6136",
    "sg:postcode":"32804",
    "sg:province":"FL",
    "sg:tags":[
        "general"
    ],
    "wof:name":"Sens Paintless Dent Repair",
    "wof:placetype":"venue"
},
  "geometry": {"coordinates":[-81.40711400000001,28.576846],"type":"Point"}
}