{
  "type": "Feature",
  "properties": {
    "addr:full":"4421 SW 75th Ave Miami FL 33155",
    "addr:housenumber":"4421",
    "addr:postcode":"33155",
    "addr:street":"Sw 75Th Ave",
    "iso:country":"US",
    "sg:address":"4421 SW 75th Ave",
    "sg:city":"Miami",
    "sg:classifiers":[
        {
            "category":"Manufacturing",
            "subcategory":"Building Materials",
            "type":"Manufacturing & Wholesale Goods"
        }
    ],
    "sg:phone":"+1 305 262 4224",
    "sg:postcode":"33155",
    "sg:province":"FL",
    "sg:tags":[
        "merchandise",
        "mfg"
    ],
    "wof:name":"Galaxy Awnings & Sign Corp",
    "wof:placetype":"venue"
},
  "geometry": {"coordinates":[-80.316767,25.726675],"type":"Point"}
}