{
  "type": "Feature",
  "properties": {
    "iso:country":"US",
    "sg:address":"10215 Cutten Green Ct",
    "sg:city":"Tampa",
    "sg:classifiers":[
        {
            "category":"Taxi",
            "type":"Transportation"
        }
    ],
    "sg:phone":"+1 813 886 5309",
    "sg:postcode":"33615",
    "sg:province":"FL",
    "wof:name":"Van Amburg Penny",
    "wof:placetype":"venue"
},
  "geometry": {"coordinates":[-82.59846,28.019979],"type":"Point"}
}