{
  "type": "Feature",
  "properties": {
    "addr:full":"5005 State Hwy 60 Bartow FL 33830",
    "addr:housenumber":"5005",
    "addr:postcode":"33830",
    "addr:street":"State Hwy 60",
    "iso:country":"US",
    "sg:address":"5005 State Hwy 60",
    "sg:city":"Bartow",
    "sg:classifiers":[
        {
            "category":"Home & Garden",
            "subcategory":"Mobile Homes",
            "type":"Retail Goods"
        }
    ],
    "sg:phone":"+1 863 533 4200",
    "sg:postcode":"33830",
    "sg:province":"FL",
    "sg:tags":[
        "manufactured"
    ],
    "wof:name":"Blue Marlin Homes Inc",
    "wof:placetype":"venue"
},
  "geometry": {"coordinates":[-81.774041,27.909425],"type":"Point"}
}