{
  "type": "Feature",
  "properties": {
    "iso:country":"US",
    "sg:address":"5417 Sun Valley Dr",
    "sg:city":"Pensacola",
    "sg:classifiers":[
        {
            "category":"Retail",
            "subcategory":"Auto Repair",
            "type":"Services"
        }
    ],
    "sg:phone":"+1 850 432 2250",
    "sg:postcode":"32505",
    "sg:province":"FL",
    "wof:name":"Robert Tau Automotive Inc",
    "wof:placetype":"venue"
},
  "geometry": {"coordinates":[-87.262024,30.46417],"type":"Point"}
}