{
  "type": "Feature",
  "properties": {
    "iso:country":"US",
    "sg:address":"3410 Chatsworth Ln",
    "sg:city":"Orlando",
    "sg:classifiers":[
        {
            "category":"Retail",
            "subcategory":"Auto Repair",
            "type":"Services"
        }
    ],
    "sg:phone":"+1 407 447 5045",
    "sg:postcode":"32812",
    "sg:province":"FL",
    "sg:tags":[
        "repairing",
        "automobile"
    ],
    "wof:name":"Island Automotive",
    "wof:placetype":"venue"
},
  "geometry": {"coordinates":[-81.31955499999999,28.508345],"type":"Point"}
}