{
  "type": "Feature",
  "properties": {
    "iso:country":"US",
    "sg:address":"2071 Emerson St",
    "sg:city":"Jacksonville",
    "sg:classifiers":[
        {
            "category":"Building & Trades",
            "subcategory":"Pest Control",
            "type":"Services"
        }
    ],
    "sg:phone":"+1 904 739 8090",
    "sg:postcode":"32207",
    "sg:province":"FL",
    "wof:name":"Greener Image",
    "wof:placetype":"venue"
},
  "geometry": {"coordinates":[-81.639842,30.284926],"type":"Point"}
}