{
  "type": "Feature",
  "properties": {
    "iso:country":"US",
    "sg:address":"475 Biltmore Way",
    "sg:city":"Coral Gables",
    "sg:classifiers":[
        {
            "category":"Health Services",
            "subcategory":"Doctor",
            "type":"Services"
        }
    ],
    "sg:phone":"+1 305 444 9177",
    "sg:postcode":"33134",
    "sg:province":"FL",
    "sg:tags":[
        "physician",
        "surgeon"
    ],
    "wof:name":"Asthma & Allergy Assoc Of Fl",
    "wof:placetype":"venue"
},
  "geometry": {"coordinates":[-80.264382,25.748392],"type":"Point"}
}