{
  "type": "Feature",
  "properties": {
    "iso:country":"US",
    "sg:address":"9556 Apalachee Pkwy",
    "sg:city":"Tallahassee",
    "sg:classifiers":[
        {
            "category":"Travel",
            "subcategory":"Hotels & Motels",
            "type":"Entertainment"
        }
    ],
    "sg:phone":"+1 850 656 6663",
    "sg:postcode":"32311",
    "sg:province":"FL",
    "wof:name":"Capital Inn Motel",
    "wof:placetype":"venue"
},
  "geometry": {"coordinates":[-84.11523099999999,30.42287],"type":"Point"}
}