{
  "type": "Feature",
  "properties": {
    "addr:full":"1020 Alton Rd Miami Beach FL 33139",
    "addr:housenumber":"1020",
    "addr:postcode":"33139",
    "addr:street":"Alton Rd",
    "iso:country":"US",
    "sg:address":"1020 Alton Rd",
    "sg:city":"Miami Beach",
    "sg:classifiers":[
        {
            "category":"Insurance",
            "subcategory":"Health Insurance",
            "type":"Services"
        },
        {
            "category":"Food & Beverages",
            "subcategory":"Groceries & Convenience Stores",
            "type":"Retail Goods"
        }
    ],
    "sg:phone":"+1 305 532 1707",
    "sg:postcode":"33139",
    "sg:province":"FL",
    "sg:tags":[
        "market"
    ],
    "sg:website":"wholefoodsmarket.com/stores/sout...",
    "wof:name":"Whole Foods Market",
    "wof:placetype":"venue"
},
  "geometry": {"coordinates":[-80.140942,25.781115],"type":"Point"}
}