{
  "type": "Feature",
  "properties": {
    "iso:country":"US",
    "sg:address":"12595 66th St N",
    "sg:city":"Largo",
    "sg:classifiers":[
        {
            "category":"Building & Trades",
            "subcategory":"Plumbing",
            "type":"Services"
        }
    ],
    "sg:phone":"+1 727 530 5059",
    "sg:postcode":"33773",
    "sg:province":"FL",
    "sg:tags":[
        "conditioning",
        "air",
        "system",
        "contractor"
    ],
    "wof:name":"Industrial Building Svc",
    "wof:placetype":"venue"
},
  "geometry": {"coordinates":[-82.729046,27.886221],"type":"Point"}
}