{
  "type": "Feature",
  "properties": {
    "iso:country":"US",
    "sg:address":"4907 S 50th St",
    "sg:city":"Tampa",
    "sg:classifiers":[
        {
            "category":"Professional",
            "type":"Services"
        }
    ],
    "sg:phone":"+1 813 671 0231",
    "sg:postcode":"33619",
    "sg:province":"FL",
    "wof:name":"Sunstate Wrecker Svc",
    "wof:placetype":"venue"
},
  "geometry": {"coordinates":[-82.401799,27.901031],"type":"Point"}
}