{
  "type": "Feature",
  "properties": {
    "iso:country":"US",
    "sg:address":"1812 State Hwy 77",
    "sg:city":"Lynn Haven",
    "sg:classifiers":[
        {
            "category":"Wholesale",
            "subcategory":"Machinery & Supplies",
            "type":"Manufacturing & Wholesale Goods"
        }
    ],
    "sg:phone":"+1 850 271 0384",
    "sg:postcode":"32444",
    "sg:province":"FL",
    "sg:tags":[
        "salon",
        "beauty"
    ],
    "wof:name":"Sally Beauty Supply",
    "wof:placetype":"venue"
},
  "geometry": {"coordinates":[-85.64913199999999,30.231915],"type":"Point"}
}