{
  "type": "Feature",
  "properties": {
    "addr:full":"1038 Rosefaire Pl Odessa FL 33556",
    "addr:housenumber":"1038",
    "addr:postcode":"33556",
    "addr:street":"Rosefaire Pl",
    "iso:country":"US",
    "sg:address":"1038 Rosefaire Pl",
    "sg:city":"Odessa",
    "sg:classifiers":[
        {
            "category":"Real Estate",
            "subcategory":"Real Estate Services",
            "type":"Services"
        },
        {
            "category":"Real Estate",
            "subcategory":"Real Estate Agent",
            "type":"Services"
        }
    ],
    "sg:phone":"+1 727 389 2090",
    "sg:postcode":"33556",
    "sg:province":"FL",
    "sg:tags":[
        "buyer",
        "broker"
    ],
    "wof:name":"Florida Luxury Realty Inc",
    "wof:placetype":"venue"
},
  "geometry": {"coordinates":[-82.53727000000001,28.173329],"type":"Point"}
}