{
  "type": "Feature",
  "properties": {
    "iso:country":"US",
    "sg:address":"4995 NW 79th Ave",
    "sg:city":"Doral",
    "sg:classifiers":[
        {
            "category":"Wholesale",
            "subcategory":"Durable Goods & Equipment",
            "type":"Manufacturing & Wholesale Goods"
        }
    ],
    "sg:phone":"+1 305 471 0084",
    "sg:postcode":"33166",
    "sg:province":"FL",
    "sg:tags":[
        "exporter"
    ],
    "wof:name":"Getoze Import Export Inc",
    "wof:placetype":"venue"
},
  "geometry": {"coordinates":[-80.325507,25.818872],"type":"Point"}
}