{
  "type": "Feature",
  "properties": {
    "iso:country":"US",
    "sg:address":"1826 Trade Center Way",
    "sg:city":"Naples",
    "sg:classifiers":[
        {
            "category":"Restaurant",
            "type":"Food & Drink"
        }
    ],
    "sg:phone":"+1 239 597 5099",
    "sg:postcode":"34109",
    "sg:province":"FL",
    "wof:name":"Bohio Cuban Cafe",
    "wof:placetype":"venue"
},
  "geometry": {"coordinates":[-81.77238800000001,26.225206],"type":"Point"}
}