{
  "type": "Feature",
  "properties": {
    "addr:full":"605 S Grandview St Mount Dora FL 32757",
    "addr:housenumber":"605",
    "addr:postcode":"32757",
    "addr:street":"S Grandview St",
    "iso:country":"US",
    "sg:address":"605 S Grandview St",
    "sg:city":"Mount Dora",
    "sg:classifiers":[
        {
            "category":"Building & Trades",
            "subcategory":"Landscaping Services",
            "type":"Services"
        }
    ],
    "sg:phone":"+1 352 383 3636",
    "sg:postcode":"32757",
    "sg:province":"FL",
    "wof:name":"John Fortson Lawn Service",
    "wof:placetype":"venue"
},
  "geometry": {"coordinates":[-81.640337,28.791363],"type":"Point"}
}