{
  "type": "Feature",
  "properties": {
    "addr:full":"3049 Drane Field Rd Lakeland FL 33811",
    "addr:housenumber":"3049",
    "addr:postcode":"33811",
    "addr:street":"Drane Field Rd",
    "iso:country":"US",
    "sg:address":"3049 Drane Field Rd",
    "sg:city":"Lakeland",
    "sg:classifiers":[
        {
            "category":"Manufacturing",
            "subcategory":"Electronics",
            "type":"Manufacturing & Wholesale Goods"
        }
    ],
    "sg:phone":"+1 863 646 5583",
    "sg:postcode":"33811",
    "sg:province":"FL",
    "sg:tags":[
        "burglar",
        "alarm",
        "monitoring",
        "system"
    ],
    "wof:name":"Micro Guard Security Systems",
    "wof:placetype":"venue"
},
  "geometry": {"coordinates":[-82.00471400000001,27.996713],"type":"Point"}
}