{
  "type": "Feature",
  "properties": {
    "addr:full":"330 W Bearss Ave Tampa FL 33613",
    "addr:housenumber":"330",
    "addr:postcode":"33613",
    "addr:street":"W Bearss Ave",
    "iso:country":"US",
    "sg:address":"330 W Bearss Ave",
    "sg:city":"Tampa",
    "sg:classifiers":[
        {
            "category":"Banks & Credit Unions",
            "subcategory":"Investment Brokerage",
            "type":"Services"
        },
        {
            "category":"Professional",
            "subcategory":"Management & Consulting",
            "type":"Services"
        }
    ],
    "sg:phone":"+1 813 961 5926",
    "sg:postcode":"33613",
    "sg:province":"FL",
    "sg:tags":[
        "consultant",
        "planning",
        "financial",
        "planner"
    ],
    "wof:name":"Florida Financial Advisors Inc",
    "wof:placetype":"venue"
},
  "geometry": {"coordinates":[-82.459975,28.087971],"type":"Point"}
}