{
  "type": "Feature",
  "properties": {
    "addr:full":"424 E Derby Ave Auburndale FL 33823",
    "addr:housenumber":"424",
    "addr:postcode":"33823",
    "addr:street":"E Derby Ave",
    "iso:country":"US",
    "sg:address":"424 E Derby Ave",
    "sg:city":"Auburndale",
    "sg:classifiers":[
        {
            "category":"Personal",
            "subcategory":"Beauty Salon",
            "type":"Services"
        },
        {
            "category":"Personal",
            "subcategory":"Nail Salon",
            "type":"Services"
        }
    ],
    "sg:phone":"+1 863 967 1800",
    "sg:postcode":"33823",
    "sg:province":"FL",
    "sg:tags":[
        "hair",
        "stylist"
    ],
    "wof:name":"Snippers Hair & Nail Salon",
    "wof:placetype":"venue"
},
  "geometry": {"coordinates":[-81.77775200000001,28.055066],"type":"Point"}
}