{
  "type": "Feature",
  "properties": {
    "iso:country":"US",
    "sg:address":"895 SW 86th Ct",
    "sg:city":"Miami",
    "sg:classifiers":[
        {
            "category":"Professional",
            "subcategory":"Lawyer & Legal Services",
            "type":"Services"
        }
    ],
    "sg:phone":"+1 305 598 8847",
    "sg:postcode":"33144",
    "sg:province":"FL",
    "wof:name":"Elite Land Title In C PA Atty",
    "wof:placetype":"venue"
},
  "geometry": {"coordinates":[-80.334929,25.761203],"type":"Point"}
}