{
  "type": "Feature",
  "properties": {
    "addr:full":"7221 Chancery Ln Orlando FL 32809",
    "addr:housenumber":"7221",
    "addr:postcode":"32809",
    "addr:street":"Chancery Ln",
    "iso:country":"US",
    "sg:address":"7221 Chancery Ln",
    "sg:city":"Orlando",
    "sg:phone":"+1 407 855 0474",
    "sg:postcode":"32809",
    "sg:province":"FL",
    "wof:name":"South Orlando Dental",
    "wof:placetype":"venue"
},
  "geometry": {"coordinates":[-81.39618900000001,28.460693],"type":"Point"}
}