{
  "type": "Feature",
  "properties": {
    "addr:full":"3909 E Semoran Blvd Apopka FL 32703",
    "addr:housenumber":"3909 e",
    "addr:postcode":"32703",
    "addr:street":"Semoran Blvd",
    "iso:country":"US",
    "sg:address":"3909 E Semoran Blvd",
    "sg:city":"Apopka",
    "sg:classifiers":[
        {
            "category":"Shopping",
            "subcategory":"Books",
            "type":"Retail Goods"
        }
    ],
    "sg:phone":"+1 407 869 9006",
    "sg:postcode":"32703",
    "sg:province":"FL",
    "sg:tags":[
        "food"
    ],
    "wof:name":"Florida Adventist Book Store",
    "wof:placetype":"venue"
},
  "geometry": {"coordinates":[-81.446183,28.669558],"type":"Point"}
}