{
  "type": "Feature",
  "properties": {
    "iso:country":"US",
    "sg:address":"5314 Pimlico Dr",
    "sg:city":"Tallahassee",
    "sg:classifiers":[
        {
            "category":"Professional",
            "subcategory":"Management & Consulting",
            "type":"Services"
        }
    ],
    "sg:phone":"+1 850 668 2034",
    "sg:postcode":"32309",
    "sg:province":"FL",
    "sg:tags":[
        "consultant"
    ],
    "wof:name":"Southern Consulting Group",
    "wof:placetype":"venue"
},
  "geometry": {"coordinates":[-84.188717,30.537998],"type":"Point"}
}