{
  "type": "Feature",
  "properties": {
    "addr:full":"174 S Collier Blvd Marco Island FL 34145",
    "addr:housenumber":"174;collier blvd",
    "addr:postcode":"34145",
    "addr:street":"S",
    "iso:country":"US",
    "sg:address":"174 S Collier Blvd",
    "sg:city":"Marco Island",
    "sg:classifiers":[
        {
            "category":"Banks & Credit Unions",
            "subcategory":"Financial Services",
            "type":"Services"
        }
    ],
    "sg:phone":"+1 239 394 1367",
    "sg:postcode":"34145",
    "sg:province":"FL",
    "sg:tags":[
        "investor"
    ],
    "wof:name":"R & R Investment & Trdg Group",
    "wof:placetype":"venue"
},
  "geometry": {"coordinates":[-81.730521,25.934014],"type":"Point"}
}