{
  "type": "Feature",
  "properties": {
    "addr:full":"521 Midland Ave Apopka FL 32703",
    "addr:housenumber":"521",
    "addr:postcode":"32703",
    "addr:street":"Midland Ave",
    "iso:country":"US",
    "sg:address":"521 Midland Ave",
    "sg:city":"Apopka",
    "sg:classifiers":[
        {
            "category":"Building & Trades",
            "subcategory":"Construction",
            "type":"Services"
        }
    ],
    "sg:phone":"+1 407 814 9404",
    "sg:postcode":"32703",
    "sg:province":"FL",
    "sg:tags":[
        "hanging",
        "contractor"
    ],
    "wof:name":"Brown Painting Greg",
    "wof:placetype":"venue"
},
  "geometry": {"coordinates":[-81.50421299999999,28.672839],"type":"Point"}
}