{
  "type": "Feature",
  "properties": {
    "iso:country":"US",
    "sg:address":"5009 N Travelers Palm Ln",
    "sg:city":"Tamarac",
    "sg:classifiers":[
        {
            "category":"Food & Beverages",
            "subcategory":"Farmers Market",
            "type":"Retail Goods"
        }
    ],
    "sg:phone":"+1 954 214 1692",
    "sg:postcode":"33319",
    "sg:province":"FL",
    "sg:tags":[
        "vegetable",
        "fruit"
    ],
    "wof:name":"G.P. Produce Corp.",
    "wof:placetype":"venue"
},
  "geometry": {"coordinates":[-80.22408,26.187745],"type":"Point"}
}