{
  "type": "Feature",
  "properties": {
    "iso:country":"US",
    "sg:address":"504 Bayard St",
    "sg:city":"Sanford",
    "sg:classifiers":[
        {
            "category":"Arts & Performance",
            "subcategory":"Art Gallery",
            "type":"Entertainment"
        },
        {
            "category":"Professional",
            "subcategory":"Art Services",
            "type":"Services"
        },
        {
            "category":"Shopping",
            "subcategory":"Crafts & Fabrics",
            "type":"Retail Goods"
        }
    ],
    "sg:phone":"+1 407 323 8177",
    "sg:postcode":"32773",
    "sg:province":"FL",
    "sg:tags":[
        "graphic",
        "artist",
        "consultant",
        "instruction",
        "commercial",
        "designer",
        "galleries"
    ],
    "wof:name":"Raphael's Realm Inc",
    "wof:placetype":"venue"
},
  "geometry": {"coordinates":[-81.27203,28.784809],"type":"Point"}
}