{
  "type": "Feature",
  "properties": {
    "addr:full":"5002 Cortez Rd W Bradenton FL 34210",
    "addr:housenumber":"5002",
    "addr:postcode":"34210",
    "addr:street":"Cortez Rd W",
    "iso:country":"US",
    "sg:address":"5002 Cortez Rd W",
    "sg:city":"Bradenton",
    "sg:classifiers":[
        {
            "category":"Restaurant",
            "type":"Food & Drink"
        }
    ],
    "sg:phone":"+1 941 792 8366",
    "sg:postcode":"34210",
    "sg:province":"FL",
    "sg:tags":[
        "eating"
    ],
    "sg:website":"www.bostonmarket.com",
    "wof:name":"Boston Market",
    "wof:placetype":"venue"
},
  "geometry": {"coordinates":[-82.612433,27.462366],"type":"Point"}
}