{
  "type": "Feature",
  "properties": {
    "iso:country":"US",
    "sg:address":"7835 SW 66th St",
    "sg:city":"South Miami",
    "sg:classifiers":[
        {
            "category":"Banks & Credit Unions",
            "subcategory":"Financial Services",
            "type":"Services"
        }
    ],
    "sg:phone":"+1 305 598 1747",
    "sg:postcode":"33143",
    "sg:province":"FL",
    "sg:tags":[
        "broker",
        "mortgage"
    ],
    "wof:name":"Home Loan Center",
    "wof:placetype":"venue"
},
  "geometry": {"coordinates":[-80.320999,25.7083],"type":"Point"}
}