{
  "type": "Feature",
  "properties": {
    "iso:country":"US",
    "sg:address":"1661 Desoto Rd",
    "sg:city":"Sarasota",
    "sg:classifiers":[
        {
            "category":"Wholesale",
            "subcategory":"Construction Materials",
            "type":"Manufacturing & Wholesale Goods"
        },
        {
            "category":"Mining & Drilling",
            "type":"Manufacturing & Wholesale Goods"
        }
    ],
    "sg:phone":"+1 941 351 6178",
    "sg:postcode":"34234",
    "sg:province":"FL",
    "sg:tags":[
        "granite",
        "stone",
        "precast"
    ],
    "wof:name":"Seashore Stones and Granite",
    "wof:placetype":"venue"
},
  "geometry": {"coordinates":[-82.53795100000001,27.381802],"type":"Point"}
}