{
  "type": "Feature",
  "properties": {
    "iso:country":"US",
    "sg:address":"3640 S West Shore Blvd",
    "sg:city":"Tampa",
    "sg:classifiers":[
        {
            "category":"Professional",
            "subcategory":"Computer Services",
            "type":"Services"
        }
    ],
    "sg:phone":"+1 813 832 1100",
    "sg:postcode":"33629",
    "sg:province":"FL",
    "sg:website":"www.qtsi.com",
    "wof:name":"Quantum Technology Svc Inc",
    "wof:placetype":"venue"
},
  "geometry": {"coordinates":[-82.526642,27.909222],"type":"Point"}
}