{
  "type": "Feature",
  "properties": {
    "addr:full":"752 July Cir Fort Myers FL 33903",
    "addr:housenumber":"752",
    "addr:postcode":"33903",
    "addr:street":"July Cir",
    "iso:country":"US",
    "sg:address":"752 July Cir",
    "sg:city":"Fort Myers",
    "sg:classifiers":[
        {
            "category":"Building & Trades",
            "subcategory":"Construction",
            "type":"Services"
        }
    ],
    "sg:phone":"+1 239 652 0231",
    "sg:postcode":"33903",
    "sg:province":"FL",
    "sg:tags":[
        "tile",
        "dealer"
    ],
    "wof:name":"Gulf Breeze Tile",
    "wof:placetype":"venue"
},
  "geometry": {"coordinates":[-81.91086,26.664995],"type":"Point"}
}