{
  "type": "Feature",
  "properties": {
    "iso:country":"US",
    "sg:address":"1318 Franklin St",
    "sg:city":"Clearwater",
    "sg:classifiers":[
        {
            "category":"Real Estate",
            "subcategory":"Real Estate Operator",
            "type":"Services"
        },
        {
            "category":"Social Services",
            "type":"Services"
        }
    ],
    "sg:phone":"+1 727 441 8400",
    "sg:postcode":"33756",
    "sg:province":"FL",
    "sg:tags":[
        "apartment"
    ],
    "wof:name":"Creekside Manor I",
    "wof:placetype":"venue"
},
  "geometry": {"coordinates":[-82.780534,27.962968],"type":"Point"}
}