{
  "type": "Feature",
  "properties": {
    "addr:full":"14400 State Rd 54 Odessa FL 33556",
    "addr:housenumber":"14400;54",
    "addr:postcode":"33556",
    "addr:street":"State Rd",
    "iso:country":"US",
    "sg:address":"14400 State Rd 54",
    "sg:city":"Odessa",
    "sg:classifiers":[
        {
            "category":"Wholesale",
            "subcategory":"Farm Supplies",
            "type":"Manufacturing & Wholesale Goods"
        }
    ],
    "sg:phone":"+1 813 926 5972",
    "sg:postcode":"33556",
    "sg:province":"FL",
    "sg:tags":[
        "feed"
    ],
    "wof:name":"This & That Equine",
    "wof:placetype":"venue"
},
  "geometry": {"coordinates":[-82.57780099999999,28.189835],"type":"Point"}
}