{
  "type": "Feature",
  "properties": {
    "iso:country":"US",
    "sg:address":"8333 W McNab Rd",
    "sg:city":"Tamarac",
    "sg:classifiers":[
        {
            "category":"Social Services",
            "type":"Services"
        }
    ],
    "sg:phone":"+1 954 726 0011",
    "sg:postcode":"33321",
    "sg:province":"FL",
    "sg:tags":[
        "senior",
        "citizen"
    ],
    "sg:website":"www.alzsefc.org",
    "wof:name":"Alzheimer's Association",
    "wof:placetype":"venue"
},
  "geometry": {"coordinates":[-80.263299,26.20846],"type":"Point"}
}