{
  "type": "Feature",
  "properties": {
    "iso:country":"US",
    "sg:address":"5226 San Miguel St",
    "sg:city":"Milton",
    "sg:classifiers":[
        {
            "category":"Manufacturing",
            "subcategory":"Motor Vehicles & Parts",
            "type":"Manufacturing & Wholesale Goods"
        },
        {
            "category":"Retail",
            "subcategory":"Repair Shop",
            "type":"Services"
        }
    ],
    "sg:phone":"+1 850 995 7409",
    "sg:postcode":"32583",
    "sg:province":"FL",
    "sg:tags":[
        "electric",
        "pumps-service"
    ],
    "wof:name":"Milstid Electric Motors & Pumps",
    "wof:placetype":"venue"
},
  "geometry": {"coordinates":[-87.107356,30.54608],"type":"Point"}
}