{
  "type": "Feature",
  "properties": {
    "iso:country":"US",
    "sg:address":"111 Atlantic Annex Pt",
    "sg:city":"Maitland",
    "sg:classifiers":[
        {
            "category":"Professional",
            "subcategory":"Engineering",
            "type":"Services"
        },
        {
            "category":"Manufacturing",
            "subcategory":"Tools & Machinery",
            "type":"Manufacturing & Wholesale Goods"
        }
    ],
    "sg:phone":"+1 407 262 9042",
    "sg:postcode":"32751",
    "sg:province":"FL",
    "sg:tags":[
        "mfg",
        "design",
        "simulator",
        "flight",
        "engineer"
    ],
    "sg:website":"www.servos.com",
    "wof:name":"Servos and Simulation Inc",
    "wof:placetype":"venue"
},
  "geometry": {"coordinates":[-81.356556,28.647069],"type":"Point"}
}