{
  "type": "Feature",
  "properties": {
    "addr:full":"1307 E 5th St Panama City FL 32401",
    "addr:housenumber":"1307",
    "addr:postcode":"32401",
    "addr:street":"E 5Th St",
    "iso:country":"US",
    "sg:address":"1307 E 5th St",
    "sg:city":"Panama City",
    "sg:classifiers":[
        {
            "category":"Food & Beverages",
            "subcategory":"Groceries & Convenience Stores",
            "type":"Retail Goods"
        }
    ],
    "sg:phone":"+1 850 763 2375",
    "sg:postcode":"32401",
    "sg:province":"FL",
    "wof:name":"E Z Mart",
    "wof:placetype":"venue"
},
  "geometry": {"coordinates":[-85.640928,30.157303],"type":"Point"}
}