{
  "type": "Feature",
  "properties": {
    "addr:full":"616 NW 167th St Miami FL 33169",
    "addr:housenumber":"616",
    "addr:postcode":"33169",
    "addr:street":"Nw 167Th St",
    "iso:country":"US",
    "sg:address":"616 NW 167th St",
    "sg:city":"Miami",
    "sg:classifiers":[
        {
            "category":"Organizations",
            "subcategory":"Religious Organization",
            "type":"Services"
        }
    ],
    "sg:phone":"+1 305 652 3229",
    "sg:postcode":"33169",
    "sg:province":"FL",
    "wof:name":"True Believers In Christ",
    "wof:placetype":"venue"
},
  "geometry": {"coordinates":[-80.21102999999999,25.927583],"type":"Point"}
}