{
  "type": "Feature",
  "properties": {
    "iso:country":"US",
    "sg:address":"7657 NW 50th St",
    "sg:city":"Miami",
    "sg:phone":"+1 305 571 0620",
    "sg:postcode":"33166",
    "sg:province":"FL",
    "wof:name":"Alpha Development Group",
    "wof:placetype":"venue"
},
  "geometry": {"coordinates":[-80.320654,25.818945],"type":"Point"}
}