{
  "type": "Feature",
  "properties": {
    "iso:country":"US",
    "sg:address":"1830 Wales Dr",
    "sg:city":"Tallahassee",
    "sg:classifiers":[
        {
            "category":"Manufacturing",
            "subcategory":"Electronics",
            "type":"Manufacturing & Wholesale Goods"
        }
    ],
    "sg:phone":"+1 850 297 1490",
    "sg:postcode":"32303",
    "sg:province":"FL",
    "sg:tags":[
        "equipment",
        "mfg",
        "communications"
    ],
    "wof:name":"Advanced Visual Solutions",
    "wof:placetype":"venue"
},
  "geometry": {"coordinates":[-84.319209,30.477084],"type":"Point"}
}