{
  "type": "Feature",
  "properties": {
    "addr:full":"1250 Reed Canal Rd Port Orange FL 32129",
    "addr:housenumber":"1250",
    "addr:postcode":"32129",
    "addr:street":"Reed Canal Rd",
    "iso:country":"US",
    "sg:address":"1250 Reed Canal Rd",
    "sg:city":"Port Orange",
    "sg:classifiers":[
        {
            "category":"Education",
            "subcategory":"School",
            "type":"Public Place"
        }
    ],
    "sg:phone":"+1 386 322 6101",
    "sg:postcode":"32129",
    "sg:province":"FL",
    "wof:name":"Volusia County Comm Schools",
    "wof:placetype":"venue"
},
  "geometry": {"coordinates":[-81.023173,29.15231],"type":"Point"}
}