{
  "type": "Feature",
  "properties": {
    "iso:country":"US",
    "sg:address":"2830 NW 55th Ct",
    "sg:city":"Fort Lauderdale",
    "sg:classifiers":[
        {
            "category":"Manufacturing",
            "subcategory":"Rubber & Plastics",
            "type":"Manufacturing & Wholesale Goods"
        },
        {
            "category":"Wholesale",
            "subcategory":"Chemicals & Plastics",
            "type":"Manufacturing & Wholesale Goods"
        }
    ],
    "sg:phone":"+1 954 735 8777",
    "sg:postcode":"33309",
    "sg:province":"FL",
    "sg:tags":[
        "product"
    ],
    "sg:website":"www.e-tplastics.com",
    "wof:name":"E T Plastics",
    "wof:placetype":"venue"
},
  "geometry": {"coordinates":[-80.17924600000001,26.194215],"type":"Point"}
}