{
  "type": "Feature",
  "properties": {
    "iso:country":"US",
    "sg:address":"699 E 36th St",
    "sg:city":"Hialeah",
    "sg:classifiers":[
        {
            "category":"Shopping",
            "subcategory":"Discount & Variety Stores",
            "type":"Retail Goods"
        }
    ],
    "sg:phone":"+1 305 696 1950",
    "sg:postcode":"33013",
    "sg:province":"FL",
    "wof:name":"Sarita Inc",
    "wof:placetype":"venue"
},
  "geometry": {"coordinates":[-80.270606,25.855269],"type":"Point"}
}