{
  "type": "Feature",
  "properties": {
    "iso:country":"US",
    "sg:address":"1439 SE 14th St",
    "sg:city":"Stuart",
    "sg:classifiers":[
        {
            "category":"Freight",
            "type":"Transportation"
        }
    ],
    "sg:phone":"+1 772 286 1004",
    "sg:postcode":"34996",
    "sg:province":"FL",
    "sg:tags":[
        "operator",
        "local",
        "trucking"
    ],
    "wof:name":"Flexico Trucking LLC",
    "wof:placetype":"venue"
},
  "geometry": {"coordinates":[-80.226094,27.186487],"type":"Point"}
}