{
  "type": "Feature",
  "properties": {
    "iso:country":"US",
    "sg:address":"6 Roosevelt Blvd",
    "sg:city":"Beverly Hills",
    "sg:classifiers":[
        {
            "category":"Organizations",
            "subcategory":"Religious Organization",
            "type":"Services"
        }
    ],
    "sg:phone":"+1 352 746 2144",
    "sg:postcode":"34465",
    "sg:province":"FL",
    "sg:tags":[
        "church"
    ],
    "wof:name":"Our Lady Of Grace Catholic Chr",
    "wof:placetype":"venue"
},
  "geometry": {"coordinates":[-82.463689,28.920353],"type":"Point"}
}