{
  "type": "Feature",
  "properties": {
    "iso:country":"US",
    "sg:address":"9450 W Mark Ct",
    "sg:city":"Crystal River",
    "sg:classifiers":[
        {
            "category":"Retail",
            "subcategory":"Auto Repair",
            "type":"Services"
        }
    ],
    "sg:phone":"+1 352 795 3411",
    "sg:postcode":"34428",
    "sg:province":"FL",
    "sg:tags":[
        "body"
    ],
    "wof:name":"Autocrafters Collision Center",
    "wof:placetype":"venue"
},
  "geometry": {"coordinates":[-82.59254300000001,28.922047],"type":"Point"}
}