{
  "type": "Feature",
  "properties": {
    "addr:full":"8091 N Military Trl Palm Beach Gardens FL 33410",
    "addr:housenumber":"8091",
    "addr:postcode":"33410",
    "addr:street":"N Military Trl",
    "iso:country":"US",
    "sg:address":"8091 N Military Trl",
    "sg:city":"Palm Beach Gardens",
    "sg:classifiers":[
        {
            "category":"Shopping",
            "subcategory":"Bicycles & Sporting Goods",
            "type":"Retail Goods"
        }
    ],
    "sg:phone":"+1 561 627 0640",
    "sg:postcode":"33410",
    "sg:province":"FL",
    "sg:tags":[
        "equipment",
        "golf"
    ],
    "wof:name":"Ricks Golf Shop",
    "wof:placetype":"venue"
},
  "geometry": {"coordinates":[-80.106798,26.794452],"type":"Point"}
}