{
  "type": "Feature",
  "properties": {
    "iso:country":"US",
    "sg:address":"146 Brooks Rd",
    "sg:city":"Fort Myers",
    "sg:classifiers":[
        {
            "category":"Banks & Credit Unions",
            "subcategory":"Bank",
            "type":"Services"
        }
    ],
    "sg:phone":"+1 239 656 6614",
    "sg:postcode":"33917",
    "sg:province":"FL",
    "sg:tags":[
        "federal",
        "savings",
        "institution"
    ],
    "wof:name":"Srd of Southwest Florida Inc",
    "wof:placetype":"venue"
},
  "geometry": {"coordinates":[-81.882093,26.671032],"type":"Point"}
}