{
  "type": "Feature",
  "properties": {
    "iso:country":"US",
    "sg:address":"2340 SW Palm City Rd",
    "sg:city":"Stuart",
    "sg:classifiers":[
        {
            "category":"Autos & Motor Vehicles",
            "subcategory":"Boat Sales",
            "type":"Retail Goods"
        }
    ],
    "sg:phone":"+1 772 220 0707",
    "sg:postcode":"34994",
    "sg:province":"FL",
    "sg:tags":[
        "yacht",
        "broker"
    ],
    "sg:website":"www.marinemax.com",
    "wof:name":"Marine Max Inc",
    "wof:placetype":"venue"
},
  "geometry": {"coordinates":[-80.257037,27.176278],"type":"Point"}
}