{
  "type": "Feature",
  "properties": {
    "addr:full":"1012 US Hwy 27 Avon Park FL 33825",
    "addr:housenumber":"1012",
    "addr:postcode":"33825",
    "addr:street":"Us Hwy 27",
    "iso:country":"US",
    "sg:address":"1012 US Hwy 27",
    "sg:city":"Avon Park",
    "sg:classifiers":[
        {
            "category":"Personal",
            "subcategory":"Beauty Salon",
            "type":"Services"
        }
    ],
    "sg:phone":"+1 863 453 3724",
    "sg:postcode":"33825",
    "sg:province":"FL",
    "sg:tags":[
        "manicuring"
    ],
    "wof:name":"Avon Nail",
    "wof:placetype":"venue"
},
  "geometry": {"coordinates":[-81.514546,27.584368],"type":"Point"}
}