{
  "type": "Feature",
  "properties": {
    "addr:full":"107 S Parsons Ave Brandon FL 33511",
    "addr:housenumber":"107",
    "addr:postcode":"33511",
    "addr:street":"S Parsons Ave",
    "iso:country":"US",
    "sg:address":"107 S Parsons Ave",
    "sg:city":"Brandon",
    "sg:classifiers":[
        {
            "category":"Professional",
            "subcategory":"Accounting & Tax Preparation",
            "type":"Services"
        }
    ],
    "sg:phone":"+1 813 681 8228",
    "sg:postcode":"33511",
    "sg:province":"FL",
    "sg:tags":[
        "return",
        "filing"
    ],
    "wof:name":"Seffner Bookkeeping Co",
    "wof:placetype":"venue"
},
  "geometry": {"coordinates":[-82.285873,27.935909],"type":"Point"}
}