{
  "type": "Feature",
  "properties": {
    "addr:full":"2318 James L Redman Pkwy Plant City FL 33563",
    "addr:housenumber":"2318",
    "addr:postcode":"33563",
    "addr:street":"James L Redman Pkwy",
    "iso:country":"US",
    "sg:address":"2318 James L Redman Pkwy",
    "sg:city":"Plant City",
    "sg:classifiers":[
        {
            "category":"Banks & Credit Unions",
            "subcategory":"Bank",
            "type":"Services"
        }
    ],
    "sg:phone":"+1 813 759 1240",
    "sg:postcode":"33563",
    "sg:province":"FL",
    "wof:name":"Colonial Bank",
    "wof:placetype":"venue"
},
  "geometry": {"coordinates":[-82.121495,27.989884],"type":"Point"}
}