{
  "type": "Feature",
  "properties": {
    "addr:full":"10035 W Hillsborough Ave Tampa FL 33615",
    "addr:housenumber":"10035",
    "addr:postcode":"33615",
    "addr:street":"W Hillsborough Ave",
    "iso:country":"US",
    "sg:address":"10035 W Hillsborough Ave",
    "sg:city":"Tampa",
    "sg:classifiers":[
        {
            "category":"Building & Trades",
            "subcategory":"Construction",
            "type":"Services"
        }
    ],
    "sg:phone":"+1 813 882 4224",
    "sg:postcode":"33615",
    "sg:province":"FL",
    "sg:tags":[
        "house"
    ],
    "wof:name":"Danire Investment Properties",
    "wof:placetype":"venue"
},
  "geometry": {"coordinates":[-82.598696,28.004429],"type":"Point"}
}