{
  "type": "Feature",
  "properties": {
    "addr:full":"2013 Morning Dove Rd Tallahassee FL 32312",
    "addr:housenumber":"2013",
    "addr:postcode":"32312",
    "addr:street":"Morning Dove Rd",
    "iso:country":"US",
    "sg:address":"2013 Morning Dove Rd",
    "sg:city":"Tallahassee",
    "sg:classifiers":[
        {
            "category":"Building & Trades",
            "subcategory":"Construction",
            "type":"Services"
        }
    ],
    "sg:phone":"+1 850 893 8820",
    "sg:postcode":"32312",
    "sg:province":"FL",
    "sg:tags":[
        "house"
    ],
    "wof:name":"Tenleytown Construction Inc",
    "wof:placetype":"venue"
},
  "geometry": {"coordinates":[-84.238928,30.605257],"type":"Point"}
}