{
  "type": "Feature",
  "properties": {
    "iso:country":"US",
    "sg:address":"6000 49th St N",
    "sg:city":"St Petersburg",
    "sg:classifiers":[
        {
            "category":"Health Services",
            "subcategory":"Hospital",
            "type":"Services"
        }
    ],
    "sg:phone":"+1 727 521 4411",
    "sg:postcode":"33709",
    "sg:province":"FL",
    "wof:name":"Northside Hospital & Heart/ Re",
    "wof:placetype":"venue"
},
  "geometry": {"coordinates":[-82.69991400000001,27.827372],"type":"Point"}
}