{
  "type": "Feature",
  "properties": {
    "addr:full":"1750 W Jefferson St Quincy FL 32351",
    "addr:housenumber":"1750",
    "addr:postcode":"32351",
    "addr:street":"W Jefferson St",
    "iso:country":"US",
    "sg:address":"1750 W Jefferson St",
    "sg:city":"Quincy",
    "sg:classifiers":[
        {
            "category":"Retail",
            "subcategory":"Veterinary Services",
            "type":"Services"
        }
    ],
    "sg:phone":"+1 850 875 4811",
    "sg:postcode":"32351",
    "sg:province":"FL",
    "sg:tags":[
        "hospital",
        "animal"
    ],
    "wof:name":"Quincy Animal Hospital Inc",
    "wof:placetype":"venue"
},
  "geometry": {"coordinates":[-84.60024,30.585559],"type":"Point"}
}