{
  "type": "Feature",
  "properties": {
    "iso:country":"US",
    "sg:address":"2323 Bayview Ave",
    "sg:city":"Panama City",
    "sg:classifiers":[
        {
            "category":"Education",
            "subcategory":"Vocational School",
            "type":"Public Place"
        }
    ],
    "sg:phone":"+1 850 785 7266",
    "sg:postcode":"32405",
    "sg:province":"FL",
    "sg:tags":[
        "aid",
        "training",
        "first"
    ],
    "wof:name":"Cpr For Life",
    "wof:placetype":"venue"
},
  "geometry": {"coordinates":[-85.701802,30.191011],"type":"Point"}
}