{
  "type": "Feature",
  "properties": {
    "addr:full":"2370 SW 56th Ave Hollywood FL 33023",
    "addr:housenumber":"2370",
    "addr:postcode":"33023",
    "addr:street":"Sw 56Th Ave",
    "iso:country":"US",
    "sg:address":"2370 SW 56th Ave",
    "sg:city":"Hollywood",
    "sg:classifiers":[
        {
            "category":"Retail",
            "subcategory":"Auto Repair",
            "type":"Services"
        }
    ],
    "sg:phone":"+1 954 962 7971",
    "sg:postcode":"33023",
    "sg:province":"FL",
    "sg:tags":[
        "repairing",
        "automobile"
    ],
    "wof:name":"A 1 Choice Auto & Trans Inc",
    "wof:placetype":"venue"
},
  "geometry": {"coordinates":[-80.198654,25.989375],"type":"Point"}
}