{
  "type": "Feature",
  "properties": {
    "iso:country":"US",
    "sg:address":"6913 NW 43rd St",
    "sg:city":"Miami",
    "sg:classifiers":[
        {
            "category":"Wholesale",
            "subcategory":"Machinery & Supplies",
            "type":"Manufacturing & Wholesale Goods"
        }
    ],
    "sg:phone":"+1 305 718 4422",
    "sg:postcode":"33166",
    "sg:province":"FL",
    "sg:tags":[
        "aircraft",
        "parts"
    ],
    "wof:name":"CMS Aircraft Support Group",
    "wof:placetype":"venue"
},
  "geometry": {"coordinates":[-80.311196,25.813534],"type":"Point"}
}