{
  "type": "Feature",
  "properties": {
    "addr:full":"220 N Federal Hwy Hallandale Beach FL 33009",
    "addr:housenumber":"220",
    "addr:postcode":"33009",
    "addr:street":"N Federal Hwy",
    "iso:country":"US",
    "sg:address":"220 N Federal Hwy",
    "sg:city":"Hallandale Beach",
    "sg:classifiers":[
        {
            "category":"Wholesale",
            "subcategory":"Hardware",
            "type":"Manufacturing & Wholesale Goods"
        }
    ],
    "sg:phone":"+1 954 457 2073",
    "sg:postcode":"33009",
    "sg:province":"FL",
    "sg:tags":[
        "lock",
        "locksmith"
    ],
    "wof:name":"United Lock & Hardware",
    "wof:placetype":"venue"
},
  "geometry": {"coordinates":[-80.142298,25.988107],"type":"Point"}
}