{
  "type": "Feature",
  "properties": {
    "iso:country":"US",
    "sg:address":"7130 S Orange Blossom Trl",
    "sg:city":"Orlando",
    "sg:classifiers":[
        {
            "category":"Professional",
            "subcategory":"Accounting & Tax Preparation",
            "type":"Services"
        }
    ],
    "sg:phone":"+1 407 851 4037",
    "sg:postcode":"32809",
    "sg:province":"FL",
    "sg:tags":[
        "return",
        "filing"
    ],
    "wof:name":"Bee-Square Income Tax Svc",
    "wof:placetype":"venue"
},
  "geometry": {"coordinates":[-81.397969,28.460687],"type":"Point"}
}