{
  "type": "Feature",
  "properties": {
    "addr:full":"212 N 1st St Immokalee FL 34142",
    "addr:housenumber":"212",
    "addr:postcode":"34142",
    "addr:street":"N 1St St",
    "iso:country":"US",
    "sg:address":"212 N 1st St",
    "sg:city":"Immokalee",
    "sg:classifiers":[
        {
            "category":"Professional",
            "subcategory":"Employment Agencies",
            "type":"Services"
        }
    ],
    "sg:phone":"+1 239 657 3128",
    "sg:postcode":"34142",
    "sg:province":"FL",
    "sg:tags":[
        "opportunity"
    ],
    "wof:name":"Job Service",
    "wof:placetype":"venue"
},
  "geometry": {"coordinates":[-81.417554,26.422172],"type":"Point"}
}