{
  "type": "Feature",
  "properties": {
    "addr:full":"8004 Landgrove Ct Orlando FL 32819",
    "addr:housenumber":"8004",
    "addr:postcode":"32819",
    "addr:street":"Landgrove Ct",
    "iso:country":"US",
    "sg:address":"8004 Landgrove Ct",
    "sg:city":"Orlando",
    "sg:classifiers":[
        {
            "category":"Organizations",
            "subcategory":"Membership Organization",
            "type":"Services"
        }
    ],
    "sg:phone":"+1 407 296 3263",
    "sg:postcode":"32819",
    "sg:province":"FL",
    "sg:tags":[
        "club",
        "travel"
    ],
    "sg:website":"http://www.playfloridagolf.com",
    "wof:name":"Play Florida Golf",
    "wof:placetype":"venue"
},
  "geometry": {"coordinates":[-81.493404,28.492159],"type":"Point"}
}