{
  "type": "Feature",
  "properties": {
    "addr:full":"14171 N Magnolia Ave Citra FL 32113",
    "addr:housenumber":"14171",
    "addr:postcode":"32113",
    "addr:street":"N Magnolia Ave",
    "iso:country":"US",
    "sg:address":"14171 N Magnolia Ave",
    "sg:city":"Citra",
    "sg:classifiers":[
        {
            "category":"Education",
            "subcategory":"Special Training",
            "type":"Public Place"
        }
    ],
    "sg:phone":"+1 352 598 4793",
    "sg:postcode":"32113",
    "sg:province":"FL",
    "sg:tags":[
        "educational"
    ],
    "wof:name":"Designs By Eme",
    "wof:placetype":"venue"
},
  "geometry": {"coordinates":[-82.138183,29.35362],"type":"Point"}
}