{
  "type": "Feature",
  "properties": {
    "addr:full":"3650 Satterfield Rd Titusville FL 32780",
    "addr:postcode":"3650;32780",
    "addr:street":"Satterfield Rd",
    "iso:country":"US",
    "sg:address":"3650 Satterfield Rd",
    "sg:city":"Titusville",
    "sg:classifiers":[
        {
            "category":"Retail",
            "subcategory":"Portrait Studio",
            "type":"Services"
        }
    ],
    "sg:phone":"+1 321 267 0655",
    "sg:postcode":"32780",
    "sg:province":"FL",
    "sg:tags":[
        "photo"
    ],
    "wof:name":"Ron Boyd Photography",
    "wof:placetype":"venue"
},
  "geometry": {"coordinates":[-80.846906,28.572385],"type":"Point"}
}