{
  "type": "Feature",
  "properties": {
    "iso:country":"US",
    "sg:address":"1015 Medallion Dr",
    "sg:city":"Rockledge",
    "sg:classifiers":[
        {
            "category":"Manufacturing",
            "subcategory":"Textiles",
            "type":"Manufacturing & Wholesale Goods"
        }
    ],
    "sg:phone":"+1 321 636 7929",
    "sg:postcode":"32955",
    "sg:province":"FL",
    "sg:tags":[
        "mill",
        "fabric"
    ],
    "wof:name":"Deborah Deans Silk Ledge",
    "wof:placetype":"venue"
},
  "geometry": {"coordinates":[-80.745993,28.326934],"type":"Point"}
}