{
  "type": "Feature",
  "properties": {
    "iso:country":"US",
    "sg:address":"11078 US Hwy 90 W",
    "sg:city":"Defuniak Springs",
    "sg:classifiers":[
        {
            "category":"Home & Garden",
            "subcategory":"Furniture",
            "type":"Retail Goods"
        }
    ],
    "sg:phone":"+1 850 892 0430",
    "sg:postcode":"32433",
    "sg:province":"FL",
    "wof:name":"This & That",
    "wof:placetype":"venue"
},
  "geometry": {"coordinates":[-86.297483,30.747823],"type":"Point"}
}