{
  "type": "Feature",
  "properties": {
    "addr:full":"3215 NE 2nd Ave Miami FL 33137",
    "addr:housenumber":"3215",
    "addr:postcode":"33137",
    "addr:street":"Ne 2Nd Ave",
    "iso:country":"US",
    "sg:address":"3215 NE 2nd Ave",
    "sg:city":"Miami",
    "sg:classifiers":[
        {
            "category":"Building & Trades",
            "subcategory":"Electrical",
            "type":"Services"
        }
    ],
    "sg:phone":"+1 305 576 8885",
    "sg:postcode":"33137",
    "sg:province":"FL",
    "sg:tags":[
        "home",
        "system",
        "automation"
    ],
    "wof:name":"Evolution Entertainment USA",
    "wof:placetype":"venue"
},
  "geometry": {"coordinates":[-80.19109,25.807432],"type":"Point"}
}