{
  "type": "Feature",
  "properties": {
    "iso:country":"US",
    "sg:address":"1495 NW 3rd Ave",
    "sg:city":"Miami",
    "sg:classifiers":[
        {
            "category":"Restaurant",
            "type":"Food & Drink"
        }
    ],
    "sg:phone":"+1 305 573 6104",
    "sg:postcode":"33136",
    "sg:province":"FL",
    "sg:tags":[
        "house",
        "steak",
        "barbecue"
    ],
    "wof:name":"Jackie's House",
    "wof:placetype":"venue"
},
  "geometry": {"coordinates":[-80.19998099999999,25.789467],"type":"Point"}
}