{
  "type": "Feature",
  "properties": {
    "iso:country":"US",
    "sg:address":"4730 Orange Blvd",
    "sg:city":"Sanford",
    "sg:classifiers":[
        {
            "category":"Organizations",
            "subcategory":"Religious Organization",
            "type":"Services"
        }
    ],
    "sg:phone":"+1 407 321 3666",
    "sg:postcode":"32771",
    "sg:province":"FL",
    "wof:name":"Blessing From Jesus Over The Road Ministry",
    "wof:placetype":"venue"
},
  "geometry": {"coordinates":[-81.336687,28.828731],"type":"Point"}
}