{
  "type": "Feature",
  "properties": {
    "addr:full":"6481 Hidden Oaks Dr Fort Myers FL 33917",
    "addr:housenumber":"6481",
    "addr:postcode":"33917",
    "addr:street":"Hidden Oaks Dr",
    "iso:country":"US",
    "sg:address":"6481 Hidden Oaks Dr",
    "sg:city":"Fort Myers",
    "sg:classifiers":[
        {
            "category":"Professional",
            "type":"Services"
        }
    ],
    "sg:phone":"+1 239 567 0746",
    "sg:postcode":"33917",
    "sg:province":"FL",
    "sg:tags":[
        "establishment"
    ],
    "wof:name":"River Estates",
    "wof:placetype":"venue"
},
  "geometry": {"coordinates":[-81.85119299999999,26.708252],"type":"Point"}
}