{
  "type": "Feature",
  "properties": {
    "addr:full":"69 Coquina Ridge Way Ormond Beach FL 32174",
    "addr:housenumber":"69",
    "addr:postcode":"32174",
    "addr:street":"Coquina Ridge Way",
    "iso:country":"US",
    "sg:address":"69 Coquina Ridge Way",
    "sg:city":"Ormond Beach",
    "sg:classifiers":[
        {
            "category":"Restaurant",
            "type":"Food & Drink"
        }
    ],
    "sg:phone":"+1 386 671 6363",
    "sg:postcode":"32174",
    "sg:province":"FL",
    "sg:tags":[
        "eating"
    ],
    "wof:name":"Hammerhead Restaurants Inc",
    "wof:placetype":"venue"
},
  "geometry": {"coordinates":[-81.146997,29.265103],"type":"Point"}
}