{
  "type": "Feature",
  "properties": {
    "addr:full":"7445 Collins Ave Miami Beach FL 33141",
    "addr:housenumber":"7445",
    "addr:postcode":"33141",
    "addr:street":"Collins Ave",
    "iso:country":"US",
    "sg:address":"7445 Collins Ave",
    "sg:city":"Miami Beach",
    "sg:classifiers":[
        {
            "category":"Restaurant",
            "type":"Food & Drink"
        }
    ],
    "sg:phone":"+1 305 868 7445",
    "sg:postcode":"33141",
    "sg:province":"FL",
    "sg:tags":[
        "eating"
    ],
    "wof:name":"Confucius Restaurant Inc",
    "wof:placetype":"venue"
},
  "geometry": {"coordinates":[-80.12050600000001,25.857418],"type":"Point"}
}