{
  "type": "Feature",
  "properties": {
    "iso:country":"US",
    "sg:address":"13232 NW 9th Ln",
    "sg:city":"Miami",
    "sg:classifiers":[
        {
            "category":"Health Services",
            "subcategory":"Nursing And Care Facility",
            "type":"Services"
        },
        {
            "category":"Social Services",
            "subcategory":"Retirement Home",
            "type":"Services"
        }
    ],
    "sg:phone":"+1 305 485 9675",
    "sg:postcode":"33182",
    "sg:province":"FL",
    "sg:tags":[
        "living",
        "assisted",
        "convalescent",
        "homes-intermediate"
    ],
    "wof:name":"Prince Of Peace Elderly Care",
    "wof:placetype":"venue"
},
  "geometry": {"coordinates":[-80.409536,25.77891],"type":"Point"}
}