{
  "type": "Feature",
  "properties": {
    "iso:country":"US",
    "sg:address":"3626 Mary St",
    "sg:city":"Miami",
    "sg:classifiers":[
        {
            "category":"Recreation",
            "subcategory":"Boat Charter",
            "type":"Entertainment"
        }
    ],
    "sg:phone":"+1 305 461 9230",
    "sg:postcode":"33133",
    "sg:province":"FL",
    "sg:tags":[
        "boat-rental"
    ],
    "wof:name":"Blue Waters JB Charters",
    "wof:placetype":"venue"
},
  "geometry": {"coordinates":[-80.238743,25.727585],"type":"Point"}
}