{
  "type": "Feature",
  "properties": {
    "iso:country":"US",
    "sg:address":"15796 129th Ter N",
    "sg:city":"Jupiter",
    "sg:classifiers":[
        {
            "category":"Building & Trades",
            "subcategory":"Construction",
            "type":"Services"
        }
    ],
    "sg:phone":"+1 561 747 0463",
    "sg:postcode":"33478",
    "sg:province":"FL",
    "sg:tags":[
        "carpentry",
        "contractor"
    ],
    "wof:name":"Robert Mickley Carpentry",
    "wof:placetype":"venue"
},
  "geometry": {"coordinates":[-80.238798,26.908388],"type":"Point"}
}