{
  "type": "Feature",
  "properties": {
    "iso:country":"US",
    "sg:address":"1225 Thunder Trl",
    "sg:city":"Maitland",
    "sg:classifiers":[
        {
            "category":"Building & Trades",
            "subcategory":"Construction",
            "type":"Services"
        }
    ],
    "sg:phone":"+1 407 830 1906",
    "sg:postcode":"32751",
    "sg:province":"FL",
    "sg:tags":[
        "roofing",
        "contractor"
    ],
    "wof:name":"Cliffco Roofing",
    "wof:placetype":"venue"
},
  "geometry": {"coordinates":[-81.32906699999999,28.640913],"type":"Point"}
}