{
  "type": "Feature",
  "properties": {
    "iso:country":"US",
    "sg:address":"1820 N Corporate Lakes Blvd",
    "sg:city":"Weston",
    "sg:classifiers":[
        {
            "category":"Real Estate",
            "subcategory":"Real Estate Services",
            "type":"Services"
        },
        {
            "category":"Real Estate",
            "subcategory":"Real Estate Agent",
            "type":"Services"
        }
    ],
    "sg:phone":"+1 954 384 9661",
    "sg:postcode":"33326",
    "sg:province":"FL",
    "sg:tags":[
        "buyer",
        "management",
        "broker"
    ],
    "wof:name":"Milano Realty",
    "wof:placetype":"venue"
},
  "geometry": {"coordinates":[-80.365567,26.095233],"type":"Point"}
}