{
  "type": "Feature",
  "properties": {
    "iso:country":"US",
    "sg:address":"1430 Elm Ave",
    "sg:city":"Winter Park",
    "sg:classifiers":[
        {
            "category":"Shopping",
            "subcategory":"Gifts & Souvenirs",
            "type":"Retail Goods"
        }
    ],
    "sg:phone":"+1 407 647 6777",
    "sg:postcode":"32789",
    "sg:province":"FL",
    "wof:name":"Balloons By Debbie",
    "wof:placetype":"venue"
},
  "geometry": {"coordinates":[-81.33463500000001,28.610364],"type":"Point"}
}