{
  "type": "Feature",
  "properties": {
    "iso:country":"US",
    "sg:address":"517 Hillcrest Dr SE",
    "sg:city":"Winter Haven",
    "sg:classifiers":[
        {
            "category":"Building & Trades",
            "subcategory":"Construction",
            "type":"Services"
        }
    ],
    "sg:phone":"+1 863 293 3842",
    "sg:postcode":"33884",
    "sg:province":"FL",
    "sg:tags":[
        "roofing",
        "contractor"
    ],
    "wof:name":"Brown Roofing",
    "wof:placetype":"venue"
},
  "geometry": {"coordinates":[-81.698807,27.998857],"type":"Point"}
}