{
  "type": "Feature",
  "properties": {
    "addr:full":"1699 Tarrytown Ave Deltona FL 32725",
    "addr:housenumber":"1699",
    "addr:postcode":"32725",
    "addr:street":"Tarrytown Ave",
    "iso:country":"US",
    "sg:address":"1699 Tarrytown Ave",
    "sg:city":"Deltona",
    "sg:classifiers":[
        {
            "category":"Building & Trades",
            "subcategory":"Construction",
            "type":"Services"
        }
    ],
    "sg:phone":"+1 386 789 4831",
    "sg:postcode":"32725",
    "sg:province":"FL",
    "sg:tags":[
        "hanging",
        "maintenance",
        "contractor"
    ],
    "wof:name":"Chriss Painting Company",
    "wof:placetype":"venue"
},
  "geometry": {"coordinates":[-81.251756,28.910445],"type":"Point"}
}