{
  "type": "Feature",
  "properties": {
    "addr:full":"5612 E Colonial Dr Orlando FL 32807",
    "addr:housenumber":"5612",
    "addr:postcode":"32807",
    "addr:street":"E Colonial Dr",
    "iso:country":"US",
    "sg:address":"5612 E Colonial Dr",
    "sg:city":"Orlando",
    "sg:classifiers":[
        {
            "category":"Shopping",
            "subcategory":"Music",
            "type":"Retail Goods"
        }
    ],
    "sg:phone":"+1 407 482 2037",
    "sg:postcode":"32807",
    "sg:province":"FL",
    "wof:name":"Arcoiris Video Club",
    "wof:placetype":"venue"
},
  "geometry": {"coordinates":[-81.310993,28.557009],"type":"Point"}
}