{
  "type": "Feature",
  "properties": {
    "iso:country":"US",
    "sg:address":"1731 S Orange Ave",
    "sg:city":"Orlando",
    "sg:classifiers":[
        {
            "category":"Communications",
            "subcategory":"Film & Video Production",
            "type":"Services"
        }
    ],
    "sg:phone":"+1 407 781 2360",
    "sg:postcode":"32806",
    "sg:province":"FL",
    "sg:tags":[
        "tv",
        "services-commercial",
        "companies-film",
        "radio"
    ],
    "wof:name":"Mobile Professional Servi",
    "wof:placetype":"venue"
},
  "geometry": {"coordinates":[-81.376411,28.521905],"type":"Point"}
}