{
  "type": "Feature",
  "properties": {
    "iso:country":"US",
    "sg:address":"528 Reserve Dr",
    "sg:city":"Tavares",
    "sg:classifiers":[
        {
            "category":"Retail",
            "subcategory":"Auto Rental",
            "type":"Services"
        }
    ],
    "sg:phone":"+1 352 742 9009",
    "sg:postcode":"32778",
    "sg:province":"FL",
    "sg:tags":[
        "trailer",
        "utility"
    ],
    "wof:name":"Broomfiled Mobile Home PA",
    "wof:placetype":"venue"
},
  "geometry": {"coordinates":[-81.729198,28.82089],"type":"Point"}
}