{
  "type": "Feature",
  "properties": {
    "addr:full":"575 79th St Ocean Marathon FL 33050",
    "addr:housenumber":"575",
    "addr:postcode":"33050",
    "addr:street":"79Th St",
    "iso:country":"US",
    "sg:address":"575 79th St Ocean",
    "sg:city":"Marathon",
    "sg:classifiers":[
        {
            "category":"Building & Trades",
            "subcategory":"Construction",
            "type":"Services"
        }
    ],
    "sg:phone":"+1 305 743 2913",
    "sg:postcode":"33050",
    "sg:province":"FL",
    "sg:tags":[
        "carpentry",
        "contractor"
    ],
    "wof:name":"Dm Cabinets & Countertops",
    "wof:placetype":"venue"
},
  "geometry": {"coordinates":[-81.05763399999999,24.721832],"type":"Point"}
}