{
  "type": "Feature",
  "properties": {
    "addr:full":"572 E Osceola Pkwy Kissimmee FL 34744",
    "addr:housenumber":"572",
    "addr:postcode":"34744",
    "addr:street":"E Osceola Pkwy",
    "iso:country":"US",
    "sg:address":"572 E Osceola Pkwy",
    "sg:city":"Kissimmee",
    "sg:classifiers":[
        {
            "category":"Shopping",
            "type":"Retail Goods"
        }
    ],
    "sg:phone":"+1 407 847 7611",
    "sg:postcode":"34744",
    "sg:province":"FL",
    "sg:tags":[
        "merchandise"
    ],
    "wof:name":"Aquarium Aqua Life",
    "wof:placetype":"venue"
},
  "geometry": {"coordinates":[-81.400549,28.337001],"type":"Point"}
}