{
  "type": "Feature",
  "properties": {
    "iso:country":"US",
    "sg:address":"12610 Henderson Rd",
    "sg:city":"Tampa",
    "sg:classifiers":[
        {
            "category":"Building & Trades",
            "subcategory":"Construction",
            "type":"Services"
        }
    ],
    "sg:phone":"+1 813 265 0020",
    "sg:postcode":"33625",
    "sg:province":"FL",
    "sg:tags":[
        "designer",
        "dealer",
        "pool",
        "swimming"
    ],
    "wof:name":"RLH Precision Pools & Spas",
    "wof:placetype":"venue"
},
  "geometry": {"coordinates":[-82.549847,28.057323],"type":"Point"}
}