{
  "type": "Feature",
  "properties": {
    "iso:country":"US",
    "sg:address":"7431 W Atlantic Ave",
    "sg:city":"Delray Beach",
    "sg:classifiers":[
        {
            "category":"Personal",
            "type":"Services"
        }
    ],
    "sg:phone":"+1 561 498 1001",
    "sg:postcode":"33446",
    "sg:province":"FL",
    "sg:tags":[
        "mail",
        "receiving"
    ],
    "wof:name":"Mailbox Express Toot",
    "wof:placetype":"venue"
},
  "geometry": {"coordinates":[-80.162251,26.45379],"type":"Point"}
}