{
  "type": "Feature",
  "properties": {
    "iso:country":"US",
    "sg:address":"16849 SE 93rd Cuthbert Cir",
    "sg:city":"Lady Lake",
    "sg:classifiers":[
        {
            "category":"Wholesale",
            "subcategory":"Hardware",
            "type":"Manufacturing & Wholesale Goods"
        }
    ],
    "sg:phone":"+1 352 750 5555",
    "sg:postcode":"32162",
    "sg:province":"FL",
    "sg:tags":[
        "purifying",
        "cleaning",
        "air"
    ],
    "wof:name":"3 Steps To Healthy Living",
    "wof:placetype":"venue"
},
  "geometry": {"coordinates":[-81.998254,28.975955],"type":"Point"}
}