{
  "type": "Feature",
  "properties": {
    "addr:full":"2631 NW 41 St Gainesville FL 32606",
    "addr:housenumber":"2631",
    "addr:postcode":"32606",
    "addr:street":"Nw 41 St",
    "iso:country":"US",
    "sg:address":"2631 NW 41 St",
    "sg:city":"Gainesville",
    "sg:classifiers":[
        {
            "category":"Professional",
            "subcategory":"Management & Consulting",
            "type":"Services"
        }
    ],
    "sg:phone":"+1 352 373 9140",
    "sg:postcode":"32606",
    "sg:province":"FL",
    "sg:tags":[
        "consultant",
        "business"
    ],
    "wof:name":"Doctor's Management",
    "wof:placetype":"venue"
},
  "geometry": {"coordinates":[-82.38665,29.676434],"type":"Point"}
}