{
  "type": "Feature",
  "properties": {
    "addr:full":"14407 SE 45th Ct Summerfield FL 34491",
    "addr:housenumber":"14407",
    "addr:postcode":"34491",
    "addr:street":"Se 45Th Ct",
    "iso:country":"US",
    "sg:address":"14407 SE 45th Ct",
    "sg:city":"Summerfield",
    "sg:classifiers":[
        {
            "category":"Shopping",
            "subcategory":"Discount & Variety Stores",
            "type":"Retail Goods"
        }
    ],
    "sg:phone":"+1 352 347 2509",
    "sg:postcode":"34491",
    "sg:province":"FL",
    "sg:tags":[
        "merchandise",
        "general"
    ],
    "wof:name":"Jennifer L Snyder",
    "wof:placetype":"venue"
},
  "geometry": {"coordinates":[-82.07281999999999,29.013135],"type":"Point"}
}