{
  "type": "Feature",
  "properties": {
    "iso:country":"US",
    "sg:address":"10033 W Hillsborough Ave",
    "sg:city":"Tampa",
    "sg:classifiers":[
        {
            "category":"Real Estate",
            "subcategory":"Real Estate Services",
            "type":"Services"
        }
    ],
    "sg:phone":"+1 813 243 4000",
    "sg:postcode":"33615",
    "sg:province":"FL",
    "sg:tags":[
        "company",
        "abstract",
        "title"
    ],
    "wof:name":"Nations Abstract and Title",
    "wof:placetype":"venue"
},
  "geometry": {"coordinates":[-82.59871200000001,28.00444],"type":"Point"}
}