{
  "type": "Feature",
  "properties": {
    "iso:country":"US",
    "sg:address":"251 S Clayton St",
    "sg:city":"Mount Dora",
    "sg:classifiers":[
        {
            "category":"Professional",
            "type":"Services"
        }
    ],
    "sg:phone":"+1 352 383 1998",
    "sg:postcode":"32757",
    "sg:province":"FL",
    "wof:name":"Patrica C Daum Dcrative Artist",
    "wof:placetype":"venue"
},
  "geometry": {"coordinates":[-81.63841499999999,28.795469],"type":"Point"}
}