{
  "type": "Feature",
  "properties": {
    "addr:full":"2524 River Reach Dr Naples FL 34104",
    "addr:housenumber":"2524",
    "addr:postcode":"34104",
    "addr:street":"River Reach Dr",
    "iso:country":"US",
    "sg:address":"2524 River Reach Dr",
    "sg:city":"Naples",
    "sg:classifiers":[
        {
            "category":"Professional",
            "subcategory":"Art Services",
            "type":"Services"
        }
    ],
    "sg:phone":"+1 239 649 0709",
    "sg:postcode":"34104",
    "sg:province":"FL",
    "sg:tags":[
        "artist"
    ],
    "wof:name":"Michele Kortbawi Artist",
    "wof:placetype":"venue"
},
  "geometry": {"coordinates":[-81.77183599999999,26.164547],"type":"Point"}
}