{
  "type": "Feature",
  "properties": {
    "addr:full":"5900 SW 100th Ter Miami FL 33156",
    "addr:housenumber":"5900",
    "addr:postcode":"33156",
    "addr:street":"Sw 100Th Ter",
    "iso:country":"US",
    "sg:address":"5900 SW 100th Ter",
    "sg:city":"Miami",
    "sg:classifiers":[
        {
            "category":"Cinema",
            "subcategory":"Movie Rental",
            "type":"Entertainment"
        }
    ],
    "sg:phone":"+1 305 661 2782",
    "sg:postcode":"33156",
    "sg:province":"FL",
    "sg:tags":[
        "picture",
        "exchange",
        "motion",
        "distributor",
        "film"
    ],
    "wof:name":"John Echevarria Productions, Inc.",
    "wof:placetype":"venue"
},
  "geometry": {"coordinates":[-80.288371,25.677849],"type":"Point"}
}