{
  "type": "Feature",
  "properties": {
    "iso:country":"US",
    "sg:address":"325 Holiday Acres Dr",
    "sg:city":"Orlando",
    "sg:classifiers":[
        {
            "category":"Real Estate",
            "subcategory":"Real Estate Operator",
            "type":"Services"
        }
    ],
    "sg:phone":"+1 407 568 8617",
    "sg:postcode":"32833",
    "sg:province":"FL",
    "sg:tags":[
        "mobile",
        "home",
        "park",
        "community"
    ],
    "wof:name":"Holiday Acres Mobile Home Park",
    "wof:placetype":"venue"
},
  "geometry": {"coordinates":[-81.119103,28.551594],"type":"Point"}
}