{
  "type": "Feature",
  "properties": {
    "addr:full":"5690 Owls Nest Rd Tallahassee FL 32309",
    "addr:housenumber":"5690",
    "addr:postcode":"32309",
    "addr:street":"Owls Nest Rd",
    "iso:country":"US",
    "sg:address":"5690 Owls Nest Rd",
    "sg:city":"Tallahassee",
    "sg:classifiers":[
        {
            "category":"Manufacturing",
            "subcategory":"Tools & Machinery",
            "type":"Manufacturing & Wholesale Goods"
        }
    ],
    "sg:phone":"+1 850 668 0521",
    "sg:postcode":"32309",
    "sg:province":"FL",
    "sg:tags":[
        "devices",
        "mfg"
    ],
    "wof:name":"Burton Sylvern",
    "wof:placetype":"venue"
},
  "geometry": {"coordinates":[-84.22223099999999,30.548379],"type":"Point"}
}