{
  "type": "Feature",
  "properties": {
    "iso:country":"US",
    "sg:address":"37 N Orange Ave Suite 740",
    "sg:city":"Orlando",
    "sg:classifiers":[
        {
            "category":"Professional",
            "subcategory":"Computer Services",
            "type":"Services"
        }
    ],
    "sg:phone":"+1 888 324 6115",
    "sg:postcode":"32801",
    "sg:province":"FL",
    "sg:tags":[
        "mobile",
        "mobile-apps",
        "mobile-technology"
    ],
    "sg:website":"http://www.echo-mobile.com",
    "wof:name":"echomobile",
    "wof:placetype":"venue"
},
  "geometry": {"coordinates":[-81.37898,28.543353],"type":"Point"}
}