{
  "type": "Feature",
  "properties": {
    "iso:country":"US",
    "sg:address":"9250 College Pkwy Ste 7",
    "sg:city":"Fort Myers",
    "sg:classifiers":[
        {
            "category":"Arena",
            "subcategory":"Sports Club",
            "type":"Entertainment"
        }
    ],
    "sg:phone":"+1 239 433 2299",
    "sg:postcode":"33919",
    "sg:province":"FL",
    "sg:tags":[
        "martial art"
    ],
    "wof:name":"United Martial Arts Center",
    "wof:placetype":"venue"
},
  "geometry": {"coordinates":[-81.90619700000001,26.556299],"type":"Point"}
}