{
  "type": "Feature",
  "properties": {
    "addr:full":"16784 Valencia Blvd Loxahatchee FL 33470",
    "addr:housenumber":"16784",
    "addr:postcode":"33470",
    "addr:street":"Valencia Blvd",
    "iso:country":"US",
    "sg:address":"16784 Valencia Blvd",
    "sg:city":"Loxahatchee",
    "sg:classifiers":[
        {
            "category":"Manufacturing",
            "subcategory":"Tools & Machinery",
            "type":"Manufacturing & Wholesale Goods"
        }
    ],
    "sg:phone":"+1 561 791 1902",
    "sg:postcode":"33470",
    "sg:province":"FL",
    "sg:tags":[
        "industry",
        "mfg"
    ],
    "wof:name":"Ameritech Parking & Access",
    "wof:placetype":"venue"
},
  "geometry": {"coordinates":[-80.307044,26.802333],"type":"Point"}
}