{
  "type": "Feature",
  "properties": {
    "iso:country":"US",
    "sg:address":"1800 NW 1st Ct",
    "sg:city":"Boca Raton",
    "sg:classifiers":[
        {
            "category":"Real Estate",
            "subcategory":"Real Estate Agent",
            "type":"Services"
        }
    ],
    "sg:phone":"+1 561 391 3400",
    "sg:postcode":"33432",
    "sg:province":"FL",
    "wof:name":"Kmc Management Co",
    "wof:placetype":"venue"
},
  "geometry": {"coordinates":[-80.086843,26.366245],"type":"Point"}
}