{
  "type": "Feature",
  "properties": {
    "addr:full":"1932 Drew St Clearwater FL 33765",
    "addr:housenumber":"1932",
    "addr:postcode":"33765",
    "addr:street":"Drew St",
    "iso:country":"US",
    "sg:address":"1932 Drew St",
    "sg:city":"Clearwater",
    "sg:classifiers":[
        {
            "category":"Professional",
            "subcategory":"Engineering",
            "type":"Services"
        }
    ],
    "sg:phone":"+1 727 447 7664",
    "sg:postcode":"33765",
    "sg:province":"FL",
    "sg:tags":[
        "engineer"
    ],
    "wof:name":"DEW Engineering",
    "wof:placetype":"venue"
},
  "geometry": {"coordinates":[-82.757316,27.96806],"type":"Point"}
}