{
  "type": "Feature",
  "properties": {
    "iso:country":"US",
    "sg:address":"6795 Miller Dr",
    "sg:city":"Miami",
    "sg:classifiers":[
        {
            "category":"Shopping",
            "subcategory":"Discount & Variety Stores",
            "type":"Retail Goods"
        }
    ],
    "sg:phone":"+1 305 661 4047",
    "sg:postcode":"33155",
    "sg:province":"FL",
    "sg:tags":[
        "merchandise",
        "general"
    ],
    "wof:name":"Milller Marathon",
    "wof:placetype":"venue"
},
  "geometry": {"coordinates":[-80.30256,25.718402],"type":"Point"}
}