{
  "type": "Feature",
  "properties": {
    "addr:full":"5710 Vanderipe Rd Sarasota FL 34241",
    "addr:housenumber":"5710",
    "addr:postcode":"34241",
    "addr:street":"Vanderipe Rd",
    "iso:country":"US",
    "sg:address":"5710 Vanderipe Rd",
    "sg:city":"Sarasota",
    "sg:classifiers":[
        {
            "category":"Wholesale",
            "subcategory":"Farm Supplies",
            "type":"Manufacturing & Wholesale Goods"
        }
    ],
    "sg:phone":"+1 941 924 1265",
    "sg:postcode":"34241",
    "sg:province":"FL",
    "sg:tags":[
        "raw",
        "product",
        "material"
    ],
    "wof:name":"Halls Horsey Things",
    "wof:placetype":"venue"
},
  "geometry": {"coordinates":[-82.332151,27.2686],"type":"Point"}
}