{
  "type": "Feature",
  "properties": {
    "iso:country":"US",
    "sg:address":"10745 Lucust St.  A2",
    "sg:city":"Palm Beach Gardens ",
    "sg:classifiers":[
        {
            "category":"Professional",
            "subcategory":"Computer Services",
            "type":"Services"
        }
    ],
    "sg:phone":"+1 561 632 6338",
    "sg:postcode":"33418",
    "sg:province":"FL",
    "sg:tags":[
        "travel-information",
        "travel-reviews",
        "vacation-destinations"
    ],
    "sg:website":"http://www.travolti.com",
    "wof:name":"Travolti",
    "wof:placetype":"venue"
},
  "geometry": {"coordinates":[-80.106927,26.834436],"type":"Point"}
}