{
  "type": "Feature",
  "properties": {
    "iso:country":"US",
    "sg:address":"6500 Cow Pen Rd Ste 104",
    "sg:city":"Hialeah",
    "sg:classifiers":[
        {
            "category":"Health Services",
            "subcategory":"Dentist",
            "type":"Services"
        }
    ],
    "sg:phone":"+1 786 507 1303",
    "sg:postcode":"33014",
    "sg:province":"FL",
    "sg:tags":[
        "pediatric"
    ],
    "wof:name":"Perfect A Smile",
    "wof:placetype":"venue"
},
  "geometry": {"coordinates":[-80.30656399999999,25.915183],"type":"Point"}
}