{
  "type": "Feature",
  "properties": {
    "addr:full":"800 71st St Miami Beach FL 33141",
    "addr:housenumber":"800",
    "addr:postcode":"33141",
    "addr:street":"71St St",
    "iso:country":"US",
    "sg:address":"800 71st St",
    "sg:city":"Miami Beach",
    "sg:classifiers":[
        {
            "category":"Wholesale",
            "subcategory":"Jewelry",
            "type":"Manufacturing & Wholesale Goods"
        }
    ],
    "sg:phone":"+1 305 868 1261",
    "sg:postcode":"33141",
    "sg:province":"FL",
    "sg:tags":[
        "distributor",
        "import",
        "gold"
    ],
    "wof:name":"Ivens Corporation",
    "wof:placetype":"venue"
},
  "geometry": {"coordinates":[-80.126623,25.855967],"type":"Point"}
}