{
  "type": "Feature",
  "properties": {
    "addr:full":"4717 NE 12th Ave Oakland Park FL 33334",
    "addr:housenumber":"4717",
    "addr:postcode":"33334",
    "addr:street":"Ne 12Th Ave",
    "iso:country":"US",
    "sg:address":"4717 NE 12th Ave",
    "sg:city":"Oakland Park",
    "sg:classifiers":[
        {
            "category":"Professional",
            "subcategory":"Computer Services",
            "type":"Services"
        }
    ],
    "sg:phone":"+1 954 351 9311",
    "sg:postcode":"33334",
    "sg:province":"FL",
    "sg:tags":[
        "scanning"
    ],
    "wof:name":"Tropical Graphics Inc",
    "wof:placetype":"venue"
},
  "geometry": {"coordinates":[-80.131265,26.186351],"type":"Point"}
}