{
  "type": "Feature",
  "properties": {
    "iso:country":"US",
    "sg:address":"4211 S Shade Ave",
    "sg:city":"Sarasota",
    "sg:classifiers":[
        {
            "category":"Shopping",
            "subcategory":"Shoes",
            "type":"Retail Goods"
        }
    ],
    "sg:phone":"+1 941 921 3696",
    "sg:postcode":"34231",
    "sg:province":"FL",
    "wof:name":"New Century Sports Inc",
    "wof:placetype":"venue"
},
  "geometry": {"coordinates":[-82.522301,27.293295],"type":"Point"}
}