{
  "type": "Feature",
  "properties": {
    "addr:full":"421 Blackburn Point Rd Osprey FL 34229",
    "addr:housenumber":"421",
    "addr:postcode":"34229",
    "addr:street":"Blackburn Point Rd",
    "iso:country":"US",
    "sg:address":"421 Blackburn Point Rd",
    "sg:city":"Osprey",
    "sg:classifiers":[
        {
            "category":"Farming",
            "subcategory":"Nursery",
            "type":"Manufacturing & Wholesale Goods"
        }
    ],
    "sg:phone":"+1 941 918 0207",
    "sg:postcode":"34229",
    "sg:province":"FL",
    "sg:tags":[
        "sod",
        "farmer"
    ],
    "wof:name":"Young Sod Inc",
    "wof:placetype":"venue"
},
  "geometry": {"coordinates":[-82.49019699999999,27.179713],"type":"Point"}
}