{
  "type": "Feature",
  "properties": {
    "iso:country":"US",
    "sg:address":"5743 SW 9th Ct",
    "sg:city":"Cape Coral",
    "sg:classifiers":[
        {
            "category":"Real Estate",
            "subcategory":"Real Estate Operator",
            "type":"Services"
        }
    ],
    "sg:phone":"+1 239 549 4727",
    "sg:postcode":"33914",
    "sg:province":"FL",
    "sg:tags":[
        "building",
        "nonresidential"
    ],
    "wof:name":"Property Referrals Co Inc",
    "wof:placetype":"venue"
},
  "geometry": {"coordinates":[-81.994264,26.544255],"type":"Point"}
}