{
  "type": "Feature",
  "properties": {
    "iso:country":"US",
    "sg:address":"541 S Orlando Ave",
    "sg:city":"Maitland",
    "sg:classifiers":[
        {
            "category":"Professional",
            "subcategory":"Accounting & Tax Preparation",
            "type":"Services"
        }
    ],
    "sg:phone":"+1 407 647 7100",
    "sg:postcode":"32751",
    "sg:province":"FL",
    "wof:name":"Century National Bank",
    "wof:placetype":"venue"
},
  "geometry": {"coordinates":[-81.36415100000001,28.622531],"type":"Point"}
}