{
  "type": "Feature",
  "properties": {
    "iso:country":"US",
    "sg:address":"2100 Trade Center Way",
    "sg:city":"Naples",
    "sg:classifiers":[
        {
            "category":"Wholesale",
            "subcategory":"Home Furnishings",
            "type":"Manufacturing & Wholesale Goods"
        }
    ],
    "sg:phone":"+1 239 596 0606",
    "sg:postcode":"34109",
    "sg:province":"FL",
    "sg:tags":[
        "tile"
    ],
    "wof:name":"Gallery Of Tile & Stone-Alpha",
    "wof:placetype":"venue"
},
  "geometry": {"coordinates":[-81.77722300000001,26.225111],"type":"Point"}
}