{
  "type": "Feature",
  "properties": {
    "addr:full":"5201 Marion County Rd Weirsdale FL 32195",
    "addr:housenumber":"5201",
    "addr:postcode":"32195",
    "addr:street":"Marion County Rd",
    "iso:country":"US",
    "sg:address":"5201 Marion County Rd",
    "sg:city":"Weirsdale",
    "sg:classifiers":[
        {
            "category":"Wholesale",
            "subcategory":"Durable Goods & Equipment",
            "type":"Manufacturing & Wholesale Goods"
        }
    ],
    "sg:phone":"+1 352 259 3607",
    "sg:postcode":"32195",
    "sg:province":"FL",
    "sg:tags":[
        "representative",
        "manufacturer"
    ],
    "wof:name":"Frank Liotine Wholesale",
    "wof:placetype":"venue"
},
  "geometry": {"coordinates":[-81.866981,28.952796],"type":"Point"}
}