{
  "type": "Feature",
  "properties": {
    "addr:full":"5028 Airport Rd Zephyrhills FL 33542",
    "addr:housenumber":"5028",
    "addr:postcode":"33542",
    "addr:street":"Airport Rd",
    "iso:country":"US",
    "sg:address":"5028 Airport Rd",
    "sg:city":"Zephyrhills",
    "sg:classifiers":[
        {
            "category":"Freight",
            "type":"Transportation"
        }
    ],
    "sg:phone":"+1 813 780 9000",
    "sg:postcode":"33542",
    "sg:province":"FL",
    "sg:tags":[
        "operator",
        "trucking"
    ],
    "wof:name":"Seminole Trnsp Specialist",
    "wof:placetype":"venue"
},
  "geometry": {"coordinates":[-82.167328,28.229684],"type":"Point"}
}