{
  "type": "Feature",
  "properties": {
    "iso:country":"US",
    "sg:address":"4655 SW 102nd Lane Rd",
    "sg:city":"Ocala",
    "sg:classifiers":[
        {
            "category":"Shopping",
            "subcategory":"Computers & Home Electronics",
            "type":"Retail Goods"
        }
    ],
    "sg:phone":"+1 352 854 6076",
    "sg:postcode":"34476",
    "sg:province":"FL",
    "sg:tags":[
        "design",
        "system",
        "network"
    ],
    "wof:name":"Residual Electronics",
    "wof:placetype":"venue"
},
  "geometry": {"coordinates":[-82.19873,29.073806],"type":"Point"}
}