{
  "type": "Feature",
  "properties": {
    "iso:country":"US",
    "sg:address":"1156 W 68th St",
    "sg:city":"Hialeah",
    "sg:classifiers":[
        {
            "category":"Retail",
            "subcategory":"Repair Shop",
            "type":"Services"
        }
    ],
    "sg:phone":"+1 305 357 1828",
    "sg:postcode":"33014",
    "sg:province":"FL",
    "sg:tags":[
        "lock",
        "key",
        "locksmith"
    ],
    "wof:name":"01 24 Hour A Day 24 Locksmith",
    "wof:placetype":"venue"
},
  "geometry": {"coordinates":[-80.306575,25.884047],"type":"Point"}
}