{
  "type": "Feature",
  "properties": {
    "addr:full":"2966 NW 60th St Fort Lauderdale FL 33309",
    "addr:housenumber":"2966",
    "addr:postcode":"33309",
    "addr:street":"Nw 60Th St",
    "iso:country":"US",
    "sg:address":"2966 NW 60th St",
    "sg:city":"Fort Lauderdale",
    "sg:classifiers":[
        {
            "category":"Wholesale",
            "subcategory":"Machinery & Supplies",
            "type":"Manufacturing & Wholesale Goods"
        }
    ],
    "sg:phone":"+1 954 972 2231",
    "sg:postcode":"33309",
    "sg:province":"FL",
    "sg:tags":[
        "aircraft",
        "avionics"
    ],
    "sg:website":"www.eagleaircraft.com",
    "wof:name":"Eagle Aircraft Svc",
    "wof:placetype":"venue"
},
  "geometry": {"coordinates":[-80.185689,26.200412],"type":"Point"}
}