{
  "type": "Feature",
  "properties": {
    "iso:country":"US",
    "sg:address":"4202 S Florida Ave",
    "sg:city":"Lakeland",
    "sg:classifiers":[
        {
            "category":"Health Services",
            "subcategory":"Doctor",
            "type":"Services"
        }
    ],
    "sg:phone":"+1 863 646 1421",
    "sg:postcode":"33813",
    "sg:province":"FL",
    "sg:tags":[
        "medical",
        "legal"
    ],
    "wof:name":"Peddy Robert B Jr Law Offices",
    "wof:placetype":"venue"
},
  "geometry": {"coordinates":[-81.95678100000001,27.985865],"type":"Point"}
}