{
  "type": "Feature",
  "properties": {
    "addr:full":"2200 Port Malabar Blvd NE Palm Bay FL 32905",
    "addr:housenumber":"2200",
    "addr:postcode":"32905",
    "addr:street":"Port Malabar Blvd Ne",
    "iso:country":"US",
    "sg:address":"2200 Port Malabar Blvd NE",
    "sg:city":"Palm Bay",
    "sg:classifiers":[
        {
            "category":"Wholesale",
            "subcategory":"Medical Equipment & Supplies",
            "type":"Manufacturing & Wholesale Goods"
        }
    ],
    "sg:phone":"+1 321 768 1400",
    "sg:postcode":"32905",
    "sg:province":"FL",
    "wof:name":"Carls Medical Supply",
    "wof:placetype":"venue"
},
  "geometry": {"coordinates":[-80.58640200000001,28.018176],"type":"Point"}
}