{
  "type": "Feature",
  "properties": {
    "addr:full":"6320 103rd St Jacksonville FL 32210",
    "addr:housenumber":"6320",
    "addr:postcode":"32210",
    "addr:street":"103Rd St",
    "iso:country":"US",
    "sg:address":"6320 103rd St",
    "sg:city":"Jacksonville",
    "sg:classifiers":[
        {
            "category":"Shopping",
            "subcategory":"Pharmacy",
            "type":"Retail Goods"
        }
    ],
    "sg:phone":"+1 904 772 8884",
    "sg:postcode":"32210",
    "sg:province":"FL",
    "wof:name":"Eckerd",
    "wof:placetype":"venue"
},
  "geometry": {"coordinates":[-81.74686199999999,30.24833],"type":"Point"}
}