{
  "type": "Feature",
  "properties": {
    "iso:country":"US",
    "sg:address":"712 E Alsobrook St",
    "sg:city":"Plant City",
    "sg:classifiers":[
        {
            "category":"Retail",
            "subcategory":"Laundry & Dry Cleaning",
            "type":"Services"
        }
    ],
    "sg:phone":"+1 813 764 0447",
    "sg:postcode":"33563",
    "sg:province":"FL",
    "sg:tags":[
        "cleaners",
        "rug",
        "carpet"
    ],
    "wof:name":"Dry-Max Carpet Cleaning",
    "wof:placetype":"venue"
},
  "geometry": {"coordinates":[-82.11789400000001,28.007479],"type":"Point"}
}