{
  "type": "Feature",
  "properties": {
    "iso:country":"US",
    "sg:address":"2102 Edgewater Dr",
    "sg:city":"Orlando",
    "sg:classifiers":[
        {
            "category":"Personal",
            "subcategory":"Beauty Salon",
            "type":"Services"
        },
        {
            "category":"Personal",
            "subcategory":"Barber",
            "type":"Services"
        }
    ],
    "sg:phone":"+1 407 481 8134",
    "sg:postcode":"32804",
    "sg:province":"FL",
    "sg:tags":[
        "hair",
        "accessory",
        "stylist",
        "supply"
    ],
    "sg:website":"http://www.haircuttery.com/",
    "wof:name":"Hair Cuttery",
    "wof:placetype":"venue"
},
  "geometry": {"coordinates":[-81.38942,28.570415],"type":"Point"}
}