{
  "type": "Feature",
  "properties": {
    "addr:full":"801 SE Central Pkwy Stuart FL 34994",
    "addr:housenumber":"801",
    "addr:postcode":"34994",
    "addr:street":"Se Central Pkwy",
    "iso:country":"US",
    "sg:address":"801 SE Central Pkwy",
    "sg:city":"Stuart",
    "sg:classifiers":[
        {
            "category":"Real Estate",
            "subcategory":"Real Estate Operator",
            "type":"Services"
        }
    ],
    "sg:phone":"+1 772 463 9200",
    "sg:postcode":"34994",
    "sg:province":"FL",
    "sg:tags":[
        "condominium"
    ],
    "wof:name":"Towne Park North Condominium",
    "wof:placetype":"venue"
},
  "geometry": {"coordinates":[-80.24603,27.180613],"type":"Point"}
}