{
  "type": "Feature",
  "properties": {
    "addr:full":"1930 SW 64th Ave Miami FL 33155",
    "addr:housenumber":"1930",
    "addr:postcode":"33155",
    "addr:street":"Sw 64Th Ave",
    "iso:country":"US",
    "sg:address":"1930 SW 64th Ave",
    "sg:city":"Miami",
    "sg:classifiers":[
        {
            "category":"Building & Trades",
            "subcategory":"Landscaping Services",
            "type":"Services"
        }
    ],
    "sg:phone":"+1 305 266 7221",
    "sg:postcode":"33155",
    "sg:province":"FL",
    "wof:name":"R&T Landscaping",
    "wof:placetype":"venue"
},
  "geometry": {"coordinates":[-80.299649,25.752136],"type":"Point"}
}