{
  "type": "Feature",
  "properties": {
    "addr:full":"8634 Hammond Forest Dr Jacksonville FL 32221",
    "addr:housenumber":"8634",
    "addr:postcode":"32221",
    "addr:street":"Hammond Forest Dr",
    "iso:country":"US",
    "sg:address":"8634 Hammond Forest Dr",
    "sg:city":"Jacksonville",
    "sg:classifiers":[
        {
            "category":"Building & Trades",
            "subcategory":"Plumbing",
            "type":"Services"
        }
    ],
    "sg:phone":"+1 904 786 5314",
    "sg:postcode":"32221",
    "sg:province":"FL",
    "sg:tags":[
        "contractor"
    ],
    "wof:name":"Clear Wtr Irrigation & Ldscpg",
    "wof:placetype":"venue"
},
  "geometry": {"coordinates":[-81.794439,30.296123],"type":"Point"}
}