{
  "type": "Feature",
  "properties": {
    "iso:country":"US",
    "sg:address":"2204 Lake Shore Blvd",
    "sg:city":"Jacksonville",
    "sg:classifiers":[
        {
            "category":"Building & Trades",
            "subcategory":"Construction",
            "type":"Services"
        }
    ],
    "sg:phone":"+1 904 389 6002",
    "sg:postcode":"32210",
    "sg:province":"FL",
    "sg:tags":[
        "investment",
        "real estate"
    ],
    "wof:name":"Jones Joseph D",
    "wof:placetype":"venue"
},
  "geometry": {"coordinates":[-81.73807100000001,30.277959],"type":"Point"}
}