{
  "type": "Feature",
  "properties": {
    "iso:country":"US",
    "sg:address":"272 W Warren Ave",
    "sg:city":"Longwood",
    "sg:classifiers":[
        {
            "category":"Professional",
            "subcategory":"Lawyer & Legal Services",
            "type":"Services"
        }
    ],
    "sg:phone":"+1 321 274 0170",
    "sg:postcode":"32750",
    "sg:province":"FL",
    "wof:name":"Bordulis Jeffrey J PA",
    "wof:placetype":"venue"
},
  "geometry": {"coordinates":[-81.34989400000001,28.699993],"type":"Point"}
}