{
  "type": "Feature",
  "properties": {
    "iso:country":"US",
    "sg:address":"906 Diplomat Pkwy",
    "sg:city":"Hallandale",
    "sg:classifiers":[
        {
            "category":"Building & Trades",
            "subcategory":"Construction",
            "type":"Services"
        }
    ],
    "sg:phone":"+1 954 455 1000",
    "sg:postcode":"33009",
    "sg:province":"FL",
    "sg:tags":[
        "nonresidential"
    ],
    "wof:name":"Durzo Demarco Development Co",
    "wof:placetype":"venue"
},
  "geometry": {"coordinates":[-80.130388,25.997052],"type":"Point"}
}