{
  "type": "Feature",
  "properties": {
    "addr:full":"16221 SW 88th St Miami FL 33196",
    "addr:housenumber":"16221",
    "addr:postcode":"33196",
    "addr:street":"Sw 88Th St",
    "iso:country":"US",
    "sg:address":"16221 SW 88th St",
    "sg:city":"Miami",
    "sg:classifiers":[
        {
            "category":"Insurance",
            "subcategory":"Insurance Agent",
            "type":"Services"
        },
        {
            "category":"Insurance",
            "subcategory":"Hazard Insurance",
            "type":"Services"
        },
        {
            "category":"Insurance",
            "subcategory":"Title Insurance",
            "type":"Services"
        },
        {
            "category":"Insurance",
            "subcategory":"Life Insurance",
            "type":"Services"
        }
    ],
    "sg:phone":"+1 305 387 1977",
    "sg:postcode":"33196",
    "sg:province":"FL",
    "sg:tags":[
        "business",
        "auto",
        "commercial",
        "homeowner",
        "motorcycle",
        "renter"
    ],
    "wof:name":"Allstate Insurance Company - Alberto Espinosa",
    "wof:placetype":"venue"
},
  "geometry": {"coordinates":[-80.454432,25.684187],"type":"Point"}
}