{
  "type": "Feature",
  "properties": {
    "addr:full":"7270 NW 12th St Miami FL 33126",
    "addr:housenumber":"7270",
    "addr:postcode":"33126",
    "addr:street":"Nw 12Th St",
    "iso:country":"US",
    "sg:address":"7270 NW 12th St",
    "sg:city":"Miami",
    "sg:classifiers":[
        {
            "category":"Wholesale",
            "subcategory":"Plants",
            "type":"Manufacturing & Wholesale Goods"
        },
        {
            "category":"Professional",
            "subcategory":"Business Services",
            "type":"Services"
        }
    ],
    "sg:phone":"+1 305 717 3477",
    "sg:postcode":"33126",
    "sg:province":"FL",
    "sg:tags":[
        "importer",
        "florists-wholesale"
    ],
    "sg:website":"http://www.splendidflowers.com",
    "wof:name":"Splendid Flowers/FAX",
    "wof:placetype":"venue"
},
  "geometry": {"coordinates":[-80.31359,25.782525],"type":"Point"}
}