{
  "type": "Feature",
  "properties": {
    "addr:full":"2121 SW 3rd Ave Fl 1 Miami FL 33129",
    "addr:housenumber":"2121;1",
    "addr:postcode":"33129",
    "addr:street":"Sw 3Rd Ave Fl",
    "iso:country":"US",
    "sg:address":"2121 SW 3rd Ave Fl 1",
    "sg:city":"Miami",
    "sg:classifiers":[
        {
            "category":"Professional",
            "subcategory":"Lawyer & Legal Services",
            "type":"Services"
        }
    ],
    "sg:phone":"+1 305 285 5550",
    "sg:postcode":"33129",
    "sg:province":"FL",
    "wof:name":"Evans & Associates",
    "wof:placetype":"venue"
},
  "geometry": {"coordinates":[-80.203962,25.757972],"type":"Point"}
}