{
  "type": "Feature",
  "properties": {
    "addr:full":"124 Hidden Court Rd Hollywood FL 33023",
    "addr:housenumber":"124",
    "addr:postcode":"33023",
    "addr:street":"Hidden Court Rd",
    "iso:country":"US",
    "sg:address":"124 Hidden Court Rd",
    "sg:city":"Hollywood",
    "sg:classifiers":[
        {
            "category":"Wholesale",
            "subcategory":"Computers",
            "type":"Manufacturing & Wholesale Goods"
        }
    ],
    "sg:phone":"+1 336 268 1419",
    "sg:postcode":"33023",
    "sg:province":"FL",
    "sg:tags":[
        "equipment"
    ],
    "sg:website":"http://www.laptopdiscounts.biz",
    "wof:name":"Laptop Discounts",
    "wof:placetype":"venue"
},
  "geometry": {"coordinates":[-80.204262,26.004219],"type":"Point"}
}