{
  "type": "Feature",
  "properties": {
    "iso:country":"US",
    "sg:address":"3825 SW 41st St",
    "sg:city":"Hollywood",
    "sg:classifiers":[
        {
            "category":"Sports & Exercise",
            "subcategory":"Gym",
            "type":"Entertainment"
        }
    ],
    "sg:phone":"+1 954 981 3033",
    "sg:postcode":"33023",
    "sg:province":"FL",
    "sg:tags":[
        "club",
        "gymnasium",
        "athletic",
        "membership",
        "health",
        "studio"
    ],
    "wof:name":"Samson's Ironhouse Co-Ed Gym",
    "wof:placetype":"venue"
},
  "geometry": {"coordinates":[-80.17999,25.973727],"type":"Point"}
}