{
  "type": "Feature",
  "properties": {
    "addr:full":"1621 N Ocean Blvd Pompano Beach FL 33062",
    "addr:housenumber":"1621",
    "addr:postcode":"33062",
    "addr:street":"N Ocean Blvd",
    "iso:country":"US",
    "sg:address":"1621 N Ocean Blvd",
    "sg:city":"Pompano Beach",
    "sg:classifiers":[
        {
            "category":"Social Services",
            "subcategory":"Adult Care",
            "type":"Services"
        }
    ],
    "sg:phone":"+1 954 942 9810",
    "sg:postcode":"33062",
    "sg:province":"FL",
    "sg:tags":[
        "home",
        "retirement"
    ],
    "wof:name":"Nova Vizcaya",
    "wof:placetype":"venue"
},
  "geometry": {"coordinates":[-80.086572,26.252914],"type":"Point"}
}