{
  "type": "Feature",
  "properties": {
    "iso:country":"US",
    "sg:address":"11226 Vera Dr",
    "sg:city":"Jacksonville",
    "sg:classifiers":[
        {
            "category":"Building & Trades",
            "subcategory":"Construction",
            "type":"Services"
        }
    ],
    "sg:phone":"+1 904 879 7018",
    "sg:postcode":"32218",
    "sg:province":"FL",
    "sg:tags":[
        "tile",
        "dealer"
    ],
    "wof:name":"D W Tile Inc",
    "wof:placetype":"venue"
},
  "geometry": {"coordinates":[-81.631585,30.442911],"type":"Point"}
}