{
  "type": "Feature",
  "properties": {
    "iso:country":"US",
    "sg:address":"26133 US Hwy 19",
    "sg:city":"Clearwater",
    "sg:classifiers":[
        {
            "category":"Professional",
            "subcategory":"Employment Agencies",
            "type":"Services"
        }
    ],
    "sg:phone":"+1 727 726 3766",
    "sg:postcode":"33763",
    "sg:province":"FL",
    "sg:tags":[
        "opportunity"
    ],
    "sg:website":"www.marsar.com",
    "wof:name":"Marsar & Co Inc",
    "wof:placetype":"venue"
},
  "geometry": {"coordinates":[-82.73128699999999,28.009355],"type":"Point"}
}