{
  "type": "Feature",
  "properties": {
    "addr:full":"7608 Hwy 77 Southport FL 32409",
    "addr:housenumber":"7608",
    "addr:postcode":"32409",
    "addr:street":"Hwy 77",
    "iso:country":"US",
    "sg:address":"7608 Hwy 77",
    "sg:city":"Southport",
    "sg:classifiers":[
        {
            "category":"Restaurant",
            "type":"Food & Drink"
        }
    ],
    "sg:phone":"+1 850 265 5929",
    "sg:postcode":"32409",
    "sg:province":"FL",
    "wof:name":"Hilda's Oyster Bar",
    "wof:placetype":"venue"
},
  "geometry": {"coordinates":[-85.639872,30.288329],"type":"Point"}
}