{
  "type": "Feature",
  "properties": {
    "iso:country":"US",
    "sg:address":"3300 Bobbi Ln",
    "sg:city":"Titusville",
    "sg:classifiers":[
        {
            "category":"Building & Trades",
            "subcategory":"Construction",
            "type":"Services"
        }
    ],
    "sg:phone":"+1 321 267 4032",
    "sg:postcode":"32780",
    "sg:province":"FL",
    "sg:tags":[
        "utility",
        "contractor"
    ],
    "wof:name":"Driveways Inc",
    "wof:placetype":"venue"
},
  "geometry": {"coordinates":[-80.848277,28.579272],"type":"Point"}
}