{
  "type": "Feature",
  "properties": {
    "iso:country":"US",
    "sg:address":"3804 Garcon Point Rd",
    "sg:city":"Milton",
    "sg:classifiers":[
        {
            "category":"Local Transit",
            "type":"Transportation"
        }
    ],
    "sg:phone":"+1 850 626 7400",
    "sg:postcode":"32583",
    "sg:province":"FL",
    "sg:tags":[
        "bus",
        "line"
    ],
    "wof:name":"Greyhound Bus Lines",
    "wof:placetype":"venue"
},
  "geometry": {"coordinates":[-87.031342,30.57187],"type":"Point"}
}