{
  "type": "Feature",
  "properties": {
    "addr:full":"1920 Palomino Rd Melbourne FL 32934",
    "addr:housenumber":"1920",
    "addr:postcode":"32934",
    "addr:street":"Palomino Rd",
    "iso:country":"US",
    "sg:address":"1920 Palomino Rd",
    "sg:city":"Melbourne",
    "sg:classifiers":[
        {
            "category":"Building & Trades",
            "subcategory":"Construction",
            "type":"Services"
        }
    ],
    "sg:phone":"+1 321 254 4955",
    "sg:postcode":"32934",
    "sg:province":"FL",
    "sg:tags":[
        "excavation",
        "contractor"
    ],
    "wof:name":"Glover Excavating",
    "wof:placetype":"venue"
},
  "geometry": {"coordinates":[-80.676958,28.139856],"type":"Point"}
}