{
  "type": "Feature",
  "properties": {
    "addr:full":"4980 W Irlo Bronson Memorial Hwy Kissimmee FL 34746",
    "addr:housenumber":"4980",
    "addr:postcode":"34746",
    "addr:street":"W Irlo Bronson Memorial Hwy",
    "iso:country":"US",
    "sg:address":"4980 W Irlo Bronson Memorial Hwy",
    "sg:city":"Kissimmee",
    "sg:classifiers":[
        {
            "category":"Restaurant",
            "type":"Food & Drink"
        }
    ],
    "sg:phone":"+1 407 397 0009",
    "sg:postcode":"34746",
    "sg:province":"FL",
    "sg:tags":[
        "eating"
    ],
    "wof:name":"New China Buffet",
    "wof:placetype":"venue"
},
  "geometry": {"coordinates":[-81.480403,28.332719],"type":"Point"}
}