{
  "type": "Feature",
  "properties": {
    "iso:country":"US",
    "sg:address":"7278 NW 58th St",
    "sg:city":"Miami",
    "sg:classifiers":[
        {
            "category":"Utilities",
            "subcategory":"Mobile Phone",
            "type":"Services"
        }
    ],
    "sg:phone":"+1 305 470 2025",
    "sg:postcode":"33166",
    "sg:province":"FL",
    "sg:tags":[
        "telephone",
        "cellular"
    ],
    "sg:website":"http://www.cingular.com",
    "wof:name":"AT&T Wireless",
    "wof:placetype":"venue"
},
  "geometry": {"coordinates":[-80.316486,25.8262],"type":"Point"}
}