{
  "type": "Feature",
  "properties": {
    "iso:country":"US",
    "sg:address":"325 US Hwy 90",
    "sg:city":"Bonifay",
    "sg:classifiers":[
        {
            "category":"Government",
            "subcategory":"Post Office",
            "type":"Public Place"
        }
    ],
    "sg:phone":"+1 850 547 2542",
    "sg:postcode":"32425",
    "sg:province":"FL",
    "sg:tags":[
        "postal",
        "us"
    ],
    "wof:name":"US Post Office",
    "wof:placetype":"venue"
},
  "geometry": {"coordinates":[-85.684005,30.78828],"type":"Point"}
}