{
  "type": "Feature",
  "properties": {
    "iso:country":"US",
    "sg:address":"3431 NW 48th St",
    "sg:city":"Miami",
    "sg:classifiers":[
        {
            "category":"Building & Trades",
            "subcategory":"Locksmith",
            "type":"Services"
        }
    ],
    "sg:phone":"+1 305 638 5996",
    "sg:postcode":"33142",
    "sg:province":"FL",
    "sg:tags":[
        "locksmiths-commercial",
        "industrial",
        "key",
        "lock"
    ],
    "wof:name":"Security Specialist Enterprise A-1",
    "wof:placetype":"venue"
},
  "geometry": {"coordinates":[-80.25203399999999,25.817528],"type":"Point"}
}