{
  "type": "Feature",
  "properties": {
    "addr:full":"2367 Coral Way Coral Gables FL 33145",
    "addr:housenumber":"2367",
    "addr:postcode":"33145",
    "addr:street":"Coral Way",
    "iso:country":"US",
    "sg:address":"2367 Coral Way",
    "sg:city":"Coral Gables",
    "sg:classifiers":[
        {
            "category":"Building & Trades",
            "subcategory":"Locksmith",
            "type":"Services"
        }
    ],
    "sg:phone":"+1 786 228 5473",
    "sg:postcode":"33145",
    "sg:province":"FL",
    "sg:tags":[
        "key"
    ],
    "wof:name":"Always Available 24 Hour Emergency Locksmith In Coral Gables",
    "wof:placetype":"venue"
},
  "geometry": {"coordinates":[-80.23326,25.75045],"type":"Point"}
}