{
  "type": "Feature",
  "properties": {
    "iso:country":"US",
    "sg:address":"16759 62nd Rd N",
    "sg:city":"Loxahatchee",
    "sg:classifiers":[
        {
            "category":"Freight",
            "type":"Transportation"
        }
    ],
    "sg:phone":"+1 561 792 2001",
    "sg:postcode":"33470",
    "sg:province":"FL",
    "sg:tags":[
        "operator",
        "local",
        "trucking"
    ],
    "wof:name":"Thompson Trucking & Brokerage",
    "wof:placetype":"venue"
},
  "geometry": {"coordinates":[-80.306848,26.768581],"type":"Point"}
}