{
  "type": "Feature",
  "properties": {
    "iso:country":"US",
    "sg:address":"6261 NW 79th Way",
    "sg:city":"Parkland",
    "sg:classifiers":[
        {
            "category":"Social Services",
            "type":"Services"
        }
    ],
    "sg:phone":"+1 954 344 0882",
    "sg:postcode":"33067",
    "sg:province":"FL",
    "sg:tags":[
        "counselor",
        "health",
        "mental"
    ],
    "wof:name":"James Dinkmeyer",
    "wof:placetype":"venue"
},
  "geometry": {"coordinates":[-80.23150200000001,26.303964],"type":"Point"}
}