{
  "type": "Feature",
  "properties": {
    "addr:full":"1200 Deltona Blvd Ste 26 Deltona FL 32725",
    "addr:housenumber":"1200",
    "addr:postcode":"32725",
    "addr:street":"Deltona Blvd Ste 26",
    "iso:country":"US",
    "sg:address":"1200 Deltona Blvd Ste 26",
    "sg:city":"Deltona",
    "sg:classifiers":[
        {
            "category":"Shopping",
            "subcategory":"Department Store",
            "type":"Retail Goods"
        },
        {
            "category":"Home & Garden",
            "subcategory":"Carpets & Floor Coverings",
            "type":"Retail Goods"
        }
    ],
    "sg:phone":"+1 386 860 9610",
    "sg:postcode":"32725",
    "sg:province":"FL",
    "sg:tags":[
        "mattress"
    ],
    "wof:name":"Furniture City Outlet",
    "wof:placetype":"venue"
},
  "geometry": {"coordinates":[-81.27159899999999,28.8957],"type":"Point"}
}