{
  "type": "Feature",
  "properties": {
    "iso:country":"US",
    "sg:address":"5424 Conway Pointe Ct",
    "sg:city":"Orlando",
    "sg:classifiers":[
        {
            "category":"Professional",
            "subcategory":"Employment Agencies",
            "type":"Services"
        }
    ],
    "sg:phone":"+1 407 381 0311",
    "sg:postcode":"32812",
    "sg:province":"FL",
    "sg:tags":[
        "help",
        "contractor"
    ],
    "wof:name":"United Solutions",
    "wof:placetype":"venue"
},
  "geometry": {"coordinates":[-81.315538,28.515638],"type":"Point"}
}