{
  "type": "Feature",
  "properties": {
    "addr:full":"1901 Collins Ave Shore Club Miami Beach FL 33139",
    "addr:housenumber":"1901",
    "addr:postcode":"33139",
    "addr:street":"Collins Ave Shore Club",
    "iso:country":"US",
    "sg:address":"1901 Collins Ave Shore Club",
    "sg:city":"Miami Beach",
    "sg:classifiers":[
        {
            "category":"Restaurant",
            "type":"Food & Drink"
        }
    ],
    "sg:phone":"+1 305 695 3244",
    "sg:postcode":"33139",
    "sg:province":"FL",
    "sg:tags":[
        "italian"
    ],
    "sg:website":"www.agorestaurant.com",
    "wof:name":"Ago Ristorante",
    "wof:placetype":"venue"
},
  "geometry": {"coordinates":[-80.129271,25.795158],"type":"Point"}
}