{
  "type": "Feature",
  "properties": {
    "iso:country":"US",
    "sg:address":"4712 Bartlett Ct",
    "sg:city":"Elkton",
    "sg:classifiers":[
        {
            "category":"Manufacturing",
            "subcategory":"Buildings",
            "type":"Manufacturing & Wholesale Goods"
        },
        {
            "category":"Building & Trades",
            "subcategory":"Construction",
            "type":"Services"
        }
    ],
    "sg:phone":"+1 904 819 1775",
    "sg:postcode":"32033",
    "sg:province":"FL",
    "sg:tags":[
        "industrial",
        "builder",
        "contractor",
        "contractors-commercial",
        "home",
        "road"
    ],
    "wof:name":"Matzen Construction Inc",
    "wof:placetype":"venue"
},
  "geometry": {"coordinates":[-81.377956,29.808182],"type":"Point"}
}