{
  "type": "Feature",
  "properties": {
    "addr:full":"2375 NE Ocean Blvd Stuart FL 34996",
    "addr:housenumber":"2375",
    "addr:postcode":"34996",
    "addr:street":"Ne Ocean Blvd",
    "iso:country":"US",
    "sg:address":"2375 NE Ocean Blvd",
    "sg:city":"Stuart",
    "sg:classifiers":[
        {
            "category":"Real Estate",
            "subcategory":"Real Estate Agent",
            "type":"Services"
        }
    ],
    "sg:phone":"+1 772 225 3878",
    "sg:postcode":"34996",
    "sg:province":"FL",
    "wof:name":"Taronto Realty",
    "wof:placetype":"venue"
},
  "geometry": {"coordinates":[-80.187285,27.236141],"type":"Point"}
}