{
  "type": "Feature",
  "properties": {
    "addr:full":"8473 Bird Rd Miami FL 33155",
    "addr:housenumber":"8473",
    "addr:postcode":"33155",
    "addr:street":"Bird Rd",
    "iso:country":"US",
    "sg:address":"8473 Bird Rd",
    "sg:city":"Miami",
    "sg:classifiers":[
        {
            "category":"Shopping",
            "subcategory":"Jewelry",
            "type":"Retail Goods"
        }
    ],
    "sg:phone":"+1 305 207 3544",
    "sg:postcode":"33155",
    "sg:province":"FL",
    "wof:name":"Jenny's Jewelry Corp",
    "wof:placetype":"venue"
},
  "geometry": {"coordinates":[-80.332396,25.733389],"type":"Point"}
}