{
  "type": "Feature",
  "properties": {
    "addr:full":"2414 NW 27th Ave Miami FL 33142",
    "addr:housenumber":"2414",
    "addr:postcode":"33142",
    "addr:street":"Nw 27Th Ave",
    "iso:country":"US",
    "sg:address":"2414 NW 27th Ave",
    "sg:city":"Miami",
    "sg:classifiers":[
        {
            "category":"Utilities",
            "subcategory":"Mobile Phone",
            "type":"Services"
        },
        {
            "category":"Utilities",
            "subcategory":"Telephone",
            "type":"Services"
        },
        {
            "category":"Shopping",
            "subcategory":"Mobile Phones",
            "type":"Retail Goods"
        },
        {
            "category":"Manufacturing",
            "subcategory":"Electronics",
            "type":"Manufacturing & Wholesale Goods"
        },
        {
            "category":"Communications",
            "type":"Services"
        }
    ],
    "sg:phone":"+1 305 637 7602",
    "sg:postcode":"33142",
    "sg:province":"FL",
    "sg:tags":[
        "equipment",
        "telecommunications-equipment",
        "system",
        "cellular",
        "supply"
    ],
    "wof:name":"Sunny Wireless",
    "wof:placetype":"venue"
},
  "geometry": {"coordinates":[-80.24012500000001,25.79904],"type":"Point"}
}