{
  "type": "Feature",
  "properties": {
    "addr:full":"4215 114th Ter N Clearwater FL 33762",
    "addr:housenumber":"4215",
    "addr:postcode":"33762",
    "addr:street":"114Th Ter N",
    "iso:country":"US",
    "sg:address":"4215 114th Ter N",
    "sg:city":"Clearwater",
    "sg:classifiers":[
        {
            "category":"Manufacturing",
            "subcategory":"Printing",
            "type":"Manufacturing & Wholesale Goods"
        }
    ],
    "sg:phone":"+1 727 572 8180",
    "sg:postcode":"33762",
    "sg:province":"FL",
    "sg:tags":[
        "printer"
    ],
    "wof:name":"Ameri Print Ink",
    "wof:placetype":"venue"
},
  "geometry": {"coordinates":[-82.691737,27.875748],"type":"Point"}
}