{
  "type": "Feature",
  "properties": {
    "iso:country":"US",
    "sg:address":"1640 W Granada Blvd",
    "sg:city":"Ormond Beach",
    "sg:classifiers":[
        {
            "category":"Retail",
            "subcategory":"Laundry & Dry Cleaning",
            "type":"Services"
        }
    ],
    "sg:phone":"+1 386 677 6572",
    "sg:postcode":"32174",
    "sg:province":"FL",
    "sg:tags":[
        "drycleaning",
        "plant"
    ],
    "wof:name":"Ne Cleaners",
    "wof:placetype":"venue"
},
  "geometry": {"coordinates":[-81.118289,29.256257],"type":"Point"}
}