{
  "type": "Feature",
  "properties": {
    "addr:full":"1975 Palm Beach Trace Dr West Palm Beach FL 33411",
    "addr:housenumber":"1975",
    "addr:postcode":"33411",
    "addr:street":"Palm Beach Trace Dr",
    "iso:country":"US",
    "sg:address":"1975 Palm Beach Trace Dr",
    "sg:city":"West Palm Beach",
    "sg:classifiers":[
        {
            "category":"Professional",
            "type":"Services"
        }
    ],
    "sg:phone":"+1 561 784 4003",
    "sg:postcode":"33411",
    "sg:province":"FL",
    "sg:tags":[
        "establishment"
    ],
    "wof:name":"Emulex",
    "wof:placetype":"venue"
},
  "geometry": {"coordinates":[-80.226434,26.712882],"type":"Point"}
}