{
  "type": "Feature",
  "properties": {
    "addr:full":"227 N Magnolia Ave Orlando FL 32801",
    "addr:housenumber":"227",
    "addr:postcode":"32801",
    "addr:street":"N Magnolia Ave",
    "iso:country":"US",
    "sg:address":"227 N Magnolia Ave",
    "sg:city":"Orlando",
    "sg:classifiers":[
        {
            "category":"Real Estate",
            "subcategory":"Real Estate Agent",
            "type":"Services"
        }
    ],
    "sg:phone":"+1 407 447 0651",
    "sg:postcode":"32801",
    "sg:province":"FL",
    "wof:name":"Apex International Realty",
    "wof:placetype":"venue"
},
  "geometry": {"coordinates":[-81.377438,28.545398],"type":"Point"}
}