{
  "type": "Feature",
  "properties": {
    "addr:full":"6725 N Armenia Ave Tampa FL 33604",
    "addr:housenumber":"6725",
    "addr:postcode":"33604",
    "addr:street":"N Armenia Ave",
    "iso:country":"US",
    "sg:address":"6725 N Armenia Ave",
    "sg:city":"Tampa",
    "sg:classifiers":[
        {
            "category":"Restaurant",
            "type":"Food & Drink"
        }
    ],
    "sg:phone":"+1 813 935 1638",
    "sg:postcode":"33604",
    "sg:province":"FL",
    "sg:tags":[
        "eating"
    ],
    "wof:name":"Sandra's Taste Of Tampa",
    "wof:placetype":"venue"
},
  "geometry": {"coordinates":[-82.484309,28.00801],"type":"Point"}
}