{
  "type": "Feature",
  "properties": {
    "iso:country":"US",
    "sg:address":"5828 Pinetree Rd",
    "sg:city":"Panama City",
    "sg:classifiers":[
        {
            "category":"Organizations",
            "subcategory":"Religious Organization",
            "type":"Services"
        }
    ],
    "sg:phone":"+1 850 769 0953",
    "sg:postcode":"32404",
    "sg:province":"FL",
    "wof:name":"Homer Hutto Ministries",
    "wof:placetype":"venue"
},
  "geometry": {"coordinates":[-85.54625,30.252813],"type":"Point"}
}