{
  "type": "Feature",
  "properties": {
    "iso:country":"US",
    "sg:address":"1508 University Blvd N",
    "sg:city":"Jacksonville",
    "sg:classifiers":[
        {
            "category":"Retail",
            "subcategory":"Auto Repair",
            "type":"Services"
        }
    ],
    "sg:phone":"+1 904 743 2055",
    "sg:postcode":"32211",
    "sg:province":"FL",
    "sg:tags":[
        "repairing",
        "automobile"
    ],
    "wof:name":"G T Auto Repair & Corp",
    "wof:placetype":"venue"
},
  "geometry": {"coordinates":[-81.602671,30.33578],"type":"Point"}
}