{
  "type": "Feature",
  "properties": {
    "addr:full":"11030 SW 42nd Ter Miami FL 33165",
    "addr:housenumber":"11030",
    "addr:postcode":"33165",
    "addr:street":"Sw 42Nd Ter",
    "iso:country":"US",
    "sg:address":"11030 SW 42nd Ter",
    "sg:city":"Miami",
    "sg:classifiers":[
        {
            "category":"Building & Trades",
            "subcategory":"Electrical",
            "type":"Services"
        }
    ],
    "sg:phone":"+1 305 552 0016",
    "sg:postcode":"33165",
    "sg:province":"FL",
    "sg:tags":[
        "electrical"
    ],
    "wof:name":"Tonys Electrical Contracting",
    "wof:placetype":"venue"
},
  "geometry": {"coordinates":[-80.373594,25.728532],"type":"Point"}
}