{
  "type": "Feature",
  "properties": {
    "iso:country":"US",
    "sg:address":"311 W Brevard St",
    "sg:city":"Tallahassee",
    "sg:classifiers":[
        {
            "category":"Building & Trades",
            "subcategory":"Equipment Rental",
            "type":"Services"
        }
    ],
    "sg:phone":"+1 850 224 7673",
    "sg:postcode":"32301",
    "sg:province":"FL",
    "sg:tags":[
        "party",
        "supply"
    ],
    "wof:name":"Party Center",
    "wof:placetype":"venue"
},
  "geometry": {"coordinates":[-84.28552999999999,30.449006],"type":"Point"}
}