{
  "type": "Feature",
  "properties": {
    "addr:full":"1018 W Brandon Blvd Brandon FL 33511",
    "addr:housenumber":"1018",
    "addr:postcode":"33511",
    "addr:street":"W Brandon Blvd",
    "iso:country":"US",
    "sg:address":"1018 W Brandon Blvd",
    "sg:city":"Brandon",
    "sg:classifiers":[
        {
            "category":"Autos & Motor Vehicles",
            "subcategory":"Auto Supplies",
            "type":"Retail Goods"
        },
        {
            "category":"Retail",
            "subcategory":"Auto Repair",
            "type":"Services"
        }
    ],
    "sg:phone":"+1 813 681 9544",
    "sg:postcode":"33511",
    "sg:province":"FL",
    "sg:tags":[
        "body",
        "automobile",
        "truck",
        "painting",
        "repairing"
    ],
    "wof:name":"Custom Classic's Inc",
    "wof:placetype":"venue"
},
  "geometry": {"coordinates":[-82.298097,27.93782],"type":"Point"}
}