{
  "type": "Feature",
  "properties": {
    "iso:country":"US",
    "sg:address":"2670 E 5th Ave",
    "sg:city":"Tampa",
    "sg:classifiers":[
        {
            "category":"Retail",
            "subcategory":"Repair Shop",
            "type":"Services"
        },
        {
            "category":"Manufacturing",
            "subcategory":"Tools & Machinery",
            "type":"Manufacturing & Wholesale Goods"
        }
    ],
    "sg:phone":"+1 813 248 8200",
    "sg:postcode":"33605",
    "sg:province":"FL",
    "sg:tags":[
        "machine",
        "fab",
        "metal",
        "mfg"
    ],
    "wof:name":"Alfred Conhagen Inc Of Florida",
    "wof:placetype":"venue"
},
  "geometry": {"coordinates":[-82.430194,27.958869],"type":"Point"}
}