{
  "type": "Feature",
  "properties": {
    "iso:country":"US",
    "sg:address":"516 Douglas Ave",
    "sg:city":"Altamonte Springs",
    "sg:classifiers":[
        {
            "category":"Professional",
            "subcategory":"Lawyer & Legal Services",
            "type":"Services"
        }
    ],
    "sg:phone":"+1 407 869 0900",
    "sg:postcode":"32714",
    "sg:province":"FL",
    "wof:name":"Alper Harvey M Atty",
    "wof:placetype":"venue"
},
  "geometry": {"coordinates":[-81.39051499999999,28.670199],"type":"Point"}
}