{
  "type": "Feature",
  "properties": {
    "iso:country":"US",
    "sg:address":"17823 Dixie Hwy",
    "sg:city":"Miami",
    "sg:classifiers":[
        {
            "category":"Shopping",
            "subcategory":"Used Merchandise",
            "type":"Retail Goods"
        }
    ],
    "sg:phone":"+1 305 232 6300",
    "sg:postcode":"33157",
    "sg:province":"FL",
    "sg:tags":[
        "shop",
        "thrift"
    ],
    "wof:name":"Attic Secrets",
    "wof:placetype":"venue"
},
  "geometry": {"coordinates":[-80.351834,25.603725],"type":"Point"}
}