{
  "type": "Feature",
  "properties": {
    "iso:country":"US",
    "sg:address":"7801 Altamira St",
    "sg:city":"Miami",
    "sg:classifiers":[
        {
            "category":"Real Estate",
            "subcategory":"Real Estate Agent",
            "type":"Services"
        }
    ],
    "sg:phone":"+1 305 667 1202",
    "sg:postcode":"33143",
    "sg:province":"FL",
    "wof:name":"McGlannan Real Estate Assn",
    "wof:placetype":"venue"
},
  "geometry": {"coordinates":[-80.267365,25.698309],"type":"Point"}
}