{
  "type": "Feature",
  "properties": {
    "addr:full":"1223 Colt St Jacksonville FL 32211",
    "addr:housenumber":"1223",
    "addr:postcode":"32211",
    "addr:street":"Colt St",
    "iso:country":"US",
    "sg:address":"1223 Colt St",
    "sg:city":"Jacksonville",
    "sg:classifiers":[
        {
            "category":"Building & Trades",
            "subcategory":"Landscaping Services",
            "type":"Services"
        }
    ],
    "sg:phone":"+1 904 743 1630",
    "sg:postcode":"32211",
    "sg:province":"FL",
    "wof:name":"James L Bryant Lawn Service",
    "wof:placetype":"venue"
},
  "geometry": {"coordinates":[-81.607764,30.333625],"type":"Point"}
}