{
  "type": "Feature",
  "properties": {
    "iso:country":"US",
    "sg:address":"4237 Rogers Rd",
    "sg:city":"Greenwood",
    "sg:classifiers":[
        {
            "category":"Farming",
            "subcategory":"Livestock Farm",
            "type":"Manufacturing & Wholesale Goods"
        }
    ],
    "sg:phone":"+1 850 592 2738",
    "sg:postcode":"32443",
    "sg:province":"FL",
    "sg:tags":[
        "beef",
        "feedlot",
        "cattle"
    ],
    "wof:name":"Herbert Rogers",
    "wof:placetype":"venue"
},
  "geometry": {"coordinates":[-85.04804,30.863038],"type":"Point"}
}