{
  "type": "Feature",
  "properties": {
    "iso:country":"US",
    "sg:address":"2809 Middle River Dr",
    "sg:city":"Fort Lauderdale",
    "sg:classifiers":[
        {
            "category":"Freight",
            "type":"Transportation"
        }
    ],
    "sg:phone":"+1 954 567 3990",
    "sg:postcode":"33306",
    "sg:province":"FL",
    "sg:tags":[
        "general"
    ],
    "wof:name":"Golden Warehouse Services Inc",
    "wof:placetype":"venue"
},
  "geometry": {"coordinates":[-80.115148,26.161242],"type":"Point"}
}