{
  "type": "Feature",
  "properties": {
    "addr:full":"807 Flag Ln Kissimmee FL 34759",
    "addr:housenumber":"807",
    "addr:postcode":"34759",
    "addr:street":"Flag Ln",
    "iso:country":"US",
    "sg:address":"807 Flag Ln",
    "sg:city":"Kissimmee",
    "sg:classifiers":[
        {
            "category":"Building & Trades",
            "subcategory":"Landscaping Services",
            "type":"Services"
        }
    ],
    "sg:phone":"+1 407 870 5075",
    "sg:postcode":"34759",
    "sg:province":"FL",
    "sg:tags":[
        "lawn",
        "maintenance",
        "grounds"
    ],
    "wof:name":"Eduardo Rocchild Lawn Svc",
    "wof:placetype":"venue"
},
  "geometry": {"coordinates":[-81.451965,28.140886],"type":"Point"}
}