{
  "type": "Feature",
  "properties": {
    "iso:country":"US",
    "sg:address":"101 NE 3rd St",
    "sg:city":"Fort Lauderdale",
    "sg:classifiers":[
        {
            "category":"Real Estate",
            "subcategory":"Real Estate Operator",
            "type":"Services"
        }
    ],
    "sg:phone":"+1 954 463 6574",
    "sg:postcode":"33301",
    "sg:province":"FL",
    "sg:tags":[
        "urban",
        "planning",
        "commission"
    ],
    "wof:name":"Down-Town Developmnt Athrty",
    "wof:placetype":"venue"
},
  "geometry": {"coordinates":[-80.140618,26.125168],"type":"Point"}
}