{
  "type": "Feature",
  "properties": {
    "iso:country":"US",
    "sg:address":"883 S Eucalyptus St",
    "sg:city":"Sebring",
    "sg:classifiers":[
        {
            "category":"Place Of Worship",
            "subcategory":"Church",
            "type":"Public Place"
        },
        {
            "category":"Place Of Worship",
            "type":"Public Place"
        }
    ],
    "sg:phone":"+1 863 471 6338",
    "sg:postcode":"33870",
    "sg:province":"FL",
    "sg:tags":[
        "churches-interdenominational",
        "churches-various",
        "denomination"
    ],
    "wof:name":"S E W",
    "wof:placetype":"venue"
},
  "geometry": {"coordinates":[-81.440569,27.489391],"type":"Point"}
}