{
  "type": "Feature",
  "properties": {
    "addr:full":"681 W 49th St Hialeah FL 33012",
    "addr:housenumber":"681",
    "addr:postcode":"33012",
    "addr:street":"W 49Th St",
    "iso:country":"US",
    "sg:address":"681 W 49th St",
    "sg:city":"Hialeah",
    "sg:classifiers":[
        {
            "category":"Utilities",
            "subcategory":"Mobile Phone",
            "type":"Services"
        }
    ],
    "sg:phone":"+1 305 266 6660",
    "sg:postcode":"33012",
    "sg:province":"FL",
    "sg:tags":[
        "repair",
        "beeper"
    ],
    "wof:name":"Beeperia Inc",
    "wof:placetype":"venue"
},
  "geometry": {"coordinates":[-80.297405,25.866719],"type":"Point"}
}