{
  "type": "Feature",
  "properties": {
    "iso:country":"US",
    "sg:address":"14209 SW 142nd St",
    "sg:city":"Miami",
    "sg:classifiers":[
        {
            "category":"Wholesale",
            "subcategory":"Medical Equipment & Supplies",
            "type":"Manufacturing & Wholesale Goods"
        },
        {
            "category":"Shopping",
            "subcategory":"Optical Goods",
            "type":"Retail Goods"
        },
        {
            "category":"Health Services",
            "subcategory":"Optometrist",
            "type":"Services"
        }
    ],
    "sg:phone":"+1 305 964 2020",
    "sg:postcode":"33186",
    "sg:province":"FL",
    "sg:tags":[
        "goods-wholesale",
        "optometrists'",
        "manufacturer"
    ],
    "sg:website":"http://www.hboptical.com",
    "wof:name":"Hb Optical Laboratories Inc",
    "wof:placetype":"venue"
},
  "geometry": {"coordinates":[-80.42291299999999,25.63528],"type":"Point"}
}