{
  "type": "Feature",
  "properties": {
    "addr:full":"6001 Freeport Dr Spring Hill FL 34606",
    "addr:housenumber":"6001",
    "addr:postcode":"34606",
    "addr:street":"Freeport Dr",
    "iso:country":"US",
    "sg:address":"6001 Freeport Dr",
    "sg:city":"Spring Hill",
    "sg:classifiers":[
        {
            "category":"Shopping",
            "subcategory":"Catalog Store",
            "type":"Retail Goods"
        }
    ],
    "sg:phone":"+1 352 596 6879",
    "sg:postcode":"34606",
    "sg:province":"FL",
    "sg:tags":[
        "mail",
        "order"
    ],
    "wof:name":"Philomena Gifts",
    "wof:placetype":"venue"
},
  "geometry": {"coordinates":[-82.565918,28.514933],"type":"Point"}
}