{
  "type": "Feature",
  "properties": {
    "iso:country":"US",
    "sg:address":"3143 SW 145th Ave",
    "sg:city":"Miami",
    "sg:classifiers":[
        {
            "category":"Professional",
            "subcategory":"Detective & Security Services",
            "type":"Services"
        }
    ],
    "sg:phone":"+1 305 207 8987",
    "sg:postcode":"33175",
    "sg:province":"FL",
    "sg:tags":[
        "information",
        "bureau"
    ],
    "wof:name":"Excellence Permitting Services Inc.",
    "wof:placetype":"venue"
},
  "geometry": {"coordinates":[-80.430871,25.7383],"type":"Point"}
}