{
  "type": "Feature",
  "properties": {
    "iso:country":"US",
    "sg:address":"515 NW 36th Ave",
    "sg:city":"Deerfield Beach",
    "sg:classifiers":[
        {
            "category":"Building & Trades",
            "subcategory":"Construction",
            "type":"Services"
        }
    ],
    "sg:phone":"+1 561 248 1045",
    "sg:postcode":"33442",
    "sg:province":"FL",
    "sg:tags":[
        "hanging",
        "contractor"
    ],
    "wof:name":"J G Painter Inc",
    "wof:placetype":"venue"
},
  "geometry": {"coordinates":[-80.15460899999999,26.324057],"type":"Point"}
}