{
  "type": "Feature",
  "properties": {
    "iso:country":"US",
    "sg:address":"205 Chatham J",
    "sg:city":"West Palm Beach",
    "sg:classifiers":[
        {
            "category":"Professional",
            "subcategory":"Business Services",
            "type":"Services"
        }
    ],
    "sg:phone":"+1 561 689 8391",
    "sg:postcode":"33417",
    "sg:province":"FL",
    "sg:tags":[
        "event"
    ],
    "wof:name":"Barbara D Chadwick Special",
    "wof:placetype":"venue"
},
  "geometry": {"coordinates":[-80.130511,26.717739],"type":"Point"}
}