{
  "type": "Feature",
  "properties": {
    "iso:country":"US",
    "sg:address":"1515 NW 167th St",
    "sg:city":"Miami",
    "sg:classifiers":[
        {
            "category":"Real Estate",
            "subcategory":"Real Estate Operator",
            "type":"Services"
        }
    ],
    "sg:phone":"+1 305 621 7460",
    "sg:postcode":"33169",
    "sg:province":"FL",
    "sg:tags":[
        "building",
        "parks"
    ],
    "wof:name":"Golden Glades Office Park",
    "wof:placetype":"venue"
},
  "geometry": {"coordinates":[-80.22444900000001,25.927507],"type":"Point"}
}