{
  "type": "Feature",
  "properties": {
    "iso:country":"US",
    "sg:address":"2600 SE 17th St",
    "sg:city":"Ocala",
    "sg:classifiers":[
        {
            "category":"Health Services",
            "subcategory":"Doctor",
            "type":"Services"
        }
    ],
    "sg:phone":"+1 352 629 7955",
    "sg:postcode":"34471",
    "sg:province":"FL",
    "sg:tags":[
        "physician",
        "surgeon"
    ],
    "wof:name":"Douglas C Hall MD",
    "wof:placetype":"venue"
},
  "geometry": {"coordinates":[-82.101068,29.171458],"type":"Point"}
}