{
  "type": "Feature",
  "properties": {
    "addr:full":"6449 W Appomattox Ln Homosassa FL 34448",
    "addr:housenumber":"6449",
    "addr:postcode":"34448",
    "addr:street":"W Appomattox Ln",
    "iso:country":"US",
    "sg:address":"6449 W Appomattox Ln",
    "sg:city":"Homosassa",
    "sg:classifiers":[
        {
            "category":"Professional",
            "subcategory":"Secretarial Services",
            "type":"Services"
        },
        {
            "category":"Professional",
            "subcategory":"Employment Agencies",
            "type":"Services"
        }
    ],
    "sg:phone":"+1 352 628 1237",
    "sg:postcode":"34448",
    "sg:province":"FL",
    "sg:tags":[
        "typing"
    ],
    "wof:name":"Healthcare Transcription Services",
    "wof:placetype":"venue"
},
  "geometry": {"coordinates":[-82.54152999999999,28.83976],"type":"Point"}
}