{
  "type": "Feature",
  "properties": {
    "iso:country":"US",
    "sg:address":"16721 NE 6th Ave",
    "sg:city":"North Miami Beach",
    "sg:classifiers":[
        {
            "category":"Deli",
            "type":"Food & Drink"
        }
    ],
    "sg:phone":"+1 305 770 0434",
    "sg:postcode":"33162",
    "sg:province":"FL",
    "wof:name":"Christine's Roti Shop",
    "wof:placetype":"venue"
},
  "geometry": {"coordinates":[-80.1884,25.929199],"type":"Point"}
}