{
  "type": "Feature",
  "properties": {
    "iso:country":"US",
    "sg:address":"8127 103rd St",
    "sg:city":"Jacksonville",
    "sg:classifiers":[
        {
            "category":"Retail",
            "subcategory":"Auto Repair",
            "type":"Services"
        }
    ],
    "sg:phone":"+1 904 908 8399",
    "sg:postcode":"32210",
    "sg:province":"FL",
    "sg:tags":[
        "body",
        "automobile",
        "painting"
    ],
    "wof:name":"T A Meeks Automotive",
    "wof:placetype":"venue"
},
  "geometry": {"coordinates":[-81.78516500000001,30.248117],"type":"Point"}
}