{
  "type": "Feature",
  "properties": {
    "addr:full":"405 2nd St S Safety Harbor FL 34695",
    "addr:housenumber":"405",
    "addr:postcode":"34695",
    "addr:street":"2Nd St S",
    "iso:country":"US",
    "sg:address":"405 2nd St S",
    "sg:city":"Safety Harbor",
    "sg:classifiers":[
        {
            "category":"Banks & Credit Unions",
            "subcategory":"Investment Brokerage",
            "type":"Services"
        }
    ],
    "sg:phone":"+1 727 725 8876",
    "sg:postcode":"34695",
    "sg:province":"FL",
    "sg:tags":[
        "advisory",
        "financial"
    ],
    "wof:name":"Turning Point Inc",
    "wof:placetype":"venue"
},
  "geometry": {"coordinates":[-82.692227,27.989986],"type":"Point"}
}