{
  "type": "Feature",
  "properties": {
    "iso:country":"US",
    "sg:address":"570 Bryant St",
    "sg:city":"Ormond Beach",
    "sg:classifiers":[
        {
            "category":"Autos & Motor Vehicles",
            "subcategory":"Motorcycle Sales",
            "type":"Retail Goods"
        }
    ],
    "sg:phone":"+1 386 676 9435",
    "sg:postcode":"32174",
    "sg:province":"FL",
    "wof:name":"K D Cycles",
    "wof:placetype":"venue"
},
  "geometry": {"coordinates":[-81.07272399999999,29.259816],"type":"Point"}
}