{
  "type": "Feature",
  "properties": {
    "addr:full":"5442 Britan Dr Orlando FL 32808",
    "addr:housenumber":"5442",
    "addr:postcode":"32808",
    "addr:street":"Britan Dr",
    "iso:country":"US",
    "sg:address":"5442 Britan Dr",
    "sg:city":"Orlando",
    "sg:classifiers":[
        {
            "category":"Shopping",
            "subcategory":"Clothing, Apparel, & Fashions",
            "type":"Retail Goods"
        }
    ],
    "sg:phone":"+1 407 522 0233",
    "sg:postcode":"32808",
    "sg:province":"FL",
    "sg:tags":[
        "wear"
    ],
    "wof:name":"Just For Children Rentals",
    "wof:placetype":"venue"
},
  "geometry": {"coordinates":[-81.46333300000001,28.608304],"type":"Point"}
}