{
  "type": "Feature",
  "properties": {
    "iso:country":"US",
    "sg:address":"602 Virginia Dr",
    "sg:city":"Bradenton",
    "sg:classifiers":[
        {
            "category":"Building & Trades",
            "subcategory":"Landscaping Services",
            "type":"Services"
        }
    ],
    "sg:phone":"+1 941 748 2681",
    "sg:postcode":"34205",
    "sg:province":"FL",
    "sg:tags":[
        "tree"
    ],
    "wof:name":"Roth Services",
    "wof:placetype":"venue"
},
  "geometry": {"coordinates":[-82.578355,27.494252],"type":"Point"}
}