{
  "type": "Feature",
  "properties": {
    "iso:country":"US",
    "sg:address":"15168 NE 6th Ave",
    "sg:city":"Miami",
    "sg:classifiers":[
        {
            "category":"Retail",
            "subcategory":"Auto Repair",
            "type":"Services"
        }
    ],
    "sg:phone":"+1 305 949 9126",
    "sg:postcode":"33162",
    "sg:province":"FL",
    "wof:name":"Harry's Auto Repair Svc",
    "wof:placetype":"venue"
},
  "geometry": {"coordinates":[-80.1875,25.914801],"type":"Point"}
}