{
  "type": "Feature",
  "properties": {
    "addr:full":"1153 Airport Rd Jacksonville FL 32218",
    "addr:housenumber":"1153",
    "addr:postcode":"32218",
    "addr:street":"Airport Rd",
    "iso:country":"US",
    "sg:address":"1153 Airport Rd",
    "sg:city":"Jacksonville",
    "sg:classifiers":[
        {
            "category":"Travel",
            "subcategory":"Hotels & Motels",
            "type":"Entertainment"
        }
    ],
    "sg:phone":"+1 904 741 4600",
    "sg:postcode":"32218",
    "sg:province":"FL",
    "wof:name":"Ramada Inn",
    "wof:placetype":"venue"
},
  "geometry": {"coordinates":[-81.650486,30.482972],"type":"Point"}
}