{
  "type": "Feature",
  "properties": {
    "iso:country":"US",
    "sg:address":"1165 W 22nd St",
    "sg:city":"Hialeah",
    "sg:classifiers":[
        {
            "category":"Home & Garden",
            "subcategory":"Carpets & Floor Coverings",
            "type":"Retail Goods"
        }
    ],
    "sg:phone":"+1 305 888 0333",
    "sg:postcode":"33010",
    "sg:province":"FL",
    "sg:tags":[
        "carpeting"
    ],
    "wof:name":"Tamiami Carpet Interiors",
    "wof:placetype":"venue"
},
  "geometry": {"coordinates":[-80.305603,25.841499],"type":"Point"}
}