{
  "type": "Feature",
  "properties": {
    "addr:full":"5858 Central Ave Saint Petersburg FL 33707",
    "addr:housenumber":"5858",
    "addr:postcode":"33707",
    "addr:street":"Central Ave",
    "iso:country":"US",
    "sg:address":"5858 Central Ave",
    "sg:city":"Saint Petersburg",
    "sg:classifiers":[
        {
            "category":"Banks & Credit Unions",
            "subcategory":"Investment Brokerage",
            "type":"Services"
        }
    ],
    "sg:phone":"+1 727 384 2000",
    "sg:postcode":"33707",
    "sg:province":"FL",
    "sg:tags":[
        "security"
    ],
    "wof:name":"Prudential",
    "wof:placetype":"venue"
},
  "geometry": {"coordinates":[-82.713089,27.770803],"type":"Point"}
}