{
  "type": "Feature",
  "properties": {
    "addr:full":"2030 Southern Dunes Blvd Haines City FL 33844",
    "addr:housenumber":"2030",
    "addr:postcode":"33844",
    "addr:street":"Southern Dunes Blvd",
    "iso:country":"US",
    "sg:address":"2030 Southern Dunes Blvd",
    "sg:city":"Haines City",
    "sg:classifiers":[
        {
            "category":"Building & Trades",
            "subcategory":"Construction",
            "type":"Services"
        }
    ],
    "sg:phone":"+1 863 421 0225",
    "sg:postcode":"33844",
    "sg:province":"FL",
    "sg:tags":[
        "house"
    ],
    "wof:name":"BDS Homes Inc",
    "wof:placetype":"venue"
},
  "geometry": {"coordinates":[-81.627668,28.125906],"type":"Point"}
}