{
  "type": "Feature",
  "properties": {
    "iso:country":"US",
    "sg:address":"5600 W Hallandale Beach Blvd",
    "sg:city":"Hollywood",
    "sg:classifiers":[
        {
            "category":"Professional",
            "type":"Services"
        }
    ],
    "sg:phone":"+1 954 889 8417",
    "sg:postcode":"33023",
    "sg:province":"FL",
    "wof:name":"AAAAA 7 Day 1 Locksmith Svc",
    "wof:placetype":"venue"
},
  "geometry": {"coordinates":[-80.19862500000001,25.984194],"type":"Point"}
}