{
  "type": "Feature",
  "properties": {
    "iso:country":"US",
    "sg:address":"134 Evernia St",
    "sg:city":"Jupiter",
    "sg:classifiers":[
        {
            "category":"Retail",
            "subcategory":"Auto Repair",
            "type":"Services"
        }
    ],
    "sg:phone":"+1 561 746 3495",
    "sg:postcode":"33458",
    "sg:province":"FL",
    "sg:tags":[
        "repairing",
        "automobile",
        "general"
    ],
    "wof:name":"Mike's Oil Slick",
    "wof:placetype":"venue"
},
  "geometry": {"coordinates":[-80.09530100000001,26.936742],"type":"Point"}
}