{
  "type": "Feature",
  "properties": {
    "iso:country":"US",
    "sg:address":"3118 Legends Cir",
    "sg:city":"Lakeland",
    "sg:classifiers":[
        {
            "category":"Shopping",
            "subcategory":"Clothing, Apparel, & Fashions",
            "type":"Retail Goods"
        }
    ],
    "sg:phone":"+1 336 516 0080",
    "sg:postcode":"33803",
    "sg:province":"FL",
    "wof:name":"Coockediesel LLC",
    "wof:placetype":"venue"
},
  "geometry": {"coordinates":[-81.984956,28.006093],"type":"Point"}
}