{
  "type": "Feature",
  "properties": {
    "iso:country":"US",
    "sg:address":"3230 NW 42nd St",
    "sg:city":"Miami",
    "sg:classifiers":[
        {
            "category":"Manufacturing",
            "subcategory":"Metals",
            "type":"Manufacturing & Wholesale Goods"
        }
    ],
    "sg:phone":"+1 305 726 2150",
    "sg:postcode":"33142",
    "sg:province":"FL",
    "sg:tags":[
        "stamping"
    ],
    "wof:name":"Iron Container",
    "wof:placetype":"venue"
},
  "geometry": {"coordinates":[-80.248851,25.813459],"type":"Point"}
}