{
  "type": "Feature",
  "properties": {
    "iso:country":"US",
    "sg:address":"6644 Old Winter Garden Rd",
    "sg:city":"Orlando",
    "sg:classifiers":[
        {
            "category":"Shopping",
            "subcategory":"Florist",
            "type":"Retail Goods"
        }
    ],
    "sg:phone":"+1 407 298 5524",
    "sg:postcode":"32835",
    "sg:province":"FL",
    "wof:name":"Blooming Crazy Florist Inc",
    "wof:placetype":"venue"
},
  "geometry": {"coordinates":[-81.474575,28.538885],"type":"Point"}
}