{
  "type": "Feature",
  "properties": {
    "addr:full":"7581 Winkler Rd Fort Myers FL 33908",
    "addr:housenumber":"7581",
    "addr:postcode":"33908",
    "addr:street":"Winkler Rd",
    "iso:country":"US",
    "sg:address":"7581 Winkler Rd",
    "sg:city":"Fort Myers",
    "sg:classifiers":[
        {
            "category":"Shopping",
            "subcategory":"Pharmacy",
            "type":"Retail Goods"
        }
    ],
    "sg:phone":"+1 239 432 2619",
    "sg:postcode":"33908",
    "sg:province":"FL",
    "sg:tags":[
        "drugstore"
    ],
    "sg:website":"www.cvs.com",
    "wof:name":"Cvs Pharmacy",
    "wof:placetype":"venue"
},
  "geometry": {"coordinates":[-81.898517,26.515652],"type":"Point"}
}