{
  "type": "Feature",
  "properties": {
    "iso:country":"US",
    "sg:address":"1820 Center Dr",
    "sg:city":"Casselberry",
    "sg:classifiers":[
        {
            "category":"Organizations",
            "subcategory":"Community Association",
            "type":"Services"
        }
    ],
    "sg:phone":"+1 407 599 1911",
    "sg:postcode":"32707",
    "sg:province":"FL",
    "sg:tags":[
        "club"
    ],
    "wof:name":"Orlando Trade Club",
    "wof:placetype":"venue"
},
  "geometry": {"coordinates":[-81.298947,28.667732],"type":"Point"}
}