{
  "type": "Feature",
  "properties": {
    "addr:full":"1073 Willa Springs Dr Ste 1013 Winter Springs FL 32708",
    "addr:housenumber":"1073",
    "addr:postcode":"32708",
    "addr:street":"Willa Springs Dr Ste 1013",
    "iso:country":"US",
    "sg:address":"1073 Willa Springs Dr Ste 1013",
    "sg:city":"Winter Springs",
    "sg:classifiers":[
        {
            "category":"Autos & Motor Vehicles",
            "subcategory":"Fuel & Gas Station",
            "type":"Retail Goods"
        }
    ],
    "sg:phone":"+1 407 696 3084",
    "sg:postcode":"32708",
    "sg:province":"FL",
    "sg:website":"www.shell.com",
    "wof:name":"Shell Oil Products US",
    "wof:placetype":"venue"
},
  "geometry": {"coordinates":[-81.268326,28.644441],"type":"Point"}
}