{
  "type": "Feature",
  "properties": {
    "iso:country":"US",
    "sg:address":"123 W Hirth Rd",
    "sg:city":"Fernandina Beach",
    "sg:classifiers":[
        {
            "category":"Professional",
            "type":"Services"
        }
    ],
    "sg:phone":"+1 904 321 0046",
    "sg:postcode":"32034",
    "sg:province":"FL",
    "wof:name":"J Paul Thibault",
    "wof:placetype":"venue"
},
  "geometry": {"coordinates":[-81.469815,30.626522],"type":"Point"}
}