{
  "type": "Feature",
  "properties": {
    "iso:country":"US",
    "sg:address":"2613 W 76th St",
    "sg:city":"Hialeah",
    "sg:classifiers":[
        {
            "category":"Arena",
            "subcategory":"Sports Club",
            "type":"Entertainment"
        }
    ],
    "sg:phone":"+1 305 826 0355",
    "sg:postcode":"33016",
    "sg:province":"FL",
    "sg:tags":[
        "martial art"
    ],
    "wof:name":"Budokan Judo School",
    "wof:placetype":"venue"
},
  "geometry": {"coordinates":[-80.336403,25.891399],"type":"Point"}
}