{
  "type": "Feature",
  "properties": {
    "iso:country":"US",
    "sg:address":"1318 S Crystal Lake Dr",
    "sg:city":"Orlando",
    "sg:classifiers":[
        {
            "category":"Health Services",
            "subcategory":"Health Practitioner",
            "type":"Services"
        }
    ],
    "sg:phone":"+1 407 898 8145",
    "sg:postcode":"32806",
    "sg:province":"FL",
    "sg:tags":[
        "shop",
        "beauty"
    ],
    "wof:name":"Central Fla Schl Hlth Science",
    "wof:placetype":"venue"
},
  "geometry": {"coordinates":[-81.343515,28.525956],"type":"Point"}
}