{
  "type": "Feature",
  "properties": {
    "iso:country":"US",
    "sg:address":"660 Mandalay Ave",
    "sg:city":"Clearwater",
    "sg:classifiers":[
        {
            "category":"Real Estate",
            "subcategory":"Real Estate Agent",
            "type":"Services"
        }
    ],
    "sg:phone":"+1 727 446 1102",
    "sg:postcode":"33767",
    "sg:province":"FL",
    "sg:website":"www.balowrealty.com",
    "wof:name":"Balow Realty",
    "wof:placetype":"venue"
},
  "geometry": {"coordinates":[-82.826616,27.989065],"type":"Point"}
}