{
  "type": "Feature",
  "properties": {
    "iso:country":"US",
    "sg:address":"1200 S View Dr",
    "sg:city":"Sarasota",
    "sg:classifiers":[
        {
            "category":"Building & Trades",
            "subcategory":"Electrical",
            "type":"Services"
        }
    ],
    "sg:phone":"+1 941 504 3470",
    "sg:postcode":"34242",
    "sg:province":"FL",
    "sg:tags":[
        "structured",
        "wiring"
    ],
    "wof:name":"Sarasota Handyman",
    "wof:placetype":"venue"
},
  "geometry": {"coordinates":[-82.54342699999999,27.271122],"type":"Point"}
}