{
  "type": "Feature",
  "properties": {
    "addr:full":"4929 Eulace Rd Jacksonville FL 32210",
    "addr:housenumber":"4929",
    "addr:postcode":"32210",
    "addr:street":"Eulace Rd",
    "iso:country":"US",
    "sg:address":"4929 Eulace Rd",
    "sg:city":"Jacksonville",
    "sg:classifiers":[
        {
            "category":"Building & Trades",
            "subcategory":"Plumbing",
            "type":"Services"
        }
    ],
    "sg:phone":"+1 904 708 7172",
    "sg:postcode":"32210",
    "sg:province":"FL",
    "sg:tags":[
        "plumbing",
        "contractor"
    ],
    "wof:name":"Sweats Plumbing",
    "wof:placetype":"venue"
},
  "geometry": {"coordinates":[-81.733199,30.247711],"type":"Point"}
}