{
  "type": "Feature",
  "properties": {
    "addr:full":"973 S Tropical Trl Merritt Island FL 32952",
    "addr:housenumber":"973",
    "addr:postcode":"32952",
    "addr:street":"S Tropical Trl",
    "iso:country":"US",
    "sg:address":"973 S Tropical Trl",
    "sg:city":"Merritt Island",
    "sg:classifiers":[
        {
            "category":"Professional",
            "subcategory":"Business Services",
            "type":"Services"
        }
    ],
    "sg:phone":"+1 321 454 3836",
    "sg:postcode":"32952",
    "sg:province":"FL",
    "wof:name":"J T Y Enterprises Inc",
    "wof:placetype":"venue"
},
  "geometry": {"coordinates":[-80.70058899999999,28.34069],"type":"Point"}
}