{
  "type": "Feature",
  "properties": {
    "iso:country":"US",
    "sg:address":"1310 W Colonial Dr Ste 5",
    "sg:city":"Orlando",
    "sg:classifiers":[
        {
            "category":"Social Services",
            "type":"Services"
        },
        {
            "category":"Health Services",
            "subcategory":"Clinic",
            "type":"Services"
        }
    ],
    "sg:phone":"+1 407 839 1441",
    "sg:postcode":"32804",
    "sg:province":"FL",
    "sg:tags":[
        "information",
        "mental"
    ],
    "wof:name":"I T M Group",
    "wof:placetype":"venue"
},
  "geometry": {"coordinates":[-81.397599,28.55294],"type":"Point"}
}