{
  "type": "Feature",
  "properties": {
    "addr:full":"21 NW 8th St Homestead FL 33030",
    "addr:housenumber":"21",
    "addr:postcode":"33030",
    "addr:street":"Nw 8Th St",
    "iso:country":"US",
    "sg:address":"21 NW 8th St",
    "sg:city":"Homestead",
    "sg:classifiers":[
        {
            "category":"Airline",
            "type":"Transportation"
        }
    ],
    "sg:phone":"+1 305 245 9778",
    "sg:postcode":"33030",
    "sg:province":"FL",
    "sg:tags":[
        "courier",
        "air"
    ],
    "wof:name":"Giant Express",
    "wof:placetype":"venue"
},
  "geometry": {"coordinates":[-80.479094,25.477216],"type":"Point"}
}