{
  "type": "Feature",
  "properties": {
    "addr:full":"2875 NE 191st St Ste 900 Miami FL 33180",
    "addr:housenumber":"2875",
    "addr:postcode":"33180",
    "addr:street":"Ne 191St St Ste 900",
    "iso:country":"US",
    "sg:address":"2875 NE 191st St Ste 900",
    "sg:city":"Miami",
    "sg:classifiers":[
        {
            "category":"Banks & Credit Unions",
            "subcategory":"Investment Brokerage",
            "type":"Services"
        }
    ],
    "sg:phone":"+1 305 935 8043",
    "sg:postcode":"33180",
    "sg:province":"FL",
    "sg:tags":[
        "investing"
    ],
    "wof:name":"Magnum Investments",
    "wof:placetype":"venue"
},
  "geometry": {"coordinates":[-80.14467999999999,25.952383],"type":"Point"}
}