{
  "type": "Feature",
  "properties": {
    "addr:full":"890 SW 87th Ave Miami FL 33174",
    "addr:housenumber":"890",
    "addr:postcode":"33174",
    "addr:street":"Sw 87Th Ave",
    "iso:country":"US",
    "sg:address":"890 SW 87th Ave",
    "sg:city":"Miami",
    "sg:classifiers":[
        {
            "category":"Shopping",
            "subcategory":"Pharmacy",
            "type":"Retail Goods"
        }
    ],
    "sg:phone":"+1 305 551 7778",
    "sg:postcode":"33174",
    "sg:province":"FL",
    "sg:tags":[
        "drugstore"
    ],
    "wof:name":"Castilla 87th Pharmacy & Discount Inc",
    "wof:placetype":"venue"
},
  "geometry": {"coordinates":[-80.336197,25.7616],"type":"Point"}
}