{
  "type": "Feature",
  "properties": {
    "addr:full":"11890 SW 4th St Miami FL 33184",
    "addr:housenumber":"11890",
    "addr:postcode":"33184",
    "addr:street":"Sw 4Th St",
    "iso:country":"US",
    "sg:address":"11890 SW 4th St",
    "sg:city":"Miami",
    "sg:classifiers":[
        {
            "category":"Communications",
            "subcategory":"Film & Video Production",
            "type":"Services"
        }
    ],
    "sg:phone":"+1 305 551 1244",
    "sg:postcode":"33184",
    "sg:province":"FL",
    "sg:tags":[
        "dvd",
        "cassette",
        "duplicating",
        "cd"
    ],
    "wof:name":"Jrs Cd Duplications Inc",
    "wof:placetype":"venue"
},
  "geometry": {"coordinates":[-80.38867399999999,25.76458],"type":"Point"}
}