{
  "type": "Feature",
  "properties": {
    "iso:country":"US",
    "sg:address":"911 Nantucket Rd",
    "sg:city":"Venice",
    "sg:classifiers":[
        {
            "category":"Building & Trades",
            "subcategory":"Landscaping Services",
            "type":"Services"
        }
    ],
    "sg:phone":"+1 941 408 9180",
    "sg:postcode":"34293",
    "sg:province":"FL",
    "wof:name":"Small Time Lawn Service",
    "wof:placetype":"venue"
},
  "geometry": {"coordinates":[-82.426512,27.057454],"type":"Point"}
}