{
  "type": "Feature",
  "properties": {
    "addr:full":"1311 Bird Ave Daytona Beach FL 32114",
    "addr:housenumber":"1311",
    "addr:postcode":"32114",
    "addr:street":"Bird Ave",
    "iso:country":"US",
    "sg:address":"1311 Bird Ave",
    "sg:city":"Daytona Beach",
    "sg:classifiers":[
        {
            "category":"Social Services",
            "type":"Services"
        }
    ],
    "sg:phone":"+1 386 254 4106",
    "sg:postcode":"32114",
    "sg:province":"FL",
    "sg:tags":[
        "crisis",
        "intervention"
    ],
    "wof:name":"Sexual Assault Recovery Ctr",
    "wof:placetype":"venue"
},
  "geometry": {"coordinates":[-81.054092,29.202801],"type":"Point"}
}