{
  "type": "Feature",
  "properties": {
    "iso:country":"US",
    "sg:address":"340 23rd Ave S",
    "sg:city":"Jacksonville Bch",
    "sg:classifiers":[
        {
            "category":"Education",
            "subcategory":"Dance Studio",
            "type":"Public Place"
        }
    ],
    "sg:phone":"+1 904 246 6662",
    "sg:postcode":"32250",
    "sg:province":"FL",
    "sg:tags":[
        "instruction",
        "dancing"
    ],
    "sg:website":"www.pollybdance.com",
    "wof:name":"Polly B Dance Academy",
    "wof:placetype":"venue"
},
  "geometry": {"coordinates":[-81.390151,30.268978],"type":"Point"}
}