{
  "type": "Feature",
  "properties": {
    "iso:country":"US",
    "sg:address":"93 SW 79th Ct",
    "sg:city":"Miami",
    "sg:classifiers":[
        {
            "category":"Health Services",
            "subcategory":"Nursing And Care Facility",
            "type":"Services"
        },
        {
            "category":"Social Services",
            "subcategory":"Adult Care",
            "type":"Services"
        }
    ],
    "sg:phone":"+1 305 266 1499",
    "sg:postcode":"33144",
    "sg:province":"FL",
    "sg:tags":[
        "retirement",
        "people",
        "community",
        "homes-elderly",
        "home",
        "aged"
    ],
    "wof:name":"Midway Retirement Residence Inc",
    "wof:placetype":"venue"
},
  "geometry": {"coordinates":[-80.32547099999999,25.768878],"type":"Point"}
}