{
  "type": "Feature",
  "properties": {
    "iso:country":"US",
    "sg:address":"2314 Edgewood Ave W",
    "sg:city":"Jacksonville",
    "sg:classifiers":[
        {
            "category":"Shopping",
            "type":"Retail Goods"
        }
    ],
    "sg:phone":"+1 904 765 3479",
    "sg:postcode":"32209",
    "sg:province":"FL",
    "sg:tags":[
        "art",
        "gallery",
        "dealer"
    ],
    "wof:name":"Ma & Pa Art Gallery",
    "wof:placetype":"venue"
},
  "geometry": {"coordinates":[-81.699862,30.378758],"type":"Point"}
}