{
  "type": "Feature",
  "properties": {
    "addr:full":"8060 Osceola Polk Line Rd Davenport FL 33896",
    "addr:housenumber":"8060",
    "addr:postcode":"33896",
    "addr:street":"Osceola Polk Line Rd",
    "iso:country":"US",
    "sg:address":"8060 Osceola Polk Line Rd",
    "sg:city":"Davenport",
    "sg:classifiers":[
        {
            "category":"Place Of Worship",
            "subcategory":"Church",
            "type":"Public Place"
        }
    ],
    "sg:phone":"+1 407 396 4556",
    "sg:postcode":"33896",
    "sg:province":"FL",
    "sg:tags":[
        "churches-baptist-independent"
    ],
    "wof:name":"Oak Hill Baptist Church",
    "wof:placetype":"venue"
},
  "geometry": {"coordinates":[-81.608681,28.259992],"type":"Point"}
}