{
  "type": "Feature",
  "properties": {
    "addr:full":"6812 Branding Iron Ln Milton FL 32570",
    "addr:housenumber":"6812",
    "addr:postcode":"32570",
    "addr:street":"Branding Iron Ln",
    "iso:country":"US",
    "sg:address":"6812 Branding Iron Ln",
    "sg:city":"Milton",
    "sg:classifiers":[
        {
            "category":"Building & Trades",
            "subcategory":"Plumbing",
            "type":"Services"
        }
    ],
    "sg:phone":"+1 850 623 9365",
    "sg:postcode":"32570",
    "sg:province":"FL",
    "sg:tags":[
        "repair",
        "contractor"
    ],
    "wof:name":"P&P Septic Tank Service",
    "wof:placetype":"venue"
},
  "geometry": {"coordinates":[-87.044618,30.682902],"type":"Point"}
}