{
  "type": "Feature",
  "properties": {
    "iso:country":"US",
    "sg:address":"1569 Palm Bay Rd NE",
    "sg:city":"Palm Bay",
    "sg:classifiers":[
        {
            "category":"Professional",
            "subcategory":"Business Services",
            "type":"Services"
        }
    ],
    "sg:phone":"+1 321 722 2804",
    "sg:postcode":"32905",
    "sg:province":"FL",
    "sg:tags":[
        "auctioneer"
    ],
    "wof:name":"Cook's Auction Co",
    "wof:placetype":"venue"
},
  "geometry": {"coordinates":[-80.62516100000001,28.035158],"type":"Point"}
}