{
  "type": "Feature",
  "properties": {
    "iso:country":"US",
    "sg:address":"943 Almond Tree Cir",
    "sg:city":"Orlando",
    "sg:classifiers":[
        {
            "category":"Professional",
            "subcategory":"Management & Consulting",
            "type":"Services"
        }
    ],
    "sg:phone":"+1 407 294 0243",
    "sg:postcode":"32835",
    "sg:province":"FL",
    "sg:tags":[
        "consultant"
    ],
    "wof:name":"MCR Research & Consulting",
    "wof:placetype":"venue"
},
  "geometry": {"coordinates":[-81.508076,28.526812],"type":"Point"}
}