{
  "type": "Feature",
  "properties": {
    "iso:country":"US",
    "sg:address":"2229 Arrow Ave",
    "sg:city":"Spring Hill",
    "sg:classifiers":[
        {
            "category":"Building & Trades",
            "subcategory":"Construction",
            "type":"Services"
        }
    ],
    "sg:phone":"+1 352 683 7480",
    "sg:postcode":"34609",
    "sg:province":"FL",
    "sg:tags":[
        "floor",
        "laying",
        "contractor"
    ],
    "wof:name":"Trepen Flooring LLC",
    "wof:placetype":"venue"
},
  "geometry": {"coordinates":[-82.50086400000001,28.467374],"type":"Point"}
}