{
  "type": "Feature",
  "properties": {
    "addr:full":"9116 Lakechase Island Way Tampa FL 33626",
    "addr:housenumber":"9116",
    "addr:postcode":"33626",
    "addr:street":"Lakechase Island Way",
    "iso:country":"US",
    "sg:address":"9116 Lakechase Island Way",
    "sg:city":"Tampa",
    "sg:classifiers":[
        {
            "category":"Utilities",
            "subcategory":"Telephone",
            "type":"Services"
        }
    ],
    "sg:phone":"+1 813 926 4922",
    "sg:postcode":"33626",
    "sg:province":"FL",
    "sg:tags":[
        "communications"
    ],
    "wof:name":"Netndatacom",
    "wof:placetype":"venue"
},
  "geometry": {"coordinates":[-82.594283,28.059167],"type":"Point"}
}