{
  "type": "Feature",
  "properties": {
    "iso:country":"US",
    "sg:address":"901 Pennsylvania Ave",
    "sg:city":"Miami Beach",
    "sg:classifiers":[
        {
            "category":"Retail",
            "subcategory":"Animal Services",
            "type":"Services"
        }
    ],
    "sg:phone":"+1 305 674 1070",
    "sg:postcode":"33139",
    "sg:province":"FL",
    "sg:tags":[
        "pet",
        "grooming",
        "washing"
    ],
    "wof:name":"South Beach Pet Shop",
    "wof:placetype":"venue"
},
  "geometry": {"coordinates":[-80.13399200000001,25.780694],"type":"Point"}
}