{
  "type": "Feature",
  "properties": {
    "iso:country":"US",
    "sg:address":"720 N Indiana Ave",
    "sg:city":"Englewood",
    "sg:classifiers":[
        {
            "category":"Real Estate",
            "subcategory":"Real Estate Agent",
            "type":"Services"
        }
    ],
    "sg:phone":"+1 941 474 7447",
    "sg:postcode":"34223",
    "sg:province":"FL",
    "wof:name":"J H Thompson Properties Inc",
    "wof:placetype":"venue"
},
  "geometry": {"coordinates":[-82.354415,26.974405],"type":"Point"}
}