{
  "type": "Feature",
  "properties": {
    "addr:full":"7250 NW 36th Ave Miami FL 33147",
    "addr:housenumber":"7250",
    "addr:postcode":"33147",
    "addr:street":"Nw 36Th Ave",
    "iso:country":"US",
    "sg:address":"7250 NW 36th Ave",
    "sg:city":"Miami",
    "sg:classifiers":[
        {
            "category":"Home & Garden",
            "subcategory":"Household Appliances",
            "type":"Retail Goods"
        }
    ],
    "sg:phone":"+1 305 691 4830",
    "sg:postcode":"33147",
    "sg:province":"FL",
    "sg:tags":[
        "appliances-major-used"
    ],
    "sg:website":"http://www.antareswineclearingusa.com",
    "wof:name":"Antares Inc",
    "wof:placetype":"venue"
},
  "geometry": {"coordinates":[-80.25524799999999,25.840742],"type":"Point"}
}