{
  "type": "Feature",
  "properties": {
    "iso:country":"US",
    "sg:address":"14 Timber Trl",
    "sg:city":"Ormond Beach",
    "sg:classifiers":[
        {
            "category":"Shopping",
            "subcategory":"Pharmacy",
            "type":"Retail Goods"
        }
    ],
    "sg:phone":"+1 386 677 4577",
    "sg:postcode":"32174",
    "sg:province":"FL",
    "sg:tags":[
        "drug",
        "store"
    ],
    "wof:name":"Nicks Pharmacy",
    "wof:placetype":"venue"
},
  "geometry": {"coordinates":[-81.062358,29.255013],"type":"Point"}
}