{
  "type": "Feature",
  "properties": {
    "iso:country":"US",
    "sg:address":"9600 NW 38th St",
    "sg:city":"Doral",
    "sg:classifiers":[
        {
            "category":"Insurance",
            "subcategory":"Insurance Agent",
            "type":"Services"
        }
    ],
    "sg:phone":"+1 305 559 9580",
    "sg:postcode":"33178",
    "sg:province":"FL",
    "sg:website":"www.lpigroup.com",
    "wof:name":"Life Partners INSURANCE Group",
    "wof:placetype":"venue"
},
  "geometry": {"coordinates":[-80.35143600000001,25.808614],"type":"Point"}
}