{
  "type": "Feature",
  "properties": {
    "iso:country":"US",
    "sg:address":"2171 N Hercules Ave",
    "sg:city":"Clearwater",
    "sg:classifiers":[
        {
            "category":"Shopping",
            "subcategory":"Florist",
            "type":"Retail Goods"
        }
    ],
    "sg:phone":"+1 727 738 8779",
    "sg:postcode":"33763",
    "sg:province":"FL",
    "wof:name":"Carol's Flowers",
    "wof:placetype":"venue"
},
  "geometry": {"coordinates":[-82.75477100000001,28.000545],"type":"Point"}
}