{
  "type": "Feature",
  "properties": {
    "iso:country":"US",
    "sg:address":"6900 Adamo Dr",
    "sg:city":"Tampa",
    "sg:classifiers":[
        {
            "category":"Home & Garden",
            "subcategory":"Building Materials",
            "type":"Retail Goods"
        }
    ],
    "sg:phone":"+1 813 630 9863",
    "sg:postcode":"33619",
    "sg:province":"FL",
    "sg:tags":[
        "wholesale"
    ],
    "wof:name":"R 24 Lumber Co",
    "wof:placetype":"venue"
},
  "geometry": {"coordinates":[-82.38227000000001,27.952327],"type":"Point"}
}