{
  "type": "Feature",
  "properties": {
    "iso:country":"US",
    "sg:address":"12951 S Orange Blossom Trl",
    "sg:city":"Orlando",
    "sg:classifiers":[
        {
            "category":"Shopping",
            "subcategory":"Florist",
            "type":"Retail Goods"
        }
    ],
    "sg:phone":"+1 407 856 1730",
    "sg:postcode":"32837",
    "sg:province":"FL",
    "wof:name":"Lizbeth Galarza Florists",
    "wof:placetype":"venue"
},
  "geometry": {"coordinates":[-81.404416,28.376391],"type":"Point"}
}