{
  "type": "Feature",
  "properties": {
    "iso:country":"US",
    "sg:address":"8700 William Sharkey St",
    "sg:city":"Orlando",
    "sg:classifiers":[
        {
            "category":"Banks & Credit Unions",
            "subcategory":"Investment Brokerage",
            "type":"Services"
        }
    ],
    "sg:phone":"+1 407 298 0078",
    "sg:postcode":"32818",
    "sg:province":"FL",
    "sg:tags":[
        "advisory",
        "financial"
    ],
    "wof:name":"CSP Financial Svc",
    "wof:placetype":"venue"
},
  "geometry": {"coordinates":[-81.502791,28.550358],"type":"Point"}
}