{
  "type": "Feature",
  "properties": {
    "iso:country":"US",
    "sg:address":"19239 Dale Mabry Hwy N # 54",
    "sg:city":"Lutz",
    "sg:classifiers":[
        {
            "category":"Personal",
            "type":"Services"
        },
        {
            "category":"Sports & Exercise",
            "subcategory":"Gym",
            "type":"Entertainment"
        }
    ],
    "sg:phone":"+1 813 949 0112",
    "sg:postcode":"33548",
    "sg:province":"FL",
    "sg:tags":[
        "trainer",
        "consultant",
        "program",
        "physical",
        "fitness"
    ],
    "wof:name":"Achieve Total Fitness Inc",
    "wof:placetype":"venue"
},
  "geometry": {"coordinates":[-82.483395,28.157811],"type":"Point"}
}