{
  "type": "Feature",
  "properties": {
    "iso:country":"US",
    "sg:address":"4913 Myrtle Dr",
    "sg:city":"Fort Pierce",
    "sg:classifiers":[
        {
            "category":"Professional",
            "subcategory":"Accounting & Tax Preparation",
            "type":"Services"
        }
    ],
    "sg:phone":"+1 772 489 9152",
    "sg:postcode":"34982",
    "sg:province":"FL",
    "sg:tags":[
        "return"
    ],
    "wof:name":"Feyereisen Tax and Accounting",
    "wof:placetype":"venue"
},
  "geometry": {"coordinates":[-80.308072,27.376608],"type":"Point"}
}