{
  "type": "Feature",
  "properties": {
    "addr:full":"13465 SW 91st Ter Miami FL 33186",
    "addr:housenumber":"13465",
    "addr:postcode":"33186",
    "addr:street":"Sw 91St Ter",
    "iso:country":"US",
    "sg:address":"13465 SW 91st Ter",
    "sg:city":"Miami",
    "sg:classifiers":[
        {
            "category":"Real Estate",
            "subcategory":"Architect",
            "type":"Services"
        }
    ],
    "sg:phone":"+1 305 408 8357",
    "sg:postcode":"33186",
    "sg:province":"FL",
    "wof:name":"Jsa Group Inc",
    "wof:placetype":"venue"
},
  "geometry": {"coordinates":[-80.41368300000001,25.682617],"type":"Point"}
}