{
  "type": "Feature",
  "properties": {
    "iso:country":"US",
    "sg:address":"2410 Flamingo Ct",
    "sg:city":"Saint Cloud",
    "sg:classifiers":[
        {
            "category":"Building & Trades",
            "subcategory":"Landscaping Services",
            "type":"Services"
        }
    ],
    "sg:phone":"+1 407 957 4215",
    "sg:postcode":"34771",
    "sg:province":"FL",
    "wof:name":"Wall Scapes of Florida Inc",
    "wof:placetype":"venue"
},
  "geometry": {"coordinates":[-81.169352,28.232055],"type":"Point"}
}