{
  "type": "Feature",
  "properties": {
    "iso:country":"US",
    "sg:address":"550 Brickell Ave",
    "sg:city":"Miami",
    "sg:classifiers":[
        {
            "category":"Professional",
            "subcategory":"Lawyer & Legal Services",
            "type":"Services"
        }
    ],
    "sg:phone":"+1 305 375 0405",
    "sg:postcode":"33131",
    "sg:province":"FL",
    "wof:name":"Singer Keith Attorney At Law",
    "wof:placetype":"venue"
},
  "geometry": {"coordinates":[-80.190248,25.768302],"type":"Point"}
}