{
  "type": "Feature",
  "properties": {
    "iso:country":"US",
    "sg:address":"815 SW 12th Ave",
    "sg:city":"Miami",
    "sg:classifiers":[
        {
            "category":"Organizations",
            "subcategory":"Religious Organization",
            "type":"Services"
        }
    ],
    "sg:phone":"+1 305 860 7777",
    "sg:postcode":"33130",
    "sg:province":"FL",
    "wof:name":"Iglesia La Luz Del Mundo",
    "wof:placetype":"venue"
},
  "geometry": {"coordinates":[-80.214302,25.765699],"type":"Point"}
}