{
  "type": "Feature",
  "properties": {
    "iso:country":"US",
    "sg:address":"28 Mildred Dr",
    "sg:city":"Fort Myers",
    "sg:classifiers":[
        {
            "category":"Retail",
            "subcategory":"Auto Repair",
            "type":"Services"
        }
    ],
    "sg:phone":"+1 239 939 1447",
    "sg:postcode":"33901",
    "sg:province":"FL",
    "wof:name":"Edison Auto Service Inc",
    "wof:placetype":"venue"
},
  "geometry": {"coordinates":[-81.873497,26.599199],"type":"Point"}
}