{
  "type": "Feature",
  "properties": {
    "iso:country":"US",
    "sg:address":"4066 Evans Ave Ste 18",
    "sg:city":"Fort Myers",
    "sg:classifiers":[
        {
            "category":"Banks & Credit Unions",
            "subcategory":"Financial Services",
            "type":"Services"
        }
    ],
    "sg:phone":"+1 239 461 2784",
    "sg:postcode":"33901",
    "sg:province":"FL",
    "sg:tags":[
        "broker",
        "mortgage"
    ],
    "wof:name":"Family Home Funding Enterprises Inc",
    "wof:placetype":"venue"
},
  "geometry": {"coordinates":[-81.859802,26.6031],"type":"Point"}
}