{
  "type": "Feature",
  "properties": {
    "iso:country":"US",
    "sg:address":"2420 NW 18th Ave",
    "sg:city":"Miami",
    "sg:classifiers":[
        {
            "category":"Education",
            "subcategory":"School",
            "type":"Public Place"
        }
    ],
    "sg:phone":"+1 305 635 7341",
    "sg:postcode":"33142",
    "sg:province":"FL",
    "sg:tags":[
        "high",
        "elementary",
        "middle"
    ],
    "sg:website":"comstockelementary.dadeschools.net",
    "wof:name":"Miami-Dade County Public Schools",
    "wof:placetype":"venue"
},
  "geometry": {"coordinates":[-80.22566999999999,25.799021],"type":"Point"}
}