{
  "type": "Feature",
  "properties": {
    "iso:country":"US",
    "sg:address":"6194 NW Pine Bridge Dr",
    "sg:city":"Arcadia",
    "sg:classifiers":[
        {
            "category":"Retail",
            "subcategory":"Repair Shop",
            "type":"Services"
        }
    ],
    "sg:phone":"+1 863 494 3442",
    "sg:postcode":"34266",
    "sg:province":"FL",
    "sg:tags":[
        "television",
        "radio"
    ],
    "wof:name":"T L Mc Donald Electronics",
    "wof:placetype":"venue"
},
  "geometry": {"coordinates":[-81.94278,27.22777],"type":"Point"}
}