{
  "type": "Feature",
  "properties": {
    "iso:country":"US",
    "sg:address":"2133 W Fairbanks Ave",
    "sg:city":"Winter Park",
    "sg:classifiers":[
        {
            "category":"Professional",
            "subcategory":"Accounting & Tax Preparation",
            "type":"Services"
        }
    ],
    "sg:phone":"+1 407 647 2101",
    "sg:postcode":"32789",
    "sg:province":"FL",
    "sg:tags":[
        "return",
        "filing"
    ],
    "wof:name":"John Mal Donado Pa",
    "wof:placetype":"venue"
},
  "geometry": {"coordinates":[-81.378412,28.593219],"type":"Point"}
}