{
  "type": "Feature",
  "properties": {
    "addr:full":"15888 SW 95th Ave Apt 203 Miami FL 33157",
    "addr:housenumber":"15888;203",
    "addr:postcode":"33157",
    "addr:street":"Sw 95Th Ave Apt",
    "iso:country":"US",
    "sg:address":"15888 SW 95th Ave Apt 203",
    "sg:city":"Miami",
    "sg:classifiers":[
        {
            "category":"Building & Trades",
            "subcategory":"Landscaping Services",
            "type":"Services"
        }
    ],
    "sg:phone":"+1 305 234 5204",
    "sg:postcode":"33157",
    "sg:province":"FL",
    "sg:tags":[
        "lawn"
    ],
    "wof:name":"Emmanuel Gardens",
    "wof:placetype":"venue"
},
  "geometry": {"coordinates":[-80.346394,25.620177],"type":"Point"}
}