{
  "type": "Feature",
  "properties": {
    "iso:country":"US",
    "sg:address":"2305 Charles Ct",
    "sg:city":"Tallahassee",
    "sg:classifiers":[
        {
            "category":"Professional",
            "type":"Services"
        }
    ],
    "sg:phone":"+1 850 385 4527",
    "sg:postcode":"32303",
    "sg:province":"FL",
    "wof:name":"Bradfordville Exchange Company",
    "wof:placetype":"venue"
},
  "geometry": {"coordinates":[-84.269263,30.474823],"type":"Point"}
}