{
  "type": "Feature",
  "properties": {
    "iso:country":"US",
    "sg:address":"14255 SW 73rd Ave",
    "sg:city":"Palmetto Bay",
    "sg:classifiers":[
        {
            "category":"Shopping",
            "subcategory":"Computers & Home Electronics",
            "type":"Retail Goods"
        }
    ],
    "sg:phone":"+1 305 253 3001",
    "sg:postcode":"33158",
    "sg:province":"FL",
    "sg:tags":[
        "equipment"
    ],
    "wof:name":"Jim Bozek",
    "wof:placetype":"venue"
},
  "geometry": {"coordinates":[-80.311302,25.6376],"type":"Point"}
}