{
  "type": "Feature",
  "properties": {
    "addr:full":"22025 Flanders Ct Boca Raton FL 33428",
    "addr:housenumber":"22025",
    "addr:postcode":"33428",
    "addr:street":"Flanders Ct",
    "iso:country":"US",
    "sg:address":"22025 Flanders Ct",
    "sg:city":"Boca Raton",
    "sg:classifiers":[
        {
            "category":"Restaurant",
            "type":"Food & Drink"
        }
    ],
    "sg:phone":"+1 561 482 9758",
    "sg:postcode":"33428",
    "sg:province":"FL",
    "sg:tags":[
        "eating"
    ],
    "wof:name":"Mouthful",
    "wof:placetype":"venue"
},
  "geometry": {"coordinates":[-80.208927,26.348618],"type":"Point"}
}