{
  "type": "Feature",
  "properties": {
    "iso:country":"US",
    "sg:address":"3978 Aenon Church Rd",
    "sg:city":"Tallahassee",
    "sg:classifiers":[
        {
            "category":"Communications",
            "type":"Services"
        }
    ],
    "sg:phone":"+1 850 575 8353",
    "sg:postcode":"32310",
    "sg:province":"FL",
    "wof:name":"Stoutamire Communications Inc",
    "wof:placetype":"venue"
},
  "geometry": {"coordinates":[-84.39770900000001,30.40412],"type":"Point"}
}