{
  "type": "Feature",
  "properties": {
    "addr:full":"3483 W Vine St Kissimmee FL 34741",
    "addr:housenumber":"3483",
    "addr:postcode":"34741",
    "addr:street":"W Vine St",
    "iso:country":"US",
    "sg:address":"3483 W Vine St",
    "sg:city":"Kissimmee",
    "sg:classifiers":[
        {
            "category":"Health Services",
            "subcategory":"Doctor",
            "type":"Services"
        }
    ],
    "sg:phone":"+1 407 932 2799",
    "sg:postcode":"34741",
    "sg:province":"FL",
    "sg:tags":[
        "physician",
        "surgeon"
    ],
    "wof:name":"Gerald Abraham MD",
    "wof:placetype":"venue"
},
  "geometry": {"coordinates":[-81.440826,28.304506],"type":"Point"}
}