{
  "type": "Feature",
  "properties": {
    "iso:country":"US",
    "sg:address":"1200 Anastasia Ave",
    "sg:city":"Miami",
    "sg:classifiers":[
        {
            "category":"Professional",
            "subcategory":"Management & Consulting",
            "type":"Services"
        }
    ],
    "sg:phone":"+1 305 445 1926",
    "sg:postcode":"33134",
    "sg:province":"FL",
    "wof:name":"Seaways Hotel Corp",
    "wof:placetype":"venue"
},
  "geometry": {"coordinates":[-80.278519,25.741423],"type":"Point"}
}