{
  "type": "Feature",
  "properties": {
    "addr:full":"115 W 22nd St Hialeah FL 33010",
    "addr:housenumber":"115",
    "addr:postcode":"33010",
    "addr:street":"W 22Nd St",
    "iso:country":"US",
    "sg:address":"115 W 22nd St",
    "sg:city":"Hialeah",
    "sg:classifiers":[
        {
            "category":"Autos & Motor Vehicles",
            "subcategory":"Auto Supplies",
            "type":"Retail Goods"
        },
        {
            "category":"Retail",
            "subcategory":"Auto Repair",
            "type":"Services"
        }
    ],
    "sg:phone":"+1 305 885 5415",
    "sg:postcode":"33010",
    "sg:province":"FL",
    "sg:tags":[
        "recap",
        "retread",
        "tire"
    ],
    "wof:name":"Fedan Tire Co",
    "wof:placetype":"venue"
},
  "geometry": {"coordinates":[-80.284401,25.841801],"type":"Point"}
}