{
  "type": "Feature",
  "properties": {
    "iso:country":"US",
    "sg:address":"338 Minorca Ave",
    "sg:city":"Coral Gables",
    "sg:classifiers":[
        {
            "category":"Professional",
            "subcategory":"Lawyer & Legal Services",
            "type":"Services"
        }
    ],
    "sg:phone":"+1 305 648 0708",
    "sg:postcode":"33134",
    "sg:province":"FL",
    "sg:tags":[
        "attorney"
    ],
    "wof:name":"Marlene Garcia",
    "wof:placetype":"venue"
},
  "geometry": {"coordinates":[-80.262159,25.753462],"type":"Point"}
}