{
  "type": "Feature",
  "properties": {
    "iso:country":"US",
    "sg:address":"432 W Boynton Beach Blvd",
    "sg:city":"Boynton Beach",
    "sg:classifiers":[
        {
            "category":"Manufacturing",
            "subcategory":"Printing",
            "type":"Manufacturing & Wholesale Goods"
        }
    ],
    "sg:phone":"+1 561 364 1583",
    "sg:postcode":"33435",
    "sg:province":"FL",
    "sg:tags":[
        "newspaper"
    ],
    "sg:website":"www.merchantsnews.com",
    "wof:name":"Merchant News",
    "wof:placetype":"venue"
},
  "geometry": {"coordinates":[-80.072452,26.528845],"type":"Point"}
}