{
  "type": "Feature",
  "properties": {
    "addr:full":"1069 N Collier Blvd Marco Island FL 34145",
    "addr:housenumber":"1069",
    "addr:postcode":"34145",
    "addr:street":"N Collier Blvd",
    "iso:country":"US",
    "sg:address":"1069 N Collier Blvd",
    "sg:city":"Marco Island",
    "sg:classifiers":[
        {
            "category":"Shopping",
            "subcategory":"Clothing, Apparel, & Fashions",
            "type":"Retail Goods"
        }
    ],
    "sg:phone":"+1 239 642 7777",
    "sg:postcode":"34145",
    "sg:province":"FL",
    "sg:tags":[
        "family",
        "store"
    ],
    "wof:name":"Beachworks",
    "wof:placetype":"venue"
},
  "geometry": {"coordinates":[-81.723966,25.954444],"type":"Point"}
}