{
  "type": "Feature",
  "properties": {
    "addr:full":"307 N Adams St Tallahassee FL 32301",
    "addr:housenumber":"307",
    "addr:postcode":"32301",
    "addr:street":"N Adams St",
    "iso:country":"US",
    "sg:address":"307 N Adams St",
    "sg:city":"Tallahassee",
    "sg:classifiers":[
        {
            "category":"Real Estate",
            "subcategory":"Real Estate Services",
            "type":"Services"
        },
        {
            "category":"Real Estate",
            "subcategory":"Real Estate Agent",
            "type":"Services"
        }
    ],
    "sg:phone":"+1 850 727 4891",
    "sg:postcode":"32301",
    "sg:province":"FL",
    "sg:tags":[
        "buyer",
        "broker",
        "auctioneer"
    ],
    "wof:name":"Southeast Realty & Auction",
    "wof:placetype":"venue"
},
  "geometry": {"coordinates":[-84.282014,30.444768],"type":"Point"}
}