{
  "type": "Feature",
  "properties": {
    "iso:country":"US",
    "sg:address":"4815 Sunfish Ct",
    "sg:city":"Fort Myers",
    "sg:classifiers":[
        {
            "category":"Building & Trades",
            "subcategory":"Construction",
            "type":"Services"
        }
    ],
    "sg:phone":"+1 239 466 8605",
    "sg:postcode":"33919",
    "sg:province":"FL",
    "sg:tags":[
        "contractor"
    ],
    "wof:name":"Solar Solutions",
    "wof:placetype":"venue"
},
  "geometry": {"coordinates":[-81.89787800000001,26.558445],"type":"Point"}
}