{
  "type": "Feature",
  "properties": {
    "addr:full":"4473 N Carl G Rose Hwy Hernando FL 34442",
    "addr:housenumber":"4473",
    "addr:postcode":"34442",
    "addr:street":"N Carl G Rose Hwy",
    "iso:country":"US",
    "sg:address":"4473 N Carl G Rose Hwy",
    "sg:city":"Hernando",
    "sg:classifiers":[
        {
            "category":"Restaurant",
            "type":"Food & Drink"
        }
    ],
    "sg:phone":"+1 352 344 3737",
    "sg:postcode":"34442",
    "sg:province":"FL",
    "wof:name":"Gennie D's",
    "wof:placetype":"venue"
},
  "geometry": {"coordinates":[-82.376738,28.928067],"type":"Point"}
}