{
  "type": "Feature",
  "properties": {
    "iso:country":"US",
    "sg:address":"132 W Colonial Dr",
    "sg:city":"Orlando",
    "sg:classifiers":[
        {
            "category":"Retail",
            "subcategory":"Driving School",
            "type":"Services"
        }
    ],
    "sg:phone":"+1 407 999 2676",
    "sg:postcode":"32801",
    "sg:province":"FL",
    "sg:tags":[
        "instruction",
        "traffic"
    ],
    "wof:name":"1st Orange County Traffic",
    "wof:placetype":"venue"
},
  "geometry": {"coordinates":[-81.381101,28.553121],"type":"Point"}
}