{
  "type": "Feature",
  "properties": {
    "iso:country":"US",
    "sg:address":"8687 W Irlo Bronson Memorial Hwy",
    "sg:city":"Kissimmee",
    "sg:classifiers":[
        {
            "category":"Restaurant",
            "type":"Food & Drink"
        }
    ],
    "sg:phone":"+1 407 238 0333",
    "sg:postcode":"34747",
    "sg:province":"FL",
    "wof:name":"Churchills",
    "wof:placetype":"venue"
},
  "geometry": {"coordinates":[-81.636121,28.346968],"type":"Point"}
}