{
  "type": "Feature",
  "properties": {
    "iso:country":"US",
    "sg:address":"2821 SW 8th St",
    "sg:city":"Fort Lauderdale",
    "sg:classifiers":[
        {
            "category":"Banks & Credit Unions",
            "subcategory":"Financial Services",
            "type":"Services"
        }
    ],
    "sg:phone":"+1 954 475 7247",
    "sg:postcode":"33312",
    "sg:province":"FL",
    "sg:tags":[
        "trust",
        "investment",
        "real estate"
    ],
    "wof:name":"Wiseberg Consolidated Inc",
    "wof:placetype":"venue"
},
  "geometry": {"coordinates":[-80.180927,26.111348],"type":"Point"}
}