{
  "type": "Feature",
  "properties": {
    "addr:full":"3416 Gulf Breeze Pkwy Gulf Breeze FL 32563",
    "addr:housenumber":"3416",
    "addr:postcode":"32563",
    "addr:street":"Gulf Breeze Pkwy",
    "iso:country":"US",
    "sg:address":"3416 Gulf Breeze Pkwy",
    "sg:city":"Gulf Breeze",
    "sg:classifiers":[
        {
            "category":"Building & Trades",
            "subcategory":"Construction",
            "type":"Services"
        }
    ],
    "sg:phone":"+1 850 932 7440",
    "sg:postcode":"32563",
    "sg:province":"FL",
    "sg:tags":[
        "masonry",
        "general",
        "contractor"
    ],
    "wof:name":"Sunchase Construction Co",
    "wof:placetype":"venue"
},
  "geometry": {"coordinates":[-87.077235,30.388227],"type":"Point"}
}