{
  "type": "Feature",
  "properties": {
    "addr:full":"29605 US Hwy 19 Clearwater FL 33761",
    "addr:postcode":"29605;33761",
    "addr:street":"Us Hwy 19",
    "iso:country":"US",
    "sg:address":"29605 US Hwy 19",
    "sg:city":"Clearwater",
    "sg:classifiers":[
        {
            "category":"Health Services",
            "subcategory":"Doctor",
            "type":"Services"
        }
    ],
    "sg:phone":"+1 727 786 6649",
    "sg:postcode":"33761",
    "sg:province":"FL",
    "wof:name":"A-One Dental",
    "wof:placetype":"venue"
},
  "geometry": {"coordinates":[-82.738356,28.040893],"type":"Point"}
}