{
  "type": "Feature",
  "properties": {
    "addr:full":"2520 Capital Cir SE Tallahassee FL 32311",
    "addr:housenumber":"2520",
    "addr:postcode":"32311",
    "addr:street":"Capital Cir Se",
    "iso:country":"US",
    "sg:address":"2520 Capital Cir SE",
    "sg:city":"Tallahassee",
    "sg:classifiers":[
        {
            "category":"Retail",
            "subcategory":"Veterinary Services",
            "type":"Services"
        }
    ],
    "sg:phone":"+1 850 942 6650",
    "sg:postcode":"32311",
    "sg:province":"FL",
    "sg:tags":[
        "veterinarian"
    ],
    "wof:name":"Seminole Animal Health Clinic",
    "wof:placetype":"venue"
},
  "geometry": {"coordinates":[-84.23506999999999,30.409],"type":"Point"}
}