{
  "type": "Feature",
  "properties": {
    "iso:country":"US",
    "sg:address":"1022 E Wade St",
    "sg:city":"Trenton",
    "sg:classifiers":[
        {
            "category":"Autos & Motor Vehicles",
            "subcategory":"Automobile Sales",
            "type":"Retail Goods"
        }
    ],
    "sg:phone":"+1 352 463 7886",
    "sg:postcode":"32693",
    "sg:province":"FL",
    "sg:tags":[
        "car",
        "dealer"
    ],
    "wof:name":"Sherwood Auto Sales",
    "wof:placetype":"venue"
},
  "geometry": {"coordinates":[-82.80889500000001,29.613412],"type":"Point"}
}