{
  "type": "Feature",
  "properties": {
    "iso:country":"US",
    "sg:address":"6 Pelican Dr",
    "sg:city":"Fort Lauderdale",
    "sg:classifiers":[
        {
            "category":"Building & Trades",
            "subcategory":"Equipment Rental",
            "type":"Services"
        }
    ],
    "sg:phone":"+1 954 524 9709",
    "sg:postcode":"33301",
    "sg:province":"FL",
    "wof:name":"Pelican Leasing Co",
    "wof:placetype":"venue"
},
  "geometry": {"coordinates":[-80.115337,26.123401],"type":"Point"}
}