{
  "type": "Feature",
  "properties": {
    "addr:full":"216 Florida Ave Cocoa FL 32922",
    "addr:housenumber":"216",
    "addr:postcode":"32922",
    "addr:street":"Florida Ave",
    "iso:country":"US",
    "sg:address":"216 Florida Ave",
    "sg:city":"Cocoa",
    "sg:classifiers":[
        {
            "category":"Professional",
            "subcategory":"Business Services",
            "type":"Services"
        }
    ],
    "sg:phone":"+1 321 433 0362",
    "sg:postcode":"32922",
    "sg:province":"FL",
    "sg:tags":[
        "information",
        "bureau",
        "convention"
    ],
    "wof:name":"Cocoa Village Welcome Center",
    "wof:placetype":"venue"
},
  "geometry": {"coordinates":[-80.72775900000001,28.355327],"type":"Point"}
}