{
  "type": "Feature",
  "properties": {
    "iso:country":"US",
    "sg:address":"12720 S Orange Blossom Trl",
    "sg:city":"Orlando",
    "sg:classifiers":[
        {
            "category":"Real Estate",
            "subcategory":"Real Estate Services",
            "type":"Services"
        }
    ],
    "sg:phone":"+1 407 816 7797",
    "sg:postcode":"32837",
    "sg:province":"FL",
    "sg:tags":[
        "company",
        "title"
    ],
    "wof:name":"Allied Abstract & Tile",
    "wof:placetype":"venue"
},
  "geometry": {"coordinates":[-81.40458599999999,28.377824],"type":"Point"}
}