{
  "type": "Feature",
  "properties": {
    "iso:country":"US",
    "sg:address":"2416 Okeechobee Rd",
    "sg:city":"Fort Pierce",
    "sg:classifiers":[
        {
            "category":"Food & Beverages",
            "subcategory":"Liquor & Beverages",
            "type":"Retail Goods"
        }
    ],
    "sg:phone":"+1 772 461 9525",
    "sg:postcode":"34950",
    "sg:province":"FL",
    "wof:name":"Princess Liquor Store",
    "wof:placetype":"venue"
},
  "geometry": {"coordinates":[-80.349222,27.438024],"type":"Point"}
}