{
  "type": "Feature",
  "properties": {
    "addr:full":"1101 Brickell Ave Ste 802 Miami FL 33131",
    "addr:housenumber":"1101",
    "addr:postcode":"33131",
    "addr:street":"Brickell Ave Ste 802",
    "iso:country":"US",
    "sg:address":"1101 Brickell Ave Ste 802",
    "sg:city":"Miami",
    "sg:classifiers":[
        {
            "category":"Health Services",
            "subcategory":"Dentist",
            "type":"Services"
        }
    ],
    "sg:phone":"+1 305 373 4950",
    "sg:postcode":"33131",
    "sg:province":"FL",
    "wof:name":"Adriana M Bove Dds",
    "wof:placetype":"venue"
},
  "geometry": {"coordinates":[-80.191351,25.763338],"type":"Point"}
}