{
  "type": "Feature",
  "properties": {
    "addr:full":"139 Aurora Ln Kissimmee FL 34758",
    "addr:housenumber":"139",
    "addr:postcode":"34758",
    "addr:street":"Aurora Ln",
    "iso:country":"US",
    "sg:address":"139 Aurora Ln",
    "sg:city":"Kissimmee",
    "sg:classifiers":[
        {
            "category":"Manufacturing",
            "subcategory":"Printing",
            "type":"Manufacturing & Wholesale Goods"
        }
    ],
    "sg:phone":"+1 407 932 3830",
    "sg:postcode":"34758",
    "sg:province":"FL",
    "sg:tags":[
        "printer"
    ],
    "wof:name":"Southern Business Forms Inc",
    "wof:placetype":"venue"
},
  "geometry": {"coordinates":[-81.48057900000001,28.161521],"type":"Point"}
}