{
  "type": "Feature",
  "properties": {
    "addr:full":"5001 Edgewater Dr Orlando FL 32810",
    "addr:housenumber":"5001",
    "addr:postcode":"32810",
    "addr:street":"Edgewater Dr",
    "iso:country":"US",
    "sg:address":"5001 Edgewater Dr",
    "sg:city":"Orlando",
    "sg:classifiers":[
        {
            "category":"Manufacturing",
            "subcategory":"Printing",
            "type":"Manufacturing & Wholesale Goods"
        }
    ],
    "sg:phone":"+1 407 290 5001",
    "sg:postcode":"32810",
    "sg:province":"FL",
    "sg:tags":[
        "lithographic",
        "commercial"
    ],
    "wof:name":"Orlando Offset",
    "wof:placetype":"venue"
},
  "geometry": {"coordinates":[-81.40821099999999,28.60466],"type":"Point"}
}