{
  "type": "Feature",
  "properties": {
    "iso:country":"US",
    "sg:address":"10014 N Dale Mabry Hwy",
    "sg:city":"Tampa",
    "sg:classifiers":[
        {
            "category":"Professional",
            "subcategory":"Employment Agencies",
            "type":"Services"
        }
    ],
    "sg:phone":"+1 813 269 9311",
    "sg:postcode":"33618",
    "sg:province":"FL",
    "sg:tags":[
        "opportunity"
    ],
    "wof:name":"Fountain Group The",
    "wof:placetype":"venue"
},
  "geometry": {"coordinates":[-82.50474699999999,28.043181],"type":"Point"}
}