{
  "type": "Feature",
  "properties": {
    "iso:country":"US",
    "sg:address":"115 Commerce Way",
    "sg:city":"Sanford",
    "sg:classifiers":[
        {
            "category":"Wholesale",
            "subcategory":"Construction Materials",
            "type":"Manufacturing & Wholesale Goods"
        }
    ],
    "sg:phone":"+1 407 323 0093",
    "sg:postcode":"32771",
    "sg:province":"FL",
    "sg:tags":[
        "carpentry",
        "contractor"
    ],
    "wof:name":"Southern Elite Cabinetry Inc",
    "wof:placetype":"venue"
},
  "geometry": {"coordinates":[-81.297003,28.797397],"type":"Point"}
}