{
  "type": "Feature",
  "properties": {
    "iso:country":"US",
    "sg:address":"176 175th Ter Dr",
    "sg:city":"Saint Petersburg",
    "sg:classifiers":[
        {
            "category":"Professional",
            "type":"Services"
        }
    ],
    "sg:phone":"+1 727 398 0863",
    "sg:postcode":"33708",
    "sg:province":"FL",
    "wof:name":"Susan Guise",
    "wof:placetype":"venue"
},
  "geometry": {"coordinates":[-82.82733899999999,27.824397],"type":"Point"}
}