{
  "type": "Feature",
  "properties": {
    "iso:country":"US",
    "sg:address":"4361 S Suncoast Blvd",
    "sg:city":"Homosassa",
    "sg:classifiers":[
        {
            "category":"Health Services",
            "subcategory":"Doctor",
            "type":"Services"
        },
        {
            "category":"Health Services",
            "subcategory":"Dentist",
            "type":"Services"
        }
    ],
    "sg:phone":"+1 352 628 7788",
    "sg:postcode":"34446",
    "sg:province":"FL",
    "sg:tags":[
        "dentists-oral",
        "physician",
        "maxillofacial",
        "surgeons",
        "surgery",
        "oral"
    ],
    "sg:website":"http://www.hanydmd.com",
    "wof:name":"Williams Hany Dmd Pa",
    "wof:placetype":"venue"
},
  "geometry": {"coordinates":[-82.57620300000001,28.798366],"type":"Point"}
}