{
  "type": "Feature",
  "properties": {
    "iso:country":"US",
    "sg:address":"710 Bragg Dr",
    "sg:city":"Tallahassee",
    "sg:classifiers":[
        {
            "category":"Professional",
            "type":"Services"
        }
    ],
    "sg:phone":"+1 850 576 8868",
    "sg:postcode":"32305",
    "sg:province":"FL",
    "wof:name":"Jumi Inc",
    "wof:placetype":"venue"
},
  "geometry": {"coordinates":[-84.295441,30.405139],"type":"Point"}
}