{
  "type": "Feature",
  "properties": {
    "iso:country":"US",
    "sg:address":"372 Marie Cir NW",
    "sg:city":"Fort Walton Bch",
    "sg:classifiers":[
        {
            "category":"Sports & Exercise",
            "subcategory":"Golf",
            "type":"Entertainment"
        }
    ],
    "sg:phone":"+1 850 243 6333",
    "sg:postcode":"32548",
    "sg:province":"FL",
    "sg:tags":[
        "course"
    ],
    "wof:name":"Arrowhead Junior Golf Tour",
    "wof:placetype":"venue"
},
  "geometry": {"coordinates":[-86.636762,30.416966],"type":"Point"}
}