{
  "type": "Feature",
  "properties": {
    "addr:full":"157 Maravilla Dr Destin FL 32550",
    "addr:housenumber":"157",
    "addr:postcode":"32550",
    "addr:street":"Maravilla Dr",
    "iso:country":"US",
    "sg:address":"157 Maravilla Dr",
    "sg:city":"Destin",
    "sg:classifiers":[
        {
            "category":"Professional",
            "type":"Services"
        }
    ],
    "sg:phone":"+1 850 650 3486",
    "sg:postcode":"32550",
    "sg:province":"FL",
    "wof:name":"Premier Vcation Resorts Destin",
    "wof:placetype":"venue"
},
  "geometry": {"coordinates":[-86.396233,30.380087],"type":"Point"}
}