{
  "type": "Feature",
  "properties": {
    "iso:country":"US",
    "sg:address":"909 N Wymore Rd",
    "sg:city":"Winter Park",
    "sg:classifiers":[
        {
            "category":"Health Services",
            "subcategory":"Nursing And Care Facility",
            "type":"Services"
        }
    ],
    "sg:phone":"+1 407 645 5515",
    "sg:postcode":"32789",
    "sg:province":"FL",
    "sg:tags":[
        "home",
        "retirement",
        "community"
    ],
    "wof:name":"Summer Time Resort Retirement",
    "wof:placetype":"venue"
},
  "geometry": {"coordinates":[-81.384861,28.609188],"type":"Point"}
}