{
  "type": "Feature",
  "properties": {
    "iso:country":"US",
    "sg:address":"1648 Main St",
    "sg:city":"Sarasota",
    "sg:classifiers":[
        {
            "category":"Shopping",
            "subcategory":"Hobbies, Toys, & Games",
            "type":"Retail Goods"
        }
    ],
    "sg:phone":"+1 941 906 8697",
    "sg:postcode":"34236",
    "sg:province":"FL",
    "wof:name":"TLC Toys",
    "wof:placetype":"venue"
},
  "geometry": {"coordinates":[-82.536767,27.33639],"type":"Point"}
}