{
  "type": "Feature",
  "properties": {
    "iso:country":"US",
    "sg:address":"2446 University Blvd W",
    "sg:city":"Jacksonville",
    "sg:classifiers":[
        {
            "category":"Personal",
            "subcategory":"Beauty Salon",
            "type":"Services"
        }
    ],
    "sg:phone":"+1 904 733 6000",
    "sg:postcode":"32217",
    "sg:province":"FL",
    "sg:tags":[
        "shop"
    ],
    "wof:name":"Beauty Palace",
    "wof:placetype":"venue"
},
  "geometry": {"coordinates":[-81.633404,30.260809],"type":"Point"}
}