{
  "type": "Feature",
  "properties": {
    "addr:full":"1403 W Saint Joseph Ave Pensacola FL 32501",
    "addr:housenumber":"1403",
    "addr:postcode":"32501",
    "addr:street":"W Saint Joseph Ave",
    "iso:country":"US",
    "sg:address":"1403 W Saint Joseph Ave",
    "sg:city":"Pensacola",
    "sg:classifiers":[
        {
            "category":"Education",
            "subcategory":"School",
            "type":"Public Place"
        }
    ],
    "sg:phone":"+1 850 595 6910",
    "sg:postcode":"32501",
    "sg:province":"FL",
    "wof:name":"Henry Mc Milan Comm Learning",
    "wof:placetype":"venue"
},
  "geometry": {"coordinates":[-87.235913,30.438459],"type":"Point"}
}