{
  "type": "Feature",
  "properties": {
    "addr:full":"4621 NE 15th Way Oakland Park FL 33334",
    "addr:housenumber":"4621",
    "addr:postcode":"33334",
    "addr:street":"Ne 15Th Way",
    "iso:country":"US",
    "sg:address":"4621 NE 15th Way",
    "sg:city":"Oakland Park",
    "sg:classifiers":[
        {
            "category":"Professional",
            "subcategory":"Engineering",
            "type":"Services"
        }
    ],
    "sg:phone":"+1 954 418 8384",
    "sg:postcode":"33334",
    "sg:province":"FL",
    "sg:tags":[
        "engineer"
    ],
    "wof:name":"Donald L Zurheide Inc",
    "wof:placetype":"venue"
},
  "geometry": {"coordinates":[-80.126592,26.184998],"type":"Point"}
}