{
  "type": "Feature",
  "properties": {
    "addr:full":"13432 Sunkiss Loop Windermere FL 34786",
    "addr:housenumber":"13432",
    "addr:postcode":"34786",
    "addr:street":"Sunkiss Loop",
    "iso:country":"US",
    "sg:address":"13432 Sunkiss Loop",
    "sg:city":"Windermere",
    "sg:classifiers":[
        {
            "category":"Government",
            "subcategory":"Post Office",
            "type":"Public Place"
        }
    ],
    "sg:phone":"+1 407 905 7870",
    "sg:postcode":"34786",
    "sg:province":"FL",
    "sg:tags":[
        "delivery",
        "courier"
    ],
    "wof:name":"Buddy's Service Company Inc",
    "wof:placetype":"venue"
},
  "geometry": {"coordinates":[-81.58439799999999,28.487981],"type":"Point"}
}