{
  "type": "Feature",
  "properties": {
    "addr:full":"300 S Coconut Palm Blvd Tavernier FL 33070",
    "addr:housenumber":"300",
    "addr:postcode":"33070",
    "addr:street":"S Coconut Palm Blvd",
    "iso:country":"US",
    "sg:address":"300 S Coconut Palm Blvd",
    "sg:city":"Tavernier",
    "sg:classifiers":[
        {
            "category":"Professional",
            "type":"Services"
        }
    ],
    "sg:phone":"+1 305 852 5784",
    "sg:postcode":"33070",
    "sg:province":"FL",
    "sg:tags":[
        "establishment"
    ],
    "wof:name":"Outdoor Systems",
    "wof:placetype":"venue"
},
  "geometry": {"coordinates":[-80.54105199999999,24.997109],"type":"Point"}
}