{
  "type": "Feature",
  "properties": {
    "iso:country":"US",
    "sg:address":"3942 Wd Judge Dr",
    "sg:city":"Orlando",
    "sg:classifiers":[
        {
            "category":"Personal",
            "type":"Services"
        }
    ],
    "sg:phone":"+1 321 276 4206",
    "sg:postcode":"32808",
    "sg:province":"FL",
    "sg:tags":[
        "butlers'",
        "maids'"
    ],
    "wof:name":"Cynthia Staffine Top Notch Clg",
    "wof:placetype":"venue"
},
  "geometry": {"coordinates":[-81.42921699999999,28.559816],"type":"Point"}
}