{
  "type": "Feature",
  "properties": {
    "addr:full":"5303 N Orange Blossom Trl Orlando FL 32810",
    "addr:housenumber":"5303",
    "addr:postcode":"32810",
    "addr:street":"N Orange Blossom Trl",
    "iso:country":"US",
    "sg:address":"5303 N Orange Blossom Trl",
    "sg:city":"Orlando",
    "sg:classifiers":[
        {
            "category":"Utilities",
            "subcategory":"Recycling",
            "type":"Services"
        }
    ],
    "sg:phone":"+1 407 296 0965",
    "sg:postcode":"32810",
    "sg:province":"FL",
    "sg:website":"http://www.southeastrecycling.com",
    "wof:name":"Orlando Division",
    "wof:placetype":"venue"
},
  "geometry": {"coordinates":[-81.423332,28.60713],"type":"Point"}
}