{
  "type": "Feature",
  "properties": {
    "addr:full":"2940 E Park Ave Tallahassee FL 32301",
    "addr:housenumber":"2940",
    "addr:postcode":"32301",
    "addr:street":"E Park Ave",
    "iso:country":"US",
    "sg:address":"2940 E Park Ave",
    "sg:city":"Tallahassee",
    "sg:classifiers":[
        {
            "category":"Real Estate",
            "subcategory":"Real Estate Agent",
            "type":"Services"
        }
    ],
    "sg:phone":"+1 850 575 4800",
    "sg:postcode":"32301",
    "sg:province":"FL",
    "sg:tags":[
        "appraiser"
    ],
    "wof:name":"Real Value Real Estate Svc Inc",
    "wof:placetype":"venue"
},
  "geometry": {"coordinates":[-84.24216199999999,30.441918],"type":"Point"}
}