{
  "type": "Feature",
  "properties": {
    "addr:full":"1900 N John Young Pkwy Kissimmee FL 34741",
    "addr:housenumber":"1900",
    "addr:postcode":"34741",
    "addr:street":"N John Young Pkwy",
    "iso:country":"US",
    "sg:address":"1900 N John Young Pkwy",
    "sg:city":"Kissimmee",
    "sg:classifiers":[
        {
            "category":"Organizations",
            "subcategory":"Religious Organization",
            "type":"Services"
        }
    ],
    "sg:phone":"+1 407 847 3978",
    "sg:postcode":"34741",
    "sg:province":"FL",
    "sg:tags":[
        "church"
    ],
    "wof:name":"Church Of Jesus Christ Of Lds",
    "wof:placetype":"venue"
},
  "geometry": {"coordinates":[-81.41581600000001,28.310052],"type":"Point"}
}