{
  "type": "Feature",
  "properties": {
    "addr:full":"442 E New York Ave Deland FL 32724",
    "addr:housenumber":"442",
    "addr:postcode":"32724",
    "addr:street":"E New York Ave",
    "iso:country":"US",
    "sg:address":"442 E New York Ave",
    "sg:city":"Deland",
    "sg:classifiers":[
        {
            "category":"Health Services",
            "subcategory":"Health Practitioner",
            "type":"Services"
        }
    ],
    "sg:phone":"+1 386 738 1085",
    "sg:postcode":"32724",
    "sg:province":"FL",
    "sg:tags":[
        "psychotherapist"
    ],
    "wof:name":"H Ken Mc Cullough",
    "wof:placetype":"venue"
},
  "geometry": {"coordinates":[-81.29624099999999,29.028029],"type":"Point"}
}