{
  "type": "Feature",
  "properties": {
    "iso:country":"US",
    "sg:address":"100 Powell Blvd",
    "sg:city":"Daytona Beach",
    "sg:classifiers":[
        {
            "category":"Real Estate",
            "subcategory":"Real Estate Operator",
            "type":"Services"
        }
    ],
    "sg:phone":"+1 386 274 2926",
    "sg:postcode":"32114",
    "sg:province":"FL",
    "sg:tags":[
        "apartment"
    ],
    "wof:name":"Indigo Plantation Apartments",
    "wof:placetype":"venue"
},
  "geometry": {"coordinates":[-81.090079,29.198145],"type":"Point"}
}