{
  "type": "Feature",
  "properties": {
    "iso:country":"US",
    "sg:address":"4410 W 16th Ave Ste 4",
    "sg:city":"Hialeah",
    "sg:classifiers":[
        {
            "category":"Personal",
            "subcategory":"Nail Salon",
            "type":"Services"
        }
    ],
    "sg:phone":"+1 305 823 3144",
    "sg:postcode":"33012",
    "sg:province":"FL",
    "wof:name":"Pro Nails 1",
    "wof:placetype":"venue"
},
  "geometry": {"coordinates":[-80.30390199999999,25.8647],"type":"Point"}
}