{
  "type": "Feature",
  "properties": {
    "addr:full":"274 Co Rd 54 Davenport FL 33896",
    "addr:housenumber":"274;54",
    "addr:postcode":"33896",
    "addr:street":"Co Rd",
    "iso:country":"US",
    "sg:address":"274 Co Rd 54",
    "sg:city":"Davenport",
    "sg:classifiers":[
        {
            "category":"Building & Trades",
            "subcategory":"Landscaping Services",
            "type":"Services"
        }
    ],
    "sg:phone":"+1 863 420 7184",
    "sg:postcode":"33896",
    "sg:province":"FL",
    "wof:name":"Ehe Landscaping Svc",
    "wof:placetype":"venue"
},
  "geometry": {"coordinates":[-81.561294,28.238671],"type":"Point"}
}