{
  "type": "Feature",
  "properties": {
    "iso:country":"US",
    "sg:address":"4714 Distribution Dr",
    "sg:city":"Tampa",
    "sg:classifiers":[
        {
            "category":"Wholesale",
            "subcategory":"Vending Machines",
            "type":"Manufacturing & Wholesale Goods"
        }
    ],
    "sg:phone":"+1 813 247 4277",
    "sg:postcode":"33605",
    "sg:province":"FL",
    "sg:tags":[
        "operator"
    ],
    "wof:name":"Paramount Automated Food Svcs",
    "wof:placetype":"venue"
},
  "geometry": {"coordinates":[-82.408137,27.956829],"type":"Point"}
}