{
  "type": "Feature",
  "properties": {
    "addr:full":"8000 Red Bug Lake Rd Oviedo FL 32765",
    "addr:housenumber":"8000",
    "addr:postcode":"32765",
    "addr:street":"Red Bug Lake Rd",
    "iso:country":"US",
    "sg:address":"8000 Red Bug Lake Rd",
    "sg:city":"Oviedo",
    "sg:classifiers":[
        {
            "category":"Health Services",
            "subcategory":"Hospital",
            "type":"Services"
        }
    ],
    "sg:phone":"+1 407 359 5211",
    "sg:postcode":"32765",
    "sg:province":"FL",
    "wof:name":"Florida Hospital Phys Therapy",
    "wof:placetype":"venue"
},
  "geometry": {"coordinates":[-81.23924100000001,28.656205],"type":"Point"}
}