{
  "type": "Feature",
  "properties": {
    "iso:country":"US",
    "sg:address":"8550 Old Winter Garden Rd",
    "sg:city":"Orlando",
    "sg:classifiers":[
        {
            "category":"Recreation",
            "subcategory":"Marina",
            "type":"Entertainment"
        }
    ],
    "sg:phone":"+1 407 295 5960",
    "sg:postcode":"32835",
    "sg:province":"FL",
    "sg:tags":[
        "operation"
    ],
    "wof:name":"AAA Mobile Storage",
    "wof:placetype":"venue"
},
  "geometry": {"coordinates":[-81.50118000000001,28.541375],"type":"Point"}
}