{
  "type": "Feature",
  "properties": {
    "iso:country":"US",
    "sg:address":"3618 Palmetto Ave",
    "sg:city":"Miami",
    "sg:classifiers":[
        {
            "category":"Professional",
            "subcategory":"Management & Consulting",
            "type":"Services"
        }
    ],
    "sg:phone":"+1 305 444 5495",
    "sg:postcode":"33133",
    "sg:province":"FL",
    "sg:tags":[
        "public",
        "relations"
    ],
    "wof:name":"Roca Inma Associates Inc",
    "wof:placetype":"venue"
},
  "geometry": {"coordinates":[-80.252932,25.722006],"type":"Point"}
}