{
  "type": "Feature",
  "properties": {
    "iso:country":"US",
    "sg:address":"225 Silas Phelps Ct",
    "sg:city":"Orlando",
    "sg:classifiers":[
        {
            "category":"Professional",
            "subcategory":"Testing Lab",
            "type":"Services"
        }
    ],
    "sg:phone":"+1 407 384 6306",
    "sg:postcode":"32828",
    "sg:province":"FL",
    "sg:tags":[
        "material"
    ],
    "wof:name":"Blount Eddy Current Svc Inc",
    "wof:placetype":"venue"
},
  "geometry": {"coordinates":[-81.19645300000001,28.541627],"type":"Point"}
}