{
  "type": "Feature",
  "properties": {
    "addr:full":"4328 Cypress Bay Ct Orlando FL 32822",
    "addr:housenumber":"4328",
    "addr:postcode":"32822",
    "addr:street":"Cypress Bay Ct",
    "iso:country":"US",
    "sg:address":"4328 Cypress Bay Ct",
    "sg:city":"Orlando",
    "sg:classifiers":[
        {
            "category":"Organizations",
            "subcategory":"Religious Organization",
            "type":"Services"
        }
    ],
    "sg:phone":"+1 407 208 0122",
    "sg:postcode":"32822",
    "sg:province":"FL",
    "sg:tags":[
        "church"
    ],
    "wof:name":"Trinity International Workshop",
    "wof:placetype":"venue"
},
  "geometry": {"coordinates":[-81.28470299999999,28.482894],"type":"Point"}
}