{
  "type": "Feature",
  "properties": {
    "addr:full":"2212 SW 13th St Gainesville FL 32608",
    "addr:housenumber":"2212",
    "addr:postcode":"32608",
    "addr:street":"Sw 13Th St",
    "iso:country":"US",
    "sg:address":"2212 SW 13th St",
    "sg:city":"Gainesville",
    "sg:classifiers":[
        {
            "category":"Bars & Pubs",
            "type":"Food & Drink"
        }
    ],
    "sg:phone":"+1 352 373 4388",
    "sg:postcode":"32608",
    "sg:province":"FL",
    "wof:name":"Trader's",
    "wof:placetype":"venue"
},
  "geometry": {"coordinates":[-82.339434,29.63363],"type":"Point"}
}