{
  "type": "Feature",
  "properties": {
    "iso:country":"US",
    "sg:address":"5200 NW 34 Ter",
    "sg:city":"Gainesville",
    "sg:classifiers":[
        {
            "category":"Shopping",
            "type":"Retail Goods"
        }
    ],
    "sg:phone":"+1 352 376 5246",
    "sg:postcode":"32605",
    "sg:province":"FL",
    "sg:tags":[
        "picture",
        "frame"
    ],
    "wof:name":"Lyndon Glassworks",
    "wof:placetype":"venue"
},
  "geometry": {"coordinates":[-82.372912,29.70312],"type":"Point"}
}