{
  "type": "Feature",
  "properties": {
    "iso:country":"US",
    "sg:address":"5203 S Kirkman Rd",
    "sg:city":"Orlando",
    "sg:classifiers":[
        {
            "category":"Restaurant",
            "type":"Food & Drink"
        }
    ],
    "sg:menulink":"http://www.allmenus.com/fl/southwest-orange/97252-ihop/menu/",
    "sg:phone":"+1 407 370 0597",
    "sg:postcode":"32819",
    "sg:province":"FL",
    "sg:tags":[
        "sandwich",
        "salad",
        "burger",
        "soup",
        "american",
        "steakhouse",
        "wrap"
    ],
    "wof:name":"IHOP",
    "wof:placetype":"venue"
},
  "geometry": {"coordinates":[-81.458162,28.486216],"type":"Point"}
}