{
  "type": "Feature",
  "properties": {
    "iso:country":"US",
    "sg:address":"6572 Cedar St",
    "sg:city":"Milton",
    "sg:classifiers":[
        {
            "category":"Building & Trades",
            "subcategory":"Construction",
            "type":"Services"
        }
    ],
    "sg:phone":"+1 850 623 4278",
    "sg:postcode":"32570",
    "sg:province":"FL",
    "sg:tags":[
        "siding",
        "contractor"
    ],
    "wof:name":"J & D Vinyl Siding",
    "wof:placetype":"venue"
},
  "geometry": {"coordinates":[-87.049537,30.64329],"type":"Point"}
}