{
  "type": "Feature",
  "properties": {
    "iso:country":"US",
    "sg:address":"3509 Trillium Ct",
    "sg:city":"Tallahassee",
    "sg:classifiers":[
        {
            "category":"Education",
            "subcategory":"Library",
            "type":"Public Place"
        }
    ],
    "sg:phone":"+1 850 668 6911",
    "sg:postcode":"32312",
    "sg:province":"FL",
    "wof:name":"Florida Library Association",
    "wof:placetype":"venue"
},
  "geometry": {"coordinates":[-84.26669800000001,30.502673],"type":"Point"}
}