{
  "type": "Feature",
  "properties": {
    "iso:country":"US",
    "sg:address":"4740 W Irlo Bronson Memorial Hwy",
    "sg:city":"Kissimmee",
    "sg:classifiers":[
        {
            "category":"Restaurant",
            "type":"Food & Drink"
        }
    ],
    "sg:menulink":"http://www.allmenus.com/fl/kissimmee/44256-capones-dinner--show/menu/",
    "sg:phone":"+1 407 397 2378",
    "sg:postcode":"34746",
    "sg:province":"FL",
    "sg:tags":[
        "american"
    ],
    "wof:name":"Capone's Dinner & Show",
    "wof:placetype":"venue"
},
  "geometry": {"coordinates":[-81.47085,28.32431],"type":"Point"}
}