{
  "type": "Feature",
  "properties": {
    "addr:full":"6354 Middlerow Ct Orlando FL 32819",
    "addr:housenumber":"6354",
    "addr:postcode":"32819",
    "addr:street":"Middlerow Ct",
    "iso:country":"US",
    "sg:address":"6354 Middlerow Ct",
    "sg:city":"Orlando",
    "sg:classifiers":[
        {
            "category":"Shopping",
            "subcategory":"Computers & Home Electronics",
            "type":"Retail Goods"
        }
    ],
    "sg:phone":"+1 407 352 7502",
    "sg:postcode":"32819",
    "sg:province":"FL",
    "sg:tags":[
        "software"
    ],
    "wof:name":"Deisseroth Inc",
    "wof:placetype":"venue"
},
  "geometry": {"coordinates":[-81.498212,28.470334],"type":"Point"}
}