{
  "type": "Feature",
  "properties": {
    "iso:country":"US",
    "sg:address":"7992 Parker Rd",
    "sg:city":"Milton",
    "sg:classifiers":[
        {
            "category":"Building & Trades",
            "subcategory":"Construction",
            "type":"Services"
        }
    ],
    "sg:phone":"+1 850 981 3413",
    "sg:postcode":"32570",
    "sg:province":"FL",
    "sg:tags":[
        "handyman"
    ],
    "wof:name":"Steven A Richmond Handyman",
    "wof:placetype":"venue"
},
  "geometry": {"coordinates":[-86.986538,30.673987],"type":"Point"}
}