{
  "type": "Feature",
  "properties": {
    "addr:full":"119 S Redland Rd Homestead FL 33034",
    "addr:housenumber":"119",
    "addr:postcode":"33034",
    "addr:street":"S Redland Rd",
    "iso:country":"US",
    "sg:address":"119 S Redland Rd",
    "sg:city":"Homestead",
    "sg:classifiers":[
        {
            "category":"Social Services",
            "subcategory":"Child Care",
            "type":"Services"
        }
    ],
    "sg:phone":"+1 305 242 4058",
    "sg:postcode":"33034",
    "sg:province":"FL",
    "wof:name":"Bloomin Babies Daycare",
    "wof:placetype":"venue"
},
  "geometry": {"coordinates":[-80.493289,25.443524],"type":"Point"}
}