{
  "type": "Feature",
  "properties": {
    "iso:country":"US",
    "sg:address":"1450 N Courtenay Pkwy",
    "sg:city":"Merritt Island",
    "sg:classifiers":[
        {
            "category":"Shopping",
            "type":"Retail Goods"
        }
    ],
    "sg:phone":"+1 321 452 0400",
    "sg:postcode":"32953",
    "sg:province":"FL",
    "sg:tags":[
        "merchandise"
    ],
    "wof:name":"Cingular Wireless",
    "wof:placetype":"venue"
},
  "geometry": {"coordinates":[-80.702685,28.384252],"type":"Point"}
}