{
  "type": "Feature",
  "properties": {
    "iso:country":"US",
    "sg:address":"7120 NW 11th Pl",
    "sg:city":"Gainesville",
    "sg:classifiers":[
        {
            "category":"Health Services",
            "subcategory":"Doctor",
            "type":"Services"
        }
    ],
    "sg:phone":"+1 352 331 8556",
    "sg:postcode":"32605",
    "sg:province":"FL",
    "sg:tags":[
        "medical"
    ],
    "wof:name":"Cardiology West",
    "wof:placetype":"venue"
},
  "geometry": {"coordinates":[-82.41826399999999,29.663553],"type":"Point"}
}