{
  "type": "Feature",
  "properties": {
    "addr:full":"1200 E Main St Pahokee FL 33476",
    "addr:housenumber":"1200",
    "addr:postcode":"33476",
    "addr:street":"E Main St",
    "iso:country":"US",
    "sg:address":"1200 E Main St",
    "sg:city":"Pahokee",
    "sg:classifiers":[
        {
            "category":"Place Of Worship",
            "subcategory":"Church",
            "type":"Public Place"
        },
        {
            "category":"Place Of Worship",
            "type":"Public Place"
        }
    ],
    "sg:phone":"+1 561 924 7305",
    "sg:postcode":"33476",
    "sg:province":"FL",
    "sg:tags":[
        "churches-catholic-traditional",
        "churches-catholic"
    ],
    "sg:website":"http://www.cardinalnewman.com",
    "wof:name":"St Mary's Catholic Church",
    "wof:placetype":"venue"
},
  "geometry": {"coordinates":[-80.65686599999999,26.82904],"type":"Point"}
}