{
  "type": "Feature",
  "properties": {
    "iso:country":"US",
    "sg:address":"1639 Palmetto Ln",
    "sg:city":"Sarasota",
    "sg:classifiers":[
        {
            "category":"Organizations",
            "subcategory":"Professional Association",
            "type":"Services"
        }
    ],
    "sg:phone":"+1 941 953 4057",
    "sg:postcode":"34236",
    "sg:province":"FL",
    "wof:name":"Tocobaga Association",
    "wof:placetype":"venue"
},
  "geometry": {"coordinates":[-82.54983799999999,27.352235],"type":"Point"}
}