{
  "type": "Feature",
  "properties": {
    "iso:country":"US",
    "sg:address":"622 SE 47th Ter",
    "sg:city":"Cape Coral",
    "sg:classifiers":[
        {
            "category":"Home & Garden",
            "subcategory":"Hardware",
            "type":"Retail Goods"
        }
    ],
    "sg:phone":"+1 239 542 6365",
    "sg:postcode":"33904",
    "sg:province":"FL",
    "sg:tags":[
        "store"
    ],
    "sg:website":"www.familyhardware.doitbest.com",
    "wof:name":"Family Hardware DO-It Express",
    "wof:placetype":"venue"
},
  "geometry": {"coordinates":[-81.960503,26.5637],"type":"Point"}
}