{
  "type": "Feature",
  "properties": {
    "addr:full":"100 S US Hwy 1 Vero Beach FL 32962",
    "addr:housenumber":"100",
    "addr:postcode":"32962",
    "addr:street":"S Us Hwy 1",
    "iso:country":"US",
    "sg:address":"100 S US Hwy 1",
    "sg:city":"Vero Beach",
    "sg:classifiers":[
        {
            "category":"Restaurant",
            "type":"Food & Drink"
        }
    ],
    "sg:phone":"+1 772 567 5444",
    "sg:postcode":"32962",
    "sg:province":"FL",
    "wof:name":"Hodges Restaurant",
    "wof:placetype":"venue"
},
  "geometry": {"coordinates":[-80.38172900000001,27.60322],"type":"Point"}
}