{
  "type": "Feature",
  "properties": {
    "iso:country":"US",
    "sg:address":"300 N Park Ave",
    "sg:city":"Winter Park",
    "sg:classifiers":[
        {
            "category":"Building & Trades",
            "subcategory":"Construction",
            "type":"Services"
        }
    ],
    "sg:phone":"+1 407 645 2021",
    "sg:postcode":"32789",
    "sg:province":"FL",
    "sg:tags":[
        "caulking",
        "contractor"
    ],
    "sg:website":"www.swpofflorida.com",
    "wof:name":"Structural Waterproofing Of Fl",
    "wof:placetype":"venue"
},
  "geometry": {"coordinates":[-81.35099099999999,28.600456],"type":"Point"}
}