{
  "type": "Feature",
  "properties": {
    "iso:country":"US",
    "sg:address":"1010 Ohio Ave",
    "sg:city":"Palm Harbor",
    "sg:classifiers":[
        {
            "category":"Personal",
            "subcategory":"Beauty Salon",
            "type":"Services"
        }
    ],
    "sg:phone":"+1 727 773 1691",
    "sg:postcode":"34683",
    "sg:province":"FL",
    "sg:tags":[
        "shop"
    ],
    "wof:name":"Rubys Cuttin Up",
    "wof:placetype":"venue"
},
  "geometry": {"coordinates":[-82.766086,28.073466],"type":"Point"}
}