{
  "type": "Feature",
  "properties": {
    "iso:country":"US",
    "sg:address":"1795 Old Moultrie Rd",
    "sg:city":"Saint Augustine",
    "sg:classifiers":[
        {
            "category":"Organizations",
            "subcategory":"Religious Organization",
            "type":"Services"
        }
    ],
    "sg:phone":"+1 904 825 3600",
    "sg:postcode":"32084",
    "sg:province":"FL",
    "wof:name":"Center For Positive Living",
    "wof:placetype":"venue"
},
  "geometry": {"coordinates":[-81.326334,29.872007],"type":"Point"}
}