{
  "type": "Feature",
  "properties": {
    "addr:full":"6613 SW 18th Ct Pompano Beach FL 33068",
    "addr:housenumber":"6613",
    "addr:postcode":"33068",
    "addr:street":"Sw 18Th Ct",
    "iso:country":"US",
    "sg:address":"6613 SW 18th Ct",
    "sg:city":"Pompano Beach",
    "sg:classifiers":[
        {
            "category":"Manufacturing",
            "subcategory":"Apparel",
            "type":"Manufacturing & Wholesale Goods"
        }
    ],
    "sg:phone":"+1 954 568 6617",
    "sg:postcode":"33068",
    "sg:province":"FL",
    "sg:tags":[
        "cap",
        "hat",
        "mfg"
    ],
    "wof:name":"Gee Gee Fashion",
    "wof:placetype":"venue"
},
  "geometry": {"coordinates":[-80.213881,26.204373],"type":"Point"}
}