{
  "type": "Feature",
  "properties": {
    "addr:full":"1301 N State Rd 7 Hollywood FL 33021",
    "addr:housenumber":"1301;7",
    "addr:postcode":"33021",
    "addr:street":"N State Rd",
    "iso:country":"US",
    "sg:address":"1301 N State Rd 7",
    "sg:city":"Hollywood",
    "sg:classifiers":[
        {
            "category":"Building & Trades",
            "subcategory":"Construction",
            "type":"Services"
        }
    ],
    "sg:phone":"+1 954 583 3555",
    "sg:postcode":"33021",
    "sg:province":"FL",
    "sg:tags":[
        "fence"
    ],
    "wof:name":"Cercas Isla Island Fence Inc",
    "wof:placetype":"venue"
},
  "geometry": {"coordinates":[-80.20806399999999,26.02219],"type":"Point"}
}