{
  "type": "Feature",
  "properties": {
    "addr:full":"13919 W Hillsborough Ave Tampa FL 33635",
    "addr:housenumber":"13919",
    "addr:postcode":"33635",
    "addr:street":"W Hillsborough Ave",
    "iso:country":"US",
    "sg:address":"13919 W Hillsborough Ave",
    "sg:city":"Tampa",
    "sg:classifiers":[
        {
            "category":"Food & Beverages",
            "subcategory":"Groceries & Convenience Stores",
            "type":"Retail Goods"
        }
    ],
    "sg:phone":"+1 813 855 7092",
    "sg:postcode":"33635",
    "sg:province":"FL",
    "wof:name":"7-Eleven",
    "wof:placetype":"venue"
},
  "geometry": {"coordinates":[-82.641187,28.031152],"type":"Point"}
}