{
  "type": "Feature",
  "properties": {
    "iso:country":"US",
    "sg:address":"735 Osceola Ave",
    "sg:city":"Lake Wales",
    "sg:classifiers":[
        {
            "category":"Building & Trades",
            "subcategory":"Landscaping Services",
            "type":"Services"
        }
    ],
    "sg:phone":"+1 863 676 8788",
    "sg:postcode":"33853",
    "sg:province":"FL",
    "sg:tags":[
        "lawn",
        "maintenance",
        "grounds"
    ],
    "wof:name":"Joe's Lawn Maintenance",
    "wof:placetype":"venue"
},
  "geometry": {"coordinates":[-81.57505399999999,27.909026],"type":"Point"}
}