{
  "type": "Feature",
  "properties": {
    "iso:country":"US",
    "sg:address":"3026 E Commercial Blvd",
    "sg:city":"Fort Lauderdale",
    "sg:classifiers":[
        {
            "category":"Restaurant",
            "type":"Food & Drink"
        }
    ],
    "sg:menulink":"http://www.allmenus.com/fl/fort-lauderdale/280029-sushi-za/menu/",
    "sg:phone":"+1 954 776 2802",
    "sg:postcode":"33308",
    "sg:province":"FL",
    "sg:tags":[
        "japanese",
        "asian"
    ],
    "wof:name":"Sushi Za",
    "wof:placetype":"venue"
},
  "geometry": {"coordinates":[-80.10738000000001,26.189678],"type":"Point"}
}