{
  "type": "Feature",
  "properties": {
    "addr:full":"10622 Bresslyn Blvd Orlando FL 32825",
    "addr:housenumber":"10622",
    "addr:postcode":"32825",
    "addr:street":"Bresslyn Blvd",
    "iso:country":"US",
    "sg:address":"10622 Bresslyn Blvd",
    "sg:city":"Orlando",
    "sg:classifiers":[
        {
            "category":"Building & Trades",
            "subcategory":"Construction",
            "type":"Services"
        }
    ],
    "sg:phone":"+1 407 273 4392",
    "sg:postcode":"32825",
    "sg:province":"FL",
    "sg:tags":[
        "carpentry",
        "contractor"
    ],
    "wof:name":"George E Schlobach",
    "wof:placetype":"venue"
},
  "geometry": {"coordinates":[-81.23045500000001,28.556962],"type":"Point"}
}