{
  "type": "Feature",
  "properties": {
    "iso:country":"US",
    "sg:address":"880 Oleander Way S",
    "sg:city":"South Pasadena",
    "sg:classifiers":[
        {
            "category":"Real Estate",
            "subcategory":"Real Estate Operator",
            "type":"Services"
        }
    ],
    "sg:phone":"+1 727 344 1491",
    "sg:postcode":"33707",
    "sg:province":"FL",
    "sg:tags":[
        "building",
        "apartment"
    ],
    "wof:name":"Bethany Towers",
    "wof:placetype":"venue"
},
  "geometry": {"coordinates":[-82.732505,27.761632],"type":"Point"}
}