{
  "type": "Feature",
  "properties": {
    "iso:country":"US",
    "sg:address":"9655 S Dixie Hwy Ste 302",
    "sg:city":"Miami",
    "sg:classifiers":[
        {
            "category":"Real Estate",
            "subcategory":"Real Estate Services",
            "type":"Services"
        },
        {
            "category":"Banks & Credit Unions",
            "subcategory":"Financial Services",
            "type":"Services"
        }
    ],
    "sg:phone":"+1 305 661 4722",
    "sg:postcode":"33156",
    "sg:province":"FL",
    "sg:tags":[
        "loan",
        "processing"
    ],
    "wof:name":"Trinity Mortage Corp",
    "wof:placetype":"venue"
},
  "geometry": {"coordinates":[-80.316419,25.680238],"type":"Point"}
}