{
  "type": "Feature",
  "properties": {
    "iso:country":"US",
    "sg:address":"9840 San Jose Blvd",
    "sg:city":"Jacksonville",
    "sg:classifiers":[
        {
            "category":"Restaurant",
            "type":"Food & Drink"
        }
    ],
    "sg:menulink":"http://www.allmenus.com/fl/jacksonville/156369-krystal-burgers/menu/",
    "sg:phone":"+1 904 292 4825",
    "sg:postcode":"32257",
    "sg:province":"FL",
    "sg:tags":[
        "burger",
        "chicken",
        "american"
    ],
    "wof:name":"Krystal Burgers",
    "wof:placetype":"venue"
},
  "geometry": {"coordinates":[-81.620861,30.198811],"type":"Point"}
}