{
  "type": "Feature",
  "properties": {
    "addr:full":"10605 S 228th Ln Boca Raton FL 33428",
    "addr:housenumber":"10605",
    "addr:postcode":"33428",
    "addr:street":"S 228Th Ln",
    "iso:country":"US",
    "sg:address":"10605 S 228th Ln",
    "sg:city":"Boca Raton",
    "sg:classifiers":[
        {
            "category":"Shopping",
            "subcategory":"Clothing, Apparel, & Fashions",
            "type":"Retail Goods"
        }
    ],
    "sg:phone":"+1 561 483 8890",
    "sg:postcode":"33428",
    "sg:province":"FL",
    "wof:name":"Crown Jewels",
    "wof:placetype":"venue"
},
  "geometry": {"coordinates":[-80.212839,26.335973],"type":"Point"}
}