{
  "type": "Feature",
  "properties": {
    "iso:country":"US",
    "sg:address":"2023 E Silver Springs Blvd",
    "sg:city":"Ocala",
    "sg:classifiers":[
        {
            "category":"Shopping",
            "subcategory":"Music",
            "type":"Retail Goods"
        }
    ],
    "sg:phone":"+1 352 867 7999",
    "sg:postcode":"34470",
    "sg:province":"FL",
    "wof:name":"Specs 33",
    "wof:placetype":"venue"
},
  "geometry": {"coordinates":[-82.11630599999999,29.187105],"type":"Point"}
}