{
  "type": "Feature",
  "properties": {
    "iso:country":"US",
    "sg:address":"209 Phipps Plz",
    "sg:city":"Palm Beach",
    "sg:classifiers":[
        {
            "category":"Professional",
            "subcategory":"Business Services",
            "type":"Services"
        }
    ],
    "sg:phone":"+1 561 659 6255",
    "sg:postcode":"33480",
    "sg:province":"FL",
    "sg:tags":[
        "interior",
        "decorating",
        "design"
    ],
    "wof:name":"Scott Snyder Inc",
    "wof:placetype":"venue"
},
  "geometry": {"coordinates":[-80.036643,26.706615],"type":"Point"}
}