{
  "type": "Feature",
  "properties": {
    "addr:full":"7340 Woodland Creek Ln Lake Worth FL 33467",
    "addr:housenumber":"7340",
    "addr:postcode":"33467",
    "addr:street":"Woodland Creek Ln",
    "iso:country":"US",
    "sg:address":"7340 Woodland Creek Ln",
    "sg:city":"Lake Worth",
    "sg:classifiers":[
        {
            "category":"Real Estate",
            "subcategory":"Real Estate Agent",
            "type":"Services"
        }
    ],
    "sg:phone":"+1 561 968 8834",
    "sg:postcode":"33467",
    "sg:province":"FL",
    "wof:name":"Pickard Realty Group Inc",
    "wof:placetype":"venue"
},
  "geometry": {"coordinates":[-80.162217,26.587483],"type":"Point"}
}