{
  "type": "Feature",
  "properties": {
    "iso:country":"US",
    "sg:address":"100 S Colorado Ave",
    "sg:city":"Stuart",
    "sg:classifiers":[
        {
            "category":"Social Services",
            "type":"Services"
        }
    ],
    "sg:phone":"+1 772 286 6068",
    "sg:postcode":"34994",
    "sg:province":"FL",
    "wof:name":"Cpr & First Aid Specialists",
    "wof:placetype":"venue"
},
  "geometry": {"coordinates":[-80.25275499999999,27.19973],"type":"Point"}
}