{
  "type": "Feature",
  "properties": {
    "addr:full":"5430 Eagles Point Cir Sarasota FL 34231",
    "addr:housenumber":"5430",
    "addr:postcode":"34231",
    "addr:street":"Eagles Point Cir",
    "iso:country":"US",
    "sg:address":"5430 Eagles Point Cir",
    "sg:city":"Sarasota",
    "sg:classifiers":[
        {
            "category":"Real Estate",
            "subcategory":"Real Estate Operator",
            "type":"Services"
        }
    ],
    "sg:phone":"+1 941 927 8509",
    "sg:postcode":"34231",
    "sg:province":"FL",
    "sg:tags":[
        "condominium"
    ],
    "wof:name":"Eagles Point II Condo",
    "wof:placetype":"venue"
},
  "geometry": {"coordinates":[-82.53699400000001,27.272266],"type":"Point"}
}