{
  "type": "Feature",
  "properties": {
    "iso:country":"US",
    "sg:address":"320 NW 32nd Pl",
    "sg:city":"Miami",
    "sg:classifiers":[
        {
            "category":"Social Services",
            "subcategory":"Retirement Home",
            "type":"Services"
        }
    ],
    "sg:phone":"+1 786 506 4137",
    "sg:postcode":"33125",
    "sg:province":"FL",
    "sg:tags":[
        "convalescent",
        "nursing"
    ],
    "wof:name":"M & M Rehabilitation Center Inc",
    "wof:placetype":"venue"
},
  "geometry": {"coordinates":[-80.24906799999999,25.775705],"type":"Point"}
}