{
  "type": "Feature",
  "properties": {
    "iso:country":"US",
    "sg:address":"1316 W Adams St",
    "sg:city":"Jacksonville",
    "sg:classifiers":[
        {
            "category":"Autos & Motor Vehicles",
            "subcategory":"Auto Supplies",
            "type":"Retail Goods"
        }
    ],
    "sg:phone":"+1 904 354 4508",
    "sg:postcode":"32204",
    "sg:province":"FL",
    "sg:tags":[
        "battery"
    ],
    "sg:website":"www.sunnbattery.com",
    "wof:name":"Sunn Battery Co",
    "wof:placetype":"venue"
},
  "geometry": {"coordinates":[-81.676745,30.331943],"type":"Point"}
}