{
  "type": "Feature",
  "properties": {
    "addr:full":"1825 Bronson Pl Odessa FL 33556",
    "addr:housenumber":"1825",
    "addr:postcode":"33556",
    "addr:street":"Bronson Pl",
    "iso:country":"US",
    "sg:address":"1825 Bronson Pl",
    "sg:city":"Odessa",
    "sg:classifiers":[
        {
            "category":"Freight",
            "type":"Transportation"
        }
    ],
    "sg:phone":"+1 813 920 3617",
    "sg:postcode":"33556",
    "sg:province":"FL",
    "sg:tags":[
        "trucking"
    ],
    "wof:name":"Nitak Transport Svc",
    "wof:placetype":"venue"
},
  "geometry": {"coordinates":[-82.56816000000001,28.184536],"type":"Point"}
}