{
  "type": "Feature",
  "properties": {
    "addr:full":"1104 S Miller Rd Valrico FL 33594",
    "addr:housenumber":"1104",
    "addr:postcode":"33594",
    "addr:street":"S Miller Rd",
    "iso:country":"US",
    "sg:address":"1104 S Miller Rd",
    "sg:city":"Valrico",
    "sg:classifiers":[
        {
            "category":"Social Services",
            "subcategory":"Child Care",
            "type":"Services"
        }
    ],
    "sg:phone":"+1 813 685 5175",
    "sg:postcode":"33594",
    "sg:province":"FL",
    "wof:name":"Thompson's Child Care",
    "wof:placetype":"venue"
},
  "geometry": {"coordinates":[-82.244557,27.920826],"type":"Point"}
}