{
  "type": "Feature",
  "properties": {
    "iso:country":"US",
    "sg:address":"187 W Madison St",
    "sg:city":"Lake City",
    "sg:classifiers":[
        {
            "category":"Banks & Credit Unions",
            "subcategory":"Bank",
            "type":"Services"
        }
    ],
    "sg:phone":"+1 386 758 8775",
    "sg:postcode":"32055",
    "sg:province":"FL",
    "sg:tags":[
        "loan",
        "real estate"
    ],
    "wof:name":"City One Mortgage Bankers",
    "wof:placetype":"venue"
},
  "geometry": {"coordinates":[-82.638616,30.190771],"type":"Point"}
}