{
  "type": "Feature",
  "properties": {
    "iso:country":"US",
    "sg:address":"2812 Abney Ave",
    "sg:city":"Orlando",
    "sg:classifiers":[
        {
            "category":"Professional",
            "subcategory":"Detective & Security Services",
            "type":"Services"
        }
    ],
    "sg:phone":"+1 407 568 1283",
    "sg:postcode":"32833",
    "sg:province":"FL",
    "sg:tags":[
        "information",
        "bureau"
    ],
    "wof:name":"Vip Vacation Services Inc",
    "wof:placetype":"venue"
},
  "geometry": {"coordinates":[-81.064628,28.505502],"type":"Point"}
}