{
  "type": "Feature",
  "properties": {
    "iso:country":"US",
    "sg:address":"3833 SW 87th Pl",
    "sg:city":"Miami",
    "sg:classifiers":[
        {
            "category":"Communications",
            "subcategory":"Film & Video Production",
            "type":"Services"
        }
    ],
    "sg:phone":"+1 305 229 0933",
    "sg:postcode":"33165",
    "sg:province":"FL",
    "sg:tags":[
        "tv",
        "radio",
        "services-commercial",
        "companies-film"
    ],
    "wof:name":"Double J Outdoor Production",
    "wof:placetype":"venue"
},
  "geometry": {"coordinates":[-80.337361,25.734589],"type":"Point"}
}