{
  "type": "Feature",
  "properties": {
    "addr:full":"3090 Aloma Ave Winter Park FL 32792",
    "addr:housenumber":"3090",
    "addr:postcode":"32792",
    "addr:street":"Aloma Ave",
    "iso:country":"US",
    "sg:address":"3090 Aloma Ave",
    "sg:city":"Winter Park",
    "sg:classifiers":[
        {
            "category":"Restaurant",
            "type":"Food & Drink"
        }
    ],
    "sg:menulink":"http://www.allmenus.com/fl/orlando/35584-china-buffet/menu/",
    "sg:phone":"+1 407 679 8866",
    "sg:postcode":"32792",
    "sg:province":"FL",
    "sg:tags":[
        "asian",
        "chinese"
    ],
    "wof:name":"China Buffet",
    "wof:placetype":"venue"
},
  "geometry": {"coordinates":[-81.30849600000001,28.603308],"type":"Point"}
}