{
  "type": "Feature",
  "properties": {
    "iso:country":"US",
    "sg:address":"4908 NW 34th St Ste 1",
    "sg:city":"Gainesville",
    "sg:classifiers":[
        {
            "category":"Insurance",
            "subcategory":"Insurance Agent",
            "type":"Services"
        },
        {
            "category":"Insurance",
            "subcategory":"Hazard Insurance",
            "type":"Services"
        }
    ],
    "sg:phone":"+1 352 375 6317",
    "sg:postcode":"32605",
    "sg:province":"FL",
    "sg:tags":[
        "auto",
        "recreational",
        "motorcycle",
        "vehicle",
        "marine",
        "boat"
    ],
    "wof:name":"Edge & Associates, Inc.",
    "wof:placetype":"venue"
},
  "geometry": {"coordinates":[-82.370946,29.699622],"type":"Point"}
}