{
  "type": "Feature",
  "properties": {
    "iso:country":"US",
    "sg:address":"518 N Lake St",
    "sg:city":"Crescent City",
    "sg:classifiers":[
        {
            "category":"Health Services",
            "subcategory":"Doctor",
            "type":"Services"
        }
    ],
    "sg:phone":"+1 386 698 4225",
    "sg:postcode":"32112",
    "sg:province":"FL",
    "sg:tags":[
        "medical"
    ],
    "wof:name":"Love Paula K M D P A Inc",
    "wof:placetype":"venue"
},
  "geometry": {"coordinates":[-81.50718999999999,29.438895],"type":"Point"}
}