{
  "type": "Feature",
  "properties": {
    "addr:full":"1217 Robie Ave Mount Dora FL 32757",
    "addr:housenumber":"1217",
    "addr:postcode":"32757",
    "addr:street":"Robie Ave",
    "iso:country":"US",
    "sg:address":"1217 Robie Ave",
    "sg:city":"Mount Dora",
    "sg:classifiers":[
        {
            "category":"Manufacturing",
            "subcategory":"Tools & Machinery",
            "type":"Manufacturing & Wholesale Goods"
        }
    ],
    "sg:phone":"+1 352 735 5070",
    "sg:postcode":"32757",
    "sg:province":"FL",
    "sg:tags":[
        "power",
        "mfg"
    ],
    "wof:name":"T C T Manufacturing",
    "wof:placetype":"venue"
},
  "geometry": {"coordinates":[-81.632819,28.78963],"type":"Point"}
}