{
  "type": "Feature",
  "properties": {
    "iso:country":"US",
    "sg:address":"14102 Stonebrook Ct",
    "sg:city":"Tampa",
    "sg:classifiers":[
        {
            "category":"Education",
            "subcategory":"Dance Studio",
            "type":"Public Place"
        },
        {
            "category":"Arts & Performance",
            "subcategory":"Theater",
            "type":"Entertainment"
        }
    ],
    "sg:phone":"+1 813 960 5136",
    "sg:postcode":"33624",
    "sg:province":"FL",
    "sg:tags":[
        "instruction",
        "group",
        "dancing"
    ],
    "wof:name":"Afet Classic Belly Dancing",
    "wof:placetype":"venue"
},
  "geometry": {"coordinates":[-82.535152,28.080401],"type":"Point"}
}