{
  "type": "Feature",
  "properties": {
    "iso:country":"US",
    "sg:address":"14736 SW 174th St",
    "sg:city":"Miami",
    "sg:classifiers":[
        {
            "category":"Health Services",
            "subcategory":"Clinic",
            "type":"Services"
        }
    ],
    "sg:phone":"+1 305 254 9483",
    "sg:postcode":"33187",
    "sg:province":"FL",
    "sg:tags":[
        "testing",
        "diagnostic"
    ],
    "wof:name":"Fla Nr-Dgnostic Specialty Inc",
    "wof:placetype":"venue"
},
  "geometry": {"coordinates":[-80.4312,25.605007],"type":"Point"}
}