{
  "type": "Feature",
  "properties": {
    "addr:full":"7100 Bird Rd Miami FL 33155",
    "addr:housenumber":"7100",
    "addr:postcode":"33155",
    "addr:street":"Bird Rd",
    "iso:country":"US",
    "sg:address":"7100 Bird Rd",
    "sg:city":"Miami",
    "sg:classifiers":[
        {
            "category":"Restaurant",
            "type":"Food & Drink"
        }
    ],
    "sg:menulink":"http://www.allmenus.com/fl/miami/122770-quiznos-sub/menu/",
    "sg:phone":"+1 305 665 4595",
    "sg:postcode":"33155",
    "sg:province":"FL",
    "sg:tags":[
        "wrap",
        "american",
        "sandwich"
    ],
    "wof:name":"Quiznos Sub",
    "wof:placetype":"venue"
},
  "geometry": {"coordinates":[-80.309478,25.732977],"type":"Point"}
}