{
  "type": "Feature",
  "properties": {
    "iso:country":"US",
    "sg:address":"8289 Normandy Blvd",
    "sg:city":"Jacksonville",
    "sg:classifiers":[
        {
            "category":"Autos & Motor Vehicles",
            "subcategory":"Fuel & Gas Station",
            "type":"Retail Goods"
        }
    ],
    "sg:phone":"+1 904 378 1327",
    "sg:postcode":"32221",
    "sg:province":"FL",
    "sg:tags":[
        "oil"
    ],
    "wof:name":"J & J Food Mart",
    "wof:placetype":"venue"
},
  "geometry": {"coordinates":[-81.787762,30.290489],"type":"Point"}
}