{
  "type": "Feature",
  "properties": {
    "iso:country":"US",
    "sg:address":"1060 Scarlet Oak St",
    "sg:city":"Hollywood",
    "sg:classifiers":[
        {
            "category":"Professional",
            "subcategory":"Business Services",
            "type":"Services"
        }
    ],
    "sg:phone":"+1 954 925 2999",
    "sg:postcode":"33019",
    "sg:province":"FL",
    "sg:tags":[
        "distributor",
        "machine",
        "automatic",
        "teller"
    ],
    "wof:name":"Merchants ATM Network Inc",
    "wof:placetype":"venue"
},
  "geometry": {"coordinates":[-80.12719199999999,26.019869],"type":"Point"}
}