{
  "type": "Feature",
  "properties": {
    "addr:full":"1725 State Hwy 60 Valrico FL 33594",
    "addr:housenumber":"1725",
    "addr:postcode":"33594",
    "addr:street":"State Hwy 60",
    "iso:country":"US",
    "sg:address":"1725 State Hwy 60",
    "sg:city":"Valrico",
    "sg:classifiers":[
        {
            "category":"Real Estate",
            "subcategory":"Real Estate Agent",
            "type":"Services"
        }
    ],
    "sg:phone":"+1 813 689 2121",
    "sg:postcode":"33594",
    "sg:province":"FL",
    "wof:name":"Century 21",
    "wof:placetype":"venue"
},
  "geometry": {"coordinates":[-82.259598,27.93779],"type":"Point"}
}