{
  "type": "Feature",
  "properties": {
    "iso:country":"US",
    "sg:address":"5258 Btc Pl",
    "sg:city":"Kissimmee",
    "sg:classifiers":[
        {
            "category":"Manufacturing",
            "subcategory":"Buildings",
            "type":"Manufacturing & Wholesale Goods"
        },
        {
            "category":"Wholesale",
            "subcategory":"Durable Goods & Equipment",
            "type":"Manufacturing & Wholesale Goods"
        }
    ],
    "sg:phone":"+1 407 933 0044",
    "sg:postcode":"34758",
    "sg:province":"FL",
    "sg:tags":[
        "manufacture",
        "supply",
        "motel",
        "hotel",
        "inns-equipment",
        "supply-wholesale",
        "hotels"
    ],
    "wof:name":"Pv Suppliers To The Hospitality Industry, Inc.",
    "wof:placetype":"venue"
},
  "geometry": {"coordinates":[-81.494344,28.246119],"type":"Point"}
}