{
  "type": "Feature",
  "properties": {
    "iso:country":"US",
    "sg:address":"2740 NW 112th Ave",
    "sg:city":"Doral",
    "sg:classifiers":[
        {
            "category":"Real Estate",
            "subcategory":"Real Estate Services",
            "type":"Services"
        }
    ],
    "sg:phone":"+1 305 597 7113",
    "sg:postcode":"33172",
    "sg:province":"FL",
    "wof:name":"Soeber Real Estate",
    "wof:placetype":"venue"
},
  "geometry": {"coordinates":[-80.377197,25.799601],"type":"Point"}
}