{
  "type": "Feature",
  "properties": {
    "iso:country":"US",
    "sg:address":"1110 Old Dixie Hwy",
    "sg:city":"Vero Beach",
    "sg:classifiers":[
        {
            "category":"Freight",
            "type":"Transportation"
        }
    ],
    "sg:phone":"+1 772 567 6137",
    "sg:postcode":"32960",
    "sg:province":"FL",
    "sg:tags":[
        "commercial",
        "storage"
    ],
    "wof:name":"Dixie Properties",
    "wof:placetype":"venue"
},
  "geometry": {"coordinates":[-80.392961,27.619936],"type":"Point"}
}