{
  "type": "Feature",
  "properties": {
    "iso:country":"US",
    "sg:address":"4900 E Lake Dr",
    "sg:city":"Winter Springs",
    "sg:classifiers":[
        {
            "category":"Professional",
            "subcategory":"Art Services",
            "type":"Services"
        }
    ],
    "sg:phone":"+1 407 679 4876",
    "sg:postcode":"32708",
    "sg:province":"FL",
    "sg:tags":[
        "graphic",
        "designer"
    ],
    "wof:name":"Rushing & Assoc Design",
    "wof:placetype":"venue"
},
  "geometry": {"coordinates":[-81.28652599999999,28.669931],"type":"Point"}
}