{
  "type": "Feature",
  "properties": {
    "iso:country":"US",
    "sg:address":"40 Coolidge Ave",
    "sg:city":"Ormond Beach",
    "sg:classifiers":[
        {
            "category":"Manufacturing",
            "subcategory":"Signs",
            "type":"Manufacturing & Wholesale Goods"
        }
    ],
    "sg:phone":"+1 386 671 9608",
    "sg:postcode":"32174",
    "sg:province":"FL",
    "wof:name":"Sign FX",
    "wof:placetype":"venue"
},
  "geometry": {"coordinates":[-81.05974399999999,29.271945],"type":"Point"}
}