{
  "type": "Feature",
  "properties": {
    "iso:country":"US",
    "sg:address":"1014 Barnett St",
    "sg:city":"Pensacola",
    "sg:classifiers":[
        {
            "category":"Building & Trades",
            "subcategory":"Construction",
            "type":"Services"
        }
    ],
    "sg:phone":"+1 850 433 7967",
    "sg:postcode":"32505",
    "sg:province":"FL",
    "sg:tags":[
        "water",
        "restoration",
        "damage"
    ],
    "wof:name":"RWMS Group",
    "wof:placetype":"venue"
},
  "geometry": {"coordinates":[-87.245803,30.469466],"type":"Point"}
}