{
  "type": "Feature",
  "properties": {
    "addr:full":"156 Florida Ave Tavernier FL 33070",
    "addr:housenumber":"156",
    "addr:postcode":"33070",
    "addr:street":"Florida Ave",
    "iso:country":"US",
    "sg:address":"156 Florida Ave",
    "sg:city":"Tavernier",
    "sg:classifiers":[
        {
            "category":"Autos & Motor Vehicles",
            "subcategory":"Boat Sales",
            "type":"Retail Goods"
        },
        {
            "category":"Recreation",
            "subcategory":"Marina",
            "type":"Entertainment"
        }
    ],
    "sg:phone":"+1 305 852 4198",
    "sg:postcode":"33070",
    "sg:province":"FL",
    "sg:tags":[
        "repairing"
    ],
    "wof:name":"Joe's Boatworks",
    "wof:placetype":"venue"
},
  "geometry": {"coordinates":[-80.51804799999999,25.009363],"type":"Point"}
}