{
  "type": "Feature",
  "properties": {
    "addr:full":"16924 NE 19th Ave North Miami Bch FL 33162",
    "addr:housenumber":"16924",
    "addr:postcode":"33162",
    "addr:street":"Ne 19Th Ave",
    "iso:country":"US",
    "sg:address":"16924 NE 19th Ave",
    "sg:city":"North Miami Bch",
    "sg:classifiers":[
        {
            "category":"Wholesale",
            "subcategory":"Stationery",
            "type":"Manufacturing & Wholesale Goods"
        }
    ],
    "sg:phone":"+1 305 944 6800",
    "sg:postcode":"33162",
    "sg:province":"FL",
    "sg:tags":[
        "business",
        "form",
        "system"
    ],
    "wof:name":"Premier Auto Forms",
    "wof:placetype":"venue"
},
  "geometry": {"coordinates":[-80.16233,25.932107],"type":"Point"}
}