{
  "type": "Feature",
  "properties": {
    "iso:country":"US",
    "sg:address":"222 NW 21 Ave",
    "sg:city":"Gainesville",
    "sg:classifiers":[
        {
            "category":"Building & Trades",
            "subcategory":"Cleaning & Sanitation",
            "type":"Services"
        }
    ],
    "sg:phone":"+1 352 367 4484",
    "sg:postcode":"32609",
    "sg:province":"FL",
    "sg:tags":[
        "maintenance"
    ],
    "wof:name":"Annette Thomas",
    "wof:placetype":"venue"
},
  "geometry": {"coordinates":[-82.327949,29.671976],"type":"Point"}
}