{
  "type": "Feature",
  "properties": {
    "addr:full":"5719 E Longboat Blvd Tampa FL 33615",
    "addr:housenumber":"5719",
    "addr:postcode":"33615",
    "addr:street":"E Longboat Blvd",
    "iso:country":"US",
    "sg:address":"5719 E Longboat Blvd",
    "sg:city":"Tampa",
    "sg:classifiers":[
        {
            "category":"Professional",
            "subcategory":"Management & Consulting",
            "type":"Services"
        }
    ],
    "sg:phone":"+1 813 818 8888",
    "sg:postcode":"33615",
    "sg:province":"FL",
    "wof:name":"DSA Marketing Inc",
    "wof:placetype":"venue"
},
  "geometry": {"coordinates":[-82.603347,27.995201],"type":"Point"}
}