{
  "type": "Feature",
  "properties": {
    "iso:country":"US",
    "sg:address":"3444 Marinatown Ln",
    "sg:city":"Fort Myers",
    "sg:classifiers":[
        {
            "category":"Shopping",
            "subcategory":"Clothing, Apparel, & Fashions",
            "type":"Retail Goods"
        }
    ],
    "sg:phone":"+1 239 656 0714",
    "sg:postcode":"33903",
    "sg:province":"FL",
    "sg:tags":[
        "item",
        "boutique"
    ],
    "wof:name":"Dock Styles",
    "wof:placetype":"venue"
},
  "geometry": {"coordinates":[-81.891171,26.660921],"type":"Point"}
}