{
  "type": "Feature",
  "properties": {
    "iso:country":"US",
    "sg:address":"218 5th Ave N",
    "sg:city":"St Petersburg",
    "sg:classifiers":[
        {
            "category":"Real Estate",
            "subcategory":"Architect",
            "type":"Services"
        }
    ],
    "sg:phone":"+1 727 323 5676",
    "sg:postcode":"33701",
    "sg:province":"FL",
    "wof:name":"Architectonics Studio",
    "wof:placetype":"venue"
},
  "geometry": {"coordinates":[-82.636886,27.777497],"type":"Point"}
}