{
  "type": "Feature",
  "properties": {
    "iso:country":"US",
    "sg:address":"1441 Tamiami Trl",
    "sg:city":"Port Charlotte",
    "sg:classifiers":[
        {
            "category":"Shopping",
            "subcategory":"Jewelry",
            "type":"Retail Goods"
        },
        {
            "category":"Shopping",
            "subcategory":"Clothing, Apparel, & Fashions",
            "type":"Retail Goods"
        }
    ],
    "sg:phone":"+1 941 627 6666",
    "sg:postcode":"33948",
    "sg:province":"FL",
    "wof:name":"Claires",
    "wof:placetype":"venue"
},
  "geometry": {"coordinates":[-82.142602,27.011002],"type":"Point"}
}