{
  "type": "Feature",
  "properties": {
    "iso:country":"US",
    "sg:address":"4802 51st St W",
    "sg:city":"Bradenton",
    "sg:classifiers":[
        {
            "category":"Real Estate",
            "subcategory":"Real Estate Operator",
            "type":"Services"
        },
        {
            "category":"Real Estate",
            "subcategory":"Real Estate Services",
            "type":"Services"
        }
    ],
    "sg:phone":"+1 941 795 7470",
    "sg:postcode":"34210",
    "sg:province":"FL",
    "sg:tags":[
        "apartment",
        "condominium",
        "vacancy",
        "management",
        "listing",
        "rental",
        "finder"
    ],
    "wof:name":"The Columns At Cortez",
    "wof:placetype":"venue"
},
  "geometry": {"coordinates":[-82.61241099999999,27.457055],"type":"Point"}
}