{
  "type": "Feature",
  "properties": {
    "iso:country":"US",
    "sg:address":"730 Washburn Rd",
    "sg:city":"Melbourne",
    "sg:classifiers":[
        {
            "category":"Retail",
            "subcategory":"Repair Shop",
            "type":"Services"
        }
    ],
    "sg:phone":"+1 321 242 2890",
    "sg:postcode":"32934",
    "sg:province":"FL",
    "sg:tags":[
        "scooter",
        "motorcycle",
        "motor"
    ],
    "wof:name":"Vikings Customs",
    "wof:placetype":"venue"
},
  "geometry": {"coordinates":[-80.68661400000001,28.118807],"type":"Point"}
}