{
  "type": "Feature",
  "properties": {
    "addr:full":"1801 Cypress Lake Dr Orlando FL 32837",
    "addr:housenumber":"1801",
    "addr:postcode":"32837",
    "addr:street":"Cypress Lake Dr",
    "iso:country":"US",
    "sg:address":"1801 Cypress Lake Dr",
    "sg:city":"Orlando",
    "sg:classifiers":[
        {
            "category":"Wholesale",
            "subcategory":"Stationery",
            "type":"Manufacturing & Wholesale Goods"
        }
    ],
    "sg:phone":"+1 407 583 2200",
    "sg:postcode":"32837",
    "sg:province":"FL",
    "sg:tags":[
        "supply",
        "furn"
    ],
    "wof:name":"Boise Cascade",
    "wof:placetype":"venue"
},
  "geometry": {"coordinates":[-81.397763,28.413544],"type":"Point"}
}