{
  "type": "Feature",
  "properties": {
    "addr:full":"356 NE 80th St Miami FL 33138",
    "addr:housenumber":"356",
    "addr:postcode":"33138",
    "addr:street":"Ne 80Th St",
    "iso:country":"US",
    "sg:address":"356 NE 80th St",
    "sg:city":"Miami",
    "sg:classifiers":[
        {
            "category":"Home & Garden",
            "subcategory":"Home Furnishings",
            "type":"Retail Goods"
        }
    ],
    "sg:phone":"+1 305 756 6652",
    "sg:postcode":"33138",
    "sg:province":"FL",
    "sg:tags":[
        "cover",
        "slip"
    ],
    "wof:name":"Franco Plastic Covers",
    "wof:placetype":"venue"
},
  "geometry": {"coordinates":[-80.18941599999999,25.848534],"type":"Point"}
}