{
  "type": "Feature",
  "properties": {
    "addr:full":"1950 SE Hillmoor Dr Port Saint Lucie FL 34952",
    "addr:housenumber":"1950",
    "addr:postcode":"34952",
    "addr:street":"Se Hillmoor Dr",
    "iso:country":"US",
    "sg:address":"1950 SE Hillmoor Dr",
    "sg:city":"Port Saint Lucie",
    "sg:classifiers":[
        {
            "category":"Building & Trades",
            "subcategory":"Cleaning & Sanitation",
            "type":"Services"
        }
    ],
    "sg:phone":"+1 772 398 8992",
    "sg:postcode":"34952",
    "sg:province":"FL",
    "sg:tags":[
        "maintenance"
    ],
    "wof:name":"Flournoy Development Co LLC",
    "wof:placetype":"venue"
},
  "geometry": {"coordinates":[-80.294662,27.286414],"type":"Point"}
}