{
  "type": "Feature",
  "properties": {
    "iso:country":"US",
    "sg:address":"7944 S George Blvd",
    "sg:city":"Sebring",
    "sg:classifiers":[
        {
            "category":"Building & Trades",
            "subcategory":"Construction",
            "type":"Services"
        },
        {
            "category":"Utilities",
            "type":"Services"
        }
    ],
    "sg:phone":"+1 863 471 1997",
    "sg:postcode":"33875",
    "sg:province":"FL",
    "sg:tags":[
        "industrial",
        "excavation",
        "contractor",
        "paving",
        "road",
        "contractors-commercial"
    ],
    "wof:name":"Excavation Point Inc",
    "wof:placetype":"venue"
},
  "geometry": {"coordinates":[-81.424621,27.429806],"type":"Point"}
}