{
  "type": "Feature",
  "properties": {
    "iso:country":"US",
    "sg:address":"306 Alcazar Ave",
    "sg:city":"Coral Gables",
    "sg:classifiers":[
        {
            "category":"Utilities",
            "subcategory":"Telephone",
            "type":"Services"
        }
    ],
    "sg:phone":"+1 305 443 7999",
    "sg:postcode":"33134",
    "sg:province":"FL",
    "sg:tags":[
        "communications",
        "telecommunication"
    ],
    "wof:name":"Itxc Corp",
    "wof:placetype":"venue"
},
  "geometry": {"coordinates":[-80.26270700000001,25.752595],"type":"Point"}
}