{
  "type": "Feature",
  "properties": {
    "iso:country":"US",
    "sg:address":"2560 Old Hwy 50 W",
    "sg:city":"Clermont",
    "sg:classifiers":[
        {
            "category":"Personal",
            "subcategory":"Beauty Salon",
            "type":"Services"
        }
    ],
    "sg:phone":"+1 352 536 2845",
    "sg:postcode":"34711",
    "sg:province":"FL",
    "sg:tags":[
        "manicuring"
    ],
    "wof:name":"Tami Nails",
    "wof:placetype":"venue"
},
  "geometry": {"coordinates":[-81.697721,28.564596],"type":"Point"}
}