{
  "type": "Feature",
  "properties": {
    "addr:full":"603 E Harvard St Inverness FL 34452",
    "addr:housenumber":"603",
    "addr:postcode":"34452",
    "addr:street":"E Harvard St",
    "iso:country":"US",
    "sg:address":"603 E Harvard St",
    "sg:city":"Inverness",
    "sg:classifiers":[
        {
            "category":"Building & Trades",
            "subcategory":"Construction",
            "type":"Services"
        }
    ],
    "sg:phone":"+1 352 302 6422",
    "sg:postcode":"34452",
    "sg:province":"FL",
    "sg:tags":[
        "layer",
        "carpet"
    ],
    "wof:name":"Cousins Carpet Installations",
    "wof:placetype":"venue"
},
  "geometry": {"coordinates":[-82.322986,28.814439],"type":"Point"}
}