{
  "type": "Feature",
  "properties": {
    "addr:full":"2726 Gulf Breeze Pkwy Gulf Breeze FL 32563",
    "addr:housenumber":"2726",
    "addr:postcode":"32563",
    "addr:street":"Gulf Breeze Pkwy",
    "iso:country":"US",
    "sg:address":"2726 Gulf Breeze Pkwy",
    "sg:city":"Gulf Breeze",
    "sg:classifiers":[
        {
            "category":"Insurance",
            "subcategory":"Insurance Agent",
            "type":"Services"
        }
    ],
    "sg:phone":"+1 850 932 0709",
    "sg:postcode":"32563",
    "sg:province":"FL",
    "wof:name":"Price Mary Beth Insurance Agcy",
    "wof:placetype":"venue"
},
  "geometry": {"coordinates":[-87.110809,30.381062],"type":"Point"}
}