{
  "type": "Feature",
  "properties": {
    "iso:country":"US",
    "sg:address":"2471 Michigan Ave",
    "sg:city":"Kissimmee",
    "sg:classifiers":[
        {
            "category":"Manufacturing",
            "subcategory":"Food",
            "type":"Manufacturing & Wholesale Goods"
        },
        {
            "category":"Food & Beverages",
            "subcategory":"Groceries & Convenience Stores",
            "type":"Retail Goods"
        }
    ],
    "sg:phone":"+1 407 343 0800",
    "sg:postcode":"34744",
    "sg:province":"FL",
    "sg:tags":[
        "product"
    ],
    "wof:name":"Michigan Donegan Moms Food Str",
    "wof:placetype":"venue"
},
  "geometry": {"coordinates":[-81.391289,28.318663],"type":"Point"}
}