{
  "type": "Feature",
  "properties": {
    "iso:country":"US",
    "sg:address":"13326 SW 28th St",
    "sg:city":"Fort Lauderdale",
    "sg:classifiers":[
        {
            "category":"Manufacturing",
            "subcategory":"Printing",
            "type":"Manufacturing & Wholesale Goods"
        }
    ],
    "sg:phone":"+1 954 370 9153",
    "sg:postcode":"33330",
    "sg:province":"FL",
    "sg:tags":[
        "periodical"
    ],
    "wof:name":"Women Publications Sub",
    "wof:placetype":"venue"
},
  "geometry": {"coordinates":[-80.329172,26.085747],"type":"Point"}
}