{
  "type": "Feature",
  "properties": {
    "iso:country":"US",
    "sg:address":"4390 Grand Ave",
    "sg:city":"De Leon Springs",
    "sg:classifiers":[
        {
            "category":"Organizations",
            "subcategory":"Religious Organization",
            "type":"Services"
        }
    ],
    "sg:phone":"+1 386 985 5951",
    "sg:postcode":"32130",
    "sg:province":"FL",
    "wof:name":"White House Christian Center",
    "wof:placetype":"venue"
},
  "geometry": {"coordinates":[-81.35445,29.105014],"type":"Point"}
}