{
  "type": "Feature",
  "properties": {
    "iso:country":"US",
    "sg:address":"3097 Russ Rd",
    "sg:city":"Marianna",
    "sg:classifiers":[
        {
            "category":"Shopping",
            "type":"Retail Goods"
        }
    ],
    "sg:phone":"+1 850 526 1556",
    "sg:postcode":"32446",
    "sg:province":"FL",
    "sg:tags":[
        "merchandise"
    ],
    "wof:name":"Jackie Live",
    "wof:placetype":"venue"
},
  "geometry": {"coordinates":[-85.16191600000001,30.791699],"type":"Point"}
}