{
  "type": "Feature",
  "properties": {
    "iso:country":"US",
    "sg:address":"2211 NW 26th Ave",
    "sg:city":"Miami",
    "sg:classifiers":[
        {
            "category":"Building & Trades",
            "subcategory":"Cleaning & Sanitation",
            "type":"Services"
        }
    ],
    "sg:phone":"+1 305 634 0030",
    "sg:postcode":"33142",
    "sg:province":"FL",
    "sg:tags":[
        "carpet"
    ],
    "sg:website":"www.mavelcarpetandtileinc.com",
    "wof:name":"Mavel Carpet and Tile Inc",
    "wof:placetype":"venue"
},
  "geometry": {"coordinates":[-80.238998,25.7974],"type":"Point"}
}