{
  "type": "Feature",
  "properties": {
    "iso:country":"US",
    "sg:address":"1007 Park St",
    "sg:city":"Clearwater",
    "sg:classifiers":[
        {
            "category":"Retail",
            "subcategory":"Auto Repair",
            "type":"Services"
        }
    ],
    "sg:phone":"+1 727 461 1272",
    "sg:postcode":"33756",
    "sg:province":"FL",
    "sg:tags":[
        "body",
        "automobile",
        "painting"
    ],
    "wof:name":"Classic Auto Body Inc",
    "wof:placetype":"venue"
},
  "geometry": {"coordinates":[-82.791844,27.96469],"type":"Point"}
}