{
  "type": "Feature",
  "properties": {
    "iso:country":"US",
    "sg:address":"3033 Drane Field Rd",
    "sg:city":"Lakeland",
    "sg:classifiers":[
        {
            "category":"Shopping",
            "subcategory":"Used Merchandise",
            "type":"Retail Goods"
        }
    ],
    "sg:phone":"+1 863 701 1351",
    "sg:postcode":"33811",
    "sg:province":"FL",
    "sg:tags":[
        "shop",
        "thrift"
    ],
    "wof:name":"Goodwill Industries",
    "wof:placetype":"venue"
},
  "geometry": {"coordinates":[-82.00493899999999,27.996713],"type":"Point"}
}