{
  "type": "Feature",
  "properties": {
    "iso:country":"US",
    "sg:address":"15887 SW 139th St",
    "sg:city":"Miami",
    "sg:classifiers":[
        {
            "category":"Banks & Credit Unions",
            "subcategory":"Bank",
            "type":"Services"
        }
    ],
    "sg:phone":"+1 305 233 2518",
    "sg:postcode":"33196",
    "sg:province":"FL",
    "sg:tags":[
        "bond",
        "broker",
        "stock"
    ],
    "wof:name":"Vhc Florida Corporation",
    "wof:placetype":"venue"
},
  "geometry": {"coordinates":[-80.451582,25.63705],"type":"Point"}
}