{
  "type": "Feature",
  "properties": {
    "iso:country":"US",
    "sg:address":"1666 Deck Ct NW",
    "sg:city":"Palm Bay",
    "sg:classifiers":[
        {
            "category":"Building & Trades",
            "subcategory":"Construction",
            "type":"Services"
        }
    ],
    "sg:phone":"+1 321 724 2734",
    "sg:postcode":"32907",
    "sg:province":"FL",
    "sg:tags":[
        "interior",
        "repair",
        "carpentry"
    ],
    "wof:name":"A Maslovsky Interior",
    "wof:placetype":"venue"
},
  "geometry": {"coordinates":[-80.71883800000001,28.001069],"type":"Point"}
}