{
  "type": "Feature",
  "properties": {
    "addr:full":"5110 San Juan Ave Jacksonville FL 32210",
    "addr:housenumber":"5110",
    "addr:postcode":"32210",
    "addr:street":"San Juan Ave",
    "iso:country":"US",
    "sg:address":"5110 San Juan Ave",
    "sg:city":"Jacksonville",
    "sg:classifiers":[
        {
            "category":"Health Services",
            "subcategory":"Doctor",
            "type":"Services"
        }
    ],
    "sg:phone":"+1 904 389 2276",
    "sg:postcode":"32210",
    "sg:province":"FL",
    "sg:tags":[
        "dentist"
    ],
    "wof:name":"Fetner & Hartigan",
    "wof:placetype":"venue"
},
  "geometry": {"coordinates":[-81.734346,30.282037],"type":"Point"}
}