{
  "type": "Feature",
  "properties": {
    "addr:full":"12996 SW 132nd Ave Miami FL 33186",
    "addr:housenumber":"12996",
    "addr:postcode":"33186",
    "addr:street":"Sw 132Nd Ave",
    "iso:country":"US",
    "sg:address":"12996 SW 132nd Ave",
    "sg:city":"Miami",
    "sg:classifiers":[
        {
            "category":"Wholesale",
            "subcategory":"Apparel",
            "type":"Manufacturing & Wholesale Goods"
        }
    ],
    "sg:phone":"+1 305 255 2809",
    "sg:postcode":"33186",
    "sg:province":"FL",
    "sg:tags":[
        "clothing"
    ],
    "wof:name":"Astrid Inc",
    "wof:placetype":"venue"
},
  "geometry": {"coordinates":[-80.40712000000001,25.646269],"type":"Point"}
}