{
  "type": "Feature",
  "properties": {
    "iso:country":"US",
    "sg:address":"4289 Orlando Dr",
    "sg:city":"Sanford",
    "sg:classifiers":[
        {
            "category":"Food & Beverages",
            "subcategory":"Groceries & Convenience Stores",
            "type":"Retail Goods"
        }
    ],
    "sg:phone":"+1 407 323 0073",
    "sg:postcode":"32771",
    "sg:province":"FL",
    "wof:name":"As Seen On Tv",
    "wof:placetype":"venue"
},
  "geometry": {"coordinates":[-81.297713,28.743055],"type":"Point"}
}