{
  "type": "Feature",
  "properties": {
    "iso:country":"US",
    "sg:address":"1577 Crescent Hill Dr",
    "sg:city":"Tallahassee",
    "sg:classifiers":[
        {
            "category":"Restaurant",
            "type":"Food & Drink"
        }
    ],
    "sg:phone":"+1 850 597 8334",
    "sg:postcode":"32303",
    "sg:province":"FL",
    "wof:name":"Papas, Maria",
    "wof:placetype":"venue"
},
  "geometry": {"coordinates":[-84.365915,30.465864],"type":"Point"}
}