{
  "type": "Feature",
  "properties": {
    "addr:full":"429 John King Rd Crestview FL 32539",
    "addr:housenumber":"429",
    "addr:postcode":"32539",
    "addr:street":"John King Rd",
    "iso:country":"US",
    "sg:address":"429 John King Rd",
    "sg:city":"Crestview",
    "sg:classifiers":[
        {
            "category":"Government",
            "subcategory":"Fire Station",
            "type":"Public Place"
        }
    ],
    "sg:phone":"+1 850 689 6633",
    "sg:postcode":"32539",
    "sg:province":"FL",
    "sg:tags":[
        "department"
    ],
    "wof:name":"North Okaloosa Fire Dist",
    "wof:placetype":"venue"
},
  "geometry": {"coordinates":[-86.54391699999999,30.720637],"type":"Point"}
}