{
  "type": "Feature",
  "properties": {
    "addr:full":"6875 SW 38th St Miami FL 33155",
    "addr:housenumber":"6875",
    "addr:postcode":"33155",
    "addr:street":"Sw 38Th St",
    "iso:country":"US",
    "sg:address":"6875 SW 38th St",
    "sg:city":"Miami",
    "sg:classifiers":[
        {
            "category":"Shopping",
            "subcategory":"Clothing, Apparel, & Fashions",
            "type":"Retail Goods"
        }
    ],
    "sg:phone":"+1 305 665 3720",
    "sg:postcode":"33155",
    "sg:province":"FL",
    "wof:name":"Hot Tracks",
    "wof:placetype":"venue"
},
  "geometry": {"coordinates":[-80.30551,25.735793],"type":"Point"}
}