{
  "type": "Feature",
  "properties": {
    "iso:country":"US",
    "sg:address":"20801 Biscayne Blvd",
    "sg:city":"Miami",
    "sg:classifiers":[
        {
            "category":"Travel",
            "subcategory":"Travel Agent",
            "type":"Entertainment"
        }
    ],
    "sg:phone":"+1 305 936 0637",
    "sg:postcode":"33180",
    "sg:province":"FL",
    "sg:tags":[
        "agency",
        "bureau"
    ],
    "wof:name":"Inka Wasi Travel Corp",
    "wof:placetype":"venue"
},
  "geometry": {"coordinates":[-80.144882,25.968049],"type":"Point"}
}