{
  "type": "Feature",
  "properties": {
    "iso:country":"US",
    "sg:address":"3152 Shadeville Rd",
    "sg:city":"Crawfordville",
    "sg:classifiers":[
        {
            "category":"Wholesale",
            "subcategory":"Computers",
            "type":"Manufacturing & Wholesale Goods"
        }
    ],
    "sg:phone":"+1 850 421 9449",
    "sg:postcode":"32326",
    "sg:province":"FL",
    "sg:tags":[
        "ope",
        "federal",
        "government",
        "resellers",
        "to",
        "state",
        "local"
    ],
    "wof:name":"Innovative Tech Inc",
    "wof:placetype":"venue"
},
  "geometry": {"coordinates":[-84.23425,30.23125],"type":"Point"}
}