{
  "type": "Feature",
  "properties": {
    "addr:full":"8050 Cleary Blvd Fort Lauderdale FL 33324",
    "addr:housenumber":"8050",
    "addr:postcode":"33324",
    "addr:street":"Cleary Blvd",
    "iso:country":"US",
    "sg:address":"8050 Cleary Blvd",
    "sg:city":"Fort Lauderdale",
    "sg:classifiers":[
        {
            "category":"Building & Trades",
            "subcategory":"Construction",
            "type":"Services"
        }
    ],
    "sg:phone":"+1 954 533 3333",
    "sg:postcode":"33324",
    "sg:province":"FL",
    "sg:tags":[
        "contractor"
    ],
    "wof:name":"Roofing Excellence Inc",
    "wof:placetype":"venue"
},
  "geometry": {"coordinates":[-80.25860400000001,26.133828],"type":"Point"}
}