{
  "type": "Feature",
  "properties": {
    "iso:country":"US",
    "sg:address":"1631 del Prado Blvd S",
    "sg:city":"Cape Coral",
    "sg:classifiers":[
        {
            "category":"Banks & Credit Unions",
            "subcategory":"Investment Brokerage",
            "type":"Services"
        }
    ],
    "sg:phone":"+1 239 574 2200",
    "sg:postcode":"33904",
    "sg:province":"FL",
    "sg:tags":[
        "security"
    ],
    "wof:name":"A G Edwards 392",
    "wof:placetype":"venue"
},
  "geometry": {"coordinates":[-81.94064899999999,26.621188],"type":"Point"}
}