{
  "type": "Feature",
  "properties": {
    "iso:country":"US",
    "sg:address":"6531 Main St",
    "sg:city":"Hialeah",
    "sg:classifiers":[
        {
            "category":"Restaurant",
            "type":"Food & Drink"
        },
        {
            "category":"Food & Beverages",
            "subcategory":"Groceries & Convenience Stores",
            "type":"Retail Goods"
        }
    ],
    "sg:phone":"+1 305 824 3235",
    "sg:postcode":"33014",
    "sg:province":"FL",
    "sg:tags":[
        "shop",
        "sandwich"
    ],
    "wof:name":"S Zitano Sub Inc",
    "wof:placetype":"venue"
},
  "geometry": {"coordinates":[-80.307101,25.913652],"type":"Point"}
}