{
  "type": "Feature",
  "properties": {
    "iso:country":"US",
    "sg:address":"7150 NW 50th St",
    "sg:city":"Miami",
    "sg:classifiers":[
        {
            "category":"Professional",
            "subcategory":"Business Services",
            "type":"Services"
        }
    ],
    "sg:phone":"+1 305 591 3957",
    "sg:postcode":"33166",
    "sg:province":"FL",
    "sg:tags":[
        "consultant",
        "custom"
    ],
    "wof:name":"Torre,-Verdejo Jorge",
    "wof:placetype":"venue"
},
  "geometry": {"coordinates":[-80.31287399999999,25.818896],"type":"Point"}
}