{
  "type": "Feature",
  "properties": {
    "iso:country":"US",
    "sg:address":"915 W Dr Martin Luther King Jr Blvd",
    "sg:city":"Seffner",
    "sg:classifiers":[
        {
            "category":"Wholesale",
            "subcategory":"Office Equipment",
            "type":"Manufacturing & Wholesale Goods"
        },
        {
            "category":"Professional",
            "subcategory":"Accounting & Tax Preparation",
            "type":"Services"
        }
    ],
    "sg:phone":"+1 813 655 0999",
    "sg:postcode":"33584",
    "sg:province":"FL",
    "sg:tags":[
        "machine",
        "bookkeeping",
        "return",
        "preparation-business",
        "supply"
    ],
    "wof:name":"Liberty Tax Service",
    "wof:placetype":"venue"
},
  "geometry": {"coordinates":[-82.28941,27.981578],"type":"Point"}
}