{
  "type": "Feature",
  "properties": {
    "addr:full":"1439 SE 8th Ct Deerfield Beach FL 33441",
    "addr:housenumber":"1439",
    "addr:postcode":"33441",
    "addr:street":"Se 8Th Ct",
    "iso:country":"US",
    "sg:address":"1439 SE 8th Ct",
    "sg:city":"Deerfield Beach",
    "sg:classifiers":[
        {
            "category":"Professional",
            "subcategory":"Engineering",
            "type":"Services"
        }
    ],
    "sg:phone":"+1 954 421 6211",
    "sg:postcode":"33441",
    "sg:province":"FL",
    "sg:tags":[
        "consultant",
        "computer"
    ],
    "wof:name":"Pure Data Systems Inc",
    "wof:placetype":"venue"
},
  "geometry": {"coordinates":[-80.082837,26.306877],"type":"Point"}
}