{
  "type": "Feature",
  "properties": {
    "addr:full":"6788 Bird Rd Miami FL 33155",
    "addr:housenumber":"6788",
    "addr:postcode":"33155",
    "addr:street":"Bird Rd",
    "iso:country":"US",
    "sg:address":"6788 Bird Rd",
    "sg:city":"Miami",
    "sg:classifiers":[
        {
            "category":"Home & Garden",
            "subcategory":"Furniture",
            "type":"Retail Goods"
        }
    ],
    "sg:phone":"+1 305 740 7800",
    "sg:postcode":"33155",
    "sg:province":"FL",
    "sg:tags":[
        "store"
    ],
    "wof:name":"Westchester Furniture Gallery",
    "wof:placetype":"venue"
},
  "geometry": {"coordinates":[-80.304857,25.733112],"type":"Point"}
}