{
  "type": "Feature",
  "properties": {
    "iso:country":"US",
    "sg:address":"2400 Diversified Way",
    "sg:city":"Orlando",
    "sg:classifiers":[
        {
            "category":"Health Services",
            "subcategory":"Nursing And Care Facility",
            "type":"Services"
        },
        {
            "category":"Social Services",
            "subcategory":"Adult Care",
            "type":"Services"
        }
    ],
    "sg:phone":"+1 407 649 9040",
    "sg:postcode":"32804",
    "sg:province":"FL",
    "sg:tags":[
        "personal",
        "living",
        "assisted",
        "home",
        "elder"
    ],
    "sg:website":"http://www.southernhomecareservices.com",
    "wof:name":"Excel Alternatives Inc",
    "wof:placetype":"venue"
},
  "geometry": {"coordinates":[-81.40740099999999,28.572591],"type":"Point"}
}