{
  "type": "Feature",
  "properties": {
    "iso:country":"US",
    "sg:address":"5145 Regalo Dr",
    "sg:city":"Pensacola",
    "sg:classifiers":[
        {
            "category":"Building & Trades",
            "subcategory":"Construction",
            "type":"Services"
        }
    ],
    "sg:phone":"+1 850 453 8785",
    "sg:postcode":"32526",
    "sg:province":"FL",
    "sg:tags":[
        "roofing",
        "contractor"
    ],
    "wof:name":"Dwight Wright Roofing",
    "wof:placetype":"venue"
},
  "geometry": {"coordinates":[-87.317938,30.458585],"type":"Point"}
}