{
  "type": "Feature",
  "properties": {
    "iso:country":"US",
    "sg:address":"3031 NE 51st St",
    "sg:city":"Fort Lauderdale",
    "sg:classifiers":[
        {
            "category":"Real Estate",
            "subcategory":"Developer",
            "type":"Services"
        }
    ],
    "sg:phone":"+1 954 491 2677",
    "sg:postcode":"33308",
    "sg:province":"FL",
    "wof:name":"Celunco Inc",
    "wof:placetype":"venue"
},
  "geometry": {"coordinates":[-80.104156,26.191004],"type":"Point"}
}