{
  "type": "Feature",
  "properties": {
    "addr:full":"1015 Ingraham Ave Delray Beach FL 33483",
    "addr:housenumber":"1015",
    "addr:postcode":"33483",
    "addr:street":"Ingraham Ave",
    "iso:country":"US",
    "sg:address":"1015 Ingraham Ave",
    "sg:city":"Delray Beach",
    "sg:classifiers":[
        {
            "category":"Manufacturing",
            "subcategory":"Retail Goods",
            "type":"Manufacturing & Wholesale Goods"
        }
    ],
    "sg:phone":"+1 561 274 8198",
    "sg:postcode":"33483",
    "sg:province":"FL",
    "sg:tags":[
        "product",
        "mfg"
    ],
    "wof:name":"Norad Industries Inc",
    "wof:placetype":"venue"
},
  "geometry": {"coordinates":[-80.06072500000001,26.458094],"type":"Point"}
}