{
  "type": "Feature",
  "properties": {
    "iso:country":"US",
    "sg:address":"1202 Lynne Ave",
    "sg:city":"Auburndale",
    "sg:classifiers":[
        {
            "category":"Building & Trades",
            "subcategory":"Construction",
            "type":"Services"
        }
    ],
    "sg:phone":"+1 863 412 1741",
    "sg:postcode":"33823",
    "sg:province":"FL",
    "sg:tags":[
        "restoration",
        "cleaning",
        "patio",
        "deck"
    ],
    "wof:name":"BNS Pressure Cleaning",
    "wof:placetype":"venue"
},
  "geometry": {"coordinates":[-81.783147,28.082899],"type":"Point"}
}