{
  "type": "Feature",
  "properties": {
    "iso:country":"US",
    "sg:address":"3730 Old Winter Garden Rd",
    "sg:city":"Orlando",
    "sg:classifiers":[
        {
            "category":"Building & Trades",
            "subcategory":"Construction",
            "type":"Services"
        },
        {
            "category":"Retail",
            "subcategory":"Auto Repair",
            "type":"Services"
        }
    ],
    "sg:phone":"+1 407 295 1410",
    "sg:postcode":"32805",
    "sg:province":"FL",
    "sg:tags":[
        "transmission",
        "house"
    ],
    "wof:name":"P L C Transmissions Builders",
    "wof:placetype":"venue"
},
  "geometry": {"coordinates":[-81.42532300000001,28.547281],"type":"Point"}
}