{
  "type": "Feature",
  "properties": {
    "addr:full":"753 Saint Albans Dr Boca Raton FL 33486",
    "addr:housenumber":"753",
    "addr:postcode":"33486",
    "addr:street":"Saint Albans Dr",
    "iso:country":"US",
    "sg:address":"753 Saint Albans Dr",
    "sg:city":"Boca Raton",
    "sg:classifiers":[
        {
            "category":"Professional",
            "subcategory":"Business Services",
            "type":"Services"
        }
    ],
    "sg:phone":"+1 561 416 2249",
    "sg:postcode":"33486",
    "sg:province":"FL",
    "sg:tags":[
        "interior",
        "consultant",
        "design",
        "decorator"
    ],
    "wof:name":"Perini Interiors",
    "wof:placetype":"venue"
},
  "geometry": {"coordinates":[-80.10314099999999,26.364757],"type":"Point"}
}