{
  "type": "Feature",
  "properties": {
    "iso:country":"US",
    "sg:address":"18401 SW 107th Ave",
    "sg:city":"Miami",
    "sg:classifiers":[
        {
            "category":"Wholesale",
            "subcategory":"Scrap",
            "type":"Manufacturing & Wholesale Goods"
        }
    ],
    "sg:phone":"+1 305 252 2084",
    "sg:postcode":"33157",
    "sg:province":"FL",
    "sg:tags":[
        "recycling",
        "center"
    ],
    "wof:name":"Bob's Recycling Ctr",
    "wof:placetype":"venue"
},
  "geometry": {"coordinates":[-80.36447099999999,25.597782],"type":"Point"}
}