{
  "type": "Feature",
  "properties": {
    "iso:country":"US",
    "sg:address":"1233 Lori Dr",
    "sg:city":"Spring Hill",
    "sg:classifiers":[
        {
            "category":"Retail",
            "subcategory":"Car Wash",
            "type":"Services"
        }
    ],
    "sg:phone":"+1 352 666 7456",
    "sg:postcode":"34606",
    "sg:province":"FL",
    "sg:tags":[
        "polishing",
        "washing"
    ],
    "wof:name":"Banana Joe's Car Wash",
    "wof:placetype":"venue"
},
  "geometry": {"coordinates":[-82.631592,28.44991],"type":"Point"}
}