{
  "type": "Feature",
  "properties": {
    "iso:country":"US",
    "sg:address":"1556 6th St SE",
    "sg:city":"Winter Haven",
    "sg:classifiers":[
        {
            "category":"Real Estate",
            "subcategory":"Real Estate Services",
            "type":"Services"
        }
    ],
    "sg:phone":"+1 863 294 0604",
    "sg:postcode":"33880",
    "sg:province":"FL",
    "sg:tags":[
        "abstract",
        "title"
    ],
    "wof:name":"Fidelity National",
    "wof:placetype":"venue"
},
  "geometry": {"coordinates":[-81.718468,28.005927],"type":"Point"}
}