{
  "type": "Feature",
  "properties": {
    "addr:full":"3134 N Woodland Blvd Deland FL 32720",
    "addr:housenumber":"3134",
    "addr:postcode":"32720",
    "addr:street":"N Woodland Blvd",
    "iso:country":"US",
    "sg:address":"3134 N Woodland Blvd",
    "sg:city":"Deland",
    "sg:classifiers":[
        {
            "category":"Home & Garden",
            "subcategory":"Garden Supply",
            "type":"Retail Goods"
        },
        {
            "category":"Shopping",
            "subcategory":"Gifts & Souvenirs",
            "type":"Retail Goods"
        },
        {
            "category":"Shopping",
            "subcategory":"Crafts & Fabrics",
            "type":"Retail Goods"
        },
        {
            "category":"Shopping",
            "subcategory":"Florist",
            "type":"Retail Goods"
        }
    ],
    "sg:phone":"+1 386 736 9099",
    "sg:postcode":"32720",
    "sg:province":"FL",
    "sg:tags":[
        "plant",
        "etc-retail",
        "dried",
        "basket",
        "trees-silk",
        "flowers"
    ],
    "sg:website":"http://www.delandflowers.com",
    "wof:name":"The Flower Gallery at",
    "wof:placetype":"venue"
},
  "geometry": {"coordinates":[-81.321618,29.085434],"type":"Point"}
}