{
  "type": "Feature",
  "properties": {
    "addr:full":"14131 Portrush Dr Orlando FL 32828",
    "addr:postcode":"14131;32828",
    "addr:street":"Portrush Dr",
    "iso:country":"US",
    "sg:address":"14131 Portrush Dr",
    "sg:city":"Orlando",
    "sg:classifiers":[
        {
            "category":"Banks & Credit Unions",
            "subcategory":"Bank",
            "type":"Services"
        }
    ],
    "sg:phone":"+1 407 281 7447",
    "sg:postcode":"32828",
    "sg:province":"FL",
    "sg:tags":[
        "loan"
    ],
    "wof:name":"Apex Lending East Orlando Br",
    "wof:placetype":"venue"
},
  "geometry": {"coordinates":[-81.176844,28.539363],"type":"Point"}
}