{
  "type": "Feature",
  "properties": {
    "iso:country":"US",
    "sg:address":"2109 E 4th Ave",
    "sg:city":"Tampa",
    "sg:classifiers":[
        {
            "category":"Retail",
            "subcategory":"Auto Repair",
            "type":"Services"
        }
    ],
    "sg:phone":"+1 813 248 6948",
    "sg:postcode":"33605",
    "sg:province":"FL",
    "sg:tags":[
        "repairing",
        "transmission",
        "general",
        "automobile"
    ],
    "wof:name":"Pepe's Truck & Auto Repair",
    "wof:placetype":"venue"
},
  "geometry": {"coordinates":[-82.4348,27.958005],"type":"Point"}
}