{
  "type": "Feature",
  "properties": {
    "addr:full":"118 91st Ave Treasure Island FL 33706",
    "addr:housenumber":"118",
    "addr:postcode":"33706",
    "addr:street":"91St Ave",
    "iso:country":"US",
    "sg:address":"118 91st Ave",
    "sg:city":"Treasure Island",
    "sg:classifiers":[
        {
            "category":"Banks & Credit Unions",
            "subcategory":"Bank",
            "type":"Services"
        }
    ],
    "sg:phone":"+1 727 363 1651",
    "sg:postcode":"33706",
    "sg:province":"FL",
    "wof:name":"Santa Barbara Bank & Trust",
    "wof:placetype":"venue"
},
  "geometry": {"coordinates":[-82.76223899999999,27.754096],"type":"Point"}
}