{
  "type": "Feature",
  "properties": {
    "iso:country":"US",
    "sg:address":"13007 SW 122nd Ave",
    "sg:city":"Miami",
    "sg:classifiers":[
        {
            "category":"Shopping",
            "subcategory":"Computers & Home Electronics",
            "type":"Retail Goods"
        }
    ],
    "sg:phone":"+1 305 233 7121",
    "sg:postcode":"33186",
    "sg:province":"FL",
    "sg:tags":[
        "equipment",
        "electronic",
        "supply"
    ],
    "wof:name":"N Ws Electronics",
    "wof:placetype":"venue"
},
  "geometry": {"coordinates":[-80.39148900000001,25.6454],"type":"Point"}
}