{
  "type": "Feature",
  "properties": {
    "addr:full":"8390 NW 142nd St Hialeah FL 33016",
    "addr:housenumber":"8390",
    "addr:postcode":"33016",
    "addr:street":"Nw 142Nd St",
    "iso:country":"US",
    "sg:address":"8390 NW 142nd St",
    "sg:city":"Hialeah",
    "sg:classifiers":[
        {
            "category":"Building & Trades",
            "subcategory":"Construction",
            "type":"Services"
        }
    ],
    "sg:phone":"+1 305 698 6374",
    "sg:postcode":"33016",
    "sg:province":"FL",
    "sg:tags":[
        "contractor"
    ],
    "wof:name":"Ring Contractors Inc",
    "wof:placetype":"venue"
},
  "geometry": {"coordinates":[-80.336065,25.902441],"type":"Point"}
}