{
  "type": "Feature",
  "properties": {
    "iso:country":"US",
    "sg:address":"104 Monroe Ave",
    "sg:city":"Fort Pierce",
    "sg:classifiers":[
        {
            "category":"Building & Trades",
            "subcategory":"Landscaping Services",
            "type":"Services"
        }
    ],
    "sg:phone":"+1 772 595 0440",
    "sg:postcode":"34982",
    "sg:province":"FL",
    "wof:name":"Innovative Grass Maintena",
    "wof:placetype":"venue"
},
  "geometry": {"coordinates":[-80.328895,27.382313],"type":"Point"}
}