{
  "type": "Feature",
  "properties": {
    "iso:country":"US",
    "sg:address":"4937 US Hwy 98",
    "sg:city":"Lakeland",
    "sg:classifiers":[
        {
            "category":"Museum",
            "type":"Entertainment"
        }
    ],
    "sg:phone":"+1 863 853 4779",
    "sg:postcode":"33809",
    "sg:province":"FL",
    "sg:tags":[
        "organization",
        "arts",
        "information"
    ],
    "wof:name":"Goldleaf Creative Arts",
    "wof:placetype":"venue"
},
  "geometry": {"coordinates":[-81.973686,28.103229],"type":"Point"}
}