{
  "type": "Feature",
  "properties": {
    "iso:country":"US",
    "sg:address":"14305 S Dixie Hwy",
    "sg:city":"Miami",
    "sg:classifiers":[
        {
            "category":"Shopping",
            "subcategory":"Gifts & Souvenirs",
            "type":"Retail Goods"
        },
        {
            "category":"Manufacturing",
            "subcategory":"Retail Goods",
            "type":"Manufacturing & Wholesale Goods"
        }
    ],
    "sg:phone":"+1 305 255 1515",
    "sg:postcode":"33176",
    "sg:province":"FL",
    "sg:tags":[
        "shop",
        "giftware's-wholesale",
        "basket",
        "manufacturer"
    ],
    "wof:name":"Copper Kettle Celtic",
    "wof:placetype":"venue"
},
  "geometry": {"coordinates":[-80.33702,25.637438],"type":"Point"}
}