{
  "type": "Feature",
  "properties": {
    "iso:country":"US",
    "sg:address":"4201 N State Rd 7",
    "sg:city":"Hollywood",
    "sg:classifiers":[
        {
            "category":"Retail",
            "subcategory":"Auto Repair",
            "type":"Services"
        }
    ],
    "sg:phone":"+1 954 987 2441",
    "sg:postcode":"33021",
    "sg:province":"FL",
    "sg:tags":[
        "repairing",
        "automobile"
    ],
    "wof:name":"Universal Motor",
    "wof:placetype":"venue"
},
  "geometry": {"coordinates":[-80.20902599999999,26.046583],"type":"Point"}
}