{
  "type": "Feature",
  "properties": {
    "iso:country":"US",
    "sg:address":"5601 Golden Eagle Cir",
    "sg:city":"Palm Beach Gardens",
    "sg:classifiers":[
        {
            "category":"Organizations",
            "subcategory":"Community Association",
            "type":"Services"
        }
    ],
    "sg:phone":"+1 561 627 7240",
    "sg:postcode":"33418",
    "sg:province":"FL",
    "wof:name":"Westwood Grdns Homeowners Assn",
    "wof:placetype":"venue"
},
  "geometry": {"coordinates":[-80.126893,26.863869],"type":"Point"}
}