{
  "type": "Feature",
  "properties": {
    "iso:country":"US",
    "sg:address":"8 Center Ln",
    "sg:city":"Key Largo",
    "sg:classifiers":[
        {
            "category":"Bus Charters",
            "type":"Transportation"
        }
    ],
    "sg:phone":"+1 305 451 3958",
    "sg:postcode":"33037",
    "sg:province":"FL",
    "sg:tags":[
        "local"
    ],
    "wof:name":"Seaductress Charter Inc",
    "wof:placetype":"venue"
},
  "geometry": {"coordinates":[-80.392718,25.160177],"type":"Point"}
}