{
  "type": "Feature",
  "properties": {
    "iso:country":"US",
    "sg:address":"13630 Gulf Blvd",
    "sg:city":"Madeira Beach",
    "sg:classifiers":[
        {
            "category":"Travel",
            "subcategory":"Hotels & Motels",
            "type":"Entertainment"
        }
    ],
    "sg:phone":"+1 727 391 8949",
    "sg:postcode":"33708",
    "sg:province":"FL",
    "sg:website":"www.greygull.com",
    "wof:name":"Grey Gull Apartments",
    "wof:placetype":"venue"
},
  "geometry": {"coordinates":[-82.791118,27.792857],"type":"Point"}
}