{
  "type": "Feature",
  "properties": {
    "iso:country":"US",
    "sg:address":"1851 W Colonial Dr",
    "sg:city":"Orlando",
    "sg:classifiers":[
        {
            "category":"Professional",
            "subcategory":"Lawyer & Legal Services",
            "type":"Services"
        }
    ],
    "sg:phone":"+1 407 648 0058",
    "sg:postcode":"32804",
    "sg:province":"FL",
    "sg:tags":[
        "attorney"
    ],
    "sg:website":"www.whmh.com",
    "wof:name":"Wolff Hill Mcfarlin & Herron",
    "wof:placetype":"venue"
},
  "geometry": {"coordinates":[-81.40409,28.552969],"type":"Point"}
}