{
  "type": "Feature",
  "properties": {
    "iso:country":"US",
    "sg:address":"13180 Cleveland Ave",
    "sg:city":"Fort Myers",
    "sg:classifiers":[
        {
            "category":"Real Estate",
            "subcategory":"Real Estate Agent",
            "type":"Services"
        }
    ],
    "sg:phone":"+1 239 652 0019",
    "sg:postcode":"33903",
    "sg:province":"FL",
    "wof:name":"West Point Real Estate",
    "wof:placetype":"venue"
},
  "geometry": {"coordinates":[-81.88657499999999,26.663641],"type":"Point"}
}