{
  "type": "Feature",
  "properties": {
    "addr:full":"981 Ulmer Rd Frostproof FL 33843",
    "addr:housenumber":"981",
    "addr:postcode":"33843",
    "addr:street":"Ulmer Rd",
    "iso:country":"US",
    "sg:address":"981 Ulmer Rd",
    "sg:city":"Frostproof",
    "sg:classifiers":[
        {
            "category":"Real Estate",
            "subcategory":"Real Estate Operator",
            "type":"Services"
        }
    ],
    "sg:phone":"+1 863 635 3215",
    "sg:postcode":"33843",
    "sg:province":"FL",
    "sg:tags":[
        "mobile",
        "home",
        "community"
    ],
    "wof:name":"Frostproof Mobile Home Park",
    "wof:placetype":"venue"
},
  "geometry": {"coordinates":[-81.538881,27.757558],"type":"Point"}
}