{
  "type": "Feature",
  "properties": {
    "iso:country":"US",
    "sg:address":"3845 Sutton Place Blvd",
    "sg:city":"Winter Park",
    "sg:classifiers":[
        {
            "category":"Building & Trades",
            "subcategory":"Locksmith",
            "type":"Services"
        }
    ],
    "sg:phone":"+1 407 702 1269",
    "sg:postcode":"32792",
    "sg:province":"FL",
    "sg:tags":[
        "key"
    ],
    "wof:name":"Aaland 24 Hour Locksmith",
    "wof:placetype":"venue"
},
  "geometry": {"coordinates":[-81.294585,28.594854],"type":"Point"}
}