{
  "type": "Feature",
  "properties": {
    "addr:full":"7316 Manatee Ave W Bradenton FL 34209",
    "addr:housenumber":"7316",
    "addr:postcode":"34209",
    "addr:street":"Manatee Ave W",
    "iso:country":"US",
    "sg:address":"7316 Manatee Ave W",
    "sg:city":"Bradenton",
    "sg:classifiers":[
        {
            "category":"Building & Trades",
            "subcategory":"Landscaping Services",
            "type":"Services"
        }
    ],
    "sg:phone":"+1 941 714 0606",
    "sg:postcode":"34209",
    "sg:province":"FL",
    "sg:tags":[
        "tree",
        "landscape"
    ],
    "wof:name":"J C Tree & Landscape",
    "wof:placetype":"venue"
},
  "geometry": {"coordinates":[-82.635499,27.496219],"type":"Point"}
}