{
  "type": "Feature",
  "properties": {
    "iso:country":"US",
    "sg:address":"1118 S Florida Ave",
    "sg:city":"Lakeland",
    "sg:classifiers":[
        {
            "category":"Building & Trades",
            "subcategory":"Construction",
            "type":"Services"
        }
    ],
    "sg:phone":"+1 863 858 9590",
    "sg:postcode":"33803",
    "sg:province":"FL",
    "sg:tags":[
        "house",
        "family"
    ],
    "wof:name":"Crovo Construction",
    "wof:placetype":"venue"
},
  "geometry": {"coordinates":[-81.95704000000001,28.029419],"type":"Point"}
}