{
  "type": "Feature",
  "properties": {
    "iso:country":"US",
    "sg:address":"1116 Le Brun Dr",
    "sg:city":"Jacksonville",
    "sg:classifiers":[
        {
            "category":"Freight",
            "type":"Transportation"
        }
    ],
    "sg:phone":"+1 904 786 0149",
    "sg:postcode":"32205",
    "sg:province":"FL",
    "sg:tags":[
        "operator",
        "local",
        "trucking"
    ],
    "wof:name":"Edward Boyd Hauling",
    "wof:placetype":"venue"
},
  "geometry": {"coordinates":[-81.764003,30.303539],"type":"Point"}
}