{
  "type": "Feature",
  "properties": {
    "iso:country":"US",
    "sg:address":"4037 Crockers Lake Blvd",
    "sg:city":"Sarasota",
    "sg:classifiers":[
        {
            "category":"Professional",
            "subcategory":"Art Services",
            "type":"Services"
        }
    ],
    "sg:phone":"+1 941 925 1740",
    "sg:postcode":"34238",
    "sg:province":"FL",
    "sg:tags":[
        "artist"
    ],
    "wof:name":"Serena Becroft Artist",
    "wof:placetype":"venue"
},
  "geometry": {"coordinates":[-82.48809199999999,27.233428],"type":"Point"}
}