{
  "type": "Feature",
  "properties": {
    "addr:full":"43 Estate Dr Boynton Beach FL 33436",
    "addr:housenumber":"43",
    "addr:postcode":"33436",
    "addr:street":"Estate Dr",
    "iso:country":"US",
    "sg:address":"43 Estate Dr",
    "sg:city":"Boynton Beach",
    "sg:classifiers":[
        {
            "category":"Professional",
            "subcategory":"Accounting & Tax Preparation",
            "type":"Services"
        }
    ],
    "sg:phone":"+1 561 736 7274",
    "sg:postcode":"33436",
    "sg:province":"FL",
    "wof:name":"Harold Shapot CPA",
    "wof:placetype":"venue"
},
  "geometry": {"coordinates":[-80.10598899999999,26.490706],"type":"Point"}
}