{
  "type": "Feature",
  "properties": {
    "addr:full":"555 N Federal Hwy Boca Raton FL 33432",
    "addr:housenumber":"555",
    "addr:postcode":"33432",
    "addr:street":"N Federal Hwy",
    "iso:country":"US",
    "sg:address":"555 N Federal Hwy",
    "sg:city":"Boca Raton",
    "sg:classifiers":[
        {
            "category":"Banks & Credit Unions",
            "subcategory":"Investment Brokerage",
            "type":"Services"
        }
    ],
    "sg:phone":"+1 561 417 2626",
    "sg:postcode":"33432",
    "sg:province":"FL",
    "sg:tags":[
        "stock",
        "bond"
    ],
    "wof:name":"Scottrade Inc",
    "wof:placetype":"venue"
},
  "geometry": {"coordinates":[-80.086551,26.354594],"type":"Point"}
}