{
  "type": "Feature",
  "properties": {
    "iso:country":"US",
    "sg:address":"16278 NW 21st St",
    "sg:city":"Hollywood",
    "sg:classifiers":[
        {
            "category":"Shopping",
            "type":"Retail Goods"
        }
    ],
    "sg:phone":"+1 954 392 7453",
    "sg:postcode":"33028",
    "sg:province":"FL",
    "sg:tags":[
        "equipment",
        "telephone",
        "merchandise",
        "supply"
    ],
    "wof:name":"Access Datacom",
    "wof:placetype":"venue"
},
  "geometry": {"coordinates":[-80.364594,26.026563],"type":"Point"}
}