{
  "type": "Feature",
  "properties": {
    "iso:country":"US",
    "sg:address":"8081 NW 54th St",
    "sg:city":"Lauderhill",
    "sg:classifiers":[
        {
            "category":"Manufacturing",
            "subcategory":"Printing",
            "type":"Manufacturing & Wholesale Goods"
        }
    ],
    "sg:phone":"+1 954 578 3575",
    "sg:postcode":"33351",
    "sg:province":"FL",
    "sg:tags":[
        "publisher"
    ],
    "wof:name":"Divine Mercy Publications Inc",
    "wof:placetype":"venue"
},
  "geometry": {"coordinates":[-80.258571,26.191568],"type":"Point"}
}