{
  "type": "Feature",
  "properties": {
    "iso:country":"US",
    "sg:address":"185 10th St S",
    "sg:city":"Naples",
    "sg:classifiers":[
        {
            "category":"Building & Trades",
            "subcategory":"Landscaping Services",
            "type":"Services"
        }
    ],
    "sg:phone":"+1 239 643 0077",
    "sg:postcode":"34102",
    "sg:province":"FL",
    "sg:tags":[
        "designer",
        "landscape"
    ],
    "wof:name":"Goetz & Stropes Landscape Arch",
    "wof:placetype":"venue"
},
  "geometry": {"coordinates":[-81.793898,26.146232],"type":"Point"}
}