{
  "type": "Feature",
  "properties": {
    "iso:country":"US",
    "sg:address":"3229 Timothy St",
    "sg:city":"Apopka",
    "sg:classifiers":[
        {
            "category":"Shopping",
            "subcategory":"Computers & Home Electronics",
            "type":"Retail Goods"
        }
    ],
    "sg:phone":"+1 407 772 0174",
    "sg:postcode":"32703",
    "sg:province":"FL",
    "sg:tags":[
        "equipment",
        "electronic",
        "supply"
    ],
    "wof:name":"BJG Electronics Inc",
    "wof:placetype":"venue"
},
  "geometry": {"coordinates":[-81.449471,28.663655],"type":"Point"}
}