{
  "type": "Feature",
  "properties": {
    "addr:full":"4712 Geiger Rd Milton FL 32583",
    "addr:housenumber":"4712",
    "addr:postcode":"32583",
    "addr:street":"Geiger Rd",
    "iso:country":"US",
    "sg:address":"4712 Geiger Rd",
    "sg:city":"Milton",
    "sg:classifiers":[
        {
            "category":"Building & Trades",
            "subcategory":"Landscaping Services",
            "type":"Services"
        }
    ],
    "sg:phone":"+1 850 623 5001",
    "sg:postcode":"32583",
    "sg:province":"FL",
    "wof:name":"Mother Earth Grounds Lawn Kare",
    "wof:placetype":"venue"
},
  "geometry": {"coordinates":[-86.969368,30.603972],"type":"Point"}
}