{
  "type": "Feature",
  "properties": {
    "addr:full":"16976 SW 145th Ave Miami FL 33177",
    "addr:housenumber":"16976",
    "addr:postcode":"33177",
    "addr:street":"Sw 145Th Ave",
    "iso:country":"US",
    "sg:address":"16976 SW 145th Ave",
    "sg:city":"Miami",
    "sg:classifiers":[
        {
            "category":"Food & Beverages",
            "subcategory":"Groceries & Convenience Stores",
            "type":"Retail Goods"
        }
    ],
    "sg:phone":"+1 305 232 8607",
    "sg:postcode":"33177",
    "sg:province":"FL",
    "wof:name":"Zesty Food Snacks Corporation",
    "wof:placetype":"venue"
},
  "geometry": {"coordinates":[-80.427633,25.609146],"type":"Point"}
}