{
  "type": "Feature",
  "properties": {
    "iso:country":"US",
    "sg:address":"5849 Washington St",
    "sg:city":"Hollywood",
    "sg:classifiers":[
        {
            "category":"Museum",
            "type":"Entertainment"
        }
    ],
    "sg:phone":"+1 954 893 5607",
    "sg:postcode":"33023",
    "sg:province":"FL",
    "sg:tags":[
        "gallery"
    ],
    "wof:name":"Hicks Reese & Delores",
    "wof:placetype":"venue"
},
  "geometry": {"coordinates":[-80.206461,26.002726],"type":"Point"}
}