{
  "type": "Feature",
  "properties": {
    "iso:country":"US",
    "sg:address":"36654 State Road 54",
    "sg:city":"Zephyrhills",
    "sg:classifiers":[
        {
            "category":"Retail",
            "subcategory":"Storage",
            "type":"Services"
        }
    ],
    "sg:phone":"+1 813 428 8693",
    "sg:postcode":"33541",
    "sg:province":"FL",
    "sg:tags":[
        "automobile",
        "self",
        "commercial",
        "household"
    ],
    "sg:website":"http://www.storagefront.com",
    "wof:name":"U-Stor Zephyrhills",
    "wof:placetype":"venue"
},
  "geometry": {"coordinates":[-82.21169399999999,28.229947],"type":"Point"}
}