{
  "type": "Feature",
  "properties": {
    "iso:country":"US",
    "sg:address":"9070 SW 157th Pl",
    "sg:city":"Miami",
    "sg:classifiers":[
        {
            "category":"Manufacturing",
            "subcategory":"Paper Products",
            "type":"Manufacturing & Wholesale Goods"
        }
    ],
    "sg:phone":"+1 305 255 5178",
    "sg:postcode":"33196",
    "sg:province":"FL",
    "sg:tags":[
        "bamboo"
    ],
    "wof:name":"Terra Palms Nursery",
    "wof:placetype":"venue"
},
  "geometry": {"coordinates":[-80.448547,25.681933],"type":"Point"}
}