{
  "type": "Feature",
  "properties": {
    "addr:full":"7621 Frog Log Ln Leesburg FL 34748",
    "addr:housenumber":"7621",
    "addr:postcode":"34748",
    "addr:street":"Frog Log Ln",
    "iso:country":"US",
    "sg:address":"7621 Frog Log Ln",
    "sg:city":"Leesburg",
    "sg:classifiers":[
        {
            "category":"Professional",
            "type":"Services"
        }
    ],
    "sg:phone":"+1 352 326 5242",
    "sg:postcode":"34748",
    "sg:province":"FL",
    "wof:name":"Thomas M Felton",
    "wof:placetype":"venue"
},
  "geometry": {"coordinates":[-81.83282800000001,28.792051],"type":"Point"}
}