{
  "type": "Feature",
  "properties": {
    "iso:country":"US",
    "sg:address":"19160 Peachland Blvd",
    "sg:city":"Port Charlotte",
    "sg:classifiers":[
        {
            "category":"Home & Garden",
            "subcategory":"Hardware",
            "type":"Retail Goods"
        },
        {
            "category":"Wholesale",
            "subcategory":"Hardware",
            "type":"Manufacturing & Wholesale Goods"
        }
    ],
    "sg:phone":"+1 941 255 1060",
    "sg:postcode":"33948",
    "sg:province":"FL",
    "sg:tags":[
        "tool"
    ],
    "wof:name":"Jackson's Tools",
    "wof:placetype":"venue"
},
  "geometry": {"coordinates":[-82.131618,27.016441],"type":"Point"}
}