{
  "type": "Feature",
  "properties": {
    "iso:country":"US",
    "sg:address":"2686 NW 12th Ave",
    "sg:city":"Miami",
    "sg:classifiers":[
        {
            "category":"Autos & Motor Vehicles",
            "subcategory":"Auto Supplies",
            "type":"Retail Goods"
        }
    ],
    "sg:phone":"+1 305 887 5460",
    "sg:postcode":"33127",
    "sg:province":"FL",
    "wof:name":"Gaelon Auto Parts Corp",
    "wof:placetype":"venue"
},
  "geometry": {"coordinates":[-80.215457,25.80099],"type":"Point"}
}