{
  "type": "Feature",
  "properties": {
    "iso:country":"US",
    "sg:address":"10031 Pines Blvd",
    "sg:city":"Hollywood",
    "sg:classifiers":[
        {
            "category":"Wholesale",
            "subcategory":"Groceries",
            "type":"Manufacturing & Wholesale Goods"
        }
    ],
    "sg:phone":"+1 954 843 0562",
    "sg:postcode":"33024",
    "sg:province":"FL",
    "sg:tags":[
        "frozen",
        "food"
    ],
    "wof:name":"Bottomline Foods",
    "wof:placetype":"venue"
},
  "geometry": {"coordinates":[-80.27867500000001,26.008429],"type":"Point"}
}