{
  "type": "Feature",
  "properties": {
    "addr:full":"300 SW 72nd Pl Ocala FL 34476",
    "addr:housenumber":"300",
    "addr:postcode":"34476",
    "addr:street":"Sw 72Nd Pl",
    "iso:country":"US",
    "sg:address":"300 SW 72nd Pl",
    "sg:city":"Ocala",
    "sg:classifiers":[
        {
            "category":"Education",
            "subcategory":"Special Training",
            "type":"Public Place"
        }
    ],
    "sg:phone":"+1 352 237 3363",
    "sg:postcode":"34476",
    "sg:province":"FL",
    "sg:tags":[
        "instruction",
        "music"
    ],
    "wof:name":"Skillfull Hands By Deena Cole",
    "wof:placetype":"venue"
},
  "geometry": {"coordinates":[-82.13833099999999,29.114073],"type":"Point"}
}