{
  "type": "Feature",
  "properties": {
    "iso:country":"US",
    "sg:address":"1212 E Broward Blvd",
    "sg:city":"Fort Lauderdale",
    "sg:classifiers":[
        {
            "category":"Health Services",
            "subcategory":"Doctor",
            "type":"Services"
        }
    ],
    "sg:phone":"+1 954 462 1526",
    "sg:postcode":"33301",
    "sg:province":"FL",
    "sg:tags":[
        "surgeon",
        "orthopedic"
    ],
    "wof:name":"Lauderdale Orthopedic Surgeons",
    "wof:placetype":"venue"
},
  "geometry": {"coordinates":[-80.13026000000001,26.122607],"type":"Point"}
}