{
  "type": "Feature",
  "properties": {
    "addr:full":"3150 S Babcock St Melbourne FL 32901",
    "addr:housenumber":"3150",
    "addr:postcode":"32901",
    "addr:street":"S Babcock St",
    "iso:country":"US",
    "sg:address":"3150 S Babcock St",
    "sg:city":"Melbourne",
    "sg:classifiers":[
        {
            "category":"Restaurant",
            "type":"Food & Drink"
        }
    ],
    "sg:menulink":"http://www.allmenus.com/fl/melbourne/62200-mighty-mushroom/menu/",
    "sg:phone":"+1 321 676 5661",
    "sg:postcode":"32901",
    "sg:province":"FL",
    "sg:tags":[
        "american",
        "pizza"
    ],
    "wof:name":"Mighty Mushroom",
    "wof:placetype":"venue"
},
  "geometry": {"coordinates":[-80.621686,28.062883],"type":"Point"}
}