{
  "type": "Feature",
  "properties": {
    "iso:country":"US",
    "sg:address":"2023 NE 8th Rd",
    "sg:city":"Ocala",
    "sg:classifiers":[
        {
            "category":"Building & Trades",
            "subcategory":"Construction",
            "type":"Services"
        }
    ],
    "sg:phone":"+1 352 622 1626",
    "sg:postcode":"34470",
    "sg:province":"FL",
    "sg:tags":[
        "roofing",
        "contractor"
    ],
    "wof:name":"Slack Const Metal Master Rfng",
    "wof:placetype":"venue"
},
  "geometry": {"coordinates":[-82.128096,29.207708],"type":"Point"}
}