{
  "type": "Feature",
  "properties": {
    "iso:country":"US",
    "sg:address":"359 W Dearborn St",
    "sg:city":"Englewood",
    "sg:classifiers":[
        {
            "category":"Professional",
            "subcategory":"Employment Agencies",
            "type":"Services"
        }
    ],
    "sg:phone":"+1 941 234 7476",
    "sg:postcode":"34223",
    "sg:province":"FL",
    "wof:name":"Florida Employment Development Services",
    "wof:placetype":"venue"
},
  "geometry": {"coordinates":[-82.36035800000001,26.962202],"type":"Point"}
}