{
  "type": "Feature",
  "properties": {
    "addr:full":"1570 Alton Rd Miami Beach FL 33139",
    "addr:housenumber":"1570",
    "addr:postcode":"33139",
    "addr:street":"Alton Rd",
    "iso:country":"US",
    "sg:address":"1570 Alton Rd",
    "sg:city":"Miami Beach",
    "sg:classifiers":[
        {
            "category":"Coffee & Tea",
            "type":"Food & Drink"
        }
    ],
    "sg:menulink":"http://www.allmenus.com/fl/miami-beach/116778-starbucks-coffee/menu/",
    "sg:phone":"+1 305 538 0958",
    "sg:postcode":"33139",
    "sg:province":"FL",
    "sg:tags":[
        "american"
    ],
    "wof:name":"Starbucks Coffee",
    "wof:placetype":"venue"
},
  "geometry": {"coordinates":[-80.141431,25.788696],"type":"Point"}
}