{
  "type": "Feature",
  "properties": {
    "iso:country":"US",
    "sg:address":"15455 SW 74th Circle Ct",
    "sg:city":"Miami",
    "sg:classifiers":[
        {
            "category":"Building & Trades",
            "subcategory":"Construction",
            "type":"Services"
        }
    ],
    "sg:phone":"+1 305 386 2034",
    "sg:postcode":"33193",
    "sg:province":"FL",
    "sg:tags":[
        "carpentry",
        "contractor"
    ],
    "wof:name":"Marios Carpentry Inc",
    "wof:placetype":"venue"
},
  "geometry": {"coordinates":[-80.443749,25.696882],"type":"Point"}
}