{
  "type": "Feature",
  "properties": {
    "iso:country":"US",
    "sg:address":"20099 SW 127th Ave",
    "sg:city":"Miami",
    "sg:classifiers":[
        {
            "category":"Banks & Credit Unions",
            "subcategory":"Bank",
            "type":"Services"
        },
        {
            "category":"Banks & Credit Unions",
            "subcategory":"Financial Services",
            "type":"Services"
        }
    ],
    "sg:phone":"+1 786 478 3139",
    "sg:postcode":"33177",
    "sg:province":"FL",
    "sg:tags":[
        "saving",
        "commercial"
    ],
    "sg:website":"http://locators.bankofamerica.com/a/BC-16550",
    "wof:name":"Bank Of America, National Association",
    "wof:placetype":"venue"
},
  "geometry": {"coordinates":[-80.396992,25.579698],"type":"Point"}
}