{
  "type": "Feature",
  "properties": {
    "addr:full":"219 8th Ave S Naples FL 34102",
    "addr:housenumber":"219",
    "addr:postcode":"34102",
    "addr:street":"8Th Ave S",
    "iso:country":"US",
    "sg:address":"219 8th Ave S",
    "sg:city":"Naples",
    "sg:classifiers":[
        {
            "category":"Professional",
            "type":"Services"
        }
    ],
    "sg:phone":"+1 239 261 3924",
    "sg:postcode":"34102",
    "sg:province":"FL",
    "sg:tags":[
        "establishment"
    ],
    "wof:name":"Petroff NG",
    "wof:placetype":"venue"
},
  "geometry": {"coordinates":[-81.80289,26.137685],"type":"Point"}
}