{
  "type": "Feature",
  "properties": {
    "addr:full":"7204 US Hwy 301 Ellenton FL 34222",
    "addr:housenumber":"7204",
    "addr:postcode":"34222",
    "addr:street":"Us Hwy 301",
    "iso:country":"US",
    "sg:address":"7204 US Hwy 301",
    "sg:city":"Ellenton",
    "sg:classifiers":[
        {
            "category":"Banks & Credit Unions",
            "subcategory":"Bank",
            "type":"Services"
        }
    ],
    "sg:phone":"+1 941 729 0569",
    "sg:postcode":"34222",
    "sg:province":"FL",
    "sg:tags":[
        "commercial"
    ],
    "wof:name":"Manatee River Community Bank",
    "wof:placetype":"venue"
},
  "geometry": {"coordinates":[-82.490089,27.536226],"type":"Point"}
}