{
  "type": "Feature",
  "properties": {
    "iso:country":"US",
    "sg:address":"3670 23rd Ave S",
    "sg:city":"Lake Worth",
    "sg:classifiers":[
        {
            "category":"Retail",
            "subcategory":"Laundry & Dry Cleaning",
            "type":"Services"
        }
    ],
    "sg:phone":"+1 561 586 5700",
    "sg:postcode":"33461",
    "sg:province":"FL",
    "sg:tags":[
        "premises",
        "on",
        "carpet",
        "rug",
        "cleaners"
    ],
    "wof:name":"Stanley Steamer Carpet Cleaner",
    "wof:placetype":"venue"
},
  "geometry": {"coordinates":[-80.077877,26.62261],"type":"Point"}
}