{
  "type": "Feature",
  "properties": {
    "addr:full":"3200 SW 34th Ave Ocala FL 34474",
    "addr:housenumber":"3200",
    "addr:postcode":"34474",
    "addr:street":"Sw 34Th Ave",
    "iso:country":"US",
    "sg:address":"3200 SW 34th Ave",
    "sg:city":"Ocala",
    "sg:classifiers":[
        {
            "category":"Health Services",
            "subcategory":"Clinic",
            "type":"Services"
        }
    ],
    "sg:phone":"+1 352 690 7200",
    "sg:postcode":"34474",
    "sg:province":"FL",
    "sg:tags":[
        "medical"
    ],
    "wof:name":"Marion Oaks Medical Clinic",
    "wof:placetype":"venue"
},
  "geometry": {"coordinates":[-82.177933,29.153543],"type":"Point"}
}