{
  "type": "Feature",
  "properties": {
    "iso:country":"US",
    "sg:address":"2950 Clark Rd Apt 114",
    "sg:city":"Sarasota",
    "sg:classifiers":[
        {
            "category":"Professional",
            "subcategory":"Detective & Security Services",
            "type":"Services"
        }
    ],
    "sg:phone":"+1 941 379 9553",
    "sg:postcode":"34231",
    "sg:province":"FL",
    "sg:tags":[
        "information",
        "bureau"
    ],
    "wof:name":"Sarasota Q Services",
    "wof:placetype":"venue"
},
  "geometry": {"coordinates":[-82.51084299999999,27.269364],"type":"Point"}
}