{
  "type": "Feature",
  "properties": {
    "iso:country":"US",
    "sg:address":"5821 NW 7th Ave",
    "sg:city":"Miami",
    "sg:classifiers":[
        {
            "category":"Real Estate",
            "subcategory":"Real Estate Operator",
            "type":"Services"
        }
    ],
    "sg:phone":"+1 305 757 6604",
    "sg:postcode":"33127",
    "sg:province":"FL",
    "sg:tags":[
        "building",
        "apartment"
    ],
    "wof:name":"Edison Towers",
    "wof:placetype":"venue"
},
  "geometry": {"coordinates":[-80.208339,25.830442],"type":"Point"}
}