{
  "type": "Feature",
  "properties": {
    "iso:country":"US",
    "sg:address":"5370 Palm Ave Ste 9",
    "sg:city":"Hialeah",
    "sg:classifiers":[
        {
            "category":"Professional",
            "subcategory":"Accounting & Tax Preparation",
            "type":"Services"
        }
    ],
    "sg:phone":"+1 305 557 1662",
    "sg:postcode":"33012",
    "sg:province":"FL",
    "sg:tags":[
        "accountant"
    ],
    "wof:name":"M & M Accounting Service Inc",
    "wof:placetype":"venue"
},
  "geometry": {"coordinates":[-80.283203,25.871201],"type":"Point"}
}