{
  "type": "Feature",
  "properties": {
    "addr:full":"3208 Central Ave Fort Myers FL 33901",
    "addr:housenumber":"3208",
    "addr:postcode":"33901",
    "addr:street":"Central Ave",
    "iso:country":"US",
    "sg:address":"3208 Central Ave",
    "sg:city":"Fort Myers",
    "sg:classifiers":[
        {
            "category":"Organizations",
            "subcategory":"Religious Organization",
            "type":"Services"
        }
    ],
    "sg:phone":"+1 239 936 1054",
    "sg:postcode":"33901",
    "sg:province":"FL",
    "wof:name":"Central Haitian Mission",
    "wof:placetype":"venue"
},
  "geometry": {"coordinates":[-81.864098,26.6187],"type":"Point"}
}