{
  "type": "Feature",
  "properties": {
    "iso:country":"US",
    "sg:address":"11440 Okeechobee Blvd",
    "sg:city":"Royal Palm Beach",
    "sg:classifiers":[
        {
            "category":"Real Estate",
            "subcategory":"Real Estate Agent",
            "type":"Services"
        }
    ],
    "sg:phone":"+1 561 798 3957",
    "sg:postcode":"33411",
    "sg:province":"FL",
    "wof:name":"Ravenssaood Properties",
    "wof:placetype":"venue"
},
  "geometry": {"coordinates":[-80.209172,26.709328],"type":"Point"}
}