{
  "type": "Feature",
  "properties": {
    "addr:full":"340 Eagle Dr Jupiter FL 33477",
    "addr:housenumber":"340",
    "addr:postcode":"33477",
    "addr:street":"Eagle Dr",
    "iso:country":"US",
    "sg:address":"340 Eagle Dr",
    "sg:city":"Jupiter",
    "sg:classifiers":[
        {
            "category":"Real Estate",
            "subcategory":"Developer",
            "type":"Services"
        }
    ],
    "sg:phone":"+1 561 743 4970",
    "sg:postcode":"33477",
    "sg:province":"FL",
    "wof:name":"JM Glad Corp",
    "wof:placetype":"venue"
},
  "geometry": {"coordinates":[-80.082651,26.899176],"type":"Point"}
}