{
  "type": "Feature",
  "properties": {
    "iso:country":"US",
    "sg:address":"310 NW 11th Ave",
    "sg:city":"Trenton",
    "sg:classifiers":[
        {
            "category":"Education",
            "subcategory":"School",
            "type":"Public Place"
        }
    ],
    "sg:phone":"+1 352 463 3200",
    "sg:postcode":"32693",
    "sg:province":"FL",
    "sg:tags":[
        "district"
    ],
    "sg:website":"www.gilchristschools.org",
    "wof:name":"Gilchrist County School Supt",
    "wof:placetype":"venue"
},
  "geometry": {"coordinates":[-82.821129,29.620642],"type":"Point"}
}