{
  "type": "Feature",
  "properties": {
    "iso:country":"US",
    "sg:address":"10737 SW 118th Ct",
    "sg:city":"Miami",
    "sg:classifiers":[
        {
            "category":"Professional",
            "subcategory":"Engineering",
            "type":"Services"
        }
    ],
    "sg:phone":"+1 305 270 9542",
    "sg:postcode":"33186",
    "sg:province":"FL",
    "wof:name":"Boddentown Dev Co",
    "wof:placetype":"venue"
},
  "geometry": {"coordinates":[-80.386419,25.668663],"type":"Point"}
}