{
  "type": "Feature",
  "properties": {
    "iso:country":"US",
    "sg:address":"5509 Broadway",
    "sg:city":"West Palm Beach",
    "sg:classifiers":[
        {
            "category":"Food & Beverages",
            "subcategory":"Meat & Fish",
            "type":"Retail Goods"
        }
    ],
    "sg:phone":"+1 561 848 1349",
    "sg:postcode":"33407",
    "sg:province":"FL",
    "wof:name":"Pan American Grocery",
    "wof:placetype":"venue"
},
  "geometry": {"coordinates":[-80.05552900000001,26.760228],"type":"Point"}
}