{
  "type": "Feature",
  "properties": {
    "iso:country":"US",
    "sg:address":"5777 Bird Rd",
    "sg:city":"Miami",
    "sg:classifiers":[
        {
            "category":"Coffee & Tea",
            "type":"Food & Drink"
        },
        {
            "category":"Restaurant",
            "type":"Food & Drink"
        },
        {
            "category":"Bakery",
            "type":"Food & Drink"
        },
        {
            "category":"Deli",
            "type":"Food & Drink"
        }
    ],
    "sg:phone":"+1 305 668 0366",
    "sg:postcode":"33155",
    "sg:province":"FL",
    "sg:tags":[
        "cuban"
    ],
    "wof:name":"Gilbert's Bakery",
    "wof:placetype":"venue"
},
  "geometry": {"coordinates":[-80.288597,25.7339],"type":"Point"}
}