{
  "type": "Feature",
  "properties": {
    "iso:country":"US",
    "sg:address":"1000 Ponce de Leon Blvd",
    "sg:city":"Coral Gables",
    "sg:classifiers":[
        {
            "category":"Real Estate",
            "subcategory":"Real Estate Agent",
            "type":"Services"
        }
    ],
    "sg:phone":"+1 305 441 2728",
    "sg:postcode":"33134",
    "sg:province":"FL",
    "sg:tags":[
        "appraiser"
    ],
    "wof:name":"Hemisphere Real Estate Inc",
    "wof:placetype":"venue"
},
  "geometry": {"coordinates":[-80.259063,25.761302],"type":"Point"}
}