{
  "type": "Feature",
  "properties": {
    "addr:full":"2518 E Hallandale Beach Blvd Hallandale Beach FL 33009",
    "addr:housenumber":"2518",
    "addr:postcode":"33009",
    "addr:street":"E Hallandale Beach Blvd",
    "iso:country":"US",
    "sg:address":"2518 E Hallandale Beach Blvd",
    "sg:city":"Hallandale Beach",
    "sg:classifiers":[
        {
            "category":"Health Services",
            "subcategory":"Doctor",
            "type":"Services"
        }
    ],
    "sg:phone":"+1 954 454 2504",
    "sg:postcode":"33009",
    "sg:province":"FL",
    "sg:tags":[
        "dentist"
    ],
    "wof:name":"Alberto Q Despaigne DDS",
    "wof:placetype":"venue"
},
  "geometry": {"coordinates":[-80.125348,25.986196],"type":"Point"}
}