{
  "type": "Feature",
  "properties": {
    "addr:full":"5910 Devon Ln Fort Lauderdale FL 33331",
    "addr:housenumber":"5910",
    "addr:postcode":"33331",
    "addr:street":"Devon Ln",
    "iso:country":"US",
    "sg:address":"5910 Devon Ln",
    "sg:city":"Fort Lauderdale",
    "sg:classifiers":[
        {
            "category":"Professional",
            "type":"Services"
        }
    ],
    "sg:phone":"+1 954 434 0620",
    "sg:postcode":"33331",
    "sg:province":"FL",
    "wof:name":"Antico Corp",
    "wof:placetype":"venue"
},
  "geometry": {"coordinates":[-80.355418,26.044925],"type":"Point"}
}