{
  "type": "Feature",
  "properties": {
    "iso:country":"US",
    "sg:address":"307 S Fielding Ave",
    "sg:city":"Tampa",
    "sg:classifiers":[
        {
            "category":"Professional",
            "subcategory":"Lawyer & Legal Services",
            "type":"Services"
        }
    ],
    "sg:phone":"+1 813 250 9797",
    "sg:postcode":"33606",
    "sg:province":"FL",
    "sg:tags":[
        "attorney"
    ],
    "wof:name":"Charles V Barrett",
    "wof:placetype":"venue"
},
  "geometry": {"coordinates":[-82.467731,27.940643],"type":"Point"}
}