{
  "type": "Feature",
  "properties": {
    "addr:full":"2410 SE Bridge Rd Hobe Sound FL 33455",
    "addr:housenumber":"2410",
    "addr:postcode":"33455",
    "addr:street":"Se Bridge Rd",
    "iso:country":"US",
    "sg:address":"2410 SE Bridge Rd",
    "sg:city":"Hobe Sound",
    "sg:classifiers":[
        {
            "category":"Farming",
            "subcategory":"Orchard",
            "type":"Manufacturing & Wholesale Goods"
        }
    ],
    "sg:phone":"+1 561 746 3467",
    "sg:postcode":"33455",
    "sg:province":"FL",
    "sg:tags":[
        "orange",
        "grove",
        "grapefruit"
    ],
    "wof:name":"Sunrise Citrus Groves Inc",
    "wof:placetype":"venue"
},
  "geometry": {"coordinates":[-80.225008,27.043902],"type":"Point"}
}