{
  "type": "Feature",
  "properties": {
    "addr:full":"901 N Nova Rd Daytona Beach FL 32117",
    "addr:housenumber":"901",
    "addr:postcode":"32117",
    "addr:street":"N Nova Rd",
    "iso:country":"US",
    "sg:address":"901 N Nova Rd",
    "sg:city":"Daytona Beach",
    "sg:classifiers":[
        {
            "category":"Autos & Motor Vehicles",
            "subcategory":"Automobile Sales",
            "type":"Retail Goods"
        }
    ],
    "sg:phone":"+1 386 258 3311",
    "sg:postcode":"32117",
    "sg:province":"FL",
    "sg:tags":[
        "car",
        "dealership",
        "dealer"
    ],
    "wof:name":"Jon Hall Pontiac-G M C",
    "wof:placetype":"venue"
},
  "geometry": {"coordinates":[-81.04926399999999,29.223571],"type":"Point"}
}