{
  "type": "Feature",
  "properties": {
    "addr:full":"5355 SW College Rd Ocala FL 34474",
    "addr:housenumber":"5355",
    "addr:postcode":"34474",
    "addr:street":"Sw College Rd",
    "iso:country":"US",
    "sg:address":"5355 SW College Rd",
    "sg:city":"Ocala",
    "sg:classifiers":[
        {
            "category":"Insurance",
            "subcategory":"Insurance Agent",
            "type":"Services"
        }
    ],
    "sg:phone":"+1 352 861 2266",
    "sg:postcode":"34474",
    "sg:province":"FL",
    "wof:name":"State Farm Insurance",
    "wof:placetype":"venue"
},
  "geometry": {"coordinates":[-82.21008500000001,29.125749],"type":"Point"}
}