{
  "type": "Feature",
  "properties": {
    "iso:country":"US",
    "sg:address":"2443 US Hwy 301",
    "sg:city":"Ellenton",
    "sg:classifiers":[
        {
            "category":"Personal",
            "subcategory":"Beauty Salon",
            "type":"Services"
        }
    ],
    "sg:phone":"+1 941 721 8799",
    "sg:postcode":"34222",
    "sg:province":"FL",
    "sg:tags":[
        "shop"
    ],
    "wof:name":"Touch of Style",
    "wof:placetype":"venue"
},
  "geometry": {"coordinates":[-82.53954400000001,27.521448],"type":"Point"}
}