{
  "type": "Feature",
  "properties": {
    "iso:country":"US",
    "sg:address":"1809 Miccosukee Commons Dr",
    "sg:city":"Tallahassee",
    "sg:classifiers":[
        {
            "category":"Professional",
            "subcategory":"Engineering",
            "type":"Services"
        }
    ],
    "sg:phone":"+1 850 386 9898",
    "sg:postcode":"32308",
    "sg:province":"FL",
    "sg:tags":[
        "engineer"
    ],
    "wof:name":"Meridian Consulting Inc",
    "wof:placetype":"venue"
},
  "geometry": {"coordinates":[-84.23251399999999,30.464912],"type":"Point"}
}