{
  "type": "Feature",
  "properties": {
    "iso:country":"US",
    "sg:address":"5415 1st Rd",
    "sg:city":"Lake Worth",
    "sg:classifiers":[
        {
            "category":"Professional",
            "subcategory":"Business Services",
            "type":"Services"
        }
    ],
    "sg:phone":"+1 561 967 4891",
    "sg:postcode":"33467",
    "sg:province":"FL",
    "wof:name":"Zettle Enterprises Inc",
    "wof:placetype":"venue"
},
  "geometry": {"coordinates":[-80.16284400000001,26.600733],"type":"Point"}
}