{
  "type": "Feature",
  "properties": {
    "iso:country":"US",
    "sg:address":"9335 E Fowler Ave",
    "sg:city":"Thonotosassa",
    "sg:classifiers":[
        {
            "category":"Shopping",
            "subcategory":"Bicycles & Sporting Goods",
            "type":"Retail Goods"
        },
        {
            "category":"Wholesale",
            "subcategory":"Non-durable Goods",
            "type":"Manufacturing & Wholesale Goods"
        }
    ],
    "sg:phone":"+1 813 986 0997",
    "sg:postcode":"33592",
    "sg:province":"FL",
    "sg:tags":[
        "boat"
    ],
    "wof:name":"Nessmuk's Trading Post",
    "wof:placetype":"venue"
},
  "geometry": {"coordinates":[-82.342286,28.054158],"type":"Point"}
}