{
  "type": "Feature",
  "properties": {
    "addr:full":"3050 Horseshoe Dr N Naples FL 34104",
    "addr:housenumber":"3050",
    "addr:postcode":"34104",
    "addr:street":"Horseshoe Dr N",
    "iso:country":"US",
    "sg:address":"3050 Horseshoe Dr N",
    "sg:city":"Naples",
    "sg:classifiers":[
        {
            "category":"Communications",
            "subcategory":"Television Station",
            "type":"Services"
        }
    ],
    "sg:phone":"+1 239 403 9130",
    "sg:postcode":"34104",
    "sg:province":"FL",
    "sg:tags":[
        "tv",
        "satellite",
        "broadcasting",
        "radio",
        "via"
    ],
    "wof:name":"Dominion Dbs Network",
    "wof:placetype":"venue"
},
  "geometry": {"coordinates":[-81.768156,26.164096],"type":"Point"}
}