{
  "type": "Feature",
  "properties": {
    "iso:country":"US",
    "sg:address":"736 6th St",
    "sg:city":"Miami Beach",
    "sg:classifiers":[
        {
            "category":"Sports & Exercise",
            "subcategory":"Gym",
            "type":"Entertainment"
        }
    ],
    "sg:phone":"+1 305 534 8988",
    "sg:postcode":"33139",
    "sg:province":"FL",
    "sg:tags":[
        "yoga"
    ],
    "sg:website":"www.miamilifecenter.com",
    "wof:name":"Miami Life Center",
    "wof:placetype":"venue"
},
  "geometry": {"coordinates":[-80.13564700000001,25.775831],"type":"Point"}
}