{
  "type": "Feature",
  "properties": {
    "iso:country":"US",
    "sg:address":"506 S Waukesha St",
    "sg:city":"Bonifay",
    "sg:classifiers":[
        {
            "category":"Real Estate",
            "subcategory":"Real Estate Agent",
            "type":"Services"
        }
    ],
    "sg:phone":"+1 850 547 4179",
    "sg:postcode":"32425",
    "sg:province":"FL",
    "wof:name":"Fish Realty Inc",
    "wof:placetype":"venue"
},
  "geometry": {"coordinates":[-85.67995999999999,30.785466],"type":"Point"}
}