{
  "type": "Feature",
  "properties": {
    "iso:country":"US",
    "sg:address":"321 S John Young Pkwy",
    "sg:city":"Kissimmee",
    "sg:classifiers":[
        {
            "category":"Restaurant",
            "type":"Food & Drink"
        }
    ],
    "sg:phone":"+1 407 933 4215",
    "sg:postcode":"34741",
    "sg:province":"FL",
    "wof:name":"La-Forchetta Inc",
    "wof:placetype":"venue"
},
  "geometry": {"coordinates":[-81.41597,28.288726],"type":"Point"}
}