{
  "type": "Feature",
  "properties": {
    "addr:full":"2460 Gulf To Bay Blvd Clearwater FL 33765",
    "addr:housenumber":"2460",
    "addr:postcode":"33765",
    "addr:street":"Gulf To Bay Blvd",
    "iso:country":"US",
    "sg:address":"2460 Gulf To Bay Blvd",
    "sg:city":"Clearwater",
    "sg:classifiers":[
        {
            "category":"Insurance",
            "subcategory":"Hazard Insurance",
            "type":"Services"
        },
        {
            "category":"Insurance",
            "subcategory":"Life Insurance",
            "type":"Services"
        },
        {
            "category":"Insurance",
            "subcategory":"Health Insurance",
            "type":"Services"
        }
    ],
    "sg:phone":"+1 727 797 0441",
    "sg:postcode":"33765",
    "sg:province":"FL",
    "sg:tags":[
        "employee",
        "benefit",
        "commercial",
        "business"
    ],
    "wof:name":"Carlisle Fields & Company Inc Insurance",
    "wof:placetype":"venue"
},
  "geometry": {"coordinates":[-82.735333,27.96059],"type":"Point"}
}