{
  "type": "Feature",
  "properties": {
    "iso:country":"US",
    "sg:address":"8032 Sycamore Dr",
    "sg:city":"New Port Richey",
    "sg:classifiers":[
        {
            "category":"Retail",
            "subcategory":"Auto Repair",
            "type":"Services"
        }
    ],
    "sg:phone":"+1 727 847 1936",
    "sg:postcode":"34654",
    "sg:province":"FL",
    "sg:tags":[
        "body"
    ],
    "wof:name":"Colors On Parade",
    "wof:placetype":"venue"
},
  "geometry": {"coordinates":[-82.66193199999999,28.27422],"type":"Point"}
}