{
  "type": "Feature",
  "properties": {
    "iso:country":"US",
    "sg:address":"1432 W Flagler St",
    "sg:city":"Miami",
    "sg:classifiers":[
        {
            "category":"Retail",
            "subcategory":"Laundry & Dry Cleaning",
            "type":"Services"
        }
    ],
    "sg:phone":"+1 305 643 3144",
    "sg:postcode":"33135",
    "sg:province":"FL",
    "sg:tags":[
        "drycleaning",
        "plant"
    ],
    "wof:name":"Andres Dry Cleaners Inc",
    "wof:placetype":"venue"
},
  "geometry": {"coordinates":[-80.216611,25.773375],"type":"Point"}
}