{
  "type": "Feature",
  "properties": {
    "iso:country":"US",
    "sg:address":"351 Hollywood Blvd",
    "sg:city":"Fort Walton Bch",
    "sg:classifiers":[
        {
            "category":"Personal",
            "subcategory":"Adult",
            "type":"Services"
        }
    ],
    "sg:phone":"+1 850 582 2750",
    "sg:postcode":"32548",
    "sg:province":"FL",
    "sg:tags":[
        "escort"
    ],
    "wof:name":"Emerald Escort Svc",
    "wof:placetype":"venue"
},
  "geometry": {"coordinates":[-86.639146,30.413137],"type":"Point"}
}