{
  "type": "Feature",
  "properties": {
    "addr:full":"15610 SW 117th Ave Miami FL 33177",
    "addr:housenumber":"15610",
    "addr:postcode":"33177",
    "addr:street":"Sw 117Th Ave",
    "iso:country":"US",
    "sg:address":"15610 SW 117th Ave",
    "sg:city":"Miami",
    "sg:classifiers":[
        {
            "category":"Government",
            "subcategory":"Office",
            "type":"Public Place"
        }
    ],
    "sg:phone":"+1 305 278 6802",
    "sg:postcode":"33177",
    "sg:province":"FL",
    "wof:name":"United States Coast Guard",
    "wof:placetype":"venue"
},
  "geometry": {"coordinates":[-80.382199,25.623886],"type":"Point"}
}