{
  "type": "Feature",
  "properties": {
    "iso:country":"US",
    "sg:address":"1083 San Remo Ave",
    "sg:city":"Naples",
    "sg:classifiers":[
        {
            "category":"Retail",
            "subcategory":"Laundry & Dry Cleaning",
            "type":"Services"
        }
    ],
    "sg:phone":"+1 239 537 0799",
    "sg:postcode":"34104",
    "sg:province":"FL",
    "sg:tags":[
        "drycleaning",
        "plant"
    ],
    "wof:name":"Matilde Vazquez Cleaners Shutt",
    "wof:placetype":"venue"
},
  "geometry": {"coordinates":[-81.76222799999999,26.142452],"type":"Point"}
}