{
  "type": "Feature",
  "properties": {
    "iso:country":"US",
    "sg:address":"18739 W Dixie Hwy",
    "sg:city":"Miami",
    "sg:classifiers":[
        {
            "category":"Shopping",
            "subcategory":"Clothing, Apparel, & Fashions",
            "type":"Retail Goods"
        },
        {
            "category":"Shopping",
            "subcategory":"Used Merchandise",
            "type":"Retail Goods"
        }
    ],
    "sg:phone":"+1 305 932 6186",
    "sg:postcode":"33180",
    "sg:province":"FL",
    "sg:tags":[
        "vintage",
        "consignment",
        "period",
        "clothing-collectible"
    ],
    "wof:name":"Luchi Clothing Store",
    "wof:placetype":"venue"
},
  "geometry": {"coordinates":[-80.14863200000001,25.948912],"type":"Point"}
}