{
  "type": "Feature",
  "properties": {
    "addr:full":"5407 Baylea Ave Port Richey FL 34668",
    "addr:housenumber":"5407",
    "addr:postcode":"34668",
    "addr:street":"Baylea Ave",
    "iso:country":"US",
    "sg:address":"5407 Baylea Ave",
    "sg:city":"Port Richey",
    "sg:classifiers":[
        {
            "category":"Autos & Motor Vehicles",
            "subcategory":"Auto Supplies",
            "type":"Retail Goods"
        }
    ],
    "sg:phone":"+1 727 847 1125",
    "sg:postcode":"34668",
    "sg:province":"FL",
    "sg:tags":[
        "repair",
        "welding"
    ],
    "wof:name":"Gulf View Enterprises Inc",
    "wof:placetype":"venue"
},
  "geometry": {"coordinates":[-82.72382500000001,28.269679],"type":"Point"}
}