{
  "type": "Feature",
  "properties": {
    "addr:full":"7500 NW 57th St Lauderhill FL 33319",
    "addr:housenumber":"7500",
    "addr:postcode":"33319",
    "addr:street":"Nw 57Th St",
    "iso:country":"US",
    "sg:address":"7500 NW 57th St",
    "sg:city":"Lauderhill",
    "sg:classifiers":[
        {
            "category":"Autos & Motor Vehicles",
            "subcategory":"Auto Supplies",
            "type":"Retail Goods"
        },
        {
            "category":"Wholesale",
            "subcategory":"Electrical",
            "type":"Manufacturing & Wholesale Goods"
        },
        {
            "category":"Wholesale",
            "subcategory":"Auto Parts",
            "type":"Manufacturing & Wholesale Goods"
        },
        {
            "category":"Retail",
            "subcategory":"Auto Repair",
            "type":"Services"
        }
    ],
    "sg:phone":"+1 954 722 0606",
    "sg:postcode":"33319",
    "sg:province":"FL",
    "sg:tags":[
        "engines-rebuild",
        "exchange",
        "battery",
        "automobile",
        "accessory",
        "equipment",
        "supplies-used",
        "truck",
        "rebuilt",
        "batteries-storage"
    ],
    "sg:website":"http://www.advanceautoparts.com",
    "wof:name":"Advance Auto Parts",
    "wof:placetype":"venue"
},
  "geometry": {"coordinates":[-80.251964,26.19476],"type":"Point"}
}