{
  "type": "Feature",
  "properties": {
    "iso:country":"US",
    "sg:address":"333 N Byron Butler Pkwy",
    "sg:city":"Perry",
    "sg:classifiers":[
        {
            "category":"Autos & Motor Vehicles",
            "subcategory":"Automobile Sales",
            "type":"Retail Goods"
        }
    ],
    "sg:phone":"+1 850 223 3763",
    "sg:postcode":"32347",
    "sg:province":"FL",
    "sg:tags":[
        "aircraft"
    ],
    "wof:name":"Cj Systems Aviation Group",
    "wof:placetype":"venue"
},
  "geometry": {"coordinates":[-83.590547,30.119116],"type":"Point"}
}