{
  "type": "Feature",
  "properties": {
    "addr:full":"2802 Terra Ceia Bay Blvd Palmetto FL 34221",
    "addr:housenumber":"2802",
    "addr:postcode":"34221",
    "addr:street":"Terra Ceia Bay Blvd",
    "iso:country":"US",
    "sg:address":"2802 Terra Ceia Bay Blvd",
    "sg:city":"Palmetto",
    "sg:classifiers":[
        {
            "category":"Sports & Exercise",
            "subcategory":"Golf",
            "type":"Entertainment"
        }
    ],
    "sg:phone":"+1 941 729 7663",
    "sg:postcode":"34221",
    "sg:province":"FL",
    "sg:tags":[
        "course"
    ],
    "wof:name":"Terra Ceia Bay Golf & Country",
    "wof:placetype":"venue"
},
  "geometry": {"coordinates":[-82.583461,27.53866],"type":"Point"}
}