{
  "type": "Feature",
  "properties": {
    "iso:country":"US",
    "sg:address":"107 Abbott Cir",
    "sg:city":"Niceville",
    "sg:classifiers":[
        {
            "category":"Building & Trades",
            "subcategory":"Construction",
            "type":"Services"
        }
    ],
    "sg:phone":"+1 850 678 6305",
    "sg:postcode":"32578",
    "sg:province":"FL",
    "sg:tags":[
        "house"
    ],
    "wof:name":"Wayne Burr Handyman",
    "wof:placetype":"venue"
},
  "geometry": {"coordinates":[-86.47586800000001,30.513881],"type":"Point"}
}