{
  "type": "Feature",
  "properties": {
    "iso:country":"US",
    "sg:address":"5805 SW 21st St",
    "sg:city":"Hollywood",
    "sg:classifiers":[
        {
            "category":"Wholesale",
            "subcategory":"Medical Equipment & Supplies",
            "type":"Manufacturing & Wholesale Goods"
        }
    ],
    "sg:phone":"+1 954 964 0017",
    "sg:postcode":"33023",
    "sg:province":"FL",
    "wof:name":"Luzon Medical Inc",
    "wof:placetype":"venue"
},
  "geometry": {"coordinates":[-80.20329700000001,25.991677],"type":"Point"}
}