{
  "type": "Feature",
  "properties": {
    "iso:country":"US",
    "sg:address":"5500 W 21st Ct",
    "sg:city":"Hialeah",
    "sg:classifiers":[
        {
            "category":"Professional",
            "type":"Services"
        }
    ],
    "sg:phone":"+1 305 828 1759",
    "sg:postcode":"33016",
    "sg:province":"FL",
    "sg:tags":[
        "establishment"
    ],
    "wof:name":"Alameda Tower",
    "wof:placetype":"venue"
},
  "geometry": {"coordinates":[-80.32581999999999,25.875593],"type":"Point"}
}