{
  "type": "Feature",
  "properties": {
    "iso:country":"US",
    "sg:address":"3876 Woodmere Park Blvd",
    "sg:city":"Venice",
    "sg:classifiers":[
        {
            "category":"Shopping",
            "subcategory":"Clothing, Apparel, & Fashions",
            "type":"Retail Goods"
        }
    ],
    "sg:phone":"+1 941 480 9296",
    "sg:postcode":"34293",
    "sg:province":"FL",
    "wof:name":"Cottonstuff",
    "wof:placetype":"venue"
},
  "geometry": {"coordinates":[-82.389718,27.053408],"type":"Point"}
}