{
  "type": "Feature",
  "properties": {
    "iso:country":"US",
    "sg:address":"1385 NW 15th St",
    "sg:city":"Miami",
    "sg:classifiers":[
        {
            "category":"Professional",
            "subcategory":"Lawyer & Legal Services",
            "type":"Services"
        }
    ],
    "sg:phone":"+1 305 358 9388",
    "sg:postcode":"33125",
    "sg:province":"FL",
    "wof:name":"Fishman Jacob",
    "wof:placetype":"venue"
},
  "geometry": {"coordinates":[-80.218829,25.789533],"type":"Point"}
}