{
  "type": "Feature",
  "properties": {
    "addr:full":"1 SE Fort King St Ocala FL 34471",
    "addr:housenumber":"1",
    "addr:postcode":"34471",
    "addr:street":"Se Fort King St",
    "iso:country":"US",
    "sg:address":"1 SE Fort King St",
    "sg:city":"Ocala",
    "sg:classifiers":[
        {
            "category":"Personal",
            "subcategory":"Beauty Salon",
            "type":"Services"
        }
    ],
    "sg:phone":"+1 352 620 8054",
    "sg:postcode":"34471",
    "sg:province":"FL",
    "wof:name":"Beauty Deli",
    "wof:placetype":"venue"
},
  "geometry": {"coordinates":[-82.136031,29.185487],"type":"Point"}
}