{
  "type": "Feature",
  "properties": {
    "iso:country":"US",
    "sg:address":"12773 Forest Hill Blvd",
    "sg:city":"Wellington",
    "sg:classifiers":[
        {
            "category":"Organizations",
            "subcategory":"Professional Association",
            "type":"Services"
        }
    ],
    "sg:phone":"+1 561 792 8799",
    "sg:postcode":"33414",
    "sg:province":"FL",
    "sg:website":"www.flara.net",
    "wof:name":"Florida Alliance For Rtrd Amer",
    "wof:placetype":"venue"
},
  "geometry": {"coordinates":[-80.247733,26.672733],"type":"Point"}
}