{
  "type": "Feature",
  "properties": {
    "addr:full":"1901 Sevilla Blvd W Atlantic Beach FL 32233",
    "addr:housenumber":"1901",
    "addr:postcode":"32233",
    "addr:street":"Sevilla Blvd W",
    "iso:country":"US",
    "sg:address":"1901 Sevilla Blvd W",
    "sg:city":"Atlantic Beach",
    "sg:classifiers":[
        {
            "category":"Real Estate",
            "subcategory":"Real Estate Agent",
            "type":"Services"
        }
    ],
    "sg:phone":"+1 904 246 6622",
    "sg:postcode":"32233",
    "sg:province":"FL",
    "wof:name":"Shoreline Property Management",
    "wof:placetype":"venue"
},
  "geometry": {"coordinates":[-81.40719,30.349196],"type":"Point"}
}