{
  "type": "Feature",
  "properties": {
    "addr:full":"1601 Laurel Leaf Ln Fort Pierce FL 34950",
    "addr:housenumber":"1601",
    "addr:postcode":"34950",
    "addr:street":"Laurel Leaf Ln",
    "iso:country":"US",
    "sg:address":"1601 Laurel Leaf Ln",
    "sg:city":"Fort Pierce",
    "sg:classifiers":[
        {
            "category":"Restaurant",
            "type":"Food & Drink"
        }
    ],
    "sg:phone":"+1 772 429 1047",
    "sg:postcode":"34950",
    "sg:province":"FL",
    "wof:name":"Buffalo Chinese Restaurant",
    "wof:placetype":"venue"
},
  "geometry": {"coordinates":[-80.34017,27.43087],"type":"Point"}
}