{
  "type": "Feature",
  "properties": {
    "addr:full":"1159 Mulberry Ave Panama City FL 32401",
    "addr:housenumber":"1159",
    "addr:postcode":"32401",
    "addr:street":"Mulberry Ave",
    "iso:country":"US",
    "sg:address":"1159 Mulberry Ave",
    "sg:city":"Panama City",
    "sg:classifiers":[
        {
            "category":"Insurance",
            "subcategory":"Title Insurance",
            "type":"Services"
        }
    ],
    "sg:phone":"+1 850 769 8272",
    "sg:postcode":"32401",
    "sg:province":"FL",
    "sg:tags":[
        "carrier"
    ],
    "wof:name":"First American Title Insur Co",
    "wof:placetype":"venue"
},
  "geometry": {"coordinates":[-85.664637,30.168638],"type":"Point"}
}