{
  "type": "Feature",
  "properties": {
    "iso:country":"US",
    "sg:address":"1125 Nestling Dr",
    "sg:city":"Gulf Breeze",
    "sg:classifiers":[
        {
            "category":"Wholesale",
            "subcategory":"Electrical",
            "type":"Manufacturing & Wholesale Goods"
        }
    ],
    "sg:phone":"+1 850 934 0938",
    "sg:postcode":"32563",
    "sg:province":"FL",
    "sg:tags":[
        "equipment"
    ],
    "wof:name":"Griffth-Hrron-Middlebrook-Ross",
    "wof:placetype":"venue"
},
  "geometry": {"coordinates":[-87.107795,30.383164],"type":"Point"}
}