{
  "type": "Feature",
  "properties": {
    "iso:country":"US",
    "sg:address":"13351 Overseas Hwy",
    "sg:city":"Marathon",
    "sg:classifiers":[
        {
            "category":"Travel",
            "subcategory":"Hotels & Motels",
            "type":"Entertainment"
        }
    ],
    "sg:phone":"+1 305 743 8550",
    "sg:postcode":"33050",
    "sg:province":"FL",
    "wof:name":"Wellesley Inn",
    "wof:placetype":"venue"
},
  "geometry": {"coordinates":[-81.017335,24.733289],"type":"Point"}
}