{
  "type": "Feature",
  "properties": {
    "iso:country":"US",
    "sg:address":"1987 Tindaro Dr",
    "sg:city":"Apopka",
    "sg:classifiers":[
        {
            "category":"Retail",
            "subcategory":"Funeral Services",
            "type":"Services"
        }
    ],
    "sg:phone":"+1 407 703 5851",
    "sg:postcode":"32703",
    "sg:province":"FL",
    "sg:tags":[
        "plans-pre-arranged"
    ],
    "wof:name":"Chatigny, Briana",
    "wof:placetype":"venue"
},
  "geometry": {"coordinates":[-81.484049,28.647842],"type":"Point"}
}