{
  "type": "Feature",
  "properties": {
    "addr:full":"8373 Mistwood Cir N Jacksonville FL 32244",
    "addr:postcode":"8373;32244",
    "addr:street":"Mistwood Cir N",
    "iso:country":"US",
    "sg:address":"8373 Mistwood Cir N",
    "sg:city":"Jacksonville",
    "sg:classifiers":[
        {
            "category":"Wholesale",
            "subcategory":"Vending Machines",
            "type":"Manufacturing & Wholesale Goods"
        }
    ],
    "sg:phone":"+1 904 772 9742",
    "sg:postcode":"32244",
    "sg:province":"FL",
    "sg:tags":[
        "operator"
    ],
    "wof:name":"Perry Vending Co",
    "wof:placetype":"venue"
},
  "geometry": {"coordinates":[-81.79217199999999,30.203201],"type":"Point"}
}