{
  "type": "Feature",
  "properties": {
    "iso:country":"US",
    "sg:address":"7022 S Mascotte St",
    "sg:city":"Tampa",
    "sg:classifiers":[
        {
            "category":"Building & Trades",
            "subcategory":"Construction",
            "type":"Services"
        }
    ],
    "sg:phone":"+1 813 831 3935",
    "sg:postcode":"33616",
    "sg:province":"FL",
    "sg:tags":[
        "system",
        "contractor",
        "air conditioning"
    ],
    "wof:name":"Hayashi Service Inc",
    "wof:placetype":"venue"
},
  "geometry": {"coordinates":[-82.52780199999999,27.864501],"type":"Point"}
}