{
  "type": "Feature",
  "properties": {
    "iso:country":"US",
    "sg:address":"310 E Government St",
    "sg:city":"Pensacola",
    "sg:classifiers":[
        {
            "category":"Building & Trades",
            "subcategory":"Construction",
            "type":"Services"
        }
    ],
    "sg:phone":"+1 850 432 5478",
    "sg:postcode":"32502",
    "sg:province":"FL",
    "sg:tags":[
        "contractor"
    ],
    "wof:name":"Lister Builders LLC",
    "wof:placetype":"venue"
},
  "geometry": {"coordinates":[-87.20950999999999,30.410206],"type":"Point"}
}