{
  "type": "Feature",
  "properties": {
    "addr:full":"6767 103rd St Jacksonville FL 32210",
    "addr:housenumber":"6767",
    "addr:postcode":"32210",
    "addr:street":"103Rd St",
    "iso:country":"US",
    "sg:address":"6767 103rd St",
    "sg:city":"Jacksonville",
    "sg:classifiers":[
        {
            "category":"Restaurant",
            "type":"Food & Drink"
        }
    ],
    "sg:menulink":"http://www.allmenus.com/fl/jacksonville/187263-mcdonalds/menu/",
    "sg:postcode":"32210",
    "sg:province":"FL",
    "sg:tags":[
        "burger",
        "american"
    ],
    "wof:name":"McDonald's",
    "wof:placetype":"venue"
},
  "geometry": {"coordinates":[-81.754426,30.250294],"type":"Point"}
}