{
  "type": "Feature",
  "properties": {
    "iso:country":"US",
    "sg:address":"10016 Kenlake Dr",
    "sg:city":"Riverview",
    "sg:classifiers":[
        {
            "category":"Communications",
            "type":"Services"
        }
    ],
    "sg:phone":"+1 813 677 4286",
    "sg:postcode":"33578",
    "sg:province":"FL",
    "sg:tags":[
        "communication"
    ],
    "wof:name":"Jerrys Communications Inc",
    "wof:placetype":"venue"
},
  "geometry": {"coordinates":[-82.340636,27.851913],"type":"Point"}
}