{
  "type": "Feature",
  "properties": {
    "iso:country":"US",
    "sg:address":"450 Seminola Blvd",
    "sg:city":"Casselberry",
    "sg:classifiers":[
        {
            "category":"Building & Trades",
            "subcategory":"Electrical",
            "type":"Services"
        }
    ],
    "sg:phone":"+1 407 331 3577",
    "sg:postcode":"32707",
    "sg:province":"FL",
    "sg:tags":[
        "electrical",
        "contractor"
    ],
    "wof:name":"Contemporary Electric",
    "wof:placetype":"venue"
},
  "geometry": {"coordinates":[-81.328757,28.677815],"type":"Point"}
}