{
  "type": "Feature",
  "properties": {
    "addr:full":"203 Truman St Fort Walton Bch FL 32547",
    "addr:housenumber":"203",
    "addr:postcode":"32547",
    "addr:street":"Truman St",
    "iso:country":"US",
    "sg:address":"203 Truman St",
    "sg:city":"Fort Walton Bch",
    "sg:classifiers":[
        {
            "category":"Retail",
            "subcategory":"Auto Repair",
            "type":"Services"
        }
    ],
    "sg:phone":"+1 850 863 5947",
    "sg:postcode":"32547",
    "sg:province":"FL",
    "sg:tags":[
        "repairing",
        "automobile",
        "general"
    ],
    "wof:name":"Automotive Excellence",
    "wof:placetype":"venue"
},
  "geometry": {"coordinates":[-86.605048,30.446114],"type":"Point"}
}