{
  "type": "Feature",
  "properties": {
    "iso:country":"US",
    "sg:address":"155 E Lake Brantley Dr",
    "sg:city":"Longwood",
    "sg:classifiers":[
        {
            "category":"Banks & Credit Unions",
            "subcategory":"Bank",
            "type":"Services"
        }
    ],
    "sg:phone":"+1 407 774 2274",
    "sg:postcode":"32779",
    "sg:province":"FL",
    "sg:tags":[
        "lender",
        "broker",
        "mortgage"
    ],
    "wof:name":"Approved Mortgage Funding Inc",
    "wof:placetype":"venue"
},
  "geometry": {"coordinates":[-81.413696,28.6877],"type":"Point"}
}