{
  "type": "Feature",
  "properties": {
    "addr:full":"151 SE 5th St Cape Coral FL 33990",
    "addr:housenumber":"151",
    "addr:postcode":"33990",
    "addr:street":"Se 5Th St",
    "iso:country":"US",
    "sg:address":"151 SE 5th St",
    "sg:city":"Cape Coral",
    "sg:classifiers":[
        {
            "category":"Personal",
            "type":"Services"
        }
    ],
    "sg:phone":"+1 239 298 0561",
    "sg:postcode":"33990",
    "sg:province":"FL",
    "sg:tags":[
        "home"
    ],
    "wof:name":"Metropolis Iron, Inc.",
    "wof:placetype":"venue"
},
  "geometry": {"coordinates":[-81.971326,26.642063],"type":"Point"}
}