{
  "type": "Feature",
  "properties": {
    "iso:country":"US",
    "sg:address":"10500 NW 7th Ave",
    "sg:city":"Miami",
    "sg:classifiers":[
        {
            "category":"Professional",
            "subcategory":"Detective & Security Services",
            "type":"Services"
        },
        {
            "category":"Manufacturing",
            "subcategory":"Electronics",
            "type":"Manufacturing & Wholesale Goods"
        }
    ],
    "sg:phone":"+1 954 785 0448",
    "sg:postcode":"33150",
    "sg:province":"FL",
    "sg:tags":[
        "control",
        "monitoring",
        "equipment-wholesale",
        "system",
        "manufacturer"
    ],
    "wof:name":"Consolidated Southern Security",
    "wof:placetype":"venue"
},
  "geometry": {"coordinates":[-80.209991,25.871031],"type":"Point"}
}