{
  "type": "Feature",
  "properties": {
    "iso:country":"US",
    "sg:address":"962 Cypress Creek Rd",
    "sg:city":"Fort Lauderdale",
    "sg:classifiers":[
        {
            "category":"Health Services",
            "subcategory":"Clinic",
            "type":"Services"
        }
    ],
    "sg:phone":"+1 954 772 6205",
    "sg:postcode":"33334",
    "sg:province":"FL",
    "sg:tags":[
        "medical",
        "specialty",
        "outpatient"
    ],
    "wof:name":"Abortion Information",
    "wof:placetype":"venue"
},
  "geometry": {"coordinates":[-80.133213,26.203596],"type":"Point"}
}