{
  "type": "Feature",
  "properties": {
    "iso:country":"US",
    "sg:address":"9032 Mockingbird Dr",
    "sg:city":"Sanibel",
    "sg:classifiers":[
        {
            "category":"Wholesale",
            "subcategory":"Medical Equipment & Supplies",
            "type":"Manufacturing & Wholesale Goods"
        }
    ],
    "sg:phone":"+1 239 472 9570",
    "sg:postcode":"33957",
    "sg:province":"FL",
    "wof:name":"All American Medical Sales",
    "wof:placetype":"venue"
},
  "geometry": {"coordinates":[-82.04984,26.454011],"type":"Point"}
}