{
  "type": "Feature",
  "properties": {
    "iso:country":"US",
    "sg:address":"423 Lakeview St",
    "sg:city":"Mary Esther",
    "sg:classifiers":[
        {
            "category":"Building & Trades",
            "subcategory":"Construction",
            "type":"Services"
        }
    ],
    "sg:phone":"+1 850 581 4207",
    "sg:postcode":"32569",
    "sg:province":"FL",
    "sg:tags":[
        "general",
        "contractor"
    ],
    "wof:name":"Holley Earthwork Inc",
    "wof:placetype":"venue"
},
  "geometry": {"coordinates":[-86.7932,30.415705],"type":"Point"}
}