{
  "type": "Feature",
  "properties": {
    "addr:full":"6897 Silver Star Rd Orlando FL 32818",
    "addr:housenumber":"6897",
    "addr:postcode":"32818",
    "addr:street":"Silver Star Rd",
    "iso:country":"US",
    "sg:address":"6897 Silver Star Rd",
    "sg:city":"Orlando",
    "sg:classifiers":[
        {
            "category":"Wholesale",
            "subcategory":"Auto Parts",
            "type":"Manufacturing & Wholesale Goods"
        }
    ],
    "sg:phone":"+1 407 298 4188",
    "sg:postcode":"32818",
    "sg:province":"FL",
    "sg:tags":[
        "joint",
        "universal"
    ],
    "wof:name":"Advanced Car Care",
    "wof:placetype":"venue"
},
  "geometry": {"coordinates":[-81.47449,28.577685],"type":"Point"}
}