{
  "type": "Feature",
  "properties": {
    "iso:country":"US",
    "sg:address":"605 Anhinga Rd",
    "sg:city":"Winter Springs",
    "sg:classifiers":[
        {
            "category":"Real Estate",
            "subcategory":"Real Estate Agent",
            "type":"Services"
        }
    ],
    "sg:phone":"+1 407 699 4058",
    "sg:postcode":"32708",
    "sg:province":"FL",
    "sg:website":"www.jamesolsonrealty.com",
    "wof:name":"James Olson Realty",
    "wof:placetype":"venue"
},
  "geometry": {"coordinates":[-81.318731,28.70962],"type":"Point"}
}