{
  "type": "Feature",
  "properties": {
    "iso:country":"US",
    "sg:address":"4575 Conroy Club Dr",
    "sg:city":"Orlando",
    "sg:classifiers":[
        {
            "category":"Building & Trades",
            "subcategory":"Cleaning & Sanitation",
            "type":"Services"
        }
    ],
    "sg:phone":"+1 407 298 7611",
    "sg:postcode":"32835",
    "sg:province":"FL",
    "sg:tags":[
        "janitor"
    ],
    "wof:name":"Eagle Cleaning Co",
    "wof:placetype":"venue"
},
  "geometry": {"coordinates":[-81.47477600000001,28.496545],"type":"Point"}
}