{
  "type": "Feature",
  "properties": {
    "addr:full":"3841 SW Archer Rd Gainesville FL 32608",
    "addr:housenumber":"3841",
    "addr:postcode":"32608",
    "addr:street":"Sw Archer Rd",
    "iso:country":"US",
    "sg:address":"3841 SW Archer Rd",
    "sg:city":"Gainesville",
    "sg:classifiers":[
        {
            "category":"Restaurant",
            "type":"Food & Drink"
        }
    ],
    "sg:menulink":"http://www.allmenus.com/fl/gainesville/63003-chipotle/menu/",
    "sg:phone":"+1 352 371 9396",
    "sg:postcode":"32608",
    "sg:province":"FL",
    "sg:tags":[
        "mexican"
    ],
    "wof:name":"Chipotle",
    "wof:placetype":"venue"
},
  "geometry": {"coordinates":[-82.380894,29.619793],"type":"Point"}
}