{
  "type": "Feature",
  "properties": {
    "iso:country":"US",
    "sg:address":"2000 Thesy Dr",
    "sg:city":"Melbourne",
    "sg:classifiers":[
        {
            "category":"Health Services",
            "subcategory":"Doctor",
            "type":"Services"
        }
    ],
    "sg:phone":"+1 321 757 9074",
    "sg:postcode":"32940",
    "sg:province":"FL",
    "sg:tags":[
        "physician",
        "surgeon"
    ],
    "wof:name":"Shantilal M Patel",
    "wof:placetype":"venue"
},
  "geometry": {"coordinates":[-80.71840899999999,28.253831],"type":"Point"}
}