{
  "type": "Feature",
  "properties": {
    "iso:country":"US",
    "sg:address":"5406 Sycamore Dr",
    "sg:city":"Pensacola",
    "sg:classifiers":[
        {
            "category":"Shopping",
            "subcategory":"Bicycles & Sporting Goods",
            "type":"Retail Goods"
        }
    ],
    "sg:phone":"+1 850 477 2223",
    "sg:postcode":"32503",
    "sg:province":"FL",
    "sg:tags":[
        "ammunition"
    ],
    "wof:name":"Ammunition Sales Co",
    "wof:placetype":"venue"
},
  "geometry": {"coordinates":[-87.23644899999999,30.46932],"type":"Point"}
}