{
  "type": "Feature",
  "properties": {
    "iso:country":"US",
    "sg:address":"4154 Herschel St",
    "sg:city":"Jacksonville",
    "sg:classifiers":[
        {
            "category":"Professional",
            "subcategory":"Engineering",
            "type":"Services"
        }
    ],
    "sg:phone":"+1 904 381 8946",
    "sg:postcode":"32210",
    "sg:province":"FL",
    "sg:tags":[
        "engineer"
    ],
    "wof:name":"Myler Engineering",
    "wof:placetype":"venue"
},
  "geometry": {"coordinates":[-81.71350700000001,30.287116],"type":"Point"}
}