{
  "type": "Feature",
  "properties": {
    "iso:country":"US",
    "sg:address":"22701 SW 65th Cir",
    "sg:city":"Boca Raton",
    "sg:classifiers":[
        {
            "category":"Building & Trades",
            "subcategory":"Construction",
            "type":"Services"
        }
    ],
    "sg:phone":"+1 561 488 7099",
    "sg:postcode":"33428",
    "sg:province":"FL",
    "sg:tags":[
        "contractor"
    ],
    "wof:name":"Dan The Shingle Man Roofing",
    "wof:placetype":"venue"
},
  "geometry": {"coordinates":[-80.1991,26.338424],"type":"Point"}
}