{
  "type": "Feature",
  "properties": {
    "iso:country":"US",
    "sg:address":"11751 SE Head Ave",
    "sg:city":"Arcadia",
    "sg:classifiers":[
        {
            "category":"Farming",
            "subcategory":"Aquatic Farm",
            "type":"Manufacturing & Wholesale Goods"
        }
    ],
    "sg:phone":"+1 863 993 2123",
    "sg:postcode":"34266",
    "sg:province":"FL",
    "sg:tags":[
        "drink",
        "soft",
        "mfg"
    ],
    "wof:name":"Ekk-Will Tropical Fish Farm",
    "wof:placetype":"venue"
},
  "geometry": {"coordinates":[-81.85255600000001,27.06229],"type":"Point"}
}