{
  "type": "Feature",
  "properties": {
    "addr:full":"12633 Shadow Ridge Blvd Hudson FL 34669",
    "addr:housenumber":"12633",
    "addr:postcode":"34669",
    "addr:street":"Shadow Ridge Blvd",
    "iso:country":"US",
    "sg:address":"12633 Shadow Ridge Blvd",
    "sg:city":"Hudson",
    "sg:classifiers":[
        {
            "category":"Building & Trades",
            "subcategory":"Cleaning & Sanitation",
            "type":"Services"
        }
    ],
    "sg:phone":"+1 727 857 9347",
    "sg:postcode":"34669",
    "sg:province":"FL",
    "sg:tags":[
        "house"
    ],
    "wof:name":"Marion Berdon Maids",
    "wof:placetype":"venue"
},
  "geometry": {"coordinates":[-82.606324,28.34365],"type":"Point"}
}