{
  "type": "Feature",
  "properties": {
    "addr:full":"240 NW 65th Ave Miami FL 33126",
    "addr:housenumber":"240",
    "addr:postcode":"33126",
    "addr:street":"Nw 65Th Ave",
    "iso:country":"US",
    "sg:address":"240 NW 65th Ave",
    "sg:city":"Miami",
    "sg:classifiers":[
        {
            "category":"Wholesale",
            "subcategory":"Vending Machines",
            "type":"Manufacturing & Wholesale Goods"
        }
    ],
    "sg:phone":"+1 305 261 5423",
    "sg:postcode":"33126",
    "sg:province":"FL",
    "wof:name":"Ignas Vending",
    "wof:placetype":"venue"
},
  "geometry": {"coordinates":[-80.30237099999999,25.773296],"type":"Point"}
}