{
  "type": "Feature",
  "properties": {
    "addr:full":"5430 Carter Rd Fort Myers FL 33905",
    "addr:housenumber":"5430",
    "addr:postcode":"33905",
    "addr:street":"Carter Rd",
    "iso:country":"US",
    "sg:address":"5430 Carter Rd",
    "sg:city":"Fort Myers",
    "sg:classifiers":[
        {
            "category":"Home & Garden",
            "subcategory":"Garden Supply",
            "type":"Retail Goods"
        }
    ],
    "sg:phone":"+1 239 463 2673",
    "sg:postcode":"33905",
    "sg:province":"FL",
    "wof:name":"Mary E Blair",
    "wof:placetype":"venue"
},
  "geometry": {"coordinates":[-81.779048,26.66487],"type":"Point"}
}