{
  "type": "Feature",
  "properties": {
    "addr:full":"14703 SW 169th Ave Indiantown FL 34956",
    "addr:housenumber":"14703",
    "addr:postcode":"34956",
    "addr:street":"Sw 169Th Ave",
    "iso:country":"US",
    "sg:address":"14703 SW 169th Ave",
    "sg:city":"Indiantown",
    "sg:classifiers":[
        {
            "category":"Organizations",
            "subcategory":"Religious Organization",
            "type":"Services"
        }
    ],
    "sg:phone":"+1 772 597 4260",
    "sg:postcode":"34956",
    "sg:province":"FL",
    "wof:name":"Evergreen First Baptist Church",
    "wof:placetype":"venue"
},
  "geometry": {"coordinates":[-80.483441,27.027339],"type":"Point"}
}