{
  "type": "Feature",
  "properties": {
    "iso:country":"US",
    "sg:address":"1702 E 8th Ave",
    "sg:city":"Tampa",
    "sg:classifiers":[
        {
            "category":"Professional",
            "type":"Services"
        }
    ],
    "sg:phone":"+1 813 248 1116",
    "sg:postcode":"33605",
    "sg:province":"FL",
    "wof:name":"Service Experts",
    "wof:placetype":"venue"
},
  "geometry": {"coordinates":[-82.439251,27.961056],"type":"Point"}
}