{
  "type": "Feature",
  "properties": {
    "iso:country":"US",
    "sg:address":"10038 NW 59 Ter",
    "sg:city":"Gainesville",
    "sg:classifiers":[
        {
            "category":"Building & Trades",
            "subcategory":"Construction",
            "type":"Services"
        }
    ],
    "sg:phone":"+1 352 318 2099",
    "sg:postcode":"32653",
    "sg:province":"FL",
    "sg:tags":[
        "stucco",
        "contractor"
    ],
    "wof:name":"Professional Finishing Systems",
    "wof:placetype":"venue"
},
  "geometry": {"coordinates":[-82.40739000000001,29.750554],"type":"Point"}
}