{
  "type": "Feature",
  "properties": {
    "addr:full":"431 E Kaley St Orlando FL 32806",
    "addr:housenumber":"431",
    "addr:postcode":"32806",
    "addr:street":"E Kaley St",
    "iso:country":"US",
    "sg:address":"431 E Kaley St",
    "sg:city":"Orlando",
    "sg:classifiers":[
        {
            "category":"Health Services",
            "subcategory":"Health Practitioner",
            "type":"Services"
        }
    ],
    "sg:phone":"+1 407 843 3192",
    "sg:postcode":"32806",
    "sg:province":"FL",
    "wof:name":"Massage By Jerry",
    "wof:placetype":"venue"
},
  "geometry": {"coordinates":[-81.371004,28.52036],"type":"Point"}
}