{
  "type": "Feature",
  "properties": {
    "addr:full":"4419 Bee Ridge Rd Sarasota FL 34233",
    "addr:housenumber":"4419",
    "addr:postcode":"34233",
    "addr:street":"Bee Ridge Rd",
    "iso:country":"US",
    "sg:address":"4419 Bee Ridge Rd",
    "sg:city":"Sarasota",
    "sg:classifiers":[
        {
            "category":"Manufacturing",
            "subcategory":"Printing",
            "type":"Manufacturing & Wholesale Goods"
        }
    ],
    "sg:phone":"+1 941 371 1111",
    "sg:postcode":"34233",
    "sg:province":"FL",
    "sg:tags":[
        "lithographic",
        "commercial"
    ],
    "wof:name":"Classic Printing",
    "wof:placetype":"venue"
},
  "geometry": {"coordinates":[-82.476951,27.298825],"type":"Point"}
}