{
  "type": "Feature",
  "properties": {
    "addr:full":"731 Riverbend Blvd Longwood FL 32779",
    "addr:housenumber":"731",
    "addr:postcode":"32779",
    "addr:street":"Riverbend Blvd",
    "iso:country":"US",
    "sg:address":"731 Riverbend Blvd",
    "sg:city":"Longwood",
    "sg:classifiers":[
        {
            "category":"Building & Trades",
            "subcategory":"Construction",
            "type":"Services"
        }
    ],
    "sg:phone":"+1 407 786 4518",
    "sg:postcode":"32779",
    "sg:province":"FL",
    "sg:tags":[
        "house",
        "nonresidential"
    ],
    "wof:name":"Montana Development Inc",
    "wof:placetype":"venue"
},
  "geometry": {"coordinates":[-81.432529,28.714419],"type":"Point"}
}