{
  "type": "Feature",
  "properties": {
    "addr:full":"7016 Pine Forest Rd Pensacola FL 32526",
    "addr:housenumber":"7016",
    "addr:postcode":"32526",
    "addr:street":"Pine Forest Rd",
    "iso:country":"US",
    "sg:address":"7016 Pine Forest Rd",
    "sg:city":"Pensacola",
    "sg:classifiers":[
        {
            "category":"Home & Garden",
            "subcategory":"Furniture",
            "type":"Retail Goods"
        }
    ],
    "sg:phone":"+1 850 944 2167",
    "sg:postcode":"32526",
    "sg:province":"FL",
    "wof:name":"Craftsman Furniture",
    "wof:placetype":"venue"
},
  "geometry": {"coordinates":[-87.306026,30.491494],"type":"Point"}
}