{
  "type": "Feature",
  "properties": {
    "iso:country":"US",
    "sg:address":"14870 Crystal Cove Ct",
    "sg:city":"Fort Myers",
    "sg:classifiers":[
        {
            "category":"Home & Garden",
            "subcategory":"Building Materials",
            "type":"Retail Goods"
        }
    ],
    "sg:phone":"+1 239 437 4265",
    "sg:postcode":"33919",
    "sg:province":"FL",
    "sg:tags":[
        "glass",
        "leaded"
    ],
    "wof:name":"Roger A Wallace Stained Glass",
    "wof:placetype":"venue"
},
  "geometry": {"coordinates":[-81.908669,26.526531],"type":"Point"}
}