{
  "type": "Feature",
  "properties": {
    "iso:country":"US",
    "sg:address":"1637 Hamilton St",
    "sg:city":"Jacksonville",
    "sg:classifiers":[
        {
            "category":"Organizations",
            "subcategory":"Religious Organization",
            "type":"Services"
        }
    ],
    "sg:phone":"+1 904 384 7268",
    "sg:postcode":"32210",
    "sg:province":"FL",
    "sg:tags":[
        "church"
    ],
    "wof:name":"Cosmic Church Of Truth",
    "wof:placetype":"venue"
},
  "geometry": {"coordinates":[-81.72189899999999,30.288618],"type":"Point"}
}