{
  "type": "Feature",
  "properties": {
    "iso:country":"US",
    "sg:address":"1740 Calumet St",
    "sg:city":"Clearwater",
    "sg:classifiers":[
        {
            "category":"Home & Garden",
            "subcategory":"Garden Supply",
            "type":"Retail Goods"
        }
    ],
    "sg:phone":"+1 727 446 3534",
    "sg:postcode":"33765",
    "sg:province":"FL",
    "sg:tags":[
        "sprinkler"
    ],
    "sg:website":"www.floridairrigation.com",
    "wof:name":"Florida Irrigation Supply Inc",
    "wof:placetype":"venue"
},
  "geometry": {"coordinates":[-82.758202,27.983728],"type":"Point"}
}