{
  "type": "Feature",
  "properties": {
    "addr:full":"59 Northwest Blvd Miami FL 33126",
    "addr:housenumber":"59",
    "addr:postcode":"33126",
    "addr:street":"Northwest Blvd",
    "iso:country":"US",
    "sg:address":"59 Northwest Blvd",
    "sg:city":"Miami",
    "sg:classifiers":[
        {
            "category":"Building & Trades",
            "subcategory":"Locksmith",
            "type":"Services"
        }
    ],
    "sg:phone":"+1 786 718 1326",
    "sg:postcode":"33126",
    "sg:province":"FL",
    "sg:tags":[
        "key"
    ],
    "wof:name":"Locksmith 1 Always",
    "wof:placetype":"venue"
},
  "geometry": {"coordinates":[-80.314313,25.771278],"type":"Point"}
}