{
  "type": "Feature",
  "properties": {
    "iso:country":"US",
    "sg:address":"5735 NW 159th St",
    "sg:city":"Hialeah",
    "sg:classifiers":[
        {
            "category":"Building & Trades",
            "subcategory":"Plumbing",
            "type":"Services"
        }
    ],
    "sg:phone":"+1 305 688 7586",
    "sg:postcode":"33014",
    "sg:province":"FL",
    "wof:name":"Tasco Plumbing Corp",
    "wof:placetype":"venue"
},
  "geometry": {"coordinates":[-80.29450199999999,25.9177],"type":"Point"}
}