{
  "type": "Feature",
  "properties": {
    "iso:country":"US",
    "sg:address":"2301 N Federal Hwy",
    "sg:city":"Fort Lauderdale",
    "sg:classifiers":[
        {
            "category":"Restaurant",
            "type":"Food & Drink"
        }
    ],
    "sg:menulink":"http://www.allmenus.com/fl/fort-lauderdale/69141-california-pizza-kitchen/menu/",
    "sg:phone":"+1 954 565 1196",
    "sg:postcode":"33305",
    "sg:province":"FL",
    "sg:tags":[
        "sandwich",
        "salad",
        "soup",
        "american",
        "pasta",
        "californian",
        "pizza"
    ],
    "wof:name":"California Pizza Kitchen",
    "wof:placetype":"venue"
},
  "geometry": {"coordinates":[-80.117763,26.156576],"type":"Point"}
}