{
  "type": "Feature",
  "properties": {
    "iso:country":"US",
    "sg:address":"2104 W Oakland Park Blvd",
    "sg:city":"Fort Lauderdale",
    "sg:classifiers":[
        {
            "category":"Shopping",
            "subcategory":"Pharmacy",
            "type":"Retail Goods"
        }
    ],
    "sg:phone":"+1 954 486 7770",
    "sg:postcode":"33311",
    "sg:province":"FL",
    "wof:name":"Walgreens",
    "wof:placetype":"venue"
},
  "geometry": {"coordinates":[-80.17412299999999,26.1655],"type":"Point"}
}