{
  "type": "Feature",
  "properties": {
    "addr:full":"9280 College Pkwy Ste 6 Fort Myers FL 33919",
    "addr:housenumber":"9280",
    "addr:postcode":"myers fl 33919",
    "addr:street":"College Pkwy Ste 6",
    "iso:country":"US",
    "sg:address":"9280 College Pkwy Ste 6",
    "sg:city":"Fort Myers",
    "sg:classifiers":[
        {
            "category":"Communications",
            "subcategory":"Newspaper",
            "type":"Services"
        }
    ],
    "sg:phone":"+1 239 482 0909",
    "sg:postcode":"33919",
    "sg:province":"FL",
    "sg:tags":[
        "print",
        "medium"
    ],
    "wof:name":"Keels & Wheels Magazine",
    "wof:placetype":"venue"
},
  "geometry": {"coordinates":[-81.9011,26.5536],"type":"Point"}
}