{
  "type": "Feature",
  "properties": {
    "iso:country":"US",
    "sg:address":"654 Bryan Terrace Dr",
    "sg:city":"Brandon",
    "sg:classifiers":[
        {
            "category":"Insurance",
            "subcategory":"Hazard Insurance",
            "type":"Services"
        }
    ],
    "sg:phone":"+1 813 684 2137",
    "sg:postcode":"33511",
    "sg:province":"FL",
    "sg:tags":[
        "fund"
    ],
    "wof:name":"American Capital Funding",
    "wof:placetype":"venue"
},
  "geometry": {"coordinates":[-82.274129,27.90504],"type":"Point"}
}