{
  "type": "Feature",
  "properties": {
    "iso:country":"US",
    "sg:address":"8102 Banister Ln",
    "sg:city":"Port Richey",
    "sg:classifiers":[
        {
            "category":"Wholesale",
            "subcategory":"Home Furnishings",
            "type":"Manufacturing & Wholesale Goods"
        }
    ],
    "sg:phone":"+1 727 937 2434",
    "sg:postcode":"34668",
    "sg:province":"FL",
    "sg:tags":[
        "floor",
        "covering"
    ],
    "wof:name":"Carpets of Distinction",
    "wof:placetype":"venue"
},
  "geometry": {"coordinates":[-82.68834200000001,28.274684],"type":"Point"}
}