{
  "type": "Feature",
  "properties": {
    "iso:country":"US",
    "sg:address":"709 Jones Ave",
    "sg:city":"Haines City",
    "sg:classifiers":[
        {
            "category":"Health Services",
            "subcategory":"Doctor",
            "type":"Services"
        }
    ],
    "sg:phone":"+1 863 422 9448",
    "sg:postcode":"33844",
    "sg:province":"FL",
    "sg:tags":[
        "physician",
        "surgeon"
    ],
    "wof:name":"First Health Inc",
    "wof:placetype":"venue"
},
  "geometry": {"coordinates":[-81.62502600000001,28.108092],"type":"Point"}
}