{
  "type": "Feature",
  "properties": {
    "iso:country":"US",
    "sg:address":"1274 3rd St S",
    "sg:city":"Jacksonville Bch",
    "sg:classifiers":[
        {
            "category":"Personal",
            "subcategory":"Beauty Salon",
            "type":"Services"
        }
    ],
    "sg:phone":"+1 904 246 7373",
    "sg:postcode":"32250",
    "sg:province":"FL",
    "sg:tags":[
        "shop"
    ],
    "wof:name":"Susan Merrick's Hair Designs",
    "wof:placetype":"venue"
},
  "geometry": {"coordinates":[-81.389503,30.276768],"type":"Point"}
}