{
  "type": "Feature",
  "properties": {
    "addr:full":"2291 Britt Rd Cantonment FL 32533",
    "addr:housenumber":"2291",
    "addr:postcode":"32533",
    "addr:street":"Britt Rd",
    "iso:country":"US",
    "sg:address":"2291 Britt Rd",
    "sg:city":"Cantonment",
    "sg:classifiers":[
        {
            "category":"Insurance",
            "subcategory":"Hazard Insurance",
            "type":"Services"
        }
    ],
    "sg:phone":"+1 850 968 5778",
    "sg:postcode":"32533",
    "sg:province":"FL",
    "wof:name":"Gary C Jensen",
    "wof:placetype":"venue"
},
  "geometry": {"coordinates":[-87.360895,30.600503],"type":"Point"}
}