{
  "type": "Feature",
  "properties": {
    "iso:country":"US",
    "sg:address":"1031 W 15th St",
    "sg:city":"Panama City",
    "sg:classifiers":[
        {
            "category":"Professional",
            "subcategory":"Accounting & Tax Preparation",
            "type":"Services"
        }
    ],
    "sg:phone":"+1 850 914 2675",
    "sg:postcode":"32401",
    "sg:province":"FL",
    "sg:tags":[
        "return",
        "filing"
    ],
    "wof:name":"Jackson Hewitt Tax Svc",
    "wof:placetype":"venue"
},
  "geometry": {"coordinates":[-85.676967,30.17519],"type":"Point"}
}