{
  "type": "Feature",
  "properties": {
    "iso:country":"US",
    "sg:address":"5221 Palm Ave",
    "sg:city":"Cocoa",
    "sg:classifiers":[
        {
            "category":"Retail",
            "subcategory":"Animal Services",
            "type":"Services"
        }
    ],
    "sg:phone":"+1 321 632 3149",
    "sg:postcode":"32926",
    "sg:province":"FL",
    "sg:tags":[
        "pet",
        "grooming"
    ],
    "wof:name":"Wigleys Grooming and Boarding",
    "wof:placetype":"venue"
},
  "geometry": {"coordinates":[-80.83004699999999,28.41284],"type":"Point"}
}