{
  "type": "Feature",
  "properties": {
    "addr:full":"918 Veronica Cir Ocoee FL 34761",
    "addr:housenumber":"918",
    "addr:postcode":"34761",
    "addr:street":"Veronica Cir",
    "iso:country":"US",
    "sg:address":"918 Veronica Cir",
    "sg:city":"Ocoee",
    "sg:classifiers":[
        {
            "category":"Building & Trades",
            "subcategory":"Construction",
            "type":"Services"
        }
    ],
    "sg:phone":"+1 407 293 1764",
    "sg:postcode":"34761",
    "sg:province":"FL",
    "sg:tags":[
        "contractor"
    ],
    "wof:name":"Christopher Allen Beigel",
    "wof:placetype":"venue"
},
  "geometry": {"coordinates":[-81.528549,28.56574],"type":"Point"}
}