{
  "type": "Feature",
  "properties": {
    "iso:country":"US",
    "sg:address":"6675 49th St N",
    "sg:city":"Pinellas Park",
    "sg:classifiers":[
        {
            "category":"Health Services",
            "subcategory":"Doctor",
            "type":"Services"
        }
    ],
    "sg:phone":"+1 727 520 7000",
    "sg:postcode":"33781",
    "sg:province":"FL",
    "sg:tags":[
        "medical"
    ],
    "wof:name":"R K Doss M D",
    "wof:placetype":"venue"
},
  "geometry": {"coordinates":[-82.699831,27.833139],"type":"Point"}
}