{
  "type": "Feature",
  "properties": {
    "iso:country":"US",
    "sg:address":"1824 Fiske Blvd",
    "sg:city":"Rockledge",
    "sg:classifiers":[
        {
            "category":"Sports & Exercise",
            "subcategory":"Race Track",
            "type":"Entertainment"
        }
    ],
    "sg:phone":"+1 321 631 1779",
    "sg:postcode":"32955",
    "sg:province":"FL",
    "sg:tags":[
        "operation",
        "racing",
        "or"
    ],
    "wof:name":"National Rcetrack Clearing Hse",
    "wof:placetype":"venue"
},
  "geometry": {"coordinates":[-80.742554,28.329007],"type":"Point"}
}