{
  "type": "Feature",
  "properties": {
    "iso:country":"US",
    "sg:address":"4856 US Hwy 17",
    "sg:city":"De Leon Springs",
    "sg:classifiers":[
        {
            "category":"Retail",
            "subcategory":"Auto Repair",
            "type":"Services"
        }
    ],
    "sg:phone":"+1 386 985 2555",
    "sg:postcode":"32130",
    "sg:province":"FL",
    "sg:tags":[
        "repairing",
        "automobile"
    ],
    "wof:name":"Carlito's",
    "wof:placetype":"venue"
},
  "geometry": {"coordinates":[-81.35176199999999,29.114869],"type":"Point"}
}