{
  "type": "Feature",
  "properties": {
    "iso:country":"US",
    "sg:address":"210 2nd St",
    "sg:city":"Orlando",
    "sg:classifiers":[
        {
            "category":"Shopping",
            "subcategory":"Florist",
            "type":"Retail Goods"
        }
    ],
    "sg:phone":"+1 407 948 7964",
    "sg:postcode":"32824",
    "sg:province":"FL",
    "wof:name":"Fireflies Florist",
    "wof:placetype":"venue"
},
  "geometry": {"coordinates":[-81.37396200000001,28.430531],"type":"Point"}
}