{
  "type": "Feature",
  "properties": {
    "addr:full":"8596 Wendy Ln E West Palm Beach FL 33411",
    "addr:housenumber":"8596;e",
    "addr:postcode":"33411",
    "addr:street":"Wendy Ln",
    "iso:country":"US",
    "sg:address":"8596 Wendy Ln E",
    "sg:city":"West Palm Beach",
    "sg:classifiers":[
        {
            "category":"Professional",
            "type":"Services"
        }
    ],
    "sg:phone":"+1 561 432 9090",
    "sg:postcode":"33411",
    "sg:province":"FL",
    "wof:name":"Multimediahouse Inc",
    "wof:placetype":"venue"
},
  "geometry": {"coordinates":[-80.178708,26.660859],"type":"Point"}
}