{
  "type": "Feature",
  "properties": {
    "iso:country":"US",
    "sg:address":"829 Reflections Loop E",
    "sg:city":"Winter Haven",
    "sg:classifiers":[
        {
            "category":"Shopping",
            "type":"Retail Goods"
        }
    ],
    "sg:phone":"+1 863 875 1377",
    "sg:postcode":"33884",
    "sg:province":"FL",
    "sg:tags":[
        "merchandise"
    ],
    "wof:name":"Tropical Shades",
    "wof:placetype":"venue"
},
  "geometry": {"coordinates":[-81.666217,27.978294],"type":"Point"}
}