{
  "type": "Feature",
  "properties": {
    "addr:full":"207 N 18th St Palatka FL 32177",
    "addr:housenumber":"207",
    "addr:postcode":"32177",
    "addr:street":"N 18Th St",
    "iso:country":"US",
    "sg:address":"207 N 18th St",
    "sg:city":"Palatka",
    "sg:classifiers":[
        {
            "category":"Bars & Pubs",
            "type":"Food & Drink"
        },
        {
            "category":"Restaurant",
            "type":"Food & Drink"
        }
    ],
    "sg:phone":"+1 386 328 8691",
    "sg:postcode":"32177",
    "sg:province":"FL",
    "sg:tags":[
        "club",
        "eating",
        "night"
    ],
    "wof:name":"Vick's Supper Club",
    "wof:placetype":"venue"
},
  "geometry": {"coordinates":[-81.64766,29.650065],"type":"Point"}
}