{
  "type": "Feature",
  "properties": {
    "iso:country":"US",
    "sg:address":"8565 NW 29th St Mia",
    "sg:city":"Doral",
    "sg:classifiers":[
        {
            "category":"Manufacturing",
            "subcategory":"Tools & Machinery",
            "type":"Manufacturing & Wholesale Goods"
        },
        {
            "category":"Shopping",
            "subcategory":"Crafts & Fabrics",
            "type":"Retail Goods"
        }
    ],
    "sg:phone":"+1 305 463 8838",
    "sg:postcode":"33122",
    "sg:province":"FL",
    "sg:tags":[
        "sewing",
        "machines-household",
        "machines-industrial"
    ],
    "sg:website":"http://www.sun-sun.com",
    "wof:name":"Sun-Sun International Inc",
    "wof:placetype":"venue"
},
  "geometry": {"coordinates":[-80.33638000000001,25.800776],"type":"Point"}
}