{
  "type": "Feature",
  "properties": {
    "iso:country":"US",
    "sg:address":"4426 SW Oakhaven Ln",
    "sg:city":"Palm City",
    "sg:classifiers":[
        {
            "category":"Real Estate",
            "subcategory":"Real Estate Agent",
            "type":"Services"
        }
    ],
    "sg:phone":"+1 772 219 0246",
    "sg:postcode":"34990",
    "sg:province":"FL",
    "wof:name":"Renaissance Waterfront Propert",
    "wof:placetype":"venue"
},
  "geometry": {"coordinates":[-80.28227200000001,27.152321],"type":"Point"}
}