{
  "type": "Feature",
  "properties": {
    "addr:full":"21021 State Rd 54 Lutz FL 33558",
    "addr:housenumber":"21021;54",
    "addr:postcode":"33558",
    "addr:street":"State Rd",
    "iso:country":"US",
    "sg:address":"21021 State Rd 54",
    "sg:city":"Lutz",
    "sg:classifiers":[
        {
            "category":"Organizations",
            "subcategory":"Religious Organization",
            "type":"Services"
        }
    ],
    "sg:phone":"+1 813 949 9377",
    "sg:postcode":"33558",
    "sg:province":"FL",
    "sg:tags":[
        "church"
    ],
    "wof:name":"Heritage Bible Church",
    "wof:placetype":"venue"
},
  "geometry": {"coordinates":[-82.46862,28.19305],"type":"Point"}
}