{
  "type": "Feature",
  "properties": {
    "addr:full":"507 S Macdill Ave Tampa FL 33609",
    "addr:housenumber":"507",
    "addr:postcode":"33609",
    "addr:street":"S Macdill Ave",
    "iso:country":"US",
    "sg:address":"507 S Macdill Ave",
    "sg:city":"Tampa",
    "sg:classifiers":[
        {
            "category":"Health Services",
            "subcategory":"Doctor",
            "type":"Services"
        }
    ],
    "sg:phone":"+1 813 350 9398",
    "sg:postcode":"33609",
    "sg:province":"FL",
    "sg:tags":[
        "clinic"
    ],
    "wof:name":"Convenient Care Walk-In Clinic",
    "wof:placetype":"venue"
},
  "geometry": {"coordinates":[-82.493408,27.938753],"type":"Point"}
}