{
  "type": "Feature",
  "properties": {
    "iso:country":"US",
    "sg:address":"911 Granville Rd",
    "sg:city":"Jacksonville",
    "sg:classifiers":[
        {
            "category":"Building & Trades",
            "subcategory":"Construction",
            "type":"Services"
        }
    ],
    "sg:phone":"+1 904 786 3425",
    "sg:postcode":"32205",
    "sg:province":"FL",
    "sg:tags":[
        "contractor"
    ],
    "wof:name":"Parsons Cabinet Inc",
    "wof:placetype":"venue"
},
  "geometry": {"coordinates":[-81.75496,30.306629],"type":"Point"}
}