{
  "type": "Feature",
  "properties": {
    "addr:full":"1035 Arlington Ave N St Petersburg FL 33705",
    "addr:housenumber":"1035",
    "addr:postcode":"33705",
    "addr:street":"Arlington Ave N",
    "iso:country":"US",
    "sg:address":"1035 Arlington Ave N",
    "sg:city":"St Petersburg",
    "sg:classifiers":[
        {
            "category":"Health Services",
            "subcategory":"Nursing And Care Facility",
            "type":"Services"
        },
        {
            "category":"Real Estate",
            "subcategory":"Real Estate Operator",
            "type":"Services"
        }
    ],
    "sg:phone":"+1 727 896 5148",
    "sg:postcode":"33705",
    "sg:province":"FL",
    "sg:tags":[
        "retirement",
        "for",
        "housing",
        "community",
        "elderly",
        "home"
    ],
    "wof:name":"John Knox Apartments",
    "wof:placetype":"venue"
},
  "geometry": {"coordinates":[-82.65156899999999,27.772597],"type":"Point"}
}