{
  "type": "Feature",
  "properties": {
    "iso:country":"US",
    "sg:address":"3140 W Pembroke Rd",
    "sg:city":"Hallandale Beach",
    "sg:classifiers":[
        {
            "category":"Arts & Performance",
            "subcategory":"Theater",
            "type":"Entertainment"
        }
    ],
    "sg:phone":"+1 954 987 7700",
    "sg:postcode":"33009",
    "sg:province":"FL",
    "sg:tags":[
        "live",
        "music"
    ],
    "wof:name":"Arista Entertainment",
    "wof:placetype":"venue"
},
  "geometry": {"coordinates":[-80.170258,25.996109],"type":"Point"}
}