{
  "type": "Feature",
  "properties": {
    "addr:full":"809 6th St Cedar Key FL 32625",
    "addr:housenumber":"809",
    "addr:postcode":"32625",
    "addr:street":"6Th St",
    "iso:country":"US",
    "sg:address":"809 6th St",
    "sg:city":"Cedar Key",
    "sg:classifiers":[
        {
            "category":"Organizations",
            "subcategory":"Community Association",
            "type":"Services"
        }
    ],
    "sg:phone":"+1 352 543 9120",
    "sg:postcode":"32625",
    "sg:province":"FL",
    "sg:tags":[
        "club"
    ],
    "wof:name":"Lion's Club",
    "wof:placetype":"venue"
},
  "geometry": {"coordinates":[-83.036726,29.137905],"type":"Point"}
}