{
  "type": "Feature",
  "properties": {
    "addr:full":"550 E Walker Dr Keystone Heights FL 32656",
    "addr:housenumber":"550",
    "addr:postcode":"32656",
    "addr:street":"E Walker Dr",
    "iso:country":"US",
    "sg:address":"550 E Walker Dr",
    "sg:city":"Keystone Heights",
    "sg:classifiers":[
        {
            "category":"Social Services",
            "subcategory":"Child Care",
            "type":"Services"
        },
        {
            "category":"Organizations",
            "subcategory":"Religious Organization",
            "type":"Services"
        }
    ],
    "sg:phone":"+1 352 473 7201",
    "sg:postcode":"32656",
    "sg:province":"FL",
    "sg:tags":[
        "baptist",
        "church"
    ],
    "wof:name":"First Baptist Church Day Care",
    "wof:placetype":"venue"
},
  "geometry": {"coordinates":[-82.025104,29.781839],"type":"Point"}
}