{
  "type": "Feature",
  "properties": {
    "iso:country":"US",
    "sg:address":"1430 Dixon Blvd",
    "sg:city":"Cocoa",
    "sg:classifiers":[
        {
            "category":"Organizations",
            "subcategory":"Non-profit Organization",
            "type":"Services"
        },
        {
            "category":"Real Estate",
            "subcategory":"Real Estate Operator",
            "type":"Services"
        }
    ],
    "sg:phone":"+1 321 632 4943",
    "sg:postcode":"32922",
    "sg:province":"FL",
    "sg:tags":[
        "retirement",
        "apartment",
        "elderly",
        "for",
        "operates"
    ],
    "wof:name":"Asbury Arms Apartments",
    "wof:placetype":"venue"
},
  "geometry": {"coordinates":[-80.750401,28.373134],"type":"Point"}
}