{
  "type": "Feature",
  "properties": {
    "iso:country":"US",
    "sg:address":"3088 N Harbor City Blvd",
    "sg:city":"Melbourne",
    "sg:classifiers":[
        {
            "category":"Autos & Motor Vehicles",
            "subcategory":"Fuel & Gas Station",
            "type":"Retail Goods"
        }
    ],
    "sg:phone":"+1 321 253 0191",
    "sg:postcode":"32935",
    "sg:province":"FL",
    "sg:tags":[
        "grocery"
    ],
    "wof:name":"Pantry Inc",
    "wof:placetype":"venue"
},
  "geometry": {"coordinates":[-80.640624,28.153754],"type":"Point"}
}