{
  "type": "Feature",
  "properties": {
    "addr:full":"210 NE 174th St Sunny Isles Bch FL 33160",
    "addr:housenumber":"210",
    "addr:postcode":"33160",
    "addr:street":"Ne 174Th St",
    "iso:country":"US",
    "sg:address":"210 NE 174th St",
    "sg:city":"Sunny Isles Bch",
    "sg:classifiers":[
        {
            "category":"Wholesale",
            "subcategory":"Durable Goods & Equipment",
            "type":"Manufacturing & Wholesale Goods"
        }
    ],
    "sg:phone":"+1 305 682 1211",
    "sg:postcode":"33160",
    "sg:province":"FL",
    "sg:tags":[
        "exporter"
    ],
    "wof:name":"Stockton Chemicals Corp",
    "wof:placetype":"venue"
},
  "geometry": {"coordinates":[-80.126131,25.93704],"type":"Point"}
}