{
  "type": "Feature",
  "properties": {
    "iso:country":"US",
    "sg:address":"613 Camelia St",
    "sg:city":"Panama City Bch",
    "sg:classifiers":[
        {
            "category":"Banks & Credit Unions",
            "subcategory":"Bank",
            "type":"Services"
        }
    ],
    "sg:phone":"+1 850 249 3763",
    "sg:postcode":"32407",
    "sg:province":"FL",
    "sg:tags":[
        "loan",
        "real estate"
    ],
    "wof:name":"Reliable Mortgage LLC",
    "wof:placetype":"venue"
},
  "geometry": {"coordinates":[-85.842263,30.200044],"type":"Point"}
}