{
  "type": "Feature",
  "properties": {
    "iso:country":"US",
    "sg:address":"5355 Spring Hill Dr",
    "sg:city":"Weeki Wachee",
    "sg:classifiers":[
        {
            "category":"Health Services",
            "subcategory":"Doctor",
            "type":"Services"
        }
    ],
    "sg:phone":"+1 352 688 5586",
    "sg:postcode":"34606",
    "sg:province":"FL",
    "sg:tags":[
        "physician",
        "surgeon"
    ],
    "wof:name":"Bayside Family Medical Care",
    "wof:placetype":"venue"
},
  "geometry": {"coordinates":[-82.625224,28.458869],"type":"Point"}
}