{
  "type": "Feature",
  "properties": {
    "addr:full":"2588 Colorado St Sarasota FL 34237",
    "addr:housenumber":"2588",
    "addr:postcode":"34237",
    "addr:street":"Colorado St",
    "iso:country":"US",
    "sg:address":"2588 Colorado St",
    "sg:city":"Sarasota",
    "sg:classifiers":[
        {
            "category":"Professional",
            "subcategory":"Management & Consulting",
            "type":"Services"
        }
    ],
    "sg:phone":"+1 941 957 3619",
    "sg:postcode":"34237",
    "sg:province":"FL",
    "sg:tags":[
        "retail",
        "direct",
        "sales"
    ],
    "wof:name":"J&M Enterprises Inc",
    "wof:placetype":"venue"
},
  "geometry": {"coordinates":[-82.519445,27.335508],"type":"Point"}
}