{
  "type": "Feature",
  "properties": {
    "addr:full":"1414 Chowkeebin Nene Tallahassee FL 32301",
    "addr:housenumber":"1414",
    "addr:postcode":"32301",
    "addr:street":"Chowkeebin Nene",
    "iso:country":"US",
    "sg:address":"1414 Chowkeebin Nene",
    "sg:city":"Tallahassee",
    "sg:classifiers":[
        {
            "category":"Education",
            "subcategory":"School",
            "type":"Public Place"
        }
    ],
    "sg:phone":"+1 850 488 7322",
    "sg:postcode":"32301",
    "sg:province":"FL",
    "sg:tags":[
        "elementary"
    ],
    "sg:website":"http://www.livelytech.com",
    "wof:name":"Frank Hartsfield Elementary School",
    "wof:placetype":"venue"
},
  "geometry": {"coordinates":[-84.25775899999999,30.433599],"type":"Point"}
}