{
  "type": "Feature",
  "properties": {
    "iso:country":"US",
    "sg:address":"8 SE 4th Ave",
    "sg:city":"Delray Beach",
    "sg:classifiers":[
        {
            "category":"Shopping",
            "subcategory":"Hobbies, Toys, & Games",
            "type":"Retail Goods"
        }
    ],
    "sg:phone":"+1 561 272 7598",
    "sg:postcode":"33483",
    "sg:province":"FL",
    "sg:tags":[
        "house",
        "doll",
        "accessory"
    ],
    "wof:name":"Doll House Corner Inc",
    "wof:placetype":"venue"
},
  "geometry": {"coordinates":[-80.069098,26.459931],"type":"Point"}
}