{
  "type": "Feature",
  "properties": {
    "addr:full":"613 Boston St Tarpon Springs FL 34689",
    "addr:housenumber":"613",
    "addr:postcode":"34689",
    "addr:street":"Boston St",
    "iso:country":"US",
    "sg:address":"613 Boston St",
    "sg:city":"Tarpon Springs",
    "sg:classifiers":[
        {
            "category":"Building & Trades",
            "subcategory":"Electrical",
            "type":"Services"
        }
    ],
    "sg:phone":"+1 727 919 0195",
    "sg:postcode":"34689",
    "sg:province":"FL",
    "sg:tags":[
        "electrical",
        "contractor"
    ],
    "wof:name":"Edward M Foraker",
    "wof:placetype":"venue"
},
  "geometry": {"coordinates":[-82.74657999999999,28.151833],"type":"Point"}
}