{
  "type": "Feature",
  "properties": {
    "addr:full":"2911 Vine St Orlando FL 32806",
    "addr:housenumber":"2911",
    "addr:postcode":"32806",
    "addr:street":"Vine St",
    "iso:country":"US",
    "sg:address":"2911 Vine St",
    "sg:city":"Orlando",
    "sg:classifiers":[
        {
            "category":"Building & Trades",
            "subcategory":"Construction",
            "type":"Services"
        }
    ],
    "sg:phone":"+1 407 898 7145",
    "sg:postcode":"32806",
    "sg:province":"FL",
    "sg:tags":[
        "house"
    ],
    "wof:name":"Mann Brothers Construction LLC",
    "wof:placetype":"venue"
},
  "geometry": {"coordinates":[-81.344779,28.526507],"type":"Point"}
}