{
  "type": "Feature",
  "properties": {
    "addr:full":"104 Scenic Hwy Haines City FL 33844",
    "addr:housenumber":"104",
    "addr:postcode":"33844",
    "addr:street":"Scenic Hwy",
    "iso:country":"US",
    "sg:address":"104 Scenic Hwy",
    "sg:city":"Haines City",
    "sg:classifiers":[
        {
            "category":"Organizations",
            "subcategory":"Religious Organization",
            "type":"Services"
        }
    ],
    "sg:phone":"+1 863 422 3334",
    "sg:postcode":"33844",
    "sg:province":"FL",
    "wof:name":"First Presbt Church-Haines Cy",
    "wof:placetype":"venue"
},
  "geometry": {"coordinates":[-81.63691300000001,28.081135],"type":"Point"}
}