{
  "type": "Feature",
  "properties": {
    "iso:country":"US",
    "sg:address":"18590 NW 67 Ave Ste 200",
    "sg:city":"Hialeah",
    "sg:classifiers":[
        {
            "category":"Banks & Credit Unions",
            "subcategory":"Atm",
            "type":"Services"
        }
    ],
    "sg:phone":"+1 305 820 0334",
    "sg:postcode":"33015",
    "sg:province":"FL",
    "sg:tags":[
        "bankruptcy"
    ],
    "sg:website":"ahernandezlaw.com",
    "wof:name":"Law Offices of Alberto H Hernandez",
    "wof:placetype":"venue"
},
  "geometry": {"coordinates":[-80.307236,25.941954],"type":"Point"}
}