{
  "type": "Feature",
  "properties": {
    "addr:full":"22289 General St Boca Raton FL 33428",
    "addr:housenumber":"22289",
    "addr:postcode":"33428",
    "addr:street":"General St",
    "iso:country":"US",
    "sg:address":"22289 General St",
    "sg:city":"Boca Raton",
    "sg:classifiers":[
        {
            "category":"Professional",
            "type":"Services"
        }
    ],
    "sg:phone":"+1 561 483 2506",
    "sg:postcode":"33428",
    "sg:province":"FL",
    "wof:name":"R Stan Breedlove",
    "wof:placetype":"venue"
},
  "geometry": {"coordinates":[-80.218227,26.345768],"type":"Point"}
}