{
  "type": "Feature",
  "properties": {
    "addr:full":"7141 Collins Ave Miami FL 33141",
    "addr:housenumber":"7141",
    "addr:postcode":"33141",
    "addr:street":"Collins Ave",
    "iso:country":"US",
    "sg:address":"7141 Collins Ave",
    "sg:city":"Miami",
    "sg:classifiers":[
        {
            "category":"Communications",
            "type":"Services"
        }
    ],
    "sg:phone":"+1 305 865 4044",
    "sg:postcode":"33141",
    "sg:province":"FL",
    "sg:tags":[
        "carrier"
    ],
    "wof:name":"Telexpress",
    "wof:placetype":"venue"
},
  "geometry": {"coordinates":[-80.120452,25.856877],"type":"Point"}
}