{
  "type": "Feature",
  "properties": {
    "iso:country":"US",
    "sg:address":"6690 W Flagler St",
    "sg:city":"Miami",
    "sg:classifiers":[
        {
            "category":"Autos & Motor Vehicles",
            "subcategory":"Fuel & Gas Station",
            "type":"Retail Goods"
        }
    ],
    "sg:phone":"+1 305 266 9719",
    "sg:postcode":"33144",
    "sg:province":"FL",
    "sg:tags":[
        "gasoline",
        "shipping"
    ],
    "wof:name":"Pak United Inc",
    "wof:placetype":"venue"
},
  "geometry": {"coordinates":[-80.303757,25.770531],"type":"Point"}
}