{
  "type": "Feature",
  "properties": {
    "iso:country":"US",
    "sg:address":"1810 Tamiami Trl N",
    "sg:city":"Naples",
    "sg:classifiers":[
        {
            "category":"Shopping",
            "subcategory":"Clothing, Apparel, & Fashions",
            "type":"Retail Goods"
        }
    ],
    "sg:phone":"+1 239 263 2026",
    "sg:postcode":"34102",
    "sg:province":"FL",
    "sg:tags":[
        "clothing",
        "store"
    ],
    "sg:website":"http://www.gap.com",
    "wof:name":"Gap",
    "wof:placetype":"venue"
},
  "geometry": {"coordinates":[-81.78284499999999,26.138081],"type":"Point"}
}