{
  "type": "Feature",
  "properties": {
    "iso:country":"US",
    "sg:address":"13327 SW 43rd Ln",
    "sg:city":"Miami",
    "sg:classifiers":[
        {
            "category":"Farming",
            "subcategory":"Farm",
            "type":"Manufacturing & Wholesale Goods"
        }
    ],
    "sg:phone":"+1 305 221 6046",
    "sg:postcode":"33175",
    "sg:province":"FL",
    "sg:tags":[
        "crop",
        "general"
    ],
    "wof:name":"Apanas Farm Inc",
    "wof:placetype":"venue"
},
  "geometry": {"coordinates":[-80.411447,25.727084],"type":"Point"}
}