{
  "type": "Feature",
  "properties": {
    "iso:country":"US",
    "sg:address":"2028 Buchanan St",
    "sg:city":"Hollywood",
    "sg:classifiers":[
        {
            "category":"Building & Trades",
            "subcategory":"Construction",
            "type":"Services"
        }
    ],
    "sg:phone":"+1 954 923 5430",
    "sg:postcode":"33020",
    "sg:province":"FL",
    "sg:tags":[
        "resurfacing",
        "laying",
        "refinishing",
        "floor"
    ],
    "wof:name":"D C Carpet Inc",
    "wof:placetype":"venue"
},
  "geometry": {"coordinates":[-80.148974,26.016878],"type":"Point"}
}