{
  "type": "Feature",
  "properties": {
    "addr:full":"6387 SW 41st St Miami FL 33155",
    "addr:housenumber":"6387",
    "addr:postcode":"33155",
    "addr:street":"Sw 41St St",
    "iso:country":"US",
    "sg:address":"6387 SW 41st St",
    "sg:city":"Miami",
    "sg:classifiers":[
        {
            "category":"Wholesale",
            "subcategory":"Non-durable Goods",
            "type":"Manufacturing & Wholesale Goods"
        }
    ],
    "sg:phone":"+1 305 668 5069",
    "sg:postcode":"33155",
    "sg:province":"FL",
    "wof:name":"Juluars Trading Inc",
    "wof:placetype":"venue"
},
  "geometry": {"coordinates":[-80.29713,25.732999],"type":"Point"}
}