{
  "type": "Feature",
  "properties": {
    "iso:country":"US",
    "sg:address":"1486 Skees Rd",
    "sg:city":"West Palm Beach",
    "sg:classifiers":[
        {
            "category":"Building & Trades",
            "subcategory":"Plumbing",
            "type":"Services"
        }
    ],
    "sg:phone":"+1 561 721 3330",
    "sg:postcode":"33411",
    "sg:province":"FL",
    "sg:tags":[
        "plumbing",
        "contractor"
    ],
    "wof:name":"Blue Water Plumbing Contractor",
    "wof:placetype":"venue"
},
  "geometry": {"coordinates":[-80.15768199999999,26.699351],"type":"Point"}
}