{
  "type": "Feature",
  "properties": {
    "iso:country":"US",
    "sg:address":"13301 SW 71st St",
    "sg:city":"Miami",
    "sg:classifiers":[
        {
            "category":"Professional",
            "subcategory":"Detective & Security Services",
            "type":"Services"
        }
    ],
    "sg:phone":"+1 305 989 4959",
    "sg:postcode":"33183",
    "sg:province":"FL",
    "sg:tags":[
        "equipment",
        "system",
        "consultant"
    ],
    "wof:name":"Pentagon Security Systems",
    "wof:placetype":"venue"
},
  "geometry": {"coordinates":[-80.408867,25.700609],"type":"Point"}
}