{
  "type": "Feature",
  "properties": {
    "iso:country":"US",
    "sg:address":"1014 Skipper Rd",
    "sg:city":"Tampa",
    "sg:classifiers":[
        {
            "category":"Organizations",
            "subcategory":"Community Association",
            "type":"Services"
        }
    ],
    "sg:phone":"+1 813 971 1881",
    "sg:postcode":"33613",
    "sg:province":"FL",
    "sg:tags":[
        "military"
    ],
    "wof:name":"Amvets Post 4",
    "wof:placetype":"venue"
},
  "geometry": {"coordinates":[-82.450526,28.080523],"type":"Point"}
}