{
  "type": "Feature",
  "properties": {
    "iso:country":"US",
    "sg:address":"771 NE 33rd St",
    "sg:city":"Boca Raton",
    "sg:classifiers":[
        {
            "category":"Health Services",
            "subcategory":"Doctor",
            "type":"Services"
        }
    ],
    "sg:phone":"+1 561 447 7818",
    "sg:postcode":"33431",
    "sg:province":"FL",
    "sg:tags":[
        "medical"
    ],
    "wof:name":"Anthony Riso MD PA",
    "wof:placetype":"venue"
},
  "geometry": {"coordinates":[-80.07248,26.380983],"type":"Point"}
}