{
  "type": "Feature",
  "properties": {
    "addr:full":"5112 N 34th St Tampa FL 33610",
    "addr:housenumber":"5112",
    "addr:postcode":"33610",
    "addr:street":"N 34Th St",
    "iso:country":"US",
    "sg:address":"5112 N 34th St",
    "sg:city":"Tampa",
    "sg:classifiers":[
        {
            "category":"Organizations",
            "subcategory":"Religious Organization",
            "type":"Services"
        }
    ],
    "sg:phone":"+1 813 232 4273",
    "sg:postcode":"33610",
    "sg:province":"FL",
    "sg:tags":[
        "church"
    ],
    "wof:name":"Agape Ministries Church Of God",
    "wof:placetype":"venue"
},
  "geometry": {"coordinates":[-82.422477,27.992946],"type":"Point"}
}