{
  "type": "Feature",
  "properties": {
    "addr:full":"925 Harbor Lake Ct Safety Harbor FL 34695",
    "addr:housenumber":"925",
    "addr:postcode":"34695",
    "addr:street":"Harbor Lake Ct",
    "iso:country":"US",
    "sg:address":"925 Harbor Lake Ct",
    "sg:city":"Safety Harbor",
    "sg:classifiers":[
        {
            "category":"Building & Trades",
            "subcategory":"Construction",
            "type":"Services"
        }
    ],
    "sg:phone":"+1 727 726 7554",
    "sg:postcode":"34695",
    "sg:province":"FL",
    "sg:tags":[
        "material",
        "fence",
        "contractor"
    ],
    "wof:name":"Bay Area Fence Factory Inc",
    "wof:placetype":"venue"
},
  "geometry": {"coordinates":[-82.69705399999999,27.998283],"type":"Point"}
}