{
  "type": "Feature",
  "properties": {
    "iso:country":"US",
    "sg:address":"7235 NE 4th Ave.",
    "sg:city":"Miami",
    "sg:classifiers":[
        {
            "category":"Shopping",
            "subcategory":"Party Supplies",
            "type":"Retail Goods"
        },
        {
            "category":"Home & Garden",
            "subcategory":"Home Furnishings",
            "type":"Retail Goods"
        },
        {
            "category":"Home & Garden",
            "subcategory":"Building Materials",
            "type":"Retail Goods"
        }
    ],
    "sg:phone":"+1 305 758 9444",
    "sg:postcode":"33138",
    "sg:province":"FL",
    "sg:tags":[
        "decor"
    ],
    "sg:website":"www.bamboobarry.com",
    "wof:name":"Bamboobarry",
    "wof:placetype":"venue"
},
  "geometry": {"coordinates":[-80.188945,25.840745],"type":"Point"}
}