{
  "type": "Feature",
  "properties": {
    "addr:full":"3109 Pga Blvd Palm Beach Gdns FL 33410",
    "addr:housenumber":"3109",
    "addr:postcode":"33410",
    "addr:street":"Pga Blvd Palm Beach Gdns",
    "iso:country":"US",
    "sg:address":"3109 Pga Blvd",
    "sg:city":"Palm Beach Gdns",
    "sg:classifiers":[
        {
            "category":"Shopping",
            "subcategory":"Department Store",
            "type":"Retail Goods"
        },
        {
            "category":"Personal",
            "subcategory":"Beauty Salon",
            "type":"Services"
        }
    ],
    "sg:phone":"+1 561 694 9009",
    "sg:postcode":"33410",
    "sg:province":"FL",
    "sg:website":"www.saks.com",
    "wof:name":"Salon At Saks Fifth Avenue",
    "wof:placetype":"venue"
},
  "geometry": {"coordinates":[-80.08539,26.845064],"type":"Point"}
}