{
  "type": "Feature",
  "properties": {
    "addr:full":"2214 W Skagway Ave Tampa FL 33604",
    "addr:housenumber":"2214",
    "addr:postcode":"33604",
    "addr:street":"W Skagway Ave",
    "iso:country":"US",
    "sg:address":"2214 W Skagway Ave",
    "sg:city":"Tampa",
    "sg:classifiers":[
        {
            "category":"Real Estate",
            "subcategory":"Real Estate Agent",
            "type":"Services"
        }
    ],
    "sg:phone":"+1 813 877 8228",
    "sg:postcode":"33604",
    "sg:province":"FL",
    "wof:name":"Patricia Realty Group",
    "wof:placetype":"venue"
},
  "geometry": {"coordinates":[-82.483906,28.032136],"type":"Point"}
}