{
  "type": "Feature",
  "properties": {
    "iso:country":"US",
    "sg:address":"1060 Aurora Rd",
    "sg:city":"Melbourne",
    "sg:classifiers":[
        {
            "category":"Wholesale",
            "subcategory":"Hardware",
            "type":"Manufacturing & Wholesale Goods"
        }
    ],
    "sg:phone":"+1 321 253 4000",
    "sg:postcode":"32935",
    "sg:province":"FL",
    "sg:tags":[
        "air",
        "parts",
        "conditioning",
        "supply"
    ],
    "wof:name":"Central Air Conditioning Inc",
    "wof:placetype":"venue"
},
  "geometry": {"coordinates":[-80.636712,28.133477],"type":"Point"}
}