{
  "type": "Feature",
  "properties": {
    "addr:full":"205 Hamilton Ave Panama City FL 32401",
    "addr:housenumber":"205",
    "addr:postcode":"32401",
    "addr:street":"Hamilton Ave",
    "iso:country":"US",
    "sg:address":"205 Hamilton Ave",
    "sg:city":"Panama City",
    "sg:classifiers":[
        {
            "category":"Education",
            "subcategory":"School",
            "type":"Public Place"
        }
    ],
    "sg:phone":"+1 850 747 0060",
    "sg:postcode":"32401",
    "sg:province":"FL",
    "wof:name":"Holy Nativity Episcopal School",
    "wof:placetype":"venue"
},
  "geometry": {"coordinates":[-85.65244300000001,30.148237],"type":"Point"}
}