{
  "type": "Feature",
  "properties": {
    "addr:full":"105 Hollywood Blvd Fort Walton Beach FL 32548",
    "addr:housenumber":"105",
    "addr:postcode":"32548",
    "addr:street":"Hollywood Blvd",
    "iso:country":"US",
    "sg:address":"105 Hollywood Blvd",
    "sg:city":"Fort Walton Beach",
    "sg:classifiers":[
        {
            "category":"Organizations",
            "subcategory":"Community Association",
            "type":"Services"
        }
    ],
    "sg:phone":"+1 850 243 0221",
    "sg:postcode":"32548",
    "sg:province":"FL",
    "sg:tags":[
        "civic"
    ],
    "wof:name":"Hinson Post 235",
    "wof:placetype":"venue"
},
  "geometry": {"coordinates":[-86.620187,30.412747],"type":"Point"}
}