{
  "type": "Feature",
  "properties": {
    "addr:full":"10726 NE Hwy 314 Silver Springs FL 34488",
    "addr:housenumber":"10726",
    "addr:postcode":"34488",
    "addr:street":"Ne Hwy 314",
    "iso:country":"US",
    "sg:address":"10726 NE Hwy 314",
    "sg:city":"Silver Springs",
    "sg:classifiers":[
        {
            "category":"Retail",
            "subcategory":"Animal Services",
            "type":"Services"
        }
    ],
    "sg:phone":"+1 352 625 4114",
    "sg:postcode":"34488",
    "sg:province":"FL",
    "sg:tags":[
        "pet",
        "grooming",
        "washing"
    ],
    "wof:name":"Heads Or Tails Pet Grooming",
    "wof:placetype":"venue"
},
  "geometry": {"coordinates":[-81.97651500000001,29.204612],"type":"Point"}
}