{
  "type": "Feature",
  "properties": {
    "addr:full":"10551 Gulf Blvd Treasure Island FL 33706",
    "addr:housenumber":"10551",
    "addr:postcode":"33706",
    "addr:street":"Gulf Blvd",
    "iso:country":"US",
    "sg:address":"10551 Gulf Blvd",
    "sg:city":"Treasure Island",
    "sg:classifiers":[
        {
            "category":"Shopping",
            "subcategory":"Pharmacy",
            "type":"Retail Goods"
        }
    ],
    "sg:phone":"+1 727 367 9800",
    "sg:postcode":"33706",
    "sg:province":"FL",
    "wof:name":"Walgreens",
    "wof:placetype":"venue"
},
  "geometry": {"coordinates":[-82.768732,27.767799],"type":"Point"}
}