{
  "type": "Feature",
  "properties": {
    "iso:country":"US",
    "sg:address":"543 SW 12th Ave",
    "sg:city":"Miami",
    "sg:classifiers":[
        {
            "category":"Food & Beverages",
            "subcategory":"Supermarket",
            "type":"Retail Goods"
        }
    ],
    "sg:phone":"+1 305 547 1995",
    "sg:postcode":"33130",
    "sg:province":"FL",
    "sg:tags":[
        "super",
        "store"
    ],
    "wof:name":"Loslatinos Supermarket",
    "wof:placetype":"venue"
},
  "geometry": {"coordinates":[-80.214495,25.768248],"type":"Point"}
}