{
  "type": "Feature",
  "properties": {
    "addr:full":"7600 S Red Rd Ste 223 South Miami FL 33143",
    "addr:housenumber":"7600",
    "addr:postcode":"33143",
    "addr:street":"S Red Rd Ste 223",
    "iso:country":"US",
    "sg:address":"7600 S Red Rd Ste 223",
    "sg:city":"South Miami",
    "sg:classifiers":[
        {
            "category":"Professional",
            "subcategory":"Lawyer & Legal Services",
            "type":"Services"
        }
    ],
    "sg:phone":"+1 305 665 5610",
    "sg:postcode":"33143",
    "sg:province":"FL",
    "wof:name":"Hamilton Maria Prats Atty",
    "wof:placetype":"venue"
},
  "geometry": {"coordinates":[-80.285667,25.700246],"type":"Point"}
}