{
  "type": "Feature",
  "properties": {
    "addr:full":"7020 Mira Flores Ave Coral Gables FL 33143",
    "addr:housenumber":"7020",
    "addr:postcode":"33143",
    "addr:street":"Mira Flores Ave",
    "iso:country":"US",
    "sg:address":"7020 Mira Flores Ave",
    "sg:city":"Coral Gables",
    "sg:classifiers":[
        {
            "category":"Professional",
            "subcategory":"Advertising",
            "type":"Services"
        }
    ],
    "sg:phone":"+1 305 666 3435",
    "sg:postcode":"33143",
    "sg:province":"FL",
    "sg:tags":[
        "distribution"
    ],
    "wof:name":"Rum Bum Distributors",
    "wof:placetype":"venue"
},
  "geometry": {"coordinates":[-80.25457,25.702117],"type":"Point"}
}