{
  "type": "Feature",
  "properties": {
    "iso:country":"US",
    "sg:address":"9641 Palm River Rd",
    "sg:city":"Tampa",
    "sg:classifiers":[
        {
            "category":"Restaurant",
            "type":"Food & Drink"
        }
    ],
    "sg:phone":"+1 813 663 9600",
    "sg:postcode":"33619",
    "sg:province":"FL",
    "sg:tags":[
        "eating"
    ],
    "wof:name":"Mima's Sandwiches N More Inc",
    "wof:placetype":"venue"
},
  "geometry": {"coordinates":[-82.34721500000001,27.94113],"type":"Point"}
}