{
  "type": "Feature",
  "properties": {
    "iso:country":"US",
    "sg:address":"901 4th St NW",
    "sg:city":"Ruskin",
    "sg:classifiers":[
        {
            "category":"Shopping",
            "subcategory":"Florist",
            "type":"Retail Goods"
        }
    ],
    "sg:phone":"+1 813 645 2528",
    "sg:postcode":"33570",
    "sg:province":"FL",
    "sg:tags":[
        "plant"
    ],
    "wof:name":"Plants Of Ruskin Inc",
    "wof:placetype":"venue"
},
  "geometry": {"coordinates":[-82.439161,27.7243],"type":"Point"}
}