{
  "type": "Feature",
  "properties": {
    "iso:country":"US",
    "sg:address":"160 C St",
    "sg:city":"Orange City",
    "sg:classifiers":[
        {
            "category":"Personal",
            "type":"Services"
        },
        {
            "category":"Retail",
            "subcategory":"Auto Repair",
            "type":"Services"
        }
    ],
    "sg:phone":"+1 386 775 6160",
    "sg:postcode":"32763",
    "sg:province":"FL",
    "sg:tags":[
        "body",
        "shop",
        "towing"
    ],
    "wof:name":"Orange City Collision Inc",
    "wof:placetype":"venue"
},
  "geometry": {"coordinates":[-81.298897,28.940399],"type":"Point"}
}