{
  "type": "Feature",
  "properties": {
    "iso:country":"US",
    "sg:address":"1319 Main St",
    "sg:city":"Sarasota",
    "sg:classifiers":[
        {
            "category":"Restaurant",
            "type":"Food & Drink"
        },
        {
            "category":"Bars & Pubs",
            "type":"Food & Drink"
        }
    ],
    "sg:phone":"+1 941 365 0469",
    "sg:postcode":"34236",
    "sg:province":"FL",
    "sg:tags":[
        "drinking"
    ],
    "wof:name":"Sports Page Bar & Grille",
    "wof:placetype":"venue"
},
  "geometry": {"coordinates":[-82.544014,27.335124],"type":"Point"}
}