{
  "type": "Feature",
  "properties": {
    "iso:country":"US",
    "sg:address":"5919 S Orange Blossom Trl",
    "sg:city":"Orlando",
    "sg:classifiers":[
        {
            "category":"Restaurant",
            "type":"Food & Drink"
        }
    ],
    "sg:menulink":"http://www.allmenus.com/fl/orlando/29819-rossis-pizza--pasta/menu/",
    "sg:phone":"+1 407 855 5755",
    "sg:postcode":"32809",
    "sg:province":"FL",
    "sg:tags":[
        "american",
        "italian",
        "pizza"
    ],
    "wof:name":"Rossi's Pizza & Pasta",
    "wof:placetype":"venue"
},
  "geometry": {"coordinates":[-81.39615499999999,28.471466],"type":"Point"}
}