{
  "type": "Feature",
  "properties": {
    "addr:full":"7566 Mill Stream Dr Naples FL 34109",
    "addr:housenumber":"7566",
    "addr:postcode":"34109",
    "addr:street":"Mill Stream Dr",
    "iso:country":"US",
    "sg:address":"7566 Mill Stream Dr",
    "sg:city":"Naples",
    "sg:classifiers":[
        {
            "category":"Retail",
            "subcategory":"Repair Shop",
            "type":"Services"
        }
    ],
    "sg:phone":"+1 239 592 6763",
    "sg:postcode":"34109",
    "sg:province":"FL",
    "wof:name":"Angelika & Martin Dziuba",
    "wof:placetype":"venue"
},
  "geometry": {"coordinates":[-81.771103,26.238461],"type":"Point"}
}