{
  "type": "Feature",
  "properties": {
    "iso:country":"US",
    "sg:address":"4421 SW 7th St",
    "sg:city":"Coral Gables",
    "sg:classifiers":[
        {
            "category":"Building & Trades",
            "subcategory":"Locksmith",
            "type":"Services"
        }
    ],
    "sg:phone":"+1 305 908 5046",
    "sg:postcode":"33134",
    "sg:province":"FL",
    "sg:tags":[
        "key"
    ],
    "wof:name":"0 1 Emergency A Locksmith",
    "wof:placetype":"venue"
},
  "geometry": {"coordinates":[-80.267616,25.764773],"type":"Point"}
}