{
  "type": "Feature",
  "properties": {
    "addr:full":"2531 NW 41st St Ste A3 Gainesville FL 32606",
    "addr:housenumber":"2531",
    "addr:postcode":"32606",
    "addr:street":"Nw 41St St Ste A3",
    "iso:country":"US",
    "sg:address":"2531 NW 41st St Ste A3",
    "sg:city":"Gainesville",
    "sg:classifiers":[
        {
            "category":"Professional",
            "subcategory":"Lawyer & Legal Services",
            "type":"Services"
        }
    ],
    "sg:phone":"+1 352 377 1774",
    "sg:postcode":"32606",
    "sg:province":"FL",
    "sg:tags":[
        "attorney"
    ],
    "wof:name":"Holthus, Gary N Law Offices Of",
    "wof:placetype":"venue"
},
  "geometry": {"coordinates":[-82.386521,29.676488],"type":"Point"}
}