{
  "type": "Feature",
  "properties": {
    "iso:country":"US",
    "sg:address":"749 S Apollo Blvd",
    "sg:city":"Melbourne",
    "sg:classifiers":[
        {
            "category":"Professional",
            "subcategory":"Printing & Photocopies",
            "type":"Services"
        },
        {
            "category":"Manufacturing",
            "subcategory":"Printing",
            "type":"Manufacturing & Wholesale Goods"
        }
    ],
    "sg:phone":"+1 321 984 8749",
    "sg:postcode":"32901",
    "sg:province":"FL",
    "sg:tags":[
        "photocopying",
        "printer"
    ],
    "wof:name":"Copies Unlimited Inc",
    "wof:placetype":"venue"
},
  "geometry": {"coordinates":[-80.618342,28.095887],"type":"Point"}
}