{
  "type": "Feature",
  "properties": {
    "iso:country":"US",
    "sg:address":"10471 SW 126th St",
    "sg:city":"Miami",
    "sg:classifiers":[
        {
            "category":"Real Estate",
            "subcategory":"Real Estate Agent",
            "type":"Services"
        }
    ],
    "sg:phone":"+1 305 235 1323",
    "sg:postcode":"33176",
    "sg:province":"FL",
    "wof:name":"F & L Realty Corp",
    "wof:placetype":"venue"
},
  "geometry": {"coordinates":[-80.36451,25.652196],"type":"Point"}
}