{
  "type": "Feature",
  "properties": {
    "addr:full":"210 Crown Point Cir Longwood FL 32779",
    "addr:housenumber":"210",
    "addr:postcode":"32779",
    "addr:street":"Crown Point Cir",
    "iso:country":"US",
    "sg:address":"210 Crown Point Cir",
    "sg:city":"Longwood",
    "sg:classifiers":[
        {
            "category":"Building & Trades",
            "subcategory":"Construction",
            "type":"Services"
        }
    ],
    "sg:phone":"+1 407 295 8000",
    "sg:postcode":"32779",
    "sg:province":"FL",
    "sg:tags":[
        "house"
    ],
    "wof:name":"Admiral Construction Inc",
    "wof:placetype":"venue"
},
  "geometry": {"coordinates":[-81.403341,28.690111],"type":"Point"}
}