{
  "type": "Feature",
  "properties": {
    "addr:full":"305 Nautilus St Panama City Bch FL 32413",
    "addr:housenumber":"305",
    "addr:postcode":"32413",
    "addr:street":"Nautilus St",
    "iso:country":"US",
    "sg:address":"305 Nautilus St",
    "sg:city":"Panama City Bch",
    "sg:classifiers":[
        {
            "category":"Manufacturing",
            "subcategory":"Building Materials",
            "type":"Manufacturing & Wholesale Goods"
        }
    ],
    "sg:phone":"+1 850 230 5428",
    "sg:postcode":"32413",
    "sg:province":"FL",
    "wof:name":"Custom Joinery & Millwork",
    "wof:placetype":"venue"
},
  "geometry": {"coordinates":[-85.84991599999999,30.209614],"type":"Point"}
}