{
  "type": "Feature",
  "properties": {
    "iso:country":"US",
    "sg:address":"9128 Nile Dr",
    "sg:city":"New Port Richey",
    "sg:classifiers":[
        {
            "category":"Retail",
            "subcategory":"Auto Repair",
            "type":"Services"
        }
    ],
    "sg:phone":"+1 727 849 1551",
    "sg:postcode":"34655",
    "sg:province":"FL",
    "sg:tags":[
        "repairing",
        "automobile"
    ],
    "wof:name":"Harry's Hi-Way Garage",
    "wof:placetype":"venue"
},
  "geometry": {"coordinates":[-82.66323300000001,28.225089],"type":"Point"}
}