{
  "type": "Feature",
  "properties": {
    "iso:country":"US",
    "sg:address":"3778 Pine Pitch Ct",
    "sg:city":"Ormond Beach",
    "sg:classifiers":[
        {
            "category":"Shopping",
            "type":"Retail Goods"
        }
    ],
    "sg:phone":"+1 386 676 9185",
    "sg:postcode":"32174",
    "sg:province":"FL",
    "sg:tags":[
        "merchandise"
    ],
    "wof:name":"Pampering Pet Sitting",
    "wof:placetype":"venue"
},
  "geometry": {"coordinates":[-81.24196999999999,29.222212],"type":"Point"}
}