{
  "type": "Feature",
  "properties": {
    "iso:country":"US",
    "sg:address":"6266 Janes Ln",
    "sg:city":"Naples",
    "sg:classifiers":[
        {
            "category":"Building & Trades",
            "subcategory":"Construction",
            "type":"Services"
        }
    ],
    "sg:phone":"+1 239 593 7702",
    "sg:postcode":"34109",
    "sg:province":"FL",
    "sg:tags":[
        "carpentry",
        "contractor"
    ],
    "wof:name":"Renaissance Cabinets and Mllwk",
    "wof:placetype":"venue"
},
  "geometry": {"coordinates":[-81.778012,26.220845],"type":"Point"}
}