{
  "type": "Feature",
  "properties": {
    "iso:country":"US",
    "sg:address":"6418 Hoffner Ave",
    "sg:city":"Orlando",
    "sg:classifiers":[
        {
            "category":"Communications",
            "subcategory":"Film & Video Production",
            "type":"Services"
        }
    ],
    "sg:phone":"+1 407 277 7728",
    "sg:postcode":"32822",
    "sg:province":"FL",
    "sg:tags":[
        "photographer",
        "aerial"
    ],
    "sg:website":"http://igtwebsites.com",
    "wof:name":"IGT Aerial Photography",
    "wof:placetype":"venue"
},
  "geometry": {"coordinates":[-81.29741199999999,28.480691],"type":"Point"}
}