{
  "type": "Feature",
  "properties": {
    "iso:country":"US",
    "sg:address":"4261 Westroads Dr",
    "sg:city":"West Palm Beach",
    "sg:classifiers":[
        {
            "category":"Autos & Motor Vehicles",
            "subcategory":"Automobile Sales",
            "type":"Retail Goods"
        }
    ],
    "sg:phone":"+1 561 840 1880",
    "sg:postcode":"33407",
    "sg:province":"FL",
    "sg:tags":[
        "car",
        "dealer"
    ],
    "wof:name":"M & M Autobody & Used Cars",
    "wof:placetype":"venue"
},
  "geometry": {"coordinates":[-80.104428,26.773363],"type":"Point"}
}