{
  "type": "Feature",
  "properties": {
    "addr:full":"526 SE Monterey Rd Stuart FL 34994",
    "addr:housenumber":"526",
    "addr:postcode":"34994",
    "addr:street":"Se Monterey Rd",
    "iso:country":"US",
    "sg:address":"526 SE Monterey Rd",
    "sg:city":"Stuart",
    "sg:classifiers":[
        {
            "category":"Retail",
            "subcategory":"Auto Repair",
            "type":"Services"
        }
    ],
    "sg:phone":"+1 772 288 3877",
    "sg:postcode":"34994",
    "sg:province":"FL",
    "sg:tags":[
        "body",
        "automobile",
        "top",
        "upholstery"
    ],
    "wof:name":"Julian's Auto Upholstery",
    "wof:placetype":"venue"
},
  "geometry": {"coordinates":[-80.245976,27.175559],"type":"Point"}
}