{
  "type": "Feature",
  "properties": {
    "addr:full":"1209 S Peninsula Dr Daytona Beach FL 32118",
    "addr:housenumber":"1209",
    "addr:postcode":"32118",
    "addr:street":"S Peninsula Dr",
    "iso:country":"US",
    "sg:address":"1209 S Peninsula Dr",
    "sg:city":"Daytona Beach",
    "sg:classifiers":[
        {
            "category":"Travel",
            "subcategory":"Hotels & Motels",
            "type":"Entertainment"
        }
    ],
    "sg:phone":"+1 386 248 8420",
    "sg:postcode":"32118",
    "sg:province":"FL",
    "sg:tags":[
        "breakfast",
        "accommodation",
        "bed"
    ],
    "wof:name":"Miss Pat's Inn",
    "wof:placetype":"venue"
},
  "geometry": {"coordinates":[-81.005391,29.210954],"type":"Point"}
}