{
  "type": "Feature",
  "properties": {
    "iso:country":"US",
    "sg:address":"6325 N Orange Blossom Trl",
    "sg:city":"Orlando",
    "sg:classifiers":[
        {
            "category":"Shopping",
            "subcategory":"Used Merchandise",
            "type":"Retail Goods"
        }
    ],
    "sg:phone":"+1 407 521 4956",
    "sg:postcode":"32810",
    "sg:province":"FL",
    "sg:tags":[
        "pawnbroker",
        "pawnshop"
    ],
    "wof:name":"Cash America Pawn",
    "wof:placetype":"venue"
},
  "geometry": {"coordinates":[-81.433311,28.61349],"type":"Point"}
}