{
  "type": "Feature",
  "properties": {
    "iso:country":"US",
    "sg:address":"9766 Old Saint Augustine Rd",
    "sg:city":"Jacksonville",
    "sg:classifiers":[
        {
            "category":"Shopping",
            "subcategory":"Bicycles & Sporting Goods",
            "type":"Retail Goods"
        }
    ],
    "sg:phone":"+1 904 731 8866",
    "sg:postcode":"32257",
    "sg:province":"FL",
    "sg:tags":[
        "equipment",
        "diver",
        "supply"
    ],
    "sg:website":"www.diverselitetraining.com",
    "wof:name":"Diver's Elite Training-Fl",
    "wof:placetype":"venue"
},
  "geometry": {"coordinates":[-81.61527,30.199705],"type":"Point"}
}