{
  "type": "Feature",
  "properties": {
    "iso:country":"US",
    "sg:address":"2239 Blanding Blvd",
    "sg:city":"Middleburg",
    "sg:classifiers":[
        {
            "category":"Real Estate",
            "subcategory":"Real Estate Services",
            "type":"Services"
        }
    ],
    "sg:phone":"+1 904 282 3477",
    "sg:postcode":"32068",
    "sg:province":"FL",
    "sg:tags":[
        "company",
        "title"
    ],
    "wof:name":"Watson & Osborne Pa",
    "wof:placetype":"venue"
},
  "geometry": {"coordinates":[-81.86010899999999,30.083818],"type":"Point"}
}