{
  "type": "Feature",
  "properties": {
    "addr:full":"3720 Silver Star Rd Orlando FL 32808",
    "addr:housenumber":"3720",
    "addr:postcode":"32808",
    "addr:street":"Silver Star Rd",
    "iso:country":"US",
    "sg:address":"3720 Silver Star Rd",
    "sg:city":"Orlando",
    "sg:classifiers":[
        {
            "category":"Organizations",
            "subcategory":"Religious Organization",
            "type":"Services"
        }
    ],
    "sg:phone":"+1 407 299 0771",
    "sg:postcode":"32808",
    "sg:province":"FL",
    "sg:tags":[
        "church"
    ],
    "wof:name":"Christ Sanctified Church",
    "wof:placetype":"venue"
},
  "geometry": {"coordinates":[-81.425361,28.578014],"type":"Point"}
}