{
  "type": "Feature",
  "properties": {
    "iso:country":"US",
    "sg:address":"279 Douglas Ave",
    "sg:city":"Altamonte Springs",
    "sg:classifiers":[
        {
            "category":"Home & Garden",
            "subcategory":"Building Materials",
            "type":"Retail Goods"
        }
    ],
    "sg:phone":"+1 407 862 3100",
    "sg:postcode":"32714",
    "sg:province":"FL",
    "sg:tags":[
        "interior",
        "shutter"
    ],
    "wof:name":"Sunburst Shutters",
    "wof:placetype":"venue"
},
  "geometry": {"coordinates":[-81.39028399999999,28.665274],"type":"Point"}
}