{
  "type": "Feature",
  "properties": {
    "iso:country":"US",
    "sg:address":"530 Brightwaters Dr",
    "sg:city":"Cocoa Beach",
    "sg:classifiers":[
        {
            "category":"Shopping",
            "subcategory":"Computers & Home Electronics",
            "type":"Retail Goods"
        }
    ],
    "sg:phone":"+1 321 783 1997",
    "sg:postcode":"32931",
    "sg:province":"FL",
    "wof:name":"Fmks Inc",
    "wof:placetype":"venue"
},
  "geometry": {"coordinates":[-80.611839,28.36542],"type":"Point"}
}