{
  "type": "Feature",
  "properties": {
    "iso:country":"US",
    "sg:address":"7162 N University Dr",
    "sg:city":"Fort Lauderdale",
    "sg:classifiers":[
        {
            "category":"Health Services",
            "subcategory":"Podiatrist",
            "type":"Services"
        }
    ],
    "sg:phone":"+1 954 726 9255",
    "sg:postcode":"33321",
    "sg:province":"FL",
    "wof:name":"Behfar Kasra N DPM PA",
    "wof:placetype":"venue"
},
  "geometry": {"coordinates":[-80.25228799999999,26.21157],"type":"Point"}
}