{
  "type": "Feature",
  "properties": {
    "iso:country":"US",
    "sg:address":"1925 Ham Brown Rd",
    "sg:city":"Kissimmee",
    "sg:classifiers":[
        {
            "category":"Education",
            "subcategory":"School",
            "type":"Public Place"
        }
    ],
    "sg:phone":"+1 407 870 4866",
    "sg:postcode":"34746",
    "sg:province":"FL",
    "sg:tags":[
        "elementary"
    ],
    "sg:website":"http://www.osceola.k12.fl.us",
    "wof:name":"Sunrise Elementary School",
    "wof:placetype":"venue"
},
  "geometry": {"coordinates":[-81.462543,28.248448],"type":"Point"}
}