{
  "type": "Feature",
  "properties": {
    "iso:country":"US",
    "sg:address":"2805 Kipps Colony Dr S",
    "sg:city":"Saint Petersburg",
    "sg:classifiers":[
        {
            "category":"Banks & Credit Unions",
            "subcategory":"Investment Brokerage",
            "type":"Services"
        }
    ],
    "sg:phone":"+1 727 345 6206",
    "sg:postcode":"33707",
    "sg:province":"FL",
    "sg:tags":[
        "advisory"
    ],
    "wof:name":"P W Northcott",
    "wof:placetype":"venue"
},
  "geometry": {"coordinates":[-82.72278900000001,27.742885],"type":"Point"}
}