{
  "type": "Feature",
  "properties": {
    "iso:country":"US",
    "sg:address":"8801 College Pkwy Ste 4",
    "sg:city":"Fort Myers",
    "sg:classifiers":[
        {
            "category":"Health Services",
            "subcategory":"Dentist",
            "type":"Services"
        }
    ],
    "sg:phone":"+1 239 433 4404",
    "sg:postcode":"33919",
    "sg:province":"FL",
    "wof:name":"Kaplan Jan DDS PA",
    "wof:placetype":"venue"
},
  "geometry": {"coordinates":[-81.900597,26.5567],"type":"Point"}
}