{
  "type": "Feature",
  "properties": {
    "iso:country":"US",
    "sg:address":"1376 Brickyard Rd Ste 5",
    "sg:city":"Chipley",
    "sg:classifiers":[
        {
            "category":"Health Services",
            "subcategory":"Doctor",
            "type":"Services"
        }
    ],
    "sg:phone":"+1 850 638 4383",
    "sg:postcode":"32428",
    "sg:province":"FL",
    "sg:tags":[
        "physician",
        "family",
        "practice",
        "surgeons",
        "medicine",
        "surgeon"
    ],
    "wof:name":"Southern Family Healthcare",
    "wof:placetype":"venue"
},
  "geometry": {"coordinates":[-85.54338199999999,30.764561],"type":"Point"}
}