{
  "type": "Feature",
  "properties": {
    "iso:country":"US",
    "sg:address":"1835 Taylor Rd",
    "sg:city":"Daytona Beach",
    "sg:classifiers":[
        {
            "category":"Organizations",
            "subcategory":"Religious Organization",
            "type":"Services"
        }
    ],
    "sg:phone":"+1 386 788 4870",
    "sg:postcode":"32128",
    "sg:province":"FL",
    "wof:name":"Living Cornerstone Church",
    "wof:placetype":"venue"
},
  "geometry": {"coordinates":[-81.05439800000001,29.085451],"type":"Point"}
}