{
  "type": "Feature",
  "properties": {
    "addr:full":"1006 NE Saint Lucie Blvd Port St Lucie FL 34957",
    "addr:housenumber":"1006",
    "addr:postcode":"34957",
    "addr:street":"Ne Saint Lucie Blvd",
    "iso:country":"US",
    "sg:address":"1006 NE Saint Lucie Blvd",
    "sg:city":"Port St Lucie",
    "sg:classifiers":[
        {
            "category":"Personal",
            "subcategory":"Beauty Salon",
            "type":"Services"
        }
    ],
    "sg:phone":"+1 772 878 0848",
    "sg:postcode":"34957",
    "sg:province":"FL",
    "sg:tags":[
        "treatment",
        "skin"
    ],
    "wof:name":"Skin & Nail Care Clinic",
    "wof:placetype":"venue"
},
  "geometry": {"coordinates":[-80.242642,27.215458],"type":"Point"}
}