{
  "type": "Feature",
  "properties": {
    "iso:country":"US",
    "sg:address":"6645 Miraflores Ave",
    "sg:city":"Cocoa",
    "sg:classifiers":[
        {
            "category":"Manufacturing",
            "subcategory":"Apparel",
            "type":"Manufacturing & Wholesale Goods"
        }
    ],
    "sg:phone":"+1 321 631 3453",
    "sg:postcode":"32927",
    "sg:province":"FL",
    "wof:name":"Taylwagon & Stuff",
    "wof:placetype":"venue"
},
  "geometry": {"coordinates":[-80.787592,28.475756],"type":"Point"}
}