{
  "type": "Feature",
  "properties": {
    "addr:full":"5120 Silver Star Rd Orlando FL 32808",
    "addr:housenumber":"5120",
    "addr:postcode":"32808",
    "addr:street":"Silver Star Rd",
    "iso:country":"US",
    "sg:address":"5120 Silver Star Rd",
    "sg:city":"Orlando",
    "sg:classifiers":[
        {
            "category":"Utilities",
            "subcategory":"Telephone",
            "type":"Services"
        }
    ],
    "sg:phone":"+1 407 298 8930",
    "sg:postcode":"32808",
    "sg:province":"FL",
    "sg:tags":[
        "company"
    ],
    "wof:name":"Bell South",
    "wof:placetype":"venue"
},
  "geometry": {"coordinates":[-81.451193,28.57788],"type":"Point"}
}