{
  "type": "Feature",
  "properties": {
    "iso:country":"US",
    "sg:address":"511 Doctors Dr",
    "sg:city":"Oviedo",
    "sg:classifiers":[
        {
            "category":"Organizations",
            "subcategory":"Religious Organization",
            "type":"Services"
        }
    ],
    "sg:phone":"+1 407 322 8717",
    "sg:postcode":"32765",
    "sg:province":"FL",
    "sg:tags":[
        "place",
        "worship",
        "church"
    ],
    "wof:name":"True Church Of God",
    "wof:placetype":"venue"
},
  "geometry": {"coordinates":[-81.198459,28.66429],"type":"Point"}
}