{
  "type": "Feature",
  "properties": {
    "iso:country":"US",
    "sg:address":"3625 Warbler Dr",
    "sg:city":"New Port Richey",
    "sg:classifiers":[
        {
            "category":"Building & Trades",
            "subcategory":"Construction",
            "type":"Services"
        }
    ],
    "sg:phone":"+1 727 848 1644",
    "sg:postcode":"34652",
    "sg:province":"FL",
    "sg:tags":[
        "floor",
        "laying",
        "contractor"
    ],
    "wof:name":"James Edward Parlett",
    "wof:placetype":"venue"
},
  "geometry": {"coordinates":[-82.71809399999999,28.213364],"type":"Point"}
}