{
  "type": "Feature",
  "properties": {
    "addr:full":"5865 Aucilla Rd Monticello FL 32344",
    "addr:housenumber":"5865",
    "addr:postcode":"32344",
    "addr:street":"Aucilla Rd",
    "iso:country":"US",
    "sg:address":"5865 Aucilla Rd",
    "sg:city":"Monticello",
    "sg:classifiers":[
        {
            "category":"Building & Trades",
            "subcategory":"Construction",
            "type":"Services"
        }
    ],
    "sg:phone":"+1 850 997 8449",
    "sg:postcode":"32344",
    "sg:province":"FL",
    "sg:tags":[
        "roofing",
        "industrial",
        "contractors-commercial",
        "contractor"
    ],
    "wof:name":"Pat's Roofing & Repair",
    "wof:placetype":"venue"
},
  "geometry": {"coordinates":[-83.789067,30.491821],"type":"Point"}
}