{
  "type": "Feature",
  "properties": {
    "addr:full":"1940 50th St SW Naples FL 34116",
    "addr:housenumber":"1940",
    "addr:postcode":"34116",
    "addr:street":"50Th St Sw",
    "iso:country":"US",
    "sg:address":"1940 50th St SW",
    "sg:city":"Naples",
    "sg:classifiers":[
        {
            "category":"Personal",
            "type":"Services"
        }
    ],
    "sg:phone":"+1 239 455 2149",
    "sg:postcode":"34116",
    "sg:province":"FL",
    "sg:tags":[
        "therapist",
        "massage"
    ],
    "wof:name":"Robin Vecchio Lmt",
    "wof:placetype":"venue"
},
  "geometry": {"coordinates":[-81.70765,26.193742],"type":"Point"}
}