{
  "type": "Feature",
  "properties": {
    "iso:country":"US",
    "sg:address":"725 Gulf Shore Dr 5058",
    "sg:city":"Destin",
    "sg:classifiers":[
        {
            "category":"Autos & Motor Vehicles",
            "subcategory":"Boat Sales",
            "type":"Retail Goods"
        }
    ],
    "sg:phone":"+1 850 259 9900",
    "sg:postcode":"32541",
    "sg:province":"FL",
    "sg:tags":[
        "ship",
        "yacht",
        "broker"
    ],
    "wof:name":"Matt Condon Yacht Sales",
    "wof:placetype":"venue"
},
  "geometry": {"coordinates":[-86.486728,30.384645],"type":"Point"}
}