{
  "type": "Feature",
  "properties": {
    "iso:country":"US",
    "sg:address":"1320 NW 171st St",
    "sg:city":"Miami",
    "sg:classifiers":[
        {
            "category":"Shopping",
            "type":"Retail Goods"
        }
    ],
    "sg:phone":"+1 305 621 2269",
    "sg:postcode":"33169",
    "sg:province":"FL",
    "sg:tags":[
        "merchandise"
    ],
    "wof:name":"Asnakala Inc",
    "wof:placetype":"venue"
},
  "geometry": {"coordinates":[-80.22326099999999,25.930808],"type":"Point"}
}