{
  "type": "Feature",
  "properties": {
    "addr:full":"125 S Ocean Ave Riviera Beach FL 33404",
    "addr:housenumber":"125",
    "addr:postcode":"33404",
    "addr:street":"S Ocean Ave",
    "iso:country":"US",
    "sg:address":"125 S Ocean Ave",
    "sg:city":"Riviera Beach",
    "sg:classifiers":[
        {
            "category":"Real Estate",
            "subcategory":"Real Estate Operator",
            "type":"Services"
        }
    ],
    "sg:phone":"+1 561 844 4550",
    "sg:postcode":"33404",
    "sg:province":"FL",
    "sg:tags":[
        "condominium"
    ],
    "wof:name":"Mayan Towers Condominium",
    "wof:placetype":"venue"
},
  "geometry": {"coordinates":[-80.03363,26.77958],"type":"Point"}
}