{
  "type": "Feature",
  "properties": {
    "iso:country":"US",
    "sg:address":"1200 Ponce De Leon Blvd",
    "sg:city":"Coral Gables",
    "sg:classifiers":[
        {
            "category":"Building & Trades",
            "subcategory":"Construction",
            "type":"Services"
        }
    ],
    "sg:phone":"+1 305 705 0001",
    "sg:postcode":"33134",
    "sg:province":"FL",
    "sg:tags":[
        "contractor"
    ],
    "wof:name":"Breakstone Construction",
    "wof:placetype":"venue"
},
  "geometry": {"coordinates":[-80.259102,25.760201],"type":"Point"}
}