{
  "type": "Feature",
  "properties": {
    "iso:country":"US",
    "sg:address":"6169 Westwood Blvd",
    "sg:city":"Orlando",
    "sg:classifiers":[
        {
            "category":"Food & Beverages",
            "subcategory":"Liquor & Beverages",
            "type":"Retail Goods"
        },
        {
            "category":"Wholesale",
            "subcategory":"Wine & Distilled Alcoholic Beverages",
            "type":"Manufacturing & Wholesale Goods"
        }
    ],
    "sg:phone":"+1 407 354 3730",
    "sg:postcode":"32821",
    "sg:province":"FL",
    "sg:tags":[
        "liquors-wholesale",
        "store"
    ],
    "wof:name":"I-Drive Liquors Inc",
    "wof:placetype":"venue"
},
  "geometry": {"coordinates":[-81.46151399999999,28.419351],"type":"Point"}
}