{
  "type": "Feature",
  "properties": {
    "iso:country":"US",
    "sg:address":"9100 Navarre Pkwy",
    "sg:city":"Gulf Breeze",
    "sg:classifiers":[
        {
            "category":"Shopping",
            "subcategory":"Computers & Home Electronics",
            "type":"Retail Goods"
        }
    ],
    "sg:phone":"+1 850 939 7222",
    "sg:postcode":"32566",
    "sg:province":"FL",
    "sg:tags":[
        "equipment",
        "satellite",
        "system"
    ],
    "wof:name":"Home Satellite Solutions",
    "wof:placetype":"venue"
},
  "geometry": {"coordinates":[-86.845068,30.40799],"type":"Point"}
}