{
  "type": "Feature",
  "properties": {
    "addr:full":"1190 E Ohio Ave Lake Helen FL 32744",
    "addr:housenumber":"1190",
    "addr:postcode":"32744",
    "addr:street":"E Ohio Ave",
    "iso:country":"US",
    "sg:address":"1190 E Ohio Ave",
    "sg:city":"Lake Helen",
    "sg:classifiers":[
        {
            "category":"Retail",
            "subcategory":"Repair Shop",
            "type":"Services"
        }
    ],
    "sg:phone":"+1 386 228 3525",
    "sg:postcode":"32744",
    "sg:province":"FL",
    "sg:tags":[
        "taxidermist"
    ],
    "wof:name":"Rick Hardy Taxidermy",
    "wof:placetype":"venue"
},
  "geometry": {"coordinates":[-81.21257900000001,28.979352],"type":"Point"}
}