{
  "type": "Feature",
  "properties": {
    "addr:full":"6021 Blanding Blvd Jacksonville FL 32244",
    "addr:housenumber":"6021",
    "addr:postcode":"32244",
    "addr:street":"Blanding Blvd",
    "iso:country":"US",
    "sg:address":"6021 Blanding Blvd",
    "sg:city":"Jacksonville",
    "sg:classifiers":[
        {
            "category":"Home & Garden",
            "subcategory":"Mobile Homes",
            "type":"Retail Goods"
        }
    ],
    "sg:phone":"+1 904 772 8031",
    "sg:postcode":"32244",
    "sg:province":"FL",
    "wof:name":"CMH",
    "wof:placetype":"venue"
},
  "geometry": {"coordinates":[-81.73993,30.23598],"type":"Point"}
}