{
  "type": "Feature",
  "properties": {
    "addr:full":"1009 S University Dr Fort Lauderdale FL 33324",
    "addr:housenumber":"1009",
    "addr:postcode":"33324",
    "addr:street":"S University Dr",
    "iso:country":"US",
    "sg:address":"1009 S University Dr",
    "sg:city":"Fort Lauderdale",
    "sg:classifiers":[
        {
            "category":"Personal",
            "subcategory":"Beauty Salon",
            "type":"Services"
        }
    ],
    "sg:phone":"+1 954 476 0727",
    "sg:postcode":"33324",
    "sg:province":"FL",
    "sg:tags":[
        "shop"
    ],
    "wof:name":"Michaels Hair & Co",
    "wof:placetype":"venue"
},
  "geometry": {"coordinates":[-80.250147,26.105629],"type":"Point"}
}