{
  "type": "Feature",
  "properties": {
    "iso:country":"US",
    "sg:address":"9905 Clint Moore Rd",
    "sg:city":"Boca Raton",
    "sg:classifiers":[
        {
            "category":"Food & Beverages",
            "subcategory":"Groceries & Convenience Stores",
            "type":"Retail Goods"
        }
    ],
    "sg:phone":"+1 561 451 8825",
    "sg:postcode":"33496",
    "sg:province":"FL",
    "wof:name":"Downs Derl",
    "wof:placetype":"venue"
},
  "geometry": {"coordinates":[-80.20130899999999,26.408779],"type":"Point"}
}