{
  "type": "Feature",
  "properties": {
    "iso:country":"US",
    "sg:address":"5419 NW 163rd St",
    "sg:city":"Hialeah",
    "sg:classifiers":[
        {
            "category":"Professional",
            "subcategory":"Management & Consulting",
            "type":"Services"
        }
    ],
    "sg:phone":"+1 305 624 6910",
    "sg:postcode":"33014",
    "sg:province":"FL",
    "sg:tags":[
        "consultant",
        "energy",
        "conservation"
    ],
    "wof:name":"Conference Resources Solutions",
    "wof:placetype":"venue"
},
  "geometry": {"coordinates":[-80.290081,25.921294],"type":"Point"}
}