{
  "type": "Feature",
  "properties": {
    "addr:full":"729 5th St Miami Beach FL 33139",
    "addr:housenumber":"729",
    "addr:postcode":"33139",
    "addr:street":"5Th St",
    "iso:country":"US",
    "sg:address":"729 5th St",
    "sg:city":"Miami Beach",
    "sg:classifiers":[
        {
            "category":"Personal",
            "subcategory":"Beauty Salon",
            "type":"Services"
        }
    ],
    "sg:phone":"+1 305 674 6836",
    "sg:postcode":"33139",
    "sg:province":"FL",
    "sg:tags":[
        "shop"
    ],
    "wof:name":"Vitabella Salon",
    "wof:placetype":"venue"
},
  "geometry": {"coordinates":[-80.135751,25.774527],"type":"Point"}
}