{
  "type": "Feature",
  "properties": {
    "iso:country":"US",
    "sg:address":"1340 Tuskawilla Rd Ste 108",
    "sg:city":"Winter Springs",
    "sg:classifiers":[
        {
            "category":"Health Services",
            "subcategory":"Dentist",
            "type":"Services"
        }
    ],
    "sg:phone":"+1 407 695 2005",
    "sg:postcode":"32708",
    "sg:province":"FL",
    "wof:name":"Matteson Robert D DMD PA",
    "wof:placetype":"venue"
},
  "geometry": {"coordinates":[-81.269402,28.6492],"type":"Point"}
}