{
  "type": "Feature",
  "properties": {
    "addr:full":"10117 Sunset Strip Fort Lauderdale FL 33322",
    "addr:housenumber":"10117",
    "addr:postcode":"33322",
    "addr:street":"Sunset Strip",
    "iso:country":"US",
    "sg:address":"10117 Sunset Strip",
    "sg:city":"Fort Lauderdale",
    "sg:classifiers":[
        {
            "category":"Shopping",
            "subcategory":"Florist",
            "type":"Retail Goods"
        }
    ],
    "sg:phone":"+1 954 748 2112",
    "sg:postcode":"33322",
    "sg:province":"FL",
    "wof:name":"Sunrise Greenery",
    "wof:placetype":"venue"
},
  "geometry": {"coordinates":[-80.28488400000001,26.152941],"type":"Point"}
}