{
  "type": "Feature",
  "properties": {
    "addr:full":"1304 Mirror Ter NW Winter Haven FL 33881",
    "addr:housenumber":"1304",
    "addr:postcode":"33881",
    "addr:street":"Mirror Ter Nw",
    "iso:country":"US",
    "sg:address":"1304 Mirror Ter NW",
    "sg:city":"Winter Haven",
    "sg:classifiers":[
        {
            "category":"Farming",
            "subcategory":"Orchard",
            "type":"Manufacturing & Wholesale Goods"
        }
    ],
    "sg:phone":"+1 863 293 8944",
    "sg:postcode":"33881",
    "sg:province":"FL",
    "sg:tags":[
        "citrus",
        "grove",
        "fruit"
    ],
    "wof:name":"Ridge Citrus",
    "wof:placetype":"venue"
},
  "geometry": {"coordinates":[-81.738052,28.034205],"type":"Point"}
}