{
  "type": "Feature",
  "properties": {
    "addr:full":"510 Dracena Way Gulf Breeze FL 32561",
    "addr:housenumber":"510",
    "addr:postcode":"32561",
    "addr:street":"Dracena Way",
    "iso:country":"US",
    "sg:address":"510 Dracena Way",
    "sg:city":"Gulf Breeze",
    "sg:classifiers":[
        {
            "category":"Wholesale",
            "subcategory":"Toys & Hobbies",
            "type":"Manufacturing & Wholesale Goods"
        }
    ],
    "sg:phone":"+1 850 934 1211",
    "sg:postcode":"32561",
    "sg:province":"FL",
    "sg:tags":[
        "wholesaler"
    ],
    "wof:name":"Southeast Supply",
    "wof:placetype":"venue"
},
  "geometry": {"coordinates":[-87.171278,30.357278],"type":"Point"}
}