{
  "type": "Feature",
  "properties": {
    "addr:full":"10352 SW 114th Ter Miami FL 33176",
    "addr:housenumber":"10352",
    "addr:postcode":"33176",
    "addr:street":"Sw 114Th Ter",
    "iso:country":"US",
    "sg:address":"10352 SW 114th Ter",
    "sg:city":"Miami",
    "sg:classifiers":[
        {
            "category":"Professional",
            "subcategory":"Engineering",
            "type":"Services"
        }
    ],
    "sg:phone":"+1 305 253 8131",
    "sg:postcode":"33176",
    "sg:province":"FL",
    "sg:tags":[
        "engineer",
        "structural"
    ],
    "wof:name":"Dario Gonzalez Pe, Dario",
    "wof:placetype":"venue"
},
  "geometry": {"coordinates":[-80.362129,25.662686],"type":"Point"}
}