{
  "type": "Feature",
  "properties": {
    "iso:country":"US",
    "sg:address":"19921 W Newberry Rd",
    "sg:city":"Newberry",
    "sg:classifiers":[
        {
            "category":"Manufacturing",
            "subcategory":"Tools & Machinery",
            "type":"Manufacturing & Wholesale Goods"
        },
        {
            "category":"Home & Garden",
            "subcategory":"Household Appliances",
            "type":"Retail Goods"
        },
        {
            "category":"Wholesale",
            "subcategory":"Electrical",
            "type":"Manufacturing & Wholesale Goods"
        },
        {
            "category":"Shopping",
            "subcategory":"Computers & Home Electronics",
            "type":"Retail Goods"
        },
        {
            "category":"Home & Garden",
            "subcategory":"Hardware",
            "type":"Retail Goods"
        }
    ],
    "sg:phone":"+1 352 472 6322",
    "sg:postcode":"32669",
    "sg:province":"FL",
    "sg:tags":[
        "major",
        "electric",
        "supply",
        "supplies-wholesale",
        "appliances-small",
        "equipment",
        "consumer",
        "store",
        "manufacturer"
    ],
    "wof:name":"Specialty Electric Supply",
    "wof:placetype":"venue"
},
  "geometry": {"coordinates":[-82.554209,29.654555],"type":"Point"}
}