{
  "type": "Feature",
  "properties": {
    "iso:country":"US",
    "sg:address":"286 N Havana Rd",
    "sg:city":"Venice",
    "sg:classifiers":[
        {
            "category":"Utilities",
            "subcategory":"Refuse",
            "type":"Services"
        }
    ],
    "sg:phone":"+1 941 485 1462",
    "sg:postcode":"34292",
    "sg:province":"FL",
    "sg:tags":[
        "garbage",
        "collection",
        "system"
    ],
    "wof:name":"Manda Construction Site Clean",
    "wof:placetype":"venue"
},
  "geometry": {"coordinates":[-82.36811400000001,27.102704],"type":"Point"}
}