{
  "type": "Feature",
  "properties": {
    "addr:full":"100 W Royal Palm Rd Boca Raton FL 33432",
    "addr:housenumber":"100",
    "addr:postcode":"33432",
    "addr:street":"W Royal Palm Rd",
    "iso:country":"US",
    "sg:address":"100 W Royal Palm Rd",
    "sg:city":"Boca Raton",
    "sg:classifiers":[
        {
            "category":"Wholesale",
            "subcategory":"Auto Parts",
            "type":"Manufacturing & Wholesale Goods"
        }
    ],
    "sg:phone":"+1 561 395 5300",
    "sg:postcode":"33432",
    "sg:province":"FL",
    "sg:tags":[
        "automobile"
    ],
    "wof:name":"Boca Raton Auto Parts",
    "wof:placetype":"venue"
},
  "geometry": {"coordinates":[-80.089764,26.349466],"type":"Point"}
}