{
  "type": "Feature",
  "properties": {
    "iso:country":"US",
    "sg:address":"850 N Wickham Rd",
    "sg:city":"Melbourne",
    "sg:classifiers":[
        {
            "category":"Restaurant",
            "type":"Food & Drink"
        }
    ],
    "sg:menulink":"http://www.allmenus.com/fl/melbourne/55613-fiesta-azteca/menu/",
    "sg:phone":"+1 321 242 5966",
    "sg:postcode":"32935",
    "sg:province":"FL",
    "sg:tags":[
        "mexican"
    ],
    "wof:name":"Fiesta Azteca",
    "wof:placetype":"venue"
},
  "geometry": {"coordinates":[-80.67224,28.120687],"type":"Point"}
}