{
  "type": "Feature",
  "properties": {
    "iso:country":"US",
    "sg:address":"710 Crenshaw Lake Rd",
    "sg:city":"Lutz",
    "sg:classifiers":[
        {
            "category":"Organizations",
            "subcategory":"Religious Organization",
            "type":"Services"
        }
    ],
    "sg:phone":"+1 813 909 4389",
    "sg:postcode":"33548",
    "sg:province":"FL",
    "wof:name":"Congregation Of Yahweh",
    "wof:placetype":"venue"
},
  "geometry": {"coordinates":[-82.474259,28.118258],"type":"Point"}
}