{
  "type": "Feature",
  "properties": {
    "iso:country":"US",
    "sg:address":"1111 96th St",
    "sg:city":"Bay Harbor Isles",
    "sg:classifiers":[
        {
            "category":"Real Estate",
            "subcategory":"Real Estate Agent",
            "type":"Services"
        }
    ],
    "sg:phone":"+1 305 861 3737",
    "sg:postcode":"33154",
    "sg:province":"FL",
    "sg:tags":[
        "management"
    ],
    "wof:name":"Pointe Management",
    "wof:placetype":"venue"
},
  "geometry": {"coordinates":[-80.133073,25.886755],"type":"Point"}
}