{
  "type": "Feature",
  "properties": {
    "addr:full":"979 N Collier Blvd Marco Island FL 34145",
    "addr:housenumber":"979;collier blvd",
    "addr:postcode":"34145",
    "addr:street":"N",
    "iso:country":"US",
    "sg:address":"979 N Collier Blvd",
    "sg:city":"Marco Island",
    "sg:classifiers":[
        {
            "category":"Banks & Credit Unions",
            "subcategory":"Investment Brokerage",
            "type":"Services"
        }
    ],
    "sg:phone":"+1 239 642 6000",
    "sg:postcode":"34145",
    "sg:province":"FL",
    "sg:tags":[
        "security"
    ],
    "wof:name":"A G Edwards 229",
    "wof:placetype":"venue"
},
  "geometry": {"coordinates":[-81.722129,25.955112],"type":"Point"}
}