{
  "type": "Feature",
  "properties": {
    "iso:country":"US",
    "sg:address":"301 W Platt St",
    "sg:city":"Tampa",
    "sg:classifiers":[
        {
            "category":"Manufacturing",
            "subcategory":"Metals",
            "type":"Manufacturing & Wholesale Goods"
        }
    ],
    "sg:phone":"+1 813 258 8334",
    "sg:postcode":"33606",
    "sg:province":"FL",
    "sg:tags":[
        "tower"
    ],
    "wof:name":"Ridan Industries",
    "wof:placetype":"venue"
},
  "geometry": {"coordinates":[-82.46392299999999,27.941677],"type":"Point"}
}