{
  "type": "Feature",
  "properties": {
    "iso:country":"US",
    "sg:address":"1100 S Federal Hwy",
    "sg:city":"Boynton Beach",
    "sg:classifiers":[
        {
            "category":"Wholesale",
            "subcategory":"Furniture",
            "type":"Manufacturing & Wholesale Goods"
        }
    ],
    "sg:phone":"+1 561 752 3455",
    "sg:postcode":"33435",
    "sg:province":"FL",
    "sg:tags":[
        "bathroom",
        "fixture",
        "accessory"
    ],
    "wof:name":"Lawrence Specialty Mgmt Corp",
    "wof:placetype":"venue"
},
  "geometry": {"coordinates":[-80.05881599999999,26.517236],"type":"Point"}
}