{
  "type": "Feature",
  "properties": {
    "iso:country":"US",
    "sg:address":"6836 14th St W",
    "sg:city":"Bradenton",
    "sg:classifiers":[
        {
            "category":"Personal",
            "subcategory":"Barber",
            "type":"Services"
        }
    ],
    "sg:phone":"+1 941 752 3964",
    "sg:postcode":"34207",
    "sg:province":"FL",
    "sg:tags":[
        "shop"
    ],
    "wof:name":"Captain Kirk's Midway Barber",
    "wof:placetype":"venue"
},
  "geometry": {"coordinates":[-82.575565,27.418533],"type":"Point"}
}