{
  "type": "Feature",
  "properties": {
    "iso:country":"US",
    "sg:address":"7936 Harding Ave",
    "sg:city":"Miami Beach",
    "sg:classifiers":[
        {
            "category":"Real Estate",
            "subcategory":"Real Estate Agent",
            "type":"Services"
        }
    ],
    "sg:phone":"+1 305 868 7722",
    "sg:postcode":"33141",
    "sg:province":"FL",
    "wof:name":"Escape Realty",
    "wof:placetype":"venue"
},
  "geometry": {"coordinates":[-80.122297,25.864726],"type":"Point"}
}