{
  "type": "Feature",
  "properties": {
    "iso:country":"US",
    "sg:address":"3990 Tampa Rd",
    "sg:city":"Oldsmar",
    "sg:classifiers":[
        {
            "category":"Travel",
            "subcategory":"Hotels & Motels",
            "type":"Entertainment"
        }
    ],
    "sg:phone":"+1 800 345 8082",
    "sg:postcode":"34677",
    "sg:province":"FL",
    "sg:website":"http://ad.doubleclick.net/clk;222816988;46581822;v?http://www.hiexpress.com/redirect?path=hd&brandCode=ex&hotelCode=oldfl&_PMID=99601036&cm_mmc=mdpr-_-yellowpages-_-ex-_-oldfl",
    "wof:name":"Holiday Inn Express Hotel & Suites Oldsmar",
    "wof:placetype":"venue"
},
  "geometry": {"coordinates":[-82.657973,28.036769],"type":"Point"}
}