{
  "type": "Feature",
  "properties": {
    "iso:country":"US",
    "sg:address":"331 Tudor Spring Ct",
    "sg:city":"Orlando",
    "sg:classifiers":[
        {
            "category":"Restaurant",
            "type":"Food & Drink"
        }
    ],
    "sg:phone":"+1 407 619 5343",
    "sg:postcode":"32828",
    "sg:province":"FL",
    "wof:name":"Hacienda Tropical Restaurant",
    "wof:placetype":"venue"
},
  "geometry": {"coordinates":[-81.139263,28.539056],"type":"Point"}
}