{
  "type": "Feature",
  "properties": {
    "iso:country":"US",
    "sg:address":"6833 State Hwy 16",
    "sg:city":"St Augustine",
    "sg:classifiers":[
        {
            "category":"Building & Trades",
            "subcategory":"Construction",
            "type":"Services"
        }
    ],
    "sg:phone":"+1 904 940 6601",
    "sg:postcode":"32092",
    "sg:province":"FL",
    "sg:tags":[
        "general",
        "contractor"
    ],
    "wof:name":"Prince Contracting Co Inc",
    "wof:placetype":"venue"
},
  "geometry": {"coordinates":[-81.530277,29.972748],"type":"Point"}
}