{
  "type": "Feature",
  "properties": {
    "iso:country":"US",
    "sg:address":"8701 Seminole Blvd",
    "sg:city":"Seminole",
    "sg:classifiers":[
        {
            "category":"Shopping",
            "subcategory":"Hobbies, Toys, & Games",
            "type":"Retail Goods"
        },
        {
            "category":"Shopping",
            "subcategory":"Crafts & Fabrics",
            "type":"Retail Goods"
        }
    ],
    "sg:phone":"+1 727 392 6829",
    "sg:postcode":"33772",
    "sg:province":"FL",
    "sg:tags":[
        "shop",
        "art",
        "supply",
        "hobby",
        "model"
    ],
    "wof:name":"Arts & Crafts Yoga",
    "wof:placetype":"venue"
},
  "geometry": {"coordinates":[-82.787041,27.85199],"type":"Point"}
}