{
  "type": "Feature",
  "properties": {
    "addr:full":"7950 Hampton Blvd Pompano Beach FL 33068",
    "addr:housenumber":"7950",
    "addr:postcode":"33068",
    "addr:street":"Hampton Blvd",
    "iso:country":"US",
    "sg:address":"7950 Hampton Blvd",
    "sg:city":"Pompano Beach",
    "sg:classifiers":[
        {
            "category":"Professional",
            "type":"Services"
        }
    ],
    "sg:phone":"+1 954 720 0106",
    "sg:postcode":"33068",
    "sg:province":"FL",
    "wof:name":"Futeboltotal Inc",
    "wof:placetype":"venue"
},
  "geometry": {"coordinates":[-80.234149,26.21086],"type":"Point"}
}