{
  "type": "Feature",
  "properties": {
    "addr:full":"1831 W Oakland Park Blvd Oakland Park FL 33311",
    "addr:housenumber":"1831",
    "addr:postcode":"33311",
    "addr:street":"W Oakland Park Blvd",
    "iso:country":"US",
    "sg:address":"1831 W Oakland Park Blvd",
    "sg:city":"Oakland Park",
    "sg:classifiers":[
        {
            "category":"Wholesale",
            "subcategory":"Motor Vehicles",
            "type":"Manufacturing & Wholesale Goods"
        }
    ],
    "sg:phone":"+1 954 735 8333",
    "sg:postcode":"33311",
    "sg:province":"FL",
    "sg:tags":[
        "automobile",
        "truck",
        "broker"
    ],
    "wof:name":"Diversifed Distributors Inc",
    "wof:placetype":"venue"
},
  "geometry": {"coordinates":[-80.16837099999999,26.165805],"type":"Point"}
}