{
  "type": "Feature",
  "properties": {
    "addr:full":"5500 Gulf Blvd Saint Petersburg FL 33706",
    "addr:housenumber":"5500",
    "addr:postcode":"33706",
    "addr:street":"Gulf Blvd",
    "iso:country":"US",
    "sg:address":"5500 Gulf Blvd",
    "sg:city":"Saint Petersburg",
    "sg:classifiers":[
        {
            "category":"Personal",
            "subcategory":"Beauty Salon",
            "type":"Services"
        }
    ],
    "sg:phone":"+1 727 360 2246",
    "sg:postcode":"33706",
    "sg:province":"FL",
    "sg:tags":[
        "shop"
    ],
    "wof:name":"Bodyworks",
    "wof:placetype":"venue"
},
  "geometry": {"coordinates":[-82.743796,27.730317],"type":"Point"}
}