{
  "type": "Feature",
  "properties": {
    "iso:country":"US",
    "sg:address":"804 NW 27th Ave",
    "sg:city":"Ocala",
    "sg:classifiers":[
        {
            "category":"Retail",
            "subcategory":"Auto Repair",
            "type":"Services"
        }
    ],
    "sg:phone":"+1 352 629 2491",
    "sg:postcode":"34475",
    "sg:province":"FL",
    "sg:tags":[
        "repairing",
        "automobile"
    ],
    "wof:name":"Jimmie Lang Auto Svc Inc",
    "wof:placetype":"venue"
},
  "geometry": {"coordinates":[-82.168705,29.194628],"type":"Point"}
}