{
  "type": "Feature",
  "properties": {
    "addr:full":"2625 SW 28th St Miami FL 33133",
    "addr:housenumber":"2625",
    "addr:postcode":"33133",
    "addr:street":"Sw 28Th St",
    "iso:country":"US",
    "sg:address":"2625 SW 28th St",
    "sg:city":"Miami",
    "sg:classifiers":[
        {
            "category":"Shopping",
            "subcategory":"Crafts & Fabrics",
            "type":"Retail Goods"
        }
    ],
    "sg:phone":"+1 305 858 1212",
    "sg:postcode":"33133",
    "sg:province":"FL",
    "sg:tags":[
        "material",
        "needlework"
    ],
    "wof:name":"Absolutely Needlepoint",
    "wof:placetype":"venue"
},
  "geometry": {"coordinates":[-80.237576,25.739335],"type":"Point"}
}