{
  "type": "Feature",
  "properties": {
    "iso:country":"US",
    "sg:address":"6201 Gunn Hwy",
    "sg:city":"Tampa",
    "sg:classifiers":[
        {
            "category":"Real Estate",
            "subcategory":"Real Estate Services",
            "type":"Services"
        }
    ],
    "sg:phone":"+1 888 854 5279",
    "sg:postcode":"33625",
    "sg:province":"FL",
    "sg:tags":[
        "apartment",
        "management",
        "rental",
        "finder"
    ],
    "sg:website":"http://www.forrent.com/apartment-community-profile/1009910.php?cmp=CAC-CSearchProfile",
    "wof:name":"Berkshires at Citrus Park",
    "wof:placetype":"venue"
},
  "geometry": {"coordinates":[-82.55175,28.06439],"type":"Point"}
}