{
  "type": "Feature",
  "properties": {
    "iso:country":"US",
    "sg:address":"28020 State Rd 33",
    "sg:city":"Leesburg",
    "sg:classifiers":[
        {
            "category":"Organizations",
            "subcategory":"Religious Organization",
            "type":"Services"
        }
    ],
    "sg:phone":"+1 352 787 7442",
    "sg:postcode":"34748",
    "sg:province":"FL",
    "sg:tags":[
        "church"
    ],
    "wof:name":"Church Of God Of Prophecy",
    "wof:placetype":"venue"
},
  "geometry": {"coordinates":[-81.88855599999999,28.754006],"type":"Point"}
}