{
  "type": "Feature",
  "properties": {
    "iso:country":"US",
    "sg:address":"3499 NW 53rd St",
    "sg:city":"Fort Lauderdale",
    "sg:classifiers":[
        {
            "category":"Utilities",
            "subcategory":"Cable",
            "type":"Services"
        }
    ],
    "sg:phone":"+1 954 739 9972",
    "sg:postcode":"33309",
    "sg:province":"FL",
    "sg:tags":[
        "television"
    ],
    "wof:name":"Bell South Entertainment",
    "wof:placetype":"venue"
},
  "geometry": {"coordinates":[-80.19535399999999,26.189673],"type":"Point"}
}