{
  "type": "Feature",
  "properties": {
    "iso:country":"US",
    "sg:address":"300 N State Rd 415",
    "sg:city":"Osteen",
    "sg:classifiers":[
        {
            "category":"Shopping",
            "subcategory":"Shoes",
            "type":"Retail Goods"
        }
    ],
    "sg:phone":"+1 407 321 1000",
    "sg:postcode":"32764",
    "sg:province":"FL",
    "sg:tags":[
        "apparel",
        "boot",
        "western",
        "accessory"
    ],
    "wof:name":"Skips Western Outfitters",
    "wof:placetype":"venue"
},
  "geometry": {"coordinates":[-81.16216300000001,28.849937],"type":"Point"}
}