{
  "type": "Feature",
  "properties": {
    "iso:country":"US",
    "sg:address":"1088 Fairfax Cir W",
    "sg:city":"Boynton Beach",
    "sg:classifiers":[
        {
            "category":"Building & Trades",
            "subcategory":"Landscaping Services",
            "type":"Services"
        }
    ],
    "sg:phone":"+1 561 432 1234",
    "sg:postcode":"33436",
    "sg:province":"FL",
    "sg:tags":[
        "landscape",
        "contractor"
    ],
    "wof:name":"Quinn Co Svc",
    "wof:placetype":"venue"
},
  "geometry": {"coordinates":[-80.103295,26.561211],"type":"Point"}
}