{
  "type": "Feature",
  "properties": {
    "iso:country":"US",
    "sg:address":"8840 Cicero Dr",
    "sg:city":"Boynton Beach",
    "sg:classifiers":[
        {
            "category":"Building & Trades",
            "subcategory":"Electrical",
            "type":"Services"
        }
    ],
    "sg:phone":"+1 561 735 0494",
    "sg:postcode":"33472",
    "sg:province":"FL",
    "sg:tags":[
        "electrical",
        "contractor"
    ],
    "wof:name":"Konyk Electric Inc",
    "wof:placetype":"venue"
},
  "geometry": {"coordinates":[-80.134495,26.54339],"type":"Point"}
}