{
  "type": "Feature",
  "properties": {
    "addr:full":"1023 Parkside Pointe Blvd Apopka FL 32712",
    "addr:housenumber":"1023",
    "addr:postcode":"32712",
    "addr:street":"Parkside Pointe Blvd",
    "iso:country":"US",
    "sg:address":"1023 Parkside Pointe Blvd",
    "sg:city":"Apopka",
    "sg:classifiers":[
        {
            "category":"Building & Trades",
            "subcategory":"Construction",
            "type":"Services"
        }
    ],
    "sg:phone":"+1 407 886 3863",
    "sg:postcode":"32712",
    "sg:province":"FL",
    "sg:tags":[
        "home",
        "builder"
    ],
    "wof:name":"Engle Homes",
    "wof:placetype":"venue"
},
  "geometry": {"coordinates":[-81.53201199999999,28.690646],"type":"Point"}
}