{
  "type": "Feature",
  "properties": {
    "addr:full":"520 Pine St Titusville FL 32796",
    "addr:housenumber":"520",
    "addr:postcode":"32796",
    "addr:street":"Pine St",
    "iso:country":"US",
    "sg:address":"520 Pine St",
    "sg:city":"Titusville",
    "sg:classifiers":[
        {
            "category":"Railroad",
            "type":"Transportation"
        }
    ],
    "sg:phone":"+1 321 264 9264",
    "sg:postcode":"32796",
    "sg:province":"FL",
    "sg:tags":[
        "operator",
        "line"
    ],
    "wof:name":"Florida East Coast RR",
    "wof:placetype":"venue"
},
  "geometry": {"coordinates":[-80.811009,28.610351],"type":"Point"}
}