{
  "type": "Feature",
  "properties": {
    "iso:country":"US",
    "sg:address":"1112 Buccaneer Blvd",
    "sg:city":"Green Cove Springs",
    "sg:classifiers":[
        {
            "category":"Building & Trades",
            "subcategory":"Construction",
            "type":"Services"
        }
    ],
    "sg:phone":"+1 904 759 3954",
    "sg:postcode":"32043",
    "sg:province":"FL",
    "sg:tags":[
        "house"
    ],
    "wof:name":"PR Remodeling",
    "wof:placetype":"venue"
},
  "geometry": {"coordinates":[-81.691806,30.000654],"type":"Point"}
}