{
  "type": "Feature",
  "properties": {
    "iso:country":"US",
    "sg:address":"2410 N Federal Hwy",
    "sg:city":"Delray Beach",
    "sg:classifiers":[
        {
            "category":"Restaurant",
            "type":"Food & Drink"
        }
    ],
    "sg:phone":"+1 561 276 1570",
    "sg:postcode":"33483",
    "sg:province":"FL",
    "wof:name":"Ellie's 50's Diner",
    "wof:placetype":"venue"
},
  "geometry": {"coordinates":[-80.064769,26.486965],"type":"Point"}
}