{
  "type": "Feature",
  "properties": {
    "addr:full":"5301 Norwood Ave Jacksonville FL 32208",
    "addr:housenumber":"5301",
    "addr:postcode":"32208",
    "addr:street":"Norwood Ave",
    "iso:country":"US",
    "sg:address":"5301 Norwood Ave",
    "sg:city":"Jacksonville",
    "sg:classifiers":[
        {
            "category":"Shopping",
            "subcategory":"Clothing, Apparel, & Fashions",
            "type":"Retail Goods"
        }
    ],
    "sg:phone":"+1 904 764 6892",
    "sg:postcode":"32208",
    "sg:province":"FL",
    "sg:tags":[
        "item",
        "boutique"
    ],
    "wof:name":"I & L Boutique",
    "wof:placetype":"venue"
},
  "geometry": {"coordinates":[-81.663881,30.371492],"type":"Point"}
}