{
  "type": "Feature",
  "properties": {
    "addr:full":"2413 Aloma Ave Winter Park FL 32792",
    "addr:housenumber":"2413",
    "addr:postcode":"32792",
    "addr:street":"Aloma Ave",
    "iso:country":"US",
    "sg:address":"2413 Aloma Ave",
    "sg:city":"Winter Park",
    "sg:classifiers":[
        {
            "category":"Real Estate",
            "subcategory":"Real Estate Agent",
            "type":"Services"
        }
    ],
    "sg:phone":"+1 407 678 5300",
    "sg:postcode":"32792",
    "sg:province":"FL",
    "wof:name":"Realty Executives",
    "wof:placetype":"venue"
},
  "geometry": {"coordinates":[-81.323663,28.600718],"type":"Point"}
}