{
  "type": "Feature",
  "properties": {
    "iso:country":"US",
    "sg:address":"11090 Delta Cir",
    "sg:city":"Boca Raton",
    "sg:classifiers":[
        {
            "category":"Building & Trades",
            "subcategory":"Construction",
            "type":"Services"
        }
    ],
    "sg:phone":"+1 561 479 2837",
    "sg:postcode":"33428",
    "sg:province":"FL",
    "sg:tags":[
        "carpentry",
        "contractor"
    ],
    "wof:name":"True Cut Construction Inc",
    "wof:placetype":"venue"
},
  "geometry": {"coordinates":[-80.220293,26.344455],"type":"Point"}
}