{
  "type": "Feature",
  "properties": {
    "iso:country":"US",
    "sg:address":"4641 Eagle Peak Dr",
    "sg:city":"Kissimmee",
    "sg:classifiers":[
        {
            "category":"Real Estate",
            "subcategory":"Real Estate Agent",
            "type":"Services"
        }
    ],
    "sg:phone":"+1 321 677 3126",
    "sg:postcode":"34746",
    "sg:province":"FL",
    "wof:name":"Edwards Real Estate",
    "wof:placetype":"venue"
},
  "geometry": {"coordinates":[-81.468819,28.284572],"type":"Point"}
}