{
  "type": "Feature",
  "properties": {
    "addr:full":"2504 Bedford Way Tallahassee FL 32308",
    "addr:housenumber":"2504",
    "addr:postcode":"32308",
    "addr:street":"Bedford Way",
    "iso:country":"US",
    "sg:address":"2504 Bedford Way",
    "sg:city":"Tallahassee",
    "sg:classifiers":[
        {
            "category":"Building & Trades",
            "subcategory":"Electrical",
            "type":"Services"
        }
    ],
    "sg:phone":"+1 850 386 1412",
    "sg:postcode":"32308",
    "sg:province":"FL",
    "sg:tags":[
        "electric",
        "contractor"
    ],
    "wof:name":"Current Electric",
    "wof:placetype":"venue"
},
  "geometry": {"coordinates":[-84.242266,30.493521],"type":"Point"}
}