{
  "type": "Feature",
  "properties": {
    "addr:full":"13650 SE 38th St Okeechobee FL 34974",
    "addr:postcode":"13650;34974",
    "addr:street":"Se 38Th St",
    "iso:country":"US",
    "sg:address":"13650 SE 38th St",
    "sg:city":"Okeechobee",
    "sg:classifiers":[
        {
            "category":"Farming",
            "subcategory":"Farm",
            "type":"Manufacturing & Wholesale Goods"
        }
    ],
    "sg:phone":"+1 863 467 4525",
    "sg:postcode":"34974",
    "sg:province":"FL",
    "sg:tags":[
        "crop",
        "animal",
        "general"
    ],
    "wof:name":"Benitez Ornan & Reiners",
    "wof:placetype":"venue"
},
  "geometry": {"coordinates":[-80.680216,27.209798],"type":"Point"}
}