{
  "type": "Feature",
  "properties": {
    "addr:full":"5393 W 20th Ave Hialeah FL 33012",
    "addr:housenumber":"5393",
    "addr:postcode":"33012",
    "addr:street":"W 20Th Ave",
    "iso:country":"US",
    "sg:address":"5393 W 20th Ave",
    "sg:city":"Hialeah",
    "sg:classifiers":[
        {
            "category":"Travel",
            "subcategory":"Travel Agent",
            "type":"Entertainment"
        }
    ],
    "sg:phone":"+1 305 820 0565",
    "sg:postcode":"33012",
    "sg:province":"FL",
    "sg:tags":[
        "agency",
        "bureau"
    ],
    "wof:name":"Royal Travel Agency",
    "wof:placetype":"venue"
},
  "geometry": {"coordinates":[-80.322619,25.871662],"type":"Point"}
}