{
  "type": "Feature",
  "properties": {
    "iso:country":"US",
    "sg:address":"710 N Miramar Ave A1a",
    "sg:city":"Indialantic",
    "sg:classifiers":[
        {
            "category":"Personal",
            "subcategory":"Beauty Salon",
            "type":"Services"
        }
    ],
    "sg:phone":"+1 321 722 1663",
    "sg:postcode":"32903",
    "sg:province":"FL",
    "sg:tags":[
        "hair",
        "stylist"
    ],
    "wof:name":"Hairteck",
    "wof:placetype":"venue"
},
  "geometry": {"coordinates":[-80.568237,28.095766],"type":"Point"}
}