{
  "type": "Feature",
  "properties": {
    "addr:full":"13533 Granville Ave Clermont FL 34711",
    "addr:housenumber":"13533",
    "addr:postcode":"34711",
    "addr:street":"Granville Ave",
    "iso:country":"US",
    "sg:address":"13533 Granville Ave",
    "sg:city":"Clermont",
    "sg:classifiers":[
        {
            "category":"Shopping",
            "subcategory":"Bicycles & Sporting Goods",
            "type":"Retail Goods"
        }
    ],
    "sg:phone":"+1 407 370 3388",
    "sg:postcode":"34711",
    "sg:province":"FL",
    "wof:name":"Americas Clearance Outlet",
    "wof:placetype":"venue"
},
  "geometry": {"coordinates":[-81.68915800000001,28.544184],"type":"Point"}
}