{
  "type": "Feature",
  "properties": {
    "iso:country":"US",
    "sg:address":"2370 SW 67th Ave",
    "sg:city":"Miami",
    "sg:classifiers":[
        {
            "category":"Manufacturing",
            "subcategory":"Apparel",
            "type":"Manufacturing & Wholesale Goods"
        }
    ],
    "sg:phone":"+1 305 262 3955",
    "sg:postcode":"33155",
    "sg:province":"FL",
    "sg:tags":[
        "manufacture",
        "automobile",
        "cover",
        "seat"
    ],
    "wof:name":"Universal Seat Covers",
    "wof:placetype":"venue"
},
  "geometry": {"coordinates":[-80.303624,25.748609],"type":"Point"}
}