{
  "type": "Feature",
  "properties": {
    "iso:country":"US",
    "sg:address":"2020 Queen St",
    "sg:city":"Fort Myers",
    "sg:classifiers":[
        {
            "category":"Professional",
            "subcategory":"Business Services",
            "type":"Services"
        }
    ],
    "sg:phone":"+1 239 656 3072",
    "sg:postcode":"33917",
    "sg:province":"FL",
    "sg:tags":[
        "auction"
    ],
    "wof:name":"Auction Man Inc",
    "wof:placetype":"venue"
},
  "geometry": {"coordinates":[-81.883228,26.690734],"type":"Point"}
}