{
  "type": "Feature",
  "properties": {
    "addr:full":"1067 Ranier Dr Altamonte Springs FL 32714",
    "addr:housenumber":"1067",
    "addr:postcode":"32714",
    "addr:street":"Ranier Dr",
    "iso:country":"US",
    "sg:address":"1067 Ranier Dr",
    "sg:city":"Altamonte Springs",
    "sg:classifiers":[
        {
            "category":"Wholesale",
            "subcategory":"Construction Materials",
            "type":"Manufacturing & Wholesale Goods"
        }
    ],
    "sg:phone":"+1 407 331 4680",
    "sg:postcode":"32714",
    "sg:province":"FL",
    "sg:tags":[
        "price",
        "made",
        "accent",
        "mural",
        "custom"
    ],
    "wof:name":"Gena Designs By John Mock",
    "wof:placetype":"venue"
},
  "geometry": {"coordinates":[-81.426316,28.656698],"type":"Point"}
}