{
  "type": "Feature",
  "properties": {
    "iso:country":"US",
    "sg:address":"5249 NW 7th St",
    "sg:city":"Miami",
    "sg:classifiers":[
        {
            "category":"Professional",
            "type":"Services"
        }
    ],
    "sg:phone":"+1 305 444 2765",
    "sg:postcode":"33126",
    "sg:province":"FL",
    "wof:name":"Mari Zoe Blanc Inc",
    "wof:placetype":"venue"
},
  "geometry": {"coordinates":[-80.281469,25.778357],"type":"Point"}
}