{
  "type": "Feature",
  "properties": {
    "addr:full":"5524 NW 41st Ter Pompano Beach FL 33073",
    "addr:housenumber":"5524",
    "addr:postcode":"33073",
    "addr:street":"Nw 41St Ter",
    "iso:country":"US",
    "sg:address":"5524 NW 41st Ter",
    "sg:city":"Pompano Beach",
    "sg:classifiers":[
        {
            "category":"Building & Trades",
            "subcategory":"Construction",
            "type":"Services"
        }
    ],
    "sg:phone":"+1 954 520 9383",
    "sg:postcode":"33073",
    "sg:province":"FL",
    "sg:tags":[
        "hanging",
        "contractor"
    ],
    "wof:name":"Proud Painting Inc",
    "wof:placetype":"venue"
},
  "geometry": {"coordinates":[-80.18001599999999,26.299778],"type":"Point"}
}