{
  "type": "Feature",
  "properties": {
    "iso:country":"US",
    "sg:address":"3912 US Hwy 301",
    "sg:city":"Ellenton",
    "sg:classifiers":[
        {
            "category":"Real Estate",
            "subcategory":"Real Estate Agent",
            "type":"Services"
        }
    ],
    "sg:phone":"+1 941 729 2381",
    "sg:postcode":"34222",
    "sg:province":"FL",
    "wof:name":"A Paradise Realty",
    "wof:placetype":"venue"
},
  "geometry": {"coordinates":[-82.522918,27.52196],"type":"Point"}
}