{
  "type": "Feature",
  "properties": {
    "iso:country":"US",
    "sg:address":"1603 Homestead St",
    "sg:city":"Sebring",
    "sg:classifiers":[
        {
            "category":"Real Estate",
            "subcategory":"Real Estate Operator",
            "type":"Services"
        }
    ],
    "sg:phone":"+1 863 385 5919",
    "sg:postcode":"33870",
    "sg:province":"FL",
    "sg:tags":[
        "building",
        "apartment"
    ],
    "wof:name":"Kendale Apts",
    "wof:placetype":"venue"
},
  "geometry": {"coordinates":[-81.486735,27.511678],"type":"Point"}
}