{
  "type": "Feature",
  "properties": {
    "addr:full":"2270 Anchorage Ln Naples FL 34104",
    "addr:housenumber":"2270",
    "addr:postcode":"34104",
    "addr:street":"Anchorage Ln",
    "iso:country":"US",
    "sg:address":"2270 Anchorage Ln",
    "sg:city":"Naples",
    "sg:classifiers":[
        {
            "category":"Professional",
            "type":"Services"
        }
    ],
    "sg:phone":"+1 239 430 0613",
    "sg:postcode":"34104",
    "sg:province":"FL",
    "wof:name":"Bruce E McNeil PA",
    "wof:placetype":"venue"
},
  "geometry": {"coordinates":[-81.77834199999999,26.145511],"type":"Point"}
}