{
  "type": "Feature",
  "properties": {
    "iso:country":"US",
    "sg:address":"9044 NW 28th Dr",
    "sg:city":"Coral Springs",
    "sg:classifiers":[
        {
            "category":"Professional",
            "type":"Services"
        }
    ],
    "sg:phone":"+1 954 227 9881",
    "sg:postcode":"33065",
    "sg:province":"FL",
    "sg:tags":[
        "art",
        "restoring"
    ],
    "wof:name":"Alrternative Art",
    "wof:placetype":"venue"
},
  "geometry": {"coordinates":[-80.24363,26.267001],"type":"Point"}
}