{
  "type": "Feature",
  "properties": {
    "addr:full":"4050 Central Ave St Petersburg FL 33711",
    "addr:housenumber":"4050",
    "addr:postcode":"33711",
    "addr:street":"Central Ave",
    "iso:country":"US",
    "sg:address":"4050 Central Ave",
    "sg:city":"St Petersburg",
    "sg:classifiers":[
        {
            "category":"Health Services",
            "subcategory":"Hospital",
            "type":"Services"
        },
        {
            "category":"Professional",
            "subcategory":"Management & Consulting",
            "type":"Services"
        }
    ],
    "sg:phone":"+1 727 327 4877",
    "sg:postcode":"33711",
    "sg:province":"FL",
    "sg:tags":[
        "organization",
        "membership",
        "mental"
    ],
    "wof:name":"Assertive Resource Management",
    "wof:placetype":"venue"
},
  "geometry": {"coordinates":[-82.68823999999999,27.770864],"type":"Point"}
}