{
  "type": "Feature",
  "properties": {
    "iso:country":"US",
    "sg:address":"2764 Cabaret St",
    "sg:city":"Port Charlotte",
    "sg:classifiers":[
        {
            "category":"Real Estate",
            "subcategory":"Real Estate Agent",
            "type":"Services"
        }
    ],
    "sg:phone":"+1 941 764 7640",
    "sg:postcode":"33948",
    "sg:province":"FL",
    "wof:name":"Horn Realty Inc",
    "wof:placetype":"venue"
},
  "geometry": {"coordinates":[-82.156222,26.989354],"type":"Point"}
}