{
  "type": "Feature",
  "properties": {
    "addr:full":"6330 Wisteria Ln Apollo Beach FL 33572",
    "addr:housenumber":"6330",
    "addr:postcode":"33572",
    "addr:street":"Wisteria Ln",
    "iso:country":"US",
    "sg:address":"6330 Wisteria Ln",
    "sg:city":"Apollo Beach",
    "sg:classifiers":[
        {
            "category":"Wholesale",
            "subcategory":"Sporting Goods",
            "type":"Manufacturing & Wholesale Goods"
        }
    ],
    "sg:phone":"+1 813 645 9226",
    "sg:postcode":"33572",
    "sg:province":"FL",
    "sg:tags":[
        "distributor"
    ],
    "wof:name":"Creime Enterprises",
    "wof:placetype":"venue"
},
  "geometry": {"coordinates":[-82.421153,27.776212],"type":"Point"}
}