{
  "type": "Feature",
  "properties": {
    "iso:country":"US",
    "sg:address":"742 NW 9th Ave",
    "sg:city":"Fort Lauderdale",
    "sg:classifiers":[
        {
            "category":"Retail",
            "subcategory":"Auto Repair",
            "type":"Services"
        },
        {
            "category":"Retail",
            "subcategory":"Auto Rental",
            "type":"Services"
        }
    ],
    "sg:phone":"+1 954 525 1318",
    "sg:postcode":"33311",
    "sg:province":"FL",
    "sg:tags":[
        "heavy",
        "transmission"
    ],
    "wof:name":"Star Transmissions",
    "wof:placetype":"venue"
},
  "geometry": {"coordinates":[-80.15361,26.132245],"type":"Point"}
}