{
  "type": "Feature",
  "properties": {
    "addr:full":"2071 Pine Ridge Rd Naples FL 34109",
    "addr:housenumber":"2071",
    "addr:postcode":"34109",
    "addr:street":"Pine Ridge Rd",
    "iso:country":"US",
    "sg:address":"2071 Pine Ridge Rd",
    "sg:city":"Naples",
    "sg:classifiers":[
        {
            "category":"Personal",
            "subcategory":"Beauty Salon",
            "type":"Services"
        }
    ],
    "sg:phone":"+1 239 592 6559",
    "sg:postcode":"34109",
    "sg:province":"FL",
    "sg:tags":[
        "manicuring"
    ],
    "wof:name":"Nail Art",
    "wof:placetype":"venue"
},
  "geometry": {"coordinates":[-81.77628900000001,26.211611],"type":"Point"}
}