{
  "type": "Feature",
  "properties": {
    "addr:full":"6617 Datura Dr Orlando FL 32809",
    "addr:housenumber":"6617",
    "addr:postcode":"32809",
    "addr:street":"Datura Dr",
    "iso:country":"US",
    "sg:address":"6617 Datura Dr",
    "sg:city":"Orlando",
    "sg:classifiers":[
        {
            "category":"Wholesale",
            "subcategory":"Metals & Minerals",
            "type":"Manufacturing & Wholesale Goods"
        }
    ],
    "sg:phone":"+1 407 851 4027",
    "sg:postcode":"32809",
    "sg:province":"FL",
    "sg:tags":[
        "aluminum"
    ],
    "wof:name":"Mike A Le Bruno Installations",
    "wof:placetype":"venue"
},
  "geometry": {"coordinates":[-81.365239,28.46011],"type":"Point"}
}