{
  "type": "Feature",
  "properties": {
    "addr:full":"4043 Cypress Lndg E Winter Haven FL 33884",
    "addr:housenumber":"4043",
    "addr:postcode":"33884",
    "addr:street":"Cypress Lndg E",
    "iso:country":"US",
    "sg:address":"4043 Cypress Lndg E",
    "sg:city":"Winter Haven",
    "sg:classifiers":[
        {
            "category":"Professional",
            "subcategory":"Business Services",
            "type":"Services"
        }
    ],
    "sg:phone":"+1 863 324 3531",
    "sg:postcode":"33884",
    "sg:province":"FL",
    "sg:tags":[
        "interior",
        "consultant",
        "design",
        "decorator"
    ],
    "wof:name":"Artistic Decor",
    "wof:placetype":"venue"
},
  "geometry": {"coordinates":[-81.673773,27.991356],"type":"Point"}
}