{
  "type": "Feature",
  "properties": {
    "iso:country":"US",
    "sg:address":"13193 88th Ave",
    "sg:city":"Seminole",
    "sg:classifiers":[
        {
            "category":"Real Estate",
            "subcategory":"Real Estate Agent",
            "type":"Services"
        }
    ],
    "sg:phone":"+1 727 319 0606",
    "sg:postcode":"33776",
    "sg:province":"FL",
    "wof:name":"Makely Realty",
    "wof:placetype":"venue"
},
  "geometry": {"coordinates":[-82.822436,27.853615],"type":"Point"}
}