{
  "type": "Feature",
  "properties": {
    "addr:full":"626 Barbuda Way Altamonte Springs FL 32714",
    "addr:housenumber":"626",
    "addr:postcode":"32714",
    "addr:street":"Barbuda Way",
    "iso:country":"US",
    "sg:address":"626 Barbuda Way",
    "sg:city":"Altamonte Springs",
    "sg:classifiers":[
        {
            "category":"Building & Trades",
            "subcategory":"Construction",
            "type":"Services"
        }
    ],
    "sg:phone":"+1 407 445 1630",
    "sg:postcode":"32714",
    "sg:province":"FL",
    "sg:tags":[
        "hanging",
        "nonresidential",
        "contractor"
    ],
    "wof:name":"Copan Painters",
    "wof:placetype":"venue"
},
  "geometry": {"coordinates":[-81.41361499999999,28.649921],"type":"Point"}
}