{
  "type": "Feature",
  "properties": {
    "iso:country":"US",
    "sg:address":"1366 SW 13th Pl",
    "sg:city":"Boca Raton",
    "sg:classifiers":[
        {
            "category":"Building & Trades",
            "subcategory":"Landscaping Services",
            "type":"Services"
        }
    ],
    "sg:phone":"+1 561 394 9323",
    "sg:postcode":"33486",
    "sg:province":"FL",
    "wof:name":"Donald O Magnuson Lawn Maint",
    "wof:placetype":"venue"
},
  "geometry": {"coordinates":[-80.11236100000001,26.336943],"type":"Point"}
}