{
  "type": "Feature",
  "properties": {
    "iso:country":"US",
    "sg:address":"1500 San Remo Ave Ste 110",
    "sg:city":"Coral Gables",
    "sg:classifiers":[
        {
            "category":"Real Estate",
            "subcategory":"Real Estate Services",
            "type":"Services"
        }
    ],
    "sg:phone":"+1 305 667 4815",
    "sg:postcode":"33146",
    "sg:province":"FL",
    "wof:name":"Bitter Barbara Rl Est",
    "wof:placetype":"venue"
},
  "geometry": {"coordinates":[-80.282303,25.705999],"type":"Point"}
}