{
  "type": "Feature",
  "properties": {
    "iso:country":"US",
    "sg:address":"6551 Stonehurst Cir",
    "sg:city":"Lake Worth",
    "sg:classifiers":[
        {
            "category":"Manufacturing",
            "subcategory":"Apparel",
            "type":"Manufacturing & Wholesale Goods"
        }
    ],
    "sg:phone":"+1 561 649 1667",
    "sg:postcode":"33467",
    "sg:province":"FL",
    "sg:tags":[
        "household",
        "furnishing",
        "mfg"
    ],
    "wof:name":"Pillow Company",
    "wof:placetype":"venue"
},
  "geometry": {"coordinates":[-80.169252,26.581307],"type":"Point"}
}