{
  "type": "Feature",
  "properties": {
    "iso:country":"US",
    "sg:address":"9401 E Colonial Dr",
    "sg:city":"Orlando",
    "sg:classifiers":[
        {
            "category":"Manufacturing",
            "subcategory":"Food",
            "type":"Manufacturing & Wholesale Goods"
        }
    ],
    "sg:phone":"+1 407 896 8699",
    "sg:postcode":"32817",
    "sg:province":"FL",
    "sg:tags":[
        "product",
        "mfg"
    ],
    "wof:name":"Auntie Annes",
    "wof:placetype":"venue"
},
  "geometry": {"coordinates":[-81.25357700000001,28.56845],"type":"Point"}
}