{
  "type": "Feature",
  "properties": {
    "iso:country":"US",
    "sg:address":"1535 Killearn Center Blvd",
    "sg:city":"Tallahassee",
    "sg:classifiers":[
        {
            "category":"Personal",
            "subcategory":"Beauty Salon",
            "type":"Services"
        }
    ],
    "sg:phone":"+1 850 877 7225",
    "sg:postcode":"32309",
    "sg:province":"FL",
    "wof:name":"Grimes Patricia",
    "wof:placetype":"venue"
},
  "geometry": {"coordinates":[-84.246146,30.505989],"type":"Point"}
}