{
  "type": "Feature",
  "properties": {
    "addr:full":"2366 Nash St Clearwater FL 33765",
    "addr:housenumber":"2366",
    "addr:postcode":"33765",
    "addr:street":"Nash St",
    "iso:country":"US",
    "sg:address":"2366 Nash St",
    "sg:city":"Clearwater",
    "sg:classifiers":[
        {
            "category":"Professional",
            "subcategory":"Lawyer & Legal Services",
            "type":"Services"
        }
    ],
    "sg:phone":"+1 727 724 3736",
    "sg:postcode":"33765",
    "sg:province":"FL",
    "sg:tags":[
        "attorney"
    ],
    "wof:name":"Debt Relief Dept LLC",
    "wof:placetype":"venue"
},
  "geometry": {"coordinates":[-82.741874,27.963935],"type":"Point"}
}