{
  "type": "Feature",
  "properties": {
    "iso:country":"US",
    "sg:address":"20575 Old Cutler Rd",
    "sg:city":"Miami",
    "sg:classifiers":[
        {
            "category":"Autos & Motor Vehicles",
            "subcategory":"Auto Supplies",
            "type":"Retail Goods"
        }
    ],
    "sg:phone":"+1 305 278 0104",
    "sg:postcode":"33189",
    "sg:province":"FL",
    "sg:tags":[
        "parts"
    ],
    "wof:name":"Discount Auto Parts Inc",
    "wof:placetype":"venue"
},
  "geometry": {"coordinates":[-80.33622699999999,25.578564],"type":"Point"}
}