{
  "type": "Feature",
  "properties": {
    "iso:country":"US",
    "sg:address":"223 Columbia Dr",
    "sg:city":"Cape Canaveral",
    "sg:classifiers":[
        {
            "category":"Professional",
            "type":"Services"
        }
    ],
    "sg:phone":"+1 321 868 6837",
    "sg:postcode":"32920",
    "sg:province":"FL",
    "wof:name":"Zomano Inc",
    "wof:placetype":"venue"
},
  "geometry": {"coordinates":[-80.611267,28.390897],"type":"Point"}
}