{
  "type": "Feature",
  "properties": {
    "iso:country":"US",
    "sg:address":"2207 State Hwy 77",
    "sg:city":"Lynn Haven",
    "sg:classifiers":[
        {
            "category":"Shopping",
            "subcategory":"Discount & Variety Stores",
            "type":"Retail Goods"
        }
    ],
    "sg:phone":"+1 850 265 1310",
    "sg:postcode":"32444",
    "sg:province":"FL",
    "sg:website":"www.dollargeneral.com",
    "wof:name":"Dollar General",
    "wof:placetype":"venue"
},
  "geometry": {"coordinates":[-85.64927299999999,30.222241],"type":"Point"}
}