{
  "type": "Feature",
  "properties": {
    "iso:country":"US",
    "sg:address":"3349 E Gold Tee Dr",
    "sg:city":"Avon Park",
    "sg:classifiers":[
        {
            "category":"Building & Trades",
            "subcategory":"Construction",
            "type":"Services"
        }
    ],
    "sg:phone":"+1 863 382 2096",
    "sg:postcode":"33825",
    "sg:province":"FL",
    "sg:tags":[
        "house"
    ],
    "wof:name":"Thomas E James General Contr",
    "wof:placetype":"venue"
},
  "geometry": {"coordinates":[-81.428279,27.537585],"type":"Point"}
}