{
  "type": "Feature",
  "properties": {
    "iso:country":"US",
    "sg:address":"4390 W Colonial Dr",
    "sg:city":"Orlando",
    "sg:classifiers":[
        {
            "category":"Autos & Motor Vehicles",
            "subcategory":"Automobile Sales",
            "type":"Retail Goods"
        }
    ],
    "sg:phone":"+1 407 521 9220",
    "sg:postcode":"32808",
    "sg:province":"FL",
    "sg:tags":[
        "used"
    ],
    "wof:name":"United Finance International",
    "wof:placetype":"venue"
},
  "geometry": {"coordinates":[-81.43359599999999,28.552618],"type":"Point"}
}