{
  "type": "Feature",
  "properties": {
    "iso:country":"US",
    "sg:address":"1510 Bottlebrush Dr",
    "sg:city":"Palm Bay",
    "sg:classifiers":[
        {
            "category":"Organizations",
            "subcategory":"Religious Organization",
            "type":"Services"
        }
    ],
    "sg:phone":"+1 321 951 3205",
    "sg:postcode":"32905",
    "sg:province":"FL",
    "sg:tags":[
        "church"
    ],
    "wof:name":"House Of Prayer",
    "wof:placetype":"venue"
},
  "geometry": {"coordinates":[-80.60930399999999,28.035054],"type":"Point"}
}