{
  "type": "Feature",
  "properties": {
    "iso:country":"US",
    "sg:address":"7133 US Hwy 1",
    "sg:city":"Port St Lucie",
    "sg:classifiers":[
        {
            "category":"Bars & Pubs",
            "type":"Food & Drink"
        }
    ],
    "sg:phone":"+1 772 879 9566",
    "sg:postcode":"34982",
    "sg:province":"FL",
    "wof:name":"Club Byrd Cage",
    "wof:placetype":"venue"
},
  "geometry": {"coordinates":[-80.324369,27.332777],"type":"Point"}
}