{
  "type": "Feature",
  "properties": {
    "addr:full":"14900 NW 24th Ct Opa Locka FL 33054",
    "addr:housenumber":"14900",
    "addr:postcode":"33054",
    "addr:street":"Nw 24Th Ct",
    "iso:country":"US",
    "sg:address":"14900 NW 24th Ct",
    "sg:city":"Opa Locka",
    "sg:classifiers":[
        {
            "category":"Manufacturing",
            "subcategory":"Rubber & Plastics",
            "type":"Manufacturing & Wholesale Goods"
        }
    ],
    "sg:phone":"+1 305 688 2577",
    "sg:postcode":"33054",
    "sg:province":"FL",
    "sg:tags":[
        "product"
    ],
    "wof:name":"Freistat Case Co",
    "wof:placetype":"venue"
},
  "geometry": {"coordinates":[-80.241179,25.910796],"type":"Point"}
}