{
  "type": "Feature",
  "properties": {
    "iso:country":"US",
    "sg:address":"1154 Railroad Ave",
    "sg:city":"De Funiak Springs",
    "sg:classifiers":[
        {
            "category":"Building & Trades",
            "subcategory":"Construction",
            "type":"Services"
        }
    ],
    "sg:phone":"+1 850 859 2163",
    "sg:postcode":"32433",
    "sg:province":"FL",
    "sg:tags":[
        "carpentry",
        "contractor"
    ],
    "wof:name":"Eddie Murphy",
    "wof:placetype":"venue"
},
  "geometry": {"coordinates":[-86.112537,30.863251],"type":"Point"}
}