{
  "type": "Feature",
  "properties": {
    "iso:country":"US",
    "sg:address":"17455 NE 38th Pl",
    "sg:city":"Silver Springs",
    "sg:classifiers":[
        {
            "category":"Building & Trades",
            "subcategory":"Landscaping Services",
            "type":"Services"
        }
    ],
    "sg:phone":"+1 352 216 5206",
    "sg:postcode":"34488",
    "sg:province":"FL",
    "sg:tags":[
        "tree"
    ],
    "wof:name":"Steven Little Tree Surgeon",
    "wof:placetype":"venue"
},
  "geometry": {"coordinates":[-81.870999,29.226582],"type":"Point"}
}