{
  "type": "Feature",
  "properties": {
    "iso:country":"US",
    "sg:address":"7330 Gladiolus Dr",
    "sg:city":"Fort Myers",
    "sg:classifiers":[
        {
            "category":"Park",
            "type":"Public Place"
        }
    ],
    "sg:phone":"+1 239 432 2000",
    "sg:postcode":"33908",
    "sg:province":"FL",
    "wof:name":"Lee County Government",
    "wof:placetype":"venue"
},
  "geometry": {"coordinates":[-81.876591,26.52563],"type":"Point"}
}