{
  "type": "Feature",
  "properties": {
    "iso:country":"US",
    "sg:address":"320 Forest Park Cir",
    "sg:city":"Longwood",
    "sg:classifiers":[
        {
            "category":"Utilities",
            "subcategory":"Electric",
            "type":"Services"
        }
    ],
    "sg:phone":"+1 407 765 0581",
    "sg:postcode":"32779",
    "sg:province":"FL",
    "sg:tags":[
        "equipment",
        "supplies-repair",
        "electronic",
        "equipment-repair"
    ],
    "wof:name":"Craig's Appliance Svc",
    "wof:placetype":"venue"
},
  "geometry": {"coordinates":[-81.444801,28.68153],"type":"Point"}
}