{
  "type": "Feature",
  "properties": {
    "addr:full":"3700 S Dixie Hwy Miami FL 33133",
    "addr:housenumber":"3700",
    "addr:postcode":"33133",
    "addr:street":"S Dixie Hwy",
    "iso:country":"US",
    "sg:address":"3700 S Dixie Hwy",
    "sg:city":"Miami",
    "sg:classifiers":[
        {
            "category":"Building & Trades",
            "subcategory":"Locksmith",
            "type":"Services"
        }
    ],
    "sg:phone":"+1 305 908 8069",
    "sg:postcode":"33133",
    "sg:province":"FL",
    "sg:tags":[
        "key"
    ],
    "wof:name":"1 Chance 2 Fix It Locksmith",
    "wof:placetype":"venue"
},
  "geometry": {"coordinates":[-80.25376300000001,25.732512],"type":"Point"}
}