{
  "type": "Feature",
  "properties": {
    "addr:full":"2769 NW 79th Ave Doral FL 33122",
    "addr:housenumber":"2769",
    "addr:postcode":"33122",
    "addr:street":"Nw 79Th Ave",
    "iso:country":"US",
    "sg:address":"2769 NW 79th Ave",
    "sg:city":"Doral",
    "sg:classifiers":[
        {
            "category":"Wholesale",
            "subcategory":"Construction Materials",
            "type":"Manufacturing & Wholesale Goods"
        },
        {
            "category":"Building & Trades",
            "subcategory":"Construction",
            "type":"Services"
        }
    ],
    "sg:phone":"+1 305 593 8050",
    "sg:postcode":"33122",
    "sg:province":"FL",
    "sg:tags":[
        "tile",
        "marble",
        "dealer"
    ],
    "wof:name":"Lefont Tile & Marble Corp",
    "wof:placetype":"venue"
},
  "geometry": {"coordinates":[-80.324938,25.798513],"type":"Point"}
}