{
  "type": "Feature",
  "properties": {
    "iso:country":"US",
    "sg:address":"1400 Colonial Blvd",
    "sg:city":"Fort Myers",
    "sg:classifiers":[
        {
            "category":"Banks & Credit Unions",
            "subcategory":"Investment Brokerage",
            "type":"Services"
        }
    ],
    "sg:phone":"+1 239 790 5590",
    "sg:postcode":"33907",
    "sg:province":"FL",
    "sg:tags":[
        "security"
    ],
    "wof:name":"Trader Stock",
    "wof:placetype":"venue"
},
  "geometry": {"coordinates":[-81.887985,26.59651],"type":"Point"}
}