{
  "type": "Feature",
  "properties": {
    "iso:country":"US",
    "sg:address":"7375 S Orange Ave",
    "sg:city":"Orlando",
    "sg:classifiers":[
        {
            "category":"Autos & Motor Vehicles",
            "subcategory":"Automobile Sales",
            "type":"Retail Goods"
        },
        {
            "category":"Autos & Motor Vehicles",
            "subcategory":"Auto Supplies",
            "type":"Retail Goods"
        },
        {
            "category":"Retail",
            "subcategory":"Auto Repair",
            "type":"Services"
        }
    ],
    "sg:phone":"+1 407 825 9898",
    "sg:postcode":"32809",
    "sg:province":"FL",
    "sg:tags":[
        "oil",
        "tire",
        "transmission",
        "equipment",
        "lube",
        "brake",
        "air conditioning"
    ],
    "sg:website":"http://www.rikersautofl.com",
    "wof:name":"Riker's Automotive",
    "wof:placetype":"venue"
},
  "geometry": {"coordinates":[-81.36590200000001,28.459202],"type":"Point"}
}