{
  "type": "Feature",
  "properties": {
    "iso:country":"US",
    "sg:address":"1865 Harlock Rd",
    "sg:city":"Melbourne",
    "sg:classifiers":[
        {
            "category":"Communications",
            "subcategory":"Radio Station",
            "type":"Services"
        }
    ],
    "sg:phone":"+1 321 757 3850",
    "sg:postcode":"32934",
    "sg:province":"FL",
    "sg:tags":[
        "company",
        "broadcasting"
    ],
    "wof:name":"Tiger Eye Broadcasting",
    "wof:placetype":"venue"
},
  "geometry": {"coordinates":[-80.704463,28.137125],"type":"Point"}
}