{
  "type": "Feature",
  "properties": {
    "iso:country":"US",
    "sg:address":"600 Jennings Ave",
    "sg:city":"Eustis",
    "sg:classifiers":[
        {
            "category":"Banks & Credit Unions",
            "subcategory":"Bank",
            "type":"Services"
        }
    ],
    "sg:phone":"+1 352 483 9390",
    "sg:postcode":"32744",
    "sg:province":"FL",
    "sg:tags":[
        "loan"
    ],
    "wof:name":"Competitive Lending Resource",
    "wof:placetype":"venue"
},
  "geometry": {"coordinates":[-81.24439599999999,28.989064],"type":"Point"}
}