{
  "type": "Feature",
  "properties": {
    "addr:full":"400 E Howry Ave Deland FL 32724",
    "addr:housenumber":"400",
    "addr:postcode":"32724",
    "addr:street":"E Howry Ave",
    "iso:country":"US",
    "sg:address":"400 E Howry Ave",
    "sg:city":"Deland",
    "sg:classifiers":[
        {
            "category":"Banks & Credit Unions",
            "subcategory":"Bank",
            "type":"Services"
        }
    ],
    "sg:phone":"+1 386 943 9093",
    "sg:postcode":"32724",
    "sg:province":"FL",
    "sg:website":"www.riversidenb.com",
    "wof:name":"Riverside Bank",
    "wof:placetype":"venue"
},
  "geometry": {"coordinates":[-81.296212,29.026153],"type":"Point"}
}