{
  "type": "Feature",
  "properties": {
    "addr:full":"1 Westmount Ln Palm Coast FL 32164",
    "addr:housenumber":"1",
    "addr:postcode":"32164",
    "addr:street":"Westmount Ln",
    "iso:country":"US",
    "sg:address":"1 Westmount Ln",
    "sg:city":"Palm Coast",
    "sg:classifiers":[
        {
            "category":"Real Estate",
            "subcategory":"Real Estate Agent",
            "type":"Services"
        }
    ],
    "sg:phone":"+1 386 447 3004",
    "sg:postcode":"32164",
    "sg:province":"FL",
    "wof:name":"Carlos Pinto PA",
    "wof:placetype":"venue"
},
  "geometry": {"coordinates":[-81.24841000000001,29.531433],"type":"Point"}
}