{
  "type": "Feature",
  "properties": {
    "addr:full":"3011 SW Martin Downs Blvd Palm City FL 34990",
    "addr:housenumber":"3011",
    "addr:postcode":"34990",
    "addr:street":"Sw Martin Downs Blvd",
    "iso:country":"US",
    "sg:address":"3011 SW Martin Downs Blvd",
    "sg:city":"Palm City",
    "sg:classifiers":[
        {
            "category":"Sports & Exercise",
            "subcategory":"Gym",
            "type":"Entertainment"
        }
    ],
    "sg:phone":"+1 772 463 1437",
    "sg:postcode":"34990",
    "sg:province":"FL",
    "sg:tags":[
        "fitness",
        "physical",
        "facility"
    ],
    "wof:name":"Curves For Women",
    "wof:placetype":"venue"
},
  "geometry": {"coordinates":[-80.298221,27.170552],"type":"Point"}
}