{
  "type": "Feature",
  "properties": {
    "addr:full":"8281 SW 40th St Miami FL 33155",
    "addr:housenumber":"8281",
    "addr:postcode":"33155",
    "addr:street":"Sw 40Th St",
    "iso:country":"US",
    "sg:address":"8281 SW 40th St",
    "sg:city":"Miami",
    "sg:classifiers":[
        {
            "category":"Personal",
            "subcategory":"Beauty Salon",
            "type":"Services"
        }
    ],
    "sg:phone":"+1 305 207 0500",
    "sg:postcode":"33155",
    "sg:province":"FL",
    "wof:name":"Hector Espinel",
    "wof:placetype":"venue"
},
  "geometry": {"coordinates":[-80.328017,25.733356],"type":"Point"}
}