{
  "type": "Feature",
  "properties": {
    "iso:country":"US",
    "sg:address":"1458 10th Ct",
    "sg:city":"West Palm Beach",
    "sg:classifiers":[
        {
            "category":"Recreation",
            "subcategory":"Marina",
            "type":"Entertainment"
        }
    ],
    "sg:phone":"+1 561 863 1035",
    "sg:postcode":"33403",
    "sg:province":"FL",
    "sg:tags":[
        "repairing",
        "boat"
    ],
    "wof:name":"Ocean Yacht Svc Inc",
    "wof:placetype":"venue"
},
  "geometry": {"coordinates":[-80.07596100000001,26.80608],"type":"Point"}
}