{
  "type": "Feature",
  "properties": {
    "iso:country":"US",
    "sg:address":"409 N Neptune Dr",
    "sg:city":"Satellite Beach",
    "sg:classifiers":[
        {
            "category":"Building & Trades",
            "subcategory":"Construction",
            "type":"Services"
        }
    ],
    "sg:phone":"+1 321 779 9002",
    "sg:postcode":"32937",
    "sg:province":"FL",
    "sg:tags":[
        "contractor"
    ],
    "wof:name":"Tile By Alex Inc",
    "wof:placetype":"venue"
},
  "geometry": {"coordinates":[-80.610069,28.189184],"type":"Point"}
}