{
  "type": "Feature",
  "properties": {
    "iso:country":"US",
    "sg:address":"700 N Wabash Ave",
    "sg:city":"Lakeland",
    "sg:classifiers":[
        {
            "category":"Autos & Motor Vehicles",
            "subcategory":"Fuel & Gas Station",
            "type":"Retail Goods"
        }
    ],
    "sg:phone":"+1 863 682 6260",
    "sg:postcode":"33815",
    "sg:province":"FL",
    "sg:tags":[
        "station",
        "gasoline"
    ],
    "wof:name":"Wabash BP",
    "wof:placetype":"venue"
},
  "geometry": {"coordinates":[-81.990129,28.049951],"type":"Point"}
}