{
  "type": "Feature",
  "properties": {
    "iso:country":"US",
    "sg:address":"18 Raemond Ln",
    "sg:city":"Palm Coast",
    "sg:classifiers":[
        {
            "category":"Building & Trades",
            "subcategory":"Construction",
            "type":"Services"
        }
    ],
    "sg:phone":"+1 386 437 9261",
    "sg:postcode":"32164",
    "sg:province":"FL",
    "sg:tags":[
        "contractor"
    ],
    "wof:name":"Elite Decking & Framing Inc",
    "wof:placetype":"venue"
},
  "geometry": {"coordinates":[-81.229957,29.507375],"type":"Point"}
}