{
  "type": "Feature",
  "properties": {
    "addr:full":"22294 SW 62nd Ave Boca Raton FL 33428",
    "addr:housenumber":"22294",
    "addr:postcode":"33428",
    "addr:street":"Sw 62Nd Ave",
    "iso:country":"US",
    "sg:address":"22294 SW 62nd Ave",
    "sg:city":"Boca Raton",
    "sg:classifiers":[
        {
            "category":"Wholesale",
            "subcategory":"Electrical",
            "type":"Manufacturing & Wholesale Goods"
        }
    ],
    "sg:phone":"+1 561 852 0173",
    "sg:postcode":"33428",
    "sg:province":"FL",
    "sg:tags":[
        "equipment"
    ],
    "wof:name":"Kerbolt Power Systems Inc",
    "wof:placetype":"venue"
},
  "geometry": {"coordinates":[-80.19435,26.344851],"type":"Point"}
}