{
  "type": "Feature",
  "properties": {
    "addr:full":"1550 Barrancas Ave Pensacola FL 32501",
    "addr:housenumber":"1550",
    "addr:postcode":"32501",
    "addr:street":"Barrancas Ave",
    "iso:country":"US",
    "sg:address":"1550 Barrancas Ave",
    "sg:city":"Pensacola",
    "sg:classifiers":[
        {
            "category":"Organizations",
            "subcategory":"Religious Organization",
            "type":"Services"
        }
    ],
    "sg:phone":"+1 850 435 7238",
    "sg:postcode":"32501",
    "sg:province":"FL",
    "sg:tags":[
        "mosque"
    ],
    "wof:name":"Al-Islam Dawah Ctr",
    "wof:placetype":"venue"
},
  "geometry": {"coordinates":[-87.234538,30.408234],"type":"Point"}
}