{
  "type": "Feature",
  "properties": {
    "iso:country":"US",
    "sg:address":"10919 US Hwy 19",
    "sg:city":"Port Richey",
    "sg:classifiers":[
        {
            "category":"Wholesale",
            "subcategory":"Toys & Hobbies",
            "type":"Manufacturing & Wholesale Goods"
        }
    ],
    "sg:phone":"+1 727 697 3929",
    "sg:postcode":"34668",
    "sg:province":"FL",
    "sg:tags":[
        "firework"
    ],
    "wof:name":"Patriotic Fireworks",
    "wof:placetype":"venue"
},
  "geometry": {"coordinates":[-82.69937899999999,28.316798],"type":"Point"}
}