{
  "type": "Feature",
  "properties": {
    "iso:country":"US",
    "sg:address":"9394 SE 110th Street Rd",
    "sg:city":"Belleview",
    "sg:classifiers":[
        {
            "category":"Building & Trades",
            "subcategory":"Construction",
            "type":"Services"
        }
    ],
    "sg:phone":"+1 352 687 2993",
    "sg:postcode":"34420",
    "sg:province":"FL",
    "sg:tags":[
        "equipment",
        "supply",
        "drywall",
        "contractor"
    ],
    "wof:name":"Albert J Wall Jr",
    "wof:placetype":"venue"
},
  "geometry": {"coordinates":[-81.996841,29.069229],"type":"Point"}
}