{
  "type": "Feature",
  "properties": {
    "iso:country":"US",
    "sg:address":"261 Milwaukee Ave",
    "sg:city":"Dunedin",
    "sg:classifiers":[
        {
            "category":"Restaurant",
            "type":"Food & Drink"
        }
    ],
    "sg:phone":"+1 727 733 3951",
    "sg:postcode":"34698",
    "sg:province":"FL",
    "sg:tags":[
        "eating"
    ],
    "wof:name":"China Express of Clearwater",
    "wof:placetype":"venue"
},
  "geometry": {"coordinates":[-82.783688,28.002336],"type":"Point"}
}