{
  "type": "Feature",
  "properties": {
    "iso:country":"US",
    "sg:address":"38 Linwood Rd NW",
    "sg:city":"Fort Walton Beach",
    "sg:classifiers":[
        {
            "category":"Professional",
            "subcategory":"Management & Consulting",
            "type":"Services"
        }
    ],
    "sg:phone":"+1 850 862 5800",
    "sg:postcode":"32547",
    "sg:province":"FL",
    "wof:name":"Flf Management Inc",
    "wof:placetype":"venue"
},
  "geometry": {"coordinates":[-86.613587,30.455134],"type":"Point"}
}