{
  "type": "Feature",
  "properties": {
    "iso:country":"US",
    "sg:address":"15068 Jog Rd",
    "sg:city":"Delray Beach",
    "sg:classifiers":[
        {
            "category":"Health Services",
            "subcategory":"Doctor",
            "type":"Services"
        }
    ],
    "sg:phone":"+1 561 499 2686",
    "sg:postcode":"33446",
    "sg:province":"FL",
    "wof:name":"Gould Alan Dr DDS Fagd",
    "wof:placetype":"venue"
},
  "geometry": {"coordinates":[-80.146976,26.452988],"type":"Point"}
}