{
  "type": "Feature",
  "properties": {
    "iso:country":"US",
    "sg:address":"8721 Busch Oaks St",
    "sg:city":"Tampa",
    "sg:classifiers":[
        {
            "category":"Manufacturing",
            "subcategory":"Building Materials",
            "type":"Manufacturing & Wholesale Goods"
        }
    ],
    "sg:phone":"+1 813 899 9690",
    "sg:postcode":"33617",
    "sg:province":"FL",
    "sg:tags":[
        "mfg",
        "wood",
        "kitchen",
        "cabinet"
    ],
    "wof:name":"Kenneth Lee Cabinets & Display",
    "wof:placetype":"venue"
},
  "geometry": {"coordinates":[-82.404287,28.03077],"type":"Point"}
}