{
  "type": "Feature",
  "properties": {
    "addr:full":"18400 NW 2nd Ave Miami FL 33169",
    "addr:housenumber":"18400",
    "addr:postcode":"33169",
    "addr:street":"Nw 2Nd Ave",
    "iso:country":"US",
    "sg:address":"18400 NW 2nd Ave",
    "sg:city":"Miami",
    "sg:classifiers":[
        {
            "category":"Bakery",
            "type":"Food & Drink"
        }
    ],
    "sg:phone":"+1 305 249 7483",
    "sg:postcode":"33169",
    "sg:province":"FL",
    "wof:name":"Taste Rite Bakery",
    "wof:placetype":"venue"
},
  "geometry": {"coordinates":[-80.205299,25.943501],"type":"Point"}
}