{
  "type": "Feature",
  "properties": {
    "addr:full":"1050 W 15th St Riviera Beach FL 33404",
    "addr:housenumber":"1050",
    "addr:postcode":"33404",
    "addr:street":"W 15Th St",
    "iso:country":"US",
    "sg:address":"1050 W 15th St",
    "sg:city":"Riviera Beach",
    "sg:classifiers":[
        {
            "category":"Government",
            "subcategory":"Office",
            "type":"Public Place"
        }
    ],
    "sg:phone":"+1 561 840 4564",
    "sg:postcode":"33404",
    "sg:province":"FL",
    "sg:tags":[
        "county",
        "program",
        "health"
    ],
    "wof:name":"Palm Beach County Health Dept",
    "wof:placetype":"venue"
},
  "geometry": {"coordinates":[-80.068152,26.775647],"type":"Point"}
}