{
  "type": "Feature",
  "properties": {
    "iso:country":"US",
    "sg:address":"14867 N Dale Mabry Hwy",
    "sg:city":"Tampa",
    "sg:classifiers":[
        {
            "category":"Personal",
            "subcategory":"Beauty Salon",
            "type":"Services"
        }
    ],
    "sg:phone":"+1 813 960 7844",
    "sg:postcode":"33618",
    "sg:province":"FL",
    "sg:tags":[
        "shop"
    ],
    "wof:name":"Nails At Last Of Carrollwood",
    "wof:placetype":"venue"
},
  "geometry": {"coordinates":[-82.506668,28.077133],"type":"Point"}
}