{
  "type": "Feature",
  "properties": {
    "addr:full":"12315 University Mall Ct Tampa FL 33612",
    "addr:housenumber":"12315",
    "addr:postcode":"33612",
    "addr:street":"University Mall Ct",
    "iso:country":"US",
    "sg:address":"12315 University Mall Ct",
    "sg:city":"Tampa",
    "sg:classifiers":[
        {
            "category":"Manufacturing",
            "subcategory":"Food",
            "type":"Manufacturing & Wholesale Goods"
        }
    ],
    "sg:phone":"+1 813 632 0850",
    "sg:postcode":"33612",
    "sg:province":"FL",
    "sg:tags":[
        "mfg"
    ],
    "wof:name":"Pretzel Time",
    "wof:placetype":"venue"
},
  "geometry": {"coordinates":[-82.43422700000001,28.057294],"type":"Point"}
}