{
  "type": "Feature",
  "properties": {
    "iso:country":"US",
    "sg:address":"10119 SW 122nd St",
    "sg:city":"Gainesville",
    "sg:classifiers":[
        {
            "category":"Shopping",
            "type":"Retail Goods"
        }
    ],
    "sg:phone":"+1 352 495 1493",
    "sg:postcode":"32608",
    "sg:province":"FL",
    "sg:tags":[
        "crook",
        "walking",
        "cane",
        "stick"
    ],
    "wof:name":"Canes & Such Inc",
    "wof:placetype":"venue"
},
  "geometry": {"coordinates":[-82.473061,29.557526],"type":"Point"}
}