{
  "type": "Feature",
  "properties": {
    "iso:country":"US",
    "sg:address":"3415 Main Hwy",
    "sg:city":"Coconut Grove",
    "sg:classifiers":[
        {
            "category":"Restaurant",
            "type":"Food & Drink"
        }
    ],
    "sg:phone":"+1 305 442 2600",
    "sg:postcode":"33146",
    "sg:province":"FL",
    "sg:tags":[
        "middle",
        "eastern"
    ],
    "sg:website":"aladdins-grill.com",
    "wof:name":"Aladdin's Grill",
    "wof:placetype":"venue"
},
  "geometry": {"coordinates":[-80.24273599999999,25.727657],"type":"Point"}
}