{
  "type": "Feature",
  "properties": {
    "addr:full":"4239 Packard Dr Jacksonville FL 32246",
    "addr:housenumber":"4239",
    "addr:postcode":"32246",
    "addr:street":"Packard Dr",
    "iso:country":"US",
    "sg:address":"4239 Packard Dr",
    "sg:city":"Jacksonville",
    "sg:classifiers":[
        {
            "category":"Retail",
            "subcategory":"Repair Shop",
            "type":"Services"
        }
    ],
    "sg:phone":"+1 904 646 5599",
    "sg:postcode":"32246",
    "sg:province":"FL",
    "sg:tags":[
        "upholsterer"
    ],
    "wof:name":"Chandler's Upholstery Shop",
    "wof:placetype":"venue"
},
  "geometry": {"coordinates":[-81.545219,30.265544],"type":"Point"}
}