{
  "type": "Feature",
  "properties": {
    "iso:country":"US",
    "sg:address":"3138 SW Pine Island Rd",
    "sg:city":"Cape Coral",
    "sg:classifiers":[
        {
            "category":"Retail",
            "subcategory":"Auto Repair",
            "type":"Services"
        }
    ],
    "sg:phone":"+1 239 283 0273",
    "sg:postcode":"33991",
    "sg:province":"FL",
    "sg:tags":[
        "repairing",
        "automobile"
    ],
    "wof:name":"UHC Of Central Florida",
    "wof:placetype":"venue"
},
  "geometry": {"coordinates":[-82.03827800000001,26.637438],"type":"Point"}
}