{
  "type": "Feature",
  "properties": {
    "addr:full":"8349 San Clemente Dr Jacksonville FL 32217",
    "addr:housenumber":"8349",
    "addr:postcode":"32217",
    "addr:street":"San Clemente Dr",
    "iso:country":"US",
    "sg:address":"8349 San Clemente Dr",
    "sg:city":"Jacksonville",
    "sg:classifiers":[
        {
            "category":"Retail",
            "subcategory":"Portrait Studio",
            "type":"Services"
        }
    ],
    "sg:phone":"+1 904 737 8700",
    "sg:postcode":"32217",
    "sg:province":"FL",
    "sg:tags":[
        "photographer"
    ],
    "wof:name":"Spottswood Photography",
    "wof:placetype":"venue"
},
  "geometry": {"coordinates":[-81.60774000000001,30.225944],"type":"Point"}
}