{
  "type": "Feature",
  "properties": {
    "addr:full":"2880 Lust Rd Apopka FL 32703",
    "addr:postcode":"2880;32703",
    "addr:street":"Lust Rd",
    "iso:country":"US",
    "sg:address":"2880 Lust Rd",
    "sg:city":"Apopka",
    "sg:classifiers":[
        {
            "category":"Freight",
            "type":"Transportation"
        },
        {
            "category":"Professional",
            "subcategory":"Business Services",
            "type":"Services"
        }
    ],
    "sg:phone":"+1 407 880 1819",
    "sg:postcode":"32703",
    "sg:province":"FL",
    "sg:tags":[
        "plant",
        "trucking"
    ],
    "wof:name":"Plant Express Company",
    "wof:placetype":"venue"
},
  "geometry": {"coordinates":[-81.572377,28.668948],"type":"Point"}
}