{
  "type": "Feature",
  "properties": {
    "iso:country":"US",
    "sg:address":"14140 SW 36th St",
    "sg:city":"Miami",
    "sg:classifiers":[
        {
            "category":"Bakery",
            "type":"Food & Drink"
        }
    ],
    "sg:phone":"+1 305 338 6040",
    "sg:postcode":"33175",
    "sg:province":"FL",
    "sg:tags":[
        "cake",
        "pastry",
        "wedding"
    ],
    "wof:name":"Piece Of Cake",
    "wof:placetype":"venue"
},
  "geometry": {"coordinates":[-80.42319999999999,25.734179],"type":"Point"}
}