{
  "type": "Feature",
  "properties": {
    "iso:country":"US",
    "sg:address":"3660 Fowler St",
    "sg:city":"Fort Myers",
    "sg:classifiers":[
        {
            "category":"Retail",
            "subcategory":"Auto Repair",
            "type":"Services"
        }
    ],
    "sg:phone":"+1 239 275 6205",
    "sg:postcode":"33901",
    "sg:province":"FL",
    "sg:tags":[
        "body",
        "shop"
    ],
    "wof:name":"Gio Auto Paint & Body Shop Inc",
    "wof:placetype":"venue"
},
  "geometry": {"coordinates":[-81.86190000000001,26.609699],"type":"Point"}
}