{
  "type": "Feature",
  "properties": {
    "iso:country":"US",
    "sg:address":"1921 Waldemere St Ste 307",
    "sg:city":"Sarasota",
    "sg:classifiers":[
        {
            "category":"Health Services",
            "subcategory":"Doctor",
            "type":"Services"
        }
    ],
    "sg:phone":"+1 941 917 8560",
    "sg:postcode":"34239",
    "sg:province":"FL",
    "sg:tags":[
        "gynecology",
        "physician",
        "surgeon",
        "surgeons",
        "obstetrics"
    ],
    "wof:name":"Michael S Finazzo Md",
    "wof:placetype":"venue"
},
  "geometry": {"coordinates":[-82.531363,27.319175],"type":"Point"}
}