{
  "type": "Feature",
  "properties": {
    "addr:full":"421 NW 32nd St Miami FL 33127",
    "addr:housenumber":"421",
    "addr:postcode":"33127",
    "addr:street":"Nw 32Nd St",
    "iso:country":"US",
    "sg:address":"421 NW 32nd St",
    "sg:city":"Miami",
    "sg:classifiers":[
        {
            "category":"Shopping",
            "subcategory":"Used Merchandise",
            "type":"Retail Goods"
        }
    ],
    "sg:phone":"+1 305 576 7386",
    "sg:postcode":"33127",
    "sg:province":"FL",
    "wof:name":"South Liquidators",
    "wof:placetype":"venue"
},
  "geometry": {"coordinates":[-80.20222200000001,25.806601],"type":"Point"}
}