{
  "type": "Feature",
  "properties": {
    "addr:full":"3921 Tucks Rd Boynton Beach FL 33436",
    "addr:housenumber":"3921",
    "addr:postcode":"33436",
    "addr:street":"Tucks Rd",
    "iso:country":"US",
    "sg:address":"3921 Tucks Rd",
    "sg:city":"Boynton Beach",
    "sg:classifiers":[
        {
            "category":"Recreation",
            "type":"Entertainment"
        }
    ],
    "sg:phone":"+1 561 732 1245",
    "sg:postcode":"33436",
    "sg:province":"FL",
    "sg:tags":[
        "instruction",
        "yoga"
    ],
    "wof:name":"ATMA Vichara Ashram",
    "wof:placetype":"venue"
},
  "geometry": {"coordinates":[-80.105886,26.542914],"type":"Point"}
}