{
  "type": "Feature",
  "properties": {
    "iso:country":"US",
    "sg:address":"3168 Lakeside Villa Rd",
    "sg:city":"Orange Park",
    "sg:classifiers":[
        {
            "category":"Professional",
            "type":"Services"
        }
    ],
    "sg:phone":"+1 904 264 3555",
    "sg:postcode":"32073",
    "sg:province":"FL",
    "sg:tags":[
        "establishment"
    ],
    "wof:name":"Basca",
    "wof:placetype":"venue"
},
  "geometry": {"coordinates":[-81.750186,30.140225],"type":"Point"}
}