{
  "type": "Feature",
  "properties": {
    "iso:country":"US",
    "sg:address":"14476 Duval Pl W",
    "sg:city":"Jacksonville",
    "sg:classifiers":[
        {
            "category":"Restaurant",
            "type":"Food & Drink"
        }
    ],
    "sg:phone":"+1 904 741 5500",
    "sg:postcode":"32218",
    "sg:province":"FL",
    "wof:name":"American Restaurant Concepts",
    "wof:placetype":"venue"
},
  "geometry": {"coordinates":[-81.649933,30.475141],"type":"Point"}
}