{
  "type": "Feature",
  "properties": {
    "iso:country":"US",
    "sg:address":"3801 NW 58th St",
    "sg:city":"Pompano Beach",
    "sg:classifiers":[
        {
            "category":"Health Services",
            "subcategory":"Clinic",
            "type":"Services"
        }
    ],
    "sg:phone":"+1 954 698 6736",
    "sg:postcode":"33073",
    "sg:province":"FL",
    "wof:name":"Babcock Medical Services Inc",
    "wof:placetype":"venue"
},
  "geometry": {"coordinates":[-80.174627,26.302298],"type":"Point"}
}