{
  "type": "Feature",
  "properties": {
    "iso:country":"US",
    "sg:address":"1001 W Lakeview Dr",
    "sg:city":"Sebastian",
    "sg:classifiers":[
        {
            "category":"Real Estate",
            "subcategory":"Real Estate Operator",
            "type":"Services"
        }
    ],
    "sg:phone":"+1 772 589 1812",
    "sg:postcode":"32958",
    "sg:province":"FL",
    "sg:tags":[
        "mobile",
        "home",
        "site"
    ],
    "wof:name":"Park Place Mobile Home Park",
    "wof:placetype":"venue"
},
  "geometry": {"coordinates":[-80.45298,27.75782],"type":"Point"}
}