{
  "type": "Feature",
  "properties": {
    "iso:country":"US",
    "sg:address":"1430 Del Prado Blvd S",
    "sg:city":"Cape Coral",
    "sg:classifiers":[
        {
            "category":"Restaurant",
            "type":"Food & Drink"
        }
    ],
    "sg:phone":"+1 239 573 7225",
    "sg:postcode":"33990",
    "sg:province":"FL",
    "sg:tags":[
        "pizza"
    ],
    "sg:website":"www.cicispizza.com",
    "wof:name":"Cici's Pizza",
    "wof:placetype":"venue"
},
  "geometry": {"coordinates":[-81.941002,26.625099],"type":"Point"}
}