{
  "type": "Feature",
  "properties": {
    "addr:full":"1145 Airport Rd Jacksonville FL 32218",
    "addr:housenumber":"1145",
    "addr:postcode":"32218",
    "addr:street":"Airport Rd",
    "iso:country":"US",
    "sg:address":"1145 Airport Rd",
    "sg:city":"Jacksonville",
    "sg:classifiers":[
        {
            "category":"Food & Beverages",
            "subcategory":"Groceries & Convenience Stores",
            "type":"Retail Goods"
        }
    ],
    "sg:phone":"+1 904 741 4526",
    "sg:postcode":"32218",
    "sg:province":"FL",
    "wof:name":"Flash Foods",
    "wof:placetype":"venue"
},
  "geometry": {"coordinates":[-81.65063499999999,30.483004],"type":"Point"}
}