{
  "type": "Feature",
  "properties": {
    "addr:full":"8530 SW 45th St Miami FL 33155",
    "addr:housenumber":"8530",
    "addr:postcode":"33155",
    "addr:street":"Sw 45Th St",
    "iso:country":"US",
    "sg:address":"8530 SW 45th St",
    "sg:city":"Miami",
    "sg:phone":"+1 305 551 4279",
    "sg:postcode":"33155",
    "sg:province":"FL",
    "wof:name":"Angel L Arias",
    "wof:placetype":"venue"
},
  "geometry": {"coordinates":[-80.333691,25.727072],"type":"Point"}
}