{
  "type": "Feature",
  "properties": {
    "addr:full":"4068 W 12th Ave Hialeah FL 33012",
    "addr:housenumber":"4068",
    "addr:postcode":"33012",
    "addr:street":"W 12Th Ave",
    "iso:country":"US",
    "sg:address":"4068 W 12th Ave",
    "sg:city":"Hialeah",
    "sg:classifiers":[
        {
            "category":"Shopping",
            "subcategory":"Musical Instruments",
            "type":"Retail Goods"
        }
    ],
    "sg:phone":"+1 305 556 7570",
    "sg:postcode":"33012",
    "sg:province":"FL",
    "sg:tags":[
        "music",
        "dealer"
    ],
    "wof:name":"Cave Records & Tapes",
    "wof:placetype":"venue"
},
  "geometry": {"coordinates":[-80.30669,25.858808],"type":"Point"}
}