{
  "type": "Feature",
  "properties": {
    "iso:country":"US",
    "sg:address":"2210 S Atlantic Ave",
    "sg:city":"Cocoa Beach",
    "sg:classifiers":[
        {
            "category":"Professional",
            "subcategory":"Research",
            "type":"Services"
        }
    ],
    "sg:phone":"+1 321 784 2880",
    "sg:postcode":"32931",
    "sg:province":"FL",
    "sg:tags":[
        "laboratory"
    ],
    "wof:name":"Tdm Labs Inc",
    "wof:placetype":"venue"
},
  "geometry": {"coordinates":[-80.60777299999999,28.286068],"type":"Point"}
}