{
  "type": "Feature",
  "properties": {
    "iso:country":"US",
    "sg:address":"305 Acacia Rd",
    "sg:city":"Vero Beach",
    "sg:classifiers":[
        {
            "category":"Government",
            "subcategory":"Office",
            "type":"Public Place"
        }
    ],
    "sg:phone":"+1 772 978 4594",
    "sg:postcode":"32963",
    "sg:province":"FL",
    "sg:tags":[
        "village"
    ],
    "wof:name":"Vero Beach Riverhouse",
    "wof:placetype":"venue"
},
  "geometry": {"coordinates":[-80.364535,27.654365],"type":"Point"}
}