{
  "type": "Feature",
  "properties": {
    "addr:full":"3949 SW 8th St Coral Gables FL 33134",
    "addr:housenumber":"3949",
    "addr:postcode":"33134",
    "addr:street":"Sw 8Th St",
    "iso:country":"US",
    "sg:address":"3949 SW 8th St",
    "sg:city":"Coral Gables",
    "sg:classifiers":[
        {
            "category":"Shopping",
            "subcategory":"Pharmacy",
            "type":"Retail Goods"
        }
    ],
    "sg:phone":"+1 305 444 7530",
    "sg:postcode":"33134",
    "sg:province":"FL",
    "sg:tags":[
        "drugstore"
    ],
    "sg:website":"www.navarropharmacies.com",
    "wof:name":"Navarro Discount Pharmacies",
    "wof:placetype":"venue"
},
  "geometry": {"coordinates":[-80.26061199999999,25.764653],"type":"Point"}
}