{
  "type": "Feature",
  "properties": {
    "iso:country":"US",
    "sg:address":"2867 Caledonia St",
    "sg:city":"Marianna",
    "sg:classifiers":[
        {
            "category":"Insurance",
            "subcategory":"Insurance Agent",
            "type":"Services"
        },
        {
            "category":"Insurance",
            "subcategory":"Hazard Insurance",
            "type":"Services"
        },
        {
            "category":"Insurance",
            "subcategory":"Title Insurance",
            "type":"Services"
        },
        {
            "category":"Insurance",
            "subcategory":"Life Insurance",
            "type":"Services"
        }
    ],
    "sg:phone":"+1 850 526 2799",
    "sg:postcode":"32448",
    "sg:province":"FL",
    "sg:tags":[
        "business",
        "auto",
        "commercial",
        "homeowner",
        "motorcycle",
        "renter"
    ],
    "wof:name":"Allstate Insurance Company - Cindi Granbury",
    "wof:placetype":"venue"
},
  "geometry": {"coordinates":[-85.22914900000001,30.773649],"type":"Point"}
}