{
  "type": "Feature",
  "properties": {
    "addr:full":"7133 Augusta Blvd Largo FL 33777",
    "addr:housenumber":"7133",
    "addr:postcode":"33777",
    "addr:street":"Augusta Blvd",
    "iso:country":"US",
    "sg:address":"7133 Augusta Blvd",
    "sg:city":"Largo",
    "sg:classifiers":[
        {
            "category":"Real Estate",
            "subcategory":"Real Estate Agent",
            "type":"Services"
        }
    ],
    "sg:phone":"+1 727 398 4400",
    "sg:postcode":"33777",
    "sg:province":"FL",
    "sg:tags":[
        "appraiser"
    ],
    "wof:name":"Sunbelt Real Estate Appraisers",
    "wof:placetype":"venue"
},
  "geometry": {"coordinates":[-82.762261,27.833937],"type":"Point"}
}