{
  "type": "Feature",
  "properties": {
    "iso:country":"US",
    "sg:address":"306 Lincoln Rd",
    "sg:city":"Miami Beach",
    "sg:classifiers":[
        {
            "category":"Shopping",
            "subcategory":"Clothing, Apparel, & Fashions",
            "type":"Retail Goods"
        }
    ],
    "sg:phone":"+1 305 534 9900",
    "sg:postcode":"33139",
    "sg:province":"FL",
    "wof:name":"Lerner Shops",
    "wof:placetype":"venue"
},
  "geometry": {"coordinates":[-80.13181400000001,25.790601],"type":"Point"}
}