{
  "type": "Feature",
  "properties": {
    "iso:country":"US",
    "sg:address":"1300 W Broward Blvd",
    "sg:city":"Fort Lauderdale",
    "sg:classifiers":[
        {
            "category":"Organizations",
            "subcategory":"Non-profit Organization",
            "type":"Services"
        }
    ],
    "sg:phone":"+1 954 761 5750",
    "sg:postcode":"33312",
    "sg:province":"FL",
    "sg:tags":[
        "agency",
        "health",
        "system"
    ],
    "wof:name":"Prison Health Services Inc",
    "wof:placetype":"venue"
},
  "geometry": {"coordinates":[-80.158585,26.121832],"type":"Point"}
}