{
  "type": "Feature",
  "properties": {
    "iso:country":"US",
    "sg:address":"1426 Country Oaks Ln",
    "sg:city":"Lakeland",
    "sg:classifiers":[
        {
            "category":"Retail",
            "subcategory":"Repair Shop",
            "type":"Services"
        }
    ],
    "sg:phone":"+1 863 686 5504",
    "sg:postcode":"33810",
    "sg:province":"FL",
    "sg:tags":[
        "antique",
        "restoring"
    ],
    "wof:name":"Miller's Antiques & Artifacts",
    "wof:placetype":"venue"
},
  "geometry": {"coordinates":[-82.050292,28.061602],"type":"Point"}
}