{
  "type": "Feature",
  "properties": {
    "iso:country":"US",
    "sg:address":"1958 W Martin Luther King Jr Blvd",
    "sg:city":"Tampa",
    "sg:classifiers":[
        {
            "category":"Professional",
            "subcategory":"Lawyer & Legal Services",
            "type":"Services"
        }
    ],
    "sg:phone":"+1 813 871 2223",
    "sg:postcode":"33607",
    "sg:province":"FL",
    "sg:tags":[
        "attorney"
    ],
    "wof:name":"Donald L Murray Atty At Law",
    "wof:placetype":"venue"
},
  "geometry": {"coordinates":[-82.479507,27.981189],"type":"Point"}
}