{
  "type": "Feature",
  "properties": {
    "iso:country":"US",
    "sg:address":"3813 N Monroe St",
    "sg:city":"Tallahassee",
    "sg:classifiers":[
        {
            "category":"Shopping",
            "subcategory":"Department Store",
            "type":"Retail Goods"
        }
    ],
    "sg:phone":"+1 850 536 0090",
    "sg:postcode":"32303",
    "sg:province":"FL",
    "sg:tags":[
        "variety"
    ],
    "sg:website":"http://www.familydollar.com",
    "wof:name":"Family Dollar Stores",
    "wof:placetype":"venue"
},
  "geometry": {"coordinates":[-84.328239,30.500681],"type":"Point"}
}