{
  "type": "Feature",
  "properties": {
    "iso:country":"US",
    "sg:address":"130 Heights Ave",
    "sg:city":"Inverness",
    "sg:classifiers":[
        {
            "category":"Health Services",
            "subcategory":"Nursing And Care Facility",
            "type":"Services"
        }
    ],
    "sg:phone":"+1 352 795 6808",
    "sg:postcode":"34452",
    "sg:province":"FL",
    "sg:tags":[
        "home",
        "retirement",
        "community"
    ],
    "wof:name":"Franklin Cottage",
    "wof:placetype":"venue"
},
  "geometry": {"coordinates":[-82.350759,28.835431],"type":"Point"}
}