{
  "type": "Feature",
  "properties": {
    "iso:country":"US",
    "sg:address":"10690 NW 19th S",
    "sg:city":"Miami",
    "sg:classifiers":[
        {
            "category":"Coffee & Tea",
            "type":"Food & Drink"
        }
    ],
    "sg:phone":"+1 305 468 3998",
    "sg:postcode":"33172",
    "sg:province":"FL",
    "sg:website":"www.starbucks.com",
    "wof:name":"Starbucks",
    "wof:placetype":"venue"
},
  "geometry": {"coordinates":[-80.319407,25.791517],"type":"Point"}
}