{
  "type": "Feature",
  "properties": {
    "iso:country":"US",
    "sg:address":"2632 Whipple Ave",
    "sg:city":"Orange Park",
    "sg:classifiers":[
        {
            "category":"Building & Trades",
            "subcategory":"Construction",
            "type":"Services"
        }
    ],
    "sg:phone":"+1 904 278 5490",
    "sg:postcode":"32073",
    "sg:province":"FL",
    "sg:tags":[
        "floor",
        "laying",
        "contractor"
    ],
    "wof:name":"Jenkins Flooring Co Inc",
    "wof:placetype":"venue"
},
  "geometry": {"coordinates":[-81.741167,30.151008],"type":"Point"}
}