{
  "type": "Feature",
  "properties": {
    "addr:full":"1110 Capital Cir NE Tallahassee FL 32301",
    "addr:housenumber":"1110",
    "addr:postcode":"32301",
    "addr:street":"Capital Cir Ne",
    "iso:country":"US",
    "sg:address":"1110 Capital Cir NE",
    "sg:city":"Tallahassee",
    "sg:classifiers":[
        {
            "category":"Personal",
            "type":"Services"
        }
    ],
    "sg:phone":"+1 850 216 2002",
    "sg:postcode":"32301",
    "sg:province":"FL",
    "sg:tags":[
        "assistant"
    ],
    "wof:name":"Global Tech Component",
    "wof:placetype":"venue"
},
  "geometry": {"coordinates":[-84.22659299999999,30.45023],"type":"Point"}
}