{
  "type": "Feature",
  "properties": {
    "iso:country":"US",
    "sg:address":"8181 NW 67th St",
    "sg:city":"Miami",
    "sg:classifiers":[
        {
            "category":"Airport",
            "type":"Transportation"
        }
    ],
    "sg:phone":"+1 305 594 1955",
    "sg:postcode":"33166",
    "sg:province":"FL",
    "sg:tags":[
        "aircraft",
        "maintenance"
    ],
    "wof:name":"Aerospace Accessory Svc",
    "wof:placetype":"venue"
},
  "geometry": {"coordinates":[-80.329414,25.834445],"type":"Point"}
}