{
  "type": "Feature",
  "properties": {
    "iso:country":"US",
    "sg:address":"1950 Calumet St",
    "sg:city":"Clearwater",
    "sg:classifiers":[
        {
            "category":"Wholesale",
            "subcategory":"Non-durable Goods",
            "type":"Manufacturing & Wholesale Goods"
        },
        {
            "category":"Shopping",
            "subcategory":"Department Store",
            "type":"Retail Goods"
        },
        {
            "category":"Building & Trades",
            "subcategory":"Cleaning & Sanitation",
            "type":"Services"
        },
        {
            "category":"Home & Garden",
            "subcategory":"Hardware",
            "type":"Retail Goods"
        },
        {
            "category":"Manufacturing",
            "subcategory":"Chemicals & Compounds",
            "type":"Manufacturing & Wholesale Goods"
        }
    ],
    "sg:phone":"+1 727 461 2546",
    "sg:postcode":"33765",
    "sg:province":"FL",
    "sg:tags":[
        "cleaner",
        "supply",
        "equipment-wholesale",
        "house",
        "rug",
        "equipment",
        "chemicals-wholesale",
        "carpet",
        "janitor",
        "supplies-wholesale",
        "manufacturer"
    ],
    "sg:website":"http://www.sanichem.com",
    "wof:name":"Sani-Chem Cleaning Supplies",
    "wof:placetype":"venue"
},
  "geometry": {"coordinates":[-82.756839,27.985821],"type":"Point"}
}