{
  "type": "Feature",
  "properties": {
    "addr:full":"10930 US Hwy 1 N St Augustine FL 32095",
    "addr:housenumber":"10930",
    "addr:postcode":"32095",
    "addr:street":"Us Hwy 1 N St",
    "iso:country":"US",
    "sg:address":"10930 US Hwy 1 N",
    "sg:city":"St Augustine",
    "sg:classifiers":[
        {
            "category":"Recreation",
            "type":"Entertainment"
        }
    ],
    "sg:phone":"+1 904 429 0153",
    "sg:postcode":"32095",
    "sg:province":"FL",
    "sg:tags":[
        "club",
        "sport"
    ],
    "wof:name":"Special Olympics Florida",
    "wof:placetype":"venue"
},
  "geometry": {"coordinates":[-81.454605,30.080733],"type":"Point"}
}