{
  "type": "Feature",
  "properties": {
    "iso:country":"US",
    "sg:address":"2113 Hovington Cir W",
    "sg:city":"Jacksonville",
    "sg:phone":"+1 904 221 3074",
    "sg:postcode":"32246",
    "sg:province":"FL",
    "sg:tags":[
        "commercial",
        "irrigation",
        "design",
        "system"
    ],
    "wof:name":"Garrett Designs",
    "wof:placetype":"venue"
},
  "geometry": {"coordinates":[-81.476572,30.310859],"type":"Point"}
}