{
  "type": "Feature",
  "properties": {
    "addr:full":"2481 NW 56th Ave Lauderhill FL 33313",
    "addr:housenumber":"2481",
    "addr:postcode":"33313",
    "addr:street":"Nw 56Th Ave",
    "iso:country":"US",
    "sg:address":"2481 NW 56th Ave",
    "sg:city":"Lauderhill",
    "sg:classifiers":[
        {
            "category":"Retail",
            "subcategory":"Auto Repair",
            "type":"Services"
        }
    ],
    "sg:phone":"+1 954 749 7480",
    "sg:postcode":"33313",
    "sg:province":"FL",
    "sg:tags":[
        "wrecker"
    ],
    "wof:name":"X L Towing",
    "wof:placetype":"venue"
},
  "geometry": {"coordinates":[-80.22698800000001,26.156931],"type":"Point"}
}