{
  "type": "Feature",
  "properties": {
    "iso:country":"US",
    "sg:address":"14510 SW 166th Ter",
    "sg:city":"Miami",
    "sg:classifiers":[
        {
            "category":"Banks & Credit Unions",
            "subcategory":"Bank",
            "type":"Services"
        }
    ],
    "sg:phone":"+1 786 242 8898",
    "sg:postcode":"33177",
    "sg:province":"FL",
    "sg:tags":[
        "loan",
        "real estate"
    ],
    "wof:name":"Dade Mortgage",
    "wof:placetype":"venue"
},
  "geometry": {"coordinates":[-80.428686,25.612315],"type":"Point"}
}