{
  "type": "Feature",
  "properties": {
    "addr:full":"218 NE 7th Pl Cape Coral FL 33909",
    "addr:housenumber":"218",
    "addr:postcode":"33909",
    "addr:street":"Ne 7Th Pl",
    "iso:country":"US",
    "sg:address":"218 NE 7th Pl",
    "sg:city":"Cape Coral",
    "sg:classifiers":[
        {
            "category":"Building & Trades",
            "subcategory":"Landscaping Services",
            "type":"Services"
        }
    ],
    "sg:phone":"+1 239 772 8321",
    "sg:postcode":"33909",
    "sg:province":"FL",
    "wof:name":"Lowandes Landscape Maintenance",
    "wof:placetype":"venue"
},
  "geometry": {"coordinates":[-81.959881,26.654323],"type":"Point"}
}