{
  "type": "Feature",
  "properties": {
    "iso:country":"US",
    "sg:address":"101 S 6th St",
    "sg:city":"Macclenny",
    "sg:classifiers":[
        {
            "category":"Autos & Motor Vehicles",
            "subcategory":"Auto Supplies",
            "type":"Retail Goods"
        }
    ],
    "sg:phone":"+1 904 259 6341",
    "sg:postcode":"32063",
    "sg:province":"FL",
    "sg:tags":[
        "automobile",
        "parts"
    ],
    "wof:name":"Auto & Truck Value Inc",
    "wof:placetype":"venue"
},
  "geometry": {"coordinates":[-82.123508,30.281319],"type":"Point"}
}