{
  "type": "Feature",
  "properties": {
    "addr:full":"1110 N Gordon St Plant City FL 33563",
    "addr:housenumber":"1110",
    "addr:postcode":"33563",
    "addr:street":"N Gordon St",
    "iso:country":"US",
    "sg:address":"1110 N Gordon St",
    "sg:city":"Plant City",
    "sg:classifiers":[
        {
            "category":"Organizations",
            "subcategory":"Religious Organization",
            "type":"Services"
        }
    ],
    "sg:phone":"+1 813 752 5005",
    "sg:postcode":"33563",
    "sg:province":"FL",
    "sg:tags":[
        "church"
    ],
    "sg:website":"www.calvaryfellowshipag.com",
    "wof:name":"Calvary Fllowship Assembly God",
    "wof:placetype":"venue"
},
  "geometry": {"coordinates":[-82.11333399999999,28.023946],"type":"Point"}
}