{
  "type": "Feature",
  "properties": {
    "addr:full":"633 Tamiami Trl Venice FL 34285",
    "addr:housenumber":"633",
    "addr:postcode":"34285",
    "addr:street":"Tamiami Trl",
    "iso:country":"US",
    "sg:address":"633 Tamiami Trl",
    "sg:city":"Venice",
    "sg:classifiers":[
        {
            "category":"Real Estate",
            "subcategory":"Real Estate Agent",
            "type":"Services"
        }
    ],
    "sg:phone":"+1 941 485 8338",
    "sg:postcode":"34285",
    "sg:province":"FL",
    "wof:name":"Richardson Kleiber Walter",
    "wof:placetype":"venue"
},
  "geometry": {"coordinates":[-82.44336800000001,27.088912],"type":"Point"}
}