{
  "type": "Feature",
  "properties": {
    "iso:country":"US",
    "sg:address":"1333 S Miami Ave Ste 302",
    "sg:city":"Miami",
    "sg:classifiers":[
        {
            "category":"Professional",
            "subcategory":"Art Services",
            "type":"Services"
        },
        {
            "category":"Communications",
            "type":"Services"
        },
        {
            "category":"Professional",
            "subcategory":"Computer Services",
            "type":"Services"
        }
    ],
    "sg:phone":"+1 866 717 5646",
    "sg:postcode":"33130",
    "sg:province":"FL",
    "sg:tags":[
        "web",
        "graphic",
        "design",
        "site"
    ],
    "sg:website":"www.EvokeDesign.com",
    "wof:name":"Evoke Design",
    "wof:placetype":"venue"
},
  "geometry": {"coordinates":[-80.193009,25.761026],"type":"Point"}
}