{
  "type": "Feature",
  "properties": {
    "iso:country":"US",
    "sg:address":"5709 Johns Rd",
    "sg:city":"Tampa",
    "sg:classifiers":[
        {
            "category":"Shopping",
            "subcategory":"Optical Goods",
            "type":"Retail Goods"
        }
    ],
    "sg:phone":"+1 813 885 3937",
    "sg:postcode":"33634",
    "sg:province":"FL",
    "sg:website":"www.opticaloutlets.com",
    "wof:name":"Optical Outlets Corporate",
    "wof:placetype":"venue"
},
  "geometry": {"coordinates":[-82.539401,28.008202],"type":"Point"}
}