{
  "type": "Feature",
  "properties": {
    "iso:country":"US",
    "sg:address":"9241 NW 23rd Pl",
    "sg:city":"Gainesville",
    "sg:classifiers":[
        {
            "category":"Personal",
            "subcategory":"Beauty Salon",
            "type":"Services"
        }
    ],
    "sg:phone":"+1 352 328 6562",
    "sg:postcode":"32606",
    "sg:province":"FL",
    "wof:name":"Wn To Earth By Gina Fox",
    "wof:placetype":"venue"
},
  "geometry": {"coordinates":[-82.440631,29.674905],"type":"Point"}
}