{
  "type": "Feature",
  "properties": {
    "addr:full":"3014 NW 6th St Gainesville FL 32609",
    "addr:housenumber":"3014",
    "addr:postcode":"32609",
    "addr:street":"Nw 6Th St",
    "iso:country":"US",
    "sg:address":"3014 NW 6th St",
    "sg:city":"Gainesville",
    "sg:classifiers":[
        {
            "category":"Retail",
            "subcategory":"Animal Services",
            "type":"Services"
        }
    ],
    "sg:phone":"+1 352 395 6577",
    "sg:postcode":"32609",
    "sg:province":"FL",
    "wof:name":"Eileen Irvine Pet Groomer",
    "wof:placetype":"venue"
},
  "geometry": {"coordinates":[-82.330865,29.680469],"type":"Point"}
}