{
  "type": "Feature",
  "properties": {
    "addr:full":"8737 Calumet Blvd Port Charlotte FL 33981",
    "addr:housenumber":"8737",
    "addr:postcode":"33981",
    "addr:street":"Calumet Blvd",
    "iso:country":"US",
    "sg:address":"8737 Calumet Blvd",
    "sg:city":"Port Charlotte",
    "sg:classifiers":[
        {
            "category":"Marine",
            "type":"Transportation"
        }
    ],
    "sg:phone":"+1 941 697 1224",
    "sg:postcode":"33981",
    "sg:province":"FL",
    "sg:tags":[
        "towing"
    ],
    "wof:name":"Sam's Moblie Marine Svc",
    "wof:placetype":"venue"
},
  "geometry": {"coordinates":[-82.19359300000001,26.910612],"type":"Point"}
}