{
  "type": "Feature",
  "properties": {
    "iso:country":"US",
    "sg:address":"1320 SW 25th Ln",
    "sg:city":"Palm City",
    "sg:classifiers":[
        {
            "category":"Banks & Credit Unions",
            "subcategory":"Investment Brokerage",
            "type":"Services"
        }
    ],
    "sg:phone":"+1 772 219 4244",
    "sg:postcode":"34990",
    "sg:province":"FL",
    "sg:tags":[
        "consultant",
        "planning",
        "financial"
    ],
    "wof:name":"DESI",
    "wof:placetype":"venue"
},
  "geometry": {"coordinates":[-80.286958,27.188266],"type":"Point"}
}