{
  "type": "Feature",
  "properties": {
    "iso:country":"US",
    "sg:address":"1439 NE 4th Ave",
    "sg:city":"Fort Lauderdale",
    "sg:classifiers":[
        {
            "category":"Personal",
            "subcategory":"Barber",
            "type":"Services"
        }
    ],
    "sg:phone":"+1 954 525 3749",
    "sg:postcode":"33304",
    "sg:province":"FL",
    "wof:name":"Best Barber Shop",
    "wof:placetype":"venue"
},
  "geometry": {"coordinates":[-80.140767,26.145092],"type":"Point"}
}