{
  "type": "Feature",
  "properties": {
    "addr:full":"5800 Center St Jupiter FL 33458",
    "addr:housenumber":"5800",
    "addr:postcode":"33458",
    "addr:street":"Center St",
    "iso:country":"US",
    "sg:address":"5800 Center St",
    "sg:city":"Jupiter",
    "sg:classifiers":[
        {
            "category":"Home & Garden",
            "subcategory":"Garden Supply",
            "type":"Retail Goods"
        }
    ],
    "sg:phone":"+1 561 747 9019",
    "sg:postcode":"33458",
    "sg:province":"FL",
    "sg:tags":[
        "nurseryman"
    ],
    "wof:name":"Dix Landscaping",
    "wof:placetype":"venue"
},
  "geometry": {"coordinates":[-80.121989,26.939006],"type":"Point"}
}