{
  "type": "Feature",
  "properties": {
    "addr:full":"669 San Juan Bay Oviedo FL 32765",
    "addr:housenumber":"669",
    "addr:postcode":"32765",
    "addr:street":"San Juan Bay",
    "iso:country":"US",
    "sg:address":"669 San Juan Bay",
    "sg:city":"Oviedo",
    "sg:classifiers":[
        {
            "category":"Professional",
            "subcategory":"Business Services",
            "type":"Services"
        }
    ],
    "sg:phone":"+1 407 971 1007",
    "sg:postcode":"32765",
    "sg:province":"FL",
    "sg:tags":[
        "pool",
        "swimming"
    ],
    "wof:name":"Allstar Pool Svc",
    "wof:placetype":"venue"
},
  "geometry": {"coordinates":[-81.199079,28.619548],"type":"Point"}
}