{
  "type": "Feature",
  "properties": {
    "addr:full":"302 S Line Ave Inverness FL 34452",
    "addr:housenumber":"302",
    "addr:postcode":"34452",
    "addr:street":"S Line Ave",
    "iso:country":"US",
    "sg:address":"302 S Line Ave",
    "sg:city":"Inverness",
    "sg:classifiers":[
        {
            "category":"Health Services",
            "subcategory":"Health Practitioner",
            "type":"Services"
        }
    ],
    "sg:phone":"+1 352 341 3740",
    "sg:postcode":"34452",
    "sg:province":"FL",
    "sg:tags":[
        "therapist",
        "physical"
    ],
    "wof:name":"Sports & Orthopedic Rehab",
    "wof:placetype":"venue"
},
  "geometry": {"coordinates":[-82.33667800000001,28.832104],"type":"Point"}
}