{
  "type": "Feature",
  "properties": {
    "iso:country":"US",
    "sg:address":"8901 Co Rd 614A",
    "sg:city":"Bushnell",
    "sg:classifiers":[
        {
            "category":"Wholesale",
            "subcategory":"Metals & Minerals",
            "type":"Manufacturing & Wholesale Goods"
        }
    ],
    "sg:phone":"+1 352 793 9093",
    "sg:postcode":"33513",
    "sg:province":"FL",
    "sg:tags":[
        "aluminum"
    ],
    "wof:name":"Alumico Inc",
    "wof:placetype":"venue"
},
  "geometry": {"coordinates":[-82.14712,28.61637],"type":"Point"}
}