{
  "type": "Feature",
  "properties": {
    "iso:country":"US",
    "sg:address":"741 N 70th Way",
    "sg:city":"Hollywood",
    "sg:classifiers":[
        {
            "category":"Manufacturing",
            "subcategory":"Furniture",
            "type":"Manufacturing & Wholesale Goods"
        }
    ],
    "sg:phone":"+1 954 963 5069",
    "sg:postcode":"33024",
    "sg:province":"FL",
    "sg:tags":[
        "drapery",
        "mfg"
    ],
    "wof:name":"Astro Vertical Blinds",
    "wof:placetype":"venue"
},
  "geometry": {"coordinates":[-80.231193,26.0166],"type":"Point"}
}