{
  "type": "Feature",
  "properties": {
    "addr:full":"15241 NE 10th Ave North Miami Bch FL 33162",
    "addr:housenumber":"15241",
    "addr:postcode":"33162",
    "addr:street":"Ne 10Th Ave",
    "iso:country":"US",
    "sg:address":"15241 NE 10th Ave",
    "sg:city":"North Miami Bch",
    "sg:classifiers":[
        {
            "category":"Professional",
            "subcategory":"Business Services",
            "type":"Services"
        }
    ],
    "sg:phone":"+1 305 354 9060",
    "sg:postcode":"33162",
    "sg:province":"FL",
    "sg:tags":[
        "packaging"
    ],
    "wof:name":"A 1 Shipping Inc",
    "wof:placetype":"venue"
},
  "geometry": {"coordinates":[-80.179534,25.915842],"type":"Point"}
}