{
  "type": "Feature",
  "properties": {
    "iso:country":"US",
    "sg:address":"225 E Stuart Ave",
    "sg:city":"Lake Wales",
    "sg:classifiers":[
        {
            "category":"Professional",
            "subcategory":"Computer Services",
            "type":"Services"
        }
    ],
    "sg:phone":"+1 863 676 3248",
    "sg:postcode":"33853",
    "sg:province":"FL",
    "sg:tags":[
        "consultant",
        "designer"
    ],
    "wof:name":"True North USA",
    "wof:placetype":"venue"
},
  "geometry": {"coordinates":[-81.587829,27.90204],"type":"Point"}
}