{
  "type": "Feature",
  "properties": {
    "iso:country":"US",
    "sg:address":"114 N Florida Ave",
    "sg:city":"Deland",
    "sg:classifiers":[
        {
            "category":"Travel",
            "subcategory":"Travel Agent",
            "type":"Entertainment"
        }
    ],
    "sg:phone":"+1 386 738 9262",
    "sg:postcode":"32720",
    "sg:province":"FL",
    "sg:tags":[
        "information",
        "tourist"
    ],
    "wof:name":"West Volusia Tourism Authority",
    "wof:placetype":"venue"
},
  "geometry": {"coordinates":[-81.305463,29.028764],"type":"Point"}
}