{
  "type": "Feature",
  "properties": {
    "iso:country":"US",
    "sg:address":"1428 Saint Johns Ave",
    "sg:city":"Palatka",
    "sg:classifiers":[
        {
            "category":"Communications",
            "subcategory":"Radio Station",
            "type":"Services"
        }
    ],
    "sg:phone":"+1 386 325 4556",
    "sg:postcode":"32177",
    "sg:province":"FL",
    "sg:tags":[
        "broadcast"
    ],
    "wof:name":"WIYD 1260 AM Radio",
    "wof:placetype":"venue"
},
  "geometry": {"coordinates":[-81.643765,29.648408],"type":"Point"}
}