{
  "type": "Feature",
  "properties": {
    "iso:country":"US",
    "sg:address":"725 Xanadu Pl",
    "sg:city":"Jupiter",
    "sg:classifiers":[
        {
            "category":"Professional",
            "subcategory":"Business Services",
            "type":"Services"
        }
    ],
    "sg:phone":"+1 561 748 7461",
    "sg:postcode":"33477",
    "sg:province":"FL",
    "wof:name":"Anna Moroncini",
    "wof:placetype":"venue"
},
  "geometry": {"coordinates":[-80.07138399999999,26.924836],"type":"Point"}
}