{
  "type": "Feature",
  "properties": {
    "addr:full":"1705 Hobbs Rd Auburndale FL 33823",
    "addr:housenumber":"1705",
    "addr:postcode":"33823",
    "addr:street":"Hobbs Rd",
    "iso:country":"US",
    "sg:address":"1705 Hobbs Rd",
    "sg:city":"Auburndale",
    "sg:classifiers":[
        {
            "category":"Restaurant",
            "type":"Food & Drink"
        }
    ],
    "sg:phone":"+1 863 224 8370",
    "sg:postcode":"33823",
    "sg:province":"FL",
    "sg:tags":[
        "eating"
    ],
    "wof:name":"Moses & Son Ice Cream",
    "wof:placetype":"venue"
},
  "geometry": {"coordinates":[-81.78030699999999,28.044059],"type":"Point"}
}