{
  "type": "Feature",
  "properties": {
    "iso:country":"US",
    "sg:address":"845 Taylor Rd",
    "sg:city":"Daytona Beach",
    "sg:classifiers":[
        {
            "category":"Retail",
            "subcategory":"Animal Services",
            "type":"Services"
        }
    ],
    "sg:phone":"+1 386 761 1424",
    "sg:postcode":"32127",
    "sg:province":"FL",
    "sg:tags":[
        "boarding",
        "pet",
        "kennel",
        "sitting"
    ],
    "wof:name":"Alabiss Kennels & Cattery",
    "wof:placetype":"venue"
},
  "geometry": {"coordinates":[-81.02054,29.106943],"type":"Point"}
}