{
  "type": "Feature",
  "properties": {
    "iso:country":"US",
    "sg:address":"11700 S Cleveland Ave",
    "sg:city":"Fort Myers",
    "sg:classifiers":[
        {
            "category":"Food & Beverages",
            "subcategory":"Groceries & Convenience Stores",
            "type":"Retail Goods"
        }
    ],
    "sg:phone":"+1 239 275 4100",
    "sg:postcode":"33907",
    "sg:province":"FL",
    "sg:website":"www.7-eleven.com",
    "wof:name":"7-Eleven Inc",
    "wof:placetype":"venue"
},
  "geometry": {"coordinates":[-81.872203,26.570641],"type":"Point"}
}