{
  "type": "Feature",
  "properties": {
    "iso:country":"US",
    "sg:address":"11849 Layton St",
    "sg:city":"Leesburg",
    "sg:classifiers":[
        {
            "category":"Retail",
            "subcategory":"Animal Services",
            "type":"Services"
        }
    ],
    "sg:phone":"+1 352 483 6976",
    "sg:postcode":"34788",
    "sg:province":"FL",
    "sg:tags":[
        "nonprofit",
        "rescue"
    ],
    "wof:name":"Critters R US Animal Rescue &",
    "wof:placetype":"venue"
},
  "geometry": {"coordinates":[-81.759968,28.848848],"type":"Point"}
}