{
  "type": "Feature",
  "properties": {
    "addr:full":"9554 Bone Bluff Dr Gulf Breeze FL 32566",
    "addr:postcode":"9554;32566",
    "addr:street":"Bone Bluff Dr",
    "iso:country":"US",
    "sg:address":"9554 Bone Bluff Dr",
    "sg:city":"Gulf Breeze",
    "sg:classifiers":[
        {
            "category":"Banks & Credit Unions",
            "subcategory":"Financial Services",
            "type":"Services"
        }
    ],
    "sg:phone":"+1 850 939 6518",
    "sg:postcode":"32566",
    "sg:province":"FL",
    "sg:tags":[
        "investor"
    ],
    "wof:name":"Jankus Family Ltd Partnership",
    "wof:placetype":"venue"
},
  "geometry": {"coordinates":[-86.825039,30.428752],"type":"Point"}
}