{
  "type": "Feature",
  "properties": {
    "addr:full":"1005 3rd Ave W Palmetto FL 34221",
    "addr:housenumber":"1005",
    "addr:postcode":"34221",
    "addr:street":"3Rd Ave W",
    "iso:country":"US",
    "sg:address":"1005 3rd Ave W",
    "sg:city":"Palmetto",
    "sg:classifiers":[
        {
            "category":"Organizations",
            "subcategory":"Non-profit Organization",
            "type":"Services"
        }
    ],
    "sg:phone":"+1 941 723 3319",
    "sg:postcode":"34221",
    "sg:province":"FL",
    "sg:tags":[
        "human"
    ],
    "wof:name":"Habitat For Humanity Manatee",
    "wof:placetype":"venue"
},
  "geometry": {"coordinates":[-82.56620100000001,27.521362],"type":"Point"}
}