{
  "type": "Feature",
  "properties": {
    "iso:country":"US",
    "sg:address":"261 Warfield Ave S",
    "sg:city":"Venice",
    "sg:classifiers":[
        {
            "category":"Retail",
            "subcategory":"Auto Repair",
            "type":"Services"
        }
    ],
    "sg:phone":"+1 941 485 0802",
    "sg:postcode":"34285",
    "sg:province":"FL",
    "sg:tags":[
        "general"
    ],
    "wof:name":"European Starr Automotive",
    "wof:placetype":"venue"
},
  "geometry": {"coordinates":[-82.43606200000001,27.097728],"type":"Point"}
}