{
  "type": "Feature",
  "properties": {
    "addr:full":"4439 Old Winter Garden Rd Orlando FL 32811",
    "addr:housenumber":"4439",
    "addr:postcode":"32811",
    "addr:street":"Old Winter Garden Rd",
    "iso:country":"US",
    "sg:address":"4439 Old Winter Garden Rd",
    "sg:city":"Orlando",
    "sg:classifiers":[
        {
            "category":"Organizations",
            "subcategory":"Non-profit Organization",
            "type":"Services"
        }
    ],
    "sg:phone":"+1 407 523 3004",
    "sg:postcode":"32811",
    "sg:province":"FL",
    "sg:tags":[
        "human"
    ],
    "wof:name":"Ivey Lane Neighborhood Ctr-Fam",
    "wof:placetype":"venue"
},
  "geometry": {"coordinates":[-81.435304,28.547194],"type":"Point"}
}