{
  "type": "Feature",
  "properties": {
    "iso:country":"US",
    "sg:address":"1425 Oviedo Marketplace Blvd",
    "sg:city":"Oviedo",
    "sg:classifiers":[
        {
            "category":"Shopping",
            "subcategory":"Gifts & Souvenirs",
            "type":"Retail Goods"
        }
    ],
    "sg:phone":"+1 407 977 4220",
    "sg:postcode":"32765",
    "sg:province":"FL",
    "sg:tags":[
        "shop"
    ],
    "wof:name":"Amy's Hallmark",
    "wof:placetype":"venue"
},
  "geometry": {"coordinates":[-81.233293,28.661008],"type":"Point"}
}