{
  "type": "Feature",
  "properties": {
    "iso:country":"US",
    "sg:address":"1100 N Main St",
    "sg:city":"Belle Glade",
    "sg:classifiers":[
        {
            "category":"Banks & Credit Unions",
            "subcategory":"Investment Brokerage",
            "type":"Services"
        }
    ],
    "sg:phone":"+1 561 996 0404",
    "sg:postcode":"33430",
    "sg:province":"FL",
    "sg:tags":[
        "security"
    ],
    "wof:name":"Citigroup Global Markets Inc",
    "wof:placetype":"venue"
},
  "geometry": {"coordinates":[-80.667737,26.697554],"type":"Point"}
}