{
  "type": "Feature",
  "properties": {
    "iso:country":"US",
    "sg:address":"5815 N Andrews Way",
    "sg:city":"Fort Lauderdale",
    "sg:classifiers":[
        {
            "category":"Wholesale",
            "subcategory":"Electrical",
            "type":"Manufacturing & Wholesale Goods"
        }
    ],
    "sg:phone":"+1 954 776 3999",
    "sg:postcode":"33309",
    "sg:province":"FL",
    "sg:tags":[
        "phone",
        "distribution",
        "whole",
        "cellular"
    ],
    "wof:name":"CLC Distributors",
    "wof:placetype":"venue"
},
  "geometry": {"coordinates":[-80.149728,26.199171],"type":"Point"}
}