{
  "type": "Feature",
  "properties": {
    "iso:country":"US",
    "sg:address":"100 E Sybelia Ave",
    "sg:city":"Maitland",
    "sg:classifiers":[
        {
            "category":"Professional",
            "subcategory":"Lawyer & Legal Services",
            "type":"Services"
        }
    ],
    "sg:phone":"+1 407 647 9733",
    "sg:postcode":"32751",
    "sg:province":"FL",
    "sg:tags":[
        "attorney"
    ],
    "wof:name":"James A Edwards",
    "wof:placetype":"venue"
},
  "geometry": {"coordinates":[-81.36434199999999,28.631268],"type":"Point"}
}