{
  "type": "Feature",
  "properties": {
    "iso:country":"US",
    "sg:address":"1539 NW 114th St",
    "sg:city":"Miami",
    "sg:classifiers":[
        {
            "category":"Autos & Motor Vehicles",
            "subcategory":"Boat Sales",
            "type":"Retail Goods"
        }
    ],
    "sg:phone":"+1 305 793 5347",
    "sg:postcode":"33167",
    "sg:province":"FL",
    "sg:tags":[
        "dealer",
        "sales"
    ],
    "wof:name":"Embassy Boats Inc",
    "wof:placetype":"venue"
},
  "geometry": {"coordinates":[-80.224817,25.878885],"type":"Point"}
}