{
  "type": "Feature",
  "properties": {
    "addr:full":"77 Rotonda Cir Rotonda West FL 33947",
    "addr:postcode":"33947",
    "addr:street":"77 Rotonda Cir",
    "iso:country":"US",
    "sg:address":"77 Rotonda Cir",
    "sg:city":"Rotonda West",
    "sg:classifiers":[
        {
            "category":"Building & Trades",
            "subcategory":"Landscaping Services",
            "type":"Services"
        }
    ],
    "sg:phone":"+1 941 697 4901",
    "sg:postcode":"33947",
    "sg:province":"FL",
    "sg:tags":[
        "landscape"
    ],
    "wof:name":"Gardener Bob Landscape Service",
    "wof:placetype":"venue"
},
  "geometry": {"coordinates":[-82.29389500000001,26.883783],"type":"Point"}
}