{
  "type": "Feature",
  "properties": {
    "iso:country":"US",
    "sg:address":"7007 US Hwy 19",
    "sg:city":"New Port Richey",
    "sg:classifiers":[
        {
            "category":"Restaurant",
            "type":"Food & Drink"
        }
    ],
    "sg:phone":"+1 727 848 3333",
    "sg:postcode":"34652",
    "sg:province":"FL",
    "wof:name":"LA Fontana's Authentic",
    "wof:placetype":"venue"
},
  "geometry": {"coordinates":[-82.72791599999999,28.259467],"type":"Point"}
}