{
  "type": "Feature",
  "properties": {
    "iso:country":"US",
    "sg:address":"751 10th St W",
    "sg:city":"Palmetto",
    "sg:classifiers":[
        {
            "category":"Banks & Credit Unions",
            "subcategory":"Financial Services",
            "type":"Services"
        }
    ],
    "sg:phone":"+1 941 723 6749",
    "sg:postcode":"34221",
    "sg:province":"FL",
    "sg:tags":[
        "trust",
        "management"
    ],
    "wof:name":"Umstattd Family Trust",
    "wof:placetype":"venue"
},
  "geometry": {"coordinates":[-82.57248800000001,27.521156],"type":"Point"}
}