{
  "type": "Feature",
  "properties": {
    "iso:country":"US",
    "sg:address":"4237 Rigels Cove Way",
    "sg:city":"Jensen Beach",
    "sg:classifiers":[
        {
            "category":"Professional",
            "subcategory":"Management & Consulting",
            "type":"Services"
        }
    ],
    "sg:phone":"+1 772 334 7002",
    "sg:postcode":"34957",
    "sg:province":"FL",
    "wof:name":"Lundstrom Realty Advisors",
    "wof:placetype":"venue"
},
  "geometry": {"coordinates":[-80.197372,27.25329],"type":"Point"}
}