{
  "type": "Feature",
  "properties": {
    "iso:country":"US",
    "sg:address":"1208 W Ave A",
    "sg:city":"Belle Glade",
    "sg:classifiers":[
        {
            "category":"Freight",
            "type":"Transportation"
        }
    ],
    "sg:phone":"+1 561 996 6312",
    "sg:postcode":"33430",
    "sg:province":"FL",
    "sg:tags":[
        "trucking"
    ],
    "wof:name":"Parrishs Trucking",
    "wof:placetype":"venue"
},
  "geometry": {"coordinates":[-80.679952,26.685821],"type":"Point"}
}