{
  "type": "Feature",
  "properties": {
    "addr:full":"5618 Hollywood Blvd Hollywood FL 33021",
    "addr:housenumber":"5618",
    "addr:postcode":"33021",
    "addr:street":"Hollywood Blvd",
    "iso:country":"US",
    "sg:address":"5618 Hollywood Blvd",
    "sg:city":"Hollywood",
    "sg:classifiers":[
        {
            "category":"Building & Trades",
            "subcategory":"Cleaning & Sanitation",
            "type":"Services"
        }
    ],
    "sg:phone":"+1 954 966 1762",
    "sg:postcode":"33021",
    "sg:province":"FL",
    "sg:tags":[
        "janitorial",
        "contract",
        "basis"
    ],
    "wof:name":"Horizon Maintenance Services",
    "wof:placetype":"venue"
},
  "geometry": {"coordinates":[-80.201385,26.010192],"type":"Point"}
}