{
  "type": "Feature",
  "properties": {
    "addr:full":"1088 NW Federal Hwy Stuart FL 34994",
    "addr:housenumber":"1088",
    "addr:postcode":"34994",
    "addr:street":"Nw Federal Hwy",
    "iso:country":"US",
    "sg:address":"1088 NW Federal Hwy",
    "sg:city":"Stuart",
    "sg:classifiers":[
        {
            "category":"Shopping",
            "subcategory":"Bicycles & Sporting Goods",
            "type":"Retail Goods"
        }
    ],
    "sg:phone":"+1 772 692 1958",
    "sg:postcode":"34994",
    "sg:province":"FL",
    "sg:tags":[
        "gun",
        "gunsmith"
    ],
    "wof:name":"Gun & Archery Pro Shop",
    "wof:placetype":"venue"
},
  "geometry": {"coordinates":[-80.262311,27.218737],"type":"Point"}
}