{
  "type": "Feature",
  "properties": {
    "addr:full":"301 McDonald Rd Plant City FL 33567",
    "addr:housenumber":"301",
    "addr:postcode":"33567",
    "addr:street":"Mcdonald Rd",
    "iso:country":"US",
    "sg:address":"301 McDonald Rd",
    "sg:city":"Plant City",
    "sg:classifiers":[
        {
            "category":"Farming",
            "subcategory":"Livestock Farm",
            "type":"Manufacturing & Wholesale Goods"
        }
    ],
    "sg:phone":"+1 813 737 2569",
    "sg:postcode":"33567",
    "sg:province":"FL",
    "sg:tags":[
        "beef",
        "feedlot",
        "cattle"
    ],
    "wof:name":"Hewbert Snapp Farms",
    "wof:placetype":"venue"
},
  "geometry": {"coordinates":[-82.109009,27.945023],"type":"Point"}
}