{
  "type": "Feature",
  "properties": {
    "addr:full":"1701 Gulfstream Ave Fort Pierce FL 34949",
    "addr:housenumber":"1701",
    "addr:postcode":"34949",
    "addr:street":"Gulfstream Ave",
    "iso:country":"US",
    "sg:address":"1701 Gulfstream Ave",
    "sg:city":"Fort Pierce",
    "sg:classifiers":[
        {
            "category":"Health Services",
            "subcategory":"Doctor",
            "type":"Services"
        }
    ],
    "sg:phone":"+1 772 464 8611",
    "sg:postcode":"34949",
    "sg:province":"FL",
    "sg:tags":[
        "medical"
    ],
    "wof:name":"Ronald W Woody MD",
    "wof:placetype":"venue"
},
  "geometry": {"coordinates":[-80.29299899999999,27.46161],"type":"Point"}
}