{
  "type": "Feature",
  "properties": {
    "addr:full":"1051 Dill Ct Marco Island FL 34145",
    "addr:housenumber":"1051",
    "addr:postcode":"34145",
    "addr:street":"Dill Ct",
    "iso:country":"US",
    "sg:address":"1051 Dill Ct",
    "sg:city":"Marco Island",
    "sg:classifiers":[
        {
            "category":"Building & Trades",
            "subcategory":"Construction",
            "type":"Services"
        }
    ],
    "sg:phone":"+1 239 394 0339",
    "sg:postcode":"34145",
    "sg:province":"FL",
    "sg:tags":[
        "tile",
        "dealer"
    ],
    "wof:name":"Dill & Sons Tile Contractors",
    "wof:placetype":"venue"
},
  "geometry": {"coordinates":[-81.72313200000001,25.933848],"type":"Point"}
}