{
  "type": "Feature",
  "properties": {
    "iso:country":"US",
    "sg:address":"665 N Wildflower Ct",
    "sg:city":"Longwood",
    "sg:classifiers":[
        {
            "category":"Professional",
            "subcategory":"Computer Services",
            "type":"Services"
        }
    ],
    "sg:phone":"+1 407 920 9772",
    "sg:postcode":"32750",
    "sg:province":"FL",
    "sg:tags":[
        "repair"
    ],
    "sg:website":"www.mightymac.net/",
    "wof:name":"Mighty Mac Computer Sales and Service",
    "wof:placetype":"venue"
},
  "geometry": {"coordinates":[-81.360499,28.705359],"type":"Point"}
}