{
  "type": "Feature",
  "properties": {
    "iso:country":"US",
    "sg:address":"5855 Midnight Pass Rd",
    "sg:city":"Sarasota",
    "sg:classifiers":[
        {
            "category":"Building & Trades",
            "subcategory":"Construction",
            "type":"Services"
        }
    ],
    "sg:phone":"+1 941 346 1892",
    "sg:postcode":"34242",
    "sg:province":"FL",
    "sg:tags":[
        "house"
    ],
    "wof:name":"Remodeling & Renovation",
    "wof:placetype":"venue"
},
  "geometry": {"coordinates":[-82.542658,27.264648],"type":"Point"}
}