{
  "type": "Feature",
  "properties": {
    "iso:country":"US",
    "sg:address":"2951 N Powerline Rd",
    "sg:city":"Pompano Beach",
    "sg:classifiers":[
        {
            "category":"Professional",
            "type":"Services"
        }
    ],
    "sg:phone":"+1 954 975 8267",
    "sg:postcode":"33069",
    "sg:province":"FL",
    "sg:tags":[
        "establishment"
    ],
    "wof:name":"USA Diamond Blade Corp",
    "wof:placetype":"venue"
},
  "geometry": {"coordinates":[-80.151954,26.266661],"type":"Point"}
}