{
  "type": "Feature",
  "properties": {
    "addr:full":"848 US Hwy 41 S Inverness FL 34450",
    "addr:housenumber":"848",
    "addr:postcode":"34450",
    "addr:street":"Us Hwy 41 S",
    "iso:country":"US",
    "sg:address":"848 US Hwy 41 S",
    "sg:city":"Inverness",
    "sg:classifiers":[
        {
            "category":"Insurance",
            "subcategory":"Insurance Agent",
            "type":"Services"
        }
    ],
    "sg:phone":"+1 352 637 0052",
    "sg:postcode":"34450",
    "sg:province":"FL",
    "wof:name":"Maria Parker Ins Inc",
    "wof:placetype":"venue"
},
  "geometry": {"coordinates":[-82.318082,28.822438],"type":"Point"}
}