{
  "type": "Feature",
  "properties": {
    "iso:country":"US",
    "sg:address":"4225 W 20th Ave",
    "sg:city":"Hialeah",
    "sg:classifiers":[
        {
            "category":"Health Services",
            "subcategory":"Hospital",
            "type":"Services"
        }
    ],
    "sg:phone":"+1 305 558 9700",
    "sg:postcode":"33012",
    "sg:province":"FL",
    "wof:name":"Southern Winds Hospital",
    "wof:placetype":"venue"
},
  "geometry": {"coordinates":[-80.32240299999999,25.860201],"type":"Point"}
}