{
  "type": "Feature",
  "properties": {
    "iso:country":"US",
    "sg:address":"9674 SW 12th Ct",
    "sg:city":"Boca Raton",
    "sg:classifiers":[
        {
            "category":"Building & Trades",
            "subcategory":"Landscaping Services",
            "type":"Services"
        }
    ],
    "sg:phone":"+1 561 482 3563",
    "sg:postcode":"33428",
    "sg:province":"FL",
    "sg:tags":[
        "landscape",
        "contractor"
    ],
    "wof:name":"Iorizzo Brothers",
    "wof:placetype":"venue"
},
  "geometry": {"coordinates":[-80.197146,26.337291],"type":"Point"}
}