{
  "type": "Feature",
  "properties": {
    "iso:country":"US",
    "sg:address":"2202 21st St W",
    "sg:city":"Bradenton",
    "sg:classifiers":[
        {
            "category":"Retail",
            "subcategory":"Repair Shop",
            "type":"Services"
        }
    ],
    "sg:phone":"+1 941 713 4311",
    "sg:postcode":"34205",
    "sg:province":"FL",
    "sg:tags":[
        "welding"
    ],
    "wof:name":"Boyer's Welding",
    "wof:placetype":"venue"
},
  "geometry": {"coordinates":[-82.58284500000001,27.479128],"type":"Point"}
}