{
  "type": "Feature",
  "properties": {
    "iso:country":"US",
    "sg:address":"4700 Bayou Blvd",
    "sg:city":"Pensacola",
    "sg:classifiers":[
        {
            "category":"Wholesale",
            "subcategory":"Electrical",
            "type":"Manufacturing & Wholesale Goods"
        }
    ],
    "sg:phone":"+1 850 479 1283",
    "sg:postcode":"32503",
    "sg:province":"FL",
    "sg:tags":[
        "photocopying",
        "parts",
        "electronic",
        "profess"
    ],
    "wof:name":"Coastal Business Products",
    "wof:placetype":"venue"
},
  "geometry": {"coordinates":[-87.204548,30.466336],"type":"Point"}
}