{
  "type": "Feature",
  "properties": {
    "addr:full":"3208 Mott Rd Dover FL 33527",
    "addr:housenumber":"3208",
    "addr:postcode":"33527",
    "addr:street":"Mott Rd",
    "iso:country":"US",
    "sg:address":"3208 Mott Rd",
    "sg:city":"Dover",
    "sg:classifiers":[
        {
            "category":"Manufacturing",
            "subcategory":"Textiles",
            "type":"Manufacturing & Wholesale Goods"
        }
    ],
    "sg:phone":"+1 813 659 2414",
    "sg:postcode":"33527",
    "sg:province":"FL",
    "sg:tags":[
        "mill",
        "fabric"
    ],
    "wof:name":"Mtw Fiberglass",
    "wof:placetype":"venue"
},
  "geometry": {"coordinates":[-82.228042,27.993135],"type":"Point"}
}