{
  "type": "Feature",
  "properties": {
    "iso:country":"US",
    "sg:address":"7640 Atlantic Blvd",
    "sg:city":"Jacksonville",
    "sg:classifiers":[
        {
            "category":"Shopping",
            "subcategory":"Used Merchandise",
            "type":"Retail Goods"
        },
        {
            "category":"Shopping",
            "subcategory":"Jewelry",
            "type":"Retail Goods"
        }
    ],
    "sg:phone":"+1 904 721 2555",
    "sg:postcode":"32211",
    "sg:province":"FL",
    "sg:tags":[
        "pawnshop",
        "jeweler"
    ],
    "wof:name":"Cash America Pawn 864",
    "wof:placetype":"venue"
},
  "geometry": {"coordinates":[-81.57836399999999,30.313371],"type":"Point"}
}