{
  "type": "Feature",
  "properties": {
    "iso:country":"US",
    "sg:address":"5526 Baybrook Ave",
    "sg:city":"Orlando",
    "sg:classifiers":[
        {
            "category":"Shopping",
            "subcategory":"Computers & Home Electronics",
            "type":"Retail Goods"
        }
    ],
    "sg:phone":"+1 407 317 4360",
    "sg:postcode":"32819",
    "sg:province":"FL",
    "sg:tags":[
        "equipment",
        "electronic",
        "supply"
    ],
    "wof:name":"Home Theatre Connection",
    "wof:placetype":"venue"
},
  "geometry": {"coordinates":[-81.486007,28.48537],"type":"Point"}
}