{
  "type": "Feature",
  "properties": {
    "addr:full":"6104 Palma del Mar Blvd S St Petersburg FL 33715",
    "addr:housenumber":"6104",
    "addr:postcode":"33715",
    "addr:street":"Palma Del Mar Blvd S",
    "iso:country":"US",
    "sg:address":"6104 Palma del Mar Blvd S",
    "sg:city":"St Petersburg",
    "sg:classifiers":[
        {
            "category":"Building & Trades",
            "subcategory":"Construction",
            "type":"Services"
        }
    ],
    "sg:phone":"+1 727 867 5688",
    "sg:postcode":"33715",
    "sg:province":"FL",
    "sg:tags":[
        "refinishing",
        "cabinet"
    ],
    "wof:name":"Quality Custom Cabinets",
    "wof:placetype":"venue"
},
  "geometry": {"coordinates":[-82.712564,27.711153],"type":"Point"}
}