{
  "type": "Feature",
  "properties": {
    "addr:full":"901 Beecher St Leesburg FL 34748",
    "addr:housenumber":"901",
    "addr:postcode":"34748",
    "addr:street":"Beecher St",
    "iso:country":"US",
    "sg:address":"901 Beecher St",
    "sg:city":"Leesburg",
    "sg:classifiers":[
        {
            "category":"Place Of Worship",
            "subcategory":"Church",
            "type":"Public Place"
        },
        {
            "category":"Place Of Worship",
            "type":"Public Place"
        }
    ],
    "sg:phone":"+1 352 787 7771",
    "sg:postcode":"34748",
    "sg:province":"FL",
    "sg:tags":[
        "testament",
        "christ-new",
        "churches-church",
        "christ"
    ],
    "wof:name":"Church Of Christ Inc",
    "wof:placetype":"venue"
},
  "geometry": {"coordinates":[-81.895752,28.822189],"type":"Point"}
}