{
  "type": "Feature",
  "properties": {
    "addr:full":"616 S Atlantic Ave Ormond Beach FL 32176",
    "addr:housenumber":"616",
    "addr:postcode":"32176",
    "addr:street":"S Atlantic Ave",
    "iso:country":"US",
    "sg:address":"616 S Atlantic Ave",
    "sg:city":"Ormond Beach",
    "sg:classifiers":[
        {
            "category":"Travel",
            "subcategory":"Hotels & Motels",
            "type":"Entertainment"
        },
        {
            "category":"Travel",
            "subcategory":"Travel Agent",
            "type":"Entertainment"
        }
    ],
    "sg:phone":"+1 386 677 3308",
    "sg:postcode":"32176",
    "sg:province":"FL",
    "sg:tags":[
        "information",
        "operation",
        "tourist"
    ],
    "sg:website":"www.daytonawelcomecenter.com",
    "wof:name":"Daytona Welcome Center",
    "wof:placetype":"venue"
},
  "geometry": {"coordinates":[-81.03267099999999,29.27723],"type":"Point"}
}