{
  "type": "Feature",
  "properties": {
    "addr:full":"15585 44th St Live Oak FL 32060",
    "addr:housenumber":"15585",
    "addr:postcode":"32060",
    "addr:street":"44Th St",
    "iso:country":"US",
    "sg:address":"15585 44th St",
    "sg:city":"Live Oak",
    "sg:classifiers":[
        {
            "category":"Real Estate",
            "subcategory":"Developer",
            "type":"Services"
        }
    ],
    "sg:phone":"+1 386 364 6519",
    "sg:postcode":"32060",
    "sg:province":"FL",
    "wof:name":"J G & S Land Development Inc",
    "wof:placetype":"venue"
},
  "geometry": {"coordinates":[-83.06895799999999,30.369926],"type":"Point"}
}