{
  "type": "Feature",
  "properties": {
    "iso:country":"US",
    "sg:address":"16990 SW 96th Ct",
    "sg:city":"Miami",
    "sg:classifiers":[
        {
            "category":"Shopping",
            "subcategory":"Books",
            "type":"Retail Goods"
        }
    ],
    "sg:phone":"+1 305 253 4661",
    "sg:postcode":"33157",
    "sg:province":"FL",
    "wof:name":"South Dade Religious Bookstore",
    "wof:placetype":"venue"
},
  "geometry": {"coordinates":[-80.34808200000001,25.613865],"type":"Point"}
}