{
  "type": "Feature",
  "properties": {
    "iso:country":"US",
    "sg:address":"7534 Dockside St",
    "sg:city":"Winter Park",
    "sg:classifiers":[
        {
            "category":"Utilities",
            "subcategory":"Telephone",
            "type":"Services"
        }
    ],
    "sg:phone":"+1 407 679 5110",
    "sg:postcode":"32792",
    "sg:province":"FL",
    "sg:tags":[
        "communications"
    ],
    "wof:name":"Vivid Concepts Inc",
    "wof:placetype":"venue"
},
  "geometry": {"coordinates":[-81.28576099999999,28.617871],"type":"Point"}
}