{
  "type": "Feature",
  "properties": {
    "iso:country":"US",
    "sg:address":"503 SE 13th Ter",
    "sg:city":"Cape Coral",
    "sg:classifiers":[
        {
            "category":"Restaurant",
            "type":"Food & Drink"
        }
    ],
    "sg:phone":"+1 239 458 0962",
    "sg:postcode":"33990",
    "sg:province":"FL",
    "sg:tags":[
        "eating"
    ],
    "wof:name":"Sheba Home Watch",
    "wof:placetype":"venue"
},
  "geometry": {"coordinates":[-81.964534,26.627656],"type":"Point"}
}