{
  "type": "Feature",
  "properties": {
    "iso:country":"US",
    "sg:address":"2064 Hemmingway Ave",
    "sg:city":"Haines City",
    "sg:classifiers":[
        {
            "category":"Real Estate",
            "subcategory":"Real Estate Agent",
            "type":"Services"
        }
    ],
    "sg:phone":"+1 863 422 6096",
    "sg:postcode":"33844",
    "sg:province":"FL",
    "wof:name":"Owen Rental",
    "wof:placetype":"venue"
},
  "geometry": {"coordinates":[-81.63225,28.128067],"type":"Point"}
}