{
  "type": "Feature",
  "properties": {
    "addr:full":"3501 Hollywood Blvd Hollywood FL 33021",
    "addr:housenumber":"3501",
    "addr:postcode":"33021",
    "addr:street":"Hollywood Blvd",
    "iso:country":"US",
    "sg:address":"3501 Hollywood Blvd",
    "sg:city":"Hollywood",
    "sg:classifiers":[
        {
            "category":"Autos & Motor Vehicles",
            "subcategory":"Fuel & Gas Station",
            "type":"Retail Goods"
        }
    ],
    "sg:phone":"+1 954 987 4510",
    "sg:postcode":"33021",
    "sg:province":"FL",
    "sg:tags":[
        "oil"
    ],
    "wof:name":"Courthouse Chevron",
    "wof:placetype":"venue"
},
  "geometry": {"coordinates":[-80.181213,26.010669],"type":"Point"}
}