{
  "type": "Feature",
  "properties": {
    "iso:country":"US",
    "sg:address":"9508 Navarre Pkwy",
    "sg:city":"Navarre",
    "sg:classifiers":[
        {
            "category":"Shopping",
            "subcategory":"Hobbies, Toys, & Games",
            "type":"Retail Goods"
        }
    ],
    "sg:phone":"+1 850 936 5696",
    "sg:postcode":"32566",
    "sg:province":"FL",
    "sg:tags":[
        "supply"
    ],
    "wof:name":"T & T Movies & Games",
    "wof:placetype":"venue"
},
  "geometry": {"coordinates":[-86.82534699999999,30.409668],"type":"Point"}
}