{
  "type": "Feature",
  "properties": {
    "iso:country":"US",
    "sg:address":"1052 US Hwy 27",
    "sg:city":"Avon Park",
    "sg:classifiers":[
        {
            "category":"Restaurant",
            "type":"Food & Drink"
        }
    ],
    "sg:phone":"+1 863 453 0303",
    "sg:postcode":"33825",
    "sg:province":"FL",
    "wof:name":"Subway Sandwiches & Salads",
    "wof:placetype":"venue"
},
  "geometry": {"coordinates":[-81.514388,27.607402],"type":"Point"}
}