{
  "type": "Feature",
  "properties": {
    "addr:full":"1052 US Hwy 27 Avon Park FL 33825",
    "addr:housenumber":"1052",
    "addr:postcode":"33825",
    "addr:street":"Us Hwy 27",
    "iso:country":"US",
    "sg:address":"1052 US Hwy 27",
    "sg:city":"Avon Park",
    "sg:classifiers":[
        {
            "category":"Restaurant",
            "type":"Food & Drink"
        }
    ],
    "sg:phone":"+1 863 453 0303",
    "sg:postcode":"33825",
    "sg:province":"FL",
    "wof:name":"Subway Sandwiches & Salads",
    "wof:placetype":"venue"
},
  "geometry": {"coordinates":[-81.514388,27.607402],"type":"Point"}
}