{
  "type": "Feature",
  "properties": {
    "addr:full":"997 N Collier Blvd Marco Island FL 34145",
    "addr:housenumber":"997",
    "addr:postcode":"34145",
    "addr:street":"N Collier Blvd",
    "iso:country":"US",
    "sg:address":"997 N Collier Blvd",
    "sg:city":"Marco Island",
    "sg:classifiers":[
        {
            "category":"Professional",
            "subcategory":"Engineering",
            "type":"Services"
        }
    ],
    "sg:phone":"+1 239 642 7280",
    "sg:postcode":"34145",
    "sg:province":"FL",
    "sg:tags":[
        "engineer"
    ],
    "wof:name":"Marchris Engineering LTD",
    "wof:placetype":"venue"
},
  "geometry": {"coordinates":[-81.722486,25.954982],"type":"Point"}
}