{
  "type": "Feature",
  "properties": {
    "iso:country":"US",
    "sg:address":"806 E Jackson St",
    "sg:city":"Tampa",
    "sg:classifiers":[
        {
            "category":"Professional",
            "subcategory":"Lawyer & Legal Services",
            "type":"Services"
        }
    ],
    "sg:phone":"+1 813 273 6646",
    "sg:postcode":"33602",
    "sg:province":"FL",
    "sg:tags":[
        "attorney",
        "criminal",
        "law"
    ],
    "wof:name":"Marc Makholm Pa",
    "wof:placetype":"venue"
},
  "geometry": {"coordinates":[-82.453355,27.948397],"type":"Point"}
}