{
  "type": "Feature",
  "properties": {
    "addr:full":"2870 N Meridian Rd Tallahassee FL 32312",
    "addr:housenumber":"2870",
    "addr:postcode":"32312",
    "addr:street":"N Meridian Rd",
    "iso:country":"US",
    "sg:address":"2870 N Meridian Rd",
    "sg:city":"Tallahassee",
    "sg:classifiers":[
        {
            "category":"Organizations",
            "subcategory":"Religious Organization",
            "type":"Services"
        }
    ],
    "sg:phone":"+1 850 422 3657",
    "sg:postcode":"32312",
    "sg:province":"FL",
    "sg:tags":[
        "church"
    ],
    "sg:website":"www.meridianwoods.org",
    "wof:name":"Church Of Christ-Meridian Wood",
    "wof:placetype":"venue"
},
  "geometry": {"coordinates":[-84.277361,30.48056],"type":"Point"}
}