{
  "type": "Feature",
  "properties": {
    "addr:full":"4040 NE 2nd Ave Miami FL 33137",
    "addr:housenumber":"4040",
    "addr:postcode":"33137",
    "addr:street":"Ne 2Nd Ave",
    "iso:country":"US",
    "sg:address":"4040 NE 2nd Ave",
    "sg:city":"Miami",
    "sg:classifiers":[
        {
            "category":"Real Estate",
            "subcategory":"Real Estate Agent",
            "type":"Services"
        }
    ],
    "sg:phone":"+1 305 373 4441",
    "sg:postcode":"33137",
    "sg:province":"FL",
    "sg:tags":[
        "broker"
    ],
    "wof:name":"Maurice Gelina and Associates",
    "wof:placetype":"venue"
},
  "geometry": {"coordinates":[-80.191485,25.813847],"type":"Point"}
}