{
  "type": "Feature",
  "properties": {
    "iso:country":"US",
    "sg:address":"960 Chalmer Dr",
    "sg:city":"Marco Island",
    "sg:classifiers":[
        {
            "category":"Autos & Motor Vehicles",
            "subcategory":"Auto Supplies",
            "type":"Retail Goods"
        }
    ],
    "sg:phone":"+1 239 393 9111",
    "sg:postcode":"34145",
    "sg:province":"FL",
    "sg:tags":[
        "automobile",
        "stereo",
        "radio"
    ],
    "wof:name":"Pro Design",
    "wof:placetype":"venue"
},
  "geometry": {"coordinates":[-81.72330599999999,25.956751],"type":"Point"}
}