{
  "type": "Feature",
  "properties": {
    "iso:country":"US",
    "sg:address":"1730 Creighton Rd",
    "sg:city":"Pensacola",
    "sg:classifiers":[
        {
            "category":"Professional",
            "subcategory":"Business Services",
            "type":"Services"
        }
    ],
    "sg:phone":"+1 850 471 3357",
    "sg:postcode":"32504",
    "sg:province":"FL",
    "sg:tags":[
        "interior",
        "consultant",
        "design",
        "decorator"
    ],
    "wof:name":"West Florida Interior",
    "wof:placetype":"venue"
},
  "geometry": {"coordinates":[-87.208943,30.4957],"type":"Point"}
}