{
  "type": "Feature",
  "properties": {
    "addr:full":"18725 5th Ave Orlando FL 32820",
    "addr:housenumber":"18725",
    "addr:postcode":"32820",
    "addr:street":"5Th Ave",
    "iso:country":"US",
    "sg:address":"18725 5th Ave",
    "sg:city":"Orlando",
    "sg:classifiers":[
        {
            "category":"Wholesale",
            "subcategory":"Scrap",
            "type":"Manufacturing & Wholesale Goods"
        }
    ],
    "sg:phone":"+1 407 568 7636",
    "sg:postcode":"32820",
    "sg:province":"FL",
    "sg:tags":[
        "material"
    ],
    "wof:name":"ABC Towing Inc",
    "wof:placetype":"venue"
},
  "geometry": {"coordinates":[-81.099615,28.554795],"type":"Point"}
}