{
  "type": "Feature",
  "properties": {
    "addr:full":"16000 Pines Blvd Pembroke Pines FL 33027",
    "addr:housenumber":"16000",
    "addr:postcode":"33027",
    "addr:street":"Pines Blvd",
    "iso:country":"US",
    "sg:address":"16000 Pines Blvd",
    "sg:city":"Pembroke Pines",
    "sg:classifiers":[
        {
            "category":"Government",
            "subcategory":"Post Office",
            "type":"Public Place"
        }
    ],
    "sg:phone":"+1 954 000 1111",
    "sg:postcode":"33027",
    "sg:province":"FL",
    "sg:website":"www.usps.gov",
    "wof:name":"US Post Office",
    "wof:placetype":"venue"
},
  "geometry": {"coordinates":[-80.36192200000001,26.007744],"type":"Point"}
}