{
  "type": "Feature",
  "properties": {
    "iso:country":"US",
    "sg:address":"4150 SW 47th Ave",
    "sg:city":"Davie",
    "sg:classifiers":[
        {
            "category":"Manufacturing",
            "subcategory":"Metals",
            "type":"Manufacturing & Wholesale Goods"
        }
    ],
    "sg:phone":"+1 954 583 5255",
    "sg:postcode":"33314",
    "sg:province":"FL",
    "sg:tags":[
        "scrap",
        "product"
    ],
    "wof:name":"Danielle Salvage",
    "wof:placetype":"venue"
},
  "geometry": {"coordinates":[-80.21011900000001,26.073162],"type":"Point"}
}