{
  "type": "Feature",
  "properties": {
    "iso:country":"US",
    "sg:address":"1195 NW 97th Ave",
    "sg:city":"Doral",
    "sg:classifiers":[
        {
            "category":"Manufacturing",
            "subcategory":"Electronics",
            "type":"Manufacturing & Wholesale Goods"
        },
        {
            "category":"Wholesale",
            "subcategory":"Electrical",
            "type":"Manufacturing & Wholesale Goods"
        }
    ],
    "sg:phone":"+1 305 592 2616",
    "sg:postcode":"33172",
    "sg:province":"FL",
    "sg:tags":[
        "equipment",
        "parts",
        "electronic",
        "supply"
    ],
    "wof:name":"Nippon America",
    "wof:placetype":"venue"
},
  "geometry": {"coordinates":[-80.352564,25.784297],"type":"Point"}
}