{
  "type": "Feature",
  "properties": {
    "iso:country":"US",
    "sg:address":"924 SW 67th Ave",
    "sg:city":"Miami",
    "sg:classifiers":[
        {
            "category":"Building & Trades",
            "subcategory":"Construction",
            "type":"Services"
        }
    ],
    "sg:phone":"+1 305 887 7702",
    "sg:postcode":"33144",
    "sg:province":"FL",
    "sg:tags":[
        "contractor"
    ],
    "wof:name":"E & C Counter Tops Inc",
    "wof:placetype":"venue"
},
  "geometry": {"coordinates":[-80.30393100000001,25.761565],"type":"Point"}
}