{
  "type": "Feature",
  "properties": {
    "addr:full":"2551 Hammondville Rd Pompano Beach FL 33069",
    "addr:housenumber":"2551",
    "addr:postcode":"33069",
    "addr:street":"Hammondville Rd",
    "iso:country":"US",
    "sg:address":"2551 Hammondville Rd",
    "sg:city":"Pompano Beach",
    "sg:classifiers":[
        {
            "category":"Wholesale",
            "subcategory":"Machinery & Supplies",
            "type":"Manufacturing & Wholesale Goods"
        }
    ],
    "sg:phone":"+1 954 972 3400",
    "sg:postcode":"33069",
    "sg:province":"FL",
    "sg:tags":[
        "industrial",
        "truck"
    ],
    "wof:name":"Worldwide Truck Sales Inc",
    "wof:placetype":"venue"
},
  "geometry": {"coordinates":[-80.156555,26.245349],"type":"Point"}
}