{
  "type": "Feature",
  "properties": {
    "iso:country":"US",
    "sg:address":"830 School St",
    "sg:city":"Brooksville",
    "sg:classifiers":[
        {
            "category":"Retail",
            "subcategory":"Funeral Services",
            "type":"Services"
        }
    ],
    "sg:phone":"+1 352 796 7033",
    "sg:postcode":"34601",
    "sg:province":"FL",
    "sg:tags":[
        "director"
    ],
    "wof:name":"Cason Funeral & Cremation Svc",
    "wof:placetype":"venue"
},
  "geometry": {"coordinates":[-82.380151,28.544871],"type":"Point"}
}