{
  "type": "Feature",
  "properties": {
    "iso:country":"US",
    "sg:address":"939 N New Warrington Rd",
    "sg:city":"Pensacola",
    "sg:classifiers":[
        {
            "category":"Personal",
            "subcategory":"Beauty Salon",
            "type":"Services"
        },
        {
            "category":"Personal",
            "subcategory":"Tanning Parlor",
            "type":"Services"
        }
    ],
    "sg:phone":"+1 850 457 6092",
    "sg:postcode":"32506",
    "sg:province":"FL",
    "wof:name":"Guys' & Dolls' Hair & Tanning Salon",
    "wof:placetype":"venue"
},
  "geometry": {"coordinates":[-87.2736,30.423775],"type":"Point"}
}