{
  "type": "Feature",
  "properties": {
    "iso:country":"US",
    "sg:address":"104 E Washington St Ste H",
    "sg:city":"Quincy",
    "sg:classifiers":[
        {
            "category":"Personal",
            "subcategory":"Beauty Salon",
            "type":"Services"
        }
    ],
    "sg:phone":"+1 850 875 2351",
    "sg:postcode":"32351",
    "sg:province":"FL",
    "sg:website":"http://www.studiojm.com",
    "wof:name":"Studio J M",
    "wof:placetype":"venue"
},
  "geometry": {"coordinates":[-84.575739,30.589201],"type":"Point"}
}