{
  "type": "Feature",
  "properties": {
    "addr:full":"3491 23rd Ave SW Naples FL 34117",
    "addr:housenumber":"3491",
    "addr:postcode":"34117",
    "addr:street":"23Rd Ave Sw",
    "iso:country":"US",
    "sg:address":"3491 23rd Ave SW",
    "sg:city":"Naples",
    "sg:classifiers":[
        {
            "category":"Building & Trades",
            "subcategory":"Pest Control",
            "type":"Services"
        }
    ],
    "sg:phone":"+1 239 261 0953",
    "sg:postcode":"34117",
    "sg:province":"FL",
    "sg:tags":[
        "extermination"
    ],
    "wof:name":"Brackett's Pest Control",
    "wof:placetype":"venue"
},
  "geometry": {"coordinates":[-81.676993,26.187123],"type":"Point"}
}