{
  "type": "Feature",
  "properties": {
    "iso:country":"US",
    "sg:address":"3101 NW 47th Ter",
    "sg:city":"Fort Lauderdale",
    "sg:classifiers":[
        {
            "category":"Building & Trades",
            "subcategory":"Construction",
            "type":"Services"
        }
    ],
    "sg:phone":"+1 954 675 1392",
    "sg:postcode":"33319",
    "sg:province":"FL",
    "sg:tags":[
        "hanging",
        "contractor"
    ],
    "wof:name":"Richie Painting",
    "wof:placetype":"venue"
},
  "geometry": {"coordinates":[-80.21235900000001,26.168165],"type":"Point"}
}