{
  "type": "Feature",
  "properties": {
    "iso:country":"US",
    "sg:address":"125 Richland Ave",
    "sg:city":"Merritt Island",
    "sg:classifiers":[
        {
            "category":"Building & Trades",
            "subcategory":"Landscaping Services",
            "type":"Services"
        }
    ],
    "sg:phone":"+1 321 449 9217",
    "sg:postcode":"32953",
    "sg:province":"FL",
    "wof:name":"Nick Watson Lawn Mtc",
    "wof:placetype":"venue"
},
  "geometry": {"coordinates":[-80.69772399999999,28.369151],"type":"Point"}
}