{
  "type": "Feature",
  "properties": {
    "iso:country":"US",
    "sg:address":"511 Wynnehurst St",
    "sg:city":"Pensacola",
    "sg:classifiers":[
        {
            "category":"Manufacturing",
            "subcategory":"Glass & Minerals",
            "type":"Manufacturing & Wholesale Goods"
        },
        {
            "category":"Building & Trades",
            "subcategory":"Construction",
            "type":"Services"
        }
    ],
    "sg:phone":"+1 850 434 0976",
    "sg:postcode":"32503",
    "sg:province":"FL",
    "sg:tags":[
        "contractor",
        "product",
        "made",
        "prod",
        "mfg"
    ],
    "wof:name":"Glass Contractors Inc",
    "wof:placetype":"venue"
},
  "geometry": {"coordinates":[-87.21960199999999,30.462617],"type":"Point"}
}