{
  "type": "Feature",
  "properties": {
    "addr:full":"1383 Nimitz Ct Rockledge FL 32955",
    "addr:housenumber":"1383",
    "addr:postcode":"32955",
    "addr:street":"Nimitz Ct",
    "iso:country":"US",
    "sg:address":"1383 Nimitz Ct",
    "sg:city":"Rockledge",
    "sg:classifiers":[
        {
            "category":"Professional",
            "subcategory":"Accounting & Tax Preparation",
            "type":"Services"
        }
    ],
    "sg:phone":"+1 321 690 3300",
    "sg:postcode":"32955",
    "sg:province":"FL",
    "sg:tags":[
        "return",
        "filing"
    ],
    "wof:name":"Liberty Tax Svc",
    "wof:placetype":"venue"
},
  "geometry": {"coordinates":[-80.736768,28.293222],"type":"Point"}
}