{
  "type": "Feature",
  "properties": {
    "addr:full":"1900 NW 49th St Miami FL 33142",
    "addr:housenumber":"1900",
    "addr:postcode":"33142",
    "addr:street":"Nw 49Th St",
    "iso:country":"US",
    "sg:address":"1900 NW 49th St",
    "sg:city":"Miami",
    "sg:classifiers":[
        {
            "category":"Banks & Credit Unions",
            "subcategory":"Bank",
            "type":"Services"
        }
    ],
    "sg:phone":"+1 305 364 2450",
    "sg:postcode":"33142",
    "sg:province":"FL",
    "sg:website":"www.wachovia.com",
    "wof:name":"Wachovia",
    "wof:placetype":"venue"
},
  "geometry": {"coordinates":[-80.2286,25.82],"type":"Point"}
}