{
  "type": "Feature",
  "properties": {
    "addr:full":"5900 N Port Blvd North Port FL 34287",
    "addr:housenumber":"5900",
    "addr:postcode":"34287",
    "addr:street":"N Port Blvd",
    "iso:country":"US",
    "sg:address":"5900 N Port Blvd",
    "sg:city":"North Port",
    "sg:classifiers":[
        {
            "category":"Retail",
            "subcategory":"Funeral Services",
            "type":"Services"
        }
    ],
    "sg:phone":"+1 941 426 2880",
    "sg:postcode":"34287",
    "sg:province":"FL",
    "sg:tags":[
        "director"
    ],
    "wof:name":"Farley Funeral Home",
    "wof:placetype":"venue"
},
  "geometry": {"coordinates":[-82.235523,27.044971],"type":"Point"}
}