{
  "type": "Feature",
  "properties": {
    "addr:full":"3123 Ocean Dr Vero Beach FL 32963",
    "addr:housenumber":"3123",
    "addr:postcode":"32963",
    "addr:street":"Ocean Dr",
    "iso:country":"US",
    "sg:address":"3123 Ocean Dr",
    "sg:city":"Vero Beach",
    "sg:classifiers":[
        {
            "category":"Shopping",
            "subcategory":"Gifts & Souvenirs",
            "type":"Retail Goods"
        }
    ],
    "sg:phone":"+1 772 562 6459",
    "sg:postcode":"32963",
    "sg:province":"FL",
    "sg:tags":[
        "collectible"
    ],
    "wof:name":"Forever Young Gifts & Creation",
    "wof:placetype":"venue"
},
  "geometry": {"coordinates":[-80.356038,27.651273],"type":"Point"}
}