{
  "type": "Feature",
  "properties": {
    "iso:country":"US",
    "sg:address":"2361 Covington Dr",
    "sg:city":"Clearwater",
    "sg:classifiers":[
        {
            "category":"Insurance",
            "subcategory":"Insurance Agent",
            "type":"Services"
        }
    ],
    "sg:phone":"+1 727 669 0309",
    "sg:postcode":"33763",
    "sg:province":"FL",
    "wof:name":"Lawrence R Meinster",
    "wof:placetype":"venue"
},
  "geometry": {"coordinates":[-82.738546,28.007866],"type":"Point"}
}