{
  "type": "Feature",
  "properties": {
    "addr:full":"2258 NW 82nd Ave Doral FL 33122",
    "addr:housenumber":"2258",
    "addr:postcode":"33122",
    "addr:street":"Nw 82Nd Ave",
    "iso:country":"US",
    "sg:address":"2258 NW 82nd Ave",
    "sg:city":"Doral",
    "sg:classifiers":[
        {
            "category":"Shopping",
            "subcategory":"Music",
            "type":"Retail Goods"
        }
    ],
    "sg:phone":"+1 786 399 9934",
    "sg:postcode":"33122",
    "sg:province":"FL",
    "sg:tags":[
        "used",
        "tapes",
        "vintage",
        "records",
        "cd's",
        "store"
    ],
    "wof:name":"Audiomaster",
    "wof:placetype":"venue"
},
  "geometry": {"coordinates":[-80.32899,25.794748],"type":"Point"}
}