{
  "type": "Feature",
  "properties": {
    "iso:country":"US",
    "sg:address":"16655 Crossandra Ln",
    "sg:city":"Spring Hill",
    "sg:classifiers":[
        {
            "category":"Building & Trades",
            "subcategory":"Construction",
            "type":"Services"
        }
    ],
    "sg:phone":"+1 727 856 3029",
    "sg:postcode":"34610",
    "sg:province":"FL",
    "sg:tags":[
        "contractor"
    ],
    "wof:name":"Touch of Class Marble & Tile",
    "wof:placetype":"venue"
},
  "geometry": {"coordinates":[-82.542429,28.414684],"type":"Point"}
}