{
  "type": "Feature",
  "properties": {
    "addr:full":"401 NW 127th Ave Fort Lauderdale FL 33325",
    "addr:housenumber":"401",
    "addr:postcode":"33325",
    "addr:street":"Nw 127Th Ave",
    "iso:country":"US",
    "sg:address":"401 NW 127th Ave",
    "sg:city":"Fort Lauderdale",
    "sg:classifiers":[
        {
            "category":"Organizations",
            "subcategory":"Membership Organization",
            "type":"Services"
        }
    ],
    "sg:phone":"+1 954 472 2368",
    "sg:postcode":"33325",
    "sg:province":"FL",
    "wof:name":"Wicklander Foundation Inc",
    "wof:placetype":"venue"
},
  "geometry": {"coordinates":[-80.318653,26.123821],"type":"Point"}
}