{
  "type": "Feature",
  "properties": {
    "addr:full":"2200 Jackson St Hollywood FL 33020",
    "addr:housenumber":"2200",
    "addr:postcode":"33020",
    "addr:street":"Jackson St",
    "iso:country":"US",
    "sg:address":"2200 Jackson St",
    "sg:city":"Hollywood",
    "sg:classifiers":[
        {
            "category":"Wholesale",
            "subcategory":"Stationery",
            "type":"Manufacturing & Wholesale Goods"
        }
    ],
    "sg:phone":"+1 954 920 0224",
    "sg:postcode":"33020",
    "sg:province":"FL",
    "sg:tags":[
        "product",
        "paper"
    ],
    "wof:name":"Automated Paper Converters",
    "wof:placetype":"venue"
},
  "geometry": {"coordinates":[-80.152715,26.008696],"type":"Point"}
}