{
  "type": "Feature",
  "properties": {
    "addr:full":"585 S Ronald Reagan Blvd Longwood FL 32750",
    "addr:housenumber":"585",
    "addr:postcode":"32750",
    "addr:street":"S Ronald Reagan Blvd",
    "iso:country":"US",
    "sg:address":"585 S Ronald Reagan Blvd",
    "sg:city":"Longwood",
    "sg:classifiers":[
        {
            "category":"Building & Trades",
            "subcategory":"Construction",
            "type":"Services"
        }
    ],
    "sg:phone":"+1 407 339 8811",
    "sg:postcode":"32750",
    "sg:province":"FL",
    "sg:tags":[
        "contractor"
    ],
    "wof:name":"Sutherland Construction",
    "wof:placetype":"venue"
},
  "geometry": {"coordinates":[-81.345901,28.691401],"type":"Point"}
}