{
  "type": "Feature",
  "properties": {
    "iso:country":"US",
    "sg:address":"425 Cross St",
    "sg:city":"Punta Gorda",
    "sg:classifiers":[
        {
            "category":"Shopping",
            "type":"Retail Goods"
        }
    ],
    "sg:phone":"+1 941 637 8551",
    "sg:postcode":"33950",
    "sg:province":"FL",
    "sg:tags":[
        "trophy",
        "medal",
        "award"
    ],
    "sg:website":"www.acp.com",
    "wof:name":"Awardcrafters",
    "wof:placetype":"venue"
},
  "geometry": {"coordinates":[-82.050174,26.932087],"type":"Point"}
}