{
  "type": "Feature",
  "properties": {
    "addr:full":"805 Levitt Pkwy Rockledge FL 32955",
    "addr:housenumber":"805",
    "addr:postcode":"32955",
    "addr:street":"Levitt Pkwy",
    "iso:country":"US",
    "sg:address":"805 Levitt Pkwy",
    "sg:city":"Rockledge",
    "sg:classifiers":[
        {
            "category":"Building & Trades",
            "subcategory":"Construction",
            "type":"Services"
        }
    ],
    "sg:phone":"+1 321 631 3528",
    "sg:postcode":"32955",
    "sg:province":"FL",
    "sg:tags":[
        "contractor"
    ],
    "wof:name":"Shawn Jeffords Roof Cleaning",
    "wof:placetype":"venue"
},
  "geometry": {"coordinates":[-80.724627,28.315617],"type":"Point"}
}