{
  "type": "Feature",
  "properties": {
    "addr:full":"12844 SW 48th Ter Miami FL 33175",
    "addr:housenumber":"12844",
    "addr:postcode":"33175",
    "addr:street":"Sw 48Th Ter",
    "iso:country":"US",
    "sg:address":"12844 SW 48th Ter",
    "sg:city":"Miami",
    "sg:classifiers":[
        {
            "category":"Retail",
            "subcategory":"Portrait Studio",
            "type":"Services"
        },
        {
            "category":"Professional",
            "subcategory":"Art Services",
            "type":"Services"
        }
    ],
    "sg:phone":"+1 305 553 4737",
    "sg:postcode":"33175",
    "sg:province":"FL",
    "sg:tags":[
        "rental",
        "photographers-portrait",
        "photographic",
        "darkroom"
    ],
    "wof:name":"Chacon Photo Studio",
    "wof:placetype":"venue"
},
  "geometry": {"coordinates":[-80.401966,25.720762],"type":"Point"}
}