{
  "type": "Feature",
  "properties": {
    "addr:full":"111 E Linebaugh Ave Tampa FL 33612",
    "addr:housenumber":"111",
    "addr:postcode":"33612",
    "addr:street":"E Linebaugh Ave",
    "iso:country":"US",
    "sg:address":"111 E Linebaugh Ave",
    "sg:city":"Tampa",
    "sg:classifiers":[
        {
            "category":"Retail",
            "subcategory":"Auto Rental",
            "type":"Services"
        }
    ],
    "sg:phone":"+1 813 935 3578",
    "sg:postcode":"33612",
    "sg:province":"FL",
    "sg:tags":[
        "mobile",
        "home",
        "leasing"
    ],
    "wof:name":"Jersey Mobile Home Park",
    "wof:placetype":"venue"
},
  "geometry": {"coordinates":[-82.455603,28.039881],"type":"Point"}
}