{
  "type": "Feature",
  "properties": {
    "iso:country":"US",
    "sg:address":"2920 E Busch Blvd",
    "sg:city":"Tampa",
    "sg:classifiers":[
        {
            "category":"Restaurant",
            "type":"Food & Drink"
        }
    ],
    "sg:phone":"+1 813 935 4535",
    "sg:postcode":"33612",
    "sg:province":"FL",
    "wof:name":"Busch's Sports Bar & Grill",
    "wof:placetype":"venue"
},
  "geometry": {"coordinates":[-82.42652099999999,28.032646],"type":"Point"}
}