{
  "type": "Feature",
  "properties": {
    "iso:country":"US",
    "sg:address":"1280 Biscayne Blvd",
    "sg:city":"Deland",
    "sg:classifiers":[
        {
            "category":"Wholesale",
            "subcategory":"Non-durable Goods",
            "type":"Manufacturing & Wholesale Goods"
        }
    ],
    "sg:phone":"+1 386 734 7923",
    "sg:postcode":"32724",
    "sg:province":"FL",
    "sg:tags":[
        "pet",
        "supply"
    ],
    "wof:name":"Pads",
    "wof:placetype":"venue"
},
  "geometry": {"coordinates":[-81.282005,29.059512],"type":"Point"}
}