{
  "type": "Feature",
  "properties": {
    "iso:country":"US",
    "sg:address":"15254 SW 112th Ct",
    "sg:city":"Miami",
    "sg:classifiers":[
        {
            "category":"Restaurant",
            "type":"Food & Drink"
        }
    ],
    "sg:phone":"+1 305 256 2688",
    "sg:postcode":"33157",
    "sg:province":"FL",
    "sg:tags":[
        "sweet",
        "pie",
        "catering"
    ],
    "wof:name":"Good Old Gashions Sweet Potato",
    "wof:placetype":"venue"
},
  "geometry": {"coordinates":[-80.374978,25.626798],"type":"Point"}
}