{
  "type": "Feature",
  "properties": {
    "iso:country":"US",
    "sg:address":"121 Nokomis Ave S",
    "sg:city":"Venice",
    "sg:classifiers":[
        {
            "category":"Building & Trades",
            "subcategory":"Landscaping Services",
            "type":"Services"
        }
    ],
    "sg:phone":"+1 941 486 1200",
    "sg:postcode":"34285",
    "sg:province":"FL",
    "sg:tags":[
        "lawn",
        "stump",
        "tree",
        "grinding",
        "removal",
        "maintenance",
        "gardener"
    ],
    "wof:name":"Affordable Lawn & Tree Service",
    "wof:placetype":"venue"
},
  "geometry": {"coordinates":[-82.445421,27.099681],"type":"Point"}
}