{
  "type": "Feature",
  "properties": {
    "iso:country":"US",
    "sg:address":"523 N 7th St",
    "sg:city":"Haines City",
    "sg:classifiers":[
        {
            "category":"Food & Beverages",
            "subcategory":"Groceries & Convenience Stores",
            "type":"Retail Goods"
        }
    ],
    "sg:phone":"+1 863 422 4102",
    "sg:postcode":"33844",
    "sg:province":"FL",
    "wof:name":"Sirmons Grocery",
    "wof:placetype":"venue"
},
  "geometry": {"coordinates":[-81.625721,28.114169],"type":"Point"}
}