{
  "type": "Feature",
  "properties": {
    "iso:country":"US",
    "sg:address":"881 Sumter Rd E",
    "sg:city":"West Palm Beach",
    "sg:classifiers":[
        {
            "category":"Professional",
            "type":"Services"
        }
    ],
    "sg:phone":"+1 561 640 7768",
    "sg:postcode":"33415",
    "sg:province":"FL",
    "wof:name":"Amworld",
    "wof:placetype":"venue"
},
  "geometry": {"coordinates":[-80.125777,26.664179],"type":"Point"}
}