{
  "type": "Feature",
  "properties": {
    "addr:full":"1130 E 15th St Panama City FL 32405",
    "addr:housenumber":"1130",
    "addr:postcode":"32405",
    "addr:street":"E 15Th St",
    "iso:country":"US",
    "sg:address":"1130 E 15th St",
    "sg:city":"Panama City",
    "sg:classifiers":[
        {
            "category":"Retail",
            "subcategory":"Repair Shop",
            "type":"Services"
        }
    ],
    "sg:phone":"+1 850 785 1261",
    "sg:postcode":"32405",
    "sg:province":"FL",
    "sg:tags":[
        "scooter",
        "motorcycle",
        "motor"
    ],
    "wof:name":"Ironhorse Cycle LLC",
    "wof:placetype":"venue"
},
  "geometry": {"coordinates":[-85.64195100000001,30.175008],"type":"Point"}
}