{
  "type": "Feature",
  "properties": {
    "addr:full":"9911 Miramar Pkwy Hollywood FL 33025",
    "addr:housenumber":"9911",
    "addr:postcode":"33025",
    "addr:street":"Miramar Pkwy",
    "iso:country":"US",
    "sg:address":"9911 Miramar Pkwy",
    "sg:city":"Hollywood",
    "sg:classifiers":[
        {
            "category":"Personal",
            "subcategory":"Beauty Salon",
            "type":"Services"
        }
    ],
    "sg:phone":"+1 954 433 9888",
    "sg:postcode":"33025",
    "sg:province":"FL",
    "sg:tags":[
        "shop"
    ],
    "wof:name":"Vans Nail Salon",
    "wof:placetype":"venue"
},
  "geometry": {"coordinates":[-80.276383,25.980814],"type":"Point"}
}