{
  "type": "Feature",
  "properties": {
    "iso:country":"US",
    "sg:address":"11 Ridgeway Ave",
    "sg:city":"Cocoa",
    "sg:classifiers":[
        {
            "category":"Autos & Motor Vehicles",
            "subcategory":"Boat Sales",
            "type":"Retail Goods"
        }
    ],
    "sg:phone":"+1 321 633 9280",
    "sg:postcode":"32922",
    "sg:province":"FL",
    "sg:tags":[
        "yacht"
    ],
    "wof:name":"Cruising Outfitters",
    "wof:placetype":"venue"
},
  "geometry": {"coordinates":[-80.73042599999999,28.35769],"type":"Point"}
}