{
  "type": "Feature",
  "properties": {
    "iso:country":"US",
    "sg:address":"2000 N Ponce de Leon Blvd",
    "sg:city":"Saint Augustine",
    "sg:classifiers":[
        {
            "category":"Food & Beverages",
            "subcategory":"Fruits & Vegetables",
            "type":"Retail Goods"
        }
    ],
    "sg:phone":"+1 904 829 5378",
    "sg:postcode":"32084",
    "sg:province":"FL",
    "wof:name":"Indian River Fruit Market",
    "wof:placetype":"venue"
},
  "geometry": {"coordinates":[-81.322745,29.912042],"type":"Point"}
}