{
  "type": "Feature",
  "properties": {
    "addr:full":"7064 NW 50th St Miami FL 33166",
    "addr:housenumber":"7064",
    "addr:postcode":"33166",
    "addr:street":"Nw 50Th St",
    "iso:country":"US",
    "sg:address":"7064 NW 50th St",
    "sg:city":"Miami",
    "sg:classifiers":[
        {
            "category":"Wholesale",
            "subcategory":"Medical Equipment & Supplies",
            "type":"Manufacturing & Wholesale Goods"
        }
    ],
    "sg:phone":"+1 305 715 7244",
    "sg:postcode":"33166",
    "sg:province":"FL",
    "sg:tags":[
        "dental",
        "clinic"
    ],
    "wof:name":"Global Dental Inc",
    "wof:placetype":"venue"
},
  "geometry": {"coordinates":[-80.311864,25.818908],"type":"Point"}
}