{
  "type": "Feature",
  "properties": {
    "iso:country":"US",
    "sg:address":"1 N Eustis St",
    "sg:city":"Eustis",
    "sg:classifiers":[
        {
            "category":"Restaurant",
            "type":"Food & Drink"
        }
    ],
    "sg:phone":"+1 352 357 2311",
    "sg:postcode":"32726",
    "sg:province":"FL",
    "sg:tags":[
        "eating"
    ],
    "wof:name":"Eustis Street Grill",
    "wof:placetype":"venue"
},
  "geometry": {"coordinates":[-81.684619,28.85363],"type":"Point"}
}