{
  "type": "Feature",
  "properties": {
    "iso:country":"US",
    "sg:address":"115 Racetrack Rd NE",
    "sg:city":"Fort Walton Beach",
    "sg:classifiers":[
        {
            "category":"Banks & Credit Unions",
            "subcategory":"Bank",
            "type":"Services"
        }
    ],
    "sg:phone":"+1 850 244 4355",
    "sg:postcode":"32547",
    "sg:province":"FL",
    "sg:tags":[
        "personal",
        "institution"
    ],
    "wof:name":"Harrison Finance",
    "wof:placetype":"venue"
},
  "geometry": {"coordinates":[-86.60802700000001,30.446408],"type":"Point"}
}