{
  "type": "Feature",
  "properties": {
    "addr:full":"4800 Manatee Ave W Bradenton FL 34209",
    "addr:housenumber":"4800",
    "addr:postcode":"34209",
    "addr:street":"Manatee Ave W",
    "iso:country":"US",
    "sg:address":"4800 Manatee Ave W",
    "sg:city":"Bradenton",
    "sg:classifiers":[
        {
            "category":"Personal",
            "subcategory":"Beauty Salon",
            "type":"Services"
        }
    ],
    "sg:phone":"+1 941 746 1699",
    "sg:postcode":"34209",
    "sg:province":"FL",
    "wof:name":"Freestyles Pools & Spas",
    "wof:placetype":"venue"
},
  "geometry": {"coordinates":[-82.609131,27.49584],"type":"Point"}
}