{
  "type": "Feature",
  "properties": {
    "iso:country":"US",
    "sg:address":"8397 Baymeadows Rd",
    "sg:city":"Jacksonville",
    "sg:classifiers":[
        {
            "category":"Autos & Motor Vehicles",
            "subcategory":"Auto Supplies",
            "type":"Retail Goods"
        }
    ],
    "sg:phone":"+1 904 731 2066",
    "sg:postcode":"32256",
    "sg:province":"FL",
    "sg:tags":[
        "automotive",
        "center",
        "tire"
    ],
    "wof:name":"Baymeadows Tire Center",
    "wof:placetype":"venue"
},
  "geometry": {"coordinates":[-81.584317,30.220823],"type":"Point"}
}