{
  "type": "Feature",
  "properties": {
    "addr:full":"6073 NW 167th St Hialeah FL 33015",
    "addr:housenumber":"6073",
    "addr:postcode":"33015",
    "addr:street":"Nw 167Th St",
    "iso:country":"US",
    "sg:address":"6073 NW 167th St",
    "sg:city":"Hialeah",
    "sg:classifiers":[
        {
            "category":"Banks & Credit Unions",
            "subcategory":"Bank",
            "type":"Services"
        }
    ],
    "sg:phone":"+1 305 557 7169",
    "sg:postcode":"33015",
    "sg:province":"FL",
    "sg:tags":[
        "loan",
        "real estate"
    ],
    "wof:name":"NIC America",
    "wof:placetype":"venue"
},
  "geometry": {"coordinates":[-80.298141,25.925193],"type":"Point"}
}