{
  "type": "Feature",
  "properties": {
    "iso:country":"US",
    "sg:address":"111 Majorca Ave",
    "sg:city":"Coral Gables",
    "sg:classifiers":[
        {
            "category":"Health Services",
            "subcategory":"Doctor",
            "type":"Services"
        }
    ],
    "sg:phone":"+1 305 448 8325",
    "sg:postcode":"33134",
    "sg:province":"FL",
    "sg:tags":[
        "psychiatrist"
    ],
    "wof:name":"Castro-Golden Judith MD",
    "wof:placetype":"venue"
},
  "geometry": {"coordinates":[-80.25707800000001,25.755435],"type":"Point"}
}