{
  "type": "Feature",
  "properties": {
    "addr:full":"27 Tahiti Beach Island Rd Miami FL 33143",
    "addr:housenumber":"27",
    "addr:postcode":"33143",
    "addr:street":"Tahiti Beach Island Rd",
    "iso:country":"US",
    "sg:address":"27 Tahiti Beach Island Rd",
    "sg:city":"Miami",
    "sg:classifiers":[
        {
            "category":"Professional",
            "type":"Services"
        }
    ],
    "sg:phone":"+1 305 662 1060",
    "sg:postcode":"33143",
    "sg:province":"FL",
    "wof:name":"Philip A Sigel",
    "wof:placetype":"venue"
},
  "geometry": {"coordinates":[-80.246495,25.700942],"type":"Point"}
}