{
  "type": "Feature",
  "properties": {
    "iso:country":"US",
    "sg:address":"715 US Hwy 92",
    "sg:city":"Longwood",
    "sg:classifiers":[
        {
            "category":"Real Estate",
            "subcategory":"Real Estate Agent",
            "type":"Services"
        }
    ],
    "sg:phone":"+1 407 699 8488",
    "sg:postcode":"32750",
    "sg:province":"FL",
    "wof:name":"York Realty",
    "wof:placetype":"venue"
},
  "geometry": {"coordinates":[-81.32582499999999,28.710227],"type":"Point"}
}