{
  "type": "Feature",
  "properties": {
    "addr:full":"5847 8th St SW Miami FL 33144",
    "addr:housenumber":"5847",
    "addr:postcode":"33144",
    "addr:street":"8Th St Sw",
    "iso:country":"US",
    "sg:address":"5847 8th St SW",
    "sg:city":"Miami",
    "sg:classifiers":[
        {
            "category":"Shopping",
            "subcategory":"Pharmacy",
            "type":"Retail Goods"
        }
    ],
    "sg:phone":"+1 305 266 9911",
    "sg:postcode":"33144",
    "sg:province":"FL",
    "wof:name":"Nebu Med Inc",
    "wof:placetype":"venue"
},
  "geometry": {"coordinates":[-80.29003400000001,25.763564],"type":"Point"}
}