{
  "type": "Feature",
  "properties": {
    "addr:full":"8665 SW 125th Ter Miami FL 33156",
    "addr:housenumber":"8665",
    "addr:postcode":"33156",
    "addr:street":"Sw 125Th Ter",
    "iso:country":"US",
    "sg:address":"8665 SW 125th Ter",
    "sg:city":"Miami",
    "sg:classifiers":[
        {
            "category":"Professional",
            "subcategory":"Accounting & Tax Preparation",
            "type":"Services"
        }
    ],
    "sg:phone":"+1 305 232 8278",
    "sg:postcode":"33156",
    "sg:province":"FL",
    "wof:name":"Executive Med Blling Cllectn S",
    "wof:placetype":"venue"
},
  "geometry": {"coordinates":[-80.33217,25.653581],"type":"Point"}
}