{
  "type": "Feature",
  "properties": {
    "iso:country":"US",
    "sg:address":"2000 Bayberry Dr",
    "sg:city":"Hollywood",
    "sg:classifiers":[
        {
            "category":"Personal",
            "subcategory":"Beauty Salon",
            "type":"Services"
        }
    ],
    "sg:phone":"+1 954 447 0165",
    "sg:postcode":"33024",
    "sg:province":"FL",
    "sg:tags":[
        "shop"
    ],
    "wof:name":"Carter Family Affair Cleaning",
    "wof:placetype":"venue"
},
  "geometry": {"coordinates":[-80.275244,26.025859],"type":"Point"}
}