{
  "type": "Feature",
  "properties": {
    "iso:country":"US",
    "sg:address":"50 Century 21 Dr",
    "sg:city":"Jacksonville",
    "sg:classifiers":[
        {
            "category":"Real Estate",
            "subcategory":"Real Estate Agent",
            "type":"Services"
        }
    ],
    "sg:phone":"+1 904 727 5046",
    "sg:postcode":"32216",
    "sg:province":"FL",
    "wof:name":"Sam Double Car Wash Inc",
    "wof:placetype":"venue"
},
  "geometry": {"coordinates":[-81.572436,30.313102],"type":"Point"}
}