{
  "type": "Feature",
  "properties": {
    "addr:full":"730 The Rialto Venice FL 34285",
    "addr:housenumber":"730",
    "addr:postcode":"34285",
    "addr:street":"The",
    "iso:country":"US",
    "sg:address":"730 The Rialto",
    "sg:city":"Venice",
    "sg:classifiers":[
        {
            "category":"Health Services",
            "subcategory":"Doctor",
            "type":"Services"
        }
    ],
    "sg:phone":"+1 941 207 3000",
    "sg:postcode":"34285",
    "sg:province":"FL",
    "sg:tags":[
        "physician",
        "surgeon"
    ],
    "wof:name":"Lenita Hanson MD",
    "wof:placetype":"venue"
},
  "geometry": {"coordinates":[-82.44445399999999,27.087464],"type":"Point"}
}