{
  "type": "Feature",
  "properties": {
    "addr:full":"2490 Dr Martin Luther King Way Sarasota FL 34234",
    "addr:housenumber":"2490",
    "addr:postcode":"34234",
    "addr:street":"Dr Martin Luther King Way",
    "iso:country":"US",
    "sg:address":"2490 Dr Martin Luther King Way",
    "sg:city":"Sarasota",
    "sg:classifiers":[
        {
            "category":"Professional",
            "subcategory":"Advertising",
            "type":"Services"
        }
    ],
    "sg:phone":"+1 941 953 4299",
    "sg:postcode":"34234",
    "sg:province":"FL",
    "sg:tags":[
        "counselor"
    ],
    "wof:name":"Black Windows Advertising Inc",
    "wof:placetype":"venue"
},
  "geometry": {"coordinates":[-82.52075499999999,27.359633],"type":"Point"}
}