{
  "type": "Feature",
  "properties": {
    "iso:country":"US",
    "sg:address":"1201 US Hwy 1",
    "sg:city":"North Palm Beach",
    "sg:classifiers":[
        {
            "category":"Utilities",
            "subcategory":"Telephone",
            "type":"Services"
        }
    ],
    "sg:phone":"+1 561 624 3770",
    "sg:postcode":"33408",
    "sg:province":"FL",
    "sg:tags":[
        "telecommunication"
    ],
    "wof:name":"Nosc Telecommunications",
    "wof:placetype":"venue"
},
  "geometry": {"coordinates":[-80.06052699999999,26.836844],"type":"Point"}
}