{
  "type": "Feature",
  "properties": {
    "iso:country":"US",
    "sg:address":"7220 Central Ave",
    "sg:city":"St Petersburg",
    "sg:classifiers":[
        {
            "category":"Restaurant",
            "type":"Food & Drink"
        }
    ],
    "sg:phone":"+1 727 343 3774",
    "sg:postcode":"33707",
    "sg:province":"FL",
    "sg:tags":[
        "eating",
        "pizza"
    ],
    "wof:name":"Mr Pizza",
    "wof:placetype":"venue"
},
  "geometry": {"coordinates":[-82.739071,27.770746],"type":"Point"}
}