{
  "type": "Feature",
  "properties": {
    "iso:country":"US",
    "sg:address":"2555 Dobbs Rd",
    "sg:city":"St Augustine",
    "sg:classifiers":[
        {
            "category":"Wholesale",
            "subcategory":"Home Furnishings",
            "type":"Manufacturing & Wholesale Goods"
        }
    ],
    "sg:phone":"+1 904 826 0051",
    "sg:postcode":"32086",
    "sg:province":"FL",
    "sg:tags":[
        "lamp"
    ],
    "wof:name":"Secrets Of The Sea",
    "wof:placetype":"venue"
},
  "geometry": {"coordinates":[-81.334017,29.849988],"type":"Point"}
}