{
  "type": "Feature",
  "properties": {
    "addr:full":"2249 34th St S St Petersburg FL 33711",
    "addr:housenumber":"2249",
    "addr:postcode":"33711",
    "addr:street":"34Th St S",
    "iso:country":"US",
    "sg:address":"2249 34th St S",
    "sg:city":"St Petersburg",
    "sg:classifiers":[
        {
            "category":"Personal",
            "subcategory":"Beauty Salon",
            "type":"Services"
        }
    ],
    "sg:phone":"+1 727 328 8548",
    "sg:postcode":"33711",
    "sg:province":"FL",
    "wof:name":"Motherland Hair Braiding",
    "wof:placetype":"venue"
},
  "geometry": {"coordinates":[-82.67939200000001,27.748143],"type":"Point"}
}