{
  "type": "Feature",
  "properties": {
    "addr:full":"7125 W Oakland Park Blvd Fort Lauderdale FL 33313",
    "addr:housenumber":"7125",
    "addr:postcode":"33313",
    "addr:street":"W Oakland Park Blvd",
    "iso:country":"US",
    "sg:address":"7125 W Oakland Park Blvd",
    "sg:city":"Fort Lauderdale",
    "sg:classifiers":[
        {
            "category":"Bagels",
            "type":"Food & Drink"
        },
        {
            "category":"Coffee & Tea",
            "type":"Food & Drink"
        },
        {
            "category":"Food & Beverages",
            "subcategory":"Bakery",
            "type":"Retail Goods"
        },
        {
            "category":"Bakery",
            "type":"Food & Drink"
        },
        {
            "category":"Donuts",
            "type":"Food & Drink"
        }
    ],
    "sg:menulink":"http://www.allmenus.com/fl/plantation/138020-dunkin-donuts/menu/",
    "sg:phone":"+1 954 742 8511",
    "sg:postcode":"33313",
    "sg:province":"FL",
    "sg:tags":[
        "coffee",
        "tea",
        "american",
        "bagel",
        "bakery",
        "pastry"
    ],
    "wof:name":"Dunkin' Donuts",
    "wof:placetype":"venue"
},
  "geometry": {"coordinates":[-80.243076,26.165378],"type":"Point"}
}