{
  "type": "Feature",
  "properties": {
    "addr:full":"12300 Sunriver Ln Dade City FL 33525",
    "addr:housenumber":"12300",
    "addr:postcode":"33525",
    "addr:street":"Sunriver Ln",
    "iso:country":"US",
    "sg:address":"12300 Sunriver Ln",
    "sg:city":"Dade City",
    "sg:classifiers":[
        {
            "category":"Wholesale",
            "subcategory":"Durable Goods & Equipment",
            "type":"Manufacturing & Wholesale Goods"
        }
    ],
    "sg:phone":"+1 352 457 1554",
    "sg:postcode":"33525",
    "sg:province":"FL",
    "sg:tags":[
        "representative",
        "manufacturer"
    ],
    "wof:name":"Bectill Inc",
    "wof:placetype":"venue"
},
  "geometry": {"coordinates":[-82.24794199999999,28.336929],"type":"Point"}
}