{
  "type": "Feature",
  "properties": {
    "addr:full":"305 SW 4th Ave Homestead FL 33030",
    "addr:housenumber":"305",
    "addr:postcode":"33030",
    "addr:street":"Sw 4Th Ave",
    "iso:country":"US",
    "sg:address":"305 SW 4th Ave",
    "sg:city":"Homestead",
    "sg:classifiers":[
        {
            "category":"Manufacturing",
            "subcategory":"Signs",
            "type":"Manufacturing & Wholesale Goods"
        }
    ],
    "sg:phone":"+1 305 971 1112",
    "sg:postcode":"33030",
    "sg:province":"FL",
    "wof:name":"Prestige Sign Design",
    "wof:placetype":"venue"
},
  "geometry": {"coordinates":[-80.48333,25.466199],"type":"Point"}
}