{
  "type": "Feature",
  "properties": {
    "iso:country":"US",
    "sg:address":"19346 SW 262nd St",
    "sg:city":"Homestead",
    "sg:classifiers":[
        {
            "category":"Professional",
            "subcategory":"Accounting & Tax Preparation",
            "type":"Services"
        }
    ],
    "sg:phone":"+1 305 248 4517",
    "sg:postcode":"33031",
    "sg:province":"FL",
    "sg:tags":[
        "bookkeeping"
    ],
    "wof:name":"Creasman Enterprises",
    "wof:placetype":"venue"
},
  "geometry": {"coordinates":[-80.505775,25.521845],"type":"Point"}
}