{
  "type": "Feature",
  "properties": {
    "addr:full":"782 E Lake Rd Palm Harbor FL 34685",
    "addr:housenumber":"782",
    "addr:postcode":"34685",
    "addr:street":"E Lake Rd",
    "iso:country":"US",
    "sg:address":"782 E Lake Rd",
    "sg:city":"Palm Harbor",
    "sg:classifiers":[
        {
            "category":"Real Estate",
            "subcategory":"Real Estate Agent",
            "type":"Services"
        }
    ],
    "sg:phone":"+1 727 784 6040",
    "sg:postcode":"34685",
    "sg:province":"FL",
    "sg:tags":[
        "residential",
        "manager",
        "condo"
    ],
    "wof:name":"Century 21",
    "wof:placetype":"venue"
},
  "geometry": {"coordinates":[-82.704449,28.072453],"type":"Point"}
}