{
  "type": "Feature",
  "properties": {
    "iso:country":"US",
    "sg:address":"26133 US Hwy 19",
    "sg:city":"Clearwater",
    "sg:classifiers":[
        {
            "category":"Professional",
            "subcategory":"Management & Consulting",
            "type":"Services"
        }
    ],
    "sg:phone":"+1 727 723 0451",
    "sg:postcode":"33763",
    "sg:province":"FL",
    "wof:name":"Healthcare Dynamics Consulting",
    "wof:placetype":"venue"
},
  "geometry": {"coordinates":[-82.73128699999999,28.009355],"type":"Point"}
}