{
  "type": "Feature",
  "properties": {
    "addr:full":"10691 SW 40th St Miami FL 33165",
    "addr:housenumber":"10691",
    "addr:postcode":"33165",
    "addr:street":"Sw 40Th St",
    "iso:country":"US",
    "sg:address":"10691 SW 40th St",
    "sg:city":"Miami",
    "sg:classifiers":[
        {
            "category":"Retail",
            "subcategory":"Repair Shop",
            "type":"Services"
        }
    ],
    "sg:phone":"+1 305 357 3634",
    "sg:postcode":"33165",
    "sg:province":"FL",
    "sg:tags":[
        "lock",
        "locksmith"
    ],
    "wof:name":"24 Emergency 7 Day Locksmith",
    "wof:placetype":"venue"
},
  "geometry": {"coordinates":[-80.367133,25.732404],"type":"Point"}
}