{
  "type": "Feature",
  "properties": {
    "iso:country":"US",
    "sg:address":"3561 Quentin Ave",
    "sg:city":"Boynton Beach",
    "sg:classifiers":[
        {
            "category":"Building & Trades",
            "subcategory":"Landscaping Services",
            "type":"Services"
        }
    ],
    "sg:phone":"+1 561 441 0767",
    "sg:postcode":"33436",
    "sg:province":"FL",
    "sg:tags":[
        "lawn",
        "maintenance",
        "grounds"
    ],
    "wof:name":"Pierre Eriole Landscaping",
    "wof:placetype":"venue"
},
  "geometry": {"coordinates":[-80.099367,26.533311],"type":"Point"}
}