{
  "type": "Feature",
  "properties": {
    "addr:full":"4370 S Tamiami Trl Sarasota FL 34231",
    "addr:housenumber":"4370",
    "addr:postcode":"34231",
    "addr:street":"S Tamiami Trl",
    "iso:country":"US",
    "sg:address":"4370 S Tamiami Trl",
    "sg:city":"Sarasota",
    "sg:classifiers":[
        {
            "category":"Insurance",
            "subcategory":"Insurance Agent",
            "type":"Services"
        }
    ],
    "sg:phone":"+1 941 926 4322",
    "sg:postcode":"34231",
    "sg:province":"FL",
    "wof:name":"Fred Engels",
    "wof:placetype":"venue"
},
  "geometry": {"coordinates":[-82.530737,27.290618],"type":"Point"}
}