{
  "type": "Feature",
  "properties": {
    "addr:full":"800 NW 6th Ter Boca Raton FL 33486",
    "addr:housenumber":"800",
    "addr:postcode":"33486",
    "addr:street":"Nw 6Th Ter",
    "iso:country":"US",
    "sg:address":"800 NW 6th Ter",
    "sg:city":"Boca Raton",
    "sg:classifiers":[
        {
            "category":"Banks & Credit Unions",
            "subcategory":"Investment Brokerage",
            "type":"Services"
        }
    ],
    "sg:phone":"+1 561 395 0023",
    "sg:postcode":"33486",
    "sg:province":"FL",
    "sg:tags":[
        "advisory",
        "financial"
    ],
    "wof:name":"Site Financial Svc Inc",
    "wof:placetype":"venue"
},
  "geometry": {"coordinates":[-80.104421,26.355772],"type":"Point"}
}