{
  "type": "Feature",
  "properties": {
    "iso:country":"US",
    "sg:address":"2523 Lee Blvd",
    "sg:city":"Lehigh Acres",
    "sg:classifiers":[
        {
            "category":"Restaurant",
            "type":"Food & Drink"
        }
    ],
    "sg:menulink":"http://www.allmenus.com/fl/lehigh-acres/187339-mcdonalds/menu/",
    "sg:phone":"+1 239 369 0060",
    "sg:postcode":"33971",
    "sg:province":"FL",
    "sg:tags":[
        "burger",
        "american"
    ],
    "wof:name":"McDonald's",
    "wof:placetype":"venue"
},
  "geometry": {"coordinates":[-81.66412200000001,26.614604],"type":"Point"}
}