{
  "type": "Feature",
  "properties": {
    "addr:full":"125 E Indiana Ave Ste A2 Deland FL 32724",
    "addr:housenumber":"125",
    "addr:postcode":"32724",
    "addr:street":"E Indiana Ave Ste A2",
    "iso:country":"US",
    "sg:address":"125 E Indiana Ave Ste A2",
    "sg:city":"Deland",
    "sg:classifiers":[
        {
            "category":"Professional",
            "subcategory":"Management & Consulting",
            "type":"Services"
        },
        {
            "category":"Professional",
            "subcategory":"Engineering",
            "type":"Services"
        }
    ],
    "sg:phone":"+1 386 943 8990",
    "sg:postcode":"32724",
    "sg:province":"FL",
    "sg:tags":[
        "environmental",
        "ecological",
        "engineer",
        "consultant"
    ],
    "wof:name":"Environmental Planning & Management Inc",
    "wof:placetype":"venue"
},
  "geometry": {"coordinates":[-81.302907,29.02898],"type":"Point"}
}