{
  "type": "Feature",
  "properties": {
    "iso:country":"US",
    "sg:address":"3050 Warehouse Rd",
    "sg:city":"Fort Myers",
    "sg:classifiers":[
        {
            "category":"Manufacturing",
            "subcategory":"Metals",
            "type":"Manufacturing & Wholesale Goods"
        }
    ],
    "sg:phone":"+1 239 337 2079",
    "sg:postcode":"33916",
    "sg:province":"FL",
    "sg:tags":[
        "steel",
        "product",
        "mfg"
    ],
    "wof:name":"Master-Halco Inc",
    "wof:placetype":"venue"
},
  "geometry": {"coordinates":[-81.850971,26.612588],"type":"Point"}
}