{
  "type": "Feature",
  "properties": {
    "iso:country":"US",
    "sg:address":"1780 NW 16th Ter",
    "sg:city":"Miami",
    "sg:classifiers":[
        {
            "category":"Autos & Motor Vehicles",
            "subcategory":"Auto Supplies",
            "type":"Retail Goods"
        }
    ],
    "sg:phone":"+1 305 898 8271",
    "sg:postcode":"33125",
    "sg:province":"FL",
    "sg:tags":[
        "automobile",
        "accessories-wholesale",
        "parts",
        "manufacturer"
    ],
    "wof:name":"Matco Tools Distributor Inc",
    "wof:placetype":"venue"
},
  "geometry": {"coordinates":[-80.224887,25.790504],"type":"Point"}
}