{
  "type": "Feature",
  "properties": {
    "iso:country":"US",
    "sg:address":"2805 Alt US Hwy 27 S",
    "sg:city":"Sebring",
    "sg:classifiers":[
        {
            "category":"Personal",
            "subcategory":"Beauty Salon",
            "type":"Services"
        }
    ],
    "sg:phone":"+1 863 385 6128",
    "sg:postcode":"33870",
    "sg:province":"FL",
    "wof:name":"Le Marj Salon Of Beauty",
    "wof:placetype":"venue"
},
  "geometry": {"coordinates":[-81.44296300000001,27.475346],"type":"Point"}
}