{
  "type": "Feature",
  "properties": {
    "iso:country":"US",
    "sg:address":"207 N Primrose Dr",
    "sg:city":"Orlando",
    "sg:classifiers":[
        {
            "category":"Restaurant",
            "type":"Food & Drink"
        }
    ],
    "sg:phone":"+1 407 896 1981",
    "sg:postcode":"32803",
    "sg:province":"FL",
    "sg:tags":[
        "eating"
    ],
    "wof:name":"Sandwich King",
    "wof:placetype":"venue"
},
  "geometry": {"coordinates":[-81.34774400000001,28.545932],"type":"Point"}
}