{
  "type": "Feature",
  "properties": {
    "iso:country":"US",
    "sg:address":"5360 N Atlantic Ave",
    "sg:city":"Cocoa Beach",
    "sg:classifiers":[
        {
            "category":"Shopping",
            "subcategory":"Clothing, Apparel, & Fashions",
            "type":"Retail Goods"
        }
    ],
    "sg:phone":"+1 321 783 8582",
    "sg:postcode":"32931",
    "sg:province":"FL",
    "wof:name":"Butchwear Retail Inc",
    "wof:placetype":"venue"
},
  "geometry": {"coordinates":[-80.606076,28.366836],"type":"Point"}
}