{
  "type": "Feature",
  "properties": {
    "addr:full":"3781 NW 100th St Ocala FL 34482",
    "addr:housenumber":"3781",
    "addr:postcode":"34482",
    "addr:street":"Nw 100Th St",
    "iso:country":"US",
    "sg:address":"3781 NW 100th St",
    "sg:city":"Ocala",
    "sg:classifiers":[
        {
            "category":"Wholesale",
            "subcategory":"Farm Supplies",
            "type":"Manufacturing & Wholesale Goods"
        }
    ],
    "sg:phone":"+1 352 369 9009",
    "sg:postcode":"34482",
    "sg:province":"FL",
    "sg:tags":[
        "horse",
        "dealer"
    ],
    "wof:name":"Florida Classic Horse Sales",
    "wof:placetype":"venue"
},
  "geometry": {"coordinates":[-82.18328200000001,29.294802],"type":"Point"}
}