{
  "type": "Feature",
  "properties": {
    "iso:country":"US",
    "sg:address":"631 Beal Pkwy NW",
    "sg:city":"Fort Walton Beach",
    "sg:classifiers":[
        {
            "category":"Retail",
            "subcategory":"Auto Rental",
            "type":"Services"
        }
    ],
    "sg:phone":"+1 850 863 2133",
    "sg:postcode":"32547",
    "sg:province":"FL",
    "sg:tags":[
        "truck",
        "trailer",
        "utility"
    ],
    "wof:name":"U-Haul",
    "wof:placetype":"venue"
},
  "geometry": {"coordinates":[-86.63953600000001,30.430545],"type":"Point"}
}