{
  "type": "Feature",
  "properties": {
    "addr:full":"5118 N 56th St Tampa FL 33610",
    "addr:housenumber":"5118",
    "addr:postcode":"33610",
    "addr:street":"N 56Th St",
    "iso:country":"US",
    "sg:address":"5118 N 56th St",
    "sg:city":"Tampa",
    "sg:classifiers":[
        {
            "category":"Professional",
            "subcategory":"Management & Consulting",
            "type":"Services"
        }
    ],
    "sg:phone":"+1 813 626 0524",
    "sg:postcode":"33610",
    "sg:province":"FL",
    "wof:name":"Letourneau Center Co",
    "wof:placetype":"venue"
},
  "geometry": {"coordinates":[-82.393556,27.993984],"type":"Point"}
}