{
  "type": "Feature",
  "properties": {
    "addr:full":"5375 3rd Rd Lake Worth FL 33467",
    "addr:housenumber":"5375",
    "addr:postcode":"33467",
    "addr:street":"3Rd Rd",
    "iso:country":"US",
    "sg:address":"5375 3rd Rd",
    "sg:city":"Lake Worth",
    "sg:classifiers":[
        {
            "category":"Building & Trades",
            "subcategory":"Pest Control",
            "type":"Services"
        }
    ],
    "sg:phone":"+1 561 735 0085",
    "sg:postcode":"33467",
    "sg:province":"FL",
    "wof:name":"Excellent Environmental Svc",
    "wof:placetype":"venue"
},
  "geometry": {"coordinates":[-80.166971,26.600164],"type":"Point"}
}