{
  "type": "Feature",
  "properties": {
    "iso:country":"US",
    "sg:address":"2727 W Oak Ridge Rd",
    "sg:city":"Orlando",
    "sg:classifiers":[
        {
            "category":"Real Estate",
            "subcategory":"Real Estate Agent",
            "type":"Services"
        },
        {
            "category":"Real Estate",
            "subcategory":"Real Estate Operator",
            "type":"Services"
        }
    ],
    "sg:phone":"+1 407 855 4227",
    "sg:postcode":"32809",
    "sg:province":"FL",
    "sg:tags":[
        "condominium"
    ],
    "wof:name":"Chateau De Ville Condominiums",
    "wof:placetype":"venue"
},
  "geometry": {"coordinates":[-81.41413300000001,28.472452],"type":"Point"}
}