{
  "type": "Feature",
  "properties": {
    "addr:full":"1718 SW 17th Ave Miami FL 33145",
    "addr:housenumber":"1718",
    "addr:postcode":"33145",
    "addr:street":"Sw 17Th Ave",
    "iso:country":"US",
    "sg:address":"1718 SW 17th Ave",
    "sg:city":"Miami",
    "sg:classifiers":[
        {
            "category":"Real Estate",
            "subcategory":"Real Estate Agent",
            "type":"Services"
        }
    ],
    "sg:phone":"+1 305 854 3258",
    "sg:postcode":"33145",
    "sg:province":"FL",
    "wof:name":"Gyori Teresita",
    "wof:placetype":"venue"
},
  "geometry": {"coordinates":[-80.222205,25.756185],"type":"Point"}
}