{
  "type": "Feature",
  "properties": {
    "iso:country":"US",
    "sg:address":"21 Bonita Ave",
    "sg:city":"Key Largo",
    "sg:classifiers":[
        {
            "category":"Shopping",
            "subcategory":"Gifts & Souvenirs",
            "type":"Retail Goods"
        }
    ],
    "sg:phone":"+1 305 453 4787",
    "sg:postcode":"33037",
    "sg:province":"FL",
    "wof:name":"Interface Greetings",
    "wof:placetype":"venue"
},
  "geometry": {"coordinates":[-80.39048200000001,25.153081],"type":"Point"}
}