{
  "type": "Feature",
  "properties": {
    "addr:full":"2619 Palmdale St Jacksonville FL 32208",
    "addr:housenumber":"2619",
    "addr:postcode":"32208",
    "addr:street":"Palmdale St",
    "iso:country":"US",
    "sg:address":"2619 Palmdale St",
    "sg:city":"Jacksonville",
    "sg:classifiers":[
        {
            "category":"Health Services",
            "subcategory":"Medical Lab",
            "type":"Services"
        }
    ],
    "sg:phone":"+1 904 766 1266",
    "sg:postcode":"32208",
    "sg:province":"FL",
    "sg:tags":[
        "laboratory"
    ],
    "wof:name":"Precision Dental Lab Services",
    "wof:placetype":"venue"
},
  "geometry": {"coordinates":[-81.696814,30.388966],"type":"Point"}
}