{
  "type": "Feature",
  "properties": {
    "addr:full":"8106 Cortez Rd W Bradenton FL 34210",
    "addr:housenumber":"8106",
    "addr:postcode":"34210",
    "addr:street":"Cortez Rd W",
    "iso:country":"US",
    "sg:address":"8106 Cortez Rd W",
    "sg:city":"Bradenton",
    "sg:classifiers":[
        {
            "category":"Professional",
            "subcategory":"Accounting & Tax Preparation",
            "type":"Services"
        },
        {
            "category":"Insurance",
            "subcategory":"Hazard Insurance",
            "type":"Services"
        }
    ],
    "sg:phone":"+1 941 794 0282",
    "sg:postcode":"34210",
    "sg:province":"FL",
    "sg:tags":[
        "commercial",
        "bookkeeping",
        "return",
        "business",
        "preparation-business"
    ],
    "wof:name":"Great Florida Insurance",
    "wof:placetype":"venue"
},
  "geometry": {"coordinates":[-82.64249700000001,27.462147],"type":"Point"}
}