{
  "type": "Feature",
  "properties": {
    "iso:country":"US",
    "sg:address":"5001 Nw 104 Ave",
    "sg:city":"Miami",
    "sg:classifiers":[
        {
            "category":"Restaurant",
            "type":"Food & Drink"
        }
    ],
    "sg:phone":"+1 305 591 8800",
    "sg:postcode":"33178",
    "sg:province":"FL",
    "sg:tags":[
        "traditional",
        "american"
    ],
    "sg:website":"www.doralpark.org/19thhole.html",
    "wof:name":"The Doral Park 19th Hole Bar And Grill",
    "wof:placetype":"venue"
},
  "geometry": {"coordinates":[-80.365089,25.817389],"type":"Point"}
}