{
  "type": "Feature",
  "properties": {
    "addr:full":"6000 Airport Cir Sarasota FL 34243",
    "addr:housenumber":"6000",
    "addr:postcode":"34243",
    "addr:street":"Airport Cir",
    "iso:country":"US",
    "sg:address":"6000 Airport Cir",
    "sg:city":"Sarasota",
    "sg:classifiers":[
        {
            "category":"Coffee & Tea",
            "type":"Food & Drink"
        },
        {
            "category":"Bakery",
            "type":"Food & Drink"
        },
        {
            "category":"Bagels",
            "subcategory":"None",
            "type":"Food & Drink"
        },
        {
            "category":"Donuts",
            "subcategory":"None",
            "type":"Food & Drink"
        }
    ],
    "sg:phone":"+1 941 306 2291",
    "sg:postcode":"34243",
    "sg:province":"FL",
    "sg:tags":[
        "shop",
        "espresso",
        "restaurant"
    ],
    "sg:website":"http://national.citysearch.com/profile/external/604250252/sarasota_fl/dunkin_donuts.html?publisher=yellowpages&reference_id=1&placement=ypwebsitemip",
    "wof:name":"Dunkin Donuts",
    "wof:placetype":"venue"
},
  "geometry": {"coordinates":[-82.551659,27.386761],"type":"Point"}
}