{
  "type": "Feature",
  "properties": {
    "addr:full":"427 N Federal Hwy Pompano Beach FL 33062",
    "addr:housenumber":"427",
    "addr:postcode":"33062",
    "addr:street":"N Federal Hwy",
    "iso:country":"US",
    "sg:address":"427 N Federal Hwy",
    "sg:city":"Pompano Beach",
    "sg:classifiers":[
        {
            "category":"Restaurant",
            "type":"Food & Drink"
        }
    ],
    "sg:phone":"+1 954 784 4282",
    "sg:postcode":"33062",
    "sg:province":"FL",
    "wof:name":"Quiznos Sub",
    "wof:placetype":"venue"
},
  "geometry": {"coordinates":[-80.102963,26.237023],"type":"Point"}
}