{
  "type": "Feature",
  "properties": {
    "iso:country":"US",
    "sg:address":"1315 W Sunrise Blvd",
    "sg:city":"Fort Lauderdale",
    "sg:classifiers":[
        {
            "category":"Food & Beverages",
            "subcategory":"Groceries & Convenience Stores",
            "type":"Retail Goods"
        }
    ],
    "sg:phone":"+1 954 527 1517",
    "sg:postcode":"33311",
    "sg:province":"FL",
    "wof:name":"Mercy Convenient Store",
    "wof:placetype":"venue"
},
  "geometry": {"coordinates":[-80.159102,26.136568],"type":"Point"}
}