{
  "type": "Feature",
  "properties": {
    "addr:full":"5764 N Orange Blossom Trl Orlando FL 32810",
    "addr:housenumber":"5764",
    "addr:postcode":"32810",
    "addr:street":"N Orange Blossom Trl",
    "iso:country":"US",
    "sg:address":"5764 N Orange Blossom Trl",
    "sg:city":"Orlando",
    "sg:classifiers":[
        {
            "category":"Freight",
            "type":"Transportation"
        },
        {
            "category":"Professional",
            "subcategory":"Lawyer & Legal Services",
            "type":"Services"
        }
    ],
    "sg:phone":"+1 407 299 7328",
    "sg:postcode":"32810",
    "sg:province":"FL",
    "sg:tags":[
        "notary",
        "shipping"
    ],
    "sg:website":"www.mailandmore.com",
    "wof:name":"Mail & More",
    "wof:placetype":"venue"
},
  "geometry": {"coordinates":[-81.42890199999999,28.610701],"type":"Point"}
}