{
  "type": "Feature",
  "properties": {
    "addr:full":"101 E 25th St Sanford FL 32771",
    "addr:housenumber":"101",
    "addr:postcode":"32771",
    "addr:street":"E 25Th St",
    "iso:country":"US",
    "sg:address":"101 E 25th St",
    "sg:city":"Sanford",
    "sg:classifiers":[
        {
            "category":"Banks & Credit Unions",
            "subcategory":"Bank",
            "type":"Services"
        }
    ],
    "sg:phone":"+1 407 321 6890",
    "sg:postcode":"32771",
    "sg:province":"FL",
    "wof:name":"Florida National Bank",
    "wof:placetype":"venue"
},
  "geometry": {"coordinates":[-81.26783,28.78668],"type":"Point"}
}