{
  "type": "Feature",
  "properties": {
    "iso:country":"US",
    "sg:address":"4950 S Orange Blossom Trl",
    "sg:city":"Orlando",
    "sg:classifiers":[
        {
            "category":"Personal",
            "subcategory":"Barber",
            "type":"Services"
        }
    ],
    "sg:phone":"+1 407 855 6474",
    "sg:postcode":"32839",
    "sg:province":"FL",
    "wof:name":"Carlos Barber Shop & Unisex",
    "wof:placetype":"venue"
},
  "geometry": {"coordinates":[-81.396867,28.48953],"type":"Point"}
}