{
  "type": "Feature",
  "properties": {
    "addr:full":"265 SW Ave E Belle Glade FL 33430",
    "addr:housenumber":"265",
    "addr:postcode":"33430",
    "addr:street":"Sw Ave E Belle Glade",
    "iso:country":"US",
    "sg:address":"265 SW Ave E",
    "sg:city":"Belle Glade",
    "sg:classifiers":[
        {
            "category":"Retail",
            "subcategory":"Car Wash",
            "type":"Services"
        }
    ],
    "sg:phone":"+1 561 996 0756",
    "sg:postcode":"33430",
    "sg:province":"FL",
    "sg:tags":[
        "polishing",
        "washing"
    ],
    "wof:name":"Hooks Car Wash",
    "wof:placetype":"venue"
},
  "geometry": {"coordinates":[-80.67027899999999,26.68232],"type":"Point"}
}