{
  "type": "Feature",
  "properties": {
    "addr:full":"3242 SW 51st St Fort Lauderdale FL 33312",
    "addr:housenumber":"3242",
    "addr:postcode":"33312",
    "addr:street":"Sw 51St St",
    "iso:country":"US",
    "sg:address":"3242 SW 51st St",
    "sg:city":"Fort Lauderdale",
    "sg:classifiers":[
        {
            "category":"Building & Trades",
            "subcategory":"Equipment Rental",
            "type":"Services"
        }
    ],
    "sg:phone":"+1 954 962 5905",
    "sg:postcode":"33312",
    "sg:province":"FL",
    "wof:name":"J & M Sales and Enterprises",
    "wof:placetype":"venue"
},
  "geometry": {"coordinates":[-80.187152,26.058329],"type":"Point"}
}