{
  "type": "Feature",
  "properties": {
    "iso:country":"US",
    "sg:address":"7501 SW 39th St",
    "sg:city":"Miami",
    "sg:classifiers":[
        {
            "category":"Building & Trades",
            "subcategory":"Electrical",
            "type":"Services"
        }
    ],
    "sg:phone":"+1 305 262 1470",
    "sg:postcode":"33155",
    "sg:province":"FL",
    "sg:tags":[
        "electrical",
        "contractor"
    ],
    "wof:name":"Ferrtell Inc",
    "wof:placetype":"venue"
},
  "geometry": {"coordinates":[-80.317999,25.734408],"type":"Point"}
}