{
  "type": "Feature",
  "properties": {
    "iso:country":"US",
    "sg:address":"1425 Aurora Rd",
    "sg:city":"Melbourne",
    "sg:classifiers":[
        {
            "category":"Social Services",
            "type":"Services"
        }
    ],
    "sg:phone":"+1 321 253 2470",
    "sg:postcode":"32935",
    "sg:province":"FL",
    "sg:tags":[
        "counselor",
        "marriage",
        "family"
    ],
    "wof:name":"Harvey Hester PHD",
    "wof:placetype":"venue"
},
  "geometry": {"coordinates":[-80.64329600000001,28.134493],"type":"Point"}
}