{
  "type": "Feature",
  "properties": {
    "addr:full":"2386 Grey Oaks Dr N Naples FL 34105",
    "addr:housenumber":"2386",
    "addr:postcode":"34105",
    "addr:street":"Grey Oaks Dr N",
    "iso:country":"US",
    "sg:address":"2386 Grey Oaks Dr N",
    "sg:city":"Naples",
    "sg:classifiers":[
        {
            "category":"Real Estate",
            "subcategory":"Real Estate Operator",
            "type":"Services"
        }
    ],
    "sg:phone":"+1 239 262 0520",
    "sg:postcode":"34105",
    "sg:province":"FL",
    "sg:tags":[
        "property",
        "management"
    ],
    "wof:name":"Grey Oaks Community Services",
    "wof:placetype":"venue"
},
  "geometry": {"coordinates":[-81.762456,26.187505],"type":"Point"}
}