{
  "type": "Feature",
  "properties": {
    "iso:country":"US",
    "sg:address":"2121 S Hopkins Ave",
    "sg:city":"Titusville",
    "sg:classifiers":[
        {
            "category":"Education",
            "subcategory":"Library",
            "type":"Public Place"
        },
        {
            "category":"Government",
            "subcategory":"Office",
            "type":"Public Place"
        }
    ],
    "sg:phone":"+1 321 264 5026",
    "sg:postcode":"32780",
    "sg:province":"FL",
    "sg:tags":[
        "township",
        "government-city",
        "village"
    ],
    "sg:website":"http://www.cocoabeachpubliclibrary.org",
    "wof:name":"North Brevard Public Library",
    "wof:placetype":"venue"
},
  "geometry": {"coordinates":[-80.806934,28.590255],"type":"Point"}
}