{
  "type": "Feature",
  "properties": {
    "iso:country":"US",
    "sg:address":"1565 Saxon Blvd",
    "sg:city":"Deltona",
    "sg:classifiers":[
        {
            "category":"Health Services",
            "subcategory":"Doctor",
            "type":"Services"
        }
    ],
    "sg:phone":"+1 386 789 6464",
    "sg:postcode":"32725",
    "sg:province":"FL",
    "sg:tags":[
        "physician",
        "surgeon"
    ],
    "wof:name":"Brodrick Thomas J MD PA",
    "wof:placetype":"venue"
},
  "geometry": {"coordinates":[-81.246853,28.906599],"type":"Point"}
}