{
  "type": "Feature",
  "properties": {
    "iso:country":"US",
    "sg:address":"4986 E Silver Springs Blvd",
    "sg:city":"Ocala",
    "sg:classifiers":[
        {
            "category":"Autos & Motor Vehicles",
            "subcategory":"Fuel & Gas Station",
            "type":"Retail Goods"
        }
    ],
    "sg:phone":"+1 352 236 2854",
    "sg:postcode":"34470",
    "sg:province":"FL",
    "sg:tags":[
        "oil"
    ],
    "wof:name":"Murphy Oil USA Inc",
    "wof:placetype":"venue"
},
  "geometry": {"coordinates":[-82.069497,29.208629],"type":"Point"}
}