{
  "type": "Feature",
  "properties": {
    "iso:country":"US",
    "sg:address":"709 NE 79th St.",
    "sg:city":"Miami",
    "sg:classifiers":[
        {
            "category":"Bars & Pubs",
            "subcategory":"Lounge",
            "type":"Food & Drink"
        }
    ],
    "sg:phone":"+1 305 757 3368",
    "sg:postcode":"33138",
    "sg:province":"FL",
    "sg:website":"www.magnumlounge.com/",
    "wof:name":"Magnum Lounge",
    "wof:placetype":"venue"
},
  "geometry": {"coordinates":[-80.182247,25.848138],"type":"Point"}
}