{
  "type": "Feature",
  "properties": {
    "addr:full":"3344 Henry J Ave St Cloud FL 34772",
    "addr:housenumber":"3344",
    "addr:postcode":"34772",
    "addr:street":"Henry J Ave",
    "iso:country":"US",
    "sg:address":"3344 Henry J Ave",
    "sg:city":"St Cloud",
    "sg:classifiers":[
        {
            "category":"Freight",
            "type":"Transportation"
        }
    ],
    "sg:phone":"+1 407 957 9685",
    "sg:postcode":"34772",
    "sg:province":"FL",
    "sg:tags":[
        "mobile",
        "contractor",
        "trucking",
        "operator",
        "home",
        "trade"
    ],
    "wof:name":"Tom's Mobile Homes Inc",
    "wof:placetype":"venue"
},
  "geometry": {"coordinates":[-81.26840900000001,28.197025],"type":"Point"}
}