{
  "type": "Feature",
  "properties": {
    "iso:country":"US",
    "sg:address":"11202 W Hillsborough Ave",
    "sg:city":"Tampa",
    "sg:classifiers":[
        {
            "category":"Restaurant",
            "type":"Food & Drink"
        }
    ],
    "sg:menulink":"http://www.allmenus.com/fl/tampa/45799-codys-original-roadhouse/menu/",
    "sg:phone":"+1 813 855 2787",
    "sg:postcode":"33635",
    "sg:province":"FL",
    "sg:tags":[
        "american"
    ],
    "wof:name":"Cody's Original Roadhouse",
    "wof:placetype":"venue"
},
  "geometry": {"coordinates":[-82.60898400000001,28.010885],"type":"Point"}
}