{
  "type": "Feature",
  "properties": {
    "addr:full":"7100 W Cam Real Boca Raton FL 33433",
    "addr:housenumber":"7100",
    "addr:postcode":"33433",
    "addr:street":"W Cam Real",
    "iso:country":"US",
    "sg:address":"7100 W Cam Real",
    "sg:city":"Boca Raton",
    "sg:classifiers":[
        {
            "category":"Professional",
            "subcategory":"Research",
            "type":"Services"
        }
    ],
    "sg:phone":"+1 561 862 5100",
    "sg:postcode":"33433",
    "sg:province":"FL",
    "sg:tags":[
        "security",
        "network",
        "solution"
    ],
    "wof:name":"14 South Networks",
    "wof:placetype":"venue"
},
  "geometry": {"coordinates":[-80.15418699999999,26.343796],"type":"Point"}
}