{
  "type": "Feature",
  "properties": {
    "addr:full":"324 S Dean Rd Orlando FL 32825",
    "addr:housenumber":"324",
    "addr:postcode":"32825",
    "addr:street":"S Dean Rd",
    "iso:country":"US",
    "sg:address":"324 S Dean Rd",
    "sg:city":"Orlando",
    "sg:classifiers":[
        {
            "category":"Food & Beverages",
            "subcategory":"Groceries & Convenience Stores",
            "type":"Retail Goods"
        }
    ],
    "sg:phone":"+1 407 823 9593",
    "sg:postcode":"32825",
    "sg:province":"FL",
    "wof:name":"Speedway/Sunoco",
    "wof:placetype":"venue"
},
  "geometry": {"coordinates":[-81.244238,28.539041],"type":"Point"}
}