{
  "type": "Feature",
  "properties": {
    "addr:full":"6508 Garland St Fort Myers FL 33966",
    "addr:housenumber":"6508",
    "addr:postcode":"33966",
    "addr:street":"Garland St",
    "iso:country":"US",
    "sg:address":"6508 Garland St",
    "sg:city":"Fort Myers",
    "sg:classifiers":[
        {
            "category":"Manufacturing",
            "subcategory":"Tools & Machinery",
            "type":"Manufacturing & Wholesale Goods"
        }
    ],
    "sg:phone":"+1 239 565 7813",
    "sg:postcode":"33966",
    "sg:province":"FL",
    "sg:tags":[
        "machine",
        "mfg"
    ],
    "wof:name":"Dave Howards Marine Services",
    "wof:placetype":"venue"
},
  "geometry": {"coordinates":[-81.84541400000001,26.584738],"type":"Point"}
}