{
  "type": "Feature",
  "properties": {
    "addr:full":"16019 SW 161st St Brooker FL 32622",
    "addr:housenumber":"16019",
    "addr:postcode":"32622",
    "addr:street":"Sw 161St St",
    "iso:country":"US",
    "sg:address":"16019 SW 161st St",
    "sg:city":"Brooker",
    "sg:classifiers":[
        {
            "category":"Farming",
            "subcategory":"Farm",
            "type":"Manufacturing & Wholesale Goods"
        }
    ],
    "sg:phone":"+1 352 485 2411",
    "sg:postcode":"32622",
    "sg:province":"FL",
    "sg:tags":[
        "crop",
        "general"
    ],
    "wof:name":"L L Johns Jr",
    "wof:placetype":"venue"
},
  "geometry": {"coordinates":[-82.294707,29.950775],"type":"Point"}
}