{
  "type": "Feature",
  "properties": {
    "addr:full":"3613 NW 191st St Opa Locka FL 33056",
    "addr:housenumber":"3613",
    "addr:postcode":"33056",
    "addr:street":"Nw 191St St;Locka",
    "iso:country":"US",
    "sg:address":"3613 NW 191st St",
    "sg:city":"Opa Locka",
    "sg:classifiers":[
        {
            "category":"Social Services",
            "type":"Services"
        }
    ],
    "sg:phone":"+1 305 620 9112",
    "sg:postcode":"33056",
    "sg:province":"FL",
    "sg:tags":[
        "organization",
        "welfare"
    ],
    "wof:name":"Mimi's Baby Food Store",
    "wof:placetype":"venue"
},
  "geometry": {"coordinates":[-80.2616,25.947678],"type":"Point"}
}