{
  "type": "Feature",
  "properties": {
    "addr:full":"330 NE 18th Ave Homestead FL 33033",
    "addr:housenumber":"330",
    "addr:postcode":"33033",
    "addr:street":"Ne 18Th Ave",
    "iso:country":"US",
    "sg:address":"330 NE 18th Ave",
    "sg:city":"Homestead",
    "sg:classifiers":[
        {
            "category":"Real Estate",
            "subcategory":"Real Estate Operator",
            "type":"Services"
        }
    ],
    "sg:phone":"+1 305 245 7100",
    "sg:postcode":"33033",
    "sg:province":"FL",
    "sg:tags":[
        "building",
        "apartment"
    ],
    "wof:name":"Riverwalk Apartments",
    "wof:placetype":"venue"
},
  "geometry": {"coordinates":[-80.45246299999999,25.468391],"type":"Point"}
}