{
  "type": "Feature",
  "properties": {
    "iso:country":"US",
    "sg:address":"112 NE 3rd Ave",
    "sg:city":"Miami",
    "sg:classifiers":[
        {
            "category":"Food & Beverages",
            "subcategory":"Specialty",
            "type":"Retail Goods"
        }
    ],
    "sg:phone":"+1 305 377 1668",
    "sg:postcode":"33132",
    "sg:province":"FL",
    "sg:tags":[
        "vitamin"
    ],
    "wof:name":"Samgys",
    "wof:placetype":"venue"
},
  "geometry": {"coordinates":[-80.188755,25.776131],"type":"Point"}
}