{
  "type": "Feature",
  "properties": {
    "iso:country":"US",
    "sg:address":"5221 Okeechobee Rd",
    "sg:city":"Fort Pierce",
    "sg:classifiers":[
        {
            "category":"Freight",
            "type":"Transportation"
        }
    ],
    "sg:phone":"+1 772 466 6473",
    "sg:postcode":"34947",
    "sg:province":"FL",
    "sg:tags":[
        "commercial",
        "storage"
    ],
    "wof:name":"Public Storage",
    "wof:placetype":"venue"
},
  "geometry": {"coordinates":[-80.37732,27.419549],"type":"Point"}
}