{
  "type": "Feature",
  "properties": {
    "iso:country":"US",
    "sg:address":"7857 SW 103rd Pl",
    "sg:city":"Miami",
    "sg:classifiers":[
        {
            "category":"Banks & Credit Unions",
            "subcategory":"Bank",
            "type":"Services"
        }
    ],
    "sg:phone":"+1 305 596 5154",
    "sg:postcode":"33173",
    "sg:province":"FL",
    "sg:tags":[
        "broker",
        "mortgage"
    ],
    "wof:name":"Dbd Financial Services Inc",
    "wof:placetype":"venue"
},
  "geometry": {"coordinates":[-80.360635,25.696708],"type":"Point"}
}