{
  "type": "Feature",
  "properties": {
    "iso:country":"US",
    "sg:address":"18120 Collins Ave",
    "sg:city":"North Miami Beach",
    "sg:classifiers":[
        {
            "category":"Restaurant",
            "type":"Food & Drink"
        }
    ],
    "sg:phone":"+1 305 792 7776",
    "sg:postcode":"33160",
    "sg:province":"FL",
    "sg:tags":[
        "american",
        "latin"
    ],
    "sg:website":"www.elreydelchivito.com",
    "wof:name":"El Rey Del Chivito",
    "wof:placetype":"venue"
},
  "geometry": {"coordinates":[-80.121242,25.943545],"type":"Point"}
}