{
  "type": "Feature",
  "properties": {
    "iso:country":"US",
    "sg:address":"4810 N Howard Ave",
    "sg:city":"Tampa",
    "sg:classifiers":[
        {
            "category":"Place Of Worship",
            "subcategory":"Church",
            "type":"Public Place"
        },
        {
            "category":"Place Of Worship",
            "type":"Public Place"
        },
        {
            "category":"Organizations",
            "subcategory":"Religious Organization",
            "type":"Services"
        }
    ],
    "sg:phone":"+1 813 876 2470",
    "sg:postcode":"33603",
    "sg:province":"FL",
    "sg:tags":[
        "god",
        "churches-church",
        "churches-pentecostal"
    ],
    "wof:name":"Iglesia De Dios La Senda Antigua",
    "wof:placetype":"venue"
},
  "geometry": {"coordinates":[-82.482564,27.989063],"type":"Point"}
}