{
  "type": "Feature",
  "properties": {
    "addr:full":"12301 McGregor Palms Dr Fort Myers FL 33908",
    "addr:housenumber":"12301",
    "addr:postcode":"33908",
    "addr:street":"Mcgregor Palms Dr",
    "iso:country":"US",
    "sg:address":"12301 McGregor Palms Dr",
    "sg:city":"Fort Myers",
    "sg:classifiers":[
        {
            "category":"Autos & Motor Vehicles",
            "subcategory":"Fuel & Gas Station",
            "type":"Retail Goods"
        }
    ],
    "sg:phone":"+1 239 481 8955",
    "sg:postcode":"33908",
    "sg:province":"FL",
    "sg:tags":[
        "station",
        "gasoline"
    ],
    "wof:name":"Shell Island Construction Inc",
    "wof:placetype":"venue"
},
  "geometry": {"coordinates":[-81.962254,26.504809],"type":"Point"}
}