{
  "type": "Feature",
  "properties": {
    "iso:country":"US",
    "sg:address":"862 20th Pl",
    "sg:city":"Vero Beach",
    "sg:classifiers":[
        {
            "category":"Organizations",
            "subcategory":"Labor Organization",
            "type":"Services"
        }
    ],
    "sg:phone":"+1 772 978 0011",
    "sg:postcode":"32960",
    "sg:province":"FL",
    "wof:name":"Local 769",
    "wof:placetype":"venue"
},
  "geometry": {"coordinates":[-80.389844,27.638955],"type":"Point"}
}