{
  "type": "Feature",
  "properties": {
    "addr:full":"10778 Greenbriar Villa Dr Lake Worth FL 33449",
    "addr:housenumber":"10778",
    "addr:postcode":"33449",
    "addr:street":"Greenbriar Villa Dr",
    "iso:country":"US",
    "sg:address":"10778 Greenbriar Villa Dr",
    "sg:city":"Lake Worth",
    "sg:classifiers":[
        {
            "category":"Banks & Credit Unions",
            "subcategory":"Investment Brokerage",
            "type":"Services"
        }
    ],
    "sg:phone":"+1 561 969 3353",
    "sg:postcode":"33449",
    "sg:province":"FL",
    "sg:tags":[
        "consultant",
        "planning",
        "financial"
    ],
    "wof:name":"Dunkirk Financial Partners",
    "wof:placetype":"venue"
},
  "geometry": {"coordinates":[-80.21675399999999,26.610325],"type":"Point"}
}