{
  "type": "Feature",
  "properties": {
    "addr:full":"4324 Atlantic Blvd Jacksonville FL 32207",
    "addr:housenumber":"4324",
    "addr:postcode":"32207",
    "addr:street":"Atlantic Blvd",
    "iso:country":"US",
    "sg:address":"4324 Atlantic Blvd",
    "sg:city":"Jacksonville",
    "sg:classifiers":[
        {
            "category":"Deli",
            "type":"Food & Drink"
        }
    ],
    "sg:menulink":"http://www.allmenus.com/fl/jacksonville/126050-blimpie-subs--sandwiches/menu/",
    "sg:phone":"+1 904 398 9444",
    "sg:postcode":"32207",
    "sg:province":"FL",
    "sg:tags":[
        "wrap",
        "american",
        "sandwich"
    ],
    "wof:name":"Blimpie Subs & Sandwiches",
    "wof:placetype":"venue"
},
  "geometry": {"coordinates":[-81.619958,30.307308],"type":"Point"}
}