{
  "type": "Feature",
  "properties": {
    "iso:country":"US",
    "sg:address":"3240 W 16th Ave",
    "sg:city":"Hialeah",
    "sg:classifiers":[
        {
            "category":"Manufacturing",
            "subcategory":"Printing",
            "type":"Manufacturing & Wholesale Goods"
        }
    ],
    "sg:phone":"+1 305 888 3528",
    "sg:postcode":"33012",
    "sg:province":"FL",
    "sg:tags":[
        "lithographic",
        "commercial",
        "manifold",
        "business",
        "mfg"
    ],
    "wof:name":"Tiger Business Forms Inc",
    "wof:placetype":"venue"
},
  "geometry": {"coordinates":[-80.314457,25.854659],"type":"Point"}
}