{
  "type": "Feature",
  "properties": {
    "iso:country":"US",
    "sg:address":"468 S Spring Garden Ave",
    "sg:city":"Deland",
    "sg:classifiers":[
        {
            "category":"Insurance",
            "subcategory":"Insurance Agent",
            "type":"Services"
        },
        {
            "category":"Insurance",
            "subcategory":"Hazard Insurance",
            "type":"Services"
        },
        {
            "category":"Insurance",
            "subcategory":"Title Insurance",
            "type":"Services"
        },
        {
            "category":"Insurance",
            "subcategory":"Life Insurance",
            "type":"Services"
        }
    ],
    "sg:phone":"+1 386 734 6551",
    "sg:postcode":"32720",
    "sg:province":"FL",
    "sg:tags":[
        "business",
        "auto",
        "commercial",
        "homeowner",
        "motorcycle",
        "renter"
    ],
    "wof:name":"Allstate Insurance Company - Dennis Cowart",
    "wof:placetype":"venue"
},
  "geometry": {"coordinates":[-81.32402,29.021641],"type":"Point"}
}