{
  "type": "Feature",
  "properties": {
    "addr:full":"7124 E Hwy 22 Panama City FL 32404",
    "addr:housenumber":"7124",
    "addr:postcode":"32404",
    "addr:street":"E Hwy 22",
    "iso:country":"US",
    "sg:address":"7124 E Hwy 22",
    "sg:city":"Panama City",
    "sg:classifiers":[
        {
            "category":"Organizations",
            "subcategory":"Religious Organization",
            "type":"Services"
        }
    ],
    "sg:phone":"+1 850 874 9745",
    "sg:postcode":"32404",
    "sg:province":"FL",
    "sg:tags":[
        "church"
    ],
    "wof:name":"High Praise Worship Ctr",
    "wof:placetype":"venue"
},
  "geometry": {"coordinates":[-85.568759,30.152819],"type":"Point"}
}