{
  "type": "Feature",
  "properties": {
    "iso:country":"US",
    "sg:address":"2365 US Hwy 19",
    "sg:city":"Perry",
    "sg:classifiers":[
        {
            "category":"Manufacturing",
            "subcategory":"Lumber",
            "type":"Manufacturing & Wholesale Goods"
        }
    ],
    "sg:phone":"+1 850 584 7030",
    "sg:postcode":"32347",
    "sg:province":"FL",
    "sg:tags":[
        "logging",
        "operation",
        "tract",
        "mill",
        "pulp",
        "timber"
    ],
    "wof:name":"Rigoni M A Inc Ofc",
    "wof:placetype":"venue"
},
  "geometry": {"coordinates":[-83.60779700000001,30.141218],"type":"Point"}
}