{
  "type": "Feature",
  "properties": {
    "addr:full":"1801 S Andrews Ave Fort Lauderdale FL 33316",
    "addr:housenumber":"1801",
    "addr:postcode":"33316",
    "addr:street":"S Andrews Ave",
    "iso:country":"US",
    "sg:address":"1801 S Andrews Ave",
    "sg:city":"Fort Lauderdale",
    "sg:classifiers":[
        {
            "category":"Wholesale",
            "subcategory":"Machinery & Supplies",
            "type":"Manufacturing & Wholesale Goods"
        }
    ],
    "sg:phone":"+1 954 462 1963",
    "sg:postcode":"33316",
    "sg:province":"FL",
    "sg:tags":[
        "concrete",
        "pumping",
        "equipment"
    ],
    "wof:name":"Awak Corp",
    "wof:placetype":"venue"
},
  "geometry": {"coordinates":[-80.141486,26.097973],"type":"Point"}
}