{
  "type": "Feature",
  "properties": {
    "iso:country":"US",
    "sg:address":"2323 Grove St",
    "sg:city":"Sarasota",
    "sg:classifiers":[
        {
            "category":"Professional",
            "type":"Services"
        }
    ],
    "sg:phone":"+1 941 365 7377",
    "sg:postcode":"34239",
    "sg:province":"FL",
    "wof:name":"Under The Sun of Sarasota Inc",
    "wof:placetype":"venue"
},
  "geometry": {"coordinates":[-82.52386799999999,27.309691],"type":"Point"}
}