{
  "type": "Feature",
  "properties": {
    "iso:country":"US",
    "sg:address":"3100 E Robinson St",
    "sg:city":"Orlando",
    "sg:classifiers":[
        {
            "category":"Personal",
            "subcategory":"Beauty Salon",
            "type":"Services"
        }
    ],
    "sg:phone":"+1 407 841 1759",
    "sg:postcode":"32803",
    "sg:province":"FL",
    "wof:name":"Lionel's-Pam & Peggy",
    "wof:placetype":"venue"
},
  "geometry": {"coordinates":[-81.345755,28.545999],"type":"Point"}
}