{
  "type": "Feature",
  "properties": {
    "iso:country":"US",
    "sg:address":"3515 Reid St",
    "sg:city":"Palatka",
    "sg:classifiers":[
        {
            "category":"Wholesale",
            "subcategory":"Auto Parts",
            "type":"Manufacturing & Wholesale Goods"
        }
    ],
    "sg:phone":"+1 386 312 8445",
    "sg:postcode":"32177",
    "sg:province":"FL",
    "sg:tags":[
        "body",
        "shop",
        "automotive",
        "retailer",
        "custom",
        "paint",
        "automobile",
        "wholesaler"
    ],
    "wof:name":"Hall's Custom Colors",
    "wof:placetype":"venue"
},
  "geometry": {"coordinates":[-81.66633299999999,29.657409],"type":"Point"}
}