{
  "type": "Feature",
  "properties": {
    "iso:country":"US",
    "sg:address":"1541 NE 34th Ct",
    "sg:city":"Pompano Beach",
    "sg:classifiers":[
        {
            "category":"Professional",
            "subcategory":"Employment Agencies",
            "type":"Services"
        }
    ],
    "sg:phone":"+1 954 781 8663",
    "sg:postcode":"33064",
    "sg:province":"FL",
    "wof:name":"Ridgeway Association Group",
    "wof:placetype":"venue"
},
  "geometry": {"coordinates":[-80.101328,26.274062],"type":"Point"}
}