{
  "type": "Feature",
  "properties": {
    "addr:full":"1908 Oakwood Ave Tampa FL 33605",
    "addr:housenumber":"1908",
    "addr:postcode":"33605",
    "addr:street":"Oakwood Ave",
    "iso:country":"US",
    "sg:address":"1908 Oakwood Ave",
    "sg:city":"Tampa",
    "sg:classifiers":[
        {
            "category":"Manufacturing",
            "subcategory":"Tools & Machinery",
            "type":"Manufacturing & Wholesale Goods"
        }
    ],
    "sg:phone":"+1 813 248 8955",
    "sg:postcode":"33605",
    "sg:province":"FL",
    "sg:tags":[
        "industrial",
        "mfg"
    ],
    "wof:name":"Charles Machine Shop",
    "wof:placetype":"venue"
},
  "geometry": {"coordinates":[-82.43682699999999,27.939723],"type":"Point"}
}