{
  "type": "Feature",
  "properties": {
    "iso:country":"US",
    "sg:address":"16655 NE Co Rd 339",
    "sg:city":"Trenton",
    "sg:classifiers":[
        {
            "category":"Organizations",
            "subcategory":"Religious Organization",
            "type":"Services"
        }
    ],
    "sg:phone":"+1 352 463 2151",
    "sg:postcode":"32693",
    "sg:province":"FL",
    "sg:website":"www.pinegrovebaptistchurchtrentonfl.com",
    "wof:name":"Pine Grove Baptist Church",
    "wof:placetype":"venue"
},
  "geometry": {"coordinates":[-82.77740799999999,29.57066],"type":"Point"}
}