{
  "type": "Feature",
  "properties": {
    "iso:country":"US",
    "sg:address":"1511 Sligh Blvd",
    "sg:city":"Orlando",
    "sg:classifiers":[
        {
            "category":"Health Services",
            "subcategory":"Doctor",
            "type":"Services"
        }
    ],
    "sg:phone":"+1 407 316 0156",
    "sg:postcode":"32806",
    "sg:province":"FL",
    "sg:tags":[
        "physician",
        "gynecology",
        "surgeons",
        "obstetrics",
        "surgeon"
    ],
    "wof:name":"Van Dyke OBGYN MD PA",
    "wof:placetype":"venue"
},
  "geometry": {"coordinates":[-81.381135,28.523885],"type":"Point"}
}