{
  "type": "Feature",
  "properties": {
    "iso:country":"US",
    "sg:address":"3289 62nd St N",
    "sg:city":"Saint Petersburg",
    "sg:classifiers":[
        {
            "category":"Insurance",
            "subcategory":"Insurance Agent",
            "type":"Services"
        }
    ],
    "sg:phone":"+1 727 821 4011",
    "sg:postcode":"33710",
    "sg:province":"FL",
    "wof:name":"Vincent Frank & Associates",
    "wof:placetype":"venue"
},
  "geometry": {"coordinates":[-82.720803,27.802135],"type":"Point"}
}