{
  "type": "Feature",
  "properties": {
    "addr:full":"6250 Shirley St Naples FL 34109",
    "addr:housenumber":"6250",
    "addr:postcode":"34109",
    "addr:street":"Shirley St",
    "iso:country":"US",
    "sg:address":"6250 Shirley St",
    "sg:city":"Naples",
    "sg:classifiers":[
        {
            "category":"Home & Garden",
            "subcategory":"Carpets & Floor Coverings",
            "type":"Retail Goods"
        }
    ],
    "sg:phone":"+1 239 254 0166",
    "sg:postcode":"34109",
    "sg:province":"FL",
    "sg:tags":[
        "dealer",
        "rug"
    ],
    "wof:name":"Ali's Oriental Rugs",
    "wof:placetype":"venue"
},
  "geometry": {"coordinates":[-81.78155599999999,26.220956],"type":"Point"}
}