{
  "type": "Feature",
  "properties": {
    "addr:full":"1924 Premier Row Orlando FL 32809",
    "addr:housenumber":"1924",
    "addr:postcode":"32809",
    "addr:street":"Premier Row",
    "iso:country":"US",
    "sg:address":"1924 Premier Row",
    "sg:city":"Orlando",
    "sg:classifiers":[
        {
            "category":"Manufacturing",
            "subcategory":"Printing",
            "type":"Manufacturing & Wholesale Goods"
        }
    ],
    "sg:phone":"+1 407 857 2400",
    "sg:postcode":"32809",
    "sg:province":"FL",
    "sg:tags":[
        "print",
        "lithographic",
        "sup"
    ],
    "wof:name":"Triple L Press Inc",
    "wof:placetype":"venue"
},
  "geometry": {"coordinates":[-81.400963,28.46057],"type":"Point"}
}