{
  "type": "Feature",
  "properties": {
    "iso:country":"US",
    "sg:address":"960 Genoa St",
    "sg:city":"Miami",
    "sg:classifiers":[
        {
            "category":"Real Estate",
            "subcategory":"Real Estate Operator",
            "type":"Services"
        }
    ],
    "sg:phone":"+1 305 445 0154",
    "sg:postcode":"33134",
    "sg:province":"FL",
    "sg:tags":[
        "building",
        "apartment"
    ],
    "wof:name":"Vegas Apartments Corporation",
    "wof:placetype":"venue"
},
  "geometry": {"coordinates":[-80.28085799999999,25.762113],"type":"Point"}
}