{
  "type": "Feature",
  "properties": {
    "iso:country":"US",
    "sg:address":"5095 Okeechobee Rd",
    "sg:city":"West Palm Beach",
    "sg:classifiers":[
        {
            "category":"Home & Garden",
            "subcategory":"Furniture",
            "type":"Retail Goods"
        }
    ],
    "sg:phone":"+1 561 682 1113",
    "sg:postcode":"33417",
    "sg:province":"FL",
    "sg:tags":[
        "store"
    ],
    "sg:website":"www.jenniferfurniture.com",
    "wof:name":"Jennifer Convertibles Leather",
    "wof:placetype":"venue"
},
  "geometry": {"coordinates":[-80.121285,26.707115],"type":"Point"}
}