{
  "type": "Feature",
  "properties": {
    "iso:country":"US",
    "sg:address":"1620 W Parker St",
    "sg:city":"Lakeland",
    "sg:classifiers":[
        {
            "category":"Social Services",
            "subcategory":"Child Care",
            "type":"Services"
        }
    ],
    "sg:phone":"+1 863 688 8002",
    "sg:postcode":"33815",
    "sg:province":"FL",
    "wof:name":"Christ Community Christian Ctr",
    "wof:placetype":"venue"
},
  "geometry": {"coordinates":[-81.981931,28.050894],"type":"Point"}
}