{
  "type": "Feature",
  "properties": {
    "addr:full":"1529 Margaret St Jacksonville FL 32204",
    "addr:housenumber":"1529",
    "addr:postcode":"32204",
    "addr:street":"Margaret St",
    "iso:country":"US",
    "sg:address":"1529 Margaret St",
    "sg:city":"Jacksonville",
    "sg:classifiers":[
        {
            "category":"Professional",
            "subcategory":"Testing Lab",
            "type":"Services"
        },
        {
            "category":"Personal",
            "type":"Services"
        }
    ],
    "sg:phone":"+1 904 358 9055",
    "sg:postcode":"32204",
    "sg:province":"FL",
    "sg:tags":[
        "typing",
        "blood",
        "paternity"
    ],
    "wof:name":"First Coast Testing Services",
    "wof:placetype":"venue"
},
  "geometry": {"coordinates":[-81.681269,30.313584],"type":"Point"}
}