{
  "type": "Feature",
  "properties": {
    "addr:full":"13198 Spring Hill Dr Spring Hill FL 34609",
    "addr:housenumber":"13198",
    "addr:postcode":"34609",
    "addr:street":"Spring Hill Dr",
    "iso:country":"US",
    "sg:address":"13198 Spring Hill Dr",
    "sg:city":"Spring Hill",
    "sg:classifiers":[
        {
            "category":"Retail",
            "subcategory":"Animal Services",
            "type":"Services"
        }
    ],
    "sg:phone":"+1 352 688 2323",
    "sg:postcode":"34609",
    "sg:province":"FL",
    "wof:name":"Its A Dogs Life",
    "wof:placetype":"venue"
},
  "geometry": {"coordinates":[-82.51129,28.466974],"type":"Point"}
}