{
  "type": "Feature",
  "properties": {
    "addr:full":"1171 Beach Blvd Jacksonville Bch FL 32250",
    "addr:housenumber":"1171",
    "addr:postcode":"32250",
    "addr:street":"Beach Blvd",
    "iso:country":"US",
    "sg:address":"1171 Beach Blvd",
    "sg:city":"Jacksonville Bch",
    "sg:classifiers":[
        {
            "category":"Building & Trades",
            "subcategory":"Construction",
            "type":"Services"
        }
    ],
    "sg:phone":"+1 904 246 0375",
    "sg:postcode":"32250",
    "sg:province":"FL",
    "sg:tags":[
        "contractor"
    ],
    "wof:name":"Thompson General Contractors",
    "wof:placetype":"venue"
},
  "geometry": {"coordinates":[-81.401015,30.288303],"type":"Point"}
}