{
  "type": "Feature",
  "properties": {
    "addr:full":"11438 Phillips Hwy Jacksonville FL 32256",
    "addr:housenumber":"11438",
    "addr:postcode":"32256",
    "addr:street":"Phillips Hwy",
    "iso:country":"US",
    "sg:address":"11438 Phillips Hwy",
    "sg:city":"Jacksonville",
    "sg:classifiers":[
        {
            "category":"Wholesale",
            "subcategory":"Durable Goods & Equipment",
            "type":"Manufacturing & Wholesale Goods"
        }
    ],
    "sg:phone":"+1 904 387 2411",
    "sg:postcode":"32256",
    "sg:province":"FL",
    "sg:tags":[
        "exporter"
    ],
    "wof:name":"Omiga C Posey",
    "wof:placetype":"venue"
},
  "geometry": {"coordinates":[-81.536933,30.163695],"type":"Point"}
}