{
  "type": "Feature",
  "properties": {
    "iso:country":"US",
    "sg:address":"704 34th St SE",
    "sg:city":"Largo",
    "sg:classifiers":[
        {
            "category":"Building & Trades",
            "subcategory":"Construction",
            "type":"Services"
        }
    ],
    "sg:phone":"+1 727 531 1108",
    "sg:postcode":"33771",
    "sg:province":"FL",
    "sg:tags":[
        "repair",
        "handyman",
        "maintenance",
        "home"
    ],
    "wof:name":"Dan The Handy Man",
    "wof:placetype":"venue"
},
  "geometry": {"coordinates":[-82.751614,27.90946],"type":"Point"}
}