{
  "type": "Feature",
  "properties": {
    "iso:country":"US",
    "sg:address":"3658 Tallavana Trl",
    "sg:city":"Havana",
    "sg:classifiers":[
        {
            "category":"Building & Trades",
            "subcategory":"Landscaping Services",
            "type":"Services"
        }
    ],
    "sg:phone":"+1 850 539 3375",
    "sg:postcode":"32333",
    "sg:province":"FL",
    "wof:name":"Buys Lawn Service",
    "wof:placetype":"venue"
},
  "geometry": {"coordinates":[-84.45968999999999,30.59451],"type":"Point"}
}