{
  "type": "Feature",
  "properties": {
    "iso:country":"US",
    "sg:address":"255 8th St S",
    "sg:city":"Naples",
    "sg:classifiers":[
        {
            "category":"Professional",
            "subcategory":"Lawyer & Legal Services",
            "type":"Services"
        }
    ],
    "sg:phone":"+1 239 263 2059",
    "sg:postcode":"34102",
    "sg:province":"FL",
    "sg:tags":[
        "law"
    ],
    "wof:name":"Mediation Arbrtration Svcs Inc",
    "wof:placetype":"venue"
},
  "geometry": {"coordinates":[-81.79662399999999,26.145616],"type":"Point"}
}