{
  "type": "Feature",
  "properties": {
    "iso:country":"US",
    "sg:address":"2460 N State Rd 7",
    "sg:city":"Lauderdale Lakes",
    "sg:classifiers":[
        {
            "category":"Retail",
            "subcategory":"Auto Rental",
            "type":"Services"
        }
    ],
    "sg:phone":"+1 954 485 4465",
    "sg:postcode":"33313",
    "sg:province":"FL",
    "sg:tags":[
        "renting",
        "truck",
        "leasing"
    ],
    "wof:name":"U-Haul Co",
    "wof:placetype":"venue"
},
  "geometry": {"coordinates":[-80.202962,26.157587],"type":"Point"}
}