{
  "type": "Feature",
  "properties": {
    "iso:country":"US",
    "sg:address":"3327 Laurel Dale Dr",
    "sg:city":"Tampa",
    "sg:classifiers":[
        {
            "category":"Banks & Credit Unions",
            "subcategory":"Financial Services",
            "type":"Services"
        }
    ],
    "sg:phone":"+1 813 264 5106",
    "sg:postcode":"33618",
    "sg:province":"FL",
    "sg:tags":[
        "trust",
        "management"
    ],
    "wof:name":"Linda Hedrick Trustee",
    "wof:placetype":"venue"
},
  "geometry": {"coordinates":[-82.499639,28.114906],"type":"Point"}
}