{
  "type": "Feature",
  "properties": {
    "iso:country":"US",
    "sg:address":"324 N Nova Rd",
    "sg:city":"Ormond Beach",
    "sg:classifiers":[
        {
            "category":"Restaurant",
            "type":"Food & Drink"
        }
    ],
    "sg:menulink":"http://www.allmenus.com/fl/ormond-beach/249797-steakhouse/menu/",
    "sg:phone":"+1 386 671 9992",
    "sg:postcode":"32174",
    "sg:province":"FL",
    "sg:tags":[
        "american",
        "steakhouse"
    ],
    "wof:name":"Steakhouse",
    "wof:placetype":"venue"
},
  "geometry": {"coordinates":[-81.08357700000001,29.285761],"type":"Point"}
}