{
  "type": "Feature",
  "properties": {
    "iso:country":"US",
    "sg:address":"611 Mount Homer Rd",
    "sg:city":"Eustis",
    "sg:classifiers":[
        {
            "category":"Real Estate",
            "subcategory":"Real Estate Operator",
            "type":"Services"
        }
    ],
    "sg:phone":"+1 352 589 0888",
    "sg:postcode":"32726",
    "sg:province":"FL",
    "sg:tags":[
        "building",
        "apartment"
    ],
    "wof:name":"Deerwood Apartments Ltd",
    "wof:placetype":"venue"
},
  "geometry": {"coordinates":[-81.692155,28.829265],"type":"Point"}
}