{
  "type": "Feature",
  "properties": {
    "iso:country":"US",
    "sg:address":"2727 Apalachee Pkwy",
    "sg:city":"Tallahassee",
    "sg:classifiers":[
        {
            "category":"Real Estate",
            "subcategory":"Real Estate Services",
            "type":"Services"
        },
        {
            "category":"Real Estate",
            "subcategory":"Real Estate Agent",
            "type":"Services"
        }
    ],
    "sg:phone":"+1 850 878 6189",
    "sg:postcode":"32301",
    "sg:province":"FL",
    "sg:tags":[
        "management"
    ],
    "wof:name":"Properties 2 Redd",
    "wof:placetype":"venue"
},
  "geometry": {"coordinates":[-84.23351099999999,30.427001],"type":"Point"}
}