{
  "type": "Feature",
  "properties": {
    "iso:country":"US",
    "sg:address":"1500 Bay Rd",
    "sg:city":"Miami Beach",
    "sg:classifiers":[
        {
            "category":"Travel",
            "subcategory":"Travel Agent",
            "type":"Entertainment"
        }
    ],
    "sg:phone":"+1 954 394 9299",
    "sg:postcode":"33139",
    "sg:province":"FL",
    "sg:tags":[
        "rental",
        "vacation"
    ],
    "sg:website":"www.weownsouthbeach.com",
    "wof:name":"WeOwnSouthBeach",
    "wof:placetype":"venue"
},
  "geometry": {"coordinates":[-80.144282,25.78628],"type":"Point"}
}