{
  "type": "Feature",
  "properties": {
    "iso:country":"US",
    "sg:address":"6015 W Farkas Rd",
    "sg:city":"Plant City",
    "sg:classifiers":[
        {
            "category":"Organizations",
            "subcategory":"Religious Organization",
            "type":"Services"
        }
    ],
    "sg:phone":"+1 813 737 3739",
    "sg:postcode":"33567",
    "sg:province":"FL",
    "sg:tags":[
        "church"
    ],
    "sg:website":"www.ahavabaptistchurch.com",
    "wof:name":"Ahava Baptist Church",
    "wof:placetype":"venue"
},
  "geometry": {"coordinates":[-82.172774,27.942184],"type":"Point"}
}