{
  "type": "Feature",
  "properties": {
    "addr:full":"5302 Bobby St Orlando FL 32807",
    "addr:housenumber":"5302",
    "addr:postcode":"32807",
    "addr:street":"Bobby St",
    "iso:country":"US",
    "sg:address":"5302 Bobby St",
    "sg:city":"Orlando",
    "sg:classifiers":[
        {
            "category":"Professional",
            "subcategory":"Management & Consulting",
            "type":"Services"
        }
    ],
    "sg:phone":"+1 407 273 3191",
    "sg:postcode":"32807",
    "sg:province":"FL",
    "sg:tags":[
        "consultant"
    ],
    "wof:name":"Mischelle H Jamieson Conslnt",
    "wof:placetype":"venue"
},
  "geometry": {"coordinates":[-81.316864,28.544809],"type":"Point"}
}