{
  "type": "Feature",
  "properties": {
    "addr:full":"15627 Century Dr Hudson FL 34667",
    "addr:housenumber":"15627",
    "addr:postcode":"34667",
    "addr:street":"Century Dr",
    "iso:country":"US",
    "sg:address":"15627 Century Dr",
    "sg:city":"Hudson",
    "sg:classifiers":[
        {
            "category":"Professional",
            "subcategory":"Computer Services",
            "type":"Services"
        }
    ],
    "sg:phone":"+1 727 869 7614",
    "sg:postcode":"34667",
    "sg:province":"FL",
    "sg:tags":[
        "repair"
    ],
    "wof:name":"Rodney T Rigby",
    "wof:placetype":"venue"
},
  "geometry": {"coordinates":[-82.697563,28.386084],"type":"Point"}
}