{
  "type": "Feature",
  "properties": {
    "iso:country":"US",
    "sg:address":"5872 Northpointe Ln",
    "sg:city":"Boynton Beach",
    "sg:classifiers":[
        {
            "category":"Building & Trades",
            "subcategory":"Landscaping Services",
            "type":"Services"
        }
    ],
    "sg:phone":"+1 561 369 8966",
    "sg:postcode":"33437",
    "sg:province":"FL",
    "wof:name":"Gulfstream Tree Care Inc",
    "wof:placetype":"venue"
},
  "geometry": {"coordinates":[-80.13772,26.496167],"type":"Point"}
}