{
  "type": "Feature",
  "properties": {
    "addr:full":"4245 Pine Island Rd NW Matlacha FL 33993",
    "addr:housenumber":"4245",
    "addr:postcode":"33993",
    "addr:street":"Pine Island Rd Nw Matlacha",
    "iso:country":"US",
    "sg:address":"4245 Pine Island Rd NW",
    "sg:city":"Matlacha",
    "sg:classifiers":[
        {
            "category":"Insurance",
            "subcategory":"Insurance Agent",
            "type":"Services"
        }
    ],
    "sg:phone":"+1 239 282 2233",
    "sg:postcode":"33993",
    "sg:province":"FL",
    "wof:name":"American Insurance",
    "wof:placetype":"venue"
},
  "geometry": {"coordinates":[-82.066982,26.633469],"type":"Point"}
}