{
  "type": "Feature",
  "properties": {
    "iso:country":"US",
    "sg:address":"7400 Cedar St NE",
    "sg:city":"Saint Petersburg",
    "sg:classifiers":[
        {
            "category":"Shopping",
            "type":"Retail Goods"
        }
    ],
    "sg:phone":"+1 727 522 8415",
    "sg:postcode":"33702",
    "sg:province":"FL",
    "sg:tags":[
        "ice"
    ],
    "wof:name":"Freemans Ice",
    "wof:placetype":"venue"
},
  "geometry": {"coordinates":[-82.63220099999999,27.841206],"type":"Point"}
}