{
  "type": "Feature",
  "properties": {
    "iso:country":"US",
    "sg:address":"1400 N US Hwy 1",
    "sg:city":"Rockledge",
    "sg:classifiers":[
        {
            "category":"Wholesale",
            "subcategory":"Beer",
            "type":"Manufacturing & Wholesale Goods"
        }
    ],
    "sg:phone":"+1 321 636 4219",
    "sg:postcode":"32955",
    "sg:province":"FL",
    "wof:name":"Stop & Save",
    "wof:placetype":"venue"
},
  "geometry": {"coordinates":[-80.72323299999999,28.331522],"type":"Point"}
}