{
  "type": "Feature",
  "properties": {
    "addr:full":"1603 W Shell Point Rd Ruskin FL 33570",
    "addr:housenumber":"1603",
    "addr:postcode":"33570",
    "addr:street":"W Shell Point Rd",
    "iso:country":"US",
    "sg:address":"1603 W Shell Point Rd",
    "sg:city":"Ruskin",
    "sg:classifiers":[
        {
            "category":"Freight",
            "type":"Transportation"
        }
    ],
    "sg:phone":"+1 813 645 0439",
    "sg:postcode":"33570",
    "sg:province":"FL",
    "sg:tags":[
        "operator",
        "local",
        "trucking"
    ],
    "wof:name":"D&G Trucking Services Inc",
    "wof:placetype":"venue"
},
  "geometry": {"coordinates":[-82.45424,27.720822],"type":"Point"}
}