{
  "type": "Feature",
  "properties": {
    "iso:country":"US",
    "sg:address":"406 Tomahawk Trl",
    "sg:city":"Brandon",
    "sg:classifiers":[
        {
            "category":"Home & Garden",
            "subcategory":"Hardware",
            "type":"Retail Goods"
        }
    ],
    "sg:phone":"+1 813 689 1412",
    "sg:postcode":"33511",
    "sg:province":"FL",
    "sg:tags":[
        "valve"
    ],
    "wof:name":"D & B Supply Inc",
    "wof:placetype":"venue"
},
  "geometry": {"coordinates":[-82.27399,27.867317],"type":"Point"}
}