{
  "type": "Feature",
  "properties": {
    "iso:country":"US",
    "sg:address":"3708 Deborah Dr",
    "sg:city":"Lakeland",
    "sg:classifiers":[
        {
            "category":"Place Of Worship",
            "type":"Public Place"
        }
    ],
    "sg:phone":"+1 863 815 0099",
    "sg:postcode":"33810",
    "sg:province":"FL",
    "sg:tags":[
        "church"
    ],
    "wof:name":"Vida Abundante Internacional O",
    "wof:placetype":"venue"
},
  "geometry": {"coordinates":[-82.02160000000001,28.109541],"type":"Point"}
}