{
  "type": "Feature",
  "properties": {
    "iso:country":"US",
    "sg:address":"124 N Riverside Dr",
    "sg:city":"New Smyrna Beach",
    "sg:classifiers":[
        {
            "category":"Government",
            "subcategory":"Court House",
            "type":"Public Place"
        }
    ],
    "sg:phone":"+1 386 423 3313",
    "sg:postcode":"32168",
    "sg:province":"FL",
    "sg:tags":[
        "county"
    ],
    "wof:name":"Judge Mary J Henderson",
    "wof:placetype":"venue"
},
  "geometry": {"coordinates":[-80.921437,29.026535],"type":"Point"}
}