{
  "type": "Feature",
  "properties": {
    "iso:country":"US",
    "sg:address":"3872 Sheridan St",
    "sg:city":"Hollywood",
    "sg:classifiers":[
        {
            "category":"Health Services",
            "subcategory":"Doctor",
            "type":"Services"
        }
    ],
    "sg:phone":"+1 954 981 8481",
    "sg:postcode":"33021",
    "sg:province":"FL",
    "wof:name":"Sinclair & Sinclair",
    "wof:placetype":"venue"
},
  "geometry": {"coordinates":[-80.183566,26.032815],"type":"Point"}
}