{
  "type": "Feature",
  "properties": {
    "addr:full":"9612 Fontainebleau Blvd Miami FL 33172",
    "addr:housenumber":"9612",
    "addr:postcode":"33172",
    "addr:street":"Fontainebleau Blvd",
    "iso:country":"US",
    "sg:address":"9612 Fontainebleau Blvd",
    "sg:city":"Miami",
    "sg:classifiers":[
        {
            "category":"Restaurant",
            "type":"Food & Drink"
        }
    ],
    "sg:phone":"+1 305 220 3791",
    "sg:postcode":"33172",
    "sg:province":"FL",
    "sg:tags":[
        "american",
        "latin"
    ],
    "sg:website":"www.fritanga.com",
    "wof:name":"Fritanga Monimbo",
    "wof:placetype":"venue"
},
  "geometry": {"coordinates":[-80.350781,25.775357],"type":"Point"}
}