{
  "type": "Feature",
  "properties": {
    "iso:country":"US",
    "sg:address":"6404 US Hwy 19",
    "sg:city":"New Port Richey",
    "sg:classifiers":[
        {
            "category":"Food & Beverages",
            "subcategory":"Bakery",
            "type":"Retail Goods"
        }
    ],
    "sg:phone":"+1 727 869 3869",
    "sg:postcode":"34652",
    "sg:province":"FL",
    "sg:tags":[
        "baker"
    ],
    "wof:name":"Bestfoods Baking Co",
    "wof:placetype":"venue"
},
  "geometry": {"coordinates":[-82.727818,28.253407],"type":"Point"}
}