{
  "type": "Feature",
  "properties": {
    "iso:country":"US",
    "sg:address":"7110 Beech Ridge Trl",
    "sg:city":"Tallahassee",
    "sg:classifiers":[
        {
            "category":"Professional",
            "type":"Services"
        }
    ],
    "sg:phone":"+1 850 907 0169",
    "sg:postcode":"32312",
    "sg:province":"FL",
    "sg:tags":[
        "establishment"
    ],
    "wof:name":"Haworth C",
    "wof:placetype":"venue"
},
  "geometry": {"coordinates":[-84.214775,30.566351],"type":"Point"}
}