{
  "type": "Feature",
  "properties": {
    "iso:country":"US",
    "sg:address":"4216 Commercial Dr",
    "sg:city":"Sebring",
    "sg:classifiers":[
        {
            "category":"Building & Trades",
            "subcategory":"Electrical",
            "type":"Services"
        }
    ],
    "sg:phone":"+1 863 382 8666",
    "sg:postcode":"33870",
    "sg:province":"FL",
    "sg:tags":[
        "electrical",
        "contractor"
    ],
    "wof:name":"Dickey Electrical Construction",
    "wof:placetype":"venue"
},
  "geometry": {"coordinates":[-81.495237,27.5203],"type":"Point"}
}