{
  "type": "Feature",
  "properties": {
    "addr:full":"3655 Maguire Blvd Orlando FL 32803",
    "addr:housenumber":"3655",
    "addr:postcode":"32803",
    "addr:street":"Maguire Blvd",
    "iso:country":"US",
    "sg:address":"3655 Maguire Blvd",
    "sg:city":"Orlando",
    "sg:classifiers":[
        {
            "category":"Wholesale",
            "subcategory":"Toys & Hobbies",
            "type":"Manufacturing & Wholesale Goods"
        }
    ],
    "sg:phone":"+1 407 898 7925",
    "sg:postcode":"32803",
    "sg:province":"FL",
    "sg:tags":[
        "puppet",
        "marionette"
    ],
    "wof:name":"Miche Lee Puppets Inc",
    "wof:placetype":"venue"
},
  "geometry": {"coordinates":[-81.333749,28.560949],"type":"Point"}
}