{
  "type": "Feature",
  "properties": {
    "iso:country":"US",
    "sg:address":"7785 NW 146th St",
    "sg:city":"Hialeah",
    "sg:classifiers":[
        {
            "category":"Real Estate",
            "subcategory":"Real Estate Services",
            "type":"Services"
        }
    ],
    "sg:phone":"+1 305 364 9945",
    "sg:postcode":"33016",
    "sg:province":"FL",
    "sg:tags":[
        "commercial"
    ],
    "wof:name":"Sheridan Enterprises Inc",
    "wof:placetype":"venue"
},
  "geometry": {"coordinates":[-80.326617,25.906027],"type":"Point"}
}