{
  "type": "Feature",
  "properties": {
    "addr:full":"3144 3rd Ave S St Petersburg FL 33712",
    "addr:housenumber":"3144",
    "addr:postcode":"33712",
    "addr:street":"3Rd Ave S",
    "iso:country":"US",
    "sg:address":"3144 3rd Ave S",
    "sg:city":"St Petersburg",
    "sg:classifiers":[
        {
            "category":"Organizations",
            "subcategory":"Religious Organization",
            "type":"Services"
        }
    ],
    "sg:phone":"+1 727 323 7518",
    "sg:postcode":"33712",
    "sg:province":"FL",
    "sg:tags":[
        "church"
    ],
    "wof:name":"First Baptist Instnl Church",
    "wof:placetype":"venue"
},
  "geometry": {"coordinates":[-82.676158,27.7685],"type":"Point"}
}