{
  "type": "Feature",
  "properties": {
    "addr:full":"4321 Carnwath Rd Tallahassee FL 32303",
    "addr:postcode":"4321;32303",
    "addr:street":"Carnwath Rd",
    "iso:country":"US",
    "sg:address":"4321 Carnwath Rd",
    "sg:city":"Tallahassee",
    "sg:classifiers":[
        {
            "category":"Building & Trades",
            "subcategory":"Construction",
            "type":"Services"
        }
    ],
    "sg:phone":"+1 850 514 8895",
    "sg:postcode":"32303",
    "sg:province":"FL",
    "sg:tags":[
        "tile-contractors"
    ],
    "wof:name":"M.R. Tile",
    "wof:placetype":"venue"
},
  "geometry": {"coordinates":[-84.340639,30.494639],"type":"Point"}
}