{
  "type": "Feature",
  "properties": {
    "iso:country":"US",
    "sg:address":"10394 Myra St",
    "sg:city":"Spring Hill",
    "sg:classifiers":[
        {
            "category":"Building & Trades",
            "subcategory":"Construction",
            "type":"Services"
        }
    ],
    "sg:phone":"+1 352 585 1803",
    "sg:postcode":"34608",
    "sg:province":"FL",
    "sg:tags":[
        "residential",
        "commercial"
    ],
    "wof:name":"Td Prime Builders Inc",
    "wof:placetype":"venue"
},
  "geometry": {"coordinates":[-82.547842,28.479457],"type":"Point"}
}