{
  "type": "Feature",
  "properties": {
    "addr:full":"663 Coventry St Boca Raton FL 33487",
    "addr:housenumber":"663",
    "addr:postcode":"33487",
    "addr:street":"Coventry St",
    "iso:country":"US",
    "sg:address":"663 Coventry St",
    "sg:city":"Boca Raton",
    "sg:classifiers":[
        {
            "category":"Professional",
            "type":"Services"
        }
    ],
    "sg:phone":"+1 561 982 8501",
    "sg:postcode":"33487",
    "sg:province":"FL",
    "wof:name":"Ann Marie Mullin PA",
    "wof:placetype":"venue"
},
  "geometry": {"coordinates":[-80.075346,26.408385],"type":"Point"}
}