{
  "type": "Feature",
  "properties": {
    "addr:full":"17357 89th Pl N Loxahatchee FL 33470",
    "addr:housenumber":"17357",
    "addr:postcode":"33470",
    "addr:street":"89Th Pl N",
    "iso:country":"US",
    "sg:address":"17357 89th Pl N",
    "sg:city":"Loxahatchee",
    "sg:classifiers":[
        {
            "category":"Building & Trades",
            "subcategory":"Construction",
            "type":"Services"
        }
    ],
    "sg:phone":"+1 561 793 9511",
    "sg:postcode":"33470",
    "sg:province":"FL",
    "sg:tags":[
        "carpentry",
        "contractor"
    ],
    "wof:name":"Tdfs Carpentry Inc",
    "wof:placetype":"venue"
},
  "geometry": {"coordinates":[-80.316856,26.808067],"type":"Point"}
}