{
  "type": "Feature",
  "properties": {
    "iso:country":"US",
    "sg:address":"1395 N Courtenay Pkwy",
    "sg:city":"Merritt Island",
    "sg:classifiers":[
        {
            "category":"Health Services",
            "subcategory":"Health Practitioner",
            "type":"Services"
        }
    ],
    "sg:phone":"+1 321 459 1003",
    "sg:postcode":"32953",
    "sg:province":"FL",
    "sg:tags":[
        "psychologist"
    ],
    "wof:name":"Psychological Services",
    "wof:placetype":"venue"
},
  "geometry": {"coordinates":[-80.702682,28.381789],"type":"Point"}
}