{
  "type": "Feature",
  "properties": {
    "addr:full":"10463 E Greenwich Ct Boca Raton FL 33428",
    "addr:housenumber":"10463",
    "addr:postcode":"33428",
    "addr:street":"E Greenwich Ct",
    "iso:country":"US",
    "sg:address":"10463 E Greenwich Ct",
    "sg:city":"Boca Raton",
    "sg:classifiers":[
        {
            "category":"Building & Trades",
            "subcategory":"Construction",
            "type":"Services"
        }
    ],
    "sg:phone":"+1 561 558 8143",
    "sg:postcode":"33428",
    "sg:province":"FL",
    "sg:tags":[
        "house"
    ],
    "wof:name":"Spring of Life Construction",
    "wof:placetype":"venue"
},
  "geometry": {"coordinates":[-80.209858,26.348642],"type":"Point"}
}