{
  "type": "Feature",
  "properties": {
    "addr:full":"9700 NE 2nd Ave Miami FL 33138",
    "addr:housenumber":"9700",
    "addr:postcode":"33138",
    "addr:street":"Ne 2Nd Ave",
    "iso:country":"US",
    "sg:address":"9700 NE 2nd Ave",
    "sg:city":"Miami",
    "sg:classifiers":[
        {
            "category":"Real Estate",
            "subcategory":"Real Estate Agent",
            "type":"Services"
        }
    ],
    "sg:phone":"+1 305 754 9997",
    "sg:postcode":"33138",
    "sg:province":"FL",
    "wof:name":"Coldwell Banker Florida",
    "wof:placetype":"venue"
},
  "geometry": {"coordinates":[-80.193506,25.865284],"type":"Point"}
}