{
  "type": "Feature",
  "properties": {
    "iso:country":"US",
    "sg:address":"2776 Enterprise Rd",
    "sg:city":"Orange City",
    "sg:classifiers":[
        {
            "category":"Home & Garden",
            "subcategory":"Household Appliances",
            "type":"Retail Goods"
        }
    ],
    "sg:phone":"+1 386 774 1763",
    "sg:postcode":"32763",
    "sg:province":"FL",
    "wof:name":"Appliance Direct",
    "wof:placetype":"venue"
},
  "geometry": {"coordinates":[-81.288741,28.905073],"type":"Point"}
}