{
  "type": "Feature",
  "properties": {
    "addr:full":"55 SW 17 Road Miami FL 33129",
    "addr:housenumber":"55",
    "addr:postcode":"33129",
    "addr:street":"Sw 17 Road",
    "iso:country":"US",
    "sg:address":"55 SW 17 Road",
    "sg:city":"Miami",
    "sg:classifiers":[
        {
            "category":"Park",
            "type":"Public Place"
        }
    ],
    "sg:phone":"+1 305 856 6801",
    "sg:postcode":"33129",
    "sg:province":"FL",
    "wof:name":"Simpson Park",
    "wof:placetype":"venue"
},
  "geometry": {"coordinates":[-80.196782,25.757781],"type":"Point"}
}