{
  "type": "Feature",
  "properties": {
    "addr:full":"1808 Elmwood Dr Oldsmar FL 34677",
    "addr:housenumber":"1808",
    "addr:postcode":"34677",
    "addr:street":"Elmwood Dr",
    "iso:country":"US",
    "sg:address":"1808 Elmwood Dr",
    "sg:city":"Oldsmar",
    "sg:classifiers":[
        {
            "category":"Wholesale",
            "subcategory":"Non-durable Goods",
            "type":"Manufacturing & Wholesale Goods"
        }
    ],
    "sg:phone":"+1 813 814 0711",
    "sg:postcode":"34677",
    "sg:province":"FL",
    "sg:tags":[
        "advertising"
    ],
    "sg:website":"www.mouse-pads.com",
    "wof:name":"Computer Specialties",
    "wof:placetype":"venue"
},
  "geometry": {"coordinates":[-82.691997,28.042091],"type":"Point"}
}