{
  "type": "Feature",
  "properties": {
    "iso:country":"US",
    "sg:address":"4723 Orange Dr",
    "sg:city":"Davie",
    "sg:classifiers":[
        {
            "category":"Home & Garden",
            "subcategory":"Building Materials",
            "type":"Retail Goods"
        }
    ],
    "sg:phone":"+1 954 766 4887",
    "sg:postcode":"33314",
    "sg:province":"FL",
    "sg:tags":[
        "shutter"
    ],
    "wof:name":"5 Day Shutters",
    "wof:placetype":"venue"
},
  "geometry": {"coordinates":[-80.21046699999999,26.06638],"type":"Point"}
}