{
  "type": "Feature",
  "properties": {
    "iso:country":"US",
    "sg:address":"8600 NW South River Dr",
    "sg:city":"Medley",
    "sg:classifiers":[
        {
            "category":"Freight",
            "type":"Transportation"
        }
    ],
    "sg:phone":"+1 305 885 6588",
    "sg:postcode":"33166",
    "sg:province":"FL",
    "sg:tags":[
        "trucking"
    ],
    "wof:name":"Doyle Transportation Inc",
    "wof:placetype":"venue"
},
  "geometry": {"coordinates":[-80.321522,25.852598],"type":"Point"}
}