{
  "type": "Feature",
  "properties": {
    "addr:full":"2967 Vineland Rd Kissimmee FL 34746",
    "addr:housenumber":"2967",
    "addr:postcode":"34746",
    "addr:street":"Vineland Rd",
    "iso:country":"US",
    "sg:address":"2967 Vineland Rd",
    "sg:city":"Kissimmee",
    "sg:classifiers":[
        {
            "category":"Real Estate",
            "subcategory":"Real Estate Services",
            "type":"Services"
        },
        {
            "category":"Real Estate",
            "subcategory":"Real Estate Agent",
            "type":"Services"
        }
    ],
    "sg:phone":"+1 407 390 7359",
    "sg:postcode":"34746",
    "sg:province":"FL",
    "sg:tags":[
        "buyer",
        "broker"
    ],
    "sg:website":"http://www.century21.com",
    "wof:name":"Century 21",
    "wof:placetype":"venue"
},
  "geometry": {"coordinates":[-81.479541,28.33546],"type":"Point"}
}