{
  "type": "Feature",
  "properties": {
    "iso:country":"US",
    "sg:address":"200 Bass Ln",
    "sg:city":"Nokomis",
    "sg:classifiers":[
        {
            "category":"Building & Trades",
            "subcategory":"Construction",
            "type":"Services"
        }
    ],
    "sg:phone":"+1 941 488 7277",
    "sg:postcode":"34275",
    "sg:province":"FL",
    "sg:tags":[
        "contractor"
    ],
    "wof:name":"Advanced MBL HM Systems A M S",
    "wof:placetype":"venue"
},
  "geometry": {"coordinates":[-82.44317599999999,27.126036],"type":"Point"}
}