{
  "type": "Feature",
  "properties": {
    "addr:full":"39417 Bay Ave Zephyrhills FL 33540",
    "addr:housenumber":"39417",
    "addr:postcode":"33540",
    "addr:street":"Bay Ave",
    "iso:country":"US",
    "sg:address":"39417 Bay Ave",
    "sg:city":"Zephyrhills",
    "sg:classifiers":[
        {
            "category":"Building & Trades",
            "subcategory":"Landscaping Services",
            "type":"Services"
        }
    ],
    "sg:phone":"+1 813 715 4958",
    "sg:postcode":"33540",
    "sg:province":"FL",
    "wof:name":"Gator Kageys Tree Service",
    "wof:placetype":"venue"
},
  "geometry": {"coordinates":[-82.16470200000001,28.181656],"type":"Point"}
}