{
  "type": "Feature",
  "properties": {
    "iso:country":"US",
    "sg:address":"1101 Main St",
    "sg:city":"Daytona Beach",
    "sg:classifiers":[
        {
            "category":"Shopping",
            "subcategory":"Gifts & Souvenirs",
            "type":"Retail Goods"
        }
    ],
    "sg:phone":"+1 386 253 4563",
    "sg:postcode":"32118",
    "sg:province":"FL",
    "sg:tags":[
        "apparel",
        "bathing",
        "sport",
        "t",
        "suit"
    ],
    "wof:name":"Zenos",
    "wof:placetype":"venue"
},
  "geometry": {"coordinates":[-81.006962,29.227128],"type":"Point"}
}