{
  "type": "Feature",
  "properties": {
    "addr:full":"6354 Rambler Dr Pensacola FL 32505",
    "addr:housenumber":"6354",
    "addr:postcode":"32505",
    "addr:street":"Rambler Dr",
    "iso:country":"US",
    "sg:address":"6354 Rambler Dr",
    "sg:city":"Pensacola",
    "sg:classifiers":[
        {
            "category":"Building & Trades",
            "subcategory":"Construction",
            "type":"Services"
        }
    ],
    "sg:phone":"+1 850 474 0212",
    "sg:postcode":"32505",
    "sg:province":"FL",
    "sg:tags":[
        "paving",
        "contractor"
    ],
    "wof:name":"Cook Byron",
    "wof:placetype":"venue"
},
  "geometry": {"coordinates":[-87.261844,30.476426],"type":"Point"}
}