{
  "type": "Feature",
  "properties": {
    "addr:full":"6601 N 40th St Tampa FL 33610",
    "addr:housenumber":"6601",
    "addr:postcode":"33610",
    "addr:street":"N 40Th St",
    "iso:country":"US",
    "sg:address":"6601 N 40th St",
    "sg:city":"Tampa",
    "sg:classifiers":[
        {
            "category":"Autos & Motor Vehicles",
            "subcategory":"Auto Supplies",
            "type":"Retail Goods"
        }
    ],
    "sg:phone":"+1 813 620 4651",
    "sg:postcode":"33610",
    "sg:province":"FL",
    "wof:name":"Killer Tires",
    "wof:placetype":"venue"
},
  "geometry": {"coordinates":[-82.41428999999999,28.008367],"type":"Point"}
}