{
  "type": "Feature",
  "properties": {
    "iso:country":"US",
    "sg:address":"11310 Sheridan St",
    "sg:city":"Hollywood",
    "sg:classifiers":[
        {
            "category":"Professional",
            "subcategory":"Business Services",
            "type":"Services"
        }
    ],
    "sg:phone":"+1 954 432 8082",
    "sg:postcode":"33026",
    "sg:province":"FL",
    "wof:name":"Vassallo Family Enterprises",
    "wof:placetype":"venue"
},
  "geometry": {"coordinates":[-80.29804,26.02954],"type":"Point"}
}