{
  "type": "Feature",
  "properties": {
    "addr:full":"2063 N Atlantic Ave Cocoa Beach FL 32931",
    "addr:housenumber":"2063",
    "addr:postcode":"32931",
    "addr:street":"N Atlantic Ave",
    "iso:country":"US",
    "sg:address":"2063 N Atlantic Ave",
    "sg:city":"Cocoa Beach",
    "sg:classifiers":[
        {
            "category":"Shopping",
            "subcategory":"Department Store",
            "type":"Retail Goods"
        }
    ],
    "sg:phone":"+1 321 784 6217",
    "sg:postcode":"32931",
    "sg:province":"FL",
    "sg:website":"www.familydollar.com",
    "wof:name":"Family Dollar Store",
    "wof:placetype":"venue"
},
  "geometry": {"coordinates":[-80.6101,28.3426],"type":"Point"}
}