{
  "type": "Feature",
  "properties": {
    "addr:full":"12517 State Rd 535 Orlando FL 32836",
    "addr:housenumber":"12517;535",
    "addr:postcode":"32836",
    "addr:street":"State Rd",
    "iso:country":"US",
    "sg:address":"12517 State Rd 535",
    "sg:city":"Orlando",
    "sg:classifiers":[
        {
            "category":"Professional",
            "type":"Services"
        }
    ],
    "sg:phone":"+1 407 827 1265",
    "sg:postcode":"32836",
    "sg:province":"FL",
    "sg:tags":[
        "establishment"
    ],
    "wof:name":"Beyond Innovations",
    "wof:placetype":"venue"
},
  "geometry": {"coordinates":[-81.50559699999999,28.383112],"type":"Point"}
}