{
  "type": "Feature",
  "properties": {
    "iso:country":"US",
    "sg:address":"13711 Harrison St",
    "sg:city":"Miami",
    "sg:classifiers":[
        {
            "category":"Manufacturing",
            "subcategory":"Tools & Machinery",
            "type":"Manufacturing & Wholesale Goods"
        },
        {
            "category":"Retail",
            "subcategory":"Repair Shop",
            "type":"Services"
        }
    ],
    "sg:phone":"+1 305 233 9919",
    "sg:postcode":"33176",
    "sg:province":"FL",
    "sg:tags":[
        "machine",
        "machinery-rebuild"
    ],
    "wof:name":"Lous Machining Corp",
    "wof:placetype":"venue"
},
  "geometry": {"coordinates":[-80.376919,25.641271],"type":"Point"}
}