{
  "type": "Feature",
  "properties": {
    "addr:full":"61 Memorial Medical Pkwy Palm Coast FL 32164",
    "addr:housenumber":"61",
    "addr:postcode":"32164",
    "addr:street":"Medical Pkwy",
    "iso:country":"US",
    "sg:address":"61 Memorial Medical Pkwy",
    "sg:city":"Palm Coast",
    "sg:classifiers":[
        {
            "category":"Health Services",
            "subcategory":"Doctor",
            "type":"Services"
        }
    ],
    "sg:phone":"+1 386 586 4740",
    "sg:postcode":"32164",
    "sg:province":"FL",
    "sg:tags":[
        "physician",
        "surgeon"
    ],
    "wof:name":"Cancer Care Ctr",
    "wof:placetype":"venue"
},
  "geometry": {"coordinates":[-81.19048600000001,29.47764],"type":"Point"}
}