{
  "type": "Feature",
  "properties": {
    "iso:country":"US",
    "sg:address":"3773 W Flagler St",
    "sg:city":"Coral Gables",
    "sg:classifiers":[
        {
            "category":"Shopping",
            "subcategory":"Optician",
            "type":"Retail Goods"
        }
    ],
    "sg:phone":"+1 305 642 0020",
    "sg:postcode":"33134",
    "sg:province":"FL",
    "sg:tags":[
        "eyewear"
    ],
    "wof:name":"Eyes MD Optical",
    "wof:placetype":"venue"
},
  "geometry": {"coordinates":[-80.25631,25.77197],"type":"Point"}
}