{
  "type": "Feature",
  "properties": {
    "addr:full":"19 Sunrise Ave Ormond Beach FL 32176",
    "addr:housenumber":"19",
    "addr:postcode":"32176",
    "addr:street":"Sunrise Ave",
    "iso:country":"US",
    "sg:address":"19 Sunrise Ave",
    "sg:city":"Ormond Beach",
    "sg:classifiers":[
        {
            "category":"Building & Trades",
            "subcategory":"Cleaning & Sanitation",
            "type":"Services"
        }
    ],
    "sg:phone":"+1 386 441 9809",
    "sg:postcode":"32176",
    "sg:province":"FL",
    "sg:tags":[
        "janitor"
    ],
    "wof:name":"Lady In White Cleaning Svc",
    "wof:placetype":"venue"
},
  "geometry": {"coordinates":[-81.073221,29.350583],"type":"Point"}
}