{
  "type": "Feature",
  "properties": {
    "iso:country":"US",
    "sg:address":"8191 College Pkwy Ste 202",
    "sg:city":"Fort Myers",
    "sg:classifiers":[
        {
            "category":"Banks & Credit Unions",
            "subcategory":"Financial Services",
            "type":"Services"
        }
    ],
    "sg:phone":"+1 239 790 5626",
    "sg:postcode":"33919",
    "sg:province":"FL",
    "sg:tags":[
        "broker",
        "mortgage"
    ],
    "wof:name":"General Mortgage Corporation of America",
    "wof:placetype":"venue"
},
  "geometry": {"coordinates":[-81.88919799999999,26.556999],"type":"Point"}
}