{
  "type": "Feature",
  "properties": {
    "iso:country":"US",
    "sg:address":"4668 Cason Cove Dr",
    "sg:city":"Orlando",
    "sg:classifiers":[
        {
            "category":"Home & Garden",
            "subcategory":"Carpets & Floor Coverings",
            "type":"Retail Goods"
        }
    ],
    "sg:phone":"+1 321 331 3790",
    "sg:postcode":"32811",
    "sg:province":"FL",
    "sg:tags":[
        "material"
    ],
    "wof:name":"A C P Flooring Corp",
    "wof:placetype":"venue"
},
  "geometry": {"coordinates":[-81.439243,28.498205],"type":"Point"}
}