{
  "type": "Feature",
  "properties": {
    "iso:country":"US",
    "sg:address":"110 Phoenetia Ave",
    "sg:city":"Coral Gables",
    "sg:classifiers":[
        {
            "category":"Health Services",
            "subcategory":"Clinic",
            "type":"Services"
        },
        {
            "category":"Social Services",
            "subcategory":"Child Care",
            "type":"Services"
        }
    ],
    "sg:phone":"+1 305 567 5881",
    "sg:postcode":"33134",
    "sg:province":"FL",
    "sg:tags":[
        "medical",
        "day"
    ],
    "sg:website":"www.crystalacademycg.org/",
    "wof:name":"Crystal Academy Coral Gables",
    "wof:placetype":"venue"
},
  "geometry": {"coordinates":[-80.257645,25.760939],"type":"Point"}
}