{
  "type": "Feature",
  "properties": {
    "iso:country":"US",
    "sg:address":"111 Deland Ave",
    "sg:city":"Indialantic",
    "sg:classifiers":[
        {
            "category":"Shopping",
            "subcategory":"Clothing, Apparel, & Fashions",
            "type":"Retail Goods"
        }
    ],
    "sg:phone":"+1 321 956 3304",
    "sg:postcode":"32903",
    "sg:province":"FL",
    "sg:tags":[
        "dance"
    ],
    "wof:name":"Annettes Uitimate Dance",
    "wof:placetype":"venue"
},
  "geometry": {"coordinates":[-80.565551,28.079465],"type":"Point"}
}