{
  "type": "Feature",
  "properties": {
    "iso:country":"US",
    "sg:address":"1661 SW Bayshore Blvd",
    "sg:city":"Port St Lucie",
    "sg:classifiers":[
        {
            "category":"Education",
            "subcategory":"School",
            "type":"Public Place"
        }
    ],
    "sg:phone":"+1 772 340 4720",
    "sg:postcode":"34984",
    "sg:province":"FL",
    "wof:name":"Bayshore Elementary School",
    "wof:placetype":"venue"
},
  "geometry": {"coordinates":[-80.365787,27.292244],"type":"Point"}
}