{
  "type": "Feature",
  "properties": {
    "iso:country":"US",
    "sg:address":"12100 Pines Blvd",
    "sg:city":"Hollywood",
    "sg:classifiers":[
        {
            "category":"Restaurant",
            "type":"Food & Drink"
        }
    ],
    "sg:menulink":"http://www.allmenus.com/fl/miramar-pembroke-pines/106690-on-the-border/menu/",
    "sg:phone":"+1 954 437 3787",
    "sg:postcode":"33026",
    "sg:province":"FL",
    "sg:tags":[
        "mexican"
    ],
    "wof:name":"On The Border",
    "wof:placetype":"venue"
},
  "geometry": {"coordinates":[-80.309135,26.007653],"type":"Point"}
}