{
  "type": "Feature",
  "properties": {
    "addr:full":"3435 49th St N St Petersburg FL 33710",
    "addr:housenumber":"3435",
    "addr:postcode":"33710",
    "addr:street":"49Th St N",
    "iso:country":"US",
    "sg:address":"3435 49th St N",
    "sg:city":"St Petersburg",
    "sg:classifiers":[
        {
            "category":"Shopping",
            "subcategory":"Optical Goods",
            "type":"Retail Goods"
        }
    ],
    "sg:phone":"+1 727 522 8423",
    "sg:postcode":"33710",
    "sg:province":"FL",
    "sg:tags":[
        "optician"
    ],
    "wof:name":"Disston Optical",
    "wof:placetype":"venue"
},
  "geometry": {"coordinates":[-82.699996,27.806377],"type":"Point"}
}