{
  "type": "Feature",
  "properties": {
    "addr:full":"1800 E Oakland Park Blvd Oakland Park FL 33334",
    "addr:housenumber":"1800",
    "addr:postcode":"33334",
    "addr:street":"E Oakland Park Blvd",
    "iso:country":"US",
    "sg:address":"1800 E Oakland Park Blvd",
    "sg:city":"Oakland Park",
    "sg:classifiers":[
        {
            "category":"Organizations",
            "subcategory":"Religious Organization",
            "type":"Services"
        }
    ],
    "sg:phone":"+1 954 928 0448",
    "sg:postcode":"33334",
    "sg:province":"FL",
    "sg:tags":[
        "church"
    ],
    "wof:name":"St Mark's Episcopal",
    "wof:placetype":"venue"
},
  "geometry": {"coordinates":[-80.12217099999999,26.167128],"type":"Point"}
}