{
  "type": "Feature",
  "properties": {
    "addr:full":"212 Apollo Beach Blvd Ruskin FL 33572",
    "addr:housenumber":"212",
    "addr:postcode":"33572",
    "addr:street":"Apollo Beach Blvd",
    "iso:country":"US",
    "sg:address":"212 Apollo Beach Blvd",
    "sg:city":"Ruskin",
    "sg:classifiers":[
        {
            "category":"Professional",
            "subcategory":"Accounting & Tax Preparation",
            "type":"Services"
        }
    ],
    "sg:phone":"+1 813 641 1040",
    "sg:postcode":"33572",
    "sg:province":"FL",
    "sg:tags":[
        "return",
        "filing"
    ],
    "wof:name":"H & R Block Tax Svc",
    "wof:placetype":"venue"
},
  "geometry": {"coordinates":[-82.394699,27.771927],"type":"Point"}
}