{
  "type": "Feature",
  "properties": {
    "addr:full":"2319 Lancelot Dr Tallahassee FL 32309",
    "addr:housenumber":"2319",
    "addr:postcode":"32309",
    "addr:street":"Lancelot Dr",
    "iso:country":"US",
    "sg:address":"2319 Lancelot Dr",
    "sg:city":"Tallahassee",
    "sg:classifiers":[
        {
            "category":"Retail",
            "subcategory":"Laundry & Dry Cleaning",
            "type":"Services"
        }
    ],
    "sg:phone":"+1 850 422 2227",
    "sg:postcode":"32309",
    "sg:province":"FL",
    "sg:tags":[
        "cleaners",
        "rug",
        "carpet"
    ],
    "wof:name":"Extreme Carpet Care Inc",
    "wof:placetype":"venue"
},
  "geometry": {"coordinates":[-84.23654000000001,30.521696],"type":"Point"}
}