{
  "type": "Feature",
  "properties": {
    "iso:country":"US",
    "sg:address":"13205 US Hwy 1",
    "sg:city":"Juno Beach",
    "sg:classifiers":[
        {
            "category":"Retail",
            "subcategory":"Animal Services",
            "type":"Services"
        }
    ],
    "sg:phone":"+1 561 627 1549",
    "sg:postcode":"33408",
    "sg:province":"FL",
    "sg:tags":[
        "pet",
        "grooming",
        "washing"
    ],
    "wof:name":"Clip & Dip All Breed Grooming",
    "wof:placetype":"venue"
},
  "geometry": {"coordinates":[-80.055229,26.867379],"type":"Point"}
}