{
  "type": "Feature",
  "properties": {
    "iso:country":"US",
    "sg:address":"1543 Kingsley Ave",
    "sg:city":"Orange Park",
    "sg:classifiers":[
        {
            "category":"Professional",
            "subcategory":"Business Services",
            "type":"Services"
        },
        {
            "category":"Building & Trades",
            "subcategory":"Construction",
            "type":"Services"
        }
    ],
    "sg:phone":"+1 904 213 8334",
    "sg:postcode":"32073",
    "sg:province":"FL",
    "sg:tags":[
        "pipe",
        "covering",
        "boiler",
        "contractor"
    ],
    "wof:name":"Boiler Inspection Service",
    "wof:placetype":"venue"
},
  "geometry": {"coordinates":[-81.730131,30.164518],"type":"Point"}
}