{
  "type": "Feature",
  "properties": {
    "iso:country":"US",
    "sg:address":"3916 NW 56th St",
    "sg:city":"Pompano Beach",
    "sg:classifiers":[
        {
            "category":"Building & Trades",
            "subcategory":"Construction",
            "type":"Services"
        }
    ],
    "sg:phone":"+1 954 426 2975",
    "sg:postcode":"33073",
    "sg:province":"FL",
    "sg:tags":[
        "nonresidential"
    ],
    "wof:name":"Rjt Construction Systems",
    "wof:placetype":"venue"
},
  "geometry": {"coordinates":[-80.176323,26.299784],"type":"Point"}
}