{
  "type": "Feature",
  "properties": {
    "iso:country":"US",
    "sg:address":"500 Elm St",
    "sg:city":"Welaka",
    "sg:classifiers":[
        {
            "category":"Travel",
            "subcategory":"Hotels & Motels",
            "type":"Entertainment"
        }
    ],
    "sg:phone":"+1 386 467 8998",
    "sg:postcode":"32193",
    "sg:province":"FL",
    "wof:name":"Historic Inn Of Welaka",
    "wof:placetype":"venue"
},
  "geometry": {"coordinates":[-81.66847,29.479129],"type":"Point"}
}