{
  "type": "Feature",
  "properties": {
    "iso:country":"US",
    "sg:address":"301 32nd St W",
    "sg:city":"Bradenton",
    "sg:classifiers":[
        {
            "category":"Organizations",
            "subcategory":"Membership Organization",
            "type":"Services"
        }
    ],
    "sg:phone":"+1 941 749 0810",
    "sg:postcode":"34205",
    "sg:province":"FL",
    "wof:name":"Winter Wonderland Inc",
    "wof:placetype":"venue"
},
  "geometry": {"coordinates":[-82.593476,27.496559],"type":"Point"}
}