{
  "type": "Feature",
  "properties": {
    "iso:country":"US",
    "sg:address":"17743 SE 117th Cir",
    "sg:city":"Summerfield",
    "sg:classifiers":[
        {
            "category":"Professional",
            "subcategory":"Art Services",
            "type":"Services"
        }
    ],
    "sg:phone":"+1 352 245 0626",
    "sg:postcode":"34491",
    "sg:province":"FL",
    "sg:tags":[
        "designer",
        "display",
        "producer"
    ],
    "wof:name":"Barbara Slocum Design",
    "wof:placetype":"venue"
},
  "geometry": {"coordinates":[-81.95728,28.965254],"type":"Point"}
}