{
  "type": "Feature",
  "properties": {
    "iso:country":"US",
    "sg:address":"2900 Blakely Dr",
    "sg:city":"Orlando",
    "sg:classifiers":[
        {
            "category":"Building & Trades",
            "subcategory":"Construction",
            "type":"Services"
        }
    ],
    "sg:phone":"+1 321 438 3838",
    "sg:postcode":"32835",
    "sg:province":"FL",
    "sg:tags":[
        "house"
    ],
    "wof:name":"Not Just Aluminum Inc",
    "wof:placetype":"venue"
},
  "geometry": {"coordinates":[-81.48661800000001,28.509458],"type":"Point"}
}