{
  "type": "Feature",
  "properties": {
    "iso:country":"US",
    "sg:address":"8017 US Hwy 1",
    "sg:city":"Port St Lucie",
    "sg:classifiers":[
        {
            "category":"Shopping",
            "type":"Retail Goods"
        }
    ],
    "sg:phone":"+1 772 871 1553",
    "sg:postcode":"34982",
    "sg:province":"FL",
    "sg:tags":[
        "coin",
        "dealer",
        "supply"
    ],
    "wof:name":"Treasure Coast Coin & Supplies",
    "wof:placetype":"venue"
},
  "geometry": {"coordinates":[-80.31595299999999,27.318499],"type":"Point"}
}