{
  "type": "Feature",
  "properties": {
    "iso:country":"US",
    "sg:address":"9440 S Orange Blossom Trl",
    "sg:city":"Orlando",
    "sg:classifiers":[
        {
            "category":"Personal",
            "subcategory":"Beauty Salon",
            "type":"Services"
        }
    ],
    "sg:phone":"+1 407 240 7771",
    "sg:postcode":"32837",
    "sg:province":"FL",
    "sg:tags":[
        "treatment",
        "skin"
    ],
    "wof:name":"Tranquil Skin Care",
    "wof:placetype":"venue"
},
  "geometry": {"coordinates":[-81.404714,28.426098],"type":"Point"}
}