{
  "type": "Feature",
  "properties": {
    "iso:country":"US",
    "sg:address":"1740 Condor Dr",
    "sg:city":"Cantonment",
    "sg:classifiers":[
        {
            "category":"Health Services",
            "subcategory":"Doctor",
            "type":"Services"
        }
    ],
    "sg:phone":"+1 850 968 6565",
    "sg:postcode":"32533",
    "sg:province":"FL",
    "sg:tags":[
        "physician",
        "surgeon"
    ],
    "wof:name":"Can Do Sports",
    "wof:placetype":"venue"
},
  "geometry": {"coordinates":[-87.282664,30.580059],"type":"Point"}
}