{
  "type": "Feature",
  "properties": {
    "addr:full":"8211 W Broward Blvd Plantation FL 33324",
    "addr:housenumber":"8211",
    "addr:postcode":"33324",
    "addr:street":"W Broward Blvd",
    "iso:country":"US",
    "sg:address":"8211 W Broward Blvd",
    "sg:city":"Plantation",
    "sg:classifiers":[
        {
            "category":"Professional",
            "subcategory":"Accounting & Tax Preparation",
            "type":"Services"
        }
    ],
    "sg:phone":"+1 954 321 9991",
    "sg:postcode":"33324",
    "sg:province":"FL",
    "sg:tags":[
        "accountant"
    ],
    "wof:name":"Bergman Spiewak Gottesman & Co",
    "wof:placetype":"venue"
},
  "geometry": {"coordinates":[-80.259334,26.120823],"type":"Point"}
}