{
  "type": "Feature",
  "properties": {
    "addr:full":"3100 E Fletcher Ave Tampa FL 33613",
    "addr:housenumber":"3100",
    "addr:postcode":"33613",
    "addr:street":"E Fletcher Ave",
    "iso:country":"US",
    "sg:address":"3100 E Fletcher Ave",
    "sg:city":"Tampa",
    "sg:classifiers":[
        {
            "category":"Health Services",
            "subcategory":"Hospital",
            "type":"Services"
        },
        {
            "category":"Community Center",
            "type":"Public Place"
        },
        {
            "category":"Health Services",
            "subcategory":"Clinic",
            "type":"Services"
        }
    ],
    "sg:phone":"+1 813 971 6000",
    "sg:postcode":"33613",
    "sg:province":"FL",
    "sg:tags":[
        "medical",
        "surgery"
    ],
    "sg:website":"http://www.universitycommunityhospital.org",
    "wof:name":"University Community Hospital",
    "wof:placetype":"venue"
},
  "geometry": {"coordinates":[-82.42449999999999,28.069229],"type":"Point"}
}