{
  "type": "Feature",
  "properties": {
    "addr:full":"2720 NE 7th Ave Pompano Beach FL 33064",
    "addr:housenumber":"2720",
    "addr:postcode":"33064",
    "addr:street":"Ne 7Th Ave",
    "iso:country":"US",
    "sg:address":"2720 NE 7th Ave",
    "sg:city":"Pompano Beach",
    "sg:classifiers":[
        {
            "category":"Manufacturing",
            "subcategory":"Wood Products",
            "type":"Manufacturing & Wholesale Goods"
        }
    ],
    "sg:phone":"+1 954 785 3331",
    "sg:postcode":"33064",
    "sg:province":"FL",
    "sg:tags":[
        "mfg"
    ],
    "wof:name":"Eric Syverson",
    "wof:placetype":"venue"
},
  "geometry": {"coordinates":[-80.11346500000001,26.265362],"type":"Point"}
}