{
  "type": "Feature",
  "properties": {
    "addr:full":"817 E Bloomingdale Ave Brandon FL 33511",
    "addr:housenumber":"817",
    "addr:postcode":"33511",
    "addr:street":"E Bloomingdale Ave",
    "iso:country":"US",
    "sg:address":"817 E Bloomingdale Ave",
    "sg:city":"Brandon",
    "sg:classifiers":[
        {
            "category":"Banks & Credit Unions",
            "subcategory":"Bank",
            "type":"Services"
        }
    ],
    "sg:phone":"+1 813 653 4475",
    "sg:postcode":"33511",
    "sg:province":"FL",
    "sg:tags":[
        "depository",
        "banking"
    ],
    "wof:name":"Ace Cash Express",
    "wof:placetype":"venue"
},
  "geometry": {"coordinates":[-82.27188599999999,27.893561],"type":"Point"}
}