{
  "type": "Feature",
  "properties": {
    "addr:full":"302 Knights Run Ave Tampa FL 33602",
    "addr:housenumber":"302",
    "addr:postcode":"33602",
    "addr:street":"Knights Run Ave",
    "iso:country":"US",
    "sg:address":"302 Knights Run Ave",
    "sg:city":"Tampa",
    "sg:classifiers":[
        {
            "category":"Professional",
            "subcategory":"Accounting & Tax Preparation",
            "type":"Services"
        }
    ],
    "sg:phone":"+1 813 383 2294",
    "sg:postcode":"33602",
    "sg:province":"FL",
    "wof:name":"Consulting Inc",
    "wof:placetype":"venue"
},
  "geometry": {"coordinates":[-82.452265,27.937528],"type":"Point"}
}