{
  "type": "Feature",
  "properties": {
    "iso:country":"US",
    "sg:address":"3033 NW 79th St",
    "sg:city":"Miami",
    "sg:classifiers":[
        {
            "category":"Shopping",
            "subcategory":"Clothing, Apparel, & Fashions",
            "type":"Retail Goods"
        }
    ],
    "sg:phone":"+1 305 836 7904",
    "sg:postcode":"33147",
    "sg:province":"FL",
    "sg:tags":[
        "t"
    ],
    "wof:name":"Computer Pictures",
    "wof:placetype":"venue"
},
  "geometry": {"coordinates":[-80.246697,25.845961],"type":"Point"}
}