{
  "type": "Feature",
  "properties": {
    "iso:country":"US",
    "sg:address":"104 Glenmawr Ct",
    "sg:city":"Ponte Vedra Beach",
    "sg:classifiers":[
        {
            "category":"Manufacturing",
            "subcategory":"Glass & Minerals",
            "type":"Manufacturing & Wholesale Goods"
        }
    ],
    "sg:phone":"+1 904 273 7227",
    "sg:postcode":"32082",
    "sg:province":"FL",
    "sg:tags":[
        "mfg",
        "refractory",
        "industrial",
        "inorganic"
    ],
    "wof:name":"Kaiser Aluminum & Chem Corp",
    "wof:placetype":"venue"
},
  "geometry": {"coordinates":[-81.38255100000001,30.217474],"type":"Point"}
}