{
  "type": "Feature",
  "properties": {
    "iso:country":"US",
    "sg:address":"1124 Live Oak Ln",
    "sg:city":"Lutz",
    "sg:classifiers":[
        {
            "category":"Building & Trades",
            "subcategory":"Construction",
            "type":"Services"
        }
    ],
    "sg:phone":"+1 813 920 3556",
    "sg:postcode":"33558",
    "sg:province":"FL",
    "sg:tags":[
        "concrete",
        "pumping"
    ],
    "wof:name":"A & B Concrete & Masonry",
    "wof:placetype":"venue"
},
  "geometry": {"coordinates":[-82.52824099999999,28.174761],"type":"Point"}
}