{
  "type": "Feature",
  "properties": {
    "iso:country":"US",
    "sg:address":"1117 Seafarer Ln",
    "sg:city":"Winter Springs",
    "sg:classifiers":[
        {
            "category":"Building & Trades",
            "subcategory":"Construction",
            "type":"Services"
        }
    ],
    "sg:phone":"+1 407 695 6804",
    "sg:postcode":"32708",
    "sg:province":"FL",
    "sg:tags":[
        "masonry",
        "contractor"
    ],
    "wof:name":"Bryan Masonry Inc",
    "wof:placetype":"venue"
},
  "geometry": {"coordinates":[-81.275182,28.688685],"type":"Point"}
}