{
  "type": "Feature",
  "properties": {
    "addr:full":"182 Pine St Homosassa FL 34446",
    "addr:housenumber":"182",
    "addr:postcode":"34446",
    "addr:street":"Pine St",
    "iso:country":"US",
    "sg:address":"182 Pine St",
    "sg:city":"Homosassa",
    "sg:classifiers":[
        {
            "category":"Manufacturing",
            "subcategory":"Toys & Sporting Goods",
            "type":"Manufacturing & Wholesale Goods"
        }
    ],
    "sg:phone":"+1 352 382 3655",
    "sg:postcode":"34446",
    "sg:province":"FL",
    "sg:tags":[
        "mfg"
    ],
    "wof:name":"D & D Wholesales",
    "wof:placetype":"venue"
},
  "geometry": {"coordinates":[-82.520888,28.735594],"type":"Point"}
}