{
  "type": "Feature",
  "properties": {
    "addr:full":"3400 Lakeside Dr Miramar FL 33027",
    "addr:housenumber":"3400",
    "addr:postcode":"33027",
    "addr:street":"Lakeside Dr",
    "iso:country":"US",
    "sg:address":"3400 Lakeside Dr",
    "sg:city":"Miramar",
    "sg:classifiers":[
        {
            "category":"Utilities",
            "subcategory":"Mobile Phone",
            "type":"Services"
        }
    ],
    "sg:phone":"+1 954 392 4501",
    "sg:postcode":"33027",
    "sg:province":"FL",
    "sg:tags":[
        "telephone",
        "cellular"
    ],
    "wof:name":"Sprint",
    "wof:placetype":"venue"
},
  "geometry": {"coordinates":[-80.344257,25.975074],"type":"Point"}
}