{
  "type": "Feature",
  "properties": {
    "addr:full":"2412 Armstrong Rd Lakeland FL 33811",
    "addr:housenumber":"2412",
    "addr:postcode":"33811",
    "addr:street":"Armstrong Rd",
    "iso:country":"US",
    "sg:address":"2412 Armstrong Rd",
    "sg:city":"Lakeland",
    "sg:classifiers":[
        {
            "category":"Building & Trades",
            "subcategory":"Landscaping Services",
            "type":"Services"
        }
    ],
    "sg:phone":"+1 863 648 4155",
    "sg:postcode":"33811",
    "sg:province":"FL",
    "wof:name":"Servios",
    "wof:placetype":"venue"
},
  "geometry": {"coordinates":[-81.994754,27.983992],"type":"Point"}
}