{
  "type": "Feature",
  "properties": {
    "iso:country":"US",
    "sg:address":"1234 W Fairbanks Ave",
    "sg:city":"Winter Park",
    "sg:classifiers":[
        {
            "category":"Autos & Motor Vehicles",
            "subcategory":"Automobile Sales",
            "type":"Retail Goods"
        }
    ],
    "sg:phone":"+1 407 629 5050",
    "sg:postcode":"32789",
    "sg:province":"FL",
    "sg:tags":[
        "car",
        "dealer"
    ],
    "wof:name":"Luxury Cars Sales & Leasing",
    "wof:placetype":"venue"
},
  "geometry": {"coordinates":[-81.367456,28.593032],"type":"Point"}
}