{
  "type": "Feature",
  "properties": {
    "iso:country":"US",
    "sg:address":"4708 E Busch Blvd",
    "sg:city":"Tampa",
    "sg:classifiers":[
        {
            "category":"Retail",
            "subcategory":"Laundry & Dry Cleaning",
            "type":"Services"
        }
    ],
    "sg:phone":"+1 813 988 7520",
    "sg:postcode":"33617",
    "sg:province":"FL",
    "sg:tags":[
        "cleaners"
    ],
    "wof:name":"Busy Bee Dry Cleaners",
    "wof:placetype":"venue"
},
  "geometry": {"coordinates":[-82.408337,28.032714],"type":"Point"}
}