{
  "type": "Feature",
  "properties": {
    "iso:country":"US",
    "sg:address":"2134 S University Dr",
    "sg:city":"Davie",
    "sg:classifiers":[
        {
            "category":"Retail",
            "subcategory":"Repair Shop",
            "type":"Services"
        }
    ],
    "sg:phone":"+1 954 446 7235",
    "sg:postcode":"33324",
    "sg:province":"FL",
    "sg:tags":[
        "lock",
        "locksmith"
    ],
    "wof:name":"24 All Day Emergency Locksmith",
    "wof:placetype":"venue"
},
  "geometry": {"coordinates":[-80.25118500000001,26.093727],"type":"Point"}
}