{
  "type": "Feature",
  "properties": {
    "addr:full":"20921 Lyons Rd Boca Raton FL 33428",
    "addr:housenumber":"20921",
    "addr:postcode":"33428",
    "addr:street":"Lyons Rd",
    "iso:country":"US",
    "sg:address":"20921 Lyons Rd",
    "sg:city":"Boca Raton",
    "sg:classifiers":[
        {
            "category":"Personal",
            "subcategory":"Beauty Salon",
            "type":"Services"
        }
    ],
    "sg:phone":"+1 561 470 1968",
    "sg:postcode":"33428",
    "sg:province":"FL",
    "sg:tags":[
        "treatment",
        "skin"
    ],
    "wof:name":"Skin Care Clinic Dermasand",
    "wof:placetype":"venue"
},
  "geometry": {"coordinates":[-80.186705,26.364198],"type":"Point"}
}