{
  "type": "Feature",
  "properties": {
    "iso:country":"US",
    "sg:address":"9220 SW 72nd St",
    "sg:city":"Miami",
    "sg:classifiers":[
        {
            "category":"Health Services",
            "subcategory":"Doctor",
            "type":"Services"
        }
    ],
    "sg:phone":"+1 305 273 5801",
    "sg:postcode":"33173",
    "sg:province":"FL",
    "sg:tags":[
        "physician",
        "surgeon"
    ],
    "wof:name":"Delago & Fleites",
    "wof:placetype":"venue"
},
  "geometry": {"coordinates":[-80.34259900000001,25.70188],"type":"Point"}
}