{
  "type": "Feature",
  "properties": {
    "iso:country":"US",
    "sg:address":"5455 Vineland Rd",
    "sg:city":"Orlando",
    "sg:classifiers":[
        {
            "category":"Local Transit",
            "type":"Transportation"
        }
    ],
    "sg:phone":"+1 407 468 6547",
    "sg:postcode":"32811",
    "sg:province":"FL",
    "sg:tags":[
        "passenger"
    ],
    "wof:name":"ABC Transportation Services",
    "wof:placetype":"venue"
},
  "geometry": {"coordinates":[-81.446839,28.483026],"type":"Point"}
}