{
  "type": "Feature",
  "properties": {
    "addr:full":"2100 B Rd Loxahatchee FL 33470",
    "addr:housenumber":"2100 b",
    "addr:postcode":"33470",
    "addr:street":"Rd",
    "iso:country":"US",
    "sg:address":"2100 B Rd",
    "sg:city":"Loxahatchee",
    "sg:classifiers":[
        {
            "category":"Freight",
            "type":"Transportation"
        }
    ],
    "sg:phone":"+1 561 798 0861",
    "sg:postcode":"33470",
    "sg:province":"FL",
    "sg:tags":[
        "operator",
        "local",
        "trucking"
    ],
    "wof:name":"Googe Transport Inc",
    "wof:placetype":"venue"
},
  "geometry": {"coordinates":[-80.289773,26.707983],"type":"Point"}
}