{
  "type": "Feature",
  "properties": {
    "iso:country":"US",
    "sg:address":"715 Sugar Bay Way",
    "sg:city":"Lake Mary",
    "sg:classifiers":[
        {
            "category":"Shopping",
            "subcategory":"Jewelry",
            "type":"Retail Goods"
        }
    ],
    "sg:phone":"+1 407 323 2691",
    "sg:postcode":"32746",
    "sg:province":"FL",
    "wof:name":"J&N Creative Jewelry",
    "wof:placetype":"venue"
},
  "geometry": {"coordinates":[-81.357136,28.738883],"type":"Point"}
}