{
  "type": "Feature",
  "properties": {
    "iso:country":"US",
    "sg:address":"928 N Collier Blvd",
    "sg:city":"Marco Island",
    "sg:classifiers":[
        {
            "category":"Insurance",
            "subcategory":"Title Insurance",
            "type":"Services"
        }
    ],
    "sg:phone":"+1 239 389 9393",
    "sg:postcode":"34145",
    "sg:province":"FL",
    "wof:name":"Sunbelt Title Agency PC",
    "wof:placetype":"venue"
},
  "geometry": {"coordinates":[-81.726084,25.953867],"type":"Point"}
}