{
  "type": "Feature",
  "properties": {
    "addr:full":"6548 Hartland St Fort Myers FL 33966",
    "addr:housenumber":"6548",
    "addr:postcode":"33966",
    "addr:street":"Hartland St",
    "iso:country":"US",
    "sg:address":"6548 Hartland St",
    "sg:city":"Fort Myers",
    "sg:classifiers":[
        {
            "category":"Professional",
            "subcategory":"Art Services",
            "type":"Services"
        }
    ],
    "sg:phone":"+1 239 277 5631",
    "sg:postcode":"33966",
    "sg:province":"FL",
    "sg:tags":[
        "commercial",
        "design"
    ],
    "wof:name":"Jaime L Hernandez",
    "wof:placetype":"venue"
},
  "geometry": {"coordinates":[-81.846177,26.583874],"type":"Point"}
}