{
  "type": "Feature",
  "properties": {
    "iso:country":"US",
    "sg:address":"7910 W Hwy 326",
    "sg:city":"Ocala",
    "sg:classifiers":[
        {
            "category":"Building & Trades",
            "subcategory":"Landscaping Services",
            "type":"Services"
        }
    ],
    "sg:phone":"+1 352 867 0431",
    "sg:postcode":"34482",
    "sg:province":"FL",
    "wof:name":"R & R Tree Service",
    "wof:placetype":"venue"
},
  "geometry": {"coordinates":[-82.249066,29.267156],"type":"Point"}
}