{
  "type": "Feature",
  "properties": {
    "addr:full":"6230 59th Ct Vero Beach FL 32967",
    "addr:housenumber":"6230",
    "addr:postcode":"32967",
    "addr:street":"59Th Ct",
    "iso:country":"US",
    "sg:address":"6230 59th Ct",
    "sg:city":"Vero Beach",
    "sg:classifiers":[
        {
            "category":"Professional",
            "subcategory":"Business Services",
            "type":"Services"
        }
    ],
    "sg:phone":"+1 772 567 8569",
    "sg:postcode":"32967",
    "sg:province":"FL",
    "wof:name":"BV Ward Enterprises Inc",
    "wof:placetype":"venue"
},
  "geometry": {"coordinates":[-80.44943600000001,27.706755],"type":"Point"}
}