{
  "type": "Feature",
  "properties": {
    "iso:country":"US",
    "sg:address":"331 N Donnelly St",
    "sg:city":"Mount Dora",
    "sg:classifiers":[
        {
            "category":"Shopping",
            "subcategory":"Used Merchandise",
            "type":"Retail Goods"
        }
    ],
    "sg:phone":"+1 352 735 4003",
    "sg:postcode":"32757",
    "sg:province":"FL",
    "wof:name":"Lanaeys Antiques Inc",
    "wof:placetype":"venue"
},
  "geometry": {"coordinates":[-81.644785,28.799343],"type":"Point"}
}