{
  "type": "Feature",
  "properties": {
    "addr:full":"100 Old Village Way Oldsmar FL 34677",
    "addr:housenumber":"100",
    "addr:postcode":"34677",
    "addr:street":"Old Village Way",
    "iso:country":"US",
    "sg:address":"100 Old Village Way",
    "sg:city":"Oldsmar",
    "sg:classifiers":[
        {
            "category":"Real Estate",
            "subcategory":"Real Estate Operator",
            "type":"Services"
        }
    ],
    "sg:phone":"+1 813 855 6681",
    "sg:postcode":"34677",
    "sg:province":"FL",
    "sg:tags":[
        "apartment"
    ],
    "wof:name":"Spinnaker Bay",
    "wof:placetype":"venue"
},
  "geometry": {"coordinates":[-82.679705,28.039081],"type":"Point"}
}