{
  "type": "Feature",
  "properties": {
    "iso:country":"US",
    "sg:address":"2421 NW 41st St",
    "sg:city":"Gainesville",
    "sg:classifiers":[
        {
            "category":"Professional",
            "subcategory":"Advertising",
            "type":"Services"
        }
    ],
    "sg:phone":"+1 352 371 3106",
    "sg:postcode":"32606",
    "sg:province":"FL",
    "sg:tags":[
        "mail",
        "direct"
    ],
    "wof:name":"Florida Mint Inc",
    "wof:placetype":"venue"
},
  "geometry": {"coordinates":[-82.38623,29.673771],"type":"Point"}
}