{
  "type": "Feature",
  "properties": {
    "iso:country":"US",
    "sg:address":"2040 Tigertail Blvd Ste H",
    "sg:city":"Dania",
    "sg:classifiers":[
        {
            "category":"Home & Garden",
            "subcategory":"Home Furnishings",
            "type":"Retail Goods"
        },
        {
            "category":"Building & Trades",
            "subcategory":"Construction",
            "type":"Services"
        },
        {
            "category":"Manufacturing",
            "subcategory":"Building Materials",
            "type":"Manufacturing & Wholesale Goods"
        }
    ],
    "sg:phone":"+1 954 926 5566",
    "sg:postcode":"33004",
    "sg:province":"FL",
    "sg:tags":[
        "industrial",
        "cabinetmakers-commercial",
        "cabinet",
        "refacing",
        "resurfacing",
        "maker",
        "cabinets-refinishing",
        "kitchen"
    ],
    "sg:website":"http://www.specialtysupplies.com",
    "wof:name":"Ebonist Inc",
    "wof:placetype":"venue"
},
  "geometry": {"coordinates":[-80.165639,26.05346],"type":"Point"}
}