{
  "type": "Feature",
  "properties": {
    "iso:country":"US",
    "sg:address":"35223 State Rd 54",
    "sg:city":"Zephyrhills",
    "sg:classifiers":[
        {
            "category":"Utilities",
            "subcategory":"Fuel Oil & Lpg",
            "type":"Services"
        }
    ],
    "sg:phone":"+1 813 782 7355",
    "sg:postcode":"33541",
    "sg:province":"FL",
    "sg:tags":[
        "liquefied",
        "gas",
        "petroleum"
    ],
    "wof:name":"Columbia Energy",
    "wof:placetype":"venue"
},
  "geometry": {"coordinates":[-82.234793,28.22389],"type":"Point"}
}