{
  "type": "Feature",
  "properties": {
    "addr:full":"3522 Sunrise Trl Port Charlotte FL 33952",
    "addr:housenumber":"3522",
    "addr:postcode":"33952",
    "addr:street":"Sunrise Trl",
    "iso:country":"US",
    "sg:address":"3522 Sunrise Trl",
    "sg:city":"Port Charlotte",
    "sg:classifiers":[
        {
            "category":"Professional",
            "type":"Services"
        }
    ],
    "sg:phone":"+1 941 276 4342",
    "sg:postcode":"33952",
    "sg:province":"FL",
    "wof:name":"William K Gaines Training Svc",
    "wof:placetype":"venue"
},
  "geometry": {"coordinates":[-82.10582700000001,26.976527],"type":"Point"}
}