{
  "type": "Feature",
  "properties": {
    "addr:full":"2020 NE 163rd St Miami FL 33162",
    "addr:housenumber":"2020",
    "addr:postcode":"33162",
    "addr:street":"Ne 163Rd St",
    "iso:country":"US",
    "sg:address":"2020 NE 163rd St",
    "sg:city":"Miami",
    "sg:classifiers":[
        {
            "category":"Food & Beverages",
            "subcategory":"Groceries & Convenience Stores",
            "type":"Retail Goods"
        }
    ],
    "sg:phone":"+1 305 948 0103",
    "sg:postcode":"33162",
    "sg:province":"FL",
    "wof:name":"Chapter 11 Group Inc",
    "wof:placetype":"venue"
},
  "geometry": {"coordinates":[-80.160265,25.925945],"type":"Point"}
}