{
  "type": "Feature",
  "properties": {
    "addr:full":"1523 SE 21st St Cape Coral FL 33990",
    "addr:housenumber":"1523",
    "addr:postcode":"33990",
    "addr:street":"Se 21St St",
    "iso:country":"US",
    "sg:address":"1523 SE 21st St",
    "sg:city":"Cape Coral",
    "sg:classifiers":[
        {
            "category":"Real Estate",
            "subcategory":"Architect",
            "type":"Services"
        }
    ],
    "sg:phone":"+1 239 573 9267",
    "sg:postcode":"33990",
    "sg:province":"FL",
    "sg:tags":[
        "architectural"
    ],
    "wof:name":"Gs Goertler Architectural",
    "wof:placetype":"venue"
},
  "geometry": {"coordinates":[-81.941136,26.613944],"type":"Point"}
}