{
  "type": "Feature",
  "properties": {
    "addr:full":"5619 E Columbus Dr Tampa FL 33619",
    "addr:housenumber":"5619",
    "addr:postcode":"33619",
    "addr:street":"E Columbus Dr",
    "iso:country":"US",
    "sg:address":"5619 E Columbus Dr",
    "sg:city":"Tampa",
    "sg:classifiers":[
        {
            "category":"Freight",
            "type":"Transportation"
        }
    ],
    "sg:phone":"+1 813 621 3043",
    "sg:postcode":"33619",
    "sg:province":"FL",
    "sg:tags":[
        "operator",
        "local",
        "trucking"
    ],
    "wof:name":"Commercial Carrier Corporation",
    "wof:placetype":"venue"
},
  "geometry": {"coordinates":[-82.392073,27.96671],"type":"Point"}
}