{
  "type": "Feature",
  "properties": {
    "addr:full":"5437 Spring Hill Dr Spring Hill FL 34606",
    "addr:housenumber":"5437",
    "addr:postcode":"34606",
    "addr:street":"Spring Hill Dr",
    "iso:country":"US",
    "sg:address":"5437 Spring Hill Dr",
    "sg:city":"Spring Hill",
    "sg:classifiers":[
        {
            "category":"Professional",
            "subcategory":"Business Services",
            "type":"Services"
        }
    ],
    "sg:phone":"+1 352 666 4933",
    "sg:postcode":"34606",
    "sg:province":"FL",
    "sg:tags":[
        "packaging"
    ],
    "wof:name":"Global Freight Trnsprtn Pack",
    "wof:placetype":"venue"
},
  "geometry": {"coordinates":[-82.62485,28.458707],"type":"Point"}
}