{
  "type": "Feature",
  "properties": {
    "iso:country":"US",
    "sg:address":"626 Stanhope Dr",
    "sg:city":"Casselberry",
    "sg:classifiers":[
        {
            "category":"Professional",
            "type":"Services"
        }
    ],
    "sg:phone":"+1 407 332 0048",
    "sg:postcode":"32707",
    "sg:province":"FL",
    "wof:name":"All Womens Per Training Ctr",
    "wof:placetype":"venue"
},
  "geometry": {"coordinates":[-81.319721,28.645159],"type":"Point"}
}