{
  "type": "Feature",
  "properties": {
    "iso:country":"US",
    "sg:address":"113 Fairview E",
    "sg:city":"Jupiter",
    "sg:classifiers":[
        {
            "category":"Banks & Credit Unions",
            "subcategory":"Financial Services",
            "type":"Services"
        }
    ],
    "sg:phone":"+1 561 743 5542",
    "sg:postcode":"33469",
    "sg:province":"FL",
    "sg:tags":[
        "investor"
    ],
    "wof:name":"Star Investment Properties LLC",
    "wof:placetype":"venue"
},
  "geometry": {"coordinates":[-80.11168499999999,26.962058],"type":"Point"}
}