{
  "type": "Feature",
  "properties": {
    "iso:country":"US",
    "sg:address":"941 17th St",
    "sg:city":"Vero Beach",
    "sg:classifiers":[
        {
            "category":"Shopping",
            "subcategory":"Computers & Home Electronics",
            "type":"Retail Goods"
        }
    ],
    "sg:phone":"+1 772 567 8564",
    "sg:postcode":"32960",
    "sg:province":"FL",
    "wof:name":"Computer Connection",
    "wof:placetype":"venue"
},
  "geometry": {"coordinates":[-80.39041,27.63257],"type":"Point"}
}