{
  "type": "Feature",
  "properties": {
    "iso:country":"US",
    "sg:address":"1211 Miller St",
    "sg:city":"Orange Park",
    "sg:classifiers":[
        {
            "category":"Organizations",
            "subcategory":"Religious Organization",
            "type":"Services"
        }
    ],
    "sg:phone":"+1 904 278 9511",
    "sg:postcode":"32073",
    "sg:province":"FL",
    "wof:name":"Miller Street Church Of Christ",
    "wof:placetype":"venue"
},
  "geometry": {"coordinates":[-81.712744,30.173134],"type":"Point"}
}