{
  "type": "Feature",
  "properties": {
    "addr:full":"6304 Ocean Pines Ln Spring Hill FL 34606",
    "addr:housenumber":"6304",
    "addr:postcode":"34606",
    "addr:street":"Ocean Pines Ln",
    "iso:country":"US",
    "sg:address":"6304 Ocean Pines Ln",
    "sg:city":"Spring Hill",
    "sg:classifiers":[
        {
            "category":"Shopping",
            "subcategory":"Jewelry",
            "type":"Retail Goods"
        }
    ],
    "sg:phone":"+1 352 684 7662",
    "sg:postcode":"34606",
    "sg:province":"FL",
    "wof:name":"D&D Jewelers Inc",
    "wof:placetype":"venue"
},
  "geometry": {"coordinates":[-82.61360000000001,28.463755],"type":"Point"}
}