{
  "type": "Feature",
  "properties": {
    "iso:country":"US",
    "sg:address":"131 2nd Ave N",
    "sg:city":"Jacksonville Bch",
    "sg:classifiers":[
        {
            "category":"Banks & Credit Unions",
            "subcategory":"Investment Brokerage",
            "type":"Services"
        }
    ],
    "sg:phone":"+1 904 241 1214",
    "sg:postcode":"32250",
    "sg:province":"FL",
    "sg:tags":[
        "security"
    ],
    "wof:name":"Raymond James Financial Svc",
    "wof:placetype":"venue"
},
  "geometry": {"coordinates":[-81.39089199999999,30.291262],"type":"Point"}
}