{
  "type": "Feature",
  "properties": {
    "iso:country":"US",
    "sg:address":"6825 Powerline Rd",
    "sg:city":"Fort Lauderdale",
    "sg:classifiers":[
        {
            "category":"Banks & Credit Unions",
            "subcategory":"Bank",
            "type":"Services"
        }
    ],
    "sg:phone":"+1 954 969 1950",
    "sg:postcode":"33309",
    "sg:province":"FL",
    "sg:website":"www.citynational.com",
    "wof:name":"City National Bank Of Fl",
    "wof:placetype":"venue"
},
  "geometry": {"coordinates":[-80.15597,26.209529],"type":"Point"}
}