{
  "type": "Feature",
  "properties": {
    "addr:full":"16209 E Course Dr Tampa FL 33624",
    "addr:housenumber":"16209",
    "addr:postcode":"33624",
    "addr:street":"E Course Dr",
    "iso:country":"US",
    "sg:address":"16209 E Course Dr",
    "sg:city":"Tampa",
    "sg:classifiers":[
        {
            "category":"Utilities",
            "subcategory":"Telephone",
            "type":"Services"
        }
    ],
    "sg:phone":"+1 813 968 6867",
    "sg:postcode":"33624",
    "sg:province":"FL",
    "sg:tags":[
        "hospitality",
        "manages",
        "system",
        "for",
        "owns"
    ],
    "wof:name":"Greenman Funding",
    "wof:placetype":"venue"
},
  "geometry": {"coordinates":[-82.521366,28.10174],"type":"Point"}
}