{
  "type": "Feature",
  "properties": {
    "iso:country":"US",
    "sg:address":"1519 Sunnyhills Dr",
    "sg:city":"Brandon",
    "sg:classifiers":[
        {
            "category":"Building & Trades",
            "subcategory":"Construction",
            "type":"Services"
        }
    ],
    "sg:phone":"+1 813 685 0593",
    "sg:postcode":"33510",
    "sg:province":"FL",
    "sg:tags":[
        "carpentry",
        "contractor"
    ],
    "wof:name":"Ultimate Design Studios",
    "wof:placetype":"venue"
},
  "geometry": {"coordinates":[-82.313928,27.96194],"type":"Point"}
}