{
  "type": "Feature",
  "properties": {
    "addr:full":"210 S French Ave Sanford FL 32771",
    "addr:housenumber":"210",
    "addr:postcode":"32771",
    "addr:street":"S French Ave",
    "iso:country":"US",
    "sg:address":"210 S French Ave",
    "sg:city":"Sanford",
    "sg:classifiers":[
        {
            "category":"Autos & Motor Vehicles",
            "subcategory":"Motorcycle Sales",
            "type":"Retail Goods"
        }
    ],
    "sg:phone":"+1 407 330 2056",
    "sg:postcode":"32771",
    "sg:province":"FL",
    "sg:tags":[
        "scooter"
    ],
    "sg:website":"www.scootersperformance.com",
    "wof:name":"Scooters Parts and Accessories",
    "wof:placetype":"venue"
},
  "geometry": {"coordinates":[-81.273241,28.809982],"type":"Point"}
}