{
  "type": "Feature",
  "properties": {
    "iso:country":"US",
    "sg:address":"16249 Ashland Ave",
    "sg:city":"Port Charlotte",
    "sg:classifiers":[
        {
            "category":"Building & Trades",
            "subcategory":"Electrical",
            "type":"Services"
        }
    ],
    "sg:phone":"+1 941 627 5808",
    "sg:postcode":"33954",
    "sg:province":"FL",
    "sg:tags":[
        "electrical",
        "electric",
        "contractor"
    ],
    "wof:name":"Mike's Electric",
    "wof:placetype":"venue"
},
  "geometry": {"coordinates":[-82.179979,27.022045],"type":"Point"}
}