{
  "type": "Feature",
  "properties": {
    "addr:full":"2826 E Commercial Blvd Fort Lauderdale FL 33308",
    "addr:housenumber":"2826",
    "addr:postcode":"33308",
    "addr:street":"E Commercial Blvd",
    "iso:country":"US",
    "sg:address":"2826 E Commercial Blvd",
    "sg:city":"Fort Lauderdale",
    "sg:classifiers":[
        {
            "category":"Travel",
            "subcategory":"Travel Agent",
            "type":"Entertainment"
        }
    ],
    "sg:phone":"+1 954 776 7666",
    "sg:postcode":"33308",
    "sg:province":"FL",
    "sg:tags":[
        "agency",
        "bureau"
    ],
    "sg:website":"www.varietyvacations.com",
    "wof:name":"Atlas Travel",
    "wof:placetype":"venue"
},
  "geometry": {"coordinates":[-80.106858,26.189733],"type":"Point"}
}