{
  "type": "Feature",
  "properties": {
    "iso:country":"US",
    "sg:address":"8001 S Orange Blossom Trl",
    "sg:city":"Orlando",
    "sg:classifiers":[
        {
            "category":"Food & Beverages",
            "subcategory":"Bakery",
            "type":"Retail Goods"
        }
    ],
    "sg:phone":"+1 407 859 1476",
    "sg:postcode":"32809",
    "sg:province":"FL",
    "sg:tags":[
        "pretzel"
    ],
    "sg:website":"www.auntieannes.com",
    "wof:name":"Auntie Anne's Hand Rolled Soft",
    "wof:placetype":"venue"
},
  "geometry": {"coordinates":[-81.401563,28.447588],"type":"Point"}
}