{
  "type": "Feature",
  "properties": {
    "addr:full":"18500 Veterans Blvd Port Charlotte FL 33954",
    "addr:housenumber":"18500",
    "addr:postcode":"33954",
    "addr:street":"Veterans Blvd",
    "iso:country":"US",
    "sg:address":"18500 Veterans Blvd",
    "sg:city":"Port Charlotte",
    "sg:classifiers":[
        {
            "category":"Wholesale",
            "subcategory":"Furniture",
            "type":"Manufacturing & Wholesale Goods"
        }
    ],
    "sg:phone":"+1 941 235 3375",
    "sg:postcode":"33954",
    "sg:province":"FL",
    "wof:name":"Desk At Home",
    "wof:placetype":"venue"
},
  "geometry": {"coordinates":[-82.144257,27.01361],"type":"Point"}
}