{
  "type": "Feature",
  "properties": {
    "iso:country":"US",
    "sg:address":"22932 State Rd 54",
    "sg:city":"Lutz",
    "sg:classifiers":[
        {
            "category":"Retail",
            "subcategory":"Auto Rental",
            "type":"Services"
        }
    ],
    "sg:phone":"+1 813 909 8872",
    "sg:postcode":"33549",
    "sg:province":"FL",
    "sg:tags":[
        "renting",
        "truck",
        "leasing"
    ],
    "wof:name":"U-Haul Co",
    "wof:placetype":"venue"
},
  "geometry": {"coordinates":[-82.43394000000001,28.186016],"type":"Point"}
}