{
  "type": "Feature",
  "properties": {
    "iso:country":"US",
    "sg:address":"Baila Conmigo 5909 NW 102nd Ave",
    "sg:city":"Doral",
    "sg:classifiers":[
        {
            "category":"Education",
            "subcategory":"Dance Studio",
            "type":"Public Place"
        }
    ],
    "sg:postcode":"33178",
    "sg:province":"FL",
    "wof:name":"Hayal Bellydance",
    "wof:placetype":"venue"
},
  "geometry": {"coordinates":[-80.361992,25.827535],"type":"Point"}
}