{
  "type": "Feature",
  "properties": {
    "addr:full":"6220 All American Blvd Orlando FL 32810",
    "addr:housenumber":"6220",
    "addr:postcode":"32810",
    "addr:street":"All American Blvd",
    "iso:country":"US",
    "sg:address":"6220 All American Blvd",
    "sg:city":"Orlando",
    "sg:classifiers":[
        {
            "category":"Organizations",
            "subcategory":"Non-profit Organization",
            "type":"Services"
        }
    ],
    "sg:phone":"+1 407 445 8444",
    "sg:postcode":"32810",
    "sg:province":"FL",
    "sg:tags":[
        "human"
    ],
    "wof:name":"Jesus The Light Of Life Street",
    "wof:placetype":"venue"
},
  "geometry": {"coordinates":[-81.419149,28.614924],"type":"Point"}
}