{
  "type": "Feature",
  "properties": {
    "iso:country":"US",
    "sg:address":"1117 Acappella Dr",
    "sg:city":"Melbourne",
    "sg:classifiers":[
        {
            "category":"Personal",
            "subcategory":"Tanning Parlor",
            "type":"Services"
        }
    ],
    "sg:phone":"+1 321 751 2973",
    "sg:postcode":"32940",
    "sg:province":"FL",
    "sg:tags":[
        "salon"
    ],
    "wof:name":"Do Tan",
    "wof:placetype":"venue"
},
  "geometry": {"coordinates":[-80.69431400000001,28.244515],"type":"Point"}
}