{
  "type": "Feature",
  "properties": {
    "iso:country":"US",
    "sg:address":"397 N Ferdon Blvd",
    "sg:city":"Crestview",
    "sg:classifiers":[
        {
            "category":"Insurance",
            "subcategory":"Title Insurance",
            "type":"Services"
        }
    ],
    "sg:phone":"+1 850 682 1746",
    "sg:postcode":"32536",
    "sg:province":"FL",
    "sg:tags":[
        "mortgage"
    ],
    "wof:name":"First National Land Title Company",
    "wof:placetype":"venue"
},
  "geometry": {"coordinates":[-86.57043400000001,30.76079],"type":"Point"}
}