{
  "type": "Feature",
  "properties": {
    "iso:country":"US",
    "sg:address":"1201 Winter Garden Vineland Rd",
    "sg:city":"Winter Garden",
    "sg:classifiers":[
        {
            "category":"Building & Trades",
            "subcategory":"Construction",
            "type":"Services"
        }
    ],
    "sg:phone":"+1 407 905 9655",
    "sg:postcode":"34787",
    "sg:province":"FL",
    "sg:tags":[
        "contractor"
    ],
    "wof:name":"Dixie Pools & Spas Inc",
    "wof:placetype":"venue"
},
  "geometry": {"coordinates":[-81.58845100000001,28.520369],"type":"Point"}
}