{
  "type": "Feature",
  "properties": {
    "addr:full":"700 Biltmore Way Coral Gables FL 33134",
    "addr:housenumber":"700",
    "addr:postcode":"33134",
    "addr:street":"Biltmore Way",
    "iso:country":"US",
    "sg:address":"700 Biltmore Way",
    "sg:city":"Coral Gables",
    "sg:classifiers":[
        {
            "category":"Travel",
            "subcategory":"Hotels & Motels",
            "type":"Entertainment"
        }
    ],
    "sg:phone":"+1 305 445 7821",
    "sg:postcode":"33134",
    "sg:province":"FL",
    "wof:name":"David William Hotel",
    "wof:placetype":"venue"
},
  "geometry": {"coordinates":[-80.268799,25.747999],"type":"Point"}
}