{
  "type": "Feature",
  "properties": {
    "addr:full":"887 Lexington Rd Pensacola FL 32514",
    "addr:housenumber":"887",
    "addr:postcode":"32514",
    "addr:street":"Lexington Rd",
    "iso:country":"US",
    "sg:address":"887 Lexington Rd",
    "sg:city":"Pensacola",
    "sg:classifiers":[
        {
            "category":"Real Estate",
            "subcategory":"Real Estate Agent",
            "type":"Services"
        }
    ],
    "sg:phone":"+1 850 478 6976",
    "sg:postcode":"32514",
    "sg:province":"FL",
    "wof:name":"Four Lakes Inc",
    "wof:placetype":"venue"
},
  "geometry": {"coordinates":[-87.25667900000001,30.557399],"type":"Point"}
}