{
  "type": "Feature",
  "properties": {
    "iso:country":"US",
    "sg:address":"4289 S Florida Ave",
    "sg:city":"Lakeland",
    "sg:classifiers":[
        {
            "category":"Personal",
            "subcategory":"Beauty Salon",
            "type":"Services"
        }
    ],
    "sg:phone":"+1 863 619 2555",
    "sg:postcode":"33813",
    "sg:province":"FL",
    "sg:tags":[
        "hair",
        "stylist"
    ],
    "sg:website":"http://www.acutabovehair.com",
    "wof:name":"A Cut Above Hair & Nail Salon",
    "wof:placetype":"venue"
},
  "geometry": {"coordinates":[-81.956934,27.987601],"type":"Point"}
}