{
  "type": "Feature",
  "properties": {
    "iso:country":"US",
    "sg:address":"4869 Amelia St",
    "sg:city":"West Palm Beach",
    "sg:classifiers":[
        {
            "category":"Retail",
            "subcategory":"Auto Repair",
            "type":"Services"
        }
    ],
    "sg:phone":"+1 561 689 6930",
    "sg:postcode":"33415",
    "sg:province":"FL",
    "sg:tags":[
        "automotive"
    ],
    "wof:name":"Lone Wolf Towing & Recovery",
    "wof:placetype":"venue"
},
  "geometry": {"coordinates":[-80.11784,26.683598],"type":"Point"}
}