{
  "type": "Feature",
  "properties": {
    "iso:country":"US",
    "sg:address":"224 Datura St",
    "sg:city":"West Palm Beach",
    "sg:classifiers":[
        {
            "category":"Professional",
            "subcategory":"Lawyer & Legal Services",
            "type":"Services"
        }
    ],
    "sg:phone":"+1 561 805 7282",
    "sg:postcode":"33401",
    "sg:province":"FL",
    "sg:tags":[
        "attorney"
    ],
    "sg:website":"www.daslawyers.com",
    "wof:name":"Del Amo & Segurola",
    "wof:placetype":"venue"
},
  "geometry": {"coordinates":[-80.05166199999999,26.712184],"type":"Point"}
}