{
  "type": "Feature",
  "properties": {
    "iso:country":"US",
    "sg:address":"2458 SE Monroe St",
    "sg:city":"Stuart",
    "sg:classifiers":[
        {
            "category":"Manufacturing",
            "subcategory":"Glass & Minerals",
            "type":"Manufacturing & Wholesale Goods"
        }
    ],
    "sg:phone":"+1 772 223 0384",
    "sg:postcode":"34997",
    "sg:province":"FL",
    "sg:tags":[
        "glass-wholesale",
        "shape",
        "circle",
        "special",
        "manufacturer"
    ],
    "wof:name":"Under The Glass",
    "wof:placetype":"venue"
},
  "geometry": {"coordinates":[-80.221046,27.15062],"type":"Point"}
}