{
  "type": "Feature",
  "properties": {
    "iso:country":"US",
    "sg:address":"4401 NW 167th St",
    "sg:city":"Opa Locka",
    "sg:classifiers":[
        {
            "category":"Manufacturing",
            "subcategory":"Apparel",
            "type":"Manufacturing & Wholesale Goods"
        }
    ],
    "sg:phone":"+1 305 474 7676",
    "sg:postcode":"33055",
    "sg:province":"FL",
    "sg:tags":[
        "outerwear"
    ],
    "sg:website":"www.ingear.com",
    "wof:name":"In Gear Fashions",
    "wof:placetype":"venue"
},
  "geometry": {"coordinates":[-80.27269099999999,25.925684],"type":"Point"}
}