{
  "type": "Feature",
  "properties": {
    "iso:country":"US",
    "sg:address":"7503 NW 36th St",
    "sg:city":"Miami",
    "sg:classifiers":[
        {
            "category":"Professional",
            "subcategory":"Management & Consulting",
            "type":"Services"
        }
    ],
    "sg:phone":"+1 305 591 1925",
    "sg:postcode":"33166",
    "sg:province":"FL",
    "sg:tags":[
        "party",
        "planning",
        "event"
    ],
    "wof:name":"Party Kingdom Inc",
    "wof:placetype":"venue"
},
  "geometry": {"coordinates":[-80.317802,25.809299],"type":"Point"}
}