{
  "type": "Feature",
  "properties": {
    "iso:country":"US",
    "sg:address":"20726 SW 81st Pl",
    "sg:city":"Miami",
    "sg:classifiers":[
        {
            "category":"Restaurant",
            "type":"Food & Drink"
        }
    ],
    "sg:phone":"+1 305 255 4054",
    "sg:postcode":"33189",
    "sg:province":"FL",
    "sg:tags":[
        "hot",
        "dog",
        "stand"
    ],
    "wof:name":"Hot Dog Cart",
    "wof:placetype":"venue"
},
  "geometry": {"coordinates":[-80.323762,25.574575],"type":"Point"}
}