{
  "type": "Feature",
  "properties": {
    "iso:country":"US",
    "sg:address":"9407 25th St E",
    "sg:city":"Parrish",
    "sg:classifiers":[
        {
            "category":"Food & Beverages",
            "subcategory":"Liquor & Beverages",
            "type":"Retail Goods"
        }
    ],
    "sg:phone":"+1 941 776 1182",
    "sg:postcode":"34219",
    "sg:province":"FL",
    "sg:tags":[
        "alcoholic"
    ],
    "wof:name":"Buy Liquors",
    "wof:placetype":"venue"
},
  "geometry": {"coordinates":[-82.468384,27.535295],"type":"Point"}
}