{
  "type": "Feature",
  "properties": {
    "addr:full":"2400 SW 102nd Dr Fort Lauderdale FL 33324",
    "addr:housenumber":"2400",
    "addr:postcode":"33324",
    "addr:street":"Sw 102Nd Dr",
    "iso:country":"US",
    "sg:address":"2400 SW 102nd Dr",
    "sg:city":"Fort Lauderdale",
    "sg:classifiers":[
        {
            "category":"Building & Trades",
            "subcategory":"Construction",
            "type":"Services"
        }
    ],
    "sg:phone":"+1 954 472 0760",
    "sg:postcode":"33324",
    "sg:province":"FL",
    "sg:tags":[
        "hanging",
        "maintenance",
        "contractor"
    ],
    "wof:name":"Gregs Custom Painting",
    "wof:placetype":"venue"
},
  "geometry": {"coordinates":[-80.28504700000001,26.089913],"type":"Point"}
}