{
  "type": "Feature",
  "properties": {
    "iso:country":"US",
    "sg:address":"7841 Cambridge Manor Pl",
    "sg:city":"Fort Myers",
    "sg:classifiers":[
        {
            "category":"Health Services",
            "subcategory":"Doctor",
            "type":"Services"
        }
    ],
    "sg:phone":"+1 239 278 0400",
    "sg:postcode":"33907",
    "sg:province":"FL",
    "sg:tags":[
        "physician",
        "surgeon"
    ],
    "wof:name":"Nancy M Troast DO",
    "wof:placetype":"venue"
},
  "geometry": {"coordinates":[-81.88352399999999,26.560119],"type":"Point"}
}