{
  "type": "Feature",
  "properties": {
    "addr:full":"2339 Gulf To Bay Blvd Clearwater FL 33765",
    "addr:housenumber":"2339",
    "addr:postcode":"33765",
    "addr:street":"Gulf To Bay Blvd",
    "iso:country":"US",
    "sg:address":"2339 Gulf To Bay Blvd",
    "sg:city":"Clearwater",
    "sg:classifiers":[
        {
            "category":"Autos & Motor Vehicles",
            "subcategory":"Automobile Sales",
            "type":"Retail Goods"
        }
    ],
    "sg:phone":"+1 727 726 1233",
    "sg:postcode":"33765",
    "sg:province":"FL",
    "sg:tags":[
        "car",
        "dealer"
    ],
    "wof:name":"Saturn Of Clearwater Inc",
    "wof:placetype":"venue"
},
  "geometry": {"coordinates":[-82.74177299999999,27.960534],"type":"Point"}
}