{
  "type": "Feature",
  "properties": {
    "addr:full":"8840 Larwin Ln Orlando FL 32817",
    "addr:housenumber":"8840",
    "addr:postcode":"32817",
    "addr:street":"Larwin Ln",
    "iso:country":"US",
    "sg:address":"8840 Larwin Ln",
    "sg:city":"Orlando",
    "sg:classifiers":[
        {
            "category":"Travel",
            "subcategory":"Travel Agent",
            "type":"Entertainment"
        }
    ],
    "sg:phone":"+1 407 678 5755",
    "sg:postcode":"32817",
    "sg:province":"FL",
    "sg:tags":[
        "operator",
        "equipment",
        "tour",
        "industrial"
    ],
    "wof:name":"H & D International Trading",
    "wof:placetype":"venue"
},
  "geometry": {"coordinates":[-81.263597,28.598232],"type":"Point"}
}