{
  "type": "Feature",
  "properties": {
    "iso:country":"US",
    "sg:address":"7868 SE Swan Ave",
    "sg:city":"Hobe Sound",
    "sg:classifiers":[
        {
            "category":"Retail",
            "subcategory":"Auto Repair",
            "type":"Services"
        }
    ],
    "sg:phone":"+1 772 545 7542",
    "sg:postcode":"33455",
    "sg:province":"FL",
    "sg:tags":[
        "body"
    ],
    "wof:name":"HI Tech Auto Works Inc",
    "wof:placetype":"venue"
},
  "geometry": {"coordinates":[-80.158542,27.1076],"type":"Point"}
}