{
  "type": "Feature",
  "properties": {
    "iso:country":"US",
    "sg:address":"14453 SW 174th St",
    "sg:city":"Miami",
    "sg:classifiers":[
        {
            "category":"Banks & Credit Unions",
            "subcategory":"Financial Services",
            "type":"Services"
        }
    ],
    "sg:phone":"+1 305 971 5208",
    "sg:postcode":"33177",
    "sg:province":"FL",
    "sg:tags":[
        "investor"
    ],
    "wof:name":"Investors South Florida",
    "wof:placetype":"venue"
},
  "geometry": {"coordinates":[-80.428901,25.605741],"type":"Point"}
}