{
  "type": "Feature",
  "properties": {
    "addr:full":"14735 W Dixie Hwy North Miami FL 33181",
    "addr:housenumber":"14735",
    "addr:postcode":"33181",
    "addr:street":"W Dixie Hwy",
    "iso:country":"US",
    "sg:address":"14735 W Dixie Hwy",
    "sg:city":"North Miami",
    "sg:classifiers":[
        {
            "category":"Building & Trades",
            "subcategory":"Locksmith",
            "type":"Services"
        }
    ],
    "sg:phone":"+1 786 228 5662",
    "sg:postcode":"33181",
    "sg:province":"FL",
    "sg:tags":[
        "key"
    ],
    "wof:name":"Available Locksmith 24 7 In North Miami",
    "wof:placetype":"venue"
},
  "geometry": {"coordinates":[-80.16649,25.911933],"type":"Point"}
}