{
  "type": "Feature",
  "properties": {
    "addr:full":"9008 Marlin St Cape Canaveral FL 32920",
    "addr:housenumber":"9008",
    "addr:postcode":"32920",
    "addr:street":"Marlin St",
    "iso:country":"US",
    "sg:address":"9008 Marlin St",
    "sg:city":"Cape Canaveral",
    "sg:classifiers":[
        {
            "category":"Shopping",
            "subcategory":"Gifts & Souvenirs",
            "type":"Retail Goods"
        }
    ],
    "sg:phone":"+1 321 783 0246",
    "sg:postcode":"32920",
    "sg:province":"FL",
    "wof:name":"Crews Creations",
    "wof:placetype":"venue"
},
  "geometry": {"coordinates":[-80.60881500000001,28.407946],"type":"Point"}
}