{
  "type": "Feature",
  "properties": {
    "iso:country":"US",
    "sg:address":"13550 Atlantic Blvd",
    "sg:city":"Jacksonville",
    "sg:classifiers":[
        {
            "category":"Autos & Motor Vehicles",
            "subcategory":"Fuel & Gas Station",
            "type":"Retail Goods"
        }
    ],
    "sg:phone":"+1 904 221 9050",
    "sg:postcode":"32225",
    "sg:province":"FL",
    "sg:tags":[
        "convenience",
        "store"
    ],
    "wof:name":"Lil Champ 164",
    "wof:placetype":"venue"
},
  "geometry": {"coordinates":[-81.44058800000001,30.322978],"type":"Point"}
}