{
  "type": "Feature",
  "properties": {
    "iso:country":"US",
    "sg:address":"15074 SW 13th Pl",
    "sg:city":"Sunrise",
    "sg:classifiers":[
        {
            "category":"Recreation",
            "type":"Entertainment"
        }
    ],
    "sg:phone":"+1 954 382 6169",
    "sg:postcode":"33326",
    "sg:province":"FL",
    "sg:tags":[
        "amusement"
    ],
    "wof:name":"Road Kill Hockey Inc",
    "wof:placetype":"venue"
},
  "geometry": {"coordinates":[-80.351489,26.103328],"type":"Point"}
}