{
  "type": "Feature",
  "properties": {
    "iso:country":"US",
    "sg:address":"120 N K St",
    "sg:city":"Lake Worth",
    "sg:classifiers":[
        {
            "category":"Wholesale",
            "subcategory":"Electrical",
            "type":"Manufacturing & Wholesale Goods"
        }
    ],
    "sg:phone":"+1 561 582 9416",
    "sg:postcode":"33460",
    "sg:province":"FL",
    "sg:tags":[
        "tape"
    ],
    "wof:name":"Validated Tapes",
    "wof:placetype":"venue"
},
  "geometry": {"coordinates":[-80.055226,26.617552],"type":"Point"}
}