{
  "type": "Feature",
  "properties": {
    "iso:country":"US",
    "sg:address":"2041 Ortiz Ave",
    "sg:city":"Fort Myers",
    "sg:classifiers":[
        {
            "category":"Bars & Pubs",
            "type":"Food & Drink"
        }
    ],
    "sg:phone":"+1 239 337 5507",
    "sg:postcode":"33905",
    "sg:province":"FL",
    "wof:name":"Outpost Bar",
    "wof:placetype":"venue"
},
  "geometry": {"coordinates":[-81.81160800000001,26.640569],"type":"Point"}
}