{
  "type": "Feature",
  "properties": {
    "addr:full":"2525 Tamiami Trl Sarasota FL 34234",
    "addr:housenumber":"2525",
    "addr:postcode":"34234",
    "addr:street":"Tamiami Trl",
    "iso:country":"US",
    "sg:address":"2525 Tamiami Trl",
    "sg:city":"Sarasota",
    "sg:classifiers":[
        {
            "category":"Mining & Drilling",
            "type":"Manufacturing & Wholesale Goods"
        }
    ],
    "sg:phone":"+1 941 366 8432",
    "sg:postcode":"34234",
    "sg:province":"FL",
    "sg:tags":[
        "oil",
        "gas",
        "producer"
    ],
    "wof:name":"Suncoast Oil Co",
    "wof:placetype":"venue"
},
  "geometry": {"coordinates":[-82.549115,27.359678],"type":"Point"}
}