{
  "type": "Feature",
  "properties": {
    "addr:full":"821 SW Natura Blvd Deerfield Beach FL 33441",
    "addr:housenumber":"821",
    "addr:postcode":"33441",
    "addr:street":"Sw Natura Blvd",
    "iso:country":"US",
    "sg:address":"821 SW Natura Blvd",
    "sg:city":"Deerfield Beach",
    "sg:classifiers":[
        {
            "category":"Shopping",
            "subcategory":"Computers & Home Electronics",
            "type":"Retail Goods"
        }
    ],
    "sg:phone":"+1 305 624 5400",
    "sg:postcode":"33441",
    "sg:province":"FL",
    "sg:tags":[
        "household",
        "appliance"
    ],
    "wof:name":"Brandsmart USA",
    "wof:placetype":"venue"
},
  "geometry": {"coordinates":[-80.116653,26.30613],"type":"Point"}
}