{
  "type": "Feature",
  "properties": {
    "iso:country":"US",
    "sg:address":"1535 Lenox Ave",
    "sg:city":"Miami",
    "sg:classifiers":[
        {
            "category":"Real Estate",
            "subcategory":"Real Estate Operator",
            "type":"Services"
        }
    ],
    "sg:phone":"+1 305 673 9805",
    "sg:postcode":"33125",
    "sg:province":"FL",
    "sg:tags":[
        "apartment"
    ],
    "wof:name":"Stevens Apts",
    "wof:placetype":"venue"
},
  "geometry": {"coordinates":[-80.233498,25.7815],"type":"Point"}
}