{
  "type": "Feature",
  "properties": {
    "iso:country":"US",
    "sg:address":"22628 Island Pines Way",
    "sg:city":"Fort Myers Beach",
    "sg:classifiers":[
        {
            "category":"Real Estate",
            "subcategory":"Real Estate Operator",
            "type":"Services"
        }
    ],
    "sg:phone":"+1 239 765 1000",
    "sg:postcode":"33931",
    "sg:province":"FL",
    "sg:tags":[
        "condominium"
    ],
    "wof:name":"Estero Bayside",
    "wof:placetype":"venue"
},
  "geometry": {"coordinates":[-81.89936299999999,26.417131],"type":"Point"}
}