{
  "type": "Feature",
  "properties": {
    "addr:full":"5680 Gulf Breeze Pkwy Gulf Breeze FL 32563",
    "addr:housenumber":"5680",
    "addr:postcode":"32563",
    "addr:street":"Gulf Breeze Pkwy",
    "iso:country":"US",
    "sg:address":"5680 Gulf Breeze Pkwy",
    "sg:city":"Gulf Breeze",
    "sg:classifiers":[
        {
            "category":"Professional",
            "subcategory":"Advertising",
            "type":"Services"
        }
    ],
    "sg:phone":"+1 850 934 1458",
    "sg:postcode":"32563",
    "sg:province":"FL",
    "sg:tags":[
        "designer",
        "display",
        "producer"
    ],
    "wof:name":"C 4 Display Interiors Inc",
    "wof:placetype":"venue"
},
  "geometry": {"coordinates":[-86.98355100000001,30.402174],"type":"Point"}
}