{
  "type": "Feature",
  "properties": {
    "addr:full":"1290 Pasadena Ave S Saint Petersburg FL 33707",
    "addr:housenumber":"1290",
    "addr:postcode":"33707",
    "addr:street":"Pasadena Ave S",
    "iso:country":"US",
    "sg:address":"1290 Pasadena Ave S",
    "sg:city":"Saint Petersburg",
    "sg:classifiers":[
        {
            "category":"Restaurant",
            "type":"Food & Drink"
        }
    ],
    "sg:menulink":"http://www.allmenus.com/fl/st-petersburg/48449-ihop/menu/",
    "sg:phone":"+1 727 343 6604",
    "sg:postcode":"33707",
    "sg:province":"FL",
    "sg:tags":[
        "american"
    ],
    "wof:name":"IHOP",
    "wof:placetype":"venue"
},
  "geometry": {"coordinates":[-82.73692699999999,27.756652],"type":"Point"}
}