{
  "type": "Feature",
  "properties": {
    "iso:country":"US",
    "sg:address":"1511 S Volusia Ave",
    "sg:city":"Orange City",
    "sg:classifiers":[
        {
            "category":"Retail",
            "subcategory":"Auto Repair",
            "type":"Services"
        }
    ],
    "sg:phone":"+1 386 774 1566",
    "sg:postcode":"32763",
    "sg:province":"FL",
    "sg:tags":[
        "repairing",
        "automobile"
    ],
    "wof:name":"Ricky's Auto Repair",
    "wof:placetype":"venue"
},
  "geometry": {"coordinates":[-81.29898300000001,28.932822],"type":"Point"}
}