{
  "type": "Feature",
  "properties": {
    "addr:full":"606 S Main Ave Minneola FL 34715",
    "addr:housenumber":"606",
    "addr:postcode":"34715",
    "addr:street":"S Main Ave",
    "iso:country":"US",
    "sg:address":"606 S Main Ave",
    "sg:city":"Minneola",
    "sg:classifiers":[
        {
            "category":"Professional",
            "subcategory":"Engineering",
            "type":"Services"
        }
    ],
    "sg:phone":"+1 352 394 5756",
    "sg:postcode":"34715",
    "sg:province":"FL",
    "sg:tags":[
        "consulting",
        "engineer"
    ],
    "wof:name":"Mccoy & Associates",
    "wof:placetype":"venue"
},
  "geometry": {"coordinates":[-81.751991,28.574632],"type":"Point"}
}