{
  "type": "Feature",
  "properties": {
    "iso:country":"US",
    "sg:address":"1210 Bluffs Cir",
    "sg:city":"Dunedin",
    "sg:classifiers":[
        {
            "category":"Professional",
            "subcategory":"Management & Consulting",
            "type":"Services"
        }
    ],
    "sg:phone":"+1 727 812 5993",
    "sg:postcode":"34698",
    "sg:province":"FL",
    "sg:tags":[
        "counselor",
        "relation",
        "public"
    ],
    "wof:name":"John E Pickens",
    "wof:placetype":"venue"
},
  "geometry": {"coordinates":[-82.76873999999999,28.002343],"type":"Point"}
}