{
  "type": "Feature",
  "properties": {
    "iso:country":"US",
    "sg:address":"1306 N Federal Hwy",
    "sg:city":"Pompano Beach",
    "sg:classifiers":[
        {
            "category":"Shopping",
            "type":"Retail Goods"
        }
    ],
    "sg:phone":"+1 954 781 8060",
    "sg:postcode":"33062",
    "sg:province":"FL",
    "sg:tags":[
        "telephone",
        "cellular"
    ],
    "wof:name":"Radio Shack",
    "wof:placetype":"venue"
},
  "geometry": {"coordinates":[-80.101072,26.249596],"type":"Point"}
}