{
  "type": "Feature",
  "properties": {
    "addr:full":"4007 Berlin Orlando FL 32822",
    "addr:housenumber":"4007",
    "addr:postcode":"32822",
    "addr:street":"Berlin Orlando",
    "iso:country":"US",
    "sg:address":"4007 Berlin",
    "sg:city":"Orlando",
    "sg:classifiers":[
        {
            "category":"Shopping",
            "subcategory":"Gifts & Souvenirs",
            "type":"Retail Goods"
        }
    ],
    "sg:phone":"+1 407 249 2712",
    "sg:postcode":"32822",
    "sg:province":"FL",
    "wof:name":"Johnny Pacheco Gifts",
    "wof:placetype":"venue"
},
  "geometry": {"coordinates":[-81.28281800000001,28.497108],"type":"Point"}
}