{
  "type": "Feature",
  "properties": {
    "iso:country":"US",
    "sg:address":"8900 NW 35th Ln Ste 130",
    "sg:city":"Doral",
    "sg:classifiers":[
        {
            "category":"Shopping",
            "subcategory":"Computers & Home Electronics",
            "type":"Retail Goods"
        },
        {
            "category":"Wholesale",
            "subcategory":"Computers",
            "type":"Manufacturing & Wholesale Goods"
        }
    ],
    "sg:phone":"+1 305 436 5155",
    "sg:postcode":"33172",
    "sg:province":"FL",
    "sg:tags":[
        "hardware",
        "manufacturer",
        "computer-wholesale",
        "supply"
    ],
    "wof:name":"Wintel Group Corp",
    "wof:placetype":"venue"
},
  "geometry": {"coordinates":[-80.34022899999999,25.807133],"type":"Point"}
}