{
  "type": "Feature",
  "properties": {
    "iso:country":"US",
    "sg:address":"1066 Shipwatch Dr E",
    "sg:city":"Jacksonville",
    "sg:classifiers":[
        {
            "category":"Manufacturing",
            "subcategory":"Jewelry",
            "type":"Manufacturing & Wholesale Goods"
        }
    ],
    "sg:phone":"+1 904 221 9889",
    "sg:postcode":"32225",
    "sg:province":"FL",
    "sg:tags":[
        "material",
        "mfg"
    ],
    "wof:name":"Merrell Designs",
    "wof:placetype":"venue"
},
  "geometry": {"coordinates":[-81.446282,30.347133],"type":"Point"}
}