{
  "type": "Feature",
  "properties": {
    "iso:country":"US",
    "sg:address":"1341 Biarritz St NW",
    "sg:city":"Palm Bay",
    "sg:classifiers":[
        {
            "category":"Building & Trades",
            "subcategory":"Construction",
            "type":"Services"
        }
    ],
    "sg:phone":"+1 321 759 8585",
    "sg:postcode":"32907",
    "sg:province":"FL",
    "sg:tags":[
        "home",
        "improvement"
    ],
    "wof:name":"Kevin Larick Home Repairs",
    "wof:placetype":"venue"
},
  "geometry": {"coordinates":[-80.70945399999999,28.002458],"type":"Point"}
}