{
  "type": "Feature",
  "properties": {
    "iso:country":"US",
    "sg:address":"208 SE Hernando Ave",
    "sg:city":"Lake City",
    "sg:classifiers":[
        {
            "category":"Banks & Credit Unions",
            "subcategory":"Bank",
            "type":"Services"
        }
    ],
    "sg:phone":"+1 386 752 7951",
    "sg:postcode":"32025",
    "sg:province":"FL",
    "sg:tags":[
        "loan",
        "real estate"
    ],
    "wof:name":"Hometowne Brokers Inc",
    "wof:placetype":"venue"
},
  "geometry": {"coordinates":[-82.63641200000001,30.187943],"type":"Point"}
}