{
  "type": "Feature",
  "properties": {
    "addr:full":"9100 SW 72nd St Miami FL 33173",
    "addr:housenumber":"9100",
    "addr:postcode":"33173",
    "addr:street":"Sw 72Nd St",
    "iso:country":"US",
    "sg:address":"9100 SW 72nd St",
    "sg:city":"Miami",
    "sg:classifiers":[
        {
            "category":"Insurance",
            "subcategory":"Insurance Agent",
            "type":"Services"
        }
    ],
    "sg:phone":"+1 305 270 1424",
    "sg:postcode":"33173",
    "sg:province":"FL",
    "wof:name":"Pan American Assurance Agency",
    "wof:placetype":"venue"
},
  "geometry": {"coordinates":[-80.341072,25.701962],"type":"Point"}
}