{
  "type": "Feature",
  "properties": {
    "iso:country":"US",
    "sg:address":"846 W Eau Gallie Blvd",
    "sg:city":"Melbourne",
    "sg:classifiers":[
        {
            "category":"Shopping",
            "subcategory":"Bicycles & Sporting Goods",
            "type":"Retail Goods"
        }
    ],
    "sg:phone":"+1 321 255 0102",
    "sg:postcode":"32935",
    "sg:province":"FL",
    "wof:name":"Captain Mullets Bait & Tackle",
    "wof:placetype":"venue"
},
  "geometry": {"coordinates":[-80.631517,28.129069],"type":"Point"}
}