{
  "type": "Feature",
  "properties": {
    "addr:full":"6539 Spring Meadow Dr West Palm Beach FL 33413",
    "addr:housenumber":"6539",
    "addr:postcode":"33413",
    "addr:street":"Spring Meadow Dr",
    "iso:country":"US",
    "sg:address":"6539 Spring Meadow Dr",
    "sg:city":"West Palm Beach",
    "sg:classifiers":[
        {
            "category":"Communications",
            "subcategory":"Film & Video Production",
            "type":"Services"
        }
    ],
    "sg:phone":"+1 561 697 3773",
    "sg:postcode":"33413",
    "sg:province":"FL",
    "sg:tags":[
        "motion"
    ],
    "wof:name":"Premiere Images Inc",
    "wof:placetype":"venue"
},
  "geometry": {"coordinates":[-80.14613,26.663498],"type":"Point"}
}