{
  "type": "Feature",
  "properties": {
    "iso:country":"US",
    "sg:address":"4651 Ayron Ter",
    "sg:city":"Palm Harbor",
    "sg:classifiers":[
        {
            "category":"Wholesale",
            "subcategory":"Non-durable Goods",
            "type":"Manufacturing & Wholesale Goods"
        }
    ],
    "sg:phone":"+1 727 789 2030",
    "sg:postcode":"34685",
    "sg:province":"FL",
    "wof:name":"Kennedy Distribution Inc",
    "wof:placetype":"venue"
},
  "geometry": {"coordinates":[-82.69636800000001,28.111608],"type":"Point"}
}