{
  "type": "Feature",
  "properties": {
    "addr:full":"1313 NE 125th St Ste 200 North Miami FL 33161",
    "addr:housenumber":"1313",
    "addr:postcode":"33161",
    "addr:street":"Ne 125Th St Ste 200",
    "iso:country":"US",
    "sg:address":"1313 NE 125th St Ste 200",
    "sg:city":"North Miami",
    "sg:classifiers":[
        {
            "category":"Professional",
            "subcategory":"Lawyer & Legal Services",
            "type":"Services"
        }
    ],
    "sg:phone":"+1 954 921 4026",
    "sg:postcode":"33161",
    "sg:province":"FL",
    "sg:tags":[
        "divorce",
        "law",
        "family"
    ],
    "wof:name":"Jacobi Benjamin R Atty",
    "wof:placetype":"venue"
},
  "geometry": {"coordinates":[-80.172203,25.8909],"type":"Point"}
}