{
  "type": "Feature",
  "properties": {
    "iso:country":"US",
    "sg:address":"1506 E Bearss Ave",
    "sg:city":"Lutz",
    "sg:classifiers":[
        {
            "category":"Professional",
            "subcategory":"Accounting & Tax Preparation",
            "type":"Services"
        }
    ],
    "sg:phone":"+1 813 972 5629",
    "sg:postcode":"33549",
    "sg:province":"FL",
    "sg:tags":[
        "bookkeeping",
        "general"
    ],
    "wof:name":"Lamat Accounting Svc",
    "wof:placetype":"venue"
},
  "geometry": {"coordinates":[-82.44397600000001,28.082584],"type":"Point"}
}