{
  "type": "Feature",
  "properties": {
    "addr:full":"2600 Island Blvd Apt 1903 Aventura FL 33160",
    "addr:housenumber":"2600",
    "addr:postcode":"1903;33160",
    "addr:street":"Island Blvd Apt",
    "iso:country":"US",
    "sg:address":"2600 Island Blvd Apt 1903",
    "sg:city":"Aventura",
    "sg:classifiers":[
        {
            "category":"Restaurant",
            "type":"Food & Drink"
        }
    ],
    "sg:phone":"+1 305 931 7930",
    "sg:postcode":"33160",
    "sg:province":"FL",
    "wof:name":"Yetta Fried Linda S Golds",
    "wof:placetype":"venue"
},
  "geometry": {"coordinates":[-80.13527000000001,25.938716],"type":"Point"}
}