{
  "type": "Feature",
  "properties": {
    "addr:full":"2130 W Martin St Kissimmee FL 34741",
    "addr:housenumber":"2130",
    "addr:postcode":"34741",
    "addr:street":"W Martin St",
    "iso:country":"US",
    "sg:address":"2130 W Martin St",
    "sg:city":"Kissimmee",
    "sg:classifiers":[
        {
            "category":"Bus Charters",
            "type":"Transportation"
        }
    ],
    "sg:phone":"+1 407 870 7510",
    "sg:postcode":"34741",
    "sg:province":"FL",
    "sg:tags":[
        "rental"
    ],
    "wof:name":"L & E Transportation",
    "wof:placetype":"venue"
},
  "geometry": {"coordinates":[-81.42540200000001,28.282519],"type":"Point"}
}