{
  "type": "Feature",
  "properties": {
    "iso:country":"US",
    "sg:address":"3233 NE 10th St",
    "sg:city":"Pompano Beach",
    "sg:classifiers":[
        {
            "category":"Building & Trades",
            "subcategory":"Landscaping Services",
            "type":"Services"
        }
    ],
    "sg:phone":"+1 954 784 9483",
    "sg:postcode":"33062",
    "sg:province":"FL",
    "sg:tags":[
        "landscape"
    ],
    "wof:name":"Plantscapes Plus Inc",
    "wof:placetype":"venue"
},
  "geometry": {"coordinates":[-80.088044,26.246663],"type":"Point"}
}