{
  "type": "Feature",
  "properties": {
    "iso:country":"US",
    "sg:address":"7468 Aprelle Dr",
    "sg:city":"Sanford",
    "sg:classifiers":[
        {
            "category":"Wholesale",
            "subcategory":"Metals & Minerals",
            "type":"Manufacturing & Wholesale Goods"
        }
    ],
    "sg:phone":"+1 407 328 8042",
    "sg:postcode":"32771",
    "sg:province":"FL",
    "sg:tags":[
        "center"
    ],
    "wof:name":"Tom Winter",
    "wof:placetype":"venue"
},
  "geometry": {"coordinates":[-81.38979399999999,28.805196],"type":"Point"}
}