{
  "type": "Feature",
  "properties": {
    "iso:country":"US",
    "sg:address":"12276 San Jose Blvd",
    "sg:city":"Jacksonville",
    "sg:classifiers":[
        {
            "category":"Wholesale",
            "subcategory":"Construction Materials",
            "type":"Manufacturing & Wholesale Goods"
        }
    ],
    "sg:phone":"+1 904 880 4944",
    "sg:postcode":"32223",
    "sg:province":"FL",
    "sg:tags":[
        "equipment",
        "maker",
        "cabinet"
    ],
    "wof:name":"Specialty Tools",
    "wof:placetype":"venue"
},
  "geometry": {"coordinates":[-81.632693,30.145909],"type":"Point"}
}