{
  "type": "Feature",
  "properties": {
    "iso:country":"US",
    "sg:address":"3863 US Hwy 27",
    "sg:city":"Sebring",
    "sg:classifiers":[
        {
            "category":"Banks & Credit Unions",
            "subcategory":"Bank",
            "type":"Services"
        }
    ],
    "sg:phone":"+1 863 382 6620",
    "sg:postcode":"33870",
    "sg:province":"FL",
    "sg:tags":[
        "federal"
    ],
    "sg:website":"www.midflorida.com",
    "wof:name":"Midflorida Federal Credit Un",
    "wof:placetype":"venue"
},
  "geometry": {"coordinates":[-81.428214,27.459169],"type":"Point"}
}