{
  "type": "Feature",
  "properties": {
    "addr:full":"2600 NW 1st Ave Boca Raton FL 33431",
    "addr:housenumber":"2600",
    "addr:postcode":"33431",
    "addr:street":"Nw 1St Ave",
    "iso:country":"US",
    "sg:address":"2600 NW 1st Ave",
    "sg:city":"Boca Raton",
    "sg:classifiers":[
        {
            "category":"Professional",
            "subcategory":"Computer Services",
            "type":"Services"
        }
    ],
    "sg:phone":"+1 561 362 7400",
    "sg:postcode":"33431",
    "sg:province":"FL",
    "sg:tags":[
        "repair"
    ],
    "wof:name":"Custom Computerz",
    "wof:placetype":"venue"
},
  "geometry": {"coordinates":[-80.08552299999999,26.373721],"type":"Point"}
}