{
  "type": "Feature",
  "properties": {
    "iso:country":"US",
    "sg:address":"4047 N Andrews Ave",
    "sg:city":"Fort Lauderdale",
    "sg:classifiers":[
        {
            "category":"Retail",
            "subcategory":"Car Wash",
            "type":"Services"
        }
    ],
    "sg:phone":"+1 954 914 9832",
    "sg:postcode":"33309",
    "sg:province":"FL",
    "sg:tags":[
        "carwash"
    ],
    "wof:name":"Joes Special Appearance",
    "wof:placetype":"venue"
},
  "geometry": {"coordinates":[-80.14685,26.177364],"type":"Point"}
}