{
  "type": "Feature",
  "properties": {
    "addr:full":"500 Maldonado Dr Gulf Breeze FL 32561",
    "addr:housenumber":"500",
    "addr:postcode":"32561",
    "addr:street":"Maldonado Dr",
    "iso:country":"US",
    "sg:address":"500 Maldonado Dr",
    "sg:city":"Gulf Breeze",
    "sg:classifiers":[
        {
            "category":"Communications",
            "type":"Services"
        }
    ],
    "sg:phone":"+1 850 932 3281",
    "sg:postcode":"32561",
    "sg:province":"FL",
    "sg:tags":[
        "communication"
    ],
    "wof:name":"Fastnet Communication Services",
    "wof:placetype":"venue"
},
  "geometry": {"coordinates":[-87.121764,30.335686],"type":"Point"}
}