{
  "type": "Feature",
  "properties": {
    "addr:full":"6500 Oriole Blvd Englewood FL 34224",
    "addr:housenumber":"6500",
    "addr:postcode":"34224",
    "addr:street":"Oriole Blvd",
    "iso:country":"US",
    "sg:address":"6500 Oriole Blvd",
    "sg:city":"Englewood",
    "sg:classifiers":[
        {
            "category":"Organizations",
            "subcategory":"Professional Association",
            "type":"Services"
        }
    ],
    "sg:phone":"+1 941 475 6941",
    "sg:postcode":"34224",
    "sg:province":"FL",
    "wof:name":"Oyster Creek Homeowners Assoc",
    "wof:placetype":"venue"
},
  "geometry": {"coordinates":[-82.30969899999999,26.934527],"type":"Point"}
}