{
  "type": "Feature",
  "properties": {
    "addr:full":"1945 W Park Ave Edgewater FL 32132",
    "addr:housenumber":"1945",
    "addr:postcode":"32132",
    "addr:street":"W Park Ave",
    "iso:country":"US",
    "sg:address":"1945 W Park Ave",
    "sg:city":"Edgewater",
    "sg:classifiers":[
        {
            "category":"Organizations",
            "subcategory":"Professional Association",
            "type":"Services"
        }
    ],
    "sg:phone":"+1 386 423 6634",
    "sg:postcode":"32132",
    "sg:province":"FL",
    "wof:name":"American Senior Fitness Assn",
    "wof:placetype":"venue"
},
  "geometry": {"coordinates":[-80.937836,28.981289],"type":"Point"}
}