{
  "type": "Feature",
  "properties": {
    "addr:full":"10130 NW 47th St Fort Lauderdale FL 33351",
    "addr:housenumber":"10130",
    "addr:postcode":"33351",
    "addr:street":"Nw 47Th St",
    "iso:country":"US",
    "sg:address":"10130 NW 47th St",
    "sg:city":"Fort Lauderdale",
    "sg:classifiers":[
        {
            "category":"Building & Trades",
            "subcategory":"Landscaping Services",
            "type":"Services"
        }
    ],
    "sg:phone":"+1 954 749 7274",
    "sg:postcode":"33351",
    "sg:province":"FL",
    "sg:tags":[
        "lawn",
        "garden"
    ],
    "wof:name":"Tru Green-Chemlawn",
    "wof:placetype":"venue"
},
  "geometry": {"coordinates":[-80.286382,26.183363],"type":"Point"}
}