{
  "type": "Feature",
  "properties": {
    "iso:country":"US",
    "sg:address":"22017 Aqua Ct",
    "sg:city":"Boca Raton",
    "sg:classifiers":[
        {
            "category":"Professional",
            "subcategory":"Computer Services",
            "type":"Services"
        }
    ],
    "sg:phone":"+1 561 208 6427",
    "sg:postcode":"33428",
    "sg:province":"FL",
    "wof:name":"Rescuecom",
    "wof:placetype":"venue"
},
  "geometry": {"coordinates":[-80.24229099999999,26.349346],"type":"Point"}
}