{
  "type": "Feature",
  "properties": {
    "addr:full":"1710 Cornwallis Pkwy Cape Coral FL 33904",
    "addr:housenumber":"1710",
    "addr:postcode":"33904",
    "addr:street":"Cornwallis Pkwy",
    "iso:country":"US",
    "sg:address":"1710 Cornwallis Pkwy",
    "sg:city":"Cape Coral",
    "sg:classifiers":[
        {
            "category":"Education",
            "subcategory":"Dance Studio",
            "type":"Public Place"
        }
    ],
    "sg:phone":"+1 239 242 9330",
    "sg:postcode":"33904",
    "sg:province":"FL",
    "sg:tags":[
        "instruction",
        "dancing"
    ],
    "wof:name":"Camelle's Art Of Dance",
    "wof:placetype":"venue"
},
  "geometry": {"coordinates":[-81.93817,26.595906],"type":"Point"}
}