{
  "type": "Feature",
  "properties": {
    "addr:full":"4652 S Hwy 71 Wewahitchka FL 32465",
    "addr:housenumber":"4652",
    "addr:postcode":"32465",
    "addr:street":"S Hwy 71",
    "iso:country":"US",
    "sg:address":"4652 S Hwy 71",
    "sg:city":"Wewahitchka",
    "sg:classifiers":[
        {
            "category":"Retail",
            "subcategory":"Laundry & Dry Cleaning",
            "type":"Services"
        }
    ],
    "sg:phone":"+1 850 639 4370",
    "sg:postcode":"32465",
    "sg:province":"FL",
    "sg:tags":[
        "cleaners",
        "rug",
        "carpet"
    ],
    "wof:name":"Coastal Chem-Dry",
    "wof:placetype":"venue"
},
  "geometry": {"coordinates":[-85.18692299999999,30.048978],"type":"Point"}
}