{
  "type": "Feature",
  "properties": {
    "iso:country":"US",
    "sg:address":"133 Inlet Harbor Rd",
    "sg:city":"Ponce Inlet",
    "sg:classifiers":[
        {
            "category":"Recreation",
            "type":"Entertainment"
        }
    ],
    "sg:phone":"+1 386 767 2883",
    "sg:postcode":"32127",
    "sg:province":"FL",
    "sg:tags":[
        "guide"
    ],
    "wof:name":"Heavy Hitter Sportfishing",
    "wof:placetype":"venue"
},
  "geometry": {"coordinates":[-80.93684500000001,29.090532],"type":"Point"}
}