{
  "type": "Feature",
  "properties": {
    "addr:full":"3555 Prospect Ave Naples FL 34104",
    "addr:housenumber":"3555",
    "addr:postcode":"34104",
    "addr:street":"Prospect Ave",
    "iso:country":"US",
    "sg:address":"3555 Prospect Ave",
    "sg:city":"Naples",
    "sg:classifiers":[
        {
            "category":"Building & Trades",
            "subcategory":"Construction",
            "type":"Services"
        }
    ],
    "sg:phone":"+1 239 643 4447",
    "sg:postcode":"34104",
    "sg:province":"FL",
    "sg:tags":[
        "heavy"
    ],
    "wof:name":"Atlas Pile Driving Inc",
    "wof:placetype":"venue"
},
  "geometry": {"coordinates":[-81.761123,26.157014],"type":"Point"}
}