{
  "type": "Feature",
  "properties": {
    "iso:country":"US",
    "sg:address":"841 W Bay Dr",
    "sg:city":"Largo",
    "sg:classifiers":[
        {
            "category":"Restaurant",
            "type":"Food & Drink"
        }
    ],
    "sg:menulink":"http://www.allmenus.com/fl/clearwater/48591-beef-obradys/menu/",
    "sg:phone":"+1 727 501 9464",
    "sg:postcode":"33770",
    "sg:province":"FL",
    "sg:tags":[
        "burger",
        "american",
        "wing",
        "pub"
    ],
    "wof:name":"Beef O'Brady's",
    "wof:placetype":"venue"
},
  "geometry": {"coordinates":[-82.79716999999999,27.916742],"type":"Point"}
}