{
  "type": "Feature",
  "properties": {
    "addr:full":"1295 W 49th Pl Hialeah FL 33012",
    "addr:housenumber":"1295",
    "addr:postcode":"33012",
    "addr:street":"W 49Th Pl",
    "iso:country":"US",
    "sg:address":"1295 W 49th Pl",
    "sg:city":"Hialeah",
    "sg:classifiers":[
        {
            "category":"Freight",
            "type":"Transportation"
        }
    ],
    "sg:phone":"+1 305 557 9250",
    "sg:postcode":"33012",
    "sg:province":"FL",
    "sg:tags":[
        "trucking"
    ],
    "wof:name":"RPB Transport Corp",
    "wof:placetype":"venue"
},
  "geometry": {"coordinates":[-80.31066199999999,25.867286],"type":"Point"}
}