{
  "type": "Feature",
  "properties": {
    "addr:full":"1751 N Washington Blvd Sarasota FL 34234",
    "addr:housenumber":"1751",
    "addr:postcode":"34234",
    "addr:street":"N Washington Blvd",
    "iso:country":"US",
    "sg:address":"1751 N Washington Blvd",
    "sg:city":"Sarasota",
    "sg:classifiers":[
        {
            "category":"Retail",
            "subcategory":"Car Wash",
            "type":"Services"
        }
    ],
    "sg:phone":"+1 941 955 8553",
    "sg:postcode":"34234",
    "sg:province":"FL",
    "sg:tags":[
        "polishing",
        "washing"
    ],
    "wof:name":"Hob Nob Car Wash",
    "wof:placetype":"venue"
},
  "geometry": {"coordinates":[-82.530494,27.352677],"type":"Point"}
}