{
  "type": "Feature",
  "properties": {
    "addr:full":"760 E 113th Ave Tampa FL 33612",
    "addr:housenumber":"760",
    "addr:postcode":"33612",
    "addr:street":"E 113Th Ave",
    "iso:country":"US",
    "sg:address":"760 E 113th Ave",
    "sg:city":"Tampa",
    "sg:classifiers":[
        {
            "category":"Retail",
            "subcategory":"Auto Repair",
            "type":"Services"
        }
    ],
    "sg:phone":"+1 813 977 8676",
    "sg:postcode":"33612",
    "sg:province":"FL",
    "sg:tags":[
        "wrecker"
    ],
    "wof:name":"Dennings Towing & Recovery",
    "wof:placetype":"venue"
},
  "geometry": {"coordinates":[-82.45125299999999,28.051005],"type":"Point"}
}