{
  "type": "Feature",
  "properties": {
    "iso:country":"US",
    "sg:address":"6110 S Congress Ave",
    "sg:city":"Lantana",
    "sg:classifiers":[
        {
            "category":"Health Services",
            "subcategory":"Doctor",
            "type":"Services"
        }
    ],
    "sg:phone":"+1 561 649 8686",
    "sg:postcode":"33462",
    "sg:province":"FL",
    "sg:tags":[
        "clinic"
    ],
    "wof:name":"Central Palm Beach Physicians",
    "wof:placetype":"venue"
},
  "geometry": {"coordinates":[-80.093688,26.585923],"type":"Point"}
}