{
  "type": "Feature",
  "properties": {
    "addr:full":"933 Lee Rd Orlando FL 32810",
    "addr:housenumber":"933",
    "addr:postcode":"32810",
    "addr:street":"Lee Rd",
    "iso:country":"US",
    "sg:address":"933 Lee Rd",
    "sg:city":"Orlando",
    "sg:classifiers":[
        {
            "category":"Building & Trades",
            "subcategory":"Construction",
            "type":"Services"
        }
    ],
    "sg:phone":"+1 407 629 5431",
    "sg:postcode":"32810",
    "sg:province":"FL",
    "sg:tags":[
        "contractor"
    ],
    "sg:website":"www.icsinfo.com",
    "wof:name":"Industrial Commercial Structures Inc",
    "wof:placetype":"venue"
},
  "geometry": {"coordinates":[-81.39389199999999,28.60687],"type":"Point"}
}