{
  "type": "Feature",
  "properties": {
    "iso:country":"US",
    "sg:address":"255 S Tessier Dr",
    "sg:city":"St Pete Beach",
    "sg:classifiers":[
        {
            "category":"Travel",
            "subcategory":"Travel Agent",
            "type":"Entertainment"
        }
    ],
    "sg:phone":"+1 727 360 7313",
    "sg:postcode":"33706",
    "sg:province":"FL",
    "sg:tags":[
        "agency",
        "bureau"
    ],
    "wof:name":"A-Aaron's All-Inclusive Travel",
    "wof:placetype":"venue"
},
  "geometry": {"coordinates":[-82.732911,27.70007],"type":"Point"}
}