{
  "type": "Feature",
  "properties": {
    "iso:country":"US",
    "sg:address":"3520 SW Armellini Ave",
    "sg:city":"Palm City",
    "sg:classifiers":[
        {
            "category":"Airport",
            "type":"Transportation"
        }
    ],
    "sg:phone":"+1 772 223 8970",
    "sg:postcode":"34990",
    "sg:province":"FL",
    "sg:tags":[
        "aircraft",
        "maintenance"
    ],
    "wof:name":"Production Technology",
    "wof:placetype":"venue"
},
  "geometry": {"coordinates":[-80.302367,27.162835],"type":"Point"}
}