{
  "type": "Feature",
  "properties": {
    "iso:country":"US",
    "sg:address":"1201 S Orlando Ave",
    "sg:city":"Winter Park",
    "sg:classifiers":[
        {
            "category":"Social Services",
            "subcategory":"Job Training",
            "type":"Services"
        }
    ],
    "sg:phone":"+1 407 622 5766",
    "sg:postcode":"32789",
    "sg:province":"FL",
    "sg:tags":[
        "rehabilitation"
    ],
    "wof:name":"Fl Pain & Rehab",
    "wof:placetype":"venue"
},
  "geometry": {"coordinates":[-81.365106,28.585746],"type":"Point"}
}