{
  "type": "Feature",
  "properties": {
    "iso:country":"US",
    "sg:address":"4638 NW 27th Ave",
    "sg:city":"Miami",
    "sg:classifiers":[
        {
            "category":"Organizations",
            "subcategory":"Membership Organization",
            "type":"Services"
        }
    ],
    "sg:phone":"+1 305 634 8886",
    "sg:postcode":"33142",
    "sg:province":"FL",
    "wof:name":"Teen Pregnancy",
    "wof:placetype":"venue"
},
  "geometry": {"coordinates":[-80.24060299999999,25.817056],"type":"Point"}
}