{
  "type": "Feature",
  "properties": {
    "addr:full":"1044 Seminole Dr Tallahassee FL 32301",
    "addr:housenumber":"1044",
    "addr:postcode":"32301",
    "addr:street":"Seminole Dr",
    "iso:country":"US",
    "sg:address":"1044 Seminole Dr",
    "sg:city":"Tallahassee",
    "sg:classifiers":[
        {
            "category":"Professional",
            "type":"Services"
        }
    ],
    "sg:phone":"+1 850 216 1707",
    "sg:postcode":"32301",
    "sg:province":"FL",
    "wof:name":"Krabco Inc",
    "wof:placetype":"venue"
},
  "geometry": {"coordinates":[-84.26675899999999,30.435247],"type":"Point"}
}