{
  "type": "Feature",
  "properties": {
    "addr:full":"29 Angelfish Cay Dr Key Largo FL 33037",
    "addr:housenumber":"29",
    "addr:postcode":"33037",
    "addr:street":"Angelfish Cay Dr",
    "iso:country":"US",
    "sg:address":"29 Angelfish Cay Dr",
    "sg:city":"Key Largo",
    "sg:classifiers":[
        {
            "category":"Professional",
            "subcategory":"Management & Consulting",
            "type":"Services"
        }
    ],
    "sg:phone":"+1 305 367 2925",
    "sg:postcode":"33037",
    "sg:province":"FL",
    "wof:name":"Daenzer Associates",
    "wof:placetype":"venue"
},
  "geometry": {"coordinates":[-80.272655,25.318085],"type":"Point"}
}