{
  "type": "Feature",
  "properties": {
    "iso:country":"US",
    "sg:address":"8062 W Sample Rd",
    "sg:city":"Pompano Beach",
    "sg:classifiers":[
        {
            "category":"Personal",
            "type":"Services"
        }
    ],
    "sg:phone":"+1 954 752 1119",
    "sg:postcode":"33065",
    "sg:province":"FL",
    "sg:tags":[
        "automobile",
        "licensing",
        "title"
    ],
    "wof:name":"Florida Auto Tag",
    "wof:placetype":"venue"
},
  "geometry": {"coordinates":[-80.23000999999999,26.27227],"type":"Point"}
}