{
  "type": "Feature",
  "properties": {
    "addr:full":"832 W Central Blvd Orlando FL 32805",
    "addr:housenumber":"832",
    "addr:postcode":"32805",
    "addr:street":"W Central Blvd",
    "iso:country":"US",
    "sg:address":"832 W Central Blvd",
    "sg:city":"Orlando",
    "sg:classifiers":[
        {
            "category":"Utilities",
            "subcategory":"Telephone",
            "type":"Services"
        }
    ],
    "sg:phone":"+1 407 423 8516",
    "sg:postcode":"32805",
    "sg:province":"FL",
    "wof:name":"Inmate Telephone",
    "wof:placetype":"venue"
},
  "geometry": {"coordinates":[-81.390945,28.542005],"type":"Point"}
}