{
  "type": "Feature",
  "properties": {
    "addr:full":"5550 NW 31st Ave Fort Lauderdale FL 33309",
    "addr:housenumber":"5550",
    "addr:postcode":"33309",
    "addr:street":"Nw 31St Ave",
    "iso:country":"US",
    "sg:address":"5550 NW 31st Ave",
    "sg:city":"Fort Lauderdale",
    "sg:classifiers":[
        {
            "category":"Restaurant",
            "type":"Food & Drink"
        }
    ],
    "sg:phone":"+1 954 731 9838",
    "sg:postcode":"33309",
    "sg:province":"FL",
    "sg:tags":[
        "out"
    ],
    "wof:name":"Chester Fried Chicken",
    "wof:placetype":"venue"
},
  "geometry": {"coordinates":[-80.18769399999999,26.194688],"type":"Point"}
}