{
  "type": "Feature",
  "properties": {
    "iso:country":"US",
    "sg:address":"300 S Pine Island Rd",
    "sg:city":"Plantation",
    "sg:classifiers":[
        {
            "category":"Health Services",
            "subcategory":"Health Practitioner",
            "type":"Services"
        }
    ],
    "sg:phone":"+1 954 452 7559",
    "sg:postcode":"33324",
    "sg:province":"FL",
    "sg:tags":[
        "psychotherapist"
    ],
    "wof:name":"Roberta Bergman",
    "wof:placetype":"venue"
},
  "geometry": {"coordinates":[-80.26214299999999,26.116287],"type":"Point"}
}