{
  "type": "Feature",
  "properties": {
    "iso:country":"US",
    "sg:address":"6110 SW 137th Ave",
    "sg:city":"Miami",
    "sg:classifiers":[
        {
            "category":"Banks & Credit Unions",
            "subcategory":"Bank",
            "type":"Services"
        }
    ],
    "sg:phone":"+1 305 387 2469",
    "sg:postcode":"33183",
    "sg:province":"FL",
    "sg:tags":[
        "bond",
        "broker",
        "stock"
    ],
    "wof:name":"Beryle Greenberg",
    "wof:placetype":"venue"
},
  "geometry": {"coordinates":[-80.415046,25.71036],"type":"Point"}
}