{
  "type": "Feature",
  "properties": {
    "addr:full":"935 Indian Beach Dr Sarasota FL 34234",
    "addr:housenumber":"935",
    "addr:postcode":"34234",
    "addr:street":"Indian Beach Dr",
    "iso:country":"US",
    "sg:address":"935 Indian Beach Dr",
    "sg:city":"Sarasota",
    "sg:classifiers":[
        {
            "category":"Professional",
            "subcategory":"Management & Consulting",
            "type":"Services"
        }
    ],
    "sg:phone":"+1 941 351 2452",
    "sg:postcode":"34234",
    "sg:province":"FL",
    "sg:tags":[
        "fuel"
    ],
    "wof:name":"Management Outsourcing",
    "wof:placetype":"venue"
},
  "geometry": {"coordinates":[-82.551867,27.359979],"type":"Point"}
}