{
  "type": "Feature",
  "properties": {
    "iso:country":"US",
    "sg:address":"104 SE 1st Ave",
    "sg:city":"Ocala",
    "sg:classifiers":[
        {
            "category":"Professional",
            "subcategory":"Accounting & Tax Preparation",
            "type":"Services"
        }
    ],
    "sg:phone":"+1 352 622 2271",
    "sg:postcode":"34471",
    "sg:province":"FL",
    "sg:tags":[
        "accountant"
    ],
    "wof:name":"Leslie Turner & Assoc",
    "wof:placetype":"venue"
},
  "geometry": {"coordinates":[-82.13611,29.184781],"type":"Point"}
}