{
  "type": "Feature",
  "properties": {
    "iso:country":"US",
    "sg:address":"27 NE 10th Ave",
    "sg:city":"Ocala",
    "sg:classifiers":[
        {
            "category":"Professional",
            "type":"Services"
        }
    ],
    "sg:phone":"+1 352 401 0643",
    "sg:postcode":"34470",
    "sg:province":"FL",
    "sg:tags":[
        "establishment"
    ],
    "wof:name":"Professional Space Design",
    "wof:placetype":"venue"
},
  "geometry": {"coordinates":[-82.12637599999999,29.18826],"type":"Point"}
}