{
  "type": "Feature",
  "properties": {
    "iso:country":"US",
    "sg:address":"2117 60th Dr E",
    "sg:city":"Bradenton",
    "sg:classifiers":[
        {
            "category":"Manufacturing",
            "subcategory":"Tools & Machinery",
            "type":"Manufacturing & Wholesale Goods"
        }
    ],
    "sg:phone":"+1 941 755 7881",
    "sg:postcode":"34203",
    "sg:province":"FL",
    "sg:tags":[
        "machine",
        "shop"
    ],
    "wof:name":"Bay Tool Inc",
    "wof:placetype":"venue"
},
  "geometry": {"coordinates":[-82.534316,27.435607],"type":"Point"}
}