{
  "type": "Feature",
  "properties": {
    "addr:full":"210 Jupiter Lakes Blvd Jupiter FL 33458",
    "addr:housenumber":"210",
    "addr:postcode":"33458",
    "addr:street":"Jupiter Lakes Blvd",
    "iso:country":"US",
    "sg:address":"210 Jupiter Lakes Blvd",
    "sg:city":"Jupiter",
    "sg:classifiers":[
        {
            "category":"Health Services",
            "subcategory":"Doctor",
            "type":"Services"
        }
    ],
    "sg:phone":"+1 561 746 0541",
    "sg:postcode":"33458",
    "sg:province":"FL",
    "sg:tags":[
        "physician",
        "surgeon"
    ],
    "wof:name":"James D Daughtry MD",
    "wof:placetype":"venue"
},
  "geometry": {"coordinates":[-80.095052,26.921214],"type":"Point"}
}