{
  "type": "Feature",
  "properties": {
    "iso:country":"US",
    "sg:address":"143 Northwood Rd",
    "sg:city":"Crawfordville",
    "sg:classifiers":[
        {
            "category":"Building & Trades",
            "subcategory":"Construction",
            "type":"Services"
        }
    ],
    "sg:phone":"+1 850 556 0252",
    "sg:postcode":"32327",
    "sg:province":"FL",
    "sg:tags":[
        "marking",
        "maintenance",
        "parking"
    ],
    "wof:name":"All American Asphalt",
    "wof:placetype":"venue"
},
  "geometry": {"coordinates":[-84.33074499999999,30.288262],"type":"Point"}
}