{
  "type": "Feature",
  "properties": {
    "addr:full":"2 Independent Dr Jacksonville FL 32202",
    "addr:housenumber":"2",
    "addr:postcode":"32202",
    "addr:street":"Independent Dr",
    "iso:country":"US",
    "sg:address":"2 Independent Dr",
    "sg:city":"Jacksonville",
    "sg:classifiers":[
        {
            "category":"Cafe",
            "type":"Food & Drink"
        }
    ],
    "sg:menulink":"http://www.allmenus.com/fl/jacksonville/39266-the-american-cafe/menu/",
    "sg:phone":"+1 904 353 4503",
    "sg:postcode":"32202",
    "sg:province":"FL",
    "sg:tags":[
        "american"
    ],
    "wof:name":"The American Cafe",
    "wof:placetype":"venue"
},
  "geometry": {"coordinates":[-81.65968599999999,30.325475],"type":"Point"}
}