{
  "type": "Feature",
  "properties": {
    "iso:country":"US",
    "sg:address":"30047 US Hwy 19",
    "sg:city":"Clearwater",
    "sg:classifiers":[
        {
            "category":"Shopping",
            "subcategory":"Florist",
            "type":"Retail Goods"
        }
    ],
    "sg:phone":"+1 727 787 0020",
    "sg:postcode":"33761",
    "sg:province":"FL",
    "wof:name":"Flower Cart",
    "wof:placetype":"venue"
},
  "geometry": {"coordinates":[-82.738471,28.048186],"type":"Point"}
}