{
  "type": "Feature",
  "properties": {
    "addr:full":"421 W Church St Jacksonville FL 32202",
    "addr:housenumber":"421",
    "addr:postcode":"32202",
    "addr:street":"W Church St",
    "iso:country":"US",
    "sg:address":"421 W Church St",
    "sg:city":"Jacksonville",
    "sg:classifiers":[
        {
            "category":"Utilities",
            "subcategory":"Telephone",
            "type":"Services"
        }
    ],
    "sg:phone":"+1 904 356 5708",
    "sg:postcode":"32202",
    "sg:province":"FL",
    "sg:tags":[
        "telecommunication"
    ],
    "wof:name":"ITC Deltacom",
    "wof:placetype":"venue"
},
  "geometry": {"coordinates":[-81.66283300000001,30.331349],"type":"Point"}
}