{
  "type": "Feature",
  "properties": {
    "iso:country":"US",
    "sg:address":"4201 el Mar Dr",
    "sg:city":"Fort Lauderdale",
    "sg:classifiers":[
        {
            "category":"Travel",
            "subcategory":"Hotels & Motels",
            "type":"Entertainment"
        }
    ],
    "sg:phone":"+1 954 776 4240",
    "sg:postcode":"33308",
    "sg:province":"FL",
    "wof:name":"Sea Cliff Apartments",
    "wof:placetype":"venue"
},
  "geometry": {"coordinates":[-80.096068,26.187544],"type":"Point"}
}