{
  "type": "Feature",
  "properties": {
    "iso:country":"US",
    "sg:address":"2292 Mayport Rd",
    "sg:city":"Atlantic Beach",
    "sg:classifiers":[
        {
            "category":"Personal",
            "subcategory":"Beauty Salon",
            "type":"Services"
        }
    ],
    "sg:phone":"+1 904 247 7080",
    "sg:postcode":"32233",
    "sg:province":"FL",
    "sg:tags":[
        "manicuring"
    ],
    "wof:name":"Amy Nails",
    "wof:placetype":"venue"
},
  "geometry": {"coordinates":[-81.41347,30.34511],"type":"Point"}
}