{
  "type": "Feature",
  "properties": {
    "iso:country":"US",
    "sg:address":"2213 Seaboard Ave",
    "sg:city":"Venice",
    "sg:classifiers":[
        {
            "category":"Real Estate",
            "subcategory":"Real Estate Agent",
            "type":"Services"
        },
        {
            "category":"Professional",
            "subcategory":"Business Services",
            "type":"Services"
        }
    ],
    "sg:phone":"+1 941 493 4155",
    "sg:postcode":"34293",
    "sg:province":"FL",
    "sg:tags":[
        "home",
        "inspection"
    ],
    "wof:name":"Apson Home Inspection Inc",
    "wof:placetype":"venue"
},
  "geometry": {"coordinates":[-82.404788,27.053512],"type":"Point"}
}