{
  "type": "Feature",
  "properties": {
    "iso:country":"US",
    "sg:address":"2150 Lake Ave SE",
    "sg:city":"Largo",
    "sg:classifiers":[
        {
            "category":"Building & Trades",
            "subcategory":"Construction",
            "type":"Services"
        }
    ],
    "sg:phone":"+1 727 584 8001",
    "sg:postcode":"33771",
    "sg:province":"FL",
    "sg:tags":[
        "concrete",
        "contractor"
    ],
    "sg:website":"www.joswigconstruction.com",
    "wof:name":"Joswig Construction Inc",
    "wof:placetype":"venue"
},
  "geometry": {"coordinates":[-82.77089700000001,27.895972],"type":"Point"}
}