{
  "type": "Feature",
  "properties": {
    "iso:country":"US",
    "sg:address":"17480 Devore Ln",
    "sg:city":"Fort Myers",
    "sg:classifiers":[
        {
            "category":"Building & Trades",
            "subcategory":"Landscaping Services",
            "type":"Services"
        }
    ],
    "sg:phone":"+1 239 454 5665",
    "sg:postcode":"33913",
    "sg:province":"FL",
    "sg:tags":[
        "lawn",
        "maintenance",
        "grounds"
    ],
    "wof:name":"All In One Lawn Care",
    "wof:placetype":"venue"
},
  "geometry": {"coordinates":[-81.72262600000001,26.489679],"type":"Point"}
}