{
  "type": "Feature",
  "properties": {
    "iso:country":"US",
    "sg:address":"4676 Hinote Rd",
    "sg:city":"Crestview",
    "sg:classifiers":[
        {
            "category":"Building & Trades",
            "subcategory":"Construction",
            "type":"Services"
        }
    ],
    "sg:phone":"+1 850 892 7844",
    "sg:postcode":"32539",
    "sg:province":"FL",
    "sg:tags":[
        "hanging",
        "contractor"
    ],
    "wof:name":"Larry Edge Painting",
    "wof:placetype":"venue"
},
  "geometry": {"coordinates":[-86.36532099999999,30.796477],"type":"Point"}
}