{
  "type": "Feature",
  "properties": {
    "iso:country":"US",
    "sg:address":"8360 Philatelic Dr",
    "sg:city":"Spring Hill",
    "sg:classifiers":[
        {
            "category":"Recreation",
            "subcategory":"Marina",
            "type":"Entertainment"
        }
    ],
    "sg:phone":"+1 352 666 7520",
    "sg:postcode":"34606",
    "sg:province":"FL",
    "sg:tags":[
        "repairing",
        "boat"
    ],
    "wof:name":"Blue Water Custom Boat Repair",
    "wof:placetype":"venue"
},
  "geometry": {"coordinates":[-82.57964,28.48517],"type":"Point"}
}