{
  "type": "Feature",
  "properties": {
    "iso:country":"US",
    "sg:address":"764 Main St",
    "sg:city":"Dunedin",
    "sg:classifiers":[
        {
            "category":"Health Services",
            "subcategory":"Clinic",
            "type":"Services"
        },
        {
            "category":"Community Center",
            "type":"Public Place"
        }
    ],
    "sg:phone":"+1 727 736 2229",
    "sg:postcode":"34698",
    "sg:province":"FL",
    "sg:tags":[
        "medical",
        "osteopathic"
    ],
    "wof:name":"Exodus Womens Center",
    "wof:placetype":"venue"
},
  "geometry": {"coordinates":[-82.782009,28.015855],"type":"Point"}
}