{
  "type": "Feature",
  "properties": {
    "iso:country":"US",
    "sg:address":"33005 Azua Bay",
    "sg:city":"Boynton Beach",
    "sg:classifiers":[
        {
            "category":"Building & Trades",
            "subcategory":"Landscaping Services",
            "type":"Services"
        }
    ],
    "sg:phone":"+1 561 734 3185",
    "sg:postcode":"33436",
    "sg:province":"FL",
    "sg:tags":[
        "landscape"
    ],
    "wof:name":"Carl Minnberg",
    "wof:placetype":"venue"
},
  "geometry": {"coordinates":[-80.12111400000001,26.543516],"type":"Point"}
}