{
  "type": "Feature",
  "properties": {
    "iso:country":"US",
    "sg:address":"663 20th Pl SW",
    "sg:city":"Vero Beach",
    "sg:classifiers":[
        {
            "category":"Real Estate",
            "subcategory":"Real Estate Agent",
            "type":"Services"
        }
    ],
    "sg:phone":"+1 772 770 2002",
    "sg:postcode":"32962",
    "sg:province":"FL",
    "sg:tags":[
        "inspection"
    ],
    "wof:name":"A 1 Home Inspectors",
    "wof:placetype":"venue"
},
  "geometry": {"coordinates":[-80.386078,27.566071],"type":"Point"}
}