{
  "type": "Feature",
  "properties": {
    "addr:full":"1301 13th Way West Palm Beach FL 33407",
    "addr:housenumber":"1301",
    "addr:postcode":"33407",
    "addr:street":"13Th Way",
    "iso:country":"US",
    "sg:address":"1301 13th Way",
    "sg:city":"West Palm Beach",
    "sg:classifiers":[
        {
            "category":"Manufacturing",
            "subcategory":"Tools & Machinery",
            "type":"Manufacturing & Wholesale Goods"
        }
    ],
    "sg:phone":"+1 561 616 3642",
    "sg:postcode":"33407",
    "sg:province":"FL",
    "sg:tags":[
        "equipment",
        "commercial",
        "laundry",
        "mfg"
    ],
    "wof:name":"Presse For Time of Palm Beach",
    "wof:placetype":"venue"
},
  "geometry": {"coordinates":[-80.09885199999999,26.752029],"type":"Point"}
}