{
  "type": "Feature",
  "properties": {
    "addr:full":"1851 Eagle Trace Blvd Palm Harbor FL 34685",
    "addr:housenumber":"1851",
    "addr:postcode":"34685",
    "addr:street":"Eagle Trace Blvd",
    "iso:country":"US",
    "sg:address":"1851 Eagle Trace Blvd",
    "sg:city":"Palm Harbor",
    "sg:classifiers":[
        {
            "category":"Professional",
            "subcategory":"Engineering",
            "type":"Services"
        }
    ],
    "sg:phone":"+1 727 787 7856",
    "sg:postcode":"34685",
    "sg:province":"FL",
    "sg:tags":[
        "general",
        "contractor"
    ],
    "wof:name":"Fluid Design & Engineering Co",
    "wof:placetype":"venue"
},
  "geometry": {"coordinates":[-82.70865499999999,28.076673],"type":"Point"}
}