{
  "type": "Feature",
  "properties": {
    "iso:country":"US",
    "sg:address":"7702 Rivergate Dr",
    "sg:city":"Tampa",
    "sg:classifiers":[
        {
            "category":"Real Estate",
            "subcategory":"Real Estate Services",
            "type":"Services"
        },
        {
            "category":"Real Estate",
            "subcategory":"Real Estate Operator",
            "type":"Services"
        }
    ],
    "sg:phone":"+1 813 621 4141",
    "sg:postcode":"33619",
    "sg:province":"FL",
    "sg:tags":[
        "vacancy",
        "apartment",
        "rental",
        "finder",
        "listing"
    ],
    "wof:name":"Rivergate Apartments",
    "wof:placetype":"venue"
},
  "geometry": {"coordinates":[-82.370678,27.947562],"type":"Point"}
}