{
  "type": "Feature",
  "properties": {
    "iso:country":"US",
    "sg:address":"339 S Ridgewood Ave",
    "sg:city":"Daytona Beach",
    "sg:classifiers":[
        {
            "category":"Professional",
            "subcategory":"Lawyer & Legal Services",
            "type":"Services"
        }
    ],
    "sg:phone":"+1 386 257 1550",
    "sg:postcode":"32114",
    "sg:province":"FL",
    "sg:tags":[
        "attorney"
    ],
    "wof:name":"Robert E Eddington",
    "wof:placetype":"venue"
},
  "geometry": {"coordinates":[-81.020087,29.205894],"type":"Point"}
}