{
  "type": "Feature",
  "properties": {
    "iso:country":"US",
    "sg:address":"23430 SW 122nd Ave",
    "sg:city":"Homestead",
    "sg:classifiers":[
        {
            "category":"Farming",
            "subcategory":"Orchard",
            "type":"Manufacturing & Wholesale Goods"
        }
    ],
    "sg:phone":"+1 305 257 5651",
    "sg:postcode":"33032",
    "sg:province":"FL",
    "sg:tags":[
        "fruit",
        "tree"
    ],
    "wof:name":"Whitman Fruit",
    "wof:placetype":"venue"
},
  "geometry": {"coordinates":[-80.388428,25.546102],"type":"Point"}
}