{
  "type": "Feature",
  "properties": {
    "iso:country":"US",
    "sg:address":"10441 NW 28th Ave",
    "sg:city":"Miami",
    "sg:classifiers":[
        {
            "category":"Wholesale",
            "subcategory":"Computers",
            "type":"Manufacturing & Wholesale Goods"
        }
    ],
    "sg:phone":"+1 305 468 9948",
    "sg:postcode":"33147",
    "sg:province":"FL",
    "sg:website":"www.onetechusa.com",
    "wof:name":"Onetech USA Corp",
    "wof:placetype":"venue"
},
  "geometry": {"coordinates":[-80.24341,25.869387],"type":"Point"}
}