{
  "type": "Feature",
  "properties": {
    "addr:full":"670 NW 154th Ave Hollywood FL 33028",
    "addr:housenumber":"670",
    "addr:postcode":"33028",
    "addr:street":"Nw 154Th Ave",
    "iso:country":"US",
    "sg:address":"670 NW 154th Ave",
    "sg:city":"Hollywood",
    "sg:classifiers":[
        {
            "category":"Freight",
            "type":"Transportation"
        }
    ],
    "sg:phone":"+1 954 437 4925",
    "sg:postcode":"33028",
    "sg:province":"FL",
    "sg:tags":[
        "arrangement"
    ],
    "wof:name":"Exim Online Corp",
    "wof:placetype":"venue"
},
  "geometry": {"coordinates":[-80.349254,26.012765],"type":"Point"}
}