{
  "type": "Feature",
  "properties": {
    "iso:country":"US",
    "sg:address":"7267 NW 78th Ter",
    "sg:city":"Medley",
    "sg:classifiers":[
        {
            "category":"Manufacturing",
            "subcategory":"Glass & Minerals",
            "type":"Manufacturing & Wholesale Goods"
        }
    ],
    "sg:phone":"+1 305 884 7667",
    "sg:postcode":"33166",
    "sg:province":"FL",
    "sg:tags":[
        "plate",
        "window",
        "glass-auto"
    ],
    "wof:name":"America's Impact Products",
    "wof:placetype":"venue"
},
  "geometry": {"coordinates":[-80.315589,25.844807],"type":"Point"}
}