{
  "type": "Feature",
  "properties": {
    "addr:full":"415 Montgomery Rd Altamonte Springs FL 32714",
    "addr:housenumber":"415",
    "addr:postcode":"32714",
    "addr:street":"Montgomery Rd",
    "iso:country":"US",
    "sg:address":"415 Montgomery Rd",
    "sg:city":"Altamonte Springs",
    "sg:classifiers":[
        {
            "category":"Travel",
            "subcategory":"Travel Agent",
            "type":"Entertainment"
        }
    ],
    "sg:phone":"+1 407 862 7668",
    "sg:postcode":"32714",
    "sg:province":"FL",
    "sg:tags":[
        "agency"
    ],
    "wof:name":"Regal Travel Services Inc",
    "wof:placetype":"venue"
},
  "geometry": {"coordinates":[-81.40249,28.66822],"type":"Point"}
}