{
  "type": "Feature",
  "properties": {
    "iso:country":"US",
    "sg:address":"2914 Oakwood Blvd",
    "sg:city":"Hollywood",
    "sg:classifiers":[
        {
            "category":"Shopping",
            "subcategory":"Optical Goods",
            "type":"Retail Goods"
        }
    ],
    "sg:phone":"+1 954 920 8546",
    "sg:postcode":"33020",
    "sg:province":"FL",
    "wof:name":"Eric Radzwill Assoc",
    "wof:placetype":"venue"
},
  "geometry": {"coordinates":[-80.160574,26.043702],"type":"Point"}
}