{
  "type": "Feature",
  "properties": {
    "iso:country":"US",
    "sg:address":"13617 Atlantic Blvd",
    "sg:city":"Jacksonville",
    "sg:classifiers":[
        {
            "category":"Building & Trades",
            "subcategory":"Construction",
            "type":"Services"
        }
    ],
    "sg:phone":"+1 904 221 8411",
    "sg:postcode":"32225",
    "sg:province":"FL",
    "sg:tags":[
        "sweeping",
        "street"
    ],
    "wof:name":"Surface Management Corp",
    "wof:placetype":"venue"
},
  "geometry": {"coordinates":[-81.44788699999999,30.321351],"type":"Point"}
}