{
  "type": "Feature",
  "properties": {
    "addr:full":"24850 Old 41 Rd Bonita Springs FL 34135",
    "addr:housenumber":"24850",
    "addr:postcode":"34135",
    "addr:street":"Old 41 Rd",
    "iso:country":"US",
    "sg:address":"24850 Old 41 Rd",
    "sg:city":"Bonita Springs",
    "sg:classifiers":[
        {
            "category":"Banks & Credit Unions",
            "subcategory":"Bank",
            "type":"Services"
        }
    ],
    "sg:phone":"+1 239 949 9520",
    "sg:postcode":"34135",
    "sg:province":"FL",
    "sg:tags":[
        "loan"
    ],
    "wof:name":"Napoleon Financial Group",
    "wof:placetype":"venue"
},
  "geometry": {"coordinates":[-81.806361,26.380163],"type":"Point"}
}