{
  "type": "Feature",
  "properties": {
    "addr:full":"105 E Dogwood St Monticello FL 32344",
    "addr:housenumber":"105",
    "addr:postcode":"32344",
    "addr:street":"E Dogwood St",
    "iso:country":"US",
    "sg:address":"105 E Dogwood St",
    "sg:city":"Monticello",
    "sg:classifiers":[
        {
            "category":"Personal",
            "subcategory":"Beauty Salon",
            "type":"Services"
        },
        {
            "category":"Personal",
            "subcategory":"Barber",
            "type":"Services"
        }
    ],
    "sg:phone":"+1 850 997 4767",
    "sg:postcode":"32344",
    "sg:province":"FL",
    "wof:name":"Christine's Barber & Beauty",
    "wof:placetype":"venue"
},
  "geometry": {"coordinates":[-83.869703,30.545885],"type":"Point"}
}