{
  "type": "Feature",
  "properties": {
    "addr:full":"502 SW Pine Tree Ln Palm City FL 34990",
    "addr:housenumber":"502",
    "addr:postcode":"34990",
    "addr:street":"Sw Pine Tree Ln",
    "iso:country":"US",
    "sg:address":"502 SW Pine Tree Ln",
    "sg:city":"Palm City",
    "sg:classifiers":[
        {
            "category":"Professional",
            "subcategory":"Business Services",
            "type":"Services"
        }
    ],
    "sg:phone":"+1 305 235 2400",
    "sg:postcode":"34990",
    "sg:province":"FL",
    "sg:tags":[
        "glass"
    ],
    "wof:name":"A-Ace Board-Up Svc",
    "wof:placetype":"venue"
},
  "geometry": {"coordinates":[-80.293136,27.198788],"type":"Point"}
}