{
  "type": "Feature",
  "properties": {
    "addr:full":"640 SW 89th Ct Miami FL 33174",
    "addr:housenumber":"640",
    "addr:postcode":"33174",
    "addr:street":"Sw 89Th Ct",
    "iso:country":"US",
    "sg:address":"640 SW 89th Ct",
    "sg:city":"Miami",
    "sg:classifiers":[
        {
            "category":"Wholesale",
            "subcategory":"Non-durable Goods",
            "type":"Manufacturing & Wholesale Goods"
        }
    ],
    "sg:phone":"+1 305 229 7336",
    "sg:postcode":"33174",
    "sg:province":"FL",
    "sg:tags":[
        "dry",
        "goods-wholesale"
    ],
    "wof:name":"Eucaris Supply Inc",
    "wof:placetype":"venue"
},
  "geometry": {"coordinates":[-80.340631,25.763186],"type":"Point"}
}