{
  "type": "Feature",
  "properties": {
    "iso:country":"US",
    "sg:address":"6745 NW 74th Ct",
    "sg:city":"Pompano Beach",
    "sg:classifiers":[
        {
            "category":"Real Estate",
            "subcategory":"Real Estate Agent",
            "type":"Services"
        }
    ],
    "sg:phone":"+1 954 340 7569",
    "sg:postcode":"33067",
    "sg:province":"FL",
    "wof:name":"Ken Weiss PA",
    "wof:placetype":"venue"
},
  "geometry": {"coordinates":[-80.215491,26.322757],"type":"Point"}
}