{
  "type": "Feature",
  "properties": {
    "iso:country":"US",
    "sg:address":"7761 NW 47th Ct",
    "sg:city":"Fort Lauderdale",
    "sg:classifiers":[
        {
            "category":"Building & Trades",
            "subcategory":"Construction",
            "type":"Services"
        }
    ],
    "sg:phone":"+1 954 748 2270",
    "sg:postcode":"33351",
    "sg:province":"FL",
    "sg:tags":[
        "contractor"
    ],
    "wof:name":"Colombia Contractors Inc",
    "wof:placetype":"venue"
},
  "geometry": {"coordinates":[-80.259682,26.183879],"type":"Point"}
}