{
  "type": "Feature",
  "properties": {
    "iso:country":"US",
    "sg:address":"2824 SW 99th Ct",
    "sg:city":"Miami",
    "sg:classifiers":[
        {
            "category":"Shopping",
            "subcategory":"Books",
            "type":"Retail Goods"
        }
    ],
    "sg:phone":"+1 305 553 5898",
    "sg:postcode":"33165",
    "sg:province":"FL",
    "wof:name":"Liberty Books & Comics Inc",
    "wof:placetype":"venue"
},
  "geometry": {"coordinates":[-80.356273,25.742796],"type":"Point"}
}