{
  "type": "Feature",
  "properties": {
    "iso:country":"US",
    "sg:address":"3460 32nd Ave N",
    "sg:city":"St Petersburg",
    "sg:classifiers":[
        {
            "category":"Real Estate",
            "subcategory":"Real Estate Agent",
            "type":"Services"
        }
    ],
    "sg:phone":"+1 727 599 1013",
    "sg:postcode":"33713",
    "sg:province":"FL",
    "wof:name":"Richard Lamborn Real Estate",
    "wof:placetype":"venue"
},
  "geometry": {"coordinates":[-82.681574,27.801008],"type":"Point"}
}