{
  "type": "Feature",
  "properties": {
    "iso:country":"US",
    "sg:address":"201 SE 2nd Ave Ste. 209",
    "sg:city":"Gainesville",
    "sg:classifiers":[
        {
            "category":"Professional",
            "subcategory":"Computer Services",
            "type":"Services"
        }
    ],
    "sg:phone":"+1 352 283 8012",
    "sg:postcode":"32601",
    "sg:province":"FL",
    "sg:tags":[
        "music",
        "file-sharing",
        "monetization"
    ],
    "sg:website":"http://listen.grooveshark.com",
    "wof:name":"Grooveshark",
    "wof:placetype":"venue"
},
  "geometry": {"coordinates":[-82.322373,29.650294],"type":"Point"}
}