{
  "type": "Feature",
  "properties": {
    "addr:full":"4205 Hollywood Blvd Hollywood FL 33021",
    "addr:housenumber":"4205",
    "addr:postcode":"33021",
    "addr:street":"Hollywood Blvd",
    "iso:country":"US",
    "sg:address":"4205 Hollywood Blvd",
    "sg:city":"Hollywood",
    "sg:classifiers":[
        {
            "category":"Banks & Credit Unions",
            "subcategory":"Bank",
            "type":"Services"
        }
    ],
    "sg:phone":"+1 954 967 4441",
    "sg:postcode":"33021",
    "sg:province":"FL",
    "sg:tags":[
        "personal",
        "institution"
    ],
    "wof:name":"Sun Credit Union",
    "wof:placetype":"venue"
},
  "geometry": {"coordinates":[-80.18747500000001,26.010627],"type":"Point"}
}