{
  "type": "Feature",
  "properties": {
    "addr:full":"1790 W 49th St Ste 116 Hialeah FL 33012",
    "addr:housenumber":"1790",
    "addr:postcode":"33012",
    "addr:street":"W 49Th St Ste 116",
    "iso:country":"US",
    "sg:address":"1790 W 49th St Ste 116",
    "sg:city":"Hialeah",
    "sg:classifiers":[
        {
            "category":"Health Services",
            "subcategory":"Doctor",
            "type":"Services"
        }
    ],
    "sg:phone":"+1 305 822 8622",
    "sg:postcode":"33012",
    "sg:province":"FL",
    "wof:name":"Fernandez Wilfred P MD",
    "wof:placetype":"venue"
},
  "geometry": {"coordinates":[-80.318825,25.866393],"type":"Point"}
}