{
  "type": "Feature",
  "properties": {
    "addr:full":"2801 Fruitville Rd Sarasota FL 34237",
    "addr:housenumber":"2801",
    "addr:postcode":"34237",
    "addr:street":"Fruitville Rd",
    "iso:country":"US",
    "sg:address":"2801 Fruitville Rd",
    "sg:city":"Sarasota",
    "sg:classifiers":[
        {
            "category":"Health Services",
            "subcategory":"Hospital",
            "type":"Services"
        }
    ],
    "sg:phone":"+1 941 955 5518",
    "sg:postcode":"34237",
    "sg:province":"FL",
    "sg:tags":[
        "mental"
    ],
    "wof:name":"Center For Change Of Florida",
    "wof:placetype":"venue"
},
  "geometry": {"coordinates":[-82.511995,27.337528],"type":"Point"}
}