{
  "type": "Feature",
  "properties": {
    "addr:full":"7311 Hearth Stone Ave Boynton Beach FL 33472",
    "addr:housenumber":"7311",
    "addr:postcode":"33472",
    "addr:street":"Hearth Stone Ave",
    "iso:country":"US",
    "sg:address":"7311 Hearth Stone Ave",
    "sg:city":"Boynton Beach",
    "sg:classifiers":[
        {
            "category":"Health Services",
            "subcategory":"Clinic",
            "type":"Services"
        }
    ],
    "sg:phone":"+1 561 731 1411",
    "sg:postcode":"33472",
    "sg:province":"FL",
    "wof:name":"Aberdeen Health Care",
    "wof:placetype":"venue"
},
  "geometry": {"coordinates":[-80.161219,26.550781],"type":"Point"}
}