{
  "type": "Feature",
  "properties": {
    "iso:country":"US",
    "sg:address":"17044 Terraverde Cir",
    "sg:city":"Fort Myers",
    "sg:classifiers":[
        {
            "category":"Professional",
            "subcategory":"Computer Services",
            "type":"Services"
        }
    ],
    "sg:phone":"+1 239 481 0723",
    "sg:postcode":"33908",
    "sg:province":"FL",
    "sg:tags":[
        "repair"
    ],
    "wof:name":"One Stop Computers",
    "wof:placetype":"venue"
},
  "geometry": {"coordinates":[-81.85534,26.491257],"type":"Point"}
}