{
  "type": "Feature",
  "properties": {
    "addr:full":"3920 Roberts Point Rd Sarasota FL 34242",
    "addr:housenumber":"3920",
    "addr:postcode":"34242",
    "addr:street":"Roberts Point Rd",
    "iso:country":"US",
    "sg:address":"3920 Roberts Point Rd",
    "sg:city":"Sarasota",
    "sg:classifiers":[
        {
            "category":"Home & Garden",
            "subcategory":"Carpets & Floor Coverings",
            "type":"Retail Goods"
        }
    ],
    "sg:phone":"+1 941 349 4456",
    "sg:postcode":"34242",
    "sg:province":"FL",
    "wof:name":"Gene Benson Carpets",
    "wof:placetype":"venue"
},
  "geometry": {"coordinates":[-82.5578,27.29892],"type":"Point"}
}