{
  "type": "Feature",
  "properties": {
    "iso:country":"US",
    "sg:address":"7300 NW 19th St",
    "sg:city":"Miami",
    "sg:classifiers":[
        {
            "category":"Manufacturing",
            "subcategory":"Food",
            "type":"Manufacturing & Wholesale Goods"
        }
    ],
    "sg:phone":"+1 305 599 9009",
    "sg:postcode":"33126",
    "sg:province":"FL",
    "sg:tags":[
        "confectionery-wholesale",
        "candy",
        "manufacturer"
    ],
    "wof:name":"Colombina Candy Co",
    "wof:placetype":"venue"
},
  "geometry": {"coordinates":[-80.31420199999999,25.791825],"type":"Point"}
}