{
  "type": "Feature",
  "properties": {
    "iso:country":"US",
    "sg:address":"201 82nd St",
    "sg:city":"Miami",
    "sg:classifiers":[
        {
            "category":"Personal",
            "subcategory":"Barber",
            "type":"Services"
        }
    ],
    "sg:phone":"+1 305 758 5306",
    "sg:postcode":"33141",
    "sg:province":"FL",
    "wof:name":"Relax Unisex Barbershop",
    "wof:placetype":"venue"
},
  "geometry": {"coordinates":[-80.12182300000001,25.86706],"type":"Point"}
}