{
  "type": "Feature",
  "properties": {
    "addr:full":"3710 16th Ave SE Naples FL 34117",
    "addr:housenumber":"3710",
    "addr:postcode":"34117",
    "addr:street":"16Th Ave Se",
    "iso:country":"US",
    "sg:address":"3710 16th Ave SE",
    "sg:city":"Naples",
    "sg:classifiers":[
        {
            "category":"Professional",
            "type":"Services"
        }
    ],
    "sg:phone":"+1 239 455 4736",
    "sg:postcode":"34117",
    "sg:province":"FL",
    "sg:tags":[
        "sculptor"
    ],
    "wof:name":"Renaissance Enterprises",
    "wof:placetype":"venue"
},
  "geometry": {"coordinates":[-81.535977,26.20146],"type":"Point"}
}