{
  "type": "Feature",
  "properties": {
    "iso:country":"US",
    "sg:address":"130 Scarlet Blvd",
    "sg:city":"Oldsmar",
    "sg:classifiers":[
        {
            "category":"Professional",
            "subcategory":"Research",
            "type":"Services"
        }
    ],
    "sg:phone":"+1 813 855 5830",
    "sg:postcode":"34677",
    "sg:province":"FL",
    "sg:tags":[
        "merger",
        "banking",
        "investment",
        "acquisition",
        "mortgage"
    ],
    "wof:name":"Financial Capital Resources",
    "wof:placetype":"venue"
},
  "geometry": {"coordinates":[-82.675116,28.041522],"type":"Point"}
}