{
  "type": "Feature",
  "properties": {
    "iso:country":"US",
    "sg:address":"308 6th Ave",
    "sg:city":"Indian Rocks Bch",
    "sg:classifiers":[
        {
            "category":"Home & Garden",
            "subcategory":"Garden Supply",
            "type":"Retail Goods"
        }
    ],
    "sg:phone":"+1 727 446 4331",
    "sg:postcode":"33785",
    "sg:province":"FL",
    "sg:tags":[
        "sprinkler"
    ],
    "wof:name":"Affordable Sprinkler Systems",
    "wof:placetype":"venue"
},
  "geometry": {"coordinates":[-82.84659600000001,27.884238],"type":"Point"}
}