{
  "type": "Feature",
  "properties": {
    "iso:country":"US",
    "sg:address":"17554 Back Beach Rd",
    "sg:city":"Panama City Bch",
    "sg:classifiers":[
        {
            "category":"Building & Trades",
            "subcategory":"Construction",
            "type":"Services"
        }
    ],
    "sg:phone":"+1 850 235 0109",
    "sg:postcode":"32413",
    "sg:province":"FL",
    "sg:tags":[
        "house",
        "contractor"
    ],
    "wof:name":"Mike Thomas Contracting",
    "wof:placetype":"venue"
},
  "geometry": {"coordinates":[-85.900661,30.234892],"type":"Point"}
}