{
  "type": "Feature",
  "properties": {
    "addr:full":"555 Challenger Rd Cape Canaveral FL 32920",
    "addr:housenumber":"555",
    "addr:postcode":"32920",
    "addr:street":"Challenger Rd",
    "iso:country":"US",
    "sg:address":"555 Challenger Rd",
    "sg:city":"Cape Canaveral",
    "sg:classifiers":[
        {
            "category":"Manufacturing",
            "subcategory":"Tools & Machinery",
            "type":"Manufacturing & Wholesale Goods"
        }
    ],
    "sg:phone":"+1 321 783 6346",
    "sg:postcode":"32920",
    "sg:province":"FL",
    "sg:tags":[
        "machine",
        "shop"
    ],
    "wof:name":"A & E Machine Shop Inc",
    "wof:placetype":"venue"
},
  "geometry": {"coordinates":[-80.615574,28.404323],"type":"Point"}
}