{
  "type": "Feature",
  "properties": {
    "addr:full":"721 W New England Ave Winter Park FL 32789",
    "addr:housenumber":"721",
    "addr:postcode":"32789",
    "addr:street":"W New England Ave",
    "iso:country":"US",
    "sg:address":"721 W New England Ave",
    "sg:city":"Winter Park",
    "sg:classifiers":[
        {
            "category":"Organizations",
            "subcategory":"Non-profit Organization",
            "type":"Services"
        }
    ],
    "sg:phone":"+1 407 599 3275",
    "sg:postcode":"32789",
    "sg:province":"FL",
    "sg:tags":[
        "service/non-profit",
        "community"
    ],
    "wof:name":"Winter Park Community Center",
    "wof:placetype":"venue"
},
  "geometry": {"coordinates":[-81.35838699999999,28.59682],"type":"Point"}
}