{
  "type": "Feature",
  "properties": {
    "addr:full":"1631 Taylor Rd Port Orange FL 32128",
    "addr:housenumber":"1631",
    "addr:postcode":"32128",
    "addr:street":"Taylor Rd",
    "iso:country":"US",
    "sg:address":"1631 Taylor Rd",
    "sg:city":"Port Orange",
    "sg:classifiers":[
        {
            "category":"Food & Beverages",
            "subcategory":"Groceries & Convenience Stores",
            "type":"Retail Goods"
        }
    ],
    "sg:phone":"+1 386 756 0082",
    "sg:postcode":"32128",
    "sg:province":"FL",
    "wof:name":"Hess Gas Station",
    "wof:placetype":"venue"
},
  "geometry": {"coordinates":[-81.035066,29.103496],"type":"Point"}
}