{
  "type": "Feature",
  "properties": {
    "iso:country":"US",
    "sg:address":"12342 Cascades Pointe Dr",
    "sg:city":"Boca Raton",
    "sg:classifiers":[
        {
            "category":"Retail",
            "subcategory":"Repair Shop",
            "type":"Services"
        }
    ],
    "sg:phone":"+1 561 483 4553",
    "sg:postcode":"33428",
    "sg:province":"FL",
    "sg:tags":[
        "elevator",
        "maintenance"
    ],
    "wof:name":"Centrellx Elevator Svc Corp",
    "wof:placetype":"venue"
},
  "geometry": {"coordinates":[-80.24259000000001,26.361281],"type":"Point"}
}