{
  "type": "Feature",
  "properties": {
    "addr:full":"11778 SE Federal Hwy Hobe Sound FL 33455",
    "addr:postcode":"11778;33455",
    "addr:street":"Se Federal Hwy",
    "iso:country":"US",
    "sg:address":"11778 SE Federal Hwy",
    "sg:city":"Hobe Sound",
    "sg:classifiers":[
        {
            "category":"Restaurant",
            "type":"Food & Drink"
        }
    ],
    "sg:menulink":"http://www.allmenus.com/fl/port-salerno-hobe-sound/31004-china-bell/menu/",
    "sg:phone":"+1 772 545 2085",
    "sg:postcode":"33455",
    "sg:province":"FL",
    "sg:tags":[
        "asian",
        "chinese"
    ],
    "wof:name":"China Bell",
    "wof:placetype":"venue"
},
  "geometry": {"coordinates":[-80.13757,27.06115],"type":"Point"}
}