{
  "type": "Feature",
  "properties": {
    "addr:full":"7701 Lexington Club Blvd Delray Beach FL 33446",
    "addr:housenumber":"7701",
    "addr:postcode":"33446",
    "addr:street":"Lexington Club Blvd",
    "iso:country":"US",
    "sg:address":"7701 Lexington Club Blvd",
    "sg:city":"Delray Beach",
    "sg:classifiers":[
        {
            "category":"Retail",
            "subcategory":"Veterinary Services",
            "type":"Services"
        }
    ],
    "sg:phone":"+1 561 499 0990",
    "sg:postcode":"33446",
    "sg:province":"FL",
    "wof:name":"Veterinary Diagnostic Imaging",
    "wof:placetype":"venue"
},
  "geometry": {"coordinates":[-80.168575,26.449063],"type":"Point"}
}