{
  "type": "Feature",
  "properties": {
    "iso:country":"US",
    "sg:address":"906 SE Lakeview Dr",
    "sg:city":"Sebring",
    "sg:classifiers":[
        {
            "category":"Professional",
            "subcategory":"Accounting & Tax Preparation",
            "type":"Services"
        }
    ],
    "sg:phone":"+1 863 382 8343",
    "sg:postcode":"33870",
    "sg:province":"FL",
    "sg:tags":[
        "return",
        "filing"
    ],
    "wof:name":"H & R Block Tax Svc",
    "wof:placetype":"venue"
},
  "geometry": {"coordinates":[-81.44043000000001,27.485718],"type":"Point"}
}