{
  "type": "Feature",
  "properties": {
    "iso:country":"US",
    "sg:address":"412 SE 2nd St",
    "sg:city":"Okeechobee",
    "sg:classifiers":[
        {
            "category":"Professional",
            "subcategory":"Accounting & Tax Preparation",
            "type":"Services"
        }
    ],
    "sg:phone":"+1 863 763 3766",
    "sg:postcode":"34974",
    "sg:province":"FL",
    "sg:tags":[
        "return",
        "filing"
    ],
    "wof:name":"Bert's Tax Svc",
    "wof:placetype":"venue"
},
  "geometry": {"coordinates":[-80.826421,27.242043],"type":"Point"}
}