{
  "type": "Feature",
  "properties": {
    "addr:full":"1100 W Euclid Ave Deland FL 32720",
    "addr:housenumber":"1100",
    "addr:postcode":"32720",
    "addr:street":"W Euclid Ave",
    "iso:country":"US",
    "sg:address":"1100 W Euclid Ave",
    "sg:city":"Deland",
    "sg:classifiers":[
        {
            "category":"Professional",
            "subcategory":"Research",
            "type":"Services"
        }
    ],
    "sg:phone":"+1 386 785 0027",
    "sg:postcode":"32720",
    "sg:province":"FL",
    "sg:tags":[
        "environmental",
        "ecological"
    ],
    "wof:name":"Earth Tech Inc",
    "wof:placetype":"venue"
},
  "geometry": {"coordinates":[-81.32398499999999,29.02075],"type":"Point"}
}