{
  "type": "Feature",
  "properties": {
    "iso:country":"US",
    "sg:address":"7522 Wiles Rd",
    "sg:city":"Pompano Beach",
    "sg:classifiers":[
        {
            "category":"Professional",
            "subcategory":"Management & Consulting",
            "type":"Services"
        }
    ],
    "sg:phone":"+1 954 341 8135",
    "sg:postcode":"33067",
    "sg:province":"FL",
    "sg:tags":[
        "marketing",
        "magazine",
        "book",
        "order",
        "subscription"
    ],
    "wof:name":"Palmetto Marketing Inc",
    "wof:placetype":"venue"
},
  "geometry": {"coordinates":[-80.227591,26.286629],"type":"Point"}
}