{
  "type": "Feature",
  "properties": {
    "iso:country":"US",
    "sg:address":"5701 Mariner St Apt 401",
    "sg:city":"Tampa",
    "sg:classifiers":[
        {
            "category":"Professional",
            "subcategory":"Engineering",
            "type":"Services"
        },
        {
            "category":"Professional",
            "subcategory":"Business Services",
            "type":"Services"
        }
    ],
    "sg:phone":"+1 813 448 0225",
    "sg:postcode":"33609",
    "sg:province":"FL",
    "sg:tags":[
        "engineer",
        "consultant",
        "coach",
        "mechanical"
    ],
    "wof:name":"Consulting Associates Inc",
    "wof:placetype":"venue"
},
  "geometry": {"coordinates":[-82.53736000000001,27.941992],"type":"Point"}
}