{
  "type": "Feature",
  "properties": {
    "iso:country":"US",
    "sg:address":"1881 N University Dr",
    "sg:city":"Coral Springs",
    "sg:classifiers":[
        {
            "category":"Professional",
            "subcategory":"Lawyer & Legal Services",
            "type":"Services"
        }
    ],
    "sg:phone":"+1 954 752 5252",
    "sg:postcode":"33071",
    "sg:province":"FL",
    "sg:tags":[
        "attorney"
    ],
    "wof:name":"Walter R Blake",
    "wof:placetype":"venue"
},
  "geometry": {"coordinates":[-80.253237,26.251163],"type":"Point"}
}