{
  "type": "Feature",
  "properties": {
    "iso:country":"US",
    "sg:address":"Centennial Park Heitman & First Streets",
    "sg:city":"Fort Myers",
    "sg:classifiers":[
        {
            "category":"Food & Beverages",
            "subcategory":"Farmers Market",
            "type":"Retail Goods"
        }
    ],
    "sg:phone":"+1 239 321 7100",
    "sg:postcode":"33901",
    "sg:province":"FL",
    "sg:website":"www.localharvest.org/farmers-mar...",
    "wof:name":"Fort Myers Downtown Farmers' Market",
    "wof:placetype":"venue"
},
  "geometry": {"coordinates":[-81.872691,26.642782],"type":"Point"}
}