{
  "type": "Feature",
  "properties": {
    "addr:full":"201 S Biscayne Blvd # 2800 Miami FL 33131",
    "addr:housenumber":"201",
    "addr:postcode":"33131",
    "addr:street":"S Biscayne Blvd # 2800",
    "iso:country":"US",
    "sg:address":"201 S Biscayne Blvd # 2800",
    "sg:city":"Miami",
    "sg:classifiers":[
        {
            "category":"Travel",
            "subcategory":"Travel Agent",
            "type":"Entertainment"
        }
    ],
    "sg:phone":"+1 305 913 6448",
    "sg:postcode":"33131",
    "sg:province":"FL",
    "sg:tags":[
        "agency",
        "services-commercial"
    ],
    "wof:name":"Magic Johnson Travel Group Gp",
    "wof:placetype":"venue"
},
  "geometry": {"coordinates":[-80.187134,25.772663],"type":"Point"}
}