{
  "type": "Feature",
  "properties": {
    "iso:country":"US",
    "sg:address":"2204 Citrus Blvd Ste 4A",
    "sg:city":"Leesburg",
    "sg:classifiers":[
        {
            "category":"Building & Trades",
            "subcategory":"Equipment Rental",
            "type":"Services"
        }
    ],
    "sg:phone":"+1 352 787 2205",
    "sg:postcode":"34748",
    "sg:province":"FL",
    "sg:tags":[
        "supplies-renting",
        "hospital",
        "wheelchairs-rental"
    ],
    "sg:website":"http://www.tlcoxygen.com/",
    "wof:name":"T L C Oxygen & Medical Supplies, Inc.",
    "wof:placetype":"venue"
},
  "geometry": {"coordinates":[-81.893393,28.839817],"type":"Point"}
}