{
  "type": "Feature",
  "properties": {
    "iso:country":"US",
    "sg:address":"701 Cleveland St",
    "sg:city":"Clearwater",
    "sg:classifiers":[
        {
            "category":"Education",
            "subcategory":"School",
            "type":"Public Place"
        }
    ],
    "sg:phone":"+1 727 446 4292",
    "sg:postcode":"33755",
    "sg:province":"FL",
    "wof:name":"Life Imprv Through Educatn",
    "wof:placetype":"venue"
},
  "geometry": {"coordinates":[-82.795903,27.965635],"type":"Point"}
}