{
  "type": "Feature",
  "properties": {
    "iso:country":"US",
    "sg:address":"9017 Terranova Dr",
    "sg:city":"Naples",
    "sg:classifiers":[
        {
            "category":"Building & Trades",
            "subcategory":"Construction",
            "type":"Services"
        }
    ],
    "sg:phone":"+1 239 594 9596",
    "sg:postcode":"34109",
    "sg:province":"FL",
    "sg:tags":[
        "home",
        "builder"
    ],
    "wof:name":"Distinctive Communities Inc",
    "wof:placetype":"venue"
},
  "geometry": {"coordinates":[-81.77575400000001,26.247616],"type":"Point"}
}