{
  "type": "Feature",
  "properties": {
    "addr:full":"1445 NW 56th St Miami FL 33142",
    "addr:housenumber":"1445",
    "addr:postcode":"33142",
    "addr:street":"Nw 56Th St",
    "iso:country":"US",
    "sg:address":"1445 NW 56th St",
    "sg:city":"Miami",
    "sg:classifiers":[
        {
            "category":"Professional",
            "type":"Services"
        }
    ],
    "sg:phone":"+1 305 634 4540",
    "sg:postcode":"33142",
    "sg:province":"FL",
    "sg:tags":[
        "establishment"
    ],
    "wof:name":"Lavvy Mathis",
    "wof:placetype":"venue"
},
  "geometry": {"coordinates":[-80.221802,25.826827],"type":"Point"}
}