{
  "type": "Feature",
  "properties": {
    "addr:full":"19569 NE 10th Ave Miami FL 33179",
    "addr:housenumber":"19569",
    "addr:postcode":"33179",
    "addr:street":"Ne 10Th Ave",
    "iso:country":"US",
    "sg:address":"19569 NE 10th Ave",
    "sg:city":"Miami",
    "sg:classifiers":[
        {
            "category":"Shopping",
            "subcategory":"Books",
            "type":"Retail Goods"
        }
    ],
    "sg:phone":"+1 305 653 4712",
    "sg:postcode":"33179",
    "sg:province":"FL",
    "sg:tags":[
        "dealer"
    ],
    "wof:name":"Distal USA Inc",
    "wof:placetype":"venue"
},
  "geometry": {"coordinates":[-80.181843,25.956038],"type":"Point"}
}