{
  "type": "Feature",
  "properties": {
    "addr:full":"1190 Alabama Ave Daytona Beach FL 32117",
    "addr:housenumber":"1190",
    "addr:postcode":"32117",
    "addr:street":"Alabama Ave",
    "iso:country":"US",
    "sg:address":"1190 Alabama Ave",
    "sg:city":"Daytona Beach",
    "sg:classifiers":[
        {
            "category":"Building & Trades",
            "subcategory":"Construction",
            "type":"Services"
        }
    ],
    "sg:phone":"+1 386 671 1597",
    "sg:postcode":"32117",
    "sg:province":"FL",
    "sg:tags":[
        "contractor"
    ],
    "wof:name":"Justin Muller Plaster & Stucco",
    "wof:placetype":"venue"
},
  "geometry": {"coordinates":[-81.069183,29.250431],"type":"Point"}
}