{
  "type": "Feature",
  "properties": {
    "addr:full":"1601 S French Ave Sanford FL 32771",
    "addr:housenumber":"1601",
    "addr:postcode":"32771",
    "addr:street":"S French Ave",
    "iso:country":"US",
    "sg:address":"1601 S French Ave",
    "sg:city":"Sanford",
    "sg:classifiers":[
        {
            "category":"Banks & Credit Unions",
            "subcategory":"Bank",
            "type":"Services"
        }
    ],
    "sg:phone":"+1 407 330 7250",
    "sg:postcode":"32771",
    "sg:province":"FL",
    "wof:name":"Wachovia Bank",
    "wof:placetype":"venue"
},
  "geometry": {"coordinates":[-81.27301900000001,28.796781],"type":"Point"}
}