{
  "type": "Feature",
  "properties": {
    "iso:country":"US",
    "sg:address":"1905 NW 32nd St",
    "sg:city":"Pompano Beach",
    "sg:classifiers":[
        {
            "category":"Building & Trades",
            "subcategory":"Construction",
            "type":"Services"
        }
    ],
    "sg:phone":"+1 954 974 4988",
    "sg:postcode":"33064",
    "sg:province":"FL",
    "sg:tags":[
        "contractor"
    ],
    "wof:name":"Tarpon Springs Construction",
    "wof:placetype":"venue"
},
  "geometry": {"coordinates":[-80.149851,26.269875],"type":"Point"}
}