{
  "type": "Feature",
  "properties": {
    "addr:full":"5300 Gulf Blvd Saint Petersburg FL 33706",
    "addr:housenumber":"5300",
    "addr:postcode":"33706",
    "addr:street":"Gulf Blvd",
    "iso:country":"US",
    "sg:address":"5300 Gulf Blvd",
    "sg:city":"Saint Petersburg",
    "sg:classifiers":[
        {
            "category":"Travel",
            "subcategory":"Hotels & Motels",
            "type":"Entertainment"
        }
    ],
    "sg:phone":"+1 727 360 3292",
    "sg:postcode":"33706",
    "sg:province":"FL",
    "sg:tags":[
        "operation",
        "eating",
        "drinking",
        "g"
    ],
    "wof:name":"Island Cafe",
    "wof:placetype":"venue"
},
  "geometry": {"coordinates":[-82.74298400000001,27.728842],"type":"Point"}
}