{
  "type": "Feature",
  "properties": {
    "iso:country":"US",
    "sg:address":"2110 Feast Rd",
    "sg:city":"Melbourne",
    "sg:classifiers":[
        {
            "category":"Building & Trades",
            "subcategory":"Landscaping Services",
            "type":"Services"
        }
    ],
    "sg:phone":"+1 321 952 9438",
    "sg:postcode":"32904",
    "sg:province":"FL",
    "wof:name":"Handschuh Tree Surgeons",
    "wof:placetype":"venue"
},
  "geometry": {"coordinates":[-80.67633600000001,28.078908],"type":"Point"}
}