{
  "type": "Feature",
  "properties": {
    "addr:full":"5525 Roosevelt Blvd Jacksonville FL 32244",
    "addr:housenumber":"5525",
    "addr:postcode":"32244",
    "addr:street":"Roosevelt Blvd",
    "iso:country":"US",
    "sg:address":"5525 Roosevelt Blvd",
    "sg:city":"Jacksonville",
    "sg:classifiers":[
        {
            "category":"Shopping",
            "subcategory":"Discount & Variety Stores",
            "type":"Retail Goods"
        }
    ],
    "sg:phone":"+1 904 384 9595",
    "sg:postcode":"32244",
    "sg:province":"FL",
    "sg:website":"http://www.dollargeneral.com",
    "wof:name":"Dollar General",
    "wof:placetype":"venue"
},
  "geometry": {"coordinates":[-81.697176,30.245815],"type":"Point"}
}