{
  "type": "Feature",
  "properties": {
    "iso:country":"US",
    "sg:address":"890 E 9th St",
    "sg:city":"Hialeah",
    "sg:classifiers":[
        {
            "category":"Retail",
            "subcategory":"Self-service Laundry",
            "type":"Services"
        }
    ],
    "sg:phone":"+1 305 887 4947",
    "sg:postcode":"33010",
    "sg:province":"FL",
    "wof:name":"New Wash House",
    "wof:placetype":"venue"
},
  "geometry": {"coordinates":[-80.263937,25.830493],"type":"Point"}
}