{
  "type": "Feature",
  "properties": {
    "iso:country":"US",
    "sg:address":"9825 San Jose Blvd",
    "sg:city":"Jacksonville",
    "sg:classifiers":[
        {
            "category":"Restaurant",
            "type":"Food & Drink"
        }
    ],
    "sg:phone":"+1 904 260 7000",
    "sg:postcode":"32257",
    "sg:province":"FL",
    "sg:tags":[
        "eating"
    ],
    "wof:name":"San Jose Pizza Inc",
    "wof:placetype":"venue"
},
  "geometry": {"coordinates":[-81.61987999999999,30.199325],"type":"Point"}
}