{
  "type": "Feature",
  "properties": {
    "iso:country":"US",
    "sg:address":"5770 W Irlo Bronson Memorial Hwy",
    "sg:city":"Kissimmee",
    "sg:classifiers":[
        {
            "category":"Professional",
            "type":"Services"
        },
        {
            "category":"Shopping",
            "subcategory":"Jewelry",
            "type":"Retail Goods"
        }
    ],
    "sg:phone":"+1 407 397 9995",
    "sg:postcode":"34746",
    "sg:province":"FL",
    "sg:tags":[
        "jeweler"
    ],
    "wof:name":"International Gold Hut",
    "wof:placetype":"venue"
},
  "geometry": {"coordinates":[-81.516617,28.332642],"type":"Point"}
}