{
  "type": "Feature",
  "properties": {
    "iso:country":"US",
    "sg:address":"99900 Overseas Hwy",
    "sg:city":"Key Largo",
    "sg:classifiers":[
        {
            "category":"Real Estate",
            "subcategory":"Real Estate Operator",
            "type":"Services"
        }
    ],
    "sg:phone":"+1 305 451 4078",
    "sg:postcode":"33037",
    "sg:province":"FL",
    "sg:tags":[
        "building",
        "nonresidential"
    ],
    "wof:name":"Marr Properties South Inc",
    "wof:placetype":"venue"
},
  "geometry": {"coordinates":[-80.43568999999999,25.099083],"type":"Point"}
}