{
  "type": "Feature",
  "properties": {
    "addr:full":"1400 59th St W Bradenton FL 34209",
    "addr:housenumber":"1400",
    "addr:postcode":"34209",
    "addr:street":"59Th St W",
    "iso:country":"US",
    "sg:address":"1400 59th St W",
    "sg:city":"Bradenton",
    "sg:classifiers":[
        {
            "category":"Professional",
            "type":"Services"
        }
    ],
    "sg:phone":"+1 941 798 9045",
    "sg:postcode":"34209",
    "sg:province":"FL",
    "wof:name":"Baron Flyers Inc",
    "wof:placetype":"venue"
},
  "geometry": {"coordinates":[-82.620574,27.485069],"type":"Point"}
}