{
  "type": "Feature",
  "properties": {
    "addr:full":"5816 S Ridgewood Ave Daytona Beach FL 32127",
    "addr:housenumber":"5816",
    "addr:postcode":"32127",
    "addr:street":"S Ridgewood Ave",
    "iso:country":"US",
    "sg:address":"5816 S Ridgewood Ave",
    "sg:city":"Daytona Beach",
    "sg:classifiers":[
        {
            "category":"Autos & Motor Vehicles",
            "subcategory":"Automobile Sales",
            "type":"Retail Goods"
        },
        {
            "category":"Autos & Motor Vehicles",
            "subcategory":"Recreational Vehicle Sales",
            "type":"Retail Goods"
        }
    ],
    "sg:phone":"+1 386 761 4721",
    "sg:postcode":"32127",
    "sg:province":"FL",
    "sg:tags":[
        "cart"
    ],
    "wof:name":"Harbor Oaks Trading Post",
    "wof:placetype":"venue"
},
  "geometry": {"coordinates":[-80.97332400000001,29.109514],"type":"Point"}
}