{
  "type": "Feature",
  "properties": {
    "addr:full":"607 Coconut Cres Nokomis FL 34275",
    "addr:housenumber":"607",
    "addr:postcode":"34275",
    "addr:street":"Coconut Cres",
    "iso:country":"US",
    "sg:address":"607 Coconut Cres",
    "sg:city":"Nokomis",
    "sg:classifiers":[
        {
            "category":"Building & Trades",
            "subcategory":"Cleaning & Sanitation",
            "type":"Services"
        }
    ],
    "sg:phone":"+1 941 484 0728",
    "sg:postcode":"34275",
    "sg:province":"FL",
    "sg:tags":[
        "janitor",
        "cleaners-interior"
    ],
    "wof:name":"Tea Tree Cleaning Inc",
    "wof:placetype":"venue"
},
  "geometry": {"coordinates":[-82.46074,27.117205],"type":"Point"}
}