{
  "type": "Feature",
  "properties": {
    "iso:country":"US",
    "sg:address":"3044 Gulf Breeze Pkwy",
    "sg:city":"Gulf Breeze",
    "sg:classifiers":[
        {
            "category":"Building & Trades",
            "subcategory":"Equipment Rental",
            "type":"Services"
        }
    ],
    "sg:phone":"+1 850 934 1700",
    "sg:postcode":"32563",
    "sg:province":"FL",
    "sg:tags":[
        "tool"
    ],
    "wof:name":"Tool Shack",
    "wof:placetype":"venue"
},
  "geometry": {"coordinates":[-87.094731,30.385651],"type":"Point"}
}