{
  "type": "Feature",
  "properties": {
    "iso:country":"US",
    "sg:address":"334 Highlands Lake Dr",
    "sg:city":"Lake Placid",
    "sg:classifiers":[
        {
            "category":"Building & Trades",
            "subcategory":"Construction",
            "type":"Services"
        }
    ],
    "sg:phone":"+1 863 699 9348",
    "sg:postcode":"33852",
    "sg:province":"FL",
    "sg:tags":[
        "handyman"
    ],
    "wof:name":"Tom's Home/Office Repair Svc",
    "wof:placetype":"venue"
},
  "geometry": {"coordinates":[-81.31807000000001,27.306986],"type":"Point"}
}