{
  "type": "Feature",
  "properties": {
    "iso:country":"US",
    "sg:address":"1470 Kastner Pl",
    "sg:city":"Sanford",
    "sg:classifiers":[
        {
            "category":"Building & Trades",
            "subcategory":"Electrical",
            "type":"Services"
        },
        {
            "category":"Shopping",
            "type":"Retail Goods"
        }
    ],
    "sg:phone":"+1 407 328 9001",
    "sg:postcode":"32771",
    "sg:province":"FL",
    "sg:tags":[
        "supply",
        "telephone",
        "contractor",
        "equipment",
        "electrical",
        "merchandise"
    ],
    "sg:website":"www.integratedoffice.com",
    "wof:name":"Integrated Office Networks",
    "wof:placetype":"venue"
},
  "geometry": {"coordinates":[-81.327967,28.829713],"type":"Point"}
}