{
  "type": "Feature",
  "properties": {
    "addr:full":"2061 Tigertail Ave Miami FL 33133",
    "addr:housenumber":"2061",
    "addr:postcode":"33133",
    "addr:street":"Tigertail Ave",
    "iso:country":"US",
    "sg:address":"2061 Tigertail Ave",
    "sg:city":"Miami",
    "sg:classifiers":[
        {
            "category":"Real Estate",
            "subcategory":"Real Estate Agent",
            "type":"Services"
        }
    ],
    "sg:phone":"+1 305 856 2441",
    "sg:postcode":"33133",
    "sg:province":"FL",
    "wof:name":"Post Realty",
    "wof:placetype":"venue"
},
  "geometry": {"coordinates":[-80.227553,25.739339],"type":"Point"}
}