{
  "type": "Feature",
  "properties": {
    "addr:full":"97 Bickford Dr Palm Coast FL 32137",
    "addr:housenumber":"97",
    "addr:postcode":"32137",
    "addr:street":"Bickford Dr",
    "iso:country":"US",
    "sg:address":"97 Bickford Dr",
    "sg:city":"Palm Coast",
    "sg:classifiers":[
        {
            "category":"Building & Trades",
            "subcategory":"Construction",
            "type":"Services"
        }
    ],
    "sg:phone":"+1 386 447 1397",
    "sg:postcode":"32137",
    "sg:province":"FL",
    "sg:tags":[
        "house"
    ],
    "wof:name":"Sunshine Homes & Development I",
    "wof:placetype":"venue"
},
  "geometry": {"coordinates":[-81.25458999999999,29.59834],"type":"Point"}
}