{
  "type": "Feature",
  "properties": {
    "iso:country":"US",
    "sg:address":"4302 Alton Rd",
    "sg:city":"Miami Beach",
    "sg:classifiers":[
        {
            "category":"Health Services",
            "subcategory":"Doctor",
            "type":"Services"
        }
    ],
    "sg:phone":"+1 305 532 4224",
    "sg:postcode":"33140",
    "sg:province":"FL",
    "sg:tags":[
        "medical"
    ],
    "wof:name":"Marc E Umlas MD P A",
    "wof:placetype":"venue"
},
  "geometry": {"coordinates":[-80.13775,25.815364],"type":"Point"}
}