{
  "type": "Feature",
  "properties": {
    "addr:full":"12990 SW 3rd St Miami FL 33184",
    "addr:housenumber":"12990",
    "addr:postcode":"33184",
    "addr:street":"Sw 3Rd St",
    "iso:country":"US",
    "sg:address":"12990 SW 3rd St",
    "sg:city":"Miami",
    "sg:classifiers":[
        {
            "category":"Building & Trades",
            "subcategory":"Construction",
            "type":"Services"
        }
    ],
    "sg:phone":"+1 305 551 0721",
    "sg:postcode":"33184",
    "sg:province":"FL",
    "sg:tags":[
        "house"
    ],
    "wof:name":"Yan Construction Corp",
    "wof:placetype":"venue"
},
  "geometry": {"coordinates":[-80.405923,25.764083],"type":"Point"}
}