{
  "type": "Feature",
  "properties": {
    "addr:full":"10202 284th St E Myakka City FL 34251",
    "addr:housenumber":"10202",
    "addr:postcode":"34251",
    "addr:street":"284Th St E;City",
    "iso:country":"US",
    "sg:address":"10202 284th St E",
    "sg:city":"Myakka City",
    "sg:classifiers":[
        {
            "category":"Shopping",
            "subcategory":"Music",
            "type":"Retail Goods"
        }
    ],
    "sg:phone":"+1 941 322 2834",
    "sg:postcode":"34251",
    "sg:province":"FL",
    "wof:name":"Bottom Line Records",
    "wof:placetype":"venue"
},
  "geometry": {"coordinates":[-82.25104,27.351808],"type":"Point"}
}