{
  "type": "Feature",
  "properties": {
    "iso:country":"US",
    "sg:address":"20004 Panama City Beach Pkwy",
    "sg:city":"Panama City Bch",
    "sg:classifiers":[
        {
            "category":"Building & Trades",
            "subcategory":"Construction",
            "type":"Services"
        }
    ],
    "sg:phone":"+1 850 230 5957",
    "sg:postcode":"32413",
    "sg:province":"FL",
    "sg:tags":[
        "concrete",
        "contractor"
    ],
    "wof:name":"Concrete Advantage",
    "wof:placetype":"venue"
},
  "geometry": {"coordinates":[-85.91989100000001,30.24409],"type":"Point"}
}