{
  "type": "Feature",
  "properties": {
    "iso:country":"US",
    "sg:address":"1517 E Fowler Ave Ste G",
    "sg:city":"Tampa",
    "sg:classifiers":[
        {
            "category":"Personal",
            "type":"Services"
        },
        {
            "category":"Sports & Exercise",
            "subcategory":"Skate Park",
            "type":"Entertainment"
        }
    ],
    "sg:phone":"+1 813 866 8577",
    "sg:postcode":"33612",
    "sg:province":"FL",
    "sg:tags":[
        "party",
        "planning",
        "event",
        "magician"
    ],
    "wof:name":"The Magic Shop",
    "wof:placetype":"venue"
},
  "geometry": {"coordinates":[-82.440789,28.05439],"type":"Point"}
}