{
  "type": "Feature",
  "properties": {
    "iso:country":"US",
    "sg:address":"4479 N 9th Ave",
    "sg:city":"Pensacola",
    "sg:classifiers":[
        {
            "category":"Building & Trades",
            "subcategory":"Landscaping Services",
            "type":"Services"
        }
    ],
    "sg:phone":"+1 850 438 5400",
    "sg:postcode":"32503",
    "sg:province":"FL",
    "sg:tags":[
        "tree"
    ],
    "wof:name":"Zoe's Tree Svc",
    "wof:placetype":"venue"
},
  "geometry": {"coordinates":[-87.21430599999999,30.46356],"type":"Point"}
}