{
  "type": "Feature",
  "properties": {
    "addr:full":"4300 W Cypress St Tampa FL 33607",
    "addr:housenumber":"4300",
    "addr:postcode":"33607",
    "addr:street":"W Cypress St",
    "iso:country":"US",
    "sg:address":"4300 W Cypress St",
    "sg:city":"Tampa",
    "sg:classifiers":[
        {
            "category":"Banks & Credit Unions",
            "subcategory":"Bank",
            "type":"Services"
        }
    ],
    "sg:phone":"+1 813 876 6006",
    "sg:postcode":"33607",
    "sg:province":"FL",
    "sg:tags":[
        "cashing",
        "check"
    ],
    "wof:name":"ACE Cash Express",
    "wof:placetype":"venue"
},
  "geometry": {"coordinates":[-82.51799099999999,27.952229],"type":"Point"}
}