{
  "type": "Feature",
  "properties": {
    "iso:country":"US",
    "sg:address":"216 S Atlantic Ave",
    "sg:city":"Ormond Beach",
    "sg:classifiers":[
        {
            "category":"Real Estate",
            "subcategory":"Real Estate Agent",
            "type":"Services"
        }
    ],
    "sg:phone":"+1 386 673 9300",
    "sg:postcode":"32176",
    "sg:province":"FL",
    "wof:name":"Beninati Realty Inc",
    "wof:placetype":"venue"
},
  "geometry": {"coordinates":[-81.03790600000001,29.28735],"type":"Point"}
}