{
  "type": "Feature",
  "properties": {
    "iso:country":"US",
    "sg:address":"531 S US Hwy 1",
    "sg:city":"Fort Pierce",
    "sg:classifiers":[
        {
            "category":"Travel",
            "subcategory":"Hotels & Motels",
            "type":"Entertainment"
        }
    ],
    "sg:phone":"+1 772 464 3700",
    "sg:postcode":"34950",
    "sg:province":"FL",
    "wof:name":"Nowalk Motel & Apartments",
    "wof:placetype":"venue"
},
  "geometry": {"coordinates":[-80.325991,27.440816],"type":"Point"}
}