{
  "type": "Feature",
  "properties": {
    "iso:country":"US",
    "sg:address":"11125 NW 29th St",
    "sg:city":"Doral",
    "sg:classifiers":[
        {
            "category":"Freight",
            "type":"Transportation"
        }
    ],
    "sg:phone":"+1 305 468 3731",
    "sg:postcode":"33172",
    "sg:province":"FL",
    "sg:tags":[
        "mover"
    ],
    "wof:name":"Clover Systems Inc",
    "wof:placetype":"venue"
},
  "geometry": {"coordinates":[-80.37609500000001,25.800623],"type":"Point"}
}