{
  "type": "Feature",
  "properties": {
    "iso:country":"US",
    "sg:address":"610 Crooked Pine Ct",
    "sg:city":"Apopka",
    "sg:classifiers":[
        {
            "category":"Organizations",
            "subcategory":"Religious Organization",
            "type":"Services"
        }
    ],
    "sg:phone":"+1 407 886 9965",
    "sg:postcode":"32712",
    "sg:province":"FL",
    "wof:name":"Abundant Life Crusade",
    "wof:placetype":"venue"
},
  "geometry": {"coordinates":[-81.46879300000001,28.690158],"type":"Point"}
}