{
  "type": "Feature",
  "properties": {
    "iso:country":"US",
    "sg:address":"11110 SW 88th St",
    "sg:city":"Miami",
    "sg:classifiers":[
        {
            "category":"Professional",
            "subcategory":"Management & Consulting",
            "type":"Services"
        }
    ],
    "sg:phone":"+1 305 271 5577",
    "sg:postcode":"33176",
    "sg:province":"FL",
    "sg:tags":[
        "ind",
        "consultant",
        "construction",
        "general"
    ],
    "wof:name":"R L Pender & Associates",
    "wof:placetype":"venue"
},
  "geometry": {"coordinates":[-80.374329,25.686649],"type":"Point"}
}