{
  "type": "Feature",
  "properties": {
    "iso:country":"US",
    "sg:address":"875 SW 13th Ave",
    "sg:city":"Miami",
    "sg:classifiers":[
        {
            "category":"Building & Trades",
            "subcategory":"Construction",
            "type":"Services"
        }
    ],
    "sg:phone":"+1 305 859 9114",
    "sg:postcode":"33135",
    "sg:province":"FL",
    "sg:tags":[
        "hanging",
        "contractor"
    ],
    "wof:name":"Boquin Painting Corp",
    "wof:placetype":"venue"
},
  "geometry": {"coordinates":[-80.216357,25.764856],"type":"Point"}
}