{
  "type": "Feature",
  "properties": {
    "addr:full":"7102 Halifax Ct Tampa FL 33615",
    "addr:housenumber":"7102",
    "addr:postcode":"33615",
    "addr:street":"Halifax Ct",
    "iso:country":"US",
    "sg:address":"7102 Halifax Ct",
    "sg:city":"Tampa",
    "sg:classifiers":[
        {
            "category":"Social Services",
            "subcategory":"Child Care",
            "type":"Services"
        }
    ],
    "sg:phone":"+1 813 885 2500",
    "sg:postcode":"33615",
    "sg:province":"FL",
    "sg:tags":[
        "day"
    ],
    "wof:name":"Your Turn 2 Learn",
    "wof:placetype":"venue"
},
  "geometry": {"coordinates":[-82.57339899999999,28.014547],"type":"Point"}
}