{
  "type": "Feature",
  "properties": {
    "addr:full":"7000 Fontainebleau Cres Jacksonville FL 32211",
    "addr:housenumber":"7000",
    "addr:postcode":"32211",
    "addr:street":"Fontainebleau Cres",
    "iso:country":"US",
    "sg:address":"7000 Fontainebleau Cres",
    "sg:city":"Jacksonville",
    "sg:classifiers":[
        {
            "category":"Building & Trades",
            "subcategory":"Pest Control",
            "type":"Services"
        }
    ],
    "sg:phone":"+1 904 743 5446",
    "sg:postcode":"32211",
    "sg:province":"FL",
    "wof:name":"Five Star Pest Management",
    "wof:placetype":"venue"
},
  "geometry": {"coordinates":[-81.58263599999999,30.343961],"type":"Point"}
}