{
  "type": "Feature",
  "properties": {
    "addr:full":"6108 E Joyce Ln Inverness FL 34452",
    "addr:housenumber":"6108",
    "addr:postcode":"34452",
    "addr:street":"E Joyce Ln",
    "iso:country":"US",
    "sg:address":"6108 E Joyce Ln",
    "sg:city":"Inverness",
    "sg:classifiers":[
        {
            "category":"Building & Trades",
            "subcategory":"Construction",
            "type":"Services"
        }
    ],
    "sg:phone":"+1 352 726 5763",
    "sg:postcode":"34452",
    "sg:province":"FL",
    "sg:tags":[
        "house"
    ],
    "wof:name":"John Tortorici Aluminum Cnstr",
    "wof:placetype":"venue"
},
  "geometry": {"coordinates":[-82.33164600000001,28.803379],"type":"Point"}
}