{
  "type": "Feature",
  "properties": {
    "addr:full":"720 Honeycomb Ln Auburndale FL 33823",
    "addr:housenumber":"720",
    "addr:postcode":"33823",
    "addr:street":"Honeycomb Ln",
    "iso:country":"US",
    "sg:address":"720 Honeycomb Ln",
    "sg:city":"Auburndale",
    "sg:classifiers":[
        {
            "category":"Building & Trades",
            "subcategory":"Construction",
            "type":"Services"
        }
    ],
    "sg:phone":"+1 863 984 1430",
    "sg:postcode":"33823",
    "sg:province":"FL",
    "sg:tags":[
        "contractor"
    ],
    "wof:name":"C A Lundy & Co",
    "wof:placetype":"venue"
},
  "geometry": {"coordinates":[-81.814947,28.130363],"type":"Point"}
}