{
  "type": "Feature",
  "properties": {
    "iso:country":"US",
    "sg:address":"151 E Highbanks Rd",
    "sg:city":"De Bary",
    "sg:classifiers":[
        {
            "category":"Retail",
            "subcategory":"Animal Services",
            "type":"Services"
        }
    ],
    "sg:phone":"+1 386 668 2275",
    "sg:postcode":"32713",
    "sg:province":"FL",
    "sg:tags":[
        "breeder",
        "border",
        "terrier"
    ],
    "wof:name":"Teri D Beverly",
    "wof:placetype":"venue"
},
  "geometry": {"coordinates":[-81.29866199999999,28.890162],"type":"Point"}
}