{
  "type": "Feature",
  "properties": {
    "iso:country":"US",
    "sg:address":"8209 Atlantic Blvd",
    "sg:city":"Jacksonville",
    "sg:classifiers":[
        {
            "category":"Autos & Motor Vehicles",
            "subcategory":"Motorcycle Sales",
            "type":"Retail Goods"
        }
    ],
    "sg:phone":"+1 904 721 2453",
    "sg:postcode":"32211",
    "sg:province":"FL",
    "sg:tags":[
        "repair",
        "scooter",
        "used",
        "new"
    ],
    "wof:name":"Honda of Jacksonville",
    "wof:placetype":"venue"
},
  "geometry": {"coordinates":[-81.57009499999999,30.31401],"type":"Point"}
}