{
  "type": "Feature",
  "properties": {
    "iso:country":"US",
    "sg:address":"208 Towne Center Cir",
    "sg:city":"Sanford",
    "sg:classifiers":[
        {
            "category":"Shopping",
            "subcategory":"Gifts & Souvenirs",
            "type":"Retail Goods"
        }
    ],
    "sg:phone":"+1 407 323 7600",
    "sg:postcode":"32771",
    "sg:province":"FL",
    "sg:tags":[
        "shop"
    ],
    "wof:name":"Best Of As Seen On TV",
    "wof:placetype":"venue"
},
  "geometry": {"coordinates":[-81.33691,28.808748],"type":"Point"}
}