{
  "type": "Feature",
  "properties": {
    "addr:full":"8547 San Jose Blvd Jacksonville FL 32217",
    "addr:housenumber":"8547",
    "addr:postcode":"32217",
    "addr:street":"San Jose Blvd",
    "iso:country":"US",
    "sg:address":"8547 San Jose Blvd",
    "sg:city":"Jacksonville",
    "sg:classifiers":[
        {
            "category":"Professional",
            "subcategory":"Advertising",
            "type":"Services"
        }
    ],
    "sg:phone":"+1 904 739 8014",
    "sg:postcode":"32217",
    "sg:province":"FL",
    "sg:tags":[
        "counselor"
    ],
    "wof:name":"Zag Advertising",
    "wof:placetype":"venue"
},
  "geometry": {"coordinates":[-81.615662,30.224283],"type":"Point"}
}