{
  "type": "Feature",
  "properties": {
    "addr:full":"4708 Parkway Commerce Blvd Orlando FL 32808",
    "addr:housenumber":"4708",
    "addr:postcode":"32808",
    "addr:street":"Parkway Commerce Blvd",
    "iso:country":"US",
    "sg:address":"4708 Parkway Commerce Blvd",
    "sg:city":"Orlando",
    "sg:classifiers":[
        {
            "category":"Building & Trades",
            "subcategory":"Plumbing",
            "type":"Services"
        }
    ],
    "sg:phone":"+1 407 299 3430",
    "sg:postcode":"32808",
    "sg:province":"FL",
    "sg:tags":[
        "product",
        "safety"
    ],
    "wof:name":"Grinnell Fire Protection",
    "wof:placetype":"venue"
},
  "geometry": {"coordinates":[-81.41995,28.598448],"type":"Point"}
}