{
  "type": "Feature",
  "properties": {
    "iso:country":"US",
    "sg:address":"2229 14th St W",
    "sg:city":"Bradenton",
    "sg:classifiers":[
        {
            "category":"Home & Garden",
            "subcategory":"Building Materials",
            "type":"Retail Goods"
        },
        {
            "category":"Building & Trades",
            "subcategory":"Construction",
            "type":"Services"
        }
    ],
    "sg:phone":"+1 941 748 2164",
    "sg:postcode":"34205",
    "sg:province":"FL",
    "sg:tags":[
        "windows",
        "glass",
        "contractor"
    ],
    "wof:name":"H B Windows",
    "wof:placetype":"venue"
},
  "geometry": {"coordinates":[-82.575277,27.479249],"type":"Point"}
}