{
  "type": "Feature",
  "properties": {
    "addr:full":"216 W 17th St Hialeah FL 33010",
    "addr:housenumber":"216",
    "addr:postcode":"33010",
    "addr:street":"W 17Th St",
    "iso:country":"US",
    "sg:address":"216 W 17th St",
    "sg:city":"Hialeah",
    "sg:classifiers":[
        {
            "category":"Food & Beverages",
            "subcategory":"Meat & Fish",
            "type":"Retail Goods"
        }
    ],
    "sg:phone":"+1 305 805 4118",
    "sg:postcode":"33010",
    "sg:province":"FL",
    "sg:tags":[
        "seafood"
    ],
    "wof:name":"Michael Smith",
    "wof:placetype":"venue"
},
  "geometry": {"coordinates":[-80.286688,25.836951],"type":"Point"}
}