{
  "type": "Feature",
  "properties": {
    "iso:country":"US",
    "sg:address":"2600 Old Moultrie Rd",
    "sg:city":"St Augustine",
    "sg:classifiers":[
        {
            "category":"Real Estate",
            "subcategory":"Developer",
            "type":"Services"
        }
    ],
    "sg:phone":"+1 904 797 4990",
    "sg:postcode":"32086",
    "sg:province":"FL",
    "sg:tags":[
        "cemetery"
    ],
    "wof:name":"St Augustine Memorial Park",
    "wof:placetype":"venue"
},
  "geometry": {"coordinates":[-81.326807,29.848334],"type":"Point"}
}