{
  "type": "Feature",
  "properties": {
    "iso:country":"US",
    "sg:address":"6450 Hoffner Ave",
    "sg:city":"Orlando",
    "sg:classifiers":[
        {
            "category":"Retail",
            "subcategory":"Auto Repair",
            "type":"Services"
        }
    ],
    "sg:phone":"+1 407 277 6639",
    "sg:postcode":"32822",
    "sg:province":"FL",
    "sg:tags":[
        "body",
        "shop",
        "painting",
        "automobile",
        "paint"
    ],
    "wof:name":"Courtesy Collision Ctr",
    "wof:placetype":"venue"
},
  "geometry": {"coordinates":[-81.29430000000001,28.480616],"type":"Point"}
}