{
  "type": "Feature",
  "properties": {
    "addr:full":"14221 NE 47th Ave Anthony FL 32113",
    "addr:housenumber":"14221",
    "addr:postcode":"32113",
    "addr:street":"Ne 47Th Ave",
    "iso:country":"US",
    "sg:address":"14221 NE 47th Ave",
    "sg:city":"Anthony",
    "sg:classifiers":[
        {
            "category":"Wholesale",
            "subcategory":"Furniture",
            "type":"Manufacturing & Wholesale Goods"
        }
    ],
    "sg:phone":"+1 352 595 5637",
    "sg:postcode":"32113",
    "sg:province":"FL",
    "wof:name":"Allstate Electropainting",
    "wof:placetype":"venue"
},
  "geometry": {"coordinates":[-82.071905,29.35539],"type":"Point"}
}