{
  "type": "Feature",
  "properties": {
    "addr:full":"8010 Grand Blvd Port Richey FL 34668",
    "addr:housenumber":"8010",
    "addr:postcode":"34668",
    "addr:street":"Grand Blvd",
    "iso:country":"US",
    "sg:address":"8010 Grand Blvd",
    "sg:city":"Port Richey",
    "sg:classifiers":[
        {
            "category":"Home & Garden",
            "subcategory":"Household Appliances",
            "type":"Retail Goods"
        }
    ],
    "sg:phone":"+1 727 841 8474",
    "sg:postcode":"34668",
    "sg:province":"FL",
    "sg:website":"www.famoustate.com",
    "wof:name":"Famous Tate Appliance Ctr",
    "wof:placetype":"venue"
},
  "geometry": {"coordinates":[-82.721884,28.273511],"type":"Point"}
}