{
  "type": "Feature",
  "properties": {
    "iso:country":"US",
    "sg:address":"6801 14th St W",
    "sg:city":"Bradenton",
    "sg:classifiers":[
        {
            "category":"Shopping",
            "subcategory":"Gifts & Souvenirs",
            "type":"Retail Goods"
        },
        {
            "category":"Banks & Credit Unions",
            "subcategory":"Bank",
            "type":"Services"
        },
        {
            "category":"Shopping",
            "subcategory":"Antiques",
            "type":"Retail Goods"
        },
        {
            "category":"Shopping",
            "subcategory":"Used Merchandise",
            "type":"Retail Goods"
        }
    ],
    "sg:phone":"+1 941 751 2026",
    "sg:postcode":"34207",
    "sg:province":"FL",
    "sg:tags":[
        "shop",
        "resale",
        "second",
        "hand"
    ],
    "wof:name":"Lavender Unique Collectibles",
    "wof:placetype":"venue"
},
  "geometry": {"coordinates":[-82.575531,27.42024],"type":"Point"}
}