{
  "type": "Feature",
  "properties": {
    "iso:country":"US",
    "sg:address":"1852 Tinsmith Cir",
    "sg:city":"Lutz",
    "sg:classifiers":[
        {
            "category":"Social Services",
            "subcategory":"Child Care",
            "type":"Services"
        }
    ],
    "sg:phone":"+1 813 948 0676",
    "sg:postcode":"33559",
    "sg:province":"FL",
    "sg:tags":[
        "day"
    ],
    "wof:name":"Gary Gwinn Land Care",
    "wof:placetype":"venue"
},
  "geometry": {"coordinates":[-82.407014,28.184067],"type":"Point"}
}