{
  "type": "Feature",
  "properties": {
    "iso:country":"US",
    "sg:address":"1838 S Ridge Dr",
    "sg:city":"Valrico",
    "sg:classifiers":[
        {
            "category":"Professional",
            "subcategory":"Research",
            "type":"Services"
        }
    ],
    "sg:phone":"+1 813 299 1108",
    "sg:postcode":"33594",
    "sg:province":"FL",
    "sg:tags":[
        "environmental",
        "ecological"
    ],
    "wof:name":"Hydrologic Data Collection",
    "wof:placetype":"venue"
},
  "geometry": {"coordinates":[-82.224042,27.913962],"type":"Point"}
}