{
  "type": "Feature",
  "properties": {
    "addr:full":"2210 SE 15th St Ocala FL 34471",
    "addr:housenumber":"2210",
    "addr:postcode":"34471",
    "addr:street":"Se 15Th St",
    "iso:country":"US",
    "sg:address":"2210 SE 15th St",
    "sg:city":"Ocala",
    "sg:classifiers":[
        {
            "category":"Banks & Credit Unions",
            "subcategory":"Financial Services",
            "type":"Services"
        }
    ],
    "sg:phone":"+1 352 732 7526",
    "sg:postcode":"34471",
    "sg:province":"FL",
    "sg:tags":[
        "company",
        "holding"
    ],
    "wof:name":"Stadium Park Inc A Florid",
    "wof:placetype":"venue"
},
  "geometry": {"coordinates":[-82.108678,29.173208],"type":"Point"}
}