{
  "type": "Feature",
  "properties": {
    "iso:country":"US",
    "sg:address":"6303 E Martin Luther King Jr Blvd",
    "sg:city":"Tampa",
    "sg:classifiers":[
        {
            "category":"Professional",
            "subcategory":"Accounting & Tax Preparation",
            "type":"Services"
        },
        {
            "category":"Health Services",
            "subcategory":"Medical Lab",
            "type":"Services"
        }
    ],
    "sg:phone":"+1 813 740 8383",
    "sg:postcode":"33619",
    "sg:province":"FL",
    "sg:tags":[
        "laboratory",
        "billing"
    ],
    "wof:name":"Quest Diagnostics Inc",
    "wof:placetype":"venue"
},
  "geometry": {"coordinates":[-82.386595,27.981441],"type":"Point"}
}