{
  "type": "Feature",
  "properties": {
    "addr:full":"515 Delannoy Ave Ste 1046 Cocoa FL 32922",
    "addr:housenumber":"515",
    "addr:postcode":"32922",
    "addr:street":"Delannoy Ave Ste 1046",
    "iso:country":"US",
    "sg:address":"515 Delannoy Ave Ste 1046",
    "sg:city":"Cocoa",
    "sg:classifiers":[
        {
            "category":"Personal",
            "subcategory":"Beauty Salon",
            "type":"Services"
        }
    ],
    "sg:phone":"+1 321 632 0783",
    "sg:postcode":"32922",
    "sg:province":"FL",
    "wof:name":"Styles By Sue And Terry",
    "wof:placetype":"venue"
},
  "geometry": {"coordinates":[-80.725313,28.352731],"type":"Point"}
}