{
  "type": "Feature",
  "properties": {
    "addr:full":"14731 N Florida Ave Tampa FL 33613",
    "addr:housenumber":"14731",
    "addr:postcode":"33613",
    "addr:street":"N Florida Ave",
    "iso:country":"US",
    "sg:address":"14731 N Florida Ave",
    "sg:city":"Tampa",
    "sg:classifiers":[
        {
            "category":"Bars & Pubs",
            "type":"Food & Drink"
        }
    ],
    "sg:phone":"+1 813 969 4077",
    "sg:postcode":"33613",
    "sg:province":"FL",
    "sg:tags":[
        "drinking"
    ],
    "wof:name":"Class Act Showbar",
    "wof:placetype":"venue"
},
  "geometry": {"coordinates":[-82.459467,28.081787],"type":"Point"}
}