{
  "type": "Feature",
  "properties": {
    "addr:full":"60 Spring Vista Dr Debary FL 32713",
    "addr:housenumber":"60",
    "addr:postcode":"32713",
    "addr:street":"Spring Vista Dr",
    "iso:country":"US",
    "sg:address":"60 Spring Vista Dr",
    "sg:city":"Debary",
    "sg:classifiers":[
        {
            "category":"Insurance",
            "subcategory":"Insurance Agent",
            "type":"Services"
        }
    ],
    "sg:phone":"+1 386 860 1777",
    "sg:postcode":"32713",
    "sg:province":"FL",
    "wof:name":"Allstate Insurance",
    "wof:placetype":"venue"
},
  "geometry": {"coordinates":[-81.31797299999999,28.870392],"type":"Point"}
}