{
  "type": "Feature",
  "properties": {
    "addr:full":"3950 NW 26th St Miami FL 33142",
    "addr:housenumber":"3950",
    "addr:postcode":"33142",
    "addr:street":"Nw 26Th St",
    "iso:country":"US",
    "sg:address":"3950 NW 26th St",
    "sg:city":"Miami",
    "sg:classifiers":[
        {
            "category":"Autos & Motor Vehicles",
            "subcategory":"Automobile Sales",
            "type":"Retail Goods"
        }
    ],
    "sg:phone":"+1 954 565 2644",
    "sg:postcode":"33142",
    "sg:province":"FL",
    "sg:tags":[
        "limo"
    ],
    "wof:name":"Absolute Limousine",
    "wof:placetype":"venue"
},
  "geometry": {"coordinates":[-80.261599,25.799441],"type":"Point"}
}