{
  "type": "Feature",
  "properties": {
    "iso:country":"US",
    "sg:address":"5060 15th Ave S",
    "sg:city":"Gulfport",
    "sg:classifiers":[
        {
            "category":"Retail",
            "subcategory":"Auto Repair",
            "type":"Services"
        }
    ],
    "sg:phone":"+1 727 323 8004",
    "sg:postcode":"33707",
    "sg:province":"FL",
    "sg:tags":[
        "repairing",
        "automobile"
    ],
    "wof:name":"Charles Auto Repair",
    "wof:placetype":"venue"
},
  "geometry": {"coordinates":[-82.700244,27.755527],"type":"Point"}
}