{
  "type": "Feature",
  "properties": {
    "iso:country":"US",
    "sg:address":"3109 Birmingham Dr",
    "sg:city":"Navarre",
    "sg:classifiers":[
        {
            "category":"Building & Trades",
            "subcategory":"Construction",
            "type":"Services"
        }
    ],
    "sg:phone":"+1 850 936 5878",
    "sg:postcode":"32566",
    "sg:province":"FL",
    "sg:tags":[
        "contractor"
    ],
    "wof:name":"Terry Forsell Construction",
    "wof:placetype":"venue"
},
  "geometry": {"coordinates":[-86.868554,30.447577],"type":"Point"}
}