{
  "type": "Feature",
  "properties": {
    "iso:country":"US",
    "sg:address":"4801 78th Ave",
    "sg:city":"Pinellas Park",
    "sg:classifiers":[
        {
            "category":"Health Services",
            "subcategory":"Hospital",
            "type":"Services"
        }
    ],
    "sg:phone":"+1 727 521 2426",
    "sg:postcode":"33781",
    "sg:province":"FL",
    "sg:tags":[
        "mental"
    ],
    "wof:name":"Vincent House",
    "wof:placetype":"venue"
},
  "geometry": {"coordinates":[-82.699111,27.842933],"type":"Point"}
}