{
  "type": "Feature",
  "properties": {
    "addr:full":"20236 Sparkman Ln Groveland FL 34736",
    "addr:postcode":"20236;34736",
    "addr:street":"Sparkman Ln",
    "iso:country":"US",
    "sg:address":"20236 Sparkman Ln",
    "sg:city":"Groveland",
    "sg:classifiers":[
        {
            "category":"Building & Trades",
            "subcategory":"Construction",
            "type":"Services"
        }
    ],
    "sg:phone":"+1 352 429 8882",
    "sg:postcode":"34736",
    "sg:province":"FL",
    "sg:tags":[
        "house"
    ],
    "wof:name":"Rmi For Homes",
    "wof:placetype":"venue"
},
  "geometry": {"coordinates":[-81.890996,28.64176],"type":"Point"}
}