{
  "type": "Feature",
  "properties": {
    "iso:country":"US",
    "sg:address":"10895 Rocket Blvd",
    "sg:city":"Orlando",
    "sg:classifiers":[
        {
            "category":"Building & Trades",
            "subcategory":"Construction",
            "type":"Services"
        }
    ],
    "sg:phone":"+1 407 859 1119",
    "sg:postcode":"32824",
    "sg:province":"FL",
    "sg:tags":[
        "contractor"
    ],
    "wof:name":"Rutland Guttering Inc",
    "wof:placetype":"venue"
},
  "geometry": {"coordinates":[-81.39071,28.409056],"type":"Point"}
}