{
  "type": "Feature",
  "properties": {
    "iso:country":"US",
    "sg:address":"13820 NW 140th St",
    "sg:city":"Alachua",
    "sg:classifiers":[
        {
            "category":"Manufacturing",
            "subcategory":"Food",
            "type":"Manufacturing & Wholesale Goods"
        },
        {
            "category":"Food & Beverages",
            "subcategory":"Groceries & Convenience Stores",
            "type":"Retail Goods"
        }
    ],
    "sg:phone":"+1 386 462 7577",
    "sg:postcode":"32615",
    "sg:province":"FL",
    "sg:tags":[
        "product"
    ],
    "sg:website":"http://www.scaffs.com",
    "wof:name":"S & S Food Store 40",
    "wof:placetype":"venue"
},
  "geometry": {"coordinates":[-82.494193,29.781751],"type":"Point"}
}