{
  "type": "Feature",
  "properties": {
    "addr:full":"9772 Gardens East Dr Palm Beach Gdns FL 33410",
    "addr:housenumber":"9772",
    "addr:postcode":"33410",
    "addr:street":"Gardens East Dr Palm",
    "iso:country":"US",
    "sg:address":"9772 Gardens East Dr",
    "sg:city":"Palm Beach Gdns",
    "sg:classifiers":[
        {
            "category":"Retail",
            "subcategory":"Repair Shop",
            "type":"Services"
        }
    ],
    "sg:phone":"+1 561 953 5178",
    "sg:postcode":"33410",
    "sg:province":"FL",
    "sg:tags":[
        "lock",
        "locksmith"
    ],
    "wof:name":"A 24 7 Emergency Locksmith",
    "wof:placetype":"venue"
},
  "geometry": {"coordinates":[-80.08703199999999,26.826355],"type":"Point"}
}