{
  "type": "Feature",
  "properties": {
    "addr:full":"7700 Hilburn Rd Pensacola FL 32514",
    "addr:housenumber":"7700",
    "addr:postcode":"32514",
    "addr:street":"Hilburn Rd",
    "iso:country":"US",
    "sg:address":"7700 Hilburn Rd",
    "sg:city":"Pensacola",
    "sg:classifiers":[
        {
            "category":"Building & Trades",
            "subcategory":"Construction",
            "type":"Services"
        }
    ],
    "sg:phone":"+1 850 477 6041",
    "sg:postcode":"32514",
    "sg:province":"FL",
    "sg:tags":[
        "painter"
    ],
    "wof:name":"David Brown Coatings",
    "wof:placetype":"venue"
},
  "geometry": {"coordinates":[-87.23066900000001,30.510737],"type":"Point"}
}