{
  "type": "Feature",
  "properties": {
    "addr:full":"2831 Vistamar St Fort Lauderdale FL 33304",
    "addr:housenumber":"2831",
    "addr:postcode":"33304",
    "addr:street":"Vistamar St",
    "iso:country":"US",
    "sg:address":"2831 Vistamar St",
    "sg:city":"Fort Lauderdale",
    "sg:classifiers":[
        {
            "category":"Travel",
            "subcategory":"Hotels & Motels",
            "type":"Entertainment"
        }
    ],
    "sg:phone":"+1 954 565 6911",
    "sg:postcode":"33304",
    "sg:province":"FL",
    "sg:tags":[
        "operation"
    ],
    "wof:name":"Brigantine Hotel",
    "wof:placetype":"venue"
},
  "geometry": {"coordinates":[-80.106859,26.13355],"type":"Point"}
}