{
  "type": "Feature",
  "properties": {
    "iso:country":"US",
    "sg:address":"2660 S Ocean Blvd",
    "sg:city":"Palm Beach",
    "sg:classifiers":[
        {
            "category":"Real Estate",
            "subcategory":"Real Estate Operator",
            "type":"Services"
        },
        {
            "category":"Organizations",
            "subcategory":"Community Association",
            "type":"Services"
        }
    ],
    "sg:phone":"+1 561 586 2648",
    "sg:postcode":"33480",
    "sg:province":"FL",
    "sg:tags":[
        "condominium"
    ],
    "wof:name":"Beach Point Condominium",
    "wof:placetype":"venue"
},
  "geometry": {"coordinates":[-80.038714,26.624879],"type":"Point"}
}