{
  "type": "Feature",
  "properties": {
    "iso:country":"US",
    "sg:address":"3698 18th Ave S",
    "sg:city":"St Petersburg",
    "sg:classifiers":[
        {
            "category":"Food & Beverages",
            "subcategory":"Groceries & Convenience Stores",
            "type":"Retail Goods"
        }
    ],
    "sg:phone":"+1 727 327 6364",
    "sg:postcode":"33711",
    "sg:province":"FL",
    "sg:tags":[
        "grocer"
    ],
    "wof:name":"C & J Grocery",
    "wof:placetype":"venue"
},
  "geometry": {"coordinates":[-82.681488,27.75196],"type":"Point"}
}