{
  "type": "Feature",
  "properties": {
    "iso:country":"US",
    "sg:address":"7425 NW 54th St",
    "sg:city":"Miami",
    "sg:classifiers":[
        {
            "category":"Autos & Motor Vehicles",
            "subcategory":"Automobile Sales",
            "type":"Retail Goods"
        }
    ],
    "sg:phone":"+1 305 436 9831",
    "sg:postcode":"33166",
    "sg:province":"FL",
    "sg:tags":[
        "car",
        "dealer"
    ],
    "wof:name":"Cars R Us Wholesales",
    "wof:placetype":"venue"
},
  "geometry": {"coordinates":[-80.31920700000001,25.822645],"type":"Point"}
}