{
  "type": "Feature",
  "properties": {
    "addr:full":"1647 SW 27th Ave Miami FL 33145",
    "addr:housenumber":"1647",
    "addr:postcode":"33145",
    "addr:street":"Sw 27Th Ave",
    "iso:country":"US",
    "sg:address":"1647 SW 27th Ave",
    "sg:city":"Miami",
    "sg:classifiers":[
        {
            "category":"Social Services",
            "type":"Services"
        }
    ],
    "sg:phone":"+1 305 646 0135",
    "sg:postcode":"33145",
    "sg:province":"FL",
    "wof:name":"Saint Jude Community Mental",
    "wof:placetype":"venue"
},
  "geometry": {"coordinates":[-80.238479,25.757738],"type":"Point"}
}