{
  "type": "Feature",
  "properties": {
    "addr:full":"24285 S Dixie Hwy Homestead FL 33032",
    "addr:housenumber":"24285",
    "addr:postcode":"33032",
    "addr:street":"S Dixie Hwy",
    "iso:country":"US",
    "sg:address":"24285 S Dixie Hwy",
    "sg:city":"Homestead",
    "sg:classifiers":[
        {
            "category":"Autos & Motor Vehicles",
            "subcategory":"Automobile Sales",
            "type":"Retail Goods"
        }
    ],
    "sg:phone":"+1 305 258 0624",
    "sg:postcode":"33032",
    "sg:province":"FL",
    "sg:tags":[
        "dealers-used",
        "used",
        "cars-wholesale",
        "car"
    ],
    "wof:name":"Family Motor Sales Corp",
    "wof:placetype":"venue"
},
  "geometry": {"coordinates":[-80.40670900000001,25.540758],"type":"Point"}
}