{
  "type": "Feature",
  "properties": {
    "iso:country":"US",
    "sg:address":"427 Lark Ln",
    "sg:city":"Kissimmee",
    "sg:classifiers":[
        {
            "category":"Building & Trades",
            "subcategory":"Construction",
            "type":"Services"
        }
    ],
    "sg:phone":"+1 863 427 2384",
    "sg:postcode":"34759",
    "sg:province":"FL",
    "sg:tags":[
        "carpentry",
        "contractor"
    ],
    "wof:name":"Complete Framing Corp",
    "wof:placetype":"venue"
},
  "geometry": {"coordinates":[-81.470613,28.09785],"type":"Point"}
}