{
  "type": "Feature",
  "properties": {
    "iso:country":"US",
    "sg:address":"5450 8th St SW",
    "sg:city":"Coral Gables",
    "sg:classifiers":[
        {
            "category":"Health Services",
            "subcategory":"Doctor",
            "type":"Services"
        }
    ],
    "sg:phone":"+1 305 444 3453",
    "sg:postcode":"33134",
    "sg:province":"FL",
    "sg:tags":[
        "physician",
        "surgeon"
    ],
    "wof:name":"Ferran & Ferran",
    "wof:placetype":"venue"
},
  "geometry": {"coordinates":[-80.283462,25.763646],"type":"Point"}
}