{
  "type": "Feature",
  "properties": {
    "addr:full":"4206 Cascade Falls Dr Sarasota FL 34243",
    "addr:housenumber":"4206",
    "addr:postcode":"34243",
    "addr:street":"Cascade Falls Dr",
    "iso:country":"US",
    "sg:address":"4206 Cascade Falls Dr",
    "sg:city":"Sarasota",
    "sg:classifiers":[
        {
            "category":"Building & Trades",
            "subcategory":"Construction",
            "type":"Services"
        }
    ],
    "sg:phone":"+1 941 358 8823",
    "sg:postcode":"34243",
    "sg:province":"FL",
    "sg:tags":[
        "home",
        "improvement"
    ],
    "wof:name":"Bill Lezotte Home Repair Spec",
    "wof:placetype":"venue"
},
  "geometry": {"coordinates":[-82.512019,27.393193],"type":"Point"}
}