{
  "type": "Feature",
  "properties": {
    "addr:full":"457 W Dearborn St Englewood FL 34223",
    "addr:housenumber":"457",
    "addr:postcode":"34223",
    "addr:street":"W Dearborn St",
    "iso:country":"US",
    "sg:address":"457 W Dearborn St",
    "sg:city":"Englewood",
    "sg:classifiers":[
        {
            "category":"Home & Garden",
            "subcategory":"Home Furnishings",
            "type":"Retail Goods"
        },
        {
            "category":"Professional",
            "subcategory":"Art Services",
            "type":"Services"
        },
        {
            "category":"Home & Garden",
            "subcategory":"Furniture",
            "type":"Retail Goods"
        }
    ],
    "sg:phone":"+1 941 474 0007",
    "sg:postcode":"34223",
    "sg:province":"FL",
    "sg:tags":[
        "draperies",
        "designer",
        "window",
        "treatment",
        "interior",
        "curtain",
        "decorator",
        "store"
    ],
    "sg:website":"http://www.deborahinteriorsfl.com",
    "wof:name":"Deborah's Interiors Inc",
    "wof:placetype":"venue"
},
  "geometry": {"coordinates":[-82.36221999999999,26.962227],"type":"Point"}
}