{
  "type": "Feature",
  "properties": {
    "iso:country":"US",
    "sg:address":"1050 Beachland Blvd",
    "sg:city":"Vero Beach",
    "sg:classifiers":[
        {
            "category":"Restaurant",
            "type":"Food & Drink"
        }
    ],
    "sg:menulink":"http://www.allmenus.com/fl/vero-beach/39325-the-ocean-grill/menu/",
    "sg:phone":"+1 772 231 5409",
    "sg:postcode":"32963",
    "sg:province":"FL",
    "sg:tags":[
        "seafood",
        "american"
    ],
    "wof:name":"The Ocean Grill",
    "wof:placetype":"venue"
},
  "geometry": {"coordinates":[-80.35623099999999,27.653352],"type":"Point"}
}