{
  "type": "Feature",
  "properties": {
    "addr:full":"609 W Lumsden Rd Brandon FL 33511",
    "addr:housenumber":"609",
    "addr:postcode":"33511",
    "addr:street":"W Lumsden Rd",
    "iso:country":"US",
    "sg:address":"609 W Lumsden Rd",
    "sg:city":"Brandon",
    "sg:classifiers":[
        {
            "category":"Building & Trades",
            "subcategory":"Construction",
            "type":"Services"
        }
    ],
    "sg:phone":"+1 813 571 7900",
    "sg:postcode":"33511",
    "sg:province":"FL",
    "sg:tags":[
        "house"
    ],
    "wof:name":"Weather Guard Construction",
    "wof:placetype":"venue"
},
  "geometry": {"coordinates":[-82.293367,27.923229],"type":"Point"}
}