{
  "type": "Feature",
  "properties": {
    "addr:full":"2231 W 80th St Ste 4 Hialeah FL 33016",
    "addr:housenumber":"2231",
    "addr:postcode":"33016",
    "addr:street":"W 80Th St Ste 4",
    "iso:country":"US",
    "sg:address":"2231 W 80th St Ste 4",
    "sg:city":"Hialeah",
    "sg:classifiers":[
        {
            "category":"Manufacturing",
            "subcategory":"Glass & Minerals",
            "type":"Manufacturing & Wholesale Goods"
        }
    ],
    "sg:phone":"+1 305 593 1115",
    "sg:postcode":"33016",
    "sg:province":"FL",
    "sg:tags":[
        "glass-stained",
        "stained",
        "leaded-commercial",
        "leaded",
        "glass-wholesale",
        "manufacturer"
    ],
    "wof:name":"Augusto Paz & Sons Corp",
    "wof:placetype":"venue"
},
  "geometry": {"coordinates":[-80.328739,25.895149],"type":"Point"}
}