{
  "type": "Feature",
  "properties": {
    "iso:country":"US",
    "sg:address":"1085 Business Ln",
    "sg:city":"Naples",
    "sg:classifiers":[
        {
            "category":"Banks & Credit Unions",
            "subcategory":"Investment Brokerage",
            "type":"Services"
        }
    ],
    "sg:phone":"+1 239 594 6852",
    "sg:postcode":"34110",
    "sg:province":"FL",
    "sg:tags":[
        "consultant",
        "planning",
        "financial"
    ],
    "wof:name":"Kathleen Schrage",
    "wof:placetype":"venue"
},
  "geometry": {"coordinates":[-81.792796,26.302892],"type":"Point"}
}