{
  "type": "Feature",
  "properties": {
    "addr:full":"801 NW 87th St Miami FL 33150",
    "addr:housenumber":"801",
    "addr:postcode":"33150",
    "addr:street":"Nw 87Th St",
    "iso:country":"US",
    "sg:address":"801 NW 87th St",
    "sg:city":"Miami",
    "sg:classifiers":[
        {
            "category":"Building & Trades",
            "subcategory":"Locksmith",
            "type":"Services"
        }
    ],
    "sg:phone":"+1 305 908 5719",
    "sg:postcode":"33150",
    "sg:province":"FL",
    "sg:tags":[
        "key"
    ],
    "wof:name":"Any 24 Hour Emerg Locksmith",
    "wof:placetype":"venue"
},
  "geometry": {"coordinates":[-80.21252800000001,25.854563],"type":"Point"}
}