{
  "type": "Feature",
  "properties": {
    "addr:full":"1109 W Orange Ave Tallahassee FL 32310",
    "addr:housenumber":"1109",
    "addr:postcode":"32310",
    "addr:street":"W Orange Ave",
    "iso:country":"US",
    "sg:address":"1109 W Orange Ave",
    "sg:city":"Tallahassee",
    "sg:classifiers":[
        {
            "category":"Retail",
            "subcategory":"Auto Rental",
            "type":"Services"
        }
    ],
    "sg:phone":"+1 850 580 5970",
    "sg:postcode":"32310",
    "sg:province":"FL",
    "sg:tags":[
        "renting",
        "truck",
        "leasing"
    ],
    "wof:name":"U-Haul Co",
    "wof:placetype":"venue"
},
  "geometry": {"coordinates":[-84.30476400000001,30.412603],"type":"Point"}
}