{
  "type": "Feature",
  "properties": {
    "addr:full":"9261 Southampton Pl Boca Raton FL 33434",
    "addr:housenumber":"9261",
    "addr:postcode":"33434",
    "addr:street":"Southampton Pl",
    "iso:country":"US",
    "sg:address":"9261 Southampton Pl",
    "sg:city":"Boca Raton",
    "sg:classifiers":[
        {
            "category":"Personal",
            "type":"Services"
        }
    ],
    "sg:phone":"+1 561 479 0542",
    "sg:postcode":"33434",
    "sg:province":"FL",
    "sg:tags":[
        "miscellaneous",
        "errand"
    ],
    "wof:name":"J D Finn Inc",
    "wof:placetype":"venue"
},
  "geometry": {"coordinates":[-80.19309800000001,26.383339],"type":"Point"}
}