{
  "type": "Feature",
  "properties": {
    "addr:full":"13197 49th St N Clearwater FL 33762",
    "addr:housenumber":"13197",
    "addr:postcode":"33762",
    "addr:street":"49Th St N",
    "iso:country":"US",
    "sg:address":"13197 49th St N",
    "sg:city":"Clearwater",
    "sg:classifiers":[
        {
            "category":"Home & Garden",
            "subcategory":"Furniture",
            "type":"Retail Goods"
        }
    ],
    "sg:phone":"+1 727 556 0872",
    "sg:postcode":"33762",
    "sg:province":"FL",
    "wof:name":"Comfort Line Bedding",
    "wof:placetype":"venue"
},
  "geometry": {"coordinates":[-82.700278,27.891274],"type":"Point"}
}