{
  "type": "Feature",
  "properties": {
    "iso:country":"US",
    "sg:address":"2445 W 80th St",
    "sg:city":"Hialeah",
    "sg:classifiers":[
        {
            "category":"Wholesale",
            "subcategory":"Construction Materials",
            "type":"Manufacturing & Wholesale Goods"
        }
    ],
    "sg:phone":"+1 305 823 4777",
    "sg:postcode":"33016",
    "sg:province":"FL",
    "sg:tags":[
        "granite"
    ],
    "wof:name":"Monarch Stone Designers",
    "wof:placetype":"venue"
},
  "geometry": {"coordinates":[-80.33281599999999,25.89525],"type":"Point"}
}