{
  "type": "Feature",
  "properties": {
    "addr:full":"1 S Orange Ave Orlando FL 32801",
    "addr:housenumber":"1",
    "addr:postcode":"32801",
    "addr:street":"S Orange Ave",
    "iso:country":"US",
    "sg:address":"1 S Orange Ave",
    "sg:city":"Orlando",
    "sg:classifiers":[
        {
            "category":"Restaurant",
            "type":"Food & Drink"
        }
    ],
    "sg:menulink":"http://www.allmenus.com/fl/orlando/36596-the-pita-pit/menu/",
    "sg:phone":"+1 407 447 7482",
    "sg:postcode":"32801",
    "sg:province":"FL",
    "sg:tags":[
        "salad",
        "soup",
        "eastern",
        "mediterranean",
        "middle",
        "american",
        "greek"
    ],
    "wof:name":"The Pita Pit",
    "wof:placetype":"venue"
},
  "geometry": {"coordinates":[-81.37898300000001,28.542128],"type":"Point"}
}