{
  "type": "Feature",
  "properties": {
    "iso:country":"US",
    "sg:address":"3020 Bravo Ct",
    "sg:city":"Orange Park",
    "sg:classifiers":[
        {
            "category":"Retail",
            "subcategory":"Auto Repair",
            "type":"Services"
        }
    ],
    "sg:phone":"+1 904 276 5003",
    "sg:postcode":"32065",
    "sg:province":"FL",
    "sg:tags":[
        "repairing",
        "automobile"
    ],
    "sg:website":"www.reinhartautomotive.com",
    "wof:name":"Reinhart Performance Engrng",
    "wof:placetype":"venue"
},
  "geometry": {"coordinates":[-81.77597799999999,30.135628],"type":"Point"}
}