{
  "type": "Feature",
  "properties": {
    "addr:full":"6090 Saint Andrews Ct Ponte Vedra Beach FL 32082",
    "addr:housenumber":"6090",
    "addr:postcode":"32082",
    "addr:street":"Saint Andrews Ct",
    "iso:country":"US",
    "sg:address":"6090 Saint Andrews Ct",
    "sg:city":"Ponte Vedra Beach",
    "sg:classifiers":[
        {
            "category":"Farming",
            "subcategory":"Farm",
            "type":"Manufacturing & Wholesale Goods"
        }
    ],
    "sg:phone":"+1 904 824 4969",
    "sg:postcode":"32082",
    "sg:province":"FL",
    "sg:tags":[
        "crop",
        "general"
    ],
    "wof:name":"Hidden Acres Farm LLC",
    "wof:placetype":"venue"
},
  "geometry": {"coordinates":[-81.398402,30.238761],"type":"Point"}
}