{
  "type": "Feature",
  "properties": {
    "iso:country":"US",
    "sg:address":"3210 S 78th St",
    "sg:city":"Tampa",
    "sg:classifiers":[
        {
            "category":"Government",
            "subcategory":"Fire Station",
            "type":"Public Place"
        }
    ],
    "sg:phone":"+1 813 744 5541",
    "sg:postcode":"33619",
    "sg:province":"FL",
    "sg:tags":[
        "county",
        "protection"
    ],
    "sg:website":"www.hillsboroughcounty.org",
    "wof:name":"Hillsborough Co Fire Mrshl Ofc",
    "wof:placetype":"venue"
},
  "geometry": {"coordinates":[-82.368623,27.918455],"type":"Point"}
}