{
  "type": "Feature",
  "properties": {
    "iso:country":"US",
    "sg:address":"7889 Maclean Rd",
    "sg:city":"Tallahassee",
    "sg:classifiers":[
        {
            "category":"Retail",
            "subcategory":"Auto Repair",
            "type":"Services"
        }
    ],
    "sg:phone":"+1 850 574 1900",
    "sg:postcode":"32312",
    "sg:province":"FL",
    "sg:tags":[
        "automotive"
    ],
    "wof:name":"All Tune & Lube",
    "wof:placetype":"venue"
},
  "geometry": {"coordinates":[-84.23866,30.575368],"type":"Point"}
}