{
  "type": "Feature",
  "properties": {
    "addr:full":"2790 US Hwy 92 Lakeland FL 33801",
    "addr:housenumber":"2790",
    "addr:postcode":"33801",
    "addr:street":"Us Hwy 92",
    "iso:country":"US",
    "sg:address":"2790 US Hwy 92",
    "sg:city":"Lakeland",
    "sg:classifiers":[
        {
            "category":"Autos & Motor Vehicles",
            "subcategory":"Auto Supplies",
            "type":"Retail Goods"
        }
    ],
    "sg:phone":"+1 863 665 4470",
    "sg:postcode":"33801",
    "sg:province":"FL",
    "sg:tags":[
        "automobile",
        "parts"
    ],
    "wof:name":"Autozone",
    "wof:placetype":"venue"
},
  "geometry": {"coordinates":[-81.906385,28.047998],"type":"Point"}
}