{
  "type": "Feature",
  "properties": {
    "addr:full":"10180 Dragonfly Run Mims FL 32754",
    "addr:housenumber":"10180",
    "addr:postcode":"32754",
    "addr:street":"Dragonfly Run",
    "iso:country":"US",
    "sg:address":"10180 Dragonfly Run",
    "sg:city":"Mims",
    "sg:classifiers":[
        {
            "category":"Building & Trades",
            "subcategory":"Construction",
            "type":"Services"
        }
    ],
    "sg:phone":"+1 407 415 0836",
    "sg:postcode":"32754",
    "sg:province":"FL",
    "sg:tags":[
        "tile",
        "dealer"
    ],
    "wof:name":"Adam Groover Tile",
    "wof:placetype":"venue"
},
  "geometry": {"coordinates":[-81.01347199999999,28.730547],"type":"Point"}
}