{
  "type": "Feature",
  "properties": {
    "iso:country":"US",
    "sg:address":"1650 Dunn Ave",
    "sg:city":"Jacksonville",
    "sg:classifiers":[
        {
            "category":"Real Estate",
            "subcategory":"Real Estate Operator",
            "type":"Services"
        }
    ],
    "sg:phone":"+1 904 714 4000",
    "sg:postcode":"32218",
    "sg:province":"FL",
    "sg:tags":[
        "commercial",
        "household",
        "storage",
        "self"
    ],
    "sg:website":"http://www.atlanticselfstorage.com/",
    "wof:name":"Atlantic Self Storage",
    "wof:placetype":"venue"
},
  "geometry": {"coordinates":[-81.67415,30.431832],"type":"Point"}
}