{
  "type": "Feature",
  "properties": {
    "addr:full":"5 Windsormere Way Oviedo FL 32765",
    "addr:housenumber":"5",
    "addr:postcode":"32765",
    "addr:street":"Windsormere Way",
    "iso:country":"US",
    "sg:address":"5 Windsormere Way",
    "sg:city":"Oviedo",
    "sg:classifiers":[
        {
            "category":"Insurance",
            "subcategory":"Hazard Insurance",
            "type":"Services"
        }
    ],
    "sg:phone":"+1 407 359 6363",
    "sg:postcode":"32765",
    "sg:province":"FL",
    "sg:tags":[
        "commercial",
        "business"
    ],
    "wof:name":"Marine Underwriter Inc",
    "wof:placetype":"venue"
},
  "geometry": {"coordinates":[-81.216016,28.669961],"type":"Point"}
}