{
  "type": "Feature",
  "properties": {
    "iso:country":"US",
    "sg:address":"945 W Michigan Ave Suite 5C",
    "sg:city":"Pensacola",
    "sg:classifiers":[
        {
            "category":"Banks & Credit Unions",
            "subcategory":"Investment Brokerage",
            "type":"Services"
        },
        {
            "category":"Banks & Credit Unions",
            "subcategory":"Bank",
            "type":"Services"
        },
        {
            "category":"Banks & Credit Unions",
            "subcategory":"Financial Services",
            "type":"Services"
        }
    ],
    "sg:phone":"+1 850 434 8266",
    "sg:postcode":"32505",
    "sg:province":"FL",
    "sg:tags":[
        "advisory",
        "mutual",
        "retirement",
        "annuity",
        "broker",
        "fund",
        "planning",
        "plan",
        "consultant",
        "security",
        "bond",
        "insurance",
        "stock"
    ],
    "sg:website":"http://national.citysearch.com/profile/external/604328932/pensacola_fl/edward_jones_vann_milheim.html?publisher=yellowpages&reference_id=1&placement=ypwebsitemip",
    "wof:name":"Edward Jones - VANN MILHEIM",
    "wof:placetype":"venue"
},
  "geometry": {"coordinates":[-87.268547,30.461691],"type":"Point"}
}