{
  "type": "Feature",
  "properties": {
    "iso:country":"US",
    "sg:address":"905 NW 2nd Ave",
    "sg:city":"Fort Lauderdale",
    "sg:classifiers":[
        {
            "category":"Organizations",
            "subcategory":"Community Association",
            "type":"Services"
        }
    ],
    "sg:phone":"+1 954 523 1741",
    "sg:postcode":"33311",
    "sg:province":"FL",
    "wof:name":"Progresso Village Civic Assn",
    "wof:placetype":"venue"
},
  "geometry": {"coordinates":[-80.146179,26.136635],"type":"Point"}
}