{
  "type": "Feature",
  "properties": {
    "iso:country":"US",
    "sg:address":"16340 San Carlos Blvd Ste 5",
    "sg:city":"Fort Myers",
    "sg:classifiers":[
        {
            "category":"Professional",
            "subcategory":"Computer Services",
            "type":"Services"
        }
    ],
    "sg:phone":"+1 239 454 6675",
    "sg:postcode":"33908",
    "sg:province":"FL",
    "sg:tags":[
        "stereo",
        "installation"
    ],
    "wof:name":"Casa Imports Inc",
    "wof:placetype":"venue"
},
  "geometry": {"coordinates":[-81.94360399999999,26.503599],"type":"Point"}
}