{
  "type": "Feature",
  "properties": {
    "addr:full":"12 Interlaken Rd Orlando FL 32804",
    "addr:housenumber":"12",
    "addr:postcode":"32804",
    "addr:street":"Interlaken Rd",
    "iso:country":"US",
    "sg:address":"12 Interlaken Rd",
    "sg:city":"Orlando",
    "sg:classifiers":[
        {
            "category":"Banks & Credit Unions",
            "subcategory":"Financial Services",
            "type":"Services"
        }
    ],
    "sg:phone":"+1 407 293 4264",
    "sg:postcode":"32804",
    "sg:province":"FL",
    "sg:tags":[
        "investor"
    ],
    "wof:name":"Coldansa Investments Inc",
    "wof:placetype":"venue"
},
  "geometry": {"coordinates":[-81.402614,28.580914],"type":"Point"}
}