{
  "type": "Feature",
  "properties": {
    "iso:country":"US",
    "sg:address":"14260 SW 136th St",
    "sg:city":"Miami",
    "sg:classifiers":[
        {
            "category":"Wholesale",
            "subcategory":"Machinery & Supplies",
            "type":"Manufacturing & Wholesale Goods"
        }
    ],
    "sg:phone":"+1 305 378 2876",
    "sg:postcode":"33186",
    "sg:province":"FL",
    "wof:name":"Eris Granite",
    "wof:placetype":"venue"
},
  "geometry": {"coordinates":[-80.425309,25.640799],"type":"Point"}
}