{
  "type": "Feature",
  "properties": {
    "addr:full":"2145 SW 2nd Ave Fort Lauderdale FL 33315",
    "addr:housenumber":"2145",
    "addr:postcode":"33315",
    "addr:street":"Sw 2Nd Ave",
    "iso:country":"US",
    "sg:address":"2145 SW 2nd Ave",
    "sg:city":"Fort Lauderdale",
    "sg:classifiers":[
        {
            "category":"Professional",
            "subcategory":"Art Services",
            "type":"Services"
        }
    ],
    "sg:phone":"+1 954 523 1312",
    "sg:postcode":"33315",
    "sg:province":"FL",
    "sg:tags":[
        "artist"
    ],
    "wof:name":"Architectural Arts By Vathauer",
    "wof:placetype":"venue"
},
  "geometry": {"coordinates":[-80.14278400000001,26.09499],"type":"Point"}
}