{
  "type": "Feature",
  "properties": {
    "addr:full":"1431 Muir Cir Clermont FL 34711",
    "addr:housenumber":"1431",
    "addr:postcode":"34711",
    "addr:street":"Muir Cir",
    "iso:country":"US",
    "sg:address":"1431 Muir Cir",
    "sg:city":"Clermont",
    "sg:classifiers":[
        {
            "category":"Restaurant",
            "type":"Food & Drink"
        }
    ],
    "sg:phone":"+1 352 989 1574",
    "sg:postcode":"34711",
    "sg:province":"FL",
    "wof:name":"Cajan Bouncers Inc",
    "wof:placetype":"venue"
},
  "geometry": {"coordinates":[-81.730835,28.563412],"type":"Point"}
}