{
  "type": "Feature",
  "properties": {
    "iso:country":"US",
    "sg:address":"275 S State Hwy 7",
    "sg:city":"Margate",
    "sg:classifiers":[
        {
            "category":"Banks & Credit Unions",
            "subcategory":"Bank",
            "type":"Services"
        }
    ],
    "sg:phone":"+1 954 978 0013",
    "sg:postcode":"33068",
    "sg:province":"FL",
    "sg:tags":[
        "loan"
    ],
    "wof:name":"Advance Til Payday",
    "wof:placetype":"venue"
},
  "geometry": {"coordinates":[-80.204666,26.226572],"type":"Point"}
}