{
  "type": "Feature",
  "properties": {
    "addr:full":"640 SE 18th St Ocala FL 34471",
    "addr:housenumber":"640",
    "addr:postcode":"34471",
    "addr:street":"Se 18Th St",
    "iso:country":"US",
    "sg:address":"640 SE 18th St",
    "sg:city":"Ocala",
    "sg:classifiers":[
        {
            "category":"Farming",
            "subcategory":"Nursery",
            "type":"Manufacturing & Wholesale Goods"
        }
    ],
    "sg:phone":"+1 352 732 8782",
    "sg:postcode":"34471",
    "sg:province":"FL",
    "sg:tags":[
        "ornamental"
    ],
    "wof:name":"Sharon Morgan",
    "wof:placetype":"venue"
},
  "geometry": {"coordinates":[-82.13287,29.169976],"type":"Point"}
}