{
  "type": "Feature",
  "properties": {
    "iso:country":"US",
    "sg:address":"731 NE 5th Ave",
    "sg:city":"Crystal River",
    "sg:classifiers":[
        {
            "category":"Home & Garden",
            "subcategory":"Furniture",
            "type":"Retail Goods"
        }
    ],
    "sg:phone":"+1 352 795 9855",
    "sg:postcode":"34428",
    "sg:province":"FL",
    "wof:name":"Payless Furniture Inc",
    "wof:placetype":"venue"
},
  "geometry": {"coordinates":[-82.585655,28.902358],"type":"Point"}
}