{
  "type": "Feature",
  "properties": {
    "addr:full":"4250 Dow Rd Melbourne FL 32934",
    "addr:housenumber":"4250",
    "addr:postcode":"32934",
    "addr:street":"Dow Rd",
    "iso:country":"US",
    "sg:address":"4250 Dow Rd",
    "sg:city":"Melbourne",
    "sg:classifiers":[
        {
            "category":"Building & Trades",
            "subcategory":"Construction",
            "type":"Services"
        }
    ],
    "sg:phone":"+1 321 255 7848",
    "sg:postcode":"32934",
    "sg:province":"FL",
    "sg:tags":[
        "contractor"
    ],
    "wof:name":"Douglas Michels",
    "wof:placetype":"venue"
},
  "geometry": {"coordinates":[-80.696415,28.107575],"type":"Point"}
}