{
  "type": "Feature",
  "properties": {
    "addr:full":"2189 Sunshine Blvd Naples FL 34116",
    "addr:housenumber":"2189",
    "addr:postcode":"34116",
    "addr:street":"Sunshine Blvd",
    "iso:country":"US",
    "sg:address":"2189 Sunshine Blvd",
    "sg:city":"Naples",
    "sg:classifiers":[
        {
            "category":"Building & Trades",
            "subcategory":"Construction",
            "type":"Services"
        }
    ],
    "sg:phone":"+1 239 353 7830",
    "sg:postcode":"34116",
    "sg:province":"FL",
    "sg:tags":[
        "tile",
        "dealer"
    ],
    "wof:name":"QSC Tile & Marble Instltn",
    "wof:placetype":"venue"
},
  "geometry": {"coordinates":[-81.70254300000001,26.188133],"type":"Point"}
}