{
  "type": "Feature",
  "properties": {
    "iso:country":"US",
    "sg:address":"3528 W Flagler St",
    "sg:city":"Miami",
    "sg:classifiers":[
        {
            "category":"Restaurant",
            "type":"Food & Drink"
        },
        {
            "category":"Bakery",
            "type":"Food & Drink"
        }
    ],
    "sg:phone":"+1 305 443 6775",
    "sg:postcode":"33135",
    "sg:province":"FL",
    "wof:name":"Marselles Bakery Inc",
    "wof:placetype":"venue"
},
  "geometry": {"coordinates":[-80.25272200000001,25.771942],"type":"Point"}
}