{
  "type": "Feature",
  "properties": {
    "iso:country":"US",
    "sg:address":"3157 Stonewater Dr",
    "sg:city":"Lakeland",
    "sg:classifiers":[
        {
            "category":"Banks & Credit Unions",
            "subcategory":"Bank",
            "type":"Services"
        }
    ],
    "sg:phone":"+1 863 646 7925",
    "sg:postcode":"33803",
    "sg:province":"FL",
    "sg:tags":[
        "machine",
        "teller",
        "automated"
    ],
    "wof:name":"ATM System Of Central Fl",
    "wof:placetype":"venue"
},
  "geometry": {"coordinates":[-81.972678,28.006669],"type":"Point"}
}