{
  "type": "Feature",
  "properties": {
    "iso:country":"US",
    "sg:address":"48 Meadow Way",
    "sg:city":"Frostproof",
    "sg:classifiers":[
        {
            "category":"Freight",
            "type":"Transportation"
        }
    ],
    "sg:phone":"+1 863 285 9994",
    "sg:postcode":"33843",
    "sg:province":"FL",
    "sg:tags":[
        "local",
        "storage",
        "trucking"
    ],
    "wof:name":"Maria Trucking Inc",
    "wof:placetype":"venue"
},
  "geometry": {"coordinates":[-81.670447,27.743567],"type":"Point"}
}