{
  "type": "Feature",
  "properties": {
    "addr:full":"6521 NW 14th St Fort Lauderdale FL 33313",
    "addr:housenumber":"6521",
    "addr:postcode":"33313",
    "addr:street":"Nw 14Th St",
    "iso:country":"US",
    "sg:address":"6521 NW 14th St",
    "sg:city":"Fort Lauderdale",
    "sg:classifiers":[
        {
            "category":"Retail",
            "subcategory":"Auto Repair",
            "type":"Services"
        }
    ],
    "sg:phone":"+1 954 797 0179",
    "sg:postcode":"33313",
    "sg:province":"FL",
    "sg:tags":[
        "automotive"
    ],
    "wof:name":"Nissan & Honda Specialists",
    "wof:placetype":"venue"
},
  "geometry": {"coordinates":[-80.236231,26.142794],"type":"Point"}
}