{
  "type": "Feature",
  "properties": {
    "addr:full":"12550 New Brittany Blvd Fort Myers FL 33907",
    "addr:housenumber":"12550",
    "addr:postcode":"33907",
    "addr:street":"New Brittany Blvd",
    "iso:country":"US",
    "sg:address":"12550 New Brittany Blvd",
    "sg:city":"Fort Myers",
    "sg:classifiers":[
        {
            "category":"Banks & Credit Unions",
            "subcategory":"Bank",
            "type":"Services"
        }
    ],
    "sg:phone":"+1 239 277 7770",
    "sg:postcode":"33907",
    "sg:province":"FL",
    "sg:tags":[
        "loan",
        "broker"
    ],
    "wof:name":"Pinnacle Financial Corporation",
    "wof:placetype":"venue"
},
  "geometry": {"coordinates":[-81.880956,26.56013],"type":"Point"}
}