{
  "type": "Feature",
  "properties": {
    "addr:full":"7975 S Orange Blossom Trl Orlando FL 32809",
    "addr:housenumber":"7975",
    "addr:postcode":"32809",
    "addr:street":"S Orange Blossom Trl",
    "iso:country":"US",
    "sg:address":"7975 S Orange Blossom Trl",
    "sg:city":"Orlando",
    "sg:classifiers":[
        {
            "category":"Restaurant",
            "type":"Food & Drink"
        }
    ],
    "sg:menulink":"http://www.allmenus.com/fl/orlando/29798-chicken-kitchen/menu/",
    "sg:phone":"+1 407 888 8318",
    "sg:postcode":"32809",
    "sg:province":"FL",
    "sg:tags":[
        "american",
        "wing"
    ],
    "wof:name":"Chicken Kitchen",
    "wof:placetype":"venue"
},
  "geometry": {"coordinates":[-81.400526,28.451041],"type":"Point"}
}