{
  "type": "Feature",
  "properties": {
    "addr:full":"21298 Hepner Ave Port Charlotte FL 33952",
    "addr:postcode":"21298;33952",
    "addr:street":"Hepner Ave",
    "iso:country":"US",
    "sg:address":"21298 Hepner Ave",
    "sg:city":"Port Charlotte",
    "sg:classifiers":[
        {
            "category":"Building & Trades",
            "subcategory":"Landscaping Services",
            "type":"Services"
        }
    ],
    "sg:phone":"+1 941 625 8514",
    "sg:postcode":"33952",
    "sg:province":"FL",
    "wof:name":"Toppers Lawn Care Services",
    "wof:placetype":"venue"
},
  "geometry": {"coordinates":[-82.09739399999999,26.99652],"type":"Point"}
}