{
  "type": "Feature",
  "properties": {
    "addr:full":"5051 Normandy Blvd Jacksonville FL 32205",
    "addr:housenumber":"5051",
    "addr:postcode":"32205",
    "addr:street":"Normandy Blvd",
    "iso:country":"US",
    "sg:address":"5051 Normandy Blvd",
    "sg:city":"Jacksonville",
    "sg:classifiers":[
        {
            "category":"Shopping",
            "subcategory":"Party Supplies",
            "type":"Retail Goods"
        },
        {
            "category":"Shopping",
            "subcategory":"Gifts & Souvenirs",
            "type":"Retail Goods"
        }
    ],
    "sg:phone":"+1 904 378 5003",
    "sg:postcode":"32205",
    "sg:province":"FL",
    "sg:tags":[
        "shop",
        "decoration",
        "rental"
    ],
    "wof:name":"Games People Play",
    "wof:placetype":"venue"
},
  "geometry": {"coordinates":[-81.73204800000001,30.309199],"type":"Point"}
}