{
  "type": "Feature",
  "properties": {
    "iso:country":"US",
    "sg:address":"326 SW 62nd Ave",
    "sg:city":"Miami",
    "sg:classifiers":[
        {
            "category":"Professional",
            "subcategory":"Engineering",
            "type":"Services"
        }
    ],
    "sg:phone":"+1 305 262 6997",
    "sg:postcode":"33144",
    "sg:province":"FL",
    "sg:tags":[
        "engineer"
    ],
    "wof:name":"Ec & Assoc Inc",
    "wof:placetype":"venue"
},
  "geometry": {"coordinates":[-80.296038,25.767645],"type":"Point"}
}