{
  "type": "Feature",
  "properties": {
    "iso:country":"US",
    "sg:address":"3260 Neff Lake Rd",
    "sg:city":"Brooksville",
    "sg:classifiers":[
        {
            "category":"Building & Trades",
            "subcategory":"Landscaping Services",
            "type":"Services"
        }
    ],
    "sg:phone":"+1 352 279 2038",
    "sg:postcode":"34602",
    "sg:province":"FL",
    "sg:tags":[
        "tree"
    ],
    "wof:name":"Absolute Tree And Asset Services",
    "wof:placetype":"venue"
},
  "geometry": {"coordinates":[-82.319474,28.477872],"type":"Point"}
}