{
  "type": "Feature",
  "properties": {
    "iso:country":"US",
    "sg:address":"550 N Nova Rd",
    "sg:city":"Ormond Beach",
    "sg:classifiers":[
        {
            "category":"Real Estate",
            "subcategory":"Developer",
            "type":"Services"
        }
    ],
    "sg:phone":"+1 386 677 8979",
    "sg:postcode":"32174",
    "sg:province":"FL",
    "sg:tags":[
        "cemetery"
    ],
    "wof:name":"Volusia Memorial Park & Fnrl",
    "wof:placetype":"venue"
},
  "geometry": {"coordinates":[-81.08729099999999,29.292723],"type":"Point"}
}