{
  "type": "Feature",
  "properties": {
    "addr:full":"8301 Scenic Hwy Pensacola FL 32514",
    "addr:housenumber":"8301",
    "addr:postcode":"32514",
    "addr:street":"Scenic Hwy",
    "iso:country":"US",
    "sg:address":"8301 Scenic Hwy",
    "sg:city":"Pensacola",
    "sg:classifiers":[
        {
            "category":"Manufacturing",
            "subcategory":"Tools & Machinery",
            "type":"Manufacturing & Wholesale Goods"
        }
    ],
    "sg:phone":"+1 850 474 4011",
    "sg:postcode":"32514",
    "sg:province":"FL",
    "sg:tags":[
        "turbine"
    ],
    "wof:name":"General Electric Co",
    "wof:placetype":"venue"
},
  "geometry": {"coordinates":[-87.164683,30.513598],"type":"Point"}
}