{
  "type": "Feature",
  "properties": {
    "iso:country":"US",
    "sg:address":"347 S Orange Ave",
    "sg:city":"Arcadia",
    "sg:classifiers":[
        {
            "category":"Professional",
            "type":"Services"
        }
    ],
    "sg:phone":"+1 863 491 7700",
    "sg:postcode":"34266",
    "sg:province":"FL",
    "sg:tags":[
        "massage"
    ],
    "wof:name":"Gentle Touch Inc",
    "wof:placetype":"venue"
},
  "geometry": {"coordinates":[-81.866196,27.210635],"type":"Point"}
}