{
  "type": "Feature",
  "properties": {
    "iso:country":"US",
    "sg:address":"960 Allendale St",
    "sg:city":"Titusville",
    "sg:classifiers":[
        {
            "category":"Shopping",
            "subcategory":"Used Merchandise",
            "type":"Retail Goods"
        }
    ],
    "sg:phone":"+1 321 267 4294",
    "sg:postcode":"32796",
    "sg:province":"FL",
    "sg:tags":[
        "flea",
        "market"
    ],
    "wof:name":"Edward R Sherman & Sons",
    "wof:placetype":"venue"
},
  "geometry": {"coordinates":[-80.85888300000001,28.626997],"type":"Point"}
}