{
  "type": "Feature",
  "properties": {
    "addr:full":"1686 Dogwood Cir Middleburg FL 32068",
    "addr:housenumber":"1686",
    "addr:postcode":"32068",
    "addr:street":"Dogwood Cir",
    "iso:country":"US",
    "sg:address":"1686 Dogwood Cir",
    "sg:city":"Middleburg",
    "sg:classifiers":[
        {
            "category":"Professional",
            "type":"Services"
        }
    ],
    "sg:phone":"+1 904 215 3264",
    "sg:postcode":"32068",
    "sg:province":"FL",
    "wof:name":"Action Graphics",
    "wof:placetype":"venue"
},
  "geometry": {"coordinates":[-81.753924,30.097239],"type":"Point"}
}