{
  "type": "Feature",
  "properties": {
    "addr:full":"127 Park Ln E Lake Worth FL 33462",
    "addr:housenumber":"127",
    "addr:postcode":"33462",
    "addr:street":"Park Ln E",
    "iso:country":"US",
    "sg:address":"127 Park Ln E",
    "sg:city":"Lake Worth",
    "sg:classifiers":[
        {
            "category":"Real Estate",
            "subcategory":"Real Estate Operator",
            "type":"Services"
        }
    ],
    "sg:phone":"+1 561 585 8080",
    "sg:postcode":"33462",
    "sg:province":"FL",
    "sg:tags":[
        "property",
        "lessor"
    ],
    "wof:name":"Manatee Property Management",
    "wof:placetype":"venue"
},
  "geometry": {"coordinates":[-80.052694,26.569468],"type":"Point"}
}