{
  "type": "Feature",
  "properties": {
    "iso:country":"US",
    "sg:address":"920 Poinsettia St",
    "sg:city":"Casselberry",
    "sg:classifiers":[
        {
            "category":"Professional",
            "subcategory":"Business Services",
            "type":"Services"
        }
    ],
    "sg:phone":"+1 407 695 4364",
    "sg:postcode":"32707",
    "sg:province":"FL",
    "sg:tags":[
        "pool",
        "swimming"
    ],
    "wof:name":"Tony's Pool Svc Inc",
    "wof:placetype":"venue"
},
  "geometry": {"coordinates":[-81.327332,28.686609],"type":"Point"}
}