{
  "type": "Feature",
  "properties": {
    "addr:full":"4509 Coral Palms Ln Naples FL 34116",
    "addr:housenumber":"4509",
    "addr:postcode":"34116",
    "addr:street":"Coral Palms Ln",
    "iso:country":"US",
    "sg:address":"4509 Coral Palms Ln",
    "sg:city":"Naples",
    "sg:classifiers":[
        {
            "category":"Professional",
            "subcategory":"Research",
            "type":"Services"
        }
    ],
    "sg:phone":"+1 239 354 0783",
    "sg:postcode":"34116",
    "sg:province":"FL",
    "wof:name":"Nielsen Media Research",
    "wof:placetype":"venue"
},
  "geometry": {"coordinates":[-81.700147,26.184723],"type":"Point"}
}