{
  "type": "Feature",
  "properties": {
    "iso:country":"US",
    "sg:address":"3552 NW 32nd St",
    "sg:city":"Miami",
    "sg:classifiers":[
        {
            "category":"Retail",
            "subcategory":"Auto Repair",
            "type":"Services"
        }
    ],
    "sg:phone":"+1 305 637 0952",
    "sg:postcode":"33142",
    "sg:province":"FL",
    "sg:tags":[
        "body",
        "automobile",
        "painting",
        "repairing"
    ],
    "wof:name":"Palacios Paint & Body Shop",
    "wof:placetype":"venue"
},
  "geometry": {"coordinates":[-80.254209,25.804973],"type":"Point"}
}