{
  "type": "Feature",
  "properties": {
    "iso:country":"US",
    "sg:address":"8232 New Kings Rd",
    "sg:city":"Jacksonville",
    "sg:classifiers":[
        {
            "category":"Restaurant",
            "type":"Food & Drink"
        }
    ],
    "sg:phone":"+1 904 768 9086",
    "sg:postcode":"32219",
    "sg:province":"FL",
    "sg:tags":[
        "barbecue"
    ],
    "wof:name":"Barbeque Grills",
    "wof:placetype":"venue"
},
  "geometry": {"coordinates":[-81.741212,30.400747],"type":"Point"}
}