{
  "type": "Feature",
  "properties": {
    "iso:country":"US",
    "sg:address":"885 State Road 436",
    "sg:city":"Casselberry",
    "sg:classifiers":[
        {
            "category":"Professional",
            "subcategory":"Printing & Photocopies",
            "type":"Services"
        }
    ],
    "sg:phone":"+1 407 831 6334",
    "sg:postcode":"32707",
    "sg:province":"FL",
    "sg:website":"www.fastsigns.com/56",
    "wof:name":"FASTSIGNS - Signs and Graphics",
    "wof:placetype":"venue"
},
  "geometry": {"coordinates":[-81.325897,28.649599],"type":"Point"}
}