{
  "type": "Feature",
  "properties": {
    "iso:country":"US",
    "sg:address":"7777 Kenway Pl W",
    "sg:city":"Boca Raton",
    "sg:classifiers":[
        {
            "category":"Wholesale",
            "subcategory":"Home Furnishings",
            "type":"Manufacturing & Wholesale Goods"
        }
    ],
    "sg:phone":"+1 561 392 4846",
    "sg:postcode":"33433",
    "sg:province":"FL",
    "wof:name":"RG Assoc",
    "wof:placetype":"venue"
},
  "geometry": {"coordinates":[-80.16690699999999,26.352085],"type":"Point"}
}