{
  "type": "Feature",
  "properties": {
    "addr:full":"5566 NW 161st St Hialeah FL 33014",
    "addr:housenumber":"5566",
    "addr:postcode":"33014",
    "addr:street":"Nw 161St St",
    "iso:country":"US",
    "sg:address":"5566 NW 161st St",
    "sg:city":"Hialeah",
    "sg:classifiers":[
        {
            "category":"Shopping",
            "subcategory":"Stationery & Office Supplies",
            "type":"Retail Goods"
        },
        {
            "category":"Shopping",
            "subcategory":"Gifts & Souvenirs",
            "type":"Retail Goods"
        }
    ],
    "sg:phone":"+1 305 430 8481",
    "sg:postcode":"33014",
    "sg:province":"FL",
    "sg:tags":[
        "shop",
        "card",
        "greeting",
        "store"
    ],
    "wof:name":"Wholesale Cards & Party Inc",
    "wof:placetype":"venue"
},
  "geometry": {"coordinates":[-80.29089,25.919523],"type":"Point"}
}