{
  "type": "Feature",
  "properties": {
    "iso:country":"US",
    "sg:address":"255 Bermuda Beach Dr",
    "sg:city":"Fort Pierce",
    "sg:classifiers":[
        {
            "category":"Building & Trades",
            "subcategory":"Construction",
            "type":"Services"
        }
    ],
    "sg:phone":"+1 772 595 9196",
    "sg:postcode":"34949",
    "sg:province":"FL",
    "sg:tags":[
        "contractor"
    ],
    "wof:name":"Randy Berry Svc",
    "wof:placetype":"venue"
},
  "geometry": {"coordinates":[-80.30264099999999,27.487291],"type":"Point"}
}