{
  "type": "Feature",
  "properties": {
    "addr:full":"2151 Sorrento Cir Winter Park FL 32792",
    "addr:housenumber":"2151",
    "addr:postcode":"32792",
    "addr:street":"Sorrento Cir",
    "iso:country":"US",
    "sg:address":"2151 Sorrento Cir",
    "sg:city":"Winter Park",
    "sg:classifiers":[
        {
            "category":"Professional",
            "type":"Services"
        }
    ],
    "sg:phone":"+1 407 856 0993",
    "sg:postcode":"32792",
    "sg:province":"FL",
    "sg:tags":[
        "establishment"
    ],
    "wof:name":"Fla Vacation Dreams",
    "wof:placetype":"venue"
},
  "geometry": {"coordinates":[-81.317972,28.624876],"type":"Point"}
}