{
  "type": "Feature",
  "properties": {
    "addr:full":"4280 Dow Rd Melbourne FL 32934",
    "addr:housenumber":"4280",
    "addr:postcode":"32934",
    "addr:street":"Dow Rd",
    "iso:country":"US",
    "sg:address":"4280 Dow Rd",
    "sg:city":"Melbourne",
    "sg:classifiers":[
        {
            "category":"Home & Garden",
            "subcategory":"Building Materials",
            "type":"Retail Goods"
        },
        {
            "category":"Building & Trades",
            "subcategory":"Construction",
            "type":"Services"
        }
    ],
    "sg:phone":"+1 321 259 2319",
    "sg:postcode":"32934",
    "sg:province":"FL",
    "sg:tags":[
        "planning",
        "remodeling",
        "kitchen"
    ],
    "wof:name":"A&A Countertops Inc",
    "wof:placetype":"venue"
},
  "geometry": {"coordinates":[-80.69708900000001,28.107562],"type":"Point"}
}