{
  "type": "Feature",
  "properties": {
    "addr:full":"3000 NW 83 St Gainesville FL 32606",
    "addr:housenumber":"3000",
    "addr:postcode":"32606",
    "addr:street":"Nw 83 St",
    "iso:country":"US",
    "sg:address":"3000 NW 83 St",
    "sg:city":"Gainesville",
    "sg:classifiers":[
        {
            "category":"Education",
            "subcategory":"Junior College",
            "type":"Public Place"
        }
    ],
    "sg:phone":"+1 352 395 5000",
    "sg:postcode":"32606",
    "sg:province":"FL",
    "sg:tags":[
        "book"
    ],
    "wof:name":"Sante Fe Bookstore",
    "wof:placetype":"venue"
},
  "geometry": {"coordinates":[-82.430397,29.675843],"type":"Point"}
}