{
  "type": "Feature",
  "properties": {
    "iso:country":"US",
    "sg:address":"4260 E Bay Dr",
    "sg:city":"Clearwater",
    "sg:classifiers":[
        {
            "category":"Autos & Motor Vehicles",
            "subcategory":"Auto Supplies",
            "type":"Retail Goods"
        }
    ],
    "sg:phone":"+1 727 531 8643",
    "sg:postcode":"33764",
    "sg:province":"FL",
    "sg:tags":[
        "automobile",
        "parts"
    ],
    "wof:name":"Discount Auto Parts Inc",
    "wof:placetype":"venue"
},
  "geometry": {"coordinates":[-82.743785,27.916403],"type":"Point"}
}