{
  "type": "Feature",
  "properties": {
    "iso:country":"US",
    "sg:address":"14220 SW 136th St",
    "sg:city":"Miami",
    "sg:classifiers":[
        {
            "category":"Professional",
            "subcategory":"Business Services",
            "type":"Services"
        }
    ],
    "sg:phone":"+1 305 232 1765",
    "sg:postcode":"33186",
    "sg:province":"FL",
    "sg:tags":[
        "repossessing"
    ],
    "wof:name":"Ace Recovery Co Inc",
    "wof:placetype":"venue"
},
  "geometry": {"coordinates":[-80.427549,25.640726],"type":"Point"}
}