{
  "type": "Feature",
  "properties": {
    "iso:country":"US",
    "sg:address":"1651 SE 140 Ter",
    "sg:city":"Morriston",
    "sg:classifiers":[
        {
            "category":"Building & Trades",
            "subcategory":"Electrical",
            "type":"Services"
        }
    ],
    "sg:phone":"+1 352 529 9122",
    "sg:postcode":"32668",
    "sg:province":"FL",
    "sg:tags":[
        "electrical",
        "contractor"
    ],
    "wof:name":"Kline Electric Inc",
    "wof:placetype":"venue"
},
  "geometry": {"coordinates":[-82.53762399999999,29.304551],"type":"Point"}
}