{
  "type": "Feature",
  "properties": {
    "iso:country":"US",
    "sg:address":"133 Sabal Ct",
    "sg:city":"Oldsmar",
    "sg:classifiers":[
        {
            "category":"Government",
            "subcategory":"Office",
            "type":"Public Place"
        }
    ],
    "sg:phone":"+1 727 523 1480",
    "sg:postcode":"34677",
    "sg:province":"FL",
    "sg:tags":[
        "national",
        "security"
    ],
    "wof:name":"Sky Way Bridge Composite 08375",
    "wof:placetype":"venue"
},
  "geometry": {"coordinates":[-82.67824299999999,28.048623],"type":"Point"}
}