{
  "type": "Feature",
  "properties": {
    "iso:country":"US",
    "sg:address":"9360 SW 72nd St",
    "sg:city":"Miami",
    "sg:classifiers":[
        {
            "category":"Building & Trades",
            "subcategory":"Electrical",
            "type":"Services"
        }
    ],
    "sg:phone":"+1 305 273 7815",
    "sg:postcode":"33173",
    "sg:province":"FL",
    "sg:tags":[
        "electrical",
        "electric",
        "contractor"
    ],
    "wof:name":"G N Electric Inc",
    "wof:placetype":"venue"
},
  "geometry": {"coordinates":[-80.34428800000001,25.701807],"type":"Point"}
}