{
  "type": "Feature",
  "properties": {
    "iso:country":"US",
    "sg:address":"2908 Seven Springs Blvd",
    "sg:city":"New Port Richey",
    "sg:classifiers":[
        {
            "category":"Food & Beverages",
            "subcategory":"Groceries & Convenience Stores",
            "type":"Retail Goods"
        }
    ],
    "sg:phone":"+1 727 372 2807",
    "sg:postcode":"34655",
    "sg:province":"FL",
    "wof:name":"Super Stop",
    "wof:placetype":"venue"
},
  "geometry": {"coordinates":[-82.694171,28.205285],"type":"Point"}
}