{
  "type": "Feature",
  "properties": {
    "addr:full":"2498 SE Stonecrop St Port St Lucie FL 34984",
    "addr:housenumber":"2498",
    "addr:postcode":"34984",
    "addr:street":"Se Stonecrop St;St",
    "iso:country":"US",
    "sg:address":"2498 SE Stonecrop St",
    "sg:city":"Port St Lucie",
    "sg:classifiers":[
        {
            "category":"Building & Trades",
            "subcategory":"Construction",
            "type":"Services"
        }
    ],
    "sg:phone":"+1 772 879 1090",
    "sg:postcode":"34984",
    "sg:province":"FL",
    "sg:tags":[
        "hanging",
        "painter",
        "contractor"
    ],
    "wof:name":"Thomas Painters Inc",
    "wof:placetype":"venue"
},
  "geometry": {"coordinates":[-80.33296,27.271359],"type":"Point"}
}