{
  "type": "Feature",
  "properties": {
    "iso:country":"US",
    "sg:address":"1414 W Magnolia Cir",
    "sg:city":"Jacksonville",
    "sg:classifiers":[
        {
            "category":"Autos & Motor Vehicles",
            "subcategory":"Automobile Sales",
            "type":"Retail Goods"
        }
    ],
    "sg:phone":"+1 904 745 1479",
    "sg:postcode":"32211",
    "sg:province":"FL",
    "sg:tags":[
        "used"
    ],
    "wof:name":"Local Motion",
    "wof:placetype":"venue"
},
  "geometry": {"coordinates":[-81.609765,30.334656],"type":"Point"}
}