{
  "type": "Feature",
  "properties": {
    "iso:country":"US",
    "sg:address":"3129 W Hallandale Beach Blvd",
    "sg:city":"Hallandale",
    "sg:classifiers":[
        {
            "category":"Shopping",
            "subcategory":"Pharmacy",
            "type":"Retail Goods"
        }
    ],
    "sg:phone":"+1 954 964 9783",
    "sg:postcode":"33009",
    "sg:province":"FL",
    "wof:name":"Pulmonary Prescription Prvdrs",
    "wof:placetype":"venue"
},
  "geometry": {"coordinates":[-80.170357,25.98495],"type":"Point"}
}