{
  "type": "Feature",
  "properties": {
    "iso:country":"US",
    "sg:address":"14902 N Florida Ave",
    "sg:city":"Tampa",
    "sg:classifiers":[
        {
            "category":"Retail",
            "subcategory":"Repair Shop",
            "type":"Services"
        },
        {
            "category":"Professional",
            "subcategory":"Management & Consulting",
            "type":"Services"
        }
    ],
    "sg:phone":"+1 813 908 5933",
    "sg:postcode":"33613",
    "sg:province":"FL",
    "sg:tags":[
        "equipment",
        "printing"
    ],
    "wof:name":"Baytec Services Inc",
    "wof:placetype":"venue"
},
  "geometry": {"coordinates":[-82.459659,28.085688],"type":"Point"}
}