{
  "type": "Feature",
  "properties": {
    "addr:full":"2035 Kings Hwy Clearwater FL 33755",
    "addr:housenumber":"2035",
    "addr:postcode":"33755",
    "addr:street":"Kings Hwy",
    "iso:country":"US",
    "sg:address":"2035 Kings Hwy",
    "sg:city":"Clearwater",
    "sg:classifiers":[
        {
            "category":"Real Estate",
            "subcategory":"Real Estate Operator",
            "type":"Services"
        }
    ],
    "sg:phone":"+1 727 447 4009",
    "sg:postcode":"33755",
    "sg:province":"FL",
    "sg:tags":[
        "apartment"
    ],
    "wof:name":"Lennox Court",
    "wof:placetype":"venue"
},
  "geometry": {"coordinates":[-82.779545,27.995205],"type":"Point"}
}