{
  "type": "Feature",
  "properties": {
    "addr:full":"5400 Diplomat Cir Orlando FL 32810",
    "addr:postcode":"5400;32810",
    "addr:street":"Diplomat Cir",
    "iso:country":"US",
    "sg:address":"5400 Diplomat Cir",
    "sg:city":"Orlando",
    "sg:classifiers":[
        {
            "category":"Insurance",
            "subcategory":"Insurance Agent",
            "type":"Services"
        }
    ],
    "sg:phone":"+1 407 647 3225",
    "sg:postcode":"32810",
    "sg:province":"FL",
    "wof:name":"United American Insurance Co",
    "wof:placetype":"venue"
},
  "geometry": {"coordinates":[-81.388054,28.608992],"type":"Point"}
}