{
  "type": "Feature",
  "properties": {
    "iso:country":"US",
    "sg:address":"905 S Laurel Ave",
    "sg:city":"Sanford",
    "sg:classifiers":[
        {
            "category":"Retail",
            "subcategory":"Funeral Services",
            "type":"Services"
        }
    ],
    "sg:phone":"+1 407 322 2131",
    "sg:postcode":"32771",
    "sg:province":"FL",
    "sg:tags":[
        "director",
        "home"
    ],
    "wof:name":"Brisson Funeral Home PA",
    "wof:placetype":"venue"
},
  "geometry": {"coordinates":[-81.271981,28.803566],"type":"Point"}
}