{
  "type": "Feature",
  "properties": {
    "addr:full":"36 US Hwy 92 Debary FL 32713",
    "addr:housenumber":"36",
    "addr:postcode":"32713",
    "addr:street":"Us Hwy 92",
    "iso:country":"US",
    "sg:address":"36 US Hwy 92",
    "sg:city":"Debary",
    "sg:classifiers":[
        {
            "category":"Personal",
            "subcategory":"Beauty Salon",
            "type":"Services"
        }
    ],
    "sg:phone":"+1 386 668 1970",
    "sg:postcode":"32713",
    "sg:province":"FL",
    "wof:name":"Legends Hair Styling Salon",
    "wof:placetype":"venue"
},
  "geometry": {"coordinates":[-81.30839899999999,28.884298],"type":"Point"}
}