{
  "type": "Feature",
  "properties": {
    "addr:full":"8602 Temple Terrace Hwy Tampa FL 33637",
    "addr:housenumber":"8602",
    "addr:postcode":"33637",
    "addr:street":"Temple Terrace Hwy",
    "iso:country":"US",
    "sg:address":"8602 Temple Terrace Hwy",
    "sg:city":"Tampa",
    "sg:classifiers":[
        {
            "category":"Shopping",
            "type":"Retail Goods"
        }
    ],
    "sg:phone":"+1 813 989 3103",
    "sg:postcode":"33637",
    "sg:province":"FL",
    "sg:tags":[
        "chemical"
    ],
    "wof:name":"Continental Chemical",
    "wof:placetype":"venue"
},
  "geometry": {"coordinates":[-82.360332,28.032666],"type":"Point"}
}