{
  "type": "Feature",
  "properties": {
    "addr:full":"6930 NW 83rd St Tamarac FL 33321",
    "addr:housenumber":"6930",
    "addr:postcode":"33321",
    "addr:street":"Nw 83Rd St",
    "iso:country":"US",
    "sg:address":"6930 NW 83rd St",
    "sg:city":"Tamarac",
    "sg:classifiers":[
        {
            "category":"Home & Garden",
            "subcategory":"Building Materials",
            "type":"Retail Goods"
        },
        {
            "category":"Manufacturing",
            "subcategory":"Building Materials",
            "type":"Manufacturing & Wholesale Goods"
        }
    ],
    "sg:phone":"+1 954 726 6772",
    "sg:postcode":"33321",
    "sg:province":"FL",
    "sg:tags":[
        "frames",
        "window",
        "doors",
        "accessory"
    ],
    "wof:name":"Global Tops Enterprises Inc",
    "wof:placetype":"venue"
},
  "geometry": {"coordinates":[-80.244884,26.226984],"type":"Point"}
}