{
  "type": "Feature",
  "properties": {
    "addr:full":"5978 W 16th Ave Hialeah FL 33012",
    "addr:housenumber":"5978",
    "addr:postcode":"33012",
    "addr:street":"W 16Th Ave",
    "iso:country":"US",
    "sg:address":"5978 W 16th Ave",
    "sg:city":"Hialeah",
    "sg:classifiers":[
        {
            "category":"Shopping",
            "subcategory":"Crafts & Fabrics",
            "type":"Retail Goods"
        }
    ],
    "sg:phone":"+1 305 558 6679",
    "sg:postcode":"33012",
    "sg:province":"FL",
    "sg:tags":[
        "shop"
    ],
    "wof:name":"Fabricsworld",
    "wof:placetype":"venue"
},
  "geometry": {"coordinates":[-80.31527800000001,25.875388],"type":"Point"}
}