{
  "type": "Feature",
  "properties": {
    "addr:full":"3865 Hickory Hill Blvd Titusville FL 32780",
    "addr:housenumber":"3865",
    "addr:postcode":"32780",
    "addr:street":"Hickory Hill Blvd",
    "iso:country":"US",
    "sg:address":"3865 Hickory Hill Blvd",
    "sg:city":"Titusville",
    "sg:classifiers":[
        {
            "category":"Shopping",
            "subcategory":"Bicycles & Sporting Goods",
            "type":"Retail Goods"
        }
    ],
    "sg:phone":"+1 321 267 4461",
    "sg:postcode":"32780",
    "sg:province":"FL",
    "wof:name":"Florida Sport/Spiel",
    "wof:placetype":"venue"
},
  "geometry": {"coordinates":[-80.83920999999999,28.570002],"type":"Point"}
}