{
  "type": "Feature",
  "properties": {
    "addr:full":"115 S Dale Mabry Hwy Tampa FL 33609",
    "addr:housenumber":"115",
    "addr:postcode":"33609",
    "addr:street":"S Dale Mabry Hwy",
    "iso:country":"US",
    "sg:address":"115 S Dale Mabry Hwy",
    "sg:city":"Tampa",
    "sg:classifiers":[
        {
            "category":"Restaurant",
            "type":"Food & Drink"
        }
    ],
    "sg:menulink":"http://www.allmenus.com/fl/tampa/43113-honeybaked-ham/menu/",
    "sg:phone":"+1 813 874 6555",
    "sg:postcode":"33609",
    "sg:province":"FL",
    "sg:tags":[
        "american"
    ],
    "wof:name":"The HoneyBaked Ham Company",
    "wof:placetype":"venue"
},
  "geometry": {"coordinates":[-82.505695,27.943846],"type":"Point"}
}