{
  "type": "Feature",
  "properties": {
    "iso:country":"US",
    "sg:address":"1425 55th Ct SW",
    "sg:city":"Vero Beach",
    "sg:classifiers":[
        {
            "category":"Manufacturing",
            "subcategory":"Toys & Sporting Goods",
            "type":"Manufacturing & Wholesale Goods"
        }
    ],
    "sg:phone":"+1 772 778 9221",
    "sg:postcode":"32968",
    "sg:province":"FL",
    "sg:tags":[
        "mfg"
    ],
    "wof:name":"Team Deans USA Inc",
    "wof:placetype":"venue"
},
  "geometry": {"coordinates":[-80.44409899999999,27.578897],"type":"Point"}
}