{
  "type": "Feature",
  "properties": {
    "iso:country":"US",
    "sg:address":"2201 2nd St",
    "sg:city":"Fort Myers",
    "sg:classifiers":[
        {
            "category":"Professional",
            "subcategory":"Computer Services",
            "type":"Services"
        }
    ],
    "sg:phone":"+1 239 337 3434",
    "sg:postcode":"33901",
    "sg:province":"FL",
    "sg:tags":[
        "scanning",
        "code",
        "bar",
        "mfg",
        "dev",
        "licensed",
        "co"
    ],
    "sg:website":"www.neom.com",
    "wof:name":"Neo Media Technologies Inc",
    "wof:placetype":"venue"
},
  "geometry": {"coordinates":[-81.86867599999999,26.64249],"type":"Point"}
}