{
  "type": "Feature",
  "properties": {
    "iso:country":"US",
    "sg:address":"101 W 27th St",
    "sg:city":"Hialeah",
    "sg:classifiers":[
        {
            "category":"Community Center",
            "type":"Public Place"
        }
    ],
    "sg:phone":"+1 305 559 2881",
    "sg:postcode":"33010",
    "sg:province":"FL",
    "sg:tags":[
        "medical"
    ],
    "wof:name":"Leon Medical Center Inc",
    "wof:placetype":"venue"
},
  "geometry": {"coordinates":[-80.28426399999999,25.84643],"type":"Point"}
}