{
  "type": "Feature",
  "properties": {
    "iso:country":"US",
    "sg:address":"204 S Jackson Rd",
    "sg:city":"Venice",
    "sg:classifiers":[
        {
            "category":"Professional",
            "subcategory":"Accounting & Tax Preparation",
            "type":"Services"
        }
    ],
    "sg:phone":"+1 941 483 1077",
    "sg:postcode":"34292",
    "sg:province":"FL",
    "wof:name":"Bonnies Cmpterized Bookkeeping",
    "wof:placetype":"venue"
},
  "geometry": {"coordinates":[-82.36007499999999,27.099211],"type":"Point"}
}