{
  "type": "Feature",
  "properties": {
    "iso:country":"US",
    "sg:address":"9417 Buck Haven Trl",
    "sg:city":"Tallahassee",
    "sg:classifiers":[
        {
            "category":"Building & Trades",
            "subcategory":"Construction",
            "type":"Services"
        }
    ],
    "sg:phone":"+1 850 545 5215",
    "sg:postcode":"32312",
    "sg:province":"FL",
    "sg:tags":[
        "hanging",
        "painter",
        "contractor"
    ],
    "wof:name":"B & B Painting Inc",
    "wof:placetype":"venue"
},
  "geometry": {"coordinates":[-84.251476,30.601425],"type":"Point"}
}