{
  "type": "Feature",
  "properties": {
    "addr:full":"333 N Croft Ave Inverness FL 34453",
    "addr:housenumber":"333",
    "addr:postcode":"34453",
    "addr:street":"N Croft Ave",
    "iso:country":"US",
    "sg:address":"333 N Croft Ave",
    "sg:city":"Inverness",
    "sg:classifiers":[
        {
            "category":"Real Estate",
            "subcategory":"Real Estate Agent",
            "type":"Services"
        }
    ],
    "sg:phone":"+1 352 341 4663",
    "sg:postcode":"34453",
    "sg:province":"FL",
    "sg:tags":[
        "management"
    ],
    "wof:name":"Castro Realty & Property Mgmt",
    "wof:placetype":"venue"
},
  "geometry": {"coordinates":[-82.386015,28.866463],"type":"Point"}
}