{
  "type": "Feature",
  "properties": {
    "addr:full":"3515 del Prado Blvd S Cape Coral FL 33904",
    "addr:housenumber":"3515",
    "addr:postcode":"33904",
    "addr:street":"Del Prado Blvd S",
    "iso:country":"US",
    "sg:address":"3515 del Prado Blvd S",
    "sg:city":"Cape Coral",
    "sg:classifiers":[
        {
            "category":"Real Estate",
            "subcategory":"Real Estate Services",
            "type":"Services"
        }
    ],
    "sg:phone":"+1 239 945 6790",
    "sg:postcode":"33904",
    "sg:province":"FL",
    "sg:tags":[
        "company",
        "abstract",
        "title"
    ],
    "wof:name":"Fidelity National Title",
    "wof:placetype":"venue"
},
  "geometry": {"coordinates":[-81.94175300000001,26.58877],"type":"Point"}
}