{
  "type": "Feature",
  "properties": {
    "iso:country":"US",
    "sg:address":"10088 Boca Cir",
    "sg:city":"Naples",
    "sg:classifiers":[
        {
            "category":"Real Estate",
            "subcategory":"Real Estate Operator",
            "type":"Services"
        }
    ],
    "sg:phone":"+1 239 592 0285",
    "sg:postcode":"34109",
    "sg:province":"FL",
    "sg:tags":[
        "property",
        "lessor"
    ],
    "wof:name":"K & C Management",
    "wof:placetype":"venue"
},
  "geometry": {"coordinates":[-81.767866,26.262246],"type":"Point"}
}