{
  "type": "Feature",
  "properties": {
    "addr:full":"3520 Lewis Speedway St Augustine FL 32084",
    "addr:housenumber":"3520",
    "addr:postcode":"32084",
    "addr:street":"Lewis Speedway St",
    "iso:country":"US",
    "sg:address":"3520 Lewis Speedway",
    "sg:city":"St Augustine",
    "sg:classifiers":[
        {
            "category":"Building & Trades",
            "subcategory":"Construction",
            "type":"Services"
        }
    ],
    "sg:phone":"+1 904 829 3400",
    "sg:postcode":"32084",
    "sg:province":"FL",
    "sg:tags":[
        "utility",
        "contractor"
    ],
    "wof:name":"Jerry's Johns & Construction",
    "wof:placetype":"venue"
},
  "geometry": {"coordinates":[-81.34268299999999,29.929236],"type":"Point"}
}