{
  "type": "Feature",
  "properties": {
    "addr:full":"175 SW 120th Ave Miami FL 33184",
    "addr:housenumber":"175",
    "addr:postcode":"33184",
    "addr:street":"Sw 120Th Ave",
    "iso:country":"US",
    "sg:address":"175 SW 120th Ave",
    "sg:city":"Miami",
    "sg:classifiers":[
        {
            "category":"Organizations",
            "subcategory":"Religious Organization",
            "type":"Services"
        }
    ],
    "sg:phone":"+1 305 553 7546",
    "sg:postcode":"33184",
    "sg:province":"FL",
    "sg:tags":[
        "place",
        "worship",
        "church"
    ],
    "wof:name":"Iglesia Presbiteriana El Redentor",
    "wof:placetype":"venue"
},
  "geometry": {"coordinates":[-80.3908,25.766399],"type":"Point"}
}