{
  "type": "Feature",
  "properties": {
    "addr:full":"9000 SW 87th Ct Miami FL 33176",
    "addr:housenumber":"9000",
    "addr:postcode":"33176",
    "addr:street":"Sw 87Th Ct",
    "iso:country":"US",
    "sg:address":"9000 SW 87th Ct",
    "sg:city":"Miami",
    "sg:classifiers":[
        {
            "category":"Wholesale",
            "subcategory":"Durable Goods & Equipment",
            "type":"Manufacturing & Wholesale Goods"
        }
    ],
    "sg:phone":"+1 305 412 9825",
    "sg:postcode":"33176",
    "sg:province":"FL",
    "sg:tags":[
        "exporter"
    ],
    "wof:name":"Patrick H Heron Pa",
    "wof:placetype":"venue"
},
  "geometry": {"coordinates":[-80.335611,25.685567],"type":"Point"}
}