{
  "type": "Feature",
  "properties": {
    "addr:full":"2218 S Orange Ave Orlando FL 32806",
    "addr:housenumber":"2218",
    "addr:postcode":"32806",
    "addr:street":"S Orange Ave",
    "iso:country":"US",
    "sg:address":"2218 S Orange Ave",
    "sg:city":"Orlando",
    "sg:classifiers":[
        {
            "category":"Home & Garden",
            "subcategory":"Hardware",
            "type":"Retail Goods"
        }
    ],
    "sg:phone":"+1 407 422 7766",
    "sg:postcode":"32806",
    "sg:province":"FL",
    "sg:website":"www.acehardware.com",
    "wof:name":"Ace Hardware",
    "wof:placetype":"venue"
},
  "geometry": {"coordinates":[-81.376434,28.516743],"type":"Point"}
}