{
  "type": "Feature",
  "properties": {
    "iso:country":"US",
    "sg:address":"115 Lithia Pinecrest Rd Ste B",
    "sg:city":"Brandon",
    "sg:phone":"+1 813 662 2002",
    "sg:postcode":"33511",
    "sg:province":"FL",
    "sg:website":"http://tampabay.citysearch.com/profile/external/45205746/brandon_fl/the_comfort_zone_spa.html?publisher=yellowpages&reference_id=1&placement=ypwebsitemip",
    "wof:name":"The Comfort Zone Spa",
    "wof:placetype":"venue"
},
  "geometry": {"coordinates":[-82.280717,27.936505],"type":"Point"}
}