{
  "type": "Feature",
  "properties": {
    "iso:country":"US",
    "sg:address":"6043 Rich Farm Rd",
    "sg:city":"Tallahassee",
    "sg:classifiers":[
        {
            "category":"Wholesale",
            "subcategory":"Medical Equipment & Supplies",
            "type":"Manufacturing & Wholesale Goods"
        }
    ],
    "sg:phone":"+1 850 878 3652",
    "sg:postcode":"32317",
    "sg:province":"FL",
    "wof:name":"Keith Brice",
    "wof:placetype":"venue"
},
  "geometry": {"coordinates":[-84.173768,30.460942],"type":"Point"}
}