{
  "type": "Feature",
  "properties": {
    "iso:country":"US",
    "sg:address":"1463 Oakfield Dr",
    "sg:city":"Brandon",
    "sg:classifiers":[
        {
            "category":"Health Services",
            "subcategory":"Clinic",
            "type":"Services"
        }
    ],
    "sg:phone":"+1 813 651 4639",
    "sg:postcode":"33511",
    "sg:province":"FL",
    "sg:tags":[
        "home"
    ],
    "wof:name":"Amedisys Home Health Care",
    "wof:placetype":"venue"
},
  "geometry": {"coordinates":[-82.30536600000001,27.934025],"type":"Point"}
}