{
  "type": "Feature",
  "properties": {
    "iso:country":"US",
    "sg:address":"1433 NW 55th Ter",
    "sg:city":"Miami",
    "sg:classifiers":[
        {
            "category":"Building & Trades",
            "subcategory":"Landscaping Services",
            "type":"Services"
        },
        {
            "category":"Social Services",
            "subcategory":"Retirement Home",
            "type":"Services"
        }
    ],
    "sg:phone":"+1 305 967 8484",
    "sg:postcode":"33142",
    "sg:province":"FL",
    "sg:tags":[
        "living",
        "nursing",
        "facility",
        "assisted",
        "convalescent",
        "homes-institutional",
        "aged"
    ],
    "wof:name":"Magnet Assisted Living Facility",
    "wof:placetype":"venue"
},
  "geometry": {"coordinates":[-80.22116200000001,25.826054],"type":"Point"}
}