{
  "type": "Feature",
  "properties": {
    "iso:country":"US",
    "sg:address":"607 Majorca Ave",
    "sg:city":"Coral Gables",
    "sg:classifiers":[
        {
            "category":"Health Services",
            "subcategory":"Doctor",
            "type":"Services"
        }
    ],
    "sg:phone":"+1 863 688 9001",
    "sg:postcode":"33134",
    "sg:province":"FL",
    "sg:tags":[
        "dentist"
    ],
    "wof:name":"William Nerestant DDS",
    "wof:placetype":"venue"
},
  "geometry": {"coordinates":[-80.269041,25.754622],"type":"Point"}
}