{
  "type": "Feature",
  "properties": {
    "iso:country":"US",
    "sg:address":"2553 25th Ave N",
    "sg:city":"Saint Petersburg",
    "sg:classifiers":[
        {
            "category":"Building & Trades",
            "subcategory":"Pest Control",
            "type":"Services"
        }
    ],
    "sg:phone":"+1 727 527 5831",
    "sg:postcode":"33713",
    "sg:province":"FL",
    "wof:name":"Terminix",
    "wof:placetype":"venue"
},
  "geometry": {"coordinates":[-82.667896,27.794762],"type":"Point"}
}