{
  "type": "Feature",
  "properties": {
    "iso:country":"US",
    "sg:address":"1111 Crandon Blvd",
    "sg:city":"Key Biscayne",
    "sg:classifiers":[
        {
            "category":"Health Services",
            "subcategory":"Doctor",
            "type":"Services"
        }
    ],
    "sg:phone":"+1 305 361 7218",
    "sg:postcode":"33149",
    "sg:province":"FL",
    "sg:tags":[
        "physician",
        "surgeon"
    ],
    "wof:name":"D Geraint James MD",
    "wof:placetype":"venue"
},
  "geometry": {"coordinates":[-80.158385,25.683427],"type":"Point"}
}