{
  "type": "Feature",
  "properties": {
    "iso:country":"US",
    "sg:address":"1467 SW 17th Ave",
    "sg:city":"Ocala",
    "sg:classifiers":[
        {
            "category":"Home & Garden",
            "subcategory":"Building Materials",
            "type":"Retail Goods"
        }
    ],
    "sg:phone":"+1 352 867 1288",
    "sg:postcode":"34471",
    "sg:province":"FL",
    "sg:tags":[
        "roofing"
    ],
    "sg:website":"www.abcsupply.com",
    "wof:name":"ABC Supply Co",
    "wof:placetype":"venue"
},
  "geometry": {"coordinates":[-82.15405,29.175238],"type":"Point"}
}