{
  "type": "Feature",
  "properties": {
    "addr:full":"1400 Pinehurst Dr Spring Hill FL 34606",
    "addr:housenumber":"1400",
    "addr:postcode":"34606",
    "addr:street":"Pinehurst Dr",
    "iso:country":"US",
    "sg:address":"1400 Pinehurst Dr",
    "sg:city":"Spring Hill",
    "sg:classifiers":[
        {
            "category":"Food & Beverages",
            "subcategory":"Groceries & Convenience Stores",
            "type":"Retail Goods"
        }
    ],
    "sg:phone":"+1 352 683 6040",
    "sg:postcode":"34606",
    "sg:province":"FL",
    "sg:tags":[
        "supermarket"
    ],
    "wof:name":"Publix",
    "wof:placetype":"venue"
},
  "geometry": {"coordinates":[-82.625649,28.460334],"type":"Point"}
}