{
  "type": "Feature",
  "properties": {
    "iso:country":"US",
    "sg:address":"6520 Pinecastle Blvd Ste A",
    "sg:city":"Orlando",
    "sg:classifiers":[
        {
            "category":"Place Of Worship",
            "subcategory":"Church",
            "type":"Public Place"
        }
    ],
    "sg:phone":"+1 407 812 8571",
    "sg:postcode":"32809",
    "sg:province":"FL",
    "sg:tags":[
        "churches-christian-reformed"
    ],
    "wof:name":"Luctor International",
    "wof:placetype":"venue"
},
  "geometry": {"coordinates":[-81.368759,28.46249],"type":"Point"}
}