{
  "type": "Feature",
  "properties": {
    "iso:country":"US",
    "sg:address":"102 Pebble Shores Dr",
    "sg:city":"Naples",
    "sg:classifiers":[
        {
            "category":"Retail",
            "subcategory":"Car Wash",
            "type":"Services"
        }
    ],
    "sg:phone":"+1 239 596 2364",
    "sg:postcode":"34110",
    "sg:province":"FL",
    "sg:tags":[
        "carwash"
    ],
    "wof:name":"5 Minute Quick Dating",
    "wof:placetype":"venue"
},
  "geometry": {"coordinates":[-81.774772,26.276803],"type":"Point"}
}