{
  "type": "Feature",
  "properties": {
    "addr:full":"1020 Lakeside Dr Brooksville FL 34601",
    "addr:housenumber":"1020",
    "addr:postcode":"34601",
    "addr:street":"Lakeside Dr",
    "iso:country":"US",
    "sg:address":"1020 Lakeside Dr",
    "sg:city":"Brooksville",
    "sg:classifiers":[
        {
            "category":"Real Estate",
            "subcategory":"Real Estate Operator",
            "type":"Services"
        }
    ],
    "sg:phone":"+1 352 796 4600",
    "sg:postcode":"34601",
    "sg:province":"FL",
    "sg:tags":[
        "mobile",
        "home",
        "site",
        "community"
    ],
    "wof:name":"Lakeside Mobile Manor Inc",
    "wof:placetype":"venue"
},
  "geometry": {"coordinates":[-82.37517800000001,28.572878],"type":"Point"}
}