{
  "type": "Feature",
  "properties": {
    "addr:full":"10055 N Dale Mabry Hwy Tampa FL 33618",
    "addr:housenumber":"10055",
    "addr:postcode":"33618",
    "addr:street":"N Dale Mabry Hwy",
    "iso:country":"US",
    "sg:address":"10055 N Dale Mabry Hwy",
    "sg:city":"Tampa",
    "sg:classifiers":[
        {
            "category":"Retail",
            "subcategory":"Laundry & Dry Cleaning",
            "type":"Services"
        }
    ],
    "sg:phone":"+1 813 961 2524",
    "sg:postcode":"33618",
    "sg:province":"FL",
    "wof:name":"Imperial Cleaners",
    "wof:placetype":"venue"
},
  "geometry": {"coordinates":[-82.504616,28.042746],"type":"Point"}
}