{
  "type": "Feature",
  "properties": {
    "addr:full":"1924 Travelers Palm Dr Edgewater FL 32141",
    "addr:housenumber":"1924",
    "addr:postcode":"32141",
    "addr:street":"Travelers Palm Dr",
    "iso:country":"US",
    "sg:address":"1924 Travelers Palm Dr",
    "sg:city":"Edgewater",
    "sg:classifiers":[
        {
            "category":"Shopping",
            "subcategory":"Used Merchandise",
            "type":"Retail Goods"
        }
    ],
    "sg:phone":"+1 386 428 1579",
    "sg:postcode":"32141",
    "sg:province":"FL",
    "sg:tags":[
        "antique"
    ],
    "wof:name":"North & South Exchange",
    "wof:placetype":"venue"
},
  "geometry": {"coordinates":[-80.911917,28.96278],"type":"Point"}
}