{
  "type": "Feature",
  "properties": {
    "addr:full":"1336 E Vine St Kissimmee FL 34744",
    "addr:housenumber":"1336",
    "addr:postcode":"34744",
    "addr:street":"E Vine St",
    "iso:country":"US",
    "sg:address":"1336 E Vine St",
    "sg:city":"Kissimmee",
    "sg:phone":"+1 407 518 0111",
    "sg:postcode":"34744",
    "sg:province":"FL",
    "wof:name":"Iglesia Jscristo Camino De Luz",
    "wof:placetype":"venue"
},
  "geometry": {"coordinates":[-81.38922599999999,28.304177],"type":"Point"}
}