{
  "type": "Feature",
  "properties": {
    "addr:full":"8900 Deer Ln Navarre FL 32566",
    "addr:housenumber":"8900",
    "addr:postcode":"32566",
    "addr:street":"Deer Ln",
    "iso:country":"US",
    "sg:address":"8900 Deer Ln",
    "sg:city":"Navarre",
    "sg:classifiers":[
        {
            "category":"Building & Trades",
            "subcategory":"Construction",
            "type":"Services"
        }
    ],
    "sg:phone":"+1 850 585 2102",
    "sg:postcode":"32566",
    "sg:province":"FL",
    "sg:tags":[
        "painter"
    ],
    "wof:name":"Robert Hill Painting",
    "wof:placetype":"venue"
},
  "geometry": {"coordinates":[-86.84764699999999,30.421003],"type":"Point"}
}