{
  "type": "Feature",
  "properties": {
    "iso:country":"US",
    "sg:address":"4012 Cortez Rd W",
    "sg:city":"Bradenton",
    "sg:classifiers":[
        {
            "category":"Professional",
            "type":"Services"
        }
    ],
    "sg:phone":"+1 941 758 2225",
    "sg:postcode":"34210",
    "sg:province":"FL",
    "sg:tags":[
        "establishment"
    ],
    "wof:name":"Gallmeyer & Assoc",
    "wof:placetype":"venue"
},
  "geometry": {"coordinates":[-82.603475,27.462605],"type":"Point"}
}