{
  "type": "Feature",
  "properties": {
    "addr:full":"4165 49th Ave S St Petersburg FL 33711",
    "addr:housenumber":"4165",
    "addr:postcode":"33711",
    "addr:street":"49Th Ave S",
    "iso:country":"US",
    "sg:address":"4165 49th Ave S",
    "sg:city":"St Petersburg",
    "sg:classifiers":[
        {
            "category":"Shopping",
            "subcategory":"Discount & Variety Stores",
            "type":"Retail Goods"
        }
    ],
    "sg:phone":"+1 727 867 7777",
    "sg:postcode":"33711",
    "sg:province":"FL",
    "sg:tags":[
        "merchandise",
        "general"
    ],
    "wof:name":"Diamond Supply & Fastener",
    "wof:placetype":"venue"
},
  "geometry": {"coordinates":[-82.690349,27.723937],"type":"Point"}
}