{
  "type": "Feature",
  "properties": {
    "addr:full":"5507 Fulmar Dr Tampa FL 33625",
    "addr:housenumber":"5507",
    "addr:postcode":"33625",
    "addr:street":"Fulmar Dr",
    "iso:country":"US",
    "sg:address":"5507 Fulmar Dr",
    "sg:city":"Tampa",
    "sg:classifiers":[
        {
            "category":"Building & Trades",
            "subcategory":"Plumbing",
            "type":"Services"
        }
    ],
    "sg:phone":"+1 813 265 9385",
    "sg:postcode":"33625",
    "sg:province":"FL",
    "sg:tags":[
        "plumbing",
        "contractor"
    ],
    "wof:name":"Odell Pembelton",
    "wof:placetype":"venue"
},
  "geometry": {"coordinates":[-82.554255,28.081676],"type":"Point"}
}