{
  "type": "Feature",
  "properties": {
    "addr:full":"420 W State Rd 434 Longwood FL 32750",
    "addr:housenumber":"420;434",
    "addr:postcode":"32750",
    "addr:street":"W State Rd",
    "iso:country":"US",
    "sg:address":"420 W State Rd 434",
    "sg:city":"Longwood",
    "sg:classifiers":[
        {
            "category":"Shopping",
            "subcategory":"Hobbies, Toys, & Games",
            "type":"Retail Goods"
        }
    ],
    "sg:phone":"+1 407 339 0202",
    "sg:postcode":"32750",
    "sg:province":"FL",
    "wof:name":"Farpoint Toys & Collectibles",
    "wof:placetype":"venue"
},
  "geometry": {"coordinates":[-81.35222400000001,28.697729],"type":"Point"}
}