{
  "type": "Feature",
  "properties": {
    "iso:country":"US",
    "sg:address":"9766 Old Saint Augustine Rd",
    "sg:city":"Jacksonville",
    "sg:classifiers":[
        {
            "category":"Retail",
            "subcategory":"Laundry & Dry Cleaning",
            "type":"Services"
        }
    ],
    "sg:phone":"+1 904 262 7476",
    "sg:postcode":"32257",
    "sg:province":"FL",
    "sg:tags":[
        "drycleaning",
        "plant",
        "cleaners"
    ],
    "wof:name":"A & H Cleaners",
    "wof:placetype":"venue"
},
  "geometry": {"coordinates":[-81.61527,30.199705],"type":"Point"}
}