{
  "type": "Feature",
  "properties": {
    "addr:full":"1801 N Powers Dr Orlando FL 32818",
    "addr:housenumber":"1801",
    "addr:postcode":"32818",
    "addr:street":"N Powers Dr",
    "iso:country":"US",
    "sg:address":"1801 N Powers Dr",
    "sg:city":"Orlando",
    "sg:classifiers":[
        {
            "category":"Building & Trades",
            "subcategory":"Construction",
            "type":"Services"
        }
    ],
    "sg:phone":"+1 407 295 8868",
    "sg:postcode":"32818",
    "sg:province":"FL",
    "sg:tags":[
        "house"
    ],
    "wof:name":"Lambert Wright Handyman Svc",
    "wof:placetype":"venue"
},
  "geometry": {"coordinates":[-81.467663,28.564607],"type":"Point"}
}