{
  "type": "Feature",
  "properties": {
    "addr:full":"227 Olson Ave Fort Pierce FL 34946",
    "addr:housenumber":"227",
    "addr:postcode":"34946",
    "addr:street":"Olson Ave",
    "iso:country":"US",
    "sg:address":"227 Olson Ave",
    "sg:city":"Fort Pierce",
    "sg:classifiers":[
        {
            "category":"Farming",
            "subcategory":"Fish & Marine Products",
            "type":"Manufacturing & Wholesale Goods"
        }
    ],
    "sg:phone":"+1 772 216 7940",
    "sg:postcode":"34946",
    "sg:province":"FL",
    "sg:tags":[
        "management"
    ],
    "wof:name":"Nuisance Ctrl By Jack Spivey",
    "wof:placetype":"venue"
},
  "geometry": {"coordinates":[-80.33803899999999,27.481859],"type":"Point"}
}