{
  "type": "Feature",
  "properties": {
    "addr:full":"4550 J Stenger Rd Bartow FL 33830",
    "addr:housenumber":"4550",
    "addr:postcode":"33830",
    "addr:street":"J Stenger Rd",
    "iso:country":"US",
    "sg:address":"4550 J Stenger Rd",
    "sg:city":"Bartow",
    "sg:classifiers":[
        {
            "category":"Farming",
            "subcategory":"Orchard",
            "type":"Manufacturing & Wholesale Goods"
        }
    ],
    "sg:phone":"+1 863 537 1443",
    "sg:postcode":"33830",
    "sg:province":"FL",
    "wof:name":"Stenger Grove Service Inc",
    "wof:placetype":"venue"
},
  "geometry": {"coordinates":[-81.769899,27.871877],"type":"Point"}
}