{
  "type": "Feature",
  "properties": {
    "addr:full":"1609 Crabapple Cove Ct N Jacksonville FL 32225",
    "addr:housenumber":"1609",
    "addr:postcode":"32225",
    "addr:street":"Crabapple Cove Ct N",
    "iso:country":"US",
    "sg:address":"1609 Crabapple Cove Ct N",
    "sg:city":"Jacksonville",
    "sg:classifiers":[
        {
            "category":"Communications",
            "subcategory":"Film & Video Production",
            "type":"Services"
        }
    ],
    "sg:phone":"+1 904 564 2356",
    "sg:postcode":"32225",
    "sg:province":"FL",
    "sg:tags":[
        "motion"
    ],
    "wof:name":"Shattered Ceiling Productions",
    "wof:placetype":"venue"
},
  "geometry": {"coordinates":[-81.490605,30.354281],"type":"Point"}
}