{
  "type": "Feature",
  "properties": {
    "addr:full":"221 N Disston Ave Clermont FL 34711",
    "addr:housenumber":"221",
    "addr:postcode":"34711",
    "addr:street":"N Disston Ave",
    "iso:country":"US",
    "sg:address":"221 N Disston Ave",
    "sg:city":"Clermont",
    "sg:classifiers":[
        {
            "category":"Banks & Credit Unions",
            "subcategory":"Financial Services",
            "type":"Services"
        }
    ],
    "sg:phone":"+1 352 394 8920",
    "sg:postcode":"34711",
    "sg:province":"FL",
    "sg:tags":[
        "trust",
        "management"
    ],
    "wof:name":"Birth Trust Doula Services",
    "wof:placetype":"venue"
},
  "geometry": {"coordinates":[-81.74996899999999,28.566445],"type":"Point"}
}