{
  "type": "Feature",
  "properties": {
    "addr:full":"1036 Silcox Branch Cir Oviedo FL 32765",
    "addr:housenumber":"1036",
    "addr:postcode":"32765",
    "addr:street":"Silcox Branch Cir",
    "iso:country":"US",
    "sg:address":"1036 Silcox Branch Cir",
    "sg:city":"Oviedo",
    "sg:classifiers":[
        {
            "category":"Building & Trades",
            "subcategory":"Pest Control",
            "type":"Services"
        }
    ],
    "sg:phone":"+1 407 359 9784",
    "sg:postcode":"32765",
    "sg:province":"FL",
    "wof:name":"Connors Pest & Termite Control",
    "wof:placetype":"venue"
},
  "geometry": {"coordinates":[-81.18426599999999,28.651611],"type":"Point"}
}