{
  "type": "Feature",
  "properties": {
    "iso:country":"US",
    "sg:address":"2790 Regal Ln",
    "sg:city":"Oviedo",
    "sg:classifiers":[
        {
            "category":"Professional",
            "subcategory":"Detective & Security Services",
            "type":"Services"
        }
    ],
    "sg:phone":"+1 407 921 5881",
    "sg:postcode":"32765",
    "sg:province":"FL",
    "sg:tags":[
        "information",
        "bureau"
    ],
    "wof:name":"Perry S Pool Service Inc",
    "wof:placetype":"venue"
},
  "geometry": {"coordinates":[-81.262489,28.620116],"type":"Point"}
}