{
  "type": "Feature",
  "properties": {
    "iso:country":"US",
    "sg:address":"10420 Lafoy Rd",
    "sg:city":"Spring Hill",
    "sg:classifiers":[
        {
            "category":"Building & Trades",
            "subcategory":"Construction",
            "type":"Services"
        }
    ],
    "sg:phone":"+1 352 666 5039",
    "sg:postcode":"34608",
    "sg:province":"FL",
    "sg:tags":[
        "house"
    ],
    "wof:name":"Robert Lanigan",
    "wof:placetype":"venue"
},
  "geometry": {"coordinates":[-82.54665300000001,28.476841],"type":"Point"}
}