{
  "type": "Feature",
  "properties": {
    "addr:full":"1910 N Himes Ave Tampa FL 33607",
    "addr:housenumber":"1910",
    "addr:postcode":"33607",
    "addr:street":"N Himes Ave",
    "iso:country":"US",
    "sg:address":"1910 N Himes Ave",
    "sg:city":"Tampa",
    "sg:classifiers":[
        {
            "category":"Personal",
            "subcategory":"Shoe Repair & Shine",
            "type":"Services"
        }
    ],
    "sg:phone":"+1 813 877 4312",
    "sg:postcode":"33607",
    "sg:province":"FL",
    "sg:tags":[
        "repairing",
        "boot"
    ],
    "wof:name":"A Express Shoe Repair",
    "wof:placetype":"venue"
},
  "geometry": {"coordinates":[-82.50149500000001,27.959344],"type":"Point"}
}