{
  "type": "Feature",
  "properties": {
    "addr:full":"21 W University Ave Gainesville FL 32601",
    "addr:housenumber":"21",
    "addr:postcode":"32601",
    "addr:street":"W University Ave",
    "iso:country":"US",
    "sg:address":"21 W University Ave",
    "sg:city":"Gainesville",
    "sg:classifiers":[
        {
            "category":"Deli",
            "type":"Food & Drink"
        }
    ],
    "sg:menulink":"http://www.allmenus.com/fl/gainesville/62989-jeffs-deli/menu/",
    "sg:phone":"+1 352 505 0224",
    "sg:postcode":"32601",
    "sg:province":"FL",
    "sg:tags":[
        "american"
    ],
    "wof:name":"Jeff's Deli",
    "wof:placetype":"venue"
},
  "geometry": {"coordinates":[-82.325203,29.651955],"type":"Point"}
}