{
  "type": "Feature",
  "properties": {
    "iso:country":"US",
    "sg:address":"112 E Maple St",
    "sg:city":"Winter Garden",
    "sg:classifiers":[
        {
            "category":"Building & Trades",
            "subcategory":"Cleaning & Sanitation",
            "type":"Services"
        }
    ],
    "sg:phone":"+1 407 877 7738",
    "sg:postcode":"34787",
    "sg:province":"FL",
    "sg:tags":[
        "house"
    ],
    "wof:name":"Cottage Care",
    "wof:placetype":"venue"
},
  "geometry": {"coordinates":[-81.583253,28.561971],"type":"Point"}
}