{
  "type": "Feature",
  "properties": {
    "addr:full":"144 S Halifax Ave Daytona Beach FL 32118",
    "addr:housenumber":"144",
    "addr:postcode":"32118",
    "addr:street":"S Halifax Ave",
    "iso:country":"US",
    "sg:address":"144 S Halifax Ave",
    "sg:city":"Daytona Beach",
    "sg:classifiers":[
        {
            "category":"Real Estate",
            "subcategory":"Real Estate Operator",
            "type":"Services"
        }
    ],
    "sg:phone":"+1 386 257 5759",
    "sg:postcode":"32118",
    "sg:province":"FL",
    "sg:tags":[
        "building",
        "nonresidential"
    ],
    "wof:name":"Sun Properties LLC",
    "wof:placetype":"venue"
},
  "geometry": {"coordinates":[-81.01176700000001,29.221143],"type":"Point"}
}