{
  "type": "Feature",
  "properties": {
    "iso:country":"US",
    "sg:address":"2447 N Wickham Rd",
    "sg:city":"Melbourne",
    "sg:classifiers":[
        {
            "category":"Shopping",
            "subcategory":"Clothing, Apparel, & Fashions",
            "type":"Retail Goods"
        }
    ],
    "sg:phone":"+1 321 259 7059",
    "sg:postcode":"32935",
    "sg:province":"FL",
    "sg:tags":[
        "shop",
        "consignment",
        "accessory"
    ],
    "wof:name":"Tulip Trunk",
    "wof:placetype":"venue"
},
  "geometry": {"coordinates":[-80.671747,28.148448],"type":"Point"}
}