{
  "type": "Feature",
  "properties": {
    "addr:full":"9592 Parksouth Ct Orlando FL 32837",
    "addr:housenumber":"9592",
    "addr:postcode":"32837",
    "addr:street":"Parksouth Ct",
    "iso:country":"US",
    "sg:address":"9592 Parksouth Ct",
    "sg:city":"Orlando",
    "sg:classifiers":[
        {
            "category":"Home & Garden",
            "subcategory":"Building Materials",
            "type":"Retail Goods"
        }
    ],
    "sg:phone":"+1 407 852 1460",
    "sg:postcode":"32837",
    "sg:province":"FL",
    "sg:tags":[
        "paint"
    ],
    "sg:website":"www.benjaminmoore.com",
    "wof:name":"Benjamin Moore Paints",
    "wof:placetype":"venue"
},
  "geometry": {"coordinates":[-81.413867,28.42818],"type":"Point"}
}