{
  "type": "Feature",
  "properties": {
    "addr:full":"1295 S Scenic Hwy Lake Wales FL 33898",
    "addr:housenumber":"1295",
    "addr:postcode":"33898",
    "addr:street":"S Scenic Hwy",
    "iso:country":"US",
    "sg:address":"1295 S Scenic Hwy",
    "sg:city":"Lake Wales",
    "sg:classifiers":[
        {
            "category":"Organizations",
            "subcategory":"Religious Organization",
            "type":"Services"
        }
    ],
    "sg:phone":"+1 863 638 1654",
    "sg:postcode":"33898",
    "sg:province":"FL",
    "sg:tags":[
        "church"
    ],
    "wof:name":"First Christian Church",
    "wof:placetype":"venue"
},
  "geometry": {"coordinates":[-81.58128499999999,27.876751],"type":"Point"}
}