{
  "type": "Feature",
  "properties": {
    "addr:full":"4774 Belden Cir Palm Harbor FL 34685",
    "addr:housenumber":"4774",
    "addr:postcode":"34685",
    "addr:street":"Belden Cir",
    "iso:country":"US",
    "sg:address":"4774 Belden Cir",
    "sg:city":"Palm Harbor",
    "sg:classifiers":[
        {
            "category":"Organizations",
            "subcategory":"Labor Organization",
            "type":"Services"
        }
    ],
    "sg:phone":"+1 727 934 4904",
    "sg:postcode":"34685",
    "sg:province":"FL",
    "sg:tags":[
        "real estate"
    ],
    "wof:name":"Amalgamated M&S Enterprises",
    "wof:placetype":"venue"
},
  "geometry": {"coordinates":[-82.697132,28.118899],"type":"Point"}
}