{
  "type": "Feature",
  "properties": {
    "iso:country":"US",
    "sg:address":"2705 Gettysburg Dr",
    "sg:city":"Titusville",
    "sg:classifiers":[
        {
            "category":"Building & Trades",
            "subcategory":"Construction",
            "type":"Services"
        }
    ],
    "sg:phone":"+1 407 748 0685",
    "sg:postcode":"32780",
    "sg:province":"FL",
    "sg:tags":[
        "handyman"
    ],
    "wof:name":"Servi-Man Handyman",
    "wof:placetype":"venue"
},
  "geometry": {"coordinates":[-80.80994699999999,28.585381],"type":"Point"}
}