{
  "type": "Feature",
  "properties": {
    "iso:country":"US",
    "sg:address":"144 Nw 37 street",
    "sg:city":"Miami",
    "sg:classifiers":[
        {
            "category":"Personal",
            "type":"Services"
        }
    ],
    "sg:phone":"+1 305 972 5924",
    "sg:postcode":"33127",
    "sg:province":"FL",
    "sg:tags":[
        "local"
    ],
    "sg:website":"www.rentwarehousemiami.wordpress...",
    "wof:name":"Rent Warehouse Miami- Penta Studios",
    "wof:placetype":"venue"
},
  "geometry": {"coordinates":[-80.198432,25.811054],"type":"Point"}
}