{
  "type": "Feature",
  "properties": {
    "iso:country":"US",
    "sg:address":"2204 Jessa Dr",
    "sg:city":"Kissimmee",
    "sg:classifiers":[
        {
            "category":"Freight",
            "type":"Transportation"
        }
    ],
    "sg:phone":"+1 407 344 8084",
    "sg:postcode":"34743",
    "sg:province":"FL",
    "sg:tags":[
        "local",
        "storage",
        "trucking"
    ],
    "wof:name":"Deltor Ismael",
    "wof:placetype":"venue"
},
  "geometry": {"coordinates":[-81.347977,28.311952],"type":"Point"}
}