{
  "type": "Feature",
  "properties": {
    "addr:full":"1601 W Garden St Pensacola FL 32501",
    "addr:housenumber":"1601",
    "addr:postcode":"32501",
    "addr:street":"W Garden St",
    "iso:country":"US",
    "sg:address":"1601 W Garden St",
    "sg:city":"Pensacola",
    "sg:classifiers":[
        {
            "category":"Professional",
            "subcategory":"Accounting & Tax Preparation",
            "type":"Services"
        }
    ],
    "sg:phone":"+1 850 438 1122",
    "sg:postcode":"32501",
    "sg:province":"FL",
    "sg:tags":[
        "accountant",
        "return"
    ],
    "wof:name":"Wade Wilson CPA PA",
    "wof:placetype":"venue"
},
  "geometry": {"coordinates":[-87.23621,30.411628],"type":"Point"}
}