{
  "type": "Feature",
  "properties": {
    "iso:country":"US",
    "sg:address":"1880 Saha Ct",
    "sg:city":"Kissimmee",
    "sg:classifiers":[
        {
            "category":"Retail",
            "subcategory":"Laundry & Dry Cleaning",
            "type":"Services"
        }
    ],
    "sg:phone":"+1 407 933 6572",
    "sg:postcode":"34744",
    "sg:province":"FL",
    "sg:tags":[
        "floor",
        "laying",
        "contractor"
    ],
    "wof:name":"Carpet Plus Inc",
    "wof:placetype":"venue"
},
  "geometry": {"coordinates":[-81.38271400000001,28.251623],"type":"Point"}
}