{
  "type": "Feature",
  "properties": {
    "addr:full":"17790 Collins Ave Sunny Isles Beach FL 33160",
    "addr:housenumber":"17790",
    "addr:postcode":"33160",
    "addr:street":"Collins Ave",
    "iso:country":"US",
    "sg:address":"17790 Collins Ave",
    "sg:city":"Sunny Isles Beach",
    "sg:classifiers":[
        {
            "category":"Food & Beverages",
            "subcategory":"Groceries & Convenience Stores",
            "type":"Retail Goods"
        }
    ],
    "sg:phone":"+1 305 932 0625",
    "sg:postcode":"33160",
    "sg:province":"FL",
    "sg:website":"7-eleven.com",
    "wof:name":"7-Eleven",
    "wof:placetype":"venue"
},
  "geometry": {"coordinates":[-80.12178900000001,25.941062],"type":"Point"}
}