{
  "type": "Feature",
  "properties": {
    "iso:country":"US",
    "sg:address":"10153 Rina Dr",
    "sg:city":"Jacksonville",
    "sg:classifiers":[
        {
            "category":"Wholesale",
            "subcategory":"Electrical",
            "type":"Manufacturing & Wholesale Goods"
        }
    ],
    "sg:phone":"+1 904 260 3141",
    "sg:postcode":"32257",
    "sg:province":"FL",
    "sg:tags":[
        "alarm",
        "burglar",
        "system"
    ],
    "wof:name":"Jentech Alarms",
    "wof:placetype":"venue"
},
  "geometry": {"coordinates":[-81.584504,30.194632],"type":"Point"}
}