{
  "type": "Feature",
  "properties": {
    "iso:country":"US",
    "sg:address":"9465 Cowpen Branch Rd",
    "sg:city":"Hastings",
    "sg:classifiers":[
        {
            "category":"Recreation",
            "type":"Entertainment"
        }
    ],
    "sg:phone":"+1 904 692 3765",
    "sg:postcode":"32145",
    "sg:province":"FL",
    "sg:tags":[
        "stable"
    ],
    "wof:name":"Lone Palm Ranch",
    "wof:placetype":"venue"
},
  "geometry": {"coordinates":[-81.453873,29.70394],"type":"Point"}
}