{
  "type": "Feature",
  "properties": {
    "iso:country":"US",
    "sg:address":"2051 Cheryl Dr",
    "sg:city":"Clearwater",
    "sg:classifiers":[
        {
            "category":"Shopping",
            "subcategory":"Florist",
            "type":"Retail Goods"
        }
    ],
    "sg:phone":"+1 727 712 9743",
    "sg:postcode":"33763",
    "sg:province":"FL",
    "wof:name":"True Blue of Pinellas Inc",
    "wof:placetype":"venue"
},
  "geometry": {"coordinates":[-82.74552,27.995731],"type":"Point"}
}