{
  "type": "Feature",
  "properties": {
    "addr:full":"522 W 79th Pl Hialeah FL 33014",
    "addr:housenumber":"522",
    "addr:postcode":"33014",
    "addr:street":"W 79Th Pl",
    "iso:country":"US",
    "sg:address":"522 W 79th Pl",
    "sg:city":"Hialeah",
    "sg:classifiers":[
        {
            "category":"Retail",
            "subcategory":"Repair Shop",
            "type":"Services"
        }
    ],
    "sg:phone":"+1 305 828 8224",
    "sg:postcode":"33014",
    "sg:province":"FL",
    "wof:name":"Anteros Business Machines",
    "wof:placetype":"venue"
},
  "geometry": {"coordinates":[-80.294331,25.894905],"type":"Point"}
}