{
  "type": "Feature",
  "properties": {
    "addr:full":"14606 Indian Ridge Trl Clermont FL 34711",
    "addr:housenumber":"14606",
    "addr:postcode":"34711",
    "addr:street":"Indian Ridge Trl",
    "iso:country":"US",
    "sg:address":"14606 Indian Ridge Trl",
    "sg:city":"Clermont",
    "sg:classifiers":[
        {
            "category":"Wholesale",
            "subcategory":"Auto Parts",
            "type":"Manufacturing & Wholesale Goods"
        }
    ],
    "sg:phone":"+1 352 241 8520",
    "sg:postcode":"34711",
    "sg:province":"FL",
    "wof:name":"Central Florida Paintworks",
    "wof:placetype":"venue"
},
  "geometry": {"coordinates":[-81.697141,28.560055],"type":"Point"}
}