{
  "type": "Feature",
  "properties": {
    "iso:country":"US",
    "sg:address":"1406 Co Rd 17 N",
    "sg:city":"Lake Placid",
    "sg:classifiers":[
        {
            "category":"Farming",
            "subcategory":"Farm",
            "type":"Manufacturing & Wholesale Goods"
        }
    ],
    "sg:phone":"+1 863 465 2195",
    "sg:postcode":"33852",
    "sg:province":"FL",
    "sg:tags":[
        "crop",
        "general"
    ],
    "wof:name":"Smith Farms",
    "wof:placetype":"venue"
},
  "geometry": {"coordinates":[-81.365898,27.309893],"type":"Point"}
}