{
  "type": "Feature",
  "properties": {
    "addr:full":"2160 Americana Blvd Orlando FL 32839",
    "addr:housenumber":"2160",
    "addr:postcode":"32839",
    "addr:street":"Americana Blvd",
    "iso:country":"US",
    "sg:address":"2160 Americana Blvd",
    "sg:city":"Orlando",
    "sg:classifiers":[
        {
            "category":"Autos & Motor Vehicles",
            "subcategory":"Fuel & Gas Station",
            "type":"Retail Goods"
        }
    ],
    "sg:phone":"+1 407 852 1212",
    "sg:postcode":"32839",
    "sg:province":"FL",
    "sg:tags":[
        "grocery",
        "oil",
        "store"
    ],
    "sg:website":"http://www.chevron.com",
    "wof:name":"Americana Chevron",
    "wof:placetype":"venue"
},
  "geometry": {"coordinates":[-81.407203,28.486453],"type":"Point"}
}