{
  "type": "Feature",
  "properties": {
    "iso:country":"US",
    "sg:address":"23375 Janice Ave",
    "sg:city":"Port Charlotte",
    "sg:classifiers":[
        {
            "category":"Manufacturing",
            "subcategory":"Apparel",
            "type":"Manufacturing & Wholesale Goods"
        }
    ],
    "sg:phone":"+1 941 629 1313",
    "sg:postcode":"33980",
    "sg:province":"FL",
    "sg:tags":[
        "canvas",
        "upholstery",
        "mfg",
        "household",
        "marine",
        "boat"
    ],
    "wof:name":"Custom Boat Tops Inc",
    "wof:placetype":"venue"
},
  "geometry": {"coordinates":[-82.06089799999999,26.966801],"type":"Point"}
}