{
  "type": "Feature",
  "properties": {
    "iso:country":"US",
    "sg:address":"7290 SW 168th St",
    "sg:city":"Palmetto Bay",
    "sg:classifiers":[
        {
            "category":"Organizations",
            "subcategory":"Religious Organization",
            "type":"Services"
        }
    ],
    "sg:phone":"+1 786 573 0770",
    "sg:postcode":"33157",
    "sg:province":"FL",
    "wof:name":"Ministries In Action",
    "wof:placetype":"venue"
},
  "geometry": {"coordinates":[-80.308755,25.614993],"type":"Point"}
}