{
  "type": "Feature",
  "properties": {
    "iso:country":"US",
    "sg:address":"6122 Pasadena Point Blvd S",
    "sg:city":"Saint Petersburg",
    "sg:classifiers":[
        {
            "category":"Real Estate",
            "subcategory":"Real Estate Operator",
            "type":"Services"
        }
    ],
    "sg:phone":"+1 727 906 9492",
    "sg:postcode":"33707",
    "sg:province":"FL",
    "sg:tags":[
        "building",
        "nonresidential"
    ],
    "wof:name":"JC Properties",
    "wof:placetype":"venue"
},
  "geometry": {"coordinates":[-82.71669900000001,27.749962],"type":"Point"}
}