{
  "type": "Feature",
  "properties": {
    "addr:full":"1851 SW 176th Ave Hollywood FL 33029",
    "addr:housenumber":"1851",
    "addr:postcode":"33029",
    "addr:street":"Sw 176Th Ave",
    "iso:country":"US",
    "sg:address":"1851 SW 176th Ave",
    "sg:city":"Hollywood",
    "sg:classifiers":[
        {
            "category":"Manufacturing",
            "subcategory":"Tools & Machinery",
            "type":"Manufacturing & Wholesale Goods"
        }
    ],
    "sg:phone":"+1 954 430 8416",
    "sg:postcode":"33029",
    "sg:province":"FL",
    "sg:tags":[
        "instrument"
    ],
    "wof:name":"Excel Import Export",
    "wof:placetype":"venue"
},
  "geometry": {"coordinates":[-80.382902,25.991184],"type":"Point"}
}