{
  "type": "Feature",
  "properties": {
    "iso:country":"US",
    "sg:address":"6309 Willard Norris Rd",
    "sg:city":"Milton",
    "sg:classifiers":[
        {
            "category":"Manufacturing",
            "subcategory":"Lumber",
            "type":"Manufacturing & Wholesale Goods"
        }
    ],
    "sg:phone":"+1 850 623 8765",
    "sg:postcode":"32570",
    "sg:province":"FL",
    "sg:tags":[
        "camp",
        "logging",
        "contractor"
    ],
    "wof:name":"Elliott Logging",
    "wof:placetype":"venue"
},
  "geometry": {"coordinates":[-87.0594,30.646259],"type":"Point"}
}