{
  "type": "Feature",
  "properties": {
    "iso:country":"US",
    "sg:address":"653 W 8th St",
    "sg:city":"Jacksonville",
    "sg:classifiers":[
        {
            "category":"Education",
            "subcategory":"College",
            "type":"Public Place"
        }
    ],
    "sg:phone":"+1 904 244 3244",
    "sg:postcode":"32209",
    "sg:province":"FL",
    "sg:tags":[
        "teaching",
        "medical",
        "facility"
    ],
    "wof:name":"Borland Health Sciences Lib",
    "wof:placetype":"venue"
},
  "geometry": {"coordinates":[-81.66281499999999,30.346466],"type":"Point"}
}