{
  "type": "Feature",
  "properties": {
    "addr:full":"1916 Okeechobee Rd Fort Pierce FL 34950",
    "addr:housenumber":"1916",
    "addr:postcode":"34950",
    "addr:street":"Okeechobee Rd",
    "iso:country":"US",
    "sg:address":"1916 Okeechobee Rd",
    "sg:city":"Fort Pierce",
    "sg:classifiers":[
        {
            "category":"Restaurant",
            "type":"Food & Drink"
        }
    ],
    "sg:phone":"+1 772 464 1942",
    "sg:postcode":"34950",
    "sg:province":"FL",
    "sg:tags":[
        "eating"
    ],
    "wof:name":"Mr Bs Chick N Treat",
    "wof:placetype":"venue"
},
  "geometry": {"coordinates":[-80.34348300000001,27.442222],"type":"Point"}
}