{
  "type": "Feature",
  "properties": {
    "iso:country":"US",
    "sg:address":"10459 E Gailwood Cir",
    "sg:city":"Jacksonville",
    "sg:classifiers":[
        {
            "category":"Professional",
            "subcategory":"Business Services",
            "type":"Services"
        }
    ],
    "sg:phone":"+1 904 635 9952",
    "sg:postcode":"32218",
    "sg:province":"FL",
    "sg:tags":[
        "pool",
        "swimming"
    ],
    "wof:name":"KIRK F Hersey Pool Svc",
    "wof:placetype":"venue"
},
  "geometry": {"coordinates":[-81.670726,30.42581],"type":"Point"}
}