{
  "type": "Feature",
  "properties": {
    "iso:country":"US",
    "sg:address":"17775 Panama City Beach Pkwy",
    "sg:city":"Panama City Bch",
    "sg:classifiers":[
        {
            "category":"Real Estate",
            "subcategory":"Real Estate Agent",
            "type":"Services"
        }
    ],
    "sg:phone":"+1 850 230 8939",
    "sg:postcode":"32413",
    "sg:province":"FL",
    "sg:website":"www.flaresort.com",
    "wof:name":"Ibis Lake Realty",
    "wof:placetype":"venue"
},
  "geometry": {"coordinates":[-85.909173,30.238169],"type":"Point"}
}