{
  "type": "Feature",
  "properties": {
    "iso:country":"US",
    "sg:address":"650 Seminole Blvd",
    "sg:city":"Largo",
    "sg:classifiers":[
        {
            "category":"Organizations",
            "subcategory":"Community Association",
            "type":"Services"
        }
    ],
    "sg:phone":"+1 727 585 6518",
    "sg:postcode":"33770",
    "sg:province":"FL",
    "wof:name":"Pinellas Classroom Teachers Association Inc",
    "wof:placetype":"venue"
},
  "geometry": {"coordinates":[-82.787723,27.910382],"type":"Point"}
}