{
  "type": "Feature",
  "properties": {
    "iso:country":"US",
    "sg:address":"3873 Powerline Rd",
    "sg:city":"Fort Lauderdale",
    "sg:classifiers":[
        {
            "category":"Home & Garden",
            "subcategory":"Household Appliances",
            "type":"Retail Goods"
        }
    ],
    "sg:phone":"+1 954 567 1895",
    "sg:postcode":"33311",
    "sg:province":"FL",
    "wof:name":"Bonair Depot Inc",
    "wof:placetype":"venue"
},
  "geometry": {"coordinates":[-80.154681,26.174329],"type":"Point"}
}