{
  "type": "Feature",
  "properties": {
    "iso:country":"US",
    "sg:address":"300 US Hwy 98",
    "sg:city":"Destin",
    "sg:classifiers":[
        {
            "category":"Real Estate",
            "subcategory":"Architect",
            "type":"Services"
        }
    ],
    "sg:phone":"+1 850 650 3761",
    "sg:postcode":"32541",
    "sg:province":"FL",
    "sg:tags":[
        "course",
        "golf"
    ],
    "wof:name":"Avant Golf Course & Landscape",
    "wof:placetype":"venue"
},
  "geometry": {"coordinates":[-86.499752,30.393001],"type":"Point"}
}