{
  "type": "Feature",
  "properties": {
    "iso:country":"US",
    "sg:address":"1900 E Main St",
    "sg:city":"Bartow",
    "sg:classifiers":[
        {
            "category":"Food & Beverages",
            "subcategory":"Groceries & Convenience Stores",
            "type":"Retail Goods"
        }
    ],
    "sg:phone":"+1 863 534 3800",
    "sg:postcode":"33830",
    "sg:province":"FL",
    "wof:name":"Super Stop",
    "wof:placetype":"venue"
},
  "geometry": {"coordinates":[-81.82140200000001,27.896926],"type":"Point"}
}