{
  "type": "Feature",
  "properties": {
    "iso:country":"US",
    "sg:address":"1075 58th St N",
    "sg:city":"St Petersburg",
    "sg:classifiers":[
        {
            "category":"Health Services",
            "subcategory":"Doctor",
            "type":"Services"
        }
    ],
    "sg:phone":"+1 727 381 4379",
    "sg:postcode":"33710",
    "sg:province":"FL",
    "sg:tags":[
        "clinic"
    ],
    "wof:name":"Colonic Therapy",
    "wof:placetype":"venue"
},
  "geometry": {"coordinates":[-82.712189,27.781981],"type":"Point"}
}