{
  "type": "Feature",
  "properties": {
    "iso:country":"US",
    "sg:address":"9900 Emerald Coast Pkwy W",
    "sg:city":"Destin",
    "sg:classifiers":[
        {
            "category":"Retail",
            "subcategory":"Auto Rental",
            "type":"Services"
        }
    ],
    "sg:phone":"+1 850 654 4600",
    "sg:postcode":"32550",
    "sg:province":"FL",
    "sg:tags":[
        "renting",
        "automobile"
    ],
    "wof:name":"Guardian Car Rental",
    "wof:placetype":"venue"
},
  "geometry": {"coordinates":[-86.340773,30.377195],"type":"Point"}
}