{
  "type": "Feature",
  "properties": {
    "addr:full":"113 E Noble Ave Williston FL 32696",
    "addr:housenumber":"113",
    "addr:postcode":"32696",
    "addr:street":"E Noble Ave",
    "iso:country":"US",
    "sg:address":"113 E Noble Ave",
    "sg:city":"Williston",
    "sg:classifiers":[
        {
            "category":"Real Estate",
            "subcategory":"Real Estate Agent",
            "type":"Services"
        }
    ],
    "sg:phone":"+1 352 528 2010",
    "sg:postcode":"32696",
    "sg:province":"FL",
    "wof:name":"Hunter Real Estate",
    "wof:placetype":"venue"
},
  "geometry": {"coordinates":[-82.44524,29.38771],"type":"Point"}
}