{
  "type": "Feature",
  "properties": {
    "iso:country":"US",
    "sg:address":"3838 Glen Oaks Manor Dr",
    "sg:city":"Sarasota",
    "sg:classifiers":[
        {
            "category":"Communications",
            "subcategory":"Film & Video Production",
            "type":"Services"
        }
    ],
    "sg:phone":"+1 941 316 0491",
    "sg:postcode":"34232",
    "sg:province":"FL",
    "sg:tags":[
        "motion"
    ],
    "wof:name":"Djr Productions Inc",
    "wof:placetype":"venue"
},
  "geometry": {"coordinates":[-82.494086,27.351194],"type":"Point"}
}