{
  "type": "Feature",
  "properties": {
    "iso:country":"US",
    "sg:address":"4112 53rd Ave E",
    "sg:city":"Bradenton",
    "sg:classifiers":[
        {
            "category":"Government",
            "subcategory":"Post Office",
            "type":"Public Place"
        }
    ],
    "sg:phone":"+1 941 755 0581",
    "sg:postcode":"34203",
    "sg:province":"FL",
    "wof:name":"US Post Office",
    "wof:placetype":"venue"
},
  "geometry": {"coordinates":[-82.51029800000001,27.446432],"type":"Point"}
}