{
  "type": "Feature",
  "properties": {
    "iso:country":"US",
    "sg:address":"7800 SW 7th St",
    "sg:city":"Pompano Beach",
    "sg:classifiers":[
        {
            "category":"Building & Trades",
            "subcategory":"Construction",
            "type":"Services"
        }
    ],
    "sg:phone":"+1 954 724 7429",
    "sg:postcode":"33068",
    "sg:province":"FL",
    "sg:tags":[
        "house"
    ],
    "wof:name":"Jef Construction Inc",
    "wof:placetype":"venue"
},
  "geometry": {"coordinates":[-80.232653,26.221995],"type":"Point"}
}