{
  "type": "Feature",
  "properties": {
    "addr:full":"801 Garden St Titusville FL 32796",
    "addr:housenumber":"801",
    "addr:postcode":"32796",
    "addr:street":"Garden St",
    "iso:country":"US",
    "sg:address":"801 Garden St",
    "sg:city":"Titusville",
    "sg:classifiers":[
        {
            "category":"Health Services",
            "subcategory":"Doctor",
            "type":"Services"
        }
    ],
    "sg:phone":"+1 321 267 1163",
    "sg:postcode":"32796",
    "sg:province":"FL",
    "sg:tags":[
        "medicine",
        "physician",
        "internal",
        "surgeons"
    ],
    "wof:name":"Shyam Verma",
    "wof:placetype":"venue"
},
  "geometry": {"coordinates":[-80.81405599999999,28.61537],"type":"Point"}
}