{
  "type": "Feature",
  "properties": {
    "iso:country":"US",
    "sg:address":"1701 Costa del Sol",
    "sg:city":"Boca Raton",
    "sg:classifiers":[
        {
            "category":"Building & Trades",
            "subcategory":"Plumbing",
            "type":"Services"
        }
    ],
    "sg:phone":"+1 561 482 7495",
    "sg:postcode":"33432",
    "sg:province":"FL",
    "sg:tags":[
        "conditioning",
        "air",
        "system",
        "contractor"
    ],
    "sg:website":"www.romeaire.com",
    "wof:name":"Rome-Aire Svc",
    "wof:placetype":"venue"
},
  "geometry": {"coordinates":[-80.089472,26.367728],"type":"Point"}
}