{
  "type": "Feature",
  "properties": {
    "iso:country":"US",
    "sg:address":"2131 13th St",
    "sg:city":"Sarasota",
    "sg:classifiers":[
        {
            "category":"Home & Garden",
            "subcategory":"Building Materials",
            "type":"Retail Goods"
        },
        {
            "category":"Building & Trades",
            "subcategory":"Construction",
            "type":"Services"
        }
    ],
    "sg:phone":"+1 941 351 8989",
    "sg:postcode":"34237",
    "sg:province":"FL",
    "sg:tags":[
        "fence-sales",
        "fence",
        "contractor"
    ],
    "sg:website":"http://www.sarasotafence.com",
    "wof:name":"Sarasota Fence",
    "wof:placetype":"venue"
},
  "geometry": {"coordinates":[-82.527704,27.349505],"type":"Point"}
}