{
  "type": "Feature",
  "properties": {
    "addr:full":"83 Marco Villas Dr Marco Island FL 34145",
    "addr:housenumber":"83",
    "addr:postcode":"34145",
    "addr:street":"Marco Villas Dr",
    "iso:country":"US",
    "sg:address":"83 Marco Villas Dr",
    "sg:city":"Marco Island",
    "sg:classifiers":[
        {
            "category":"Building & Trades",
            "subcategory":"Construction",
            "type":"Services"
        }
    ],
    "sg:phone":"+1 239 389 2743",
    "sg:postcode":"34145",
    "sg:province":"FL",
    "sg:tags":[
        "hanging",
        "contractor"
    ],
    "wof:name":"James Gratkowski Painting",
    "wof:placetype":"venue"
},
  "geometry": {"coordinates":[-81.71436,25.935096],"type":"Point"}
}