{
  "type": "Feature",
  "properties": {
    "iso:country":"US",
    "sg:address":"5298 S Cherokee Way",
    "sg:city":"Homosassa",
    "sg:classifiers":[
        {
            "category":"Travel",
            "subcategory":"Hotels & Motels",
            "type":"Entertainment"
        }
    ],
    "sg:phone":"+1 352 628 4111",
    "sg:postcode":"34448",
    "sg:province":"FL",
    "wof:name":"Homosassa Safe Boating Inc",
    "wof:placetype":"venue"
},
  "geometry": {"coordinates":[-82.618037,28.784473],"type":"Point"}
}