{
  "type": "Feature",
  "properties": {
    "addr:full":"7370 W 18th Ave Hialeah FL 33014",
    "addr:housenumber":"7370",
    "addr:postcode":"33014",
    "addr:street":"W 18Th Ave",
    "iso:country":"US",
    "sg:address":"7370 W 18th Ave",
    "sg:city":"Hialeah",
    "sg:classifiers":[
        {
            "category":"Personal",
            "type":"Services"
        },
        {
            "category":"Professional",
            "subcategory":"Art Services",
            "type":"Services"
        }
    ],
    "sg:phone":"+1 305 362 0116",
    "sg:postcode":"33014",
    "sg:province":"FL",
    "sg:tags":[
        "photography",
        "videography",
        "wedding"
    ],
    "wof:name":"Alin Photography Corp",
    "wof:placetype":"venue"
},
  "geometry": {"coordinates":[-80.319892,25.890851],"type":"Point"}
}