{
  "type": "Feature",
  "properties": {
    "addr:full":"5898 S Orange Blossom Trl Orlando FL 32839",
    "addr:housenumber":"5898",
    "addr:postcode":"32839",
    "addr:street":"S Orange Blossom Trl",
    "iso:country":"US",
    "sg:address":"5898 S Orange Blossom Trl",
    "sg:city":"Orlando",
    "sg:classifiers":[
        {
            "category":"Restaurant",
            "type":"Food & Drink"
        }
    ],
    "sg:menulink":"http://www.allmenus.com/fl/orlando/81350-papa-johns-pizza/menu/",
    "sg:phone":"+1 407 859 7272",
    "sg:postcode":"32839",
    "sg:province":"FL",
    "sg:tags":[
        "american",
        "pizza"
    ],
    "wof:name":"Papa John's Pizza",
    "wof:placetype":"venue"
},
  "geometry": {"coordinates":[-81.39703299999999,28.472909],"type":"Point"}
}