{
  "type": "Feature",
  "properties": {
    "addr:full":"10014 N Dale Mabry Hwy Tampa FL 33618",
    "addr:housenumber":"10014",
    "addr:postcode":"33618",
    "addr:street":"N Dale Mabry Hwy",
    "iso:country":"US",
    "sg:address":"10014 N Dale Mabry Hwy",
    "sg:city":"Tampa",
    "sg:classifiers":[
        {
            "category":"Real Estate",
            "subcategory":"Real Estate Services",
            "type":"Services"
        },
        {
            "category":"Professional",
            "subcategory":"Business Services",
            "type":"Services"
        }
    ],
    "sg:phone":"+1 813 350 9584",
    "sg:postcode":"33618",
    "sg:province":"FL",
    "sg:tags":[
        "appraisers-business",
        "industrial",
        "commercial",
        "broker",
        "buyer",
        "appraiser"
    ],
    "wof:name":"Meridian Appraisal Services",
    "wof:placetype":"venue"
},
  "geometry": {"coordinates":[-82.504947,28.040358],"type":"Point"}
}