{
  "type": "Feature",
  "properties": {
    "addr:full":"21475 Linwood Ct Boca Raton FL 33433",
    "addr:housenumber":"21475",
    "addr:postcode":"33433",
    "addr:street":"Linwood Ct",
    "iso:country":"US",
    "sg:address":"21475 Linwood Ct",
    "sg:city":"Boca Raton",
    "sg:classifiers":[
        {
            "category":"Manufacturing",
            "subcategory":"Printing",
            "type":"Manufacturing & Wholesale Goods"
        }
    ],
    "sg:phone":"+1 561 487 6909",
    "sg:postcode":"33433",
    "sg:province":"FL",
    "sg:tags":[
        "lithographic",
        "commercial"
    ],
    "wof:name":"Hair Color Express",
    "wof:placetype":"venue"
},
  "geometry": {"coordinates":[-80.15786799999999,26.358587],"type":"Point"}
}