{
  "type": "Feature",
  "properties": {
    "addr:full":"923 Ridgecrest Rd Orlando FL 32806",
    "addr:housenumber":"923",
    "addr:postcode":"32806",
    "addr:street":"Ridgecrest Rd",
    "iso:country":"US",
    "sg:address":"923 Ridgecrest Rd",
    "sg:city":"Orlando",
    "sg:classifiers":[
        {
            "category":"Professional",
            "subcategory":"Lawyer & Legal Services",
            "type":"Services"
        }
    ],
    "sg:phone":"+1 407 855 4352",
    "sg:postcode":"32806",
    "sg:province":"FL",
    "wof:name":"Michael J Canan Atty",
    "wof:placetype":"venue"
},
  "geometry": {"coordinates":[-81.365776,28.505078],"type":"Point"}
}