{
  "type": "Feature",
  "properties": {
    "iso:country":"US",
    "sg:address":"13939 Lakeshore Blvd",
    "sg:city":"Hudson",
    "sg:classifiers":[
        {
            "category":"Health Services",
            "subcategory":"Health Practitioner",
            "type":"Services"
        }
    ],
    "sg:phone":"+1 727 992 2098",
    "sg:postcode":"34667",
    "sg:province":"FL",
    "sg:tags":[
        "psychologist"
    ],
    "wof:name":"Scot D Machlus PHD",
    "wof:placetype":"venue"
},
  "geometry": {"coordinates":[-82.68816,28.355869],"type":"Point"}
}