{
  "type": "Feature",
  "properties": {
    "addr:full":"6817 SW 81st Ter Miami FL 33143",
    "addr:housenumber":"6817",
    "addr:postcode":"33143",
    "addr:street":"Sw 81St Ter",
    "iso:country":"US",
    "sg:address":"6817 SW 81st Ter",
    "sg:city":"Miami",
    "sg:classifiers":[
        {
            "category":"Building & Trades",
            "subcategory":"Construction",
            "type":"Services"
        }
    ],
    "sg:phone":"+1 305 668 4949",
    "sg:postcode":"33143",
    "sg:province":"FL",
    "sg:tags":[
        "contractor"
    ],
    "wof:name":"Shear Construction & Development Inc",
    "wof:placetype":"venue"
},
  "geometry": {"coordinates":[-80.303703,25.694599],"type":"Point"}
}