{
  "type": "Feature",
  "properties": {
    "addr:full":"1313 Tampa St N Tampa FL 33602",
    "addr:housenumber":"1313",
    "addr:postcode":"33602",
    "addr:street":"Tampa St N",
    "iso:country":"US",
    "sg:address":"1313 Tampa St N",
    "sg:city":"Tampa",
    "sg:classifiers":[
        {
            "category":"Government",
            "subcategory":"Jail",
            "type":"Public Place"
        }
    ],
    "sg:phone":"+1 813 272 3561",
    "sg:postcode":"33602",
    "sg:province":"FL",
    "sg:tags":[
        "correctional",
        "institution"
    ],
    "wof:name":"Tampa Circuit Office",
    "wof:placetype":"venue"
},
  "geometry": {"coordinates":[-82.460869,27.955302],"type":"Point"}
}