{
  "type": "Feature",
  "properties": {
    "iso:country":"US",
    "sg:address":"13960 NW 22nd Ave",
    "sg:city":"Opa Locka",
    "sg:classifiers":[
        {
            "category":"Retail",
            "subcategory":"Repair Shop",
            "type":"Services"
        }
    ],
    "sg:phone":"+1 305 681 5018",
    "sg:postcode":"33054",
    "sg:province":"FL",
    "sg:tags":[
        "ironwork"
    ],
    "wof:name":"LA Famosa Ironworks Inc",
    "wof:placetype":"venue"
},
  "geometry": {"coordinates":[-80.23576300000001,25.902379],"type":"Point"}
}