{
  "type": "Feature",
  "properties": {
    "iso:country":"US",
    "sg:address":"3110 C R Smith St",
    "sg:city":"Orlando",
    "sg:classifiers":[
        {
            "category":"Social Services",
            "type":"Services"
        }
    ],
    "sg:phone":"+1 407 578 6268",
    "sg:postcode":"32805",
    "sg:province":"FL",
    "sg:tags":[
        "youth",
        "organization",
        "center"
    ],
    "sg:website":"www.bgccf.org",
    "wof:name":"Boys & Girls Club-Central Fla",
    "wof:placetype":"venue"
},
  "geometry": {"coordinates":[-81.41445899999999,28.534598],"type":"Point"}
}