{
  "type": "Feature",
  "properties": {
    "iso:country":"US",
    "sg:address":"1322 Hidden Creek Ct",
    "sg:city":"Winter Haven",
    "sg:classifiers":[
        {
            "category":"Insurance",
            "subcategory":"Insurance Agent",
            "type":"Services"
        }
    ],
    "sg:phone":"+1 863 412 2038",
    "sg:postcode":"33880",
    "sg:province":"FL",
    "wof:name":"Barfield Insur Fincl Svcs Inc",
    "wof:placetype":"venue"
},
  "geometry": {"coordinates":[-81.815444,27.991354],"type":"Point"}
}