{
  "type": "Feature",
  "properties": {
    "iso:country":"US",
    "sg:address":"5528 Cinderlane Pkwy Ste B",
    "sg:city":"Orlando",
    "sg:classifiers":[
        {
            "category":"Real Estate",
            "subcategory":"Real Estate Operator",
            "type":"Services"
        }
    ],
    "sg:phone":"+1 407 299 7564",
    "sg:postcode":"32808",
    "sg:province":"FL",
    "sg:tags":[
        "apartment"
    ],
    "sg:website":"http://www.rosemontcountryclubapartments.com",
    "wof:name":"Rosemont Country Club Apartments",
    "wof:placetype":"venue"
},
  "geometry": {"coordinates":[-81.429199,28.6094],"type":"Point"}
}