{
  "type": "Feature",
  "properties": {
    "addr:full":"1320 S Dixie Hwy W Pompano Beach FL 33060",
    "addr:housenumber":"1320",
    "addr:postcode":"33060",
    "addr:street":"S Dixie Hwy W",
    "iso:country":"US",
    "sg:address":"1320 S Dixie Hwy W",
    "sg:city":"Pompano Beach",
    "sg:classifiers":[
        {
            "category":"Education",
            "subcategory":"Special Training",
            "type":"Public Place"
        }
    ],
    "sg:phone":"+1 954 545 0708",
    "sg:postcode":"33060",
    "sg:province":"FL",
    "wof:name":"Lesmarges Driving School",
    "wof:placetype":"venue"
},
  "geometry": {"coordinates":[-80.13211800000001,26.214222],"type":"Point"}
}