{
  "type": "Feature",
  "properties": {
    "iso:country":"US",
    "sg:address":"3070 NW 48th Ter",
    "sg:city":"Fort Lauderdale",
    "sg:classifiers":[
        {
            "category":"Organizations",
            "subcategory":"Membership Organization",
            "type":"Services"
        }
    ],
    "sg:phone":"+1 954 731 3103",
    "sg:postcode":"33313",
    "sg:province":"FL",
    "sg:tags":[
        "builder",
        "operative"
    ],
    "wof:name":"Cypress Chase Condo Assn C",
    "wof:placetype":"venue"
},
  "geometry": {"coordinates":[-80.215042,26.164374],"type":"Point"}
}