{
  "type": "Feature",
  "properties": {
    "iso:country":"US",
    "sg:address":"526 S Lakeview Ave",
    "sg:city":"Winter Garden",
    "sg:classifiers":[
        {
            "category":"Autos & Motor Vehicles",
            "subcategory":"Motorcycle Sales",
            "type":"Retail Goods"
        }
    ],
    "sg:phone":"+1 407 656 9686",
    "sg:postcode":"34787",
    "sg:province":"FL",
    "sg:tags":[
        "repair"
    ],
    "wof:name":"K & P Cycles Inc",
    "wof:placetype":"venue"
},
  "geometry": {"coordinates":[-81.587793,28.558813],"type":"Point"}
}