{
  "type": "Feature",
  "properties": {
    "iso:country":"US",
    "sg:address":"609 Norma Dr",
    "sg:city":"Orlando",
    "sg:classifiers":[
        {
            "category":"Building & Trades",
            "subcategory":"Construction",
            "type":"Services"
        }
    ],
    "sg:phone":"+1 407 482 6790",
    "sg:postcode":"32807",
    "sg:province":"FL",
    "sg:tags":[
        "hanging",
        "contractor"
    ],
    "wof:name":"Jose J Montes",
    "wof:placetype":"venue"
},
  "geometry": {"coordinates":[-81.309572,28.550923],"type":"Point"}
}