{
  "type": "Feature",
  "properties": {
    "iso:country":"US",
    "sg:address":"2112 SW 58th Ave",
    "sg:city":"Hollywood",
    "sg:classifiers":[
        {
            "category":"Building & Trades",
            "subcategory":"Construction",
            "type":"Services"
        }
    ],
    "sg:phone":"+1 954 987 6062",
    "sg:postcode":"33023",
    "sg:province":"FL",
    "sg:tags":[
        "hanging",
        "contractor"
    ],
    "sg:website":"www.abestpainting.com",
    "wof:name":"A-Best Painting Contractors",
    "wof:placetype":"venue"
},
  "geometry": {"coordinates":[-80.202799,25.989869],"type":"Point"}
}