{
  "type": "Feature",
  "properties": {
    "addr:full":"9699 San Jose Blvd Jacksonville FL 32257",
    "addr:housenumber":"9699",
    "addr:postcode":"32257",
    "addr:street":"San Jose Blvd",
    "iso:country":"US",
    "sg:address":"9699 San Jose Blvd",
    "sg:city":"Jacksonville",
    "sg:classifiers":[
        {
            "category":"Retail",
            "subcategory":"Auto Repair",
            "type":"Services"
        }
    ],
    "sg:phone":"+1 904 268 8084",
    "sg:postcode":"32257",
    "sg:province":"FL",
    "sg:tags":[
        "automotive",
        "lube",
        "oil"
    ],
    "wof:name":"Jiffy Lube",
    "wof:placetype":"venue"
},
  "geometry": {"coordinates":[-81.61718999999999,30.205699],"type":"Point"}
}