{
  "type": "Feature",
  "properties": {
    "addr:full":"310 Krider Rd Sanford FL 32773",
    "addr:housenumber":"310",
    "addr:postcode":"32773",
    "addr:street":"Krider Rd",
    "iso:country":"US",
    "sg:address":"310 Krider Rd",
    "sg:city":"Sanford",
    "sg:classifiers":[
        {
            "category":"Freight",
            "type":"Transportation"
        }
    ],
    "sg:phone":"+1 407 322 9081",
    "sg:postcode":"32773",
    "sg:province":"FL",
    "sg:tags":[
        "operator",
        "trucking"
    ],
    "wof:name":"Marvin Nelson Trucking Inc",
    "wof:placetype":"venue"
},
  "geometry": {"coordinates":[-81.259298,28.768907],"type":"Point"}
}