{
  "type": "Feature",
  "properties": {
    "iso:country":"US",
    "sg:address":"213 N Dixie Hwy",
    "sg:city":"West Palm Beach",
    "sg:classifiers":[
        {
            "category":"Restaurant",
            "type":"Food & Drink"
        }
    ],
    "sg:phone":"+1 561 586 1188",
    "sg:postcode":"33401",
    "sg:province":"FL",
    "wof:name":"El Sabor Pinolero",
    "wof:placetype":"venue"
},
  "geometry": {"coordinates":[-80.053572,26.714762],"type":"Point"}
}