{
  "type": "Feature",
  "properties": {
    "addr:full":"4735 Pembrooke Ln Bonita Springs FL 34134",
    "addr:postcode":"4735;34134",
    "addr:street":"Pembrooke Ln",
    "iso:country":"US",
    "sg:address":"4735 Pembrooke Ln",
    "sg:city":"Bonita Springs",
    "sg:classifiers":[
        {
            "category":"Professional",
            "subcategory":"Computer Services",
            "type":"Services"
        }
    ],
    "sg:phone":"+1 239 498 1622",
    "sg:postcode":"34134",
    "sg:province":"FL",
    "sg:tags":[
        "consultant",
        "designer"
    ],
    "wof:name":"W L Nilsen Consultants",
    "wof:placetype":"venue"
},
  "geometry": {"coordinates":[-81.83139799999999,26.384167],"type":"Point"}
}