{
  "type": "Feature",
  "properties": {
    "iso:country":"US",
    "sg:address":"17721 62nd Rd N",
    "sg:city":"Loxahatchee",
    "sg:classifiers":[
        {
            "category":"Real Estate",
            "subcategory":"Surveying",
            "type":"Services"
        }
    ],
    "sg:phone":"+1 561 204 1035",
    "sg:postcode":"33470",
    "sg:province":"FL",
    "sg:tags":[
        "surveyor"
    ],
    "wof:name":"Prism Surveying Inc",
    "wof:placetype":"venue"
},
  "geometry": {"coordinates":[-80.32247599999999,26.769201],"type":"Point"}
}