{
  "type": "Feature",
  "properties": {
    "iso:country":"US",
    "sg:address":"3460 W Pennington Ct",
    "sg:city":"Lecanto",
    "sg:classifiers":[
        {
            "category":"Home & Garden",
            "subcategory":"Building Materials",
            "type":"Retail Goods"
        }
    ],
    "sg:phone":"+1 352 628 7575",
    "sg:postcode":"34461",
    "sg:province":"FL",
    "sg:tags":[
        "mixed",
        "concrete"
    ],
    "wof:name":"Sunshine Materials Inc",
    "wof:placetype":"venue"
},
  "geometry": {"coordinates":[-82.489987,28.816246],"type":"Point"}
}