{
  "type": "Feature",
  "properties": {
    "iso:country":"US",
    "sg:address":"3500 9th St E",
    "sg:city":"Bradenton",
    "sg:classifiers":[
        {
            "category":"Education",
            "subcategory":"School",
            "type":"Public Place"
        },
        {
            "category":"Education",
            "subcategory":"Special Training",
            "type":"Public Place"
        }
    ],
    "sg:phone":"+1 941 708 6100",
    "sg:postcode":"34208",
    "sg:province":"FL",
    "sg:tags":[
        "elementary"
    ],
    "wof:name":"C W Rowlett Elementary School",
    "wof:placetype":"venue"
},
  "geometry": {"coordinates":[-82.55483,27.467792],"type":"Point"}
}