{
  "type": "Feature",
  "properties": {
    "addr:full":"10840 Endeavour Way Largo FL 33777",
    "addr:housenumber":"10840",
    "addr:postcode":"33777",
    "addr:street":"Endeavour Way",
    "iso:country":"US",
    "sg:address":"10840 Endeavour Way",
    "sg:city":"Largo",
    "sg:classifiers":[
        {
            "category":"Wholesale",
            "subcategory":"Durable Goods & Equipment",
            "type":"Manufacturing & Wholesale Goods"
        }
    ],
    "sg:phone":"+1 727 535 3310",
    "sg:postcode":"33777",
    "sg:province":"FL",
    "sg:tags":[
        "commercial",
        "sign"
    ],
    "wof:name":"Adept Neon",
    "wof:placetype":"venue"
},
  "geometry": {"coordinates":[-82.73515500000001,27.869848],"type":"Point"}
}