{
  "type": "Feature",
  "properties": {
    "addr:full":"109 Sheppard Rd NW Lake Placid FL 33852",
    "addr:housenumber":"109",
    "addr:postcode":"33852",
    "addr:street":"Sheppard Rd Nw",
    "iso:country":"US",
    "sg:address":"109 Sheppard Rd NW",
    "sg:city":"Lake Placid",
    "sg:classifiers":[
        {
            "category":"Building & Trades",
            "subcategory":"Construction",
            "type":"Services"
        }
    ],
    "sg:phone":"+1 863 465 4696",
    "sg:postcode":"33852",
    "sg:province":"FL",
    "sg:tags":[
        "hanging",
        "painter",
        "contractor"
    ],
    "wof:name":"Floyd Wierda Painting Inc",
    "wof:placetype":"venue"
},
  "geometry": {"coordinates":[-81.402732,27.26412],"type":"Point"}
}