{
  "type": "Feature",
  "properties": {
    "addr:full":"4315 Rum Cay Cir Sarasota FL 34233",
    "addr:postcode":"4315;34233",
    "addr:street":"Cay Cir",
    "iso:country":"US",
    "sg:address":"4315 Rum Cay Cir",
    "sg:city":"Sarasota",
    "sg:classifiers":[
        {
            "category":"Freight",
            "type":"Transportation"
        }
    ],
    "sg:phone":"+1 941 302 3170",
    "sg:postcode":"34233",
    "sg:province":"FL",
    "sg:tags":[
        "operator",
        "local",
        "trucking"
    ],
    "wof:name":"Packard Allen D 111 LLC",
    "wof:placetype":"venue"
},
  "geometry": {"coordinates":[-82.460156,27.290748],"type":"Point"}
}