{
  "type": "Feature",
  "properties": {
    "addr:full":"12924 N Dale Mabry Hwy Tampa FL 33618",
    "addr:housenumber":"12924",
    "addr:postcode":"33618",
    "addr:street":"N Dale Mabry Hwy",
    "iso:country":"US",
    "sg:address":"12924 N Dale Mabry Hwy",
    "sg:city":"Tampa",
    "sg:classifiers":[
        {
            "category":"Recreation",
            "type":"Entertainment"
        }
    ],
    "sg:phone":"+1 813 264 5425",
    "sg:postcode":"33618",
    "sg:province":"FL",
    "wof:name":"Carrollwood Black Belt Academy",
    "wof:placetype":"venue"
},
  "geometry": {"coordinates":[-82.504115,28.063606],"type":"Point"}
}