{
  "type": "Feature",
  "properties": {
    "addr:full":"348 N Park Ave Winter Park FL 32789",
    "addr:housenumber":"348",
    "addr:postcode":"32789",
    "addr:street":"N Park Ave",
    "iso:country":"US",
    "sg:address":"348 N Park Ave",
    "sg:city":"Winter Park",
    "sg:classifiers":[
        {
            "category":"Shopping",
            "subcategory":"Beauty & Cosmetics",
            "type":"Retail Goods"
        }
    ],
    "sg:phone":"+1 407 622 1086",
    "sg:postcode":"32789",
    "sg:province":"FL",
    "sg:tags":[
        "supply"
    ],
    "sg:website":"www.kromamakeup.com",
    "wof:name":"Kroma Makeup Services",
    "wof:placetype":"venue"
},
  "geometry": {"coordinates":[-81.350998,28.6003],"type":"Point"}
}