{
  "type": "Feature",
  "properties": {
    "addr:full":"7001 SW 87th Ct Miami FL 33173",
    "addr:housenumber":"7001",
    "addr:postcode":"33173",
    "addr:street":"Sw 87Th Ct",
    "iso:country":"US",
    "sg:address":"7001 SW 87th Ct",
    "sg:city":"Miami",
    "sg:classifiers":[
        {
            "category":"Personal",
            "subcategory":"Adult",
            "type":"Services"
        }
    ],
    "sg:phone":"+1 305 271 3200",
    "sg:postcode":"33173",
    "sg:province":"FL",
    "sg:tags":[
        "midwife"
    ],
    "wof:name":"Carbo Clarissa Cnm",
    "wof:placetype":"venue"
},
  "geometry": {"coordinates":[-80.334999,25.704],"type":"Point"}
}