{
  "type": "Feature",
  "properties": {
    "addr:full":"207 Key Deer Blvd Big Pine Key FL 33043",
    "addr:housenumber":"207",
    "addr:postcode":"33043",
    "addr:street":"Key Deer Blvd",
    "iso:country":"US",
    "sg:address":"207 Key Deer Blvd",
    "sg:city":"Big Pine Key",
    "sg:classifiers":[
        {
            "category":"Health Services",
            "subcategory":"Chiropractor",
            "type":"Services"
        }
    ],
    "sg:phone":"+1 305 872 4664",
    "sg:postcode":"33043",
    "sg:province":"FL",
    "wof:name":"Big Pine Key Chiropractic",
    "wof:placetype":"venue"
},
  "geometry": {"coordinates":[-81.358029,24.672689],"type":"Point"}
}