{
  "type": "Feature",
  "properties": {
    "iso:country":"US",
    "sg:address":"15625 SW 88th St",
    "sg:city":"Miami",
    "sg:classifiers":[
        {
            "category":"Shopping",
            "subcategory":"Baby Store",
            "type":"Retail Goods"
        },
        {
            "category":"Shopping",
            "subcategory":"Hobbies, Toys, & Games",
            "type":"Retail Goods"
        },
        {
            "category":"Home & Garden",
            "subcategory":"Home Furnishings",
            "type":"Retail Goods"
        }
    ],
    "sg:phone":"+1 305 382 4829",
    "sg:postcode":"33196",
    "sg:province":"FL",
    "sg:tags":[
        "infant",
        "toy",
        "accessories",
        "furniture-children's",
        "children's",
        "wear"
    ],
    "wof:name":"Babies R Us The Baby Superstore",
    "wof:placetype":"venue"
},
  "geometry": {"coordinates":[-80.444982,25.684492],"type":"Point"}
}