{
  "type": "Feature",
  "properties": {
    "iso:country":"US",
    "sg:address":"4252 NW 66th Dr",
    "sg:city":"Boca Raton",
    "sg:classifiers":[
        {
            "category":"Wholesale",
            "subcategory":"Home Furnishings",
            "type":"Manufacturing & Wholesale Goods"
        }
    ],
    "sg:phone":"+1 561 988 0202",
    "sg:postcode":"33496",
    "sg:province":"FL",
    "wof:name":"M/S Creations Inc",
    "wof:placetype":"venue"
},
  "geometry": {"coordinates":[-80.170102,26.407274],"type":"Point"}
}