{
  "type": "Feature",
  "properties": {
    "addr:full":"1380 S Ocean Blvd Pompano Beach FL 33062",
    "addr:housenumber":"1380",
    "addr:postcode":"33062",
    "addr:street":"S Ocean Blvd",
    "iso:country":"US",
    "sg:address":"1380 S Ocean Blvd",
    "sg:city":"Pompano Beach",
    "sg:classifiers":[
        {
            "category":"Recreation",
            "type":"Entertainment"
        }
    ],
    "sg:phone":"+1 954 941 2891",
    "sg:postcode":"33062",
    "sg:province":"FL",
    "sg:tags":[
        "water",
        "equipment",
        "sport"
    ],
    "wof:name":"Wave Blast Water Sports II",
    "wof:placetype":"venue"
},
  "geometry": {"coordinates":[-80.091182,26.221194],"type":"Point"}
}