{
  "type": "Feature",
  "properties": {
    "addr:full":"4504 NW 183rd St Opa Locka FL 33055",
    "addr:housenumber":"4504",
    "addr:postcode":"33055",
    "addr:street":"Nw 183Rd St;Locka",
    "iso:country":"US",
    "sg:address":"4504 NW 183rd St",
    "sg:city":"Opa Locka",
    "sg:classifiers":[
        {
            "category":"Utilities",
            "subcategory":"Mobile Phone",
            "type":"Services"
        }
    ],
    "sg:phone":"+1 305 621 2522",
    "sg:postcode":"33055",
    "sg:province":"FL",
    "sg:tags":[
        "communication",
        "radiotelephone"
    ],
    "wof:name":"Bc Beepers & Cmmnctns Crp",
    "wof:placetype":"venue"
},
  "geometry": {"coordinates":[-80.274705,25.939734],"type":"Point"}
}