{
  "type": "Feature",
  "properties": {
    "iso:country":"US",
    "sg:address":"4436 Fox Ridge Dr",
    "sg:city":"Fort Lauderdale",
    "sg:classifiers":[
        {
            "category":"Wholesale",
            "subcategory":"Scrap",
            "type":"Manufacturing & Wholesale Goods"
        },
        {
            "category":"Building & Trades",
            "subcategory":"Landscaping Services",
            "type":"Services"
        }
    ],
    "sg:phone":"+1 954 385 9275",
    "sg:postcode":"33331",
    "sg:province":"FL",
    "sg:tags":[
        "material",
        "landscape"
    ],
    "wof:name":"1 800 Got Junk of SE Florida",
    "wof:placetype":"venue"
},
  "geometry": {"coordinates":[-80.384124,26.065254],"type":"Point"}
}