{
  "type": "Feature",
  "properties": {
    "addr:full":"3909 Shelley Rd S West Palm Beach FL 33407",
    "addr:housenumber":"3909",
    "addr:postcode":"33407",
    "addr:street":"Shelley Rd S",
    "iso:country":"US",
    "sg:address":"3909 Shelley Rd S",
    "sg:city":"West Palm Beach",
    "sg:classifiers":[
        {
            "category":"Health Services",
            "subcategory":"Doctor",
            "type":"Services"
        }
    ],
    "sg:phone":"+1 561 478 3598",
    "sg:postcode":"33407",
    "sg:province":"FL",
    "sg:tags":[
        "medical"
    ],
    "wof:name":"Porter Crow Dr",
    "wof:placetype":"venue"
},
  "geometry": {"coordinates":[-80.09598200000001,26.755322],"type":"Point"}
}