{
  "type": "Feature",
  "properties": {
    "iso:country":"US",
    "sg:address":"11100 E Colonial Dr",
    "sg:city":"Orlando",
    "sg:classifiers":[
        {
            "category":"Shopping",
            "subcategory":"Gifts & Souvenirs",
            "type":"Retail Goods"
        }
    ],
    "sg:phone":"+1 407 737 8300",
    "sg:postcode":"32817",
    "sg:province":"FL",
    "sg:tags":[
        "shop"
    ],
    "wof:name":"Beauty & Gift Shop",
    "wof:placetype":"venue"
},
  "geometry": {"coordinates":[-81.219972,28.568288],"type":"Point"}
}