{
  "type": "Feature",
  "properties": {
    "iso:country":"US",
    "sg:address":"9411 Cypress Lake Dr",
    "sg:city":"Fort Myers",
    "sg:classifiers":[
        {
            "category":"Health Services",
            "subcategory":"Dentist",
            "type":"Services"
        }
    ],
    "sg:phone":"+1 239 482 0252",
    "sg:postcode":"33919",
    "sg:province":"FL",
    "wof:name":"Grumbach Paul G DDS PA",
    "wof:placetype":"venue"
},
  "geometry": {"coordinates":[-81.910301,26.545601],"type":"Point"}
}