{
  "type": "Feature",
  "properties": {
    "iso:country":"US",
    "sg:address":"6916 Hammock Lakes Dr",
    "sg:city":"Melbourne",
    "sg:classifiers":[
        {
            "category":"Building & Trades",
            "subcategory":"Landscaping Services",
            "type":"Services"
        }
    ],
    "sg:phone":"+1 321 242 7295",
    "sg:postcode":"32940",
    "sg:province":"FL",
    "sg:tags":[
        "landscape"
    ],
    "wof:name":"Jsc Landscape",
    "wof:placetype":"venue"
},
  "geometry": {"coordinates":[-80.7141,28.238545],"type":"Point"}
}