{
  "type": "Feature",
  "properties": {
    "addr:full":"3411 45th St E Bradenton FL 34208",
    "addr:housenumber":"3411",
    "addr:postcode":"34208",
    "addr:street":"45Th St",
    "iso:country":"US",
    "sg:address":"3411 45th St E",
    "sg:city":"Bradenton",
    "sg:classifiers":[
        {
            "category":"Building & Trades",
            "subcategory":"Construction",
            "type":"Services"
        }
    ],
    "sg:phone":"+1 941 746 4406",
    "sg:postcode":"34208",
    "sg:province":"FL",
    "sg:tags":[
        "contractor"
    ],
    "wof:name":"Tyvan Anderson Texture SE",
    "wof:placetype":"venue"
},
  "geometry": {"coordinates":[-82.50555900000001,27.470745],"type":"Point"}
}