{
  "type": "Feature",
  "properties": {
    "iso:country":"US",
    "sg:address":"14050 NW 82nd Ave",
    "sg:city":"Hialeah",
    "sg:classifiers":[
        {
            "category":"Professional",
            "subcategory":"Detective & Security Services",
            "type":"Services"
        },
        {
            "category":"Utilities",
            "subcategory":"Telephone",
            "type":"Services"
        }
    ],
    "sg:phone":"+1 305 362 6767",
    "sg:postcode":"33016",
    "sg:province":"FL",
    "sg:tags":[
        "control",
        "monitoring",
        "fire",
        "consultant",
        "alarm",
        "system",
        "access",
        "equipment",
        "communication"
    ],
    "sg:website":"http://www.horizonsecurity.com",
    "wof:name":"Horizon Security & Telecom Systems",
    "wof:placetype":"venue"
},
  "geometry": {"coordinates":[-80.33238,25.90004],"type":"Point"}
}