{
  "type": "Feature",
  "properties": {
    "iso:country":"US",
    "sg:address":"12950 Trade Way Four",
    "sg:city":"Bonita Springs",
    "sg:classifiers":[
        {
            "category":"Restaurant",
            "type":"Food & Drink"
        }
    ],
    "sg:phone":"+1 239 947 9977",
    "sg:postcode":"34135",
    "sg:province":"FL",
    "wof:name":"China A",
    "wof:placetype":"venue"
},
  "geometry": {"coordinates":[-81.739554,26.328733],"type":"Point"}
}