{
  "type": "Feature",
  "properties": {
    "addr:full":"10033 Balm Riverview Rd Riverview FL 33569",
    "addr:housenumber":"10033",
    "addr:postcode":"33569",
    "addr:street":"Balm Riverview Rd",
    "iso:country":"US",
    "sg:address":"10033 Balm Riverview Rd",
    "sg:city":"Riverview",
    "sg:classifiers":[
        {
            "category":"Restaurant",
            "type":"Food & Drink"
        }
    ],
    "sg:menulink":"http://www.allmenus.com/fl/brandon/207093-sonic/menu/",
    "sg:phone":"+1 813 234 1492",
    "sg:postcode":"33569",
    "sg:province":"FL",
    "sg:tags":[
        "burger",
        "american"
    ],
    "wof:name":"Sonic",
    "wof:placetype":"venue"
},
  "geometry": {"coordinates":[-82.314504,27.854348],"type":"Point"}
}