{
  "type": "Feature",
  "properties": {
    "iso:country":"US",
    "sg:address":"12569 Phillips Hwy",
    "sg:city":"Jacksonville",
    "sg:classifiers":[
        {
            "category":"Autos & Motor Vehicles",
            "subcategory":"Fuel & Gas Station",
            "type":"Retail Goods"
        }
    ],
    "sg:phone":"+1 904 260 6705",
    "sg:postcode":"32256",
    "sg:province":"FL",
    "sg:tags":[
        "oil"
    ],
    "wof:name":"Baynard Service Ctr",
    "wof:placetype":"venue"
},
  "geometry": {"coordinates":[-81.51768,30.143134],"type":"Point"}
}