{
  "type": "Feature",
  "properties": {
    "iso:country":"US",
    "sg:address":"16107 Craigend Pl",
    "sg:city":"Odessa",
    "sg:classifiers":[
        {
            "category":"Building & Trades",
            "subcategory":"Construction",
            "type":"Services"
        }
    ],
    "sg:phone":"+1 813 926 9586",
    "sg:postcode":"33556",
    "sg:province":"FL",
    "sg:tags":[
        "contractor"
    ],
    "wof:name":"Pete The Builder Inc",
    "wof:placetype":"venue"
},
  "geometry": {"coordinates":[-82.639765,28.099367],"type":"Point"}
}