{
  "type": "Feature",
  "properties": {
    "iso:country":"US",
    "sg:address":"20335 Biscayne Blvd",
    "sg:city":"Aventura",
    "sg:classifiers":[
        {
            "category":"Personal",
            "subcategory":"Nail Salon",
            "type":"Services"
        }
    ],
    "sg:phone":"+1 305 931 4645",
    "sg:postcode":"33160",
    "sg:province":"FL",
    "sg:website":"http://nailsbysixta.com",
    "wof:name":"Nails By Sixta",
    "wof:placetype":"venue"
},
  "geometry": {"coordinates":[-80.139613,25.926379],"type":"Point"}
}