{
  "type": "Feature",
  "properties": {
    "addr:full":"316 3rd Ave N Jacksonville Beach FL 32250",
    "addr:housenumber":"316",
    "addr:postcode":"32250",
    "addr:street":"3Rd Ave N",
    "iso:country":"US",
    "sg:address":"316 3rd Ave N",
    "sg:city":"Jacksonville Beach",
    "sg:classifiers":[
        {
            "category":"Farming",
            "subcategory":"Farm & Veterinary Services",
            "type":"Manufacturing & Wholesale Goods"
        }
    ],
    "sg:phone":"+1 904 247 8899",
    "sg:postcode":"32250",
    "sg:province":"FL",
    "sg:tags":[
        "crop"
    ],
    "wof:name":"Florida Irrigation Supply Inc",
    "wof:placetype":"venue"
},
  "geometry": {"coordinates":[-81.39349799999999,30.291644],"type":"Point"}
}