{
  "type": "Feature",
  "properties": {
    "iso:country":"US",
    "sg:address":"10924 Pathfinder Trl",
    "sg:city":"Lakeland",
    "sg:classifiers":[
        {
            "category":"Freight",
            "type":"Transportation"
        }
    ],
    "sg:phone":"+1 863 858 1255",
    "sg:postcode":"33809",
    "sg:province":"FL",
    "sg:tags":[
        "trucking"
    ],
    "wof:name":"C & J Transport",
    "wof:placetype":"venue"
},
  "geometry": {"coordinates":[-81.97281700000001,28.195713],"type":"Point"}
}