{
  "type": "Feature",
  "properties": {
    "addr:full":"467 Lake Howell Rd Ste 5 Maitland FL 32751",
    "addr:housenumber":"467",
    "addr:postcode":"32751",
    "addr:street":"Lake Howell Rd Ste 5",
    "iso:country":"US",
    "sg:address":"467 Lake Howell Rd Ste 5",
    "sg:city":"Maitland",
    "sg:classifiers":[
        {
            "category":"Food & Beverages",
            "subcategory":"Specialty",
            "type":"Retail Goods"
        }
    ],
    "sg:phone":"+1 407 616 6942",
    "sg:postcode":"32751",
    "sg:province":"FL",
    "sg:tags":[
        "product",
        "supplement",
        "health",
        "vitamin",
        "diet"
    ],
    "wof:name":"Cjays Mega Grow",
    "wof:placetype":"venue"
},
  "geometry": {"coordinates":[-81.32409699999999,28.62862],"type":"Point"}
}