{
  "type": "Feature",
  "properties": {
    "addr:full":"800 Goodlette Rd N Naples FL 34102",
    "addr:housenumber":"800",
    "addr:postcode":"34102",
    "addr:street":"Goodlette Rd N",
    "iso:country":"US",
    "sg:address":"800 Goodlette Rd N",
    "sg:city":"Naples",
    "sg:classifiers":[
        {
            "category":"Health Services",
            "subcategory":"Doctor",
            "type":"Services"
        }
    ],
    "sg:phone":"+1 239 262 6660",
    "sg:postcode":"34102",
    "sg:province":"FL",
    "sg:tags":[
        "physician",
        "surgeon"
    ],
    "wof:name":"Hiranya A Rajasinghe MD",
    "wof:placetype":"venue"
},
  "geometry": {"coordinates":[-81.79111899999999,26.162339],"type":"Point"}
}