{
  "type": "Feature",
  "properties": {
    "addr:full":"305 N 4th St Lantana FL 33462",
    "addr:housenumber":"305",
    "addr:postcode":"33462",
    "addr:street":"N 4Th St",
    "iso:country":"US",
    "sg:address":"305 N 4th St",
    "sg:city":"Lantana",
    "sg:classifiers":[
        {
            "category":"Shopping",
            "type":"Retail Goods"
        }
    ],
    "sg:phone":"+1 561 721 0757",
    "sg:postcode":"33462",
    "sg:province":"FL",
    "sg:tags":[
        "cosmetic",
        "perfume"
    ],
    "wof:name":"Aly Beauty Supply",
    "wof:placetype":"venue"
},
  "geometry": {"coordinates":[-80.054304,26.586784],"type":"Point"}
}