{
  "type": "Feature",
  "properties": {
    "iso:country":"US",
    "sg:address":"4323 N Ocean Dr",
    "sg:city":"Fort Lauderdale",
    "sg:classifiers":[
        {
            "category":"Retail",
            "subcategory":"Laundry & Dry Cleaning",
            "type":"Services"
        }
    ],
    "sg:phone":"+1 954 958 9241",
    "sg:postcode":"33308",
    "sg:province":"FL",
    "sg:tags":[
        "garment",
        "agent"
    ],
    "wof:name":"By The Sea Laundry",
    "wof:placetype":"venue"
},
  "geometry": {"coordinates":[-80.09761899999999,26.181767],"type":"Point"}
}