{
  "type": "Feature",
  "properties": {
    "iso:country":"US",
    "sg:address":"490 S Old Wire Rd",
    "sg:city":"Wildwood",
    "sg:classifiers":[
        {
            "category":"Social Services",
            "subcategory":"Retirement Home",
            "type":"Services"
        }
    ],
    "sg:phone":"+1 352 748 3322",
    "sg:postcode":"34785",
    "sg:province":"FL",
    "sg:tags":[
        "convalescent",
        "nursing"
    ],
    "wof:name":"The Alliance Foundation For Housing & Health Care Inc",
    "wof:placetype":"venue"
},
  "geometry": {"coordinates":[-82.037109,28.85468],"type":"Point"}
}