{
  "type": "Feature",
  "properties": {
    "iso:country":"US",
    "sg:address":"814 Nottingham Dr",
    "sg:city":"Fernandina Beach",
    "sg:classifiers":[
        {
            "category":"Farming",
            "subcategory":"Fish & Marine Products",
            "type":"Manufacturing & Wholesale Goods"
        }
    ],
    "sg:phone":"+1 904 261 5569",
    "sg:postcode":"32034",
    "sg:province":"FL",
    "sg:tags":[
        "shellfish",
        "fishing"
    ],
    "wof:name":"Rushton Seafood",
    "wof:placetype":"venue"
},
  "geometry": {"coordinates":[-81.45564,30.63599],"type":"Point"}
}