{
  "type": "Feature",
  "properties": {
    "iso:country":"US",
    "sg:address":"270 Biscayne Boulevard Way",
    "sg:city":"Miami",
    "sg:classifiers":[
        {
            "category":"Health Services",
            "subcategory":"Clinic",
            "type":"Services"
        }
    ],
    "sg:phone":"+1 786 347 5768",
    "sg:postcode":"33131",
    "sg:province":"FL",
    "sg:tags":[
        "spa",
        "medical"
    ],
    "sg:website":"http://mindbodyspa6.reachlocal.com/?scid=1861528",
    "wof:name":"Exhale MindBody Spa Miami",
    "wof:placetype":"venue"
},
  "geometry": {"coordinates":[-80.189052,25.770933],"type":"Point"}
}