{
  "type": "Feature",
  "properties": {
    "iso:country":"US",
    "sg:address":"41991 Little Farm Rd",
    "sg:city":"Punta Gorda",
    "sg:classifiers":[
        {
            "category":"Freight",
            "type":"Transportation"
        }
    ],
    "sg:phone":"+1 239 543 8768",
    "sg:postcode":"33982",
    "sg:province":"FL",
    "sg:tags":[
        "recreational",
        "vehicle"
    ],
    "wof:name":"Highway 31 Storage",
    "wof:placetype":"venue"
},
  "geometry": {"coordinates":[-81.79622000000001,26.789826],"type":"Point"}
}