{
  "type": "Feature",
  "properties": {
    "iso:country":"US",
    "sg:address":"1121 Virginia Dr",
    "sg:city":"Orlando",
    "sg:classifiers":[
        {
            "category":"Shopping",
            "subcategory":"Computers & Home Electronics",
            "type":"Retail Goods"
        },
        {
            "category":"Professional",
            "subcategory":"Computer Services",
            "type":"Services"
        }
    ],
    "sg:phone":"+1 407 898 8886",
    "sg:postcode":"32803",
    "sg:province":"FL",
    "sg:tags":[
        "repair",
        "sales"
    ],
    "sg:website":"www.myadvantagecomputers.com",
    "wof:name":"Advantage Computers Inc",
    "wof:placetype":"venue"
},
  "geometry": {"coordinates":[-81.36449,28.564114],"type":"Point"}
}