{
  "type": "Feature",
  "properties": {
    "iso:country":"US",
    "sg:address":"718 NE 1st St",
    "sg:city":"Boynton Beach",
    "sg:classifiers":[
        {
            "category":"Building & Trades",
            "subcategory":"Landscaping Services",
            "type":"Services"
        }
    ],
    "sg:phone":"+1 561 732 9352",
    "sg:postcode":"33435",
    "sg:province":"FL",
    "wof:name":"Otis Lawn Care",
    "wof:placetype":"venue"
},
  "geometry": {"coordinates":[-80.06219400000001,26.533511],"type":"Point"}
}