{
  "type": "Feature",
  "properties": {
    "iso:country":"US",
    "sg:address":"145 Lookout Dr",
    "sg:city":"Apollo Beach",
    "sg:classifiers":[
        {
            "category":"Shopping",
            "type":"Retail Goods"
        }
    ],
    "sg:phone":"+1 813 645 1716",
    "sg:postcode":"33572",
    "sg:province":"FL",
    "sg:tags":[
        "merchandise"
    ],
    "wof:name":"Supplies On Spot",
    "wof:placetype":"venue"
},
  "geometry": {"coordinates":[-82.39521000000001,27.768733],"type":"Point"}
}