{
  "type": "Feature",
  "properties": {
    "addr:full":"13255 SW 137th Ave Miami FL 33186",
    "addr:housenumber":"13255",
    "addr:postcode":"33186",
    "addr:street":"Sw 137Th Ave",
    "iso:country":"US",
    "sg:address":"13255 SW 137th Ave",
    "sg:city":"Miami",
    "sg:classifiers":[
        {
            "category":"Travel",
            "subcategory":"Travel Agent",
            "type":"Entertainment"
        }
    ],
    "sg:phone":"+1 305 232 5322",
    "sg:postcode":"33186",
    "sg:province":"FL",
    "sg:tags":[
        "consultant",
        "transportation"
    ],
    "wof:name":"AGA Express Corp",
    "wof:placetype":"venue"
},
  "geometry": {"coordinates":[-80.41498900000001,25.643822],"type":"Point"}
}