{
  "type": "Feature",
  "properties": {
    "addr:full":"135 N US Highway 17 92 Longwood FL 32750",
    "addr:housenumber":"135;92",
    "addr:postcode":"32750",
    "addr:street":"N Us Highway 17",
    "iso:country":"US",
    "sg:address":"135 N US Highway 17 92",
    "sg:city":"Longwood",
    "sg:classifiers":[
        {
            "category":"Shopping",
            "subcategory":"Jewelry",
            "type":"Retail Goods"
        },
        {
            "category":"Shopping",
            "subcategory":"Pawn Shop",
            "type":"Retail Goods"
        }
    ],
    "sg:phone":"+1 407 695 7400",
    "sg:postcode":"32750",
    "sg:province":"FL",
    "sg:website":"www.cashamerica.com",
    "wof:name":"Cash America Pawn",
    "wof:placetype":"venue"
},
  "geometry": {"coordinates":[-81.32675500000001,28.698506],"type":"Point"}
}