{
  "type": "Feature",
  "properties": {
    "iso:country":"US",
    "sg:address":"875 Cosmos Ct",
    "sg:city":"West Palm Beach",
    "sg:classifiers":[
        {
            "category":"Building & Trades",
            "subcategory":"Construction",
            "type":"Services"
        }
    ],
    "sg:phone":"+1 561 784 8432",
    "sg:postcode":"33414",
    "sg:province":"FL",
    "sg:tags":[
        "industrial"
    ],
    "wof:name":"Big Enterprises Inc",
    "wof:placetype":"venue"
},
  "geometry": {"coordinates":[-80.26599899999999,26.668389],"type":"Point"}
}