{
  "type": "Feature",
  "properties": {
    "addr:full":"5123 State Rd 54 New Port Richey FL 34652",
    "addr:housenumber":"5123;54",
    "addr:postcode":"34652",
    "addr:street":"State Rd",
    "iso:country":"US",
    "sg:address":"5123 State Rd 54",
    "sg:city":"New Port Richey",
    "sg:classifiers":[
        {
            "category":"Personal",
            "subcategory":"Beauty Salon",
            "type":"Services"
        }
    ],
    "sg:phone":"+1 727 849 8873",
    "sg:postcode":"34652",
    "sg:province":"FL",
    "sg:tags":[
        "shop"
    ],
    "wof:name":"Cameo Beauty Salon",
    "wof:placetype":"venue"
},
  "geometry": {"coordinates":[-82.728615,28.217024],"type":"Point"}
}