{
  "type": "Feature",
  "properties": {
    "iso:country":"US",
    "sg:address":"3656 Stokes Dr",
    "sg:city":"Sarasota",
    "sg:classifiers":[
        {
            "category":"Building & Trades",
            "subcategory":"Construction",
            "type":"Services"
        }
    ],
    "sg:phone":"+1 941 371 6419",
    "sg:postcode":"34232",
    "sg:province":"FL",
    "sg:tags":[
        "house"
    ],
    "wof:name":"Superior Construction Saras",
    "wof:placetype":"venue"
},
  "geometry": {"coordinates":[-82.465031,27.303987],"type":"Point"}
}