{
  "type": "Feature",
  "properties": {
    "addr:full":"3585 SW Corporate Pkwy Palm City FL 34990",
    "addr:housenumber":"3585",
    "addr:postcode":"34990",
    "addr:street":"Sw Corporate Pkwy",
    "iso:country":"US",
    "sg:address":"3585 SW Corporate Pkwy",
    "sg:city":"Palm City",
    "sg:classifiers":[
        {
            "category":"Building & Trades",
            "subcategory":"Construction",
            "type":"Services"
        }
    ],
    "sg:phone":"+1 772 286 9090",
    "sg:postcode":"34990",
    "sg:province":"FL",
    "sg:tags":[
        "home",
        "builder"
    ],
    "wof:name":"Mercedes Homes Inc",
    "wof:placetype":"venue"
},
  "geometry": {"coordinates":[-80.30016000000001,27.166795],"type":"Point"}
}