{
  "type": "Feature",
  "properties": {
    "addr:full":"12 S Lake Ave Avon Park FL 33825",
    "addr:housenumber":"12",
    "addr:postcode":"33825",
    "addr:street":"S Lake Ave",
    "iso:country":"US",
    "sg:address":"12 S Lake Ave",
    "sg:city":"Avon Park",
    "sg:classifiers":[
        {
            "category":"Insurance",
            "subcategory":"Title Insurance",
            "type":"Services"
        }
    ],
    "sg:phone":"+1 863 452 6777",
    "sg:postcode":"33825",
    "sg:province":"FL",
    "wof:name":"South Ridge Abstract & Title",
    "wof:placetype":"venue"
},
  "geometry": {"coordinates":[-81.502168,27.595149],"type":"Point"}
}