{
  "type": "Feature",
  "properties": {
    "iso:country":"US",
    "sg:address":"506 Lincoln Rd",
    "sg:city":"Miami Beach",
    "sg:classifiers":[
        {
            "category":"Professional",
            "subcategory":"Lawyer & Legal Services",
            "type":"Services"
        }
    ],
    "sg:phone":"+1 305 532 7800",
    "sg:postcode":"33139",
    "sg:province":"FL",
    "sg:tags":[
        "attorney"
    ],
    "wof:name":"Affordable Title",
    "wof:placetype":"venue"
},
  "geometry": {"coordinates":[-80.13422300000001,25.79055],"type":"Point"}
}