{
  "type": "Feature",
  "properties": {
    "addr:full":"1100 Lee Wagener Blvd Fort Lauderdale FL 33315",
    "addr:housenumber":"1100",
    "addr:postcode":"33315",
    "addr:street":"Lee Wagener Blvd",
    "iso:country":"US",
    "sg:address":"1100 Lee Wagener Blvd",
    "sg:city":"Fort Lauderdale",
    "sg:classifiers":[
        {
            "category":"Government",
            "subcategory":"Office",
            "type":"Public Place"
        }
    ],
    "sg:phone":"+1 954 359 7939",
    "sg:postcode":"33315",
    "sg:province":"FL",
    "sg:tags":[
        "federal",
        "program"
    ],
    "wof:name":"US Agricultural Dept",
    "wof:placetype":"venue"
},
  "geometry": {"coordinates":[-80.155023,26.070225],"type":"Point"}
}