{
  "type": "Feature",
  "properties": {
    "addr:full":"1151 Hammond Blvd Jacksonville FL 32221",
    "addr:housenumber":"1151",
    "addr:postcode":"32221",
    "addr:street":"Hammond Blvd",
    "iso:country":"US",
    "sg:address":"1151 Hammond Blvd",
    "sg:city":"Jacksonville",
    "sg:classifiers":[
        {
            "category":"Building & Trades",
            "subcategory":"Construction",
            "type":"Services"
        }
    ],
    "sg:phone":"+1 904 781 3319",
    "sg:postcode":"32221",
    "sg:province":"FL",
    "sg:tags":[
        "contractor"
    ],
    "wof:name":"Paul Hershberger Masonry",
    "wof:placetype":"venue"
},
  "geometry": {"coordinates":[-81.795772,30.304082],"type":"Point"}
}