{
  "type": "Feature",
  "properties": {
    "iso:country":"US",
    "sg:address":"1070 E Indiantown Rd",
    "sg:city":"Jupiter",
    "sg:classifiers":[
        {
            "category":"Professional",
            "subcategory":"Business Services",
            "type":"Services"
        }
    ],
    "sg:phone":"+1 561 684 6664",
    "sg:postcode":"33477",
    "sg:province":"FL",
    "wof:name":"Quik Shred",
    "wof:placetype":"venue"
},
  "geometry": {"coordinates":[-80.074648,26.933805],"type":"Point"}
}