{
  "type": "Feature",
  "properties": {
    "addr:full":"129 NW 13th St Boca Raton FL 33432",
    "addr:housenumber":"129",
    "addr:postcode":"33432",
    "addr:street":"Nw 13Th St",
    "iso:country":"US",
    "sg:address":"129 NW 13th St",
    "sg:city":"Boca Raton",
    "sg:classifiers":[
        {
            "category":"Manufacturing",
            "subcategory":"Metals",
            "type":"Manufacturing & Wholesale Goods"
        }
    ],
    "sg:phone":"+1 561 362 3932",
    "sg:postcode":"33432",
    "sg:province":"FL",
    "sg:tags":[
        "coating",
        "powder"
    ],
    "wof:name":"Flocoat Inc",
    "wof:placetype":"venue"
},
  "geometry": {"coordinates":[-80.08984,26.362043],"type":"Point"}
}