{
  "type": "Feature",
  "properties": {
    "iso:country":"US",
    "sg:address":"2551 S Nashville Ave",
    "sg:city":"Orlando",
    "sg:classifiers":[
        {
            "category":"Manufacturing",
            "subcategory":"Rubber & Plastics",
            "type":"Manufacturing & Wholesale Goods"
        },
        {
            "category":"Retail",
            "subcategory":"Repair Shop",
            "type":"Services"
        },
        {
            "category":"Wholesale",
            "subcategory":"Machinery & Supplies",
            "type":"Manufacturing & Wholesale Goods"
        },
        {
            "category":"Shopping",
            "subcategory":"Crafts & Fabrics",
            "type":"Retail Goods"
        }
    ],
    "sg:phone":"+1 407 425 2280",
    "sg:postcode":"32805",
    "sg:province":"FL",
    "sg:tags":[
        "sponge",
        "foam",
        "upholstery",
        "upholsterer"
    ],
    "wof:name":"Tropical Decorators And Upholstery",
    "wof:placetype":"venue"
},
  "geometry": {"coordinates":[-81.39913900000001,28.5159],"type":"Point"}
}