{
  "type": "Feature",
  "properties": {
    "iso:country":"US",
    "sg:address":"12101 N.56th St.",
    "sg:city":"Tampa",
    "sg:classifiers":[
        {
            "category":"Arts & Performance",
            "subcategory":"Dance",
            "type":"Entertainment"
        }
    ],
    "sg:phone":"+1 813 919 8539",
    "sg:postcode":"33617",
    "sg:province":"FL",
    "sg:website":"http://www.dancewithustampa.com",
    "wof:name":"Dance With Us Tampa",
    "wof:placetype":"venue"
},
  "geometry": {"coordinates":[-82.39357800000001,28.057647],"type":"Point"}
}