{
  "type": "Feature",
  "properties": {
    "addr:full":"2705 NW 109th Ave Doral FL 33172",
    "addr:housenumber":"2705",
    "addr:postcode":"33172",
    "addr:street":"Nw 109Th Ave",
    "iso:country":"US",
    "sg:address":"2705 NW 109th Ave",
    "sg:city":"Doral",
    "sg:classifiers":[
        {
            "category":"Professional",
            "subcategory":"Management & Consulting",
            "type":"Services"
        }
    ],
    "sg:phone":"+1 305 599 0155",
    "sg:postcode":"33172",
    "sg:province":"FL",
    "sg:tags":[
        "consultant",
        "business"
    ],
    "wof:name":"International Business Trade",
    "wof:placetype":"venue"
},
  "geometry": {"coordinates":[-80.373687,25.800499],"type":"Point"}
}