{
  "type": "Feature",
  "properties": {
    "iso:country":"US",
    "sg:address":"41219 Highway 27",
    "sg:city":"Davenport",
    "sg:classifiers":[
        {
            "category":"Organizations",
            "subcategory":"Religious Organization",
            "type":"Services"
        }
    ],
    "sg:phone":"+1 863 420 7000",
    "sg:postcode":"33837",
    "sg:province":"FL",
    "sg:website":"www.ag.org",
    "wof:name":"Ridge Assembly of God",
    "wof:placetype":"venue"
},
  "geometry": {"coordinates":[-81.620499,28.1891],"type":"Point"}
}