{
  "type": "Feature",
  "properties": {
    "addr:full":"926 9th Ave S Jacksonville Bch FL 32250",
    "addr:housenumber":"926",
    "addr:postcode":"32250",
    "addr:street":"9Th Ave S",
    "iso:country":"US",
    "sg:address":"926 9th Ave S",
    "sg:city":"Jacksonville Bch",
    "sg:classifiers":[
        {
            "category":"Building & Trades",
            "subcategory":"Electrical",
            "type":"Services"
        }
    ],
    "sg:phone":"+1 904 221 0430",
    "sg:postcode":"32250",
    "sg:province":"FL",
    "sg:tags":[
        "lighting",
        "landscape"
    ],
    "sg:website":"www.gatorirrigation.com",
    "wof:name":"Gator Irrigation Inc",
    "wof:placetype":"venue"
},
  "geometry": {"coordinates":[-81.39750600000001,30.278547],"type":"Point"}
}