{
  "type": "Feature",
  "properties": {
    "iso:country":"US",
    "sg:address":"238 Ponte Vedra Park Dr",
    "sg:city":"Ponte Vedra Bch",
    "sg:classifiers":[
        {
            "category":"Insurance",
            "subcategory":"Insurance Agent",
            "type":"Services"
        }
    ],
    "sg:phone":"+1 904 246 5250",
    "sg:postcode":"32082",
    "sg:province":"FL",
    "sg:website":"www.montoyabrower.com",
    "wof:name":"Montoya Brower & Assoc",
    "wof:placetype":"venue"
},
  "geometry": {"coordinates":[-81.387913,30.246572],"type":"Point"}
}