{
  "type": "Feature",
  "properties": {
    "iso:country":"US",
    "sg:address":"2382 Havana Dr",
    "sg:city":"Clearwater",
    "sg:classifiers":[
        {
            "category":"Food & Beverages",
            "subcategory":"Specialty",
            "type":"Retail Goods"
        }
    ],
    "sg:phone":"+1 727 531 8173",
    "sg:postcode":"33764",
    "sg:province":"FL",
    "wof:name":"Tom Foods",
    "wof:placetype":"venue"
},
  "geometry": {"coordinates":[-82.73738899999999,27.939978],"type":"Point"}
}