{
  "type": "Feature",
  "properties": {
    "iso:country":"US",
    "sg:address":"14849 SW 176th Ter",
    "sg:city":"Miami",
    "sg:classifiers":[
        {
            "category":"Farming",
            "subcategory":"Farm",
            "type":"Manufacturing & Wholesale Goods"
        },
        {
            "category":"Wholesale",
            "subcategory":"Fruits & Vegetables",
            "type":"Manufacturing & Wholesale Goods"
        }
    ],
    "sg:phone":"+1 786 573 0315",
    "sg:postcode":"33187",
    "sg:province":"FL",
    "sg:tags":[
        "packaging",
        "veg",
        "fresh",
        "also"
    ],
    "wof:name":"Sardinas Farms Inc",
    "wof:placetype":"venue"
},
  "geometry": {"coordinates":[-80.431144,25.602862],"type":"Point"}
}