{
  "type": "Feature",
  "properties": {
    "iso:country":"US",
    "sg:address":"36 NE 1st St",
    "sg:city":"Miami",
    "sg:classifiers":[
        {
            "category":"Manufacturing",
            "subcategory":"Metals",
            "type":"Manufacturing & Wholesale Goods"
        }
    ],
    "sg:phone":"+1 305 808 0989",
    "sg:postcode":"33132",
    "sg:province":"FL",
    "sg:tags":[
        "diamond",
        "setter"
    ],
    "wof:name":"Matanzas Diamond Setter",
    "wof:placetype":"venue"
},
  "geometry": {"coordinates":[-80.193207,25.77511],"type":"Point"}
}