{
  "type": "Feature",
  "properties": {
    "iso:country":"US",
    "sg:address":"633 Dunlawton Ave",
    "sg:city":"Port Orange",
    "sg:classifiers":[
        {
            "category":"Health Services",
            "subcategory":"Doctor",
            "type":"Services"
        }
    ],
    "sg:phone":"+1 386 756 1945",
    "sg:postcode":"32127",
    "sg:province":"FL",
    "sg:tags":[
        "physician",
        "surgeon"
    ],
    "wof:name":"Atlantic Urological Assoc",
    "wof:placetype":"venue"
},
  "geometry": {"coordinates":[-80.996662,29.139285],"type":"Point"}
}