{
  "type": "Feature",
  "properties": {
    "iso:country":"US",
    "sg:address":"11177 Palmetto Ridge Dr",
    "sg:city":"Naples",
    "sg:classifiers":[
        {
            "category":"Professional",
            "subcategory":"Management & Consulting",
            "type":"Services"
        }
    ],
    "sg:phone":"+1 239 594 5461",
    "sg:postcode":"34110",
    "sg:province":"FL",
    "wof:name":"Stropes Assoc",
    "wof:placetype":"venue"
},
  "geometry": {"coordinates":[-81.758206,26.274122],"type":"Point"}
}