{
  "type": "Feature",
  "properties": {
    "iso:country":"US",
    "sg:address":"6793 E Colonial Dr",
    "sg:city":"Orlando",
    "sg:classifiers":[
        {
            "category":"Autos & Motor Vehicles",
            "subcategory":"Fuel & Gas Station",
            "type":"Retail Goods"
        }
    ],
    "sg:phone":"+1 407 275 2366",
    "sg:postcode":"32807",
    "sg:province":"FL",
    "sg:tags":[
        "oil"
    ],
    "wof:name":"Fina Express Mart",
    "wof:placetype":"venue"
},
  "geometry": {"coordinates":[-81.294831,28.566804],"type":"Point"}
}