{
  "type": "Feature",
  "properties": {
    "iso:country":"US",
    "sg:address":"1200 W Holden Ave Apt 101",
    "sg:city":"Orlando",
    "sg:classifiers":[
        {
            "category":"Building & Trades",
            "subcategory":"Construction",
            "type":"Services"
        }
    ],
    "sg:phone":"+1 407 744 6462",
    "sg:postcode":"32839",
    "sg:province":"FL",
    "sg:tags":[
        "carpenter"
    ],
    "wof:name":"Custom Carpentry Usa Inc",
    "wof:placetype":"venue"
},
  "geometry": {"coordinates":[-81.394902,28.49451],"type":"Point"}
}