{
  "type": "Feature",
  "properties": {
    "iso:country":"US",
    "sg:address":"1933 Crown Hill Blvd",
    "sg:city":"Orlando",
    "sg:classifiers":[
        {
            "category":"Coffee & Tea",
            "type":"Food & Drink"
        }
    ],
    "sg:phone":"+1 407 408 6132",
    "sg:postcode":"32828",
    "sg:province":"FL",
    "wof:name":"Green Beans - Organic Coffee",
    "wof:placetype":"venue"
},
  "geometry": {"coordinates":[-81.15531300000001,28.527211],"type":"Point"}
}