{
  "type": "Feature",
  "properties": {
    "iso:country":"US",
    "sg:address":"1258 Barrett Rd",
    "sg:city":"Fort Myers",
    "sg:classifiers":[
        {
            "category":"Building & Trades",
            "subcategory":"Construction",
            "type":"Services"
        }
    ],
    "sg:phone":"+1 239 995 0708",
    "sg:postcode":"33903",
    "sg:province":"FL",
    "sg:tags":[
        "hanging",
        "painter",
        "contractor"
    ],
    "wof:name":"Daniel Sheffler Painting Contr",
    "wof:placetype":"venue"
},
  "geometry": {"coordinates":[-81.909189,26.668107],"type":"Point"}
}