{
  "type": "Feature",
  "properties": {
    "addr:full":"4448 Inverrary Blvd Fort Lauderdale FL 33319",
    "addr:housenumber":"4448",
    "addr:postcode":"33319",
    "addr:street":"Inverrary Blvd",
    "iso:country":"US",
    "sg:address":"4448 Inverrary Blvd",
    "sg:city":"Fort Lauderdale",
    "sg:classifiers":[
        {
            "category":"Banks & Credit Unions",
            "subcategory":"Bank",
            "type":"Services"
        }
    ],
    "sg:phone":"+1 954 572 3113",
    "sg:postcode":"33319",
    "sg:province":"FL",
    "sg:tags":[
        "broker",
        "mortgage"
    ],
    "wof:name":"Genesis Business & Mortgage",
    "wof:placetype":"venue"
},
  "geometry": {"coordinates":[-80.23977499999999,26.179841],"type":"Point"}
}