{
  "type": "Feature",
  "properties": {
    "addr:full":"6168 4th Ave N St Petersburg FL 33710",
    "addr:housenumber":"6168",
    "addr:postcode":"33710",
    "addr:street":"4Th Ave N",
    "iso:country":"US",
    "sg:address":"6168 4th Ave N",
    "sg:city":"St Petersburg",
    "sg:classifiers":[
        {
            "category":"Professional",
            "subcategory":"Business Services",
            "type":"Services"
        }
    ],
    "sg:phone":"+1 727 344 3194",
    "sg:postcode":"33710",
    "sg:province":"FL",
    "sg:tags":[
        "auctioneer"
    ],
    "sg:website":"www.merchantssquare.com",
    "wof:name":"Merchants Square Inc",
    "wof:placetype":"venue"
},
  "geometry": {"coordinates":[-82.719003,27.77538],"type":"Point"}
}