{
  "type": "Feature",
  "properties": {
    "addr:full":"895 NE 118th Ave Rd Silver Springs FL 34488",
    "addr:housenumber":"895",
    "addr:postcode":"34488",
    "addr:street":"Ne 118Th Ave Rd",
    "iso:country":"US",
    "sg:address":"895 NE 118th Ave Rd",
    "sg:city":"Silver Springs",
    "sg:classifiers":[
        {
            "category":"Building & Trades",
            "subcategory":"Construction",
            "type":"Services"
        }
    ],
    "sg:phone":"+1 352 625 1592",
    "sg:postcode":"34488",
    "sg:province":"FL",
    "sg:tags":[
        "concrete",
        "contractor"
    ],
    "wof:name":"Robert Meade Concrete Contr",
    "wof:placetype":"venue"
},
  "geometry": {"coordinates":[-81.954195,29.193662],"type":"Point"}
}