{
  "type": "Feature",
  "properties": {
    "addr:full":"410 Glen Ridge Ave Tampa FL 33617",
    "addr:housenumber":"410",
    "addr:postcode":"33617",
    "addr:street":"Glen Ridge Ave",
    "iso:country":"US",
    "sg:address":"410 Glen Ridge Ave",
    "sg:city":"Tampa",
    "sg:classifiers":[
        {
            "category":"Building & Trades",
            "subcategory":"Plumbing",
            "type":"Services"
        }
    ],
    "sg:phone":"+1 813 987 2809",
    "sg:postcode":"33617",
    "sg:province":"FL",
    "sg:tags":[
        "plumbing",
        "industrial",
        "commercial"
    ],
    "wof:name":"Florida Industrial Plbg LLC",
    "wof:placetype":"venue"
},
  "geometry": {"coordinates":[-82.384815,28.040561],"type":"Point"}
}