{
  "type": "Feature",
  "properties": {
    "iso:country":"US",
    "sg:address":"2050 Franklin St",
    "sg:city":"Jacksonville",
    "sg:classifiers":[
        {
            "category":"Social Services",
            "subcategory":"Child Care",
            "type":"Services"
        }
    ],
    "sg:phone":"+1 904 798 8706",
    "sg:postcode":"32206",
    "sg:province":"FL",
    "wof:name":"Thomas & Prince Daycare",
    "wof:placetype":"venue"
},
  "geometry": {"coordinates":[-81.63955199999999,30.34954],"type":"Point"}
}