{
  "type": "Feature",
  "properties": {
    "iso:country":"US",
    "sg:address":"166 Derby Woods Dr",
    "sg:city":"Lynn Haven",
    "sg:classifiers":[
        {
            "category":"Communications",
            "subcategory":"Film & Video Production",
            "type":"Services"
        }
    ],
    "sg:phone":"+1 850 271 0826",
    "sg:postcode":"32444",
    "sg:province":"FL",
    "sg:tags":[
        "taping"
    ],
    "wof:name":"Digital Imagery",
    "wof:placetype":"venue"
},
  "geometry": {"coordinates":[-85.620726,30.237852],"type":"Point"}
}