{
  "type": "Feature",
  "properties": {
    "addr:full":"5914 Bartram St Boca Raton FL 33433",
    "addr:housenumber":"5914",
    "addr:postcode":"33433",
    "addr:street":"Bartram St",
    "iso:country":"US",
    "sg:address":"5914 Bartram St",
    "sg:city":"Boca Raton",
    "sg:classifiers":[
        {
            "category":"Professional",
            "type":"Services"
        }
    ],
    "sg:phone":"+1 561 393 3262",
    "sg:postcode":"33433",
    "sg:province":"FL",
    "wof:name":"Janice P Boothe Rcdd Inc",
    "wof:placetype":"venue"
},
  "geometry": {"coordinates":[-80.13534,26.331294],"type":"Point"}
}