{
  "type": "Feature",
  "properties": {
    "iso:country":"US",
    "sg:address":"180 W 50th St",
    "sg:city":"Hialeah",
    "sg:classifiers":[
        {
            "category":"Personal",
            "subcategory":"Beauty Salon",
            "type":"Services"
        }
    ],
    "sg:phone":"+1 305 826 1015",
    "sg:postcode":"33012",
    "sg:province":"FL",
    "sg:tags":[
        "shop"
    ],
    "wof:name":"Waves Investments Corp",
    "wof:placetype":"venue"
},
  "geometry": {"coordinates":[-80.285267,25.86767],"type":"Point"}
}