{
  "type": "Feature",
  "properties": {
    "addr:full":"2944 Ocean Shore Blvd Ormond Beach FL 32176",
    "addr:housenumber":"2944",
    "addr:postcode":"32176",
    "addr:street":"Ocean Shore Blvd",
    "iso:country":"US",
    "sg:address":"2944 Ocean Shore Blvd",
    "sg:city":"Ormond Beach",
    "sg:classifiers":[
        {
            "category":"Building & Trades",
            "subcategory":"Construction",
            "type":"Services"
        }
    ],
    "sg:phone":"+1 386 441 5282",
    "sg:postcode":"32176",
    "sg:province":"FL",
    "sg:tags":[
        "masonry",
        "contractor"
    ],
    "wof:name":"Colombo Construction Inc",
    "wof:placetype":"venue"
},
  "geometry": {"coordinates":[-81.07504400000001,29.366963],"type":"Point"}
}