{
  "type": "Feature",
  "properties": {
    "iso:country":"US",
    "sg:address":"5490 Yahl St",
    "sg:city":"Naples",
    "sg:classifiers":[
        {
            "category":"Building & Trades",
            "subcategory":"Construction",
            "type":"Services"
        }
    ],
    "sg:phone":"+1 239 593 1877",
    "sg:postcode":"34109",
    "sg:province":"FL",
    "sg:tags":[
        "maker",
        "cabinet"
    ],
    "wof:name":"Mica Specialists",
    "wof:placetype":"venue"
},
  "geometry": {"coordinates":[-81.777361,26.214132],"type":"Point"}
}