{
  "type": "Feature",
  "properties": {
    "iso:country":"US",
    "sg:address":"17322 Hubers Ct",
    "sg:city":"Odessa",
    "sg:classifiers":[
        {
            "category":"Banks & Credit Unions",
            "subcategory":"Investment Brokerage",
            "type":"Services"
        }
    ],
    "sg:phone":"+1 813 852 2426",
    "sg:postcode":"33556",
    "sg:province":"FL",
    "wof:name":"Edward Jones Co",
    "wof:placetype":"venue"
},
  "geometry": {"coordinates":[-82.57458200000001,28.123571],"type":"Point"}
}