{
  "type": "Feature",
  "properties": {
    "iso:country":"US",
    "sg:address":"2035 NW 4th Ct",
    "sg:city":"Miami",
    "sg:classifiers":[
        {
            "category":"Government",
            "subcategory":"Office",
            "type":"Public Place"
        }
    ],
    "sg:phone":"+1 305 438 8600",
    "sg:postcode":"33127",
    "sg:province":"FL",
    "wof:name":"Dade County Employment Svc Bur",
    "wof:placetype":"venue"
},
  "geometry": {"coordinates":[-80.20242399999999,25.795927],"type":"Point"}
}