{
  "type": "Feature",
  "properties": {
    "addr:full":"2015 N Atlantic Ave Cocoa Beach FL 32931",
    "addr:housenumber":"2015",
    "addr:postcode":"32931",
    "addr:street":"N Atlantic Ave",
    "iso:country":"US",
    "sg:address":"2015 N Atlantic Ave",
    "sg:city":"Cocoa Beach",
    "sg:classifiers":[
        {
            "category":"Personal",
            "subcategory":"Nail Salon",
            "type":"Services"
        }
    ],
    "sg:phone":"+1 321 799 0844",
    "sg:postcode":"32931",
    "sg:province":"FL",
    "wof:name":"Hollywood Nails",
    "wof:placetype":"venue"
},
  "geometry": {"coordinates":[-80.6101,28.3417],"type":"Point"}
}