{
  "type": "Feature",
  "properties": {
    "iso:country":"US",
    "sg:address":"4860 48th Ave N",
    "sg:city":"Saint Petersburg",
    "sg:classifiers":[
        {
            "category":"Shopping",
            "subcategory":"Jewelry",
            "type":"Retail Goods"
        }
    ],
    "sg:phone":"+1 727 527 9192",
    "sg:postcode":"33714",
    "sg:province":"FL",
    "sg:tags":[
        "stone",
        "sewing",
        "sup"
    ],
    "wof:name":"Lizs Needle Arts",
    "wof:placetype":"venue"
},
  "geometry": {"coordinates":[-82.696532,27.815597],"type":"Point"}
}