{
  "type": "Feature",
  "properties": {
    "iso:country":"US",
    "sg:address":"266 Ridgewood Ave",
    "sg:city":"Daytona Beach",
    "sg:classifiers":[
        {
            "category":"Retail",
            "subcategory":"Auto Rental",
            "type":"Services"
        }
    ],
    "sg:phone":"+1 386 255 5520",
    "sg:postcode":"32117",
    "sg:province":"FL",
    "sg:tags":[
        "passenger",
        "used",
        "car",
        "automobile"
    ],
    "wof:name":"Riviera Auto Sales South",
    "wof:placetype":"venue"
},
  "geometry": {"coordinates":[-81.033738,29.231059],"type":"Point"}
}