{
  "type": "Feature",
  "properties": {
    "addr:full":"401 S H St Lake Worth FL 33460",
    "addr:housenumber":"401",
    "addr:postcode":"33460",
    "addr:street":"S H St",
    "iso:country":"US",
    "sg:address":"401 S H St",
    "sg:city":"Lake Worth",
    "sg:classifiers":[
        {
            "category":"Building & Trades",
            "subcategory":"Equipment Rental",
            "type":"Services"
        }
    ],
    "sg:phone":"+1 561 588 7880",
    "sg:postcode":"33460",
    "sg:province":"FL",
    "sg:tags":[
        "leasing"
    ],
    "wof:name":"William Thies & Sons Inc",
    "wof:placetype":"venue"
},
  "geometry": {"coordinates":[-80.05856799999999,26.609859],"type":"Point"}
}