{
  "type": "Feature",
  "properties": {
    "addr:full":"150 N Atlantic Ave Cocoa Beach FL 32931",
    "addr:housenumber":"150",
    "addr:postcode":"32931",
    "addr:street":"N Atlantic Ave",
    "iso:country":"US",
    "sg:address":"150 N Atlantic Ave",
    "sg:city":"Cocoa Beach",
    "sg:classifiers":[
        {
            "category":"Real Estate",
            "subcategory":"Real Estate Agent",
            "type":"Services"
        }
    ],
    "sg:phone":"+1 321 783 9350",
    "sg:postcode":"32931",
    "sg:province":"FL",
    "wof:name":"Barley & Weese Properties",
    "wof:placetype":"venue"
},
  "geometry": {"coordinates":[-80.608868,28.321077],"type":"Point"}
}