{
  "type": "Feature",
  "properties": {
    "addr:full":"9160 Roe St Pensacola FL 32514",
    "addr:housenumber":"9160",
    "addr:postcode":"32514",
    "addr:street":"Roe St",
    "iso:country":"US",
    "sg:address":"9160 Roe St",
    "sg:city":"Pensacola",
    "sg:classifiers":[
        {
            "category":"Professional",
            "subcategory":"Computer Services",
            "type":"Services"
        }
    ],
    "sg:phone":"+1 850 473 6573",
    "sg:postcode":"32514",
    "sg:province":"FL",
    "sg:tags":[
        "c",
        "design",
        "system",
        "telephone"
    ],
    "wof:name":"Nusa Group",
    "wof:placetype":"venue"
},
  "geometry": {"coordinates":[-87.20192299999999,30.528386],"type":"Point"}
}