{
  "type": "Feature",
  "properties": {
    "iso:country":"US",
    "sg:address":"134 Sunrise Blvd",
    "sg:city":"De Bary",
    "sg:classifiers":[
        {
            "category":"Building & Trades",
            "subcategory":"Construction",
            "type":"Services"
        }
    ],
    "sg:phone":"+1 386 668 6942",
    "sg:postcode":"32713",
    "sg:province":"FL",
    "sg:tags":[
        "carpentry",
        "contractor"
    ],
    "wof:name":"Hartmann of Florida",
    "wof:placetype":"venue"
},
  "geometry": {"coordinates":[-81.30120100000001,28.872328],"type":"Point"}
}