{
  "type": "Feature",
  "properties": {
    "iso:country":"US",
    "sg:address":"711-A North Orange Ave",
    "sg:city":"Winter Park",
    "sg:classifiers":[
        {
            "category":"Personal",
            "subcategory":"Massage",
            "type":"Services"
        }
    ],
    "sg:phone":"+1 407 461 1795",
    "sg:postcode":"32789",
    "sg:province":"FL",
    "sg:website":"www.wannamellow.com",
    "wof:name":"mellow",
    "wof:placetype":"venue"
},
  "geometry": {"coordinates":[-81.358146,28.591949],"type":"Point"}
}