{
  "type": "Feature",
  "properties": {
    "iso:country":"US",
    "sg:address":"7482 NE Jacksonville Rd",
    "sg:city":"Ocala",
    "sg:classifiers":[
        {
            "category":"Real Estate",
            "subcategory":"Real Estate Services",
            "type":"Services"
        },
        {
            "category":"Real Estate",
            "subcategory":"Real Estate Agent",
            "type":"Services"
        }
    ],
    "sg:phone":"+1 352 351 1911",
    "sg:postcode":"34479",
    "sg:province":"FL",
    "sg:tags":[
        "buyer",
        "broker"
    ],
    "wof:name":"Ronald Alan Weiss Real Estate",
    "wof:placetype":"venue"
},
  "geometry": {"coordinates":[-82.112144,29.264847],"type":"Point"}
}