{
  "type": "Feature",
  "properties": {
    "addr:full":"101 S Manatee Ave Arcadia FL 34266",
    "addr:housenumber":"101",
    "addr:postcode":"34266",
    "addr:street":"S Manatee Ave",
    "iso:country":"US",
    "sg:address":"101 S Manatee Ave",
    "sg:city":"Arcadia",
    "sg:classifiers":[
        {
            "category":"Arts & Performance",
            "subcategory":"Theater",
            "type":"Entertainment"
        }
    ],
    "sg:phone":"+1 863 494 4888",
    "sg:postcode":"34266",
    "sg:province":"FL",
    "sg:tags":[
        "bureau"
    ],
    "wof:name":"King's Ransome Entrtn Inc",
    "wof:placetype":"venue"
},
  "geometry": {"coordinates":[-81.86511,27.21588],"type":"Point"}
}