{
  "type": "Feature",
  "properties": {
    "iso:country":"US",
    "sg:address":"372 Oak Springs Ct",
    "sg:city":"Debary",
    "sg:classifiers":[
        {
            "category":"Real Estate",
            "subcategory":"Real Estate Agent",
            "type":"Services"
        }
    ],
    "sg:phone":"+1 407 302 5929",
    "sg:postcode":"32713",
    "sg:province":"FL",
    "sg:tags":[
        "appraiser"
    ],
    "wof:name":"First Orlando Appraisal",
    "wof:placetype":"venue"
},
  "geometry": {"coordinates":[-81.321709,28.870752],"type":"Point"}
}