{
  "type": "Feature",
  "properties": {
    "addr:full":"101 SE 2 Pl Gainesville FL 32601",
    "addr:housenumber":"101;2",
    "addr:postcode":"32601",
    "addr:street":"Se;Pl",
    "iso:country":"US",
    "sg:address":"101 SE 2 Pl",
    "sg:city":"Gainesville",
    "sg:classifiers":[
        {
            "category":"Professional",
            "subcategory":"Advertising",
            "type":"Services"
        }
    ],
    "sg:phone":"+1 352 378 1223",
    "sg:postcode":"32601",
    "sg:province":"FL",
    "sg:tags":[
        "counselor"
    ],
    "wof:name":"Communications A LA Carte",
    "wof:placetype":"venue"
},
  "geometry": {"coordinates":[-82.323092,29.649656],"type":"Point"}
}