{
  "type": "Feature",
  "properties": {
    "addr:full":"22756 Marbella Cir Boca Raton FL 33433",
    "addr:housenumber":"22756",
    "addr:postcode":"33433",
    "addr:street":"Marbella Cir",
    "iso:country":"US",
    "sg:address":"22756 Marbella Cir",
    "sg:city":"Boca Raton",
    "sg:classifiers":[
        {
            "category":"Building & Trades",
            "subcategory":"Construction",
            "type":"Services"
        }
    ],
    "sg:phone":"+1 561 393 7559",
    "sg:postcode":"33433",
    "sg:province":"FL",
    "sg:tags":[
        "handyman"
    ],
    "wof:name":"Bob's Small Jobs",
    "wof:placetype":"venue"
},
  "geometry": {"coordinates":[-80.14316100000001,26.339036],"type":"Point"}
}