{
  "type": "Feature",
  "properties": {
    "addr:full":"1798 NW 9th Ave Okeechobee FL 34972",
    "addr:housenumber":"1798",
    "addr:postcode":"34972",
    "addr:street":"Nw 9Th Ave",
    "iso:country":"US",
    "sg:address":"1798 NW 9th Ave",
    "sg:city":"Okeechobee",
    "sg:classifiers":[
        {
            "category":"Government",
            "subcategory":"Office",
            "type":"Public Place"
        }
    ],
    "sg:phone":"+1 863 462 5819",
    "sg:postcode":"34972",
    "sg:province":"FL",
    "sg:tags":[
        "state",
        "program",
        "health"
    ],
    "wof:name":"Okeechobee County Health Dept",
    "wof:placetype":"venue"
},
  "geometry": {"coordinates":[-80.838427,27.261199],"type":"Point"}
}