{
  "type": "Feature",
  "properties": {
    "iso:country":"US",
    "sg:address":"1560 Semoran Blvd",
    "sg:city":"Winter Park",
    "sg:classifiers":[
        {
            "category":"Restaurant",
            "type":"Food & Drink"
        },
        {
            "category":"Bars & Pubs",
            "type":"Food & Drink"
        }
    ],
    "sg:phone":"+1 407 678 2388",
    "sg:postcode":"32792",
    "sg:province":"FL",
    "sg:tags":[
        "drinking"
    ],
    "wof:name":"Greek Flame Tavern",
    "wof:placetype":"venue"
},
  "geometry": {"coordinates":[-81.31564899999999,28.625183],"type":"Point"}
}