{
  "type": "Feature",
  "properties": {
    "iso:country":"US",
    "sg:address":"4474 W Mainmast Ct",
    "sg:city":"Fort Myers",
    "sg:classifiers":[
        {
            "category":"Shopping",
            "subcategory":"Clothing, Apparel, & Fashions",
            "type":"Retail Goods"
        }
    ],
    "sg:phone":"+1 239 481 8011",
    "sg:postcode":"33919",
    "sg:province":"FL",
    "sg:tags":[
        "sportswear"
    ],
    "wof:name":"Sportsmania",
    "wof:placetype":"venue"
},
  "geometry": {"coordinates":[-81.91579,26.549944],"type":"Point"}
}