{
  "type": "Feature",
  "properties": {
    "addr:full":"7371 Spring Hill Dr Spring Hill FL 34606",
    "addr:housenumber":"7371",
    "addr:postcode":"34606",
    "addr:street":"Spring Hill Dr",
    "iso:country":"US",
    "sg:address":"7371 Spring Hill Dr",
    "sg:city":"Spring Hill",
    "sg:classifiers":[
        {
            "category":"Home & Garden",
            "subcategory":"Furniture",
            "type":"Retail Goods"
        }
    ],
    "sg:phone":"+1 352 688 7040",
    "sg:postcode":"34606",
    "sg:province":"FL",
    "sg:tags":[
        "opera",
        "used",
        "local",
        "merchandise",
        "trucking"
    ],
    "wof:name":"Better New & Used Furniture",
    "wof:placetype":"venue"
},
  "geometry": {"coordinates":[-82.594548,28.451156],"type":"Point"}
}