{
  "type": "Feature",
  "properties": {
    "iso:country":"US",
    "sg:address":"11301 SW 40th St",
    "sg:city":"Miami",
    "sg:classifiers":[
        {
            "category":"Restaurant",
            "type":"Food & Drink"
        }
    ],
    "sg:menulink":"http://www.allmenus.com/fl/south-westside/187371-mcdonalds/menu/",
    "sg:phone":"+1 305 223 0179",
    "sg:postcode":"33165",
    "sg:province":"FL",
    "sg:tags":[
        "burger",
        "american"
    ],
    "wof:name":"McDonald's",
    "wof:placetype":"venue"
},
  "geometry": {"coordinates":[-80.379696,25.73217],"type":"Point"}
}