{
  "type": "Feature",
  "properties": {
    "iso:country":"US",
    "sg:address":"1189 E Altamonte Dr",
    "sg:city":"Orlando",
    "sg:classifiers":[
        {
            "category":"Building & Trades",
            "subcategory":"Locksmith",
            "type":"Services"
        }
    ],
    "sg:phone":"+1 877 813 7223",
    "sg:postcode":"32839",
    "sg:province":"FL",
    "sg:tags":[
        "key"
    ],
    "wof:name":"24 Emergency Locksmith",
    "wof:placetype":"venue"
},
  "geometry": {"coordinates":[-81.350404,28.663345],"type":"Point"}
}