{
  "type": "Feature",
  "properties": {
    "addr:full":"10135 Richardson Ct Orlando FL 32825",
    "addr:housenumber":"10135",
    "addr:postcode":"32825",
    "addr:street":"Richardson Ct",
    "iso:country":"US",
    "sg:address":"10135 Richardson Ct",
    "sg:city":"Orlando",
    "sg:classifiers":[
        {
            "category":"Professional",
            "subcategory":"Management & Consulting",
            "type":"Services"
        },
        {
            "category":"Professional",
            "subcategory":"Employment Agencies",
            "type":"Services"
        }
    ],
    "sg:phone":"+1 407 281 9174",
    "sg:postcode":"32825",
    "sg:province":"FL",
    "sg:tags":[
        "consultant",
        "resource",
        "human"
    ],
    "wof:name":"Horizon Industries",
    "wof:placetype":"venue"
},
  "geometry": {"coordinates":[-81.243189,28.55274],"type":"Point"}
}