{
  "type": "Feature",
  "properties": {
    "iso:country":"US",
    "sg:address":"601 Sabal Lake Dr",
    "sg:city":"Longwood",
    "sg:classifiers":[
        {
            "category":"Freight",
            "type":"Transportation"
        }
    ],
    "sg:phone":"+1 407 682 3078",
    "sg:postcode":"32779",
    "sg:province":"FL",
    "sg:tags":[
        "operator",
        "local",
        "trucking"
    ],
    "wof:name":"U S Delivery",
    "wof:placetype":"venue"
},
  "geometry": {"coordinates":[-81.41316500000001,28.703082],"type":"Point"}
}