{
  "type": "Feature",
  "properties": {
    "addr:full":"72 Miracle Mile Miami FL 33134",
    "addr:housenumber":"72",
    "addr:postcode":"33134",
    "addr:street":"Miracle Mile",
    "iso:country":"US",
    "sg:address":"72 Miracle Mile",
    "sg:city":"Miami",
    "sg:classifiers":[
        {
            "category":"Shopping",
            "subcategory":"Clothing, Apparel, & Fashions",
            "type":"Retail Goods"
        },
        {
            "category":"Manufacturing",
            "subcategory":"Building Materials",
            "type":"Manufacturing & Wholesale Goods"
        },
        {
            "category":"Sports & Exercise",
            "subcategory":"Playing Field",
            "type":"Entertainment"
        }
    ],
    "sg:phone":"+1 305 448 9386",
    "sg:postcode":"33134",
    "sg:province":"FL",
    "sg:tags":[
        "repairing",
        "storage",
        "fur",
        "remodeling"
    ],
    "wof:name":"Jennie's Furs",
    "wof:placetype":"venue"
},
  "geometry": {"coordinates":[-80.25620000000001,25.749726],"type":"Point"}
}