{
  "type": "Feature",
  "properties": {
    "addr:full":"683 Winyah Dr Orlando FL 32803",
    "addr:housenumber":"683",
    "addr:postcode":"32803",
    "addr:street":"Winyah Dr",
    "iso:country":"US",
    "sg:address":"683 Winyah Dr",
    "sg:city":"Orlando",
    "sg:classifiers":[
        {
            "category":"Wholesale",
            "subcategory":"Books, Periodicals, & Newspapers",
            "type":"Manufacturing & Wholesale Goods"
        }
    ],
    "sg:phone":"+1 407 303 1929",
    "sg:postcode":"32803",
    "sg:province":"FL",
    "sg:tags":[
        "publisher",
        "book"
    ],
    "wof:name":"Florida Hospital",
    "wof:placetype":"venue"
},
  "geometry": {"coordinates":[-81.368764,28.576662],"type":"Point"}
}