{
  "type": "Feature",
  "properties": {
    "iso:country":"US",
    "sg:address":"515 Mary Ave",
    "sg:city":"New Smyrna Beach",
    "sg:classifiers":[
        {
            "category":"Retail",
            "subcategory":"Car Wash",
            "type":"Services"
        }
    ],
    "sg:phone":"+1 386 428 2997",
    "sg:postcode":"32168",
    "sg:province":"FL",
    "sg:tags":[
        "automobile",
        "detail",
        "clean"
    ],
    "wof:name":"Lil Pop Detailing Svc",
    "wof:placetype":"venue"
},
  "geometry": {"coordinates":[-80.93057899999999,29.026957],"type":"Point"}
}