{
  "type": "Feature",
  "properties": {
    "iso:country":"US",
    "sg:address":"900 Canal St",
    "sg:city":"Jacksonville",
    "sg:classifiers":[
        {
            "category":"Freight",
            "type":"Transportation"
        }
    ],
    "sg:phone":"+1 904 981 2700",
    "sg:postcode":"32209",
    "sg:province":"FL",
    "sg:tags":[
        "delivery"
    ],
    "wof:name":"C D & L Inc",
    "wof:placetype":"venue"
},
  "geometry": {"coordinates":[-81.698684,30.33596],"type":"Point"}
}