{
  "type": "Feature",
  "properties": {
    "addr:full":"6928 Sawgrass Dr St Cloud FL 34771",
    "addr:housenumber":"6928",
    "addr:postcode":"34771",
    "addr:street":"Sawgrass Dr",
    "iso:country":"US",
    "sg:address":"6928 Sawgrass Dr",
    "sg:city":"St Cloud",
    "sg:classifiers":[
        {
            "category":"Building & Trades",
            "subcategory":"Cleaning & Sanitation",
            "type":"Services"
        }
    ],
    "sg:phone":"+1 407 957 3223",
    "sg:postcode":"34771",
    "sg:province":"FL",
    "sg:tags":[
        "janitor"
    ],
    "wof:name":"Last Detail LTD Inc",
    "wof:placetype":"venue"
},
  "geometry": {"coordinates":[-81.156648,28.244124],"type":"Point"}
}