{
  "type": "Feature",
  "properties": {
    "iso:country":"US",
    "sg:address":"6113 US Hwy 1",
    "sg:city":"Daytona Beach",
    "sg:classifiers":[
        {
            "category":"Autos & Motor Vehicles",
            "subcategory":"Automobile Sales",
            "type":"Retail Goods"
        }
    ],
    "sg:phone":"+1 386 761 8037",
    "sg:postcode":"32127",
    "sg:province":"FL",
    "sg:tags":[
        "car",
        "used",
        "dealer"
    ],
    "wof:name":"Moores Auto Sales",
    "wof:placetype":"venue"
},
  "geometry": {"coordinates":[-80.970619,29.091764],"type":"Point"}
}