{
  "type": "Feature",
  "properties": {
    "addr:full":"4625 US Hwy 1 Vero Beach FL 32905",
    "addr:housenumber":"4625",
    "addr:postcode":"32905",
    "addr:street":"Us Hwy 1",
    "iso:country":"US",
    "sg:address":"4625 US Hwy 1",
    "sg:city":"Vero Beach",
    "sg:classifiers":[
        {
            "category":"Real Estate",
            "subcategory":"Real Estate Agent",
            "type":"Services"
        }
    ],
    "sg:phone":"+1 772 234 3801",
    "sg:postcode":"32905",
    "sg:province":"FL",
    "wof:name":"Nichols and Associates",
    "wof:placetype":"venue"
},
  "geometry": {"coordinates":[-80.574907,28.025921],"type":"Point"}
}