{
  "type": "Feature",
  "properties": {
    "addr:full":"66 W Flagler St Ste 300 Miami FL 33130",
    "addr:housenumber":"66",
    "addr:postcode":"33130",
    "addr:street":"W Flagler St Ste 300",
    "iso:country":"US",
    "sg:address":"66 W Flagler St Ste 300",
    "sg:city":"Miami",
    "sg:classifiers":[
        {
            "category":"Professional",
            "subcategory":"Lawyer & Legal Services",
            "type":"Services"
        }
    ],
    "sg:phone":"+1 305 379 1500",
    "sg:postcode":"33130",
    "sg:province":"FL",
    "wof:name":"Property Tax Appeals Thomas R Post PA",
    "wof:placetype":"venue"
},
  "geometry": {"coordinates":[-80.194996,25.774072],"type":"Point"}
}