{
  "type": "Feature",
  "properties": {
    "addr:full":"4530 SW 25th Ter Fort Lauderdale FL 33312",
    "addr:housenumber":"4530",
    "addr:postcode":"33312",
    "addr:street":"Sw 25Th Ter",
    "iso:country":"US",
    "sg:address":"4530 SW 25th Ter",
    "sg:city":"Fort Lauderdale",
    "sg:classifiers":[
        {
            "category":"Shopping",
            "subcategory":"Clothing, Apparel, & Fashions",
            "type":"Retail Goods"
        }
    ],
    "sg:phone":"+1 954 981 6608",
    "sg:postcode":"33312",
    "sg:province":"FL",
    "wof:name":"Daniel A Sheila A Modas",
    "wof:placetype":"venue"
},
  "geometry": {"coordinates":[-80.174598,26.062977],"type":"Point"}
}