{
  "type": "Feature",
  "properties": {
    "addr:full":"117 1st Ave SW Largo FL 33770",
    "addr:housenumber":"117",
    "addr:postcode":"33770",
    "addr:street":"1St Ave Sw",
    "iso:country":"US",
    "sg:address":"117 1st Ave SW",
    "sg:city":"Largo",
    "sg:classifiers":[
        {
            "category":"Professional",
            "subcategory":"Lawyer & Legal Services",
            "type":"Services"
        }
    ],
    "sg:phone":"+1 727 584 8890",
    "sg:postcode":"33770",
    "sg:province":"FL",
    "sg:tags":[
        "litigation",
        "civil",
        "attorney",
        "law",
        "trial"
    ],
    "wof:name":"Dela Costa Neville Pa",
    "wof:placetype":"venue"
},
  "geometry": {"coordinates":[-82.788944,27.916023],"type":"Point"}
}