{
  "type": "Feature",
  "properties": {
    "addr:full":"2460 S Chaires Cross Roads Tallahassee FL 32317",
    "addr:housenumber":"2460",
    "addr:postcode":"32317",
    "addr:street":"S Chaires Cross Roads",
    "iso:country":"US",
    "sg:address":"2460 S Chaires Cross Roads",
    "sg:city":"Tallahassee",
    "sg:classifiers":[
        {
            "category":"Organizations",
            "subcategory":"Religious Organization",
            "type":"Services"
        }
    ],
    "sg:phone":"+1 850 878 1342",
    "sg:postcode":"32317",
    "sg:province":"FL",
    "sg:tags":[
        "church"
    ],
    "wof:name":"Shady Grove",
    "wof:placetype":"venue"
},
  "geometry": {"coordinates":[-84.12557,30.471117],"type":"Point"}
}