{
  "type": "Feature",
  "properties": {
    "iso:country":"US",
    "sg:address":"3045 N Federal Hwy",
    "sg:city":"Fort Lauderdale",
    "sg:classifiers":[
        {
            "category":"Bars & Pubs",
            "type":"Food & Drink"
        }
    ],
    "sg:phone":"+1 954 630 2856",
    "sg:postcode":"33306",
    "sg:province":"FL",
    "wof:name":"Briny Irish Pub",
    "wof:placetype":"venue"
},
  "geometry": {"coordinates":[-80.11610400000001,26.16568],"type":"Point"}
}