{
  "type": "Feature",
  "properties": {
    "addr:full":"4452 Timber Bluff Ct Jacksonville FL 32224",
    "addr:housenumber":"4452",
    "addr:postcode":"32224",
    "addr:street":"Timber Bluff Ct",
    "iso:country":"US",
    "sg:address":"4452 Timber Bluff Ct",
    "sg:city":"Jacksonville",
    "sg:classifiers":[
        {
            "category":"Building & Trades",
            "subcategory":"Construction",
            "type":"Services"
        }
    ],
    "sg:phone":"+1 904 813 3468",
    "sg:postcode":"32224",
    "sg:province":"FL",
    "sg:tags":[
        "restoration",
        "cleaning",
        "patio",
        "deck"
    ],
    "wof:name":"Pro-Tech Power Wash",
    "wof:placetype":"venue"
},
  "geometry": {"coordinates":[-81.489369,30.272126],"type":"Point"}
}