{
  "type": "Feature",
  "properties": {
    "iso:country":"US",
    "sg:address":"3801 Hogshead Rd",
    "sg:city":"Apopka",
    "sg:classifiers":[
        {
            "category":"Home & Garden",
            "subcategory":"Garden Supply",
            "type":"Retail Goods"
        }
    ],
    "sg:phone":"+1 407 886 1000",
    "sg:postcode":"32703",
    "sg:province":"FL",
    "wof:name":"Country Color Nursery",
    "wof:placetype":"venue"
},
  "geometry": {"coordinates":[-81.574018,28.694601],"type":"Point"}
}