{
  "type": "Feature",
  "properties": {
    "iso:country":"US",
    "sg:address":"1 Imeson Park Blvd",
    "sg:city":"Jacksonville",
    "sg:classifiers":[
        {
            "category":"Banks & Credit Unions",
            "subcategory":"Financial Services",
            "type":"Services"
        }
    ],
    "sg:phone":"+1 904 696 3407",
    "sg:postcode":"32218",
    "sg:province":"FL",
    "sg:tags":[
        "company",
        "holding"
    ],
    "wof:name":"Jacksonville Holdings",
    "wof:placetype":"venue"
},
  "geometry": {"coordinates":[-81.647752,30.419736],"type":"Point"}
}