{
  "type": "Feature",
  "properties": {
    "iso:country":"US",
    "sg:address":"855 W New York Ave",
    "sg:city":"Deland",
    "sg:classifiers":[
        {
            "category":"Shopping",
            "type":"Retail Goods"
        }
    ],
    "sg:phone":"+1 386 734 0101",
    "sg:postcode":"32720",
    "sg:province":"FL",
    "sg:tags":[
        "trophy",
        "medal",
        "award"
    ],
    "wof:name":"Trophy Factory & Advertising",
    "wof:placetype":"venue"
},
  "geometry": {"coordinates":[-81.319671,29.028012],"type":"Point"}
}