{
  "type": "Feature",
  "properties": {
    "iso:country":"US",
    "sg:address":"118 Dunlawton Ave",
    "sg:city":"Port Orange",
    "sg:classifiers":[
        {
            "category":"Retail",
            "subcategory":"Auto Repair",
            "type":"Services"
        }
    ],
    "sg:phone":"+1 386 788 7877",
    "sg:postcode":"32127",
    "sg:province":"FL",
    "sg:tags":[
        "repairing",
        "automobile"
    ],
    "wof:name":"DAD Auto Diagnostic Ctr",
    "wof:placetype":"venue"
},
  "geometry": {"coordinates":[-80.987031,29.14318],"type":"Point"}
}