{
  "type": "Feature",
  "properties": {
    "addr:full":"1463 Oakfield Dr Brandon FL 33511",
    "addr:housenumber":"1463",
    "addr:postcode":"33511",
    "addr:street":"Oakfield Dr",
    "iso:country":"US",
    "sg:address":"1463 Oakfield Dr",
    "sg:city":"Brandon",
    "sg:classifiers":[
        {
            "category":"Farming",
            "subcategory":"Livestock Farm",
            "type":"Manufacturing & Wholesale Goods"
        }
    ],
    "sg:phone":"+1 813 653 9616",
    "sg:postcode":"33511",
    "sg:province":"FL",
    "sg:tags":[
        "equine"
    ],
    "wof:name":"Alafia Arabian Farms Inc",
    "wof:placetype":"venue"
},
  "geometry": {"coordinates":[-82.30536600000001,27.934025],"type":"Point"}
}