{
  "type": "Feature",
  "properties": {
    "iso:country":"US",
    "sg:address":"108 Commerce St",
    "sg:city":"Lake Mary",
    "sg:classifiers":[
        {
            "category":"Building & Trades",
            "subcategory":"Electrical",
            "type":"Services"
        }
    ],
    "sg:phone":"+1 407 444 0441",
    "sg:postcode":"32746",
    "sg:province":"FL",
    "sg:tags":[
        "electric",
        "contractor"
    ],
    "wof:name":"United Enterprises Inc",
    "wof:placetype":"venue"
},
  "geometry": {"coordinates":[-81.36306399999999,28.740161],"type":"Point"}
}