{
  "type": "Feature",
  "properties": {
    "addr:full":"665 NE 42nd St Oakland Park FL 33334",
    "addr:housenumber":"665",
    "addr:postcode":"33334",
    "addr:street":"Ne 42Nd St",
    "iso:country":"US",
    "sg:address":"665 NE 42nd St",
    "sg:city":"Oakland Park",
    "sg:classifiers":[
        {
            "category":"Manufacturing",
            "subcategory":"Tools & Machinery",
            "type":"Manufacturing & Wholesale Goods"
        }
    ],
    "sg:phone":"+1 954 568 9826",
    "sg:postcode":"33334",
    "sg:province":"FL",
    "sg:tags":[
        "machine",
        "shop"
    ],
    "wof:name":"Codling Tools & Mfg",
    "wof:placetype":"venue"
},
  "geometry": {"coordinates":[-80.13834,26.178385],"type":"Point"}
}