{
  "type": "Feature",
  "properties": {
    "addr:full":"91760 Overseas Hwy Tavernier FL 33070",
    "addr:housenumber":"91760",
    "addr:postcode":"33070",
    "addr:street":"Overseas Hwy",
    "iso:country":"US",
    "sg:address":"91760 Overseas Hwy",
    "sg:city":"Tavernier",
    "sg:classifiers":[
        {
            "category":"Professional",
            "subcategory":"Accounting & Tax Preparation",
            "type":"Services"
        }
    ],
    "sg:phone":"+1 305 852 4833",
    "sg:postcode":"33070",
    "sg:province":"FL",
    "sg:tags":[
        "accountant"
    ],
    "wof:name":"Catarineau & Catarineau LLC",
    "wof:placetype":"venue"
},
  "geometry": {"coordinates":[-80.51840799999999,25.007928],"type":"Point"}
}