{
  "type": "Feature",
  "properties": {
    "addr:full":"7269 SE Seagate Ln Stuart FL 34997",
    "addr:housenumber":"7269",
    "addr:postcode":"34997",
    "addr:street":"Se Seagate Ln",
    "iso:country":"US",
    "sg:address":"7269 SE Seagate Ln",
    "sg:city":"Stuart",
    "sg:classifiers":[
        {
            "category":"Professional",
            "subcategory":"Business Services",
            "type":"Services"
        }
    ],
    "sg:phone":"+1 772 219 4062",
    "sg:postcode":"34997",
    "sg:province":"FL",
    "wof:name":"Lrd Inc",
    "wof:placetype":"venue"
},
  "geometry": {"coordinates":[-80.186137,27.117061],"type":"Point"}
}