{
  "type": "Feature",
  "properties": {
    "iso:country":"US",
    "sg:address":"362 E 14th St",
    "sg:city":"Hialeah",
    "sg:classifiers":[
        {
            "category":"Retail",
            "subcategory":"Auto Repair",
            "type":"Services"
        }
    ],
    "sg:phone":"+1 305 884 1610",
    "sg:postcode":"33010",
    "sg:province":"FL",
    "sg:tags":[
        "automotive"
    ],
    "wof:name":"Alis Towing",
    "wof:placetype":"venue"
},
  "geometry": {"coordinates":[-80.274925,25.834617],"type":"Point"}
}