{
  "type": "Feature",
  "properties": {
    "addr:full":"995 Cherry Tree Rd Saint Augustine FL 32086",
    "addr:housenumber":"995",
    "addr:postcode":"32086",
    "addr:street":"Cherry Tree Rd",
    "iso:country":"US",
    "sg:address":"995 Cherry Tree Rd",
    "sg:city":"Saint Augustine",
    "sg:classifiers":[
        {
            "category":"Building & Trades",
            "subcategory":"Construction",
            "type":"Services"
        }
    ],
    "sg:phone":"+1 904 797 3015",
    "sg:postcode":"32086",
    "sg:province":"FL",
    "sg:tags":[
        "contractor"
    ],
    "wof:name":"Moultrie Concrete & Masnry Inc",
    "wof:placetype":"venue"
},
  "geometry": {"coordinates":[-81.344238,29.834527],"type":"Point"}
}