{
  "type": "Feature",
  "properties": {
    "addr:full":"1036 Seminole Creek Dr Oviedo FL 32765",
    "addr:housenumber":"1036",
    "addr:postcode":"32765",
    "addr:street":"Seminole Creek Dr",
    "iso:country":"US",
    "sg:address":"1036 Seminole Creek Dr",
    "sg:city":"Oviedo",
    "sg:classifiers":[
        {
            "category":"Building & Trades",
            "subcategory":"Construction",
            "type":"Services"
        }
    ],
    "sg:phone":"+1 407 538 1604",
    "sg:postcode":"32765",
    "sg:province":"FL",
    "sg:tags":[
        "contractor"
    ],
    "wof:name":"Noah S Custom Framing And Remodeling",
    "wof:placetype":"venue"
},
  "geometry": {"coordinates":[-81.179001,28.635521],"type":"Point"}
}