{
  "type": "Feature",
  "properties": {
    "addr:full":"3530 Webber St Sarasota FL 34239",
    "addr:housenumber":"3530",
    "addr:postcode":"34239",
    "addr:street":"Webber St",
    "iso:country":"US",
    "sg:address":"3530 Webber St",
    "sg:city":"Sarasota",
    "sg:classifiers":[
        {
            "category":"Insurance",
            "subcategory":"Insurance Agent",
            "type":"Services"
        }
    ],
    "sg:phone":"+1 941 923 2371",
    "sg:postcode":"34239",
    "sg:province":"FL",
    "sg:tags":[
        "company",
        "title"
    ],
    "wof:name":"Stewart Title Co of Sarasota",
    "wof:placetype":"venue"
},
  "geometry": {"coordinates":[-82.497996,27.308219],"type":"Point"}
}