{
  "type": "Feature",
  "properties": {
    "iso:country":"US",
    "sg:address":"2583 N Atlantic Ave",
    "sg:city":"Daytona Beach",
    "sg:classifiers":[
        {
            "category":"Utilities",
            "subcategory":"Mobile Phone",
            "type":"Services"
        }
    ],
    "sg:phone":"+1 386 672 0079",
    "sg:postcode":"32118",
    "sg:province":"FL",
    "sg:tags":[
        "telephone",
        "cellular"
    ],
    "wof:name":"Wireless Wizard",
    "wof:placetype":"venue"
},
  "geometry": {"coordinates":[-81.025598,29.262121],"type":"Point"}
}