{
  "type": "Feature",
  "properties": {
    "iso:country":"US",
    "sg:address":"14341 Ponce de Leon Blvd",
    "sg:city":"Brooksville",
    "sg:classifiers":[
        {
            "category":"Building & Trades",
            "subcategory":"Construction",
            "type":"Services"
        }
    ],
    "sg:phone":"+1 352 796 0149",
    "sg:postcode":"34601",
    "sg:province":"FL",
    "sg:tags":[
        "excavating",
        "contractor"
    ],
    "wof:name":"Goodwin Brothers Construction",
    "wof:placetype":"venue"
},
  "geometry": {"coordinates":[-82.423068,28.62939],"type":"Point"}
}