{
  "type": "Feature",
  "properties": {
    "addr:full":"1723 Tallo Way Orlando FL 32818",
    "addr:postcode":"1723;32818",
    "addr:street":"Tallo Way",
    "iso:country":"US",
    "sg:address":"1723 Tallo Way",
    "sg:city":"Orlando",
    "sg:classifiers":[
        {
            "category":"Building & Trades",
            "subcategory":"Construction",
            "type":"Services"
        }
    ],
    "sg:phone":"+1 407 297 9777",
    "sg:postcode":"32818",
    "sg:province":"FL",
    "sg:tags":[
        "contractor"
    ],
    "wof:name":"Anderson Concrete and Masonry",
    "wof:placetype":"venue"
},
  "geometry": {"coordinates":[-81.488749,28.561595],"type":"Point"}
}