{
  "type": "Feature",
  "properties": {
    "addr:full":"8003 45th Way N Palm Beach Gardens FL 33418",
    "addr:housenumber":"8003",
    "addr:postcode":"33418",
    "addr:street":"45Th Way N",
    "iso:country":"US",
    "sg:address":"8003 45th Way N",
    "sg:city":"Palm Beach Gardens",
    "sg:classifiers":[
        {
            "category":"Autos & Motor Vehicles",
            "subcategory":"Boat Sales",
            "type":"Retail Goods"
        }
    ],
    "sg:phone":"+1 561 626 0033",
    "sg:postcode":"33418",
    "sg:province":"FL",
    "sg:tags":[
        "yacht",
        "dealer",
        "broker"
    ],
    "wof:name":"Lomas Yacht Sales",
    "wof:placetype":"venue"
},
  "geometry": {"coordinates":[-80.10835899999999,26.79492],"type":"Point"}
}