{
  "type": "Feature",
  "properties": {
    "addr:full":"1576 Cypress Ave Melbourne FL 32935",
    "addr:housenumber":"1576",
    "addr:postcode":"32935",
    "addr:street":"Cypress Ave",
    "iso:country":"US",
    "sg:address":"1576 Cypress Ave",
    "sg:city":"Melbourne",
    "sg:classifiers":[
        {
            "category":"Retail",
            "subcategory":"Auto Repair",
            "type":"Services"
        }
    ],
    "sg:phone":"+1 321 254 8100",
    "sg:postcode":"32935",
    "sg:province":"FL",
    "sg:tags":[
        "repairing",
        "automobile",
        "general",
        "supply"
    ],
    "wof:name":"Donhoff Ben Automotive",
    "wof:placetype":"venue"
},
  "geometry": {"coordinates":[-80.632775,28.131898],"type":"Point"}
}