{
  "type": "Feature",
  "properties": {
    "addr:full":"72 Princess Ruth Ln Palm Coast FL 32164",
    "addr:housenumber":"72",
    "addr:postcode":"32164",
    "addr:street":"Princess Ruth Ln",
    "iso:country":"US",
    "sg:address":"72 Princess Ruth Ln",
    "sg:city":"Palm Coast",
    "sg:classifiers":[
        {
            "category":"Freight",
            "type":"Transportation"
        }
    ],
    "sg:phone":"+1 386 931 6222",
    "sg:postcode":"32164",
    "sg:province":"FL",
    "sg:tags":[
        "operator",
        "local",
        "trucking"
    ],
    "wof:name":"Sr Transport & Hauling Inc",
    "wof:placetype":"venue"
},
  "geometry": {"coordinates":[-81.222493,29.519161],"type":"Point"}
}