{
  "type": "Feature",
  "properties": {
    "addr:full":"74 Willoughby Dr Naples FL 34110",
    "addr:housenumber":"74",
    "addr:postcode":"34110",
    "addr:street":"Willoughby Dr",
    "iso:country":"US",
    "sg:address":"74 Willoughby Dr",
    "sg:city":"Naples",
    "sg:classifiers":[
        {
            "category":"Shopping",
            "type":"Retail Goods"
        },
        {
            "category":"Shopping",
            "subcategory":"Computers & Home Electronics",
            "type":"Retail Goods"
        }
    ],
    "sg:phone":"+1 239 821 8967",
    "sg:postcode":"34110",
    "sg:province":"FL",
    "sg:tags":[
        "system",
        "merchandise"
    ],
    "wof:name":"Music Everywhere Inc",
    "wof:placetype":"venue"
},
  "geometry": {"coordinates":[-81.766693,26.275825],"type":"Point"}
}