{
  "type": "Feature",
  "properties": {
    "iso:country":"US",
    "sg:address":"650 N State Rd 7",
    "sg:city":"Hollywood",
    "sg:classifiers":[
        {
            "category":"Professional",
            "subcategory":"Detective & Security Services",
            "type":"Services"
        }
    ],
    "sg:phone":"+1 954 963 1124",
    "sg:postcode":"33021",
    "sg:province":"FL",
    "sg:tags":[
        "car"
    ],
    "wof:name":"First American Security & Inve",
    "wof:placetype":"venue"
},
  "geometry": {"coordinates":[-80.207908,26.015524],"type":"Point"}
}