{
  "type": "Feature",
  "properties": {
    "iso:country":"US",
    "sg:address":"4369 NW 201st St",
    "sg:city":"Opa Locka",
    "sg:classifiers":[
        {
            "category":"Manufacturing",
            "subcategory":"Electronics",
            "type":"Manufacturing & Wholesale Goods"
        }
    ],
    "sg:phone":"+1 305 624 4416",
    "sg:postcode":"33055",
    "sg:province":"FL",
    "sg:tags":[
        "electronic",
        "component",
        "mfg"
    ],
    "wof:name":"Crespo Enterprises Inc",
    "wof:placetype":"venue"
},
  "geometry": {"coordinates":[-80.27637900000001,25.95582],"type":"Point"}
}