{
  "type": "Feature",
  "properties": {
    "addr:full":"7600 Kingspointe Pkwy Orlando FL 32819",
    "addr:housenumber":"7600",
    "addr:postcode":"32819",
    "addr:street":"Kingspointe Pkwy",
    "iso:country":"US",
    "sg:address":"7600 Kingspointe Pkwy",
    "sg:city":"Orlando",
    "sg:classifiers":[
        {
            "category":"Wholesale",
            "subcategory":"Groceries",
            "type":"Manufacturing & Wholesale Goods"
        }
    ],
    "sg:phone":"+1 407 355 7833",
    "sg:postcode":"32819",
    "sg:province":"FL",
    "sg:tags":[
        "beverage"
    ],
    "wof:name":"Az Beverage",
    "wof:placetype":"venue"
},
  "geometry": {"coordinates":[-81.439357,28.450322],"type":"Point"}
}