{
  "type": "Feature",
  "properties": {
    "addr:full":"97 Sunrise Ave Fort Myers FL 33903",
    "addr:housenumber":"97",
    "addr:postcode":"33903",
    "addr:street":"Sunrise Ave",
    "iso:country":"US",
    "sg:address":"97 Sunrise Ave",
    "sg:city":"Fort Myers",
    "sg:classifiers":[
        {
            "category":"Building & Trades",
            "subcategory":"Construction",
            "type":"Services"
        }
    ],
    "sg:phone":"+1 239 997 0819",
    "sg:postcode":"33903",
    "sg:province":"FL",
    "sg:tags":[
        "handyman"
    ],
    "wof:name":"Doyle Elsass Maintenance Svc",
    "wof:placetype":"venue"
},
  "geometry": {"coordinates":[-81.91016399999999,26.69789],"type":"Point"}
}