{
  "type": "Feature",
  "properties": {
    "addr:full":"10627 Cami Ct Riverview FL 33578",
    "addr:postcode":"10627;33578",
    "addr:street":"Cami Ct",
    "iso:country":"US",
    "sg:address":"10627 Cami Ct",
    "sg:city":"Riverview",
    "sg:classifiers":[
        {
            "category":"Personal",
            "type":"Services"
        }
    ],
    "sg:phone":"+1 813 671 0820",
    "sg:postcode":"33578",
    "sg:province":"FL",
    "wof:name":"Begetan Inc",
    "wof:placetype":"venue"
},
  "geometry": {"coordinates":[-82.333485,27.816619],"type":"Point"}
}