{
  "type": "Feature",
  "properties": {
    "addr:full":"500 US Hwy 441 Wellington FL 33414",
    "addr:housenumber":"500",
    "addr:postcode":"33414",
    "addr:street":"Us Hwy 441",
    "iso:country":"US",
    "sg:address":"500 US Hwy 441",
    "sg:city":"Wellington",
    "sg:classifiers":[
        {
            "category":"Utilities",
            "subcategory":"Mobile Phone",
            "type":"Services"
        }
    ],
    "sg:phone":"+1 561 333 8093",
    "sg:postcode":"33414",
    "sg:province":"FL",
    "sg:tags":[
        "telephone",
        "cellular"
    ],
    "wof:name":"Cellular & Wireless Warehouse",
    "wof:placetype":"venue"
},
  "geometry": {"coordinates":[-80.202393,26.671308],"type":"Point"}
}