{
  "type": "Feature",
  "properties": {
    "iso:country":"US",
    "sg:address":"1333 E Hallandale Beach Blvd",
    "sg:city":"Hallandale Beach",
    "sg:classifiers":[
        {
            "category":"Real Estate",
            "subcategory":"Real Estate Operator",
            "type":"Services"
        }
    ],
    "sg:phone":"+1 954 458 8337",
    "sg:postcode":"33009",
    "sg:province":"FL",
    "sg:tags":[
        "condominium"
    ],
    "wof:name":"April Mist Condo Assn",
    "wof:placetype":"venue"
},
  "geometry": {"coordinates":[-80.135514,25.985948],"type":"Point"}
}