{
  "type": "Feature",
  "properties": {
    "addr:full":"392 SW 187th Ter Pembroke Pines FL 33029",
    "addr:housenumber":"392",
    "addr:postcode":"33029",
    "addr:street":"Sw 187Th Ter",
    "iso:country":"US",
    "sg:address":"392 SW 187th Ter",
    "sg:city":"Pembroke Pines",
    "sg:classifiers":[
        {
            "category":"Professional",
            "type":"Services"
        }
    ],
    "sg:phone":"+1 954 430 4496",
    "sg:postcode":"33029",
    "sg:province":"FL",
    "sg:tags":[
        "establishment"
    ],
    "wof:name":"Dirty Work Inc",
    "wof:placetype":"venue"
},
  "geometry": {"coordinates":[-80.398679,26.003688],"type":"Point"}
}