{
  "type": "Feature",
  "properties": {
    "addr:full":"3121 SE 35 St Gainesville FL 32641",
    "addr:housenumber":"3121;35",
    "addr:postcode":"32641",
    "addr:street":"Se;St",
    "iso:country":"US",
    "sg:address":"3121 SE 35 St",
    "sg:city":"Gainesville",
    "sg:classifiers":[
        {
            "category":"Building & Trades",
            "subcategory":"Construction",
            "type":"Services"
        }
    ],
    "sg:phone":"+1 352 371 0632",
    "sg:postcode":"32641",
    "sg:province":"FL",
    "sg:tags":[
        "home",
        "general",
        "family",
        "contractor"
    ],
    "wof:name":"Rainbow Builders",
    "wof:placetype":"venue"
},
  "geometry": {"coordinates":[-82.28083599999999,29.620524],"type":"Point"}
}