{
  "type": "Feature",
  "properties": {
    "iso:country":"US",
    "sg:address":"1800 N Main St",
    "sg:city":"Gainesville",
    "sg:classifiers":[
        {
            "category":"Professional",
            "subcategory":"Lawyer & Legal Services",
            "type":"Services"
        }
    ],
    "sg:phone":"+1 352 378 1107",
    "sg:postcode":"32609",
    "sg:province":"FL",
    "sg:tags":[
        "attorney",
        "criminal",
        "law"
    ],
    "sg:website":"http://www.reasonabledoubt.org",
    "wof:name":"Blount-Powell Barbara",
    "wof:placetype":"venue"
},
  "geometry": {"coordinates":[-82.32430600000001,29.668791],"type":"Point"}
}