{
  "type": "Feature",
  "properties": {
    "iso:country":"US",
    "sg:address":"801 S University Dr",
    "sg:city":"Fort Lauderdale",
    "sg:classifiers":[
        {
            "category":"Deli",
            "type":"Food & Drink"
        }
    ],
    "sg:menulink":"http://www.allmenus.com/fl/plantation/16000-too-jays/menu/",
    "sg:phone":"+1 954 423 1993",
    "sg:postcode":"33324",
    "sg:province":"FL",
    "sg:tags":[
        "american"
    ],
    "wof:name":"Too Jay's",
    "wof:placetype":"venue"
},
  "geometry": {"coordinates":[-80.25036900000001,26.109806],"type":"Point"}
}