{
  "type": "Feature",
  "properties": {
    "iso:country":"US",
    "sg:address":"2151 Tamiami Trl",
    "sg:city":"Port Charlotte",
    "sg:classifiers":[
        {
            "category":"Retail",
            "subcategory":"Funeral Services",
            "type":"Services"
        }
    ],
    "sg:phone":"+1 941 629 3141",
    "sg:postcode":"33948",
    "sg:province":"FL",
    "sg:tags":[
        "director"
    ],
    "sg:website":"www.robersonfh.com",
    "wof:name":"Roberson Funeral Home",
    "wof:placetype":"venue"
},
  "geometry": {"coordinates":[-82.12517699999999,27.000977],"type":"Point"}
}