{
  "type": "Feature",
  "properties": {
    "iso:country":"US",
    "sg:address":"7777 E Gulf To Lake Hwy",
    "sg:city":"Inverness",
    "sg:classifiers":[
        {
            "category":"Insurance",
            "subcategory":"Insurance Agent",
            "type":"Services"
        }
    ],
    "sg:phone":"+1 352 726 8838",
    "sg:postcode":"34450",
    "sg:province":"FL",
    "wof:name":"Perry Sydnia Insurance",
    "wof:placetype":"venue"
},
  "geometry": {"coordinates":[-82.30491499999999,28.840164],"type":"Point"}
}