{
  "type": "Feature",
  "properties": {
    "iso:country":"US",
    "sg:address":"3804 Gulf Blvd",
    "sg:city":"Saint Petersburg",
    "sg:classifiers":[
        {
            "category":"Organizations",
            "subcategory":"Community Association",
            "type":"Services"
        }
    ],
    "sg:phone":"+1 727 367 2781",
    "sg:postcode":"33706",
    "sg:province":"FL",
    "sg:tags":[
        "condominium",
        "timeshare"
    ],
    "wof:name":"Lessees Association",
    "wof:placetype":"venue"
},
  "geometry": {"coordinates":[-82.739103,27.717857],"type":"Point"}
}