{
  "type": "Feature",
  "properties": {
    "iso:country":"US",
    "sg:address":"5411 Tomlinson Rd",
    "sg:city":"Pensacola",
    "sg:classifiers":[
        {
            "category":"Wholesale",
            "subcategory":"Plants",
            "type":"Manufacturing & Wholesale Goods"
        }
    ],
    "sg:phone":"+1 850 457 1678",
    "sg:postcode":"32526",
    "sg:province":"FL",
    "sg:tags":[
        "supply"
    ],
    "wof:name":"Cynthia Hansons Crative Design",
    "wof:placetype":"venue"
},
  "geometry": {"coordinates":[-87.289978,30.456628],"type":"Point"}
}