{
  "type": "Feature",
  "properties": {
    "iso:country":"US",
    "sg:address":"4921 Headlee Dr",
    "sg:city":"Orlando",
    "sg:classifiers":[
        {
            "category":"Social Services",
            "type":"Services"
        }
    ],
    "sg:phone":"+1 407 273 0753",
    "sg:postcode":"32822",
    "sg:province":"FL",
    "wof:name":"Children Of Love Foundation",
    "wof:placetype":"venue"
},
  "geometry": {"coordinates":[-81.304681,28.483098],"type":"Point"}
}