{
  "type": "Feature",
  "properties": {
    "iso:country":"US",
    "sg:address":"6108 45th St W",
    "sg:city":"Bradenton",
    "sg:classifiers":[
        {
            "category":"Professional",
            "subcategory":"Accounting & Tax Preparation",
            "type":"Services"
        }
    ],
    "sg:phone":"+1 941 758 2868",
    "sg:postcode":"34210",
    "sg:province":"FL",
    "sg:tags":[
        "bookkeeping",
        "general"
    ],
    "wof:name":"Hubbard Business Svc",
    "wof:placetype":"venue"
},
  "geometry": {"coordinates":[-82.60732299999999,27.433399],"type":"Point"}
}