{
  "type": "Feature",
  "properties": {
    "addr:full":"251 Vinings Way Blvd Destin FL 32541",
    "addr:housenumber":"251",
    "addr:postcode":"32541",
    "addr:street":"Vinings Way Blvd",
    "iso:country":"US",
    "sg:address":"251 Vinings Way Blvd",
    "sg:city":"Destin",
    "sg:classifiers":[
        {
            "category":"Real Estate",
            "subcategory":"Real Estate Operator",
            "type":"Services"
        }
    ],
    "sg:phone":"+1 850 650 7446",
    "sg:postcode":"32541",
    "sg:province":"FL",
    "sg:tags":[
        "building",
        "apartment"
    ],
    "wof:name":"Legacy On The Bay Apartments",
    "wof:placetype":"venue"
},
  "geometry": {"coordinates":[-86.408472,30.389592],"type":"Point"}
}