{
  "type": "Feature",
  "properties": {
    "addr:full":"2603 SE 17th St Ocala FL 34471",
    "addr:housenumber":"2603",
    "addr:postcode":"34471",
    "addr:street":"Se 17Th St",
    "iso:country":"US",
    "sg:address":"2603 SE 17th St",
    "sg:city":"Ocala",
    "sg:classifiers":[
        {
            "category":"Professional",
            "subcategory":"Management & Consulting",
            "type":"Services"
        }
    ],
    "sg:phone":"+1 352 622 3214",
    "sg:postcode":"34471",
    "sg:province":"FL",
    "wof:name":"Blue Leaf Condominium Assn",
    "wof:placetype":"venue"
},
  "geometry": {"coordinates":[-82.1005,29.171604],"type":"Point"}
}