{
  "type": "Feature",
  "properties": {
    "addr:full":"4300 Randolph Way Palm Beach Gdns FL 33410",
    "addr:housenumber":"4300",
    "addr:postcode":"33410",
    "addr:street":"Randolph Way Palm Beach Gdns",
    "iso:country":"US",
    "sg:address":"4300 Randolph Way",
    "sg:city":"Palm Beach Gdns",
    "sg:classifiers":[
        {
            "category":"Building & Trades",
            "subcategory":"Equipment Rental",
            "type":"Services"
        }
    ],
    "sg:phone":"+1 561 799 0120",
    "sg:postcode":"33410",
    "sg:province":"FL",
    "sg:tags":[
        "leasing"
    ],
    "wof:name":"Union Square Leasing",
    "wof:placetype":"venue"
},
  "geometry": {"coordinates":[-80.104173,26.834522],"type":"Point"}
}