{
  "type": "Feature",
  "properties": {
    "iso:country":"US",
    "sg:address":"1288 Rainbow Ct",
    "sg:city":"Naples",
    "sg:classifiers":[
        {
            "category":"Building & Trades",
            "subcategory":"Cleaning & Sanitation",
            "type":"Services"
        }
    ],
    "sg:phone":"+1 239 513 0773",
    "sg:postcode":"34110",
    "sg:province":"FL",
    "sg:tags":[
        "house"
    ],
    "wof:name":"Gloria Rhodes House Cleaning",
    "wof:placetype":"venue"
},
  "geometry": {"coordinates":[-81.80743099999999,26.287511],"type":"Point"}
}