{
  "type": "Feature",
  "properties": {
    "addr:full":"404 Green Acres Rd Fort Walton Beach FL 32547",
    "addr:housenumber":"404",
    "addr:postcode":"32547",
    "addr:street":"Green Acres Rd",
    "iso:country":"US",
    "sg:address":"404 Green Acres Rd",
    "sg:city":"Fort Walton Beach",
    "sg:classifiers":[
        {
            "category":"Recreation",
            "type":"Entertainment"
        }
    ],
    "sg:phone":"+1 850 315 0686",
    "sg:postcode":"32547",
    "sg:province":"FL",
    "wof:name":"Fort Walton Sail Pwr Squadron",
    "wof:placetype":"venue"
},
  "geometry": {"coordinates":[-86.64698799999999,30.456126],"type":"Point"}
}