{
  "type": "Feature",
  "properties": {
    "iso:country":"US",
    "sg:address":"341 N 68th Way",
    "sg:city":"Hollywood",
    "sg:classifiers":[
        {
            "category":"Building & Trades",
            "subcategory":"Landscaping Services",
            "type":"Services"
        }
    ],
    "sg:phone":"+1 954 963 2542",
    "sg:postcode":"33024",
    "sg:province":"FL",
    "wof:name":"Jim S Lawn Service",
    "wof:placetype":"venue"
},
  "geometry": {"coordinates":[-80.224001,26.011013],"type":"Point"}
}