{
  "type": "Feature",
  "properties": {
    "addr:full":"925 SE 13th Pl Cape Coral FL 33990",
    "addr:housenumber":"925",
    "addr:postcode":"33990",
    "addr:street":"Se 13Th Pl",
    "iso:country":"US",
    "sg:address":"925 SE 13th Pl",
    "sg:city":"Cape Coral",
    "sg:classifiers":[
        {
            "category":"Freight",
            "type":"Transportation"
        }
    ],
    "sg:phone":"+1 239 574 5676",
    "sg:postcode":"33990",
    "sg:province":"FL",
    "sg:tags":[
        "general"
    ],
    "wof:name":"X-S Storage Co",
    "wof:placetype":"venue"
},
  "geometry": {"coordinates":[-81.94562500000001,26.63455],"type":"Point"}
}