{
  "type": "Feature",
  "properties": {
    "addr:full":"1225 Kass Cir Spring Hill FL 34606",
    "addr:housenumber":"1225",
    "addr:postcode":"34606",
    "addr:street":"Kass Cir",
    "iso:country":"US",
    "sg:address":"1225 Kass Cir",
    "sg:city":"Spring Hill",
    "sg:classifiers":[
        {
            "category":"Restaurant",
            "type":"Food & Drink"
        }
    ],
    "sg:phone":"+1 352 688 4464",
    "sg:postcode":"34606",
    "sg:province":"FL",
    "sg:tags":[
        "eating",
        "product",
        "dairy"
    ],
    "wof:name":"Clyde S Papa Ice Cream",
    "wof:placetype":"venue"
},
  "geometry": {"coordinates":[-82.59245300000001,28.452009],"type":"Point"}
}