{
  "type": "Feature",
  "properties": {
    "iso:country":"US",
    "sg:address":"1515 W Bearss Ave",
    "sg:city":"Tampa",
    "sg:classifiers":[
        {
            "category":"Organizations",
            "subcategory":"Religious Organization",
            "type":"Services"
        }
    ],
    "sg:phone":"+1 813 264 1515",
    "sg:postcode":"33613",
    "sg:province":"FL",
    "sg:tags":[
        "baptist",
        "church"
    ],
    "wof:name":"Exciting Idlwild Baptst Church",
    "wof:placetype":"venue"
},
  "geometry": {"coordinates":[-82.477267,28.089708],"type":"Point"}
}