{
  "type": "Feature",
  "properties": {
    "iso:country":"US",
    "sg:address":"3908 SW 180th St",
    "sg:city":"Newberry",
    "sg:classifiers":[
        {
            "category":"Restaurant",
            "type":"Food & Drink"
        }
    ],
    "sg:phone":"+1 352 495 9240",
    "sg:postcode":"32669",
    "sg:province":"FL",
    "sg:tags":[
        "style",
        "family"
    ],
    "wof:name":"Humlet Holdings Cedar Key",
    "wof:placetype":"venue"
},
  "geometry": {"coordinates":[-82.531998,29.615977],"type":"Point"}
}