{
  "type": "Feature",
  "properties": {
    "addr:full":"1313 Turner Pl Naples FL 34110",
    "addr:housenumber":"1313",
    "addr:postcode":"34110",
    "addr:street":"Turner Pl",
    "iso:country":"US",
    "sg:address":"1313 Turner Pl",
    "sg:city":"Naples",
    "sg:classifiers":[
        {
            "category":"Real Estate",
            "subcategory":"Real Estate Agent",
            "type":"Services"
        }
    ],
    "sg:phone":"+1 239 592 0192",
    "sg:postcode":"34110",
    "sg:province":"FL",
    "sg:tags":[
        "investment"
    ],
    "wof:name":"Bloomfield Associated Grp Inc",
    "wof:placetype":"venue"
},
  "geometry": {"coordinates":[-81.791507,26.286835],"type":"Point"}
}