{
  "type": "Feature",
  "properties": {
    "addr:full":"937 N Central Ave Umatilla FL 32784",
    "addr:housenumber":"937",
    "addr:postcode":"32784",
    "addr:street":"N Central Ave",
    "iso:country":"US",
    "sg:address":"937 N Central Ave",
    "sg:city":"Umatilla",
    "sg:classifiers":[
        {
            "category":"Shopping",
            "subcategory":"Florist",
            "type":"Retail Goods"
        }
    ],
    "sg:phone":"+1 352 669 5994",
    "sg:postcode":"32784",
    "sg:province":"FL",
    "wof:name":"Umatilla Florist",
    "wof:placetype":"venue"
},
  "geometry": {"coordinates":[-81.658241,28.948992],"type":"Point"}
}