{
  "type": "Feature",
  "properties": {
    "addr:full":"2280 Aaron St Port Charlotte FL 33952",
    "addr:housenumber":"2280",
    "addr:postcode":"33952",
    "addr:street":"Aaron St",
    "iso:country":"US",
    "sg:address":"2280 Aaron St",
    "sg:city":"Port Charlotte",
    "sg:classifiers":[
        {
            "category":"Education",
            "subcategory":"College",
            "type":"Public Place"
        }
    ],
    "sg:phone":"+1 941 883 2423",
    "sg:postcode":"33952",
    "sg:province":"FL",
    "sg:tags":[
        "academic",
        "school"
    ],
    "wof:name":"Florida Gulf Coast University",
    "wof:placetype":"venue"
},
  "geometry": {"coordinates":[-82.100258,26.993622],"type":"Point"}
}