{
  "type": "Feature",
  "properties": {
    "iso:country":"US",
    "sg:address":"3202 Tamiami Trl",
    "sg:city":"Sarasota",
    "sg:classifiers":[
        {
            "category":"Professional",
            "subcategory":"Accounting & Tax Preparation",
            "type":"Services"
        }
    ],
    "sg:phone":"+1 941 355 9781",
    "sg:postcode":"34234",
    "sg:province":"FL",
    "sg:tags":[
        "accountant"
    ],
    "wof:name":"T J Ropp Accounting Svc",
    "wof:placetype":"venue"
},
  "geometry": {"coordinates":[-82.55074500000001,27.364601],"type":"Point"}
}