{
  "type": "Feature",
  "properties": {
    "iso:country":"US",
    "sg:address":"22492 Middletown Dr",
    "sg:city":"Boca Raton",
    "sg:classifiers":[
        {
            "category":"Building & Trades",
            "subcategory":"Electrical",
            "type":"Services"
        }
    ],
    "sg:phone":"+1 561 883 6776",
    "sg:postcode":"33428",
    "sg:province":"FL",
    "sg:tags":[
        "electrical",
        "contractor"
    ],
    "wof:name":"J P Electric",
    "wof:placetype":"venue"
},
  "geometry": {"coordinates":[-80.250303,26.345208],"type":"Point"}
}