{
  "type": "Feature",
  "properties": {
    "iso:country":"US",
    "sg:address":"1900 Park Meadows Dr",
    "sg:city":"Fort Myers",
    "sg:classifiers":[
        {
            "category":"Bars & Pubs",
            "subcategory":"Nightclub",
            "type":"Food & Drink"
        }
    ],
    "sg:phone":"+1 239 278 1355",
    "sg:postcode":"33907",
    "sg:province":"FL",
    "sg:tags":[
        "nightlife"
    ],
    "wof:name":"Elks Lodge No 1288",
    "wof:placetype":"venue"
},
  "geometry": {"coordinates":[-81.87640399999999,26.566999],"type":"Point"}
}