{
  "type": "Feature",
  "properties": {
    "iso:country":"US",
    "sg:address":"5200 Fay Blvd",
    "sg:city":"Cocoa",
    "sg:classifiers":[
        {
            "category":"Building & Trades",
            "subcategory":"Construction",
            "type":"Services"
        }
    ],
    "sg:phone":"+1 321 431 8482",
    "sg:postcode":"32927",
    "sg:province":"FL",
    "sg:tags":[
        "wallcoverings-installation",
        "wallpaper",
        "painting",
        "contractor"
    ],
    "wof:name":"Knowles Painting",
    "wof:placetype":"venue"
},
  "geometry": {"coordinates":[-80.808414,28.468421],"type":"Point"}
}