{
  "type": "Feature",
  "properties": {
    "addr:full":"2775 Glen Mawr Rd Jacksonville FL 32207",
    "addr:housenumber":"2775",
    "addr:postcode":"32207",
    "addr:street":"Glen Mawr Rd",
    "iso:country":"US",
    "sg:address":"2775 Glen Mawr Rd",
    "sg:city":"Jacksonville",
    "sg:classifiers":[
        {
            "category":"Restaurant",
            "type":"Food & Drink"
        }
    ],
    "sg:phone":"+1 407 447 9866",
    "sg:postcode":"32207",
    "sg:province":"FL",
    "wof:name":"Fireshouse Subs",
    "wof:placetype":"venue"
},
  "geometry": {"coordinates":[-81.633109,30.29682],"type":"Point"}
}