{
  "type": "Feature",
  "properties": {
    "iso:country":"US",
    "sg:address":"455 E Cummings St",
    "sg:city":"Lake Alfred",
    "sg:classifiers":[
        {
            "category":"Education",
            "subcategory":"School",
            "type":"Public Place"
        }
    ],
    "sg:phone":"+1 863 295 5988",
    "sg:postcode":"33850",
    "sg:province":"FL",
    "wof:name":"Lake Alfred Career Academy",
    "wof:placetype":"venue"
},
  "geometry": {"coordinates":[-81.723175,28.088034],"type":"Point"}
}