{
  "type": "Feature",
  "properties": {
    "addr:full":"10901 SW 24th St Miami FL 33165",
    "addr:housenumber":"10901",
    "addr:postcode":"33165",
    "addr:street":"Sw 24Th St",
    "iso:country":"US",
    "sg:address":"10901 SW 24th St",
    "sg:city":"Miami",
    "sg:classifiers":[
        {
            "category":"Government",
            "subcategory":"Office",
            "type":"Public Place"
        }
    ],
    "sg:phone":"+1 305 223 7060",
    "sg:postcode":"33165",
    "sg:province":"FL",
    "sg:tags":[
        "parish",
        "government-county"
    ],
    "wof:name":"Miami-Dade County Fair & Exposition",
    "wof:placetype":"venue"
},
  "geometry": {"coordinates":[-80.371819,25.7467],"type":"Point"}
}