{
  "type": "Feature",
  "properties": {
    "addr:full":"13020 SW 92nd Ave Miami FL 33176",
    "addr:housenumber":"13020",
    "addr:postcode":"33176",
    "addr:street":"Sw 92Nd Ave",
    "iso:country":"US",
    "sg:address":"13020 SW 92nd Ave",
    "sg:city":"Miami",
    "sg:classifiers":[
        {
            "category":"Shopping",
            "type":"Retail Goods"
        }
    ],
    "sg:phone":"+1 305 238 2451",
    "sg:postcode":"33176",
    "sg:province":"FL",
    "sg:tags":[
        "merchandise"
    ],
    "wof:name":"Sunshine Coins Inc",
    "wof:placetype":"venue"
},
  "geometry": {"coordinates":[-80.343672,25.648133],"type":"Point"}
}