{
  "type": "Feature",
  "properties": {
    "addr:full":"308 11th Ave N Saint Petersburg FL 33701",
    "addr:housenumber":"308",
    "addr:postcode":"33701",
    "addr:street":"11Th Ave N",
    "iso:country":"US",
    "sg:address":"308 11th Ave N",
    "sg:city":"Saint Petersburg",
    "sg:classifiers":[
        {
            "category":"Manufacturing",
            "subcategory":"Printing",
            "type":"Manufacturing & Wholesale Goods"
        }
    ],
    "sg:phone":"+1 727 502 5833",
    "sg:postcode":"33701",
    "sg:province":"FL",
    "sg:tags":[
        "lithographic",
        "commercial"
    ],
    "wof:name":"Mrt Enterprises Inc",
    "wof:placetype":"venue"
},
  "geometry": {"coordinates":[-82.638396,27.782966],"type":"Point"}
}