{
  "type": "Feature",
  "properties": {
    "addr:full":"9133 Queen Elizabeth Ct Orlando FL 32818",
    "addr:housenumber":"9133",
    "addr:postcode":"32818",
    "addr:street":"Queen Elizabeth Ct",
    "iso:country":"US",
    "sg:address":"9133 Queen Elizabeth Ct",
    "sg:city":"Orlando",
    "sg:classifiers":[
        {
            "category":"Building & Trades",
            "subcategory":"Construction",
            "type":"Services"
        }
    ],
    "sg:phone":"+1 407 299 1598",
    "sg:postcode":"32818",
    "sg:province":"FL",
    "sg:tags":[
        "hanging",
        "contractor"
    ],
    "wof:name":"Anthony English Wallpapering",
    "wof:placetype":"venue"
},
  "geometry": {"coordinates":[-81.512317,28.557522],"type":"Point"}
}