{
  "type": "Feature",
  "properties": {
    "addr:full":"2312 Transmitter Rd Panama City FL 32404",
    "addr:postcode":"2312;32404",
    "addr:street":"Transmitter Rd",
    "iso:country":"US",
    "sg:address":"2312 Transmitter Rd",
    "sg:city":"Panama City",
    "sg:classifiers":[
        {
            "category":"Shopping",
            "subcategory":"Used Merchandise",
            "type":"Retail Goods"
        }
    ],
    "sg:phone":"+1 850 872 0700",
    "sg:postcode":"32404",
    "sg:province":"FL",
    "wof:name":"Alamo Pawnshop",
    "wof:placetype":"venue"
},
  "geometry": {"coordinates":[-85.60773,30.186656],"type":"Point"}
}