{
  "type": "Feature",
  "properties": {
    "iso:country":"US",
    "sg:address":"10250 SW 56th St",
    "sg:city":"Miami",
    "sg:classifiers":[
        {
            "category":"Home & Garden",
            "subcategory":"Household Appliances",
            "type":"Retail Goods"
        }
    ],
    "sg:phone":"+1 305 273 6161",
    "sg:postcode":"33165",
    "sg:province":"FL",
    "sg:tags":[
        "cleaners",
        "vacuum"
    ],
    "wof:name":"J T Towers",
    "wof:placetype":"venue"
},
  "geometry": {"coordinates":[-80.359977,25.715655],"type":"Point"}
}