{
  "type": "Feature",
  "properties": {
    "addr:full":"11581 Riggs Rd Naples FL 34114",
    "addr:housenumber":"11581",
    "addr:postcode":"34114",
    "addr:street":"Riggs Rd",
    "iso:country":"US",
    "sg:address":"11581 Riggs Rd",
    "sg:city":"Naples",
    "sg:classifiers":[
        {
            "category":"Shopping",
            "subcategory":"Florist",
            "type":"Retail Goods"
        },
        {
            "category":"Home & Garden",
            "subcategory":"Garden Supply",
            "type":"Retail Goods"
        }
    ],
    "sg:phone":"+1 239 775 4489",
    "sg:postcode":"34114",
    "sg:province":"FL",
    "wof:name":"Roseglen Gardens Inc",
    "wof:placetype":"venue"
},
  "geometry": {"coordinates":[-81.62836900000001,26.022481],"type":"Point"}
}