{
  "type": "Feature",
  "properties": {
    "addr:full":"82201 Overseas Hwy Islamorada FL 33036",
    "addr:housenumber":"82201",
    "addr:postcode":"33036",
    "addr:street":"Overseas Hwy",
    "iso:country":"US",
    "sg:address":"82201 Overseas Hwy",
    "sg:city":"Islamorada",
    "sg:classifiers":[
        {
            "category":"Restaurant",
            "type":"Food & Drink"
        }
    ],
    "sg:menulink":"http://www.allmenus.com/fl/upper-keys/160451-burger-king/menu/",
    "sg:phone":"+1 305 664 9292",
    "sg:postcode":"33036",
    "sg:province":"FL",
    "sg:tags":[
        "burger",
        "american"
    ],
    "wof:name":"Burger King",
    "wof:placetype":"venue"
},
  "geometry": {"coordinates":[-80.629659,24.92298],"type":"Point"}
}