{
  "type": "Feature",
  "properties": {
    "iso:country":"US",
    "sg:address":"8305 SE 58th Ave",
    "sg:city":"Ocala",
    "sg:classifiers":[
        {
            "category":"Wholesale",
            "subcategory":"Stationery",
            "type":"Manufacturing & Wholesale Goods"
        }
    ],
    "sg:phone":"+1 352 347 9225",
    "sg:postcode":"34480",
    "sg:province":"FL",
    "sg:tags":[
        "product",
        "paper"
    ],
    "wof:name":"Joshen Paper & Packaging",
    "wof:placetype":"venue"
},
  "geometry": {"coordinates":[-82.05349699999999,29.103037],"type":"Point"}
}