{
  "type": "Feature",
  "properties": {
    "iso:country":"US",
    "sg:address":"1840 W 49th St Ste 105",
    "sg:city":"Hialeah",
    "sg:classifiers":[
        {
            "category":"Professional",
            "subcategory":"Employment Agencies",
            "type":"Services"
        }
    ],
    "sg:phone":"+1 305 822 0688",
    "sg:postcode":"33012",
    "sg:province":"FL",
    "sg:website":"www.pystaffing.com",
    "wof:name":"Personally Yours Staffing",
    "wof:placetype":"venue"
},
  "geometry": {"coordinates":[-80.319754,25.865785],"type":"Point"}
}