{
  "type": "Feature",
  "properties": {
    "iso:country":"US",
    "sg:address":"1202 E Busch Blvd",
    "sg:city":"Tampa",
    "sg:classifiers":[
        {
            "category":"Food & Beverages",
            "subcategory":"Groceries & Convenience Stores",
            "type":"Retail Goods"
        }
    ],
    "sg:phone":"+1 813 930 0780",
    "sg:postcode":"33612",
    "sg:province":"FL",
    "wof:name":"Discount Food Mart",
    "wof:placetype":"venue"
},
  "geometry": {"coordinates":[-82.44629999999999,28.032795],"type":"Point"}
}