{
  "type": "Feature",
  "properties": {
    "iso:country":"US",
    "sg:address":"1726 Kingsley Ave",
    "sg:city":"Orange Park",
    "sg:classifiers":[
        {
            "category":"Professional",
            "subcategory":"Lawyer & Legal Services",
            "type":"Services"
        }
    ],
    "sg:phone":"+1 904 541 1643",
    "sg:postcode":"32073",
    "sg:province":"FL",
    "sg:tags":[
        "attorney"
    ],
    "wof:name":"Raymond B Labella Law Ofc Pl",
    "wof:placetype":"venue"
},
  "geometry": {"coordinates":[-81.737049,30.164872],"type":"Point"}
}