{
  "type": "Feature",
  "properties": {
    "iso:country":"US",
    "sg:address":"7082 State Hwy 37",
    "sg:city":"Mulberry",
    "sg:classifiers":[
        {
            "category":"Building & Trades",
            "subcategory":"Construction",
            "type":"Services"
        }
    ],
    "sg:phone":"+1 813 477 1860",
    "sg:postcode":"33860",
    "sg:province":"FL",
    "sg:tags":[
        "concrete",
        "contractor"
    ],
    "wof:name":"Santa Fe Concrete",
    "wof:placetype":"venue"
},
  "geometry": {"coordinates":[-81.97419499999999,27.931666],"type":"Point"}
}