{
  "type": "Feature",
  "properties": {
    "iso:country":"US",
    "sg:address":"3309 SW 13th Ave",
    "sg:city":"Fort Lauderdale",
    "sg:classifiers":[
        {
            "category":"Professional",
            "type":"Services"
        }
    ],
    "sg:phone":"+1 954 358 2488",
    "sg:postcode":"33315",
    "sg:province":"FL",
    "wof:name":"Professional Line Service Inc",
    "wof:placetype":"venue"
},
  "geometry": {"coordinates":[-80.158643,26.081509],"type":"Point"}
}