{
  "type": "Feature",
  "properties": {
    "addr:full":"609 E Atlantic Blvd Pompano Beach FL 33060",
    "addr:housenumber":"609",
    "addr:postcode":"33060",
    "addr:street":"E Atlantic Blvd",
    "iso:country":"US",
    "sg:address":"609 E Atlantic Blvd",
    "sg:city":"Pompano Beach",
    "sg:classifiers":[
        {
            "category":"Wholesale",
            "subcategory":"Machinery & Supplies",
            "type":"Manufacturing & Wholesale Goods"
        }
    ],
    "sg:phone":"+1 954 788 7471",
    "sg:postcode":"33060",
    "sg:province":"FL",
    "sg:tags":[
        "equipment",
        "motel",
        "hotel"
    ],
    "wof:name":"Atlantic Hospitality Supply",
    "wof:placetype":"venue"
},
  "geometry": {"coordinates":[-80.11668,26.231758],"type":"Point"}
}