{
  "type": "Feature",
  "properties": {
    "addr:full":"1213 E Atlantic Blvd Pompano Beach FL 33060",
    "addr:housenumber":"1213",
    "addr:postcode":"33060",
    "addr:street":"E Atlantic Blvd",
    "iso:country":"US",
    "sg:address":"1213 E Atlantic Blvd",
    "sg:city":"Pompano Beach",
    "sg:classifiers":[
        {
            "category":"Education",
            "subcategory":"Library",
            "type":"Public Place"
        }
    ],
    "sg:phone":"+1 954 786 2181",
    "sg:postcode":"33060",
    "sg:province":"FL",
    "wof:name":"County Library",
    "wof:placetype":"venue"
},
  "geometry": {"coordinates":[-80.110837,26.231821],"type":"Point"}
}