{
  "type": "Feature",
  "properties": {
    "iso:country":"US",
    "sg:address":"534 N Lecanto Hwy",
    "sg:city":"Lecanto",
    "sg:classifiers":[
        {
            "category":"Health Services",
            "subcategory":"Doctor",
            "type":"Services"
        }
    ],
    "sg:phone":"+1 352 746 0654",
    "sg:postcode":"34461",
    "sg:province":"FL",
    "sg:tags":[
        "osteopathic"
    ],
    "wof:name":"Richard C Couch Do",
    "wof:placetype":"venue"
},
  "geometry": {"coordinates":[-82.490234,28.879963],"type":"Point"}
}