{
  "type": "Feature",
  "properties": {
    "iso:country":"US",
    "sg:address":"8101 Nadmar Ave",
    "sg:city":"Boca Raton",
    "sg:classifiers":[
        {
            "category":"Autos & Motor Vehicles",
            "subcategory":"Fuel & Gas Station",
            "type":"Retail Goods"
        }
    ],
    "sg:phone":"+1 561 482 4375",
    "sg:postcode":"33434",
    "sg:province":"FL",
    "sg:tags":[
        "repair",
        "station",
        "gasoline",
        "general"
    ],
    "wof:name":"Shrub Oak Auto Service Center",
    "wof:placetype":"venue"
},
  "geometry": {"coordinates":[-80.172982,26.380154],"type":"Point"}
}