{
  "type": "Feature",
  "properties": {
    "addr:full":"5155 32nd Ave N Saint Petersburg FL 33710",
    "addr:housenumber":"5155",
    "addr:postcode":"33710",
    "addr:street":"32Nd Ave N",
    "iso:country":"US",
    "sg:address":"5155 32nd Ave N",
    "sg:city":"Saint Petersburg",
    "sg:classifiers":[
        {
            "category":"Professional",
            "subcategory":"Computer Services",
            "type":"Services"
        }
    ],
    "sg:phone":"+1 727 526 2308",
    "sg:postcode":"33710",
    "sg:province":"FL",
    "sg:tags":[
        "related"
    ],
    "wof:name":"Imagineers Inc",
    "wof:placetype":"venue"
},
  "geometry": {"coordinates":[-82.703406,27.800834],"type":"Point"}
}