{
  "type": "Feature",
  "properties": {
    "addr:full":"504 Amethyst Way Lake Mary FL 32746",
    "addr:housenumber":"504",
    "addr:postcode":"32746",
    "addr:street":"Amethyst Way",
    "iso:country":"US",
    "sg:address":"504 Amethyst Way",
    "sg:city":"Lake Mary",
    "sg:classifiers":[
        {
            "category":"Professional",
            "subcategory":"Management & Consulting",
            "type":"Services"
        }
    ],
    "sg:phone":"+1 407 323 8626",
    "sg:postcode":"32746",
    "sg:province":"FL",
    "sg:tags":[
        "computer",
        "software"
    ],
    "wof:name":"Sierra Micro",
    "wof:placetype":"venue"
},
  "geometry": {"coordinates":[-81.33754999999999,28.742905],"type":"Point"}
}