{
  "type": "Feature",
  "properties": {
    "addr:full":"8554 NW 64th St Miami FL 33166",
    "addr:housenumber":"8554",
    "addr:postcode":"33166",
    "addr:street":"Nw 64Th St",
    "iso:country":"US",
    "sg:address":"8554 NW 64th St",
    "sg:city":"Miami",
    "sg:classifiers":[
        {
            "category":"Home & Garden",
            "subcategory":"Building Materials",
            "type":"Retail Goods"
        }
    ],
    "sg:phone":"+1 305 591 0044",
    "sg:postcode":"33166",
    "sg:province":"FL",
    "sg:tags":[
        "door"
    ],
    "wof:name":"Door Galore",
    "wof:placetype":"venue"
},
  "geometry": {"coordinates":[-80.336074,25.831585],"type":"Point"}
}