{
  "type": "Feature",
  "properties": {
    "iso:country":"US",
    "sg:address":"261 Bayshore Dr",
    "sg:city":"Cape Coral",
    "sg:classifiers":[
        {
            "category":"Building & Trades",
            "subcategory":"Cleaning & Sanitation",
            "type":"Services"
        }
    ],
    "sg:phone":"+1 239 549 4921",
    "sg:postcode":"33904",
    "sg:province":"FL",
    "sg:tags":[
        "maintenance"
    ],
    "wof:name":"Arthur Tate Pool Cleaning",
    "wof:placetype":"venue"
},
  "geometry": {"coordinates":[-81.970795,26.546989],"type":"Point"}
}