{
  "type": "Feature",
  "properties": {
    "iso:country":"US",
    "sg:address":"13600 Southampton Dr",
    "sg:city":"Bonita Springs",
    "sg:classifiers":[
        {
            "category":"Autos & Motor Vehicles",
            "subcategory":"Automobile Sales",
            "type":"Retail Goods"
        }
    ],
    "sg:phone":"+1 239 495 9305",
    "sg:postcode":"34135",
    "sg:province":"FL",
    "wof:name":"Guy Foster Enterprises",
    "wof:placetype":"venue"
},
  "geometry": {"coordinates":[-81.724934,26.325471],"type":"Point"}
}