{
  "type": "Feature",
  "properties": {
    "addr:full":"7715 W Hwy 40 Ocala FL 34482",
    "addr:housenumber":"7715",
    "addr:postcode":"34482",
    "addr:street":"W Hwy 40",
    "iso:country":"US",
    "sg:address":"7715 W Hwy 40",
    "sg:city":"Ocala",
    "sg:classifiers":[
        {
            "category":"Wholesale",
            "subcategory":"Non-durable Goods",
            "type":"Manufacturing & Wholesale Goods"
        }
    ],
    "sg:phone":"+1 352 854 0528",
    "sg:postcode":"34482",
    "sg:province":"FL",
    "sg:tags":[
        "blacksmith",
        "shop",
        "supply"
    ],
    "wof:name":"T T Distributors",
    "wof:placetype":"venue"
},
  "geometry": {"coordinates":[-82.248251,29.186752],"type":"Point"}
}