{
  "type": "Feature",
  "properties": {
    "addr:full":"603 N Dort St Plant City FL 33563",
    "addr:housenumber":"603",
    "addr:postcode":"33563",
    "addr:street":"N Dort St",
    "iso:country":"US",
    "sg:address":"603 N Dort St",
    "sg:city":"Plant City",
    "sg:classifiers":[
        {
            "category":"Real Estate",
            "subcategory":"Real Estate Operator",
            "type":"Services"
        }
    ],
    "sg:phone":"+1 813 752 7520",
    "sg:postcode":"33563",
    "sg:province":"FL",
    "sg:tags":[
        "building",
        "apartment"
    ],
    "wof:name":"Georgetown Apartments Rentals",
    "wof:placetype":"venue"
},
  "geometry": {"coordinates":[-82.135965,28.019278],"type":"Point"}
}