{
  "type": "Feature",
  "properties": {
    "iso:country":"US",
    "sg:address":"1001 NW 6th Ave",
    "sg:city":"Pompano Beach",
    "sg:classifiers":[
        {
            "category":"Travel",
            "subcategory":"Bed & Breakfast",
            "type":"Entertainment"
        }
    ],
    "sg:phone":"+1 954 943 3784",
    "sg:postcode":"33060",
    "sg:province":"FL",
    "sg:tags":[
        "house"
    ],
    "wof:name":"Volunteers of America Florida",
    "wof:placetype":"venue"
},
  "geometry": {"coordinates":[-80.130662,26.244165],"type":"Point"}
}