{
  "type": "Feature",
  "properties": {
    "addr:full":"2077 1st St Ste 201 Fort Myers FL 33901",
    "addr:housenumber":"2077",
    "addr:postcode":"myers;33901",
    "addr:street":"1St St Ste 201",
    "iso:country":"US",
    "sg:address":"2077 1st St Ste 201",
    "sg:city":"Fort Myers",
    "sg:classifiers":[
        {
            "category":"Professional",
            "subcategory":"Lawyer & Legal Services",
            "type":"Services"
        }
    ],
    "sg:phone":"+1 239 337 1999",
    "sg:postcode":"33901",
    "sg:province":"FL",
    "wof:name":"Donald Robert L Attorney",
    "wof:placetype":"venue"
},
  "geometry": {"coordinates":[-81.872415,26.643522],"type":"Point"}
}