{
  "type": "Feature",
  "properties": {
    "addr:full":"500 Fairway Dr Pompano Beach FL 33069",
    "addr:housenumber":"500",
    "addr:postcode":"33069",
    "addr:street":"Fairway Dr",
    "iso:country":"US",
    "sg:address":"500 Fairway Dr",
    "sg:city":"Pompano Beach",
    "sg:classifiers":[
        {
            "category":"Professional",
            "subcategory":"Advertising",
            "type":"Services"
        }
    ],
    "sg:phone":"+1 954 725 9394",
    "sg:postcode":"33069",
    "sg:province":"FL",
    "sg:tags":[
        "distribution"
    ],
    "wof:name":"Red Reef Laboratories",
    "wof:placetype":"venue"
},
  "geometry": {"coordinates":[-80.171345,26.236729],"type":"Point"}
}