{
  "type": "Feature",
  "properties": {
    "addr:full":"12534 Bronco Dr Tampa FL 33626",
    "addr:housenumber":"12534",
    "addr:postcode":"33626",
    "addr:street":"Bronco Dr",
    "iso:country":"US",
    "sg:address":"12534 Bronco Dr",
    "sg:city":"Tampa",
    "sg:classifiers":[
        {
            "category":"Building & Trades",
            "subcategory":"Equipment Rental",
            "type":"Services"
        }
    ],
    "sg:phone":"+1 813 855 1224",
    "sg:postcode":"33626",
    "sg:province":"FL",
    "wof:name":"Jims Bobcat Rental",
    "wof:placetype":"venue"
},
  "geometry": {"coordinates":[-82.63585500000001,28.052136],"type":"Point"}
}