{
  "type": "Feature",
  "properties": {
    "iso:country":"US",
    "sg:address":"7700 N Okeechobee Rd",
    "sg:city":"Hialeah",
    "sg:classifiers":[
        {
            "category":"Wholesale",
            "subcategory":"Sporting Goods",
            "type":"Manufacturing & Wholesale Goods"
        }
    ],
    "sg:phone":"+1 305 558 8691",
    "sg:postcode":"33016",
    "sg:province":"FL",
    "wof:name":"All Stars Uniforms Co",
    "wof:placetype":"venue"
},
  "geometry": {"coordinates":[-80.32937,25.859236],"type":"Point"}
}