{
  "type": "Feature",
  "properties": {
    "addr:full":"7782 N Tamiami Trl Sarasota FL 34243",
    "addr:housenumber":"7782",
    "addr:postcode":"34243",
    "addr:street":"N Tamiami Trl",
    "iso:country":"US",
    "sg:address":"7782 N Tamiami Trl",
    "sg:city":"Sarasota",
    "sg:classifiers":[
        {
            "category":"Insurance",
            "subcategory":"Insurance Agent",
            "type":"Services"
        }
    ],
    "sg:phone":"+1 941 351 4627",
    "sg:postcode":"34243",
    "sg:province":"FL",
    "wof:name":"Nationwide Insurance",
    "wof:placetype":"venue"
},
  "geometry": {"coordinates":[-82.56567699999999,27.401465],"type":"Point"}
}