{
  "type": "Feature",
  "properties": {
    "iso:country":"US",
    "sg:address":"9530 Starkey Rd",
    "sg:city":"Seminole",
    "sg:classifiers":[
        {
            "category":"Place Of Worship",
            "subcategory":"Church",
            "type":"Public Place"
        },
        {
            "category":"Place Of Worship",
            "type":"Public Place"
        }
    ],
    "sg:phone":"+1 727 391 0218",
    "sg:postcode":"33777",
    "sg:province":"FL",
    "sg:tags":[
        "churches-united",
        "methodist",
        "churches-methodist"
    ],
    "wof:name":"Aldersgate United Methodist Church",
    "wof:placetype":"venue"
},
  "geometry": {"coordinates":[-82.762404,27.858874],"type":"Point"}
}