{
  "type": "Feature",
  "properties": {
    "addr:full":"2801 Snyder Rd Sebring FL 33870",
    "addr:housenumber":"2801",
    "addr:postcode":"33870",
    "addr:street":"Snyder Rd",
    "iso:country":"US",
    "sg:address":"2801 Snyder Rd",
    "sg:city":"Sebring",
    "sg:classifiers":[
        {
            "category":"Farming",
            "subcategory":"Orchard",
            "type":"Manufacturing & Wholesale Goods"
        }
    ],
    "sg:phone":"+1 863 382 0447",
    "sg:postcode":"33870",
    "sg:province":"FL",
    "sg:tags":[
        "citrus",
        "grove",
        "fruit"
    ],
    "wof:name":"Jim Haynes Family Citrus",
    "wof:placetype":"venue"
},
  "geometry": {"coordinates":[-81.386527,27.464303],"type":"Point"}
}