{
  "type": "Feature",
  "properties": {
    "addr:full":"2311 Southern Lites Ave Lutz FL 33549",
    "addr:housenumber":"2311",
    "addr:postcode":"33549",
    "addr:street":"Southern Lites Ave",
    "iso:country":"US",
    "sg:address":"2311 Southern Lites Ave",
    "sg:city":"Lutz",
    "sg:classifiers":[
        {
            "category":"Building & Trades",
            "subcategory":"Landscaping Services",
            "type":"Services"
        }
    ],
    "sg:phone":"+1 813 949 9088",
    "sg:postcode":"33549",
    "sg:province":"FL",
    "wof:name":"R&J Lawn Service",
    "wof:placetype":"venue"
},
  "geometry": {"coordinates":[-82.435244,28.137577],"type":"Point"}
}