{
  "type": "Feature",
  "properties": {
    "iso:country":"US",
    "sg:address":"617 E International Speedway Blvd",
    "sg:city":"Daytona Beach",
    "sg:classifiers":[
        {
            "category":"Food & Beverages",
            "subcategory":"Groceries & Convenience Stores",
            "type":"Retail Goods"
        }
    ],
    "sg:phone":"+1 386 248 1998",
    "sg:postcode":"32118",
    "sg:province":"FL",
    "wof:name":"E-Z Food Shop",
    "wof:placetype":"venue"
},
  "geometry": {"coordinates":[-81.007858,29.221453],"type":"Point"}
}