{
  "type": "Feature",
  "properties": {
    "iso:country":"US",
    "sg:address":"1501 N State Rd 7",
    "sg:city":"Hollywood",
    "sg:classifiers":[
        {
            "category":"Autos & Motor Vehicles",
            "subcategory":"Automobile Sales",
            "type":"Retail Goods"
        }
    ],
    "sg:phone":"+1 954 961 7557",
    "sg:postcode":"33021",
    "sg:province":"FL",
    "sg:tags":[
        "car",
        "dealer"
    ],
    "wof:name":"Wholesale Auto Brokers Inc",
    "wof:placetype":"venue"
},
  "geometry": {"coordinates":[-80.20816499999999,26.024919],"type":"Point"}
}