{
  "type": "Feature",
  "properties": {
    "iso:country":"US",
    "sg:address":"10600 NW 37th St",
    "sg:city":"Doral",
    "sg:classifiers":[
        {
            "category":"Wholesale",
            "subcategory":"Auto Parts",
            "type":"Manufacturing & Wholesale Goods"
        }
    ],
    "sg:phone":"+1 305 477 4446",
    "sg:postcode":"33178",
    "sg:province":"FL",
    "sg:tags":[
        "heavy",
        "automotive",
        "accessory",
        "automobile",
        "supply"
    ],
    "wof:name":"Lindeco International Corp",
    "wof:placetype":"venue"
},
  "geometry": {"coordinates":[-80.384258,25.808588],"type":"Point"}
}