{
  "type": "Feature",
  "properties": {
    "iso:country":"US",
    "sg:address":"541 Solo Ct",
    "sg:city":"St Augustine",
    "sg:classifiers":[
        {
            "category":"Personal",
            "type":"Services"
        }
    ],
    "sg:phone":"+1 904 794 4816",
    "sg:postcode":"32086",
    "sg:province":"FL",
    "sg:tags":[
        "therapist",
        "massage"
    ],
    "wof:name":"Energy Works",
    "wof:placetype":"venue"
},
  "geometry": {"coordinates":[-81.299081,29.811023],"type":"Point"}
}