{
  "type": "Feature",
  "properties": {
    "addr:full":"2965 1st Rd Vero Beach FL 32968",
    "addr:housenumber":"2965",
    "addr:postcode":"32968",
    "addr:street":"1St Rd",
    "iso:country":"US",
    "sg:address":"2965 1st Rd",
    "sg:city":"Vero Beach",
    "sg:classifiers":[
        {
            "category":"Farming",
            "subcategory":"Farm & Veterinary Services",
            "type":"Manufacturing & Wholesale Goods"
        }
    ],
    "sg:phone":"+1 772 567 2746",
    "sg:postcode":"32968",
    "sg:province":"FL",
    "sg:tags":[
        "management"
    ],
    "wof:name":"Kinchen Groves Inc",
    "wof:placetype":"venue"
},
  "geometry": {"coordinates":[-80.418485,27.602507],"type":"Point"}
}