{
  "type": "Feature",
  "properties": {
    "addr:full":"9436 Regency Park Blvd Port Richey FL 34668",
    "addr:housenumber":"9436",
    "addr:postcode":"34668",
    "addr:street":"Regency Park Blvd",
    "iso:country":"US",
    "sg:address":"9436 Regency Park Blvd",
    "sg:city":"Port Richey",
    "sg:classifiers":[
        {
            "category":"Professional",
            "subcategory":"Lawyer & Legal Services",
            "type":"Services"
        }
    ],
    "sg:phone":"+1 727 849 1958",
    "sg:postcode":"34668",
    "sg:province":"FL",
    "wof:name":"Raymond L Parri PA",
    "wof:placetype":"venue"
},
  "geometry": {"coordinates":[-82.695639,28.294798],"type":"Point"}
}