{
  "type": "Feature",
  "properties": {
    "iso:country":"US",
    "sg:address":"2730 Mine Mill Rd",
    "sg:city":"Lakeland",
    "sg:classifiers":[
        {
            "category":"Manufacturing",
            "subcategory":"Tools & Machinery",
            "type":"Manufacturing & Wholesale Goods"
        }
    ],
    "sg:phone":"+1 863 667 3883",
    "sg:postcode":"33801",
    "sg:province":"FL",
    "sg:tags":[
        "erectors",
        "mover",
        "millwright"
    ],
    "wof:name":"Ms Industrial",
    "wof:placetype":"venue"
},
  "geometry": {"coordinates":[-81.905022,28.015367],"type":"Point"}
}