{
  "type": "Feature",
  "properties": {
    "addr:full":"290 SW 6th St Pompano Beach FL 33060",
    "addr:housenumber":"290",
    "addr:postcode":"33060",
    "addr:street":"Sw 6Th St",
    "iso:country":"US",
    "sg:address":"290 SW 6th St",
    "sg:city":"Pompano Beach",
    "sg:classifiers":[
        {
            "category":"Restaurant",
            "type":"Food & Drink"
        }
    ],
    "sg:phone":"+1 954 520 4332",
    "sg:postcode":"33060",
    "sg:province":"FL",
    "sg:tags":[
        "eating"
    ],
    "wof:name":"Potreros Ranch Restaurant",
    "wof:placetype":"venue"
},
  "geometry": {"coordinates":[-80.123501,26.222599],"type":"Point"}
}