{
  "type": "Feature",
  "properties": {
    "iso:country":"US",
    "sg:address":"8798 Sonoma Lake Blvd",
    "sg:city":"Boca Raton",
    "sg:classifiers":[
        {
            "category":"Professional",
            "subcategory":"Accounting & Tax Preparation",
            "type":"Services"
        }
    ],
    "sg:phone":"+1 561 482 0651",
    "sg:postcode":"33434",
    "sg:province":"FL",
    "wof:name":"Managerial Accounting Plg Svcs",
    "wof:placetype":"venue"
},
  "geometry": {"coordinates":[-80.183094,26.370969],"type":"Point"}
}