{
  "type": "Feature",
  "properties": {
    "iso:country":"US",
    "sg:address":"90 NE 54th St Ste. E",
    "sg:city":"Miami",
    "sg:classifiers":[
        {
            "category":"Insurance",
            "subcategory":"Insurance Agent",
            "type":"Services"
        },
        {
            "category":"Insurance",
            "subcategory":"Hazard Insurance",
            "type":"Services"
        },
        {
            "category":"Insurance",
            "subcategory":"Life Insurance",
            "type":"Services"
        }
    ],
    "sg:phone":"+1 305 759 1316",
    "sg:postcode":"33137",
    "sg:province":"FL",
    "sg:tags":[
        "auto",
        "motorcycle",
        "renter"
    ],
    "sg:website":"http://clickserve.dartsearch.net/link/click?lid=43000000142096548",
    "wof:name":"Leon Mondesir, MBA - Allstate Insurance Company",
    "wof:placetype":"venue"
},
  "geometry": {"coordinates":[-80.19420100000001,25.825317],"type":"Point"}
}