{
  "type": "Feature",
  "properties": {
    "iso:country":"US",
    "sg:address":"1598 W 37th St",
    "sg:city":"Hialeah",
    "sg:classifiers":[
        {
            "category":"Restaurant",
            "type":"Food & Drink"
        }
    ],
    "sg:phone":"+1 305 362 3595",
    "sg:postcode":"33012",
    "sg:province":"FL",
    "sg:tags":[
        "eating"
    ],
    "wof:name":"MI Publo Rsturante Y Cafeteria",
    "wof:placetype":"venue"
},
  "geometry": {"coordinates":[-80.312906,25.85524],"type":"Point"}
}