{
  "type": "Feature",
  "properties": {
    "iso:country":"US",
    "sg:address":"1218 Cleveland St",
    "sg:city":"Clearwater",
    "sg:classifiers":[
        {
            "category":"Shopping",
            "subcategory":"Clothing, Apparel, & Fashions",
            "type":"Retail Goods"
        }
    ],
    "sg:phone":"+1 727 443 2027",
    "sg:postcode":"33755",
    "sg:province":"FL",
    "sg:tags":[
        "jean"
    ],
    "wof:name":"Uncle Milty's Denim Exchange",
    "wof:placetype":"venue"
},
  "geometry": {"coordinates":[-82.785912,27.96571],"type":"Point"}
}