{
  "type": "Feature",
  "properties": {
    "iso:country":"US",
    "sg:address":"558 W New England Ave",
    "sg:city":"Winter Park",
    "sg:classifiers":[
        {
            "category":"Restaurant",
            "type":"Food & Drink"
        }
    ],
    "sg:menulink":"http://www.allmenus.com/fl/orlando/33974-dexters-of-winter-park/menu/",
    "sg:phone":"+1 407 629 1150",
    "sg:postcode":"32789",
    "sg:province":"FL",
    "sg:tags":[
        "american"
    ],
    "wof:name":"Dexter's of Winter Park",
    "wof:placetype":"venue"
},
  "geometry": {"coordinates":[-81.356414,28.59585],"type":"Point"}
}