{
  "type": "Feature",
  "properties": {
    "addr:full":"3454 Stoneler Rd Tallahassee FL 32303",
    "addr:housenumber":"3454",
    "addr:postcode":"32303",
    "addr:street":"Stoneler Rd",
    "iso:country":"US",
    "sg:address":"3454 Stoneler Rd",
    "sg:city":"Tallahassee",
    "sg:classifiers":[
        {
            "category":"Building & Trades",
            "subcategory":"Construction",
            "type":"Services"
        }
    ],
    "sg:phone":"+1 850 562 2769",
    "sg:postcode":"32303",
    "sg:province":"FL",
    "sg:tags":[
        "contractor"
    ],
    "wof:name":"Brown Terence Plst & Drywall",
    "wof:placetype":"venue"
},
  "geometry": {"coordinates":[-84.368269,30.510577],"type":"Point"}
}