{
  "type": "Feature",
  "properties": {
    "iso:country":"US",
    "sg:address":"169 E Flagler St Ste 928",
    "sg:city":"Miami",
    "sg:classifiers":[
        {
            "category":"Shopping",
            "subcategory":"Jewelry",
            "type":"Retail Goods"
        }
    ],
    "sg:phone":"+1 305 371 9111",
    "sg:postcode":"33131",
    "sg:province":"FL",
    "wof:name":"Davidoff Company Miamiinc",
    "wof:placetype":"venue"
},
  "geometry": {"coordinates":[-80.19090300000001,25.7742],"type":"Point"}
}