{
  "type": "Feature",
  "properties": {
    "iso:country":"US",
    "sg:address":"108 NE Dixie Hwy",
    "sg:city":"Stuart",
    "sg:phone":"+1 772 692 9672",
    "sg:postcode":"34994",
    "sg:province":"FL",
    "sg:website":"http://www.realpagessites.com/premierplumbingandair",
    "wof:name":"Premier Air Conditioning Company A",
    "wof:placetype":"venue"
},
  "geometry": {"coordinates":[-80.24910199999999,27.219572],"type":"Point"}
}