{
  "type": "Feature",
  "properties": {
    "iso:country":"US",
    "sg:address":"9056 Foxwood Dr S",
    "sg:city":"Tallahassee",
    "sg:classifiers":[
        {
            "category":"Building & Trades",
            "subcategory":"Construction",
            "type":"Services"
        }
    ],
    "sg:phone":"+1 850 216 1695",
    "sg:postcode":"32309",
    "sg:province":"FL",
    "sg:tags":[
        "hanging",
        "contractor"
    ],
    "wof:name":"Sunbelt Painting",
    "wof:placetype":"venue"
},
  "geometry": {"coordinates":[-84.123126,30.508059],"type":"Point"}
}