{
  "type": "Feature",
  "properties": {
    "iso:country":"US",
    "sg:address":"1320 Beville Rd",
    "sg:city":"Daytona Beach",
    "sg:classifiers":[
        {
            "category":"Social Services",
            "subcategory":"Child Care",
            "type":"Services"
        }
    ],
    "sg:phone":"+1 386 252 7193",
    "sg:postcode":"32114",
    "sg:province":"FL",
    "sg:website":"www.kindercare.com",
    "wof:name":"Kinder Care Learning Ctr",
    "wof:placetype":"venue"
},
  "geometry": {"coordinates":[-81.03818200000001,29.171392],"type":"Point"}
}