{
  "type": "Feature",
  "properties": {
    "addr:full":"960 Railroad Ave Winter Park FL 32789",
    "addr:housenumber":"960",
    "addr:postcode":"32789",
    "addr:street":"Railroad Ave",
    "iso:country":"US",
    "sg:address":"960 Railroad Ave",
    "sg:city":"Winter Park",
    "sg:classifiers":[
        {
            "category":"Retail",
            "subcategory":"Auto Repair",
            "type":"Services"
        }
    ],
    "sg:phone":"+1 407 647 2699",
    "sg:postcode":"32789",
    "sg:province":"FL",
    "sg:tags":[
        "body",
        "shop"
    ],
    "wof:name":"Hank N'son Auto Collision",
    "wof:placetype":"venue"
},
  "geometry": {"coordinates":[-81.359802,28.605801],"type":"Point"}
}