{
  "type": "Feature",
  "properties": {
    "iso:country":"US",
    "sg:address":"12910 Spivey Farms Rd",
    "sg:city":"Groveland",
    "sg:classifiers":[
        {
            "category":"Wholesale",
            "subcategory":"Motor Vehicles",
            "type":"Manufacturing & Wholesale Goods"
        }
    ],
    "sg:phone":"+1 321 229 0218",
    "sg:postcode":"34736",
    "sg:province":"FL",
    "sg:tags":[
        "automobile",
        "transporter"
    ],
    "wof:name":"Jr's Transport By Harvey Huffs",
    "wof:placetype":"venue"
},
  "geometry": {"coordinates":[-81.86836599999999,28.535515],"type":"Point"}
}