{
  "type": "Feature",
  "properties": {
    "iso:country":"US",
    "sg:address":"20314 SW 124th Pl",
    "sg:city":"Miami",
    "sg:classifiers":[
        {
            "category":"Professional",
            "subcategory":"Computer Services",
            "type":"Services"
        }
    ],
    "sg:phone":"+1 305 971 6131",
    "sg:postcode":"33177",
    "sg:province":"FL",
    "sg:tags":[
        "consultant",
        "designer",
        "system"
    ],
    "wof:name":"Two Binary, Inc.",
    "wof:placetype":"venue"
},
  "geometry": {"coordinates":[-80.394552,25.577755],"type":"Point"}
}