{
  "type": "Feature",
  "properties": {
    "iso:country":"US",
    "sg:address":"2605 Barna Ave",
    "sg:city":"Titusville",
    "sg:classifiers":[
        {
            "category":"Wholesale",
            "subcategory":"Medical Equipment & Supplies",
            "type":"Manufacturing & Wholesale Goods"
        },
        {
            "category":"Shopping",
            "subcategory":"Pharmacy",
            "type":"Retail Goods"
        }
    ],
    "sg:phone":"+1 321 269 7392",
    "sg:postcode":"32780",
    "sg:province":"FL",
    "sg:tags":[
        "home",
        "care",
        "health",
        "first",
        "aid"
    ],
    "sg:website":"http://www.walgreens.com",
    "wof:name":"Walgreen Drug Stores",
    "wof:placetype":"venue"
},
  "geometry": {"coordinates":[-80.818816,28.585638],"type":"Point"}
}