{
  "type": "Feature",
  "properties": {
    "iso:country":"US",
    "sg:address":"1538 Garden Ave",
    "sg:city":"Daytona Beach",
    "sg:classifiers":[
        {
            "category":"Home & Garden",
            "subcategory":"Building Materials",
            "type":"Retail Goods"
        }
    ],
    "sg:phone":"+1 386 671 1134",
    "sg:postcode":"32117",
    "sg:province":"FL",
    "sg:tags":[
        "windows"
    ],
    "wof:name":"Allstar Building Materials",
    "wof:placetype":"venue"
},
  "geometry": {"coordinates":[-81.04947900000001,29.251531],"type":"Point"}
}