{
  "type": "Feature",
  "properties": {
    "iso:country":"US",
    "sg:address":"5621 Central Ave",
    "sg:city":"St Petersburg",
    "sg:classifiers":[
        {
            "category":"Health Services",
            "subcategory":"Chiropractor",
            "type":"Services"
        }
    ],
    "sg:phone":"+1 727 343 6060",
    "sg:postcode":"33710",
    "sg:province":"FL",
    "wof:name":"Hartley Chiropractic Ctr",
    "wof:placetype":"venue"
},
  "geometry": {"coordinates":[-82.710534,27.770957],"type":"Point"}
}