{
  "type": "Feature",
  "properties": {
    "iso:country":"US",
    "sg:address":"4554 S Semoran Blvd",
    "sg:city":"Orlando",
    "sg:classifiers":[
        {
            "category":"Travel",
            "subcategory":"Travel Agent",
            "type":"Entertainment"
        }
    ],
    "sg:phone":"+1 407 281 0775",
    "sg:postcode":"32822",
    "sg:province":"FL",
    "sg:tags":[
        "agency"
    ],
    "wof:name":"Nta Pacific",
    "wof:placetype":"venue"
},
  "geometry": {"coordinates":[-81.31028999999999,28.495306],"type":"Point"}
}