{
  "type": "Feature",
  "properties": {
    "addr:full":"1111 Cheshire Ct Safety Harbor FL 34695",
    "addr:housenumber":"1111",
    "addr:postcode":"34695",
    "addr:street":"Cheshire Ct",
    "iso:country":"US",
    "sg:address":"1111 Cheshire Ct",
    "sg:city":"Safety Harbor",
    "sg:classifiers":[
        {
            "category":"Real Estate",
            "subcategory":"Real Estate Operator",
            "type":"Services"
        }
    ],
    "sg:phone":"+1 727 723 7922",
    "sg:postcode":"34695",
    "sg:province":"FL",
    "sg:tags":[
        "building",
        "nonresidential"
    ],
    "wof:name":"BBC Properties LLC",
    "wof:placetype":"venue"
},
  "geometry": {"coordinates":[-82.69716200000001,28.006024],"type":"Point"}
}