{
  "type": "Feature",
  "properties": {
    "iso:country":"US",
    "sg:address":"12001 Avalon Lake Dr",
    "sg:city":"Orlando",
    "sg:classifiers":[
        {
            "category":"Bakery",
            "type":"Food & Drink"
        }
    ],
    "sg:phone":"+1 407 207 0205",
    "sg:postcode":"32828",
    "sg:province":"FL",
    "wof:name":"Davis Bakery And Company",
    "wof:placetype":"venue"
},
  "geometry": {"coordinates":[-81.156319,28.510269],"type":"Point"}
}