{
  "type": "Feature",
  "properties": {
    "addr:full":"721 NE 51st Ct Pompano Beach FL 33064",
    "addr:housenumber":"721",
    "addr:postcode":"33064",
    "addr:street":"Ne 51St Ct",
    "iso:country":"US",
    "sg:address":"721 NE 51st Ct",
    "sg:city":"Pompano Beach",
    "sg:classifiers":[
        {
            "category":"Social Services",
            "subcategory":"Child Care",
            "type":"Services"
        }
    ],
    "sg:phone":"+1 954 481 8388",
    "sg:postcode":"33064",
    "sg:province":"FL",
    "wof:name":"Tots Unlimited",
    "wof:placetype":"venue"
},
  "geometry": {"coordinates":[-80.11317,26.294348],"type":"Point"}
}