{
  "type": "Feature",
  "properties": {
    "addr:full":"6107 Broad St Brooksville FL 34601",
    "addr:housenumber":"6107",
    "addr:postcode":"34601",
    "addr:street":"Broad St",
    "iso:country":"US",
    "sg:address":"6107 Broad St",
    "sg:city":"Brooksville",
    "sg:classifiers":[
        {
            "category":"Bars & Pubs",
            "type":"Food & Drink"
        }
    ],
    "sg:phone":"+1 352 796 1877",
    "sg:postcode":"34601",
    "sg:province":"FL",
    "wof:name":"Sail Inn",
    "wof:placetype":"venue"
},
  "geometry": {"coordinates":[-82.41442000000001,28.52095],"type":"Point"}
}