{
  "type": "Feature",
  "properties": {
    "iso:country":"US",
    "sg:address":"3811 University Blvd W",
    "sg:city":"Jacksonville",
    "sg:classifiers":[
        {
            "category":"Home & Garden",
            "subcategory":"Furniture",
            "type":"Retail Goods"
        }
    ],
    "sg:phone":"+1 904 737 6906",
    "sg:postcode":"32217",
    "sg:province":"FL",
    "sg:tags":[
        "cabinet"
    ],
    "wof:name":"Custom Wood Products",
    "wof:placetype":"venue"
},
  "geometry": {"coordinates":[-81.622327,30.263797],"type":"Point"}
}