{
  "type": "Feature",
  "properties": {
    "iso:country":"US",
    "sg:address":"49 NW 5th St",
    "sg:city":"Miami",
    "sg:classifiers":[
        {
            "category":"Government",
            "subcategory":"Office",
            "type":"Public Place"
        }
    ],
    "sg:phone":"+1 305 374 5776",
    "sg:postcode":"33128",
    "sg:province":"FL",
    "sg:tags":[
        "administrative",
        "program",
        "economic",
        "general"
    ],
    "wof:name":"Small Business Resource Center",
    "wof:placetype":"venue"
},
  "geometry": {"coordinates":[-80.19379600000001,25.778979],"type":"Point"}
}