{
  "type": "Feature",
  "properties": {
    "iso:country":"US",
    "sg:address":"557 Beville Rd",
    "sg:city":"South Daytona",
    "sg:classifiers":[
        {
            "category":"Shopping",
            "subcategory":"Computers & Home Electronics",
            "type":"Retail Goods"
        }
    ],
    "sg:phone":"+1 386 304 8005",
    "sg:postcode":"32119",
    "sg:province":"FL",
    "sg:tags":[
        "equipment",
        "dealer"
    ],
    "wof:name":"Your Computer Techs Inc",
    "wof:placetype":"venue"
},
  "geometry": {"coordinates":[-81.011897,29.18216],"type":"Point"}
}