{
  "type": "Feature",
  "properties": {
    "addr:full":"3617 Saint Johns Ave Jacksonville FL 32205",
    "addr:housenumber":"3617",
    "addr:postcode":"32205",
    "addr:street":"Saint Johns Ave",
    "iso:country":"US",
    "sg:address":"3617 Saint Johns Ave",
    "sg:city":"Jacksonville",
    "sg:classifiers":[
        {
            "category":"Shopping",
            "subcategory":"Jewelry",
            "type":"Retail Goods"
        }
    ],
    "sg:phone":"+1 904 388 5406",
    "sg:postcode":"32205",
    "sg:province":"FL",
    "sg:tags":[
        "jeweler"
    ],
    "wof:name":"Underwood Jewelers Corp",
    "wof:placetype":"venue"
},
  "geometry": {"coordinates":[-81.699091,30.300491],"type":"Point"}
}