{
  "type": "Feature",
  "properties": {
    "iso:country":"US",
    "sg:address":"595 Lotus Landing Blvd",
    "sg:city":"Altamonte Springs",
    "sg:classifiers":[
        {
            "category":"Real Estate",
            "subcategory":"Real Estate Operator",
            "type":"Services"
        }
    ],
    "sg:phone":"+1 407 297 9415",
    "sg:postcode":"32714",
    "sg:province":"FL",
    "sg:tags":[
        "apartment"
    ],
    "wof:name":"Lotus Landing Apartments",
    "wof:placetype":"venue"
},
  "geometry": {"coordinates":[-81.41709899999999,28.6479],"type":"Point"}
}