{
  "type": "Feature",
  "properties": {
    "iso:country":"US",
    "sg:address":"8955 Charleston Park",
    "sg:city":"Orlando",
    "sg:classifiers":[
        {
            "category":"Farming",
            "subcategory":"Farm",
            "type":"Manufacturing & Wholesale Goods"
        }
    ],
    "sg:phone":"+1 407 876 4331",
    "sg:postcode":"32819",
    "sg:province":"FL",
    "wof:name":"State Farm Tom Mc Coy Ag",
    "wof:placetype":"venue"
},
  "geometry": {"coordinates":[-81.50612599999999,28.463921],"type":"Point"}
}