{
  "type": "Feature",
  "properties": {
    "iso:country":"US",
    "sg:address":"300 Brunson Blvd",
    "sg:city":"Cocoa",
    "sg:classifiers":[
        {
            "category":"Government",
            "subcategory":"Fire Station",
            "type":"Public Place"
        }
    ],
    "sg:phone":"+1 321 639 7500",
    "sg:postcode":"32922",
    "sg:province":"FL",
    "sg:tags":[
        "protection"
    ],
    "wof:name":"City of Cocoa Fire Dept 3",
    "wof:placetype":"venue"
},
  "geometry": {"coordinates":[-80.733554,28.361037],"type":"Point"}
}