{
  "type": "Feature",
  "properties": {
    "iso:country":"US",
    "sg:address":"1600 E 8th Ave",
    "sg:city":"Tampa",
    "sg:classifiers":[
        {
            "category":"Shopping",
            "subcategory":"Gifts & Souvenirs",
            "type":"Retail Goods"
        }
    ],
    "sg:phone":"+1 813 241 8292",
    "sg:postcode":"33605",
    "sg:province":"FL",
    "sg:tags":[
        "shop"
    ],
    "wof:name":"Centro Ybor Intl Bazaar",
    "wof:placetype":"venue"
},
  "geometry": {"coordinates":[-82.442802,27.961073],"type":"Point"}
}