{
  "type": "Feature",
  "properties": {
    "addr:full":"1833 NE 24th St Pompano Beach FL 33064",
    "addr:housenumber":"1833",
    "addr:postcode":"33064",
    "addr:street":"Ne 24Th St",
    "iso:country":"US",
    "sg:address":"1833 NE 24th St",
    "sg:city":"Pompano Beach",
    "sg:classifiers":[
        {
            "category":"Shopping",
            "type":"Retail Goods"
        }
    ],
    "sg:phone":"+1 954 941 6315",
    "sg:postcode":"33064",
    "sg:province":"FL",
    "sg:tags":[
        "pet",
        "grooming",
        "supply"
    ],
    "wof:name":"Pet Haven",
    "wof:placetype":"venue"
},
  "geometry": {"coordinates":[-80.09911,26.261247],"type":"Point"}
}