{
  "type": "Feature",
  "properties": {
    "iso:country":"US",
    "sg:address":"7345 Bay St",
    "sg:city":"St Pete Beach",
    "sg:classifiers":[
        {
            "category":"Travel",
            "subcategory":"Hotels & Motels",
            "type":"Entertainment"
        }
    ],
    "sg:phone":"+1 727 367 5098",
    "sg:postcode":"33706",
    "sg:province":"FL",
    "wof:name":"Bay Winds Resort Motel & Apt",
    "wof:placetype":"venue"
},
  "geometry": {"coordinates":[-82.746241,27.743483],"type":"Point"}
}