{
  "type": "Feature",
  "properties": {
    "addr:full":"10612 Front Beach Rd Panama City Bch FL 32407",
    "addr:housenumber":"10612",
    "addr:postcode":"32407",
    "addr:street":"Front Beach Rd",
    "iso:country":"US",
    "sg:address":"10612 Front Beach Rd",
    "sg:city":"Panama City Bch",
    "sg:classifiers":[
        {
            "category":"Banks & Credit Unions",
            "subcategory":"Investment Brokerage",
            "type":"Services"
        }
    ],
    "sg:phone":"+1 850 235 4258",
    "sg:postcode":"32407",
    "sg:province":"FL",
    "sg:tags":[
        "advisory",
        "financial"
    ],
    "wof:name":"American Coast To Coast Fnncl",
    "wof:placetype":"venue"
},
  "geometry": {"coordinates":[-85.81093799999999,30.179299],"type":"Point"}
}