{
  "type": "Feature",
  "properties": {
    "iso:country":"US",
    "sg:address":"6230 SW 16th St",
    "sg:city":"Miami",
    "sg:classifiers":[
        {
            "category":"Real Estate",
            "subcategory":"Real Estate Services",
            "type":"Services"
        }
    ],
    "sg:phone":"+1 305 265 6199",
    "sg:postcode":"33155",
    "sg:province":"FL",
    "sg:tags":[
        "company",
        "title"
    ],
    "wof:name":"Florida State Title Svc Only",
    "wof:placetype":"venue"
},
  "geometry": {"coordinates":[-80.29684,25.755937],"type":"Point"}
}