{
  "type": "Feature",
  "properties": {
    "iso:country":"US",
    "sg:address":"22312 Calibre Ct",
    "sg:city":"Boca Raton",
    "sg:classifiers":[
        {
            "category":"Building & Trades",
            "subcategory":"Construction",
            "type":"Services"
        }
    ],
    "sg:phone":"+1 561 338 6576",
    "sg:postcode":"33433",
    "sg:province":"FL",
    "sg:tags":[
        "residential"
    ],
    "wof:name":"Exquisite Designs",
    "wof:placetype":"venue"
},
  "geometry": {"coordinates":[-80.155655,26.345943],"type":"Point"}
}