{
  "type": "Feature",
  "properties": {
    "addr:full":"757 Arthur Godfrey Rd Miami Beach FL 33140",
    "addr:housenumber":"757",
    "addr:postcode":"33140",
    "addr:street":"Arthur Godfrey Rd",
    "iso:country":"US",
    "sg:address":"757 Arthur Godfrey Rd",
    "sg:city":"Miami Beach",
    "sg:classifiers":[
        {
            "category":"Health Services",
            "subcategory":"Dentist",
            "type":"Services"
        }
    ],
    "sg:phone":"+1 305 673 3474",
    "sg:postcode":"33140",
    "sg:province":"FL",
    "wof:name":"Davis Howard M DDS",
    "wof:placetype":"venue"
},
  "geometry": {"coordinates":[-80.13221799999999,25.813994],"type":"Point"}
}