{
  "type": "Feature",
  "properties": {
    "addr:full":"651 NE 25th St Hialeah FL 33064",
    "addr:housenumber":"651",
    "addr:postcode":"33064",
    "addr:street":"Ne 25Th St",
    "iso:country":"US",
    "sg:address":"651 NE 25th St",
    "sg:city":"Hialeah",
    "sg:classifiers":[
        {
            "category":"Health Services",
            "subcategory":"Doctor",
            "type":"Services"
        }
    ],
    "sg:phone":"+1 305 835 4725",
    "sg:postcode":"33064",
    "sg:province":"FL",
    "sg:tags":[
        "medical"
    ],
    "wof:name":"Carlos J Goldenberg MD",
    "wof:placetype":"venue"
},
  "geometry": {"coordinates":[-80.113395,26.261853],"type":"Point"}
}