{
  "type": "Feature",
  "properties": {
    "iso:country":"US",
    "sg:address":"116 Fiesta Dr",
    "sg:city":"Kissimmee",
    "sg:classifiers":[
        {
            "category":"Professional",
            "subcategory":"Detective & Security Services",
            "type":"Services"
        }
    ],
    "sg:phone":"+1 407 344 2997",
    "sg:postcode":"34743",
    "sg:province":"FL",
    "sg:tags":[
        "investigator"
    ],
    "wof:name":"Lacy Investigation",
    "wof:placetype":"venue"
},
  "geometry": {"coordinates":[-81.36187099999999,28.325506],"type":"Point"}
}