{
  "type": "Feature",
  "properties": {
    "iso:country":"US",
    "sg:address":"3216 Little Rd",
    "sg:city":"New Port Richey",
    "sg:classifiers":[
        {
            "category":"Restaurant",
            "type":"Food & Drink"
        }
    ],
    "sg:menulink":"http://www.allmenus.com/fl/new-port-richey/48625-beef-obradys/menu/",
    "sg:phone":"+1 727 376 5550",
    "sg:postcode":"34655",
    "sg:province":"FL",
    "sg:tags":[
        "burger",
        "american",
        "wing",
        "pub"
    ],
    "wof:name":"Beef O'Brady's",
    "wof:placetype":"venue"
},
  "geometry": {"coordinates":[-82.666016,28.205064],"type":"Point"}
}