{
  "type": "Feature",
  "properties": {
    "iso:country":"US",
    "sg:address":"1720 Harrison St",
    "sg:city":"Hollywood",
    "sg:classifiers":[
        {
            "category":"Professional",
            "subcategory":"Lawyer & Legal Services",
            "type":"Services"
        }
    ],
    "sg:phone":"+1 954 239 7903",
    "sg:postcode":"33020",
    "sg:province":"FL",
    "sg:tags":[
        "litigation",
        "attorney",
        "accident",
        "personal",
        "civil",
        "damage",
        "trial",
        "malpractice",
        "injury",
        "property",
        "law"
    ],
    "sg:website":"http://www.adamscherlaw.calls.net/",
    "wof:name":"Adam Scher Law Group",
    "wof:placetype":"venue"
},
  "geometry": {"coordinates":[-80.14124,26.010668],"type":"Point"}
}