{
  "type": "Feature",
  "properties": {
    "iso:country":"US",
    "sg:address":"10800 Aria Ct",
    "sg:city":"Clermont",
    "sg:classifiers":[
        {
            "category":"Banks & Credit Unions",
            "subcategory":"Bank",
            "type":"Services"
        }
    ],
    "sg:phone":"+1 352 242 9292",
    "sg:postcode":"34711",
    "sg:province":"FL",
    "sg:tags":[
        "loan",
        "real estate"
    ],
    "wof:name":"Abraham Mortgage",
    "wof:placetype":"venue"
},
  "geometry": {"coordinates":[-81.76124900000001,28.50144],"type":"Point"}
}