{
  "type": "Feature",
  "properties": {
    "iso:country":"US",
    "sg:address":"535 Central Ave",
    "sg:city":"St Petersburg",
    "sg:classifiers":[
        {
            "category":"Professional",
            "subcategory":"Lawyer & Legal Services",
            "type":"Services"
        }
    ],
    "sg:phone":"+1 727 898 2700",
    "sg:postcode":"33705",
    "sg:province":"FL",
    "sg:tags":[
        "attorney"
    ],
    "wof:name":"Randall C Hiepe",
    "wof:placetype":"venue"
},
  "geometry": {"coordinates":[-82.64126,27.771275],"type":"Point"}
}