{
  "type": "Feature",
  "properties": {
    "iso:country":"US",
    "sg:address":"15013 Madeira Way",
    "sg:city":"Madeira Beach",
    "sg:classifiers":[
        {
            "category":"Autos & Motor Vehicles",
            "subcategory":"Boat Sales",
            "type":"Retail Goods"
        }
    ],
    "sg:phone":"+1 727 391 0069",
    "sg:postcode":"33708",
    "sg:province":"FL",
    "sg:tags":[
        "yacht",
        "broker"
    ],
    "wof:name":"Us Yacht Brokerage",
    "wof:placetype":"venue"
},
  "geometry": {"coordinates":[-82.801023,27.802011],"type":"Point"}
}