{
  "type": "Feature",
  "properties": {
    "addr:full":"1657 Michigan Ave Miami Beach FL 33139",
    "addr:housenumber":"1657",
    "addr:postcode":"33139",
    "addr:street":"Michigan Ave",
    "iso:country":"US",
    "sg:address":"1657 Michigan Ave",
    "sg:city":"Miami Beach",
    "sg:classifiers":[
        {
            "category":"Building & Trades",
            "subcategory":"Locksmith",
            "type":"Services"
        }
    ],
    "sg:phone":"+1 786 228 5679",
    "sg:postcode":"33139",
    "sg:province":"FL",
    "sg:tags":[
        "key"
    ],
    "wof:name":"Miami Beach 24 Hour Emergency Locksmith",
    "wof:placetype":"venue"
},
  "geometry": {"coordinates":[-80.138921,25.790596],"type":"Point"}
}