{
  "type": "Feature",
  "properties": {
    "addr:full":"5914 Jeff Ates Rd Milton FL 32583",
    "addr:housenumber":"5914",
    "addr:postcode":"32583",
    "addr:street":"Jeff Ates Rd",
    "iso:country":"US",
    "sg:address":"5914 Jeff Ates Rd",
    "sg:city":"Milton",
    "sg:classifiers":[
        {
            "category":"Government",
            "subcategory":"Office",
            "type":"Public Place"
        }
    ],
    "sg:phone":"+1 850 981 2409",
    "sg:postcode":"32583",
    "sg:province":"FL",
    "sg:tags":[
        "parish",
        "township",
        "government-city",
        "government-county",
        "village"
    ],
    "wof:name":"Blackwater River Correctional Facility",
    "wof:placetype":"venue"
},
  "geometry": {"coordinates":[-86.954984,30.645534],"type":"Point"}
}