{
  "type": "Feature",
  "properties": {
    "iso:country":"US",
    "sg:address":"3440 Hollywood Blvd",
    "sg:city":"Hollywood",
    "sg:classifiers":[
        {
            "category":"Professional",
            "subcategory":"Secretarial Services",
            "type":"Services"
        }
    ],
    "sg:phone":"+1 954 989 2423",
    "sg:postcode":"33021",
    "sg:province":"FL",
    "sg:tags":[
        "reporting"
    ],
    "wof:name":"Esquire Deposition Services",
    "wof:placetype":"venue"
},
  "geometry": {"coordinates":[-80.178118,26.010663],"type":"Point"}
}