{
  "type": "Feature",
  "properties": {
    "addr:full":"6850 Coral Way Ste 304 Miami FL 33155",
    "addr:housenumber":"6850",
    "addr:postcode":"33155",
    "addr:street":"Coral Way Ste 304",
    "iso:country":"US",
    "sg:address":"6850 Coral Way Ste 304",
    "sg:city":"Miami",
    "sg:classifiers":[
        {
            "category":"Health Services",
            "subcategory":"Doctor",
            "type":"Services"
        }
    ],
    "sg:phone":"+1 305 665 8205",
    "sg:postcode":"33155",
    "sg:province":"FL",
    "wof:name":"Mestre Canals Luis MD",
    "wof:placetype":"venue"
},
  "geometry": {"coordinates":[-80.30635599999999,25.747803],"type":"Point"}
}