{
  "type": "Feature",
  "properties": {
    "iso:country":"US",
    "sg:address":"411 Piney Island Dr",
    "sg:city":"Fernandina Beach",
    "sg:classifiers":[
        {
            "category":"Building & Trades",
            "subcategory":"Construction",
            "type":"Services"
        }
    ],
    "sg:phone":"+1 904 261 5013",
    "sg:postcode":"32034",
    "sg:province":"FL",
    "sg:tags":[
        "residential",
        "contractor"
    ],
    "wof:name":"Bean Builders Inc",
    "wof:placetype":"venue"
},
  "geometry": {"coordinates":[-81.498608,30.632638],"type":"Point"}
}