{
  "type": "Feature",
  "properties": {
    "addr:full":"500 John Ringling Blvd Ste 1 Sarasota FL 34236",
    "addr:housenumber":"500",
    "addr:postcode":"34236",
    "addr:street":"John Ringling Blvd Ste 1",
    "iso:country":"US",
    "sg:address":"500 John Ringling Blvd Ste 1",
    "sg:city":"Sarasota",
    "sg:classifiers":[
        {
            "category":"Health Services",
            "subcategory":"Doctor",
            "type":"Services"
        },
        {
            "category":"Health Services",
            "subcategory":"Nursing And Care Facility",
            "type":"Services"
        }
    ],
    "sg:phone":"+1 941 388 4408",
    "sg:postcode":"34236",
    "sg:province":"FL",
    "sg:tags":[
        "physician",
        "management",
        "pain",
        "family",
        "practice",
        "surgeons",
        "medicine",
        "surgeon"
    ],
    "wof:name":"Carlstrom, Edward F, Md - St Armands Medical Ctr",
    "wof:placetype":"venue"
},
  "geometry": {"coordinates":[-82.575661,27.31917],"type":"Point"}
}