{
  "type": "Feature",
  "properties": {
    "iso:country":"US",
    "sg:address":"7105 W 12th Ave",
    "sg:city":"Hialeah",
    "sg:classifiers":[
        {
            "category":"Personal",
            "subcategory":"Beauty Salon",
            "type":"Services"
        }
    ],
    "sg:phone":"+1 305 819 1747",
    "sg:postcode":"33014",
    "sg:province":"FL",
    "wof:name":"Pretty Woman Hair & Nail",
    "wof:placetype":"venue"
},
  "geometry": {"coordinates":[-80.30766800000001,25.887885],"type":"Point"}
}