{
  "type": "Feature",
  "properties": {
    "addr:full":"1540 Palm Pl Bartow FL 33830",
    "addr:housenumber":"1540",
    "addr:postcode":"33830",
    "addr:street":"Palm Pl",
    "iso:country":"US",
    "sg:address":"1540 Palm Pl",
    "sg:city":"Bartow",
    "sg:classifiers":[
        {
            "category":"Utilities",
            "subcategory":"Refuse",
            "type":"Services"
        }
    ],
    "sg:phone":"+1 863 581 4625",
    "sg:postcode":"33830",
    "sg:province":"FL",
    "sg:tags":[
        "garbage",
        "collection"
    ],
    "wof:name":"Swift Debris & Trash Removal",
    "wof:placetype":"venue"
},
  "geometry": {"coordinates":[-81.833736,27.880213],"type":"Point"}
}