{
  "type": "Feature",
  "properties": {
    "iso:country":"US",
    "sg:address":"11 Cherrytree Ct",
    "sg:city":"Palm Coast",
    "sg:classifiers":[
        {
            "category":"Banks & Credit Unions",
            "subcategory":"Financial Services",
            "type":"Services"
        }
    ],
    "sg:phone":"+1 386 445 9091",
    "sg:postcode":"32137",
    "sg:province":"FL",
    "sg:tags":[
        "investor"
    ],
    "wof:name":"Lily White Investment Company",
    "wof:placetype":"venue"
},
  "geometry": {"coordinates":[-81.21880899999999,29.596899],"type":"Point"}
}