{
  "type": "Feature",
  "properties": {
    "addr:full":"211 E Park Ave Lake Wales FL 33858",
    "addr:housenumber":"211",
    "addr:postcode":"33858",
    "addr:street":"E Park Ave",
    "iso:country":"US",
    "sg:address":"211 E Park Ave",
    "sg:city":"Lake Wales",
    "sg:classifiers":[
        {
            "category":"Personal",
            "subcategory":"Beauty Salon",
            "type":"Services"
        }
    ],
    "sg:phone":"+1 863 676 2655",
    "sg:postcode":"33858",
    "sg:province":"FL",
    "sg:tags":[
        "shop"
    ],
    "wof:name":"Hair Affair",
    "wof:placetype":"venue"
},
  "geometry": {"coordinates":[-81.587153,27.90277],"type":"Point"}
}