{
  "type": "Feature",
  "properties": {
    "addr:full":"22115 27th Ave E Bradenton FL 34211",
    "addr:housenumber":"22115",
    "addr:postcode":"34211",
    "addr:street":"27Th Ave E",
    "iso:country":"US",
    "sg:address":"22115 27th Ave E",
    "sg:city":"Bradenton",
    "sg:classifiers":[
        {
            "category":"Freight",
            "type":"Transportation"
        }
    ],
    "sg:phone":"+1 941 322 1762",
    "sg:postcode":"34211",
    "sg:province":"FL",
    "wof:name":"Becker Steven and Cleta",
    "wof:placetype":"venue"
},
  "geometry": {"coordinates":[-82.315811,27.468233],"type":"Point"}
}