{
  "type": "Feature",
  "properties": {
    "iso:country":"US",
    "sg:address":"9212 Anderson Rd",
    "sg:city":"Tampa",
    "sg:classifiers":[
        {
            "category":"Restaurant",
            "type":"Food & Drink"
        }
    ],
    "sg:phone":"+1 813 901 8027",
    "sg:postcode":"33634",
    "sg:province":"FL",
    "wof:name":"Vallarta's Mexican Restaurant",
    "wof:placetype":"venue"
},
  "geometry": {"coordinates":[-82.540633,28.032633],"type":"Point"}
}