{
  "type": "Feature",
  "properties": {
    "iso:country":"US",
    "sg:address":"309 Farmington Dr",
    "sg:city":"Fort Lauderdale",
    "sg:classifiers":[
        {
            "category":"Marine",
            "type":"Transportation"
        }
    ],
    "sg:phone":"+1 954 792 0535",
    "sg:postcode":"33317",
    "sg:province":"FL",
    "sg:tags":[
        "water",
        "transport"
    ],
    "wof:name":"World Yacht Survey",
    "wof:placetype":"venue"
},
  "geometry": {"coordinates":[-80.225219,26.126451],"type":"Point"}
}