{
  "type": "Feature",
  "properties": {
    "iso:country":"US",
    "sg:address":"4616 W San Miguel St",
    "sg:city":"Tampa",
    "sg:classifiers":[
        {
            "category":"Banks & Credit Unions",
            "subcategory":"Bank",
            "type":"Services"
        }
    ],
    "sg:phone":"+1 813 251 5901",
    "sg:postcode":"33629",
    "sg:province":"FL",
    "sg:tags":[
        "institution",
        "business"
    ],
    "wof:name":"Maureen A Cohn",
    "wof:placetype":"venue"
},
  "geometry": {"coordinates":[-82.522535,27.924756],"type":"Point"}
}