{
  "type": "Feature",
  "properties": {
    "addr:full":"2401 Gulfstream Dr Hollywood FL 33023",
    "addr:housenumber":"2401",
    "addr:postcode":"33023",
    "addr:street":"Gulfstream Dr",
    "iso:country":"US",
    "sg:address":"2401 Gulfstream Dr",
    "sg:city":"Hollywood",
    "sg:classifiers":[
        {
            "category":"Professional",
            "subcategory":"Business Services",
            "type":"Services"
        }
    ],
    "sg:phone":"+1 954 894 3307",
    "sg:postcode":"33023",
    "sg:province":"FL",
    "wof:name":"Donna K Marsh",
    "wof:placetype":"venue"
},
  "geometry": {"coordinates":[-80.236739,25.990345],"type":"Point"}
}