{
  "type": "Feature",
  "properties": {
    "addr:full":"750 S Orange Blossom Trl Orlando FL 32805",
    "addr:housenumber":"750",
    "addr:postcode":"32805",
    "addr:street":"S Orange Blossom Trl",
    "iso:country":"US",
    "sg:address":"750 S Orange Blossom Trl",
    "sg:city":"Orlando",
    "sg:classifiers":[
        {
            "category":"Manufacturing",
            "subcategory":"Printing",
            "type":"Manufacturing & Wholesale Goods"
        }
    ],
    "sg:phone":"+1 407 770 0062",
    "sg:postcode":"32805",
    "sg:province":"FL",
    "sg:tags":[
        "printer"
    ],
    "wof:name":"Xcitment Print Club & Network",
    "wof:placetype":"venue"
},
  "geometry": {"coordinates":[-81.397237,28.533842],"type":"Point"}
}