{
  "type": "Feature",
  "properties": {
    "addr:full":"1998 SW Sunset Trl Palm City FL 34990",
    "addr:housenumber":"1998",
    "addr:postcode":"34990",
    "addr:street":"Sw Sunset Trl",
    "iso:country":"US",
    "sg:address":"1998 SW Sunset Trl",
    "sg:city":"Palm City",
    "sg:classifiers":[
        {
            "category":"Freight",
            "type":"Transportation"
        }
    ],
    "sg:phone":"+1 772 221 7746",
    "sg:postcode":"34990",
    "sg:province":"FL",
    "wof:name":"Twilight Transportation",
    "wof:placetype":"venue"
},
  "geometry": {"coordinates":[-80.280539,27.168408],"type":"Point"}
}