{
  "type": "Feature",
  "properties": {
    "iso:country":"US",
    "sg:address":"6414 126th Ave N",
    "sg:city":"Largo",
    "sg:classifiers":[
        {
            "category":"Recreation",
            "type":"Entertainment"
        }
    ],
    "sg:phone":"+1 727 530 4884",
    "sg:postcode":"33773",
    "sg:province":"FL",
    "sg:tags":[
        "paint",
        "ball",
        "sport"
    ],
    "wof:name":"Gladiator Paintball",
    "wof:placetype":"venue"
},
  "geometry": {"coordinates":[-82.725697,27.886378],"type":"Point"}
}