{
  "type": "Feature",
  "properties": {
    "iso:country":"US",
    "sg:address":"222 Michigan Ave",
    "sg:city":"Indialantic",
    "sg:classifiers":[
        {
            "category":"Building & Trades",
            "subcategory":"Construction",
            "type":"Services"
        }
    ],
    "sg:phone":"+1 321 725 7490",
    "sg:postcode":"32903",
    "sg:province":"FL",
    "sg:tags":[
        "carpentry",
        "contractor"
    ],
    "wof:name":"Quality Window & Trim",
    "wof:placetype":"venue"
},
  "geometry": {"coordinates":[-80.571821,28.094114],"type":"Point"}
}