{
  "type": "Feature",
  "properties": {
    "addr:full":"3200 US Hwy 27 Sebring FL 33870",
    "addr:housenumber":"3200",
    "addr:postcode":"33870",
    "addr:street":"Us Hwy 27",
    "iso:country":"US",
    "sg:address":"3200 US Hwy 27",
    "sg:city":"Sebring",
    "sg:classifiers":[
        {
            "category":"Professional",
            "subcategory":"Lawyer & Legal Services",
            "type":"Services"
        }
    ],
    "sg:phone":"+1 863 386 1500",
    "sg:postcode":"33870",
    "sg:province":"FL",
    "sg:tags":[
        "attorney"
    ],
    "wof:name":"Keith Chasin",
    "wof:placetype":"venue"
},
  "geometry": {"coordinates":[-81.440347,27.469458],"type":"Point"}
}