{
  "type": "Feature",
  "properties": {
    "addr:full":"1415 N Monitor Ave Orlando FL 32818",
    "addr:housenumber":"1415",
    "addr:postcode":"32818",
    "addr:street":"N Monitor Ave",
    "iso:country":"US",
    "sg:address":"1415 N Monitor Ave",
    "sg:city":"Orlando",
    "sg:classifiers":[
        {
            "category":"Freight",
            "type":"Transportation"
        }
    ],
    "sg:phone":"+1 407 445 0352",
    "sg:postcode":"32818",
    "sg:province":"FL",
    "sg:tags":[
        "operator",
        "local",
        "trucking"
    ],
    "wof:name":"KDJ Trucking Inc",
    "wof:placetype":"venue"
},
  "geometry": {"coordinates":[-81.471695,28.557951],"type":"Point"}
}