{
  "type": "Feature",
  "properties": {
    "iso:country":"US",
    "sg:address":"1290 US Hwy 92",
    "sg:city":"Longwood",
    "sg:classifiers":[
        {
            "category":"Autos & Motor Vehicles",
            "subcategory":"Automobile Sales",
            "type":"Retail Goods"
        },
        {
            "category":"Retail",
            "subcategory":"Auto Repair",
            "type":"Services"
        }
    ],
    "sg:phone":"+1 407 263 7162",
    "sg:postcode":"32750",
    "sg:province":"FL",
    "sg:tags":[
        "car",
        "dealer",
        "general"
    ],
    "wof:name":"Affordable Import Auto Inc",
    "wof:placetype":"venue"
},
  "geometry": {"coordinates":[-81.32890399999999,28.689042],"type":"Point"}
}