{
  "type": "Feature",
  "properties": {
    "addr:full":"1314 Tampa Rd Palm Harbor FL 34683",
    "addr:housenumber":"1314",
    "addr:postcode":"34683",
    "addr:street":"Tampa Rd",
    "iso:country":"US",
    "sg:address":"1314 Tampa Rd",
    "sg:city":"Palm Harbor",
    "sg:classifiers":[
        {
            "category":"Restaurant",
            "type":"Food & Drink"
        }
    ],
    "sg:phone":"+1 727 781 8880",
    "sg:postcode":"34683",
    "sg:province":"FL",
    "wof:name":"Happy China",
    "wof:placetype":"venue"
},
  "geometry": {"coordinates":[-82.76465899999999,28.068153],"type":"Point"}
}