{
  "type": "Feature",
  "properties": {
    "addr:full":"7546 W McNab Rd North Lauderdale FL 33068",
    "addr:housenumber":"7546",
    "addr:postcode":"33068",
    "addr:street":"W Mcnab Rd",
    "iso:country":"US",
    "sg:address":"7546 W McNab Rd",
    "sg:city":"North Lauderdale",
    "sg:classifiers":[
        {
            "category":"Food & Beverages",
            "subcategory":"Specialty",
            "type":"Retail Goods"
        }
    ],
    "sg:phone":"+1 954 726 3584",
    "sg:postcode":"33068",
    "sg:province":"FL",
    "sg:tags":[
        "spice"
    ],
    "wof:name":"Specialty Brands",
    "wof:placetype":"venue"
},
  "geometry": {"coordinates":[-80.228078,26.208362],"type":"Point"}
}