{
  "type": "Feature",
  "properties": {
    "addr:full":"40 Ocean Blvd Atlantic Beach FL 32233",
    "addr:housenumber":"40",
    "addr:postcode":"32233",
    "addr:street":"Ocean Blvd",
    "iso:country":"US",
    "sg:address":"40 Ocean Blvd",
    "sg:city":"Atlantic Beach",
    "sg:classifiers":[
        {
            "category":"Home & Garden",
            "subcategory":"Furniture",
            "type":"Retail Goods"
        }
    ],
    "sg:phone":"+1 904 242 4990",
    "sg:postcode":"32233",
    "sg:province":"FL",
    "wof:name":"Patina",
    "wof:placetype":"venue"
},
  "geometry": {"coordinates":[-81.39623400000001,30.324906],"type":"Point"}
}