{
  "type": "Feature",
  "properties": {
    "addr:full":"1431 N Federal Hwy Lake Worth FL 33460",
    "addr:housenumber":"1431",
    "addr:postcode":"33460",
    "addr:street":"N Federal Hwy",
    "iso:country":"US",
    "sg:address":"1431 N Federal Hwy",
    "sg:city":"Lake Worth",
    "sg:classifiers":[
        {
            "category":"Shopping",
            "subcategory":"Clothing, Apparel, & Fashions",
            "type":"Retail Goods"
        }
    ],
    "sg:phone":"+1 561 582 4141",
    "sg:postcode":"33460",
    "sg:province":"FL",
    "sg:tags":[
        "alteration"
    ],
    "wof:name":"Ann's Alterations",
    "wof:placetype":"venue"
},
  "geometry": {"coordinates":[-80.052204,26.633075],"type":"Point"}
}