{
  "type": "Feature",
  "properties": {
    "addr:full":"37846 Meridian Ave Dade City FL 33525",
    "addr:housenumber":"37846",
    "addr:postcode":"33525",
    "addr:street":"Meridian Ave",
    "iso:country":"US",
    "sg:address":"37846 Meridian Ave",
    "sg:city":"Dade City",
    "sg:classifiers":[
        {
            "category":"Shopping",
            "subcategory":"Used Merchandise",
            "type":"Retail Goods"
        }
    ],
    "sg:phone":"+1 352 567 7712",
    "sg:postcode":"33525",
    "sg:province":"FL",
    "sg:tags":[
        "antique",
        "gift"
    ],
    "wof:name":"Sugarcreek",
    "wof:placetype":"venue"
},
  "geometry": {"coordinates":[-82.189911,28.364524],"type":"Point"}
}