{
  "type": "Feature",
  "properties": {
    "addr:full":"641 Oakford Rd Sarasota FL 34240",
    "addr:housenumber":"641",
    "addr:postcode":"34240",
    "addr:street":"Oakford Rd",
    "iso:country":"US",
    "sg:address":"641 Oakford Rd",
    "sg:city":"Sarasota",
    "sg:classifiers":[
        {
            "category":"Building & Trades",
            "subcategory":"Construction",
            "type":"Services"
        }
    ],
    "sg:phone":"+1 941 378 9988",
    "sg:postcode":"34240",
    "sg:province":"FL",
    "sg:tags":[
        "concrete",
        "contractor"
    ],
    "wof:name":"Advanced Decking",
    "wof:placetype":"venue"
},
  "geometry": {"coordinates":[-82.302823,27.326523],"type":"Point"}
}