{
  "type": "Feature",
  "properties": {
    "iso:country":"US",
    "sg:address":"100 W Vine St",
    "sg:city":"Kissimmee",
    "sg:classifiers":[
        {
            "category":"Restaurant",
            "type":"Food & Drink"
        }
    ],
    "sg:menulink":"http://www.allmenus.com/fl/kissimmee/81276-papa-johns-pizza/menu/",
    "sg:phone":"+1 407 846 2211",
    "sg:postcode":"34741",
    "sg:province":"FL",
    "sg:tags":[
        "american",
        "pizza"
    ],
    "wof:name":"Papa John's Pizza",
    "wof:placetype":"venue"
},
  "geometry": {"coordinates":[-81.40475499999999,28.304393],"type":"Point"}
}