{
  "type": "Feature",
  "properties": {
    "iso:country":"US",
    "sg:address":"4811 NW 65th Ave",
    "sg:city":"Lauderhill",
    "sg:classifiers":[
        {
            "category":"Manufacturing",
            "subcategory":"Buildings",
            "type":"Manufacturing & Wholesale Goods"
        },
        {
            "category":"Building & Trades",
            "subcategory":"Construction",
            "type":"Services"
        },
        {
            "category":"Building & Trades",
            "subcategory":"Electrical",
            "type":"Services"
        }
    ],
    "sg:phone":"+1 954 741 9467",
    "sg:postcode":"33319",
    "sg:province":"FL",
    "sg:tags":[
        "home",
        "builder",
        "electrician",
        "contractor"
    ],
    "wof:name":"Abba Electric Construction Corp",
    "wof:placetype":"venue"
},
  "geometry": {"coordinates":[-80.236812,26.18495],"type":"Point"}
}