{
  "type": "Feature",
  "properties": {
    "iso:country":"US",
    "sg:address":"1821 Kim Acres Ln",
    "sg:city":"Dover",
    "sg:classifiers":[
        {
            "category":"Building & Trades",
            "subcategory":"Electrical",
            "type":"Services"
        }
    ],
    "sg:phone":"+1 813 685 0263",
    "sg:postcode":"33527",
    "sg:province":"FL",
    "sg:tags":[
        "electric",
        "contractor"
    ],
    "wof:name":"Haseltine Electric",
    "wof:placetype":"venue"
},
  "geometry": {"coordinates":[-82.25719700000001,27.970125],"type":"Point"}
}