{
  "type": "Feature",
  "properties": {
    "iso:country":"US",
    "sg:address":"27601 Pullen Ave",
    "sg:city":"Bonita Springs",
    "sg:classifiers":[
        {
            "category":"Home & Garden",
            "subcategory":"Hardware",
            "type":"Retail Goods"
        }
    ],
    "sg:phone":"+1 239 992 8429",
    "sg:postcode":"34135",
    "sg:province":"FL",
    "wof:name":"Dan Handy",
    "wof:placetype":"venue"
},
  "geometry": {"coordinates":[-81.77562399999999,26.337704],"type":"Point"}
}