{
  "type": "Feature",
  "properties": {
    "addr:full":"1114 W Government St Pensacola FL 32501",
    "addr:housenumber":"1114",
    "addr:postcode":"32501",
    "addr:street":"W Government St",
    "iso:country":"US",
    "sg:address":"1114 W Government St",
    "sg:city":"Pensacola",
    "sg:classifiers":[
        {
            "category":"Shopping",
            "subcategory":"Crafts & Fabrics",
            "type":"Retail Goods"
        }
    ],
    "sg:phone":"+1 850 438 7608",
    "sg:postcode":"32501",
    "sg:province":"FL",
    "sg:tags":[
        "monogram"
    ],
    "wof:name":"Broadway's",
    "wof:placetype":"venue"
},
  "geometry": {"coordinates":[-87.230695,30.407524],"type":"Point"}
}