{
  "type": "Feature",
  "properties": {
    "addr:full":"10104 Searcy Ct Orlando FL 32817",
    "addr:housenumber":"10104",
    "addr:postcode":"32817",
    "addr:street":"Searcy Ct",
    "iso:country":"US",
    "sg:address":"10104 Searcy Ct",
    "sg:city":"Orlando",
    "sg:classifiers":[
        {
            "category":"Building & Trades",
            "subcategory":"Cleaning & Sanitation",
            "type":"Services"
        }
    ],
    "sg:phone":"+1 407 273 8014",
    "sg:postcode":"32817",
    "sg:province":"FL",
    "sg:tags":[
        "maintenance"
    ],
    "wof:name":"AC Solution Cleaning",
    "wof:placetype":"venue"
},
  "geometry": {"coordinates":[-81.242284,28.588561],"type":"Point"}
}