{
  "type": "Feature",
  "properties": {
    "iso:country":"US",
    "sg:address":"9350 NW 16th St",
    "sg:city":"Plantation",
    "sg:classifiers":[
        {
            "category":"Communications",
            "subcategory":"Film & Video Production",
            "type":"Services"
        }
    ],
    "sg:phone":"+1 954 472 2888",
    "sg:postcode":"33322",
    "sg:province":"FL",
    "sg:tags":[
        "taping"
    ],
    "wof:name":"Video Man",
    "wof:placetype":"venue"
},
  "geometry": {"coordinates":[-80.276207,26.14419],"type":"Point"}
}