{
  "type": "Feature",
  "properties": {
    "addr:full":"1141 S McCall Rd Englewood FL 34223",
    "addr:housenumber":"1141",
    "addr:postcode":"34223",
    "addr:street":"S Mccall Rd",
    "iso:country":"US",
    "sg:address":"1141 S McCall Rd",
    "sg:city":"Englewood",
    "sg:classifiers":[
        {
            "category":"Professional",
            "type":"Services"
        }
    ],
    "sg:phone":"+1 941 365 5178",
    "sg:postcode":"34223",
    "sg:province":"FL",
    "wof:name":"Wamac Inc",
    "wof:placetype":"venue"
},
  "geometry": {"coordinates":[-82.349869,26.942787],"type":"Point"}
}