{
  "type": "Feature",
  "properties": {
    "iso:country":"US",
    "sg:address":"3700 S US Hwy 1",
    "sg:city":"Fort Pierce",
    "sg:classifiers":[
        {
            "category":"Retail",
            "subcategory":"Repair Shop",
            "type":"Services"
        }
    ],
    "sg:phone":"+1 772 340 0029",
    "sg:postcode":"34982",
    "sg:province":"FL",
    "sg:tags":[
        "electrical"
    ],
    "wof:name":"Reagan John Appliance Ctr USA",
    "wof:placetype":"venue"
},
  "geometry": {"coordinates":[-80.325751,27.392662],"type":"Point"}
}