{
  "type": "Feature",
  "properties": {
    "addr:full":"855 S Highland Ave Clearwater FL 33756",
    "addr:housenumber":"855",
    "addr:postcode":"33756",
    "addr:street":"S Highland Ave",
    "iso:country":"US",
    "sg:address":"855 S Highland Ave",
    "sg:city":"Clearwater",
    "sg:classifiers":[
        {
            "category":"Social Services",
            "type":"Services"
        }
    ],
    "sg:phone":"+1 727 442 8150",
    "sg:postcode":"33756",
    "sg:province":"FL",
    "sg:tags":[
        "organization",
        "welfare"
    ],
    "wof:name":"Salvation Army Correctional",
    "wof:placetype":"venue"
},
  "geometry": {"coordinates":[-82.77513500000001,27.956701],"type":"Point"}
}