{
  "type": "Feature",
  "properties": {
    "addr:full":"1000 US Hwy 17 Bartow FL 33830",
    "addr:housenumber":"1000",
    "addr:postcode":"33830",
    "addr:street":"Us Hwy 17",
    "iso:country":"US",
    "sg:address":"1000 US Hwy 17",
    "sg:city":"Bartow",
    "sg:classifiers":[
        {
            "category":"Autos & Motor Vehicles",
            "subcategory":"Auto Supplies",
            "type":"Retail Goods"
        }
    ],
    "sg:phone":"+1 863 533 6559",
    "sg:postcode":"33830",
    "sg:province":"FL",
    "sg:tags":[
        "automobile",
        "parts"
    ],
    "sg:website":"www.autozone.com",
    "wof:name":"Autozone",
    "wof:placetype":"venue"
},
  "geometry": {"coordinates":[-81.83022699999999,27.903397],"type":"Point"}
}