{
  "type": "Feature",
  "properties": {
    "addr:full":"1022 W State Road 436 Ste 1008 Altamonte Springs FL 32714",
    "addr:housenumber":"1022",
    "addr:postcode":"32714",
    "addr:street":"W State Road 436 Ste 1008",
    "iso:country":"US",
    "sg:address":"1022 W State Road 436 Ste 1008",
    "sg:city":"Altamonte Springs",
    "sg:classifiers":[
        {
            "category":"Health Services",
            "subcategory":"Dentist",
            "type":"Services"
        }
    ],
    "sg:phone":"+1 407 774 6622",
    "sg:postcode":"32714",
    "sg:province":"FL",
    "sg:website":"www.altamontespringsfamilydentis...",
    "wof:name":"Lakeside Family Dentistry",
    "wof:placetype":"venue"
},
  "geometry": {"coordinates":[-81.424712,28.665229],"type":"Point"}
}