{
  "type": "Feature",
  "properties": {
    "iso:country":"US",
    "sg:address":"5636 3rd Ave",
    "sg:city":"Key West",
    "sg:classifiers":[
        {
            "category":"Food & Beverages",
            "subcategory":"Groceries & Convenience Stores",
            "type":"Retail Goods"
        }
    ],
    "sg:phone":"+1 305 292 2949",
    "sg:postcode":"33040",
    "sg:province":"FL",
    "sg:tags":[
        "market"
    ],
    "wof:name":"Tropical Food Market",
    "wof:placetype":"venue"
},
  "geometry": {"coordinates":[-81.740273,24.569692],"type":"Point"}
}