{
  "type": "Feature",
  "properties": {
    "addr:full":"3190 S State Road 7 Ste 16 Miramar FL 33023",
    "addr:housenumber":"3190",
    "addr:postcode":"33023",
    "addr:street":"S State Road 7 Ste 16",
    "iso:country":"US",
    "sg:address":"3190 S State Road 7 Ste 16",
    "sg:city":"Miramar",
    "sg:classifiers":[
        {
            "category":"Home & Garden",
            "subcategory":"Household Appliances",
            "type":"Retail Goods"
        }
    ],
    "sg:phone":"+1 954 962 0450",
    "sg:postcode":"33023",
    "sg:province":"FL",
    "sg:tags":[
        "equipment",
        "purifying",
        "cleaning",
        "air"
    ],
    "sg:website":"http://www.pure-air.com",
    "wof:name":"Air Purifying Systems Inc",
    "wof:placetype":"venue"
},
  "geometry": {"coordinates":[-80.206543,25.981993],"type":"Point"}
}