{
  "type": "Feature",
  "properties": {
    "addr:full":"639 Arrow Ln Kissimmee FL 34746",
    "addr:housenumber":"639",
    "addr:postcode":"34746",
    "addr:street":"Arrow Ln",
    "iso:country":"US",
    "sg:address":"639 Arrow Ln",
    "sg:city":"Kissimmee",
    "sg:classifiers":[
        {
            "category":"Building & Trades",
            "subcategory":"Construction",
            "type":"Services"
        }
    ],
    "sg:phone":"+1 407 390 7200",
    "sg:postcode":"34746",
    "sg:province":"FL",
    "sg:tags":[
        "house"
    ],
    "wof:name":"Leangelos Renovation",
    "wof:placetype":"venue"
},
  "geometry": {"coordinates":[-81.49753699999999,28.320853],"type":"Point"}
}