{
  "type": "Feature",
  "properties": {
    "addr:full":"12450 S Orange Blossom Trl Orlando FL 32837",
    "addr:housenumber":"12450",
    "addr:postcode":"32837",
    "addr:street":"S Orange Blossom Trl",
    "iso:country":"US",
    "sg:address":"12450 S Orange Blossom Trl",
    "sg:city":"Orlando",
    "sg:classifiers":[
        {
            "category":"Shopping",
            "subcategory":"Musical Instruments",
            "type":"Retail Goods"
        }
    ],
    "sg:phone":"+1 407 251 6659",
    "sg:postcode":"32837",
    "sg:province":"FL",
    "wof:name":"Guitar Center",
    "wof:placetype":"venue"
},
  "geometry": {"coordinates":[-81.404622,28.3834],"type":"Point"}
}