{
  "type": "Feature",
  "properties": {
    "iso:country":"US",
    "sg:address":"1062 N State Hwy 19",
    "sg:city":"Palatka",
    "sg:classifiers":[
        {
            "category":"Personal",
            "type":"Services"
        }
    ],
    "sg:phone":"+1 386 329 5576",
    "sg:postcode":"32177",
    "sg:province":"FL",
    "wof:name":"Body Mechanics Therapy",
    "wof:placetype":"venue"
},
  "geometry": {"coordinates":[-81.70657199999999,29.617132],"type":"Point"}
}