{
  "type": "Feature",
  "properties": {
    "addr:full":"10595 SE 151st St Summerfield FL 34491",
    "addr:postcode":"10595;34491",
    "addr:street":"Se 151St St",
    "iso:country":"US",
    "sg:address":"10595 SE 151st St",
    "sg:city":"Summerfield",
    "sg:classifiers":[
        {
            "category":"Building & Trades",
            "subcategory":"Construction",
            "type":"Services"
        }
    ],
    "sg:phone":"+1 352 288 8499",
    "sg:postcode":"34491",
    "sg:province":"FL",
    "sg:tags":[
        "contractor"
    ],
    "wof:name":"William Spurrell Construction",
    "wof:placetype":"venue"
},
  "geometry": {"coordinates":[-81.976777,29.000299],"type":"Point"}
}