{
  "type": "Feature",
  "properties": {
    "addr:full":"6850 Pangola Dr Fort Myers FL 33905",
    "addr:housenumber":"6850",
    "addr:postcode":"33905",
    "addr:street":"Pangola Dr",
    "iso:country":"US",
    "sg:address":"6850 Pangola Dr",
    "sg:city":"Fort Myers",
    "sg:classifiers":[
        {
            "category":"Building & Trades",
            "subcategory":"Construction",
            "type":"Services"
        }
    ],
    "sg:phone":"+1 239 694 0384",
    "sg:postcode":"33905",
    "sg:province":"FL",
    "sg:tags":[
        "maintenance",
        "contractor"
    ],
    "wof:name":"Donald L Elwell Jr Maintenance",
    "wof:placetype":"venue"
},
  "geometry": {"coordinates":[-81.757684,26.653511],"type":"Point"}
}