{
  "type": "Feature",
  "properties": {
    "iso:country":"US",
    "sg:address":"5551 W Hallandale Beach Blvd",
    "sg:city":"Hollywood",
    "sg:classifiers":[
        {
            "category":"Banks & Credit Unions",
            "subcategory":"Bank",
            "type":"Services"
        }
    ],
    "sg:phone":"+1 954 983 8908",
    "sg:postcode":"33023",
    "sg:province":"FL",
    "sg:tags":[
        "machine",
        "teller",
        "automated"
    ],
    "wof:name":"Atm Machanie",
    "wof:placetype":"venue"
},
  "geometry": {"coordinates":[-80.197992,25.984281],"type":"Point"}
}