{
  "type": "Feature",
  "properties": {
    "addr:full":"4153 NW 132nd St Opa Locka FL 33054",
    "addr:housenumber":"4153",
    "addr:postcode":"33054",
    "addr:street":"Nw 132Nd St;Locka",
    "iso:country":"US",
    "sg:address":"4153 NW 132nd St",
    "sg:city":"Opa Locka",
    "sg:classifiers":[
        {
            "category":"Shopping",
            "subcategory":"Clothing, Apparel, & Fashions",
            "type":"Retail Goods"
        }
    ],
    "sg:phone":"+1 305 826 7312",
    "sg:postcode":"33054",
    "sg:province":"FL",
    "sg:tags":[
        "sportswear"
    ],
    "wof:name":"Caribbean Apparel Assoc",
    "wof:placetype":"venue"
},
  "geometry": {"coordinates":[-80.266558,25.893913],"type":"Point"}
}