{
  "type": "Feature",
  "properties": {
    "iso:country":"US",
    "sg:address":"250 N Orange Ave",
    "sg:city":"Orlando",
    "sg:classifiers":[
        {
            "category":"Professional",
            "subcategory":"Lawyer & Legal Services",
            "type":"Services"
        }
    ],
    "sg:phone":"+1 407 843 3464",
    "sg:postcode":"32801",
    "sg:province":"FL",
    "wof:name":"Namey John F",
    "wof:placetype":"venue"
},
  "geometry": {"coordinates":[-81.37916300000001,28.545132],"type":"Point"}
}