{
  "type": "Feature",
  "properties": {
    "iso:country":"US",
    "sg:address":"36524 Jackson Ave",
    "sg:city":"Dade City",
    "sg:classifiers":[
        {
            "category":"Shopping",
            "type":"Retail Goods"
        }
    ],
    "sg:phone":"+1 352 458 0116",
    "sg:postcode":"33525",
    "sg:province":"FL",
    "sg:tags":[
        "merchandise"
    ],
    "wof:name":"Simplicity Shoppe",
    "wof:placetype":"venue"
},
  "geometry": {"coordinates":[-82.211079,28.353701],"type":"Point"}
}