{
  "type": "Feature",
  "properties": {
    "addr:full":"5925 Rodman St Hollywood FL 33023",
    "addr:housenumber":"5925",
    "addr:postcode":"33023",
    "addr:street":"Rodman St",
    "iso:country":"US",
    "sg:address":"5925 Rodman St",
    "sg:city":"Hollywood",
    "sg:classifiers":[
        {
            "category":"Wholesale",
            "subcategory":"Sporting Goods",
            "type":"Manufacturing & Wholesale Goods"
        }
    ],
    "sg:phone":"+1 954 961 3005",
    "sg:postcode":"33023",
    "sg:province":"FL",
    "wof:name":"Dorphil Inc",
    "wof:placetype":"venue"
},
  "geometry": {"coordinates":[-80.204808,25.999763],"type":"Point"}
}