{
  "type": "Feature",
  "properties": {
    "iso:country":"US",
    "sg:address":"5245 Ramsey Way",
    "sg:city":"Fort Myers",
    "sg:classifiers":[
        {
            "category":"Shopping",
            "subcategory":"Florist",
            "type":"Retail Goods"
        },
        {
            "category":"Personal",
            "type":"Services"
        }
    ],
    "sg:phone":"+1 239 939 7765",
    "sg:postcode":"33907",
    "sg:province":"FL",
    "wof:name":"Planned Perfection Inc",
    "wof:placetype":"venue"
},
  "geometry": {"coordinates":[-81.873823,26.583621],"type":"Point"}
}