{
  "type": "Feature",
  "properties": {
    "iso:country":"US",
    "sg:address":"8024 Macdougall Dr E",
    "sg:city":"Jacksonville",
    "sg:classifiers":[
        {
            "category":"Science Facility",
            "type":"Public Place"
        }
    ],
    "sg:phone":"+1 904 705 7189",
    "sg:postcode":"32244",
    "sg:province":"FL",
    "sg:tags":[
        "development",
        "laboratories-research"
    ],
    "wof:name":"Po-Writers",
    "wof:placetype":"venue"
},
  "geometry": {"coordinates":[-81.7734,30.201041],"type":"Point"}
}