{
  "type": "Feature",
  "properties": {
    "addr:full":"21760 Club Villa Ter Boca Raton FL 33433",
    "addr:housenumber":"21760",
    "addr:postcode":"33433",
    "addr:street":"Club Villa Ter",
    "iso:country":"US",
    "sg:address":"21760 Club Villa Ter",
    "sg:city":"Boca Raton",
    "sg:classifiers":[
        {
            "category":"Arts & Performance",
            "subcategory":"Theater",
            "type":"Entertainment"
        }
    ],
    "sg:phone":"+1 561 362 0031",
    "sg:postcode":"33433",
    "sg:province":"FL",
    "sg:tags":[
        "theatrical"
    ],
    "wof:name":"Tempo Music Inc",
    "wof:placetype":"venue"
},
  "geometry": {"coordinates":[-80.136127,26.352947],"type":"Point"}
}