{
  "type": "Feature",
  "properties": {
    "addr:full":"1242 N Harbor Dr West Palm Beach FL 33404",
    "addr:housenumber":"1242",
    "addr:postcode":"33404",
    "addr:street":"N Harbor Dr",
    "iso:country":"US",
    "sg:address":"1242 N Harbor Dr",
    "sg:city":"West Palm Beach",
    "sg:classifiers":[
        {
            "category":"Professional",
            "subcategory":"Employment Agencies",
            "type":"Services"
        }
    ],
    "sg:phone":"+1 561 842 2091",
    "sg:postcode":"33404",
    "sg:province":"FL",
    "sg:tags":[
        "help",
        "supply"
    ],
    "wof:name":"ABC Staffing Services",
    "wof:placetype":"venue"
},
  "geometry": {"coordinates":[-80.035703,26.787348],"type":"Point"}
}