{
  "type": "Feature",
  "properties": {
    "addr:full":"4084 Arnold Ave Naples FL 34104",
    "addr:housenumber":"4084",
    "addr:postcode":"34104",
    "addr:street":"Arnold Ave",
    "iso:country":"US",
    "sg:address":"4084 Arnold Ave",
    "sg:city":"Naples",
    "sg:classifiers":[
        {
            "category":"Building & Trades",
            "subcategory":"Plumbing",
            "type":"Services"
        }
    ],
    "sg:phone":"+1 239 643 5111",
    "sg:postcode":"34104",
    "sg:province":"FL",
    "sg:tags":[
        "conditioning",
        "air",
        "system",
        "contractor"
    ],
    "wof:name":"Superb Heating & Air Cond",
    "wof:placetype":"venue"
},
  "geometry": {"coordinates":[-81.76459699999999,26.167064],"type":"Point"}
}