{
  "type": "Feature",
  "properties": {
    "addr:full":"16017 Harbour Palms Dr Fort Myers FL 33908",
    "addr:housenumber":"16017",
    "addr:postcode":"33908",
    "addr:street":"Harbour Palms Dr",
    "iso:country":"US",
    "sg:address":"16017 Harbour Palms Dr",
    "sg:city":"Fort Myers",
    "sg:classifiers":[
        {
            "category":"Building & Trades",
            "subcategory":"Construction",
            "type":"Services"
        }
    ],
    "sg:phone":"+1 239 671 7355",
    "sg:postcode":"33908",
    "sg:province":"FL",
    "sg:tags":[
        "maintenance",
        "contractor"
    ],
    "wof:name":"Chris Mouyos Maintenance & Rpr",
    "wof:placetype":"venue"
},
  "geometry": {"coordinates":[-81.977386,26.507685],"type":"Point"}
}