{
  "type": "Feature",
  "properties": {
    "iso:country":"US",
    "sg:address":"86 NE 1st Ave",
    "sg:city":"Webster",
    "sg:classifiers":[
        {
            "category":"Shopping",
            "subcategory":"Music",
            "type":"Retail Goods"
        }
    ],
    "sg:phone":"+1 352 793 9454",
    "sg:postcode":"33597",
    "sg:province":"FL",
    "sg:tags":[
        "video",
        "disc",
        "tape",
        "cassette"
    ],
    "wof:name":"Video Store Of Webster",
    "wof:placetype":"venue"
},
  "geometry": {"coordinates":[-82.053742,28.610235],"type":"Point"}
}