{
  "type": "Feature",
  "properties": {
    "iso:country":"US",
    "sg:address":"4550 Oak Haven Dr",
    "sg:city":"Orlando",
    "sg:classifiers":[
        {
            "category":"Shopping",
            "type":"Retail Goods"
        }
    ],
    "sg:phone":"+1 407 355 0326",
    "sg:postcode":"32839",
    "sg:province":"FL",
    "sg:tags":[
        "merchandise"
    ],
    "wof:name":"Discount Smokes",
    "wof:placetype":"venue"
},
  "geometry": {"coordinates":[-81.43459799999999,28.472919],"type":"Point"}
}