{
  "type": "Feature",
  "properties": {
    "addr:full":"465 N Alafaya Trl Orlando FL 32828",
    "addr:housenumber":"465",
    "addr:postcode":"32828",
    "addr:street":"N Alafaya Trl",
    "iso:country":"US",
    "sg:address":"465 N Alafaya Trl",
    "sg:city":"Orlando",
    "sg:classifiers":[
        {
            "category":"Personal",
            "subcategory":"Beauty Salon",
            "type":"Services"
        }
    ],
    "sg:phone":"+1 407 382 9432",
    "sg:postcode":"32828",
    "sg:province":"FL",
    "sg:tags":[
        "barber"
    ],
    "sg:website":"http://www.haircuttery.com/",
    "wof:name":"Hair Cuttery",
    "wof:placetype":"venue"
},
  "geometry": {"coordinates":[-81.204555,28.552046],"type":"Point"}
}