{
  "type": "Feature",
  "properties": {
    "addr:full":"127 1st Ave N Jacksonville Beach FL 32250",
    "addr:housenumber":"127",
    "addr:postcode":"32250",
    "addr:street":"1St Ave N",
    "iso:country":"US",
    "sg:address":"127 1st Ave N",
    "sg:city":"Jacksonville Beach",
    "sg:classifiers":[
        {
            "category":"Bars & Pubs",
            "type":"Food & Drink"
        }
    ],
    "sg:phone":"+1 904 249 3322",
    "sg:postcode":"32250",
    "sg:province":"FL",
    "sg:tags":[
        "lounge"
    ],
    "wof:name":"Campeche Bay Catina",
    "wof:placetype":"venue"
},
  "geometry": {"coordinates":[-81.390739,30.290318],"type":"Point"}
}