{
  "type": "Feature",
  "properties": {
    "addr:full":"1012 New York Ave St Cloud FL 34769",
    "addr:housenumber":"1012",
    "addr:postcode":"34769",
    "addr:street":"New York Ave",
    "iso:country":"US",
    "sg:address":"1012 New York Ave",
    "sg:city":"St Cloud",
    "sg:classifiers":[
        {
            "category":"Health Services",
            "subcategory":"Clinic",
            "type":"Services"
        }
    ],
    "sg:phone":"+1 407 891 8884",
    "sg:postcode":"34769",
    "sg:province":"FL",
    "sg:tags":[
        "home"
    ],
    "wof:name":"Comfort Keepers",
    "wof:placetype":"venue"
},
  "geometry": {"coordinates":[-81.283624,28.248844],"type":"Point"}
}