{
  "type": "Feature",
  "properties": {
    "iso:country":"US",
    "sg:address":"105 N Grove St",
    "sg:city":"Merritt Island",
    "sg:classifiers":[
        {
            "category":"Health Services",
            "subcategory":"Doctor",
            "type":"Services"
        },
        {
            "category":"Health Services",
            "subcategory":"Dentist",
            "type":"Services"
        }
    ],
    "sg:phone":"+1 321 459 1313",
    "sg:postcode":"32953",
    "sg:province":"FL",
    "sg:tags":[
        "surgeon",
        "oral",
        "orthodontist"
    ],
    "wof:name":"Barlow Jeffrey DDS",
    "wof:placetype":"venue"
},
  "geometry": {"coordinates":[-80.7024,28.3585],"type":"Point"}
}