{
  "type": "Feature",
  "properties": {
    "addr:full":"1085 Business Ln Naples FL 34110",
    "addr:housenumber":"1085",
    "addr:postcode":"34110",
    "addr:street":"Business Ln",
    "iso:country":"US",
    "sg:address":"1085 Business Ln",
    "sg:city":"Naples",
    "sg:classifiers":[
        {
            "category":"Real Estate",
            "subcategory":"Developer",
            "type":"Services"
        },
        {
            "category":"Building & Trades",
            "subcategory":"Construction",
            "type":"Services"
        }
    ],
    "sg:phone":"+1 239 592 7466",
    "sg:postcode":"34110",
    "sg:province":"FL",
    "sg:tags":[
        "house"
    ],
    "wof:name":"Damon Custom Structures Inc",
    "wof:placetype":"venue"
},
  "geometry": {"coordinates":[-81.792796,26.302892],"type":"Point"}
}