{
  "type": "Feature",
  "properties": {
    "addr:full":"1163 Royal Palm Beach Blvd West Palm Beach FL 33411",
    "addr:housenumber":"1163",
    "addr:postcode":"33411",
    "addr:street":"Royal Palm Beach Blvd",
    "iso:country":"US",
    "sg:address":"1163 Royal Palm Beach Blvd",
    "sg:city":"West Palm Beach",
    "sg:classifiers":[
        {
            "category":"Building & Trades",
            "subcategory":"Plumbing",
            "type":"Services"
        }
    ],
    "sg:phone":"+1 561 793 7682",
    "sg:postcode":"33411",
    "sg:province":"FL",
    "sg:tags":[
        "installation",
        "heating",
        "solar"
    ],
    "wof:name":"Sun-Tek Systems Inc",
    "wof:placetype":"venue"
},
  "geometry": {"coordinates":[-80.22904200000001,26.710558],"type":"Point"}
}