{
  "type": "Feature",
  "properties": {
    "addr:full":"2119 W 73rd St Hialeah FL 33016",
    "addr:housenumber":"2119",
    "addr:postcode":"33016",
    "addr:street":"W 73Rd St",
    "iso:country":"US",
    "sg:address":"2119 W 73rd St",
    "sg:city":"Hialeah",
    "sg:classifiers":[
        {
            "category":"Manufacturing",
            "subcategory":"Furniture",
            "type":"Manufacturing & Wholesale Goods"
        }
    ],
    "sg:phone":"+1 305 822 3999",
    "sg:postcode":"33016",
    "sg:province":"FL",
    "wof:name":"Allmica & Stone Furniture",
    "wof:placetype":"venue"
},
  "geometry": {"coordinates":[-80.32577999999999,25.887935],"type":"Point"}
}