{
  "type": "Feature",
  "properties": {
    "iso:country":"US",
    "sg:address":"5842 14th St W",
    "sg:city":"Bradenton",
    "sg:classifiers":[
        {
            "category":"Education",
            "subcategory":"Dance Studio",
            "type":"Public Place"
        }
    ],
    "sg:phone":"+1 941 753 1032",
    "sg:postcode":"34207",
    "sg:province":"FL",
    "sg:tags":[
        "instruction",
        "dancing"
    ],
    "wof:name":"Sarabay Dance Club",
    "wof:placetype":"venue"
},
  "geometry": {"coordinates":[-82.575519,27.437698],"type":"Point"}
}