{
  "type": "Feature",
  "properties": {
    "addr:full":"7305 NW 61st St Miami FL 33166",
    "addr:housenumber":"7305",
    "addr:postcode":"33166",
    "addr:street":"Nw 61St St",
    "iso:country":"US",
    "sg:address":"7305 NW 61st St",
    "sg:city":"Miami",
    "sg:classifiers":[
        {
            "category":"Retail",
            "subcategory":"Repair Shop",
            "type":"Services"
        }
    ],
    "sg:phone":"+1 305 863 3211",
    "sg:postcode":"33166",
    "sg:province":"FL",
    "sg:tags":[
        "refinishing",
        "furniture"
    ],
    "wof:name":"Fernando's Funiture",
    "wof:placetype":"venue"
},
  "geometry": {"coordinates":[-80.315926,25.828999],"type":"Point"}
}