{
  "type": "Feature",
  "properties": {
    "iso:country":"US",
    "sg:address":"1600 N Hercules Ave",
    "sg:city":"Clearwater",
    "sg:classifiers":[
        {
            "category":"Wholesale",
            "subcategory":"Chemicals & Plastics",
            "type":"Manufacturing & Wholesale Goods"
        }
    ],
    "sg:phone":"+1 727 443 3843",
    "sg:postcode":"33765",
    "sg:province":"FL",
    "sg:tags":[
        "product",
        "paper"
    ],
    "wof:name":"Advantage Service & Products",
    "wof:placetype":"venue"
},
  "geometry": {"coordinates":[-82.754694,27.980607],"type":"Point"}
}