{
  "type": "Feature",
  "properties": {
    "iso:country":"US",
    "sg:address":"5242 Sunset Way S",
    "sg:city":"Lakeland",
    "sg:classifiers":[
        {
            "category":"Building & Trades",
            "subcategory":"Construction",
            "type":"Services"
        }
    ],
    "sg:phone":"+1 863 944 0375",
    "sg:postcode":"33805",
    "sg:province":"FL",
    "sg:tags":[
        "contractor",
        "mason"
    ],
    "wof:name":"Rod Lineberger Masonry",
    "wof:placetype":"venue"
},
  "geometry": {"coordinates":[-81.92805799999999,28.109643],"type":"Point"}
}