{
  "type": "Feature",
  "properties": {
    "iso:country":"US",
    "sg:address":"6889 Jackman Blvd",
    "sg:city":"Winter Park",
    "sg:classifiers":[
        {
            "category":"Building & Trades",
            "subcategory":"Construction",
            "type":"Services"
        }
    ],
    "sg:phone":"+1 407 679 5946",
    "sg:postcode":"32792",
    "sg:province":"FL",
    "sg:tags":[
        "hanging",
        "contractor"
    ],
    "wof:name":"Bryan Blake",
    "wof:placetype":"venue"
},
  "geometry": {"coordinates":[-81.298872,28.620686],"type":"Point"}
}