{
  "type": "Feature",
  "properties": {
    "addr:full":"400 Celebration Pl Kissimmee FL 34747",
    "addr:housenumber":"400",
    "addr:postcode":"34747",
    "addr:street":"Celebration Pl",
    "iso:country":"US",
    "sg:address":"400 Celebration Pl",
    "sg:city":"Kissimmee",
    "sg:classifiers":[
        {
            "category":"Health Services",
            "subcategory":"Hospital",
            "type":"Services"
        }
    ],
    "sg:phone":"+1 407 303 4000",
    "sg:postcode":"34747",
    "sg:province":"FL",
    "wof:name":"Celebration Health",
    "wof:placetype":"venue"
},
  "geometry": {"coordinates":[-81.538399,28.3297],"type":"Point"}
}