{
  "type": "Feature",
  "properties": {
    "addr:full":"3007 de Soto Blvd Miami FL 33134",
    "addr:housenumber":"3007",
    "addr:postcode":"33134",
    "addr:street":"De Soto Blvd",
    "iso:country":"US",
    "sg:address":"3007 de Soto Blvd",
    "sg:city":"Miami",
    "sg:classifiers":[
        {
            "category":"Wholesale",
            "subcategory":"Non-durable Goods",
            "type":"Manufacturing & Wholesale Goods"
        }
    ],
    "sg:phone":"+1 305 448 7841",
    "sg:postcode":"33134",
    "sg:province":"FL",
    "wof:name":"Pegi Trading LLC",
    "wof:placetype":"venue"
},
  "geometry": {"coordinates":[-80.278165,25.742453],"type":"Point"}
}