{
  "type": "Feature",
  "properties": {
    "iso:country":"US",
    "sg:address":"5512 Monterrey Rd",
    "sg:city":"Crestview",
    "sg:classifiers":[
        {
            "category":"Building & Trades",
            "subcategory":"Construction",
            "type":"Services"
        }
    ],
    "sg:phone":"+1 850 683 0815",
    "sg:postcode":"32539",
    "sg:province":"FL",
    "sg:tags":[
        "contractor"
    ],
    "wof:name":"Toolan Development Inc",
    "wof:placetype":"venue"
},
  "geometry": {"coordinates":[-86.540823,30.775225],"type":"Point"}
}