{
  "type": "Feature",
  "properties": {
    "iso:country":"US",
    "sg:address":"142 Kingsley Ave",
    "sg:city":"Orange Park",
    "sg:classifiers":[
        {
            "category":"Organizations",
            "subcategory":"Non-profit Organization",
            "type":"Services"
        }
    ],
    "sg:phone":"+1 904 215 3150",
    "sg:postcode":"32073",
    "sg:province":"FL",
    "wof:name":"Waste Not Want Not",
    "wof:placetype":"venue"
},
  "geometry": {"coordinates":[-81.69853999999999,30.165839],"type":"Point"}
}