{
  "type": "Feature",
  "properties": {
    "addr:full":"1066 Bayshore Rd Gulf Breeze FL 32563",
    "addr:housenumber":"1066",
    "addr:postcode":"32563",
    "addr:street":"Bayshore Rd",
    "iso:country":"US",
    "sg:address":"1066 Bayshore Rd",
    "sg:city":"Gulf Breeze",
    "sg:classifiers":[
        {
            "category":"Building & Trades",
            "subcategory":"Plumbing",
            "type":"Services"
        }
    ],
    "sg:phone":"+1 850 932 2755",
    "sg:postcode":"32563",
    "sg:province":"FL",
    "sg:tags":[
        "plumbing",
        "contractor"
    ],
    "wof:name":"Hodges Plumbing",
    "wof:placetype":"venue"
},
  "geometry": {"coordinates":[-87.119899,30.378352],"type":"Point"}
}