{
  "type": "Feature",
  "properties": {
    "addr:full":"1721 SE 16th Ave Ocala FL 34471",
    "addr:housenumber":"1721",
    "addr:postcode":"34471",
    "addr:street":"Se 16Th Ave",
    "iso:country":"US",
    "sg:address":"1721 SE 16th Ave",
    "sg:city":"Ocala",
    "sg:classifiers":[
        {
            "category":"Insurance",
            "subcategory":"Insurance Agent",
            "type":"Services"
        },
        {
            "category":"Insurance",
            "subcategory":"Hazard Insurance",
            "type":"Services"
        },
        {
            "category":"Insurance",
            "subcategory":"Title Insurance",
            "type":"Services"
        },
        {
            "category":"Insurance",
            "subcategory":"Life Insurance",
            "type":"Services"
        }
    ],
    "sg:phone":"+1 352 732 9632",
    "sg:postcode":"34471",
    "sg:province":"FL",
    "sg:tags":[
        "business",
        "auto",
        "commercial",
        "homeowner",
        "motorcycle",
        "renter"
    ],
    "wof:name":"Allstate Insurance Company - Drew Ditty",
    "wof:placetype":"venue"
},
  "geometry": {"coordinates":[-82.116547,29.171293],"type":"Point"}
}