{
  "type": "Feature",
  "properties": {
    "addr:full":"4625 Cleveland Heights Blvd Lakeland FL 33813",
    "addr:housenumber":"4625",
    "addr:postcode":"33813",
    "addr:street":"Cleveland Heights Blvd",
    "iso:country":"US",
    "sg:address":"4625 Cleveland Heights Blvd",
    "sg:city":"Lakeland",
    "sg:classifiers":[
        {
            "category":"Organizations",
            "subcategory":"Religious Organization",
            "type":"Services"
        }
    ],
    "sg:phone":"+1 863 646 3318",
    "sg:postcode":"33813",
    "sg:province":"FL",
    "sg:tags":[
        "church"
    ],
    "sg:website":"www.fellowshipbc-lakeland.org",
    "wof:name":"Fellowship Baptist Church",
    "wof:placetype":"venue"
},
  "geometry": {"coordinates":[-81.94866,27.980942],"type":"Point"}
}