{
  "type": "Feature",
  "properties": {
    "iso:country":"US",
    "sg:address":"7502 E Broadway Ave",
    "sg:city":"Tampa",
    "sg:classifiers":[
        {
            "category":"Manufacturing",
            "subcategory":"Pottery",
            "type":"Manufacturing & Wholesale Goods"
        }
    ],
    "sg:phone":"+1 813 621 5862",
    "sg:postcode":"33619",
    "sg:province":"FL",
    "sg:tags":[
        "equipment",
        "chinaware",
        "supply"
    ],
    "wof:name":"True Discount Restaurant Sup",
    "wof:placetype":"venue"
},
  "geometry": {"coordinates":[-82.370942,27.96683],"type":"Point"}
}