{
  "type": "Feature",
  "properties": {
    "addr:full":"900 Linton Blvd Delray Beach FL 33444",
    "addr:housenumber":"900",
    "addr:postcode":"33444",
    "addr:street":"Linton Blvd",
    "iso:country":"US",
    "sg:address":"900 Linton Blvd",
    "sg:city":"Delray Beach",
    "sg:classifiers":[
        {
            "category":"Banks & Credit Unions",
            "subcategory":"Bank",
            "type":"Services"
        }
    ],
    "sg:phone":"+1 561 243 6000",
    "sg:postcode":"33444",
    "sg:province":"FL",
    "sg:tags":[
        "state",
        "commercial"
    ],
    "wof:name":"Wachovia Bank National Assn",
    "wof:placetype":"venue"
},
  "geometry": {"coordinates":[-80.082229,26.43961],"type":"Point"}
}