{
  "type": "Feature",
  "properties": {
    "addr:full":"2395 N Courtenay Pkwy Merritt Island FL 32953",
    "addr:housenumber":"2395",
    "addr:postcode":"32953",
    "addr:street":"N Courtenay Pkwy",
    "iso:country":"US",
    "sg:address":"2395 N Courtenay Pkwy",
    "sg:city":"Merritt Island",
    "sg:classifiers":[
        {
            "category":"Banks & Credit Unions",
            "subcategory":"Investment Brokerage",
            "type":"Services"
        }
    ],
    "sg:phone":"+1 321 452 0061",
    "sg:postcode":"32953",
    "sg:province":"FL",
    "sg:tags":[
        "consultant",
        "planning",
        "financial"
    ],
    "wof:name":"Raymond James Financial Svc",
    "wof:placetype":"venue"
},
  "geometry": {"coordinates":[-80.70483900000001,28.398064],"type":"Point"}
}