{
  "type": "Feature",
  "properties": {
    "addr:full":"1503 Poinsettia Ave Tampa FL 33612",
    "addr:housenumber":"1503",
    "addr:postcode":"33612",
    "addr:street":"Poinsettia Ave",
    "iso:country":"US",
    "sg:address":"1503 Poinsettia Ave",
    "sg:city":"Tampa",
    "sg:classifiers":[
        {
            "category":"Building & Trades",
            "subcategory":"Landscaping Services",
            "type":"Services"
        }
    ],
    "sg:phone":"+1 813 975 9691",
    "sg:postcode":"33612",
    "sg:province":"FL",
    "sg:tags":[
        "landscape",
        "contractor"
    ],
    "wof:name":"Abraham Cortes Lwn Maintenance",
    "wof:placetype":"venue"
},
  "geometry": {"coordinates":[-82.44154399999999,28.041667],"type":"Point"}
}