{
  "type": "Feature",
  "properties": {
    "addr:full":"3351 Fowler St Fort Myers FL 33901",
    "addr:housenumber":"3351",
    "addr:postcode":"33901",
    "addr:street":"Fowler St",
    "iso:country":"US",
    "sg:address":"3351 Fowler St",
    "sg:city":"Fort Myers",
    "sg:classifiers":[
        {
            "category":"Restaurant",
            "type":"Food & Drink"
        }
    ],
    "sg:phone":"+1 239 936 6100",
    "sg:postcode":"33901",
    "sg:province":"FL",
    "sg:tags":[
        "eating"
    ],
    "wof:name":"Sub or Sandwich",
    "wof:placetype":"venue"
},
  "geometry": {"coordinates":[-81.86187099999999,26.616109],"type":"Point"}
}