{
  "type": "Feature",
  "properties": {
    "addr:full":"2401 Citrus Blvd Haines City FL 33844",
    "addr:housenumber":"2401",
    "addr:postcode":"33844",
    "addr:street":"Citrus Blvd",
    "iso:country":"US",
    "sg:address":"2401 Citrus Blvd",
    "sg:city":"Haines City",
    "sg:classifiers":[
        {
            "category":"Manufacturing",
            "subcategory":"Food",
            "type":"Manufacturing & Wholesale Goods"
        }
    ],
    "sg:phone":"+1 863 967 5424",
    "sg:postcode":"33844",
    "sg:province":"FL",
    "sg:tags":[
        "desert",
        "ice",
        "mfg"
    ],
    "wof:name":"Courtside Delights",
    "wof:placetype":"venue"
},
  "geometry": {"coordinates":[-81.610536,28.117673],"type":"Point"}
}