{
  "type": "Feature",
  "properties": {
    "addr:full":"5767 157th Ave N Clearwater FL 33760",
    "addr:housenumber":"5767",
    "addr:postcode":"33760",
    "addr:street":"157Th Ave N",
    "iso:country":"US",
    "sg:address":"5767 157th Ave N",
    "sg:city":"Clearwater",
    "sg:classifiers":[
        {
            "category":"Home & Garden",
            "subcategory":"Building Materials",
            "type":"Retail Goods"
        }
    ],
    "sg:phone":"+1 727 507 0002",
    "sg:postcode":"33760",
    "sg:province":"FL",
    "sg:tags":[
        "glass"
    ],
    "wof:name":"Glass Pros",
    "wof:placetype":"venue"
},
  "geometry": {"coordinates":[-82.71322600000001,27.915309],"type":"Point"}
}