{
  "type": "Feature",
  "properties": {
    "iso:country":"US",
    "sg:address":"103 Cortez Cir W",
    "sg:city":"Pompano Beach",
    "sg:classifiers":[
        {
            "category":"Retail",
            "subcategory":"Repair Shop",
            "type":"Services"
        }
    ],
    "sg:phone":"+1 954 970 7302",
    "sg:postcode":"33068",
    "sg:province":"FL",
    "wof:name":"AAA Rooter Services Inc",
    "wof:placetype":"venue"
},
  "geometry": {"coordinates":[-80.19483700000001,26.227177],"type":"Point"}
}