{
  "type": "Feature",
  "properties": {
    "iso:country":"US",
    "sg:address":"292 N Spring St",
    "sg:city":"Crestview",
    "sg:classifiers":[
        {
            "category":"Real Estate",
            "subcategory":"Real Estate Services",
            "type":"Services"
        }
    ],
    "sg:phone":"+1 850 683 1923",
    "sg:postcode":"32536",
    "sg:province":"FL",
    "sg:tags":[
        "company",
        "title"
    ],
    "wof:name":"Accu Title Agency",
    "wof:placetype":"venue"
},
  "geometry": {"coordinates":[-86.572039,30.757345],"type":"Point"}
}