{
  "type": "Feature",
  "properties": {
    "addr:full":"105 Coastline Rd Sanford FL 32771",
    "addr:housenumber":"105",
    "addr:postcode":"32771",
    "addr:street":"Coastline Rd",
    "iso:country":"US",
    "sg:address":"105 Coastline Rd",
    "sg:city":"Sanford",
    "sg:classifiers":[
        {
            "category":"Professional",
            "subcategory":"Engineering",
            "type":"Services"
        }
    ],
    "sg:phone":"+1 407 330 7763",
    "sg:postcode":"32771",
    "sg:province":"FL",
    "sg:tags":[
        "engineer"
    ],
    "wof:name":"Andreyev Engineering Inc",
    "wof:placetype":"venue"
},
  "geometry": {"coordinates":[-81.322682,28.803856],"type":"Point"}
}