{
  "type": "Feature",
  "properties": {
    "addr:full":"1704 23rd St Sarasota FL 34234",
    "addr:housenumber":"1704",
    "addr:postcode":"34234",
    "addr:street":"23Rd St",
    "iso:country":"US",
    "sg:address":"1704 23rd St",
    "sg:city":"Sarasota",
    "sg:classifiers":[
        {
            "category":"Building & Trades",
            "subcategory":"Landscaping Services",
            "type":"Services"
        }
    ],
    "sg:phone":"+1 941 951 1266",
    "sg:postcode":"34234",
    "sg:province":"FL",
    "wof:name":"Cambells Lawn Service",
    "wof:placetype":"venue"
},
  "geometry": {"coordinates":[-82.537205,27.35764],"type":"Point"}
}