{
  "type": "Feature",
  "properties": {
    "iso:country":"US",
    "sg:address":"409 SW 29th Ave",
    "sg:city":"Miami",
    "sg:classifiers":[
        {
            "category":"Retail",
            "subcategory":"Repair Shop",
            "type":"Services"
        }
    ],
    "sg:phone":"+1 305 649 6845",
    "sg:postcode":"33135",
    "sg:province":"FL",
    "sg:tags":[
        "physician",
        "surgeon",
        "refinishing",
        "equipment-repairing"
    ],
    "wof:name":"C & T Medical Equipment",
    "wof:placetype":"venue"
},
  "geometry": {"coordinates":[-80.24100900000001,25.768271],"type":"Point"}
}