{
  "type": "Feature",
  "properties": {
    "addr:full":"2308 Evenglow Ave Spring Hill FL 34609",
    "addr:housenumber":"2308",
    "addr:postcode":"34609",
    "addr:street":"Evenglow Ave",
    "iso:country":"US",
    "sg:address":"2308 Evenglow Ave",
    "sg:city":"Spring Hill",
    "sg:classifiers":[
        {
            "category":"Retail",
            "subcategory":"Funeral Services",
            "type":"Services"
        }
    ],
    "sg:phone":"+1 352 684 1421",
    "sg:postcode":"34609",
    "sg:province":"FL",
    "wof:name":"David Anthony Home Inspections",
    "wof:placetype":"venue"
},
  "geometry": {"coordinates":[-82.52194900000001,28.468441],"type":"Point"}
}