{
  "type": "Feature",
  "properties": {
    "addr:full":"8547 Merrimoor Blvd E Seminole FL 33777",
    "addr:housenumber":"8547",
    "addr:postcode":"33777",
    "addr:street":"Merrimoor Blvd E",
    "iso:country":"US",
    "sg:address":"8547 Merrimoor Blvd E",
    "sg:city":"Seminole",
    "sg:classifiers":[
        {
            "category":"Wholesale",
            "subcategory":"Medical Equipment & Supplies",
            "type":"Manufacturing & Wholesale Goods"
        }
    ],
    "sg:phone":"+1 727 420 7236",
    "sg:postcode":"33777",
    "sg:province":"FL",
    "sg:tags":[
        "instrument",
        "surgical"
    ],
    "wof:name":"Innovative Medical Technologie",
    "wof:placetype":"venue"
},
  "geometry": {"coordinates":[-82.749132,27.849811],"type":"Point"}
}