{
  "type": "Feature",
  "properties": {
    "addr:full":"4524 Gun Club Rd West Palm Beach FL 33415",
    "addr:housenumber":"4524",
    "addr:postcode":"33415",
    "addr:street":"Gun Club Rd",
    "iso:country":"US",
    "sg:address":"4524 Gun Club Rd",
    "sg:city":"West Palm Beach",
    "sg:classifiers":[
        {
            "category":"Wholesale",
            "subcategory":"Toys & Hobbies",
            "type":"Manufacturing & Wholesale Goods"
        }
    ],
    "sg:phone":"+1 561 718 2447",
    "sg:postcode":"33415",
    "sg:province":"FL",
    "wof:name":"Travel Palace Inc of USA",
    "wof:placetype":"venue"
},
  "geometry": {"coordinates":[-80.116412,26.673689],"type":"Point"}
}