{
  "type": "Feature",
  "properties": {
    "iso:country":"US",
    "sg:address":"1801 9th St W",
    "sg:city":"Bradenton",
    "sg:classifiers":[
        {
            "category":"Autos & Motor Vehicles",
            "subcategory":"Automobile Sales",
            "type":"Retail Goods"
        }
    ],
    "sg:phone":"+1 941 749 1000",
    "sg:postcode":"34205",
    "sg:province":"FL",
    "sg:tags":[
        "used"
    ],
    "wof:name":"First Auto Sales",
    "wof:placetype":"venue"
},
  "geometry": {"coordinates":[-82.57123300000001,27.48253],"type":"Point"}
}