{
  "type": "Feature",
  "properties": {
    "iso:country":"US",
    "sg:address":"6624 Breeze Way",
    "sg:city":"Orlando",
    "sg:classifiers":[
        {
            "category":"Building & Trades",
            "subcategory":"Construction",
            "type":"Services"
        }
    ],
    "sg:phone":"+1 407 277 4809",
    "sg:postcode":"32807",
    "sg:province":"FL",
    "sg:tags":[
        "contractor"
    ],
    "wof:name":"Todd Sherbondy Contractor",
    "wof:placetype":"venue"
},
  "geometry": {"coordinates":[-81.291541,28.540641],"type":"Point"}
}