{
  "type": "Feature",
  "properties": {
    "iso:country":"US",
    "sg:address":"9645 SE Highway 42",
    "sg:city":"Summerfield",
    "sg:classifiers":[
        {
            "category":"Building & Trades",
            "subcategory":"Construction",
            "type":"Services"
        }
    ],
    "sg:phone":"+1 352 245 2490",
    "sg:postcode":"34491",
    "sg:province":"FL",
    "sg:tags":[
        "contractor",
        "paving",
        "asphalt",
        "sealcoating"
    ],
    "wof:name":"Masterpiece Brick Paving",
    "wof:placetype":"venue"
},
  "geometry": {"coordinates":[-81.992994,28.982059],"type":"Point"}
}