{
  "type": "Feature",
  "properties": {
    "iso:country":"US",
    "sg:address":"3960 SW 8th St",
    "sg:city":"Coral Gables",
    "sg:classifiers":[
        {
            "category":"Building & Trades",
            "subcategory":"Locksmith",
            "type":"Services"
        }
    ],
    "sg:phone":"+1 305 423 3312",
    "sg:postcode":"33134",
    "sg:province":"FL",
    "sg:tags":[
        "key"
    ],
    "wof:name":"1 Alpha Lock and Key of Fl",
    "wof:placetype":"venue"
},
  "geometry": {"coordinates":[-80.26057,25.76438],"type":"Point"}
}