{
  "type": "Feature",
  "properties": {
    "iso:country":"US",
    "sg:address":"6275 Ember Ave",
    "sg:city":"Cocoa",
    "sg:classifiers":[
        {
            "category":"Building & Trades",
            "subcategory":"Construction",
            "type":"Services"
        }
    ],
    "sg:phone":"+1 321 863 9981",
    "sg:postcode":"32927",
    "sg:province":"FL",
    "sg:tags":[
        "grading",
        "contractor"
    ],
    "wof:name":"Teddy Back's Tractor Svc",
    "wof:placetype":"venue"
},
  "geometry": {"coordinates":[-80.810456,28.467944],"type":"Point"}
}