{
  "type": "Feature",
  "properties": {
    "addr:full":"760 NW 62nd St Miami FL 33150",
    "addr:housenumber":"760",
    "addr:postcode":"33150",
    "addr:street":"Nw 62Nd St",
    "iso:country":"US",
    "sg:address":"760 NW 62nd St",
    "sg:city":"Miami",
    "sg:classifiers":[
        {
            "category":"Government",
            "subcategory":"Post Office",
            "type":"Public Place"
        }
    ],
    "sg:phone":"+1 305 754 1329",
    "sg:postcode":"33150",
    "sg:province":"FL",
    "sg:tags":[
        "postal",
        "us"
    ],
    "wof:name":"Edison Center Station",
    "wof:placetype":"venue"
},
  "geometry": {"coordinates":[-80.209408,25.832166],"type":"Point"}
}