{
  "type": "Feature",
  "properties": {
    "addr:full":"1717 Collins Ave Miami Beach FL 33139",
    "addr:housenumber":"1717",
    "addr:postcode":"33139",
    "addr:street":"Collins Ave",
    "iso:country":"US",
    "sg:address":"1717 Collins Ave",
    "sg:city":"Miami Beach",
    "sg:classifiers":[
        {
            "category":"Restaurant",
            "type":"Food & Drink"
        }
    ],
    "sg:postcode":"33139",
    "sg:province":"FL",
    "wof:name":"Love Food Cafe",
    "wof:placetype":"venue"
},
  "geometry": {"coordinates":[-80.130045,25.790654],"type":"Point"}
}