{
  "type": "Feature",
  "properties": {
    "addr:full":"1111 E Amelia St Orlando FL 32803",
    "addr:housenumber":"1111",
    "addr:postcode":"32803",
    "addr:street":"E Amelia St",
    "iso:country":"US",
    "sg:address":"1111 E Amelia St",
    "sg:city":"Orlando",
    "sg:classifiers":[
        {
            "category":"Wholesale",
            "subcategory":"Medical Equipment & Supplies",
            "type":"Manufacturing & Wholesale Goods"
        }
    ],
    "sg:phone":"+1 407 316 0202",
    "sg:postcode":"32803",
    "sg:province":"FL",
    "sg:tags":[
        "representative"
    ],
    "wof:name":"United Sales Associates",
    "wof:placetype":"venue"
},
  "geometry": {"coordinates":[-81.365464,28.549526],"type":"Point"}
}