{
  "type": "Feature",
  "properties": {
    "iso:country":"US",
    "sg:address":"4768 N Citation Dr",
    "sg:city":"Delray Beach",
    "sg:classifiers":[
        {
            "category":"Shopping",
            "subcategory":"Jewelry",
            "type":"Retail Goods"
        }
    ],
    "sg:phone":"+1 561 865 9854",
    "sg:postcode":"33445",
    "sg:province":"FL",
    "wof:name":"Crysangelis Inc",
    "wof:placetype":"venue"
},
  "geometry": {"coordinates":[-80.11926099999999,26.43532],"type":"Point"}
}