{
  "type": "Feature",
  "properties": {
    "addr:full":"1711 N 50th St Tampa FL 33619",
    "addr:housenumber":"1711",
    "addr:postcode":"33619",
    "addr:street":"N 50Th St",
    "iso:country":"US",
    "sg:address":"1711 N 50th St",
    "sg:city":"Tampa",
    "sg:classifiers":[
        {
            "category":"Shopping",
            "subcategory":"Music",
            "type":"Retail Goods"
        }
    ],
    "sg:phone":"+1 813 241 2500",
    "sg:postcode":"33619",
    "sg:province":"FL",
    "sg:tags":[
        "video",
        "disc",
        "tape",
        "cassette"
    ],
    "wof:name":"Hott Flixxx",
    "wof:placetype":"venue"
},
  "geometry": {"coordinates":[-82.401775,27.961587],"type":"Point"}
}