{
  "type": "Feature",
  "properties": {
    "addr:full":"324 W Jefferson St Brooksville FL 34601",
    "addr:housenumber":"324",
    "addr:postcode":"34601",
    "addr:street":"W Jefferson St",
    "iso:country":"US",
    "sg:address":"324 W Jefferson St",
    "sg:city":"Brooksville",
    "sg:classifiers":[
        {
            "category":"Government",
            "subcategory":"Office",
            "type":"Public Place"
        }
    ],
    "sg:phone":"+1 352 754 6796",
    "sg:postcode":"34601",
    "sg:province":"FL",
    "sg:tags":[
        "state",
        "resource"
    ],
    "wof:name":"Unemployment Compensation",
    "wof:placetype":"venue"
},
  "geometry": {"coordinates":[-82.39081899999999,28.555656],"type":"Point"}
}