{
  "type": "Feature",
  "properties": {
    "addr:full":"4525 Del Prado Blvd S Cape Coral FL 33904",
    "addr:housenumber":"4525",
    "addr:postcode":"33904",
    "addr:street":"Del Prado Blvd S",
    "iso:country":"US",
    "sg:address":"4525 Del Prado Blvd S",
    "sg:city":"Cape Coral",
    "sg:classifiers":[
        {
            "category":"Arena",
            "subcategory":"Sports Club",
            "type":"Entertainment"
        }
    ],
    "sg:phone":"+1 239 541 9999",
    "sg:postcode":"33904",
    "sg:province":"FL",
    "sg:tags":[
        "martial art"
    ],
    "wof:name":"Karate Plus",
    "wof:placetype":"venue"
},
  "geometry": {"coordinates":[-81.943703,26.5672],"type":"Point"}
}