{
  "type": "Feature",
  "properties": {
    "addr:full":"3915 Holiday Dr Panama City FL 32408",
    "addr:housenumber":"3915",
    "addr:postcode":"32408",
    "addr:street":"Holiday Dr",
    "iso:country":"US",
    "sg:address":"3915 Holiday Dr",
    "sg:city":"Panama City",
    "sg:classifiers":[
        {
            "category":"Building & Trades",
            "subcategory":"Construction",
            "type":"Services"
        }
    ],
    "sg:phone":"+1 850 784 3688",
    "sg:postcode":"32408",
    "sg:province":"FL",
    "sg:tags":[
        "house"
    ],
    "wof:name":"Total Home Concepts",
    "wof:placetype":"venue"
},
  "geometry": {"coordinates":[-85.76969200000001,30.157518],"type":"Point"}
}