{
  "type": "Feature",
  "properties": {
    "iso:country":"US",
    "sg:address":"344 Cello Cir",
    "sg:city":"Winter Springs",
    "sg:classifiers":[
        {
            "category":"Shopping",
            "subcategory":"Computers & Home Electronics",
            "type":"Retail Goods"
        }
    ],
    "sg:phone":"+1 407 388 1687",
    "sg:postcode":"32708",
    "sg:province":"FL",
    "wof:name":"Mighty Eagle Computers",
    "wof:placetype":"venue"
},
  "geometry": {"coordinates":[-81.299887,28.689327],"type":"Point"}
}