{
  "type": "Feature",
  "properties": {
    "iso:country":"US",
    "sg:address":"11233 N Williams St",
    "sg:city":"Dunnellon",
    "sg:classifiers":[
        {
            "category":"Government",
            "subcategory":"Office",
            "type":"Public Place"
        }
    ],
    "sg:phone":"+1 352 489 4317",
    "sg:postcode":"34432",
    "sg:province":"FL",
    "sg:tags":[
        "transportation"
    ],
    "wof:name":"Marion County Tax Office",
    "wof:placetype":"venue"
},
  "geometry": {"coordinates":[-82.453846,29.062137],"type":"Point"}
}