{
  "type": "Feature",
  "properties": {
    "addr:full":"1302 N Krome Ave Homestead FL 33030",
    "addr:housenumber":"1302",
    "addr:postcode":"33030",
    "addr:street":"N Krome Ave",
    "iso:country":"US",
    "sg:address":"1302 N Krome Ave",
    "sg:city":"Homestead",
    "sg:classifiers":[
        {
            "category":"Retail",
            "subcategory":"Veterinary Services",
            "type":"Services"
        }
    ],
    "sg:phone":"+1 305 248 4400",
    "sg:postcode":"33030",
    "sg:province":"FL",
    "sg:tags":[
        "veterinarian"
    ],
    "wof:name":"Avocado Animal Clinic",
    "wof:placetype":"venue"
},
  "geometry": {"coordinates":[-80.477478,25.482639],"type":"Point"}
}