{
  "type": "Feature",
  "properties": {
    "iso:country":"US",
    "sg:address":"2830 Oakbrook Ln",
    "sg:city":"Fort Lauderdale",
    "sg:classifiers":[
        {
            "category":"Shopping",
            "subcategory":"Books",
            "type":"Retail Goods"
        }
    ],
    "sg:phone":"+1 954 385 6897",
    "sg:postcode":"33332",
    "sg:province":"FL",
    "wof:name":"Playful Learning",
    "wof:placetype":"venue"
},
  "geometry": {"coordinates":[-80.40225,26.08604],"type":"Point"}
}