{
  "type": "Feature",
  "properties": {
    "iso:country":"US",
    "sg:address":"2431 Bear Creek Dr",
    "sg:city":"Naples",
    "sg:classifiers":[
        {
            "category":"Building & Trades",
            "subcategory":"Construction",
            "type":"Services"
        }
    ],
    "sg:phone":"+1 239 566 3992",
    "sg:postcode":"34109",
    "sg:province":"FL",
    "sg:tags":[
        "hanging",
        "contractor"
    ],
    "wof:name":"Utterback Painting",
    "wof:placetype":"venue"
},
  "geometry": {"coordinates":[-81.76853,26.228847],"type":"Point"}
}