{
  "type": "Feature",
  "properties": {
    "iso:country":"US",
    "sg:address":"10632 Ave Santa Ana",
    "sg:city":"Boca Raton",
    "sg:classifiers":[
        {
            "category":"Autos & Motor Vehicles",
            "subcategory":"Automobile Sales",
            "type":"Retail Goods"
        }
    ],
    "sg:phone":"+1 561 451 8434",
    "sg:postcode":"33498",
    "sg:province":"FL",
    "sg:tags":[
        "used"
    ],
    "wof:name":"Evs Auto Sales Inc",
    "wof:placetype":"venue"
},
  "geometry": {"coordinates":[-80.213289,26.372127],"type":"Point"}
}