{
  "type": "Feature",
  "properties": {
    "addr:full":"11528 Perpetual Dr Odessa FL 33556",
    "addr:housenumber":"11528",
    "addr:postcode":"33556",
    "addr:street":"Perpetual Dr",
    "iso:country":"US",
    "sg:address":"11528 Perpetual Dr",
    "sg:city":"Odessa",
    "sg:classifiers":[
        {
            "category":"Autos & Motor Vehicles",
            "subcategory":"Automobile Sales",
            "type":"Retail Goods"
        }
    ],
    "sg:phone":"+1 727 376 9292",
    "sg:postcode":"33556",
    "sg:province":"FL",
    "sg:tags":[
        "aircraft"
    ],
    "wof:name":"Aircraft Systems Group",
    "wof:placetype":"venue"
},
  "geometry": {"coordinates":[-82.623946,28.197691],"type":"Point"}
}