{
  "type": "Feature",
  "properties": {
    "addr:full":"12989 Southern Blvd Ste 103 Loxahatchee FL 33470",
    "addr:housenumber":"12989",
    "addr:postcode":"33470",
    "addr:street":"Southern Blvd Ste 103",
    "iso:country":"US",
    "sg:address":"12989 Southern Blvd Ste 103",
    "sg:city":"Loxahatchee",
    "sg:classifiers":[
        {
            "category":"Health Services",
            "subcategory":"Doctor",
            "type":"Services"
        }
    ],
    "sg:phone":"+1 561 798 2800",
    "sg:postcode":"33470",
    "sg:province":"FL",
    "sg:tags":[
        "medicine",
        "physician",
        "practice",
        "surgeons",
        "family"
    ],
    "wof:name":"Jack I Newcomer Mdpa",
    "wof:placetype":"venue"
},
  "geometry": {"coordinates":[-80.24960299999999,26.681889],"type":"Point"}
}