{
  "type": "Feature",
  "properties": {
    "addr:full":"3452 Old Dixie Hwy Stuart FL 34994",
    "addr:housenumber":"3452",
    "addr:postcode":"34994",
    "addr:street":"Old Dixie Hwy",
    "iso:country":"US",
    "sg:address":"3452 Old Dixie Hwy",
    "sg:city":"Stuart",
    "sg:classifiers":[
        {
            "category":"Personal",
            "subcategory":"Beauty Salon",
            "type":"Services"
        }
    ],
    "sg:phone":"+1 772 223 7025",
    "sg:postcode":"34994",
    "sg:province":"FL",
    "sg:tags":[
        "shop"
    ],
    "wof:name":"Salon 3400",
    "wof:placetype":"venue"
},
  "geometry": {"coordinates":[-80.21607400000001,27.16214],"type":"Point"}
}