{
  "type": "Feature",
  "properties": {
    "addr:full":"930 Wekiva Springs Rd Longwood FL 32779",
    "addr:housenumber":"930",
    "addr:postcode":"32779",
    "addr:street":"Wekiva Springs Rd",
    "iso:country":"US",
    "sg:address":"930 Wekiva Springs Rd",
    "sg:city":"Longwood",
    "sg:classifiers":[
        {
            "category":"Retail",
            "subcategory":"Car Wash",
            "type":"Services"
        }
    ],
    "sg:phone":"+1 407 869 3226",
    "sg:postcode":"32779",
    "sg:province":"FL",
    "wof:name":"Elite Mobile Detailers",
    "wof:placetype":"venue"
},
  "geometry": {"coordinates":[-81.41767299999999,28.701216],"type":"Point"}
}