{
  "type": "Feature",
  "properties": {
    "addr:full":"4316 Gulf Breeze Pkwy Gulf Breeze FL 32563",
    "addr:housenumber":"4316",
    "addr:postcode":"32563",
    "addr:street":"Gulf Breeze Pkwy",
    "iso:country":"US",
    "sg:address":"4316 Gulf Breeze Pkwy",
    "sg:city":"Gulf Breeze",
    "sg:classifiers":[
        {
            "category":"Retail",
            "subcategory":"Repair Shop",
            "type":"Services"
        }
    ],
    "sg:phone":"+1 850 934 1510",
    "sg:postcode":"32563",
    "sg:province":"FL",
    "wof:name":"Runyans Boats & Motors Inc",
    "wof:placetype":"venue"
},
  "geometry": {"coordinates":[-87.040041,30.39379],"type":"Point"}
}