{
  "type": "Feature",
  "properties": {
    "iso:country":"US",
    "sg:address":"7168 SW 47th St",
    "sg:city":"Miami",
    "sg:classifiers":[
        {
            "category":"Professional",
            "subcategory":"Computer Services",
            "type":"Services"
        }
    ],
    "sg:phone":"+1 305 661 6764",
    "sg:postcode":"33155",
    "sg:province":"FL",
    "sg:tags":[
        "consultant",
        "designer"
    ],
    "wof:name":"DATACREATORS.COM",
    "wof:placetype":"venue"
},
  "geometry": {"coordinates":[-80.309342,25.726328],"type":"Point"}
}