{
  "type": "Feature",
  "properties": {
    "addr:full":"11310 Carrollwood Pl Tampa FL 33618",
    "addr:housenumber":"11310",
    "addr:postcode":"33618",
    "addr:street":"Carrollwood Pl",
    "iso:country":"US",
    "sg:address":"11310 Carrollwood Pl",
    "sg:city":"Tampa",
    "sg:classifiers":[
        {
            "category":"Real Estate",
            "subcategory":"Real Estate Agent",
            "type":"Services"
        }
    ],
    "sg:phone":"+1 813 932 6504",
    "sg:postcode":"33618",
    "sg:province":"FL",
    "wof:name":"Rose Property Management Inc",
    "wof:placetype":"venue"
},
  "geometry": {"coordinates":[-82.502174,28.052518],"type":"Point"}
}