{
  "type": "Feature",
  "properties": {
    "iso:country":"US",
    "sg:address":"10066 103rd St",
    "sg:city":"Jacksonville",
    "sg:classifiers":[
        {
            "category":"Retail",
            "subcategory":"Auto Repair",
            "type":"Services"
        }
    ],
    "sg:phone":"+1 904 908 0555",
    "sg:postcode":"32210",
    "sg:province":"FL",
    "sg:tags":[
        "repairing",
        "automobile"
    ],
    "wof:name":"Omar's Auto Air",
    "wof:placetype":"venue"
},
  "geometry": {"coordinates":[-81.824726,30.247439],"type":"Point"}
}