{
  "type": "Feature",
  "properties": {
    "addr:full":"4201 NW 37th Ave Miami FL 33142",
    "addr:housenumber":"4201",
    "addr:postcode":"33142",
    "addr:street":"Nw 37Th Ave",
    "iso:country":"US",
    "sg:address":"4201 NW 37th Ave",
    "sg:city":"Miami",
    "sg:classifiers":[
        {
            "category":"Retail",
            "subcategory":"Repair Shop",
            "type":"Services"
        }
    ],
    "sg:phone":"+1 305 633 2346",
    "sg:postcode":"33142",
    "sg:province":"FL",
    "sg:tags":[
        "related"
    ],
    "wof:name":"Erik Transmission Inc",
    "wof:placetype":"venue"
},
  "geometry": {"coordinates":[-80.25662199999999,25.814119],"type":"Point"}
}