{
  "type": "Feature",
  "properties": {
    "iso:country":"US",
    "sg:address":"4140 W 18th Ct",
    "sg:city":"Hialeah",
    "sg:classifiers":[
        {
            "category":"Wholesale",
            "subcategory":"Durable Goods & Equipment",
            "type":"Manufacturing & Wholesale Goods"
        }
    ],
    "sg:phone":"+1 305 558 8212",
    "sg:postcode":"33012",
    "sg:province":"FL",
    "sg:tags":[
        "exporter"
    ],
    "wof:name":"Rocha Enterprises Inc",
    "wof:placetype":"venue"
},
  "geometry": {"coordinates":[-80.319242,25.859657],"type":"Point"}
}