{
  "type": "Feature",
  "properties": {
    "iso:country":"US",
    "sg:address":"1500 Placida Rd",
    "sg:city":"Englewood",
    "sg:classifiers":[
        {
            "category":"Restaurant",
            "type":"Food & Drink"
        }
    ],
    "sg:phone":"+1 941 475 5888",
    "sg:postcode":"34223",
    "sg:province":"FL",
    "sg:tags":[
        "eating"
    ],
    "wof:name":"China Express",
    "wof:placetype":"venue"
},
  "geometry": {"coordinates":[-82.337422,26.936688],"type":"Point"}
}