{
  "type": "Feature",
  "properties": {
    "iso:country":"US",
    "sg:address":"4840 New Broad St",
    "sg:city":"Orlando",
    "sg:classifiers":[
        {
            "category":"Banks & Credit Unions",
            "subcategory":"Financial Services",
            "type":"Services"
        }
    ],
    "sg:phone":"+1 407 894 5511",
    "sg:postcode":"32814",
    "sg:province":"FL",
    "sg:tags":[
        "international",
        "trade"
    ],
    "wof:name":"Cross Trade Intl LLC",
    "wof:placetype":"venue"
},
  "geometry": {"coordinates":[-81.32777900000001,28.566676],"type":"Point"}
}