{
  "type": "Feature",
  "properties": {
    "iso:country":"US",
    "sg:address":"1301 S Woodland Blvd",
    "sg:city":"Deland",
    "sg:classifiers":[
        {
            "category":"Retail",
            "subcategory":"Auto Repair",
            "type":"Services"
        }
    ],
    "sg:phone":"+1 386 736 5710",
    "sg:postcode":"32720",
    "sg:province":"FL",
    "sg:tags":[
        "transmission",
        "automotive",
        "shop"
    ],
    "wof:name":"Tpa Transmissions Inc",
    "wof:placetype":"venue"
},
  "geometry": {"coordinates":[-81.30273099999999,29.006273],"type":"Point"}
}