{
  "type": "Feature",
  "properties": {
    "iso:country":"US",
    "sg:address":"933 Douglas Avenue",
    "sg:city":"Altamonte Springs",
    "sg:classifiers":[
        {
            "category":"Professional",
            "subcategory":"Employment Agencies",
            "type":"Services"
        }
    ],
    "sg:phone":"+1 407 774 4884",
    "sg:postcode":"32714",
    "sg:province":"FL",
    "sg:website":"www.proimagesolutions.com",
    "wof:name":"Pro Image Solutions Inc",
    "wof:placetype":"venue"
},
  "geometry": {"coordinates":[-81.389993,28.681563],"type":"Point"}
}