{
  "type": "Feature",
  "properties": {
    "iso:country":"US",
    "sg:address":"716 W Robinson St",
    "sg:city":"Orlando",
    "sg:classifiers":[
        {
            "category":"Food & Beverages",
            "subcategory":"Groceries & Convenience Stores",
            "type":"Retail Goods"
        }
    ],
    "sg:phone":"+1 407 422 1672",
    "sg:postcode":"32805",
    "sg:province":"FL",
    "sg:tags":[
        "grocer"
    ],
    "wof:name":"P & D Food Ctr",
    "wof:placetype":"venue"
},
  "geometry": {"coordinates":[-81.390486,28.545707],"type":"Point"}
}