{
  "type": "Feature",
  "properties": {
    "iso:country":"US",
    "sg:address":"460 W 51st Pl",
    "sg:city":"Hialeah",
    "sg:classifiers":[
        {
            "category":"Health Services",
            "subcategory":"Clinic",
            "type":"Services"
        }
    ],
    "sg:phone":"+1 305 825 3995",
    "sg:postcode":"33012",
    "sg:province":"FL",
    "sg:tags":[
        "rehabilitation"
    ],
    "wof:name":"Medley Pain & Rehabilitation",
    "wof:placetype":"venue"
},
  "geometry": {"coordinates":[-80.29176200000001,25.86942],"type":"Point"}
}