{
  "type": "Feature",
  "properties": {
    "iso:country":"US",
    "sg:address":"2626 Ave V NW",
    "sg:city":"Winter Haven",
    "sg:classifiers":[
        {
            "category":"Shopping",
            "subcategory":"Discount & Variety Stores",
            "type":"Retail Goods"
        }
    ],
    "sg:phone":"+1 863 965 1248",
    "sg:postcode":"33881",
    "sg:province":"FL",
    "sg:tags":[
        "merchandise",
        "general"
    ],
    "wof:name":"Family Variety Sales",
    "wof:placetype":"venue"
},
  "geometry": {"coordinates":[-81.760491,28.046079],"type":"Point"}
}