{
  "type": "Feature",
  "properties": {
    "addr:full":"334 E Trinidad Ave Clewiston FL 33440",
    "addr:housenumber":"334",
    "addr:postcode":"33440",
    "addr:street":"E Trinidad Ave",
    "iso:country":"US",
    "sg:address":"334 E Trinidad Ave",
    "sg:city":"Clewiston",
    "sg:classifiers":[
        {
            "category":"Real Estate",
            "subcategory":"Real Estate Agent",
            "type":"Services"
        }
    ],
    "sg:phone":"+1 863 983 8786",
    "sg:postcode":"33440",
    "sg:province":"FL",
    "wof:name":"Smith Properties",
    "wof:placetype":"venue"
},
  "geometry": {"coordinates":[-80.931541,26.751446],"type":"Point"}
}