{
  "type": "Feature",
  "properties": {
    "iso:country":"US",
    "sg:address":"10692 SE 58th Ave",
    "sg:city":"Belleview",
    "sg:classifiers":[
        {
            "category":"Retail",
            "subcategory":"Auto Repair",
            "type":"Services"
        }
    ],
    "sg:phone":"+1 352 804 1184",
    "sg:postcode":"34420",
    "sg:province":"FL",
    "sg:tags":[
        "repairing",
        "automobile"
    ],
    "wof:name":"Gary's Auto Repair",
    "wof:placetype":"venue"
},
  "geometry": {"coordinates":[-82.05323300000001,29.06727],"type":"Point"}
}