{
  "type": "Feature",
  "properties": {
    "iso:country":"US",
    "sg:address":"4658 NW 74th Ave",
    "sg:city":"Miami",
    "sg:classifiers":[
        {
            "category":"Wholesale",
            "subcategory":"Electrical",
            "type":"Manufacturing & Wholesale Goods"
        }
    ],
    "sg:phone":"+1 305 477 1687",
    "sg:postcode":"33166",
    "sg:province":"FL",
    "sg:tags":[
        "equipment",
        "electronic",
        "supply"
    ],
    "wof:name":"Central Box",
    "wof:placetype":"venue"
},
  "geometry": {"coordinates":[-80.317503,25.817088],"type":"Point"}
}