{
  "type": "Feature",
  "properties": {
    "addr:full":"9627 Palm River Rd Tampa FL 33619",
    "addr:housenumber":"9627",
    "addr:postcode":"33619",
    "addr:street":"Palm River Rd",
    "iso:country":"US",
    "sg:address":"9627 Palm River Rd",
    "sg:city":"Tampa",
    "sg:classifiers":[
        {
            "category":"Building & Trades",
            "subcategory":"Construction",
            "type":"Services"
        }
    ],
    "sg:phone":"+1 813 200 6202",
    "sg:postcode":"33619",
    "sg:province":"FL",
    "sg:tags":[
        "system",
        "specialty",
        "heating",
        "contractor",
        "air conditioning"
    ],
    "wof:name":"Tudi Mechanical Systems FL",
    "wof:placetype":"venue"
},
  "geometry": {"coordinates":[-82.347286,27.94113],"type":"Point"}
}