{
  "type": "Feature",
  "properties": {
    "addr:full":"1601 SW 107 Ave Miami FL 33165",
    "addr:housenumber":"1601",
    "addr:postcode":"33165",
    "addr:street":"Sw 107 Ave",
    "iso:country":"US",
    "sg:address":"1601 SW 107 Ave",
    "sg:city":"Miami",
    "sg:classifiers":[
        {
            "category":"Retail",
            "subcategory":"Portrait Studio",
            "type":"Services"
        },
        {
            "category":"Shopping",
            "subcategory":"Pharmacy",
            "type":"Retail Goods"
        }
    ],
    "sg:phone":"+1 305 554 1706",
    "sg:postcode":"33165",
    "sg:province":"FL",
    "sg:tags":[
        "photography",
        "drugstore",
        "store"
    ],
    "sg:website":"www.walgreens.com/",
    "wof:name":"Walgreens",
    "wof:placetype":"venue"
},
  "geometry": {"coordinates":[-80.36768600000001,25.753843],"type":"Point"}
}