{
  "type": "Feature",
  "properties": {
    "iso:country":"US",
    "sg:address":"9121 Berry Ave",
    "sg:city":"Jacksonville",
    "sg:classifiers":[
        {
            "category":"Autos & Motor Vehicles",
            "subcategory":"Auto Supplies",
            "type":"Retail Goods"
        },
        {
            "category":"Retail",
            "subcategory":"Auto Repair",
            "type":"Services"
        }
    ],
    "sg:phone":"+1 904 592 6666",
    "sg:postcode":"32211",
    "sg:province":"FL",
    "sg:tags":[
        "lettering",
        "automobile",
        "body",
        "truck",
        "customizing",
        "painting",
        "repairing"
    ],
    "wof:name":"Elite Custom Body & Paint",
    "wof:placetype":"venue"
},
  "geometry": {"coordinates":[-81.560947,30.316258],"type":"Point"}
}