{
  "type": "Feature",
  "properties": {
    "addr:full":"2433 Stanford Rd Apopka FL 32703",
    "addr:housenumber":"2433",
    "addr:postcode":"32703",
    "addr:street":"Stanford Rd",
    "iso:country":"US",
    "sg:address":"2433 Stanford Rd",
    "sg:city":"Apopka",
    "sg:classifiers":[
        {
            "category":"Building & Trades",
            "subcategory":"Plumbing",
            "type":"Services"
        }
    ],
    "sg:phone":"+1 407 701 0354",
    "sg:postcode":"32703",
    "sg:province":"FL",
    "sg:tags":[
        "plumbing",
        "contractor"
    ],
    "wof:name":"JE Torres Plumbing",
    "wof:placetype":"venue"
},
  "geometry": {"coordinates":[-81.49982300000001,28.642275],"type":"Point"}
}