{
  "type": "Feature",
  "properties": {
    "iso:country":"US",
    "sg:address":"30 Pine Island Cir",
    "sg:city":"Kissimmee",
    "sg:classifiers":[
        {
            "category":"Building & Trades",
            "subcategory":"Construction",
            "type":"Services"
        }
    ],
    "sg:phone":"+1 407 348 3660",
    "sg:postcode":"34743",
    "sg:province":"FL",
    "sg:tags":[
        "carpenter"
    ],
    "wof:name":"Skrocki Custom Carpentry Inc",
    "wof:placetype":"venue"
},
  "geometry": {"coordinates":[-81.360553,28.339911],"type":"Point"}
}