{
  "type": "Feature",
  "properties": {
    "addr:full":"1470 Glen Haven Dr Merritt Island FL 32952",
    "addr:housenumber":"1470",
    "addr:postcode":"32952",
    "addr:street":"Glen Haven Dr",
    "iso:country":"US",
    "sg:address":"1470 Glen Haven Dr",
    "sg:city":"Merritt Island",
    "sg:classifiers":[
        {
            "category":"Farming",
            "subcategory":"Nursery",
            "type":"Manufacturing & Wholesale Goods"
        }
    ],
    "sg:phone":"+1 321 452 6776",
    "sg:postcode":"32952",
    "sg:province":"FL",
    "sg:tags":[
        "ornamental"
    ],
    "wof:name":"A Rose Fantasy",
    "wof:placetype":"venue"
},
  "geometry": {"coordinates":[-80.668094,28.363081],"type":"Point"}
}