{
  "type": "Feature",
  "properties": {
    "iso:country":"US",
    "sg:address":"101 E Brandon Blvd",
    "sg:city":"Brandon",
    "sg:classifiers":[
        {
            "category":"Autos & Motor Vehicles",
            "subcategory":"Auto Supplies",
            "type":"Retail Goods"
        }
    ],
    "sg:phone":"+1 813 689 6161",
    "sg:postcode":"33511",
    "sg:province":"FL",
    "sg:tags":[
        "automobile",
        "parts"
    ],
    "wof:name":"Advance Discount Auto Parts",
    "wof:placetype":"venue"
},
  "geometry": {"coordinates":[-82.28448299999999,27.937745],"type":"Point"}
}