{
  "type": "Feature",
  "properties": {
    "addr:full":"815 E Fee Ave Melbourne FL 32901",
    "addr:housenumber":"815",
    "addr:postcode":"32901",
    "addr:street":"E Fee Ave",
    "iso:country":"US",
    "sg:address":"815 E Fee Ave",
    "sg:city":"Melbourne",
    "sg:classifiers":[
        {
            "category":"Social Services",
            "type":"Services"
        }
    ],
    "sg:phone":"+1 321 723 1060",
    "sg:postcode":"32901",
    "sg:province":"FL",
    "sg:tags":[
        "soup",
        "clinic",
        "program",
        "health",
        "welfare",
        "kitchen"
    ],
    "wof:name":"Daily Bread Inc",
    "wof:placetype":"venue"
},
  "geometry": {"coordinates":[-80.606793,28.081748],"type":"Point"}
}