{
  "type": "Feature",
  "properties": {
    "iso:country":"US",
    "sg:address":"33 Caswell Dr",
    "sg:city":"Orlando",
    "sg:classifiers":[
        {
            "category":"Building & Trades",
            "subcategory":"Construction",
            "type":"Services"
        }
    ],
    "sg:phone":"+1 407 282 0747",
    "sg:postcode":"32825",
    "sg:province":"FL",
    "sg:tags":[
        "carpentry",
        "contractor"
    ],
    "wof:name":"B&B Carpentry",
    "wof:placetype":"venue"
},
  "geometry": {"coordinates":[-81.269485,28.54465],"type":"Point"}
}