{
  "type": "Feature",
  "properties": {
    "addr:full":"3211 Quail Dr Deltona FL 32738",
    "addr:housenumber":"3211",
    "addr:postcode":"32738",
    "addr:street":"Quail Dr",
    "iso:country":"US",
    "sg:address":"3211 Quail Dr",
    "sg:city":"Deltona",
    "sg:classifiers":[
        {
            "category":"Building & Trades",
            "subcategory":"Construction",
            "type":"Services"
        }
    ],
    "sg:phone":"+1 386 848 1686",
    "sg:postcode":"32738",
    "sg:province":"FL",
    "sg:tags":[
        "hanging",
        "contractor"
    ],
    "wof:name":"J & J Painters",
    "wof:placetype":"venue"
},
  "geometry": {"coordinates":[-81.213059,28.954295],"type":"Point"}
}