{
  "type": "Feature",
  "properties": {
    "addr:full":"1309 NW 192nd Ave Gainesville FL 32609",
    "addr:housenumber":"1309",
    "addr:postcode":"32609",
    "addr:street":"Nw 192Nd Ave",
    "iso:country":"US",
    "sg:address":"1309 NW 192nd Ave",
    "sg:city":"Gainesville",
    "sg:classifiers":[
        {
            "category":"Government",
            "subcategory":"Office",
            "type":"Public Place"
        }
    ],
    "sg:phone":"+1 352 485 1250",
    "sg:postcode":"32609",
    "sg:province":"FL",
    "sg:tags":[
        "endangered",
        "agency",
        "species",
        "conservation"
    ],
    "wof:name":"Lubee Foundation Inc",
    "wof:placetype":"venue"
},
  "geometry": {"coordinates":[-82.34107299999999,29.829883],"type":"Point"}
}