{
  "type": "Feature",
  "properties": {
    "iso:country":"US",
    "sg:address":"1515 Elizabeth St Ste G",
    "sg:city":"Melbourne",
    "sg:classifiers":[
        {
            "category":"Building & Trades",
            "subcategory":"Construction",
            "type":"Services"
        }
    ],
    "sg:phone":"+1 321 728 9447",
    "sg:postcode":"32901",
    "sg:province":"FL",
    "sg:tags":[
        "roofing",
        "industrial",
        "contractors-commercial",
        "contractor"
    ],
    "wof:name":"Cedar Valley Exteriors",
    "wof:placetype":"venue"
},
  "geometry": {"coordinates":[-80.62441699999999,28.085015],"type":"Point"}
}