{
  "type": "Feature",
  "properties": {
    "iso:country":"US",
    "sg:address":"1310 Cassat Ave",
    "sg:city":"Jacksonville",
    "sg:classifiers":[
        {
            "category":"Autos & Motor Vehicles",
            "subcategory":"Auto Supplies",
            "type":"Retail Goods"
        }
    ],
    "sg:phone":"+1 904 389 4561",
    "sg:postcode":"32205",
    "sg:province":"FL",
    "sg:tags":[
        "automobile",
        "parts"
    ],
    "wof:name":"Westside Toyota",
    "wof:placetype":"venue"
},
  "geometry": {"coordinates":[-81.73047699999999,30.297569],"type":"Point"}
}