{
  "type": "Feature",
  "properties": {
    "iso:country":"US",
    "sg:address":"11281 Tamiami Trl",
    "sg:city":"Punta Gorda",
    "sg:classifiers":[
        {
            "category":"Home & Garden",
            "subcategory":"Mobile Homes",
            "type":"Retail Goods"
        }
    ],
    "sg:phone":"+1 941 575 1003",
    "sg:postcode":"33955",
    "sg:province":"FL",
    "wof:name":"Highway 41 Home Ctr",
    "wof:placetype":"venue"
},
  "geometry": {"coordinates":[-81.99776199999999,26.86662],"type":"Point"}
}