{
  "type": "Feature",
  "properties": {
    "addr:full":"4729 96th St N St Petersburg FL 33708",
    "addr:housenumber":"4729",
    "addr:postcode":"33708",
    "addr:street":"96Th St N",
    "iso:country":"US",
    "sg:address":"4729 96th St N",
    "sg:city":"St Petersburg",
    "sg:classifiers":[
        {
            "category":"Manufacturing",
            "subcategory":"Tools & Machinery",
            "type":"Manufacturing & Wholesale Goods"
        }
    ],
    "sg:phone":"+1 727 393 5238",
    "sg:postcode":"33708",
    "sg:province":"FL",
    "sg:tags":[
        "shop",
        "repair",
        "industrial",
        "mfg",
        "trade",
        "machine",
        "welding"
    ],
    "wof:name":"Gunn's Welding & Fabricating",
    "wof:placetype":"venue"
},
  "geometry": {"coordinates":[-82.771958,27.816446],"type":"Point"}
}