{
  "type": "Feature",
  "properties": {
    "iso:country":"US",
    "sg:address":"1940 Finn Hill Dr",
    "sg:city":"Boynton Beach",
    "sg:classifiers":[
        {
            "category":"Real Estate",
            "subcategory":"Real Estate Agent",
            "type":"Services"
        }
    ],
    "sg:phone":"+1 561 547 1094",
    "sg:postcode":"33426",
    "sg:province":"FL",
    "sg:tags":[
        "business"
    ],
    "wof:name":"Stark & Stark RE Appraisal",
    "wof:placetype":"venue"
},
  "geometry": {"coordinates":[-80.07379,26.56996],"type":"Point"}
}