{
  "type": "Feature",
  "properties": {
    "iso:country":"US",
    "sg:address":"3360 SW 22nd Ter",
    "sg:city":"Miami",
    "sg:classifiers":[
        {
            "category":"Real Estate",
            "subcategory":"Architect",
            "type":"Services"
        }
    ],
    "sg:phone":"+1 305 443 2727",
    "sg:postcode":"33145",
    "sg:province":"FL",
    "sg:tags":[
        "architectural"
    ],
    "wof:name":"Giorgio Blli AIA Architects PA",
    "wof:placetype":"venue"
},
  "geometry": {"coordinates":[-80.24724399999999,25.749092],"type":"Point"}
}