{
  "type": "Feature",
  "properties": {
    "iso:country":"US",
    "sg:address":"158 NW 16th St",
    "sg:city":"Boca Raton",
    "sg:classifiers":[
        {
            "category":"Recreation",
            "type":"Entertainment"
        }
    ],
    "sg:phone":"+1 561 955 9645",
    "sg:postcode":"33432",
    "sg:province":"FL",
    "sg:tags":[
        "martial",
        "arts",
        "instruction"
    ],
    "wof:name":"Millennium Martial Arts",
    "wof:placetype":"venue"
},
  "geometry": {"coordinates":[-80.089978,26.364473],"type":"Point"}
}