{
  "type": "Feature",
  "properties": {
    "iso:country":"US",
    "sg:address":"7832 US Hwy 19",
    "sg:city":"Port Richey",
    "sg:classifiers":[
        {
            "category":"Building & Trades",
            "subcategory":"Construction",
            "type":"Services"
        }
    ],
    "sg:phone":"+1 727 847 1114",
    "sg:postcode":"34668",
    "sg:province":"FL",
    "sg:tags":[
        "glass",
        "installation",
        "tinting"
    ],
    "wof:name":"ACA Glass Inc",
    "wof:placetype":"venue"
},
  "geometry": {"coordinates":[-82.724752,28.270526],"type":"Point"}
}