{
  "type": "Feature",
  "properties": {
    "addr:full":"616 Ololu Dr Winter Park FL 32789",
    "addr:housenumber":"616",
    "addr:postcode":"32789",
    "addr:street":"Ololu Dr",
    "iso:country":"US",
    "sg:address":"616 Ololu Dr",
    "sg:city":"Winter Park",
    "sg:classifiers":[
        {
            "category":"Social Services",
            "type":"Services"
        }
    ],
    "sg:phone":"+1 407 644 7413",
    "sg:postcode":"32789",
    "sg:province":"FL",
    "sg:tags":[
        "agency",
        "adoption"
    ],
    "wof:name":"Circle Of Love Inc",
    "wof:placetype":"venue"
},
  "geometry": {"coordinates":[-81.38431199999999,28.602641],"type":"Point"}
}