{
  "type": "Feature",
  "properties": {
    "addr:full":"3301 NW 97th Ave Miami FL 33172",
    "addr:housenumber":"3301",
    "addr:postcode":"33172",
    "addr:street":"Nw 97Th Ave",
    "iso:country":"US",
    "sg:address":"3301 NW 97th Ave",
    "sg:city":"Miami",
    "sg:classifiers":[
        {
            "category":"Wholesale",
            "subcategory":"Plants",
            "type":"Manufacturing & Wholesale Goods"
        }
    ],
    "sg:phone":"+1 305 639 2607",
    "sg:postcode":"33172",
    "sg:province":"FL",
    "sg:tags":[
        "supply"
    ],
    "wof:name":"Floral Resources",
    "wof:placetype":"venue"
},
  "geometry": {"coordinates":[-80.353182,25.800997],"type":"Point"}
}