{
  "type": "Feature",
  "properties": {
    "iso:country":"US",
    "sg:address":"9465 NW 109th St",
    "sg:city":"Medley",
    "sg:classifiers":[
        {
            "category":"Home & Garden",
            "subcategory":"Building Materials",
            "type":"Retail Goods"
        },
        {
            "category":"Manufacturing",
            "subcategory":"Building Materials",
            "type":"Manufacturing & Wholesale Goods"
        }
    ],
    "sg:phone":"+1 305 863 2727",
    "sg:postcode":"33178",
    "sg:province":"FL",
    "sg:tags":[
        "accessory",
        "shutter",
        "doors",
        "frames",
        "shutters-wholesale",
        "manufacturer"
    ],
    "sg:website":"http://www.jcimpactshutters.com",
    "wof:name":"JC Impact Shutters & Glass Inc",
    "wof:placetype":"venue"
},
  "geometry": {"coordinates":[-80.34930900000001,25.872469],"type":"Point"}
}