{
  "type": "Feature",
  "properties": {
    "addr:full":"1740 NE Miami Gardens Dr Miami FL 33179",
    "addr:housenumber":"1740",
    "addr:postcode":"33179",
    "addr:street":"Ne Miami Gardens Dr",
    "iso:country":"US",
    "sg:address":"1740 NE Miami Gardens Dr",
    "sg:city":"Miami",
    "sg:classifiers":[
        {
            "category":"Personal",
            "subcategory":"Barber",
            "type":"Services"
        }
    ],
    "sg:phone":"+1 305 947 2052",
    "sg:postcode":"33179",
    "sg:province":"FL",
    "wof:name":"Roma Skylake Mall Barber Shop",
    "wof:placetype":"venue"
},
  "geometry": {"coordinates":[-80.1661,25.945801],"type":"Point"}
}