{
  "type": "Feature",
  "properties": {
    "iso:country":"US",
    "sg:address":"6080 NW 84th Ave",
    "sg:city":"Miami",
    "sg:classifiers":[
        {
            "category":"Home & Garden",
            "subcategory":"Furniture",
            "type":"Retail Goods"
        }
    ],
    "sg:phone":"+1 305 477 2211",
    "sg:postcode":"33166",
    "sg:province":"FL",
    "wof:name":"Kreativa For Kids",
    "wof:placetype":"venue"
},
  "geometry": {"coordinates":[-80.333922,25.826575],"type":"Point"}
}