{
  "type": "Feature",
  "properties": {
    "iso:country":"US",
    "sg:address":"420 94th Ave N",
    "sg:city":"Saint Petersburg",
    "sg:classifiers":[
        {
            "category":"Wholesale",
            "subcategory":"Medical Equipment & Supplies",
            "type":"Manufacturing & Wholesale Goods"
        }
    ],
    "sg:phone":"+1 727 521 3216",
    "sg:postcode":"33702",
    "sg:province":"FL",
    "sg:tags":[
        "hospital",
        "mfg"
    ],
    "wof:name":"Exelint International Co",
    "wof:placetype":"venue"
},
  "geometry": {"coordinates":[-82.64048200000001,27.857441],"type":"Point"}
}