{
  "type": "Feature",
  "properties": {
    "addr:full":"1100 N Young Blvd Chiefland FL 32626",
    "addr:housenumber":"1100",
    "addr:postcode":"32626",
    "addr:street":"N Young Blvd",
    "iso:country":"US",
    "sg:address":"1100 N Young Blvd",
    "sg:city":"Chiefland",
    "sg:classifiers":[
        {
            "category":"Shopping",
            "subcategory":"Pharmacy",
            "type":"Retail Goods"
        }
    ],
    "sg:phone":"+1 352 490 7700",
    "sg:postcode":"32626",
    "sg:province":"FL",
    "wof:name":"North Fla Phrm of Chiefland",
    "wof:placetype":"venue"
},
  "geometry": {"coordinates":[-82.86256,29.49024],"type":"Point"}
}