{
  "type": "Feature",
  "properties": {
    "iso:country":"US",
    "sg:address":"5541 SW 11th St",
    "sg:city":"Pompano Beach",
    "sg:classifiers":[
        {
            "category":"Social Services",
            "subcategory":"Child Care",
            "type":"Services"
        }
    ],
    "sg:phone":"+1 954 973 1673",
    "sg:postcode":"33068",
    "sg:province":"FL",
    "sg:tags":[
        "day"
    ],
    "wof:name":"Clark Day Care",
    "wof:placetype":"venue"
},
  "geometry": {"coordinates":[-80.20223799999999,26.214355],"type":"Point"}
}