{
  "type": "Feature",
  "properties": {
    "iso:country":"US",
    "sg:address":"11213 NW 73rd St",
    "sg:city":"Doral",
    "sg:classifiers":[
        {
            "category":"Professional",
            "type":"Services"
        }
    ],
    "sg:phone":"+1 305 592 8218",
    "sg:postcode":"33178",
    "sg:province":"FL",
    "sg:tags":[
        "establishment"
    ],
    "wof:name":"Compuworking & System Corp",
    "wof:placetype":"venue"
},
  "geometry": {"coordinates":[-80.37902099999999,25.839641],"type":"Point"}
}