{
  "type": "Feature",
  "properties": {
    "addr:full":"4505 N Rome Ave Tampa FL 33603",
    "addr:housenumber":"4505",
    "addr:postcode":"33603",
    "addr:street":"N Rome Ave",
    "iso:country":"US",
    "sg:address":"4505 N Rome Ave",
    "sg:city":"Tampa",
    "sg:classifiers":[
        {
            "category":"Organizations",
            "subcategory":"Religious Organization",
            "type":"Services"
        }
    ],
    "sg:phone":"+1 813 239 0066",
    "sg:postcode":"33603",
    "sg:province":"FL",
    "sg:tags":[
        "clergy"
    ],
    "wof:name":"Pages Pastor",
    "wof:placetype":"venue"
},
  "geometry": {"coordinates":[-82.476523,27.983407],"type":"Point"}
}