{
  "type": "Feature",
  "properties": {
    "addr:full":"14 Claridge Ct N Palm Coast FL 32137",
    "addr:housenumber":"14",
    "addr:postcode":"32137",
    "addr:street":"Claridge Ct N",
    "iso:country":"US",
    "sg:address":"14 Claridge Ct N",
    "sg:city":"Palm Coast",
    "sg:classifiers":[
        {
            "category":"Building & Trades",
            "subcategory":"Construction",
            "type":"Services"
        }
    ],
    "sg:phone":"+1 386 447 7077",
    "sg:postcode":"32137",
    "sg:province":"FL",
    "sg:tags":[
        "concrete",
        "contractor"
    ],
    "wof:name":"Stay Hard Concrete LLC",
    "wof:placetype":"venue"
},
  "geometry": {"coordinates":[-81.201446,29.58002],"type":"Point"}
}