{
  "type": "Feature",
  "properties": {
    "iso:country":"US",
    "sg:address":"909 Fish Hatchery Rd",
    "sg:city":"Lakeland",
    "sg:classifiers":[
        {
            "category":"Building & Trades",
            "subcategory":"Electrical",
            "type":"Services"
        }
    ],
    "sg:phone":"+1 863 665 4577",
    "sg:postcode":"33801",
    "sg:province":"FL",
    "sg:tags":[
        "electrical",
        "contractor"
    ],
    "wof:name":"Wilkes Electric Inc",
    "wof:placetype":"venue"
},
  "geometry": {"coordinates":[-81.89564300000001,28.053562],"type":"Point"}
}