{
  "type": "Feature",
  "properties": {
    "addr:full":"18269 Fresh Lake Way Boca Raton FL 33498",
    "addr:housenumber":"18269",
    "addr:postcode":"33498",
    "addr:street":"Fresh Lake Way",
    "iso:country":"US",
    "sg:address":"18269 Fresh Lake Way",
    "sg:city":"Boca Raton",
    "sg:classifiers":[
        {
            "category":"Health Services",
            "subcategory":"Doctor",
            "type":"Services"
        }
    ],
    "sg:phone":"+1 561 482 1960",
    "sg:postcode":"33498",
    "sg:province":"FL",
    "sg:tags":[
        "phys"
    ],
    "wof:name":"Joseph M Mavica Do",
    "wof:placetype":"venue"
},
  "geometry": {"coordinates":[-80.22720700000001,26.404881],"type":"Point"}
}