{
  "type": "Feature",
  "properties": {
    "iso:country":"US",
    "sg:address":"4410 Kenilworth Blvd",
    "sg:city":"Sebring",
    "sg:classifiers":[
        {
            "category":"Food & Beverages",
            "subcategory":"Groceries & Convenience Stores",
            "type":"Retail Goods"
        }
    ],
    "sg:phone":"+1 863 382 6988",
    "sg:postcode":"33870",
    "sg:province":"FL",
    "sg:tags":[
        "grocer"
    ],
    "wof:name":"Canovas Fish & Meat Market",
    "wof:placetype":"venue"
},
  "geometry": {"coordinates":[-81.42264400000001,27.485919],"type":"Point"}
}