{
  "type": "Feature",
  "properties": {
    "iso:country":"US",
    "sg:address":"111 NE 2nd Ave",
    "sg:city":"Okeechobee",
    "sg:classifiers":[
        {
            "category":"Professional",
            "subcategory":"Business Services",
            "type":"Services"
        }
    ],
    "sg:phone":"+1 863 467 2524",
    "sg:postcode":"34972",
    "sg:province":"FL",
    "sg:tags":[
        "auctioneer"
    ],
    "wof:name":"Big Lake Online",
    "wof:placetype":"venue"
},
  "geometry": {"coordinates":[-80.828791,27.244653],"type":"Point"}
}