{
  "type": "Feature",
  "properties": {
    "iso:country":"US",
    "sg:address":"1123 John Sims Pkwy",
    "sg:city":"Niceville",
    "sg:classifiers":[
        {
            "category":"Personal",
            "subcategory":"Beauty Salon",
            "type":"Services"
        }
    ],
    "sg:phone":"+1 850 729 1865",
    "sg:postcode":"32578",
    "sg:province":"FL",
    "sg:tags":[
        "shop"
    ],
    "wof:name":"Hollywood Nails",
    "wof:placetype":"venue"
},
  "geometry": {"coordinates":[-86.461901,30.514916],"type":"Point"}
}