{
  "type": "Feature",
  "properties": {
    "addr:full":"339 Eaton St Maitland FL 32751",
    "addr:housenumber":"339",
    "addr:postcode":"32751",
    "addr:street":"Eaton St",
    "iso:country":"US",
    "sg:address":"339 Eaton St",
    "sg:city":"Maitland",
    "sg:classifiers":[
        {
            "category":"Building & Trades",
            "subcategory":"Cleaning & Sanitation",
            "type":"Services"
        }
    ],
    "sg:phone":"+1 407 448 5643",
    "sg:postcode":"32751",
    "sg:province":"FL",
    "wof:name":"Joiner Janitoral",
    "wof:placetype":"venue"
},
  "geometry": {"coordinates":[-81.38157200000001,28.620435],"type":"Point"}
}