{
  "type": "Feature",
  "properties": {
    "addr:full":"435 Clark Rd Jacksonville FL 32218",
    "addr:housenumber":"435",
    "addr:postcode":"32218",
    "addr:street":"Clark Rd",
    "iso:country":"US",
    "sg:address":"435 Clark Rd",
    "sg:city":"Jacksonville",
    "sg:classifiers":[
        {
            "category":"Banks & Credit Unions",
            "subcategory":"Bank",
            "type":"Services"
        }
    ],
    "sg:phone":"+1 904 765 1316",
    "sg:postcode":"32218",
    "sg:province":"FL",
    "sg:tags":[
        "loan",
        "real estate"
    ],
    "wof:name":"Harold Simpson Financial Inc",
    "wof:placetype":"venue"
},
  "geometry": {"coordinates":[-81.65824499999999,30.41412],"type":"Point"}
}