{
  "type": "Feature",
  "properties": {
    "addr:full":"3308 NE 32nd St Fort Lauderdale FL 33308",
    "addr:housenumber":"3308",
    "addr:postcode":"33308",
    "addr:street":"Ne 32Nd St",
    "iso:country":"US",
    "sg:address":"3308 NE 32nd St",
    "sg:city":"Fort Lauderdale",
    "sg:classifiers":[
        {
            "category":"Personal",
            "subcategory":"Beauty Salon",
            "type":"Services"
        }
    ],
    "sg:phone":"+1 954 537 0365",
    "sg:postcode":"33308",
    "sg:province":"FL",
    "wof:name":"Beauty 365",
    "wof:placetype":"venue"
},
  "geometry": {"coordinates":[-80.10037199999999,26.1684],"type":"Point"}
}