{
  "type": "Feature",
  "properties": {
    "iso:country":"US",
    "sg:address":"11891 N Campwest Dr",
    "sg:city":"Dunnellon",
    "sg:classifiers":[
        {
            "category":"Retail",
            "subcategory":"Repair Shop",
            "type":"Services"
        }
    ],
    "sg:phone":"+1 352 489 3591",
    "sg:postcode":"34433",
    "sg:province":"FL",
    "sg:tags":[
        "sharpening"
    ],
    "wof:name":"D B Spraker Saw & Tool",
    "wof:placetype":"venue"
},
  "geometry": {"coordinates":[-82.505624,29.037716],"type":"Point"}
}