{
  "type": "Feature",
  "properties": {
    "iso:country":"US",
    "sg:address":"127 Candace Dr",
    "sg:city":"Maitland",
    "sg:classifiers":[
        {
            "category":"Wholesale",
            "subcategory":"Electrical",
            "type":"Manufacturing & Wholesale Goods"
        }
    ],
    "sg:phone":"+1 407 678 9955",
    "sg:postcode":"32751",
    "sg:province":"FL",
    "sg:tags":[
        "home",
        "electronic",
        "mfg"
    ],
    "sg:website":"www.poweramper.com",
    "wof:name":"Power Amper Industry Inc",
    "wof:placetype":"venue"
},
  "geometry": {"coordinates":[-81.355445,28.644368],"type":"Point"}
}