{
  "type": "Feature",
  "properties": {
    "iso:country":"US",
    "sg:address":"303 E 25th St",
    "sg:city":"Sanford",
    "sg:classifiers":[
        {
            "category":"Food & Beverages",
            "subcategory":"Groceries & Convenience Stores",
            "type":"Retail Goods"
        }
    ],
    "sg:phone":"+1 407 322 0601",
    "sg:postcode":"32771",
    "sg:province":"FL",
    "sg:website":"http://www.beequik.com",
    "wof:name":"Handy Way Food Stores",
    "wof:placetype":"venue"
},
  "geometry": {"coordinates":[-81.265743,28.78669],"type":"Point"}
}