{
  "type": "Feature",
  "properties": {
    "addr:full":"4146 San Ysidro Way Rockledge FL 32955",
    "addr:housenumber":"4146",
    "addr:postcode":"32955",
    "addr:street":"San Ysidro Way",
    "iso:country":"US",
    "sg:address":"4146 San Ysidro Way",
    "sg:city":"Rockledge",
    "sg:classifiers":[
        {
            "category":"Building & Trades",
            "subcategory":"Construction",
            "type":"Services"
        }
    ],
    "sg:phone":"+1 321 403 5060",
    "sg:postcode":"32955",
    "sg:province":"FL",
    "sg:tags":[
        "handyman"
    ],
    "wof:name":"Frank W Dejose Handyman Svc",
    "wof:placetype":"venue"
},
  "geometry": {"coordinates":[-80.71923,28.28851],"type":"Point"}
}