{
  "type": "Feature",
  "properties": {
    "addr:full":"5284 Dellbrook Ave Spring Hill FL 34608",
    "addr:housenumber":"5284",
    "addr:postcode":"34608",
    "addr:street":"Dellbrook Ave",
    "iso:country":"US",
    "sg:address":"5284 Dellbrook Ave",
    "sg:city":"Spring Hill",
    "sg:classifiers":[
        {
            "category":"Building & Trades",
            "subcategory":"Landscaping Services",
            "type":"Services"
        }
    ],
    "sg:phone":"+1 352 686 8961",
    "sg:postcode":"34608",
    "sg:province":"FL",
    "wof:name":"Brian Charlies Lawn Maintence",
    "wof:placetype":"venue"
},
  "geometry": {"coordinates":[-82.526447,28.508148],"type":"Point"}
}