{
  "type": "Feature",
  "properties": {
    "addr:full":"315 S Calhoun St Tallahassee FL 32301",
    "addr:housenumber":"315",
    "addr:postcode":"32301",
    "addr:street":"S Calhoun St",
    "iso:country":"US",
    "sg:address":"315 S Calhoun St",
    "sg:city":"Tallahassee",
    "sg:classifiers":[
        {
            "category":"Government",
            "subcategory":"Court House",
            "type":"Public Place"
        }
    ],
    "sg:phone":"+1 850 942 8430",
    "sg:postcode":"32301",
    "sg:province":"FL",
    "sg:tags":[
        "federal",
        "counsel"
    ],
    "wof:name":"US Attorney",
    "wof:placetype":"venue"
},
  "geometry": {"coordinates":[-84.279512,30.43941],"type":"Point"}
}