{
  "type": "Feature",
  "properties": {
    "addr:full":"2706 W Azeele St Tampa FL 33609",
    "addr:housenumber":"2706",
    "addr:postcode":"33609",
    "addr:street":"W Azeele St",
    "iso:country":"US",
    "sg:address":"2706 W Azeele St",
    "sg:city":"Tampa",
    "sg:classifiers":[
        {
            "category":"Autos & Motor Vehicles",
            "subcategory":"Automobile Sales",
            "type":"Retail Goods"
        },
        {
            "category":"Wholesale",
            "subcategory":"Motor Vehicles",
            "type":"Manufacturing & Wholesale Goods"
        }
    ],
    "sg:phone":"+1 813 874 8333",
    "sg:postcode":"33609",
    "sg:province":"FL",
    "sg:tags":[
        "car",
        "only",
        "used",
        "truck",
        "broker"
    ],
    "wof:name":"Sam Meeke Auto Wholesale",
    "wof:placetype":"venue"
},
  "geometry": {"coordinates":[-82.487104,27.94111],"type":"Point"}
}