{
  "type": "Feature",
  "properties": {
    "iso:country":"US",
    "sg:address":"6316 San Michel Way",
    "sg:city":"Delray Beach",
    "sg:classifiers":[
        {
            "category":"Building & Trades",
            "subcategory":"Construction",
            "type":"Services"
        }
    ],
    "sg:phone":"+1 561 637 8550",
    "sg:postcode":"33484",
    "sg:province":"FL",
    "sg:tags":[
        "house"
    ],
    "wof:name":"Marinucci Builders",
    "wof:placetype":"venue"
},
  "geometry": {"coordinates":[-80.141943,26.425199],"type":"Point"}
}