{
  "type": "Feature",
  "properties": {
    "iso:country":"US",
    "sg:address":"7805 Coral Way",
    "sg:city":"Miami",
    "sg:classifiers":[
        {
            "category":"Insurance",
            "subcategory":"Insurance Agent",
            "type":"Services"
        },
        {
            "category":"Banks & Credit Unions",
            "subcategory":"Financial Services",
            "type":"Services"
        }
    ],
    "sg:phone":"+1 786 388 0606",
    "sg:postcode":"33155",
    "sg:province":"FL",
    "sg:tags":[
        "counseling",
        "debt",
        "adjuster"
    ],
    "wof:name":"Apex Credit Report",
    "wof:placetype":"venue"
},
  "geometry": {"coordinates":[-80.322031,25.748117],"type":"Point"}
}