{
  "type": "Feature",
  "properties": {
    "addr:full":"7700 Beneva Rd Sarasota FL 34238",
    "addr:postcode":"7700;34238",
    "addr:street":"Beneva Rd",
    "iso:country":"US",
    "sg:address":"7700 Beneva Rd",
    "sg:city":"Sarasota",
    "sg:classifiers":[
        {
            "category":"Place Of Worship",
            "subcategory":"Synagogue",
            "type":"Public Place"
        },
        {
            "category":"Place Of Worship",
            "type":"Public Place"
        }
    ],
    "sg:phone":"+1 941 925 0770",
    "sg:postcode":"34238",
    "sg:province":"FL",
    "sg:tags":[
        "synagogues-reform",
        "church"
    ],
    "sg:website":"http://www.chabadofsarasota.com",
    "wof:name":"Chabad Of Sarasota",
    "wof:placetype":"venue"
},
  "geometry": {"coordinates":[-82.497581,27.242611],"type":"Point"}
}