{
  "type": "Feature",
  "properties": {
    "addr:full":"16 Church Dr Venus FL 33960",
    "addr:housenumber":"16",
    "addr:postcode":"33960",
    "addr:street":"Church Dr",
    "iso:country":"US",
    "sg:address":"16 Church Dr",
    "sg:city":"Venus",
    "sg:classifiers":[
        {
            "category":"Organizations",
            "subcategory":"Religious Organization",
            "type":"Services"
        }
    ],
    "sg:phone":"+1 863 465 5283",
    "sg:postcode":"33960",
    "sg:province":"FL",
    "sg:tags":[
        "church"
    ],
    "wof:name":"Venus Baptist Church",
    "wof:placetype":"venue"
},
  "geometry": {"coordinates":[-81.365351,27.064391],"type":"Point"}
}