{
  "type": "Feature",
  "properties": {
    "addr:full":"3440 Prancer Ln Ormond Beach FL 32174",
    "addr:housenumber":"3440",
    "addr:postcode":"32174",
    "addr:street":"Prancer Ln",
    "iso:country":"US",
    "sg:address":"3440 Prancer Ln",
    "sg:city":"Ormond Beach",
    "sg:classifiers":[
        {
            "category":"Retail",
            "subcategory":"Repair Shop",
            "type":"Services"
        }
    ],
    "sg:phone":"+1 386 453 3277",
    "sg:postcode":"32174",
    "sg:province":"FL",
    "sg:tags":[
        "appliance"
    ],
    "wof:name":"Caswell's Repair Svc",
    "wof:placetype":"venue"
},
  "geometry": {"coordinates":[-81.217657,29.254603],"type":"Point"}
}