{
  "type": "Feature",
  "properties": {
    "iso:country":"US",
    "sg:address":"2677 Old Bainbridge Rd",
    "sg:city":"Tallahassee",
    "sg:classifiers":[
        {
            "category":"Real Estate",
            "subcategory":"Real Estate Operator",
            "type":"Services"
        }
    ],
    "sg:phone":"+1 850 514 4000",
    "sg:postcode":"32303",
    "sg:province":"FL",
    "sg:tags":[
        "apartment"
    ],
    "sg:website":"http://www.livetheoasis.com",
    "wof:name":"The Oasis",
    "wof:placetype":"venue"
},
  "geometry": {"coordinates":[-84.319519,30.48204],"type":"Point"}
}