{
  "type": "Feature",
  "properties": {
    "addr:full":"1555 Saxon Blvd Ste 201 Deltona FL 32725",
    "addr:housenumber":"1555",
    "addr:postcode":"32725",
    "addr:street":"Saxon Blvd Ste 201",
    "iso:country":"US",
    "sg:address":"1555 Saxon Blvd Ste 201",
    "sg:city":"Deltona",
    "sg:classifiers":[
        {
            "category":"Health Services",
            "subcategory":"Doctor",
            "type":"Services"
        }
    ],
    "sg:phone":"+1 386 575 0202",
    "sg:postcode":"32725",
    "sg:province":"FL",
    "sg:tags":[
        "practice",
        "family"
    ],
    "wof:name":"Family Practice of Deltona",
    "wof:placetype":"venue"
},
  "geometry": {"coordinates":[-81.242104,28.898199],"type":"Point"}
}