{
  "type": "Feature",
  "properties": {
    "iso:country":"US",
    "sg:address":"3022 NW 72nd Ave",
    "sg:city":"Miami",
    "sg:classifiers":[
        {
            "category":"Food & Beverages",
            "subcategory":"Meat & Fish",
            "type":"Retail Goods"
        }
    ],
    "sg:phone":"+1 305 477 2955",
    "sg:postcode":"33122",
    "sg:province":"FL",
    "sg:tags":[
        "seafood"
    ],
    "wof:name":"Aly's Marine Seafood Inc",
    "wof:placetype":"venue"
},
  "geometry": {"coordinates":[-80.313146,25.8022],"type":"Point"}
}