{
  "type": "Feature",
  "properties": {
    "iso:country":"US",
    "sg:address":"21319 Town Lakes Dr",
    "sg:city":"Boca Raton",
    "sg:classifiers":[
        {
            "category":"Shopping",
            "subcategory":"Musical Instruments",
            "type":"Retail Goods"
        }
    ],
    "sg:phone":"+1 561 338 9432",
    "sg:postcode":"33486",
    "sg:province":"FL",
    "sg:tags":[
        "violin"
    ],
    "wof:name":"Gustavo Correa",
    "wof:placetype":"venue"
},
  "geometry": {"coordinates":[-80.130405,26.359508],"type":"Point"}
}