{
  "type": "Feature",
  "properties": {
    "addr:full":"950 Montgomery Rd Altamonte Spgs FL 32714",
    "addr:housenumber":"950",
    "addr:postcode":"32714",
    "addr:street":"Montgomery Rd",
    "iso:country":"US",
    "sg:address":"950 Montgomery Rd",
    "sg:city":"Altamonte Spgs",
    "sg:classifiers":[
        {
            "category":"Real Estate",
            "subcategory":"Real Estate Operator",
            "type":"Services"
        }
    ],
    "sg:phone":"+1 407 774 4774",
    "sg:postcode":"32714",
    "sg:province":"FL",
    "sg:tags":[
        "building",
        "apartment"
    ],
    "wof:name":"Wekiva Woods",
    "wof:placetype":"venue"
},
  "geometry": {"coordinates":[-81.40272,28.684074],"type":"Point"}
}