{
  "type": "Feature",
  "properties": {
    "iso:country":"US",
    "sg:address":"655 Tamiami Canal Rd",
    "sg:city":"Miami",
    "sg:classifiers":[
        {
            "category":"Building & Trades",
            "subcategory":"Electrical",
            "type":"Services"
        }
    ],
    "sg:phone":"+1 305 338 8394",
    "sg:postcode":"33144",
    "sg:province":"FL",
    "sg:tags":[
        "electrician"
    ],
    "wof:name":"A R Electric Services Inc",
    "wof:placetype":"venue"
},
  "geometry": {"coordinates":[-80.31729300000001,25.763702],"type":"Point"}
}