{
  "type": "Feature",
  "properties": {
    "iso:country":"US",
    "sg:address":"7226 Ayrshire Ln",
    "sg:city":"Boca Raton",
    "sg:classifiers":[
        {
            "category":"Banks & Credit Unions",
            "subcategory":"Financial Services",
            "type":"Services"
        }
    ],
    "sg:phone":"+1 561 482 1513",
    "sg:postcode":"33496",
    "sg:province":"FL",
    "sg:tags":[
        "trust",
        "management"
    ],
    "wof:name":"Bernstein Family Partnership",
    "wof:placetype":"venue"
},
  "geometry": {"coordinates":[-80.155855,26.415238],"type":"Point"}
}