{
  "type": "Feature",
  "properties": {
    "addr:full":"4000 N Goldenrod Rd Winter Park FL 32792",
    "addr:housenumber":"4000",
    "addr:postcode":"32792",
    "addr:street":"N Goldenrod Rd",
    "iso:country":"US",
    "sg:address":"4000 N Goldenrod Rd",
    "sg:city":"Winter Park",
    "sg:classifiers":[
        {
            "category":"Shopping",
            "subcategory":"Pharmacy",
            "type":"Retail Goods"
        }
    ],
    "sg:phone":"+1 407 671 1177",
    "sg:postcode":"32792",
    "sg:province":"FL",
    "wof:name":"Kmart Pharmacies Inc",
    "wof:placetype":"venue"
},
  "geometry": {"coordinates":[-81.28661099999999,28.599169],"type":"Point"}
}