{
  "type": "Feature",
  "properties": {
    "addr:full":"3312 E Atlantic Blvd Pompano Beach FL 33062",
    "addr:housenumber":"3312",
    "addr:postcode":"33062",
    "addr:street":"E Atlantic Blvd",
    "iso:country":"US",
    "sg:address":"3312 E Atlantic Blvd",
    "sg:city":"Pompano Beach",
    "sg:classifiers":[
        {
            "category":"Shopping",
            "subcategory":"Music",
            "type":"Retail Goods"
        }
    ],
    "sg:phone":"+1 954 946 3511",
    "sg:postcode":"33062",
    "sg:province":"FL",
    "sg:tags":[
        "video",
        "disc",
        "tape",
        "cassette"
    ],
    "wof:name":"Beach Video",
    "wof:placetype":"venue"
},
  "geometry": {"coordinates":[-80.091078,26.23188],"type":"Point"}
}