{
  "type": "Feature",
  "properties": {
    "iso:country":"US",
    "sg:address":"2518 NW 21st Ter",
    "sg:city":"Miami",
    "sg:classifiers":[
        {
            "category":"Building & Trades",
            "subcategory":"Construction",
            "type":"Services"
        }
    ],
    "sg:phone":"+1 305 633 4893",
    "sg:postcode":"33142",
    "sg:province":"FL",
    "sg:tags":[
        "railing"
    ],
    "wof:name":"Babilonia Enterprises",
    "wof:placetype":"venue"
},
  "geometry": {"coordinates":[-80.23861599999999,25.796077],"type":"Point"}
}