{
  "type": "Feature",
  "properties": {
    "iso:country":"US",
    "sg:address":"311 SW 7th St",
    "sg:city":"Miami",
    "sg:classifiers":[
        {
            "category":"Insurance",
            "subcategory":"Health Insurance",
            "type":"Services"
        },
        {
            "category":"Shopping",
            "subcategory":"Pharmacy",
            "type":"Retail Goods"
        },
        {
            "category":"Food & Beverages",
            "subcategory":"Groceries & Convenience Stores",
            "type":"Retail Goods"
        }
    ],
    "sg:phone":"+1 305 860 9477",
    "sg:postcode":"33130",
    "sg:province":"FL",
    "sg:tags":[
        "drugstore",
        "market"
    ],
    "sg:website":"www.publix.com",
    "wof:name":"Publix",
    "wof:placetype":"venue"
},
  "geometry": {"coordinates":[-80.199298,25.767197],"type":"Point"}
}