{
  "type": "Feature",
  "properties": {
    "iso:country":"US",
    "sg:address":"451 Eagle Ridge Dr",
    "sg:city":"Lake Wales",
    "sg:classifiers":[
        {
            "category":"Professional",
            "subcategory":"Accounting & Tax Preparation",
            "type":"Services"
        }
    ],
    "sg:phone":"+1 863 679 9200",
    "sg:postcode":"33837",
    "sg:province":"FL",
    "sg:tags":[
        "return",
        "filing"
    ],
    "wof:name":"Jackson Hewitt Tax Svc",
    "wof:placetype":"venue"
},
  "geometry": {"coordinates":[-81.618343,28.192454],"type":"Point"}
}