{
  "type": "Feature",
  "properties": {
    "iso:country":"US",
    "sg:address":"27535 Miller Rd",
    "sg:city":"Dade City",
    "sg:phone":"+1 352 588 2174",
    "sg:postcode":"33525",
    "sg:province":"FL",
    "sg:tags":[
        "tomato",
        "farm"
    ],
    "wof:name":"Darby Farms",
    "wof:placetype":"venue"
},
  "geometry": {"coordinates":[-82.36180299999999,28.354058],"type":"Point"}
}