{
  "type": "Feature",
  "properties": {
    "iso:country":"US",
    "sg:address":"4625 Palm Beach Blvd",
    "sg:city":"Fort Myers",
    "sg:classifiers":[
        {
            "category":"Organizations",
            "subcategory":"Non-profit Organization",
            "type":"Services"
        }
    ],
    "sg:phone":"+1 239 332 7575",
    "sg:postcode":"33905",
    "sg:province":"FL",
    "wof:name":"Nations Associations Inc",
    "wof:placetype":"venue"
},
  "geometry": {"coordinates":[-81.817204,26.673735],"type":"Point"}
}