{
  "type": "Feature",
  "properties": {
    "addr:full":"3259 SE Federal Hwy Stuart FL 34997",
    "addr:housenumber":"3259",
    "addr:postcode":"34997",
    "addr:street":"Se Federal Hwy",
    "iso:country":"US",
    "sg:address":"3259 SE Federal Hwy",
    "sg:city":"Stuart",
    "sg:classifiers":[
        {
            "category":"Bars & Pubs",
            "type":"Food & Drink"
        }
    ],
    "sg:phone":"+1 772 220 1541",
    "sg:postcode":"34997",
    "sg:province":"FL",
    "sg:tags":[
        "drinking",
        "eating"
    ],
    "wof:name":"Rj Gators Florida Food n Fun",
    "wof:placetype":"venue"
},
  "geometry": {"coordinates":[-80.226512,27.16513],"type":"Point"}
}