{
  "type": "Feature",
  "properties": {
    "addr:full":"1313 Ponce de Leon Blvd Coral Gables FL 33134",
    "addr:housenumber":"1313",
    "addr:postcode":"33134",
    "addr:street":"Ponce De Leon Blvd",
    "iso:country":"US",
    "sg:address":"1313 Ponce de Leon Blvd",
    "sg:city":"Coral Gables",
    "sg:classifiers":[
        {
            "category":"Professional",
            "subcategory":"Accounting & Tax Preparation",
            "type":"Services"
        }
    ],
    "sg:phone":"+1 305 443 8500",
    "sg:postcode":"33134",
    "sg:province":"FL",
    "sg:tags":[
        "accountant"
    ],
    "sg:website":"www.mlrivero.com",
    "wof:name":"Manuel L Rivero Accounting",
    "wof:placetype":"venue"
},
  "geometry": {"coordinates":[-80.258877,25.759038],"type":"Point"}
}