{
  "type": "Feature",
  "properties": {
    "iso:country":"US",
    "sg:address":"2825 Winkler Ave",
    "sg:city":"Fort Myers",
    "sg:classifiers":[
        {
            "category":"Real Estate",
            "subcategory":"Real Estate Operator",
            "type":"Services"
        }
    ],
    "sg:phone":"+1 239 337 9601",
    "sg:postcode":"33916",
    "sg:province":"FL",
    "sg:tags":[
        "apartment"
    ],
    "wof:name":"Village Creek",
    "wof:placetype":"venue"
},
  "geometry": {"coordinates":[-81.853363,26.604471],"type":"Point"}
}