{
  "type": "Feature",
  "properties": {
    "addr:full":"5719 Myrtle Hill Dr W Lakeland FL 33811",
    "addr:housenumber":"5719",
    "addr:postcode":"33811",
    "addr:street":"Myrtle Hill Dr W",
    "iso:country":"US",
    "sg:address":"5719 Myrtle Hill Dr W",
    "sg:city":"Lakeland",
    "sg:classifiers":[
        {
            "category":"Building & Trades",
            "subcategory":"Plumbing",
            "type":"Services"
        }
    ],
    "sg:phone":"+1 863 647 5765",
    "sg:postcode":"33811",
    "sg:province":"FL",
    "sg:tags":[
        "plumber"
    ],
    "sg:website":"http://www.sparkmanplumbing.com",
    "wof:name":"Sparkman Plumbing Inc",
    "wof:placetype":"venue"
},
  "geometry": {"coordinates":[-82.02047399999999,27.961095],"type":"Point"}
}