{
  "type": "Feature",
  "properties": {
    "iso:country":"US",
    "sg:address":"4035 J Louis St",
    "sg:city":"Green Cove Springs",
    "sg:classifiers":[
        {
            "category":"Professional",
            "subcategory":"Business Services",
            "type":"Services"
        }
    ],
    "sg:phone":"+1 904 529 9896",
    "sg:postcode":"32043",
    "sg:province":"FL",
    "sg:tags":[
        "packaging",
        "labeling"
    ],
    "wof:name":"Home Fragrance Holding",
    "wof:placetype":"venue"
},
  "geometry": {"coordinates":[-81.65993899999999,29.979239],"type":"Point"}
}