{
  "type": "Feature",
  "properties": {
    "iso:country":"US",
    "sg:address":"1862 W Flagler St",
    "sg:city":"Miami",
    "sg:classifiers":[
        {
            "category":"Restaurant",
            "type":"Food & Drink"
        }
    ],
    "sg:phone":"+1 305 649 8540",
    "sg:postcode":"33135",
    "sg:province":"FL",
    "wof:name":"L A Tropical",
    "wof:placetype":"venue"
},
  "geometry": {"coordinates":[-80.22580000000001,25.7728],"type":"Point"}
}