{
  "type": "Feature",
  "properties": {
    "iso:country":"US",
    "sg:address":"5006 N Federal Hwy",
    "sg:city":"Pompano Beach",
    "sg:classifiers":[
        {
            "category":"Social Services",
            "subcategory":"Child Care",
            "type":"Services"
        }
    ],
    "sg:phone":"+1 954 571 8787",
    "sg:postcode":"33064",
    "sg:province":"FL",
    "sg:tags":[
        "day"
    ],
    "wof:name":"Kids Play Town Inc",
    "wof:placetype":"venue"
},
  "geometry": {"coordinates":[-80.09492899999999,26.292665],"type":"Point"}
}