{
  "type": "Feature",
  "properties": {
    "iso:country":"US",
    "sg:address":"1150 45th St",
    "sg:city":"West Palm Beach",
    "sg:classifiers":[
        {
            "category":"Government",
            "subcategory":"Office",
            "type":"Public Place"
        }
    ],
    "sg:phone":"+1 561 514 5300",
    "sg:postcode":"33407",
    "sg:province":"FL",
    "sg:tags":[
        "county",
        "program",
        "health"
    ],
    "wof:name":"West Palm Beach Health Ctr",
    "wof:placetype":"venue"
},
  "geometry": {"coordinates":[-80.07217900000001,26.753151],"type":"Point"}
}