{
  "type": "Feature",
  "properties": {
    "addr:full":"9200 Talway Cir Boynton Beach FL 33472",
    "addr:housenumber":"9200",
    "addr:postcode":"33472",
    "addr:street":"Talway Cir",
    "iso:country":"US",
    "sg:address":"9200 Talway Cir",
    "sg:city":"Boynton Beach",
    "sg:classifiers":[
        {
            "category":"Professional",
            "subcategory":"Business Services",
            "type":"Services"
        }
    ],
    "sg:phone":"+1 561 737 4101",
    "sg:postcode":"33472",
    "sg:province":"FL",
    "wof:name":"Susan Gale & Assoc Inc",
    "wof:placetype":"venue"
},
  "geometry": {"coordinates":[-80.19695900000001,26.551261],"type":"Point"}
}