{
  "type": "Feature",
  "properties": {
    "addr:full":"2510 Grandview Ave Sanford FL 32773",
    "addr:housenumber":"2510",
    "addr:postcode":"32773",
    "addr:street":"Grandview Ave",
    "iso:country":"US",
    "sg:address":"2510 Grandview Ave",
    "sg:city":"Sanford",
    "sg:classifiers":[
        {
            "category":"Utilities",
            "subcategory":"Electric",
            "type":"Services"
        }
    ],
    "sg:phone":"+1 407 322 8026",
    "sg:postcode":"32773",
    "sg:province":"FL",
    "sg:tags":[
        "plant",
        "power"
    ],
    "wof:name":"FPL",
    "wof:placetype":"venue"
},
  "geometry": {"coordinates":[-81.263801,28.784683],"type":"Point"}
}