{
  "type": "Feature",
  "properties": {
    "addr:full":"13303 NW 7th Ave Miami FL 33168",
    "addr:housenumber":"13303",
    "addr:postcode":"33168",
    "addr:street":"Nw 7Th Ave",
    "iso:country":"US",
    "sg:address":"13303 NW 7th Ave",
    "sg:city":"Miami",
    "sg:classifiers":[
        {
            "category":"Personal",
            "subcategory":"Beauty Salon",
            "type":"Services"
        }
    ],
    "sg:phone":"+1 305 681 6566",
    "sg:postcode":"33168",
    "sg:province":"FL",
    "sg:tags":[
        "shop"
    ],
    "wof:name":"Marta Hair Styling",
    "wof:placetype":"venue"
},
  "geometry": {"coordinates":[-80.21113800000001,25.897354],"type":"Point"}
}