{
  "type": "Feature",
  "properties": {
    "iso:country":"US",
    "sg:address":"1623 Goodyear Ave",
    "sg:city":"Lakeland",
    "sg:classifiers":[
        {
            "category":"Retail",
            "subcategory":"Auto Repair",
            "type":"Services"
        }
    ],
    "sg:phone":"+1 863 669 1235",
    "sg:postcode":"33801",
    "sg:province":"FL",
    "sg:tags":[
        "body",
        "automobile",
        "painting"
    ],
    "wof:name":"Williams Paint Shop",
    "wof:placetype":"venue"
},
  "geometry": {"coordinates":[-81.901008,28.023395],"type":"Point"}
}