{
  "type": "Feature",
  "properties": {
    "iso:country":"US",
    "sg:address":"13050 Summerfield Blvd",
    "sg:city":"Riverview",
    "sg:classifiers":[
        {
            "category":"Sports & Exercise",
            "subcategory":"Golf",
            "type":"Entertainment"
        }
    ],
    "sg:phone":"+1 813 671 3311",
    "sg:postcode":"33579",
    "sg:province":"FL",
    "sg:tags":[
        "course",
        "public"
    ],
    "wof:name":"Summerfield Golf Club Inc",
    "wof:placetype":"venue"
},
  "geometry": {"coordinates":[-81.95195699999999,30.349113],"type":"Point"}
}