{
  "type": "Feature",
  "properties": {
    "iso:country":"US",
    "sg:address":"1653 Banks Rd",
    "sg:city":"Pompano Beach",
    "sg:classifiers":[
        {
            "category":"Building & Trades",
            "subcategory":"Electrical",
            "type":"Services"
        }
    ],
    "sg:phone":"+1 954 974 3840",
    "sg:postcode":"33063",
    "sg:province":"FL",
    "sg:tags":[
        "electrical",
        "contractor"
    ],
    "wof:name":"Ohms Electrical Corp",
    "wof:placetype":"venue"
},
  "geometry": {"coordinates":[-80.194389,26.250019],"type":"Point"}
}