{
  "type": "Feature",
  "properties": {
    "iso:country":"US",
    "sg:address":"15510 Furlong Cir",
    "sg:city":"Odessa",
    "sg:classifiers":[
        {
            "category":"Freight",
            "type":"Transportation"
        }
    ],
    "sg:phone":"+1 813 926 2722",
    "sg:postcode":"33556",
    "sg:province":"FL",
    "wof:name":"Robert Bears Enterprises",
    "wof:placetype":"venue"
},
  "geometry": {"coordinates":[-82.61984099999999,28.091922],"type":"Point"}
}