{
  "type": "Feature",
  "properties": {
    "addr:full":"1548 Co Rd 501 Wildwood FL 34785",
    "addr:housenumber":"1548",
    "addr:postcode":"34785",
    "addr:street":"Co Rd 501",
    "iso:country":"US",
    "sg:address":"1548 Co Rd 501",
    "sg:city":"Wildwood",
    "sg:classifiers":[
        {
            "category":"Building & Trades",
            "subcategory":"Construction",
            "type":"Services"
        }
    ],
    "sg:phone":"+1 352 748 7799",
    "sg:postcode":"34785",
    "sg:province":"FL",
    "sg:tags":[
        "contractor"
    ],
    "wof:name":"Construction Admin Office Fbop",
    "wof:placetype":"venue"
},
  "geometry": {"coordinates":[-82.004243,28.783292],"type":"Point"}
}