{
  "type": "Feature",
  "properties": {
    "iso:country":"US",
    "sg:address":"8295 SW 43rd Ter",
    "sg:city":"Miami",
    "sg:classifiers":[
        {
            "category":"Home & Garden",
            "subcategory":"Furniture",
            "type":"Retail Goods"
        }
    ],
    "sg:phone":"+1 305 552 1481",
    "sg:postcode":"33155",
    "sg:province":"FL",
    "sg:tags":[
        "wall",
        "item",
        "household",
        "interior",
        "including"
    ],
    "wof:name":"Florido Interiors Inc",
    "wof:placetype":"venue"
},
  "geometry": {"coordinates":[-80.32741,25.728778],"type":"Point"}
}