{
  "type": "Feature",
  "properties": {
    "iso:country":"US",
    "sg:address":"438 Lakeview Dr",
    "sg:city":"Weston",
    "sg:classifiers":[
        {
            "category":"Personal",
            "subcategory":"Beauty Salon",
            "type":"Services"
        }
    ],
    "sg:phone":"+1 954 385 6868",
    "sg:postcode":"33326",
    "sg:province":"FL",
    "wof:name":"Weston Beauty",
    "wof:placetype":"venue"
},
  "geometry": {"coordinates":[-80.384708,26.118547],"type":"Point"}
}