{
  "type": "Feature",
  "properties": {
    "iso:country":"US",
    "sg:address":"1429 W Tennessee St",
    "sg:city":"Tallahassee",
    "sg:classifiers":[
        {
            "category":"Restaurant",
            "type":"Food & Drink"
        }
    ],
    "sg:menulink":"http://www.allmenus.com/fl/tallahassee-central/81400-papa-johns-pizza/menu/",
    "sg:phone":"+1 850 224 1222",
    "sg:postcode":"32304",
    "sg:province":"FL",
    "sg:tags":[
        "american",
        "pizza"
    ],
    "wof:name":"Papa John's Pizza",
    "wof:placetype":"venue"
},
  "geometry": {"coordinates":[-84.306426,30.448686],"type":"Point"}
}