{
  "type": "Feature",
  "properties": {
    "addr:full":"461 89th Ave N St Petersburg FL 33702",
    "addr:housenumber":"461",
    "addr:postcode":"33702",
    "addr:street":"89Th Ave N",
    "iso:country":"US",
    "sg:address":"461 89th Ave N",
    "sg:city":"St Petersburg",
    "sg:classifiers":[
        {
            "category":"Building & Trades",
            "subcategory":"Landscaping Services",
            "type":"Services"
        }
    ],
    "sg:phone":"+1 727 576 3852",
    "sg:postcode":"33702",
    "sg:province":"FL",
    "sg:tags":[
        "tree"
    ],
    "wof:name":"Intensive Care Tree Trimming",
    "wof:placetype":"venue"
},
  "geometry": {"coordinates":[-82.639706,27.853501],"type":"Point"}
}