{
  "type": "Feature",
  "properties": {
    "iso:country":"US",
    "sg:address":"522 N W St",
    "sg:city":"Pensacola",
    "sg:classifiers":[
        {
            "category":"Organizations",
            "subcategory":"Political Organization",
            "type":"Services"
        }
    ],
    "sg:phone":"+1 850 434 0454",
    "sg:postcode":"32505",
    "sg:province":"FL",
    "wof:name":"Reelect Sheriff Mc Nesby",
    "wof:placetype":"venue"
},
  "geometry": {"coordinates":[-87.250249,30.41887],"type":"Point"}
}