{
  "type": "Feature",
  "properties": {
    "addr:full":"8360 W Flagler St Ste 203 Miami FL 33144",
    "addr:housenumber":"8360",
    "addr:postcode":"33144",
    "addr:street":"W Flagler St Ste 203",
    "iso:country":"US",
    "sg:address":"8360 W Flagler St Ste 203",
    "sg:city":"Miami",
    "sg:classifiers":[
        {
            "category":"Professional",
            "subcategory":"Accounting & Tax Preparation",
            "type":"Services"
        }
    ],
    "sg:phone":"+1 305 553 9801",
    "sg:postcode":"33144",
    "sg:province":"FL",
    "sg:tags":[
        "accountant"
    ],
    "wof:name":"Longaray and Associates Accounting & Income Tax",
    "wof:placetype":"venue"
},
  "geometry": {"coordinates":[-80.306,25.7654],"type":"Point"}
}