{
  "type": "Feature",
  "properties": {
    "iso:country":"US",
    "sg:address":"4900 Donovan St",
    "sg:city":"Orlando",
    "sg:classifiers":[
        {
            "category":"Place Of Worship",
            "subcategory":"Church",
            "type":"Public Place"
        }
    ],
    "sg:phone":"+1 407 291 8877",
    "sg:postcode":"32808",
    "sg:province":"FL",
    "sg:tags":[
        "churches-non-denominational"
    ],
    "sg:website":"http://www.newlifewoc.org",
    "wof:name":"New Life Ministries World Outreach Center Inc",
    "wof:placetype":"venue"
},
  "geometry": {"coordinates":[-81.44774200000001,28.589563],"type":"Point"}
}