{
  "type": "Feature",
  "properties": {
    "addr:full":"202 Lake Miriam Dr Lakeland FL 33813",
    "addr:housenumber":"202",
    "addr:postcode":"33813",
    "addr:street":"Lake Miriam Dr",
    "iso:country":"US",
    "sg:address":"202 Lake Miriam Dr",
    "sg:city":"Lakeland",
    "sg:classifiers":[
        {
            "category":"Professional",
            "subcategory":"Accounting & Tax Preparation",
            "type":"Services"
        }
    ],
    "sg:phone":"+1 863 646 3488",
    "sg:postcode":"33813",
    "sg:province":"FL",
    "sg:tags":[
        "bookkeeping",
        "general"
    ],
    "wof:name":"John N Peronto",
    "wof:placetype":"venue"
},
  "geometry": {"coordinates":[-81.959594,27.974949],"type":"Point"}
}