{
  "type": "Feature",
  "properties": {
    "iso:country":"US",
    "sg:address":"700 E Airport Blvd",
    "sg:city":"Sanford",
    "sg:classifiers":[
        {
            "category":"Freight",
            "type":"Transportation"
        }
    ],
    "sg:phone":"+1 407 330 6477",
    "sg:postcode":"32773",
    "sg:province":"FL",
    "sg:tags":[
        "operator",
        "local",
        "trucking"
    ],
    "wof:name":"Ckb Delivery Service Inc",
    "wof:placetype":"venue"
},
  "geometry": {"coordinates":[-81.27088999999999,28.771061],"type":"Point"}
}