{
  "type": "Feature",
  "properties": {
    "addr:full":"7159 Rose Ave Orlando FL 32810",
    "addr:housenumber":"7159",
    "addr:postcode":"32810",
    "addr:street":"Rose Ave",
    "iso:country":"US",
    "sg:address":"7159 Rose Ave",
    "sg:city":"Orlando",
    "sg:classifiers":[
        {
            "category":"Home & Garden",
            "subcategory":"Building Materials",
            "type":"Retail Goods"
        },
        {
            "category":"Manufacturing",
            "subcategory":"Furniture",
            "type":"Manufacturing & Wholesale Goods"
        }
    ],
    "sg:phone":"+1 407 299 9394",
    "sg:postcode":"32810",
    "sg:province":"FL",
    "sg:tags":[
        "counter",
        "product",
        "cut",
        "top",
        "mfg"
    ],
    "sg:website":"www.adifferentperspective.com",
    "wof:name":"A Different Perspective Inc",
    "wof:placetype":"venue"
},
  "geometry": {"coordinates":[-81.44316600000001,28.620903],"type":"Point"}
}