{
  "type": "Feature",
  "properties": {
    "iso:country":"US",
    "sg:address":"6091 Marthas Ln",
    "sg:city":"Saint Cloud",
    "sg:classifiers":[
        {
            "category":"Farming",
            "subcategory":"Farm",
            "type":"Manufacturing & Wholesale Goods"
        }
    ],
    "sg:phone":"+1 407 498 0401",
    "sg:postcode":"34771",
    "sg:province":"FL",
    "sg:tags":[
        "crop",
        "general"
    ],
    "wof:name":"Practically Heaven Farms Inc",
    "wof:placetype":"venue"
},
  "geometry": {"coordinates":[-81.195019,28.308102],"type":"Point"}
}