{
  "type": "Feature",
  "properties": {
    "iso:country":"US",
    "sg:address":"1770 el Jobean Rd",
    "sg:city":"Port Charlotte",
    "sg:classifiers":[
        {
            "category":"Shopping",
            "subcategory":"Gifts & Souvenirs",
            "type":"Retail Goods"
        }
    ],
    "sg:phone":"+1 941 624 0233",
    "sg:postcode":"33948",
    "sg:province":"FL",
    "sg:tags":[
        "collectible",
        "country",
        "furniture"
    ],
    "wof:name":"Country Peddler Inc",
    "wof:placetype":"venue"
},
  "geometry": {"coordinates":[-82.168443,27.004925],"type":"Point"}
}