{
  "type": "Feature",
  "properties": {
    "iso:country":"US",
    "sg:address":"2224 Mullet Lake Park Rd",
    "sg:city":"Geneva",
    "sg:classifiers":[
        {
            "category":"Personal",
            "subcategory":"Beauty Salon",
            "type":"Services"
        }
    ],
    "sg:phone":"+1 407 349 5060",
    "sg:postcode":"32732",
    "sg:province":"FL",
    "wof:name":"Lawn Illusions By Amit Patel",
    "wof:placetype":"venue"
},
  "geometry": {"coordinates":[-81.14441100000001,28.787391],"type":"Point"}
}