{
  "type": "Feature",
  "properties": {
    "addr:full":"3406 SE 5th Ave Cape Coral FL 33904",
    "addr:housenumber":"3406",
    "addr:postcode":"33904",
    "addr:street":"Se 5Th Ave",
    "iso:country":"US",
    "sg:address":"3406 SE 5th Ave",
    "sg:city":"Cape Coral",
    "sg:classifiers":[
        {
            "category":"Real Estate",
            "subcategory":"Real Estate Operator",
            "type":"Services"
        }
    ],
    "sg:phone":"+1 239 540 3839",
    "sg:postcode":"33904",
    "sg:province":"FL",
    "sg:tags":[
        "building",
        "nonresidential"
    ],
    "wof:name":"Sunset Marine & Property Svc",
    "wof:placetype":"venue"
},
  "geometry": {"coordinates":[-81.96439700000001,26.588617],"type":"Point"}
}