{
  "type": "Feature",
  "properties": {
    "iso:country":"US",
    "sg:address":"120 S Fremont Ave",
    "sg:city":"Tampa",
    "sg:classifiers":[
        {
            "category":"Health Services",
            "subcategory":"Doctor",
            "type":"Services"
        }
    ],
    "sg:phone":"+1 813 871 5000",
    "sg:postcode":"33606",
    "sg:province":"FL",
    "sg:tags":[
        "physician",
        "surgeon"
    ],
    "wof:name":"Tampa Bay Plastic Surgery Inc",
    "wof:placetype":"venue"
},
  "geometry": {"coordinates":[-82.478774,27.943588],"type":"Point"}
}