{
  "type": "Feature",
  "properties": {
    "iso:country":"US",
    "sg:address":"1262 Gondola Ct",
    "sg:city":"Boynton Beach",
    "sg:classifiers":[
        {
            "category":"Food & Beverages",
            "subcategory":"Groceries & Convenience Stores",
            "type":"Retail Goods"
        }
    ],
    "sg:phone":"+1 561 736 1005",
    "sg:postcode":"33426",
    "sg:province":"FL",
    "sg:tags":[
        "grocer"
    ],
    "wof:name":"Rainbow City Grocery Store",
    "wof:placetype":"venue"
},
  "geometry": {"coordinates":[-80.08642399999999,26.52994],"type":"Point"}
}