{
  "type": "Feature",
  "properties": {
    "iso:country":"US",
    "sg:address":"7919 Magnolia Homes Rd",
    "sg:city":"Orlando",
    "sg:classifiers":[
        {
            "category":"Place Of Worship",
            "subcategory":"Church",
            "type":"Public Place"
        },
        {
            "category":"Place Of Worship",
            "type":"Public Place"
        }
    ],
    "sg:phone":"+1 407 253 9464",
    "sg:postcode":"32810",
    "sg:province":"FL",
    "sg:tags":[
        "churches-interdenominational",
        "churches-pentecostal-independent",
        "churches-various",
        "churches-pentecostal",
        "denomination"
    ],
    "wof:name":"Time Of Refreshing Christian Worship Center",
    "wof:placetype":"venue"
},
  "geometry": {"coordinates":[-81.42742200000001,28.628199],"type":"Point"}
}