{
  "type": "Feature",
  "properties": {
    "iso:country":"US",
    "sg:address":"212 Canterbury Dr W",
    "sg:city":"Palm Beach Gardens",
    "sg:classifiers":[
        {
            "category":"Restaurant",
            "type":"Food & Drink"
        }
    ],
    "sg:phone":"+1 561 626 3878",
    "sg:postcode":"33418",
    "sg:province":"FL",
    "sg:tags":[
        "eating"
    ],
    "wof:name":"Rene Rooney Designs",
    "wof:placetype":"venue"
},
  "geometry": {"coordinates":[-80.137539,26.815814],"type":"Point"}
}