{
  "type": "Feature",
  "properties": {
    "iso:country":"US",
    "sg:address":"1510 NE 130th St",
    "sg:city":"North Miami",
    "sg:classifiers":[
        {
            "category":"Professional",
            "subcategory":"Art Services",
            "type":"Services"
        }
    ],
    "sg:phone":"+1 305 892 9198",
    "sg:postcode":"33161",
    "sg:province":"FL",
    "sg:tags":[
        "artist"
    ],
    "wof:name":"Elias Art",
    "wof:placetype":"venue"
},
  "geometry": {"coordinates":[-80.16996899999999,25.895448],"type":"Point"}
}