{
  "type": "Feature",
  "properties": {
    "addr:full":"1313 W Midway Rd Fort Pierce FL 34982",
    "addr:housenumber":"1313",
    "addr:postcode":"34982",
    "addr:street":"W Midway Rd",
    "iso:country":"US",
    "sg:address":"1313 W Midway Rd",
    "sg:city":"Fort Pierce",
    "sg:classifiers":[
        {
            "category":"Farming",
            "subcategory":"Farm & Veterinary Services",
            "type":"Manufacturing & Wholesale Goods"
        }
    ],
    "sg:phone":"+1 772 467 8677",
    "sg:postcode":"34982",
    "sg:province":"FL",
    "sg:tags":[
        "citrus",
        "groves",
        "management"
    ],
    "sg:website":"www.rivercountrycitrus.com",
    "wof:name":"River Country Citrus",
    "wof:placetype":"venue"
},
  "geometry": {"coordinates":[-80.34211500000001,27.374287],"type":"Point"}
}