{
  "type": "Feature",
  "properties": {
    "addr:full":"3032 Fox Hill Cir Apopka FL 32703",
    "addr:housenumber":"3032",
    "addr:postcode":"32703",
    "addr:street":"Fox Hill Cir",
    "iso:country":"US",
    "sg:address":"3032 Fox Hill Cir",
    "sg:city":"Apopka",
    "sg:classifiers":[
        {
            "category":"Manufacturing",
            "subcategory":"Tools & Machinery",
            "type":"Manufacturing & Wholesale Goods"
        }
    ],
    "sg:phone":"+1 407 579 5953",
    "sg:postcode":"32703",
    "sg:province":"FL",
    "sg:tags":[
        "machine",
        "mfg",
        "accessory"
    ],
    "wof:name":"Shashaco Chucks Pvt Ltd Inc",
    "wof:placetype":"venue"
},
  "geometry": {"coordinates":[-81.452331,28.672723],"type":"Point"}
}