{
  "type": "Feature",
  "properties": {
    "addr:full":"1279 Kingsley Ave Orange Park FL 32073",
    "addr:housenumber":"1279",
    "addr:postcode":"32073",
    "addr:street":"Kingsley Ave",
    "iso:country":"US",
    "sg:address":"1279 Kingsley Ave",
    "sg:city":"Orange Park",
    "sg:classifiers":[
        {
            "category":"Professional",
            "subcategory":"Lawyer & Legal Services",
            "type":"Services"
        }
    ],
    "sg:phone":"+1 904 541 1702",
    "sg:postcode":"32073",
    "sg:province":"FL",
    "sg:tags":[
        "attorney"
    ],
    "wof:name":"Larry Smith Pa",
    "wof:placetype":"venue"
},
  "geometry": {"coordinates":[-81.72040800000001,30.165322],"type":"Point"}
}