{
  "type": "Feature",
  "properties": {
    "addr:full":"1186 NW 128th Pl Miami FL 33182",
    "addr:housenumber":"1186",
    "addr:postcode":"33182",
    "addr:street":"Nw 128Th Pl",
    "iso:country":"US",
    "sg:address":"1186 NW 128th Pl",
    "sg:city":"Miami",
    "sg:classifiers":[
        {
            "category":"Communications",
            "type":"Services"
        }
    ],
    "sg:phone":"+1 305 554 4738",
    "sg:postcode":"33182",
    "sg:province":"FL",
    "sg:tags":[
        "translator",
        "interpreter"
    ],
    "wof:name":"Dreams Innovators, Inc.",
    "wof:placetype":"venue"
},
  "geometry": {"coordinates":[-80.404263,25.782263],"type":"Point"}
}