{
  "type": "Feature",
  "properties": {
    "addr:full":"7495 NW 4th St Plantation FL 33317",
    "addr:housenumber":"7495",
    "addr:postcode":"33317",
    "addr:street":"Nw 4Th St",
    "iso:country":"US",
    "sg:address":"7495 NW 4th St",
    "sg:city":"Plantation",
    "sg:classifiers":[
        {
            "category":"Professional",
            "subcategory":"Management & Consulting",
            "type":"Services"
        }
    ],
    "sg:phone":"+1 954 327 2524",
    "sg:postcode":"33317",
    "sg:province":"FL",
    "sg:tags":[
        "consultant"
    ],
    "wof:name":"Dynamic Corporate Consultants",
    "wof:placetype":"venue"
},
  "geometry": {"coordinates":[-80.249562,26.126929],"type":"Point"}
}