{
  "type": "Feature",
  "properties": {
    "addr:full":"4325 W Lake Mary Blvd Lake Mary FL 32746",
    "addr:housenumber":"4325",
    "addr:postcode":"32746",
    "addr:street":"W Lake Mary Blvd",
    "iso:country":"US",
    "sg:address":"4325 W Lake Mary Blvd",
    "sg:city":"Lake Mary",
    "sg:classifiers":[
        {
            "category":"Restaurant",
            "type":"Food & Drink"
        },
        {
            "category":"Ice Cream",
            "type":"Food & Drink"
        }
    ],
    "sg:menulink":"http://www.allmenus.com/fl/sanford/92359-steak-n-shake/menu/",
    "sg:phone":"+1 407 328 4200",
    "sg:postcode":"32746",
    "sg:province":"FL",
    "sg:tags":[
        "american",
        "ice",
        "cream"
    ],
    "wof:name":"Steak 'n Shake",
    "wof:placetype":"venue"
},
  "geometry": {"coordinates":[-81.350819,28.755836],"type":"Point"}
}