{
  "type": "Feature",
  "properties": {
    "iso:country":"US",
    "sg:address":"187 Cessna Blvd",
    "sg:city":"Port Orange",
    "sg:classifiers":[
        {
            "category":"Autos & Motor Vehicles",
            "subcategory":"Automobile Sales",
            "type":"Retail Goods"
        }
    ],
    "sg:phone":"+1 386 304 8266",
    "sg:postcode":"32128",
    "sg:province":"FL",
    "sg:tags":[
        "aircraft"
    ],
    "wof:name":"Highland Helicopter Mntnnc",
    "wof:placetype":"venue"
},
  "geometry": {"coordinates":[-81.04443999999999,29.077834],"type":"Point"}
}