{
  "type": "Feature",
  "properties": {
    "iso:country":"US",
    "sg:address":"16783 NW 14th Ct",
    "sg:city":"Hollywood",
    "sg:classifiers":[
        {
            "category":"Wholesale",
            "subcategory":"Auto Parts",
            "type":"Manufacturing & Wholesale Goods"
        }
    ],
    "sg:phone":"+1 954 704 4924",
    "sg:postcode":"33028",
    "sg:province":"FL",
    "wof:name":"Practical Solutions Inc",
    "wof:placetype":"venue"
},
  "geometry": {"coordinates":[-80.370097,26.020097],"type":"Point"}
}