{
  "type": "Feature",
  "properties": {
    "iso:country":"US",
    "sg:address":"13400 NW 27th Ave",
    "sg:city":"Opa Locka",
    "sg:classifiers":[
        {
            "category":"Autos & Motor Vehicles",
            "subcategory":"Auto Supplies",
            "type":"Retail Goods"
        }
    ],
    "sg:phone":"+1 305 681 3802",
    "sg:postcode":"33054",
    "sg:province":"FL",
    "sg:tags":[
        "automobile",
        "parts"
    ],
    "sg:website":"www.advanceautoparts.com",
    "wof:name":"Discount Auto Parts Inc",
    "wof:placetype":"venue"
},
  "geometry": {"coordinates":[-80.243691,25.897172],"type":"Point"}
}