{
  "type": "Feature",
  "properties": {
    "iso:country":"US",
    "sg:address":"506 E Broadway St",
    "sg:city":"Fort Meade",
    "sg:classifiers":[
        {
            "category":"Farming",
            "subcategory":"Orchard",
            "type":"Manufacturing & Wholesale Goods"
        }
    ],
    "sg:phone":"+1 863 285 9413",
    "sg:postcode":"33841",
    "sg:province":"FL",
    "sg:tags":[
        "citrus",
        "grove",
        "fruit"
    ],
    "wof:name":"Martin Groves",
    "wof:placetype":"venue"
},
  "geometry": {"coordinates":[-81.793352,27.751971],"type":"Point"}
}