{
  "type": "Feature",
  "properties": {
    "iso:country":"US",
    "sg:address":"909 Cherry St",
    "sg:city":"New Smyrna Beach",
    "sg:classifiers":[
        {
            "category":"Professional",
            "subcategory":"Business Services",
            "type":"Services"
        }
    ],
    "sg:phone":"+1 386 423 8300",
    "sg:postcode":"32168",
    "sg:province":"FL",
    "wof:name":"Mel Cal Enterprises Inc",
    "wof:placetype":"venue"
},
  "geometry": {"coordinates":[-80.941547,29.029265],"type":"Point"}
}