{
  "type": "Feature",
  "properties": {
    "addr:full":"4056 Sunnyside Dr Middleburg FL 32068",
    "addr:housenumber":"4056",
    "addr:postcode":"32068",
    "addr:street":"Sunnyside Dr",
    "iso:country":"US",
    "sg:address":"4056 Sunnyside Dr",
    "sg:city":"Middleburg",
    "sg:classifiers":[
        {
            "category":"Freight",
            "type":"Transportation"
        }
    ],
    "sg:phone":"+1 904 282 4699",
    "sg:postcode":"32068",
    "sg:province":"FL",
    "sg:tags":[
        "operator",
        "local",
        "trucking"
    ],
    "wof:name":"Sinclair Trucking",
    "wof:placetype":"venue"
},
  "geometry": {"coordinates":[-81.85311900000001,30.0227],"type":"Point"}
}