{
  "type": "Feature",
  "properties": {
    "iso:country":"US",
    "sg:address":"11580 Hagen Ranch Rd",
    "sg:city":"Boynton Beach",
    "sg:classifiers":[
        {
            "category":"Farming",
            "subcategory":"Nursery",
            "type":"Manufacturing & Wholesale Goods"
        }
    ],
    "sg:phone":"+1 561 732 2071",
    "sg:postcode":"33437",
    "sg:province":"FL",
    "sg:tags":[
        "ornamental"
    ],
    "wof:name":"Alberts & Merkel Bros Inc",
    "wof:placetype":"venue"
},
  "geometry": {"coordinates":[-80.163918,26.504561],"type":"Point"}
}