{
  "type": "Feature",
  "properties": {
    "addr:full":"9765 S Orange Blossom Trl Orlando FL 32837",
    "addr:housenumber":"9765",
    "addr:postcode":"32837",
    "addr:street":"S Orange Blossom Trl",
    "iso:country":"US",
    "sg:address":"9765 S Orange Blossom Trl",
    "sg:city":"Orlando",
    "sg:classifiers":[
        {
            "category":"Wholesale",
            "subcategory":"Auto Parts",
            "type":"Manufacturing & Wholesale Goods"
        }
    ],
    "sg:phone":"+1 407 850 0004",
    "sg:postcode":"32837",
    "sg:province":"FL",
    "sg:tags":[
        "automobile",
        "rebuilt"
    ],
    "wof:name":"USA Reman",
    "wof:placetype":"venue"
},
  "geometry": {"coordinates":[-81.40463699999999,28.424513],"type":"Point"}
}