{
  "type": "Feature",
  "properties": {
    "iso:country":"US",
    "sg:address":"792 NW Waterlily Pl",
    "sg:city":"Jensen Beach",
    "sg:classifiers":[
        {
            "category":"Building & Trades",
            "subcategory":"Landscaping Services",
            "type":"Services"
        }
    ],
    "sg:phone":"+1 772 692 4984",
    "sg:postcode":"34957",
    "sg:province":"FL",
    "sg:tags":[
        "lawn",
        "maintenance",
        "grounds"
    ],
    "wof:name":"Jones Lawn Care",
    "wof:placetype":"venue"
},
  "geometry": {"coordinates":[-80.26472099999999,27.233234],"type":"Point"}
}