{
  "type": "Feature",
  "properties": {
    "iso:country":"US",
    "sg:address":"13290 NW 43rd Ave",
    "sg:city":"Opa Locka",
    "sg:classifiers":[
        {
            "category":"Restaurant",
            "type":"Food & Drink"
        }
    ],
    "sg:phone":"+1 305 688 1606",
    "sg:postcode":"33054",
    "sg:province":"FL",
    "wof:name":"Esquina Carbiena",
    "wof:placetype":"venue"
},
  "geometry": {"coordinates":[-80.269402,25.8946],"type":"Point"}
}