{
  "type": "Feature",
  "properties": {
    "iso:country":"US",
    "sg:address":"2045 Sweet St",
    "sg:city":"Navarre",
    "sg:classifiers":[
        {
            "category":"Home & Garden",
            "subcategory":"Furniture",
            "type":"Retail Goods"
        }
    ],
    "sg:phone":"+1 850 685 3419",
    "sg:postcode":"32566",
    "sg:province":"FL",
    "sg:tags":[
        "top",
        "counter"
    ],
    "wof:name":"Master Stone Design",
    "wof:placetype":"venue"
},
  "geometry": {"coordinates":[-86.804608,30.407838],"type":"Point"}
}