{
  "type": "Feature",
  "properties": {
    "iso:country":"US",
    "sg:address":"820 NE 44th St",
    "sg:city":"Ocala",
    "sg:classifiers":[
        {
            "category":"Building & Trades",
            "subcategory":"Plumbing",
            "type":"Services"
        }
    ],
    "sg:phone":"+1 352 629 5202",
    "sg:postcode":"34479",
    "sg:province":"FL",
    "sg:tags":[
        "contractor"
    ],
    "wof:name":"Florida Air Coolers Inc",
    "wof:placetype":"venue"
},
  "geometry": {"coordinates":[-82.127528,29.231871],"type":"Point"}
}