{
  "type": "Feature",
  "properties": {
    "addr:full":"722 E 46th St Hialeah FL 33013",
    "addr:housenumber":"722",
    "addr:postcode":"33013",
    "addr:street":"E 46Th St",
    "iso:country":"US",
    "sg:address":"722 E 46th St",
    "sg:city":"Hialeah",
    "sg:classifiers":[
        {
            "category":"Building & Trades",
            "subcategory":"Construction",
            "type":"Services"
        }
    ],
    "sg:phone":"+1 305 685 6692",
    "sg:postcode":"33013",
    "sg:province":"FL",
    "sg:tags":[
        "house"
    ],
    "wof:name":"Inca Marine Construction",
    "wof:placetype":"venue"
},
  "geometry": {"coordinates":[-80.267143,25.864479],"type":"Point"}
}