{
  "type": "Feature",
  "properties": {
    "iso:country":"US",
    "sg:address":"6271 N Dixie Hwy",
    "sg:city":"Fort Lauderdale",
    "sg:classifiers":[
        {
            "category":"Real Estate",
            "subcategory":"Real Estate Operator",
            "type":"Services"
        }
    ],
    "sg:phone":"+1 954 772 7616",
    "sg:postcode":"33334",
    "sg:province":"FL",
    "sg:tags":[
        "mobile",
        "home",
        "community"
    ],
    "wof:name":"Cypress Creek Mobile Country",
    "wof:placetype":"venue"
},
  "geometry": {"coordinates":[-80.132785,26.203789],"type":"Point"}
}