{
  "type": "Feature",
  "properties": {
    "iso:country":"US",
    "sg:address":"4811 Atlantic Blvd",
    "sg:city":"Jacksonville",
    "sg:classifiers":[
        {
            "category":"Professional",
            "subcategory":"Lawyer & Legal Services",
            "type":"Services"
        }
    ],
    "sg:phone":"+1 904 858 9447",
    "sg:postcode":"32207",
    "sg:province":"FL",
    "wof:name":"Erik Berger",
    "wof:placetype":"venue"
},
  "geometry": {"coordinates":[-81.615326,30.309196],"type":"Point"}
}