{
  "type": "Feature",
  "properties": {
    "iso:country":"US",
    "sg:address":"7774 S George Blvd",
    "sg:city":"Sebring",
    "sg:classifiers":[
        {
            "category":"Building & Trades",
            "subcategory":"Construction",
            "type":"Services"
        }
    ],
    "sg:phone":"+1 863 471 1709",
    "sg:postcode":"33875",
    "sg:province":"FL",
    "sg:tags":[
        "general",
        "contractor"
    ],
    "wof:name":"Action General Contracting Inc",
    "wof:placetype":"venue"
},
  "geometry": {"coordinates":[-81.42364499999999,27.433245],"type":"Point"}
}