{
  "type": "Feature",
  "properties": {
    "addr:full":"300 Jeffords St Clearwater FL 33756",
    "addr:housenumber":"300",
    "addr:postcode":"33756",
    "addr:street":"Jeffords St",
    "iso:country":"US",
    "sg:address":"300 Jeffords St",
    "sg:city":"Clearwater",
    "sg:classifiers":[
        {
            "category":"Health Services",
            "subcategory":"Doctor",
            "type":"Services"
        }
    ],
    "sg:phone":"+1 727 441 1524",
    "sg:postcode":"33756",
    "sg:province":"FL",
    "sg:tags":[
        "physician",
        "surgeon"
    ],
    "wof:name":"Anesthesia Associates",
    "wof:placetype":"venue"
},
  "geometry": {"coordinates":[-82.80253399999999,27.953663],"type":"Point"}
}