{
  "type": "Feature",
  "properties": {
    "addr:full":"911 N Broadwalk Hollywood FL 33019",
    "addr:housenumber":"911",
    "addr:postcode":"33019",
    "addr:street":"N Broadwalk",
    "iso:country":"US",
    "sg:address":"911 N Broadwalk",
    "sg:city":"Hollywood",
    "sg:classifiers":[
        {
            "category":"Restaurant",
            "type":"Food & Drink"
        }
    ],
    "sg:phone":"+1 954 920 0033",
    "sg:postcode":"33019",
    "sg:province":"FL",
    "wof:name":"Labrochetterie",
    "wof:placetype":"venue"
},
  "geometry": {"coordinates":[-80.11521500000001,26.018241],"type":"Point"}
}