{
  "type": "Feature",
  "properties": {
    "iso:country":"US",
    "sg:address":"645 Cypress Rd",
    "sg:city":"Vero Beach",
    "sg:classifiers":[
        {
            "category":"Professional",
            "subcategory":"Management & Consulting",
            "type":"Services"
        }
    ],
    "sg:phone":"+1 772 492 0742",
    "sg:postcode":"32963",
    "sg:province":"FL",
    "sg:tags":[
        "business"
    ],
    "wof:name":"C To C Merchandising",
    "wof:placetype":"venue"
},
  "geometry": {"coordinates":[-80.361694,27.656185],"type":"Point"}
}