{
  "type": "Feature",
  "properties": {
    "addr:full":"12012 Holbrook Dr Port Richey FL 34667",
    "addr:housenumber":"12012",
    "addr:postcode":"34667",
    "addr:street":"Holbrook Dr",
    "iso:country":"US",
    "sg:address":"12012 Holbrook Dr",
    "sg:city":"Port Richey",
    "sg:classifiers":[
        {
            "category":"Personal",
            "subcategory":"Beauty Salon",
            "type":"Services"
        }
    ],
    "sg:phone":"+1 727 697 2133",
    "sg:postcode":"34667",
    "sg:province":"FL",
    "sg:tags":[
        "shop",
        "merchandise"
    ],
    "wof:name":"Above & Beyond Cleaning Svc",
    "wof:placetype":"venue"
},
  "geometry": {"coordinates":[-82.67411199999999,28.330969],"type":"Point"}
}