{
  "type": "Feature",
  "properties": {
    "addr:full":"8018 Mobilaire Dr Orlando FL 32822",
    "addr:housenumber":"8018",
    "addr:postcode":"32822",
    "addr:street":"Mobilaire Dr",
    "iso:country":"US",
    "sg:address":"8018 Mobilaire Dr",
    "sg:city":"Orlando",
    "sg:classifiers":[
        {
            "category":"Building & Trades",
            "subcategory":"Construction",
            "type":"Services"
        }
    ],
    "sg:phone":"+1 407 275 3998",
    "sg:postcode":"32822",
    "sg:province":"FL",
    "sg:tags":[
        "home",
        "improvement"
    ],
    "wof:name":"Cj's Maintenance & Janitorial",
    "wof:placetype":"venue"
},
  "geometry": {"coordinates":[-81.28007100000001,28.491368],"type":"Point"}
}