{
  "type": "Feature",
  "properties": {
    "addr:full":"403 S Pinellas Ave Tarpon Springs FL 34689",
    "addr:housenumber":"403",
    "addr:postcode":"34689",
    "addr:street":"S Pinellas Ave",
    "iso:country":"US",
    "sg:address":"403 S Pinellas Ave",
    "sg:city":"Tarpon Springs",
    "sg:classifiers":[
        {
            "category":"Shopping",
            "subcategory":"Clothing, Apparel, & Fashions",
            "type":"Retail Goods"
        }
    ],
    "sg:phone":"+1 727 943 8336",
    "sg:postcode":"34689",
    "sg:province":"FL",
    "sg:tags":[
        "dressmaker"
    ],
    "wof:name":"Mrs G's",
    "wof:placetype":"venue"
},
  "geometry": {"coordinates":[-82.75653800000001,28.142272],"type":"Point"}
}