{
  "type": "Feature",
  "properties": {
    "iso:country":"US",
    "sg:address":"671 E 44th St",
    "sg:city":"Hialeah",
    "sg:classifiers":[
        {
            "category":"Building & Trades",
            "subcategory":"Construction",
            "type":"Services"
        }
    ],
    "sg:phone":"+1 305 687 5674",
    "sg:postcode":"33013",
    "sg:province":"FL",
    "sg:tags":[
        "contractor"
    ],
    "wof:name":"Marble Plus Tile Inc",
    "wof:placetype":"venue"
},
  "geometry": {"coordinates":[-80.26997,25.862712],"type":"Point"}
}