{
  "type": "Feature",
  "properties": {
    "addr:full":"502 North St New Smyrna Beach FL 32168",
    "addr:housenumber":"502",
    "addr:postcode":"32168",
    "addr:street":"North St",
    "iso:country":"US",
    "sg:address":"502 North St",
    "sg:city":"New Smyrna Beach",
    "sg:classifiers":[
        {
            "category":"Recreation",
            "type":"Entertainment"
        }
    ],
    "sg:phone":"+1 386 428 0777",
    "sg:postcode":"32168",
    "sg:province":"FL",
    "sg:tags":[
        "parlor",
        "billiard"
    ],
    "wof:name":"Dally's Billiards",
    "wof:placetype":"venue"
},
  "geometry": {"coordinates":[-80.95349,29.06555],"type":"Point"}
}