{
  "type": "Feature",
  "properties": {
    "iso:country":"US",
    "sg:address":"3850 N Miami Ave",
    "sg:city":"Miami",
    "sg:classifiers":[
        {
            "category":"Shopping",
            "subcategory":"Clothing, Apparel, & Fashions",
            "type":"Retail Goods"
        }
    ],
    "sg:phone":"+1 305 572 1240",
    "sg:postcode":"33127",
    "sg:province":"FL",
    "wof:name":"The Fechheimer Brothers Co",
    "wof:placetype":"venue"
},
  "geometry": {"coordinates":[-80.19547799999999,25.81226],"type":"Point"}
}