{
  "type": "Feature",
  "properties": {
    "addr:full":"1372 Bennett Dr Longwood FL 32750",
    "addr:housenumber":"1372",
    "addr:postcode":"32750",
    "addr:street":"Bennett Dr",
    "iso:country":"US",
    "sg:address":"1372 Bennett Dr",
    "sg:city":"Longwood",
    "sg:classifiers":[
        {
            "category":"Wholesale",
            "subcategory":"Machinery & Supplies",
            "type":"Manufacturing & Wholesale Goods"
        },
        {
            "category":"Wholesale",
            "subcategory":"Durable Goods & Equipment",
            "type":"Manufacturing & Wholesale Goods"
        }
    ],
    "sg:phone":"+1 407 834 6782",
    "sg:postcode":"32750",
    "sg:province":"FL",
    "sg:tags":[
        "fire",
        "extinguisher",
        "fighting"
    ],
    "wof:name":"A-1 Fire Safety",
    "wof:placetype":"venue"
},
  "geometry": {"coordinates":[-81.35382199999999,28.690406],"type":"Point"}
}