{
  "type": "Feature",
  "properties": {
    "iso:country":"US",
    "sg:address":"3530 Okeechobee Rd",
    "sg:city":"Fort Pierce",
    "sg:classifiers":[
        {
            "category":"Health Services",
            "subcategory":"Doctor",
            "type":"Services"
        }
    ],
    "sg:phone":"+1 772 464 4303",
    "sg:postcode":"34947",
    "sg:province":"FL",
    "sg:tags":[
        "medical"
    ],
    "wof:name":"Primary Care Medical Services",
    "wof:placetype":"venue"
},
  "geometry": {"coordinates":[-80.361242,27.429343],"type":"Point"}
}