{
  "type": "Feature",
  "properties": {
    "iso:country":"US",
    "sg:address":"808 N Main St",
    "sg:city":"Bushnell",
    "sg:classifiers":[
        {
            "category":"Home & Garden",
            "subcategory":"Building Materials",
            "type":"Retail Goods"
        }
    ],
    "sg:phone":"+1 352 793 6071",
    "sg:postcode":"33513",
    "sg:province":"FL",
    "wof:name":"Scottys 408",
    "wof:placetype":"venue"
},
  "geometry": {"coordinates":[-82.111569,28.676363],"type":"Point"}
}