{
  "type": "Feature",
  "properties": {
    "addr:full":"215 N Federal Hwy Boca Raton FL 33432",
    "addr:housenumber":"215",
    "addr:postcode":"33432",
    "addr:street":"N Federal Hwy",
    "iso:country":"US",
    "sg:address":"215 N Federal Hwy",
    "sg:city":"Boca Raton",
    "sg:classifiers":[
        {
            "category":"Real Estate",
            "subcategory":"Real Estate Agent",
            "type":"Services"
        },
        {
            "category":"Real Estate",
            "subcategory":"Real Estate Operator",
            "type":"Services"
        }
    ],
    "sg:phone":"+1 561 392 9594",
    "sg:postcode":"33432",
    "sg:province":"FL",
    "sg:tags":[
        "building",
        "residential",
        "commercial"
    ],
    "wof:name":"Investments Limited Rsdntl",
    "wof:placetype":"venue"
},
  "geometry": {"coordinates":[-80.08653200000001,26.353099],"type":"Point"}
}