{
  "type": "Feature",
  "properties": {
    "iso:country":"US",
    "sg:address":"1600 E 8th Ave",
    "sg:city":"Tampa",
    "sg:classifiers":[
        {
            "category":"Real Estate",
            "subcategory":"Developer",
            "type":"Services"
        }
    ],
    "sg:phone":"+1 813 242 4314",
    "sg:postcode":"33605",
    "sg:province":"FL",
    "sg:website":"www.centroybor.com",
    "wof:name":"Steiner & Associates Inc",
    "wof:placetype":"venue"
},
  "geometry": {"coordinates":[-82.442802,27.961073],"type":"Point"}
}