{
  "type": "Feature",
  "properties": {
    "addr:full":"2700 W Silver Springs Blvd Ocala FL 34475",
    "addr:housenumber":"2700",
    "addr:postcode":"34475",
    "addr:street":"W Silver Springs Blvd",
    "iso:country":"US",
    "sg:address":"2700 W Silver Springs Blvd",
    "sg:city":"Ocala",
    "sg:classifiers":[
        {
            "category":"Shopping",
            "type":"Retail Goods"
        }
    ],
    "sg:phone":"+1 352 622 2755",
    "sg:postcode":"34475",
    "sg:province":"FL",
    "sg:tags":[
        "merchandise"
    ],
    "wof:name":"Mattress Whse.",
    "wof:placetype":"venue"
},
  "geometry": {"coordinates":[-82.168671,29.186171],"type":"Point"}
}