{
  "type": "Feature",
  "properties": {
    "iso:country":"US",
    "sg:address":"5160 N Kaliga Dr",
    "sg:city":"Saint Cloud",
    "sg:classifiers":[
        {
            "category":"Building & Trades",
            "subcategory":"Construction",
            "type":"Services"
        }
    ],
    "sg:phone":"+1 407 957 9181",
    "sg:postcode":"34771",
    "sg:province":"FL",
    "sg:tags":[
        "concrete",
        "contractor"
    ],
    "wof:name":"Michael Center Concrete",
    "wof:placetype":"venue"
},
  "geometry": {"coordinates":[-81.23909,28.327145],"type":"Point"}
}