{
  "type": "Feature",
  "properties": {
    "addr:full":"119 S Lake Ave Avon Park FL 33825",
    "addr:housenumber":"119",
    "addr:postcode":"33825",
    "addr:street":"S Lake Ave",
    "iso:country":"US",
    "sg:address":"119 S Lake Ave",
    "sg:city":"Avon Park",
    "sg:classifiers":[
        {
            "category":"Personal",
            "subcategory":"Beauty Salon",
            "type":"Services"
        }
    ],
    "sg:phone":"+1 863 453 4630",
    "sg:postcode":"33825",
    "sg:province":"FL",
    "wof:name":"Anita's Beauty & Barber Shop",
    "wof:placetype":"venue"
},
  "geometry": {"coordinates":[-81.50209,27.59452],"type":"Point"}
}