{
  "type": "Feature",
  "properties": {
    "addr:full":"4520 Shirley Ave Jacksonville FL 32210",
    "addr:housenumber":"4520",
    "addr:postcode":"32210",
    "addr:street":"Shirley Ave",
    "iso:country":"US",
    "sg:address":"4520 Shirley Ave",
    "sg:city":"Jacksonville",
    "sg:classifiers":[
        {
            "category":"Building & Trades",
            "subcategory":"Electrical",
            "type":"Services"
        }
    ],
    "sg:phone":"+1 904 389 6761",
    "sg:postcode":"32210",
    "sg:province":"FL",
    "sg:tags":[
        "electrical",
        "contractor"
    ],
    "wof:name":"Electrical Associates",
    "wof:placetype":"venue"
},
  "geometry": {"coordinates":[-81.721434,30.28394],"type":"Point"}
}