{
  "type": "Feature",
  "properties": {
    "iso:country":"US",
    "sg:address":"3640 NW 118th Ave",
    "sg:city":"Pompano Beach",
    "sg:classifiers":[
        {
            "category":"Building & Trades",
            "subcategory":"Construction",
            "type":"Services"
        }
    ],
    "sg:phone":"+1 954 755 7110",
    "sg:postcode":"33065",
    "sg:province":"FL",
    "sg:tags":[
        "floor",
        "laying",
        "contractor"
    ],
    "wof:name":"Petes Carpet Co",
    "wof:placetype":"venue"
},
  "geometry": {"coordinates":[-80.284052,26.274887],"type":"Point"}
}