{
  "type": "Feature",
  "properties": {
    "addr:full":"3111 S Dixie Hwy West Palm Beach FL 33405",
    "addr:housenumber":"3111",
    "addr:postcode":"33405",
    "addr:street":"S Dixie Hwy",
    "iso:country":"US",
    "sg:address":"3111 S Dixie Hwy",
    "sg:city":"West Palm Beach",
    "sg:classifiers":[
        {
            "category":"Government",
            "subcategory":"Office",
            "type":"Public Place"
        }
    ],
    "sg:phone":"+1 561 837 5412",
    "sg:postcode":"33405",
    "sg:province":"FL",
    "sg:tags":[
        "state",
        "resource"
    ],
    "wof:name":"Workers' Compensation Div",
    "wof:placetype":"venue"
},
  "geometry": {"coordinates":[-80.05460600000001,26.683976],"type":"Point"}
}