{
  "type": "Feature",
  "properties": {
    "iso:country":"US",
    "sg:address":"12200 W Colonial Dr",
    "sg:city":"Winter Garden",
    "sg:classifiers":[
        {
            "category":"Wholesale",
            "subcategory":"Durable Goods & Equipment",
            "type":"Manufacturing & Wholesale Goods"
        }
    ],
    "sg:phone":"+1 407 654 0213",
    "sg:postcode":"34787",
    "sg:province":"FL",
    "sg:tags":[
        "representative",
        "manufacturer"
    ],
    "wof:name":"Tab Products LLC",
    "wof:placetype":"venue"
},
  "geometry": {"coordinates":[-81.562398,28.551219],"type":"Point"}
}