{
  "type": "Feature",
  "properties": {
    "addr:full":"576 1st Ave N St Petersburg FL 33701",
    "addr:housenumber":"576",
    "addr:postcode":"33701",
    "addr:street":"1St Ave N",
    "iso:country":"US",
    "sg:address":"576 1st Ave N",
    "sg:city":"St Petersburg",
    "sg:classifiers":[
        {
            "category":"Shopping",
            "type":"Retail Goods"
        }
    ],
    "sg:phone":"+1 727 894 4082",
    "sg:postcode":"33701",
    "sg:province":"FL",
    "sg:tags":[
        "stamp",
        "collector",
        "for",
        "merchandise"
    ],
    "wof:name":"Stamp Place",
    "wof:placetype":"venue"
},
  "geometry": {"coordinates":[-82.64057200000001,27.772005],"type":"Point"}
}