{
  "type": "Feature",
  "properties": {
    "iso:country":"US",
    "sg:address":"3711 W Azeele St",
    "sg:city":"Tampa",
    "sg:classifiers":[
        {
            "category":"Professional",
            "subcategory":"Lawyer & Legal Services",
            "type":"Services"
        }
    ],
    "sg:phone":"+1 813 353 1616",
    "sg:postcode":"33609",
    "sg:province":"FL",
    "wof:name":"Kevin Burns Atty",
    "wof:placetype":"venue"
},
  "geometry": {"coordinates":[-82.50553499999999,27.941302],"type":"Point"}
}