{
  "type": "Feature",
  "properties": {
    "addr:full":"1876 Trade Center Way Naples FL 34109",
    "addr:housenumber":"1876",
    "addr:postcode":"34109",
    "addr:street":"Trade Center Way",
    "iso:country":"US",
    "sg:address":"1876 Trade Center Way",
    "sg:city":"Naples",
    "sg:classifiers":[
        {
            "category":"Professional",
            "subcategory":"Engineering",
            "type":"Services"
        }
    ],
    "sg:phone":"+1 239 596 3200",
    "sg:postcode":"34109",
    "sg:province":"FL",
    "sg:tags":[
        "engineer"
    ],
    "wof:name":"W J Johnson & Assoc",
    "wof:placetype":"venue"
},
  "geometry": {"coordinates":[-81.773163,26.225188],"type":"Point"}
}