{
  "type": "Feature",
  "properties": {
    "iso:country":"US",
    "sg:address":"6063 Timberwood Cir Apt 301",
    "sg:city":"Fort Myers",
    "sg:classifiers":[
        {
            "category":"Personal",
            "type":"Services"
        }
    ],
    "sg:phone":"+1 239 454 8420",
    "sg:postcode":"33908",
    "sg:province":"FL",
    "sg:tags":[
        "party",
        "planning",
        "event"
    ],
    "wof:name":"Friendly Faces",
    "wof:placetype":"venue"
},
  "geometry": {"coordinates":[-81.855797,26.498301],"type":"Point"}
}