{
  "type": "Feature",
  "properties": {
    "addr:full":"7275 SW 61st St Miami FL 33143",
    "addr:housenumber":"7275",
    "addr:postcode":"33143",
    "addr:street":"Sw 61St St",
    "iso:country":"US",
    "sg:address":"7275 SW 61st St",
    "sg:city":"Miami",
    "sg:classifiers":[
        {
            "category":"Real Estate",
            "subcategory":"Real Estate Agent",
            "type":"Services"
        }
    ],
    "sg:phone":"+1 305 662 4224",
    "sg:postcode":"33143",
    "sg:province":"FL",
    "sg:tags":[
        "appraiser"
    ],
    "wof:name":"Chastain & Co Inc",
    "wof:placetype":"venue"
},
  "geometry": {"coordinates":[-80.311181,25.713453],"type":"Point"}
}