{
  "type": "Feature",
  "properties": {
    "iso:country":"US",
    "sg:address":"5905 S Kirkman Rd",
    "sg:city":"Orlando",
    "sg:classifiers":[
        {
            "category":"Professional",
            "type":"Services"
        }
    ],
    "sg:phone":"+1 407 351 1015",
    "sg:postcode":"32811",
    "sg:province":"FL",
    "sg:tags":[
        "establishment"
    ],
    "wof:name":"Dimension Development Co",
    "wof:placetype":"venue"
},
  "geometry": {"coordinates":[-81.45871699999999,28.476963],"type":"Point"}
}