{
  "type": "Feature",
  "properties": {
    "addr:full":"3987 N W St Pensacola FL 32505",
    "addr:housenumber":"3987",
    "addr:postcode":"32505",
    "addr:street":"N W St",
    "iso:country":"US",
    "sg:address":"3987 N W St",
    "sg:city":"Pensacola",
    "sg:classifiers":[
        {
            "category":"Banks & Credit Unions",
            "subcategory":"Investment Brokerage",
            "type":"Services"
        }
    ],
    "sg:phone":"+1 850 439 6614",
    "sg:postcode":"32505",
    "sg:province":"FL",
    "wof:name":"Baroco Investments",
    "wof:placetype":"venue"
},
  "geometry": {"coordinates":[-87.24994599999999,30.454393],"type":"Point"}
}