{
  "type": "Feature",
  "properties": {
    "iso:country":"US",
    "sg:address":"1632 3rd St",
    "sg:city":"Leesburg",
    "sg:classifiers":[
        {
            "category":"Manufacturing",
            "subcategory":"Metals",
            "type":"Manufacturing & Wholesale Goods"
        }
    ],
    "sg:phone":"+1 352 787 4401",
    "sg:postcode":"34748",
    "sg:province":"FL",
    "sg:tags":[
        "building",
        "product",
        "exterior",
        "aluminum",
        "mfg"
    ],
    "wof:name":"Metals USA Building Pdts LP",
    "wof:placetype":"venue"
},
  "geometry": {"coordinates":[-81.85145799999999,28.817475],"type":"Point"}
}