{
  "type": "Feature",
  "properties": {
    "addr:full":"713 W Fribley St Tampa FL 33603",
    "addr:housenumber":"713",
    "addr:postcode":"33603",
    "addr:street":"W Fribley St",
    "iso:country":"US",
    "sg:address":"713 W Fribley St",
    "sg:city":"Tampa",
    "sg:classifiers":[
        {
            "category":"Utilities",
            "subcategory":"Electric",
            "type":"Services"
        }
    ],
    "sg:phone":"+1 813 225 1056",
    "sg:postcode":"33603",
    "sg:province":"FL",
    "sg:tags":[
        "equipment-repair"
    ],
    "wof:name":"Reyna's Heating And Air",
    "wof:placetype":"venue"
},
  "geometry": {"coordinates":[-82.467901,27.974572],"type":"Point"}
}