{
  "type": "Feature",
  "properties": {
    "iso:country":"US",
    "sg:address":"10123 W Atlantic Blvd",
    "sg:city":"Pompano Beach",
    "sg:classifiers":[
        {
            "category":"Retail",
            "subcategory":"Auto Repair",
            "type":"Services"
        }
    ],
    "sg:phone":"+1 954 255 3952",
    "sg:postcode":"33071",
    "sg:province":"FL",
    "sg:tags":[
        "general"
    ],
    "wof:name":"Efay Automotive Inc",
    "wof:placetype":"venue"
},
  "geometry": {"coordinates":[-80.261413,26.240801],"type":"Point"}
}