{
  "type": "Feature",
  "properties": {
    "iso:country":"US",
    "sg:address":"306 S Pegasus Ave",
    "sg:city":"Clearwater",
    "sg:classifiers":[
        {
            "category":"Banks & Credit Unions",
            "subcategory":"Bank",
            "type":"Services"
        }
    ],
    "sg:phone":"+1 727 447 2151",
    "sg:postcode":"33765",
    "sg:province":"FL",
    "sg:tags":[
        "loan",
        "broker",
        "real estate"
    ],
    "wof:name":"Magna Mortgage & Investments",
    "wof:placetype":"venue"
},
  "geometry": {"coordinates":[-82.760882,27.960642],"type":"Point"}
}