{
  "type": "Feature",
  "properties": {
    "addr:full":"5100 SW 41st St Hollywood FL 33023",
    "addr:housenumber":"5100",
    "addr:postcode":"hollywood;33023",
    "addr:street":"Sw 41St St",
    "iso:country":"US",
    "sg:address":"5100 SW 41st St",
    "sg:city":"Hollywood",
    "sg:classifiers":[
        {
            "category":"Real Estate",
            "subcategory":"Real Estate Services",
            "type":"Services"
        },
        {
            "category":"Real Estate",
            "subcategory":"Real Estate Agent",
            "type":"Services"
        }
    ],
    "sg:phone":"+1 754 816 3124",
    "sg:postcode":"33023",
    "sg:province":"FL",
    "sg:tags":[
        "management"
    ],
    "wof:name":"Condado Real",
    "wof:placetype":"venue"
},
  "geometry": {"coordinates":[-80.19355299999999,25.973167],"type":"Point"}
}