{
  "type": "Feature",
  "properties": {
    "iso:country":"US",
    "sg:address":"9051 Tamiami Trl N",
    "sg:city":"Naples",
    "sg:classifiers":[
        {
            "category":"Wholesale",
            "subcategory":"Construction Materials",
            "type":"Manufacturing & Wholesale Goods"
        }
    ],
    "sg:phone":"+1 239 594 2299",
    "sg:postcode":"34108",
    "sg:province":"FL",
    "sg:tags":[
        "kitchen",
        "imported",
        "cabinet"
    ],
    "wof:name":"Siematic of Naples",
    "wof:placetype":"venue"
},
  "geometry": {"coordinates":[-81.80131799999999,26.252341],"type":"Point"}
}