{
  "type": "Feature",
  "properties": {
    "iso:country":"US",
    "sg:address":"6161 SW 19th St",
    "sg:city":"Pompano Beach",
    "sg:classifiers":[
        {
            "category":"Personal",
            "type":"Services"
        }
    ],
    "sg:phone":"+1 954 895 2612",
    "sg:postcode":"33068",
    "sg:province":"FL",
    "wof:name":"Tres Estrellas Inc",
    "wof:placetype":"venue"
},
  "geometry": {"coordinates":[-80.206806,26.203079],"type":"Point"}
}