{
  "type": "Feature",
  "properties": {
    "iso:country":"US",
    "sg:address":"401 S Cocoa Blvd",
    "sg:city":"Cocoa",
    "sg:classifiers":[
        {
            "category":"Retail",
            "subcategory":"Auto Repair",
            "type":"Services"
        }
    ],
    "sg:phone":"+1 321 636 3503",
    "sg:postcode":"32922",
    "sg:province":"FL",
    "sg:tags":[
        "muffler",
        "exhaust",
        "system"
    ],
    "wof:name":"Meineke Car Care Ctr",
    "wof:placetype":"venue"
},
  "geometry": {"coordinates":[-80.73196799999999,28.353353],"type":"Point"}
}