{
  "type": "Feature",
  "properties": {
    "addr:full":"12846 Greenmeadow Pl Jacksonville FL 32246",
    "addr:housenumber":"12846",
    "addr:postcode":"32246",
    "addr:street":"Greenmeadow Pl",
    "iso:country":"US",
    "sg:address":"12846 Greenmeadow Pl",
    "sg:city":"Jacksonville",
    "sg:classifiers":[
        {
            "category":"Professional",
            "type":"Services"
        }
    ],
    "sg:phone":"+1 904 221 4136",
    "sg:postcode":"32246",
    "sg:province":"FL",
    "wof:name":"D818 Inc",
    "wof:placetype":"venue"
},
  "geometry": {"coordinates":[-81.46769999999999,30.316431],"type":"Point"}
}