{
  "type": "Feature",
  "properties": {
    "addr:full":"2126 Wallace Branch Rd Plant City FL 33565",
    "addr:housenumber":"2126",
    "addr:postcode":"33565",
    "addr:street":"Wallace Branch Rd",
    "iso:country":"US",
    "sg:address":"2126 Wallace Branch Rd",
    "sg:city":"Plant City",
    "sg:classifiers":[
        {
            "category":"Education",
            "subcategory":"Special Training",
            "type":"Public Place"
        }
    ],
    "sg:phone":"+1 813 764 8212",
    "sg:postcode":"33565",
    "sg:province":"FL",
    "sg:tags":[
        "ceramics"
    ],
    "wof:name":"DMT Ceramics & More",
    "wof:placetype":"venue"
},
  "geometry": {"coordinates":[-82.161317,28.034023],"type":"Point"}
}