{
  "type": "Feature",
  "properties": {
    "addr:full":"726 NE 8 Ave Gainesville FL 32601",
    "addr:housenumber":"726",
    "addr:postcode":"32601",
    "addr:street":"Ne 8 Ave",
    "iso:country":"US",
    "sg:address":"726 NE 8 Ave",
    "sg:city":"Gainesville",
    "sg:classifiers":[
        {
            "category":"Building & Trades",
            "subcategory":"Cleaning & Sanitation",
            "type":"Services"
        }
    ],
    "sg:phone":"+1 352 384 0123",
    "sg:postcode":"32601",
    "sg:province":"FL",
    "sg:tags":[
        "house"
    ],
    "wof:name":"A Personal Touch By Patricia",
    "wof:placetype":"venue"
},
  "geometry": {"coordinates":[-82.31662300000001,29.659357],"type":"Point"}
}