{
  "type": "Feature",
  "properties": {
    "iso:country":"US",
    "sg:address":"4265 NW 9th St",
    "sg:city":"Delray Beach",
    "sg:classifiers":[
        {
            "category":"Banks & Credit Unions",
            "subcategory":"Bank",
            "type":"Services"
        }
    ],
    "sg:phone":"+1 561 752 5696",
    "sg:postcode":"33445",
    "sg:province":"FL",
    "sg:tags":[
        "loan",
        "real estate"
    ],
    "wof:name":"SBCS Mortgage",
    "wof:placetype":"venue"
},
  "geometry": {"coordinates":[-80.11322800000001,26.475169],"type":"Point"}
}