{
  "type": "Feature",
  "properties": {
    "iso:country":"US",
    "sg:address":"7531 S Orange Blossom Trl",
    "sg:city":"Orlando",
    "sg:classifiers":[
        {
            "category":"Professional",
            "subcategory":"Employment Agencies",
            "type":"Services"
        }
    ],
    "sg:phone":"+1 407 235 1522",
    "sg:postcode":"32809",
    "sg:province":"FL",
    "sg:tags":[
        "opportunity"
    ],
    "sg:website":"http://www.jobspartnershipfl.org",
    "wof:name":"Jobs Partnership Of Florida Inc",
    "wof:placetype":"venue"
},
  "geometry": {"coordinates":[-81.39892500000001,28.45708],"type":"Point"}
}