{
  "type": "Feature",
  "properties": {
    "iso:country":"US",
    "sg:address":"9527 Bone Bluff Dr",
    "sg:city":"Navarre",
    "sg:classifiers":[
        {
            "category":"Building & Trades",
            "subcategory":"Construction",
            "type":"Services"
        }
    ],
    "sg:phone":"+1 850 936 4101",
    "sg:postcode":"32566",
    "sg:province":"FL",
    "sg:tags":[
        "tile",
        "dealer"
    ],
    "wof:name":"Ceramic Tile & Stone",
    "wof:placetype":"venue"
},
  "geometry": {"coordinates":[-86.827793,30.42848],"type":"Point"}
}