{
  "type": "Feature",
  "properties": {
    "addr:full":"2760 SW 32nd Ave Miami FL 33133",
    "addr:housenumber":"2760",
    "addr:postcode":"33133",
    "addr:street":"Sw 32Nd Ave",
    "iso:country":"US",
    "sg:address":"2760 SW 32nd Ave",
    "sg:city":"Miami",
    "sg:classifiers":[
        {
            "category":"Building & Trades",
            "subcategory":"Landscaping Services",
            "type":"Services"
        }
    ],
    "sg:phone":"+1 305 529 0369",
    "sg:postcode":"33133",
    "sg:province":"FL",
    "wof:name":"Alberto R Montes Lawn Mntnc",
    "wof:placetype":"venue"
},
  "geometry": {"coordinates":[-80.24612500000001,25.740687],"type":"Point"}
}