{
  "type": "Feature",
  "properties": {
    "addr:full":"3344 Edgewater Dr Orlando FL 32804",
    "addr:housenumber":"3344",
    "addr:postcode":"32804",
    "addr:street":"Edgewater Dr",
    "iso:country":"US",
    "sg:address":"3344 Edgewater Dr",
    "sg:city":"Orlando",
    "sg:classifiers":[
        {
            "category":"Personal",
            "subcategory":"Beauty Salon",
            "type":"Services"
        }
    ],
    "sg:phone":"+1 407 843 3388",
    "sg:postcode":"32804",
    "sg:province":"FL",
    "sg:tags":[
        "shop"
    ],
    "wof:name":"Hobnobbers Inc",
    "wof:placetype":"venue"
},
  "geometry": {"coordinates":[-81.389668,28.581668],"type":"Point"}
}