{
  "type": "Feature",
  "properties": {
    "iso:country":"US",
    "sg:address":"11557 SW 71st Cir",
    "sg:city":"Ocala",
    "sg:classifiers":[
        {
            "category":"Retail",
            "subcategory":"Repair Shop",
            "type":"Services"
        }
    ],
    "sg:phone":"+1 352 237 7025",
    "sg:postcode":"34476",
    "sg:province":"FL",
    "sg:tags":[
        "small",
        "major",
        "appliance",
        "refinishing"
    ],
    "wof:name":"Bawden Appliance Service",
    "wof:placetype":"venue"
},
  "geometry": {"coordinates":[-82.237967,29.054387],"type":"Point"}
}