{
  "type": "Feature",
  "properties": {
    "iso:country":"US",
    "sg:address":"335 N Clayton St",
    "sg:city":"Mount Dora",
    "sg:classifiers":[
        {
            "category":"Professional",
            "subcategory":"Art Services",
            "type":"Services"
        }
    ],
    "sg:phone":"+1 352 735 2848",
    "sg:postcode":"32757",
    "sg:province":"FL",
    "sg:tags":[
        "home",
        "painting",
        "for",
        "custom"
    ],
    "wof:name":"Fee FI Faux",
    "wof:placetype":"venue"
},
  "geometry": {"coordinates":[-81.63856199999999,28.800262],"type":"Point"}
}