{
  "type": "Feature",
  "properties": {
    "addr:full":"1802 N Orange Ave Orlando FL 32804",
    "addr:housenumber":"1802",
    "addr:postcode":"32804",
    "addr:street":"N Orange Ave",
    "iso:country":"US",
    "sg:address":"1802 N Orange Ave",
    "sg:city":"Orlando",
    "sg:classifiers":[
        {
            "category":"Professional",
            "subcategory":"Art Services",
            "type":"Services"
        }
    ],
    "sg:phone":"+1 407 898 2461",
    "sg:postcode":"32804",
    "sg:province":"FL",
    "sg:tags":[
        "photo",
        "photography",
        "commercial",
        "studio",
        "portrait"
    ],
    "wof:name":"Esquire Photographers Inc",
    "wof:placetype":"venue"
},
  "geometry": {"coordinates":[-81.37278000000001,28.568641],"type":"Point"}
}