{
  "type": "Feature",
  "properties": {
    "iso:country":"US",
    "sg:address":"6188 Lee Ann Ln",
    "sg:city":"Naples",
    "sg:classifiers":[
        {
            "category":"Building & Trades",
            "subcategory":"Landscaping Services",
            "type":"Services"
        },
        {
            "category":"Wholesale",
            "subcategory":"Machinery & Supplies",
            "type":"Manufacturing & Wholesale Goods"
        },
        {
            "category":"Professional",
            "subcategory":"Business Services",
            "type":"Services"
        }
    ],
    "sg:phone":"+1 239 597 8008",
    "sg:postcode":"34109",
    "sg:province":"FL",
    "sg:tags":[
        "lawn",
        "consultant",
        "irrigation",
        "system",
        "equipment",
        "maintenance"
    ],
    "wof:name":"Aqua-Matic Irrigation Systems, Inc.",
    "wof:placetype":"venue"
},
  "geometry": {"coordinates":[-81.777021,26.219991],"type":"Point"}
}