{
  "type": "Feature",
  "properties": {
    "addr:full":"6549 Industrial Ave Port Richey FL 34668",
    "addr:housenumber":"6549",
    "addr:postcode":"34668",
    "addr:street":"Industrial Ave",
    "iso:country":"US",
    "sg:address":"6549 Industrial Ave",
    "sg:city":"Port Richey",
    "sg:classifiers":[
        {
            "category":"Education",
            "subcategory":"School",
            "type":"Public Place"
        }
    ],
    "sg:phone":"+1 727 849 7698",
    "sg:postcode":"34668",
    "sg:province":"FL",
    "wof:name":"Ceis Of Florida Inc",
    "wof:placetype":"venue"
},
  "geometry": {"coordinates":[-82.706816,28.278393],"type":"Point"}
}