{
  "type": "Feature",
  "properties": {
    "iso:country":"US",
    "sg:address":"2883 50th Ter SW",
    "sg:city":"Naples",
    "sg:classifiers":[
        {
            "category":"Building & Trades",
            "subcategory":"Construction",
            "type":"Services"
        }
    ],
    "sg:phone":"+1 239 455 5064",
    "sg:postcode":"34116",
    "sg:province":"FL",
    "sg:tags":[
        "painter"
    ],
    "wof:name":"Canada Garrett Custom Painting",
    "wof:placetype":"venue"
},
  "geometry": {"coordinates":[-81.70691100000001,26.1755],"type":"Point"}
}