{
  "type": "Feature",
  "properties": {
    "iso:country":"US",
    "sg:address":"7300 SW 17th Ct",
    "sg:city":"Trenton",
    "sg:classifiers":[
        {
            "category":"Wholesale",
            "subcategory":"Farm Supplies",
            "type":"Manufacturing & Wholesale Goods"
        }
    ],
    "sg:phone":"+1 352 463 2683",
    "sg:postcode":"32693",
    "sg:province":"FL",
    "wof:name":"Dukes Quality Hay Inc",
    "wof:placetype":"venue"
},
  "geometry": {"coordinates":[-82.835948,29.646486],"type":"Point"}
}