{
  "type": "Feature",
  "properties": {
    "iso:country":"US",
    "sg:address":"8314 NW 103rd St",
    "sg:city":"Hialeah",
    "sg:classifiers":[
        {
            "category":"Building & Trades",
            "subcategory":"Locksmith",
            "type":"Services"
        }
    ],
    "sg:phone":"+1 305 908 8015",
    "sg:postcode":"33016",
    "sg:province":"FL",
    "sg:tags":[
        "key"
    ],
    "wof:name":"1 And 1 Hialeah Locksmith Service",
    "wof:placetype":"venue"
},
  "geometry": {"coordinates":[-80.332419,25.869163],"type":"Point"}
}