{
  "type": "Feature",
  "properties": {
    "iso:country":"US",
    "sg:address":"9556 NW 41 ST",
    "sg:city":"Doral",
    "sg:classifiers":[
        {
            "category":"Insurance",
            "subcategory":"Hazard Insurance",
            "type":"Services"
        }
    ],
    "sg:phone":"+1 305 436 9006",
    "sg:postcode":"33178",
    "sg:province":"FL",
    "wof:name":"Doral Insurance Advisors",
    "wof:placetype":"venue"
},
  "geometry": {"coordinates":[-80.350255,25.811551],"type":"Point"}
}