{
  "type": "Feature",
  "properties": {
    "addr:full":"4560 Bedford Rd Sanford FL 32773",
    "addr:housenumber":"4560",
    "addr:postcode":"32773",
    "addr:street":"Bedford Rd",
    "iso:country":"US",
    "sg:address":"4560 Bedford Rd",
    "sg:city":"Sanford",
    "sg:classifiers":[
        {
            "category":"Manufacturing",
            "subcategory":"Tools & Machinery",
            "type":"Manufacturing & Wholesale Goods"
        },
        {
            "category":"Wholesale",
            "subcategory":"Electrical",
            "type":"Manufacturing & Wholesale Goods"
        }
    ],
    "sg:phone":"+1 407 328 8195",
    "sg:postcode":"32773",
    "sg:province":"FL",
    "sg:tags":[
        "equipment",
        "manufacturer",
        "supplies-wholesale",
        "electric",
        "supply"
    ],
    "wof:name":"Chaney & Assoc Inc",
    "wof:placetype":"venue"
},
  "geometry": {"coordinates":[-81.276561,28.740317],"type":"Point"}
}