{
  "type": "Feature",
  "properties": {
    "addr:full":"11217 Bridge House Rd Windermere FL 34786",
    "addr:housenumber":"11217",
    "addr:postcode":"34786",
    "addr:street":"Bridge House Rd",
    "iso:country":"US",
    "sg:address":"11217 Bridge House Rd",
    "sg:city":"Windermere",
    "sg:classifiers":[
        {
            "category":"Banks & Credit Unions",
            "subcategory":"Financial Services",
            "type":"Services"
        }
    ],
    "sg:phone":"+1 407 909 0030",
    "sg:postcode":"34786",
    "sg:province":"FL",
    "sg:tags":[
        "company",
        "holding"
    ],
    "wof:name":"Ramberg Holdings LTD",
    "wof:placetype":"venue"
},
  "geometry": {"coordinates":[-81.55730699999999,28.469828],"type":"Point"}
}