{
  "type": "Feature",
  "properties": {
    "addr:full":"3753 Foxcroft Rd Jacksonville FL 32257",
    "addr:housenumber":"3753",
    "addr:postcode":"32257",
    "addr:street":"Foxcroft Rd",
    "iso:country":"US",
    "sg:address":"3753 Foxcroft Rd",
    "sg:city":"Jacksonville",
    "sg:classifiers":[
        {
            "category":"Social Services",
            "subcategory":"Child Care",
            "type":"Services"
        }
    ],
    "sg:phone":"+1 904 886 7143",
    "sg:postcode":"32257",
    "sg:province":"FL",
    "sg:tags":[
        "day"
    ],
    "wof:name":"Jeanine Halls Home Daycare",
    "wof:placetype":"venue"
},
  "geometry": {"coordinates":[-81.615279,30.190615],"type":"Point"}
}