{
  "type": "Feature",
  "properties": {
    "iso:country":"US",
    "sg:address":"8165 W Morgan St",
    "sg:city":"Crystal River",
    "sg:classifiers":[
        {
            "category":"Manufacturing",
            "subcategory":"Building Materials",
            "type":"Manufacturing & Wholesale Goods"
        }
    ],
    "sg:phone":"+1 352 795 7307",
    "sg:postcode":"34428",
    "sg:province":"FL",
    "sg:tags":[
        "mfg",
        "wood",
        "kitchen",
        "cabinet"
    ],
    "wof:name":"Scott & Timothy Covey",
    "wof:placetype":"venue"
},
  "geometry": {"coordinates":[-82.57474000000001,29.013189],"type":"Point"}
}