{
  "type": "Feature",
  "properties": {
    "iso:country":"US",
    "sg:address":"2224 Armadillo Ave",
    "sg:city":"Spring Hill",
    "sg:classifiers":[
        {
            "category":"Professional",
            "subcategory":"Business Services",
            "type":"Services"
        }
    ],
    "sg:phone":"+1 352 684 7338",
    "sg:postcode":"34609",
    "sg:province":"FL",
    "sg:tags":[
        "embroidery"
    ],
    "wof:name":"Monge Wear Embroidery Design",
    "wof:placetype":"venue"
},
  "geometry": {"coordinates":[-82.507705,28.46537],"type":"Point"}
}