{
  "type": "Feature",
  "properties": {
    "iso:country":"US",
    "sg:address":"1917 Weekend Ln",
    "sg:city":"Odessa",
    "sg:classifiers":[
        {
            "category":"Manufacturing",
            "subcategory":"Wood Products",
            "type":"Manufacturing & Wholesale Goods"
        },
        {
            "category":"Building & Trades",
            "subcategory":"Construction",
            "type":"Services"
        }
    ],
    "sg:phone":"+1 813 920 2415",
    "sg:postcode":"33556",
    "sg:province":"FL",
    "sg:tags":[
        "woodworking",
        "carpenter"
    ],
    "wof:name":"Holcomb, Stephen Fine Woodwork",
    "wof:placetype":"venue"
},
  "geometry": {"coordinates":[-82.587751,28.186638],"type":"Point"}
}