{
  "type": "Feature",
  "properties": {
    "iso:country":"US",
    "sg:address":"4085 Conway Place Cir",
    "sg:city":"Orlando",
    "sg:classifiers":[
        {
            "category":"Shopping",
            "subcategory":"Discount & Variety Stores",
            "type":"Retail Goods"
        }
    ],
    "sg:phone":"+1 321 251 1222",
    "sg:postcode":"32812",
    "sg:province":"FL",
    "sg:tags":[
        "liquidator"
    ],
    "wof:name":"Probate Liquidators Of West Central Florida",
    "wof:placetype":"venue"
},
  "geometry": {"coordinates":[-81.337801,28.493827],"type":"Point"}
}