{
  "type": "Feature",
  "properties": {
    "iso:country":"US",
    "sg:address":"8687 Commodity Cir",
    "sg:city":"Orlando",
    "sg:classifiers":[
        {
            "category":"Travel",
            "subcategory":"Hotels & Motels",
            "type":"Entertainment"
        }
    ],
    "sg:phone":"+1 407 248 2612",
    "sg:postcode":"32819",
    "sg:province":"FL",
    "wof:name":"Home Gate Studios & Suites",
    "wof:placetype":"venue"
},
  "geometry": {"coordinates":[-81.43108599999999,28.446663],"type":"Point"}
}