{
  "type": "Feature",
  "properties": {
    "addr:full":"335 E State Road 434 Longwood FL 32750",
    "addr:housenumber":"335",
    "addr:postcode":"32750",
    "addr:street":"E State Road 434",
    "iso:country":"US",
    "sg:address":"335 E State Road 434",
    "sg:city":"Longwood",
    "sg:classifiers":[
        {
            "category":"Retail",
            "subcategory":"Funeral Services",
            "type":"Services"
        }
    ],
    "sg:phone":"+1 407 767 5101",
    "sg:postcode":"32750",
    "sg:province":"FL",
    "sg:tags":[
        "cemetery"
    ],
    "wof:name":"Woodlawn Carey Hand Funeral Homes",
    "wof:placetype":"venue"
},
  "geometry": {"coordinates":[-81.34139999999999,28.698],"type":"Point"}
}