{
  "type": "Feature",
  "properties": {
    "iso:country":"US",
    "sg:address":"4200 Conroy Rd Ste 115",
    "sg:city":"Orlando",
    "sg:classifiers":[
        {
            "category":"Personal",
            "subcategory":"Shoe Repair & Shine",
            "type":"Services"
        }
    ],
    "sg:phone":"+1 407 352 7648",
    "sg:postcode":"32839",
    "sg:province":"FL",
    "sg:tags":[
        "sunglass"
    ],
    "sg:website":"http://www.sunglasshut.com",
    "wof:name":"Sunglass Hut",
    "wof:placetype":"venue"
},
  "geometry": {"coordinates":[-81.429467,28.489388],"type":"Point"}
}