{
  "type": "Feature",
  "properties": {
    "addr:full":"3416 Sanborn Ln Deltona FL 32738",
    "addr:housenumber":"3416",
    "addr:postcode":"32738",
    "addr:street":"Sanborn Ln",
    "iso:country":"US",
    "sg:address":"3416 Sanborn Ln",
    "sg:city":"Deltona",
    "sg:classifiers":[
        {
            "category":"Personal",
            "subcategory":"Beauty Salon",
            "type":"Services"
        }
    ],
    "sg:phone":"+1 407 999 9810",
    "sg:postcode":"32738",
    "sg:province":"FL",
    "sg:tags":[
        "shop"
    ],
    "wof:name":"Visions Hair & Nails Studio",
    "wof:placetype":"venue"
},
  "geometry": {"coordinates":[-81.167371,28.906904],"type":"Point"}
}