{
  "type": "Feature",
  "properties": {
    "iso:country":"US",
    "sg:address":"1442 42nd St NW",
    "sg:city":"Winter Haven",
    "sg:classifiers":[
        {
            "category":"Bars & Pubs",
            "type":"Food & Drink"
        }
    ],
    "sg:phone":"+1 863 967 8796",
    "sg:postcode":"33881",
    "sg:province":"FL",
    "sg:tags":[
        "drinking"
    ],
    "wof:name":"Duffy's Pub",
    "wof:placetype":"venue"
},
  "geometry": {"coordinates":[-81.776752,28.047156],"type":"Point"}
}