{
  "type": "Feature",
  "properties": {
    "iso:country":"US",
    "sg:address":"12072 Cradock St",
    "sg:city":"Spring Hill",
    "sg:classifiers":[
        {
            "category":"Shopping",
            "subcategory":"Gifts & Souvenirs",
            "type":"Retail Goods"
        }
    ],
    "sg:phone":"+1 727 844 7940",
    "sg:postcode":"34608",
    "sg:province":"FL",
    "sg:tags":[
        "shop"
    ],
    "wof:name":"Country Works",
    "wof:placetype":"venue"
},
  "geometry": {"coordinates":[-82.528007,28.508616],"type":"Point"}
}