{
  "type": "Feature",
  "properties": {
    "iso:country":"US",
    "sg:address":"935 NE 125th St",
    "sg:city":"North Miami",
    "sg:classifiers":[
        {
            "category":"Banks & Credit Unions",
            "subcategory":"Investment Brokerage",
            "type":"Services"
        }
    ],
    "sg:phone":"+1 305 891 9770",
    "sg:postcode":"33161",
    "sg:province":"FL",
    "sg:tags":[
        "advisory",
        "financial"
    ],
    "wof:name":"H & N Acctng & Financial Svc",
    "wof:placetype":"venue"
},
  "geometry": {"coordinates":[-80.179035,25.890653],"type":"Point"}
}