{
  "type": "Feature",
  "properties": {
    "iso:country":"US",
    "sg:address":"2405 Woodley Ave",
    "sg:city":"Lakeland",
    "sg:classifiers":[
        {
            "category":"Manufacturing",
            "subcategory":"Printing",
            "type":"Manufacturing & Wholesale Goods"
        }
    ],
    "sg:phone":"+1 863 686 4117",
    "sg:postcode":"33803",
    "sg:province":"FL",
    "sg:tags":[
        "offset"
    ],
    "wof:name":"St John Printing Company Inc",
    "wof:placetype":"venue"
},
  "geometry": {"coordinates":[-81.934057,28.015661],"type":"Point"}
}