{
  "type": "Feature",
  "properties": {
    "iso:country":"US",
    "sg:address":"1030 Ocoee Apopka Rd",
    "sg:city":"Apopka",
    "sg:classifiers":[
        {
            "category":"Sports & Exercise",
            "subcategory":"Gym",
            "type":"Entertainment"
        }
    ],
    "sg:phone":"+1 407 814 9400",
    "sg:postcode":"32703",
    "sg:province":"FL",
    "sg:tags":[
        "gymnasium"
    ],
    "wof:name":"CATS Gym",
    "wof:placetype":"venue"
},
  "geometry": {"coordinates":[-81.522323,28.663945],"type":"Point"}
}