{
  "type": "Feature",
  "properties": {
    "iso:country":"US",
    "sg:address":"801 Brickell Avenue Suite 900",
    "sg:city":"Miami",
    "sg:classifiers":[
        {
            "category":"Professional",
            "subcategory":"Computer Services",
            "type":"Services"
        }
    ],
    "sg:phone":"+1 650 378 1349",
    "sg:postcode":"33131",
    "sg:province":"FL",
    "sg:tags":[
        "agile-development-java--net-open-source"
    ],
    "sg:website":"http://www.b-vision.com/",
    "wof:name":"Business Vision",
    "wof:placetype":"venue"
},
  "geometry": {"coordinates":[-80.19095299999999,25.765055],"type":"Point"}
}