{
  "type": "Feature",
  "properties": {
    "iso:country":"US",
    "sg:address":"3420 Canal St",
    "sg:city":"Fort Myers",
    "sg:classifiers":[
        {
            "category":"Wholesale",
            "subcategory":"Books, Periodicals, & Newspapers",
            "type":"Manufacturing & Wholesale Goods"
        }
    ],
    "sg:phone":"+1 239 461 0766",
    "sg:postcode":"33901",
    "sg:province":"FL",
    "sg:tags":[
        "magazine"
    ],
    "wof:name":"Anderson News Co",
    "wof:placetype":"venue"
},
  "geometry": {"coordinates":[-81.843065,26.6267],"type":"Point"}
}