{
  "type": "Feature",
  "properties": {
    "iso:country":"US",
    "sg:address":"13862 Palm Grove Pl",
    "sg:city":"Palm Beach Gardens",
    "sg:classifiers":[
        {
            "category":"Health Services",
            "subcategory":"Doctor",
            "type":"Services"
        }
    ],
    "sg:phone":"+1 561 624 5655",
    "sg:postcode":"33418",
    "sg:province":"FL",
    "sg:tags":[
        "medical"
    ],
    "wof:name":"Irwin Kirschenbaum Dr",
    "wof:placetype":"venue"
},
  "geometry": {"coordinates":[-80.142563,26.879804],"type":"Point"}
}