{
  "type": "Feature",
  "properties": {
    "addr:full":"118 NE 9th Pl Cape Coral FL 33909",
    "addr:housenumber":"118",
    "addr:postcode":"33909",
    "addr:street":"Ne 9Th Pl",
    "iso:country":"US",
    "sg:address":"118 NE 9th Pl",
    "sg:city":"Cape Coral",
    "sg:classifiers":[
        {
            "category":"Real Estate",
            "subcategory":"Real Estate Operator",
            "type":"Services"
        }
    ],
    "sg:phone":"+1 239 772 7994",
    "sg:postcode":"33909",
    "sg:province":"FL",
    "sg:tags":[
        "building",
        "nonresidential"
    ],
    "wof:name":"Three Pheonix Properties LLC",
    "wof:placetype":"venue"
},
  "geometry": {"coordinates":[-81.956096,26.65612],"type":"Point"}
}