{
  "type": "Feature",
  "properties": {
    "addr:full":"7927 Congress St Port Richey FL 34668",
    "addr:housenumber":"7927",
    "addr:postcode":"34668",
    "addr:street":"Congress St",
    "iso:country":"US",
    "sg:address":"7927 Congress St",
    "sg:city":"Port Richey",
    "sg:classifiers":[
        {
            "category":"Health Services",
            "subcategory":"Nursing And Care Facility",
            "type":"Services"
        }
    ],
    "sg:phone":"+1 727 846 0131",
    "sg:postcode":"34668",
    "sg:province":"FL",
    "sg:tags":[
        "hospice"
    ],
    "wof:name":"Hernando-Pasco Hospice",
    "wof:placetype":"venue"
},
  "geometry": {"coordinates":[-82.70711,28.277448],"type":"Point"}
}