{
  "type": "Feature",
  "properties": {
    "addr:full":"2201 NW 7th Ave Miami FL 33127",
    "addr:housenumber":"2201",
    "addr:postcode":"33127",
    "addr:street":"Nw 7Th Ave",
    "iso:country":"US",
    "sg:address":"2201 NW 7th Ave",
    "sg:city":"Miami",
    "sg:classifiers":[
        {
            "category":"Retail",
            "subcategory":"Auto Repair",
            "type":"Services"
        }
    ],
    "sg:phone":"+1 305 324 0038",
    "sg:postcode":"33127",
    "sg:province":"FL",
    "sg:tags":[
        "body",
        "automobile",
        "painting"
    ],
    "wof:name":"Larkin's Paint & Body Shop Inc",
    "wof:placetype":"venue"
},
  "geometry": {"coordinates":[-80.207143,25.798927],"type":"Point"}
}