{
  "type": "Feature",
  "properties": {
    "iso:country":"US",
    "sg:address":"37751 Robinson Ave",
    "sg:city":"Dade City",
    "sg:classifiers":[
        {
            "category":"Wholesale",
            "subcategory":"Metals & Minerals",
            "type":"Manufacturing & Wholesale Goods"
        }
    ],
    "sg:phone":"+1 352 567 5540",
    "sg:postcode":"33523",
    "sg:province":"FL",
    "sg:tags":[
        "steel",
        "shop",
        "machine",
        "equipment",
        "warehouse",
        "welding"
    ],
    "wof:name":"Stalnaker Inc",
    "wof:placetype":"venue"
},
  "geometry": {"coordinates":[-82.18906800000001,28.366677],"type":"Point"}
}