{
  "type": "Feature",
  "properties": {
    "addr:full":"5770 W Irlo Bronson Memorial Hwy Ste 414 Kissimmee FL 34746",
    "addr:housenumber":"5770",
    "addr:postcode":"34746",
    "addr:street":"W Irlo Bronson Memorial Hwy Ste 414",
    "iso:country":"US",
    "sg:address":"5770 W Irlo Bronson Memorial Hwy Ste 414",
    "sg:city":"Kissimmee",
    "sg:classifiers":[
        {
            "category":"Restaurant",
            "type":"Food & Drink"
        }
    ],
    "sg:phone":"+1 407 396 6577",
    "sg:postcode":"34746",
    "sg:province":"FL",
    "wof:name":"Spring Roll",
    "wof:placetype":"venue"
},
  "geometry": {"coordinates":[-81.515958,28.330426],"type":"Point"}
}