{
  "type": "Feature",
  "properties": {
    "iso:country":"US",
    "sg:address":"720 E Colonial Dr",
    "sg:city":"Orlando",
    "sg:classifiers":[
        {
            "category":"Professional",
            "subcategory":"Lawyer & Legal Services",
            "type":"Services"
        }
    ],
    "sg:phone":"+1 407 422 7333",
    "sg:postcode":"32803",
    "sg:province":"FL",
    "sg:tags":[
        "attorney"
    ],
    "wof:name":"Bruce W Batts",
    "wof:placetype":"venue"
},
  "geometry": {"coordinates":[-81.36671,28.553098],"type":"Point"}
}