{
  "type": "Feature",
  "properties": {
    "addr:full":"5500 Marina Dr Holmes Beach FL 34217",
    "addr:housenumber":"5500",
    "addr:postcode":"34217",
    "addr:street":"Marina Dr",
    "iso:country":"US",
    "sg:address":"5500 Marina Dr",
    "sg:city":"Holmes Beach",
    "sg:classifiers":[
        {
            "category":"Building & Trades",
            "subcategory":"Construction",
            "type":"Services"
        }
    ],
    "sg:phone":"+1 941 778 7555",
    "sg:postcode":"34217",
    "sg:province":"FL",
    "sg:tags":[
        "painter"
    ],
    "wof:name":"Quality Painting Inc",
    "wof:placetype":"venue"
},
  "geometry": {"coordinates":[-82.71440699999999,27.50651],"type":"Point"}
}