{
  "type": "Feature",
  "properties": {
    "addr:full":"4162 Chelmsford Rd Tallahassee FL 32309",
    "addr:housenumber":"4162",
    "addr:postcode":"32309",
    "addr:street":"Chelmsford Rd",
    "iso:country":"US",
    "sg:address":"4162 Chelmsford Rd",
    "sg:city":"Tallahassee",
    "sg:classifiers":[
        {
            "category":"Manufacturing",
            "subcategory":"Apparel",
            "type":"Manufacturing & Wholesale Goods"
        }
    ],
    "sg:phone":"+1 850 894 1638",
    "sg:postcode":"32309",
    "sg:province":"FL",
    "sg:tags":[
        "mfg"
    ],
    "wof:name":"Rsaa Inc",
    "wof:placetype":"venue"
},
  "geometry": {"coordinates":[-84.19821,30.527248],"type":"Point"}
}