{
  "type": "Feature",
  "properties": {
    "addr:full":"2100 Consulate Dr Orlando FL 32837",
    "addr:postcode":"32837",
    "addr:street":"Consulate Dr",
    "iso:country":"US",
    "sg:address":"2100 Consulate Dr",
    "sg:city":"Orlando",
    "sg:classifiers":[
        {
            "category":"Banks & Credit Unions",
            "subcategory":"Investment Brokerage",
            "type":"Services"
        }
    ],
    "sg:phone":"+1 407 438 3224",
    "sg:postcode":"32837",
    "sg:province":"FL",
    "sg:tags":[
        "stock",
        "bond"
    ],
    "wof:name":"Security Capital Ind",
    "wof:placetype":"venue"
},
  "geometry": {"coordinates":[-81.40751,28.430857],"type":"Point"}
}