{
  "type": "Feature",
  "properties": {
    "addr:full":"1617 Airport Rd Jacksonville FL 32218",
    "addr:housenumber":"1617",
    "addr:postcode":"32218",
    "addr:street":"Airport Rd",
    "iso:country":"US",
    "sg:address":"1617 Airport Rd",
    "sg:city":"Jacksonville",
    "sg:classifiers":[
        {
            "category":"Retail",
            "subcategory":"Auto Rental",
            "type":"Services"
        }
    ],
    "sg:phone":"+1 904 741 4105",
    "sg:postcode":"32218",
    "sg:province":"FL",
    "sg:tags":[
        "renting",
        "automobile"
    ],
    "wof:name":"U-Save Auto Rental",
    "wof:placetype":"venue"
},
  "geometry": {"coordinates":[-81.662458,30.484918],"type":"Point"}
}