{
  "type": "Feature",
  "properties": {
    "addr:full":"4009 Broadway West Palm Beach FL 33407",
    "addr:housenumber":"4009",
    "addr:postcode":"33407",
    "addr:street":"Broadway",
    "iso:country":"US",
    "sg:address":"4009 Broadway",
    "sg:city":"West Palm Beach",
    "sg:classifiers":[
        {
            "category":"Personal",
            "subcategory":"Beauty Salon",
            "type":"Services"
        }
    ],
    "sg:phone":"+1 561 842 2918",
    "sg:postcode":"33407",
    "sg:province":"FL",
    "wof:name":"K M & D Unisex Beauty Salon",
    "wof:placetype":"venue"
},
  "geometry": {"coordinates":[-80.056605,26.748846],"type":"Point"}
}