{
  "type": "Feature",
  "properties": {
    "addr:full":"252 Ewing Ct NW Fort Walton Bch FL 32548",
    "addr:housenumber":"252",
    "addr:postcode":"32548",
    "addr:street":"Ewing Ct Nw Fort",
    "iso:country":"US",
    "sg:address":"252 Ewing Ct NW",
    "sg:city":"Fort Walton Bch",
    "sg:classifiers":[
        {
            "category":"Social Services",
            "subcategory":"Child Care",
            "type":"Services"
        }
    ],
    "sg:phone":"+1 850 862 9652",
    "sg:postcode":"32548",
    "sg:province":"FL",
    "sg:tags":[
        "sitting"
    ],
    "wof:name":"Nanny's Sitters Inc",
    "wof:placetype":"venue"
},
  "geometry": {"coordinates":[-86.63525799999999,30.428299],"type":"Point"}
}