{
  "type": "Feature",
  "properties": {
    "iso:country":"US",
    "sg:address":"1450 W 49th St",
    "sg:city":"Hialeah",
    "sg:classifiers":[
        {
            "category":"Shopping",
            "subcategory":"Shoes",
            "type":"Retail Goods"
        }
    ],
    "sg:phone":"+1 305 822 7416",
    "sg:postcode":"33012",
    "sg:province":"FL",
    "sg:tags":[
        "store"
    ],
    "wof:name":"Victory Shoes Corp",
    "wof:placetype":"venue"
},
  "geometry": {"coordinates":[-80.31199599999999,25.8666],"type":"Point"}
}