{
  "type": "Feature",
  "properties": {
    "addr:full":"1400 S Orlando Ave Winter Park FL 32789",
    "addr:housenumber":"1400",
    "addr:postcode":"32789",
    "addr:street":"S Orlando Ave",
    "iso:country":"US",
    "sg:address":"1400 S Orlando Ave",
    "sg:city":"Winter Park",
    "sg:classifiers":[
        {
            "category":"Health Services",
            "subcategory":"Doctor",
            "type":"Services"
        }
    ],
    "sg:phone":"+1 407 599 7600",
    "sg:postcode":"32789",
    "sg:province":"FL",
    "sg:tags":[
        "physician",
        "surgeon"
    ],
    "wof:name":"Friedman Knee & Shoulder",
    "wof:placetype":"venue"
},
  "geometry": {"coordinates":[-81.364904,28.584061],"type":"Point"}
}