{
  "type": "Feature",
  "properties": {
    "addr:full":"281 S Pompano Pkwy Pompano Beach FL 33069",
    "addr:housenumber":"281",
    "addr:postcode":"33069",
    "addr:street":"S Pompano Pkwy",
    "iso:country":"US",
    "sg:address":"281 S Pompano Pkwy",
    "sg:city":"Pompano Beach",
    "sg:classifiers":[
        {
            "category":"Cinema",
            "subcategory":"Movie Rental",
            "type":"Entertainment"
        }
    ],
    "sg:phone":"+1 954 968 7030",
    "sg:postcode":"33069",
    "sg:province":"FL",
    "sg:tags":[
        "leasing",
        "video",
        "disc",
        "tape"
    ],
    "wof:name":"Blockbuster Video",
    "wof:placetype":"venue"
},
  "geometry": {"coordinates":[-80.156783,26.230672],"type":"Point"}
}