{
  "type": "Feature",
  "properties": {
    "addr:city":"Hollywood",
    "addr:full":"751 Sheridan Street Hollywood, Fl 33019",
    "addr:house_number":"751",
    "addr:housenumber":"751",
    "addr:phone":"+1 954-357-5161",
    "addr:postcode":"33019",
    "addr:road":"Sheridan Street",
    "addr:state":"FL",
    "addr:street":"E Sheridan St",
    "iso:country":"US",
    "sg:address":"751 E Sheridan St",
    "sg:city":"Hollywood",
    "sg:classifiers":[
        {
            "category":"Government",
            "subcategory":"Office",
            "type":"Public Place"
        }
    ],
    "sg:phone":"+1 954 926 2480",
    "sg:postcode":"33019",
    "sg:province":"FL",
    "wof:airports":[
        102530161,
        102528421,
        102530841,
        102533719
    ],
    "wof:name":"Anne Kolb Nature Center",
    "wof:placetype":"venue"
},
  "geometry": {"coordinates":[-80.11546,26.03438],"type":"Point"}
}