{
  "type": "Feature",
  "properties": {
    "addr:full":"2455 E Sunrise Blvd Fort Lauderdale FL 33304",
    "addr:housenumber":"2455",
    "addr:postcode":"33304",
    "addr:street":"E Sunrise Blvd",
    "iso:country":"US",
    "sg:address":"2455 E Sunrise Blvd",
    "sg:city":"Fort Lauderdale",
    "sg:classifiers":[
        {
            "category":"Professional",
            "subcategory":"Management & Consulting",
            "type":"Services"
        }
    ],
    "sg:phone":"+1 954 564 7701",
    "sg:postcode":"33304",
    "sg:province":"FL",
    "sg:tags":[
        "accounting",
        "bookkeeping",
        "financial"
    ],
    "wof:name":"Gss Advisory Services Inc",
    "wof:placetype":"venue"
},
  "geometry": {"coordinates":[-80.11382399999999,26.137913],"type":"Point"}
}