{
  "type": "Feature",
  "properties": {
    "addr:full":"10300 SW 72nd St Miami FL 33173",
    "addr:housenumber":"10300",
    "addr:postcode":"33173",
    "addr:street":"Sw 72Nd St",
    "iso:country":"US",
    "sg:address":"10300 SW 72nd St",
    "sg:city":"Miami",
    "sg:classifiers":[
        {
            "category":"Travel",
            "subcategory":"Travel Agent",
            "type":"Entertainment"
        }
    ],
    "sg:phone":"+1 305 596 1110",
    "sg:postcode":"33173",
    "sg:province":"FL",
    "sg:tags":[
        "agency",
        "bureau"
    ],
    "wof:name":"Marcia Travel",
    "wof:placetype":"venue"
},
  "geometry": {"coordinates":[-80.363089,25.701197],"type":"Point"}
}