{
  "type": "Feature",
  "properties": {
    "addr:full":"2520 SW 56 Ave Gainesville FL 32608",
    "addr:housenumber":"2520",
    "addr:postcode":"32608",
    "addr:street":"Sw 56 Ave",
    "iso:country":"US",
    "sg:address":"2520 SW 56 Ave",
    "sg:city":"Gainesville",
    "sg:classifiers":[
        {
            "category":"Manufacturing",
            "subcategory":"Tools & Machinery",
            "type":"Manufacturing & Wholesale Goods"
        }
    ],
    "sg:phone":"+1 352 378 5256",
    "sg:postcode":"32608",
    "sg:province":"FL",
    "sg:tags":[
        "industrial",
        "electrical",
        "apparatus"
    ],
    "wof:name":"Elliott L Brown",
    "wof:placetype":"venue"
},
  "geometry": {"coordinates":[-82.362348,29.600286],"type":"Point"}
}