{
  "type": "Feature",
  "properties": {
    "addr:full":"388 Gardner Dr NE Fort Walton Beach FL 32548",
    "addr:housenumber":"388",
    "addr:postcode":"32548",
    "addr:street":"Gardner Dr Ne",
    "iso:country":"US",
    "sg:address":"388 Gardner Dr NE",
    "sg:city":"Fort Walton Beach",
    "sg:classifiers":[
        {
            "category":"Personal",
            "type":"Services"
        }
    ],
    "sg:phone":"+1 850 243 8802",
    "sg:postcode":"32548",
    "sg:province":"FL",
    "wof:name":"PMS",
    "wof:placetype":"venue"
},
  "geometry": {"coordinates":[-86.591005,30.418421],"type":"Point"}
}