{
  "type": "Feature",
  "properties": {
    "iso:country":"US",
    "sg:address":"7344 Grotto Ave",
    "sg:city":"Orlando",
    "sg:classifiers":[
        {
            "category":"Freight",
            "type":"Transportation"
        }
    ],
    "sg:phone":"+1 407 240 6655",
    "sg:postcode":"32812",
    "sg:province":"FL",
    "wof:name":"Wheels To Wings Transportation",
    "wof:placetype":"venue"
},
  "geometry": {"coordinates":[-81.335773,28.459607],"type":"Point"}
}