{
  "type": "Feature",
  "properties": {
    "addr:full":"2010 Wilton Dr Fort Lauderdale FL 33305",
    "addr:housenumber":"2010",
    "addr:postcode":"33305",
    "addr:street":"Wilton Dr",
    "iso:country":"US",
    "sg:address":"2010 Wilton Dr",
    "sg:city":"Fort Lauderdale",
    "sg:classifiers":[
        {
            "category":"Restaurant",
            "type":"Food & Drink"
        }
    ],
    "sg:phone":"+1 954 564 3411",
    "sg:postcode":"33305",
    "sg:province":"FL",
    "wof:name":"Siam Curry House",
    "wof:placetype":"venue"
},
  "geometry": {"coordinates":[-80.13999099999999,26.154171],"type":"Point"}
}