{
  "type": "Feature",
  "properties": {
    "iso:country":"US",
    "sg:address":"3430 Edgewater Dr",
    "sg:city":"Orlando",
    "sg:classifiers":[
        {
            "category":"Home & Garden",
            "subcategory":"Furniture",
            "type":"Retail Goods"
        }
    ],
    "sg:phone":"+1 407 423 4173",
    "sg:postcode":"32804",
    "sg:province":"FL",
    "sg:tags":[
        "resident",
        "household",
        "wood",
        "mfg"
    ],
    "wof:name":"Driftwood Decor",
    "wof:placetype":"venue"
},
  "geometry": {"coordinates":[-81.391195,28.583276],"type":"Point"}
}