{
  "type": "Feature",
  "properties": {
    "iso:country":"US",
    "sg:address":"56 NW Irwin Ave",
    "sg:city":"West Melbourne",
    "sg:classifiers":[
        {
            "category":"Retail",
            "subcategory":"Auto Repair",
            "type":"Services"
        }
    ],
    "sg:phone":"+1 321 952 8418",
    "sg:postcode":"32904",
    "sg:province":"FL",
    "sg:tags":[
        "repairing",
        "automobile"
    ],
    "wof:name":"Paul's Automotive",
    "wof:placetype":"venue"
},
  "geometry": {"coordinates":[-80.64122,28.081082],"type":"Point"}
}