{
  "type": "Feature",
  "properties": {
    "iso:country":"US",
    "sg:address":"255 S Orange Ave Ste 1240",
    "sg:city":"Orlando",
    "sg:classifiers":[
        {
            "category":"Banks & Credit Unions",
            "subcategory":"Investment Brokerage",
            "type":"Services"
        },
        {
            "category":"Banks & Credit Unions",
            "subcategory":"Bank",
            "type":"Services"
        }
    ],
    "sg:phone":"+1 407 839 3904",
    "sg:postcode":"32801",
    "sg:province":"FL",
    "sg:tags":[
        "commercial",
        "trust",
        "saving"
    ],
    "sg:website":"http://www.hancockbank.com",
    "wof:name":"Hancock Bank",
    "wof:placetype":"venue"
},
  "geometry": {"coordinates":[-81.379008,28.539607],"type":"Point"}
}