{
  "type": "Feature",
  "properties": {
    "iso:country":"US",
    "sg:address":"1775 Bayberry Dr",
    "sg:city":"Merritt Island",
    "sg:classifiers":[
        {
            "category":"Building & Trades",
            "subcategory":"Construction",
            "type":"Services"
        }
    ],
    "sg:phone":"+1 321 454 9702",
    "sg:postcode":"32953",
    "sg:province":"FL",
    "sg:tags":[
        "home",
        "improvement"
    ],
    "wof:name":"Richard Kujawa's Luxury Svc",
    "wof:placetype":"venue"
},
  "geometry": {"coordinates":[-80.704976,28.387845],"type":"Point"}
}