{
  "type": "Feature",
  "properties": {
    "iso:country":"US",
    "sg:address":"9031 Ulmerton Rd",
    "sg:city":"Largo",
    "sg:classifiers":[
        {
            "category":"Personal",
            "subcategory":"Beauty Salon",
            "type":"Services"
        }
    ],
    "sg:phone":"+1 727 518 9373",
    "sg:postcode":"33771",
    "sg:province":"FL",
    "wof:name":"Casual Clips",
    "wof:placetype":"venue"
},
  "geometry": {"coordinates":[-82.76483899999999,27.894567],"type":"Point"}
}