{
  "type": "Feature",
  "properties": {
    "addr:full":"5502 Britan Dr Orlando FL 32808",
    "addr:housenumber":"5502",
    "addr:postcode":"32808",
    "addr:street":"Britan Dr",
    "iso:country":"US",
    "sg:address":"5502 Britan Dr",
    "sg:city":"Orlando",
    "sg:classifiers":[
        {
            "category":"Education",
            "subcategory":"School",
            "type":"Public Place"
        }
    ],
    "sg:phone":"+1 407 854 6145",
    "sg:postcode":"32808",
    "sg:province":"FL",
    "wof:name":"Saints Academy Inc",
    "wof:placetype":"venue"
},
  "geometry": {"coordinates":[-81.461782,28.60773],"type":"Point"}
}