{
  "type": "Feature",
  "properties": {
    "addr:full":"425 Ocean Dunes Rd Daytona Beach FL 32118",
    "addr:housenumber":"425",
    "addr:postcode":"32118",
    "addr:street":"Ocean Dunes Rd",
    "iso:country":"US",
    "sg:address":"425 Ocean Dunes Rd",
    "sg:city":"Daytona Beach",
    "sg:classifiers":[
        {
            "category":"Personal",
            "subcategory":"Beauty Salon",
            "type":"Services"
        }
    ],
    "sg:phone":"+1 386 253 7722",
    "sg:postcode":"32118",
    "sg:province":"FL",
    "sg:tags":[
        "shop"
    ],
    "wof:name":"La Bella Donna",
    "wof:placetype":"venue"
},
  "geometry": {"coordinates":[-80.99985,29.206216],"type":"Point"}
}