{
  "type": "Feature",
  "properties": {
    "iso:country":"US",
    "sg:address":"17019 Pines Blvd",
    "sg:city":"Hollywood",
    "sg:classifiers":[
        {
            "category":"Health Services",
            "subcategory":"Optometrist",
            "type":"Services"
        }
    ],
    "sg:phone":"+1 954 432 5822",
    "sg:postcode":"33027",
    "sg:province":"FL",
    "wof:name":"Jerome D Friedman Dr",
    "wof:placetype":"venue"
},
  "geometry": {"coordinates":[-80.374,26.007806],"type":"Point"}
}