{
  "type": "Feature",
  "properties": {
    "addr:full":"156 Yelvington Rd East Palatka FL 32131",
    "addr:housenumber":"156",
    "addr:postcode":"32131",
    "addr:street":"Yelvington Rd",
    "iso:country":"US",
    "sg:address":"156 Yelvington Rd",
    "sg:city":"East Palatka",
    "sg:classifiers":[
        {
            "category":"Building & Trades",
            "subcategory":"Construction",
            "type":"Services"
        }
    ],
    "sg:phone":"+1 386 328 4862",
    "sg:postcode":"32131",
    "sg:province":"FL",
    "wof:name":"Shed Country",
    "wof:placetype":"venue"
},
  "geometry": {"coordinates":[-81.583378,29.642332],"type":"Point"}
}