{
  "type": "Feature",
  "properties": {
    "addr:full":"2607 NW 39th Ave Miami FL 33142",
    "addr:housenumber":"2607",
    "addr:postcode":"33142",
    "addr:street":"Nw 39Th Ave",
    "iso:country":"US",
    "sg:address":"2607 NW 39th Ave",
    "sg:city":"Miami",
    "sg:classifiers":[
        {
            "category":"Retail",
            "subcategory":"Auto Rental",
            "type":"Services"
        }
    ],
    "sg:phone":"+1 305 871 8735",
    "sg:postcode":"33142",
    "sg:province":"FL",
    "sg:tags":[
        "car"
    ],
    "wof:name":"Excel Rent-A-Car Inc",
    "wof:placetype":"venue"
},
  "geometry": {"coordinates":[-80.25993699999999,25.799637],"type":"Point"}
}