{
  "type": "Feature",
  "properties": {
    "iso:country":"US",
    "sg:address":"3801 Corporex Park Dr",
    "sg:city":"Tampa",
    "sg:classifiers":[
        {
            "category":"Professional",
            "subcategory":"Computer Services",
            "type":"Services"
        }
    ],
    "sg:phone":"+1 813 626 3963",
    "sg:postcode":"33619",
    "sg:province":"FL",
    "sg:tags":[
        "consultant"
    ],
    "sg:website":"www.apollonetworks.com",
    "wof:name":"Apollo Network Solutions Inc",
    "wof:placetype":"venue"
},
  "geometry": {"coordinates":[-82.378452,27.975275],"type":"Point"}
}