{
  "type": "Feature",
  "properties": {
    "iso:country":"US",
    "sg:address":"8255 NE 2nd Ave",
    "sg:city":"Miami",
    "sg:classifiers":[
        {
            "category":"Home & Garden",
            "subcategory":"Home Furnishings",
            "type":"Retail Goods"
        }
    ],
    "sg:phone":"+1 305 758 6811",
    "sg:postcode":"33138",
    "sg:province":"FL",
    "sg:tags":[
        "material",
        "mirror"
    ],
    "wof:name":"Clement's Glass & Mirrors",
    "wof:placetype":"venue"
},
  "geometry": {"coordinates":[-80.192937,25.850998],"type":"Point"}
}