{
  "type": "Feature",
  "properties": {
    "addr:full":"4750 W Commercial Blvd Fort Lauderdale FL 33319",
    "addr:housenumber":"4750",
    "addr:postcode":"33319",
    "addr:street":"W Commercial Blvd",
    "iso:country":"US",
    "sg:address":"4750 W Commercial Blvd",
    "sg:city":"Fort Lauderdale",
    "sg:classifiers":[
        {
            "category":"Professional",
            "subcategory":"Business Services",
            "type":"Services"
        }
    ],
    "sg:phone":"+1 954 714 9004",
    "sg:postcode":"33319",
    "sg:province":"FL",
    "wof:name":"Pines Financial Inc",
    "wof:placetype":"venue"
},
  "geometry": {"coordinates":[-80.20947,26.189592],"type":"Point"}
}