{
  "type": "Feature",
  "properties": {
    "addr:full":"21 Heather Ln Winter Haven FL 33884",
    "addr:housenumber":"21",
    "addr:postcode":"33884",
    "addr:street":"Heather Ln",
    "iso:country":"US",
    "sg:address":"21 Heather Ln",
    "sg:city":"Winter Haven",
    "sg:classifiers":[
        {
            "category":"Building & Trades",
            "subcategory":"Landscaping Services",
            "type":"Services"
        }
    ],
    "sg:phone":"+1 863 324 4316",
    "sg:postcode":"33884",
    "sg:province":"FL",
    "sg:tags":[
        "contractor",
        "f",
        "landscape",
        "supply"
    ],
    "wof:name":"Childers Lawn Maintenance Inc",
    "wof:placetype":"venue"
},
  "geometry": {"coordinates":[-81.691869,27.944348],"type":"Point"}
}