{
  "type": "Feature",
  "properties": {
    "iso:country":"US",
    "sg:address":"2460 Vanderbilt Beach Rd",
    "sg:city":"Naples",
    "sg:classifiers":[
        {
            "category":"Restaurant",
            "type":"Food & Drink"
        }
    ],
    "sg:phone":"+1 239 592 9999",
    "sg:postcode":"34109",
    "sg:province":"FL",
    "sg:tags":[
        "bar"
    ],
    "sg:website":"www.samsneadstavern.com",
    "wof:name":"Sam Snead's Tavern",
    "wof:placetype":"venue"
},
  "geometry": {"coordinates":[-81.7684,26.243744],"type":"Point"}
}