{
  "type": "Feature",
  "properties": {
    "addr:full":"4050 Briarglen Rd Milton FL 32583",
    "addr:housenumber":"4050",
    "addr:postcode":"32583",
    "addr:street":"Briarglen Rd",
    "iso:country":"US",
    "sg:address":"4050 Briarglen Rd",
    "sg:city":"Milton",
    "sg:classifiers":[
        {
            "category":"Manufacturing",
            "subcategory":"Glass & Minerals",
            "type":"Manufacturing & Wholesale Goods"
        }
    ],
    "sg:phone":"+1 850 492 5625",
    "sg:postcode":"32583",
    "sg:province":"FL",
    "sg:tags":[
        "brick",
        "block",
        "mfg"
    ],
    "wof:name":"APAC",
    "wof:placetype":"venue"
},
  "geometry": {"coordinates":[-87.065769,30.583479],"type":"Point"}
}