{
  "type": "Feature",
  "properties": {
    "iso:country":"US",
    "sg:address":"742 NW 12th Ave",
    "sg:city":"Miami",
    "sg:classifiers":[
        {
            "category":"Personal",
            "type":"Services"
        }
    ],
    "sg:phone":"+1 305 325 9444",
    "sg:postcode":"33136",
    "sg:province":"FL",
    "sg:tags":[
        "assistant"
    ],
    "wof:name":"La Cubana Bail Bond",
    "wof:placetype":"venue"
},
  "geometry": {"coordinates":[-80.214828,25.780982],"type":"Point"}
}