{
  "type": "Feature",
  "properties": {
    "iso:country":"US",
    "sg:address":"2316 Winter Woods Blvd",
    "sg:city":"Winter Park",
    "sg:classifiers":[
        {
            "category":"Banks & Credit Unions",
            "subcategory":"Bank",
            "type":"Services"
        }
    ],
    "sg:phone":"+1 407 737 3355",
    "sg:postcode":"32792",
    "sg:province":"FL",
    "sg:tags":[
        "loan",
        "real estate"
    ],
    "wof:name":"Sage Mortgage Svc Inc",
    "wof:placetype":"venue"
},
  "geometry": {"coordinates":[-81.314189,28.618389],"type":"Point"}
}