{
  "type": "Feature",
  "properties": {
    "iso:country":"US",
    "sg:address":"2385 Stonehaven Ct E",
    "sg:city":"Orange Park",
    "sg:classifiers":[
        {
            "category":"Shopping",
            "subcategory":"Books",
            "type":"Retail Goods"
        }
    ],
    "sg:phone":"+1 904 210 7024",
    "sg:postcode":"32065",
    "sg:province":"FL",
    "sg:tags":[
        "science",
        "medium",
        "health",
        "related"
    ],
    "wof:name":"Blue Sky Bookstore",
    "wof:placetype":"venue"
},
  "geometry": {"coordinates":[-81.764892,30.14175],"type":"Point"}
}