{
  "type": "Feature",
  "properties": {
    "iso:country":"US",
    "sg:address":"227 W Beresford Ave",
    "sg:city":"Deland",
    "sg:classifiers":[
        {
            "category":"Wholesale",
            "subcategory":"Electrical",
            "type":"Manufacturing & Wholesale Goods"
        }
    ],
    "sg:phone":"+1 386 734 3244",
    "sg:postcode":"32720",
    "sg:province":"FL",
    "sg:tags":[
        "repair",
        "electric",
        "power",
        "same",
        "equipment",
        "pump",
        "motor"
    ],
    "wof:name":"A-1 Electric Motor Shop Inc",
    "wof:placetype":"venue"
},
  "geometry": {"coordinates":[-81.30527600000001,29.013806],"type":"Point"}
}