{
  "type": "Feature",
  "properties": {
    "iso:country":"US",
    "sg:address":"1053 N Orlando Ave",
    "sg:city":"Maitland",
    "sg:classifiers":[
        {
            "category":"Social Services",
            "type":"Services"
        }
    ],
    "sg:phone":"+1 407 622 4673",
    "sg:postcode":"32751",
    "sg:province":"FL",
    "sg:tags":[
        "organization",
        "welfare"
    ],
    "wof:name":"Make A Wish Foundation",
    "wof:placetype":"venue"
},
  "geometry": {"coordinates":[-81.359802,28.63605],"type":"Point"}
}