{
  "type": "Feature",
  "properties": {
    "addr:full":"1720 NE 9th Ave Fort Lauderdale FL 33305",
    "addr:housenumber":"1720",
    "addr:postcode":"33305",
    "addr:street":"Ne 9Th Ave",
    "iso:country":"US",
    "sg:address":"1720 NE 9th Ave",
    "sg:city":"Fort Lauderdale",
    "sg:classifiers":[
        {
            "category":"Building & Trades",
            "subcategory":"Landscaping Services",
            "type":"Services"
        }
    ],
    "sg:phone":"+1 954 728 9290",
    "sg:postcode":"33305",
    "sg:province":"FL",
    "wof:name":"Tlcs Greenery",
    "wof:placetype":"venue"
},
  "geometry": {"coordinates":[-80.134353,26.151332],"type":"Point"}
}