{
  "type": "Feature",
  "properties": {
    "iso:country":"US",
    "sg:address":"106 S Tampania Ave",
    "sg:city":"Tampa",
    "sg:classifiers":[
        {
            "category":"Professional",
            "subcategory":"Lawyer & Legal Services",
            "type":"Services"
        }
    ],
    "sg:phone":"+1 813 840 0944",
    "sg:postcode":"33609",
    "sg:province":"FL",
    "sg:tags":[
        "attorney"
    ],
    "wof:name":"David W Holloway",
    "wof:placetype":"venue"
},
  "geometry": {"coordinates":[-82.48638099999999,27.94454],"type":"Point"}
}