{
  "type": "Feature",
  "properties": {
    "iso:country":"US",
    "sg:address":"4908 Crofton Way",
    "sg:city":"Tampa",
    "sg:classifiers":[
        {
            "category":"Building & Trades",
            "subcategory":"Construction",
            "type":"Services"
        }
    ],
    "sg:phone":"+1 813 265 9454",
    "sg:postcode":"33625",
    "sg:province":"FL",
    "sg:tags":[
        "residential"
    ],
    "wof:name":"C M Welch Corporation",
    "wof:placetype":"venue"
},
  "geometry": {"coordinates":[-82.544918,28.077447],"type":"Point"}
}