{
  "type": "Feature",
  "properties": {
    "iso:country":"US",
    "sg:address":"12940 NW 27th Ave",
    "sg:city":"Opa Locka",
    "sg:classifiers":[
        {
            "category":"Autos & Motor Vehicles",
            "subcategory":"Automobile Sales",
            "type":"Retail Goods"
        }
    ],
    "sg:phone":"+1 305 681 6792",
    "sg:postcode":"33054",
    "sg:province":"FL",
    "sg:tags":[
        "pickup",
        "used"
    ],
    "wof:name":"Flea Market Auto Sales Inc",
    "wof:placetype":"venue"
},
  "geometry": {"coordinates":[-80.243332,25.890148],"type":"Point"}
}