{
  "type": "Feature",
  "properties": {
    "addr:full":"424 E Central Blvd Orlando FL 32801",
    "addr:housenumber":"424",
    "addr:postcode":"32801",
    "addr:street":"E Central Blvd",
    "iso:country":"US",
    "sg:address":"424 E Central Blvd",
    "sg:city":"Orlando",
    "sg:classifiers":[
        {
            "category":"Shopping",
            "subcategory":"Stationery & Office Supplies",
            "type":"Retail Goods"
        }
    ],
    "sg:phone":"+1 352 217 3391",
    "sg:postcode":"32801",
    "sg:province":"FL",
    "sg:tags":[
        "manufacturing",
        "social"
    ],
    "wof:name":"Affordable Wedding Invitations",
    "wof:placetype":"venue"
},
  "geometry": {"coordinates":[-81.371791,28.542199],"type":"Point"}
}