{
  "type": "Feature",
  "properties": {
    "iso:country":"US",
    "sg:address":"2962 SE Dalhart Rd",
    "sg:city":"Port Saint Lucie",
    "sg:classifiers":[
        {
            "category":"Building & Trades",
            "subcategory":"Construction",
            "type":"Services"
        }
    ],
    "sg:phone":"+1 772 335 7531",
    "sg:postcode":"34952",
    "sg:province":"FL",
    "sg:tags":[
        "contractor"
    ],
    "wof:name":"All In One Screening",
    "wof:placetype":"venue"
},
  "geometry": {"coordinates":[-80.287278,27.25345],"type":"Point"}
}