{
  "type": "Feature",
  "properties": {
    "iso:country":"US",
    "sg:address":"3123C NW 73rd St",
    "sg:city":"Miami",
    "sg:classifiers":[
        {
            "category":"Shopping",
            "subcategory":"Department Store",
            "type":"Retail Goods"
        },
        {
            "category":"Food & Beverages",
            "subcategory":"Groceries & Convenience Stores",
            "type":"Retail Goods"
        }
    ],
    "sg:phone":"+1 305 836 3386",
    "sg:postcode":"33147",
    "sg:province":"FL",
    "sg:tags":[
        "oils-vegetable"
    ],
    "wof:name":"Palm Oil",
    "wof:placetype":"venue"
},
  "geometry": {"coordinates":[-80.248148,25.840273],"type":"Point"}
}