{
  "type": "Feature",
  "properties": {
    "iso:country":"US",
    "sg:address":"5711 Independence Cir",
    "sg:city":"Fort Myers",
    "sg:classifiers":[
        {
            "category":"Wholesale",
            "subcategory":"Electrical",
            "type":"Manufacturing & Wholesale Goods"
        }
    ],
    "sg:phone":"+1 239 489 2980",
    "sg:postcode":"33912",
    "sg:province":"FL",
    "sg:tags":[
        "equipment",
        "parts",
        "electronic"
    ],
    "wof:name":"Global Solutions",
    "wof:placetype":"venue"
},
  "geometry": {"coordinates":[-81.858672,26.529766],"type":"Point"}
}