{
  "type": "Feature",
  "properties": {
    "iso:country":"US",
    "sg:address":"13751 S Tamiami Trl",
    "sg:city":"Fort Myers",
    "sg:classifiers":[
        {
            "category":"Communications",
            "subcategory":"Newspaper",
            "type":"Services"
        }
    ],
    "sg:phone":"+1 239 437 0654",
    "sg:postcode":"33912",
    "sg:province":"FL",
    "sg:tags":[
        "magazine"
    ],
    "sg:website":"www.barnesandnoble.com",
    "wof:name":"Barnes & Noble Booksellers",
    "wof:placetype":"venue"
},
  "geometry": {"coordinates":[-81.871201,26.5415],"type":"Point"}
}