{
  "type": "Feature",
  "properties": {
    "iso:country":"US",
    "sg:address":"1600 S Federal Hwy",
    "sg:city":"Pompano Beach",
    "sg:classifiers":[
        {
            "category":"Health Services",
            "subcategory":"Doctor",
            "type":"Services"
        }
    ],
    "sg:phone":"+1 954 781 7044",
    "sg:postcode":"33062",
    "sg:province":"FL",
    "sg:tags":[
        "physician",
        "surgeon"
    ],
    "wof:name":"Cutting Edge Medical Group",
    "wof:placetype":"venue"
},
  "geometry": {"coordinates":[-80.10706,26.210726],"type":"Point"}
}