{
  "type": "Feature",
  "properties": {
    "iso:country":"US",
    "sg:address":"4405 Willa Creek Dr",
    "sg:city":"Winter Springs",
    "sg:classifiers":[
        {
            "category":"Professional",
            "type":"Services"
        }
    ],
    "sg:phone":"+1 407 696 5159",
    "sg:postcode":"32708",
    "sg:province":"FL",
    "sg:tags":[
        "establishment"
    ],
    "wof:name":"Careersoft",
    "wof:placetype":"venue"
},
  "geometry": {"coordinates":[-81.268452,28.643436],"type":"Point"}
}