{
  "type": "Feature",
  "properties": {
    "addr:full":"5848 Arthur St Hollywood FL 33021",
    "addr:housenumber":"5848",
    "addr:postcode":"33021",
    "addr:street":"Arthur St",
    "iso:country":"US",
    "sg:address":"5848 Arthur St",
    "sg:city":"Hollywood",
    "sg:classifiers":[
        {
            "category":"Shopping",
            "type":"Retail Goods"
        }
    ],
    "sg:phone":"+1 954 963 5156",
    "sg:postcode":"33021",
    "sg:province":"FL",
    "sg:tags":[
        "repair",
        "accessory"
    ],
    "wof:name":"Fine Art & Frames",
    "wof:placetype":"venue"
},
  "geometry": {"coordinates":[-80.20564,26.021275],"type":"Point"}
}