{
  "type": "Feature",
  "properties": {
    "iso:country":"US",
    "sg:address":"26236 US Hwy 19",
    "sg:city":"Clearwater",
    "sg:classifiers":[
        {
            "category":"Retail",
            "subcategory":"Auto Rental",
            "type":"Services"
        }
    ],
    "sg:phone":"+1 727 791 9353",
    "sg:postcode":"33761",
    "sg:province":"FL",
    "sg:tags":[
        "passenger",
        "car"
    ],
    "wof:name":"Avis Rent A Car Systems",
    "wof:placetype":"venue"
},
  "geometry": {"coordinates":[-82.732445,28.01038],"type":"Point"}
}