{
  "type": "Feature",
  "properties": {
    "addr:full":"1221 Hillview Dr Sarasota FL 34239",
    "addr:housenumber":"1221",
    "addr:postcode":"34239",
    "addr:street":"Hillview Dr",
    "iso:country":"US",
    "sg:address":"1221 Hillview Dr",
    "sg:city":"Sarasota",
    "sg:classifiers":[
        {
            "category":"Building & Trades",
            "subcategory":"Construction",
            "type":"Services"
        }
    ],
    "sg:phone":"+1 941 365 5758",
    "sg:postcode":"34239",
    "sg:province":"FL",
    "sg:tags":[
        "house"
    ],
    "wof:name":"Angeleri Associates",
    "wof:placetype":"venue"
},
  "geometry": {"coordinates":[-82.54364099999999,27.317457],"type":"Point"}
}