{
  "type": "Feature",
  "properties": {
    "iso:country":"US",
    "sg:address":"1325 Sunrise Rd",
    "sg:city":"West Palm Beach",
    "sg:classifiers":[
        {
            "category":"Manufacturing",
            "subcategory":"Apparel",
            "type":"Manufacturing & Wholesale Goods"
        }
    ],
    "sg:phone":"+1 561 966 6465",
    "sg:postcode":"33406",
    "sg:province":"FL",
    "sg:tags":[
        "product",
        "mfg"
    ],
    "wof:name":"Best Price Boat Canvas",
    "wof:placetype":"venue"
},
  "geometry": {"coordinates":[-80.10239199999999,26.659512],"type":"Point"}
}