{
  "type": "Feature",
  "properties": {
    "iso:country":"US",
    "sg:address":"1 W Mckey St",
    "sg:city":"Ocoee",
    "sg:classifiers":[
        {
            "category":"Autos & Motor Vehicles",
            "subcategory":"Automobile Sales",
            "type":"Retail Goods"
        }
    ],
    "sg:phone":"+1 407 656 3700",
    "sg:postcode":"34761",
    "sg:province":"FL",
    "sg:tags":[
        "used",
        "car",
        "dealers-used",
        "new",
        "cars-wholesale"
    ],
    "wof:name":"Dj's Auto Sales Of Ocoee Inc",
    "wof:placetype":"venue"
},
  "geometry": {"coordinates":[-81.544113,28.5695],"type":"Point"}
}