{
  "type": "Feature",
  "properties": {
    "iso:country":"US",
    "sg:address":"2194 S Chickasaw Trl",
    "sg:city":"Orlando",
    "sg:classifiers":[
        {
            "category":"Shopping",
            "subcategory":"Department Store",
            "type":"Retail Goods"
        }
    ],
    "sg:phone":"+1 407 737 1260",
    "sg:postcode":"32825",
    "sg:province":"FL",
    "sg:tags":[
        "shop"
    ],
    "wof:name":"Dollar Shop",
    "wof:placetype":"venue"
},
  "geometry": {"coordinates":[-81.269093,28.514741],"type":"Point"}
}