{
  "type": "Feature",
  "properties": {
    "iso:country":"US",
    "sg:address":"2524 W Leroy St",
    "sg:city":"Tampa",
    "sg:classifiers":[
        {
            "category":"Restaurant",
            "type":"Food & Drink"
        }
    ],
    "sg:phone":"+1 813 876 6678",
    "sg:postcode":"33607",
    "sg:province":"FL",
    "sg:tags":[
        "style",
        "family"
    ],
    "wof:name":"La Familia Investment Group Inc",
    "wof:placetype":"venue"
},
  "geometry": {"coordinates":[-82.485328,27.971815],"type":"Point"}
}