{
  "type": "Feature",
  "properties": {
    "iso:country":"US",
    "sg:address":"14005 SW 106th Ter",
    "sg:city":"Miami",
    "sg:classifiers":[
        {
            "category":"Building & Trades",
            "subcategory":"Landscaping Services",
            "type":"Services"
        }
    ],
    "sg:phone":"+1 305 382 3569",
    "sg:postcode":"33186",
    "sg:province":"FL",
    "sg:tags":[
        "landscape"
    ],
    "wof:name":"J&D Tropical Landscapes Inc",
    "wof:placetype":"venue"
},
  "geometry": {"coordinates":[-80.42379099999999,25.668263],"type":"Point"}
}