{
  "type": "Feature",
  "properties": {
    "iso:country":"US",
    "sg:address":"5324 9th St N",
    "sg:city":"St Petersburg",
    "sg:classifiers":[
        {
            "category":"Insurance",
            "subcategory":"Insurance Agent",
            "type":"Services"
        }
    ],
    "sg:phone":"+1 727 525 2131",
    "sg:postcode":"33703",
    "sg:province":"FL",
    "wof:name":"John K Orr Insurance",
    "wof:placetype":"venue"
},
  "geometry": {"coordinates":[-82.646925,27.820135],"type":"Point"}
}