{
  "type": "Feature",
  "properties": {
    "addr:full":"704 Shady Lane Dr Fort Walton Beach FL 32547",
    "addr:housenumber":"704",
    "addr:postcode":"32547",
    "addr:street":"Shady Lane Dr",
    "iso:country":"US",
    "sg:address":"704 Shady Lane Dr",
    "sg:city":"Fort Walton Beach",
    "sg:classifiers":[
        {
            "category":"Building & Trades",
            "subcategory":"Construction",
            "type":"Services"
        }
    ],
    "sg:phone":"+1 850 699 2631",
    "sg:postcode":"32547",
    "sg:province":"FL",
    "sg:tags":[
        "contractor"
    ],
    "wof:name":"Julio & Nirama Drywall Inc",
    "wof:placetype":"venue"
},
  "geometry": {"coordinates":[-86.642194,30.437047],"type":"Point"}
}