{
  "type": "Feature",
  "properties": {
    "addr:full":"3250 Vineland Rd Kissimmee FL 34746",
    "addr:housenumber":"3250",
    "addr:postcode":"34746",
    "addr:street":"Vineland Rd",
    "iso:country":"US",
    "sg:address":"3250 Vineland Rd",
    "sg:city":"Kissimmee",
    "sg:classifiers":[
        {
            "category":"Restaurant",
            "type":"Food & Drink"
        }
    ],
    "sg:menulink":"http://www.allmenus.com/fl/kissimmee/207039-sonic/menu/",
    "sg:phone":"+1 407 396 9378",
    "sg:postcode":"34746",
    "sg:province":"FL",
    "sg:tags":[
        "burger",
        "american"
    ],
    "wof:name":"Sonic",
    "wof:placetype":"venue"
},
  "geometry": {"coordinates":[-81.48723699999999,28.346303],"type":"Point"}
}