{
  "type": "Feature",
  "properties": {
    "addr:full":"3837 Headsail Dr New Port Richey FL 34652",
    "addr:housenumber":"3837",
    "addr:postcode":"34652",
    "addr:street":"Headsail Dr",
    "iso:country":"US",
    "sg:address":"3837 Headsail Dr",
    "sg:city":"New Port Richey",
    "sg:classifiers":[
        {
            "category":"Restaurant",
            "type":"Food & Drink"
        }
    ],
    "sg:phone":"+1 727 844 0741",
    "sg:postcode":"34652",
    "sg:province":"FL",
    "sg:tags":[
        "eating"
    ],
    "wof:name":"Rainbow Diner Inc",
    "wof:placetype":"venue"
},
  "geometry": {"coordinates":[-82.751229,28.237242],"type":"Point"}
}