{
  "type": "Feature",
  "properties": {
    "iso:country":"US",
    "sg:address":"1900 Clifford St",
    "sg:city":"Fort Myers",
    "sg:classifiers":[
        {
            "category":"Professional",
            "subcategory":"Management & Consulting",
            "type":"Services"
        }
    ],
    "sg:phone":"+1 239 337 1497",
    "sg:postcode":"33901",
    "sg:province":"FL",
    "sg:tags":[
        "business"
    ],
    "wof:name":"Troika Consultants Inc",
    "wof:placetype":"venue"
},
  "geometry": {"coordinates":[-81.877269,26.639091],"type":"Point"}
}