{
  "type": "Feature",
  "properties": {
    "addr:full":"11190 NE 60th St Bronson FL 32621",
    "addr:housenumber":"11190",
    "addr:postcode":"32621",
    "addr:street":"Ne 60Th St",
    "iso:country":"US",
    "sg:address":"11190 NE 60th St",
    "sg:city":"Bronson",
    "sg:classifiers":[
        {
            "category":"Shopping",
            "type":"Retail Goods"
        }
    ],
    "sg:phone":"+1 352 486 3777",
    "sg:postcode":"32621",
    "sg:province":"FL",
    "sg:tags":[
        "regalia",
        "fraternal",
        "supply"
    ],
    "wof:name":"Kustom KUT",
    "wof:placetype":"venue"
},
  "geometry": {"coordinates":[-82.57969,29.421383],"type":"Point"}
}