{
  "type": "Feature",
  "properties": {
    "addr:full":"625 Mary Jane Ln Saint Augustine FL 32086",
    "addr:housenumber":"625",
    "addr:postcode":"32086",
    "addr:street":"Mary Jane Ln",
    "iso:country":"US",
    "sg:address":"625 Mary Jane Ln",
    "sg:city":"Saint Augustine",
    "sg:classifiers":[
        {
            "category":"Travel",
            "subcategory":"Travel Agent",
            "type":"Entertainment"
        }
    ],
    "sg:phone":"+1 904 794 2367",
    "sg:postcode":"32086",
    "sg:province":"FL",
    "sg:tags":[
        "agency"
    ],
    "wof:name":"Travel & Timber Inc",
    "wof:placetype":"venue"
},
  "geometry": {"coordinates":[-81.317564,29.764213],"type":"Point"}
}