{
  "type": "Feature",
  "properties": {
    "addr:full":"1800 7th St SW Winter Haven FL 33880",
    "addr:housenumber":"1800",
    "addr:postcode":"33880",
    "addr:street":"7Th St Sw",
    "iso:country":"US",
    "sg:address":"1800 7th St SW",
    "sg:city":"Winter Haven",
    "sg:classifiers":[
        {
            "category":"Freight",
            "type":"Transportation"
        }
    ],
    "sg:phone":"+1 863 294 9203",
    "sg:postcode":"33880",
    "sg:province":"FL",
    "wof:name":"Amtrak",
    "wof:placetype":"venue"
},
  "geometry": {"coordinates":[-81.735044,28.002912],"type":"Point"}
}