{
  "type": "Feature",
  "properties": {
    "iso:country":"US",
    "sg:address":"1025 Clearwater Largo Rd N",
    "sg:city":"Largo",
    "sg:classifiers":[
        {
            "category":"Real Estate",
            "subcategory":"Real Estate Operator",
            "type":"Services"
        }
    ],
    "sg:phone":"+1 727 584 7131",
    "sg:postcode":"33770",
    "sg:province":"FL",
    "sg:tags":[
        "mobile",
        "home",
        "motel",
        "park"
    ],
    "wof:name":"Belleair Vlg Mtl MBL HM Parks",
    "wof:placetype":"venue"
},
  "geometry": {"coordinates":[-82.796255,27.924977],"type":"Point"}
}