{
  "type": "Feature",
  "properties": {
    "addr:full":"8120 S Suncoast Blvd Homosassa FL 34446",
    "addr:housenumber":"8120",
    "addr:postcode":"34446",
    "addr:street":"S Suncoast Blvd",
    "iso:country":"US",
    "sg:address":"8120 S Suncoast Blvd",
    "sg:city":"Homosassa",
    "sg:classifiers":[
        {
            "category":"Building & Trades",
            "subcategory":"Construction",
            "type":"Services"
        }
    ],
    "sg:phone":"+1 352 382 4547",
    "sg:postcode":"34446",
    "sg:province":"FL",
    "sg:tags":[
        "home",
        "builder",
        "general",
        "family",
        "contractor"
    ],
    "wof:name":"Sweetwater Homes of Citrus",
    "wof:placetype":"venue"
},
  "geometry": {"coordinates":[-82.553144,28.745947],"type":"Point"}
}