{
  "type": "Feature",
  "properties": {
    "addr:full":"23026 Panama City Beach Pkwy Panama City Bch FL 32413",
    "addr:housenumber":"23026",
    "addr:postcode":"32413",
    "addr:street":"Panama;Beach Pkwy",
    "iso:country":"US",
    "sg:address":"23026 Panama City Beach Pkwy",
    "sg:city":"Panama City Bch",
    "sg:classifiers":[
        {
            "category":"Food & Beverages",
            "subcategory":"Groceries & Convenience Stores",
            "type":"Retail Goods"
        }
    ],
    "sg:phone":"+1 850 233 4392",
    "sg:postcode":"32413",
    "sg:province":"FL",
    "sg:tags":[
        "grocer"
    ],
    "wof:name":"Publix Super Market",
    "wof:placetype":"venue"
},
  "geometry": {"coordinates":[-85.97063300000001,30.264141],"type":"Point"}
}