{
  "type": "Feature",
  "properties": {
    "iso:country":"US",
    "sg:address":"5709 SE Abshier Blvd",
    "sg:city":"Belleview",
    "sg:classifiers":[
        {
            "category":"Professional",
            "subcategory":"Lawyer & Legal Services",
            "type":"Services"
        }
    ],
    "sg:phone":"+1 352 245 5184",
    "sg:postcode":"34420",
    "sg:province":"FL",
    "sg:tags":[
        "attorney"
    ],
    "wof:name":"Landt Wiechens Lapeer & Ayres",
    "wof:placetype":"venue"
},
  "geometry": {"coordinates":[-82.055233,29.059277],"type":"Point"}
}