{
  "type": "Feature",
  "properties": {
    "iso:country":"US",
    "sg:address":"950 N Collier Blvd",
    "sg:city":"Marco Island",
    "sg:classifiers":[
        {
            "category":"Insurance",
            "subcategory":"Insurance Agent",
            "type":"Services"
        }
    ],
    "sg:phone":"+1 239 394 3133",
    "sg:postcode":"34145",
    "sg:province":"FL",
    "wof:name":"Gulfshore Insurance Inc",
    "wof:placetype":"venue"
},
  "geometry": {"coordinates":[-81.727069,25.953477],"type":"Point"}
}