{
  "type": "Feature",
  "properties": {
    "iso:country":"US",
    "sg:address":"4005 W Cypress St",
    "sg:city":"Tampa",
    "sg:classifiers":[
        {
            "category":"Manufacturing",
            "subcategory":"Signs",
            "type":"Manufacturing & Wholesale Goods"
        }
    ],
    "sg:phone":"+1 813 876 6834",
    "sg:postcode":"33607",
    "sg:province":"FL",
    "wof:name":"Sign Systems & Graphic Designs",
    "wof:placetype":"venue"
},
  "geometry": {"coordinates":[-82.511786,27.95226],"type":"Point"}
}