{
  "type": "Feature",
  "properties": {
    "iso:country":"US",
    "sg:address":"1331 W Cass St",
    "sg:city":"Tampa",
    "sg:classifiers":[
        {
            "category":"Health Services",
            "subcategory":"Chiropractor",
            "type":"Services"
        }
    ],
    "sg:phone":"+1 813 251 4666",
    "sg:postcode":"33606",
    "sg:province":"FL",
    "wof:name":"City Chiropractic Clinic",
    "wof:placetype":"venue"
},
  "geometry": {"coordinates":[-82.474121,27.949867],"type":"Point"}
}