{
  "type": "Feature",
  "properties": {
    "iso:country":"US",
    "sg:address":"4302 Alton Rd",
    "sg:city":"Miami",
    "sg:classifiers":[
        {
            "category":"Health Services",
            "subcategory":"Medical Lab",
            "type":"Services"
        }
    ],
    "sg:phone":"+1 305 532 0436",
    "sg:postcode":"33140",
    "sg:province":"FL",
    "sg:tags":[
        "laboratory"
    ],
    "wof:name":"Laboratory Corp Of America",
    "wof:placetype":"venue"
},
  "geometry": {"coordinates":[-80.13775,25.815364],"type":"Point"}
}