{
  "type": "Feature",
  "properties": {
    "iso:country":"US",
    "sg:address":"6367 Alleghany Ave",
    "sg:city":"Cocoa",
    "sg:classifiers":[
        {
            "category":"Food & Beverages",
            "subcategory":"Specialty",
            "type":"Retail Goods"
        }
    ],
    "sg:phone":"+1 321 720 8008",
    "sg:postcode":"32927",
    "sg:province":"FL",
    "sg:tags":[
        "herb"
    ],
    "wof:name":"Live Cell Technology Inc",
    "wof:placetype":"venue"
},
  "geometry": {"coordinates":[-80.820072,28.467615],"type":"Point"}
}