{
  "type": "Feature",
  "properties": {
    "iso:country":"US",
    "sg:address":"7745 Indian Oaks Dr",
    "sg:city":"Vero Beach",
    "sg:classifiers":[
        {
            "category":"Banks & Credit Unions",
            "subcategory":"Investment Brokerage",
            "type":"Services"
        }
    ],
    "sg:phone":"+1 772 299 4035",
    "sg:postcode":"32966",
    "sg:province":"FL",
    "sg:tags":[
        "advisory",
        "financial"
    ],
    "wof:name":"Golf Investment Advisors",
    "wof:placetype":"venue"
},
  "geometry": {"coordinates":[-80.48469,27.6431],"type":"Point"}
}