{
  "type": "Feature",
  "properties": {
    "addr:full":"11760 SW 72nd Ave Miami FL 33156",
    "addr:housenumber":"11760",
    "addr:postcode":"33156",
    "addr:street":"Sw 72Nd Ave",
    "iso:country":"US",
    "sg:address":"11760 SW 72nd Ave",
    "sg:city":"Miami",
    "sg:classifiers":[
        {
            "category":"Marine",
            "type":"Transportation"
        }
    ],
    "sg:phone":"+1 305 378 6626",
    "sg:postcode":"33156",
    "sg:province":"FL",
    "sg:tags":[
        "equipment",
        "distributor",
        "supplies-wholesale"
    ],
    "wof:name":"D&S Marine Inc",
    "wof:placetype":"venue"
},
  "geometry": {"coordinates":[-80.310303,25.661909],"type":"Point"}
}