{
  "type": "Feature",
  "properties": {
    "addr:full":"1500 Apalachee Pkwy Tallahassee FL 32301",
    "addr:housenumber":"1500",
    "addr:postcode":"32301",
    "addr:street":"Apalachee Pkwy",
    "iso:country":"US",
    "sg:address":"1500 Apalachee Pkwy",
    "sg:city":"Tallahassee",
    "sg:classifiers":[
        {
            "category":"Home & Garden",
            "subcategory":"Furniture",
            "type":"Retail Goods"
        }
    ],
    "sg:phone":"+1 850 942 9888",
    "sg:postcode":"32301",
    "sg:province":"FL",
    "sg:tags":[
        "mattress"
    ],
    "wof:name":"Select Comfort Corp",
    "wof:placetype":"venue"
},
  "geometry": {"coordinates":[-84.251132,30.432944],"type":"Point"}
}