{
  "type": "Feature",
  "properties": {
    "addr:full":"2334 Meadow Ln Daytona Beach FL 32128",
    "addr:housenumber":"2334",
    "addr:postcode":"32128",
    "addr:street":"Meadow Ln",
    "iso:country":"US",
    "sg:address":"2334 Meadow Ln",
    "sg:city":"Daytona Beach",
    "sg:classifiers":[
        {
            "category":"Building & Trades",
            "subcategory":"Construction",
            "type":"Services"
        }
    ],
    "sg:phone":"+1 386 248 0033",
    "sg:postcode":"32128",
    "sg:province":"FL",
    "sg:tags":[
        "house"
    ],
    "wof:name":"Wise Builders LLC",
    "wof:placetype":"venue"
},
  "geometry": {"coordinates":[-81.05815200000001,29.09197],"type":"Point"}
}