{
  "type": "Feature",
  "properties": {
    "iso:country":"US",
    "sg:address":"13643 SW 26th St",
    "sg:city":"Miami",
    "sg:classifiers":[
        {
            "category":"Personal",
            "subcategory":"Beauty Salon",
            "type":"Services"
        }
    ],
    "sg:phone":"+1 305 551 7475",
    "sg:postcode":"33175",
    "sg:province":"FL",
    "sg:tags":[
        "treatment",
        "skin"
    ],
    "wof:name":"Luna Nueva",
    "wof:placetype":"venue"
},
  "geometry": {"coordinates":[-80.415437,25.743662],"type":"Point"}
}