{
  "type": "Feature",
  "properties": {
    "addr:full":"3205 Ridgeland Ct Tallahassee FL 32312",
    "addr:housenumber":"3205",
    "addr:postcode":"32312",
    "addr:street":"Ridgeland Ct",
    "iso:country":"US",
    "sg:address":"3205 Ridgeland Ct",
    "sg:city":"Tallahassee",
    "sg:classifiers":[
        {
            "category":"Professional",
            "subcategory":"Computer Services",
            "type":"Services"
        }
    ],
    "sg:phone":"+1 850 531 0084",
    "sg:postcode":"32312",
    "sg:province":"FL",
    "sg:tags":[
        "prepackaged",
        "software"
    ],
    "wof:name":"Diversified Technology Consult",
    "wof:placetype":"venue"
},
  "geometry": {"coordinates":[-84.28971,30.493996],"type":"Point"}
}