{
  "type": "Feature",
  "properties": {
    "addr:full":"7830 38th Ave N St Petersburg FL 33710",
    "addr:housenumber":"7830",
    "addr:postcode":"33710",
    "addr:street":"38Th Ave N",
    "iso:country":"US",
    "sg:address":"7830 38th Ave N",
    "sg:city":"St Petersburg",
    "sg:classifiers":[
        {
            "category":"Retail",
            "subcategory":"Repair Shop",
            "type":"Services"
        }
    ],
    "sg:phone":"+1 727 347 3103",
    "sg:postcode":"33710",
    "sg:province":"FL",
    "sg:tags":[
        "repairing",
        "lawn",
        "mower"
    ],
    "wof:name":"Affordable Mowers",
    "wof:placetype":"venue"
},
  "geometry": {"coordinates":[-82.74642799999999,27.806324],"type":"Point"}
}