{
  "type": "Feature",
  "properties": {
    "addr:full":"219 Monastery Ct Valrico FL 33594",
    "addr:housenumber":"219",
    "addr:postcode":"33594",
    "addr:street":"Monastery Ct",
    "iso:country":"US",
    "sg:address":"219 Monastery Ct",
    "sg:city":"Valrico",
    "sg:classifiers":[
        {
            "category":"Real Estate",
            "subcategory":"Real Estate Services",
            "type":"Services"
        }
    ],
    "sg:phone":"+1 866 307 9695",
    "sg:postcode":"33594",
    "sg:province":"FL",
    "sg:tags":[
        "apartment",
        "management",
        "rental",
        "finder"
    ],
    "sg:website":"http://tampabay.citysearch.com/profile/external/2658222/valrico_fl/hermitage_the.html?publisher=yellowpages&reference_id=1&placement=ypwebsitemip",
    "wof:name":"Hermitage, The",
    "wof:placetype":"venue"
},
  "geometry": {"coordinates":[-82.244372,27.940998],"type":"Point"}
}