{
  "type": "Feature",
  "properties": {
    "iso:country":"US",
    "sg:address":"2161 SW 59th Ave",
    "sg:city":"Miami",
    "sg:classifiers":[
        {
            "category":"Freight",
            "type":"Transportation"
        }
    ],
    "sg:phone":"+1 305 354 8184",
    "sg:postcode":"33155",
    "sg:province":"FL",
    "sg:tags":[
        "mover"
    ],
    "wof:name":"All Pro Van Lines",
    "wof:placetype":"venue"
},
  "geometry": {"coordinates":[-80.29138,25.751854],"type":"Point"}
}