{
  "type": "Feature",
  "properties": {
    "iso:country":"US",
    "sg:address":"2702 N Pine Hills Rd",
    "sg:city":"Orlando",
    "sg:classifiers":[
        {
            "category":"Food & Beverages",
            "subcategory":"Meat & Fish",
            "type":"Retail Goods"
        }
    ],
    "sg:phone":"+1 407 532 5111",
    "sg:postcode":"32808",
    "sg:province":"FL",
    "sg:tags":[
        "seafood"
    ],
    "wof:name":"Lucky Seafood & Wings",
    "wof:placetype":"venue"
},
  "geometry": {"coordinates":[-81.45161899999999,28.580046],"type":"Point"}
}