{
  "type": "Feature",
  "properties": {
    "addr:full":"1147 NE 4th Ave Fort Lauderdale FL 33304",
    "addr:housenumber":"1147",
    "addr:postcode":"33304",
    "addr:street":"Ne 4Th Ave",
    "iso:country":"US",
    "sg:address":"1147 NE 4th Ave",
    "sg:city":"Fort Lauderdale",
    "sg:classifiers":[
        {
            "category":"Home & Garden",
            "subcategory":"Garden Supply",
            "type":"Retail Goods"
        }
    ],
    "sg:phone":"+1 954 523 1117",
    "sg:postcode":"33304",
    "sg:province":"FL",
    "sg:tags":[
        "center"
    ],
    "wof:name":"River Of Grass Imports",
    "wof:placetype":"venue"
},
  "geometry": {"coordinates":[-80.140522,26.139666],"type":"Point"}
}