{
  "type": "Feature",
  "properties": {
    "iso:country":"US",
    "sg:address":"400 N Ashley Dr",
    "sg:city":"Tampa",
    "sg:classifiers":[
        {
            "category":"Real Estate",
            "subcategory":"Real Estate Agent",
            "type":"Services"
        }
    ],
    "sg:phone":"+1 813 229 2590",
    "sg:postcode":"33602",
    "sg:province":"FL",
    "sg:tags":[
        "management"
    ],
    "wof:name":"America's Capital Partners",
    "wof:placetype":"venue"
},
  "geometry": {"coordinates":[-82.45999999999999,27.947827],"type":"Point"}
}