{
  "type": "Feature",
  "properties": {
    "iso:country":"US",
    "sg:address":"1920 Jacaranda Dr",
    "sg:city":"Fort Pierce",
    "sg:classifiers":[
        {
            "category":"Banks & Credit Unions",
            "subcategory":"Financial Services",
            "type":"Services"
        }
    ],
    "sg:phone":"+1 772 595 5738",
    "sg:postcode":"34949",
    "sg:province":"FL",
    "sg:tags":[
        "company",
        "holding"
    ],
    "wof:name":"Ronbec Holdings",
    "wof:placetype":"venue"
},
  "geometry": {"coordinates":[-80.285956,27.448087],"type":"Point"}
}