{
  "type": "Feature",
  "properties": {
    "iso:country":"US",
    "sg:address":"8928 Taft St",
    "sg:city":"Hollywood",
    "sg:classifiers":[
        {
            "category":"Wholesale",
            "subcategory":"Machinery & Supplies",
            "type":"Manufacturing & Wholesale Goods"
        }
    ],
    "sg:phone":"+1 954 430 1175",
    "sg:postcode":"33024",
    "sg:province":"FL",
    "sg:tags":[
        "equipment",
        "industrial"
    ],
    "wof:name":"Continental Pool & Spa",
    "wof:placetype":"venue"
},
  "geometry": {"coordinates":[-80.26579,26.023084],"type":"Point"}
}