{
  "type": "Feature",
  "properties": {
    "addr:full":"5248 Red Bug Lake Rd. Winter Springs FL 32708",
    "addr:housenumber":"5248",
    "addr:postcode":"32708",
    "addr:street":"Red Bug Lake Rd.",
    "iso:country":"US",
    "sg:address":"5248 Red Bug Lake Rd.",
    "sg:city":"Winter Springs",
    "sg:classifiers":[
        {
            "category":"Bars & Pubs",
            "type":"Food & Drink"
        },
        {
            "category":"Restaurant",
            "type":"Food & Drink"
        }
    ],
    "sg:phone":"+1 407 699 4444",
    "sg:postcode":"32708",
    "sg:province":"FL",
    "sg:website":"www.stonewoodgrill.com",
    "wof:name":"Stonewood Grill & Tavern",
    "wof:placetype":"venue"
},
  "geometry": {"coordinates":[-81.276774,28.648262],"type":"Point"}
}