{
  "type": "Feature",
  "properties": {
    "addr:full":"1339 Pattison Ave Sarasota FL 34239",
    "addr:housenumber":"1339",
    "addr:postcode":"34239",
    "addr:street":"Pattison Ave",
    "iso:country":"US",
    "sg:address":"1339 Pattison Ave",
    "sg:city":"Sarasota",
    "sg:classifiers":[
        {
            "category":"Building & Trades",
            "subcategory":"Cleaning & Sanitation",
            "type":"Services"
        }
    ],
    "sg:phone":"+1 941 955 7546",
    "sg:postcode":"34239",
    "sg:province":"FL",
    "sg:tags":[
        "maintenance"
    ],
    "wof:name":"King Cleaning Service",
    "wof:placetype":"venue"
},
  "geometry": {"coordinates":[-82.511481,27.321971],"type":"Point"}
}