{
  "type": "Feature",
  "properties": {
    "addr:full":"625 Palm St West Palm Beach FL 33401",
    "addr:housenumber":"625",
    "addr:postcode":"33401",
    "addr:street":"Palm St",
    "iso:country":"US",
    "sg:address":"625 Palm St",
    "sg:city":"West Palm Beach",
    "sg:classifiers":[
        {
            "category":"Professional",
            "subcategory":"Computer Services",
            "type":"Services"
        }
    ],
    "sg:phone":"+1 561 820 2444",
    "sg:postcode":"33401",
    "sg:province":"FL",
    "sg:tags":[
        "prepackaged",
        "software"
    ],
    "wof:name":"Cirilium Holdings Inc",
    "wof:placetype":"venue"
},
  "geometry": {"coordinates":[-80.05783099999999,26.699463],"type":"Point"}
}