{
  "type": "Feature",
  "properties": {
    "iso:country":"US",
    "sg:address":"8234 NW 14th St",
    "sg:city":"Doral",
    "sg:classifiers":[
        {
            "category":"Insurance",
            "subcategory":"Insurance Agent",
            "type":"Services"
        }
    ],
    "sg:phone":"+1 305 463 7875",
    "sg:postcode":"33126",
    "sg:province":"FL",
    "wof:name":"All American Ins Brokers Inc",
    "wof:placetype":"venue"
},
  "geometry": {"coordinates":[-80.326984,25.786193],"type":"Point"}
}