{
  "type": "Feature",
  "properties": {
    "addr:full":"150 Clearwater Largo Rd N Largo FL 33770",
    "addr:housenumber":"150",
    "addr:postcode":"33770",
    "addr:street":"Clearwater Largo Rd N",
    "iso:country":"US",
    "sg:address":"150 Clearwater Largo Rd N",
    "sg:city":"Largo",
    "sg:classifiers":[
        {
            "category":"Restaurant",
            "type":"Food & Drink"
        }
    ],
    "sg:phone":"+1 727 518 0941",
    "sg:postcode":"33770",
    "sg:province":"FL",
    "wof:name":"Sonic Drive-In",
    "wof:placetype":"venue"
},
  "geometry": {"coordinates":[-82.796381,27.918111],"type":"Point"}
}