{
  "type": "Feature",
  "properties": {
    "iso:country":"US",
    "sg:address":"7560 Red Bug Lake Rd",
    "sg:city":"Oviedo",
    "sg:classifiers":[
        {
            "category":"Building & Trades",
            "subcategory":"Construction",
            "type":"Services"
        }
    ],
    "sg:phone":"+1 407 359 5499",
    "sg:postcode":"32765",
    "sg:province":"FL",
    "sg:tags":[
        "contractor"
    ],
    "wof:name":"Skorman Construction",
    "wof:placetype":"venue"
},
  "geometry": {"coordinates":[-81.24348500000001,28.650449],"type":"Point"}
}