{
  "type": "Feature",
  "properties": {
    "iso:country":"US",
    "sg:address":"8877 N 56th St",
    "sg:city":"Tampa",
    "sg:classifiers":[
        {
            "category":"Home & Garden",
            "subcategory":"Garden Supply",
            "type":"Retail Goods"
        }
    ],
    "sg:phone":"+1 813 514 9376",
    "sg:postcode":"33617",
    "sg:province":"FL",
    "sg:tags":[
        "center"
    ],
    "wof:name":"Grace Hydro Organic Garden Ctr",
    "wof:placetype":"venue"
},
  "geometry": {"coordinates":[-82.39339,28.031662],"type":"Point"}
}