{
  "type": "Feature",
  "properties": {
    "iso:country":"US",
    "sg:address":"12225 Collier Blvd",
    "sg:city":"Naples",
    "sg:classifiers":[
        {
            "category":"Restaurant",
            "type":"Food & Drink"
        }
    ],
    "sg:phone":"+1 239 455 1883",
    "sg:postcode":"34116",
    "sg:province":"FL",
    "sg:tags":[
        "eating"
    ],
    "wof:name":"KFC",
    "wof:placetype":"venue"
},
  "geometry": {"coordinates":[-81.68711999999999,26.191212],"type":"Point"}
}