{
  "type": "Feature",
  "properties": {
    "addr:full":"1620 Trade Center Way Naples FL 34109",
    "addr:housenumber":"1620",
    "addr:postcode":"34109",
    "addr:street":"Trade Center Way",
    "iso:country":"US",
    "sg:address":"1620 Trade Center Way",
    "sg:city":"Naples",
    "sg:classifiers":[
        {
            "category":"Wholesale",
            "subcategory":"Machinery & Supplies",
            "type":"Manufacturing & Wholesale Goods"
        }
    ],
    "sg:phone":"+1 239 594 1958",
    "sg:postcode":"34109",
    "sg:province":"FL",
    "wof:name":"Boynton Pump",
    "wof:placetype":"venue"
},
  "geometry": {"coordinates":[-81.76893099999999,26.225292],"type":"Point"}
}