{
  "type": "Feature",
  "properties": {
    "addr:full":"3446 S West Shore Blvd Tampa FL 33629",
    "addr:housenumber":"3446",
    "addr:postcode":"33629",
    "addr:street":"S West Shore Blvd",
    "iso:country":"US",
    "sg:address":"3446 S West Shore Blvd",
    "sg:city":"Tampa",
    "sg:classifiers":[
        {
            "category":"Retail",
            "subcategory":"Auto Rental",
            "type":"Services"
        }
    ],
    "sg:phone":"+1 813 837 9777",
    "sg:postcode":"33629",
    "sg:province":"FL",
    "sg:tags":[
        "renting",
        "truck",
        "leasing"
    ],
    "wof:name":"U-Haul Co",
    "wof:placetype":"venue"
},
  "geometry": {"coordinates":[-82.526636,27.91169],"type":"Point"}
}