{
  "type": "Feature",
  "properties": {
    "iso:country":"US",
    "sg:address":"4428 Hendricks Ave",
    "sg:city":"Jacksonville",
    "sg:classifiers":[
        {
            "category":"Shopping",
            "subcategory":"Pharmacy",
            "type":"Retail Goods"
        }
    ],
    "sg:phone":"+1 904 448 8181",
    "sg:postcode":"32207",
    "sg:province":"FL",
    "wof:name":"Advanced Rx Compouding Phrmcy",
    "wof:placetype":"venue"
},
  "geometry": {"coordinates":[-81.650471,30.27724],"type":"Point"}
}