{
  "type": "Feature",
  "properties": {
    "iso:country":"US",
    "sg:address":"8850 Goodby's Executive Dr",
    "sg:city":"Jacksonville",
    "sg:classifiers":[
        {
            "category":"Banks & Credit Unions",
            "subcategory":"Investment Brokerage",
            "type":"Services"
        }
    ],
    "sg:phone":"+1 904 733 3909",
    "sg:postcode":"32217",
    "sg:province":"FL",
    "sg:tags":[
        "security"
    ],
    "wof:name":"Securities America Inc",
    "wof:placetype":"venue"
},
  "geometry": {"coordinates":[-81.610896,30.21917],"type":"Point"}
}