{
  "type": "Feature",
  "properties": {
    "addr:full":"1003 N East Ave Sarasota FL 34237",
    "addr:housenumber":"1003",
    "addr:postcode":"34237",
    "addr:street":"N East Ave",
    "iso:country":"US",
    "sg:address":"1003 N East Ave",
    "sg:city":"Sarasota",
    "sg:classifiers":[
        {
            "category":"Building & Trades",
            "subcategory":"Construction",
            "type":"Services"
        }
    ],
    "sg:phone":"+1 941 955 3053",
    "sg:postcode":"34237",
    "sg:province":"FL",
    "sg:tags":[
        "fence",
        "contractor"
    ],
    "wof:name":"Jay's Fencing",
    "wof:placetype":"venue"
},
  "geometry": {"coordinates":[-82.528341,27.345591],"type":"Point"}
}