{
  "type": "Feature",
  "properties": {
    "addr:full":"661 53rd Ave S Saint Petersburg FL 33705",
    "addr:housenumber":"661",
    "addr:postcode":"33705",
    "addr:street":"53Rd Ave S",
    "iso:country":"US",
    "sg:address":"661 53rd Ave S",
    "sg:city":"Saint Petersburg",
    "sg:classifiers":[
        {
            "category":"Wholesale",
            "subcategory":"Non-durable Goods",
            "type":"Manufacturing & Wholesale Goods"
        }
    ],
    "sg:phone":"+1 727 867 1395",
    "sg:postcode":"33705",
    "sg:province":"FL",
    "wof:name":"Perry Virginia H Partylight Co",
    "wof:placetype":"venue"
},
  "geometry": {"coordinates":[-82.641402,27.72045],"type":"Point"}
}