{
  "type": "Feature",
  "properties": {
    "iso:country":"US",
    "sg:address":"936 Caribbean Pl",
    "sg:city":"Casselberry",
    "sg:classifiers":[
        {
            "category":"Retail",
            "subcategory":"Repair Shop",
            "type":"Services"
        }
    ],
    "sg:phone":"+1 407 695 5724",
    "sg:postcode":"32707",
    "sg:province":"FL",
    "sg:tags":[
        "related"
    ],
    "wof:name":"Grebz & Sons Repair",
    "wof:placetype":"venue"
},
  "geometry": {"coordinates":[-81.32513,28.691094],"type":"Point"}
}