{
  "type": "Feature",
  "properties": {
    "iso:country":"US",
    "sg:address":"8015 Front Beach Rd",
    "sg:city":"Panama City Bch",
    "sg:classifiers":[
        {
            "category":"Wholesale",
            "subcategory":"Tobacco Products",
            "type":"Manufacturing & Wholesale Goods"
        }
    ],
    "sg:phone":"+1 850 230 3006",
    "sg:postcode":"32407",
    "sg:province":"FL",
    "sg:tags":[
        "cigarette",
        "cigar",
        "dealer"
    ],
    "wof:name":"Smokes Tobacoo Outlet",
    "wof:placetype":"venue"
},
  "geometry": {"coordinates":[-85.773946,30.185349],"type":"Point"}
}