{
  "type": "Feature",
  "properties": {
    "iso:country":"US",
    "sg:address":"6317 Norwood Ave",
    "sg:city":"Jacksonville",
    "sg:classifiers":[
        {
            "category":"Personal",
            "subcategory":"Beauty Salon",
            "type":"Services"
        }
    ],
    "sg:phone":"+1 904 768 8222",
    "sg:postcode":"32208",
    "sg:province":"FL",
    "sg:tags":[
        "shop"
    ],
    "wof:name":"Tillys Beauty Salon",
    "wof:placetype":"venue"
},
  "geometry": {"coordinates":[-81.668237,30.377439],"type":"Point"}
}