{
  "type": "Feature",
  "properties": {
    "iso:country":"US",
    "sg:address":"3120 SW 120th Rd",
    "sg:city":"Miami",
    "sg:classifiers":[
        {
            "category":"Home & Garden",
            "subcategory":"Home Furnishings",
            "type":"Retail Goods"
        }
    ],
    "sg:phone":"+1 305 485 4430",
    "sg:postcode":"33175",
    "sg:province":"FL",
    "sg:tags":[
        "blinds-venetian",
        "vertical"
    ],
    "wof:name":"Iritas Blinds",
    "wof:placetype":"venue"
},
  "geometry": {"coordinates":[-80.38951400000001,25.739495],"type":"Point"}
}