{
  "type": "Feature",
  "properties": {
    "iso:country":"US",
    "sg:address":"12206 SW 129th Ct",
    "sg:city":"Miami",
    "sg:classifiers":[
        {
            "category":"Home & Garden",
            "subcategory":"Garden Supply",
            "type":"Retail Goods"
        },
        {
            "category":"Home & Garden",
            "subcategory":"Building Materials",
            "type":"Retail Goods"
        },
        {
            "category":"Manufacturing",
            "subcategory":"Building Materials",
            "type":"Manufacturing & Wholesale Goods"
        }
    ],
    "sg:phone":"+1 305 253 5137",
    "sg:postcode":"33186",
    "sg:province":"FL",
    "sg:tags":[
        "additive",
        "mulch",
        "topsoil",
        "concrete",
        "sand",
        "aggregate",
        "gravel"
    ],
    "wof:name":"Carl & Tom Waters' Sand Co",
    "wof:placetype":"venue"
},
  "geometry": {"coordinates":[-80.404388,25.652857],"type":"Point"}
}