{
  "type": "Feature",
  "properties": {
    "addr:full":"5374 SW 80th St Miami FL 33143",
    "addr:housenumber":"5374",
    "addr:postcode":"33143",
    "addr:street":"Sw 80Th St",
    "iso:country":"US",
    "sg:address":"5374 SW 80th St",
    "sg:city":"Miami",
    "sg:classifiers":[
        {
            "category":"Professional",
            "subcategory":"Lawyer & Legal Services",
            "type":"Services"
        }
    ],
    "sg:phone":"+1 305 667 9316",
    "sg:postcode":"33143",
    "sg:province":"FL",
    "wof:name":"Karcher David P Atty",
    "wof:placetype":"venue"
},
  "geometry": {"coordinates":[-80.279999,25.6973],"type":"Point"}
}