{
  "type": "Feature",
  "properties": {
    "addr:full":"300 Powerline Rd New Smyrna Beach FL 32168",
    "addr:housenumber":"300",
    "addr:postcode":"32168",
    "addr:street":"Powerline Rd",
    "iso:country":"US",
    "sg:address":"300 Powerline Rd",
    "sg:city":"New Smyrna Beach",
    "sg:classifiers":[
        {
            "category":"Building & Trades",
            "subcategory":"Construction",
            "type":"Services"
        }
    ],
    "sg:phone":"+1 386 427 7375",
    "sg:postcode":"32168",
    "sg:province":"FL",
    "sg:tags":[
        "maintenance",
        "contractor"
    ],
    "wof:name":"Five Star Maintenance",
    "wof:placetype":"venue"
},
  "geometry": {"coordinates":[-81.083648,29.027488],"type":"Point"}
}