{
  "type": "Feature",
  "properties": {
    "addr:full":"2900 SW 69th Ave Miami FL 33155",
    "addr:housenumber":"2900",
    "addr:postcode":"33155",
    "addr:street":"Sw 69Th Ave",
    "iso:country":"US",
    "sg:address":"2900 SW 69th Ave",
    "sg:city":"Miami",
    "sg:classifiers":[
        {
            "category":"Wholesale",
            "subcategory":"Fruits & Vegetables",
            "type":"Manufacturing & Wholesale Goods"
        }
    ],
    "sg:phone":"+1 305 233 5532",
    "sg:postcode":"33155",
    "sg:province":"FL",
    "sg:tags":[
        "packaging",
        "fresh"
    ],
    "wof:name":"Tur Corporation",
    "wof:placetype":"venue"
},
  "geometry": {"coordinates":[-80.306949,25.74298],"type":"Point"}
}