{
  "type": "Feature",
  "properties": {
    "iso:country":"US",
    "sg:address":"48 Miracle Strip Pkwy",
    "sg:city":"Fort Walton Bch",
    "sg:classifiers":[
        {
            "category":"Personal",
            "subcategory":"Barber",
            "type":"Services"
        }
    ],
    "sg:phone":"+1 850 301 9266",
    "sg:postcode":"32548",
    "sg:province":"FL",
    "wof:name":"Alan's Original Barber Shop",
    "wof:placetype":"venue"
},
  "geometry": {"coordinates":[-86.611068,30.403898],"type":"Point"}
}