{
  "type": "Feature",
  "properties": {
    "iso:country":"US",
    "sg:address":"85 Market St",
    "sg:city":"Apalachicola",
    "sg:classifiers":[
        {
            "category":"Shopping",
            "subcategory":"Jewelry",
            "type":"Retail Goods"
        }
    ],
    "sg:phone":"+1 850 653 8882",
    "sg:postcode":"32320",
    "sg:province":"FL",
    "wof:name":"Friperie",
    "wof:placetype":"venue"
},
  "geometry": {"coordinates":[-84.98368499999999,29.724001],"type":"Point"}
}