{
  "type": "Feature",
  "properties": {
    "iso:country":"US",
    "sg:address":"2800 Ponce De Leon Blvd",
    "sg:city":"Coral Gables",
    "sg:classifiers":[
        {
            "category":"Health Services",
            "subcategory":"Doctor",
            "type":"Services"
        }
    ],
    "sg:phone":"+1 305 444 0112",
    "sg:postcode":"33134",
    "sg:province":"FL",
    "sg:tags":[
        "dermatologist"
    ],
    "wof:name":"Cohen Bernard H MD PA",
    "wof:placetype":"venue"
},
  "geometry": {"coordinates":[-80.258797,25.746099],"type":"Point"}
}