{
  "type": "Feature",
  "properties": {
    "iso:country":"US",
    "sg:address":"2150 NW 93rd Ave",
    "sg:city":"Doral",
    "sg:classifiers":[
        {
            "category":"Wholesale",
            "subcategory":"Medical Equipment & Supplies",
            "type":"Manufacturing & Wholesale Goods"
        }
    ],
    "sg:phone":"+1 305 477 4773",
    "sg:postcode":"33172",
    "sg:province":"FL",
    "sg:tags":[
        "hospital"
    ],
    "wof:name":"Intramedica",
    "wof:placetype":"venue"
},
  "geometry": {"coordinates":[-80.34661,25.794352],"type":"Point"}
}