{
  "type": "Feature",
  "properties": {
    "addr:full":"37190 Singletary Rd Myakka City FL 34251",
    "addr:postcode":"37190;34251",
    "addr:street":"Singletary Rd",
    "iso:country":"US",
    "sg:address":"37190 Singletary Rd",
    "sg:city":"Myakka City",
    "sg:classifiers":[
        {
            "category":"Recreation",
            "type":"Entertainment"
        },
        {
            "category":"Organizations",
            "subcategory":"Community Association",
            "type":"Services"
        }
    ],
    "sg:phone":"+1 941 322 1900",
    "sg:postcode":"34251",
    "sg:province":"FL",
    "sg:tags":[
        "club",
        "membership"
    ],
    "wof:name":"Myakka City Community Center",
    "wof:placetype":"venue"
},
  "geometry": {"coordinates":[-82.162539,27.347343],"type":"Point"}
}