{
  "type": "Feature",
  "properties": {
    "iso:country":"US",
    "sg:address":"5451 Norwood Ave",
    "sg:city":"Jacksonville",
    "sg:classifiers":[
        {
            "category":"Shopping",
            "subcategory":"Discount & Variety Stores",
            "type":"Retail Goods"
        }
    ],
    "sg:phone":"+1 904 768 6976",
    "sg:postcode":"32208",
    "sg:province":"FL",
    "wof:name":"Allied Department Stores",
    "wof:placetype":"venue"
},
  "geometry": {"coordinates":[-81.66440900000001,30.372202],"type":"Point"}
}