{
  "type": "Feature",
  "properties": {
    "addr:full":"1044 Gay Rd Lakeland FL 33811",
    "addr:housenumber":"1044",
    "addr:postcode":"33811",
    "addr:street":"Gay Rd",
    "iso:country":"US",
    "sg:address":"1044 Gay Rd",
    "sg:city":"Lakeland",
    "sg:classifiers":[
        {
            "category":"Organizations",
            "subcategory":"Membership Organization",
            "type":"Services"
        }
    ],
    "sg:phone":"+1 863 686 4424",
    "sg:postcode":"33811",
    "sg:province":"FL",
    "wof:name":"H&H",
    "wof:placetype":"venue"
},
  "geometry": {"coordinates":[-82.01457000000001,28.029466],"type":"Point"}
}