{
  "type": "Feature",
  "properties": {
    "iso:country":"US",
    "sg:address":"4583 Appaloosa St",
    "sg:city":"West Palm Beach",
    "sg:classifiers":[
        {
            "category":"Building & Trades",
            "subcategory":"Construction",
            "type":"Services"
        }
    ],
    "sg:phone":"+1 561 686 8174",
    "sg:postcode":"33417",
    "sg:province":"FL",
    "sg:tags":[
        "carpentry",
        "contractor"
    ],
    "wof:name":"Victor Torres Trim",
    "wof:placetype":"venue"
},
  "geometry": {"coordinates":[-80.11243399999999,26.745694],"type":"Point"}
}