{
  "type": "Feature",
  "properties": {
    "addr:full":"21721 NE Hwy 27 Williston FL 32696",
    "addr:housenumber":"21721",
    "addr:postcode":"32696",
    "addr:street":"Ne Hwy 27",
    "iso:country":"US",
    "sg:address":"21721 NE Hwy 27",
    "sg:city":"Williston",
    "sg:classifiers":[
        {
            "category":"Shopping",
            "subcategory":"Used Merchandise",
            "type":"Retail Goods"
        }
    ],
    "sg:phone":"+1 352 528 0515",
    "sg:postcode":"32696",
    "sg:province":"FL",
    "sg:tags":[
        "antique"
    ],
    "wof:name":"Hill's Bargain Barn",
    "wof:placetype":"venue"
},
  "geometry": {"coordinates":[-82.411992,29.368529],"type":"Point"}
}