{
  "type": "Feature",
  "properties": {
    "iso:country":"US",
    "sg:address":"809 Driver Ave",
    "sg:city":"Winter Park",
    "sg:classifiers":[
        {
            "category":"Building & Trades",
            "subcategory":"Plumbing",
            "type":"Services"
        }
    ],
    "sg:phone":"+1 407 644 9855",
    "sg:postcode":"32789",
    "sg:province":"FL",
    "sg:tags":[
        "contractor"
    ],
    "wof:name":"Robbins Plumbing Inc",
    "wof:placetype":"venue"
},
  "geometry": {"coordinates":[-81.384636,28.589553],"type":"Point"}
}