{
  "type": "Feature",
  "properties": {
    "addr:full":"450 Harbor Ct Fort Myers Beach FL 33931",
    "addr:housenumber":"450",
    "addr:postcode":"33931",
    "addr:street":"Harbor Ct",
    "iso:country":"US",
    "sg:address":"450 Harbor Ct",
    "sg:city":"Fort Myers Beach",
    "sg:classifiers":[
        {
            "category":"Travel",
            "subcategory":"Hotels & Motels",
            "type":"Entertainment"
        }
    ],
    "sg:phone":"+1 239 765 7529",
    "sg:postcode":"33931",
    "sg:province":"FL",
    "sg:tags":[
        "casino"
    ],
    "wof:name":"Big M Casino",
    "wof:placetype":"venue"
},
  "geometry": {"coordinates":[-81.95693900000001,26.45656],"type":"Point"}
}