{
  "type": "Feature",
  "properties": {
    "iso:country":"US",
    "sg:address":"1222 Ravida Cir",
    "sg:city":"Orlando",
    "sg:classifiers":[
        {
            "category":"Professional",
            "subcategory":"Employment Agencies",
            "type":"Services"
        }
    ],
    "sg:phone":"+1 407 381 0661",
    "sg:postcode":"32825",
    "sg:province":"FL",
    "sg:tags":[
        "help",
        "supply"
    ],
    "wof:name":"Prieto Eliomar",
    "wof:placetype":"venue"
},
  "geometry": {"coordinates":[-81.241804,28.562657],"type":"Point"}
}