{
  "type": "Feature",
  "properties": {
    "addr:full":"28233 State Rd 54 Zephyrhills FL 33543",
    "addr:housenumber":"28233;54",
    "addr:postcode":"33543",
    "addr:street":"State Rd",
    "iso:country":"US",
    "sg:address":"28233 State Rd 54",
    "sg:city":"Zephyrhills",
    "sg:classifiers":[
        {
            "category":"Shopping",
            "type":"Retail Goods"
        }
    ],
    "sg:phone":"+1 813 973 4431",
    "sg:postcode":"33543",
    "sg:province":"FL",
    "sg:tags":[
        "pet",
        "shop"
    ],
    "wof:name":"Cassie's Pet Grooming",
    "wof:placetype":"venue"
},
  "geometry": {"coordinates":[-82.344897,28.237724],"type":"Point"}
}