{
  "type": "Feature",
  "properties": {
    "addr:full":"10389 159th Ct N Jupiter FL 33478",
    "addr:housenumber":"10389",
    "addr:postcode":"33478",
    "addr:street":"159Th Ct N",
    "iso:country":"US",
    "sg:address":"10389 159th Ct N",
    "sg:city":"Jupiter",
    "sg:classifiers":[
        {
            "category":"Shopping",
            "subcategory":"Used Merchandise",
            "type":"Retail Goods"
        }
    ],
    "sg:phone":"+1 561 747 5286",
    "sg:postcode":"33478",
    "sg:province":"FL",
    "wof:name":"Antiques/Clctbls By K McKenzi",
    "wof:placetype":"venue"
},
  "geometry": {"coordinates":[-80.195453,26.911922],"type":"Point"}
}