{
  "type": "Feature",
  "properties": {
    "iso:country":"US",
    "sg:address":"3660 SW 185th Ave",
    "sg:city":"Miramar",
    "sg:classifiers":[
        {
            "category":"Sports & Exercise",
            "subcategory":"Tennis Court",
            "type":"Entertainment"
        }
    ],
    "sg:phone":"+1 954 662 9658",
    "sg:postcode":"33029",
    "sg:province":"FL",
    "sg:tags":[
        "equipment",
        "supply"
    ],
    "wof:name":"Topspin Usa Inc",
    "wof:placetype":"venue"
},
  "geometry": {"coordinates":[-80.392776,25.975179],"type":"Point"}
}