{
  "type": "Feature",
  "properties": {
    "addr:full":"1300 Pine St Largo FL 33770",
    "addr:housenumber":"1300",
    "addr:postcode":"33770",
    "addr:street":"Pine St",
    "iso:country":"US",
    "sg:address":"1300 Pine St",
    "sg:city":"Largo",
    "sg:classifiers":[
        {
            "category":"Building & Trades",
            "subcategory":"Construction",
            "type":"Services"
        }
    ],
    "sg:phone":"+1 727 584 5944",
    "sg:postcode":"33770",
    "sg:province":"FL",
    "sg:tags":[
        "contractor",
        "paving",
        "asphalt",
        "sealcoating"
    ],
    "wof:name":"All-Phase Paving And Sealing",
    "wof:placetype":"venue"
},
  "geometry": {"coordinates":[-82.816383,27.905001],"type":"Point"}
}