{
  "type": "Feature",
  "properties": {
    "iso:country":"US",
    "sg:address":"3961 Black Forest Cir",
    "sg:city":"Boynton Beach",
    "sg:classifiers":[
        {
            "category":"Manufacturing",
            "subcategory":"Retail Goods",
            "type":"Manufacturing & Wholesale Goods"
        }
    ],
    "sg:phone":"+1 561 736 6607",
    "sg:postcode":"33436",
    "sg:province":"FL",
    "sg:tags":[
        "interior"
    ],
    "wof:name":"Kevin's Window Designs",
    "wof:placetype":"venue"
},
  "geometry": {"coordinates":[-80.106128,26.538056],"type":"Point"}
}