{
  "type": "Feature",
  "properties": {
    "addr:full":"8400 NW 25th St Miami FL 33122",
    "addr:housenumber":"8400",
    "addr:postcode":"33122",
    "addr:street":"Nw 25Th St",
    "iso:country":"US",
    "sg:address":"8400 NW 25th St",
    "sg:city":"Miami",
    "sg:classifiers":[
        {
            "category":"Professional",
            "subcategory":"Detective & Security Services",
            "type":"Services"
        }
    ],
    "sg:phone":"+1 305 470 1230",
    "sg:postcode":"33122",
    "sg:province":"FL",
    "sg:tags":[
        "system"
    ],
    "wof:name":"S A Cop-U Inc",
    "wof:placetype":"venue"
},
  "geometry": {"coordinates":[-80.337012,25.796941],"type":"Point"}
}