{
  "type": "Feature",
  "properties": {
    "iso:country":"US",
    "sg:address":"1430 E Park Cir",
    "sg:city":"Tampa",
    "sg:classifiers":[
        {
            "category":"Professional",
            "subcategory":"Management & Consulting",
            "type":"Services"
        }
    ],
    "sg:phone":"+1 813 239 3889",
    "sg:postcode":"33604",
    "sg:province":"FL",
    "sg:tags":[
        "marketing",
        "program"
    ],
    "wof:name":"Liz Taylor Marketing",
    "wof:placetype":"venue"
},
  "geometry": {"coordinates":[-82.44290100000001,28.015029],"type":"Point"}
}