{
  "type": "Feature",
  "properties": {
    "iso:country":"US",
    "sg:address":"2993 US Hwy 27",
    "sg:city":"Avon Park",
    "sg:classifiers":[
        {
            "category":"Freight",
            "type":"Transportation"
        }
    ],
    "sg:phone":"+1 863 453 5588",
    "sg:postcode":"33825",
    "sg:province":"FL",
    "sg:tags":[
        "auto",
        "company",
        "transport"
    ],
    "wof:name":"State To State Sales",
    "wof:placetype":"venue"
},
  "geometry": {"coordinates":[-81.52471799999999,27.640827],"type":"Point"}
}