{
  "type": "Feature",
  "properties": {
    "iso:country":"US",
    "sg:address":"5317 Gunn Hwy",
    "sg:city":"Tampa",
    "sg:classifiers":[
        {
            "category":"Retail",
            "subcategory":"Laundry & Dry Cleaning",
            "type":"Services"
        }
    ],
    "sg:phone":"+1 813 264 2990",
    "sg:postcode":"33624",
    "sg:province":"FL",
    "sg:tags":[
        "cleaners"
    ],
    "wof:name":"Hampton Cleaners",
    "wof:placetype":"venue"
},
  "geometry": {"coordinates":[-82.529775,28.056281],"type":"Point"}
}