{
  "type": "Feature",
  "properties": {
    "addr:full":"5431 NW 176th St Opa Locka FL 33055",
    "addr:housenumber":"5431",
    "addr:postcode":"33055",
    "addr:street":"Nw 176Th St;Locka",
    "iso:country":"US",
    "sg:address":"5431 NW 176th St",
    "sg:city":"Opa Locka",
    "sg:classifiers":[
        {
            "category":"Building & Trades",
            "subcategory":"Landscaping Services",
            "type":"Services"
        }
    ],
    "sg:phone":"+1 305 623 9388",
    "sg:postcode":"33055",
    "sg:province":"FL",
    "sg:tags":[
        "lawn",
        "maintenance",
        "grounds"
    ],
    "wof:name":"J P Lawn Svc",
    "wof:placetype":"venue"
},
  "geometry": {"coordinates":[-80.290508,25.933182],"type":"Point"}
}