{
  "type": "Feature",
  "properties": {
    "iso:country":"US",
    "sg:address":"2200 W Eau Gallie Blvd 202A",
    "sg:city":"Melbourne",
    "sg:classifiers":[
        {
            "category":"Health Services",
            "subcategory":"Doctor",
            "type":"Services"
        }
    ],
    "sg:phone":"+1 321 254 4773",
    "sg:postcode":"32935",
    "sg:province":"FL",
    "sg:tags":[
        "physician",
        "family",
        "practice",
        "surgeons",
        "medicine"
    ],
    "wof:name":"Binod Singh Md",
    "wof:placetype":"venue"
},
  "geometry": {"coordinates":[-80.656713,28.128816],"type":"Point"}
}