{
  "type": "Feature",
  "properties": {
    "iso:country":"US",
    "sg:address":"13135 SW 26th St",
    "sg:city":"Miami",
    "sg:classifiers":[
        {
            "category":"Communications",
            "type":"Services"
        }
    ],
    "sg:phone":"+1 305 227 6242",
    "sg:postcode":"33175",
    "sg:province":"FL",
    "wof:name":"Mdcps Mis Communications",
    "wof:placetype":"venue"
},
  "geometry": {"coordinates":[-80.40682200000001,25.743883],"type":"Point"}
}