{
  "type": "Feature",
  "properties": {
    "addr:full":"1036 NE 3rd Ave Homestead FL 33030",
    "addr:housenumber":"1036",
    "addr:postcode":"33030",
    "addr:street":"Ne 3Rd Ave",
    "iso:country":"US",
    "sg:address":"1036 NE 3rd Ave",
    "sg:city":"Homestead",
    "sg:classifiers":[
        {
            "category":"Banks & Credit Unions",
            "subcategory":"Bank",
            "type":"Services"
        }
    ],
    "sg:phone":"+1 305 247 7622",
    "sg:postcode":"33030",
    "sg:province":"FL",
    "sg:tags":[
        "mortgage",
        "loan",
        "broker",
        "real estate"
    ],
    "wof:name":"Arnason Mortgage Company",
    "wof:placetype":"venue"
},
  "geometry": {"coordinates":[-80.471598,25.480089],"type":"Point"}
}