{
  "type": "Feature",
  "properties": {
    "addr:full":"140 Intracoastal Pointe Dr Jupiter FL 33477",
    "addr:housenumber":"140",
    "addr:postcode":"33477",
    "addr:street":"Intracoastal Pointe Dr",
    "iso:country":"US",
    "sg:address":"140 Intracoastal Pointe Dr",
    "sg:city":"Jupiter",
    "sg:classifiers":[
        {
            "category":"Wholesale",
            "subcategory":"Machinery & Supplies",
            "type":"Manufacturing & Wholesale Goods"
        }
    ],
    "sg:phone":"+1 561 575 5775",
    "sg:postcode":"33477",
    "sg:province":"FL",
    "wof:name":"Science Applications Intl Corp",
    "wof:placetype":"venue"
},
  "geometry": {"coordinates":[-80.088707,26.934375],"type":"Point"}
}