{
  "type": "Feature",
  "properties": {
    "addr:full":"267 W Cocoa Beach Cswy Cocoa Beach FL 32931",
    "addr:housenumber":"267",
    "addr:postcode":"32931",
    "addr:street":"W Cocoa;Cswy",
    "iso:country":"US",
    "sg:address":"267 W Cocoa Beach Cswy",
    "sg:city":"Cocoa Beach",
    "sg:classifiers":[
        {
            "category":"Shopping",
            "type":"Retail Goods"
        }
    ],
    "sg:phone":"+1 321 783 5333",
    "sg:postcode":"32931",
    "sg:province":"FL",
    "sg:tags":[
        "merchandise",
        "supply"
    ],
    "wof:name":"Brevard Card",
    "wof:placetype":"venue"
},
  "geometry": {"coordinates":[-80.609616,28.357975],"type":"Point"}
}