{
  "type": "Feature",
  "properties": {
    "addr:full":"501 NW 12th Ave Miami FL 33136",
    "addr:housenumber":"501",
    "addr:postcode":"33136",
    "addr:street":"Nw 12Th Ave",
    "iso:country":"US",
    "sg:address":"501 NW 12th Ave",
    "sg:city":"Miami",
    "sg:classifiers":[
        {
            "category":"Food & Beverages",
            "subcategory":"Groceries & Convenience Stores",
            "type":"Retail Goods"
        }
    ],
    "sg:phone":"+1 305 547 1001",
    "sg:postcode":"33136",
    "sg:province":"FL",
    "wof:name":"Cuco's Mini Market",
    "wof:placetype":"venue"
},
  "geometry": {"coordinates":[-80.21481199999999,25.779291],"type":"Point"}
}