{
  "type": "Feature",
  "properties": {
    "iso:country":"US",
    "sg:address":"4730 Sarazen Dr",
    "sg:city":"Hollywood",
    "sg:classifiers":[
        {
            "category":"Professional",
            "subcategory":"Employment Agencies",
            "type":"Services"
        }
    ],
    "sg:phone":"+1 954 963 1512",
    "sg:postcode":"33021",
    "sg:province":"FL",
    "wof:name":"Half Price",
    "wof:placetype":"venue"
},
  "geometry": {"coordinates":[-80.192217,26.039469],"type":"Point"}
}