{
  "type": "Feature",
  "properties": {
    "iso:country":"US",
    "sg:address":"13020 Park Blvd",
    "sg:city":"Seminole",
    "sg:classifiers":[
        {
            "category":"Health Services",
            "subcategory":"Doctor",
            "type":"Services"
        },
        {
            "category":"Health Services",
            "subcategory":"Clinic",
            "type":"Services"
        },
        {
            "category":"Community Center",
            "type":"Public Place"
        }
    ],
    "sg:phone":"+1 727 393 3404",
    "sg:postcode":"33776",
    "sg:province":"FL",
    "sg:tags":[
        "physician",
        "family",
        "medical",
        "practice",
        "surgeons",
        "internal",
        "medicine"
    ],
    "sg:website":"http://www.oakmed.com",
    "wof:name":"Oakhurst Medical Clinic",
    "wof:placetype":"venue"
},
  "geometry": {"coordinates":[-82.81935300000001,27.843611],"type":"Point"}
}