{
  "type": "Feature",
  "properties": {
    "iso:country":"US",
    "sg:address":"4483 Real Ct",
    "sg:city":"Orlando",
    "sg:classifiers":[
        {
            "category":"Building & Trades",
            "subcategory":"Construction",
            "type":"Services"
        }
    ],
    "sg:phone":"+1 407 363 7541",
    "sg:postcode":"32808",
    "sg:province":"FL",
    "sg:tags":[
        "coating",
        "stucco",
        "exterior",
        "contractor"
    ],
    "wof:name":"F&B Stucco Associates Inc",
    "wof:placetype":"venue"
},
  "geometry": {"coordinates":[-81.43617,28.590333],"type":"Point"}
}