{
  "type": "Feature",
  "properties": {
    "addr:full":"5226 Glenmore Dr Lakeland FL 33813",
    "addr:housenumber":"5226",
    "addr:postcode":"33813",
    "addr:street":"Glenmore Dr",
    "iso:country":"US",
    "sg:address":"5226 Glenmore Dr",
    "sg:city":"Lakeland",
    "sg:classifiers":[
        {
            "category":"Building & Trades",
            "subcategory":"Landscaping Services",
            "type":"Services"
        }
    ],
    "sg:phone":"+1 863 648 4705",
    "sg:postcode":"33813",
    "sg:province":"FL",
    "wof:name":"Jasso Landscape Management Co",
    "wof:placetype":"venue"
},
  "geometry": {"coordinates":[-81.93580300000001,27.969222],"type":"Point"}
}