{
  "type": "Feature",
  "properties": {
    "iso:country":"US",
    "sg:address":"3600 Vineland Rd Ste 101",
    "sg:city":"Orlando",
    "sg:classifiers":[
        {
            "category":"Manufacturing",
            "subcategory":"Buildings",
            "type":"Manufacturing & Wholesale Goods"
        },
        {
            "category":"Building & Trades",
            "subcategory":"Construction",
            "type":"Services"
        }
    ],
    "sg:phone":"+1 407 841 1414",
    "sg:postcode":"32811",
    "sg:province":"FL",
    "sg:tags":[
        "industrial",
        "system",
        "specialty",
        "builder",
        "heating",
        "contractor",
        "contractors-commercial",
        "home",
        "air conditioning"
    ],
    "wof:name":"Webb William C Company",
    "wof:placetype":"venue"
},
  "geometry": {"coordinates":[-81.42862700000001,28.504177],"type":"Point"}
}