{
  "type": "Feature",
  "properties": {
    "iso:country":"US",
    "sg:address":"5522 W Sample Rd",
    "sg:city":"Margate",
    "sg:classifiers":[
        {
            "category":"Health Services",
            "subcategory":"Dentist",
            "type":"Services"
        }
    ],
    "sg:phone":"+1 954 968 4466",
    "sg:postcode":"33073",
    "sg:province":"FL",
    "sg:tags":[
        "dentists-cosmetic",
        "dental",
        "dentists-periodontists",
        "clinic",
        "dentists-endodontists",
        "dentistry",
        "implant",
        "dentists-implantology"
    ],
    "sg:website":"http://www.realpagessites.com/crescentdentalservices",
    "wof:name":"Crescent Dental",
    "wof:placetype":"venue"
},
  "geometry": {"coordinates":[-80.19750000000001,26.274044],"type":"Point"}
}