{
  "type": "Feature",
  "properties": {
    "addr:full":"7723 Anderson Rd Tampa FL 33634",
    "addr:housenumber":"7723",
    "addr:postcode":"33634",
    "addr:street":"Anderson Rd",
    "iso:country":"US",
    "sg:address":"7723 Anderson Rd",
    "sg:city":"Tampa",
    "sg:classifiers":[
        {
            "category":"Wholesale",
            "subcategory":"Machinery & Supplies",
            "type":"Manufacturing & Wholesale Goods"
        }
    ],
    "sg:phone":"+1 813 886 2700",
    "sg:postcode":"33634",
    "sg:province":"FL",
    "sg:tags":[
        "equipment",
        "establishment"
    ],
    "wof:name":"Seitz Inc",
    "wof:placetype":"venue"
},
  "geometry": {"coordinates":[-82.533946,28.018314],"type":"Point"}
}