{
  "type": "Feature",
  "properties": {
    "iso:country":"US",
    "sg:address":"15757 Sea Mist Ln",
    "sg:city":"West Palm Beach",
    "sg:classifiers":[
        {
            "category":"Farming",
            "subcategory":"Livestock Farm",
            "type":"Manufacturing & Wholesale Goods"
        }
    ],
    "sg:phone":"+1 561 753 0307",
    "sg:postcode":"33414",
    "sg:province":"FL",
    "sg:tags":[
        "equine"
    ],
    "wof:name":"Wild Ocean Farm",
    "wof:placetype":"venue"
},
  "geometry": {"coordinates":[-80.296172,26.632574],"type":"Point"}
}