{
  "type": "Feature",
  "properties": {
    "addr:full":"2706 White Sands Dr Sarasota FL 34231",
    "addr:housenumber":"2706",
    "addr:postcode":"34231",
    "addr:street":"White Sands Dr",
    "iso:country":"US",
    "sg:address":"2706 White Sands Dr",
    "sg:city":"Sarasota",
    "sg:classifiers":[
        {
            "category":"Building & Trades",
            "subcategory":"Construction",
            "type":"Services"
        }
    ],
    "sg:phone":"+1 941 922 4155",
    "sg:postcode":"34231",
    "sg:province":"FL",
    "sg:tags":[
        "hanging",
        "contractor"
    ],
    "wof:name":"Gary W Bullock S Painting",
    "wof:placetype":"venue"
},
  "geometry": {"coordinates":[-82.51048900000001,27.260897],"type":"Point"}
}