{
  "type": "Feature",
  "properties": {
    "addr:full":"14262 Citrus Way Brooksville FL 34601",
    "addr:housenumber":"14262",
    "addr:postcode":"34601",
    "addr:street":"Citrus Way",
    "iso:country":"US",
    "sg:address":"14262 Citrus Way",
    "sg:city":"Brooksville",
    "sg:classifiers":[
        {
            "category":"Farming",
            "subcategory":"Livestock Farm",
            "type":"Manufacturing & Wholesale Goods"
        }
    ],
    "sg:phone":"+1 352 797 9091",
    "sg:postcode":"34601",
    "sg:province":"FL",
    "sg:tags":[
        "beef",
        "feedlot",
        "cattle"
    ],
    "wof:name":"Walker Properties",
    "wof:placetype":"venue"
},
  "geometry": {"coordinates":[-82.446843,28.650167],"type":"Point"}
}