{
  "type": "Feature",
  "properties": {
    "iso:country":"US",
    "sg:address":"8737 Commodity Cir",
    "sg:city":"Orlando",
    "sg:classifiers":[
        {
            "category":"Restaurant",
            "type":"Food & Drink"
        }
    ],
    "sg:phone":"+1 407 903 5500",
    "sg:postcode":"32819",
    "sg:province":"FL",
    "sg:website":"www.planethollywood.com",
    "wof:name":"Planet Hollywood Inc",
    "wof:placetype":"venue"
},
  "geometry": {"coordinates":[-81.432478,28.445564],"type":"Point"}
}