{
  "type": "Feature",
  "properties": {
    "iso:country":"US",
    "sg:address":"802 N State St",
    "sg:city":"Bunnell",
    "sg:classifiers":[
        {
            "category":"Autos & Motor Vehicles",
            "subcategory":"Recreational Vehicle Sales",
            "type":"Retail Goods"
        }
    ],
    "sg:phone":"+1 386 586 5338",
    "sg:postcode":"32110",
    "sg:province":"FL",
    "sg:tags":[
        "camper"
    ],
    "wof:name":"RV Having Fun",
    "wof:placetype":"venue"
},
  "geometry": {"coordinates":[-81.264595,29.470561],"type":"Point"}
}