{
  "type": "Feature",
  "properties": {
    "iso:country":"US",
    "sg:address":"833 Monticello Ct",
    "sg:city":"Cape Coral",
    "sg:classifiers":[
        {
            "category":"Professional",
            "subcategory":"Management & Consulting",
            "type":"Services"
        }
    ],
    "sg:phone":"+1 239 945 5116",
    "sg:postcode":"33904",
    "sg:province":"FL",
    "wof:name":"Islandtime Management LLC",
    "wof:placetype":"venue"
},
  "geometry": {"coordinates":[-81.956534,26.552052],"type":"Point"}
}