{
  "type": "Feature",
  "properties": {
    "iso:country":"US",
    "sg:address":"6435 Wyndotte Rd",
    "sg:city":"Pensacola",
    "sg:classifiers":[
        {
            "category":"Building & Trades",
            "subcategory":"Electrical",
            "type":"Services"
        }
    ],
    "sg:phone":"+1 850 748 5748",
    "sg:postcode":"32526",
    "sg:province":"FL",
    "sg:tags":[
        "electrician"
    ],
    "wof:name":"D&T Electric Of Pensacola",
    "wof:placetype":"venue"
},
  "geometry": {"coordinates":[-87.356481,30.471901],"type":"Point"}
}