{
  "type": "Feature",
  "properties": {
    "addr:full":"761 NW 21st St Miami FL 33127",
    "addr:housenumber":"761",
    "addr:postcode":"33127",
    "addr:street":"Nw 21St St",
    "iso:country":"US",
    "sg:address":"761 NW 21st St",
    "sg:city":"Miami",
    "sg:classifiers":[
        {
            "category":"Retail",
            "subcategory":"Auto Rental",
            "type":"Services"
        },
        {
            "category":"Building & Trades",
            "subcategory":"Equipment Rental",
            "type":"Services"
        },
        {
            "category":"Retail",
            "subcategory":"Storage",
            "type":"Services"
        }
    ],
    "sg:phone":"+1 305 545 4885",
    "sg:postcode":"33127",
    "sg:province":"FL",
    "sg:tags":[
        "renting",
        "moving-self",
        "leasing",
        "truck",
        "van",
        "moving",
        "trailer"
    ],
    "sg:website":"http://www.budgettruck.com",
    "wof:name":"Budget Truck Rental",
    "wof:placetype":"venue"
},
  "geometry": {"coordinates":[-80.20828400000001,25.796113],"type":"Point"}
}