{
  "type": "Feature",
  "properties": {
    "iso:country":"US",
    "sg:address":"17801 NW 2nd Ave",
    "sg:city":"Miami",
    "sg:classifiers":[
        {
            "category":"Autos & Motor Vehicles",
            "subcategory":"Motorcycle Sales",
            "type":"Retail Goods"
        }
    ],
    "sg:phone":"+1 305 866 1440",
    "sg:postcode":"33169",
    "sg:province":"FL",
    "sg:tags":[
        "scooter"
    ],
    "wof:name":"Chewy's Street World",
    "wof:placetype":"venue"
},
  "geometry": {"coordinates":[-80.204866,25.938017],"type":"Point"}
}