{
  "type": "Feature",
  "properties": {
    "iso:country":"US",
    "sg:address":"4805 S Suncoast Blvd",
    "sg:city":"Homosassa",
    "sg:classifiers":[
        {
            "category":"Health Services",
            "subcategory":"Doctor",
            "type":"Services"
        }
    ],
    "sg:phone":"+1 352 628 0012",
    "sg:postcode":"34446",
    "sg:province":"FL",
    "wof:name":"Frank J Vascimini Dr",
    "wof:placetype":"venue"
},
  "geometry": {"coordinates":[-82.570261,28.792381],"type":"Point"}
}