{
  "type": "Feature",
  "properties": {
    "addr:full":"1738 Kingsley Ave Orange Park FL 32073",
    "addr:housenumber":"1738",
    "addr:postcode":"32073",
    "addr:street":"Kingsley Ave",
    "iso:country":"US",
    "sg:address":"1738 Kingsley Ave",
    "sg:city":"Orange Park",
    "sg:classifiers":[
        {
            "category":"Food & Beverages",
            "subcategory":"Groceries & Convenience Stores",
            "type":"Retail Goods"
        }
    ],
    "sg:phone":"+1 904 269 7222",
    "sg:postcode":"32073",
    "sg:province":"FL",
    "wof:name":"Granary Whole Foods Inc",
    "wof:placetype":"venue"
},
  "geometry": {"coordinates":[-81.73941499999999,30.164793],"type":"Point"}
}