{
  "type": "Feature",
  "properties": {
    "addr:full":"6336 Powerline Rd Fort Lauderdale FL 33309",
    "addr:housenumber":"6336",
    "addr:postcode":"33309",
    "addr:street":"Powerline Rd",
    "iso:country":"US",
    "sg:address":"6336 Powerline Rd",
    "sg:city":"Fort Lauderdale",
    "sg:classifiers":[
        {
            "category":"Shopping",
            "type":"Retail Goods"
        }
    ],
    "sg:phone":"+1 954 772 3227",
    "sg:postcode":"33309",
    "sg:province":"FL",
    "sg:tags":[
        "merchandise"
    ],
    "wof:name":"Call On US",
    "wof:placetype":"venue"
},
  "geometry": {"coordinates":[-80.15574599999999,26.206842],"type":"Point"}
}