{
  "type": "Feature",
  "properties": {
    "addr:full":"416 N Orange Ave Deland FL 32720",
    "addr:housenumber":"416",
    "addr:postcode":"32720",
    "addr:street":"N Orange Ave",
    "iso:country":"US",
    "sg:address":"416 N Orange Ave",
    "sg:city":"Deland",
    "sg:classifiers":[
        {
            "category":"Manufacturing",
            "subcategory":"Printing",
            "type":"Manufacturing & Wholesale Goods"
        }
    ],
    "sg:phone":"+1 386 734 7837",
    "sg:postcode":"32720",
    "sg:province":"FL",
    "sg:tags":[
        "lithographic",
        "printer",
        "commercial"
    ],
    "wof:name":"Cypress Printing Co",
    "wof:placetype":"venue"
},
  "geometry": {"coordinates":[-81.314053,29.033643],"type":"Point"}
}