{
  "type": "Feature",
  "properties": {
    "iso:country":"US",
    "sg:address":"7210 SW 57th Ave Ste 202-B",
    "sg:city":"South Miami",
    "sg:classifiers":[
        {
            "category":"Personal",
            "subcategory":"Massage",
            "type":"Services"
        }
    ],
    "sg:phone":"+1 315 278 1009",
    "sg:postcode":"33143",
    "sg:province":"FL",
    "sg:website":"www.sportsmassagemiami.com",
    "wof:name":"Tammy Frisinger, LMT",
    "wof:placetype":"venue"
},
  "geometry": {"coordinates":[-80.28540599999999,25.704342],"type":"Point"}
}