{
  "type": "Feature",
  "properties": {
    "addr:full":"8924 Winged Foot Dr Tallahassee FL 32312",
    "addr:housenumber":"8924",
    "addr:postcode":"32312",
    "addr:street":"Winged Foot Dr",
    "iso:country":"US",
    "sg:address":"8924 Winged Foot Dr",
    "sg:city":"Tallahassee",
    "sg:classifiers":[
        {
            "category":"Shopping",
            "subcategory":"Bicycles & Sporting Goods",
            "type":"Retail Goods"
        }
    ],
    "sg:phone":"+1 850 668 2441",
    "sg:postcode":"32312",
    "sg:province":"FL",
    "wof:name":"Priority Golf",
    "wof:placetype":"venue"
},
  "geometry": {"coordinates":[-84.224633,30.59456],"type":"Point"}
}