{
  "type": "Feature",
  "properties": {
    "iso:country":"US",
    "sg:address":"4000 Central Florida Blvd",
    "sg:city":"Orlando",
    "sg:classifiers":[
        {
            "category":"Education",
            "subcategory":"Special Training",
            "type":"Public Place"
        }
    ],
    "sg:phone":"+1 407 488 8868",
    "sg:postcode":"32816",
    "sg:province":"FL",
    "sg:tags":[
        "educational"
    ],
    "wof:name":"Florida Alliance For Arts Education, Inc.",
    "wof:placetype":"venue"
},
  "geometry": {"coordinates":[-81.203576,28.597305],"type":"Point"}
}