{
  "type": "Feature",
  "properties": {
    "iso:country":"US",
    "sg:address":"444 SE Monterey Rd",
    "sg:city":"Stuart",
    "sg:classifiers":[
        {
            "category":"Retail",
            "subcategory":"Auto Repair",
            "type":"Services"
        }
    ],
    "sg:phone":"+1 772 219 4321",
    "sg:postcode":"34994",
    "sg:province":"FL",
    "sg:tags":[
        "general"
    ],
    "wof:name":"Hernan & Sons Auto Repair",
    "wof:placetype":"venue"
},
  "geometry": {"coordinates":[-80.247007,27.17557],"type":"Point"}
}