{
  "type": "Feature",
  "properties": {
    "iso:country":"US",
    "sg:address":"3575 Hancock Rd",
    "sg:city":"Clermont",
    "sg:classifiers":[
        {
            "category":"Education",
            "subcategory":"School",
            "type":"Public Place"
        }
    ],
    "sg:phone":"+1 352 394 2123",
    "sg:postcode":"34711",
    "sg:province":"FL",
    "sg:website":"www.lake.k12.fl.us",
    "wof:name":"Windy Hill Middle School",
    "wof:placetype":"venue"
},
  "geometry": {"coordinates":[-81.70689900000001,28.515959],"type":"Point"}
}