{
  "type": "Feature",
  "properties": {
    "addr:full":"10214 Usa Today Way Hollywood FL 33025",
    "addr:postcode":"10214;33025",
    "addr:street":"Today Way",
    "iso:country":"US",
    "sg:address":"10214 Usa Today Way",
    "sg:city":"Hollywood",
    "sg:classifiers":[
        {
            "category":"Shopping",
            "subcategory":"Pharmacy",
            "type":"Retail Goods"
        },
        {
            "category":"Professional",
            "subcategory":"Management & Consulting",
            "type":"Services"
        }
    ],
    "sg:phone":"+1 954 442 7326",
    "sg:postcode":"33025",
    "sg:province":"FL",
    "wof:name":"Prescribit Rx LLC",
    "wof:placetype":"venue"
},
  "geometry": {"coordinates":[-80.280362,25.97654],"type":"Point"}
}