{
  "type": "Feature",
  "properties": {
    "iso:country":"US",
    "sg:address":"886 NE 79th St",
    "sg:city":"Miami",
    "sg:classifiers":[
        {
            "category":"Education",
            "subcategory":"Kindergarten",
            "type":"Public Place"
        }
    ],
    "sg:phone":"+1 305 756 6666",
    "sg:postcode":"33138",
    "sg:province":"FL",
    "sg:tags":[
        "school",
        "driving"
    ],
    "wof:name":"Redram Traffic School",
    "wof:placetype":"venue"
},
  "geometry": {"coordinates":[-80.178675,25.847859],"type":"Point"}
}