{
  "type": "Feature",
  "properties": {
    "addr:full":"12250 N 22nd St Tampa FL 33612",
    "addr:housenumber":"12250",
    "addr:postcode":"33612",
    "addr:street":"N 22Nd St",
    "iso:country":"US",
    "sg:address":"12250 N 22nd St",
    "sg:city":"Tampa",
    "sg:classifiers":[
        {
            "category":"Health Services",
            "subcategory":"Nursing And Care Facility",
            "type":"Services"
        }
    ],
    "sg:phone":"+1 813 975 5372",
    "sg:postcode":"33612",
    "sg:province":"FL",
    "sg:tags":[
        "home",
        "convalescent"
    ],
    "wof:name":"Lillian Peacock",
    "wof:placetype":"venue"
},
  "geometry": {"coordinates":[-82.434645,28.061312],"type":"Point"}
}