{
  "type": "Feature",
  "properties": {
    "addr:full":"16489 NW 49th Ave Hialeah FL 33014",
    "addr:housenumber":"16489",
    "addr:postcode":"33014",
    "addr:street":"Nw 49Th Ave",
    "iso:country":"US",
    "sg:address":"16489 NW 49th Ave",
    "sg:city":"Hialeah",
    "sg:classifiers":[
        {
            "category":"Manufacturing",
            "subcategory":"Textiles",
            "type":"Manufacturing & Wholesale Goods"
        }
    ],
    "sg:phone":"+1 305 430 0911",
    "sg:postcode":"33014",
    "sg:province":"FL",
    "sg:tags":[
        "textiles-manufacturers"
    ],
    "wof:name":"Century International",
    "wof:placetype":"venue"
},
  "geometry": {"coordinates":[-80.280636,25.92319],"type":"Point"}
}