{
  "type": "Feature",
  "properties": {
    "iso:country":"US",
    "sg:address":"4200 S John Young Pkwy",
    "sg:city":"Orlando",
    "sg:classifiers":[
        {
            "category":"Government",
            "subcategory":"Office",
            "type":"Public Place"
        }
    ],
    "sg:phone":"+1 407 836 7820",
    "sg:postcode":"32839",
    "sg:province":"FL",
    "wof:name":"John Young Maintenance Fclty",
    "wof:placetype":"venue"
},
  "geometry": {"coordinates":[-81.41749799999999,28.50121],"type":"Point"}
}