{
  "type": "Feature",
  "properties": {
    "iso:country":"US",
    "sg:address":"12650 NW 107th Ave",
    "sg:city":"Medley",
    "sg:classifiers":[
        {
            "category":"Shopping",
            "subcategory":"Florist",
            "type":"Retail Goods"
        }
    ],
    "sg:phone":"+1 305 863 8593",
    "sg:postcode":"33178",
    "sg:province":"FL",
    "wof:name":"Flowers Royale Inc",
    "wof:placetype":"venue"
},
  "geometry": {"coordinates":[-80.37204699999999,25.88615],"type":"Point"}
}