{
  "type": "Feature",
  "properties": {
    "iso:country":"US",
    "sg:address":"246 E Fort Dade Ave",
    "sg:city":"Brooksville",
    "sg:classifiers":[
        {
            "category":"Real Estate",
            "subcategory":"Real Estate Agent",
            "type":"Services"
        }
    ],
    "sg:phone":"+1 352 799 8070",
    "sg:postcode":"34601",
    "sg:province":"FL",
    "wof:name":"Landmark Realty",
    "wof:placetype":"venue"
},
  "geometry": {"coordinates":[-82.384632,28.556341],"type":"Point"}
}