{
  "type": "Feature",
  "properties": {
    "iso:country":"US",
    "sg:address":"1925 Brickell Ave",
    "sg:city":"Miami",
    "sg:classifiers":[
        {
            "category":"Building & Trades",
            "subcategory":"Construction",
            "type":"Services"
        }
    ],
    "sg:phone":"+1 305 858 5085",
    "sg:postcode":"33129",
    "sg:province":"FL",
    "sg:tags":[
        "house"
    ],
    "wof:name":"Say Construction LLC",
    "wof:placetype":"venue"
},
  "geometry": {"coordinates":[-80.197,25.755068],"type":"Point"}
}