{
  "type": "Feature",
  "properties": {
    "addr:full":"470 11th Ave Vero Beach FL 32962",
    "addr:housenumber":"470",
    "addr:postcode":"32962",
    "addr:street":"11Th Ave",
    "iso:country":"US",
    "sg:address":"470 11th Ave",
    "sg:city":"Vero Beach",
    "sg:classifiers":[
        {
            "category":"Building & Trades",
            "subcategory":"Construction",
            "type":"Services"
        }
    ],
    "sg:phone":"+1 772 569 8857",
    "sg:postcode":"32962",
    "sg:province":"FL",
    "sg:tags":[
        "residential",
        "commercial",
        "painting",
        "painter"
    ],
    "wof:name":"All City Texture Coating Pntg",
    "wof:placetype":"venue"
},
  "geometry": {"coordinates":[-80.39586799999999,27.611189],"type":"Point"}
}