{
  "type": "Feature",
  "properties": {
    "addr:full":"150 Bus Park Way Royal Palm Beach FL 33411",
    "addr:housenumber":"150",
    "addr:postcode":"33411",
    "addr:street":"Bus Park Way",
    "iso:country":"US",
    "sg:address":"150 Bus Park Way",
    "sg:city":"Royal Palm Beach",
    "sg:classifiers":[
        {
            "category":"Manufacturing",
            "subcategory":"Signs",
            "type":"Manufacturing & Wholesale Goods"
        }
    ],
    "sg:phone":"+1 561 792 0522",
    "sg:postcode":"33411",
    "sg:province":"FL",
    "wof:name":"Superior Engraving Inc",
    "wof:placetype":"venue"
},
  "geometry": {"coordinates":[-80.208682,26.697592],"type":"Point"}
}