{
  "type": "Feature",
  "properties": {
    "iso:country":"US",
    "sg:address":"1 Enterprise Dr",
    "sg:city":"Bunnell",
    "sg:classifiers":[
        {
            "category":"Retail",
            "subcategory":"Storage",
            "type":"Services"
        }
    ],
    "sg:phone":"+1 386 447 0222",
    "sg:postcode":"32110",
    "sg:province":"FL",
    "sg:tags":[
        "household",
        "commercial"
    ],
    "wof:name":"Mullen Development Inc",
    "wof:placetype":"venue"
},
  "geometry": {"coordinates":[-81.263161,29.526421],"type":"Point"}
}