{
  "type": "Feature",
  "properties": {
    "addr:full":"2800 Somerset Dr Fort Lauderdale FL 33311",
    "addr:housenumber":"2800",
    "addr:postcode":"33311",
    "addr:street":"Somerset Dr",
    "iso:country":"US",
    "sg:address":"2800 Somerset Dr",
    "sg:city":"Fort Lauderdale",
    "sg:classifiers":[
        {
            "category":"Building & Trades",
            "subcategory":"Landscaping Services",
            "type":"Services"
        }
    ],
    "sg:phone":"+1 954 731 2072",
    "sg:postcode":"33311",
    "sg:province":"FL",
    "wof:name":"Economical Lawn Maintenance In",
    "wof:placetype":"venue"
},
  "geometry": {"coordinates":[-80.18953399999999,26.163214],"type":"Point"}
}