{
  "type": "Feature",
  "properties": {
    "iso:country":"US",
    "sg:address":"411 Dracaena Dr",
    "sg:city":"Naples",
    "sg:classifiers":[
        {
            "category":"Building & Trades",
            "subcategory":"Construction",
            "type":"Services"
        }
    ],
    "sg:phone":"+1 239 417 2382",
    "sg:postcode":"34114",
    "sg:province":"FL",
    "sg:tags":[
        "restoration",
        "cleaning",
        "patio",
        "deck"
    ],
    "wof:name":"Thomas LA Prade Pressure Wshng",
    "wof:placetype":"venue"
},
  "geometry": {"coordinates":[-81.68920300000001,26.021697],"type":"Point"}
}