{
  "type": "Feature",
  "properties": {
    "iso:country":"US",
    "sg:address":"6550 SW 42nd St",
    "sg:city":"Palm City",
    "sg:classifiers":[
        {
            "category":"Building & Trades",
            "subcategory":"Construction",
            "type":"Services"
        }
    ],
    "sg:phone":"+1 772 283 8795",
    "sg:postcode":"34990",
    "sg:province":"FL",
    "sg:tags":[
        "concrete",
        "contractor"
    ],
    "wof:name":"Coral Concrete Inc",
    "wof:placetype":"venue"
},
  "geometry": {"coordinates":[-80.351044,27.154542],"type":"Point"}
}