{
  "type": "Feature",
  "properties": {
    "iso:country":"US",
    "sg:address":"112 W 5th Ave",
    "sg:city":"Tallahassee",
    "sg:classifiers":[
        {
            "category":"Professional",
            "subcategory":"Advertising",
            "type":"Services"
        }
    ],
    "sg:phone":"+1 850 577 0588",
    "sg:postcode":"32303",
    "sg:province":"FL",
    "sg:tags":[
        "mail",
        "direct"
    ],
    "wof:name":"Mailsouth",
    "wof:placetype":"venue"
},
  "geometry": {"coordinates":[-84.282967,30.454785],"type":"Point"}
}