{
  "type": "Feature",
  "properties": {
    "iso:country":"US",
    "sg:address":"729 NE 71st St",
    "sg:city":"Miami",
    "sg:classifiers":[
        {
            "category":"Professional",
            "type":"Services"
        }
    ],
    "sg:phone":"+1 305 606 8806",
    "sg:postcode":"33138",
    "sg:province":"FL",
    "sg:tags":[
        "caterer"
    ],
    "wof:name":"Michael S Catering",
    "wof:placetype":"venue"
},
  "geometry": {"coordinates":[-80.18171,25.840404],"type":"Point"}
}