{
  "type": "Feature",
  "properties": {
    "addr:full":"757 SE Hidden River Dr Port Saint Lucie FL 34983",
    "addr:housenumber":"757",
    "addr:postcode":"34983",
    "addr:street":"Se Hidden River Dr",
    "iso:country":"US",
    "sg:address":"757 SE Hidden River Dr",
    "sg:city":"Port Saint Lucie",
    "sg:classifiers":[
        {
            "category":"Professional",
            "subcategory":"Management & Consulting",
            "type":"Services"
        }
    ],
    "sg:phone":"+1 772 878 9001",
    "sg:postcode":"34983",
    "sg:province":"FL",
    "sg:tags":[
        "business"
    ],
    "wof:name":"Ameri-Kleen Services Inc",
    "wof:placetype":"venue"
},
  "geometry": {"coordinates":[-80.32675399999999,27.310543],"type":"Point"}
}