{
  "type": "Feature",
  "properties": {
    "addr:full":"4423 NW 34 Dr Gainesville FL 32605",
    "addr:housenumber":"4423",
    "addr:postcode":"32605",
    "addr:street":"Nw 34 Dr",
    "iso:country":"US",
    "sg:address":"4423 NW 34 Dr",
    "sg:city":"Gainesville",
    "sg:classifiers":[
        {
            "category":"Building & Trades",
            "subcategory":"Landscaping Services",
            "type":"Services"
        }
    ],
    "sg:phone":"+1 352 378 9562",
    "sg:postcode":"32605",
    "sg:province":"FL",
    "sg:tags":[
        "lawn",
        "maintenance",
        "grounds"
    ],
    "wof:name":"Lane's Lawn Svc",
    "wof:placetype":"venue"
},
  "geometry": {"coordinates":[-82.373615,29.696464],"type":"Point"}
}