{
  "type": "Feature",
  "properties": {
    "iso:country":"US",
    "sg:address":"70 Rock Hill Church Rd",
    "sg:city":"Cottondale",
    "sg:classifiers":[
        {
            "category":"Building & Trades",
            "subcategory":"Landscaping Services",
            "type":"Services"
        }
    ],
    "sg:phone":"+1 850 415 1845",
    "sg:postcode":"32431",
    "sg:province":"FL",
    "sg:tags":[
        "tree"
    ],
    "wof:name":"Chipola Landtree",
    "wof:placetype":"venue"
},
  "geometry": {"coordinates":[-85.455792,30.752473],"type":"Point"}
}