{
  "type": "Feature",
  "properties": {
    "addr:full":"10498 Spring Hill Dr Spring Hill FL 34608",
    "addr:housenumber":"10498",
    "addr:postcode":"34608",
    "addr:street":"Spring Hill Dr",
    "iso:country":"US",
    "sg:address":"10498 Spring Hill Dr",
    "sg:city":"Spring Hill",
    "sg:classifiers":[
        {
            "category":"Shopping",
            "subcategory":"Clothing, Apparel, & Fashions",
            "type":"Retail Goods"
        }
    ],
    "sg:phone":"+1 352 684 5226",
    "sg:postcode":"34608",
    "sg:province":"FL",
    "sg:tags":[
        "family"
    ],
    "wof:name":"Flava Wear Street Gear",
    "wof:placetype":"venue"
},
  "geometry": {"coordinates":[-82.542531,28.460912],"type":"Point"}
}