{
  "type": "Feature",
  "properties": {
    "iso:country":"US",
    "sg:address":"4800 Co Rd 19A",
    "sg:city":"Mt Dora",
    "sg:classifiers":[
        {
            "category":"Autos & Motor Vehicles",
            "subcategory":"Automobile Sales",
            "type":"Retail Goods"
        }
    ],
    "sg:phone":"+1 352 483 1200",
    "sg:postcode":"32757",
    "sg:province":"FL",
    "sg:tags":[
        "car",
        "dealer"
    ],
    "wof:name":"Bill Bryan Jeep",
    "wof:placetype":"venue"
},
  "geometry": {"coordinates":[-81.685391,28.820754],"type":"Point"}
}