{
  "type": "Feature",
  "properties": {
    "iso:country":"US",
    "sg:address":"2954 Macalpin Dr N",
    "sg:city":"Palm Harbor",
    "sg:classifiers":[
        {
            "category":"Organizations",
            "subcategory":"Membership Organization",
            "type":"Services"
        }
    ],
    "sg:phone":"+1 727 784 1258",
    "sg:postcode":"34684",
    "sg:province":"FL",
    "wof:name":"Hadassah",
    "wof:placetype":"venue"
},
  "geometry": {"coordinates":[-82.733892,28.092358],"type":"Point"}
}