{
  "type": "Feature",
  "properties": {
    "iso:country":"US",
    "sg:address":"4515 33rd Ave N",
    "sg:city":"St Petersburg",
    "sg:classifiers":[
        {
            "category":"Home & Garden",
            "subcategory":"Garden Supply",
            "type":"Retail Goods"
        }
    ],
    "sg:phone":"+1 727 526 1129",
    "sg:postcode":"33713",
    "sg:province":"FL",
    "sg:tags":[
        "tree"
    ],
    "wof:name":"Top Notch Tree Svc",
    "wof:placetype":"venue"
},
  "geometry": {"coordinates":[-82.69570400000001,27.801926],"type":"Point"}
}