{
  "type": "Feature",
  "properties": {
    "addr:full":"8382 Baymeadows Rd Jacksonville FL 32256",
    "addr:postcode":"8382;32256",
    "addr:street":"Baymeadows Rd",
    "iso:country":"US",
    "sg:address":"8382 Baymeadows Rd",
    "sg:city":"Jacksonville",
    "sg:classifiers":[
        {
            "category":"Professional",
            "subcategory":"Research",
            "type":"Services"
        }
    ],
    "sg:phone":"+1 904 724 0064",
    "sg:postcode":"32256",
    "sg:province":"FL",
    "sg:tags":[
        "foundation",
        "philanthropic"
    ],
    "wof:name":"Cystic Fibrosis Foundation",
    "wof:placetype":"venue"
},
  "geometry": {"coordinates":[-81.58391399999999,30.220684],"type":"Point"}
}