{
  "type": "Feature",
  "properties": {
    "addr:full":"17355 NW 59th Ave Hialeah FL 33015",
    "addr:housenumber":"17355",
    "addr:postcode":"33015",
    "addr:street":"Nw 59Th Ave",
    "iso:country":"US",
    "sg:address":"17355 NW 59th Ave",
    "sg:city":"Hialeah",
    "sg:classifiers":[
        {
            "category":"Cinema",
            "subcategory":"Movie Theater",
            "type":"Entertainment"
        }
    ],
    "sg:phone":"+1 305 231 5226",
    "sg:postcode":"33015",
    "sg:province":"FL",
    "sg:tags":[
        "motion",
        "picture"
    ],
    "wof:name":"Crown Theaters",
    "wof:placetype":"venue"
},
  "geometry": {"coordinates":[-80.29810000000001,25.932137],"type":"Point"}
}