{
  "type": "Feature",
  "properties": {
    "iso:country":"US",
    "sg:address":"379 Beth Page Rd",
    "sg:city":"Monticello",
    "sg:classifiers":[
        {
            "category":"Organizations",
            "subcategory":"Religious Organization",
            "type":"Services"
        }
    ],
    "sg:phone":"+1 850 997 0967",
    "sg:postcode":"32344",
    "sg:province":"FL",
    "sg:tags":[
        "church"
    ],
    "wof:name":"Beth Page Missionary Baptist",
    "wof:placetype":"venue"
},
  "geometry": {"coordinates":[-83.982753,30.368944],"type":"Point"}
}