{
  "type": "Feature",
  "properties": {
    "iso:country":"US",
    "sg:address":"1050 E 9th St",
    "sg:city":"Hialeah",
    "sg:classifiers":[
        {
            "category":"Manufacturing",
            "subcategory":"Tools & Machinery",
            "type":"Manufacturing & Wholesale Goods"
        }
    ],
    "sg:phone":"+1 305 887 1596",
    "sg:postcode":"33010",
    "sg:province":"FL",
    "sg:tags":[
        "mfg",
        "marine",
        "hardware",
        "equipment",
        "distributor",
        "supplies-wholesale"
    ],
    "wof:name":"Aqua-Air Manufacturing",
    "wof:placetype":"venue"
},
  "geometry": {"coordinates":[-80.260266,25.830691],"type":"Point"}
}