{
  "type": "Feature",
  "properties": {
    "iso:country":"US",
    "sg:address":"12107 Panama City Beach Pkwy",
    "sg:city":"Panama City Bch",
    "sg:classifiers":[
        {
            "category":"Real Estate",
            "subcategory":"Real Estate Agent",
            "type":"Services"
        }
    ],
    "sg:phone":"+1 850 230 4301",
    "sg:postcode":"32407",
    "sg:province":"FL",
    "wof:name":"Century 21",
    "wof:placetype":"venue"
},
  "geometry": {"coordinates":[-85.83351500000001,30.205412],"type":"Point"}
}