{
  "type": "Feature",
  "properties": {
    "iso:country":"US",
    "sg:address":"426 S Burkett Dr",
    "sg:city":"Panama City",
    "sg:classifiers":[
        {
            "category":"Organizations",
            "subcategory":"Religious Organization",
            "type":"Services"
        }
    ],
    "sg:phone":"+1 850 769 8836",
    "sg:postcode":"32404",
    "sg:province":"FL",
    "wof:name":"Panama City Korean Church",
    "wof:placetype":"venue"
},
  "geometry": {"coordinates":[-85.589292,30.141391],"type":"Point"}
}