{
  "type": "Feature",
  "properties": {
    "addr:full":"3330 Manor Cove Cir Riverview FL 33569",
    "addr:housenumber":"3330",
    "addr:postcode":"33569",
    "addr:street":"Manor Cove Cir",
    "iso:country":"US",
    "sg:address":"3330 Manor Cove Cir",
    "sg:city":"Riverview",
    "sg:classifiers":[
        {
            "category":"Recreation",
            "type":"Entertainment"
        }
    ],
    "sg:phone":"+1 813 246 9183",
    "sg:postcode":"33569",
    "sg:province":"FL",
    "sg:tags":[
        "center"
    ],
    "wof:name":"Pavillion Recreational Ctr",
    "wof:placetype":"venue"
},
  "geometry": {"coordinates":[-82.35278700000001,27.917748],"type":"Point"}
}