{
  "type": "Feature",
  "properties": {
    "addr:full":"2605 Thonotosassa Rd Plant City FL 33563",
    "addr:housenumber":"2605",
    "addr:postcode":"33563",
    "addr:street":"Thonotosassa Rd",
    "iso:country":"US",
    "sg:address":"2605 Thonotosassa Rd",
    "sg:city":"Plant City",
    "sg:classifiers":[
        {
            "category":"Personal",
            "subcategory":"Beauty Salon",
            "type":"Services"
        }
    ],
    "sg:phone":"+1 813 752 5407",
    "sg:postcode":"33563",
    "sg:province":"FL",
    "wof:name":"Hair Masters",
    "wof:placetype":"venue"
},
  "geometry": {"coordinates":[-82.150036,28.02538],"type":"Point"}
}