{
  "type": "Feature",
  "properties": {
    "iso:country":"US",
    "sg:address":"11030 SW 88th St",
    "sg:city":"Miami",
    "sg:classifiers":[
        {
            "category":"Health Services",
            "subcategory":"Dentist",
            "type":"Services"
        }
    ],
    "sg:phone":"+1 305 412 7202",
    "sg:postcode":"33176",
    "sg:province":"FL",
    "sg:tags":[
        "pediatric"
    ],
    "wof:name":"Smith Maria V DMD",
    "wof:placetype":"venue"
},
  "geometry": {"coordinates":[-80.374702,25.6866],"type":"Point"}
}