{
  "type": "Feature",
  "properties": {
    "addr:full":"3825 Henderson Blvd Tampa FL 33629",
    "addr:housenumber":"3825",
    "addr:postcode":"33629",
    "addr:street":"Henderson Blvd",
    "iso:country":"US",
    "sg:address":"3825 Henderson Blvd",
    "sg:city":"Tampa",
    "sg:classifiers":[
        {
            "category":"Banks & Credit Unions",
            "subcategory":"Investment Brokerage",
            "type":"Services"
        }
    ],
    "sg:phone":"+1 813 288 0889",
    "sg:postcode":"33629",
    "sg:province":"FL",
    "sg:tags":[
        "advisory",
        "financial"
    ],
    "wof:name":"Securities Trust Financial Grp",
    "wof:placetype":"venue"
},
  "geometry": {"coordinates":[-82.507504,27.932584],"type":"Point"}
}