{
  "type": "Feature",
  "properties": {
    "addr:full":"197 Lurton St Pensacola FL 32505",
    "addr:housenumber":"197",
    "addr:postcode":"32505",
    "addr:street":"Lurton St",
    "iso:country":"US",
    "sg:address":"197 Lurton St",
    "sg:city":"Pensacola",
    "sg:classifiers":[
        {
            "category":"Wholesale",
            "subcategory":"Electrical",
            "type":"Manufacturing & Wholesale Goods"
        }
    ],
    "sg:phone":"+1 850 432 3463",
    "sg:postcode":"32505",
    "sg:province":"FL",
    "sg:tags":[
        "equipment",
        "electric",
        "supply"
    ],
    "sg:website":"www.graybar.com",
    "wof:name":"Graybar Electric Co",
    "wof:placetype":"venue"
},
  "geometry": {"coordinates":[-87.231273,30.451225],"type":"Point"}
}