{
  "type": "Feature",
  "properties": {
    "addr:full":"2514 Mango Ave Sarasota FL 34234",
    "addr:housenumber":"2514",
    "addr:postcode":"34234",
    "addr:street":"Mango Ave",
    "iso:country":"US",
    "sg:address":"2514 Mango Ave",
    "sg:city":"Sarasota",
    "sg:classifiers":[
        {
            "category":"Building & Trades",
            "subcategory":"Construction",
            "type":"Services"
        }
    ],
    "sg:phone":"+1 239 450 0725",
    "sg:postcode":"34234",
    "sg:province":"FL",
    "sg:tags":[
        "plastering",
        "contractor"
    ],
    "wof:name":"Francis Armaud Stucco",
    "wof:placetype":"venue"
},
  "geometry": {"coordinates":[-82.52629,27.35879],"type":"Point"}
}