{
  "type": "Feature",
  "properties": {
    "iso:country":"US",
    "sg:address":"2640 NW 39th Ave",
    "sg:city":"Gainesville",
    "sg:classifiers":[
        {
            "category":"Organizations",
            "subcategory":"Religious Organization",
            "type":"Services"
        }
    ],
    "sg:phone":"+1 352 378 1800",
    "sg:postcode":"32605",
    "sg:province":"FL",
    "sg:tags":[
        "church"
    ],
    "sg:website":"www.creeksidecc.org",
    "wof:name":"Creekside Community Church",
    "wof:placetype":"venue"
},
  "geometry": {"coordinates":[-82.36278900000001,29.688652],"type":"Point"}
}