{
  "type": "Feature",
  "properties": {
    "iso:country":"US",
    "sg:address":"1322 NE 4th Ave",
    "sg:city":"Fort Lauderdale",
    "sg:classifiers":[
        {
            "category":"Real Estate",
            "subcategory":"Real Estate Agent",
            "type":"Services"
        }
    ],
    "sg:phone":"+1 954 523 2315",
    "sg:postcode":"33304",
    "sg:province":"FL",
    "wof:name":"First Florida Real Estate",
    "wof:placetype":"venue"
},
  "geometry": {"coordinates":[-80.14055,26.143641],"type":"Point"}
}