{
  "type": "Feature",
  "properties": {
    "iso:country":"US",
    "sg:address":"2451 N McMullen Booth Rd",
    "sg:city":"Clearwater",
    "sg:classifiers":[
        {
            "category":"Restaurant",
            "type":"Food & Drink"
        }
    ],
    "sg:phone":"+1 727 669 8618",
    "sg:postcode":"33759",
    "sg:province":"FL",
    "sg:tags":[
        "grocery",
        "store"
    ],
    "wof:name":"Eastern Favor Mini Shop",
    "wof:placetype":"venue"
},
  "geometry": {"coordinates":[-82.70884700000001,28.009195],"type":"Point"}
}