{
  "type": "Feature",
  "properties": {
    "iso:country":"US",
    "sg:address":"803 Village Pl",
    "sg:city":"Lakeland",
    "sg:classifiers":[
        {
            "category":"Shopping",
            "subcategory":"Bicycles & Sporting Goods",
            "type":"Retail Goods"
        }
    ],
    "sg:phone":"+1 863 413 0410",
    "sg:postcode":"33815",
    "sg:province":"FL",
    "wof:name":"Shooters Supply Gun Shop",
    "wof:placetype":"venue"
},
  "geometry": {"coordinates":[-82.013595,28.035561],"type":"Point"}
}