{
  "type": "Feature",
  "properties": {
    "iso:country":"US",
    "sg:address":"2889 SW Collings Dr",
    "sg:city":"Port Saint Lucie",
    "sg:classifiers":[
        {
            "category":"Building & Trades",
            "subcategory":"Landscaping Services",
            "type":"Services"
        }
    ],
    "sg:phone":"+1 772 336 5334",
    "sg:postcode":"34953",
    "sg:province":"FL",
    "wof:name":"Dovey S Lawn Service",
    "wof:placetype":"venue"
},
  "geometry": {"coordinates":[-80.394925,27.257903],"type":"Point"}
}