{
  "type": "Feature",
  "properties": {
    "iso:country":"US",
    "sg:address":"107 Beaumont Ln",
    "sg:city":"Palm Beach Gdns",
    "sg:classifiers":[
        {
            "category":"Personal",
            "type":"Services"
        }
    ],
    "sg:phone":"+1 561 313 9148",
    "sg:postcode":"33410",
    "sg:province":"FL",
    "sg:tags":[
        "therapist",
        "massage"
    ],
    "wof:name":"Carmenzas Healing Touch",
    "wof:placetype":"venue"
},
  "geometry": {"coordinates":[-80.104206,26.849892],"type":"Point"}
}