{
  "type": "Feature",
  "properties": {
    "iso:country":"US",
    "sg:address":"1820 Shawnee Trl",
    "sg:city":"Maitland",
    "sg:classifiers":[
        {
            "category":"Banks & Credit Unions",
            "subcategory":"Bank",
            "type":"Services"
        }
    ],
    "sg:phone":"+1 407 539 2826",
    "sg:postcode":"32751",
    "sg:province":"FL",
    "sg:tags":[
        "loan",
        "real estate"
    ],
    "wof:name":"Gooding & Co Mortgage",
    "wof:placetype":"venue"
},
  "geometry": {"coordinates":[-81.34685500000001,28.633314],"type":"Point"}
}