{
  "type": "Feature",
  "properties": {
    "iso:country":"US",
    "sg:address":"2220 SW Hwy 484 Ste C",
    "sg:city":"Ocala",
    "sg:classifiers":[
        {
            "category":"Home & Garden",
            "subcategory":"Building Materials",
            "type":"Retail Goods"
        },
        {
            "category":"Building & Trades",
            "subcategory":"Construction",
            "type":"Services"
        },
        {
            "category":"Home & Garden",
            "subcategory":"Carpets & Floor Coverings",
            "type":"Retail Goods"
        }
    ],
    "sg:phone":"+1 352 347 4008",
    "sg:postcode":"34473",
    "sg:province":"FL",
    "sg:tags":[
        "bathroom",
        "roof",
        "improvement",
        "accessory",
        "tile-contractors",
        "fixtures",
        "cabinet",
        "remodeling",
        "structure"
    ],
    "sg:website":"http://www.firstchoicegrout.com",
    "wof:name":"OCALA TILE & CONTRACTORS, INC",
    "wof:placetype":"venue"
},
  "geometry": {"coordinates":[-82.16017100000001,29.025477],"type":"Point"}
}