{
  "type": "Feature",
  "properties": {
    "addr:full":"1822 Edgewater Dr Orlando FL 32804",
    "addr:housenumber":"1822",
    "addr:postcode":"32804",
    "addr:street":"Edgewater Dr",
    "iso:country":"US",
    "sg:address":"1822 Edgewater Dr",
    "sg:city":"Orlando",
    "sg:classifiers":[
        {
            "category":"Professional",
            "subcategory":"Business Services",
            "type":"Services"
        },
        {
            "category":"Home & Garden",
            "subcategory":"Furniture",
            "type":"Retail Goods"
        }
    ],
    "sg:phone":"+1 407 423 1224",
    "sg:postcode":"32804",
    "sg:province":"FL",
    "sg:tags":[
        "interior",
        "consultant",
        "designer",
        "design",
        "decorator"
    ],
    "wof:name":"Gribble Interior Group Inc",
    "wof:placetype":"venue"
},
  "geometry": {"coordinates":[-81.38947899999999,28.568699],"type":"Point"}
}