{
  "type": "Feature",
  "properties": {
    "iso:country":"US",
    "sg:address":"103400 Overseas Hwy",
    "sg:city":"Key Largo",
    "sg:classifiers":[
        {
            "category":"Shopping",
            "subcategory":"Pharmacy",
            "type":"Retail Goods"
        }
    ],
    "sg:phone":"+1 305 451 2512",
    "sg:postcode":"33037",
    "sg:province":"FL",
    "sg:tags":[
        "photofinishing",
        "laboratory"
    ],
    "wof:name":"Walgreens",
    "wof:placetype":"venue"
},
  "geometry": {"coordinates":[-80.405044,25.134716],"type":"Point"}
}