{
  "type": "Feature",
  "properties": {
    "iso:country":"US",
    "sg:address":"325 S 3rd St",
    "sg:city":"Lantana",
    "sg:classifiers":[
        {
            "category":"Manufacturing",
            "subcategory":"Printing",
            "type":"Manufacturing & Wholesale Goods"
        }
    ],
    "sg:phone":"+1 561 585 0949",
    "sg:postcode":"33462",
    "sg:province":"FL",
    "sg:tags":[
        "printer"
    ],
    "wof:name":"Rudik Printing Inc",
    "wof:placetype":"venue"
},
  "geometry": {"coordinates":[-80.052769,26.581735],"type":"Point"}
}