{
  "type": "Feature",
  "properties": {
    "iso:country":"US",
    "sg:address":"100 Southpark Blvd",
    "sg:city":"Saint Augustine",
    "sg:classifiers":[
        {
            "category":"Health Services",
            "subcategory":"Doctor",
            "type":"Services"
        }
    ],
    "sg:phone":"+1 904 827 9600",
    "sg:postcode":"32086",
    "sg:province":"FL",
    "sg:tags":[
        "medical"
    ],
    "wof:name":"Emanuel Martinez MD",
    "wof:placetype":"venue"
},
  "geometry": {"coordinates":[-81.322996,29.862582],"type":"Point"}
}