{
  "type": "Feature",
  "properties": {
    "addr:full":"6325 Siguenza Dr Pensacola FL 32507",
    "addr:housenumber":"6325",
    "addr:postcode":"32507",
    "addr:street":"Siguenza Dr",
    "iso:country":"US",
    "sg:address":"6325 Siguenza Dr",
    "sg:city":"Pensacola",
    "sg:classifiers":[
        {
            "category":"Building & Trades",
            "subcategory":"Landscaping Services",
            "type":"Services"
        }
    ],
    "sg:phone":"+1 850 492 8924",
    "sg:postcode":"32507",
    "sg:province":"FL",
    "sg:tags":[
        "tree"
    ],
    "wof:name":"Budget Tree Svc",
    "wof:placetype":"venue"
},
  "geometry": {"coordinates":[-87.424027,30.307787],"type":"Point"}
}