{
  "type": "Feature",
  "properties": {
    "addr:full":"244 E Highland Ave Clermont FL 34711",
    "addr:housenumber":"244",
    "addr:postcode":"34711",
    "addr:street":"E Highland Ave",
    "iso:country":"US",
    "sg:address":"244 E Highland Ave",
    "sg:city":"Clermont",
    "sg:classifiers":[
        {
            "category":"Real Estate",
            "subcategory":"Real Estate Services",
            "type":"Services"
        }
    ],
    "sg:phone":"+1 352 394 2515",
    "sg:postcode":"34711",
    "sg:province":"FL",
    "sg:tags":[
        "company",
        "title"
    ],
    "wof:name":"Eagle Title",
    "wof:placetype":"venue"
},
  "geometry": {"coordinates":[-81.756192,28.551623],"type":"Point"}
}