{
  "type": "Feature",
  "properties": {
    "iso:country":"US",
    "sg:address":"125 Olympic Club Ct",
    "sg:city":"Orlando",
    "sg:classifiers":[
        {
            "category":"Wholesale",
            "subcategory":"Chemicals & Plastics",
            "type":"Manufacturing & Wholesale Goods"
        }
    ],
    "sg:phone":"+1 407 761 0587",
    "sg:postcode":"32828",
    "sg:province":"FL",
    "sg:tags":[
        "conditioner",
        "air",
        "for",
        "adhesive"
    ],
    "wof:name":"Quality Coat  Inc",
    "wof:placetype":"venue"
},
  "geometry": {"coordinates":[-81.190729,28.531617],"type":"Point"}
}