{
  "type": "Feature",
  "properties": {
    "iso:country":"US",
    "sg:address":"23 SE 2nd Ave",
    "sg:city":"Miami",
    "sg:classifiers":[
        {
            "category":"Personal",
            "subcategory":"Beauty Salon",
            "type":"Services"
        }
    ],
    "sg:phone":"+1 305 577 4999",
    "sg:postcode":"33131",
    "sg:province":"FL",
    "wof:name":"Spa Salon",
    "wof:placetype":"venue"
},
  "geometry": {"coordinates":[-80.190128,25.773598],"type":"Point"}
}