{
  "type": "Feature",
  "properties": {
    "iso:country":"US",
    "sg:address":"1372 S State Rd 545",
    "sg:city":"Winter Garden",
    "sg:classifiers":[
        {
            "category":"Freight",
            "type":"Transportation"
        }
    ],
    "sg:phone":"+1 407 656 4369",
    "sg:postcode":"34787",
    "sg:province":"FL",
    "sg:tags":[
        "delivery"
    ],
    "wof:name":"C & P Delivery",
    "wof:placetype":"venue"
},
  "geometry": {"coordinates":[-81.607904,28.546173],"type":"Point"}
}