{
  "type": "Feature",
  "properties": {
    "iso:country":"US",
    "sg:address":"2755 SW 58th St",
    "sg:city":"Ocala",
    "sg:classifiers":[
        {
            "category":"Shopping",
            "subcategory":"Computers & Home Electronics",
            "type":"Retail Goods"
        }
    ],
    "sg:phone":"+1 352 367 1000",
    "sg:postcode":"34471",
    "sg:province":"FL",
    "sg:tags":[
        "equipment",
        "satellite",
        "system"
    ],
    "wof:name":"Advanved Satellite & Antenna",
    "wof:placetype":"venue"
},
  "geometry": {"coordinates":[-82.17836699999999,29.129591],"type":"Point"}
}