{
  "type": "Feature",
  "properties": {
    "iso:country":"US",
    "sg:address":"1950 Wrenfield Ln",
    "sg:city":"Oviedo",
    "sg:classifiers":[
        {
            "category":"Real Estate",
            "subcategory":"Real Estate Agent",
            "type":"Services"
        }
    ],
    "sg:phone":"+1 407 341 7150",
    "sg:postcode":"32765",
    "sg:province":"FL",
    "wof:name":"Lawhun Enterprises",
    "wof:placetype":"venue"
},
  "geometry": {"coordinates":[-81.175792,28.621554],"type":"Point"}
}