{
  "type": "Feature",
  "properties": {
    "addr:full":"11024 Greenaire Dr Tampa FL 33624",
    "addr:housenumber":"11024",
    "addr:postcode":"33624",
    "addr:street":"Greenaire Dr",
    "iso:country":"US",
    "sg:address":"11024 Greenaire Dr",
    "sg:city":"Tampa",
    "sg:classifiers":[
        {
            "category":"Professional",
            "type":"Services"
        }
    ],
    "sg:phone":"+1 813 265 0937",
    "sg:postcode":"33624",
    "sg:province":"FL",
    "wof:name":"Xylyk Inc",
    "wof:placetype":"venue"
},
  "geometry": {"coordinates":[-82.531256,28.050421],"type":"Point"}
}