{
  "type": "Feature",
  "properties": {
    "addr:full":"8130 NW 15th St Pembroke Pines FL 33024",
    "addr:housenumber":"8130",
    "addr:postcode":"33024",
    "addr:street":"Nw 15Th St",
    "iso:country":"US",
    "sg:address":"8130 NW 15th St",
    "sg:city":"Pembroke Pines",
    "sg:classifiers":[
        {
            "category":"Banks & Credit Unions",
            "subcategory":"Bank",
            "type":"Services"
        }
    ],
    "sg:phone":"+1 954 602 2001",
    "sg:postcode":"33024",
    "sg:province":"FL",
    "sg:tags":[
        "other",
        "plan",
        "card"
    ],
    "wof:name":"American Express",
    "wof:placetype":"venue"
},
  "geometry": {"coordinates":[-80.250073,26.021339],"type":"Point"}
}