{
  "type": "Feature",
  "properties": {
    "addr:full":"10733 Phillips Hwy Jacksonville FL 32256",
    "addr:housenumber":"10733",
    "addr:postcode":"32256",
    "addr:street":"Phillips Hwy",
    "iso:country":"US",
    "sg:address":"10733 Phillips Hwy",
    "sg:city":"Jacksonville",
    "sg:classifiers":[
        {
            "category":"Retail",
            "subcategory":"Auto Repair",
            "type":"Services"
        }
    ],
    "sg:phone":"+1 904 886 9240",
    "sg:postcode":"32256",
    "sg:province":"FL",
    "sg:tags":[
        "repairing",
        "automobile",
        "general"
    ],
    "sg:website":"www.tiresplus.com",
    "wof:name":"Team Tires Plus",
    "wof:placetype":"venue"
},
  "geometry": {"coordinates":[-81.54680500000001,30.173646],"type":"Point"}
}