{
  "type": "Feature",
  "properties": {
    "iso:country":"US",
    "sg:address":"731 Tamiami Blvd",
    "sg:city":"Miami",
    "sg:classifiers":[
        {
            "category":"Insurance",
            "subcategory":"Insurance Agent",
            "type":"Services"
        }
    ],
    "sg:phone":"+1 305 266 9666",
    "sg:postcode":"33144",
    "sg:province":"FL",
    "sg:tags":[
        "agency"
    ],
    "wof:name":"VIP Insurance Agency Inc",
    "wof:placetype":"venue"
},
  "geometry": {"coordinates":[-80.31537299999999,25.763909],"type":"Point"}
}