{
  "type": "Feature",
  "properties": {
    "iso:country":"US",
    "sg:address":"14 S B St",
    "sg:city":"Lake Worth",
    "sg:classifiers":[
        {
            "category":"Building & Trades",
            "subcategory":"Landscaping Services",
            "type":"Services"
        }
    ],
    "sg:phone":"+1 561 540 8570",
    "sg:postcode":"33460",
    "sg:province":"FL",
    "sg:tags":[
        "landscape"
    ],
    "wof:name":"Thomas McGreevy Landscaping",
    "wof:placetype":"venue"
},
  "geometry": {"coordinates":[-80.064195,26.615018],"type":"Point"}
}