{
  "type": "Feature",
  "properties": {
    "iso:country":"US",
    "sg:address":"14531 Farrington Way",
    "sg:city":"Fort Myers",
    "sg:classifiers":[
        {
            "category":"Manufacturing",
            "subcategory":"Printing",
            "type":"Manufacturing & Wholesale Goods"
        }
    ],
    "sg:phone":"+1 239 543 6787",
    "sg:postcode":"33912",
    "sg:province":"FL",
    "sg:tags":[
        "typesetting"
    ],
    "wof:name":"Cox & Associates",
    "wof:placetype":"venue"
},
  "geometry": {"coordinates":[-81.81612,26.529202],"type":"Point"}
}