{
  "type": "Feature",
  "properties": {
    "addr:full":"4614 NW 21 Ter Gainesville FL 32605",
    "addr:housenumber":"4614",
    "addr:postcode":"32605",
    "addr:street":"Nw 21 Ter",
    "iso:country":"US",
    "sg:address":"4614 NW 21 Ter",
    "sg:city":"Gainesville",
    "sg:classifiers":[
        {
            "category":"Professional",
            "subcategory":"Management & Consulting",
            "type":"Services"
        }
    ],
    "sg:phone":"+1 352 371 3719",
    "sg:postcode":"32605",
    "sg:province":"FL",
    "sg:tags":[
        "consultant",
        "educational"
    ],
    "wof:name":"Great Books Foundation",
    "wof:placetype":"venue"
},
  "geometry": {"coordinates":[-82.35232999999999,29.696498],"type":"Point"}
}