{
  "type": "Feature",
  "properties": {
    "addr:full":"10480 W Atlantic Ave Delray Beach FL 33446",
    "addr:housenumber":"10480",
    "addr:postcode":"33446",
    "addr:street":"W Atlantic Ave",
    "iso:country":"US",
    "sg:address":"10480 W Atlantic Ave",
    "sg:city":"Delray Beach",
    "sg:classifiers":[
        {
            "category":"Building & Trades",
            "subcategory":"Landscaping Services",
            "type":"Services"
        }
    ],
    "sg:phone":"+1 561 638 2356",
    "sg:postcode":"33446",
    "sg:province":"FL",
    "sg:tags":[
        "lawn",
        "maintenance"
    ],
    "wof:name":"Grasshoppers Ldscp & Design",
    "wof:placetype":"venue"
},
  "geometry": {"coordinates":[-80.214275,26.453536],"type":"Point"}
}