{
  "type": "Feature",
  "properties": {
    "addr:full":"301 Kenilworth Ave Ormond Beach FL 32174",
    "addr:housenumber":"301",
    "addr:postcode":"32174",
    "addr:street":"Kenilworth Ave",
    "iso:country":"US",
    "sg:address":"301 Kenilworth Ave",
    "sg:city":"Ormond Beach",
    "sg:classifiers":[
        {
            "category":"Real Estate",
            "subcategory":"Real Estate Agent",
            "type":"Services"
        }
    ],
    "sg:phone":"+1 386 672 0601",
    "sg:postcode":"32174",
    "sg:province":"FL",
    "sg:website":"www.triangle-realty.com",
    "wof:name":"Triangle Realty",
    "wof:placetype":"venue"
},
  "geometry": {"coordinates":[-81.069987,29.289592],"type":"Point"}
}