{
  "type": "Feature",
  "properties": {
    "iso:country":"US",
    "sg:address":"2513 W Hillsborough Ave",
    "sg:city":"Tampa",
    "sg:classifiers":[
        {
            "category":"Restaurant",
            "type":"Food & Drink"
        }
    ],
    "sg:menulink":"http://www.allmenus.com/fl/tampa/89376-china-dragon/menu/",
    "sg:phone":"+1 813 876 8866",
    "sg:postcode":"33614",
    "sg:province":"FL",
    "sg:tags":[
        "asian",
        "chinese"
    ],
    "wof:name":"China Dragon",
    "wof:placetype":"venue"
},
  "geometry": {"coordinates":[-82.485113,27.996574],"type":"Point"}
}