{
  "type": "Feature",
  "properties": {
    "addr:full":"17621 NE 7th Pl Miami FL 33162",
    "addr:housenumber":"17621",
    "addr:postcode":"33162",
    "addr:street":"Ne 7Th Pl",
    "iso:country":"US",
    "sg:address":"17621 NE 7th Pl",
    "sg:city":"Miami",
    "sg:classifiers":[
        {
            "category":"Food & Beverages",
            "subcategory":"Specialty",
            "type":"Retail Goods"
        }
    ],
    "sg:phone":"+1 305 652 2040",
    "sg:postcode":"33162",
    "sg:province":"FL",
    "sg:tags":[
        "oriental"
    ],
    "wof:name":"Mikah Corp Wholesale & Retail",
    "wof:placetype":"venue"
},
  "geometry": {"coordinates":[-80.184878,25.93683],"type":"Point"}
}