{
  "type": "Feature",
  "properties": {
    "iso:country":"US",
    "sg:address":"2124 S Dale Mabry Hwy",
    "sg:city":"Tampa",
    "sg:classifiers":[
        {
            "category":"Shopping",
            "subcategory":"Beauty & Cosmetics",
            "type":"Retail Goods"
        },
        {
            "category":"Personal",
            "subcategory":"Barber",
            "type":"Services"
        },
        {
            "category":"Personal",
            "subcategory":"Beauty Salon",
            "type":"Services"
        }
    ],
    "sg:phone":"+1 813 250 0952",
    "sg:postcode":"33629",
    "sg:province":"FL",
    "sg:tags":[
        "equipment",
        "perfume",
        "salons-equipment",
        "supply"
    ],
    "wof:name":"Beauty Alliance",
    "wof:placetype":"venue"
},
  "geometry": {"coordinates":[-82.505898,27.926081],"type":"Point"}
}