{
  "type": "Feature",
  "properties": {
    "addr:full":"3766 SW Masilunas St Port Saint Lucie FL 34953",
    "addr:housenumber":"3766",
    "addr:postcode":"34953",
    "addr:street":"Sw Masilunas St",
    "iso:country":"US",
    "sg:address":"3766 SW Masilunas St",
    "sg:city":"Port Saint Lucie",
    "sg:classifiers":[
        {
            "category":"Building & Trades",
            "subcategory":"Construction",
            "type":"Services"
        }
    ],
    "sg:phone":"+1 772 873 5594",
    "sg:postcode":"34953",
    "sg:province":"FL",
    "sg:tags":[
        "contractor"
    ],
    "wof:name":"Chad E Farris",
    "wof:placetype":"venue"
},
  "geometry": {"coordinates":[-80.39475299999999,27.232752],"type":"Point"}
}