{
  "type": "Feature",
  "properties": {
    "iso:country":"US",
    "sg:address":"7060 W State Road 84",
    "sg:city":"Davie",
    "sg:classifiers":[
        {
            "category":"Shopping",
            "subcategory":"Clothing, Apparel, & Fashions",
            "type":"Retail Goods"
        }
    ],
    "sg:phone":"+1 954 467 5077",
    "sg:postcode":"33317",
    "sg:province":"FL",
    "sg:tags":[
        "apparel",
        "women's"
    ],
    "wof:name":"F.S.I - Fort Lauderdale, Inc.",
    "wof:placetype":"venue"
},
  "geometry": {"coordinates":[-80.238955,26.095795],"type":"Point"}
}