{
  "type": "Feature",
  "properties": {
    "addr:full":"880 NE Industrial Blvd Jensen Beach FL 34957",
    "addr:housenumber":"880",
    "addr:postcode":"34957",
    "addr:street":"Ne Industrial Blvd",
    "iso:country":"US",
    "sg:address":"880 NE Industrial Blvd",
    "sg:city":"Jensen Beach",
    "sg:classifiers":[
        {
            "category":"Retail",
            "subcategory":"Auto Repair",
            "type":"Services"
        }
    ],
    "sg:phone":"+1 772 334 8488",
    "sg:postcode":"34957",
    "sg:province":"FL",
    "sg:tags":[
        "body"
    ],
    "wof:name":"Auto Depot",
    "wof:placetype":"venue"
},
  "geometry": {"coordinates":[-80.238282,27.226098],"type":"Point"}
}