{
  "type": "Feature",
  "properties": {
    "addr:full":"720 W Lumsden Rd Brandon FL 33511",
    "addr:housenumber":"720",
    "addr:postcode":"33511",
    "addr:street":"W Lumsden Rd",
    "iso:country":"US",
    "sg:address":"720 W Lumsden Rd",
    "sg:city":"Brandon",
    "sg:classifiers":[
        {
            "category":"Shopping",
            "subcategory":"Used Merchandise",
            "type":"Retail Goods"
        }
    ],
    "sg:phone":"+1 813 684 0588",
    "sg:postcode":"33511",
    "sg:province":"FL",
    "wof:name":"Somewhere In Time",
    "wof:placetype":"venue"
},
  "geometry": {"coordinates":[-82.29435599999999,27.923227],"type":"Point"}
}