{
  "type": "Feature",
  "properties": {
    "addr:full":"900 A Philip Randolph Blvd Jacksonville FL 32206",
    "addr:housenumber":"900 a",
    "addr:postcode":"32206",
    "addr:street":"Philip Randolph Blvd",
    "iso:country":"US",
    "sg:address":"900 A Philip Randolph Blvd",
    "sg:city":"Jacksonville",
    "sg:classifiers":[
        {
            "category":"Retail",
            "subcategory":"Funeral Services",
            "type":"Services"
        }
    ],
    "sg:phone":"+1 904 358 3949",
    "sg:postcode":"32206",
    "sg:province":"FL",
    "sg:tags":[
        "director"
    ],
    "wof:name":"Marion Graham Mortuaries",
    "wof:placetype":"venue"
},
  "geometry": {"coordinates":[-81.64255199999999,30.333582],"type":"Point"}
}