{
  "type": "Feature",
  "properties": {
    "addr:full":"8000 NW 31st St Ste 1 Doral FL 33122",
    "addr:housenumber":"8000",
    "addr:postcode":"33122",
    "addr:street":"Nw 31St St Ste 1",
    "iso:country":"US",
    "sg:address":"8000 NW 31st St Ste 1",
    "sg:city":"Doral",
    "sg:classifiers":[
        {
            "category":"Wholesale",
            "subcategory":"Home Furnishings",
            "type":"Manufacturing & Wholesale Goods"
        }
    ],
    "sg:phone":"+1 305 591 8342",
    "sg:postcode":"33122",
    "sg:province":"FL",
    "sg:tags":[
        "blind",
        "shade"
    ],
    "wof:name":"Decosol",
    "wof:placetype":"venue"
},
  "geometry": {"coordinates":[-80.3265,25.802601],"type":"Point"}
}