{
  "type": "Feature",
  "properties": {
    "iso:country":"US",
    "sg:address":"118 E Wright St",
    "sg:city":"Pensacola",
    "sg:classifiers":[
        {
            "category":"Personal",
            "subcategory":"Beauty Salon",
            "type":"Services"
        }
    ],
    "sg:phone":"+1 850 433 4333",
    "sg:postcode":"32501",
    "sg:province":"FL",
    "wof:name":"Mondellos Hair Studio",
    "wof:placetype":"venue"
},
  "geometry": {"coordinates":[-87.21390700000001,30.417109],"type":"Point"}
}