{
  "type": "Feature",
  "properties": {
    "iso:country":"US",
    "sg:address":"1021 Cherry Ln",
    "sg:city":"Wellington",
    "sg:classifiers":[
        {
            "category":"Real Estate",
            "subcategory":"Real Estate Agent",
            "type":"Services"
        }
    ],
    "sg:phone":"+1 561 753 0135",
    "sg:postcode":"33414",
    "sg:province":"FL",
    "wof:name":"International Properties",
    "wof:placetype":"venue"
},
  "geometry": {"coordinates":[-80.261897,26.666662],"type":"Point"}
}