{
  "type": "Feature",
  "properties": {
    "iso:country":"US",
    "sg:address":"3350 NW 199th St",
    "sg:city":"Miami",
    "sg:classifiers":[
        {
            "category":"Manufacturing",
            "subcategory":"Metals",
            "type":"Manufacturing & Wholesale Goods"
        }
    ],
    "sg:phone":"+1 305 681 8844",
    "sg:postcode":"33169",
    "sg:province":"FL",
    "sg:tags":[
        "company",
        "holding"
    ],
    "wof:name":"Industrial Galvanizers Miami",
    "wof:placetype":"venue"
},
  "geometry": {"coordinates":[-80.25713500000001,25.954934],"type":"Point"}
}