{
  "type": "Feature",
  "properties": {
    "addr:full":"9100 SW 36th St Davie FL 33328",
    "addr:housenumber":"9100",
    "addr:postcode":"33328",
    "addr:street":"Sw 36Th St",
    "iso:country":"US",
    "sg:address":"9100 SW 36th St",
    "sg:city":"Davie",
    "sg:classifiers":[
        {
            "category":"Education",
            "subcategory":"School",
            "type":"Public Place"
        }
    ],
    "sg:phone":"+1 954 474 8200",
    "sg:postcode":"33328",
    "sg:province":"FL",
    "sg:website":"www.browardschools.com",
    "wof:name":"Silver Ridge Elementary School",
    "wof:placetype":"venue"
},
  "geometry": {"coordinates":[-80.26672600000001,26.076312],"type":"Point"}
}