{
  "type": "Feature",
  "properties": {
    "addr:full":"1585 South Dr Sarasota FL 34239",
    "addr:housenumber":"1585",
    "addr:postcode":"34239",
    "addr:street":"South Dr",
    "iso:country":"US",
    "sg:address":"1585 South Dr",
    "sg:city":"Sarasota",
    "sg:classifiers":[
        {
            "category":"Farming",
            "subcategory":"Farm",
            "type":"Manufacturing & Wholesale Goods"
        }
    ],
    "sg:phone":"+1 941 365 0398",
    "sg:postcode":"34239",
    "sg:province":"FL",
    "sg:tags":[
        "crop",
        "general"
    ],
    "wof:name":"Lamb Meetze Acres Inc",
    "wof:placetype":"venue"
},
  "geometry": {"coordinates":[-82.536512,27.30647],"type":"Point"}
}