{
  "type": "Feature",
  "properties": {
    "iso:country":"US",
    "sg:address":"915 Seneca St",
    "sg:city":"Jupiter",
    "sg:classifiers":[
        {
            "category":"Building & Trades",
            "subcategory":"Cleaning & Sanitation",
            "type":"Services"
        }
    ],
    "sg:phone":"+1 561 747 2768",
    "sg:postcode":"33458",
    "sg:province":"FL",
    "sg:tags":[
        "janitor"
    ],
    "wof:name":"Sandra Underhill Cleaning Svc",
    "wof:placetype":"venue"
},
  "geometry": {"coordinates":[-80.11056499999999,26.935435],"type":"Point"}
}