{
  "type": "Feature",
  "properties": {
    "iso:country":"US",
    "sg:address":"4774 Exeter Estate Ln",
    "sg:city":"Lake Worth",
    "sg:classifiers":[
        {
            "category":"Professional",
            "type":"Services"
        }
    ],
    "sg:phone":"+1 561 642 5321",
    "sg:postcode":"33449",
    "sg:province":"FL",
    "wof:name":"Ernest Adler",
    "wof:placetype":"venue"
},
  "geometry": {"coordinates":[-80.211142,26.60976],"type":"Point"}
}