{
  "type": "Feature",
  "properties": {
    "iso:country":"US",
    "sg:address":"50 Pine Island Rd",
    "sg:city":"Fort Myers",
    "sg:classifiers":[
        {
            "category":"Health Services",
            "subcategory":"Doctor",
            "type":"Services"
        }
    ],
    "sg:phone":"+1 239 656 0455",
    "sg:postcode":"33903",
    "sg:province":"FL",
    "sg:tags":[
        "medical"
    ],
    "wof:name":"Aguilar Ephraim G MD",
    "wof:placetype":"venue"
},
  "geometry": {"coordinates":[-81.885834,26.682033],"type":"Point"}
}