{
  "type": "Feature",
  "properties": {
    "addr:full":"4719A NW 53rd Ave Ste A Gainesville FL 32653",
    "addr:housenumber":"4719a",
    "addr:postcode":"32653",
    "addr:street":"Nw 53Rd Ave Ste A",
    "iso:country":"US",
    "sg:address":"4719A NW 53rd Ave Ste A",
    "sg:city":"Gainesville",
    "sg:classifiers":[
        {
            "category":"Professional",
            "subcategory":"Lawyer & Legal Services",
            "type":"Services"
        }
    ],
    "sg:phone":"+1 352 371 2630",
    "sg:postcode":"32653",
    "sg:province":"FL",
    "sg:tags":[
        "plan"
    ],
    "wof:name":"Resolution Center",
    "wof:placetype":"venue"
},
  "geometry": {"coordinates":[-82.36315500000001,29.703341],"type":"Point"}
}