{
  "type": "Feature",
  "properties": {
    "iso:country":"US",
    "sg:address":"4222 24th Ct",
    "sg:city":"Vero Beach",
    "sg:classifiers":[
        {
            "category":"Organizations",
            "subcategory":"Religious Organization",
            "type":"Services"
        }
    ],
    "sg:phone":"+1 772 770 3668",
    "sg:postcode":"32967",
    "sg:province":"FL",
    "sg:tags":[
        "church"
    ],
    "wof:name":"Holy Temple Of God",
    "wof:placetype":"venue"
},
  "geometry": {"coordinates":[-80.4102,27.669989],"type":"Point"}
}