{
  "type": "Feature",
  "properties": {
    "addr:full":"1526 US Hwy 19 Holiday FL 34691",
    "addr:housenumber":"1526",
    "addr:postcode":"34691",
    "addr:street":"Us Hwy 19",
    "iso:country":"US",
    "sg:address":"1526 US Hwy 19",
    "sg:city":"Holiday",
    "sg:classifiers":[
        {
            "category":"Retail",
            "subcategory":"Auto Repair",
            "type":"Services"
        }
    ],
    "sg:phone":"+1 727 937 5196",
    "sg:postcode":"34691",
    "sg:province":"FL",
    "sg:tags":[
        "body",
        "automobile",
        "painting"
    ],
    "wof:name":"West Coast Collision Ctr",
    "wof:placetype":"venue"
},
  "geometry": {"coordinates":[-82.740296,28.181165],"type":"Point"}
}