{
  "type": "Feature",
  "properties": {
    "iso:country":"US",
    "sg:address":"8875 SW 129th Ter",
    "sg:city":"Miami",
    "sg:classifiers":[
        {
            "category":"Manufacturing",
            "subcategory":"Building Materials",
            "type":"Manufacturing & Wholesale Goods"
        }
    ],
    "sg:phone":"+1 305 251 9668",
    "sg:postcode":"33176",
    "sg:province":"FL",
    "sg:tags":[
        "ornamental",
        "product",
        "wood",
        "millwork",
        "mfg"
    ],
    "wof:name":"Pinnacle Wood Design",
    "wof:placetype":"venue"
},
  "geometry": {"coordinates":[-80.338632,25.649618],"type":"Point"}
}