{
  "type": "Feature",
  "properties": {
    "iso:country":"US",
    "sg:address":"1602 NW 84th Ave",
    "sg:city":"Miami",
    "sg:classifiers":[
        {
            "category":"Freight",
            "type":"Transportation"
        }
    ],
    "sg:phone":"+1 305 593 8542",
    "sg:postcode":"33126",
    "sg:province":"FL",
    "sg:tags":[
        "arrangement"
    ],
    "wof:name":"Air Carrier Logistics Inc",
    "wof:placetype":"venue"
},
  "geometry": {"coordinates":[-80.332347,25.787427],"type":"Point"}
}