{
  "type": "Feature",
  "properties": {
    "addr:full":"3881 NE 3rd Ave Fort Lauderdale FL 33334",
    "addr:housenumber":"3881",
    "addr:postcode":"33334",
    "addr:street":"Ne 3Rd Ave",
    "iso:country":"US",
    "sg:address":"3881 NE 3rd Ave",
    "sg:city":"Fort Lauderdale",
    "sg:classifiers":[
        {
            "category":"Health Services",
            "subcategory":"Nursing And Care Facility",
            "type":"Services"
        }
    ],
    "sg:phone":"+1 954 563 6617",
    "sg:postcode":"33334",
    "sg:province":"FL",
    "wof:name":"Treemont On The Park",
    "wof:placetype":"venue"
},
  "geometry": {"coordinates":[-80.142757,26.175352],"type":"Point"}
}