{
  "type": "Feature",
  "properties": {
    "addr:full":"392 W Pinestead Rd Pensacola FL 32503",
    "addr:housenumber":"392",
    "addr:postcode":"32503",
    "addr:street":"W Pinestead Rd",
    "iso:country":"US",
    "sg:address":"392 W Pinestead Rd",
    "sg:city":"Pensacola",
    "sg:classifiers":[
        {
            "category":"Retail",
            "subcategory":"Auto Repair",
            "type":"Services"
        }
    ],
    "sg:phone":"+1 850 479 2787",
    "sg:postcode":"32503",
    "sg:province":"FL",
    "sg:tags":[
        "body",
        "automobile",
        "painting"
    ],
    "wof:name":"Fresh & Clean Auto Paint & Dtl",
    "wof:placetype":"venue"
},
  "geometry": {"coordinates":[-87.258499,30.49406],"type":"Point"}
}