{
  "type": "Feature",
  "properties": {
    "iso:country":"US",
    "sg:address":"11685 NW 7th Ave",
    "sg:city":"Miami",
    "sg:classifiers":[
        {
            "category":"Manufacturing",
            "subcategory":"Printing",
            "type":"Manufacturing & Wholesale Goods"
        }
    ],
    "sg:phone":"+1 305 681 1338",
    "sg:postcode":"33168",
    "sg:province":"FL",
    "sg:tags":[
        "scanning",
        "supply",
        "lithographic",
        "commercial",
        "equipment",
        "plotting"
    ],
    "wof:name":"A & M Parks Printers Inc",
    "wof:placetype":"venue"
},
  "geometry": {"coordinates":[-80.210503,25.882099],"type":"Point"}
}