{
  "type": "Feature",
  "properties": {
    "iso:country":"US",
    "sg:address":"8842 NW 75th Ct",
    "sg:city":"Tamarac",
    "sg:classifiers":[
        {
            "category":"Professional",
            "type":"Services"
        }
    ],
    "sg:phone":"+1 954 746 9375",
    "sg:postcode":"33321",
    "sg:province":"FL",
    "sg:tags":[
        "establishment"
    ],
    "wof:name":"Ami Amrani",
    "wof:placetype":"venue"
},
  "geometry": {"coordinates":[-80.27342400000001,26.214348],"type":"Point"}
}