{
  "type": "Feature",
  "properties": {
    "addr:full":"7109 NW 11th Pl Gainesville FL 32605",
    "addr:housenumber":"7109",
    "addr:postcode":"32605",
    "addr:street":"Nw 11Th Pl",
    "iso:country":"US",
    "sg:address":"7109 NW 11th Pl",
    "sg:city":"Gainesville",
    "sg:classifiers":[
        {
            "category":"Health Services",
            "subcategory":"Doctor",
            "type":"Services"
        }
    ],
    "sg:phone":"+1 352 373 7723",
    "sg:postcode":"32605",
    "sg:province":"FL",
    "sg:tags":[
        "physician",
        "surgeon"
    ],
    "wof:name":"Jain Hand Surgery Ctr",
    "wof:placetype":"venue"
},
  "geometry": {"coordinates":[-82.418362,29.663403],"type":"Point"}
}