{
  "type": "Feature",
  "properties": {
    "addr:full":"4190 Honeysuckle Cir Middleburg FL 32068",
    "addr:housenumber":"4190",
    "addr:postcode":"32068",
    "addr:street":"Honeysuckle Cir",
    "iso:country":"US",
    "sg:address":"4190 Honeysuckle Cir",
    "sg:city":"Middleburg",
    "sg:classifiers":[
        {
            "category":"Wholesale",
            "subcategory":"Machinery & Supplies",
            "type":"Manufacturing & Wholesale Goods"
        }
    ],
    "sg:phone":"+1 904 282 5306",
    "sg:postcode":"32068",
    "sg:province":"FL",
    "sg:tags":[
        "equipment",
        "establishment"
    ],
    "wof:name":"Halfa Distributors",
    "wof:placetype":"venue"
},
  "geometry": {"coordinates":[-81.87639299999999,30.044527],"type":"Point"}
}