{
  "type": "Feature",
  "properties": {
    "addr:full":"615 Castaways St NE Palm Bay FL 32907",
    "addr:housenumber":"615",
    "addr:postcode":"32907",
    "addr:street":"Castaways St Ne",
    "iso:country":"US",
    "sg:address":"615 Castaways St NE",
    "sg:city":"Palm Bay",
    "sg:classifiers":[
        {
            "category":"Banks & Credit Unions",
            "subcategory":"Financial Services",
            "type":"Services"
        }
    ],
    "sg:phone":"+1 321 726 8980",
    "sg:postcode":"32907",
    "sg:province":"FL",
    "sg:tags":[
        "investor"
    ],
    "wof:name":"Colpro LLC",
    "wof:placetype":"venue"
},
  "geometry": {"coordinates":[-80.657008,28.01019],"type":"Point"}
}