{
  "type": "Feature",
  "properties": {
    "iso:country":"US",
    "sg:address":"280 N Tropical Trl",
    "sg:city":"Merritt Island",
    "sg:classifiers":[
        {
            "category":"Professional",
            "subcategory":"Accounting & Tax Preparation",
            "type":"Services"
        }
    ],
    "sg:phone":"+1 321 453 6256",
    "sg:postcode":"32953",
    "sg:province":"FL",
    "sg:tags":[
        "accountant"
    ],
    "wof:name":"Dale Linda P CPA",
    "wof:placetype":"venue"
},
  "geometry": {"coordinates":[-80.70610000000001,28.3603],"type":"Point"}
}