{
  "type": "Feature",
  "properties": {
    "iso:country":"US",
    "sg:address":"2716 N Financial Ct",
    "sg:city":"Sanford",
    "sg:classifiers":[
        {
            "category":"Wholesale",
            "subcategory":"Durable Goods & Equipment",
            "type":"Manufacturing & Wholesale Goods"
        }
    ],
    "sg:phone":"+1 407 302 5611",
    "sg:postcode":"32773",
    "sg:province":"FL",
    "sg:tags":[
        "representative",
        "manufacturer"
    ],
    "sg:website":"www.fluidcontrolspec.com",
    "wof:name":"Fluid Control Specialist Inc",
    "wof:placetype":"venue"
},
  "geometry": {"coordinates":[-81.299724,28.730027],"type":"Point"}
}