{
  "type": "Feature",
  "properties": {
    "iso:country":"US",
    "sg:address":"4249 Magnolia Ridge Dr",
    "sg:city":"Weston",
    "sg:classifiers":[
        {
            "category":"Professional",
            "type":"Services"
        }
    ],
    "sg:phone":"+1 954 349 4903",
    "sg:postcode":"33331",
    "sg:province":"FL",
    "sg:tags":[
        "establishment"
    ],
    "wof:name":"Acevedo Martinez Inc",
    "wof:placetype":"venue"
},
  "geometry": {"coordinates":[-80.37714099999999,26.065061],"type":"Point"}
}