{
  "type": "Feature",
  "properties": {
    "addr:full":"5600 Stadium Pkwy Melbourne FL 32940",
    "addr:housenumber":"5600",
    "addr:postcode":"32940",
    "addr:street":"Stadium Pkwy",
    "iso:country":"US",
    "sg:address":"5600 Stadium Pkwy",
    "sg:city":"Melbourne",
    "sg:classifiers":[
        {
            "category":"Organizations",
            "subcategory":"Membership Organization",
            "type":"Services"
        }
    ],
    "sg:phone":"+1 321 633 8119",
    "sg:postcode":"32940",
    "sg:province":"FL",
    "sg:tags":[
        "athletic"
    ],
    "wof:name":"Florida Marlins-Player Develop",
    "wof:placetype":"venue"
},
  "geometry": {"coordinates":[-80.73800300000001,28.253308],"type":"Point"}
}