{
  "type": "Feature",
  "properties": {
    "addr:full":"220 29th St SW Naples FL 34117",
    "addr:housenumber":"220",
    "addr:postcode":"34117",
    "addr:street":"29Th St Sw",
    "iso:country":"US",
    "sg:address":"220 29th St SW",
    "sg:city":"Naples",
    "sg:classifiers":[
        {
            "category":"Manufacturing",
            "subcategory":"Glass & Minerals",
            "type":"Manufacturing & Wholesale Goods"
        }
    ],
    "sg:phone":"+1 239 455 6634",
    "sg:postcode":"34117",
    "sg:province":"FL",
    "sg:tags":[
        "ready",
        "concrete",
        "mfg",
        "contractor"
    ],
    "wof:name":"Jims Concrete",
    "wof:placetype":"venue"
},
  "geometry": {"coordinates":[-81.66504500000001,26.22685],"type":"Point"}
}