{
  "type": "Feature",
  "properties": {
    "addr:full":"4720 Salisbury Rd Jacksonville FL 32256",
    "addr:housenumber":"4720",
    "addr:postcode":"32256",
    "addr:street":"Salisbury Rd",
    "iso:country":"US",
    "sg:address":"4720 Salisbury Rd",
    "sg:city":"Jacksonville",
    "sg:classifiers":[
        {
            "category":"Professional",
            "subcategory":"Management & Consulting",
            "type":"Services"
        }
    ],
    "sg:phone":"+1 904 493 6105",
    "sg:postcode":"32256",
    "sg:province":"FL",
    "sg:tags":[
        "counselor",
        "relation",
        "public"
    ],
    "wof:name":"Media Masters Group",
    "wof:placetype":"venue"
},
  "geometry": {"coordinates":[-81.58822499999999,30.246037],"type":"Point"}
}