{
  "type": "Feature",
  "properties": {
    "addr:full":"1351 Nicholson Rd Jacksonville FL 32207",
    "addr:housenumber":"1351",
    "addr:postcode":"32207",
    "addr:street":"Nicholson Rd",
    "iso:country":"US",
    "sg:address":"1351 Nicholson Rd",
    "sg:city":"Jacksonville",
    "sg:classifiers":[
        {
            "category":"Professional",
            "subcategory":"Management & Consulting",
            "type":"Services"
        }
    ],
    "sg:phone":"+1 904 384 7900",
    "sg:postcode":"32207",
    "sg:province":"FL",
    "wof:name":"Ost Patient Advocates Inc",
    "wof:placetype":"venue"
},
  "geometry": {"coordinates":[-81.634992,30.305964],"type":"Point"}
}