{
  "type": "Feature",
  "properties": {
    "iso:country":"US",
    "sg:address":"5759 Beney Rd",
    "sg:city":"Jacksonville",
    "sg:phone":"+1 904 443 7112",
    "sg:postcode":"32207",
    "sg:province":"FL",
    "sg:tags":[
        "equipment",
        "commercial"
    ],
    "wof:name":"Mainstream Wholesale",
    "wof:placetype":"venue"
},
  "geometry": {"coordinates":[-81.60331600000001,30.277699],"type":"Point"}
}