{
  "type": "Feature",
  "properties": {
    "iso:country":"US",
    "sg:address":"1542 Canal St",
    "sg:city":"Lehigh Acres",
    "sg:classifiers":[
        {
            "category":"Banks & Credit Unions",
            "subcategory":"Financial Services",
            "type":"Services"
        }
    ],
    "sg:phone":"+1 239 822 7072",
    "sg:postcode":"33936",
    "sg:province":"FL",
    "sg:tags":[
        "investment",
        "real estate"
    ],
    "wof:name":"Keiko-Ty Investments Inc",
    "wof:placetype":"venue"
},
  "geometry": {"coordinates":[-81.601539,26.603269],"type":"Point"}
}