{
  "type": "Feature",
  "properties": {
    "iso:country":"US",
    "sg:address":"6355 S Florida Ave",
    "sg:city":"Floral City",
    "sg:classifiers":[
        {
            "category":"Museum",
            "subcategory":"Botanical Garden",
            "type":"Entertainment"
        }
    ],
    "sg:phone":"+1 352 726 8622",
    "sg:postcode":"34436",
    "sg:province":"FL",
    "wof:name":"State of Florida",
    "wof:placetype":"venue"
},
  "geometry": {"coordinates":[-82.29401300000001,28.773647],"type":"Point"}
}