{
  "type": "Feature",
  "properties": {
    "addr:full":"6431 Topaz Ct Fort Myers FL 33966",
    "addr:housenumber":"6431",
    "addr:postcode":"33966",
    "addr:street":"Topaz Ct",
    "iso:country":"US",
    "sg:address":"6431 Topaz Ct",
    "sg:city":"Fort Myers",
    "sg:classifiers":[
        {
            "category":"Building & Trades",
            "subcategory":"Construction",
            "type":"Services"
        }
    ],
    "sg:phone":"+1 239 939 7674",
    "sg:postcode":"33966",
    "sg:province":"FL",
    "sg:tags":[
        "home",
        "builder"
    ],
    "wof:name":"Affordable Family Homes",
    "wof:placetype":"venue"
},
  "geometry": {"coordinates":[-81.85303999999999,26.569205],"type":"Point"}
}