{
  "type": "Feature",
  "properties": {
    "addr:full":"7709 Alton Ave Jacksonville FL 32211",
    "addr:housenumber":"7709",
    "addr:postcode":"32211",
    "addr:street":"Alton Ave",
    "iso:country":"US",
    "sg:address":"7709 Alton Ave",
    "sg:city":"Jacksonville",
    "sg:classifiers":[
        {
            "category":"Retail",
            "subcategory":"Repair Shop",
            "type":"Services"
        }
    ],
    "sg:phone":"+1 904 721 5431",
    "sg:postcode":"32211",
    "sg:province":"FL",
    "sg:tags":[
        "equipment"
    ],
    "wof:name":"Progasco Corp",
    "wof:placetype":"venue"
},
  "geometry": {"coordinates":[-81.577821,30.314458],"type":"Point"}
}