{
  "type": "Feature",
  "properties": {
    "addr:full":"18495 Dixie Hwy Miami FL 33157",
    "addr:housenumber":"18495",
    "addr:postcode":"33157",
    "addr:street":"Dixie Hwy",
    "iso:country":"US",
    "sg:address":"18495 Dixie Hwy",
    "sg:city":"Miami",
    "sg:classifiers":[
        {
            "category":"Professional",
            "subcategory":"Detective & Security Services",
            "type":"Services"
        }
    ],
    "sg:phone":"+1 305 718 3776",
    "sg:postcode":"33157",
    "sg:province":"FL",
    "sg:tags":[
        "guard",
        "patrol"
    ],
    "wof:name":"Amcore Security",
    "wof:placetype":"venue"
},
  "geometry": {"coordinates":[-80.354776,25.597248],"type":"Point"}
}