{
  "type": "Feature",
  "properties": {
    "iso:country":"US",
    "sg:address":"2700 S Commerce Pkwy",
    "sg:city":"Weston",
    "sg:classifiers":[
        {
            "category":"Professional",
            "subcategory":"Management & Consulting",
            "type":"Services"
        }
    ],
    "sg:phone":"+1 954 626 3500",
    "sg:postcode":"33331",
    "sg:province":"FL",
    "sg:tags":[
        "consultant",
        "business"
    ],
    "wof:name":"Brokerick Mac John",
    "wof:placetype":"venue"
},
  "geometry": {"coordinates":[-80.36578799999999,26.084472],"type":"Point"}
}