{
  "type": "Feature",
  "properties": {
    "addr:full":"229 Viola Ave Panama City FL 32404",
    "addr:housenumber":"229",
    "addr:postcode":"32404",
    "addr:street":"Viola Ave",
    "iso:country":"US",
    "sg:address":"229 Viola Ave",
    "sg:city":"Panama City",
    "sg:classifiers":[
        {
            "category":"Building & Trades",
            "subcategory":"Construction",
            "type":"Services"
        }
    ],
    "sg:phone":"+1 850 871 0285",
    "sg:postcode":"32404",
    "sg:province":"FL",
    "sg:tags":[
        "contractor"
    ],
    "wof:name":"Taylors Vinyl Siding Inc",
    "wof:placetype":"venue"
},
  "geometry": {"coordinates":[-85.573086,30.142878],"type":"Point"}
}