{
  "type": "Feature",
  "properties": {
    "addr:full":"357 NE Floresta Dr Port Saint Lucie FL 34983",
    "addr:housenumber":"357",
    "addr:postcode":"34983",
    "addr:street":"Ne Floresta Dr",
    "iso:country":"US",
    "sg:address":"357 NE Floresta Dr",
    "sg:city":"Port Saint Lucie",
    "sg:classifiers":[
        {
            "category":"Home & Garden",
            "subcategory":"Garden Supply",
            "type":"Retail Goods"
        }
    ],
    "sg:phone":"+1 772 344 2636",
    "sg:postcode":"34983",
    "sg:province":"FL",
    "wof:name":"Harts N Pieces",
    "wof:placetype":"venue"
},
  "geometry": {"coordinates":[-80.341318,27.320486],"type":"Point"}
}