{
  "type": "Feature",
  "properties": {
    "iso:country":"US",
    "sg:address":"150 Cinnamon Dr",
    "sg:city":"Satellite Beach",
    "sg:classifiers":[
        {
            "category":"Building & Trades",
            "subcategory":"Construction",
            "type":"Services"
        }
    ],
    "sg:phone":"+1 321 773 8718",
    "sg:postcode":"32937",
    "sg:province":"FL",
    "sg:tags":[
        "resurfacing",
        "laying",
        "refinishing",
        "floor"
    ],
    "wof:name":"Mc Carthy Clean",
    "wof:placetype":"venue"
},
  "geometry": {"coordinates":[-80.593845,28.173213],"type":"Point"}
}