{
  "type": "Feature",
  "properties": {
    "iso:country":"US",
    "sg:address":"1700 SW 3rd Ave",
    "sg:city":"Miami",
    "sg:classifiers":[
        {
            "category":"Sports & Exercise",
            "subcategory":"Gym",
            "type":"Entertainment"
        }
    ],
    "sg:phone":"+1 305 358 0909",
    "sg:postcode":"33255",
    "sg:province":"FL",
    "sg:tags":[
        "pilate"
    ],
    "sg:website":"www.sanctuary7.net",
    "wof:name":"Sanctuary 7 The Studio",
    "wof:placetype":"venue"
},
  "geometry": {"coordinates":[-80.200298,25.761171],"type":"Point"}
}