{
  "type": "Feature",
  "properties": {
    "addr:full":"147 NW 3rd Ave Dania FL 33004",
    "addr:housenumber":"147",
    "addr:postcode":"33004",
    "addr:street":"Nw 3Rd Ave",
    "iso:country":"US",
    "sg:address":"147 NW 3rd Ave",
    "sg:city":"Dania",
    "sg:classifiers":[
        {
            "category":"Wholesale",
            "subcategory":"Toys & Hobbies",
            "type":"Manufacturing & Wholesale Goods"
        }
    ],
    "sg:phone":"+1 954 924 8008",
    "sg:postcode":"33004",
    "sg:province":"FL",
    "sg:tags":[
        "puppet",
        "marionette"
    ],
    "wof:name":"Rigadoon",
    "wof:placetype":"venue"
},
  "geometry": {"coordinates":[-80.145359,26.055006],"type":"Point"}
}