{
  "type": "Feature",
  "properties": {
    "iso:country":"US",
    "sg:address":"1242 Vineland Pl",
    "sg:city":"Lake Mary",
    "sg:classifiers":[
        {
            "category":"Building & Trades",
            "subcategory":"Construction",
            "type":"Services"
        }
    ],
    "sg:phone":"+1 407 320 7328",
    "sg:postcode":"32746",
    "sg:province":"FL",
    "sg:tags":[
        "floor"
    ],
    "wof:name":"Equipment Development Co Inc",
    "wof:placetype":"venue"
},
  "geometry": {"coordinates":[-81.30542800000001,28.776865],"type":"Point"}
}