{
  "type": "Feature",
  "properties": {
    "iso:country":"US",
    "sg:address":"5318 SW 91 Ter",
    "sg:city":"Gainesville",
    "sg:classifiers":[
        {
            "category":"Professional",
            "subcategory":"Business Services",
            "type":"Services"
        }
    ],
    "sg:phone":"+1 352 384 0054",
    "sg:postcode":"32608",
    "sg:province":"FL",
    "sg:tags":[
        "paging",
        "answering"
    ],
    "wof:name":"Gator Communications",
    "wof:placetype":"venue"
},
  "geometry": {"coordinates":[-82.439656,29.593678],"type":"Point"}
}