{
  "type": "Feature",
  "properties": {
    "addr:full":"3275 Natural Bridge Rd Tallahassee FL 32305",
    "addr:housenumber":"3275",
    "addr:postcode":"32305",
    "addr:street":"Natural Bridge Rd",
    "iso:country":"US",
    "sg:address":"3275 Natural Bridge Rd",
    "sg:city":"Tallahassee",
    "sg:classifiers":[
        {
            "category":"Building & Trades",
            "subcategory":"Construction",
            "type":"Services"
        }
    ],
    "sg:phone":"+1 850 421 8307",
    "sg:postcode":"32305",
    "sg:province":"FL",
    "sg:tags":[
        "company"
    ],
    "wof:name":"Tim Christie Construction",
    "wof:placetype":"venue"
},
  "geometry": {"coordinates":[-84.224216,30.305705],"type":"Point"}
}