{
  "type": "Feature",
  "properties": {
    "iso:country":"US",
    "sg:address":"2385 Pga Blvd",
    "sg:city":"Palm Beach Gdns",
    "sg:classifiers":[
        {
            "category":"Professional",
            "subcategory":"Business Services",
            "type":"Services"
        }
    ],
    "sg:phone":"+1 561 630 2720",
    "sg:postcode":"33410",
    "sg:province":"FL",
    "sg:tags":[
        "broker",
        "merchandise"
    ],
    "wof:name":"Star Marine Of Palm Beach",
    "wof:placetype":"venue"
},
  "geometry": {"coordinates":[-80.070888,26.844711],"type":"Point"}
}