{
  "type": "Feature",
  "properties": {
    "addr:full":"6516 NW 18 Dr Gainesville FL 32653",
    "addr:housenumber":"6516",
    "addr:postcode":"32653",
    "addr:street":"Nw 18 Dr",
    "iso:country":"US",
    "sg:address":"6516 NW 18 Dr",
    "sg:city":"Gainesville",
    "sg:classifiers":[
        {
            "category":"Professional",
            "subcategory":"Advertising",
            "type":"Services"
        }
    ],
    "sg:phone":"+1 352 377 2455",
    "sg:postcode":"32653",
    "sg:province":"FL",
    "sg:tags":[
        "distribution"
    ],
    "wof:name":"Goodman Distribution",
    "wof:placetype":"venue"
},
  "geometry": {"coordinates":[-82.34700100000001,29.715613],"type":"Point"}
}