{
  "type": "Feature",
  "properties": {
    "iso:country":"US",
    "sg:address":"318 Atlantic Ave",
    "sg:city":"Interlachen",
    "sg:classifiers":[
        {
            "category":"Shopping",
            "subcategory":"Discount & Variety Stores",
            "type":"Retail Goods"
        }
    ],
    "sg:phone":"+1 386 684 1548",
    "sg:postcode":"32148",
    "sg:province":"FL",
    "sg:tags":[
        "merchandise",
        "general"
    ],
    "wof:name":"Bravo Store",
    "wof:placetype":"venue"
},
  "geometry": {"coordinates":[-81.891327,29.624506],"type":"Point"}
}