{
  "type": "Feature",
  "properties": {
    "addr:full":"1271 W 19th St Jacksonville FL 32209",
    "addr:housenumber":"1271",
    "addr:postcode":"32209",
    "addr:street":"W 19Th St",
    "iso:country":"US",
    "sg:address":"1271 W 19th St",
    "sg:city":"Jacksonville",
    "sg:classifiers":[
        {
            "category":"Personal",
            "subcategory":"Beauty Salon",
            "type":"Services"
        }
    ],
    "sg:phone":"+1 904 359 0088",
    "sg:postcode":"32209",
    "sg:province":"FL",
    "wof:name":"Kierra's Braiding",
    "wof:placetype":"venue"
},
  "geometry": {"coordinates":[-81.67556,30.355211],"type":"Point"}
}