{
  "type": "Feature",
  "properties": {
    "addr:full":"1932 NW 5th St Ocala FL 34475",
    "addr:housenumber":"1932",
    "addr:postcode":"34475",
    "addr:street":"Nw 5Th St",
    "iso:country":"US",
    "sg:address":"1932 NW 5th St",
    "sg:city":"Ocala",
    "sg:classifiers":[
        {
            "category":"Farming",
            "subcategory":"Farm & Veterinary Services",
            "type":"Manufacturing & Wholesale Goods"
        }
    ],
    "sg:phone":"+1 352 622 1834",
    "sg:postcode":"34475",
    "sg:province":"FL",
    "sg:tags":[
        "crop",
        "harvesting"
    ],
    "wof:name":"James F Ponder",
    "wof:placetype":"venue"
},
  "geometry": {"coordinates":[-82.157652,29.191039],"type":"Point"}
}