{
  "type": "Feature",
  "properties": {
    "iso:country":"US",
    "sg:address":"804 SW 1st Ct",
    "sg:city":"Boynton Beach",
    "sg:classifiers":[
        {
            "category":"Building & Trades",
            "subcategory":"Construction",
            "type":"Services"
        }
    ],
    "sg:phone":"+1 561 439 3617",
    "sg:postcode":"33426",
    "sg:province":"FL",
    "sg:tags":[
        "carpentry",
        "contractor"
    ],
    "wof:name":"Keefer Mica Inc",
    "wof:placetype":"venue"
},
  "geometry": {"coordinates":[-80.080659,26.526331],"type":"Point"}
}