{
  "type": "Feature",
  "properties": {
    "addr:full":"442 Magnolia Ave Merritt Island FL 32952",
    "addr:housenumber":"442",
    "addr:postcode":"32952",
    "addr:street":"Magnolia Ave",
    "iso:country":"US",
    "sg:address":"442 Magnolia Ave",
    "sg:city":"Merritt Island",
    "sg:classifiers":[
        {
            "category":"Real Estate",
            "subcategory":"Real Estate Operator",
            "type":"Services"
        }
    ],
    "sg:phone":"+1 321 453 3030",
    "sg:postcode":"32952",
    "sg:province":"FL",
    "sg:tags":[
        "building",
        "apartment"
    ],
    "wof:name":"Kapus Apartments",
    "wof:placetype":"venue"
},
  "geometry": {"coordinates":[-80.70486699999999,28.355887],"type":"Point"}
}