{
  "type": "Feature",
  "properties": {
    "addr:full":"818 Fig Tree Ln Brandon FL 33511",
    "addr:housenumber":"818",
    "addr:postcode":"33511",
    "addr:street":"Fig Tree Ln",
    "iso:country":"US",
    "sg:address":"818 Fig Tree Ln",
    "sg:city":"Brandon",
    "sg:classifiers":[
        {
            "category":"Real Estate",
            "subcategory":"Real Estate Agent",
            "type":"Services"
        }
    ],
    "sg:phone":"+1 813 681 3555",
    "sg:postcode":"33511",
    "sg:province":"FL",
    "wof:name":"Neal Bonnie Sue PA",
    "wof:placetype":"venue"
},
  "geometry": {"coordinates":[-82.273183,27.932384],"type":"Point"}
}