{
  "type": "Feature",
  "properties": {
    "addr:full":"9580 W Colonial Dr Ocoee FL 34761",
    "addr:housenumber":"9580",
    "addr:postcode":"34761",
    "addr:street":"W Colonial Dr",
    "iso:country":"US",
    "sg:address":"9580 W Colonial Dr",
    "sg:city":"Ocoee",
    "sg:classifiers":[
        {
            "category":"Health Services",
            "subcategory":"Clinic",
            "type":"Services"
        },
        {
            "category":"Health Services",
            "subcategory":"Health Practitioner",
            "type":"Services"
        }
    ],
    "sg:phone":"+1 407 532 6815",
    "sg:postcode":"34761",
    "sg:province":"FL",
    "sg:tags":[
        "therapist",
        "physical",
        "specialty",
        "outpatient"
    ],
    "wof:name":"Florida Hospital Rehab",
    "wof:placetype":"venue"
},
  "geometry": {"coordinates":[-81.51964,28.551712],"type":"Point"}
}