{
  "type": "Feature",
  "properties": {
    "iso:country":"US",
    "sg:address":"4983 Spencer Oaks Blvd",
    "sg:city":"Milton",
    "sg:classifiers":[
        {
            "category":"Shopping",
            "subcategory":"Computers & Home Electronics",
            "type":"Retail Goods"
        }
    ],
    "sg:phone":"+1 850 994 2109",
    "sg:postcode":"32571",
    "sg:province":"FL",
    "sg:tags":[
        "repair",
        "sales"
    ],
    "wof:name":"All Pro Inks",
    "wof:placetype":"venue"
},
  "geometry": {"coordinates":[-87.143036,30.617746],"type":"Point"}
}