{
  "type": "Feature",
  "properties": {
    "addr:full":"9271 Edgemont Ln Boca Raton FL 33434",
    "addr:housenumber":"9271",
    "addr:postcode":"33434",
    "addr:street":"Edgemont Ln",
    "iso:country":"US",
    "sg:address":"9271 Edgemont Ln",
    "sg:city":"Boca Raton",
    "sg:classifiers":[
        {
            "category":"Retail",
            "subcategory":"Animal Services",
            "type":"Services"
        }
    ],
    "sg:phone":"+1 561 883 7927",
    "sg:postcode":"33434",
    "sg:province":"FL",
    "wof:name":"Best Friends Pet Styling",
    "wof:placetype":"venue"
},
  "geometry": {"coordinates":[-80.190524,26.391887],"type":"Point"}
}