{
  "type": "Feature",
  "properties": {
    "addr:full":"2417 Mill Creek Ln Tallahassee FL 32308",
    "addr:housenumber":"2417",
    "addr:postcode":"32308",
    "addr:street":"Mill Creek Ln",
    "iso:country":"US",
    "sg:address":"2417 Mill Creek Ln",
    "sg:city":"Tallahassee",
    "sg:classifiers":[
        {
            "category":"Personal",
            "subcategory":"Beauty Salon",
            "type":"Services"
        }
    ],
    "sg:phone":"+1 850 878 0648",
    "sg:postcode":"32308",
    "sg:province":"FL",
    "wof:name":"Hair Apparent",
    "wof:placetype":"venue"
},
  "geometry": {"coordinates":[-84.23581,30.483497],"type":"Point"}
}