{
  "type": "Feature",
  "properties": {
    "addr:full":"17344 NW 74th Ave Hialeah FL 33015",
    "addr:housenumber":"17344",
    "addr:postcode":"33015",
    "addr:street":"Nw 74Th Ave",
    "iso:country":"US",
    "sg:address":"17344 NW 74th Ave",
    "sg:city":"Hialeah",
    "sg:classifiers":[
        {
            "category":"Retail",
            "subcategory":"Car Wash",
            "type":"Services"
        }
    ],
    "sg:phone":"+1 954 558 2095",
    "sg:postcode":"33015",
    "sg:province":"FL",
    "wof:name":"Auto Spa Detailing Co.",
    "wof:placetype":"venue"
},
  "geometry": {"coordinates":[-80.32164,25.9296],"type":"Point"}
}