{
  "type": "Feature",
  "properties": {
    "addr:full":"520 NW 165th St Miami FL 33169",
    "addr:housenumber":"520",
    "addr:postcode":"33169",
    "addr:street":"Nw 165Th St",
    "iso:country":"US",
    "sg:address":"520 NW 165th St",
    "sg:city":"Miami",
    "sg:classifiers":[
        {
            "category":"Insurance",
            "subcategory":"Insurance Agent",
            "type":"Services"
        }
    ],
    "sg:phone":"+1 305 945 7880",
    "sg:postcode":"33169",
    "sg:province":"FL",
    "wof:name":"Primerica Financial Svc",
    "wof:placetype":"venue"
},
  "geometry": {"coordinates":[-80.205889,25.925971],"type":"Point"}
}