{
  "type": "Feature",
  "properties": {
    "iso:country":"US",
    "sg:address":"150 W Evergreen Ave",
    "sg:city":"Longwood",
    "sg:classifiers":[
        {
            "category":"Wholesale",
            "subcategory":"Groceries",
            "type":"Manufacturing & Wholesale Goods"
        }
    ],
    "sg:phone":"+1 407 834 5004",
    "sg:postcode":"32750",
    "sg:province":"FL",
    "sg:tags":[
        "bakery"
    ],
    "wof:name":"Florida Bakery",
    "wof:placetype":"venue"
},
  "geometry": {"coordinates":[-81.346397,28.697001],"type":"Point"}
}