{
  "type": "Feature",
  "properties": {
    "addr:full":"640 NW 71st Ave Fort Lauderdale FL 33317",
    "addr:housenumber":"640",
    "addr:postcode":"33317",
    "addr:street":"Nw 71St Ave",
    "iso:country":"US",
    "sg:address":"640 NW 71st Ave",
    "sg:city":"Fort Lauderdale",
    "sg:classifiers":[
        {
            "category":"Building & Trades",
            "subcategory":"Construction",
            "type":"Services"
        }
    ],
    "sg:phone":"+1 954 581 5719",
    "sg:postcode":"33317",
    "sg:province":"FL",
    "sg:tags":[
        "contracting",
        "carpentry"
    ],
    "wof:name":"Tradeworks of Broward Inc",
    "wof:placetype":"venue"
},
  "geometry": {"coordinates":[-80.24190400000001,26.130091],"type":"Point"}
}