{
  "type": "Feature",
  "properties": {
    "addr:full":"2520 W Tennessee St Tallahassee FL 32304",
    "addr:housenumber":"2520",
    "addr:postcode":"32304",
    "addr:street":"W Tennessee St",
    "iso:country":"US",
    "sg:address":"2520 W Tennessee St",
    "sg:city":"Tallahassee",
    "sg:classifiers":[
        {
            "category":"Real Estate",
            "subcategory":"Developer",
            "type":"Services"
        }
    ],
    "sg:phone":"+1 850 580 2267",
    "sg:postcode":"32304",
    "sg:province":"FL",
    "wof:name":"Tharpe Development Corp",
    "wof:placetype":"venue"
},
  "geometry": {"coordinates":[-84.327986,30.447958],"type":"Point"}
}