{
  "type": "Feature",
  "properties": {
    "iso:country":"US",
    "sg:address":"9721 Sunny Isle Cir",
    "sg:city":"Boca Raton",
    "sg:classifiers":[
        {
            "category":"Building & Trades",
            "subcategory":"Cleaning & Sanitation",
            "type":"Services"
        }
    ],
    "sg:phone":"+1 561 479 0999",
    "sg:postcode":"33428",
    "sg:province":"FL",
    "sg:tags":[
        "janitor"
    ],
    "wof:name":"Quick N Clean Inc",
    "wof:placetype":"venue"
},
  "geometry": {"coordinates":[-80.198677,26.353739],"type":"Point"}
}