{
  "type": "Feature",
  "properties": {
    "addr:full":"21636 Belhaven Way Estero FL 33928",
    "addr:postcode":"21636;33928",
    "addr:street":"Belhaven Way",
    "iso:country":"US",
    "sg:address":"21636 Belhaven Way",
    "sg:city":"Estero",
    "sg:classifiers":[
        {
            "category":"Freight",
            "type":"Transportation"
        }
    ],
    "sg:phone":"+1 239 948 0232",
    "sg:postcode":"33928",
    "sg:province":"FL",
    "sg:tags":[
        "trucking"
    ],
    "wof:name":"Jumbo Inc",
    "wof:placetype":"venue"
},
  "geometry": {"coordinates":[-81.754198,26.417262],"type":"Point"}
}