{
  "type": "Feature",
  "properties": {
    "addr:full":"10960 Beach Blvd Jacksonville FL 32246",
    "addr:housenumber":"10960",
    "addr:postcode":"32246",
    "addr:street":"Beach Blvd",
    "iso:country":"US",
    "sg:address":"10960 Beach Blvd",
    "sg:city":"Jacksonville",
    "sg:classifiers":[
        {
            "category":"Banks & Credit Unions",
            "subcategory":"Financial Services",
            "type":"Services"
        }
    ],
    "sg:phone":"+1 904 642 4478",
    "sg:postcode":"32246",
    "sg:province":"FL",
    "sg:tags":[
        "investor"
    ],
    "wof:name":"Joseph Ogiba",
    "wof:placetype":"venue"
},
  "geometry": {"coordinates":[-81.534808,30.286742],"type":"Point"}
}