{
  "type": "Feature",
  "properties": {
    "iso:country":"US",
    "sg:address":"1457 Vale Cir",
    "sg:city":"Deltona",
    "sg:classifiers":[
        {
            "category":"Building & Trades",
            "subcategory":"Construction",
            "type":"Services"
        }
    ],
    "sg:phone":"+1 386 479 2317",
    "sg:postcode":"32738",
    "sg:province":"FL",
    "sg:tags":[
        "contractor"
    ],
    "wof:name":"Q V & Assocs Inc",
    "wof:placetype":"venue"
},
  "geometry": {"coordinates":[-81.203542,28.903373],"type":"Point"}
}