{
  "type": "Feature",
  "properties": {
    "addr:full":"1965 Ford Cir N Melbourne FL 32935",
    "addr:housenumber":"1965",
    "addr:postcode":"32935",
    "addr:street":"Ford Cir N",
    "iso:country":"US",
    "sg:address":"1965 Ford Cir N",
    "sg:city":"Melbourne",
    "sg:classifiers":[
        {
            "category":"Home & Garden",
            "subcategory":"Carpets & Floor Coverings",
            "type":"Retail Goods"
        }
    ],
    "sg:phone":"+1 321 255 7894",
    "sg:postcode":"32935",
    "sg:province":"FL",
    "wof:name":"Magic Carpets of Persia Inc",
    "wof:placetype":"venue"
},
  "geometry": {"coordinates":[-80.652871,28.117309],"type":"Point"}
}