{
  "type": "Feature",
  "properties": {
    "addr:full":"105 Rose Island Way Ponte Vedra Bch FL 32082",
    "addr:housenumber":"105",
    "addr:postcode":"32082",
    "addr:street":"Rose Island Way",
    "iso:country":"US",
    "sg:address":"105 Rose Island Way",
    "sg:city":"Ponte Vedra Bch",
    "sg:classifiers":[
        {
            "category":"Professional",
            "subcategory":"Detective & Security Services",
            "type":"Services"
        }
    ],
    "sg:phone":"+1 904 699 8060",
    "sg:postcode":"32082",
    "sg:province":"FL",
    "sg:tags":[
        "investigator"
    ],
    "wof:name":"Schulz Investigative Svc",
    "wof:placetype":"venue"
},
  "geometry": {"coordinates":[-81.392512,30.250379],"type":"Point"}
}