{
  "type": "Feature",
  "properties": {
    "iso:country":"US",
    "sg:address":"256 Lake Eden Way",
    "sg:city":"Delray Beach",
    "sg:classifiers":[
        {
            "category":"Professional",
            "subcategory":"Accounting & Tax Preparation",
            "type":"Services"
        }
    ],
    "sg:phone":"+1 561 330 0616",
    "sg:postcode":"33444",
    "sg:province":"FL",
    "sg:tags":[
        "auditing",
        "bookkeeping"
    ],
    "wof:name":"Marian Retterer",
    "wof:placetype":"venue"
},
  "geometry": {"coordinates":[-80.076108,26.486908],"type":"Point"}
}