{
  "type": "Feature",
  "properties": {
    "iso:country":"US",
    "sg:address":"426 SW 8th St",
    "sg:city":"Miami",
    "sg:classifiers":[
        {
            "category":"Personal",
            "subcategory":"Massage",
            "type":"Services"
        }
    ],
    "sg:phone":"+1 305 856 3606",
    "sg:postcode":"33130",
    "sg:province":"FL",
    "wof:name":"All Modalities Massage",
    "wof:placetype":"venue"
},
  "geometry": {"coordinates":[-80.20117,25.766047],"type":"Point"}
}