{
  "type": "Feature",
  "properties": {
    "addr:full":"5929 University Blvd W Jacksonville FL 32216",
    "addr:housenumber":"5929",
    "addr:postcode":"32216",
    "addr:street":"University Blvd W",
    "iso:country":"US",
    "sg:address":"5929 University Blvd W",
    "sg:city":"Jacksonville",
    "sg:classifiers":[
        {
            "category":"Retail",
            "subcategory":"Laundry & Dry Cleaning",
            "type":"Services"
        }
    ],
    "sg:phone":"+1 904 448 9977",
    "sg:postcode":"32216",
    "sg:province":"FL",
    "wof:name":"Sparkle Coin Laundry & Dry Cln",
    "wof:placetype":"venue"
},
  "geometry": {"coordinates":[-81.60374,30.276748],"type":"Point"}
}