{
  "type": "Feature",
  "properties": {
    "iso:country":"US",
    "sg:address":"8644 Eagle Run Dr",
    "sg:city":"Boca Raton",
    "sg:classifiers":[
        {
            "category":"Manufacturing",
            "subcategory":"Textiles",
            "type":"Manufacturing & Wholesale Goods"
        }
    ],
    "sg:phone":"+1 561 271 7682",
    "sg:postcode":"33434",
    "sg:province":"FL",
    "sg:tags":[
        "medical",
        "scrubs",
        "manufacturer"
    ],
    "wof:name":"American Scrubs Inc",
    "wof:placetype":"venue"
},
  "geometry": {"coordinates":[-80.181082,26.371982],"type":"Point"}
}