{
  "type": "Feature",
  "properties": {
    "addr:full":"800 20th Pl Vero Beach FL 32960",
    "addr:housenumber":"800",
    "addr:postcode":"32960",
    "addr:street":"20Th Pl",
    "iso:country":"US",
    "sg:address":"800 20th Pl",
    "sg:city":"Vero Beach",
    "sg:classifiers":[
        {
            "category":"Real Estate",
            "subcategory":"Real Estate Agent",
            "type":"Services"
        }
    ],
    "sg:phone":"+1 772 794 2800",
    "sg:postcode":"32960",
    "sg:province":"FL",
    "wof:name":"M J Property Solution Inc",
    "wof:placetype":"venue"
},
  "geometry": {"coordinates":[-80.39117899999999,27.638869],"type":"Point"}
}