{
  "type": "Feature",
  "properties": {
    "addr:full":"1362 W 42nd Pl Hialeah FL 33012",
    "addr:housenumber":"1362",
    "addr:postcode":"33012",
    "addr:street":"W 42Nd Pl",
    "iso:country":"US",
    "sg:address":"1362 W 42nd Pl",
    "sg:city":"Hialeah",
    "sg:classifiers":[
        {
            "category":"Retail",
            "subcategory":"Repair Shop",
            "type":"Services"
        }
    ],
    "sg:phone":"+1 305 558 3828",
    "sg:postcode":"33012",
    "sg:province":"FL",
    "sg:tags":[
        "small",
        "major",
        "appliance",
        "refinishing"
    ],
    "wof:name":"Gonzalez Appliance Repair",
    "wof:placetype":"venue"
},
  "geometry": {"coordinates":[-80.31020599999999,25.860374],"type":"Point"}
}