{
  "type": "Feature",
  "properties": {
    "addr:full":"1555 Carroll St Clearwater FL 33755",
    "addr:housenumber":"1555",
    "addr:postcode":"33755",
    "addr:street":"Carroll St",
    "iso:country":"US",
    "sg:address":"1555 Carroll St",
    "sg:city":"Clearwater",
    "sg:classifiers":[
        {
            "category":"Professional",
            "type":"Services"
        }
    ],
    "sg:phone":"+1 727 441 9737",
    "sg:postcode":"33755",
    "sg:province":"FL",
    "wof:name":"Blue Networks Inc",
    "wof:placetype":"venue"
},
  "geometry": {"coordinates":[-82.771275,27.978978],"type":"Point"}
}