{
  "type": "Feature",
  "properties": {
    "addr:full":"1629 N Hiatus Rd Pembroke Pines FL 33026",
    "addr:housenumber":"1629",
    "addr:postcode":"33026",
    "addr:street":"N Hiatus Rd",
    "iso:country":"US",
    "sg:address":"1629 N Hiatus Rd",
    "sg:city":"Pembroke Pines",
    "sg:classifiers":[
        {
            "category":"Restaurant",
            "type":"Food & Drink"
        }
    ],
    "sg:phone":"+1 954 431 4554",
    "sg:postcode":"33026",
    "sg:province":"FL",
    "wof:name":"Amici's Restorante & Pizzeria",
    "wof:placetype":"venue"
},
  "geometry": {"coordinates":[-80.297883,26.025346],"type":"Point"}
}