{
  "type": "Feature",
  "properties": {
    "iso:country":"US",
    "sg:address":"11818 71st St E",
    "sg:city":"Parrish",
    "sg:classifiers":[
        {
            "category":"Building & Trades",
            "subcategory":"Construction",
            "type":"Services"
        }
    ],
    "sg:phone":"+1 941 776 0808",
    "sg:postcode":"34219",
    "sg:province":"FL",
    "sg:tags":[
        "house"
    ],
    "wof:name":"Denver Moore Builder",
    "wof:placetype":"venue"
},
  "geometry": {"coordinates":[-82.432012,27.577783],"type":"Point"}
}