{
  "type": "Feature",
  "properties": {
    "iso:country":"US",
    "sg:address":"2912 Ponce de Leon Blvd",
    "sg:city":"Coral Gables",
    "sg:classifiers":[
        {
            "category":"Professional",
            "type":"Services"
        }
    ],
    "sg:phone":"+1 305 774 6006",
    "sg:postcode":"33134",
    "sg:province":"FL",
    "sg:tags":[
        "arts",
        "artist"
    ],
    "wof:name":"Gallery Ziv",
    "wof:placetype":"venue"
},
  "geometry": {"coordinates":[-80.258594,25.745237],"type":"Point"}
}