{
  "type": "Feature",
  "properties": {
    "iso:country":"US",
    "sg:address":"3111 3rd St W",
    "sg:city":"Bradenton",
    "sg:classifiers":[
        {
            "category":"Retail",
            "subcategory":"Auto Repair",
            "type":"Services"
        }
    ],
    "sg:phone":"+1 941 746 4417",
    "sg:postcode":"34205",
    "sg:province":"FL",
    "sg:tags":[
        "repairing",
        "automobile"
    ],
    "sg:website":"http://clickserve.dartsearch.net/link/click?lid=43000000313867661&ds_s_kwgid=58000000006820725&ds_e_matchtype={MatchType}&ds_e_kwdid={OrderItemId}&ds_e_adid={AdId}&ds_url_v=2",
    "wof:name":"Road Tech Automotive",
    "wof:placetype":"venue"
},
  "geometry": {"coordinates":[-82.565067,27.472396],"type":"Point"}
}