{
  "type": "Feature",
  "properties": {
    "iso:country":"US",
    "sg:address":"3062 NW 72nd Ave",
    "sg:city":"Miami",
    "sg:classifiers":[
        {
            "category":"Professional",
            "subcategory":"Computer Services",
            "type":"Services"
        }
    ],
    "sg:phone":"+1 305 994 9933",
    "sg:postcode":"33122",
    "sg:province":"FL",
    "sg:tags":[
        "specializing",
        "integrator",
        "system",
        "equipment"
    ],
    "wof:name":"Wwwarcosyscom",
    "wof:placetype":"venue"
},
  "geometry": {"coordinates":[-80.313135,25.803023],"type":"Point"}
}