{
  "type": "Feature",
  "properties": {
    "addr:full":"3747 Cleveland Ave Fort Myers FL 33901",
    "addr:housenumber":"3747",
    "addr:postcode":"33901",
    "addr:street":"Cleveland Ave",
    "iso:country":"US",
    "sg:address":"3747 Cleveland Ave",
    "sg:city":"Fort Myers",
    "sg:classifiers":[
        {
            "category":"Restaurant",
            "type":"Food & Drink"
        }
    ],
    "sg:menulink":"http://www.allmenus.com/fl/fort-myers/200813-long-john-silvers/menu/",
    "sg:phone":"+1 239 936 6457",
    "sg:postcode":"33901",
    "sg:province":"FL",
    "sg:tags":[
        "seafood",
        "american"
    ],
    "wof:name":"Long John Silver's",
    "wof:placetype":"venue"
},
  "geometry": {"coordinates":[-81.871425,26.607782],"type":"Point"}
}