{
  "type": "Feature",
  "properties": {
    "addr:full":"24400 Oaks Blvd Land O Lakes FL 34639",
    "addr:housenumber":"24400",
    "addr:postcode":"34639",
    "addr:street":"Oaks Blvd Land",
    "iso:country":"US",
    "sg:address":"24400 Oaks Blvd",
    "sg:city":"Land O Lakes",
    "sg:classifiers":[
        {
            "category":"Restaurant",
            "type":"Food & Drink"
        }
    ],
    "sg:phone":"+1 813 994 3131",
    "sg:postcode":"34639",
    "sg:province":"FL",
    "sg:tags":[
        "eating"
    ],
    "wof:name":"Sundays Best Inc",
    "wof:placetype":"venue"
},
  "geometry": {"coordinates":[-82.402946,28.218692],"type":"Point"}
}