{
  "type": "Feature",
  "properties": {
    "addr:full":"4518 SW 6th Pl Cape Coral FL 33914",
    "addr:housenumber":"4518",
    "addr:postcode":"33914",
    "addr:street":"Sw 6Th Pl",
    "iso:country":"US",
    "sg:address":"4518 SW 6th Pl",
    "sg:city":"Cape Coral",
    "sg:classifiers":[
        {
            "category":"Retail",
            "subcategory":"Auto Repair",
            "type":"Services"
        }
    ],
    "sg:phone":"+1 239 549 2984",
    "sg:postcode":"33914",
    "sg:province":"FL",
    "sg:tags":[
        "general"
    ],
    "wof:name":"First Rate Auto & Truck Svcs",
    "wof:placetype":"venue"
},
  "geometry": {"coordinates":[-81.98783299999999,26.564798],"type":"Point"}
}