{
  "type": "Feature",
  "properties": {
    "iso:country":"US",
    "sg:address":"1980 N Atlantic Ave Ste 102",
    "sg:city":"Cocoa Beach",
    "sg:classifiers":[
        {
            "category":"Personal",
            "subcategory":"Day Spa",
            "type":"Services"
        },
        {
            "category":"Personal",
            "subcategory":"Nail Salon",
            "type":"Services"
        }
    ],
    "sg:phone":"+1 321 783 2003",
    "sg:postcode":"32931",
    "sg:province":"FL",
    "wof:name":"Hair Classics",
    "wof:placetype":"venue"
},
  "geometry": {"coordinates":[-80.610001,28.341499],"type":"Point"}
}