{
  "type": "Feature",
  "properties": {
    "addr:full":"9142 79th Ave Seminole FL 33777",
    "addr:housenumber":"9142",
    "addr:postcode":"33777",
    "addr:street":"79Th Ave",
    "iso:country":"US",
    "sg:address":"9142 79th Ave",
    "sg:city":"Seminole",
    "sg:classifiers":[
        {
            "category":"Building & Trades",
            "subcategory":"Cleaning & Sanitation",
            "type":"Services"
        }
    ],
    "sg:phone":"+1 727 397 0994",
    "sg:postcode":"33777",
    "sg:province":"FL",
    "sg:tags":[
        "maintenance"
    ],
    "wof:name":"K & R Landscape Maintenance",
    "wof:placetype":"venue"
},
  "geometry": {"coordinates":[-82.766141,27.844441],"type":"Point"}
}