{
  "type": "Feature",
  "properties": {
    "iso:country":"US",
    "sg:address":"705 S Federal Hwy",
    "sg:city":"Pompano Beach",
    "sg:classifiers":[
        {
            "category":"Manufacturing",
            "subcategory":"Apparel",
            "type":"Manufacturing & Wholesale Goods"
        }
    ],
    "sg:phone":"+1 954 781 7408",
    "sg:postcode":"33062",
    "sg:province":"FL",
    "sg:tags":[
        "product",
        "mfg"
    ],
    "wof:name":"Tropical Canvas",
    "wof:placetype":"venue"
},
  "geometry": {"coordinates":[-80.103431,26.223592],"type":"Point"}
}