{
  "type": "Feature",
  "properties": {
    "iso:country":"US",
    "sg:address":"8932 SW 17th Ter",
    "sg:city":"Miami",
    "sg:classifiers":[
        {
            "category":"Insurance",
            "subcategory":"Insurance Agent",
            "type":"Services"
        }
    ],
    "sg:phone":"+1 305 223 9743",
    "sg:postcode":"33165",
    "sg:province":"FL",
    "wof:name":"Framen Insurance Agency I",
    "wof:placetype":"venue"
},
  "geometry": {"coordinates":[-80.33935,25.753275],"type":"Point"}
}