{
  "type": "Feature",
  "properties": {
    "addr:full":"3133 Grand Ave Miami FL 33133",
    "addr:housenumber":"3133",
    "addr:postcode":"33133",
    "addr:street":"Grand Ave",
    "iso:country":"US",
    "sg:address":"3133 Grand Ave",
    "sg:city":"Miami",
    "sg:classifiers":[
        {
            "category":"Restaurant",
            "type":"Food & Drink"
        }
    ],
    "sg:phone":"+1 305 445 0805",
    "sg:postcode":"33133",
    "sg:province":"FL",
    "sg:tags":[
        "vegetarian"
    ],
    "wof:name":"The Last Carrot",
    "wof:placetype":"venue"
},
  "geometry": {"coordinates":[-80.24400300000001,25.7279],"type":"Point"}
}