{
  "type": "Feature",
  "properties": {
    "iso:country":"US",
    "sg:address":"4623 Atlantic Ave",
    "sg:city":"Sarasota",
    "sg:classifiers":[
        {
            "category":"Retail",
            "subcategory":"Repair Shop",
            "type":"Services"
        }
    ],
    "sg:phone":"+1 941 924 8564",
    "sg:postcode":"34233",
    "sg:province":"FL",
    "sg:tags":[
        "luggage"
    ],
    "wof:name":"D&R Luggage Repair",
    "wof:placetype":"venue"
},
  "geometry": {"coordinates":[-82.47735299999999,27.287409],"type":"Point"}
}