{
  "type": "Feature",
  "properties": {
    "iso:country":"US",
    "sg:address":"25150 W Newberry Rd",
    "sg:city":"Newberry",
    "sg:classifiers":[
        {
            "category":"Food & Beverages",
            "subcategory":"Groceries & Convenience Stores",
            "type":"Retail Goods"
        }
    ],
    "sg:phone":"+1 352 472 3899",
    "sg:postcode":"32669",
    "sg:province":"FL",
    "wof:name":"Hitchcocks Foodway",
    "wof:placetype":"venue"
},
  "geometry": {"coordinates":[-82.608473,29.646505],"type":"Point"}
}