{
  "type": "Feature",
  "properties": {
    "addr:full":"2285 NW 150th St Opa Locka FL 33054",
    "addr:housenumber":"2285",
    "addr:postcode":"33054",
    "addr:street":"Nw 150Th St;Locka",
    "iso:country":"US",
    "sg:address":"2285 NW 150th St",
    "sg:city":"Opa Locka",
    "sg:classifiers":[
        {
            "category":"Manufacturing",
            "subcategory":"Apparel",
            "type":"Manufacturing & Wholesale Goods"
        }
    ],
    "sg:phone":"+1 305 687 8725",
    "sg:postcode":"33054",
    "sg:province":"FL",
    "sg:tags":[
        "1",
        "largest",
        "uniform",
        "maker",
        "team"
    ],
    "wof:name":"Bold Look Inc",
    "wof:placetype":"venue"
},
  "geometry": {"coordinates":[-80.236261,25.911432],"type":"Point"}
}