{
  "type": "Feature",
  "properties": {
    "iso:country":"US",
    "sg:address":"12812 S Shore Dr",
    "sg:city":"Palm Beach Gardens",
    "sg:classifiers":[
        {
            "category":"Health Services",
            "subcategory":"Doctor",
            "type":"Services"
        }
    ],
    "sg:phone":"+1 561 627 6131",
    "sg:postcode":"33410",
    "sg:province":"FL",
    "wof:name":"Stephen Bradford & Leiann Dr",
    "wof:placetype":"venue"
},
  "geometry": {"coordinates":[-80.068798,26.866218],"type":"Point"}
}