{
  "type": "Feature",
  "properties": {
    "iso:country":"US",
    "sg:address":"443 Jax Estates Dr N",
    "sg:city":"Jacksonville",
    "sg:classifiers":[
        {
            "category":"Arts & Performance",
            "subcategory":"Theater",
            "type":"Entertainment"
        }
    ],
    "sg:phone":"+1 904 751 6142",
    "sg:postcode":"32218",
    "sg:province":"FL",
    "sg:tags":[
        "group"
    ],
    "wof:name":"Allied Powarz Entertainment",
    "wof:placetype":"venue"
},
  "geometry": {"coordinates":[-81.644559,30.467934],"type":"Point"}
}