{
  "type": "Feature",
  "properties": {
    "iso:country":"US",
    "sg:address":"144 Ave Messina",
    "sg:city":"Sarasota",
    "sg:classifiers":[
        {
            "category":"Shopping",
            "subcategory":"Clothing, Apparel, & Fashions",
            "type":"Retail Goods"
        }
    ],
    "sg:phone":"+1 941 346 8906",
    "sg:postcode":"34242",
    "sg:province":"FL",
    "sg:tags":[
        "t"
    ],
    "wof:name":"Rocketman",
    "wof:placetype":"venue"
},
  "geometry": {"coordinates":[-82.56767600000001,27.27604],"type":"Point"}
}