{
  "type": "Feature",
  "properties": {
    "iso:country":"US",
    "sg:address":"725 Gulf Shore Dr",
    "sg:city":"Destin",
    "sg:classifiers":[
        {
            "category":"Professional",
            "type":"Services"
        }
    ],
    "sg:phone":"+1 850 654 2744",
    "sg:postcode":"32541",
    "sg:province":"FL",
    "sg:tags":[
        "establishment"
    ],
    "wof:name":"Roy Anderson Corp",
    "wof:placetype":"venue"
},
  "geometry": {"coordinates":[-86.484827,30.384761],"type":"Point"}
}