{
  "type": "Feature",
  "properties": {
    "iso:country":"US",
    "sg:address":"1150 NE 86th St",
    "sg:city":"Miami",
    "sg:classifiers":[
        {
            "category":"Manufacturing",
            "subcategory":"Toys & Sporting Goods",
            "type":"Manufacturing & Wholesale Goods"
        }
    ],
    "sg:phone":"+1 305 751 5397",
    "sg:postcode":"33138",
    "sg:province":"FL",
    "sg:tags":[
        "mfg"
    ],
    "wof:name":"Robert Axelrod",
    "wof:placetype":"venue"
},
  "geometry": {"coordinates":[-80.17224299999999,25.854576],"type":"Point"}
}