{
  "type": "Feature",
  "properties": {
    "iso:country":"US",
    "sg:address":"502 W 49th St",
    "sg:city":"Hialeah",
    "sg:classifiers":[
        {
            "category":"Shopping",
            "subcategory":"Clothing, Apparel, & Fashions",
            "type":"Retail Goods"
        }
    ],
    "sg:phone":"+1 305 558 1944",
    "sg:postcode":"33012",
    "sg:province":"FL",
    "sg:tags":[
        "apparel",
        "women's"
    ],
    "sg:website":"http://www.ashleystewart.com",
    "wof:name":"Ashley Stewart Ltd.",
    "wof:placetype":"venue"
},
  "geometry": {"coordinates":[-80.293071,25.86659],"type":"Point"}
}