{
  "type": "Feature",
  "properties": {
    "iso:country":"US",
    "sg:address":"1918 NE 32nd Ave",
    "sg:city":"Fort Lauderdale",
    "sg:classifiers":[
        {
            "category":"Building & Trades",
            "subcategory":"Construction",
            "type":"Services"
        }
    ],
    "sg:phone":"+1 954 566 7221",
    "sg:postcode":"33305",
    "sg:province":"FL",
    "sg:tags":[
        "contractor"
    ],
    "wof:name":"American Contracting Funding",
    "wof:placetype":"venue"
},
  "geometry": {"coordinates":[-80.10298,26.155333],"type":"Point"}
}