{
  "type": "Feature",
  "properties": {
    "iso:country":"US",
    "sg:address":"3101 W Hwy 98",
    "sg:city":"Panama City",
    "sg:classifiers":[
        {
            "category":"Building & Trades",
            "subcategory":"Construction",
            "type":"Services"
        }
    ],
    "sg:phone":"+1 850 747 1936",
    "sg:postcode":"32401",
    "sg:province":"FL",
    "sg:tags":[
        "general",
        "contractor"
    ],
    "wof:name":"Pro Con Construction",
    "wof:placetype":"venue"
},
  "geometry": {"coordinates":[-85.70348199999999,30.180006],"type":"Point"}
}