{
  "type": "Feature",
  "properties": {
    "iso:country":"US",
    "sg:address":"17575 Dixie Hwy",
    "sg:city":"Miami",
    "sg:classifiers":[
        {
            "category":"Shopping",
            "type":"Retail Goods"
        }
    ],
    "sg:phone":"+1 305 232 1332",
    "sg:postcode":"33157",
    "sg:province":"FL",
    "sg:tags":[
        "merchandise"
    ],
    "wof:name":"Academy Trophies South",
    "wof:placetype":"venue"
},
  "geometry": {"coordinates":[-80.350455,25.606677],"type":"Point"}
}