{
  "type": "Feature",
  "properties": {
    "iso:country":"US",
    "sg:address":"3650 Coral Ridge Dr",
    "sg:city":"Pompano Beach",
    "sg:classifiers":[
        {
            "category":"Wholesale",
            "subcategory":"Computers",
            "type":"Manufacturing & Wholesale Goods"
        }
    ],
    "sg:phone":"+1 954 757 5844",
    "sg:postcode":"33065",
    "sg:province":"FL",
    "sg:tags":[
        "peripheral",
        "software"
    ],
    "wof:name":"Vertex Intl Trdg Group",
    "wof:placetype":"venue"
},
  "geometry": {"coordinates":[-80.28258599999999,26.276489],"type":"Point"}
}