{
  "type": "Feature",
  "properties": {
    "addr:full":"2825 Pine Ave Mims FL 32754",
    "addr:housenumber":"2825",
    "addr:postcode":"32754",
    "addr:street":"Pine Ave",
    "iso:country":"US",
    "sg:address":"2825 Pine Ave",
    "sg:city":"Mims",
    "sg:classifiers":[
        {
            "category":"Farming",
            "subcategory":"Orchard",
            "type":"Manufacturing & Wholesale Goods"
        }
    ],
    "sg:phone":"+1 321 269 7875",
    "sg:postcode":"32754",
    "sg:province":"FL",
    "sg:tags":[
        "citrus",
        "grove",
        "fruit"
    ],
    "wof:name":"C H Taylor",
    "wof:placetype":"venue"
},
  "geometry": {"coordinates":[-80.865332,28.666732],"type":"Point"}
}