{
  "type": "Feature",
  "properties": {
    "addr:full":"709 Silver Palm Ave Melbourne FL 32901",
    "addr:housenumber":"709",
    "addr:postcode":"32901",
    "addr:street":"Silver Palm Ave",
    "iso:country":"US",
    "sg:address":"709 Silver Palm Ave",
    "sg:city":"Melbourne",
    "sg:classifiers":[
        {
            "category":"Wholesale",
            "subcategory":"Hardware",
            "type":"Manufacturing & Wholesale Goods"
        }
    ],
    "sg:phone":"+1 321 729 6761",
    "sg:postcode":"32901",
    "sg:province":"FL",
    "sg:tags":[
        "equipment",
        "energy",
        "heating",
        "solar",
        "supply"
    ],
    "wof:name":"Hatcher Pool Heating",
    "wof:placetype":"venue"
},
  "geometry": {"coordinates":[-80.608407,28.084136],"type":"Point"}
}