{
  "type": "Feature",
  "properties": {
    "iso:country":"US",
    "sg:address":"403 Georgia St",
    "sg:city":"Starke",
    "sg:classifiers":[
        {
            "category":"Professional",
            "subcategory":"Lawyer & Legal Services",
            "type":"Services"
        }
    ],
    "sg:phone":"+1 904 964 5701",
    "sg:postcode":"32091",
    "sg:province":"FL",
    "sg:tags":[
        "attorney"
    ],
    "wof:name":"Dudley P Hardy Law Office",
    "wof:placetype":"venue"
},
  "geometry": {"coordinates":[-82.108801,29.955165],"type":"Point"}
}