{
  "type": "Feature",
  "properties": {
    "addr:full":"8415 SW 137th Ave Miami FL 33183",
    "addr:housenumber":"8415",
    "addr:postcode":"33183",
    "addr:street":"Sw 137Th Ave",
    "iso:country":"US",
    "sg:address":"8415 SW 137th Ave",
    "sg:city":"Miami",
    "sg:classifiers":[
        {
            "category":"Personal",
            "type":"Services"
        }
    ],
    "sg:phone":"+1 305 383 8960",
    "sg:postcode":"33183",
    "sg:province":"FL",
    "sg:tags":[
        "assistant"
    ],
    "wof:name":"Chamorros Enterprises Inc",
    "wof:placetype":"venue"
},
  "geometry": {"coordinates":[-80.41623,25.688111],"type":"Point"}
}