{
  "type": "Feature",
  "properties": {
    "addr:full":"7221 Aloma Ave Winter Park FL 32792",
    "addr:housenumber":"7221",
    "addr:postcode":"32792",
    "addr:street":"Aloma Ave",
    "iso:country":"US",
    "sg:address":"7221 Aloma Ave",
    "sg:city":"Winter Park",
    "sg:classifiers":[
        {
            "category":"Personal",
            "subcategory":"Beauty Salon",
            "type":"Services"
        }
    ],
    "sg:phone":"+1 407 657 9596",
    "sg:postcode":"32792",
    "sg:province":"FL",
    "sg:tags":[
        "treatment",
        "skin"
    ],
    "wof:name":"Skin TLC",
    "wof:placetype":"venue"
},
  "geometry": {"coordinates":[-81.291849,28.608059],"type":"Point"}
}