{
  "type": "Feature",
  "properties": {
    "iso:country":"US",
    "sg:address":"12835 US Hwy 19",
    "sg:city":"Port Richey",
    "sg:classifiers":[
        {
            "category":"Shopping",
            "subcategory":"Computers & Home Electronics",
            "type":"Retail Goods"
        }
    ],
    "sg:phone":"+1 727 862 7266",
    "sg:postcode":"34667",
    "sg:province":"FL",
    "wof:name":"PC Consultants of Pasco Inc",
    "wof:placetype":"venue"
},
  "geometry": {"coordinates":[-82.699319,28.34366],"type":"Point"}
}