{
  "type": "Feature",
  "properties": {
    "addr:full":"3109 W Colonial Dr Orlando FL 32808",
    "addr:housenumber":"3109",
    "addr:postcode":"32808",
    "addr:street":"W Colonial Dr",
    "iso:country":"US",
    "sg:address":"3109 W Colonial Dr",
    "sg:city":"Orlando",
    "sg:classifiers":[
        {
            "category":"Wholesale",
            "subcategory":"Machinery & Supplies",
            "type":"Manufacturing & Wholesale Goods"
        },
        {
            "category":"Shopping",
            "type":"Retail Goods"
        }
    ],
    "sg:phone":"+1 407 532 9933",
    "sg:postcode":"32808",
    "sg:province":"FL",
    "sg:tags":[
        "equipment",
        "establishment",
        "cosmetic",
        "perfume"
    ],
    "wof:name":"Vibe Beauty Supply Inc",
    "wof:placetype":"venue"
},
  "geometry": {"coordinates":[-81.415927,28.552855],"type":"Point"}
}