{
  "type": "Feature",
  "properties": {
    "iso:country":"US",
    "sg:address":"1653 NW 79th Ave",
    "sg:city":"Doral",
    "sg:classifiers":[
        {
            "category":"Wholesale",
            "subcategory":"Computers",
            "type":"Manufacturing & Wholesale Goods"
        }
    ],
    "sg:phone":"+1 305 477 2036",
    "sg:postcode":"33126",
    "sg:province":"FL",
    "wof:name":"Holocenter Corp",
    "wof:placetype":"venue"
},
  "geometry": {"coordinates":[-80.323967,25.789485],"type":"Point"}
}