{
  "type": "Feature",
  "properties": {
    "addr:full":"15455 Cedarwood Ln Naples FL 34110",
    "addr:housenumber":"15455",
    "addr:postcode":"34110",
    "addr:street":"Cedarwood Ln",
    "iso:country":"US",
    "sg:address":"15455 Cedarwood Ln",
    "sg:city":"Naples",
    "sg:classifiers":[
        {
            "category":"Real Estate",
            "subcategory":"Real Estate Agent",
            "type":"Services"
        }
    ],
    "sg:phone":"+1 239 594 2272",
    "sg:postcode":"34110",
    "sg:province":"FL",
    "wof:name":"MASON Realty",
    "wof:placetype":"venue"
},
  "geometry": {"coordinates":[-81.824112,26.31092],"type":"Point"}
}