{
  "type": "Feature",
  "properties": {
    "iso:country":"US",
    "sg:address":"1330 W Industrial Ave",
    "sg:city":"Boynton Beach",
    "sg:classifiers":[
        {
            "category":"Building & Trades",
            "subcategory":"Plumbing",
            "type":"Services"
        }
    ],
    "sg:phone":"+1 561 742 4220",
    "sg:postcode":"33426",
    "sg:province":"FL",
    "sg:tags":[
        "contractor"
    ],
    "wof:name":"A 1 Sun Protection",
    "wof:placetype":"venue"
},
  "geometry": {"coordinates":[-80.07622600000001,26.52974],"type":"Point"}
}