{
  "type": "Feature",
  "properties": {
    "iso:country":"US",
    "sg:address":"2701 E Fletcher Ave",
    "sg:city":"Tampa",
    "sg:classifiers":[
        {
            "category":"Shopping",
            "subcategory":"Department Store",
            "type":"Retail Goods"
        }
    ],
    "sg:phone":"+1 813 558 0994",
    "sg:postcode":"33612",
    "sg:province":"FL",
    "wof:name":"National Vision Inc",
    "wof:placetype":"venue"
},
  "geometry": {"coordinates":[-82.428236,28.069248],"type":"Point"}
}