{
  "type": "Feature",
  "properties": {
    "iso:country":"US",
    "sg:address":"1820 Barrs St",
    "sg:city":"Jacksonville",
    "sg:classifiers":[
        {
            "category":"Health Services",
            "subcategory":"Doctor",
            "type":"Services"
        }
    ],
    "sg:phone":"+1 904 387 1113",
    "sg:postcode":"32204",
    "sg:province":"FL",
    "sg:tags":[
        "medical"
    ],
    "wof:name":"Mayer George L MD",
    "wof:placetype":"venue"
},
  "geometry": {"coordinates":[-81.689143,30.307953],"type":"Point"}
}