{
  "type": "Feature",
  "properties": {
    "addr:full":"10180 Riverside Dr Palm Beach Gardens FL 33410",
    "addr:housenumber":"10180",
    "addr:postcode":"33410",
    "addr:street":"Riverside Dr",
    "iso:country":"US",
    "sg:address":"10180 Riverside Dr",
    "sg:city":"Palm Beach Gardens",
    "sg:classifiers":[
        {
            "category":"Wholesale",
            "subcategory":"Electrical",
            "type":"Manufacturing & Wholesale Goods"
        }
    ],
    "sg:phone":"+1 561 622 6294",
    "sg:postcode":"33410",
    "sg:province":"FL",
    "sg:tags":[
        "equipment"
    ],
    "wof:name":"Coilform Company",
    "wof:placetype":"venue"
},
  "geometry": {"coordinates":[-80.091499,26.825993],"type":"Point"}
}