{
  "type": "Feature",
  "properties": {
    "addr:full":"314 E Ocean Ave Boynton Beach FL 33435",
    "addr:housenumber":"314",
    "addr:postcode":"33435",
    "addr:street":"E Ocean Ave",
    "iso:country":"US",
    "sg:address":"314 E Ocean Ave",
    "sg:city":"Boynton Beach",
    "sg:classifiers":[
        {
            "category":"Recreation",
            "type":"Entertainment"
        }
    ],
    "sg:phone":"+1 561 588 7612",
    "sg:postcode":"33435",
    "sg:province":"FL",
    "sg:tags":[
        "guide"
    ],
    "wof:name":"B-Love III Driftboat",
    "wof:placetype":"venue"
},
  "geometry": {"coordinates":[-80.061413,26.527016],"type":"Point"}
}