{
  "type": "Feature",
  "properties": {
    "addr:full":"125 W Plant St Winter Garden FL 34787",
    "addr:housenumber":"125",
    "addr:postcode":"34787",
    "addr:street":"W Plant St",
    "iso:country":"US",
    "sg:address":"125 W Plant St",
    "sg:city":"Winter Garden",
    "sg:classifiers":[
        {
            "category":"Shopping",
            "subcategory":"Used Merchandise",
            "type":"Retail Goods"
        }
    ],
    "sg:phone":"+1 407 654 5885",
    "sg:postcode":"34787",
    "sg:province":"FL",
    "wof:name":"General Thrift Store",
    "wof:placetype":"venue"
},
  "geometry": {"coordinates":[-81.587514,28.565401],"type":"Point"}
}