{
  "type": "Feature",
  "properties": {
    "iso:country":"US",
    "sg:address":"21000 NW 2nd Ave",
    "sg:city":"Miami",
    "sg:classifiers":[
        {
            "category":"Building & Trades",
            "subcategory":"Equipment Rental",
            "type":"Services"
        }
    ],
    "sg:phone":"+1 954 763 1037",
    "sg:postcode":"33169",
    "sg:province":"FL",
    "sg:tags":[
        "leasing"
    ],
    "wof:name":"Lehman Isuzu & Leasing",
    "wof:placetype":"venue"
},
  "geometry": {"coordinates":[-80.20617900000001,25.971759],"type":"Point"}
}