{
  "type": "Feature",
  "properties": {
    "iso:country":"US",
    "sg:address":"7444 NW 14th St",
    "sg:city":"Ocala",
    "sg:classifiers":[
        {
            "category":"Building & Trades",
            "subcategory":"Construction",
            "type":"Services"
        }
    ],
    "sg:phone":"+1 352 854 2211",
    "sg:postcode":"34482",
    "sg:province":"FL",
    "sg:tags":[
        "home",
        "improvement"
    ],
    "wof:name":"A Best Home Repair & Mntnc",
    "wof:placetype":"venue"
},
  "geometry": {"coordinates":[-82.24263999999999,29.201098],"type":"Point"}
}