{
  "type": "Feature",
  "properties": {
    "addr:full":"7802 NW 103rd St Hialeah FL 33016",
    "addr:housenumber":"7802",
    "addr:postcode":"33016",
    "addr:street":"Nw 103Rd St",
    "iso:country":"US",
    "sg:address":"7802 NW 103rd St",
    "sg:city":"Hialeah",
    "sg:classifiers":[
        {
            "category":"Social Services",
            "type":"Services"
        }
    ],
    "sg:phone":"+1 305 819 4146",
    "sg:postcode":"33016",
    "sg:province":"FL",
    "sg:tags":[
        "program",
        "services-information",
        "referral"
    ],
    "wof:name":"Salvation Army",
    "wof:placetype":"venue"
},
  "geometry": {"coordinates":[-80.32441900000001,25.866756],"type":"Point"}
}