{
  "type": "Feature",
  "properties": {
    "addr:full":"11486 Corporate Blvd Orlando FL 32817",
    "addr:housenumber":"11486",
    "addr:postcode":"32817",
    "addr:street":"Corporate Blvd",
    "iso:country":"US",
    "sg:address":"11486 Corporate Blvd",
    "sg:city":"Orlando",
    "sg:classifiers":[
        {
            "category":"Banks & Credit Unions",
            "subcategory":"Bank",
            "type":"Services"
        }
    ],
    "sg:phone":"+1 407 273 5082",
    "sg:postcode":"32817",
    "sg:province":"FL",
    "sg:tags":[
        "loan",
        "real estate"
    ],
    "sg:website":"www.ameriquest.com",
    "wof:name":"Ameriquest",
    "wof:placetype":"venue"
},
  "geometry": {"coordinates":[-81.221333,28.602321],"type":"Point"}
}