{
  "type": "Feature",
  "properties": {
    "iso:country":"US",
    "sg:address":"2255 SW 70th Ave",
    "sg:city":"Fort Lauderdale",
    "sg:classifiers":[
        {
            "category":"Manufacturing",
            "subcategory":"Building Materials",
            "type":"Manufacturing & Wholesale Goods"
        }
    ],
    "sg:phone":"+1 954 801 8595",
    "sg:postcode":"33317",
    "sg:province":"FL",
    "sg:tags":[
        "mfg",
        "cabinet",
        "wood",
        "carpentry",
        "contractor",
        "kitchen"
    ],
    "wof:name":"Millcreek Fine Cabinetry Inc",
    "wof:placetype":"venue"
},
  "geometry": {"coordinates":[-80.238884,26.090889],"type":"Point"}
}