{
  "type": "Feature",
  "properties": {
    "iso:country":"US",
    "sg:address":"14689 Northlake Blvd",
    "sg:city":"West Palm Beach",
    "sg:classifiers":[
        {
            "category":"Building & Trades",
            "subcategory":"Landscaping Services",
            "type":"Services"
        }
    ],
    "sg:phone":"+1 561 333 0558",
    "sg:postcode":"33412",
    "sg:province":"FL",
    "sg:tags":[
        "landscape",
        "contractor"
    ],
    "wof:name":"Northlake Garden Ctr",
    "wof:placetype":"venue"
},
  "geometry": {"coordinates":[-80.272119,26.812153],"type":"Point"}
}