{
  "type": "Feature",
  "properties": {
    "iso:country":"US",
    "sg:address":"2751 Snyder Rd",
    "sg:city":"Sebring",
    "sg:classifiers":[
        {
            "category":"Retail",
            "subcategory":"Repair Shop",
            "type":"Services"
        }
    ],
    "sg:phone":"+1 863 381 0046",
    "sg:postcode":"33870",
    "sg:province":"FL",
    "sg:tags":[
        "related"
    ],
    "wof:name":"Mike Doerr's Mobile AC",
    "wof:placetype":"venue"
},
  "geometry": {"coordinates":[-81.38476,27.464338],"type":"Point"}
}