{
  "type": "Feature",
  "properties": {
    "iso:country":"US",
    "sg:address":"3738 Whidbey Way",
    "sg:city":"Naples",
    "sg:classifiers":[
        {
            "category":"Professional",
            "subcategory":"Employment Agencies",
            "type":"Services"
        }
    ],
    "sg:phone":"+1 239 566 8331",
    "sg:postcode":"34119",
    "sg:province":"FL",
    "wof:name":"Ad Staff Executive Search Inc",
    "wof:placetype":"venue"
},
  "geometry": {"coordinates":[-81.706636,26.250033],"type":"Point"}
}