{
  "type": "Feature",
  "properties": {
    "addr:full":"457 NE 1st Ter Crystal River FL 34429",
    "addr:housenumber":"457",
    "addr:postcode":"34429",
    "addr:street":"Ne 1St Ter",
    "iso:country":"US",
    "sg:address":"457 NE 1st Ter",
    "sg:city":"Crystal River",
    "sg:classifiers":[
        {
            "category":"Personal",
            "subcategory":"Beauty Salon",
            "type":"Services"
        }
    ],
    "sg:phone":"+1 352 795 7851",
    "sg:postcode":"34429",
    "sg:province":"FL",
    "wof:name":"K Nails",
    "wof:placetype":"venue"
},
  "geometry": {"coordinates":[-82.58323300000001,28.894972],"type":"Point"}
}