{
  "type": "Feature",
  "properties": {
    "iso:country":"US",
    "sg:address":"3627 SW Archer Rd",
    "sg:city":"Gainesville",
    "sg:classifiers":[
        {
            "category":"Building & Trades",
            "subcategory":"Construction",
            "type":"Services"
        }
    ],
    "sg:phone":"+1 352 372 0987",
    "sg:postcode":"32608",
    "sg:province":"FL",
    "sg:tags":[
        "general",
        "contractor"
    ],
    "wof:name":"Haynes Co",
    "wof:placetype":"venue"
},
  "geometry": {"coordinates":[-82.387593,29.616449],"type":"Point"}
}