{
  "type": "Feature",
  "properties": {
    "iso:country":"US",
    "sg:address":"2401 University Pkwy",
    "sg:city":"Sarasota",
    "sg:classifiers":[
        {
            "category":"Health Services",
            "subcategory":"Doctor",
            "type":"Services"
        }
    ],
    "sg:phone":"+1 941 351 9940",
    "sg:postcode":"34243",
    "sg:province":"FL",
    "sg:tags":[
        "physician",
        "surgeon"
    ],
    "wof:name":"Brian E Angsten MD",
    "wof:placetype":"venue"
},
  "geometry": {"coordinates":[-82.522958,27.388939],"type":"Point"}
}