{
  "type": "Feature",
  "properties": {
    "iso:country":"US",
    "sg:address":"2885 Kensington Trce",
    "sg:city":"Tarpon Springs",
    "sg:classifiers":[
        {
            "category":"Banks & Credit Unions",
            "subcategory":"Financial Services",
            "type":"Services"
        }
    ],
    "sg:phone":"+1 727 944 2560",
    "sg:postcode":"34688",
    "sg:province":"FL",
    "sg:tags":[
        "company",
        "holding"
    ],
    "wof:name":"R&D Holdings LLC",
    "wof:placetype":"venue"
},
  "geometry": {"coordinates":[-82.70255,28.13814],"type":"Point"}
}