{
  "type": "Feature",
  "properties": {
    "addr:full":"1350 W Broward Blvd Fort Lauderdale FL 33312",
    "addr:housenumber":"1350",
    "addr:postcode":"33312",
    "addr:street":"W Broward Blvd",
    "iso:country":"US",
    "sg:address":"1350 W Broward Blvd",
    "sg:city":"Fort Lauderdale",
    "sg:classifiers":[
        {
            "category":"Recreation",
            "type":"Entertainment"
        }
    ],
    "sg:phone":"+1 954 828 5346",
    "sg:postcode":"33312",
    "sg:province":"FL",
    "wof:name":"Parks Rcrtons Admnstrtion Svcs",
    "wof:placetype":"venue"
},
  "geometry": {"coordinates":[-80.158153,26.121844],"type":"Point"}
}