{
  "type": "Feature",
  "properties": {
    "iso:country":"US",
    "sg:address":"10863 NW 7th St",
    "sg:city":"Miami",
    "sg:classifiers":[
        {
            "category":"Communications",
            "subcategory":"Radio Station",
            "type":"Services"
        }
    ],
    "sg:phone":"+1 305 551 4135",
    "sg:postcode":"33172",
    "sg:province":"FL",
    "sg:tags":[
        "broadcast"
    ],
    "wof:name":"FM Productions Inc",
    "wof:placetype":"venue"
},
  "geometry": {"coordinates":[-80.37358999999999,25.775503],"type":"Point"}
}