{
  "type": "Feature",
  "properties": {
    "iso:country":"US",
    "sg:address":"627 6th St",
    "sg:city":"West Palm Beach",
    "sg:classifiers":[
        {
            "category":"Professional",
            "type":"Services"
        }
    ],
    "sg:phone":"+1 561 659 1694",
    "sg:postcode":"33401",
    "sg:province":"FL",
    "sg:tags":[
        "establishment"
    ],
    "wof:name":"Housing Partnership Inc",
    "wof:placetype":"venue"
},
  "geometry": {"coordinates":[-80.05815,26.719022],"type":"Point"}
}