{
  "type": "Feature",
  "properties": {
    "iso:country":"US",
    "sg:address":"825 Mockingbird Dr",
    "sg:city":"Port Orange",
    "sg:classifiers":[
        {
            "category":"Professional",
            "subcategory":"Advertising",
            "type":"Services"
        }
    ],
    "sg:phone":"+1 386 304 0191",
    "sg:postcode":"32127",
    "sg:province":"FL",
    "wof:name":"Mobile Billboards USA",
    "wof:placetype":"venue"
},
  "geometry": {"coordinates":[-81.01348900000001,29.118329],"type":"Point"}
}