{
  "type": "Feature",
  "properties": {
    "iso:country":"US",
    "sg:address":"5225 Silver Star Rd",
    "sg:city":"Orlando",
    "sg:classifiers":[
        {
            "category":"Building & Trades",
            "subcategory":"Construction",
            "type":"Services"
        }
    ],
    "sg:phone":"+1 407 578 6086",
    "sg:postcode":"32808",
    "sg:province":"FL",
    "sg:tags":[
        "body",
        "auto",
        "contractor"
    ],
    "wof:name":"Florida Custom Tinting",
    "wof:placetype":"venue"
},
  "geometry": {"coordinates":[-81.4539,28.578027],"type":"Point"}
}