{
  "type": "Feature",
  "properties": {
    "addr:full":"570 W Taylor Rd De Land FL 32720",
    "addr:housenumber":"570",
    "addr:postcode":"32720",
    "addr:street":"W Taylor Rd De Land",
    "iso:country":"US",
    "sg:address":"570 W Taylor Rd",
    "sg:city":"De Land",
    "sg:classifiers":[
        {
            "category":"Railroad",
            "type":"Transportation"
        }
    ],
    "sg:phone":"+1 386 734 4617",
    "sg:postcode":"32720",
    "sg:province":"FL",
    "sg:tags":[
        "operator",
        "line"
    ],
    "wof:name":"CSX",
    "wof:placetype":"venue"
},
  "geometry": {"coordinates":[-81.31235100000001,28.998932],"type":"Point"}
}