{
  "type": "Feature",
  "properties": {
    "iso:country":"US",
    "sg:address":"963 Sabal Grove Dr",
    "sg:city":"Rockledge",
    "sg:classifiers":[
        {
            "category":"Building & Trades",
            "subcategory":"Landscaping Services",
            "type":"Services"
        }
    ],
    "sg:phone":"+1 321 633 1063",
    "sg:postcode":"32955",
    "sg:province":"FL",
    "wof:name":"A Big Kahuna Lawn Care",
    "wof:placetype":"venue"
},
  "geometry": {"coordinates":[-80.72640699999999,28.310381],"type":"Point"}
}