{
  "type": "Feature",
  "properties": {
    "iso:country":"US",
    "sg:address":"33 E Gregory St",
    "sg:city":"Pensacola",
    "sg:classifiers":[
        {
            "category":"Education",
            "subcategory":"School",
            "type":"Public Place"
        }
    ],
    "sg:phone":"+1 850 433 2463",
    "sg:postcode":"32502",
    "sg:province":"FL",
    "sg:tags":[
        "child",
        "day",
        "care"
    ],
    "wof:name":"Child Dscvry Ctr of Frst Pres",
    "wof:placetype":"venue"
},
  "geometry": {"coordinates":[-87.214179,30.415711],"type":"Point"}
}