{
  "type": "Feature",
  "properties": {
    "iso:country":"US",
    "sg:address":"7455 NW 41st St",
    "sg:city":"Miami",
    "sg:classifiers":[
        {
            "category":"Real Estate",
            "subcategory":"Real Estate Agent",
            "type":"Services"
        }
    ],
    "sg:phone":"+1 305 470 2022",
    "sg:postcode":"33166",
    "sg:province":"FL",
    "wof:name":"Challenge Corp",
    "wof:placetype":"venue"
},
  "geometry": {"coordinates":[-80.31635900000001,25.811674],"type":"Point"}
}