{
  "type": "Feature",
  "properties": {
    "iso:country":"US",
    "sg:address":"2121 State Rd 472",
    "sg:city":"Deland",
    "sg:classifiers":[
        {
            "category":"Home & Garden",
            "subcategory":"Building Materials",
            "type":"Retail Goods"
        }
    ],
    "sg:phone":"+1 386 775 2300",
    "sg:postcode":"32724",
    "sg:province":"FL",
    "wof:name":"Kobrin Builders Supply Inc",
    "wof:placetype":"venue"
},
  "geometry": {"coordinates":[-81.27704199999999,28.967451],"type":"Point"}
}