{
  "type": "Feature",
  "properties": {
    "iso:country":"US",
    "sg:address":"23345 Water Cir",
    "sg:city":"Boca Raton",
    "sg:classifiers":[
        {
            "category":"Retail",
            "subcategory":"Repair Shop",
            "type":"Services"
        }
    ],
    "sg:phone":"+1 561 367 1216",
    "sg:postcode":"33486",
    "sg:province":"FL",
    "sg:tags":[
        "equipment",
        "conditioning",
        "air"
    ],
    "wof:name":"Rainbow Mechanical Co",
    "wof:placetype":"venue"
},
  "geometry": {"coordinates":[-80.12520600000001,26.331619],"type":"Point"}
}