{
  "type": "Feature",
  "properties": {
    "iso:country":"US",
    "sg:address":"33 N Garden Ave",
    "sg:city":"Clearwater",
    "sg:classifiers":[
        {
            "category":"Food & Beverages",
            "subcategory":"Groceries & Convenience Stores",
            "type":"Retail Goods"
        },
        {
            "category":"Restaurant",
            "type":"Food & Drink"
        }
    ],
    "sg:phone":"+1 727 445 9376",
    "sg:postcode":"33755",
    "sg:province":"FL",
    "sg:tags":[
        "delicatessen"
    ],
    "wof:name":"Jack's Downstown Deli",
    "wof:placetype":"venue"
},
  "geometry": {"coordinates":[-82.798625,27.966572],"type":"Point"}
}