{
  "type": "Feature",
  "properties": {
    "iso:country":"US",
    "sg:address":"4348 Palm Ave",
    "sg:city":"West Palm Beach",
    "sg:classifiers":[
        {
            "category":"Food & Beverages",
            "subcategory":"Specialty",
            "type":"Retail Goods"
        }
    ],
    "sg:phone":"+1 561 965 9692",
    "sg:postcode":"33406",
    "sg:province":"FL",
    "sg:tags":[
        "health",
        "diet"
    ],
    "wof:name":"Low Carb Marketplace",
    "wof:placetype":"venue"
},
  "geometry": {"coordinates":[-80.109163,26.659824],"type":"Point"}
}