{
  "type": "Feature",
  "properties": {
    "iso:country":"US",
    "sg:address":"113 6th Ln",
    "sg:city":"Key Largo",
    "sg:classifiers":[
        {
            "category":"Professional",
            "subcategory":"Lawyer & Legal Services",
            "type":"Services"
        }
    ],
    "sg:phone":"+1 305 451 0143",
    "sg:postcode":"33037",
    "sg:province":"FL",
    "wof:name":"Esther Arango",
    "wof:placetype":"venue"
},
  "geometry": {"coordinates":[-80.413166,25.114974],"type":"Point"}
}