{
  "type": "Feature",
  "properties": {
    "addr:full":"1315 W 17th St Panama City FL 32405",
    "addr:housenumber":"1315",
    "addr:postcode":"32405",
    "addr:street":"W 17Th St",
    "iso:country":"US",
    "sg:address":"1315 W 17th St",
    "sg:city":"Panama City",
    "sg:classifiers":[
        {
            "category":"Government",
            "subcategory":"Post Office",
            "type":"Public Place"
        }
    ],
    "sg:phone":"+1 850 914 2539",
    "sg:postcode":"32405",
    "sg:province":"FL",
    "sg:tags":[
        "postal",
        "us"
    ],
    "wof:name":"Vehical Maintenance Department",
    "wof:placetype":"venue"
},
  "geometry": {"coordinates":[-85.684637,30.17889],"type":"Point"}
}