{
  "type": "Feature",
  "properties": {
    "addr:full":"700 S Nova Rd Daytona Beach FL 32114",
    "addr:housenumber":"700",
    "addr:postcode":"32114",
    "addr:street":"S Nova Rd",
    "iso:country":"US",
    "sg:address":"700 S Nova Rd",
    "sg:city":"Daytona Beach",
    "sg:classifiers":[
        {
            "category":"Wholesale",
            "subcategory":"Auto Parts",
            "type":"Manufacturing & Wholesale Goods"
        }
    ],
    "sg:phone":"+1 386 226 2070",
    "sg:postcode":"32114",
    "sg:province":"FL",
    "sg:tags":[
        "automobile",
        "rebuilds",
        "compress",
        "condition",
        "air"
    ],
    "wof:name":"Tropical Auto Air of Daytona",
    "wof:placetype":"venue"
},
  "geometry": {"coordinates":[-81.032023,29.189456],"type":"Point"}
}