{
  "type": "Feature",
  "properties": {
    "iso:country":"US",
    "sg:address":"4425 N US Hwy 17",
    "sg:city":"Deland",
    "sg:classifiers":[
        {
            "category":"Bars & Pubs",
            "type":"Food & Drink"
        }
    ],
    "sg:phone":"+1 386 985 3456",
    "sg:postcode":"32720",
    "sg:province":"FL",
    "wof:name":"Traders Jack",
    "wof:placetype":"venue"
},
  "geometry": {"coordinates":[-81.33969399999999,29.102719],"type":"Point"}
}