{
  "type": "Feature",
  "properties": {
    "addr:full":"852 S Flagler Dr West Palm Beach FL 33401",
    "addr:housenumber":"852",
    "addr:postcode":"33401",
    "addr:street":"S Flagler Dr",
    "iso:country":"US",
    "sg:address":"852 S Flagler Dr",
    "sg:city":"West Palm Beach",
    "sg:classifiers":[
        {
            "category":"Professional",
            "type":"Services"
        }
    ],
    "sg:phone":"+1 561 833 5571",
    "sg:postcode":"33401",
    "sg:province":"FL",
    "sg:tags":[
        "establishment"
    ],
    "wof:name":"Southern Power & Controls",
    "wof:placetype":"venue"
},
  "geometry": {"coordinates":[-80.048762,26.705748],"type":"Point"}
}