{
  "type": "Feature",
  "properties": {
    "iso:country":"US",
    "sg:address":"495 NW 77th Street",
    "sg:city":"Miami",
    "sg:classifiers":[
        {
            "category":"Professional",
            "subcategory":"Art Services",
            "type":"Services"
        },
        {
            "category":"Shopping",
            "subcategory":"Crafts & Fabrics",
            "type":"Retail Goods"
        }
    ],
    "sg:phone":"+1 305 917 5376",
    "sg:postcode":"33147",
    "sg:province":"FL",
    "sg:tags":[
        "choreographer",
        "supply"
    ],
    "sg:website":"http://www.youthmiami.com",
    "wof:name":"YES! Program, Inc.",
    "wof:placetype":"venue"
},
  "geometry": {"coordinates":[-80.205321,25.845312],"type":"Point"}
}