{
  "type": "Feature",
  "properties": {
    "addr:full":"9700 SW 344th St Homestead FL 33035",
    "addr:housenumber":"9700",
    "addr:postcode":"33035",
    "addr:street":"Sw 344Th St",
    "iso:country":"US",
    "sg:address":"9700 SW 344th St",
    "sg:city":"Homestead",
    "sg:classifiers":[
        {
            "category":"Restaurant",
            "type":"Food & Drink"
        }
    ],
    "sg:phone":"+1 305 246 6582",
    "sg:postcode":"33035",
    "sg:province":"FL",
    "sg:tags":[
        "eating"
    ],
    "wof:name":"Aramark",
    "wof:placetype":"venue"
},
  "geometry": {"coordinates":[-80.41224099999999,25.448392],"type":"Point"}
}