{
  "type": "Feature",
  "properties": {
    "iso:country":"US",
    "sg:address":"4219 Saint Johns Ave",
    "sg:city":"Jacksonville",
    "sg:classifiers":[
        {
            "category":"Bars & Pubs",
            "subcategory":"Nightclub",
            "type":"Food & Drink"
        }
    ],
    "sg:phone":"+1 904 387 3582",
    "sg:postcode":"32210",
    "sg:province":"FL",
    "sg:tags":[
        "club",
        "night"
    ],
    "wof:name":"Cross Currents Inc",
    "wof:placetype":"venue"
},
  "geometry": {"coordinates":[-81.713776,30.288757],"type":"Point"}
}