{
  "type": "Feature",
  "properties": {
    "iso:country":"US",
    "sg:address":"3018 Dividing Creek Dr",
    "sg:city":"Sarasota",
    "sg:classifiers":[
        {
            "category":"Building & Trades",
            "subcategory":"Construction",
            "type":"Services"
        }
    ],
    "sg:phone":"+1 941 364 8356",
    "sg:postcode":"34237",
    "sg:province":"FL",
    "sg:tags":[
        "contractor"
    ],
    "wof:name":"Mike Myers Masonry Inc",
    "wof:placetype":"venue"
},
  "geometry": {"coordinates":[-82.509834,27.348008],"type":"Point"}
}