{
  "type": "Feature",
  "properties": {
    "addr:full":"3736 Powers Ridge Ct Orlando FL 32808",
    "addr:housenumber":"3736",
    "addr:postcode":"32808",
    "addr:street":"Powers Ridge Ct",
    "iso:country":"US",
    "sg:address":"3736 Powers Ridge Ct",
    "sg:city":"Orlando",
    "sg:classifiers":[
        {
            "category":"Social Services",
            "type":"Services"
        }
    ],
    "sg:phone":"+1 407 298 0429",
    "sg:postcode":"32808",
    "sg:province":"FL",
    "wof:name":"Belinda Jackson Family Child C",
    "wof:placetype":"venue"
},
  "geometry": {"coordinates":[-81.466611,28.594099],"type":"Point"}
}