{
  "type": "Feature",
  "properties": {
    "addr:full":"12816 139th St Largo FL 33774",
    "addr:housenumber":"12816",
    "addr:postcode":"33774",
    "addr:street":"139Th St",
    "iso:country":"US",
    "sg:address":"12816 139th St",
    "sg:city":"Largo",
    "sg:classifiers":[
        {
            "category":"Social Services",
            "type":"Services"
        }
    ],
    "sg:phone":"+1 727 595 4542",
    "sg:postcode":"33774",
    "sg:province":"FL",
    "sg:tags":[
        "youth",
        "organization",
        "center"
    ],
    "wof:name":"Young Life Assoc Regl Director",
    "wof:placetype":"venue"
},
  "geometry": {"coordinates":[-82.831585,27.88932],"type":"Point"}
}