{
  "type": "Feature",
  "properties": {
    "iso:country":"US",
    "sg:address":"6901 Della Dr",
    "sg:city":"Orlando",
    "sg:classifiers":[
        {
            "category":"Building & Trades",
            "subcategory":"Cleaning & Sanitation",
            "type":"Services"
        }
    ],
    "sg:phone":"+1 407 226 8171",
    "sg:postcode":"32819",
    "sg:province":"FL",
    "sg:tags":[
        "house"
    ],
    "wof:name":"HCC House Cleaning Corp",
    "wof:placetype":"venue"
},
  "geometry": {"coordinates":[-81.489862,28.459721],"type":"Point"}
}