{
  "type": "Feature",
  "properties": {
    "iso:country":"US",
    "sg:address":"5220 Belfort Rd",
    "sg:city":"Jacksonville",
    "sg:classifiers":[
        {
            "category":"Insurance",
            "subcategory":"Insurance Agent",
            "type":"Services"
        }
    ],
    "sg:phone":"+1 904 296 0310",
    "sg:postcode":"32256",
    "sg:province":"FL",
    "wof:name":"Kemper Insurance Co",
    "wof:placetype":"venue"
},
  "geometry": {"coordinates":[-81.585331,30.241317],"type":"Point"}
}