{
  "type": "Feature",
  "properties": {
    "addr:full":"6415 Lake Worth Rd Greenacres FL 33463",
    "addr:housenumber":"6415",
    "addr:postcode":"33463",
    "addr:street":"Lake Worth Rd",
    "iso:country":"US",
    "sg:address":"6415 Lake Worth Rd",
    "sg:city":"Greenacres",
    "sg:classifiers":[
        {
            "category":"Organizations",
            "subcategory":"Professional Association",
            "type":"Services"
        }
    ],
    "sg:phone":"+1 561 304 3400",
    "sg:postcode":"33463",
    "sg:province":"FL",
    "wof:name":"Children's Internatinal Netwrk",
    "wof:placetype":"venue"
},
  "geometry": {"coordinates":[-80.146012,26.619162],"type":"Point"}
}