{
  "type": "Feature",
  "properties": {
    "addr:full":"1199 W Church St Jacksonville FL 32204",
    "addr:housenumber":"1199",
    "addr:postcode":"32204",
    "addr:street":"W Church St",
    "iso:country":"US",
    "sg:address":"1199 W Church St",
    "sg:city":"Jacksonville",
    "sg:classifiers":[
        {
            "category":"Government",
            "subcategory":"Office",
            "type":"Public Place"
        }
    ],
    "sg:phone":"+1 904 630 0360",
    "sg:postcode":"32204",
    "sg:province":"FL",
    "sg:tags":[
        "village"
    ],
    "wof:name":"Florida C Dwight Community Ctr",
    "wof:placetype":"venue"
},
  "geometry": {"coordinates":[-81.673306,30.333233],"type":"Point"}
}