{
  "type": "Feature",
  "properties": {
    "iso:country":"US",
    "sg:address":"10351 Westside Ln",
    "sg:city":"Bonita Springs",
    "sg:classifiers":[
        {
            "category":"Retail",
            "subcategory":"Auto Repair",
            "type":"Services"
        }
    ],
    "sg:phone":"+1 239 947 5661",
    "sg:postcode":"34135",
    "sg:province":"FL",
    "sg:tags":[
        "glass",
        "coating",
        "tinting"
    ],
    "wof:name":"Sun & Shield Inc",
    "wof:placetype":"venue"
},
  "geometry": {"coordinates":[-81.781373,26.370475],"type":"Point"}
}