{
  "type": "Feature",
  "properties": {
    "addr:full":"11391 NW 37th St Fort Lauderdale FL 33323",
    "addr:housenumber":"11391",
    "addr:postcode":"33323",
    "addr:street":"Nw 37Th St",
    "iso:country":"US",
    "sg:address":"11391 NW 37th St",
    "sg:city":"Fort Lauderdale",
    "sg:classifiers":[
        {
            "category":"Building & Trades",
            "subcategory":"Construction",
            "type":"Services"
        }
    ],
    "sg:phone":"+1 954 349 3995",
    "sg:postcode":"33323",
    "sg:province":"FL",
    "sg:tags":[
        "house"
    ],
    "wof:name":"Tryco Investments Corp",
    "wof:placetype":"venue"
},
  "geometry": {"coordinates":[-80.299694,26.172098],"type":"Point"}
}