{
  "type": "Feature",
  "properties": {
    "iso:country":"US",
    "sg:address":"10351 NE 5th Ave",
    "sg:city":"Miami Shores",
    "sg:classifiers":[
        {
            "category":"Education",
            "subcategory":"School",
            "type":"Public Place"
        }
    ],
    "sg:phone":"+1 305 754 0192",
    "sg:postcode":"33138",
    "sg:province":"FL",
    "sg:tags":[
        "elementary"
    ],
    "sg:website":"www.dadeschools.net",
    "wof:name":"Miami Shores Elementary School",
    "wof:placetype":"venue"
},
  "geometry": {"coordinates":[-80.187468,25.870696],"type":"Point"}
}