{
  "type": "Feature",
  "properties": {
    "iso:country":"US",
    "sg:address":"3091 SE Jay St",
    "sg:city":"Stuart",
    "sg:classifiers":[
        {
            "category":"Autos & Motor Vehicles",
            "subcategory":"Auto Supplies",
            "type":"Retail Goods"
        }
    ],
    "sg:phone":"+1 772 219 8860",
    "sg:postcode":"34997",
    "sg:province":"FL",
    "wof:name":"Race Car Factory Inc",
    "wof:placetype":"venue"
},
  "geometry": {"coordinates":[-80.211742,27.153957],"type":"Point"}
}