{
  "type": "Feature",
  "properties": {
    "addr:full":"2347 Pinecrest Ct West Palm Beach FL 33415",
    "addr:housenumber":"2347",
    "addr:postcode":"33415",
    "addr:street":"Pinecrest Ct",
    "iso:country":"US",
    "sg:address":"2347 Pinecrest Ct",
    "sg:city":"West Palm Beach",
    "sg:classifiers":[
        {
            "category":"Education",
            "subcategory":"Special Training",
            "type":"Public Place"
        }
    ],
    "sg:phone":"+1 561 968 5291",
    "sg:postcode":"33415",
    "sg:province":"FL",
    "wof:name":"Jim Trasports Services",
    "wof:placetype":"venue"
},
  "geometry": {"coordinates":[-80.123993,26.642436],"type":"Point"}
}