{
  "type": "Feature",
  "properties": {
    "iso:country":"US",
    "sg:address":"42845 Jewell Dr",
    "sg:city":"Deland",
    "sg:classifiers":[
        {
            "category":"Autos & Motor Vehicles",
            "subcategory":"Boat Sales",
            "type":"Retail Goods"
        },
        {
            "category":"Recreation",
            "subcategory":"Marina",
            "type":"Entertainment"
        }
    ],
    "sg:phone":"+1 352 589 0612",
    "sg:postcode":"32720",
    "sg:province":"FL",
    "sg:tags":[
        "mercury",
        "repair",
        "outboard",
        "repairing"
    ],
    "wof:name":"Ranch Marine Inc",
    "wof:placetype":"venue"
},
  "geometry": {"coordinates":[-81.436027,28.971168],"type":"Point"}
}