{
  "type": "Feature",
  "properties": {
    "iso:country":"US",
    "sg:address":"3865 E Gulf To Lake Hwy",
    "sg:city":"Inverness",
    "sg:classifiers":[
        {
            "category":"Home & Garden",
            "subcategory":"Mobile Homes",
            "type":"Retail Goods"
        }
    ],
    "sg:phone":"+1 352 726 1968",
    "sg:postcode":"34453",
    "sg:province":"FL",
    "wof:name":"Inverness Mobile Home Sales",
    "wof:placetype":"venue"
},
  "geometry": {"coordinates":[-82.37035899999999,28.846746],"type":"Point"}
}