{
  "type": "Feature",
  "properties": {
    "iso:country":"US",
    "sg:address":"405 Racetrack Rd NE",
    "sg:city":"Fort Walton Bch",
    "sg:classifiers":[
        {
            "category":"Personal",
            "subcategory":"Tanning Parlor",
            "type":"Services"
        }
    ],
    "sg:phone":"+1 850 863 4786",
    "sg:postcode":"32547",
    "sg:province":"FL",
    "sg:tags":[
        "salon"
    ],
    "wof:name":"Showbiz Tan Fort Walton",
    "wof:placetype":"venue"
},
  "geometry": {"coordinates":[-86.600465,30.442484],"type":"Point"}
}