{
  "type": "Feature",
  "properties": {
    "iso:country":"US",
    "sg:address":"1295 Dog Track Rd",
    "sg:city":"Pensacola",
    "sg:classifiers":[
        {
            "category":"Manufacturing",
            "subcategory":"Signs",
            "type":"Manufacturing & Wholesale Goods"
        }
    ],
    "sg:phone":"+1 850 457 3855",
    "sg:postcode":"32506",
    "sg:province":"FL",
    "wof:name":"Coastal Sign Zone",
    "wof:placetype":"venue"
},
  "geometry": {"coordinates":[-87.36071800000001,30.389278],"type":"Point"}
}