{
  "type": "Feature",
  "properties": {
    "iso:country":"US",
    "sg:address":"15307 SW 179th Ter",
    "sg:city":"Miami",
    "sg:classifiers":[
        {
            "category":"Freight",
            "type":"Transportation"
        }
    ],
    "sg:phone":"+1 305 254 8957",
    "sg:postcode":"33187",
    "sg:province":"FL",
    "sg:tags":[
        "trucking"
    ],
    "wof:name":"Ntr Transport Inc",
    "wof:placetype":"venue"
},
  "geometry": {"coordinates":[-80.440423,25.600014],"type":"Point"}
}