{
  "type": "Feature",
  "properties": {
    "iso:country":"US",
    "sg:address":"9759 NW 80th Ave",
    "sg:city":"Hialeah",
    "sg:classifiers":[
        {
            "category":"Manufacturing",
            "subcategory":"Rubber & Plastics",
            "type":"Manufacturing & Wholesale Goods"
        }
    ],
    "sg:phone":"+1 305 828 8525",
    "sg:postcode":"33016",
    "sg:province":"FL",
    "sg:tags":[
        "high",
        "import",
        "pressure",
        "laminate"
    ],
    "wof:name":"Vladimir Laminates Inc",
    "wof:placetype":"venue"
},
  "geometry": {"coordinates":[-80.327179,25.860152],"type":"Point"}
}