{
  "type": "Feature",
  "properties": {
    "iso:country":"US",
    "sg:address":"725 W Ave A",
    "sg:city":"Jupiter",
    "sg:classifiers":[
        {
            "category":"Utilities",
            "subcategory":"Telephone",
            "type":"Services"
        }
    ],
    "sg:phone":"+1 561 745 2995",
    "sg:postcode":"33430",
    "sg:province":"FL",
    "sg:tags":[
        "telecommunication"
    ],
    "wof:name":"NOSC Telecommunications",
    "wof:placetype":"venue"
},
  "geometry": {"coordinates":[-80.675104,26.685971],"type":"Point"}
}