{
  "type": "Feature",
  "properties": {
    "iso:country":"US",
    "sg:address":"696 Cimarosa Ct",
    "sg:city":"Ocoee",
    "sg:classifiers":[
        {
            "category":"Building & Trades",
            "subcategory":"Construction",
            "type":"Services"
        }
    ],
    "sg:phone":"+1 407 654 9611",
    "sg:postcode":"34761",
    "sg:province":"FL",
    "sg:tags":[
        "general",
        "contractor"
    ],
    "wof:name":"Trans Eastern Construction",
    "wof:placetype":"venue"
},
  "geometry": {"coordinates":[-81.555024,28.60645],"type":"Point"}
}