{
  "type": "Feature",
  "properties": {
    "addr:full":"4530 Prairie Ave Miami Beach FL 33140",
    "addr:housenumber":"4530",
    "addr:postcode":"33140",
    "addr:street":"Prairie Ave",
    "iso:country":"US",
    "sg:address":"4530 Prairie Ave",
    "sg:city":"Miami Beach",
    "sg:classifiers":[
        {
            "category":"Health Services",
            "subcategory":"Clinic",
            "type":"Services"
        }
    ],
    "sg:phone":"+1 305 674 8158",
    "sg:postcode":"33140",
    "sg:province":"FL",
    "sg:tags":[
        "counseling",
        "mental"
    ],
    "wof:name":"Shapiro Roberta Ed Med Lcsw Nbcch",
    "wof:placetype":"venue"
},
  "geometry": {"coordinates":[-80.12960099999999,25.819401],"type":"Point"}
}