{
  "type": "Feature",
  "properties": {
    "addr:full":"403 Greenwood Way Niceville FL 32578",
    "addr:housenumber":"403",
    "addr:postcode":"32578",
    "addr:street":"Greenwood Way",
    "iso:country":"US",
    "sg:address":"403 Greenwood Way",
    "sg:city":"Niceville",
    "sg:classifiers":[
        {
            "category":"Wholesale",
            "subcategory":"Non-durable Goods",
            "type":"Manufacturing & Wholesale Goods"
        }
    ],
    "sg:phone":"+1 850 897 1102",
    "sg:postcode":"32578",
    "sg:province":"FL",
    "sg:tags":[
        "basket"
    ],
    "wof:name":"J & L International Imports Inc",
    "wof:placetype":"venue"
},
  "geometry": {"coordinates":[-86.412903,30.4727],"type":"Point"}
}