{
  "type": "Feature",
  "properties": {
    "addr:full":"1342 Colonial Blvd Fort Myers FL 33907",
    "addr:housenumber":"1342",
    "addr:postcode":"33907",
    "addr:street":"Colonial Blvd",
    "iso:country":"US",
    "sg:address":"1342 Colonial Blvd",
    "sg:city":"Fort Myers",
    "sg:classifiers":[
        {
            "category":"Professional",
            "type":"Services"
        }
    ],
    "sg:phone":"+1 239 790 3297",
    "sg:postcode":"33907",
    "sg:province":"FL",
    "sg:tags":[
        "establishment"
    ],
    "wof:name":"Spider Byte Agency",
    "wof:placetype":"venue"
},
  "geometry": {"coordinates":[-81.890456,26.596435],"type":"Point"}
}