{
  "type": "Feature",
  "properties": {
    "iso:country":"US",
    "sg:address":"3706 Hemlock St",
    "sg:city":"Jacksonville",
    "sg:classifiers":[
        {
            "category":"Wholesale",
            "subcategory":"Machinery & Supplies",
            "type":"Manufacturing & Wholesale Goods"
        }
    ],
    "sg:phone":"+1 904 766 1547",
    "sg:postcode":"32218",
    "sg:province":"FL",
    "sg:tags":[
        "machine",
        "floor"
    ],
    "wof:name":"Mechanical Floor Tech Svc",
    "wof:placetype":"venue"
},
  "geometry": {"coordinates":[-81.712265,30.460496],"type":"Point"}
}