{
  "type": "Feature",
  "properties": {
    "iso:country":"US",
    "sg:address":"12454 NW 7th Ln",
    "sg:city":"Miami",
    "sg:classifiers":[
        {
            "category":"Wholesale",
            "subcategory":"Non-durable Goods",
            "type":"Manufacturing & Wholesale Goods"
        }
    ],
    "sg:phone":"+1 305 552 1047",
    "sg:postcode":"33182",
    "sg:province":"FL",
    "sg:tags":[
        "advertising"
    ],
    "wof:name":"Calvet Advertising",
    "wof:placetype":"venue"
},
  "geometry": {"coordinates":[-80.398054,25.774774],"type":"Point"}
}