{
  "type": "Feature",
  "properties": {
    "addr:full":"8520 SW Hwy 200 Ocala FL 34481",
    "addr:housenumber":"8520",
    "addr:postcode":"34481",
    "addr:street":"Sw Hwy 200",
    "iso:country":"US",
    "sg:address":"8520 SW Hwy 200",
    "sg:city":"Ocala",
    "sg:classifiers":[
        {
            "category":"Health Services",
            "subcategory":"Doctor",
            "type":"Services"
        }
    ],
    "sg:phone":"+1 352 854 0052",
    "sg:postcode":"34481",
    "sg:province":"FL",
    "sg:tags":[
        "medical"
    ],
    "wof:name":"Ocala Eye PA",
    "wof:placetype":"venue"
},
  "geometry": {"coordinates":[-82.240022,29.096227],"type":"Point"}
}