{
  "type": "Feature",
  "properties": {
    "addr:full":"1357 Barrett Rd Fort Myers FL 33903",
    "addr:housenumber":"1357",
    "addr:postcode":"33903",
    "addr:street":"Barrett Rd",
    "iso:country":"US",
    "sg:address":"1357 Barrett Rd",
    "sg:city":"Fort Myers",
    "sg:classifiers":[
        {
            "category":"Retail",
            "subcategory":"Repair Shop",
            "type":"Services"
        }
    ],
    "sg:phone":"+1 239 731 3025",
    "sg:postcode":"33903",
    "sg:province":"FL",
    "sg:tags":[
        "welding"
    ],
    "wof:name":"Denny's Custom Welding",
    "wof:placetype":"venue"
},
  "geometry": {"coordinates":[-81.91220800000001,26.675016],"type":"Point"}
}