{
  "type": "Feature",
  "properties": {
    "addr:full":"4141 SE 180th St Summerfield FL 34491",
    "addr:housenumber":"4141",
    "addr:postcode":"34491",
    "addr:street":"Se 180Th St",
    "iso:country":"US",
    "sg:address":"4141 SE 180th St",
    "sg:city":"Summerfield",
    "sg:classifiers":[
        {
            "category":"Shopping",
            "subcategory":"Hobbies, Toys, & Games",
            "type":"Retail Goods"
        }
    ],
    "sg:phone":"+1 352 330 1974",
    "sg:postcode":"34491",
    "sg:province":"FL",
    "sg:tags":[
        "craft"
    ],
    "wof:name":"Touched By A Brush",
    "wof:placetype":"venue"
},
  "geometry": {"coordinates":[-82.079003,28.960314],"type":"Point"}
}