{
  "type": "Feature",
  "properties": {
    "iso:country":"US",
    "sg:address":"10741 Leader Ln",
    "sg:city":"Orlando",
    "sg:classifiers":[
        {
            "category":"Manufacturing",
            "subcategory":"Printing",
            "type":"Manufacturing & Wholesale Goods"
        }
    ],
    "sg:phone":"+1 407 247 6152",
    "sg:postcode":"32825",
    "sg:province":"FL",
    "sg:tags":[
        "publishing"
    ],
    "wof:name":"Kennedy Publishing",
    "wof:placetype":"venue"
},
  "geometry": {"coordinates":[-81.23620099999999,28.536855],"type":"Point"}
}