{
  "type": "Feature",
  "properties": {
    "addr:full":"4101 E 10th Ln Hialeah FL 33013",
    "addr:housenumber":"4101",
    "addr:postcode":"33013",
    "addr:street":"E 10Th Ln",
    "iso:country":"US",
    "sg:address":"4101 E 10th Ln",
    "sg:city":"Hialeah",
    "sg:classifiers":[
        {
            "category":"Retail",
            "subcategory":"Auto Repair",
            "type":"Services"
        }
    ],
    "sg:phone":"+1 305 681 3040",
    "sg:postcode":"33013",
    "sg:province":"FL",
    "sg:tags":[
        "transmission"
    ],
    "wof:name":"Miami Core & Transmission Part",
    "wof:placetype":"venue"
},
  "geometry": {"coordinates":[-80.26134399999999,25.861967],"type":"Point"}
}