{
  "type": "Feature",
  "properties": {
    "addr:full":"2626 Central Ave St Petersburg FL 33712",
    "addr:housenumber":"2626",
    "addr:postcode":"33712",
    "addr:street":"Central Ave",
    "iso:country":"US",
    "sg:address":"2626 Central Ave",
    "sg:city":"St Petersburg",
    "sg:classifiers":[
        {
            "category":"Building & Trades",
            "subcategory":"Plumbing",
            "type":"Services"
        }
    ],
    "sg:phone":"+1 727 327 4691",
    "sg:postcode":"33712",
    "sg:province":"FL",
    "sg:tags":[
        "conditioning",
        "air",
        "system",
        "contractor"
    ],
    "wof:name":"Acme Air Conditioning Co Inc",
    "wof:placetype":"venue"
},
  "geometry": {"coordinates":[-82.669904,27.770996],"type":"Point"}
}