{
  "type": "Feature",
  "properties": {
    "iso:country":"US",
    "sg:address":"12901 McGregor Blvd. Suite 5",
    "sg:city":"Fort Myers",
    "sg:classifiers":[
        {
            "category":"Food & Beverages",
            "subcategory":"Specialty",
            "type":"Retail Goods"
        },
        {
            "category":"Restaurant",
            "type":"Food & Drink"
        }
    ],
    "sg:phone":"+1 239 337 7979",
    "sg:postcode":"33919",
    "sg:province":"FL",
    "sg:tags":[
        "gluten-free",
        "vegan",
        "pizza"
    ],
    "sg:website":"www.pizzafusion.com",
    "wof:name":"Pizza Fusion",
    "wof:placetype":"venue"
},
  "geometry": {"coordinates":[-81.91143099999999,26.554048],"type":"Point"}
}