{
  "type": "Feature",
  "properties": {
    "addr:full":"340 SW 16th St Dania FL 33004",
    "addr:housenumber":"340",
    "addr:postcode":"33004",
    "addr:street":"Sw 16Th St",
    "iso:country":"US",
    "sg:address":"340 SW 16th St",
    "sg:city":"Dania",
    "sg:classifiers":[
        {
            "category":"Professional",
            "type":"Services"
        }
    ],
    "sg:phone":"+1 954 923 2495",
    "sg:postcode":"33004",
    "sg:province":"FL",
    "sg:tags":[
        "establishment"
    ],
    "wof:name":"Trafalgar Associates",
    "wof:placetype":"venue"
},
  "geometry": {"coordinates":[-80.14955999999999,26.03353],"type":"Point"}
}