{
  "type": "Feature",
  "properties": {
    "iso:country":"US",
    "sg:address":"2413 Hammock Pine Blvd",
    "sg:city":"Clearwater",
    "sg:classifiers":[
        {
            "category":"Manufacturing",
            "subcategory":"Tools & Machinery",
            "type":"Manufacturing & Wholesale Goods"
        }
    ],
    "sg:phone":"+1 727 725 4660",
    "sg:postcode":"33761",
    "sg:province":"FL",
    "sg:tags":[
        "photographic",
        "mfg"
    ],
    "wof:name":"Camera Obscura",
    "wof:placetype":"venue"
},
  "geometry": {"coordinates":[-82.73660599999999,28.028344],"type":"Point"}
}