{
  "type": "Feature",
  "properties": {
    "iso:country":"US",
    "sg:address":"341 SE 2nd St",
    "sg:city":"Belle Glade",
    "sg:classifiers":[
        {
            "category":"Professional",
            "subcategory":"Lawyer & Legal Services",
            "type":"Services"
        }
    ],
    "sg:phone":"+1 561 992 4208",
    "sg:postcode":"33430",
    "sg:province":"FL",
    "sg:tags":[
        "attorney"
    ],
    "wof:name":"Washington Mamie",
    "wof:placetype":"venue"
},
  "geometry": {"coordinates":[-80.665226,26.683661],"type":"Point"}
}