{
  "type": "Feature",
  "properties": {
    "addr:full":"7041 Grand National Dr Orlando FL 32819",
    "addr:housenumber":"7041",
    "addr:postcode":"32819",
    "addr:street":"Grand National Dr",
    "iso:country":"US",
    "sg:address":"7041 Grand National Dr",
    "sg:city":"Orlando",
    "sg:classifiers":[
        {
            "category":"Place Of Worship",
            "type":"Public Place"
        }
    ],
    "sg:phone":"+1 407 363 0511",
    "sg:postcode":"32819",
    "sg:province":"FL",
    "sg:tags":[
        "church"
    ],
    "wof:name":"Crystal Cingular River",
    "wof:placetype":"venue"
},
  "geometry": {"coordinates":[-81.45623000000001,28.459582],"type":"Point"}
}