{
  "type": "Feature",
  "properties": {
    "iso:country":"US",
    "sg:address":"120 International Pkwy Ste 184",
    "sg:city":"Lake Mary",
    "sg:classifiers":[
        {
            "category":"Building & Trades",
            "subcategory":"Construction",
            "type":"Services"
        }
    ],
    "sg:phone":"+1 407 833 3710",
    "sg:postcode":"32746",
    "sg:province":"FL",
    "sg:tags":[
        "interior",
        "design"
    ],
    "wof:name":"Classic Interior Solutions",
    "wof:placetype":"venue"
},
  "geometry": {"coordinates":[-81.36792699999999,28.757674],"type":"Point"}
}