{
  "type": "Feature",
  "properties": {
    "iso:country":"US",
    "sg:address":"8202 Verano St",
    "sg:city":"Navarre",
    "sg:classifiers":[
        {
            "category":"Building & Trades",
            "subcategory":"Landscaping Services",
            "type":"Services"
        }
    ],
    "sg:phone":"+1 850 939 8476",
    "sg:postcode":"32566",
    "sg:province":"FL",
    "sg:tags":[
        "lawn"
    ],
    "wof:name":"A&F Landscaping Inc",
    "wof:placetype":"venue"
},
  "geometry": {"coordinates":[-86.879507,30.422298],"type":"Point"}
}