{
  "type": "Feature",
  "properties": {
    "iso:country":"US",
    "sg:address":"15502 Fiorenza Cir",
    "sg:city":"Delray Beach",
    "sg:classifiers":[
        {
            "category":"Professional",
            "type":"Services"
        }
    ],
    "sg:phone":"+1 561 865 1765",
    "sg:postcode":"33446",
    "sg:province":"FL",
    "sg:tags":[
        "establishment"
    ],
    "wof:name":"Frank & Frank",
    "wof:placetype":"venue"
},
  "geometry": {"coordinates":[-80.156935,26.446749],"type":"Point"}
}