{
  "type": "Feature",
  "properties": {
    "iso:country":"US",
    "sg:address":"4471 Westroads Dr",
    "sg:city":"West Palm Beach",
    "sg:classifiers":[
        {
            "category":"Wholesale",
            "subcategory":"Medical Equipment & Supplies",
            "type":"Manufacturing & Wholesale Goods"
        }
    ],
    "sg:phone":"+1 561 844 2215",
    "sg:postcode":"33407",
    "sg:province":"FL",
    "sg:tags":[
        "physician",
        "surgeon"
    ],
    "wof:name":"Medical Shoppe",
    "wof:placetype":"venue"
},
  "geometry": {"coordinates":[-80.107038,26.773488],"type":"Point"}
}