{
  "type": "Feature",
  "properties": {
    "iso:country":"US",
    "sg:address":"2250 W 9th Ave",
    "sg:city":"Hialeah",
    "sg:classifiers":[
        {
            "category":"Wholesale",
            "subcategory":"Groceries",
            "type":"Manufacturing & Wholesale Goods"
        }
    ],
    "sg:phone":"+1 305 887 9700",
    "sg:postcode":"33010",
    "sg:province":"FL",
    "sg:tags":[
        "grocers-wholesale"
    ],
    "wof:name":"Jomara Wholesale",
    "wof:placetype":"venue"
},
  "geometry": {"coordinates":[-80.30013700000001,25.842109],"type":"Point"}
}