{
  "type": "Feature",
  "properties": {
    "addr:full":"3955 N Quail Ridge Dr Boynton Beach FL 33436",
    "addr:housenumber":"3955",
    "addr:postcode":"33436",
    "addr:street":"N Quail Ridge Dr",
    "iso:country":"US",
    "sg:address":"3955 N Quail Ridge Dr",
    "sg:city":"Boynton Beach",
    "sg:classifiers":[
        {
            "category":"Real Estate",
            "subcategory":"Real Estate Agent",
            "type":"Services"
        }
    ],
    "sg:phone":"+1 561 737 5100",
    "sg:postcode":"33436",
    "sg:province":"FL",
    "wof:name":"Quail Ridge Country Club",
    "wof:placetype":"venue"
},
  "geometry": {"coordinates":[-80.10920900000001,26.512492],"type":"Point"}
}