{
  "type": "Feature",
  "properties": {
    "iso:country":"US",
    "sg:address":"139 12th St",
    "sg:city":"Apalachicola",
    "sg:classifiers":[
        {
            "category":"Government",
            "subcategory":"Office",
            "type":"Public Place"
        }
    ],
    "sg:phone":"+1 850 653 2111",
    "sg:postcode":"32320",
    "sg:province":"FL",
    "sg:tags":[
        "state",
        "agency",
        "health"
    ],
    "wof:name":"Franklin County Health Dept",
    "wof:placetype":"venue"
},
  "geometry": {"coordinates":[-84.99240899999999,29.723329],"type":"Point"}
}