{
  "type": "Feature",
  "properties": {
    "addr:full":"6036 Seminole Blvd Seminole FL 33772",
    "addr:housenumber":"6036",
    "addr:postcode":"33772",
    "addr:street":"Seminole Blvd",
    "iso:country":"US",
    "sg:address":"6036 Seminole Blvd",
    "sg:city":"Seminole",
    "sg:classifiers":[
        {
            "category":"Retail",
            "subcategory":"Repair Shop",
            "type":"Services"
        }
    ],
    "sg:phone":"+1 727 398 4435",
    "sg:postcode":"33772",
    "sg:province":"FL",
    "sg:tags":[
        "scooter",
        "motorcycle",
        "motor"
    ],
    "wof:name":"American Heritage Cycles Inc",
    "wof:placetype":"venue"
},
  "geometry": {"coordinates":[-82.786942,27.827107],"type":"Point"}
}