{
  "type": "Feature",
  "properties": {
    "iso:country":"US",
    "sg:address":"8700 N Kendall Dr Ste 204",
    "sg:city":"Miami",
    "sg:classifiers":[
        {
            "category":"Health Services",
            "subcategory":"Doctor",
            "type":"Services"
        }
    ],
    "sg:phone":"+1 305 412 1420",
    "sg:postcode":"33176",
    "sg:province":"FL",
    "sg:tags":[
        "podiatrist"
    ],
    "wof:name":"Kushner Stephen DPM",
    "wof:placetype":"venue"
},
  "geometry": {"coordinates":[-80.334176,25.687309],"type":"Point"}
}