{
  "type": "Feature",
  "properties": {
    "iso:country":"US",
    "sg:address":"855 NE 365th Ct",
    "sg:city":"Okeechobee",
    "sg:classifiers":[
        {
            "category":"Professional",
            "subcategory":"Accounting & Tax Preparation",
            "type":"Services"
        }
    ],
    "sg:phone":"+1 863 467 4001",
    "sg:postcode":"34972",
    "sg:province":"FL",
    "wof:name":"B J Flemming & Associates",
    "wof:placetype":"venue"
},
  "geometry": {"coordinates":[-80.813457,27.583464],"type":"Point"}
}