{
  "type": "Feature",
  "properties": {
    "iso:country":"US",
    "sg:address":"1710 Tamiami Trl",
    "sg:city":"Port Charlotte",
    "sg:classifiers":[
        {
            "category":"Restaurant",
            "type":"Food & Drink"
        }
    ],
    "sg:phone":"+1 941 255 1221",
    "sg:postcode":"33948",
    "sg:province":"FL",
    "sg:tags":[
        "eating"
    ],
    "wof:name":"Taco Bell",
    "wof:placetype":"venue"
},
  "geometry": {"coordinates":[-82.133638,27.007219],"type":"Point"}
}