{
  "type": "Feature",
  "properties": {
    "iso:country":"US",
    "sg:address":"11967 SW Hamlin Ct",
    "sg:city":"Palm City",
    "sg:classifiers":[
        {
            "category":"Manufacturing",
            "subcategory":"Lumber",
            "type":"Manufacturing & Wholesale Goods"
        }
    ],
    "sg:phone":"+1 772 283 4440",
    "sg:postcode":"34990",
    "sg:province":"FL",
    "sg:tags":[
        "operation",
        "timber",
        "tract"
    ],
    "wof:name":"Five Smooth Stones Inc",
    "wof:placetype":"venue"
},
  "geometry": {"coordinates":[-80.361535,27.048711],"type":"Point"}
}