{
  "type": "Feature",
  "properties": {
    "addr:full":"3014 E Cervantes St Pensacola FL 32503",
    "addr:housenumber":"3014",
    "addr:postcode":"32503",
    "addr:street":"E Cervantes St",
    "iso:country":"US",
    "sg:address":"3014 E Cervantes St",
    "sg:city":"Pensacola",
    "sg:classifiers":[
        {
            "category":"Home & Garden",
            "subcategory":"Building Materials",
            "type":"Retail Goods"
        }
    ],
    "sg:phone":"+1 850 438 1680",
    "sg:postcode":"32503",
    "sg:province":"FL",
    "sg:tags":[
        "windows"
    ],
    "wof:name":"Pella Window & Door Co",
    "wof:placetype":"venue"
},
  "geometry": {"coordinates":[-87.180831,30.425201],"type":"Point"}
}