{
  "type": "Feature",
  "properties": {
    "iso:country":"US",
    "sg:address":"6975 NW 11th St",
    "sg:city":"Pompano Beach",
    "sg:classifiers":[
        {
            "category":"Insurance",
            "subcategory":"Insurance Agent",
            "type":"Services"
        }
    ],
    "sg:phone":"+1 954 973 4314",
    "sg:postcode":"33063",
    "sg:province":"FL",
    "wof:name":"Personal Touch Claim Service",
    "wof:placetype":"venue"
},
  "geometry": {"coordinates":[-80.219336,26.243793],"type":"Point"}
}