{
  "type": "Feature",
  "properties": {
    "iso:country":"US",
    "sg:address":"9835 Antilles Dr",
    "sg:city":"Seminole",
    "sg:classifiers":[
        {
            "category":"Wholesale",
            "subcategory":"Furniture",
            "type":"Manufacturing & Wholesale Goods"
        }
    ],
    "sg:phone":"+1 727 595 2324",
    "sg:postcode":"33776",
    "sg:province":"FL",
    "sg:tags":[
        "furniture-wholesale",
        "manufacturer"
    ],
    "wof:name":"Elite Warehousing",
    "wof:placetype":"venue"
},
  "geometry": {"coordinates":[-82.82820100000001,27.862259],"type":"Point"}
}