{
  "type": "Feature",
  "properties": {
    "iso:country":"US",
    "sg:address":"2469 NW 62nd St",
    "sg:city":"Miami",
    "sg:classifiers":[
        {
            "category":"Restaurant",
            "type":"Food & Drink"
        }
    ],
    "sg:phone":"+1 305 693 0303",
    "sg:postcode":"33147",
    "sg:province":"FL",
    "wof:name":"Arline & Schoolie's Restaurant",
    "wof:placetype":"venue"
},
  "geometry": {"coordinates":[-80.238602,25.8312],"type":"Point"}
}