{
  "type": "Feature",
  "properties": {
    "iso:country":"US",
    "sg:address":"3675 NW 36th St",
    "sg:city":"Miami",
    "sg:classifiers":[
        {
            "category":"Wholesale",
            "subcategory":"Groceries",
            "type":"Manufacturing & Wholesale Goods"
        }
    ],
    "sg:phone":"+1 305 691 7993",
    "sg:postcode":"33142",
    "sg:province":"FL",
    "sg:tags":[
        "food",
        "product"
    ],
    "wof:name":"Criollos Food Distributors",
    "wof:placetype":"venue"
},
  "geometry": {"coordinates":[-80.255548,25.808704],"type":"Point"}
}