{
  "type": "Feature",
  "properties": {
    "addr:full":"900 W 5th St West Palm Beach FL 33404",
    "addr:housenumber":"900",
    "addr:postcode":"33404",
    "addr:street":"W 5Th St",
    "iso:country":"US",
    "sg:address":"900 W 5th St",
    "sg:city":"West Palm Beach",
    "sg:classifiers":[
        {
            "category":"Building & Trades",
            "subcategory":"Equipment Rental",
            "type":"Services"
        }
    ],
    "sg:phone":"+1 561 798 5776",
    "sg:postcode":"33404",
    "sg:province":"FL",
    "sg:tags":[
        "crane"
    ],
    "wof:name":"Beyel Brothers Crane",
    "wof:placetype":"venue"
},
  "geometry": {"coordinates":[-80.06829999999999,26.767222],"type":"Point"}
}