{
  "type": "Feature",
  "properties": {
    "addr:full":"11005 NW 26th Pl Fort Lauderdale FL 33322",
    "addr:housenumber":"11005",
    "addr:postcode":"33322",
    "addr:street":"Nw 26Th Pl",
    "iso:country":"US",
    "sg:address":"11005 NW 26th Pl",
    "sg:city":"Fort Lauderdale",
    "sg:classifiers":[
        {
            "category":"Banks & Credit Unions",
            "subcategory":"Financial Services",
            "type":"Services"
        }
    ],
    "sg:phone":"+1 954 749 7432",
    "sg:postcode":"33322",
    "sg:province":"FL",
    "sg:tags":[
        "investor"
    ],
    "wof:name":"G L R Investments Inc",
    "wof:placetype":"venue"
},
  "geometry": {"coordinates":[-80.29638799999999,26.157744],"type":"Point"}
}