{
  "type": "Feature",
  "properties": {
    "addr:full":"3609 Sun Eagle Ln Bradenton FL 34210",
    "addr:housenumber":"3609",
    "addr:postcode":"34210",
    "addr:street":"Sun Eagle Ln",
    "iso:country":"US",
    "sg:address":"3609 Sun Eagle Ln",
    "sg:city":"Bradenton",
    "sg:classifiers":[
        {
            "category":"Real Estate",
            "subcategory":"Real Estate Agent",
            "type":"Services"
        }
    ],
    "sg:phone":"+1 941 758 0096",
    "sg:postcode":"34210",
    "sg:province":"FL",
    "wof:name":"Arbuckle French & Green Realty",
    "wof:placetype":"venue"
},
  "geometry": {"coordinates":[-82.600791,27.428503],"type":"Point"}
}