{
  "type": "Feature",
  "properties": {
    "iso:country":"US",
    "sg:address":"1019 Shadick Dr",
    "sg:city":"Orange City",
    "sg:classifiers":[
        {
            "category":"Building & Trades",
            "subcategory":"Construction",
            "type":"Services"
        }
    ],
    "sg:phone":"+1 386 774 4155",
    "sg:postcode":"32763",
    "sg:province":"FL",
    "sg:tags":[
        "roofing",
        "contractor"
    ],
    "wof:name":"First Quality Service",
    "wof:placetype":"venue"
},
  "geometry": {"coordinates":[-81.283528,28.938702],"type":"Point"}
}