{
  "type": "Feature",
  "properties": {
    "iso:country":"US",
    "sg:address":"43 San Jose Dr",
    "sg:city":"Ormond Beach",
    "sg:classifiers":[
        {
            "category":"Food & Beverages",
            "subcategory":"Bakery",
            "type":"Retail Goods"
        }
    ],
    "sg:phone":"+1 386 441 0290",
    "sg:postcode":"32176",
    "sg:province":"FL",
    "sg:tags":[
        "bagel"
    ],
    "wof:name":"New York Bagel Deli",
    "wof:placetype":"venue"
},
  "geometry": {"coordinates":[-81.076421,29.35623],"type":"Point"}
}