{
  "type": "Feature",
  "properties": {
    "addr:full":"866 Riverside Dr Ormond Beach FL 32176",
    "addr:housenumber":"866",
    "addr:postcode":"32176",
    "addr:street":"Riverside Dr",
    "iso:country":"US",
    "sg:address":"866 Riverside Dr",
    "sg:city":"Ormond Beach",
    "sg:classifiers":[
        {
            "category":"Insurance",
            "subcategory":"Insurance Agent",
            "type":"Services"
        }
    ],
    "sg:phone":"+1 386 673 0040",
    "sg:postcode":"32176",
    "sg:province":"FL",
    "wof:name":"Reaves Glendale",
    "wof:placetype":"venue"
},
  "geometry": {"coordinates":[-81.03762399999999,29.269225],"type":"Point"}
}