{
  "type": "Feature",
  "properties": {
    "iso:country":"US",
    "sg:address":"5657 Axminster Dr",
    "sg:city":"Sarasota",
    "sg:classifiers":[
        {
            "category":"Professional",
            "subcategory":"Management & Consulting",
            "type":"Services"
        }
    ],
    "sg:phone":"+1 941 923 4719",
    "sg:postcode":"34241",
    "sg:province":"FL",
    "wof:name":"Opticom International Limited",
    "wof:placetype":"venue"
},
  "geometry": {"coordinates":[-82.447575,27.272619],"type":"Point"}
}