{
  "type": "Feature",
  "properties": {
    "iso:country":"US",
    "sg:address":"2684 Cahill Way",
    "sg:city":"Lake Mary",
    "sg:classifiers":[
        {
            "category":"Professional",
            "subcategory":"Management & Consulting",
            "type":"Services"
        }
    ],
    "sg:phone":"+1 407 492 9350",
    "sg:postcode":"32746",
    "sg:province":"FL",
    "sg:tags":[
        "business"
    ],
    "wof:name":"Control Designer Inc",
    "wof:placetype":"venue"
},
  "geometry": {"coordinates":[-81.302442,28.782207],"type":"Point"}
}