{
  "type": "Feature",
  "properties": {
    "iso:country":"US",
    "sg:address":"1326 S Orange Blossom Trl",
    "sg:city":"Apopka",
    "sg:classifiers":[
        {
            "category":"Retail",
            "subcategory":"Animal Services",
            "type":"Services"
        }
    ],
    "sg:phone":"+1 407 886 7004",
    "sg:postcode":"32703",
    "sg:province":"FL",
    "sg:tags":[
        "pet",
        "grooming",
        "washing"
    ],
    "wof:name":"Bow Wow Baren Pet Salon",
    "wof:placetype":"venue"
},
  "geometry": {"coordinates":[-81.476134,28.659024],"type":"Point"}
}