{
  "type": "Feature",
  "properties": {
    "iso:country":"US",
    "sg:address":"175 Fontainebleau Blvd",
    "sg:city":"Miami",
    "sg:classifiers":[
        {
            "category":"Building & Trades",
            "subcategory":"Construction",
            "type":"Services"
        }
    ],
    "sg:phone":"+1 305 551 6913",
    "sg:postcode":"33172",
    "sg:province":"FL",
    "sg:tags":[
        "handyman"
    ],
    "wof:name":"Pros Credit Repair",
    "wof:placetype":"venue"
},
  "geometry": {"coordinates":[-80.33908099999999,25.771252],"type":"Point"}
}