{
  "type": "Feature",
  "properties": {
    "iso:country":"US",
    "sg:address":"3335 E Oakland Park Blvd",
    "sg:city":"Fort Lauderdale",
    "sg:classifiers":[
        {
            "category":"Restaurant",
            "type":"Food & Drink"
        }
    ],
    "sg:phone":"+1 954 564 7755",
    "sg:postcode":"33308",
    "sg:province":"FL",
    "sg:tags":[
        "eating"
    ],
    "wof:name":"Kims Chinese & Mandarin",
    "wof:placetype":"venue"
},
  "geometry": {"coordinates":[-80.101821,26.167639],"type":"Point"}
}