{
  "type": "Feature",
  "properties": {
    "addr:full":"7234 Turner St Tallahassee FL 32311",
    "addr:housenumber":"7234",
    "addr:postcode":"32311",
    "addr:street":"Turner St",
    "iso:country":"US",
    "sg:address":"7234 Turner St",
    "sg:city":"Tallahassee",
    "sg:classifiers":[
        {
            "category":"Building & Trades",
            "subcategory":"Landscaping Services",
            "type":"Services"
        }
    ],
    "sg:phone":"+1 850 309 0758",
    "sg:postcode":"32311",
    "sg:province":"FL",
    "sg:tags":[
        "tree"
    ],
    "wof:name":"Nelson's Tree Svc",
    "wof:placetype":"venue"
},
  "geometry": {"coordinates":[-84.156886,30.417874],"type":"Point"}
}