{
  "type": "Feature",
  "properties": {
    "addr:full":"2041 George Jenkins Blvd Lakeland FL 33815",
    "addr:housenumber":"2041",
    "addr:postcode":"33815",
    "addr:street":"George Jenkins Blvd",
    "iso:country":"US",
    "sg:address":"2041 George Jenkins Blvd",
    "sg:city":"Lakeland",
    "sg:classifiers":[
        {
            "category":"Shopping",
            "subcategory":"Pharmacy",
            "type":"Retail Goods"
        }
    ],
    "sg:phone":"+1 863 686 3131",
    "sg:postcode":"33815",
    "sg:province":"FL",
    "wof:name":"CVS Pharmacy",
    "wof:placetype":"venue"
},
  "geometry": {"coordinates":[-81.989041,28.041711],"type":"Point"}
}