{
  "type": "Feature",
  "properties": {
    "addr:full":"2200 Front St Melbourne FL 32901",
    "addr:housenumber":"2200",
    "addr:postcode":"32901",
    "addr:street":"Front St",
    "iso:country":"US",
    "sg:address":"2200 Front St",
    "sg:city":"Melbourne",
    "sg:classifiers":[
        {
            "category":"Professional",
            "subcategory":"Accounting & Tax Preparation",
            "type":"Services"
        }
    ],
    "sg:phone":"+1 321 984 1230",
    "sg:postcode":"32901",
    "sg:province":"FL",
    "sg:tags":[
        "return",
        "preparation-business"
    ],
    "wof:name":"Jd Tax Service",
    "wof:placetype":"venue"
},
  "geometry": {"coordinates":[-80.60005200000001,28.07823],"type":"Point"}
}