{
  "type": "Feature",
  "properties": {
    "iso:country":"US",
    "sg:address":"2975 Gulf To Bay Blvd",
    "sg:city":"Clearwater",
    "sg:classifiers":[
        {
            "category":"Building & Trades",
            "subcategory":"Plumbing",
            "type":"Services"
        }
    ],
    "sg:phone":"+1 727 443 6318",
    "sg:postcode":"33759",
    "sg:province":"FL",
    "sg:tags":[
        "contractor"
    ],
    "wof:name":"Glen Myers Plumbing",
    "wof:placetype":"venue"
},
  "geometry": {"coordinates":[-82.71336700000001,27.96061],"type":"Point"}
}