{
  "type": "Feature",
  "properties": {
    "iso:country":"US",
    "sg:address":"103 N Alexander St",
    "sg:city":"Plant City",
    "sg:classifiers":[
        {
            "category":"Personal",
            "subcategory":"Beauty Salon",
            "type":"Services"
        }
    ],
    "sg:phone":"+1 813 764 8010",
    "sg:postcode":"33563",
    "sg:province":"FL",
    "wof:name":"Tanglz Family Hair Salon",
    "wof:placetype":"venue"
},
  "geometry": {"coordinates":[-82.138104,28.012969],"type":"Point"}
}