{
  "type": "Feature",
  "properties": {
    "addr:full":"333 S Washington Ave Titusville FL 32796",
    "addr:housenumber":"333",
    "addr:postcode":"32796",
    "addr:street":"S Washington Ave",
    "iso:country":"US",
    "sg:address":"333 S Washington Ave",
    "sg:city":"Titusville",
    "sg:classifiers":[
        {
            "category":"Real Estate",
            "subcategory":"Architect",
            "type":"Services"
        }
    ],
    "sg:phone":"+1 321 264 1366",
    "sg:postcode":"32796",
    "sg:province":"FL",
    "wof:name":"Michael A Penney",
    "wof:placetype":"venue"
},
  "geometry": {"coordinates":[-80.807498,28.611418],"type":"Point"}
}