{
  "type": "Feature",
  "properties": {
    "iso:country":"US",
    "sg:address":"27160 Bay Landing Dr",
    "sg:city":"Bonita Springs",
    "sg:classifiers":[
        {
            "category":"Personal",
            "subcategory":"Beauty Salon",
            "type":"Services"
        }
    ],
    "sg:phone":"+1 239 947 5900",
    "sg:postcode":"34135",
    "sg:province":"FL",
    "sg:tags":[
        "spa",
        "day"
    ],
    "wof:name":"Danielle Spa For Beauty",
    "wof:placetype":"venue"
},
  "geometry": {"coordinates":[-81.806991,26.343477],"type":"Point"}
}