{
  "type": "Feature",
  "properties": {
    "iso:country":"US",
    "sg:address":"51 3rd St",
    "sg:city":"Shalimar",
    "sg:classifiers":[
        {
            "category":"Manufacturing",
            "subcategory":"Tools & Machinery",
            "type":"Manufacturing & Wholesale Goods"
        }
    ],
    "sg:phone":"+1 850 609 0036",
    "sg:postcode":"32579",
    "sg:province":"FL",
    "sg:tags":[
        "industry",
        "aerospace"
    ],
    "wof:name":"Pattison & Assoc",
    "wof:placetype":"venue"
},
  "geometry": {"coordinates":[-86.578153,30.443418],"type":"Point"}
}