{
  "type": "Feature",
  "properties": {
    "iso:country":"US",
    "sg:address":"706 NW 202nd St",
    "sg:city":"Newberry",
    "sg:classifiers":[
        {
            "category":"Recreation",
            "type":"Entertainment"
        }
    ],
    "sg:phone":"+1 352 472 4066",
    "sg:postcode":"32669",
    "sg:province":"FL",
    "sg:tags":[
        "animal",
        "stable"
    ],
    "wof:name":"Dragon's Lair Farm",
    "wof:placetype":"venue"
},
  "geometry": {"coordinates":[-82.55718400000001,29.675023],"type":"Point"}
}