{
  "type": "Feature",
  "properties": {
    "addr:full":"415 W 51st Pl Hialeah FL 33012",
    "addr:housenumber":"415",
    "addr:postcode":"33012",
    "addr:street":"W 51St Pl",
    "iso:country":"US",
    "sg:address":"415 W 51st Pl",
    "sg:city":"Hialeah",
    "sg:classifiers":[
        {
            "category":"Arts & Performance",
            "subcategory":"Arts Center",
            "type":"Entertainment"
        }
    ],
    "sg:phone":"+1 305 557 1142",
    "sg:postcode":"33012",
    "sg:province":"FL",
    "sg:tags":[
        "performing"
    ],
    "wof:name":"Ballet Etudes",
    "wof:placetype":"venue"
},
  "geometry": {"coordinates":[-80.291397,25.869699],"type":"Point"}
}