{
  "type": "Feature",
  "properties": {
    "addr:full":"31 NE 47th St Fort Lauderdale FL 33334",
    "addr:housenumber":"31",
    "addr:postcode":"33334",
    "addr:street":"Ne 47Th St",
    "iso:country":"US",
    "sg:address":"31 NE 47th St",
    "sg:city":"Fort Lauderdale",
    "sg:classifiers":[
        {
            "category":"Real Estate",
            "subcategory":"Real Estate Agent",
            "type":"Services"
        }
    ],
    "sg:phone":"+1 954 491 0075",
    "sg:postcode":"33334",
    "sg:province":"FL",
    "wof:name":"Steady Realty Inc",
    "wof:placetype":"venue"
},
  "geometry": {"coordinates":[-80.14523699999999,26.185121],"type":"Point"}
}