{
  "type": "Feature",
  "properties": {
    "iso:country":"US",
    "sg:address":"8369 Wren Rd",
    "sg:city":"Fort Myers",
    "sg:classifiers":[
        {
            "category":"Wholesale",
            "subcategory":"Hardware",
            "type":"Manufacturing & Wholesale Goods"
        }
    ],
    "sg:phone":"+1 239 340 0784",
    "sg:postcode":"33967",
    "sg:province":"FL",
    "sg:tags":[
        "tool"
    ],
    "wof:name":"Snap-On Tools Co",
    "wof:placetype":"venue"
},
  "geometry": {"coordinates":[-81.808983,26.464891],"type":"Point"}
}