{
  "type": "Feature",
  "properties": {
    "iso:country":"US",
    "sg:address":"12520 SW 88th St",
    "sg:city":"Miami",
    "sg:classifiers":[
        {
            "category":"Travel",
            "subcategory":"Travel Agent",
            "type":"Entertainment"
        }
    ],
    "sg:phone":"+1 305 271 2820",
    "sg:postcode":"33186",
    "sg:province":"FL",
    "sg:tags":[
        "agency",
        "bureau"
    ],
    "wof:name":"Chasquitour Travel",
    "wof:placetype":"venue"
},
  "geometry": {"coordinates":[-80.395899,25.686062],"type":"Point"}
}