{
  "type": "Feature",
  "properties": {
    "iso:country":"US",
    "sg:address":"9628 State Rd 52",
    "sg:city":"Port Richey",
    "sg:classifiers":[
        {
            "category":"Building & Trades",
            "subcategory":"Construction",
            "type":"Services"
        }
    ],
    "sg:phone":"+1 727 857 0599",
    "sg:postcode":"34669",
    "sg:province":"FL",
    "sg:tags":[
        "contractor"
    ],
    "wof:name":"Sun Smart Solution Inc",
    "wof:placetype":"venue"
},
  "geometry": {"coordinates":[-82.653682,28.330363],"type":"Point"}
}