{
  "type": "Feature",
  "properties": {
    "iso:country":"US",
    "sg:address":"8 Redwood Run Loop",
    "sg:city":"Ocala",
    "sg:classifiers":[
        {
            "category":"Building & Trades",
            "subcategory":"Pest Control",
            "type":"Services"
        }
    ],
    "sg:phone":"+1 352 687 0408",
    "sg:postcode":"34472",
    "sg:province":"FL",
    "wof:name":"Direct Pest Management",
    "wof:placetype":"venue"
},
  "geometry": {"coordinates":[-82.029619,29.14789],"type":"Point"}
}