{
  "type": "Feature",
  "properties": {
    "iso:country":"US",
    "sg:address":"660 NE 125th St",
    "sg:city":"Miami",
    "sg:classifiers":[
        {
            "category":"Health Services",
            "subcategory":"Doctor",
            "type":"Services"
        },
        {
            "category":"Social Services",
            "type":"Services"
        }
    ],
    "sg:phone":"+1 305 893 7992",
    "sg:postcode":"33161",
    "sg:province":"FL",
    "sg:tags":[
        "info",
        "medical",
        "program",
        "referral"
    ],
    "wof:name":"Alert",
    "wof:placetype":"venue"
},
  "geometry": {"coordinates":[-80.18463800000001,25.890288],"type":"Point"}
}