{
  "type": "Feature",
  "properties": {
    "iso:country":"US",
    "sg:address":"1921 NW 141st St",
    "sg:city":"Opa Locka",
    "sg:classifiers":[
        {
            "category":"Building & Trades",
            "subcategory":"Construction",
            "type":"Services"
        }
    ],
    "sg:phone":"+1 305 681 2337",
    "sg:postcode":"33054",
    "sg:province":"FL",
    "sg:tags":[
        "concrete",
        "contractor"
    ],
    "wof:name":"Central Concrete Supermix Inc",
    "wof:placetype":"venue"
},
  "geometry": {"coordinates":[-80.23232899999999,25.903084],"type":"Point"}
}