{
  "type": "Feature",
  "properties": {
    "iso:country":"US",
    "sg:address":"3890 N Ronald Reagan Blvd",
    "sg:city":"Longwood",
    "sg:classifiers":[
        {
            "category":"Retail",
            "subcategory":"Auto Repair",
            "type":"Services"
        }
    ],
    "sg:phone":"+1 407 322 9858",
    "sg:postcode":"32750",
    "sg:province":"FL",
    "sg:tags":[
        "automotive",
        "lube",
        "oil"
    ],
    "wof:name":"Jiffy Lube",
    "wof:placetype":"venue"
},
  "geometry": {"coordinates":[-81.30892900000001,28.73165],"type":"Point"}
}