{
  "type": "Feature",
  "properties": {
    "iso:country":"US",
    "sg:address":"2828 Euston Rd",
    "sg:city":"Winter Park",
    "sg:classifiers":[
        {
            "category":"Professional",
            "subcategory":"Detective & Security Services",
            "type":"Services"
        }
    ],
    "sg:phone":"+1 407 814 1004",
    "sg:postcode":"32789",
    "sg:province":"FL",
    "sg:tags":[
        "guard",
        "patrol"
    ],
    "wof:name":"Allegiance Security & Patrol",
    "wof:placetype":"venue"
},
  "geometry": {"coordinates":[-81.387427,28.598704],"type":"Point"}
}