{
  "type": "Feature",
  "properties": {
    "iso:country":"US",
    "sg:address":"923 W Dixie Ave",
    "sg:city":"Leesburg",
    "sg:classifiers":[
        {
            "category":"Travel",
            "subcategory":"Travel Agent",
            "type":"Entertainment"
        }
    ],
    "sg:phone":"+1 352 326 9433",
    "sg:postcode":"34748",
    "sg:province":"FL",
    "sg:tags":[
        "agency",
        "bureau"
    ],
    "wof:name":"Atlantis Travel Agency Inc",
    "wof:placetype":"venue"
},
  "geometry": {"coordinates":[-81.879638,28.806399],"type":"Point"}
}