{
  "type": "Feature",
  "properties": {
    "iso:country":"US",
    "sg:address":"11141 Essex Ridge Ct",
    "sg:city":"Orlando",
    "sg:classifiers":[
        {
            "category":"Building & Trades",
            "subcategory":"Equipment Rental",
            "type":"Services"
        }
    ],
    "sg:phone":"+1 407 855 5851",
    "sg:postcode":"32837",
    "sg:province":"FL",
    "wof:name":"Kenneth D Lafrance Rental Main",
    "wof:placetype":"venue"
},
  "geometry": {"coordinates":[-81.414631,28.407382],"type":"Point"}
}