{
  "type": "Feature",
  "properties": {
    "addr:full":"20383 144th St Live Oak FL 32060",
    "addr:housenumber":"20383",
    "addr:postcode":"32060",
    "addr:street":"144Th St",
    "iso:country":"US",
    "sg:address":"20383 144th St",
    "sg:city":"Live Oak",
    "sg:classifiers":[
        {
            "category":"Organizations",
            "subcategory":"Religious Organization",
            "type":"Services"
        }
    ],
    "sg:phone":"+1 386 776 2799",
    "sg:postcode":"32060",
    "sg:province":"FL",
    "sg:tags":[
        "church"
    ],
    "wof:name":"Beulah Baptist Church",
    "wof:placetype":"venue"
},
  "geometry": {"coordinates":[-83.18120999999999,30.18781],"type":"Point"}
}