{
  "type": "Feature",
  "properties": {
    "iso:country":"US",
    "sg:address":"5100 W Hwy 98",
    "sg:city":"Panama City",
    "sg:classifiers":[
        {
            "category":"Food & Beverages",
            "subcategory":"Groceries & Convenience Stores",
            "type":"Retail Goods"
        }
    ],
    "sg:phone":"+1 850 784 0599",
    "sg:postcode":"32401",
    "sg:province":"FL",
    "wof:name":"Pop In 3",
    "wof:placetype":"venue"
},
  "geometry": {"coordinates":[-85.726333,30.183055],"type":"Point"}
}