{
  "type": "Feature",
  "properties": {
    "iso:country":"US",
    "sg:address":"3601 Regent Blvd",
    "sg:city":"Jacksonville",
    "sg:classifiers":[
        {
            "category":"Professional",
            "subcategory":"Advertising",
            "type":"Services"
        },
        {
            "category":"Wholesale",
            "subcategory":"Non-durable Goods",
            "type":"Manufacturing & Wholesale Goods"
        }
    ],
    "sg:phone":"+1 904 641 3936",
    "sg:postcode":"32224",
    "sg:province":"FL",
    "sg:tags":[
        "distribution"
    ],
    "wof:name":"Triple P Distributing Co Inc",
    "wof:placetype":"venue"
},
  "geometry": {"coordinates":[-81.506745,30.27779],"type":"Point"}
}