{
  "type": "Feature",
  "properties": {
    "iso:country":"US",
    "sg:address":"1561 SW 68th Ave",
    "sg:city":"Fort Lauderdale",
    "sg:classifiers":[
        {
            "category":"Shopping",
            "subcategory":"Stationery & Office Supplies",
            "type":"Retail Goods"
        },
        {
            "category":"Wholesale",
            "subcategory":"Non-durable Goods",
            "type":"Manufacturing & Wholesale Goods"
        }
    ],
    "sg:phone":"+1 954 792 8226",
    "sg:postcode":"33317",
    "sg:province":"FL",
    "sg:tags":[
        "system",
        "sales",
        "agent",
        "broker",
        "equipment",
        "filing"
    ],
    "wof:name":"Advanced Filing Systems Inc",
    "wof:placetype":"venue"
},
  "geometry": {"coordinates":[-80.2392,26.103351],"type":"Point"}
}