{
  "type": "Feature",
  "properties": {
    "iso:country":"US",
    "sg:address":"39 River Beach Dr",
    "sg:city":"Ormond Beach",
    "sg:classifiers":[
        {
            "category":"Real Estate",
            "subcategory":"Real Estate Agent",
            "type":"Services"
        }
    ],
    "sg:phone":"+1 386 672 4560",
    "sg:postcode":"32176",
    "sg:province":"FL",
    "wof:name":"Anderson & Perkins LLC",
    "wof:placetype":"venue"
},
  "geometry": {"coordinates":[-81.03929599999999,29.276299],"type":"Point"}
}