{
  "type": "Feature",
  "properties": {
    "addr:full":"3431 Trout River Blvd Jacksonville FL 32208",
    "addr:housenumber":"3431",
    "addr:postcode":"32208",
    "addr:street":"Trout River Blvd",
    "iso:country":"US",
    "sg:address":"3431 Trout River Blvd",
    "sg:city":"Jacksonville",
    "sg:classifiers":[
        {
            "category":"Home & Garden",
            "subcategory":"Building Materials",
            "type":"Retail Goods"
        }
    ],
    "sg:phone":"+1 904 768 7430",
    "sg:postcode":"32208",
    "sg:province":"FL",
    "sg:tags":[
        "windows"
    ],
    "wof:name":"Grande Openings Inc",
    "wof:placetype":"venue"
},
  "geometry": {"coordinates":[-81.702754,30.415617],"type":"Point"}
}