{
  "type": "Feature",
  "properties": {
    "iso:country":"US",
    "sg:address":"10911 Tumbleweed Dr",
    "sg:city":"Dade City",
    "sg:classifiers":[
        {
            "category":"Building & Trades",
            "subcategory":"Cleaning & Sanitation",
            "type":"Services"
        }
    ],
    "sg:phone":"+1 352 567 1949",
    "sg:postcode":"33525",
    "sg:province":"FL",
    "sg:tags":[
        "janitor"
    ],
    "wof:name":"Pat Denton's Cleaning Svc",
    "wof:placetype":"venue"
},
  "geometry": {"coordinates":[-82.176143,28.31639],"type":"Point"}
}