{
  "type": "Feature",
  "properties": {
    "iso:country":"US",
    "sg:address":"1202 E 3rd St",
    "sg:city":"Panama City",
    "sg:classifiers":[
        {
            "category":"Shopping",
            "subcategory":"Gifts & Souvenirs",
            "type":"Retail Goods"
        }
    ],
    "sg:phone":"+1 850 784 0887",
    "sg:postcode":"32401",
    "sg:province":"FL",
    "sg:tags":[
        "balloon"
    ],
    "wof:name":"Annas Balloons & Entrmt",
    "wof:placetype":"venue"
},
  "geometry": {"coordinates":[-85.642923,30.150961],"type":"Point"}
}