{
  "type": "Feature",
  "properties": {
    "addr:full":"2831 57th Dr E Bradenton FL 34203",
    "addr:housenumber":"2831",
    "addr:postcode":"34203",
    "addr:street":"57Th Dr E",
    "iso:country":"US",
    "sg:address":"2831 57th Dr E",
    "sg:city":"Bradenton",
    "sg:classifiers":[
        {
            "category":"Professional",
            "subcategory":"Management & Consulting",
            "type":"Services"
        }
    ],
    "sg:phone":"+1 941 962 3420",
    "sg:postcode":"34203",
    "sg:province":"FL",
    "sg:tags":[
        "consultant"
    ],
    "wof:name":"Karen Vail",
    "wof:placetype":"venue"
},
  "geometry": {"coordinates":[-82.529236,27.439403],"type":"Point"}
}