{
  "type": "Feature",
  "properties": {
    "addr:full":"16105 SW Archer Rd Archer FL 32618",
    "addr:housenumber":"16105",
    "addr:postcode":"32618",
    "addr:street":"Sw Archer Rd",
    "iso:country":"US",
    "sg:address":"16105 SW Archer Rd",
    "sg:city":"Archer",
    "sg:classifiers":[
        {
            "category":"Retail",
            "subcategory":"Veterinary Services",
            "type":"Services"
        }
    ],
    "sg:phone":"+1 352 373 6172",
    "sg:postcode":"32618",
    "sg:province":"FL",
    "sg:tags":[
        "veterinarian"
    ],
    "wof:name":"Kimberly H De Vries DVM",
    "wof:placetype":"venue"
},
  "geometry": {"coordinates":[-82.517088,29.538285],"type":"Point"}
}