{
  "type": "Feature",
  "properties": {
    "addr:full":"1905 Wyoming Ave Fort Pierce FL 34982",
    "addr:housenumber":"1905",
    "addr:postcode":"34982",
    "addr:street":"Wyoming Ave",
    "iso:country":"US",
    "sg:address":"1905 Wyoming Ave",
    "sg:city":"Fort Pierce",
    "sg:classifiers":[
        {
            "category":"Real Estate",
            "subcategory":"Real Estate Operator",
            "type":"Services"
        }
    ],
    "sg:phone":"+1 772 464 3974",
    "sg:postcode":"34982",
    "sg:province":"FL",
    "sg:tags":[
        "building",
        "nonresidential"
    ],
    "wof:name":"Sunrise Tractor and Equipment",
    "wof:placetype":"venue"
},
  "geometry": {"coordinates":[-80.3436,27.42492],"type":"Point"}
}