{
  "type": "Feature",
  "properties": {
    "addr:full":"1800 SE Village Green Dr Port St Lucie FL 34952",
    "addr:housenumber":"1800",
    "addr:postcode":"34952",
    "addr:street":"Se Village Green Dr",
    "iso:country":"US",
    "sg:address":"1800 SE Village Green Dr",
    "sg:city":"Port St Lucie",
    "sg:classifiers":[
        {
            "category":"Organizations",
            "subcategory":"Religious Organization",
            "type":"Services"
        }
    ],
    "sg:phone":"+1 772 337 9766",
    "sg:postcode":"34952",
    "sg:province":"FL",
    "sg:tags":[
        "church"
    ],
    "wof:name":"Grace Church",
    "wof:placetype":"venue"
},
  "geometry": {"coordinates":[-80.296542,27.298692],"type":"Point"}
}