{
  "type": "Feature",
  "properties": {
    "iso:country":"US",
    "sg:address":"13917 SW 66th St",
    "sg:city":"Miami",
    "sg:classifiers":[
        {
            "category":"Personal",
            "subcategory":"Beauty Salon",
            "type":"Services"
        }
    ],
    "sg:phone":"+1 305 387 3763",
    "sg:postcode":"33183",
    "sg:province":"FL",
    "wof:name":"Images Hair Designers",
    "wof:placetype":"venue"
},
  "geometry": {"coordinates":[-80.42012099999999,25.705918],"type":"Point"}
}