{
  "type": "Feature",
  "properties": {
    "iso:country":"US",
    "sg:address":"33 NE 4th St",
    "sg:city":"Miami",
    "sg:classifiers":[
        {
            "category":"Professional",
            "subcategory":"Advertising",
            "type":"Services"
        }
    ],
    "sg:phone":"+1 305 577 9937",
    "sg:postcode":"33132",
    "sg:province":"FL",
    "sg:tags":[
        "agency",
        "specialty"
    ],
    "wof:name":"At&Tsolutionsjut.net",
    "wof:placetype":"venue"
},
  "geometry": {"coordinates":[-80.193208,25.778016],"type":"Point"}
}