{
  "type": "Feature",
  "properties": {
    "addr:full":"1411 NW 24th Ter Fort Lauderdale FL 33311",
    "addr:housenumber":"1411",
    "addr:postcode":"33311",
    "addr:street":"Nw 24Th Ter",
    "iso:country":"US",
    "sg:address":"1411 NW 24th Ter",
    "sg:city":"Fort Lauderdale",
    "sg:classifiers":[
        {
            "category":"Social Services",
            "subcategory":"Child Care",
            "type":"Services"
        }
    ],
    "sg:phone":"+1 954 485 6531",
    "sg:postcode":"33311",
    "sg:province":"FL",
    "sg:tags":[
        "day"
    ],
    "wof:name":"Sandy's Home Day Care",
    "wof:placetype":"venue"
},
  "geometry": {"coordinates":[-80.17496800000001,26.143572],"type":"Point"}
}