{
  "type": "Feature",
  "properties": {
    "iso:country":"US",
    "sg:address":"1170 Pebble Ridge Dr",
    "sg:city":"Jacksonville",
    "sg:classifiers":[
        {
            "category":"Building & Trades",
            "subcategory":"Landscaping Services",
            "type":"Services"
        }
    ],
    "sg:phone":"+1 904 781 8122",
    "sg:postcode":"32220",
    "sg:province":"FL",
    "wof:name":"R&K Lawn Service",
    "wof:placetype":"venue"
},
  "geometry": {"coordinates":[-81.828357,30.331212],"type":"Point"}
}