{
  "type": "Feature",
  "properties": {
    "addr:full":"4400 N Alafaya Trl Orlando FL 32826",
    "addr:housenumber":"4400",
    "addr:postcode":"32826",
    "addr:street":"N Alafaya Trl",
    "iso:country":"US",
    "sg:address":"4400 N Alafaya Trl",
    "sg:city":"Orlando",
    "sg:classifiers":[
        {
            "category":"Retail",
            "subcategory":"Auto Repair",
            "type":"Services"
        }
    ],
    "sg:phone":"+1 866 866 4775",
    "sg:postcode":"32826",
    "sg:province":"FL",
    "sg:tags":[
        "engine",
        "rebuilding"
    ],
    "wof:name":"Continental Automotive",
    "wof:placetype":"venue"
},
  "geometry": {"coordinates":[-81.20777099999999,28.602369],"type":"Point"}
}