{
  "type": "Feature",
  "properties": {
    "addr:full":"514 Gulf Blvd Indian Rocks Bch FL 33785",
    "addr:housenumber":"514",
    "addr:postcode":"33785",
    "addr:street":"Gulf Blvd Indian Rocks",
    "iso:country":"US",
    "sg:address":"514 Gulf Blvd",
    "sg:city":"Indian Rocks Bch",
    "sg:classifiers":[
        {
            "category":"Travel",
            "subcategory":"Hotels & Motels",
            "type":"Entertainment"
        },
        {
            "category":"Real Estate",
            "subcategory":"Real Estate Operator",
            "type":"Services"
        }
    ],
    "sg:phone":"+1 727 596 2794",
    "sg:postcode":"33785",
    "sg:province":"FL",
    "sg:tags":[
        "operation",
        "condominium"
    ],
    "wof:name":"Cay Pointe Villa",
    "wof:placetype":"venue"
},
  "geometry": {"coordinates":[-82.850594,27.88427],"type":"Point"}
}