{
  "type": "Feature",
  "properties": {
    "addr:full":"9759 Piney Point Cir Orlando FL 32825",
    "addr:housenumber":"9759",
    "addr:postcode":"32825",
    "addr:street":"Piney Point Cir",
    "iso:country":"US",
    "sg:address":"9759 Piney Point Cir",
    "sg:city":"Orlando",
    "sg:classifiers":[
        {
            "category":"Professional",
            "subcategory":"Business Services",
            "type":"Services"
        }
    ],
    "sg:phone":"+1 407 384 0932",
    "sg:postcode":"32825",
    "sg:province":"FL",
    "wof:name":"Collins Johnell D",
    "wof:placetype":"venue"
},
  "geometry": {"coordinates":[-81.245575,28.557675],"type":"Point"}
}