{
  "type": "Feature",
  "properties": {
    "iso:country":"US",
    "sg:address":"2240 Proctor Rd",
    "sg:city":"Sarasota",
    "sg:classifiers":[
        {
            "category":"Social Services",
            "subcategory":"Child Care",
            "type":"Services"
        }
    ],
    "sg:phone":"+1 941 922 5449",
    "sg:postcode":"34231",
    "sg:province":"FL",
    "wof:name":"TLC Child Care Ctr",
    "wof:placetype":"venue"
},
  "geometry": {"coordinates":[-82.53012699999999,27.284599],"type":"Point"}
}