{
  "type": "Feature",
  "properties": {
    "addr:full":"1801 7th St SW Winter Haven FL 33880",
    "addr:housenumber":"1801",
    "addr:postcode":"33880",
    "addr:street":"7Th St Sw",
    "iso:country":"US",
    "sg:address":"1801 7th St SW",
    "sg:city":"Winter Haven",
    "sg:classifiers":[
        {
            "category":"Home & Garden",
            "subcategory":"Building Materials",
            "type":"Retail Goods"
        }
    ],
    "sg:phone":"+1 863 294 0611",
    "sg:postcode":"33880",
    "sg:province":"FL",
    "sg:tags":[
        "lumber",
        "including",
        "t",
        "supply"
    ],
    "wof:name":"Adams Building Materials Inc",
    "wof:placetype":"venue"
},
  "geometry": {"coordinates":[-81.735044,28.002912],"type":"Point"}
}