{
  "type": "Feature",
  "properties": {
    "addr:full":"6513 14th St W Bradenton FL 34207",
    "addr:housenumber":"6513",
    "addr:postcode":"34207",
    "addr:street":"14Th St W",
    "iso:country":"US",
    "sg:address":"6513 14th St W",
    "sg:city":"Bradenton",
    "sg:classifiers":[
        {
            "category":"Professional",
            "subcategory":"Management & Consulting",
            "type":"Services"
        }
    ],
    "sg:phone":"+1 941 753 0034",
    "sg:postcode":"34207",
    "sg:province":"FL",
    "sg:tags":[
        "personnel",
        "consultant"
    ],
    "wof:name":"Express Personnel Svc",
    "wof:placetype":"venue"
},
  "geometry": {"coordinates":[-82.57541999999999,27.425642],"type":"Point"}
}