{
  "type": "Feature",
  "properties": {
    "iso:country":"US",
    "sg:address":"15 SW 10th St",
    "sg:city":"Fort Lauderdale",
    "sg:classifiers":[
        {
            "category":"Professional",
            "subcategory":"Lawyer & Legal Services",
            "type":"Services"
        }
    ],
    "sg:phone":"+1 954 523 5994",
    "sg:postcode":"33315",
    "sg:province":"FL",
    "wof:name":"Mark Skipper PA",
    "wof:placetype":"venue"
},
  "geometry": {"coordinates":[-80.143153,26.110385],"type":"Point"}
}