{
  "type": "Feature",
  "properties": {
    "iso:country":"US",
    "sg:address":"600 NW 79th Ave",
    "sg:city":"Miami",
    "sg:classifiers":[
        {
            "category":"Utilities",
            "subcategory":"Telephone",
            "type":"Services"
        }
    ],
    "sg:phone":"+1 305 260 8192",
    "sg:postcode":"33126",
    "sg:province":"FL",
    "sg:tags":[
        "communications"
    ],
    "wof:name":"Bellsouth",
    "wof:placetype":"venue"
},
  "geometry": {"coordinates":[-80.32435,25.773105],"type":"Point"}
}