{
  "type": "Feature",
  "properties": {
    "iso:country":"US",
    "sg:address":"1020 N Pine Hills Rd",
    "sg:city":"Orlando",
    "sg:classifiers":[
        {
            "category":"Insurance",
            "subcategory":"Insurance Agent",
            "type":"Services"
        }
    ],
    "sg:phone":"+1 407 290 8997",
    "sg:postcode":"32808",
    "sg:province":"FL",
    "sg:tags":[
        "preparation",
        "tax",
        "return"
    ],
    "wof:name":"Express Insurance and Tax",
    "wof:placetype":"venue"
},
  "geometry": {"coordinates":[-81.44982299999999,28.56103],"type":"Point"}
}