{
  "type": "Feature",
  "properties": {
    "addr:full":"6905 NW 77th Ave Miami FL 33166",
    "addr:housenumber":"6905",
    "addr:postcode":"33166",
    "addr:street":"Nw 77Th Ave",
    "iso:country":"US",
    "sg:address":"6905 NW 77th Ave",
    "sg:city":"Miami",
    "sg:classifiers":[
        {
            "category":"Social Services",
            "subcategory":"Job Training",
            "type":"Services"
        }
    ],
    "sg:phone":"+1 305 430 8777",
    "sg:postcode":"33166",
    "sg:province":"FL",
    "sg:tags":[
        "rehabilitation"
    ],
    "wof:name":"Florida Plus Medical Ctr",
    "wof:placetype":"venue"
},
  "geometry": {"coordinates":[-80.32158200000001,25.836156],"type":"Point"}
}