{
  "type": "Feature",
  "properties": {
    "addr:full":"105 Corporation Way Venice FL 34285",
    "addr:housenumber":"105",
    "addr:postcode":"34285",
    "addr:street":"Corporation Way",
    "iso:country":"US",
    "sg:address":"105 Corporation Way",
    "sg:city":"Venice",
    "sg:classifiers":[
        {
            "category":"Professional",
            "subcategory":"Business Services",
            "type":"Services"
        }
    ],
    "sg:phone":"+1 941 488 3900",
    "sg:postcode":"34285",
    "sg:province":"FL",
    "sg:tags":[
        "holding"
    ],
    "wof:name":"Preston Bozworth Holdings Inc",
    "wof:placetype":"venue"
},
  "geometry": {"coordinates":[-82.424896,27.084379],"type":"Point"}
}