{
  "type": "Feature",
  "properties": {
    "addr:full":"1018 Antelope Trl Winter Springs FL 32708",
    "addr:housenumber":"1018",
    "addr:postcode":"32708",
    "addr:street":"Antelope Trl",
    "iso:country":"US",
    "sg:address":"1018 Antelope Trl",
    "sg:city":"Winter Springs",
    "sg:classifiers":[
        {
            "category":"Wholesale",
            "subcategory":"Machinery & Supplies",
            "type":"Manufacturing & Wholesale Goods"
        }
    ],
    "sg:phone":"+1 407 696 4826",
    "sg:postcode":"32708",
    "sg:province":"FL",
    "sg:tags":[
        "equipment",
        "establishment"
    ],
    "wof:name":"Cns Interprizes",
    "wof:placetype":"venue"
},
  "geometry": {"coordinates":[-81.265387,28.671622],"type":"Point"}
}