{
  "type": "Feature",
  "properties": {
    "iso:country":"US",
    "sg:address":"3882 SW 112th Ave",
    "sg:city":"Miami",
    "sg:classifiers":[
        {
            "category":"Education",
            "subcategory":"Library",
            "type":"Public Place"
        }
    ],
    "sg:phone":"+1 305 207 1344",
    "sg:postcode":"33165",
    "sg:province":"FL",
    "sg:website":"http://www.miamidade.gov",
    "wof:name":"Concord Library",
    "wof:placetype":"venue"
},
  "geometry": {"coordinates":[-80.37572299999999,25.733258],"type":"Point"}
}