{
  "type": "Feature",
  "properties": {
    "iso:country":"US",
    "sg:address":"111 S Knowles Ave",
    "sg:city":"Winter Park",
    "sg:classifiers":[
        {
            "category":"Building & Trades",
            "subcategory":"Locksmith",
            "type":"Services"
        }
    ],
    "sg:phone":"+1 877 551 8506",
    "sg:postcode":"32789",
    "sg:province":"FL",
    "sg:tags":[
        "key"
    ],
    "wof:name":"24 Emergency Locksmith",
    "wof:placetype":"venue"
},
  "geometry": {"coordinates":[-81.349963,28.597609],"type":"Point"}
}