{
  "type": "Feature",
  "properties": {
    "iso:country":"US",
    "sg:address":"1410 Ardsley Rd",
    "sg:city":"Jacksonville",
    "sg:classifiers":[
        {
            "category":"Real Estate",
            "subcategory":"Real Estate Operator",
            "type":"Services"
        }
    ],
    "sg:phone":"+1 904 730 8786",
    "sg:postcode":"32207",
    "sg:province":"FL",
    "sg:tags":[
        "building",
        "nonresidential"
    ],
    "wof:name":"Kemp Properties",
    "wof:placetype":"venue"
},
  "geometry": {"coordinates":[-81.64952599999999,30.272893],"type":"Point"}
}