{
  "type": "Feature",
  "properties": {
    "iso:country":"US",
    "sg:address":"5420 Jaeger Rd",
    "sg:city":"Naples",
    "sg:classifiers":[
        {
            "category":"Professional",
            "subcategory":"Business Services",
            "type":"Services"
        }
    ],
    "sg:phone":"+1 239 591 2060",
    "sg:postcode":"34109",
    "sg:province":"FL",
    "sg:tags":[
        "interior",
        "design"
    ],
    "wof:name":"Courchene Holding Group LLC",
    "wof:placetype":"venue"
},
  "geometry": {"coordinates":[-81.78496199999999,26.213436],"type":"Point"}
}