{
  "type": "Feature",
  "properties": {
    "addr:full":"920 Henscratch Rd Lake Placid FL 33852",
    "addr:housenumber":"920",
    "addr:postcode":"33852",
    "addr:street":"Henscratch Rd",
    "iso:country":"US",
    "sg:address":"920 Henscratch Rd",
    "sg:city":"Lake Placid",
    "sg:classifiers":[
        {
            "category":"Home & Garden",
            "subcategory":"Garden Supply",
            "type":"Retail Goods"
        }
    ],
    "sg:phone":"+1 863 465 7621",
    "sg:postcode":"33852",
    "sg:province":"FL",
    "sg:tags":[
        "nurseryman"
    ],
    "wof:name":"Ordehi Nursery",
    "wof:placetype":"venue"
},
  "geometry": {"coordinates":[-81.465902,27.364184],"type":"Point"}
}