{
  "type": "Feature",
  "properties": {
    "addr:full":"1556 6th St SE Winter Haven FL 33880",
    "addr:housenumber":"1556",
    "addr:postcode":"33880",
    "addr:street":"6Th St Se",
    "iso:country":"US",
    "sg:address":"1556 6th St SE",
    "sg:city":"Winter Haven",
    "sg:classifiers":[
        {
            "category":"Professional",
            "subcategory":"Lawyer & Legal Services",
            "type":"Services"
        }
    ],
    "sg:phone":"+1 863 293 3801",
    "sg:postcode":"33880",
    "sg:province":"FL",
    "sg:tags":[
        "attorney"
    ],
    "wof:name":"Floyd & Sammons",
    "wof:placetype":"venue"
},
  "geometry": {"coordinates":[-81.718468,28.005927],"type":"Point"}
}