{
  "type": "Feature",
  "properties": {
    "iso:country":"US",
    "sg:address":"5725 Corporate Way",
    "sg:city":"West Palm Beach",
    "sg:classifiers":[
        {
            "category":"Professional",
            "subcategory":"Advertising",
            "type":"Services"
        }
    ],
    "sg:phone":"+1 561 688 8155",
    "sg:postcode":"33407",
    "sg:province":"FL",
    "sg:tags":[
        "counselor"
    ],
    "sg:website":"www.liggiolaw.com",
    "wof:name":"Strategic Marketing Inc",
    "wof:placetype":"venue"
},
  "geometry": {"coordinates":[-80.08924,26.760588],"type":"Point"}
}