{
  "type": "Feature",
  "properties": {
    "addr:full":"6025 Roberts Rd Tallahassee FL 32309",
    "addr:housenumber":"6025",
    "addr:postcode":"32309",
    "addr:street":"Roberts Rd",
    "iso:country":"US",
    "sg:address":"6025 Roberts Rd",
    "sg:city":"Tallahassee",
    "sg:classifiers":[
        {
            "category":"Professional",
            "type":"Services"
        }
    ],
    "sg:phone":"+1 850 893 9804",
    "sg:postcode":"32309",
    "sg:province":"FL",
    "sg:tags":[
        "establishment"
    ],
    "wof:name":"Crown Castle Towers",
    "wof:placetype":"venue"
},
  "geometry": {"coordinates":[-84.17272699999999,30.536181],"type":"Point"}
}