{
  "type": "Feature",
  "properties": {
    "addr:full":"107 W Plant St Winter Garden FL 34787",
    "addr:housenumber":"107",
    "addr:postcode":"34787",
    "addr:street":"W Plant St",
    "iso:country":"US",
    "sg:address":"107 W Plant St",
    "sg:city":"Winter Garden",
    "sg:classifiers":[
        {
            "category":"Manufacturing",
            "subcategory":"Printing",
            "type":"Manufacturing & Wholesale Goods"
        }
    ],
    "sg:phone":"+1 407 656 4719",
    "sg:postcode":"34787",
    "sg:province":"FL",
    "sg:tags":[
        "lithographic",
        "commercial"
    ],
    "wof:name":"Hill Printing",
    "wof:placetype":"venue"
},
  "geometry": {"coordinates":[-81.58770199999999,28.565364],"type":"Point"}
}