{
  "type": "Feature",
  "properties": {
    "iso:country":"US",
    "sg:address":"1000 W Main St",
    "sg:city":"Avon Park",
    "sg:classifiers":[
        {
            "category":"Shopping",
            "subcategory":"Stationery & Office Supplies",
            "type":"Retail Goods"
        }
    ],
    "sg:phone":"+1 863 453 2636",
    "sg:postcode":"33825",
    "sg:province":"FL",
    "wof:name":"Horace Williams Office Product",
    "wof:placetype":"venue"
},
  "geometry": {"coordinates":[-81.512373,27.595601],"type":"Point"}
}