{
  "type": "Feature",
  "properties": {
    "addr:full":"4755 W 8th Ave Hialeah FL 33012",
    "addr:housenumber":"4755",
    "addr:postcode":"33012",
    "addr:street":"W 8Th Ave",
    "iso:country":"US",
    "sg:address":"4755 W 8th Ave",
    "sg:city":"Hialeah",
    "sg:classifiers":[
        {
            "category":"Social Services",
            "subcategory":"Child Care",
            "type":"Services"
        }
    ],
    "sg:phone":"+1 305 826 4020",
    "sg:postcode":"33012",
    "sg:province":"FL",
    "sg:tags":[
        "day"
    ],
    "wof:name":"Bambi Land Day Care Center",
    "wof:placetype":"venue"
},
  "geometry": {"coordinates":[-80.298897,25.865499],"type":"Point"}
}