{
  "type": "Feature",
  "properties": {
    "iso:country":"US",
    "sg:address":"5985 Mobile Hwy",
    "sg:city":"Pensacola",
    "sg:classifiers":[
        {
            "category":"Banks & Credit Unions",
            "subcategory":"Bank",
            "type":"Services"
        }
    ],
    "sg:phone":"+1 850 444 1060",
    "sg:postcode":"32526",
    "sg:province":"FL",
    "sg:tags":[
        "state"
    ],
    "wof:name":"AmSouth",
    "wof:placetype":"venue"
},
  "geometry": {"coordinates":[-87.300111,30.459289],"type":"Point"}
}