{
  "type": "Feature",
  "properties": {
    "addr:full":"8930 SW 49th Ct Cooper City FL 33328",
    "addr:housenumber":"8930",
    "addr:postcode":"33328",
    "addr:street":"Sw 49Th Ct",
    "iso:country":"US",
    "sg:address":"8930 SW 49th Ct",
    "sg:city":"Cooper City",
    "sg:classifiers":[
        {
            "category":"Building & Trades",
            "subcategory":"Landscaping Services",
            "type":"Services"
        }
    ],
    "sg:phone":"+1 954 252 5700",
    "sg:postcode":"33328",
    "sg:province":"FL",
    "sg:tags":[
        "designer",
        "landscape"
    ],
    "wof:name":"Best Landscaping Inc",
    "wof:placetype":"venue"
},
  "geometry": {"coordinates":[-80.270804,26.063036],"type":"Point"}
}