{
  "type": "Feature",
  "properties": {
    "addr:full":"122 S 8th St Fernandina Beach FL 32034",
    "addr:housenumber":"122",
    "addr:postcode":"32034",
    "addr:street":"S 8Th St",
    "iso:country":"US",
    "sg:address":"122 S 8th St",
    "sg:city":"Fernandina Beach",
    "sg:classifiers":[
        {
            "category":"Food & Beverages",
            "subcategory":"Liquor & Beverages",
            "type":"Retail Goods"
        }
    ],
    "sg:phone":"+1 904 491 4198",
    "sg:postcode":"32034",
    "sg:province":"FL",
    "sg:tags":[
        "wine"
    ],
    "wof:name":"Vintage",
    "wof:placetype":"venue"
},
  "geometry": {"coordinates":[-81.458951,30.669146],"type":"Point"}
}