{
  "type": "Feature",
  "properties": {
    "addr:full":"13501 S Dixie Hwy Miami FL 33156",
    "addr:housenumber":"13501",
    "addr:postcode":"33156",
    "addr:street":"S Dixie Hwy",
    "iso:country":"US",
    "sg:address":"13501 S Dixie Hwy",
    "sg:city":"Miami",
    "sg:classifiers":[
        {
            "category":"Home & Garden",
            "subcategory":"Garden Supply",
            "type":"Retail Goods"
        }
    ],
    "sg:phone":"+1 305 254 8765",
    "sg:postcode":"33156",
    "sg:province":"FL",
    "sg:website":"www.homedepot.com",
    "wof:name":"The Home Depot",
    "wof:placetype":"venue"
},
  "geometry": {"coordinates":[-80.3319,25.64517],"type":"Point"}
}