{
  "type": "Feature",
  "properties": {
    "iso:country":"US",
    "sg:address":"1638 S San Remo Ave",
    "sg:city":"Clearwater",
    "sg:classifiers":[
        {
            "category":"Manufacturing",
            "subcategory":"Tools & Machinery",
            "type":"Manufacturing & Wholesale Goods"
        }
    ],
    "sg:phone":"+1 727 581 5405",
    "sg:postcode":"33756",
    "sg:province":"FL",
    "sg:tags":[
        "mfg"
    ],
    "wof:name":"Clearwater Carbide Die Co",
    "wof:placetype":"venue"
},
  "geometry": {"coordinates":[-82.777472,27.937687],"type":"Point"}
}