{
  "type": "Feature",
  "properties": {
    "iso:country":"US",
    "sg:address":"403 SW 2nd St",
    "sg:city":"Okeechobee",
    "sg:classifiers":[
        {
            "category":"Building & Trades",
            "subcategory":"Construction",
            "type":"Services"
        }
    ],
    "sg:phone":"+1 863 467 6364",
    "sg:postcode":"34974",
    "sg:province":"FL",
    "sg:tags":[
        "general",
        "contractor"
    ],
    "wof:name":"N & A Real Estate",
    "wof:placetype":"venue"
},
  "geometry": {"coordinates":[-80.834467,27.242038],"type":"Point"}
}