{
  "type": "Feature",
  "properties": {
    "iso:country":"US",
    "sg:address":"8710 SE 19th Avenue Rd",
    "sg:city":"Ocala",
    "sg:classifiers":[
        {
            "category":"Building & Trades",
            "subcategory":"Construction",
            "type":"Services"
        }
    ],
    "sg:phone":"+1 352 867 5288",
    "sg:postcode":"34480",
    "sg:province":"FL",
    "sg:tags":[
        "contractor",
        "painting",
        "hanging"
    ],
    "wof:name":"Robert Burns Painting Inc",
    "wof:placetype":"venue"
},
  "geometry": {"coordinates":[-82.11209599999999,29.096095],"type":"Point"}
}