{
  "type": "Feature",
  "properties": {
    "iso:country":"US",
    "sg:address":"512 NE 3rd Ave",
    "sg:city":"Fort Lauderdale",
    "sg:classifiers":[
        {
            "category":"Arts & Performance",
            "subcategory":"Theater",
            "type":"Entertainment"
        }
    ],
    "sg:phone":"+1 954 767 0686",
    "sg:postcode":"33301",
    "sg:province":"FL",
    "sg:tags":[
        "theatrical"
    ],
    "sg:website":"www.winterfestparade.com",
    "wof:name":"Winterfest Inc",
    "wof:placetype":"venue"
},
  "geometry": {"coordinates":[-80.140703,26.1296],"type":"Point"}
}