{
  "type": "Feature",
  "properties": {
    "iso:country":"US",
    "sg:address":"1457 Van Buren St",
    "sg:city":"Hollywood",
    "sg:classifiers":[
        {
            "category":"Building & Trades",
            "subcategory":"Construction",
            "type":"Services"
        }
    ],
    "sg:phone":"+1 954 923 6307",
    "sg:postcode":"33020",
    "sg:province":"FL",
    "sg:tags":[
        "house"
    ],
    "wof:name":"Adriatic Construction Inc",
    "wof:placetype":"venue"
},
  "geometry": {"coordinates":[-80.13592300000001,26.009935],"type":"Point"}
}