{
  "type": "Feature",
  "properties": {
    "addr:full":"3315 Kinard Ln Holiday FL 34691",
    "addr:postcode":"3315;34691",
    "addr:street":"Kinard Ln",
    "iso:country":"US",
    "sg:address":"3315 Kinard Ln",
    "sg:city":"Holiday",
    "sg:classifiers":[
        {
            "category":"Building & Trades",
            "subcategory":"Landscaping Services",
            "type":"Services"
        }
    ],
    "sg:phone":"+1 727 849 3030",
    "sg:postcode":"34691",
    "sg:province":"FL",
    "sg:tags":[
        "landscaper"
    ],
    "wof:name":"Bay Area Landscape & Lawn Care",
    "wof:placetype":"venue"
},
  "geometry": {"coordinates":[-82.748524,28.206808],"type":"Point"}
}