{
  "type": "Feature",
  "properties": {
    "addr:full":"7807 NW 57th St Doral FL 33166",
    "addr:housenumber":"7807",
    "addr:postcode":"33166",
    "addr:street":"Nw 57Th St",
    "iso:country":"US",
    "sg:address":"7807 NW 57th St",
    "sg:city":"Doral",
    "sg:classifiers":[
        {
            "category":"Real Estate",
            "subcategory":"Real Estate Services",
            "type":"Services"
        }
    ],
    "sg:phone":"+1 305 591 7378",
    "sg:postcode":"33166",
    "sg:province":"FL",
    "sg:tags":[
        "home",
        "inspector"
    ],
    "wof:name":"Pest Control by United Termite",
    "wof:placetype":"venue"
},
  "geometry": {"coordinates":[-80.324303,25.825199],"type":"Point"}
}