{
  "type": "Feature",
  "properties": {
    "iso:country":"US",
    "sg:address":"8400 NW 52nd St Ste 210",
    "sg:city":"Doral",
    "sg:classifiers":[
        {
            "category":"Airline",
            "type":"Transportation"
        }
    ],
    "sg:phone":"+1 305 266 6760",
    "sg:postcode":"33166",
    "sg:province":"FL",
    "sg:tags":[
        "ticket",
        "agency"
    ],
    "wof:name":"Cayman Airways Ltd",
    "wof:placetype":"venue"
},
  "geometry": {"coordinates":[-80.334671,25.818029],"type":"Point"}
}