{
  "type": "Feature",
  "properties": {
    "addr:full":"763 Jacqueline Ln Palm Harbor FL 34683",
    "addr:housenumber":"763",
    "addr:postcode":"34683",
    "addr:street":"Jacqueline Ln",
    "iso:country":"US",
    "sg:address":"763 Jacqueline Ln",
    "sg:city":"Palm Harbor",
    "sg:classifiers":[
        {
            "category":"Wholesale",
            "subcategory":"Medical Equipment & Supplies",
            "type":"Manufacturing & Wholesale Goods"
        }
    ],
    "sg:phone":"+1 727 784 6758",
    "sg:postcode":"34683",
    "sg:province":"FL",
    "wof:name":"Lifequest Enterprises Inc",
    "wof:placetype":"venue"
},
  "geometry": {"coordinates":[-82.770252,28.077559],"type":"Point"}
}