{
  "type": "Feature",
  "properties": {
    "addr:full":"2035 Linton Lake Dr Delray Beach FL 33445",
    "addr:housenumber":"2035",
    "addr:postcode":"33445",
    "addr:street":"Linton Lake Dr",
    "iso:country":"US",
    "sg:address":"2035 Linton Lake Dr",
    "sg:city":"Delray Beach",
    "sg:classifiers":[
        {
            "category":"Social Services",
            "subcategory":"Job Training",
            "type":"Services"
        }
    ],
    "sg:phone":"+1 561 276 8539",
    "sg:postcode":"33445",
    "sg:province":"FL",
    "sg:tags":[
        "career",
        "counseling",
        "vocational"
    ],
    "wof:name":"Career Development Svc",
    "wof:placetype":"venue"
},
  "geometry": {"coordinates":[-80.0972,26.438297],"type":"Point"}
}