{
  "type": "Feature",
  "properties": {
    "addr:full":"7135 Mariner Blvd Brooksville FL 34609",
    "addr:housenumber":"7135",
    "addr:postcode":"34609",
    "addr:street":"Mariner Blvd",
    "iso:country":"US",
    "sg:address":"7135 Mariner Blvd",
    "sg:city":"Brooksville",
    "sg:classifiers":[
        {
            "category":"Health Services",
            "subcategory":"Doctor",
            "type":"Services"
        }
    ],
    "sg:phone":"+1 352 597 1100",
    "sg:postcode":"34609",
    "sg:province":"FL",
    "sg:tags":[
        "dentist"
    ],
    "wof:name":"Ronald E Myers DDS",
    "wof:placetype":"venue"
},
  "geometry": {"coordinates":[-82.511638,28.531699],"type":"Point"}
}