{
  "type": "Feature",
  "properties": {
    "iso:country":"US",
    "sg:address":"7314 Collins Ave",
    "sg:city":"Miami Beach",
    "sg:classifiers":[
        {
            "category":"Personal",
            "subcategory":"Beauty Salon",
            "type":"Services"
        }
    ],
    "sg:phone":"+1 305 868 1110",
    "sg:postcode":"33141",
    "sg:province":"FL",
    "sg:tags":[
        "shop"
    ],
    "wof:name":"Valentis Hair Design",
    "wof:placetype":"venue"
},
  "geometry": {"coordinates":[-80.12105099999999,25.859414],"type":"Point"}
}