{
  "type": "Feature",
  "properties": {
    "addr:full":"2112 Fairway Villas Ln S Atlantic Beach FL 32233",
    "addr:housenumber":"2112",
    "addr:postcode":"32233",
    "addr:street":"Fairway Villas Ln S Atlantic Beach",
    "iso:country":"US",
    "sg:address":"2112 Fairway Villas Ln S",
    "sg:city":"Atlantic Beach",
    "sg:classifiers":[
        {
            "category":"Building & Trades",
            "subcategory":"Construction",
            "type":"Services"
        }
    ],
    "sg:phone":"+1 904 249 7203",
    "sg:postcode":"32233",
    "sg:province":"FL",
    "sg:tags":[
        "hanging",
        "contractor"
    ],
    "wof:name":"Lefts Painting of Jax Inc",
    "wof:placetype":"venue"
},
  "geometry": {"coordinates":[-81.41284400000001,30.344692],"type":"Point"}
}