{
  "type": "Feature",
  "properties": {
    "iso:country":"US",
    "sg:address":"8000 NW 31st St",
    "sg:city":"Doral",
    "sg:classifiers":[
        {
            "category":"Health Services",
            "subcategory":"Medical Lab",
            "type":"Services"
        },
        {
            "category":"Wholesale",
            "subcategory":"Machinery & Supplies",
            "type":"Manufacturing & Wholesale Goods"
        }
    ],
    "sg:phone":"+1 305 463 6999",
    "sg:postcode":"33122",
    "sg:province":"FL",
    "sg:tags":[
        "industrial",
        "testing",
        "broker",
        "machine",
        "part",
        "laboratory"
    ],
    "wof:name":"Solo Dental Lab",
    "wof:placetype":"venue"
},
  "geometry": {"coordinates":[-80.327533,25.802572],"type":"Point"}
}