{
  "type": "Feature",
  "properties": {
    "addr:full":"2920 Claire Ln Jacksonville FL 32223",
    "addr:housenumber":"2920",
    "addr:postcode":"32223",
    "addr:street":"Claire Ln",
    "iso:country":"US",
    "sg:address":"2920 Claire Ln",
    "sg:city":"Jacksonville",
    "sg:classifiers":[
        {
            "category":"Professional",
            "type":"Services"
        }
    ],
    "sg:phone":"+1 904 268 7478",
    "sg:postcode":"32223",
    "sg:province":"FL",
    "wof:name":"Mamie G Schultz Svc",
    "wof:placetype":"venue"
},
  "geometry": {"coordinates":[-81.633951,30.175185],"type":"Point"}
}