{
  "type": "Feature",
  "properties": {
    "addr:full":"1111 NW 43rd Ave Miami FL 33126",
    "addr:housenumber":"1111",
    "addr:postcode":"33126",
    "addr:street":"Nw 43Rd Ave",
    "iso:country":"US",
    "sg:address":"1111 NW 43rd Ave",
    "sg:city":"Miami",
    "sg:classifiers":[
        {
            "category":"Shopping",
            "subcategory":"Stationery & Office Supplies",
            "type":"Retail Goods"
        }
    ],
    "sg:phone":"+1 305 569 0088",
    "sg:postcode":"33126",
    "sg:province":"FL",
    "sg:tags":[
        "machine",
        "copy",
        "envelope",
        "store"
    ],
    "wof:name":"Services On Site",
    "wof:placetype":"venue"
},
  "geometry": {"coordinates":[-80.266053,25.782455],"type":"Point"}
}