{
  "type": "Feature",
  "properties": {
    "addr:full":"19026 Bruce B Downs Blvd Tampa FL 33647",
    "addr:housenumber":"19026",
    "addr:postcode":"33647",
    "addr:street":"Bruce B Downs Blvd",
    "iso:country":"US",
    "sg:address":"19026 Bruce B Downs Blvd",
    "sg:city":"Tampa",
    "sg:classifiers":[
        {
            "category":"Real Estate",
            "subcategory":"Real Estate Services",
            "type":"Services"
        }
    ],
    "sg:phone":"+1 813 631 9715",
    "sg:postcode":"33647",
    "sg:province":"FL",
    "sg:tags":[
        "company",
        "title"
    ],
    "wof:name":"Sunbelt Title Agency",
    "wof:placetype":"venue"
},
  "geometry": {"coordinates":[-82.353313,28.14577],"type":"Point"}
}