{
  "type": "Feature",
  "properties": {
    "addr:full":"507 SW 19th Ln Cape Coral FL 33991",
    "addr:housenumber":"507",
    "addr:postcode":"33991",
    "addr:street":"Sw 19Th Ln",
    "iso:country":"US",
    "sg:address":"507 SW 19th Ln",
    "sg:city":"Cape Coral",
    "sg:classifiers":[
        {
            "category":"Professional",
            "type":"Services"
        }
    ],
    "sg:phone":"+1 239 772 4980",
    "sg:postcode":"33991",
    "sg:province":"FL",
    "sg:tags":[
        "establishment"
    ],
    "wof:name":"Creative Scapes",
    "wof:placetype":"venue"
},
  "geometry": {"coordinates":[-81.983777,26.616036],"type":"Point"}
}