{
  "type": "Feature",
  "properties": {
    "addr:full":"22 W Monument Ave Kissimmee FL 34741",
    "addr:housenumber":"22",
    "addr:postcode":"34741",
    "addr:street":"W Monument Ave",
    "iso:country":"US",
    "sg:address":"22 W Monument Ave",
    "sg:city":"Kissimmee",
    "sg:classifiers":[
        {
            "category":"Building & Trades",
            "subcategory":"Cleaning & Sanitation",
            "type":"Services"
        }
    ],
    "sg:phone":"+1 407 935 9177",
    "sg:postcode":"34741",
    "sg:province":"FL",
    "sg:tags":[
        "property",
        "maintenance"
    ],
    "wof:name":"Mid Florida Property Mntnc",
    "wof:placetype":"venue"
},
  "geometry": {"coordinates":[-81.407087,28.293904],"type":"Point"}
}