{
  "type": "Feature",
  "properties": {
    "addr:full":"2827 SW 130th Ter Miramar FL 33027",
    "addr:housenumber":"2827",
    "addr:postcode":"33027",
    "addr:street":"Sw 130Th Ter",
    "iso:country":"US",
    "sg:address":"2827 SW 130th Ter",
    "sg:city":"Miramar",
    "sg:classifiers":[
        {
            "category":"Professional",
            "subcategory":"Management & Consulting",
            "type":"Services"
        }
    ],
    "sg:phone":"+1 954 435 7376",
    "sg:postcode":"33027",
    "sg:province":"FL",
    "sg:tags":[
        "science",
        "consultant",
        "academic"
    ],
    "wof:name":"Garrison Environmental Analysis",
    "wof:placetype":"venue"
},
  "geometry": {"coordinates":[-80.32023100000001,25.982779],"type":"Point"}
}