{
  "type": "Feature",
  "properties": {
    "iso:country":"US",
    "sg:address":"3038 Rayford St",
    "sg:city":"Jacksonville",
    "sg:classifiers":[
        {
            "category":"Personal",
            "subcategory":"Barber",
            "type":"Services"
        }
    ],
    "sg:phone":"+1 904 384 4388",
    "sg:postcode":"32205",
    "sg:province":"FL",
    "wof:name":"Curtis Barber Shop",
    "wof:placetype":"venue"
},
  "geometry": {"coordinates":[-81.70854799999999,30.320451],"type":"Point"}
}