{
  "type": "Feature",
  "properties": {
    "iso:country":"US",
    "sg:address":"2814 NW 6th St",
    "sg:city":"Gainesville",
    "sg:classifiers":[
        {
            "category":"Wholesale",
            "subcategory":"Machinery & Supplies",
            "type":"Manufacturing & Wholesale Goods"
        }
    ],
    "sg:phone":"+1 352 264 7884",
    "sg:postcode":"32609",
    "sg:province":"FL",
    "sg:tags":[
        "casket"
    ],
    "wof:name":"North Florida Casket & Urn",
    "wof:placetype":"venue"
},
  "geometry": {"coordinates":[-82.330714,29.677503],"type":"Point"}
}