{
  "type": "Feature",
  "properties": {
    "addr:full":"7421 N University Dr # 210 Tamarac FL 33321",
    "addr:housenumber":"7421",
    "addr:postcode":"33321",
    "addr:street":"N University Dr # 210",
    "iso:country":"US",
    "sg:address":"7421 N University Dr # 210",
    "sg:city":"Tamarac",
    "sg:classifiers":[
        {
            "category":"Health Services",
            "subcategory":"Doctor",
            "type":"Services"
        }
    ],
    "sg:phone":"+1 954 720 5600",
    "sg:postcode":"33321",
    "sg:province":"FL",
    "sg:tags":[
        "medicine",
        "physician",
        "surgeon",
        "internal",
        "surgeons"
    ],
    "wof:name":"Sackin, Alan J Md Pa",
    "wof:placetype":"venue"
},
  "geometry": {"coordinates":[-80.252605,26.213826],"type":"Point"}
}