{
  "type": "Feature",
  "properties": {
    "addr:full":"3201 Fox Squirrel Ln Valrico FL 33596",
    "addr:housenumber":"3201",
    "addr:postcode":"33596",
    "addr:street":"Fox Squirrel Ln",
    "iso:country":"US",
    "sg:address":"3201 Fox Squirrel Ln",
    "sg:city":"Valrico",
    "sg:classifiers":[
        {
            "category":"Shopping",
            "type":"Retail Goods"
        }
    ],
    "sg:phone":"+1 813 661 0172",
    "sg:postcode":"33596",
    "sg:province":"FL",
    "sg:tags":[
        "merchandise"
    ],
    "wof:name":"Gillette",
    "wof:placetype":"venue"
},
  "geometry": {"coordinates":[-82.20830599999999,27.893749],"type":"Point"}
}