{
  "type": "Feature",
  "properties": {
    "addr:full":"57 Snapper St Santa Rosa Beach FL 32459",
    "addr:housenumber":"57",
    "addr:postcode":"32459",
    "addr:street":"Snapper St;Rosa",
    "iso:country":"US",
    "sg:address":"57 Snapper St",
    "sg:city":"Santa Rosa Beach",
    "sg:classifiers":[
        {
            "category":"Real Estate",
            "subcategory":"Real Estate Agent",
            "type":"Services"
        }
    ],
    "sg:phone":"+1 850 622 2329",
    "sg:postcode":"32459",
    "sg:province":"FL",
    "wof:name":"Stephanie Burke PA",
    "wof:placetype":"venue"
},
  "geometry": {"coordinates":[-86.208068,30.344432],"type":"Point"}
}