{
  "type": "Feature",
  "properties": {
    "addr:full":"5553 Gatlin Ave Orlando FL 32812",
    "addr:housenumber":"5553",
    "addr:postcode":"32812",
    "addr:street":"Gatlin Ave",
    "iso:country":"US",
    "sg:address":"5553 Gatlin Ave",
    "sg:city":"Orlando",
    "sg:classifiers":[
        {
            "category":"Building & Trades",
            "subcategory":"Construction",
            "type":"Services"
        }
    ],
    "sg:phone":"+1 407 737 7910",
    "sg:postcode":"32812",
    "sg:province":"FL",
    "sg:tags":[
        "hanging",
        "contractor"
    ],
    "wof:name":"Oscars Painting of Central FL",
    "wof:placetype":"venue"
},
  "geometry": {"coordinates":[-81.31141,28.495279],"type":"Point"}
}