{
  "type": "Feature",
  "properties": {
    "iso:country":"US",
    "sg:address":"656 2nd Ln",
    "sg:city":"Vero Beach",
    "sg:classifiers":[
        {
            "category":"Building & Trades",
            "subcategory":"Construction",
            "type":"Services"
        }
    ],
    "sg:phone":"+1 772 569 4004",
    "sg:postcode":"32962",
    "sg:province":"FL",
    "sg:tags":[
        "downspouts",
        "gutter"
    ],
    "wof:name":"Deubel Seamless Gutters",
    "wof:placetype":"venue"
},
  "geometry": {"coordinates":[-80.38679399999999,27.606355],"type":"Point"}
}