{
  "type": "Feature",
  "properties": {
    "iso:country":"US",
    "sg:address":"5380 N Ocean Dr",
    "sg:city":"West Palm Beach",
    "sg:classifiers":[
        {
            "category":"Autos & Motor Vehicles",
            "subcategory":"Auto Supplies",
            "type":"Retail Goods"
        }
    ],
    "sg:phone":"+1 561 845 8851",
    "sg:postcode":"33404",
    "sg:province":"FL",
    "sg:tags":[
        "tire"
    ],
    "wof:name":"Beck's Tire Svc",
    "wof:placetype":"venue"
},
  "geometry": {"coordinates":[-80.03603099999999,26.810448],"type":"Point"}
}