{
  "type": "Feature",
  "properties": {
    "addr:full":"15303 Amberly Dr Tampa FL 33647",
    "addr:housenumber":"15303",
    "addr:postcode":"33647",
    "addr:street":"Amberly Dr",
    "iso:country":"US",
    "sg:address":"15303 Amberly Dr",
    "sg:city":"Tampa",
    "sg:classifiers":[
        {
            "category":"Banks & Credit Unions",
            "subcategory":"Investment Brokerage",
            "type":"Services"
        }
    ],
    "sg:phone":"+1 813 903 6680",
    "sg:postcode":"33647",
    "sg:province":"FL",
    "sg:tags":[
        "security"
    ],
    "wof:name":"UBS Financial Svc",
    "wof:placetype":"venue"
},
  "geometry": {"coordinates":[-82.40453100000001,28.096022],"type":"Point"}
}