{
  "type": "Feature",
  "properties": {
    "addr:full":"1081 N Paul Dr Inverness FL 34453",
    "addr:housenumber":"1081",
    "addr:postcode":"34453",
    "addr:street":"N Paul Dr",
    "iso:country":"US",
    "sg:address":"1081 N Paul Dr",
    "sg:city":"Inverness",
    "sg:classifiers":[
        {
            "category":"Restaurant",
            "type":"Food & Drink"
        }
    ],
    "sg:phone":"+1 352 726 1009",
    "sg:postcode":"34453",
    "sg:province":"FL",
    "sg:tags":[
        "eating"
    ],
    "wof:name":"Support Services",
    "wof:placetype":"venue"
},
  "geometry": {"coordinates":[-82.364288,28.877668],"type":"Point"}
}