{
  "type": "Feature",
  "properties": {
    "iso:country":"US",
    "sg:address":"675 Sierra Cir",
    "sg:city":"Miami",
    "sg:classifiers":[
        {
            "category":"Home & Garden",
            "subcategory":"Mobile Homes",
            "type":"Retail Goods"
        }
    ],
    "sg:phone":"+1 305 740 6468",
    "sg:postcode":"33156",
    "sg:province":"FL",
    "wof:name":"NV Modern Living Corp",
    "wof:placetype":"venue"
},
  "geometry": {"coordinates":[-80.27722799999999,25.672226],"type":"Point"}
}