{
  "type": "Feature",
  "properties": {
    "iso:country":"US",
    "sg:address":"2400 E Las Olas Blvd",
    "sg:city":"Fort Lauderdale",
    "sg:classifiers":[
        {
            "category":"Restaurant",
            "type":"Food & Drink"
        }
    ],
    "sg:menulink":"http://www.allmenus.com/fl/fort-lauderdale/37892-chima-steakhouse/menu/",
    "sg:phone":"+1 954 712 0580",
    "sg:postcode":"33301",
    "sg:province":"FL",
    "sg:tags":[
        "american",
        "steakhouse"
    ],
    "wof:name":"Chima Steakhouse",
    "wof:placetype":"venue"
},
  "geometry": {"coordinates":[-80.11411,26.120135],"type":"Point"}
}