{
  "type": "Feature",
  "properties": {
    "iso:country":"US",
    "sg:address":"10885 Eureka St",
    "sg:city":"Boca Raton",
    "sg:classifiers":[
        {
            "category":"Building & Trades",
            "subcategory":"Construction",
            "type":"Services"
        }
    ],
    "sg:phone":"+1 561 482 5545",
    "sg:postcode":"33428",
    "sg:province":"FL",
    "sg:tags":[
        "tile",
        "dealer"
    ],
    "wof:name":"Veloso Marble & Tile",
    "wof:placetype":"venue"
},
  "geometry": {"coordinates":[-80.216927,26.342475],"type":"Point"}
}