{
  "type": "Feature",
  "properties": {
    "addr:full":"1227 55th Ave N St Petersburg FL 33703",
    "addr:housenumber":"1227",
    "addr:postcode":"33703",
    "addr:street":"55Th Ave N",
    "iso:country":"US",
    "sg:address":"1227 55th Ave N",
    "sg:city":"St Petersburg",
    "sg:classifiers":[
        {
            "category":"Professional",
            "subcategory":"Computer Services",
            "type":"Services"
        }
    ],
    "sg:phone":"+1 813 909 9780",
    "sg:postcode":"33703",
    "sg:province":"FL",
    "sg:tags":[
        "repair"
    ],
    "wof:name":"My Mac Guys",
    "wof:placetype":"venue"
},
  "geometry": {"coordinates":[-82.651946,27.822141],"type":"Point"}
}