{
  "type": "Feature",
  "properties": {
    "iso:country":"US",
    "sg:address":"105 N Falkenburg Rd",
    "sg:city":"Tampa",
    "sg:classifiers":[
        {
            "category":"Building & Trades",
            "subcategory":"Construction",
            "type":"Services"
        }
    ],
    "sg:phone":"+1 813 685 6005",
    "sg:postcode":"33619",
    "sg:province":"FL",
    "sg:tags":[
        "road",
        "contractor"
    ],
    "wof:name":"Hubbard Construction Company",
    "wof:placetype":"venue"
},
  "geometry": {"coordinates":[-82.33509599999999,27.955973],"type":"Point"}
}