{
  "type": "Feature",
  "properties": {
    "iso:country":"US",
    "sg:address":"1100 SW 24th Ave",
    "sg:city":"Deerfield Beach",
    "sg:classifiers":[
        {
            "category":"Social Services",
            "subcategory":"Child Care",
            "type":"Services"
        }
    ],
    "sg:phone":"+1 954 426 9898",
    "sg:postcode":"33442",
    "sg:province":"FL",
    "sg:tags":[
        "day"
    ],
    "wof:name":"Tutor Time Child Care Lrng Ctr",
    "wof:placetype":"venue"
},
  "geometry": {"coordinates":[-80.136133,26.302028],"type":"Point"}
}