{
  "type": "Feature",
  "properties": {
    "iso:country":"US",
    "sg:address":"1762 W Flagler St",
    "sg:city":"Miami",
    "sg:classifiers":[
        {
            "category":"Shopping",
            "subcategory":"Crafts & Fabrics",
            "type":"Retail Goods"
        }
    ],
    "sg:phone":"+1 305 541 2568",
    "sg:postcode":"33135",
    "sg:province":"FL",
    "sg:tags":[
        "shop"
    ],
    "wof:name":"Laretazera",
    "wof:placetype":"venue"
},
  "geometry": {"coordinates":[-80.224682,25.772669],"type":"Point"}
}