{
  "type": "Feature",
  "properties": {
    "addr:full":"11605 SW 138th Ter Miami FL 33176",
    "addr:housenumber":"11605",
    "addr:postcode":"33176",
    "addr:street":"Sw 138Th Ter",
    "iso:country":"US",
    "sg:address":"11605 SW 138th Ter",
    "sg:city":"Miami",
    "sg:classifiers":[
        {
            "category":"Professional",
            "subcategory":"Management & Consulting",
            "type":"Services"
        }
    ],
    "sg:phone":"+1 305 232 8154",
    "sg:postcode":"33176",
    "sg:province":"FL",
    "sg:tags":[
        "party",
        "planning"
    ],
    "wof:name":"E B Grands",
    "wof:placetype":"venue"
},
  "geometry": {"coordinates":[-80.381691,25.639759],"type":"Point"}
}