{
  "type": "Feature",
  "properties": {
    "iso:country":"US",
    "sg:address":"102 N Rome Ave",
    "sg:city":"Tampa",
    "sg:classifiers":[
        {
            "category":"Freight",
            "type":"Transportation"
        }
    ],
    "sg:phone":"+1 813 250 0502",
    "sg:postcode":"33606",
    "sg:province":"FL",
    "sg:tags":[
        "commercial",
        "storage"
    ],
    "sg:website":"www.extraspacecenter.com",
    "wof:name":"Extra Space Ctr Self Storage",
    "wof:placetype":"venue"
},
  "geometry": {"coordinates":[-82.47685199999999,27.945551],"type":"Point"}
}