{
  "type": "Feature",
  "properties": {
    "addr:full":"29 N Brown Ave Fort Meade FL 33841",
    "addr:housenumber":"29",
    "addr:postcode":"33841",
    "addr:street":"N Brown Ave",
    "iso:country":"US",
    "sg:address":"29 N Brown Ave",
    "sg:city":"Fort Meade",
    "sg:classifiers":[
        {
            "category":"Manufacturing",
            "subcategory":"Retail Goods",
            "type":"Manufacturing & Wholesale Goods"
        }
    ],
    "sg:phone":"+1 863 285 7179",
    "sg:postcode":"33841",
    "sg:province":"FL",
    "sg:tags":[
        "assembly",
        "fabricating"
    ],
    "wof:name":"Acu Fab Inc",
    "wof:placetype":"venue"
},
  "geometry": {"coordinates":[-81.80588400000001,27.751972],"type":"Point"}
}