{
  "type": "Feature",
  "properties": {
    "iso:country":"US",
    "sg:address":"3601 Henderson Blvd",
    "sg:city":"Tampa",
    "sg:classifiers":[
        {
            "category":"Shopping",
            "type":"Retail Goods"
        }
    ],
    "sg:phone":"+1 813 875 7500",
    "sg:postcode":"33609",
    "sg:province":"FL",
    "sg:tags":[
        "mobile",
        "telephone",
        "accessory"
    ],
    "wof:name":"T-Mobile USA Inc",
    "wof:placetype":"venue"
},
  "geometry": {"coordinates":[-82.503686,27.935722],"type":"Point"}
}