{
  "type": "Feature",
  "properties": {
    "iso:country":"US",
    "sg:address":"5512 Normandy Blvd",
    "sg:city":"Jacksonville",
    "sg:classifiers":[
        {
            "category":"Food & Beverages",
            "subcategory":"Liquor & Beverages",
            "type":"Retail Goods"
        }
    ],
    "sg:phone":"+1 904 783 0024",
    "sg:postcode":"32205",
    "sg:province":"FL",
    "wof:name":"Davis Discount Beverage",
    "wof:placetype":"venue"
},
  "geometry": {"coordinates":[-81.741331,30.308711],"type":"Point"}
}