{
  "type": "Feature",
  "properties": {
    "addr:full":"5641 Ohio Ave Lady Lake FL 32159",
    "addr:housenumber":"5641",
    "addr:postcode":"32159",
    "addr:street":"Ohio Ave",
    "iso:country":"US",
    "sg:address":"5641 Ohio Ave",
    "sg:city":"Lady Lake",
    "sg:classifiers":[
        {
            "category":"Building & Trades",
            "subcategory":"Construction",
            "type":"Services"
        }
    ],
    "sg:phone":"+1 352 259 2378",
    "sg:postcode":"32159",
    "sg:province":"FL",
    "sg:tags":[
        "carpentry",
        "contractor"
    ],
    "wof:name":"Shawn Cinaders Custom Constru",
    "wof:placetype":"venue"
},
  "geometry": {"coordinates":[-81.85912,28.9051],"type":"Point"}
}