{
  "type": "Feature",
  "properties": {
    "addr:full":"220 S Dillard St Winter Garden FL 34787",
    "addr:housenumber":"220",
    "addr:postcode":"34787",
    "addr:street":"S Dillard St",
    "iso:country":"US",
    "sg:address":"220 S Dillard St",
    "sg:city":"Winter Garden",
    "sg:classifiers":[
        {
            "category":"Building & Trades",
            "subcategory":"Pest Control",
            "type":"Services"
        }
    ],
    "sg:phone":"+1 407 877 6660",
    "sg:postcode":"34787",
    "sg:province":"FL",
    "wof:name":"Rhino Pest Control Inc",
    "wof:placetype":"venue"
},
  "geometry": {"coordinates":[-81.58361600000001,28.562299],"type":"Point"}
}