{
  "type": "Feature",
  "properties": {
    "iso:country":"US",
    "sg:address":"44 NE 51st St",
    "sg:city":"Miami",
    "sg:classifiers":[
        {
            "category":"Professional",
            "type":"Services"
        }
    ],
    "sg:phone":"+1 305 758 5640",
    "sg:postcode":"33137",
    "sg:province":"FL",
    "sg:tags":[
        "establishment"
    ],
    "wof:name":"Children-Sun Endowment",
    "wof:placetype":"venue"
},
  "geometry": {"coordinates":[-80.195374,25.822637],"type":"Point"}
}