{
  "type": "Feature",
  "properties": {
    "iso:country":"US",
    "sg:address":"1158 Fay Blvd",
    "sg:city":"Cocoa",
    "sg:classifiers":[
        {
            "category":"Building & Trades",
            "subcategory":"Plumbing",
            "type":"Services"
        }
    ],
    "sg:phone":"+1 321 633 3258",
    "sg:postcode":"32927",
    "sg:province":"FL",
    "sg:tags":[
        "conditioning",
        "air",
        "system",
        "contractor"
    ],
    "wof:name":"Everett H Platt Heating & Air",
    "wof:placetype":"venue"
},
  "geometry": {"coordinates":[-80.77566899999999,28.476981],"type":"Point"}
}