{
  "type": "Feature",
  "properties": {
    "iso:country":"US",
    "sg:address":"9525 Raptor Ct",
    "sg:city":"Tallahassee",
    "sg:classifiers":[
        {
            "category":"Building & Trades",
            "subcategory":"Electrical",
            "type":"Services"
        }
    ],
    "sg:phone":"+1 850 402 9725",
    "sg:postcode":"32309",
    "sg:province":"FL",
    "sg:tags":[
        "electrician"
    ],
    "wof:name":"Dawsons Electrical Service",
    "wof:placetype":"venue"
},
  "geometry": {"coordinates":[-84.11194999999999,30.503755],"type":"Point"}
}