{
  "type": "Feature",
  "properties": {
    "addr:full":"616 2nd Ave Waverly FL 33877",
    "addr:housenumber":"616",
    "addr:postcode":"33877",
    "addr:street":"2Nd Ave",
    "iso:country":"US",
    "sg:address":"616 2nd Ave",
    "sg:city":"Waverly",
    "sg:classifiers":[
        {
            "category":"Personal",
            "subcategory":"Beauty Salon",
            "type":"Services"
        }
    ],
    "sg:phone":"+1 863 439 2624",
    "sg:postcode":"33877",
    "sg:province":"FL",
    "wof:name":"Kristy's Beauty Salon",
    "wof:placetype":"venue"
},
  "geometry": {"coordinates":[-81.618287,27.98368],"type":"Point"}
}