{
  "type": "Feature",
  "properties": {
    "iso:country":"US",
    "sg:address":"7448 Kreamers Dr",
    "sg:city":"Bokeelia",
    "sg:classifiers":[
        {
            "category":"Retail",
            "subcategory":"Repair Shop",
            "type":"Services"
        }
    ],
    "sg:phone":"+1 239 283 1445",
    "sg:postcode":"33922",
    "sg:province":"FL",
    "sg:tags":[
        "refinishing",
        "furniture"
    ],
    "wof:name":"Gene Carns",
    "wof:placetype":"venue"
},
  "geometry": {"coordinates":[-82.146413,26.680455],"type":"Point"}
}