{
  "type": "Feature",
  "properties": {
    "iso:country":"US",
    "sg:address":"8318 Gardenia Cir",
    "sg:city":"Pensacola",
    "sg:classifiers":[
        {
            "category":"Retail",
            "subcategory":"Auto Repair",
            "type":"Services"
        }
    ],
    "sg:phone":"+1 850 476 3859",
    "sg:postcode":"32534",
    "sg:province":"FL",
    "sg:tags":[
        "body",
        "automobile",
        "painting",
        "repairing"
    ],
    "wof:name":"Five Star Paint & Body Inc",
    "wof:placetype":"venue"
},
  "geometry": {"coordinates":[-87.274975,30.517762],"type":"Point"}
}