{
  "type": "Feature",
  "properties": {
    "addr:full":"3109 Old State Hwy 8 Lake Placid FL 33852",
    "addr:housenumber":"3109",
    "addr:postcode":"33852",
    "addr:street":"Old State Hwy 8",
    "iso:country":"US",
    "sg:address":"3109 Old State Hwy 8",
    "sg:city":"Lake Placid",
    "sg:classifiers":[
        {
            "category":"Manufacturing",
            "subcategory":"Printing",
            "type":"Manufacturing & Wholesale Goods"
        }
    ],
    "sg:phone":"+1 863 465 4213",
    "sg:postcode":"33852",
    "sg:province":"FL",
    "sg:tags":[
        "newspaper"
    ],
    "sg:website":"www.newszap.com",
    "wof:name":"Sunshine Newspaper Printing",
    "wof:placetype":"venue"
},
  "geometry": {"coordinates":[-81.341562,27.228015],"type":"Point"}
}