{
  "type": "Feature",
  "properties": {
    "addr:full":"1890 Elsa St Naples FL 34109",
    "addr:housenumber":"1890",
    "addr:postcode":"34109",
    "addr:street":"Elsa St",
    "iso:country":"US",
    "sg:address":"1890 Elsa St",
    "sg:city":"Naples",
    "sg:classifiers":[
        {
            "category":"Building & Trades",
            "subcategory":"Cleaning & Sanitation",
            "type":"Services"
        }
    ],
    "sg:phone":"+1 239 513 0513",
    "sg:postcode":"34109",
    "sg:province":"FL",
    "sg:tags":[
        "janitor"
    ],
    "wof:name":"Fanaticklean",
    "wof:placetype":"venue"
},
  "geometry": {"coordinates":[-81.77933400000001,26.219282],"type":"Point"}
}