{
  "type": "Feature",
  "properties": {
    "iso:country":"US",
    "sg:address":"8202 Mills Drive",
    "sg:city":"Miami",
    "sg:classifiers":[
        {
            "category":"Restaurant",
            "type":"Food & Drink"
        }
    ],
    "sg:phone":"+1 305 279 3409",
    "sg:postcode":"33183",
    "sg:province":"FL",
    "sg:tags":[
        "cuban"
    ],
    "sg:website":"www.casavana.com",
    "wof:name":"Casavana Cuban Cuisine",
    "wof:placetype":"venue"
},
  "geometry": {"coordinates":[-80.383673,25.690783],"type":"Point"}
}