{
  "type": "Feature",
  "properties": {
    "iso:country":"US",
    "sg:address":"1005 SW 27th Ave",
    "sg:city":"Miami",
    "sg:classifiers":[
        {
            "category":"Utilities",
            "subcategory":"Mobile Phone",
            "type":"Services"
        }
    ],
    "sg:phone":"+1 786 953 4399",
    "sg:postcode":"33135",
    "sg:province":"FL",
    "sg:tags":[
        "telephone",
        "cellular"
    ],
    "wof:name":"Miami Best Wireless",
    "wof:placetype":"venue"
},
  "geometry": {"coordinates":[-80.238721,25.763615],"type":"Point"}
}