{
  "type": "Feature",
  "properties": {
    "iso:country":"US",
    "sg:address":"4522 Del Prado Blvd S",
    "sg:city":"Cape Coral",
    "sg:classifiers":[
        {
            "category":"Home & Garden",
            "subcategory":"Carpets & Floor Coverings",
            "type":"Retail Goods"
        }
    ],
    "sg:phone":"+1 239 542 8643",
    "sg:postcode":"33904",
    "sg:province":"FL",
    "sg:tags":[
        "carpeting"
    ],
    "wof:name":"Costello Pat the Carpet Man Inc",
    "wof:placetype":"venue"
},
  "geometry": {"coordinates":[-81.94409899999999,26.5676],"type":"Point"}
}