{
  "type": "Feature",
  "properties": {
    "iso:country":"US",
    "sg:address":"1416 SE 2nd Ter",
    "sg:city":"Deerfield Beach",
    "sg:classifiers":[
        {
            "category":"Organizations",
            "subcategory":"Religious Organization",
            "type":"Services"
        }
    ],
    "sg:phone":"+1 954 421 3506",
    "sg:postcode":"33441",
    "sg:province":"FL",
    "sg:tags":[
        "church"
    ],
    "wof:name":"St Peters Anglican Cathedral",
    "wof:placetype":"venue"
},
  "geometry": {"coordinates":[-80.099563,26.297781],"type":"Point"}
}