{
  "type": "Feature",
  "properties": {
    "addr:full":"9950 S York Way Homosassa FL 34448",
    "addr:housenumber":"9950",
    "addr:postcode":"34448",
    "addr:street":"S York Way",
    "iso:country":"US",
    "sg:address":"9950 S York Way",
    "sg:city":"Homosassa",
    "sg:classifiers":[
        {
            "category":"Government",
            "subcategory":"Office",
            "type":"Public Place"
        }
    ],
    "sg:phone":"+1 352 382 3069",
    "sg:postcode":"34448",
    "sg:province":"FL",
    "sg:tags":[
        "conservation"
    ],
    "wof:name":"Captain Kenneth R Alvarez",
    "wof:placetype":"venue"
},
  "geometry": {"coordinates":[-82.55542199999999,28.718925],"type":"Point"}
}