{
  "type": "Feature",
  "properties": {
    "iso:country":"US",
    "sg:address":"1075 Mason Ave",
    "sg:city":"Daytona Beach",
    "sg:classifiers":[
        {
            "category":"Health Services",
            "subcategory":"Doctor",
            "type":"Services"
        }
    ],
    "sg:phone":"+1 386 255 4596",
    "sg:postcode":"32117",
    "sg:province":"FL",
    "sg:tags":[
        "medical"
    ],
    "wof:name":"Dr Thurman Gillespy",
    "wof:placetype":"venue"
},
  "geometry": {"coordinates":[-81.0527,29.217406],"type":"Point"}
}