{
  "type": "Feature",
  "properties": {
    "addr:full":"4704 64th Dr W Bradenton FL 34210",
    "addr:housenumber":"4704",
    "addr:postcode":"34210",
    "addr:street":"64Th Dr W",
    "iso:country":"US",
    "sg:address":"4704 64th Dr W",
    "sg:city":"Bradenton",
    "sg:classifiers":[
        {
            "category":"Organizations",
            "subcategory":"Religious Organization",
            "type":"Services"
        }
    ],
    "sg:phone":"+1 941 751 9395",
    "sg:postcode":"34210",
    "sg:province":"FL",
    "sg:tags":[
        "counseling"
    ],
    "wof:name":"Maureen Young",
    "wof:placetype":"venue"
},
  "geometry": {"coordinates":[-82.610049,27.428225],"type":"Point"}
}