{
  "type": "Feature",
  "properties": {
    "iso:country":"US",
    "sg:address":"109 Ridge Ct",
    "sg:city":"Brandon",
    "sg:classifiers":[
        {
            "category":"Farming",
            "subcategory":"Livestock Farm",
            "type":"Manufacturing & Wholesale Goods"
        }
    ],
    "sg:phone":"+1 813 689 3053",
    "sg:postcode":"33511",
    "sg:province":"FL",
    "sg:tags":[
        "bearing",
        "fur",
        "animal"
    ],
    "wof:name":"Charles E and Betty Mink",
    "wof:placetype":"venue"
},
  "geometry": {"coordinates":[-82.28473099999999,27.903729],"type":"Point"}
}