{
  "type": "Feature",
  "properties": {
    "addr:full":"1217 Tech Blvd Tampa FL 33619",
    "addr:housenumber":"1217",
    "addr:postcode":"33619",
    "addr:street":"Tech Blvd",
    "iso:country":"US",
    "sg:address":"1217 Tech Blvd",
    "sg:city":"Tampa",
    "sg:classifiers":[
        {
            "category":"Manufacturing",
            "subcategory":"Tools & Machinery",
            "type":"Manufacturing & Wholesale Goods"
        }
    ],
    "sg:phone":"+1 813 664 0032",
    "sg:postcode":"33619",
    "sg:province":"FL",
    "sg:tags":[
        "machine",
        "shop"
    ],
    "sg:website":"www.vulcanmachine.com",
    "wof:name":"Vulcan Machine",
    "wof:placetype":"venue"
},
  "geometry": {"coordinates":[-82.332759,27.961399],"type":"Point"}
}