{
  "type": "Feature",
  "properties": {
    "addr:full":"531 SW 12th Ave Miami FL 33130",
    "addr:housenumber":"531",
    "addr:postcode":"33130",
    "addr:street":"Sw 12Th Ave",
    "iso:country":"US",
    "sg:address":"531 SW 12th Ave",
    "sg:city":"Miami",
    "sg:classifiers":[
        {
            "category":"Place Of Worship",
            "subcategory":"Church",
            "type":"Public Place"
        },
        {
            "category":"Place Of Worship",
            "type":"Public Place"
        }
    ],
    "sg:phone":"+1 305 324 1711",
    "sg:postcode":"33130",
    "sg:province":"FL",
    "sg:tags":[
        "churches-interdenominational",
        "churches-various",
        "denomination"
    ],
    "wof:name":"Iglesia Cosecha De Cristo Inc",
    "wof:placetype":"venue"
},
  "geometry": {"coordinates":[-80.214499,25.768366],"type":"Point"}
}