{
  "type": "Feature",
  "properties": {
    "addr:full":"18750 NW 67th Ave Hialeah FL 33015",
    "addr:housenumber":"18750",
    "addr:postcode":"33015",
    "addr:street":"Nw 67Th Ave",
    "iso:country":"US",
    "sg:address":"18750 NW 67th Ave",
    "sg:city":"Hialeah",
    "sg:classifiers":[
        {
            "category":"Restaurant",
            "type":"Food & Drink"
        }
    ],
    "sg:menulink":"http://www.allmenus.com/fl/hialeah/207466-taco-bell/menu/",
    "sg:phone":"+1 305 620 7146",
    "sg:postcode":"33015",
    "sg:province":"FL",
    "sg:tags":[
        "mexican"
    ],
    "wof:name":"Taco Bell",
    "wof:placetype":"venue"
},
  "geometry": {"coordinates":[-80.30709899999999,25.944057],"type":"Point"}
}