{
  "type": "Feature",
  "properties": {
    "addr:full":"311 SW 182nd Way Hollywood FL 33029",
    "addr:housenumber":"311",
    "addr:postcode":"33029",
    "addr:street":"Sw 182Nd Way",
    "iso:country":"US",
    "sg:address":"311 SW 182nd Way",
    "sg:city":"Hollywood",
    "sg:classifiers":[
        {
            "category":"Freight",
            "type":"Transportation"
        }
    ],
    "sg:phone":"+1 954 442 9454",
    "sg:postcode":"33029",
    "sg:province":"FL",
    "sg:tags":[
        "operator",
        "local",
        "trucking"
    ],
    "wof:name":"JC Morales Trucking Inc",
    "wof:placetype":"venue"
},
  "geometry": {"coordinates":[-80.388383,26.002901],"type":"Point"}
}