{
  "type": "Feature",
  "properties": {
    "addr:full":"2300 SW 60th Ter Hollywood FL 33023",
    "addr:housenumber":"2300",
    "addr:postcode":"33023",
    "addr:street":"Sw 60Th Ter",
    "iso:country":"US",
    "sg:address":"2300 SW 60th Ter",
    "sg:city":"Hollywood",
    "sg:classifiers":[
        {
            "category":"Retail",
            "subcategory":"Repair Shop",
            "type":"Services"
        }
    ],
    "sg:phone":"+1 954 963 6555",
    "sg:postcode":"33023",
    "sg:province":"FL",
    "sg:tags":[
        "refinishing",
        "furniture"
    ],
    "wof:name":"B & R Refinishing",
    "wof:placetype":"venue"
},
  "geometry": {"coordinates":[-80.20761299999999,25.987993],"type":"Point"}
}