{
  "type": "Feature",
  "properties": {
    "addr:full":"2351 NW 97th Ave Doral FL 33172",
    "addr:housenumber":"2351",
    "addr:postcode":"33172",
    "addr:street":"Nw 97Th Ave",
    "iso:country":"US",
    "sg:address":"2351 NW 97th Ave",
    "sg:city":"Doral",
    "sg:classifiers":[
        {
            "category":"Utilities",
            "subcategory":"Cable",
            "type":"Services"
        }
    ],
    "sg:phone":"+1 305 436 0886",
    "sg:postcode":"33172",
    "sg:province":"FL",
    "sg:tags":[
        "television"
    ],
    "wof:name":"Sti Operations",
    "wof:placetype":"venue"
},
  "geometry": {"coordinates":[-80.352874,25.791703],"type":"Point"}
}