{
  "type": "Feature",
  "properties": {
    "iso:country":"US",
    "sg:address":"1842 Joyce St",
    "sg:city":"Sarasota",
    "sg:classifiers":[
        {
            "category":"Real Estate",
            "subcategory":"Real Estate Agent",
            "type":"Services"
        }
    ],
    "sg:phone":"+1 941 966 5317",
    "sg:postcode":"34231",
    "sg:province":"FL",
    "wof:name":"Waterbird Co",
    "wof:placetype":"venue"
},
  "geometry": {"coordinates":[-82.49450299999999,27.222768],"type":"Point"}
}