{
  "type": "Feature",
  "properties": {
    "addr:full":"3101 Justina Rd Jacksonville FL 32277",
    "addr:housenumber":"3101",
    "addr:postcode":"32277",
    "addr:street":"Justina Rd",
    "iso:country":"US",
    "sg:address":"3101 Justina Rd",
    "sg:city":"Jacksonville",
    "sg:classifiers":[
        {
            "category":"Sports & Exercise",
            "subcategory":"Sports Center",
            "type":"Entertainment"
        }
    ],
    "sg:phone":"+1 904 743 3111",
    "sg:postcode":"32277",
    "sg:province":"FL",
    "sg:tags":[
        "manager",
        "promoter"
    ],
    "wof:name":"Justina Athletic",
    "wof:placetype":"venue"
},
  "geometry": {"coordinates":[-81.600303,30.356321],"type":"Point"}
}