{
  "type": "Feature",
  "properties": {
    "addr:full":"1040 E Caroline Blvd Panama City FL 32401",
    "addr:housenumber":"1040",
    "addr:postcode":"32401",
    "addr:street":"E Caroline Blvd",
    "iso:country":"US",
    "sg:address":"1040 E Caroline Blvd",
    "sg:city":"Panama City",
    "sg:classifiers":[
        {
            "category":"Insurance",
            "subcategory":"Hazard Insurance",
            "type":"Services"
        }
    ],
    "sg:phone":"+1 850 872 8700",
    "sg:postcode":"32401",
    "sg:province":"FL",
    "sg:tags":[
        "bond"
    ],
    "wof:name":"Barbara Farmer Bail Bonds",
    "wof:placetype":"venue"
},
  "geometry": {"coordinates":[-85.68164899999999,30.166],"type":"Point"}
}