{
  "type": "Feature",
  "properties": {
    "addr:full":"1236 42nd Ave Vero Beach FL 32960",
    "addr:housenumber":"1236",
    "addr:postcode":"32960",
    "addr:street":"42Nd Ave",
    "iso:country":"US",
    "sg:address":"1236 42nd Ave",
    "sg:city":"Vero Beach",
    "sg:classifiers":[
        {
            "category":"Education",
            "subcategory":"Special Training",
            "type":"Public Place"
        }
    ],
    "sg:phone":"+1 772 562 3936",
    "sg:postcode":"32960",
    "sg:province":"FL",
    "wof:name":"Spevsqsa Bur Vero Bch Chapter",
    "wof:placetype":"venue"
},
  "geometry": {"coordinates":[-80.428777,27.625464],"type":"Point"}
}