{
  "type": "Feature",
  "properties": {
    "iso:country":"US",
    "sg:address":"315 W Grant St",
    "sg:city":"Orlando",
    "sg:classifiers":[
        {
            "category":"Shopping",
            "subcategory":"Music",
            "type":"Retail Goods"
        }
    ],
    "sg:phone":"+1 407 425 3332",
    "sg:postcode":"32806",
    "sg:province":"FL",
    "sg:tags":[
        "backing",
        "track",
        "audio",
        "tape"
    ],
    "wof:name":"All Amrican Sing A Long Entrmt",
    "wof:placetype":"venue"
},
  "geometry": {"coordinates":[-81.38376,28.516589],"type":"Point"}
}