{
  "type": "Feature",
  "properties": {
    "addr:full":"330 S Parrott Ave Okeechobee FL 34974",
    "addr:housenumber":"330",
    "addr:postcode":"34974",
    "addr:street":"S Parrott Ave",
    "iso:country":"US",
    "sg:address":"330 S Parrott Ave",
    "sg:city":"Okeechobee",
    "sg:classifiers":[
        {
            "category":"Food & Beverages",
            "subcategory":"Groceries & Convenience Stores",
            "type":"Retail Goods"
        }
    ],
    "sg:phone":"+1 863 467 1091",
    "sg:postcode":"34974",
    "sg:province":"FL",
    "sg:tags":[
        "grocer"
    ],
    "wof:name":"U-Save Supermarket 30",
    "wof:placetype":"venue"
},
  "geometry": {"coordinates":[-80.82996900000001,27.240776],"type":"Point"}
}