{
  "type": "Feature",
  "properties": {
    "addr:full":"521 Lake Ave Lake Worth FL 33460",
    "addr:housenumber":"521",
    "addr:postcode":"33460",
    "addr:street":"Lake Ave",
    "iso:country":"US",
    "sg:address":"521 Lake Ave",
    "sg:city":"Lake Worth",
    "sg:classifiers":[
        {
            "category":"Banks & Credit Unions",
            "subcategory":"Bank",
            "type":"Services"
        }
    ],
    "sg:phone":"+1 561 586 3645",
    "sg:postcode":"33460",
    "sg:province":"FL",
    "sg:tags":[
        "loan",
        "mortgage",
        "real estate"
    ],
    "sg:website":"www.complianceconsultingcorp.com",
    "wof:name":"Compliance Consulting Corp Fla",
    "wof:placetype":"venue"
},
  "geometry": {"coordinates":[-80.05420700000001,26.615747],"type":"Point"}
}