{
  "type": "Feature",
  "properties": {
    "iso:country":"US",
    "sg:address":"9446 Sacramento Dr",
    "sg:city":"New Port Richey",
    "sg:classifiers":[
        {
            "category":"Retail",
            "subcategory":"Laundry & Dry Cleaning",
            "type":"Services"
        }
    ],
    "sg:phone":"+1 727 372 8136",
    "sg:postcode":"34655",
    "sg:province":"FL",
    "wof:name":"Moon Carpet Cleaning",
    "wof:placetype":"venue"
},
  "geometry": {"coordinates":[-82.658539,28.223007],"type":"Point"}
}