{
  "type": "Feature",
  "properties": {
    "iso:country":"US",
    "sg:address":"926 W Tharpe St",
    "sg:city":"Tallahassee",
    "sg:classifiers":[
        {
            "category":"Social Services",
            "type":"Services"
        }
    ],
    "sg:phone":"+1 850 878 5227",
    "sg:postcode":"32303",
    "sg:province":"FL",
    "sg:tags":[
        "organization",
        "welfare"
    ],
    "wof:name":"Resources For Human Dvlpmnt",
    "wof:placetype":"venue"
},
  "geometry": {"coordinates":[-84.298473,30.463727],"type":"Point"}
}