{
  "type": "Feature",
  "properties": {
    "iso:country":"US",
    "sg:address":"3221 Glendale Blvd",
    "sg:city":"Fort Lauderdale",
    "sg:classifiers":[
        {
            "category":"Organizations",
            "subcategory":"Community Association",
            "type":"Services"
        }
    ],
    "sg:phone":"+1 954 583 0702",
    "sg:postcode":"33312",
    "sg:province":"FL",
    "wof:name":"Eagles Cove Villa Inc",
    "wof:placetype":"venue"
},
  "geometry": {"coordinates":[-80.188552,26.114045],"type":"Point"}
}