{
  "type": "Feature",
  "properties": {
    "addr:full":"1111 Lincoln Rd 4th Fl Miami Beach FL 33139",
    "addr:housenumber":"1111",
    "addr:postcode":"33139",
    "addr:street":"Lincoln Rd",
    "iso:country":"US",
    "sg:address":"1111 Lincoln Rd 4th Fl",
    "sg:city":"Miami Beach",
    "sg:classifiers":[
        {
            "category":"Sports & Exercise",
            "subcategory":"Bicycle Rental",
            "type":"Entertainment"
        }
    ],
    "sg:phone":"+1 305 767 3841",
    "sg:postcode":"33139",
    "sg:province":"FL",
    "sg:tags":[
        "bike"
    ],
    "sg:website":"www.thesobescooters.com",
    "wof:name":"Sobe Scooters",
    "wof:placetype":"venue"
},
  "geometry": {"coordinates":[-80.141042,25.790728],"type":"Point"}
}