{
  "type": "Feature",
  "properties": {
    "iso:country":"US",
    "sg:address":"10041 Southwest 37th Terrace",
    "sg:city":"Miami",
    "sg:classifiers":[
        {
            "category":"Building & Trades",
            "subcategory":"Plumbing",
            "type":"Services"
        }
    ],
    "sg:phone":"+1 305 905 0385",
    "sg:postcode":"33165",
    "sg:province":"FL",
    "wof:name":"Busy Bee Septic",
    "wof:placetype":"venue"
},
  "geometry": {"coordinates":[-80.358563,25.734882],"type":"Point"}
}