{
  "type": "Feature",
  "properties": {
    "iso:country":"US",
    "sg:address":"1605 Fruitville Rd",
    "sg:city":"Sarasota",
    "sg:classifiers":[
        {
            "category":"Shopping",
            "subcategory":"Used Merchandise",
            "type":"Retail Goods"
        }
    ],
    "sg:phone":"+1 941 954 0042",
    "sg:postcode":"34236",
    "sg:province":"FL",
    "sg:tags":[
        "antique"
    ],
    "wof:name":"French Horn",
    "wof:placetype":"venue"
},
  "geometry": {"coordinates":[-82.53764200000001,27.338951],"type":"Point"}
}