{
  "type": "Feature",
  "properties": {
    "addr:full":"4566 Hiatus Rd Sunrise FL 33351",
    "addr:housenumber":"4566",
    "addr:postcode":"33351",
    "addr:street":"Hiatus Rd",
    "iso:country":"US",
    "sg:address":"4566 Hiatus Rd",
    "sg:city":"Sunrise",
    "sg:classifiers":[
        {
            "category":"Food & Beverages",
            "subcategory":"Groceries & Convenience Stores",
            "type":"Retail Goods"
        }
    ],
    "sg:phone":"+1 954 749 3965",
    "sg:postcode":"33351",
    "sg:province":"FL",
    "sg:tags":[
        "product"
    ],
    "wof:name":"Sunland Foods",
    "wof:placetype":"venue"
},
  "geometry": {"coordinates":[-80.290825,26.180213],"type":"Point"}
}