{
  "type": "Feature",
  "properties": {
    "iso:country":"US",
    "sg:address":"1309 S Flagler Dr",
    "sg:city":"West Palm Beach",
    "sg:classifiers":[
        {
            "category":"Health Services",
            "subcategory":"Doctor",
            "type":"Services"
        }
    ],
    "sg:phone":"+1 561 366 4131",
    "sg:postcode":"33401",
    "sg:province":"FL",
    "sg:tags":[
        "medical",
        "hospital"
    ],
    "wof:name":"Rothschild Neal E MD",
    "wof:placetype":"venue"
},
  "geometry": {"coordinates":[-80.050504,26.701092],"type":"Point"}
}