{
  "type": "Feature",
  "properties": {
    "iso:country":"US",
    "sg:address":"7900 Island Blvd",
    "sg:city":"Aventura",
    "sg:classifiers":[
        {
            "category":"Sports & Exercise",
            "subcategory":"Golf",
            "type":"Entertainment"
        }
    ],
    "sg:phone":"+1 305 651 5100",
    "sg:postcode":"33160",
    "sg:province":"FL",
    "wof:name":"Williams Island Country Club",
    "wof:placetype":"venue"
},
  "geometry": {"coordinates":[-80.136002,25.944099],"type":"Point"}
}