{
  "type": "Feature",
  "properties": {
    "iso:country":"US",
    "sg:address":"3815 7th Pl",
    "sg:city":"Vero Beach",
    "sg:classifiers":[
        {
            "category":"Professional",
            "subcategory":"Advertising",
            "type":"Services"
        }
    ],
    "sg:phone":"+1 772 562 0140",
    "sg:postcode":"32968",
    "sg:province":"FL",
    "sg:tags":[
        "mail",
        "direct"
    ],
    "wof:name":"Val Pak",
    "wof:placetype":"venue"
},
  "geometry": {"coordinates":[-80.42524899999999,27.614934],"type":"Point"}
}