{
  "type": "Feature",
  "properties": {
    "iso:country":"US",
    "sg:address":"15864 Brothers Ct",
    "sg:city":"Fort Myers",
    "sg:classifiers":[
        {
            "category":"Retail",
            "subcategory":"Auto Repair",
            "type":"Services"
        }
    ],
    "sg:phone":"+1 239 482 1582",
    "sg:postcode":"33912",
    "sg:province":"FL",
    "sg:tags":[
        "body"
    ],
    "wof:name":"South Point",
    "wof:placetype":"venue"
},
  "geometry": {"coordinates":[-81.85823000000001,26.511988],"type":"Point"}
}