{
  "type": "Feature",
  "properties": {
    "iso:country":"US",
    "sg:address":"3584 Progress Ave",
    "sg:city":"Naples",
    "sg:classifiers":[
        {
            "category":"Professional",
            "type":"Services"
        }
    ],
    "sg:phone":"+1 239 659 2776",
    "sg:postcode":"34104",
    "sg:province":"FL",
    "sg:tags":[
        "establishment"
    ],
    "wof:name":"Alumapro LLC",
    "wof:placetype":"venue"
},
  "geometry": {"coordinates":[-81.76109700000001,26.164211],"type":"Point"}
}