{
  "type": "Feature",
  "properties": {
    "iso:country":"US",
    "sg:address":"4749 W Irlo Bronson Memorial Hwy",
    "sg:city":"Kissimmee",
    "sg:classifiers":[
        {
            "category":"Professional",
            "subcategory":"Management & Consulting",
            "type":"Services"
        }
    ],
    "sg:phone":"+1 407 396 6699",
    "sg:postcode":"34746",
    "sg:province":"FL",
    "sg:tags":[
        "marketing",
        "consultant"
    ],
    "wof:name":"VIP Marketing Group",
    "wof:placetype":"venue"
},
  "geometry": {"coordinates":[-81.470719,28.325391],"type":"Point"}
}