{
  "type": "Feature",
  "properties": {
    "addr:full":"580 Busch Dr Jacksonville FL 32218",
    "addr:housenumber":"580",
    "addr:postcode":"32218",
    "addr:street":"Busch Dr",
    "iso:country":"US",
    "sg:address":"580 Busch Dr",
    "sg:city":"Jacksonville",
    "sg:classifiers":[
        {
            "category":"Restaurant",
            "type":"Food & Drink"
        }
    ],
    "sg:menulink":"http://www.allmenus.com/fl/jacksonville/43488-waffle-house/menu/",
    "sg:phone":"+1 904 757 8668",
    "sg:postcode":"32218",
    "sg:province":"FL",
    "sg:tags":[
        "american",
        "diner"
    ],
    "wof:name":"Waffle House",
    "wof:placetype":"venue"
},
  "geometry": {"coordinates":[-81.654144,30.429948],"type":"Point"}
}