{
  "type": "Feature",
  "properties": {
    "addr:full":"11244 Lorence Ave Jacksonville FL 32218",
    "addr:housenumber":"11244",
    "addr:postcode":"32218",
    "addr:street":"Lorence Ave",
    "iso:country":"US",
    "sg:address":"11244 Lorence Ave",
    "sg:city":"Jacksonville",
    "sg:classifiers":[
        {
            "category":"Freight",
            "type":"Transportation"
        }
    ],
    "sg:phone":"+1 904 768 9526",
    "sg:postcode":"32218",
    "sg:province":"FL",
    "sg:tags":[
        "operator",
        "trucking"
    ],
    "wof:name":"Leroy E Cox Services",
    "wof:placetype":"venue"
},
  "geometry": {"coordinates":[-81.69554100000001,30.443695],"type":"Point"}
}