{
  "type": "Feature",
  "properties": {
    "iso:country":"US",
    "sg:address":"8036 Walt Williams Rd",
    "sg:city":"Lakeland",
    "sg:classifiers":[
        {
            "category":"Freight",
            "type":"Transportation"
        }
    ],
    "sg:phone":"+1 863 815 4933",
    "sg:postcode":"33809",
    "sg:province":"FL",
    "sg:tags":[
        "operator",
        "local",
        "trucking"
    ],
    "wof:name":"S & W Trucking Inc",
    "wof:placetype":"venue"
},
  "geometry": {"coordinates":[-81.926177,28.147852],"type":"Point"}
}