{
  "type": "Feature",
  "properties": {
    "addr:full":"1616 12th St W Palmetto FL 34221",
    "addr:housenumber":"1616",
    "addr:postcode":"34221",
    "addr:street":"12Th St W",
    "iso:country":"US",
    "sg:address":"1616 12th St W",
    "sg:city":"Palmetto",
    "sg:classifiers":[
        {
            "category":"Building & Trades",
            "subcategory":"Construction",
            "type":"Services"
        }
    ],
    "sg:phone":"+1 941 721 9717",
    "sg:postcode":"34221",
    "sg:province":"FL",
    "sg:tags":[
        "house"
    ],
    "wof:name":"Jack Weaks Construction",
    "wof:placetype":"venue"
},
  "geometry": {"coordinates":[-82.58439799999999,27.523193],"type":"Point"}
}