{
  "type": "Feature",
  "properties": {
    "iso:country":"US",
    "sg:address":"9999 NE 2nd Ave",
    "sg:city":"Miami Shores",
    "sg:classifiers":[
        {
            "category":"Health Services",
            "subcategory":"Doctor",
            "type":"Services"
        }
    ],
    "sg:phone":"+1 305 757 1559",
    "sg:postcode":"33138",
    "sg:province":"FL",
    "sg:tags":[
        "orthopedist"
    ],
    "wof:name":"Ziegler Gary S MD Faaos",
    "wof:placetype":"venue"
},
  "geometry": {"coordinates":[-80.19360399999999,25.867201],"type":"Point"}
}