{
  "type": "Feature",
  "properties": {
    "addr:full":"15014 US Hwy 19 Hudson FL 34667",
    "addr:postcode":"15014;34667",
    "addr:street":"Us Hwy 19",
    "iso:country":"US",
    "sg:address":"15014 US Hwy 19",
    "sg:city":"Hudson",
    "sg:classifiers":[
        {
            "category":"Food & Beverages",
            "subcategory":"Groceries & Convenience Stores",
            "type":"Retail Goods"
        }
    ],
    "sg:phone":"+1 727 863 8649",
    "sg:postcode":"34667",
    "sg:province":"FL",
    "sg:website":"www.7eleven.com",
    "wof:name":"7-Eleven",
    "wof:placetype":"venue"
},
  "geometry": {"coordinates":[-82.68264499999999,28.375382],"type":"Point"}
}