{
  "type": "Feature",
  "properties": {
    "iso:country":"US",
    "sg:address":"6984 Collins Ave",
    "sg:city":"Miami Beach",
    "sg:classifiers":[
        {
            "category":"Restaurant",
            "type":"Food & Drink"
        }
    ],
    "sg:phone":"+1 305 868 7001",
    "sg:postcode":"33141",
    "sg:province":"FL",
    "sg:tags":[
        "eating"
    ],
    "wof:name":"Mangia Mangia",
    "wof:placetype":"venue"
},
  "geometry": {"coordinates":[-80.12051599999999,25.854727],"type":"Point"}
}