{
  "type": "Feature",
  "properties": {
    "iso:country":"US",
    "sg:address":"5900 Georgia Ave",
    "sg:city":"West Palm Beach",
    "sg:classifiers":[
        {
            "category":"Local Transit",
            "type":"Transportation"
        }
    ],
    "sg:phone":"+1 561 655 6626",
    "sg:postcode":"33405",
    "sg:province":"FL",
    "sg:tags":[
        "airport"
    ],
    "wof:name":"Palm Beach Tours & Trnsprtn",
    "wof:placetype":"venue"
},
  "geometry": {"coordinates":[-80.058899,26.661101],"type":"Point"}
}