{
  "type": "Feature",
  "properties": {
    "addr:full":"7689 Doubleton Dr Delray Beach FL 33446",
    "addr:housenumber":"7689",
    "addr:postcode":"33446",
    "addr:street":"Doubleton Dr",
    "iso:country":"US",
    "sg:address":"7689 Doubleton Dr",
    "sg:city":"Delray Beach",
    "sg:classifiers":[
        {
            "category":"Building & Trades",
            "subcategory":"Electrical",
            "type":"Services"
        }
    ],
    "sg:phone":"+1 561 637 2504",
    "sg:postcode":"33446",
    "sg:province":"FL",
    "sg:tags":[
        "electrical",
        "contractor"
    ],
    "wof:name":"Positive Electric Inc",
    "wof:placetype":"venue"
},
  "geometry": {"coordinates":[-80.16532599999999,26.47486],"type":"Point"}
}