{
  "type": "Feature",
  "properties": {
    "iso:country":"US",
    "sg:address":"4200 NW 21 St",
    "sg:city":"Miami",
    "sg:classifiers":[
        {
            "category":"Airline",
            "type":"Transportation"
        },
        {
            "category":"Travel",
            "subcategory":"Travel Agent",
            "type":"Entertainment"
        }
    ],
    "sg:phone":"+1 305 917 1602",
    "sg:postcode":"33142",
    "sg:province":"FL",
    "sg:tags":[
        "airport"
    ],
    "sg:website":"www.miamiprivatejetcharter.com",
    "wof:name":"Miami Private Jet Charter",
    "wof:placetype":"venue"
},
  "geometry": {"coordinates":[-80.230233,25.813881],"type":"Point"}
}