{
  "type": "Feature",
  "properties": {
    "iso:country":"US",
    "sg:address":"4016 Dover Rd",
    "sg:city":"Jacksonville",
    "sg:classifiers":[
        {
            "category":"Shopping",
            "subcategory":"Used Merchandise",
            "type":"Retail Goods"
        }
    ],
    "sg:phone":"+1 904 636 8829",
    "sg:postcode":"32207",
    "sg:province":"FL",
    "wof:name":"At A One Time",
    "wof:placetype":"venue"
},
  "geometry": {"coordinates":[-81.652812,30.278603],"type":"Point"}
}