{
  "type": "Feature",
  "properties": {
    "addr:full":"1909 Grimes Ln Tallahassee FL 32303",
    "addr:housenumber":"1909",
    "addr:postcode":"32303",
    "addr:street":"Grimes Ln",
    "iso:country":"US",
    "sg:address":"1909 Grimes Ln",
    "sg:city":"Tallahassee",
    "sg:classifiers":[
        {
            "category":"Building & Trades",
            "subcategory":"Cleaning & Sanitation",
            "type":"Services"
        }
    ],
    "sg:phone":"+1 850 668 2610",
    "sg:postcode":"32303",
    "sg:province":"FL",
    "sg:tags":[
        "janitor"
    ],
    "wof:name":"Abracadabra Service",
    "wof:placetype":"venue"
},
  "geometry": {"coordinates":[-84.34273899999999,30.467225],"type":"Point"}
}