{
  "type": "Feature",
  "properties": {
    "addr:full":"101 N Woodland Blvd Deland FL 32720",
    "addr:housenumber":"101",
    "addr:postcode":"32720",
    "addr:street":"N Woodland Blvd",
    "iso:country":"US",
    "sg:address":"101 N Woodland Blvd",
    "sg:city":"Deland",
    "sg:classifiers":[
        {
            "category":"Professional",
            "subcategory":"Lawyer & Legal Services",
            "type":"Services"
        }
    ],
    "sg:phone":"+1 386 738 9030",
    "sg:postcode":"32720",
    "sg:province":"FL",
    "wof:name":"Charlton Kathlyn J Atty",
    "wof:placetype":"venue"
},
  "geometry": {"coordinates":[-81.329399,29.027901],"type":"Point"}
}