{
  "type": "Feature",
  "properties": {
    "iso:country":"US",
    "sg:address":"311 Aulin Ave - Sutie 200",
    "sg:city":"Oviedo",
    "sg:classifiers":[
        {
            "category":"Professional",
            "subcategory":"Engineering",
            "type":"Services"
        },
        {
            "category":"Home & Garden",
            "subcategory":"Building Materials",
            "type":"Retail Goods"
        },
        {
            "category":"Building & Trades",
            "subcategory":"Construction",
            "type":"Services"
        }
    ],
    "sg:phone":"+1 407 365 9521",
    "sg:postcode":"32765",
    "sg:province":"FL",
    "sg:tags":[
        "system",
        "specialty",
        "heating",
        "contractor",
        "equipment",
        "air conditioning"
    ],
    "sg:website":"http://find.trane.com/tcs-dealer-455494?utm_source=YP&utm_medium=banner&utm_campaign=TL",
    "wof:name":"Lukas Refrig. & Air Cond.",
    "wof:placetype":"venue"
},
  "geometry": {"coordinates":[-81.21883,28.6657],"type":"Point"}
}