{
  "type": "Feature",
  "properties": {
    "addr:full":"2535 SW 125th Ct Miami FL 33175",
    "addr:housenumber":"2535",
    "addr:postcode":"33175",
    "addr:street":"Sw 125Th Ct",
    "iso:country":"US",
    "sg:address":"2535 SW 125th Ct",
    "sg:city":"Miami",
    "sg:classifiers":[
        {
            "category":"Communications",
            "subcategory":"Film & Video Production",
            "type":"Services"
        },
        {
            "category":"Communications",
            "subcategory":"Television Station",
            "type":"Services"
        }
    ],
    "sg:phone":"+1 305 572 0525",
    "sg:postcode":"33175",
    "sg:province":"FL",
    "sg:tags":[
        "tv",
        "commercials-radio",
        "radio",
        "companies-film"
    ],
    "sg:website":"http://www.clearimagecreative.com",
    "wof:name":"Clear Image Creative Group Inc",
    "wof:placetype":"venue"
},
  "geometry": {"coordinates":[-80.39846799999999,25.744514],"type":"Point"}
}