{
  "type": "Feature",
  "properties": {
    "iso:country":"US",
    "sg:address":"2545 W 80th St",
    "sg:city":"Hialeah",
    "sg:classifiers":[
        {
            "category":"Wholesale",
            "subcategory":"Non-durable Goods",
            "type":"Manufacturing & Wholesale Goods"
        }
    ],
    "sg:phone":"+1 305 717 3397",
    "sg:postcode":"33016",
    "sg:province":"FL",
    "wof:name":"Integra Business Solutions",
    "wof:placetype":"venue"
},
  "geometry": {"coordinates":[-80.33540000000001,25.895235],"type":"Point"}
}