{
  "type": "Feature",
  "properties": {
    "iso:country":"US",
    "sg:address":"9460 Tangerine Pl",
    "sg:city":"Davie",
    "sg:classifiers":[
        {
            "category":"Banks & Credit Unions",
            "subcategory":"Investment Brokerage",
            "type":"Services"
        }
    ],
    "sg:phone":"+1 954 723 9594",
    "sg:postcode":"33324",
    "sg:province":"FL",
    "sg:tags":[
        "consultant",
        "financing"
    ],
    "wof:name":"Trufelli Finance Consultants",
    "wof:placetype":"venue"
},
  "geometry": {"coordinates":[-80.27175699999999,26.101017],"type":"Point"}
}