{
  "type": "Feature",
  "properties": {
    "iso:country":"US",
    "sg:address":"82229 Overseas Hwy",
    "sg:city":"Islamorada",
    "sg:classifiers":[
        {
            "category":"Home & Garden",
            "subcategory":"Home Furnishings",
            "type":"Retail Goods"
        }
    ],
    "sg:phone":"+1 305 517 4110",
    "sg:postcode":"33036",
    "sg:province":"FL",
    "wof:name":"Island Ceramics Studio",
    "wof:placetype":"venue"
},
  "geometry": {"coordinates":[-80.62807599999999,24.924376],"type":"Point"}
}