{
  "type": "Feature",
  "properties": {
    "addr:full":"759 Dodecanese Blvd Tarpon Springs FL 34689",
    "addr:housenumber":"759",
    "addr:postcode":"34689",
    "addr:street":"Dodecanese Blvd",
    "iso:country":"US",
    "sg:address":"759 Dodecanese Blvd",
    "sg:city":"Tarpon Springs",
    "sg:classifiers":[
        {
            "category":"Shopping",
            "subcategory":"Gifts & Souvenirs",
            "type":"Retail Goods"
        }
    ],
    "sg:phone":"+1 727 938 1905",
    "sg:postcode":"34689",
    "sg:province":"FL",
    "sg:tags":[
        "shop"
    ],
    "wof:name":"Yia Yia's",
    "wof:placetype":"venue"
},
  "geometry": {"coordinates":[-82.761071,28.155486],"type":"Point"}
}