{
  "type": "Feature",
  "properties": {
    "iso:country":"US",
    "sg:address":"6101 NW 54 Way",
    "sg:city":"Gainesville",
    "sg:classifiers":[
        {
            "category":"Professional",
            "type":"Services"
        }
    ],
    "sg:phone":"+1 352 372 1131",
    "sg:postcode":"32653",
    "sg:province":"FL",
    "wof:name":"Classroom Nature",
    "wof:placetype":"venue"
},
  "geometry": {"coordinates":[-82.403131,29.714308],"type":"Point"}
}