{
  "type": "Feature",
  "properties": {
    "iso:country":"US",
    "sg:address":"1 SE 3rd Ave",
    "sg:city":"Miami",
    "sg:classifiers":[
        {
            "category":"Professional",
            "subcategory":"Lawyer & Legal Services",
            "type":"Services"
        }
    ],
    "sg:phone":"+1 305 358 8400",
    "sg:postcode":"33131",
    "sg:province":"FL",
    "sg:tags":[
        "attorney"
    ],
    "wof:name":"Friedman & Heydasch",
    "wof:placetype":"venue"
},
  "geometry": {"coordinates":[-80.188964,25.773439],"type":"Point"}
}