{
  "type": "Feature",
  "properties": {
    "iso:country":"US",
    "sg:address":"13411 Gateway Dr",
    "sg:city":"Fort Myers",
    "sg:classifiers":[
        {
            "category":"Wholesale",
            "subcategory":"Vending Machines",
            "type":"Manufacturing & Wholesale Goods"
        }
    ],
    "sg:phone":"+1 239 433 3410",
    "sg:postcode":"33919",
    "sg:province":"FL",
    "wof:name":"Armstrong Vending Enterprises",
    "wof:placetype":"venue"
},
  "geometry": {"coordinates":[-81.893119,26.54767],"type":"Point"}
}