{
  "type": "Feature",
  "properties": {
    "addr:full":"412 N Dixie Hwy Lake Worth FL 33460",
    "addr:housenumber":"412",
    "addr:postcode":"33460",
    "addr:street":"N Dixie Hwy",
    "iso:country":"US",
    "sg:address":"412 N Dixie Hwy",
    "sg:city":"Lake Worth",
    "sg:classifiers":[
        {
            "category":"Insurance",
            "subcategory":"Insurance Agent",
            "type":"Services"
        }
    ],
    "sg:phone":"+1 561 586 0029",
    "sg:postcode":"33460",
    "sg:province":"FL",
    "sg:tags":[
        "agency"
    ],
    "wof:name":"B & B Insurance Agency Inc",
    "wof:placetype":"venue"
},
  "geometry": {"coordinates":[-80.057086,26.621343],"type":"Point"}
}