{
  "type": "Feature",
  "properties": {
    "addr:full":"1500 NE 131st St Miami FL 33161",
    "addr:housenumber":"1500",
    "addr:postcode":"33161",
    "addr:street":"Ne 131St St",
    "iso:country":"US",
    "sg:address":"1500 NE 131st St",
    "sg:city":"Miami",
    "sg:classifiers":[
        {
            "category":"Manufacturing",
            "subcategory":"Apparel",
            "type":"Manufacturing & Wholesale Goods"
        }
    ],
    "sg:phone":"+1 305 899 9006",
    "sg:postcode":"33161",
    "sg:province":"FL",
    "sg:tags":[
        "screen",
        "printing",
        "embroidery"
    ],
    "wof:name":"World Emblem International Inc",
    "wof:placetype":"venue"
},
  "geometry": {"coordinates":[-80.16779699999999,25.896547],"type":"Point"}
}