{
  "type": "Feature",
  "properties": {
    "iso:country":"US",
    "sg:address":"5731 NW 40th Ter",
    "sg:city":"Pompano Beach",
    "sg:classifiers":[
        {
            "category":"Travel",
            "subcategory":"Travel Agent",
            "type":"Entertainment"
        }
    ],
    "sg:phone":"+1 954 426 5003",
    "sg:postcode":"33073",
    "sg:province":"FL",
    "sg:tags":[
        "agency"
    ],
    "wof:name":"Tomorrows Solution Today",
    "wof:placetype":"venue"
},
  "geometry": {"coordinates":[-80.178636,26.300758],"type":"Point"}
}