{
  "type": "Feature",
  "properties": {
    "iso:country":"US",
    "sg:address":"13380 Cortez Blvd",
    "sg:city":"Brooksville",
    "sg:classifiers":[
        {
            "category":"Shopping",
            "type":"Retail Goods"
        }
    ],
    "sg:phone":"+1 727 849 7030",
    "sg:postcode":"34613",
    "sg:province":"FL",
    "sg:tags":[
        "telephone",
        "cellular"
    ],
    "wof:name":"Advance Cellular Inc",
    "wof:placetype":"venue"
},
  "geometry": {"coordinates":[-82.499848,28.533747],"type":"Point"}
}