{
  "type": "Feature",
  "properties": {
    "iso:country":"US",
    "sg:address":"2850 NW 27th Ave",
    "sg:city":"Miami",
    "sg:classifiers":[
        {
            "category":"Retail",
            "subcategory":"Auto Repair",
            "type":"Services"
        }
    ],
    "sg:phone":"+1 305 633 6062",
    "sg:postcode":"33142",
    "sg:province":"FL",
    "sg:tags":[
        "muffler",
        "exhaust",
        "system"
    ],
    "wof:name":"Mufflers Air Less Inc",
    "wof:placetype":"venue"
},
  "geometry": {"coordinates":[-80.240117,25.80213],"type":"Point"}
}