{
  "type": "Feature",
  "properties": {
    "iso:country":"US",
    "sg:address":"2825 Airport Pulling Rd N",
    "sg:city":"Naples",
    "sg:classifiers":[
        {
            "category":"Building & Trades",
            "subcategory":"Construction",
            "type":"Services"
        }
    ],
    "sg:phone":"+1 239 263 4208",
    "sg:postcode":"34105",
    "sg:province":"FL",
    "sg:tags":[
        "company"
    ],
    "wof:name":"Kraft Construction Co Inc",
    "wof:placetype":"venue"
},
  "geometry": {"coordinates":[-81.767605,26.185317],"type":"Point"}
}