{
  "type": "Feature",
  "properties": {
    "iso:country":"US",
    "sg:address":"1311 Bay St",
    "sg:city":"Kissimmee",
    "sg:classifiers":[
        {
            "category":"Professional",
            "subcategory":"Business Services",
            "type":"Services"
        }
    ],
    "sg:phone":"+1 407 847 5592",
    "sg:postcode":"34744",
    "sg:province":"FL",
    "sg:tags":[
        "interior",
        "window",
        "design",
        "treatment"
    ],
    "wof:name":"International Verticals Inc",
    "wof:placetype":"venue"
},
  "geometry": {"coordinates":[-81.401364,28.304344],"type":"Point"}
}