{
  "type": "Feature",
  "properties": {
    "iso:country":"US",
    "sg:address":"3541 N Lecanto Hwy",
    "sg:city":"Beverly Hills",
    "sg:classifiers":[
        {
            "category":"Professional",
            "type":"Services"
        }
    ],
    "sg:phone":"+1 352 746 3811",
    "sg:postcode":"34465",
    "sg:province":"FL",
    "sg:tags":[
        "establishment"
    ],
    "wof:name":"Spectrum Global Network",
    "wof:placetype":"venue"
},
  "geometry": {"coordinates":[-82.47128499999999,28.915792],"type":"Point"}
}