{
  "type": "Feature",
  "properties": {
    "addr:full":"4982 Palm Coast Pkwy NW Palm Coast FL 32137",
    "addr:housenumber":"4982",
    "addr:postcode":"32137",
    "addr:street":"Palm Coast Pkwy Nw",
    "iso:country":"US",
    "sg:address":"4982 Palm Coast Pkwy NW",
    "sg:city":"Palm Coast",
    "sg:classifiers":[
        {
            "category":"Home & Garden",
            "subcategory":"Home Furnishings",
            "type":"Retail Goods"
        }
    ],
    "sg:phone":"+1 386 446 5131",
    "sg:postcode":"32137",
    "sg:province":"FL",
    "sg:tags":[
        "fireplace"
    ],
    "wof:name":"Grill & Hearth Inc",
    "wof:placetype":"venue"
},
  "geometry": {"coordinates":[-81.23755199999999,29.5534],"type":"Point"}
}