{
  "type": "Feature",
  "properties": {
    "iso:country":"US",
    "sg:address":"101 E James Lee Blvd # 105",
    "sg:city":"Crestview",
    "sg:classifiers":[
        {
            "category":"Government",
            "subcategory":"Office",
            "type":"Public Place"
        }
    ],
    "sg:phone":"+1 850 689 5000",
    "sg:postcode":"32536",
    "sg:province":"FL",
    "sg:tags":[
        "government-state",
        "government-county",
        "parish"
    ],
    "sg:website":"http://www.okaloosa.k12.fl.us",
    "wof:name":"Okaloosa County Board",
    "wof:placetype":"venue"
},
  "geometry": {"coordinates":[-86.572884,30.761709],"type":"Point"}
}