{
  "type": "Feature",
  "properties": {
    "addr:full":"259 Ellis Rd S Jacksonville FL 32254",
    "addr:housenumber":"259",
    "addr:postcode":"32254",
    "addr:street":"Ellis Rd",
    "iso:country":"US",
    "sg:address":"259 Ellis Rd S",
    "sg:city":"Jacksonville",
    "sg:classifiers":[
        {
            "category":"Professional",
            "subcategory":"Advertising",
            "type":"Services"
        }
    ],
    "sg:phone":"+1 904 781 9284",
    "sg:postcode":"32254",
    "sg:province":"FL",
    "sg:tags":[
        "distribution"
    ],
    "wof:name":"Engine Distributors Inc",
    "wof:placetype":"venue"
},
  "geometry": {"coordinates":[-81.743566,30.320842],"type":"Point"}
}