{
  "type": "Feature",
  "properties": {
    "iso:country":"US",
    "sg:address":"5360 Palm Ave",
    "sg:city":"Hialeah",
    "sg:classifiers":[
        {
            "category":"Personal",
            "subcategory":"Beauty Salon",
            "type":"Services"
        }
    ],
    "sg:phone":"+1 305 822 2371",
    "sg:postcode":"33012",
    "sg:province":"FL",
    "sg:tags":[
        "hair",
        "stylist"
    ],
    "wof:name":"Salon Rubio",
    "wof:placetype":"venue"
},
  "geometry": {"coordinates":[-80.283191,25.871172],"type":"Point"}
}