{
  "type": "Feature",
  "properties": {
    "iso:country":"US",
    "sg:address":"9888 Universal Blvd",
    "sg:city":"Orlando",
    "sg:classifiers":[
        {
            "category":"Professional",
            "subcategory":"Business Services",
            "type":"Services"
        },
        {
            "category":"Conference Center",
            "type":"Public Place"
        }
    ],
    "sg:phone":"+1 407 685 5718",
    "sg:postcode":"32819",
    "sg:province":"FL",
    "sg:tags":[
        "convention",
        "facility",
        "supply"
    ],
    "wof:name":"Orange County Convention Center",
    "wof:placetype":"venue"
},
  "geometry": {"coordinates":[-81.443095,28.427629],"type":"Point"}
}