{
  "type": "Feature",
  "properties": {
    "iso:country":"US",
    "sg:address":"1787 Emerald Ln",
    "sg:city":"Middleburg",
    "sg:classifiers":[
        {
            "category":"Shopping",
            "subcategory":"Books",
            "type":"Retail Goods"
        }
    ],
    "sg:phone":"+1 904 276 2913",
    "sg:postcode":"32068",
    "sg:province":"FL",
    "sg:tags":[
        "technical",
        "dealer",
        "trade"
    ],
    "wof:name":"Horton Chilton Sales",
    "wof:placetype":"venue"
},
  "geometry": {"coordinates":[-81.787537,30.103029],"type":"Point"}
}