{
  "type": "Feature",
  "properties": {
    "iso:country":"US",
    "sg:address":"9984 Commodore Dr",
    "sg:city":"Seminole",
    "sg:classifiers":[
        {
            "category":"Building & Trades",
            "subcategory":"Construction",
            "type":"Services"
        }
    ],
    "sg:phone":"+1 727 393 9991",
    "sg:postcode":"33776",
    "sg:province":"FL",
    "sg:tags":[
        "contractor"
    ],
    "wof:name":"Gulf To Bay Contracting Inc",
    "wof:placetype":"venue"
},
  "geometry": {"coordinates":[-82.835066,27.863221],"type":"Point"}
}