{
  "type": "Feature",
  "properties": {
    "addr:full":"11160 SW 88th St Miami FL 33176",
    "addr:housenumber":"11160",
    "addr:postcode":"33176",
    "addr:street":"Sw 88Th St",
    "iso:country":"US",
    "sg:address":"11160 SW 88th St",
    "sg:city":"Miami",
    "sg:classifiers":[
        {
            "category":"Health Services",
            "subcategory":"Doctor",
            "type":"Services"
        }
    ],
    "sg:phone":"+1 786 263 0911",
    "sg:postcode":"33176",
    "sg:province":"FL",
    "sg:tags":[
        "practice",
        "family"
    ],
    "sg:website":"www.familyphysiciansofkendall.com",
    "wof:name":"Family Physicians of Kendall",
    "wof:placetype":"venue"
},
  "geometry": {"coordinates":[-80.37603799999999,25.6864],"type":"Point"}
}