{
  "type": "Feature",
  "properties": {
    "iso:country":"US",
    "sg:address":"4737 NW 72nd Ave",
    "sg:city":"Miami",
    "sg:classifiers":[
        {
            "category":"Government",
            "subcategory":"City Hall",
            "type":"Public Place"
        }
    ],
    "sg:phone":"+1 305 593 0288",
    "sg:postcode":"33166",
    "sg:province":"FL",
    "sg:tags":[
        "transfer",
        "express"
    ],
    "wof:name":"E C Transfer",
    "wof:placetype":"venue"
},
  "geometry": {"coordinates":[-80.313378,25.816498],"type":"Point"}
}