{
  "type": "Feature",
  "properties": {
    "addr:full":"1361 Alafaya Trl Oviedo FL 32765",
    "addr:housenumber":"1361",
    "addr:postcode":"32765",
    "addr:street":"Alafaya Trl",
    "iso:country":"US",
    "sg:address":"1361 Alafaya Trl",
    "sg:city":"Oviedo",
    "sg:classifiers":[
        {
            "category":"Ice Cream",
            "type":"Food & Drink"
        }
    ],
    "sg:menulink":"http://www.allmenus.com/fl/oviedo/184655-cold-stone-creamery/menu/",
    "sg:phone":"+1 407 359 9122",
    "sg:postcode":"32765",
    "sg:province":"FL",
    "sg:tags":[
        "smoothy",
        "juice",
        "american"
    ],
    "wof:name":"Cold Stone Creamery",
    "wof:placetype":"venue"
},
  "geometry": {"coordinates":[-81.20818300000001,28.650452],"type":"Point"}
}