{
  "type": "Feature",
  "properties": {
    "iso:country":"US",
    "sg:address":"225 NE Mizner Blvd",
    "sg:city":"Boca Raton",
    "sg:classifiers":[
        {
            "category":"Banks & Credit Unions",
            "subcategory":"Investment Brokerage",
            "type":"Services"
        }
    ],
    "sg:phone":"+1 561 672 4645",
    "sg:postcode":"33432",
    "sg:province":"FL",
    "sg:tags":[
        "security"
    ],
    "wof:name":"Millennium Capitl Partners LLC",
    "wof:placetype":"venue"
},
  "geometry": {"coordinates":[-80.08382400000001,26.352998],"type":"Point"}
}