{
  "type": "Feature",
  "properties": {
    "iso:country":"US",
    "sg:address":"25 E 4th St",
    "sg:city":"Hialeah",
    "sg:classifiers":[
        {
            "category":"Health Services",
            "subcategory":"Health Practitioner",
            "type":"Services"
        }
    ],
    "sg:phone":"+1 786 337 9898",
    "sg:postcode":"33010",
    "sg:province":"FL",
    "sg:tags":[
        "nutritionist",
        "dietitian"
    ],
    "wof:name":"International Nutrition Master",
    "wof:placetype":"venue"
},
  "geometry": {"coordinates":[-80.280957,25.825398],"type":"Point"}
}