{
  "type": "Feature",
  "properties": {
    "addr:full":"9293 Bay Pines Blvd St Petersburg FL 33708",
    "addr:housenumber":"9293",
    "addr:postcode":"33708",
    "addr:street":"Bay Pines Blvd",
    "iso:country":"US",
    "sg:address":"9293 Bay Pines Blvd",
    "sg:city":"St Petersburg",
    "sg:classifiers":[
        {
            "category":"Autos & Motor Vehicles",
            "subcategory":"Boat Sales",
            "type":"Retail Goods"
        }
    ],
    "sg:phone":"+1 727 398 8112",
    "sg:postcode":"33708",
    "sg:province":"FL",
    "sg:tags":[
        "dealer",
        "sales"
    ],
    "wof:name":"Keith's Marine",
    "wof:placetype":"venue"
},
  "geometry": {"coordinates":[-82.76897200000001,27.813928],"type":"Point"}
}