{
  "type": "Feature",
  "properties": {
    "iso:country":"US",
    "sg:address":"7370 Coldstream Dr",
    "sg:city":"Hialeah",
    "sg:classifiers":[
        {
            "category":"Professional",
            "subcategory":"Management & Consulting",
            "type":"Services"
        }
    ],
    "sg:phone":"+1 305 829 2995",
    "sg:postcode":"33015",
    "sg:province":"FL",
    "wof:name":"Itl",
    "wof:placetype":"venue"
},
  "geometry": {"coordinates":[-80.322022,25.953078],"type":"Point"}
}