{
  "type": "Feature",
  "properties": {
    "iso:country":"US",
    "sg:address":"4622 Lee Blvd",
    "sg:city":"Lehigh Acres",
    "sg:classifiers":[
        {
            "category":"Building & Trades",
            "subcategory":"Construction",
            "type":"Services"
        }
    ],
    "sg:phone":"+1 239 303 9108",
    "sg:postcode":"33971",
    "sg:province":"FL",
    "sg:tags":[
        "residential",
        "home"
    ],
    "wof:name":"Harden Homes",
    "wof:placetype":"venue"
},
  "geometry": {"coordinates":[-81.72024399999999,26.61682],"type":"Point"}
}