{
  "type": "Feature",
  "properties": {
    "iso:country":"US",
    "sg:address":"1207 Princeton Ave",
    "sg:city":"Bradenton",
    "sg:classifiers":[
        {
            "category":"Home & Garden",
            "subcategory":"Mobile Homes",
            "type":"Retail Goods"
        }
    ],
    "sg:phone":"+1 941 756 5474",
    "sg:postcode":"34207",
    "sg:province":"FL",
    "sg:tags":[
        "homes-repair"
    ],
    "wof:name":"Mitch's Mobile Home Service",
    "wof:placetype":"venue"
},
  "geometry": {"coordinates":[-82.581754,27.427687],"type":"Point"}
}