{
  "type": "Feature",
  "properties": {
    "iso:country":"US",
    "sg:address":"1300 Hand Ave",
    "sg:city":"Ormond Beach",
    "sg:classifiers":[
        {
            "category":"Building & Trades",
            "subcategory":"Cleaning & Sanitation",
            "type":"Services"
        }
    ],
    "sg:phone":"+1 386 295 2453",
    "sg:postcode":"32174",
    "sg:province":"FL",
    "sg:tags":[
        "maintenance"
    ],
    "wof:name":"Renees Cleaning Service",
    "wof:placetype":"venue"
},
  "geometry": {"coordinates":[-81.085989,29.261597],"type":"Point"}
}