{
  "type": "Feature",
  "properties": {
    "addr:full":"1514 W Hiawatha St Tampa FL 33604",
    "addr:housenumber":"1514",
    "addr:postcode":"33604",
    "addr:street":"W Hiawatha St",
    "iso:country":"US",
    "sg:address":"1514 W Hiawatha St",
    "sg:city":"Tampa",
    "sg:classifiers":[
        {
            "category":"Building & Trades",
            "subcategory":"Construction",
            "type":"Services"
        }
    ],
    "sg:phone":"+1 813 931 4995",
    "sg:postcode":"33604",
    "sg:province":"FL",
    "sg:tags":[
        "hanging",
        "contractor"
    ],
    "wof:name":"In Decorating Enterprises",
    "wof:placetype":"venue"
},
  "geometry": {"coordinates":[-82.47471400000001,28.009067],"type":"Point"}
}