{
  "type": "Feature",
  "properties": {
    "addr:full":"200 Plaza Dr Lehigh Acres FL 33936",
    "addr:housenumber":"200",
    "addr:postcode":"33936",
    "addr:street":"Plaza Dr",
    "iso:country":"US",
    "sg:address":"200 Plaza Dr",
    "sg:city":"Lehigh Acres",
    "sg:classifiers":[
        {
            "category":"Autos & Motor Vehicles",
            "subcategory":"Automobile Sales",
            "type":"Retail Goods"
        }
    ],
    "sg:phone":"+1 239 369 8657",
    "sg:postcode":"33936",
    "sg:province":"FL",
    "sg:tags":[
        "car",
        "used",
        "dealer"
    ],
    "wof:name":"Joyce Allen's Midtown Motors",
    "wof:placetype":"venue"
},
  "geometry": {"coordinates":[-81.651465,26.608214],"type":"Point"}
}