{
  "type": "Feature",
  "properties": {
    "iso:country":"US",
    "sg:address":"16019 Redington Dr",
    "sg:city":"Saint Petersburg",
    "sg:classifiers":[
        {
            "category":"Utilities",
            "subcategory":"Cable",
            "type":"Services"
        }
    ],
    "sg:phone":"+1 727 393 7371",
    "sg:postcode":"33708",
    "sg:province":"FL",
    "sg:tags":[
        "television"
    ],
    "wof:name":"Bellmore Enterprises Inc",
    "wof:placetype":"venue"
},
  "geometry": {"coordinates":[-82.810621,27.812241],"type":"Point"}
}