{
  "type": "Feature",
  "properties": {
    "iso:country":"US",
    "sg:address":"7123 Ayrshire Ln",
    "sg:city":"Boca Raton",
    "sg:classifiers":[
        {
            "category":"Banks & Credit Unions",
            "subcategory":"Financial Services",
            "type":"Services"
        }
    ],
    "sg:phone":"+1 561 482 6604",
    "sg:postcode":"33496",
    "sg:province":"FL",
    "sg:tags":[
        "investor"
    ],
    "wof:name":"Coleman Capital Corporation",
    "wof:placetype":"venue"
},
  "geometry": {"coordinates":[-80.155456,26.412545],"type":"Point"}
}