{
  "type": "Feature",
  "properties": {
    "addr:full":"547 Drage Dr Apopka FL 32703",
    "addr:housenumber":"547",
    "addr:postcode":"32703",
    "addr:street":"Drage Dr",
    "iso:country":"US",
    "sg:address":"547 Drage Dr",
    "sg:city":"Apopka",
    "sg:classifiers":[
        {
            "category":"Real Estate",
            "subcategory":"Real Estate Operator",
            "type":"Services"
        }
    ],
    "sg:phone":"+1 407 886 5776",
    "sg:postcode":"32703",
    "sg:province":"FL",
    "sg:tags":[
        "mobile",
        "home",
        "community"
    ],
    "wof:name":"Valencia Estates Mobile Home",
    "wof:placetype":"venue"
},
  "geometry": {"coordinates":[-81.544133,28.687965],"type":"Point"}
}