{
  "type": "Feature",
  "properties": {
    "addr:full":"10310 Lem Turner Rd Jacksonville FL 32218",
    "addr:postcode":"10310;32218",
    "addr:street":"Turner Rd",
    "iso:country":"US",
    "sg:address":"10310 Lem Turner Rd",
    "sg:city":"Jacksonville",
    "sg:classifiers":[
        {
            "category":"Social Services",
            "subcategory":"Child Care",
            "type":"Services"
        }
    ],
    "sg:phone":"+1 904 764 2113",
    "sg:postcode":"32218",
    "sg:province":"FL",
    "sg:tags":[
        "kindergarten",
        "academic",
        "school",
        "day"
    ],
    "wof:name":"Kidsmart Christian Learning",
    "wof:placetype":"venue"
},
  "geometry": {"coordinates":[-81.695988,30.422639],"type":"Point"}
}