{
  "type": "Feature",
  "properties": {
    "addr:full":"23186 Maclellan Ave Port Charlotte FL 33980",
    "addr:postcode":"23186;33980",
    "addr:street":"Maclellan Ave",
    "iso:country":"US",
    "sg:address":"23186 Maclellan Ave",
    "sg:city":"Port Charlotte",
    "sg:classifiers":[
        {
            "category":"Manufacturing",
            "subcategory":"Printing",
            "type":"Manufacturing & Wholesale Goods"
        }
    ],
    "sg:phone":"+1 941 286 8505",
    "sg:postcode":"33980",
    "sg:province":"FL",
    "sg:tags":[
        "publishing"
    ],
    "wof:name":"Brandon J Brown Publishing Co",
    "wof:placetype":"venue"
},
  "geometry": {"coordinates":[-82.06869500000001,26.988623],"type":"Point"}
}