{
  "type": "Feature",
  "properties": {
    "addr:full":"3685 Peddie Dr Tallahassee FL 32303",
    "addr:housenumber":"3685",
    "addr:postcode":"32303",
    "addr:street":"Peddie Dr",
    "iso:country":"US",
    "sg:address":"3685 Peddie Dr",
    "sg:city":"Tallahassee",
    "sg:classifiers":[
        {
            "category":"Retail",
            "subcategory":"Auto Repair",
            "type":"Services"
        }
    ],
    "sg:phone":"+1 850 575 4472",
    "sg:postcode":"32303",
    "sg:province":"FL",
    "sg:tags":[
        "transmission"
    ],
    "wof:name":"Performance Transmission Svc",
    "wof:placetype":"venue"
},
  "geometry": {"coordinates":[-84.35373,30.467844],"type":"Point"}
}