{
  "type": "Feature",
  "properties": {
    "addr:full":"4355 SE 115th St Belleview FL 34420",
    "addr:housenumber":"4355",
    "addr:postcode":"34420",
    "addr:street":"Se 115Th St",
    "iso:country":"US",
    "sg:address":"4355 SE 115th St",
    "sg:city":"Belleview",
    "sg:classifiers":[
        {
            "category":"Wholesale",
            "subcategory":"Machinery & Supplies",
            "type":"Manufacturing & Wholesale Goods"
        }
    ],
    "sg:phone":"+1 352 629 9526",
    "sg:postcode":"34420",
    "sg:province":"FL",
    "sg:tags":[
        "pump"
    ],
    "wof:name":"Robinson Water Conditioning",
    "wof:placetype":"venue"
},
  "geometry": {"coordinates":[-82.074957,29.055259],"type":"Point"}
}