{
  "type": "Feature",
  "properties": {
    "addr:full":"219 Juno St Jupiter FL 33458",
    "addr:housenumber":"219",
    "addr:postcode":"33458",
    "addr:street":"Juno St",
    "iso:country":"US",
    "sg:address":"219 Juno St",
    "sg:city":"Jupiter",
    "sg:classifiers":[
        {
            "category":"Autos & Motor Vehicles",
            "subcategory":"Fuel & Gas Station",
            "type":"Retail Goods"
        }
    ],
    "sg:phone":"+1 561 622 0195",
    "sg:postcode":"33458",
    "sg:province":"FL",
    "sg:tags":[
        "oil"
    ],
    "wof:name":"Eurostar Auto Svc & Repair",
    "wof:placetype":"venue"
},
  "geometry": {"coordinates":[-80.09727100000001,26.938509],"type":"Point"}
}