{
  "type": "Feature",
  "properties": {
    "iso:country":"US",
    "sg:address":"6188 Chesham Dr",
    "sg:city":"New Port Richey",
    "sg:classifiers":[
        {
            "category":"Arts & Performance",
            "subcategory":"Theater",
            "type":"Entertainment"
        }
    ],
    "sg:phone":"+1 727 845 0116",
    "sg:postcode":"34653",
    "sg:province":"FL",
    "sg:tags":[
        "group"
    ],
    "wof:name":"39 Stripes Inc",
    "wof:placetype":"venue"
},
  "geometry": {"coordinates":[-82.714901,28.219278],"type":"Point"}
}