{
  "type": "Feature",
  "properties": {
    "iso:country":"US",
    "sg:address":"606 Greenwood Dr",
    "sg:city":"Jupiter",
    "sg:classifiers":[
        {
            "category":"Building & Trades",
            "subcategory":"Construction",
            "type":"Services"
        }
    ],
    "sg:phone":"+1 561 848 6690",
    "sg:postcode":"33458",
    "sg:province":"FL",
    "sg:tags":[
        "excavating",
        "contractor"
    ],
    "wof:name":"Burns Bobcat & Backhoe Svc",
    "wof:placetype":"venue"
},
  "geometry": {"coordinates":[-80.114206,26.93925],"type":"Point"}
}