{
  "type": "Feature",
  "properties": {
    "iso:country":"US",
    "sg:address":"161 Emanuel Church Rd",
    "sg:city":"Bainbridge",
    "sg:classifiers":[
        {
            "category":"Organizations",
            "subcategory":"Religious Organization",
            "type":"Services"
        }
    ],
    "sg:phone":"+1 229 246 0824",
    "sg:postcode":"39819",
    "sg:province":"FL",
    "wof:name":"Emanuel Baptist Church",
    "wof:placetype":"venue"
},
  "geometry": {"coordinates":[-84.590654,30.791774],"type":"Point"}
}