{
  "type": "Feature",
  "properties": {
    "addr:full":"685 Golden Beach Dr Golden Beach FL 33160",
    "addr:housenumber":"685",
    "addr:postcode":"33160",
    "addr:street":"Golden Beach Dr",
    "iso:country":"US",
    "sg:address":"685 Golden Beach Dr",
    "sg:city":"Golden Beach",
    "sg:classifiers":[
        {
            "category":"Health Services",
            "subcategory":"Health Practitioner",
            "type":"Services"
        }
    ],
    "sg:phone":"+1 305 682 9418",
    "sg:postcode":"33160",
    "sg:province":"FL",
    "sg:tags":[
        "nutritionist"
    ],
    "wof:name":"Diet Print Program",
    "wof:placetype":"venue"
},
  "geometry": {"coordinates":[-80.120413,25.972295],"type":"Point"}
}