{
  "type": "Feature",
  "properties": {
    "iso:country":"US",
    "sg:address":"40 SE 1st Ave",
    "sg:city":"Homestead",
    "sg:classifiers":[
        {
            "category":"Restaurant",
            "type":"Food & Drink"
        }
    ],
    "sg:menulink":"http://www.allmenus.com/fl/homestead/160311-burger-king/menu/",
    "sg:phone":"+1 305 247 2258",
    "sg:postcode":"33034",
    "sg:province":"FL",
    "sg:tags":[
        "burger",
        "american"
    ],
    "wof:name":"Burger King",
    "wof:placetype":"venue"
},
  "geometry": {"coordinates":[-80.47577,25.4468],"type":"Point"}
}