{
  "type": "Feature",
  "properties": {
    "addr:full":"930 S Harbor City Blvd Melbourne FL 32901",
    "addr:housenumber":"930",
    "addr:postcode":"32901",
    "addr:street":"S Harbor City Blvd",
    "iso:country":"US",
    "sg:address":"930 S Harbor City Blvd",
    "sg:city":"Melbourne",
    "sg:classifiers":[
        {
            "category":"Professional",
            "subcategory":"Lawyer & Legal Services",
            "type":"Services"
        }
    ],
    "sg:phone":"+1 321 984 3300",
    "sg:postcode":"32901",
    "sg:province":"FL",
    "wof:name":"Charles Ian Nash",
    "wof:placetype":"venue"
},
  "geometry": {"coordinates":[-80.61211400000001,28.09811],"type":"Point"}
}