{
  "type": "Feature",
  "properties": {
    "addr:full":"1774 8th St SE Miami FL 33135",
    "addr:housenumber":"1774",
    "addr:postcode":"33135",
    "addr:street":"8Th St Se",
    "iso:country":"US",
    "sg:address":"1774 8th St SE",
    "sg:city":"Miami",
    "sg:classifiers":[
        {
            "category":"Retail",
            "subcategory":"Auto Repair",
            "type":"Services"
        }
    ],
    "sg:phone":"+1 305 646 0041",
    "sg:postcode":"33135",
    "sg:province":"FL",
    "sg:tags":[
        "automotive"
    ],
    "wof:name":"Adri Diagnostic Inc",
    "wof:placetype":"venue"
},
  "geometry": {"coordinates":[-80.22316499999999,25.765522],"type":"Point"}
}