{
  "type": "Feature",
  "properties": {
    "addr:full":"4260 Delespine Rd Cocoa FL 32927",
    "addr:housenumber":"4260",
    "addr:postcode":"32927",
    "addr:street":"Delespine Rd",
    "iso:country":"US",
    "sg:address":"4260 Delespine Rd",
    "sg:city":"Cocoa",
    "sg:classifiers":[
        {
            "category":"Real Estate",
            "subcategory":"Surveying",
            "type":"Services"
        }
    ],
    "sg:phone":"+1 321 631 1041",
    "sg:postcode":"32927",
    "sg:province":"FL",
    "wof:name":"True North Surveying & Mapping",
    "wof:placetype":"venue"
},
  "geometry": {"coordinates":[-80.788207,28.476289],"type":"Point"}
}