{
  "type": "Feature",
  "properties": {
    "iso:country":"US",
    "sg:address":"954 SW 2nd Ter",
    "sg:city":"Deerfield Beach",
    "sg:classifiers":[
        {
            "category":"Manufacturing",
            "subcategory":"Retail Goods",
            "type":"Manufacturing & Wholesale Goods"
        }
    ],
    "sg:phone":"+1 954 596 9778",
    "sg:postcode":"33441",
    "sg:province":"FL",
    "sg:tags":[
        "product",
        "mfg"
    ],
    "wof:name":"Artenal Industries Diversified",
    "wof:placetype":"venue"
},
  "geometry": {"coordinates":[-80.10691799999999,26.30528],"type":"Point"}
}