{
  "type": "Feature",
  "properties": {
    "addr:full":"1605 E Hillsborough Ave Tampa FL 33610",
    "addr:housenumber":"1605",
    "addr:postcode":"33610",
    "addr:street":"E Hillsborough Ave",
    "iso:country":"US",
    "sg:address":"1605 E Hillsborough Ave",
    "sg:city":"Tampa",
    "sg:classifiers":[
        {
            "category":"Social Services",
            "type":"Services"
        }
    ],
    "sg:phone":"+1 813 231 4474",
    "sg:postcode":"33610",
    "sg:province":"FL",
    "sg:tags":[
        "organization",
        "welfare"
    ],
    "wof:name":"Community Support & Treatment",
    "wof:placetype":"venue"
},
  "geometry": {"coordinates":[-82.441839,27.995989],"type":"Point"}
}