{
  "type": "Feature",
  "properties": {
    "iso:country":"US",
    "sg:address":"7945 Palmer Blvd",
    "sg:city":"Sarasota",
    "sg:classifiers":[
        {
            "category":"Professional",
            "subcategory":"Engineering",
            "type":"Services"
        }
    ],
    "sg:phone":"+1 941 379 0055",
    "sg:postcode":"34240",
    "sg:province":"FL",
    "sg:tags":[
        "engineer"
    ],
    "wof:name":"AMEC Earth & Environmental",
    "wof:placetype":"venue"
},
  "geometry": {"coordinates":[-82.40763699999999,27.320478],"type":"Point"}
}