{
  "type": "Feature",
  "properties": {
    "iso:country":"US",
    "sg:address":"2932 Breckenridge Dr",
    "sg:city":"Pensacola",
    "sg:classifiers":[
        {
            "category":"Wholesale",
            "subcategory":"Vending Machines",
            "type":"Manufacturing & Wholesale Goods"
        }
    ],
    "sg:phone":"+1 850 458 5170",
    "sg:postcode":"32526",
    "sg:province":"FL",
    "sg:tags":[
        "operator"
    ],
    "wof:name":"Elsie Carson Vending",
    "wof:placetype":"venue"
},
  "geometry": {"coordinates":[-87.322833,30.437996],"type":"Point"}
}