{
  "type": "Feature",
  "properties": {
    "addr:full":"1110 NE 2nd Ave Cape Coral FL 33909",
    "addr:housenumber":"1110",
    "addr:postcode":"33909",
    "addr:street":"Ne 2Nd Ave",
    "iso:country":"US",
    "sg:address":"1110 NE 2nd Ave",
    "sg:city":"Cape Coral",
    "sg:classifiers":[
        {
            "category":"Manufacturing",
            "subcategory":"Metals",
            "type":"Manufacturing & Wholesale Goods"
        }
    ],
    "sg:phone":"+1 239 772 7336",
    "sg:postcode":"33909",
    "sg:province":"FL",
    "sg:tags":[
        "installs",
        "screen",
        "enclosure",
        "mfg"
    ],
    "wof:name":"ABC Screen Masters Inc",
    "wof:placetype":"venue"
},
  "geometry": {"coordinates":[-81.97012599999999,26.673101],"type":"Point"}
}