{
  "type": "Feature",
  "properties": {
    "addr:full":"1795 Eagle Trace Blvd W Pompano Beach FL 33071",
    "addr:housenumber":"1795",
    "addr:postcode":"33071",
    "addr:street":"Eagle Trace Blvd W",
    "iso:country":"US",
    "sg:address":"1795 Eagle Trace Blvd W",
    "sg:city":"Pompano Beach",
    "sg:classifiers":[
        {
            "category":"Professional",
            "subcategory":"Business Services",
            "type":"Services"
        }
    ],
    "sg:phone":"+1 954 753 9107",
    "sg:postcode":"33071",
    "sg:province":"FL",
    "wof:name":"Chen Engineering Associates",
    "wof:placetype":"venue"
},
  "geometry": {"coordinates":[-80.294802,26.25145],"type":"Point"}
}