{
  "type": "Feature",
  "properties": {
    "addr:full":"9644 Scenic Dr Port Richey FL 34668",
    "addr:housenumber":"9644",
    "addr:postcode":"34668",
    "addr:street":"Scenic Dr",
    "iso:country":"US",
    "sg:address":"9644 Scenic Dr",
    "sg:city":"Port Richey",
    "sg:classifiers":[
        {
            "category":"Shopping",
            "subcategory":"Optical Goods",
            "type":"Retail Goods"
        }
    ],
    "sg:phone":"+1 727 848 3018",
    "sg:postcode":"34668",
    "sg:province":"FL",
    "wof:name":"Visionworks",
    "wof:placetype":"venue"
},
  "geometry": {"coordinates":[-82.707223,28.298946],"type":"Point"}
}