{
  "type": "Feature",
  "properties": {
    "iso:country":"US",
    "sg:address":"10271 SW 72nd St",
    "sg:city":"Miami",
    "sg:classifiers":[
        {
            "category":"Wholesale",
            "subcategory":"Machinery & Supplies",
            "type":"Manufacturing & Wholesale Goods"
        }
    ],
    "sg:phone":"+1 305 595 5452",
    "sg:postcode":"33173",
    "sg:province":"FL",
    "sg:tags":[
        "engine",
        "aircraft"
    ],
    "sg:website":"www.aviasupport.com",
    "wof:name":"Avia Support",
    "wof:placetype":"venue"
},
  "geometry": {"coordinates":[-80.359731,25.701398],"type":"Point"}
}