{
  "type": "Feature",
  "properties": {
    "iso:country":"US",
    "sg:address":"437 Charles Pinckney St",
    "sg:city":"Orange Park",
    "sg:classifiers":[
        {
            "category":"Professional",
            "subcategory":"Business Services",
            "type":"Services"
        }
    ],
    "sg:phone":"+1 904 298 1589",
    "sg:postcode":"32073",
    "sg:province":"FL",
    "wof:name":"Risen Son Enterprises Inc",
    "wof:placetype":"venue"
},
  "geometry": {"coordinates":[-81.767888,30.157838],"type":"Point"}
}