{
  "type": "Feature",
  "properties": {
    "addr:full":"1500 Collins Ave Miami Beach FL 33139",
    "addr:housenumber":"1500",
    "addr:postcode":"33139",
    "addr:street":"Collins Ave",
    "iso:country":"US",
    "sg:address":"1500 Collins Ave",
    "sg:city":"Miami Beach",
    "sg:classifiers":[
        {
            "category":"Travel",
            "subcategory":"Hotels & Motels",
            "type":"Entertainment"
        }
    ],
    "sg:phone":"+1 305 531 1251",
    "sg:postcode":"33139",
    "sg:province":"FL",
    "sg:website":"haddonhallmiamibeach.com/",
    "wof:name":"Haddon Hall Miami Beach",
    "wof:placetype":"venue"
},
  "geometry": {"coordinates":[-80.13085,25.78748],"type":"Point"}
}