{
  "type": "Feature",
  "properties": {
    "iso:country":"US",
    "sg:address":"3367 W Vine St",
    "sg:city":"Kissimmee",
    "sg:classifiers":[
        {
            "category":"Professional",
            "subcategory":"Lawyer & Legal Services",
            "type":"Services"
        }
    ],
    "sg:phone":"+1 407 847 7775",
    "sg:postcode":"34741",
    "sg:province":"FL",
    "sg:tags":[
        "attorney"
    ],
    "wof:name":"Udowychenko & Garcia Law Firm",
    "wof:placetype":"venue"
},
  "geometry": {"coordinates":[-81.437241,28.304514],"type":"Point"}
}