{
  "type": "Feature",
  "properties": {
    "iso:country":"US",
    "sg:address":"4601 State Hwy 60",
    "sg:city":"Plant City",
    "sg:classifiers":[
        {
            "category":"Retail",
            "subcategory":"Auto Repair",
            "type":"Services"
        }
    ],
    "sg:phone":"+1 813 737 1112",
    "sg:postcode":"33567",
    "sg:province":"FL",
    "sg:tags":[
        "parts"
    ],
    "wof:name":"Gillespie Auto Service & Repr",
    "wof:placetype":"venue"
},
  "geometry": {"coordinates":[-82.16815200000001,27.937485],"type":"Point"}
}