{
  "type": "Feature",
  "properties": {
    "addr:full":"5680 NW 163rd St Hialeah FL 33014",
    "addr:housenumber":"5680",
    "addr:postcode":"33014",
    "addr:street":"Nw 163Rd St",
    "iso:country":"US",
    "sg:address":"5680 NW 163rd St",
    "sg:city":"Hialeah",
    "sg:classifiers":[
        {
            "category":"Wholesale",
            "subcategory":"Construction Materials",
            "type":"Manufacturing & Wholesale Goods"
        }
    ],
    "sg:phone":"+1 305 474 7070",
    "sg:postcode":"33014",
    "sg:province":"FL",
    "sg:tags":[
        "wall",
        "rep",
        "floor",
        "mfg",
        "covering"
    ],
    "wof:name":"Kbt Distributors",
    "wof:placetype":"venue"
},
  "geometry": {"coordinates":[-80.29088,25.921137],"type":"Point"}
}