{
  "type": "Feature",
  "properties": {
    "addr:full":"4260 Progress Ave Naples FL 34104",
    "addr:housenumber":"4260",
    "addr:postcode":"34104",
    "addr:street":"Progress Ave",
    "iso:country":"US",
    "sg:address":"4260 Progress Ave",
    "sg:city":"Naples",
    "sg:classifiers":[
        {
            "category":"Shopping",
            "subcategory":"Bicycles & Sporting Goods",
            "type":"Retail Goods"
        }
    ],
    "sg:phone":"+1 239 643 5577",
    "sg:postcode":"34104",
    "sg:province":"FL",
    "sg:tags":[
        "equipment",
        "golf",
        "supply"
    ],
    "wof:name":"Naples Golf Co",
    "wof:placetype":"venue"
},
  "geometry": {"coordinates":[-81.755627,26.164296],"type":"Point"}
}