{
  "type": "Feature",
  "properties": {
    "iso:country":"US",
    "sg:address":"3600 S Atlantic Ave",
    "sg:city":"New Smyrna Beach",
    "sg:classifiers":[
        {
            "category":"Shopping",
            "subcategory":"Hobbies, Toys, & Games",
            "type":"Retail Goods"
        }
    ],
    "sg:phone":"+1 386 428 2001",
    "sg:postcode":"32169",
    "sg:province":"FL",
    "sg:tags":[
        "basket"
    ],
    "wof:name":"Sunshine Baskets",
    "wof:placetype":"venue"
},
  "geometry": {"coordinates":[-80.87940399999999,29.0092],"type":"Point"}
}