{
  "type": "Feature",
  "properties": {
    "iso:country":"US",
    "sg:address":"300 Shopping Center Dr",
    "sg:city":"Wildwood",
    "sg:classifiers":[
        {
            "category":"Home & Garden",
            "subcategory":"Hardware",
            "type":"Retail Goods"
        }
    ],
    "sg:phone":"+1 352 748 3204",
    "sg:postcode":"34785",
    "sg:province":"FL",
    "sg:tags":[
        "equipment-sales",
        "repair",
        "outdoor",
        "saw",
        "power"
    ],
    "sg:website":"http://www.stihldealer.net/default-dealer-045322.aspx",
    "wof:name":"Wildwood Ace Hardware",
    "wof:placetype":"venue"
},
  "geometry": {"coordinates":[-82.040733,28.860809],"type":"Point"}
}