{
  "type": "Feature",
  "properties": {
    "iso:country":"US",
    "sg:address":"1395 Deltona Blvd",
    "sg:city":"Spring Hill",
    "sg:classifiers":[
        {
            "category":"Retail",
            "subcategory":"Repair Shop",
            "type":"Services"
        }
    ],
    "sg:phone":"+1 352 684 6864",
    "sg:postcode":"34606",
    "sg:province":"FL",
    "sg:tags":[
        "plumbing",
        "drain",
        "cleaning",
        "sewer"
    ],
    "wof:name":"Payless Rooter Drain & Sewer",
    "wof:placetype":"venue"
},
  "geometry": {"coordinates":[-82.587886,28.455627],"type":"Point"}
}