{
  "type": "Feature",
  "properties": {
    "addr:full":"3300 W Desoto St Pensacola FL 32505",
    "addr:housenumber":"3300",
    "addr:postcode":"32505",
    "addr:street":"W Desoto St",
    "iso:country":"US",
    "sg:address":"3300 W Desoto St",
    "sg:city":"Pensacola",
    "sg:classifiers":[
        {
            "category":"Organizations",
            "subcategory":"Community Association",
            "type":"Services"
        }
    ],
    "sg:phone":"+1 850 432 8214",
    "sg:postcode":"32505",
    "sg:province":"FL",
    "wof:name":"West Pensacola Masonic Lodge",
    "wof:placetype":"venue"
},
  "geometry": {"coordinates":[-87.255686,30.423302],"type":"Point"}
}