{
  "type": "Feature",
  "properties": {
    "iso:country":"US",
    "sg:address":"703 SE 5th St",
    "sg:city":"Cape Coral",
    "sg:classifiers":[
        {
            "category":"Building & Trades",
            "subcategory":"Cleaning & Sanitation",
            "type":"Services"
        }
    ],
    "sg:phone":"+1 239 246 2939",
    "sg:postcode":"33990",
    "sg:province":"FL",
    "sg:tags":[
        "janitor"
    ],
    "wof:name":"Janitron Cleaning Svc",
    "wof:placetype":"venue"
},
  "geometry": {"coordinates":[-81.959425,26.643151],"type":"Point"}
}