{
  "type": "Feature",
  "properties": {
    "addr:full":"2440 S Volusia Ave Orange City FL 32763",
    "addr:housenumber":"2440",
    "addr:postcode":"32763",
    "addr:street":"S Volusia Ave",
    "iso:country":"US",
    "sg:address":"2440 S Volusia Ave",
    "sg:city":"Orange City",
    "sg:classifiers":[
        {
            "category":"Personal",
            "subcategory":"Beauty Salon",
            "type":"Services"
        }
    ],
    "sg:phone":"+1 386 775 2222",
    "sg:postcode":"32763",
    "sg:province":"FL",
    "sg:tags":[
        "hair"
    ],
    "wof:name":"Cutups",
    "wof:placetype":"venue"
},
  "geometry": {"coordinates":[-81.30046299999999,28.919451],"type":"Point"}
}