{
  "type": "Feature",
  "properties": {
    "addr:full":"15334 W Dixie Hwy North Miami Bch FL 33162",
    "addr:housenumber":"15334",
    "addr:postcode":"33162",
    "addr:street":"W Dixie Hwy",
    "iso:country":"US",
    "sg:address":"15334 W Dixie Hwy",
    "sg:city":"North Miami Bch",
    "sg:classifiers":[
        {
            "category":"Professional",
            "subcategory":"Business Services",
            "type":"Services"
        }
    ],
    "sg:phone":"+1 305 948 3657",
    "sg:postcode":"33162",
    "sg:province":"FL",
    "wof:name":"Gram The Business Svc Inc",
    "wof:placetype":"venue"
},
  "geometry": {"coordinates":[-80.161317,25.917001],"type":"Point"}
}