{
  "type": "Feature",
  "properties": {
    "iso:country":"US",
    "sg:address":"12622 Park Blvd",
    "sg:city":"Largo",
    "sg:classifiers":[
        {
            "category":"Organizations",
            "subcategory":"Religious Organization",
            "type":"Services"
        }
    ],
    "sg:phone":"+1 727 392 8078",
    "sg:postcode":"33776",
    "sg:province":"FL",
    "sg:tags":[
        "church"
    ],
    "wof:name":"Jehovah's Witnesses Bay Pines",
    "wof:placetype":"venue"
},
  "geometry": {"coordinates":[-82.81558699999999,27.843572],"type":"Point"}
}