{
  "type": "Feature",
  "properties": {
    "iso:country":"US",
    "sg:address":"3742 W 12th Ave",
    "sg:city":"Hialeah",
    "sg:classifiers":[
        {
            "category":"Social Services",
            "subcategory":"Job Training",
            "type":"Services"
        }
    ],
    "sg:phone":"+1 305 824 1182",
    "sg:postcode":"33012",
    "sg:province":"FL",
    "sg:tags":[
        "rehabilitation"
    ],
    "wof:name":"Atlas Group Rehab Ctr",
    "wof:placetype":"venue"
},
  "geometry": {"coordinates":[-80.306618,25.855505],"type":"Point"}
}