{
  "type": "Feature",
  "properties": {
    "iso:country":"US",
    "sg:address":"660 W Oakland Park Blvd",
    "sg:city":"Wilton Manors",
    "sg:classifiers":[
        {
            "category":"Professional",
            "subcategory":"Accounting & Tax Preparation",
            "type":"Services"
        }
    ],
    "sg:phone":"+1 954 561 1040",
    "sg:postcode":"33311",
    "sg:province":"FL",
    "sg:tags":[
        "return",
        "filing"
    ],
    "wof:name":"Better Income Tax Svc",
    "wof:placetype":"venue"
},
  "geometry": {"coordinates":[-80.153137,26.166251],"type":"Point"}
}