{
  "type": "Feature",
  "properties": {
    "iso:country":"US",
    "sg:address":"1495 State Hwy 81",
    "sg:city":"Westville",
    "sg:classifiers":[
        {
            "category":"Building & Trades",
            "subcategory":"Landscaping Services",
            "type":"Services"
        }
    ],
    "sg:phone":"+1 850 643 3474",
    "sg:postcode":"32464",
    "sg:province":"FL",
    "wof:name":"Gator Landscaping",
    "wof:placetype":"venue"
},
  "geometry": {"coordinates":[-85.965189,30.929094],"type":"Point"}
}