{
  "type": "Feature",
  "properties": {
    "addr:full":"12351 S Orange Blossom Trl Orlando FL 32837",
    "addr:housenumber":"12351",
    "addr:postcode":"32837",
    "addr:street":"S Orange Blossom Trl",
    "iso:country":"US",
    "sg:address":"12351 S Orange Blossom Trl",
    "sg:city":"Orlando",
    "sg:classifiers":[
        {
            "category":"Food & Beverages",
            "subcategory":"Groceries & Convenience Stores",
            "type":"Retail Goods"
        }
    ],
    "sg:phone":"+1 407 856 9492",
    "sg:postcode":"32837",
    "sg:province":"FL",
    "sg:tags":[
        "photofinishing",
        "laboratory"
    ],
    "wof:name":"Winn-Dixie Stores Inc",
    "wof:placetype":"venue"
},
  "geometry": {"coordinates":[-81.40445699999999,28.382012],"type":"Point"}
}