{
  "type": "Feature",
  "properties": {
    "iso:country":"US",
    "sg:address":"10860 SW 38th Dr",
    "sg:city":"Davie",
    "sg:classifiers":[
        {
            "category":"Personal",
            "type":"Services"
        }
    ],
    "sg:phone":"+1 954 472 0320",
    "sg:postcode":"33328",
    "sg:province":"FL",
    "sg:tags":[
        "wedding",
        "chapel"
    ],
    "sg:website":"www.aweddingforyou.com",
    "wof:name":"A Wedding For You Inc",
    "wof:placetype":"venue"
},
  "geometry": {"coordinates":[-80.292968,26.072523],"type":"Point"}
}