{
  "type": "Feature",
  "properties": {
    "addr:full":"402 Noland Dr Brandon FL 33511",
    "addr:housenumber":"402",
    "addr:postcode":"33511",
    "addr:street":"Noland Dr",
    "iso:country":"US",
    "sg:address":"402 Noland Dr",
    "sg:city":"Brandon",
    "sg:classifiers":[
        {
            "category":"Health Services",
            "subcategory":"Doctor",
            "type":"Services"
        }
    ],
    "sg:phone":"+1 813 655 9000",
    "sg:postcode":"33511",
    "sg:province":"FL",
    "sg:tags":[
        "physician",
        "surgeon"
    ],
    "wof:name":"Tampa Bay Sleep Disorder Ctr",
    "wof:placetype":"venue"
},
  "geometry": {"coordinates":[-82.29047799999999,27.933128],"type":"Point"}
}