{
  "type": "Feature",
  "properties": {
    "addr:full":"1801 W Sample Rd Pompano Beach FL 33064",
    "addr:housenumber":"1801",
    "addr:postcode":"33064",
    "addr:street":"W Sample Rd",
    "iso:country":"US",
    "sg:address":"1801 W Sample Rd",
    "sg:city":"Pompano Beach",
    "sg:classifiers":[
        {
            "category":"Government",
            "subcategory":"Jail",
            "type":"Public Place"
        }
    ],
    "sg:phone":"+1 954 969 4290",
    "sg:postcode":"33064",
    "sg:province":"FL",
    "sg:tags":[
        "correctional",
        "institution"
    ],
    "wof:name":"Juvenile Probation",
    "wof:placetype":"venue"
},
  "geometry": {"coordinates":[-80.148089,26.274701],"type":"Point"}
}