{
  "type": "Feature",
  "properties": {
    "addr:full":"508 SW 1st Ct Pompano Beach FL 33060",
    "addr:housenumber":"508",
    "addr:postcode":"33060",
    "addr:street":"Sw 1St Ct",
    "iso:country":"US",
    "sg:address":"508 SW 1st Ct",
    "sg:city":"Pompano Beach",
    "sg:classifiers":[
        {
            "category":"Food & Beverages",
            "subcategory":"Fruits & Vegetables",
            "type":"Retail Goods"
        }
    ],
    "sg:phone":"+1 954 782 6069",
    "sg:postcode":"33060",
    "sg:province":"FL",
    "sg:tags":[
        "produce"
    ],
    "wof:name":"Anelle Produce",
    "wof:placetype":"venue"
},
  "geometry": {"coordinates":[-80.133145,26.230098],"type":"Point"}
}