{
  "type": "Feature",
  "properties": {
    "addr:full":"795 Appleton Pl Oviedo FL 32765",
    "addr:housenumber":"795",
    "addr:postcode":"32765",
    "addr:street":"Appleton Pl",
    "iso:country":"US",
    "sg:address":"795 Appleton Pl",
    "sg:city":"Oviedo",
    "sg:classifiers":[
        {
            "category":"Professional",
            "subcategory":"Accounting & Tax Preparation",
            "type":"Services"
        }
    ],
    "sg:phone":"+1 407 366 0393",
    "sg:postcode":"32765",
    "sg:province":"FL",
    "sg:tags":[
        "bookkeeping",
        "general"
    ],
    "wof:name":"Bookkeeping Services By Edwin",
    "wof:placetype":"venue"
},
  "geometry": {"coordinates":[-81.194076,28.629836],"type":"Point"}
}