{
  "type": "Feature",
  "properties": {
    "iso:country":"US",
    "sg:address":"8200 Penzance Blvd",
    "sg:city":"Fort Myers",
    "sg:classifiers":[
        {
            "category":"Building & Trades",
            "subcategory":"Construction",
            "type":"Services"
        }
    ],
    "sg:phone":"+1 239 225 1479",
    "sg:postcode":"33912",
    "sg:province":"FL",
    "wof:name":"Southwest Fla Slcting Striping",
    "wof:placetype":"venue"
},
  "geometry": {"coordinates":[-81.820973,26.568756],"type":"Point"}
}