{
  "type": "Feature",
  "properties": {
    "iso:country":"US",
    "sg:address":"5519 W Colonial Dr",
    "sg:city":"Orlando",
    "sg:classifiers":[
        {
            "category":"Personal",
            "subcategory":"Beauty Salon",
            "type":"Services"
        }
    ],
    "sg:phone":"+1 407 578 7738",
    "sg:postcode":"32808",
    "sg:province":"FL",
    "wof:name":"Beauty Comb Salon Inc",
    "wof:placetype":"venue"
},
  "geometry": {"coordinates":[-81.454711,28.552476],"type":"Point"}
}