{
  "type": "Feature",
  "properties": {
    "iso:country":"US",
    "sg:address":"1221 NE 141st St",
    "sg:city":"Miami",
    "sg:classifiers":[
        {
            "category":"Autos & Motor Vehicles",
            "subcategory":"Automobile Sales",
            "type":"Retail Goods"
        }
    ],
    "sg:phone":"+1 305 899 0808",
    "sg:postcode":"33161",
    "sg:province":"FL",
    "sg:tags":[
        "used"
    ],
    "wof:name":"Jonathan D Salvant",
    "wof:placetype":"venue"
},
  "geometry": {"coordinates":[-80.174102,25.905484],"type":"Point"}
}