{
  "type": "Feature",
  "properties": {
    "addr:full":"2709 E South St Orlando FL 32803",
    "addr:housenumber":"2709 e",
    "addr:postcode":"32803",
    "addr:street":"South St",
    "iso:country":"US",
    "sg:address":"2709 E South St",
    "sg:city":"Orlando",
    "sg:classifiers":[
        {
            "category":"Wholesale",
            "subcategory":"Painting Supplies",
            "type":"Manufacturing & Wholesale Goods"
        }
    ],
    "sg:phone":"+1 407 898 9237",
    "sg:postcode":"32803",
    "sg:province":"FL",
    "wof:name":"Wonder Products",
    "wof:placetype":"venue"
},
  "geometry": {"coordinates":[-81.348747,28.538765],"type":"Point"}
}