{
  "type": "Feature",
  "properties": {
    "iso:country":"US",
    "sg:address":"920 Maple Ridge Rd N",
    "sg:city":"Palm Harbor",
    "sg:classifiers":[
        {
            "category":"Insurance",
            "subcategory":"Insurance Agent",
            "type":"Services"
        }
    ],
    "sg:phone":"+1 727 784 2875",
    "sg:postcode":"34683",
    "sg:province":"FL",
    "wof:name":"Kardos Insurance Inc",
    "wof:placetype":"venue"
},
  "geometry": {"coordinates":[-82.752303,28.092577],"type":"Point"}
}