{
  "type": "Feature",
  "properties": {
    "iso:country":"US",
    "sg:address":"11820 Beach Blvd",
    "sg:city":"Jacksonville",
    "sg:classifiers":[
        {
            "category":"Professional",
            "type":"Services"
        }
    ],
    "sg:phone":"+1 904 642 6658",
    "sg:postcode":"32246",
    "sg:province":"FL",
    "sg:tags":[
        "establishment"
    ],
    "wof:name":"Center For Life Enrichment",
    "wof:placetype":"venue"
},
  "geometry": {"coordinates":[-81.51536400000001,30.286964],"type":"Point"}
}