{
  "type": "Feature",
  "properties": {
    "iso:country":"US",
    "sg:address":"3114 Blue Heron St",
    "sg:city":"Safety Harbor",
    "sg:classifiers":[
        {
            "category":"Wholesale",
            "subcategory":"Vending Machines",
            "type":"Manufacturing & Wholesale Goods"
        }
    ],
    "sg:phone":"+1 727 725 1682",
    "sg:postcode":"34695",
    "sg:province":"FL",
    "sg:tags":[
        "operator"
    ],
    "wof:name":"Madco Vending Inc",
    "wof:placetype":"venue"
},
  "geometry": {"coordinates":[-82.698337,28.019281],"type":"Point"}
}