{
  "type": "Feature",
  "properties": {
    "iso:country":"US",
    "sg:address":"14540 SW 136th St",
    "sg:city":"Miami",
    "sg:classifiers":[
        {
            "category":"Place Of Worship",
            "type":"Public Place"
        }
    ],
    "sg:phone":"+1 305 233 5444",
    "sg:postcode":"33186",
    "sg:province":"FL",
    "sg:tags":[
        "church"
    ],
    "wof:name":"Caribbean Regional Office Church Of The Nazarene",
    "wof:placetype":"venue"
},
  "geometry": {"coordinates":[-80.430362,25.640529],"type":"Point"}
}