{
  "type": "Feature",
  "properties": {
    "addr:full":"7877 Gunn Hwy Tampa FL 33626",
    "addr:housenumber":"7877",
    "addr:postcode":"33626",
    "addr:street":"Gunn Hwy",
    "iso:country":"US",
    "sg:address":"7877 Gunn Hwy",
    "sg:city":"Tampa",
    "sg:classifiers":[
        {
            "category":"Restaurant",
            "type":"Food & Drink"
        }
    ],
    "sg:phone":"+1 813 926 5202",
    "sg:postcode":"33626",
    "sg:province":"FL",
    "wof:name":"Louis Pappas Market Cafe",
    "wof:placetype":"venue"
},
  "geometry": {"coordinates":[-82.57565,28.078779],"type":"Point"}
}