{
  "type": "Feature",
  "properties": {
    "iso:country":"US",
    "sg:address":"2611 Cobblestone Forest Dr",
    "sg:city":"Jacksonville",
    "sg:classifiers":[
        {
            "category":"Building & Trades",
            "subcategory":"Construction",
            "type":"Services"
        }
    ],
    "sg:phone":"+1 904 642 0430",
    "sg:postcode":"32225",
    "sg:province":"FL",
    "sg:tags":[
        "contractor"
    ],
    "wof:name":"Alesch & Sons Inc",
    "wof:placetype":"venue"
},
  "geometry": {"coordinates":[-81.49798199999999,30.362766],"type":"Point"}
}