{
  "type": "Feature",
  "properties": {
    "iso:country":"US",
    "sg:address":"1581 Logan Ct",
    "sg:city":"Naples",
    "sg:classifiers":[
        {
            "category":"Retail",
            "subcategory":"Repair Shop",
            "type":"Services"
        },
        {
            "category":"Building & Trades",
            "subcategory":"Construction",
            "type":"Services"
        }
    ],
    "sg:phone":"+1 239 455 2541",
    "sg:postcode":"34116",
    "sg:province":"FL",
    "sg:tags":[
        "screen",
        "contractor"
    ],
    "wof:name":"R C Screen & Maintenance Inc",
    "wof:placetype":"venue"
},
  "geometry": {"coordinates":[-81.717742,26.19933],"type":"Point"}
}