{
  "type": "Feature",
  "properties": {
    "addr:full":"3240 Whitehorse Ct Deltona FL 32738",
    "addr:postcode":"3240;32738",
    "addr:street":"Whitehorse Ct",
    "iso:country":"US",
    "sg:address":"3240 Whitehorse Ct",
    "sg:city":"Deltona",
    "sg:classifiers":[
        {
            "category":"Home & Garden",
            "subcategory":"Building Materials",
            "type":"Retail Goods"
        }
    ],
    "sg:phone":"+1 386 532 5544",
    "sg:postcode":"32738",
    "sg:province":"FL",
    "sg:tags":[
        "windows"
    ],
    "wof:name":"Heritage Installations",
    "wof:placetype":"venue"
},
  "geometry": {"coordinates":[-81.198024,28.954488],"type":"Point"}
}