{
  "type": "Feature",
  "properties": {
    "iso:country":"US",
    "sg:address":"7081 Rain Forest Dr",
    "sg:city":"Boca Raton",
    "sg:classifiers":[
        {
            "category":"Real Estate",
            "subcategory":"Developer",
            "type":"Services"
        }
    ],
    "sg:phone":"+1 561 482 3060",
    "sg:postcode":"33434",
    "sg:province":"FL",
    "wof:name":"Northside Development Inc",
    "wof:placetype":"venue"
},
  "geometry": {"coordinates":[-80.153138,26.38156],"type":"Point"}
}