{
  "type": "Feature",
  "properties": {
    "iso:country":"US",
    "sg:address":"7350 Blanding Blvd",
    "sg:city":"Jacksonville",
    "sg:classifiers":[
        {
            "category":"Freight",
            "type":"Transportation"
        }
    ],
    "sg:phone":"+1 904 771 9725",
    "sg:postcode":"32244",
    "sg:province":"FL",
    "wof:name":"Mountain Transportation I",
    "wof:placetype":"venue"
},
  "geometry": {"coordinates":[-81.738541,30.20948],"type":"Point"}
}