{
  "type": "Feature",
  "properties": {
    "iso:country":"US",
    "sg:address":"17626 Nathans Dr",
    "sg:city":"Tampa",
    "sg:classifiers":[
        {
            "category":"Banks & Credit Unions",
            "subcategory":"Investment Brokerage",
            "type":"Services"
        }
    ],
    "sg:phone":"+1 813 991 9977",
    "sg:postcode":"33647",
    "sg:province":"FL",
    "sg:tags":[
        "advisory",
        "financial"
    ],
    "wof:name":"Greenleaf Financial Svc",
    "wof:placetype":"venue"
},
  "geometry": {"coordinates":[-82.342457,28.131155],"type":"Point"}
}