{
  "type": "Feature",
  "properties": {
    "iso:country":"US",
    "sg:address":"2405 E Washington St",
    "sg:city":"Orlando",
    "sg:classifiers":[
        {
            "category":"Manufacturing",
            "subcategory":"Tobacco Products",
            "type":"Manufacturing & Wholesale Goods"
        }
    ],
    "sg:phone":"+1 407 286 5941",
    "sg:postcode":"32803",
    "sg:province":"FL",
    "sg:tags":[
        "cigarette",
        "cigar",
        "manufacturer",
        "tobacco-wholesale"
    ],
    "wof:name":"Cigar Bros",
    "wof:placetype":"venue"
},
  "geometry": {"coordinates":[-81.35190799999999,28.544081],"type":"Point"}
}