{
  "type": "Feature",
  "properties": {
    "addr:full":"7455 Wimpole Dr New Port Richey FL 34655",
    "addr:housenumber":"7455",
    "addr:postcode":"34655",
    "addr:street":"Wimpole Dr",
    "iso:country":"US",
    "sg:address":"7455 Wimpole Dr",
    "sg:city":"New Port Richey",
    "sg:classifiers":[
        {
            "category":"Building & Trades",
            "subcategory":"Construction",
            "type":"Services"
        }
    ],
    "sg:phone":"+1 727 372 7516",
    "sg:postcode":"34655",
    "sg:province":"FL",
    "sg:tags":[
        "home",
        "builder"
    ],
    "wof:name":"Lexington Homes Inc",
    "wof:placetype":"venue"
},
  "geometry": {"coordinates":[-82.69708199999999,28.19468],"type":"Point"}
}