{
  "type": "Feature",
  "properties": {
    "iso:country":"US",
    "sg:address":"1011 Bichara Blvd",
    "sg:city":"Lady Lake",
    "sg:classifiers":[
        {
            "category":"Restaurant",
            "type":"Food & Drink"
        }
    ],
    "sg:menulink":"http://www.allmenus.com/fl/fruitland-park-lady-lake/169497-wendys/menu/",
    "sg:phone":"+1 352 750 6022",
    "sg:postcode":"32159",
    "sg:province":"FL",
    "sg:tags":[
        "burger",
        "american",
        "soup"
    ],
    "wof:name":"Wendy's",
    "wof:placetype":"venue"
},
  "geometry": {"coordinates":[-81.94379000000001,28.937819],"type":"Point"}
}