{
  "type": "Feature",
  "properties": {
    "iso:country":"US",
    "sg:address":"3852 NW 42nd Way",
    "sg:city":"Pompano Beach",
    "sg:classifiers":[
        {
            "category":"Utilities",
            "subcategory":"Cable",
            "type":"Services"
        }
    ],
    "sg:phone":"+1 954 977 0999",
    "sg:postcode":"33073",
    "sg:province":"FL",
    "sg:tags":[
        "television"
    ],
    "wof:name":"Cable Phonics Inc",
    "wof:placetype":"venue"
},
  "geometry": {"coordinates":[-80.182883,26.277943],"type":"Point"}
}