{
  "type": "Feature",
  "properties": {
    "addr:full":"2119 NE Van Loon Ter Cape Coral FL 33909",
    "addr:housenumber":"2119",
    "addr:postcode":"33909",
    "addr:street":"Ne Van Loon Ter",
    "iso:country":"US",
    "sg:address":"2119 NE Van Loon Ter",
    "sg:city":"Cape Coral",
    "sg:classifiers":[
        {
            "category":"Utilities",
            "subcategory":"Telephone",
            "type":"Services"
        }
    ],
    "sg:phone":"+1 239 458 3951",
    "sg:postcode":"33909",
    "sg:province":"FL",
    "sg:tags":[
        "communications"
    ],
    "wof:name":"Wil Tel Communications Inc",
    "wof:placetype":"venue"
},
  "geometry": {"coordinates":[-81.928459,26.653618],"type":"Point"}
}