{
  "type": "Feature",
  "properties": {
    "iso:country":"US",
    "sg:address":"3174 W 76th St",
    "sg:city":"Hialeah",
    "sg:classifiers":[
        {
            "category":"Banks & Credit Unions",
            "subcategory":"Bank",
            "type":"Services"
        }
    ],
    "sg:phone":"+1 305 819 8682",
    "sg:postcode":"33018",
    "sg:province":"FL",
    "sg:website":"www.uscentury.com",
    "wof:name":"US Century Bank Villa Verde",
    "wof:placetype":"venue"
},
  "geometry": {"coordinates":[-80.34755,25.891373],"type":"Point"}
}