{
  "type": "Feature",
  "properties": {
    "iso:country":"US",
    "sg:address":"13301 SW 80th Rd",
    "sg:city":"Miami",
    "sg:classifiers":[
        {
            "category":"Recreation",
            "type":"Entertainment"
        }
    ],
    "sg:phone":"+1 305 238 2337",
    "sg:postcode":"33156",
    "sg:province":"FL",
    "wof:name":"Tumblebees Gymnastics",
    "wof:placetype":"venue"
},
  "geometry": {"coordinates":[-80.32379299999999,25.646862],"type":"Point"}
}