{
  "type": "Feature",
  "properties": {
    "iso:country":"US",
    "sg:address":"1022 NE 215th St",
    "sg:city":"Miami",
    "sg:classifiers":[
        {
            "category":"Shopping",
            "subcategory":"Department Store",
            "type":"Retail Goods"
        },
        {
            "category":"Shopping",
            "subcategory":"Discount & Variety Stores",
            "type":"Retail Goods"
        }
    ],
    "sg:phone":"+1 305 651 1158",
    "sg:postcode":"33179",
    "sg:province":"FL",
    "wof:name":"99 Cents Store",
    "wof:placetype":"venue"
},
  "geometry": {"coordinates":[-80.182185,25.973287],"type":"Point"}
}