{
  "type": "Feature",
  "properties": {
    "addr:full":"12401 SW 124th Ter Miami FL 33186",
    "addr:housenumber":"12401",
    "addr:postcode":"33186",
    "addr:street":"Sw 124Th Ter",
    "iso:country":"US",
    "sg:address":"12401 SW 124th Ter",
    "sg:city":"Miami",
    "sg:classifiers":[
        {
            "category":"Retail",
            "subcategory":"Laundry & Dry Cleaning",
            "type":"Services"
        },
        {
            "category":"Building & Trades",
            "subcategory":"Cleaning & Sanitation",
            "type":"Services"
        }
    ],
    "sg:phone":"+1 305 233 0290",
    "sg:postcode":"33186",
    "sg:province":"FL",
    "sg:tags":[
        "cleaner",
        "carpet",
        "rug",
        "house"
    ],
    "wof:name":"Dry Perfect Cleaning.Com",
    "wof:placetype":"venue"
},
  "geometry": {"coordinates":[-80.39558,25.652795],"type":"Point"}
}