{
  "type": "Feature",
  "properties": {
    "addr:full":"1241 Altoona Ave Spring Hill FL 34609",
    "addr:housenumber":"1241",
    "addr:postcode":"34609",
    "addr:street":"Altoona Ave",
    "iso:country":"US",
    "sg:address":"1241 Altoona Ave",
    "sg:city":"Spring Hill",
    "sg:classifiers":[
        {
            "category":"Insurance",
            "subcategory":"Insurance Agent",
            "type":"Services"
        }
    ],
    "sg:phone":"+1 352 686 7501",
    "sg:postcode":"34609",
    "sg:province":"FL",
    "wof:name":"MLA Financial",
    "wof:placetype":"venue"
},
  "geometry": {"coordinates":[-82.497861,28.453091],"type":"Point"}
}