{
  "type": "Feature",
  "properties": {
    "iso:country":"US",
    "sg:address":"950 Fay Blvd",
    "sg:city":"Cocoa",
    "sg:classifiers":[
        {
            "category":"Insurance",
            "subcategory":"Insurance Agent",
            "type":"Services"
        },
        {
            "category":"Insurance",
            "subcategory":"Hazard Insurance",
            "type":"Services"
        },
        {
            "category":"Insurance",
            "subcategory":"Title Insurance",
            "type":"Services"
        },
        {
            "category":"Insurance",
            "subcategory":"Life Insurance",
            "type":"Services"
        }
    ],
    "sg:phone":"+1 321 631 3777",
    "sg:postcode":"32927",
    "sg:province":"FL",
    "sg:tags":[
        "business",
        "auto",
        "commercial",
        "homeowner",
        "motorcycle",
        "renter"
    ],
    "wof:name":"Allstate Insurance Company - Jennifer Dicandio",
    "wof:placetype":"venue"
},
  "geometry": {"coordinates":[-80.77681200000001,28.476915],"type":"Point"}
}