{
  "type": "Feature",
  "properties": {
    "addr:full":"706 Springview Dr Orlando FL 32803",
    "addr:housenumber":"706",
    "addr:postcode":"32803",
    "addr:street":"Springview Dr",
    "iso:country":"US",
    "sg:address":"706 Springview Dr",
    "sg:city":"Orlando",
    "sg:classifiers":[
        {
            "category":"Wholesale",
            "subcategory":"Groceries",
            "type":"Manufacturing & Wholesale Goods"
        }
    ],
    "sg:phone":"+1 407 894 2917",
    "sg:postcode":"32803",
    "sg:province":"FL",
    "wof:name":"Eds Soda & Snacks",
    "wof:placetype":"venue"
},
  "geometry": {"coordinates":[-81.33585600000001,28.532721],"type":"Point"}
}