{
  "type": "Feature",
  "properties": {
    "iso:country":"US",
    "sg:address":"1200 SE Federal Hwy",
    "sg:city":"Stuart",
    "sg:classifiers":[
        {
            "category":"Travel",
            "subcategory":"Hotels & Motels",
            "type":"Entertainment"
        }
    ],
    "sg:phone":"+1 772 287 6900",
    "sg:postcode":"34994",
    "sg:province":"FL",
    "sg:tags":[
        "lodging"
    ],
    "sg:website":"http://www.clarionhotel.com/hotel-stuart-florida-FL423?ywlocal",
    "wof:name":"Clarion Inn Stuart",
    "wof:placetype":"venue"
},
  "geometry": {"coordinates":[-80.246627,27.187776],"type":"Point"}
}