{
  "type": "Feature",
  "properties": {
    "addr:full":"510 S Ramona Ave Lake Alfred FL 33850",
    "addr:housenumber":"510",
    "addr:postcode":"33850",
    "addr:street":"S Ramona Ave",
    "iso:country":"US",
    "sg:address":"510 S Ramona Ave",
    "sg:city":"Lake Alfred",
    "sg:classifiers":[
        {
            "category":"Recreation",
            "type":"Entertainment"
        }
    ],
    "sg:phone":"+1 863 956 0360",
    "sg:postcode":"33850",
    "sg:province":"FL",
    "sg:tags":[
        "sporting"
    ],
    "wof:name":"Bonifay Ski School Inc",
    "wof:placetype":"venue"
},
  "geometry": {"coordinates":[-81.71887099999999,28.089556],"type":"Point"}
}