{
  "type": "Feature",
  "properties": {
    "iso:country":"US",
    "sg:address":"3183 4th St N",
    "sg:city":"St Petersburg",
    "sg:classifiers":[
        {
            "category":"Personal",
            "subcategory":"Beauty Salon",
            "type":"Services"
        }
    ],
    "sg:phone":"+1 727 895 2249",
    "sg:postcode":"33704",
    "sg:province":"FL",
    "wof:name":"Excalibur Styling Salon",
    "wof:placetype":"venue"
},
  "geometry": {"coordinates":[-82.63851099999999,27.800465],"type":"Point"}
}