{
  "type": "Feature",
  "properties": {
    "iso:country":"US",
    "sg:address":"3461 W Lakeshore Dr",
    "sg:city":"Tallahassee",
    "sg:classifiers":[
        {
            "category":"Education",
            "subcategory":"Library",
            "type":"Public Place"
        }
    ],
    "sg:phone":"+1 850 385 4830",
    "sg:postcode":"32312",
    "sg:province":"FL",
    "sg:tags":[
        "research"
    ],
    "wof:name":"Virginia E Warfel",
    "wof:placetype":"venue"
},
  "geometry": {"coordinates":[-84.299741,30.505491],"type":"Point"}
}