{
  "type": "Feature",
  "properties": {
    "addr:full":"5400 W Irlo Bronson Memorial Hwy Kissimmee FL 34746",
    "addr:housenumber":"5400",
    "addr:postcode":"34746",
    "addr:street":"W Irlo Bronson Memorial Hwy",
    "iso:country":"US",
    "sg:address":"5400 W Irlo Bronson Memorial Hwy",
    "sg:city":"Kissimmee",
    "sg:classifiers":[
        {
            "category":"Bars & Pubs",
            "type":"Food & Drink"
        }
    ],
    "sg:menulink":"http://www.allmenus.com/fl/kissimmee/35135-cracker-barrel-old-country-store/menu/",
    "sg:phone":"+1 407 396 6521",
    "sg:postcode":"34746",
    "sg:province":"FL",
    "sg:tags":[
        "american",
        "southern"
    ],
    "wof:name":"Cracker Barrel Old Country Store",
    "wof:placetype":"venue"
},
  "geometry": {"coordinates":[-81.499419,28.332779],"type":"Point"}
}