{
  "type": "Feature",
  "properties": {
    "iso:country":"US",
    "sg:address":"4800 S Orange Ave",
    "sg:city":"Orlando",
    "sg:classifiers":[
        {
            "category":"Restaurant",
            "type":"Food & Drink"
        }
    ],
    "sg:phone":"+1 407 851 6980",
    "sg:postcode":"32806",
    "sg:province":"FL",
    "sg:tags":[
        "french"
    ],
    "wof:name":"Le Coq Au Vin",
    "wof:placetype":"venue"
},
  "geometry": {"coordinates":[-81.37454200000001,28.49375],"type":"Point"}
}