{
  "type": "Feature",
  "properties": {
    "iso:country":"US",
    "sg:address":"7501 W Hillsborough Ave",
    "sg:city":"Tampa",
    "sg:classifiers":[
        {
            "category":"Autos & Motor Vehicles",
            "subcategory":"Auto Supplies",
            "type":"Retail Goods"
        }
    ],
    "sg:phone":"+1 813 886 9220",
    "sg:postcode":"33615",
    "sg:province":"FL",
    "sg:tags":[
        "parts",
        "accessory"
    ],
    "sg:website":"www.autozone.com",
    "wof:name":"Autozone",
    "wof:placetype":"venue"
},
  "geometry": {"coordinates":[-82.56482099999999,27.996589],"type":"Point"}
}