{
  "type": "Feature",
  "properties": {
    "iso:country":"US",
    "sg:address":"1044 Big Oaks Blvd",
    "sg:city":"Oviedo",
    "sg:classifiers":[
        {
            "category":"Real Estate",
            "subcategory":"Real Estate Agent",
            "type":"Services"
        }
    ],
    "sg:phone":"+1 407 366 9915",
    "sg:postcode":"32765",
    "sg:province":"FL",
    "wof:name":"Grande Appraisals",
    "wof:placetype":"venue"
},
  "geometry": {"coordinates":[-81.181406,28.653285],"type":"Point"}
}