{
  "type": "Feature",
  "properties": {
    "iso:country":"US",
    "sg:address":"6943 NW 26th St",
    "sg:city":"Pompano Beach",
    "sg:classifiers":[
        {
            "category":"Banks & Credit Unions",
            "subcategory":"Investment Brokerage",
            "type":"Services"
        }
    ],
    "sg:phone":"+1 954 346 8596",
    "sg:postcode":"33063",
    "sg:province":"FL",
    "sg:tags":[
        "advisory"
    ],
    "wof:name":"Deran High Tech Corp",
    "wof:placetype":"venue"
},
  "geometry": {"coordinates":[-80.220929,26.25972],"type":"Point"}
}