{
  "type": "Feature",
  "properties": {
    "iso:country":"US",
    "sg:address":"4357 Rock Island Rd",
    "sg:city":"Fort Lauderdale",
    "sg:classifiers":[
        {
            "category":"Home & Garden",
            "subcategory":"Furniture",
            "type":"Retail Goods"
        }
    ],
    "sg:phone":"+1 954 735 3351",
    "sg:postcode":"33319",
    "sg:province":"FL",
    "sg:tags":[
        "mattress"
    ],
    "wof:name":"Discount Mattress Express Inc",
    "wof:placetype":"venue"
},
  "geometry": {"coordinates":[-80.220682,26.173084],"type":"Point"}
}