{
  "type": "Feature",
  "properties": {
    "iso:country":"US",
    "sg:address":"524 Cape Cod Ln",
    "sg:city":"Altamonte Springs",
    "sg:classifiers":[
        {
            "category":"Shopping",
            "subcategory":"Gifts & Souvenirs",
            "type":"Retail Goods"
        }
    ],
    "sg:phone":"+1 407 786 3816",
    "sg:postcode":"32714",
    "sg:province":"FL",
    "wof:name":"Grace Gift Shop",
    "wof:placetype":"venue"
},
  "geometry": {"coordinates":[-81.41907500000001,28.67203],"type":"Point"}
}