{
  "type": "Feature",
  "properties": {
    "addr:full":"12249 Country Cove Ct Jacksonville FL 32225",
    "addr:housenumber":"12249",
    "addr:postcode":"32225",
    "addr:street":"Country Cove Ct",
    "iso:country":"US",
    "sg:address":"12249 Country Cove Ct",
    "sg:city":"Jacksonville",
    "sg:classifiers":[
        {
            "category":"Wholesale",
            "subcategory":"Machinery & Supplies",
            "type":"Manufacturing & Wholesale Goods"
        }
    ],
    "sg:phone":"+1 904 221 7157",
    "sg:postcode":"32225",
    "sg:province":"FL",
    "sg:tags":[
        "equipment",
        "establishment"
    ],
    "wof:name":"Pool Beautician",
    "wof:placetype":"venue"
},
  "geometry": {"coordinates":[-81.48763,30.329276],"type":"Point"}
}