{
  "type": "Feature",
  "properties": {
    "addr:full":"2404 Sam Rd Jacksonville FL 32216",
    "addr:housenumber":"2404",
    "addr:postcode":"32216",
    "addr:street":"Sam Rd",
    "iso:country":"US",
    "sg:address":"2404 Sam Rd",
    "sg:city":"Jacksonville",
    "sg:classifiers":[
        {
            "category":"Shopping",
            "subcategory":"Gifts & Souvenirs",
            "type":"Retail Goods"
        }
    ],
    "sg:phone":"+1 904 725 2479",
    "sg:postcode":"32216",
    "sg:province":"FL",
    "wof:name":"Discount Gifts",
    "wof:placetype":"venue"
},
  "geometry": {"coordinates":[-81.595753,30.277297],"type":"Point"}
}