{
  "type": "Feature",
  "properties": {
    "iso:country":"US",
    "sg:address":"10910 W Flagler St",
    "sg:city":"Miami",
    "sg:classifiers":[
        {
            "category":"Restaurant",
            "type":"Food & Drink"
        }
    ],
    "sg:phone":"+1 305 220 3333",
    "sg:postcode":"33174",
    "sg:province":"FL",
    "sg:tags":[
        "pizza"
    ],
    "wof:name":"Jerry & Joe's Pizza",
    "wof:placetype":"venue"
},
  "geometry": {"coordinates":[-80.373178,25.768366],"type":"Point"}
}