{
  "type": "Feature",
  "properties": {
    "iso:country":"US",
    "sg:address":"2500 W 84th St",
    "sg:city":"Hialeah",
    "sg:classifiers":[
        {
            "category":"Manufacturing",
            "subcategory":"Apparel",
            "type":"Manufacturing & Wholesale Goods"
        }
    ],
    "sg:phone":"+1 305 820 5400",
    "sg:postcode":"33016",
    "sg:province":"FL",
    "sg:tags":[
        "mfg",
        "belt"
    ],
    "wof:name":"Belts Inc",
    "wof:placetype":"venue"
},
  "geometry": {"coordinates":[-80.333799,25.89752],"type":"Point"}
}