{
  "type": "Feature",
  "properties": {
    "iso:country":"US",
    "sg:address":"8701 US Hwy 19",
    "sg:city":"Port Richey",
    "sg:classifiers":[
        {
            "category":"Shopping",
            "type":"Retail Goods"
        }
    ],
    "sg:phone":"+1 727 834 9503",
    "sg:postcode":"34668",
    "sg:province":"FL",
    "sg:tags":[
        "merchandise"
    ],
    "wof:name":"National Hearing Centers  Inc",
    "wof:placetype":"venue"
},
  "geometry": {"coordinates":[-82.71538700000001,28.283701],"type":"Point"}
}