{
  "type": "Feature",
  "properties": {
    "iso:country":"US",
    "sg:address":"3032 Bloomsbury Dr",
    "sg:city":"Kissimmee",
    "sg:classifiers":[
        {
            "category":"Home & Garden",
            "subcategory":"Building Materials",
            "type":"Retail Goods"
        }
    ],
    "sg:phone":"+1 407 396 0997",
    "sg:postcode":"34747",
    "sg:province":"FL",
    "wof:name":"1st America Overhead Doors",
    "wof:placetype":"venue"
},
  "geometry": {"coordinates":[-81.641747,28.33887],"type":"Point"}
}