{
  "type": "Feature",
  "properties": {
    "addr:full":"1046 W Busch Blvd Tampa FL 33612",
    "addr:housenumber":"1046",
    "addr:postcode":"33612",
    "addr:street":"W Busch Blvd",
    "iso:country":"US",
    "sg:address":"1046 W Busch Blvd",
    "sg:city":"Tampa",
    "sg:classifiers":[
        {
            "category":"Personal",
            "subcategory":"Beauty Salon",
            "type":"Services"
        }
    ],
    "sg:phone":"+1 813 932 4400",
    "sg:postcode":"33612",
    "sg:province":"FL",
    "sg:tags":[
        "shop",
        "spa",
        "day"
    ],
    "wof:name":"Bioganic Facial Clinic",
    "wof:placetype":"venue"
},
  "geometry": {"coordinates":[-82.471182,28.033327],"type":"Point"}
}