{
  "type": "Feature",
  "properties": {
    "iso:country":"US",
    "sg:address":"1650 Sand Lake Rd",
    "sg:city":"Orlando",
    "sg:classifiers":[
        {
            "category":"Professional",
            "subcategory":"Employment Agencies",
            "type":"Services"
        }
    ],
    "sg:phone":"+1 407 851 5997",
    "sg:postcode":"32809",
    "sg:province":"FL",
    "sg:tags":[
        "temporary",
        "help",
        "contractor"
    ],
    "wof:name":"Kelly Services Inc",
    "wof:placetype":"venue"
},
  "geometry": {"coordinates":[-81.39864900000001,28.450275],"type":"Point"}
}