{
  "type": "Feature",
  "properties": {
    "iso:country":"US",
    "sg:address":"4460 SW 35th Ter",
    "sg:city":"Gainesville",
    "sg:classifiers":[
        {
            "category":"Building & Trades",
            "subcategory":"Electrical",
            "type":"Services"
        }
    ],
    "sg:phone":"+1 352 335 7101",
    "sg:postcode":"32608",
    "sg:province":"FL",
    "sg:tags":[
        "industrial",
        "electrician",
        "contractors-commercial",
        "electric"
    ],
    "wof:name":"Bolt Electric Contractors Inc",
    "wof:placetype":"venue"
},
  "geometry": {"coordinates":[-82.375103,29.611746],"type":"Point"}
}