{
  "type": "Feature",
  "properties": {
    "iso:country":"US",
    "sg:address":"9875 Heather Dr",
    "sg:city":"Cantonment",
    "sg:classifiers":[
        {
            "category":"Autos & Motor Vehicles",
            "subcategory":"Fuel & Gas Station",
            "type":"Retail Goods"
        }
    ],
    "sg:phone":"+1 850 456 2103",
    "sg:postcode":"32533",
    "sg:province":"FL",
    "sg:tags":[
        "station",
        "gasoline"
    ],
    "wof:name":"Beacons Store",
    "wof:placetype":"venue"
},
  "geometry": {"coordinates":[-87.322682,30.543275],"type":"Point"}
}