{
  "type": "Feature",
  "properties": {
    "iso:country":"US",
    "sg:address":"516 10th St W",
    "sg:city":"Bradenton",
    "sg:classifiers":[
        {
            "category":"Professional",
            "subcategory":"Lawyer & Legal Services",
            "type":"Services"
        }
    ],
    "sg:phone":"+1 941 747 2215",
    "sg:postcode":"34205",
    "sg:province":"FL",
    "sg:tags":[
        "attorney"
    ],
    "wof:name":"Haynes & Miller",
    "wof:placetype":"venue"
},
  "geometry": {"coordinates":[-82.572036,27.494368],"type":"Point"}
}