{
  "type": "Feature",
  "properties": {
    "iso:country":"US",
    "sg:address":"800 S Florida Ave",
    "sg:city":"Lakeland",
    "sg:classifiers":[
        {
            "category":"Professional",
            "subcategory":"Lawyer & Legal Services",
            "type":"Services"
        }
    ],
    "sg:phone":"+1 863 683 1111",
    "sg:postcode":"33801",
    "sg:province":"FL",
    "sg:tags":[
        "attorney"
    ],
    "wof:name":"Lilly O'Toole & Brown",
    "wof:placetype":"venue"
},
  "geometry": {"coordinates":[-81.95714099999999,28.034262],"type":"Point"}
}