{
  "type": "Feature",
  "properties": {
    "addr:full":"2301 Centennial Blvd Leesburg FL 34748",
    "addr:housenumber":"2301",
    "addr:postcode":"34748",
    "addr:street":"Centennial Blvd",
    "iso:country":"US",
    "sg:address":"2301 Centennial Blvd",
    "sg:city":"Leesburg",
    "sg:classifiers":[
        {
            "category":"Professional",
            "type":"Services"
        }
    ],
    "sg:phone":"+1 352 787 0732",
    "sg:postcode":"34748",
    "sg:province":"FL",
    "wof:name":"Lovol Corp",
    "wof:placetype":"venue"
},
  "geometry": {"coordinates":[-81.913599,28.838336],"type":"Point"}
}