{
  "type": "Feature",
  "properties": {
    "iso:country":"US",
    "sg:address":"6890 SW 9th Pl",
    "sg:city":"North Lauderdale",
    "sg:classifiers":[
        {
            "category":"Retail",
            "subcategory":"Repair Shop",
            "type":"Services"
        }
    ],
    "sg:phone":"+1 954 917 4405",
    "sg:postcode":"33068",
    "sg:province":"FL",
    "sg:tags":[
        "screen"
    ],
    "wof:name":"Zimmerman Screen",
    "wof:placetype":"venue"
},
  "geometry": {"coordinates":[-80.217838,26.216992],"type":"Point"}
}