{
  "type": "Feature",
  "properties": {
    "iso:country":"US",
    "sg:address":"8940 N Kendall Dr",
    "sg:city":"Miami",
    "sg:classifiers":[
        {
            "category":"Health Services",
            "subcategory":"Doctor",
            "type":"Services"
        }
    ],
    "sg:phone":"+1 305 835 7300",
    "sg:postcode":"33176",
    "sg:province":"FL",
    "sg:tags":[
        "physician",
        "surgeon"
    ],
    "wof:name":"Florida Hand Surgery",
    "wof:placetype":"venue"
},
  "geometry": {"coordinates":[-80.341283,25.687705],"type":"Point"}
}