{
  "type": "Feature",
  "properties": {
    "addr:full":"1655 Drexel Ave Miami Beach FL 33139",
    "addr:housenumber":"1655",
    "addr:postcode":"33139",
    "addr:street":"Drexel Ave",
    "iso:country":"US",
    "sg:address":"1655 Drexel Ave",
    "sg:city":"Miami Beach",
    "sg:classifiers":[
        {
            "category":"Professional",
            "subcategory":"Advertising",
            "type":"Services"
        }
    ],
    "sg:phone":"+1 305 672 3293",
    "sg:postcode":"33139",
    "sg:province":"FL",
    "sg:tags":[
        "counselor"
    ],
    "sg:website":"www.jacober.com",
    "wof:name":"Jacober & Assoc",
    "wof:placetype":"venue"
},
  "geometry": {"coordinates":[-80.133067,25.791078],"type":"Point"}
}