{
  "type": "Feature",
  "properties": {
    "iso:country":"US",
    "sg:address":"369 Ave Leona",
    "sg:city":"Sarasota",
    "sg:classifiers":[
        {
            "category":"Building & Trades",
            "subcategory":"Landscaping Services",
            "type":"Services"
        }
    ],
    "sg:phone":"+1 941 349 6379",
    "sg:postcode":"34242",
    "sg:province":"FL",
    "wof:name":"Siesta Charters",
    "wof:placetype":"venue"
},
  "geometry": {"coordinates":[-82.562713,27.278864],"type":"Point"}
}