{
  "type": "Feature",
  "properties": {
    "addr:full":"201 NW 46th Ave Plantation FL 33317",
    "addr:housenumber":"201",
    "addr:postcode":"33317",
    "addr:street":"Nw 46Th Ave",
    "iso:country":"US",
    "sg:address":"201 NW 46th Ave",
    "sg:city":"Plantation",
    "sg:classifiers":[
        {
            "category":"Education",
            "subcategory":"School",
            "type":"Public Place"
        }
    ],
    "sg:phone":"+1 954 316 8301",
    "sg:postcode":"33317",
    "sg:province":"FL",
    "wof:name":"Broward JUNIOR Academy",
    "wof:placetype":"venue"
},
  "geometry": {"coordinates":[-80.210145,26.12408],"type":"Point"}
}