{
  "type": "Feature",
  "properties": {
    "iso:country":"US",
    "sg:address":"3633 Reynolds Rd",
    "sg:city":"Lakeland",
    "sg:classifiers":[
        {
            "category":"Manufacturing",
            "subcategory":"Chemicals & Compounds",
            "type":"Manufacturing & Wholesale Goods"
        }
    ],
    "sg:phone":"+1 863 667 4450",
    "sg:postcode":"33803",
    "sg:province":"FL",
    "sg:tags":[
        "preparation",
        "equipment",
        "industrial",
        "mfg"
    ],
    "wof:name":"Graphic Sciences",
    "wof:placetype":"venue"
},
  "geometry": {"coordinates":[-81.891268,27.999172],"type":"Point"}
}