{
  "type": "Feature",
  "properties": {
    "addr:full":"1606 N Main St Jacksonville FL 32206",
    "addr:housenumber":"1606",
    "addr:postcode":"32206",
    "addr:street":"N Main St",
    "iso:country":"US",
    "sg:address":"1606 N Main St",
    "sg:city":"Jacksonville",
    "sg:classifiers":[
        {
            "category":"Retail",
            "subcategory":"Portrait Studio",
            "type":"Services"
        },
        {
            "category":"Insurance",
            "subcategory":"Insurance Agent",
            "type":"Services"
        }
    ],
    "sg:phone":"+1 904 356 6305",
    "sg:postcode":"32206",
    "sg:province":"FL",
    "sg:tags":[
        "photo"
    ],
    "wof:name":"Gator Auto Insurance Agency",
    "wof:placetype":"venue"
},
  "geometry": {"coordinates":[-81.65419900000001,30.344341],"type":"Point"}
}