{
  "type": "Feature",
  "properties": {
    "addr:full":"6890 Miramar Pkwy Miramar FL 33023",
    "addr:housenumber":"6890",
    "addr:postcode":"33023",
    "addr:street":"Miramar Pkwy",
    "iso:country":"US",
    "sg:address":"6890 Miramar Pkwy",
    "sg:city":"Miramar",
    "sg:classifiers":[
        {
            "category":"Shopping",
            "subcategory":"Pharmacy",
            "type":"Retail Goods"
        }
    ],
    "sg:phone":"+1 954 963 7513",
    "sg:postcode":"33023",
    "sg:province":"FL",
    "wof:name":"CVS Pharmacy",
    "wof:placetype":"venue"
},
  "geometry": {"coordinates":[-80.22586699999999,25.981949],"type":"Point"}
}