{
  "type": "Feature",
  "properties": {
    "iso:country":"US",
    "sg:address":"1030 Arabian Dr",
    "sg:city":"Loxahatchee",
    "sg:classifiers":[
        {
            "category":"Professional",
            "type":"Services"
        }
    ],
    "sg:phone":"+1 561 820 0834",
    "sg:postcode":"33470",
    "sg:province":"FL",
    "sg:tags":[
        "artist"
    ],
    "wof:name":"E R Painting",
    "wof:placetype":"venue"
},
  "geometry": {"coordinates":[-80.328676,26.695001],"type":"Point"}
}