{
  "type": "Feature",
  "properties": {
    "iso:country":"US",
    "sg:address":"127 W 23rd St",
    "sg:city":"Panama City",
    "sg:classifiers":[
        {
            "category":"Health Services",
            "subcategory":"Chiropractor",
            "type":"Services"
        }
    ],
    "sg:phone":"+1 850 872 8880",
    "sg:postcode":"32405",
    "sg:province":"FL",
    "wof:name":"Chiro Network Health Care Ctr",
    "wof:placetype":"venue"
},
  "geometry": {"coordinates":[-85.660962,30.189549],"type":"Point"}
}