{
  "type": "Feature",
  "properties": {
    "iso:country":"US",
    "sg:address":"11147 NW 6th St",
    "sg:city":"Miami",
    "sg:classifiers":[
        {
            "category":"Health Services",
            "subcategory":"Nursing And Care Facility",
            "type":"Services"
        }
    ],
    "sg:phone":"+1 305 225 7717",
    "sg:postcode":"33172",
    "sg:province":"FL",
    "sg:tags":[
        "residential"
    ],
    "wof:name":"Nubias Health Care Center Cor",
    "wof:placetype":"venue"
},
  "geometry": {"coordinates":[-80.376999,25.774338],"type":"Point"}
}