{
  "type": "Feature",
  "properties": {
    "iso:country":"US",
    "sg:address":"5225 Sorrell Dr",
    "sg:city":"Melbourne",
    "sg:classifiers":[
        {
            "category":"Building & Trades",
            "subcategory":"Landscaping Services",
            "type":"Services"
        }
    ],
    "sg:phone":"+1 321 259 4227",
    "sg:postcode":"32934",
    "sg:province":"FL",
    "sg:tags":[
        "yard",
        "care"
    ],
    "wof:name":"Wilmarths S Dixie Greens Lawn",
    "wof:placetype":"venue"
},
  "geometry": {"coordinates":[-80.715501,28.14987],"type":"Point"}
}