{
  "type": "Feature",
  "properties": {
    "iso:country":"US",
    "sg:address":"857 SE 47th Ter",
    "sg:city":"Cape Coral",
    "sg:classifiers":[
        {
            "category":"Professional",
            "subcategory":"Art Services",
            "type":"Services"
        }
    ],
    "sg:phone":"+1 239 945 2525",
    "sg:postcode":"33904",
    "sg:province":"FL",
    "sg:tags":[
        "commercial",
        "design",
        "datum"
    ],
    "wof:name":"Intergraphic",
    "wof:placetype":"venue"
},
  "geometry": {"coordinates":[-81.954337,26.563811],"type":"Point"}
}