{
  "type": "Feature",
  "properties": {
    "iso:country":"US",
    "sg:address":"10055 NW 19th St",
    "sg:city":"Doral",
    "sg:classifiers":[
        {
            "category":"Real Estate",
            "subcategory":"Architect",
            "type":"Services"
        }
    ],
    "sg:phone":"+1 305 477 0800",
    "sg:postcode":"33172",
    "sg:province":"FL",
    "wof:name":"G T Scale Models Inc",
    "wof:placetype":"venue"
},
  "geometry": {"coordinates":[-80.360327,25.791338],"type":"Point"}
}