{
  "type": "Feature",
  "properties": {
    "iso:country":"US",
    "sg:address":"953 N Ronald Reagan Blvd",
    "sg:city":"Longwood",
    "sg:classifiers":[
        {
            "category":"Retail",
            "subcategory":"Auto Repair",
            "type":"Services"
        }
    ],
    "sg:phone":"+1 407 695 4299",
    "sg:postcode":"32750",
    "sg:province":"FL",
    "sg:tags":[
        "automobile",
        "electric"
    ],
    "wof:name":"Longwood Auto Electric",
    "wof:placetype":"venue"
},
  "geometry": {"coordinates":[-81.34223799999999,28.708092],"type":"Point"}
}