{
  "type": "Feature",
  "properties": {
    "addr:full":"101 W 1st St Sanford FL 32771",
    "addr:housenumber":"101",
    "addr:postcode":"32771",
    "addr:street":"W 1St St",
    "iso:country":"US",
    "sg:address":"101 W 1st St",
    "sg:city":"Sanford",
    "sg:classifiers":[
        {
            "category":"Insurance",
            "subcategory":"Insurance Agent",
            "type":"Services"
        }
    ],
    "sg:phone":"+1 407 324 3800",
    "sg:postcode":"32771",
    "sg:province":"FL",
    "wof:name":"Allstate",
    "wof:placetype":"venue"
},
  "geometry": {"coordinates":[-81.268793,28.811698],"type":"Point"}
}