{
  "type": "Feature",
  "properties": {
    "iso:country":"US",
    "sg:address":"625 E Atlantic Blvd",
    "sg:city":"Pompano Beach",
    "sg:classifiers":[
        {
            "category":"Restaurant",
            "type":"Food & Drink"
        }
    ],
    "sg:phone":"+1 954 943 2140",
    "sg:postcode":"33060",
    "sg:province":"FL",
    "wof:name":"Bagel Restaurant",
    "wof:placetype":"venue"
},
  "geometry": {"coordinates":[-80.11685,26.231757],"type":"Point"}
}