{
  "type": "Feature",
  "properties": {
    "addr:full":"1108 Nebraska Ave Palm Harbor FL 34683",
    "addr:housenumber":"1108",
    "addr:postcode":"34683",
    "addr:street":"Nebraska Ave",
    "iso:country":"US",
    "sg:address":"1108 Nebraska Ave",
    "sg:city":"Palm Harbor",
    "sg:classifiers":[
        {
            "category":"Shopping",
            "subcategory":"Computers & Home Electronics",
            "type":"Retail Goods"
        }
    ],
    "sg:phone":"+1 727 772 1886",
    "sg:postcode":"34683",
    "sg:province":"FL",
    "sg:tags":[
        "sales",
        "software"
    ],
    "wof:name":"Automated Software Technology",
    "wof:placetype":"venue"
},
  "geometry": {"coordinates":[-82.765045,28.078919],"type":"Point"}
}