{
  "type": "Feature",
  "properties": {
    "iso:country":"US",
    "sg:address":"26200 SW 130th Pl",
    "sg:city":"Homestead",
    "sg:classifiers":[
        {
            "category":"Manufacturing",
            "subcategory":"Metals",
            "type":"Manufacturing & Wholesale Goods"
        }
    ],
    "sg:phone":"+1 305 258 9091",
    "sg:postcode":"33032",
    "sg:province":"FL",
    "sg:tags":[
        "coating",
        "powder"
    ],
    "wof:name":"Powdercoat Junction Inc",
    "wof:placetype":"venue"
},
  "geometry": {"coordinates":[-80.40299899999999,25.524393],"type":"Point"}
}