{
  "type": "Feature",
  "properties": {
    "addr:full":"4125 Macaulay Ln Sarasota FL 34241",
    "addr:housenumber":"4125",
    "addr:postcode":"34241",
    "addr:street":"Macaulay Ln",
    "iso:country":"US",
    "sg:address":"4125 Macaulay Ln",
    "sg:city":"Sarasota",
    "sg:classifiers":[
        {
            "category":"Autos & Motor Vehicles",
            "subcategory":"Boat Sales",
            "type":"Retail Goods"
        }
    ],
    "sg:phone":"+1 941 377 8696",
    "sg:postcode":"34241",
    "sg:province":"FL",
    "wof:name":"Tides Boatworks Inc",
    "wof:placetype":"venue"
},
  "geometry": {"coordinates":[-82.41543799999999,27.293766],"type":"Point"}
}