{
  "type": "Feature",
  "properties": {
    "iso:country":"US",
    "sg:address":"3303 37th St",
    "sg:city":"Orlando",
    "sg:classifiers":[
        {
            "category":"Building & Trades",
            "subcategory":"Construction",
            "type":"Services"
        }
    ],
    "sg:phone":"+1 407 843 6666",
    "sg:postcode":"32839",
    "sg:province":"FL",
    "sg:tags":[
        "paving",
        "contractor"
    ],
    "wof:name":"CSE Paving",
    "wof:placetype":"venue"
},
  "geometry": {"coordinates":[-81.422667,28.505244],"type":"Point"}
}