{
  "type": "Feature",
  "properties": {
    "iso:country":"US",
    "sg:address":"1555 Washington Ave",
    "sg:city":"Miami Beach",
    "sg:classifiers":[
        {
            "category":"Restaurant",
            "type":"Food & Drink"
        }
    ],
    "sg:phone":"+1 305 538 4330",
    "sg:postcode":"33139",
    "sg:province":"FL",
    "wof:name":"Fuddruckers",
    "wof:placetype":"venue"
},
  "geometry": {"coordinates":[-80.131737,25.788871],"type":"Point"}
}