{
  "type": "Feature",
  "properties": {
    "iso:country":"US",
    "sg:address":"1704 Huntington Ct",
    "sg:city":"Safety Harbor",
    "sg:classifiers":[
        {
            "category":"Restaurant",
            "type":"Food & Drink"
        }
    ],
    "sg:phone":"+1 727 725 4733",
    "sg:postcode":"34695",
    "sg:province":"FL",
    "wof:name":"Lierjet International Inc",
    "wof:placetype":"venue"
},
  "geometry": {"coordinates":[-82.70401,28.00761],"type":"Point"}
}