{
  "type": "Feature",
  "properties": {
    "addr:full":"2561 Countryside Blvd Clearwater FL 33761",
    "addr:housenumber":"2561",
    "addr:postcode":"33761",
    "addr:street":"Countryside Blvd",
    "iso:country":"US",
    "sg:address":"2561 Countryside Blvd",
    "sg:city":"Clearwater",
    "sg:classifiers":[
        {
            "category":"Professional",
            "subcategory":"Business Services",
            "type":"Services"
        }
    ],
    "sg:phone":"+1 727 724 8100",
    "sg:postcode":"33761",
    "sg:province":"FL",
    "wof:name":"Monograms Plus Inc",
    "wof:placetype":"venue"
},
  "geometry": {"coordinates":[-82.731797,28.015307],"type":"Point"}
}