{
  "type": "Feature",
  "properties": {
    "iso:country":"US",
    "sg:address":"18911 S Tamiami Trl",
    "sg:city":"Fort Myers",
    "sg:classifiers":[
        {
            "category":"Shopping",
            "subcategory":"Computers & Home Electronics",
            "type":"Retail Goods"
        }
    ],
    "sg:phone":"+1 239 267 1235",
    "sg:postcode":"33908",
    "sg:province":"FL",
    "wof:name":"Radio Shack",
    "wof:placetype":"venue"
},
  "geometry": {"coordinates":[-81.831678,26.464651],"type":"Point"}
}