{
  "type": "Feature",
  "properties": {
    "iso:country":"US",
    "sg:address":"5807 N 56th St",
    "sg:city":"Tampa",
    "sg:classifiers":[
        {
            "category":"Personal",
            "subcategory":"Beauty Salon",
            "type":"Services"
        }
    ],
    "sg:phone":"+1 813 627 8844",
    "sg:postcode":"33610",
    "sg:province":"FL",
    "wof:name":"Khair Stylists",
    "wof:placetype":"venue"
},
  "geometry": {"coordinates":[-82.393477,28.002458],"type":"Point"}
}