{
  "type": "Feature",
  "properties": {
    "iso:country":"US",
    "sg:address":"7810 NW 16th Ct",
    "sg:city":"Pembroke Pines",
    "sg:classifiers":[
        {
            "category":"Building & Trades",
            "subcategory":"Cleaning & Sanitation",
            "type":"Services"
        }
    ],
    "sg:phone":"+1 954 261 0312",
    "sg:postcode":"33024",
    "sg:province":"FL",
    "sg:tags":[
        "house"
    ],
    "wof:name":"Blessed Homes Cleaning Svc Inc",
    "wof:placetype":"venue"
},
  "geometry": {"coordinates":[-80.245428,26.022988],"type":"Point"}
}