{
  "type": "Feature",
  "properties": {
    "iso:country":"US",
    "sg:address":"108 W Beresford Ave",
    "sg:city":"Deland",
    "sg:classifiers":[
        {
            "category":"Retail",
            "subcategory":"Auto Repair",
            "type":"Services"
        }
    ],
    "sg:phone":"+1 386 740 0008",
    "sg:postcode":"32720",
    "sg:province":"FL",
    "sg:tags":[
        "body",
        "shop"
    ],
    "wof:name":"Expert Body Shop",
    "wof:placetype":"venue"
},
  "geometry": {"coordinates":[-81.3032,29.013901],"type":"Point"}
}