{
  "type": "Feature",
  "properties": {
    "iso:country":"US",
    "sg:address":"13917 Middle Park Dr",
    "sg:city":"Tampa",
    "sg:classifiers":[
        {
            "category":"Banks & Credit Unions",
            "subcategory":"Investment Brokerage",
            "type":"Services"
        }
    ],
    "sg:phone":"+1 813 961 3856",
    "sg:postcode":"33624",
    "sg:province":"FL",
    "sg:tags":[
        "trust"
    ],
    "wof:name":"Abdon Rodriguez Family Foundation Inc",
    "wof:placetype":"venue"
},
  "geometry": {"coordinates":[-82.518069,28.073267],"type":"Point"}
}