{
  "type": "Feature",
  "properties": {
    "iso:country":"US",
    "sg:address":"1550 NE 147th St",
    "sg:city":"Miami",
    "sg:classifiers":[
        {
            "category":"Social Services",
            "subcategory":"Child Care",
            "type":"Services"
        }
    ],
    "sg:phone":"+1 305 956 2468",
    "sg:postcode":"33161",
    "sg:province":"FL",
    "sg:tags":[
        "day"
    ],
    "wof:name":"Kid R First",
    "wof:placetype":"venue"
},
  "geometry": {"coordinates":[-80.16739699999999,25.9109],"type":"Point"}
}