{
  "type": "Feature",
  "properties": {
    "addr:full":"1200 E 6th Ave Tallahassee FL 32303",
    "addr:housenumber":"1200",
    "addr:postcode":"32303",
    "addr:street":"E 6Th Ave",
    "iso:country":"US",
    "sg:address":"1200 E 6th Ave",
    "sg:city":"Tallahassee",
    "sg:classifiers":[
        {
            "category":"Banks & Credit Unions",
            "subcategory":"Bank",
            "type":"Services"
        }
    ],
    "sg:phone":"+1 850 431 5301",
    "sg:postcode":"32303",
    "sg:province":"FL",
    "wof:name":"TMH Federal Credit Union",
    "wof:placetype":"venue"
},
  "geometry": {"coordinates":[-84.26434399999999,30.456312],"type":"Point"}
}