{
  "type": "Feature",
  "properties": {
    "addr:full":"1007 W Powhatan Ave Tampa FL 33603",
    "addr:housenumber":"1007",
    "addr:postcode":"33603",
    "addr:street":"W Powhatan Ave",
    "iso:country":"US",
    "sg:address":"1007 W Powhatan Ave",
    "sg:city":"Tampa",
    "sg:classifiers":[
        {
            "category":"Freight",
            "type":"Transportation"
        }
    ],
    "sg:phone":"+1 813 231 2133",
    "sg:postcode":"33603",
    "sg:province":"FL",
    "sg:tags":[
        "operator",
        "local",
        "trucking"
    ],
    "wof:name":"Ruffroad Trucking Inc",
    "wof:placetype":"venue"
},
  "geometry": {"coordinates":[-82.47483800000001,27.999389],"type":"Point"}
}