{
  "type": "Feature",
  "properties": {
    "iso:country":"US",
    "sg:address":"5401 S Kirkman Rd",
    "sg:city":"Orlando",
    "sg:classifiers":[
        {
            "category":"Government",
            "subcategory":"Office",
            "type":"Public Place"
        }
    ],
    "sg:phone":"+1 407 903 7350",
    "sg:postcode":"32819",
    "sg:province":"FL",
    "sg:tags":[
        "state",
        "taxation"
    ],
    "wof:name":"Revenue Dept",
    "wof:placetype":"venue"
},
  "geometry": {"coordinates":[-81.458786,28.484312],"type":"Point"}
}