{
  "type": "Feature",
  "properties": {
    "addr:full":"3520 Thomasville Rd Tallahassee FL 32309",
    "addr:housenumber":"3520",
    "addr:postcode":"32309",
    "addr:street":"Thomasville Rd",
    "iso:country":"US",
    "sg:address":"3520 Thomasville Rd",
    "sg:city":"Tallahassee",
    "sg:classifiers":[
        {
            "category":"Insurance",
            "subcategory":"Insurance Agent",
            "type":"Services"
        }
    ],
    "sg:phone":"+1 850 668 3000",
    "sg:postcode":"32309",
    "sg:province":"FL",
    "sg:tags":[
        "management"
    ],
    "wof:name":"Health Enterprises Inc",
    "wof:placetype":"venue"
},
  "geometry": {"coordinates":[-84.246623,30.51078],"type":"Point"}
}