{
  "type": "Feature",
  "properties": {
    "addr:full":"922 Palm Way West Palm Beach FL 33408",
    "addr:housenumber":"922",
    "addr:postcode":"33408",
    "addr:street":"Palm Way",
    "iso:country":"US",
    "sg:address":"922 Palm Way",
    "sg:city":"West Palm Beach",
    "sg:classifiers":[
        {
            "category":"Shopping",
            "subcategory":"Clothing, Apparel, & Fashions",
            "type":"Retail Goods"
        }
    ],
    "sg:phone":"+1 561 881 8769",
    "sg:postcode":"33408",
    "sg:province":"FL",
    "sg:tags":[
        "furnishing"
    ],
    "wof:name":"Michael's European Men's Wear",
    "wof:placetype":"venue"
},
  "geometry": {"coordinates":[-80.049454,26.851501],"type":"Point"}
}