{
  "type": "Feature",
  "properties": {
    "iso:country":"US",
    "sg:address":"729 Roberts Ave",
    "sg:city":"Deland",
    "sg:classifiers":[
        {
            "category":"Professional",
            "subcategory":"Business Services",
            "type":"Services"
        }
    ],
    "sg:phone":"+1 386 801 2601",
    "sg:postcode":"32724",
    "sg:province":"FL",
    "wof:name":"A M Svc",
    "wof:placetype":"venue"
},
  "geometry": {"coordinates":[-81.29064,29.044654],"type":"Point"}
}