{
  "type": "Feature",
  "properties": {
    "iso:country":"US",
    "sg:address":"4131 NW 13th St",
    "sg:city":"Gainesville",
    "sg:classifiers":[
        {
            "category":"Real Estate",
            "subcategory":"Real Estate Operator",
            "type":"Services"
        }
    ],
    "sg:phone":"+1 352 372 1535",
    "sg:postcode":"32609",
    "sg:province":"FL",
    "sg:tags":[
        "building",
        "parks",
        "nonresidential"
    ],
    "wof:name":"Executive Center",
    "wof:placetype":"venue"
},
  "geometry": {"coordinates":[-82.338939,29.690186],"type":"Point"}
}