{
  "type": "Feature",
  "properties": {
    "iso:country":"US",
    "sg:address":"1515 N University Dr",
    "sg:city":"Coral Springs",
    "sg:classifiers":[
        {
            "category":"Real Estate",
            "subcategory":"Real Estate Agent",
            "type":"Services"
        }
    ],
    "sg:phone":"+1 954 340 3707",
    "sg:postcode":"33071",
    "sg:province":"FL",
    "wof:name":"Cole Realty",
    "wof:placetype":"venue"
},
  "geometry": {"coordinates":[-80.253219,26.24924],"type":"Point"}
}