{
  "type": "Feature",
  "properties": {
    "addr:full":"4555 Southside Blvd Jacksonville FL 32216",
    "addr:housenumber":"4555",
    "addr:postcode":"32216",
    "addr:street":"Southside Blvd",
    "iso:country":"US",
    "sg:address":"4555 Southside Blvd",
    "sg:city":"Jacksonville",
    "sg:classifiers":[
        {
            "category":"Restaurant",
            "type":"Food & Drink"
        }
    ],
    "sg:phone":"+1 904 998 9778",
    "sg:postcode":"32216",
    "sg:province":"FL",
    "wof:name":"Don Pablo's Mexican Kitchen",
    "wof:placetype":"venue"
},
  "geometry": {"coordinates":[-81.55731299999999,30.262783],"type":"Point"}
}