{
  "type": "Feature",
  "properties": {
    "addr:full":"4571 Sheridan St Hollywood FL 33021",
    "addr:housenumber":"4571",
    "addr:postcode":"33021",
    "addr:street":"Sheridan St",
    "iso:country":"US",
    "sg:address":"4571 Sheridan St",
    "sg:city":"Hollywood",
    "sg:classifiers":[
        {
            "category":"Communications",
            "subcategory":"Radio Station",
            "type":"Services"
        }
    ],
    "sg:phone":"+1 954 983 6695",
    "sg:postcode":"33021",
    "sg:province":"FL",
    "sg:tags":[
        "broadcast"
    ],
    "wof:name":"TCI of Hollywood",
    "wof:placetype":"venue"
},
  "geometry": {"coordinates":[-80.189144,26.032858],"type":"Point"}
}