{
  "type": "Feature",
  "properties": {
    "addr:full":"3347 Fowler St Fort Myers FL 33901",
    "addr:housenumber":"3347",
    "addr:postcode":"33901",
    "addr:street":"Fowler St",
    "iso:country":"US",
    "sg:address":"3347 Fowler St",
    "sg:city":"Fort Myers",
    "sg:classifiers":[
        {
            "category":"Retail",
            "subcategory":"Repair Shop",
            "type":"Services"
        }
    ],
    "sg:phone":"+1 239 936 4104",
    "sg:postcode":"33901",
    "sg:province":"FL",
    "sg:tags":[
        "appliance"
    ],
    "wof:name":"A & A Appliance",
    "wof:placetype":"venue"
},
  "geometry": {"coordinates":[-81.86187,26.616016],"type":"Point"}
}