{
  "type": "Feature",
  "properties": {
    "iso:country":"US",
    "sg:address":"1411 Edgewater Dr",
    "sg:city":"Orlando",
    "sg:classifiers":[
        {
            "category":"Banks & Credit Unions",
            "subcategory":"Bank",
            "type":"Services"
        }
    ],
    "sg:phone":"+1 407 447 0386",
    "sg:postcode":"32804",
    "sg:province":"FL",
    "sg:tags":[
        "state",
        "commercial"
    ],
    "wof:name":"United Heritage Bank",
    "wof:placetype":"venue"
},
  "geometry": {"coordinates":[-81.38927700000001,28.564764],"type":"Point"}
}