{
  "type": "Feature",
  "properties": {
    "addr:full":"6210 N 53rd St Tampa FL 33610",
    "addr:housenumber":"6210",
    "addr:postcode":"33610",
    "addr:street":"N 53Rd St",
    "iso:country":"US",
    "sg:address":"6210 N 53rd St",
    "sg:city":"Tampa",
    "sg:classifiers":[
        {
            "category":"Manufacturing",
            "subcategory":"Paper Products",
            "type":"Manufacturing & Wholesale Goods"
        }
    ],
    "sg:phone":"+1 813 621 3051",
    "sg:postcode":"33610",
    "sg:province":"FL",
    "sg:tags":[
        "system",
        "mill",
        "refuse",
        "mfg"
    ],
    "wof:name":"Waste MGT Tampa-Recycle Amer",
    "wof:placetype":"venue"
},
  "geometry": {"coordinates":[-82.397857,28.006022],"type":"Point"}
}