{
  "type": "Feature",
  "properties": {
    "addr:full":"7479 Mill Pond Cir Naples FL 34109",
    "addr:housenumber":"7479",
    "addr:postcode":"34109",
    "addr:street":"Mill Pond Cir",
    "iso:country":"US",
    "sg:address":"7479 Mill Pond Cir",
    "sg:city":"Naples",
    "sg:classifiers":[
        {
            "category":"Professional",
            "subcategory":"Art Services",
            "type":"Services"
        }
    ],
    "sg:phone":"+1 239 289 9072",
    "sg:postcode":"34109",
    "sg:province":"FL",
    "sg:tags":[
        "graphic",
        "designer"
    ],
    "wof:name":"Alternative Graphics & Design",
    "wof:placetype":"venue"
},
  "geometry": {"coordinates":[-81.77656,26.237763],"type":"Point"}
}