{
  "type": "Feature",
  "properties": {
    "iso:country":"US",
    "sg:address":"11901 Devoe Ct",
    "sg:city":"Orlando",
    "sg:classifiers":[
        {
            "category":"Wholesale",
            "subcategory":"Construction Materials",
            "type":"Manufacturing & Wholesale Goods"
        },
        {
            "category":"Building & Trades",
            "subcategory":"Construction",
            "type":"Services"
        }
    ],
    "sg:phone":"+1 407 239 0048",
    "sg:postcode":"32821",
    "sg:province":"FL",
    "sg:tags":[
        "tile",
        "contractor"
    ],
    "wof:name":"Bol Tile Contractor Inc",
    "wof:placetype":"venue"
},
  "geometry": {"coordinates":[-81.44349,28.395899],"type":"Point"}
}