{
  "type": "Feature",
  "properties": {
    "addr:full":"774 Shaw Lake Rd Pierson FL 32180",
    "addr:housenumber":"774",
    "addr:postcode":"32180",
    "addr:street":"Shaw Lake Rd",
    "iso:country":"US",
    "sg:address":"774 Shaw Lake Rd",
    "sg:city":"Pierson",
    "sg:classifiers":[
        {
            "category":"Farming",
            "subcategory":"Orchard",
            "type":"Manufacturing & Wholesale Goods"
        }
    ],
    "sg:phone":"+1 386 749 4935",
    "sg:postcode":"32180",
    "sg:province":"FL",
    "sg:tags":[
        "citrus",
        "grove",
        "fruit"
    ],
    "wof:name":"Braddock Grove",
    "wof:placetype":"venue"
},
  "geometry": {"coordinates":[-81.43154699999999,29.229152],"type":"Point"}
}