{
  "type": "Feature",
  "properties": {
    "iso:country":"US",
    "sg:address":"401 Biscayne Blvd. Bayside Marketplace",
    "sg:city":"Miami",
    "sg:classifiers":[
        {
            "category":"Ice Cream",
            "type":"Food & Drink"
        }
    ],
    "sg:phone":"+1 305 371 3497",
    "sg:postcode":"33132",
    "sg:province":"FL",
    "sg:tags":[
        "frozen",
        "yogurt"
    ],
    "wof:name":"Coco Gelato",
    "wof:placetype":"venue"
},
  "geometry": {"coordinates":[-80.13442999999999,25.768339],"type":"Point"}
}