{
  "type": "Feature",
  "properties": {
    "iso:country":"US",
    "sg:address":"925 N Orlando Ave",
    "sg:city":"Maitland",
    "sg:classifiers":[
        {
            "category":"Personal",
            "type":"Services"
        },
        {
            "category":"Professional",
            "subcategory":"Art Services",
            "type":"Services"
        },
        {
            "category":"Communications",
            "subcategory":"Film & Video Production",
            "type":"Services"
        }
    ],
    "sg:phone":"+1 407 629 4250",
    "sg:postcode":"32751",
    "sg:province":"FL",
    "sg:tags":[
        "videography",
        "aerial",
        "photographer",
        "photography",
        "wedding"
    ],
    "wof:name":"Smith Aerial Photography",
    "wof:placetype":"venue"
},
  "geometry": {"coordinates":[-81.360688,28.635049],"type":"Point"}
}