{
  "type": "Feature",
  "properties": {
    "addr:full":"5458 Steeplechase Boca Raton FL 33496",
    "addr:housenumber":"5458",
    "addr:postcode":"33496",
    "addr:street":"Steeplechase",
    "iso:country":"US",
    "sg:address":"5458 Steeplechase",
    "sg:city":"Boca Raton",
    "sg:classifiers":[
        {
            "category":"Professional",
            "subcategory":"Business Services",
            "type":"Services"
        }
    ],
    "sg:phone":"+1 561 893 0680",
    "sg:postcode":"33496",
    "sg:province":"FL",
    "sg:tags":[
        "interior",
        "consultant",
        "design",
        "decorator"
    ],
    "wof:name":"Consultants For Interiors Inc",
    "wof:placetype":"venue"
},
  "geometry": {"coordinates":[-80.127456,26.417424],"type":"Point"}
}