{
  "type": "Feature",
  "properties": {
    "iso:country":"US",
    "sg:address":"6619 S Dixie Hwy",
    "sg:city":"Miami",
    "sg:classifiers":[
        {
            "category":"Professional",
            "subcategory":"Lawyer & Legal Services",
            "type":"Services"
        }
    ],
    "sg:phone":"+1 305 576 5600",
    "sg:postcode":"33143",
    "sg:province":"FL",
    "sg:tags":[
        "attorney",
        "criminal",
        "law"
    ],
    "sg:website":"http://www.robertbarrar.com",
    "wof:name":"Law Office of Robert I. Barrar",
    "wof:placetype":"venue"
},
  "geometry": {"coordinates":[-80.300268,25.695387],"type":"Point"}
}