{
  "type": "Feature",
  "properties": {
    "iso:country":"US",
    "sg:address":"402 W 18th Ct",
    "sg:city":"Lynn Haven",
    "sg:classifiers":[
        {
            "category":"Building & Trades",
            "subcategory":"Equipment Rental",
            "type":"Services"
        }
    ],
    "sg:phone":"+1 850 265 1446",
    "sg:postcode":"32444",
    "sg:province":"FL",
    "sg:tags":[
        "heavy",
        "construction"
    ],
    "wof:name":"Anthonys Better Crane Service",
    "wof:placetype":"venue"
},
  "geometry": {"coordinates":[-85.65187,30.23119],"type":"Point"}
}