{
  "type": "Feature",
  "properties": {
    "addr:full":"901 S Collier Blvd Marco Island FL 34145",
    "addr:housenumber":"901;collier blvd",
    "addr:postcode":"34145",
    "addr:street":"S",
    "iso:country":"US",
    "sg:address":"901 S Collier Blvd",
    "sg:city":"Marco Island",
    "sg:classifiers":[
        {
            "category":"Travel",
            "subcategory":"Hotels & Motels",
            "type":"Entertainment"
        }
    ],
    "sg:phone":"+1 239 394 9955",
    "sg:postcode":"34145",
    "sg:province":"FL",
    "sg:tags":[
        "resort"
    ],
    "sg:website":"www.resortquest.com",
    "wof:name":"Resortquest",
    "wof:placetype":"venue"
},
  "geometry": {"coordinates":[-81.72668,25.913432],"type":"Point"}
}