{
  "type": "Feature",
  "properties": {
    "iso:country":"US",
    "sg:address":"7990 NW 96th Ter",
    "sg:city":"Fort Lauderdale",
    "sg:classifiers":[
        {
            "category":"Professional",
            "type":"Services"
        }
    ],
    "sg:phone":"+1 954 931 9334",
    "sg:postcode":"33321",
    "sg:province":"FL",
    "wof:name":"AAW Windows & Doors Inc",
    "wof:placetype":"venue"
},
  "geometry": {"coordinates":[-80.281262,26.224598],"type":"Point"}
}