{
  "type": "Feature",
  "properties": {
    "iso:country":"US",
    "sg:address":"15 E Star Island Dr",
    "sg:city":"Miami Beach",
    "sg:classifiers":[
        {
            "category":"Professional",
            "subcategory":"Computer Services",
            "type":"Services"
        }
    ],
    "sg:phone":"+1 305 672 9595",
    "sg:postcode":"33139",
    "sg:province":"FL",
    "sg:tags":[
        "consultant",
        "designer"
    ],
    "wof:name":"Miami Worldwide Partners",
    "wof:placetype":"venue"
},
  "geometry": {"coordinates":[-80.150892,25.779951],"type":"Point"}
}