{
  "type": "Feature",
  "properties": {
    "iso:country":"US",
    "sg:address":"7002 Dormany Loop",
    "sg:city":"Plant City",
    "sg:classifiers":[
        {
            "category":"Building & Trades",
            "subcategory":"Construction",
            "type":"Services"
        }
    ],
    "sg:phone":"+1 813 986 6533",
    "sg:postcode":"33565",
    "sg:province":"FL",
    "sg:tags":[
        "house"
    ],
    "wof:name":"Allstate Construction",
    "wof:placetype":"venue"
},
  "geometry": {"coordinates":[-82.209136,28.103115],"type":"Point"}
}