{
  "type": "Feature",
  "properties": {
    "addr:full":"14251 SW 29th Ct Davie FL 33330",
    "addr:housenumber":"14251",
    "addr:postcode":"33330",
    "addr:street":"Sw 29Th Ct",
    "iso:country":"US",
    "sg:address":"14251 SW 29th Ct",
    "sg:city":"Davie",
    "sg:classifiers":[
        {
            "category":"Marine",
            "type":"Transportation"
        }
    ],
    "sg:phone":"+1 954 349 1191",
    "sg:postcode":"33330",
    "sg:province":"FL",
    "sg:tags":[
        "water",
        "towing",
        "transport"
    ],
    "wof:name":"A-1 Boat Trasport Inc",
    "wof:placetype":"venue"
},
  "geometry": {"coordinates":[-80.341123,26.083428],"type":"Point"}
}