{
  "type": "Feature",
  "properties": {
    "iso:country":"US",
    "sg:address":"12041 SW 78th Ter",
    "sg:city":"Miami",
    "sg:classifiers":[
        {
            "category":"Transit Center",
            "subcategory":"Freight",
            "type":"Transportation"
        },
        {
            "category":"Freight",
            "type":"Transportation"
        }
    ],
    "sg:phone":"+1 305 251 8912",
    "sg:postcode":"33183",
    "sg:province":"FL",
    "sg:tags":[
        "local",
        "trucking-motor",
        "trucking"
    ],
    "wof:name":"Delta Trucking Inc",
    "wof:placetype":"venue"
},
  "geometry": {"coordinates":[-80.387563,25.694874],"type":"Point"}
}