{
  "type": "Feature",
  "properties": {
    "iso:country":"US",
    "sg:address":"2326 Stillwater Ave",
    "sg:city":"Apopka",
    "sg:classifiers":[
        {
            "category":"Building & Trades",
            "subcategory":"Construction",
            "type":"Services"
        }
    ],
    "sg:phone":"+1 407 884 4818",
    "sg:postcode":"32703",
    "sg:province":"FL",
    "sg:tags":[
        "concrete",
        "contractor"
    ],
    "wof:name":"Decorative Concrete Creations",
    "wof:placetype":"venue"
},
  "geometry": {"coordinates":[-81.54289199999999,28.628412],"type":"Point"}
}