{
  "type": "Feature",
  "properties": {
    "addr:full":"188 Barton Blvd Rockledge FL 32955",
    "addr:housenumber":"188",
    "addr:postcode":"32955",
    "addr:street":"Barton Blvd",
    "iso:country":"US",
    "sg:address":"188 Barton Blvd",
    "sg:city":"Rockledge",
    "sg:classifiers":[
        {
            "category":"Restaurant",
            "type":"Food & Drink"
        }
    ],
    "sg:menulink":"http://www.allmenus.com/fl/cocoa-rockledge/207579-taco-bell/menu/",
    "sg:phone":"+1 321 636 2400",
    "sg:postcode":"32955",
    "sg:province":"FL",
    "sg:tags":[
        "mexican"
    ],
    "wof:name":"Taco Bell",
    "wof:placetype":"venue"
},
  "geometry": {"coordinates":[-80.72675599999999,28.332233],"type":"Point"}
}