{
  "type": "Feature",
  "properties": {
    "addr:full":"1310 10th St Lake Park FL 33403",
    "addr:housenumber":"1310",
    "addr:postcode":"33403",
    "addr:street":"10Th St",
    "iso:country":"US",
    "sg:address":"1310 10th St",
    "sg:city":"Lake Park",
    "sg:classifiers":[
        {
            "category":"Autos & Motor Vehicles",
            "subcategory":"Auto Supplies",
            "type":"Retail Goods"
        },
        {
            "category":"Wholesale",
            "subcategory":"Auto Parts",
            "type":"Manufacturing & Wholesale Goods"
        }
    ],
    "sg:phone":"+1 561 844 8996",
    "sg:postcode":"33403",
    "sg:province":"FL",
    "sg:tags":[
        "automobile"
    ],
    "wof:name":"Bennett Auto Supply Inc",
    "wof:placetype":"venue"
},
  "geometry": {"coordinates":[-80.074663,26.804602],"type":"Point"}
}