{
  "type": "Feature",
  "properties": {
    "iso:country":"US",
    "sg:address":"700 S Dixie Hwy",
    "sg:city":"West Palm Beach",
    "sg:classifiers":[
        {
            "category":"Professional",
            "subcategory":"Research",
            "type":"Services"
        }
    ],
    "sg:phone":"+1 561 835 2025",
    "sg:postcode":"33401",
    "sg:province":"FL",
    "sg:tags":[
        "foundation",
        "philanthropic"
    ],
    "wof:name":"Pegasus Foundation",
    "wof:placetype":"venue"
},
  "geometry": {"coordinates":[-80.053708,26.706623],"type":"Point"}
}