{
  "type": "Feature",
  "properties": {
    "addr:full":"5518 River Forest Dr Jacksonville FL 32211",
    "addr:housenumber":"5518",
    "addr:postcode":"32211",
    "addr:street":"River Forest Dr",
    "iso:country":"US",
    "sg:address":"5518 River Forest Dr",
    "sg:city":"Jacksonville",
    "sg:classifiers":[
        {
            "category":"Sports & Exercise",
            "subcategory":"Gym",
            "type":"Entertainment"
        }
    ],
    "sg:phone":"+1 904 743 3975",
    "sg:postcode":"32211",
    "sg:province":"FL",
    "sg:tags":[
        "fitness",
        "physical",
        "facility"
    ],
    "wof:name":"Online Fitness Solutions",
    "wof:placetype":"venue"
},
  "geometry": {"coordinates":[-81.60285399999999,30.336683],"type":"Point"}
}