{
  "type": "Feature",
  "properties": {
    "addr:full":"7550 Uss Essex St Milton FL 32570",
    "addr:postcode":"7550;32570",
    "addr:street":"Uss Essex St",
    "iso:country":"US",
    "sg:address":"7550 Uss Essex St",
    "sg:city":"Milton",
    "sg:classifiers":[
        {
            "category":"Government",
            "subcategory":"Office",
            "type":"Public Place"
        }
    ],
    "sg:phone":"+1 850 623 7121",
    "sg:postcode":"32570",
    "sg:province":"FL",
    "sg:tags":[
        "national",
        "security"
    ],
    "wof:name":"Whiting Field Air Station",
    "wof:placetype":"venue"
},
  "geometry": {"coordinates":[-87.02022700000001,30.710095],"type":"Point"}
}