{
  "type": "Feature",
  "properties": {
    "addr:full":"5348 Medicine Bow St Milton FL 32570",
    "addr:housenumber":"5348",
    "addr:postcode":"32570",
    "addr:street":"Medicine Bow St",
    "iso:country":"US",
    "sg:address":"5348 Medicine Bow St",
    "sg:city":"Milton",
    "sg:classifiers":[
        {
            "category":"Science Facility",
            "type":"Public Place"
        }
    ],
    "sg:phone":"+1 850 384 1708",
    "sg:postcode":"32570",
    "sg:province":"FL",
    "sg:tags":[
        "development",
        "laboratories-research"
    ],
    "wof:name":"Institute For Development Of Educational Activit",
    "wof:placetype":"venue"
},
  "geometry": {"coordinates":[-87.098615,30.661261],"type":"Point"}
}