{
  "type": "Feature",
  "properties": {
    "iso:country":"US",
    "sg:address":"235 Kincaid Ave",
    "sg:city":"De Land",
    "sg:classifiers":[
        {
            "category":"Real Estate",
            "subcategory":"Real Estate Operator",
            "type":"Services"
        }
    ],
    "sg:phone":"+1 386 738 4123",
    "sg:postcode":"32724",
    "sg:province":"FL",
    "sg:tags":[
        "building",
        "apartment"
    ],
    "wof:name":"Boulevard Laundry & Apts LLC",
    "wof:placetype":"venue"
},
  "geometry": {"coordinates":[-81.295354,28.991341],"type":"Point"}
}