{
  "type": "Feature",
  "properties": {
    "iso:country":"US",
    "sg:address":"9792 Airport Blvd",
    "sg:city":"Orlando",
    "sg:classifiers":[
        {
            "category":"Shopping",
            "subcategory":"Gifts & Souvenirs",
            "type":"Retail Goods"
        }
    ],
    "sg:phone":"+1 407 825 2679",
    "sg:postcode":"32827",
    "sg:province":"FL",
    "wof:name":"Stellar Partners Inc",
    "wof:placetype":"venue"
},
  "geometry": {"coordinates":[-81.30659199999999,28.427201],"type":"Point"}
}