{
  "type": "Feature",
  "properties": {
    "iso:country":"US",
    "sg:address":"8181 NW 36th St Ste 22",
    "sg:city":"Doral",
    "sg:classifiers":[
        {
            "category":"Professional",
            "subcategory":"Management & Consulting",
            "type":"Services"
        },
        {
            "category":"Professional",
            "subcategory":"Employment Agencies",
            "type":"Services"
        }
    ],
    "sg:phone":"+1 305 477 2233",
    "sg:postcode":"33166",
    "sg:province":"FL",
    "sg:tags":[
        "consultant",
        "search",
        "executive",
        "temporary"
    ],
    "sg:website":"www.victoriaassociates.com",
    "wof:name":"Victoria & Associates Career Services",
    "wof:placetype":"venue"
},
  "geometry": {"coordinates":[-80.32910800000001,25.81003],"type":"Point"}
}