{
  "type": "Feature",
  "properties": {
    "iso:country":"US",
    "sg:address":"8672 159th Ct N",
    "sg:city":"Palm Beach Gardens",
    "sg:classifiers":[
        {
            "category":"Building & Trades",
            "subcategory":"Construction",
            "type":"Services"
        }
    ],
    "sg:phone":"+1 561 744 6340",
    "sg:postcode":"33418",
    "sg:province":"FL",
    "sg:tags":[
        "general",
        "contractor"
    ],
    "wof:name":"G L Archer",
    "wof:placetype":"venue"
},
  "geometry": {"coordinates":[-80.16959900000001,26.910795],"type":"Point"}
}