{
  "type": "Feature",
  "properties": {
    "iso:country":"US",
    "sg:address":"4301 Oak Cir",
    "sg:city":"Boca Raton",
    "sg:classifiers":[
        {
            "category":"Retail",
            "subcategory":"Auto Repair",
            "type":"Services"
        }
    ],
    "sg:phone":"+1 561 416 9585",
    "sg:postcode":"33431",
    "sg:province":"FL",
    "sg:tags":[
        "repairing",
        "automobile"
    ],
    "wof:name":"Joel Automotor",
    "wof:placetype":"venue"
},
  "geometry": {"coordinates":[-80.083511,26.386876],"type":"Point"}
}