{
  "type": "Feature",
  "properties": {
    "iso:country":"US",
    "sg:address":"27395 W Dixie Hwy",
    "sg:city":"Homestead",
    "sg:classifiers":[
        {
            "category":"Organizations",
            "subcategory":"Membership Organization",
            "type":"Services"
        }
    ],
    "sg:phone":"+1 786 243 1155",
    "sg:postcode":"33032",
    "sg:province":"FL",
    "wof:name":"Cuban American National Cncl",
    "wof:placetype":"venue"
},
  "geometry": {"coordinates":[-80.43548199999999,25.512228],"type":"Point"}
}