{
  "type": "Feature",
  "properties": {
    "iso:country":"US",
    "sg:address":"6272 Forest Hill Blvd",
    "sg:city":"Greenacres",
    "sg:classifiers":[
        {
            "category":"Retail",
            "subcategory":"Repair Shop",
            "type":"Services"
        }
    ],
    "sg:phone":"+1 561 953 5164",
    "sg:postcode":"33415",
    "sg:province":"FL",
    "sg:tags":[
        "lock",
        "locksmith"
    ],
    "wof:name":"A 24 All Day Emergency Lcksmth",
    "wof:placetype":"venue"
},
  "geometry": {"coordinates":[-80.142188,26.651523],"type":"Point"}
}