{
  "type": "Feature",
  "properties": {
    "iso:country":"US",
    "sg:address":"3508 Sydney Rd",
    "sg:city":"Plant City",
    "sg:classifiers":[
        {
            "category":"Manufacturing",
            "subcategory":"Food",
            "type":"Manufacturing & Wholesale Goods"
        }
    ],
    "sg:phone":"+1 813 752 3482",
    "sg:postcode":"33566",
    "sg:province":"FL",
    "sg:tags":[
        "mayonnaise",
        "salad",
        "dressing"
    ],
    "wof:name":"Marjon Specialty Foods Inc",
    "wof:placetype":"venue"
},
  "geometry": {"coordinates":[-82.15748600000001,27.994123],"type":"Point"}
}