{
  "type": "Feature",
  "properties": {
    "iso:country":"US",
    "sg:address":"777 Horseman Dr",
    "sg:city":"Daytona Beach",
    "sg:classifiers":[
        {
            "category":"Building & Trades",
            "subcategory":"Landscaping Services",
            "type":"Services"
        }
    ],
    "sg:phone":"+1 386 761 0251",
    "sg:postcode":"32127",
    "sg:province":"FL",
    "wof:name":"Brauns Lawns Inc",
    "wof:placetype":"venue"
},
  "geometry": {"coordinates":[-80.998525,29.126416],"type":"Point"}
}