{
  "type": "Feature",
  "properties": {
    "iso:country":"US",
    "sg:address":"520 W 29th St",
    "sg:city":"Hialeah",
    "sg:classifiers":[
        {
            "category":"Personal",
            "subcategory":"Tattoo Parlor",
            "type":"Services"
        }
    ],
    "sg:phone":"+1 305 888 5129",
    "sg:postcode":"33012",
    "sg:province":"FL",
    "wof:name":"Body Art Fitness",
    "wof:placetype":"venue"
},
  "geometry": {"coordinates":[-80.293267,25.848119],"type":"Point"}
}