{
  "type": "Feature",
  "properties": {
    "addr:full":"2555 Old Dixie Hwy Stuart FL 34996",
    "addr:housenumber":"2555",
    "addr:postcode":"34996",
    "addr:street":"Old Dixie Hwy",
    "iso:country":"US",
    "sg:address":"2555 Old Dixie Hwy",
    "sg:city":"Stuart",
    "sg:classifiers":[
        {
            "category":"Building & Trades",
            "subcategory":"Equipment Rental",
            "type":"Services"
        },
        {
            "category":"Education",
            "subcategory":"Special Training",
            "type":"Public Place"
        }
    ],
    "sg:phone":"+1 772 221 0838",
    "sg:postcode":"34996",
    "sg:province":"FL",
    "sg:tags":[
        "aircraft",
        "school"
    ],
    "wof:name":"Flight Training International",
    "wof:placetype":"venue"
},
  "geometry": {"coordinates":[-80.231285,27.176204],"type":"Point"}
}