{
  "type": "Feature",
  "properties": {
    "iso:country":"US",
    "sg:address":"1495 Pacific Ave",
    "sg:city":"Sanford",
    "sg:classifiers":[
        {
            "category":"Utilities",
            "subcategory":"Water",
            "type":"Services"
        }
    ],
    "sg:phone":"+1 407 463 6433",
    "sg:postcode":"32771",
    "sg:province":"FL",
    "sg:tags":[
        "pump",
        "well",
        "drilling",
        "contractor"
    ],
    "wof:name":"Bill Young Well Drilling Llc",
    "wof:placetype":"venue"
},
  "geometry": {"coordinates":[-81.357516,28.800319],"type":"Point"}
}