{
  "type": "Feature",
  "properties": {
    "addr:full":"1992 Pandora Dr Milton FL 32583",
    "addr:housenumber":"1992",
    "addr:postcode":"32583",
    "addr:street":"Pandora Dr",
    "iso:country":"US",
    "sg:address":"1992 Pandora Dr",
    "sg:city":"Milton",
    "sg:classifiers":[
        {
            "category":"Retail",
            "subcategory":"Portrait Studio",
            "type":"Services"
        }
    ],
    "sg:phone":"+1 850 623 5580",
    "sg:postcode":"32583",
    "sg:province":"FL",
    "sg:tags":[
        "photo"
    ],
    "wof:name":"Garcon Photography & Graphics",
    "wof:placetype":"venue"
},
  "geometry": {"coordinates":[-87.09042700000001,30.508372],"type":"Point"}
}