{
  "type": "Feature",
  "properties": {
    "iso:country":"US",
    "sg:address":"2471 N McMullen Booth Rd",
    "sg:city":"Clearwater",
    "sg:classifiers":[
        {
            "category":"Professional",
            "type":"Services"
        }
    ],
    "sg:phone":"+1 727 791 9177",
    "sg:postcode":"33759",
    "sg:province":"FL",
    "sg:tags":[
        "establishment"
    ],
    "wof:name":"American Medical",
    "wof:placetype":"venue"
},
  "geometry": {"coordinates":[-82.70892000000001,28.011974],"type":"Point"}
}