{
  "type": "Feature",
  "properties": {
    "iso:country":"US",
    "sg:address":"42 W Oak St Ofc",
    "sg:city":"Osprey",
    "sg:classifiers":[
        {
            "category":"Building & Trades",
            "subcategory":"Construction",
            "type":"Services"
        }
    ],
    "sg:phone":"+1 941 966 5430",
    "sg:postcode":"34229",
    "sg:province":"FL",
    "sg:tags":[
        "manufactured",
        "housing-communities"
    ],
    "wof:name":"Sarasota Bay Mobile Home Park",
    "wof:placetype":"venue"
},
  "geometry": {"coordinates":[-82.491478,27.19998],"type":"Point"}
}