{
  "type": "Feature",
  "properties": {
    "iso:country":"US",
    "sg:address":"323 W Keuka Lake Trl",
    "sg:city":"Interlachen",
    "sg:classifiers":[
        {
            "category":"Building & Trades",
            "subcategory":"Construction",
            "type":"Services"
        }
    ],
    "sg:phone":"+1 386 684 4874",
    "sg:postcode":"32148",
    "sg:province":"FL",
    "sg:tags":[
        "carpentry",
        "contractor"
    ],
    "wof:name":"William Powell",
    "wof:placetype":"venue"
},
  "geometry": {"coordinates":[-81.913076,29.603294],"type":"Point"}
}