{
  "type": "Feature",
  "properties": {
    "addr:full":"401 Brigadier St Pensacola FL 32507",
    "addr:housenumber":"401",
    "addr:postcode":"32507",
    "addr:street":"Brigadier St",
    "iso:country":"US",
    "sg:address":"401 Brigadier St",
    "sg:city":"Pensacola",
    "sg:classifiers":[
        {
            "category":"Education",
            "subcategory":"School",
            "type":"Public Place"
        }
    ],
    "sg:phone":"+1 850 453 7463",
    "sg:postcode":"32507",
    "sg:province":"FL",
    "wof:name":"E-Seal Special Ctr",
    "wof:placetype":"venue"
},
  "geometry": {"coordinates":[-87.28460099999999,30.393728],"type":"Point"}
}