{
  "type": "Feature",
  "properties": {
    "iso:country":"US",
    "sg:address":"6362 Pine Summit Dr",
    "sg:city":"Jacksonville",
    "sg:classifiers":[
        {
            "category":"Freight",
            "type":"Transportation"
        }
    ],
    "sg:phone":"+1 904 743 6545",
    "sg:postcode":"32211",
    "sg:province":"FL",
    "sg:tags":[
        "warehouse",
        "merchandise"
    ],
    "wof:name":"Lacey Support Svc Co",
    "wof:placetype":"venue"
},
  "geometry": {"coordinates":[-81.589443,30.345076],"type":"Point"}
}