{
  "type": "Feature",
  "properties": {
    "addr:full":"333 SW 28th St Fort Lauderdale FL 33315",
    "addr:housenumber":"333",
    "addr:postcode":"33315",
    "addr:street":"Sw 28Th St",
    "iso:country":"US",
    "sg:address":"333 SW 28th St",
    "sg:city":"Fort Lauderdale",
    "sg:classifiers":[
        {
            "category":"Government",
            "subcategory":"Office",
            "type":"Public Place"
        }
    ],
    "sg:phone":"+1 954 762 3800",
    "sg:postcode":"33315",
    "sg:province":"FL",
    "wof:name":"Children & Families Dept",
    "wof:placetype":"venue"
},
  "geometry": {"coordinates":[-80.146005,26.089039],"type":"Point"}
}