{
  "type": "Feature",
  "properties": {
    "iso:country":"US",
    "sg:address":"1897 Cotton Bay Ln",
    "sg:city":"Navarre",
    "sg:classifiers":[
        {
            "category":"Professional",
            "subcategory":"Computer Services",
            "type":"Services"
        }
    ],
    "sg:phone":"+1 850 936 0200",
    "sg:postcode":"32566",
    "sg:province":"FL",
    "sg:tags":[
        "home",
        "consulting",
        "page",
        "dev",
        "internet"
    ],
    "wof:name":"Small Change",
    "wof:placetype":"venue"
},
  "geometry": {"coordinates":[-86.933403,30.402667],"type":"Point"}
}