{
  "type": "Feature",
  "properties": {
    "iso:country":"US",
    "sg:address":"3507 Sharer Rd",
    "sg:city":"Tallahassee",
    "sg:classifiers":[
        {
            "category":"Professional",
            "subcategory":"Business Services",
            "type":"Services"
        }
    ],
    "sg:phone":"+1 850 386 7575",
    "sg:postcode":"32312",
    "sg:province":"FL",
    "sg:tags":[
        "est",
        "merchandise"
    ],
    "wof:name":"National Fire Extinguishers",
    "wof:placetype":"venue"
},
  "geometry": {"coordinates":[-84.294945,30.507569],"type":"Point"}
}