{
  "type": "Feature",
  "properties": {
    "addr:full":"2198 NE Coachman Rd Clearwater FL 33765",
    "addr:housenumber":"2198",
    "addr:postcode":"33765",
    "addr:street":"Ne Coachman Rd",
    "iso:country":"US",
    "sg:address":"2198 NE Coachman Rd",
    "sg:city":"Clearwater",
    "sg:classifiers":[
        {
            "category":"Personal",
            "subcategory":"Beauty Salon",
            "type":"Services"
        }
    ],
    "sg:phone":"+1 727 441 2602",
    "sg:postcode":"33765",
    "sg:province":"FL",
    "sg:tags":[
        "shop"
    ],
    "wof:name":"Michael Studio 54 Inc",
    "wof:placetype":"venue"
},
  "geometry": {"coordinates":[-82.74653499999999,27.972005],"type":"Point"}
}