{
  "type": "Feature",
  "properties": {
    "iso:country":"US",
    "sg:address":"1101 N Maitland Ave Ste 2",
    "sg:city":"Maitland",
    "sg:classifiers":[
        {
            "category":"Health Services",
            "subcategory":"Hospital",
            "type":"Services"
        }
    ],
    "sg:phone":"+1 407 644 4222",
    "sg:postcode":"32751",
    "sg:province":"FL",
    "wof:name":"Mnh Surgical Center",
    "wof:placetype":"venue"
},
  "geometry": {"coordinates":[-81.3657,28.6366],"type":"Point"}
}