{
  "type": "Feature",
  "properties": {
    "iso:country":"US",
    "sg:address":"312 N Kentucky Ave",
    "sg:city":"Lakeland",
    "sg:classifiers":[
        {
            "category":"Home & Garden",
            "subcategory":"Building Materials",
            "type":"Retail Goods"
        }
    ],
    "sg:phone":"+1 863 687 2718",
    "sg:postcode":"33801",
    "sg:province":"FL",
    "sg:tags":[
        "glass",
        "leaded"
    ],
    "wof:name":"Southern Art Glass",
    "wof:placetype":"venue"
},
  "geometry": {"coordinates":[-81.95527,28.046409],"type":"Point"}
}