{
  "type": "Feature",
  "properties": {
    "iso:country":"US",
    "sg:address":"2350 Buckskin Dr",
    "sg:city":"Englewood",
    "sg:classifiers":[
        {
            "category":"Building & Trades",
            "subcategory":"Cleaning & Sanitation",
            "type":"Services"
        }
    ],
    "sg:phone":"+1 941 475 8982",
    "sg:postcode":"34223",
    "sg:province":"FL",
    "sg:tags":[
        "janitor"
    ],
    "wof:name":"Pamela Carter's Cleaning Svc",
    "wof:placetype":"venue"
},
  "geometry": {"coordinates":[-82.31187799999999,26.974831],"type":"Point"}
}