{
  "type": "Feature",
  "properties": {
    "addr:full":"1250 E 26th Pl Sanford FL 32773",
    "addr:housenumber":"1250",
    "addr:postcode":"32773",
    "addr:street":"E 26Th Pl",
    "iso:country":"US",
    "sg:address":"1250 E 26th Pl",
    "sg:city":"Sanford",
    "sg:classifiers":[
        {
            "category":"Autos & Motor Vehicles",
            "subcategory":"Automobile Sales",
            "type":"Retail Goods"
        }
    ],
    "sg:phone":"+1 407 323 0818",
    "sg:postcode":"32773",
    "sg:province":"FL",
    "sg:tags":[
        "aircraft"
    ],
    "wof:name":"Corair",
    "wof:placetype":"venue"
},
  "geometry": {"coordinates":[-81.252044,28.779266],"type":"Point"}
}