{
  "type": "Feature",
  "properties": {
    "addr:full":"1030 SE 12th Ave Cape Coral FL 33990",
    "addr:housenumber":"1030",
    "addr:postcode":"33990",
    "addr:street":"Se 12Th Ave",
    "iso:country":"US",
    "sg:address":"1030 SE 12th Ave",
    "sg:city":"Cape Coral",
    "sg:classifiers":[
        {
            "category":"Wholesale",
            "subcategory":"Construction Materials",
            "type":"Manufacturing & Wholesale Goods"
        }
    ],
    "sg:phone":"+1 239 772 4441",
    "sg:postcode":"33990",
    "sg:province":"FL",
    "sg:tags":[
        "interior",
        "building",
        "exterior"
    ],
    "wof:name":"Florida Sales & Marketing Inc",
    "wof:placetype":"venue"
},
  "geometry": {"coordinates":[-81.951634,26.632922],"type":"Point"}
}