{
  "type": "Feature",
  "properties": {
    "iso:country":"US",
    "sg:address":"731 Pinetree Rd",
    "sg:city":"Winter Park",
    "sg:classifiers":[
        {
            "category":"Professional",
            "type":"Services"
        }
    ],
    "sg:phone":"+1 407 647 5896",
    "sg:postcode":"32789",
    "sg:province":"FL",
    "sg:tags":[
        "establishment"
    ],
    "wof:name":"Heavner Co",
    "wof:placetype":"venue"
},
  "geometry": {"coordinates":[-81.343639,28.616764],"type":"Point"}
}