{
  "type": "Feature",
  "properties": {
    "addr:full":"1817 NE 164th St North Miami Bch FL 33162",
    "addr:housenumber":"1817",
    "addr:postcode":"33162",
    "addr:street":"Ne 164Th St",
    "iso:country":"US",
    "sg:address":"1817 NE 164th St",
    "sg:city":"North Miami Bch",
    "sg:classifiers":[
        {
            "category":"Real Estate",
            "subcategory":"Real Estate Agent",
            "type":"Services"
        }
    ],
    "sg:phone":"+1 305 945 6993",
    "sg:postcode":"33162",
    "sg:province":"FL",
    "wof:name":"Fairbanks Homes & Loans",
    "wof:placetype":"venue"
},
  "geometry": {"coordinates":[-80.162313,25.927151],"type":"Point"}
}