{
  "type": "Feature",
  "properties": {
    "addr:full":"2508 Rustic Oaks Dr Lutz FL 33559",
    "addr:housenumber":"2508",
    "addr:postcode":"33559",
    "addr:street":"Rustic Oaks Dr",
    "iso:country":"US",
    "sg:address":"2508 Rustic Oaks Dr",
    "sg:city":"Lutz",
    "sg:classifiers":[
        {
            "category":"Building & Trades",
            "subcategory":"Construction",
            "type":"Services"
        }
    ],
    "sg:phone":"+1 813 948 8389",
    "sg:postcode":"33559",
    "sg:province":"FL",
    "sg:tags":[
        "carpenter"
    ],
    "wof:name":"Gulf Coast Commercial Flooring, Inc.",
    "wof:placetype":"venue"
},
  "geometry": {"coordinates":[-82.430074,28.161401],"type":"Point"}
}