{
  "type": "Feature",
  "properties": {
    "iso:country":"US",
    "sg:address":"2300 State Rte 524",
    "sg:city":"Cocoa",
    "sg:classifiers":[
        {
            "category":"Government",
            "subcategory":"Office",
            "type":"Public Place"
        }
    ],
    "sg:phone":"+1 321 634 3596",
    "sg:postcode":"32926",
    "sg:province":"FL",
    "sg:tags":[
        "state",
        "resource"
    ],
    "wof:name":"Workers Compensation Div",
    "wof:placetype":"venue"
},
  "geometry": {"coordinates":[-80.76924099999999,28.3968],"type":"Point"}
}