{
  "type": "Feature",
  "properties": {
    "iso:country":"US",
    "sg:address":"801 E Nine Mile Rd",
    "sg:city":"Pensacola",
    "sg:classifiers":[
        {
            "category":"Freight",
            "type":"Transportation"
        }
    ],
    "sg:phone":"+1 850 474 0161",
    "sg:postcode":"32514",
    "sg:province":"FL",
    "sg:tags":[
        "commercial",
        "storage"
    ],
    "wof:name":"Uncle Bob's Self-Storage",
    "wof:placetype":"venue"
},
  "geometry": {"coordinates":[-87.24683,30.532743],"type":"Point"}
}