{
  "type": "Feature",
  "properties": {
    "addr:full":"1103 W 15th St Panama City FL 32401",
    "addr:housenumber":"1103",
    "addr:postcode":"32401",
    "addr:street":"W 15Th St",
    "iso:country":"US",
    "sg:address":"1103 W 15th St",
    "sg:city":"Panama City",
    "sg:classifiers":[
        {
            "category":"Food & Beverages",
            "subcategory":"Groceries & Convenience Stores",
            "type":"Retail Goods"
        }
    ],
    "sg:phone":"+1 850 785 2960",
    "sg:postcode":"32401",
    "sg:province":"FL",
    "wof:name":"S Tommy Cai Seafood",
    "wof:placetype":"venue"
},
  "geometry": {"coordinates":[-85.67833,30.175202],"type":"Point"}
}