{
  "type": "Feature",
  "properties": {
    "iso:country":"US",
    "sg:address":"6305 S Williamson Blvd",
    "sg:city":"Port Orange",
    "sg:classifiers":[
        {
            "category":"Real Estate",
            "subcategory":"Real Estate Operator",
            "type":"Services"
        }
    ],
    "sg:phone":"+1 386 763 3818",
    "sg:postcode":"32128",
    "sg:province":"FL",
    "sg:tags":[
        "apartment"
    ],
    "wof:name":"Ashton Point Apartments",
    "wof:placetype":"venue"
},
  "geometry": {"coordinates":[-81.02433000000001,29.073679],"type":"Point"}
}