{
  "type": "Feature",
  "properties": {
    "iso:country":"US",
    "sg:address":"505 N Morgan St",
    "sg:city":"Tampa",
    "sg:classifiers":[
        {
            "category":"Professional",
            "type":"Services"
        }
    ],
    "sg:phone":"+1 813 229 2866",
    "sg:postcode":"33602",
    "sg:province":"FL",
    "sg:tags":[
        "establishment"
    ],
    "wof:name":"Private Courthouse Inc",
    "wof:placetype":"venue"
},
  "geometry": {"coordinates":[-82.455984,27.950043],"type":"Point"}
}