{
  "type": "Feature",
  "properties": {
    "addr:full":"5162 Ave del Fuego Milton FL 32571",
    "addr:housenumber":"5162",
    "addr:postcode":"32571",
    "addr:street":"Ave Del Fuego",
    "iso:country":"US",
    "sg:address":"5162 Ave del Fuego",
    "sg:city":"Milton",
    "sg:classifiers":[
        {
            "category":"Organizations",
            "subcategory":"Religious Organization",
            "type":"Services"
        }
    ],
    "sg:phone":"+1 850 994 8949",
    "sg:postcode":"32571",
    "sg:province":"FL",
    "sg:tags":[
        "church"
    ],
    "wof:name":"First Church Of The Nazarene",
    "wof:placetype":"venue"
},
  "geometry": {"coordinates":[-87.109666,30.590304],"type":"Point"}
}