{
  "type": "Feature",
  "properties": {
    "addr:full":"9411 SW 56th St Miami FL 33165",
    "addr:housenumber":"9411",
    "addr:postcode":"33165",
    "addr:street":"Sw 56Th St",
    "iso:country":"US",
    "sg:address":"9411 SW 56th St",
    "sg:city":"Miami",
    "sg:classifiers":[
        {
            "category":"Shopping",
            "type":"Retail Goods"
        }
    ],
    "sg:phone":"+1 305 595 7665",
    "sg:postcode":"33165",
    "sg:province":"FL",
    "sg:tags":[
        "pool",
        "swimming"
    ],
    "wof:name":"South Florida Pool Co",
    "wof:placetype":"venue"
},
  "geometry": {"coordinates":[-80.346042,25.716369],"type":"Point"}
}