{
  "type": "Feature",
  "properties": {
    "iso:country":"US",
    "sg:address":"428 Thomas Dr",
    "sg:city":"Panama City Bch",
    "sg:classifiers":[
        {
            "category":"Retail",
            "subcategory":"Repair Shop",
            "type":"Services"
        }
    ],
    "sg:phone":"+1 850 230 6700",
    "sg:postcode":"32408",
    "sg:province":"FL",
    "sg:tags":[
        "appliance"
    ],
    "wof:name":"Budget Appliance Repair Svc",
    "wof:placetype":"venue"
},
  "geometry": {"coordinates":[-85.76103000000001,30.18365],"type":"Point"}
}