{
  "type": "Feature",
  "properties": {
    "addr:full":"2878 Mahan Dr Tallahassee FL 32308",
    "addr:housenumber":"2878",
    "addr:postcode":"32308",
    "addr:street":"Mahan Dr",
    "iso:country":"US",
    "sg:address":"2878 Mahan Dr",
    "sg:city":"Tallahassee",
    "sg:classifiers":[
        {
            "category":"Professional",
            "subcategory":"Accounting & Tax Preparation",
            "type":"Services"
        }
    ],
    "sg:phone":"+1 850 878 2494",
    "sg:postcode":"32308",
    "sg:province":"FL",
    "sg:tags":[
        "accountant"
    ],
    "sg:website":"www.holleycpa.com",
    "wof:name":"James DA Holley & Co",
    "wof:placetype":"venue"
},
  "geometry": {"coordinates":[-84.229277,30.459633],"type":"Point"}
}