{
  "type": "Feature",
  "properties": {
    "iso:country":"US",
    "sg:address":"4111 Land O Lakes Blvd",
    "sg:city":"Land O Lakes",
    "sg:classifiers":[
        {
            "category":"Professional",
            "subcategory":"Lawyer & Legal Services",
            "type":"Services"
        }
    ],
    "sg:phone":"+1 813 996 7710",
    "sg:postcode":"34639",
    "sg:province":"FL",
    "sg:tags":[
        "attorney"
    ],
    "wof:name":"Kuenzel & Lutes",
    "wof:placetype":"venue"
},
  "geometry": {"coordinates":[-82.45935299999999,28.21704],"type":"Point"}
}