{
  "type": "Feature",
  "properties": {
    "iso:country":"US",
    "sg:address":"2711 Rew Cir",
    "sg:city":"Winter Garden",
    "sg:classifiers":[
        {
            "category":"Manufacturing",
            "subcategory":"Retail Goods",
            "type":"Manufacturing & Wholesale Goods"
        }
    ],
    "sg:phone":"+1 407 654 1435",
    "sg:postcode":"34761",
    "sg:province":"FL",
    "sg:tags":[
        "manufacturer"
    ],
    "wof:name":"Baring Industries",
    "wof:placetype":"venue"
},
  "geometry": {"coordinates":[-81.53689900000001,28.549725],"type":"Point"}
}