{
  "type": "Feature",
  "properties": {
    "iso:country":"US",
    "sg:address":"252 Wilshire Blvd",
    "sg:city":"Casselberry",
    "sg:classifiers":[
        {
            "category":"Banks & Credit Unions",
            "subcategory":"Investment Brokerage",
            "type":"Services"
        }
    ],
    "sg:phone":"+1 407 339 7964",
    "sg:postcode":"32707",
    "sg:province":"FL",
    "sg:tags":[
        "trade",
        "barter",
        "exchange"
    ],
    "wof:name":"Alpha Omega Network",
    "wof:placetype":"venue"
},
  "geometry": {"coordinates":[-81.32948,28.650396],"type":"Point"}
}