{
  "type": "Feature",
  "properties": {
    "addr:full":"81 Seagate Dr Naples FL 34103",
    "addr:housenumber":"81",
    "addr:postcode":"34103",
    "addr:street":"Seagate Dr",
    "iso:country":"US",
    "sg:address":"81 Seagate Dr",
    "sg:city":"Naples",
    "sg:classifiers":[
        {
            "category":"Real Estate",
            "subcategory":"Real Estate Operator",
            "type":"Services"
        }
    ],
    "sg:phone":"+1 239 262 4523",
    "sg:postcode":"34103",
    "sg:province":"FL",
    "sg:tags":[
        "condominium"
    ],
    "sg:website":"www.wcicommunities.com",
    "wof:name":"Seasons At Naples Cay",
    "wof:placetype":"venue"
},
  "geometry": {"coordinates":[-81.81535700000001,26.207784],"type":"Point"}
}