{
  "type": "Feature",
  "properties": {
    "iso:country":"US",
    "sg:address":"140 N Thompson St",
    "sg:city":"Starke",
    "sg:classifiers":[
        {
            "category":"Building & Trades",
            "subcategory":"Landscaping Services",
            "type":"Services"
        }
    ],
    "sg:phone":"+1 904 964 5269",
    "sg:postcode":"32091",
    "sg:province":"FL",
    "sg:tags":[
        "tree"
    ],
    "wof:name":"Robert's Tree Svc",
    "wof:placetype":"venue"
},
  "geometry": {"coordinates":[-82.108856,29.944332],"type":"Point"}
}