{
  "type": "Feature",
  "properties": {
    "addr:full":"5263 International Dr Orlando FL 32819",
    "addr:housenumber":"5263",
    "addr:postcode":"32819",
    "addr:street":"International Dr",
    "iso:country":"US",
    "sg:address":"5263 International Dr",
    "sg:city":"Orlando",
    "sg:classifiers":[
        {
            "category":"Shopping",
            "type":"Retail Goods"
        }
    ],
    "sg:phone":"+1 407 248 8363",
    "sg:postcode":"32819",
    "sg:province":"FL",
    "sg:tags":[
        "sun",
        "gas"
    ],
    "wof:name":"Sunglass Hut",
    "wof:placetype":"venue"
},
  "geometry": {"coordinates":[-81.450489,28.465536],"type":"Point"}
}