{
  "type": "Feature",
  "properties": {
    "iso:country":"US",
    "sg:address":"800 Lomax St",
    "sg:city":"Jacksonville",
    "sg:classifiers":[
        {
            "category":"Health Services",
            "subcategory":"Medical Lab",
            "type":"Services"
        }
    ],
    "sg:phone":"+1 904 358 8400",
    "sg:postcode":"32204",
    "sg:province":"FL",
    "sg:tags":[
        "laboratory"
    ],
    "wof:name":"Hi-Tech Dental Lab-Northeast",
    "wof:placetype":"venue"
},
  "geometry": {"coordinates":[-81.68119799999999,30.313854],"type":"Point"}
}