{
  "type": "Feature",
  "properties": {
    "addr:full":"4841 E Hwy 98 Panama City FL 32404",
    "addr:housenumber":"4841",
    "addr:postcode":"32404",
    "addr:street":"E Hwy 98",
    "iso:country":"US",
    "sg:address":"4841 E Hwy 98",
    "sg:city":"Panama City",
    "sg:classifiers":[
        {
            "category":"Organizations",
            "subcategory":"Professional Association",
            "type":"Services"
        }
    ],
    "sg:phone":"+1 850 871 6436",
    "sg:postcode":"32404",
    "sg:province":"FL",
    "wof:name":"77 Endangered Animal Preserve",
    "wof:placetype":"venue"
},
  "geometry": {"coordinates":[-85.603302,30.131088],"type":"Point"}
}