{
  "type": "Feature",
  "properties": {
    "addr:full":"6852 Gulfport Blvd S South Pasadena FL 33707",
    "addr:postcode":"6852;33707",
    "addr:street":"Gulfport Blvd S South",
    "iso:country":"US",
    "sg:address":"6852 Gulfport Blvd S",
    "sg:city":"South Pasadena",
    "sg:classifiers":[
        {
            "category":"Banks & Credit Unions",
            "subcategory":"Financial Services",
            "type":"Services"
        }
    ],
    "sg:phone":"+1 727 343 0481",
    "sg:postcode":"33707",
    "sg:province":"FL",
    "sg:tags":[
        "franchising"
    ],
    "wof:name":"Newberne & Assoc",
    "wof:placetype":"venue"
},
  "geometry": {"coordinates":[-82.734447,27.758522],"type":"Point"}
}