{
  "type": "Feature",
  "properties": {
    "iso:country":"US",
    "sg:address":"2472 SW 106th Ave",
    "sg:city":"Hollywood",
    "sg:classifiers":[
        {
            "category":"Shopping",
            "subcategory":"Florist",
            "type":"Retail Goods"
        }
    ],
    "sg:phone":"+1 954 392 6787",
    "sg:postcode":"33025",
    "sg:province":"FL",
    "wof:name":"Flowers & More",
    "wof:placetype":"venue"
},
  "geometry": {"coordinates":[-80.287025,25.987],"type":"Point"}
}