{
  "type": "Feature",
  "properties": {
    "addr:full":"417 Lake Blvd Sanford FL 32773",
    "addr:housenumber":"417",
    "addr:postcode":"32773",
    "addr:street":"Lake Blvd",
    "iso:country":"US",
    "sg:address":"417 Lake Blvd",
    "sg:city":"Sanford",
    "sg:classifiers":[
        {
            "category":"Wholesale",
            "subcategory":"Machinery & Supplies",
            "type":"Manufacturing & Wholesale Goods"
        }
    ],
    "sg:phone":"+1 407 302 1211",
    "sg:postcode":"32773",
    "sg:province":"FL",
    "sg:tags":[
        "equipment",
        "motel",
        "hotel"
    ],
    "wof:name":"Bartech Automatic Systems",
    "wof:placetype":"venue"
},
  "geometry": {"coordinates":[-81.315871,28.782435],"type":"Point"}
}