{
  "type": "Feature",
  "properties": {
    "addr:full":"4215 Irvington Ave Jacksonville FL 32210",
    "addr:housenumber":"4215",
    "addr:postcode":"32210",
    "addr:street":"Irvington Ave",
    "iso:country":"US",
    "sg:address":"4215 Irvington Ave",
    "sg:city":"Jacksonville",
    "sg:classifiers":[
        {
            "category":"Retail",
            "subcategory":"Laundry & Dry Cleaning",
            "type":"Services"
        }
    ],
    "sg:phone":"+1 904 249 7776",
    "sg:postcode":"32210",
    "sg:province":"FL",
    "wof:name":"Master Clean Enterprises Inc",
    "wof:placetype":"venue"
},
  "geometry": {"coordinates":[-81.71535,30.285892],"type":"Point"}
}