{
  "type": "Feature",
  "properties": {
    "iso:country":"US",
    "sg:address":"7463 W Grover Cleveland Blvd",
    "sg:city":"Homosassa",
    "sg:classifiers":[
        {
            "category":"Organizations",
            "subcategory":"Religious Organization",
            "type":"Services"
        }
    ],
    "sg:phone":"+1 352 621 3277",
    "sg:postcode":"34446",
    "sg:province":"FL",
    "wof:name":"Sanctuary Mission Inc",
    "wof:placetype":"venue"
},
  "geometry": {"coordinates":[-82.556844,28.80386],"type":"Point"}
}