{
  "type": "Feature",
  "properties": {
    "addr:full":"216 Santa Barbara Blvd Cape Coral FL 33991",
    "addr:housenumber":"216",
    "addr:postcode":"33991",
    "addr:street":"Santa Barbara Blvd",
    "iso:country":"US",
    "sg:address":"216 Santa Barbara Blvd",
    "sg:city":"Cape Coral",
    "sg:classifiers":[
        {
            "category":"Health Services",
            "subcategory":"Nursing And Care Facility",
            "type":"Services"
        }
    ],
    "sg:phone":"+1 239 772 4600",
    "sg:postcode":"33991",
    "sg:province":"FL",
    "sg:tags":[
        "home"
    ],
    "wof:name":"Beverly",
    "wof:placetype":"venue"
},
  "geometry": {"coordinates":[-81.97423999999999,26.645009],"type":"Point"}
}