{
  "type": "Feature",
  "properties": {
    "iso:country":"US",
    "sg:address":"700 NE 8th St",
    "sg:city":"Fort Lauderdale",
    "sg:classifiers":[
        {
            "category":"Organizations",
            "subcategory":"Community Association",
            "type":"Services"
        }
    ],
    "sg:phone":"+1 954 764 4080",
    "sg:postcode":"33304",
    "sg:province":"FL",
    "wof:name":"Doric Lodge No 140 F&Am",
    "wof:placetype":"venue"
},
  "geometry": {"coordinates":[-80.13484099999999,26.133626],"type":"Point"}
}