{
  "type": "Feature",
  "properties": {
    "iso:country":"US",
    "sg:address":"5742 Johnson St",
    "sg:city":"Hollywood",
    "sg:classifiers":[
        {
            "category":"Personal",
            "subcategory":"Beauty Salon",
            "type":"Services"
        }
    ],
    "sg:phone":"+1 954 964 9943",
    "sg:postcode":"33021",
    "sg:province":"FL",
    "sg:tags":[
        "shop",
        "manicuring"
    ],
    "wof:name":"Starlite Nails Inc",
    "wof:placetype":"venue"
},
  "geometry": {"coordinates":[-80.20301499999999,26.017692],"type":"Point"}
}