{
  "type": "Feature",
  "properties": {
    "iso:country":"US",
    "sg:address":"22218 131st Dr",
    "sg:city":"O Brien",
    "sg:classifiers":[
        {
            "category":"Manufacturing",
            "subcategory":"Chemicals & Compounds",
            "type":"Manufacturing & Wholesale Goods"
        }
    ],
    "sg:phone":"+1 386 935 0876",
    "sg:postcode":"32071",
    "sg:province":"FL",
    "sg:tags":[
        "preparation",
        "pharmaceutical",
        "mfg"
    ],
    "wof:name":"Pharmacy Returns",
    "wof:placetype":"venue"
},
  "geometry": {"coordinates":[-83.017787,30.053255],"type":"Point"}
}