{
  "type": "Feature",
  "properties": {
    "iso:country":"US",
    "sg:address":"4419 Parkbreeze Ct",
    "sg:city":"Orlando",
    "sg:classifiers":[
        {
            "category":"Insurance",
            "subcategory":"Health Insurance",
            "type":"Services"
        }
    ],
    "sg:phone":"+1 407 298 0402",
    "sg:postcode":"32808",
    "sg:province":"FL",
    "sg:tags":[
        "market"
    ],
    "wof:name":"Future Alliance",
    "wof:placetype":"venue"
},
  "geometry": {"coordinates":[-81.420998,28.5965],"type":"Point"}
}