{
  "type": "Feature",
  "properties": {
    "addr:full":"965 1st St Monticello FL 32344",
    "addr:housenumber":"965",
    "addr:postcode":"32344",
    "addr:street":"1St St",
    "iso:country":"US",
    "sg:address":"965 1st St",
    "sg:city":"Monticello",
    "sg:classifiers":[
        {
            "category":"Food & Beverages",
            "subcategory":"Groceries & Convenience Stores",
            "type":"Retail Goods"
        }
    ],
    "sg:phone":"+1 850 997 0069",
    "sg:postcode":"32344",
    "sg:province":"FL",
    "sg:tags":[
        "grocer"
    ],
    "wof:name":"Rooster Food Store",
    "wof:placetype":"venue"
},
  "geometry": {"coordinates":[-83.86223099999999,30.540649],"type":"Point"}
}