{
  "type": "Feature",
  "properties": {
    "addr:full":"704 Tampa Rd Palm Harbor FL 34683",
    "addr:housenumber":"704",
    "addr:postcode":"34683",
    "addr:street":"Tampa Rd",
    "iso:country":"US",
    "sg:address":"704 Tampa Rd",
    "sg:city":"Palm Harbor",
    "sg:classifiers":[
        {
            "category":"Retail",
            "subcategory":"Repair Shop",
            "type":"Services"
        }
    ],
    "sg:phone":"+1 727 784 1603",
    "sg:postcode":"34683",
    "sg:province":"FL",
    "sg:tags":[
        "air",
        "heating",
        "conditioning"
    ],
    "wof:name":"Barrons AC & Appl Svc",
    "wof:placetype":"venue"
},
  "geometry": {"coordinates":[-82.77395,28.068761],"type":"Point"}
}