{
  "type": "Feature",
  "properties": {
    "addr:full":"4649 Cason Cove Dr # 2522 Orlando FL 32811",
    "addr:housenumber":"4649",
    "addr:postcode":"32811",
    "addr:street":"Cason Cove Dr # 2522",
    "iso:country":"US",
    "sg:address":"4649 Cason Cove Dr # 2522",
    "sg:city":"Orlando",
    "sg:classifiers":[
        {
            "category":"Place Of Worship",
            "subcategory":"Church",
            "type":"Public Place"
        },
        {
            "category":"Place Of Worship",
            "type":"Public Place"
        }
    ],
    "sg:phone":"+1 407 489 5989",
    "sg:postcode":"32811",
    "sg:province":"FL",
    "sg:tags":[
        "churches-non-denominational"
    ],
    "wof:name":"Abundant Life Ministries, Inc",
    "wof:placetype":"venue"
},
  "geometry": {"coordinates":[-81.43876,28.497822],"type":"Point"}
}