{
  "type": "Feature",
  "properties": {
    "iso:country":"US",
    "sg:address":"6336 Buford St Apt 602",
    "sg:city":"Orlando",
    "sg:classifiers":[
        {
            "category":"Professional",
            "subcategory":"Management & Consulting",
            "type":"Services"
        }
    ],
    "sg:phone":"+1 407 454 8920",
    "sg:postcode":"32835",
    "sg:province":"FL",
    "sg:tags":[
        "consultant"
    ],
    "sg:website":"http://www.floridapipettecalibrations.com",
    "wof:name":"Florida Pipette Calibration",
    "wof:placetype":"venue"
},
  "geometry": {"coordinates":[-81.467663,28.506185],"type":"Point"}
}