{
  "type": "Feature",
  "properties": {
    "addr:full":"1099 Citrus Tower Blvd Clermont FL 34711",
    "addr:housenumber":"1099",
    "addr:postcode":"34711",
    "addr:street":"Citrus Tower Blvd",
    "iso:country":"US",
    "sg:address":"1099 Citrus Tower Blvd",
    "sg:city":"Clermont",
    "sg:classifiers":[
        {
            "category":"Health Services",
            "subcategory":"Hospital",
            "type":"Services"
        }
    ],
    "sg:phone":"+1 352 394 4071",
    "sg:postcode":"34711",
    "sg:province":"FL",
    "sg:website":"http://www.southlakehospital.com",
    "wof:name":"South Lake Hospital",
    "wof:placetype":"venue"
},
  "geometry": {"coordinates":[-81.72344699999999,28.551891],"type":"Point"}
}