{
  "type": "Feature",
  "properties": {
    "addr:full":"1214 Capital Cir SE Tallahassee FL 32301",
    "addr:housenumber":"1214",
    "addr:postcode":"32301",
    "addr:street":"Capital Cir Se",
    "iso:country":"US",
    "sg:address":"1214 Capital Cir SE",
    "sg:city":"Tallahassee",
    "sg:classifiers":[
        {
            "category":"Shopping",
            "subcategory":"Discount & Variety Stores",
            "type":"Retail Goods"
        }
    ],
    "sg:phone":"+1 850 671 4520",
    "sg:postcode":"32301",
    "sg:province":"FL",
    "wof:name":"Dollar Tree",
    "wof:placetype":"venue"
},
  "geometry": {"coordinates":[-84.226861,30.42781],"type":"Point"}
}