{
  "type": "Feature",
  "properties": {
    "addr:full":"3291 S Suncoast Blvd Homosassa FL 34448",
    "addr:housenumber":"3291",
    "addr:postcode":"34448",
    "addr:street":"S Suncoast Blvd",
    "iso:country":"US",
    "sg:address":"3291 S Suncoast Blvd",
    "sg:city":"Homosassa",
    "sg:classifiers":[
        {
            "category":"Utilities",
            "subcategory":"Telephone",
            "type":"Services"
        }
    ],
    "sg:phone":"+1 352 628 9767",
    "sg:postcode":"34448",
    "sg:province":"FL",
    "sg:tags":[
        "web",
        "internet",
        "hosting",
        "provider"
    ],
    "wof:name":"Citrus Online Inc",
    "wof:placetype":"venue"
},
  "geometry": {"coordinates":[-82.576669,28.814292],"type":"Point"}
}