{
  "type": "Feature",
  "properties": {
    "iso:country":"US",
    "sg:address":"44 McCabe St",
    "sg:city":"Port Charlotte",
    "sg:classifiers":[
        {
            "category":"Professional",
            "subcategory":"Business Services",
            "type":"Services"
        }
    ],
    "sg:phone":"+1 941 627 8506",
    "sg:postcode":"33953",
    "sg:province":"FL",
    "sg:tags":[
        "water",
        "treatment"
    ],
    "wof:name":"Water Doctor",
    "wof:placetype":"venue"
},
  "geometry": {"coordinates":[-82.219324,27.032787],"type":"Point"}
}