{
  "type": "Feature",
  "properties": {
    "iso:country":"US",
    "sg:address":"3312 S Hopkins Ave",
    "sg:city":"Titusville",
    "sg:classifiers":[
        {
            "category":"Shopping",
            "subcategory":"Used Merchandise",
            "type":"Retail Goods"
        }
    ],
    "sg:phone":"+1 321 269 8894",
    "sg:postcode":"32780",
    "sg:province":"FL",
    "sg:tags":[
        "shop",
        "thrift"
    ],
    "wof:name":"Storehouse Ministries Thrift",
    "wof:placetype":"venue"
},
  "geometry": {"coordinates":[-80.80454400000001,28.578193],"type":"Point"}
}