{
  "type": "Feature",
  "properties": {
    "iso:country":"US",
    "sg:address":"6909 Johns Rd",
    "sg:city":"Naples",
    "sg:classifiers":[
        {
            "category":"Building & Trades",
            "subcategory":"Electrical",
            "type":"Services"
        }
    ],
    "sg:phone":"+1 239 417 4665",
    "sg:postcode":"34114",
    "sg:province":"FL",
    "sg:tags":[
        "electrical",
        "contractor"
    ],
    "wof:name":"Jeff Leblanc",
    "wof:placetype":"venue"
},
  "geometry": {"coordinates":[-81.683652,26.102586],"type":"Point"}
}