{
  "type": "Feature",
  "properties": {
    "iso:country":"US",
    "sg:address":"6525 Beach Blvd",
    "sg:city":"Jacksonville",
    "sg:classifiers":[
        {
            "category":"Shopping",
            "subcategory":"Bicycles & Sporting Goods",
            "type":"Retail Goods"
        }
    ],
    "sg:phone":"+1 904 805 8800",
    "sg:postcode":"32216",
    "sg:province":"FL",
    "wof:name":"Shoe Warehouse",
    "wof:placetype":"venue"
},
  "geometry": {"coordinates":[-81.592822,30.29033],"type":"Point"}
}