{
  "type": "Feature",
  "properties": {
    "addr:full":"7071 Davis Creek Rd Jacksonville FL 32256",
    "addr:housenumber":"7071",
    "addr:postcode":"32256",
    "addr:street":"Davis Creek Rd",
    "iso:country":"US",
    "sg:address":"7071 Davis Creek Rd",
    "sg:city":"Jacksonville",
    "sg:classifiers":[
        {
            "category":"Manufacturing",
            "subcategory":"Printing",
            "type":"Manufacturing & Wholesale Goods"
        },
        {
            "category":"Professional",
            "subcategory":"Advertising",
            "type":"Services"
        },
        {
            "category":"Professional",
            "subcategory":"Printing & Photocopies",
            "type":"Services"
        }
    ],
    "sg:phone":"+1 904 262 8912",
    "sg:postcode":"32256",
    "sg:province":"FL",
    "sg:tags":[
        "product",
        "form",
        "services-commercial",
        "specialty",
        "printers-business",
        "imaging",
        "digital",
        "advertising-promotional"
    ],
    "sg:website":"http://www.promoplace.com/gapromos",
    "wof:name":"Greg Allens', Inc.",
    "wof:placetype":"venue"
},
  "geometry": {"coordinates":[-81.523679,30.160085],"type":"Point"}
}