{
  "type": "Feature",
  "properties": {
    "iso:country":"US",
    "sg:address":"1766 Bay Rd",
    "sg:city":"Miami Beach",
    "sg:classifiers":[
        {
            "category":"Restaurant",
            "type":"Food & Drink"
        }
    ],
    "sg:menulink":"http://www.allmenus.com/fl/miami-beach/15874-madiba-miami/menu/",
    "sg:phone":"+1 305 695 1566",
    "sg:postcode":"33139",
    "sg:province":"FL",
    "sg:tags":[
        "sandwich",
        "salad",
        "burger",
        "seafood",
        "soup",
        "american",
        "wrap"
    ],
    "wof:name":"Madiba Miami",
    "wof:placetype":"venue"
},
  "geometry": {"coordinates":[-80.143711,25.793059],"type":"Point"}
}