{
  "type": "Feature",
  "properties": {
    "iso:country":"US",
    "sg:address":"837 Edgehill Dr",
    "sg:city":"Palm Harbor",
    "sg:classifiers":[
        {
            "category":"Health Services",
            "subcategory":"Health Practitioner",
            "type":"Services"
        }
    ],
    "sg:phone":"+1 727 786 5812",
    "sg:postcode":"34684",
    "sg:province":"FL",
    "wof:name":"Mabest Inc",
    "wof:placetype":"venue"
},
  "geometry": {"coordinates":[-82.728956,28.056069],"type":"Point"}
}