{
  "type": "Feature",
  "properties": {
    "addr:full":"611 Post Ave SW Winter Haven FL 33880",
    "addr:housenumber":"611",
    "addr:postcode":"33880",
    "addr:street":"Post Ave Sw Winter Haven",
    "iso:country":"US",
    "sg:address":"611 Post Ave SW",
    "sg:city":"Winter Haven",
    "sg:classifiers":[
        {
            "category":"Organizations",
            "subcategory":"Non-profit Organization",
            "type":"Services"
        }
    ],
    "sg:phone":"+1 863 294 1853",
    "sg:postcode":"33880",
    "sg:province":"FL",
    "sg:tags":[
        "info",
        "addiction",
        "abuse",
        "treatment",
        "drug"
    ],
    "wof:name":"Pride Of Polk County Inc",
    "wof:placetype":"venue"
},
  "geometry": {"coordinates":[-81.734846,28.005353],"type":"Point"}
}