{
  "type": "Feature",
  "properties": {
    "iso:country":"US",
    "sg:address":"913 SE Hillcrest Ave",
    "sg:city":"Stuart",
    "sg:classifiers":[
        {
            "category":"Professional",
            "subcategory":"Engineering",
            "type":"Services"
        }
    ],
    "sg:phone":"+1 772 286 8797",
    "sg:postcode":"34994",
    "sg:province":"FL",
    "sg:tags":[
        "engineer"
    ],
    "wof:name":"GBF Engineering Inc",
    "wof:placetype":"venue"
},
  "geometry": {"coordinates":[-80.24800999999999,27.191373],"type":"Point"}
}