{
  "type": "Feature",
  "properties": {
    "iso:country":"US",
    "sg:address":"3018 NW 72nd Ave",
    "sg:city":"Miami",
    "sg:classifiers":[
        {
            "category":"Wholesale",
            "subcategory":"Wine & Distilled Alcoholic Beverages",
            "type":"Manufacturing & Wholesale Goods"
        }
    ],
    "sg:phone":"+1 305 994 3200",
    "sg:postcode":"33122",
    "sg:province":"FL",
    "wof:name":"Select Vintages",
    "wof:placetype":"venue"
},
  "geometry": {"coordinates":[-80.313148,25.80227],"type":"Point"}
}