{
  "type": "Feature",
  "properties": {
    "iso:country":"US",
    "sg:address":"1790 W 49th St Ste 209",
    "sg:city":"Hialeah",
    "sg:classifiers":[
        {
            "category":"Health Services",
            "subcategory":"Doctor",
            "type":"Services"
        },
        {
            "category":"Health Services",
            "subcategory":"Hospital",
            "type":"Services"
        }
    ],
    "sg:phone":"+1 305 826 5887",
    "sg:postcode":"33012",
    "sg:province":"FL",
    "sg:tags":[
        "nursing",
        "consultant",
        "medical",
        "practice",
        "home"
    ],
    "wof:name":"Pbs",
    "wof:placetype":"venue"
},
  "geometry": {"coordinates":[-80.318983,25.86652],"type":"Point"}
}