{
  "type": "Feature",
  "properties": {
    "addr:full":"750 S Old Dixie Hwy Jupiter FL 33458",
    "addr:housenumber":"750",
    "addr:postcode":"33458",
    "addr:street":"S Old Dixie Hwy",
    "iso:country":"US",
    "sg:address":"750 S Old Dixie Hwy",
    "sg:city":"Jupiter",
    "sg:classifiers":[
        {
            "category":"Building & Trades",
            "subcategory":"Construction",
            "type":"Services"
        }
    ],
    "sg:phone":"+1 561 741 3110",
    "sg:postcode":"33458",
    "sg:province":"FL",
    "sg:tags":[
        "maker",
        "cabinet"
    ],
    "wof:name":"Superior Woodworking Inc",
    "wof:placetype":"venue"
},
  "geometry": {"coordinates":[-80.09451300000001,26.92718],"type":"Point"}
}