{
  "type": "Feature",
  "properties": {
    "iso:country":"US",
    "sg:address":"5831 NW 199th St",
    "sg:city":"Hialeah",
    "sg:classifiers":[
        {
            "category":"Home & Garden",
            "subcategory":"Carpets & Floor Coverings",
            "type":"Retail Goods"
        }
    ],
    "sg:phone":"+1 305 820 1093",
    "sg:postcode":"33015",
    "sg:province":"FL",
    "wof:name":"Isidro Hrnndez Crpt Instlltion",
    "wof:placetype":"venue"
},
  "geometry": {"coordinates":[-80.297201,25.953493],"type":"Point"}
}