{
  "type": "Feature",
  "properties": {
    "addr:full":"10580 W Colonial Dr Ocoee FL 34761",
    "addr:housenumber":"10580",
    "addr:postcode":"34761",
    "addr:street":"W Colonial Dr",
    "iso:country":"US",
    "sg:address":"10580 W Colonial Dr",
    "sg:city":"Ocoee",
    "sg:classifiers":[
        {
            "category":"Personal",
            "subcategory":"Beauty Salon",
            "type":"Services"
        }
    ],
    "sg:phone":"+1 407 654 1562",
    "sg:postcode":"34761",
    "sg:province":"FL",
    "sg:tags":[
        "manicuring"
    ],
    "wof:name":"Tami Nails",
    "wof:placetype":"venue"
},
  "geometry": {"coordinates":[-81.534727,28.551606],"type":"Point"}
}