{
  "type": "Feature",
  "properties": {
    "iso:country":"US",
    "sg:address":"727 S Semoran Blvd",
    "sg:city":"Orlando",
    "sg:classifiers":[
        {
            "category":"Utilities",
            "subcategory":"Telephone",
            "type":"Services"
        },
        {
            "category":"Banks & Credit Unions",
            "subcategory":"Bank",
            "type":"Services"
        }
    ],
    "sg:phone":"+1 407 282 7870",
    "sg:postcode":"32807",
    "sg:province":"FL",
    "sg:tags":[
        "money",
        "transfer",
        "communications"
    ],
    "wof:name":"A T & T Corp",
    "wof:placetype":"venue"
},
  "geometry": {"coordinates":[-81.310423,28.534068],"type":"Point"}
}