{
  "type": "Feature",
  "properties": {
    "addr:full":"3804 US Hwy 1 Cocoa FL 32926",
    "addr:housenumber":"3804",
    "addr:postcode":"32926",
    "addr:street":"Us Hwy 1",
    "iso:country":"US",
    "sg:address":"3804 US Hwy 1",
    "sg:city":"Cocoa",
    "sg:classifiers":[
        {
            "category":"Autos & Motor Vehicles",
            "subcategory":"Automobile Sales",
            "type":"Retail Goods"
        }
    ],
    "sg:phone":"+1 321 632 4449",
    "sg:postcode":"32926",
    "sg:province":"FL",
    "sg:tags":[
        "car",
        "used",
        "dealer"
    ],
    "wof:name":"Zach's Cars",
    "wof:placetype":"venue"
},
  "geometry": {"coordinates":[-80.75697,28.422152],"type":"Point"}
}