{
  "type": "Feature",
  "properties": {
    "iso:country":"US",
    "sg:address":"6631 SW 7th Pl",
    "sg:city":"North Lauderdale",
    "sg:classifiers":[
        {
            "category":"Building & Trades",
            "subcategory":"Landscaping Services",
            "type":"Services"
        }
    ],
    "sg:phone":"+1 954 724 5238",
    "sg:postcode":"33068",
    "sg:province":"FL",
    "sg:tags":[
        "lawn",
        "maintenance",
        "grounds"
    ],
    "wof:name":"Elena's Lawn Svc",
    "wof:placetype":"venue"
},
  "geometry": {"coordinates":[-80.215468,26.221572],"type":"Point"}
}