{
  "type": "Feature",
  "properties": {
    "addr:full":"1325 NE 42nd St Ocala FL 34479",
    "addr:housenumber":"1325",
    "addr:postcode":"34479",
    "addr:street":"Ne 42Nd St",
    "iso:country":"US",
    "sg:address":"1325 NE 42nd St",
    "sg:city":"Ocala",
    "sg:classifiers":[
        {
            "category":"Health Services",
            "subcategory":"Doctor",
            "type":"Services"
        }
    ],
    "sg:phone":"+1 352 732 4881",
    "sg:postcode":"34479",
    "sg:province":"FL",
    "sg:tags":[
        "dentist"
    ],
    "wof:name":"Family Dental Care",
    "wof:placetype":"venue"
},
  "geometry": {"coordinates":[-82.11963799999999,29.230293],"type":"Point"}
}