{
  "type": "Feature",
  "properties": {
    "iso:country":"US",
    "sg:address":"2727 Neptune Rd",
    "sg:city":"Kissimmee",
    "sg:classifiers":[
        {
            "category":"Education",
            "subcategory":"School",
            "type":"Public Place"
        }
    ],
    "sg:phone":"+1 407 935 3500",
    "sg:postcode":"34744",
    "sg:province":"FL",
    "sg:tags":[
        "middle"
    ],
    "sg:website":"http://www.nms.osceola.k12.fl.us/",
    "wof:name":"Neptune Middle School",
    "wof:placetype":"venue"
},
  "geometry": {"coordinates":[-81.332915,28.256816],"type":"Point"}
}