{
  "type": "Feature",
  "properties": {
    "addr:full":"5240 Albion Rd Venice FL 34293",
    "addr:housenumber":"5240",
    "addr:postcode":"34293",
    "addr:street":"Albion Rd",
    "iso:country":"US",
    "sg:address":"5240 Albion Rd",
    "sg:city":"Venice",
    "sg:classifiers":[
        {
            "category":"Building & Trades",
            "subcategory":"Construction",
            "type":"Services"
        }
    ],
    "sg:phone":"+1 941 497 3441",
    "sg:postcode":"34293",
    "sg:province":"FL",
    "sg:tags":[
        "concrete",
        "contractor"
    ],
    "wof:name":"Aci Concrete Inc",
    "wof:placetype":"venue"
},
  "geometry": {"coordinates":[-82.40266200000001,27.03449],"type":"Point"}
}