{
  "type": "Feature",
  "properties": {
    "addr:full":"100 4th Ave NW Lutz FL 33548",
    "addr:housenumber":"100",
    "addr:postcode":"33548",
    "addr:street":"4Th Ave Nw",
    "iso:country":"US",
    "sg:address":"100 4th Ave NW",
    "sg:city":"Lutz",
    "sg:classifiers":[
        {
            "category":"Real Estate",
            "subcategory":"Real Estate Services",
            "type":"Services"
        },
        {
            "category":"Real Estate",
            "subcategory":"Real Estate Agent",
            "type":"Services"
        }
    ],
    "sg:phone":"+1 813 948 8005",
    "sg:postcode":"33548",
    "sg:province":"FL",
    "sg:tags":[
        "buyer",
        "broker"
    ],
    "wof:name":"Gulfwind Credit Services",
    "wof:placetype":"venue"
},
  "geometry": {"coordinates":[-82.461403,28.154699],"type":"Point"}
}