{
  "type": "Feature",
  "properties": {
    "addr:full":"16688 Collins Ave Miami FL 33160",
    "addr:housenumber":"16688",
    "addr:postcode":"33160",
    "addr:street":"Collins Ave",
    "iso:country":"US",
    "sg:address":"16688 Collins Ave",
    "sg:city":"Miami",
    "sg:classifiers":[
        {
            "category":"Real Estate",
            "subcategory":"Real Estate Agent",
            "type":"Services"
        }
    ],
    "sg:phone":"+1 305 949 5939",
    "sg:postcode":"33160",
    "sg:province":"FL",
    "wof:name":"Sunny Isles Exclusive Realty",
    "wof:placetype":"venue"
},
  "geometry": {"coordinates":[-80.12215399999999,25.929197],"type":"Point"}
}