{
  "type": "Feature",
  "properties": {
    "iso:country":"US",
    "sg:address":"14090 Metropolis Ave",
    "sg:city":"Fort Myers",
    "sg:classifiers":[
        {
            "category":"Health Services",
            "subcategory":"Doctor",
            "type":"Services"
        }
    ],
    "sg:phone":"+1 239 225 6304",
    "sg:postcode":"33912",
    "sg:province":"FL",
    "wof:name":"Gulfcoast MD PA",
    "wof:placetype":"venue"
},
  "geometry": {"coordinates":[-81.853764,26.537905],"type":"Point"}
}