{
  "type": "Feature",
  "properties": {
    "iso:country":"US",
    "sg:address":"1531 Talbot Ave",
    "sg:city":"Jacksonville",
    "sg:classifiers":[
        {
            "category":"Professional",
            "subcategory":"Management & Consulting",
            "type":"Services"
        }
    ],
    "sg:phone":"+1 904 389 0446",
    "sg:postcode":"32205",
    "sg:province":"FL",
    "sg:tags":[
        "fuel"
    ],
    "wof:name":"H L Operation Mgmt Inc",
    "wof:placetype":"venue"
},
  "geometry": {"coordinates":[-81.70675,30.300839],"type":"Point"}
}