{
  "type": "Feature",
  "properties": {
    "iso:country":"US",
    "sg:address":"1654 Town Center Cir",
    "sg:city":"Weston",
    "sg:classifiers":[
        {
            "category":"Personal",
            "subcategory":"Beauty Salon",
            "type":"Services"
        },
        {
            "category":"Personal",
            "subcategory":"Barber",
            "type":"Services"
        },
        {
            "category":"Shopping",
            "subcategory":"Beauty & Cosmetics",
            "type":"Retail Goods"
        },
        {
            "category":"Personal",
            "subcategory":"Nail Salon",
            "type":"Services"
        }
    ],
    "sg:phone":"+1 954 358 4868",
    "sg:postcode":"33326",
    "sg:province":"FL",
    "sg:tags":[
        "perfume"
    ],
    "wof:name":"Applewoods Hair & Nail Salon",
    "wof:placetype":"venue"
},
  "geometry": {"coordinates":[-80.385564,26.098237],"type":"Point"}
}