{
  "type": "Feature",
  "properties": {
    "iso:country":"US",
    "sg:address":"17557 W Claridge Oval",
    "sg:city":"Boca Raton",
    "sg:classifiers":[
        {
            "category":"Recreation",
            "type":"Entertainment"
        },
        {
            "category":"Organizations",
            "subcategory":"Community Association",
            "type":"Services"
        }
    ],
    "sg:phone":"+1 561 451 4900",
    "sg:postcode":"33496",
    "sg:province":"FL",
    "sg:tags":[
        "club",
        "country"
    ],
    "sg:website":"www.standrewscc.com",
    "wof:name":"St Andrews Country Club Inc",
    "wof:placetype":"venue"
},
  "geometry": {"coordinates":[-80.16668799999999,26.415706],"type":"Point"}
}