{
  "type": "Feature",
  "properties": {
    "iso:country":"US",
    "sg:address":"367 Williams Point Blvd",
    "sg:city":"Cocoa",
    "sg:classifiers":[
        {
            "category":"Retail",
            "subcategory":"Auto Repair",
            "type":"Services"
        }
    ],
    "sg:phone":"+1 321 638 4733",
    "sg:postcode":"32927",
    "sg:province":"FL",
    "sg:tags":[
        "general"
    ],
    "wof:name":"Raam Truck Repair & Parts Inc",
    "wof:placetype":"venue"
},
  "geometry": {"coordinates":[-80.76713599999999,28.450014],"type":"Point"}
}