{
  "type": "Feature",
  "properties": {
    "iso:country":"US",
    "sg:address":"3140 McDonald St",
    "sg:city":"Miami",
    "sg:classifiers":[
        {
            "category":"Shopping",
            "subcategory":"Florist",
            "type":"Retail Goods"
        }
    ],
    "sg:phone":"+1 305 444 4401",
    "sg:postcode":"33133",
    "sg:province":"FL",
    "wof:name":"Key West Florist Of Miami",
    "wof:placetype":"venue"
},
  "geometry": {"coordinates":[-80.24578700000001,25.732374],"type":"Point"}
}