{
  "type": "Feature",
  "properties": {
    "iso:country":"US",
    "sg:address":"716 White Pine Tree Rd",
    "sg:city":"Venice",
    "sg:classifiers":[
        {
            "category":"Retail",
            "subcategory":"Self-service Laundry",
            "type":"Services"
        }
    ],
    "sg:phone":"+1 941 480 0678",
    "sg:postcode":"34285",
    "sg:province":"FL",
    "sg:tags":[
        "coin"
    ],
    "wof:name":"Scentsational Soaps & Candles",
    "wof:placetype":"venue"
},
  "geometry": {"coordinates":[-82.43574599999999,27.110425],"type":"Point"}
}