{
  "type": "Feature",
  "properties": {
    "addr:full":"23 Jackson Ave N Jacksonville FL 32220",
    "addr:housenumber":"23",
    "addr:postcode":"32220",
    "addr:street":"Jackson Ave N",
    "iso:country":"US",
    "sg:address":"23 Jackson Ave N",
    "sg:city":"Jacksonville",
    "sg:classifiers":[
        {
            "category":"Education",
            "subcategory":"Vocational School",
            "type":"Public Place"
        }
    ],
    "sg:phone":"+1 904 378 0102",
    "sg:postcode":"32220",
    "sg:province":"FL",
    "wof:name":"Affordable Training",
    "wof:placetype":"venue"
},
  "geometry": {"coordinates":[-81.785803,30.32298],"type":"Point"}
}