{
  "type": "Feature",
  "properties": {
    "addr:full":"300 Golfview Rd North Palm Beach FL 33408",
    "addr:housenumber":"300",
    "addr:postcode":"33408",
    "addr:street":"Golfview Rd",
    "iso:country":"US",
    "sg:address":"300 Golfview Rd",
    "sg:city":"North Palm Beach",
    "sg:classifiers":[
        {
            "category":"Real Estate",
            "subcategory":"Architect",
            "type":"Services"
        }
    ],
    "sg:phone":"+1 561 622 2823",
    "sg:postcode":"33408",
    "sg:province":"FL",
    "sg:tags":[
        "building",
        "construction"
    ],
    "wof:name":"Chudnow Construction Co",
    "wof:placetype":"venue"
},
  "geometry": {"coordinates":[-80.06258200000001,26.837087],"type":"Point"}
}