{
  "type": "Feature",
  "properties": {
    "addr:full":"1136 Seminole Dr Rockledge FL 32955",
    "addr:housenumber":"1136",
    "addr:postcode":"32955",
    "addr:street":"Seminole Dr",
    "iso:country":"US",
    "sg:address":"1136 Seminole Dr",
    "sg:city":"Rockledge",
    "sg:classifiers":[
        {
            "category":"Place Of Worship",
            "subcategory":"Church",
            "type":"Public Place"
        },
        {
            "category":"Place Of Worship",
            "type":"Public Place"
        }
    ],
    "sg:phone":"+1 321 633 9985",
    "sg:postcode":"32955",
    "sg:province":"FL",
    "sg:tags":[
        "churches-catholic-traditional",
        "churches-catholic"
    ],
    "sg:website":"http://www.ascensioncatholic.net",
    "wof:name":"St Mary's Catholic Church",
    "wof:placetype":"venue"
},
  "geometry": {"coordinates":[-80.72187099999999,28.331447],"type":"Point"}
}