{
  "type": "Feature",
  "properties": {
    "iso:country":"US",
    "sg:address":"24000 Marbella Dr",
    "sg:city":"Sorrento",
    "sg:classifiers":[
        {
            "category":"Arena",
            "subcategory":"Sports Club",
            "type":"Entertainment"
        },
        {
            "category":"Sports & Exercise",
            "subcategory":"Sports Center",
            "type":"Entertainment"
        },
        {
            "category":"Sports & Exercise",
            "subcategory":"Golf",
            "type":"Entertainment"
        }
    ],
    "sg:phone":"+1 352 357 0123",
    "sg:postcode":"32776",
    "sg:province":"FL",
    "sg:tags":[
        "course"
    ],
    "sg:website":"http://www.eagledunes.com/",
    "wof:name":"Eagle Dunes Golf Club",
    "wof:placetype":"venue"
},
  "geometry": {"coordinates":[-81.559967,28.85062],"type":"Point"}
}