{
  "type": "Feature",
  "properties": {
    "addr:full":"6445 Sextant Ct Orlando FL 32807",
    "addr:housenumber":"6445",
    "addr:postcode":"32807",
    "addr:street":"Sextant Ct",
    "iso:country":"US",
    "sg:address":"6445 Sextant Ct",
    "sg:city":"Orlando",
    "sg:classifiers":[
        {
            "category":"Retail",
            "subcategory":"Repair Shop",
            "type":"Services"
        }
    ],
    "sg:phone":"+1 407 282 1364",
    "sg:postcode":"32807",
    "sg:province":"FL",
    "sg:tags":[
        "appliance"
    ],
    "wof:name":"Harvey's Repair Svc",
    "wof:placetype":"venue"
},
  "geometry": {"coordinates":[-81.295159,28.526817],"type":"Point"}
}