{
  "type": "Feature",
  "properties": {
    "addr:full":"2880 Capital Medical Blvd Tallahassee FL 32308",
    "addr:postcode":"2880;32308",
    "addr:street":"Capital Medical Blvd",
    "iso:country":"US",
    "sg:address":"2880 Capital Medical Blvd",
    "sg:city":"Tallahassee",
    "sg:classifiers":[
        {
            "category":"Health Services",
            "subcategory":"Health Practitioner",
            "type":"Services"
        }
    ],
    "sg:phone":"+1 850 222 2880",
    "sg:postcode":"32308",
    "sg:province":"FL",
    "sg:tags":[
        "psychologist"
    ],
    "wof:name":"Holistic Psychological Svc",
    "wof:placetype":"venue"
},
  "geometry": {"coordinates":[-84.231706,30.474438],"type":"Point"}
}