{
  "type": "Feature",
  "properties": {
    "addr:full":"3555 NW 53rd Ct Fort Lauderdale FL 33309",
    "addr:housenumber":"3555",
    "addr:postcode":"33309",
    "addr:street":"Nw 53Rd Ct",
    "iso:country":"US",
    "sg:address":"3555 NW 53rd Ct",
    "sg:city":"Fort Lauderdale",
    "sg:classifiers":[
        {
            "category":"Real Estate",
            "subcategory":"Architect",
            "type":"Services"
        }
    ],
    "sg:phone":"+1 954 717 4155",
    "sg:postcode":"33309",
    "sg:province":"FL",
    "sg:tags":[
        "architectural"
    ],
    "wof:name":"Luminis USA",
    "wof:placetype":"venue"
},
  "geometry": {"coordinates":[-80.197076,26.191562],"type":"Point"}
}