{
  "type": "Feature",
  "properties": {
    "addr:full":"27132 Iron Gate Ln Zephyrhills FL 33544",
    "addr:housenumber":"27132",
    "addr:postcode":"33544",
    "addr:street":"Iron Gate Ln",
    "iso:country":"US",
    "sg:address":"27132 Iron Gate Ln",
    "sg:city":"Zephyrhills",
    "sg:classifiers":[
        {
            "category":"Home & Garden",
            "subcategory":"Garden Supply",
            "type":"Retail Goods"
        }
    ],
    "sg:phone":"+1 813 994 7246",
    "sg:postcode":"33544",
    "sg:province":"FL",
    "sg:tags":[
        "sprinkler"
    ],
    "wof:name":"Aqua Tek Irrigation LLC",
    "wof:placetype":"venue"
},
  "geometry": {"coordinates":[-82.36476500000001,28.265649],"type":"Point"}
}