{
  "type": "Feature",
  "properties": {
    "addr:full":"2315 W 15th St Panama City FL 32401",
    "addr:housenumber":"2315",
    "addr:postcode":"32401",
    "addr:street":"W 15Th St",
    "iso:country":"US",
    "sg:address":"2315 W 15th St",
    "sg:city":"Panama City",
    "sg:classifiers":[
        {
            "category":"Building & Trades",
            "subcategory":"Construction",
            "type":"Services"
        },
        {
            "category":"Retail",
            "subcategory":"Auto Repair",
            "type":"Services"
        }
    ],
    "sg:phone":"+1 850 763 0004",
    "sg:postcode":"32401",
    "sg:province":"FL",
    "sg:tags":[
        "glass",
        "coating",
        "tinting",
        "contractor"
    ],
    "wof:name":"Window Graphics",
    "wof:placetype":"venue"
},
  "geometry": {"coordinates":[-85.69513600000001,30.175316],"type":"Point"}
}