{
  "type": "Feature",
  "properties": {
    "addr:full":"751 N Greenway Dr Miami FL 33134",
    "addr:housenumber":"751",
    "addr:postcode":"33134",
    "addr:street":"N Greenway Dr",
    "iso:country":"US",
    "sg:address":"751 N Greenway Dr",
    "sg:city":"Miami",
    "sg:classifiers":[
        {
            "category":"Wholesale",
            "subcategory":"Machinery & Supplies",
            "type":"Manufacturing & Wholesale Goods"
        }
    ],
    "sg:phone":"+1 305 666 5174",
    "sg:postcode":"33134",
    "sg:province":"FL",
    "wof:name":"Vincent Import & Export Inc",
    "wof:placetype":"venue"
},
  "geometry": {"coordinates":[-80.270933,25.751306],"type":"Point"}
}