{
  "type": "Feature",
  "properties": {
    "iso:country":"US",
    "sg:address":"292 S Federal Hwy",
    "sg:city":"Deerfield Beach",
    "sg:classifiers":[
        {
            "category":"Retail",
            "subcategory":"Laundry & Dry Cleaning",
            "type":"Services"
        }
    ],
    "sg:phone":"+1 954 418 8024",
    "sg:postcode":"33441",
    "sg:province":"FL",
    "sg:tags":[
        "garment",
        "agent"
    ],
    "wof:name":"Nu Look 1 Hour Cleaners",
    "wof:placetype":"venue"
},
  "geometry": {"coordinates":[-80.091432,26.313787],"type":"Point"}
}