{
  "type": "Feature",
  "properties": {
    "addr:full":"2627 Blairstone Rd Tallahassee FL 32301",
    "addr:housenumber":"2627",
    "addr:postcode":"32301",
    "addr:street":"Blairstone Rd",
    "iso:country":"US",
    "sg:address":"2627 Blairstone Rd",
    "sg:city":"Tallahassee",
    "sg:classifiers":[
        {
            "category":"Professional",
            "type":"Services"
        }
    ],
    "sg:phone":"+1 850 656 7055",
    "sg:postcode":"32301",
    "sg:province":"FL",
    "sg:tags":[
        "establishment"
    ],
    "wof:name":"D L Harris & Assoc",
    "wof:placetype":"venue"
},
  "geometry": {"coordinates":[-84.249433,30.426409],"type":"Point"}
}