{
  "type": "Feature",
  "properties": {
    "iso:country":"US",
    "sg:address":"8080 Tatum Waterway Dr",
    "sg:city":"Miami Beach",
    "sg:classifiers":[
        {
            "category":"Banks & Credit Unions",
            "subcategory":"Financial Services",
            "type":"Services"
        }
    ],
    "sg:phone":"+1 305 865 8013",
    "sg:postcode":"33141",
    "sg:province":"FL",
    "sg:tags":[
        "company",
        "holding"
    ],
    "wof:name":"Beech Holdings Inc",
    "wof:placetype":"venue"
},
  "geometry": {"coordinates":[-80.124149,25.866004],"type":"Point"}
}