{
  "type": "Feature",
  "properties": {
    "addr:full":"6339 Sutherland Ave New Port Richey FL 34653",
    "addr:housenumber":"6339",
    "addr:postcode":"34653",
    "addr:street":"Sutherland Ave",
    "iso:country":"US",
    "sg:address":"6339 Sutherland Ave",
    "sg:city":"New Port Richey",
    "sg:classifiers":[
        {
            "category":"Building & Trades",
            "subcategory":"Landscaping Services",
            "type":"Services"
        }
    ],
    "sg:phone":"+1 727 815 0148",
    "sg:postcode":"34653",
    "sg:province":"FL",
    "wof:name":"Green Heaven Lawn Care",
    "wof:placetype":"venue"
},
  "geometry": {"coordinates":[-82.708955,28.268477],"type":"Point"}
}