{
  "type": "Feature",
  "properties": {
    "iso:country":"US",
    "sg:address":"501 Oak Briar Pl",
    "sg:city":"Brandon",
    "sg:classifiers":[
        {
            "category":"Local Transit",
            "type":"Transportation"
        }
    ],
    "sg:phone":"+1 813 681 7171",
    "sg:postcode":"33510",
    "sg:province":"FL",
    "sg:tags":[
        "ambulance"
    ],
    "wof:name":"Lifefleet",
    "wof:placetype":"venue"
},
  "geometry": {"coordinates":[-82.28214199999999,27.94633],"type":"Point"}
}