{
  "type": "Feature",
  "properties": {
    "iso:country":"US",
    "sg:address":"501 NE 14th Ave",
    "sg:city":"Hallandale Beach",
    "sg:classifiers":[
        {
            "category":"Wholesale",
            "subcategory":"Durable Goods & Equipment",
            "type":"Manufacturing & Wholesale Goods"
        }
    ],
    "sg:phone":"+1 305 932 7779",
    "sg:postcode":"33009",
    "sg:province":"FL",
    "sg:tags":[
        "exporter"
    ],
    "wof:name":"Sommer By Kids Inc",
    "wof:placetype":"venue"
},
  "geometry": {"coordinates":[-80.13446399999999,25.991732],"type":"Point"}
}