{
  "type": "Feature",
  "properties": {
    "addr:full":"18468 SE Heritage Dr Jupiter FL 33469",
    "addr:housenumber":"18468",
    "addr:postcode":"33469",
    "addr:street":"Se Heritage Dr",
    "iso:country":"US",
    "sg:address":"18468 SE Heritage Dr",
    "sg:city":"Jupiter",
    "sg:classifiers":[
        {
            "category":"Autos & Motor Vehicles",
            "subcategory":"Fuel & Gas Station",
            "type":"Retail Goods"
        }
    ],
    "sg:phone":"+1 561 744 0652",
    "sg:postcode":"33469",
    "sg:province":"FL",
    "sg:tags":[
        "station",
        "gasoline"
    ],
    "wof:name":"Horizon Oil Inc",
    "wof:placetype":"venue"
},
  "geometry": {"coordinates":[-80.116321,26.983941],"type":"Point"}
}