{
  "type": "Feature",
  "properties": {
    "iso:country":"US",
    "sg:address":"85 4th Ave",
    "sg:city":"Shalimar",
    "sg:classifiers":[
        {
            "category":"Banks & Credit Unions",
            "subcategory":"Investment Brokerage",
            "type":"Services"
        }
    ],
    "sg:phone":"+1 850 609 3737",
    "sg:postcode":"32579",
    "sg:province":"FL",
    "sg:tags":[
        "advisory",
        "financial"
    ],
    "wof:name":"TATM Financial Systems",
    "wof:placetype":"venue"
},
  "geometry": {"coordinates":[-86.569087,30.438984],"type":"Point"}
}