{
  "type": "Feature",
  "properties": {
    "addr:full":"3015 Alafaya Trl Oviedo FL 32765",
    "addr:housenumber":"3015",
    "addr:postcode":"32765",
    "addr:street":"Alafaya Trl",
    "iso:country":"US",
    "sg:address":"3015 Alafaya Trl",
    "sg:city":"Oviedo",
    "sg:classifiers":[
        {
            "category":"Restaurant",
            "type":"Food & Drink"
        }
    ],
    "sg:phone":"+1 407 366 4416",
    "sg:postcode":"32765",
    "sg:province":"FL",
    "wof:name":"Blimpie Subs & Salads",
    "wof:placetype":"venue"
},
  "geometry": {"coordinates":[-81.207711,28.627027],"type":"Point"}
}