{
  "type": "Feature",
  "properties": {
    "iso:country":"US",
    "sg:address":"12835 NE 6th Ave",
    "sg:city":"North Miami",
    "sg:classifiers":[
        {
            "category":"Shopping",
            "subcategory":"Beauty & Cosmetics",
            "type":"Retail Goods"
        }
    ],
    "sg:phone":"+1 305 899 6937",
    "sg:postcode":"33161",
    "sg:province":"FL",
    "sg:tags":[
        "supply"
    ],
    "wof:name":"Beauty Supply and More",
    "wof:placetype":"venue"
},
  "geometry": {"coordinates":[-80.186425,25.893317],"type":"Point"}
}