{
  "type": "Feature",
  "properties": {
    "addr:full":"400 S Atlantic Ave Ormond Beach FL 32176",
    "addr:housenumber":"400",
    "addr:postcode":"32176",
    "addr:street":"S Atlantic Ave",
    "iso:country":"US",
    "sg:address":"400 S Atlantic Ave",
    "sg:city":"Ormond Beach",
    "sg:classifiers":[
        {
            "category":"Wholesale",
            "subcategory":"Medical Equipment & Supplies",
            "type":"Manufacturing & Wholesale Goods"
        }
    ],
    "sg:phone":"+1 386 672 3278",
    "sg:postcode":"32176",
    "sg:province":"FL",
    "sg:tags":[
        "physician",
        "surgeon"
    ],
    "sg:website":"www.americandiabeticsupply.com",
    "wof:name":"American Diabetic Supply Inc",
    "wof:placetype":"venue"
},
  "geometry": {"coordinates":[-81.035507,29.282757],"type":"Point"}
}