{
  "type": "Feature",
  "properties": {
    "iso:country":"US",
    "sg:address":"1176 Edgewood Ave S",
    "sg:city":"Jacksonville",
    "sg:classifiers":[
        {
            "category":"Home & Garden",
            "subcategory":"Carpets & Floor Coverings",
            "type":"Retail Goods"
        }
    ],
    "sg:phone":"+1 904 389 5474",
    "sg:postcode":"32205",
    "sg:province":"FL",
    "sg:tags":[
        "dealer",
        "rug"
    ],
    "wof:name":"Carpet King",
    "wof:placetype":"venue"
},
  "geometry": {"coordinates":[-81.713568,30.30818],"type":"Point"}
}