{
  "type": "Feature",
  "properties": {
    "iso:country":"US",
    "sg:address":"6220 Beach Blvd",
    "sg:city":"Jacksonville",
    "sg:classifiers":[
        {
            "category":"Building & Trades",
            "subcategory":"Plumbing",
            "type":"Services"
        }
    ],
    "sg:phone":"+1 904 724 0453",
    "sg:postcode":"32216",
    "sg:province":"FL",
    "sg:tags":[
        "conditioning",
        "air",
        "system",
        "contractor"
    ],
    "wof:name":"Harvey's Fuel Oil",
    "wof:placetype":"venue"
},
  "geometry": {"coordinates":[-81.598529,30.291482],"type":"Point"}
}