{
  "type": "Feature",
  "properties": {
    "addr:full":"1212 SW 4th Ave Delray Beach FL 33444",
    "addr:housenumber":"1212",
    "addr:postcode":"33444",
    "addr:street":"Sw 4Th Ave",
    "iso:country":"US",
    "sg:address":"1212 SW 4th Ave",
    "sg:city":"Delray Beach",
    "sg:classifiers":[
        {
            "category":"Building & Trades",
            "subcategory":"Construction",
            "type":"Services"
        }
    ],
    "sg:phone":"+1 561 266 8569",
    "sg:postcode":"33444",
    "sg:province":"FL",
    "sg:tags":[
        "tile",
        "dealer",
        "contractor"
    ],
    "wof:name":"Sully's Tile Inc",
    "wof:placetype":"venue"
},
  "geometry": {"coordinates":[-80.077162,26.443146],"type":"Point"}
}