{
  "type": "Feature",
  "properties": {
    "iso:country":"US",
    "sg:address":"701 NW 7th Ave",
    "sg:city":"Plantation",
    "sg:classifiers":[
        {
            "category":"Retail",
            "subcategory":"Auto Repair",
            "type":"Services"
        }
    ],
    "sg:phone":"+1 954 522 4141",
    "sg:postcode":"33311",
    "sg:province":"FL",
    "sg:tags":[
        "repairing",
        "automobile"
    ],
    "wof:name":"Eava Auto Repair",
    "wof:placetype":"venue"
},
  "geometry": {"coordinates":[-80.150796,26.133087],"type":"Point"}
}