{
  "type": "Feature",
  "properties": {
    "iso:country":"US",
    "sg:address":"17502 E Colonial Dr",
    "sg:city":"Orlando",
    "sg:classifiers":[
        {
            "category":"Restaurant",
            "type":"Food & Drink"
        },
        {
            "category":"Bars & Pubs",
            "type":"Food & Drink"
        }
    ],
    "sg:phone":"+1 407 568 6669",
    "sg:postcode":"32820",
    "sg:province":"FL",
    "sg:tags":[
        "lounge",
        "drinking",
        "eating",
        "cocktail"
    ],
    "wof:name":"Bottle Caps Bar & Grill Inc",
    "wof:placetype":"venue"
},
  "geometry": {"coordinates":[-81.11585599999999,28.556273],"type":"Point"}
}