{
  "type": "Feature",
  "properties": {
    "iso:country":"US",
    "sg:address":"1630 Periwinkle Way",
    "sg:city":"Sanibel",
    "sg:classifiers":[
        {
            "category":"Travel",
            "subcategory":"Hotels & Motels",
            "type":"Entertainment"
        }
    ],
    "sg:phone":"+1 239 472 6565",
    "sg:postcode":"33957",
    "sg:province":"FL",
    "sg:tags":[
        "operation"
    ],
    "sg:website":"www.sanibelholiday.com",
    "wof:name":"Sainbel Holiday",
    "wof:placetype":"venue"
},
  "geometry": {"coordinates":[-82.057033,26.442073],"type":"Point"}
}