{
  "type": "Feature",
  "properties": {
    "addr:full":"1700 Waterford Dr Vero Beach FL 32966",
    "addr:housenumber":"1700",
    "addr:postcode":"32966",
    "addr:street":"Waterford Dr",
    "iso:country":"US",
    "sg:address":"1700 Waterford Dr",
    "sg:city":"Vero Beach",
    "sg:classifiers":[
        {
            "category":"Health Services",
            "subcategory":"Health Practitioner",
            "type":"Services"
        }
    ],
    "sg:phone":"+1 772 564 0484",
    "sg:postcode":"32966",
    "sg:province":"FL",
    "sg:tags":[
        "therapist",
        "physical"
    ],
    "wof:name":"Alliance Health Care Svc Inc",
    "wof:placetype":"venue"
},
  "geometry": {"coordinates":[-80.47225,27.63244],"type":"Point"}
}