{
  "type": "Feature",
  "properties": {
    "addr:full":"2150 W International Speedway Blvd Daytona Beach FL 32114",
    "addr:housenumber":"2150",
    "addr:postcode":"32114",
    "addr:street":"W International Speedway Blvd",
    "iso:country":"US",
    "sg:address":"2150 W International Speedway Blvd",
    "sg:city":"Daytona Beach",
    "sg:classifiers":[
        {
            "category":"Food & Beverages",
            "subcategory":"Groceries & Convenience Stores",
            "type":"Retail Goods"
        }
    ],
    "sg:phone":"+1 386 253 3468",
    "sg:postcode":"32114",
    "sg:province":"FL",
    "wof:name":"7-Eleven",
    "wof:placetype":"venue"
},
  "geometry": {"coordinates":[-81.07861800000001,29.18312],"type":"Point"}
}