{
  "type": "Feature",
  "properties": {
    "iso:country":"US",
    "sg:address":"6070 Shakespeare Dr",
    "sg:city":"Jacksonville",
    "sg:classifiers":[
        {
            "category":"Professional",
            "subcategory":"Art Services",
            "type":"Services"
        }
    ],
    "sg:phone":"+1 904 908 0866",
    "sg:postcode":"32244",
    "sg:province":"FL",
    "sg:tags":[
        "photographer"
    ],
    "wof:name":"Serrano Video & Photo",
    "wof:placetype":"venue"
},
  "geometry": {"coordinates":[-81.78509699999999,30.23919],"type":"Point"}
}