{
  "type": "Feature",
  "properties": {
    "addr:full":"3439 W Hillsborough Ave Tampa FL 33614",
    "addr:housenumber":"3439",
    "addr:postcode":"33614",
    "addr:street":"W Hillsborough Ave",
    "iso:country":"US",
    "sg:address":"3439 W Hillsborough Ave",
    "sg:city":"Tampa",
    "sg:classifiers":[
        {
            "category":"Banks & Credit Unions",
            "subcategory":"Bank",
            "type":"Services"
        }
    ],
    "sg:phone":"+1 813 872 9174",
    "sg:postcode":"33614",
    "sg:province":"FL",
    "sg:tags":[
        "national",
        "commercial"
    ],
    "wof:name":"Bank Of America",
    "wof:placetype":"venue"
},
  "geometry": {"coordinates":[-82.49806599999999,27.99608],"type":"Point"}
}