{
  "type": "Feature",
  "properties": {
    "iso:country":"US",
    "sg:address":"745 Ridgewood Ave",
    "sg:city":"Daytona Beach",
    "sg:classifiers":[
        {
            "category":"Restaurant",
            "type":"Food & Drink"
        }
    ],
    "sg:menulink":"http://www.allmenus.com/fl/ormond-beach/219491-diamond-backs/menu/",
    "sg:phone":"+1 386 255 5596",
    "sg:postcode":"32117",
    "sg:province":"FL",
    "sg:tags":[
        "american"
    ],
    "wof:name":"Diamond Backs",
    "wof:placetype":"venue"
},
  "geometry": {"coordinates":[-81.037554,29.238389],"type":"Point"}
}