{
  "type": "Feature",
  "properties": {
    "iso:country":"US",
    "sg:address":"863 School St",
    "sg:city":"Brooksville",
    "sg:classifiers":[
        {
            "category":"Organizations",
            "subcategory":"Religious Organization",
            "type":"Services"
        }
    ],
    "sg:phone":"+1 352 799 2775",
    "sg:postcode":"34601",
    "sg:province":"FL",
    "sg:tags":[
        "church"
    ],
    "wof:name":"Mount Pilgrim Freewill Baptist",
    "wof:placetype":"venue"
},
  "geometry": {"coordinates":[-82.379998,28.544244],"type":"Point"}
}