{
  "type": "Feature",
  "properties": {
    "iso:country":"US",
    "sg:address":"9130 S Dadeland Blvd",
    "sg:city":"Miami",
    "sg:classifiers":[
        {
            "category":"Banks & Credit Unions",
            "subcategory":"Financial Services",
            "type":"Services"
        }
    ],
    "sg:phone":"+1 305 670 4400",
    "sg:postcode":"33156",
    "sg:province":"FL",
    "sg:tags":[
        "consultant",
        "planning"
    ],
    "wof:name":"Miami /Ft Lauderdale Branch",
    "wof:placetype":"venue"
},
  "geometry": {"coordinates":[-80.31473,25.685558],"type":"Point"}
}