{
  "type": "Feature",
  "properties": {
    "addr:full":"16110 SW 101st Ave Miami FL 33157",
    "addr:housenumber":"16110",
    "addr:postcode":"33157",
    "addr:street":"Sw 101St Ave",
    "iso:country":"US",
    "sg:address":"16110 SW 101st Ave",
    "sg:city":"Miami",
    "sg:classifiers":[
        {
            "category":"Health Services",
            "subcategory":"Nursing And Care Facility",
            "type":"Services"
        }
    ],
    "sg:phone":"+1 305 252 3453",
    "sg:postcode":"33157",
    "sg:province":"FL",
    "sg:tags":[
        "home",
        "retirement",
        "community"
    ],
    "wof:name":"Palms Villa Retirement",
    "wof:placetype":"venue"
},
  "geometry": {"coordinates":[-80.35690200000001,25.620541],"type":"Point"}
}