{
  "type": "Feature",
  "properties": {
    "addr:full":"8725 NW 18th Ave Miami FL 33147",
    "addr:housenumber":"8725",
    "addr:postcode":"33147",
    "addr:street":"Nw 18Th Ave",
    "iso:country":"US",
    "sg:address":"8725 NW 18th Ave",
    "sg:city":"Miami",
    "sg:classifiers":[
        {
            "category":"Banks & Credit Unions",
            "subcategory":"Financial Services",
            "type":"Services"
        }
    ],
    "sg:phone":"+1 305 728 8200",
    "sg:postcode":"33147",
    "sg:province":"FL",
    "sg:tags":[
        "broker",
        "mortgage"
    ],
    "wof:name":"Total Home Financial Services",
    "wof:placetype":"venue"
},
  "geometry": {"coordinates":[-80.227514,25.853797],"type":"Point"}
}