{
  "type": "Feature",
  "properties": {
    "iso:country":"US",
    "sg:address":"1014 Creighton Rd",
    "sg:city":"Pensacola",
    "sg:classifiers":[
        {
            "category":"Wholesale",
            "subcategory":"Durable Goods & Equipment",
            "type":"Manufacturing & Wholesale Goods"
        }
    ],
    "sg:phone":"+1 850 477 1200",
    "sg:postcode":"32504",
    "sg:province":"FL",
    "sg:tags":[
        "representative",
        "manufacturer"
    ],
    "sg:website":"www.rmtugwell.com",
    "wof:name":"R M Tugwell & Assoc",
    "wof:placetype":"venue"
},
  "geometry": {"coordinates":[-87.21757100000001,30.496402],"type":"Point"}
}