{
  "type": "Feature",
  "properties": {
    "addr:full":"820 Patio Rd Fort Walton Bch FL 32547",
    "addr:housenumber":"820",
    "addr:postcode":"32547",
    "addr:street":"Patio Rd",
    "iso:country":"US",
    "sg:address":"820 Patio Rd",
    "sg:city":"Fort Walton Bch",
    "sg:classifiers":[
        {
            "category":"Professional",
            "type":"Services"
        }
    ],
    "sg:phone":"+1 850 243 4613",
    "sg:postcode":"32547",
    "sg:province":"FL",
    "sg:tags":[
        "metal",
        "cleaning"
    ],
    "wof:name":"Mirror Finishes",
    "wof:placetype":"venue"
},
  "geometry": {"coordinates":[-86.620774,30.447851],"type":"Point"}
}