{
  "type": "Feature",
  "properties": {
    "iso:country":"US",
    "sg:address":"600 Second St",
    "sg:city":"Miami",
    "sg:classifiers":[
        {
            "category":"Deli",
            "type":"Food & Drink"
        },
        {
            "category":"Food & Beverages",
            "subcategory":"Bakery",
            "type":"Retail Goods"
        }
    ],
    "sg:phone":"+1 800 933 8309",
    "sg:postcode":"33189",
    "sg:province":"FL",
    "sg:tags":[
        "sandwich"
    ],
    "wof:name":"N. Miami Florists & Gifts Deli",
    "wof:placetype":"venue"
},
  "geometry": {"coordinates":[-80.20439500000001,25.775643],"type":"Point"}
}