{
  "type": "Feature",
  "properties": {
    "iso:country":"US",
    "sg:address":"425 SE 14th St",
    "sg:city":"Dania",
    "sg:classifiers":[
        {
            "category":"Professional",
            "subcategory":"Business Services",
            "type":"Services"
        }
    ],
    "sg:phone":"+1 954 732 9769",
    "sg:postcode":"33004",
    "sg:province":"FL",
    "sg:tags":[
        "holding"
    ],
    "wof:name":"Florida Investment Holdings",
    "wof:placetype":"venue"
},
  "geometry": {"coordinates":[-80.136454,26.03561],"type":"Point"}
}