{
  "type": "Feature",
  "properties": {
    "iso:country":"US",
    "sg:address":"7354 SW 48th St",
    "sg:city":"Miami",
    "sg:classifiers":[
        {
            "category":"Wholesale",
            "subcategory":"Auto Parts",
            "type":"Manufacturing & Wholesale Goods"
        }
    ],
    "sg:phone":"+1 305 663 0919",
    "sg:postcode":"33155",
    "sg:province":"FL",
    "wof:name":"Parts Depot Inc",
    "wof:placetype":"venue"
},
  "geometry": {"coordinates":[-80.31193399999999,25.725527],"type":"Point"}
}