{
  "type": "Feature",
  "properties": {
    "iso:country":"US",
    "sg:address":"2852 Ashton Ter",
    "sg:city":"Oviedo",
    "sg:classifiers":[
        {
            "category":"Manufacturing",
            "subcategory":"Electronics",
            "type":"Manufacturing & Wholesale Goods"
        }
    ],
    "sg:phone":"+1 407 977 7888",
    "sg:postcode":"32765",
    "sg:province":"FL",
    "sg:tags":[
        "equipment",
        "electronic",
        "supply"
    ],
    "wof:name":"Danfoss Water & Wastewater",
    "wof:placetype":"venue"
},
  "geometry": {"coordinates":[-81.23343800000001,28.634158],"type":"Point"}
}