{
  "type": "Feature",
  "properties": {
    "addr:full":"2539 Russell Rd Green Cove Springs FL 32043",
    "addr:housenumber":"2539",
    "addr:postcode":"32043",
    "addr:street":"Russell Rd",
    "iso:country":"US",
    "sg:address":"2539 Russell Rd",
    "sg:city":"Green Cove Springs",
    "sg:classifiers":[
        {
            "category":"Freight",
            "type":"Transportation"
        }
    ],
    "sg:phone":"+1 904 284 2235",
    "sg:postcode":"32043",
    "sg:province":"FL",
    "sg:tags":[
        "operator",
        "trucking"
    ],
    "wof:name":"Fowler Ventures Inc",
    "wof:placetype":"venue"
},
  "geometry": {"coordinates":[-81.78094900000001,30.074869],"type":"Point"}
}