{
  "type": "Feature",
  "properties": {
    "iso:country":"US",
    "sg:address":"51 NE 40th St",
    "sg:city":"Miami",
    "sg:classifiers":[
        {
            "category":"Home & Garden",
            "subcategory":"Furniture",
            "type":"Retail Goods"
        }
    ],
    "sg:phone":"+1 305 573 9988",
    "sg:postcode":"33137",
    "sg:province":"FL",
    "sg:tags":[
        "store"
    ],
    "wof:name":"Now A Style Store Inc",
    "wof:placetype":"venue"
},
  "geometry": {"coordinates":[-80.195198,25.813499],"type":"Point"}
}