{
  "type": "Feature",
  "properties": {
    "addr:full":"1318 E Las Olas Blvd Fort Lauderdale FL 33301",
    "addr:housenumber":"1318",
    "addr:postcode":"33301",
    "addr:street":"E Las Olas Blvd",
    "iso:country":"US",
    "sg:address":"1318 E Las Olas Blvd",
    "sg:city":"Fort Lauderdale",
    "sg:classifiers":[
        {
            "category":"Shopping",
            "subcategory":"Gifts & Souvenirs",
            "type":"Retail Goods"
        }
    ],
    "sg:phone":"+1 954 522 4720",
    "sg:postcode":"33301",
    "sg:province":"FL",
    "sg:tags":[
        "shop"
    ],
    "wof:name":"Angel Haven",
    "wof:placetype":"venue"
},
  "geometry": {"coordinates":[-80.128939,26.119319],"type":"Point"}
}