{
  "type": "Feature",
  "properties": {
    "iso:country":"US",
    "sg:address":"3301 Ave D",
    "sg:city":"Fort Pierce",
    "sg:classifiers":[
        {
            "category":"Manufacturing",
            "subcategory":"Metals",
            "type":"Manufacturing & Wholesale Goods"
        }
    ],
    "sg:phone":"+1 772 461 1831",
    "sg:postcode":"34947",
    "sg:province":"FL",
    "sg:tags":[
        "secondary",
        "refining",
        "smelting"
    ],
    "wof:name":"Atlantic Coast Recycling Inc",
    "wof:placetype":"venue"
},
  "geometry": {"coordinates":[-80.358906,27.452913],"type":"Point"}
}