{
  "type": "Feature",
  "properties": {
    "iso:country":"US",
    "sg:address":"1020 Capri Isles Blvd",
    "sg:city":"Venice",
    "sg:classifiers":[
        {
            "category":"Building & Trades",
            "subcategory":"Construction",
            "type":"Services"
        }
    ],
    "sg:phone":"+1 941 358 7559",
    "sg:postcode":"34292",
    "sg:province":"FL",
    "sg:tags":[
        "contractor"
    ],
    "wof:name":"Bingo Sign Co Inc",
    "wof:placetype":"venue"
},
  "geometry": {"coordinates":[-82.410501,27.114523],"type":"Point"}
}