{
  "type": "Feature",
  "properties": {
    "iso:country":"US",
    "sg:address":"2238 Hayes St",
    "sg:city":"Hollywood",
    "sg:classifiers":[
        {
            "category":"Food & Beverages",
            "subcategory":"Specialty",
            "type":"Retail Goods"
        }
    ],
    "sg:phone":"+1 954 927 6278",
    "sg:postcode":"33020",
    "sg:province":"FL",
    "wof:name":"Hollywood Gourmet Coffee Inc",
    "wof:placetype":"venue"
},
  "geometry": {"coordinates":[-80.154152,26.02049],"type":"Point"}
}