{
  "type": "Feature",
  "properties": {
    "addr:full":"312 Lewis St Tallahassee FL 32301",
    "addr:housenumber":"312",
    "addr:postcode":"32301",
    "addr:street":"Lewis St",
    "iso:country":"US",
    "sg:address":"312 Lewis St",
    "sg:city":"Tallahassee",
    "sg:classifiers":[
        {
            "category":"Building & Trades",
            "subcategory":"Construction",
            "type":"Services"
        }
    ],
    "sg:phone":"+1 850 878 5407",
    "sg:postcode":"32301",
    "sg:province":"FL",
    "sg:tags":[
        "painter"
    ],
    "wof:name":"Clinton Painting",
    "wof:placetype":"venue"
},
  "geometry": {"coordinates":[-84.27951299999999,30.4207],"type":"Point"}
}