{
  "type": "Feature",
  "properties": {
    "iso:country":"US",
    "sg:address":"13595 NW 102nd Ave",
    "sg:city":"Hialeah",
    "sg:classifiers":[
        {
            "category":"Building & Trades",
            "subcategory":"Plumbing",
            "type":"Services"
        }
    ],
    "sg:phone":"+1 305 512 4505",
    "sg:postcode":"33018",
    "sg:province":"FL",
    "sg:tags":[
        "plumbing",
        "contractor"
    ],
    "wof:name":"J C Plumbing",
    "wof:placetype":"venue"
},
  "geometry": {"coordinates":[-80.364347,25.89754],"type":"Point"}
}