{
  "type": "Feature",
  "properties": {
    "addr:full":"2564 Palm Shores Dr Shalimar FL 32579",
    "addr:housenumber":"2564",
    "addr:postcode":"32579",
    "addr:street":"Palm Shores Dr",
    "iso:country":"US",
    "sg:address":"2564 Palm Shores Dr",
    "sg:city":"Shalimar",
    "sg:classifiers":[
        {
            "category":"Professional",
            "subcategory":"Engineering",
            "type":"Services"
        }
    ],
    "sg:phone":"+1 850 651 5900",
    "sg:postcode":"32579",
    "sg:province":"FL",
    "sg:tags":[
        "engineer"
    ],
    "wof:name":"Paradigm Technical Svc",
    "wof:placetype":"venue"
},
  "geometry": {"coordinates":[-86.58432000000001,30.446388],"type":"Point"}
}