{
  "type": "Feature",
  "properties": {
    "iso:country":"US",
    "sg:address":"101 W Cypress St",
    "sg:city":"Kissimmee",
    "sg:classifiers":[
        {
            "category":"Organizations",
            "subcategory":"Religious Organization",
            "type":"Services"
        }
    ],
    "sg:phone":"+1 407 847 3696",
    "sg:postcode":"34741",
    "sg:province":"FL",
    "wof:name":"Love Temple Fellowship Inc",
    "wof:placetype":"venue"
},
  "geometry": {"coordinates":[-81.40593200000001,28.305801],"type":"Point"}
}