{
  "type": "Feature",
  "properties": {
    "addr:full":"1045 W Orange Blossom Trl Apopka FL 32712",
    "addr:housenumber":"1045",
    "addr:postcode":"32712",
    "addr:street":"W Orange Blossom Trl",
    "iso:country":"US",
    "sg:address":"1045 W Orange Blossom Trl",
    "sg:city":"Apopka",
    "sg:classifiers":[
        {
            "category":"Education",
            "subcategory":"Special Training",
            "type":"Public Place"
        }
    ],
    "sg:phone":"+1 407 884 4600",
    "sg:postcode":"32712",
    "sg:province":"FL",
    "sg:tags":[
        "center"
    ],
    "wof:name":"Apopka Learning Ctr",
    "wof:placetype":"venue"
},
  "geometry": {"coordinates":[-81.527383,28.682135],"type":"Point"}
}