{
  "type": "Feature",
  "properties": {
    "addr:full":"1411 el Rito Dr Gulf Breeze FL 32563",
    "addr:housenumber":"1411",
    "addr:postcode":"32563",
    "addr:street":"El Rito Dr",
    "iso:country":"US",
    "sg:address":"1411 el Rito Dr",
    "sg:city":"Gulf Breeze",
    "sg:classifiers":[
        {
            "category":"Building & Trades",
            "subcategory":"Landscaping Services",
            "type":"Services"
        }
    ],
    "sg:phone":"+1 850 934 7363",
    "sg:postcode":"32563",
    "sg:province":"FL",
    "wof:name":"Hering Inc",
    "wof:placetype":"venue"
},
  "geometry": {"coordinates":[-87.082938,30.388787],"type":"Point"}
}