{
  "type": "Feature",
  "properties": {
    "iso:country":"US",
    "sg:address":"7055 S Semoran Blvd",
    "sg:city":"Orlando",
    "sg:classifiers":[
        {
            "category":"Restaurant",
            "type":"Food & Drink"
        }
    ],
    "sg:menulink":"http://www.allmenus.com/fl/orlando/33257-bennigans-grill--tavern/menu/",
    "sg:phone":"+1 407 852 1871",
    "sg:postcode":"32822",
    "sg:province":"FL",
    "sg:tags":[
        "sandwich",
        "salad",
        "burger",
        "pub",
        "soup",
        "american",
        "wrap"
    ],
    "wof:name":"Bennigan's Grill & Tavern",
    "wof:placetype":"venue"
},
  "geometry": {"coordinates":[-81.309922,28.460865],"type":"Point"}
}