{
  "type": "Feature",
  "properties": {
    "iso:country":"US",
    "sg:address":"4051 Arbor Lake Dr W",
    "sg:city":"Jacksonville",
    "sg:classifiers":[
        {
            "category":"Building & Trades",
            "subcategory":"Landscaping Services",
            "type":"Services"
        }
    ],
    "sg:phone":"+1 904 565 9651",
    "sg:postcode":"32225",
    "sg:province":"FL",
    "wof:name":"James Terry Holt Jr Lawn Care",
    "wof:placetype":"venue"
},
  "geometry": {"coordinates":[-81.510378,30.371571],"type":"Point"}
}