{
  "type": "Feature",
  "properties": {
    "iso:country":"US",
    "sg:address":"20071 Petrucka Cir",
    "sg:city":"Lehigh Acres",
    "sg:classifiers":[
        {
            "category":"Restaurant",
            "type":"Food & Drink"
        }
    ],
    "sg:phone":"+1 239 344 0039",
    "sg:postcode":"33936",
    "sg:province":"FL",
    "wof:name":"Huday's Ball Park",
    "wof:placetype":"venue"
},
  "geometry": {"coordinates":[-81.629245,26.572789],"type":"Point"}
}