{
  "type": "Feature",
  "properties": {
    "iso:country":"US",
    "sg:address":"17116 Hanna Rd",
    "sg:city":"Lutz",
    "sg:classifiers":[
        {
            "category":"Wholesale",
            "subcategory":"Machinery & Supplies",
            "type":"Manufacturing & Wholesale Goods"
        }
    ],
    "sg:phone":"+1 813 949 1330",
    "sg:postcode":"33549",
    "sg:province":"FL",
    "sg:tags":[
        "equipment",
        "industrial"
    ],
    "wof:name":"Malphur Pressure Cleaning",
    "wof:placetype":"venue"
},
  "geometry": {"coordinates":[-82.442982,28.117679],"type":"Point"}
}