{
  "type": "Feature",
  "properties": {
    "iso:country":"US",
    "sg:address":"466 2nd St",
    "sg:city":"Cedar Key",
    "sg:classifiers":[
        {
            "category":"Education",
            "subcategory":"Library",
            "type":"Public Place"
        }
    ],
    "sg:phone":"+1 352 543 0610",
    "sg:postcode":"32625",
    "sg:province":"FL",
    "wof:name":"Cedear Key Library",
    "wof:placetype":"venue"
},
  "geometry": {"coordinates":[-83.03194999999999,29.136755],"type":"Point"}
}