{
  "type": "Feature",
  "properties": {
    "iso:country":"US",
    "sg:address":"1615 NE 163rd St",
    "sg:city":"North Miami Beach",
    "sg:classifiers":[
        {
            "category":"Personal",
            "subcategory":"Beauty Salon",
            "type":"Services"
        }
    ],
    "sg:phone":"+1 305 956 2777",
    "sg:postcode":"33162",
    "sg:province":"FL",
    "sg:tags":[
        "hair"
    ],
    "wof:name":"Prima Dominican Hair & Beauty Salon",
    "wof:placetype":"venue"
},
  "geometry": {"coordinates":[-80.16749,25.925873],"type":"Point"}
}