{
  "type": "Feature",
  "properties": {
    "addr:full":"720 Portia St N Nokomis FL 34275",
    "addr:housenumber":"720",
    "addr:postcode":"34275",
    "addr:street":"Portia St N",
    "iso:country":"US",
    "sg:address":"720 Portia St N",
    "sg:city":"Nokomis",
    "sg:classifiers":[
        {
            "category":"Building & Trades",
            "subcategory":"Construction",
            "type":"Services"
        }
    ],
    "sg:phone":"+1 941 346 3395",
    "sg:postcode":"34275",
    "sg:province":"FL",
    "sg:tags":[
        "contractor"
    ],
    "wof:name":"Rooflines South Inc",
    "wof:placetype":"venue"
},
  "geometry": {"coordinates":[-82.436577,27.132269],"type":"Point"}
}