{
  "type": "Feature",
  "properties": {
    "iso:country":"US",
    "sg:address":"1251 Jupiter Park Dr",
    "sg:city":"Jupiter",
    "sg:classifiers":[
        {
            "category":"Professional",
            "subcategory":"Advertising",
            "type":"Services"
        },
        {
            "category":"Professional",
            "subcategory":"Art Services",
            "type":"Services"
        },
        {
            "category":"Professional",
            "subcategory":"Printing & Photocopies",
            "type":"Services"
        }
    ],
    "sg:phone":"+1 561 743 5220",
    "sg:postcode":"33458",
    "sg:province":"FL",
    "sg:tags":[
        "graphic",
        "form",
        "services-commercial",
        "printers-business",
        "designer",
        "print"
    ],
    "sg:website":"http://www.marlingraphics.com",
    "wof:name":"Marlin Graphics",
    "wof:placetype":"venue"
},
  "geometry": {"coordinates":[-80.145526,26.921835],"type":"Point"}
}