{
  "type": "Feature",
  "properties": {
    "addr:full":"14261 SW 119th Ave Miami FL 33186",
    "addr:housenumber":"14261",
    "addr:postcode":"33186",
    "addr:street":"Sw 119Th Ave",
    "iso:country":"US",
    "sg:address":"14261 SW 119th Ave",
    "sg:city":"Miami",
    "sg:classifiers":[
        {
            "category":"Personal",
            "type":"Services"
        }
    ],
    "sg:phone":"+1 305 234 4555",
    "sg:postcode":"33186",
    "sg:province":"FL",
    "sg:tags":[
        "party",
        "planning",
        "event"
    ],
    "wof:name":"A Bounce Mouse Prod",
    "wof:placetype":"venue"
},
  "geometry": {"coordinates":[-80.386703,25.636],"type":"Point"}
}