{
  "type": "Feature",
  "properties": {
    "addr:full":"446 N Wabash Ave Lakeland FL 33815",
    "addr:housenumber":"446",
    "addr:postcode":"33815",
    "addr:street":"N Wabash Ave",
    "iso:country":"US",
    "sg:address":"446 N Wabash Ave",
    "sg:city":"Lakeland",
    "sg:classifiers":[
        {
            "category":"Organizations",
            "subcategory":"Religious Organization",
            "type":"Services"
        }
    ],
    "sg:phone":"+1 863 682 6428",
    "sg:postcode":"33815",
    "sg:province":"FL",
    "sg:tags":[
        "church"
    ],
    "wof:name":"Full Gospel Chr-God In Chrst",
    "wof:placetype":"venue"
},
  "geometry": {"coordinates":[-81.990261,28.047665],"type":"Point"}
}