{
  "type": "Feature",
  "properties": {
    "iso:country":"US",
    "sg:address":"1050 NW 52nd St",
    "sg:city":"Fort Lauderdale",
    "sg:classifiers":[
        {
            "category":"Airport",
            "type":"Transportation"
        }
    ],
    "sg:phone":"+1 954 772 5189",
    "sg:postcode":"33309",
    "sg:province":"FL",
    "sg:tags":[
        "interior",
        "executive",
        "design",
        "provides",
        "for"
    ],
    "wof:name":"Flex Aircraft Interiors Inc",
    "wof:placetype":"venue"
},
  "geometry": {"coordinates":[-80.15897099999999,26.191089],"type":"Point"}
}