{
  "type": "Feature",
  "properties": {
    "addr:full":"3725 10th Ct Vero Beach FL 32960",
    "addr:housenumber":"3725",
    "addr:postcode":"32960",
    "addr:street":"10Th Ct",
    "iso:country":"US",
    "sg:address":"3725 10th Ct",
    "sg:city":"Vero Beach",
    "sg:classifiers":[
        {
            "category":"Health Services",
            "subcategory":"Clinic",
            "type":"Services"
        }
    ],
    "sg:phone":"+1 772 569 2730",
    "sg:postcode":"32960",
    "sg:province":"FL",
    "sg:tags":[
        "home"
    ],
    "wof:name":"Interim Healthcare",
    "wof:placetype":"venue"
},
  "geometry": {"coordinates":[-80.396788,27.66056],"type":"Point"}
}