{
  "type": "Feature",
  "properties": {
    "addr:full":"1975 Rockledge Dr Rockledge FL 32955",
    "addr:housenumber":"1975",
    "addr:postcode":"32955",
    "addr:street":"Rockledge Dr",
    "iso:country":"US",
    "sg:address":"1975 Rockledge Dr",
    "sg:city":"Rockledge",
    "sg:classifiers":[
        {
            "category":"Wholesale",
            "subcategory":"Computers",
            "type":"Manufacturing & Wholesale Goods"
        }
    ],
    "sg:phone":"+1 321 638 8948",
    "sg:postcode":"32955",
    "sg:province":"FL",
    "sg:tags":[
        "peripheral",
        "software"
    ],
    "wof:name":"Select Electronics Corporation",
    "wof:placetype":"venue"
},
  "geometry": {"coordinates":[-80.701229,28.302232],"type":"Point"}
}