{
  "type": "Feature",
  "properties": {
    "iso:country":"US",
    "sg:address":"680 Yucca Rd",
    "sg:city":"Naples",
    "sg:classifiers":[
        {
            "category":"Museum",
            "type":"Entertainment"
        }
    ],
    "sg:phone":"+1 239 261 2637",
    "sg:postcode":"34102",
    "sg:province":"FL",
    "sg:tags":[
        "gallery"
    ],
    "wof:name":"Harmon-Meek Gallery",
    "wof:placetype":"venue"
},
  "geometry": {"coordinates":[-81.803297,26.164087],"type":"Point"}
}