{
  "type": "Feature",
  "properties": {
    "addr:full":"6634 Brookridge Trl Lakeland FL 33810",
    "addr:housenumber":"6634",
    "addr:postcode":"33810",
    "addr:street":"Brookridge Trl",
    "iso:country":"US",
    "sg:address":"6634 Brookridge Trl",
    "sg:city":"Lakeland",
    "sg:classifiers":[
        {
            "category":"Building & Trades",
            "subcategory":"Landscaping Services",
            "type":"Services"
        }
    ],
    "sg:phone":"+1 863 815 7213",
    "sg:postcode":"33810",
    "sg:province":"FL",
    "sg:tags":[
        "landscape",
        "contractor"
    ],
    "wof:name":"Frank's Landscaping",
    "wof:placetype":"venue"
},
  "geometry": {"coordinates":[-82.05444,28.128511],"type":"Point"}
}