{
  "type": "Feature",
  "properties": {
    "addr:full":"529 Atlantic Blvd Atlantic Beach FL 32233",
    "addr:housenumber":"529",
    "addr:postcode":"32233",
    "addr:street":"Atlantic Blvd",
    "iso:country":"US",
    "sg:address":"529 Atlantic Blvd",
    "sg:city":"Atlantic Beach",
    "sg:classifiers":[
        {
            "category":"Real Estate",
            "subcategory":"Real Estate Agent",
            "type":"Services"
        }
    ],
    "sg:phone":"+1 904 247 4442",
    "sg:postcode":"32233",
    "sg:province":"FL",
    "wof:name":"Assist To Sell Buyers & Seller",
    "wof:placetype":"venue"
},
  "geometry": {"coordinates":[-81.402626,30.32467],"type":"Point"}
}