{
  "type": "Feature",
  "properties": {
    "iso:country":"US",
    "sg:address":"1037 E Main St",
    "sg:city":"Lakeland",
    "sg:classifiers":[
        {
            "category":"Restaurant",
            "type":"Food & Drink"
        }
    ],
    "sg:phone":"+1 863 682 0909",
    "sg:postcode":"33801",
    "sg:province":"FL",
    "wof:name":"Live Oak Restaurant",
    "wof:placetype":"venue"
},
  "geometry": {"coordinates":[-81.944272,28.044084],"type":"Point"}
}