{
  "type": "Feature",
  "properties": {
    "iso:country":"US",
    "sg:address":"2526 SE 16th Pl",
    "sg:city":"Cape Coral",
    "sg:classifiers":[
        {
            "category":"Restaurant",
            "type":"Food & Drink"
        }
    ],
    "sg:phone":"+1 239 275 8430",
    "sg:postcode":"33904",
    "sg:province":"FL",
    "wof:name":"Teledine Inc",
    "wof:placetype":"venue"
},
  "geometry": {"coordinates":[-81.939542,26.604924],"type":"Point"}
}