{
  "type": "Feature",
  "properties": {
    "iso:country":"US",
    "sg:address":"1225 45th St",
    "sg:city":"West Palm Beach",
    "sg:classifiers":[
        {
            "category":"Shopping",
            "subcategory":"Clothing, Apparel, & Fashions",
            "type":"Retail Goods"
        }
    ],
    "sg:phone":"+1 561 845 1946",
    "sg:postcode":"33407",
    "sg:province":"FL",
    "wof:name":"Jenny's Fashions",
    "wof:placetype":"venue"
},
  "geometry": {"coordinates":[-80.070973,26.753292],"type":"Point"}
}