{
  "type": "Feature",
  "properties": {
    "iso:country":"US",
    "sg:address":"7810 46th Ave N",
    "sg:city":"St Petersburg",
    "sg:classifiers":[
        {
            "category":"Education",
            "subcategory":"Dance Studio",
            "type":"Public Place"
        }
    ],
    "sg:phone":"+1 727 544 5995",
    "sg:postcode":"33709",
    "sg:province":"FL",
    "sg:tags":[
        "instruction",
        "dancing"
    ],
    "wof:name":"Jeanne Lynn Dance Studio Inc",
    "wof:placetype":"venue"
},
  "geometry": {"coordinates":[-82.745845,27.813597],"type":"Point"}
}