{
  "type": "Feature",
  "properties": {
    "iso:country":"US",
    "sg:address":"601 N Magnolia Ave",
    "sg:city":"Orlando",
    "sg:classifiers":[
        {
            "category":"Real Estate",
            "subcategory":"Architect",
            "type":"Services"
        }
    ],
    "sg:phone":"+1 407 648 7288",
    "sg:postcode":"32801",
    "sg:province":"FL",
    "sg:tags":[
        "architectural"
    ],
    "sg:website":"www.rbarchitects.com",
    "wof:name":"Rhodes & Brito Architects Inc",
    "wof:placetype":"venue"
},
  "geometry": {"coordinates":[-81.376846,28.552215],"type":"Point"}
}