{
  "type": "Feature",
  "properties": {
    "iso:country":"US",
    "sg:address":"455 Mansfield K",
    "sg:city":"Boca Raton",
    "sg:classifiers":[
        {
            "category":"Building & Trades",
            "subcategory":"Construction",
            "type":"Services"
        }
    ],
    "sg:phone":"+1 561 477 0518",
    "sg:postcode":"33434",
    "sg:province":"FL",
    "sg:tags":[
        "builder",
        "operative"
    ],
    "wof:name":"Vincent Anastasio Condo Svcs",
    "wof:placetype":"venue"
},
  "geometry": {"coordinates":[-80.17340299999999,26.393625],"type":"Point"}
}