{
  "type": "Feature",
  "properties": {
    "addr:full":"4397 Four Lakes Dr Melbourne FL 32940",
    "addr:housenumber":"4397",
    "addr:postcode":"32940",
    "addr:street":"Four Lakes Dr",
    "iso:country":"US",
    "sg:address":"4397 Four Lakes Dr",
    "sg:city":"Melbourne",
    "sg:classifiers":[
        {
            "category":"Building & Trades",
            "subcategory":"Landscaping Services",
            "type":"Services"
        }
    ],
    "sg:phone":"+1 321 259 8996",
    "sg:postcode":"32940",
    "sg:province":"FL",
    "wof:name":"Arbor Tech",
    "wof:placetype":"venue"
},
  "geometry": {"coordinates":[-80.70000899999999,28.192275],"type":"Point"}
}