{
  "type": "Feature",
  "properties": {
    "addr:full":"732 NE 79th St Miami FL 33138",
    "addr:housenumber":"732",
    "addr:postcode":"33138",
    "addr:street":"Ne 79Th St",
    "iso:country":"US",
    "sg:address":"732 NE 79th St",
    "sg:city":"Miami",
    "sg:classifiers":[
        {
            "category":"Retail",
            "subcategory":"Repair Shop",
            "type":"Services"
        }
    ],
    "sg:phone":"+1 305 758 3693",
    "sg:postcode":"33138",
    "sg:province":"FL",
    "sg:tags":[
        "reupholstery",
        "furniture"
    ],
    "wof:name":"Anchor Yatcat Upholstery",
    "wof:placetype":"venue"
},
  "geometry": {"coordinates":[-80.181602,25.847799],"type":"Point"}
}