{
  "type": "Feature",
  "properties": {
    "addr:full":"2250 W 60th St Hialeah FL 33016",
    "addr:housenumber":"2250",
    "addr:postcode":"33016",
    "addr:street":"W 60Th St",
    "iso:country":"US",
    "sg:address":"2250 W 60th St",
    "sg:city":"Hialeah",
    "sg:classifiers":[
        {
            "category":"Government",
            "subcategory":"Office",
            "type":"Public Place"
        }
    ],
    "sg:phone":"+1 305 824 5706",
    "sg:postcode":"33016",
    "sg:province":"FL",
    "sg:tags":[
        "village"
    ],
    "sg:website":"www.cityofhialeah.com",
    "wof:name":"Edgar J Hall Spec Population",
    "wof:placetype":"venue"
},
  "geometry": {"coordinates":[-80.32788600000001,25.876931],"type":"Point"}
}