{
  "type": "Feature",
  "properties": {
    "addr:full":"707 S Orange Blossom Trl Orlando FL 32805",
    "addr:housenumber":"707",
    "addr:postcode":"32805",
    "addr:street":"S Orange Blossom Trl",
    "iso:country":"US",
    "sg:address":"707 S Orange Blossom Trl",
    "sg:city":"Orlando",
    "sg:classifiers":[
        {
            "category":"Restaurant",
            "type":"Food & Drink"
        }
    ],
    "sg:phone":"+1 407 312 1028",
    "sg:postcode":"32805",
    "sg:province":"FL",
    "sg:tags":[
        "eating"
    ],
    "wof:name":"La Cafeteria Deloscuban",
    "wof:placetype":"venue"
},
  "geometry": {"coordinates":[-81.397077,28.533037],"type":"Point"}
}