{
  "type": "Feature",
  "properties": {
    "iso:country":"US",
    "sg:address":"9074 NW 121st St",
    "sg:city":"Hialeah",
    "sg:classifiers":[
        {
            "category":"Health Services",
            "subcategory":"Clinic",
            "type":"Services"
        }
    ],
    "sg:phone":"+1 305 698 1072",
    "sg:postcode":"33018",
    "sg:province":"FL",
    "wof:name":"Mir Medical Equipments Inc",
    "wof:placetype":"venue"
},
  "geometry": {"coordinates":[-80.34653,25.883247],"type":"Point"}
}