{
  "type": "Feature",
  "properties": {
    "iso:country":"US",
    "sg:address":"1705 E Mann Rd",
    "sg:city":"Bartow",
    "sg:classifiers":[
        {
            "category":"Manufacturing",
            "subcategory":"Food",
            "type":"Manufacturing & Wholesale Goods"
        },
        {
            "category":"Manufacturing",
            "subcategory":"Chemicals & Compounds",
            "type":"Manufacturing & Wholesale Goods"
        }
    ],
    "sg:phone":"+1 863 533 2498",
    "sg:postcode":"33830",
    "sg:province":"FL",
    "sg:tags":[
        "liquor",
        "industrial",
        "organic",
        "che",
        "mfg"
    ],
    "wof:name":"Bartow Ethanol Inc",
    "wof:placetype":"venue"
},
  "geometry": {"coordinates":[-81.828649,27.875019],"type":"Point"}
}