{
  "type": "Feature",
  "properties": {
    "iso:country":"US",
    "sg:address":"2998 Cypress St",
    "sg:city":"Naples",
    "sg:classifiers":[
        {
            "category":"Retail",
            "subcategory":"Repair Shop",
            "type":"Services"
        }
    ],
    "sg:phone":"+1 239 774 1467",
    "sg:postcode":"34112",
    "sg:province":"FL",
    "sg:tags":[
        "blacksmith"
    ],
    "wof:name":"John B Hall Corrective Svc",
    "wof:placetype":"venue"
},
  "geometry": {"coordinates":[-81.77162199999999,26.126459],"type":"Point"}
}