{
  "type": "Feature",
  "properties": {
    "iso:country":"US",
    "sg:address":"1001 Riverside Dr Ste 230",
    "sg:city":"Palmetto",
    "sg:classifiers":[
        {
            "category":"Personal",
            "subcategory":"Beauty Salon",
            "type":"Services"
        }
    ],
    "sg:phone":"+1 941 721 4013",
    "sg:postcode":"34221",
    "sg:province":"FL",
    "wof:name":"Interstate Industrial",
    "wof:placetype":"venue"
},
  "geometry": {"coordinates":[-82.57562299999999,27.512289],"type":"Point"}
}