{
  "type": "Feature",
  "properties": {
    "addr:full":"11505 SW 90th Ter Miami FL 33176",
    "addr:housenumber":"11505",
    "addr:postcode":"33176",
    "addr:street":"Sw 90Th Ter",
    "iso:country":"US",
    "sg:address":"11505 SW 90th Ter",
    "sg:city":"Miami",
    "sg:classifiers":[
        {
            "category":"Building & Trades",
            "subcategory":"Construction",
            "type":"Services"
        }
    ],
    "sg:phone":"+1 305 271 4042",
    "sg:postcode":"33176",
    "sg:province":"FL",
    "sg:tags":[
        "painter"
    ],
    "wof:name":"Larry's Custom Painting",
    "wof:placetype":"venue"
},
  "geometry": {"coordinates":[-80.382569,25.684182],"type":"Point"}
}