{
  "type": "Feature",
  "properties": {
    "iso:country":"US",
    "sg:address":"220 NW 23rd St",
    "sg:city":"Miami",
    "sg:classifiers":[
        {
            "category":"Real Estate",
            "subcategory":"Real Estate Operator",
            "type":"Services"
        }
    ],
    "sg:phone":"+1 305 538 8897",
    "sg:postcode":"33127",
    "sg:province":"FL",
    "sg:tags":[
        "apartment"
    ],
    "wof:name":"Shep Davis",
    "wof:placetype":"venue"
},
  "geometry": {"coordinates":[-80.199375,25.799454],"type":"Point"}
}