{
  "type": "Feature",
  "properties": {
    "iso:country":"US",
    "sg:address":"529 N Magnolia Ave",
    "sg:city":"Orlando",
    "sg:classifiers":[
        {
            "category":"Professional",
            "subcategory":"Lawyer & Legal Services",
            "type":"Services"
        }
    ],
    "sg:phone":"+1 407 228 2223",
    "sg:postcode":"32801",
    "sg:province":"FL",
    "sg:tags":[
        "attorney"
    ],
    "wof:name":"Il Sun We Law Office",
    "wof:placetype":"venue"
},
  "geometry": {"coordinates":[-81.37674800000001,28.550505],"type":"Point"}
}