{
  "type": "Feature",
  "properties": {
    "iso:country":"US",
    "sg:address":"12650 NW Hwy 19",
    "sg:city":"Chiefland",
    "sg:classifiers":[
        {
            "category":"Freight",
            "type":"Transportation"
        }
    ],
    "sg:phone":"+1 352 493 0705",
    "sg:postcode":"32626",
    "sg:province":"FL",
    "sg:tags":[
        "mobile",
        "home"
    ],
    "wof:name":"Hall Brothers Mobile Home Twng",
    "wof:placetype":"venue"
},
  "geometry": {"coordinates":[-82.87747899999999,29.51352],"type":"Point"}
}