{
  "type": "Feature",
  "properties": {
    "iso:country":"US",
    "sg:address":"4960 SW 72nd Ave",
    "sg:city":"Miami",
    "sg:classifiers":[
        {
            "category":"Professional",
            "subcategory":"Accounting & Tax Preparation",
            "type":"Services"
        }
    ],
    "sg:phone":"+1 305 669 7999",
    "sg:postcode":"33155",
    "sg:province":"FL",
    "sg:tags":[
        "accountant"
    ],
    "wof:name":"Ferro Holman & Co",
    "wof:placetype":"venue"
},
  "geometry": {"coordinates":[-80.310723,25.723986],"type":"Point"}
}