{
  "type": "Feature",
  "properties": {
    "iso:country":"US",
    "sg:address":"197 2nd Ave N",
    "sg:city":"St Petersburg",
    "sg:classifiers":[
        {
            "category":"Restaurant",
            "type":"Food & Drink"
        }
    ],
    "sg:phone":"+1 727 894 5700",
    "sg:postcode":"33701",
    "sg:province":"FL",
    "wof:name":"Grand Grill",
    "wof:placetype":"venue"
},
  "geometry": {"coordinates":[-82.634125,27.773614],"type":"Point"}
}