{
  "type": "Feature",
  "properties": {
    "addr:full":"26536 W Dixie Hwy Homestead FL 33032",
    "addr:housenumber":"26536",
    "addr:postcode":"33032",
    "addr:street":"W Dixie Hwy",
    "iso:country":"US",
    "sg:address":"26536 W Dixie Hwy",
    "sg:city":"Homestead",
    "sg:classifiers":[
        {
            "category":"Home & Garden",
            "subcategory":"Garden Supply",
            "type":"Retail Goods"
        }
    ],
    "sg:phone":"+1 305 258 3191",
    "sg:postcode":"33032",
    "sg:province":"FL",
    "sg:tags":[
        "nurseryman"
    ],
    "wof:name":"Cimago's Nursery Inc",
    "wof:placetype":"venue"
},
  "geometry": {"coordinates":[-80.42775399999999,25.519584],"type":"Point"}
}