{
  "type": "Feature",
  "properties": {
    "addr:full":"117 Cam del Rio Port St Lucie FL 34952",
    "addr:housenumber":"117",
    "addr:postcode":"34952",
    "addr:street":"Cam Del Rio;St",
    "iso:country":"US",
    "sg:address":"117 Cam del Rio",
    "sg:city":"Port St Lucie",
    "sg:classifiers":[
        {
            "category":"Professional",
            "subcategory":"Accounting & Tax Preparation",
            "type":"Services"
        }
    ],
    "sg:phone":"+1 772 340 3335",
    "sg:postcode":"34952",
    "sg:province":"FL",
    "sg:tags":[
        "consultant"
    ],
    "wof:name":"Southern Property Conslnt Inc",
    "wof:placetype":"venue"
},
  "geometry": {"coordinates":[-80.32130600000001,27.317893],"type":"Point"}
}