{
  "type": "Feature",
  "properties": {
    "iso:country":"US",
    "sg:address":"489 John Knox Rd",
    "sg:city":"Tallahassee",
    "sg:classifiers":[
        {
            "category":"Real Estate",
            "subcategory":"Surveying",
            "type":"Services"
        }
    ],
    "sg:phone":"+1 850 385 1036",
    "sg:postcode":"32303",
    "sg:province":"FL",
    "sg:tags":[
        "surveyor"
    ],
    "wof:name":"A D Platt & Assoc Inc",
    "wof:placetype":"venue"
},
  "geometry": {"coordinates":[-84.28632500000001,30.474409],"type":"Point"}
}