{
  "type": "Feature",
  "properties": {
    "iso:country":"US",
    "sg:address":"2477 J and C Blvd",
    "sg:city":"Naples",
    "sg:classifiers":[
        {
            "category":"Insurance",
            "subcategory":"Insurance Agent",
            "type":"Services"
        }
    ],
    "sg:phone":"+1 239 596 8703",
    "sg:postcode":"34109",
    "sg:province":"FL",
    "wof:name":"Colonial Supplemental Ins",
    "wof:placetype":"venue"
},
  "geometry": {"coordinates":[-81.77698700000001,26.223883],"type":"Point"}
}