{
  "type": "Feature",
  "properties": {
    "iso:country":"US",
    "sg:address":"14700 Front Beach Rd",
    "sg:city":"Panama City Bch",
    "sg:classifiers":[
        {
            "category":"Building & Trades",
            "subcategory":"Construction",
            "type":"Services"
        }
    ],
    "sg:phone":"+1 850 249 4711",
    "sg:postcode":"32413",
    "sg:province":"FL",
    "sg:tags":[
        "general",
        "contractor"
    ],
    "wof:name":"Emerald Beach Resort",
    "wof:placetype":"venue"
},
  "geometry": {"coordinates":[-85.859606,30.206605],"type":"Point"}
}