{
  "type": "Feature",
  "properties": {
    "iso:country":"US",
    "sg:address":"5026 Trenton St",
    "sg:city":"Tampa",
    "sg:classifiers":[
        {
            "category":"Building & Trades",
            "subcategory":"Construction",
            "type":"Services"
        }
    ],
    "sg:phone":"+1 813 643 7663",
    "sg:postcode":"33619",
    "sg:province":"FL",
    "sg:tags":[
        "roofing",
        "contractor"
    ],
    "wof:name":"Roof Pro Of Tampa Bay Inc",
    "wof:placetype":"venue"
},
  "geometry": {"coordinates":[-82.398004,27.913128],"type":"Point"}
}