{
  "type": "Feature",
  "properties": {
    "addr:full":"1718 S Orange Ave Orlando FL 32806",
    "addr:housenumber":"1718",
    "addr:postcode":"32806",
    "addr:street":"S Orange Ave",
    "iso:country":"US",
    "sg:address":"1718 S Orange Ave",
    "sg:city":"Orlando",
    "sg:classifiers":[
        {
            "category":"Health Services",
            "subcategory":"Doctor",
            "type":"Services"
        }
    ],
    "sg:phone":"+1 407 841 0822",
    "sg:postcode":"32806",
    "sg:province":"FL",
    "sg:tags":[
        "physician",
        "surgeon",
        "radiology",
        "surgeons"
    ],
    "wof:name":"Curry, Susan L, Md - Womens Center For Radiology",
    "wof:placetype":"venue"
},
  "geometry": {"coordinates":[-81.376413,28.522203],"type":"Point"}
}