{
  "type": "Feature",
  "properties": {
    "addr:full":"10844 Beckum Rd Dade City FL 33525",
    "addr:housenumber":"10844",
    "addr:postcode":"33525",
    "addr:street":"Beckum Rd",
    "iso:country":"US",
    "sg:address":"10844 Beckum Rd",
    "sg:city":"Dade City",
    "sg:classifiers":[
        {
            "category":"Manufacturing",
            "subcategory":"Metals",
            "type":"Manufacturing & Wholesale Goods"
        }
    ],
    "sg:phone":"+1 352 567 6706",
    "sg:postcode":"33525",
    "sg:province":"FL",
    "sg:tags":[
        "fabrication",
        "structural"
    ],
    "wof:name":"Metal Creations By Ziggy",
    "wof:placetype":"venue"
},
  "geometry": {"coordinates":[-82.15881299999999,28.312426],"type":"Point"}
}