{
  "type": "Feature",
  "properties": {
    "iso:country":"US",
    "sg:address":"10750 NW 23rd Ave",
    "sg:city":"Miami",
    "sg:classifiers":[
        {
            "category":"Retail",
            "subcategory":"Auto Repair",
            "type":"Services"
        }
    ],
    "sg:phone":"+1 305 513 4833",
    "sg:postcode":"33167",
    "sg:province":"FL",
    "sg:tags":[
        "body",
        "shop"
    ],
    "wof:name":"Imperio Auto Repair",
    "wof:placetype":"venue"
},
  "geometry": {"coordinates":[-80.237105,25.872803],"type":"Point"}
}