{
  "type": "Feature",
  "properties": {
    "iso:country":"US",
    "sg:address":"1570 Nottingham Dr",
    "sg:city":"Naples",
    "sg:classifiers":[
        {
            "category":"Real Estate",
            "subcategory":"Real Estate Agent",
            "type":"Services"
        }
    ],
    "sg:phone":"+1 239 597 9018",
    "sg:postcode":"34109",
    "sg:province":"FL",
    "wof:name":"Glenn C Woodrich Appraiser",
    "wof:placetype":"venue"
},
  "geometry": {"coordinates":[-81.784954,26.258512],"type":"Point"}
}