{
  "type": "Feature",
  "properties": {
    "iso:country":"US",
    "sg:address":"4404 Thicket Ridge Ln",
    "sg:city":"Jacksonville",
    "sg:classifiers":[
        {
            "category":"Professional",
            "subcategory":"Management & Consulting",
            "type":"Services"
        }
    ],
    "sg:phone":"+1 904 886 4285",
    "sg:postcode":"32258",
    "sg:province":"FL",
    "sg:tags":[
        "personnel",
        "consultant"
    ],
    "wof:name":"Carroll Permanent Med Pro",
    "wof:placetype":"venue"
},
  "geometry": {"coordinates":[-81.591701,30.138329],"type":"Point"}
}