{
  "type": "Feature",
  "properties": {
    "addr:full":"1890 S Suncoast Blvd Homosassa FL 34448",
    "addr:housenumber":"1890",
    "addr:postcode":"34448",
    "addr:street":"S Suncoast Blvd",
    "iso:country":"US",
    "sg:address":"1890 S Suncoast Blvd",
    "sg:city":"Homosassa",
    "sg:classifiers":[
        {
            "category":"Building & Trades",
            "subcategory":"Landscaping Services",
            "type":"Services"
        }
    ],
    "sg:phone":"+1 352 563 2313",
    "sg:postcode":"34448",
    "sg:province":"FL",
    "wof:name":"Helens Nursery Inc",
    "wof:placetype":"venue"
},
  "geometry": {"coordinates":[-82.579679,28.843599],"type":"Point"}
}