{
  "type": "Feature",
  "properties": {
    "iso:country":"US",
    "sg:address":"400 Highpoint Dr",
    "sg:city":"Cocoa",
    "sg:classifiers":[
        {
            "category":"Professional",
            "subcategory":"Engineering",
            "type":"Services"
        },
        {
            "category":"Government",
            "subcategory":"Office",
            "type":"Public Place"
        }
    ],
    "sg:phone":"+1 321 453 7655",
    "sg:postcode":"32926",
    "sg:province":"FL",
    "sg:tags":[
        "federal",
        "engineer"
    ],
    "wof:name":"US Army Corps Of Engineers",
    "wof:placetype":"venue"
},
  "geometry": {"coordinates":[-80.75135299999999,28.402843],"type":"Point"}
}