{
  "type": "Feature",
  "properties": {
    "addr:full":"4499 Weston Rd Fort Lauderdale FL 33331",
    "addr:housenumber":"4499",
    "addr:postcode":"33331",
    "addr:street":"Weston Rd",
    "iso:country":"US",
    "sg:address":"4499 Weston Rd",
    "sg:city":"Fort Lauderdale",
    "sg:classifiers":[
        {
            "category":"Restaurant",
            "type":"Food & Drink"
        }
    ],
    "sg:menulink":"http://www.allmenus.com/fl/davie/12340-bonefish-grill/menu/",
    "sg:phone":"+1 954 389 9273",
    "sg:postcode":"33331",
    "sg:province":"FL",
    "sg:tags":[
        "seafood",
        "american"
    ],
    "wof:name":"Bonefish Grill",
    "wof:placetype":"venue"
},
  "geometry": {"coordinates":[-80.36226600000001,26.062644],"type":"Point"}
}