{
  "type": "Feature",
  "properties": {
    "addr:full":"461 Greynolds Cir Lake Worth FL 33462",
    "addr:housenumber":"461",
    "addr:postcode":"33462",
    "addr:street":"Greynolds Cir",
    "iso:country":"US",
    "sg:address":"461 Greynolds Cir",
    "sg:city":"Lake Worth",
    "sg:classifiers":[
        {
            "category":"Shopping",
            "subcategory":"Shoes",
            "type":"Retail Goods"
        }
    ],
    "sg:phone":"+1 561 585 8773",
    "sg:postcode":"33462",
    "sg:province":"FL",
    "wof:name":"Mm Shoe Shoe Company",
    "wof:placetype":"venue"
},
  "geometry": {"coordinates":[-80.054959,26.576799],"type":"Point"}
}