{
  "type": "Feature",
  "properties": {
    "addr:full":"5680 Halifax Ave Fort Myers FL 33912",
    "addr:housenumber":"5680",
    "addr:postcode":"33912",
    "addr:street":"Halifax Ave",
    "iso:country":"US",
    "sg:address":"5680 Halifax Ave",
    "sg:city":"Fort Myers",
    "sg:classifiers":[
        {
            "category":"Building & Trades",
            "subcategory":"Construction",
            "type":"Services"
        }
    ],
    "sg:phone":"+1 239 267 8453",
    "sg:postcode":"33912",
    "sg:province":"FL",
    "sg:tags":[
        "tile",
        "dealer"
    ],
    "wof:name":"Ciano's Granite & Marble",
    "wof:placetype":"venue"
},
  "geometry": {"coordinates":[-81.857204,26.53096],"type":"Point"}
}