{
  "type": "Feature",
  "properties": {
    "iso:country":"US",
    "sg:address":"1155 NE 62nd Ave",
    "sg:city":"Okeechobee",
    "sg:classifiers":[
        {
            "category":"Utilities",
            "subcategory":"Mobile Phone",
            "type":"Services"
        }
    ],
    "sg:phone":"+1 863 467 9930",
    "sg:postcode":"34974",
    "sg:province":"FL",
    "sg:tags":[
        "local",
        "trucking"
    ],
    "wof:name":"Koebernik Trucking",
    "wof:placetype":"venue"
},
  "geometry": {"coordinates":[-80.762399,27.254176],"type":"Point"}
}