{
  "type": "Feature",
  "properties": {
    "addr:full":"13 Cherry Laurel Ct Winter Springs FL 32708",
    "addr:housenumber":"13",
    "addr:postcode":"32708",
    "addr:street":"Cherry Laurel Ct",
    "iso:country":"US",
    "sg:address":"13 Cherry Laurel Ct",
    "sg:city":"Winter Springs",
    "sg:classifiers":[
        {
            "category":"Professional",
            "subcategory":"Business Services",
            "type":"Services"
        }
    ],
    "sg:phone":"+1 407 448 1324",
    "sg:postcode":"32708",
    "sg:province":"FL",
    "wof:name":"Task Enterprises Inc",
    "wof:placetype":"venue"
},
  "geometry": {"coordinates":[-81.322896,28.702078],"type":"Point"}
}