{
  "type": "Feature",
  "properties": {
    "addr:full":"548 Southside Dr Holt FL 32564",
    "addr:housenumber":"548",
    "addr:postcode":"32564",
    "addr:street":"Southside Dr",
    "iso:country":"US",
    "sg:address":"548 Southside Dr",
    "sg:city":"Holt",
    "sg:classifiers":[
        {
            "category":"Personal",
            "subcategory":"Beauty Salon",
            "type":"Services"
        }
    ],
    "sg:phone":"+1 850 537 8842",
    "sg:postcode":"32564",
    "sg:province":"FL",
    "sg:tags":[
        "hair",
        "stylist"
    ],
    "wof:name":"Andrea Patten Hairdresser",
    "wof:placetype":"venue"
},
  "geometry": {"coordinates":[-86.745811,30.713329],"type":"Point"}
}