{
  "type": "Feature",
  "properties": {
    "addr:full":"1716 Wind Willow Rd Belle Isle FL 32809",
    "addr:housenumber":"1716",
    "addr:postcode":"32809",
    "addr:street":"Wind Willow Rd;Isle",
    "iso:country":"US",
    "sg:address":"1716 Wind Willow Rd",
    "sg:city":"Belle Isle",
    "sg:classifiers":[
        {
            "category":"Building & Trades",
            "subcategory":"Construction",
            "type":"Services"
        }
    ],
    "sg:phone":"+1 407 855 7644",
    "sg:postcode":"32809",
    "sg:province":"FL",
    "sg:tags":[
        "painter"
    ],
    "wof:name":"Copley Painting",
    "wof:placetype":"venue"
},
  "geometry": {"coordinates":[-81.357055,28.455089],"type":"Point"}
}