{
  "type": "Feature",
  "properties": {
    "addr:full":"4660 Voyager Dr Pensacola FL 32514",
    "addr:housenumber":"4660",
    "addr:postcode":"32514",
    "addr:street":"Voyager Dr",
    "iso:country":"US",
    "sg:address":"4660 Voyager Dr",
    "sg:city":"Pensacola",
    "sg:classifiers":[
        {
            "category":"Wholesale",
            "subcategory":"Medical Equipment & Supplies",
            "type":"Manufacturing & Wholesale Goods"
        }
    ],
    "sg:phone":"+1 850 476 1078",
    "sg:postcode":"32514",
    "sg:province":"FL",
    "sg:tags":[
        "physician",
        "surgeon"
    ],
    "wof:name":"Van Arsdale Innovative Prods",
    "wof:placetype":"venue"
},
  "geometry": {"coordinates":[-87.174336,30.514993],"type":"Point"}
}