{
  "type": "Feature",
  "properties": {
    "iso:country":"US",
    "sg:address":"105 Candace Dr",
    "sg:city":"Maitland",
    "sg:classifiers":[
        {
            "category":"Wholesale",
            "subcategory":"Motor Vehicles",
            "type":"Manufacturing & Wholesale Goods"
        }
    ],
    "sg:phone":"+1 407 831 4660",
    "sg:postcode":"32751",
    "sg:province":"FL",
    "sg:tags":[
        "automobile",
        "truck",
        "broker"
    ],
    "wof:name":"Mast Enteprises",
    "wof:placetype":"venue"
},
  "geometry": {"coordinates":[-81.356003,28.644366],"type":"Point"}
}