{
  "type": "Feature",
  "properties": {
    "iso:country":"US",
    "sg:address":"1213 Garden St",
    "sg:city":"Titusville",
    "sg:classifiers":[
        {
            "category":"Retail",
            "subcategory":"Repair Shop",
            "type":"Services"
        }
    ],
    "sg:phone":"+1 321 264 9600",
    "sg:postcode":"32796",
    "sg:province":"FL",
    "sg:tags":[
        "scooter",
        "motorcycle",
        "motor"
    ],
    "wof:name":"Street Thunder American",
    "wof:placetype":"venue"
},
  "geometry": {"coordinates":[-80.81788899999999,28.615347],"type":"Point"}
}