{
  "type": "Feature",
  "properties": {
    "iso:country":"US",
    "sg:address":"17890 NE 31st Ct",
    "sg:city":"Aventura",
    "sg:classifiers":[
        {
            "category":"Banks & Credit Unions",
            "subcategory":"Investment Brokerage",
            "type":"Services"
        }
    ],
    "sg:phone":"+1 305 692 1799",
    "sg:postcode":"33160",
    "sg:province":"FL",
    "sg:tags":[
        "advisory",
        "financial"
    ],
    "wof:name":"PVN Capital",
    "wof:placetype":"venue"
},
  "geometry": {"coordinates":[-80.13803299999999,25.943651],"type":"Point"}
}