{
  "type": "Feature",
  "properties": {
    "addr:full":"101 S Congress Ave Delray Beach FL 33445",
    "addr:housenumber":"101",
    "addr:postcode":"33445",
    "addr:street":"S Congress Ave",
    "iso:country":"US",
    "sg:address":"101 S Congress Ave",
    "sg:city":"Delray Beach",
    "sg:classifiers":[
        {
            "category":"Manufacturing",
            "subcategory":"Retail Goods",
            "type":"Manufacturing & Wholesale Goods"
        },
        {
            "category":"Wholesale",
            "subcategory":"Home Furnishings",
            "type":"Manufacturing & Wholesale Goods"
        }
    ],
    "sg:phone":"+1 561 276 4343",
    "sg:postcode":"33445",
    "sg:province":"FL",
    "sg:tags":[
        "picture",
        "product",
        "frame",
        "mfg"
    ],
    "wof:name":"Wizard Arts Inc",
    "wof:placetype":"venue"
},
  "geometry": {"coordinates":[-80.093648,26.458738],"type":"Point"}
}