{
  "type": "Feature",
  "properties": {
    "iso:country":"US",
    "sg:address":"4430 NE 8th Ave",
    "sg:city":"Oakland Park",
    "sg:classifiers":[
        {
            "category":"Building & Trades",
            "subcategory":"Construction",
            "type":"Services"
        }
    ],
    "sg:phone":"+1 954 772 2666",
    "sg:postcode":"33334",
    "sg:province":"FL",
    "sg:tags":[
        "roof",
        "deck"
    ],
    "wof:name":"Don Works & Co",
    "wof:placetype":"venue"
},
  "geometry": {"coordinates":[-80.13620400000001,26.182606],"type":"Point"}
}