{
  "type": "Feature",
  "properties": {
    "addr:full":"406 Country Wood Cir Lake Mary FL 32746",
    "addr:housenumber":"406",
    "addr:postcode":"32746",
    "addr:street":"Country Wood Cir",
    "iso:country":"US",
    "sg:address":"406 Country Wood Cir",
    "sg:city":"Lake Mary",
    "sg:classifiers":[
        {
            "category":"Home & Garden",
            "subcategory":"Furniture",
            "type":"Retail Goods"
        }
    ],
    "sg:phone":"+1 407 302 8143",
    "sg:postcode":"32746",
    "sg:province":"FL",
    "wof:name":"Suncoast Trading Group In",
    "wof:placetype":"venue"
},
  "geometry": {"coordinates":[-81.333788,28.784383],"type":"Point"}
}