{
  "type": "Feature",
  "properties": {
    "iso:country":"US",
    "sg:address":"3800 Fowler St",
    "sg:city":"Fort Myers",
    "sg:classifiers":[
        {
            "category":"Professional",
            "type":"Services"
        }
    ],
    "sg:phone":"+1 239 275 9977",
    "sg:postcode":"33901",
    "sg:province":"FL",
    "sg:tags":[
        "establishment"
    ],
    "wof:name":"Installer's Express",
    "wof:placetype":"venue"
},
  "geometry": {"coordinates":[-81.861879,26.608063],"type":"Point"}
}