{
  "type": "Feature",
  "properties": {
    "addr:full":"210 SW 53rd Ct Miami FL 33134",
    "addr:housenumber":"210",
    "addr:postcode":"33134",
    "addr:street":"Sw 53Rd Ct",
    "iso:country":"US",
    "sg:address":"210 SW 53rd Ct",
    "sg:city":"Miami",
    "sg:classifiers":[
        {
            "category":"Banks & Credit Unions",
            "subcategory":"Financial Services",
            "type":"Services"
        }
    ],
    "sg:phone":"+1 305 447 0994",
    "sg:postcode":"33134",
    "sg:province":"FL",
    "sg:tags":[
        "investor"
    ],
    "wof:name":"Giordano Investments Inc",
    "wof:placetype":"venue"
},
  "geometry": {"coordinates":[-80.282377,25.769438],"type":"Point"}
}