{
  "type": "Feature",
  "properties": {
    "addr:full":"519 N Tyndall Pkwy Panama City FL 32404",
    "addr:housenumber":"519",
    "addr:postcode":"32404",
    "addr:street":"N Tyndall Pkwy",
    "iso:country":"US",
    "sg:address":"519 N Tyndall Pkwy",
    "sg:city":"Panama City",
    "sg:classifiers":[
        {
            "category":"Restaurant",
            "type":"Food & Drink"
        }
    ],
    "sg:menulink":"http://www.allmenus.com/fl/panama-city/82150-dominos-pizza/menu/",
    "sg:phone":"+1 850 763 5906",
    "sg:postcode":"32404",
    "sg:province":"FL",
    "sg:tags":[
        "american",
        "wing",
        "pizza"
    ],
    "wof:name":"Domino's Pizza",
    "wof:placetype":"venue"
},
  "geometry": {"coordinates":[-85.591211,30.156557],"type":"Point"}
}