{
  "type": "Feature",
  "properties": {
    "addr:full":"8600 Dalkeith Ln Hialeah FL 33016",
    "addr:postcode":"8600;33016",
    "addr:street":"Dalkeith Ln",
    "iso:country":"US",
    "sg:address":"8600 Dalkeith Ln",
    "sg:city":"Hialeah",
    "sg:classifiers":[
        {
            "category":"Professional",
            "subcategory":"Business Services",
            "type":"Services"
        }
    ],
    "sg:phone":"+1 305 827 4350",
    "sg:postcode":"33016",
    "sg:province":"FL",
    "sg:tags":[
        "sell",
        "wholesale",
        "network"
    ],
    "wof:name":"Axs2net LLC",
    "wof:placetype":"venue"
},
  "geometry": {"coordinates":[-80.340069,25.910834],"type":"Point"}
}