{
  "type": "Feature",
  "properties": {
    "iso:country":"US",
    "sg:address":"180 NW 183rd St",
    "sg:city":"Miami",
    "sg:classifiers":[
        {
            "category":"Food & Beverages",
            "subcategory":"Fruits & Vegetables",
            "type":"Retail Goods"
        },
        {
            "category":"Wholesale",
            "subcategory":"Fruits & Vegetables",
            "type":"Manufacturing & Wholesale Goods"
        }
    ],
    "sg:phone":"+1 305 999 9344",
    "sg:postcode":"33169",
    "sg:province":"FL",
    "sg:tags":[
        "produce"
    ],
    "wof:name":"B & L Produce",
    "wof:placetype":"venue"
},
  "geometry": {"coordinates":[-80.203791,25.942523],"type":"Point"}
}