{
  "type": "Feature",
  "properties": {
    "addr:full":"3225 Aviation Ave Miami FL 33133",
    "addr:housenumber":"3225",
    "addr:postcode":"33133",
    "addr:street":"Aviation Ave",
    "iso:country":"US",
    "sg:address":"3225 Aviation Ave",
    "sg:city":"Miami",
    "sg:classifiers":[
        {
            "category":"Professional",
            "subcategory":"Lawyer & Legal Services",
            "type":"Services"
        }
    ],
    "sg:phone":"+1 305 347 3721",
    "sg:postcode":"33133",
    "sg:province":"FL",
    "sg:tags":[
        "law"
    ],
    "wof:name":"Sands Leonard A Atty",
    "wof:placetype":"venue"
},
  "geometry": {"coordinates":[-80.23393299999999,25.733106],"type":"Point"}
}