{
  "type": "Feature",
  "properties": {
    "addr:full":"17118 Front Beach Rd Panama City Bch FL 32413",
    "addr:housenumber":"17118",
    "addr:postcode":"32413",
    "addr:street":"Front Beach Rd",
    "iso:country":"US",
    "sg:address":"17118 Front Beach Rd",
    "sg:city":"Panama City Bch",
    "sg:classifiers":[
        {
            "category":"Shopping",
            "subcategory":"Gifts & Souvenirs",
            "type":"Retail Goods"
        }
    ],
    "sg:phone":"+1 850 230 3992",
    "sg:postcode":"32413",
    "sg:province":"FL",
    "sg:tags":[
        "shop"
    ],
    "wof:name":"Dollar Outlet",
    "wof:placetype":"venue"
},
  "geometry": {"coordinates":[-85.909645,30.232298],"type":"Point"}
}