{
  "type": "Feature",
  "properties": {
    "iso:country":"US",
    "sg:address":"4020 S Semoran Blvd",
    "sg:city":"Orlando",
    "sg:classifiers":[
        {
            "category":"Health Services",
            "subcategory":"Doctor",
            "type":"Services"
        }
    ],
    "sg:phone":"+1 407 277 5787",
    "sg:postcode":"32822",
    "sg:province":"FL",
    "wof:name":"Advanced Dental Care",
    "wof:placetype":"venue"
},
  "geometry": {"coordinates":[-81.310322,28.503538],"type":"Point"}
}