{
  "type": "Feature",
  "properties": {
    "addr:full":"1889 SW 17th St Miami FL 33145",
    "addr:housenumber":"1889",
    "addr:postcode":"33145",
    "addr:street":"Sw 17Th St",
    "iso:country":"US",
    "sg:address":"1889 SW 17th St",
    "sg:city":"Miami",
    "sg:classifiers":[
        {
            "category":"Wholesale",
            "subcategory":"Hardware",
            "type":"Manufacturing & Wholesale Goods"
        }
    ],
    "sg:phone":"+1 305 250 9966",
    "sg:postcode":"33145",
    "sg:province":"FL",
    "sg:tags":[
        "refrigerating"
    ],
    "wof:name":"Hussmann Corp",
    "wof:placetype":"venue"
},
  "geometry": {"coordinates":[-80.224655,25.75678],"type":"Point"}
}