{
  "type": "Feature",
  "properties": {
    "addr:full":"2700 Starlite Ln Port Charlotte FL 33952",
    "addr:housenumber":"2700",
    "addr:postcode":"33952",
    "addr:street":"Starlite Ln",
    "iso:country":"US",
    "sg:address":"2700 Starlite Ln",
    "sg:city":"Port Charlotte",
    "sg:classifiers":[
        {
            "category":"Building & Trades",
            "subcategory":"Construction",
            "type":"Services"
        }
    ],
    "sg:phone":"+1 941 764 6235",
    "sg:postcode":"33952",
    "sg:province":"FL",
    "sg:tags":[
        "dry wall",
        "contractor"
    ],
    "wof:name":"John Palmer Drywall",
    "wof:placetype":"venue"
},
  "geometry": {"coordinates":[-82.08836100000001,26.986727],"type":"Point"}
}