{
  "type": "Feature",
  "properties": {
    "addr:full":"320 NW 171st St Miami FL 33169",
    "addr:housenumber":"320",
    "addr:postcode":"33169",
    "addr:street":"Nw 171St St",
    "iso:country":"US",
    "sg:address":"320 NW 171st St",
    "sg:city":"Miami",
    "sg:classifiers":[
        {
            "category":"Wholesale",
            "subcategory":"Sporting Goods",
            "type":"Manufacturing & Wholesale Goods"
        }
    ],
    "sg:phone":"+1 305 652 0016",
    "sg:postcode":"33169",
    "sg:province":"FL",
    "sg:tags":[
        "equipment",
        "swimming",
        "pool",
        "supply"
    ],
    "wof:name":"Dorphil Inc",
    "wof:placetype":"venue"
},
  "geometry": {"coordinates":[-80.20839100000001,25.931348],"type":"Point"}
}