{
  "type": "Feature",
  "properties": {
    "iso:country":"US",
    "sg:address":"1518 Sunnyhills Dr",
    "sg:city":"Brandon",
    "sg:classifiers":[
        {
            "category":"Building & Trades",
            "subcategory":"Construction",
            "type":"Services"
        }
    ],
    "sg:phone":"+1 813 361 5967",
    "sg:postcode":"33510",
    "sg:province":"FL",
    "sg:tags":[
        "house"
    ],
    "wof:name":"Ace Home RPS & Installation",
    "wof:placetype":"venue"
},
  "geometry": {"coordinates":[-82.313315,27.960139],"type":"Point"}
}