{
  "type": "Feature",
  "properties": {
    "iso:country":"US",
    "sg:address":"5663 Park Blvd",
    "sg:city":"Pinellas Park",
    "sg:classifiers":[
        {
            "category":"Building & Trades",
            "subcategory":"Cleaning & Sanitation",
            "type":"Services"
        }
    ],
    "sg:phone":"+1 813 915 2919",
    "sg:postcode":"33781",
    "sg:province":"FL",
    "sg:tags":[
        "janitor"
    ],
    "wof:name":"Proforce USA-Tampa",
    "wof:placetype":"venue"
},
  "geometry": {"coordinates":[-82.710849,27.839272],"type":"Point"}
}