{
  "type": "Feature",
  "properties": {
    "iso:country":"US",
    "sg:address":"1502 W 3rd St",
    "sg:city":"Sanford",
    "sg:classifiers":[
        {
            "category":"Organizations",
            "subcategory":"Religious Organization",
            "type":"Services"
        }
    ],
    "sg:phone":"+1 407 321 4302",
    "sg:postcode":"32771",
    "sg:province":"FL",
    "sg:tags":[
        "church"
    ],
    "wof:name":"Jehovah's Witnesses",
    "wof:placetype":"venue"
},
  "geometry": {"coordinates":[-81.283537,28.809876],"type":"Point"}
}