{
  "type": "Feature",
  "properties": {
    "addr:full":"12060 Miramar Pkwy Miramar FL 33025",
    "addr:housenumber":"12060",
    "addr:postcode":"33025",
    "addr:street":"Miramar Pkwy",
    "iso:country":"US",
    "sg:address":"12060 Miramar Pkwy",
    "sg:city":"Miramar",
    "sg:classifiers":[
        {
            "category":"Wholesale",
            "subcategory":"Hardware",
            "type":"Manufacturing & Wholesale Goods"
        }
    ],
    "sg:phone":"+1 954 392 7050",
    "sg:postcode":"33025",
    "sg:province":"FL",
    "sg:tags":[
        "rivet"
    ],
    "wof:name":"Adchem Rivits Florida",
    "wof:placetype":"venue"
},
  "geometry": {"coordinates":[-80.306149,25.978683],"type":"Point"}
}