{
  "type": "Feature",
  "properties": {
    "iso:country":"US",
    "sg:address":"1366 S Hillcrest Ave",
    "sg:city":"Clearwater",
    "sg:classifiers":[
        {
            "category":"Building & Trades",
            "subcategory":"Construction",
            "type":"Services"
        }
    ],
    "sg:phone":"+1 727 443 5822",
    "sg:postcode":"33756",
    "sg:province":"FL",
    "sg:tags":[
        "contractor",
        "carpenter",
        "carpentry"
    ],
    "wof:name":"Done Right Carpentry & Remodelling",
    "wof:placetype":"venue"
},
  "geometry": {"coordinates":[-82.780117,27.947377],"type":"Point"}
}