{
  "type": "Feature",
  "properties": {
    "addr:full":"11389 SW 40th St Miami FL 33165",
    "addr:housenumber":"11389",
    "addr:postcode":"33165",
    "addr:street":"Sw 40Th St",
    "iso:country":"US",
    "sg:address":"11389 SW 40th St",
    "sg:city":"Miami",
    "sg:classifiers":[
        {
            "category":"Personal",
            "subcategory":"Barber",
            "type":"Services"
        }
    ],
    "sg:phone":"+1 305 220 0505",
    "sg:postcode":"33165",
    "sg:province":"FL",
    "wof:name":"Barbers At Work",
    "wof:placetype":"venue"
},
  "geometry": {"coordinates":[-80.380129,25.7323],"type":"Point"}
}