{
  "type": "Feature",
  "properties": {
    "iso:country":"US",
    "sg:address":"1312 Morningside Dr",
    "sg:city":"Melbourne",
    "sg:classifiers":[
        {
            "category":"Home & Garden",
            "subcategory":"Garden Supply",
            "type":"Retail Goods"
        }
    ],
    "sg:phone":"+1 321 984 9404",
    "sg:postcode":"32901",
    "sg:province":"FL",
    "sg:tags":[
        "lawn",
        "mower"
    ],
    "wof:name":"Matt's Mobile Mechanic Svc",
    "wof:placetype":"venue"
},
  "geometry": {"coordinates":[-80.608574,28.087269],"type":"Point"}
}