{
  "type": "Feature",
  "properties": {
    "iso:country":"US",
    "sg:address":"4692 NW 183rd St",
    "sg:city":"Miami Gardens",
    "sg:classifiers":[
        {
            "category":"Shopping",
            "subcategory":"Department Store",
            "type":"Retail Goods"
        }
    ],
    "sg:phone":"+1 305 474 9831",
    "sg:postcode":"33055",
    "sg:province":"FL",
    "wof:name":"Top Buy",
    "wof:placetype":"venue"
},
  "geometry": {"coordinates":[-80.277295,25.939468],"type":"Point"}
}