{
  "type": "Feature",
  "properties": {
    "iso:country":"US",
    "sg:address":"3737 Thornwood Dr",
    "sg:city":"Tampa",
    "sg:classifiers":[
        {
            "category":"Shopping",
            "subcategory":"Catalog Store",
            "type":"Retail Goods"
        }
    ],
    "sg:phone":"+1 813 961 1816",
    "sg:postcode":"33618",
    "sg:province":"FL",
    "sg:tags":[
        "mail",
        "house"
    ],
    "wof:name":"Orcutt Enterprises Inc",
    "wof:placetype":"venue"
},
  "geometry": {"coordinates":[-82.504222,28.080782],"type":"Point"}
}