{
  "type": "Feature",
  "properties": {
    "addr:full":"4732 18th St Zephyrhills FL 33542",
    "addr:housenumber":"4732",
    "addr:postcode":"33542",
    "addr:street":"18Th St",
    "iso:country":"US",
    "sg:address":"4732 18th St",
    "sg:city":"Zephyrhills",
    "sg:classifiers":[
        {
            "category":"Building & Trades",
            "subcategory":"Construction",
            "type":"Services"
        }
    ],
    "sg:phone":"+1 813 783 2636",
    "sg:postcode":"33542",
    "sg:province":"FL",
    "sg:tags":[
        "contractor"
    ],
    "wof:name":"Ted Baer",
    "wof:placetype":"venue"
},
  "geometry": {"coordinates":[-82.173542,28.227444],"type":"Point"}
}