{
  "type": "Feature",
  "properties": {
    "addr:full":"107 S Main St Wildwood FL 34785",
    "addr:housenumber":"107",
    "addr:postcode":"34785",
    "addr:street":"S Main St",
    "iso:country":"US",
    "sg:address":"107 S Main St",
    "sg:city":"Wildwood",
    "sg:classifiers":[
        {
            "category":"Food & Beverages",
            "subcategory":"Specialty",
            "type":"Retail Goods"
        }
    ],
    "sg:phone":"+1 352 330 0112",
    "sg:postcode":"34785",
    "sg:province":"FL",
    "sg:tags":[
        "herb"
    ],
    "wof:name":"Raphael's Healing Herbs",
    "wof:placetype":"venue"
},
  "geometry": {"coordinates":[-82.04122700000001,28.862293],"type":"Point"}
}