{
  "type": "Feature",
  "properties": {
    "addr:full":"3229 Hypoluxo Rd Lantana FL 33462",
    "addr:housenumber":"3229",
    "addr:postcode":"33462",
    "addr:street":"Hypoluxo Rd",
    "iso:country":"US",
    "sg:address":"3229 Hypoluxo Rd",
    "sg:city":"Lantana",
    "sg:classifiers":[
        {
            "category":"Building & Trades",
            "subcategory":"Construction",
            "type":"Services"
        }
    ],
    "sg:phone":"+1 561 433 0870",
    "sg:postcode":"33462",
    "sg:province":"FL",
    "sg:tags":[
        "masonry",
        "contractor"
    ],
    "wof:name":"Duane Thomas Masonry Inc",
    "wof:placetype":"venue"
},
  "geometry": {"coordinates":[-80.094506,26.572],"type":"Point"}
}