{
  "type": "Feature",
  "properties": {
    "addr:full":"3850 S Econlockhatchee Trl Orlando FL 32829",
    "addr:housenumber":"3850",
    "addr:postcode":"32829",
    "addr:street":"S Econlockhatchee Trl",
    "iso:country":"US",
    "sg:address":"3850 S Econlockhatchee Trl",
    "sg:city":"Orlando",
    "sg:classifiers":[
        {
            "category":"Personal",
            "type":"Services"
        },
        {
            "category":"Sports & Exercise",
            "subcategory":"Gym",
            "type":"Entertainment"
        }
    ],
    "sg:phone":"+1 866 975 5781",
    "sg:postcode":"32829",
    "sg:province":"FL",
    "sg:tags":[
        "trainer",
        "consultant",
        "program",
        "physical",
        "fitness"
    ],
    "sg:website":"http://orlando.citysearch.com/profile/external/603955312/orlando_fl/jazzercise_orlando_magic_recreation_center.html?publisher=yellowpages&reference_id=1&placement=ypwebsitemip",
    "wof:name":"Jazzercise Orlando Magic Recreation Center",
    "wof:placetype":"venue"
},
  "geometry": {"coordinates":[-81.25520299999999,28.497752],"type":"Point"}
}