{
  "type": "Feature",
  "properties": {
    "addr:full":"1335 E Vine St Kissimmee FL 34744",
    "addr:housenumber":"1335",
    "addr:postcode":"34744",
    "addr:street":"E Vine St",
    "iso:country":"US",
    "sg:address":"1335 E Vine St",
    "sg:city":"Kissimmee",
    "sg:classifiers":[
        {
            "category":"Personal",
            "subcategory":"Beauty Salon",
            "type":"Services"
        }
    ],
    "sg:phone":"+1 407 933 1111",
    "sg:postcode":"34744",
    "sg:province":"FL",
    "wof:name":"Super Image",
    "wof:placetype":"venue"
},
  "geometry": {"coordinates":[-81.387162,28.304252],"type":"Point"}
}