{
  "type": "Feature",
  "properties": {
    "iso:country":"US",
    "sg:address":"518 27th St E",
    "sg:city":"Bradenton",
    "sg:classifiers":[
        {
            "category":"Building & Trades",
            "subcategory":"Plumbing",
            "type":"Services"
        }
    ],
    "sg:phone":"+1 941 748 1602",
    "sg:postcode":"34208",
    "sg:province":"FL",
    "sg:tags":[
        "plumbing",
        "contractor"
    ],
    "wof:name":"Bradenton Plumbing Inc",
    "wof:placetype":"venue"
},
  "geometry": {"coordinates":[-82.530417,27.493496],"type":"Point"}
}