{
  "type": "Feature",
  "properties": {
    "iso:country":"US",
    "sg:address":"1608 Heritage Dr",
    "sg:city":"Valrico",
    "sg:classifiers":[
        {
            "category":"Building & Trades",
            "subcategory":"Construction",
            "type":"Services"
        }
    ],
    "sg:phone":"+1 813 685 1771",
    "sg:postcode":"33594",
    "sg:province":"FL",
    "sg:tags":[
        "contractor"
    ],
    "wof:name":"Rl Ross Masonry Inc",
    "wof:placetype":"venue"
},
  "geometry": {"coordinates":[-82.24912500000001,27.96542],"type":"Point"}
}