{
  "type": "Feature",
  "properties": {
    "iso:country":"US",
    "sg:address":"17315 Rosa Lee Way",
    "sg:city":"Saint Petersburg",
    "sg:classifiers":[
        {
            "category":"Shopping",
            "subcategory":"Gifts & Souvenirs",
            "type":"Retail Goods"
        }
    ],
    "sg:phone":"+1 727 392 3244",
    "sg:postcode":"33708",
    "sg:province":"FL",
    "wof:name":"Baskets of Sweet Dreams",
    "wof:placetype":"venue"
},
  "geometry": {"coordinates":[-82.820291,27.82534],"type":"Point"}
}