{
  "type": "Feature",
  "properties": {
    "addr:full":"5729 Browntown Rd Graceville FL 32440",
    "addr:housenumber":"5729",
    "addr:postcode":"32440",
    "addr:street":"Browntown Rd",
    "iso:country":"US",
    "sg:address":"5729 Browntown Rd",
    "sg:city":"Graceville",
    "sg:classifiers":[
        {
            "category":"Place Of Worship",
            "subcategory":"Church",
            "type":"Public Place"
        },
        {
            "category":"Place Of Worship",
            "type":"Public Place"
        }
    ],
    "sg:phone":"+1 850 263 3344",
    "sg:postcode":"32440",
    "sg:province":"FL",
    "sg:tags":[
        "episcopal",
        "churches-african",
        "ame",
        "methodist"
    ],
    "wof:name":"Salem Ame Church",
    "wof:placetype":"venue"
},
  "geometry": {"coordinates":[-85.46864100000001,30.98212],"type":"Point"}
}