{
  "type": "Feature",
  "properties": {
    "iso:country":"US",
    "sg:address":"2800 S 14th St",
    "sg:city":"Fernandina Beach",
    "sg:classifiers":[
        {
            "category":"Organizations",
            "subcategory":"Religious Organization",
            "type":"Services"
        }
    ],
    "sg:phone":"+1 904 261 7370",
    "sg:postcode":"32034",
    "sg:province":"FL",
    "sg:tags":[
        "church"
    ],
    "wof:name":"Church Of Jesus Christ Of Lds",
    "wof:placetype":"venue"
},
  "geometry": {"coordinates":[-81.455011,30.628323],"type":"Point"}
}