{
  "type": "Feature",
  "properties": {
    "iso:country":"US",
    "sg:address":"2185 NW 27th Ave",
    "sg:city":"Miami",
    "sg:classifiers":[
        {
            "category":"Retail",
            "subcategory":"Auto Repair",
            "type":"Services"
        }
    ],
    "sg:phone":"+1 305 635 7906",
    "sg:postcode":"33142",
    "sg:province":"FL",
    "sg:tags":[
        "body",
        "shop",
        "painting",
        "repairing",
        "automobile"
    ],
    "wof:name":"Classic One Paint & Body Shop",
    "wof:placetype":"venue"
},
  "geometry": {"coordinates":[-80.23989899999999,25.796801],"type":"Point"}
}