{
  "type": "Feature",
  "properties": {
    "iso:country":"US",
    "sg:address":"96 Lake Arbor Dr",
    "sg:city":"Lake Worth",
    "sg:classifiers":[
        {
            "category":"Professional",
            "type":"Services"
        }
    ],
    "sg:phone":"+1 561 968 6725",
    "sg:postcode":"33461",
    "sg:province":"FL",
    "wof:name":"CCH Processing By Cynthia",
    "wof:placetype":"venue"
},
  "geometry": {"coordinates":[-80.08598000000001,26.635899],"type":"Point"}
}