{
  "type": "Feature",
  "properties": {
    "iso:country":"US",
    "sg:address":"4411 US Hwy 92",
    "sg:city":"Lakeland",
    "sg:classifiers":[
        {
            "category":"Freight",
            "type":"Transportation"
        },
        {
            "category":"Real Estate",
            "subcategory":"Real Estate Operator",
            "type":"Services"
        }
    ],
    "sg:phone":"+1 863 606 9458",
    "sg:postcode":"33801",
    "sg:province":"FL",
    "sg:tags":[
        "building",
        "storage",
        "nonresidential"
    ],
    "wof:name":"Guys Commercial Park & Self",
    "wof:placetype":"venue"
},
  "geometry": {"coordinates":[-81.868891,28.047868],"type":"Point"}
}