{
  "type": "Feature",
  "properties": {
    "addr:full":"595 NW 54th St Miami FL 33127",
    "addr:housenumber":"595",
    "addr:postcode":"33127",
    "addr:street":"Nw 54Th St",
    "iso:country":"US",
    "sg:address":"595 NW 54th St",
    "sg:city":"Miami",
    "sg:classifiers":[
        {
            "category":"Professional",
            "type":"Services"
        }
    ],
    "sg:phone":"+1 305 756 2680",
    "sg:postcode":"33127",
    "sg:province":"FL",
    "sg:tags":[
        "establishment"
    ],
    "wof:name":"Dan How Inc",
    "wof:placetype":"venue"
},
  "geometry": {"coordinates":[-80.203903,25.82514],"type":"Point"}
}