{
  "type": "Feature",
  "properties": {
    "iso:country":"US",
    "sg:address":"20 SW 27th Ave.",
    "sg:city":"Pompano Beach",
    "sg:classifiers":[
        {
            "category":"Professional",
            "subcategory":"Advertising",
            "type":"Services"
        }
    ],
    "sg:phone":"+1 213 408 0080",
    "sg:postcode":"33069",
    "sg:province":"FL",
    "sg:tags":[
        "domainacquisition",
        "leadgeneration",
        "advertising",
        "domainnames"
    ],
    "sg:website":"http://www.oversee.net",
    "wof:name":"OverSee",
    "wof:placetype":"venue"
},
  "geometry": {"coordinates":[-80.159244,26.22766],"type":"Point"}
}