{
  "type": "Feature",
  "properties": {
    "iso:country":"US",
    "sg:address":"819 SW 14th St",
    "sg:city":"Fort Lauderdale",
    "sg:classifiers":[
        {
            "category":"Travel",
            "subcategory":"Travel Agent",
            "type":"Entertainment"
        }
    ],
    "sg:phone":"+1 954 525 4441",
    "sg:postcode":"33315",
    "sg:province":"FL",
    "sg:tags":[
        "operator",
        "tour"
    ],
    "wof:name":"Keys Adventure Tours Inc",
    "wof:placetype":"venue"
},
  "geometry": {"coordinates":[-80.149612,26.104702],"type":"Point"}
}