{
  "type": "Feature",
  "properties": {
    "addr:full":"9729 Hammocks Blvd Miami FL 33196",
    "addr:housenumber":"9729",
    "addr:postcode":"33196",
    "addr:street":"Hammocks Blvd",
    "iso:country":"US",
    "sg:address":"9729 Hammocks Blvd",
    "sg:city":"Miami",
    "sg:classifiers":[
        {
            "category":"Building & Trades",
            "subcategory":"Construction",
            "type":"Services"
        }
    ],
    "sg:phone":"+1 305 265 8777",
    "sg:postcode":"33196",
    "sg:province":"FL",
    "sg:tags":[
        "floor",
        "laying",
        "contractor"
    ],
    "wof:name":"All Carpet Style Inc",
    "wof:placetype":"venue"
},
  "geometry": {"coordinates":[-80.441891,25.675622],"type":"Point"}
}