{
  "type": "Feature",
  "properties": {
    "iso:country":"US",
    "sg:address":"1334 NW 54th St",
    "sg:city":"Miami",
    "sg:classifiers":[
        {
            "category":"Building & Trades",
            "subcategory":"Construction",
            "type":"Services"
        }
    ],
    "sg:phone":"+1 305 759 1904",
    "sg:postcode":"33142",
    "sg:province":"FL",
    "sg:tags":[
        "welder"
    ],
    "wof:name":"Willie's Welding & Ornamental Shop",
    "wof:placetype":"venue"
},
  "geometry": {"coordinates":[-80.219025,25.824579],"type":"Point"}
}