{
  "type": "Feature",
  "properties": {
    "addr:full":"3319 NE 17th Ct Fort Lauderdale FL 33305",
    "addr:housenumber":"3319",
    "addr:postcode":"33305",
    "addr:street":"Ne 17Th Ct",
    "iso:country":"US",
    "sg:address":"3319 NE 17th Ct",
    "sg:city":"Fort Lauderdale",
    "sg:classifiers":[
        {
            "category":"Restaurant",
            "type":"Food & Drink"
        }
    ],
    "sg:phone":"+1 954 566 4449",
    "sg:postcode":"33305",
    "sg:province":"FL",
    "wof:name":"Sweetsop",
    "wof:placetype":"venue"
},
  "geometry": {"coordinates":[-80.10119,26.151403],"type":"Point"}
}