{
  "type": "Feature",
  "properties": {
    "addr:full":"2829 SW 4th Pl Fort Lauderdale FL 33312",
    "addr:housenumber":"2829",
    "addr:postcode":"33312",
    "addr:street":"Sw 4Th Pl",
    "iso:country":"US",
    "sg:address":"2829 SW 4th Pl",
    "sg:city":"Fort Lauderdale",
    "sg:classifiers":[
        {
            "category":"Shopping",
            "type":"Retail Goods"
        }
    ],
    "sg:phone":"+1 954 731 4210",
    "sg:postcode":"33312",
    "sg:province":"FL",
    "sg:tags":[
        "wedding",
        "supply"
    ],
    "wof:name":"A & S Productions",
    "wof:placetype":"venue"
},
  "geometry": {"coordinates":[-80.182265,26.115828],"type":"Point"}
}