{
  "type": "Feature",
  "properties": {
    "iso:country":"US",
    "sg:address":"960 NE 62nd St",
    "sg:city":"Fort Lauderdale",
    "sg:classifiers":[
        {
            "category":"Shopping",
            "subcategory":"Pharmacy",
            "type":"Retail Goods"
        }
    ],
    "sg:phone":"+1 954 771 6346",
    "sg:postcode":"33334",
    "sg:province":"FL",
    "sg:tags":[
        "drugstore"
    ],
    "wof:name":"Colonial Garden Pharmacy Inc",
    "wof:placetype":"venue"
},
  "geometry": {"coordinates":[-80.13319799999999,26.203596],"type":"Point"}
}