{
  "type": "Feature",
  "properties": {
    "addr:full":"2725 Hollywood Blvd Hollywood FL 33020",
    "addr:housenumber":"2725",
    "addr:postcode":"33020",
    "addr:street":"Hollywood Blvd",
    "iso:country":"US",
    "sg:address":"2725 Hollywood Blvd",
    "sg:city":"Hollywood",
    "sg:classifiers":[
        {
            "category":"Insurance",
            "subcategory":"Insurance Agent",
            "type":"Services"
        }
    ],
    "sg:phone":"+1 954 926 5900",
    "sg:postcode":"33020",
    "sg:province":"FL",
    "wof:name":"Allstate",
    "wof:placetype":"venue"
},
  "geometry": {"coordinates":[-80.162561,26.011148],"type":"Point"}
}