{
  "type": "Feature",
  "properties": {
    "iso:country":"US",
    "sg:address":"617 E Washington St",
    "sg:city":"Orlando",
    "sg:classifiers":[
        {
            "category":"Real Estate",
            "subcategory":"Developer",
            "type":"Services"
        }
    ],
    "sg:phone":"+1 407 420 9671",
    "sg:postcode":"32801",
    "sg:province":"FL",
    "wof:name":"J Lewless Holding LLC",
    "wof:placetype":"venue"
},
  "geometry": {"coordinates":[-81.368684,28.543718],"type":"Point"}
}