{
  "type": "Feature",
  "properties": {
    "iso:country":"US",
    "sg:address":"6645 SW 94th Ct",
    "sg:city":"Miami",
    "sg:classifiers":[
        {
            "category":"Professional",
            "subcategory":"Engineering",
            "type":"Services"
        }
    ],
    "sg:phone":"+1 305 596 0844",
    "sg:postcode":"33173",
    "sg:province":"FL",
    "sg:tags":[
        "consulting",
        "engineer"
    ],
    "wof:name":"Jorge Guillermo Valdes",
    "wof:placetype":"venue"
},
  "geometry": {"coordinates":[-80.347392,25.706762],"type":"Point"}
}