{
  "type": "Feature",
  "properties": {
    "addr:full":"39732 Meadowood Loop Zephyrhills FL 33542",
    "addr:housenumber":"39732",
    "addr:postcode":"33542",
    "addr:street":"Meadowood Loop",
    "iso:country":"US",
    "sg:address":"39732 Meadowood Loop",
    "sg:city":"Zephyrhills",
    "sg:classifiers":[
        {
            "category":"Retail",
            "subcategory":"Car Wash",
            "type":"Services"
        }
    ],
    "sg:phone":"+1 813 788 0406",
    "sg:postcode":"33542",
    "sg:province":"FL",
    "sg:tags":[
        "carwash"
    ],
    "wof:name":"Goldie",
    "wof:placetype":"venue"
},
  "geometry": {"coordinates":[-82.15737799999999,28.217065],"type":"Point"}
}