{
  "type": "Feature",
  "properties": {
    "addr:full":"412 E Ocean Ave Boynton Beach FL 33435",
    "addr:housenumber":"412",
    "addr:postcode":"33435",
    "addr:street":"E Ocean Ave",
    "iso:country":"US",
    "sg:address":"412 E Ocean Ave",
    "sg:city":"Boynton Beach",
    "sg:classifiers":[
        {
            "category":"Personal",
            "type":"Services"
        }
    ],
    "sg:phone":"+1 561 737 4377",
    "sg:postcode":"33435",
    "sg:province":"FL",
    "sg:tags":[
        "program",
        "physical",
        "exercise",
        "fitness"
    ],
    "wof:name":"Pilates Body",
    "wof:placetype":"venue"
},
  "geometry": {"coordinates":[-80.06020100000001,26.527012],"type":"Point"}
}