{
  "type": "Feature",
  "properties": {
    "iso:country":"US",
    "sg:address":"740 S Gulfview Blvd",
    "sg:city":"Clearwater",
    "sg:classifiers":[
        {
            "category":"Restaurant",
            "type":"Food & Drink"
        }
    ],
    "sg:phone":"+1 727 441 3924",
    "sg:postcode":"33767",
    "sg:province":"FL",
    "sg:tags":[
        "eating"
    ],
    "wof:name":"Island Breeze Cafe Grill Rest",
    "wof:placetype":"venue"
},
  "geometry": {"coordinates":[-82.823246,27.966171],"type":"Point"}
}