{
  "type": "Feature",
  "properties": {
    "iso:country":"US",
    "sg:address":"13251 Eastern Ave",
    "sg:city":"Palmetto",
    "sg:classifiers":[
        {
            "category":"Professional",
            "subcategory":"Employment Agencies",
            "type":"Services"
        }
    ],
    "sg:phone":"+1 941 722 0558",
    "sg:postcode":"34221",
    "sg:province":"FL",
    "sg:tags":[
        "contractor"
    ],
    "wof:name":"WSI Of The Southeast",
    "wof:placetype":"venue"
},
  "geometry": {"coordinates":[-82.557222,27.633593],"type":"Point"}
}