{
  "type": "Feature",
  "properties": {
    "addr:full":"256 N Kentucky Ave Lakeland FL 33801",
    "addr:housenumber":"256",
    "addr:postcode":"33801",
    "addr:street":"N Kentucky Ave",
    "iso:country":"US",
    "sg:address":"256 N Kentucky Ave",
    "sg:city":"Lakeland",
    "sg:classifiers":[
        {
            "category":"Banks & Credit Unions",
            "subcategory":"Bank",
            "type":"Services"
        }
    ],
    "sg:phone":"+1 863 581 6655",
    "sg:postcode":"33801",
    "sg:province":"FL",
    "sg:tags":[
        "loan",
        "mortgage",
        "real estate"
    ],
    "wof:name":"Cornerstone Mortgage Services",
    "wof:placetype":"venue"
},
  "geometry": {"coordinates":[-81.955277,28.045718],"type":"Point"}
}