{
  "type": "Feature",
  "properties": {
    "addr:full":"212 E Boynton Beach Blvd Boynton Beach FL 33435",
    "addr:housenumber":"212",
    "addr:postcode":"33435",
    "addr:street":"E Boynton Beach Blvd",
    "iso:country":"US",
    "sg:address":"212 E Boynton Beach Blvd",
    "sg:city":"Boynton Beach",
    "sg:classifiers":[
        {
            "category":"Health Services",
            "subcategory":"Health Practitioner",
            "type":"Services"
        }
    ],
    "sg:phone":"+1 561 733 6000",
    "sg:postcode":"33435",
    "sg:province":"FL",
    "sg:tags":[
        "therapist",
        "physical"
    ],
    "wof:name":"Absolute Physical Therapy",
    "wof:placetype":"venue"
},
  "geometry": {"coordinates":[-80.06165300000001,26.528832],"type":"Point"}
}