{
  "type": "Feature",
  "properties": {
    "iso:country":"US",
    "sg:address":"940 NW 41st Ave",
    "sg:city":"Miami",
    "sg:classifiers":[
        {
            "category":"Retail",
            "subcategory":"Auto Repair",
            "type":"Services"
        }
    ],
    "sg:phone":"+1 305 649 9128",
    "sg:postcode":"33126",
    "sg:province":"FL",
    "sg:tags":[
        "automotive"
    ],
    "wof:name":"Yuniors Towing Inc",
    "wof:placetype":"venue"
},
  "geometry": {"coordinates":[-80.263103,25.782087],"type":"Point"}
}