{
  "type": "Feature",
  "properties": {
    "iso:country":"US",
    "sg:address":"4008 N Federal Hwy",
    "sg:city":"Fort Lauderdale",
    "sg:classifiers":[
        {
            "category":"Shopping",
            "subcategory":"Computers & Home Electronics",
            "type":"Retail Goods"
        }
    ],
    "sg:phone":"+1 954 564 4434",
    "sg:postcode":"33308",
    "sg:province":"FL",
    "sg:tags":[
        "consumer",
        "product",
        "electronic",
        "entertainment"
    ],
    "wof:name":"Sound Advice Inc",
    "wof:placetype":"venue"
},
  "geometry": {"coordinates":[-80.11969999999999,26.180702],"type":"Point"}
}