{
  "type": "Feature",
  "properties": {
    "addr:full":"3301 Walton Rd Apopka FL 32703",
    "addr:housenumber":"3301",
    "addr:postcode":"32703",
    "addr:street":"Walton Rd",
    "iso:country":"US",
    "sg:address":"3301 Walton Rd",
    "sg:city":"Apopka",
    "sg:classifiers":[
        {
            "category":"Building & Trades",
            "subcategory":"Construction",
            "type":"Services"
        }
    ],
    "sg:phone":"+1 407 774 6278",
    "sg:postcode":"32703",
    "sg:province":"FL",
    "sg:tags":[
        "house"
    ],
    "wof:name":"Steve Samuels Home Repairs",
    "wof:placetype":"venue"
},
  "geometry": {"coordinates":[-81.44971700000001,28.667931],"type":"Point"}
}