{
  "type": "Feature",
  "properties": {
    "addr:full":"5330 Cleveland Ave Fort Myers FL 33907",
    "addr:housenumber":"5330",
    "addr:postcode":"33907",
    "addr:street":"Cleveland Ave",
    "iso:country":"US",
    "sg:address":"5330 Cleveland Ave",
    "sg:city":"Fort Myers",
    "sg:classifiers":[
        {
            "category":"Shopping",
            "type":"Retail Goods"
        }
    ],
    "sg:phone":"+1 239 939 7111",
    "sg:postcode":"33907",
    "sg:province":"FL",
    "sg:tags":[
        "picture",
        "frame"
    ],
    "wof:name":"50 Percent Off Framing",
    "wof:placetype":"venue"
},
  "geometry": {"coordinates":[-81.87206500000001,26.57615],"type":"Point"}
}