{
  "type": "Feature",
  "properties": {
    "iso:country":"US",
    "sg:address":"4680 W 17th Ct",
    "sg:city":"Hialeah",
    "sg:classifiers":[
        {
            "category":"Restaurant",
            "type":"Food & Drink"
        }
    ],
    "sg:phone":"+1 305 827 6565",
    "sg:postcode":"33012",
    "sg:province":"FL",
    "sg:tags":[
        "sandwich"
    ],
    "wof:name":"Popular Sub",
    "wof:placetype":"venue"
},
  "geometry": {"coordinates":[-80.317733,25.865865],"type":"Point"}
}