{
  "type": "Feature",
  "properties": {
    "addr:full":"11101 Old Saint Augustine Rd Jacksonville FL 32257",
    "addr:housenumber":"11101",
    "addr:postcode":"32257",
    "addr:street":"Old Saint Augustine Rd",
    "iso:country":"US",
    "sg:address":"11101 Old Saint Augustine Rd",
    "sg:city":"Jacksonville",
    "sg:classifiers":[
        {
            "category":"Professional",
            "subcategory":"Advertising",
            "type":"Services"
        }
    ],
    "sg:phone":"+1 904 288 0026",
    "sg:postcode":"32257",
    "sg:province":"FL",
    "sg:tags":[
        "mailing",
        "shipping"
    ],
    "wof:name":"American Postal",
    "wof:placetype":"venue"
},
  "geometry": {"coordinates":[-81.602975,30.171514],"type":"Point"}
}