{
  "type": "Feature",
  "properties": {
    "iso:country":"US",
    "sg:address":"10481 N Kendall Dr D-202",
    "sg:city":"Miami",
    "sg:classifiers":[
        {
            "category":"Real Estate",
            "subcategory":"Real Estate Services",
            "type":"Services"
        }
    ],
    "sg:phone":"+1 866 595 6025",
    "sg:postcode":"33173",
    "sg:province":"FL",
    "sg:website":"www.xcellencerealty.com/",
    "wof:name":"Xcellence Realty, Inc",
    "wof:placetype":"venue"
},
  "geometry": {"coordinates":[-80.36247,25.687172],"type":"Point"}
}