{
  "type": "Feature",
  "properties": {
    "addr:full":"6702 Benjamin Rd Tampa FL 33634",
    "addr:housenumber":"6702",
    "addr:postcode":"33634",
    "addr:street":"Benjamin Rd",
    "iso:country":"US",
    "sg:address":"6702 Benjamin Rd",
    "sg:city":"Tampa",
    "sg:classifiers":[
        {
            "category":"Building & Trades",
            "subcategory":"Construction",
            "type":"Services"
        }
    ],
    "sg:phone":"+1 813 884 9440",
    "sg:postcode":"33634",
    "sg:province":"FL",
    "sg:tags":[
        "maker",
        "cabinet"
    ],
    "wof:name":"Park Avenue Designs",
    "wof:placetype":"venue"
},
  "geometry": {"coordinates":[-82.542025,28.010934],"type":"Point"}
}