{
  "type": "Feature",
  "properties": {
    "iso:country":"US",
    "sg:address":"1357 Washington Ave",
    "sg:city":"Miami Beach",
    "sg:classifiers":[
        {
            "category":"Restaurant",
            "type":"Food & Drink"
        }
    ],
    "sg:phone":"+1 305 673 5800",
    "sg:postcode":"33139",
    "sg:province":"FL",
    "sg:tags":[
        "pizza"
    ],
    "wof:name":"Hot Sobe Gourmet Pizza & Pasta",
    "wof:placetype":"venue"
},
  "geometry": {"coordinates":[-80.13200399999999,25.7852],"type":"Point"}
}