{
  "type": "Feature",
  "properties": {
    "addr:full":"1253 E 10th Ave Hialeah FL 33010",
    "addr:housenumber":"1253",
    "addr:postcode":"33010",
    "addr:street":"E 10Th Ave",
    "iso:country":"US",
    "sg:address":"1253 E 10th Ave",
    "sg:city":"Hialeah",
    "sg:classifiers":[
        {
            "category":"Shopping",
            "subcategory":"Clothing, Apparel, & Fashions",
            "type":"Retail Goods"
        }
    ],
    "sg:phone":"+1 305 883 1007",
    "sg:postcode":"33010",
    "sg:province":"FL",
    "sg:tags":[
        "accessory"
    ],
    "wof:name":"Rainbow's",
    "wof:placetype":"venue"
},
  "geometry": {"coordinates":[-80.26142400000001,25.83378],"type":"Point"}
}