{
  "type": "Feature",
  "properties": {
    "iso:country":"US",
    "sg:address":"205 S 2nd St",
    "sg:city":"Flagler Beach",
    "sg:classifiers":[
        {
            "category":"Personal",
            "type":"Services"
        }
    ],
    "sg:phone":"+1 386 439 6715",
    "sg:postcode":"32136",
    "sg:province":"FL",
    "sg:tags":[
        "therapist",
        "massage"
    ],
    "wof:name":"Beachside Body Works Inc",
    "wof:placetype":"venue"
},
  "geometry": {"coordinates":[-81.128276,29.479828],"type":"Point"}
}