{
  "type": "Feature",
  "properties": {
    "addr:full":"3718 Silver Star Rd Orlando FL 32808",
    "addr:housenumber":"3718",
    "addr:postcode":"32808",
    "addr:street":"Silver Star Rd",
    "iso:country":"US",
    "sg:address":"3718 Silver Star Rd",
    "sg:city":"Orlando",
    "sg:classifiers":[
        {
            "category":"Freight",
            "type":"Transportation"
        }
    ],
    "sg:phone":"+1 407 296 5083",
    "sg:postcode":"32808",
    "sg:province":"FL",
    "wof:name":"Kinsman Transportation Inc",
    "wof:placetype":"venue"
},
  "geometry": {"coordinates":[-81.42537299999999,28.578014],"type":"Point"}
}