{
  "type": "Feature",
  "properties": {
    "addr:full":"633 Kirkland Rd Yulee FL 32097",
    "addr:housenumber":"633",
    "addr:postcode":"32097",
    "addr:street":"Kirkland Rd",
    "iso:country":"US",
    "sg:address":"633 Kirkland Rd",
    "sg:city":"Yulee",
    "sg:classifiers":[
        {
            "category":"Autos & Motor Vehicles",
            "subcategory":"Motorcycle Sales",
            "type":"Retail Goods"
        }
    ],
    "sg:phone":"+1 904 225 8695",
    "sg:postcode":"32097",
    "sg:province":"FL",
    "sg:tags":[
        "scooter"
    ],
    "wof:name":"Antioch Coach & Chopper",
    "wof:placetype":"venue"
},
  "geometry": {"coordinates":[-81.576283,30.603036],"type":"Point"}
}