{
  "type": "Feature",
  "properties": {
    "iso:country":"US",
    "sg:address":"1534 Atlantic Blvd",
    "sg:city":"Jacksonville",
    "sg:classifiers":[
        {
            "category":"Professional",
            "subcategory":"Business Services",
            "type":"Services"
        }
    ],
    "sg:phone":"+1 904 396 5744",
    "sg:postcode":"32207",
    "sg:province":"FL",
    "sg:tags":[
        "interior",
        "consultant",
        "design",
        "decorator"
    ],
    "wof:name":"KLD Designs",
    "wof:placetype":"venue"
},
  "geometry": {"coordinates":[-81.652529,30.305259],"type":"Point"}
}