{
  "type": "Feature",
  "properties": {
    "addr:full":"1610 W Bay Dr Largo FL 33770",
    "addr:housenumber":"1610",
    "addr:postcode":"33770",
    "addr:street":"W Bay Dr",
    "iso:country":"US",
    "sg:address":"1610 W Bay Dr",
    "sg:city":"Largo",
    "sg:classifiers":[
        {
            "category":"Travel",
            "subcategory":"Campground",
            "type":"Entertainment"
        }
    ],
    "sg:phone":"+1 727 586 2440",
    "sg:postcode":"33770",
    "sg:province":"FL",
    "wof:name":"West Bay Mobile Home & Rv Park",
    "wof:placetype":"venue"
},
  "geometry": {"coordinates":[-82.80588299999999,27.916666],"type":"Point"}
}