{
  "type": "Feature",
  "properties": {
    "iso:country":"US",
    "sg:address":"1012 Crane St",
    "sg:city":"Key Largo",
    "sg:classifiers":[
        {
            "category":"Marine",
            "type":"Transportation"
        }
    ],
    "sg:phone":"+1 305 453 9801",
    "sg:postcode":"33037",
    "sg:province":"FL",
    "sg:tags":[
        "surveyor"
    ],
    "wof:name":"Swanson Marine Survey Inc",
    "wof:placetype":"venue"
},
  "geometry": {"coordinates":[-80.412859,25.133262],"type":"Point"}
}