{
  "type": "Feature",
  "properties": {
    "addr:full":"2400 42nd Ter SW Naples FL 34116",
    "addr:housenumber":"2400",
    "addr:postcode":"34116",
    "addr:street":"42Nd Ter Sw",
    "iso:country":"US",
    "sg:address":"2400 42nd Ter SW",
    "sg:city":"Naples",
    "sg:classifiers":[
        {
            "category":"Building & Trades",
            "subcategory":"Construction",
            "type":"Services"
        }
    ],
    "sg:phone":"+1 239 353 2421",
    "sg:postcode":"34116",
    "sg:province":"FL",
    "sg:tags":[
        "general",
        "contractor"
    ],
    "wof:name":"Post Man",
    "wof:placetype":"venue"
},
  "geometry": {"coordinates":[-81.69255699999999,26.184405],"type":"Point"}
}