{
  "type": "Feature",
  "properties": {
    "addr:full":"11332 Edgewater Cir Wellington FL 33414",
    "addr:housenumber":"11332",
    "addr:postcode":"33414",
    "addr:street":"Edgewater Cir",
    "iso:country":"US",
    "sg:address":"11332 Edgewater Cir",
    "sg:city":"Wellington",
    "sg:classifiers":[
        {
            "category":"Professional",
            "subcategory":"Business Services",
            "type":"Services"
        }
    ],
    "sg:phone":"+1 561 798 0030",
    "sg:postcode":"33414",
    "sg:province":"FL",
    "wof:name":"Delray",
    "wof:placetype":"venue"
},
  "geometry": {"coordinates":[-80.22776500000001,26.623096],"type":"Point"}
}