{
  "type": "Feature",
  "properties": {
    "addr:full":"5661 Red Bug Lake Rd Winter Springs FL 32708",
    "addr:housenumber":"5661",
    "addr:postcode":"32708",
    "addr:street":"Red Bug Lake Rd",
    "iso:country":"US",
    "sg:address":"5661 Red Bug Lake Rd",
    "sg:city":"Winter Springs",
    "sg:classifiers":[
        {
            "category":"Restaurant",
            "type":"Food & Drink"
        }
    ],
    "sg:phone":"+1 407 388 7766",
    "sg:postcode":"32708",
    "sg:province":"FL",
    "wof:name":"Villa Capri Rstrnt & Pizzeria",
    "wof:placetype":"venue"
},
  "geometry": {"coordinates":[-81.267696,28.647725],"type":"Point"}
}