{
  "type": "Feature",
  "properties": {
    "addr:full":"2300 Econ Cir Orlando FL 32817",
    "addr:housenumber":"2300",
    "addr:postcode":"32817",
    "addr:street":"Econ Cir",
    "iso:country":"US",
    "sg:address":"2300 Econ Cir",
    "sg:city":"Orlando",
    "sg:classifiers":[
        {
            "category":"Real Estate",
            "subcategory":"Real Estate Operator",
            "type":"Services"
        }
    ],
    "sg:phone":"+1 407 679 6061",
    "sg:postcode":"32817",
    "sg:province":"FL",
    "sg:tags":[
        "apartment"
    ],
    "wof:name":"Colonial Pointe",
    "wof:placetype":"venue"
},
  "geometry": {"coordinates":[-81.257009,28.577111],"type":"Point"}
}