{
  "type": "Feature",
  "properties": {
    "addr:full":"1102 3rd St S Jacksonville Bch FL 32250",
    "addr:housenumber":"1102",
    "addr:postcode":"32250",
    "addr:street":"3Rd St S",
    "iso:country":"US",
    "sg:address":"1102 3rd St S",
    "sg:city":"Jacksonville Bch",
    "sg:classifiers":[
        {
            "category":"Utilities",
            "subcategory":"Mobile Phone",
            "type":"Services"
        }
    ],
    "sg:phone":"+1 904 242 2772",
    "sg:postcode":"32250",
    "sg:province":"FL",
    "sg:tags":[
        "telephone",
        "cellular"
    ],
    "wof:name":"Beepers N Phones",
    "wof:placetype":"venue"
},
  "geometry": {"coordinates":[-81.389573,30.277018],"type":"Point"}
}