{
  "type": "Feature",
  "properties": {
    "iso:country":"US",
    "sg:address":"5520 Grand Blvd",
    "sg:city":"New Port Richey",
    "sg:classifiers":[
        {
            "category":"Education",
            "subcategory":"School",
            "type":"Public Place"
        }
    ],
    "sg:phone":"+1 727 774 0000",
    "sg:postcode":"34652",
    "sg:province":"FL",
    "wof:name":"Schwettman Education Ctr",
    "wof:placetype":"venue"
},
  "geometry": {"coordinates":[-82.719712,28.238903],"type":"Point"}
}