{
  "type": "Feature",
  "properties": {
    "iso:country":"US",
    "sg:address":"3327 Sheridan St",
    "sg:city":"Hollywood",
    "sg:classifiers":[
        {
            "category":"Restaurant",
            "type":"Food & Drink"
        }
    ],
    "sg:phone":"+1 954 987 1388",
    "sg:postcode":"33021",
    "sg:province":"FL",
    "sg:tags":[
        "japanese"
    ],
    "wof:name":"Wan's Sushi House",
    "wof:placetype":"venue"
},
  "geometry": {"coordinates":[-80.176874,26.033142],"type":"Point"}
}