{
  "type": "Feature",
  "properties": {
    "iso:country":"US",
    "sg:address":"1351 SE 3rd St",
    "sg:city":"Deerfield Beach",
    "sg:classifiers":[
        {
            "category":"Real Estate",
            "subcategory":"Real Estate Operator",
            "type":"Services"
        }
    ],
    "sg:phone":"+1 954 571 6987",
    "sg:postcode":"33441",
    "sg:province":"FL",
    "sg:tags":[
        "building",
        "apartment"
    ],
    "wof:name":"Pirate Cove",
    "wof:placetype":"venue"
},
  "geometry": {"coordinates":[-80.086522,26.314213],"type":"Point"}
}