{
  "type": "Feature",
  "properties": {
    "iso:country":"US",
    "sg:address":"632 W Oak Ridge Rd",
    "sg:city":"Orlando",
    "sg:classifiers":[
        {
            "category":"Shopping",
            "subcategory":"Bicycles & Sporting Goods",
            "type":"Retail Goods"
        }
    ],
    "sg:phone":"+1 407 857 5663",
    "sg:postcode":"32809",
    "sg:province":"FL",
    "sg:tags":[
        "gun",
        "gunsmith"
    ],
    "wof:name":"Oak Ridge Gun Range",
    "wof:placetype":"venue"
},
  "geometry": {"coordinates":[-81.38439200000001,28.472639],"type":"Point"}
}