{
  "type": "Feature",
  "properties": {
    "iso:country":"US",
    "sg:address":"5240 Gall Blvd",
    "sg:city":"Zephyrhills",
    "sg:classifiers":[
        {
            "category":"Retail",
            "subcategory":"Auto Repair",
            "type":"Services"
        }
    ],
    "sg:phone":"+1 813 788 1200",
    "sg:postcode":"33542",
    "sg:province":"FL",
    "sg:tags":[
        "repairing",
        "automobile"
    ],
    "sg:website":"www.tiresplus.com",
    "wof:name":"Tires Plus Total Car Care",
    "wof:placetype":"venue"
},
  "geometry": {"coordinates":[-82.182501,28.23529],"type":"Point"}
}