{
  "type": "Feature",
  "properties": {
    "iso:country":"US",
    "sg:address":"115 Buckner Rd",
    "sg:city":"Middleburg",
    "sg:classifiers":[
        {
            "category":"Building & Trades",
            "subcategory":"Construction",
            "type":"Services"
        }
    ],
    "sg:phone":"+1 904 272 1412",
    "sg:postcode":"32068",
    "sg:province":"FL",
    "sg:tags":[
        "house"
    ],
    "wof:name":"Cercy Builders",
    "wof:placetype":"venue"
},
  "geometry": {"coordinates":[-81.768638,30.108969],"type":"Point"}
}