{
  "type": "Feature",
  "properties": {
    "iso:country":"US",
    "sg:address":"5030 Dr Phillips Blvd",
    "sg:city":"Orlando",
    "sg:classifiers":[
        {
            "category":"Shopping",
            "subcategory":"Used Merchandise",
            "type":"Retail Goods"
        }
    ],
    "sg:phone":"+1 407 253 4100",
    "sg:postcode":"32819",
    "sg:province":"FL",
    "wof:name":"Pine Traditions",
    "wof:placetype":"venue"
},
  "geometry": {"coordinates":[-81.490942,28.491445],"type":"Point"}
}