{
  "type": "Feature",
  "properties": {
    "addr:full":"1515 US Hwy 1 Sebastian FL 32958",
    "addr:housenumber":"1515",
    "addr:postcode":"32958",
    "addr:street":"Us Hwy 1",
    "iso:country":"US",
    "sg:address":"1515 US Hwy 1",
    "sg:city":"Sebastian",
    "sg:classifiers":[
        {
            "category":"Personal",
            "subcategory":"Beauty Salon",
            "type":"Services"
        },
        {
            "category":"Sports & Exercise",
            "subcategory":"Gym",
            "type":"Entertainment"
        }
    ],
    "sg:phone":"+1 772 581 9262",
    "sg:postcode":"32958",
    "sg:province":"FL",
    "sg:tags":[
        "fitness",
        "physical",
        "facility"
    ],
    "wof:name":"A Hidden Oasis Day Spa",
    "wof:placetype":"venue"
},
  "geometry": {"coordinates":[-80.472791,27.821896],"type":"Point"}
}