{
  "type": "Feature",
  "properties": {
    "iso:country":"US",
    "sg:address":"2895 46th Ave N",
    "sg:city":"St Petersburg",
    "sg:classifiers":[
        {
            "category":"Manufacturing",
            "subcategory":"Tools & Machinery",
            "type":"Manufacturing & Wholesale Goods"
        }
    ],
    "sg:phone":"+1 727 460 9627",
    "sg:postcode":"33714",
    "sg:province":"FL",
    "sg:tags":[
        "machine",
        "shop",
        "industrial",
        "mfg"
    ],
    "wof:name":"A American Precision Machining",
    "wof:placetype":"venue"
},
  "geometry": {"coordinates":[-82.67379200000001,27.813882],"type":"Point"}
}