{
  "type": "Feature",
  "properties": {
    "iso:country":"US",
    "sg:address":"1636 N Central Ave",
    "sg:city":"Sebastian",
    "sg:classifiers":[
        {
            "category":"Building & Trades",
            "subcategory":"Construction",
            "type":"Services"
        }
    ],
    "sg:phone":"+1 772 388 1502",
    "sg:postcode":"32958",
    "sg:province":"FL",
    "sg:tags":[
        "general",
        "contractor"
    ],
    "wof:name":"Kenson Construction Co",
    "wof:placetype":"venue"
},
  "geometry": {"coordinates":[-80.474605,27.825459],"type":"Point"}
}