{
  "type": "Feature",
  "properties": {
    "iso:country":"US",
    "sg:address":"7100 SW 8th St",
    "sg:city":"Hollywood",
    "sg:classifiers":[
        {
            "category":"Wholesale",
            "subcategory":"Non-durable Goods",
            "type":"Manufacturing & Wholesale Goods"
        }
    ],
    "sg:phone":"+1 954 986 2359",
    "sg:postcode":"33023",
    "sg:province":"FL",
    "wof:name":"McArthur HP Dairy Distributor",
    "wof:placetype":"venue"
},
  "geometry": {"coordinates":[-80.229816,26.002962],"type":"Point"}
}