{
  "type": "Feature",
  "properties": {
    "addr:full":"3511 39th St E Palmetto FL 34221",
    "addr:housenumber":"3511",
    "addr:postcode":"34221",
    "addr:street":"39Th St E",
    "iso:country":"US",
    "sg:address":"3511 39th St E",
    "sg:city":"Palmetto",
    "sg:classifiers":[
        {
            "category":"Building & Trades",
            "subcategory":"Electrical",
            "type":"Services"
        }
    ],
    "sg:phone":"+1 941 723 3277",
    "sg:postcode":"34221",
    "sg:province":"FL",
    "sg:tags":[
        "electrical",
        "electric",
        "contractor"
    ],
    "wof:name":"Advanced Electrical Services",
    "wof:placetype":"venue"
},
  "geometry": {"coordinates":[-82.530687,27.548731],"type":"Point"}
}