{
  "type": "Feature",
  "properties": {
    "iso:country":"US",
    "sg:address":"3501 13th St",
    "sg:city":"Saint Cloud",
    "sg:classifiers":[
        {
            "category":"Professional",
            "subcategory":"Accounting & Tax Preparation",
            "type":"Services"
        }
    ],
    "sg:phone":"+1 407 892 1002",
    "sg:postcode":"34769",
    "sg:province":"FL",
    "wof:name":"Danley Richard D",
    "wof:placetype":"venue"
},
  "geometry": {"coordinates":[-81.30846699999999,28.248337],"type":"Point"}
}