{
  "type": "Feature",
  "properties": {
    "iso:country":"US",
    "sg:address":"7191 Cypress Lake Dr",
    "sg:city":"Fort Myers",
    "sg:classifiers":[
        {
            "category":"Shopping",
            "subcategory":"Stationery & Office Supplies",
            "type":"Retail Goods"
        },
        {
            "category":"Professional",
            "subcategory":"Printing & Photocopies",
            "type":"Services"
        }
    ],
    "sg:phone":"+1 239 466 5487",
    "sg:postcode":"33907",
    "sg:province":"FL",
    "sg:tags":[
        "equipment"
    ],
    "wof:name":"Staples",
    "wof:placetype":"venue"
},
  "geometry": {"coordinates":[-81.875298,26.546101],"type":"Point"}
}