{
  "type": "Feature",
  "properties": {
    "iso:country":"US",
    "sg:address":"1620 NW 49th St",
    "sg:city":"Miami",
    "sg:classifiers":[
        {
            "category":"Banks & Credit Unions",
            "subcategory":"Bank",
            "type":"Services"
        }
    ],
    "sg:phone":"+1 305 929 1080",
    "sg:postcode":"33142",
    "sg:province":"FL",
    "sg:website":"www.wachovia.com",
    "wof:name":"Southtrust Bank",
    "wof:placetype":"venue"
},
  "geometry": {"coordinates":[-80.223686,25.819699],"type":"Point"}
}