{
  "type": "Feature",
  "properties": {
    "iso:country":"US",
    "sg:address":"1529 State Hwy 60",
    "sg:city":"Valrico",
    "sg:classifiers":[
        {
            "category":"Wholesale",
            "subcategory":"Construction Materials",
            "type":"Manufacturing & Wholesale Goods"
        }
    ],
    "sg:phone":"+1 813 779 7433",
    "sg:postcode":"33594",
    "sg:province":"FL",
    "wof:name":"Superior Sheds Inc",
    "wof:placetype":"venue"
},
  "geometry": {"coordinates":[-82.268807,27.937723],"type":"Point"}
}