{
  "type": "Feature",
  "properties": {
    "iso:country":"US",
    "sg:address":"99 Juniper Rd",
    "sg:city":"Hollywood",
    "sg:classifiers":[
        {
            "category":"Autos & Motor Vehicles",
            "subcategory":"Auto Supplies",
            "type":"Retail Goods"
        }
    ],
    "sg:phone":"+1 954 983 8200",
    "sg:postcode":"33021",
    "sg:province":"FL",
    "sg:tags":[
        "filter",
        "gas"
    ],
    "wof:name":"Tri-Dim Filter Corp",
    "wof:placetype":"venue"
},
  "geometry": {"coordinates":[-80.19830399999999,26.036759],"type":"Point"}
}