{
  "type": "Feature",
  "properties": {
    "iso:country":"US",
    "sg:address":"4333 Orangewood Ave",
    "sg:city":"Fort Myers",
    "sg:classifiers":[
        {
            "category":"Retail",
            "subcategory":"Animal Services",
            "type":"Services"
        }
    ],
    "sg:phone":"+1 239 277 1359",
    "sg:postcode":"33901",
    "sg:province":"FL",
    "wof:name":"Wild & Running Free LLC",
    "wof:placetype":"venue"
},
  "geometry": {"coordinates":[-81.87779399999999,26.598478],"type":"Point"}
}