{
  "type": "Feature",
  "properties": {
    "iso:country":"US",
    "sg:address":"4500 Swift Rd",
    "sg:city":"Sarasota",
    "sg:classifiers":[
        {
            "category":"Organizations",
            "subcategory":"Religious Organization",
            "type":"Services"
        }
    ],
    "sg:phone":"+1 941 954 8646",
    "sg:postcode":"34231",
    "sg:province":"FL",
    "wof:name":"Beth Simcha Inc",
    "wof:placetype":"venue"
},
  "geometry": {"coordinates":[-82.514155,27.288605],"type":"Point"}
}