{
  "type": "Feature",
  "properties": {
    "iso:country":"US",
    "sg:address":"11205 Hutchison Blvd",
    "sg:city":"Panama City Bch",
    "sg:classifiers":[
        {
            "category":"Sports & Exercise",
            "subcategory":"Gym",
            "type":"Entertainment"
        }
    ],
    "sg:phone":"+1 850 233 2111",
    "sg:postcode":"32407",
    "sg:province":"FL",
    "sg:tags":[
        "club",
        "health",
        "studio",
        "gymnasium"
    ],
    "wof:name":"Gold's Gym",
    "wof:placetype":"venue"
},
  "geometry": {"coordinates":[-85.81541199999999,30.187628],"type":"Point"}
}