{
  "type": "Feature",
  "properties": {
    "iso:country":"US",
    "sg:address":"34900 US Hwy 19 N",
    "sg:city":"Palm Harbor",
    "sg:classifiers":[
        {
            "category":"Restaurant",
            "type":"Food & Drink"
        }
    ],
    "sg:phone":"+1 727 786 2286",
    "sg:postcode":"34684",
    "sg:province":"FL",
    "sg:tags":[
        "eating"
    ],
    "wof:name":"Steak and Ale",
    "wof:placetype":"venue"
},
  "geometry": {"coordinates":[-82.73941000000001,28.086277],"type":"Point"}
}