{
  "type": "Feature",
  "properties": {
    "addr:full":"7200 US Hwy 19 Pinellas Park FL 33781",
    "addr:housenumber":"7200",
    "addr:postcode":"33781",
    "addr:street":"Us Hwy 19",
    "iso:country":"US",
    "sg:address":"7200 US Hwy 19",
    "sg:city":"Pinellas Park",
    "sg:classifiers":[
        {
            "category":"Shopping",
            "subcategory":"Shoes",
            "type":"Retail Goods"
        }
    ],
    "sg:phone":"+1 727 521 0038",
    "sg:postcode":"33781",
    "sg:province":"FL",
    "wof:name":"Discount Sport Shoes",
    "wof:placetype":"venue"
},
  "geometry": {"coordinates":[-82.683572,27.838967],"type":"Point"}
}