{
  "type": "Feature",
  "properties": {
    "iso:country":"US",
    "sg:address":"7273 Bee Ridge Rd",
    "sg:city":"Sarasota",
    "sg:classifiers":[
        {
            "category":"Professional",
            "subcategory":"Lawyer & Legal Services",
            "type":"Services"
        }
    ],
    "sg:phone":"+1 941 342 9345",
    "sg:postcode":"34241",
    "sg:province":"FL",
    "sg:tags":[
        "attorney"
    ],
    "wof:name":"James W Collins Law Office",
    "wof:placetype":"venue"
},
  "geometry": {"coordinates":[-82.420818,27.298772],"type":"Point"}
}