{
  "type": "Feature",
  "properties": {
    "addr:full":"2001 NE 48th St Fort Lauderdale FL 33308",
    "addr:housenumber":"2001",
    "addr:postcode":"33308",
    "addr:street":"Ne 48Th St",
    "iso:country":"US",
    "sg:address":"2001 NE 48th St",
    "sg:city":"Fort Lauderdale",
    "sg:classifiers":[
        {
            "category":"Health Services",
            "subcategory":"Doctor",
            "type":"Services"
        }
    ],
    "sg:phone":"+1 954 771 3929",
    "sg:postcode":"33308",
    "sg:province":"FL",
    "sg:tags":[
        "medical"
    ],
    "wof:name":"Ft Lauderdale Renal Group",
    "wof:placetype":"venue"
},
  "geometry": {"coordinates":[-80.117976,26.186611],"type":"Point"}
}