{
  "type": "Feature",
  "properties": {
    "iso:country":"US",
    "sg:address":"1091 SW 131st Place Ct",
    "sg:city":"Miami",
    "sg:classifiers":[
        {
            "category":"Travel",
            "subcategory":"Travel Agent",
            "type":"Entertainment"
        }
    ],
    "sg:phone":"+1 305 207 2968",
    "sg:postcode":"33184",
    "sg:province":"FL",
    "sg:tags":[
        "agency",
        "services-commercial"
    ],
    "wof:name":"Crew Travel",
    "wof:placetype":"venue"
},
  "geometry": {"coordinates":[-80.40926399999999,25.75687],"type":"Point"}
}