{
  "type": "Feature",
  "properties": {
    "addr:full":"6131 NW 58th Way Pompano Beach FL 33067",
    "addr:housenumber":"6131",
    "addr:postcode":"33067",
    "addr:street":"Nw 58Th Way",
    "iso:country":"US",
    "sg:address":"6131 NW 58th Way",
    "sg:city":"Pompano Beach",
    "sg:classifiers":[
        {
            "category":"Professional",
            "subcategory":"Advertising",
            "type":"Services"
        }
    ],
    "sg:phone":"+1 954 255 7970",
    "sg:postcode":"33067",
    "sg:province":"FL",
    "sg:tags":[
        "agency"
    ],
    "wof:name":"Allied Communications",
    "wof:placetype":"venue"
},
  "geometry": {"coordinates":[-80.204172,26.306664],"type":"Point"}
}