{
  "type": "Feature",
  "properties": {
    "iso:country":"US",
    "sg:address":"2307 S Douglas Rd",
    "sg:city":"Miami",
    "sg:classifiers":[
        {
            "category":"Insurance",
            "subcategory":"Insurance Agent",
            "type":"Services"
        }
    ],
    "sg:phone":"+1 305 461 4884",
    "sg:postcode":"33145",
    "sg:province":"FL",
    "wof:name":"Florida Insurance Accounting",
    "wof:placetype":"venue"
},
  "geometry": {"coordinates":[-80.254548,25.750077],"type":"Point"}
}