{
  "type": "Feature",
  "properties": {
    "iso:country":"US",
    "sg:address":"4666 E Colonial Dr",
    "sg:city":"Orlando",
    "sg:classifiers":[
        {
            "category":"Shopping",
            "subcategory":"Musical Instruments",
            "type":"Retail Goods"
        }
    ],
    "sg:phone":"+1 407 228 6460",
    "sg:postcode":"32803",
    "sg:province":"FL",
    "sg:tags":[
        "music",
        "dealer"
    ],
    "wof:name":"All About Music",
    "wof:placetype":"venue"
},
  "geometry": {"coordinates":[-81.328795,28.5533],"type":"Point"}
}