{
  "type": "Feature",
  "properties": {
    "addr:full":"801 Palm Grove Ct Daytona Beach FL 32119",
    "addr:housenumber":"801",
    "addr:postcode":"32119",
    "addr:street":"Palm Grove Ct",
    "iso:country":"US",
    "sg:address":"801 Palm Grove Ct",
    "sg:city":"Daytona Beach",
    "sg:classifiers":[
        {
            "category":"Freight",
            "type":"Transportation"
        }
    ],
    "sg:phone":"+1 386 767 2333",
    "sg:postcode":"32119",
    "sg:province":"FL",
    "sg:tags":[
        "operator",
        "local",
        "trucking"
    ],
    "wof:name":"Norman E Gavin Trucking",
    "wof:placetype":"venue"
},
  "geometry": {"coordinates":[-81.012621,29.158348],"type":"Point"}
}