{
  "type": "Feature",
  "properties": {
    "addr:full":"4902 N Kings Hwy Fort Pierce FL 34951",
    "addr:housenumber":"4902",
    "addr:postcode":"34951",
    "addr:street":"N Kings Hwy",
    "iso:country":"US",
    "sg:address":"4902 N Kings Hwy",
    "sg:city":"Fort Pierce",
    "sg:classifiers":[
        {
            "category":"Food & Beverages",
            "subcategory":"Liquor & Beverages",
            "type":"Retail Goods"
        }
    ],
    "sg:phone":"+1 772 465 1653",
    "sg:postcode":"34951",
    "sg:province":"FL",
    "sg:tags":[
        "bar",
        "store"
    ],
    "wof:name":"Lakewood Park Liquors",
    "wof:placetype":"venue"
},
  "geometry": {"coordinates":[-80.398197,27.524629],"type":"Point"}
}