{
  "type": "Feature",
  "properties": {
    "iso:country":"US",
    "sg:address":"8432 Cooper Creek Blvd",
    "sg:city":"University Park",
    "sg:classifiers":[
        {
            "category":"Health Services",
            "subcategory":"Chiropractor",
            "type":"Services"
        }
    ],
    "sg:phone":"+1 941 360 2220",
    "sg:postcode":"34201",
    "sg:province":"FL",
    "wof:name":"University Chiropractic Ctr",
    "wof:placetype":"venue"
},
  "geometry": {"coordinates":[-82.45559900000001,27.389813],"type":"Point"}
}