{
  "type": "Feature",
  "properties": {
    "addr:full":"34 Amaryliss Dr Lake Wales FL 33853",
    "addr:housenumber":"34",
    "addr:postcode":"33853",
    "addr:street":"Amaryliss Dr",
    "iso:country":"US",
    "sg:address":"34 Amaryliss Dr",
    "sg:city":"Lake Wales",
    "sg:classifiers":[
        {
            "category":"Real Estate",
            "subcategory":"Real Estate Agent",
            "type":"Services"
        }
    ],
    "sg:phone":"+1 863 692 1040",
    "sg:postcode":"33853",
    "sg:province":"FL",
    "wof:name":"Hankins Realty Corp",
    "wof:placetype":"venue"
},
  "geometry": {"coordinates":[-81.37973,27.820441],"type":"Point"}
}