{
  "type": "Feature",
  "properties": {
    "iso:country":"US",
    "sg:address":"419 E Coconut Palm Rd",
    "sg:city":"Boca Raton",
    "sg:classifiers":[
        {
            "category":"Banks & Credit Unions",
            "subcategory":"Bank",
            "type":"Services"
        }
    ],
    "sg:phone":"+1 561 750 7797",
    "sg:postcode":"33432",
    "sg:province":"FL",
    "sg:tags":[
        "personal",
        "institution"
    ],
    "wof:name":"Oliver Dully",
    "wof:placetype":"venue"
},
  "geometry": {"coordinates":[-80.082418,26.323689],"type":"Point"}
}