{
  "type": "Feature",
  "properties": {
    "iso:country":"US",
    "sg:address":"2035 W Washington St",
    "sg:city":"Orlando",
    "sg:classifiers":[
        {
            "category":"Social Services",
            "subcategory":"Child Care",
            "type":"Services"
        }
    ],
    "sg:phone":"+1 407 426 8042",
    "sg:postcode":"32805",
    "sg:province":"FL",
    "sg:tags":[
        "nursery",
        "day"
    ],
    "wof:name":"Kids At Work",
    "wof:placetype":"venue"
},
  "geometry": {"coordinates":[-81.406897,28.5443],"type":"Point"}
}