{
  "type": "Feature",
  "properties": {
    "iso:country":"US",
    "sg:address":"965 E Altamonte Dr",
    "sg:city":"Altamonte Springs",
    "sg:classifiers":[
        {
            "category":"Health Services",
            "subcategory":"Doctor",
            "type":"Services"
        }
    ],
    "sg:phone":"+1 407 331 6423",
    "sg:postcode":"32701",
    "sg:province":"FL",
    "sg:website":"www.cyntrist.com",
    "wof:name":"Cyntrist",
    "wof:placetype":"venue"
},
  "geometry": {"coordinates":[-81.358507,28.663387],"type":"Point"}
}