{
  "type": "Feature",
  "properties": {
    "iso:country":"US",
    "sg:address":"1020 NW 99th Ave",
    "sg:city":"Fort Lauderdale",
    "sg:classifiers":[
        {
            "category":"Real Estate",
            "subcategory":"Real Estate Agent",
            "type":"Services"
        }
    ],
    "sg:phone":"+1 954 472 8269",
    "sg:postcode":"33322",
    "sg:province":"FL",
    "wof:name":"Ester R Cohen",
    "wof:placetype":"venue"
},
  "geometry": {"coordinates":[-80.281925,26.139895],"type":"Point"}
}