{
  "type": "Feature",
  "properties": {
    "iso:country":"US",
    "sg:address":"503 SW 3 St",
    "sg:city":"Gainesville",
    "sg:classifiers":[
        {
            "category":"Retail",
            "subcategory":"Laundry & Dry Cleaning",
            "type":"Services"
        }
    ],
    "sg:phone":"+1 352 372 4184",
    "sg:postcode":"32601",
    "sg:province":"FL",
    "sg:tags":[
        "cleaners"
    ],
    "wof:name":"S & S Cleaners",
    "wof:placetype":"venue"
},
  "geometry": {"coordinates":[-82.32801000000001,29.6465],"type":"Point"}
}