{
  "type": "Feature",
  "properties": {
    "iso:country":"US",
    "sg:address":"9700 International Dr",
    "sg:city":"Orlando",
    "sg:classifiers":[
        {
            "category":"Restaurant",
            "type":"Food & Drink"
        }
    ],
    "sg:menulink":"http://www.allmenus.com/fl/southwest-orange/3371-jacks-place/menu/",
    "sg:phone":"+1 407 996 1781",
    "sg:postcode":"32819",
    "sg:province":"FL",
    "sg:tags":[
        "american"
    ],
    "wof:name":"Jack's Place",
    "wof:placetype":"venue"
},
  "geometry": {"coordinates":[-81.470471,28.430222],"type":"Point"}
}