{
  "type": "Feature",
  "properties": {
    "iso:country":"US",
    "sg:address":"9300 NW 41st St",
    "sg:city":"Doral",
    "sg:classifiers":[
        {
            "category":"Communications",
            "subcategory":"Radio Station",
            "type":"Services"
        }
    ],
    "sg:phone":"+1 305 500 9844",
    "sg:postcode":"33178",
    "sg:province":"FL",
    "sg:tags":[
        "broadcast"
    ],
    "wof:name":"Univision Radio",
    "wof:placetype":"venue"
},
  "geometry": {"coordinates":[-80.348671,25.81152],"type":"Point"}
}