{
  "type": "Feature",
  "properties": {
    "iso:country":"US",
    "sg:address":"69 Harbor Dr",
    "sg:city":"Key Biscayne",
    "sg:classifiers":[
        {
            "category":"Personal",
            "subcategory":"Shoe Repair & Shine",
            "type":"Services"
        }
    ],
    "sg:phone":"+1 305 361 9913",
    "sg:postcode":"33149",
    "sg:province":"FL",
    "sg:tags":[
        "repairing",
        "boot"
    ],
    "wof:name":"Golden Shoe",
    "wof:placetype":"venue"
},
  "geometry": {"coordinates":[-80.163234,25.699261],"type":"Point"}
}