{
  "type": "Feature",
  "properties": {
    "iso:country":"US",
    "sg:address":"8189 S Florida Ave",
    "sg:city":"Floral City",
    "sg:classifiers":[
        {
            "category":"Utilities",
            "subcategory":"Water",
            "type":"Services"
        }
    ],
    "sg:phone":"+1 352 726 3366",
    "sg:postcode":"34436",
    "sg:province":"FL",
    "sg:tags":[
        "company",
        "sewage"
    ],
    "wof:name":"Floral City Water Assn",
    "wof:placetype":"venue"
},
  "geometry": {"coordinates":[-82.29930899999999,28.743494],"type":"Point"}
}