{
  "type": "Feature",
  "properties": {
    "addr:full":"9703 S Dixie Hwy Miami FL 33156",
    "addr:housenumber":"9703",
    "addr:postcode":"33156",
    "addr:street":"S Dixie Hwy",
    "iso:country":"US",
    "sg:address":"9703 S Dixie Hwy",
    "sg:city":"Miami",
    "sg:classifiers":[
        {
            "category":"Professional",
            "subcategory":"Employment Agencies",
            "type":"Services"
        }
    ],
    "sg:phone":"+1 305 668 8840",
    "sg:postcode":"33156",
    "sg:province":"FL",
    "wof:name":"Florida Recruiters Inc",
    "wof:placetype":"venue"
},
  "geometry": {"coordinates":[-80.3116,25.6714],"type":"Point"}
}