{
  "type": "Feature",
  "properties": {
    "iso:country":"US",
    "sg:address":"5821 SW 1st Ave",
    "sg:city":"Cape Coral",
    "sg:classifiers":[
        {
            "category":"Restaurant",
            "type":"Food & Drink"
        }
    ],
    "sg:phone":"+1 239 542 4461",
    "sg:postcode":"33914",
    "sg:province":"FL",
    "sg:tags":[
        "eating"
    ],
    "wof:name":"Mangos",
    "wof:placetype":"venue"
},
  "geometry": {"coordinates":[-81.97577699999999,26.542506],"type":"Point"}
}