{
  "type": "Feature",
  "properties": {
    "addr:full":"404 5th Ave Indialantic FL 32903",
    "addr:housenumber":"404",
    "addr:postcode":"32903",
    "addr:street":"5Th Ave",
    "iso:country":"US",
    "sg:address":"404 5th Ave",
    "sg:city":"Indialantic",
    "sg:classifiers":[
        {
            "category":"Health Services",
            "subcategory":"Doctor",
            "type":"Services"
        }
    ],
    "sg:phone":"+1 321 727 8937",
    "sg:postcode":"32903",
    "sg:province":"FL",
    "sg:tags":[
        "dentist"
    ],
    "wof:name":"Joseph R Cwikla DMD PA",
    "wof:placetype":"venue"
},
  "geometry": {"coordinates":[-80.57501600000001,28.089284],"type":"Point"}
}