{
  "type": "Feature",
  "properties": {
    "iso:country":"US",
    "sg:address":"542 E Brandon Blvd",
    "sg:city":"Brandon",
    "sg:classifiers":[
        {
            "category":"Shopping",
            "subcategory":"Jewelry",
            "type":"Retail Goods"
        }
    ],
    "sg:phone":"+1 813 685 8178",
    "sg:postcode":"33511",
    "sg:province":"FL",
    "sg:tags":[
        "jeweler"
    ],
    "wof:name":"Icing By Claire's",
    "wof:placetype":"venue"
},
  "geometry": {"coordinates":[-82.278363,27.93781],"type":"Point"}
}