{
  "type": "Feature",
  "properties": {
    "iso:country":"US",
    "sg:address":"208 Semoran Blvd",
    "sg:city":"Casselberry",
    "sg:classifiers":[
        {
            "category":"Shopping",
            "subcategory":"Pharmacy",
            "type":"Retail Goods"
        }
    ],
    "sg:phone":"+1 407 339 5801",
    "sg:postcode":"32707",
    "sg:province":"FL",
    "sg:tags":[
        "drug",
        "store"
    ],
    "wof:name":"CVS",
    "wof:placetype":"venue"
},
  "geometry": {"coordinates":[-81.337435,28.658562],"type":"Point"}
}