{
  "type": "Feature",
  "properties": {
    "iso:country":"US",
    "sg:address":"5219 Lime Rd",
    "sg:city":"Sebring",
    "sg:classifiers":[
        {
            "category":"Building & Trades",
            "subcategory":"Construction",
            "type":"Services"
        }
    ],
    "sg:phone":"+1 863 382 6267",
    "sg:postcode":"33875",
    "sg:province":"FL",
    "sg:tags":[
        "general",
        "contractor"
    ],
    "wof:name":"Mourer & Mourer Construction",
    "wof:placetype":"venue"
},
  "geometry": {"coordinates":[-81.485631,27.446495],"type":"Point"}
}