{
  "type": "Feature",
  "properties": {
    "addr:full":"6995 NW 50th St Miami FL 33166",
    "addr:housenumber":"6995",
    "addr:postcode":"33166",
    "addr:street":"Nw 50Th St",
    "iso:country":"US",
    "sg:address":"6995 NW 50th St",
    "sg:city":"Miami",
    "sg:classifiers":[
        {
            "category":"Professional",
            "subcategory":"Management & Consulting",
            "type":"Services"
        }
    ],
    "sg:phone":"+1 305 513 4426",
    "sg:postcode":"33166",
    "sg:province":"FL",
    "sg:tags":[
        "consultant"
    ],
    "wof:name":"Makro Us Inc",
    "wof:placetype":"venue"
},
  "geometry": {"coordinates":[-80.311041,25.818917],"type":"Point"}
}