{
  "type": "Feature",
  "properties": {
    "iso:country":"US",
    "sg:address":"839 S Beach St",
    "sg:city":"Daytona Beach",
    "sg:classifiers":[
        {
            "category":"Building & Trades",
            "subcategory":"Construction",
            "type":"Services"
        }
    ],
    "sg:phone":"+1 386 252 7436",
    "sg:postcode":"32114",
    "sg:province":"FL",
    "sg:tags":[
        "restoration",
        "cleaning",
        "patio",
        "deck"
    ],
    "wof:name":"Diamond's Pressure Cleaning",
    "wof:placetype":"venue"
},
  "geometry": {"coordinates":[-81.01241,29.196422],"type":"Point"}
}