{
  "type": "Feature",
  "properties": {
    "addr:full":"4747 N Ocean Dr Fort Lauderdale FL 33308",
    "addr:housenumber":"4747",
    "addr:postcode":"33308",
    "addr:street":"N Ocean Dr",
    "iso:country":"US",
    "sg:address":"4747 N Ocean Dr",
    "sg:city":"Fort Lauderdale",
    "sg:classifiers":[
        {
            "category":"Banks & Credit Unions",
            "subcategory":"Bank",
            "type":"Services"
        }
    ],
    "sg:phone":"+1 954 784 5542",
    "sg:postcode":"33308",
    "sg:province":"FL",
    "sg:tags":[
        "loan",
        "mortgage",
        "real estate"
    ],
    "wof:name":"Casa Mortgage Corp",
    "wof:placetype":"venue"
},
  "geometry": {"coordinates":[-80.095754,26.199807],"type":"Point"}
}