{
  "type": "Feature",
  "properties": {
    "iso:country":"US",
    "sg:address":"3764 W 12th Ave",
    "sg:city":"Hialeah",
    "sg:classifiers":[
        {
            "category":"Education",
            "subcategory":"School",
            "type":"Public Place"
        }
    ],
    "sg:phone":"+1 305 823 7888",
    "sg:postcode":"33012",
    "sg:province":"FL",
    "sg:tags":[
        "k-",
        "private"
    ],
    "wof:name":"Jean Piaget Academy Inc",
    "wof:placetype":"venue"
},
  "geometry": {"coordinates":[-80.30653599999999,25.855818],"type":"Point"}
}