{
  "type": "Feature",
  "properties": {
    "iso:country":"US",
    "sg:address":"2101 N 50th Ave",
    "sg:city":"Hollywood",
    "sg:classifiers":[
        {
            "category":"Health Services",
            "subcategory":"Chiropractor",
            "type":"Services"
        }
    ],
    "sg:phone":"+1 954 961 7581",
    "sg:postcode":"33021",
    "sg:province":"FL",
    "sg:tags":[
        "chiropractic"
    ],
    "wof:name":"Chiropractic Cent Of Bro",
    "wof:placetype":"venue"
},
  "geometry": {"coordinates":[-80.19412199999999,26.02878],"type":"Point"}
}