{
  "type": "Feature",
  "properties": {
    "addr:full":"1224 SE Magnolia Exd Ocala FL 34471",
    "addr:housenumber":"1224",
    "addr:postcode":"34471",
    "addr:street":"Se Magnolia Exd",
    "iso:country":"US",
    "sg:address":"1224 SE Magnolia Exd",
    "sg:city":"Ocala",
    "sg:classifiers":[
        {
            "category":"Health Services",
            "subcategory":"Doctor",
            "type":"Services"
        }
    ],
    "sg:phone":"+1 352 622 2477",
    "sg:postcode":"34471",
    "sg:province":"FL",
    "sg:tags":[
        "medical"
    ],
    "wof:name":"Larry R Popeil M D",
    "wof:placetype":"venue"
},
  "geometry": {"coordinates":[-82.134792,29.175755],"type":"Point"}
}