{
  "type": "Feature",
  "properties": {
    "addr:full":"1521 Ohio Ave Saint Cloud FL 34769",
    "addr:housenumber":"1521",
    "addr:postcode":"34769",
    "addr:street":"Ohio Ave",
    "iso:country":"US",
    "sg:address":"1521 Ohio Ave",
    "sg:city":"Saint Cloud",
    "sg:classifiers":[
        {
            "category":"Wholesale",
            "subcategory":"Non-durable Goods",
            "type":"Manufacturing & Wholesale Goods"
        }
    ],
    "sg:phone":"+1 407 957 7900",
    "sg:postcode":"34769",
    "sg:province":"FL",
    "wof:name":"Simpson Distributing",
    "wof:placetype":"venue"
},
  "geometry": {"coordinates":[-81.280114,28.243917],"type":"Point"}
}