{
  "type": "Feature",
  "properties": {
    "iso:country":"US",
    "sg:address":"3015 S Congress Ave",
    "sg:city":"Lake Worth",
    "sg:classifiers":[
        {
            "category":"Health Services",
            "subcategory":"Doctor",
            "type":"Services"
        }
    ],
    "sg:phone":"+1 561 965 9345",
    "sg:postcode":"33461",
    "sg:province":"FL",
    "sg:tags":[
        "dental"
    ],
    "wof:name":"Light John Dr Hrrson Jmes A Dd",
    "wof:placetype":"venue"
},
  "geometry": {"coordinates":[-80.088627,26.632499],"type":"Point"}
}