{
  "type": "Feature",
  "properties": {
    "addr:full":"1500 NE 35th Ter Jensen Beach FL 34957",
    "addr:housenumber":"1500",
    "addr:postcode":"34957",
    "addr:street":"Ne 35Th Ter;Beach",
    "iso:country":"US",
    "sg:address":"1500 NE 35th Ter",
    "sg:city":"Jensen Beach",
    "sg:classifiers":[
        {
            "category":"Building & Trades",
            "subcategory":"Construction",
            "type":"Services"
        }
    ],
    "sg:phone":"+1 772 263 9071",
    "sg:postcode":"34957",
    "sg:province":"FL",
    "sg:tags":[
        "concrete",
        "contractor"
    ],
    "wof:name":"Action Concrete Inc",
    "wof:placetype":"venue"
},
  "geometry": {"coordinates":[-80.23218799999999,27.247586],"type":"Point"}
}