{
  "type": "Feature",
  "properties": {
    "iso:country":"US",
    "sg:address":"5809 N 50th St",
    "sg:city":"Tampa",
    "sg:classifiers":[
        {
            "category":"Home & Garden",
            "subcategory":"Furniture",
            "type":"Retail Goods"
        }
    ],
    "sg:phone":"+1 813 626 9669",
    "sg:postcode":"33610",
    "sg:province":"FL",
    "wof:name":"Norwegian Wood Inc",
    "wof:placetype":"venue"
},
  "geometry": {"coordinates":[-82.401842,28.000092],"type":"Point"}
}