{
  "type": "Feature",
  "properties": {
    "iso:country":"US",
    "sg:address":"255 Alhambra Cir Ste 550",
    "sg:city":"Coral Gables",
    "sg:classifiers":[
        {
            "category":"Professional",
            "subcategory":"Lawyer & Legal Services",
            "type":"Services"
        }
    ],
    "sg:phone":"+1 305 476 5272",
    "sg:postcode":"33134",
    "sg:province":"FL",
    "wof:name":"De La Osa Jorge PA",
    "wof:placetype":"venue"
},
  "geometry": {"coordinates":[-80.260149,25.752704],"type":"Point"}
}