{
  "type": "Feature",
  "properties": {
    "addr:full":"4879 Clydo Rd S Ste 1 Jacksonville FL 32207",
    "addr:housenumber":"4879",
    "addr:postcode":"32207",
    "addr:street":"Clydo Rd S Ste 1",
    "iso:country":"US",
    "sg:address":"4879 Clydo Rd S Ste 1",
    "sg:city":"Jacksonville",
    "sg:classifiers":[
        {
            "category":"Manufacturing",
            "subcategory":"Metals",
            "type":"Manufacturing & Wholesale Goods"
        },
        {
            "category":"Manufacturing",
            "subcategory":"Building Materials",
            "type":"Manufacturing & Wholesale Goods"
        }
    ],
    "sg:phone":"+1 904 733 9393",
    "sg:postcode":"32207",
    "sg:province":"FL",
    "sg:tags":[
        "work-manufacturers",
        "fabricator",
        "work",
        "sheet"
    ],
    "wof:name":"Agr Fabricator-Florida Inc",
    "wof:placetype":"venue"
},
  "geometry": {"coordinates":[-81.633914,30.270211],"type":"Point"}
}