{
  "type": "Feature",
  "properties": {
    "addr:full":"301 NW 69th Ter Margate FL 33063",
    "addr:housenumber":"301",
    "addr:postcode":"33063",
    "addr:street":"Nw 69Th Ter Margate",
    "iso:country":"US",
    "sg:address":"301 NW 69th Ter",
    "sg:city":"Margate",
    "sg:classifiers":[
        {
            "category":"Education",
            "subcategory":"School",
            "type":"Public Place"
        }
    ],
    "sg:phone":"+1 754 322 5300",
    "sg:postcode":"33063",
    "sg:province":"FL",
    "wof:name":"Atlantic West Elementary Schl",
    "wof:placetype":"venue"
},
  "geometry": {"coordinates":[-80.218108,26.232224],"type":"Point"}
}