{
  "type": "Feature",
  "properties": {
    "addr:full":"2304 NE 3rd Pl Gainesville FL 32641",
    "addr:housenumber":"2304",
    "addr:postcode":"32641",
    "addr:street":"Ne 3Rd Pl",
    "iso:country":"US",
    "sg:address":"2304 NE 3rd Pl",
    "sg:city":"Gainesville",
    "sg:classifiers":[
        {
            "category":"Restaurant",
            "type":"Food & Drink"
        }
    ],
    "sg:phone":"+1 352 378 8892",
    "sg:postcode":"32641",
    "sg:province":"FL",
    "wof:name":"Ernest's Crab Shack",
    "wof:placetype":"venue"
},
  "geometry": {"coordinates":[-82.29464400000001,29.654249],"type":"Point"}
}