{
  "type": "Feature",
  "properties": {
    "addr:full":"5008 Cumberland Dr Tampa FL 33617",
    "addr:housenumber":"5008",
    "addr:postcode":"33617",
    "addr:street":"Cumberland Dr",
    "iso:country":"US",
    "sg:address":"5008 Cumberland Dr",
    "sg:city":"Tampa",
    "sg:classifiers":[
        {
            "category":"Real Estate",
            "subcategory":"Real Estate Agent",
            "type":"Services"
        }
    ],
    "sg:phone":"+1 877 454 8857",
    "sg:postcode":"33617",
    "sg:province":"FL",
    "wof:name":"Quality Homes Realty Inc",
    "wof:placetype":"venue"
},
  "geometry": {"coordinates":[-82.399541,28.014021],"type":"Point"}
}