{
  "type": "Feature",
  "properties": {
    "iso:country":"US",
    "sg:address":"208 Berkley Rd",
    "sg:city":"Auburndale",
    "sg:classifiers":[
        {
            "category":"Social Services",
            "subcategory":"Child Care",
            "type":"Services"
        }
    ],
    "sg:phone":"+1 863 965 5410",
    "sg:postcode":"33823",
    "sg:province":"FL",
    "sg:tags":[
        "nursery",
        "day"
    ],
    "wof:name":"Lena Vista Kid Care Cdc",
    "wof:placetype":"venue"
},
  "geometry": {"coordinates":[-81.81755800000001,28.058242],"type":"Point"}
}