{
  "type": "Feature",
  "properties": {
    "iso:country":"US",
    "sg:address":"5814 S Dixie Hwy",
    "sg:city":"West Palm Beach",
    "sg:classifiers":[
        {
            "category":"Personal",
            "subcategory":"Beauty Salon",
            "type":"Services"
        }
    ],
    "sg:phone":"+1 561 540 9322",
    "sg:postcode":"33405",
    "sg:province":"FL",
    "wof:name":"All City Barbers",
    "wof:placetype":"venue"
},
  "geometry": {"coordinates":[-80.05567499999999,26.661843],"type":"Point"}
}