{
  "type": "Feature",
  "properties": {
    "addr:full":"516 N Harbor City Blvd Melbourne FL 32935",
    "addr:housenumber":"516",
    "addr:postcode":"32935",
    "addr:street":"N Harbor City Blvd",
    "iso:country":"US",
    "sg:address":"516 N Harbor City Blvd",
    "sg:city":"Melbourne",
    "sg:classifiers":[
        {
            "category":"Professional",
            "subcategory":"Lawyer & Legal Services",
            "type":"Services"
        }
    ],
    "sg:phone":"+1 321 757 9844",
    "sg:postcode":"32935",
    "sg:province":"FL",
    "sg:tags":[
        "attorney"
    ],
    "wof:name":"Lori Henninger Law Office",
    "wof:placetype":"venue"
},
  "geometry": {"coordinates":[-80.626667,28.117254],"type":"Point"}
}