{
  "type": "Feature",
  "properties": {
    "addr:full":"136 Savannah Rd Crawfordville FL 32327",
    "addr:housenumber":"136",
    "addr:postcode":"32327",
    "addr:street":"Savannah Rd",
    "iso:country":"US",
    "sg:address":"136 Savannah Rd",
    "sg:city":"Crawfordville",
    "sg:classifiers":[
        {
            "category":"Building & Trades",
            "subcategory":"Construction",
            "type":"Services"
        }
    ],
    "sg:phone":"+1 850 421 2625",
    "sg:postcode":"32327",
    "sg:province":"FL",
    "sg:tags":[
        "wallcoverings-installation",
        "wallpaper",
        "painting",
        "contractor"
    ],
    "wof:name":"Eric Mayne",
    "wof:placetype":"venue"
},
  "geometry": {"coordinates":[-84.226893,30.249052],"type":"Point"}
}