{
  "type": "Feature",
  "properties": {
    "iso:country":"US",
    "sg:address":"7555 San Miguel Way",
    "sg:city":"Naples",
    "sg:classifiers":[
        {
            "category":"Real Estate",
            "subcategory":"Real Estate Agent",
            "type":"Services"
        }
    ],
    "sg:phone":"+1 239 566 1735",
    "sg:postcode":"34109",
    "sg:province":"FL",
    "wof:name":"John H Dew P A",
    "wof:placetype":"venue"
},
  "geometry": {"coordinates":[-81.783592,26.239924],"type":"Point"}
}