{
  "type": "Feature",
  "properties": {
    "iso:country":"US",
    "sg:address":"2637 W 81st St",
    "sg:city":"Hialeah",
    "sg:classifiers":[
        {
            "category":"Shopping",
            "subcategory":"Mobile Phones",
            "type":"Retail Goods"
        }
    ],
    "sg:phone":"+1 305 822 4242",
    "sg:postcode":"33016",
    "sg:province":"FL",
    "wof:name":"E Communications",
    "wof:placetype":"venue"
},
  "geometry": {"coordinates":[-80.336403,25.895901],"type":"Point"}
}