{
  "type": "Feature",
  "properties": {
    "addr:full":"2368 Sandy Run Dr N Middleburg FL 32068",
    "addr:housenumber":"2368",
    "addr:postcode":"32068",
    "addr:street":"Sandy Run Dr N",
    "iso:country":"US",
    "sg:address":"2368 Sandy Run Dr N",
    "sg:city":"Middleburg",
    "sg:classifiers":[
        {
            "category":"Building & Trades",
            "subcategory":"Construction",
            "type":"Services"
        }
    ],
    "sg:phone":"+1 904 291 5639",
    "sg:postcode":"32068",
    "sg:province":"FL",
    "sg:tags":[
        "house"
    ],
    "wof:name":"Home Improvement Headquarters",
    "wof:placetype":"venue"
},
  "geometry": {"coordinates":[-81.873655,30.05465],"type":"Point"}
}