{
  "type": "Feature",
  "properties": {
    "iso:country":"US",
    "sg:address":"3511 Windham Dr",
    "sg:city":"Holiday",
    "sg:classifiers":[
        {
            "category":"Freight",
            "type":"Transportation"
        }
    ],
    "sg:phone":"+1 727 844 5901",
    "sg:postcode":"34691",
    "sg:province":"FL",
    "sg:tags":[
        "operator",
        "local",
        "trucking"
    ],
    "wof:name":"Eddie S Hauling",
    "wof:placetype":"venue"
},
  "geometry": {"coordinates":[-82.749555,28.212768],"type":"Point"}
}