{
  "type": "Feature",
  "properties": {
    "iso:country":"US",
    "sg:address":"8882 SE Bridge Rd",
    "sg:city":"Hobe Sound",
    "sg:classifiers":[
        {
            "category":"Real Estate",
            "subcategory":"Real Estate Agent",
            "type":"Services"
        }
    ],
    "sg:phone":"+1 772 546 2662",
    "sg:postcode":"33455",
    "sg:province":"FL",
    "wof:name":"Macleod Properties",
    "wof:placetype":"venue"
},
  "geometry": {"coordinates":[-80.136641,27.059471],"type":"Point"}
}