{
  "type": "Feature",
  "properties": {
    "iso:country":"US",
    "sg:address":"1100 NE 79th St",
    "sg:city":"Miami",
    "sg:classifiers":[
        {
            "category":"Restaurant",
            "type":"Food & Drink"
        }
    ],
    "sg:phone":"+1 305 754 2722",
    "sg:postcode":"33138",
    "sg:province":"FL",
    "sg:tags":[
        "chicken",
        "eating"
    ],
    "wof:name":"Capt Crab's Take-Away",
    "wof:placetype":"venue"
},
  "geometry": {"coordinates":[-80.173973,25.84811],"type":"Point"}
}