{
  "type": "Feature",
  "properties": {
    "iso:country":"US",
    "sg:address":"5103 E Fowler Ave",
    "sg:city":"Tampa",
    "sg:classifiers":[
        {
            "category":"Wholesale",
            "subcategory":"Electrical",
            "type":"Manufacturing & Wholesale Goods"
        }
    ],
    "sg:phone":"+1 813 987 2987",
    "sg:postcode":"33617",
    "sg:province":"FL",
    "sg:tags":[
        "car",
        "alarm",
        "audio",
        "tint"
    ],
    "wof:name":"Audio Inventions",
    "wof:placetype":"venue"
},
  "geometry": {"coordinates":[-82.39755599999999,28.054357],"type":"Point"}
}