{
  "type": "Feature",
  "properties": {
    "addr:full":"365 Desoto Pkwy Satellite Beach FL 32937",
    "addr:housenumber":"365",
    "addr:postcode":"32937",
    "addr:street":"Desoto Pkwy",
    "iso:country":"US",
    "sg:address":"365 Desoto Pkwy",
    "sg:city":"Satellite Beach",
    "sg:classifiers":[
        {
            "category":"Building & Trades",
            "subcategory":"Construction",
            "type":"Services"
        }
    ],
    "sg:phone":"+1 321 779 3777",
    "sg:postcode":"32937",
    "sg:province":"FL",
    "sg:tags":[
        "hanging",
        "contractor"
    ],
    "wof:name":"Marathon Painters",
    "wof:placetype":"venue"
},
  "geometry": {"coordinates":[-80.59830599999999,28.164826],"type":"Point"}
}