{
  "type": "Feature",
  "properties": {
    "addr:full":"314 SW 7th St Delray Beach FL 33444",
    "addr:housenumber":"314",
    "addr:postcode":"33444",
    "addr:street":"Sw 7Th St",
    "iso:country":"US",
    "sg:address":"314 SW 7th St",
    "sg:city":"Delray Beach",
    "sg:classifiers":[
        {
            "category":"Organizations",
            "subcategory":"Religious Organization",
            "type":"Services"
        }
    ],
    "sg:phone":"+1 561 274 3556",
    "sg:postcode":"33444",
    "sg:province":"FL",
    "sg:tags":[
        "church"
    ],
    "wof:name":"Mt Moriah AME Church",
    "wof:placetype":"venue"
},
  "geometry": {"coordinates":[-80.07597800000001,26.451073],"type":"Point"}
}