{
  "type": "Feature",
  "properties": {
    "addr:full":"101 Southhall Ln Maitland FL 32751",
    "addr:housenumber":"101",
    "addr:postcode":"32751",
    "addr:street":"Southhall Ln",
    "iso:country":"US",
    "sg:address":"101 Southhall Ln",
    "sg:city":"Maitland",
    "sg:classifiers":[
        {
            "category":"Shopping",
            "subcategory":"Computers & Home Electronics",
            "type":"Retail Goods"
        }
    ],
    "sg:phone":"+1 407 667 4831",
    "sg:postcode":"32751",
    "sg:province":"FL",
    "sg:tags":[
        "software"
    ],
    "wof:name":"Inherent Quality Inc",
    "wof:placetype":"venue"
},
  "geometry": {"coordinates":[-81.396467,28.62717],"type":"Point"}
}