{
  "type": "Feature",
  "properties": {
    "addr:full":"1699 SE Avanti Ct Port Saint Lucie FL 34952",
    "addr:housenumber":"1699",
    "addr:postcode":"34952",
    "addr:street":"Se Avanti Ct",
    "iso:country":"US",
    "sg:address":"1699 SE Avanti Ct",
    "sg:city":"Port Saint Lucie",
    "sg:classifiers":[
        {
            "category":"Building & Trades",
            "subcategory":"Landscaping Services",
            "type":"Services"
        }
    ],
    "sg:phone":"+1 772 337 9195",
    "sg:postcode":"34952",
    "sg:province":"FL",
    "sg:tags":[
        "maintenance"
    ],
    "wof:name":"Treasure Coast Care Inc",
    "wof:placetype":"venue"
},
  "geometry": {"coordinates":[-80.30009,27.283369],"type":"Point"}
}