{
  "type": "Feature",
  "properties": {
    "addr:full":"324 Woodbine St Jacksonville FL 32206",
    "addr:housenumber":"324",
    "addr:postcode":"32206",
    "addr:street":"Woodbine St",
    "iso:country":"US",
    "sg:address":"324 Woodbine St",
    "sg:city":"Jacksonville",
    "sg:classifiers":[
        {
            "category":"Food & Beverages",
            "subcategory":"Groceries & Convenience Stores",
            "type":"Retail Goods"
        }
    ],
    "sg:phone":"+1 904 634 0103",
    "sg:postcode":"32206",
    "sg:province":"FL",
    "wof:name":"Woodbine Grocery",
    "wof:placetype":"venue"
},
  "geometry": {"coordinates":[-81.657515,30.362903],"type":"Point"}
}