{
  "type": "Feature",
  "properties": {
    "iso:country":"US",
    "sg:address":"9 E 17th St",
    "sg:city":"St Cloud",
    "sg:classifiers":[
        {
            "category":"Building & Trades",
            "subcategory":"Electrical",
            "type":"Services"
        },
        {
            "category":"Shopping",
            "type":"Retail Goods"
        }
    ],
    "sg:phone":"+1 407 294 2665",
    "sg:postcode":"34769",
    "sg:province":"FL",
    "sg:tags":[
        "installation",
        "supply",
        "communication",
        "telephone",
        "contractor",
        "equipment"
    ],
    "sg:website":"www.suntelcom.com",
    "wof:name":"Sun Tel Communications Inc",
    "wof:placetype":"venue"
},
  "geometry": {"coordinates":[-81.265933,28.242349],"type":"Point"}
}