{
  "type": "Feature",
  "properties": {
    "iso:country":"US",
    "sg:address":"2282 Atlantic Blvd",
    "sg:city":"Jacksonville",
    "sg:classifiers":[
        {
            "category":"Manufacturing",
            "subcategory":"Tools & Machinery",
            "type":"Manufacturing & Wholesale Goods"
        }
    ],
    "sg:phone":"+1 904 398 1776",
    "sg:postcode":"32207",
    "sg:province":"FL",
    "sg:tags":[
        "machine",
        "folding"
    ],
    "wof:name":"Automated Business Machines",
    "wof:placetype":"venue"
},
  "geometry": {"coordinates":[-81.642141,30.307412],"type":"Point"}
}