{
  "type": "Feature",
  "properties": {
    "iso:country":"US",
    "sg:address":"1550 Madruga Ave",
    "sg:city":"Coral Gables",
    "sg:classifiers":[
        {
            "category":"Health Services",
            "subcategory":"Health Practitioner",
            "type":"Services"
        }
    ],
    "sg:phone":"+1 305 663 5336",
    "sg:postcode":"33146",
    "sg:province":"FL",
    "sg:tags":[
        "psychologist"
    ],
    "wof:name":"Mirta C Laufer",
    "wof:placetype":"venue"
},
  "geometry": {"coordinates":[-80.2837,25.707812],"type":"Point"}
}