{
  "type": "Feature",
  "properties": {
    "addr:full":"11620 Timberridge Rd Tampa FL 33625",
    "addr:housenumber":"11620",
    "addr:postcode":"33625",
    "addr:street":"Timberridge Rd",
    "iso:country":"US",
    "sg:address":"11620 Timberridge Rd",
    "sg:city":"Tampa",
    "sg:classifiers":[
        {
            "category":"Building & Trades",
            "subcategory":"Construction",
            "type":"Services"
        }
    ],
    "sg:phone":"+1 813 920 6329",
    "sg:postcode":"33625",
    "sg:province":"FL",
    "sg:tags":[
        "house"
    ],
    "wof:name":"Wards Home Improvement",
    "wof:placetype":"venue"
},
  "geometry": {"coordinates":[-82.568647,28.054386],"type":"Point"}
}