{
  "type": "Feature",
  "properties": {
    "addr:full":"13613 Hawkeye Dr Orlando FL 32837",
    "addr:housenumber":"13613",
    "addr:postcode":"32837",
    "addr:street":"Hawkeye Dr",
    "iso:country":"US",
    "sg:address":"13613 Hawkeye Dr",
    "sg:city":"Orlando",
    "sg:classifiers":[
        {
            "category":"Freight",
            "type":"Transportation"
        }
    ],
    "sg:phone":"+1 407 375 6221",
    "sg:postcode":"32837",
    "sg:province":"FL",
    "sg:tags":[
        "courier"
    ],
    "wof:name":"Stewart & Savage",
    "wof:placetype":"venue"
},
  "geometry": {"coordinates":[-81.397803,28.364225],"type":"Point"}
}