{
  "type": "Feature",
  "properties": {
    "addr:full":"4973 Capital Cir SE Tallahassee FL 32311",
    "addr:housenumber":"4973",
    "addr:postcode":"32311",
    "addr:street":"Capital Cir Se",
    "iso:country":"US",
    "sg:address":"4973 Capital Cir SE",
    "sg:city":"Tallahassee",
    "sg:classifiers":[
        {
            "category":"Retail",
            "subcategory":"Auto Repair",
            "type":"Services"
        }
    ],
    "sg:phone":"+1 850 878 0778",
    "sg:postcode":"32311",
    "sg:province":"FL",
    "sg:tags":[
        "body",
        "automobile",
        "painting"
    ],
    "wof:name":"Extreme Paint & Body Inc",
    "wof:placetype":"venue"
},
  "geometry": {"coordinates":[-84.23833399999999,30.377619],"type":"Point"}
}