{
  "type": "Feature",
  "properties": {
    "iso:country":"US",
    "sg:address":"5586 N Orange Blossom Trl",
    "sg:city":"Orlando",
    "sg:classifiers":[
        {
            "category":"Fast Food",
            "type":"Food & Drink"
        }
    ],
    "sg:phone":"+1 407 296 2766",
    "sg:postcode":"32810",
    "sg:province":"FL",
    "sg:tags":[
        "chicken",
        "wing"
    ],
    "wof:name":"Original Buffalo Wings & Sub Co",
    "wof:placetype":"venue"
},
  "geometry": {"coordinates":[-81.426903,28.609501],"type":"Point"}
}