{
  "type": "Feature",
  "properties": {
    "iso:country":"US",
    "sg:address":"2344 Rogero Rd",
    "sg:city":"Jacksonville",
    "sg:classifiers":[
        {
            "category":"Real Estate",
            "subcategory":"Real Estate Agent",
            "type":"Services"
        }
    ],
    "sg:phone":"+1 904 745 3331",
    "sg:postcode":"32211",
    "sg:province":"FL",
    "wof:name":"Action Inc",
    "wof:placetype":"venue"
},
  "geometry": {"coordinates":[-81.589513,30.348036],"type":"Point"}
}