{
  "type": "Feature",
  "properties": {
    "iso:country":"US",
    "sg:address":"9751 NW Co Rd 345",
    "sg:city":"Chiefland",
    "sg:classifiers":[
        {
            "category":"Wholesale",
            "subcategory":"Machinery & Supplies",
            "type":"Manufacturing & Wholesale Goods"
        }
    ],
    "sg:phone":"+1 352 493 4904",
    "sg:postcode":"32626",
    "sg:province":"FL",
    "sg:tags":[
        "hardware",
        "repair",
        "mach"
    ],
    "wof:name":"Beauchamp Saw Shop",
    "wof:placetype":"venue"
},
  "geometry": {"coordinates":[-82.889195,29.469982],"type":"Point"}
}