{
  "type": "Feature",
  "properties": {
    "addr:full":"1005 Ohio Ave Lynn Haven FL 32444",
    "addr:housenumber":"1005",
    "addr:postcode":"32444",
    "addr:street":"Ohio Ave",
    "iso:country":"US",
    "sg:address":"1005 Ohio Ave",
    "sg:city":"Lynn Haven",
    "sg:classifiers":[
        {
            "category":"Organizations",
            "subcategory":"Religious Organization",
            "type":"Services"
        }
    ],
    "sg:phone":"+1 850 265 3688",
    "sg:postcode":"32444",
    "sg:province":"FL",
    "sg:tags":[
        "church"
    ],
    "wof:name":"First Baptist Church",
    "wof:placetype":"venue"
},
  "geometry": {"coordinates":[-85.648597,30.242277],"type":"Point"}
}