{
  "type": "Feature",
  "properties": {
    "addr:full":"8603 S Dixie Hwy Ste 301 Miami FL 33143",
    "addr:housenumber":"8603",
    "addr:postcode":"33143",
    "addr:street":"S Dixie Hwy Ste 301",
    "iso:country":"US",
    "sg:address":"8603 S Dixie Hwy Ste 301",
    "sg:city":"Miami",
    "sg:classifiers":[
        {
            "category":"Professional",
            "subcategory":"Detective & Security Services",
            "type":"Services"
        }
    ],
    "sg:phone":"+1 305 666 9878",
    "sg:postcode":"33143",
    "sg:province":"FL",
    "sg:tags":[
        "bodyguard",
        "patrol",
        "investigator",
        "private",
        "guard"
    ],
    "wof:name":"Southeast Investigations & Security Group",
    "wof:placetype":"venue"
},
  "geometry": {"coordinates":[-80.30615400000001,25.690573],"type":"Point"}
}