{
  "type": "Feature",
  "properties": {
    "addr:full":"2724 SW 137th Ave Miami FL 33175",
    "addr:housenumber":"2724",
    "addr:postcode":"33175",
    "addr:street":"Sw 137Th Ave",
    "iso:country":"US",
    "sg:address":"2724 SW 137th Ave",
    "sg:city":"Miami",
    "sg:classifiers":[
        {
            "category":"Retail",
            "subcategory":"Auto Rental",
            "type":"Services"
        },
        {
            "category":"Retail",
            "subcategory":"Storage",
            "type":"Services"
        }
    ],
    "sg:phone":"+1 305 227 9634",
    "sg:postcode":"33175",
    "sg:province":"FL",
    "sg:tags":[
        "renting",
        "moving-self",
        "leasing",
        "truck",
        "trailer"
    ],
    "sg:website":"http://www.uhaul.com",
    "wof:name":"U-Haul Co",
    "wof:placetype":"venue"
},
  "geometry": {"coordinates":[-80.41628300000001,25.742351],"type":"Point"}
}