{
  "type": "Feature",
  "properties": {
    "addr:full":"185 N Cswy New Smyrna Beach FL 32169",
    "addr:housenumber":"185",
    "addr:postcode":"32169",
    "addr:street":"N Cswy",
    "iso:country":"US",
    "sg:address":"185 N Cswy",
    "sg:city":"New Smyrna Beach",
    "sg:classifiers":[
        {
            "category":"Sports & Exercise",
            "subcategory":"Bowling",
            "type":"Entertainment"
        }
    ],
    "sg:phone":"+1 386 428 4332",
    "sg:postcode":"32169",
    "sg:province":"FL",
    "sg:tags":[
        "center"
    ],
    "wof:name":"New Smyrna Lanes",
    "wof:placetype":"venue"
},
  "geometry": {"coordinates":[-80.915633,29.033314],"type":"Point"}
}