{
  "type": "Feature",
  "properties": {
    "iso:country":"US",
    "sg:address":"2751 Patty Ln",
    "sg:city":"Melbourne",
    "sg:classifiers":[
        {
            "category":"Retail",
            "subcategory":"Repair Shop",
            "type":"Services"
        }
    ],
    "sg:phone":"+1 321 259 5625",
    "sg:postcode":"32935",
    "sg:province":"FL",
    "sg:tags":[
        "lock",
        "locksmith"
    ],
    "wof:name":"Melbourne Lock & Key",
    "wof:placetype":"venue"
},
  "geometry": {"coordinates":[-80.668955,28.123455],"type":"Point"}
}