{
  "type": "Feature",
  "properties": {
    "iso:country":"US",
    "sg:address":"12256 Park Ave",
    "sg:city":"Windermere",
    "sg:classifiers":[
        {
            "category":"Manufacturing",
            "subcategory":"Retail Goods",
            "type":"Manufacturing & Wholesale Goods"
        }
    ],
    "sg:phone":"+1 407 876 6075",
    "sg:postcode":"34786",
    "sg:province":"FL",
    "sg:tags":[
        "product",
        "mfg"
    ],
    "wof:name":"Internet Industries LLC",
    "wof:placetype":"venue"
},
  "geometry": {"coordinates":[-81.567684,28.498791],"type":"Point"}
}