{
  "type": "Feature",
  "properties": {
    "iso:country":"US",
    "sg:address":"696 Rochester Dr",
    "sg:city":"Melbourne",
    "sg:classifiers":[
        {
            "category":"Building & Trades",
            "subcategory":"Construction",
            "type":"Services"
        }
    ],
    "sg:phone":"+1 321 725 7240",
    "sg:postcode":"32904",
    "sg:province":"FL",
    "wof:name":"Lifestyle Homes",
    "wof:placetype":"venue"
},
  "geometry": {"coordinates":[-80.65125,28.066732],"type":"Point"}
}