{
  "type": "Feature",
  "properties": {
    "iso:country":"US",
    "sg:address":"1301 E International Speedway Blvd",
    "sg:city":"Deland",
    "sg:classifiers":[
        {
            "category":"Building & Trades",
            "subcategory":"Construction",
            "type":"Services"
        }
    ],
    "sg:phone":"+1 386 943 8358",
    "sg:postcode":"32724",
    "sg:province":"FL",
    "sg:tags":[
        "general",
        "contractor"
    ],
    "wof:name":"Turbine Truck Engines Inc",
    "wof:placetype":"venue"
},
  "geometry": {"coordinates":[-81.280689,29.055654],"type":"Point"}
}