{
  "type": "Feature",
  "properties": {
    "addr:full":"3528 Westerham Dr Clermont FL 34711",
    "addr:postcode":"3528;34711",
    "addr:street":"Westerham Dr",
    "iso:country":"US",
    "sg:address":"3528 Westerham Dr",
    "sg:city":"Clermont",
    "sg:classifiers":[
        {
            "category":"Insurance",
            "subcategory":"Insurance Agent",
            "type":"Services"
        }
    ],
    "sg:phone":"+1 352 241 9776",
    "sg:postcode":"34711",
    "sg:province":"FL",
    "wof:name":"Apple Premium Finance Svc Co",
    "wof:placetype":"venue"
},
  "geometry": {"coordinates":[-81.715236,28.513677],"type":"Point"}
}