{
  "type": "Feature",
  "properties": {
    "iso:country":"US",
    "sg:address":"3952 Northlake Blvd",
    "sg:city":"Palm Beach Gdns",
    "sg:classifiers":[
        {
            "category":"Government",
            "subcategory":"Office",
            "type":"Public Place"
        }
    ],
    "sg:phone":"+1 561 627 0411",
    "sg:postcode":"33403",
    "sg:province":"FL",
    "sg:tags":[
        "armed",
        "force",
        "recruiting"
    ],
    "wof:name":"US Government Army Recruiting",
    "wof:placetype":"venue"
},
  "geometry": {"coordinates":[-80.096937,26.80865],"type":"Point"}
}