{
  "type": "Feature",
  "properties": {
    "iso:country":"US",
    "sg:address":"2614 NW 21st Ter",
    "sg:city":"Miami",
    "sg:classifiers":[
        {
            "category":"Health Services",
            "subcategory":"Doctor",
            "type":"Services"
        },
        {
            "category":"Health Services",
            "subcategory":"Hospital",
            "type":"Services"
        }
    ],
    "sg:phone":"+1 305 779 0386",
    "sg:postcode":"33142",
    "sg:province":"FL",
    "sg:tags":[
        "nursing",
        "consultant",
        "medical",
        "practice",
        "home"
    ],
    "wof:name":"Telemercado, Inc",
    "wof:placetype":"venue"
},
  "geometry": {"coordinates":[-80.238968,25.796138],"type":"Point"}
}