{
  "type": "Feature",
  "properties": {
    "addr:full":"1500 Sheridan St Hollywood FL 33020",
    "addr:housenumber":"1500",
    "addr:postcode":"33020",
    "addr:street":"Sheridan St",
    "iso:country":"US",
    "sg:address":"1500 Sheridan St",
    "sg:city":"Hollywood",
    "sg:classifiers":[
        {
            "category":"Building & Trades",
            "subcategory":"Equipment Rental",
            "type":"Services"
        }
    ],
    "sg:phone":"+1 954 926 2202",
    "sg:postcode":"33020",
    "sg:province":"FL",
    "sg:tags":[
        "leasing"
    ],
    "sg:website":"www.southfloridaleasing.com",
    "wof:name":"South Florida Leasing",
    "wof:placetype":"venue"
},
  "geometry": {"coordinates":[-80.14269899999999,26.033263],"type":"Point"}
}