{
  "type": "Feature",
  "properties": {
    "addr:full":"1918 Mack Lewis Dr Panama City FL 32401",
    "addr:housenumber":"1918",
    "addr:postcode":"32401",
    "addr:street":"Mack Lewis Dr",
    "iso:country":"US",
    "sg:address":"1918 Mack Lewis Dr",
    "sg:city":"Panama City",
    "sg:classifiers":[
        {
            "category":"Government",
            "subcategory":"Office",
            "type":"Public Place"
        }
    ],
    "sg:phone":"+1 850 784 2511",
    "sg:postcode":"32401",
    "sg:province":"FL",
    "sg:tags":[
        "housing",
        "program"
    ],
    "wof:name":"Section Eight Program",
    "wof:placetype":"venue"
},
  "geometry": {"coordinates":[-85.690809,30.173195],"type":"Point"}
}