{
  "type": "Feature",
  "properties": {
    "iso:country":"US",
    "sg:address":"7274 State Rd 54",
    "sg:city":"New Port Richey",
    "sg:classifiers":[
        {
            "category":"Bars & Pubs",
            "type":"Food & Drink"
        }
    ],
    "sg:phone":"+1 727 375 5165",
    "sg:postcode":"34653",
    "sg:province":"FL",
    "wof:name":"Wishing Well Pub",
    "wof:placetype":"venue"
},
  "geometry": {"coordinates":[-82.69364299999999,28.216963],"type":"Point"}
}