{
  "type": "Feature",
  "properties": {
    "addr:full":"1952 San Marco Rd Marco Island FL 34145",
    "addr:housenumber":"1952",
    "addr:postcode":"34145",
    "addr:street":"San Marco Rd",
    "iso:country":"US",
    "sg:address":"1952 San Marco Rd",
    "sg:city":"Marco Island",
    "sg:classifiers":[
        {
            "category":"Professional",
            "subcategory":"Computer Services",
            "type":"Services"
        }
    ],
    "sg:phone":"+1 239 394 5835",
    "sg:postcode":"34145",
    "sg:province":"FL",
    "sg:tags":[
        "system",
        "analysis"
    ],
    "wof:name":"Diversified Science Labs",
    "wof:placetype":"venue"
},
  "geometry": {"coordinates":[-81.69283900000001,25.937387],"type":"Point"}
}