{
  "type": "Feature",
  "properties": {
    "iso:country":"US",
    "sg:address":"7420 Wiles Rd",
    "sg:city":"Pompano Beach",
    "sg:classifiers":[
        {
            "category":"Home & Garden",
            "subcategory":"Mobile Homes",
            "type":"Retail Goods"
        }
    ],
    "sg:phone":"+1 954 755 8880",
    "sg:postcode":"33067",
    "sg:province":"FL",
    "wof:name":"New Homes Sales Realty",
    "wof:placetype":"venue"
},
  "geometry": {"coordinates":[-80.226158,26.28661],"type":"Point"}
}