{
  "type": "Feature",
  "properties": {
    "iso:country":"US",
    "sg:address":"8300 N Nebraska Ave",
    "sg:city":"Tampa",
    "sg:classifiers":[
        {
            "category":"Professional",
            "subcategory":"Computer Services",
            "type":"Services"
        }
    ],
    "sg:phone":"+1 813 931 5580",
    "sg:postcode":"33604",
    "sg:province":"FL",
    "sg:tags":[
        "repair"
    ],
    "wof:name":"Amtote",
    "wof:placetype":"venue"
},
  "geometry": {"coordinates":[-82.45126500000001,28.025185],"type":"Point"}
}