{
  "type": "Feature",
  "properties": {
    "iso:country":"US",
    "sg:address":"3610 Shamrock St W",
    "sg:city":"Tallahassee",
    "sg:classifiers":[
        {
            "category":"Shopping",
            "subcategory":"Florist",
            "type":"Retail Goods"
        }
    ],
    "sg:phone":"+1 850 893 0440",
    "sg:postcode":"32309",
    "sg:province":"FL",
    "wof:name":"Itty Biddy Florist",
    "wof:placetype":"venue"
},
  "geometry": {"coordinates":[-84.22378999999999,30.514443],"type":"Point"}
}