{
  "type": "Feature",
  "properties": {
    "addr:full":"4437 Central Ave Saint Petersburg FL 33713",
    "addr:housenumber":"4437",
    "addr:postcode":"33713",
    "addr:street":"Central Ave",
    "iso:country":"US",
    "sg:address":"4437 Central Ave",
    "sg:city":"Saint Petersburg",
    "sg:classifiers":[
        {
            "category":"Professional",
            "subcategory":"Accounting & Tax Preparation",
            "type":"Services"
        }
    ],
    "sg:phone":"+1 727 327 6979",
    "sg:postcode":"33713",
    "sg:province":"FL",
    "wof:name":"Krodel & Associates",
    "wof:placetype":"venue"
},
  "geometry": {"coordinates":[-82.69397499999999,27.771005],"type":"Point"}
}