{
  "type": "Feature",
  "properties": {
    "iso:country":"US",
    "sg:address":"9921 Atlantic Blvd",
    "sg:city":"Jacksonville",
    "sg:classifiers":[
        {
            "category":"Restaurant",
            "type":"Food & Drink"
        }
    ],
    "sg:phone":"+1 904 721 2131",
    "sg:postcode":"32225",
    "sg:province":"FL",
    "wof:name":"Ole Mexican Restaurant",
    "wof:placetype":"venue"
},
  "geometry": {"coordinates":[-81.54191299999999,30.322523],"type":"Point"}
}