{
  "type": "Feature",
  "properties": {
    "iso:country":"US",
    "sg:address":"13011 Co Rd 101",
    "sg:city":"Oxford",
    "sg:classifiers":[
        {
            "category":"Utilities",
            "subcategory":"Cable",
            "type":"Services"
        }
    ],
    "sg:phone":"+1 352 751 1901",
    "sg:postcode":"34484",
    "sg:province":"FL",
    "sg:tags":[
        "television"
    ],
    "wof:name":"Villages",
    "wof:placetype":"venue"
},
  "geometry": {"coordinates":[-82.016279,28.949741],"type":"Point"}
}