{
  "type": "Feature",
  "properties": {
    "addr:full":"2005 US Hwy 27 Sebring FL 33870",
    "addr:housenumber":"2005",
    "addr:postcode":"33870",
    "addr:street":"Us Hwy 27",
    "iso:country":"US",
    "sg:address":"2005 US Hwy 27",
    "sg:city":"Sebring",
    "sg:classifiers":[
        {
            "category":"Autos & Motor Vehicles",
            "subcategory":"Auto Supplies",
            "type":"Retail Goods"
        }
    ],
    "sg:phone":"+1 863 385 2500",
    "sg:postcode":"33870",
    "sg:province":"FL",
    "sg:tags":[
        "tire"
    ],
    "wof:name":"Yarbrough Tire Svc Inc",
    "wof:placetype":"venue"
},
  "geometry": {"coordinates":[-81.457965,27.47103],"type":"Point"}
}