{
  "type": "Feature",
  "properties": {
    "iso:country":"US",
    "sg:address":"3833 Cleveland Ave Ste B",
    "sg:city":"Fort Myers",
    "sg:classifiers":[
        {
            "category":"Personal",
            "subcategory":"Shoe Repair & Shine",
            "type":"Services"
        }
    ],
    "sg:phone":"+1 239 939 7991",
    "sg:postcode":"33901",
    "sg:province":"FL",
    "wof:name":"Morreale Shoe Repair",
    "wof:placetype":"venue"
},
  "geometry": {"coordinates":[-81.87190200000001,26.606199],"type":"Point"}
}