{
  "type": "Feature",
  "properties": {
    "addr:full":"2901 W McNab Rd Pompano Beach FL 33069",
    "addr:housenumber":"2901",
    "addr:postcode":"33069",
    "addr:street":"W Mcnab Rd",
    "iso:country":"US",
    "sg:address":"2901 W McNab Rd",
    "sg:city":"Pompano Beach",
    "sg:classifiers":[
        {
            "category":"Wholesale",
            "subcategory":"Medical Equipment & Supplies",
            "type":"Manufacturing & Wholesale Goods"
        }
    ],
    "sg:phone":"+1 954 975 0100",
    "sg:postcode":"33069",
    "sg:province":"FL",
    "sg:tags":[
        "ophthalmic",
        "mfg"
    ],
    "wof:name":"Kosh Ophthalmic Inc",
    "wof:placetype":"venue"
},
  "geometry": {"coordinates":[-80.161931,26.21053],"type":"Point"}
}