{
  "type": "Feature",
  "properties": {
    "addr:full":"268 State Hwy 207 East Palatka FL 32131",
    "addr:housenumber":"268",
    "addr:postcode":"32131",
    "addr:street":"State Hwy 207 East",
    "iso:country":"US",
    "sg:address":"268 State Hwy 207",
    "sg:city":"East Palatka",
    "sg:classifiers":[
        {
            "category":"Building & Trades",
            "subcategory":"Equipment Rental",
            "type":"Services"
        }
    ],
    "sg:phone":"+1 386 326 9292",
    "sg:postcode":"32131",
    "sg:province":"FL",
    "sg:tags":[
        "crane"
    ],
    "wof:name":"Grace Crane Svc",
    "wof:placetype":"venue"
},
  "geometry": {"coordinates":[-81.59392200000001,29.659609],"type":"Point"}
}