{
  "type": "Feature",
  "properties": {
    "iso:country":"US",
    "sg:address":"3436 Bee Ridge Rd",
    "sg:city":"Sarasota",
    "sg:classifiers":[
        {
            "category":"Health Services",
            "subcategory":"Chiropractor",
            "type":"Services"
        }
    ],
    "sg:phone":"+1 941 922 8222",
    "sg:postcode":"34239",
    "sg:province":"FL",
    "wof:name":"Sarasota Chiropractic Centre",
    "wof:placetype":"venue"
},
  "geometry": {"coordinates":[-82.50174199999999,27.29872],"type":"Point"}
}