{
  "type": "Feature",
  "properties": {
    "iso:country":"US",
    "sg:address":"796 108th Ave N",
    "sg:city":"Naples",
    "sg:classifiers":[
        {
            "category":"Professional",
            "type":"Services"
        }
    ],
    "sg:phone":"+1 239 596 8900",
    "sg:postcode":"34108",
    "sg:province":"FL",
    "sg:tags":[
        "establishment"
    ],
    "wof:name":"Opus Focus Inc",
    "wof:placetype":"venue"
},
  "geometry": {"coordinates":[-81.80924400000001,26.269587],"type":"Point"}
}