{
  "type": "Feature",
  "properties": {
    "iso:country":"US",
    "sg:address":"10165 US Hwy 1",
    "sg:city":"Port St Lucie",
    "sg:classifiers":[
        {
            "category":"Shopping",
            "subcategory":"Clothing, Apparel, & Fashions",
            "type":"Retail Goods"
        }
    ],
    "sg:phone":"+1 772 398 2284",
    "sg:postcode":"34952",
    "sg:province":"FL",
    "sg:tags":[
        "infant",
        "wear"
    ],
    "wof:name":"Cute Kids",
    "wof:placetype":"venue"
},
  "geometry": {"coordinates":[-80.290556,27.274961],"type":"Point"}
}