{
  "type": "Feature",
  "properties": {
    "iso:country":"US",
    "sg:address":"126 S M St",
    "sg:city":"Lake Worth",
    "sg:classifiers":[
        {
            "category":"Building & Trades",
            "subcategory":"Construction",
            "type":"Services"
        }
    ],
    "sg:phone":"+1 561 533 3862",
    "sg:postcode":"33460",
    "sg:province":"FL",
    "sg:tags":[
        "material",
        "contractor"
    ],
    "wof:name":"Buff It Technologies",
    "wof:placetype":"venue"
},
  "geometry": {"coordinates":[-80.053403,26.613671],"type":"Point"}
}