{
  "type": "Feature",
  "properties": {
    "addr:full":"6112 Jasmine Vine Dr Daytona Beach FL 32128",
    "addr:housenumber":"6112",
    "addr:postcode":"32128",
    "addr:street":"Jasmine Vine Dr",
    "iso:country":"US",
    "sg:address":"6112 Jasmine Vine Dr",
    "sg:city":"Daytona Beach",
    "sg:classifiers":[
        {
            "category":"Wholesale",
            "subcategory":"Non-durable Goods",
            "type":"Manufacturing & Wholesale Goods"
        }
    ],
    "sg:phone":"+1 386 304 9295",
    "sg:postcode":"32128",
    "sg:province":"FL",
    "wof:name":"Paper & Ink Promotions",
    "wof:placetype":"venue"
},
  "geometry": {"coordinates":[-81.032628,29.079888],"type":"Point"}
}