{
  "type": "Feature",
  "properties": {
    "iso:country":"US",
    "sg:address":"3101 Collins Ave",
    "sg:city":"Miami Beach",
    "sg:classifiers":[
        {
            "category":"Travel",
            "subcategory":"Hotels & Motels",
            "type":"Entertainment"
        }
    ],
    "sg:phone":"+1 305 535 1486",
    "sg:postcode":"33140",
    "sg:province":"FL",
    "wof:name":"US2U Inc",
    "wof:placetype":"venue"
},
  "geometry": {"coordinates":[-80.12415900000001,25.806469],"type":"Point"}
}