{
  "type": "Feature",
  "properties": {
    "addr:full":"242 Palm Coast Pkwy NE Palm Coast FL 32137",
    "addr:housenumber":"242",
    "addr:postcode":"32137",
    "addr:street":"Palm Coast Pkwy Ne",
    "iso:country":"US",
    "sg:address":"242 Palm Coast Pkwy NE",
    "sg:city":"Palm Coast",
    "sg:classifiers":[
        {
            "category":"Restaurant",
            "type":"Food & Drink"
        }
    ],
    "sg:phone":"+1 386 446 4843",
    "sg:postcode":"32137",
    "sg:province":"FL",
    "wof:name":"LA Hacienda Mexican Restaurant",
    "wof:placetype":"venue"
},
  "geometry": {"coordinates":[-81.19413900000001,29.562708],"type":"Point"}
}