{
  "type": "Feature",
  "properties": {
    "iso:country":"US",
    "sg:address":"418 Treemonte Dr",
    "sg:city":"Orange City",
    "sg:classifiers":[
        {
            "category":"Health Services",
            "subcategory":"Clinic",
            "type":"Services"
        }
    ],
    "sg:phone":"+1 386 775 2885",
    "sg:postcode":"32763",
    "sg:province":"FL",
    "sg:tags":[
        "home",
        "care"
    ],
    "wof:name":"Home Care Associates",
    "wof:placetype":"venue"
},
  "geometry": {"coordinates":[-81.29998500000001,28.918625],"type":"Point"}
}