{
  "type": "Feature",
  "properties": {
    "iso:country":"US",
    "sg:address":"132 Shady Pkwy",
    "sg:city":"Sarasota",
    "sg:classifiers":[
        {
            "category":"Building & Trades",
            "subcategory":"Construction",
            "type":"Services"
        }
    ],
    "sg:phone":"+1 941 378 4520",
    "sg:postcode":"34232",
    "sg:province":"FL",
    "sg:tags":[
        "finisher",
        "metal"
    ],
    "wof:name":"Finishing Systems Corp",
    "wof:placetype":"venue"
},
  "geometry": {"coordinates":[-82.471091,27.336265],"type":"Point"}
}