{
  "type": "Feature",
  "properties": {
    "iso:country":"US",
    "sg:address":"3332 Lampp Rd",
    "sg:city":"Plant City",
    "sg:classifiers":[
        {
            "category":"Building & Trades",
            "subcategory":"Construction",
            "type":"Services"
        }
    ],
    "sg:phone":"+1 813 759 0800",
    "sg:postcode":"33565",
    "sg:province":"FL",
    "sg:tags":[
        "excavation",
        "contractor"
    ],
    "wof:name":"Timothy D Tindle",
    "wof:placetype":"venue"
},
  "geometry": {"coordinates":[-82.09017299999999,28.055],"type":"Point"}
}