{
  "type": "Feature",
  "properties": {
    "addr:full":"2 Courthouse Sq Kissimmee FL 34741",
    "addr:housenumber":"2",
    "addr:postcode":"34741",
    "addr:street":"Courthouse Sq",
    "iso:country":"US",
    "sg:address":"2 Courthouse Sq",
    "sg:city":"Kissimmee",
    "sg:classifiers":[
        {
            "category":"Government",
            "subcategory":"Court House",
            "type":"Public Place"
        },
        {
            "category":"Government",
            "subcategory":"Office",
            "type":"Public Place"
        }
    ],
    "sg:phone":"+1 407 847 1300",
    "sg:postcode":"34741",
    "sg:province":"FL",
    "sg:tags":[
        "justice",
        "parish",
        "government-county"
    ],
    "sg:website":"http://www.duvalclerk.com",
    "wof:name":"Osceola County County Court",
    "wof:placetype":"venue"
},
  "geometry": {"coordinates":[-81.411011,28.29174],"type":"Point"}
}