{
  "type": "Feature",
  "properties": {
    "addr:full":"1540 W 84th St Hialeah FL 33014",
    "addr:housenumber":"1540",
    "addr:postcode":"33014",
    "addr:street":"W 84Th St",
    "iso:country":"US",
    "sg:address":"1540 W 84th St",
    "sg:city":"Hialeah",
    "sg:classifiers":[
        {
            "category":"Autos & Motor Vehicles",
            "subcategory":"Fuel & Gas Station",
            "type":"Retail Goods"
        }
    ],
    "sg:phone":"+1 786 621 5873",
    "sg:postcode":"33014",
    "sg:province":"FL",
    "wof:name":"Best Corp Investment Llc",
    "wof:placetype":"venue"
},
  "geometry": {"coordinates":[-80.314989,25.898415],"type":"Point"}
}