{
  "type": "Feature",
  "properties": {
    "addr:full":"417 12th St W Bradenton FL 34205",
    "addr:housenumber":"417",
    "addr:postcode":"34205",
    "addr:street":"12Th St W",
    "iso:country":"US",
    "sg:address":"417 12th St W",
    "sg:city":"Bradenton",
    "sg:classifiers":[
        {
            "category":"Professional",
            "subcategory":"Accounting & Tax Preparation",
            "type":"Services"
        }
    ],
    "sg:phone":"+1 941 748 0200",
    "sg:postcode":"34205",
    "sg:province":"FL",
    "sg:tags":[
        "accountant"
    ],
    "wof:name":"Jennifer R Price CPA",
    "wof:placetype":"venue"
},
  "geometry": {"coordinates":[-82.573384,27.495631],"type":"Point"}
}