{
  "type": "Feature",
  "properties": {
    "addr:full":"4629 36th St Orlando FL 32811",
    "addr:housenumber":"4629",
    "addr:postcode":"32811",
    "addr:street":"36Th St",
    "iso:country":"US",
    "sg:address":"4629 36th St",
    "sg:city":"Orlando",
    "sg:classifiers":[
        {
            "category":"Building & Trades",
            "subcategory":"Electrical",
            "type":"Services"
        }
    ],
    "sg:phone":"+1 407 648 4433",
    "sg:postcode":"32811",
    "sg:province":"FL",
    "sg:tags":[
        "electrical",
        "electric",
        "contractor"
    ],
    "wof:name":"Aneco Inc",
    "wof:placetype":"venue"
},
  "geometry": {"coordinates":[-81.434234,28.502667],"type":"Point"}
}