{
  "type": "Feature",
  "properties": {
    "addr:full":"5021 W Tennessee St Tallahassee FL 32304",
    "addr:housenumber":"5021",
    "addr:postcode":"32304",
    "addr:street":"W Tennessee St",
    "iso:country":"US",
    "sg:address":"5021 W Tennessee St",
    "sg:city":"Tallahassee",
    "sg:classifiers":[
        {
            "category":"Autos & Motor Vehicles",
            "subcategory":"Auto Supplies",
            "type":"Retail Goods"
        }
    ],
    "sg:phone":"+1 850 575 9559",
    "sg:postcode":"32304",
    "sg:province":"FL",
    "sg:tags":[
        "automotive",
        "tire"
    ],
    "wof:name":"Berlin Tire Centers",
    "wof:placetype":"venue"
},
  "geometry": {"coordinates":[-84.361602,30.458585],"type":"Point"}
}