{
  "type": "Feature",
  "properties": {
    "iso:country":"US",
    "sg:address":"1357 SW County Road 769",
    "sg:city":"Arcadia",
    "sg:classifiers":[
        {
            "category":"Building & Trades",
            "subcategory":"Plumbing",
            "type":"Services"
        }
    ],
    "sg:phone":"+1 863 491 5434",
    "sg:postcode":"34266",
    "sg:province":"FL",
    "sg:tags":[
        "plumber",
        "industrial",
        "contractors-commercial"
    ],
    "wof:name":"Mercer Plumbing Co",
    "wof:placetype":"venue"
},
  "geometry": {"coordinates":[-81.959091,27.195021],"type":"Point"}
}