{
  "type": "Feature",
  "properties": {
    "addr:full":"2512 Harriman Cir Tallahassee FL 32308",
    "addr:housenumber":"2512",
    "addr:postcode":"32308",
    "addr:street":"Harriman Cir",
    "iso:country":"US",
    "sg:address":"2512 Harriman Cir",
    "sg:city":"Tallahassee",
    "sg:classifiers":[
        {
            "category":"Farming",
            "subcategory":"Livestock Farm",
            "type":"Manufacturing & Wholesale Goods"
        }
    ],
    "sg:phone":"+1 850 385 4489",
    "sg:postcode":"32308",
    "sg:province":"FL",
    "sg:tags":[
        "beef",
        "feedlot",
        "cattle"
    ],
    "wof:name":"Running M Ranch",
    "wof:placetype":"venue"
},
  "geometry": {"coordinates":[-84.25115599999999,30.475042],"type":"Point"}
}