{
  "type": "Feature",
  "properties": {
    "addr:full":"1521 Alton Rd Miami FL 33139",
    "addr:housenumber":"1521",
    "addr:postcode":"33139",
    "addr:street":"Alton Rd",
    "iso:country":"US",
    "sg:address":"1521 Alton Rd",
    "sg:city":"Miami",
    "sg:classifiers":[
        {
            "category":"Professional",
            "subcategory":"Engineering",
            "type":"Services"
        },
        {
            "category":"Professional",
            "type":"Services"
        }
    ],
    "sg:phone":"+1 305 978 4700",
    "sg:postcode":"33139",
    "sg:province":"FL",
    "sg:tags":[
        "engineer"
    ],
    "wof:name":"Midwest Granite Inc",
    "wof:placetype":"venue"
},
  "geometry": {"coordinates":[-80.14106099999999,25.787835],"type":"Point"}
}