{
  "type": "Feature",
  "properties": {
    "addr:full":"3525 NW 7th St Miami FL 33125",
    "addr:housenumber":"3525",
    "addr:postcode":"33125",
    "addr:street":"Nw 7Th St",
    "iso:country":"US",
    "sg:address":"3525 NW 7th St",
    "sg:city":"Miami",
    "sg:classifiers":[
        {
            "category":"Professional",
            "subcategory":"Employment Agencies",
            "type":"Services"
        }
    ],
    "sg:phone":"+1 305 643 6730",
    "sg:postcode":"33125",
    "sg:province":"FL",
    "wof:name":"Youth Co-Op Inc",
    "wof:placetype":"venue"
},
  "geometry": {"coordinates":[-80.253304,25.7789],"type":"Point"}
}