{
  "type": "Feature",
  "properties": {
    "iso:country":"US",
    "sg:address":"5967 W Oakland Park Blvd",
    "sg:city":"Fort Lauderdale",
    "sg:classifiers":[
        {
            "category":"Restaurant",
            "type":"Food & Drink"
        }
    ],
    "sg:menulink":"http://www.allmenus.com/fl/plantation/60806-golden-krust/menu/",
    "sg:phone":"+1 954 760 6448",
    "sg:postcode":"33313",
    "sg:province":"FL",
    "sg:tags":[
        "caribbean"
    ],
    "wof:name":"Golden Krust",
    "wof:placetype":"venue"
},
  "geometry": {"coordinates":[-80.231565,26.164832],"type":"Point"}
}