{
  "type": "Feature",
  "properties": {
    "iso:country":"US",
    "sg:address":"114 Broadway",
    "sg:city":"Kissimmee",
    "sg:classifiers":[
        {
            "category":"Manufacturing",
            "subcategory":"Chemicals & Compounds",
            "type":"Manufacturing & Wholesale Goods"
        },
        {
            "category":"Wholesale",
            "subcategory":"Medical Equipment & Supplies",
            "type":"Manufacturing & Wholesale Goods"
        },
        {
            "category":"Shopping",
            "subcategory":"Pharmacy",
            "type":"Retail Goods"
        }
    ],
    "sg:phone":"+1 407 847 2424",
    "sg:postcode":"34741",
    "sg:province":"FL",
    "sg:tags":[
        "pharmaceutical",
        "product",
        "proprietary",
        "products-wholesale",
        "medicines-patent",
        "manufacturer"
    ],
    "wof:name":"Robinson's Coffee Shop",
    "wof:placetype":"venue"
},
  "geometry": {"coordinates":[-81.40692799999999,28.292689],"type":"Point"}
}