{
  "type": "Feature",
  "properties": {
    "addr:full":"407 W Franklin St Ocoee FL 34761",
    "addr:housenumber":"407",
    "addr:postcode":"34761",
    "addr:street":"W Franklin St",
    "iso:country":"US",
    "sg:address":"407 W Franklin St",
    "sg:city":"Ocoee",
    "sg:classifiers":[
        {
            "category":"Shopping",
            "subcategory":"Computers & Home Electronics",
            "type":"Retail Goods"
        }
    ],
    "sg:phone":"+1 407 656 2358",
    "sg:postcode":"34761",
    "sg:province":"FL",
    "sg:tags":[
        "system"
    ],
    "wof:name":"All-In-One Entertainment",
    "wof:placetype":"venue"
},
  "geometry": {"coordinates":[-81.552119,28.572073],"type":"Point"}
}