{
  "type": "Feature",
  "properties": {
    "iso:country":"US",
    "sg:address":"502 N 30th St",
    "sg:city":"Haines City",
    "sg:classifiers":[
        {
            "category":"Organizations",
            "subcategory":"Religious Organization",
            "type":"Services"
        }
    ],
    "sg:phone":"+1 863 421 0559",
    "sg:postcode":"33844",
    "sg:province":"FL",
    "sg:tags":[
        "church"
    ],
    "wof:name":"First Free Will Baptist Church",
    "wof:placetype":"venue"
},
  "geometry": {"coordinates":[-81.60690099999999,28.114047],"type":"Point"}
}