{
  "type": "Feature",
  "properties": {
    "iso:country":"US",
    "sg:address":"2605 W Lake Mary Blvd",
    "sg:city":"Lake Mary",
    "sg:classifiers":[
        {
            "category":"Manufacturing",
            "subcategory":"Printing",
            "type":"Manufacturing & Wholesale Goods"
        }
    ],
    "sg:phone":"+1 407 688 2000",
    "sg:postcode":"32746",
    "sg:province":"FL",
    "sg:tags":[
        "publisher",
        "software"
    ],
    "wof:name":"Home Retention Intelligence",
    "wof:placetype":"venue"
},
  "geometry": {"coordinates":[-81.325907,28.756044],"type":"Point"}
}