{
  "type": "Feature",
  "properties": {
    "iso:country":"US",
    "sg:address":"10501 San Jose Blvd",
    "sg:city":"Jacksonville",
    "sg:classifiers":[
        {
            "category":"Personal",
            "subcategory":"Beauty Salon",
            "type":"Services"
        }
    ],
    "sg:phone":"+1 904 268 6199",
    "sg:postcode":"32257",
    "sg:province":"FL",
    "sg:tags":[
        "hair",
        "stylist"
    ],
    "sg:website":"http://www.lizchico.com",
    "wof:name":"Cherchez Inc",
    "wof:placetype":"venue"
},
  "geometry": {"coordinates":[-81.627324,30.188679],"type":"Point"}
}