{
  "type": "Feature",
  "properties": {
    "addr:full":"2081 Lake Todd Ct Apopka FL 32712",
    "addr:housenumber":"2081",
    "addr:postcode":"32712",
    "addr:street":"Lake Todd Ct",
    "iso:country":"US",
    "sg:address":"2081 Lake Todd Ct",
    "sg:city":"Apopka",
    "sg:classifiers":[
        {
            "category":"Personal",
            "subcategory":"Beauty Salon",
            "type":"Services"
        }
    ],
    "sg:phone":"+1 407 948 0693",
    "sg:postcode":"32712",
    "sg:province":"FL",
    "sg:tags":[
        "treatment",
        "skin"
    ],
    "wof:name":"One World Wellness Inc",
    "wof:placetype":"venue"
},
  "geometry": {"coordinates":[-81.541678,28.695866],"type":"Point"}
}