{
  "type": "Feature",
  "properties": {
    "addr:full":"150 NW 36th St Miami FL 33127",
    "addr:housenumber":"150",
    "addr:postcode":"33127",
    "addr:street":"Nw 36Th St",
    "iso:country":"US",
    "sg:address":"150 NW 36th St",
    "sg:city":"Miami",
    "sg:classifiers":[
        {
            "category":"Wholesale",
            "subcategory":"Painting Supplies",
            "type":"Manufacturing & Wholesale Goods"
        },
        {
            "category":"Wholesale",
            "subcategory":"Auto Parts",
            "type":"Manufacturing & Wholesale Goods"
        }
    ],
    "sg:phone":"+1 305 573 5224",
    "sg:postcode":"33127",
    "sg:province":"FL",
    "sg:tags":[
        "body",
        "shop",
        "equipment",
        "automobile",
        "paint"
    ],
    "wof:name":"National Oak Distributors",
    "wof:placetype":"venue"
},
  "geometry": {"coordinates":[-80.198402,25.810341],"type":"Point"}
}