{
  "type": "Feature",
  "properties": {
    "addr:full":"304 Monticello Dr Altamonte Springs FL 32701",
    "addr:housenumber":"304",
    "addr:postcode":"32701",
    "addr:street":"Monticello Dr",
    "iso:country":"US",
    "sg:address":"304 Monticello Dr",
    "sg:city":"Altamonte Springs",
    "sg:classifiers":[
        {
            "category":"Autos & Motor Vehicles",
            "subcategory":"Boat Sales",
            "type":"Retail Goods"
        }
    ],
    "sg:phone":"+1 407 339 2532",
    "sg:postcode":"32701",
    "sg:province":"FL",
    "wof:name":"Strother Max Boat Broker",
    "wof:placetype":"venue"
},
  "geometry": {"coordinates":[-81.37809900000001,28.644234],"type":"Point"}
}