{
  "type": "Feature",
  "properties": {
    "addr:full":"426 Eagles Nest Ln Sarasota FL 34243",
    "addr:housenumber":"426",
    "addr:postcode":"34243",
    "addr:street":"Eagles Nest Ln",
    "iso:country":"US",
    "sg:address":"426 Eagles Nest Ln",
    "sg:city":"Sarasota",
    "sg:classifiers":[
        {
            "category":"Wholesale",
            "subcategory":"Drugs",
            "type":"Manufacturing & Wholesale Goods"
        }
    ],
    "sg:phone":"+1 941 780 5023",
    "sg:postcode":"34243",
    "sg:province":"FL",
    "sg:tags":[
        "water",
        "biological",
        "treatment",
        "waster"
    ],
    "wof:name":"Industrial Environmental",
    "wof:placetype":"venue"
},
  "geometry": {"coordinates":[-82.565268,27.39321],"type":"Point"}
}