{
  "type": "Feature",
  "properties": {
    "iso:country":"US",
    "sg:address":"1855 W State Road 434",
    "sg:city":"Longwood",
    "sg:classifiers":[
        {
            "category":"Shopping Center",
            "type":"Public Place"
        }
    ],
    "sg:phone":"+1 407 331 0971",
    "sg:postcode":"32750",
    "sg:province":"FL",
    "sg:tags":[
        "mall"
    ],
    "wof:name":"Longwood Village Shopping Center",
    "wof:placetype":"venue"
},
  "geometry": {"coordinates":[-81.385946,28.692341],"type":"Point"}
}