{
  "type": "Feature",
  "properties": {
    "addr:full":"7807 Cocobay Ct Naples FL 34108",
    "addr:housenumber":"7807",
    "addr:postcode":"34108",
    "addr:street":"Cocobay Ct",
    "iso:country":"US",
    "sg:address":"7807 Cocobay Ct",
    "sg:city":"Naples",
    "sg:classifiers":[
        {
            "category":"Manufacturing",
            "subcategory":"Printing",
            "type":"Manufacturing & Wholesale Goods"
        }
    ],
    "sg:phone":"+1 239 594 9193",
    "sg:postcode":"34108",
    "sg:province":"FL",
    "sg:tags":[
        "publishing"
    ],
    "wof:name":"Ithaka Press Limited Inc",
    "wof:placetype":"venue"
},
  "geometry": {"coordinates":[-81.81258699999999,26.24245],"type":"Point"}
}