{
  "type": "Feature",
  "properties": {
    "addr:full":"5324 Spring Hill Dr Spring Hill FL 34606",
    "addr:housenumber":"5324",
    "addr:postcode":"34606",
    "addr:street":"Spring Hill Dr",
    "iso:country":"US",
    "sg:address":"5324 Spring Hill Dr",
    "sg:city":"Spring Hill",
    "sg:classifiers":[
        {
            "category":"Professional",
            "subcategory":"Advertising",
            "type":"Services"
        }
    ],
    "sg:phone":"+1 352 686 4942",
    "sg:postcode":"34606",
    "sg:province":"FL",
    "sg:tags":[
        "outdoor"
    ],
    "wof:name":"Whistle Stop Station",
    "wof:placetype":"venue"
},
  "geometry": {"coordinates":[-82.62542000000001,28.458791],"type":"Point"}
}