{
  "type": "Feature",
  "properties": {
    "iso:country":"US",
    "sg:address":"1942 Suwanee Ave",
    "sg:city":"Fort Myers",
    "sg:classifiers":[
        {
            "category":"Personal",
            "type":"Services"
        }
    ],
    "sg:phone":"+1 239 690 0200",
    "sg:postcode":"33901",
    "sg:province":"FL",
    "sg:tags":[
        "party",
        "planning",
        "event"
    ],
    "wof:name":"Special Moments by Amparon",
    "wof:placetype":"venue"
},
  "geometry": {"coordinates":[-81.872851,26.606083],"type":"Point"}
}