{
  "type": "Feature",
  "properties": {
    "iso:country":"US",
    "sg:address":"6129 Black Dairy Rd",
    "sg:city":"Seffner",
    "sg:classifiers":[
        {
            "category":"Government",
            "subcategory":"Department Of Motor Vehicles",
            "type":"Public Place"
        }
    ],
    "sg:phone":"+1 813 626 8598",
    "sg:postcode":"33584",
    "sg:province":"FL",
    "sg:tags":[
        "truck",
        "trailer"
    ],
    "wof:name":"Rebel Trailer Services, Inc.",
    "wof:placetype":"venue"
},
  "geometry": {"coordinates":[-82.311375,28.006958],"type":"Point"}
}