{
  "type": "Feature",
  "properties": {
    "addr:full":"11771 SW 181st St Miami FL 33177",
    "addr:housenumber":"11771",
    "addr:postcode":"33177",
    "addr:street":"Sw 181St St",
    "iso:country":"US",
    "sg:address":"11771 SW 181st St",
    "sg:city":"Miami",
    "sg:classifiers":[
        {
            "category":"Retail",
            "subcategory":"Car Wash",
            "type":"Services"
        }
    ],
    "sg:phone":"+1 305 233 6437",
    "sg:postcode":"33177",
    "sg:province":"FL",
    "sg:tags":[
        "carwash"
    ],
    "wof:name":"Dwayne D Greene Car Wash",
    "wof:placetype":"venue"
},
  "geometry": {"coordinates":[-80.381787,25.600626],"type":"Point"}
}