{
  "type": "Feature",
  "properties": {
    "iso:country":"US",
    "sg:address":"10601 Gulf Blvd",
    "sg:city":"Saint Petersburg",
    "sg:classifiers":[
        {
            "category":"Restaurant",
            "type":"Food & Drink"
        }
    ],
    "sg:phone":"+1 727 363 7425",
    "sg:postcode":"33706",
    "sg:province":"FL",
    "sg:tags":[
        "grill",
        "bar"
    ],
    "wof:name":"Ricky TS Bar & Grille Inc",
    "wof:placetype":"venue"
},
  "geometry": {"coordinates":[-82.769222,27.769071],"type":"Point"}
}