{
  "type": "Feature",
  "properties": {
    "iso:country":"US",
    "sg:address":"17451 NE 2 Pl",
    "sg:city":"Williston",
    "sg:classifiers":[
        {
            "category":"Shopping",
            "type":"Retail Goods"
        }
    ],
    "sg:phone":"+1 352 528 4525",
    "sg:postcode":"32696",
    "sg:province":"FL",
    "sg:tags":[
        "art",
        "gallery",
        "dealer"
    ],
    "wof:name":"Ballantine Studio",
    "wof:placetype":"venue"
},
  "geometry": {"coordinates":[-82.505728,29.335061],"type":"Point"}
}