{
  "type": "Feature",
  "properties": {
    "addr:full":"3677 Cocoplum Cir Pompano Beach FL 33063",
    "addr:housenumber":"3677",
    "addr:postcode":"33063",
    "addr:street":"Cocoplum Cir",
    "iso:country":"US",
    "sg:address":"3677 Cocoplum Cir",
    "sg:city":"Pompano Beach",
    "sg:classifiers":[
        {
            "category":"Wholesale",
            "subcategory":"Non-durable Goods",
            "type":"Manufacturing & Wholesale Goods"
        }
    ],
    "sg:phone":"+1 954 973 6614",
    "sg:postcode":"33063",
    "sg:province":"FL",
    "wof:name":"P&D Gutierrez Export Import In",
    "wof:placetype":"venue"
},
  "geometry": {"coordinates":[-80.190175,26.267947],"type":"Point"}
}