{
  "type": "Feature",
  "properties": {
    "iso:country":"US",
    "sg:address":"1535 University Blvd N",
    "sg:city":"Jacksonville",
    "sg:classifiers":[
        {
            "category":"Manufacturing",
            "subcategory":"Furniture",
            "type":"Manufacturing & Wholesale Goods"
        },
        {
            "category":"Home & Garden",
            "subcategory":"Home Furnishings",
            "type":"Retail Goods"
        }
    ],
    "sg:phone":"+1 904 744 5422",
    "sg:postcode":"32211",
    "sg:province":"FL",
    "sg:tags":[
        "manufacture",
        "made",
        "custom",
        "window",
        "treatment",
        "curtain",
        "drapery"
    ],
    "wof:name":"Arlington Interiors Inc",
    "wof:placetype":"venue"
},
  "geometry": {"coordinates":[-81.60252699999999,30.336411],"type":"Point"}
}