{
  "type": "Feature",
  "properties": {
    "addr:full":"6109 Sherwin Dr Port Richey FL 34668",
    "addr:housenumber":"6109",
    "addr:postcode":"34668",
    "addr:street":"Sherwin Dr",
    "iso:country":"US",
    "sg:address":"6109 Sherwin Dr",
    "sg:city":"Port Richey",
    "sg:classifiers":[
        {
            "category":"Manufacturing",
            "subcategory":"Tools & Machinery",
            "type":"Manufacturing & Wholesale Goods"
        }
    ],
    "sg:phone":"+1 727 844 5626",
    "sg:postcode":"34668",
    "sg:province":"FL",
    "sg:tags":[
        "machine",
        "shop"
    ],
    "wof:name":"Graphic Media Products",
    "wof:placetype":"venue"
},
  "geometry": {"coordinates":[-82.71437,28.276518],"type":"Point"}
}