{
  "type": "Feature",
  "properties": {
    "iso:country":"US",
    "sg:address":"2985 45th St",
    "sg:city":"West Palm Beach",
    "sg:classifiers":[
        {
            "category":"Restaurant",
            "type":"Food & Drink"
        }
    ],
    "sg:menulink":"http://www.allmenus.com/fl/riviera-beach/21581-pollo-tropical/menu/",
    "sg:phone":"+1 561 491 6701",
    "sg:postcode":"33407",
    "sg:province":"FL",
    "sg:tags":[
        "new",
        "american"
    ],
    "wof:name":"Pollo Tropical",
    "wof:placetype":"venue"
},
  "geometry": {"coordinates":[-80.098873,26.759588],"type":"Point"}
}