{
  "type": "Feature",
  "properties": {
    "iso:country":"US",
    "sg:address":"1 Florida Park Dr N",
    "sg:city":"Palm Coast",
    "sg:classifiers":[
        {
            "category":"Real Estate",
            "subcategory":"Real Estate Agent",
            "type":"Services"
        }
    ],
    "sg:phone":"+1 386 447 9007",
    "sg:postcode":"32137",
    "sg:province":"FL",
    "sg:tags":[
        "appraiser"
    ],
    "wof:name":"Premiere Consulting & Apprsl",
    "wof:placetype":"venue"
},
  "geometry": {"coordinates":[-81.2075,29.55832],"type":"Point"}
}