{
  "type": "Feature",
  "properties": {
    "iso:country":"US",
    "sg:address":"7100 Beneva Rd",
    "sg:city":"Sarasota",
    "sg:classifiers":[
        {
            "category":"Banks & Credit Unions",
            "subcategory":"Investment Brokerage",
            "type":"Services"
        }
    ],
    "sg:phone":"+1 941 922 4400",
    "sg:postcode":"34233",
    "sg:province":"FL",
    "sg:tags":[
        "security"
    ],
    "sg:website":"www.agewards.com",
    "wof:name":"A G Edwards & Sons Inc",
    "wof:placetype":"venue"
},
  "geometry": {"coordinates":[-82.49768400000001,27.255022],"type":"Point"}
}