{
  "type": "Feature",
  "properties": {
    "addr:full":"2105 Killarney Dr Winter Park FL 32789",
    "addr:housenumber":"2105",
    "addr:postcode":"32789",
    "addr:street":"Killarney Dr",
    "iso:country":"US",
    "sg:address":"2105 Killarney Dr",
    "sg:city":"Winter Park",
    "sg:classifiers":[
        {
            "category":"Building & Trades",
            "subcategory":"Construction",
            "type":"Services"
        }
    ],
    "sg:phone":"+1 407 644 4427",
    "sg:postcode":"32789",
    "sg:province":"FL",
    "sg:tags":[
        "drywall",
        "dry wall",
        "contractor"
    ],
    "wof:name":"Above All Dry Wall Ser",
    "wof:placetype":"venue"
},
  "geometry": {"coordinates":[-81.378426,28.596739],"type":"Point"}
}