{
  "type": "Feature",
  "properties": {
    "iso:country":"US",
    "sg:address":"1647 Bonaventure Blvd",
    "sg:city":"Weston",
    "sg:classifiers":[
        {
            "category":"Home & Garden",
            "subcategory":"Furniture",
            "type":"Retail Goods"
        }
    ],
    "sg:phone":"+1 954 358 6900",
    "sg:postcode":"33326",
    "sg:province":"FL",
    "sg:tags":[
        "store"
    ],
    "wof:name":"Avanti Contemporary Furniture",
    "wof:placetype":"venue"
},
  "geometry": {"coordinates":[-80.377549,26.100215],"type":"Point"}
}