{
  "type": "Feature",
  "properties": {
    "iso:country":"US",
    "sg:address":"1368 Trinidad Ave",
    "sg:city":"Marco Island",
    "sg:classifiers":[
        {
            "category":"Building & Trades",
            "subcategory":"Landscaping Services",
            "type":"Services"
        }
    ],
    "sg:phone":"+1 239 394 6611",
    "sg:postcode":"34145",
    "sg:province":"FL",
    "sg:tags":[
        "lawn",
        "maintenance",
        "grounds"
    ],
    "wof:name":"Island Yard Art",
    "wof:placetype":"venue"
},
  "geometry": {"coordinates":[-81.71170600000001,25.941775],"type":"Point"}
}