{
  "type": "Feature",
  "properties": {
    "iso:country":"US",
    "sg:address":"45 Princewood Ln",
    "sg:city":"Palm Beach Gdns",
    "sg:classifiers":[
        {
            "category":"Professional",
            "subcategory":"Business Services",
            "type":"Services"
        }
    ],
    "sg:phone":"+1 561 694 9477",
    "sg:postcode":"33410",
    "sg:province":"FL",
    "sg:tags":[
        "pool",
        "swimming"
    ],
    "wof:name":"Waterworld Pool Svc",
    "wof:placetype":"venue"
},
  "geometry": {"coordinates":[-80.07629900000001,26.870599],"type":"Point"}
}