{
  "type": "Feature",
  "properties": {
    "iso:country":"US",
    "sg:address":"7444 Chesterfield Rd",
    "sg:city":"Pensacola",
    "sg:classifiers":[
        {
            "category":"Shopping",
            "subcategory":"Used Merchandise",
            "type":"Retail Goods"
        }
    ],
    "sg:phone":"+1 850 455 1590",
    "sg:postcode":"32506",
    "sg:province":"FL",
    "wof:name":"Second Blessings",
    "wof:placetype":"venue"
},
  "geometry": {"coordinates":[-87.311074,30.408515],"type":"Point"}
}