{
  "type": "Feature",
  "properties": {
    "addr:full":"310 Robin Hood Cir Naples FL 34104",
    "addr:housenumber":"310",
    "addr:postcode":"34104",
    "addr:street":"Robin Hood Cir",
    "iso:country":"US",
    "sg:address":"310 Robin Hood Cir",
    "sg:city":"Naples",
    "sg:classifiers":[
        {
            "category":"Home & Garden",
            "subcategory":"Building Materials",
            "type":"Retail Goods"
        }
    ],
    "sg:phone":"+1 239 436 3758",
    "sg:postcode":"34104",
    "sg:province":"FL",
    "sg:tags":[
        "shutter"
    ],
    "wof:name":"All Cleaning & Hurricane",
    "wof:placetype":"venue"
},
  "geometry": {"coordinates":[-81.700338,26.159901],"type":"Point"}
}