{
  "type": "Feature",
  "properties": {
    "iso:country":"US",
    "sg:address":"2005 Gandy Blvd N",
    "sg:city":"St Petersburg",
    "sg:classifiers":[
        {
            "category":"Professional",
            "type":"Services"
        }
    ],
    "sg:phone":"+1 727 563 9712",
    "sg:postcode":"33702",
    "sg:province":"FL",
    "sg:tags":[
        "establishment"
    ],
    "wof:name":"Gateway Business LTD",
    "wof:placetype":"venue"
},
  "geometry": {"coordinates":[-82.653418,27.857779],"type":"Point"}
}