{
  "type": "Feature",
  "properties": {
    "iso:country":"US",
    "sg:address":"176 Oxford Rd",
    "sg:city":"Casselberry",
    "sg:classifiers":[
        {
            "category":"Manufacturing",
            "subcategory":"Electronics",
            "type":"Manufacturing & Wholesale Goods"
        }
    ],
    "sg:phone":"+1 407 331 6333",
    "sg:postcode":"32730",
    "sg:province":"FL",
    "sg:tags":[
        "sound",
        "equipment",
        "system"
    ],
    "sg:website":"www.yrsmidi.com",
    "wof:name":"Yrs Midi Systems",
    "wof:placetype":"venue"
},
  "geometry": {"coordinates":[-81.3395,28.6567],"type":"Point"}
}