{
  "type": "Feature",
  "properties": {
    "iso:country":"US",
    "sg:address":"1720 J and C Blvd",
    "sg:city":"Naples",
    "sg:classifiers":[
        {
            "category":"Home & Garden",
            "subcategory":"Furniture",
            "type":"Retail Goods"
        }
    ],
    "sg:phone":"+1 239 566 3240",
    "sg:postcode":"34109",
    "sg:province":"FL",
    "sg:tags":[
        "manufacture",
        "custom"
    ],
    "wof:name":"Naples Custom Cabinets LLC",
    "wof:placetype":"venue"
},
  "geometry": {"coordinates":[-81.78207,26.22364],"type":"Point"}
}