{
  "type": "Feature",
  "properties": {
    "iso:country":"US",
    "sg:address":"1819 Thacker Ave",
    "sg:city":"Jacksonville",
    "sg:classifiers":[
        {
            "category":"Professional",
            "type":"Services"
        }
    ],
    "sg:phone":"+1 904 838 4026",
    "sg:postcode":"32207",
    "sg:province":"FL",
    "sg:tags":[
        "establishment"
    ],
    "wof:name":"Batson-Cook Co",
    "wof:placetype":"venue"
},
  "geometry": {"coordinates":[-81.652626,30.305534],"type":"Point"}
}