{
  "type": "Feature",
  "properties": {
    "addr:full":"211 N Ridgewood Ave Daytona Beach FL 32114",
    "addr:housenumber":"211",
    "addr:postcode":"32114",
    "addr:street":"N Ridgewood Ave",
    "iso:country":"US",
    "sg:address":"211 N Ridgewood Ave",
    "sg:city":"Daytona Beach",
    "sg:classifiers":[
        {
            "category":"Banks & Credit Unions",
            "subcategory":"Investment Brokerage",
            "type":"Services"
        }
    ],
    "sg:phone":"+1 386 446 3331",
    "sg:postcode":"32114",
    "sg:province":"FL",
    "sg:tags":[
        "consultant",
        "planning",
        "financial"
    ],
    "wof:name":"Strategic Investment Planning",
    "wof:placetype":"venue"
},
  "geometry": {"coordinates":[-81.024219,29.213621],"type":"Point"}
}