{
  "type": "Feature",
  "properties": {
    "addr:full":"3190 S Us Highway 17/92 Casselberry FL 32707",
    "addr:housenumber":"3190;92",
    "addr:postcode":"32707",
    "addr:street":"S Us Highway 17 /",
    "iso:country":"US",
    "sg:address":"3190 S Us Highway 17/92",
    "sg:city":"Casselberry",
    "sg:classifiers":[
        {
            "category":"Deli",
            "type":"Food & Drink"
        }
    ],
    "sg:menulink":"http://www.allmenus.com/fl/casselberry-altamonte-springs/126006-blimpie-subs--sandwiches/menu/",
    "sg:phone":"+1 407 265 9206",
    "sg:postcode":"32707",
    "sg:province":"FL",
    "sg:tags":[
        "wrap",
        "american",
        "sandwich"
    ],
    "wof:name":"Blimpie Subs & Sandwiches",
    "wof:placetype":"venue"
},
  "geometry": {"coordinates":[-81.336243,28.679096],"type":"Point"}
}