{
  "type": "Feature",
  "properties": {
    "iso:country":"US",
    "sg:address":"3301 NW 86th Ave",
    "sg:city":"Pompano Beach",
    "sg:classifiers":[
        {
            "category":"Health Services",
            "subcategory":"Clinic",
            "type":"Services"
        }
    ],
    "sg:phone":"+1 954 341 6188",
    "sg:postcode":"33065",
    "sg:province":"FL",
    "wof:name":"Docteroff Medical Billing Inc",
    "wof:placetype":"venue"
},
  "geometry": {"coordinates":[-80.24047400000001,26.271186],"type":"Point"}
}