{
  "type": "Feature",
  "properties": {
    "addr:full":"1891 SE Manth Ln Port St Lucie FL 34983",
    "addr:housenumber":"1891",
    "addr:postcode":"34983",
    "addr:street":"Se Manth Ln",
    "iso:country":"US",
    "sg:address":"1891 SE Manth Ln",
    "sg:city":"Port St Lucie",
    "sg:classifiers":[
        {
            "category":"Building & Trades",
            "subcategory":"Cleaning & Sanitation",
            "type":"Services"
        }
    ],
    "sg:phone":"+1 772 340 7359",
    "sg:postcode":"34983",
    "sg:province":"FL",
    "sg:tags":[
        "house"
    ],
    "wof:name":"Andel Touch Inc",
    "wof:placetype":"venue"
},
  "geometry": {"coordinates":[-80.334563,27.284464],"type":"Point"}
}