{
  "type": "Feature",
  "properties": {
    "addr:full":"3633 Idle Hour Dr Orlando FL 32822",
    "addr:housenumber":"3633",
    "addr:postcode":"32822",
    "addr:street":"Idle Hour Dr",
    "iso:country":"US",
    "sg:address":"3633 Idle Hour Dr",
    "sg:city":"Orlando",
    "sg:classifiers":[
        {
            "category":"Professional",
            "type":"Services"
        }
    ],
    "sg:phone":"+1 407 277 1800",
    "sg:postcode":"32822",
    "sg:province":"FL",
    "wof:name":"William Saxon Inc",
    "wof:placetype":"venue"
},
  "geometry": {"coordinates":[-81.298861,28.506296],"type":"Point"}
}