{
  "type": "Feature",
  "properties": {
    "addr:full":"1217 N Conrad Ave Sarasota FL 34237",
    "addr:housenumber":"1217",
    "addr:postcode":"34237",
    "addr:street":"N Conrad Ave",
    "iso:country":"US",
    "sg:address":"1217 N Conrad Ave",
    "sg:city":"Sarasota",
    "sg:classifiers":[
        {
            "category":"Professional",
            "subcategory":"Detective & Security Services",
            "type":"Services"
        }
    ],
    "sg:phone":"+1 941 371 7555",
    "sg:postcode":"34237",
    "sg:province":"FL",
    "sg:tags":[
        "car"
    ],
    "wof:name":"Without A Doubt Investigations",
    "wof:placetype":"venue"
},
  "geometry": {"coordinates":[-82.5091,27.350376],"type":"Point"}
}