{
  "type": "Feature",
  "properties": {
    "addr:full":"5812 Twin Oaks Dr Milton FL 32571",
    "addr:housenumber":"5812",
    "addr:postcode":"32571",
    "addr:street":"Twin Oaks Dr",
    "iso:country":"US",
    "sg:address":"5812 Twin Oaks Dr",
    "sg:city":"Milton",
    "sg:classifiers":[
        {
            "category":"Real Estate",
            "subcategory":"Real Estate Agent",
            "type":"Services"
        }
    ],
    "sg:phone":"+1 850 994 0818",
    "sg:postcode":"32571",
    "sg:province":"FL",
    "wof:name":"Metro America Mc Call Realty",
    "wof:placetype":"venue"
},
  "geometry": {"coordinates":[-87.162918,30.647725],"type":"Point"}
}