{
  "type": "Feature",
  "properties": {
    "iso:country":"US",
    "sg:address":"1425 Highfield Dr",
    "sg:city":"Clearwater",
    "sg:classifiers":[
        {
            "category":"Food & Beverages",
            "subcategory":"Candy",
            "type":"Retail Goods"
        }
    ],
    "sg:phone":"+1 727 507 9424",
    "sg:postcode":"33764",
    "sg:province":"FL",
    "wof:name":"Candyland Express Inc",
    "wof:placetype":"venue"
},
  "geometry": {"coordinates":[-82.75626099999999,27.943164],"type":"Point"}
}