{
  "type": "Feature",
  "properties": {
    "iso:country":"US",
    "sg:address":"340 E Adams St",
    "sg:city":"Jacksonville",
    "sg:classifiers":[
        {
            "category":"Professional",
            "subcategory":"Lawyer & Legal Services",
            "type":"Services"
        }
    ],
    "sg:phone":"+1 904 354 4910",
    "sg:postcode":"32202",
    "sg:province":"FL",
    "sg:tags":[
        "attorney"
    ],
    "wof:name":"Donald G Nichols Law Office",
    "wof:placetype":"venue"
},
  "geometry": {"coordinates":[-81.652956,30.326668],"type":"Point"}
}