{
  "type": "Feature",
  "properties": {
    "addr:full":"4468 Golf Club Ln Spring Hill FL 34609",
    "addr:housenumber":"4468",
    "addr:postcode":"34609",
    "addr:street":"Golf Club Ln",
    "iso:country":"US",
    "sg:address":"4468 Golf Club Ln",
    "sg:city":"Spring Hill",
    "sg:classifiers":[
        {
            "category":"Real Estate",
            "subcategory":"Real Estate Agent",
            "type":"Services"
        }
    ],
    "sg:phone":"+1 352 585 1716",
    "sg:postcode":"34609",
    "sg:province":"FL",
    "wof:name":"Gpt Group LLC",
    "wof:placetype":"venue"
},
  "geometry": {"coordinates":[-82.48378700000001,28.498326],"type":"Point"}
}