{
  "type": "Feature",
  "properties": {
    "iso:country":"US",
    "sg:address":"751 Cypress Gardens Blvd",
    "sg:city":"Winter Haven",
    "sg:classifiers":[
        {
            "category":"Insurance",
            "subcategory":"Insurance Agent",
            "type":"Services"
        }
    ],
    "sg:phone":"+1 863 294 7637",
    "sg:postcode":"33880",
    "sg:province":"FL",
    "wof:name":"Allstate",
    "wof:placetype":"venue"
},
  "geometry": {"coordinates":[-81.714552,28.003968],"type":"Point"}
}