{
  "type": "Feature",
  "properties": {
    "iso:country":"US",
    "sg:address":"6428 Massachusetts Ave",
    "sg:city":"New Port Richey",
    "sg:classifiers":[
        {
            "category":"Shopping",
            "type":"Retail Goods"
        }
    ],
    "sg:phone":"+1 727 849 0135",
    "sg:postcode":"34653",
    "sg:province":"FL",
    "sg:tags":[
        "test",
        "aids",
        "provides",
        "hearing"
    ],
    "wof:name":"Hearusa Inc",
    "wof:placetype":"venue"
},
  "geometry": {"coordinates":[-82.710013,28.258638],"type":"Point"}
}