{
  "type": "Feature",
  "properties": {
    "addr:full":"1625 Wells Rd Orange Park FL 32073",
    "addr:housenumber":"1625",
    "addr:postcode":"32073",
    "addr:street":"Wells Rd",
    "iso:country":"US",
    "sg:address":"1625 Wells Rd",
    "sg:city":"Orange Park",
    "sg:classifiers":[
        {
            "category":"Bakery",
            "type":"Food & Drink"
        }
    ],
    "sg:menulink":"http://www.allmenus.com/fl/orange-park/39467-sweet-tomatoes/menu/",
    "sg:phone":"+1 904 269 6116",
    "sg:postcode":"32073",
    "sg:province":"FL",
    "sg:tags":[
        "soup",
        "american",
        "pastry",
        "salad"
    ],
    "wof:name":"Sweet Tomatoes",
    "wof:placetype":"venue"
},
  "geometry": {"coordinates":[-81.723372,30.187548],"type":"Point"}
}