{
  "type": "Feature",
  "properties": {
    "iso:country":"US",
    "sg:address":"5057 Ocean Blvd",
    "sg:city":"Sarasota",
    "sg:classifiers":[
        {
            "category":"Personal",
            "subcategory":"Beauty Salon",
            "type":"Services"
        }
    ],
    "sg:phone":"+1 941 349 5257",
    "sg:postcode":"34242",
    "sg:province":"FL",
    "sg:tags":[
        "shop"
    ],
    "wof:name":"Salon Capelli",
    "wof:placetype":"venue"
},
  "geometry": {"coordinates":[-82.564218,27.277069],"type":"Point"}
}