{
  "type": "Feature",
  "properties": {
    "addr:full":"5710 E Broadway Ave Tampa FL 33619",
    "addr:housenumber":"5710",
    "addr:postcode":"33619",
    "addr:street":"E Broadway Ave",
    "iso:country":"US",
    "sg:address":"5710 E Broadway Ave",
    "sg:city":"Tampa",
    "sg:classifiers":[
        {
            "category":"Building & Trades",
            "subcategory":"Construction",
            "type":"Services"
        }
    ],
    "sg:phone":"+1 813 663 0604",
    "sg:postcode":"33619",
    "sg:province":"FL",
    "sg:tags":[
        "tile",
        "dealer"
    ],
    "wof:name":"A & D Granite & Tile Co",
    "wof:placetype":"venue"
},
  "geometry": {"coordinates":[-82.390608,27.964723],"type":"Point"}
}