{
  "type": "Feature",
  "properties": {
    "iso:country":"US",
    "sg:address":"9721 Fontainebleau Blvd",
    "sg:city":"Miami",
    "sg:classifiers":[
        {
            "category":"Real Estate",
            "subcategory":"Real Estate Operator",
            "type":"Services"
        }
    ],
    "sg:phone":"+1 305 221 8400",
    "sg:postcode":"33172",
    "sg:province":"FL",
    "sg:tags":[
        "condominium"
    ],
    "wof:name":"Soleil At Fontainbleau",
    "wof:placetype":"venue"
},
  "geometry": {"coordinates":[-80.348248,25.773334],"type":"Point"}
}