{
  "type": "Feature",
  "properties": {
    "addr:full":"201 SE 2nd Ave Gainesville FL 32601",
    "addr:housenumber":"201",
    "addr:postcode":"32601",
    "addr:street":"Se 2Nd Ave",
    "iso:country":"US",
    "sg:address":"201 SE 2nd Ave",
    "sg:city":"Gainesville",
    "sg:classifiers":[
        {
            "category":"Restaurant",
            "type":"Food & Drink"
        }
    ],
    "sg:menulink":"http://www.allmenus.com/fl/gainesville/257790-101-downtown/menu/",
    "sg:phone":"+1 352 376 4177",
    "sg:postcode":"32601",
    "sg:province":"FL",
    "sg:tags":[
        "new",
        "american"
    ],
    "wof:name":"101 Downtown",
    "wof:placetype":"venue"
},
  "geometry": {"coordinates":[-82.323019,29.650226],"type":"Point"}
}