{
  "type": "Feature",
  "properties": {
    "addr:full":"2691 NW 5th Ave Miami FL 33127",
    "addr:housenumber":"2691",
    "addr:postcode":"33127",
    "addr:street":"Nw 5Th Ave",
    "iso:country":"US",
    "sg:address":"2691 NW 5th Ave",
    "sg:city":"Miami",
    "sg:classifiers":[
        {
            "category":"Shopping",
            "subcategory":"Clothing, Apparel, & Fashions",
            "type":"Retail Goods"
        }
    ],
    "sg:phone":"+1 305 438 0966",
    "sg:postcode":"33127",
    "sg:province":"FL",
    "sg:tags":[
        "clothing",
        "glove",
        "store"
    ],
    "wof:name":"Lim Heung",
    "wof:placetype":"venue"
},
  "geometry": {"coordinates":[-80.20310000000001,25.801808],"type":"Point"}
}