{
  "type": "Feature",
  "properties": {
    "addr:full":"802 Old Dixie Hwy Lake Park FL 33403",
    "addr:housenumber":"802",
    "addr:postcode":"33403",
    "addr:street":"Old Dixie Hwy",
    "iso:country":"US",
    "sg:address":"802 Old Dixie Hwy",
    "sg:city":"Lake Park",
    "sg:classifiers":[
        {
            "category":"Autos & Motor Vehicles",
            "subcategory":"Automobile Sales",
            "type":"Retail Goods"
        }
    ],
    "sg:phone":"+1 561 863 9877",
    "sg:postcode":"33403",
    "sg:province":"FL",
    "sg:tags":[
        "car",
        "dealer"
    ],
    "wof:name":"Old Dixie Motor Car Sales Corp",
    "wof:placetype":"venue"
},
  "geometry": {"coordinates":[-80.075335,26.799613],"type":"Point"}
}