{
  "type": "Feature",
  "properties": {
    "addr:full":"700 Oak St Daytona Beach FL 32127",
    "addr:housenumber":"700",
    "addr:postcode":"32127",
    "addr:street":"Oak St",
    "iso:country":"US",
    "sg:address":"700 Oak St",
    "sg:city":"Daytona Beach",
    "sg:classifiers":[
        {
            "category":"Building & Trades",
            "subcategory":"Construction",
            "type":"Services"
        }
    ],
    "sg:phone":"+1 386 767 0711",
    "sg:postcode":"32127",
    "sg:province":"FL",
    "sg:tags":[
        "contractor"
    ],
    "wof:name":"Atlas Glass of Port Orange",
    "wof:placetype":"venue"
},
  "geometry": {"coordinates":[-80.990641,29.136797],"type":"Point"}
}