{
  "type": "Feature",
  "properties": {
    "iso:country":"US",
    "sg:address":"1069 NE 204th Ter",
    "sg:city":"Miami",
    "sg:classifiers":[
        {
            "category":"Building & Trades",
            "subcategory":"Plumbing",
            "type":"Services"
        }
    ],
    "sg:phone":"+1 305 651 3833",
    "sg:postcode":"33179",
    "sg:province":"FL",
    "sg:tags":[
        "contractor"
    ],
    "wof:name":"Dixie Mechanical Inc",
    "wof:placetype":"venue"
},
  "geometry": {"coordinates":[-80.18165,25.963242],"type":"Point"}
}