{
  "type": "Feature",
  "properties": {
    "addr:full":"4320 15th St E Bradenton FL 34208",
    "addr:housenumber":"4320",
    "addr:postcode":"34208",
    "addr:street":"15Th St",
    "iso:country":"US",
    "sg:address":"4320 15th St E",
    "sg:city":"Bradenton",
    "sg:classifiers":[
        {
            "category":"Autos & Motor Vehicles",
            "subcategory":"Automobile Sales",
            "type":"Retail Goods"
        }
    ],
    "sg:phone":"+1 941 753 4705",
    "sg:postcode":"34208",
    "sg:province":"FL",
    "sg:tags":[
        "repair",
        "used",
        "parts",
        "new",
        "fabrication",
        "trailer",
        "welding"
    ],
    "wof:name":"Bluegrass Industries Inc",
    "wof:placetype":"venue"
},
  "geometry": {"coordinates":[-82.54672600000001,27.463748],"type":"Point"}
}