{
  "type": "Feature",
  "properties": {
    "iso:country":"US",
    "sg:address":"1220 W Vine St",
    "sg:city":"Kissimmee",
    "sg:classifiers":[
        {
            "category":"Restaurant",
            "type":"Food & Drink"
        }
    ],
    "sg:menulink":"http://www.allmenus.com/fl/kissimmee/42006-subway/menu/",
    "sg:phone":"+1 407 933 1483",
    "sg:postcode":"34741",
    "sg:province":"FL",
    "sg:tags":[
        "american",
        "sandwich"
    ],
    "wof:name":"Subway",
    "wof:placetype":"venue"
},
  "geometry": {"coordinates":[-81.416393,28.304435],"type":"Point"}
}