{
  "type": "Feature",
  "properties": {
    "iso:country":"US",
    "sg:address":"10031 N Dale Mabry Hwy",
    "sg:city":"Tampa",
    "sg:classifiers":[
        {
            "category":"Health Services",
            "subcategory":"Chiropractor",
            "type":"Services"
        }
    ],
    "sg:phone":"+1 813 968 5404",
    "sg:postcode":"33618",
    "sg:province":"FL",
    "sg:tags":[
        "chiropractic"
    ],
    "wof:name":"Chiropractic Life Center",
    "wof:placetype":"venue"
},
  "geometry": {"coordinates":[-82.50479,28.040222],"type":"Point"}
}