{
  "type": "Feature",
  "properties": {
    "addr:full":"3775 Hield Rd Melbourne FL 32904",
    "addr:housenumber":"3775",
    "addr:postcode":"32904",
    "addr:street":"Hield Rd",
    "iso:country":"US",
    "sg:address":"3775 Hield Rd",
    "sg:city":"Melbourne",
    "sg:classifiers":[
        {
            "category":"Farming",
            "subcategory":"Orchard",
            "type":"Manufacturing & Wholesale Goods"
        }
    ],
    "sg:phone":"+1 321 951 7428",
    "sg:postcode":"32904",
    "sg:province":"FL",
    "sg:tags":[
        "citrus",
        "grove",
        "fruit"
    ],
    "wof:name":"Jeff Citrus",
    "wof:placetype":"venue"
},
  "geometry": {"coordinates":[-80.68691200000001,28.038879],"type":"Point"}
}