{
  "type": "Feature",
  "properties": {
    "iso:country":"US",
    "sg:address":"817 SE 9th St",
    "sg:city":"Deerfield Beach",
    "sg:classifiers":[
        {
            "category":"Health Services",
            "subcategory":"Clinic",
            "type":"Services"
        }
    ],
    "sg:phone":"+1 954 421 0703",
    "sg:postcode":"33441",
    "sg:province":"FL",
    "sg:tags":[
        "colonic",
        "irrigation"
    ],
    "wof:name":"A Colon Care Ctr",
    "wof:placetype":"venue"
},
  "geometry": {"coordinates":[-80.092934,26.306282],"type":"Point"}
}