{
  "type": "Feature",
  "properties": {
    "iso:country":"US",
    "sg:address":"882 SE Damask Ave",
    "sg:city":"Port Saint Lucie",
    "sg:classifiers":[
        {
            "category":"Building & Trades",
            "subcategory":"Construction",
            "type":"Services"
        }
    ],
    "sg:phone":"+1 772 336 1742",
    "sg:postcode":"34983",
    "sg:province":"FL",
    "sg:tags":[
        "house"
    ],
    "wof:name":"Forrest Builders Inc",
    "wof:placetype":"venue"
},
  "geometry": {"coordinates":[-80.32653999999999,27.293051],"type":"Point"}
}