{
  "type": "Feature",
  "properties": {
    "iso:country":"US",
    "sg:address":"1181 Sunset Strip",
    "sg:city":"Sunrise",
    "sg:classifiers":[
        {
            "category":"Retail",
            "subcategory":"Auto Repair",
            "type":"Services"
        }
    ],
    "sg:phone":"+1 954 316 8930",
    "sg:postcode":"33313",
    "sg:province":"FL",
    "sg:tags":[
        "repairing",
        "automobile"
    ],
    "wof:name":"B Auto Tech & Tires",
    "wof:placetype":"venue"
},
  "geometry": {"coordinates":[-80.231527,26.13854],"type":"Point"}
}