{
  "type": "Feature",
  "properties": {
    "addr:full":"8727 Phillips Hwy Jacksonville FL 32256",
    "addr:housenumber":"8727",
    "addr:postcode":"32256",
    "addr:street":"Phillips Hwy",
    "iso:country":"US",
    "sg:address":"8727 Phillips Hwy",
    "sg:city":"Jacksonville",
    "sg:classifiers":[
        {
            "category":"Insurance",
            "subcategory":"Insurance Agent",
            "type":"Services"
        }
    ],
    "sg:phone":"+1 904 732 7353",
    "sg:postcode":"32256",
    "sg:province":"FL",
    "wof:name":"Florida All Lines Insurance Co",
    "wof:placetype":"venue"
},
  "geometry": {"coordinates":[-81.57799300000001,30.208059],"type":"Point"}
}