{
  "type": "Feature",
  "properties": {
    "iso:country":"US",
    "sg:address":"1364 Palmetto St",
    "sg:city":"Clearwater",
    "sg:classifiers":[
        {
            "category":"Professional",
            "subcategory":"Business Services",
            "type":"Services"
        }
    ],
    "sg:phone":"+1 727 442 6106",
    "sg:postcode":"33755",
    "sg:province":"FL",
    "wof:name":"Marlo & Mollee Enterprises",
    "wof:placetype":"venue"
},
  "geometry": {"coordinates":[-82.78313,27.975498],"type":"Point"}
}