{
  "type": "Feature",
  "properties": {
    "addr:full":"600 N Thacker Ave Kissimmee FL 34741",
    "addr:housenumber":"600",
    "addr:postcode":"34741",
    "addr:street":"N Thacker Ave",
    "iso:country":"US",
    "sg:address":"600 N Thacker Ave",
    "sg:city":"Kissimmee",
    "sg:classifiers":[
        {
            "category":"Insurance",
            "subcategory":"Insurance Agent",
            "type":"Services"
        },
        {
            "category":"Insurance",
            "subcategory":"Hazard Insurance",
            "type":"Services"
        },
        {
            "category":"Insurance",
            "subcategory":"Title Insurance",
            "type":"Services"
        },
        {
            "category":"Insurance",
            "subcategory":"Life Insurance",
            "type":"Services"
        }
    ],
    "sg:phone":"+1 407 933 1121",
    "sg:postcode":"34741",
    "sg:province":"FL",
    "sg:tags":[
        "business",
        "auto",
        "commercial",
        "homeowner",
        "motorcycle",
        "renter"
    ],
    "wof:name":"Allstate Insurance Company - Revels Dale",
    "wof:placetype":"venue"
},
  "geometry": {"coordinates":[-81.424278,28.298198],"type":"Point"}
}