{
  "type": "Feature",
  "properties": {
    "iso:country":"US",
    "sg:address":"99 NE 4th St",
    "sg:city":"Miami",
    "sg:classifiers":[
        {
            "category":"Government",
            "subcategory":"Court House",
            "type":"Public Place"
        }
    ],
    "sg:phone":"+1 305 530 7888",
    "sg:postcode":"33132",
    "sg:province":"FL",
    "sg:tags":[
        "justice"
    ],
    "wof:name":"U S District Court",
    "wof:placetype":"venue"
},
  "geometry": {"coordinates":[-80.19206200000001,25.778049],"type":"Point"}
}