{
  "type": "Feature",
  "properties": {
    "iso:country":"US",
    "sg:address":"1755 NW 21st Ter",
    "sg:city":"Miami",
    "sg:classifiers":[
        {
            "category":"Retail",
            "subcategory":"Auto Repair",
            "type":"Services"
        }
    ],
    "sg:phone":"+1 305 325 8351",
    "sg:postcode":"33142",
    "sg:province":"FL",
    "sg:tags":[
        "repairing",
        "automobile",
        "general"
    ],
    "wof:name":"Lilo Auto Repair",
    "wof:placetype":"venue"
},
  "geometry": {"coordinates":[-80.22439,25.796632],"type":"Point"}
}