{
  "type": "Feature",
  "properties": {
    "iso:country":"US",
    "sg:address":"5053 126th Ave N",
    "sg:city":"Clearwater",
    "sg:classifiers":[
        {
            "category":"Freight",
            "type":"Transportation"
        }
    ],
    "sg:phone":"+1 727 540 0098",
    "sg:postcode":"33760",
    "sg:province":"FL",
    "sg:tags":[
        "building",
        "nonresidential",
        "opera",
        "general",
        "warehouse",
        "public"
    ],
    "wof:name":"Sunshine Industrial Park Inc",
    "wof:placetype":"venue"
},
  "geometry": {"coordinates":[-82.70230599999999,27.88648],"type":"Point"}
}