{
  "type": "Feature",
  "properties": {
    "addr:full":"225 Mooring Line Dr Naples FL 34102",
    "addr:housenumber":"225",
    "addr:postcode":"34102",
    "addr:street":"Mooring Line Dr",
    "iso:country":"US",
    "sg:address":"225 Mooring Line Dr",
    "sg:city":"Naples",
    "sg:classifiers":[
        {
            "category":"Organizations",
            "subcategory":"Community Association",
            "type":"Services"
        }
    ],
    "sg:phone":"+1 239 434 7559",
    "sg:postcode":"34102",
    "sg:province":"FL",
    "wof:name":"Friends of Gummi Inc",
    "wof:placetype":"venue"
},
  "geometry": {"coordinates":[-81.807418,26.172631],"type":"Point"}
}