{
  "type": "Feature",
  "properties": {
    "iso:country":"US",
    "sg:address":"7601 N 9th Ave",
    "sg:city":"Pensacola",
    "sg:classifiers":[
        {
            "category":"Real Estate",
            "subcategory":"Real Estate Operator",
            "type":"Services"
        }
    ],
    "sg:phone":"+1 850 477 4574",
    "sg:postcode":"32514",
    "sg:province":"FL",
    "sg:tags":[
        "apartment"
    ],
    "wof:name":"Jasmine Park Apartments",
    "wof:placetype":"venue"
},
  "geometry": {"coordinates":[-87.183764,30.50234],"type":"Point"}
}