{
  "type": "Feature",
  "properties": {
    "iso:country":"US",
    "sg:address":"13411 Ashcroft Landing Ct",
    "sg:city":"Jacksonville",
    "sg:classifiers":[
        {
            "category":"Shopping",
            "subcategory":"Computers & Home Electronics",
            "type":"Retail Goods"
        }
    ],
    "sg:phone":"+1 904 221 7686",
    "sg:postcode":"32225",
    "sg:province":"FL",
    "sg:tags":[
        "equipment",
        "dealer"
    ],
    "wof:name":"GHA Technologies",
    "wof:placetype":"venue"
},
  "geometry": {"coordinates":[-81.461169,30.32921],"type":"Point"}
}