{
  "type": "Feature",
  "properties": {
    "addr:full":"1661 W 2nd Ave Hialeah FL 33010",
    "addr:housenumber":"1661",
    "addr:postcode":"33010",
    "addr:street":"W 2Nd Ave",
    "iso:country":"US",
    "sg:address":"1661 W 2nd Ave",
    "sg:city":"Hialeah",
    "sg:classifiers":[
        {
            "category":"Wholesale",
            "subcategory":"Furniture",
            "type":"Manufacturing & Wholesale Goods"
        }
    ],
    "sg:phone":"+1 305 888 3902",
    "sg:postcode":"33010",
    "sg:province":"FL",
    "sg:tags":[
        "seating",
        "company"
    ],
    "wof:name":"Hialeah Grandstand Co",
    "wof:placetype":"venue"
},
  "geometry": {"coordinates":[-80.28579499999999,25.8365],"type":"Point"}
}