{
  "type": "Feature",
  "properties": {
    "addr:full":"850 6th Ave S Jacksonville Bch FL 32250",
    "addr:housenumber":"850",
    "addr:postcode":"32250",
    "addr:street":"6Th Ave S",
    "iso:country":"US",
    "sg:address":"850 6th Ave S",
    "sg:city":"Jacksonville Bch",
    "sg:classifiers":[
        {
            "category":"Social Services",
            "subcategory":"Job Training",
            "type":"Services"
        }
    ],
    "sg:phone":"+1 904 249 8556",
    "sg:postcode":"32250",
    "sg:province":"FL",
    "sg:tags":[
        "retardation",
        "disabled",
        "mental",
        "dev"
    ],
    "wof:name":"Association-Retarded Citizens",
    "wof:placetype":"venue"
},
  "geometry": {"coordinates":[-81.396755,30.281578],"type":"Point"}
}