{
  "type": "Feature",
  "properties": {
    "addr:full":"8246 NE 2nd Ave Miami FL 33138",
    "addr:housenumber":"8246",
    "addr:postcode":"33138",
    "addr:street":"Ne 2Nd Ave",
    "iso:country":"US",
    "sg:address":"8246 NE 2nd Ave",
    "sg:city":"Miami",
    "sg:classifiers":[
        {
            "category":"Insurance",
            "subcategory":"Health Insurance",
            "type":"Services"
        }
    ],
    "sg:phone":"+1 305 754 1435",
    "sg:postcode":"33138",
    "sg:province":"FL",
    "sg:tags":[
        "market"
    ],
    "wof:name":"Florida Baby Food Center",
    "wof:placetype":"venue"
},
  "geometry": {"coordinates":[-80.19305900000001,25.85068],"type":"Point"}
}