{
  "type": "Feature",
  "properties": {
    "addr:full":"3055 State Hwy 60 Okeechobee FL 34972",
    "addr:housenumber":"3055",
    "addr:postcode":"34972",
    "addr:street":"State Hwy 60",
    "iso:country":"US",
    "sg:address":"3055 State Hwy 60",
    "sg:city":"Okeechobee",
    "sg:classifiers":[
        {
            "category":"Food & Beverages",
            "subcategory":"Candy",
            "type":"Retail Goods"
        }
    ],
    "sg:phone":"+1 407 436 1241",
    "sg:postcode":"34972",
    "sg:province":"FL",
    "sg:tags":[
        "confectionery"
    ],
    "wof:name":"Stuckey's Pecan Shoppe",
    "wof:placetype":"venue"
},
  "geometry": {"coordinates":[-80.900144,27.698089],"type":"Point"}
}