{
  "type": "Feature",
  "properties": {
    "addr:full":"229 Ave K SE Winter Haven FL 33880",
    "addr:housenumber":"229",
    "addr:postcode":"33880",
    "addr:street":"Ave K Se",
    "iso:country":"US",
    "sg:address":"229 Ave K SE",
    "sg:city":"Winter Haven",
    "sg:classifiers":[
        {
            "category":"Professional",
            "subcategory":"Accounting & Tax Preparation",
            "type":"Services"
        }
    ],
    "sg:phone":"+1 863 293 8888",
    "sg:postcode":"33880",
    "sg:province":"FL",
    "sg:tags":[
        "accountant"
    ],
    "wof:name":"Dial & Assoc Inc",
    "wof:placetype":"venue"
},
  "geometry": {"coordinates":[-81.724423,28.011369],"type":"Point"}
}