{
  "type": "Feature",
  "properties": {
    "addr:full":"180 Alhambra Way Fort Lauderdale FL 33326",
    "addr:housenumber":"180",
    "addr:postcode":"33326",
    "addr:street":"Alhambra Way",
    "iso:country":"US",
    "sg:address":"180 Alhambra Way",
    "sg:city":"Fort Lauderdale",
    "sg:classifiers":[
        {
            "category":"Professional",
            "type":"Services"
        }
    ],
    "sg:phone":"+1 954 385 1777",
    "sg:postcode":"33326",
    "sg:province":"FL",
    "wof:name":"Bienestar International Inc",
    "wof:placetype":"venue"
},
  "geometry": {"coordinates":[-80.379165,26.128933],"type":"Point"}
}