{
  "type": "Feature",
  "properties": {
    "addr:full":"5948 Frond Way Apollo Beach FL 33572",
    "addr:housenumber":"5948",
    "addr:postcode":"33572",
    "addr:street":"Frond Way",
    "iso:country":"US",
    "sg:address":"5948 Frond Way",
    "sg:city":"Apollo Beach",
    "sg:classifiers":[
        {
            "category":"Wholesale",
            "subcategory":"Construction Materials",
            "type":"Manufacturing & Wholesale Goods"
        }
    ],
    "sg:phone":"+1 813 641 0090",
    "sg:postcode":"33572",
    "sg:province":"FL",
    "sg:tags":[
        "tie",
        "railroad"
    ],
    "wof:name":"Tampa Crosstie & Landscape",
    "wof:placetype":"venue"
},
  "geometry": {"coordinates":[-82.398765,27.762944],"type":"Point"}
}