{
  "type": "Feature",
  "properties": {
    "iso:country":"US",
    "sg:address":"3390 Blanchette Trl",
    "sg:city":"Lake Worth",
    "sg:classifiers":[
        {
            "category":"Building & Trades",
            "subcategory":"Construction",
            "type":"Services"
        }
    ],
    "sg:phone":"+1 561 963 1208",
    "sg:postcode":"33467",
    "sg:province":"FL",
    "sg:tags":[
        "heavy"
    ],
    "wof:name":"South Florida Tractor Service",
    "wof:placetype":"venue"
},
  "geometry": {"coordinates":[-80.181473,26.627033],"type":"Point"}
}