{
  "type": "Feature",
  "properties": {
    "addr:full":"2920 Lee Blvd Lehigh Acres FL 33971",
    "addr:housenumber":"2920",
    "addr:postcode":"33971",
    "addr:street":"Lee Blvd",
    "iso:country":"US",
    "sg:address":"2920 Lee Blvd",
    "sg:city":"Lehigh Acres",
    "sg:classifiers":[
        {
            "category":"Retail",
            "subcategory":"Veterinary Services",
            "type":"Services"
        }
    ],
    "sg:phone":"+1 239 369 0555",
    "sg:postcode":"33971",
    "sg:province":"FL",
    "sg:tags":[
        "veterinarian"
    ],
    "wof:name":"Animal Medical Ctr",
    "wof:placetype":"venue"
},
  "geometry": {"coordinates":[-81.67524299999999,26.617244],"type":"Point"}
}