{
  "type": "Feature",
  "properties": {
    "addr:full":"1660 Market St Weston FL 33326",
    "addr:housenumber":"1660",
    "addr:postcode":"33326",
    "addr:street":"Market St",
    "iso:country":"US",
    "sg:address":"1660 Market St",
    "sg:city":"Weston",
    "sg:classifiers":[
        {
            "category":"Personal",
            "subcategory":"Beauty Salon",
            "type":"Services"
        }
    ],
    "sg:phone":"+1 954 349 9220",
    "sg:postcode":"33326",
    "sg:province":"FL",
    "wof:name":"Helen Charles",
    "wof:placetype":"venue"
},
  "geometry": {"coordinates":[-80.38109900000001,26.097814],"type":"Point"}
}