{
  "type": "Feature",
  "properties": {
    "iso:country":"US",
    "sg:address":"3813 Murrell Rd",
    "sg:city":"Rockledge",
    "sg:classifiers":[
        {
            "category":"Wholesale",
            "subcategory":"Sporting Goods",
            "type":"Manufacturing & Wholesale Goods"
        }
    ],
    "sg:phone":"+1 321 504 6400",
    "sg:postcode":"32955",
    "sg:province":"FL",
    "sg:tags":[
        "equipment",
        "pool",
        "swimming"
    ],
    "wof:name":"Pinch-A-Penny Pool & Patio Spa",
    "wof:placetype":"venue"
},
  "geometry": {"coordinates":[-80.721881,28.292168],"type":"Point"}
}