{
  "type": "Feature",
  "properties": {
    "iso:country":"US",
    "sg:address":"633 NE 167th St",
    "sg:city":"Miami",
    "sg:classifiers":[
        {
            "category":"Banks & Credit Unions",
            "subcategory":"Financial Services",
            "type":"Services"
        }
    ],
    "sg:phone":"+1 305 770 2773",
    "sg:postcode":"33162",
    "sg:province":"FL",
    "sg:tags":[
        "broker",
        "mortgage"
    ],
    "wof:name":"American Dream Financial Realty Inc",
    "wof:placetype":"venue"
},
  "geometry": {"coordinates":[-80.18759900000001,25.928699],"type":"Point"}
}