{
  "type": "Feature",
  "properties": {
    "iso:country":"US",
    "sg:address":"2710 Big John Dr",
    "sg:city":"De Land",
    "sg:classifiers":[
        {
            "category":"Professional",
            "subcategory":"Research",
            "type":"Services"
        }
    ],
    "sg:phone":"+1 386 734 3049",
    "sg:postcode":"32724",
    "sg:province":"FL",
    "sg:tags":[
        "organization",
        "noncommercial"
    ],
    "wof:name":"Medtoxin Laboratories",
    "wof:placetype":"venue"
},
  "geometry": {"coordinates":[-81.23348,29.08094],"type":"Point"}
}