{
  "type": "Feature",
  "properties": {
    "iso:country":"US",
    "sg:address":"2801 E Irlo Bronson Memorial Hwy",
    "sg:city":"Saint Cloud",
    "sg:classifiers":[
        {
            "category":"Shopping",
            "subcategory":"Musical Instruments",
            "type":"Retail Goods"
        }
    ],
    "sg:phone":"+1 407 340 2105",
    "sg:postcode":"34771",
    "sg:province":"FL",
    "wof:name":"Michelle Tribe",
    "wof:placetype":"venue"
},
  "geometry": {"coordinates":[-81.249405,28.24599],"type":"Point"}
}