{
  "type": "Feature",
  "properties": {
    "addr:full":"4667 N University Dr Pompano Beach FL 33067",
    "addr:housenumber":"4667",
    "addr:postcode":"33067",
    "addr:street":"N University Dr",
    "iso:country":"US",
    "sg:address":"4667 N University Dr",
    "sg:city":"Pompano Beach",
    "sg:classifiers":[
        {
            "category":"Professional",
            "type":"Services"
        }
    ],
    "sg:phone":"+1 954 755 7604",
    "sg:postcode":"33067",
    "sg:province":"FL",
    "wof:name":"World Gym Fitness Centers",
    "wof:placetype":"venue"
},
  "geometry": {"coordinates":[-80.25004300000001,26.28927],"type":"Point"}
}