{
  "type": "Feature",
  "properties": {
    "addr:full":"349 Chiquita Ct Kissimmee FL 34758",
    "addr:housenumber":"349",
    "addr:postcode":"34758",
    "addr:street":"Chiquita Ct",
    "iso:country":"US",
    "sg:address":"349 Chiquita Ct",
    "sg:city":"Kissimmee",
    "sg:classifiers":[
        {
            "category":"Autos & Motor Vehicles",
            "subcategory":"Auto Supplies",
            "type":"Retail Goods"
        }
    ],
    "sg:phone":"+1 407 321 1957",
    "sg:postcode":"34758",
    "sg:province":"FL",
    "wof:name":"GK Liner",
    "wof:placetype":"venue"
},
  "geometry": {"coordinates":[-81.471689,28.174251],"type":"Point"}
}