{
  "type": "Feature",
  "properties": {
    "addr:full":"11064 52nd Rd N West Palm Beach FL 33411",
    "addr:housenumber":"11064",
    "addr:postcode":"33411",
    "addr:street":"52Nd Rd N",
    "iso:country":"US",
    "sg:address":"11064 52nd Rd N",
    "sg:city":"West Palm Beach",
    "sg:classifiers":[
        {
            "category":"Building & Trades",
            "subcategory":"Construction",
            "type":"Services"
        }
    ],
    "sg:phone":"+1 561 333 0735",
    "sg:postcode":"33411",
    "sg:province":"FL",
    "sg:tags":[
        "marble",
        "terrazzo"
    ],
    "wof:name":"Marble Tech Inc",
    "wof:placetype":"venue"
},
  "geometry": {"coordinates":[-80.21603399999999,26.754395],"type":"Point"}
}