{
  "type": "Feature",
  "properties": {
    "addr:full":"2455 W Okeechobee Rd Hialeah FL 33010",
    "addr:housenumber":"2455",
    "addr:postcode":"33010",
    "addr:street":"W Okeechobee Rd",
    "iso:country":"US",
    "sg:address":"2455 W Okeechobee Rd",
    "sg:city":"Hialeah",
    "sg:classifiers":[
        {
            "category":"Building & Trades",
            "subcategory":"Locksmith",
            "type":"Services"
        }
    ],
    "sg:phone":"+1 305 428 9393",
    "sg:postcode":"33010",
    "sg:province":"FL",
    "sg:tags":[
        "key"
    ],
    "wof:name":"0 0 0 1 24 Hour A Emerg Locksmith",
    "wof:placetype":"venue"
},
  "geometry": {"coordinates":[-80.30958099999999,25.84466],"type":"Point"}
}