{
  "type": "Feature",
  "properties": {
    "addr:full":"769 South St Daytona Beach FL 32114",
    "addr:housenumber":"769",
    "addr:postcode":"32114",
    "addr:street":"South St",
    "iso:country":"US",
    "sg:address":"769 South St",
    "sg:city":"Daytona Beach",
    "sg:classifiers":[
        {
            "category":"Social Services",
            "subcategory":"Child Care",
            "type":"Services"
        }
    ],
    "sg:phone":"+1 386 258 4456",
    "sg:postcode":"32114",
    "sg:province":"FL",
    "wof:name":"Carl Brinkley Family Education",
    "wof:placetype":"venue"
},
  "geometry": {"coordinates":[-81.027266,29.195119],"type":"Point"}
}