{
  "type": "Feature",
  "properties": {
    "addr:full":"310 Reeves St Kissimmee FL 34747",
    "addr:housenumber":"310",
    "addr:postcode":"34747",
    "addr:street":"Reeves St",
    "iso:country":"US",
    "sg:address":"310 Reeves St",
    "sg:city":"Kissimmee",
    "sg:classifiers":[
        {
            "category":"Building & Trades",
            "subcategory":"Construction",
            "type":"Services"
        }
    ],
    "sg:phone":"+1 407 375 1131",
    "sg:postcode":"34747",
    "sg:province":"FL",
    "sg:tags":[
        "handyman"
    ],
    "wof:name":"Thomas Horn Handyman",
    "wof:placetype":"venue"
},
  "geometry": {"coordinates":[-81.52675000000001,28.323552],"type":"Point"}
}