{
  "type": "Feature",
  "properties": {
    "iso:country":"US",
    "sg:address":"1409 Kingsley Ave",
    "sg:city":"Orange Park",
    "sg:classifiers":[
        {
            "category":"Health Services",
            "subcategory":"Doctor",
            "type":"Services"
        }
    ],
    "sg:phone":"+1 904 264 2297",
    "sg:postcode":"32073",
    "sg:province":"FL",
    "sg:tags":[
        "physician",
        "medical",
        "surgeon"
    ],
    "wof:name":"Choisser Medical Group",
    "wof:placetype":"venue"
},
  "geometry": {"coordinates":[-81.729455,30.164752],"type":"Point"}
}