{
  "type": "Feature",
  "properties": {
    "addr:full":"630 Khyber Ln Venice FL 34293",
    "addr:housenumber":"630",
    "addr:postcode":"34293",
    "addr:street":"Khyber Ln",
    "iso:country":"US",
    "sg:address":"630 Khyber Ln",
    "sg:city":"Venice",
    "sg:classifiers":[
        {
            "category":"Building & Trades",
            "subcategory":"Construction",
            "type":"Services"
        }
    ],
    "sg:phone":"+1 941 493 5385",
    "sg:postcode":"34293",
    "sg:province":"FL",
    "sg:tags":[
        "house"
    ],
    "wof:name":"Ammon Schrock Realty Inc",
    "wof:placetype":"venue"
},
  "geometry": {"coordinates":[-82.356509,27.067386],"type":"Point"}
}