{
  "type": "Feature",
  "properties": {
    "addr:full":"2375 NE 30th Ct Pompano Beach FL 33064",
    "addr:housenumber":"2375",
    "addr:postcode":"33064",
    "addr:street":"Ne 30Th Ct",
    "iso:country":"US",
    "sg:address":"2375 NE 30th Ct",
    "sg:city":"Pompano Beach",
    "sg:classifiers":[
        {
            "category":"Manufacturing",
            "subcategory":"Metals",
            "type":"Manufacturing & Wholesale Goods"
        }
    ],
    "sg:phone":"+1 954 783 7087",
    "sg:postcode":"33064",
    "sg:province":"FL",
    "sg:tags":[
        "cutlery",
        "mfg"
    ],
    "wof:name":"Carving Co Inc",
    "wof:placetype":"venue"
},
  "geometry": {"coordinates":[-80.091571,26.268976],"type":"Point"}
}