{
  "type": "Feature",
  "properties": {
    "addr:full":"11 Black Water Way Ormond Beach FL 32174",
    "addr:housenumber":"11",
    "addr:postcode":"32174",
    "addr:street":"Black Water Way",
    "iso:country":"US",
    "sg:address":"11 Black Water Way",
    "sg:city":"Ormond Beach",
    "sg:classifiers":[
        {
            "category":"Food & Beverages",
            "subcategory":"Specialty",
            "type":"Retail Goods"
        }
    ],
    "sg:phone":"+1 407 832 0825",
    "sg:postcode":"32174",
    "sg:province":"FL",
    "wof:name":"Shape Works Distributor",
    "wof:placetype":"venue"
},
  "geometry": {"coordinates":[-81.137372,29.266869],"type":"Point"}
}