{
  "type": "Feature",
  "properties": {
    "addr:full":"2378 Pine Island Ct Jacksonville FL 32224",
    "addr:housenumber":"2378",
    "addr:postcode":"32224",
    "addr:street":"Pine Island Ct",
    "iso:country":"US",
    "sg:address":"2378 Pine Island Ct",
    "sg:city":"Jacksonville",
    "sg:classifiers":[
        {
            "category":"Restaurant",
            "type":"Food & Drink"
        }
    ],
    "sg:phone":"+1 904 992 2300",
    "sg:postcode":"32224",
    "sg:province":"FL",
    "wof:name":"Mc Donald's",
    "wof:placetype":"venue"
},
  "geometry": {"coordinates":[-81.429163,30.309061],"type":"Point"}
}