{
  "type": "Feature",
  "properties": {
    "iso:country":"US",
    "sg:address":"7440 SW 50th Ter",
    "sg:city":"Miami",
    "sg:classifiers":[
        {
            "category":"Wholesale",
            "subcategory":"Drugs",
            "type":"Manufacturing & Wholesale Goods"
        }
    ],
    "sg:phone":"+1 305 666 7829",
    "sg:postcode":"33155",
    "sg:province":"FL",
    "wof:name":"Pronova Inc",
    "wof:placetype":"venue"
},
  "geometry": {"coordinates":[-80.31608900000001,25.722956],"type":"Point"}
}