{
  "type": "Feature",
  "properties": {
    "iso:country":"US",
    "sg:address":"10361 SW 145th St",
    "sg:city":"Miami",
    "sg:classifiers":[
        {
            "category":"Building & Trades",
            "subcategory":"Landscaping Services",
            "type":"Services"
        }
    ],
    "sg:phone":"+1 305 251 8101",
    "sg:postcode":"33176",
    "sg:province":"FL",
    "wof:name":"Warren G Anderson and Sons",
    "wof:placetype":"venue"
},
  "geometry": {"coordinates":[-80.36216400000001,25.635166],"type":"Point"}
}