{
  "type": "Feature",
  "properties": {
    "iso:country":"US",
    "sg:address":"12205 S Apopka Vineland Rd",
    "sg:city":"Orlando",
    "sg:classifiers":[
        {
            "category":"Travel",
            "subcategory":"Hotels & Motels",
            "type":"Entertainment"
        },
        {
            "category":"Travel",
            "subcategory":"Resort",
            "type":"Entertainment"
        },
        {
            "category":"Sports & Exercise",
            "subcategory":"Ski Resort",
            "type":"Entertainment"
        }
    ],
    "sg:phone":"+1 888 625 5144",
    "sg:postcode":"32836",
    "sg:province":"FL",
    "sg:tags":[
        "corporate",
        "lodging"
    ],
    "sg:website":"http://clk.atdmt.com/NYC/go/249187464/direct/01/",
    "wof:name":"Sheraton Safari Hotel & Suites Lake Buena Vista",
    "wof:placetype":"venue"
},
  "geometry": {"coordinates":[-81.50627299999999,28.387281],"type":"Point"}
}