{
  "type": "Feature",
  "properties": {
    "addr:full":"2975 Bee Ridge Rd Ste C Sarasota FL 34239",
    "addr:housenumber":"2975",
    "addr:postcode":"34239",
    "addr:street":"Bee Ridge Rd Ste C",
    "iso:country":"US",
    "sg:address":"2975 Bee Ridge Rd Ste C",
    "sg:city":"Sarasota",
    "sg:classifiers":[
        {
            "category":"Professional",
            "subcategory":"Management & Consulting",
            "type":"Services"
        },
        {
            "category":"Professional",
            "subcategory":"Engineering",
            "type":"Services"
        }
    ],
    "sg:phone":"+1 941 926 7929",
    "sg:postcode":"34239",
    "sg:province":"FL",
    "sg:tags":[
        "environmental",
        "ecological",
        "engineer",
        "consultant"
    ],
    "sg:website":"http://www.campuspublicationsinc.com",
    "wof:name":"Demaximis Inc",
    "wof:placetype":"venue"
},
  "geometry": {"coordinates":[-82.509731,27.29884],"type":"Point"}
}