{
  "type": "Feature",
  "properties": {
    "addr:full":"3948 3rd St S Jacksonville Beach FL 32250",
    "addr:housenumber":"3948",
    "addr:postcode":"32250",
    "addr:street":"3Rd St S",
    "iso:country":"US",
    "sg:address":"3948 3rd St S",
    "sg:city":"Jacksonville Beach",
    "sg:classifiers":[
        {
            "category":"Building & Trades",
            "subcategory":"Construction",
            "type":"Services"
        }
    ],
    "sg:phone":"+1 770 740 9190",
    "sg:postcode":"32250",
    "sg:province":"FL",
    "sg:tags":[
        "garage",
        "door"
    ],
    "wof:name":"Americas Choice Door Comapny",
    "wof:placetype":"venue"
},
  "geometry": {"coordinates":[-81.38739200000001,30.25898],"type":"Point"}
}