{
  "type": "Feature",
  "properties": {
    "iso:country":"US",
    "sg:address":"11700 NW 18th St",
    "sg:city":"Plantation",
    "sg:classifiers":[
        {
            "category":"Insurance",
            "subcategory":"Insurance Agent",
            "type":"Services"
        }
    ],
    "sg:phone":"+1 954 472 7060",
    "sg:postcode":"33323",
    "sg:province":"FL",
    "sg:tags":[
        "adjuster"
    ],
    "wof:name":"National Claims Services",
    "wof:placetype":"venue"
},
  "geometry": {"coordinates":[-80.304789,26.14813],"type":"Point"}
}