{
  "type": "Feature",
  "properties": {
    "iso:country":"US",
    "sg:address":"2925 Vineland Rd",
    "sg:city":"Kissimmee",
    "sg:classifiers":[
        {
            "category":"Restaurant",
            "type":"Food & Drink"
        }
    ],
    "sg:menulink":"http://www.allmenus.com/fl/kissimmee/44502-fish,-chips--beyond/menu/",
    "sg:phone":"+1 407 396 7888",
    "sg:postcode":"34746",
    "sg:province":"FL",
    "sg:tags":[
        "british"
    ],
    "wof:name":"Fish, Chips & Beyond",
    "wof:placetype":"venue"
},
  "geometry": {"coordinates":[-81.478426,28.33636],"type":"Point"}
}