{
  "type": "Feature",
  "properties": {
    "addr:full":"10491 72nd St N Seminole FL 33777",
    "addr:housenumber":"10491",
    "addr:postcode":"33777",
    "addr:street":"72Nd St N",
    "iso:country":"US",
    "sg:address":"10491 72nd St N",
    "sg:city":"Seminole",
    "sg:classifiers":[
        {
            "category":"Wholesale",
            "subcategory":"Electrical",
            "type":"Manufacturing & Wholesale Goods"
        }
    ],
    "sg:phone":"+1 727 541 7440",
    "sg:postcode":"33777",
    "sg:province":"FL",
    "sg:tags":[
        "parts",
        "electronic"
    ],
    "wof:name":"Hamilton Hallmark",
    "wof:placetype":"venue"
},
  "geometry": {"coordinates":[-82.738366,27.867754],"type":"Point"}
}