{
  "type": "Feature",
  "properties": {
    "addr:full":"7705 NW 48th St Doral FL 33166",
    "addr:housenumber":"7705",
    "addr:postcode":"33166",
    "addr:street":"Nw 48Th St",
    "iso:country":"US",
    "sg:address":"7705 NW 48th St",
    "sg:city":"Doral",
    "sg:classifiers":[
        {
            "category":"Insurance",
            "subcategory":"Insurance Agent",
            "type":"Services"
        }
    ],
    "sg:phone":"+1 305 592 9926",
    "sg:postcode":"33166",
    "sg:province":"FL",
    "wof:name":"National Marketing Group Svcs",
    "wof:placetype":"venue"
},
  "geometry": {"coordinates":[-80.324265,25.817268],"type":"Point"}
}