{
  "type": "Feature",
  "properties": {
    "addr:full":"5182 E Silver Springs Blvd Silver Springs FL 34488",
    "addr:housenumber":"5182",
    "addr:postcode":"34488",
    "addr:street":"E Silver Springs Blvd",
    "iso:country":"US",
    "sg:address":"5182 E Silver Springs Blvd",
    "sg:city":"Silver Springs",
    "sg:classifiers":[
        {
            "category":"Food & Beverages",
            "subcategory":"Groceries & Convenience Stores",
            "type":"Retail Goods"
        }
    ],
    "sg:phone":"+1 352 236 3240",
    "sg:postcode":"34488",
    "sg:province":"FL",
    "wof:name":"Circle K Store",
    "wof:placetype":"venue"
},
  "geometry": {"coordinates":[-82.063896,29.211894],"type":"Point"}
}