{
  "type": "Feature",
  "properties": {
    "addr:full":"4109 Arrow Ridge Pl Kissimmee FL 34741",
    "addr:housenumber":"4109",
    "addr:postcode":"34741",
    "addr:street":"Arrow Ridge Pl",
    "iso:country":"US",
    "sg:address":"4109 Arrow Ridge Pl",
    "sg:city":"Kissimmee",
    "sg:classifiers":[
        {
            "category":"Building & Trades",
            "subcategory":"Construction",
            "type":"Services"
        }
    ],
    "sg:phone":"+1 407 709 8605",
    "sg:postcode":"34741",
    "sg:province":"FL",
    "sg:tags":[
        "contractor"
    ],
    "wof:name":"Sun Drywall Central Florida",
    "wof:placetype":"venue"
},
  "geometry": {"coordinates":[-81.44511799999999,28.314802],"type":"Point"}
}