{
  "type": "Feature",
  "properties": {
    "addr:full":"5221 Galina Cir Lake Worth FL 33463",
    "addr:housenumber":"5221",
    "addr:postcode":"33463",
    "addr:street":"Galina Cir",
    "iso:country":"US",
    "sg:address":"5221 Galina Cir",
    "sg:city":"Lake Worth",
    "sg:classifiers":[
        {
            "category":"Local Transit",
            "type":"Transportation"
        }
    ],
    "sg:phone":"+1 561 964 3508",
    "sg:postcode":"33463",
    "sg:province":"FL",
    "wof:name":"Alfonso's Brothers Inc",
    "wof:placetype":"venue"
},
  "geometry": {"coordinates":[-80.139912,26.601047],"type":"Point"}
}