{
  "type": "Feature",
  "properties": {
    "addr:full":"7850 NW 178th St Hialeah FL 33015",
    "addr:housenumber":"7850",
    "addr:postcode":"33015",
    "addr:street":"Nw 178Th St",
    "iso:country":"US",
    "sg:address":"7850 NW 178th St",
    "sg:city":"Hialeah",
    "sg:classifiers":[
        {
            "category":"Professional",
            "subcategory":"Business Services",
            "type":"Services"
        }
    ],
    "sg:phone":"+1 305 826 0042",
    "sg:postcode":"33015",
    "sg:province":"FL",
    "sg:tags":[
        "appraiser"
    ],
    "wof:name":"State Appraisers Inc",
    "wof:placetype":"venue"
},
  "geometry": {"coordinates":[-80.32745,25.934941],"type":"Point"}
}