{
  "type": "Feature",
  "properties": {
    "iso:country":"US",
    "sg:address":"1197 Gulfstar Dr",
    "sg:city":"Winter Springs",
    "sg:classifiers":[
        {
            "category":"Food & Beverages",
            "subcategory":"Specialty",
            "type":"Retail Goods"
        }
    ],
    "sg:phone":"+1 407 699 9030",
    "sg:postcode":"32708",
    "sg:province":"FL",
    "sg:tags":[
        "health",
        "diet"
    ],
    "wof:name":"Tahitian Noni",
    "wof:placetype":"venue"
},
  "geometry": {"coordinates":[-81.265659,28.688909],"type":"Point"}
}