{
  "type": "Feature",
  "properties": {
    "iso:country":"US",
    "sg:address":"7615 NW 2nd Ave",
    "sg:city":"Miami",
    "sg:classifiers":[
        {
            "category":"Building & Trades",
            "subcategory":"Landscaping Services",
            "type":"Services"
        }
    ],
    "sg:phone":"+1 305 757 3190",
    "sg:postcode":"33150",
    "sg:province":"FL",
    "sg:tags":[
        "aged",
        "homes-institutional"
    ],
    "wof:name":"St Mary Towers Inc",
    "wof:placetype":"venue"
},
  "geometry": {"coordinates":[-80.20086499999999,25.844652],"type":"Point"}
}