{
  "type": "Feature",
  "properties": {
    "addr:full":"8355 NW 53rd St Fl 1 Miami FL 33166",
    "addr:housenumber":"8355;1",
    "addr:postcode":"33166",
    "addr:street":"Nw 53Rd St",
    "iso:country":"US",
    "sg:address":"8355 NW 53rd St Fl 1",
    "sg:city":"Miami",
    "sg:classifiers":[
        {
            "category":"Professional",
            "subcategory":"Business Services",
            "type":"Services"
        }
    ],
    "sg:phone":"+1 305 499 2100",
    "sg:postcode":"33166",
    "sg:province":"FL",
    "sg:tags":[
        "medical",
        "administration"
    ],
    "sg:website":"http://www.seminolecohealth.com",
    "wof:name":"Medicaid Office",
    "wof:placetype":"venue"
},
  "geometry": {"coordinates":[-80.333074,25.820831],"type":"Point"}
}