{
  "type": "Feature",
  "properties": {
    "addr:full":"1808 N Dixie Hwy West Palm Beach FL 33407",
    "addr:housenumber":"1808",
    "addr:postcode":"33407",
    "addr:street":"N Dixie Hwy",
    "iso:country":"US",
    "sg:address":"1808 N Dixie Hwy",
    "sg:city":"West Palm Beach",
    "sg:classifiers":[
        {
            "category":"Professional",
            "subcategory":"Lawyer & Legal Services",
            "type":"Services"
        }
    ],
    "sg:phone":"+1 561 585 2905",
    "sg:postcode":"33407",
    "sg:province":"FL",
    "sg:tags":[
        "naturalization",
        "immigration"
    ],
    "wof:name":"Molina Immigration Specialist",
    "wof:placetype":"venue"
},
  "geometry": {"coordinates":[-80.053073,26.728544],"type":"Point"}
}