{
  "type": "Feature",
  "properties": {
    "iso:country":"US",
    "sg:address":"115 Indian Hills Dr",
    "sg:city":"Fort Pierce",
    "sg:classifiers":[
        {
            "category":"Freight",
            "type":"Transportation"
        }
    ],
    "sg:phone":"+1 772 465 9457",
    "sg:postcode":"34982",
    "sg:province":"FL",
    "sg:tags":[
        "operator",
        "local",
        "trucking"
    ],
    "wof:name":"Molinevos Teresa Dump Trck Svc",
    "wof:placetype":"venue"
},
  "geometry": {"coordinates":[-80.322495,27.43828],"type":"Point"}
}