{
  "type": "Feature",
  "properties": {
    "addr:full":"38 Caswell Dr Orlando FL 32825",
    "addr:housenumber":"38",
    "addr:postcode":"32825",
    "addr:street":"Caswell Dr",
    "iso:country":"US",
    "sg:address":"38 Caswell Dr",
    "sg:city":"Orlando",
    "sg:classifiers":[
        {
            "category":"Professional",
            "type":"Services"
        }
    ],
    "sg:phone":"+1 407 823 9573",
    "sg:postcode":"32825",
    "sg:province":"FL",
    "sg:tags":[
        "publication",
        "editorial"
    ],
    "wof:name":"Nina Steel Adventures",
    "wof:placetype":"venue"
},
  "geometry": {"coordinates":[-81.269558,28.54472],"type":"Point"}
}