{
  "type": "Feature",
  "properties": {
    "addr:full":"5335 Broad Acres St Merritt Island FL 32953",
    "addr:housenumber":"5335",
    "addr:postcode":"32953",
    "addr:street":"Broad;St",
    "iso:country":"US",
    "sg:address":"5335 Broad Acres St",
    "sg:city":"Merritt Island",
    "sg:classifiers":[
        {
            "category":"Shopping",
            "subcategory":"Hobbies, Toys, & Games",
            "type":"Retail Goods"
        }
    ],
    "sg:phone":"+1 321 452 8468",
    "sg:postcode":"32953",
    "sg:province":"FL",
    "sg:tags":[
        "craft"
    ],
    "wof:name":"John Noonan's Custom Knives",
    "wof:placetype":"venue"
},
  "geometry": {"coordinates":[-80.676677,28.453447],"type":"Point"}
}