{
  "type": "Feature",
  "properties": {
    "iso:country":"US",
    "sg:address":"6861 SW 18th Ct",
    "sg:city":"Pompano Beach",
    "sg:classifiers":[
        {
            "category":"Professional",
            "subcategory":"Advertising",
            "type":"Services"
        }
    ],
    "sg:phone":"+1 954 970 4107",
    "sg:postcode":"33068",
    "sg:province":"FL",
    "sg:tags":[
        "mail",
        "direct"
    ],
    "wof:name":"Duke Lawn Express",
    "wof:placetype":"venue"
},
  "geometry": {"coordinates":[-80.215732,26.204788],"type":"Point"}
}