{
  "type": "Feature",
  "properties": {
    "iso:country":"US",
    "sg:address":"3952 Granada Blvd",
    "sg:city":"Coral Gables",
    "sg:classifiers":[
        {
            "category":"Social Services",
            "type":"Services"
        }
    ],
    "sg:phone":"+1 305 448 0180",
    "sg:postcode":"33134",
    "sg:province":"FL",
    "sg:tags":[
        "youth",
        "organization",
        "center"
    ],
    "wof:name":"Girl Scout Council-Trop Flrd",
    "wof:placetype":"venue"
},
  "geometry": {"coordinates":[-80.274269,25.735469],"type":"Point"}
}