{
  "type": "Feature",
  "properties": {
    "iso:country":"US",
    "sg:address":"1255 SW 58th Ave",
    "sg:city":"Hollywood",
    "sg:classifiers":[
        {
            "category":"Banks & Credit Unions",
            "subcategory":"Bank",
            "type":"Services"
        }
    ],
    "sg:phone":"+1 954 894 0200",
    "sg:postcode":"33023",
    "sg:province":"FL",
    "wof:name":"Marka Exports Inc",
    "wof:placetype":"venue"
},
  "geometry": {"coordinates":[-80.202988,25.999345],"type":"Point"}
}