{
  "type": "Feature",
  "properties": {
    "addr:full":"4604 Rock Springs Rd Apopka FL 32712",
    "addr:housenumber":"4604",
    "addr:postcode":"32712",
    "addr:street":"Rock Springs Rd",
    "iso:country":"US",
    "sg:address":"4604 Rock Springs Rd",
    "sg:city":"Apopka",
    "sg:classifiers":[
        {
            "category":"Farming",
            "subcategory":"Nursery",
            "type":"Manufacturing & Wholesale Goods"
        }
    ],
    "sg:phone":"+1 407 889 0018",
    "sg:postcode":"32712",
    "sg:province":"FL",
    "sg:tags":[
        "ornamental"
    ],
    "wof:name":"Wright Horvath Nursery",
    "wof:placetype":"venue"
},
  "geometry": {"coordinates":[-81.50902600000001,28.752024],"type":"Point"}
}