{
  "type": "Feature",
  "properties": {
    "iso:country":"US",
    "sg:address":"7625 Little Rd",
    "sg:city":"New Port Richey",
    "sg:classifiers":[
        {
            "category":"Government",
            "subcategory":"Office",
            "type":"Public Place"
        }
    ],
    "sg:phone":"+1 727 841 4242",
    "sg:postcode":"34654",
    "sg:province":"FL",
    "sg:tags":[
        "admin",
        "res",
        "human",
        "social"
    ],
    "wof:name":"Social Service Office",
    "wof:placetype":"venue"
},
  "geometry": {"coordinates":[-82.674373,28.269908],"type":"Point"}
}