{
  "type": "Feature",
  "properties": {
    "addr:full":"5581 NW 79th Ave Miami FL 33166",
    "addr:housenumber":"5581",
    "addr:postcode":"33166",
    "addr:street":"Nw 79Th Ave",
    "iso:country":"US",
    "sg:address":"5581 NW 79th Ave",
    "sg:city":"Miami",
    "sg:classifiers":[
        {
            "category":"Wholesale",
            "subcategory":"Auto Parts",
            "type":"Manufacturing & Wholesale Goods"
        }
    ],
    "sg:phone":"+1 305 597 9400",
    "sg:postcode":"33166",
    "sg:province":"FL",
    "sg:tags":[
        "new",
        "retail",
        "used",
        "automotive"
    ],
    "wof:name":"Corvette Hang Out",
    "wof:placetype":"venue"
},
  "geometry": {"coordinates":[-80.32565200000001,25.82422],"type":"Point"}
}