{
  "type": "Feature",
  "properties": {
    "iso:country":"US",
    "sg:address":"105 W Hampton Springs Ave",
    "sg:city":"Perry",
    "sg:classifiers":[
        {
            "category":"Shopping",
            "subcategory":"Pharmacy",
            "type":"Retail Goods"
        }
    ],
    "sg:phone":"+1 850 838 3437",
    "sg:postcode":"32347",
    "sg:province":"FL",
    "wof:name":"CVS Pharmacy",
    "wof:placetype":"venue"
},
  "geometry": {"coordinates":[-83.583028,30.111504],"type":"Point"}
}