{
  "type": "Feature",
  "properties": {
    "iso:country":"US",
    "sg:address":"244 SW 37th Ln",
    "sg:city":"Cape Coral",
    "sg:classifiers":[
        {
            "category":"Organizations",
            "subcategory":"Professional Association",
            "type":"Services"
        }
    ],
    "sg:phone":"+1 239 910 0717",
    "sg:postcode":"33914",
    "sg:province":"FL",
    "sg:tags":[
        "agency",
        "advertising",
        "business"
    ],
    "wof:name":"Etom Express",
    "wof:placetype":"venue"
},
  "geometry": {"coordinates":[-81.979606,26.581888],"type":"Point"}
}