{
  "type": "Feature",
  "properties": {
    "iso:country":"US",
    "sg:address":"4812 N Coolidge Ave",
    "sg:city":"Tampa",
    "sg:classifiers":[
        {
            "category":"Building & Trades",
            "subcategory":"Construction",
            "type":"Services"
        }
    ],
    "sg:phone":"+1 813 870 0630",
    "sg:postcode":"33614",
    "sg:province":"FL",
    "sg:tags":[
        "development",
        "contractor"
    ],
    "wof:name":"Nichter Contracting Inc",
    "wof:placetype":"venue"
},
  "geometry": {"coordinates":[-82.516732,27.991205],"type":"Point"}
}