{
  "type": "Feature",
  "properties": {
    "iso:country":"US",
    "sg:address":"8080 W Flagler St Ste 2B",
    "sg:city":"Miami",
    "sg:classifiers":[
        {
            "category":"Health Services",
            "subcategory":"Health Practitioner",
            "type":"Services"
        }
    ],
    "sg:phone":"+1 305 235 0760",
    "sg:postcode":"33144",
    "sg:province":"FL",
    "sg:tags":[
        "gambling",
        "addiction-information",
        "treatment"
    ],
    "wof:name":"Ocean Blue Rehab",
    "wof:placetype":"venue"
},
  "geometry": {"coordinates":[-80.32623100000001,25.769701],"type":"Point"}
}