{
  "type": "Feature",
  "properties": {
    "addr:full":"900 S US Hwy 1 Jupiter FL 33477",
    "addr:housenumber":"900",
    "addr:postcode":"33477",
    "addr:street":"S Us Hwy 1",
    "iso:country":"US",
    "sg:address":"900 S US Hwy 1",
    "sg:city":"Jupiter",
    "sg:classifiers":[
        {
            "category":"Health Services",
            "subcategory":"Doctor",
            "type":"Services"
        }
    ],
    "sg:phone":"+1 561 746 7224",
    "sg:postcode":"33477",
    "sg:province":"FL",
    "sg:tags":[
        "physician",
        "medical",
        "surgeon"
    ],
    "wof:name":"William J Romanos Jr MD",
    "wof:placetype":"venue"
},
  "geometry": {"coordinates":[-80.076302,26.925087],"type":"Point"}
}