{
  "type": "Feature",
  "properties": {
    "addr:full":"14546 SW 142nd Court Cir Miami FL 33186",
    "addr:housenumber":"14546",
    "addr:postcode":"33186",
    "addr:street":"Sw 142Nd Court Cir",
    "iso:country":"US",
    "sg:address":"14546 SW 142nd Court Cir",
    "sg:city":"Miami",
    "sg:classifiers":[
        {
            "category":"Banks & Credit Unions",
            "subcategory":"Financial Services",
            "type":"Services"
        }
    ],
    "sg:phone":"+1 305 278 4184",
    "sg:postcode":"33186",
    "sg:province":"FL",
    "wof:name":"Financial Rescue Services",
    "wof:placetype":"venue"
},
  "geometry": {"coordinates":[-80.42323399999999,25.630659],"type":"Point"}
}