{
  "type": "Feature",
  "properties": {
    "iso:country":"US",
    "sg:address":"7301 18th St NE",
    "sg:city":"Saint Petersburg",
    "sg:classifiers":[
        {
            "category":"Real Estate",
            "subcategory":"Real Estate Agent",
            "type":"Services"
        }
    ],
    "sg:phone":"+1 727 502 0050",
    "sg:postcode":"33702",
    "sg:province":"FL",
    "wof:name":"Rainier Realty Inc",
    "wof:placetype":"venue"
},
  "geometry": {"coordinates":[-82.610698,27.838797],"type":"Point"}
}