{
  "type": "Feature",
  "properties": {
    "addr:full":"13160 Broadhurst Loop Fort Myers FL 33919",
    "addr:housenumber":"13160",
    "addr:postcode":"33919",
    "addr:street":"Broadhurst Loop",
    "iso:country":"US",
    "sg:address":"13160 Broadhurst Loop",
    "sg:city":"Fort Myers",
    "sg:classifiers":[
        {
            "category":"Real Estate",
            "subcategory":"Real Estate Operator",
            "type":"Services"
        }
    ],
    "sg:phone":"+1 239 466 3391",
    "sg:postcode":"33919",
    "sg:province":"FL",
    "sg:tags":[
        "apartment"
    ],
    "wof:name":"Enclave At Cypress Lakes",
    "wof:placetype":"venue"
},
  "geometry": {"coordinates":[-81.895138,26.548567],"type":"Point"}
}