{
  "type": "Feature",
  "properties": {
    "addr:full":"18705 Biscayne Blvd Miami FL 33180",
    "addr:housenumber":"18705",
    "addr:postcode":"33180",
    "addr:street":"Biscayne Blvd",
    "iso:country":"US",
    "sg:address":"18705 Biscayne Blvd",
    "sg:city":"Miami",
    "sg:classifiers":[
        {
            "category":"Shopping",
            "subcategory":"Jewelry",
            "type":"Retail Goods"
        }
    ],
    "sg:phone":"+1 305 931 5620",
    "sg:postcode":"33180",
    "sg:province":"FL",
    "wof:name":"Burt Belenke's House of Diamonds",
    "wof:placetype":"venue"
},
  "geometry": {"coordinates":[-80.14649799999999,25.950802],"type":"Point"}
}