{
  "type": "Feature",
  "properties": {
    "addr:full":"2445 N Courtenay Pkwy Ste C Merritt Island FL 32953",
    "addr:housenumber":"2445",
    "addr:postcode":"32953",
    "addr:street":"N Courtenay Pkwy Ste C",
    "iso:country":"US",
    "sg:address":"2445 N Courtenay Pkwy Ste C",
    "sg:city":"Merritt Island",
    "sg:classifiers":[
        {
            "category":"Retail",
            "subcategory":"Auto Repair",
            "type":"Services"
        }
    ],
    "sg:phone":"+1 321 576 9077",
    "sg:postcode":"32953",
    "sg:province":"FL",
    "sg:website":"meineke.com",
    "wof:name":"Meineke Car Care Center",
    "wof:placetype":"venue"
},
  "geometry": {"coordinates":[-80.705528,28.400817],"type":"Point"}
}