{
  "type": "Feature",
  "properties": {
    "addr:full":"5905 SE Federal Hwy Stuart FL 34997",
    "addr:housenumber":"5905",
    "addr:postcode":"34997",
    "addr:street":"Se Federal Hwy",
    "iso:country":"US",
    "sg:address":"5905 SE Federal Hwy",
    "sg:city":"Stuart",
    "sg:classifiers":[
        {
            "category":"Shopping",
            "subcategory":"Discount & Variety Stores",
            "type":"Retail Goods"
        },
        {
            "category":"Shopping",
            "subcategory":"Department Store",
            "type":"Retail Goods"
        }
    ],
    "sg:phone":"+1 772 286 3230",
    "sg:postcode":"34997",
    "sg:province":"FL",
    "wof:name":"Dollar Value Store",
    "wof:placetype":"venue"
},
  "geometry": {"coordinates":[-80.204868,27.132298],"type":"Point"}
}