{
  "type": "Feature",
  "properties": {
    "iso:country":"US",
    "sg:address":"5201 Cedar Point Rd",
    "sg:city":"Jacksonville",
    "sg:classifiers":[
        {
            "category":"Organizations",
            "subcategory":"Religious Organization",
            "type":"Services"
        }
    ],
    "sg:phone":"+1 904 757 8133",
    "sg:postcode":"32226",
    "sg:province":"FL",
    "sg:tags":[
        "church"
    ],
    "wof:name":"Oak Grove Baptist Church",
    "wof:placetype":"venue"
},
  "geometry": {"coordinates":[-81.52168899999999,30.458398],"type":"Point"}
}