{
  "type": "Feature",
  "properties": {
    "addr:full":"5989 Approach Rd Sarasota FL 34238",
    "addr:housenumber":"5989",
    "addr:postcode":"34238",
    "addr:street":"Approach Rd",
    "iso:country":"US",
    "sg:address":"5989 Approach Rd",
    "sg:city":"Sarasota",
    "sg:classifiers":[
        {
            "category":"Health Services",
            "subcategory":"Doctor",
            "type":"Services"
        }
    ],
    "sg:phone":"+1 941 708 5445",
    "sg:postcode":"34238",
    "sg:province":"FL",
    "sg:tags":[
        "physician",
        "surgeon"
    ],
    "wof:name":"K & H Healthkare Inc",
    "wof:placetype":"venue"
},
  "geometry": {"coordinates":[-82.456079,27.265658],"type":"Point"}
}