{
  "type": "Feature",
  "properties": {
    "iso:country":"US",
    "sg:address":"1711 Hammondville Rd",
    "sg:city":"Pompano Beach",
    "sg:classifiers":[
        {
            "category":"Social Services",
            "type":"Services"
        },
        {
            "category":"Health Services",
            "subcategory":"Doctor",
            "type":"Services"
        }
    ],
    "sg:phone":"+1 954 972 6450",
    "sg:postcode":"33069",
    "sg:province":"FL",
    "sg:tags":[
        "clinic",
        "center",
        "community"
    ],
    "wof:name":"Sunshine Health Center Inc",
    "wof:placetype":"venue"
},
  "geometry": {"coordinates":[-80.146456,26.240471],"type":"Point"}
}