{
  "type": "Feature",
  "properties": {
    "iso:country":"US",
    "sg:address":"13705 NW 7th Ave",
    "sg:city":"North Miami",
    "sg:classifiers":[
        {
            "category":"Building & Trades",
            "subcategory":"Locksmith",
            "type":"Services"
        }
    ],
    "sg:phone":"+1 305 423 3672",
    "sg:postcode":"33168",
    "sg:province":"FL",
    "sg:tags":[
        "key"
    ],
    "wof:name":"1 Alpha Emergency Locksmith",
    "wof:placetype":"venue"
},
  "geometry": {"coordinates":[-80.211128,25.900055],"type":"Point"}
}