{
  "type": "Feature",
  "properties": {
    "addr:full":"6788 NW 17th Ave Fort Lauderdale FL 33309",
    "addr:housenumber":"6788",
    "addr:postcode":"33309",
    "addr:street":"Nw 17Th Ave",
    "iso:country":"US",
    "sg:address":"6788 NW 17th Ave",
    "sg:city":"Fort Lauderdale",
    "sg:classifiers":[
        {
            "category":"Professional",
            "type":"Services"
        }
    ],
    "sg:phone":"+1 954 979 5696",
    "sg:postcode":"33309",
    "sg:province":"FL",
    "wof:name":"Daphnes Broom Closet Inc",
    "wof:placetype":"venue"
},
  "geometry": {"coordinates":[-80.168496,26.207905],"type":"Point"}
}