{
  "type": "Feature",
  "properties": {
    "iso:country":"US",
    "sg:address":"40904 Florida Ave",
    "sg:city":"Eustis",
    "sg:classifiers":[
        {
            "category":"Home & Garden",
            "subcategory":"Home Furnishings",
            "type":"Retail Goods"
        }
    ],
    "sg:phone":"+1 352 483 5343",
    "sg:postcode":"32736",
    "sg:province":"FL",
    "wof:name":"Circle W Trading",
    "wof:placetype":"venue"
},
  "geometry": {"coordinates":[-81.42658900000001,28.943558],"type":"Point"}
}