{
  "type": "Feature",
  "properties": {
    "iso:country":"US",
    "sg:address":"1704 Hendricks Ave",
    "sg:city":"Jacksonville",
    "sg:classifiers":[
        {
            "category":"Social Services",
            "type":"Services"
        }
    ],
    "sg:phone":"+1 904 398 6888",
    "sg:postcode":"32207",
    "sg:province":"FL",
    "sg:tags":[
        "organization",
        "welfare"
    ],
    "wof:name":"Angel Aid",
    "wof:placetype":"venue"
},
  "geometry": {"coordinates":[-81.654647,30.308107],"type":"Point"}
}