{
  "type": "Feature",
  "properties": {
    "iso:country":"US",
    "sg:address":"7910 Pines Blvd",
    "sg:city":"Pembroke Pines",
    "sg:classifiers":[
        {
            "category":"Shopping",
            "subcategory":"Clothing, Apparel, & Fashions",
            "type":"Retail Goods"
        }
    ],
    "sg:phone":"+1 954 962 0740",
    "sg:postcode":"33024",
    "sg:province":"FL",
    "sg:tags":[
        "furnishing"
    ],
    "wof:name":"Big & Tall Men's Shop",
    "wof:placetype":"venue"
},
  "geometry": {"coordinates":[-80.24799899999999,26.009149],"type":"Point"}
}