{
  "type": "Feature",
  "properties": {
    "addr:full":"16689 Wellington Lakes Cir Fort Myers FL 33908",
    "addr:housenumber":"16689",
    "addr:postcode":"33908",
    "addr:street":"Wellington Lakes Cir",
    "iso:country":"US",
    "sg:address":"16689 Wellington Lakes Cir",
    "sg:city":"Fort Myers",
    "sg:classifiers":[
        {
            "category":"Professional",
            "subcategory":"Management & Consulting",
            "type":"Services"
        }
    ],
    "sg:phone":"+1 239 481 1371",
    "sg:postcode":"33908",
    "sg:province":"FL",
    "sg:tags":[
        "business"
    ],
    "wof:name":"Beh Consulting Inc",
    "wof:placetype":"venue"
},
  "geometry": {"coordinates":[-81.899951,26.498955],"type":"Point"}
}