{
  "type": "Feature",
  "properties": {
    "iso:country":"US",
    "sg:address":"904 W Michigan St",
    "sg:city":"Orlando",
    "sg:classifiers":[
        {
            "category":"Autos & Motor Vehicles",
            "subcategory":"Automobile Sales",
            "type":"Retail Goods"
        }
    ],
    "sg:phone":"+1 407 872 7553",
    "sg:postcode":"32805",
    "sg:province":"FL",
    "sg:tags":[
        "used"
    ],
    "wof:name":"Popular Used Cars Inc",
    "wof:placetype":"venue"
},
  "geometry": {"coordinates":[-81.392787,28.514565],"type":"Point"}
}