{
  "type": "Feature",
  "properties": {
    "iso:country":"US",
    "sg:address":"2288 Jessica Ln",
    "sg:city":"Kissimmee",
    "sg:classifiers":[
        {
            "category":"Professional",
            "subcategory":"Computer Services",
            "type":"Services"
        }
    ],
    "sg:phone":"+1 407 595 2011",
    "sg:postcode":"34744",
    "sg:province":"FL",
    "sg:tags":[
        "internet"
    ],
    "wof:name":"Smart Group Solutions",
    "wof:placetype":"venue"
},
  "geometry": {"coordinates":[-81.354187,28.261371],"type":"Point"}
}