{
  "type": "Feature",
  "properties": {
    "iso:country":"US",
    "sg:address":"5071 Sheridan St",
    "sg:city":"Hollywood",
    "sg:classifiers":[
        {
            "category":"Restaurant",
            "type":"Food & Drink"
        }
    ],
    "sg:menulink":"http://www.allmenus.com/fl/hollywood/50649-chicken-kitchen/menu/",
    "sg:phone":"+1 954 989 6446",
    "sg:postcode":"33021",
    "sg:province":"FL",
    "sg:tags":[
        "american",
        "wing"
    ],
    "wof:name":"Chicken Kitchen",
    "wof:placetype":"venue"
},
  "geometry": {"coordinates":[-80.194408,26.032679],"type":"Point"}
}