{
  "type": "Feature",
  "properties": {
    "iso:country":"US",
    "sg:address":"19061 SE Barus Dr",
    "sg:city":"Jupiter",
    "sg:classifiers":[
        {
            "category":"Building & Trades",
            "subcategory":"Construction",
            "type":"Services"
        }
    ],
    "sg:phone":"+1 561 358 7858",
    "sg:postcode":"33469",
    "sg:province":"FL",
    "sg:tags":[
        "carpentry",
        "contractor"
    ],
    "wof:name":"York Pottratz",
    "wof:placetype":"venue"
},
  "geometry": {"coordinates":[-80.09951100000001,26.972189],"type":"Point"}
}