{
  "type": "Feature",
  "properties": {
    "iso:country":"US",
    "sg:address":"47 E 8th St",
    "sg:city":"Hialeah",
    "sg:classifiers":[
        {
            "category":"Real Estate",
            "subcategory":"Real Estate Agent",
            "type":"Services"
        }
    ],
    "sg:phone":"+1 305 863 4176",
    "sg:postcode":"33010",
    "sg:province":"FL",
    "wof:name":"Azoy Property Management Inc",
    "wof:placetype":"venue"
},
  "geometry": {"coordinates":[-80.28041399999999,25.829117],"type":"Point"}
}