{
  "type": "Feature",
  "properties": {
    "iso:country":"US",
    "sg:address":"304 Andover Ct",
    "sg:city":"Boynton Beach",
    "sg:classifiers":[
        {
            "category":"Shopping",
            "subcategory":"Gifts & Souvenirs",
            "type":"Retail Goods"
        }
    ],
    "sg:phone":"+1 561 967 5519",
    "sg:postcode":"33436",
    "sg:province":"FL",
    "wof:name":"Rescue Buff Collectibles",
    "wof:placetype":"venue"
},
  "geometry": {"coordinates":[-80.092252,26.561512],"type":"Point"}
}