{
  "type": "Feature",
  "properties": {
    "iso:country":"US",
    "sg:address":"310 NE 1st Ave",
    "sg:city":"Hallandale Beach",
    "sg:classifiers":[
        {
            "category":"Insurance",
            "subcategory":"Insurance Agent",
            "type":"Services"
        }
    ],
    "sg:phone":"+1 954 455 8622",
    "sg:postcode":"33009",
    "sg:province":"FL",
    "wof:name":"All Claims Insurance",
    "wof:placetype":"venue"
},
  "geometry": {"coordinates":[-80.147997,25.990994],"type":"Point"}
}