{
  "type": "Feature",
  "properties": {
    "iso:country":"US",
    "sg:address":"4685 US Hwy 98",
    "sg:city":"Lakeland",
    "sg:classifiers":[
        {
            "category":"Recreation",
            "subcategory":"Amusement Park",
            "type":"Entertainment"
        }
    ],
    "sg:phone":"+1 863 648 0567",
    "sg:postcode":"33813",
    "sg:province":"FL",
    "sg:tags":[
        "park"
    ],
    "wof:name":"Gator Family Theme Park Inc",
    "wof:placetype":"venue"
},
  "geometry": {"coordinates":[-81.89122,27.984367],"type":"Point"}
}