{
  "type": "Feature",
  "properties": {
    "addr:full":"2404 Lakeland Hills Blvd Lakeland FL 33805",
    "addr:housenumber":"2404",
    "addr:postcode":"33805",
    "addr:street":"Lakeland Hills Blvd",
    "iso:country":"US",
    "sg:address":"2404 Lakeland Hills Blvd",
    "sg:city":"Lakeland",
    "sg:classifiers":[
        {
            "category":"Health Services",
            "subcategory":"Doctor",
            "type":"Services"
        }
    ],
    "sg:phone":"+1 863 802 8440",
    "sg:postcode":"33805",
    "sg:province":"FL",
    "sg:tags":[
        "physician",
        "surgeon"
    ],
    "wof:name":"Josephine B Lim MD",
    "wof:placetype":"venue"
},
  "geometry": {"coordinates":[-81.953357,28.07515],"type":"Point"}
}