{
  "type": "Feature",
  "properties": {
    "iso:country":"US",
    "sg:address":"5433 SW 149th Ct",
    "sg:city":"Miami",
    "sg:classifiers":[
        {
            "category":"Professional",
            "type":"Services"
        }
    ],
    "sg:phone":"+1 305 227 5962",
    "sg:postcode":"33185",
    "sg:province":"FL",
    "wof:name":"Jet Tech Aviation Inc",
    "wof:placetype":"venue"
},
  "geometry": {"coordinates":[-80.434803,25.714544],"type":"Point"}
}