{
  "type": "Feature",
  "properties": {
    "addr:full":"1040 Mason Ave Daytona Beach FL 32117",
    "addr:housenumber":"1040",
    "addr:postcode":"32117",
    "addr:street":"Mason Ave",
    "iso:country":"US",
    "sg:address":"1040 Mason Ave",
    "sg:city":"Daytona Beach",
    "sg:classifiers":[
        {
            "category":"Real Estate",
            "subcategory":"Surveying",
            "type":"Services"
        }
    ],
    "sg:phone":"+1 386 322 0976",
    "sg:postcode":"32117",
    "sg:province":"FL",
    "wof:name":"Powers and Associates",
    "wof:placetype":"venue"
},
  "geometry": {"coordinates":[-81.048276,29.219508],"type":"Point"}
}