{
  "type": "Feature",
  "properties": {
    "addr:full":"18054 Royal Hammock Blvd Naples FL 34114",
    "addr:housenumber":"18054",
    "addr:postcode":"34114",
    "addr:street":"Royal Hammock Blvd",
    "iso:country":"US",
    "sg:address":"18054 Royal Hammock Blvd",
    "sg:city":"Naples",
    "sg:classifiers":[
        {
            "category":"Retail",
            "subcategory":"Laundry & Dry Cleaning",
            "type":"Services"
        }
    ],
    "sg:phone":"+1 239 732 5188",
    "sg:postcode":"34114",
    "sg:province":"FL",
    "sg:tags":[
        "cleaners",
        "rug",
        "carpet"
    ],
    "wof:name":"Sparkle Cleaning",
    "wof:placetype":"venue"
},
  "geometry": {"coordinates":[-81.632937,26.012272],"type":"Point"}
}