{
  "type": "Feature",
  "properties": {
    "iso:country":"US",
    "sg:address":"2002 Pennwood Dr",
    "sg:city":"Melbourne",
    "sg:classifiers":[
        {
            "category":"Shopping",
            "subcategory":"Clothing, Apparel, & Fashions",
            "type":"Retail Goods"
        },
        {
            "category":"Personal",
            "type":"Services"
        },
        {
            "category":"Shopping",
            "subcategory":"Party Supplies",
            "type":"Retail Goods"
        },
        {
            "category":"Shopping",
            "subcategory":"Bridal",
            "type":"Retail Goods"
        }
    ],
    "sg:phone":"+1 321 729 8010",
    "sg:postcode":"32901",
    "sg:province":"FL",
    "sg:tags":[
        "shop",
        "dressmaker",
        "tailoring",
        "alteration",
        "tailor",
        "wedding"
    ],
    "wof:name":"The Tailor Shop",
    "wof:placetype":"venue"
},
  "geometry": {"coordinates":[-80.61936900000001,28.078529],"type":"Point"}
}