{
  "type": "Feature",
  "properties": {
    "addr:full":"2900 NW 42nd Ave Pompano Beach FL 33066",
    "addr:housenumber":"2900",
    "addr:postcode":"33066",
    "addr:street":"Nw 42Nd Ave",
    "iso:country":"US",
    "sg:address":"2900 NW 42nd Ave",
    "sg:city":"Pompano Beach",
    "sg:classifiers":[
        {
            "category":"Shopping",
            "subcategory":"Used Merchandise",
            "type":"Retail Goods"
        }
    ],
    "sg:phone":"+1 561 750 5535",
    "sg:postcode":"33066",
    "sg:province":"FL",
    "wof:name":"Vintage N Vogue",
    "wof:placetype":"venue"
},
  "geometry": {"coordinates":[-80.181624,26.27073],"type":"Point"}
}