{
  "type": "Feature",
  "properties": {
    "iso:country":"US",
    "sg:address":"100 Maxcy Dr",
    "sg:city":"Haines City",
    "sg:classifiers":[
        {
            "category":"Retail",
            "subcategory":"Auto Repair",
            "type":"Services"
        }
    ],
    "sg:phone":"+1 863 422 4965",
    "sg:postcode":"33843",
    "sg:province":"FL",
    "sg:tags":[
        "repairing",
        "automobile"
    ],
    "sg:website":"www.goodyear.com",
    "wof:name":"Goodyear Auto Svc Ctr",
    "wof:placetype":"venue"
},
  "geometry": {"coordinates":[-81.545011,27.714625],"type":"Point"}
}