{
  "type": "Feature",
  "properties": {
    "iso:country":"US",
    "sg:address":"1766 Oakbreeze Ln",
    "sg:city":"Jacksonville Beach",
    "sg:classifiers":[
        {
            "category":"Professional",
            "type":"Services"
        }
    ],
    "sg:phone":"+1 904 247 7553",
    "sg:postcode":"32250",
    "sg:province":"FL",
    "wof:name":"Seabrooke Information Co",
    "wof:placetype":"venue"
},
  "geometry": {"coordinates":[-81.40496400000001,30.267522],"type":"Point"}
}