{
  "type": "Feature",
  "properties": {
    "iso:country":"US",
    "sg:address":"6550 N Atlantic Ave",
    "sg:city":"Cape Canaveral",
    "sg:classifiers":[
        {
            "category":"Personal",
            "type":"Services"
        }
    ],
    "sg:phone":"+1 321 784 6436",
    "sg:postcode":"32920",
    "sg:province":"FL",
    "sg:tags":[
        "therapist",
        "massage"
    ],
    "wof:name":"Excel Sports Intl",
    "wof:placetype":"venue"
},
  "geometry": {"coordinates":[-80.60567399999999,28.376382],"type":"Point"}
}