{
  "type": "Feature",
  "properties": {
    "iso:country":"US",
    "sg:address":"3600 Plymouth Sorrento Rd",
    "sg:city":"Apopka",
    "sg:classifiers":[
        {
            "category":"Wholesale",
            "subcategory":"Plants",
            "type":"Manufacturing & Wholesale Goods"
        }
    ],
    "sg:phone":"+1 407 814 7633",
    "sg:postcode":"32712",
    "sg:province":"FL",
    "sg:tags":[
        "nursery",
        "tree",
        "supply"
    ],
    "wof:name":"Select Foliage & Flowers Inc",
    "wof:placetype":"venue"
},
  "geometry": {"coordinates":[-81.55973299999999,28.738495],"type":"Point"}
}