{
  "type": "Feature",
  "properties": {
    "iso:country":"US",
    "sg:address":"827 17th Ave S",
    "sg:city":"St Petersburg",
    "sg:classifiers":[
        {
            "category":"Building & Trades",
            "subcategory":"Plumbing",
            "type":"Services"
        }
    ],
    "sg:phone":"+1 727 822 1742",
    "sg:postcode":"33701",
    "sg:province":"FL",
    "sg:tags":[
        "plumbing",
        "contractor"
    ],
    "wof:name":"Anytime Plumbing & Drain Clng",
    "wof:placetype":"venue"
},
  "geometry": {"coordinates":[-82.646552,27.753508],"type":"Point"}
}