{
  "type": "Feature",
  "properties": {
    "addr:full":"800 41st Ave N Saint Petersburg FL 33703",
    "addr:housenumber":"800",
    "addr:postcode":"33703",
    "addr:street":"41St Ave N",
    "iso:country":"US",
    "sg:address":"800 41st Ave N",
    "sg:city":"Saint Petersburg",
    "sg:classifiers":[
        {
            "category":"Professional",
            "subcategory":"Employment Agencies",
            "type":"Services"
        }
    ],
    "sg:phone":"+1 727 528 2738",
    "sg:postcode":"33703",
    "sg:province":"FL",
    "wof:name":"Onshore Offshore Magazine",
    "wof:placetype":"venue"
},
  "geometry": {"coordinates":[-82.645387,27.809235],"type":"Point"}
}