{
  "type": "Feature",
  "properties": {
    "addr:full":"2685 E Silver Springs Blvd Ocala FL 34470",
    "addr:housenumber":"2685",
    "addr:postcode":"34470",
    "addr:street":"E Silver Springs Blvd",
    "iso:country":"US",
    "sg:address":"2685 E Silver Springs Blvd",
    "sg:city":"Ocala",
    "sg:classifiers":[
        {
            "category":"Banks & Credit Unions",
            "subcategory":"Bank",
            "type":"Services"
        }
    ],
    "sg:phone":"+1 352 694 9195",
    "sg:postcode":"34470",
    "sg:province":"FL",
    "sg:tags":[
        "loan"
    ],
    "wof:name":"Sunbelt Credit Inc",
    "wof:placetype":"venue"
},
  "geometry": {"coordinates":[-82.101598,29.188035],"type":"Point"}
}