{
  "type": "Feature",
  "properties": {
    "iso:country":"US",
    "sg:address":"4202 Gulf Shore Blvd N",
    "sg:city":"Naples",
    "sg:classifiers":[
        {
            "category":"Shopping",
            "subcategory":"Clothing, Apparel, & Fashions",
            "type":"Retail Goods"
        }
    ],
    "sg:phone":"+1 239 213 4202",
    "sg:postcode":"34103",
    "sg:province":"FL",
    "wof:name":"Diane's Fine Fashions",
    "wof:placetype":"venue"
},
  "geometry": {"coordinates":[-81.81309,26.191194],"type":"Point"}
}