{
  "type": "Feature",
  "properties": {
    "iso:country":"US",
    "sg:address":"7230 Isle of Capri Rd",
    "sg:city":"Naples",
    "sg:classifiers":[
        {
            "category":"Building & Trades",
            "subcategory":"Construction",
            "type":"Services"
        }
    ],
    "sg:phone":"+1 239 793 6682",
    "sg:postcode":"34114",
    "sg:province":"FL",
    "sg:tags":[
        "product",
        "asphalt"
    ],
    "wof:name":"Coral Isle Factory Shops",
    "wof:placetype":"venue"
},
  "geometry": {"coordinates":[-81.700141,26.042379],"type":"Point"}
}