{
  "type": "Feature",
  "properties": {
    "iso:country":"US",
    "sg:address":"12408 N 56th St",
    "sg:city":"Tampa",
    "sg:classifiers":[
        {
            "category":"Personal",
            "subcategory":"Beauty Salon",
            "type":"Services"
        }
    ],
    "sg:phone":"+1 813 989 2225",
    "sg:postcode":"33617",
    "sg:province":"FL",
    "sg:tags":[
        "manicuring"
    ],
    "wof:name":"At Your Fingertips",
    "wof:placetype":"venue"
},
  "geometry": {"coordinates":[-82.393765,28.061824],"type":"Point"}
}