{
  "type": "Feature",
  "properties": {
    "iso:country":"US",
    "sg:address":"250 Van Buren Ave",
    "sg:city":"Lake Mary",
    "sg:classifiers":[
        {
            "category":"Professional",
            "subcategory":"Lawyer & Legal Services",
            "type":"Services"
        }
    ],
    "sg:phone":"+1 407 321 0782",
    "sg:postcode":"32746",
    "sg:province":"FL",
    "wof:name":"Whigham Frank C Atty",
    "wof:placetype":"venue"
},
  "geometry": {"coordinates":[-81.328003,28.7491],"type":"Point"}
}