{
  "type": "Feature",
  "properties": {
    "iso:country":"US",
    "sg:address":"1708 SE 1st St",
    "sg:city":"Cape Coral",
    "sg:classifiers":[
        {
            "category":"Retail",
            "subcategory":"Auto Repair",
            "type":"Services"
        }
    ],
    "sg:phone":"+1 239 693 5858",
    "sg:postcode":"33990",
    "sg:province":"FL",
    "sg:tags":[
        "repairing",
        "automobile"
    ],
    "wof:name":"Kennedy's Super Svc",
    "wof:placetype":"venue"
},
  "geometry": {"coordinates":[-81.935585,26.650671],"type":"Point"}
}