{
  "type": "Feature",
  "properties": {
    "iso:country":"US",
    "sg:address":"4791 60th Way N",
    "sg:city":"Kenneth City",
    "sg:classifiers":[
        {
            "category":"Shopping",
            "subcategory":"Computers & Home Electronics",
            "type":"Retail Goods"
        }
    ],
    "sg:phone":"+1 727 544 5317",
    "sg:postcode":"33709",
    "sg:province":"FL",
    "sg:tags":[
        "parts",
        "supply"
    ],
    "wof:name":"Advance PC Parts & Consulting",
    "wof:placetype":"venue"
},
  "geometry": {"coordinates":[-82.71706,27.8153],"type":"Point"}
}