{
  "type": "Feature",
  "properties": {
    "addr:full":"21905 US Hwy 19 Clearwater FL 33765",
    "addr:postcode":"21905;33765",
    "addr:street":"Us Hwy 19",
    "iso:country":"US",
    "sg:address":"21905 US Hwy 19",
    "sg:city":"Clearwater",
    "sg:classifiers":[
        {
            "category":"Utilities",
            "subcategory":"Telephone",
            "type":"Services"
        }
    ],
    "sg:phone":"+1 727 799 9709",
    "sg:postcode":"33765",
    "sg:province":"FL",
    "sg:tags":[
        "distance",
        "long"
    ],
    "wof:name":"Lease Cost Routing",
    "wof:placetype":"venue"
},
  "geometry": {"coordinates":[-82.72977899999999,27.968085],"type":"Point"}
}