{
  "type": "Feature",
  "properties": {
    "addr:full":"5045 Cameron Ln Boynton Beach FL 33472",
    "addr:housenumber":"5045",
    "addr:postcode":"33472",
    "addr:street":"Cameron Ln",
    "iso:country":"US",
    "sg:address":"5045 Cameron Ln",
    "sg:city":"Boynton Beach",
    "sg:classifiers":[
        {
            "category":"Professional",
            "subcategory":"Business Services",
            "type":"Services"
        }
    ],
    "sg:phone":"+1 561 731 2476",
    "sg:postcode":"33472",
    "sg:province":"FL",
    "sg:tags":[
        "hanging",
        "contractor"
    ],
    "wof:name":"Interior Vistas Inc",
    "wof:placetype":"venue"
},
  "geometry": {"coordinates":[-80.12402899999999,26.541464],"type":"Point"}
}