{
  "type": "Feature",
  "properties": {
    "iso:country":"US",
    "sg:address":"2360 Jason St",
    "sg:city":"Merritt Island",
    "sg:classifiers":[
        {
            "category":"Recreation",
            "type":"Entertainment"
        }
    ],
    "sg:phone":"+1 321 459 0165",
    "sg:postcode":"32952",
    "sg:province":"FL",
    "sg:tags":[
        "practitioner"
    ],
    "wof:name":"Kathryn S Donat",
    "wof:placetype":"venue"
},
  "geometry": {"coordinates":[-80.675129,28.397671],"type":"Point"}
}