{
  "type": "Feature",
  "properties": {
    "iso:country":"US",
    "sg:address":"1454 E Hallandale Beach Blvd",
    "sg:city":"Hallandale",
    "sg:classifiers":[
        {
            "category":"Shopping",
            "subcategory":"Gifts & Souvenirs",
            "type":"Retail Goods"
        }
    ],
    "sg:phone":"+1 954 454 9077",
    "sg:postcode":"33009",
    "sg:province":"FL",
    "wof:name":"Hallandale Disc Grtg Cds Gifts",
    "wof:placetype":"venue"
},
  "geometry": {"coordinates":[-80.133281,25.985859],"type":"Point"}
}