{
  "type": "Feature",
  "properties": {
    "addr:full":"5900 9th St S St Petersburg FL 33705",
    "addr:housenumber":"5900",
    "addr:postcode":"33705",
    "addr:street":"9Th St S",
    "iso:country":"US",
    "sg:address":"5900 9th St S",
    "sg:city":"St Petersburg",
    "sg:classifiers":[
        {
            "category":"Education",
            "subcategory":"School",
            "type":"Public Place"
        }
    ],
    "sg:phone":"+1 727 893 2335",
    "sg:postcode":"33705",
    "sg:province":"FL",
    "wof:name":"Bay Vista Elementary School",
    "wof:placetype":"venue"
},
  "geometry": {"coordinates":[-82.64639699999999,27.71396],"type":"Point"}
}