{
  "type": "Feature",
  "properties": {
    "addr:full":"2105 Park Ave Orange Park FL 32073",
    "addr:housenumber":"2105",
    "addr:postcode":"32073",
    "addr:street":"Park Ave",
    "iso:country":"US",
    "sg:address":"2105 Park Ave",
    "sg:city":"Orange Park",
    "sg:classifiers":[
        {
            "category":"Banks & Credit Unions",
            "subcategory":"Investment Brokerage",
            "type":"Services"
        }
    ],
    "sg:phone":"+1 904 269 1109",
    "sg:postcode":"32073",
    "sg:province":"FL",
    "sg:tags":[
        "consultant",
        "planning",
        "financial"
    ],
    "wof:name":"Quality Credit Svc",
    "wof:placetype":"venue"
},
  "geometry": {"coordinates":[-81.70096700000001,30.162875],"type":"Point"}
}