{
  "type": "Feature",
  "properties": {
    "iso:country":"US",
    "sg:address":"10012 N Dale Mabry Hwy # 214",
    "sg:city":"Tampa",
    "sg:classifiers":[
        {
            "category":"Home & Garden",
            "subcategory":"Carpets & Floor Coverings",
            "type":"Retail Goods"
        }
    ],
    "sg:phone":"+1 813 960 7370",
    "sg:postcode":"33618",
    "sg:province":"FL",
    "sg:tags":[
        "material"
    ],
    "wof:name":"Signature Floors & More",
    "wof:placetype":"venue"
},
  "geometry": {"coordinates":[-82.504947,28.040321],"type":"Point"}
}