{
  "type": "Feature",
  "properties": {
    "addr:full":"333 N Falkenburg Rd Ste A Tampa FL 33619",
    "addr:housenumber":"333",
    "addr:postcode":"33619",
    "addr:street":"N Falkenburg Rd Ste A",
    "iso:country":"US",
    "sg:address":"333 N Falkenburg Rd Ste A",
    "sg:city":"Tampa",
    "sg:classifiers":[
        {
            "category":"Building & Trades",
            "subcategory":"Construction",
            "type":"Services"
        }
    ],
    "sg:phone":"+1 800 999 3930",
    "sg:postcode":"33619",
    "sg:province":"FL",
    "sg:tags":[
        "roofing",
        "contractor",
        "industrial",
        "contractors-commercial",
        "consultant"
    ],
    "sg:website":"http://www.alumatile.com",
    "wof:name":"Aluma-Tile Roofers",
    "wof:placetype":"venue"
},
  "geometry": {"coordinates":[-82.33510699999999,27.955044],"type":"Point"}
}