{
  "type": "Feature",
  "properties": {
    "iso:country":"US",
    "sg:address":"32855 Crooked Oaks Ln",
    "sg:city":"Leesburg",
    "sg:classifiers":[
        {
            "category":"Professional",
            "subcategory":"Business Services",
            "type":"Services"
        }
    ],
    "sg:phone":"+1 352 323 3570",
    "sg:postcode":"34748",
    "sg:province":"FL",
    "sg:tags":[
        "merchandise"
    ],
    "wof:name":"Maries Party Cake & Supply",
    "wof:placetype":"venue"
},
  "geometry": {"coordinates":[-81.941041,28.827388],"type":"Point"}
}