{
  "type": "Feature",
  "properties": {
    "addr:full":"41 Lake Eden Dr Boynton Beach FL 33435",
    "addr:housenumber":"41",
    "addr:postcode":"33435",
    "addr:street":"Lake Eden Dr",
    "iso:country":"US",
    "sg:address":"41 Lake Eden Dr",
    "sg:city":"Boynton Beach",
    "sg:classifiers":[
        {
            "category":"Insurance",
            "subcategory":"Insurance Agent",
            "type":"Services"
        }
    ],
    "sg:phone":"+1 561 735 7558",
    "sg:postcode":"33435",
    "sg:province":"FL",
    "wof:name":"Retirement Products Inc",
    "wof:placetype":"venue"
},
  "geometry": {"coordinates":[-80.072946,26.491763],"type":"Point"}
}