{
  "type": "Feature",
  "properties": {
    "addr:full":"1650 W Orange Blossom Trl Apopka FL 32712",
    "addr:housenumber":"1650",
    "addr:postcode":"32712",
    "addr:street":"W Orange Blossom Trl",
    "iso:country":"US",
    "sg:address":"1650 W Orange Blossom Trl",
    "sg:city":"Apopka",
    "sg:classifiers":[
        {
            "category":"Restaurant",
            "type":"Food & Drink"
        }
    ],
    "sg:menulink":"http://www.allmenus.com/fl/apopka/169590-wendys/menu/",
    "sg:phone":"+1 407 464 0267",
    "sg:postcode":"32712",
    "sg:province":"FL",
    "sg:tags":[
        "burger",
        "american",
        "soup"
    ],
    "wof:name":"Wendy's",
    "wof:placetype":"venue"
},
  "geometry": {"coordinates":[-81.540009,28.687378],"type":"Point"}
}