{
  "type": "Feature",
  "properties": {
    "addr:full":"20770 W Dixie Hwy Miami FL 33180",
    "addr:housenumber":"20770",
    "addr:postcode":"33180",
    "addr:street":"W Dixie Hwy",
    "iso:country":"US",
    "sg:address":"20770 W Dixie Hwy",
    "sg:city":"Miami",
    "sg:classifiers":[
        {
            "category":"Professional",
            "subcategory":"Accounting & Tax Preparation",
            "type":"Services"
        }
    ],
    "sg:phone":"+1 305 705 0551",
    "sg:postcode":"33180",
    "sg:province":"FL",
    "sg:tags":[
        "accountant"
    ],
    "wof:name":"Jesse Small CPA",
    "wof:placetype":"venue"
},
  "geometry": {"coordinates":[-80.147925,25.968158],"type":"Point"}
}