{
  "type": "Feature",
  "properties": {
    "iso:country":"US",
    "sg:address":"7353 Aloma Ave",
    "sg:city":"Winter Park",
    "sg:classifiers":[
        {
            "category":"Personal",
            "type":"Services"
        }
    ],
    "sg:phone":"+1 407 431 8801",
    "sg:postcode":"32792",
    "sg:province":"FL",
    "sg:tags":[
        "home"
    ],
    "sg:website":"www.atticblowninsulation.com",
    "wof:name":"Ario's Services, Inc.",
    "wof:placetype":"venue"
},
  "geometry": {"coordinates":[-81.288691,28.609103],"type":"Point"}
}