{
  "type": "Feature",
  "properties": {
    "iso:country":"US",
    "sg:address":"14831 Hole in 1 Cir",
    "sg:city":"Fort Myers",
    "sg:classifiers":[
        {
            "category":"Sports & Exercise",
            "subcategory":"Golf",
            "type":"Entertainment"
        }
    ],
    "sg:phone":"+1 239 432 9475",
    "sg:postcode":"33919",
    "sg:province":"FL",
    "sg:tags":[
        "course"
    ],
    "wof:name":"Golfview Golf & Racquet Club",
    "wof:placetype":"venue"
},
  "geometry": {"coordinates":[-81.894904,26.524499],"type":"Point"}
}