{
  "type": "Feature",
  "properties": {
    "iso:country":"US",
    "sg:address":"13110 Lillian Hwy",
    "sg:city":"Pensacola",
    "sg:classifiers":[
        {
            "category":"Coffee & Tea",
            "type":"Food & Drink"
        },
        {
            "category":"Restaurant",
            "type":"Food & Drink"
        }
    ],
    "sg:phone":"+1 850 455 5252",
    "sg:postcode":"32506",
    "sg:province":"FL",
    "sg:tags":[
        "lunch",
        "brunch",
        "cafeteria",
        "espresso",
        "breakfast"
    ],
    "wof:name":"Crazy Horse Cafe",
    "wof:placetype":"venue"
},
  "geometry": {"coordinates":[-87.419162,30.398031],"type":"Point"}
}