{
  "type": "Feature",
  "properties": {
    "iso:country":"US",
    "sg:address":"7430 Aloma Ave",
    "sg:city":"Winter Park",
    "sg:classifiers":[
        {
            "category":"Autos & Motor Vehicles",
            "subcategory":"Auto Supplies",
            "type":"Retail Goods"
        }
    ],
    "sg:phone":"+1 407 677 7778",
    "sg:postcode":"32792",
    "sg:province":"FL",
    "sg:tags":[
        "tire"
    ],
    "wof:name":"Florida Tire Inc",
    "wof:placetype":"venue"
},
  "geometry": {"coordinates":[-81.28769699999999,28.6091],"type":"Point"}
}