{
  "type": "Feature",
  "properties": {
    "iso:country":"US",
    "sg:address":"1711 Industrial St",
    "sg:city":"Edgewater",
    "sg:classifiers":[
        {
            "category":"Building & Trades",
            "subcategory":"Construction",
            "type":"Services"
        }
    ],
    "sg:phone":"+1 386 427 3555",
    "sg:postcode":"32132",
    "sg:province":"FL",
    "wof:name":"Jones Electrical Construction",
    "wof:placetype":"venue"
},
  "geometry": {"coordinates":[-80.902534,28.972906],"type":"Point"}
}