{
  "type": "Feature",
  "properties": {
    "iso:country":"US",
    "sg:address":"8700 Commerce St",
    "sg:city":"Cape Canaveral",
    "sg:classifiers":[
        {
            "category":"Manufacturing",
            "subcategory":"Metals",
            "type":"Manufacturing & Wholesale Goods"
        }
    ],
    "sg:phone":"+1 321 868 2200",
    "sg:postcode":"32920",
    "sg:province":"FL",
    "sg:tags":[
        "small",
        "ammunition",
        "arms",
        "mfg"
    ],
    "sg:website":"www.22lrconversions.com",
    "wof:name":"Jonathan Arthur Ciener Inc",
    "wof:placetype":"venue"
},
  "geometry": {"coordinates":[-80.610879,28.39784],"type":"Point"}
}