{
  "type": "Feature",
  "properties": {
    "addr:full":"1270 Salford St SE Palm Bay FL 32909",
    "addr:housenumber":"1270",
    "addr:postcode":"32909",
    "addr:street":"Salford St Se",
    "iso:country":"US",
    "sg:address":"1270 Salford St SE",
    "sg:city":"Palm Bay",
    "sg:classifiers":[
        {
            "category":"Wholesale",
            "subcategory":"Fruits & Vegetables",
            "type":"Manufacturing & Wholesale Goods"
        }
    ],
    "sg:phone":"+1 321 952 5513",
    "sg:postcode":"32909",
    "sg:province":"FL",
    "wof:name":"Tom Ridleys Old World Fra",
    "wof:placetype":"venue"
},
  "geometry": {"coordinates":[-80.63672,27.963603],"type":"Point"}
}