{
  "type": "Feature",
  "properties": {
    "iso:country":"US",
    "sg:address":"680 W State Road 434",
    "sg:city":"Winter Springs",
    "sg:classifiers":[
        {
            "category":"Real Estate",
            "subcategory":"Real Estate Services",
            "type":"Services"
        }
    ],
    "sg:phone":"+1 407 327 7898",
    "sg:postcode":"32708",
    "sg:province":"FL",
    "sg:tags":[
        "management",
        "property"
    ],
    "wof:name":"Paine-Anderson Properties Inc",
    "wof:placetype":"venue"
},
  "geometry": {"coordinates":[-81.31201299999999,28.69826],"type":"Point"}
}