{
  "type": "Feature",
  "properties": {
    "iso:country":"US",
    "sg:address":"413 S Palmetto Ave",
    "sg:city":"Daytona Beach",
    "sg:classifiers":[
        {
            "category":"Real Estate",
            "subcategory":"Real Estate Operator",
            "type":"Services"
        }
    ],
    "sg:phone":"+1 386 212 3061",
    "sg:postcode":"32114",
    "sg:province":"FL",
    "sg:tags":[
        "apartment"
    ],
    "wof:name":"Stoney Brook Apts Inc",
    "wof:placetype":"venue"
},
  "geometry": {"coordinates":[-81.017555,29.204008],"type":"Point"}
}