{
  "type": "Feature",
  "properties": {
    "iso:country":"US",
    "sg:address":"700 NW 75th St",
    "sg:city":"Gainesville",
    "sg:phone":"+1 352 332 2346",
    "sg:postcode":"32607",
    "sg:province":"FL",
    "sg:website":"http://www.econolodge.com/hotel-gainesville-florida-FL366",
    "wof:name":"Econo Lodge West Gainesville",
    "wof:placetype":"venue"
},
  "geometry": {"coordinates":[-82.422409,29.658798],"type":"Point"}
}