{
  "type": "Feature",
  "properties": {
    "addr:full":"6852 NW 77th Ct Miami FL 33166",
    "addr:housenumber":"6852",
    "addr:postcode":"33166",
    "addr:street":"Nw 77Th Ct",
    "iso:country":"US",
    "sg:address":"6852 NW 77th Ct",
    "sg:city":"Miami",
    "sg:classifiers":[
        {
            "category":"Insurance",
            "subcategory":"Insurance Agent",
            "type":"Services"
        }
    ],
    "sg:phone":"+1 305 718 8894",
    "sg:postcode":"33166",
    "sg:province":"FL",
    "sg:tags":[
        "adjuster"
    ],
    "sg:website":"http://www.tpaf.com",
    "wof:name":"The Public Adjusting Firm Inc",
    "wof:placetype":"venue"
},
  "geometry": {"coordinates":[-80.322385,25.835951],"type":"Point"}
}