{
  "type": "Feature",
  "properties": {
    "addr:full":"1400 S Ocean Dr Hollywood FL 33019",
    "addr:housenumber":"1400",
    "addr:postcode":"33019",
    "addr:street":"S Ocean Dr",
    "iso:country":"US",
    "sg:address":"1400 S Ocean Dr",
    "sg:city":"Hollywood",
    "sg:classifiers":[
        {
            "category":"Real Estate",
            "subcategory":"Real Estate Operator",
            "type":"Services"
        },
        {
            "category":"Organizations",
            "subcategory":"Community Association",
            "type":"Services"
        }
    ],
    "sg:phone":"+1 954 927 2400",
    "sg:postcode":"33019",
    "sg:province":"FL",
    "sg:tags":[
        "condominium"
    ],
    "wof:name":"Trafalgar Towers Assoc I",
    "wof:placetype":"venue"
},
  "geometry": {"coordinates":[-80.11779,26.001506],"type":"Point"}
}