{
  "type": "Feature",
  "properties": {
    "iso:country":"US",
    "sg:address":"999 Rock Island Pl",
    "sg:city":"Pensacola",
    "sg:classifiers":[
        {
            "category":"Autos & Motor Vehicles",
            "subcategory":"Motorcycle Sales",
            "type":"Retail Goods"
        }
    ],
    "sg:phone":"+1 850 429 9222",
    "sg:postcode":"32505",
    "sg:province":"FL",
    "sg:tags":[
        "scooter"
    ],
    "wof:name":"Skip's Cycle Supply",
    "wof:placetype":"venue"
},
  "geometry": {"coordinates":[-87.25587299999999,30.464086],"type":"Point"}
}