{
  "type": "Feature",
  "properties": {
    "iso:country":"US",
    "sg:address":"1064 Waterside Cir",
    "sg:city":"Weston",
    "sg:classifiers":[
        {
            "category":"Professional",
            "type":"Services"
        }
    ],
    "sg:phone":"+1 954 217 6429",
    "sg:postcode":"33327",
    "sg:province":"FL",
    "wof:name":"4 L Corp",
    "wof:placetype":"venue"
},
  "geometry": {"coordinates":[-80.405315,26.118813],"type":"Point"}
}