{
  "type": "Feature",
  "properties": {
    "addr:full":"7658 Phillips Hwy Jacksonville FL 32256",
    "addr:housenumber":"7658",
    "addr:postcode":"32256",
    "addr:street":"Phillips Hwy",
    "iso:country":"US",
    "sg:address":"7658 Phillips Hwy",
    "sg:city":"Jacksonville",
    "sg:classifiers":[
        {
            "category":"Manufacturing",
            "subcategory":"Retail Goods",
            "type":"Manufacturing & Wholesale Goods"
        }
    ],
    "sg:phone":"+1 904 739 3986",
    "sg:postcode":"32256",
    "sg:province":"FL",
    "sg:tags":[
        "manufacturer"
    ],
    "wof:name":"Gulf Coast Industries",
    "wof:placetype":"venue"
},
  "geometry": {"coordinates":[-81.590354,30.228713],"type":"Point"}
}