{
  "type": "Feature",
  "properties": {
    "iso:country":"US",
    "sg:address":"1845 Lindberg Dr",
    "sg:city":"Jacksonville",
    "sg:classifiers":[
        {
            "category":"Real Estate",
            "subcategory":"Real Estate Operator",
            "type":"Services"
        }
    ],
    "sg:phone":"+1 904 695 2500",
    "sg:postcode":"32210",
    "sg:province":"FL",
    "sg:tags":[
        "apartment"
    ],
    "wof:name":"Lindberg Apartment Homes",
    "wof:placetype":"venue"
},
  "geometry": {"coordinates":[-81.742453,30.283687],"type":"Point"}
}