{
  "type": "Feature",
  "properties": {
    "iso:country":"US",
    "sg:address":"1055 N Liberty St",
    "sg:city":"Jacksonville",
    "sg:classifiers":[
        {
            "category":"Food & Beverages",
            "subcategory":"Groceries & Convenience Stores",
            "type":"Retail Goods"
        }
    ],
    "sg:phone":"+1 904 359 9967",
    "sg:postcode":"32206",
    "sg:province":"FL",
    "wof:name":"Bejra's Food Mart",
    "wof:placetype":"venue"
},
  "geometry": {"coordinates":[-81.65026899999999,30.335902],"type":"Point"}
}