{
  "type": "Feature",
  "properties": {
    "iso:country":"US",
    "sg:address":"217 Central Ave",
    "sg:city":"Saint Petersburg",
    "sg:classifiers":[
        {
            "category":"Restaurant",
            "type":"Food & Drink"
        }
    ],
    "sg:menulink":"http://www.allmenus.com/fl/st-petersburg/16219-garden-restaurant/menu/",
    "sg:phone":"+1 727 896 3800",
    "sg:postcode":"33701",
    "sg:province":"FL",
    "sg:tags":[
        "soup",
        "seafood",
        "american",
        "salad",
        "pizza"
    ],
    "wof:name":"Garden Restaurant",
    "wof:placetype":"venue"
},
  "geometry": {"coordinates":[-82.63584400000001,27.771214],"type":"Point"}
}