{
  "type": "Feature",
  "properties": {
    "iso:country":"US",
    "sg:address":"1830 NE 2 St",
    "sg:city":"Gainesville",
    "sg:classifiers":[
        {
            "category":"Utilities",
            "subcategory":"Telephone",
            "type":"Services"
        }
    ],
    "sg:phone":"+1 352 380 2890",
    "sg:postcode":"32609",
    "sg:province":"FL",
    "sg:tags":[
        "communications",
        "business"
    ],
    "wof:name":"Tower Communications",
    "wof:placetype":"venue"
},
  "geometry": {"coordinates":[-82.32180099999999,29.668997],"type":"Point"}
}