{
  "type": "Feature",
  "properties": {
    "iso:country":"US",
    "sg:address":"140 Royal Palm Ct",
    "sg:city":"Fort Lauderdale",
    "sg:classifiers":[
        {
            "category":"Retail",
            "subcategory":"Repair Shop",
            "type":"Services"
        }
    ],
    "sg:phone":"+1 954 584 4275",
    "sg:postcode":"33317",
    "sg:province":"FL",
    "wof:name":"A1a Superior Lock & Safe",
    "wof:placetype":"venue"
},
  "geometry": {"coordinates":[-80.225679,26.123386],"type":"Point"}
}