{
  "type": "Feature",
  "properties": {
    "iso:country":"US",
    "sg:address":"118 N Woodland Blvd",
    "sg:city":"Deland",
    "sg:classifiers":[
        {
            "category":"Building & Trades",
            "subcategory":"Construction",
            "type":"Services"
        }
    ],
    "sg:phone":"+1 386 740 0022",
    "sg:postcode":"32720",
    "sg:province":"FL",
    "sg:tags":[
        "interior",
        "design"
    ],
    "wof:name":"Bali Villa",
    "wof:placetype":"venue"
},
  "geometry": {"coordinates":[-81.303552,29.028767],"type":"Point"}
}