{
  "type": "Feature",
  "properties": {
    "iso:country":"US",
    "sg:address":"1515 Elizabeth St",
    "sg:city":"Melbourne",
    "sg:classifiers":[
        {
            "category":"Organizations",
            "subcategory":"Non-profit Organization",
            "type":"Services"
        }
    ],
    "sg:phone":"+1 321 676 5798",
    "sg:postcode":"32901",
    "sg:province":"FL",
    "wof:name":"Junior League Of South Brevard",
    "wof:placetype":"venue"
},
  "geometry": {"coordinates":[-80.62435600000001,28.084203],"type":"Point"}
}