{
  "type": "Feature",
  "properties": {
    "iso:country":"US",
    "sg:address":"419 W 49 St #109",
    "sg:city":"Hialeah",
    "sg:classifiers":[
        {
            "category":"Manufacturing",
            "subcategory":"Jewelry",
            "type":"Manufacturing & Wholesale Goods"
        }
    ],
    "sg:phone":"+1 786 313 0850",
    "sg:postcode":"33012",
    "sg:province":"FL",
    "sg:tags":[
        "stone",
        "manufacturer",
        "jewelers-wholesale",
        "jewels-imitation"
    ],
    "wof:name":"Extreme Jewelry Inc",
    "wof:placetype":"venue"
},
  "geometry": {"coordinates":[-80.291487,25.86672],"type":"Point"}
}