{
  "type": "Feature",
  "properties": {
    "iso:country":"US",
    "sg:address":"1335 Griff St",
    "sg:city":"Chattahoochee",
    "sg:classifiers":[
        {
            "category":"Home & Garden",
            "subcategory":"Building Materials",
            "type":"Retail Goods"
        },
        {
            "category":"Building & Trades",
            "subcategory":"Construction",
            "type":"Services"
        }
    ],
    "sg:phone":"+1 850 663 9557",
    "sg:postcode":"32324",
    "sg:province":"FL",
    "sg:tags":[
        "fence-sales",
        "fence",
        "contractor"
    ],
    "wof:name":"Property Fence Inc",
    "wof:placetype":"venue"
},
  "geometry": {"coordinates":[-84.84681399999999,30.679614],"type":"Point"}
}