{
  "type": "Feature",
  "properties": {
    "iso:country":"US",
    "sg:address":"178 N Powerline Rd",
    "sg:city":"Pompano Beach",
    "sg:classifiers":[
        {
            "category":"Social Services",
            "subcategory":"Child Care",
            "type":"Services"
        }
    ],
    "sg:phone":"+1 954 984 5888",
    "sg:postcode":"33069",
    "sg:province":"FL",
    "sg:tags":[
        "day"
    ],
    "wof:name":"All My Children Academy II",
    "wof:placetype":"venue"
},
  "geometry": {"coordinates":[-80.156623,26.229704],"type":"Point"}
}