{
  "type": "Feature",
  "properties": {
    "iso:country":"US",
    "sg:address":"11248 Portsmouth St",
    "sg:city":"Spring Hill",
    "sg:classifiers":[
        {
            "category":"Building & Trades",
            "subcategory":"Construction",
            "type":"Services"
        }
    ],
    "sg:phone":"+1 352 686 7846",
    "sg:postcode":"34609",
    "sg:province":"FL",
    "sg:tags":[
        "hanging",
        "contractor"
    ],
    "wof:name":"Torres Americo Reyes",
    "wof:placetype":"venue"
},
  "geometry": {"coordinates":[-82.535166,28.471521],"type":"Point"}
}