{
  "type": "Feature",
  "properties": {
    "addr:full":"1044 Castello Dr Naples FL 34103",
    "addr:housenumber":"1044",
    "addr:postcode":"34103",
    "addr:street":"Castello Dr",
    "iso:country":"US",
    "sg:address":"1044 Castello Dr",
    "sg:city":"Naples",
    "sg:classifiers":[
        {
            "category":"Health Services",
            "subcategory":"Doctor",
            "type":"Services"
        }
    ],
    "sg:phone":"+1 239 261 5566",
    "sg:postcode":"34103",
    "sg:province":"FL",
    "sg:tags":[
        "dentist"
    ],
    "wof:name":"Philip Logrippo DDS",
    "wof:placetype":"venue"
},
  "geometry": {"coordinates":[-81.799086,26.20593],"type":"Point"}
}