{
  "type": "Feature",
  "properties": {
    "addr:full":"3780 Burns Rd Palm Beach Gdns FL 33410",
    "addr:housenumber":"3780",
    "addr:postcode":"33410",
    "addr:street":"Burns Rd;Beach Gdns",
    "iso:country":"US",
    "sg:address":"3780 Burns Rd",
    "sg:city":"Palm Beach Gdns",
    "sg:classifiers":[
        {
            "category":"Health Services",
            "subcategory":"Medical Lab",
            "type":"Services"
        }
    ],
    "sg:phone":"+1 561 721 9866",
    "sg:postcode":"33410",
    "sg:province":"FL",
    "sg:tags":[
        "laboratory"
    ],
    "wof:name":"Biotech Dental Prosthetics",
    "wof:placetype":"venue"
},
  "geometry": {"coordinates":[-80.09354399999999,26.830485],"type":"Point"}
}