{
  "type": "Feature",
  "properties": {
    "iso:country":"US",
    "sg:address":"6040 4th St N",
    "sg:city":"Saint Petersburg",
    "sg:classifiers":[
        {
            "category":"Restaurant",
            "type":"Food & Drink"
        }
    ],
    "sg:menulink":"http://www.allmenus.com/fl/st-petersburg/29499-thai-am/menu/",
    "sg:phone":"+1 727 522 7813",
    "sg:postcode":"33703",
    "sg:province":"FL",
    "sg:tags":[
        "thai",
        "asian"
    ],
    "wof:name":"Thai Am",
    "wof:placetype":"venue"
},
  "geometry": {"coordinates":[-82.638734,27.826474],"type":"Point"}
}