{
  "type": "Feature",
  "properties": {
    "addr:full":"3949 Commerce Pkwy Miramar FL 33025",
    "addr:housenumber":"3949",
    "addr:postcode":"33025",
    "addr:street":"Commerce Pkwy",
    "iso:country":"US",
    "sg:address":"3949 Commerce Pkwy",
    "sg:city":"Miramar",
    "sg:classifiers":[
        {
            "category":"Wholesale",
            "subcategory":"Durable Goods & Equipment",
            "type":"Manufacturing & Wholesale Goods"
        }
    ],
    "sg:phone":"+1 954 499 1925",
    "sg:postcode":"33025",
    "sg:province":"FL",
    "sg:tags":[
        "exporter"
    ],
    "sg:website":"www.gochamp.net",
    "wof:name":"Champion Transportation Pallet",
    "wof:placetype":"venue"
},
  "geometry": {"coordinates":[-80.281631,25.98001],"type":"Point"}
}