{
  "type": "Feature",
  "properties": {
    "addr:full":"1902 Harden Blvd Lakeland FL 33803",
    "addr:housenumber":"1902",
    "addr:postcode":"33803",
    "addr:street":"Harden Blvd",
    "iso:country":"US",
    "sg:address":"1902 Harden Blvd",
    "sg:city":"Lakeland",
    "sg:classifiers":[
        {
            "category":"Shopping",
            "subcategory":"Musical Instruments",
            "type":"Retail Goods"
        }
    ],
    "sg:phone":"+1 863 686 3179",
    "sg:postcode":"33803",
    "sg:province":"FL",
    "sg:website":"www.carltonmusic.com",
    "wof:name":"Carlton Music Center Inc",
    "wof:placetype":"venue"
},
  "geometry": {"coordinates":[-81.97362699999999,28.023146],"type":"Point"}
}