{
  "type": "Feature",
  "properties": {
    "iso:country":"US",
    "sg:address":"4431 Embarcardero Dr",
    "sg:city":"West Palm Beach",
    "sg:classifiers":[
        {
            "category":"Professional",
            "subcategory":"Engineering",
            "type":"Services"
        }
    ],
    "sg:phone":"+1 561 845 0665",
    "sg:postcode":"33407",
    "sg:province":"FL",
    "wof:name":"Kimley-Horn",
    "wof:placetype":"venue"
},
  "geometry": {"coordinates":[-80.084671,26.756052],"type":"Point"}
}