{
  "type": "Feature",
  "properties": {
    "addr:full":"706 Anchors St NW Fort Walton Bch FL 32548",
    "addr:housenumber":"706",
    "addr:postcode":"32548",
    "addr:street":"Anchors St Nw Fort",
    "iso:country":"US",
    "sg:address":"706 Anchors St NW",
    "sg:city":"Fort Walton Bch",
    "sg:classifiers":[
        {
            "category":"Wholesale",
            "subcategory":"Durable Goods & Equipment",
            "type":"Manufacturing & Wholesale Goods"
        }
    ],
    "sg:phone":"+1 850 863 7866",
    "sg:postcode":"32548",
    "sg:province":"FL",
    "sg:tags":[
        "importer"
    ],
    "wof:name":"Estone Horse Imports",
    "wof:placetype":"venue"
},
  "geometry": {"coordinates":[-86.66715600000001,30.422472],"type":"Point"}
}