{
  "type": "Feature",
  "properties": {
    "iso:country":"US",
    "sg:address":"8850 SW 45 Blvd",
    "sg:city":"Gainesville",
    "sg:classifiers":[
        {
            "category":"Manufacturing",
            "subcategory":"Aerospace",
            "type":"Manufacturing & Wholesale Goods"
        }
    ],
    "sg:phone":"+1 352 376 2993",
    "sg:postcode":"32608",
    "sg:province":"FL",
    "sg:tags":[
        "aircraft",
        "mfg"
    ],
    "wof:name":"Altair International Inc",
    "wof:placetype":"venue"
},
  "geometry": {"coordinates":[-82.437318,29.610315],"type":"Point"}
}