{
  "type": "Feature",
  "properties": {
    "iso:country":"US",
    "sg:address":"9515 S Dixie Hwy",
    "sg:city":"Miami",
    "sg:classifiers":[
        {
            "category":"Restaurant",
            "type":"Food & Drink"
        }
    ],
    "sg:phone":"+1 305 669 1761",
    "sg:postcode":"33156",
    "sg:province":"FL",
    "sg:tags":[
        "pizza"
    ],
    "wof:name":"Two Guys Pizzaria",
    "wof:placetype":"venue"
},
  "geometry": {"coordinates":[-80.315573,25.681746],"type":"Point"}
}