{
  "type": "Feature",
  "properties": {
    "iso:country":"US",
    "sg:address":"2990 NW 81st Ter",
    "sg:city":"Miami",
    "sg:classifiers":[
        {
            "category":"Education",
            "subcategory":"Special Training",
            "type":"Public Place"
        }
    ],
    "sg:phone":"+1 305 835 2708",
    "sg:postcode":"33147",
    "sg:province":"FL",
    "sg:tags":[
        "educational"
    ],
    "wof:name":"It Is A Small World Academy",
    "wof:placetype":"venue"
},
  "geometry": {"coordinates":[-80.246833,25.848093],"type":"Point"}
}