{
  "type": "Feature",
  "properties": {
    "addr:full":"1209 Edgerton Dr Valrico FL 33594",
    "addr:housenumber":"1209",
    "addr:postcode":"33594",
    "addr:street":"Edgerton Dr",
    "iso:country":"US",
    "sg:address":"1209 Edgerton Dr",
    "sg:city":"Valrico",
    "sg:classifiers":[
        {
            "category":"Professional",
            "subcategory":"Detective & Security Services",
            "type":"Services"
        }
    ],
    "sg:phone":"+1 813 681 9475",
    "sg:postcode":"33594",
    "sg:province":"FL",
    "sg:tags":[
        "information",
        "bureau"
    ],
    "wof:name":"Mclean Services",
    "wof:placetype":"venue"
},
  "geometry": {"coordinates":[-82.224869,27.921921],"type":"Point"}
}