{
  "type": "Feature",
  "properties": {
    "iso:country":"US",
    "sg:address":"2645 SW 37th Ave Ste 504",
    "sg:city":"Miami",
    "sg:classifiers":[
        {
            "category":"Professional",
            "subcategory":"Lawyer & Legal Services",
            "type":"Services"
        }
    ],
    "sg:phone":"+1 305 448 2297",
    "sg:postcode":"33133",
    "sg:province":"FL",
    "sg:tags":[
        "divorce",
        "attorney",
        "practice",
        "family",
        "law"
    ],
    "wof:name":"Jennifer Sardina",
    "wof:placetype":"venue"
},
  "geometry": {"coordinates":[-80.254272,25.742109],"type":"Point"}
}