{
  "type": "Feature",
  "properties": {
    "iso:country":"US",
    "sg:address":"1472 NE 133rd Rd",
    "sg:city":"Miami",
    "sg:classifiers":[
        {
            "category":"Professional",
            "subcategory":"Business Services",
            "type":"Services"
        }
    ],
    "sg:phone":"+1 305 891 0580",
    "sg:postcode":"33161",
    "sg:province":"FL",
    "wof:name":"Decker Corp",
    "wof:placetype":"venue"
},
  "geometry": {"coordinates":[-80.169765,25.898378],"type":"Point"}
}