{
  "type": "Feature",
  "properties": {
    "addr:full":"642 W Brevard St Tallahassee FL 32304",
    "addr:housenumber":"642",
    "addr:postcode":"32304",
    "addr:street":"W Brevard St",
    "iso:country":"US",
    "sg:address":"642 W Brevard St",
    "sg:city":"Tallahassee",
    "sg:classifiers":[
        {
            "category":"Building & Trades",
            "subcategory":"Construction",
            "type":"Services"
        }
    ],
    "sg:phone":"+1 850 681 7767",
    "sg:postcode":"32304",
    "sg:province":"FL",
    "sg:tags":[
        "home",
        "builder"
    ],
    "sg:website":"www.floridadevelopers.com",
    "wof:name":"Florida Developers/General",
    "wof:placetype":"venue"
},
  "geometry": {"coordinates":[-84.292693,30.449127],"type":"Point"}
}