{
  "type": "Feature",
  "properties": {
    "iso:country":"US",
    "sg:address":"3185 Mariners Way",
    "sg:city":"Vero Beach",
    "sg:classifiers":[
        {
            "category":"Manufacturing",
            "subcategory":"Signs",
            "type":"Manufacturing & Wholesale Goods"
        }
    ],
    "sg:phone":"+1 772 581 8810",
    "sg:postcode":"32963",
    "sg:province":"FL",
    "sg:website":"www.buysignletters.com",
    "wof:name":"BUYSIGNLETTERS.COM",
    "wof:placetype":"venue"
},
  "geometry": {"coordinates":[-80.414164,27.792603],"type":"Point"}
}