{
  "type": "Feature",
  "properties": {
    "addr:full":"12011 SW 131st Ave Miami FL 33186",
    "addr:housenumber":"12011",
    "addr:postcode":"33186",
    "addr:street":"Sw 131St Ave",
    "iso:country":"US",
    "sg:address":"12011 SW 131st Ave",
    "sg:city":"Miami",
    "sg:classifiers":[
        {
            "category":"Food & Beverages",
            "subcategory":"Specialty",
            "type":"Retail Goods"
        },
        {
            "category":"Coffee & Tea",
            "type":"Food & Drink"
        },
        {
            "category":"Food & Beverages",
            "subcategory":"Fruits & Vegetables",
            "type":"Retail Goods"
        },
        {
            "category":"Shopping",
            "subcategory":"Pharmacy",
            "type":"Retail Goods"
        }
    ],
    "sg:phone":"+1 305 951 2448",
    "sg:postcode":"33186",
    "sg:province":"FL",
    "sg:tags":[
        "shop",
        "product",
        "gourmet",
        "wellness",
        "diet",
        "health",
        "herb"
    ],
    "sg:website":"http://www.facebook.com/tea.n.sanity",
    "wof:name":"Tea n Sanity",
    "wof:placetype":"venue"
},
  "geometry": {"coordinates":[-80.405878,25.656565],"type":"Point"}
}