{
  "type": "Feature",
  "properties": {
    "addr:full":"5998 US Hwy 41 Apollo Beach FL 33572",
    "addr:housenumber":"5998",
    "addr:postcode":"33572",
    "addr:street":"Us Hwy 41",
    "iso:country":"US",
    "sg:address":"5998 US Hwy 41",
    "sg:city":"Apollo Beach",
    "sg:classifiers":[
        {
            "category":"Retail",
            "subcategory":"Veterinary Services",
            "type":"Services"
        }
    ],
    "sg:phone":"+1 813 645 9208",
    "sg:postcode":"33572",
    "sg:province":"FL",
    "wof:name":"Sandra A Yetson Dvm PA",
    "wof:placetype":"venue"
},
  "geometry": {"coordinates":[-82.398701,27.761236],"type":"Point"}
}