{
  "type": "Feature",
  "properties": {
    "addr:full":"568 NE 28th St Boca Raton FL 33431",
    "addr:housenumber":"568",
    "addr:postcode":"33431",
    "addr:street":"Ne 28Th St",
    "iso:country":"US",
    "sg:address":"568 NE 28th St",
    "sg:city":"Boca Raton",
    "sg:classifiers":[
        {
            "category":"Building & Trades",
            "subcategory":"Landscaping Services",
            "type":"Services"
        }
    ],
    "sg:phone":"+1 561 243 6873",
    "sg:postcode":"33431",
    "sg:province":"FL",
    "wof:name":"Green Acres Lawn Maintenance",
    "wof:placetype":"venue"
},
  "geometry": {"coordinates":[-80.077107,26.375431],"type":"Point"}
}