{
  "type": "Feature",
  "properties": {
    "addr:full":"36333 Henderson Ln Zephyrhills FL 33541",
    "addr:housenumber":"36333",
    "addr:postcode":"33541",
    "addr:street":"Henderson Ln",
    "iso:country":"US",
    "sg:address":"36333 Henderson Ln",
    "sg:city":"Zephyrhills",
    "sg:classifiers":[
        {
            "category":"Building & Trades",
            "subcategory":"Cleaning & Sanitation",
            "type":"Services"
        }
    ],
    "sg:phone":"+1 813 782 8246",
    "sg:postcode":"33541",
    "sg:province":"FL",
    "sg:tags":[
        "janitor"
    ],
    "wof:name":"G & S Svc",
    "wof:placetype":"venue"
},
  "geometry": {"coordinates":[-82.21677099999999,28.220437],"type":"Point"}
}