{
  "type": "Feature",
  "properties": {
    "addr:full":"3385 Sheridan St Hollywood FL 33021",
    "addr:housenumber":"3385",
    "addr:postcode":"33021",
    "addr:street":"Sheridan St",
    "iso:country":"US",
    "sg:address":"3385 Sheridan St",
    "sg:city":"Hollywood",
    "sg:classifiers":[
        {
            "category":"Personal",
            "subcategory":"Beauty Salon",
            "type":"Services"
        }
    ],
    "sg:phone":"+1 954 987 3210",
    "sg:postcode":"33021",
    "sg:province":"FL",
    "sg:tags":[
        "shop"
    ],
    "wof:name":"Panache",
    "wof:placetype":"venue"
},
  "geometry": {"coordinates":[-80.175635,26.033168],"type":"Point"}
}