{
  "type": "Feature",
  "properties": {
    "iso:country":"US",
    "sg:address":"2508 N State Road 7",
    "sg:city":"Margate",
    "sg:classifiers":[
        {
            "category":"Insurance",
            "subcategory":"Insurance Agent",
            "type":"Services"
        },
        {
            "category":"Insurance",
            "subcategory":"Hazard Insurance",
            "type":"Services"
        },
        {
            "category":"Insurance",
            "subcategory":"Title Insurance",
            "type":"Services"
        },
        {
            "category":"Insurance",
            "subcategory":"Life Insurance",
            "type":"Services"
        }
    ],
    "sg:phone":"+1 954 978 9272",
    "sg:postcode":"33063",
    "sg:province":"FL",
    "sg:tags":[
        "business",
        "auto",
        "commercial",
        "homeowner",
        "motorcycle",
        "renter"
    ],
    "wof:name":"Allstate Insurance Company - Paul Bonomo",
    "wof:placetype":"venue"
},
  "geometry": {"coordinates":[-80.201427,26.258851],"type":"Point"}
}