{
  "type": "Feature",
  "properties": {
    "addr:full":"3009 NE 19th Dr Gainesville FL 32609",
    "addr:housenumber":"3009",
    "addr:postcode":"32609",
    "addr:street":"Ne 19Th Dr",
    "iso:country":"US",
    "sg:address":"3009 NE 19th Dr",
    "sg:city":"Gainesville",
    "sg:classifiers":[
        {
            "category":"Home & Garden",
            "subcategory":"Building Materials",
            "type":"Retail Goods"
        },
        {
            "category":"Manufacturing",
            "subcategory":"Building Materials",
            "type":"Manufacturing & Wholesale Goods"
        }
    ],
    "sg:phone":"+1 352 375 8539",
    "sg:postcode":"32609",
    "sg:province":"FL",
    "sg:tags":[
        "mfg"
    ],
    "wof:name":"Gator Door & Supply Co Inc",
    "wof:placetype":"venue"
},
  "geometry": {"coordinates":[-82.29879200000001,29.678969],"type":"Point"}
}