{
  "type": "Feature",
  "properties": {
    "addr:full":"907 E Semoran Blvd Apopka FL 32703",
    "addr:housenumber":"907 e",
    "addr:postcode":"32703",
    "addr:street":"Semoran Blvd",
    "iso:country":"US",
    "sg:address":"907 E Semoran Blvd",
    "sg:city":"Apopka",
    "sg:classifiers":[
        {
            "category":"Autos & Motor Vehicles",
            "subcategory":"Auto Supplies",
            "type":"Retail Goods"
        }
    ],
    "sg:phone":"+1 407 880 5911",
    "sg:postcode":"32703",
    "sg:province":"FL",
    "sg:tags":[
        "tire"
    ],
    "wof:name":"Tire Super Center",
    "wof:placetype":"venue"
},
  "geometry": {"coordinates":[-81.491192,28.673082],"type":"Point"}
}