{
  "type": "Feature",
  "properties": {
    "iso:country":"US",
    "sg:address":"3211 Flowertree Rd",
    "sg:city":"Orlando",
    "sg:classifiers":[
        {
            "category":"Real Estate",
            "subcategory":"Real Estate Agent",
            "type":"Services"
        }
    ],
    "sg:phone":"+1 407 251 6780",
    "sg:postcode":"32812",
    "sg:province":"FL",
    "sg:tags":[
        "inspection"
    ],
    "wof:name":"Gore Home Inspections",
    "wof:placetype":"venue"
},
  "geometry": {"coordinates":[-81.343155,28.45228],"type":"Point"}
}