{
  "type": "Feature",
  "properties": {
    "iso:country":"US",
    "sg:address":"1086 Exeter E",
    "sg:city":"Boca Raton",
    "sg:classifiers":[
        {
            "category":"Shopping",
            "subcategory":"Gifts & Souvenirs",
            "type":"Retail Goods"
        }
    ],
    "sg:phone":"+1 561 852 9134",
    "sg:postcode":"33434",
    "sg:province":"FL",
    "wof:name":"Mannys Gifts & Clock",
    "wof:placetype":"venue"
},
  "geometry": {"coordinates":[-80.177774,26.384888],"type":"Point"}
}