{
  "type": "Feature",
  "properties": {
    "iso:country":"US",
    "sg:address":"10360 NW 30th Ct",
    "sg:city":"Fort Lauderdale",
    "sg:classifiers":[
        {
            "category":"Shopping",
            "subcategory":"Clothing, Apparel, & Fashions",
            "type":"Retail Goods"
        }
    ],
    "sg:phone":"+1 954 746 5645",
    "sg:postcode":"33322",
    "sg:province":"FL",
    "sg:tags":[
        "sportswear"
    ],
    "wof:name":"Sport Time",
    "wof:placetype":"venue"
},
  "geometry": {"coordinates":[-80.287323,26.164102],"type":"Point"}
}