{
  "type": "Feature",
  "properties": {
    "iso:country":"US",
    "sg:address":"3323 Valencia Rd",
    "sg:city":"Tampa",
    "sg:classifiers":[
        {
            "category":"Organizations",
            "subcategory":"Membership Organization",
            "type":"Services"
        }
    ],
    "sg:phone":"+1 813 817 4653",
    "sg:postcode":"33618",
    "sg:province":"FL",
    "wof:name":"Beuhring Golf Association Inc",
    "wof:placetype":"venue"
},
  "geometry": {"coordinates":[-82.498953,28.050907],"type":"Point"}
}