{
  "type": "Feature",
  "properties": {
    "iso:country":"US",
    "sg:address":"3540 S Park Ave",
    "sg:city":"Titusville",
    "sg:classifiers":[
        {
            "category":"Manufacturing",
            "subcategory":"Signs",
            "type":"Manufacturing & Wholesale Goods"
        }
    ],
    "sg:phone":"+1 321 267 5067",
    "sg:postcode":"32780",
    "sg:province":"FL",
    "wof:name":"Barnett Signs & Graphics",
    "wof:placetype":"venue"
},
  "geometry": {"coordinates":[-80.836592,28.574656],"type":"Point"}
}