{
  "type": "Feature",
  "properties": {
    "iso:country":"US",
    "sg:address":"17223 Holly Ct",
    "sg:city":"Umatilla",
    "sg:classifiers":[
        {
            "category":"Retail",
            "subcategory":"Repair Shop",
            "type":"Services"
        }
    ],
    "sg:phone":"+1 352 357 8400",
    "sg:postcode":"32784",
    "sg:province":"FL",
    "sg:tags":[
        "industrial"
    ],
    "wof:name":"Boston & Associates",
    "wof:placetype":"venue"
},
  "geometry": {"coordinates":[-81.67133800000001,28.890218],"type":"Point"}
}