{
  "type": "Feature",
  "properties": {
    "addr:full":"1103 NE 118th St Biscayne Park FL 33161",
    "addr:housenumber":"1103",
    "addr:postcode":"33161",
    "addr:street":"Ne 118Th St",
    "iso:country":"US",
    "sg:address":"1103 NE 118th St",
    "sg:city":"Biscayne Park",
    "sg:classifiers":[
        {
            "category":"Building & Trades",
            "subcategory":"Construction",
            "type":"Services"
        }
    ],
    "sg:phone":"+1 305 893 8845",
    "sg:postcode":"33161",
    "sg:province":"FL",
    "sg:tags":[
        "designer",
        "dealer",
        "pool",
        "swimming"
    ],
    "wof:name":"Dixie Blue Pools",
    "wof:placetype":"venue"
},
  "geometry": {"coordinates":[-80.17478199999999,25.884409],"type":"Point"}
}