{
  "type": "Feature",
  "properties": {
    "iso:country":"US",
    "sg:address":"2235 Groveland Dr",
    "sg:city":"Lutz",
    "sg:classifiers":[
        {
            "category":"Shopping",
            "type":"Retail Goods"
        }
    ],
    "sg:phone":"+1 813 909 9119",
    "sg:postcode":"33549",
    "sg:province":"FL",
    "sg:tags":[
        "system",
        "equipment",
        "telephone",
        "repair"
    ],
    "wof:name":"Bailey Telephone Service",
    "wof:placetype":"venue"
},
  "geometry": {"coordinates":[-82.44187100000001,28.13794],"type":"Point"}
}