{
  "type": "Feature",
  "properties": {
    "iso:country":"US",
    "sg:address":"395 12th Ave",
    "sg:city":"Vero Beach",
    "sg:classifiers":[
        {
            "category":"Freight",
            "type":"Transportation"
        }
    ],
    "sg:phone":"+1 772 978 6502",
    "sg:postcode":"32962",
    "sg:province":"FL",
    "sg:tags":[
        "trucking"
    ],
    "wof:name":"Sunstar Logistics Inc",
    "wof:placetype":"venue"
},
  "geometry": {"coordinates":[-80.398008,27.60528],"type":"Point"}
}