{
  "type": "Feature",
  "properties": {
    "iso:country":"US",
    "sg:address":"285 N Courtenay Pkwy",
    "sg:city":"Merritt Island",
    "sg:classifiers":[
        {
            "category":"Professional",
            "type":"Services"
        }
    ],
    "sg:phone":"+1 321 454 3300",
    "sg:postcode":"32953",
    "sg:province":"FL",
    "sg:tags":[
        "establishment"
    ],
    "wof:name":"AAA 24 Hour Glass Windows",
    "wof:placetype":"venue"
},
  "geometry": {"coordinates":[-80.700329,28.360748],"type":"Point"}
}