{
  "type": "Feature",
  "properties": {
    "iso:country":"US",
    "sg:address":"335 Beville Rd",
    "sg:city":"South Daytona",
    "sg:classifiers":[
        {
            "category":"Shopping",
            "subcategory":"Used Merchandise",
            "type":"Retail Goods"
        }
    ],
    "sg:phone":"+1 386 257 0801",
    "sg:postcode":"32119",
    "sg:province":"FL",
    "sg:tags":[
        "shop",
        "thrift"
    ],
    "wof:name":"Domestic Abuse Thrift Shop",
    "wof:placetype":"venue"
},
  "geometry": {"coordinates":[-81.009788,29.183118],"type":"Point"}
}