{
  "type": "Feature",
  "properties": {
    "addr:full":"213 Mount Pleasant Rd Nokomis FL 34275",
    "addr:housenumber":"213",
    "addr:postcode":"34275",
    "addr:street":"Mount Pleasant Rd",
    "iso:country":"US",
    "sg:address":"213 Mount Pleasant Rd",
    "sg:city":"Nokomis",
    "sg:classifiers":[
        {
            "category":"Building & Trades",
            "subcategory":"Construction",
            "type":"Services"
        }
    ],
    "sg:phone":"+1 941 488 2547",
    "sg:postcode":"34275",
    "sg:province":"FL",
    "sg:tags":[
        "carpentry",
        "contractor"
    ],
    "wof:name":"Kp Carpentry",
    "wof:placetype":"venue"
},
  "geometry": {"coordinates":[-82.456384,27.137311],"type":"Point"}
}