{
  "type": "Feature",
  "properties": {
    "iso:country":"US",
    "sg:address":"1855 Medical Dr",
    "sg:city":"Titusville",
    "sg:classifiers":[
        {
            "category":"Health Services",
            "subcategory":"Doctor",
            "type":"Services"
        }
    ],
    "sg:phone":"+1 321 269 5228",
    "sg:postcode":"32796",
    "sg:province":"FL",
    "sg:tags":[
        "medical"
    ],
    "wof:name":"J E Rojas MD",
    "wof:placetype":"venue"
},
  "geometry": {"coordinates":[-80.82283,28.626859],"type":"Point"}
}