{
  "type": "Feature",
  "properties": {
    "iso:country":"US",
    "sg:address":"13265 SW 104th Ter",
    "sg:city":"Miami",
    "sg:classifiers":[
        {
            "category":"Professional",
            "type":"Services"
        }
    ],
    "sg:phone":"+1 305 387 3200",
    "sg:postcode":"33186",
    "sg:province":"FL",
    "wof:name":"Miguel Tartaglione Svc",
    "wof:placetype":"venue"
},
  "geometry": {"coordinates":[-80.41073799999999,25.67048],"type":"Point"}
}