{
  "type": "Feature",
  "properties": {
    "iso:country":"US",
    "sg:address":"301 N Olive Ave",
    "sg:city":"West Palm Beach",
    "sg:classifiers":[
        {
            "category":"Government",
            "subcategory":"Office",
            "type":"Public Place"
        }
    ],
    "sg:phone":"+1 561 355 3230",
    "sg:postcode":"33401",
    "sg:province":"FL",
    "sg:tags":[
        "policy"
    ],
    "wof:name":"Property Assessors Office",
    "wof:placetype":"venue"
},
  "geometry": {"coordinates":[-80.051829,26.716049],"type":"Point"}
}