{
  "type": "Feature",
  "properties": {
    "addr:full":"1516 E 4th Ave Hialeah FL 33010",
    "addr:housenumber":"1516",
    "addr:postcode":"33010",
    "addr:street":"E 4Th Ave",
    "iso:country":"US",
    "sg:address":"1516 E 4th Ave",
    "sg:city":"Hialeah",
    "sg:classifiers":[
        {
            "category":"Shopping",
            "subcategory":"Pharmacy",
            "type":"Retail Goods"
        }
    ],
    "sg:phone":"+1 305 887 1196",
    "sg:postcode":"33010",
    "sg:province":"FL",
    "sg:tags":[
        "drugstore"
    ],
    "sg:website":"www.mgcpharmacy.com",
    "wof:name":"Mgc Pharmacy",
    "wof:placetype":"venue"
},
  "geometry": {"coordinates":[-80.27394700000001,25.835764],"type":"Point"}
}