{
  "type": "Feature",
  "properties": {
    "iso:country":"US",
    "sg:address":"11099 Percheron Dr",
    "sg:city":"Jacksonville",
    "sg:classifiers":[
        {
            "category":"Shopping",
            "subcategory":"Shoes",
            "type":"Retail Goods"
        }
    ],
    "sg:phone":"+1 904 880 4758",
    "sg:postcode":"32257",
    "sg:province":"FL",
    "wof:name":"Footloose Entertainment",
    "wof:placetype":"venue"
},
  "geometry": {"coordinates":[-81.579629,30.172959],"type":"Point"}
}