{
  "type": "Feature",
  "properties": {
    "addr:full":"14100 Palmwood Rd Palm Beach Gdns FL 33410",
    "addr:postcode":"14100;33410",
    "addr:street":"Palmwood Rd;Beach Gdns",
    "iso:country":"US",
    "sg:address":"14100 Palmwood Rd",
    "sg:city":"Palm Beach Gdns",
    "sg:classifiers":[
        {
            "category":"Organizations",
            "subcategory":"Religious Organization",
            "type":"Services"
        }
    ],
    "sg:phone":"+1 561 775 0969",
    "sg:postcode":"33410",
    "sg:province":"FL",
    "sg:tags":[
        "church"
    ],
    "wof:name":"Jehovah's Witnesses",
    "wof:placetype":"venue"
},
  "geometry": {"coordinates":[-80.075546,26.88391],"type":"Point"}
}