{
  "type": "Feature",
  "properties": {
    "addr:full":"1125 E Cross St Pensacola FL 32503",
    "addr:housenumber":"1125",
    "addr:postcode":"32503",
    "addr:street":"E Cross St",
    "iso:country":"US",
    "sg:address":"1125 E Cross St",
    "sg:city":"Pensacola",
    "sg:classifiers":[
        {
            "category":"Wholesale",
            "subcategory":"Non-durable Goods",
            "type":"Manufacturing & Wholesale Goods"
        },
        {
            "category":"Professional",
            "subcategory":"Advertising",
            "type":"Services"
        }
    ],
    "sg:phone":"+1 850 434 1084",
    "sg:postcode":"32503",
    "sg:province":"FL",
    "sg:tags":[
        "specialty"
    ],
    "wof:name":"Boatwright Company Inc",
    "wof:placetype":"venue"
},
  "geometry": {"coordinates":[-87.207027,30.44165],"type":"Point"}
}