{
  "type": "Feature",
  "properties": {
    "addr:full":"5431 Panda Rd Venice FL 34293",
    "addr:housenumber":"5431",
    "addr:postcode":"34293",
    "addr:street":"Panda Rd",
    "iso:country":"US",
    "sg:address":"5431 Panda Rd",
    "sg:city":"Venice",
    "sg:classifiers":[
        {
            "category":"Building & Trades",
            "subcategory":"Construction",
            "type":"Services"
        },
        {
            "category":"Real Estate",
            "subcategory":"Real Estate Operator",
            "type":"Services"
        }
    ],
    "sg:phone":"+1 941 497 1320",
    "sg:postcode":"34293",
    "sg:province":"FL",
    "sg:tags":[
        "repairing",
        "contractor",
        "remodeling",
        "nonresidential"
    ],
    "wof:name":"Pascale's Properties Of Venice",
    "wof:placetype":"venue"
},
  "geometry": {"coordinates":[-82.413667,27.030509],"type":"Point"}
}