{
  "type": "Feature",
  "properties": {
    "iso:country":"US",
    "sg:address":"67 S Federal Hwy",
    "sg:city":"Boca Raton",
    "sg:classifiers":[
        {
            "category":"Shopping",
            "subcategory":"Used Merchandise",
            "type":"Retail Goods"
        }
    ],
    "sg:phone":"+1 561 391 1052",
    "sg:postcode":"33432",
    "sg:province":"FL",
    "sg:tags":[
        "shop",
        "consignment"
    ],
    "wof:name":"Mark's Interiors On Cnsgnmnt",
    "wof:placetype":"venue"
},
  "geometry": {"coordinates":[-80.08647499999999,26.348984],"type":"Point"}
}