{
  "type": "Feature",
  "properties": {
    "iso:country":"US",
    "sg:address":"8221 23rd Ave N",
    "sg:city":"Saint Petersburg",
    "sg:classifiers":[
        {
            "category":"Parking",
            "type":"Transportation"
        }
    ],
    "sg:phone":"+1 727 381 8238",
    "sg:postcode":"33710",
    "sg:province":"FL",
    "sg:tags":[
        "automobile"
    ],
    "wof:name":"A T D Power Sweeping Inc",
    "wof:placetype":"venue"
},
  "geometry": {"coordinates":[-82.755066,27.792701],"type":"Point"}
}