{
  "type": "Feature",
  "properties": {
    "iso:country":"US",
    "sg:address":"2519 N Ocean Blvd",
    "sg:city":"Boca Raton",
    "sg:classifiers":[
        {
            "category":"Real Estate",
            "subcategory":"Real Estate Operator",
            "type":"Services"
        }
    ],
    "sg:phone":"+1 561 392 9080",
    "sg:postcode":"33431",
    "sg:province":"FL",
    "sg:tags":[
        "apartment"
    ],
    "wof:name":"Oceanview-Lakeview Apartments",
    "wof:placetype":"venue"
},
  "geometry": {"coordinates":[-80.068094,26.373777],"type":"Point"}
}