{
  "type": "Feature",
  "properties": {
    "addr:full":"5501 Corporate Way West Palm Beach FL 33407",
    "addr:housenumber":"5501",
    "addr:postcode":"33407",
    "addr:street":"Corporate Way",
    "iso:country":"US",
    "sg:address":"5501 Corporate Way",
    "sg:city":"West Palm Beach",
    "sg:classifiers":[
        {
            "category":"Restaurant",
            "type":"Food & Drink"
        }
    ],
    "sg:menulink":"http://www.allmenus.com/fl/west-palm-beach/160371-burger-king/menu/",
    "sg:phone":"+1 561 683 2099",
    "sg:postcode":"33407",
    "sg:province":"FL",
    "sg:tags":[
        "burger",
        "american"
    ],
    "wof:name":"Burger King",
    "wof:placetype":"venue"
},
  "geometry": {"coordinates":[-80.08905,26.759529],"type":"Point"}
}