{
  "type": "Feature",
  "properties": {
    "iso:country":"US",
    "sg:address":"4296 SE Cove Rd",
    "sg:city":"Stuart",
    "sg:classifiers":[
        {
            "category":"Home & Garden",
            "subcategory":"Home Furnishings",
            "type":"Retail Goods"
        }
    ],
    "sg:phone":"+1 772 219 0436",
    "sg:postcode":"34997",
    "sg:province":"FL",
    "wof:name":"Cutlery Specialties",
    "wof:placetype":"venue"
},
  "geometry": {"coordinates":[-80.19618199999999,27.138101],"type":"Point"}
}