{
  "type": "Feature",
  "properties": {
    "addr:full":"80 N Homestead Blvd Homestead FL 33030",
    "addr:housenumber":"80",
    "addr:postcode":"33030",
    "addr:street":"N Homestead Blvd",
    "iso:country":"US",
    "sg:address":"80 N Homestead Blvd",
    "sg:city":"Homestead",
    "sg:classifiers":[
        {
            "category":"Shopping",
            "type":"Retail Goods"
        }
    ],
    "sg:phone":"+1 305 245 0011",
    "sg:postcode":"33030",
    "sg:province":"FL",
    "sg:tags":[
        "equipment",
        "lo",
        "telephone",
        "provides",
        "system"
    ],
    "wof:name":"Southern Electronic Telephone",
    "wof:placetype":"venue"
},
  "geometry": {"coordinates":[-80.471312,25.470052],"type":"Point"}
}