{
  "type": "Feature",
  "properties": {
    "iso:country":"US",
    "sg:address":"1677 Linkside Ct N",
    "sg:city":"Atlantic Beach",
    "sg:classifiers":[
        {
            "category":"Real Estate",
            "subcategory":"Real Estate Agent",
            "type":"Services"
        }
    ],
    "sg:phone":"+1 904 246 9811",
    "sg:postcode":"32233",
    "sg:province":"FL",
    "sg:tags":[
        "appraiser"
    ],
    "wof:name":"Suncoast Appraisal Inc",
    "wof:placetype":"venue"
},
  "geometry": {"coordinates":[-81.409328,30.340142],"type":"Point"}
}