{
  "type": "Feature",
  "properties": {
    "addr:full":"5005 Sesame St Palm Beach Gardens FL 33418",
    "addr:housenumber":"5005",
    "addr:postcode":"33418",
    "addr:street":"Sesame St",
    "iso:country":"US",
    "sg:address":"5005 Sesame St",
    "sg:city":"Palm Beach Gardens",
    "sg:classifiers":[
        {
            "category":"Building & Trades",
            "subcategory":"Construction",
            "type":"Services"
        }
    ],
    "sg:phone":"+1 561 626 2356",
    "sg:postcode":"33418",
    "sg:province":"FL",
    "sg:tags":[
        "bridge",
        "utility",
        "highway",
        "contractor"
    ],
    "wof:name":"Hugo Key & Son Inc",
    "wof:placetype":"venue"
},
  "geometry": {"coordinates":[-80.11360999999999,26.839026],"type":"Point"}
}