{
  "type": "Feature",
  "properties": {
    "addr:full":"380 San Lorenzo Ave Coral Gables FL 33146",
    "addr:housenumber":"380",
    "addr:postcode":"33146",
    "addr:street":"San Lorenzo Ave",
    "iso:country":"US",
    "sg:address":"380 San Lorenzo Ave",
    "sg:city":"Coral Gables",
    "sg:classifiers":[
        {
            "category":"Restaurant",
            "type":"Food & Drink"
        }
    ],
    "sg:phone":"+1 305 461 1113",
    "sg:postcode":"33146",
    "sg:province":"FL",
    "sg:tags":[
        "shop",
        "coffee"
    ],
    "wof:name":"Java Of Merrick Park",
    "wof:placetype":"venue"
},
  "geometry": {"coordinates":[-80.261354,25.732065],"type":"Point"}
}