{
  "type": "Feature",
  "properties": {
    "addr:full":"3214 Heather Grove Ct Jacksonville FL 32223",
    "addr:housenumber":"3214",
    "addr:postcode":"32223",
    "addr:street":"Heather Grove Ct",
    "iso:country":"US",
    "sg:address":"3214 Heather Grove Ct",
    "sg:city":"Jacksonville",
    "sg:classifiers":[
        {
            "category":"Shopping",
            "type":"Retail Goods"
        }
    ],
    "sg:phone":"+1 904 288 6720",
    "sg:postcode":"32223",
    "sg:province":"FL",
    "sg:tags":[
        "equipment",
        "resells",
        "telecommunication"
    ],
    "wof:name":"Specsig Inc",
    "wof:placetype":"venue"
},
  "geometry": {"coordinates":[-81.628281,30.15637],"type":"Point"}
}