{
  "type": "Feature",
  "properties": {
    "iso:country":"US",
    "sg:address":"20630 Bay Brook Ct",
    "sg:city":"Boca Raton",
    "sg:classifiers":[
        {
            "category":"Wholesale",
            "subcategory":"Groceries",
            "type":"Manufacturing & Wholesale Goods"
        }
    ],
    "sg:phone":"+1 561 883 6676",
    "sg:postcode":"33498",
    "sg:province":"FL",
    "wof:name":"Roscommon Group Corp",
    "wof:placetype":"venue"
},
  "geometry": {"coordinates":[-80.22693200000001,26.36912],"type":"Point"}
}