{
  "type": "Feature",
  "properties": {
    "iso:country":"US",
    "sg:address":"2920 NE 49th St",
    "sg:city":"Ocala",
    "sg:classifiers":[
        {
            "category":"Building & Trades",
            "subcategory":"Landscaping Services",
            "type":"Services"
        }
    ],
    "sg:phone":"+1 352 732 3358",
    "sg:postcode":"34479",
    "sg:province":"FL",
    "wof:name":"Even-Trim Lawn Service Inc",
    "wof:placetype":"venue"
},
  "geometry": {"coordinates":[-82.09837899999999,29.237449],"type":"Point"}
}