{
  "type": "Feature",
  "properties": {
    "iso:country":"US",
    "sg:address":"8201 Bardmoor Pl",
    "sg:city":"Seminole",
    "sg:classifiers":[
        {
            "category":"Shopping",
            "subcategory":"Gifts & Souvenirs",
            "type":"Retail Goods"
        }
    ],
    "sg:phone":"+1 727 319 3129",
    "sg:postcode":"33777",
    "sg:province":"FL",
    "wof:name":"L & Ss World of Gifts",
    "wof:placetype":"venue"
},
  "geometry": {"coordinates":[-82.75225500000001,27.865647],"type":"Point"}
}