{
  "type": "Feature",
  "properties": {
    "iso:country":"US",
    "sg:address":"3801 N Main St",
    "sg:city":"Gainesville",
    "sg:classifiers":[
        {
            "category":"Autos & Motor Vehicles",
            "subcategory":"Automobile Sales",
            "type":"Retail Goods"
        }
    ],
    "sg:phone":"+1 352 372 2329",
    "sg:postcode":"32609",
    "sg:province":"FL",
    "sg:tags":[
        "car",
        "dealer"
    ],
    "wof:name":"Wade Raulerson Honda",
    "wof:placetype":"venue"
},
  "geometry": {"coordinates":[-82.3193,29.685777],"type":"Point"}
}