{
  "type": "Feature",
  "properties": {
    "iso:country":"US",
    "sg:address":"5500 W 21st Ct",
    "sg:city":"Hialeah",
    "sg:classifiers":[
        {
            "category":"Health Services",
            "subcategory":"Clinic",
            "type":"Services"
        }
    ],
    "sg:phone":"+1 305 819 7076",
    "sg:postcode":"33016",
    "sg:province":"FL",
    "wof:name":"O&J Medical Services Inc",
    "wof:placetype":"venue"
},
  "geometry": {"coordinates":[-80.32581999999999,25.875593],"type":"Point"}
}