{
  "type": "Feature",
  "properties": {
    "addr:full":"100 Ferrol Rd Saint Augustine FL 32084",
    "addr:housenumber":"100",
    "addr:postcode":"32084",
    "addr:street":"Ferrol Rd",
    "iso:country":"US",
    "sg:address":"100 Ferrol Rd",
    "sg:city":"Saint Augustine",
    "sg:classifiers":[
        {
            "category":"Building & Trades",
            "subcategory":"Construction",
            "type":"Services"
        }
    ],
    "sg:phone":"+1 904 824 2930",
    "sg:postcode":"32084",
    "sg:province":"FL",
    "sg:tags":[
        "contractor"
    ],
    "wof:name":"Apex Tile & Marble",
    "wof:placetype":"venue"
},
  "geometry": {"coordinates":[-81.293935,29.915216],"type":"Point"}
}