{
  "type": "Feature",
  "properties": {
    "iso:country":"US",
    "sg:address":"1933 Premier Row",
    "sg:city":"Orlando",
    "sg:classifiers":[
        {
            "category":"Manufacturing",
            "subcategory":"Tools & Machinery",
            "type":"Manufacturing & Wholesale Goods"
        }
    ],
    "sg:phone":"+1 407 447 7281",
    "sg:postcode":"32809",
    "sg:province":"FL",
    "sg:tags":[
        "distributor",
        "instrument",
        "surgical"
    ],
    "wof:name":"Certified Srgcal Instrmntation",
    "wof:placetype":"venue"
},
  "geometry": {"coordinates":[-81.400795,28.46072],"type":"Point"}
}