{
  "type": "Feature",
  "properties": {
    "addr:full":"700 Kingston Ct Apollo Beach FL 33572",
    "addr:housenumber":"700",
    "addr:postcode":"33572",
    "addr:street":"Kingston Ct",
    "iso:country":"US",
    "sg:address":"700 Kingston Ct",
    "sg:city":"Apollo Beach",
    "sg:classifiers":[
        {
            "category":"Real Estate",
            "subcategory":"Real Estate Operator",
            "type":"Services"
        }
    ],
    "sg:phone":"+1 813 361 5980",
    "sg:postcode":"33572",
    "sg:province":"FL",
    "sg:tags":[
        "building",
        "nonresidential"
    ],
    "wof:name":"Butler Diaz Properties",
    "wof:placetype":"venue"
},
  "geometry": {"coordinates":[-82.415823,27.773144],"type":"Point"}
}