{
  "type": "Feature",
  "properties": {
    "addr:full":"1105 US Hwy 1 Sebastian FL 32958",
    "addr:housenumber":"1105",
    "addr:postcode":"32958",
    "addr:street":"Us Hwy 1",
    "iso:country":"US",
    "sg:address":"1105 US Hwy 1",
    "sg:city":"Sebastian",
    "sg:classifiers":[
        {
            "category":"Shopping",
            "subcategory":"Clothing, Apparel, & Fashions",
            "type":"Retail Goods"
        }
    ],
    "sg:phone":"+1 772 388 3334",
    "sg:postcode":"32958",
    "sg:province":"FL",
    "sg:tags":[
        "merchandise"
    ],
    "wof:name":"Beach Shop Inc",
    "wof:placetype":"venue"
},
  "geometry": {"coordinates":[-80.46786899999999,27.812953],"type":"Point"}
}