{
  "type": "Feature",
  "properties": {
    "iso:country":"US",
    "sg:address":"2400 NE Waldo Rd",
    "sg:city":"Gainesville",
    "sg:classifiers":[
        {
            "category":"Professional",
            "subcategory":"Management & Consulting",
            "type":"Services"
        }
    ],
    "sg:phone":"+1 352 371 1505",
    "sg:postcode":"32609",
    "sg:province":"FL",
    "sg:tags":[
        "provides"
    ],
    "wof:name":"For-A Corporation",
    "wof:placetype":"venue"
},
  "geometry": {"coordinates":[-82.296429,29.674464],"type":"Point"}
}