{
  "type": "Feature",
  "properties": {
    "iso:country":"US",
    "sg:address":"1880 N Commerce Pkwy",
    "sg:city":"Weston",
    "sg:classifiers":[
        {
            "category":"Arts & Performance",
            "subcategory":"Theater",
            "type":"Entertainment"
        }
    ],
    "sg:phone":"+1 954 370 3383",
    "sg:postcode":"33326",
    "sg:province":"FL",
    "sg:tags":[
        "talent",
        "agency",
        "casting"
    ],
    "wof:name":"Enter Focus Talent",
    "wof:placetype":"venue"
},
  "geometry": {"coordinates":[-80.365053,26.097246],"type":"Point"}
}