{
  "type": "Feature",
  "properties": {
    "iso:country":"US",
    "sg:address":"590 NW 109th Ave",
    "sg:city":"Miami",
    "sg:classifiers":[
        {
            "category":"Freight",
            "type":"Transportation"
        },
        {
            "category":"Professional",
            "subcategory":"Business Services",
            "type":"Services"
        },
        {
            "category":"Local Transit",
            "type":"Transportation"
        }
    ],
    "sg:phone":"+1 305 220 7883",
    "sg:postcode":"33172",
    "sg:province":"FL",
    "sg:tags":[
        "provider",
        "broker",
        "shipping",
        "trucking"
    ],
    "wof:name":"Lazo Cargo Envios",
    "wof:placetype":"venue"
},
  "geometry": {"coordinates":[-80.373554,25.775054],"type":"Point"}
}