{
  "type": "Feature",
  "properties": {
    "iso:country":"US",
    "sg:address":"1384 NW 65th Ave",
    "sg:city":"Plantation",
    "sg:classifiers":[
        {
            "category":"Retail",
            "subcategory":"Auto Repair",
            "type":"Services"
        }
    ],
    "sg:phone":"+1 954 584 3579",
    "sg:postcode":"33313",
    "sg:province":"FL",
    "sg:tags":[
        "automobile",
        "top",
        "upholstery"
    ],
    "wof:name":"Economy Auto Upholstery",
    "wof:placetype":"venue"
},
  "geometry": {"coordinates":[-80.23584099999999,26.141963],"type":"Point"}
}