{
  "type": "Feature",
  "properties": {
    "iso:country":"US",
    "sg:address":"2348 Foxrun Loop",
    "sg:city":"Lake Wales",
    "sg:classifiers":[
        {
            "category":"Building & Trades",
            "subcategory":"Construction",
            "type":"Services"
        }
    ],
    "sg:phone":"+1 863 676 6307",
    "sg:postcode":"33898",
    "sg:province":"FL",
    "sg:tags":[
        "general",
        "contractor"
    ],
    "wof:name":"Dubois Construction",
    "wof:placetype":"venue"
},
  "geometry": {"coordinates":[-81.551851,27.939438],"type":"Point"}
}