{
  "type": "Feature",
  "properties": {
    "iso:country":"US",
    "sg:address":"312 W 1st St",
    "sg:city":"Sanford",
    "sg:classifiers":[
        {
            "category":"Communications",
            "subcategory":"Film & Video Production",
            "type":"Services"
        }
    ],
    "sg:phone":"+1 407 328 4747",
    "sg:postcode":"32771",
    "sg:province":"FL",
    "sg:tags":[
        "motion",
        "picture",
        "studio",
        "facility"
    ],
    "sg:website":"www.skystorm.com",
    "wof:name":"Skystorm Productions",
    "wof:placetype":"venue"
},
  "geometry": {"coordinates":[-81.27103700000001,28.811763],"type":"Point"}
}