{
  "type": "Feature",
  "properties": {
    "iso:country":"US",
    "sg:address":"3753 Honeydew Ln",
    "sg:city":"New Smyrna Beach",
    "sg:classifiers":[
        {
            "category":"Manufacturing",
            "subcategory":"Glass & Minerals",
            "type":"Manufacturing & Wholesale Goods"
        }
    ],
    "sg:phone":"+1 386 427 0372",
    "sg:postcode":"32168",
    "sg:province":"FL",
    "sg:tags":[
        "concrete",
        "mfg"
    ],
    "wof:name":"Innovative Building & Engrg",
    "wof:placetype":"venue"
},
  "geometry": {"coordinates":[-81.053681,29.004123],"type":"Point"}
}