{
  "type": "Feature",
  "properties": {
    "iso:country":"US",
    "sg:address":"844 Thornton Ave",
    "sg:city":"Orlando",
    "sg:classifiers":[
        {
            "category":"Health Services",
            "subcategory":"Doctor",
            "type":"Services"
        }
    ],
    "sg:phone":"+1 407 894 8768",
    "sg:postcode":"32803",
    "sg:province":"FL",
    "sg:tags":[
        "physician",
        "surgeon"
    ],
    "wof:name":"Central Florida Pediatric Care",
    "wof:placetype":"venue"
},
  "geometry": {"coordinates":[-81.365557,28.555954],"type":"Point"}
}