{
  "type": "Feature",
  "properties": {
    "iso:country":"US",
    "sg:address":"949 SE 11th Ave",
    "sg:city":"Cape Coral",
    "sg:classifiers":[
        {
            "category":"Building & Trades",
            "subcategory":"Construction",
            "type":"Services"
        }
    ],
    "sg:phone":"+1 239 574 5528",
    "sg:postcode":"33990",
    "sg:province":"FL",
    "sg:tags":[
        "floor",
        "laying",
        "contractor"
    ],
    "wof:name":"Total Flooring Systems",
    "wof:placetype":"venue"
},
  "geometry": {"coordinates":[-81.95380400000001,26.63422],"type":"Point"}
}