{
  "type": "Feature",
  "properties": {
    "iso:country":"US",
    "sg:address":"12855 SW 136th Ave",
    "sg:city":"Miami",
    "sg:classifiers":[
        {
            "category":"Banks & Credit Unions",
            "subcategory":"Bank",
            "type":"Services"
        }
    ],
    "sg:phone":"+1 305 388 2277",
    "sg:postcode":"33186",
    "sg:province":"FL",
    "sg:tags":[
        "loan",
        "broker"
    ],
    "wof:name":"E Home Loans Corp",
    "wof:placetype":"venue"
},
  "geometry": {"coordinates":[-80.414204,25.647627],"type":"Point"}
}