{
  "type": "Feature",
  "properties": {
    "iso:country":"US",
    "sg:address":"157 Venetian Dr",
    "sg:city":"Islamorada",
    "sg:classifiers":[
        {
            "category":"Wholesale",
            "subcategory":"Computers",
            "type":"Manufacturing & Wholesale Goods"
        }
    ],
    "sg:phone":"+1 305 517 9644",
    "sg:postcode":"33036",
    "sg:province":"FL",
    "wof:name":"Emerald Key Technologies",
    "wof:placetype":"venue"
},
  "geometry": {"coordinates":[-80.73369099999999,24.858167],"type":"Point"}
}