{
  "type": "Feature",
  "properties": {
    "iso:country":"US",
    "sg:address":"140 Gunnery Rd S",
    "sg:city":"Lehigh Acres",
    "sg:classifiers":[
        {
            "category":"Building & Trades",
            "subcategory":"Landscaping Services",
            "type":"Services"
        }
    ],
    "sg:phone":"+1 239 368 6763",
    "sg:postcode":"33973",
    "sg:province":"FL",
    "sg:tags":[
        "sod",
        "sodding"
    ],
    "wof:name":"Big Lake Sod",
    "wof:placetype":"venue"
},
  "geometry": {"coordinates":[-81.714247,26.610848],"type":"Point"}
}