{
  "type": "Feature",
  "properties": {
    "iso:country":"US",
    "sg:address":"3807 W Barcelona St",
    "sg:city":"Tampa",
    "sg:classifiers":[
        {
            "category":"Home & Garden",
            "subcategory":"Building Materials",
            "type":"Retail Goods"
        }
    ],
    "sg:phone":"+1 813 837 0272",
    "sg:postcode":"33629",
    "sg:province":"FL",
    "wof:name":"Another Pane In Glass",
    "wof:placetype":"venue"
},
  "geometry": {"coordinates":[-82.50790000000001,27.921945],"type":"Point"}
}