{
  "type": "Feature",
  "properties": {
    "addr:full":"3399 Eagle Nest Dr Spring Hill FL 34607",
    "addr:housenumber":"3399",
    "addr:postcode":"34607",
    "addr:street":"Eagle Nest Dr",
    "iso:country":"US",
    "sg:address":"3399 Eagle Nest Dr",
    "sg:city":"Spring Hill",
    "sg:classifiers":[
        {
            "category":"Manufacturing",
            "subcategory":"Apparel",
            "type":"Manufacturing & Wholesale Goods"
        }
    ],
    "sg:phone":"+1 352 597 3200",
    "sg:postcode":"34607",
    "sg:province":"FL",
    "sg:tags":[
        "flag",
        "mfg"
    ],
    "wof:name":"Fun Flags",
    "wof:placetype":"venue"
},
  "geometry": {"coordinates":[-82.65875800000001,28.502754],"type":"Point"}
}