{
  "type": "Feature",
  "properties": {
    "iso:country":"US",
    "sg:address":"16647 Traders Xing N",
    "sg:city":"Jupiter",
    "sg:classifiers":[
        {
            "category":"Professional",
            "subcategory":"Management & Consulting",
            "type":"Services"
        }
    ],
    "sg:phone":"+1 561 744 2627",
    "sg:postcode":"33477",
    "sg:province":"FL",
    "wof:name":"Garry House Assoc Co",
    "wof:placetype":"venue"
},
  "geometry": {"coordinates":[-80.091436,26.922756],"type":"Point"}
}