{
  "type": "Feature",
  "properties": {
    "addr:full":"2913 W Broward Blvd Fort Lauderdale FL 33312",
    "addr:housenumber":"2913",
    "addr:postcode":"33312",
    "addr:street":"W Broward Blvd",
    "iso:country":"US",
    "sg:address":"2913 W Broward Blvd",
    "sg:city":"Fort Lauderdale",
    "sg:classifiers":[
        {
            "category":"Personal",
            "subcategory":"Beauty Salon",
            "type":"Services"
        }
    ],
    "sg:phone":"+1 954 327 9806",
    "sg:postcode":"33312",
    "sg:province":"FL",
    "wof:name":"Styles By Theresa",
    "wof:placetype":"venue"
},
  "geometry": {"coordinates":[-80.18339400000001,26.121412],"type":"Point"}
}