{
  "type": "Feature",
  "properties": {
    "iso:country":"US",
    "sg:address":"15901 W Lake Burrell Dr",
    "sg:city":"Lutz",
    "sg:classifiers":[
        {
            "category":"Professional",
            "type":"Services"
        }
    ],
    "sg:phone":"+1 813 978 1777",
    "sg:postcode":"33549",
    "sg:province":"FL",
    "sg:tags":[
        "establishment"
    ],
    "wof:name":"Hogar Restoracion Inc",
    "wof:placetype":"venue"
},
  "geometry": {"coordinates":[-82.450868,28.094223],"type":"Point"}
}