{
  "type": "Feature",
  "properties": {
    "addr:full":"13946 W Hillsborough Ave Tampa FL 33635",
    "addr:housenumber":"13946",
    "addr:postcode":"33635",
    "addr:street":"W Hillsborough Ave",
    "iso:country":"US",
    "sg:address":"13946 W Hillsborough Ave",
    "sg:city":"Tampa",
    "sg:classifiers":[
        {
            "category":"Retail",
            "subcategory":"Auto Rental",
            "type":"Services"
        }
    ],
    "sg:phone":"+1 813 855 2200",
    "sg:postcode":"33635",
    "sg:province":"FL",
    "sg:tags":[
        "renting",
        "automobile"
    ],
    "wof:name":"Avis Rent A Car",
    "wof:placetype":"venue"
},
  "geometry": {"coordinates":[-82.64153,28.031161],"type":"Point"}
}