{
  "type": "Feature",
  "properties": {
    "iso:country":"US",
    "sg:address":"1968 Kings Hwy",
    "sg:city":"Port Charlotte",
    "sg:classifiers":[
        {
            "category":"Restaurant",
            "type":"Food & Drink"
        }
    ],
    "sg:menulink":"http://www.allmenus.com/fl/port-charlotte/88025-top-china/menu/",
    "sg:phone":"+1 941 629 6888",
    "sg:postcode":"33980",
    "sg:province":"FL",
    "sg:tags":[
        "asian",
        "chinese"
    ],
    "wof:name":"Top China",
    "wof:placetype":"venue"
},
  "geometry": {"coordinates":[-82.05387,27.008899],"type":"Point"}
}