{
  "type": "Feature",
  "properties": {
    "addr:full":"3921 Barbara Ter Saint Augustine FL 32086",
    "addr:housenumber":"3921",
    "addr:postcode":"32086",
    "addr:street":"Barbara Ter",
    "iso:country":"US",
    "sg:address":"3921 Barbara Ter",
    "sg:city":"Saint Augustine",
    "sg:classifiers":[
        {
            "category":"Organizations",
            "subcategory":"Community Association",
            "type":"Services"
        }
    ],
    "sg:phone":"+1 904 797 6869",
    "sg:postcode":"32086",
    "sg:province":"FL",
    "wof:name":"Saint Augustine Youth",
    "wof:placetype":"venue"
},
  "geometry": {"coordinates":[-81.310461,29.824643],"type":"Point"}
}