{
  "type": "Feature",
  "properties": {
    "addr:full":"11995 Southern Blvd Royal Palm Beach FL 33411",
    "addr:housenumber":"11995",
    "addr:postcode":"33411",
    "addr:street":"Southern Blvd",
    "iso:country":"US",
    "sg:address":"11995 Southern Blvd",
    "sg:city":"Royal Palm Beach",
    "sg:classifiers":[
        {
            "category":"Restaurant",
            "type":"Food & Drink"
        }
    ],
    "sg:phone":"+1 561 784 0778",
    "sg:postcode":"33411",
    "sg:province":"FL",
    "wof:name":"Sal's Italian Restaurant",
    "wof:placetype":"venue"
},
  "geometry": {"coordinates":[-80.233688,26.681208],"type":"Point"}
}