{
  "type": "Feature",
  "properties": {
    "addr:full":"1201 Winter Green Way Winter Garden FL 34787",
    "addr:housenumber":"1201",
    "addr:postcode":"34787",
    "addr:street":"Winter Green Way",
    "iso:country":"US",
    "sg:address":"1201 Winter Green Way",
    "sg:city":"Winter Garden",
    "sg:classifiers":[
        {
            "category":"Retail",
            "subcategory":"Laundry & Dry Cleaning",
            "type":"Services"
        }
    ],
    "sg:phone":"+1 407 656 8872",
    "sg:postcode":"34787",
    "sg:province":"FL",
    "sg:tags":[
        "cleaners"
    ],
    "wof:name":"V U Cleaners",
    "wof:placetype":"venue"
},
  "geometry": {"coordinates":[-81.595719,28.545634],"type":"Point"}
}