{
  "type": "Feature",
  "properties": {
    "addr:full":"5390 Laurie Ln Middleburg FL 32068",
    "addr:housenumber":"5390",
    "addr:postcode":"32068",
    "addr:street":"Laurie Ln",
    "iso:country":"US",
    "sg:address":"5390 Laurie Ln",
    "sg:city":"Middleburg",
    "sg:classifiers":[
        {
            "category":"Building & Trades",
            "subcategory":"Construction",
            "type":"Services"
        }
    ],
    "sg:phone":"+1 904 282 0860",
    "sg:postcode":"32068",
    "sg:province":"FL",
    "sg:tags":[
        "tile",
        "dealer"
    ],
    "wof:name":"Jeff Davis Tile & Marble",
    "wof:placetype":"venue"
},
  "geometry": {"coordinates":[-81.957257,30.104078],"type":"Point"}
}