{
  "type": "Feature",
  "properties": {
    "iso:country":"US",
    "sg:address":"291 Triplet Lake Dr",
    "sg:city":"Casselberry",
    "sg:classifiers":[
        {
            "category":"Shopping",
            "subcategory":"Bicycles & Sporting Goods",
            "type":"Retail Goods"
        }
    ],
    "sg:phone":"+1 407 695 3600",
    "sg:postcode":"32707",
    "sg:province":"FL",
    "wof:name":"Busy Body Inc",
    "wof:placetype":"venue"
},
  "geometry": {"coordinates":[-81.333158,28.669474],"type":"Point"}
}