{
  "type": "Feature",
  "properties": {
    "addr:full":"260 Columbus St Port Saint Joe FL 32456",
    "addr:housenumber":"260",
    "addr:postcode":"32456",
    "addr:street":"Columbus St",
    "iso:country":"US",
    "sg:address":"260 Columbus St",
    "sg:city":"Port Saint Joe",
    "sg:classifiers":[
        {
            "category":"Food & Beverages",
            "subcategory":"Groceries & Convenience Stores",
            "type":"Retail Goods"
        }
    ],
    "sg:phone":"+1 850 647 5880",
    "sg:postcode":"32456",
    "sg:province":"FL",
    "wof:name":"United Fd & Coml Wkrs Intl Un",
    "wof:placetype":"venue"
},
  "geometry": {"coordinates":[-85.364983,29.90369],"type":"Point"}
}