{
  "type": "Feature",
  "properties": {
    "addr:full":"2010 Canterbury Dr Indialantic FL 32903",
    "addr:housenumber":"2010",
    "addr:postcode":"32903",
    "addr:street":"Canterbury Dr",
    "iso:country":"US",
    "sg:address":"2010 Canterbury Dr",
    "sg:city":"Indialantic",
    "sg:classifiers":[
        {
            "category":"Professional",
            "type":"Services"
        }
    ],
    "sg:phone":"+1 321 724 9409",
    "sg:postcode":"32903",
    "sg:province":"FL",
    "sg:tags":[
        "establishment"
    ],
    "wof:name":"Cloisters Clubhouse",
    "wof:placetype":"venue"
},
  "geometry": {"coordinates":[-80.58287199999999,28.108657],"type":"Point"}
}