{
  "type": "Feature",
  "properties": {
    "addr:full":"433 W Plz Real Boca Raton FL 33432",
    "addr:housenumber":"433",
    "addr:postcode":"33432",
    "addr:street":"W Plz Real",
    "iso:country":"US",
    "sg:address":"433 W Plz Real",
    "sg:city":"Boca Raton",
    "sg:classifiers":[
        {
            "category":"Health Services",
            "subcategory":"Chiropractor",
            "type":"Services"
        }
    ],
    "sg:phone":"+1 561 338 9700",
    "sg:postcode":"33432",
    "sg:province":"FL",
    "wof:name":"Advanced Spinal Tech Inc",
    "wof:placetype":"venue"
},
  "geometry": {"coordinates":[-80.085515,26.355536],"type":"Point"}
}