{
  "type": "Feature",
  "properties": {
    "addr:full":"10780 NW 52nd St Doral FL 33178",
    "addr:housenumber":"10780",
    "addr:postcode":"33178",
    "addr:street":"Nw 52Nd St",
    "iso:country":"US",
    "sg:address":"10780 NW 52nd St",
    "sg:city":"Doral",
    "sg:classifiers":[
        {
            "category":"Professional",
            "subcategory":"Engineering",
            "type":"Services"
        }
    ],
    "sg:phone":"+1 305 639 2526",
    "sg:postcode":"33178",
    "sg:province":"FL",
    "sg:website":"www.hd-engineering.com",
    "wof:name":"H & D Engineering Corp",
    "wof:placetype":"venue"
},
  "geometry": {"coordinates":[-80.371802,25.82176],"type":"Point"}
}