{
  "type": "Feature",
  "properties": {
    "addr:full":"1377 N Harbor City Blvd Melbourne FL 32935",
    "addr:housenumber":"1377",
    "addr:postcode":"32935",
    "addr:street":"N Harbor City Blvd",
    "iso:country":"US",
    "sg:address":"1377 N Harbor City Blvd",
    "sg:city":"Melbourne",
    "sg:classifiers":[
        {
            "category":"Restaurant",
            "type":"Food & Drink"
        }
    ],
    "sg:phone":"+1 321 254 4380",
    "sg:postcode":"32935",
    "sg:province":"FL",
    "sg:tags":[
        "eating"
    ],
    "wof:name":"Subway",
    "wof:placetype":"venue"
},
  "geometry": {"coordinates":[-80.63047400000001,28.13023],"type":"Point"}
}