{
  "type": "Feature",
  "properties": {
    "iso:country":"US",
    "sg:address":"973 SW 8th St",
    "sg:city":"Miami",
    "sg:classifiers":[
        {
            "category":"Professional",
            "subcategory":"Business Services",
            "type":"Services"
        },
        {
            "category":"Government",
            "subcategory":"Post Office",
            "type":"Public Place"
        }
    ],
    "sg:phone":"+1 305 857 9188",
    "sg:postcode":"33130",
    "sg:province":"FL",
    "sg:tags":[
        "delivery",
        "messenger",
        "courier"
    ],
    "wof:name":"Eagle Express Messenger",
    "wof:placetype":"venue"
},
  "geometry": {"coordinates":[-80.21061899999999,25.765961],"type":"Point"}
}