{
  "type": "Feature",
  "properties": {
    "iso:country":"US",
    "sg:address":"7416 NW 8th St",
    "sg:city":"Miami",
    "sg:classifiers":[
        {
            "category":"Retail",
            "subcategory":"Repair Shop",
            "type":"Services"
        }
    ],
    "sg:phone":"+1 305 262 4441",
    "sg:postcode":"33126",
    "sg:province":"FL",
    "sg:tags":[
        "upholsterer"
    ],
    "wof:name":"Sergio Acosta Upholstery",
    "wof:placetype":"venue"
},
  "geometry": {"coordinates":[-80.31544,25.778404],"type":"Point"}
}