{
  "type": "Feature",
  "properties": {
    "addr:full":"11780 SW 9th Ct Pembroke Pines FL 33025",
    "addr:housenumber":"11780",
    "addr:postcode":"33025",
    "addr:street":"Sw 9Th Ct",
    "iso:country":"US",
    "sg:address":"11780 SW 9th Ct",
    "sg:city":"Pembroke Pines",
    "sg:classifiers":[
        {
            "category":"Personal",
            "type":"Services"
        }
    ],
    "sg:phone":"+1 954 885 9539",
    "sg:postcode":"33025",
    "sg:province":"FL",
    "sg:tags":[
        "credit",
        "debt",
        "counseling"
    ],
    "wof:name":"Equitable Resources Inc",
    "wof:placetype":"venue"
},
  "geometry": {"coordinates":[-80.30441,26.000049],"type":"Point"}
}