{
  "type": "Feature",
  "properties": {
    "iso:country":"US",
    "sg:address":"3070 Blanding Blvd",
    "sg:city":"Middleburg",
    "sg:classifiers":[
        {
            "category":"Building & Trades",
            "subcategory":"Construction",
            "type":"Services"
        },
        {
            "category":"Manufacturing",
            "subcategory":"Chemicals & Compounds",
            "type":"Manufacturing & Wholesale Goods"
        }
    ],
    "sg:phone":"+1 904 282 3431",
    "sg:postcode":"32068",
    "sg:province":"FL",
    "sg:tags":[
        "for",
        "mfg",
        "residential",
        "commercial",
        "vinyl",
        "coating",
        "painter"
    ],
    "wof:name":"Vanguard Vinyl Coatings Inc",
    "wof:placetype":"venue"
},
  "geometry": {"coordinates":[-81.89544600000001,30.041235],"type":"Point"}
}