{
  "type": "Feature",
  "properties": {
    "addr:full":"37837 Cecil Ln Zephyrhills FL 33542",
    "addr:housenumber":"37837",
    "addr:postcode":"33542",
    "addr:street":"Cecil Ln",
    "iso:country":"US",
    "sg:address":"37837 Cecil Ln",
    "sg:city":"Zephyrhills",
    "sg:classifiers":[
        {
            "category":"Shopping",
            "subcategory":"Used Merchandise",
            "type":"Retail Goods"
        }
    ],
    "sg:phone":"+1 813 782 1727",
    "sg:postcode":"33542",
    "sg:province":"FL",
    "sg:tags":[
        "repair"
    ],
    "wof:name":"Hanks Music Enterprises",
    "wof:placetype":"venue"
},
  "geometry": {"coordinates":[-82.19153900000001,28.249252],"type":"Point"}
}