{
  "type": "Feature",
  "properties": {
    "iso:country":"US",
    "sg:address":"450 N Park Rd",
    "sg:city":"Hollywood",
    "sg:classifiers":[
        {
            "category":"Insurance",
            "subcategory":"Title Insurance",
            "type":"Services"
        }
    ],
    "sg:phone":"+1 954 893 5788",
    "sg:postcode":"33021",
    "sg:province":"FL",
    "wof:name":"Title Closers Inc",
    "wof:placetype":"venue"
},
  "geometry": {"coordinates":[-80.175563,26.011208],"type":"Point"}
}