{
  "type": "Feature",
  "properties": {
    "addr:full":"3800 N Cocoa Blvd Cocoa FL 32926",
    "addr:housenumber":"3800",
    "addr:postcode":"32926",
    "addr:street":"N Cocoa Blvd",
    "iso:country":"US",
    "sg:address":"3800 N Cocoa Blvd",
    "sg:city":"Cocoa",
    "sg:classifiers":[
        {
            "category":"Home & Garden",
            "subcategory":"Building Materials",
            "type":"Retail Goods"
        }
    ],
    "sg:phone":"+1 321 631 1341",
    "sg:postcode":"32926",
    "sg:province":"FL",
    "sg:tags":[
        "glass",
        "window",
        "plate"
    ],
    "wof:name":"Central Florida Glass & Mirror",
    "wof:placetype":"venue"
},
  "geometry": {"coordinates":[-80.757036,28.422406],"type":"Point"}
}