{
  "type": "Feature",
  "properties": {
    "iso:country":"US",
    "sg:address":"397 Shackelford Rd",
    "sg:city":"Wauchula",
    "sg:classifiers":[
        {
            "category":"Farming",
            "subcategory":"Nursery",
            "type":"Manufacturing & Wholesale Goods"
        }
    ],
    "sg:phone":"+1 863 773 4853",
    "sg:postcode":"33873",
    "sg:province":"FL",
    "sg:tags":[
        "florist",
        "ornamental"
    ],
    "wof:name":"Voogd Growers",
    "wof:placetype":"venue"
},
  "geometry": {"coordinates":[-81.77667700000001,27.542736],"type":"Point"}
}