{
  "type": "Feature",
  "properties": {
    "addr:full":"2904 Abbey Ct Winter Park FL 32792",
    "addr:housenumber":"2904",
    "addr:postcode":"32792",
    "addr:street":"Abbey Ct",
    "iso:country":"US",
    "sg:address":"2904 Abbey Ct",
    "sg:city":"Winter Park",
    "sg:classifiers":[
        {
            "category":"Professional",
            "subcategory":"Management & Consulting",
            "type":"Services"
        }
    ],
    "sg:phone":"+1 407 679 5613",
    "sg:postcode":"32792",
    "sg:province":"FL",
    "sg:tags":[
        "consultant"
    ],
    "wof:name":"Lightware Technologies Inc",
    "wof:placetype":"venue"
},
  "geometry": {"coordinates":[-81.310412,28.600314],"type":"Point"}
}