{
  "type": "Feature",
  "properties": {
    "iso:country":"US",
    "sg:address":"9501 US Hwy 19",
    "sg:city":"Port Richey",
    "sg:classifiers":[
        {
            "category":"Banks & Credit Unions",
            "subcategory":"Bank",
            "type":"Services"
        }
    ],
    "sg:phone":"+1 727 859 9444",
    "sg:postcode":"34668",
    "sg:province":"FL",
    "sg:tags":[
        "loan",
        "real estate"
    ],
    "wof:name":"Mortgage One Finance Corp",
    "wof:placetype":"venue"
},
  "geometry": {"coordinates":[-82.707329,28.297292],"type":"Point"}
}