{
  "type": "Feature",
  "properties": {
    "iso:country":"US",
    "sg:address":"449 Gokchoff Rd",
    "sg:city":"Fort Pierce",
    "sg:classifiers":[
        {
            "category":"Restaurant",
            "type":"Food & Drink"
        }
    ],
    "sg:phone":"+1 772 465 1321",
    "sg:postcode":"34945",
    "sg:province":"FL",
    "sg:tags":[
        "eating"
    ],
    "wof:name":"Carnell Co of Fort Pierce",
    "wof:placetype":"venue"
},
  "geometry": {"coordinates":[-80.420108,27.444447],"type":"Point"}
}