{
  "type": "Feature",
  "properties": {
    "iso:country":"US",
    "sg:address":"3655 S Suncoast Blvd",
    "sg:city":"Homosassa",
    "sg:classifiers":[
        {
            "category":"Banks & Credit Unions",
            "subcategory":"Investment Brokerage",
            "type":"Services"
        }
    ],
    "sg:phone":"+1 352 628 9009",
    "sg:postcode":"34448",
    "sg:province":"FL",
    "sg:tags":[
        "advisory",
        "financial"
    ],
    "wof:name":"Financial Services Support Grp",
    "wof:placetype":"venue"
},
  "geometry": {"coordinates":[-82.57645599999999,28.808317],"type":"Point"}
}