{
  "type": "Feature",
  "properties": {
    "addr:full":"41 Wood Owl Ave Ellenton FL 34222",
    "addr:housenumber":"41",
    "addr:postcode":"34222",
    "addr:street":"Wood Owl Ave",
    "iso:country":"US",
    "sg:address":"41 Wood Owl Ave",
    "sg:city":"Ellenton",
    "sg:classifiers":[
        {
            "category":"Organizations",
            "subcategory":"Religious Organization",
            "type":"Services"
        }
    ],
    "sg:phone":"+1 941 723 9771",
    "sg:postcode":"34222",
    "sg:province":"FL",
    "wof:name":"New Start Ministry Ellenton",
    "wof:placetype":"venue"
},
  "geometry": {"coordinates":[-82.49326000000001,27.538705],"type":"Point"}
}