{
  "type": "Feature",
  "properties": {
    "addr:full":"440 Royal Palm Way Palm Beach FL 33480",
    "addr:housenumber":"440",
    "addr:postcode":"33480",
    "addr:street":"Royal Palm Way",
    "iso:country":"US",
    "sg:address":"440 Royal Palm Way",
    "sg:city":"Palm Beach",
    "sg:classifiers":[
        {
            "category":"Banks & Credit Unions",
            "subcategory":"Investment Brokerage",
            "type":"Services"
        }
    ],
    "sg:phone":"+1 561 659 9500",
    "sg:postcode":"33480",
    "sg:province":"FL",
    "sg:tags":[
        "stock",
        "bond"
    ],
    "wof:name":"UBS Financial Svc",
    "wof:placetype":"venue"
},
  "geometry": {"coordinates":[-80.04313,26.705702],"type":"Point"}
}