{
  "type": "Feature",
  "properties": {
    "addr:full":"5330 Berryhill Rd Milton FL 32570",
    "addr:housenumber":"5330",
    "addr:postcode":"32570",
    "addr:street":"Berryhill Rd",
    "iso:country":"US",
    "sg:address":"5330 Berryhill Rd",
    "sg:city":"Milton",
    "sg:classifiers":[
        {
            "category":"Government",
            "subcategory":"Office",
            "type":"Public Place"
        }
    ],
    "sg:phone":"+1 850 626 2124",
    "sg:postcode":"32570",
    "sg:province":"FL",
    "sg:tags":[
        "state",
        "program"
    ],
    "wof:name":"Vocational Rehabilitation Div",
    "wof:placetype":"venue"
},
  "geometry": {"coordinates":[-87.10082800000001,30.646837],"type":"Point"}
}