{
  "type": "Feature",
  "properties": {
    "iso:country":"US",
    "sg:address":"3785 NW 82nd Ave",
    "sg:city":"Miami",
    "sg:classifiers":[
        {
            "category":"Health Services",
            "subcategory":"Doctor",
            "type":"Services"
        }
    ],
    "sg:phone":"+1 305 805 3315",
    "sg:postcode":"33166",
    "sg:province":"FL",
    "sg:tags":[
        "medical"
    ],
    "wof:name":"Drs Eagle Inc",
    "wof:placetype":"venue"
},
  "geometry": {"coordinates":[-80.329295,25.809727],"type":"Point"}
}