{
  "type": "Feature",
  "properties": {
    "addr:full":"3813 S Lake Ter Hollywood FL 33023",
    "addr:housenumber":"3813",
    "addr:postcode":"33023",
    "addr:street":"S Lake Ter",
    "iso:country":"US",
    "sg:address":"3813 S Lake Ter",
    "sg:city":"Hollywood",
    "sg:classifiers":[
        {
            "category":"Building & Trades",
            "subcategory":"Construction",
            "type":"Services"
        }
    ],
    "sg:phone":"+1 954 964 5474",
    "sg:postcode":"33023",
    "sg:province":"FL",
    "sg:tags":[
        "concrete",
        "contractor"
    ],
    "wof:name":"Marco Gallegos",
    "wof:placetype":"venue"
},
  "geometry": {"coordinates":[-80.219043,25.973079],"type":"Point"}
}