{
  "type": "Feature",
  "properties": {
    "addr:full":"1241 Wyndcliff Dr Wellington FL 33414",
    "addr:housenumber":"1241",
    "addr:postcode":"33414",
    "addr:street":"Wyndcliff Dr",
    "iso:country":"US",
    "sg:address":"1241 Wyndcliff Dr",
    "sg:city":"Wellington",
    "sg:classifiers":[
        {
            "category":"Personal",
            "subcategory":"Beauty Salon",
            "type":"Services"
        }
    ],
    "sg:phone":"+1 561 721 1410",
    "sg:postcode":"33414",
    "sg:province":"FL",
    "sg:tags":[
        "manicuring"
    ],
    "wof:name":"Leslie Nail Supply",
    "wof:placetype":"venue"
},
  "geometry": {"coordinates":[-80.23065200000001,26.661344],"type":"Point"}
}