{
  "type": "Feature",
  "properties": {
    "addr:full":"6931 NW 87th Ave Miami FL 33178",
    "addr:housenumber":"6931",
    "addr:postcode":"33178",
    "addr:street":"Nw 87Th Ave",
    "iso:country":"US",
    "sg:address":"6931 NW 87th Ave",
    "sg:city":"Miami",
    "sg:classifiers":[
        {
            "category":"Transit Center",
            "subcategory":"Freight",
            "type":"Transportation"
        },
        {
            "category":"Professional",
            "subcategory":"Business Services",
            "type":"Services"
        },
        {
            "category":"Freight",
            "type":"Transportation"
        }
    ],
    "sg:phone":"+1 786 336 0644",
    "sg:postcode":"33178",
    "sg:province":"FL",
    "sg:tags":[
        "trucking-motor",
        "shipping",
        "trucking"
    ],
    "wof:name":"Supreme International Freight",
    "wof:placetype":"venue"
},
  "geometry": {"coordinates":[-80.33809100000001,25.836455],"type":"Point"}
}