{
  "type": "Feature",
  "properties": {
    "iso:country":"US",
    "sg:address":"3591 Landmark Trl",
    "sg:city":"Palm Harbor",
    "sg:classifiers":[
        {
            "category":"Health Services",
            "subcategory":"Doctor",
            "type":"Services"
        }
    ],
    "sg:phone":"+1 727 785 4873",
    "sg:postcode":"34684",
    "sg:province":"FL",
    "sg:tags":[
        "medical"
    ],
    "wof:name":"S G Weiss MD Inc",
    "wof:placetype":"venue"
},
  "geometry": {"coordinates":[-82.714142,28.050324],"type":"Point"}
}