{
  "type": "Feature",
  "properties": {
    "addr:full":"5151 Old Berryhill Rd Milton FL 32570",
    "addr:housenumber":"5151",
    "addr:postcode":"32570",
    "addr:street":"Old Berryhill Rd",
    "iso:country":"US",
    "sg:address":"5151 Old Berryhill Rd",
    "sg:city":"Milton",
    "sg:classifiers":[
        {
            "category":"Building & Trades",
            "subcategory":"Construction",
            "type":"Services"
        }
    ],
    "sg:phone":"+1 850 623 0494",
    "sg:postcode":"32570",
    "sg:province":"FL",
    "sg:tags":[
        "house"
    ],
    "wof:name":"Danny Holt Construction",
    "wof:placetype":"venue"
},
  "geometry": {"coordinates":[-87.106263,30.64263],"type":"Point"}
}