{
  "type": "Feature",
  "properties": {
    "iso:country":"US",
    "sg:address":"1502 Lily Pond Ct",
    "sg:city":"Fort Myers",
    "sg:classifiers":[
        {
            "category":"Building & Trades",
            "subcategory":"Construction",
            "type":"Services"
        }
    ],
    "sg:phone":"+1 239 489 3101",
    "sg:postcode":"33901",
    "sg:province":"FL",
    "sg:tags":[
        "interior",
        "design"
    ],
    "wof:name":"Hunting Catherine Interiors Inc",
    "wof:placetype":"venue"
},
  "geometry": {"coordinates":[-81.883386,26.600641],"type":"Point"}
}