{
  "type": "Feature",
  "properties": {
    "iso:country":"US",
    "sg:address":"925 S Orlando Ave",
    "sg:city":"Maitland",
    "sg:classifiers":[
        {
            "category":"Personal",
            "subcategory":"Beauty Salon",
            "type":"Services"
        },
        {
            "category":"Personal",
            "subcategory":"Nail Salon",
            "type":"Services"
        }
    ],
    "sg:phone":"+1 407 712 4884",
    "sg:postcode":"32751",
    "sg:province":"FL",
    "sg:website":"http://www.StudioBeautifulSalon.com",
    "wof:name":"Studio B",
    "wof:placetype":"venue"
},
  "geometry": {"coordinates":[-81.365433,28.620142],"type":"Point"}
}