{
  "type": "Feature",
  "properties": {
    "addr:full":"542 Washington Ave Miami FL 33139",
    "addr:housenumber":"542",
    "addr:postcode":"33139",
    "addr:street":"Washington Ave",
    "iso:country":"US",
    "sg:address":"542 Washington Ave",
    "sg:city":"Miami",
    "sg:classifiers":[
        {
            "category":"Professional",
            "subcategory":"Lawyer & Legal Services",
            "type":"Services"
        }
    ],
    "sg:phone":"+1 305 674 1515",
    "sg:postcode":"33139",
    "sg:province":"FL",
    "sg:tags":[
        "attorney"
    ],
    "wof:name":"Immigration Law Offices",
    "wof:placetype":"venue"
},
  "geometry": {"coordinates":[-80.134091,25.775109],"type":"Point"}
}