{
  "type": "Feature",
  "properties": {
    "iso:country":"US",
    "sg:address":"545 W 12th Pl",
    "sg:city":"Hialeah",
    "sg:classifiers":[
        {
            "category":"Building & Trades",
            "subcategory":"Construction",
            "type":"Services"
        }
    ],
    "sg:phone":"+1 305 665 1909",
    "sg:postcode":"33010",
    "sg:province":"FL",
    "sg:tags":[
        "general",
        "contractor"
    ],
    "wof:name":"Form & Function Inc",
    "wof:placetype":"venue"
},
  "geometry": {"coordinates":[-80.29282600000001,25.83299],"type":"Point"}
}