{
  "type": "Feature",
  "properties": {
    "iso:country":"US",
    "sg:address":"4302 Redwood Dr",
    "sg:city":"Fort Pierce",
    "sg:classifiers":[
        {
            "category":"Building & Trades",
            "subcategory":"Cleaning & Sanitation",
            "type":"Services"
        }
    ],
    "sg:phone":"+1 772 595 1917",
    "sg:postcode":"34951",
    "sg:province":"FL",
    "sg:tags":[
        "janitor"
    ],
    "wof:name":"Clean Sweep Cleaning Svc",
    "wof:placetype":"venue"
},
  "geometry": {"coordinates":[-80.382756,27.525628],"type":"Point"}
}