{
  "type": "Feature",
  "properties": {
    "iso:country":"US",
    "sg:address":"8685 93rd Ave",
    "sg:city":"Largo",
    "sg:classifiers":[
        {
            "category":"Utilities",
            "type":"Services"
        }
    ],
    "sg:phone":"+1 727 392 1020",
    "sg:postcode":"33777",
    "sg:province":"FL",
    "sg:tags":[
        "sweeping",
        "sanitary",
        "trade",
        "contractor"
    ],
    "wof:name":"Dave's Power Sweeping",
    "wof:placetype":"venue"
},
  "geometry": {"coordinates":[-82.760775,27.857063],"type":"Point"}
}