{
  "type": "Feature",
  "properties": {
    "iso:country":"US",
    "sg:address":"680 S Lake Shore Way",
    "sg:city":"Lake Alfred",
    "sg:classifiers":[
        {
            "category":"Personal",
            "subcategory":"Barber",
            "type":"Services"
        }
    ],
    "sg:phone":"+1 863 956 3283",
    "sg:postcode":"33850",
    "sg:province":"FL",
    "sg:tags":[
        "shop"
    ],
    "wof:name":"Lake Alfred City Barber Shop",
    "wof:placetype":"venue"
},
  "geometry": {"coordinates":[-81.72977,28.085475],"type":"Point"}
}