{
  "type": "Feature",
  "properties": {
    "addr:full":"5505 38th Ave N St Petersburg FL 33710",
    "addr:housenumber":"5505",
    "addr:postcode":"33710",
    "addr:street":"38Th Ave N",
    "iso:country":"US",
    "sg:address":"5505 38th Ave N",
    "sg:city":"St Petersburg",
    "sg:classifiers":[
        {
            "category":"Professional",
            "subcategory":"Accounting & Tax Preparation",
            "type":"Services"
        }
    ],
    "sg:phone":"+1 727 384 4888",
    "sg:postcode":"33710",
    "sg:province":"FL",
    "sg:tags":[
        "accountant"
    ],
    "wof:name":"Raymond J Hetterich CPA",
    "wof:placetype":"venue"
},
  "geometry": {"coordinates":[-82.709109,27.806481],"type":"Point"}
}