{
  "type": "Feature",
  "properties": {
    "iso:country":"US",
    "sg:address":"442 W Kennedy Blvd # 160",
    "sg:city":"Tampa",
    "sg:classifiers":[
        {
            "category":"Personal",
            "type":"Services"
        }
    ],
    "sg:phone":"+1 813 254 6511",
    "sg:postcode":"33606",
    "sg:province":"FL",
    "sg:tags":[
        "assistant"
    ],
    "sg:website":"http://www.fireflytechnologies.com",
    "wof:name":"Firefly Technologies",
    "wof:placetype":"venue"
},
  "geometry": {"coordinates":[-82.464479,27.945285],"type":"Point"}
}