{
  "type": "Feature",
  "properties": {
    "iso:country":"US",
    "sg:address":"2800 W Tennessee St",
    "sg:city":"Tallahassee",
    "sg:classifiers":[
        {
            "category":"Autos & Motor Vehicles",
            "subcategory":"Automobile Sales",
            "type":"Retail Goods"
        }
    ],
    "sg:phone":"+1 850 575 6600",
    "sg:postcode":"32304",
    "sg:province":"FL",
    "wof:name":"First Team Isuzu",
    "wof:placetype":"venue"
},
  "geometry": {"coordinates":[-84.34351599999999,30.455589],"type":"Point"}
}