{
  "type": "Feature",
  "properties": {
    "iso:country":"US",
    "sg:address":"1544 W Flagler St",
    "sg:city":"Miami",
    "sg:classifiers":[
        {
            "category":"Shopping",
            "subcategory":"Bicycles & Sporting Goods",
            "type":"Retail Goods"
        }
    ],
    "sg:phone":"+1 305 649 8882",
    "sg:postcode":"33135",
    "sg:province":"FL",
    "wof:name":"Galifutbol Soccer Outlet",
    "wof:placetype":"venue"
},
  "geometry": {"coordinates":[-80.220685,25.773247],"type":"Point"}
}