{
  "type": "Feature",
  "properties": {
    "iso:country":"US",
    "sg:address":"9155 S Dadeland Blvd",
    "sg:city":"Miami",
    "sg:classifiers":[
        {
            "category":"Professional",
            "subcategory":"Lawyer & Legal Services",
            "type":"Services"
        }
    ],
    "sg:phone":"+1 305 373 2888",
    "sg:postcode":"33156",
    "sg:province":"FL",
    "wof:name":"Craig Lawrance B III Atty",
    "wof:placetype":"venue"
},
  "geometry": {"coordinates":[-80.31529999999999,25.6847],"type":"Point"}
}