{
  "type": "Feature",
  "properties": {
    "addr:full":"1420 16th Ave NE Naples FL 34120",
    "addr:housenumber":"1420",
    "addr:postcode":"34120",
    "addr:street":"16Th Ave Ne",
    "iso:country":"US",
    "sg:address":"1420 16th Ave NE",
    "sg:city":"Naples",
    "sg:classifiers":[
        {
            "category":"Building & Trades",
            "subcategory":"Construction",
            "type":"Services"
        }
    ],
    "sg:phone":"+1 239 353 8211",
    "sg:postcode":"34120",
    "sg:province":"FL",
    "sg:tags":[
        "concrete",
        "contractor"
    ],
    "wof:name":"Keith Hartmann Concrete Pumpin",
    "wof:placetype":"venue"
},
  "geometry": {"coordinates":[-81.574606,26.259428],"type":"Point"}
}