{
  "type": "Feature",
  "properties": {
    "iso:country":"US",
    "sg:address":"2535 W Tennessee St",
    "sg:city":"Tallahassee",
    "sg:classifiers":[
        {
            "category":"Building & Trades",
            "subcategory":"Construction",
            "type":"Services"
        }
    ],
    "sg:phone":"+1 850 576 6542",
    "sg:postcode":"32304",
    "sg:province":"FL",
    "sg:tags":[
        "contractor"
    ],
    "wof:name":"Jim Walter Mortgage Inc",
    "wof:placetype":"venue"
},
  "geometry": {"coordinates":[-84.331745,30.449748],"type":"Point"}
}