{
  "type": "Feature",
  "properties": {
    "iso:country":"US",
    "sg:address":"1312 SW 19th St",
    "sg:city":"Fort Lauderdale",
    "sg:classifiers":[
        {
            "category":"Wholesale",
            "subcategory":"Non-durable Goods",
            "type":"Manufacturing & Wholesale Goods"
        }
    ],
    "sg:phone":"+1 954 779 1083",
    "sg:postcode":"33315",
    "sg:province":"FL",
    "wof:name":"Suttons Bay Trading Co",
    "wof:placetype":"venue"
},
  "geometry": {"coordinates":[-80.15890400000001,26.096984],"type":"Point"}
}