{
  "type": "Feature",
  "properties": {
    "iso:country":"US",
    "sg:address":"60 Cordona Dr",
    "sg:city":"Kissimmee",
    "sg:classifiers":[
        {
            "category":"Real Estate",
            "subcategory":"Real Estate Services",
            "type":"Services"
        }
    ],
    "sg:phone":"+1 407 944 1973",
    "sg:postcode":"34758",
    "sg:province":"FL",
    "sg:tags":[
        "buyer",
        "broker"
    ],
    "wof:name":"Kema Properties",
    "wof:placetype":"venue"
},
  "geometry": {"coordinates":[-81.44689700000001,28.150167],"type":"Point"}
}