{
  "type": "Feature",
  "properties": {
    "iso:country":"US",
    "sg:address":"644 Old Dixie Hwy SW",
    "sg:city":"Vero Beach",
    "sg:classifiers":[
        {
            "category":"Home & Garden",
            "subcategory":"Hardware",
            "type":"Retail Goods"
        }
    ],
    "sg:phone":"+1 772 567 0096",
    "sg:postcode":"32962",
    "sg:province":"FL",
    "wof:name":"Fastenal Co",
    "wof:placetype":"venue"
},
  "geometry": {"coordinates":[-80.380898,27.591183],"type":"Point"}
}