{
  "type": "Feature",
  "properties": {
    "iso:country":"US",
    "sg:address":"10001 NW 5th St",
    "sg:city":"Fort Lauderdale",
    "sg:classifiers":[
        {
            "category":"Freight",
            "type":"Transportation"
        }
    ],
    "sg:phone":"+1 954 423 2239",
    "sg:postcode":"33324",
    "sg:province":"FL",
    "sg:tags":[
        "general"
    ],
    "wof:name":"BGB Ltd",
    "wof:placetype":"venue"
},
  "geometry": {"coordinates":[-80.283489,26.127983],"type":"Point"}
}