{
  "type": "Feature",
  "properties": {
    "iso:country":"US",
    "sg:address":"6215 Pine Ln",
    "sg:city":"Lakeland",
    "sg:classifiers":[
        {
            "category":"Wholesale",
            "subcategory":"Vending Machines",
            "type":"Manufacturing & Wholesale Goods"
        }
    ],
    "sg:phone":"+1 863 644 5966",
    "sg:postcode":"33813",
    "sg:province":"FL",
    "sg:tags":[
        "operator"
    ],
    "wof:name":"Total Refreshment Ctr Vend Svc",
    "wof:placetype":"venue"
},
  "geometry": {"coordinates":[-81.961174,27.951255],"type":"Point"}
}