{
  "type": "Feature",
  "properties": {
    "iso:country":"US",
    "sg:address":"35 NE 25th Ave",
    "sg:city":"Pompano Beach",
    "sg:classifiers":[
        {
            "category":"Retail",
            "subcategory":"Veterinary Services",
            "type":"Services"
        }
    ],
    "sg:phone":"+1 954 942 3323",
    "sg:postcode":"33062",
    "sg:province":"FL",
    "sg:tags":[
        "veterinarian"
    ],
    "wof:name":"Wilson J Martin Dvm",
    "wof:placetype":"venue"
},
  "geometry": {"coordinates":[-80.099118,26.233346],"type":"Point"}
}