{
  "type": "Feature",
  "properties": {
    "addr:full":"6788 Lantana Rd Lake Worth FL 33467",
    "addr:housenumber":"6788",
    "addr:postcode":"33467",
    "addr:street":"Lantana Rd",
    "iso:country":"US",
    "sg:address":"6788 Lantana Rd",
    "sg:city":"Lake Worth",
    "sg:classifiers":[
        {
            "category":"Freight",
            "type":"Transportation"
        }
    ],
    "sg:phone":"+1 561 641 0606",
    "sg:postcode":"33467",
    "sg:province":"FL",
    "sg:tags":[
        "commercial",
        "storage"
    ],
    "wof:name":"U-Store-It",
    "wof:placetype":"venue"
},
  "geometry": {"coordinates":[-80.149838,26.589608],"type":"Point"}
}