{
  "type": "Feature",
  "properties": {
    "addr:full":"8043 Horse Ferry Rd Orlando FL 32835",
    "addr:housenumber":"8043",
    "addr:postcode":"32835",
    "addr:street":"Horse Ferry Rd",
    "iso:country":"US",
    "sg:address":"8043 Horse Ferry Rd",
    "sg:city":"Orlando",
    "sg:classifiers":[
        {
            "category":"Travel",
            "subcategory":"Travel Agent",
            "type":"Entertainment"
        },
        {
            "category":"Landmark",
            "subcategory":"Tourist Information",
            "type":"Public Place"
        }
    ],
    "sg:phone":"+1 407 299 9981",
    "sg:postcode":"32835",
    "sg:province":"FL",
    "sg:tags":[
        "agency",
        "services-commercial",
        "tours-operators",
        "promoter"
    ],
    "wof:name":"S A Tour And Travel Inc",
    "wof:placetype":"venue"
},
  "geometry": {"coordinates":[-81.503799,28.505564],"type":"Point"}
}