{
  "type": "Feature",
  "properties": {
    "addr:full":"812 17th Ave W Bradenton FL 34205",
    "addr:housenumber":"812",
    "addr:postcode":"34205",
    "addr:street":"17Th Ave W",
    "iso:country":"US",
    "sg:address":"812 17th Ave W",
    "sg:city":"Bradenton",
    "sg:classifiers":[
        {
            "category":"Fast Food",
            "type":"Food & Drink"
        },
        {
            "category":"Restaurant",
            "type":"Food & Drink"
        },
        {
            "category":"Professional",
            "type":"Services"
        }
    ],
    "sg:phone":"+1 941 747 7879",
    "sg:postcode":"34205",
    "sg:province":"FL",
    "sg:tags":[
        "delivery",
        "take",
        "pizza"
    ],
    "sg:website":"http://www.dominospizza.com",
    "wof:name":"Domino's Pizza",
    "wof:placetype":"venue"
},
  "geometry": {"coordinates":[-82.570323,27.484417],"type":"Point"}
}