{
  "type": "Feature",
  "properties": {
    "iso:country":"US",
    "sg:address":"6756 Ixora Dr",
    "sg:city":"Hollywood",
    "sg:classifiers":[
        {
            "category":"Building & Trades",
            "subcategory":"Construction",
            "type":"Services"
        }
    ],
    "sg:phone":"+1 954 987 8084",
    "sg:postcode":"33023",
    "sg:province":"FL",
    "sg:tags":[
        "contractor"
    ],
    "wof:name":"Absolute Roofing Inc",
    "wof:placetype":"venue"
},
  "geometry": {"coordinates":[-80.221452,25.972862],"type":"Point"}
}