{
  "type": "Feature",
  "properties": {
    "iso:country":"US",
    "sg:address":"2689 Sunset Point Rd",
    "sg:city":"Clearwater",
    "sg:classifiers":[
        {
            "category":"Wholesale",
            "subcategory":"Machinery & Supplies",
            "type":"Manufacturing & Wholesale Goods"
        }
    ],
    "sg:phone":"+1 727 723 0071",
    "sg:postcode":"33759",
    "sg:province":"FL",
    "sg:tags":[
        "equipment",
        "casket",
        "establishment"
    ],
    "wof:name":"Casket & Urn Gallery",
    "wof:placetype":"venue"
},
  "geometry": {"coordinates":[-82.72568099999999,27.990723],"type":"Point"}
}