{
  "type": "Feature",
  "properties": {
    "addr:full":"10103 E Colonial Dr Orlando FL 32817",
    "addr:housenumber":"10103",
    "addr:postcode":"32817",
    "addr:street":"E Colonial Dr",
    "iso:country":"US",
    "sg:address":"10103 E Colonial Dr",
    "sg:city":"Orlando",
    "sg:classifiers":[
        {
            "category":"Utilities",
            "subcategory":"Mobile Phone",
            "type":"Services"
        }
    ],
    "sg:phone":"+1 407 380 8686",
    "sg:postcode":"32817",
    "sg:province":"FL",
    "sg:tags":[
        "telephone",
        "cellular"
    ],
    "wof:name":"Cellular Oasis",
    "wof:placetype":"venue"
},
  "geometry": {"coordinates":[-81.24158,28.569614],"type":"Point"}
}