{
  "type": "Feature",
  "properties": {
    "addr:full":"3940 N Dean Rd Orlando FL 32817",
    "addr:housenumber":"3940",
    "addr:postcode":"32817",
    "addr:street":"N Dean Rd",
    "iso:country":"US",
    "sg:address":"3940 N Dean Rd",
    "sg:city":"Orlando",
    "sg:classifiers":[
        {
            "category":"Restaurant",
            "type":"Food & Drink"
        }
    ],
    "sg:menulink":"http://www.allmenus.com/fl/union-park/33827-donatos-pizza/menu/",
    "sg:phone":"+1 407 673 8888",
    "sg:postcode":"32817",
    "sg:province":"FL",
    "sg:tags":[
        "sandwich",
        "salad",
        "soup",
        "american",
        "wrap",
        "pizza"
    ],
    "wof:name":"Donatos Pizza",
    "wof:placetype":"venue"
},
  "geometry": {"coordinates":[-81.244748,28.596742],"type":"Point"}
}