{
  "type": "Feature",
  "properties": {
    "addr:full":"5170 S Ferdon Blvd Crestview FL 32536",
    "addr:housenumber":"5170",
    "addr:postcode":"32536",
    "addr:street":"S Ferdon Blvd",
    "iso:country":"US",
    "sg:address":"5170 S Ferdon Blvd",
    "sg:city":"Crestview",
    "sg:classifiers":[
        {
            "category":"Real Estate",
            "subcategory":"Real Estate Agent",
            "type":"Services"
        }
    ],
    "sg:phone":"+1 850 682 4953",
    "sg:postcode":"32536",
    "sg:province":"FL",
    "wof:name":"Best Choice Realty Inc",
    "wof:placetype":"venue"
},
  "geometry": {"coordinates":[-86.570937,30.704359],"type":"Point"}
}