{
  "type": "Feature",
  "properties": {
    "addr:full":"2185 W 76th St Hialeah FL 33016",
    "addr:housenumber":"2185",
    "addr:postcode":"33016",
    "addr:street":"W 76Th St",
    "iso:country":"US",
    "sg:address":"2185 W 76th St",
    "sg:city":"Hialeah",
    "sg:classifiers":[
        {
            "category":"Manufacturing",
            "subcategory":"Petroleum Products",
            "type":"Manufacturing & Wholesale Goods"
        },
        {
            "category":"Wholesale",
            "subcategory":"Petroleum",
            "type":"Manufacturing & Wholesale Goods"
        }
    ],
    "sg:phone":"+1 305 558 9911",
    "sg:postcode":"33016",
    "sg:province":"FL",
    "sg:tags":[
        "oil",
        "refiner",
        "products-wholesale",
        "manufacturer",
        "oils-petroleum"
    ],
    "sg:website":"http://www.pemcofl.com",
    "wof:name":"Petroleum Equipment & Manufacturing Co Inc",
    "wof:placetype":"venue"
},
  "geometry": {"coordinates":[-80.32777900000001,25.891511],"type":"Point"}
}