{
  "type": "Feature",
  "properties": {
    "iso:country":"US",
    "sg:address":"12720 E Wheeler Rd",
    "sg:city":"Dover",
    "sg:classifiers":[
        {
            "category":"Building & Trades",
            "subcategory":"Construction",
            "type":"Services"
        }
    ],
    "sg:phone":"+1 813 655 9886",
    "sg:postcode":"33527",
    "sg:province":"FL",
    "sg:tags":[
        "designer",
        "dealer",
        "pool",
        "swimming"
    ],
    "wof:name":"Jackson's Swimming Pools",
    "wof:placetype":"venue"
},
  "geometry": {"coordinates":[-82.252848,27.974349],"type":"Point"}
}