{
  "type": "Feature",
  "properties": {
    "addr:full":"3601 Rio Vista Blvd Vero Beach FL 32963",
    "addr:housenumber":"3601",
    "addr:postcode":"32963",
    "addr:street":"Rio Vista Blvd",
    "iso:country":"US",
    "sg:address":"3601 Rio Vista Blvd",
    "sg:city":"Vero Beach",
    "sg:classifiers":[
        {
            "category":"Recreation",
            "type":"Entertainment"
        }
    ],
    "sg:phone":"+1 772 231 2211",
    "sg:postcode":"32963",
    "sg:province":"FL",
    "sg:tags":[
        "club",
        "membership"
    ],
    "wof:name":"Vero Beach Yacht Club",
    "wof:placetype":"venue"
},
  "geometry": {"coordinates":[-80.3689,27.65746],"type":"Point"}
}