{
  "type": "Feature",
  "properties": {
    "iso:country":"US",
    "sg:address":"1510 Normandy Dr",
    "sg:city":"Miami Beach",
    "sg:classifiers":[
        {
            "category":"Professional",
            "type":"Services"
        }
    ],
    "sg:phone":"+1 305 868 0980",
    "sg:postcode":"33141",
    "sg:province":"FL",
    "wof:name":"Lemon Trap Inc",
    "wof:placetype":"venue"
},
  "geometry": {"coordinates":[-80.13736,25.852464],"type":"Point"}
}