{
  "type": "Feature",
  "properties": {
    "iso:country":"US",
    "sg:address":"1109 S Rome Ave",
    "sg:city":"Tampa",
    "sg:classifiers":[
        {
            "category":"Professional",
            "type":"Services"
        }
    ],
    "sg:phone":"+1 813 258 1884",
    "sg:postcode":"33606",
    "sg:province":"FL",
    "wof:name":"Debra Hempel Rodgers Co",
    "wof:placetype":"venue"
},
  "geometry": {"coordinates":[-82.476522,27.929369],"type":"Point"}
}