{
  "type": "Feature",
  "properties": {
    "addr:full":"1052 Pepperidge Dr Palm Harbor FL 34683",
    "addr:housenumber":"1052",
    "addr:postcode":"34683",
    "addr:street":"Pepperidge Dr",
    "iso:country":"US",
    "sg:address":"1052 Pepperidge Dr",
    "sg:city":"Palm Harbor",
    "sg:classifiers":[
        {
            "category":"Building & Trades",
            "subcategory":"Construction",
            "type":"Services"
        }
    ],
    "sg:phone":"+1 727 784 2433",
    "sg:postcode":"34683",
    "sg:province":"FL",
    "sg:tags":[
        "company"
    ],
    "wof:name":"Dias Construction Inc",
    "wof:placetype":"venue"
},
  "geometry": {"coordinates":[-82.766993,28.064769],"type":"Point"}
}