{
  "type": "Feature",
  "properties": {
    "iso:country":"US",
    "sg:address":"6810 SW 81st St",
    "sg:city":"Miami",
    "sg:classifiers":[
        {
            "category":"Retail",
            "subcategory":"Auto Repair",
            "type":"Services"
        }
    ],
    "sg:phone":"+1 305 666 1702",
    "sg:postcode":"33143",
    "sg:province":"FL",
    "sg:tags":[
        "repairing",
        "automobile"
    ],
    "wof:name":"Automobile Electric Parts",
    "wof:placetype":"venue"
},
  "geometry": {"coordinates":[-80.30282699999999,25.695309],"type":"Point"}
}