{
  "type": "Feature",
  "properties": {
    "iso:country":"US",
    "sg:address":"4584 Enterprise Ave",
    "sg:city":"Naples",
    "sg:classifiers":[
        {
            "category":"Restaurant",
            "type":"Food & Drink"
        }
    ],
    "sg:phone":"+1 239 261 2248",
    "sg:postcode":"34104",
    "sg:province":"FL",
    "sg:tags":[
        "eating",
        "caterer"
    ],
    "wof:name":"Budget Gourmet",
    "wof:placetype":"venue"
},
  "geometry": {"coordinates":[-81.75744400000001,26.160636],"type":"Point"}
}