{
  "type": "Feature",
  "properties": {
    "addr:full":"7845 Cam Real Miami FL 33143",
    "addr:housenumber":"7845",
    "addr:postcode":"33143",
    "addr:street":"Cam Real",
    "iso:country":"US",
    "sg:address":"7845 Cam Real",
    "sg:city":"Miami",
    "sg:classifiers":[
        {
            "category":"Professional",
            "subcategory":"Accounting & Tax Preparation",
            "type":"Services"
        }
    ],
    "sg:phone":"+1 305 279 6859",
    "sg:postcode":"33143",
    "sg:province":"FL",
    "wof:name":"Swiss Capital Corp",
    "wof:placetype":"venue"
},
  "geometry": {"coordinates":[-80.31997800000001,25.694508],"type":"Point"}
}