{
  "type": "Feature",
  "properties": {
    "addr:full":"7409 E Colonial Dr Orlando FL 32807",
    "addr:housenumber":"7409",
    "addr:postcode":"32807",
    "addr:street":"E Colonial Dr",
    "iso:country":"US",
    "sg:address":"7409 E Colonial Dr",
    "sg:city":"Orlando",
    "sg:classifiers":[
        {
            "category":"Restaurant",
            "type":"Food & Drink"
        }
    ],
    "sg:menulink":"http://www.allmenus.com/fl/orlando/187549-mcdonalds/menu/",
    "sg:phone":"+1 407 281 6606",
    "sg:postcode":"32807",
    "sg:province":"FL",
    "sg:tags":[
        "burger",
        "american"
    ],
    "wof:name":"McDonald's",
    "wof:placetype":"venue"
},
  "geometry": {"coordinates":[-81.287374,28.569292],"type":"Point"}
}