{
  "type": "Feature",
  "properties": {
    "iso:country":"US",
    "sg:address":"10613 Hammocks Blvd",
    "sg:city":"Miami",
    "sg:classifiers":[
        {
            "category":"Health Services",
            "subcategory":"Doctor",
            "type":"Services"
        }
    ],
    "sg:phone":"+1 305 666 6511",
    "sg:postcode":"33196",
    "sg:province":"FL",
    "sg:tags":[
        "physician",
        "surgeon"
    ],
    "wof:name":"John C Peng MD",
    "wof:placetype":"venue"
},
  "geometry": {"coordinates":[-80.443074,25.667441],"type":"Point"}
}