{
  "type": "Feature",
  "properties": {
    "iso:country":"US",
    "sg:address":"603 15th St",
    "sg:city":"Daytona Beach",
    "sg:classifiers":[
        {
            "category":"Professional",
            "subcategory":"Accounting & Tax Preparation",
            "type":"Services"
        }
    ],
    "sg:phone":"+1 386 254 8692",
    "sg:postcode":"32117",
    "sg:province":"FL",
    "wof:name":"Figure That Accounting Svc",
    "wof:placetype":"venue"
},
  "geometry": {"coordinates":[-81.054669,29.248319],"type":"Point"}
}