{
  "type": "Feature",
  "properties": {
    "iso:country":"US",
    "sg:address":"15320 Temple Blvd",
    "sg:city":"Loxahatchee",
    "sg:classifiers":[
        {
            "category":"Wholesale",
            "subcategory":"Hardware",
            "type":"Manufacturing & Wholesale Goods"
        }
    ],
    "sg:phone":"+1 561 792 0161",
    "sg:postcode":"33470",
    "sg:province":"FL",
    "wof:name":"Comet Aire Corp",
    "wof:placetype":"venue"
},
  "geometry": {"coordinates":[-80.282622,26.795567],"type":"Point"}
}