{
  "type": "Feature",
  "properties": {
    "addr:full":"413 Sombrero Beach Rd Marathon FL 33050",
    "addr:housenumber":"413",
    "addr:postcode":"33050",
    "addr:street":"Sombrero Beach Rd",
    "iso:country":"US",
    "sg:address":"413 Sombrero Beach Rd",
    "sg:city":"Marathon",
    "sg:classifiers":[
        {
            "category":"Professional",
            "type":"Services"
        }
    ],
    "sg:phone":"+1 305 743 9812",
    "sg:postcode":"33050",
    "sg:province":"FL",
    "wof:name":"Baymore & Co Inc",
    "wof:placetype":"venue"
},
  "geometry": {"coordinates":[-81.081563,24.693141],"type":"Point"}
}