{
  "type": "Feature",
  "properties": {
    "addr:full":"1516 S Oceanshore Blvd Flagler Beach FL 32136",
    "addr:housenumber":"1516",
    "addr:postcode":"32136",
    "addr:street":"S Oceanshore Blvd",
    "iso:country":"US",
    "sg:address":"1516 S Oceanshore Blvd",
    "sg:city":"Flagler Beach",
    "sg:classifiers":[
        {
            "category":"Real Estate",
            "subcategory":"Real Estate Agent",
            "type":"Services"
        }
    ],
    "sg:phone":"+1 386 439 2021",
    "sg:postcode":"32136",
    "sg:province":"FL",
    "sg:website":"www.century21a1arealty.com",
    "wof:name":"Century 21 A1a Realty",
    "wof:placetype":"venue"
},
  "geometry": {"coordinates":[-81.12164199999999,29.468843],"type":"Point"}
}