{
  "type": "Feature",
  "properties": {
    "addr:full":"1011 E Eau Gallie Blvd Satellite Beach FL 32937",
    "addr:housenumber":"1011",
    "addr:postcode":"32937",
    "addr:street":"E Eau Gallie Blvd",
    "iso:country":"US",
    "sg:address":"1011 E Eau Gallie Blvd",
    "sg:city":"Satellite Beach",
    "sg:classifiers":[
        {
            "category":"Restaurant",
            "type":"Food & Drink"
        },
        {
            "category":"Ice Cream",
            "type":"Food & Drink"
        }
    ],
    "sg:menulink":"http://www.allmenus.com/fl/indialantic-melbourne-beach/99050-friendlys/menu/",
    "sg:phone":"+1 321 777 5035",
    "sg:postcode":"32937",
    "sg:province":"FL",
    "sg:tags":[
        "burger",
        "american",
        "ice",
        "cream"
    ],
    "wof:name":"Friendly's",
    "wof:placetype":"venue"
},
  "geometry": {"coordinates":[-80.581429,28.138207],"type":"Point"}
}