{
  "type": "Feature",
  "properties": {
    "iso:country":"US",
    "sg:address":"4474 Edgewater Dr",
    "sg:city":"Orlando",
    "sg:classifiers":[
        {
            "category":"Health Services",
            "subcategory":"Doctor",
            "type":"Services"
        }
    ],
    "sg:phone":"+1 407 297 8007",
    "sg:postcode":"32804",
    "sg:province":"FL",
    "wof:name":"Pressley Kevin L DO PA",
    "wof:placetype":"venue"
},
  "geometry": {"coordinates":[-81.401703,28.5994],"type":"Point"}
}