{
  "type": "Feature",
  "properties": {
    "iso:country":"US",
    "sg:address":"1051 Town Center Dr",
    "sg:city":"Orange City",
    "sg:classifiers":[
        {
            "category":"Health Services",
            "subcategory":"Doctor",
            "type":"Services"
        },
        {
            "category":"Health Services",
            "subcategory":"Chiropractor",
            "type":"Services"
        }
    ],
    "sg:phone":"+1 386 774 8444",
    "sg:postcode":"32763",
    "sg:province":"FL",
    "sg:tags":[
        "orthopedist"
    ],
    "wof:name":"Alvarez Frank S Jr MD",
    "wof:placetype":"venue"
},
  "geometry": {"coordinates":[-81.286973,28.906321],"type":"Point"}
}