{
  "type": "Feature",
  "properties": {
    "addr:full":"21213 Harrow Ct Boca Raton FL 33433",
    "addr:housenumber":"21213",
    "addr:postcode":"33433",
    "addr:street":"Harrow Ct",
    "iso:country":"US",
    "sg:address":"21213 Harrow Ct",
    "sg:city":"Boca Raton",
    "sg:classifiers":[
        {
            "category":"Professional",
            "subcategory":"Advertising",
            "type":"Services"
        },
        {
            "category":"Manufacturing",
            "subcategory":"Printing",
            "type":"Manufacturing & Wholesale Goods"
        }
    ],
    "sg:phone":"+1 561 470 1345",
    "sg:postcode":"33433",
    "sg:province":"FL",
    "sg:tags":[
        "commercial",
        "lithographic",
        "list",
        "mailing"
    ],
    "wof:name":"Universal Print & Mail Inc",
    "wof:placetype":"venue"
},
  "geometry": {"coordinates":[-80.165963,26.358904],"type":"Point"}
}