{
  "type": "Feature",
  "properties": {
    "iso:country":"US",
    "sg:address":"450 Knights Run Ave",
    "sg:city":"Tampa",
    "sg:classifiers":[
        {
            "category":"Building & Trades",
            "subcategory":"Construction",
            "type":"Services"
        }
    ],
    "sg:phone":"+1 813 226 8585",
    "sg:postcode":"33602",
    "sg:province":"FL",
    "sg:tags":[
        "condominium"
    ],
    "wof:name":"Plaza Harbor Island",
    "wof:placetype":"venue"
},
  "geometry": {"coordinates":[-82.45178,27.937638],"type":"Point"}
}