{
  "type": "Feature",
  "properties": {
    "addr:full":"9523 Bay Vista Estates Blvd Orlando FL 32836",
    "addr:housenumber":"9523",
    "addr:postcode":"32836",
    "addr:street":"Bay Vista Estates Blvd",
    "iso:country":"US",
    "sg:address":"9523 Bay Vista Estates Blvd",
    "sg:city":"Orlando",
    "sg:classifiers":[
        {
            "category":"Education",
            "subcategory":"Special Training",
            "type":"Public Place"
        }
    ],
    "sg:phone":"+1 407 363 9303",
    "sg:postcode":"32836",
    "sg:province":"FL",
    "sg:tags":[
        "self",
        "motivational",
        "improvement"
    ],
    "wof:name":"I-Train",
    "wof:placetype":"venue"
},
  "geometry": {"coordinates":[-81.502252,28.426408],"type":"Point"}
}