{
  "type": "Feature",
  "properties": {
    "iso:country":"US",
    "sg:address":"8230 Navarre Pkwy",
    "sg:city":"Navarre",
    "sg:classifiers":[
        {
            "category":"Restaurant",
            "type":"Food & Drink"
        },
        {
            "category":"Food & Beverages",
            "subcategory":"Groceries & Convenience Stores",
            "type":"Retail Goods"
        }
    ],
    "sg:phone":"+1 850 939 6400",
    "sg:postcode":"32566",
    "sg:province":"FL",
    "sg:tags":[
        "shop",
        "sandwich",
        "pizza"
    ],
    "sg:website":"http://www.hungryhowies.com",
    "wof:name":"Hungry Howie's Store 223",
    "wof:placetype":"venue"
},
  "geometry": {"coordinates":[-86.878744,30.401731],"type":"Point"}
}