{
  "type": "Feature",
  "properties": {
    "addr:full":"17856 Dixie Hwy Miami FL 33157",
    "addr:housenumber":"17856",
    "addr:postcode":"33157",
    "addr:street":"Dixie Hwy",
    "iso:country":"US",
    "sg:address":"17856 Dixie Hwy",
    "sg:city":"Miami",
    "sg:classifiers":[
        {
            "category":"Shopping",
            "subcategory":"Used Merchandise",
            "type":"Retail Goods"
        }
    ],
    "sg:phone":"+1 305 255 5673",
    "sg:postcode":"33157",
    "sg:province":"FL",
    "wof:name":"Yesterdays Memories",
    "wof:placetype":"venue"
},
  "geometry": {"coordinates":[-80.352549,25.602452],"type":"Point"}
}