{
  "type": "Feature",
  "properties": {
    "addr:full":"2333 Brickell Ave Miami FL 33129",
    "addr:housenumber":"2333",
    "addr:postcode":"33129",
    "addr:street":"Brickell Ave",
    "iso:country":"US",
    "sg:address":"2333 Brickell Ave",
    "sg:city":"Miami",
    "sg:classifiers":[
        {
            "category":"Arena",
            "subcategory":"Sports Club",
            "type":"Entertainment"
        }
    ],
    "sg:phone":"+1 305 856 9914",
    "sg:postcode":"33129",
    "sg:province":"FL",
    "sg:tags":[
        "health"
    ],
    "wof:name":"Pfeiffer Fitness",
    "wof:placetype":"venue"
},
  "geometry": {"coordinates":[-80.201566,25.751871],"type":"Point"}
}