{
  "type": "Feature",
  "properties": {
    "iso:country":"US",
    "sg:address":"4705 Sleepy Hollow Ln",
    "sg:city":"Plant City",
    "sg:classifiers":[
        {
            "category":"Building & Trades",
            "subcategory":"Construction",
            "type":"Services"
        }
    ],
    "sg:phone":"+1 813 752 4665",
    "sg:postcode":"33565",
    "sg:province":"FL",
    "sg:tags":[
        "house",
        "nonresidential"
    ],
    "wof:name":"Allen Ham Construction Inc",
    "wof:placetype":"venue"
},
  "geometry": {"coordinates":[-82.144813,28.073714],"type":"Point"}
}