{
  "type": "Feature",
  "properties": {
    "addr:full":"838 A Philip Randolph Blvd Jacksonville FL 32206",
    "addr:housenumber":"838 a",
    "addr:postcode":"32206",
    "addr:street":"Philip Randolph Blvd",
    "iso:country":"US",
    "sg:address":"838 A Philip Randolph Blvd",
    "sg:city":"Jacksonville",
    "sg:classifiers":[
        {
            "category":"Food & Beverages",
            "subcategory":"Groceries & Convenience Stores",
            "type":"Retail Goods"
        }
    ],
    "sg:phone":"+1 904 353 9666",
    "sg:postcode":"32206",
    "sg:province":"FL",
    "sg:tags":[
        "grocer"
    ],
    "wof:name":"Jax's Food Mart",
    "wof:placetype":"venue"
},
  "geometry": {"coordinates":[-81.642601,30.332717],"type":"Point"}
}