{
  "type": "Feature",
  "properties": {
    "addr:full":"10627 Boca Entrada Blvd Boca Raton FL 33428",
    "addr:housenumber":"10627",
    "addr:postcode":"33428",
    "addr:street":"Boca Entrada Blvd",
    "iso:country":"US",
    "sg:address":"10627 Boca Entrada Blvd",
    "sg:city":"Boca Raton",
    "sg:classifiers":[
        {
            "category":"Building & Trades",
            "subcategory":"Landscaping Services",
            "type":"Services"
        }
    ],
    "sg:phone":"+1 561 852 6563",
    "sg:postcode":"33428",
    "sg:province":"FL",
    "sg:tags":[
        "lawn",
        "garden"
    ],
    "wof:name":"Juarez Lawn Service",
    "wof:placetype":"venue"
},
  "geometry": {"coordinates":[-80.207769,26.329651],"type":"Point"}
}