{
  "type": "Feature",
  "properties": {
    "iso:country":"US",
    "sg:address":"1539 NW 3rd Ave",
    "sg:city":"Miami",
    "sg:classifiers":[
        {
            "category":"Food & Beverages",
            "subcategory":"Groceries & Convenience Stores",
            "type":"Retail Goods"
        }
    ],
    "sg:phone":"+1 305 576 8877",
    "sg:postcode":"33136",
    "sg:province":"FL",
    "sg:tags":[
        "grocer"
    ],
    "wof:name":"16th Street Supermarket",
    "wof:placetype":"venue"
},
  "geometry": {"coordinates":[-80.199911,25.789959],"type":"Point"}
}