{
  "type": "Feature",
  "properties": {
    "iso:country":"US",
    "sg:address":"1165 19th St",
    "sg:city":"Vero Beach",
    "sg:classifiers":[
        {
            "category":"Shopping",
            "subcategory":"Computers & Home Electronics",
            "type":"Retail Goods"
        }
    ],
    "sg:phone":"+1 772 778 5560",
    "sg:postcode":"32960",
    "sg:province":"FL",
    "sg:tags":[
        "parts",
        "supply"
    ],
    "wof:name":"Lok Technology Inc",
    "wof:placetype":"venue"
},
  "geometry": {"coordinates":[-80.39716799999999,27.636061],"type":"Point"}
}