{
  "type": "Feature",
  "properties": {
    "iso:country":"US",
    "sg:address":"7817 Nature Trl",
    "sg:city":"Lakeland",
    "sg:classifiers":[
        {
            "category":"Professional",
            "subcategory":"Advertising",
            "type":"Services"
        }
    ],
    "sg:phone":"+1 863 859 3668",
    "sg:postcode":"33809",
    "sg:province":"FL",
    "wof:name":"Go Chamber Power Fl",
    "wof:placetype":"venue"
},
  "geometry": {"coordinates":[-81.92434,28.142425],"type":"Point"}
}