{
  "type": "Feature",
  "properties": {
    "iso:country":"US",
    "sg:address":"3600 SW 102nd Ave",
    "sg:city":"Miami",
    "sg:classifiers":[
        {
            "category":"Personal",
            "subcategory":"Barber",
            "type":"Services"
        }
    ],
    "sg:phone":"+1 305 596 0554",
    "sg:postcode":"33165",
    "sg:province":"FL",
    "wof:name":"Ledesma Nursery & Landscaping",
    "wof:placetype":"venue"
},
  "geometry": {"coordinates":[-80.35990099999999,25.735901],"type":"Point"}
}