{
  "type": "Feature",
  "properties": {
    "iso:country":"US",
    "sg:address":"4518 Curry Ford Rd",
    "sg:city":"Orlando",
    "sg:classifiers":[
        {
            "category":"Communications",
            "subcategory":"Film & Video Production",
            "type":"Services"
        }
    ],
    "sg:phone":"+1 407 281 1018",
    "sg:postcode":"32812",
    "sg:province":"FL",
    "sg:tags":[
        "duplication",
        "tape"
    ],
    "wof:name":"Medi Clone",
    "wof:placetype":"venue"
},
  "geometry": {"coordinates":[-81.32911799999999,28.524179],"type":"Point"}
}