{
  "type": "Feature",
  "properties": {
    "addr:full":"11551 SW 74th Ave Miami FL 33156",
    "addr:housenumber":"11551",
    "addr:postcode":"33156",
    "addr:street":"Sw 74Th Ave",
    "iso:country":"US",
    "sg:address":"11551 SW 74th Ave",
    "sg:city":"Miami",
    "sg:classifiers":[
        {
            "category":"Professional",
            "subcategory":"Management & Consulting",
            "type":"Services"
        }
    ],
    "sg:phone":"+1 305 607 7565",
    "sg:postcode":"33156",
    "sg:province":"FL",
    "sg:tags":[
        "training",
        "end",
        "complete",
        "broker",
        "high",
        "technology"
    ],
    "wof:name":"University Corp Trning Sltions",
    "wof:placetype":"venue"
},
  "geometry": {"coordinates":[-80.31442699999999,25.663974],"type":"Point"}
}