{
  "type": "Feature",
  "properties": {
    "iso:country":"US",
    "sg:address":"4131 Lenox Ave",
    "sg:city":"Jacksonville",
    "sg:classifiers":[
        {
            "category":"Retail",
            "subcategory":"Repair Shop",
            "type":"Services"
        }
    ],
    "sg:phone":"+1 904 384 1424",
    "sg:postcode":"32254",
    "sg:province":"FL",
    "sg:tags":[
        "refinishing",
        "furniture"
    ],
    "wof:name":"Woodmasters-Florida Furn Rpr",
    "wof:placetype":"venue"
},
  "geometry": {"coordinates":[-81.719821,30.321894],"type":"Point"}
}