{
  "type": "Feature",
  "properties": {
    "addr:full":"20404 Front Beach Rd Panama City FL 32413",
    "addr:housenumber":"20404",
    "addr:postcode":"32413",
    "addr:street":"Front Beach Rd",
    "iso:country":"US",
    "sg:address":"20404 Front Beach Rd",
    "sg:city":"Panama City",
    "sg:classifiers":[
        {
            "category":"Travel",
            "subcategory":"Hotels & Motels",
            "type":"Entertainment"
        }
    ],
    "sg:phone":"+1 850 234 0557",
    "sg:postcode":"32413",
    "sg:province":"FL",
    "wof:name":"Wisteria Inn",
    "wof:placetype":"venue"
},
  "geometry": {"coordinates":[-85.942695,30.247814],"type":"Point"}
}