{
  "type": "Feature",
  "properties": {
    "iso:country":"US",
    "sg:address":"31821 Vine St",
    "sg:city":"Sorrento",
    "sg:classifiers":[
        {
            "category":"Wholesale",
            "subcategory":"Plants",
            "type":"Manufacturing & Wholesale Goods"
        }
    ],
    "sg:phone":"+1 352 735 9220",
    "sg:postcode":"32776",
    "sg:province":"FL",
    "sg:tags":[
        "farm",
        "supply"
    ],
    "wof:name":"Vine Street Foliage",
    "wof:placetype":"venue"
},
  "geometry": {"coordinates":[-81.562236,28.814172],"type":"Point"}
}