{
  "type": "Feature",
  "properties": {
    "addr:full":"1029 George Ave Rockledge FL 32955",
    "addr:housenumber":"1029",
    "addr:postcode":"32955",
    "addr:street":"George Ave",
    "iso:country":"US",
    "sg:address":"1029 George Ave",
    "sg:city":"Rockledge",
    "sg:classifiers":[
        {
            "category":"Building & Trades",
            "subcategory":"Electrical",
            "type":"Services"
        }
    ],
    "sg:phone":"+1 321 632 9080",
    "sg:postcode":"32955",
    "sg:province":"FL",
    "sg:tags":[
        "electrical",
        "contractor"
    ],
    "wof:name":"Blanton Electric Service",
    "wof:placetype":"venue"
},
  "geometry": {"coordinates":[-80.74594999999999,28.311817],"type":"Point"}
}