{
  "type": "Feature",
  "properties": {
    "iso:country":"US",
    "sg:address":"2884 SE Pace Dr",
    "sg:city":"Port Saint Lucie",
    "sg:classifiers":[
        {
            "category":"Professional",
            "subcategory":"Employment Agencies",
            "type":"Services"
        }
    ],
    "sg:phone":"+1 772 336 4951",
    "sg:postcode":"34984",
    "sg:province":"FL",
    "sg:tags":[
        "help",
        "supply"
    ],
    "wof:name":"Career Bureau Staffing Inc",
    "wof:placetype":"venue"
},
  "geometry": {"coordinates":[-80.334565,27.25041],"type":"Point"}
}