{
  "type": "Feature",
  "properties": {
    "iso:country":"US",
    "sg:address":"1025 E 45th St",
    "sg:city":"Hialeah",
    "sg:classifiers":[
        {
            "category":"Professional",
            "subcategory":"Business Services",
            "type":"Services"
        }
    ],
    "sg:phone":"+1 305 681 5448",
    "sg:postcode":"33013",
    "sg:province":"FL",
    "sg:tags":[
        "automobile",
        "appraiser"
    ],
    "wof:name":"T R Independent Appraisal Corp",
    "wof:placetype":"venue"
},
  "geometry": {"coordinates":[-80.262587,25.863821],"type":"Point"}
}