{
  "type": "Feature",
  "properties": {
    "iso:country":"US",
    "sg:address":"2396 Edgewood Ave N",
    "sg:city":"Jacksonville",
    "sg:classifiers":[
        {
            "category":"Health Services",
            "subcategory":"Chiropractor",
            "type":"Services"
        }
    ],
    "sg:phone":"+1 904 781 5829",
    "sg:postcode":"32254",
    "sg:province":"FL",
    "sg:tags":[
        "chiropractic"
    ],
    "wof:name":"Robinson Chiropractic Inc",
    "wof:placetype":"venue"
},
  "geometry": {"coordinates":[-81.73120900000001,30.353961],"type":"Point"}
}