{
  "type": "Feature",
  "properties": {
    "addr:full":"10769 SW 104th St Miami FL 33176",
    "addr:housenumber":"10769",
    "addr:postcode":"33176",
    "addr:street":"Sw 104Th St",
    "iso:country":"US",
    "sg:address":"10769 SW 104th St",
    "sg:city":"Miami",
    "sg:classifiers":[
        {
            "category":"Social Services",
            "type":"Services"
        }
    ],
    "sg:phone":"+1 305 279 3041",
    "sg:postcode":"33176",
    "sg:province":"FL",
    "sg:tags":[
        "worker"
    ],
    "wof:name":"Romance Joseph Phd Lcsw",
    "wof:placetype":"venue"
},
  "geometry": {"coordinates":[-80.368753,25.672443],"type":"Point"}
}