{
  "type": "Feature",
  "properties": {
    "addr:full":"1830 Ridgewood Ave Daytona Beach FL 32117",
    "addr:housenumber":"1830",
    "addr:postcode":"32117",
    "addr:street":"Ridgewood Ave",
    "iso:country":"US",
    "sg:address":"1830 Ridgewood Ave",
    "sg:city":"Daytona Beach",
    "sg:classifiers":[
        {
            "category":"Restaurant",
            "type":"Food & Drink"
        }
    ],
    "sg:menulink":"http://www.allmenus.com/fl/ormond-beach/207026-sonic/menu/",
    "sg:phone":"+1 386 672 7448",
    "sg:postcode":"32117",
    "sg:province":"FL",
    "sg:tags":[
        "burger",
        "american"
    ],
    "wof:name":"Sonic",
    "wof:placetype":"venue"
},
  "geometry": {"coordinates":[-81.049837,29.260988],"type":"Point"}
}