{
  "type": "Feature",
  "properties": {
    "iso:country":"US",
    "sg:address":"5795 Parkview Point Dr",
    "sg:city":"Orlando",
    "sg:classifiers":[
        {
            "category":"Wholesale",
            "subcategory":"Groceries",
            "type":"Manufacturing & Wholesale Goods"
        }
    ],
    "sg:phone":"+1 407 239 7170",
    "sg:postcode":"32821",
    "sg:province":"FL",
    "sg:tags":[
        "beverage"
    ],
    "wof:name":"Triark Beverages",
    "wof:placetype":"venue"
},
  "geometry": {"coordinates":[-81.44971700000001,28.401313],"type":"Point"}
}