{
  "type": "Feature",
  "properties": {
    "addr:full":"11043 Crystal Springs Rd Jacksonville FL 32221",
    "addr:housenumber":"11043",
    "addr:postcode":"32221",
    "addr:street":"Crystal Springs Rd",
    "iso:country":"US",
    "sg:address":"11043 Crystal Springs Rd",
    "sg:city":"Jacksonville",
    "sg:classifiers":[
        {
            "category":"Professional",
            "subcategory":"Accounting & Tax Preparation",
            "type":"Services"
        }
    ],
    "sg:phone":"+1 904 781 4816",
    "sg:postcode":"32221",
    "sg:province":"FL",
    "sg:tags":[
        "bookkeeping",
        "return",
        "representative",
        "preparation-business",
        "taxes-consultants"
    ],
    "sg:website":"http://www.jacksonhewitt.com/",
    "wof:name":"Jackson Hewitt Tax Service",
    "wof:placetype":"venue"
},
  "geometry": {"coordinates":[-81.846008,30.304375],"type":"Point"}
}