{
  "type": "Feature",
  "properties": {
    "addr:full":"8578 SW 113th Pl Miami FL 33173",
    "addr:housenumber":"8578",
    "addr:postcode":"33173",
    "addr:street":"Sw 113Th Pl",
    "iso:country":"US",
    "sg:address":"8578 SW 113th Pl",
    "sg:city":"Miami",
    "sg:classifiers":[
        {
            "category":"Insurance",
            "subcategory":"Insurance Agent",
            "type":"Services"
        }
    ],
    "sg:phone":"+1 305 596 2755",
    "sg:postcode":"33173",
    "sg:province":"FL",
    "wof:name":"Murray Dronsky",
    "wof:placetype":"venue"
},
  "geometry": {"coordinates":[-80.37648299999999,25.688204],"type":"Point"}
}