{
  "type": "Feature",
  "properties": {
    "iso:country":"US",
    "sg:address":"916 US Hwy 301",
    "sg:city":"Tampa",
    "sg:classifiers":[
        {
            "category":"Banks & Credit Unions",
            "subcategory":"Bank",
            "type":"Services"
        }
    ],
    "sg:phone":"+1 813 612 9618",
    "sg:postcode":"33619",
    "sg:province":"FL",
    "sg:tags":[
        "cashing",
        "check"
    ],
    "wof:name":"Cash Connection",
    "wof:placetype":"venue"
},
  "geometry": {"coordinates":[-82.353617,27.944592],"type":"Point"}
}