{
  "type": "Feature",
  "properties": {
    "addr:full":"1155 Samar Rd Cocoa Beach FL 32931",
    "addr:housenumber":"1155",
    "addr:postcode":"32931",
    "addr:street":"Samar Rd",
    "iso:country":"US",
    "sg:address":"1155 Samar Rd",
    "sg:city":"Cocoa Beach",
    "sg:classifiers":[
        {
            "category":"Building & Trades",
            "subcategory":"Construction",
            "type":"Services"
        }
    ],
    "sg:phone":"+1 321 783 7387",
    "sg:postcode":"32931",
    "sg:province":"FL",
    "sg:tags":[
        "carpenter"
    ],
    "wof:name":"William C Forsyth Framing",
    "wof:placetype":"venue"
},
  "geometry": {"coordinates":[-80.61422399999999,28.333392],"type":"Point"}
}