{
  "type": "Feature",
  "properties": {
    "addr:full":"1633 Boathouse Cir Sarasota FL 34231",
    "addr:housenumber":"1633",
    "addr:postcode":"34231",
    "addr:street":"Boathouse Cir",
    "iso:country":"US",
    "sg:address":"1633 Boathouse Cir",
    "sg:city":"Sarasota",
    "sg:classifiers":[
        {
            "category":"Professional",
            "subcategory":"Management & Consulting",
            "type":"Services"
        }
    ],
    "sg:phone":"+1 941 966 3220",
    "sg:postcode":"34231",
    "sg:province":"FL",
    "sg:tags":[
        "business"
    ],
    "wof:name":"W H Bushing & Company Inc",
    "wof:placetype":"venue"
},
  "geometry": {"coordinates":[-82.501223,27.230406],"type":"Point"}
}