{
  "type": "Feature",
  "properties": {
    "iso:country":"US",
    "sg:address":"12685 Dixie Hwy",
    "sg:city":"Miami",
    "sg:classifiers":[
        {
            "category":"Organizations",
            "subcategory":"Community Association",
            "type":"Services"
        }
    ],
    "sg:phone":"+1 305 254 0310",
    "sg:postcode":"33156",
    "sg:province":"FL",
    "sg:tags":[
        "youth"
    ],
    "wof:name":"YMCA",
    "wof:placetype":"venue"
},
  "geometry": {"coordinates":[-80.329449,25.654043],"type":"Point"}
}