{
  "type": "Feature",
  "properties": {
    "iso:country":"US",
    "sg:address":"513 Minnesota Ave",
    "sg:city":"Lynn Haven",
    "sg:classifiers":[
        {
            "category":"Social Services",
            "subcategory":"Child Care",
            "type":"Services"
        }
    ],
    "sg:phone":"+1 850 271 8260",
    "sg:postcode":"32444",
    "sg:province":"FL",
    "sg:tags":[
        "day"
    ],
    "wof:name":"Staceys Swingers Day Car",
    "wof:placetype":"venue"
},
  "geometry": {"coordinates":[-85.64391000000001,30.249164],"type":"Point"}
}