{
  "type": "Feature",
  "properties": {
    "iso:country":"US",
    "sg:address":"1440 Windorah Way",
    "sg:city":"West Palm Beach",
    "sg:classifiers":[
        {
            "category":"Freight",
            "type":"Transportation"
        }
    ],
    "sg:phone":"+1 561 615 5289",
    "sg:postcode":"33411",
    "sg:province":"FL",
    "sg:tags":[
        "operator",
        "local",
        "trucking"
    ],
    "wof:name":"Leonard Holton Trucking",
    "wof:placetype":"venue"
},
  "geometry": {"coordinates":[-80.173503,26.701256],"type":"Point"}
}