{
  "type": "Feature",
  "properties": {
    "iso:country":"US",
    "sg:address":"232 S Yonge St",
    "sg:city":"Ormond Beach",
    "sg:classifiers":[
        {
            "category":"Wholesale",
            "subcategory":"Electrical",
            "type":"Manufacturing & Wholesale Goods"
        }
    ],
    "sg:phone":"+1 386 672 7061",
    "sg:postcode":"32174",
    "sg:province":"FL",
    "sg:tags":[
        "alarm",
        "burglar",
        "system"
    ],
    "sg:website":"www.guardian-security-systems.com",
    "wof:name":"Guardian Security Systems Inc",
    "wof:placetype":"venue"
},
  "geometry": {"coordinates":[-81.05908599999999,29.277],"type":"Point"}
}