{
  "type": "Feature",
  "properties": {
    "addr:full":"3230 Spees Harris Ln Perry FL 32347",
    "addr:postcode":"3230;32347",
    "addr:street":"Spees Harris Ln",
    "iso:country":"US",
    "sg:address":"3230 Spees Harris Ln",
    "sg:city":"Perry",
    "sg:classifiers":[
        {
            "category":"Government",
            "subcategory":"Office",
            "type":"Public Place"
        }
    ],
    "sg:phone":"+1 850 584 8174",
    "sg:postcode":"32347",
    "sg:province":"FL",
    "wof:name":"Sr Lee Spees",
    "wof:placetype":"venue"
},
  "geometry": {"coordinates":[-83.564133,30.164565],"type":"Point"}
}