{
  "type": "Feature",
  "properties": {
    "iso:country":"US",
    "sg:address":"2100 SE Ocean Blvd Ste 20",
    "sg:city":"Stuart",
    "sg:classifiers":[
        {
            "category":"Professional",
            "subcategory":"Lawyer & Legal Services",
            "type":"Services"
        }
    ],
    "sg:phone":"+1 772 283 3051",
    "sg:postcode":"34996",
    "sg:province":"FL",
    "sg:tags":[
        "attorney",
        "practice"
    ],
    "wof:name":"Jeffrey Kirsch M",
    "wof:placetype":"venue"
},
  "geometry": {"coordinates":[-80.224136,27.19735],"type":"Point"}
}