{
  "type": "Feature",
  "properties": {
    "addr:full":"1508 San Ignacio Ave Miami FL 33146",
    "addr:housenumber":"1508",
    "addr:postcode":"33146",
    "addr:street":"San Ignacio Ave",
    "iso:country":"US",
    "sg:address":"1508 San Ignacio Ave",
    "sg:city":"Miami",
    "sg:classifiers":[
        {
            "category":"Health Services",
            "subcategory":"Clinic",
            "type":"Services"
        }
    ],
    "sg:phone":"+1 305 669 0104",
    "sg:postcode":"33146",
    "sg:province":"FL",
    "wof:name":"Millennium Intl P P O LLC",
    "wof:placetype":"venue"
},
  "geometry": {"coordinates":[-80.28518699999999,25.705175],"type":"Point"}
}