{
  "type": "Feature",
  "properties": {
    "addr:full":"5901 Beggs Rd Orlando FL 32810",
    "addr:housenumber":"5901",
    "addr:postcode":"32810",
    "addr:street":"Beggs Rd",
    "iso:country":"US",
    "sg:address":"5901 Beggs Rd",
    "sg:city":"Orlando",
    "sg:classifiers":[
        {
            "category":"Wholesale",
            "subcategory":"Hardware",
            "type":"Manufacturing & Wholesale Goods"
        },
        {
            "category":"Home & Garden",
            "subcategory":"Building Materials",
            "type":"Retail Goods"
        },
        {
            "category":"Manufacturing",
            "subcategory":"Building Materials",
            "type":"Manufacturing & Wholesale Goods"
        }
    ],
    "sg:phone":"+1 407 293 1811",
    "sg:postcode":"32810",
    "sg:province":"FL",
    "sg:tags":[
        "frames",
        "window",
        "hardware-builders",
        "doors",
        "accessory"
    ],
    "sg:website":"http://www.outdoorlivingproducts.net",
    "wof:name":"Outdoor Living Products Inc",
    "wof:placetype":"venue"
},
  "geometry": {"coordinates":[-81.449631,28.62553],"type":"Point"}
}