{
  "type": "Feature",
  "properties": {
    "addr:full":"633 S Federal Hwy Boynton Beach FL 33435",
    "addr:housenumber":"633",
    "addr:postcode":"33435",
    "addr:street":"S Federal Hwy",
    "iso:country":"US",
    "sg:address":"633 S Federal Hwy",
    "sg:city":"Boynton Beach",
    "sg:classifiers":[
        {
            "category":"Professional",
            "subcategory":"Lawyer & Legal Services",
            "type":"Services"
        }
    ],
    "sg:phone":"+1 561 736 0118",
    "sg:postcode":"33435",
    "sg:province":"FL",
    "sg:tags":[
        "attorney"
    ],
    "sg:website":"www.conradscherer.com",
    "wof:name":"Conrad & Scherer",
    "wof:placetype":"venue"
},
  "geometry": {"coordinates":[-80.058038,26.522125],"type":"Point"}
}