{
  "type": "Feature",
  "properties": {
    "iso:country":"US",
    "sg:address":"3501 Townsend Blvd Unit167",
    "sg:city":"Jacksonville",
    "sg:classifiers":[
        {
            "category":"Education",
            "subcategory":"Special Training",
            "type":"Public Place"
        },
        {
            "category":"Social Services",
            "subcategory":"Child Care",
            "type":"Services"
        }
    ],
    "sg:phone":"+1 904 743 0519",
    "sg:postcode":"32277",
    "sg:province":"FL",
    "sg:tags":[
        "educational",
        "sitting"
    ],
    "wof:name":"kelleycare service",
    "wof:placetype":"venue"
},
  "geometry": {"coordinates":[-81.577084,30.364387],"type":"Point"}
}