{
  "type": "Feature",
  "properties": {
    "iso:country":"US",
    "sg:address":"919 Douglas St SE",
    "sg:city":"Palm Bay",
    "sg:classifiers":[
        {
            "category":"Building & Trades",
            "subcategory":"Construction",
            "type":"Services"
        }
    ],
    "sg:phone":"+1 321 724 6353",
    "sg:postcode":"32909",
    "sg:province":"FL",
    "sg:tags":[
        "contractor"
    ],
    "wof:name":"Star Masonry",
    "wof:placetype":"venue"
},
  "geometry": {"coordinates":[-80.643574,27.992089],"type":"Point"}
}