{
  "type": "Feature",
  "properties": {
    "iso:country":"US",
    "sg:address":"1620 W Cervantes St",
    "sg:city":"Pensacola",
    "sg:classifiers":[
        {
            "category":"Wholesale",
            "subcategory":"Hardware",
            "type":"Manufacturing & Wholesale Goods"
        }
    ],
    "sg:phone":"+1 850 433 0035",
    "sg:postcode":"32501",
    "sg:province":"FL",
    "sg:tags":[
        "air",
        "parts",
        "conditioning",
        "supply"
    ],
    "wof:name":"Pensacola Refrigeration Supply",
    "wof:placetype":"venue"
},
  "geometry": {"coordinates":[-87.23659600000001,30.420551],"type":"Point"}
}