{
  "type": "Feature",
  "properties": {
    "iso:country":"US",
    "sg:address":"1226 SE Pruitt Rd",
    "sg:city":"Port St Lucie",
    "sg:classifiers":[
        {
            "category":"Shopping",
            "subcategory":"Shoes",
            "type":"Retail Goods"
        }
    ],
    "sg:phone":"+1 772 380 9998",
    "sg:postcode":"34952",
    "sg:province":"FL",
    "wof:name":"Doctor's Shoe Store",
    "wof:placetype":"venue"
},
  "geometry": {"coordinates":[-80.31776499999999,27.258202],"type":"Point"}
}