{
  "type": "Feature",
  "properties": {
    "iso:country":"US",
    "sg:address":"2095 Cheney Hwy",
    "sg:city":"Titusville",
    "sg:classifiers":[
        {
            "category":"Health Services",
            "subcategory":"Doctor",
            "type":"Services"
        }
    ],
    "sg:phone":"+1 321 269 7534",
    "sg:postcode":"32780",
    "sg:province":"FL",
    "sg:tags":[
        "dentist"
    ],
    "wof:name":"Brevard Pediatric Dental Assoc",
    "wof:placetype":"venue"
},
  "geometry": {"coordinates":[-80.82516800000001,28.55765],"type":"Point"}
}