{
  "type": "Feature",
  "properties": {
    "addr:full":"1947 Lee Rd Winter Park FL 32789",
    "addr:housenumber":"1947",
    "addr:postcode":"32789",
    "addr:street":"Lee Rd",
    "iso:country":"US",
    "sg:address":"1947 Lee Rd",
    "sg:city":"Winter Park",
    "sg:classifiers":[
        {
            "category":"Banks & Credit Unions",
            "subcategory":"Financial Services",
            "type":"Services"
        }
    ],
    "sg:phone":"+1 407 629 7799",
    "sg:postcode":"32789",
    "sg:province":"FL",
    "sg:tags":[
        "investment",
        "real estate"
    ],
    "wof:name":"Kegan Funding",
    "wof:placetype":"venue"
},
  "geometry": {"coordinates":[-81.375219,28.605982],"type":"Point"}
}