{
  "type": "Feature",
  "properties": {
    "addr:full":"1384 SE Huffman Rd Port Saint Lucie FL 34952",
    "addr:housenumber":"1384",
    "addr:postcode":"34952",
    "addr:street":"Se Huffman Rd",
    "iso:country":"US",
    "sg:address":"1384 SE Huffman Rd",
    "sg:city":"Port Saint Lucie",
    "sg:classifiers":[
        {
            "category":"Manufacturing",
            "subcategory":"Tools & Machinery",
            "type":"Manufacturing & Wholesale Goods"
        }
    ],
    "sg:phone":"+1 772 398 0190",
    "sg:postcode":"34952",
    "sg:province":"FL",
    "sg:tags":[
        "machine",
        "shop",
        "jobbing",
        "repair"
    ],
    "wof:name":"Aclon Machine & Tool",
    "wof:placetype":"venue"
},
  "geometry": {"coordinates":[-80.307306,27.307545],"type":"Point"}
}