{
  "type": "Feature",
  "properties": {
    "addr:full":"3850 N 46th Ave Hollywood FL 33021",
    "addr:housenumber":"3850",
    "addr:postcode":"33021",
    "addr:street":"N 46Th Ave",
    "iso:country":"US",
    "sg:address":"3850 N 46th Ave",
    "sg:city":"Hollywood",
    "sg:classifiers":[
        {
            "category":"Food & Beverages",
            "subcategory":"Groceries & Convenience Stores",
            "type":"Retail Goods"
        }
    ],
    "sg:phone":"+1 954 987 7537",
    "sg:postcode":"33021",
    "sg:province":"FL",
    "sg:website":"www.winn-dixie.com",
    "wof:name":"Winn-Dixie",
    "wof:placetype":"venue"
},
  "geometry": {"coordinates":[-80.19053700000001,26.046584],"type":"Point"}
}