{
  "type": "Feature",
  "properties": {
    "iso:country":"US",
    "sg:address":"200 Central Ave",
    "sg:city":"St Petersburg",
    "sg:classifiers":[
        {
            "category":"Professional",
            "subcategory":"Lawyer & Legal Services",
            "type":"Services"
        }
    ],
    "sg:phone":"+1 727 898 7474",
    "sg:postcode":"33705",
    "sg:province":"FL",
    "sg:tags":[
        "attorney"
    ],
    "sg:website":"www.trenam.com",
    "wof:name":"Trenam Kemker Scharf Barkin",
    "wof:placetype":"venue"
},
  "geometry": {"coordinates":[-82.637086,27.77121],"type":"Point"}
}