{
  "type": "Feature",
  "properties": {
    "addr:full":"7545 E Treasure Dr Miami Beach FL 33141",
    "addr:housenumber":"7545",
    "addr:postcode":"33141",
    "addr:street":"E Treasure",
    "iso:country":"US",
    "sg:address":"7545 E Treasure Dr",
    "sg:city":"Miami Beach",
    "sg:classifiers":[
        {
            "category":"Real Estate",
            "subcategory":"Real Estate Operator",
            "type":"Services"
        }
    ],
    "sg:phone":"+1 305 866 5201",
    "sg:postcode":"33141",
    "sg:province":"FL",
    "sg:tags":[
        "building",
        "apartment"
    ],
    "wof:name":"Caribbean Towers",
    "wof:placetype":"venue"
},
  "geometry": {"coordinates":[-80.146191,25.845887],"type":"Point"}
}