{
  "type": "Feature",
  "properties": {
    "iso:country":"US",
    "sg:address":"7300 Sand Lake Commons Blvd",
    "sg:city":"Orlando",
    "sg:classifiers":[
        {
            "category":"Health Services",
            "subcategory":"Doctor",
            "type":"Services"
        }
    ],
    "sg:phone":"+1 407 345 0250",
    "sg:postcode":"32819",
    "sg:province":"FL",
    "sg:tags":[
        "physician",
        "clinic",
        "surgeon",
        "medical"
    ],
    "wof:name":"Shyam G Nadkarni MD",
    "wof:placetype":"venue"
},
  "geometry": {"coordinates":[-81.48098,28.431146],"type":"Point"}
}