{
  "type": "Feature",
  "properties": {
    "addr:full":"7475 W Irlo Bronson Memorial Hwy Kissimmee FL 34747",
    "addr:housenumber":"7475",
    "addr:postcode":"34747",
    "addr:street":"W Irlo Bronson Memorial Hwy",
    "iso:country":"US",
    "sg:address":"7475 W Irlo Bronson Memorial Hwy",
    "sg:city":"Kissimmee",
    "sg:classifiers":[
        {
            "category":"Travel",
            "subcategory":"Hotels & Motels",
            "type":"Entertainment"
        }
    ],
    "sg:phone":"+1 407 396 4200",
    "sg:postcode":"34747",
    "sg:province":"FL",
    "sg:website":"www.knightsinn.com",
    "wof:name":"Knights Inn Maingate",
    "wof:placetype":"venue"
},
  "geometry": {"coordinates":[-81.586128,28.334438],"type":"Point"}
}