{
  "type": "Feature",
  "properties": {
    "addr:full":"918 N Main St Kissimmee FL 34744",
    "addr:housenumber":"918",
    "addr:postcode":"34744",
    "addr:street":"N Main St",
    "iso:country":"US",
    "sg:address":"918 N Main St",
    "sg:city":"Kissimmee",
    "sg:classifiers":[
        {
            "category":"Shopping",
            "type":"Retail Goods"
        }
    ],
    "sg:phone":"+1 407 846 4155",
    "sg:postcode":"34744",
    "sg:province":"FL",
    "sg:tags":[
        "aids",
        "hearing"
    ],
    "wof:name":"Best Hearing Aids",
    "wof:placetype":"venue"
},
  "geometry": {"coordinates":[-81.403826,28.300639],"type":"Point"}
}