{
  "type": "Feature",
  "properties": {
    "addr:full":"1000 5th St Ste 200 Miami Beach FL 33139",
    "addr:housenumber":"1000",
    "addr:postcode":"33139",
    "addr:street":"5Th St Ste 200",
    "iso:country":"US",
    "sg:address":"1000 5th St Ste 200",
    "sg:city":"Miami Beach",
    "sg:classifiers":[
        {
            "category":"Travel",
            "subcategory":"Travel Agent",
            "type":"Entertainment"
        }
    ],
    "sg:phone":"+1 305 420 6900",
    "sg:postcode":"33139",
    "sg:province":"FL",
    "wof:name":"Rio.com",
    "wof:placetype":"venue"
},
  "geometry": {"coordinates":[-80.138615,25.773895],"type":"Point"}
}