{
  "type": "Feature",
  "properties": {
    "addr:full":"53 N Old Kings Rd Ormond Beach FL 32174",
    "addr:housenumber":"53",
    "addr:postcode":"32174",
    "addr:street":"N Old Kings Rd",
    "iso:country":"US",
    "sg:address":"53 N Old Kings Rd",
    "sg:city":"Ormond Beach",
    "sg:classifiers":[
        {
            "category":"Health Services",
            "subcategory":"Doctor",
            "type":"Services"
        }
    ],
    "sg:phone":"+1 386 677 0089",
    "sg:postcode":"32174",
    "sg:province":"FL",
    "sg:tags":[
        "dentist"
    ],
    "wof:name":"R Michael Reavis DDS",
    "wof:placetype":"venue"
},
  "geometry": {"coordinates":[-81.08089,29.279728],"type":"Point"}
}