{
  "type": "Feature",
  "properties": {
    "iso:country":"US",
    "sg:address":"1026 NW 9th Ave",
    "sg:city":"Fort Lauderdale",
    "sg:classifiers":[
        {
            "category":"Restaurant",
            "type":"Food & Drink"
        }
    ],
    "sg:phone":"+1 954 767 8084",
    "sg:postcode":"33311",
    "sg:province":"FL",
    "sg:tags":[
        "delivery"
    ],
    "wof:name":"Sapibon Take Out",
    "wof:placetype":"venue"
},
  "geometry": {"coordinates":[-80.153808,26.138201],"type":"Point"}
}