{
  "type": "Feature",
  "properties": {
    "addr:full":"1750 S Osprey Ave Sarasota FL 34239",
    "addr:housenumber":"1750",
    "addr:postcode":"34239",
    "addr:street":"S Osprey Ave",
    "iso:country":"US",
    "sg:address":"1750 S Osprey Ave",
    "sg:city":"Sarasota",
    "sg:classifiers":[
        {
            "category":"Health Services",
            "subcategory":"Doctor",
            "type":"Services"
        }
    ],
    "sg:phone":"+1 941 364 8220",
    "sg:postcode":"34239",
    "sg:province":"FL",
    "sg:tags":[
        "medical"
    ],
    "wof:name":"Cathy P Milam MD",
    "wof:placetype":"venue"
},
  "geometry": {"coordinates":[-82.53383599999999,27.3178],"type":"Point"}
}