{
  "type": "Feature",
  "properties": {
    "iso:country":"US",
    "sg:address":"9774 SW 60th St",
    "sg:city":"Miami",
    "sg:classifiers":[
        {
            "category":"Building & Trades",
            "subcategory":"Landscaping Services",
            "type":"Services"
        }
    ],
    "sg:phone":"+1 305 596 7120",
    "sg:postcode":"33173",
    "sg:province":"FL",
    "sg:tags":[
        "designer",
        "landscape"
    ],
    "sg:website":"www.greensleevesinc.com",
    "wof:name":"Greensleeves Inc",
    "wof:placetype":"venue"
},
  "geometry": {"coordinates":[-80.35336,25.712313],"type":"Point"}
}