{
  "type": "Feature",
  "properties": {
    "addr:full":"2031 W Sample Rd Pompano Beach FL 33064",
    "addr:housenumber":"2031",
    "addr:postcode":"33064",
    "addr:street":"W Sample Rd",
    "iso:country":"US",
    "sg:address":"2031 W Sample Rd",
    "sg:city":"Pompano Beach",
    "sg:classifiers":[
        {
            "category":"Autos & Motor Vehicles",
            "subcategory":"Fuel & Gas Station",
            "type":"Retail Goods"
        }
    ],
    "sg:phone":"+1 954 975 8015",
    "sg:postcode":"33064",
    "sg:province":"FL",
    "sg:tags":[
        "station"
    ],
    "wof:name":"Citgo",
    "wof:placetype":"venue"
},
  "geometry": {"coordinates":[-80.15114199999999,26.274635],"type":"Point"}
}