{
  "type": "Feature",
  "properties": {
    "addr:full":"14564 SW 174th Ter Miami FL 33177",
    "addr:housenumber":"14564",
    "addr:postcode":"33177",
    "addr:street":"Sw 174Th Ter",
    "iso:country":"US",
    "sg:address":"14564 SW 174th Ter",
    "sg:city":"Miami",
    "sg:classifiers":[
        {
            "category":"Communications",
            "subcategory":"Film & Video Production",
            "type":"Services"
        }
    ],
    "sg:phone":"+1 305 254 3738",
    "sg:postcode":"33177",
    "sg:province":"FL",
    "sg:tags":[
        "services-commercial"
    ],
    "wof:name":"Mr Video Productions Corp",
    "wof:placetype":"venue"
},
  "geometry": {"coordinates":[-80.42908799999999,25.605035],"type":"Point"}
}