{
  "type": "Feature",
  "properties": {
    "iso:country":"US",
    "sg:address":"555 NE 25th St",
    "sg:city":"Hialeah",
    "sg:classifiers":[
        {
            "category":"Personal",
            "subcategory":"Beauty Salon",
            "type":"Services"
        }
    ],
    "sg:phone":"+1 305 693 4474",
    "sg:postcode":"33064",
    "sg:province":"FL",
    "sg:tags":[
        "shop"
    ],
    "wof:name":"Aha Hair",
    "wof:placetype":"venue"
},
  "geometry": {"coordinates":[-80.11481000000001,26.261818],"type":"Point"}
}