{
  "type": "Feature",
  "properties": {
    "iso:country":"US",
    "sg:address":"7257 New Kings Rd",
    "sg:city":"Jacksonville",
    "sg:classifiers":[
        {
            "category":"Retail",
            "subcategory":"Auto Repair",
            "type":"Services"
        }
    ],
    "sg:phone":"+1 904 764 1495",
    "sg:postcode":"32219",
    "sg:province":"FL",
    "sg:tags":[
        "repairing",
        "supply",
        "automobile",
        "r",
        "automotive",
        "part"
    ],
    "wof:name":"Sherwood Auto Parts & Repair Inc",
    "wof:placetype":"venue"
},
  "geometry": {"coordinates":[-81.73290799999999,30.386342],"type":"Point"}
}