{
  "type": "Feature",
  "properties": {
    "addr:full":"6146 9th Ave Cir NE Bradenton FL 34212",
    "addr:housenumber":"6146",
    "addr:postcode":"34212",
    "addr:street":"9Th Ave Cir Ne",
    "iso:country":"US",
    "sg:address":"6146 9th Ave Cir NE",
    "sg:city":"Bradenton",
    "sg:classifiers":[
        {
            "category":"Freight",
            "type":"Transportation"
        }
    ],
    "sg:phone":"+1 941 750 8990",
    "sg:postcode":"34212",
    "sg:province":"FL",
    "sg:tags":[
        "broker"
    ],
    "wof:name":"Commercial Transport Network",
    "wof:placetype":"venue"
},
  "geometry": {"coordinates":[-82.482585,27.512208],"type":"Point"}
}