{
  "type": "Feature",
  "properties": {
    "iso:country":"US",
    "sg:address":"19375 SW 127th Ct",
    "sg:city":"Miami",
    "sg:classifiers":[
        {
            "category":"Utilities",
            "type":"Services"
        }
    ],
    "sg:phone":"+1 305 256 9418",
    "sg:postcode":"33177",
    "sg:province":"FL",
    "sg:tags":[
        "sanitary"
    ],
    "wof:name":"Sweepmasters Sweeping Service",
    "wof:placetype":"venue"
},
  "geometry": {"coordinates":[-80.398053,25.584755],"type":"Point"}
}