{
  "type": "Feature",
  "properties": {
    "iso:country":"US",
    "sg:address":"315 Carroll St",
    "sg:city":"Eastpoint",
    "sg:classifiers":[
        {
            "category":"Building & Trades",
            "subcategory":"Construction",
            "type":"Services"
        }
    ],
    "sg:phone":"+1 850 670 4515",
    "sg:postcode":"32328",
    "sg:province":"FL",
    "sg:tags":[
        "heavy"
    ],
    "wof:name":"Tideline Construction Inc",
    "wof:placetype":"venue"
},
  "geometry": {"coordinates":[-84.882508,29.759817],"type":"Point"}
}