{
  "type": "Feature",
  "properties": {
    "addr:full":"1901 Main St Dunedin FL 34698",
    "addr:housenumber":"1901",
    "addr:postcode":"34698",
    "addr:street":"Main St",
    "iso:country":"US",
    "sg:address":"1901 Main St",
    "sg:city":"Dunedin",
    "sg:classifiers":[
        {
            "category":"Autos & Motor Vehicles",
            "subcategory":"Auto Supplies",
            "type":"Retail Goods"
        }
    ],
    "sg:phone":"+1 727 738 1414",
    "sg:postcode":"34698",
    "sg:province":"FL",
    "sg:tags":[
        "tire"
    ],
    "wof:name":"Tire Kingdom",
    "wof:placetype":"venue"
},
  "geometry": {"coordinates":[-82.753714,28.019379],"type":"Point"}
}