{
  "type": "Feature",
  "properties": {
    "iso:country":"US",
    "sg:address":"5960 7th Ave W",
    "sg:city":"Bradenton",
    "sg:classifiers":[
        {
            "category":"Shopping",
            "subcategory":"Clothing, Apparel, & Fashions",
            "type":"Retail Goods"
        }
    ],
    "sg:phone":"+1 941 798 9611",
    "sg:postcode":"34209",
    "sg:province":"FL",
    "wof:name":"Speechless Couture",
    "wof:placetype":"venue"
},
  "geometry": {"coordinates":[-82.622277,27.495137],"type":"Point"}
}