{
  "type": "Feature",
  "properties": {
    "iso:country":"US",
    "sg:address":"1781 NE 8th St",
    "sg:city":"Homestead",
    "sg:classifiers":[
        {
            "category":"Food & Beverages",
            "subcategory":"Groceries & Convenience Stores",
            "type":"Retail Goods"
        }
    ],
    "sg:phone":"+1 305 247 1350",
    "sg:postcode":"33033",
    "sg:province":"FL",
    "wof:name":"Food Spot",
    "wof:placetype":"venue"
},
  "geometry": {"coordinates":[-80.45456299999999,25.477428],"type":"Point"}
}