{
  "type": "Feature",
  "properties": {
    "iso:country":"US",
    "sg:address":"9820 NW 80th Ave",
    "sg:city":"Hialeah",
    "sg:classifiers":[
        {
            "category":"Manufacturing",
            "subcategory":"Leather Goods",
            "type":"Manufacturing & Wholesale Goods"
        }
    ],
    "sg:phone":"+1 305 821 0047",
    "sg:postcode":"33016",
    "sg:province":"FL",
    "wof:name":"Canal Sales Co",
    "wof:placetype":"venue"
},
  "geometry": {"coordinates":[-80.326926,25.862744],"type":"Point"}
}