{
  "type": "Feature",
  "properties": {
    "addr:full":"12401 174th Ct N Jupiter FL 33478",
    "addr:housenumber":"12401",
    "addr:postcode":"33478",
    "addr:street":"174Th Ct N",
    "iso:country":"US",
    "sg:address":"12401 174th Ct N",
    "sg:city":"Jupiter",
    "sg:classifiers":[
        {
            "category":"Professional",
            "subcategory":"Management & Consulting",
            "type":"Services"
        }
    ],
    "sg:phone":"+1 561 262 6509",
    "sg:postcode":"33478",
    "sg:province":"FL",
    "sg:tags":[
        "business"
    ],
    "wof:name":"Accelagrow Inc",
    "wof:placetype":"venue"
},
  "geometry": {"coordinates":[-80.230582,26.934136],"type":"Point"}
}