{
  "type": "Feature",
  "properties": {
    "iso:country":"US",
    "sg:address":"11667 Countryway Blvd",
    "sg:city":"Tampa",
    "sg:classifiers":[
        {
            "category":"Insurance",
            "subcategory":"Insurance Agent",
            "type":"Services"
        }
    ],
    "sg:phone":"+1 813 814 5777",
    "sg:postcode":"33626",
    "sg:province":"FL",
    "wof:name":"AAA Insurance",
    "wof:placetype":"venue"
},
  "geometry": {"coordinates":[-82.623605,28.055124],"type":"Point"}
}