{
  "type": "Feature",
  "properties": {
    "iso:country":"US",
    "sg:address":"546 E Mallard Creek Dr",
    "sg:city":"Freeport",
    "sg:classifiers":[
        {
            "category":"Freight",
            "type":"Transportation"
        }
    ],
    "sg:phone":"+1 850 835 1599",
    "sg:postcode":"32439",
    "sg:province":"FL",
    "sg:tags":[
        "operator",
        "local",
        "trucking"
    ],
    "wof:name":"Cooeys Trucking Inc",
    "wof:placetype":"venue"
},
  "geometry": {"coordinates":[-86.120722,30.477596],"type":"Point"}
}