{
  "type": "Feature",
  "properties": {
    "iso:country":"US",
    "sg:address":"8647 Uranus Ter",
    "sg:city":"West Palm Beach",
    "sg:classifiers":[
        {
            "category":"Building & Trades",
            "subcategory":"Construction",
            "type":"Services"
        }
    ],
    "sg:phone":"+1 561 776 0575",
    "sg:postcode":"33403",
    "sg:province":"FL",
    "sg:tags":[
        "contractor"
    ],
    "wof:name":"Marion Hardy Pressure Cleaning",
    "wof:placetype":"venue"
},
  "geometry": {"coordinates":[-80.09174899999999,26.803561],"type":"Point"}
}