{
  "type": "Feature",
  "properties": {
    "iso:country":"US",
    "sg:address":"2339 Mango Ave",
    "sg:city":"Sarasota",
    "sg:classifiers":[
        {
            "category":"Building & Trades",
            "subcategory":"Cleaning & Sanitation",
            "type":"Services"
        }
    ],
    "sg:phone":"+1 941 365 1274",
    "sg:postcode":"34234",
    "sg:province":"FL",
    "sg:tags":[
        "janitor"
    ],
    "wof:name":"Clark & Wallace",
    "wof:placetype":"venue"
},
  "geometry": {"coordinates":[-82.526374,27.357381],"type":"Point"}
}