{
  "type": "Feature",
  "properties": {
    "iso:country":"US",
    "sg:address":"3351 Northern Blvd",
    "sg:city":"Lake Placid",
    "sg:classifiers":[
        {
            "category":"Building & Trades",
            "subcategory":"Construction",
            "type":"Services"
        }
    ],
    "sg:phone":"+1 863 699 9872",
    "sg:postcode":"33852",
    "sg:province":"FL",
    "sg:tags":[
        "house",
        "general",
        "contractor"
    ],
    "wof:name":"J E Siegle Construction Inc",
    "wof:placetype":"venue"
},
  "geometry": {"coordinates":[-81.446343,27.354905],"type":"Point"}
}