{
  "type": "Feature",
  "properties": {
    "iso:country":"US",
    "sg:address":"3379 Bowers Ln",
    "sg:city":"Jacksonville",
    "sg:classifiers":[
        {
            "category":"Restaurant",
            "type":"Food & Drink"
        }
    ],
    "sg:phone":"+1 904 448 6938",
    "sg:postcode":"32257",
    "sg:province":"FL",
    "sg:tags":[
        "eating"
    ],
    "wof:name":"Thyme For A Change",
    "wof:placetype":"venue"
},
  "geometry": {"coordinates":[-81.626248,30.203924],"type":"Point"}
}