{
  "type": "Feature",
  "properties": {
    "iso:country":"US",
    "sg:address":"547 E New York Ave",
    "sg:city":"De Land",
    "sg:classifiers":[
        {
            "category":"Health Services",
            "subcategory":"Health Practitioner",
            "type":"Services"
        }
    ],
    "sg:phone":"+1 386 740 1234",
    "sg:postcode":"32724",
    "sg:province":"FL",
    "wof:name":"Hypnosis Information Hotline",
    "wof:placetype":"venue"
},
  "geometry": {"coordinates":[-81.294166,29.0282],"type":"Point"}
}