{
  "type": "Feature",
  "properties": {
    "addr:full":"1549 Townsend Blvd Jacksonville FL 32211",
    "addr:housenumber":"1549",
    "addr:postcode":"32211",
    "addr:street":"Townsend Blvd",
    "iso:country":"US",
    "sg:address":"1549 Townsend Blvd",
    "sg:city":"Jacksonville",
    "sg:classifiers":[
        {
            "category":"Professional",
            "type":"Services"
        }
    ],
    "sg:phone":"+1 904 247 5225",
    "sg:postcode":"32211",
    "sg:province":"FL",
    "wof:name":"John K Bolen Svc",
    "wof:placetype":"venue"
},
  "geometry": {"coordinates":[-81.57521800000001,30.339194],"type":"Point"}
}