{
  "type": "Feature",
  "properties": {
    "iso:country":"US",
    "sg:address":"104 Indian Bayou Dr",
    "sg:city":"Destin",
    "sg:classifiers":[
        {
            "category":"Autos & Motor Vehicles",
            "subcategory":"Boat Sales",
            "type":"Retail Goods"
        }
    ],
    "sg:phone":"+1 850 837 5469",
    "sg:postcode":"32541",
    "sg:province":"FL",
    "wof:name":"Southeastern Powerboats Inc",
    "wof:placetype":"venue"
},
  "geometry": {"coordinates":[-86.44997499999999,30.399968],"type":"Point"}
}