{
  "type": "Feature",
  "properties": {
    "iso:country":"US",
    "sg:address":"1603 Camerbur Dr",
    "sg:city":"Orlando",
    "sg:classifiers":[
        {
            "category":"Home & Garden",
            "subcategory":"Household Appliances",
            "type":"Retail Goods"
        },
        {
            "category":"Wholesale",
            "subcategory":"Electrical",
            "type":"Manufacturing & Wholesale Goods"
        },
        {
            "category":"Professional",
            "subcategory":"Engineering",
            "type":"Services"
        }
    ],
    "sg:phone":"+1 407 447 7774",
    "sg:postcode":"32805",
    "sg:province":"FL",
    "sg:tags":[
        "purifying",
        "system",
        "systems-wholesale",
        "equipment",
        "manufacturer",
        "air conditioning",
        "cleaning"
    ],
    "wof:name":"Evergreen Sales & Service Inc",
    "wof:placetype":"venue"
},
  "geometry": {"coordinates":[-81.401312,28.528499],"type":"Point"}
}