{
  "type": "Feature",
  "properties": {
    "iso:country":"US",
    "sg:address":"107 Wymore Rd",
    "sg:city":"Maitland",
    "sg:classifiers":[
        {
            "category":"Social Services",
            "subcategory":"Child Care",
            "type":"Services"
        }
    ],
    "sg:phone":"+1 407 622 1330",
    "sg:postcode":"32751",
    "sg:province":"FL",
    "sg:tags":[
        "day"
    ],
    "wof:name":"Christian Eatonville Academy",
    "wof:placetype":"venue"
},
  "geometry": {"coordinates":[-81.385226,28.631723],"type":"Point"}
}