{
  "type": "Feature",
  "properties": {
    "iso:country":"US",
    "sg:address":"7513 Red Bud Ct",
    "sg:city":"Orlando",
    "sg:classifiers":[
        {
            "category":"Building & Trades",
            "subcategory":"Construction",
            "type":"Services"
        }
    ],
    "sg:phone":"+1 407 677 8277",
    "sg:postcode":"32807",
    "sg:province":"FL",
    "sg:tags":[
        "hanging",
        "contractor"
    ],
    "wof:name":"Tom Eaton Painting & Pressure",
    "wof:placetype":"venue"
},
  "geometry": {"coordinates":[-81.285285,28.581848],"type":"Point"}
}