{
  "type": "Feature",
  "properties": {
    "iso:country":"US",
    "sg:address":"4756 Bay Point Rd",
    "sg:city":"Miami",
    "sg:classifiers":[
        {
            "category":"Professional",
            "type":"Services"
        }
    ],
    "sg:phone":"+1 305 573 2445",
    "sg:postcode":"33137",
    "sg:province":"FL",
    "wof:name":"World Biznet Inc",
    "wof:placetype":"venue"
},
  "geometry": {"coordinates":[-80.186961,25.820011],"type":"Point"}
}