{
  "type": "Feature",
  "properties": {
    "iso:country":"US",
    "sg:address":"1714 Co Rd 1",
    "sg:city":"Dunedin",
    "sg:classifiers":[
        {
            "category":"Personal",
            "subcategory":"Barber",
            "type":"Services"
        }
    ],
    "sg:phone":"+1 727 733 1044",
    "sg:postcode":"34698",
    "sg:province":"FL",
    "sg:tags":[
        "shop"
    ],
    "wof:name":"Fred's Barber & Styling Shop",
    "wof:placetype":"venue"
},
  "geometry": {"coordinates":[-82.76243100000001,28.029788],"type":"Point"}
}