{
  "type": "Feature",
  "properties": {
    "iso:country":"US",
    "sg:address":"7431 Mott Ave",
    "sg:city":"Orlando",
    "sg:classifiers":[
        {
            "category":"Building & Trades",
            "subcategory":"Construction",
            "type":"Services"
        }
    ],
    "sg:phone":"+1 407 298 9228",
    "sg:postcode":"32810",
    "sg:province":"FL",
    "sg:tags":[
        "hanging",
        "contractor"
    ],
    "wof:name":"Don Yeoman S Painting",
    "wof:placetype":"venue"
},
  "geometry": {"coordinates":[-81.438574,28.623786],"type":"Point"}
}