{
  "type": "Feature",
  "properties": {
    "iso:country":"US",
    "sg:address":"644 Beulah Rd",
    "sg:city":"Winter Garden",
    "sg:classifiers":[
        {
            "category":"Government",
            "subcategory":"Office",
            "type":"Public Place"
        }
    ],
    "sg:phone":"+1 407 836 3111",
    "sg:postcode":"34787",
    "sg:province":"FL",
    "sg:website":"www.ocfl.net",
    "wof:name":"Orange County Highway Mntnc",
    "wof:placetype":"venue"
},
  "geometry": {"coordinates":[-81.572665,28.534961],"type":"Point"}
}