{
  "type": "Feature",
  "properties": {
    "iso:country":"US",
    "sg:address":"923 Hwy 2297",
    "sg:city":"Panama City",
    "sg:classifiers":[
        {
            "category":"Building & Trades",
            "subcategory":"Electrical",
            "type":"Services"
        }
    ],
    "sg:phone":"+1 850 871 5511",
    "sg:postcode":"32404",
    "sg:province":"FL",
    "sg:tags":[
        "electric",
        "contractor"
    ],
    "wof:name":"Steve Davis Electrical Svc Inc",
    "wof:placetype":"venue"
},
  "geometry": {"coordinates":[-85.50158,30.12918],"type":"Point"}
}