{
  "type": "Feature",
  "properties": {
    "addr:full":"950 Roosevelt Blvd Tarpon Springs FL 34689",
    "addr:housenumber":"950",
    "addr:postcode":"34689",
    "addr:street":"Roosevelt Blvd",
    "iso:country":"US",
    "sg:address":"950 Roosevelt Blvd",
    "sg:city":"Tarpon Springs",
    "sg:classifiers":[
        {
            "category":"Shopping",
            "subcategory":"Clothing, Apparel, & Fashions",
            "type":"Retail Goods"
        }
    ],
    "sg:phone":"+1 727 943 5296",
    "sg:postcode":"34689",
    "sg:province":"FL",
    "wof:name":"Carols of Tarpon",
    "wof:placetype":"venue"
},
  "geometry": {"coordinates":[-82.76365,28.155452],"type":"Point"}
}