{
  "type": "Feature",
  "properties": {
    "iso:country":"US",
    "sg:address":"9655 Westview Dr",
    "sg:city":"Coral Springs",
    "sg:classifiers":[
        {
            "category":"Personal",
            "subcategory":"Beauty Salon",
            "type":"Services"
        }
    ],
    "sg:phone":"+1 954 752 5356",
    "sg:postcode":"33076",
    "sg:province":"FL",
    "wof:name":"Super Nail Spa",
    "wof:placetype":"venue"
},
  "geometry": {"coordinates":[-80.255117,26.297923],"type":"Point"}
}