{
  "type": "Feature",
  "properties": {
    "addr:full":"144 131st Ave E Madeira Beach FL 33708",
    "addr:housenumber":"144",
    "addr:postcode":"33708",
    "addr:street":"131St Ave E",
    "iso:country":"US",
    "sg:address":"144 131st Ave E",
    "sg:city":"Madeira Beach",
    "sg:classifiers":[
        {
            "category":"Professional",
            "type":"Services"
        }
    ],
    "sg:phone":"+1 727 392 8707",
    "sg:postcode":"33708",
    "sg:province":"FL",
    "sg:tags":[
        "establishment"
    ],
    "wof:name":"D & M Post",
    "wof:placetype":"venue"
},
  "geometry": {"coordinates":[-82.783495,27.789231],"type":"Point"}
}