{
  "type": "Feature",
  "properties": {
    "addr:full":"2626 Goodlette Rd N Naples FL 34103",
    "addr:housenumber":"2626",
    "addr:postcode":"34103",
    "addr:street":"Goodlette Rd N",
    "iso:country":"US",
    "sg:address":"2626 Goodlette Rd N",
    "sg:city":"Naples",
    "sg:classifiers":[
        {
            "category":"Retail",
            "subcategory":"Animal Services",
            "type":"Services"
        }
    ],
    "sg:phone":"+1 239 775 9567",
    "sg:postcode":"34103",
    "sg:province":"FL",
    "wof:name":"Kennel Em",
    "wof:placetype":"venue"
},
  "geometry": {"coordinates":[-81.791641,26.179652],"type":"Point"}
}