{
  "type": "Feature",
  "properties": {
    "iso:country":"US",
    "sg:address":"1901 Arnold Rd",
    "sg:city":"Jacksonville",
    "sg:classifiers":[
        {
            "category":"Building & Trades",
            "subcategory":"Construction",
            "type":"Services"
        }
    ],
    "sg:phone":"+1 904 221 1779",
    "sg:postcode":"32218",
    "sg:province":"FL",
    "sg:tags":[
        "excavation",
        "contractor"
    ],
    "wof:name":"Thomas Backhoe Service Inc",
    "wof:placetype":"venue"
},
  "geometry": {"coordinates":[-81.680322,30.52237],"type":"Point"}
}