{
  "type": "Feature",
  "properties": {
    "iso:country":"US",
    "sg:address":"2690 Lakeville Rd",
    "sg:city":"Apopka",
    "sg:classifiers":[
        {
            "category":"Farming",
            "subcategory":"Nursery",
            "type":"Manufacturing & Wholesale Goods"
        }
    ],
    "sg:phone":"+1 407 886 5910",
    "sg:postcode":"32703",
    "sg:province":"FL",
    "sg:tags":[
        "potted",
        "plant",
        "grower"
    ],
    "sg:website":"www.lakevillenursery.com",
    "wof:name":"Lakeville Nursery Inc",
    "wof:placetype":"venue"
},
  "geometry": {"coordinates":[-81.480513,28.640409],"type":"Point"}
}