{
  "type": "Feature",
  "properties": {
    "addr:full":"825 Veranda Pl Kissimmee FL 34747",
    "addr:housenumber":"825",
    "addr:postcode":"34747",
    "addr:street":"Veranda Pl",
    "iso:country":"US",
    "sg:address":"825 Veranda Pl",
    "sg:city":"Kissimmee",
    "sg:classifiers":[
        {
            "category":"Insurance",
            "subcategory":"Insurance Agent",
            "type":"Services"
        }
    ],
    "sg:phone":"+1 407 566 0472",
    "sg:postcode":"34747",
    "sg:province":"FL",
    "wof:name":"Barrett Insurance Service",
    "wof:placetype":"venue"
},
  "geometry": {"coordinates":[-81.54688299999999,28.322362],"type":"Point"}
}