{
  "type": "Feature",
  "properties": {
    "addr:full":"1904 NW 12th Ter Gainesville FL 32609",
    "addr:housenumber":"1904",
    "addr:postcode":"32609",
    "addr:street":"Nw 12Th Ter",
    "iso:country":"US",
    "sg:address":"1904 NW 12th Ter",
    "sg:city":"Gainesville",
    "sg:classifiers":[
        {
            "category":"Education",
            "subcategory":"Special Training",
            "type":"Public Place"
        }
    ],
    "sg:phone":"+1 352 335 5950",
    "sg:postcode":"32609",
    "sg:province":"FL",
    "sg:tags":[
        "instruction",
        "driving"
    ],
    "wof:name":"Sun-Coast Driver Edcuation",
    "wof:placetype":"venue"
},
  "geometry": {"coordinates":[-82.338213,29.669275],"type":"Point"}
}