{
  "type": "Feature",
  "properties": {
    "iso:country":"US",
    "sg:address":"2781 E Atlantic Blvd",
    "sg:city":"Pompano Beach",
    "sg:classifiers":[
        {
            "category":"Food & Beverages",
            "subcategory":"Meat & Fish",
            "type":"Retail Goods"
        }
    ],
    "sg:phone":"+1 954 941 3275",
    "sg:postcode":"33062",
    "sg:province":"FL",
    "sg:tags":[
        "seafood",
        "market"
    ],
    "wof:name":"Mr Fish Seafood Inc",
    "wof:placetype":"venue"
},
  "geometry": {"coordinates":[-80.09626299999999,26.231981],"type":"Point"}
}