{
  "type": "Feature",
  "properties": {
    "iso:country":"US",
    "sg:address":"11628 Bay Vista Rd",
    "sg:city":"Panama City",
    "sg:classifiers":[
        {
            "category":"Building & Trades",
            "subcategory":"Construction",
            "type":"Services"
        }
    ],
    "sg:phone":"+1 850 874 9886",
    "sg:postcode":"32404",
    "sg:province":"FL",
    "sg:tags":[
        "house"
    ],
    "wof:name":"Billy Cox Construction",
    "wof:placetype":"venue"
},
  "geometry": {"coordinates":[-85.510651,30.134453],"type":"Point"}
}