{
  "type": "Feature",
  "properties": {
    "iso:country":"US",
    "sg:address":"2401 28th Ave N",
    "sg:city":"St Petersburg",
    "sg:classifiers":[
        {
            "category":"Autos & Motor Vehicles",
            "subcategory":"Boat Sales",
            "type":"Retail Goods"
        },
        {
            "category":"Retail",
            "subcategory":"Repair Shop",
            "type":"Services"
        }
    ],
    "sg:phone":"+1 727 898 2010",
    "sg:postcode":"33713",
    "sg:province":"FL",
    "sg:tags":[
        "equipment",
        "marine",
        "supply"
    ],
    "wof:name":"Escardo Marine",
    "wof:placetype":"venue"
},
  "geometry": {"coordinates":[-82.665277,27.797452],"type":"Point"}
}