{
  "type": "Feature",
  "properties": {
    "iso:country":"US",
    "sg:address":"1239 Mount Vernon St",
    "sg:city":"Orlando",
    "sg:classifiers":[
        {
            "category":"Real Estate",
            "subcategory":"Real Estate Agent",
            "type":"Services"
        }
    ],
    "sg:phone":"+1 407 228 9901",
    "sg:postcode":"32803",
    "sg:province":"FL",
    "wof:name":"Classic Properties Group Inc",
    "wof:placetype":"venue"
},
  "geometry": {"coordinates":[-81.36328399999999,28.550458],"type":"Point"}
}