{
  "type": "Feature",
  "properties": {
    "iso:country":"US",
    "sg:address":"1621 Rogero Rd",
    "sg:city":"Jacksonville",
    "sg:classifiers":[
        {
            "category":"Building & Trades",
            "subcategory":"Pest Control",
            "type":"Services"
        }
    ],
    "sg:phone":"+1 904 745 5002",
    "sg:postcode":"32211",
    "sg:province":"FL",
    "wof:name":"Ross Turf & Ornamental Inc",
    "wof:placetype":"venue"
},
  "geometry": {"coordinates":[-81.589088,30.337651],"type":"Point"}
}