{
  "type": "Feature",
  "properties": {
    "iso:country":"US",
    "sg:address":"2245 State Hwy 210",
    "sg:city":"Jacksonville",
    "sg:classifiers":[
        {
            "category":"Shopping",
            "type":"Retail Goods"
        }
    ],
    "sg:phone":"+1 904 823 1700",
    "sg:postcode":"32259",
    "sg:province":"FL",
    "sg:tags":[
        "pet",
        "shop"
    ],
    "wof:name":"Fish Bowls Aquarium",
    "wof:placetype":"venue"
},
  "geometry": {"coordinates":[-81.51544800000001,30.06001],"type":"Point"}
}