{
  "type": "Feature",
  "properties": {
    "iso:country":"US",
    "sg:address":"3501 Jackson St",
    "sg:city":"Hollywood",
    "sg:classifiers":[
        {
            "category":"Professional",
            "type":"Services"
        }
    ],
    "sg:phone":"+1 954 986 1742",
    "sg:postcode":"33021",
    "sg:province":"FL",
    "wof:name":"Ramirez Access Control Corp",
    "wof:placetype":"venue"
},
  "geometry": {"coordinates":[-80.180905,26.007921],"type":"Point"}
}