{
  "type": "Feature",
  "properties": {
    "iso:country":"US",
    "sg:address":"3605 NE 207th St",
    "sg:city":"Miami",
    "sg:classifiers":[
        {
            "category":"Retail",
            "subcategory":"Animal Services",
            "type":"Services"
        }
    ],
    "sg:phone":"+1 305 342 3854",
    "sg:postcode":"33180",
    "sg:province":"FL",
    "sg:tags":[
        "pet",
        "boarding",
        "sitting"
    ],
    "sg:website":"www.runningrascals.com",
    "wof:name":"Running Rascals Pet Svc",
    "wof:placetype":"venue"
},
  "geometry": {"coordinates":[-80.130865,25.967823],"type":"Point"}
}