{
  "type": "Feature",
  "properties": {
    "addr:full":"3000 Medical Park Dr Tampa FL 33613",
    "addr:housenumber":"3000",
    "addr:postcode":"33613",
    "addr:street":"Medical Park Dr",
    "iso:country":"US",
    "sg:address":"3000 Medical Park Dr",
    "sg:city":"Tampa",
    "sg:classifiers":[
        {
            "category":"Health Services",
            "subcategory":"Doctor",
            "type":"Services"
        }
    ],
    "sg:phone":"+1 813 971 2470",
    "sg:postcode":"33613",
    "sg:province":"FL",
    "sg:tags":[
        "physician",
        "family",
        "practice",
        "surgeons",
        "medicine",
        "surgeon"
    ],
    "wof:name":"Dietrick, John",
    "wof:placetype":"venue"
},
  "geometry": {"coordinates":[-82.425392,28.071301],"type":"Point"}
}