{
  "type": "Feature",
  "properties": {
    "addr:full":"7215 Forest City Rd Orlando FL 32810",
    "addr:housenumber":"7215",
    "addr:postcode":"32810",
    "addr:street":"Forest City Rd",
    "iso:country":"US",
    "sg:address":"7215 Forest City Rd",
    "sg:city":"Orlando",
    "sg:classifiers":[
        {
            "category":"Organizations",
            "subcategory":"Religious Organization",
            "type":"Services"
        }
    ],
    "sg:phone":"+1 407 291 4532",
    "sg:postcode":"32810",
    "sg:province":"FL",
    "sg:tags":[
        "church"
    ],
    "sg:website":"www.iglesiaforestcity.com",
    "wof:name":"Iglesia De Dios Pentecostal",
    "wof:placetype":"venue"
},
  "geometry": {"coordinates":[-81.414918,28.62345],"type":"Point"}
}