{
  "type": "Feature",
  "properties": {
    "addr:full":"10011 SW 197th St Miami FL 33157",
    "addr:housenumber":"10011",
    "addr:postcode":"33157",
    "addr:street":"Sw 197Th St",
    "iso:country":"US",
    "sg:address":"10011 SW 197th St",
    "sg:city":"Miami",
    "sg:classifiers":[
        {
            "category":"Recreation",
            "type":"Entertainment"
        }
    ],
    "sg:phone":"+1 305 255 8192",
    "sg:postcode":"33157",
    "sg:province":"FL",
    "wof:name":"Adventure Bound Charters Inc",
    "wof:placetype":"venue"
},
  "geometry": {"coordinates":[-80.355138,25.584907],"type":"Point"}
}