{
  "type": "Feature",
  "properties": {
    "iso:country":"US",
    "sg:address":"5462 80th Avenue Cir E",
    "sg:city":"Palmetto",
    "sg:classifiers":[
        {
            "category":"Social Services",
            "type":"Services"
        }
    ],
    "sg:phone":"+1 941 722 5872",
    "sg:postcode":"34221",
    "sg:province":"FL",
    "sg:tags":[
        "personal"
    ],
    "wof:name":"Chiropractic Fitness Center",
    "wof:placetype":"venue"
},
  "geometry": {"coordinates":[-82.482783,27.562482],"type":"Point"}
}