{
  "type": "Feature",
  "properties": {
    "addr:full":"17775 N Bay Rd Miami FL 33160",
    "addr:housenumber":"17775",
    "addr:postcode":"33160",
    "addr:street":"N Bay Rd",
    "iso:country":"US",
    "sg:address":"17775 N Bay Rd",
    "sg:city":"Miami",
    "sg:classifiers":[
        {
            "category":"Organizations",
            "subcategory":"Religious Organization",
            "type":"Services"
        }
    ],
    "sg:phone":"+1 305 931 0600",
    "sg:postcode":"33160",
    "sg:province":"FL",
    "sg:tags":[
        "catholic",
        "church"
    ],
    "wof:name":"Saint Mary Magdalen Church",
    "wof:placetype":"venue"
},
  "geometry": {"coordinates":[-80.125682,25.939907],"type":"Point"}
}