{
  "type": "Feature",
  "properties": {
    "addr:full":"18350 NE 2nd Ave Miami FL 33179",
    "addr:housenumber":"18350",
    "addr:postcode":"33179",
    "addr:street":"Ne 2Nd Ave",
    "iso:country":"US",
    "sg:address":"18350 NE 2nd Ave",
    "sg:city":"Miami",
    "sg:classifiers":[
        {
            "category":"Manufacturing",
            "subcategory":"Food",
            "type":"Manufacturing & Wholesale Goods"
        }
    ],
    "sg:phone":"+1 305 651 2242",
    "sg:postcode":"33179",
    "sg:province":"FL",
    "sg:tags":[
        "mayonnaise",
        "salad",
        "dressing"
    ],
    "wof:name":"Captain Rick's Packaging Inc",
    "wof:placetype":"venue"
},
  "geometry": {"coordinates":[-80.19695900000001,25.945199],"type":"Point"}
}