{
  "type": "Feature",
  "properties": {
    "iso:country":"US",
    "sg:address":"7226 US Hwy 1",
    "sg:city":"Port Saint Lucie",
    "sg:classifiers":[
        {
            "category":"Food & Beverages",
            "subcategory":"Meat & Fish",
            "type":"Retail Goods"
        }
    ],
    "sg:phone":"+1 772 873 0394",
    "sg:postcode":"34952",
    "sg:province":"FL",
    "wof:name":"Unlimited Caribbean",
    "wof:placetype":"venue"
},
  "geometry": {"coordinates":[-80.32261800000001,27.330101],"type":"Point"}
}