{
  "type": "Feature",
  "properties": {
    "iso:country":"US",
    "sg:address":"728 Tigris Ln",
    "sg:city":"Lake Mary",
    "sg:classifiers":[
        {
            "category":"Building & Trades",
            "subcategory":"Construction",
            "type":"Services"
        }
    ],
    "sg:phone":"+1 407 322 5443",
    "sg:postcode":"32746",
    "sg:province":"FL",
    "sg:tags":[
        "home",
        "alteration"
    ],
    "wof:name":"Greg Gebben Custom Builder",
    "wof:placetype":"venue"
},
  "geometry": {"coordinates":[-81.344939,28.775196],"type":"Point"}
}