{
  "type": "Feature",
  "properties": {
    "iso:country":"US",
    "sg:address":"64 Hypolita St",
    "sg:city":"St Augustine",
    "sg:classifiers":[
        {
            "category":"Shopping",
            "subcategory":"Gifts & Souvenirs",
            "type":"Retail Goods"
        }
    ],
    "sg:phone":"+1 904 829 5220",
    "sg:postcode":"32084",
    "sg:province":"FL",
    "sg:tags":[
        "shop",
        "commercial",
        "design"
    ],
    "wof:name":"Dream Street Too",
    "wof:placetype":"venue"
},
  "geometry": {"coordinates":[-81.31377000000001,29.894753],"type":"Point"}
}