{
  "type": "Feature",
  "properties": {
    "iso:country":"US",
    "sg:address":"1550 W 84th St Ste 1",
    "sg:city":"Hialeah",
    "sg:classifiers":[
        {
            "category":"Restaurant",
            "type":"Food & Drink"
        }
    ],
    "sg:phone":"+1 305 821 7016",
    "sg:postcode":"33014",
    "sg:province":"FL",
    "wof:name":"Salvatore Pizzeria",
    "wof:placetype":"venue"
},
  "geometry": {"coordinates":[-80.315201,25.8986],"type":"Point"}
}