{
  "type": "Feature",
  "properties": {
    "iso:country":"US",
    "sg:address":"825 NW 119th St",
    "sg:city":"North Miami",
    "sg:classifiers":[
        {
            "category":"Building & Trades",
            "subcategory":"Locksmith",
            "type":"Services"
        }
    ],
    "sg:phone":"+1 305 428 9629",
    "sg:postcode":"33168",
    "sg:province":"FL",
    "sg:tags":[
        "key"
    ],
    "wof:name":"0 0 0 0 24 Hour A Emergency A Locksmith",
    "wof:placetype":"venue"
},
  "geometry": {"coordinates":[-80.213088,25.883777],"type":"Point"}
}