{
  "type": "Feature",
  "properties": {
    "iso:country":"US",
    "sg:address":"9245 SW 44th St",
    "sg:city":"Miami",
    "sg:classifiers":[
        {
            "category":"Real Estate",
            "subcategory":"Surveying",
            "type":"Services"
        }
    ],
    "sg:phone":"+1 305 553 1410",
    "sg:postcode":"33165",
    "sg:province":"FL",
    "wof:name":"All South Surveyors Inc",
    "wof:placetype":"venue"
},
  "geometry": {"coordinates":[-80.344672,25.72736],"type":"Point"}
}