{
  "type": "Feature",
  "properties": {
    "addr:full":"7710 US Hwy 1 Port St Lucie FL 34952",
    "addr:housenumber":"7710",
    "addr:postcode":"34952",
    "addr:street":"Us Hwy 1",
    "iso:country":"US",
    "sg:address":"7710 US Hwy 1",
    "sg:city":"Port St Lucie",
    "sg:classifiers":[
        {
            "category":"Health Services",
            "subcategory":"Doctor",
            "type":"Services"
        }
    ],
    "sg:phone":"+1 772 335 5300",
    "sg:postcode":"34952",
    "sg:province":"FL",
    "sg:tags":[
        "physician",
        "surgeon"
    ],
    "wof:name":"Coastal Orthopedic",
    "wof:placetype":"venue"
},
  "geometry": {"coordinates":[-80.318721,27.323412],"type":"Point"}
}