{
  "type": "Feature",
  "properties": {
    "addr:full":"12361 SW 128 Ct Ste 205 Miami FL 33186",
    "addr:housenumber":"12361",
    "addr:postcode":"33186",
    "addr:street":"Sw 128 Ct Ste 205",
    "iso:country":"US",
    "sg:address":"12361 SW 128 Ct Ste 205",
    "sg:city":"Miami",
    "sg:classifiers":[
        {
            "category":"Home & Garden",
            "subcategory":"Building Materials",
            "type":"Retail Goods"
        },
        {
            "category":"Building & Trades",
            "subcategory":"Construction",
            "type":"Services"
        }
    ],
    "sg:phone":"+1 305 253 5850",
    "sg:postcode":"33186",
    "sg:province":"FL",
    "sg:tags":[
        "awning",
        "canopy",
        "builder",
        "canopies-repair",
        "patio"
    ],
    "sg:website":"http://www.tecord.com",
    "wof:name":"Ace Awning Inc",
    "wof:placetype":"venue"
},
  "geometry": {"coordinates":[-80.40236899999999,25.65316],"type":"Point"}
}