{
  "type": "Feature",
  "properties": {
    "iso:country":"US",
    "sg:address":"260 SW 84th Ave Ste A",
    "sg:city":"Plantation",
    "sg:classifiers":[
        {
            "category":"Health Services",
            "subcategory":"Hospital",
            "type":"Services"
        },
        {
            "category":"Community Center",
            "type":"Public Place"
        }
    ],
    "sg:phone":"+1 954 382 0700",
    "sg:postcode":"33324",
    "sg:province":"FL",
    "sg:tags":[
        "medical"
    ],
    "wof:name":"Broward General Medical Center Broward Heart Specialists",
    "wof:placetype":"venue"
},
  "geometry": {"coordinates":[-80.260705,26.11717],"type":"Point"}
}