{
  "type": "Feature",
  "properties": {
    "addr:full":"1715 Lakeside Ave St Augustine FL 32084",
    "addr:housenumber":"1715",
    "addr:postcode":"32084",
    "addr:street":"Lakeside Ave St",
    "iso:country":"US",
    "sg:address":"1715 Lakeside Ave",
    "sg:city":"St Augustine",
    "sg:classifiers":[
        {
            "category":"Building & Trades",
            "subcategory":"Construction",
            "type":"Services"
        }
    ],
    "sg:phone":"+1 904 829 3466",
    "sg:postcode":"32084",
    "sg:province":"FL",
    "sg:tags":[
        "general",
        "contractor"
    ],
    "wof:name":"BTS Builders",
    "wof:placetype":"venue"
},
  "geometry": {"coordinates":[-81.331532,29.868409],"type":"Point"}
}