{
  "type": "Feature",
  "properties": {
    "iso:country":"US",
    "sg:address":"3333 Keystone Rd",
    "sg:city":"Tarpon Springs",
    "sg:classifiers":[
        {
            "category":"Organizations",
            "subcategory":"Religious Organization",
            "type":"Services"
        }
    ],
    "sg:phone":"+1 727 937 7333",
    "sg:postcode":"34688",
    "sg:province":"FL",
    "wof:name":"World Outreach International",
    "wof:placetype":"venue"
},
  "geometry": {"coordinates":[-82.684498,28.145193],"type":"Point"}
}