{
  "type": "Feature",
  "properties": {
    "iso:country":"US",
    "sg:address":"3783 Palm Valley Rd",
    "sg:city":"Ponte Vedra Bch",
    "sg:classifiers":[
        {
            "category":"Banks & Credit Unions",
            "subcategory":"Bank",
            "type":"Services"
        }
    ],
    "sg:phone":"+1 904 543 0478",
    "sg:postcode":"32082",
    "sg:province":"FL",
    "wof:name":"Mercantile Bank",
    "wof:placetype":"venue"
},
  "geometry": {"coordinates":[-81.37709099999999,30.145688],"type":"Point"}
}