{
  "type": "Feature",
  "properties": {
    "addr:full":"495 N Keller Rd Maitland FL 32751",
    "addr:housenumber":"495",
    "addr:postcode":"32751",
    "addr:street":"N Keller Rd",
    "iso:country":"US",
    "sg:address":"495 N Keller Rd",
    "sg:city":"Maitland",
    "sg:classifiers":[
        {
            "category":"Health Services",
            "subcategory":"Clinic",
            "type":"Services"
        },
        {
            "category":"Insurance",
            "subcategory":"Health Insurance",
            "type":"Services"
        }
    ],
    "sg:phone":"+1 407 659 6900",
    "sg:postcode":"32751",
    "sg:province":"FL",
    "sg:tags":[
        "plan"
    ],
    "sg:website":"www.unitedhealthcare.com",
    "wof:name":"United Healthcare",
    "wof:placetype":"venue"
},
  "geometry": {"coordinates":[-81.398584,28.630538],"type":"Point"}
}