{
  "type": "Feature",
  "properties": {
    "addr:full":"1105 Guava Isle Fort Lauderdale FL 33315",
    "addr:housenumber":"1105",
    "addr:postcode":"33315",
    "addr:street":"Guava Isle",
    "iso:country":"US",
    "sg:address":"1105 Guava Isle",
    "sg:city":"Fort Lauderdale",
    "sg:classifiers":[
        {
            "category":"Shopping",
            "subcategory":"Clothing, Apparel, & Fashions",
            "type":"Retail Goods"
        }
    ],
    "sg:phone":"+1 954 766 6005",
    "sg:postcode":"33315",
    "sg:province":"FL",
    "wof:name":"Classic Clothiers Inc",
    "wof:placetype":"venue"
},
  "geometry": {"coordinates":[-80.156918,26.103311],"type":"Point"}
}