{
  "type": "Feature",
  "properties": {
    "iso:country":"US",
    "sg:address":"415 Pasadena Ave S",
    "sg:city":"St Petersburg",
    "sg:classifiers":[
        {
            "category":"Real Estate",
            "subcategory":"Real Estate Agent",
            "type":"Services"
        }
    ],
    "sg:phone":"+1 727 344 0808",
    "sg:postcode":"33707",
    "sg:province":"FL",
    "wof:name":"ARPL Real Estate Inc",
    "wof:placetype":"venue"
},
  "geometry": {"coordinates":[-82.733518,27.766884],"type":"Point"}
}