{
  "type": "Feature",
  "properties": {
    "iso:country":"US",
    "sg:address":"60 Seagate Dr",
    "sg:city":"Naples",
    "sg:classifiers":[
        {
            "category":"Banks & Credit Unions",
            "subcategory":"Financial Services",
            "type":"Services"
        }
    ],
    "sg:phone":"+1 239 430 2126",
    "sg:postcode":"34103",
    "sg:province":"FL",
    "sg:tags":[
        "trust",
        "investment"
    ],
    "wof:name":"Cbc Capital Ltd",
    "wof:placetype":"venue"
},
  "geometry": {"coordinates":[-81.81539600000001,26.207897],"type":"Point"}
}