{
  "type": "Feature",
  "properties": {
    "iso:country":"US",
    "sg:address":"1001 SE 21st St",
    "sg:city":"Cape Coral",
    "sg:classifiers":[
        {
            "category":"Shopping",
            "subcategory":"Beauty & Cosmetics",
            "type":"Retail Goods"
        }
    ],
    "sg:phone":"+1 239 574 8414",
    "sg:postcode":"33990",
    "sg:province":"FL",
    "sg:tags":[
        "merchandise"
    ],
    "wof:name":"Kay Whitney",
    "wof:placetype":"venue"
},
  "geometry": {"coordinates":[-81.95132099999999,26.613878],"type":"Point"}
}