{
  "type": "Feature",
  "properties": {
    "iso:country":"US",
    "sg:address":"7170 123rd Cir N",
    "sg:city":"Largo",
    "sg:classifiers":[
        {
            "category":"Wholesale",
            "subcategory":"Chemicals & Plastics",
            "type":"Manufacturing & Wholesale Goods"
        }
    ],
    "sg:phone":"+1 727 530 5990",
    "sg:postcode":"33773",
    "sg:province":"FL",
    "wof:name":"Plexi-Kraft",
    "wof:placetype":"venue"
},
  "geometry": {"coordinates":[-82.73874600000001,27.883941],"type":"Point"}
}