{
  "type": "Feature",
  "properties": {
    "iso:country":"US",
    "sg:address":"4640 6th Ave S",
    "sg:city":"St Petersburg",
    "sg:classifiers":[
        {
            "category":"Building & Trades",
            "subcategory":"Cleaning & Sanitation",
            "type":"Services"
        }
    ],
    "sg:phone":"+1 727 328 2210",
    "sg:postcode":"33711",
    "sg:province":"FL",
    "sg:tags":[
        "janitor"
    ],
    "wof:name":"Quick Clean",
    "wof:placetype":"venue"
},
  "geometry": {"coordinates":[-82.696635,27.764535],"type":"Point"}
}