{
  "type": "Feature",
  "properties": {
    "addr:full":"922 Chestwood Ave Tallahassee FL 32303",
    "addr:housenumber":"922",
    "addr:postcode":"32303",
    "addr:street":"Chestwood Ave",
    "iso:country":"US",
    "sg:address":"922 Chestwood Ave",
    "sg:city":"Tallahassee",
    "sg:classifiers":[
        {
            "category":"Building & Trades",
            "subcategory":"Landscaping Services",
            "type":"Services"
        }
    ],
    "sg:phone":"+1 850 386 3455",
    "sg:postcode":"32303",
    "sg:province":"FL",
    "sg:tags":[
        "tree"
    ],
    "wof:name":"The Mood Tree",
    "wof:placetype":"venue"
},
  "geometry": {"coordinates":[-84.299758,30.4713],"type":"Point"}
}