{
  "type": "Feature",
  "properties": {
    "iso:country":"US",
    "sg:address":"420 NW 23rd Ct",
    "sg:city":"Miami",
    "sg:classifiers":[
        {
            "category":"Shopping",
            "subcategory":"Tobacco",
            "type":"Retail Goods"
        }
    ],
    "sg:phone":"+1 305 541 8735",
    "sg:postcode":"33125",
    "sg:province":"FL",
    "sg:tags":[
        "cigarette",
        "cigar"
    ],
    "wof:name":"Smoke & Mirrors Electronic Cigarette",
    "wof:placetype":"venue"
},
  "geometry": {"coordinates":[-80.233687,25.777557],"type":"Point"}
}