{
  "type": "Feature",
  "properties": {
    "addr:full":"5100 Tamiami Trl N Naples FL 34103",
    "addr:housenumber":"5100",
    "addr:postcode":"34103",
    "addr:street":"Tamiami Trl N",
    "iso:country":"US",
    "sg:address":"5100 Tamiami Trl N",
    "sg:city":"Naples",
    "sg:classifiers":[
        {
            "category":"Insurance",
            "subcategory":"Insurance Agent",
            "type":"Services"
        }
    ],
    "sg:phone":"+1 239 262 8530",
    "sg:postcode":"34103",
    "sg:province":"FL",
    "wof:name":"New England Financial",
    "wof:placetype":"venue"
},
  "geometry": {"coordinates":[-81.80040700000001,26.210209],"type":"Point"}
}