{
  "type": "Feature",
  "properties": {
    "addr:full":"11438 Genter Dr Spring Hill FL 34609",
    "addr:housenumber":"11438",
    "addr:postcode":"34609",
    "addr:street":"Genter Dr",
    "iso:country":"US",
    "sg:address":"11438 Genter Dr",
    "sg:city":"Spring Hill",
    "sg:classifiers":[
        {
            "category":"Building & Trades",
            "subcategory":"Construction",
            "type":"Services"
        }
    ],
    "sg:phone":"+1 352 666 2671",
    "sg:postcode":"34609",
    "sg:province":"FL",
    "sg:tags":[
        "hanging",
        "contractor"
    ],
    "wof:name":"Gerald J Boice Painting",
    "wof:placetype":"venue"
},
  "geometry": {"coordinates":[-82.53152799999999,28.450167],"type":"Point"}
}