{
  "type": "Feature",
  "properties": {
    "iso:country":"US",
    "sg:address":"381 Hidden Valley Dr",
    "sg:city":"Naples",
    "sg:classifiers":[
        {
            "category":"Professional",
            "subcategory":"Computer Services",
            "type":"Services"
        }
    ],
    "sg:phone":"+1 239 775 5200",
    "sg:postcode":"34113",
    "sg:province":"FL",
    "sg:tags":[
        "school",
        "processing",
        "datum",
        "related"
    ],
    "wof:name":"HMS Management Group Inc",
    "wof:placetype":"venue"
},
  "geometry": {"coordinates":[-81.72974000000001,26.097428],"type":"Point"}
}