{
  "type": "Feature",
  "properties": {
    "iso:country":"US",
    "sg:address":"1500 SE 24th Rd",
    "sg:city":"Ocala",
    "sg:classifiers":[
        {
            "category":"Social Services",
            "subcategory":"Adult Care",
            "type":"Services"
        }
    ],
    "sg:phone":"+1 352 732 1122",
    "sg:postcode":"34471",
    "sg:province":"FL",
    "sg:tags":[
        "home",
        "residential"
    ],
    "wof:name":"Alterra Sterling House",
    "wof:placetype":"venue"
},
  "geometry": {"coordinates":[-82.117441,29.160429],"type":"Point"}
}