{
  "type": "Feature",
  "properties": {
    "iso:country":"US",
    "sg:address":"8120 NW 66th St",
    "sg:city":"Miami",
    "sg:classifiers":[
        {
            "category":"Wholesale",
            "subcategory":"Durable Goods & Equipment",
            "type":"Manufacturing & Wholesale Goods"
        }
    ],
    "sg:phone":"+1 305 629 9141",
    "sg:postcode":"33166",
    "sg:province":"FL",
    "sg:tags":[
        "exporter"
    ],
    "wof:name":"River Export Transport",
    "wof:placetype":"venue"
},
  "geometry": {"coordinates":[-80.328157,25.833413],"type":"Point"}
}