{
  "type": "Feature",
  "properties": {
    "addr:full":"1646 Fruitwood Dr Clearwater FL 33756",
    "addr:housenumber":"1646",
    "addr:postcode":"33756",
    "addr:street":"Fruitwood Dr",
    "iso:country":"US",
    "sg:address":"1646 Fruitwood Dr",
    "sg:city":"Clearwater",
    "sg:classifiers":[
        {
            "category":"Retail",
            "subcategory":"Repair Shop",
            "type":"Services"
        },
        {
            "category":"Building & Trades",
            "subcategory":"Plumbing",
            "type":"Services"
        }
    ],
    "sg:phone":"+1 727 507 8462",
    "sg:postcode":"33756",
    "sg:province":"FL",
    "sg:tags":[
        "conditioning",
        "air",
        "system",
        "contractor"
    ],
    "wof:name":"Keith's Air Conditioning Inc",
    "wof:placetype":"venue"
},
  "geometry": {"coordinates":[-82.766817,27.944514],"type":"Point"}
}