{
  "type": "Feature",
  "properties": {
    "iso:country":"US",
    "sg:address":"2305 Urban Rd",
    "sg:city":"Jacksonville",
    "sg:classifiers":[
        {
            "category":"Professional",
            "subcategory":"Business Services",
            "type":"Services"
        }
    ],
    "sg:phone":"+1 904 389 5672",
    "sg:postcode":"32210",
    "sg:province":"FL",
    "wof:name":"Vernon Townsend Lumber Co",
    "wof:placetype":"venue"
},
  "geometry": {"coordinates":[-81.72076800000001,30.276899],"type":"Point"}
}