{
  "type": "Feature",
  "properties": {
    "addr:full":"583 E State Rd 434 Longwood FL 32750",
    "addr:housenumber":"583;434",
    "addr:postcode":"32750",
    "addr:street":"E State Rd",
    "iso:country":"US",
    "sg:address":"583 E State Rd 434",
    "sg:city":"Longwood",
    "sg:classifiers":[
        {
            "category":"Organizations",
            "subcategory":"Non-profit Organization",
            "type":"Services"
        }
    ],
    "sg:phone":"+1 407 327 1765",
    "sg:postcode":"32750",
    "sg:province":"FL",
    "sg:tags":[
        "info",
        "addiction",
        "abuse",
        "treatment",
        "drug"
    ],
    "sg:website":"www.thegrove.org",
    "wof:name":"Grove Counseling Ctr Inc",
    "wof:placetype":"venue"
},
  "geometry": {"coordinates":[-81.33537,28.698185],"type":"Point"}
}