{
  "type": "Feature",
  "properties": {
    "addr:full":"9400 International Ct N Saint Petersburg FL 33716",
    "addr:housenumber":"9400",
    "addr:postcode":"33716",
    "addr:street":"International Ct N",
    "iso:country":"US",
    "sg:address":"9400 International Ct N",
    "sg:city":"Saint Petersburg",
    "sg:classifiers":[
        {
            "category":"Retail",
            "subcategory":"Repair Shop",
            "type":"Services"
        }
    ],
    "sg:phone":"+1 727 578 2200",
    "sg:postcode":"33716",
    "sg:province":"FL",
    "sg:tags":[
        "refrigeration",
        "conditioning",
        "air"
    ],
    "wof:name":"Service America Network Inc",
    "wof:placetype":"venue"
},
  "geometry": {"coordinates":[-82.65385499999999,27.860561],"type":"Point"}
}