{
  "type": "Feature",
  "properties": {
    "iso:country":"US",
    "sg:address":"9811 NW 80th Ave Unit 7G",
    "sg:city":"Hialeah",
    "sg:classifiers":[
        {
            "category":"Home & Garden",
            "subcategory":"Furniture",
            "type":"Retail Goods"
        }
    ],
    "sg:phone":"+1 305 827 1656",
    "sg:postcode":"33016",
    "sg:province":"FL",
    "sg:tags":[
        "store"
    ],
    "wof:name":"Bulit Carpentry",
    "wof:placetype":"venue"
},
  "geometry": {"coordinates":[-80.326671,25.862682],"type":"Point"}
}