{
  "type": "Feature",
  "properties": {
    "iso:country":"US",
    "sg:address":"7470 Commerce Pl",
    "sg:city":"Sarasota",
    "sg:classifiers":[
        {
            "category":"Retail",
            "subcategory":"Auto Repair",
            "type":"Services"
        }
    ],
    "sg:phone":"+1 941 359 2896",
    "sg:postcode":"34243",
    "sg:province":"FL",
    "sg:tags":[
        "body",
        "automobile",
        "painting",
        "repairing"
    ],
    "wof:name":"Draper's Auto Clinic",
    "wof:placetype":"venue"
},
  "geometry": {"coordinates":[-82.548827,27.407647],"type":"Point"}
}