{
  "type": "Feature",
  "properties": {
    "addr:full":"8035 NW Gainesville Rd Ocala FL 34475",
    "addr:housenumber":"8035",
    "addr:postcode":"34475",
    "addr:street":"Nw Gainesville Rd",
    "iso:country":"US",
    "sg:address":"8035 NW Gainesville Rd",
    "sg:city":"Ocala",
    "sg:classifiers":[
        {
            "category":"Building & Trades",
            "subcategory":"Equipment Rental",
            "type":"Services"
        }
    ],
    "sg:phone":"+1 352 867 5438",
    "sg:postcode":"34475",
    "sg:province":"FL",
    "sg:tags":[
        "crane"
    ],
    "wof:name":"Gold Coast Crane Svc",
    "wof:placetype":"venue"
},
  "geometry": {"coordinates":[-82.183566,29.27769],"type":"Point"}
}