{
  "type": "Feature",
  "properties": {
    "iso:country":"US",
    "sg:address":"980 Wekiva Springs Rd",
    "sg:city":"Longwood",
    "sg:classifiers":[
        {
            "category":"Food & Beverages",
            "subcategory":"Groceries & Convenience Stores",
            "type":"Retail Goods"
        }
    ],
    "sg:phone":"+1 407 862 3246",
    "sg:postcode":"32779",
    "sg:province":"FL",
    "wof:name":"7-Eleven",
    "wof:placetype":"venue"
},
  "geometry": {"coordinates":[-81.419799,28.703507],"type":"Point"}
}