{
  "type": "Feature",
  "properties": {
    "iso:country":"US",
    "sg:address":"4000 S Babcock St",
    "sg:city":"Melbourne",
    "sg:classifiers":[
        {
            "category":"Retail",
            "subcategory":"Laundry & Dry Cleaning",
            "type":"Services"
        }
    ],
    "sg:phone":"+1 321 984 0848",
    "sg:postcode":"32901",
    "sg:province":"FL",
    "wof:name":"Babcock Laundromat & Dry Clnrs",
    "wof:placetype":"venue"
},
  "geometry": {"coordinates":[-80.62156,28.047895],"type":"Point"}
}