{
  "type": "Feature",
  "properties": {
    "addr:full":"2546 NE 97th Street Rd Anthony FL 32617",
    "addr:housenumber":"2546",
    "addr:postcode":"32617",
    "addr:street":"Ne 97Th Street Rd",
    "iso:country":"US",
    "sg:address":"2546 NE 97th Street Rd",
    "sg:city":"Anthony",
    "sg:classifiers":[
        {
            "category":"Restaurant",
            "type":"Food & Drink"
        }
    ],
    "sg:phone":"+1 352 867 9931",
    "sg:postcode":"32617",
    "sg:province":"FL",
    "sg:tags":[
        "eating"
    ],
    "wof:name":"Luigi Italian Restaurant",
    "wof:placetype":"venue"
},
  "geometry": {"coordinates":[-82.100101,29.291969],"type":"Point"}
}