{
  "type": "Feature",
  "properties": {
    "addr:full":"2712 NW 95th St Miami FL 33147",
    "addr:housenumber":"2712",
    "addr:postcode":"33147",
    "addr:street":"Nw 95Th St",
    "iso:country":"US",
    "sg:address":"2712 NW 95th St",
    "sg:city":"Miami",
    "sg:classifiers":[
        {
            "category":"Food & Beverages",
            "subcategory":"Groceries & Convenience Stores",
            "type":"Retail Goods"
        }
    ],
    "sg:phone":"+1 305 696 6365",
    "sg:postcode":"33147",
    "sg:province":"FL",
    "sg:tags":[
        "grocer"
    ],
    "wof:name":"Price Choice Supermarket",
    "wof:placetype":"venue"
},
  "geometry": {"coordinates":[-80.24258,25.860088],"type":"Point"}
}