{
  "type": "Feature",
  "properties": {
    "iso:country":"US",
    "sg:address":"10910 Atlantic Blvd",
    "sg:city":"Jacksonville",
    "sg:classifiers":[
        {
            "category":"Food & Beverages",
            "subcategory":"Groceries & Convenience Stores",
            "type":"Retail Goods"
        }
    ],
    "sg:phone":"+1 904 642 2981",
    "sg:postcode":"32225",
    "sg:province":"FL",
    "wof:name":"Sprint Food Store",
    "wof:placetype":"venue"
},
  "geometry": {"coordinates":[-81.516715,30.324534],"type":"Point"}
}