{
  "type": "Feature",
  "properties": {
    "iso:country":"US",
    "sg:address":"8221 Biscayne Blvd",
    "sg:city":"Miami",
    "sg:classifiers":[
        {
            "category":"Retail",
            "subcategory":"Repair Shop",
            "type":"Services"
        }
    ],
    "sg:phone":"+1 305 751 5851",
    "sg:postcode":"33138",
    "sg:province":"FL",
    "sg:tags":[
        "reupholstery",
        "furniture"
    ],
    "wof:name":"Rayco Car Service",
    "wof:placetype":"venue"
},
  "geometry": {"coordinates":[-80.184898,25.8507],"type":"Point"}
}