{
  "type": "Feature",
  "properties": {
    "iso:country":"US",
    "sg:address":"1731 S Ridgewood Ave",
    "sg:city":"South Daytona",
    "sg:classifiers":[
        {
            "category":"Building & Trades",
            "subcategory":"Construction",
            "type":"Services"
        }
    ],
    "sg:phone":"+1 386 761 1763",
    "sg:postcode":"32119",
    "sg:province":"FL",
    "sg:tags":[
        "coping",
        "plastering",
        "tiling",
        "pool",
        "swimming"
    ],
    "sg:website":"www.bluewaterpoolsupplies.com",
    "wof:name":"Blue Water Pool Supplies & Svc",
    "wof:placetype":"venue"
},
  "geometry": {"coordinates":[-81.006974,29.181063],"type":"Point"}
}