{
  "type": "Feature",
  "properties": {
    "addr:full":"300 Mears Blvd Oldsmar FL 34677",
    "addr:housenumber":"300",
    "addr:postcode":"34677",
    "addr:street":"Mears Blvd",
    "iso:country":"US",
    "sg:address":"300 Mears Blvd",
    "sg:city":"Oldsmar",
    "sg:classifiers":[
        {
            "category":"Manufacturing",
            "subcategory":"Wood Products",
            "type":"Manufacturing & Wholesale Goods"
        }
    ],
    "sg:phone":"+1 813 818 7100",
    "sg:postcode":"34677",
    "sg:province":"FL",
    "sg:tags":[
        "specialty",
        "mfg"
    ],
    "wof:name":"Mail Box Impressions",
    "wof:placetype":"venue"
},
  "geometry": {"coordinates":[-82.67506400000001,28.039596],"type":"Point"}
}