{
  "type": "Feature",
  "properties": {
    "addr:full":"4817 Manville Cir Jacksonville FL 32244",
    "addr:postcode":"4817;32244",
    "addr:street":"Manville Cir",
    "iso:country":"US",
    "sg:address":"4817 Manville Cir",
    "sg:city":"Jacksonville",
    "sg:classifiers":[
        {
            "category":"Freight",
            "type":"Transportation"
        }
    ],
    "sg:phone":"+1 904 779 6914",
    "sg:postcode":"32244",
    "sg:province":"FL",
    "sg:tags":[
        "operator",
        "local",
        "trucking"
    ],
    "wof:name":"Lamm Trucking Inc",
    "wof:placetype":"venue"
},
  "geometry": {"coordinates":[-81.705376,30.217578],"type":"Point"}
}