{
  "type": "Feature",
  "properties": {
    "iso:country":"US",
    "sg:address":"4412 Barnes Rd S",
    "sg:city":"Jacksonville",
    "sg:classifiers":[
        {
            "category":"Government",
            "subcategory":"Office",
            "type":"Public Place"
        }
    ],
    "sg:phone":"+1 904 733 7975",
    "sg:postcode":"32207",
    "sg:province":"FL",
    "sg:tags":[
        "educational",
        "program",
        "administrative"
    ],
    "wof:name":"Duval Co Sch Dist Area 1",
    "wof:placetype":"venue"
},
  "geometry": {"coordinates":[-81.610079,30.276757],"type":"Point"}
}