{
  "type": "Feature",
  "properties": {
    "addr:full":"18445 US Hwy 41 Lutz FL 33549",
    "addr:postcode":"18445;33549",
    "addr:street":"Us Hwy 41",
    "iso:country":"US",
    "sg:address":"18445 US Hwy 41",
    "sg:city":"Lutz",
    "sg:classifiers":[
        {
            "category":"Shopping",
            "subcategory":"Department Store",
            "type":"Retail Goods"
        }
    ],
    "sg:phone":"+1 813 909 0790",
    "sg:postcode":"33549",
    "sg:province":"FL",
    "sg:tags":[
        "shop"
    ],
    "wof:name":"Beall's Outlet",
    "wof:placetype":"venue"
},
  "geometry": {"coordinates":[-82.46261199999999,28.140853],"type":"Point"}
}