{
  "type": "Feature",
  "properties": {
    "iso:country":"US",
    "sg:address":"7280 W Palmetto Park Rd",
    "sg:city":"Boca Raton",
    "sg:classifiers":[
        {
            "category":"Professional",
            "subcategory":"Credit Reporting & Collection",
            "type":"Services"
        }
    ],
    "sg:phone":"+1 561 241 2600",
    "sg:postcode":"33433",
    "sg:province":"FL",
    "sg:tags":[
        "agency"
    ],
    "wof:name":"Corporate Credit Exchange",
    "wof:placetype":"venue"
},
  "geometry": {"coordinates":[-80.15894,26.350235],"type":"Point"}
}