{
  "type": "Feature",
  "properties": {
    "iso:country":"US",
    "sg:address":"1426 Roxie St",
    "sg:city":"Atlantic Beach",
    "sg:classifiers":[
        {
            "category":"Building & Trades",
            "subcategory":"Landscaping Services",
            "type":"Services"
        }
    ],
    "sg:phone":"+1 904 247 6801",
    "sg:postcode":"32233",
    "sg:province":"FL",
    "sg:tags":[
        "landscape",
        "contractor"
    ],
    "wof:name":"Earthscapes Inc",
    "wof:placetype":"venue"
},
  "geometry": {"coordinates":[-81.43026399999999,30.393165],"type":"Point"}
}