{
  "type": "Feature",
  "properties": {
    "addr:full":"3023 W Kennedy Blvd Tampa FL 33609",
    "addr:housenumber":"3023",
    "addr:postcode":"33609",
    "addr:street":"W Kennedy Blvd",
    "iso:country":"US",
    "sg:address":"3023 W Kennedy Blvd",
    "sg:city":"Tampa",
    "sg:classifiers":[
        {
            "category":"Bars & Pubs",
            "type":"Food & Drink"
        }
    ],
    "sg:phone":"+1 813 874 1145",
    "sg:postcode":"33609",
    "sg:province":"FL",
    "sg:tags":[
        "drinking"
    ],
    "wof:name":"Seven Seas",
    "wof:placetype":"venue"
},
  "geometry": {"coordinates":[-82.493274,27.944792],"type":"Point"}
}