{
  "type": "Feature",
  "properties": {
    "addr:full":"2605 State Hwy 37 Mulberry FL 33860",
    "addr:housenumber":"2605",
    "addr:postcode":"33860",
    "addr:street":"State Hwy 37",
    "iso:country":"US",
    "sg:address":"2605 State Hwy 37",
    "sg:city":"Mulberry",
    "sg:classifiers":[
        {
            "category":"Wholesale",
            "subcategory":"Scrap",
            "type":"Manufacturing & Wholesale Goods"
        }
    ],
    "sg:phone":"+1 863 425 2550",
    "sg:postcode":"33860",
    "sg:province":"FL",
    "sg:tags":[
        "metal",
        "iron"
    ],
    "wof:name":"T & M Salvage Inc",
    "wof:placetype":"venue"
},
  "geometry": {"coordinates":[-81.973885,27.911479],"type":"Point"}
}