{
  "type": "Feature",
  "properties": {
    "addr:full":"415 Angle Rd Fort Pierce FL 34947",
    "addr:housenumber":"415",
    "addr:postcode":"34947",
    "addr:street":"Angle Rd",
    "iso:country":"US",
    "sg:address":"415 Angle Rd",
    "sg:city":"Fort Pierce",
    "sg:classifiers":[
        {
            "category":"Retail",
            "subcategory":"Auto Repair",
            "type":"Services"
        }
    ],
    "sg:phone":"+1 772 595 0387",
    "sg:postcode":"34947",
    "sg:province":"FL",
    "sg:tags":[
        "road"
    ],
    "wof:name":"All American Towing & Recovery",
    "wof:placetype":"venue"
},
  "geometry": {"coordinates":[-80.361166,27.452772],"type":"Point"}
}