{
  "type": "Feature",
  "properties": {
    "iso:country":"US",
    "sg:address":"1240 SW 11 Ave",
    "sg:city":"Gainesville",
    "sg:classifiers":[
        {
            "category":"Personal",
            "type":"Services"
        }
    ],
    "sg:phone":"+1 352 375 7466",
    "sg:postcode":"32601",
    "sg:province":"FL",
    "sg:tags":[
        "therapist",
        "massage"
    ],
    "wof:name":"Therapeutic Massage-A Marshall",
    "wof:placetype":"venue"
},
  "geometry": {"coordinates":[-82.33768600000001,29.640257],"type":"Point"}
}