{
  "type": "Feature",
  "properties": {
    "iso:country":"US",
    "sg:address":"411 N Ffa Rd",
    "sg:city":"Port St Lucie",
    "sg:classifiers":[
        {
            "category":"Building & Trades",
            "subcategory":"Landscaping Services",
            "type":"Services"
        }
    ],
    "sg:phone":"+1 772 878 1292",
    "sg:postcode":"34945",
    "sg:province":"FL",
    "sg:tags":[
        "lawn",
        "maintenance",
        "grounds"
    ],
    "wof:name":"Centex Hometeam Lawn Care",
    "wof:placetype":"venue"
},
  "geometry": {"coordinates":[-80.43146299999999,27.451024],"type":"Point"}
}