{
  "type": "Feature",
  "properties": {
    "addr:full":"22 S Ridgewood Ave Ormond Beach FL 32174",
    "addr:housenumber":"22",
    "addr:postcode":"32174",
    "addr:street":"S Ridgewood Ave",
    "iso:country":"US",
    "sg:address":"22 S Ridgewood Ave",
    "sg:city":"Ormond Beach",
    "sg:classifiers":[
        {
            "category":"Retail",
            "subcategory":"Laundry & Dry Cleaning",
            "type":"Services"
        }
    ],
    "sg:phone":"+1 386 446 1717",
    "sg:postcode":"32174",
    "sg:province":"FL",
    "sg:tags":[
        "cleaners",
        "rug",
        "carpet"
    ],
    "wof:name":"Seaside Services",
    "wof:placetype":"venue"
},
  "geometry": {"coordinates":[-81.058013,29.282794],"type":"Point"}
}