{
  "type": "Feature",
  "properties": {
    "iso:country":"US",
    "sg:address":"2150 SW 22nd St",
    "sg:city":"Coral Gables",
    "sg:classifiers":[
        {
            "category":"Shopping",
            "subcategory":"Pharmacy",
            "type":"Retail Goods"
        }
    ],
    "sg:phone":"+1 786 924 8271",
    "sg:postcode":"33145",
    "sg:province":"FL",
    "wof:name":"Rx Cardiovascular Spec Inc",
    "wof:placetype":"venue"
},
  "geometry": {"coordinates":[-80.22918300000001,25.750561],"type":"Point"}
}