{
  "type": "Feature",
  "properties": {
    "iso:country":"US",
    "sg:address":"177 Dan River Dr",
    "sg:city":"Spring Hill",
    "sg:classifiers":[
        {
            "category":"Education",
            "subcategory":"Dance Studio",
            "type":"Public Place"
        }
    ],
    "sg:phone":"+1 727 845 3626",
    "sg:postcode":"34606",
    "sg:province":"FL",
    "sg:tags":[
        "instruction",
        "dancing"
    ],
    "wof:name":"Dance Workshop",
    "wof:placetype":"venue"
},
  "geometry": {"coordinates":[-82.629474,28.436596],"type":"Point"}
}