{
  "type": "Feature",
  "properties": {
    "iso:country":"US",
    "sg:address":"5675 US Hwy 90",
    "sg:city":"Milton",
    "sg:classifiers":[
        {
            "category":"Shopping",
            "type":"Retail Goods"
        }
    ],
    "sg:phone":"+1 850 623 8194",
    "sg:postcode":"32583",
    "sg:province":"FL",
    "sg:tags":[
        "art",
        "gallery",
        "dealer"
    ],
    "wof:name":"Limited Edition Art Gallery",
    "wof:placetype":"venue"
},
  "geometry": {"coordinates":[-87.089924,30.602594],"type":"Point"}
}