{
  "type": "Feature",
  "properties": {
    "iso:country":"US",
    "sg:address":"5879 W Hwy 326",
    "sg:city":"Ocala",
    "sg:classifiers":[
        {
            "category":"Freight",
            "type":"Transportation"
        }
    ],
    "sg:phone":"+1 352 732 3902",
    "sg:postcode":"34482",
    "sg:province":"FL",
    "sg:tags":[
        "horse",
        "transporting"
    ],
    "sg:website":"www.hudsonhorsetransport.com",
    "wof:name":"Hudson Horse Vans Inc",
    "wof:placetype":"venue"
},
  "geometry": {"coordinates":[-82.21558,29.267097],"type":"Point"}
}