{
  "type": "Feature",
  "properties": {
    "iso:country":"US",
    "sg:address":"201 W Hallandale Beach Blvd",
    "sg:city":"Hallandale",
    "sg:classifiers":[
        {
            "category":"Retail",
            "subcategory":"Funeral Services",
            "type":"Services"
        }
    ],
    "sg:phone":"+1 954 454 6464",
    "sg:postcode":"33009",
    "sg:province":"FL",
    "wof:name":"Robert Greaver Funeral Home",
    "wof:placetype":"venue"
},
  "geometry": {"coordinates":[-80.151307,25.985523],"type":"Point"}
}