{
  "type": "Feature",
  "properties": {
    "iso:country":"US",
    "sg:address":"1446 Keats Rd",
    "sg:city":"Jacksonville",
    "sg:classifiers":[
        {
            "category":"Building & Trades",
            "subcategory":"Construction",
            "type":"Services"
        }
    ],
    "sg:phone":"+1 904 765 5782",
    "sg:postcode":"32208",
    "sg:province":"FL",
    "sg:tags":[
        "contractor"
    ],
    "wof:name":"Willie L Jones Ceramic Tile",
    "wof:placetype":"venue"
},
  "geometry": {"coordinates":[-81.683272,30.392576],"type":"Point"}
}