{
  "type": "Feature",
  "properties": {
    "iso:country":"US",
    "sg:address":"5104 N Orange Blossom Trl",
    "sg:city":"Orlando",
    "sg:classifiers":[
        {
            "category":"Organizations",
            "subcategory":"Religious Organization",
            "type":"Services"
        }
    ],
    "sg:phone":"+1 407 290 0088",
    "sg:postcode":"32810",
    "sg:province":"FL",
    "wof:name":"Insight With Faye Hardin",
    "wof:placetype":"venue"
},
  "geometry": {"coordinates":[-81.42089799999999,28.6045],"type":"Point"}
}