{
  "type": "Feature",
  "properties": {
    "addr:full":"360 Greco Ave Coral Gables FL 33146",
    "addr:housenumber":"360",
    "addr:postcode":"33146",
    "addr:street":"Greco Ave",
    "iso:country":"US",
    "sg:address":"360 Greco Ave",
    "sg:city":"Coral Gables",
    "sg:classifiers":[
        {
            "category":"Real Estate",
            "subcategory":"Real Estate Services",
            "type":"Services"
        }
    ],
    "sg:phone":"+1 305 445 1145",
    "sg:postcode":"33146",
    "sg:province":"FL",
    "sg:tags":[
        "management",
        "property"
    ],
    "wof:name":"Landmark Real Estate of Miami Inc",
    "wof:placetype":"venue"
},
  "geometry": {"coordinates":[-80.2612,25.730101],"type":"Point"}
}