{
  "type": "Feature",
  "properties": {
    "iso:country":"US",
    "sg:address":"14512 Perdido Key Dr",
    "sg:city":"Pensacola",
    "sg:classifiers":[
        {
            "category":"Real Estate",
            "subcategory":"Real Estate Agent",
            "type":"Services"
        }
    ],
    "sg:phone":"+1 850 492 2000",
    "sg:postcode":"32507",
    "sg:province":"FL",
    "wof:name":"Real Estates Sales Inc",
    "wof:placetype":"venue"
},
  "geometry": {"coordinates":[-87.44673400000001,30.294779],"type":"Point"}
}