{
  "type": "Feature",
  "properties": {
    "iso:country":"US",
    "sg:address":"900 N Spring Garden Ave",
    "sg:city":"Deland",
    "sg:classifiers":[
        {
            "category":"Banks & Credit Unions",
            "subcategory":"Bank",
            "type":"Services"
        }
    ],
    "sg:phone":"+1 386 738 8832",
    "sg:postcode":"32720",
    "sg:province":"FL",
    "sg:tags":[
        "state"
    ],
    "wof:name":"South Trust Bank",
    "wof:placetype":"venue"
},
  "geometry": {"coordinates":[-81.324653,29.040363],"type":"Point"}
}