{
  "type": "Feature",
  "properties": {
    "addr:full":"2095 59th St N Clearwater FL 33760",
    "addr:housenumber":"2095",
    "addr:postcode":"33760",
    "addr:street":"59Th St N",
    "iso:country":"US",
    "sg:address":"2095 59th St N",
    "sg:city":"Clearwater",
    "sg:classifiers":[
        {
            "category":"Manufacturing",
            "subcategory":"Apparel",
            "type":"Manufacturing & Wholesale Goods"
        }
    ],
    "sg:phone":"+1 727 536 1031",
    "sg:postcode":"33760",
    "sg:province":"FL",
    "sg:tags":[
        "cap",
        "hat",
        "millinery"
    ],
    "wof:name":"No-Knots By Harris'",
    "wof:placetype":"venue"
},
  "geometry": {"coordinates":[-82.715942,27.920476],"type":"Point"}
}