{
  "type": "Feature",
  "properties": {
    "iso:country":"US",
    "sg:address":"9369 Sheridan St Ste 713",
    "sg:city":"Hollywood",
    "sg:classifiers":[
        {
            "category":"Transit Center",
            "subcategory":"Freight",
            "type":"Transportation"
        }
    ],
    "sg:phone":"+1 954 434 6905",
    "sg:postcode":"33024",
    "sg:province":"FL",
    "sg:tags":[
        "forwarding"
    ],
    "wof:name":"Trinity Perishable Exports",
    "wof:placetype":"venue"
},
  "geometry": {"coordinates":[-80.271213,26.030348],"type":"Point"}
}