{
  "type": "Feature",
  "properties": {
    "addr:full":"3801 N University Dr Fort Lauderdale FL 33351",
    "addr:housenumber":"3801",
    "addr:postcode":"33351",
    "addr:street":"N University Dr",
    "iso:country":"US",
    "sg:address":"3801 N University Dr",
    "sg:city":"Fort Lauderdale",
    "sg:classifiers":[
        {
            "category":"Insurance",
            "subcategory":"Insurance Agent",
            "type":"Services"
        }
    ],
    "sg:phone":"+1 954 748 1700",
    "sg:postcode":"33351",
    "sg:province":"FL",
    "wof:name":"Allstate",
    "wof:placetype":"venue"
},
  "geometry": {"coordinates":[-80.256023,26.171187],"type":"Point"}
}