{
  "type": "Feature",
  "properties": {
    "addr:full":"7011 A C Skinner Pkwy Jacksonville FL 32256",
    "addr:housenumber":"7011 a c",
    "addr:postcode":"32256",
    "addr:street":"Skinner Pkwy",
    "iso:country":"US",
    "sg:address":"7011 A C Skinner Pkwy",
    "sg:city":"Jacksonville",
    "sg:classifiers":[
        {
            "category":"Education",
            "subcategory":"College",
            "type":"Public Place"
        }
    ],
    "sg:phone":"+1 904 296 3435",
    "sg:postcode":"32256",
    "sg:province":"FL",
    "sg:tags":[
        "academic",
        "school"
    ],
    "wof:name":"Education America-Jacksonville",
    "wof:placetype":"venue"
},
  "geometry": {"coordinates":[-81.57411999999999,30.24859],"type":"Point"}
}