{
  "type": "Feature",
  "properties": {
    "iso:country":"US",
    "sg:address":"206 S Park Ave Ste A",
    "sg:city":"Winter Park",
    "sg:classifiers":[
        {
            "category":"Communications",
            "type":"Services"
        }
    ],
    "sg:phone":"+1 407 838 3158",
    "sg:postcode":"32789",
    "sg:province":"FL",
    "sg:tags":[
        "web",
        "design"
    ],
    "sg:website":"www.caxiamgroup.com",
    "wof:name":"Caxiam Group",
    "wof:placetype":"venue"
},
  "geometry": {"coordinates":[-81.350748,28.596671],"type":"Point"}
}