{
  "type": "Feature",
  "properties": {
    "addr:full":"11401 NW 12th St Miami FL 33172",
    "addr:housenumber":"11401",
    "addr:postcode":"33172",
    "addr:street":"Nw 12Th St",
    "iso:country":"US",
    "sg:address":"11401 NW 12th St",
    "sg:city":"Miami",
    "sg:classifiers":[
        {
            "category":"Personal",
            "subcategory":"Beauty Salon",
            "type":"Services"
        }
    ],
    "sg:phone":"+1 305 463 0222",
    "sg:postcode":"33172",
    "sg:province":"FL",
    "sg:tags":[
        "spa"
    ],
    "sg:website":"www.browart23.com",
    "wof:name":"Brow Art 23",
    "wof:placetype":"venue"
},
  "geometry": {"coordinates":[-80.380928,25.786893],"type":"Point"}
}