{
  "type": "Feature",
  "properties": {
    "iso:country":"US",
    "sg:address":"113 E 44th St",
    "sg:city":"Jacksonville",
    "sg:classifiers":[
        {
            "category":"Professional",
            "type":"Services"
        }
    ],
    "sg:phone":"+1 904 634 0268",
    "sg:postcode":"32208",
    "sg:province":"FL",
    "wof:name":"Sharon McGregor Licensed Cosmt",
    "wof:placetype":"venue"
},
  "geometry": {"coordinates":[-81.650068,30.372718],"type":"Point"}
}