{
  "type": "Feature",
  "properties": {
    "addr:full":"4111 Cleveland St Hollywood FL 33021",
    "addr:housenumber":"4111",
    "addr:postcode":"33021",
    "addr:street":"Cleveland St",
    "iso:country":"US",
    "sg:address":"4111 Cleveland St",
    "sg:city":"Hollywood",
    "sg:classifiers":[
        {
            "category":"Professional",
            "subcategory":"Accounting & Tax Preparation",
            "type":"Services"
        }
    ],
    "sg:phone":"+1 954 966 5168",
    "sg:postcode":"33021",
    "sg:province":"FL",
    "sg:tags":[
        "accountant",
        "public",
        "certified"
    ],
    "wof:name":"Kary M Johnson",
    "wof:placetype":"venue"
},
  "geometry": {"coordinates":[-80.187787,26.022725],"type":"Point"}
}