{
  "type": "Feature",
  "properties": {
    "iso:country":"US",
    "sg:address":"21055 Bachmann Blvd",
    "sg:city":"Port Charlotte",
    "sg:classifiers":[
        {
            "category":"Building & Trades",
            "subcategory":"Construction",
            "type":"Services"
        }
    ],
    "sg:phone":"+1 941 766 8263",
    "sg:postcode":"33954",
    "sg:province":"FL",
    "sg:tags":[
        "floor",
        "laying",
        "contractor"
    ],
    "wof:name":"Floors With Klass Inc",
    "wof:placetype":"venue"
},
  "geometry": {"coordinates":[-82.103759,27.026991],"type":"Point"}
}