{
  "type": "Feature",
  "properties": {
    "iso:country":"US",
    "sg:address":"12330 SW 131st Ave",
    "sg:city":"Miami",
    "sg:classifiers":[
        {
            "category":"Home & Garden",
            "subcategory":"Home Furnishings",
            "type":"Retail Goods"
        }
    ],
    "sg:phone":"+1 305 256 9116",
    "sg:postcode":"33186",
    "sg:province":"FL",
    "sg:tags":[
        "draperies",
        "vertical",
        "blinds-venetian",
        "window",
        "treatment",
        "curtain"
    ],
    "wof:name":"A Plus Window Covering Inc",
    "wof:placetype":"venue"
},
  "geometry": {"coordinates":[-80.406532,25.655011],"type":"Point"}
}