{
  "type": "Feature",
  "properties": {
    "addr:full":"901 US Hwy 41 Venice FL 34285",
    "addr:housenumber":"901",
    "addr:postcode":"34285",
    "addr:street":"Us Hwy 41",
    "iso:country":"US",
    "sg:address":"901 US Hwy 41",
    "sg:city":"Venice",
    "sg:classifiers":[
        {
            "category":"Home & Garden",
            "subcategory":"Household Appliances",
            "type":"Retail Goods"
        }
    ],
    "sg:phone":"+1 941 485 0000",
    "sg:postcode":"34285",
    "sg:province":"FL",
    "wof:name":"Appliance Depot & More",
    "wof:placetype":"venue"
},
  "geometry": {"coordinates":[-82.439139,27.085314],"type":"Point"}
}