{
  "type": "Feature",
  "properties": {
    "addr:full":"10930 W Flagler St Miami FL 33174",
    "addr:housenumber":"10930",
    "addr:postcode":"33174",
    "addr:street":"W Flagler St",
    "iso:country":"US",
    "sg:address":"10930 W Flagler St",
    "sg:city":"Miami",
    "sg:classifiers":[
        {
            "category":"Military Area",
            "subcategory":"Coast Guard Base",
            "type":"Public Place"
        },
        {
            "category":"Insurance",
            "subcategory":"Hazard Insurance",
            "type":"Services"
        },
        {
            "category":"Government",
            "subcategory":"Department Of Motor Vehicles",
            "type":"Public Place"
        },
        {
            "category":"Professional",
            "subcategory":"Business Services",
            "type":"Services"
        },
        {
            "category":"Insurance",
            "subcategory":"Insurance Agent",
            "type":"Services"
        }
    ],
    "sg:phone":"+1 305 221 5042",
    "sg:postcode":"33174",
    "sg:province":"FL",
    "sg:tags":[
        "license",
        "auto",
        "tags-vehicle",
        "tag",
        "registration"
    ],
    "sg:website":"http://www.realpagessites.com/sweetwaterautotag",
    "wof:name":"Sweetwater Auto Tag Agency Inc",
    "wof:placetype":"venue"
},
  "geometry": {"coordinates":[-80.373547,25.768358],"type":"Point"}
}