{
  "type": "Feature",
  "properties": {
    "iso:country":"US",
    "sg:address":"8709 Tarragon Dr",
    "sg:city":"Orlando",
    "sg:classifiers":[
        {
            "category":"Organizations",
            "subcategory":"Religious Organization",
            "type":"Services"
        }
    ],
    "sg:phone":"+1 407 282 5841",
    "sg:postcode":"32825",
    "sg:province":"FL",
    "sg:tags":[
        "churches-baptist"
    ],
    "wof:name":"Elim Baptist Ministries Inc",
    "wof:placetype":"venue"
},
  "geometry": {"coordinates":[-81.261634,28.546117],"type":"Point"}
}