{
  "type": "Feature",
  "properties": {
    "addr:full":"2410 Deltona Blvd Spring Hill FL 34606",
    "addr:postcode":"2410;34606",
    "addr:street":"Deltona Blvd",
    "iso:country":"US",
    "sg:address":"2410 Deltona Blvd",
    "sg:city":"Spring Hill",
    "sg:classifiers":[
        {
            "category":"Professional",
            "subcategory":"Computer Services",
            "type":"Services"
        }
    ],
    "sg:phone":"+1 352 684 1020",
    "sg:postcode":"34606",
    "sg:province":"FL",
    "sg:tags":[
        "related"
    ],
    "wof:name":"Agnat Inc",
    "wof:placetype":"venue"
},
  "geometry": {"coordinates":[-82.582674,28.470745],"type":"Point"}
}