{
  "type": "Feature",
  "properties": {
    "iso:country":"US",
    "sg:address":"3015 Grand Ave",
    "sg:city":"Coconut Grove",
    "sg:classifiers":[
        {
            "category":"Restaurant",
            "type":"Food & Drink"
        }
    ],
    "sg:phone":"+1 305 444 2989",
    "sg:postcode":"33146",
    "sg:province":"FL",
    "sg:tags":[
        "yogurt",
        "frozen",
        "parlor",
        "ice",
        "cream"
    ],
    "sg:website":"www.cocogelato.com",
    "wof:name":"Coco Gelato",
    "wof:placetype":"venue"
},
  "geometry": {"coordinates":[-80.241823,25.728142],"type":"Point"}
}