{
  "type": "Feature",
  "properties": {
    "addr:full":"3290 W Sunrise Blvd Fort Lauderdale FL 33311",
    "addr:housenumber":"3290",
    "addr:postcode":"33311",
    "addr:street":"W Sunrise Blvd",
    "iso:country":"US",
    "sg:address":"3290 W Sunrise Blvd",
    "sg:city":"Fort Lauderdale",
    "sg:classifiers":[
        {
            "category":"Restaurant",
            "type":"Food & Drink"
        }
    ],
    "sg:phone":"+1 954 583 9002",
    "sg:postcode":"33311",
    "sg:province":"FL",
    "wof:name":"Subway Sandwiches & Salads",
    "wof:placetype":"venue"
},
  "geometry": {"coordinates":[-80.19025000000001,26.136075],"type":"Point"}
}