{
  "type": "Feature",
  "properties": {
    "iso:country":"US",
    "sg:address":"2453 NW 77th Ter",
    "sg:city":"Miami",
    "sg:classifiers":[
        {
            "category":"Retail",
            "subcategory":"Auto Repair",
            "type":"Services"
        }
    ],
    "sg:phone":"+1 305 835 8117",
    "sg:postcode":"33147",
    "sg:province":"FL",
    "sg:tags":[
        "body",
        "automobile",
        "painting"
    ],
    "wof:name":"Taller Body Shop Franco Preval",
    "wof:placetype":"venue"
},
  "geometry": {"coordinates":[-80.238581,25.844661],"type":"Point"}
}