{
  "type": "Feature",
  "properties": {
    "iso:country":"US",
    "sg:address":"1006 US Hwy 98",
    "sg:city":"Destin",
    "sg:classifiers":[
        {
            "category":"Professional",
            "subcategory":"Management & Consulting",
            "type":"Services"
        }
    ],
    "sg:phone":"+1 850 654 9646",
    "sg:postcode":"32541",
    "sg:province":"FL",
    "sg:tags":[
        "fuel"
    ],
    "wof:name":"JKP Intl Management Inc",
    "wof:placetype":"venue"
},
  "geometry": {"coordinates":[-86.469795,30.386605],"type":"Point"}
}