{
  "type": "Feature",
  "properties": {
    "addr:full":"2820 4th Ave N St Petersburg FL 33713",
    "addr:housenumber":"2820",
    "addr:postcode":"33713",
    "addr:street":"4Th Ave N",
    "iso:country":"US",
    "sg:address":"2820 4th Ave N",
    "sg:city":"St Petersburg",
    "sg:classifiers":[
        {
            "category":"Restaurant",
            "type":"Food & Drink"
        }
    ],
    "sg:phone":"+1 727 327 2481",
    "sg:postcode":"33713",
    "sg:province":"FL",
    "sg:tags":[
        "barbecue"
    ],
    "wof:name":"Old Man's Smokin Barbeque",
    "wof:placetype":"venue"
},
  "geometry": {"coordinates":[-82.672374,27.775493],"type":"Point"}
}