{
  "type": "Feature",
  "properties": {
    "iso:country":"US",
    "sg:address":"318 Indian Trce",
    "sg:city":"Fort Lauderdale",
    "sg:classifiers":[
        {
            "category":"Professional",
            "subcategory":"Computer Services",
            "type":"Services"
        }
    ],
    "sg:phone":"+1 954 659 3101",
    "sg:postcode":"33326",
    "sg:province":"FL",
    "sg:tags":[
        "programing",
        "custom"
    ],
    "wof:name":"Imaging 101 Inc",
    "wof:placetype":"venue"
},
  "geometry": {"coordinates":[-80.394148,26.120214],"type":"Point"}
}