{
  "type": "Feature",
  "properties": {
    "addr:full":"2811 SW 3rd Ave Miami FL 33129",
    "addr:housenumber":"2811",
    "addr:postcode":"33129",
    "addr:street":"Sw 3Rd Ave",
    "iso:country":"US",
    "sg:address":"2811 SW 3rd Ave",
    "sg:city":"Miami",
    "sg:classifiers":[
        {
            "category":"Professional",
            "subcategory":"Business Services",
            "type":"Services"
        }
    ],
    "sg:phone":"+1 305 860 6960",
    "sg:postcode":"33129",
    "sg:province":"FL",
    "sg:tags":[
        "recording",
        "studio"
    ],
    "wof:name":"Sprockets Music & Post",
    "wof:placetype":"venue"
},
  "geometry": {"coordinates":[-80.21066999999999,25.753586],"type":"Point"}
}