{
  "type": "Feature",
  "properties": {
    "iso:country":"US",
    "sg:address":"3555 Hispania Pl",
    "sg:city":"Sarasota",
    "sg:classifiers":[
        {
            "category":"Real Estate",
            "subcategory":"Real Estate Operator",
            "type":"Services"
        }
    ],
    "sg:phone":"+1 941 921 7575",
    "sg:postcode":"34232",
    "sg:province":"FL",
    "sg:tags":[
        "building",
        "apartment"
    ],
    "wof:name":"Village Plaza Condominium Assn",
    "wof:placetype":"venue"
},
  "geometry": {"coordinates":[-82.49592199999999,27.301934],"type":"Point"}
}