{
  "type": "Feature",
  "properties": {
    "addr:full":"6556 Bass Ln Milton FL 32570",
    "addr:housenumber":"6556",
    "addr:postcode":"32570",
    "addr:street":"Bass Ln",
    "iso:country":"US",
    "sg:address":"6556 Bass Ln",
    "sg:city":"Milton",
    "sg:classifiers":[
        {
            "category":"Building & Trades",
            "subcategory":"Construction",
            "type":"Services"
        }
    ],
    "sg:phone":"+1 850 626 5999",
    "sg:postcode":"32570",
    "sg:province":"FL",
    "sg:tags":[
        "home",
        "improvement"
    ],
    "wof:name":"H & M Home Improvement",
    "wof:placetype":"venue"
},
  "geometry": {"coordinates":[-87.045981,30.683377],"type":"Point"}
}