{
  "type": "Feature",
  "properties": {
    "iso:country":"US",
    "sg:address":"1815 Englewood Rd",
    "sg:city":"Englewood",
    "sg:classifiers":[
        {
            "category":"Real Estate",
            "subcategory":"Real Estate Agent",
            "type":"Services"
        }
    ],
    "sg:phone":"+1 941 473 8326",
    "sg:postcode":"34223",
    "sg:province":"FL",
    "wof:name":"J P Whittaker Realtor",
    "wof:placetype":"venue"
},
  "geometry": {"coordinates":[-82.37636500000001,27.000101],"type":"Point"}
}