{
  "type": "Feature",
  "properties": {
    "iso:country":"US",
    "sg:address":"1228 Orange Rd",
    "sg:city":"Lake Placid",
    "sg:classifiers":[
        {
            "category":"Building & Trades",
            "subcategory":"Construction",
            "type":"Services"
        }
    ],
    "sg:phone":"+1 863 465 1819",
    "sg:postcode":"33852",
    "sg:province":"FL",
    "sg:tags":[
        "commercial",
        "contractor"
    ],
    "wof:name":"Bodon Inc",
    "wof:placetype":"venue"
},
  "geometry": {"coordinates":[-81.35529099999999,27.31238],"type":"Point"}
}