{
  "type": "Feature",
  "properties": {
    "iso:country":"US",
    "sg:address":"8975 W Beaver St",
    "sg:city":"Jacksonville",
    "sg:classifiers":[
        {
            "category":"Building & Trades",
            "subcategory":"Construction",
            "type":"Services"
        }
    ],
    "sg:phone":"+1 904 781 4382",
    "sg:postcode":"32220",
    "sg:province":"FL",
    "sg:tags":[
        "welder"
    ],
    "wof:name":"Eatmon Welding Inc",
    "wof:placetype":"venue"
},
  "geometry": {"coordinates":[-81.804253,30.319139],"type":"Point"}
}