{
  "type": "Feature",
  "properties": {
    "iso:country":"US",
    "sg:address":"5850 Lake Grove Dr",
    "sg:city":"Lakeland",
    "sg:classifiers":[
        {
            "category":"Building & Trades",
            "subcategory":"Construction",
            "type":"Services"
        }
    ],
    "sg:phone":"+1 863 221 8164",
    "sg:postcode":"33809",
    "sg:province":"FL",
    "sg:tags":[
        "floor",
        "laying",
        "contractor"
    ],
    "wof:name":"Pablo Barbosa Flooring",
    "wof:placetype":"venue"
},
  "geometry": {"coordinates":[-81.965952,28.117824],"type":"Point"}
}