{
  "type": "Feature",
  "properties": {
    "addr:full":"7270 Lewis Grove Rd Groveland FL 34736",
    "addr:housenumber":"7270",
    "addr:postcode":"34736",
    "addr:street":"Lewis Grove Rd",
    "iso:country":"US",
    "sg:address":"7270 Lewis Grove Rd",
    "sg:city":"Groveland",
    "sg:classifiers":[
        {
            "category":"Building & Trades",
            "subcategory":"Landscaping Services",
            "type":"Services"
        }
    ],
    "sg:phone":"+1 352 429 8377",
    "sg:postcode":"34736",
    "sg:province":"FL",
    "wof:name":"Moore & Assoc Inc",
    "wof:placetype":"venue"
},
  "geometry": {"coordinates":[-81.83049,28.628618],"type":"Point"}
}