{
  "type": "Feature",
  "properties": {
    "iso:country":"US",
    "sg:address":"3145 NE 9th St",
    "sg:city":"Fort Lauderdale",
    "sg:classifiers":[
        {
            "category":"Restaurant",
            "type":"Food & Drink"
        }
    ],
    "sg:phone":"+1 954 565 3089",
    "sg:postcode":"33304",
    "sg:province":"FL",
    "sg:tags":[
        "eating"
    ],
    "wof:name":"Lucky Dvil Tttoos Bdy Piercing",
    "wof:placetype":"venue"
},
  "geometry": {"coordinates":[-80.10303999999999,26.136888],"type":"Point"}
}