{
  "type": "Feature",
  "properties": {
    "addr:full":"2407 del Prado Blvd S Cape Coral FL 33904",
    "addr:housenumber":"2407",
    "addr:postcode":"33904",
    "addr:street":"Del Prado Blvd S",
    "iso:country":"US",
    "sg:address":"2407 del Prado Blvd S",
    "sg:city":"Cape Coral",
    "sg:classifiers":[
        {
            "category":"Shopping",
            "subcategory":"Gifts & Souvenirs",
            "type":"Retail Goods"
        }
    ],
    "sg:phone":"+1 239 242 2434",
    "sg:postcode":"33904",
    "sg:province":"FL",
    "sg:tags":[
        "shop"
    ],
    "wof:name":"Candlelight Gifts",
    "wof:placetype":"venue"
},
  "geometry": {"coordinates":[-81.941064,26.607396],"type":"Point"}
}