{
  "type": "Feature",
  "properties": {
    "iso:country":"US",
    "sg:address":"12400 SW 128th St",
    "sg:city":"Miami",
    "sg:classifiers":[
        {
            "category":"Retail",
            "subcategory":"Auto Repair",
            "type":"Services"
        }
    ],
    "sg:phone":"+1 305 971 5850",
    "sg:postcode":"33186",
    "sg:province":"FL",
    "sg:tags":[
        "repairing",
        "automobile",
        "general"
    ],
    "wof:name":"Auto Germanica Inc",
    "wof:placetype":"venue"
},
  "geometry": {"coordinates":[-80.394723,25.648994],"type":"Point"}
}