{
  "type": "Feature",
  "properties": {
    "iso:country":"US",
    "sg:address":"22644 Pickerel Cir",
    "sg:city":"Boca Raton",
    "sg:classifiers":[
        {
            "category":"Shopping",
            "subcategory":"Musical Instruments",
            "type":"Retail Goods"
        }
    ],
    "sg:phone":"+1 561 883 2677",
    "sg:postcode":"33428",
    "sg:province":"FL",
    "wof:name":"Streader Music Inc",
    "wof:placetype":"venue"
},
  "geometry": {"coordinates":[-80.236126,26.339138],"type":"Point"}
}