{
  "type": "Feature",
  "properties": {
    "addr:full":"1025 S Orlando Ave Winter Park FL 32789",
    "addr:housenumber":"1025",
    "addr:postcode":"32789",
    "addr:street":"S Orlando Ave",
    "iso:country":"US",
    "sg:address":"1025 S Orlando Ave",
    "sg:city":"Winter Park",
    "sg:classifiers":[
        {
            "category":"Real Estate",
            "subcategory":"Real Estate Agent",
            "type":"Services"
        }
    ],
    "sg:phone":"+1 407 294 8505",
    "sg:postcode":"32789",
    "sg:province":"FL",
    "sg:tags":[
        "broker",
        "mortgage"
    ],
    "wof:name":"Loans To Go",
    "wof:placetype":"venue"
},
  "geometry": {"coordinates":[-81.364893,28.587865],"type":"Point"}
}