{
  "type": "Feature",
  "properties": {
    "addr:full":"233 Apache St Tavernier FL 33070",
    "addr:housenumber":"233",
    "addr:postcode":"33070",
    "addr:street":"Apache St",
    "iso:country":"US",
    "sg:address":"233 Apache St",
    "sg:city":"Tavernier",
    "sg:classifiers":[
        {
            "category":"Manufacturing",
            "subcategory":"Tools & Machinery",
            "type":"Manufacturing & Wholesale Goods"
        }
    ],
    "sg:phone":"+1 305 852 1846",
    "sg:postcode":"33070",
    "sg:province":"FL",
    "sg:tags":[
        "contractor",
        "construction",
        "paving",
        "mfg"
    ],
    "wof:name":"Precision Pavers Of Monroe County",
    "wof:placetype":"venue"
},
  "geometry": {"coordinates":[-80.549279,24.988367],"type":"Point"}
}