{
  "type": "Feature",
  "properties": {
    "addr:full":"14955 Gulf Blvd Madeira Beach FL 33708",
    "addr:housenumber":"14955",
    "addr:postcode":"33708",
    "addr:street":"Gulf Blvd",
    "iso:country":"US",
    "sg:address":"14955 Gulf Blvd",
    "sg:city":"Madeira Beach",
    "sg:classifiers":[
        {
            "category":"Organizations",
            "subcategory":"Religious Organization",
            "type":"Services"
        }
    ],
    "sg:phone":"+1 727 391 6364",
    "sg:postcode":"33708",
    "sg:province":"FL",
    "sg:tags":[
        "church"
    ],
    "sg:website":"www.calvarychapel.com",
    "wof:name":"Calvary Chapel",
    "wof:placetype":"venue"
},
  "geometry": {"coordinates":[-82.79903299999999,27.799394],"type":"Point"}
}