{
  "type": "Feature",
  "properties": {
    "iso:country":"US",
    "sg:address":"9100 N Nebraska Ave",
    "sg:city":"Tampa",
    "sg:classifiers":[
        {
            "category":"Building & Trades",
            "subcategory":"Construction",
            "type":"Services"
        }
    ],
    "sg:phone":"+1 813 933 8468",
    "sg:postcode":"33604",
    "sg:province":"FL",
    "sg:tags":[
        "contractor"
    ],
    "wof:name":"Glass Act Window Tinting",
    "wof:placetype":"venue"
},
  "geometry": {"coordinates":[-82.45126500000001,28.032632],"type":"Point"}
}