{
  "type": "Feature",
  "properties": {
    "addr:full":"2616 NE 27th Ct Pompano Beach FL 33064",
    "addr:housenumber":"2616",
    "addr:postcode":"33064",
    "addr:street":"Ne 27Th Ct",
    "iso:country":"US",
    "sg:address":"2616 NE 27th Ct",
    "sg:city":"Pompano Beach",
    "sg:classifiers":[
        {
            "category":"Building & Trades",
            "subcategory":"Construction",
            "type":"Services"
        }
    ],
    "sg:phone":"+1 954 592 7375",
    "sg:postcode":"33064",
    "sg:province":"FL",
    "sg:tags":[
        "hanging",
        "contractor"
    ],
    "wof:name":"Greco Interior Painting",
    "wof:placetype":"venue"
},
  "geometry": {"coordinates":[-80.086831,26.26538],"type":"Point"}
}