{
  "type": "Feature",
  "properties": {
    "addr:full":"3175 S Federal Hwy Delray Beach FL 33483",
    "addr:housenumber":"3175",
    "addr:postcode":"33483",
    "addr:street":"S Federal Hwy",
    "iso:country":"US",
    "sg:address":"3175 S Federal Hwy",
    "sg:city":"Delray Beach",
    "sg:classifiers":[
        {
            "category":"Professional",
            "subcategory":"Business Services",
            "type":"Services"
        }
    ],
    "sg:phone":"+1 561 272 2766",
    "sg:postcode":"33483",
    "sg:province":"FL",
    "sg:tags":[
        "auctioneer"
    ],
    "wof:name":"Auction It Off",
    "wof:placetype":"venue"
},
  "geometry": {"coordinates":[-80.073196,26.42608],"type":"Point"}
}