{
  "type": "Feature",
  "properties": {
    "addr:full":"1527 Pine Ave Holly Hill FL 32117",
    "addr:housenumber":"1527",
    "addr:postcode":"32117",
    "addr:street":"Pine Ave",
    "iso:country":"US",
    "sg:address":"1527 Pine Ave",
    "sg:city":"Holly Hill",
    "sg:classifiers":[
        {
            "category":"Manufacturing",
            "subcategory":"Motor Vehicles & Parts",
            "type":"Manufacturing & Wholesale Goods"
        }
    ],
    "sg:phone":"+1 386 677 9093",
    "sg:postcode":"32117",
    "sg:province":"FL",
    "sg:tags":[
        "motorcycle"
    ],
    "sg:website":"www.depss.com",
    "wof:name":"Diamond Engineering",
    "wof:placetype":"venue"
},
  "geometry": {"coordinates":[-81.048625,29.25183],"type":"Point"}
}