{
  "type": "Feature",
  "properties": {
    "addr:full":"909 W Amelia St Orlando FL 32805",
    "addr:housenumber":"909",
    "addr:postcode":"32805",
    "addr:street":"W Amelia St",
    "iso:country":"US",
    "sg:address":"909 W Amelia St",
    "sg:city":"Orlando",
    "sg:classifiers":[
        {
            "category":"Retail",
            "subcategory":"Auto Repair",
            "type":"Services"
        }
    ],
    "sg:phone":"+1 407 423 2294",
    "sg:postcode":"32805",
    "sg:province":"FL",
    "sg:tags":[
        "body",
        "automobile",
        "painting",
        "repairing"
    ],
    "wof:name":"Colonial Auto Body",
    "wof:placetype":"venue"
},
  "geometry": {"coordinates":[-81.39257000000001,28.54936],"type":"Point"}
}