{
  "type": "Feature",
  "properties": {
    "addr:full":"2012 N 59th St Tampa FL 33619",
    "addr:housenumber":"2012",
    "addr:postcode":"33619",
    "addr:street":"N 59Th St",
    "iso:country":"US",
    "sg:address":"2012 N 59th St",
    "sg:city":"Tampa",
    "sg:classifiers":[
        {
            "category":"Manufacturing",
            "subcategory":"Lumber",
            "type":"Manufacturing & Wholesale Goods"
        }
    ],
    "sg:phone":"+1 813 626 6792",
    "sg:postcode":"33619",
    "sg:province":"FL",
    "sg:tags":[
        "product",
        "forest",
        "gathering"
    ],
    "wof:name":"Frank & Beba Nursery",
    "wof:placetype":"venue"
},
  "geometry": {"coordinates":[-82.388929,27.964349],"type":"Point"}
}