{
  "type": "Feature",
  "properties": {
    "iso:country":"US",
    "sg:address":"819 W Desoto St",
    "sg:city":"Clermont",
    "sg:classifiers":[
        {
            "category":"Building & Trades",
            "subcategory":"Construction",
            "type":"Services"
        }
    ],
    "sg:phone":"+1 352 241 6003",
    "sg:postcode":"34711",
    "sg:province":"FL",
    "sg:tags":[
        "water",
        "restoration",
        "damage"
    ],
    "wof:name":"DTS Restorative Svc",
    "wof:placetype":"venue"
},
  "geometry": {"coordinates":[-81.77012999999999,28.554206],"type":"Point"}
}