{
  "type": "Feature",
  "properties": {
    "addr:full":"4698 US Hwy 27 Sebring FL 33870",
    "addr:housenumber":"4698",
    "addr:postcode":"33870",
    "addr:street":"Us Hwy 27",
    "iso:country":"US",
    "sg:address":"4698 US Hwy 27",
    "sg:city":"Sebring",
    "sg:classifiers":[
        {
            "category":"Shopping",
            "subcategory":"Used Merchandise",
            "type":"Retail Goods"
        }
    ],
    "sg:phone":"+1 863 314 8723",
    "sg:postcode":"33870",
    "sg:province":"FL",
    "sg:tags":[
        "furniture"
    ],
    "wof:name":"Trader Dan's",
    "wof:placetype":"venue"
},
  "geometry": {"coordinates":[-81.423293,27.455222],"type":"Point"}
}