{
  "type": "Feature",
  "properties": {
    "addr:full":"3200 Galilee Rd Jacksonville FL 32207",
    "addr:housenumber":"3200",
    "addr:postcode":"32207",
    "addr:street":"Galilee Rd",
    "iso:country":"US",
    "sg:address":"3200 Galilee Rd",
    "sg:city":"Jacksonville",
    "sg:classifiers":[
        {
            "category":"Home & Garden",
            "subcategory":"Building Materials",
            "type":"Retail Goods"
        }
    ],
    "sg:phone":"+1 904 683 3118",
    "sg:postcode":"32207",
    "sg:province":"FL",
    "wof:name":"Tony Valenzuela Wallpaper Inst",
    "wof:placetype":"venue"
},
  "geometry": {"coordinates":[-81.62229499999999,30.292786],"type":"Point"}
}