{
  "type": "Feature",
  "properties": {
    "iso:country":"US",
    "sg:address":"30 Llewellyn Trl",
    "sg:city":"Palm Coast",
    "sg:classifiers":[
        {
            "category":"Building & Trades",
            "subcategory":"Construction",
            "type":"Services"
        }
    ],
    "sg:phone":"+1 386 437 9773",
    "sg:postcode":"32164",
    "sg:province":"FL",
    "sg:tags":[
        "contractor"
    ],
    "wof:name":"A1 Window Tinting",
    "wof:placetype":"venue"
},
  "geometry": {"coordinates":[-81.21617000000001,29.449192],"type":"Point"}
}