{
  "type": "Feature",
  "properties": {
    "addr:full":"173 E Bloomingdale Ave Brandon FL 33511",
    "addr:housenumber":"173",
    "addr:postcode":"33511",
    "addr:street":"E Bloomingdale Ave",
    "iso:country":"US",
    "sg:address":"173 E Bloomingdale Ave",
    "sg:city":"Brandon",
    "sg:classifiers":[
        {
            "category":"Education",
            "subcategory":"Special Training",
            "type":"Public Place"
        }
    ],
    "sg:phone":"+1 813 661 1952",
    "sg:postcode":"33511",
    "sg:province":"FL",
    "sg:tags":[
        "tutoring"
    ],
    "wof:name":"Kumon Math & Reading Ctr",
    "wof:placetype":"venue"
},
  "geometry": {"coordinates":[-82.28278299999999,27.893592],"type":"Point"}
}