{
  "type": "Feature",
  "properties": {
    "addr:full":"414 E State Hwy 44 Wildwood FL 34785",
    "addr:housenumber":"414",
    "addr:postcode":"34785",
    "addr:street":"E State Hwy 44",
    "iso:country":"US",
    "sg:address":"414 E State Hwy 44",
    "sg:city":"Wildwood",
    "sg:classifiers":[
        {
            "category":"Retail",
            "subcategory":"Auto Repair",
            "type":"Services"
        }
    ],
    "sg:phone":"+1 352 330 1175",
    "sg:postcode":"34785",
    "sg:province":"FL",
    "sg:tags":[
        "truck"
    ],
    "wof:name":"All Fleet Refrigeration",
    "wof:placetype":"venue"
},
  "geometry": {"coordinates":[-82.096813,28.874937],"type":"Point"}
}