{
  "type": "Feature",
  "properties": {
    "addr:full":"1342 Sand Castle Rd Sanibel FL 33957",
    "addr:housenumber":"1342",
    "addr:postcode":"33957",
    "addr:street":"Sand Castle Rd",
    "iso:country":"US",
    "sg:address":"1342 Sand Castle Rd",
    "sg:city":"Sanibel",
    "sg:classifiers":[
        {
            "category":"Social Services",
            "subcategory":"Child Care",
            "type":"Services"
        }
    ],
    "sg:phone":"+1 239 395 4339",
    "sg:postcode":"33957",
    "sg:province":"FL",
    "sg:tags":[
        "day"
    ],
    "wof:name":"Rainbow Road Inc",
    "wof:placetype":"venue"
},
  "geometry": {"coordinates":[-82.04200299999999,26.450802],"type":"Point"}
}