{
  "type": "Feature",
  "properties": {
    "iso:country":"US",
    "sg:address":"200 SE 134th Ave",
    "sg:city":"Micanopy",
    "sg:classifiers":[
        {
            "category":"Communications",
            "subcategory":"Radio Station",
            "type":"Services"
        }
    ],
    "sg:phone":"+1 352 466 3883",
    "sg:postcode":"32667",
    "sg:province":"FL",
    "sg:tags":[
        "broadcast"
    ],
    "wof:name":"Wsky",
    "wof:placetype":"venue"
},
  "geometry": {"coordinates":[-82.32581999999999,29.538251],"type":"Point"}
}