{
  "type": "Feature",
  "properties": {
    "iso:country":"US",
    "sg:address":"15055 NW 22nd Ave",
    "sg:city":"Opa Locka",
    "sg:classifiers":[
        {
            "category":"Autos & Motor Vehicles",
            "subcategory":"Fuel & Gas Station",
            "type":"Retail Goods"
        }
    ],
    "sg:phone":"+1 786 621 7566",
    "sg:postcode":"33054",
    "sg:province":"FL",
    "wof:name":"4 B and B",
    "wof:placetype":"venue"
},
  "geometry": {"coordinates":[-80.23584,25.911448],"type":"Point"}
}