{
  "type": "Feature",
  "properties": {
    "iso:country":"US",
    "sg:address":"505 N John Rodes Blvd",
    "sg:city":"Melbourne",
    "sg:classifiers":[
        {
            "category":"Manufacturing",
            "subcategory":"Electronics",
            "type":"Manufacturing & Wholesale Goods"
        }
    ],
    "sg:phone":"+1 321 242 5000",
    "sg:postcode":"32934",
    "sg:province":"FL",
    "sg:tags":[
        "electronic",
        "system",
        "mfg"
    ],
    "wof:name":"Media Span",
    "wof:placetype":"venue"
},
  "geometry": {"coordinates":[-80.700171,28.113072],"type":"Point"}
}