{
  "type": "Feature",
  "properties": {
    "addr:full":"201 Baytree Dr Melbourne FL 32940",
    "addr:housenumber":"201",
    "addr:postcode":"32940",
    "addr:street":"Baytree Dr",
    "iso:country":"US",
    "sg:address":"201 Baytree Dr",
    "sg:city":"Melbourne",
    "sg:classifiers":[
        {
            "category":"Professional",
            "type":"Services"
        }
    ],
    "sg:phone":"+1 321 254 0017",
    "sg:postcode":"32940",
    "sg:province":"FL",
    "sg:tags":[
        "establishment"
    ],
    "wof:name":"Baytree Gate House",
    "wof:placetype":"venue"
},
  "geometry": {"coordinates":[-80.705698,28.229442],"type":"Point"}
}