{
  "type": "Feature",
  "properties": {
    "addr:full":"2013 State Hwy 87 Navarre FL 32566",
    "addr:housenumber":"2013",
    "addr:postcode":"32566",
    "addr:street":"State Hwy 87",
    "iso:country":"US",
    "sg:address":"2013 State Hwy 87",
    "sg:city":"Navarre",
    "sg:classifiers":[
        {
            "category":"Home & Garden",
            "subcategory":"Building Materials",
            "type":"Retail Goods"
        }
    ],
    "sg:phone":"+1 850 939 2550",
    "sg:postcode":"32566",
    "sg:province":"FL",
    "sg:tags":[
        "lumber"
    ],
    "wof:name":"Navarre Lumber & Supply",
    "wof:placetype":"venue"
},
  "geometry": {"coordinates":[-86.86967199999999,30.412889],"type":"Point"}
}