{
  "type": "Feature",
  "properties": {
    "iso:country":"US",
    "sg:address":"157 SW 127th Ave",
    "sg:city":"Fort Lauderdale",
    "sg:classifiers":[
        {
            "category":"Insurance",
            "subcategory":"Life Insurance",
            "type":"Services"
        }
    ],
    "sg:phone":"+1 954 473 6890",
    "sg:postcode":"33325",
    "sg:province":"FL",
    "sg:tags":[
        "carrier"
    ],
    "wof:name":"JP Financial Svcs",
    "wof:placetype":"venue"
},
  "geometry": {"coordinates":[-80.31842,26.118718],"type":"Point"}
}