{
  "type": "Feature",
  "properties": {
    "iso:country":"US",
    "sg:address":"2304 Killearn Center Blvd",
    "sg:city":"Tallahassee",
    "sg:classifiers":[
        {
            "category":"Organizations",
            "subcategory":"Membership Organization",
            "type":"Services"
        }
    ],
    "sg:phone":"+1 850 906 9333",
    "sg:postcode":"32309",
    "sg:province":"FL",
    "wof:name":"Florida Society-Health System",
    "wof:placetype":"venue"
},
  "geometry": {"coordinates":[-84.245204,30.506064],"type":"Point"}
}