{
  "type": "Feature",
  "properties": {
    "iso:country":"US",
    "sg:address":"2201 N Young Blvd",
    "sg:city":"Chiefland",
    "sg:classifiers":[
        {
            "category":"Professional",
            "subcategory":"Accounting & Tax Preparation",
            "type":"Services"
        }
    ],
    "sg:phone":"+1 352 490 9635",
    "sg:postcode":"32626",
    "sg:province":"FL",
    "sg:tags":[
        "return",
        "filing"
    ],
    "wof:name":"H & R Block Tax Svc",
    "wof:placetype":"venue"
},
  "geometry": {"coordinates":[-82.87094999999999,29.50135],"type":"Point"}
}