{
  "type": "Feature",
  "properties": {
    "iso:country":"US",
    "sg:address":"7190 Galloway Rd (sw 87th ave) Suite 205",
    "sg:city":"MIAMI",
    "sg:classifiers":[
        {
            "category":"Health Services",
            "subcategory":"Podiatrist",
            "type":"Services"
        }
    ],
    "sg:phone":"+1 305 598 1114",
    "sg:postcode":"33173",
    "sg:province":"FL",
    "sg:tags":[
        "physician",
        "surgeons"
    ],
    "wof:name":"Pedro M Abrantes Dpm",
    "wof:placetype":"venue"
},
  "geometry": {"coordinates":[-80.334199,25.702556],"type":"Point"}
}