{
  "type": "Feature",
  "properties": {
    "iso:country":"US",
    "sg:address":"2906 NE 14th St",
    "sg:city":"Ocala",
    "sg:classifiers":[
        {
            "category":"Insurance",
            "subcategory":"Insurance Agent",
            "type":"Services"
        }
    ],
    "sg:phone":"+1 352 622 2350",
    "sg:postcode":"34470",
    "sg:province":"FL",
    "sg:tags":[
        "motorcycle"
    ],
    "sg:website":"http://www.expressinsurancequote.com",
    "wof:name":"Express Insurance",
    "wof:placetype":"venue"
},
  "geometry": {"coordinates":[-82.09702299999999,29.200688],"type":"Point"}
}