{
  "type": "Feature",
  "properties": {
    "iso:country":"US",
    "sg:address":"4412 NW 74th Ave",
    "sg:city":"Miami",
    "sg:classifiers":[
        {
            "category":"Freight",
            "type":"Transportation"
        }
    ],
    "sg:phone":"+1 305 591 5969",
    "sg:postcode":"33166",
    "sg:province":"FL",
    "sg:tags":[
        "mail",
        "shipping",
        "agent",
        "direct"
    ],
    "sg:website":"www.abbulk.com",
    "wof:name":"A & B Bulk Mailers Inc",
    "wof:placetype":"venue"
},
  "geometry": {"coordinates":[-80.31731000000001,25.814365],"type":"Point"}
}