{
  "type": "Feature",
  "properties": {
    "iso:country":"US",
    "sg:address":"5629 Indiana Ave",
    "sg:city":"New Port Richey",
    "sg:classifiers":[
        {
            "category":"Building & Trades",
            "subcategory":"Landscaping Services",
            "type":"Services"
        }
    ],
    "sg:phone":"+1 727 842 3903",
    "sg:postcode":"34652",
    "sg:province":"FL",
    "sg:tags":[
        "landscape",
        "contractor"
    ],
    "wof:name":"Tna Environmental Inc",
    "wof:placetype":"venue"
},
  "geometry": {"coordinates":[-82.720972,28.253473],"type":"Point"}
}