{
  "type": "Feature",
  "properties": {
    "addr:full":"101 Lake Emma Cove Dr Lake Mary FL 32746",
    "addr:housenumber":"101",
    "addr:postcode":"32746",
    "addr:street":"Lake Emma Cove Dr",
    "iso:country":"US",
    "sg:address":"101 Lake Emma Cove Dr",
    "sg:city":"Lake Mary",
    "sg:classifiers":[
        {
            "category":"Professional",
            "subcategory":"Business Services",
            "type":"Services"
        }
    ],
    "sg:phone":"+1 407 531 1144",
    "sg:postcode":"32746",
    "sg:province":"FL",
    "wof:name":"Hilton Group Company",
    "wof:placetype":"venue"
},
  "geometry": {"coordinates":[-81.348033,28.758017],"type":"Point"}
}