{
  "type": "Feature",
  "properties": {
    "iso:country":"US",
    "sg:address":"612 Arnold Dr",
    "sg:city":"Daytona Beach",
    "sg:classifiers":[
        {
            "category":"Building & Trades",
            "subcategory":"Landscaping Services",
            "type":"Services"
        }
    ],
    "sg:phone":"+1 386 295 6968",
    "sg:postcode":"32114",
    "sg:province":"FL",
    "sg:tags":[
        "lawn",
        "maintenance",
        "grounds"
    ],
    "wof:name":"KDS Lawn Care",
    "wof:placetype":"venue"
},
  "geometry": {"coordinates":[-81.03623,29.182403],"type":"Point"}
}