{
  "type": "Feature",
  "properties": {
    "addr:full":"2677 W 76th St Hialeah FL 33016",
    "addr:housenumber":"2677",
    "addr:postcode":"33016",
    "addr:street":"W 76Th St",
    "iso:country":"US",
    "sg:address":"2677 W 76th St",
    "sg:city":"Hialeah",
    "sg:classifiers":[
        {
            "category":"Manufacturing",
            "subcategory":"Furniture",
            "type":"Manufacturing & Wholesale Goods"
        }
    ],
    "sg:phone":"+1 305 828 4780",
    "sg:postcode":"33016",
    "sg:province":"FL",
    "sg:tags":[
        "mfg"
    ],
    "wof:name":"Robaina Furniture",
    "wof:placetype":"venue"
},
  "geometry": {"coordinates":[-80.338565,25.891576],"type":"Point"}
}