{
  "type": "Feature",
  "properties": {
    "addr:full":"2441 S Byron Butler Pkwy Perry FL 32348",
    "addr:housenumber":"2441",
    "addr:postcode":"32348",
    "addr:street":"S Byron Butler Pkwy",
    "iso:country":"US",
    "sg:address":"2441 S Byron Butler Pkwy",
    "sg:city":"Perry",
    "sg:classifiers":[
        {
            "category":"Autos & Motor Vehicles",
            "subcategory":"Automobile Sales",
            "type":"Retail Goods"
        }
    ],
    "sg:phone":"+1 850 584 6178",
    "sg:postcode":"32348",
    "sg:province":"FL",
    "wof:name":"New Perry Ford-Mercury Inc",
    "wof:placetype":"venue"
},
  "geometry": {"coordinates":[-83.57613000000001,30.091102],"type":"Point"}
}