{
  "type": "Feature",
  "properties": {
    "iso:country":"US",
    "sg:address":"254 Ridgewood Dr",
    "sg:city":"Crawfordville",
    "sg:classifiers":[
        {
            "category":"Freight",
            "type":"Transportation"
        }
    ],
    "sg:phone":"+1 850 421 3396",
    "sg:postcode":"32327",
    "sg:province":"FL",
    "sg:tags":[
        "operator",
        "local",
        "trucking"
    ],
    "wof:name":"D&M Trucking",
    "wof:placetype":"venue"
},
  "geometry": {"coordinates":[-84.242373,30.25637],"type":"Point"}
}