{
  "type": "Feature",
  "properties": {
    "addr:full":"2939 Indian Creek Dr Miami Beach FL 33140",
    "addr:housenumber":"2939",
    "addr:postcode":"33140",
    "addr:street":"Indian Creek Dr",
    "iso:country":"US",
    "sg:address":"2939 Indian Creek Dr",
    "sg:city":"Miami Beach",
    "sg:classifiers":[
        {
            "category":"Professional",
            "type":"Services"
        }
    ],
    "sg:phone":"+1 305 672 9093",
    "sg:postcode":"33140",
    "sg:province":"FL",
    "sg:tags":[
        "establishment"
    ],
    "wof:name":"Beach Plaza South",
    "wof:placetype":"venue"
},
  "geometry": {"coordinates":[-80.126013,25.805982],"type":"Point"}
}