{
  "type": "Feature",
  "properties": {
    "addr:full":"7414 W Commercial Blvd Lauderhill FL 33319",
    "addr:housenumber":"7414",
    "addr:postcode":"33319",
    "addr:street":"W Commercial Blvd",
    "iso:country":"US",
    "sg:address":"7414 W Commercial Blvd",
    "sg:city":"Lauderhill",
    "sg:classifiers":[
        {
            "category":"Real Estate",
            "subcategory":"Real Estate Agent",
            "type":"Services"
        }
    ],
    "sg:phone":"+1 954 741 1550",
    "sg:postcode":"33319",
    "sg:province":"FL",
    "wof:name":"Kong, Maria - Markon Realty & Management Inc",
    "wof:placetype":"venue"
},
  "geometry": {"coordinates":[-80.250671,26.193703],"type":"Point"}
}