{
  "type": "Feature",
  "properties": {
    "iso:country":"US",
    "sg:address":"1540 Lyndale Blvd",
    "sg:city":"Maitland",
    "sg:classifiers":[
        {
            "category":"Professional",
            "subcategory":"Lawyer & Legal Services",
            "type":"Services"
        }
    ],
    "sg:phone":"+1 407 644 2403",
    "sg:postcode":"32751",
    "sg:province":"FL",
    "wof:name":"Charles R Harrison Atty",
    "wof:placetype":"venue"
},
  "geometry": {"coordinates":[-81.362267,28.614857],"type":"Point"}
}