{
  "type": "Feature",
  "properties": {
    "iso:country":"US",
    "sg:address":"114 W Bloomingdale Ave",
    "sg:city":"Brandon",
    "sg:classifiers":[
        {
            "category":"Insurance",
            "subcategory":"Insurance Agent",
            "type":"Services"
        }
    ],
    "sg:phone":"+1 813 653 1315",
    "sg:postcode":"33511",
    "sg:province":"FL",
    "wof:name":"Federated Mutual Insurance Co",
    "wof:placetype":"venue"
},
  "geometry": {"coordinates":[-82.28846900000001,27.893704],"type":"Point"}
}