{
  "type": "Feature",
  "properties": {
    "iso:country":"US",
    "sg:address":"5250 International Dr",
    "sg:city":"Orlando",
    "sg:classifiers":[
        {
            "category":"Shopping",
            "subcategory":"Clothing, Apparel, & Fashions",
            "type":"Retail Goods"
        }
    ],
    "sg:phone":"+1 407 351 4512",
    "sg:postcode":"32819",
    "sg:province":"FL",
    "sg:tags":[
        "swimwear",
        "accessory"
    ],
    "wof:name":"Swim Smart",
    "wof:placetype":"venue"
},
  "geometry": {"coordinates":[-81.450338,28.465159],"type":"Point"}
}