{
  "type": "Feature",
  "properties": {
    "iso:country":"US",
    "sg:address":"5542 SW 6th Pl",
    "sg:city":"Ocala",
    "sg:classifiers":[
        {
            "category":"Wholesale",
            "subcategory":"Medical Equipment & Supplies",
            "type":"Manufacturing & Wholesale Goods"
        }
    ],
    "sg:phone":"+1 352 237 9654",
    "sg:postcode":"34474",
    "sg:province":"FL",
    "wof:name":"Infolab Inc",
    "wof:placetype":"venue"
},
  "geometry": {"coordinates":[-82.21166100000001,29.180621],"type":"Point"}
}