{
  "type": "Feature",
  "properties": {
    "iso:country":"US",
    "sg:address":"4234 NW 65 Ter",
    "sg:city":"Gainesville",
    "sg:classifiers":[
        {
            "category":"Professional",
            "subcategory":"Business Services",
            "type":"Services"
        }
    ],
    "sg:phone":"+1 352 373 1776",
    "sg:postcode":"32606",
    "sg:province":"FL",
    "sg:tags":[
        "legal"
    ],
    "wof:name":"Peterson Marilyn W Atty At Lw",
    "wof:placetype":"venue"
},
  "geometry": {"coordinates":[-82.41243299999999,29.694465],"type":"Point"}
}