{
  "type": "Feature",
  "properties": {
    "addr:full":"131 1st Ave N Jacksonville Bch FL 32250",
    "addr:housenumber":"131",
    "addr:postcode":"32250",
    "addr:street":"1St Ave N",
    "iso:country":"US",
    "sg:address":"131 1st Ave N",
    "sg:city":"Jacksonville Bch",
    "sg:classifiers":[
        {
            "category":"Shopping",
            "subcategory":"Clothing, Apparel, & Fashions",
            "type":"Retail Goods"
        }
    ],
    "sg:phone":"+1 904 242 8133",
    "sg:postcode":"32250",
    "sg:province":"FL",
    "sg:tags":[
        "swimwear",
        "accessory"
    ],
    "wof:name":"Waves Surf Shop",
    "wof:placetype":"venue"
},
  "geometry": {"coordinates":[-81.3907,30.290325],"type":"Point"}
}