{
  "type": "Feature",
  "properties": {
    "iso:country":"US",
    "sg:address":"2170 N Dixie Hwy",
    "sg:city":"Boca Raton",
    "sg:classifiers":[
        {
            "category":"Shopping",
            "subcategory":"Bicycles & Sporting Goods",
            "type":"Retail Goods"
        }
    ],
    "sg:phone":"+1 561 416 9433",
    "sg:postcode":"33431",
    "sg:province":"FL",
    "wof:name":"Racer's Edge",
    "wof:placetype":"venue"
},
  "geometry": {"coordinates":[-80.084481,26.3698],"type":"Point"}
}