{
  "type": "Feature",
  "properties": {
    "addr:full":"328 N Ridgewood Ave Edgewater FL 32132",
    "addr:housenumber":"328",
    "addr:postcode":"32132",
    "addr:street":"N Ridgewood Ave",
    "iso:country":"US",
    "sg:address":"328 N Ridgewood Ave",
    "sg:city":"Edgewater",
    "sg:classifiers":[
        {
            "category":"Marine",
            "type":"Transportation"
        }
    ],
    "sg:phone":"+1 386 409 7340",
    "sg:postcode":"32132",
    "sg:province":"FL",
    "sg:tags":[
        "transporting",
        "boat"
    ],
    "wof:name":"Chock & Block Marine Inc",
    "wof:placetype":"venue"
},
  "geometry": {"coordinates":[-80.911142,28.99818],"type":"Point"}
}