{
  "type": "Feature",
  "properties": {
    "iso:country":"US",
    "sg:address":"17175 NW Gainesville Rd",
    "sg:city":"Reddick",
    "sg:classifiers":[
        {
            "category":"Manufacturing",
            "subcategory":"Motor Vehicles & Parts",
            "type":"Manufacturing & Wholesale Goods"
        }
    ],
    "sg:phone":"+1 352 591 2161",
    "sg:postcode":"32686",
    "sg:province":"FL",
    "sg:tags":[
        "boat",
        "trailer",
        "mfg"
    ],
    "wof:name":"B&S Trailer Mfg",
    "wof:placetype":"venue"
},
  "geometry": {"coordinates":[-82.206953,29.398656],"type":"Point"}
}