{
  "type": "Feature",
  "properties": {
    "iso:country":"US",
    "sg:address":"698 N Homestead Blvd",
    "sg:city":"Homestead",
    "sg:classifiers":[
        {
            "category":"Real Estate",
            "subcategory":"Real Estate Agent",
            "type":"Services"
        }
    ],
    "sg:phone":"+1 305 248 3588",
    "sg:postcode":"33030",
    "sg:province":"FL",
    "wof:name":"Chamber Centre Realty Inc",
    "wof:placetype":"venue"
},
  "geometry": {"coordinates":[-80.46764400000001,25.473754],"type":"Point"}
}