{
  "type": "Feature",
  "properties": {
    "addr:full":"4620 Bay Blvd Port Richey FL 34668",
    "addr:housenumber":"4620",
    "addr:postcode":"34668",
    "addr:street":"Bay Blvd",
    "iso:country":"US",
    "sg:address":"4620 Bay Blvd",
    "sg:city":"Port Richey",
    "sg:classifiers":[
        {
            "category":"Banks & Credit Unions",
            "subcategory":"Financial Services",
            "type":"Services"
        }
    ],
    "sg:phone":"+1 727 816 9131",
    "sg:postcode":"34668",
    "sg:province":"FL",
    "sg:tags":[
        "investor"
    ],
    "wof:name":"Joint Venture Investments Corp",
    "wof:placetype":"venue"
},
  "geometry": {"coordinates":[-82.736527,28.278183],"type":"Point"}
}