{
  "type": "Feature",
  "properties": {
    "addr:full":"413 S Macdill Ave Tampa FL 33609",
    "addr:housenumber":"413",
    "addr:postcode":"33609",
    "addr:street":"S Macdill Ave",
    "iso:country":"US",
    "sg:address":"413 S Macdill Ave",
    "sg:city":"Tampa",
    "sg:classifiers":[
        {
            "category":"Real Estate",
            "subcategory":"Real Estate Services",
            "type":"Services"
        }
    ],
    "sg:phone":"+1 813 879 0261",
    "sg:postcode":"33609",
    "sg:province":"FL",
    "sg:tags":[
        "company",
        "title"
    ],
    "wof:name":"Investors Title & Settlement",
    "wof:placetype":"venue"
},
  "geometry": {"coordinates":[-82.49341099999999,27.940051],"type":"Point"}
}