{
  "type": "Feature",
  "properties": {
    "iso:country":"US",
    "sg:address":"39 East Rd",
    "sg:city":"Delray Beach",
    "sg:classifiers":[
        {
            "category":"Shopping",
            "subcategory":"Used Merchandise",
            "type":"Retail Goods"
        }
    ],
    "sg:phone":"+1 561 265 2720",
    "sg:postcode":"33483",
    "sg:province":"FL",
    "wof:name":"Favorite Finds",
    "wof:placetype":"venue"
},
  "geometry": {"coordinates":[-80.06210299999999,26.462858],"type":"Point"}
}