{
  "type": "Feature",
  "properties": {
    "addr:full":"224 Palermo Ave Miami FL 33134",
    "addr:housenumber":"224",
    "addr:postcode":"33134",
    "addr:street":"Palermo Ave",
    "iso:country":"US",
    "sg:address":"224 Palermo Ave",
    "sg:city":"Miami",
    "sg:classifiers":[
        {
            "category":"Insurance",
            "subcategory":"Insurance Agent",
            "type":"Services"
        }
    ],
    "sg:phone":"+1 305 567 1032",
    "sg:postcode":"33134",
    "sg:province":"FL",
    "wof:name":"Ecpa Inc",
    "wof:placetype":"venue"
},
  "geometry": {"coordinates":[-80.26015200000001,25.745414],"type":"Point"}
}