{
  "type": "Feature",
  "properties": {
    "iso:country":"US",
    "sg:address":"5850 Retha Rd",
    "sg:city":"Jacksonville",
    "sg:classifiers":[
        {
            "category":"Manufacturing",
            "subcategory":"Building Materials",
            "type":"Manufacturing & Wholesale Goods"
        }
    ],
    "sg:phone":"+1 904 786 2697",
    "sg:postcode":"32254",
    "sg:province":"FL",
    "sg:tags":[
        "mfg",
        "wood",
        "kitchen",
        "cabinet"
    ],
    "wof:name":"Picketts Custom Cabinets",
    "wof:placetype":"venue"
},
  "geometry": {"coordinates":[-81.746039,30.364242],"type":"Point"}
}