{
  "type": "Feature",
  "properties": {
    "iso:country":"US",
    "sg:address":"801 Laurel Oak Dr #303",
    "sg:city":"Naples",
    "sg:classifiers":[
        {
            "category":"Professional",
            "subcategory":"Accounting & Tax Preparation",
            "type":"Services"
        }
    ],
    "sg:phone":"+1 888 675 3409",
    "sg:postcode":"34108",
    "sg:province":"FL",
    "sg:tags":[
        "bookkeeping",
        "payroll",
        "public",
        "accountants-certified"
    ],
    "sg:website":"http://www.swflcpas.com",
    "wof:name":"Phillips Harvey Group",
    "wof:placetype":"venue"
},
  "geometry": {"coordinates":[-81.80297899999999,26.21468],"type":"Point"}
}