{
  "type": "Feature",
  "properties": {
    "iso:country":"US",
    "sg:address":"277 SW 33rd St",
    "sg:city":"Fort Lauderdale",
    "sg:classifiers":[
        {
            "category":"Manufacturing",
            "subcategory":"Electronics",
            "type":"Manufacturing & Wholesale Goods"
        }
    ],
    "sg:phone":"+1 954 463 9003",
    "sg:postcode":"33315",
    "sg:province":"FL",
    "sg:tags":[
        "equipment",
        "mfg",
        "communications"
    ],
    "wof:name":"Iron-Link Communications Inc",
    "wof:placetype":"venue"
},
  "geometry": {"coordinates":[-80.144183,26.083522],"type":"Point"}
}