{
  "type": "Feature",
  "properties": {
    "iso:country":"US",
    "sg:address":"410 NE Waldo Rd",
    "sg:city":"Gainesville",
    "sg:classifiers":[
        {
            "category":"Health Services",
            "subcategory":"Hospital",
            "type":"Services"
        }
    ],
    "sg:phone":"+1 352 265 8000",
    "sg:postcode":"32609",
    "sg:province":"FL",
    "wof:name":"Shands Healthcare",
    "wof:placetype":"venue"
},
  "geometry": {"coordinates":[-82.311752,29.651684],"type":"Point"}
}