{
  "type": "Feature",
  "properties": {
    "addr:full":"4777 Silver Star Rd Orlando FL 32808",
    "addr:housenumber":"4777",
    "addr:postcode":"32808",
    "addr:street":"Silver Star Rd",
    "iso:country":"US",
    "sg:address":"4777 Silver Star Rd",
    "sg:city":"Orlando",
    "sg:classifiers":[
        {
            "category":"Organizations",
            "subcategory":"Religious Organization",
            "type":"Services"
        }
    ],
    "sg:phone":"+1 407 299 3911",
    "sg:postcode":"32808",
    "sg:province":"FL",
    "sg:tags":[
        "church"
    ],
    "wof:name":"Miracle Tabernacle Full Gospel",
    "wof:placetype":"venue"
},
  "geometry": {"coordinates":[-81.444605,28.577921],"type":"Point"}
}