{
  "type": "Feature",
  "properties": {
    "addr:full":"3002 E 7th Ave Tampa FL 33605",
    "addr:housenumber":"3002",
    "addr:postcode":"33605",
    "addr:street":"E 7Th Ave",
    "iso:country":"US",
    "sg:address":"3002 E 7th Ave",
    "sg:city":"Tampa",
    "sg:classifiers":[
        {
            "category":"Wholesale",
            "subcategory":"Farm Supplies",
            "type":"Manufacturing & Wholesale Goods"
        },
        {
            "category":"Freight",
            "type":"Transportation"
        }
    ],
    "sg:phone":"+1 813 241 4711",
    "sg:postcode":"33605",
    "sg:province":"FL",
    "sg:tags":[
        "feed",
        "product",
        "warehousing"
    ],
    "wof:name":"Jim Dandy Feed & Supply Co",
    "wof:placetype":"venue"
},
  "geometry": {"coordinates":[-82.425321,27.960298],"type":"Point"}
}