{
  "type": "Feature",
  "properties": {
    "iso:country":"US",
    "sg:address":"9755 SW 40th Ter",
    "sg:city":"Miami",
    "sg:classifiers":[
        {
            "category":"Professional",
            "subcategory":"Lawyer & Legal Services",
            "type":"Services"
        }
    ],
    "sg:phone":"+1 305 223 9999",
    "sg:postcode":"33165",
    "sg:province":"FL",
    "wof:name":"Gonzalez Alexis Law Office of",
    "wof:placetype":"venue"
},
  "geometry": {"coordinates":[-80.353419,25.731884],"type":"Point"}
}