{
  "type": "Feature",
  "properties": {
    "addr:full":"5706 Haines Rd N St Petersburg FL 33714",
    "addr:housenumber":"5706",
    "addr:postcode":"33714",
    "addr:street":"Haines Rd N",
    "iso:country":"US",
    "sg:address":"5706 Haines Rd N",
    "sg:city":"St Petersburg",
    "sg:classifiers":[
        {
            "category":"Autos & Motor Vehicles",
            "subcategory":"Automobile Sales",
            "type":"Retail Goods"
        }
    ],
    "sg:phone":"+1 727 525 2411",
    "sg:postcode":"33714",
    "sg:province":"FL",
    "sg:tags":[
        "car",
        "used",
        "dealer"
    ],
    "wof:name":"Ashley Auto Sales Inc",
    "wof:placetype":"venue"
},
  "geometry": {"coordinates":[-82.671784,27.824197],"type":"Point"}
}