{
  "type": "Feature",
  "properties": {
    "iso:country":"US",
    "sg:address":"2110 State Road 66",
    "sg:city":"Sebring",
    "sg:classifiers":[
        {
            "category":"Shopping",
            "subcategory":"Pets & Pet Supplies",
            "type":"Retail Goods"
        },
        {
            "category":"Retail",
            "subcategory":"Veterinary Services",
            "type":"Services"
        }
    ],
    "sg:phone":"+1 863 382 1394",
    "sg:postcode":"33875",
    "sg:province":"FL",
    "sg:tags":[
        "specialty"
    ],
    "wof:name":"Pe Paws Fix It Shop",
    "wof:placetype":"venue"
},
  "geometry": {"coordinates":[-81.42539600000001,27.427855],"type":"Point"}
}