{
  "type": "Feature",
  "properties": {
    "iso:country":"US",
    "sg:address":"5116 S Lakeland Dr",
    "sg:city":"Lakeland",
    "sg:classifiers":[
        {
            "category":"Professional",
            "subcategory":"Lawyer & Legal Services",
            "type":"Services"
        }
    ],
    "sg:phone":"+1 863 619 7330",
    "sg:postcode":"33813",
    "sg:province":"FL",
    "wof:name":"Dezayas Bruno F Atty",
    "wof:placetype":"venue"
},
  "geometry": {"coordinates":[-81.96331499999999,27.972869],"type":"Point"}
}