{
  "type": "Feature",
  "properties": {
    "addr:full":"526 S Forest Ave Apopka FL 32703",
    "addr:housenumber":"526",
    "addr:postcode":"32703",
    "addr:street":"S Forest Ave",
    "iso:country":"US",
    "sg:address":"526 S Forest Ave",
    "sg:city":"Apopka",
    "sg:classifiers":[
        {
            "category":"Retail",
            "subcategory":"Auto Repair",
            "type":"Services"
        }
    ],
    "sg:phone":"+1 407 814 9501",
    "sg:postcode":"32703",
    "sg:province":"FL",
    "sg:tags":[
        "body"
    ],
    "wof:name":"Singleton Motorsports",
    "wof:placetype":"venue"
},
  "geometry": {"coordinates":[-81.507535,28.671005],"type":"Point"}
}