{
  "type": "Feature",
  "properties": {
    "iso:country":"US",
    "sg:address":"906 Blountstown Hwy",
    "sg:city":"Tallahassee",
    "sg:classifiers":[
        {
            "category":"Personal",
            "type":"Services"
        },
        {
            "category":"Retail",
            "subcategory":"Car Wash",
            "type":"Services"
        },
        {
            "category":"Autos & Motor Vehicles",
            "subcategory":"Auto Supplies",
            "type":"Retail Goods"
        },
        {
            "category":"Retail",
            "subcategory":"Auto Repair",
            "type":"Services"
        }
    ],
    "sg:phone":"+1 850 575 2678",
    "sg:postcode":"32304",
    "sg:province":"FL",
    "sg:tags":[
        "body",
        "tire",
        "automobile",
        "detailing",
        "towing",
        "painting",
        "repairing"
    ],
    "wof:name":"Turn 4 Collision",
    "wof:placetype":"venue"
},
  "geometry": {"coordinates":[-84.346981,30.445404],"type":"Point"}
}