{
  "type": "Feature",
  "properties": {
    "iso:country":"US",
    "sg:address":"410 Stan Dr",
    "sg:city":"Melbourne",
    "sg:classifiers":[
        {
            "category":"Wholesale",
            "subcategory":"Electrical",
            "type":"Manufacturing & Wholesale Goods"
        },
        {
            "category":"Shopping",
            "subcategory":"Computers & Home Electronics",
            "type":"Retail Goods"
        }
    ],
    "sg:phone":"+1 321 676 3711",
    "sg:postcode":"32904",
    "sg:province":"FL",
    "sg:tags":[
        "supply",
        "rep",
        "mfg",
        "equipment",
        "distributor",
        "electronic",
        "tool"
    ],
    "wof:name":"Starboard Technology of Amer",
    "wof:placetype":"venue"
},
  "geometry": {"coordinates":[-80.69442600000001,28.102081],"type":"Point"}
}