{
  "type": "Feature",
  "properties": {
    "iso:country":"US",
    "sg:address":"16107 Wentworth Way",
    "sg:city":"Odessa",
    "sg:classifiers":[
        {
            "category":"Professional",
            "type":"Services"
        }
    ],
    "sg:phone":"+1 813 920 3991",
    "sg:postcode":"33556",
    "sg:province":"FL",
    "wof:name":"Gem Silver Inc",
    "wof:placetype":"venue"
},
  "geometry": {"coordinates":[-82.646737,28.099969],"type":"Point"}
}