{
  "type": "Feature",
  "properties": {
    "addr:full":"200 S Pine Island Rd Fort Lauderdale FL 33324",
    "addr:housenumber":"200",
    "addr:postcode":"33324",
    "addr:street":"S Pine Island Rd",
    "iso:country":"US",
    "sg:address":"200 S Pine Island Rd",
    "sg:city":"Fort Lauderdale",
    "sg:classifiers":[
        {
            "category":"Banks & Credit Unions",
            "subcategory":"Bank",
            "type":"Services"
        }
    ],
    "sg:phone":"+1 954 370 5522",
    "sg:postcode":"33324",
    "sg:province":"FL",
    "sg:tags":[
        "federal",
        "savings",
        "institution"
    ],
    "wof:name":"Washington Mutual",
    "wof:placetype":"venue"
},
  "geometry": {"coordinates":[-80.262528,26.116749],"type":"Point"}
}