{
  "type": "Feature",
  "properties": {
    "iso:country":"US",
    "sg:address":"1397 Majesty Ter",
    "sg:city":"Fort Lauderdale",
    "sg:classifiers":[
        {
            "category":"Health Services",
            "subcategory":"Doctor",
            "type":"Services"
        }
    ],
    "sg:phone":"+1 954 217 2960",
    "sg:postcode":"33327",
    "sg:province":"FL",
    "sg:tags":[
        "medical"
    ],
    "wof:name":"Stratus Svc Grp Inc",
    "wof:placetype":"venue"
},
  "geometry": {"coordinates":[-80.435025,26.120207],"type":"Point"}
}