{
  "type": "Feature",
  "properties": {
    "iso:country":"US",
    "sg:address":"1370 Bedford Dr",
    "sg:city":"Melbourne",
    "sg:classifiers":[
        {
            "category":"Professional",
            "type":"Services"
        }
    ],
    "sg:phone":"+1 321 757 6321",
    "sg:postcode":"32940",
    "sg:province":"FL",
    "sg:tags":[
        "establishment"
    ],
    "wof:name":"Owens Center For Biofeedback",
    "wof:placetype":"venue"
},
  "geometry": {"coordinates":[-80.70282,28.229546],"type":"Point"}
}