{
  "type": "Feature",
  "properties": {
    "iso:country":"US",
    "sg:address":"7960 US Hwy 1",
    "sg:city":"Sebastian",
    "sg:classifiers":[
        {
            "category":"Food & Beverages",
            "subcategory":"Groceries & Convenience Stores",
            "type":"Retail Goods"
        }
    ],
    "sg:phone":"+1 772 663 0835",
    "sg:postcode":"32976",
    "sg:province":"FL",
    "sg:tags":[
        "grocer"
    ],
    "sg:website":"www.winndixie.com",
    "wof:name":"Winn-Dixie",
    "wof:placetype":"venue"
},
  "geometry": {"coordinates":[-80.50208600000001,27.88183],"type":"Point"}
}