{
  "type": "Feature",
  "properties": {
    "addr:full":"20561 Powell Rd Dunnellon FL 34431",
    "addr:housenumber":"20561",
    "addr:postcode":"34431",
    "addr:street":"Powell Rd",
    "iso:country":"US",
    "sg:address":"20561 Powell Rd",
    "sg:city":"Dunnellon",
    "sg:classifiers":[
        {
            "category":"Shopping",
            "subcategory":"Jewelry",
            "type":"Retail Goods"
        }
    ],
    "sg:phone":"+1 352 489 8525",
    "sg:postcode":"34431",
    "sg:province":"FL",
    "sg:tags":[
        "designer"
    ],
    "wof:name":"Tangles Jewlery & Tanning",
    "wof:placetype":"venue"
},
  "geometry": {"coordinates":[-82.459959,29.054255],"type":"Point"}
}