{
  "type": "Feature",
  "properties": {
    "iso:country":"US",
    "sg:address":"2888 Ringling Blvd",
    "sg:city":"Sarasota",
    "sg:classifiers":[
        {
            "category":"Social Services",
            "type":"Services"
        }
    ],
    "sg:phone":"+1 941 556 1600",
    "sg:postcode":"34237",
    "sg:province":"FL",
    "sg:tags":[
        "info",
        "program",
        "referral"
    ],
    "wof:name":"Child Care Connection-Sarasota",
    "wof:placetype":"venue"
},
  "geometry": {"coordinates":[-82.511516,27.336387],"type":"Point"}
}