{
  "type": "Feature",
  "properties": {
    "addr:full":"9531 US Hwy 90 Milton FL 32583",
    "addr:housenumber":"9531",
    "addr:postcode":"32583",
    "addr:street":"Us Hwy 90",
    "iso:country":"US",
    "sg:address":"9531 US Hwy 90",
    "sg:city":"Milton",
    "sg:classifiers":[
        {
            "category":"Shopping",
            "subcategory":"Gifts & Souvenirs",
            "type":"Retail Goods"
        }
    ],
    "sg:phone":"+1 850 626 2535",
    "sg:postcode":"32583",
    "sg:province":"FL",
    "wof:name":"James Gifts",
    "wof:placetype":"venue"
},
  "geometry": {"coordinates":[-86.927134,30.645134],"type":"Point"}
}