{
  "type": "Feature",
  "properties": {
    "addr:full":"2631 Jammes Rd Jacksonville FL 32210",
    "addr:housenumber":"2631",
    "addr:postcode":"32210",
    "addr:street":"Jammes Rd",
    "iso:country":"US",
    "sg:address":"2631 Jammes Rd",
    "sg:city":"Jacksonville",
    "sg:classifiers":[
        {
            "category":"Insurance",
            "subcategory":"Insurance Agent",
            "type":"Services"
        }
    ],
    "sg:phone":"+1 904 779 2777",
    "sg:postcode":"32210",
    "sg:province":"FL",
    "sg:tags":[
        "agency"
    ],
    "wof:name":"Armor Insurance Agency",
    "wof:placetype":"venue"
},
  "geometry": {"coordinates":[-81.747496,30.270268],"type":"Point"}
}