{
  "type": "Feature",
  "properties": {
    "addr:full":"2290 Heritage Cir Gulf Breeze FL 32566",
    "addr:housenumber":"2290",
    "addr:postcode":"32566",
    "addr:street":"Heritage Cir",
    "iso:country":"US",
    "sg:address":"2290 Heritage Cir",
    "sg:city":"Gulf Breeze",
    "sg:classifiers":[
        {
            "category":"Professional",
            "subcategory":"Art Services",
            "type":"Services"
        }
    ],
    "sg:phone":"+1 850 939 0310",
    "sg:postcode":"32566",
    "sg:province":"FL",
    "sg:tags":[
        "commercial",
        "design"
    ],
    "wof:name":"Protoscope Inc",
    "wof:placetype":"venue"
},
  "geometry": {"coordinates":[-86.821884,30.416618],"type":"Point"}
}