{
  "type": "Feature",
  "properties": {
    "iso:country":"US",
    "sg:address":"1447 Alton Rd",
    "sg:city":"Miami Beach",
    "sg:classifiers":[
        {
            "category":"Building & Trades",
            "subcategory":"Locksmith",
            "type":"Services"
        }
    ],
    "sg:phone":"+1 786 228 5650",
    "sg:postcode":"33139",
    "sg:province":"FL",
    "sg:tags":[
        "key"
    ],
    "wof:name":"Anywhere Locksmith Service On Alton Rd",
    "wof:placetype":"venue"
},
  "geometry": {"coordinates":[-80.14118000000001,25.787195],"type":"Point"}
}