{
  "type": "Feature",
  "properties": {
    "iso:country":"US",
    "sg:address":"751 Harvey St",
    "sg:city":"Englewood",
    "sg:classifiers":[
        {
            "category":"Manufacturing",
            "subcategory":"Watercraft",
            "type":"Manufacturing & Wholesale Goods"
        }
    ],
    "sg:phone":"+1 941 474 1708",
    "sg:postcode":"34223",
    "sg:province":"FL",
    "wof:name":"Dale L Harvey",
    "wof:placetype":"venue"
},
  "geometry": {"coordinates":[-82.348099,26.948801],"type":"Point"}
}