{
  "type": "Feature",
  "properties": {
    "addr:full":"1220 Willis Ave Daytona Beach FL 32114",
    "addr:housenumber":"1220",
    "addr:postcode":"32114",
    "addr:street":"Willis Ave",
    "iso:country":"US",
    "sg:address":"1220 Willis Ave",
    "sg:city":"Daytona Beach",
    "sg:classifiers":[
        {
            "category":"Health Services",
            "subcategory":"Nursing And Care Facility",
            "type":"Services"
        }
    ],
    "sg:phone":"+1 386 947 4200",
    "sg:postcode":"32114",
    "sg:province":"FL",
    "sg:tags":[
        "residential",
        "intermediate"
    ],
    "wof:name":"Hinegrove Hospital",
    "wof:placetype":"venue"
},
  "geometry": {"coordinates":[-81.051181,29.206654],"type":"Point"}
}