{
  "type": "Feature",
  "properties": {
    "iso:country":"US",
    "sg:address":"29450 US Hwy 19",
    "sg:city":"Clearwater",
    "sg:classifiers":[
        {
            "category":"Wholesale",
            "subcategory":"Electrical",
            "type":"Manufacturing & Wholesale Goods"
        }
    ],
    "sg:phone":"+1 727 781 6600",
    "sg:postcode":"33761",
    "sg:province":"FL",
    "sg:tags":[
        "equipment"
    ],
    "wof:name":"City Electric Supply Co",
    "wof:placetype":"venue"
},
  "geometry": {"coordinates":[-82.738247,28.038472],"type":"Point"}
}