{
  "type": "Feature",
  "properties": {
    "iso:country":"US",
    "sg:address":"565 Fairbanks Ave",
    "sg:city":"Winter Park",
    "sg:classifiers":[
        {
            "category":"Restaurant",
            "type":"Food & Drink"
        }
    ],
    "sg:phone":"+1 407 513 4815",
    "sg:postcode":"32789",
    "sg:province":"FL",
    "sg:tags":[
        "traditional",
        "american"
    ],
    "sg:website":"www.facebook.com/pages/Winter-Pa...",
    "wof:name":"Boathouse",
    "wof:placetype":"venue"
},
  "geometry": {"coordinates":[-81.356149,28.593414],"type":"Point"}
}