{
  "type": "Feature",
  "properties": {
    "iso:country":"US",
    "sg:address":"231 State Ave",
    "sg:city":"Daytona Beach",
    "sg:classifiers":[
        {
            "category":"Arts & Performance",
            "subcategory":"Theater",
            "type":"Entertainment"
        }
    ],
    "sg:phone":"+1 386 239 0032",
    "sg:postcode":"32117",
    "sg:province":"FL",
    "sg:tags":[
        "live",
        "music"
    ],
    "wof:name":"Raulerson DJ Svc",
    "wof:placetype":"venue"
},
  "geometry": {"coordinates":[-81.033799,29.229168],"type":"Point"}
}