{
  "type": "Feature",
  "properties": {
    "addr:full":"164 Day Dr Sebastian FL 32958",
    "addr:housenumber":"164",
    "addr:postcode":"32958",
    "addr:street":"Day Dr",
    "iso:country":"US",
    "sg:address":"164 Day Dr",
    "sg:city":"Sebastian",
    "sg:classifiers":[
        {
            "category":"Professional",
            "subcategory":"Computer Services",
            "type":"Services"
        }
    ],
    "sg:phone":"+1 772 589 4591",
    "sg:postcode":"32958",
    "sg:province":"FL",
    "sg:tags":[
        "networking",
        "dist",
        "form"
    ],
    "sg:website":"www.precision-art.com",
    "wof:name":"Precision Art",
    "wof:placetype":"venue"
},
  "geometry": {"coordinates":[-80.462665,27.766195],"type":"Point"}
}