{
  "type": "Feature",
  "properties": {
    "addr:full":"6830 Central Ave Saint Petersburg FL 33707",
    "addr:housenumber":"6830",
    "addr:postcode":"33707",
    "addr:street":"Central Ave",
    "iso:country":"US",
    "sg:address":"6830 Central Ave",
    "sg:city":"Saint Petersburg",
    "sg:classifiers":[
        {
            "category":"Insurance",
            "subcategory":"Insurance Agent",
            "type":"Services"
        }
    ],
    "sg:phone":"+1 727 343 8103",
    "sg:postcode":"33707",
    "sg:province":"FL",
    "wof:name":"Judy McCain",
    "wof:placetype":"venue"
},
  "geometry": {"coordinates":[-82.732119,27.770741],"type":"Point"}
}