{
  "type": "Feature",
  "properties": {
    "addr:full":"6662 Mission Club Blvd Orlando FL 32821",
    "addr:housenumber":"6662",
    "addr:postcode":"32821",
    "addr:street":"Mission Club Blvd",
    "iso:country":"US",
    "sg:address":"6662 Mission Club Blvd",
    "sg:city":"Orlando",
    "sg:classifiers":[
        {
            "category":"Travel",
            "subcategory":"Hotels & Motels",
            "type":"Entertainment"
        }
    ],
    "sg:phone":"+1 407 238 0801",
    "sg:postcode":"32821",
    "sg:province":"FL",
    "wof:name":"Temporary VIP Suites",
    "wof:placetype":"venue"
},
  "geometry": {"coordinates":[-81.471419,28.387215],"type":"Point"}
}