{
  "type": "Feature",
  "properties": {
    "iso:country":"US",
    "sg:address":"1990 Michigan Ave",
    "sg:city":"Cocoa",
    "sg:classifiers":[
        {
            "category":"Restaurant",
            "type":"Food & Drink"
        }
    ],
    "sg:menulink":"http://www.allmenus.com/fl/cocoa-rockledge/81972-dominos-pizza/menu/",
    "sg:phone":"+1 321 636 4311",
    "sg:postcode":"32922",
    "sg:province":"FL",
    "sg:tags":[
        "american",
        "wing",
        "pizza"
    ],
    "wof:name":"Domino's Pizza",
    "wof:placetype":"venue"
},
  "geometry": {"coordinates":[-80.754453,28.388376],"type":"Point"}
}