{
  "type": "Feature",
  "properties": {
    "addr:full":"1675 94th Dr Vero Beach FL 32966",
    "addr:housenumber":"1675",
    "addr:postcode":"32966",
    "addr:street":"94Th Dr",
    "iso:country":"US",
    "sg:address":"1675 94th Dr",
    "sg:city":"Vero Beach",
    "sg:classifiers":[
        {
            "category":"Shopping",
            "subcategory":"Department Store",
            "type":"Retail Goods"
        }
    ],
    "sg:phone":"+1 772 778 1832",
    "sg:postcode":"32966",
    "sg:province":"FL",
    "sg:tags":[
        "shop"
    ],
    "wof:name":"Beall's Outlet",
    "wof:placetype":"venue"
},
  "geometry": {"coordinates":[-80.52213399999999,27.636145],"type":"Point"}
}