{
  "type": "Feature",
  "properties": {
    "addr:full":"458 Gus Hipp Blvd Rockledge FL 32955",
    "addr:housenumber":"458",
    "addr:postcode":"32955",
    "addr:street":"Gus Hipp Blvd",
    "iso:country":"US",
    "sg:address":"458 Gus Hipp Blvd",
    "sg:city":"Rockledge",
    "sg:classifiers":[
        {
            "category":"Manufacturing",
            "subcategory":"Toys & Sporting Goods",
            "type":"Manufacturing & Wholesale Goods"
        }
    ],
    "sg:phone":"+1 321 632 6503",
    "sg:postcode":"32955",
    "sg:province":"FL",
    "sg:tags":[
        "sailboard",
        "fin",
        "surfboard",
        "mfg"
    ],
    "wof:name":"Hyperform Inc",
    "wof:placetype":"venue"
},
  "geometry": {"coordinates":[-80.717135,28.304185],"type":"Point"}
}