{
  "type": "Feature",
  "properties": {
    "iso:country":"US",
    "sg:address":"595 W Church St",
    "sg:city":"Orlando",
    "sg:classifiers":[
        {
            "category":"Restaurant",
            "type":"Food & Drink"
        }
    ],
    "sg:menulink":"http://www.allmenus.com/fl/orlando/58961-johnsons-diner/menu/",
    "sg:phone":"+1 407 841 0717",
    "sg:postcode":"32805",
    "sg:province":"FL",
    "sg:tags":[
        "american"
    ],
    "wof:name":"Johnson's Diner",
    "wof:placetype":"venue"
},
  "geometry": {"coordinates":[-81.386194,28.540651],"type":"Point"}
}