{
  "type": "Feature",
  "properties": {
    "iso:country":"US",
    "sg:address":"810 SE 10th Ct",
    "sg:city":"Cape Coral",
    "sg:classifiers":[
        {
            "category":"Social Services",
            "subcategory":"Job Training",
            "type":"Services"
        }
    ],
    "sg:phone":"+1 239 574 1153",
    "sg:postcode":"33990",
    "sg:province":"FL",
    "sg:tags":[
        "rehabilitation"
    ],
    "wof:name":"United Cerebral Palsy",
    "wof:placetype":"venue"
},
  "geometry": {"coordinates":[-81.954228,26.636262],"type":"Point"}
}