{
  "type": "Feature",
  "properties": {
    "iso:country":"US",
    "sg:address":"10001 N Wickham Rd",
    "sg:city":"Melbourne",
    "sg:classifiers":[
        {
            "category":"Professional",
            "type":"Services"
        }
    ],
    "sg:phone":"+1 321 757 6945",
    "sg:postcode":"32940",
    "sg:province":"FL",
    "sg:tags":[
        "agency",
        "government"
    ],
    "wof:name":"National Oceanic & Atmospheric",
    "wof:placetype":"venue"
},
  "geometry": {"coordinates":[-80.725443,28.229937],"type":"Point"}
}