{
  "type": "Feature",
  "properties": {
    "addr:full":"7530 Merrill Rd Jacksonville FL 32277",
    "addr:housenumber":"7530",
    "addr:postcode":"32277",
    "addr:street":"Merrill Rd",
    "iso:country":"US",
    "sg:address":"7530 Merrill Rd",
    "sg:city":"Jacksonville",
    "sg:classifiers":[
        {
            "category":"Retail",
            "subcategory":"Veterinary Services",
            "type":"Services"
        }
    ],
    "sg:phone":"+1 904 744 7206",
    "sg:postcode":"32277",
    "sg:province":"FL",
    "sg:tags":[
        "clinic",
        "veterinarian",
        "hospital"
    ],
    "sg:website":"http://www.merrillanimalclinic.com",
    "wof:name":"Merrill Animal Clinic",
    "wof:placetype":"venue"
},
  "geometry": {"coordinates":[-81.57129500000001,30.352132],"type":"Point"}
}