{
  "type": "Feature",
  "properties": {
    "addr:full":"753 SW River Ct Palm City FL 34990",
    "addr:housenumber":"753",
    "addr:postcode":"34990",
    "addr:street":"Sw River Ct",
    "iso:country":"US",
    "sg:address":"753 SW River Ct",
    "sg:city":"Palm City",
    "sg:classifiers":[
        {
            "category":"Retail",
            "subcategory":"Repair Shop",
            "type":"Services"
        }
    ],
    "sg:phone":"+1 772 486 2554",
    "sg:postcode":"34990",
    "sg:province":"FL",
    "sg:tags":[
        "appliance"
    ],
    "wof:name":"Blair's Appliance Repair Inc",
    "wof:placetype":"venue"
},
  "geometry": {"coordinates":[-80.2902,27.196513],"type":"Point"}
}