{
  "type": "Feature",
  "properties": {
    "iso:country":"US",
    "sg:address":"6251 W Sample Rd",
    "sg:city":"Pompano Beach",
    "sg:classifiers":[
        {
            "category":"Utilities",
            "subcategory":"Mobile Phone",
            "type":"Services"
        }
    ],
    "sg:phone":"+1 954 796 8370",
    "sg:postcode":"33064",
    "sg:province":"FL",
    "wof:name":"Cingular Wireless",
    "wof:placetype":"venue"
},
  "geometry": {"coordinates":[-80.210427,26.274036],"type":"Point"}
}