{
  "type": "Feature",
  "properties": {
    "addr:full":"10741 Endeavor Way Ste C Seminole FL 33777",
    "addr:housenumber":"10741",
    "addr:postcode":"33777",
    "addr:street":"Endeavor Way Ste C",
    "iso:country":"US",
    "sg:address":"10741 Endeavor Way Ste C",
    "sg:city":"Seminole",
    "sg:classifiers":[
        {
            "category":"Professional",
            "subcategory":"Art Services",
            "type":"Services"
        }
    ],
    "sg:phone":"+1 727 545 4477",
    "sg:postcode":"33777",
    "sg:province":"FL",
    "sg:tags":[
        "interior",
        "designer",
        "decorator"
    ],
    "sg:website":"http://designerspecialties.com",
    "wof:name":"Designer Specialties",
    "wof:placetype":"venue"
},
  "geometry": {"coordinates":[-82.73506,27.868805],"type":"Point"}
}