{
  "type": "Feature",
  "properties": {
    "iso:country":"US",
    "sg:address":"2164 W 1st St Ste B",
    "sg:city":"Fort Myers",
    "sg:classifiers":[
        {
            "category":"Real Estate",
            "subcategory":"Real Estate Services",
            "type":"Services"
        }
    ],
    "sg:phone":"+1 239 332 3988",
    "sg:postcode":"33901",
    "sg:province":"FL",
    "sg:website":"www.firststreetvillage.com",
    "wof:name":"First Street Village",
    "wof:placetype":"venue"
},
  "geometry": {"coordinates":[-81.87761399999999,26.638978],"type":"Point"}
}