{
  "type": "Feature",
  "properties": {
    "iso:country":"US",
    "sg:address":"109 NE 39th St",
    "sg:city":"Miami",
    "sg:classifiers":[
        {
            "category":"Manufacturing",
            "subcategory":"Metals",
            "type":"Manufacturing & Wholesale Goods"
        },
        {
            "category":"Wholesale",
            "subcategory":"Hardware",
            "type":"Manufacturing & Wholesale Goods"
        }
    ],
    "sg:phone":"+1 305 576 0022",
    "sg:postcode":"33137",
    "sg:province":"FL",
    "sg:tags":[
        "plumbing",
        "fixture",
        "supply"
    ],
    "wof:name":"Decorators Plumbing Inc",
    "wof:placetype":"venue"
},
  "geometry": {"coordinates":[-80.1925,25.812839],"type":"Point"}
}