{
  "type": "Feature",
  "properties": {
    "addr:full":"1006 Ferndell Rd Orlando FL 32808",
    "addr:housenumber":"1006",
    "addr:postcode":"32808",
    "addr:street":"Ferndell Rd",
    "iso:country":"US",
    "sg:address":"1006 Ferndell Rd",
    "sg:city":"Orlando",
    "sg:classifiers":[
        {
            "category":"Education",
            "subcategory":"School",
            "type":"Public Place"
        }
    ],
    "sg:phone":"+1 407 296 6500",
    "sg:postcode":"32808",
    "sg:province":"FL",
    "sg:tags":[
        "executive"
    ],
    "wof:name":"Pine Hills Elementary School",
    "wof:placetype":"venue"
},
  "geometry": {"coordinates":[-81.455923,28.561595],"type":"Point"}
}