{
  "type": "Feature",
  "properties": {
    "addr:full":"7129 Hideaway Trl New Port Richey FL 34655",
    "addr:housenumber":"7129",
    "addr:postcode":"34655",
    "addr:street":"Hideaway Trl",
    "iso:country":"US",
    "sg:address":"7129 Hideaway Trl",
    "sg:city":"New Port Richey",
    "sg:classifiers":[
        {
            "category":"Insurance",
            "subcategory":"Insurance Agent",
            "type":"Services"
        }
    ],
    "sg:phone":"+1 727 372 3062",
    "sg:postcode":"34655",
    "sg:province":"FL",
    "wof:name":"Long Term Insurance Corp",
    "wof:placetype":"venue"
},
  "geometry": {"coordinates":[-82.69434099999999,28.190673],"type":"Point"}
}