{
  "type": "Feature",
  "properties": {
    "addr:full":"2600 Clearlake Rd Cocoa FL 32922",
    "addr:housenumber":"2600",
    "addr:postcode":"32922",
    "addr:street":"Clearlake Rd",
    "iso:country":"US",
    "sg:address":"2600 Clearlake Rd",
    "sg:city":"Cocoa",
    "sg:classifiers":[
        {
            "category":"Real Estate",
            "subcategory":"Real Estate Operator",
            "type":"Services"
        }
    ],
    "sg:phone":"+1 321 631 0851",
    "sg:postcode":"32922",
    "sg:province":"FL",
    "sg:tags":[
        "building",
        "apartment"
    ],
    "wof:name":"Clearlake Pines Apartments",
    "wof:placetype":"venue"
},
  "geometry": {"coordinates":[-80.754943,28.391957],"type":"Point"}
}