{
  "type": "Feature",
  "properties": {
    "addr:full":"5621 Harney Rd Tampa FL 33610",
    "addr:housenumber":"5621",
    "addr:postcode":"33610",
    "addr:street":"Harney Rd",
    "iso:country":"US",
    "sg:address":"5621 Harney Rd",
    "sg:city":"Tampa",
    "sg:classifiers":[
        {
            "category":"Organizations",
            "subcategory":"Labor Organization",
            "type":"Services"
        }
    ],
    "sg:phone":"+1 813 621 6451",
    "sg:postcode":"33610",
    "sg:province":"FL",
    "wof:name":"IBEW",
    "wof:placetype":"venue"
},
  "geometry": {"coordinates":[-82.393835,27.987349],"type":"Point"}
}