{
  "type": "Feature",
  "properties": {
    "addr:full":"3072 Watson Dr Marianna FL 32446",
    "addr:housenumber":"3072",
    "addr:postcode":"32446",
    "addr:street":"Watson Dr",
    "iso:country":"US",
    "sg:address":"3072 Watson Dr",
    "sg:city":"Marianna",
    "sg:classifiers":[
        {
            "category":"Autos & Motor Vehicles",
            "subcategory":"Automobile Sales",
            "type":"Retail Goods"
        }
    ],
    "sg:phone":"+1 850 482 3860",
    "sg:postcode":"32446",
    "sg:province":"FL",
    "sg:tags":[
        "sport",
        "trailer",
        "utility"
    ],
    "sg:website":"www.bobsvcs.com",
    "wof:name":"Bob Svc",
    "wof:placetype":"venue"
},
  "geometry": {"coordinates":[-85.22808999999999,30.789059],"type":"Point"}
}