{
  "type": "Feature",
  "properties": {
    "addr:full":"5300 E Adamo Dr Ste A Tampa FL 33619",
    "addr:housenumber":"5300",
    "addr:postcode":"33619",
    "addr:street":"E Adamo Dr Ste A",
    "iso:country":"US",
    "sg:address":"5300 E Adamo Dr Ste A",
    "sg:city":"Tampa",
    "sg:classifiers":[
        {
            "category":"Professional",
            "subcategory":"Business Services",
            "type":"Services"
        }
    ],
    "sg:phone":"+1 813 630 4820",
    "sg:postcode":"33619",
    "sg:province":"FL",
    "sg:tags":[
        "exporter"
    ],
    "wof:name":"L C Trading International",
    "wof:placetype":"venue"
},
  "geometry": {"coordinates":[-82.396332,27.952198],"type":"Point"}
}