{
  "type": "Feature",
  "properties": {
    "iso:country":"US",
    "sg:address":"1500 San Remo Ave Ste 205",
    "sg:city":"Coral Gables",
    "sg:classifiers":[
        {
            "category":"Health Services",
            "subcategory":"Doctor",
            "type":"Services"
        }
    ],
    "sg:phone":"+1 305 669 6800",
    "sg:postcode":"33146",
    "sg:province":"FL",
    "sg:tags":[
        "psychiatrist"
    ],
    "wof:name":"Gonzalez Carlos P MD",
    "wof:placetype":"venue"
},
  "geometry": {"coordinates":[-80.282303,25.705999],"type":"Point"}
}