{
  "type": "Feature",
  "properties": {
    "addr:full":"1210 Capital Cir SE Tallahassee FL 32301",
    "addr:housenumber":"1210",
    "addr:postcode":"32301",
    "addr:street":"Capital Cir Se",
    "iso:country":"US",
    "sg:address":"1210 Capital Cir SE",
    "sg:city":"Tallahassee",
    "sg:classifiers":[
        {
            "category":"Banks & Credit Unions",
            "subcategory":"Bank",
            "type":"Services"
        }
    ],
    "sg:phone":"+1 850 878 1190",
    "sg:postcode":"32301",
    "sg:province":"FL",
    "sg:tags":[
        "loan"
    ],
    "wof:name":"Equity One Inc",
    "wof:placetype":"venue"
},
  "geometry": {"coordinates":[-84.22685799999999,30.427667],"type":"Point"}
}