{
  "type": "Feature",
  "properties": {
    "iso:country":"US",
    "sg:address":"7485 NW 2nd Ave",
    "sg:city":"Miami",
    "sg:classifiers":[
        {
            "category":"Place Of Worship",
            "subcategory":"Church",
            "type":"Public Place"
        }
    ],
    "sg:phone":"+1 305 795 2000",
    "sg:postcode":"33150",
    "sg:province":"FL",
    "sg:website":"www.cathedralofsaintmary.com",
    "wof:name":"Cathederal of St. Mary",
    "wof:placetype":"venue"
},
  "geometry": {"coordinates":[-80.200791,25.843042],"type":"Point"}
}