{
  "type": "Feature",
  "properties": {
    "iso:country":"US",
    "sg:address":"34 Truth Cir",
    "sg:city":"Atmore",
    "sg:classifiers":[
        {
            "category":"Organizations",
            "subcategory":"Religious Organization",
            "type":"Services"
        }
    ],
    "sg:phone":"+1 251 368 1106",
    "sg:postcode":"36502",
    "sg:province":"FL",
    "wof:name":"House Of God Church",
    "wof:placetype":"venue"
},
  "geometry": {"coordinates":[-87.513904,31.072089],"type":"Point"}
}