{
  "type": "Feature",
  "properties": {
    "addr:full":"8338 Embassy Blvd Port Richey FL 34668",
    "addr:housenumber":"8338",
    "addr:postcode":"34668",
    "addr:street":"Embassy Blvd",
    "iso:country":"US",
    "sg:address":"8338 Embassy Blvd",
    "sg:city":"Port Richey",
    "sg:classifiers":[
        {
            "category":"Banks & Credit Unions",
            "subcategory":"Bank",
            "type":"Services"
        }
    ],
    "sg:phone":"+1 727 863 5823",
    "sg:postcode":"34668",
    "sg:province":"FL",
    "wof:name":"Bank Of America",
    "wof:placetype":"venue"
},
  "geometry": {"coordinates":[-82.67634,28.291572],"type":"Point"}
}