{
  "type": "Feature",
  "properties": {
    "iso:country":"US",
    "sg:address":"451 E Copans Rd",
    "sg:city":"Pompano Beach",
    "sg:classifiers":[
        {
            "category":"Shopping",
            "subcategory":"Used Merchandise",
            "type":"Retail Goods"
        }
    ],
    "sg:phone":"+1 954 782 3925",
    "sg:postcode":"33064",
    "sg:province":"FL",
    "wof:name":"Western Territorial Salvation",
    "wof:placetype":"venue"
},
  "geometry": {"coordinates":[-80.11668899999999,26.260233],"type":"Point"}
}