{
  "type": "Feature",
  "properties": {
    "iso:country":"US",
    "sg:address":"2698 NW 38th St",
    "sg:city":"Boca Raton",
    "sg:classifiers":[
        {
            "category":"Professional",
            "subcategory":"Business Services",
            "type":"Services"
        }
    ],
    "sg:phone":"+1 561 994 2721",
    "sg:postcode":"33434",
    "sg:province":"FL",
    "wof:name":"Fie Associates Inc",
    "wof:placetype":"venue"
},
  "geometry": {"coordinates":[-80.13833099999999,26.384158],"type":"Point"}
}