{
  "type": "Feature",
  "properties": {
    "addr:full":"9725 Bay Harbor Ter Bay Harbor Isles FL 33154",
    "addr:housenumber":"9725",
    "addr:postcode":"33154",
    "addr:street":"Bay;Ter Bay",
    "iso:country":"US",
    "sg:address":"9725 Bay Harbor Ter",
    "sg:city":"Bay Harbor Isles",
    "sg:classifiers":[
        {
            "category":"Shopping",
            "subcategory":"Catalog Store",
            "type":"Retail Goods"
        }
    ],
    "sg:phone":"+1 305 742 8929",
    "sg:postcode":"33154",
    "sg:province":"FL",
    "sg:tags":[
        "e"
    ],
    "sg:website":"www.aleph-net.com",
    "wof:name":"Aleph Net Corp",
    "wof:placetype":"venue"
},
  "geometry": {"coordinates":[-80.131277,25.888471],"type":"Point"}
}