{
  "type": "Feature",
  "properties": {
    "addr:full":"5647 Factory Shops Blvd Ellenton FL 34222",
    "addr:housenumber":"5647",
    "addr:postcode":"34222",
    "addr:street":"Factory Shops Blvd",
    "iso:country":"US",
    "sg:address":"5647 Factory Shops Blvd",
    "sg:city":"Ellenton",
    "sg:classifiers":[
        {
            "category":"Shopping",
            "subcategory":"Clothing, Apparel, & Fashions",
            "type":"Retail Goods"
        }
    ],
    "sg:phone":"+1 941 723 3676",
    "sg:postcode":"34222",
    "sg:province":"FL",
    "wof:name":"Casual Corner",
    "wof:placetype":"venue"
},
  "geometry": {"coordinates":[-82.505188,27.534133],"type":"Point"}
}