{
  "type": "Feature",
  "properties": {
    "addr:full":"1645 20th St Vero Beach FL 32960",
    "addr:housenumber":"1645",
    "addr:postcode":"32960",
    "addr:street":"20Th St",
    "iso:country":"US",
    "sg:address":"1645 20th St",
    "sg:city":"Vero Beach",
    "sg:classifiers":[
        {
            "category":"Shopping",
            "type":"Retail Goods"
        }
    ],
    "sg:phone":"+1 772 465 0588",
    "sg:postcode":"32960",
    "sg:province":"FL",
    "sg:tags":[
        "merchandise"
    ],
    "wof:name":"Bruce Buffington Cpo",
    "wof:placetype":"venue"
},
  "geometry": {"coordinates":[-80.40199200000001,27.638565],"type":"Point"}
}