{
  "type": "Feature",
  "properties": {
    "iso:country":"US",
    "sg:address":"2228 Winter Woods Blvd",
    "sg:city":"Winter Park",
    "sg:classifiers":[
        {
            "category":"Education",
            "subcategory":"Special Training",
            "type":"Public Place"
        }
    ],
    "sg:phone":"+1 407 678 4945",
    "sg:postcode":"32792",
    "sg:province":"FL",
    "sg:tags":[
        "tutoring"
    ],
    "sg:website":"www.wiseowltutoring.net",
    "wof:name":"Wise Owl Tutoring",
    "wof:placetype":"venue"
},
  "geometry": {"coordinates":[-81.315504,28.618323],"type":"Point"}
}