{
  "type": "Feature",
  "properties": {
    "addr:full":"310 SE 13th St Fort Lauderdale FL 33316",
    "addr:housenumber":"310",
    "addr:postcode":"33316",
    "addr:street":"Se 13Th St",
    "iso:country":"US",
    "sg:address":"310 SE 13th St",
    "sg:city":"Fort Lauderdale",
    "sg:classifiers":[
        {
            "category":"Professional",
            "subcategory":"Lawyer & Legal Services",
            "type":"Services"
        }
    ],
    "sg:phone":"+1 954 522 4433",
    "sg:postcode":"33316",
    "sg:province":"FL",
    "wof:name":"Allen G William Jr Attorney",
    "wof:placetype":"venue"
},
  "geometry": {"coordinates":[-80.13903999999999,26.106023],"type":"Point"}
}