{
  "type": "Feature",
  "properties": {
    "addr:full":"8240 SW 203rd St Miami FL 33189",
    "addr:housenumber":"8240",
    "addr:postcode":"33189",
    "addr:street":"Sw 203Rd St",
    "iso:country":"US",
    "sg:address":"8240 SW 203rd St",
    "sg:city":"Miami",
    "sg:classifiers":[
        {
            "category":"Manufacturing",
            "subcategory":"Watercraft",
            "type":"Manufacturing & Wholesale Goods"
        }
    ],
    "sg:phone":"+1 305 251 9463",
    "sg:postcode":"33189",
    "sg:province":"FL",
    "wof:name":"Archer International Inc",
    "wof:placetype":"venue"
},
  "geometry": {"coordinates":[-80.32311199999999,25.578481],"type":"Point"}
}