{
  "type": "Feature",
  "properties": {
    "iso:country":"US",
    "sg:address":"6523 SW 81 St",
    "sg:city":"Gainesville",
    "sg:classifiers":[
        {
            "category":"Professional",
            "type":"Services"
        }
    ],
    "sg:phone":"+1 352 395 6556",
    "sg:postcode":"32608",
    "sg:province":"FL",
    "wof:name":"US Biomedical Information",
    "wof:placetype":"venue"
},
  "geometry": {"coordinates":[-82.428814,29.592417],"type":"Point"}
}