{
  "type": "Feature",
  "properties": {
    "addr:full":"2816 Pinetree Dr Ste 3 Miami Beach FL 33140",
    "addr:housenumber":"2816",
    "addr:postcode":"33140",
    "addr:street":"Pinetree Dr Ste 3",
    "iso:country":"US",
    "sg:address":"2816 Pinetree Dr Ste 3",
    "sg:city":"Miami Beach",
    "sg:classifiers":[
        {
            "category":"Communications",
            "type":"Services"
        }
    ],
    "sg:phone":"+1 305 532 1752",
    "sg:postcode":"33140",
    "sg:province":"FL",
    "sg:tags":[
        "web",
        "design"
    ],
    "sg:website":"www.neneproductions.com",
    "wof:name":"Nene Productions",
    "wof:placetype":"venue"
},
  "geometry": {"coordinates":[-80.12818,25.804429],"type":"Point"}
}