{
  "type": "Feature",
  "properties": {
    "iso:country":"US",
    "sg:address":"101 Blossom Ln",
    "sg:city":"West Palm Beach",
    "sg:classifiers":[
        {
            "category":"Travel",
            "subcategory":"Hotels & Motels",
            "type":"Entertainment"
        }
    ],
    "sg:phone":"+1 561 844 6194",
    "sg:postcode":"33404",
    "sg:province":"FL",
    "wof:name":"Sunshine Shores Motel Apt",
    "wof:placetype":"venue"
},
  "geometry": {"coordinates":[-80.035282,26.779925],"type":"Point"}
}