{
  "type": "Feature",
  "properties": {
    "addr:full":"501 Village Green Pkwy Bradenton FL 34209",
    "addr:housenumber":"501",
    "addr:postcode":"34209",
    "addr:street":"Village Green Pkwy",
    "iso:country":"US",
    "sg:address":"501 Village Green Pkwy",
    "sg:city":"Bradenton",
    "sg:classifiers":[
        {
            "category":"Wholesale",
            "subcategory":"Medical Equipment & Supplies",
            "type":"Manufacturing & Wholesale Goods"
        },
        {
            "category":"Retail",
            "subcategory":"Repair Shop",
            "type":"Services"
        }
    ],
    "sg:phone":"+1 941 795 2811",
    "sg:postcode":"34209",
    "sg:province":"FL",
    "sg:tags":[
        "repairing",
        "aids-parts",
        "hearing",
        "device",
        "assistive",
        "aid"
    ],
    "sg:website":"http://www.kellyshearcare.com",
    "wof:name":"Kelly's Hear Care Centers",
    "wof:placetype":"venue"
},
  "geometry": {"coordinates":[-82.633247,27.49609],"type":"Point"}
}