{
  "type": "Feature",
  "properties": {
    "addr:full":"1399 Barineau Rd Tallahassee FL 32304",
    "addr:housenumber":"1399",
    "addr:postcode":"32304",
    "addr:street":"Barineau Rd",
    "iso:country":"US",
    "sg:address":"1399 Barineau Rd",
    "sg:city":"Tallahassee",
    "sg:classifiers":[
        {
            "category":"Real Estate",
            "subcategory":"Real Estate Agent",
            "type":"Services"
        }
    ],
    "sg:phone":"+1 850 576 0473",
    "sg:postcode":"32304",
    "sg:province":"FL",
    "wof:name":"Carolyn Harris",
    "wof:placetype":"venue"
},
  "geometry": {"coordinates":[-84.386625,30.441976],"type":"Point"}
}