{
  "type": "Feature",
  "properties": {
    "iso:country":"US",
    "sg:address":"999 Brickell Bay Dr",
    "sg:city":"Miami",
    "sg:classifiers":[
        {
            "category":"Professional",
            "subcategory":"Lawyer & Legal Services",
            "type":"Services"
        }
    ],
    "sg:phone":"+1 305 372 9400",
    "sg:postcode":"33131",
    "sg:province":"FL",
    "wof:name":"Marks Deborah",
    "wof:placetype":"venue"
},
  "geometry": {"coordinates":[-80.19000200000001,25.764],"type":"Point"}
}