{
  "type": "Feature",
  "properties": {
    "addr:full":"1672 S Congress Ave Lake Worth FL 33461",
    "addr:housenumber":"1672",
    "addr:postcode":"33461",
    "addr:street":"S Congress Ave",
    "iso:country":"US",
    "sg:address":"1672 S Congress Ave",
    "sg:city":"Lake Worth",
    "sg:classifiers":[
        {
            "category":"Restaurant",
            "type":"Food & Drink"
        }
    ],
    "sg:menulink":"http://www.allmenus.com/fl/lake-worth/82052-dominos-pizza/menu/",
    "sg:phone":"+1 561 965 3030",
    "sg:postcode":"33461",
    "sg:province":"FL",
    "sg:tags":[
        "american",
        "wing",
        "pizza"
    ],
    "wof:name":"Domino's Pizza",
    "wof:placetype":"venue"
},
  "geometry": {"coordinates":[-80.088269,26.637306],"type":"Point"}
}