{
  "type": "Feature",
  "properties": {
    "addr:full":"2300 NW 48th St Coconut Creek FL 33073",
    "addr:housenumber":"2300",
    "addr:postcode":"33073",
    "addr:street":"Nw 48Th St",
    "iso:country":"US",
    "sg:address":"2300 NW 48th St",
    "sg:city":"Coconut Creek",
    "sg:classifiers":[
        {
            "category":"Professional",
            "subcategory":"Credit Reporting & Collection",
            "type":"Services"
        }
    ],
    "sg:phone":"+1 954 984 9580",
    "sg:postcode":"33073",
    "sg:province":"FL",
    "sg:tags":[
        "agency"
    ],
    "wof:name":"A Absolute Recovery",
    "wof:placetype":"venue"
},
  "geometry": {"coordinates":[-80.156065,26.2889],"type":"Point"}
}