{
  "type": "Feature",
  "properties": {
    "addr:full":"1750 Croton Rd Melbourne FL 32935",
    "addr:housenumber":"1750",
    "addr:postcode":"32935",
    "addr:street":"Croton Rd",
    "iso:country":"US",
    "sg:address":"1750 Croton Rd",
    "sg:city":"Melbourne",
    "sg:classifiers":[
        {
            "category":"Banks & Credit Unions",
            "subcategory":"Bank",
            "type":"Services"
        }
    ],
    "sg:phone":"+1 321 253 1711",
    "sg:postcode":"32935",
    "sg:province":"FL",
    "sg:tags":[
        "loan",
        "real estate"
    ],
    "wof:name":"GMAC Mortgage Training",
    "wof:placetype":"venue"
},
  "geometry": {"coordinates":[-80.655125,28.135409],"type":"Point"}
}