{
  "type": "Feature",
  "properties": {
    "iso:country":"US",
    "sg:address":"2786 NW 79th Ave",
    "sg:city":"Miami",
    "sg:classifiers":[
        {
            "category":"Professional",
            "type":"Services"
        }
    ],
    "sg:phone":"+1 305 594 6505",
    "sg:postcode":"33122",
    "sg:province":"FL",
    "wof:name":"Etelcom Inc",
    "wof:placetype":"venue"
},
  "geometry": {"coordinates":[-80.32508199999999,25.798344],"type":"Point"}
}