{
  "type": "Feature",
  "properties": {
    "addr:full":"11228 NW 56th St Doral FL 33178",
    "addr:housenumber":"11228",
    "addr:postcode":"33178",
    "addr:street":"Nw 56Th St",
    "iso:country":"US",
    "sg:address":"11228 NW 56th St",
    "sg:city":"Doral",
    "sg:classifiers":[
        {
            "category":"Manufacturing",
            "subcategory":"Tools & Machinery",
            "type":"Manufacturing & Wholesale Goods"
        }
    ],
    "sg:phone":"+1 305 594 5747",
    "sg:postcode":"33178",
    "sg:province":"FL",
    "sg:tags":[
        "industry",
        "aerospace"
    ],
    "wof:name":"Orion Aerospace LLC",
    "wof:placetype":"venue"
},
  "geometry": {"coordinates":[-80.37929,25.824363],"type":"Point"}
}