{
  "type": "Feature",
  "properties": {
    "iso:country":"US",
    "sg:address":"1503 Montana Ave",
    "sg:city":"St Cloud",
    "sg:classifiers":[
        {
            "category":"Retail",
            "subcategory":"Auto Rental",
            "type":"Services"
        }
    ],
    "sg:phone":"+1 407 892 2388",
    "sg:postcode":"34769",
    "sg:province":"FL",
    "sg:tags":[
        "moving"
    ],
    "wof:name":"W & L Mini Storage",
    "wof:placetype":"venue"
},
  "geometry": {"coordinates":[-81.30029,28.24321],"type":"Point"}
}