{
  "type": "Feature",
  "properties": {
    "addr:full":"4138 Hanging Moss Ct Jacksonville FL 32257",
    "addr:housenumber":"4138",
    "addr:postcode":"32257",
    "addr:street":"Hanging Moss Ct",
    "iso:country":"US",
    "sg:address":"4138 Hanging Moss Ct",
    "sg:city":"Jacksonville",
    "sg:classifiers":[
        {
            "category":"Banks & Credit Unions",
            "subcategory":"Financial Services",
            "type":"Services"
        }
    ],
    "sg:phone":"+1 904 374 6758",
    "sg:postcode":"32257",
    "sg:province":"FL",
    "sg:tags":[
        "investment",
        "real estate"
    ],
    "wof:name":"Rikiese King",
    "wof:placetype":"venue"
},
  "geometry": {"coordinates":[-81.607615,30.193168],"type":"Point"}
}