{
  "type": "Feature",
  "properties": {
    "iso:country":"US",
    "sg:address":"2172 E Silver Springs Blvd",
    "sg:city":"Ocala",
    "sg:classifiers":[
        {
            "category":"Personal",
            "subcategory":"Beauty Salon",
            "type":"Services"
        }
    ],
    "sg:phone":"+1 352 629 5941",
    "sg:postcode":"34470",
    "sg:province":"FL",
    "sg:tags":[
        "shop"
    ],
    "wof:name":"Anthony's Hair Studio",
    "wof:placetype":"venue"
},
  "geometry": {"coordinates":[-82.11026200000001,29.18687],"type":"Point"}
}