{
  "type": "Feature",
  "properties": {
    "iso:country":"US",
    "sg:address":"5041 E Hinson Ave",
    "sg:city":"Haines City",
    "sg:classifiers":[
        {
            "category":"Wholesale",
            "subcategory":"Machinery & Supplies",
            "type":"Manufacturing & Wholesale Goods"
        }
    ],
    "sg:phone":"+1 863 421 6048",
    "sg:postcode":"33844",
    "sg:province":"FL",
    "sg:tags":[
        "tractor"
    ],
    "wof:name":"C & B Tractors & Equipment",
    "wof:placetype":"venue"
},
  "geometry": {"coordinates":[-81.58418399999999,28.106662],"type":"Point"}
}