{
  "type": "Feature",
  "properties": {
    "iso:country":"US",
    "sg:address":"10901 NW 83rd St",
    "sg:city":"Doral",
    "sg:classifiers":[
        {
            "category":"Building & Trades",
            "subcategory":"Construction",
            "type":"Services"
        }
    ],
    "sg:phone":"+1 305 887 1116",
    "sg:postcode":"33178",
    "sg:province":"FL",
    "sg:tags":[
        "contractor"
    ],
    "wof:name":"E B Developers Promenade",
    "wof:placetype":"venue"
},
  "geometry": {"coordinates":[-80.32869100000001,25.669101],"type":"Point"}
}