{
  "type": "Feature",
  "properties": {
    "iso:country":"US",
    "sg:address":"1353 N Courtenay Pkwy",
    "sg:city":"Merritt Island",
    "sg:classifiers":[
        {
            "category":"Insurance",
            "subcategory":"Insurance Agent",
            "type":"Services"
        }
    ],
    "sg:phone":"+1 321 452 8200",
    "sg:postcode":"32953",
    "sg:province":"FL",
    "wof:name":"G M Guill Ins & Investment Svc",
    "wof:placetype":"venue"
},
  "geometry": {"coordinates":[-80.70261499999999,28.380088],"type":"Point"}
}