{
  "type": "Feature",
  "properties": {
    "iso:country":"US",
    "sg:address":"1961 US Hwy 19",
    "sg:city":"Holiday",
    "sg:classifiers":[
        {
            "category":"Professional",
            "subcategory":"Computer Services",
            "type":"Services"
        }
    ],
    "sg:phone":"+1 727 934 5348",
    "sg:postcode":"34691",
    "sg:province":"FL",
    "sg:tags":[
        "reseller",
        "value"
    ],
    "wof:name":"Computronics Computer Corp",
    "wof:placetype":"venue"
},
  "geometry": {"coordinates":[-82.740212,28.185359],"type":"Point"}
}