{
  "type": "Feature",
  "properties": {
    "iso:country":"US",
    "sg:address":"3722 Grissom Ln",
    "sg:city":"Kissimmee",
    "sg:classifiers":[
        {
            "category":"Shopping",
            "subcategory":"Stationery & Office Supplies",
            "type":"Retail Goods"
        }
    ],
    "sg:phone":"+1 407 847 8899",
    "sg:postcode":"34741",
    "sg:province":"FL",
    "sg:website":"www.pattersonsofficesupply.com",
    "wof:name":"Patterson's Office Supply",
    "wof:placetype":"venue"
},
  "geometry": {"coordinates":[-81.44051399999999,28.302371],"type":"Point"}
}