{
  "type": "Feature",
  "properties": {
    "addr:full":"851 Casselberry Dr Lake Wales FL 33853",
    "addr:housenumber":"851",
    "addr:postcode":"33853",
    "addr:street":"Casselberry Dr",
    "iso:country":"US",
    "sg:address":"851 Casselberry Dr",
    "sg:city":"Lake Wales",
    "sg:classifiers":[
        {
            "category":"Personal",
            "type":"Services"
        }
    ],
    "sg:phone":"+1 863 676 6449",
    "sg:postcode":"33853",
    "sg:province":"FL",
    "wof:name":"Rec Enterprises Inc",
    "wof:placetype":"venue"
},
  "geometry": {"coordinates":[-81.58828200000001,27.888113],"type":"Point"}
}