{
  "type": "Feature",
  "properties": {
    "iso:country":"US",
    "sg:address":"37312 Howard Ave",
    "sg:city":"Dade City",
    "sg:classifiers":[
        {
            "category":"Government",
            "subcategory":"Police Station",
            "type":"Public Place"
        }
    ],
    "sg:phone":"+1 352 521 5101",
    "sg:postcode":"33525",
    "sg:province":"FL",
    "sg:tags":[
        "sheriff"
    ],
    "wof:name":"Pasco County Sheriff",
    "wof:placetype":"venue"
},
  "geometry": {"coordinates":[-82.19849600000001,28.361405],"type":"Point"}
}