{
  "type": "Feature",
  "properties": {
    "iso:country":"US",
    "sg:address":"1425 Tomoka Farms Rd",
    "sg:city":"Daytona Beach",
    "sg:classifiers":[
        {
            "category":"Manufacturing",
            "subcategory":"Leather Goods",
            "type":"Manufacturing & Wholesale Goods"
        }
    ],
    "sg:phone":"+1 386 255 9272",
    "sg:postcode":"32124",
    "sg:province":"FL",
    "sg:tags":[
        "mfg",
        "luggage"
    ],
    "wof:name":"Travelers Connection",
    "wof:placetype":"venue"
},
  "geometry": {"coordinates":[-81.083433,29.15407],"type":"Point"}
}