{
  "type": "Feature",
  "properties": {
    "iso:country":"US",
    "sg:address":"2755 SW 27th Ave",
    "sg:city":"Miami",
    "sg:classifiers":[
        {
            "category":"Personal",
            "subcategory":"Beauty Salon",
            "type":"Services"
        }
    ],
    "sg:phone":"+1 305 285 3282",
    "sg:postcode":"33133",
    "sg:province":"FL",
    "sg:tags":[
        "hair"
    ],
    "wof:name":"Lakshmi Aroma Therapy Spa & Salon",
    "wof:placetype":"venue"
},
  "geometry": {"coordinates":[-80.237701,25.740601],"type":"Point"}
}