{
  "type": "Feature",
  "properties": {
    "addr:full":"8602 SW 74th St Miami FL 33143",
    "addr:housenumber":"8602",
    "addr:postcode":"33143",
    "addr:street":"Sw 74Th St",
    "iso:country":"US",
    "sg:address":"8602 SW 74th St",
    "sg:city":"Miami",
    "sg:classifiers":[
        {
            "category":"Professional",
            "subcategory":"Accounting & Tax Preparation",
            "type":"Services"
        }
    ],
    "sg:phone":"+1 305 595 3739",
    "sg:postcode":"33143",
    "sg:province":"FL",
    "sg:tags":[
        "general",
        "architect",
        "contractor"
    ],
    "wof:name":"J C M Development Group Inc",
    "wof:placetype":"venue"
},
  "geometry": {"coordinates":[-80.331952,25.700717],"type":"Point"}
}