{
  "type": "Feature",
  "properties": {
    "iso:country":"US",
    "sg:address":"7700 N Kendall Dr",
    "sg:city":"Miami",
    "sg:classifiers":[
        {
            "category":"Organizations",
            "subcategory":"Community Association",
            "type":"Services"
        }
    ],
    "sg:phone":"+1 305 273 3744",
    "sg:postcode":"33156",
    "sg:province":"FL",
    "sg:tags":[
        "club"
    ],
    "sg:website":"http://www.madd.org",
    "wof:name":"Mothers Against Drunk Driving",
    "wof:placetype":"venue"
},
  "geometry": {"coordinates":[-80.319389,25.688398],"type":"Point"}
}