{
  "type": "Feature",
  "properties": {
    "iso:country":"US",
    "sg:address":"3540 SW 8th St",
    "sg:city":"Miami",
    "sg:classifiers":[
        {
            "category":"Health Services",
            "subcategory":"Doctor",
            "type":"Services"
        }
    ],
    "sg:phone":"+1 305 443 2840",
    "sg:postcode":"33135",
    "sg:province":"FL",
    "wof:name":"George Hector Morales MD",
    "wof:placetype":"venue"
},
  "geometry": {"coordinates":[-80.252489,25.764634],"type":"Point"}
}