{
  "type": "Feature",
  "properties": {
    "iso:country":"US",
    "sg:address":"1848 Wilbur Ave",
    "sg:city":"Vero Beach",
    "sg:classifiers":[
        {
            "category":"Retail",
            "subcategory":"Auto Repair",
            "type":"Services"
        }
    ],
    "sg:phone":"+1 772 567 1200",
    "sg:postcode":"32960",
    "sg:province":"FL",
    "sg:tags":[
        "shop",
        "automobile"
    ],
    "wof:name":"Joe Bouleys Auto Repair",
    "wof:placetype":"venue"
},
  "geometry": {"coordinates":[-80.3948,27.635827],"type":"Point"}
}