{
  "type": "Feature",
  "properties": {
    "addr:full":"6475 SW 39th St Miami FL 33155",
    "addr:housenumber":"6475",
    "addr:postcode":"33155",
    "addr:street":"Sw 39Th St",
    "iso:country":"US",
    "sg:address":"6475 SW 39th St",
    "sg:city":"Miami",
    "sg:classifiers":[
        {
            "category":"Home & Garden",
            "subcategory":"Building Materials",
            "type":"Retail Goods"
        }
    ],
    "sg:phone":"+1 305 662 7043",
    "sg:postcode":"33155",
    "sg:province":"FL",
    "wof:name":"Bills Concrete Pumping Inc",
    "wof:placetype":"venue"
},
  "geometry": {"coordinates":[-80.299503,25.735104],"type":"Point"}
}