{
  "type": "Feature",
  "properties": {
    "addr:full":"2171 Turkey Run Winter Park FL 32789",
    "addr:housenumber":"2171",
    "addr:postcode":"32789",
    "addr:street":"Turkey Run",
    "iso:country":"US",
    "sg:address":"2171 Turkey Run",
    "sg:city":"Winter Park",
    "sg:classifiers":[
        {
            "category":"Professional",
            "type":"Services"
        }
    ],
    "sg:phone":"+1 407 647 8210",
    "sg:postcode":"32789",
    "sg:province":"FL",
    "wof:name":"Blue Manatee Inc",
    "wof:placetype":"venue"
},
  "geometry": {"coordinates":[-81.343121,28.578157],"type":"Point"}
}