{
  "type": "Feature",
  "properties": {
    "iso:country":"US",
    "sg:address":"705 101st Ave N",
    "sg:city":"Naples",
    "sg:classifiers":[
        {
            "category":"Personal",
            "type":"Services"
        }
    ],
    "sg:phone":"+1 239 593 0104",
    "sg:postcode":"34108",
    "sg:province":"FL",
    "sg:tags":[
        "contractor"
    ],
    "wof:name":"Ace Painting",
    "wof:placetype":"venue"
},
  "geometry": {"coordinates":[-81.805393,26.263446],"type":"Point"}
}