{
  "type": "Feature",
  "properties": {
    "addr:full":"1220 Ali Baba Ave Opa Locka FL 33054",
    "addr:housenumber":"1220",
    "addr:postcode":"33054",
    "addr:street":"Ali Baba Ave;Locka",
    "iso:country":"US",
    "sg:address":"1220 Ali Baba Ave",
    "sg:city":"Opa Locka",
    "sg:classifiers":[
        {
            "category":"Manufacturing",
            "subcategory":"Metals",
            "type":"Manufacturing & Wholesale Goods"
        }
    ],
    "sg:phone":"+1 305 685 6313",
    "sg:postcode":"33054",
    "sg:province":"FL",
    "sg:tags":[
        "aircraft",
        "parts",
        "electroplating"
    ],
    "wof:name":"Action Plating Corp",
    "wof:placetype":"venue"
},
  "geometry": {"coordinates":[-80.245609,25.904078],"type":"Point"}
}