{
  "type": "Feature",
  "properties": {
    "addr:full":"100 N Ashley Dr Tampa FL 33602",
    "addr:housenumber":"100",
    "addr:postcode":"33602",
    "addr:street":"N Ashley Dr",
    "iso:country":"US",
    "sg:address":"100 N Ashley Dr",
    "sg:city":"Tampa",
    "sg:classifiers":[
        {
            "category":"Organizations",
            "subcategory":"Professional Association",
            "type":"Services"
        }
    ],
    "sg:phone":"+1 813 223 7099",
    "sg:postcode":"33602",
    "sg:province":"FL",
    "wof:name":"American Association-Kidney",
    "wof:placetype":"venue"
},
  "geometry": {"coordinates":[-82.458775,27.945732],"type":"Point"}
}