{
  "type": "Feature",
  "properties": {
    "addr:full":"1930 SW Biltmore St Port St Lucie FL 34984",
    "addr:housenumber":"1930",
    "addr:postcode":"34984",
    "addr:street":"Sw Biltmore St;St",
    "iso:country":"US",
    "sg:address":"1930 SW Biltmore St",
    "sg:city":"Port St Lucie",
    "sg:classifiers":[
        {
            "category":"Home & Garden",
            "subcategory":"Building Materials",
            "type":"Retail Goods"
        }
    ],
    "sg:phone":"+1 772 343 1034",
    "sg:postcode":"34984",
    "sg:province":"FL",
    "sg:tags":[
        "screen",
        "window"
    ],
    "wof:name":"Avaiable Aluminum Inc",
    "wof:placetype":"venue"
},
  "geometry": {"coordinates":[-80.360744,27.280597],"type":"Point"}
}