{
  "type": "Feature",
  "properties": {
    "addr:full":"1351 S 14th Ave Hollywood FL 33020",
    "addr:housenumber":"1351",
    "addr:postcode":"33020",
    "addr:street":"S 14Th Ave",
    "iso:country":"US",
    "sg:address":"1351 S 14th Ave",
    "sg:city":"Hollywood",
    "sg:classifiers":[
        {
            "category":"Organizations",
            "subcategory":"Religious Organization",
            "type":"Services"
        }
    ],
    "sg:phone":"+1 954 920 8225",
    "sg:postcode":"33020",
    "sg:province":"FL",
    "sg:tags":[
        "synagogue"
    ],
    "sg:website":"www.templebethelhollywood.org",
    "wof:name":"Bethel Temple",
    "wof:placetype":"venue"
},
  "geometry": {"coordinates":[-80.134621,26.000333],"type":"Point"}
}