{
  "type": "Feature",
  "properties": {
    "iso:country":"US",
    "sg:address":"10701 Sheldon Rd",
    "sg:city":"Tampa",
    "sg:classifiers":[
        {
            "category":"Organizations",
            "subcategory":"Religious Organization",
            "type":"Services"
        }
    ],
    "sg:phone":"+1 813 926 5006",
    "sg:postcode":"33626",
    "sg:province":"FL",
    "sg:tags":[
        "church"
    ],
    "wof:name":"Wellspring United Methodist",
    "wof:placetype":"venue"
},
  "geometry": {"coordinates":[-82.58257399999999,28.04772],"type":"Point"}
}