{
  "type": "Feature",
  "properties": {
    "iso:country":"US",
    "sg:address":"14670 Tullamore Loop",
    "sg:city":"Winter Garden",
    "sg:classifiers":[
        {
            "category":"Building & Trades",
            "subcategory":"Construction",
            "type":"Services"
        }
    ],
    "sg:phone":"+1 407 877 0763",
    "sg:postcode":"34787",
    "sg:province":"FL",
    "sg:tags":[
        "home",
        "builder"
    ],
    "wof:name":"KB Home",
    "wof:placetype":"venue"
},
  "geometry": {"coordinates":[-81.607595,28.508942],"type":"Point"}
}