{
  "type": "Feature",
  "properties": {
    "iso:country":"US",
    "sg:address":"807 Pine St",
    "sg:city":"Orlando",
    "sg:classifiers":[
        {
            "category":"Restaurant",
            "type":"Food & Drink"
        }
    ],
    "sg:phone":"+1 407 851 8726",
    "sg:postcode":"32824",
    "sg:province":"FL",
    "wof:name":"Sabor Latino",
    "wof:placetype":"venue"
},
  "geometry": {"coordinates":[-81.367514,28.432688],"type":"Point"}
}