{
  "type": "Feature",
  "properties": {
    "addr:full":"12015 SW 144th St Miami FL 33186",
    "addr:housenumber":"12015",
    "addr:postcode":"33186",
    "addr:street":"Sw 144Th St",
    "iso:country":"US",
    "sg:address":"12015 SW 144th St",
    "sg:city":"Miami",
    "sg:classifiers":[
        {
            "category":"Manufacturing",
            "subcategory":"Chemicals & Compounds",
            "type":"Manufacturing & Wholesale Goods"
        },
        {
            "category":"Professional",
            "subcategory":"Business Services",
            "type":"Services"
        },
        {
            "category":"Building & Trades",
            "subcategory":"Pest Control",
            "type":"Services"
        }
    ],
    "sg:phone":"+1 305 909 6782",
    "sg:postcode":"33186",
    "sg:province":"FL",
    "sg:tags":[
        "industrial",
        "supply",
        "services-commercial",
        "termite",
        "bee",
        "equipment",
        "repellent",
        "mothproofing",
        "barriers",
        "removal",
        "inspection",
        "bird"
    ],
    "sg:website":"http://www.terminix.com",
    "wof:name":"Terminix",
    "wof:placetype":"venue"
},
  "geometry": {"coordinates":[-80.390738,25.634262],"type":"Point"}
}