{
  "type": "Feature",
  "properties": {
    "iso:country":"US",
    "sg:address":"73 SW 12th Ave Ste 106",
    "sg:city":"Dania",
    "sg:classifiers":[
        {
            "category":"Communications",
            "subcategory":"Television Station",
            "type":"Services"
        }
    ],
    "sg:phone":"+1 305 655 2629",
    "sg:postcode":"33004",
    "sg:province":"FL",
    "sg:tags":[
        "repair",
        "satellite",
        "antenna",
        "cable",
        "tv",
        "system",
        "equipment"
    ],
    "sg:website":"http://www.calhounsat.com",
    "wof:name":"Calhoun Satellite Communications Inc",
    "wof:placetype":"venue"
},
  "geometry": {"coordinates":[-80.15186300000001,26.049551],"type":"Point"}
}