{
  "type": "Feature",
  "properties": {
    "iso:country":"US",
    "sg:address":"5440 James St",
    "sg:city":"New Port Richey",
    "sg:classifiers":[
        {
            "category":"Real Estate",
            "subcategory":"Real Estate Agent",
            "type":"Services"
        }
    ],
    "sg:phone":"+1 727 815 1522",
    "sg:postcode":"34652",
    "sg:province":"FL",
    "sg:tags":[
        "appraiser"
    ],
    "wof:name":"Henry Appaisal Co Inc",
    "wof:placetype":"venue"
},
  "geometry": {"coordinates":[-82.72377299999999,28.237164],"type":"Point"}
}