{
  "type": "Feature",
  "properties": {
    "iso:country":"US",
    "sg:address":"8812 Industrial Dr",
    "sg:city":"Tampa",
    "sg:classifiers":[
        {
            "category":"Building & Trades",
            "subcategory":"Construction",
            "type":"Services"
        }
    ],
    "sg:phone":"+1 813 985 4541",
    "sg:postcode":"33637",
    "sg:province":"FL",
    "sg:tags":[
        "concrete",
        "contractor"
    ],
    "wof:name":"Advanced Prssure Grouting Svcs",
    "wof:placetype":"venue"
},
  "geometry": {"coordinates":[-82.359612,28.016845],"type":"Point"}
}