{
  "type": "Feature",
  "properties": {
    "iso:country":"US",
    "sg:address":"120 International Pkwy Ste 128",
    "sg:city":"Heathrow",
    "sg:classifiers":[
        {
            "category":"Personal",
            "subcategory":"Beauty Salon",
            "type":"Services"
        },
        {
            "category":"Personal",
            "subcategory":"Day Spa",
            "type":"Services"
        },
        {
            "category":"Personal",
            "subcategory":"Nail Salon",
            "type":"Services"
        }
    ],
    "sg:phone":"+1 407 333 3571",
    "sg:postcode":"32746",
    "sg:province":"FL",
    "sg:tags":[
        "hair"
    ],
    "sg:website":"www.fawnfeatherspa.com",
    "wof:name":"Fawnfeather Salon and Spa",
    "wof:placetype":"venue"
},
  "geometry": {"coordinates":[-81.369088,28.757768],"type":"Point"}
}