{
  "type": "Feature",
  "properties": {
    "iso:country":"US",
    "sg:address":"254 S Ronald Reagan Blvd",
    "sg:city":"Longwood",
    "sg:classifiers":[
        {
            "category":"Professional",
            "subcategory":"Employment Agencies",
            "type":"Services"
        }
    ],
    "sg:phone":"+1 407 659 3947",
    "sg:postcode":"32750",
    "sg:province":"FL",
    "wof:name":"Nirvana Search",
    "wof:placetype":"venue"
},
  "geometry": {"coordinates":[-81.34625699999999,28.695674],"type":"Point"}
}