{
  "type": "Feature",
  "properties": {
    "addr:full":"6189 Bobby Padgett Rd Jacksonville FL 32234",
    "addr:housenumber":"6189",
    "addr:postcode":"32234",
    "addr:street":"Bobby Padgett Rd",
    "iso:country":"US",
    "sg:address":"6189 Bobby Padgett Rd",
    "sg:city":"Jacksonville",
    "sg:classifiers":[
        {
            "category":"Building & Trades",
            "subcategory":"Construction",
            "type":"Services"
        }
    ],
    "sg:phone":"+1 904 289 1871",
    "sg:postcode":"32234",
    "sg:province":"FL",
    "sg:tags":[
        "foundation"
    ],
    "wof:name":"Jmr Foundations Inc",
    "wof:placetype":"venue"
},
  "geometry": {"coordinates":[-82.007488,30.131381],"type":"Point"}
}