{
  "type": "Feature",
  "properties": {
    "iso:country":"US",
    "sg:address":"3037 E Olive Rd",
    "sg:city":"Pensacola",
    "sg:classifiers":[
        {
            "category":"Food & Beverages",
            "subcategory":"Candy",
            "type":"Retail Goods"
        }
    ],
    "sg:phone":"+1 850 484 8399",
    "sg:postcode":"32514",
    "sg:province":"FL",
    "sg:tags":[
        "popcorn",
        "supply"
    ],
    "wof:name":"Pensacola Popcorn",
    "wof:placetype":"venue"
},
  "geometry": {"coordinates":[-87.20135500000001,30.509885],"type":"Point"}
}