{
  "type": "Feature",
  "properties": {
    "iso:country":"US",
    "sg:address":"137 E Woolbright Rd",
    "sg:city":"Boynton Beach",
    "sg:classifiers":[
        {
            "category":"Health Services",
            "subcategory":"Doctor",
            "type":"Services"
        }
    ],
    "sg:phone":"+1 561 740 4051",
    "sg:postcode":"33435",
    "sg:province":"FL",
    "sg:tags":[
        "clinic"
    ],
    "wof:name":"Woolbright Chiropractic",
    "wof:placetype":"venue"
},
  "geometry": {"coordinates":[-80.06266100000001,26.514619],"type":"Point"}
}