{
  "type": "Feature",
  "properties": {
    "iso:country":"US",
    "sg:address":"534 Piedmont Rd",
    "sg:city":"Sanibel",
    "sg:classifiers":[
        {
            "category":"Health Services",
            "subcategory":"Clinic",
            "type":"Services"
        }
    ],
    "sg:phone":"+1 239 472 3327",
    "sg:postcode":"33957",
    "sg:province":"FL",
    "sg:tags":[
        "home"
    ],
    "wof:name":"Susan Bluehs Health Care Svc",
    "wof:placetype":"venue"
},
  "geometry": {"coordinates":[-82.06122000000001,26.435502],"type":"Point"}
}