{
  "type": "Feature",
  "properties": {
    "addr:full":"2490 State Hwy 580 Clearwater FL 33761",
    "addr:housenumber":"2490",
    "addr:postcode":"33761",
    "addr:street":"State Hwy 580",
    "iso:country":"US",
    "sg:address":"2490 State Hwy 580",
    "sg:city":"Clearwater",
    "sg:classifiers":[
        {
            "category":"Restaurant",
            "type":"Food & Drink"
        }
    ],
    "sg:phone":"+1 727 796 1648",
    "sg:postcode":"33761",
    "sg:province":"FL",
    "sg:tags":[
        "eating"
    ],
    "wof:name":"Steak 'n Shake",
    "wof:placetype":"venue"
},
  "geometry": {"coordinates":[-82.735022,28.019476],"type":"Point"}
}