{
  "type": "Feature",
  "properties": {
    "iso:country":"US",
    "sg:address":"425 W Hallandale Beach Blvd",
    "sg:city":"Hallandale Beach",
    "sg:classifiers":[
        {
            "category":"Personal",
            "type":"Services"
        },
        {
            "category":"Insurance",
            "subcategory":"Insurance Agent",
            "type":"Services"
        }
    ],
    "sg:phone":"+1 954 456 5771",
    "sg:postcode":"33009",
    "sg:province":"FL",
    "sg:tags":[
        "department",
        "motor",
        "vehicle"
    ],
    "wof:name":"Auto Tags Of Hollandale",
    "wof:placetype":"venue"
},
  "geometry": {"coordinates":[-80.15302699999999,25.985406],"type":"Point"}
}