{
  "type": "Feature",
  "properties": {
    "addr:full":"1164 NW 12th Ter Stuart FL 34994",
    "addr:housenumber":"1164",
    "addr:postcode":"34994",
    "addr:street":"Nw 12Th Ter",
    "iso:country":"US",
    "sg:address":"1164 NW 12th Ter",
    "sg:city":"Stuart",
    "sg:classifiers":[
        {
            "category":"Real Estate",
            "subcategory":"Real Estate Agent",
            "type":"Services"
        }
    ],
    "sg:phone":"+1 772 692 7037",
    "sg:postcode":"34994",
    "sg:province":"FL",
    "wof:name":"Corona Real Estate Co",
    "wof:placetype":"venue"
},
  "geometry": {"coordinates":[-80.268728,27.220114],"type":"Point"}
}