{
  "type": "Feature",
  "properties": {
    "addr:full":"10375 SW Green Ridge Ln Palm City FL 34990",
    "addr:housenumber":"10375",
    "addr:postcode":"34990",
    "addr:street":"Sw Green Ridge Ln",
    "iso:country":"US",
    "sg:address":"10375 SW Green Ridge Ln",
    "sg:city":"Palm City",
    "sg:classifiers":[
        {
            "category":"Building & Trades",
            "subcategory":"Construction",
            "type":"Services"
        }
    ],
    "sg:phone":"+1 772 283 8425",
    "sg:postcode":"34990",
    "sg:province":"FL",
    "sg:tags":[
        "house"
    ],
    "wof:name":"McDonald Gen Contr Ed",
    "wof:placetype":"venue"
},
  "geometry": {"coordinates":[-80.310036,27.081064],"type":"Point"}
}