{
  "type": "Feature",
  "properties": {
    "addr:full":"3222 Winter Lake Rd Lakeland FL 33803",
    "addr:housenumber":"3222",
    "addr:postcode":"33803",
    "addr:street":"Winter Lake Rd",
    "iso:country":"US",
    "sg:address":"3222 Winter Lake Rd",
    "sg:city":"Lakeland",
    "sg:classifiers":[
        {
            "category":"Manufacturing",
            "subcategory":"Glass & Minerals",
            "type":"Manufacturing & Wholesale Goods"
        }
    ],
    "sg:phone":"+1 863 666 5300",
    "sg:postcode":"33803",
    "sg:province":"FL",
    "sg:tags":[
        "refractory",
        "mfg",
        "clay"
    ],
    "wof:name":"Harbisn-Wlker Refractories Co",
    "wof:placetype":"venue"
},
  "geometry": {"coordinates":[-81.893235,27.996895],"type":"Point"}
}