{
  "type": "Feature",
  "properties": {
    "iso:country":"US",
    "sg:address":"2302 59th St W",
    "sg:city":"Bradenton",
    "sg:classifiers":[
        {
            "category":"Health Services",
            "subcategory":"Nursing And Care Facility",
            "type":"Services"
        }
    ],
    "sg:phone":"+1 941 792 8480",
    "sg:postcode":"34209",
    "sg:province":"FL",
    "sg:tags":[
        "home"
    ],
    "wof:name":"I H S of Bradenton",
    "wof:placetype":"venue"
},
  "geometry": {"coordinates":[-82.620465,27.47944],"type":"Point"}
}