{
  "type": "Feature",
  "properties": {
    "addr:full":"5619 SW 107th Ave Miami FL 33173",
    "addr:housenumber":"5619",
    "addr:postcode":"33173",
    "addr:street":"Sw 107Th Ave",
    "iso:country":"US",
    "sg:address":"5619 SW 107th Ave",
    "sg:city":"Miami",
    "sg:classifiers":[
        {
            "category":"Retail",
            "subcategory":"Laundry & Dry Cleaning",
            "type":"Services"
        }
    ],
    "sg:phone":"+1 305 596 5201",
    "sg:postcode":"33173",
    "sg:province":"FL",
    "sg:tags":[
        "cleaners"
    ],
    "wof:name":"Jaxix Imports",
    "wof:placetype":"venue"
},
  "geometry": {"coordinates":[-80.366754,25.713798],"type":"Point"}
}