{
  "type": "Feature",
  "properties": {
    "iso:country":"US",
    "sg:address":"4910 Turkey Creek Rd",
    "sg:city":"Plant City",
    "sg:classifiers":[
        {
            "category":"Autos & Motor Vehicles",
            "subcategory":"Automobile Sales",
            "type":"Retail Goods"
        }
    ],
    "sg:phone":"+1 813 707 9899",
    "sg:postcode":"33567",
    "sg:province":"FL",
    "sg:tags":[
        "used"
    ],
    "wof:name":"C & S Quality Cars Inc",
    "wof:placetype":"venue"
},
  "geometry": {"coordinates":[-82.17034099999999,27.947568],"type":"Point"}
}