{
  "type": "Feature",
  "properties": {
    "iso:country":"US",
    "sg:address":"7900 Venture Center Way",
    "sg:city":"Boynton Beach",
    "sg:classifiers":[
        {
            "category":"Health Services",
            "subcategory":"Nursing And Care Facility",
            "type":"Services"
        }
    ],
    "sg:phone":"+1 561 736 6000",
    "sg:postcode":"33437",
    "sg:province":"FL",
    "sg:tags":[
        "skilled"
    ],
    "wof:name":"Boynton Health Care Center",
    "wof:placetype":"venue"
},
  "geometry": {"coordinates":[-80.167592,26.524675],"type":"Point"}
}