{
  "type": "Feature",
  "properties": {
    "iso:country":"US",
    "sg:address":"4825 N Dixie Hwy",
    "sg:city":"Oakland Park",
    "sg:classifiers":[
        {
            "category":"Organizations",
            "subcategory":"Non-profit Organization",
            "type":"Services"
        }
    ],
    "sg:phone":"+1 954 446 6988",
    "sg:postcode":"33334",
    "sg:province":"FL",
    "sg:tags":[
        "information",
        "alcoholism",
        "treatment"
    ],
    "wof:name":"Alcohol AAAAHA Abuse",
    "wof:placetype":"venue"
},
  "geometry": {"coordinates":[-80.134637,26.186593],"type":"Point"}
}