{
  "type": "Feature",
  "properties": {
    "iso:country":"US",
    "sg:address":"1607 N 43rd St",
    "sg:city":"Tampa",
    "sg:classifiers":[
        {
            "category":"Freight",
            "type":"Transportation"
        },
        {
            "category":"Building & Trades",
            "subcategory":"Construction",
            "type":"Services"
        }
    ],
    "sg:phone":"+1 813 248 2451",
    "sg:postcode":"33605",
    "sg:province":"FL",
    "sg:tags":[
        "local",
        "contractor",
        "storage",
        "paving",
        "trucking"
    ],
    "wof:name":"Tyndall & Associates Inc",
    "wof:placetype":"venue"
},
  "geometry": {"coordinates":[-82.409944,27.958032],"type":"Point"}
}