{
  "type": "Feature",
  "properties": {
    "iso:country":"US",
    "sg:address":"2002 Wallace Ave",
    "sg:city":"Melbourne",
    "sg:classifiers":[
        {
            "category":"Building & Trades",
            "subcategory":"Construction",
            "type":"Services"
        }
    ],
    "sg:phone":"+1 321 431 0709",
    "sg:postcode":"32935",
    "sg:province":"FL",
    "sg:tags":[
        "contractor"
    ],
    "wof:name":"Jay Shirey Contractor",
    "wof:placetype":"venue"
},
  "geometry": {"coordinates":[-80.651478,28.118836],"type":"Point"}
}