{
  "type": "Feature",
  "properties": {
    "addr:full":"3035 Palm Rd West Palm Beach FL 33409",
    "addr:housenumber":"3035",
    "addr:postcode":"33409",
    "addr:street":"Palm Rd",
    "iso:country":"US",
    "sg:address":"3035 Palm Rd",
    "sg:city":"West Palm Beach",
    "sg:classifiers":[
        {
            "category":"Autos & Motor Vehicles",
            "subcategory":"Fuel & Gas Station",
            "type":"Retail Goods"
        }
    ],
    "sg:phone":"+1 561 640 9650",
    "sg:postcode":"33409",
    "sg:province":"FL",
    "sg:tags":[
        "convenience",
        "station",
        "gasoline",
        "store"
    ],
    "wof:name":"Mobil",
    "wof:placetype":"venue"
},
  "geometry": {"coordinates":[-80.102369,26.7227],"type":"Point"}
}