{
  "type": "Feature",
  "properties": {
    "iso:country":"US",
    "sg:address":"1016 S Lakeside Dr",
    "sg:city":"Lake Worth",
    "sg:classifiers":[
        {
            "category":"Education",
            "subcategory":"School",
            "type":"Public Place"
        }
    ],
    "sg:phone":"+1 561 585 2958",
    "sg:postcode":"33460",
    "sg:province":"FL",
    "wof:name":"Calling All Colors of Flo",
    "wof:placetype":"venue"
},
  "geometry": {"coordinates":[-80.050573,26.602565],"type":"Point"}
}