{
  "type": "Feature",
  "properties": {
    "iso:country":"US",
    "sg:address":"700 W Ave del Rio",
    "sg:city":"Clewiston",
    "sg:classifiers":[
        {
            "category":"Retail",
            "subcategory":"Portrait Studio",
            "type":"Services"
        }
    ],
    "sg:phone":"+1 863 902 0887",
    "sg:postcode":"33440",
    "sg:province":"FL",
    "sg:tags":[
        "photographer"
    ],
    "wof:name":"Photos By Rene Malbog",
    "wof:placetype":"venue"
},
  "geometry": {"coordinates":[-80.94625499999999,26.762031],"type":"Point"}
}