{
  "type": "Feature",
  "properties": {
    "iso:country":"US",
    "sg:address":"1031 W Busch Blvd",
    "sg:city":"Tampa",
    "sg:classifiers":[
        {
            "category":"Professional",
            "subcategory":"Computer Services",
            "type":"Services"
        }
    ],
    "sg:phone":"+1 813 931 4976",
    "sg:postcode":"33612",
    "sg:province":"FL",
    "sg:tags":[
        "repair",
        "security-systems",
        "equipment-service"
    ],
    "wof:name":"PC Services",
    "wof:placetype":"venue"
},
  "geometry": {"coordinates":[-82.46894399999999,28.033383],"type":"Point"}
}