{
  "type": "Feature",
  "properties": {
    "iso:country":"US",
    "sg:address":"8610 Elm Fair Blvd",
    "sg:city":"Tampa",
    "sg:classifiers":[
        {
            "category":"Travel",
            "subcategory":"Hotels & Motels",
            "type":"Entertainment"
        },
        {
            "category":"Retail",
            "subcategory":"Event Space",
            "type":"Services"
        }
    ],
    "sg:phone":"+1 800 345 8082",
    "sg:postcode":"33610",
    "sg:province":"FL",
    "sg:tags":[
        "facility",
        "banquet",
        "reception",
        "lodging",
        "corporate",
        "hall"
    ],
    "sg:website":"http://ad.doubleclick.net/clk;222816988;46581822;v?http://www.hiexpress.com/redirect?path=hd&brandCode=ex&hotelCode=tpafl&_PMID=99601036&cm_mmc=mdpr-_-yellowpages-_-ex-_-tpafl",
    "wof:name":"Holiday Inn Express Hotel & Suites Tampa-Fairgrounds-Casino",
    "wof:placetype":"venue"
},
  "geometry": {"coordinates":[-82.356323,27.99017],"type":"Point"}
}