{
  "type": "Feature",
  "properties": {
    "addr:full":"635 Bimini Rd Satellite Beach FL 32937",
    "addr:housenumber":"635",
    "addr:postcode":"32937",
    "addr:street":"Bimini Rd",
    "iso:country":"US",
    "sg:address":"635 Bimini Rd",
    "sg:city":"Satellite Beach",
    "sg:classifiers":[
        {
            "category":"Professional",
            "type":"Services"
        }
    ],
    "sg:phone":"+1 321 480 6966",
    "sg:postcode":"32937",
    "sg:province":"FL",
    "sg:tags":[
        "establishment"
    ],
    "wof:name":"Andrew Martin Contractor",
    "wof:placetype":"venue"
},
  "geometry": {"coordinates":[-80.595567,28.163154],"type":"Point"}
}