{
  "type": "Feature",
  "properties": {
    "iso:country":"US",
    "sg:address":"7710 Meadowglen Dr",
    "sg:city":"Orlando",
    "sg:classifiers":[
        {
            "category":"Wholesale",
            "subcategory":"Durable Goods & Equipment",
            "type":"Manufacturing & Wholesale Goods"
        }
    ],
    "sg:phone":"+1 407 660 2456",
    "sg:postcode":"32810",
    "sg:province":"FL",
    "sg:tags":[
        "representative",
        "manufacturer"
    ],
    "wof:name":"Tom Burton & Assoc",
    "wof:placetype":"venue"
},
  "geometry": {"coordinates":[-81.409367,28.628882],"type":"Point"}
}