{
  "type": "Feature",
  "properties": {
    "iso:country":"US",
    "sg:address":"4503 NW 103rd Ave",
    "sg:city":"Fort Lauderdale",
    "sg:classifiers":[
        {
            "category":"Manufacturing",
            "subcategory":"Tools & Machinery",
            "type":"Manufacturing & Wholesale Goods"
        }
    ],
    "sg:phone":"+1 954 726 1422",
    "sg:postcode":"33351",
    "sg:province":"FL",
    "sg:tags":[
        "security",
        "identification",
        "system",
        "mfg"
    ],
    "wof:name":"A Developmental Stage Entp",
    "wof:placetype":"venue"
},
  "geometry": {"coordinates":[-80.287378,26.179718],"type":"Point"}
}