{
  "type": "Feature",
  "properties": {
    "iso:country":"US",
    "sg:address":"110 N Franklin St",
    "sg:city":"Tampa",
    "sg:classifiers":[
        {
            "category":"Utilities",
            "subcategory":"Telephone",
            "type":"Services"
        }
    ],
    "sg:phone":"+1 813 273 9877",
    "sg:postcode":"33602",
    "sg:province":"FL",
    "sg:tags":[
        "communications"
    ],
    "wof:name":"Sprint",
    "wof:placetype":"venue"
},
  "geometry": {"coordinates":[-82.457341,27.946145],"type":"Point"}
}