{
  "type": "Feature",
  "properties": {
    "iso:country":"US",
    "sg:address":"4801 Sawyer Pine Rd",
    "sg:city":"Sarasota",
    "sg:classifiers":[
        {
            "category":"Building & Trades",
            "subcategory":"Plumbing",
            "type":"Services"
        }
    ],
    "sg:phone":"+1 941 922 7008",
    "sg:postcode":"34233",
    "sg:province":"FL",
    "sg:tags":[
        "contractor"
    ],
    "wof:name":"George Lagasse Plmg",
    "wof:placetype":"venue"
},
  "geometry": {"coordinates":[-82.49087900000001,27.282605],"type":"Point"}
}