{
  "type": "Feature",
  "properties": {
    "addr:full":"306 SE Monterey Rd Stuart FL 34994",
    "addr:housenumber":"306",
    "addr:postcode":"34994",
    "addr:street":"Se Monterey Rd",
    "iso:country":"US",
    "sg:address":"306 SE Monterey Rd",
    "sg:city":"Stuart",
    "sg:classifiers":[
        {
            "category":"Home & Garden",
            "subcategory":"Mobile Homes",
            "type":"Retail Goods"
        }
    ],
    "sg:phone":"+1 772 223 1179",
    "sg:postcode":"34994",
    "sg:province":"FL",
    "sg:tags":[
        "dealer"
    ],
    "wof:name":"5 Star Mobile Homes",
    "wof:placetype":"venue"
},
  "geometry": {"coordinates":[-80.248902,27.175592],"type":"Point"}
}