{
  "type": "Feature",
  "properties": {
    "addr:full":"6218 Forestwood Dr E Lakeland FL 33811",
    "addr:housenumber":"6218",
    "addr:postcode":"33811",
    "addr:street":"Forestwood Dr E",
    "iso:country":"US",
    "sg:address":"6218 Forestwood Dr E",
    "sg:city":"Lakeland",
    "sg:classifiers":[
        {
            "category":"Wholesale",
            "subcategory":"Sporting Goods",
            "type":"Manufacturing & Wholesale Goods"
        }
    ],
    "sg:phone":"+1 863 647 4313",
    "sg:postcode":"33811",
    "sg:province":"FL",
    "wof:name":"Jims Sea Dive Center",
    "wof:placetype":"venue"
},
  "geometry": {"coordinates":[-82.018367,27.947687],"type":"Point"}
}