{
  "type": "Feature",
  "properties": {
    "iso:country":"US",
    "sg:address":"7998 Lola Cir",
    "sg:city":"Navarre",
    "sg:classifiers":[
        {
            "category":"Professional",
            "subcategory":"Management & Consulting",
            "type":"Services"
        }
    ],
    "sg:phone":"+1 850 582 4462",
    "sg:postcode":"32566",
    "sg:province":"FL",
    "sg:tags":[
        "personnel",
        "consultant"
    ],
    "wof:name":"V G Thomas Staffing",
    "wof:placetype":"venue"
},
  "geometry": {"coordinates":[-86.899536,30.436874],"type":"Point"}
}