{
  "type": "Feature",
  "properties": {
    "iso:country":"US",
    "sg:address":"6120 Powers Ave",
    "sg:city":"Jacksonville",
    "sg:classifiers":[
        {
            "category":"Building & Trades",
            "subcategory":"Construction",
            "type":"Services"
        }
    ],
    "sg:phone":"+1 904 591 2538",
    "sg:postcode":"32217",
    "sg:province":"FL",
    "sg:tags":[
        "dry wall",
        "contractor"
    ],
    "wof:name":"Drywall & Textures Inc",
    "wof:placetype":"venue"
},
  "geometry": {"coordinates":[-81.62108000000001,30.262078],"type":"Point"}
}