{
  "type": "Feature",
  "properties": {
    "addr:full":"1625 Cotswold Dr Orlando FL 32825",
    "addr:housenumber":"1625",
    "addr:postcode":"32825",
    "addr:street":"Cotswold Dr",
    "iso:country":"US",
    "sg:address":"1625 Cotswold Dr",
    "sg:city":"Orlando",
    "sg:classifiers":[
        {
            "category":"Building & Trades",
            "subcategory":"Construction",
            "type":"Services"
        }
    ],
    "sg:phone":"+1 407 948 3730",
    "sg:postcode":"32825",
    "sg:province":"FL",
    "sg:tags":[
        "concrete",
        "pumping",
        "contractor"
    ],
    "wof:name":"Ace Concrete Pumping Of Orlando Inc",
    "wof:placetype":"venue"
},
  "geometry": {"coordinates":[-81.26675400000001,28.523911],"type":"Point"}
}