{
  "type": "Feature",
  "properties": {
    "addr:full":"26609 State Rd 54 Lutz FL 33559",
    "addr:housenumber":"26609;54",
    "addr:postcode":"33559",
    "addr:street":"State Rd",
    "iso:country":"US",
    "sg:address":"26609 State Rd 54",
    "sg:city":"Lutz",
    "sg:classifiers":[
        {
            "category":"Shopping",
            "subcategory":"Department Store",
            "type":"Retail Goods"
        }
    ],
    "sg:phone":"+1 813 929 7210",
    "sg:postcode":"33559",
    "sg:province":"FL",
    "wof:name":"Dollar General",
    "wof:placetype":"venue"
},
  "geometry": {"coordinates":[-82.37952799999999,28.225112],"type":"Point"}
}