{
  "type": "Feature",
  "properties": {
    "addr:full":"6113 Newport Village Way Lake Worth FL 33463",
    "addr:housenumber":"6113",
    "addr:postcode":"33463",
    "addr:street":"Newport Village Way",
    "iso:country":"US",
    "sg:address":"6113 Newport Village Way",
    "sg:city":"Lake Worth",
    "sg:classifiers":[
        {
            "category":"Organizations",
            "subcategory":"Labor Organization",
            "type":"Services"
        }
    ],
    "sg:phone":"+1 561 439 3850",
    "sg:postcode":"33463",
    "sg:province":"FL",
    "wof:name":"Jim and Pauline Saba Lc",
    "wof:placetype":"venue"
},
  "geometry": {"coordinates":[-80.140846,26.576876],"type":"Point"}
}