{
  "type": "Feature",
  "properties": {
    "addr:full":"1699 Sopchoppy Hwy Sopchoppy FL 32358",
    "addr:housenumber":"1699",
    "addr:postcode":"32358",
    "addr:street":"Sopchoppy Hwy",
    "iso:country":"US",
    "sg:address":"1699 Sopchoppy Hwy",
    "sg:city":"Sopchoppy",
    "sg:classifiers":[
        {
            "category":"Building & Trades",
            "subcategory":"Landscaping Services",
            "type":"Services"
        }
    ],
    "sg:phone":"+1 850 962 2660",
    "sg:postcode":"32358",
    "sg:province":"FL",
    "wof:name":"Brannens Lawn Care Service",
    "wof:placetype":"venue"
},
  "geometry": {"coordinates":[-84.466168,30.065169],"type":"Point"}
}