{
  "type": "Feature",
  "properties": {
    "iso:country":"US",
    "sg:address":"43553 Ratliff Rd",
    "sg:city":"Callahan",
    "sg:classifiers":[
        {
            "category":"Manufacturing",
            "subcategory":"Soap",
            "type":"Manufacturing & Wholesale Goods"
        }
    ],
    "sg:phone":"+1 904 879 7094",
    "sg:postcode":"32011",
    "sg:province":"FL",
    "sg:tags":[
        "detergents-wholesale",
        "manufacturer"
    ],
    "sg:website":"http://www.magnoliahillsoap.com",
    "wof:name":"Magnolia Hill Soap Company",
    "wof:placetype":"venue"
},
  "geometry": {"coordinates":[-81.808098,30.50127],"type":"Point"}
}