{
  "type": "Feature",
  "properties": {
    "iso:country":"US",
    "sg:address":"2889 College St",
    "sg:city":"Jacksonville",
    "sg:classifiers":[
        {
            "category":"Building & Trades",
            "subcategory":"Landscaping Services",
            "type":"Services"
        }
    ],
    "sg:phone":"+1 904 387 9897",
    "sg:postcode":"32205",
    "sg:province":"FL",
    "sg:tags":[
        "lawn",
        "maintenance",
        "grounds"
    ],
    "wof:name":"Griner's Lawn Svc",
    "wof:placetype":"venue"
},
  "geometry": {"coordinates":[-81.703208,30.314157],"type":"Point"}
}