{
  "type": "Feature",
  "properties": {
    "iso:country":"US",
    "sg:address":"2026 Fannie Dr",
    "sg:city":"Tallahassee",
    "sg:classifiers":[
        {
            "category":"Real Estate",
            "subcategory":"Real Estate Services",
            "type":"Services"
        },
        {
            "category":"Real Estate",
            "subcategory":"Real Estate Agent",
            "type":"Services"
        }
    ],
    "sg:phone":"+1 850 251 9804",
    "sg:postcode":"32303",
    "sg:province":"FL",
    "sg:tags":[
        "buyer",
        "broker"
    ],
    "wof:name":"Real Estate Rescue",
    "wof:placetype":"venue"
},
  "geometry": {"coordinates":[-84.336827,30.468033],"type":"Point"}
}