{
  "type": "Feature",
  "properties": {
    "iso:country":"US",
    "sg:address":"629 Prairie Ln",
    "sg:city":"Altamonte Springs",
    "sg:classifiers":[
        {
            "category":"Health Services",
            "subcategory":"Clinic",
            "type":"Services"
        }
    ],
    "sg:phone":"+1 407 772 2860",
    "sg:postcode":"32714",
    "sg:province":"FL",
    "wof:name":"Barbara Musser Health Services",
    "wof:placetype":"venue"
},
  "geometry": {"coordinates":[-81.403991,28.677812],"type":"Point"}
}