{
  "type": "Feature",
  "properties": {
    "addr:full":"4700 NW 167th St Hialeah FL 33014",
    "addr:housenumber":"4700",
    "addr:postcode":"33014",
    "addr:street":"Nw 167Th St",
    "iso:country":"US",
    "sg:address":"4700 NW 167th St",
    "sg:city":"Hialeah",
    "sg:classifiers":[
        {
            "category":"Home & Garden",
            "subcategory":"Furniture",
            "type":"Retail Goods"
        }
    ],
    "sg:phone":"+1 305 626 0900",
    "sg:postcode":"33014",
    "sg:province":"FL",
    "sg:tags":[
        "store"
    ],
    "wof:name":"Swingles Furniture Sales & Rentals",
    "wof:placetype":"venue"
},
  "geometry": {"coordinates":[-80.276802,25.924999],"type":"Point"}
}