{
  "type": "Feature",
  "properties": {
    "iso:country":"US",
    "sg:address":"1455 Oviedo Marketplace Blvd",
    "sg:city":"Oviedo",
    "sg:classifiers":[
        {
            "category":"Shopping",
            "subcategory":"Clothing, Apparel, & Fashions",
            "type":"Retail Goods"
        }
    ],
    "sg:phone":"+1 407 359 7870",
    "sg:postcode":"32765",
    "sg:province":"FL",
    "sg:tags":[
        "sportswear"
    ],
    "wof:name":"Beach Scene Surf & Skate Shop",
    "wof:placetype":"venue"
},
  "geometry": {"coordinates":[-81.23424900000001,28.661499],"type":"Point"}
}