{
  "type": "Feature",
  "properties": {
    "addr:full":"14271 NW 66 Ave Chiefland FL 32626",
    "addr:housenumber":"14271",
    "addr:postcode":"32626",
    "addr:street":"Nw 66 Ave",
    "iso:country":"US",
    "sg:address":"14271 NW 66 Ave",
    "sg:city":"Chiefland",
    "sg:classifiers":[
        {
            "category":"Manufacturing",
            "subcategory":"Glass & Minerals",
            "type":"Manufacturing & Wholesale Goods"
        }
    ],
    "sg:phone":"+1 352 490 9694",
    "sg:postcode":"32626",
    "sg:province":"FL",
    "sg:tags":[
        "concrete",
        "product",
        "mfg"
    ],
    "wof:name":"Marcus V Hall",
    "wof:placetype":"venue"
},
  "geometry": {"coordinates":[-82.88347899999999,29.539388],"type":"Point"}
}