{
  "type": "Feature",
  "properties": {
    "addr:full":"1233 S Tamiami Trl Sarasota FL 34239",
    "addr:housenumber":"1233",
    "addr:postcode":"34239",
    "addr:street":"S Tamiami Trl",
    "iso:country":"US",
    "sg:address":"1233 S Tamiami Trl",
    "sg:city":"Sarasota",
    "sg:classifiers":[
        {
            "category":"Shopping",
            "subcategory":"Computers & Home Electronics",
            "type":"Retail Goods"
        }
    ],
    "sg:phone":"+1 941 953 9800",
    "sg:postcode":"34239",
    "sg:province":"FL",
    "sg:tags":[
        "software"
    ],
    "wof:name":"Corporate Technology & Acctg",
    "wof:placetype":"venue"
},
  "geometry": {"coordinates":[-82.529639,27.32164],"type":"Point"}
}