{
  "type": "Feature",
  "properties": {
    "addr:full":"220 Tulsa Dr Pensacola FL 32534",
    "addr:housenumber":"220",
    "addr:postcode":"32534",
    "addr:street":"Tulsa Dr",
    "iso:country":"US",
    "sg:address":"220 Tulsa Dr",
    "sg:city":"Pensacola",
    "sg:classifiers":[
        {
            "category":"Building & Trades",
            "subcategory":"Construction",
            "type":"Services"
        }
    ],
    "sg:phone":"+1 850 473 9755",
    "sg:postcode":"32534",
    "sg:province":"FL",
    "sg:tags":[
        "screen",
        "enclosure"
    ],
    "wof:name":"Bay Aluminum & Screen Inc",
    "wof:placetype":"venue"
},
  "geometry": {"coordinates":[-87.26489100000001,30.536283],"type":"Point"}
}