{
  "type": "Feature",
  "properties": {
    "iso:country":"US",
    "sg:address":"4403 Metzger Rd",
    "sg:city":"Fort Pierce",
    "sg:classifiers":[
        {
            "category":"Farming",
            "subcategory":"Farm & Veterinary Services",
            "type":"Manufacturing & Wholesale Goods"
        }
    ],
    "sg:phone":"+1 772 464 8813",
    "sg:postcode":"34947",
    "sg:province":"FL",
    "sg:tags":[
        "vegetable",
        "fruit"
    ],
    "wof:name":"Quality Citrus Harvesting",
    "wof:placetype":"venue"
},
  "geometry": {"coordinates":[-80.370763,27.454785],"type":"Point"}
}