{
  "type": "Feature",
  "properties": {
    "iso:country":"US",
    "sg:address":"2245 W Devon Dr",
    "sg:city":"Citrus Springs",
    "sg:classifiers":[
        {
            "category":"Building & Trades",
            "subcategory":"Landscaping Services",
            "type":"Services"
        }
    ],
    "sg:phone":"+1 352 465 5649",
    "sg:postcode":"34434",
    "sg:province":"FL",
    "sg:tags":[
        "tree"
    ],
    "wof:name":"Jessica Flanagn Tree Svc",
    "wof:placetype":"venue"
},
  "geometry": {"coordinates":[-82.472717,29.000742],"type":"Point"}
}