{
  "type": "Feature",
  "properties": {
    "iso:country":"US",
    "sg:address":"4476 N University Dr",
    "sg:city":"Fort Lauderdale",
    "sg:classifiers":[
        {
            "category":"Insurance",
            "subcategory":"Insurance Agent",
            "type":"Services"
        }
    ],
    "sg:phone":"+1 954 748 6420",
    "sg:postcode":"33351",
    "sg:province":"FL",
    "wof:name":"Flag Insurance Services",
    "wof:placetype":"venue"
},
  "geometry": {"coordinates":[-80.25160099999999,26.179596],"type":"Point"}
}