{
  "type": "Feature",
  "properties": {
    "iso:country":"US",
    "sg:address":"2571 Flower Rd",
    "sg:city":"Venice",
    "sg:classifiers":[
        {
            "category":"Recreation",
            "type":"Entertainment"
        }
    ],
    "sg:phone":"+1 941 493 3625",
    "sg:postcode":"34293",
    "sg:province":"FL",
    "sg:tags":[
        "instruction",
        "swimming"
    ],
    "wof:name":"Infant Swimming Research",
    "wof:placetype":"venue"
},
  "geometry": {"coordinates":[-82.427474,27.067289],"type":"Point"}
}