{
  "type": "Feature",
  "properties": {
    "addr:full":"4849 State Hwy 5 Jacksonville FL 32207",
    "addr:housenumber":"4849",
    "addr:postcode":"32207",
    "addr:street":"State Hwy 5",
    "iso:country":"US",
    "sg:address":"4849 State Hwy 5",
    "sg:city":"Jacksonville",
    "sg:classifiers":[
        {
            "category":"Wholesale",
            "subcategory":"Hardware",
            "type":"Manufacturing & Wholesale Goods"
        }
    ],
    "sg:phone":"+1 904 306 9171",
    "sg:postcode":"32207",
    "sg:province":"FL",
    "sg:tags":[
        "plumbing",
        "fixture",
        "supply"
    ],
    "wof:name":"Lionheart Products",
    "wof:placetype":"venue"
},
  "geometry": {"coordinates":[-81.622962,30.272726],"type":"Point"}
}