{
  "type": "Feature",
  "properties": {
    "iso:country":"US",
    "sg:address":"121 W Underwood St",
    "sg:city":"Orlando",
    "sg:classifiers":[
        {
            "category":"Health Services",
            "subcategory":"Doctor",
            "type":"Services"
        }
    ],
    "sg:phone":"+1 407 843 1471",
    "sg:postcode":"32806",
    "sg:province":"FL",
    "sg:tags":[
        "surgeon",
        "eye"
    ],
    "wof:name":"Laserview",
    "wof:placetype":"venue"
},
  "geometry": {"coordinates":[-81.38118799999999,28.526963],"type":"Point"}
}