{
  "type": "Feature",
  "properties": {
    "addr:full":"2016 W US Hwy 90 Lake City FL 32055",
    "addr:housenumber":"2016",
    "addr:postcode":"32055",
    "addr:street":"W Us Hwy 90",
    "iso:country":"US",
    "sg:address":"2016 W US Hwy 90",
    "sg:city":"Lake City",
    "sg:classifiers":[
        {
            "category":"Travel",
            "subcategory":"Hotels & Motels",
            "type":"Entertainment"
        }
    ],
    "sg:phone":"+1 386 752 8334",
    "sg:postcode":"32055",
    "sg:province":"FL",
    "sg:tags":[
        "operation"
    ],
    "wof:name":"Piney Woods Lodge",
    "wof:placetype":"venue"
},
  "geometry": {"coordinates":[-82.653666,30.18555],"type":"Point"}
}