{
  "type": "Feature",
  "properties": {
    "iso:country":"US",
    "sg:address":"601 S Lake Destiny Rd",
    "sg:city":"Maitland",
    "sg:classifiers":[
        {
            "category":"Restaurant",
            "type":"Food & Drink"
        }
    ],
    "sg:phone":"+1 407 660 9260",
    "sg:postcode":"32751",
    "sg:province":"FL",
    "sg:tags":[
        "eating"
    ],
    "wof:name":"Maitland Green Cafe",
    "wof:placetype":"venue"
},
  "geometry": {"coordinates":[-81.38715999999999,28.620898],"type":"Point"}
}