{
  "type": "Feature",
  "properties": {
    "addr:full":"12601 State Rd 545 Winter Garden FL 34787",
    "addr:housenumber":"12601;545",
    "addr:postcode":"34787",
    "addr:street":"State Rd",
    "iso:country":"US",
    "sg:address":"12601 State Rd 545",
    "sg:city":"Winter Garden",
    "sg:classifiers":[
        {
            "category":"Building & Trades",
            "subcategory":"Construction",
            "type":"Services"
        }
    ],
    "sg:phone":"+1 407 238 0034",
    "sg:postcode":"34787",
    "sg:province":"FL",
    "sg:tags":[
        "concrete",
        "contractor"
    ],
    "wof:name":"Reliante Construction Group",
    "wof:placetype":"venue"
},
  "geometry": {"coordinates":[-81.6413,28.384333],"type":"Point"}
}