{
  "type": "Feature",
  "properties": {
    "addr:full":"5475 54th Ave N St Petersburg FL 33709",
    "addr:housenumber":"5475",
    "addr:postcode":"33709",
    "addr:street":"54Th Ave N",
    "iso:country":"US",
    "sg:address":"5475 54th Ave N",
    "sg:city":"St Petersburg",
    "sg:classifiers":[
        {
            "category":"Organizations",
            "subcategory":"Religious Organization",
            "type":"Services"
        }
    ],
    "sg:phone":"+1 727 525 7496",
    "sg:postcode":"33709",
    "sg:province":"FL",
    "sg:tags":[
        "church"
    ],
    "wof:name":"Family Fellowship Of St Pete",
    "wof:placetype":"venue"
},
  "geometry": {"coordinates":[-82.707796,27.821086],"type":"Point"}
}