{
  "type": "Feature",
  "properties": {
    "iso:country":"US",
    "sg:address":"2200 Seacrest Blvd",
    "sg:city":"Delray Beach",
    "sg:classifiers":[
        {
            "category":"Food & Beverages",
            "subcategory":"Groceries & Convenience Stores",
            "type":"Retail Goods"
        }
    ],
    "sg:phone":"+1 561 274 7476",
    "sg:postcode":"33444",
    "sg:province":"FL",
    "wof:name":"Kwik Stop Market",
    "wof:placetype":"venue"
},
  "geometry": {"coordinates":[-80.071285,26.486651],"type":"Point"}
}