{
  "type": "Feature",
  "properties": {
    "addr:full":"3047 Paddle Creek Dr Jacksonville FL 32223",
    "addr:housenumber":"3047",
    "addr:postcode":"32223",
    "addr:street":"Paddle Creek Dr",
    "iso:country":"US",
    "sg:address":"3047 Paddle Creek Dr",
    "sg:city":"Jacksonville",
    "sg:classifiers":[
        {
            "category":"Personal",
            "subcategory":"Beauty Salon",
            "type":"Services"
        }
    ],
    "sg:phone":"+1 904 268 5914",
    "sg:postcode":"32223",
    "sg:province":"FL",
    "sg:tags":[
        "shop"
    ],
    "wof:name":"Kaleel Hair Stylist",
    "wof:placetype":"venue"
},
  "geometry": {"coordinates":[-81.62983800000001,30.145764],"type":"Point"}
}