{
  "type": "Feature",
  "properties": {
    "iso:country":"US",
    "sg:address":"19190 San Carlos Blvd",
    "sg:city":"Fort Myers Beach",
    "sg:classifiers":[
        {
            "category":"Shopping",
            "subcategory":"Computers & Home Electronics",
            "type":"Retail Goods"
        }
    ],
    "sg:phone":"+1 239 463 3500",
    "sg:postcode":"33931",
    "sg:province":"FL",
    "sg:tags":[
        "marine",
        "e",
        "sales",
        "for",
        "dealer"
    ],
    "wof:name":"Heinz Marine Electronics",
    "wof:placetype":"venue"
},
  "geometry": {"coordinates":[-81.952147,26.463156],"type":"Point"}
}