{
  "type": "Feature",
  "properties": {
    "addr:full":"4070 Herschel St Jacksonville FL 32210",
    "addr:housenumber":"4070",
    "addr:postcode":"32210",
    "addr:street":"Herschel St",
    "iso:country":"US",
    "sg:address":"4070 Herschel St",
    "sg:city":"Jacksonville",
    "sg:classifiers":[
        {
            "category":"Professional",
            "subcategory":"Management & Consulting",
            "type":"Services"
        }
    ],
    "sg:phone":"+1 904 388 1650",
    "sg:postcode":"32210",
    "sg:province":"FL",
    "sg:tags":[
        "counselor",
        "public",
        "relations"
    ],
    "wof:name":"Creative Group",
    "wof:placetype":"venue"
},
  "geometry": {"coordinates":[-81.713471,30.289552],"type":"Point"}
}