{
  "type": "Feature",
  "properties": {
    "addr:full":"2309 S Ridgewood Ave Daytona Beach FL 32119",
    "addr:housenumber":"2309",
    "addr:postcode":"32119",
    "addr:street":"S Ridgewood Ave",
    "iso:country":"US",
    "sg:address":"2309 S Ridgewood Ave",
    "sg:city":"Daytona Beach",
    "sg:classifiers":[
        {
            "category":"Restaurant",
            "type":"Food & Drink"
        }
    ],
    "sg:phone":"+1 386 760 0300",
    "sg:postcode":"32119",
    "sg:province":"FL",
    "sg:tags":[
        "eating"
    ],
    "wof:name":"Songkran Thai Restaurant",
    "wof:placetype":"venue"
},
  "geometry": {"coordinates":[-80.998813,29.16577],"type":"Point"}
}