{
  "type": "Feature",
  "properties": {
    "iso:country":"US",
    "sg:address":"656 Beal Pkwy NW",
    "sg:city":"Fort Walton Beach",
    "sg:classifiers":[
        {
            "category":"Shopping",
            "subcategory":"Clothing, Apparel, & Fashions",
            "type":"Retail Goods"
        }
    ],
    "sg:phone":"+1 850 862 7577",
    "sg:postcode":"32547",
    "sg:province":"FL",
    "wof:name":"Sues Beauty Care",
    "wof:placetype":"venue"
},
  "geometry": {"coordinates":[-86.639301,30.433808],"type":"Point"}
}