{
  "type": "Feature",
  "properties": {
    "addr:full":"101 NE 23rd St Miami FL 33137",
    "addr:housenumber":"101",
    "addr:postcode":"33137",
    "addr:street":"Ne 23Rd St",
    "iso:country":"US",
    "sg:address":"101 NE 23rd St",
    "sg:city":"Miami",
    "sg:classifiers":[
        {
            "category":"Wholesale",
            "subcategory":"Durable Goods & Equipment",
            "type":"Manufacturing & Wholesale Goods"
        }
    ],
    "sg:phone":"+1 305 325 8118",
    "sg:postcode":"33137",
    "sg:province":"FL",
    "sg:tags":[
        "importer",
        "shoe",
        "store"
    ],
    "sg:website":"www.glamourfootwear.com",
    "wof:name":"Glamour Footwear Corp",
    "wof:placetype":"venue"
},
  "geometry": {"coordinates":[-80.192398,25.799101],"type":"Point"}
}