{
  "type": "Feature",
  "properties": {
    "iso:country":"US",
    "sg:address":"5817 12th St E",
    "sg:city":"Bradenton",
    "sg:classifiers":[
        {
            "category":"Building & Trades",
            "subcategory":"Plumbing",
            "type":"Services"
        }
    ],
    "sg:phone":"+1 941 755 8015",
    "sg:postcode":"34203",
    "sg:province":"FL",
    "sg:tags":[
        "heating",
        "solar",
        "contractor"
    ],
    "wof:name":"Westcoast Solar Svc",
    "wof:placetype":"venue"
},
  "geometry": {"coordinates":[-82.550781,27.440282],"type":"Point"}
}