{
  "type": "Feature",
  "properties": {
    "iso:country":"US",
    "sg:address":"8702 N Lake Dasha Dr",
    "sg:city":"Plantation",
    "sg:classifiers":[
        {
            "category":"Wholesale",
            "subcategory":"Durable Goods & Equipment",
            "type":"Manufacturing & Wholesale Goods"
        }
    ],
    "sg:phone":"+1 954 423 3666",
    "sg:postcode":"33324",
    "sg:province":"FL",
    "sg:tags":[
        "representative",
        "manufacturer"
    ],
    "wof:name":"Suncoast Sports",
    "wof:placetype":"venue"
},
  "geometry": {"coordinates":[-80.264686,26.115391],"type":"Point"}
}