{
  "type": "Feature",
  "properties": {
    "iso:country":"US",
    "sg:address":"206 E Ocean Ave",
    "sg:city":"Boynton Beach",
    "sg:classifiers":[
        {
            "category":"Food & Beverages",
            "subcategory":"Bakery",
            "type":"Retail Goods"
        }
    ],
    "sg:phone":"+1 561 585 0222",
    "sg:postcode":"33435",
    "sg:province":"FL",
    "sg:tags":[
        "baker"
    ],
    "wof:name":"Palm Beach Bakery & Cafe",
    "wof:placetype":"venue"
},
  "geometry": {"coordinates":[-80.060737,26.527014],"type":"Point"}
}