{
  "type": "Feature",
  "properties": {
    "iso:country":"US",
    "sg:address":"5455 Verna Blvd",
    "sg:city":"Jacksonville",
    "sg:classifiers":[
        {
            "category":"Government",
            "subcategory":"Post Office",
            "type":"Public Place"
        }
    ],
    "sg:phone":"+1 904 781 2651",
    "sg:postcode":"32205",
    "sg:province":"FL",
    "sg:tags":[
        "postal",
        "us"
    ],
    "wof:name":"Murray Hill Station",
    "wof:placetype":"venue"
},
  "geometry": {"coordinates":[-81.737206,30.312402],"type":"Point"}
}