{
  "type": "Feature",
  "properties": {
    "iso:country":"US",
    "sg:address":"994 SW Lighthouse Dr",
    "sg:city":"Palm City",
    "sg:classifiers":[
        {
            "category":"Utilities",
            "subcategory":"Electric",
            "type":"Services"
        }
    ],
    "sg:phone":"+1 772 220 4480",
    "sg:postcode":"34990",
    "sg:province":"FL",
    "wof:name":"Direct Electric Inc",
    "wof:placetype":"venue"
},
  "geometry": {"coordinates":[-80.276466,27.190801],"type":"Point"}
}