{
  "type": "Feature",
  "properties": {
    "addr:full":"835 96th St Ocean Marathon FL 33050",
    "addr:housenumber":"835",
    "addr:postcode":"33050",
    "addr:street":"96Th St",
    "iso:country":"US",
    "sg:address":"835 96th St Ocean",
    "sg:city":"Marathon",
    "sg:classifiers":[
        {
            "category":"Building & Trades",
            "subcategory":"Plumbing",
            "type":"Services"
        }
    ],
    "sg:phone":"+1 305 743 6315",
    "sg:postcode":"33050",
    "sg:province":"FL",
    "sg:tags":[
        "contractor"
    ],
    "wof:name":"Sam Williams Co",
    "wof:placetype":"venue"
},
  "geometry": {"coordinates":[-81.046835,24.723721],"type":"Point"}
}