{
  "type": "Feature",
  "properties": {
    "addr:full":"6370 15th St E Sarasota FL 34243",
    "addr:housenumber":"6370",
    "addr:postcode":"34243",
    "addr:street":"15Th St E",
    "iso:country":"US",
    "sg:address":"6370 15th St E",
    "sg:city":"Sarasota",
    "sg:classifiers":[
        {
            "category":"Museum",
            "type":"Entertainment"
        }
    ],
    "sg:phone":"+1 941 752 9031",
    "sg:postcode":"34243",
    "sg:province":"FL",
    "sg:tags":[
        "organization",
        "arts",
        "information"
    ],
    "wof:name":"Arts Billiards",
    "wof:placetype":"venue"
},
  "geometry": {"coordinates":[-82.54677100000001,27.427247],"type":"Point"}
}