{
  "type": "Feature",
  "properties": {
    "iso:country":"US",
    "sg:address":"95 Brookwood Dr",
    "sg:city":"Ormond Beach",
    "sg:classifiers":[
        {
            "category":"Arts & Performance",
            "subcategory":"Theater",
            "type":"Entertainment"
        }
    ],
    "sg:phone":"+1 386 677 1101",
    "sg:postcode":"32174",
    "sg:province":"FL",
    "sg:tags":[
        "group"
    ],
    "wof:name":"Fisher-Lyons Entertament Inc",
    "wof:placetype":"venue"
},
  "geometry": {"coordinates":[-81.089659,29.276976],"type":"Point"}
}