{
  "type": "Feature",
  "properties": {
    "addr:full":"1840 NW 49th St Miami FL 33142",
    "addr:housenumber":"1840",
    "addr:postcode":"33142",
    "addr:street":"Nw 49Th St",
    "iso:country":"US",
    "sg:address":"1840 NW 49th St",
    "sg:city":"Miami",
    "sg:classifiers":[
        {
            "category":"Health Services",
            "subcategory":"Optometrist",
            "type":"Services"
        }
    ],
    "sg:phone":"+1 305 828 0201",
    "sg:postcode":"33142",
    "sg:province":"FL",
    "sg:tags":[
        "ophthalmologist"
    ],
    "wof:name":"Bustillo Andres MD",
    "wof:placetype":"venue"
},
  "geometry": {"coordinates":[-80.227243,25.81972],"type":"Point"}
}