{
  "type": "Feature",
  "properties": {
    "addr:full":"459 Branscomb Rd Green Cove Spgs FL 32043",
    "addr:housenumber":"459",
    "addr:postcode":"32043",
    "addr:street":"Branscomb Rd",
    "iso:country":"US",
    "sg:address":"459 Branscomb Rd",
    "sg:city":"Green Cove Spgs",
    "sg:classifiers":[
        {
            "category":"Building & Trades",
            "subcategory":"Construction",
            "type":"Services"
        }
    ],
    "sg:phone":"+1 904 291 3338",
    "sg:postcode":"32043",
    "sg:province":"FL",
    "sg:tags":[
        "utility",
        "contractor"
    ],
    "wof:name":"Grade One Sight & Utility",
    "wof:placetype":"venue"
},
  "geometry": {"coordinates":[-81.82496999999999,30.048419],"type":"Point"}
}