{
  "type": "Feature",
  "properties": {
    "addr:full":"1904 Honda Dr Fort Myers FL 33907",
    "addr:housenumber":"1904",
    "addr:postcode":"33907",
    "addr:street":"Honda Dr",
    "iso:country":"US",
    "sg:address":"1904 Honda Dr",
    "sg:city":"Fort Myers",
    "sg:classifiers":[
        {
            "category":"Retail",
            "subcategory":"Repair Shop",
            "type":"Services"
        }
    ],
    "sg:phone":"+1 239 267 4727",
    "sg:postcode":"33907",
    "sg:province":"FL",
    "sg:tags":[
        "welding"
    ],
    "wof:name":"Diversified Welding & Mach",
    "wof:placetype":"venue"
},
  "geometry": {"coordinates":[-81.873361,26.579048],"type":"Point"}
}