{
  "type": "Feature",
  "properties": {
    "iso:country":"US",
    "sg:address":"1225 Park Ave",
    "sg:city":"Orange Park",
    "sg:classifiers":[
        {
            "category":"Building & Trades",
            "subcategory":"Construction",
            "type":"Services"
        }
    ],
    "sg:phone":"+1 904 269 7277",
    "sg:postcode":"32073",
    "sg:province":"FL",
    "sg:tags":[
        "swimming",
        "contractor",
        "pool",
        "supply"
    ],
    "sg:website":"www.stanleypools.com",
    "wof:name":"Stanley Pools Inc",
    "wof:placetype":"venue"
},
  "geometry": {"coordinates":[-81.701424,30.174535],"type":"Point"}
}