{
  "type": "Feature",
  "properties": {
    "iso:country":"US",
    "sg:address":"2644 Sabal Springs Dr # 3",
    "sg:city":"Clearwater",
    "sg:classifiers":[
        {
            "category":"Shopping",
            "subcategory":"Computers & Home Electronics",
            "type":"Retail Goods"
        },
        {
            "category":"Wholesale",
            "subcategory":"Computers",
            "type":"Manufacturing & Wholesale Goods"
        }
    ],
    "sg:phone":"+1 727 797 1836",
    "sg:postcode":"33761",
    "sg:province":"FL",
    "sg:tags":[
        "equipment",
        "printer",
        "supply"
    ],
    "wof:name":"W H Quill & Associates",
    "wof:placetype":"venue"
},
  "geometry": {"coordinates":[-82.727102,28.021893],"type":"Point"}
}