{
  "type": "Feature",
  "properties": {
    "addr:full":"2012 Curry Ford Rd Orlando FL 32806",
    "addr:housenumber":"2012",
    "addr:postcode":"32806",
    "addr:street":"Curry Ford Rd",
    "iso:country":"US",
    "sg:address":"2012 Curry Ford Rd",
    "sg:city":"Orlando",
    "sg:classifiers":[
        {
            "category":"Building & Trades",
            "subcategory":"Electrical",
            "type":"Services"
        }
    ],
    "sg:phone":"+1 407 895 7075",
    "sg:postcode":"32806",
    "sg:province":"FL",
    "sg:tags":[
        "industrial",
        "electrician",
        "contractors-commercial",
        "electric"
    ],
    "wof:name":"Southeast Electric-Central Fl",
    "wof:placetype":"venue"
},
  "geometry": {"coordinates":[-81.35468899999999,28.524071],"type":"Point"}
}