{
  "type": "Feature",
  "properties": {
    "addr:full":"14500 SW 252nd St Homestead FL 33032",
    "addr:housenumber":"14500",
    "addr:postcode":"33032",
    "addr:street":"Sw 252Nd St",
    "iso:country":"US",
    "sg:address":"14500 SW 252nd St",
    "sg:city":"Homestead",
    "sg:classifiers":[
        {
            "category":"Retail",
            "subcategory":"Veterinary Services",
            "type":"Services"
        }
    ],
    "sg:phone":"+1 786 457 0687",
    "sg:postcode":"33032",
    "sg:province":"FL",
    "sg:tags":[
        "clinic",
        "hospital"
    ],
    "wof:name":"The Vet Smith",
    "wof:placetype":"venue"
},
  "geometry": {"coordinates":[-80.42636899999999,25.532709],"type":"Point"}
}