{
  "type": "Feature",
  "properties": {
    "iso:country":"US",
    "sg:address":"3940 NW 48 Pl",
    "sg:city":"Gainesville",
    "sg:classifiers":[
        {
            "category":"Professional",
            "subcategory":"Accounting & Tax Preparation",
            "type":"Services"
        }
    ],
    "sg:phone":"+1 352 377 2864",
    "sg:postcode":"32606",
    "sg:province":"FL",
    "sg:tags":[
        "return",
        "filing"
    ],
    "wof:name":"Pearl Griffin Tax Svc",
    "wof:placetype":"venue"
},
  "geometry": {"coordinates":[-82.38355,29.699126],"type":"Point"}
}