{
  "type": "Feature",
  "properties": {
    "iso:country":"US",
    "sg:address":"127 Hillcrest Dr",
    "sg:city":"Cocoa",
    "sg:classifiers":[
        {
            "category":"Banks & Credit Unions",
            "subcategory":"Investment Brokerage",
            "type":"Services"
        }
    ],
    "sg:phone":"+1 321 636 6103",
    "sg:postcode":"32922",
    "sg:province":"FL",
    "sg:tags":[
        "tape",
        "video",
        "sale",
        "dvds-rental"
    ],
    "wof:name":"Eugene F Hoard Video Promotions",
    "wof:placetype":"venue"
},
  "geometry": {"coordinates":[-80.733851,28.365495],"type":"Point"}
}