{
  "type": "Feature",
  "properties": {
    "iso:country":"US",
    "sg:address":"5001 4th St N",
    "sg:city":"Saint Petersburg",
    "sg:classifiers":[
        {
            "category":"Health Services",
            "subcategory":"Chiropractor",
            "type":"Services"
        }
    ],
    "sg:phone":"+1 727 327 3412",
    "sg:postcode":"33703",
    "sg:province":"FL",
    "wof:name":"Frank Cannarozzo DC PC",
    "wof:placetype":"venue"
},
  "geometry": {"coordinates":[-82.638656,27.818482],"type":"Point"}
}