{
  "type": "Feature",
  "properties": {
    "addr:full":"6676 US Hwy 1 Port Saint Lucie FL 34952",
    "addr:housenumber":"6676",
    "addr:postcode":"34952",
    "addr:street":"Us Hwy 1",
    "iso:country":"US",
    "sg:address":"6676 US Hwy 1",
    "sg:city":"Port Saint Lucie",
    "sg:classifiers":[
        {
            "category":"Utilities",
            "subcategory":"Mobile Phone",
            "type":"Services"
        }
    ],
    "sg:phone":"+1 772 284 6589",
    "sg:postcode":"34952",
    "sg:province":"FL",
    "sg:tags":[
        "communication",
        "radiotelephone"
    ],
    "wof:name":"Central Florida Cellular",
    "wof:placetype":"venue"
},
  "geometry": {"coordinates":[-80.325811,27.340854],"type":"Point"}
}