{
  "type": "Feature",
  "properties": {
    "iso:country":"US",
    "sg:address":"3886 SW 30th St",
    "sg:city":"Hollywood",
    "sg:classifiers":[
        {
            "category":"Building & Trades",
            "subcategory":"Electrical",
            "type":"Services"
        }
    ],
    "sg:phone":"+1 954 792 5444",
    "sg:postcode":"33023",
    "sg:province":"FL",
    "sg:tags":[
        "electrical",
        "contractor"
    ],
    "wof:name":"Universal Electrical Serv",
    "wof:placetype":"venue"
},
  "geometry": {"coordinates":[-80.181725,25.983895],"type":"Point"}
}