{
  "type": "Feature",
  "properties": {
    "addr:full":"1600 S Dixie Hwy Boca Raton FL 33432",
    "addr:housenumber":"1600",
    "addr:postcode":"33432",
    "addr:street":"S Dixie Hwy",
    "iso:country":"US",
    "sg:address":"1600 S Dixie Hwy",
    "sg:city":"Boca Raton",
    "sg:classifiers":[
        {
            "category":"Building & Trades",
            "subcategory":"Equipment Rental",
            "type":"Services"
        }
    ],
    "sg:phone":"+1 561 338 0790",
    "sg:postcode":"33432",
    "sg:province":"FL",
    "sg:tags":[
        "leasing"
    ],
    "wof:name":"Associated Leasing Intl Corp",
    "wof:placetype":"venue"
},
  "geometry": {"coordinates":[-80.0903,26.334457],"type":"Point"}
}