{
  "type": "Feature",
  "properties": {
    "iso:country":"US",
    "sg:address":"5928 SW 152nd Ct",
    "sg:city":"Miami",
    "sg:classifiers":[
        {
            "category":"Wholesale",
            "subcategory":"Non-durable Goods",
            "type":"Manufacturing & Wholesale Goods"
        }
    ],
    "sg:phone":"+1 305 408 8859",
    "sg:postcode":"33193",
    "sg:province":"FL",
    "wof:name":"Vene Movil Export & Impor",
    "wof:placetype":"venue"
},
  "geometry": {"coordinates":[-80.439932,25.710711],"type":"Point"}
}