{
  "type": "Feature",
  "properties": {
    "iso:country":"US",
    "sg:address":"17634 Bridle Ln",
    "sg:city":"Jupiter",
    "sg:classifiers":[
        {
            "category":"Shopping",
            "type":"Retail Goods"
        }
    ],
    "sg:phone":"+1 561 741 2050",
    "sg:postcode":"33478",
    "sg:province":"FL",
    "sg:tags":[
        "merchandise"
    ],
    "wof:name":"Senior Discounts On Line Inc",
    "wof:placetype":"venue"
},
  "geometry": {"coordinates":[-80.204194,26.940208],"type":"Point"}
}