{
  "type": "Feature",
  "properties": {
    "iso:country":"US",
    "sg:address":"540 Old Geneva Rd",
    "sg:city":"Geneva",
    "sg:classifiers":[
        {
            "category":"Freight",
            "type":"Transportation"
        }
    ],
    "sg:phone":"+1 407 349 9070",
    "sg:postcode":"32732",
    "sg:province":"FL",
    "sg:tags":[
        "hauling",
        "trucking"
    ],
    "wof:name":"C R Barrett & Son Svc",
    "wof:placetype":"venue"
},
  "geometry": {"coordinates":[-81.11964999999999,28.751941],"type":"Point"}
}