{
  "type": "Feature",
  "properties": {
    "iso:country":"US",
    "sg:address":"5157 SW 87th Ave",
    "sg:city":"Fort Lauderdale",
    "sg:classifiers":[
        {
            "category":"Building & Trades",
            "subcategory":"Landscaping Services",
            "type":"Services"
        }
    ],
    "sg:phone":"+1 954 680 9919",
    "sg:postcode":"33328",
    "sg:province":"FL",
    "sg:tags":[
        "landscape"
    ],
    "wof:name":"Entec Diversified Services",
    "wof:placetype":"venue"
},
  "geometry": {"coordinates":[-80.26123800000001,26.059309],"type":"Point"}
}