{
  "type": "Feature",
  "properties": {
    "iso:country":"US",
    "sg:address":"3809 W Platt St",
    "sg:city":"Tampa",
    "sg:classifiers":[
        {
            "category":"Banks & Credit Unions",
            "subcategory":"Bank",
            "type":"Services"
        }
    ],
    "sg:phone":"+1 813 875 3100",
    "sg:postcode":"33609",
    "sg:province":"FL",
    "sg:tags":[
        "consultant",
        "flow"
    ],
    "wof:name":"Power Funding Works",
    "wof:placetype":"venue"
},
  "geometry": {"coordinates":[-82.50773100000001,27.942174],"type":"Point"}
}