{
  "type": "Feature",
  "properties": {
    "iso:country":"US",
    "sg:address":"705 Northwest Dr SW",
    "sg:city":"Live Oak",
    "sg:classifiers":[
        {
            "category":"Real Estate",
            "subcategory":"Real Estate Operator",
            "type":"Services"
        }
    ],
    "sg:phone":"+1 386 364 7936",
    "sg:postcode":"32064",
    "sg:province":"FL",
    "sg:tags":[
        "building",
        "apartment"
    ],
    "wof:name":"Village Oaks Apartments",
    "wof:placetype":"venue"
},
  "geometry": {"coordinates":[-82.999234,30.281024],"type":"Point"}
}