{
  "type": "Feature",
  "properties": {
    "addr:full":"1869 Laurelwood Ln Dunedin FL 34698",
    "addr:housenumber":"1869",
    "addr:postcode":"34698",
    "addr:street":"Laurelwood Ln",
    "iso:country":"US",
    "sg:address":"1869 Laurelwood Ln",
    "sg:city":"Dunedin",
    "sg:classifiers":[
        {
            "category":"Freight",
            "type":"Transportation"
        }
    ],
    "sg:phone":"+1 727 738 4110",
    "sg:postcode":"34698",
    "sg:province":"FL",
    "sg:tags":[
        "operator",
        "trucking"
    ],
    "wof:name":"Richard Alan Whitbeck",
    "wof:placetype":"venue"
},
  "geometry": {"coordinates":[-82.749567,28.033933],"type":"Point"}
}