{
  "type": "Feature",
  "properties": {
    "addr:full":"3860 Magnolia St Middleburg FL 32068",
    "addr:housenumber":"3860",
    "addr:postcode":"32068",
    "addr:street":"Magnolia St",
    "iso:country":"US",
    "sg:address":"3860 Magnolia St",
    "sg:city":"Middleburg",
    "sg:classifiers":[
        {
            "category":"Travel",
            "subcategory":"Travel Agent",
            "type":"Entertainment"
        },
        {
            "category":"Retail",
            "subcategory":"Auto Rental",
            "type":"Services"
        },
        {
            "category":"Bus Charters",
            "type":"Transportation"
        },
        {
            "category":"Landmark",
            "subcategory":"Tourist Attraction",
            "type":"Public Place"
        },
        {
            "category":"Landmark",
            "subcategory":"Tourist Information",
            "type":"Public Place"
        }
    ],
    "sg:phone":"+1 904 282 8500",
    "sg:postcode":"32068",
    "sg:province":"FL",
    "sg:tags":[
        "agency",
        "promoter",
        "tour",
        "tours-operators",
        "buses-charter",
        "limousine",
        "sightseeing"
    ],
    "sg:website":"http://www.tourtimeinc.com",
    "wof:name":"TourTime Inc",
    "wof:placetype":"venue"
},
  "geometry": {"coordinates":[-81.862167,30.073835],"type":"Point"}
}