{
  "type": "Feature",
  "properties": {
    "iso:country":"US",
    "sg:address":"278 John Rd",
    "sg:city":"Holt",
    "sg:classifiers":[
        {
            "category":"Shopping",
            "subcategory":"Bicycles & Sporting Goods",
            "type":"Retail Goods"
        }
    ],
    "sg:phone":"+1 850 537 2879",
    "sg:postcode":"32564",
    "sg:province":"FL",
    "wof:name":"Sues Bait & Snacks",
    "wof:placetype":"venue"
},
  "geometry": {"coordinates":[-86.76599299999999,30.713562],"type":"Point"}
}