{
  "type": "Feature",
  "properties": {
    "iso:country":"US",
    "sg:address":"1710 S Federal Hwy",
    "sg:city":"Fort Lauderdale",
    "sg:classifiers":[
        {
            "category":"Restaurant",
            "type":"Food & Drink"
        }
    ],
    "sg:phone":"+1 954 524 8200",
    "sg:postcode":"33316",
    "sg:province":"FL",
    "wof:name":"Tokyo Bowl",
    "wof:placetype":"venue"
},
  "geometry": {"coordinates":[-80.136572,26.099451],"type":"Point"}
}