{
  "type": "Feature",
  "properties": {
    "addr:full":"245 SE 5th Ave Delray Beach FL 33483",
    "addr:housenumber":"245",
    "addr:postcode":"33483",
    "addr:street":"Se 5Th Ave",
    "iso:country":"US",
    "sg:address":"245 SE 5th Ave",
    "sg:city":"Delray Beach",
    "sg:classifiers":[
        {
            "category":"Health Services",
            "subcategory":"Chiropractor",
            "type":"Services"
        }
    ],
    "sg:phone":"+1 561 278 2727",
    "sg:postcode":"33483",
    "sg:province":"FL",
    "wof:name":"Shore Chiropractic PA",
    "wof:placetype":"venue"
},
  "geometry": {"coordinates":[-80.06787199999999,26.457002],"type":"Point"}
}