{
  "type": "Feature",
  "properties": {
    "iso:country":"US",
    "sg:address":"1123 Salerno Ct",
    "sg:city":"Orlando",
    "sg:classifiers":[
        {
            "category":"Banks & Credit Unions",
            "subcategory":"Financial Services",
            "type":"Services"
        }
    ],
    "sg:phone":"+1 407 245 8708",
    "sg:postcode":"32806",
    "sg:province":"FL",
    "sg:tags":[
        "investor"
    ],
    "wof:name":"Abelardo Investments LLC",
    "wof:placetype":"venue"
},
  "geometry": {"coordinates":[-81.36423000000001,28.509967],"type":"Point"}
}