{
  "type": "Feature",
  "properties": {
    "addr:full":"2136 Pinnacle Cir S Palm Harbor FL 34684",
    "addr:housenumber":"2136",
    "addr:postcode":"34684",
    "addr:street":"Pinnacle Cir S Palm",
    "iso:country":"US",
    "sg:address":"2136 Pinnacle Cir S",
    "sg:city":"Palm Harbor",
    "sg:classifiers":[
        {
            "category":"Building & Trades",
            "subcategory":"Construction",
            "type":"Services"
        }
    ],
    "sg:phone":"+1 727 787 0105",
    "sg:postcode":"34684",
    "sg:province":"FL",
    "sg:tags":[
        "carpentry",
        "contractor"
    ],
    "wof:name":"Dehart Carpentry Inc",
    "wof:placetype":"venue"
},
  "geometry": {"coordinates":[-82.721288,28.086735],"type":"Point"}
}