{
  "type": "Feature",
  "properties": {
    "iso:country":"US",
    "sg:address":"546 Lynneda Ave",
    "sg:city":"Fort Myers",
    "sg:classifiers":[
        {
            "category":"Social Services",
            "subcategory":"Child Care",
            "type":"Services"
        }
    ],
    "sg:phone":"+1 239 694 6502",
    "sg:postcode":"33905",
    "sg:province":"FL",
    "sg:tags":[
        "day"
    ],
    "wof:name":"Peter Pan Day Care Ctr",
    "wof:placetype":"venue"
},
  "geometry": {"coordinates":[-81.819596,26.670202],"type":"Point"}
}