{
  "type": "Feature",
  "properties": {
    "addr:full":"4240 NW 77 Ter Gainesville FL 32606",
    "addr:housenumber":"4240",
    "addr:postcode":"32606",
    "addr:street":"Nw 77 Ter",
    "iso:country":"US",
    "sg:address":"4240 NW 77 Ter",
    "sg:city":"Gainesville",
    "sg:classifiers":[
        {
            "category":"Building & Trades",
            "subcategory":"Construction",
            "type":"Services"
        }
    ],
    "sg:phone":"+1 352 379 0057",
    "sg:postcode":"32606",
    "sg:province":"FL",
    "sg:tags":[
        "stone",
        "setting",
        "contractor"
    ],
    "wof:name":"Moyer Marble & Tile Co",
    "wof:placetype":"venue"
},
  "geometry": {"coordinates":[-82.42483799999999,29.692442],"type":"Point"}
}