{
  "type": "Feature",
  "properties": {
    "iso:country":"US",
    "sg:address":"810 E 3rd Ave",
    "sg:city":"New Smyrna Beach",
    "sg:classifiers":[
        {
            "category":"Shopping",
            "subcategory":"Florist",
            "type":"Retail Goods"
        }
    ],
    "sg:phone":"+1 386 423 5927",
    "sg:postcode":"32169",
    "sg:province":"FL",
    "wof:name":"Pink Flamingo At Petals",
    "wof:placetype":"venue"
},
  "geometry": {"coordinates":[-80.894964,29.028848],"type":"Point"}
}