{
  "type": "Feature",
  "properties": {
    "iso:country":"US",
    "sg:address":"4241 Newland",
    "sg:city":"Clermont",
    "sg:classifiers":[
        {
            "category":"Wholesale",
            "subcategory":"Vending Machines",
            "type":"Manufacturing & Wholesale Goods"
        }
    ],
    "sg:phone":"+1 352 243 9537",
    "sg:postcode":"34711",
    "sg:province":"FL",
    "sg:tags":[
        "operator"
    ],
    "wof:name":"H&R Vendors Inc",
    "wof:placetype":"venue"
},
  "geometry": {"coordinates":[-81.709056,28.50315],"type":"Point"}
}