{
  "type": "Feature",
  "properties": {
    "addr:full":"3231 Garden St Titusville FL 32796",
    "addr:housenumber":"3231",
    "addr:postcode":"32796",
    "addr:street":"Garden St",
    "iso:country":"US",
    "sg:address":"3231 Garden St",
    "sg:city":"Titusville",
    "sg:classifiers":[
        {
            "category":"Wholesale",
            "subcategory":"Machinery & Supplies",
            "type":"Manufacturing & Wholesale Goods"
        }
    ],
    "sg:phone":"+1 321 269 1297",
    "sg:postcode":"32796",
    "sg:province":"FL",
    "sg:tags":[
        "shop",
        "equipment",
        "salon",
        "barber",
        "beauty"
    ],
    "wof:name":"Sally Beauty Supply 1246",
    "wof:placetype":"venue"
},
  "geometry": {"coordinates":[-80.843857,28.618982],"type":"Point"}
}