{
  "type": "Feature",
  "properties": {
    "iso:country":"US",
    "sg:address":"124 Flotto Ave",
    "sg:city":"Tampa",
    "sg:classifiers":[
        {
            "category":"Education",
            "subcategory":"School",
            "type":"Public Place"
        }
    ],
    "sg:phone":"+1 813 987 6903",
    "sg:postcode":"33617",
    "sg:province":"FL",
    "sg:tags":[
        "elementary"
    ],
    "wof:name":"Temple Terrace Elem School",
    "wof:placetype":"venue"
},
  "geometry": {"coordinates":[-82.391829,28.033478],"type":"Point"}
}