{
  "type": "Feature",
  "properties": {
    "addr:full":"72 Lakebluff Dr Ormond Beach FL 32174",
    "addr:housenumber":"72",
    "addr:postcode":"32174",
    "addr:street":"Lakebluff Dr",
    "iso:country":"US",
    "sg:address":"72 Lakebluff Dr",
    "sg:city":"Ormond Beach",
    "sg:classifiers":[
        {
            "category":"Retail",
            "subcategory":"Laundry & Dry Cleaning",
            "type":"Services"
        }
    ],
    "sg:phone":"+1 386 257 2075",
    "sg:postcode":"32174",
    "sg:province":"FL",
    "sg:tags":[
        "cleaners"
    ],
    "wof:name":"Divine Quality Cleaners",
    "wof:placetype":"venue"
},
  "geometry": {"coordinates":[-81.10833700000001,29.329433],"type":"Point"}
}