{
  "type": "Feature",
  "properties": {
    "iso:country":"US",
    "sg:address":"2403 W Oak Ridge Rd",
    "sg:city":"Orlando",
    "sg:classifiers":[
        {
            "category":"Shopping",
            "subcategory":"Department Store",
            "type":"Retail Goods"
        }
    ],
    "sg:phone":"+1 407 857 8356",
    "sg:postcode":"32809",
    "sg:province":"FL",
    "sg:tags":[
        "variety"
    ],
    "sg:website":"http://www.dollar.com",
    "wof:name":"Dolex Dollar Express Inc",
    "wof:placetype":"venue"
},
  "geometry": {"coordinates":[-81.411331,28.472401],"type":"Point"}
}