{
  "type": "Feature",
  "properties": {
    "iso:country":"US",
    "sg:address":"1520 Park Ave",
    "sg:city":"Orange Park",
    "sg:classifiers":[
        {
            "category":"Restaurant",
            "type":"Food & Drink"
        }
    ],
    "sg:menulink":"http://www.allmenus.com/fl/orange-park/99321-beef-obradys/menu/",
    "sg:phone":"+1 904 637 0385",
    "sg:postcode":"32073",
    "sg:province":"FL",
    "sg:tags":[
        "burger",
        "american",
        "wing",
        "pub"
    ],
    "wof:name":"Beef O'Brady's",
    "wof:placetype":"venue"
},
  "geometry": {"coordinates":[-81.70142199999999,30.172133],"type":"Point"}
}