{
  "type": "Feature",
  "properties": {
    "iso:country":"US",
    "sg:address":"4601 Seminole Pratt Whitney Rd",
    "sg:city":"Loxahatchee",
    "sg:classifiers":[
        {
            "category":"Education",
            "subcategory":"School",
            "type":"Public Place"
        }
    ],
    "sg:phone":"+1 561 422 2600",
    "sg:postcode":"33470",
    "sg:province":"FL",
    "sg:website":"http://www.palmbeach.k12.fl.us",
    "wof:name":"Seminole Ridge Cmnty High Schl",
    "wof:placetype":"venue"
},
  "geometry": {"coordinates":[-80.307693,26.746333],"type":"Point"}
}