{
  "type": "Feature",
  "properties": {
    "iso:country":"US",
    "sg:address":"1600 E 8th Ave",
    "sg:city":"Tampa",
    "sg:classifiers":[
        {
            "category":"Restaurant",
            "type":"Food & Drink"
        }
    ],
    "sg:phone":"+1 866 295 4203",
    "sg:postcode":"33605",
    "sg:province":"FL",
    "sg:tags":[
        "german",
        "american",
        "mexican",
        "french"
    ],
    "sg:website":"http://www.mjbarleyhoppers.com",
    "wof:name":"M.J. Barleyhoppers",
    "wof:placetype":"venue"
},
  "geometry": {"coordinates":[-82.44171799999999,27.960979],"type":"Point"}
}