{
  "type": "Feature",
  "properties": {
    "addr:full":"3176 S University Dr Miramar FL 33025",
    "addr:housenumber":"3176",
    "addr:postcode":"33025",
    "addr:street":"S University Dr",
    "iso:country":"US",
    "sg:address":"3176 S University Dr",
    "sg:city":"Miramar",
    "sg:classifiers":[
        {
            "category":"Professional",
            "type":"Services"
        }
    ],
    "sg:phone":"+1 954 447 4714",
    "sg:postcode":"33025",
    "sg:province":"FL",
    "sg:tags":[
        "establishment"
    ],
    "wof:name":"Dane Belth Group Inc",
    "wof:placetype":"venue"
},
  "geometry": {"coordinates":[-80.24694700000001,25.974942],"type":"Point"}
}