{
  "type": "Feature",
  "properties": {
    "iso:country":"US",
    "sg:address":"7875 N Federal Hwy",
    "sg:city":"Boca Raton",
    "sg:classifiers":[
        {
            "category":"Restaurant",
            "type":"Food & Drink"
        }
    ],
    "sg:menulink":"http://www.allmenus.com/fl/boca-raton/52647-orient-palace-restaurant/menu/",
    "sg:phone":"+1 561 997 7889",
    "sg:postcode":"33487",
    "sg:province":"FL",
    "sg:tags":[
        "asian",
        "chinese"
    ],
    "wof:name":"Orient Palace Restaurant",
    "wof:placetype":"venue"
},
  "geometry": {"coordinates":[-80.074293,26.420452],"type":"Point"}
}