{
  "type": "Feature",
  "properties": {
    "iso:country":"US",
    "sg:address":"11911 SW 35th Ter",
    "sg:city":"Miami",
    "sg:classifiers":[
        {
            "category":"Freight",
            "type":"Transportation"
        }
    ],
    "sg:phone":"+1 305 559 2561",
    "sg:postcode":"33175",
    "sg:province":"FL",
    "sg:tags":[
        "operator",
        "local",
        "trucking"
    ],
    "wof:name":"Jenroka Trucking Corp",
    "wof:placetype":"venue"
},
  "geometry": {"coordinates":[-80.388318,25.735722],"type":"Point"}
}