{
  "type": "Feature",
  "properties": {
    "iso:country":"US",
    "sg:address":"5000 N Main St",
    "sg:city":"Jacksonville",
    "sg:classifiers":[
        {
            "category":"Organizations",
            "subcategory":"Religious Organization",
            "type":"Services"
        }
    ],
    "sg:phone":"+1 904 388 6275",
    "sg:postcode":"32206",
    "sg:province":"FL",
    "sg:tags":[
        "church"
    ],
    "wof:name":"We'Re For Jesus House-Prayer",
    "wof:placetype":"venue"
},
  "geometry": {"coordinates":[-81.651748,30.370162],"type":"Point"}
}