{
  "type": "Feature",
  "properties": {
    "iso:country":"US",
    "sg:address":"16200 Bay Pointe Blvd",
    "sg:city":"Fort Myers",
    "sg:classifiers":[
        {
            "category":"Building & Trades",
            "subcategory":"Construction",
            "type":"Services"
        }
    ],
    "sg:phone":"+1 239 633 3917",
    "sg:postcode":"33917",
    "sg:province":"FL",
    "sg:tags":[
        "house"
    ],
    "wof:name":"Jared F Northrop Contractor",
    "wof:placetype":"venue"
},
  "geometry": {"coordinates":[-81.775262,26.71139],"type":"Point"}
}