{
  "type": "Feature",
  "properties": {
    "iso:country":"US",
    "sg:address":"2228 N University Dr",
    "sg:city":"Coral Springs",
    "sg:classifiers":[
        {
            "category":"Health Services",
            "subcategory":"Chiropractor",
            "type":"Services"
        }
    ],
    "sg:phone":"+1 954 752 0090",
    "sg:postcode":"33071",
    "sg:province":"FL",
    "wof:name":"Wechsel Pain & Rehabilitation",
    "wof:placetype":"venue"
},
  "geometry": {"coordinates":[-80.249847,26.258925],"type":"Point"}
}