{
  "type": "Feature",
  "properties": {
    "addr:full":"1532 S Federal Hwy Delray Beach FL 33483",
    "addr:housenumber":"1532",
    "addr:postcode":"33483",
    "addr:street":"S Federal Hwy",
    "iso:country":"US",
    "sg:address":"1532 S Federal Hwy",
    "sg:city":"Delray Beach",
    "sg:classifiers":[
        {
            "category":"Shopping",
            "subcategory":"Computers & Home Electronics",
            "type":"Retail Goods"
        }
    ],
    "sg:phone":"+1 561 279 2822",
    "sg:postcode":"33483",
    "sg:province":"FL",
    "sg:tags":[
        "game",
        "video"
    ],
    "wof:name":"EB Games",
    "wof:placetype":"venue"
},
  "geometry": {"coordinates":[-80.06704999999999,26.446783],"type":"Point"}
}