{
  "type": "Feature",
  "properties": {
    "iso:country":"US",
    "sg:address":"2716 Mendelin St",
    "sg:city":"Apopka",
    "sg:classifiers":[
        {
            "category":"Building & Trades",
            "subcategory":"Construction",
            "type":"Services"
        },
        {
            "category":"Home & Garden",
            "subcategory":"Furniture",
            "type":"Retail Goods"
        }
    ],
    "sg:phone":"+1 407 880 8096",
    "sg:postcode":"32703",
    "sg:province":"FL",
    "sg:tags":[
        "maker",
        "cabinet"
    ],
    "wof:name":"Paul A Friday",
    "wof:placetype":"venue"
},
  "geometry": {"coordinates":[-81.460836,28.676545],"type":"Point"}
}