{
  "type": "Feature",
  "properties": {
    "iso:country":"US",
    "sg:address":"515 Dona Dr",
    "sg:city":"Nokomis",
    "sg:classifiers":[
        {
            "category":"Health Services",
            "subcategory":"Podiatrist",
            "type":"Services"
        }
    ],
    "sg:phone":"+1 941 485 0205",
    "sg:postcode":"34275",
    "sg:province":"FL",
    "sg:tags":[
        "physician",
        "surgeons"
    ],
    "wof:name":"Boyd Robinson Dpm",
    "wof:placetype":"venue"
},
  "geometry": {"coordinates":[-82.44632900000001,27.120394],"type":"Point"}
}