{
  "type": "Feature",
  "properties": {
    "iso:country":"US",
    "sg:address":"5108 W Colonial Dr",
    "sg:city":"Orlando",
    "sg:classifiers":[
        {
            "category":"Building & Trades",
            "subcategory":"Equipment Rental",
            "type":"Services"
        },
        {
            "category":"Home & Garden",
            "subcategory":"Furniture",
            "type":"Retail Goods"
        }
    ],
    "sg:phone":"+1 407 290 5555",
    "sg:postcode":"32808",
    "sg:province":"FL",
    "sg:tags":[
        "renting",
        "yard",
        "leasing",
        "store",
        "contractors'"
    ],
    "sg:website":"http://www.rentacenter.com",
    "wof:name":"Rent A Center",
    "wof:placetype":"venue"
},
  "geometry": {"coordinates":[-81.44977,28.552387],"type":"Point"}
}