{
  "type": "Feature",
  "properties": {
    "addr:full":"8490 N Tamiami Trl Sarasota FL 34243",
    "addr:housenumber":"8490",
    "addr:postcode":"34243",
    "addr:street":"N Tamiami Trl",
    "iso:country":"US",
    "sg:address":"8490 N Tamiami Trl",
    "sg:city":"Sarasota",
    "sg:classifiers":[
        {
            "category":"Professional",
            "subcategory":"Management & Consulting",
            "type":"Services"
        }
    ],
    "sg:phone":"+1 941 371 7999",
    "sg:postcode":"34243",
    "sg:province":"FL",
    "sg:tags":[
        "consultant",
        "business"
    ],
    "wof:name":"Leedom & Assoc",
    "wof:placetype":"venue"
},
  "geometry": {"coordinates":[-82.56019499999999,27.390876],"type":"Point"}
}