{
  "type": "Feature",
  "properties": {
    "iso:country":"US",
    "sg:address":"10053 Lake Underhill Rd",
    "sg:city":"Orlando",
    "sg:classifiers":[
        {
            "category":"Freight",
            "type":"Transportation"
        }
    ],
    "sg:phone":"+1 407 382 0130",
    "sg:postcode":"32825",
    "sg:province":"FL",
    "sg:tags":[
        "commercial",
        "storage"
    ],
    "wof:name":"Shurgard Storage Ctr",
    "wof:placetype":"venue"
},
  "geometry": {"coordinates":[-81.240668,28.539436],"type":"Point"}
}