{
  "type": "Feature",
  "properties": {
    "addr:full":"3200 S Hiawassee Rd Orlando FL 32835",
    "addr:housenumber":"3200",
    "addr:postcode":"32835",
    "addr:street":"S Hiawassee Rd",
    "iso:country":"US",
    "sg:address":"3200 S Hiawassee Rd",
    "sg:city":"Orlando",
    "sg:classifiers":[
        {
            "category":"Banks & Credit Unions",
            "subcategory":"Investment Brokerage",
            "type":"Services"
        },
        {
            "category":"Banks & Credit Unions",
            "subcategory":"Bank",
            "type":"Services"
        },
        {
            "category":"Banks & Credit Unions",
            "subcategory":"Financial Services",
            "type":"Services"
        }
    ],
    "sg:phone":"+1 407 295 8300",
    "sg:postcode":"32835",
    "sg:province":"FL",
    "sg:tags":[
        "mutual",
        "retirement",
        "broker",
        "fund",
        "planning",
        "security",
        "bond",
        "stock"
    ],
    "sg:website":"http://www.edwardjones.com/en_US/fa/index.html&CIRN=760510",
    "wof:name":"Edward Jones - Financial Advisor: NEIL OEHLSTROM",
    "wof:placetype":"venue"
},
  "geometry": {"coordinates":[-81.48581799999999,28.507874],"type":"Point"}
}