{
  "type": "Feature",
  "properties": {
    "addr:full":"333 1st St N Jacksonville Beach FL 32250",
    "addr:housenumber":"333",
    "addr:postcode":"32250",
    "addr:street":"1St St N",
    "iso:country":"US",
    "sg:address":"333 1st St N",
    "sg:city":"Jacksonville Beach",
    "sg:classifiers":[
        {
            "category":"Professional",
            "subcategory":"Lawyer & Legal Services",
            "type":"Services"
        }
    ],
    "sg:phone":"+1 904 247 1755",
    "sg:postcode":"32250",
    "sg:province":"FL",
    "wof:name":"Anthony Berry Dirito Goode LLP",
    "wof:placetype":"venue"
},
  "geometry": {"coordinates":[-81.390134,30.291936],"type":"Point"}
}