{
  "type": "Feature",
  "properties": {
    "addr:full":"3838 Curry Ford Rd Orlando FL 32806",
    "addr:housenumber":"3838",
    "addr:postcode":"32806",
    "addr:street":"Curry Ford Rd",
    "iso:country":"US",
    "sg:address":"3838 Curry Ford Rd",
    "sg:city":"Orlando",
    "sg:classifiers":[
        {
            "category":"Personal",
            "subcategory":"Beauty Salon",
            "type":"Services"
        }
    ],
    "sg:phone":"+1 407 894 8193",
    "sg:postcode":"32806",
    "sg:province":"FL",
    "wof:name":"Alicia's Hair Fashions",
    "wof:placetype":"venue"
},
  "geometry": {"coordinates":[-81.336164,28.524138],"type":"Point"}
}