{
  "type": "Feature",
  "properties": {
    "iso:country":"US",
    "sg:address":"5976 Coral Ridge Dr",
    "sg:city":"Coral Springs",
    "sg:classifiers":[
        {
            "category":"Shopping",
            "subcategory":"Optical Goods",
            "type":"Retail Goods"
        }
    ],
    "sg:phone":"+1 954 227 2770",
    "sg:postcode":"33076",
    "sg:province":"FL",
    "wof:name":"Vision Unlimited Eyecare",
    "wof:placetype":"venue"
},
  "geometry": {"coordinates":[-80.27892300000001,26.304373],"type":"Point"}
}