{
  "type": "Feature",
  "properties": {
    "iso:country":"US",
    "sg:address":"251 S US Hwy 1",
    "sg:city":"Jupiter",
    "sg:classifiers":[
        {
            "category":"Personal",
            "subcategory":"Barber",
            "type":"Services"
        }
    ],
    "sg:phone":"+1 561 746 9853",
    "sg:postcode":"33477",
    "sg:province":"FL",
    "sg:tags":[
        "shop"
    ],
    "wof:name":"Village Square Barber Shop",
    "wof:placetype":"venue"
},
  "geometry": {"coordinates":[-80.079763,26.932202],"type":"Point"}
}