{
  "type": "Feature",
  "properties": {
    "iso:country":"US",
    "sg:address":"1726 Alvarado Ct",
    "sg:city":"Longwood",
    "sg:classifiers":[
        {
            "category":"Real Estate",
            "subcategory":"Real Estate Agent",
            "type":"Services"
        }
    ],
    "sg:phone":"+1 407 865 5438",
    "sg:postcode":"32779",
    "sg:province":"FL",
    "wof:name":"Re/Max",
    "wof:placetype":"venue"
},
  "geometry": {"coordinates":[-81.38976099999999,28.721044],"type":"Point"}
}