{
  "type": "Feature",
  "properties": {
    "iso:country":"US",
    "sg:address":"2200 Lake Dr",
    "sg:city":"Dunedin",
    "sg:classifiers":[
        {
            "category":"Recreation",
            "type":"Entertainment"
        }
    ],
    "sg:phone":"+1 727 669 1951",
    "sg:postcode":"34698",
    "sg:province":"FL",
    "sg:tags":[
        "parks"
    ],
    "wof:name":"John Chesnut Sr Park",
    "wof:placetype":"venue"
},
  "geometry": {"coordinates":[-82.742852,28.047815],"type":"Point"}
}