{
  "type": "Feature",
  "properties": {
    "addr:full":"9419 SE Maricamp Rd Ocala FL 34472",
    "addr:housenumber":"9419",
    "addr:postcode":"34472",
    "addr:street":"Se Maricamp Rd",
    "iso:country":"US",
    "sg:address":"9419 SE Maricamp Rd",
    "sg:city":"Ocala",
    "sg:classifiers":[
        {
            "category":"Retail",
            "subcategory":"Laundry & Dry Cleaning",
            "type":"Services"
        }
    ],
    "sg:phone":"+1 352 680 9617",
    "sg:postcode":"34472",
    "sg:province":"FL",
    "wof:name":"Ventrys Laundry Mat",
    "wof:placetype":"venue"
},
  "geometry": {"coordinates":[-81.984178,29.079414],"type":"Point"}
}