{
  "type": "Feature",
  "properties": {
    "iso:country":"US",
    "sg:address":"3412 SW 106th Ave",
    "sg:city":"Miami",
    "sg:classifiers":[
        {
            "category":"Insurance",
            "subcategory":"Insurance Agent",
            "type":"Services"
        }
    ],
    "sg:phone":"+1 305 222 1791",
    "sg:postcode":"33165",
    "sg:province":"FL",
    "wof:name":"Lap Insurance Services Inc",
    "wof:placetype":"venue"
},
  "geometry": {"coordinates":[-80.367009,25.736071],"type":"Point"}
}