{
  "type": "Feature",
  "properties": {
    "addr:full":"2001 NW 15th St Pompano Beach FL 33069",
    "addr:housenumber":"2001",
    "addr:postcode":"33069",
    "addr:street":"Nw 15Th St",
    "iso:country":"US",
    "sg:address":"2001 NW 15th St",
    "sg:city":"Pompano Beach",
    "sg:classifiers":[
        {
            "category":"Freight",
            "type":"Transportation"
        }
    ],
    "sg:phone":"+1 954 979 1122",
    "sg:postcode":"33069",
    "sg:province":"FL",
    "sg:tags":[
        "packaging",
        "shipping"
    ],
    "wof:name":"Craters Frghters Southeast Fla",
    "wof:placetype":"venue"
},
  "geometry": {"coordinates":[-80.15065199999999,26.24555],"type":"Point"}
}