{
  "type": "Feature",
  "properties": {
    "iso:country":"US",
    "sg:address":"1311 E Main St",
    "sg:city":"Lakeland",
    "sg:classifiers":[
        {
            "category":"Home & Garden",
            "subcategory":"Carpets & Floor Coverings",
            "type":"Retail Goods"
        }
    ],
    "sg:phone":"+1 863 688 1444",
    "sg:postcode":"33801",
    "sg:province":"FL",
    "sg:tags":[
        "dealer",
        "rug"
    ],
    "wof:name":"Fashion Floors Of Lakeland",
    "wof:placetype":"venue"
},
  "geometry": {"coordinates":[-81.93724899999999,28.044107],"type":"Point"}
}