{
  "type": "Feature",
  "properties": {
    "addr:full":"1355 NW 93rd Ct Miami FL 33172",
    "addr:housenumber":"1355",
    "addr:postcode":"33172",
    "addr:street":"Nw 93Rd Ct",
    "iso:country":"US",
    "sg:address":"1355 NW 93rd Ct",
    "sg:city":"Miami",
    "sg:classifiers":[
        {
            "category":"Wholesale",
            "subcategory":"Non-durable Goods",
            "type":"Manufacturing & Wholesale Goods"
        }
    ],
    "sg:phone":"+1 305 406 9878",
    "sg:postcode":"33172",
    "sg:province":"FL",
    "wof:name":"Ask Point Import & Export Inc",
    "wof:placetype":"venue"
},
  "geometry": {"coordinates":[-80.347601,25.7837],"type":"Point"}
}