{
  "type": "Feature",
  "properties": {
    "addr:full":"3522 Shore Line Cir Palm Harbor FL 34684",
    "addr:housenumber":"3522",
    "addr:postcode":"34684",
    "addr:street":"Shore Line Cir",
    "iso:country":"US",
    "sg:address":"3522 Shore Line Cir",
    "sg:city":"Palm Harbor",
    "sg:classifiers":[
        {
            "category":"Professional",
            "subcategory":"Lawyer & Legal Services",
            "type":"Services"
        }
    ],
    "sg:phone":"+1 727 787 7972",
    "sg:postcode":"34684",
    "sg:province":"FL",
    "wof:name":"Susan P Lentz Assoc",
    "wof:placetype":"venue"
},
  "geometry": {"coordinates":[-82.71776699999999,28.088807],"type":"Point"}
}