{
  "type": "Feature",
  "properties": {
    "iso:country":"US",
    "sg:address":"1131 Rosetta Dr",
    "sg:city":"Deltona",
    "sg:classifiers":[
        {
            "category":"Banks & Credit Unions",
            "subcategory":"Investment Brokerage",
            "type":"Services"
        }
    ],
    "sg:phone":"+1 386 860 6511",
    "sg:postcode":"32725",
    "sg:province":"FL",
    "sg:tags":[
        "security"
    ],
    "wof:name":"Edward Jones Co",
    "wof:placetype":"venue"
},
  "geometry": {"coordinates":[-81.219038,28.894384],"type":"Point"}
}