{
  "type": "Feature",
  "properties": {
    "iso:country":"US",
    "sg:address":"4002 SE 4th Ave",
    "sg:city":"Cape Coral",
    "sg:classifiers":[
        {
            "category":"Professional",
            "subcategory":"Business Services",
            "type":"Services"
        }
    ],
    "sg:phone":"+1 239 549 7647",
    "sg:postcode":"33904",
    "sg:province":"FL",
    "sg:tags":[
        "water",
        "treatment"
    ],
    "wof:name":"Bill Carroll Water Cond",
    "wof:placetype":"venue"
},
  "geometry": {"coordinates":[-81.966494,26.576894],"type":"Point"}
}