{
  "type": "Feature",
  "properties": {
    "iso:country":"US",
    "sg:address":"614 N Dixie Hwy",
    "sg:city":"Hollywood",
    "sg:classifiers":[
        {
            "category":"Autos & Motor Vehicles",
            "subcategory":"Automobile Sales",
            "type":"Retail Goods"
        }
    ],
    "sg:phone":"+1 954 923 9277",
    "sg:postcode":"33020",
    "sg:province":"FL",
    "sg:tags":[
        "used"
    ],
    "wof:name":"SunTrust Motors",
    "wof:placetype":"venue"
},
  "geometry": {"coordinates":[-80.149576,26.017329],"type":"Point"}
}