{
  "type": "Feature",
  "properties": {
    "iso:country":"US",
    "sg:address":"1501 Co Rd 315",
    "sg:city":"Green Cove Spgs",
    "sg:classifiers":[
        {
            "category":"Professional",
            "type":"Services"
        }
    ],
    "sg:phone":"+1 904 284 1200",
    "sg:postcode":"32043",
    "sg:province":"FL",
    "sg:tags":[
        "establishment"
    ],
    "wof:name":"St Brendan's Isle Inc",
    "wof:placetype":"venue"
},
  "geometry": {"coordinates":[-81.71100800000001,30.024074],"type":"Point"}
}