{
  "type": "Feature",
  "properties": {
    "iso:country":"US",
    "sg:address":"1158 N Powerline Rd",
    "sg:city":"Pompano Beach",
    "sg:classifiers":[
        {
            "category":"Utilities",
            "subcategory":"Telephone",
            "type":"Services"
        }
    ],
    "sg:phone":"+1 954 917 3557",
    "sg:postcode":"33069",
    "sg:province":"FL",
    "sg:tags":[
        "communications"
    ],
    "wof:name":"Gates Adweb  Inc",
    "wof:placetype":"venue"
},
  "geometry": {"coordinates":[-80.155984,26.213641],"type":"Point"}
}