{
  "type": "Feature",
  "properties": {
    "iso:country":"US",
    "sg:address":"359 Chasteen St",
    "sg:city":"Punta Gorda",
    "sg:classifiers":[
        {
            "category":"Building & Trades",
            "subcategory":"Construction",
            "type":"Services"
        }
    ],
    "sg:phone":"+1 941 456 0443",
    "sg:postcode":"33950",
    "sg:province":"FL",
    "sg:tags":[
        "restoration",
        "cleaning",
        "patio",
        "deck"
    ],
    "wof:name":"J & J Pressure Washing",
    "wof:placetype":"venue"
},
  "geometry": {"coordinates":[-82.055131,26.929113],"type":"Point"}
}