{
  "type": "Feature",
  "properties": {
    "iso:country":"US",
    "sg:address":"14401 Military Trl",
    "sg:city":"Delray Beach",
    "sg:classifiers":[
        {
            "category":"Recreation",
            "type":"Entertainment"
        }
    ],
    "sg:phone":"+1 561 278 7300",
    "sg:postcode":"33484",
    "sg:province":"FL",
    "wof:name":"Jamie Frith Golf Studio Inc",
    "wof:placetype":"venue"
},
  "geometry": {"coordinates":[-80.12270599999999,26.463102],"type":"Point"}
}