{
  "type": "Feature",
  "properties": {
    "addr:full":"5806 N 56th St Tampa FL 33610",
    "addr:housenumber":"5806",
    "addr:postcode":"33610",
    "addr:street":"N 56Th St",
    "iso:country":"US",
    "sg:address":"5806 N 56th St",
    "sg:city":"Tampa",
    "sg:classifiers":[
        {
            "category":"Retail",
            "subcategory":"Auto Rental",
            "type":"Services"
        }
    ],
    "sg:phone":"+1 813 621 9764",
    "sg:postcode":"33610",
    "sg:province":"FL",
    "sg:tags":[
        "renting",
        "truck",
        "leasing"
    ],
    "wof:name":"U-Haul Co",
    "wof:placetype":"venue"
},
  "geometry": {"coordinates":[-82.393627,28.002458],"type":"Point"}
}