{
  "type": "Feature",
  "properties": {
    "addr:full":"770 Sundial Ct Fort Walton Beach FL 32548",
    "addr:housenumber":"770",
    "addr:postcode":"32548",
    "addr:street":"Sundial Ct",
    "iso:country":"US",
    "sg:address":"770 Sundial Ct",
    "sg:city":"Fort Walton Beach",
    "sg:classifiers":[
        {
            "category":"Real Estate",
            "subcategory":"Real Estate Agent",
            "type":"Services"
        }
    ],
    "sg:phone":"+1 850 664 0821",
    "sg:postcode":"32548",
    "sg:province":"FL",
    "wof:name":"Eden Properties",
    "wof:placetype":"venue"
},
  "geometry": {"coordinates":[-86.624341,30.39757],"type":"Point"}
}