{
  "type": "Feature",
  "properties": {
    "addr:full":"5854 Atlantic Blvd Jacksonville FL 32207",
    "addr:housenumber":"5854",
    "addr:postcode":"32207",
    "addr:street":"Atlantic Blvd",
    "iso:country":"US",
    "sg:address":"5854 Atlantic Blvd",
    "sg:city":"Jacksonville",
    "sg:classifiers":[
        {
            "category":"Personal",
            "subcategory":"Beauty Salon",
            "type":"Services"
        }
    ],
    "sg:phone":"+1 904 721 2990",
    "sg:postcode":"32207",
    "sg:province":"FL",
    "wof:name":"Sandy's Hair Place",
    "wof:placetype":"venue"
},
  "geometry": {"coordinates":[-81.60221300000001,30.313186],"type":"Point"}
}