{
  "type": "Feature",
  "properties": {
    "iso:country":"US",
    "sg:address":"7560 US Hwy 1",
    "sg:city":"Port St Lucie",
    "sg:classifiers":[
        {
            "category":"Shopping",
            "subcategory":"Discount & Variety Stores",
            "type":"Retail Goods"
        }
    ],
    "sg:phone":"+1 772 621 9469",
    "sg:postcode":"34952",
    "sg:province":"FL",
    "wof:name":"Tropical Dollar",
    "wof:placetype":"venue"
},
  "geometry": {"coordinates":[-80.320047,27.325709],"type":"Point"}
}