{
  "type": "Feature",
  "properties": {
    "addr:full":"168 W Dearborn St Englewood FL 34223",
    "addr:housenumber":"168",
    "addr:postcode":"34223",
    "addr:street":"W Dearborn St",
    "iso:country":"US",
    "sg:address":"168 W Dearborn St",
    "sg:city":"Englewood",
    "sg:classifiers":[
        {
            "category":"Personal",
            "subcategory":"Beauty Salon",
            "type":"Services"
        }
    ],
    "sg:phone":"+1 941 475 5252",
    "sg:postcode":"34223",
    "sg:province":"FL",
    "sg:tags":[
        "shop"
    ],
    "wof:name":"All About You",
    "wof:placetype":"venue"
},
  "geometry": {"coordinates":[-82.356359,26.962203],"type":"Point"}
}