{
  "type": "Feature",
  "properties": {
    "iso:country":"US",
    "sg:address":"2102 W Central Blvd",
    "sg:city":"Orlando",
    "sg:classifiers":[
        {
            "category":"Manufacturing",
            "subcategory":"Signs",
            "type":"Manufacturing & Wholesale Goods"
        }
    ],
    "sg:phone":"+1 407 841 4004",
    "sg:postcode":"32805",
    "sg:province":"FL",
    "sg:tags":[
        "mfg",
        "material",
        "specialty",
        "plastic"
    ],
    "wof:name":"Freddies Plastics Inc",
    "wof:placetype":"venue"
},
  "geometry": {"coordinates":[-81.40852099999999,28.541843],"type":"Point"}
}