{
  "type": "Feature",
  "properties": {
    "iso:country":"US",
    "sg:address":"561 S Duncan Ave",
    "sg:city":"Clearwater",
    "sg:classifiers":[
        {
            "category":"Community Center",
            "type":"Public Place"
        }
    ],
    "sg:phone":"+1 727 449 1903",
    "sg:postcode":"33756",
    "sg:province":"FL",
    "sg:tags":[
        "medical"
    ],
    "wof:name":"Associate Medical Centers",
    "wof:placetype":"venue"
},
  "geometry": {"coordinates":[-82.76687699999999,27.959102],"type":"Point"}
}