{
  "type": "Feature",
  "properties": {
    "iso:country":"US",
    "sg:address":"3740 All American Blvd",
    "sg:city":"Orlando",
    "sg:classifiers":[
        {
            "category":"Building & Trades",
            "subcategory":"Construction",
            "type":"Services"
        }
    ],
    "sg:phone":"+1 407 835 1273",
    "sg:postcode":"32810",
    "sg:province":"FL",
    "sg:tags":[
        "brick-clay-common",
        "face"
    ],
    "wof:name":"Thornton Park Constructio",
    "wof:placetype":"venue"
},
  "geometry": {"coordinates":[-81.425297,28.609155],"type":"Point"}
}