{
  "type": "Feature",
  "properties": {
    "iso:country":"US",
    "sg:address":"2180 W State Rd 434",
    "sg:city":"Longwood",
    "sg:classifiers":[
        {
            "category":"Organizations",
            "subcategory":"Professional Association",
            "type":"Services"
        }
    ],
    "sg:phone":"+1 407 869 9110",
    "sg:postcode":"32779",
    "sg:province":"FL",
    "sg:tags":[
        "accounting",
        "assoc"
    ],
    "wof:name":"Rgl Forensic Accountants Cons",
    "wof:placetype":"venue"
},
  "geometry": {"coordinates":[-81.392528,28.688375],"type":"Point"}
}