{
  "type": "Feature",
  "properties": {
    "addr:full":"874 N Dixie Hwy Lake Worth FL 33460",
    "addr:housenumber":"874",
    "addr:postcode":"33460",
    "addr:street":"N Dixie Hwy",
    "iso:country":"US",
    "sg:address":"874 N Dixie Hwy",
    "sg:city":"Lake Worth",
    "sg:classifiers":[
        {
            "category":"Food & Beverages",
            "subcategory":"Groceries & Convenience Stores",
            "type":"Retail Goods"
        }
    ],
    "sg:phone":"+1 561 588 6768",
    "sg:postcode":"33460",
    "sg:province":"FL",
    "sg:tags":[
        "gasoline"
    ],
    "wof:name":"U S Food Mart",
    "wof:placetype":"venue"
},
  "geometry": {"coordinates":[-80.05694200000001,26.625418],"type":"Point"}
}