{
  "type": "Feature",
  "properties": {
    "iso:country":"US",
    "sg:address":"101 Wymore Rd Ste 107",
    "sg:city":"Altamonte Springs",
    "sg:classifiers":[
        {
            "category":"Personal",
            "subcategory":"Barber",
            "type":"Services"
        }
    ],
    "sg:phone":"+1 407 869 6062",
    "sg:postcode":"32714",
    "sg:province":"FL",
    "wof:name":"Razor's Edge",
    "wof:placetype":"venue"
},
  "geometry": {"coordinates":[-81.389719,28.661265],"type":"Point"}
}