{
  "type": "Feature",
  "properties": {
    "iso:country":"US",
    "sg:address":"4800 NE 20th Ave",
    "sg:city":"Fort Lauderdale",
    "sg:classifiers":[
        {
            "category":"Health Services",
            "subcategory":"Doctor",
            "type":"Services"
        }
    ],
    "sg:phone":"+1 954 771 8891",
    "sg:postcode":"33308",
    "sg:province":"FL",
    "sg:tags":[
        "dentist"
    ],
    "wof:name":"Arnold Pediatric Assoc",
    "wof:placetype":"venue"
},
  "geometry": {"coordinates":[-80.118213,26.187754],"type":"Point"}
}