{
  "type": "Feature",
  "properties": {
    "addr:full":"5001 SW Orchid Bay Dr Palm City FL 34990",
    "addr:housenumber":"5001",
    "addr:postcode":"34990",
    "addr:street":"Sw Orchid Bay Dr",
    "iso:country":"US",
    "sg:address":"5001 SW Orchid Bay Dr",
    "sg:city":"Palm City",
    "sg:classifiers":[
        {
            "category":"Professional",
            "subcategory":"Research",
            "type":"Services"
        }
    ],
    "sg:phone":"+1 772 287 7698",
    "sg:postcode":"34990",
    "sg:province":"FL",
    "sg:tags":[
        "environmental",
        "ecological"
    ],
    "sg:website":"www.byogon.com",
    "wof:name":"Lake Pointe Environmental Grp",
    "wof:placetype":"venue"
},
  "geometry": {"coordinates":[-80.271784,27.140784],"type":"Point"}
}