{
  "type": "Feature",
  "properties": {
    "iso:country":"US",
    "sg:address":"3082 NW 62nd St",
    "sg:city":"Miami",
    "sg:classifiers":[
        {
            "category":"Retail",
            "subcategory":"Auto Repair",
            "type":"Services"
        }
    ],
    "sg:phone":"+1 305 637 4470",
    "sg:postcode":"33147",
    "sg:province":"FL",
    "wof:name":"Euro Auto Service",
    "wof:placetype":"venue"
},
  "geometry": {"coordinates":[-80.246498,25.8311],"type":"Point"}
}