{
  "type": "Feature",
  "properties": {
    "iso:country":"US",
    "sg:address":"1524 Jupiter Ave",
    "sg:city":"Deltona",
    "sg:classifiers":[
        {
            "category":"Building & Trades",
            "subcategory":"Landscaping Services",
            "type":"Services"
        }
    ],
    "sg:phone":"+1 321 277 1797",
    "sg:postcode":"32738",
    "sg:province":"FL",
    "sg:tags":[
        "landscape"
    ],
    "wof:name":"Brucelas Landscaping",
    "wof:placetype":"venue"
},
  "geometry": {"coordinates":[-81.178584,28.905988],"type":"Point"}
}