{
  "type": "Feature",
  "properties": {
    "addr:full":"6611 Hwy 40 W Yankeetown FL 34498",
    "addr:housenumber":"6611",
    "addr:postcode":"34498",
    "addr:street":"Hwy 40 W Yankeetown",
    "iso:country":"US",
    "sg:address":"6611 Hwy 40 W",
    "sg:city":"Yankeetown",
    "sg:classifiers":[
        {
            "category":"Shopping",
            "subcategory":"Discount & Variety Stores",
            "type":"Retail Goods"
        },
        {
            "category":"Shopping",
            "subcategory":"Bicycles & Sporting Goods",
            "type":"Retail Goods"
        }
    ],
    "sg:phone":"+1 352 447 2532",
    "sg:postcode":"34498",
    "sg:province":"FL",
    "sg:tags":[
        "bait",
        "gasoline",
        "general",
        "station",
        "fishing",
        "merchandise"
    ],
    "wof:name":"Yankeetown General Store Inc",
    "wof:placetype":"venue"
},
  "geometry": {"coordinates":[-82.72132499999999,29.029251],"type":"Point"}
}