{
  "type": "Feature",
  "properties": {
    "addr:full":"201 E Terrace Dr Plant City FL 33563",
    "addr:housenumber":"201",
    "addr:postcode":"33563",
    "addr:street":"E Terrace Dr",
    "iso:country":"US",
    "sg:address":"201 E Terrace Dr",
    "sg:city":"Plant City",
    "sg:classifiers":[
        {
            "category":"Food & Beverages",
            "subcategory":"Fruits & Vegetables",
            "type":"Retail Goods"
        }
    ],
    "sg:phone":"+1 813 759 1021",
    "sg:postcode":"33563",
    "sg:province":"FL",
    "sg:tags":[
        "produce"
    ],
    "wof:name":"B & G Produce",
    "wof:placetype":"venue"
},
  "geometry": {"coordinates":[-82.127044,28.040279],"type":"Point"}
}