{
  "type": "Feature",
  "properties": {
    "iso:country":"US",
    "sg:address":"129 NW 13th St",
    "sg:city":"Okeechobee",
    "sg:classifiers":[
        {
            "category":"Retail",
            "subcategory":"Auto Repair",
            "type":"Services"
        }
    ],
    "sg:phone":"+1 863 357 1717",
    "sg:postcode":"34972",
    "sg:province":"FL",
    "sg:tags":[
        "repairing",
        "automobile"
    ],
    "wof:name":"Hi-Tek Automotive",
    "wof:placetype":"venue"
},
  "geometry": {"coordinates":[-80.830432,27.257042],"type":"Point"}
}