{
  "type": "Feature",
  "properties": {
    "iso:country":"US",
    "sg:address":"136 N Marion St",
    "sg:city":"Lake City",
    "sg:classifiers":[
        {
            "category":"Banks & Credit Unions",
            "subcategory":"Bank",
            "type":"Services"
        }
    ],
    "sg:phone":"+1 386 752 9900",
    "sg:postcode":"32055",
    "sg:province":"FL",
    "sg:tags":[
        "loan",
        "broker"
    ],
    "wof:name":"First Atlantic Mrtg of Lk Cy",
    "wof:placetype":"venue"
},
  "geometry": {"coordinates":[-82.63720499999999,30.190441],"type":"Point"}
}