{
  "type": "Feature",
  "properties": {
    "iso:country":"US",
    "sg:address":"7045 N Tamiami Trl",
    "sg:city":"Sarasota",
    "sg:classifiers":[
        {
            "category":"Social Services",
            "subcategory":"Child Care",
            "type":"Services"
        }
    ],
    "sg:phone":"+1 941 351 0722",
    "sg:postcode":"34243",
    "sg:province":"FL",
    "wof:name":"John Calvin & Hobbes Child Ctr",
    "wof:placetype":"venue"
},
  "geometry": {"coordinates":[-82.572898,27.413491],"type":"Point"}
}