{
  "type": "Feature",
  "properties": {
    "addr:full":"616 S Macdill Ave Tampa FL 33609",
    "addr:housenumber":"616",
    "addr:postcode":"33609",
    "addr:street":"S Macdill Ave",
    "iso:country":"US",
    "sg:address":"616 S Macdill Ave",
    "sg:city":"Tampa",
    "sg:classifiers":[
        {
            "category":"Retail",
            "subcategory":"Repair Shop",
            "type":"Services"
        }
    ],
    "sg:phone":"+1 813 879 6652",
    "sg:postcode":"33609",
    "sg:province":"FL",
    "sg:tags":[
        "upholsterer"
    ],
    "wof:name":"Rite Way Upholsterers",
    "wof:placetype":"venue"
},
  "geometry": {"coordinates":[-82.49324799999999,27.937649],"type":"Point"}
}