{
  "type": "Feature",
  "properties": {
    "iso:country":"US",
    "sg:address":"310 E Interlake Blvd",
    "sg:city":"Lake Placid",
    "sg:classifiers":[
        {
            "category":"Shopping",
            "subcategory":"Used Merchandise",
            "type":"Retail Goods"
        }
    ],
    "sg:phone":"+1 863 699 2744",
    "sg:postcode":"33852",
    "sg:province":"FL",
    "sg:tags":[
        "antique"
    ],
    "wof:name":"Suzanne's Antique",
    "wof:placetype":"venue"
},
  "geometry": {"coordinates":[-81.362032,27.297095],"type":"Point"}
}