{
  "type": "Feature",
  "properties": {
    "addr:full":"955 Byron Ct Sarasota FL 34243",
    "addr:housenumber":"955",
    "addr:postcode":"34243",
    "addr:street":"Byron Ct",
    "iso:country":"US",
    "sg:address":"955 Byron Ct",
    "sg:city":"Sarasota",
    "sg:classifiers":[
        {
            "category":"Organizations",
            "subcategory":"Community Association",
            "type":"Services"
        }
    ],
    "sg:phone":"+1 941 755 5731",
    "sg:postcode":"34243",
    "sg:province":"FL",
    "sg:tags":[
        "condominium"
    ],
    "wof:name":"Shadybrook Village Condo Assn",
    "wof:placetype":"venue"
},
  "geometry": {"coordinates":[-82.554267,27.419309],"type":"Point"}
}