{
  "type": "Feature",
  "properties": {
    "iso:country":"US",
    "sg:address":"579 27th St S",
    "sg:city":"St Petersburg",
    "sg:classifiers":[
        {
            "category":"Communications",
            "subcategory":"Film & Video Production",
            "type":"Services"
        }
    ],
    "sg:phone":"+1 727 327 0557",
    "sg:postcode":"33712",
    "sg:province":"FL",
    "sg:tags":[
        "equipment",
        "visual",
        "audio",
        "rent",
        "creative"
    ],
    "wof:name":"Best Audio Visual Inc",
    "wof:placetype":"venue"
},
  "geometry": {"coordinates":[-82.66995,27.764807],"type":"Point"}
}