{
  "type": "Feature",
  "properties": {
    "iso:country":"US",
    "sg:address":"1402 Dunlawton Ave",
    "sg:city":"Port Orange",
    "sg:classifiers":[
        {
            "category":"Building & Trades",
            "subcategory":"Construction",
            "type":"Services"
        }
    ],
    "sg:phone":"+1 386 761 0364",
    "sg:postcode":"32127",
    "sg:province":"FL",
    "sg:tags":[
        "steel",
        "erectors"
    ],
    "wof:name":"Eagle Steel Inc",
    "wof:placetype":"venue"
},
  "geometry": {"coordinates":[-81.023034,29.116816],"type":"Point"}
}