{
  "type": "Feature",
  "properties": {
    "iso:country":"US",
    "sg:address":"2215 Curry Ford Rd",
    "sg:city":"Orlando",
    "sg:classifiers":[
        {
            "category":"Home & Garden",
            "subcategory":"Home Furnishings",
            "type":"Retail Goods"
        }
    ],
    "sg:phone":"+1 407 898 1199",
    "sg:postcode":"32806",
    "sg:province":"FL",
    "sg:tags":[
        "venetian",
        "blind"
    ],
    "wof:name":"A R Verticals & Installation",
    "wof:placetype":"venue"
},
  "geometry": {"coordinates":[-81.35281999999999,28.524163],"type":"Point"}
}