{
  "type": "Feature",
  "properties": {
    "addr:full":"7163 Lake Worth Rd Lake Worth FL 33467",
    "addr:housenumber":"7163",
    "addr:postcode":"33467",
    "addr:street":"Lake Worth Rd",
    "iso:country":"US",
    "sg:address":"7163 Lake Worth Rd",
    "sg:city":"Lake Worth",
    "sg:classifiers":[
        {
            "category":"Restaurant",
            "type":"Food & Drink"
        }
    ],
    "sg:menulink":"http://www.allmenus.com/fl/lake-worth/283853-kam-wah-chinese-food-take-out/menu/",
    "sg:phone":"+1 561 964 3110",
    "sg:postcode":"33467",
    "sg:province":"FL",
    "sg:tags":[
        "asian",
        "chinese"
    ],
    "wof:name":"Kam Wah Chinese Food Take-Out",
    "wof:placetype":"venue"
},
  "geometry": {"coordinates":[-80.159102,26.617681],"type":"Point"}
}