{
  "type": "Feature",
  "properties": {
    "iso:country":"US",
    "sg:address":"999 N Krome Ave",
    "sg:city":"Homestead",
    "sg:classifiers":[
        {
            "category":"Health Services",
            "subcategory":"Doctor",
            "type":"Services"
        }
    ],
    "sg:phone":"+1 305 246 4774",
    "sg:postcode":"33030",
    "sg:province":"FL",
    "sg:tags":[
        "physician",
        "surgeon"
    ],
    "sg:website":"http://www.painfulfoot.com",
    "wof:name":"Southernmost Podiatry",
    "wof:placetype":"venue"
},
  "geometry": {"coordinates":[-80.477463,25.47986],"type":"Point"}
}