{
  "type": "Feature",
  "properties": {
    "iso:country":"US",
    "sg:address":"6915 Osborne Dr",
    "sg:city":"Lake Worth",
    "sg:classifiers":[
        {
            "category":"Food & Beverages",
            "subcategory":"Groceries & Convenience Stores",
            "type":"Retail Goods"
        }
    ],
    "sg:phone":"+1 561 281 7949",
    "sg:postcode":"33462",
    "sg:province":"FL",
    "sg:tags":[
        "product"
    ],
    "wof:name":"Jalapenos",
    "wof:placetype":"venue"
},
  "geometry": {"coordinates":[-80.084062,26.574104],"type":"Point"}
}