{
  "type": "Feature",
  "properties": {
    "addr:full":"8269 Knotts Landing Dr N Jacksonville FL 32244",
    "addr:housenumber":"8269",
    "addr:postcode":"32244",
    "addr:street":"Knotts Landing Dr N",
    "iso:country":"US",
    "sg:address":"8269 Knotts Landing Dr N",
    "sg:city":"Jacksonville",
    "sg:classifiers":[
        {
            "category":"Building & Trades",
            "subcategory":"Construction",
            "type":"Services"
        }
    ],
    "sg:phone":"+1 904 379 2285",
    "sg:postcode":"32244",
    "sg:province":"FL",
    "sg:tags":[
        "system",
        "contractor",
        "air conditioning"
    ],
    "wof:name":"Economy Comfortaire",
    "wof:placetype":"venue"
},
  "geometry": {"coordinates":[-81.76409099999999,30.199802],"type":"Point"}
}