{
  "type": "Feature",
  "properties": {
    "iso:country":"US",
    "sg:address":"9331 Tamiami Trl N",
    "sg:city":"Naples",
    "sg:classifiers":[
        {
            "category":"Shopping",
            "type":"Retail Goods"
        },
        {
            "category":"Recreation",
            "type":"Entertainment"
        }
    ],
    "sg:phone":"+1 239 598 2552",
    "sg:postcode":"34108",
    "sg:province":"FL",
    "sg:tags":[
        "art",
        "gallery",
        "merchandise",
        "dealer"
    ],
    "wof:name":"Pretty As A Picture",
    "wof:placetype":"venue"
},
  "geometry": {"coordinates":[-81.801413,26.256759],"type":"Point"}
}