{
  "type": "Feature",
  "properties": {
    "addr:full":"2980 W Oakland Park Blvd Oakland Park FL 33311",
    "addr:housenumber":"2980",
    "addr:postcode":"33311",
    "addr:street":"W Oakland Park Blvd",
    "iso:country":"US",
    "sg:address":"2980 W Oakland Park Blvd",
    "sg:city":"Oakland Park",
    "sg:classifiers":[
        {
            "category":"Autos & Motor Vehicles",
            "subcategory":"Automobile Sales",
            "type":"Retail Goods"
        }
    ],
    "sg:phone":"+1 954 486 8888",
    "sg:postcode":"33311",
    "sg:province":"FL",
    "sg:tags":[
        "car",
        "dealer"
    ],
    "sg:website":"www.anythingonwheels.com",
    "wof:name":"Anything On Wheels",
    "wof:placetype":"venue"
},
  "geometry": {"coordinates":[-80.18441900000001,26.165327],"type":"Point"}
}