{
  "type": "Feature",
  "properties": {
    "iso:country":"US",
    "sg:address":"5691 SW 137th Ave",
    "sg:city":"Miami",
    "sg:classifiers":[
        {
            "category":"Personal",
            "type":"Services"
        }
    ],
    "sg:phone":"+1 305 382 6588",
    "sg:postcode":"33183",
    "sg:province":"FL",
    "sg:tags":[
        "bakery",
        "retail"
    ],
    "wof:name":"Tejadito Bakery",
    "wof:placetype":"venue"
},
  "geometry": {"coordinates":[-80.41501700000001,25.714154],"type":"Point"}
}