{
  "type": "Feature",
  "properties": {
    "addr:full":"2682 Millstone Plantation Rd Tallahassee FL 32312",
    "addr:housenumber":"2682",
    "addr:postcode":"32312",
    "addr:street":"Millstone Plantation Rd",
    "iso:country":"US",
    "sg:address":"2682 Millstone Plantation Rd",
    "sg:city":"Tallahassee",
    "sg:classifiers":[
        {
            "category":"Real Estate",
            "subcategory":"Real Estate Operator",
            "type":"Services"
        }
    ],
    "sg:phone":"+1 850 893 7416",
    "sg:postcode":"32312",
    "sg:province":"FL",
    "sg:tags":[
        "building",
        "nonresidential"
    ],
    "wof:name":"Out of Bounds Properties LLC",
    "wof:placetype":"venue"
},
  "geometry": {"coordinates":[-84.243769,30.560262],"type":"Point"}
}