{
  "type": "Feature",
  "properties": {
    "iso:country":"US",
    "sg:address":"205 N 1st St",
    "sg:city":"Immokalee",
    "sg:classifiers":[
        {
            "category":"Professional",
            "subcategory":"Business Services",
            "type":"Services"
        }
    ],
    "sg:phone":"+1 239 658 2055",
    "sg:postcode":"34142",
    "sg:province":"FL",
    "wof:name":"Judith Jean Bptste Interrprete",
    "wof:placetype":"venue"
},
  "geometry": {"coordinates":[-81.417524,26.420425],"type":"Point"}
}