{
  "type": "Feature",
  "properties": {
    "addr:full":"4324 W 20th St Panama City FL 32405",
    "addr:housenumber":"4324",
    "addr:postcode":"32405",
    "addr:street":"W 20Th St",
    "iso:country":"US",
    "sg:address":"4324 W 20th St",
    "sg:city":"Panama City",
    "sg:classifiers":[
        {
            "category":"Real Estate",
            "subcategory":"Real Estate Operator",
            "type":"Services"
        }
    ],
    "sg:phone":"+1 850 785 7904",
    "sg:postcode":"32405",
    "sg:province":"FL",
    "sg:tags":[
        "building",
        "apartment"
    ],
    "wof:name":"Turtle Lake Apartments",
    "wof:placetype":"venue"
},
  "geometry": {"coordinates":[-85.714823,30.184748],"type":"Point"}
}