{
  "type": "Feature",
  "properties": {
    "iso:country":"US",
    "sg:address":"9220 Bonita Beach Rd SE",
    "sg:city":"Bonita Springs",
    "sg:classifiers":[
        {
            "category":"Insurance",
            "subcategory":"Insurance Agent",
            "type":"Services"
        }
    ],
    "sg:phone":"+1 239 947 4333",
    "sg:postcode":"34135",
    "sg:province":"FL",
    "wof:name":"Leppala-Orr Agency",
    "wof:placetype":"venue"
},
  "geometry": {"coordinates":[-81.800471,26.330659],"type":"Point"}
}