{
  "type": "Feature",
  "properties": {
    "iso:country":"US",
    "sg:address":"300 Clyde Morris Blvd",
    "sg:city":"Ormond Beach",
    "sg:classifiers":[
        {
            "category":"Health Services",
            "subcategory":"Doctor",
            "type":"Services"
        }
    ],
    "sg:phone":"+1 386 672 1080",
    "sg:postcode":"32174",
    "sg:province":"FL",
    "sg:tags":[
        "physician",
        "surgeon"
    ],
    "sg:website":"www.floridaurology.com",
    "wof:name":"Physicians Ambulatory Surgery",
    "wof:placetype":"venue"
},
  "geometry": {"coordinates":[-81.093884,29.260061],"type":"Point"}
}