{
  "type": "Feature",
  "properties": {
    "iso:country":"US",
    "sg:address":"1377 Kass Cir",
    "sg:city":"Spring Hill",
    "sg:classifiers":[
        {
            "category":"Building & Trades",
            "subcategory":"Construction",
            "type":"Services"
        }
    ],
    "sg:phone":"+1 352 688 3606",
    "sg:postcode":"34606",
    "sg:province":"FL",
    "sg:tags":[
        "residential",
        "general",
        "commercial",
        "contractor"
    ],
    "wof:name":"N P Construction Co",
    "wof:placetype":"venue"
},
  "geometry": {"coordinates":[-82.595541,28.453384],"type":"Point"}
}