{
  "type": "Feature",
  "properties": {
    "addr:full":"10138 W Indiantown Rd Jupiter FL 33478",
    "addr:housenumber":"10138",
    "addr:postcode":"33478",
    "addr:street":"W Indiantown Rd",
    "iso:country":"US",
    "sg:address":"10138 W Indiantown Rd",
    "sg:city":"Jupiter",
    "sg:classifiers":[
        {
            "category":"Personal",
            "subcategory":"Beauty Salon",
            "type":"Services"
        }
    ],
    "sg:phone":"+1 561 747 5556",
    "sg:postcode":"33478",
    "sg:province":"FL",
    "sg:website":"www.companychair.com",
    "wof:name":"Company C Hair",
    "wof:placetype":"venue"
},
  "geometry": {"coordinates":[-80.197923,26.942159],"type":"Point"}
}