{
  "type": "Feature",
  "properties": {
    "addr:full":"539 E Call St Starke FL 32091",
    "addr:housenumber":"539",
    "addr:postcode":"32091",
    "addr:street":"E Call St",
    "iso:country":"US",
    "sg:address":"539 E Call St",
    "sg:city":"Starke",
    "sg:classifiers":[
        {
            "category":"Building & Trades",
            "subcategory":"Pest Control",
            "type":"Services"
        }
    ],
    "sg:phone":"+1 904 964 5745",
    "sg:postcode":"32091",
    "sg:province":"FL",
    "wof:name":"Florida Pest Control & Chem Co",
    "wof:placetype":"venue"
},
  "geometry": {"coordinates":[-82.10681,29.943357],"type":"Point"}
}