{
  "type": "Feature",
  "properties": {
    "addr:full":"12401 Eloian Dr Thonotosassa FL 33592",
    "addr:housenumber":"12401",
    "addr:postcode":"33592",
    "addr:street":"Eloian Dr",
    "iso:country":"US",
    "sg:address":"12401 Eloian Dr",
    "sg:city":"Thonotosassa",
    "sg:classifiers":[
        {
            "category":"Food & Beverages",
            "subcategory":"Fruits & Vegetables",
            "type":"Retail Goods"
        }
    ],
    "sg:phone":"+1 813 986 6897",
    "sg:postcode":"33592",
    "sg:province":"FL",
    "wof:name":"Deborah K Gulledge",
    "wof:placetype":"venue"
},
  "geometry": {"coordinates":[-82.33102,28.075951],"type":"Point"}
}