{
  "type": "Feature",
  "properties": {
    "iso:country":"US",
    "sg:address":"7100 Kimberly Blvd",
    "sg:city":"Pompano Beach",
    "sg:classifiers":[
        {
            "category":"Autos & Motor Vehicles",
            "subcategory":"Fuel & Gas Station",
            "type":"Retail Goods"
        }
    ],
    "sg:phone":"+1 954 721 6490",
    "sg:postcode":"33068",
    "sg:province":"FL",
    "sg:tags":[
        "convenience",
        "station",
        "gasoline",
        "store",
        "general"
    ],
    "wof:name":"NAPA Auto Parts",
    "wof:placetype":"venue"
},
  "geometry": {"coordinates":[-80.220972,26.218667],"type":"Point"}
}