{
  "type": "Feature",
  "properties": {
    "iso:country":"US",
    "sg:address":"3205 SE 21st Ave",
    "sg:city":"Ocala",
    "sg:classifiers":[
        {
            "category":"Banks & Credit Unions",
            "subcategory":"Financial Services",
            "type":"Services"
        }
    ],
    "sg:phone":"+1 352 732 7699",
    "sg:postcode":"34471",
    "sg:province":"FL",
    "sg:tags":[
        "trust",
        "investment",
        "real estate"
    ],
    "wof:name":"Jmg Properties LLC",
    "wof:placetype":"venue"
},
  "geometry": {"coordinates":[-82.108437,29.155843],"type":"Point"}
}