{
  "type": "Feature",
  "properties": {
    "addr:full":"1350 E Newport Center Dr Deerfield Beach FL 33442",
    "addr:housenumber":"1350",
    "addr:postcode":"33442",
    "addr:street":"E Newport Center Dr",
    "iso:country":"US",
    "sg:address":"1350 E Newport Center Dr",
    "sg:city":"Deerfield Beach",
    "sg:classifiers":[
        {
            "category":"Building & Trades",
            "subcategory":"Construction",
            "type":"Services"
        }
    ],
    "sg:phone":"+1 954 426 6100",
    "sg:postcode":"33442",
    "sg:province":"FL",
    "sg:tags":[
        "house",
        "residential"
    ],
    "wof:name":"Pulte",
    "wof:placetype":"venue"
},
  "geometry": {"coordinates":[-80.12387699999999,26.299673],"type":"Point"}
}