{
  "type": "Feature",
  "properties": {
    "iso:country":"US",
    "sg:address":"192 Huntley Oaks Blvd",
    "sg:city":"Lake Placid",
    "sg:classifiers":[
        {
            "category":"Building & Trades",
            "subcategory":"Construction",
            "type":"Services"
        }
    ],
    "sg:phone":"+1 863 465 0053",
    "sg:postcode":"33852",
    "sg:province":"FL",
    "sg:tags":[
        "contractor"
    ],
    "wof:name":"Bevis Construction",
    "wof:placetype":"venue"
},
  "geometry": {"coordinates":[-81.352801,27.29781],"type":"Point"}
}