{
  "type": "Feature",
  "properties": {
    "iso:country":"US",
    "sg:address":"2840 SW 38th Ct",
    "sg:city":"Miami",
    "sg:classifiers":[
        {
            "category":"Professional",
            "subcategory":"Accounting & Tax Preparation",
            "type":"Services"
        }
    ],
    "sg:phone":"+1 305 443 2824",
    "sg:postcode":"33134",
    "sg:province":"FL",
    "wof:name":"Delaorra & Associates",
    "wof:placetype":"venue"
},
  "geometry": {"coordinates":[-80.25722500000001,25.737568],"type":"Point"}
}