{
  "type": "Feature",
  "properties": {
    "addr:full":"3633 Effee St Jacksonville FL 32209",
    "addr:housenumber":"3633",
    "addr:postcode":"32209",
    "addr:street":"Effee St",
    "iso:country":"US",
    "sg:address":"3633 Effee St",
    "sg:city":"Jacksonville",
    "sg:classifiers":[
        {
            "category":"Building & Trades",
            "subcategory":"Construction",
            "type":"Services"
        }
    ],
    "sg:phone":"+1 904 768 1285",
    "sg:postcode":"32209",
    "sg:province":"FL",
    "sg:tags":[
        "fence",
        "contractor"
    ],
    "wof:name":"Shield Of Faith",
    "wof:placetype":"venue"
},
  "geometry": {"coordinates":[-81.689482,30.360688],"type":"Point"}
}