{
  "type": "Feature",
  "properties": {
    "addr:full":"243 Yacht Club Dr NE Fort Walton Beach FL 32548",
    "addr:housenumber":"243",
    "addr:postcode":"32548",
    "addr:street":"Yacht Club Dr Ne",
    "iso:country":"US",
    "sg:address":"243 Yacht Club Dr NE",
    "sg:city":"Fort Walton Beach",
    "sg:classifiers":[
        {
            "category":"Manufacturing",
            "subcategory":"Tools & Machinery",
            "type":"Manufacturing & Wholesale Goods"
        }
    ],
    "sg:phone":"+1 850 244 4920",
    "sg:postcode":"32548",
    "sg:province":"FL",
    "sg:tags":[
        "mfg",
        "garden",
        "accessory"
    ],
    "wof:name":"Marigolds Ltd Co",
    "wof:placetype":"venue"
},
  "geometry": {"coordinates":[-86.593012,30.423858],"type":"Point"}
}