{
  "type": "Feature",
  "properties": {
    "iso:country":"US",
    "sg:address":"250 Catalonia Ave",
    "sg:city":"Miami",
    "sg:classifiers":[
        {
            "category":"Building & Trades",
            "subcategory":"Landscaping Services",
            "type":"Services"
        }
    ],
    "sg:phone":"+1 305 445 9223",
    "sg:postcode":"33134",
    "sg:province":"FL",
    "sg:tags":[
        "landscape"
    ],
    "wof:name":"Perez Albert R & Associate PA",
    "wof:placetype":"venue"
},
  "geometry": {"coordinates":[-80.25954900000001,25.744665],"type":"Point"}
}