{
  "type": "Feature",
  "properties": {
    "addr:full":"2327 Hickory Rd Bonifay FL 32425",
    "addr:housenumber":"2327",
    "addr:postcode":"32425",
    "addr:street":"Hickory Rd",
    "iso:country":"US",
    "sg:address":"2327 Hickory Rd",
    "sg:city":"Bonifay",
    "sg:classifiers":[
        {
            "category":"Home & Garden",
            "subcategory":"Home Furnishings",
            "type":"Retail Goods"
        }
    ],
    "sg:phone":"+1 850 548 5480",
    "sg:postcode":"32425",
    "sg:province":"FL",
    "wof:name":"Plan-It Pottery",
    "wof:placetype":"venue"
},
  "geometry": {"coordinates":[-85.80511300000001,30.808954],"type":"Point"}
}