{
  "type": "Feature",
  "properties": {
    "addr:full":"11911 Curley Rd San Antonio FL 33576",
    "addr:housenumber":"11911",
    "addr:postcode":"33576",
    "addr:street":"Curley Rd",
    "iso:country":"US",
    "sg:address":"11911 Curley Rd",
    "sg:city":"San Antonio",
    "sg:classifiers":[
        {
            "category":"Real Estate",
            "subcategory":"Architect",
            "type":"Services"
        }
    ],
    "sg:phone":"+1 352 588 3336",
    "sg:postcode":"33576",
    "sg:province":"FL",
    "sg:tags":[
        "building",
        "designer",
        "design"
    ],
    "wof:name":"Corner Stone Design Group",
    "wof:placetype":"venue"
},
  "geometry": {"coordinates":[-82.274359,28.331027],"type":"Point"}
}