{
  "type": "Feature",
  "properties": {
    "addr:full":"3001 E Oakland Park Blvd Fort Lauderdale FL 33306",
    "addr:housenumber":"3001",
    "addr:postcode":"33306",
    "addr:street":"E Oakland Park Blvd",
    "iso:country":"US",
    "sg:address":"3001 E Oakland Park Blvd",
    "sg:city":"Fort Lauderdale",
    "sg:classifiers":[
        {
            "category":"Ferry",
            "type":"Transportation"
        }
    ],
    "sg:phone":"+1 954 565 2547",
    "sg:postcode":"33306",
    "sg:province":"FL",
    "sg:tags":[
        "boat"
    ],
    "wof:name":"Bix Inc",
    "wof:placetype":"venue"
},
  "geometry": {"coordinates":[-80.104731,26.167527],"type":"Point"}
}