{
  "type": "Feature",
  "properties": {
    "addr:full":"12311 Wedge Way Boynton Beach FL 33437",
    "addr:housenumber":"12311",
    "addr:postcode":"33437",
    "addr:street":"Wedge Way",
    "iso:country":"US",
    "sg:address":"12311 Wedge Way",
    "sg:city":"Boynton Beach",
    "sg:classifiers":[
        {
            "category":"Professional",
            "subcategory":"Art Services",
            "type":"Services"
        }
    ],
    "sg:phone":"+1 561 731 4662",
    "sg:postcode":"33437",
    "sg:province":"FL",
    "sg:tags":[
        "artist"
    ],
    "wof:name":"Vicki Oriold Designs",
    "wof:placetype":"venue"
},
  "geometry": {"coordinates":[-80.13341800000001,26.492545],"type":"Point"}
}