{
  "type": "Feature",
  "properties": {
    "addr:full":"5325 NW 108th Ave Fort Lauderdale FL 33351",
    "addr:housenumber":"5325",
    "addr:postcode":"33351",
    "addr:street":"Nw 108Th Ave",
    "iso:country":"US",
    "sg:address":"5325 NW 108th Ave",
    "sg:city":"Fort Lauderdale",
    "sg:classifiers":[
        {
            "category":"Manufacturing",
            "subcategory":"Electronics",
            "type":"Manufacturing & Wholesale Goods"
        }
    ],
    "sg:phone":"+1 954 747 7022",
    "sg:postcode":"33351",
    "sg:province":"FL",
    "sg:tags":[
        "heavy",
        "mfg",
        "electronic",
        "component",
        "equipment",
        "construction",
        "marine"
    ],
    "wof:name":"Digital Antenna Inc",
    "wof:placetype":"venue"
},
  "geometry": {"coordinates":[-80.292614,26.189134],"type":"Point"}
}