{
  "type": "Feature",
  "properties": {
    "iso:country":"US",
    "sg:address":"1300 N 15th St Ste 2",
    "sg:city":"Immokalee",
    "sg:classifiers":[
        {
            "category":"Organizations",
            "subcategory":"Community Association",
            "type":"Services"
        }
    ],
    "sg:phone":"+1 239 657 3237",
    "sg:postcode":"34142",
    "sg:province":"FL",
    "sg:tags":[
        "chamber",
        "commerce"
    ],
    "wof:name":"The Greater Eastern Collier County Chamber Of Commerce Inc",
    "wof:placetype":"venue"
},
  "geometry": {"coordinates":[-81.433853,26.43502],"type":"Point"}
}