{
  "type": "Feature",
  "properties": {
    "iso:country":"US",
    "sg:address":"8500 Parkline Blvd",
    "sg:city":"Orlando",
    "sg:classifiers":[
        {
            "category":"Shopping",
            "type":"Retail Goods"
        }
    ],
    "sg:phone":"+1 407 888 9902",
    "sg:postcode":"32809",
    "sg:province":"FL",
    "sg:tags":[
        "miscellaneous",
        "store"
    ],
    "wof:name":"Alpha Retail",
    "wof:placetype":"venue"
},
  "geometry": {"coordinates":[-81.361197,28.447903],"type":"Point"}
}