{
  "type": "Feature",
  "properties": {
    "iso:country":"US",
    "sg:address":"1685 Washington Ave",
    "sg:city":"Miami Beach",
    "sg:classifiers":[
        {
            "category":"Building & Trades",
            "subcategory":"Locksmith",
            "type":"Services"
        }
    ],
    "sg:phone":"+1 305 423 3339",
    "sg:postcode":"33139",
    "sg:province":"FL",
    "sg:tags":[
        "key"
    ],
    "wof:name":"1 Badass 24 Hour Locksmith",
    "wof:placetype":"venue"
},
  "geometry": {"coordinates":[-80.13175,25.791901],"type":"Point"}
}