{
  "type": "Feature",
  "properties": {
    "iso:country":"US",
    "sg:address":"420 Myrtle St",
    "sg:city":"Punta Gorda",
    "sg:classifiers":[
        {
            "category":"Government",
            "subcategory":"Office",
            "type":"Public Place"
        }
    ],
    "sg:phone":"+1 941 639 4344",
    "sg:postcode":"33950",
    "sg:province":"FL",
    "sg:tags":[
        "housing",
        "program"
    ],
    "wof:name":"Punta Gorda Housing Authority",
    "wof:placetype":"venue"
},
  "geometry": {"coordinates":[-82.04231799999999,26.931731],"type":"Point"}
}