{
  "type": "Feature",
  "properties": {
    "iso:country":"US",
    "sg:address":"254 Driggs Dr",
    "sg:city":"Winter Park",
    "sg:classifiers":[
        {
            "category":"Retail",
            "subcategory":"Auto Rental",
            "type":"Services"
        }
    ],
    "sg:phone":"+1 407 678 6000",
    "sg:postcode":"32792",
    "sg:province":"FL",
    "sg:tags":[
        "car"
    ],
    "wof:name":"Bryan Automotive Group Inc",
    "wof:placetype":"venue"
},
  "geometry": {"coordinates":[-81.30510700000001,28.598757],"type":"Point"}
}