{
  "type": "Feature",
  "properties": {
    "iso:country":"US",
    "sg:address":"1950 S Tamiami Trl",
    "sg:city":"Sarasota",
    "sg:classifiers":[
        {
            "category":"Banks & Credit Unions",
            "subcategory":"Bank",
            "type":"Services"
        }
    ],
    "sg:phone":"+1 941 366 8585",
    "sg:postcode":"34239",
    "sg:province":"FL",
    "sg:tags":[
        "federal",
        "savings"
    ],
    "wof:name":"Liberty Savings Bank",
    "wof:placetype":"venue"
},
  "geometry": {"coordinates":[-82.529731,27.315954],"type":"Point"}
}