{
  "type": "Feature",
  "properties": {
    "addr:full":"4890 NW 7th St Miami FL 33126",
    "addr:housenumber":"4890",
    "addr:postcode":"33126",
    "addr:street":"Nw 7Th St",
    "iso:country":"US",
    "sg:address":"4890 NW 7th St",
    "sg:city":"Miami",
    "sg:classifiers":[
        {
            "category":"Health Services",
            "subcategory":"Doctor",
            "type":"Services"
        }
    ],
    "sg:phone":"+1 305 445 5812",
    "sg:postcode":"33126",
    "sg:province":"FL",
    "sg:tags":[
        "clinic"
    ],
    "wof:name":"Belen Medical Svc Inc",
    "wof:placetype":"venue"
},
  "geometry": {"coordinates":[-80.274013,25.778603],"type":"Point"}
}