{
  "type": "Feature",
  "properties": {
    "addr:full":"4401 SW 10th St Miami FL 33134",
    "addr:housenumber":"4401",
    "addr:postcode":"33134",
    "addr:street":"Sw 10Th St",
    "iso:country":"US",
    "sg:address":"4401 SW 10th St",
    "sg:city":"Miami",
    "sg:classifiers":[
        {
            "category":"Autos & Motor Vehicles",
            "subcategory":"Automobile Sales",
            "type":"Retail Goods"
        }
    ],
    "sg:phone":"+1 305 461 2487",
    "sg:postcode":"33134",
    "sg:province":"FL",
    "sg:tags":[
        "new",
        "car"
    ],
    "wof:name":"Mercedes Ed, Inc.",
    "wof:placetype":"venue"
},
  "geometry": {"coordinates":[-80.267258,25.76173],"type":"Point"}
}