{
  "type": "Feature",
  "properties": {
    "iso:country":"US",
    "sg:address":"1390 Absher Rd",
    "sg:city":"St Cloud",
    "sg:classifiers":[
        {
            "category":"Recreation",
            "type":"Entertainment"
        }
    ],
    "sg:phone":"+1 407 957 0857",
    "sg:postcode":"34771",
    "sg:province":"FL",
    "sg:tags":[
        "stable"
    ],
    "sg:website":"www.ecqha.org",
    "wof:name":"Rising Stars Stables",
    "wof:placetype":"venue"
},
  "geometry": {"coordinates":[-81.198852,28.305322],"type":"Point"}
}