{
  "type": "Feature",
  "properties": {
    "addr:full":"110 State Hwy 60 Lake Wales FL 33853",
    "addr:housenumber":"110",
    "addr:postcode":"33853",
    "addr:street":"State Hwy 60",
    "iso:country":"US",
    "sg:address":"110 State Hwy 60",
    "sg:city":"Lake Wales",
    "sg:classifiers":[
        {
            "category":"Personal",
            "subcategory":"Beauty Salon",
            "type":"Services"
        }
    ],
    "sg:phone":"+1 863 679 9579",
    "sg:postcode":"33853",
    "sg:province":"FL",
    "sg:tags":[
        "shop"
    ],
    "wof:name":"Roberson's Beauty Salon",
    "wof:placetype":"venue"
},
  "geometry": {"coordinates":[-81.587733,27.894034],"type":"Point"}
}