{
  "type": "Feature",
  "properties": {
    "addr:full":"1035 Lee Rd Orlando FL 32810",
    "addr:housenumber":"1035",
    "addr:postcode":"32810",
    "addr:street":"Lee Rd",
    "iso:country":"US",
    "sg:address":"1035 Lee Rd",
    "sg:city":"Orlando",
    "sg:classifiers":[
        {
            "category":"Restaurant",
            "type":"Food & Drink"
        }
    ],
    "sg:phone":"+1 407 628 0811",
    "sg:postcode":"32810",
    "sg:province":"FL",
    "wof:name":"Checkers Drive-In Restaurant",
    "wof:placetype":"venue"
},
  "geometry": {"coordinates":[-81.39452199999999,28.606249],"type":"Point"}
}