{
  "type": "Feature",
  "properties": {
    "addr:full":"11401 NW 12th St Miami FL 33172",
    "addr:housenumber":"11401",
    "addr:postcode":"33172",
    "addr:street":"Nw 12Th St",
    "iso:country":"US",
    "sg:address":"11401 NW 12th St",
    "sg:city":"Miami",
    "sg:classifiers":[
        {
            "category":"Shopping",
            "subcategory":"Music",
            "type":"Retail Goods"
        },
        {
            "category":"Shopping",
            "subcategory":"Books",
            "type":"Retail Goods"
        }
    ],
    "sg:phone":"+1 305 597 8866",
    "sg:postcode":"33172",
    "sg:province":"FL",
    "sg:tags":[
        "bookstore",
        "dvd's"
    ],
    "wof:name":"Borders",
    "wof:placetype":"venue"
},
  "geometry": {"coordinates":[-80.380044,25.786728],"type":"Point"}
}