{
  "type": "Feature",
  "properties": {
    "addr:full":"2511 Brucken Rd Brandon FL 33511",
    "addr:housenumber":"2511",
    "addr:postcode":"33511",
    "addr:street":"Brucken Rd",
    "iso:country":"US",
    "sg:address":"2511 Brucken Rd",
    "sg:city":"Brandon",
    "sg:classifiers":[
        {
            "category":"Shopping",
            "subcategory":"Gifts & Souvenirs",
            "type":"Retail Goods"
        }
    ],
    "sg:phone":"+1 813 661 6755",
    "sg:postcode":"33511",
    "sg:province":"FL",
    "wof:name":"Lavender",
    "wof:placetype":"venue"
},
  "geometry": {"coordinates":[-82.261017,27.910473],"type":"Point"}
}