{
  "type": "Feature",
  "properties": {
    "iso:country":"US",
    "sg:address":"901 E 2nd St",
    "sg:city":"Sanford",
    "sg:classifiers":[
        {
            "category":"Professional",
            "subcategory":"Lawyer & Legal Services",
            "type":"Services"
        }
    ],
    "sg:phone":"+1 407 324 0778",
    "sg:postcode":"32771",
    "sg:province":"FL",
    "sg:tags":[
        "attorney"
    ],
    "wof:name":"Gray & Gorenflo P A",
    "wof:placetype":"venue"
},
  "geometry": {"coordinates":[-81.25860299999999,28.810122],"type":"Point"}
}