{
  "type": "Feature",
  "properties": {
    "iso:country":"US",
    "sg:address":"827 S Woodland Blvd",
    "sg:city":"Deland",
    "sg:classifiers":[
        {
            "category":"Restaurant",
            "type":"Food & Drink"
        }
    ],
    "sg:phone":"+1 386 736 8989",
    "sg:postcode":"32720",
    "sg:province":"FL",
    "sg:tags":[
        "chinese"
    ],
    "wof:name":"New China Restaurant",
    "wof:placetype":"venue"
},
  "geometry": {"coordinates":[-81.302803,29.0147],"type":"Point"}
}