{
  "type": "Feature",
  "properties": {
    "addr:full":"5435 Garfield Rd Delray Beach FL 33484",
    "addr:housenumber":"5435",
    "addr:postcode":"33484",
    "addr:street":"Garfield Rd",
    "iso:country":"US",
    "sg:address":"5435 Garfield Rd",
    "sg:city":"Delray Beach",
    "sg:classifiers":[
        {
            "category":"Building & Trades",
            "subcategory":"Construction",
            "type":"Services"
        }
    ],
    "sg:phone":"+1 561 638 1130",
    "sg:postcode":"33484",
    "sg:province":"FL",
    "sg:tags":[
        "carpenter"
    ],
    "wof:name":"David Tart Carpentry",
    "wof:placetype":"venue"
},
  "geometry": {"coordinates":[-80.129216,26.448004],"type":"Point"}
}