{
  "type": "Feature",
  "properties": {
    "iso:country":"US",
    "sg:address":"317 E Barnes Ave",
    "sg:city":"Eustis",
    "sg:classifiers":[
        {
            "category":"Building & Trades",
            "subcategory":"Landscaping Services",
            "type":"Services"
        }
    ],
    "sg:phone":"+1 352 357 1696",
    "sg:postcode":"32726",
    "sg:province":"FL",
    "wof:name":"Bonsal Mike Lawn Care Service",
    "wof:placetype":"venue"
},
  "geometry": {"coordinates":[-81.68232500000001,28.8394],"type":"Point"}
}