{
  "type": "Feature",
  "properties": {
    "iso:country":"US",
    "sg:address":"3510 E 5th St",
    "sg:city":"Panama City",
    "sg:classifiers":[
        {
            "category":"Professional",
            "type":"Services"
        }
    ],
    "sg:phone":"+1 850 769 7835",
    "sg:postcode":"32401",
    "sg:province":"FL",
    "sg:tags":[
        "establishment"
    ],
    "wof:name":"Springfield Head End",
    "wof:placetype":"venue"
},
  "geometry": {"coordinates":[-85.61476,30.156656],"type":"Point"}
}