{
  "type": "Feature",
  "properties": {
    "iso:country":"US",
    "sg:address":"3221 Notre Dame Dr",
    "sg:city":"Gulf Breeze",
    "sg:classifiers":[
        {
            "category":"Restaurant",
            "type":"Food & Drink"
        }
    ],
    "sg:phone":"+1 850 477 1313",
    "sg:postcode":"32563",
    "sg:province":"FL",
    "wof:name":"C J's Smokehouse",
    "wof:placetype":"venue"
},
  "geometry": {"coordinates":[-87.090653,30.389464],"type":"Point"}
}