{
  "type": "Feature",
  "properties": {
    "addr:full":"7833 9th Ave S St Petersburg FL 33707",
    "addr:housenumber":"7833",
    "addr:postcode":"33707",
    "addr:street":"9Th Ave S",
    "iso:country":"US",
    "sg:address":"7833 9th Ave S",
    "sg:city":"St Petersburg",
    "sg:classifiers":[
        {
            "category":"Building & Trades",
            "subcategory":"Construction",
            "type":"Services"
        }
    ],
    "sg:phone":"+1 727 381 1975",
    "sg:postcode":"33707",
    "sg:province":"FL",
    "sg:tags":[
        "hanging",
        "painter",
        "contractor"
    ],
    "wof:name":"Bill Riley Painting",
    "wof:placetype":"venue"
},
  "geometry": {"coordinates":[-82.74764999999999,27.760953],"type":"Point"}
}