{
  "type": "Feature",
  "properties": {
    "addr:full":"2900 NW 48th Ter Fort Lauderdale FL 33313",
    "addr:housenumber":"2900",
    "addr:postcode":"33313",
    "addr:street":"Nw 48Th Ter",
    "iso:country":"US",
    "sg:address":"2900 NW 48th Ter",
    "sg:city":"Fort Lauderdale",
    "sg:classifiers":[
        {
            "category":"Real Estate",
            "subcategory":"Real Estate Operator",
            "type":"Services"
        },
        {
            "category":"Organizations",
            "subcategory":"Community Association",
            "type":"Services"
        }
    ],
    "sg:phone":"+1 954 733 8849",
    "sg:postcode":"33313",
    "sg:province":"FL",
    "sg:tags":[
        "condominium"
    ],
    "wof:name":"Cypress Chase Condominium Off",
    "wof:placetype":"venue"
},
  "geometry": {"coordinates":[-80.2152,26.161198],"type":"Point"}
}