{
  "type": "Feature",
  "properties": {
    "iso:country":"US",
    "sg:address":"1250 Business Way",
    "sg:city":"Lehigh Acres",
    "sg:classifiers":[
        {
            "category":"Real Estate",
            "subcategory":"Real Estate Agent",
            "type":"Services"
        }
    ],
    "sg:phone":"+1 239 368 5055",
    "sg:postcode":"33936",
    "sg:province":"FL",
    "wof:name":"Mallow Associates & Realty",
    "wof:placetype":"venue"
},
  "geometry": {"coordinates":[-81.653993,26.607225],"type":"Point"}
}