{
  "type": "Feature",
  "properties": {
    "addr:full":"7376 W 20th Ave Hialeah FL 33016",
    "addr:housenumber":"7376",
    "addr:postcode":"33016",
    "addr:street":"W 20Th Ave",
    "iso:country":"US",
    "sg:address":"7376 W 20th Ave",
    "sg:city":"Hialeah",
    "sg:classifiers":[
        {
            "category":"Manufacturing",
            "subcategory":"Retail Goods",
            "type":"Manufacturing & Wholesale Goods"
        }
    ],
    "sg:phone":"+1 305 362 7797",
    "sg:postcode":"33016",
    "sg:province":"FL",
    "sg:tags":[
        "product",
        "mfg"
    ],
    "wof:name":"Jovelin Interiors Inc",
    "wof:placetype":"venue"
},
  "geometry": {"coordinates":[-80.324501,25.889656],"type":"Point"}
}