{
  "type": "Feature",
  "properties": {
    "iso:country":"US",
    "sg:address":"3385 Old Dixie Hwy",
    "sg:city":"Stuart",
    "sg:classifiers":[
        {
            "category":"Autos & Motor Vehicles",
            "subcategory":"Boat Sales",
            "type":"Retail Goods"
        }
    ],
    "sg:phone":"+1 772 286 2118",
    "sg:postcode":"34997",
    "sg:province":"FL",
    "sg:tags":[
        "equipment",
        "marine",
        "supply"
    ],
    "wof:name":"Lewis Marine Supply Inc",
    "wof:placetype":"venue"
},
  "geometry": {"coordinates":[-80.216543,27.162734],"type":"Point"}
}