{
  "type": "Feature",
  "properties": {
    "iso:country":"US",
    "sg:address":"1435 Lantana Ct",
    "sg:city":"Weston",
    "sg:classifiers":[
        {
            "category":"Real Estate",
            "subcategory":"Real Estate Agent",
            "type":"Services"
        }
    ],
    "sg:phone":"+1 954 385 8706",
    "sg:postcode":"33326",
    "sg:province":"FL",
    "wof:name":"Myles Of Hope Inc",
    "wof:placetype":"venue"
},
  "geometry": {"coordinates":[-80.391971,26.100186],"type":"Point"}
}