{
  "type": "Feature",
  "properties": {
    "addr:full":"21 Blake Blvd Kissimmee FL 34747",
    "addr:housenumber":"21",
    "addr:postcode":"34747",
    "addr:street":"Blake Blvd",
    "iso:country":"US",
    "sg:address":"21 Blake Blvd",
    "sg:city":"Kissimmee",
    "sg:classifiers":[
        {
            "category":"Banks & Credit Unions",
            "subcategory":"Investment Brokerage",
            "type":"Services"
        }
    ],
    "sg:phone":"+1 321 939 6951",
    "sg:postcode":"34747",
    "sg:province":"FL",
    "sg:tags":[
        "tape",
        "video",
        "sale",
        "dvds-rental"
    ],
    "wof:name":"Matrix Video Sound",
    "wof:placetype":"venue"
},
  "geometry": {"coordinates":[-81.526031,28.332125],"type":"Point"}
}