{
  "type": "Feature",
  "properties": {
    "addr:full":"3300 S Atlantic Ave Daytona Beach FL 32118",
    "addr:housenumber":"3300",
    "addr:postcode":"32118",
    "addr:street":"S Atlantic Ave",
    "iso:country":"US",
    "sg:address":"3300 S Atlantic Ave",
    "sg:city":"Daytona Beach",
    "sg:classifiers":[
        {
            "category":"Real Estate",
            "subcategory":"Real Estate Agent",
            "type":"Services"
        }
    ],
    "sg:phone":"+1 386 788 2250",
    "sg:postcode":"32118",
    "sg:province":"FL",
    "wof:name":"GMAC-Triangle Realty",
    "wof:placetype":"venue"
},
  "geometry": {"coordinates":[-80.971526,29.155539],"type":"Point"}
}