{
  "type": "Feature",
  "properties": {
    "iso:country":"US",
    "sg:address":"1661 Banks Rd",
    "sg:city":"Margate",
    "sg:classifiers":[
        {
            "category":"Autos & Motor Vehicles",
            "subcategory":"Automobile Sales",
            "type":"Retail Goods"
        }
    ],
    "sg:phone":"+1 954 977 8550",
    "sg:postcode":"33063",
    "sg:province":"FL",
    "sg:tags":[
        "dealers-used",
        "used",
        "cars-wholesale",
        "car"
    ],
    "wof:name":"Midnite Motor Classics Inc",
    "wof:placetype":"venue"
},
  "geometry": {"coordinates":[-80.194436,26.251041],"type":"Point"}
}