{
  "type": "Feature",
  "properties": {
    "iso:country":"US",
    "sg:address":"4467 SW 71st Ave",
    "sg:city":"Miami",
    "sg:classifiers":[
        {
            "category":"Retail",
            "subcategory":"Auto Repair",
            "type":"Services"
        }
    ],
    "sg:phone":"+1 305 663 3214",
    "sg:postcode":"33155",
    "sg:province":"FL",
    "wof:name":"Unique Automotive",
    "wof:placetype":"venue"
},
  "geometry": {"coordinates":[-80.308661,25.729158],"type":"Point"}
}