{
  "type": "Feature",
  "properties": {
    "iso:country":"US",
    "sg:address":"574 Ave A",
    "sg:city":"Satellite Beach",
    "sg:classifiers":[
        {
            "category":"Professional",
            "subcategory":"Business Services",
            "type":"Services"
        }
    ],
    "sg:phone":"+1 321 773 6555",
    "sg:postcode":"32951",
    "sg:province":"FL",
    "wof:name":"Pool Doctor of Brevard Inc",
    "wof:placetype":"venue"
},
  "geometry": {"coordinates":[-80.564072,28.069496],"type":"Point"}
}