{
  "type": "Feature",
  "properties": {
    "addr:full":"117 E Magnolia St Lakeland FL 33801",
    "addr:housenumber":"117",
    "addr:postcode":"33801",
    "addr:street":"E Magnolia St",
    "iso:country":"US",
    "sg:address":"117 E Magnolia St",
    "sg:city":"Lakeland",
    "sg:classifiers":[
        {
            "category":"Organizations",
            "subcategory":"Non-profit Organization",
            "type":"Services"
        }
    ],
    "sg:phone":"+1 863 687 3705",
    "sg:postcode":"33801",
    "sg:province":"FL",
    "sg:website":"www.lighthousemin.org",
    "wof:name":"Lighthouse Ministries",
    "wof:placetype":"venue"
},
  "geometry": {"coordinates":[-81.956405,28.049356],"type":"Point"}
}