{
  "type": "Feature",
  "properties": {
    "iso:country":"US",
    "sg:address":"17941 NW 9th Ct",
    "sg:city":"Hollywood",
    "sg:classifiers":[
        {
            "category":"Professional",
            "subcategory":"Business Services",
            "type":"Services"
        }
    ],
    "sg:phone":"+1 954 438 0694",
    "sg:postcode":"33029",
    "sg:province":"FL",
    "wof:name":"Luksang Enterprises Inc",
    "wof:placetype":"venue"
},
  "geometry": {"coordinates":[-80.38718299999999,26.011826],"type":"Point"}
}