{
  "type": "Feature",
  "properties": {
    "iso:country":"US",
    "sg:address":"6127 Southgate Blvd",
    "sg:city":"Margate",
    "sg:classifiers":[
        {
            "category":"Insurance",
            "subcategory":"Insurance Agent",
            "type":"Services"
        }
    ],
    "sg:phone":"+1 954 978 0086",
    "sg:postcode":"33068",
    "sg:province":"FL",
    "wof:name":"Chris Carroll & Assoc",
    "wof:placetype":"venue"
},
  "geometry": {"coordinates":[-80.20963,26.228258],"type":"Point"}
}