{
  "type": "Feature",
  "properties": {
    "addr:full":"900 Airport Rd Merritt Island FL 32901",
    "addr:housenumber":"900",
    "addr:postcode":"32901",
    "addr:street":"Airport Rd",
    "iso:country":"US",
    "sg:address":"900 Airport Rd",
    "sg:city":"Merritt Island",
    "sg:classifiers":[
        {
            "category":"Ferry",
            "type":"Transportation"
        }
    ],
    "sg:phone":"+1 561 470 8413",
    "sg:postcode":"32901",
    "sg:province":"FL",
    "sg:tags":[
        "water",
        "passenger",
        "truck"
    ],
    "wof:name":"Go Boats of America LLC",
    "wof:placetype":"venue"
},
  "geometry": {"coordinates":[-80.625612,28.095247],"type":"Point"}
}