{
  "type": "Feature",
  "properties": {
    "iso:country":"US",
    "sg:address":"145 NE 165th St",
    "sg:city":"Miami",
    "sg:classifiers":[
        {
            "category":"Professional",
            "subcategory":"Engineering",
            "type":"Services"
        }
    ],
    "sg:phone":"+1 305 354 3866",
    "sg:postcode":"33162",
    "sg:province":"FL",
    "wof:name":"Aurelus Engineering Inc",
    "wof:placetype":"venue"
},
  "geometry": {"coordinates":[-80.197024,25.926421],"type":"Point"}
}