{
  "type": "Feature",
  "properties": {
    "iso:country":"US",
    "sg:address":"131 Swan Pkwy W",
    "sg:city":"Royal Palm Beach",
    "sg:classifiers":[
        {
            "category":"Professional",
            "subcategory":"Computer Services",
            "type":"Services"
        }
    ],
    "sg:phone":"+1 561 798 6582",
    "sg:postcode":"33411",
    "sg:province":"FL",
    "sg:tags":[
        "repair"
    ],
    "wof:name":"Gary M Chirillo Computer Rpr",
    "wof:placetype":"venue"
},
  "geometry": {"coordinates":[-80.221306,26.70105],"type":"Point"}
}