{
  "type": "Feature",
  "properties": {
    "iso:country":"US",
    "sg:address":"7402 N 56th St",
    "sg:city":"Tampa",
    "sg:classifiers":[
        {
            "category":"Social Services",
            "type":"Services"
        }
    ],
    "sg:phone":"+1 813 987 6717",
    "sg:postcode":"33617",
    "sg:province":"FL",
    "sg:tags":[
        "probation"
    ],
    "sg:website":"www.dc.state.fl.us",
    "wof:name":"Probation & Parole Svc",
    "wof:placetype":"venue"
},
  "geometry": {"coordinates":[-82.39357099999999,28.016128],"type":"Point"}
}