{
  "type": "Feature",
  "properties": {
    "iso:country":"US",
    "sg:address":"6501 102nd Ave",
    "sg:city":"Pinellas Park",
    "sg:classifiers":[
        {
            "category":"Food & Beverages",
            "subcategory":"Groceries & Convenience Stores",
            "type":"Retail Goods"
        }
    ],
    "sg:phone":"+1 727 541 2070",
    "sg:postcode":"33782",
    "sg:province":"FL",
    "wof:name":"Winn-Dixie",
    "wof:placetype":"venue"
},
  "geometry": {"coordinates":[-82.726731,27.864696],"type":"Point"}
}