{
  "type": "Feature",
  "properties": {
    "addr:full":"407 S Federal Hwy Boynton Beach FL 33435",
    "addr:housenumber":"407",
    "addr:postcode":"33435",
    "addr:street":"S Federal Hwy",
    "iso:country":"US",
    "sg:address":"407 S Federal Hwy",
    "sg:city":"Boynton Beach",
    "sg:classifiers":[
        {
            "category":"Local Transit",
            "type":"Transportation"
        }
    ],
    "sg:phone":"+1 561 424 0424",
    "sg:postcode":"33435",
    "sg:province":"FL",
    "sg:tags":[
        "airport",
        "limo"
    ],
    "wof:name":"Skycap Limo",
    "wof:placetype":"venue"
},
  "geometry": {"coordinates":[-80.05804000000001,26.523215],"type":"Point"}
}