{
  "type": "Feature",
  "properties": {
    "addr:full":"18100 Wells Rd Fort Myers FL 33917",
    "addr:housenumber":"18100",
    "addr:postcode":"33917",
    "addr:street":"Wells Rd",
    "iso:country":"US",
    "sg:address":"18100 Wells Rd",
    "sg:city":"Fort Myers",
    "sg:classifiers":[
        {
            "category":"Building & Trades",
            "subcategory":"Landscaping Services",
            "type":"Services"
        }
    ],
    "sg:phone":"+1 239 567 1857",
    "sg:postcode":"33917",
    "sg:province":"FL",
    "wof:name":"Woods & Wetlands Inc",
    "wof:placetype":"venue"
},
  "geometry": {"coordinates":[-81.80576000000001,26.726373],"type":"Point"}
}