{
  "type": "Feature",
  "properties": {
    "iso:country":"US",
    "sg:address":"3000 22nd Ave S",
    "sg:city":"St Petersburg",
    "sg:classifiers":[
        {
            "category":"Social Services",
            "subcategory":"Child Care",
            "type":"Services"
        }
    ],
    "sg:phone":"+1 727 323 9419",
    "sg:postcode":"33712",
    "sg:province":"FL",
    "sg:tags":[
        "day"
    ],
    "wof:name":"Celebrity Kids Club Inc",
    "wof:placetype":"venue"
},
  "geometry": {"coordinates":[-82.675195,27.748369],"type":"Point"}
}