{
  "type": "Feature",
  "properties": {
    "addr:full":"119 7th St Niceville FL 32578",
    "addr:housenumber":"119",
    "addr:postcode":"32578",
    "addr:street":"7Th St",
    "iso:country":"US",
    "sg:address":"119 7th St",
    "sg:city":"Niceville",
    "sg:classifiers":[
        {
            "category":"Building & Trades",
            "subcategory":"Construction",
            "type":"Services"
        }
    ],
    "sg:phone":"+1 850 279 4839",
    "sg:postcode":"32578",
    "sg:province":"FL",
    "sg:tags":[
        "mason",
        "masonry",
        "industrial",
        "contractors-commercial",
        "contractor"
    ],
    "wof:name":"Advanced Masonry",
    "wof:placetype":"venue"
},
  "geometry": {"coordinates":[-86.45744000000001,30.492276],"type":"Point"}
}