{
  "type": "Feature",
  "properties": {
    "addr:full":"2850 Lake Washington Rd Melbourne FL 32935",
    "addr:housenumber":"2850",
    "addr:postcode":"32935",
    "addr:street":"Lake Washington Rd",
    "iso:country":"US",
    "sg:address":"2850 Lake Washington Rd",
    "sg:city":"Melbourne",
    "sg:classifiers":[
        {
            "category":"Insurance",
            "subcategory":"Insurance Agent",
            "type":"Services"
        },
        {
            "category":"Insurance",
            "subcategory":"Hazard Insurance",
            "type":"Services"
        },
        {
            "category":"Insurance",
            "subcategory":"Title Insurance",
            "type":"Services"
        }
    ],
    "sg:phone":"+1 321 255 1077",
    "sg:postcode":"32935",
    "sg:province":"FL",
    "sg:tags":[
        "business",
        "auto",
        "commercial",
        "homeowner",
        "motorcycle",
        "renter",
        "marine",
        "boat"
    ],
    "sg:website":"http://www.ainsurance.biz",
    "wof:name":"Advanced Insurance Net",
    "wof:placetype":"venue"
},
  "geometry": {"coordinates":[-80.66914800000001,28.146804],"type":"Point"}
}