{
  "type": "Feature",
  "properties": {
    "addr:full":"11404 Orange Grove Dr Tampa FL 33618",
    "addr:housenumber":"11404",
    "addr:postcode":"33618",
    "addr:street":"Orange Grove Dr",
    "iso:country":"US",
    "sg:address":"11404 Orange Grove Dr",
    "sg:city":"Tampa",
    "sg:classifiers":[
        {
            "category":"Shopping",
            "subcategory":"Clothing, Apparel, & Fashions",
            "type":"Retail Goods"
        }
    ],
    "sg:phone":"+1 813 932 6476",
    "sg:postcode":"33618",
    "sg:province":"FL",
    "wof:name":"Carroll Apparel Inc",
    "wof:placetype":"venue"
},
  "geometry": {"coordinates":[-82.50080800000001,28.052033],"type":"Point"}
}