{
  "type": "Feature",
  "properties": {
    "iso:country":"US",
    "sg:address":"600 S Lake Ave",
    "sg:city":"Clearwater",
    "sg:classifiers":[
        {
            "category":"Recreation",
            "type":"Entertainment"
        }
    ],
    "sg:phone":"+1 727 584 5505",
    "sg:postcode":"33756",
    "sg:province":"FL",
    "sg:tags":[
        "club",
        "baseball"
    ],
    "wof:name":"Greater Largo Little League",
    "wof:placetype":"venue"
},
  "geometry": {"coordinates":[-82.77109299999999,27.957041],"type":"Point"}
}