{
  "type": "Feature",
  "properties": {
    "addr:full":"13112 SW 128th St Miami FL 33186",
    "addr:housenumber":"13112",
    "addr:postcode":"33186",
    "addr:street":"Sw 128Th St",
    "iso:country":"US",
    "sg:address":"13112 SW 128th St",
    "sg:city":"Miami",
    "sg:classifiers":[
        {
            "category":"Health Services",
            "subcategory":"Nursing And Care Facility",
            "type":"Services"
        },
        {
            "category":"Health Services",
            "subcategory":"Clinic",
            "type":"Services"
        }
    ],
    "sg:phone":"+1 305 238 8080",
    "sg:postcode":"33186",
    "sg:province":"FL",
    "sg:tags":[
        "home"
    ],
    "wof:name":"Support Care Group Inc",
    "wof:placetype":"venue"
},
  "geometry": {"coordinates":[-80.40548800000001,25.648573],"type":"Point"}
}