{
  "type": "Feature",
  "properties": {
    "iso:country":"US",
    "sg:address":"310 Hidden Lake Dr",
    "sg:city":"Sanford",
    "sg:classifiers":[
        {
            "category":"Building & Trades",
            "subcategory":"Construction",
            "type":"Services"
        }
    ],
    "sg:phone":"+1 407 322 6618",
    "sg:postcode":"32773",
    "sg:province":"FL",
    "sg:tags":[
        "contractor"
    ],
    "wof:name":"All About Pools",
    "wof:placetype":"venue"
},
  "geometry": {"coordinates":[-81.300186,28.769349],"type":"Point"}
}