{
  "type": "Feature",
  "properties": {
    "iso:country":"US",
    "sg:address":"2315 SE 15th Pl",
    "sg:city":"Cape Coral",
    "sg:classifiers":[
        {
            "category":"Social Services",
            "subcategory":"Adult Care",
            "type":"Services"
        }
    ],
    "sg:phone":"+1 239 458 4229",
    "sg:postcode":"33990",
    "sg:province":"FL",
    "sg:tags":[
        "home",
        "group"
    ],
    "wof:name":"Haven Of Divine Love",
    "wof:placetype":"venue"
},
  "geometry": {"coordinates":[-81.94211900000001,26.609391],"type":"Point"}
}