{
  "type": "Feature",
  "properties": {
    "iso:country":"US",
    "sg:address":"190 Ave K SW",
    "sg:city":"Winter Haven",
    "sg:classifiers":[
        {
            "category":"Retail",
            "subcategory":"Auto Repair",
            "type":"Services"
        }
    ],
    "sg:phone":"+1 863 595 2190",
    "sg:postcode":"33880",
    "sg:province":"FL",
    "sg:tags":[
        "body",
        "automobile",
        "painting"
    ],
    "wof:name":"Winter Haven Auto Body",
    "wof:placetype":"venue"
},
  "geometry": {"coordinates":[-81.73134400000001,28.011207],"type":"Point"}
}