{
  "type": "Feature",
  "properties": {
    "iso:country":"US",
    "sg:address":"3501 SW Archer Rd",
    "sg:city":"Gainesville",
    "sg:classifiers":[
        {
            "category":"Restaurant",
            "type":"Food & Drink"
        }
    ],
    "sg:menulink":"http://www.allmenus.com/fl/gainesville/62330-tony-and-pats/menu/",
    "sg:phone":"+1 352 377 7400",
    "sg:postcode":"32608",
    "sg:province":"FL",
    "sg:tags":[
        "wrap",
        "american",
        "sandwich"
    ],
    "wof:name":"Tony And Pats",
    "wof:placetype":"venue"
},
  "geometry": {"coordinates":[-82.375736,29.623783],"type":"Point"}
}