{
  "type": "Feature",
  "properties": {
    "iso:country":"US",
    "sg:address":"7640 NW 25th St",
    "sg:city":"Miami",
    "sg:classifiers":[
        {
            "category":"Arts & Performance",
            "subcategory":"Theater",
            "type":"Entertainment"
        }
    ],
    "sg:phone":"+1 305 477 7155",
    "sg:postcode":"33122",
    "sg:province":"FL",
    "sg:tags":[
        "instrument",
        "musical",
        "karaoke"
    ],
    "wof:name":"Karaoke Usa",
    "wof:placetype":"venue"
},
  "geometry": {"coordinates":[-80.319444,25.79701],"type":"Point"}
}