{
  "type": "Feature",
  "properties": {
    "addr:full":"321 Brandy Ln Naples FL 34114",
    "addr:housenumber":"321",
    "addr:postcode":"34114",
    "addr:street":"Brandy Ln",
    "iso:country":"US",
    "sg:address":"321 Brandy Ln",
    "sg:city":"Naples",
    "sg:classifiers":[
        {
            "category":"Building & Trades",
            "subcategory":"Landscaping Services",
            "type":"Services"
        }
    ],
    "sg:phone":"+1 239 417 9098",
    "sg:postcode":"34114",
    "sg:province":"FL",
    "sg:tags":[
        "lawn",
        "maintenance",
        "grounds"
    ],
    "wof:name":"South Florida Landscape",
    "wof:placetype":"venue"
},
  "geometry": {"coordinates":[-81.664554,26.098634],"type":"Point"}
}