{
  "type": "Feature",
  "properties": {
    "addr:full":"1101 Marshall Farms Rd Ocoee FL 34761",
    "addr:housenumber":"1101",
    "addr:postcode":"34761",
    "addr:street":"Marshall Farms Rd",
    "iso:country":"US",
    "sg:address":"1101 Marshall Farms Rd",
    "sg:city":"Ocoee",
    "sg:classifiers":[
        {
            "category":"Retail",
            "subcategory":"Auto Rental",
            "type":"Services"
        }
    ],
    "sg:phone":"+1 407 877 0076",
    "sg:postcode":"34761",
    "sg:province":"FL",
    "sg:tags":[
        "renting",
        "truck",
        "leasing"
    ],
    "wof:name":"U-Haul Co",
    "wof:placetype":"venue"
},
  "geometry": {"coordinates":[-81.549722,28.553269],"type":"Point"}
}