{
  "type": "Feature",
  "properties": {
    "addr:full":"5052 NE 12th Ave Oakland Park FL 33334",
    "addr:housenumber":"5052",
    "addr:postcode":"33334",
    "addr:street":"Ne 12Th Ave",
    "iso:country":"US",
    "sg:address":"5052 NE 12th Ave",
    "sg:city":"Oakland Park",
    "sg:classifiers":[
        {
            "category":"Retail",
            "subcategory":"Auto Rental",
            "type":"Services"
        }
    ],
    "sg:phone":"+1 954 493 8810",
    "sg:postcode":"33334",
    "sg:province":"FL",
    "sg:tags":[
        "renting",
        "truck",
        "leasing"
    ],
    "wof:name":"Zwick Truck Rentals",
    "wof:placetype":"venue"
},
  "geometry": {"coordinates":[-80.131249,26.19186],"type":"Point"}
}