{
  "type": "Feature",
  "properties": {
    "iso:country":"US",
    "sg:address":"400 Palm St",
    "sg:city":"West Palm Beach",
    "sg:classifiers":[
        {
            "category":"Professional",
            "subcategory":"Lawyer & Legal Services",
            "type":"Services"
        }
    ],
    "sg:phone":"+1 561 684 8866",
    "sg:postcode":"33401",
    "sg:province":"FL",
    "wof:name":"Goodmark & Goldstone PA",
    "wof:placetype":"venue"
},
  "geometry": {"coordinates":[-80.05564,26.699322],"type":"Point"}
}