{
  "type": "Feature",
  "properties": {
    "addr:full":"5309 Congo Ct Cape Coral FL 33904",
    "addr:housenumber":"5309",
    "addr:postcode":"33904",
    "addr:street":"Congo Ct",
    "iso:country":"US",
    "sg:address":"5309 Congo Ct",
    "sg:city":"Cape Coral",
    "sg:classifiers":[
        {
            "category":"Building & Trades",
            "subcategory":"Construction",
            "type":"Services"
        }
    ],
    "sg:phone":"+1 239 945 5905",
    "sg:postcode":"33904",
    "sg:province":"FL",
    "sg:tags":[
        "house"
    ],
    "wof:name":"Castle Home Improvement",
    "wof:placetype":"venue"
},
  "geometry": {"coordinates":[-81.968391,26.549036],"type":"Point"}
}