{
  "type": "Feature",
  "properties": {
    "iso:country":"US",
    "sg:address":"700 Giese Ln",
    "sg:city":"Pensacola",
    "sg:classifiers":[
        {
            "category":"Shopping",
            "subcategory":"Pets & Pet Supplies",
            "type":"Retail Goods"
        },
        {
            "category":"Retail",
            "subcategory":"Veterinary Services",
            "type":"Services"
        },
        {
            "category":"Retail",
            "subcategory":"Animal Services",
            "type":"Services"
        }
    ],
    "sg:phone":"+1 850 607 6632",
    "sg:postcode":"32506",
    "sg:province":"FL",
    "sg:tags":[
        "dog",
        "specialty",
        "cat",
        "furnishing",
        "grooming",
        "store"
    ],
    "sg:website":"http://www.myabcspace.com/bellapooch",
    "wof:name":"Bella Pooch",
    "wof:placetype":"venue"
},
  "geometry": {"coordinates":[-87.33739199999999,30.400821],"type":"Point"}
}