{
  "type": "Feature",
  "properties": {
    "iso:country":"US",
    "sg:address":"4526 Tamiami Trl N",
    "sg:city":"Naples",
    "sg:classifiers":[
        {
            "category":"Autos & Motor Vehicles",
            "subcategory":"Motorcycle Sales",
            "type":"Retail Goods"
        }
    ],
    "sg:phone":"+1 239 435 3223",
    "sg:postcode":"34103",
    "sg:province":"FL",
    "sg:tags":[
        "scooter"
    ],
    "wof:name":"Motor Toys",
    "wof:placetype":"venue"
},
  "geometry": {"coordinates":[-81.80015299999999,26.200107],"type":"Point"}
}