{
  "type": "Feature",
  "properties": {
    "addr:full":"6032 NW 31 Ter Gainesville FL 32653",
    "addr:housenumber":"6032",
    "addr:postcode":"32653",
    "addr:street":"Nw 31 Ter",
    "iso:country":"US",
    "sg:address":"6032 NW 31 Ter",
    "sg:city":"Gainesville",
    "sg:classifiers":[
        {
            "category":"Cinema",
            "subcategory":"Movie Rental",
            "type":"Entertainment"
        }
    ],
    "sg:phone":"+1 352 372 4462",
    "sg:postcode":"32653",
    "sg:province":"FL",
    "sg:tags":[
        "video",
        "tape"
    ],
    "wof:name":"Js Photo Video",
    "wof:placetype":"venue"
},
  "geometry": {"coordinates":[-82.368512,29.709339],"type":"Point"}
}