{
  "type": "Feature",
  "properties": {
    "iso:country":"US",
    "sg:address":"8978 Bonnet Way",
    "sg:city":"Weeki Wachee",
    "sg:classifiers":[
        {
            "category":"Professional",
            "subcategory":"Computer Services",
            "type":"Services"
        }
    ],
    "sg:phone":"+1 352 592 4412",
    "sg:postcode":"34613",
    "sg:province":"FL",
    "sg:tags":[
        "internet"
    ],
    "wof:name":"Synergy Retail Concepts",
    "wof:placetype":"venue"
},
  "geometry": {"coordinates":[-82.575778,28.537322],"type":"Point"}
}