{
  "type": "Feature",
  "properties": {
    "iso:country":"US",
    "sg:address":"4873 Ulmerton Rd",
    "sg:city":"Clearwater",
    "sg:classifiers":[
        {
            "category":"Restaurant",
            "type":"Food & Drink"
        }
    ],
    "sg:menulink":"http://www.allmenus.com/fl/st-petersburg/29492-bascoms-chop-house/menu/",
    "sg:phone":"+1 727 573 3363",
    "sg:postcode":"33762",
    "sg:province":"FL",
    "sg:tags":[
        "american",
        "steakhouse"
    ],
    "wof:name":"Bascom's Chop House",
    "wof:placetype":"venue"
},
  "geometry": {"coordinates":[-82.699381,27.894022],"type":"Point"}
}