{
  "type": "Feature",
  "properties": {
    "addr:full":"5224 W State Rd 46 Sanford FL 32771",
    "addr:housenumber":"5224;46",
    "addr:postcode":"32771",
    "addr:street":"W State Rd",
    "iso:country":"US",
    "sg:address":"5224 W State Rd 46",
    "sg:city":"Sanford",
    "sg:classifiers":[
        {
            "category":"Professional",
            "subcategory":"Business Services",
            "type":"Services"
        },
        {
            "category":"Professional",
            "subcategory":"Advertising",
            "type":"Services"
        }
    ],
    "sg:phone":"+1 407 322 2312",
    "sg:postcode":"32771",
    "sg:province":"FL",
    "sg:tags":[
        "mailing",
        "shipping"
    ],
    "wof:name":"UPS Stores",
    "wof:placetype":"venue"
},
  "geometry": {"coordinates":[-81.352987,28.811413],"type":"Point"}
}