{
  "type": "Feature",
  "properties": {
    "iso:country":"US",
    "sg:address":"30 W Government St",
    "sg:city":"Panama City",
    "sg:classifiers":[
        {
            "category":"Real Estate",
            "subcategory":"Developer",
            "type":"Services"
        }
    ],
    "sg:phone":"+1 850 872 0250",
    "sg:postcode":"32401",
    "sg:province":"FL",
    "wof:name":"Rudnick Development",
    "wof:placetype":"venue"
},
  "geometry": {"coordinates":[-85.66368799999999,30.154077],"type":"Point"}
}