{
  "type": "Feature",
  "properties": {
    "iso:country":"US",
    "sg:address":"1751 NW 79th St",
    "sg:city":"Miami",
    "sg:classifiers":[
        {
            "category":"Utilities",
            "subcategory":"Mobile Phone",
            "type":"Services"
        },
        {
            "category":"Communications",
            "type":"Services"
        }
    ],
    "sg:phone":"+1 305 418 4845",
    "sg:postcode":"33147",
    "sg:province":"FL",
    "sg:tags":[
        "equipment",
        "cellular",
        "telephone",
        "systems-repair"
    ],
    "wof:name":"Cooper General Global Service",
    "wof:placetype":"venue"
},
  "geometry": {"coordinates":[-80.226191,25.846593],"type":"Point"}
}