{
  "type": "Feature",
  "properties": {
    "iso:country":"US",
    "sg:address":"209 E Main St",
    "sg:city":"Lakeland",
    "sg:classifiers":[
        {
            "category":"Bars & Pubs",
            "type":"Food & Drink"
        }
    ],
    "sg:phone":"+1 863 683 7195",
    "sg:postcode":"33801",
    "sg:province":"FL",
    "sg:tags":[
        "tavern"
    ],
    "wof:name":"Linkstersnp",
    "wof:placetype":"venue"
},
  "geometry": {"coordinates":[-81.956192,28.044142],"type":"Point"}
}