{
  "type": "Feature",
  "properties": {
    "iso:country":"US",
    "sg:address":"830 NW 171st St Ofc",
    "sg:city":"Miami",
    "sg:classifiers":[
        {
            "category":"Wholesale",
            "subcategory":"Office Equipment",
            "type":"Manufacturing & Wholesale Goods"
        },
        {
            "category":"Retail",
            "subcategory":"Repair Shop",
            "type":"Services"
        },
        {
            "category":"Social Services",
            "subcategory":"Adult Care",
            "type":"Services"
        },
        {
            "category":"Shopping",
            "subcategory":"Computers & Home Electronics",
            "type":"Retail Goods"
        }
    ],
    "sg:phone":"+1 305 624 4433",
    "sg:postcode":"33169",
    "sg:province":"FL",
    "sg:tags":[
        "typewriter",
        "typewriters-repairing",
        "equipment-wholesale",
        "refinish",
        "equipment-repair",
        "attachment",
        "typewriters-supplies",
        "manufacturer",
        "furniture"
    ],
    "wof:name":"Office Equipment Service",
    "wof:placetype":"venue"
},
  "geometry": {"coordinates":[-80.215288,25.931203],"type":"Point"}
}