{
  "type": "Feature",
  "properties": {
    "iso:country":"US",
    "sg:address":"180 NW Pine St",
    "sg:city":"Melbourne",
    "sg:classifiers":[
        {
            "category":"Building & Trades",
            "subcategory":"Electrical",
            "type":"Services"
        }
    ],
    "sg:phone":"+1 321 723 8537",
    "sg:postcode":"32904",
    "sg:province":"FL",
    "sg:tags":[
        "electrical",
        "contractor"
    ],
    "wof:name":"C & J Electric",
    "wof:placetype":"venue"
},
  "geometry": {"coordinates":[-80.670058,28.080752],"type":"Point"}
}