{
  "type": "Feature",
  "properties": {
    "iso:country":"US",
    "sg:address":"7810 Akron Ave",
    "sg:city":"Hudson",
    "sg:classifiers":[
        {
            "category":"Building & Trades",
            "subcategory":"Construction",
            "type":"Services"
        }
    ],
    "sg:phone":"+1 727 226 3115",
    "sg:postcode":"34667",
    "sg:province":"FL",
    "sg:tags":[
        "altering",
        "remodeling",
        "contractor"
    ],
    "wof:name":"Marrero All American Home Svc",
    "wof:placetype":"venue"
},
  "geometry": {"coordinates":[-82.68493599999999,28.375891],"type":"Point"}
}