{
  "type": "Feature",
  "properties": {
    "iso:country":"US",
    "sg:address":"1609 Cardinal Rd",
    "sg:city":"Orlando",
    "sg:classifiers":[
        {
            "category":"Real Estate",
            "subcategory":"Real Estate Agent",
            "type":"Services"
        }
    ],
    "sg:phone":"+1 407 896 4320",
    "sg:postcode":"32803",
    "sg:province":"FL",
    "wof:name":"Condemnation Appraisal SE",
    "wof:placetype":"venue"
},
  "geometry": {"coordinates":[-81.34198000000001,28.566329],"type":"Point"}
}