{
  "type": "Feature",
  "properties": {
    "iso:country":"US",
    "sg:address":"29056 Wildlife Ln",
    "sg:city":"Brooksville",
    "sg:classifiers":[
        {
            "category":"Banks & Credit Unions",
            "subcategory":"Investment Brokerage",
            "type":"Services"
        }
    ],
    "sg:phone":"+1 352 796 6578",
    "sg:postcode":"34602",
    "sg:province":"FL",
    "sg:tags":[
        "security"
    ],
    "wof:name":"Caleb Paine Computer Consultan",
    "wof:placetype":"venue"
},
  "geometry": {"coordinates":[-82.256472,28.535588],"type":"Point"}
}