{
  "type": "Feature",
  "properties": {
    "addr:full":"12626 US Hwy 301 Dade City FL 33525",
    "addr:housenumber":"12626",
    "addr:postcode":"33525",
    "addr:street":"Us Hwy 301",
    "iso:country":"US",
    "sg:address":"12626 US Hwy 301",
    "sg:city":"Dade City",
    "sg:classifiers":[
        {
            "category":"Shopping",
            "subcategory":"Jewelry",
            "type":"Retail Goods"
        }
    ],
    "sg:phone":"+1 352 567 8361",
    "sg:postcode":"33525",
    "sg:province":"FL",
    "sg:tags":[
        "store"
    ],
    "wof:name":"Jewelry Shop The",
    "wof:placetype":"venue"
},
  "geometry": {"coordinates":[-82.18749099999999,28.341303],"type":"Point"}
}