{
  "type": "Feature",
  "properties": {
    "addr:full":"3300 NW 90th Ave Pompano Beach FL 33065",
    "addr:housenumber":"3300",
    "addr:postcode":"33065",
    "addr:street":"Nw 90Th Ave",
    "iso:country":"US",
    "sg:address":"3300 NW 90th Ave",
    "sg:city":"Pompano Beach",
    "sg:classifiers":[
        {
            "category":"Building & Trades",
            "subcategory":"Electrical",
            "type":"Services"
        }
    ],
    "sg:phone":"+1 954 752 5796",
    "sg:postcode":"33065",
    "sg:province":"FL",
    "sg:tags":[
        "electrical",
        "contractor"
    ],
    "wof:name":"JM Electrical Services",
    "wof:placetype":"venue"
},
  "geometry": {"coordinates":[-80.246797,26.272412],"type":"Point"}
}