{
  "type": "Feature",
  "properties": {
    "addr:full":"4075 US Hwy 1 Cocoa FL 32927",
    "addr:housenumber":"4075",
    "addr:postcode":"32927",
    "addr:street":"Us Hwy 1",
    "iso:country":"US",
    "sg:address":"4075 US Hwy 1",
    "sg:city":"Cocoa",
    "sg:classifiers":[
        {
            "category":"Home & Garden",
            "subcategory":"Furniture",
            "type":"Retail Goods"
        }
    ],
    "sg:phone":"+1 321 632 9556",
    "sg:postcode":"32927",
    "sg:province":"FL",
    "wof:name":"Havertys",
    "wof:placetype":"venue"
},
  "geometry": {"coordinates":[-80.760779,28.434358],"type":"Point"}
}