{
  "type": "Feature",
  "properties": {
    "addr:full":"1700 Cypress Trace Dr Safety Harbor FL 34695",
    "addr:housenumber":"1700",
    "addr:postcode":"34695",
    "addr:street":"Cypress Trace Dr",
    "iso:country":"US",
    "sg:address":"1700 Cypress Trace Dr",
    "sg:city":"Safety Harbor",
    "sg:classifiers":[
        {
            "category":"Real Estate",
            "subcategory":"Real Estate Agent",
            "type":"Services"
        }
    ],
    "sg:phone":"+1 727 726 4530",
    "sg:postcode":"34695",
    "sg:province":"FL",
    "wof:name":"Joe Watson",
    "wof:placetype":"venue"
},
  "geometry": {"coordinates":[-82.70614399999999,27.998828],"type":"Point"}
}