{
  "type": "Feature",
  "properties": {
    "iso:country":"US",
    "sg:address":"8475 SW 58th St",
    "sg:city":"Miami",
    "sg:classifiers":[
        {
            "category":"Building & Trades",
            "subcategory":"Construction",
            "type":"Services"
        }
    ],
    "sg:phone":"+1 305 412 1389",
    "sg:postcode":"33143",
    "sg:province":"FL",
    "sg:tags":[
        "acoustical",
        "ceiling",
        "installation"
    ],
    "wof:name":"Lara Company of Miami The",
    "wof:placetype":"venue"
},
  "geometry": {"coordinates":[-80.331847,25.715152],"type":"Point"}
}