{
  "type": "Feature",
  "properties": {
    "iso:country":"US",
    "sg:address":"108 Bayberry Cir Ste 5",
    "sg:city":"Jupiter",
    "sg:classifiers":[
        {
            "category":"Health Services",
            "subcategory":"Doctor",
            "type":"Services"
        }
    ],
    "sg:phone":"+1 561 575 0737",
    "sg:postcode":"33458",
    "sg:province":"FL",
    "sg:tags":[
        "physician",
        "family",
        "practice",
        "surgeons",
        "medicine"
    ],
    "wof:name":"Nierman Practice Management",
    "wof:placetype":"venue"
},
  "geometry": {"coordinates":[-80.11183200000001,26.917549],"type":"Point"}
}