{
  "type": "Feature",
  "properties": {
    "addr:full":"5364 S Suncoast Blvd Homosassa FL 34446",
    "addr:housenumber":"5364",
    "addr:postcode":"34446",
    "addr:street":"S Suncoast Blvd",
    "iso:country":"US",
    "sg:address":"5364 S Suncoast Blvd",
    "sg:city":"Homosassa",
    "sg:classifiers":[
        {
            "category":"Restaurant",
            "type":"Food & Drink"
        }
    ],
    "sg:phone":"+1 352 628 0990",
    "sg:postcode":"34446",
    "sg:province":"FL",
    "sg:tags":[
        "delicatessen"
    ],
    "wof:name":"Sunny Days Deli",
    "wof:placetype":"venue"
},
  "geometry": {"coordinates":[-82.56086000000001,28.784008],"type":"Point"}
}