{
  "type": "Feature",
  "properties": {
    "addr:full":"3673 US Hwy 90 Milton FL 32571",
    "addr:housenumber":"3673",
    "addr:postcode":"32571",
    "addr:street":"Us Hwy 90",
    "iso:country":"US",
    "sg:address":"3673 US Hwy 90",
    "sg:city":"Milton",
    "sg:classifiers":[
        {
            "category":"Health Services",
            "subcategory":"Doctor",
            "type":"Services"
        }
    ],
    "sg:phone":"+1 850 994 0100",
    "sg:postcode":"32571",
    "sg:province":"FL",
    "sg:tags":[
        "dentist"
    ],
    "wof:name":"Miguel Bernal DDS",
    "wof:placetype":"venue"
},
  "geometry": {"coordinates":[-87.17140999999999,30.594862],"type":"Point"}
}