{
  "type": "Feature",
  "properties": {
    "iso:country":"US",
    "sg:address":"Aventura Mall 19501 Biscayne Blvd",
    "sg:city":"Aventura",
    "sg:classifiers":[
        {
            "category":"Sports & Exercise",
            "subcategory":"Bicycle Rental",
            "type":"Entertainment"
        }
    ],
    "sg:phone":"+1 305 931 0165",
    "sg:postcode":"33180",
    "sg:province":"FL",
    "sg:tags":[
        "wear"
    ],
    "sg:website":"www.lucy.com",
    "wof:name":"Lucy",
    "wof:placetype":"venue"
},
  "geometry": {"coordinates":[-80.144938,25.957102],"type":"Point"}
}