{
  "type": "Feature",
  "properties": {
    "addr:full":"4811 Tamiami Trl Naples FL 34112",
    "addr:housenumber":"4811",
    "addr:postcode":"34112",
    "addr:street":"Tamiami Trl",
    "iso:country":"US",
    "sg:address":"4811 Tamiami Trl",
    "sg:city":"Naples",
    "sg:classifiers":[
        {
            "category":"Shopping",
            "subcategory":"Computers & Home Electronics",
            "type":"Retail Goods"
        }
    ],
    "sg:phone":"+1 239 793 6229",
    "sg:postcode":"34112",
    "sg:province":"FL",
    "sg:tags":[
        "equipment",
        "dealer"
    ],
    "wof:name":"X M Bytes",
    "wof:placetype":"venue"
},
  "geometry": {"coordinates":[-81.749032,26.108507],"type":"Point"}
}