{
  "type": "Feature",
  "properties": {
    "iso:country":"US",
    "sg:address":"10087 NW 57th Ter",
    "sg:city":"Miami",
    "sg:classifiers":[
        {
            "category":"Professional",
            "subcategory":"Management & Consulting",
            "type":"Services"
        }
    ],
    "sg:phone":"+1 305 594 8908",
    "sg:postcode":"33178",
    "sg:province":"FL",
    "sg:tags":[
        "business"
    ],
    "wof:name":"North American Systems Corp",
    "wof:placetype":"venue"
},
  "geometry": {"coordinates":[-80.361368,25.825566],"type":"Point"}
}