{
  "type": "Feature",
  "properties": {
    "iso:country":"US",
    "sg:address":"346 Thornbush Pkwy",
    "sg:city":"Davenport",
    "sg:classifiers":[
        {
            "category":"Professional",
            "subcategory":"Detective & Security Services",
            "type":"Services"
        }
    ],
    "sg:phone":"+1 863 424 6797",
    "sg:postcode":"33837",
    "sg:province":"FL",
    "sg:tags":[
        "information",
        "bureau"
    ],
    "wof:name":"Baatoure Brothers Services",
    "wof:placetype":"venue"
},
  "geometry": {"coordinates":[-81.608932,28.240212],"type":"Point"}
}