{
  "type": "Feature",
  "properties": {
    "iso:country":"US",
    "sg:address":"970 Sunshine Ln",
    "sg:city":"Altamonte Spgs",
    "sg:classifiers":[
        {
            "category":"Manufacturing",
            "subcategory":"Electronics",
            "type":"Manufacturing & Wholesale Goods"
        },
        {
            "category":"Shopping",
            "subcategory":"Computers & Home Electronics",
            "type":"Retail Goods"
        }
    ],
    "sg:phone":"+1 407 862 3363",
    "sg:postcode":"32714",
    "sg:province":"FL",
    "sg:tags":[
        "boards",
        "supply",
        "mfg",
        "p",
        "equipment",
        "design",
        "printed",
        "circuit",
        "electronic"
    ],
    "wof:name":"J M Electronics",
    "wof:placetype":"venue"
},
  "geometry": {"coordinates":[-81.421126,28.655411],"type":"Point"}
}