{
  "type": "Feature",
  "properties": {
    "iso:country":"US",
    "sg:address":"8304 Camphor Tree Dr",
    "sg:city":"Orlando",
    "sg:classifiers":[
        {
            "category":"Restaurant",
            "type":"Food & Drink"
        }
    ],
    "sg:phone":"+1 407 295 5639",
    "sg:postcode":"32810",
    "sg:province":"FL",
    "wof:name":"Amoroso D",
    "wof:placetype":"venue"
},
  "geometry": {"coordinates":[-81.427902,28.631599],"type":"Point"}
}