{
  "type": "Feature",
  "properties": {
    "iso:country":"US",
    "sg:address":"132 3rd Ln",
    "sg:city":"Key Largo",
    "sg:classifiers":[
        {
            "category":"Personal",
            "subcategory":"Beauty Salon",
            "type":"Services"
        }
    ],
    "sg:phone":"+1 305 453 0295",
    "sg:postcode":"33037",
    "sg:province":"FL",
    "sg:tags":[
        "shop"
    ],
    "wof:name":"Hair N There",
    "wof:placetype":"venue"
},
  "geometry": {"coordinates":[-80.413476,25.117861],"type":"Point"}
}