{
  "type": "Feature",
  "properties": {
    "iso:country":"US",
    "sg:address":"1046 Shadick Dr",
    "sg:city":"Orange City",
    "sg:classifiers":[
        {
            "category":"Home & Garden",
            "subcategory":"Building Materials",
            "type":"Retail Goods"
        }
    ],
    "sg:phone":"+1 386 775 7706",
    "sg:postcode":"32763",
    "sg:province":"FL",
    "sg:tags":[
        "door",
        "gate",
        "operating",
        "devices"
    ],
    "wof:name":"Delta Automatic Doors Inc",
    "wof:placetype":"venue"
},
  "geometry": {"coordinates":[-81.283914,28.938558],"type":"Point"}
}