{
  "type": "Feature",
  "properties": {
    "iso:country":"US",
    "sg:address":"315 SE 7th St",
    "sg:city":"Fort Lauderdale",
    "sg:classifiers":[
        {
            "category":"Professional",
            "subcategory":"Secretarial Services",
            "type":"Services"
        }
    ],
    "sg:phone":"+1 954 358 9090",
    "sg:postcode":"33301",
    "sg:province":"FL",
    "sg:tags":[
        "convention",
        "court",
        "reporter"
    ],
    "wof:name":"Bailey & Assoc Reporting",
    "wof:placetype":"venue"
},
  "geometry": {"coordinates":[-80.13918700000001,26.113146],"type":"Point"}
}