{
  "type": "Feature",
  "properties": {
    "iso:country":"US",
    "sg:address":"551 Kingfisher Dr",
    "sg:city":"Kissimmee",
    "sg:classifiers":[
        {
            "category":"Landmark",
            "subcategory":"Tourist Information",
            "type":"Public Place"
        }
    ],
    "sg:phone":"+1 407 254 5100",
    "sg:postcode":"34759",
    "sg:province":"FL",
    "sg:tags":[
        "promoter",
        "tours-operators"
    ],
    "sg:website":"http://www.bristoltrailways.com",
    "wof:name":"Bristol Trailways",
    "wof:placetype":"venue"
},
  "geometry": {"coordinates":[-81.467061,28.098946],"type":"Point"}
}