{
  "type": "Feature",
  "properties": {
    "addr:full":"15551 N US Hwy 301 Citra FL 32113",
    "addr:housenumber":"15551",
    "addr:postcode":"32113",
    "addr:street":"N Us Hwy 301",
    "iso:country":"US",
    "sg:address":"15551 N US Hwy 301",
    "sg:city":"Citra",
    "sg:classifiers":[
        {
            "category":"Retail",
            "subcategory":"Auto Repair",
            "type":"Services"
        }
    ],
    "sg:phone":"+1 352 595 8215",
    "sg:postcode":"32113",
    "sg:province":"FL",
    "sg:tags":[
        "repairing",
        "automobile"
    ],
    "wof:name":"Jones Garage",
    "wof:placetype":"venue"
},
  "geometry": {"coordinates":[-82.134497,29.370049],"type":"Point"}
}