{
  "type": "Feature",
  "properties": {
    "addr:full":"1035 King St Cocoa FL 32922",
    "addr:housenumber":"1035",
    "addr:postcode":"32922",
    "addr:street":"King St",
    "iso:country":"US",
    "sg:address":"1035 King St",
    "sg:city":"Cocoa",
    "sg:classifiers":[
        {
            "category":"Autos & Motor Vehicles",
            "subcategory":"Fuel & Gas Station",
            "type":"Retail Goods"
        }
    ],
    "sg:phone":"+1 321 631 2842",
    "sg:postcode":"32922",
    "sg:province":"FL",
    "sg:tags":[
        "station",
        "gasoline"
    ],
    "wof:name":"Amerada Hess Corporation",
    "wof:placetype":"venue"
},
  "geometry": {"coordinates":[-80.74381200000001,28.35563],"type":"Point"}
}