{
  "type": "Feature",
  "properties": {
    "addr:full":"8923 Teacher Ln Zephyrhills FL 33541",
    "addr:housenumber":"8923",
    "addr:postcode":"33541",
    "addr:street":"Teacher Ln",
    "iso:country":"US",
    "sg:address":"8923 Teacher Ln",
    "sg:city":"Zephyrhills",
    "sg:classifiers":[
        {
            "category":"Professional",
            "subcategory":"Accounting & Tax Preparation",
            "type":"Services"
        }
    ],
    "sg:phone":"+1 813 782 3100",
    "sg:postcode":"33541",
    "sg:province":"FL",
    "sg:tags":[
        "bookkeeping",
        "general"
    ],
    "wof:name":"Easy Tax & Accounting",
    "wof:placetype":"venue"
},
  "geometry": {"coordinates":[-82.199265,28.287428],"type":"Point"}
}