{
  "type": "Feature",
  "properties": {
    "addr:full":"1108 Beville Rd Daytona Beach FL 32114",
    "addr:housenumber":"1108",
    "addr:postcode":"32114",
    "addr:street":"Beville Rd",
    "iso:country":"US",
    "sg:address":"1108 Beville Rd",
    "sg:city":"Daytona Beach",
    "sg:classifiers":[
        {
            "category":"Restaurant",
            "type":"Food & Drink"
        }
    ],
    "sg:phone":"+1 386 239 8988",
    "sg:postcode":"32114",
    "sg:province":"FL",
    "sg:tags":[
        "eating"
    ],
    "wof:name":"Super Buffet",
    "wof:placetype":"venue"
},
  "geometry": {"coordinates":[-81.032454,29.173798],"type":"Point"}
}