{
  "type": "Feature",
  "properties": {
    "addr:full":"623 N Walker St Lake Wales FL 33853",
    "addr:housenumber":"623",
    "addr:postcode":"33853",
    "addr:street":"N Walker St",
    "iso:country":"US",
    "sg:address":"623 N Walker St",
    "sg:city":"Lake Wales",
    "sg:classifiers":[
        {
            "category":"Professional",
            "subcategory":"Business Services",
            "type":"Services"
        }
    ],
    "sg:phone":"+1 863 679 3998",
    "sg:postcode":"33853",
    "sg:province":"FL",
    "sg:tags":[
        "water",
        "treatment"
    ],
    "wof:name":"Harmsco Filtration Products",
    "wof:placetype":"venue"
},
  "geometry": {"coordinates":[-81.59379,27.907381],"type":"Point"}
}