{
  "type": "Feature",
  "properties": {
    "addr:full":"5661 NE 6th Ave Fort Lauderdale FL 33334",
    "addr:housenumber":"5661",
    "addr:postcode":"33334",
    "addr:street":"Ne 6Th Ave",
    "iso:country":"US",
    "sg:address":"5661 NE 6th Ave",
    "sg:city":"Fort Lauderdale",
    "sg:classifiers":[
        {
            "category":"Real Estate",
            "subcategory":"Real Estate Agent",
            "type":"Services"
        }
    ],
    "sg:phone":"+1 954 351 0079",
    "sg:postcode":"33334",
    "sg:province":"FL",
    "wof:name":"Team Gerrity",
    "wof:placetype":"venue"
},
  "geometry": {"coordinates":[-80.13924400000001,26.198014],"type":"Point"}
}