{
  "type": "Feature",
  "properties": {
    "addr:full":"4805 Gulf Blvd St Pete Beach FL 33706",
    "addr:housenumber":"4805",
    "addr:postcode":"33706",
    "addr:street":"Gulf Blvd St Pete Beach",
    "iso:country":"US",
    "sg:address":"4805 Gulf Blvd",
    "sg:city":"St Pete Beach",
    "sg:classifiers":[
        {
            "category":"Shopping",
            "subcategory":"Clothing, Apparel, & Fashions",
            "type":"Retail Goods"
        }
    ],
    "sg:phone":"+1 727 360 7700",
    "sg:postcode":"33706",
    "sg:province":"FL",
    "sg:tags":[
        "sportswear"
    ],
    "wof:name":"Sports City",
    "wof:placetype":"venue"
},
  "geometry": {"coordinates":[-82.740217,27.722091],"type":"Point"}
}