{
  "type": "Feature",
  "properties": {
    "iso:country":"US",
    "sg:address":"11475 NW 34th St",
    "sg:city":"Doral",
    "sg:classifiers":[
        {
            "category":"Manufacturing",
            "subcategory":"Printing",
            "type":"Manufacturing & Wholesale Goods"
        }
    ],
    "sg:phone":"+1 305 468 1656",
    "sg:postcode":"33178",
    "sg:province":"FL",
    "sg:tags":[
        "printer"
    ],
    "wof:name":"EMI Graphics Inc",
    "wof:placetype":"venue"
},
  "geometry": {"coordinates":[-80.323893,25.805826],"type":"Point"}
}