{
  "type": "Feature",
  "properties": {
    "addr:full":"4 James Roy Ave W Palm Coast FL 32137",
    "addr:housenumber":"4",
    "addr:postcode":"32137",
    "addr:street":"James Roy Ave W",
    "iso:country":"US",
    "sg:address":"4 James Roy Ave W",
    "sg:city":"Palm Coast",
    "sg:classifiers":[
        {
            "category":"Home & Garden",
            "subcategory":"Furniture",
            "type":"Retail Goods"
        }
    ],
    "sg:phone":"+1 386 437 1200",
    "sg:postcode":"32137",
    "sg:province":"FL",
    "sg:tags":[
        "moving",
        "store"
    ],
    "wof:name":"Scott Moving & Storage",
    "wof:placetype":"venue"
},
  "geometry": {"coordinates":[-81.19381799999999,29.58738],"type":"Point"}
}