{
  "type": "Feature",
  "properties": {
    "addr:full":"1408 S Burgandy Trl Jacksonville FL 32259",
    "addr:housenumber":"1408",
    "addr:postcode":"32259",
    "addr:street":"S Burgandy Trl",
    "iso:country":"US",
    "sg:address":"1408 S Burgandy Trl",
    "sg:city":"Jacksonville",
    "sg:classifiers":[
        {
            "category":"Professional",
            "subcategory":"Engineering",
            "type":"Services"
        }
    ],
    "sg:phone":"+1 904 230 3650",
    "sg:postcode":"32259",
    "sg:province":"FL",
    "sg:tags":[
        "engineer"
    ],
    "wof:name":"Lucas & Scott Engineering Inc",
    "wof:placetype":"venue"
},
  "geometry": {"coordinates":[-81.60771099999999,30.09506],"type":"Point"}
}