{
  "type": "Feature",
  "properties": {
    "iso:country":"US",
    "sg:address":"50 SE Kindred St",
    "sg:city":"Stuart",
    "sg:classifiers":[
        {
            "category":"Health Services",
            "subcategory":"Hospital",
            "type":"Services"
        }
    ],
    "sg:phone":"+1 772 221 8585",
    "sg:postcode":"34994",
    "sg:province":"FL",
    "sg:tags":[
        "mental"
    ],
    "wof:name":"Suncoast Mental Health Ctr",
    "wof:placetype":"venue"
},
  "geometry": {"coordinates":[-80.251407,27.192499],"type":"Point"}
}