{
  "type": "Feature",
  "properties": {
    "addr:full":"830 Jimmy Ann Dr Daytona Beach FL 32117",
    "addr:housenumber":"830",
    "addr:postcode":"32117",
    "addr:street":"Jimmy Ann Dr",
    "iso:country":"US",
    "sg:address":"830 Jimmy Ann Dr",
    "sg:city":"Daytona Beach",
    "sg:classifiers":[
        {
            "category":"Freight",
            "type":"Transportation"
        }
    ],
    "sg:phone":"+1 386 274 4519",
    "sg:postcode":"32117",
    "sg:province":"FL",
    "sg:tags":[
        "operator",
        "trucking"
    ],
    "wof:name":"Roadway Express Inc",
    "wof:placetype":"venue"
},
  "geometry": {"coordinates":[-81.069682,29.211446],"type":"Point"}
}