{
  "type": "Feature",
  "properties": {
    "addr:full":"3260 US Hwy 92 Longwood FL 32750",
    "addr:housenumber":"3260",
    "addr:postcode":"32750",
    "addr:street":"Us Hwy 92",
    "iso:country":"US",
    "sg:address":"3260 US Hwy 92",
    "sg:city":"Longwood",
    "sg:classifiers":[
        {
            "category":"Manufacturing",
            "subcategory":"Signs",
            "type":"Manufacturing & Wholesale Goods"
        }
    ],
    "sg:phone":"+1 407 467 1656",
    "sg:postcode":"32750",
    "sg:province":"FL",
    "sg:tags":[
        "advertising",
        "specialty"
    ],
    "wof:name":"Sign Factory",
    "wof:placetype":"venue"
},
  "geometry": {"coordinates":[-81.313109,28.727365],"type":"Point"}
}