{
  "type": "Feature",
  "properties": {
    "iso:country":"US",
    "sg:address":"1715 Silver Star Rd",
    "sg:city":"Orlando",
    "sg:classifiers":[
        {
            "category":"Wholesale",
            "subcategory":"Plants",
            "type":"Manufacturing & Wholesale Goods"
        }
    ],
    "sg:phone":"+1 407 293 2451",
    "sg:postcode":"32804",
    "sg:province":"FL",
    "sg:tags":[
        "orchid",
        "grower",
        "supply"
    ],
    "wof:name":"Tropical Plant Products",
    "wof:placetype":"venue"
},
  "geometry": {"coordinates":[-81.40508800000001,28.578306],"type":"Point"}
}