{
  "type": "Feature",
  "properties": {
    "iso:country":"US",
    "sg:address":"3607 W Santiago St",
    "sg:city":"Tampa",
    "sg:classifiers":[
        {
            "category":"Professional",
            "subcategory":"Employment Agencies",
            "type":"Services"
        }
    ],
    "sg:phone":"+1 813 831 6459",
    "sg:postcode":"33629",
    "sg:province":"FL",
    "wof:name":"Artillery Sales",
    "wof:placetype":"venue"
},
  "geometry": {"coordinates":[-82.50381899999999,27.919135],"type":"Point"}
}