{
  "type": "Feature",
  "properties": {
    "addr:full":"1716 Ocean Shore Blvd Ormond Beach FL 32176",
    "addr:housenumber":"1716",
    "addr:postcode":"32176",
    "addr:street":"Ocean Shore Blvd",
    "iso:country":"US",
    "sg:address":"1716 Ocean Shore Blvd",
    "sg:city":"Ormond Beach",
    "sg:classifiers":[
        {
            "category":"Food & Beverages",
            "subcategory":"Groceries & Convenience Stores",
            "type":"Retail Goods"
        }
    ],
    "sg:phone":"+1 386 441 6094",
    "sg:postcode":"32176",
    "sg:province":"FL",
    "wof:name":"Handy-Way",
    "wof:placetype":"venue"
},
  "geometry": {"coordinates":[-81.059513,29.334685],"type":"Point"}
}