{
  "type": "Feature",
  "properties": {
    "addr:full":"5455 Jaeger Rd Naples FL 34109",
    "addr:housenumber":"5455",
    "addr:postcode":"34109",
    "addr:street":"Jaeger Rd",
    "iso:country":"US",
    "sg:address":"5455 Jaeger Rd",
    "sg:city":"Naples",
    "sg:classifiers":[
        {
            "category":"Insurance",
            "subcategory":"Insurance Agent",
            "type":"Services"
        }
    ],
    "sg:phone":"+1 239 593 4044",
    "sg:postcode":"34109",
    "sg:province":"FL",
    "wof:name":"Rick Loux Insurance",
    "wof:placetype":"venue"
},
  "geometry": {"coordinates":[-81.785096,26.212544],"type":"Point"}
}