{
  "type": "Feature",
  "properties": {
    "iso:country":"US",
    "sg:address":"4125 Cleveland Ave",
    "sg:city":"Fort Myers",
    "sg:classifiers":[
        {
            "category":"Food & Beverages",
            "subcategory":"Candy",
            "type":"Retail Goods"
        }
    ],
    "sg:phone":"+1 239 275 0775",
    "sg:postcode":"33901",
    "sg:province":"FL",
    "sg:tags":[
        "confectionery"
    ],
    "wof:name":"Bourbon Street Candy Inc",
    "wof:placetype":"venue"
},
  "geometry": {"coordinates":[-81.87179399999999,26.602732],"type":"Point"}
}