{
  "type": "Feature",
  "properties": {
    "addr:full":"8040 NW 154th St Hialeah FL 33016",
    "addr:housenumber":"8040",
    "addr:postcode":"33016",
    "addr:street":"Nw 154Th St",
    "iso:country":"US",
    "sg:address":"8040 NW 154th St",
    "sg:city":"Hialeah",
    "sg:classifiers":[
        {
            "category":"Building & Trades",
            "subcategory":"Locksmith",
            "type":"Services"
        }
    ],
    "sg:phone":"+1 305 423 0176",
    "sg:postcode":"33016",
    "sg:province":"FL",
    "sg:tags":[
        "key"
    ],
    "wof:name":"7 Days Emergency Locksmith Service of",
    "wof:placetype":"venue"
},
  "geometry": {"coordinates":[-80.33091899999999,25.913099],"type":"Point"}
}