{
  "type": "Feature",
  "properties": {
    "iso:country":"US",
    "sg:address":"1612 Rowe Ave",
    "sg:city":"Jacksonville",
    "sg:classifiers":[
        {
            "category":"Retail",
            "subcategory":"Auto Repair",
            "type":"Services"
        }
    ],
    "sg:phone":"+1 904 768 0566",
    "sg:postcode":"32208",
    "sg:province":"FL",
    "sg:tags":[
        "automotive"
    ],
    "wof:name":"Allmond Wrecker Service",
    "wof:placetype":"venue"
},
  "geometry": {"coordinates":[-81.681755,30.385161],"type":"Point"}
}