{
  "type": "Feature",
  "properties": {
    "addr:full":"1950 Jamaica St Navarre FL 32566",
    "addr:housenumber":"1950",
    "addr:postcode":"32566",
    "addr:street":"Jamaica St",
    "iso:country":"US",
    "sg:address":"1950 Jamaica St",
    "sg:city":"Navarre",
    "sg:classifiers":[
        {
            "category":"Social Services",
            "subcategory":"Child Care",
            "type":"Services"
        }
    ],
    "sg:phone":"+1 850 515 0817",
    "sg:postcode":"32566",
    "sg:province":"FL",
    "sg:tags":[
        "nursery",
        "day"
    ],
    "wof:name":"Shepards Touch Home Child Care",
    "wof:placetype":"venue"
},
  "geometry": {"coordinates":[-86.90081499999999,30.407624],"type":"Point"}
}