{
  "type": "Feature",
  "properties": {
    "addr:full":"15008 SW 139th Pl Miami FL 33186",
    "addr:housenumber":"15008",
    "addr:postcode":"33186",
    "addr:street":"Sw 139Th Pl",
    "iso:country":"US",
    "sg:address":"15008 SW 139th Pl",
    "sg:city":"Miami",
    "sg:classifiers":[
        {
            "category":"Building & Trades",
            "subcategory":"Construction",
            "type":"Services"
        }
    ],
    "sg:phone":"+1 305 252 2106",
    "sg:postcode":"33186",
    "sg:province":"FL",
    "wof:name":"Fiona Lubega",
    "wof:placetype":"venue"
},
  "geometry": {"coordinates":[-80.419586,25.628411],"type":"Point"}
}