{
  "type": "Feature",
  "properties": {
    "addr:full":"1969 10th Ave N Lake Worth FL 33461",
    "addr:housenumber":"1969",
    "addr:postcode":"33461",
    "addr:street":"10Th Ave N",
    "iso:country":"US",
    "sg:address":"1969 10th Ave N",
    "sg:city":"Lake Worth",
    "sg:classifiers":[
        {
            "category":"Wholesale",
            "subcategory":"Auto Parts",
            "type":"Manufacturing & Wholesale Goods"
        }
    ],
    "sg:phone":"+1 561 588 1958",
    "sg:postcode":"33461",
    "sg:province":"FL",
    "sg:tags":[
        "automobile",
        "supply"
    ],
    "wof:name":"Cold Air Distributors",
    "wof:placetype":"venue"
},
  "geometry": {"coordinates":[-80.071241,26.627883],"type":"Point"}
}