{
  "type": "Feature",
  "properties": {
    "iso:country":"US",
    "sg:address":"4971 Calypso Cay Way",
    "sg:city":"Kissimmee",
    "sg:classifiers":[
        {
            "category":"Travel",
            "subcategory":"Hotels & Motels",
            "type":"Entertainment"
        }
    ],
    "sg:phone":"+1 407 396 8700",
    "sg:postcode":"34746",
    "sg:province":"FL",
    "sg:tags":[
        "lodging"
    ],
    "sg:website":"http://www.orlandosouthlakebuenavistasuites.hamptoninn.com",
    "wof:name":"Hampton Inn and Suites",
    "wof:placetype":"venue"
},
  "geometry": {"coordinates":[-81.482348,28.338173],"type":"Point"}
}