{
  "type": "Feature",
  "properties": {
    "addr:full":"5731 NW 37th St Miami FL 33166",
    "addr:housenumber":"5731",
    "addr:postcode":"33166",
    "addr:street":"Nw 37Th St",
    "iso:country":"US",
    "sg:address":"5731 NW 37th St",
    "sg:city":"Miami",
    "sg:classifiers":[
        {
            "category":"Building & Trades",
            "subcategory":"Electrical",
            "type":"Services"
        }
    ],
    "sg:phone":"+1 305 871 4446",
    "sg:postcode":"33166",
    "sg:province":"FL",
    "sg:tags":[
        "electrical",
        "contractor"
    ],
    "wof:name":"Livefrog Inc",
    "wof:placetype":"venue"
},
  "geometry": {"coordinates":[-80.29060699999999,25.808162],"type":"Point"}
}