{
  "type": "Feature",
  "properties": {
    "iso:country":"US",
    "sg:address":"8668 Navarre Pkwy",
    "sg:city":"Navarre",
    "sg:classifiers":[
        {
            "category":"Retail",
            "subcategory":"Animal Services",
            "type":"Services"
        }
    ],
    "sg:phone":"+1 850 939 1635",
    "sg:postcode":"32566",
    "sg:province":"FL",
    "sg:tags":[
        "pet",
        "boarding",
        "sitting"
    ],
    "wof:name":"All My Children Pet Sitting",
    "wof:placetype":"venue"
},
  "geometry": {"coordinates":[-86.86166299999999,30.401463],"type":"Point"}
}