{
  "type": "Feature",
  "properties": {
    "addr:full":"7090 60th Way N Pinellas Park FL 33781",
    "addr:housenumber":"7090",
    "addr:postcode":"33781",
    "addr:street":"60Th Way N",
    "iso:country":"US",
    "sg:address":"7090 60th Way N",
    "sg:city":"Pinellas Park",
    "sg:classifiers":[
        {
            "category":"Building & Trades",
            "subcategory":"Construction",
            "type":"Services"
        }
    ],
    "sg:phone":"+1 727 541 5482",
    "sg:postcode":"33781",
    "sg:province":"FL",
    "sg:tags":[
        "nonresidential"
    ],
    "wof:name":"Eric Lowe LLC",
    "wof:placetype":"venue"
},
  "geometry": {"coordinates":[-82.71709,27.83562],"type":"Point"}
}