{
  "type": "Feature",
  "properties": {
    "addr:full":"3090 N Pace Blvd Pensacola FL 32505",
    "addr:housenumber":"3090",
    "addr:postcode":"32505",
    "addr:street":"N Pace Blvd",
    "iso:country":"US",
    "sg:address":"3090 N Pace Blvd",
    "sg:city":"Pensacola",
    "sg:classifiers":[
        {
            "category":"Manufacturing",
            "subcategory":"Signs",
            "type":"Manufacturing & Wholesale Goods"
        }
    ],
    "sg:phone":"+1 850 469 9999",
    "sg:postcode":"32505",
    "sg:province":"FL",
    "sg:tags":[
        "specialty",
        "mfg"
    ],
    "wof:name":"Signs Now",
    "wof:placetype":"venue"
},
  "geometry": {"coordinates":[-87.23993900000001,30.441607],"type":"Point"}
}