{
  "type": "Feature",
  "properties": {
    "addr:full":"3650 Weston Rd Davie FL 33331",
    "addr:housenumber":"3650",
    "addr:postcode":"33331",
    "addr:street":"Weston Rd",
    "iso:country":"US",
    "sg:address":"3650 Weston Rd",
    "sg:city":"Davie",
    "sg:classifiers":[
        {
            "category":"Autos & Motor Vehicles",
            "subcategory":"Automobile Sales",
            "type":"Retail Goods"
        },
        {
            "category":"Retail",
            "subcategory":"Auto Rental",
            "type":"Services"
        }
    ],
    "sg:phone":"+1 954 385 5044",
    "sg:postcode":"33331",
    "sg:province":"FL",
    "sg:tags":[
        "truck",
        "leasing",
        "car"
    ],
    "sg:website":"http://www.enterprise.com/car_rental/deeplinkmap.do?gpbr=41G9&bid=004&cnty=US&arc=YPTRL01&cm_mmc=Yellowpages.com-_-IYP-_-Tradelisting-_-branch",
    "wof:name":"Enterprise Rent-A-Car",
    "wof:placetype":"venue"
},
  "geometry": {"coordinates":[-80.36250800000001,26.074276],"type":"Point"}
}