{
  "type": "Feature",
  "properties": {
    "iso:country":"US",
    "sg:address":"4747 Hollywood Blvd",
    "sg:city":"Hollywood",
    "sg:classifiers":[
        {
            "category":"Health Services",
            "subcategory":"Medical Lab",
            "type":"Services"
        }
    ],
    "sg:phone":"+1 954 965 2248",
    "sg:postcode":"33021",
    "sg:province":"FL",
    "sg:tags":[
        "detection",
        "equipment",
        "drug"
    ],
    "sg:website":"www.doctorsos.org",
    "wof:name":"Sobriety",
    "wof:placetype":"venue"
},
  "geometry": {"coordinates":[-80.190195,26.010575],"type":"Point"}
}