{
  "type": "Feature",
  "properties": {
    "iso:country":"US",
    "sg:address":"3314 Easy St",
    "sg:city":"Port Charlotte",
    "sg:classifiers":[
        {
            "category":"Home & Garden",
            "subcategory":"Carpets & Floor Coverings",
            "type":"Retail Goods"
        }
    ],
    "sg:phone":"+1 941 627 3934",
    "sg:postcode":"33952",
    "sg:province":"FL",
    "wof:name":"EZ Eg Carpet Service Inc",
    "wof:placetype":"venue"
},
  "geometry": {"coordinates":[-82.089673,26.981589],"type":"Point"}
}