{
  "type": "Feature",
  "properties": {
    "iso:country":"US",
    "sg:address":"21587 State Rd 71 N",
    "sg:city":"Altha",
    "sg:classifiers":[
        {
            "category":"Food & Beverages",
            "subcategory":"Specialty",
            "type":"Retail Goods"
        }
    ],
    "sg:phone":"+1 850 674 8227",
    "sg:postcode":"32421",
    "sg:province":"FL",
    "wof:name":"Healthy Living Products",
    "wof:placetype":"venue"
},
  "geometry": {"coordinates":[-85.126952,30.519934],"type":"Point"}
}