{
  "type": "Feature",
  "properties": {
    "addr:full":"12320 SW 224th St Miami FL 33170",
    "addr:housenumber":"12320",
    "addr:postcode":"33170",
    "addr:street":"Sw 224Th St",
    "iso:country":"US",
    "sg:address":"12320 SW 224th St",
    "sg:city":"Miami",
    "sg:classifiers":[
        {
            "category":"Personal",
            "subcategory":"Beauty Salon",
            "type":"Services"
        }
    ],
    "sg:phone":"+1 305 257 5083",
    "sg:postcode":"33170",
    "sg:province":"FL",
    "wof:name":"Ruby's Places Corp",
    "wof:placetype":"venue"
},
  "geometry": {"coordinates":[-80.39216500000001,25.558725],"type":"Point"}
}