{
  "type": "Feature",
  "properties": {
    "iso:country":"US",
    "sg:address":"6706 Biscayne Blvd",
    "sg:city":"Miami",
    "sg:classifiers":[
        {
            "category":"Personal",
            "subcategory":"Nail Salon",
            "type":"Services"
        }
    ],
    "sg:phone":"+1 305 757 1597",
    "sg:postcode":"33138",
    "sg:province":"FL",
    "wof:name":"VN Nails",
    "wof:placetype":"venue"
},
  "geometry": {"coordinates":[-80.184223,25.837614],"type":"Point"}
}