{
  "type": "Feature",
  "properties": {
    "addr:full":"5130 Red Bay Ln Grant FL 32949",
    "addr:housenumber":"5130",
    "addr:postcode":"32949",
    "addr:street":"Red Bay Ln",
    "iso:country":"US",
    "sg:address":"5130 Red Bay Ln",
    "sg:city":"Grant",
    "sg:classifiers":[
        {
            "category":"Banks & Credit Unions",
            "subcategory":"Financial Services",
            "type":"Services"
        }
    ],
    "sg:phone":"+1 321 724 1897",
    "sg:postcode":"32949",
    "sg:province":"FL",
    "sg:tags":[
        "company",
        "holding"
    ],
    "wof:name":"Desro Holdings LLC",
    "wof:placetype":"venue"
},
  "geometry": {"coordinates":[-80.552571,27.934102],"type":"Point"}
}