{
  "type": "Feature",
  "properties": {
    "addr:full":"3301 NW 79th St Miami FL 33147",
    "addr:housenumber":"3301",
    "addr:postcode":"33147",
    "addr:street":"Nw 79Th St",
    "iso:country":"US",
    "sg:address":"3301 NW 79th St",
    "sg:city":"Miami",
    "sg:classifiers":[
        {
            "category":"Autos & Motor Vehicles",
            "subcategory":"Automobile Sales",
            "type":"Retail Goods"
        }
    ],
    "sg:phone":"+1 305 835 1900",
    "sg:postcode":"33147",
    "sg:province":"FL",
    "sg:tags":[
        "car",
        "used"
    ],
    "wof:name":"Hot Wheels Auto Brokers",
    "wof:placetype":"venue"
},
  "geometry": {"coordinates":[-80.251953,25.8458],"type":"Point"}
}