{
  "type": "Feature",
  "properties": {
    "addr:full":"3506 Exchange Ave Naples FL 34104",
    "addr:housenumber":"3506",
    "addr:postcode":"34104",
    "addr:street":"Exchange Ave",
    "iso:country":"US",
    "sg:address":"3506 Exchange Ave",
    "sg:city":"Naples",
    "sg:classifiers":[
        {
            "category":"Professional",
            "type":"Services"
        }
    ],
    "sg:phone":"+1 239 643 0962",
    "sg:postcode":"34104",
    "sg:province":"FL",
    "sg:tags":[
        "establishment"
    ],
    "wof:name":"Richardson & Assoc Inc",
    "wof:placetype":"venue"
},
  "geometry": {"coordinates":[-81.76058,26.158694],"type":"Point"}
}