{
  "type": "Feature",
  "properties": {
    "iso:country":"US",
    "sg:address":"6444 W Homosassa Trl",
    "sg:city":"Homosassa",
    "sg:classifiers":[
        {
            "category":"Freight",
            "type":"Transportation"
        }
    ],
    "sg:phone":"+1 352 628 0708",
    "sg:postcode":"34448",
    "sg:province":"FL",
    "sg:tags":[
        "courier"
    ],
    "wof:name":"Five Star Enterprises",
    "wof:placetype":"venue"
},
  "geometry": {"coordinates":[-82.541293,28.818458],"type":"Point"}
}