{
  "type": "Feature",
  "properties": {
    "iso:country":"US",
    "sg:address":"12858 85th Rd N",
    "sg:city":"West Palm Beach",
    "sg:classifiers":[
        {
            "category":"Professional",
            "subcategory":"Business Services",
            "type":"Services"
        }
    ],
    "sg:phone":"+1 561 793 9200",
    "sg:postcode":"33412",
    "sg:province":"FL",
    "sg:tags":[
        "repossessing"
    ],
    "wof:name":"Rap Research & Recovery",
    "wof:placetype":"venue"
},
  "geometry": {"coordinates":[-80.24280400000001,26.803444],"type":"Point"}
}