{
  "type": "Feature",
  "properties": {
    "addr:full":"199 N Goldenrod Rd Orlando FL 32807",
    "addr:housenumber":"199",
    "addr:postcode":"32807",
    "addr:street":"N Goldenrod Rd",
    "iso:country":"US",
    "sg:address":"199 N Goldenrod Rd",
    "sg:city":"Orlando",
    "sg:classifiers":[
        {
            "category":"Home & Garden",
            "subcategory":"Garden Supply",
            "type":"Retail Goods"
        }
    ],
    "sg:phone":"+1 407 383 0694",
    "sg:postcode":"32807",
    "sg:province":"FL",
    "sg:tags":[
        "lawn",
        "mower"
    ],
    "wof:name":"Mower Shop",
    "wof:placetype":"venue"
},
  "geometry": {"coordinates":[-81.285844,28.551937],"type":"Point"}
}