{
  "type": "Feature",
  "properties": {
    "addr:full":"337 Jacksonville Dr Jacksonville Bch FL 32250",
    "addr:housenumber":"337",
    "addr:postcode":"32250",
    "addr:street":"Jacksonville Dr",
    "iso:country":"US",
    "sg:address":"337 Jacksonville Dr",
    "sg:city":"Jacksonville Bch",
    "sg:classifiers":[
        {
            "category":"Building & Trades",
            "subcategory":"Cleaning & Sanitation",
            "type":"Services"
        }
    ],
    "sg:phone":"+1 904 242 9394",
    "sg:postcode":"32250",
    "sg:province":"FL",
    "sg:tags":[
        "house"
    ],
    "wof:name":"As You Like It Housekeeping",
    "wof:placetype":"venue"
},
  "geometry": {"coordinates":[-81.388828,30.260184],"type":"Point"}
}