{
  "type": "Feature",
  "properties": {
    "iso:country":"US",
    "sg:address":"97 Tollgate Trl",
    "sg:city":"Longwood",
    "sg:classifiers":[
        {
            "category":"Health Services",
            "subcategory":"Chiropractor",
            "type":"Services"
        }
    ],
    "sg:phone":"+1 407 331 4040",
    "sg:postcode":"32750",
    "sg:province":"FL",
    "wof:name":"Darrow Chiropractor Clinic",
    "wof:placetype":"venue"
},
  "geometry": {"coordinates":[-81.374702,28.698299],"type":"Point"}
}