{
  "type": "Feature",
  "properties": {
    "addr:full":"893 E Palmetto Park Rd Boca Raton FL 33432",
    "addr:housenumber":"893",
    "addr:postcode":"33432",
    "addr:street":"E Palmetto Park Rd",
    "iso:country":"US",
    "sg:address":"893 E Palmetto Park Rd",
    "sg:city":"Boca Raton",
    "sg:classifiers":[
        {
            "category":"Government",
            "subcategory":"Police Station",
            "type":"Public Place"
        }
    ],
    "sg:phone":"+1 561 347 3029",
    "sg:postcode":"33432",
    "sg:province":"FL",
    "sg:tags":[
        "department"
    ],
    "wof:name":"Boca Raton Police Annex",
    "wof:placetype":"venue"
},
  "geometry": {"coordinates":[-80.072948,26.350711],"type":"Point"}
}