{
  "type": "Feature",
  "properties": {
    "iso:country":"US",
    "sg:address":"2401 Monument Rd",
    "sg:city":"Jacksonville",
    "sg:classifiers":[
        {
            "category":"Health Services",
            "subcategory":"Doctor",
            "type":"Services"
        }
    ],
    "sg:phone":"+1 904 642 0337",
    "sg:postcode":"32225",
    "sg:province":"FL",
    "sg:tags":[
        "physician",
        "surgeon"
    ],
    "wof:name":"Solantic Arlington",
    "wof:placetype":"venue"
},
  "geometry": {"coordinates":[-81.506817,30.354228],"type":"Point"}
}