{
  "type": "Feature",
  "properties": {
    "addr:full":"2101 Brickell Ave # 1211 Miami FL 33129",
    "addr:housenumber":"2101",
    "addr:postcode":"33129",
    "addr:street":"Brickell Ave # 1211",
    "iso:country":"US",
    "sg:address":"2101 Brickell Ave # 1211",
    "sg:city":"Miami",
    "sg:classifiers":[
        {
            "category":"Communications",
            "subcategory":"Film & Video Production",
            "type":"Services"
        },
        {
            "category":"Communications",
            "subcategory":"Television Station",
            "type":"Services"
        }
    ],
    "sg:phone":"+1 646 267 7656",
    "sg:postcode":"33129",
    "sg:province":"FL",
    "sg:tags":[
        "companies-film",
        "producer",
        "tv",
        "program",
        "radio",
        "distributor"
    ],
    "wof:name":"Fabilous Entertainment, Corp.",
    "wof:placetype":"venue"
},
  "geometry": {"coordinates":[-80.201543,25.75189],"type":"Point"}
}