{
  "type": "Feature",
  "properties": {
    "iso:country":"US",
    "sg:address":"8060 Mainline Pkwy",
    "sg:city":"Fort Myers",
    "sg:classifiers":[
        {
            "category":"Building & Trades",
            "subcategory":"Construction",
            "type":"Services"
        }
    ],
    "sg:phone":"+1 239 482 3033",
    "sg:postcode":"33912",
    "sg:province":"FL",
    "sg:tags":[
        "contractor"
    ],
    "wof:name":"Phillips & Jordan Incorporated",
    "wof:placetype":"venue"
},
  "geometry": {"coordinates":[-81.82262299999999,26.498168],"type":"Point"}
}