{
  "type": "Feature",
  "properties": {
    "iso:country":"US",
    "sg:address":"3680 Interstate Park Way",
    "sg:city":"Riviera Beach",
    "sg:classifiers":[
        {
            "category":"Freight",
            "type":"Transportation"
        }
    ],
    "sg:phone":"+1 561 844 3848",
    "sg:postcode":"33404",
    "sg:province":"FL",
    "sg:tags":[
        "mover"
    ],
    "wof:name":"Fazio's Moving Inc",
    "wof:placetype":"venue"
},
  "geometry": {"coordinates":[-80.094302,26.776401],"type":"Point"}
}