{
  "type": "Feature",
  "properties": {
    "iso:country":"US",
    "sg:address":"1216 NE 8th Ave",
    "sg:city":"Fort Lauderdale",
    "sg:classifiers":[
        {
            "category":"Retail",
            "subcategory":"Auto Repair",
            "type":"Services"
        }
    ],
    "sg:phone":"+1 954 523 2006",
    "sg:postcode":"33304",
    "sg:province":"FL",
    "sg:tags":[
        "body",
        "automobile",
        "painting"
    ],
    "wof:name":"United Auto Body Collision Inc",
    "wof:placetype":"venue"
},
  "geometry": {"coordinates":[-80.135745,26.142145],"type":"Point"}
}