{
  "type": "Feature",
  "properties": {
    "addr:full":"6350 Bonnie Ct St Cloud FL 34771",
    "addr:housenumber":"6350",
    "addr:postcode":"34771",
    "addr:street":"Bonnie Ct",
    "iso:country":"US",
    "sg:address":"6350 Bonnie Ct",
    "sg:city":"St Cloud",
    "sg:classifiers":[
        {
            "category":"Building & Trades",
            "subcategory":"Cleaning & Sanitation",
            "type":"Services"
        }
    ],
    "sg:phone":"+1 407 251 5335",
    "sg:postcode":"34771",
    "sg:province":"FL",
    "sg:tags":[
        "janitor"
    ],
    "wof:name":"Accident Trauma Scene Cleaners",
    "wof:placetype":"venue"
},
  "geometry": {"coordinates":[-81.183297,28.279067],"type":"Point"}
}