{
  "type": "Feature",
  "properties": {
    "iso:country":"US",
    "sg:address":"5800 Sheridan St",
    "sg:city":"Hollywood",
    "sg:classifiers":[
        {
            "category":"Professional",
            "subcategory":"Lawyer & Legal Services",
            "type":"Services"
        }
    ],
    "sg:phone":"+1 954 522 5926",
    "sg:postcode":"33021",
    "sg:province":"FL",
    "sg:tags":[
        "attorney"
    ],
    "wof:name":"Ticket Clinic A Law Firm",
    "wof:placetype":"venue"
},
  "geometry": {"coordinates":[-80.205139,26.032283],"type":"Point"}
}