{
  "type": "Feature",
  "properties": {
    "iso:country":"US",
    "sg:address":"13293 SE 107th Ct",
    "sg:city":"Ocklawaha",
    "sg:classifiers":[
        {
            "category":"Personal",
            "subcategory":"Beauty Salon",
            "type":"Services"
        }
    ],
    "sg:phone":"+1 352 620 2772",
    "sg:postcode":"32179",
    "sg:province":"FL",
    "sg:tags":[
        "shop"
    ],
    "wof:name":"Ellens New Images",
    "wof:placetype":"venue"
},
  "geometry": {"coordinates":[-81.97410499999999,29.029119],"type":"Point"}
}