{
  "type": "Feature",
  "properties": {
    "addr:full":"3501 N University Dr Pompano Beach FL 33065",
    "addr:housenumber":"3501",
    "addr:postcode":"33065",
    "addr:street":"N University Dr",
    "iso:country":"US",
    "sg:address":"3501 N University Dr",
    "sg:city":"Pompano Beach",
    "sg:classifiers":[
        {
            "category":"Professional",
            "subcategory":"Accounting & Tax Preparation",
            "type":"Services"
        }
    ],
    "sg:phone":"+1 954 341 2183",
    "sg:postcode":"33065",
    "sg:province":"FL",
    "wof:name":"CL Claimswatch Inc",
    "wof:placetype":"venue"
},
  "geometry": {"coordinates":[-80.25002600000001,26.272986],"type":"Point"}
}