{
  "type": "Feature",
  "properties": {
    "addr:full":"7 Rotonda Cir Rotonda West FL 33947",
    "addr:postcode":"33947",
    "addr:street":"Rotonda Cir",
    "iso:country":"US",
    "sg:address":"7 Rotonda Cir",
    "sg:city":"Rotonda West",
    "sg:classifiers":[
        {
            "category":"Wholesale",
            "subcategory":"Motor Vehicles",
            "type":"Manufacturing & Wholesale Goods"
        }
    ],
    "sg:phone":"+1 941 697 0938",
    "sg:postcode":"33947",
    "sg:province":"FL",
    "wof:name":"Addison of Florida Inc",
    "wof:placetype":"venue"
},
  "geometry": {"coordinates":[-82.289462,26.877957],"type":"Point"}
}