{
  "type": "Feature",
  "properties": {
    "addr:full":"42 S Blue Angel Pkwy Pensacola FL 32506",
    "addr:housenumber":"42",
    "addr:postcode":"32506",
    "addr:street":"S Blue Angel Pkwy",
    "iso:country":"US",
    "sg:address":"42 S Blue Angel Pkwy",
    "sg:city":"Pensacola",
    "sg:classifiers":[
        {
            "category":"Personal",
            "subcategory":"Nail Salon",
            "type":"Services"
        }
    ],
    "sg:phone":"+1 850 454 0201",
    "sg:postcode":"32506",
    "sg:province":"FL",
    "wof:name":"Starlight Nails 2",
    "wof:placetype":"venue"
},
  "geometry": {"coordinates":[-87.342522,30.40081],"type":"Point"}
}