{
  "type": "Feature",
  "properties": {
    "addr:full":"5650 Timuquana Rd Jacksonville FL 32210",
    "addr:housenumber":"5650",
    "addr:postcode":"32210",
    "addr:street":"Timuquana Rd",
    "iso:country":"US",
    "sg:address":"5650 Timuquana Rd",
    "sg:city":"Jacksonville",
    "sg:classifiers":[
        {
            "category":"Insurance",
            "subcategory":"Insurance Agent",
            "type":"Services"
        }
    ],
    "sg:phone":"+1 904 771 2066",
    "sg:postcode":"32210",
    "sg:province":"FL",
    "wof:name":"State Farm Insurance",
    "wof:placetype":"venue"
},
  "geometry": {"coordinates":[-81.72825,30.247307],"type":"Point"}
}