{
  "type": "Feature",
  "properties": {
    "addr:full":"3430 SW 59th Ter Davie FL 33314",
    "addr:housenumber":"3430",
    "addr:postcode":"33314",
    "addr:street":"Sw 59Th Ter",
    "iso:country":"US",
    "sg:address":"3430 SW 59th Ter",
    "sg:city":"Davie",
    "sg:classifiers":[
        {
            "category":"Professional",
            "subcategory":"Business Services",
            "type":"Services"
        }
    ],
    "sg:phone":"+1 954 791 7005",
    "sg:postcode":"33314",
    "sg:province":"FL",
    "sg:tags":[
        "pool",
        "swimming"
    ],
    "wof:name":"Southern Coast Pool Svc",
    "wof:placetype":"venue"
},
  "geometry": {"coordinates":[-80.227242,26.078234],"type":"Point"}
}