{
  "type": "Feature",
  "properties": {
    "addr:full":"405 S Riverhills Dr Tampa FL 33617",
    "addr:housenumber":"405",
    "addr:postcode":"33617",
    "addr:street":"S Riverhills Dr",
    "iso:country":"US",
    "sg:address":"405 S Riverhills Dr",
    "sg:city":"Tampa",
    "sg:classifiers":[
        {
            "category":"Education",
            "subcategory":"School",
            "type":"Public Place"
        }
    ],
    "sg:phone":"+1 813 987 6911",
    "sg:postcode":"33617",
    "sg:province":"FL",
    "sg:tags":[
        "elementary"
    ],
    "wof:name":"Riverhills Elementary School",
    "wof:placetype":"venue"
},
  "geometry": {"coordinates":[-82.384929,28.02165],"type":"Point"}
}