{
  "type": "Feature",
  "properties": {
    "iso:country":"US",
    "sg:address":"184 S Hibiscus Dr",
    "sg:city":"Miami Beach",
    "sg:classifiers":[
        {
            "category":"Building & Trades",
            "subcategory":"Locksmith",
            "type":"Services"
        }
    ],
    "sg:phone":"+1 305 200 0224",
    "sg:postcode":"33139",
    "sg:province":"FL",
    "sg:tags":[
        "key"
    ],
    "wof:name":"7 Day Always Emergency Locksmith",
    "wof:placetype":"venue"
},
  "geometry": {"coordinates":[-80.15989500000001,25.782288],"type":"Point"}
}