{
  "type": "Feature",
  "properties": {
    "addr:full":"17311 Boca Club Blvd Boca Raton FL 33487",
    "addr:housenumber":"17311",
    "addr:postcode":"33487",
    "addr:street":"Boca Club Blvd",
    "iso:country":"US",
    "sg:address":"17311 Boca Club Blvd",
    "sg:city":"Boca Raton",
    "sg:classifiers":[
        {
            "category":"Wholesale",
            "subcategory":"Vending Machines",
            "type":"Manufacturing & Wholesale Goods"
        }
    ],
    "sg:phone":"+1 561 995 0779",
    "sg:postcode":"33487",
    "sg:province":"FL",
    "sg:tags":[
        "operator"
    ],
    "wof:name":"M R M Vending International",
    "wof:placetype":"venue"
},
  "geometry": {"coordinates":[-80.105059,26.420893],"type":"Point"}
}