{
  "type": "Feature",
  "properties": {
    "addr:full":"2306 Ridgeside Rd Apopka FL 32712",
    "addr:housenumber":"2306",
    "addr:postcode":"32712",
    "addr:street":"Ridgeside Rd",
    "iso:country":"US",
    "sg:address":"2306 Ridgeside Rd",
    "sg:city":"Apopka",
    "sg:classifiers":[
        {
            "category":"Manufacturing",
            "subcategory":"Electronics",
            "type":"Manufacturing & Wholesale Goods"
        }
    ],
    "sg:phone":"+1 407 884 5725",
    "sg:postcode":"32712",
    "sg:province":"FL",
    "sg:tags":[
        "apparatus",
        "mfg"
    ],
    "wof:name":"Lucent Technologies",
    "wof:placetype":"venue"
},
  "geometry": {"coordinates":[-81.466607,28.696702],"type":"Point"}
}