{
  "type": "Feature",
  "properties": {
    "iso:country":"US",
    "sg:address":"2259 Citrus Blvd",
    "sg:city":"Leesburg",
    "sg:classifiers":[
        {
            "category":"Restaurant",
            "type":"Food & Drink"
        }
    ],
    "sg:menulink":"http://www.allmenus.com/fl/leesburg/62201-international-super-buffet/menu/",
    "sg:phone":"+1 352 326 9888",
    "sg:postcode":"34748",
    "sg:province":"FL",
    "sg:tags":[
        "asian",
        "chinese"
    ],
    "wof:name":"International Super Buffet",
    "wof:placetype":"venue"
},
  "geometry": {"coordinates":[-81.893709,28.840248],"type":"Point"}
}