{
  "type": "Feature",
  "properties": {
    "iso:country":"US",
    "sg:address":"1700 NE 116 Rd",
    "sg:city":"Miami",
    "sg:classifiers":[
        {
            "category":"Building & Trades",
            "subcategory":"Locksmith",
            "type":"Services"
        }
    ],
    "sg:phone":"+1 305 908 7608",
    "sg:postcode":"33181",
    "sg:province":"FL",
    "sg:tags":[
        "key"
    ],
    "wof:name":"Lock To Pop 24 Hr Locksmith",
    "wof:placetype":"venue"
},
  "geometry": {"coordinates":[-80.163882,25.884247],"type":"Point"}
}