{
  "type": "Feature",
  "properties": {
    "addr:full":"10700 Gulf Blvd Saint Petersburg FL 33706",
    "addr:housenumber":"10700",
    "addr:postcode":"33706",
    "addr:street":"Gulf Blvd",
    "iso:country":"US",
    "sg:address":"10700 Gulf Blvd",
    "sg:city":"Saint Petersburg",
    "sg:classifiers":[
        {
            "category":"Restaurant",
            "type":"Food & Drink"
        }
    ],
    "sg:phone":"+1 727 368 9548",
    "sg:postcode":"33706",
    "sg:province":"FL",
    "sg:tags":[
        "eating"
    ],
    "wof:name":"Karim's Bistro",
    "wof:placetype":"venue"
},
  "geometry": {"coordinates":[-82.769899,27.769925],"type":"Point"}
}