{
  "type": "Feature",
  "properties": {
    "iso:country":"US",
    "sg:address":"156 Harston Ct",
    "sg:city":"Lake Mary",
    "sg:classifiers":[
        {
            "category":"Freight",
            "type":"Transportation"
        }
    ],
    "sg:phone":"+1 407 688 0749",
    "sg:postcode":"32746",
    "sg:province":"FL",
    "sg:tags":[
        "domestic",
        "sea"
    ],
    "wof:name":"Dennis M Drazen",
    "wof:placetype":"venue"
},
  "geometry": {"coordinates":[-81.39935699999999,28.763814],"type":"Point"}
}