{
  "type": "Feature",
  "properties": {
    "addr:full":"1600 Murphy St Oviedo FL 32765",
    "addr:housenumber":"1600",
    "addr:postcode":"32765",
    "addr:street":"Murphy St",
    "iso:country":"US",
    "sg:address":"1600 Murphy St",
    "sg:city":"Oviedo",
    "sg:classifiers":[
        {
            "category":"Building & Trades",
            "subcategory":"Construction",
            "type":"Services"
        }
    ],
    "sg:phone":"+1 407 359 7514",
    "sg:postcode":"32765",
    "sg:province":"FL",
    "sg:tags":[
        "plastering",
        "contractor"
    ],
    "wof:name":"Pommell's Drywall Systems Inc.",
    "wof:placetype":"venue"
},
  "geometry": {"coordinates":[-81.151512,28.692511],"type":"Point"}
}