{
  "type": "Feature",
  "properties": {
    "iso:country":"US",
    "sg:address":"2622 Sheridan St",
    "sg:city":"Hollywood",
    "sg:classifiers":[
        {
            "category":"Building & Trades",
            "subcategory":"Construction",
            "type":"Services"
        }
    ],
    "sg:phone":"+1 954 921 4338",
    "sg:postcode":"33020",
    "sg:province":"FL",
    "sg:tags":[
        "contractor"
    ],
    "wof:name":"Sandman",
    "wof:placetype":"venue"
},
  "geometry": {"coordinates":[-80.161557,26.033433],"type":"Point"}
}