{
  "type": "Feature",
  "properties": {
    "iso:country":"US",
    "sg:address":"151 Mary Esther Blvd",
    "sg:city":"Mary Esther",
    "sg:classifiers":[
        {
            "category":"Professional",
            "type":"Services"
        }
    ],
    "sg:phone":"+1 850 243 6544",
    "sg:postcode":"32569",
    "sg:province":"FL",
    "sg:tags":[
        "establishment"
    ],
    "wof:name":"NWFLCADD Inc",
    "wof:placetype":"venue"
},
  "geometry": {"coordinates":[-86.65528500000001,30.410347],"type":"Point"}
}