{
  "type": "Feature",
  "properties": {
    "addr:full":"4560 L B Mcleod Rd Orlando FL 32811",
    "addr:housenumber":"4560;b",
    "addr:postcode":"32811",
    "addr:street":"L;Mcleod Rd",
    "iso:country":"US",
    "sg:address":"4560 L B Mcleod Rd",
    "sg:city":"Orlando",
    "sg:classifiers":[
        {
            "category":"Professional",
            "subcategory":"Printing & Photocopies",
            "type":"Services"
        }
    ],
    "sg:phone":"+1 407 843 5811",
    "sg:postcode":"32811",
    "sg:province":"FL",
    "sg:tags":[
        "lithographer"
    ],
    "wof:name":"Matlat Inc",
    "wof:placetype":"venue"
},
  "geometry": {"coordinates":[-81.437197,28.508657],"type":"Point"}
}