{
  "type": "Feature",
  "properties": {
    "iso:country":"US",
    "sg:address":"811 E 23rd St",
    "sg:city":"Panama City",
    "sg:classifiers":[
        {
            "category":"Shopping",
            "subcategory":"Books",
            "type":"Retail Goods"
        }
    ],
    "sg:phone":"+1 850 784 3040",
    "sg:postcode":"32405",
    "sg:province":"FL",
    "sg:website":"www.bamm.com",
    "wof:name":"Books-A-Million",
    "wof:placetype":"venue"
},
  "geometry": {"coordinates":[-85.647279,30.189623],"type":"Point"}
}