{
  "type": "Feature",
  "properties": {
    "addr:full":"7026 SW 46th St Miami FL 33155",
    "addr:housenumber":"7026",
    "addr:postcode":"33155",
    "addr:street":"Sw 46Th St",
    "iso:country":"US",
    "sg:address":"7026 SW 46th St",
    "sg:city":"Miami",
    "sg:classifiers":[
        {
            "category":"Arts & Performance",
            "subcategory":"Theater",
            "type":"Entertainment"
        }
    ],
    "sg:phone":"+1 305 665 9690",
    "sg:postcode":"33155",
    "sg:province":"FL",
    "sg:tags":[
        "dj",
        "live",
        "music"
    ],
    "wof:name":"Rames Productions",
    "wof:placetype":"venue"
},
  "geometry": {"coordinates":[-80.308502,25.7281],"type":"Point"}
}