{
  "type": "Feature",
  "properties": {
    "iso:country":"US",
    "sg:address":"2510 Santa Barbara Blvd",
    "sg:city":"Cape Coral",
    "sg:classifiers":[
        {
            "category":"Banks & Credit Unions",
            "subcategory":"Bank",
            "type":"Services"
        }
    ],
    "sg:phone":"+1 239 242 1276",
    "sg:postcode":"33914",
    "sg:province":"FL",
    "sg:website":"www.colonialbank.com",
    "wof:name":"Colonial Bank",
    "wof:placetype":"venue"
},
  "geometry": {"coordinates":[-81.974523,26.606246],"type":"Point"}
}