{
  "type": "Feature",
  "properties": {
    "addr:full":"20283 Old Cutler Rd Miami FL 33189",
    "addr:housenumber":"20283",
    "addr:postcode":"33189",
    "addr:street":"Old Cutler Rd",
    "iso:country":"US",
    "sg:address":"20283 Old Cutler Rd",
    "sg:city":"Miami",
    "sg:classifiers":[
        {
            "category":"Shopping",
            "subcategory":"Florist",
            "type":"Retail Goods"
        }
    ],
    "sg:phone":"+1 305 255 1922",
    "sg:postcode":"33189",
    "sg:province":"FL",
    "wof:name":"Cutler Florist",
    "wof:placetype":"venue"
},
  "geometry": {"coordinates":[-80.334766,25.579246],"type":"Point"}
}