{
  "type": "Feature",
  "properties": {
    "iso:country":"US",
    "sg:address":"201 NW 40th St",
    "sg:city":"Miami",
    "sg:classifiers":[
        {
            "category":"Wholesale",
            "subcategory":"Construction Materials",
            "type":"Manufacturing & Wholesale Goods"
        }
    ],
    "sg:phone":"+1 305 576 0944",
    "sg:postcode":"33127",
    "sg:province":"FL",
    "wof:name":"A C Tile Tile & Supply",
    "wof:placetype":"venue"
},
  "geometry": {"coordinates":[-80.20156799999999,25.813208],"type":"Point"}
}