{
  "type": "Feature",
  "properties": {
    "iso:country":"US",
    "sg:address":"105 S Rockingham Ave",
    "sg:city":"Tavares",
    "sg:classifiers":[
        {
            "category":"Government",
            "subcategory":"Jail",
            "type":"Public Place"
        }
    ],
    "sg:phone":"+1 352 742 6242",
    "sg:postcode":"32778",
    "sg:province":"FL",
    "sg:tags":[
        "correctional",
        "institution"
    ],
    "wof:name":"Correction Institute",
    "wof:placetype":"venue"
},
  "geometry": {"coordinates":[-81.726876,28.802163],"type":"Point"}
}