{
  "type": "Feature",
  "properties": {
    "iso:country":"US",
    "sg:address":"405 E New Haven Ave",
    "sg:city":"Melbourne",
    "sg:classifiers":[
        {
            "category":"Home & Garden",
            "subcategory":"Hardware",
            "type":"Retail Goods"
        }
    ],
    "sg:phone":"+1 321 723 6434",
    "sg:postcode":"32901",
    "sg:province":"FL",
    "sg:tags":[
        "florist",
        "repair"
    ],
    "wof:name":"Stebbins Hardware Inc",
    "wof:placetype":"venue"
},
  "geometry": {"coordinates":[-80.61412,28.078519],"type":"Point"}
}