{
  "type": "Feature",
  "properties": {
    "iso:country":"US",
    "sg:address":"1650 SE Green Acres Cir",
    "sg:city":"Port Saint Lucie",
    "sg:classifiers":[
        {
            "category":"Building & Trades",
            "subcategory":"Landscaping Services",
            "type":"Services"
        }
    ],
    "sg:phone":"+1 772 398 2274",
    "sg:postcode":"34952",
    "sg:province":"FL",
    "wof:name":"Brad Wright Lawn Maintenance",
    "wof:placetype":"venue"
},
  "geometry": {"coordinates":[-80.30004,27.28981],"type":"Point"}
}