{
  "type": "Feature",
  "properties": {
    "addr:full":"3219 NE 16th Ct Ocala FL 34479",
    "addr:housenumber":"3219",
    "addr:postcode":"34479",
    "addr:street":"Ne 16Th Ct",
    "iso:country":"US",
    "sg:address":"3219 NE 16th Ct",
    "sg:city":"Ocala",
    "sg:classifiers":[
        {
            "category":"Professional",
            "type":"Services"
        }
    ],
    "sg:phone":"+1 352 351 1100",
    "sg:postcode":"34479",
    "sg:province":"FL",
    "sg:tags":[
        "establishment"
    ],
    "wof:name":"A M Stives Lawnmaitence",
    "wof:placetype":"venue"
},
  "geometry": {"coordinates":[-82.115774,29.219479],"type":"Point"}
}