{
  "type": "Feature",
  "properties": {
    "addr:full":"7485 Pine Park Dr S Lake Worth FL 33467",
    "addr:housenumber":"7485",
    "addr:postcode":"33467",
    "addr:street":"Pine Park Dr S",
    "iso:country":"US",
    "sg:address":"7485 Pine Park Dr S",
    "sg:city":"Lake Worth",
    "sg:classifiers":[
        {
            "category":"Building & Trades",
            "subcategory":"Construction",
            "type":"Services"
        }
    ],
    "sg:phone":"+1 561 434 4890",
    "sg:postcode":"33467",
    "sg:province":"FL",
    "sg:tags":[
        "concrete",
        "contractor"
    ],
    "wof:name":"John Wichterman",
    "wof:placetype":"venue"
},
  "geometry": {"coordinates":[-80.16244,26.612286],"type":"Point"}
}