{
  "type": "Feature",
  "properties": {
    "iso:country":"US",
    "sg:address":"18270 River Oaks Dr",
    "sg:city":"Jupiter",
    "sg:classifiers":[
        {
            "category":"Building & Trades",
            "subcategory":"Construction",
            "type":"Services"
        }
    ],
    "sg:phone":"+1 561 741 3525",
    "sg:postcode":"33458",
    "sg:province":"FL",
    "sg:tags":[
        "specializing",
        "partition",
        "installation",
        "demountable",
        "air"
    ],
    "wof:name":"Precision Wall",
    "wof:placetype":"venue"
},
  "geometry": {"coordinates":[-80.12651700000001,26.944979],"type":"Point"}
}