{
  "type": "Feature",
  "properties": {
    "iso:country":"US",
    "sg:address":"211 Louella Ln",
    "sg:city":"Nokomis",
    "sg:classifiers":[
        {
            "category":"Health Services",
            "subcategory":"Doctor",
            "type":"Services"
        }
    ],
    "sg:phone":"+1 941 484 2289",
    "sg:postcode":"34275",
    "sg:province":"FL",
    "sg:tags":[
        "osteopathic"
    ],
    "wof:name":"Donald F Blem Do",
    "wof:placetype":"venue"
},
  "geometry": {"coordinates":[-82.465182,27.123054],"type":"Point"}
}