{
  "type": "Feature",
  "properties": {
    "iso:country":"US",
    "sg:address":"749 Helicon Ter",
    "sg:city":"Sebastian",
    "sg:classifiers":[
        {
            "category":"Real Estate",
            "subcategory":"Real Estate Agent",
            "type":"Services"
        }
    ],
    "sg:phone":"+1 772 388 2300",
    "sg:postcode":"32958",
    "sg:province":"FL",
    "wof:name":"Busy B Concierge LLC",
    "wof:placetype":"venue"
},
  "geometry": {"coordinates":[-80.49241499999999,27.771175],"type":"Point"}
}