{
  "type": "Feature",
  "properties": {
    "iso:country":"US",
    "sg:address":"820 S F St",
    "sg:city":"Lake Worth",
    "sg:classifiers":[
        {
            "category":"Retail",
            "subcategory":"Repair Shop",
            "type":"Services"
        }
    ],
    "sg:phone":"+1 561 540 4084",
    "sg:postcode":"33460",
    "sg:province":"FL",
    "wof:name":"Ana & Rosa Quiroz",
    "wof:placetype":"venue"
},
  "geometry": {"coordinates":[-80.06061200000001,26.60532],"type":"Point"}
}