{
  "type": "Feature",
  "properties": {
    "addr:full":"1123 SE 36th Ter Cape Coral FL 33904",
    "addr:housenumber":"1123",
    "addr:postcode":"33904",
    "addr:street":"Se 36Th Ter",
    "iso:country":"US",
    "sg:address":"1123 SE 36th Ter",
    "sg:city":"Cape Coral",
    "sg:classifiers":[
        {
            "category":"Insurance",
            "subcategory":"Insurance Agent",
            "type":"Services"
        }
    ],
    "sg:phone":"+1 239 549 6865",
    "sg:postcode":"33904",
    "sg:province":"FL",
    "wof:name":"Rhoad Insurance Inc",
    "wof:placetype":"venue"
},
  "geometry": {"coordinates":[-81.949343,26.584862],"type":"Point"}
}