{
  "type": "Feature",
  "properties": {
    "iso:country":"US",
    "sg:address":"15560 McGregor Blvd Ste 3",
    "sg:city":"Fort Myers",
    "sg:classifiers":[
        {
            "category":"Retail",
            "subcategory":"Veterinary Services",
            "type":"Services"
        }
    ],
    "sg:phone":"+1 239 433 2424",
    "sg:postcode":"33908",
    "sg:province":"FL",
    "sg:tags":[
        "veterinarian"
    ],
    "wof:name":"Gulf Coast Veterinary Clinic",
    "wof:placetype":"venue"
},
  "geometry": {"coordinates":[-81.947098,26.5156],"type":"Point"}
}