{
  "type": "Feature",
  "properties": {
    "iso:country":"US",
    "sg:address":"4678 US Hwy 27",
    "sg:city":"Sebring",
    "sg:classifiers":[
        {
            "category":"Home & Garden",
            "subcategory":"Building Materials",
            "type":"Retail Goods"
        }
    ],
    "sg:phone":"+1 863 385 2202",
    "sg:postcode":"33870",
    "sg:province":"FL",
    "sg:tags":[
        "glass",
        "window",
        "plate"
    ],
    "wof:name":"Broken Glass",
    "wof:placetype":"venue"
},
  "geometry": {"coordinates":[-81.423365,27.455295],"type":"Point"}
}