{
  "type": "Feature",
  "properties": {
    "addr:full":"5838 Trouble Creek Rd New Port Richey FL 34652",
    "addr:housenumber":"5838",
    "addr:postcode":"34652",
    "addr:street":"Trouble Creek Rd",
    "iso:country":"US",
    "sg:address":"5838 Trouble Creek Rd",
    "sg:city":"New Port Richey",
    "sg:classifiers":[
        {
            "category":"Home & Garden",
            "subcategory":"Building Materials",
            "type":"Retail Goods"
        },
        {
            "category":"Building & Trades",
            "subcategory":"Construction",
            "type":"Services"
        }
    ],
    "sg:phone":"+1 727 934 5694",
    "sg:postcode":"34652",
    "sg:province":"FL",
    "sg:tags":[
        "windows",
        "shutter",
        "mfg",
        "remodeling",
        "also"
    ],
    "sg:website":"www.pwdi.com",
    "wof:name":"Pasco Window & Door Inc",
    "wof:placetype":"venue"
},
  "geometry": {"coordinates":[-82.71555600000001,28.224302],"type":"Point"}
}