{
  "type": "Feature",
  "properties": {
    "iso:country":"US",
    "sg:address":"2762 Blanding Blvd",
    "sg:city":"Jacksonville",
    "sg:classifiers":[
        {
            "category":"Banks & Credit Unions",
            "subcategory":"Bank",
            "type":"Services"
        }
    ],
    "sg:phone":"+1 904 777 6000",
    "sg:postcode":"32210",
    "sg:province":"FL",
    "wof:name":"Vystar Credit Union",
    "wof:placetype":"venue"
},
  "geometry": {"coordinates":[-81.73243100000001,30.274192],"type":"Point"}
}