{
  "type": "Feature",
  "properties": {
    "iso:country":"US",
    "sg:address":"2250 N Commerce Pkwy",
    "sg:city":"Weston",
    "sg:classifiers":[
        {
            "category":"Real Estate",
            "subcategory":"Developer",
            "type":"Services"
        }
    ],
    "sg:phone":"+1 954 660 0994",
    "sg:postcode":"33326",
    "sg:province":"FL",
    "wof:name":"Codina Development",
    "wof:placetype":"venue"
},
  "geometry": {"coordinates":[-80.365404,26.095536],"type":"Point"}
}