{
  "type": "Feature",
  "properties": {
    "iso:country":"US",
    "sg:address":"2030 Old Dixie Hwy SE",
    "sg:city":"Vero Beach",
    "sg:classifiers":[
        {
            "category":"Professional",
            "subcategory":"Accounting & Tax Preparation",
            "type":"Services"
        }
    ],
    "sg:phone":"+1 772 978 9555",
    "sg:postcode":"32962",
    "sg:province":"FL",
    "sg:tags":[
        "billing"
    ],
    "wof:name":"Physician Billing & Practice",
    "wof:placetype":"venue"
},
  "geometry": {"coordinates":[-80.371999,27.565242],"type":"Point"}
}