{
  "type": "Feature",
  "properties": {
    "addr:full":"44 Bahia Trace Cir Ocala FL 34472",
    "addr:housenumber":"44",
    "addr:postcode":"34472",
    "addr:street":"Bahia Trace Cir",
    "iso:country":"US",
    "sg:address":"44 Bahia Trace Cir",
    "sg:city":"Ocala",
    "sg:classifiers":[
        {
            "category":"Health Services",
            "subcategory":"Doctor",
            "type":"Services"
        }
    ],
    "sg:phone":"+1 352 680 0802",
    "sg:postcode":"34472",
    "sg:province":"FL",
    "sg:tags":[
        "physician",
        "surgeon"
    ],
    "wof:name":"Hossain Liaquat",
    "wof:placetype":"venue"
},
  "geometry": {"coordinates":[-82.01152,29.13685],"type":"Point"}
}