{
  "type": "Feature",
  "properties": {
    "iso:country":"US",
    "sg:address":"6043 Miramar Pkwy",
    "sg:city":"Miramar",
    "sg:classifiers":[
        {
            "category":"Shopping",
            "subcategory":"Florist",
            "type":"Retail Goods"
        }
    ],
    "sg:phone":"+1 305 558 9763",
    "sg:postcode":"33023",
    "sg:province":"FL",
    "wof:name":"A Florist In The USA",
    "wof:placetype":"venue"
},
  "geometry": {"coordinates":[-80.207739,25.984712],"type":"Point"}
}