{
  "type": "Feature",
  "properties": {
    "iso:country":"US",
    "sg:address":"12302 SW 128 St",
    "sg:city":"Miami",
    "sg:classifiers":[
        {
            "category":"Building & Trades",
            "subcategory":"Cleaning & Sanitation",
            "type":"Services"
        }
    ],
    "sg:phone":"+1 305 971 2788",
    "sg:postcode":"33186",
    "sg:province":"FL",
    "sg:tags":[
        "home"
    ],
    "sg:website":"servicemasterofcoralgables.info/",
    "wof:name":"Service Master of Coral Gables",
    "wof:placetype":"venue"
},
  "geometry": {"coordinates":[-80.393109,25.649131],"type":"Point"}
}