{
  "type": "Feature",
  "properties": {
    "iso:country":"US",
    "sg:address":"1813 NW 126th Way",
    "sg:city":"Pompano Beach",
    "sg:classifiers":[
        {
            "category":"Professional",
            "type":"Services"
        }
    ],
    "sg:phone":"+1 954 345 0351",
    "sg:postcode":"33071",
    "sg:province":"FL",
    "wof:name":"Dogleg Left Inc",
    "wof:placetype":"venue"
},
  "geometry": {"coordinates":[-80.293595,26.253674],"type":"Point"}
}