{
  "type": "Feature",
  "properties": {
    "iso:country":"US",
    "sg:address":"165 US Hwy 1",
    "sg:city":"North Palm Beach",
    "sg:classifiers":[
        {
            "category":"Food & Beverages",
            "subcategory":"Groceries & Convenience Stores",
            "type":"Retail Goods"
        }
    ],
    "sg:phone":"+1 561 841 4700",
    "sg:postcode":"33408",
    "sg:province":"FL",
    "wof:name":"Milan Pizza & Deli",
    "wof:placetype":"venue"
},
  "geometry": {"coordinates":[-80.054349,26.793024],"type":"Point"}
}