{
  "type": "Feature",
  "properties": {
    "addr:full":"2060 Aberdeen Ln Naples FL 34109",
    "addr:housenumber":"2060",
    "addr:postcode":"34109",
    "addr:street":"Aberdeen Ln",
    "iso:country":"US",
    "sg:address":"2060 Aberdeen Ln",
    "sg:city":"Naples",
    "sg:classifiers":[
        {
            "category":"Home & Garden",
            "subcategory":"Home Furnishings",
            "type":"Retail Goods"
        }
    ],
    "sg:phone":"+1 239 591 1429",
    "sg:postcode":"34109",
    "sg:province":"FL",
    "wof:name":"Blind Concepts Inc",
    "wof:placetype":"venue"
},
  "geometry": {"coordinates":[-81.77527499999999,26.269713],"type":"Point"}
}