{
  "type": "Feature",
  "properties": {
    "iso:country":"US",
    "sg:address":"565 Harbor Dr",
    "sg:city":"Key Biscayne",
    "sg:classifiers":[
        {
            "category":"Professional",
            "type":"Services"
        }
    ],
    "sg:phone":"+1 305 365 9500",
    "sg:postcode":"33149",
    "sg:province":"FL",
    "wof:name":"Key For Colombia Corp",
    "wof:placetype":"venue"
},
  "geometry": {"coordinates":[-80.17241,25.69158],"type":"Point"}
}