{
  "type": "Feature",
  "properties": {
    "iso:country":"US",
    "sg:address":"230 SW 128th Ave",
    "sg:city":"Miami",
    "sg:classifiers":[
        {
            "category":"Building & Trades",
            "subcategory":"Equipment Rental",
            "type":"Services"
        }
    ],
    "sg:phone":"+1 305 207 8378",
    "sg:postcode":"33184",
    "sg:province":"FL",
    "sg:tags":[
        "yard",
        "leasing",
        "store"
    ],
    "wof:name":"Charles Perez Food Equiptment",
    "wof:placetype":"venue"
},
  "geometry": {"coordinates":[-80.402869,25.76519],"type":"Point"}
}