{
  "type": "Feature",
  "properties": {
    "iso:country":"US",
    "sg:address":"13656 NW 160th Ave",
    "sg:city":"Morriston",
    "sg:classifiers":[
        {
            "category":"Farming",
            "subcategory":"Farm",
            "type":"Manufacturing & Wholesale Goods"
        }
    ],
    "sg:phone":"+1 352 528 4207",
    "sg:postcode":"32668",
    "sg:province":"FL",
    "wof:name":"Victor Centeno",
    "wof:placetype":"venue"
},
  "geometry": {"coordinates":[-82.38878099999999,29.339709],"type":"Point"}
}