{
  "type": "Feature",
  "properties": {
    "iso:country":"US",
    "sg:address":"3815 N Cocoa Blvd",
    "sg:city":"Cocoa",
    "sg:classifiers":[
        {
            "category":"Autos & Motor Vehicles",
            "subcategory":"Boat Sales",
            "type":"Retail Goods"
        },
        {
            "category":"Wholesale",
            "subcategory":"Machinery & Supplies",
            "type":"Manufacturing & Wholesale Goods"
        }
    ],
    "sg:phone":"+1 321 636 5212",
    "sg:postcode":"32926",
    "sg:province":"FL",
    "sg:tags":[
        "equipment",
        "dealer",
        "sales"
    ],
    "wof:name":"Lifeline Inflatable Services",
    "wof:placetype":"venue"
},
  "geometry": {"coordinates":[-80.755925,28.418112],"type":"Point"}
}