{
  "type": "Feature",
  "properties": {
    "iso:country":"US",
    "sg:address":"6279 W Oakland Park Blvd",
    "sg:city":"Fort Lauderdale",
    "sg:classifiers":[
        {
            "category":"Government",
            "subcategory":"Police Station",
            "type":"Public Place"
        }
    ],
    "sg:phone":"+1 954 497 4700",
    "sg:postcode":"33313",
    "sg:province":"FL",
    "sg:tags":[
        "protection"
    ],
    "wof:name":"Lauderhill Police Department",
    "wof:placetype":"venue"
},
  "geometry": {"coordinates":[-80.233676,26.164911],"type":"Point"}
}