{
  "type": "Feature",
  "properties": {
    "iso:country":"US",
    "sg:address":"3103 Glen Elyn Blvd",
    "sg:city":"Sarasota",
    "sg:classifiers":[
        {
            "category":"Banks & Credit Unions",
            "subcategory":"Investment Brokerage",
            "type":"Services"
        }
    ],
    "sg:phone":"+1 941 954 9900",
    "sg:postcode":"34237",
    "sg:province":"FL",
    "sg:tags":[
        "advisory",
        "financial"
    ],
    "wof:name":"Presidential Financial",
    "wof:placetype":"venue"
},
  "geometry": {"coordinates":[-82.506821,27.345323],"type":"Point"}
}