{
  "type": "Feature",
  "properties": {
    "addr:full":"9950 Princess Palm Ave Tampa FL 33619",
    "addr:housenumber":"9950",
    "addr:postcode":"33619",
    "addr:street":"Princess Palm Ave",
    "iso:country":"US",
    "sg:address":"9950 Princess Palm Ave",
    "sg:city":"Tampa",
    "sg:classifiers":[
        {
            "category":"Professional",
            "type":"Services"
        }
    ],
    "sg:phone":"+1 813 635 0300",
    "sg:postcode":"33619",
    "sg:province":"FL",
    "sg:tags":[
        "establishment"
    ],
    "wof:name":"D & L Enterprises",
    "wof:placetype":"venue"
},
  "geometry": {"coordinates":[-82.339877,27.98019],"type":"Point"}
}