{
  "type": "Feature",
  "properties": {
    "iso:country":"US",
    "sg:address":"686 N Indiana Ave",
    "sg:city":"Englewood",
    "sg:classifiers":[
        {
            "category":"Professional",
            "subcategory":"Lawyer & Legal Services",
            "type":"Services"
        }
    ],
    "sg:phone":"+1 941 474 3241",
    "sg:postcode":"34223",
    "sg:province":"FL",
    "sg:tags":[
        "attorney",
        "law"
    ],
    "wof:name":"Wellbaum & Wolff PA",
    "wof:placetype":"venue"
},
  "geometry": {"coordinates":[-82.353792,26.973225],"type":"Point"}
}