{
  "type": "Feature",
  "properties": {
    "iso:country":"US",
    "sg:address":"17370 Alt. A1a",
    "sg:city":"Jupiter",
    "sg:classifiers":[
        {
            "category":"Restaurant",
            "type":"Food & Drink"
        }
    ],
    "sg:menulink":"http://www.allmenus.com/fl/jupiter/40135-molte-bene/menu/",
    "sg:phone":"+1 561 748 7717",
    "sg:postcode":"33477",
    "sg:province":"FL",
    "sg:tags":[
        "italian"
    ],
    "wof:name":"Molte Bene",
    "wof:placetype":"venue"
},
  "geometry": {"coordinates":[-80.093469,26.931097],"type":"Point"}
}