{
  "type": "Feature",
  "properties": {
    "iso:country":"US",
    "sg:address":"4019 NW 28th St",
    "sg:city":"Miami",
    "sg:classifiers":[
        {
            "category":"Retail",
            "subcategory":"Auto Rental",
            "type":"Services"
        }
    ],
    "sg:phone":"+1 305 871 5008",
    "sg:postcode":"33142",
    "sg:province":"FL",
    "sg:tags":[
        "car"
    ],
    "wof:name":"Total Auto Rental",
    "wof:placetype":"venue"
},
  "geometry": {"coordinates":[-80.262001,25.8009],"type":"Point"}
}