{
  "type": "Feature",
  "properties": {
    "addr:full":"7261 State Hwy 80 Alva FL 33920",
    "addr:housenumber":"7261",
    "addr:postcode":"33920",
    "addr:street":"State Hwy 80",
    "iso:country":"US",
    "sg:address":"7261 State Hwy 80",
    "sg:city":"Alva",
    "sg:classifiers":[
        {
            "category":"Wholesale",
            "subcategory":"Machinery & Supplies",
            "type":"Manufacturing & Wholesale Goods"
        }
    ],
    "sg:phone":"+1 239 633 6294",
    "sg:postcode":"33920",
    "sg:province":"FL",
    "wof:name":"Tractor Implements Plus",
    "wof:placetype":"venue"
},
  "geometry": {"coordinates":[-81.555098,26.709439],"type":"Point"}
}