{
  "type": "Feature",
  "properties": {
    "addr:full":"2610 Orange Ct Longwood FL 32779",
    "addr:housenumber":"2610",
    "addr:postcode":"32779",
    "addr:street":"Orange Ct",
    "iso:country":"US",
    "sg:address":"2610 Orange Ct",
    "sg:city":"Longwood",
    "sg:classifiers":[
        {
            "category":"Utilities",
            "subcategory":"Cable",
            "type":"Services"
        }
    ],
    "sg:phone":"+1 407 862 8203",
    "sg:postcode":"32779",
    "sg:province":"FL",
    "sg:tags":[
        "television"
    ],
    "wof:name":"A & C Cable Inc",
    "wof:placetype":"venue"
},
  "geometry": {"coordinates":[-81.433222,28.691809],"type":"Point"}
}