{
  "type": "Feature",
  "properties": {
    "iso:country":"US",
    "sg:address":"11551 E Terry St",
    "sg:city":"Bonita Springs",
    "sg:classifiers":[
        {
            "category":"Organizations",
            "subcategory":"Religious Organization",
            "type":"Services"
        }
    ],
    "sg:phone":"+1 239 992 3306",
    "sg:postcode":"34135",
    "sg:province":"FL",
    "wof:name":"Christian Science Church",
    "wof:placetype":"venue"
},
  "geometry": {"coordinates":[-81.761792,26.345879],"type":"Point"}
}