{
  "type": "Feature",
  "properties": {
    "iso:country":"US",
    "sg:address":"2161 E Commercial Blvd",
    "sg:city":"Fort Lauderdale",
    "sg:classifiers":[
        {
            "category":"Health Services",
            "subcategory":"Optometrist",
            "type":"Services"
        }
    ],
    "sg:phone":"+1 954 771 9120",
    "sg:postcode":"33308",
    "sg:province":"FL",
    "wof:name":"Shepard & Assoc",
    "wof:placetype":"venue"
},
  "geometry": {"coordinates":[-80.113793,26.18963],"type":"Point"}
}