{
  "type": "Feature",
  "properties": {
    "addr:full":"13901 SW 88th St Miami FL 33186",
    "addr:housenumber":"13901",
    "addr:postcode":"33186",
    "addr:street":"Sw 88Th St",
    "iso:country":"US",
    "sg:address":"13901 SW 88th St",
    "sg:city":"Miami",
    "sg:classifiers":[
        {
            "category":"Professional",
            "type":"Services"
        },
        {
            "category":"Professional",
            "subcategory":"Business Services",
            "type":"Services"
        },
        {
            "category":"Professional",
            "subcategory":"Printing & Photocopies",
            "type":"Services"
        },
        {
            "category":"Shopping",
            "subcategory":"Stationery & Office Supplies",
            "type":"Retail Goods"
        },
        {
            "category":"Manufacturing",
            "subcategory":"Printing",
            "type":"Manufacturing & Wholesale Goods"
        },
        {
            "category":"Manufacturing",
            "subcategory":"Signs",
            "type":"Manufacturing & Wholesale Goods"
        }
    ],
    "sg:phone":"+1 305 383 3550",
    "sg:postcode":"33186",
    "sg:province":"FL",
    "sg:tags":[
        "machine",
        "document",
        "duplicating",
        "shipping",
        "materials-shipping",
        "packaging",
        "packing",
        "imaging",
        "copying",
        "digital",
        "copy"
    ],
    "sg:website":"http://www.fedex.com/Dropoff/start?FY11-FXO-YELLOWPAGES",
    "wof:name":"FedEx Office Print & Ship Center",
    "wof:placetype":"venue"
},
  "geometry": {"coordinates":[-80.419392,25.68533],"type":"Point"}
}