{
  "type": "Feature",
  "properties": {
    "addr:full":"1517 Sand Castle Rd Sanibel FL 33957",
    "addr:housenumber":"1517",
    "addr:postcode":"33957",
    "addr:street":"Sand Castle Rd",
    "iso:country":"US",
    "sg:address":"1517 Sand Castle Rd",
    "sg:city":"Sanibel",
    "sg:classifiers":[
        {
            "category":"Banks & Credit Unions",
            "subcategory":"Financial Services",
            "type":"Services"
        }
    ],
    "sg:phone":"+1 239 472 8022",
    "sg:postcode":"33957",
    "sg:province":"FL",
    "sg:tags":[
        "trust",
        "nonprofit",
        "management"
    ],
    "wof:name":"Hanser Family Foundation",
    "wof:placetype":"venue"
},
  "geometry": {"coordinates":[-82.051388,26.453318],"type":"Point"}
}