{
  "type": "Feature",
  "properties": {
    "addr:full":"1021 SW 26th St Ocala FL 34471",
    "addr:housenumber":"1021",
    "addr:postcode":"34471",
    "addr:street":"Sw 26Th St",
    "iso:country":"US",
    "sg:address":"1021 SW 26th St",
    "sg:city":"Ocala",
    "sg:classifiers":[
        {
            "category":"Restaurant",
            "type":"Food & Drink"
        },
        {
            "category":"Ice Cream",
            "type":"Food & Drink"
        }
    ],
    "sg:phone":"+1 352 732 6767",
    "sg:postcode":"34471",
    "sg:province":"FL",
    "sg:tags":[
        "frozen",
        "dessert"
    ],
    "wof:name":"Dairy Queen",
    "wof:placetype":"venue"
},
  "geometry": {"coordinates":[-82.147746,29.162428],"type":"Point"}
}