{
  "type": "Feature",
  "properties": {
    "iso:country":"US",
    "sg:address":"3951 N 51st Ave",
    "sg:city":"Hollywood",
    "sg:classifiers":[
        {
            "category":"Shopping",
            "subcategory":"Jewelry",
            "type":"Retail Goods"
        }
    ],
    "sg:phone":"+1 954 921 1990",
    "sg:postcode":"33021",
    "sg:province":"FL",
    "wof:name":"Jewelry Network com Inc",
    "wof:placetype":"venue"
},
  "geometry": {"coordinates":[-80.19506199999999,26.044914],"type":"Point"}
}