{
  "type": "Feature",
  "properties": {
    "iso:country":"US",
    "sg:address":"5700 Memorial Hwy",
    "sg:city":"Tampa",
    "sg:classifiers":[
        {
            "category":"Professional",
            "subcategory":"Business Services",
            "type":"Services"
        }
    ],
    "sg:phone":"+1 813 890 8654",
    "sg:postcode":"33615",
    "sg:province":"FL",
    "sg:tags":[
        "inspection"
    ],
    "wof:name":"Inspectpros Central Florida",
    "wof:placetype":"venue"
},
  "geometry": {"coordinates":[-82.56633600000001,27.982211],"type":"Point"}
}