{
  "type": "Feature",
  "properties": {
    "addr:full":"7025 Fairway Dr Palm Beach Gdns FL 33418",
    "addr:housenumber":"7025",
    "addr:postcode":"33418",
    "addr:street":"Fairway Dr Palm",
    "iso:country":"US",
    "sg:address":"7025 Fairway Dr",
    "sg:city":"Palm Beach Gdns",
    "sg:classifiers":[
        {
            "category":"Building & Trades",
            "subcategory":"Construction",
            "type":"Services"
        }
    ],
    "sg:phone":"+1 561 656 0710",
    "sg:postcode":"33418",
    "sg:province":"FL",
    "sg:tags":[
        "roofing",
        "contractor"
    ],
    "wof:name":"Advanced Roofing Inc",
    "wof:placetype":"venue"
},
  "geometry": {"coordinates":[-80.131828,26.838614],"type":"Point"}
}