{
  "type": "Feature",
  "properties": {
    "iso:country":"US",
    "sg:address":"6104 Black Dairy Rd",
    "sg:city":"Seffner",
    "sg:classifiers":[
        {
            "category":"Wholesale",
            "subcategory":"Durable Goods & Equipment",
            "type":"Manufacturing & Wholesale Goods"
        }
    ],
    "sg:phone":"+1 813 626 5809",
    "sg:postcode":"33584",
    "sg:province":"FL",
    "sg:tags":[
        "sign"
    ],
    "wof:name":"Tampa Wholesale Neon Supplies",
    "wof:placetype":"venue"
},
  "geometry": {"coordinates":[-82.311522,28.006739],"type":"Point"}
}