{
  "type": "Feature",
  "properties": {
    "iso:country":"US",
    "sg:address":"2930 9th St N",
    "sg:city":"St Petersburg",
    "sg:classifiers":[
        {
            "category":"Personal",
            "subcategory":"Beauty Salon",
            "type":"Services"
        }
    ],
    "sg:phone":"+1 727 820 9197",
    "sg:postcode":"33704",
    "sg:province":"FL",
    "sg:tags":[
        "shop",
        "manicuring"
    ],
    "wof:name":"B J Nails",
    "wof:placetype":"venue"
},
  "geometry": {"coordinates":[-82.646807,27.799095],"type":"Point"}
}