{
  "type": "Feature",
  "properties": {
    "iso:country":"US",
    "sg:address":"1290 E Normandy Blvd Ste 2",
    "sg:city":"Deltona",
    "sg:classifiers":[
        {
            "category":"Health Services",
            "subcategory":"Dentist",
            "type":"Services"
        }
    ],
    "sg:phone":"+1 386 574 5161",
    "sg:postcode":"32725",
    "sg:province":"FL",
    "wof:name":"Dr Turner Dentistry",
    "wof:placetype":"venue"
},
  "geometry": {"coordinates":[-81.23857599999999,28.883203],"type":"Point"}
}