{
  "type": "Feature",
  "properties": {
    "iso:country":"US",
    "sg:address":"6208 Rodgers Ave",
    "sg:city":"Sarasota",
    "sg:classifiers":[
        {
            "category":"Building & Trades",
            "subcategory":"Construction",
            "type":"Services"
        }
    ],
    "sg:phone":"+1 941 924 6560",
    "sg:postcode":"34231",
    "sg:province":"FL",
    "sg:tags":[
        "tile",
        "dealer"
    ],
    "wof:name":"Sarasota Ceramic Tile & Marble",
    "wof:placetype":"venue"
},
  "geometry": {"coordinates":[-82.51542999999999,27.263394],"type":"Point"}
}