{
  "type": "Feature",
  "properties": {
    "iso:country":"US",
    "sg:address":"1010 W Oak Ridge Rd",
    "sg:city":"Orlando",
    "sg:classifiers":[
        {
            "category":"Social Services",
            "subcategory":"Child Care",
            "type":"Services"
        }
    ],
    "sg:phone":"+1 407 857 6864",
    "sg:postcode":"32809",
    "sg:province":"FL",
    "wof:name":"Galaxy Of Learning",
    "wof:placetype":"venue"
},
  "geometry": {"coordinates":[-81.392993,28.472554],"type":"Point"}
}