{
  "type": "Feature",
  "properties": {
    "iso:country":"US",
    "sg:address":"926 Bannerman Rd",
    "sg:city":"Tallahassee",
    "sg:classifiers":[
        {
            "category":"Shopping",
            "type":"Retail Goods"
        }
    ],
    "sg:phone":"+1 850 942 5912",
    "sg:postcode":"32312",
    "sg:province":"FL",
    "sg:tags":[
        "equipment",
        "training",
        "patient",
        "durable",
        "medical"
    ],
    "wof:name":"Extended Medical Service Inc",
    "wof:placetype":"venue"
},
  "geometry": {"coordinates":[-84.262361,30.587415],"type":"Point"}
}