{
  "type": "Feature",
  "properties": {
    "iso:country":"US",
    "sg:address":"1345 W Granada Blvd",
    "sg:city":"Ormond Beach",
    "sg:classifiers":[
        {
            "category":"Personal",
            "subcategory":"Beauty Salon",
            "type":"Services"
        }
    ],
    "sg:phone":"+1 386 672 4445",
    "sg:postcode":"32174",
    "sg:province":"FL",
    "wof:name":"Sport Clips",
    "wof:placetype":"venue"
},
  "geometry": {"coordinates":[-81.108279,29.261952],"type":"Point"}
}