{
  "type": "Feature",
  "properties": {
    "iso:country":"US",
    "sg:address":"3312 NW 2nd Ave",
    "sg:city":"Miami",
    "sg:classifiers":[
        {
            "category":"Professional",
            "subcategory":"Computer Services",
            "type":"Services"
        }
    ],
    "sg:phone":"+1 305 329 3120",
    "sg:postcode":"33127",
    "sg:province":"FL",
    "sg:tags":[
        "repair",
        "equipment-service"
    ],
    "wof:name":"Geek Choice",
    "wof:placetype":"venue"
},
  "geometry": {"coordinates":[-80.199313,25.80743],"type":"Point"}
}