{
  "type": "Feature",
  "properties": {
    "iso:country":"US",
    "sg:address":"10184 Sleepy Brook Way",
    "sg:city":"Boca Raton",
    "sg:classifiers":[
        {
            "category":"Building & Trades",
            "subcategory":"Construction",
            "type":"Services"
        }
    ],
    "sg:phone":"+1 561 487 7910",
    "sg:postcode":"33428",
    "sg:province":"FL",
    "sg:tags":[
        "contractor"
    ],
    "wof:name":"L Dale McIntyre Tile & Marble",
    "wof:placetype":"venue"
},
  "geometry": {"coordinates":[-80.206278,26.337582],"type":"Point"}
}