{
  "type": "Feature",
  "properties": {
    "iso:country":"US",
    "sg:address":"1220 W Industrial Ave",
    "sg:city":"Boynton Beach",
    "sg:classifiers":[
        {
            "category":"Travel",
            "subcategory":"Travel Agent",
            "type":"Entertainment"
        }
    ],
    "sg:phone":"+1 561 738 6008",
    "sg:postcode":"33426",
    "sg:province":"FL",
    "sg:tags":[
        "operator",
        "tour"
    ],
    "wof:name":"Coach USA",
    "wof:placetype":"venue"
},
  "geometry": {"coordinates":[-80.076255,26.53065],"type":"Point"}
}