{
  "type": "Feature",
  "properties": {
    "iso:country":"US",
    "sg:address":"11249 Pines Blvd",
    "sg:city":"Hollywood",
    "sg:classifiers":[
        {
            "category":"Home & Garden",
            "subcategory":"Furniture",
            "type":"Retail Goods"
        }
    ],
    "sg:phone":"+1 954 431 6220",
    "sg:postcode":"33026",
    "sg:province":"FL",
    "wof:name":"City Furniture Inc",
    "wof:placetype":"venue"
},
  "geometry": {"coordinates":[-80.29725500000001,26.00791],"type":"Point"}
}