{
  "type": "Feature",
  "properties": {
    "iso:country":"US",
    "sg:address":"405 Cypress Gardens Blvd",
    "sg:city":"Winter Haven",
    "sg:classifiers":[
        {
            "category":"Restaurant",
            "type":"Food & Drink"
        }
    ],
    "sg:menulink":"http://www.allmenus.com/fl/winter-haven-auburndale/13904-olive-garden-italian-restaurant/menu/",
    "sg:phone":"+1 863 294 6641",
    "sg:postcode":"33880",
    "sg:province":"FL",
    "sg:tags":[
        "italian"
    ],
    "wof:name":"Olive Garden Italian Restaurant",
    "wof:placetype":"venue"
},
  "geometry": {"coordinates":[-81.723786,28.003927],"type":"Point"}
}