{
  "type": "Feature",
  "properties": {
    "addr:full":"2308 Dog Leg Dr Sebring FL 33872",
    "addr:housenumber":"2308",
    "addr:postcode":"33872",
    "addr:street":"Dog Leg Dr",
    "iso:country":"US",
    "sg:address":"2308 Dog Leg Dr",
    "sg:city":"Sebring",
    "sg:classifiers":[
        {
            "category":"Organizations",
            "subcategory":"Membership Organization",
            "type":"Services"
        }
    ],
    "sg:phone":"+1 863 471 0145",
    "sg:postcode":"33872",
    "sg:province":"FL",
    "wof:name":"Highlands Radio Control Club",
    "wof:placetype":"venue"
},
  "geometry": {"coordinates":[-81.509833,27.480645],"type":"Point"}
}