{
  "type": "Feature",
  "properties": {
    "addr:full":"2136 23rd Ave N Saint Petersburg FL 33713",
    "addr:housenumber":"2136",
    "addr:postcode":"33713",
    "addr:street":"23Rd Ave N",
    "iso:country":"US",
    "sg:address":"2136 23rd Ave N",
    "sg:city":"Saint Petersburg",
    "sg:classifiers":[
        {
            "category":"Personal",
            "type":"Services"
        }
    ],
    "sg:phone":"+1 727 821 2924",
    "sg:postcode":"33713",
    "sg:province":"FL",
    "wof:name":"Aquaproof and Roofing",
    "wof:placetype":"venue"
},
  "geometry": {"coordinates":[-82.66257400000001,27.792785],"type":"Point"}
}