{
  "type": "Feature",
  "properties": {
    "iso:country":"US",
    "sg:address":"5056 Tacon Dr",
    "sg:city":"Orlando",
    "sg:classifiers":[
        {
            "category":"Education",
            "subcategory":"School",
            "type":"Public Place"
        }
    ],
    "sg:phone":"+1 407 858 5920",
    "sg:postcode":"32837",
    "sg:province":"FL",
    "wof:name":"West Creek Elementary School",
    "wof:placetype":"venue"
},
  "geometry": {"coordinates":[-81.46441299999999,28.359171],"type":"Point"}
}