{
  "type": "Feature",
  "properties": {
    "addr:full":"19500 NW 1st Ct Miami FL 33169",
    "addr:housenumber":"19500",
    "addr:postcode":"33169",
    "addr:street":"Nw 1St Ct",
    "iso:country":"US",
    "sg:address":"19500 NW 1st Ct",
    "sg:city":"Miami",
    "sg:classifiers":[
        {
            "category":"Professional",
            "type":"Services"
        }
    ],
    "sg:phone":"+1 305 652 5418",
    "sg:postcode":"33169",
    "sg:province":"FL",
    "wof:name":"Dennis Ingram Mobile Marine",
    "wof:placetype":"venue"
},
  "geometry": {"coordinates":[-80.20393,25.954869],"type":"Point"}
}