{
  "type": "Feature",
  "properties": {
    "iso:country":"US",
    "sg:address":"6244 Morning Dove Way",
    "sg:city":"Hobe Sound",
    "sg:classifiers":[
        {
            "category":"Retail",
            "subcategory":"Repair Shop",
            "type":"Services"
        }
    ],
    "sg:phone":"+1 772 545 2948",
    "sg:postcode":"33455",
    "sg:province":"FL",
    "wof:name":"At Metc Inc",
    "wof:placetype":"venue"
},
  "geometry": {"coordinates":[-80.15858299999999,27.123241],"type":"Point"}
}