{
  "type": "Feature",
  "properties": {
    "iso:country":"US",
    "sg:address":"12613 Clendenning Dr",
    "sg:city":"Tampa",
    "sg:classifiers":[
        {
            "category":"Autos & Motor Vehicles",
            "subcategory":"Auto Supplies",
            "type":"Retail Goods"
        }
    ],
    "sg:phone":"+1 813 908 0101",
    "sg:postcode":"33618",
    "sg:province":"FL",
    "sg:tags":[
        "automobile",
        "alarm"
    ],
    "wof:name":"Auto Security Devices",
    "wof:placetype":"venue"
},
  "geometry": {"coordinates":[-82.50627900000001,28.060092],"type":"Point"}
}