{
  "type": "Feature",
  "properties": {
    "iso:country":"US",
    "sg:address":"2607 S Chesterfield Dr",
    "sg:city":"Fort Pierce",
    "sg:classifiers":[
        {
            "category":"Food & Beverages",
            "subcategory":"Specialty",
            "type":"Retail Goods"
        }
    ],
    "sg:phone":"+1 772 461 3103",
    "sg:postcode":"34982",
    "sg:province":"FL",
    "wof:name":"A Better Living Inc",
    "wof:placetype":"venue"
},
  "geometry": {"coordinates":[-80.34972500000001,27.421263],"type":"Point"}
}