{
  "type": "Feature",
  "properties": {
    "addr:full":"850 Cattlemen Rd Sarasota FL 34232",
    "addr:housenumber":"850",
    "addr:postcode":"34232",
    "addr:street":"Cattlemen Rd",
    "iso:country":"US",
    "sg:address":"850 Cattlemen Rd",
    "sg:city":"Sarasota",
    "sg:classifiers":[
        {
            "category":"Home & Garden",
            "subcategory":"Garden Supply",
            "type":"Retail Goods"
        }
    ],
    "sg:phone":"+1 941 371 2966",
    "sg:postcode":"34232",
    "sg:province":"FL",
    "wof:name":"Preferred Turf Equipment",
    "wof:placetype":"venue"
},
  "geometry": {"coordinates":[-82.45119200000001,27.327888],"type":"Point"}
}