{
  "type": "Feature",
  "properties": {
    "iso:country":"US",
    "sg:address":"412 NW 3rd St",
    "sg:city":"Okeechobee",
    "sg:classifiers":[
        {
            "category":"Professional",
            "subcategory":"Advertising",
            "type":"Services"
        }
    ],
    "sg:phone":"+1 863 357 4455",
    "sg:postcode":"34972",
    "sg:province":"FL",
    "wof:name":"Okeechobee Classifieds",
    "wof:placetype":"venue"
},
  "geometry": {"coordinates":[-80.83439199999999,27.245882],"type":"Point"}
}