{
  "type": "Feature",
  "properties": {
    "iso:country":"US",
    "sg:address":"100210 Overseas Hwy",
    "sg:city":"Key Largo",
    "sg:classifiers":[
        {
            "category":"Insurance",
            "subcategory":"Insurance Agent",
            "type":"Services"
        }
    ],
    "sg:phone":"+1 305 453 1445",
    "sg:postcode":"33037",
    "sg:province":"FL",
    "wof:name":"Keys Insurance Inc",
    "wof:placetype":"venue"
},
  "geometry": {"coordinates":[-80.435385,25.099459],"type":"Point"}
}