{
  "type": "Feature",
  "properties": {
    "addr:full":"1890 E 4th Ave Hialeah FL 33010",
    "addr:housenumber":"1890",
    "addr:postcode":"33010",
    "addr:street":"E 4Th Ave",
    "iso:country":"US",
    "sg:address":"1890 E 4th Ave",
    "sg:city":"Hialeah",
    "sg:classifiers":[
        {
            "category":"Wholesale",
            "subcategory":"Electrical",
            "type":"Manufacturing & Wholesale Goods"
        }
    ],
    "sg:phone":"+1 305 883 9030",
    "sg:postcode":"33010",
    "sg:province":"FL",
    "sg:tags":[
        "parts"
    ],
    "wof:name":"Iling",
    "wof:placetype":"venue"
},
  "geometry": {"coordinates":[-80.273991,25.838417],"type":"Point"}
}