{
  "type": "Feature",
  "properties": {
    "iso:country":"US",
    "sg:address":"220 E Desoto St",
    "sg:city":"Clermont",
    "sg:classifiers":[
        {
            "category":"Shopping",
            "subcategory":"Gifts & Souvenirs",
            "type":"Retail Goods"
        }
    ],
    "sg:phone":"+1 352 394 4992",
    "sg:postcode":"34711",
    "sg:province":"FL",
    "wof:name":"Abbey Rose",
    "wof:placetype":"venue"
},
  "geometry": {"coordinates":[-81.75332299999999,28.554231],"type":"Point"}
}