{
  "type": "Feature",
  "properties": {
    "addr:full":"12006 Havana Ave New Port Richey FL 34654",
    "addr:housenumber":"12006",
    "addr:postcode":"34654",
    "addr:street":"Havana Ave",
    "iso:country":"US",
    "sg:address":"12006 Havana Ave",
    "sg:city":"New Port Richey",
    "sg:classifiers":[
        {
            "category":"Building & Trades",
            "subcategory":"Construction",
            "type":"Services"
        }
    ],
    "sg:phone":"+1 727 856 3977",
    "sg:postcode":"34654",
    "sg:province":"FL",
    "sg:tags":[
        "concrete",
        "cutting",
        "breaking",
        "sawing"
    ],
    "wof:name":"Diamond Core Drilling-Sawing",
    "wof:placetype":"venue"
},
  "geometry": {"coordinates":[-82.607511,28.300326],"type":"Point"}
}