{
  "type": "Feature",
  "properties": {
    "addr:full":"607 W Bloomingdale Ave Brandon FL 33511",
    "addr:housenumber":"607",
    "addr:postcode":"33511",
    "addr:street":"W Bloomingdale Ave",
    "iso:country":"US",
    "sg:address":"607 W Bloomingdale Ave",
    "sg:city":"Brandon",
    "sg:classifiers":[
        {
            "category":"Health Services",
            "subcategory":"Doctor",
            "type":"Services"
        },
        {
            "category":"Health Services",
            "subcategory":"Dentist",
            "type":"Services"
        }
    ],
    "sg:phone":"+1 813 681 2529",
    "sg:postcode":"33511",
    "sg:province":"FL",
    "sg:tags":[
        "dentists-oral",
        "physician",
        "maxillofacial",
        "surgeons",
        "surgery",
        "oral"
    ],
    "wof:name":"Stuckert Jeffrey J Dds",
    "wof:placetype":"venue"
},
  "geometry": {"coordinates":[-82.293071,27.89362],"type":"Point"}
}