{
  "type": "Feature",
  "properties": {
    "addr:full":"150 Citrus Dr Kissimmee FL 34743",
    "addr:housenumber":"150",
    "addr:postcode":"34743",
    "addr:street":"Citrus Dr",
    "iso:country":"US",
    "sg:address":"150 Citrus Dr",
    "sg:city":"Kissimmee",
    "sg:classifiers":[
        {
            "category":"Building & Trades",
            "subcategory":"Construction",
            "type":"Services"
        }
    ],
    "sg:phone":"+1 407 344 3318",
    "sg:postcode":"34743",
    "sg:province":"FL",
    "sg:tags":[
        "hanging",
        "contractor"
    ],
    "wof:name":"Carlos Quintana",
    "wof:placetype":"venue"
},
  "geometry": {"coordinates":[-81.352401,28.337508],"type":"Point"}
}