{
  "type": "Feature",
  "properties": {
    "addr:full":"39 Rotonda Plz Rotonda West FL 33947",
    "addr:postcode":"33947",
    "addr:street":"39 Rotonda Plz",
    "iso:country":"US",
    "sg:address":"39 Rotonda Plz",
    "sg:city":"Rotonda West",
    "sg:classifiers":[
        {
            "category":"Building & Trades",
            "subcategory":"Landscaping Services",
            "type":"Services"
        }
    ],
    "sg:phone":"+1 941 697 2264",
    "sg:postcode":"33947",
    "sg:province":"FL",
    "wof:name":"Adam Baer Lawn Care",
    "wof:placetype":"venue"
},
  "geometry": {"coordinates":[-82.277354,26.892195],"type":"Point"}
}