{
  "type": "Feature",
  "properties": {
    "iso:country":"US",
    "sg:address":"10280 SW 124th St",
    "sg:city":"Miami",
    "sg:classifiers":[
        {
            "category":"Retail",
            "subcategory":"Veterinary Services",
            "type":"Services"
        }
    ],
    "sg:phone":"+1 305 790 0238",
    "sg:postcode":"33176",
    "sg:province":"FL",
    "sg:tags":[
        "veterinarian",
        "specialty"
    ],
    "wof:name":"Zachary Franklin, D.V.M., P.A.",
    "wof:placetype":"venue"
},
  "geometry": {"coordinates":[-80.360646,25.654115],"type":"Point"}
}