{
  "type": "Feature",
  "properties": {
    "iso:country":"US",
    "sg:address":"7211 Environmental Rd",
    "sg:city":"Arcadia",
    "sg:classifiers":[
        {
            "category":"Home & Garden",
            "subcategory":"Garden Supply",
            "type":"Retail Goods"
        },
        {
            "category":"Building & Trades",
            "subcategory":"Landscaping Services",
            "type":"Services"
        }
    ],
    "sg:phone":"+1 863 494 1015",
    "sg:postcode":"34266",
    "sg:province":"FL",
    "sg:tags":[
        "grounds",
        "lawn",
        "nursery",
        "maintenance",
        "care"
    ],
    "wof:name":"Desoto Greenscapes Inc",
    "wof:placetype":"venue"
},
  "geometry": {"coordinates":[-81.97890700000001,27.174816],"type":"Point"}
}