{
  "type": "Feature",
  "properties": {
    "iso:country":"US",
    "sg:address":"9728 W Sample Rd",
    "sg:city":"Pompano Beach",
    "sg:classifiers":[
        {
            "category":"Professional",
            "subcategory":"Accounting & Tax Preparation",
            "type":"Services"
        }
    ],
    "sg:phone":"+1 954 753 5559",
    "sg:postcode":"33065",
    "sg:province":"FL",
    "wof:name":"David Pinchevsky and Assoc",
    "wof:placetype":"venue"
},
  "geometry": {"coordinates":[-80.25654,26.272457],"type":"Point"}
}