{
  "type": "Feature",
  "properties": {
    "iso:country":"US",
    "sg:address":"1052 Willa Springs Dr",
    "sg:city":"Winter Springs",
    "sg:classifiers":[
        {
            "category":"Banks & Credit Unions",
            "subcategory":"Investment Brokerage",
            "type":"Services"
        }
    ],
    "sg:phone":"+1 407 862 3755",
    "sg:postcode":"32708",
    "sg:province":"FL",
    "sg:tags":[
        "investing"
    ],
    "wof:name":"Summer Field Financial Inc",
    "wof:placetype":"venue"
},
  "geometry": {"coordinates":[-81.269819,28.644338],"type":"Point"}
}