{
  "type": "Feature",
  "properties": {
    "iso:country":"US",
    "sg:address":"26315 Northern Cross Rd",
    "sg:city":"Punta Gorda",
    "sg:classifiers":[
        {
            "category":"Social Services",
            "subcategory":"Adult Care",
            "type":"Services"
        }
    ],
    "sg:phone":"+1 941 625 0030",
    "sg:postcode":"33983",
    "sg:province":"FL",
    "sg:tags":[
        "residential"
    ],
    "wof:name":"Kimberly Place",
    "wof:placetype":"venue"
},
  "geometry": {"coordinates":[-82.015325,27.010802],"type":"Point"}
}