{
  "type": "Feature",
  "properties": {
    "addr:full":"1381 Cross Creek Way Tallahassee FL 32301",
    "addr:housenumber":"1381",
    "addr:postcode":"32301",
    "addr:street":"Cross Creek Way",
    "iso:country":"US",
    "sg:address":"1381 Cross Creek Way",
    "sg:city":"Tallahassee",
    "sg:classifiers":[
        {
            "category":"Wholesale",
            "subcategory":"Electrical",
            "type":"Manufacturing & Wholesale Goods"
        }
    ],
    "sg:phone":"+1 850 309 7600",
    "sg:postcode":"32301",
    "sg:province":"FL",
    "sg:tags":[
        "alarm",
        "burglar",
        "system"
    ],
    "wof:name":"Ferrell Security Group Inc",
    "wof:placetype":"venue"
},
  "geometry": {"coordinates":[-84.235545,30.432185],"type":"Point"}
}