{
  "type": "Feature",
  "properties": {
    "iso:country":"US",
    "sg:address":"15205 SW 104th St",
    "sg:city":"Miami",
    "sg:classifiers":[
        {
            "category":"Autos & Motor Vehicles",
            "subcategory":"Fuel & Gas Station",
            "type":"Retail Goods"
        }
    ],
    "sg:phone":"+1 305 385 3343",
    "sg:postcode":"33196",
    "sg:province":"FL",
    "sg:tags":[
        "station",
        "gasoline"
    ],
    "wof:name":"Mobil",
    "wof:placetype":"venue"
},
  "geometry": {"coordinates":[-80.44218499999999,25.669881],"type":"Point"}
}