{
  "type": "Feature",
  "properties": {
    "addr:full":"4200 W Sample Rd Pompano Beach FL 33073",
    "addr:housenumber":"4200",
    "addr:postcode":"33073",
    "addr:street":"W Sample Rd",
    "iso:country":"US",
    "sg:address":"4200 W Sample Rd",
    "sg:city":"Pompano Beach",
    "sg:classifiers":[
        {
            "category":"Restaurant",
            "type":"Food & Drink"
        }
    ],
    "sg:menulink":"http://www.allmenus.com/fl/pompano-beach/187077-mcdonalds/menu/",
    "sg:phone":"+1 954 968 3310",
    "sg:postcode":"33073",
    "sg:province":"FL",
    "sg:tags":[
        "burger",
        "american"
    ],
    "wof:name":"McDonald's",
    "wof:placetype":"venue"
},
  "geometry": {"coordinates":[-80.182444,26.27378],"type":"Point"}
}