{
  "type": "Feature",
  "properties": {
    "iso:country":"US",
    "sg:address":"10302 NW 87th Ave",
    "sg:city":"Hialeah",
    "sg:classifiers":[
        {
            "category":"Utilities",
            "subcategory":"Telephone",
            "type":"Services"
        }
    ],
    "sg:phone":"+1 786 621 5418",
    "sg:postcode":"33018",
    "sg:province":"FL",
    "sg:tags":[
        "phones-equipment",
        "pay"
    ],
    "wof:name":"Garden Shell Pay Phone",
    "wof:placetype":"venue"
},
  "geometry": {"coordinates":[-80.340565,25.902135],"type":"Point"}
}