{
  "type": "Feature",
  "properties": {
    "iso:country":"US",
    "sg:address":"207 N Bay Hills Blvd",
    "sg:city":"Safety Harbor",
    "sg:classifiers":[
        {
            "category":"Professional",
            "subcategory":"Management & Consulting",
            "type":"Services"
        }
    ],
    "sg:phone":"+1 727 669 6313",
    "sg:postcode":"34695",
    "sg:province":"FL",
    "sg:tags":[
        "business"
    ],
    "wof:name":"Business Success Institute",
    "wof:placetype":"venue"
},
  "geometry": {"coordinates":[-82.695002,28.022108],"type":"Point"}
}