{
  "type": "Feature",
  "properties": {
    "iso:country":"US",
    "sg:address":"214 Miracle Strip Pkwy",
    "sg:city":"Fort Walton Bch",
    "sg:classifiers":[
        {
            "category":"Real Estate",
            "subcategory":"Real Estate Operator",
            "type":"Services"
        }
    ],
    "sg:phone":"+1 850 244 5101",
    "sg:postcode":"32548",
    "sg:province":"FL",
    "sg:tags":[
        "condominium"
    ],
    "sg:website":"www.miramarr.com",
    "wof:name":"Pirates Bay Condo Hotel",
    "wof:placetype":"venue"
},
  "geometry": {"coordinates":[-86.605149,30.403613],"type":"Point"}
}