{
  "type": "Feature",
  "properties": {
    "addr:full":"6639 Van Gundy Rd Jacksonville FL 32208",
    "addr:housenumber":"6639",
    "addr:postcode":"32208",
    "addr:street":"Van Gundy Rd",
    "iso:country":"US",
    "sg:address":"6639 Van Gundy Rd",
    "sg:city":"Jacksonville",
    "sg:classifiers":[
        {
            "category":"Social Services",
            "subcategory":"Child Care",
            "type":"Services"
        }
    ],
    "sg:phone":"+1 904 765 2401",
    "sg:postcode":"32208",
    "sg:province":"FL",
    "wof:name":"For Your Child Only Vg",
    "wof:placetype":"venue"
},
  "geometry": {"coordinates":[-81.703236,30.390893],"type":"Point"}
}