{
  "type": "Feature",
  "properties": {
    "iso:country":"US",
    "sg:address":"1975 Niblick Dr",
    "sg:city":"Jacksonville",
    "sg:classifiers":[
        {
            "category":"Building & Trades",
            "subcategory":"Cleaning & Sanitation",
            "type":"Services"
        }
    ],
    "sg:phone":"+1 904 379 4900",
    "sg:postcode":"32210",
    "sg:province":"FL",
    "sg:tags":[
        "equipment"
    ],
    "wof:name":"United Cleaning Specialists",
    "wof:placetype":"venue"
},
  "geometry": {"coordinates":[-81.743452,30.2823],"type":"Point"}
}