{
  "type": "Feature",
  "properties": {
    "addr:full":"11400 W Flagler St Miami FL 33174",
    "addr:housenumber":"11400",
    "addr:postcode":"33174",
    "addr:street":"W Flagler St",
    "iso:country":"US",
    "sg:address":"11400 W Flagler St",
    "sg:city":"Miami",
    "sg:classifiers":[
        {
            "category":"Shopping",
            "subcategory":"Gifts & Souvenirs",
            "type":"Retail Goods"
        }
    ],
    "sg:phone":"+1 305 553 1166",
    "sg:postcode":"33174",
    "sg:province":"FL",
    "sg:tags":[
        "shop"
    ],
    "wof:name":"Angeles Guardians",
    "wof:placetype":"venue"
},
  "geometry": {"coordinates":[-80.380019,25.768214],"type":"Point"}
}