{
  "type": "Feature",
  "properties": {
    "addr:full":"2081 Chaffee Rd S Jacksonville FL 32221",
    "addr:housenumber":"2081",
    "addr:postcode":"32221",
    "addr:street":"Chaffee Rd",
    "iso:country":"US",
    "sg:address":"2081 Chaffee Rd S",
    "sg:city":"Jacksonville",
    "sg:classifiers":[
        {
            "category":"Building & Trades",
            "subcategory":"Pest Control",
            "type":"Services"
        }
    ],
    "sg:phone":"+1 904 693 6560",
    "sg:postcode":"32221",
    "sg:province":"FL",
    "wof:name":"Cannon Pest Control",
    "wof:placetype":"venue"
},
  "geometry": {"coordinates":[-81.848569,30.281636],"type":"Point"}
}