{
  "type": "Feature",
  "properties": {
    "addr:full":"3423 Saddlebrook Dr Melbourne FL 32934",
    "addr:housenumber":"3423",
    "addr:postcode":"32934",
    "addr:street":"Saddlebrook Dr",
    "iso:country":"US",
    "sg:address":"3423 Saddlebrook Dr",
    "sg:city":"Melbourne",
    "sg:classifiers":[
        {
            "category":"Building & Trades",
            "subcategory":"Construction",
            "type":"Services"
        }
    ],
    "sg:phone":"+1 321 242 8343",
    "sg:postcode":"32934",
    "sg:province":"FL",
    "sg:tags":[
        "residential"
    ],
    "wof:name":"Sandcastle Construction Inc",
    "wof:placetype":"venue"
},
  "geometry": {"coordinates":[-80.67719,28.158037],"type":"Point"}
}