{
  "type": "Feature",
  "properties": {
    "addr:full":"5090 Bay St NE St Petersburg FL 33703",
    "addr:housenumber":"5090",
    "addr:postcode":"33703",
    "addr:street":"Bay St Ne",
    "iso:country":"US",
    "sg:address":"5090 Bay St NE",
    "sg:city":"St Petersburg",
    "sg:classifiers":[
        {
            "category":"Personal",
            "subcategory":"Beauty Salon",
            "type":"Services"
        }
    ],
    "sg:phone":"+1 727 527 4110",
    "sg:postcode":"33703",
    "sg:province":"FL",
    "wof:name":"Gonnella Hair Fashions",
    "wof:placetype":"venue"
},
  "geometry": {"coordinates":[-82.632362,27.817669],"type":"Point"}
}