{
  "type": "Feature",
  "properties": {
    "addr:full":"9510 April Rd Miami FL 33157",
    "addr:housenumber":"9510",
    "addr:postcode":"33157",
    "addr:street":"April Rd",
    "iso:country":"US",
    "sg:address":"9510 April Rd",
    "sg:city":"Miami",
    "sg:classifiers":[
        {
            "category":"Autos & Motor Vehicles",
            "subcategory":"Automobile Sales",
            "type":"Retail Goods"
        }
    ],
    "sg:phone":"+1 305 378 2530",
    "sg:postcode":"33157",
    "sg:province":"FL",
    "wof:name":"Blake Chevrolet Buick",
    "wof:placetype":"venue"
},
  "geometry": {"coordinates":[-80.34799599999999,25.585598],"type":"Point"}
}