{
  "type": "Feature",
  "properties": {
    "iso:country":"US",
    "sg:address":"2101 Bent Oak Ct",
    "sg:city":"Panama City",
    "sg:classifiers":[
        {
            "category":"Personal",
            "type":"Services"
        }
    ],
    "sg:phone":"+1 850 236 1953",
    "sg:postcode":"32408",
    "sg:province":"FL",
    "wof:name":"Your Pets Nanny",
    "wof:placetype":"venue"
},
  "geometry": {"coordinates":[-85.75870399999999,30.166418],"type":"Point"}
}