{
  "type": "Feature",
  "properties": {
    "iso:country":"US",
    "sg:address":"326 E Boynton Beach Blvd",
    "sg:city":"Boynton Beach",
    "sg:classifiers":[
        {
            "category":"Shopping",
            "subcategory":"Computers & Home Electronics",
            "type":"Retail Goods"
        }
    ],
    "sg:phone":"+1 561 278 5220",
    "sg:postcode":"33435",
    "sg:province":"FL",
    "sg:tags":[
        "television",
        "radio"
    ],
    "wof:name":"Good Life The TV",
    "wof:placetype":"venue"
},
  "geometry": {"coordinates":[-80.061938,26.528832],"type":"Point"}
}