{
  "type": "Feature",
  "properties": {
    "iso:country":"US",
    "sg:address":"892 SW 70th Ave",
    "sg:city":"Miami",
    "sg:classifiers":[
        {
            "category":"Wholesale",
            "subcategory":"Construction Materials",
            "type":"Manufacturing & Wholesale Goods"
        }
    ],
    "sg:phone":"+1 305 261 3700",
    "sg:postcode":"33144",
    "sg:province":"FL",
    "sg:tags":[
        "stone",
        "floor",
        "wall",
        "ceramic",
        "tile",
        "brick"
    ],
    "wof:name":"Imperial Tiles Inc",
    "wof:placetype":"venue"
},
  "geometry": {"coordinates":[-80.308615,25.762874],"type":"Point"}
}