{
  "type": "Feature",
  "properties": {
    "iso:country":"US",
    "sg:address":"7312 SW 80th St Plz",
    "sg:city":"Miami",
    "sg:classifiers":[
        {
            "category":"Manufacturing",
            "subcategory":"Printing",
            "type":"Manufacturing & Wholesale Goods"
        }
    ],
    "sg:phone":"+1 305 661 8743",
    "sg:postcode":"33143",
    "sg:province":"FL",
    "sg:tags":[
        "publishing"
    ],
    "wof:name":"Mass Groovement Publishing Co",
    "wof:placetype":"venue"
},
  "geometry": {"coordinates":[-80.313109,25.695341],"type":"Point"}
}