{
  "type": "Feature",
  "properties": {
    "addr:full":"8497 Bonita Isle Dr Lake Worth FL 33467",
    "addr:housenumber":"8497",
    "addr:postcode":"33467",
    "addr:street":"Bonita Isle Dr",
    "iso:country":"US",
    "sg:address":"8497 Bonita Isle Dr",
    "sg:city":"Lake Worth",
    "sg:classifiers":[
        {
            "category":"Building & Trades",
            "subcategory":"Landscaping Services",
            "type":"Services"
        }
    ],
    "sg:phone":"+1 561 670 8489",
    "sg:postcode":"33467",
    "sg:province":"FL",
    "sg:tags":[
        "lawn",
        "maintenance",
        "grounds"
    ],
    "wof:name":"Art Johnson Complete Lawn Care",
    "wof:placetype":"venue"
},
  "geometry": {"coordinates":[-80.17993300000001,26.596987],"type":"Point"}
}