{
  "type": "Feature",
  "properties": {
    "iso:country":"US",
    "sg:address":"1903 N Hercules Ave",
    "sg:city":"Clearwater",
    "sg:classifiers":[
        {
            "category":"Food & Beverages",
            "subcategory":"Liquor & Beverages",
            "type":"Retail Goods"
        }
    ],
    "sg:phone":"+1 727 443 6987",
    "sg:postcode":"33763",
    "sg:province":"FL",
    "sg:tags":[
        "beer",
        "ale"
    ],
    "wof:name":"Aum's Discount Beverage",
    "wof:placetype":"venue"
},
  "geometry": {"coordinates":[-82.754666,27.992004],"type":"Point"}
}