{
  "type": "Feature",
  "properties": {
    "iso:country":"US",
    "sg:address":"9495 SW 72nd St",
    "sg:city":"Miami",
    "sg:classifiers":[
        {
            "category":"Health Services",
            "subcategory":"Doctor",
            "type":"Services"
        }
    ],
    "sg:phone":"+1 305 271 8098",
    "sg:postcode":"33173",
    "sg:province":"FL",
    "sg:tags":[
        "clinic"
    ],
    "wof:name":"AAMFT Clinical Members",
    "wof:placetype":"venue"
},
  "geometry": {"coordinates":[-80.34733300000001,25.701823],"type":"Point"}
}