{
  "type": "Feature",
  "properties": {
    "iso:country":"US",
    "sg:address":"20225 NE 34th Ct Ofc",
    "sg:city":"Miami",
    "sg:classifiers":[
        {
            "category":"Manufacturing",
            "subcategory":"Building Materials",
            "type":"Manufacturing & Wholesale Goods"
        },
        {
            "category":"Home & Garden",
            "subcategory":"Carpets & Floor Coverings",
            "type":"Retail Goods"
        }
    ],
    "sg:phone":"+1 954 914 1721",
    "sg:postcode":"33180",
    "sg:province":"FL",
    "sg:tags":[
        "materials-wholesale",
        "manufacturer"
    ],
    "wof:name":"Stone Solutions",
    "wof:placetype":"venue"
},
  "geometry": {"coordinates":[-80.13391900000001,25.965068],"type":"Point"}
}