{
  "type": "Feature",
  "properties": {
    "iso:country":"US",
    "sg:address":"4903 Donovan St",
    "sg:city":"Orlando",
    "sg:classifiers":[
        {
            "category":"Education",
            "subcategory":"School",
            "type":"Public Place"
        }
    ],
    "sg:phone":"+1 407 296 6530",
    "sg:postcode":"32808",
    "sg:province":"FL",
    "wof:name":"Rolling Hills Elementary Schl",
    "wof:placetype":"venue"
},
  "geometry": {"coordinates":[-81.44613099999999,28.589381],"type":"Point"}
}