{
  "type": "Feature",
  "properties": {
    "addr:full":"6012 Tippin Ave Pensacola FL 32504",
    "addr:housenumber":"6012",
    "addr:postcode":"32504",
    "addr:street":"Tippin Ave",
    "iso:country":"US",
    "sg:address":"6012 Tippin Ave",
    "sg:city":"Pensacola",
    "sg:classifiers":[
        {
            "category":"Professional",
            "subcategory":"Accounting & Tax Preparation",
            "type":"Services"
        }
    ],
    "sg:phone":"+1 850 476 0042",
    "sg:postcode":"32504",
    "sg:province":"FL",
    "sg:tags":[
        "accountant"
    ],
    "wof:name":"Katherine X Wilborn CPA",
    "wof:placetype":"venue"
},
  "geometry": {"coordinates":[-87.196851,30.485007],"type":"Point"}
}