{
  "type": "Feature",
  "properties": {
    "addr:full":"5657 America Dr Sarasota FL 34231",
    "addr:housenumber":"5657",
    "addr:postcode":"34231",
    "addr:street":"America Dr",
    "iso:country":"US",
    "sg:address":"5657 America Dr",
    "sg:city":"Sarasota",
    "sg:classifiers":[
        {
            "category":"Marine",
            "type":"Transportation"
        }
    ],
    "sg:phone":"+1 941 921 5523",
    "sg:postcode":"34231",
    "sg:province":"FL",
    "wof:name":"Choice Marines Service",
    "wof:placetype":"venue"
},
  "geometry": {"coordinates":[-82.526015,27.271868],"type":"Point"}
}