{
  "type": "Feature",
  "properties": {
    "addr:full":"3137 Commerce Pkwy Hollywood FL 33025",
    "addr:housenumber":"3137",
    "addr:postcode":"33025",
    "addr:street":"Commerce Pkwy",
    "iso:country":"US",
    "sg:address":"3137 Commerce Pkwy",
    "sg:city":"Hollywood",
    "sg:classifiers":[
        {
            "category":"Building & Trades",
            "subcategory":"Electrical",
            "type":"Services"
        }
    ],
    "sg:phone":"+1 954 436 2600",
    "sg:postcode":"33025",
    "sg:province":"FL",
    "sg:tags":[
        "installation",
        "telephone"
    ],
    "wof:name":"Lucent Technologies Inc",
    "wof:placetype":"venue"
},
  "geometry": {"coordinates":[-80.281263,25.976766],"type":"Point"}
}