{
  "type": "Feature",
  "properties": {
    "addr:full":"3512 Doreen Dr Lakeland FL 33810",
    "addr:housenumber":"3512",
    "addr:postcode":"33810",
    "addr:street":"Doreen Dr",
    "iso:country":"US",
    "sg:address":"3512 Doreen Dr",
    "sg:city":"Lakeland",
    "sg:classifiers":[
        {
            "category":"Freight",
            "type":"Transportation"
        }
    ],
    "sg:phone":"+1 863 683 1962",
    "sg:postcode":"33810",
    "sg:province":"FL",
    "wof:name":"A D Logistics",
    "wof:placetype":"venue"
},
  "geometry": {"coordinates":[-82.01797999999999,28.051959],"type":"Point"}
}