{
  "type": "Feature",
  "properties": {
    "addr:full":"1509 Neil St Plant City FL 33563",
    "addr:housenumber":"1509",
    "addr:postcode":"33563",
    "addr:street":"Neil St",
    "iso:country":"US",
    "sg:address":"1509 Neil St",
    "sg:city":"Plant City",
    "sg:classifiers":[
        {
            "category":"Personal",
            "subcategory":"Beauty Salon",
            "type":"Services"
        }
    ],
    "sg:phone":"+1 813 707 0824",
    "sg:postcode":"33563",
    "sg:province":"FL",
    "sg:tags":[
        "shop"
    ],
    "wof:name":"Wright Beauty Salon",
    "wof:placetype":"venue"
},
  "geometry": {"coordinates":[-82.10920400000001,28.016903],"type":"Point"}
}