{
  "type": "Feature",
  "properties": {
    "iso:country":"US",
    "sg:address":"2222 Old St Augustine Rd",
    "sg:city":"Tallahassee",
    "sg:classifiers":[
        {
            "category":"Social Services",
            "type":"Services"
        }
    ],
    "sg:phone":"+1 850 656 7110",
    "sg:postcode":"32301",
    "sg:province":"FL",
    "wof:name":"Brehon Institute",
    "wof:placetype":"venue"
},
  "geometry": {"coordinates":[-84.242734,30.424961],"type":"Point"}
}