{
  "type": "Feature",
  "properties": {
    "addr:full":"744 Rider Rd Boynton Beach FL 33435",
    "addr:housenumber":"744",
    "addr:postcode":"33435",
    "addr:street":"Rider Rd",
    "iso:country":"US",
    "sg:address":"744 Rider Rd",
    "sg:city":"Boynton Beach",
    "sg:classifiers":[
        {
            "category":"Building & Trades",
            "subcategory":"Construction",
            "type":"Services"
        }
    ],
    "sg:phone":"+1 561 369 8797",
    "sg:postcode":"33435",
    "sg:province":"FL",
    "sg:tags":[
        "siding",
        "gutter"
    ],
    "wof:name":"Guttersmith Inc",
    "wof:placetype":"venue"
},
  "geometry": {"coordinates":[-80.05509000000001,26.536511],"type":"Point"}
}