{
  "type": "Feature",
  "properties": {
    "addr:full":"506 15th St West Palm Beach FL 33401",
    "addr:housenumber":"506",
    "addr:postcode":"33401",
    "addr:street":"15Th St",
    "iso:country":"US",
    "sg:address":"506 15th St",
    "sg:city":"West Palm Beach",
    "sg:classifiers":[
        {
            "category":"Organizations",
            "subcategory":"Religious Organization",
            "type":"Services"
        }
    ],
    "sg:phone":"+1 561 659 5015",
    "sg:postcode":"33401",
    "sg:province":"FL",
    "sg:tags":[
        "church"
    ],
    "wof:name":"Bibleway Missionary Bapt Chr",
    "wof:placetype":"venue"
},
  "geometry": {"coordinates":[-80.056843,26.7272],"type":"Point"}
}