{
  "type": "Feature",
  "properties": {
    "addr:full":"16920 Lake James Rd Odessa FL 33556",
    "addr:housenumber":"16920",
    "addr:postcode":"33556",
    "addr:street":"Lake James Rd",
    "iso:country":"US",
    "sg:address":"16920 Lake James Rd",
    "sg:city":"Odessa",
    "sg:classifiers":[
        {
            "category":"Organizations",
            "subcategory":"Religious Organization",
            "type":"Services"
        }
    ],
    "sg:phone":"+1 813 852 2400",
    "sg:postcode":"33556",
    "sg:province":"FL",
    "sg:tags":[
        "church"
    ],
    "wof:name":"Crosspointe A Chr-The Nzrn",
    "wof:placetype":"venue"
},
  "geometry": {"coordinates":[-82.57158099999999,28.114899],"type":"Point"}
}