{
  "type": "Feature",
  "properties": {
    "addr:full":"155 W 22nd St Hialeah FL 33010",
    "addr:housenumber":"155",
    "addr:postcode":"33010",
    "addr:street":"W 22Nd St",
    "iso:country":"US",
    "sg:address":"155 W 22nd St",
    "sg:city":"Hialeah",
    "sg:classifiers":[
        {
            "category":"Retail",
            "subcategory":"Auto Repair",
            "type":"Services"
        }
    ],
    "sg:phone":"+1 305 885 2228",
    "sg:postcode":"33010",
    "sg:province":"FL",
    "wof:name":"Jj Auto Repair",
    "wof:placetype":"venue"
},
  "geometry": {"coordinates":[-80.28510300000001,25.841801],"type":"Point"}
}