{
  "type": "Feature",
  "properties": {
    "iso:country":"US",
    "sg:address":"178 Captains Ct",
    "sg:city":"Tavernier",
    "sg:classifiers":[
        {
            "category":"Farming",
            "subcategory":"Fish & Marine Products",
            "type":"Manufacturing & Wholesale Goods"
        },
        {
            "category":"Autos & Motor Vehicles",
            "subcategory":"Boat Sales",
            "type":"Retail Goods"
        }
    ],
    "sg:phone":"+1 305 852 6363",
    "sg:postcode":"33070",
    "sg:province":"FL",
    "sg:tags":[
        "repair",
        "electric",
        "maintenance"
    ],
    "wof:name":"Southern Marine Maintenance Inc",
    "wof:placetype":"venue"
},
  "geometry": {"coordinates":[-80.533191,25.007637],"type":"Point"}
}