{
  "type": "Feature",
  "properties": {
    "iso:country":"US",
    "sg:address":"341 W Gardenia Dr",
    "sg:city":"Orange City",
    "sg:classifiers":[
        {
            "category":"Shopping",
            "subcategory":"Used Merchandise",
            "type":"Retail Goods"
        }
    ],
    "sg:phone":"+1 386 775 3542",
    "sg:postcode":"32763",
    "sg:province":"FL",
    "sg:tags":[
        "flea",
        "market"
    ],
    "wof:name":"Oswald R Donald Jr Flea Market",
    "wof:placetype":"venue"
},
  "geometry": {"coordinates":[-81.30587199999999,28.928254],"type":"Point"}
}