{
  "type": "Feature",
  "properties": {
    "addr:full":"2550 Sunset Point Rd Clearwater FL 33765",
    "addr:housenumber":"2550",
    "addr:postcode":"33765",
    "addr:street":"Sunset Point Rd",
    "iso:country":"US",
    "sg:address":"2550 Sunset Point Rd",
    "sg:city":"Clearwater",
    "sg:classifiers":[
        {
            "category":"Building & Trades",
            "subcategory":"Construction",
            "type":"Services"
        }
    ],
    "sg:phone":"+1 727 712 3847",
    "sg:postcode":"33765",
    "sg:province":"FL",
    "sg:tags":[
        "floor",
        "laying",
        "contractor"
    ],
    "wof:name":"Flooringworldcom Inc",
    "wof:placetype":"venue"
},
  "geometry": {"coordinates":[-82.731905,27.990596],"type":"Point"}
}