{
  "type": "Feature",
  "properties": {
    "addr:full":"702 Suwanee St Jupiter FL 33458",
    "addr:housenumber":"702",
    "addr:postcode":"33458",
    "addr:street":"Suwanee St",
    "iso:country":"US",
    "sg:address":"702 Suwanee St",
    "sg:city":"Jupiter",
    "sg:classifiers":[
        {
            "category":"Shopping",
            "subcategory":"Clothing, Apparel, & Fashions",
            "type":"Retail Goods"
        }
    ],
    "sg:phone":"+1 561 743 7567",
    "sg:postcode":"33458",
    "sg:province":"FL",
    "sg:tags":[
        "alteration"
    ],
    "wof:name":"Alterations & Custom Designs",
    "wof:placetype":"venue"
},
  "geometry": {"coordinates":[-80.114355,26.927841],"type":"Point"}
}