{
  "type": "Feature",
  "properties": {
    "addr:full":"2501 Taylor St Hollywood FL 33020",
    "addr:housenumber":"2501",
    "addr:postcode":"33020",
    "addr:street":"Taylor St",
    "iso:country":"US",
    "sg:address":"2501 Taylor St",
    "sg:city":"Hollywood",
    "sg:classifiers":[
        {
            "category":"Building & Trades",
            "subcategory":"Landscaping Services",
            "type":"Services"
        }
    ],
    "sg:phone":"+1 954 929 8864",
    "sg:postcode":"33020",
    "sg:province":"FL",
    "wof:name":"Heavy Duty Grounds Maintenance",
    "wof:placetype":"venue"
},
  "geometry": {"coordinates":[-80.157023,26.013741],"type":"Point"}
}