{
  "type": "Feature",
  "properties": {
    "iso:country":"US",
    "sg:address":"12680 McGregor Blvd",
    "sg:city":"Fort Myers",
    "sg:classifiers":[
        {
            "category":"Food & Beverages",
            "subcategory":"Bakery",
            "type":"Retail Goods"
        }
    ],
    "sg:phone":"+1 239 489 2666",
    "sg:postcode":"33919",
    "sg:province":"FL",
    "sg:tags":[
        "sandwich"
    ],
    "wof:name":"Boombalattis Sandwich Company",
    "wof:placetype":"venue"
},
  "geometry": {"coordinates":[-81.909848,26.558824],"type":"Point"}
}