{
  "type": "Feature",
  "properties": {
    "addr:full":"6712 NW 2nd St Margate FL 33063",
    "addr:housenumber":"6712",
    "addr:postcode":"33063",
    "addr:street":"Nw 2Nd St Margate",
    "iso:country":"US",
    "sg:address":"6712 NW 2nd St",
    "sg:city":"Margate",
    "sg:classifiers":[
        {
            "category":"Home & Garden",
            "subcategory":"Home Furnishings",
            "type":"Retail Goods"
        }
    ],
    "sg:phone":"+1 954 255 8887",
    "sg:postcode":"33063",
    "sg:province":"FL",
    "sg:tags":[
        "venetian",
        "blind"
    ],
    "wof:name":"Blind Stop USA Inc",
    "wof:placetype":"venue"
},
  "geometry": {"coordinates":[-80.21584,26.232318],"type":"Point"}
}