{
  "type": "Feature",
  "properties": {
    "iso:country":"US",
    "sg:address":"4810 Davis Blvd",
    "sg:city":"Naples",
    "sg:classifiers":[
        {
            "category":"Restaurant",
            "type":"Food & Drink"
        }
    ],
    "sg:phone":"+1 239 775 4655",
    "sg:postcode":"34104",
    "sg:province":"FL",
    "wof:name":"Cheeburger Cheeburger",
    "wof:placetype":"venue"
},
  "geometry": {"coordinates":[-81.747553,26.138606],"type":"Point"}
}