{
  "type": "Feature",
  "properties": {
    "iso:country":"US",
    "sg:address":"1360 Trotters Walk Way",
    "sg:city":"Jacksonville",
    "sg:classifiers":[
        {
            "category":"Building & Trades",
            "subcategory":"Landscaping Services",
            "type":"Services"
        }
    ],
    "sg:phone":"+1 904 996 7216",
    "sg:postcode":"32225",
    "sg:province":"FL",
    "sg:tags":[
        "landscape"
    ],
    "wof:name":"William H Callander",
    "wof:placetype":"venue"
},
  "geometry": {"coordinates":[-81.491184,30.350036],"type":"Point"}
}