{
  "type": "Feature",
  "properties": {
    "iso:country":"US",
    "sg:address":"20502 W Dixie Hwy",
    "sg:city":"Miami",
    "sg:classifiers":[
        {
            "category":"Personal",
            "subcategory":"Beauty Salon",
            "type":"Services"
        }
    ],
    "sg:phone":"+1 305 933 0090",
    "sg:postcode":"33180",
    "sg:province":"FL",
    "sg:tags":[
        "treatment",
        "skin"
    ],
    "wof:name":"Permanent Elegance By Eskala",
    "wof:placetype":"venue"
},
  "geometry": {"coordinates":[-80.14785000000001,25.96617],"type":"Point"}
}