{
  "type": "Feature",
  "properties": {
    "addr:full":"2873 Oakbrook Dr Fort Lauderdale FL 33332",
    "addr:housenumber":"2873",
    "addr:postcode":"33332",
    "addr:street":"Oakbrook Dr",
    "iso:country":"US",
    "sg:address":"2873 Oakbrook Dr",
    "sg:city":"Fort Lauderdale",
    "sg:classifiers":[
        {
            "category":"Health Services",
            "subcategory":"Clinic",
            "type":"Services"
        }
    ],
    "sg:phone":"+1 954 385 1071",
    "sg:postcode":"33332",
    "sg:province":"FL",
    "sg:tags":[
        "specialty",
        "outpatient"
    ],
    "wof:name":"Flex Rehab Services Inc",
    "wof:placetype":"venue"
},
  "geometry": {"coordinates":[-80.402798,26.086803],"type":"Point"}
}