{
  "type": "Feature",
  "properties": {
    "iso:country":"US",
    "sg:address":"4018 W Cayuga St",
    "sg:city":"Tampa",
    "sg:classifiers":[
        {
            "category":"Building & Trades",
            "subcategory":"Construction",
            "type":"Services"
        }
    ],
    "sg:phone":"+1 813 872 5658",
    "sg:postcode":"33614",
    "sg:province":"FL",
    "sg:tags":[
        "roofing",
        "contractor"
    ],
    "wof:name":"Gem Roofing Of Tampa Inc",
    "wof:placetype":"venue"
},
  "geometry": {"coordinates":[-82.512032,27.986394],"type":"Point"}
}