{
  "type": "Feature",
  "properties": {
    "addr:full":"1627 E Gary Rd Lakeland FL 33801",
    "addr:housenumber":"1627",
    "addr:postcode":"33801",
    "addr:street":"E Gary Rd",
    "iso:country":"US",
    "sg:address":"1627 E Gary Rd",
    "sg:city":"Lakeland",
    "sg:classifiers":[
        {
            "category":"Home & Garden",
            "subcategory":"Carpets & Floor Coverings",
            "type":"Retail Goods"
        }
    ],
    "sg:phone":"+1 863 682 6700",
    "sg:postcode":"33801",
    "sg:province":"FL",
    "sg:tags":[
        "dealer",
        "rug"
    ],
    "wof:name":"Nance's Floring",
    "wof:placetype":"venue"
},
  "geometry": {"coordinates":[-81.930037,28.049154],"type":"Point"}
}