{
  "type": "Feature",
  "properties": {
    "iso:country":"US",
    "sg:address":"4230 Parkside Dr",
    "sg:city":"Orlando",
    "sg:classifiers":[
        {
            "category":"Professional",
            "subcategory":"Business Services",
            "type":"Services"
        }
    ],
    "sg:phone":"+1 407 812 9433",
    "sg:postcode":"32812",
    "sg:province":"FL",
    "sg:tags":[
        "water",
        "treatment"
    ],
    "wof:name":"Classicasa",
    "wof:placetype":"venue"
},
  "geometry": {"coordinates":[-81.33241200000001,28.499315],"type":"Point"}
}