{
  "type": "Feature",
  "properties": {
    "iso:country":"US",
    "sg:address":"25227 State Rd 54",
    "sg:city":"Lutz",
    "sg:classifiers":[
        {
            "category":"Retail",
            "subcategory":"Animal Services",
            "type":"Services"
        }
    ],
    "sg:phone":"+1 813 909 2020",
    "sg:postcode":"33559",
    "sg:province":"FL",
    "sg:tags":[
        "pet",
        "grooming",
        "washing"
    ],
    "wof:name":"Picture Perfect Dog Grooming",
    "wof:placetype":"venue"
},
  "geometry": {"coordinates":[-82.399157,28.198592],"type":"Point"}
}