{
  "type": "Feature",
  "properties": {
    "addr:full":"3939 Hollywood Blvd Hollywood FL 33021",
    "addr:housenumber":"3939",
    "addr:postcode":"33021",
    "addr:street":"Hollywood Blvd",
    "iso:country":"US",
    "sg:address":"3939 Hollywood Blvd",
    "sg:city":"Hollywood",
    "sg:classifiers":[
        {
            "category":"Health Services",
            "subcategory":"Doctor",
            "type":"Services"
        }
    ],
    "sg:phone":"+1 954 961 7700",
    "sg:postcode":"33021",
    "sg:province":"FL",
    "sg:tags":[
        "physician"
    ],
    "wof:name":"Joel L Martin MD",
    "wof:placetype":"venue"
},
  "geometry": {"coordinates":[-80.18293300000001,26.011629],"type":"Point"}
}