{
  "type": "Feature",
  "properties": {
    "addr:full":"1155 W State Road 434 Longwood FL 32750",
    "addr:housenumber":"1155",
    "addr:postcode":"32750",
    "addr:street":"W State Road 434",
    "iso:country":"US",
    "sg:address":"1155 W State Road 434",
    "sg:city":"Longwood",
    "sg:classifiers":[
        {
            "category":"Restaurant",
            "type":"Food & Drink"
        }
    ],
    "sg:menulink":"http://www.allmenus.com/fl/casselberry-altamonte-springs/37605-ali-baba/menu/",
    "sg:phone":"+1 407 331 8680",
    "sg:postcode":"32750",
    "sg:province":"FL",
    "sg:tags":[
        "indian",
        "asian"
    ],
    "wof:name":"Ali Baba",
    "wof:placetype":"venue"
},
  "geometry": {"coordinates":[-81.36508600000001,28.697931],"type":"Point"}
}