{
  "type": "Feature",
  "properties": {
    "iso:country":"US",
    "sg:address":"4407 Grand Blvd",
    "sg:city":"New Port Richey",
    "sg:classifiers":[
        {
            "category":"Retail",
            "subcategory":"Auto Repair",
            "type":"Services"
        }
    ],
    "sg:phone":"+1 727 815 9905",
    "sg:postcode":"34652",
    "sg:province":"FL",
    "sg:tags":[
        "repairing",
        "automobile",
        "general"
    ],
    "wof:name":"Custom 4 Wheel Drive Inc",
    "wof:placetype":"venue"
},
  "geometry": {"coordinates":[-82.722964,28.223369],"type":"Point"}
}