{
  "type": "Feature",
  "properties": {
    "iso:country":"US",
    "sg:address":"1914 Calumet St",
    "sg:city":"Clearwater",
    "sg:classifiers":[
        {
            "category":"Shopping",
            "subcategory":"Bicycles & Sporting Goods",
            "type":"Retail Goods"
        }
    ],
    "sg:phone":"+1 727 445 9726",
    "sg:postcode":"33765",
    "sg:province":"FL",
    "sg:tags":[
        "tent"
    ],
    "sg:website":"www.srtproducts.com",
    "wof:name":"SRT Products",
    "wof:placetype":"venue"
},
  "geometry": {"coordinates":[-82.754859,27.985902],"type":"Point"}
}