{
  "type": "Feature",
  "properties": {
    "addr:full":"6453 109th Ter Pinellas Park FL 33782",
    "addr:housenumber":"6453",
    "addr:postcode":"33782",
    "addr:street":"109Th Ter;Park",
    "iso:country":"US",
    "sg:address":"6453 109th Ter",
    "sg:city":"Pinellas Park",
    "sg:classifiers":[
        {
            "category":"Building & Trades",
            "subcategory":"Construction",
            "type":"Services"
        }
    ],
    "sg:phone":"+1 727 547 8950",
    "sg:postcode":"33782",
    "sg:province":"FL",
    "sg:tags":[
        "contractor"
    ],
    "wof:name":"Kobra Enterprises Inc",
    "wof:placetype":"venue"
},
  "geometry": {"coordinates":[-82.72461199999999,27.871637],"type":"Point"}
}