{
  "type": "Feature",
  "properties": {
    "addr:full":"321 E Highbanks Rd Debary FL 32713",
    "addr:housenumber":"321",
    "addr:postcode":"32713",
    "addr:street":"E Highbanks Rd",
    "iso:country":"US",
    "sg:address":"321 E Highbanks Rd",
    "sg:city":"Debary",
    "sg:classifiers":[
        {
            "category":"Retail",
            "subcategory":"Auto Repair",
            "type":"Services"
        }
    ],
    "sg:phone":"+1 386 668 6677",
    "sg:postcode":"32713",
    "sg:province":"FL",
    "sg:tags":[
        "body",
        "shop"
    ],
    "wof:name":"Oc Collision Center",
    "wof:placetype":"venue"
},
  "geometry": {"coordinates":[-81.285202,28.890499],"type":"Point"}
}