{
  "type": "Feature",
  "properties": {
    "iso:country":"US",
    "sg:address":"8100 E Broadway Ave",
    "sg:city":"Tampa",
    "sg:classifiers":[
        {
            "category":"Building & Trades",
            "subcategory":"Construction",
            "type":"Services"
        }
    ],
    "sg:phone":"+1 813 623 6835",
    "sg:postcode":"33619",
    "sg:province":"FL",
    "sg:tags":[
        "sheet",
        "work",
        "metal",
        "heating",
        "air",
        "combined"
    ],
    "wof:name":"M C S",
    "wof:placetype":"venue"
},
  "geometry": {"coordinates":[-82.360383,27.967692],"type":"Point"}
}