{
  "type": "Feature",
  "properties": {
    "addr:full":"2870 Raintree Lake Cir Merritt Island FL 32953",
    "addr:housenumber":"2870",
    "addr:postcode":"32953",
    "addr:street":"Raintree Lake Cir",
    "iso:country":"US",
    "sg:address":"2870 Raintree Lake Cir",
    "sg:city":"Merritt Island",
    "sg:classifiers":[
        {
            "category":"Retail",
            "subcategory":"Portrait Studio",
            "type":"Services"
        }
    ],
    "sg:phone":"+1 321 453 6446",
    "sg:postcode":"32953",
    "sg:province":"FL",
    "sg:tags":[
        "photographer"
    ],
    "wof:name":"Photography By Cheryl",
    "wof:placetype":"venue"
},
  "geometry": {"coordinates":[-80.700478,28.398594],"type":"Point"}
}