{
  "type": "Feature",
  "properties": {
    "addr:full":"1065 S Florida Ave Lakeland FL 33803",
    "addr:housenumber":"1065",
    "addr:postcode":"33803",
    "addr:street":"S Florida Ave",
    "iso:country":"US",
    "sg:address":"1065 S Florida Ave",
    "sg:city":"Lakeland",
    "sg:classifiers":[
        {
            "category":"Shopping",
            "type":"Retail Goods"
        }
    ],
    "sg:phone":"+1 863 683 0888",
    "sg:postcode":"33803",
    "sg:province":"FL",
    "sg:tags":[
        "picture",
        "frame",
        "merchandise",
        "repair"
    ],
    "wof:name":"Framing Master",
    "wof:placetype":"venue"
},
  "geometry": {"coordinates":[-81.95711799999999,28.029505],"type":"Point"}
}