{
  "type": "Feature",
  "properties": {
    "iso:country":"US",
    "sg:address":"10804 NW 58th St",
    "sg:city":"Miami",
    "sg:classifiers":[
        {
            "category":"Banks & Credit Unions",
            "subcategory":"Bank",
            "type":"Services"
        }
    ],
    "sg:phone":"+1 305 477 7768",
    "sg:postcode":"33178",
    "sg:province":"FL",
    "sg:tags":[
        "depository",
        "banking"
    ],
    "wof:name":"B G Envios Corp",
    "wof:placetype":"venue"
},
  "geometry": {"coordinates":[-80.366772,25.826281],"type":"Point"}
}