{
  "type": "Feature",
  "properties": {
    "iso:country":"US",
    "sg:address":"1529 Sunrise Plaza Dr",
    "sg:city":"Clermont",
    "sg:classifiers":[
        {
            "category":"Real Estate",
            "subcategory":"Real Estate Agent",
            "type":"Services"
        }
    ],
    "sg:phone":"+1 352 242 2024",
    "sg:postcode":"34711",
    "sg:province":"FL",
    "wof:name":"Britannia Properties Inc",
    "wof:placetype":"venue"
},
  "geometry": {"coordinates":[-81.68203200000001,28.370087],"type":"Point"}
}