{
  "type": "Feature",
  "properties": {
    "addr:full":"8563 Argyle Business Loop Jacksonville FL 32244",
    "addr:housenumber":"8563",
    "addr:postcode":"32244",
    "addr:street":"Argyle Business Loop",
    "iso:country":"US",
    "sg:address":"8563 Argyle Business Loop",
    "sg:city":"Jacksonville",
    "sg:classifiers":[
        {
            "category":"Shopping",
            "type":"Retail Goods"
        }
    ],
    "sg:phone":"+1 904 778 7458",
    "sg:postcode":"32244",
    "sg:province":"FL",
    "sg:tags":[
        "merchandise"
    ],
    "wof:name":"Advantedge Medical Products",
    "wof:placetype":"venue"
},
  "geometry": {"coordinates":[-81.746493,30.190341],"type":"Point"}
}