{
  "type": "Feature",
  "properties": {
    "iso:country":"US",
    "sg:address":"2398 Fruitville Rd",
    "sg:city":"Sarasota",
    "sg:classifiers":[
        {
            "category":"Banks & Credit Unions",
            "subcategory":"Financial Services",
            "type":"Services"
        }
    ],
    "sg:phone":"+1 941 362 3800",
    "sg:postcode":"34237",
    "sg:province":"FL",
    "sg:tags":[
        "investor"
    ],
    "wof:name":"Southeast Capital Investors",
    "wof:placetype":"venue"
},
  "geometry": {"coordinates":[-82.523196,27.337518],"type":"Point"}
}