{
  "type": "Feature",
  "properties": {
    "addr:full":"1914 University Blvd W Jacksonville FL 32217",
    "addr:housenumber":"1914",
    "addr:postcode":"32217",
    "addr:street":"University Blvd W",
    "iso:country":"US",
    "sg:address":"1914 University Blvd W",
    "sg:city":"Jacksonville",
    "sg:classifiers":[
        {
            "category":"Professional",
            "type":"Services"
        },
        {
            "category":"Building & Trades",
            "subcategory":"Construction",
            "type":"Services"
        }
    ],
    "sg:phone":"+1 904 739 5642",
    "sg:postcode":"32217",
    "sg:province":"FL",
    "sg:tags":[
        "house",
        "establishment"
    ],
    "wof:name":"Smoky Mountain Dreams Inc",
    "wof:placetype":"venue"
},
  "geometry": {"coordinates":[-81.6369,30.260785],"type":"Point"}
}