{
  "type": "Feature",
  "properties": {
    "addr:full":"228 Harrison Ave Panama City FL 32401",
    "addr:housenumber":"228",
    "addr:postcode":"32401",
    "addr:street":"Harrison Ave",
    "iso:country":"US",
    "sg:address":"228 Harrison Ave",
    "sg:city":"Panama City",
    "sg:classifiers":[
        {
            "category":"Professional",
            "subcategory":"Research",
            "type":"Services"
        }
    ],
    "sg:phone":"+1 850 522 8005",
    "sg:postcode":"32401",
    "sg:province":"FL",
    "sg:tags":[
        "environmental",
        "ecological"
    ],
    "wof:name":"Integrated Science/Technology",
    "wof:placetype":"venue"
},
  "geometry": {"coordinates":[-85.66143599999999,30.154306],"type":"Point"}
}