{
  "type": "Feature",
  "properties": {
    "iso:country":"US",
    "sg:address":"3962 Mammoth Grove Rd",
    "sg:city":"Lake Wales",
    "sg:classifiers":[
        {
            "category":"Building & Trades",
            "subcategory":"Plumbing",
            "type":"Services"
        }
    ],
    "sg:phone":"+1 863 676 8955",
    "sg:postcode":"33898",
    "sg:province":"FL",
    "sg:tags":[
        "contractor"
    ],
    "wof:name":"Graces Rv & Air Conditioning",
    "wof:placetype":"venue"
},
  "geometry": {"coordinates":[-81.48424300000001,27.911268],"type":"Point"}
}