{
  "type": "Feature",
  "properties": {
    "addr:full":"316 Tavernier St Tavernier FL 33070",
    "addr:housenumber":"316",
    "addr:postcode":"33070",
    "addr:street":"Tavernier St",
    "iso:country":"US",
    "sg:address":"316 Tavernier St",
    "sg:city":"Tavernier",
    "sg:classifiers":[
        {
            "category":"Building & Trades",
            "subcategory":"Landscaping Services",
            "type":"Services"
        }
    ],
    "sg:phone":"+1 305 852 9746",
    "sg:postcode":"33070",
    "sg:province":"FL",
    "sg:tags":[
        "tree"
    ],
    "wof:name":"Florida Keys Tree Service",
    "wof:placetype":"venue"
},
  "geometry": {"coordinates":[-80.51902,25.008401],"type":"Point"}
}