{
  "type": "Feature",
  "properties": {
    "iso:country":"US",
    "sg:address":"1421 Jackson Ave",
    "sg:city":"Daytona Beach",
    "sg:classifiers":[
        {
            "category":"Social Services",
            "subcategory":"Child Care",
            "type":"Services"
        }
    ],
    "sg:phone":"+1 386 672 0464",
    "sg:postcode":"32117",
    "sg:province":"FL",
    "wof:name":"Westwood Heights Playschool",
    "wof:placetype":"venue"
},
  "geometry": {"coordinates":[-81.0737,29.246363],"type":"Point"}
}