{
  "type": "Feature",
  "properties": {
    "addr:full":"1027 5th Ave N Naples FL 34102",
    "addr:housenumber":"1027",
    "addr:postcode":"34102",
    "addr:street":"5Th Ave N",
    "iso:country":"US",
    "sg:address":"1027 5th Ave N",
    "sg:city":"Naples",
    "sg:classifiers":[
        {
            "category":"Real Estate",
            "subcategory":"Real Estate Agent",
            "type":"Services"
        }
    ],
    "sg:phone":"+1 239 434 0446",
    "sg:postcode":"34102",
    "sg:province":"FL",
    "wof:name":"S W Florida Realty Consultants",
    "wof:placetype":"venue"
},
  "geometry": {"coordinates":[-81.792542,26.153374],"type":"Point"}
}