{
  "type": "Feature",
  "properties": {
    "addr:full":"950 NE 171st St Apt 208 Miami FL 33162",
    "addr:housenumber":"950;208",
    "addr:postcode":"33162",
    "addr:street":"Ne 171St St Apt",
    "iso:country":"US",
    "sg:address":"950 NE 171st St Apt 208",
    "sg:city":"Miami",
    "sg:classifiers":[
        {
            "category":"Professional",
            "subcategory":"Detective & Security Services",
            "type":"Services"
        }
    ],
    "sg:phone":"+1 954 822 5416",
    "sg:postcode":"33162",
    "sg:province":"FL",
    "sg:tags":[
        "guard",
        "patrol"
    ],
    "wof:name":"Fire, Life Safety, & Security Institute, Inc.",
    "wof:placetype":"venue"
},
  "geometry": {"coordinates":[-80.18135599999999,25.932581],"type":"Point"}
}