{
  "type": "Feature",
  "properties": {
    "iso:country":"US",
    "sg:address":"100 Miracle Mile",
    "sg:city":"Miami",
    "sg:classifiers":[
        {
            "category":"Banks & Credit Unions",
            "subcategory":"Bank",
            "type":"Services"
        }
    ],
    "sg:phone":"+1 305 442 3102",
    "sg:postcode":"33134",
    "sg:province":"FL",
    "sg:website":"www.suntrust.com",
    "wof:name":"Suntrust",
    "wof:placetype":"venue"
},
  "geometry": {"coordinates":[-80.256699,25.749599],"type":"Point"}
}