{
  "type": "Feature",
  "properties": {
    "addr:full":"2044 Lake Shore Blvd Jacksonville FL 32210",
    "addr:housenumber":"2044",
    "addr:postcode":"32210",
    "addr:street":"Lake Shore Blvd",
    "iso:country":"US",
    "sg:address":"2044 Lake Shore Blvd",
    "sg:city":"Jacksonville",
    "sg:classifiers":[
        {
            "category":"Marine",
            "type":"Transportation"
        },
        {
            "category":"Autos & Motor Vehicles",
            "subcategory":"Fuel & Gas Station",
            "type":"Retail Goods"
        }
    ],
    "sg:phone":"+1 904 981 0085",
    "sg:postcode":"32210",
    "sg:province":"FL",
    "sg:tags":[
        "gasoline",
        "station",
        "towing"
    ],
    "wof:name":"Steven Schoolcraft Marine Svc",
    "wof:placetype":"venue"
},
  "geometry": {"coordinates":[-81.738219,30.281833],"type":"Point"}
}