{
  "type": "Feature",
  "properties": {
    "addr:full":"2074 Cascades Cove Dr Orlando FL 32820",
    "addr:housenumber":"2074",
    "addr:postcode":"32820",
    "addr:street":"Cascades Cove Dr",
    "iso:country":"US",
    "sg:address":"2074 Cascades Cove Dr",
    "sg:city":"Orlando",
    "sg:classifiers":[
        {
            "category":"Health Services",
            "subcategory":"Clinic",
            "type":"Services"
        }
    ],
    "sg:phone":"+1 407 568 0869",
    "sg:postcode":"32820",
    "sg:province":"FL",
    "sg:tags":[
        "welfare"
    ],
    "wof:name":"Central Florida Medical Massage Inc",
    "wof:placetype":"venue"
},
  "geometry": {"coordinates":[-81.124343,28.570878],"type":"Point"}
}