{
  "type": "Feature",
  "properties": {
    "addr:full":"2331 Sydney Dover Rd Dover FL 33527",
    "addr:housenumber":"2331",
    "addr:postcode":"33527",
    "addr:street":"Sydney Dover Rd",
    "iso:country":"US",
    "sg:address":"2331 Sydney Dover Rd",
    "sg:city":"Dover",
    "sg:classifiers":[
        {
            "category":"Professional",
            "subcategory":"Business Services",
            "type":"Services"
        }
    ],
    "sg:phone":"+1 813 759 2555",
    "sg:postcode":"33527",
    "sg:province":"FL",
    "wof:name":"K&J Solutions Inc",
    "wof:placetype":"venue"
},
  "geometry": {"coordinates":[-82.207207,27.970552],"type":"Point"}
}