{
  "type": "Feature",
  "properties": {
    "iso:country":"US",
    "sg:address":"1011 S Yachtsman Dr",
    "sg:city":"Sanibel",
    "sg:classifiers":[
        {
            "category":"Shopping",
            "subcategory":"Gifts & Souvenirs",
            "type":"Retail Goods"
        }
    ],
    "sg:phone":"+1 239 472 6155",
    "sg:postcode":"33957",
    "sg:province":"FL",
    "wof:name":"Leonardi Peter & Karin",
    "wof:placetype":"venue"
},
  "geometry": {"coordinates":[-82.029741,26.446535],"type":"Point"}
}