{
  "type": "Feature",
  "properties": {
    "iso:country":"US",
    "sg:address":"40950 US-19 N",
    "sg:city":"Tarpon Springs",
    "sg:classifiers":[
        {
            "category":"Restaurant",
            "type":"Food & Drink"
        }
    ],
    "sg:menulink":"http://www.allmenus.com/fl/tarpon-springs/34316-papa-johns-pizza/menu/",
    "sg:phone":"+1 727 943 7272",
    "sg:postcode":"34689",
    "sg:province":"FL",
    "sg:tags":[
        "american",
        "pizza"
    ],
    "wof:name":"Papa John's Pizza",
    "wof:placetype":"venue"
},
  "geometry": {"coordinates":[-82.74045599999999,28.14468],"type":"Point"}
}