{
  "type": "Feature",
  "properties": {
    "addr:full":"1013 Dundee Rd Dundee FL 33838",
    "addr:housenumber":"1013",
    "addr:postcode":"33838",
    "addr:street":"Dundee Rd",
    "iso:country":"US",
    "sg:address":"1013 Dundee Rd",
    "sg:city":"Dundee",
    "sg:classifiers":[
        {
            "category":"Banks & Credit Unions",
            "subcategory":"Bank",
            "type":"Services"
        }
    ],
    "sg:phone":"+1 863 439 2946",
    "sg:postcode":"33838",
    "sg:province":"FL",
    "wof:name":"Citizens Bank & Trust",
    "wof:placetype":"venue"
},
  "geometry": {"coordinates":[-81.63562899999999,28.018533],"type":"Point"}
}