{
  "type": "Feature",
  "properties": {
    "iso:country":"US",
    "sg:address":"7328 Lake Worth Rd",
    "sg:city":"Lake Worth",
    "sg:classifiers":[
        {
            "category":"Building & Trades",
            "subcategory":"Construction",
            "type":"Services"
        }
    ],
    "sg:phone":"+1 561 304 4032",
    "sg:postcode":"33467",
    "sg:province":"FL",
    "sg:tags":[
        "painter"
    ],
    "wof:name":"All Brothers Painting Inc",
    "wof:placetype":"venue"
},
  "geometry": {"coordinates":[-80.16389599999999,26.617465],"type":"Point"}
}