{
  "type": "Feature",
  "properties": {
    "addr:full":"10871 Ulmerton Rd Largo FL 33778",
    "addr:housenumber":"10871",
    "addr:postcode":"33778",
    "addr:street":"Ulmerton Rd",
    "iso:country":"US",
    "sg:address":"10871 Ulmerton Rd",
    "sg:city":"Largo",
    "sg:classifiers":[
        {
            "category":"Personal",
            "subcategory":"Beauty Salon",
            "type":"Services"
        }
    ],
    "sg:phone":"+1 727 587 0028",
    "sg:postcode":"33778",
    "sg:province":"FL",
    "wof:name":"De-Ziners Full Svc Salon & Tan",
    "wof:placetype":"venue"
},
  "geometry": {"coordinates":[-82.79099100000001,27.894553],"type":"Point"}
}