{
  "type": "Feature",
  "properties": {
    "addr:full":"8760 Summerville Pl Orlando FL 32819",
    "addr:housenumber":"8760",
    "addr:postcode":"32819",
    "addr:street":"Summerville Pl",
    "iso:country":"US",
    "sg:address":"8760 Summerville Pl",
    "sg:city":"Orlando",
    "sg:classifiers":[
        {
            "category":"Building & Trades",
            "subcategory":"Landscaping Services",
            "type":"Services"
        },
        {
            "category":"Building & Trades",
            "subcategory":"Pest Control",
            "type":"Services"
        }
    ],
    "sg:phone":"+1 407 894 5662",
    "sg:postcode":"32819",
    "sg:province":"FL",
    "sg:tags":[
        "lawn",
        "maintenance"
    ],
    "sg:website":"http://www.scientificpestcontrol.net",
    "wof:name":"Scientific Pest Control & Termite Inc",
    "wof:placetype":"venue"
},
  "geometry": {"coordinates":[-81.50387499999999,28.485756],"type":"Point"}
}