{
  "type": "Feature",
  "properties": {
    "iso:country":"US",
    "sg:address":"4814 N Coolidge Ave",
    "sg:city":"Tampa",
    "sg:classifiers":[
        {
            "category":"Wholesale",
            "subcategory":"Machinery & Supplies",
            "type":"Manufacturing & Wholesale Goods"
        },
        {
            "category":"Manufacturing",
            "subcategory":"Tools & Machinery",
            "type":"Manufacturing & Wholesale Goods"
        }
    ],
    "sg:phone":"+1 813 873 1614",
    "sg:postcode":"33614",
    "sg:province":"FL",
    "sg:tags":[
        "lift",
        "marine",
        "boat"
    ],
    "sg:website":"www.floridaboatlifts.com",
    "wof:name":"Florida Boatlifts Inc",
    "wof:placetype":"venue"
},
  "geometry": {"coordinates":[-82.516732,27.991154],"type":"Point"}
}