{
  "type": "Feature",
  "properties": {
    "iso:country":"US",
    "sg:address":"8735 N 50th St",
    "sg:city":"Tampa",
    "sg:classifiers":[
        {
            "category":"Retail",
            "subcategory":"Auto Repair",
            "type":"Services"
        }
    ],
    "sg:phone":"+1 813 985 6204",
    "sg:postcode":"33617",
    "sg:province":"FL",
    "sg:tags":[
        "transmission",
        "automotive",
        "general"
    ],
    "wof:name":"Toyota Repair Toy House",
    "wof:placetype":"venue"
},
  "geometry": {"coordinates":[-82.401606,28.028844],"type":"Point"}
}