{
  "type": "Feature",
  "properties": {
    "iso:country":"US",
    "sg:address":"35 Golf View Dr",
    "sg:city":"Jupiter",
    "sg:classifiers":[
        {
            "category":"Real Estate",
            "subcategory":"Real Estate Agent",
            "type":"Services"
        }
    ],
    "sg:phone":"+1 561 746 0337",
    "sg:postcode":"33469",
    "sg:province":"FL",
    "wof:name":"United Costal Realty Inc",
    "wof:placetype":"venue"
},
  "geometry": {"coordinates":[-80.113472,26.958919],"type":"Point"}
}