{
  "type": "Feature",
  "properties": {
    "iso:country":"US",
    "sg:address":"1111 96th St",
    "sg:city":"Bay Harbor Isles",
    "sg:classifiers":[
        {
            "category":"Professional",
            "subcategory":"Accounting & Tax Preparation",
            "type":"Services"
        }
    ],
    "sg:phone":"+1 305 864 7888",
    "sg:postcode":"33154",
    "sg:province":"FL",
    "sg:tags":[
        "accountant"
    ],
    "wof:name":"Isaac Salver CPA",
    "wof:placetype":"venue"
},
  "geometry": {"coordinates":[-80.133073,25.886755],"type":"Point"}
}