{
  "type": "Feature",
  "properties": {
    "iso:country":"US",
    "sg:address":"1310 NW 23 Ave",
    "sg:city":"Gainesville",
    "sg:classifiers":[
        {
            "category":"Cinema",
            "subcategory":"Movie Rental",
            "type":"Entertainment"
        }
    ],
    "sg:phone":"+1 352 377 6322",
    "sg:postcode":"32609",
    "sg:province":"FL",
    "sg:tags":[
        "video"
    ],
    "wof:name":"Blockbuster",
    "wof:placetype":"venue"
},
  "geometry": {"coordinates":[-82.343101,29.674077],"type":"Point"}
}