{
  "type": "Feature",
  "properties": {
    "addr:full":"1414 NW 107th Ave Doral FL 33172",
    "addr:housenumber":"1414",
    "addr:postcode":"33172",
    "addr:street":"Nw 107Th Ave",
    "iso:country":"US",
    "sg:address":"1414 NW 107th Ave",
    "sg:city":"Doral",
    "sg:classifiers":[
        {
            "category":"Banks & Credit Unions",
            "subcategory":"Bank",
            "type":"Services"
        }
    ],
    "sg:phone":"+1 305 513 4610",
    "sg:postcode":"33172",
    "sg:province":"FL",
    "sg:tags":[
        "loan",
        "real estate"
    ],
    "sg:website":"www.qualimae.com",
    "wof:name":"Qualimae Corp",
    "wof:placetype":"venue"
},
  "geometry": {"coordinates":[-80.368842,25.786796],"type":"Point"}
}