{
  "type": "Feature",
  "properties": {
    "addr:full":"140 Wekiva Springs Rd Longwood FL 32779",
    "addr:housenumber":"140",
    "addr:postcode":"32779",
    "addr:street":"Wekiva Springs Rd",
    "iso:country":"US",
    "sg:address":"140 Wekiva Springs Rd",
    "sg:city":"Longwood",
    "sg:classifiers":[
        {
            "category":"Banks & Credit Unions",
            "subcategory":"Bank",
            "type":"Services"
        }
    ],
    "sg:phone":"+1 407 788 4100",
    "sg:postcode":"32779",
    "sg:province":"FL",
    "sg:tags":[
        "diverse",
        "financial"
    ],
    "wof:name":"GE",
    "wof:placetype":"venue"
},
  "geometry": {"coordinates":[-81.405218,28.689553],"type":"Point"}
}