{
  "type": "Feature",
  "properties": {
    "addr:full":"17200 SW 248th St Homestead FL 33031",
    "addr:housenumber":"17200",
    "addr:postcode":"33031",
    "addr:street":"Sw 248Th St",
    "iso:country":"US",
    "sg:address":"17200 SW 248th St",
    "sg:city":"Homestead",
    "sg:classifiers":[
        {
            "category":"Wholesale",
            "subcategory":"Plants",
            "type":"Manufacturing & Wholesale Goods"
        }
    ],
    "sg:phone":"+1 305 245 0828",
    "sg:postcode":"33031",
    "sg:province":"FL",
    "sg:tags":[
        "nursery",
        "tree"
    ],
    "sg:website":"www.superior-foliage.com",
    "wof:name":"Superior Foliage Inc",
    "wof:placetype":"venue"
},
  "geometry": {"coordinates":[-80.462219,25.535876],"type":"Point"}
}