{
  "type": "Feature",
  "properties": {
    "addr:full":"1210 Pasadena Ave S Saint Petersburg FL 33707",
    "addr:housenumber":"1210",
    "addr:postcode":"33707",
    "addr:street":"Pasadena Ave S",
    "iso:country":"US",
    "sg:address":"1210 Pasadena Ave S",
    "sg:city":"Saint Petersburg",
    "sg:classifiers":[
        {
            "category":"Food & Beverages",
            "subcategory":"Specialty",
            "type":"Retail Goods"
        }
    ],
    "sg:phone":"+1 727 345 5548",
    "sg:postcode":"33707",
    "sg:province":"FL",
    "wof:name":"Health Food Herbs & Vitamins",
    "wof:placetype":"venue"
},
  "geometry": {"coordinates":[-82.73636999999999,27.758166],"type":"Point"}
}