{
  "type": "Feature",
  "properties": {
    "iso:country":"US",
    "sg:address":"30627 Round Lake Rd",
    "sg:city":"Mount Dora",
    "sg:classifiers":[
        {
            "category":"Wholesale",
            "subcategory":"Plants",
            "type":"Manufacturing & Wholesale Goods"
        }
    ],
    "sg:phone":"+1 352 383 4228",
    "sg:postcode":"32757",
    "sg:province":"FL",
    "sg:tags":[
        "supply"
    ],
    "wof:name":"Red Lion Nursery",
    "wof:placetype":"venue"
},
  "geometry": {"coordinates":[-81.592888,28.794543],"type":"Point"}
}