{
  "type": "Feature",
  "properties": {
    "addr:full":"2976 8th St SW Miami FL 33135",
    "addr:housenumber":"2976",
    "addr:postcode":"33135",
    "addr:street":"8Th St Sw",
    "iso:country":"US",
    "sg:address":"2976 8th St SW",
    "sg:city":"Miami",
    "sg:classifiers":[
        {
            "category":"Restaurant",
            "type":"Food & Drink"
        }
    ],
    "sg:phone":"+1 305 642 5089",
    "sg:postcode":"33135",
    "sg:province":"FL",
    "wof:name":"Martin Fierro Restaurant",
    "wof:placetype":"venue"
},
  "geometry": {"coordinates":[-80.24283200000001,25.764983],"type":"Point"}
}