{
  "type": "Feature",
  "properties": {
    "iso:country":"US",
    "sg:address":"1691 Michigan Ave Ste 210",
    "sg:city":"Miami Beach",
    "sg:classifiers":[
        {
            "category":"Real Estate",
            "subcategory":"Real Estate Services",
            "type":"Services"
        }
    ],
    "sg:phone":"+1 305 695 6300",
    "sg:postcode":"33139",
    "sg:province":"FL",
    "sg:website":"ellimanflorida.com",
    "wof:name":"Douglas Elliman Florida",
    "wof:placetype":"venue"
},
  "geometry": {"coordinates":[-80.138808,25.791711],"type":"Point"}
}