{
  "type": "Feature",
  "properties": {
    "addr:full":"1833 Shore Acres Blvd NE Saint Petersburg FL 33703",
    "addr:housenumber":"1833",
    "addr:postcode":"33703",
    "addr:street":"Shore Acres Blvd Ne",
    "iso:country":"US",
    "sg:address":"1833 Shore Acres Blvd NE",
    "sg:city":"Saint Petersburg",
    "sg:classifiers":[
        {
            "category":"Building & Trades",
            "subcategory":"Construction",
            "type":"Services"
        }
    ],
    "sg:phone":"+1 727 526 2446",
    "sg:postcode":"33703",
    "sg:province":"FL",
    "sg:tags":[
        "residential"
    ],
    "wof:name":"Joseph E Hood Inc",
    "wof:placetype":"venue"
},
  "geometry": {"coordinates":[-82.602388,27.819453],"type":"Point"}
}