{
  "type": "Feature",
  "properties": {
    "addr:full":"5820 S Macdill Ave Tampa FL 33611",
    "addr:housenumber":"5820",
    "addr:postcode":"33611",
    "addr:street":"S Macdill Ave",
    "iso:country":"US",
    "sg:address":"5820 S Macdill Ave",
    "sg:city":"Tampa",
    "sg:classifiers":[
        {
            "category":"Personal",
            "subcategory":"Beauty Salon",
            "type":"Services"
        }
    ],
    "sg:phone":"+1 813 902 1904",
    "sg:postcode":"33611",
    "sg:province":"FL",
    "sg:tags":[
        "spa",
        "day"
    ],
    "sg:website":"www.awaspa.com",
    "wof:name":"Awa A Spa & Wellness Sanctuary",
    "wof:placetype":"venue"
},
  "geometry": {"coordinates":[-82.49391300000001,27.880642],"type":"Point"}
}