{
  "type": "Feature",
  "properties": {
    "iso:country":"US",
    "sg:address":"310 W 56th St",
    "sg:city":"Hialeah",
    "sg:classifiers":[
        {
            "category":"Professional",
            "type":"Services"
        }
    ],
    "sg:phone":"+1 305 828 9286",
    "sg:postcode":"33012",
    "sg:province":"FL",
    "wof:name":"Radamanto Corp",
    "wof:placetype":"venue"
},
  "geometry": {"coordinates":[-80.289714,25.873128],"type":"Point"}
}