{
  "type": "Feature",
  "properties": {
    "addr:full":"909 Tamiami Trl Nokomis FL 34275",
    "addr:housenumber":"909",
    "addr:postcode":"34275",
    "addr:street":"Tamiami Trl",
    "iso:country":"US",
    "sg:address":"909 Tamiami Trl",
    "sg:city":"Nokomis",
    "sg:classifiers":[
        {
            "category":"Health Services",
            "subcategory":"Health Practitioner",
            "type":"Services"
        }
    ],
    "sg:phone":"+1 941 480 1897",
    "sg:postcode":"34275",
    "sg:province":"FL",
    "sg:tags":[
        "psychotherapist"
    ],
    "wof:name":"Anne Olshansky",
    "wof:placetype":"venue"
},
  "geometry": {"coordinates":[-82.44876600000001,27.115206],"type":"Point"}
}