{
  "type": "Feature",
  "properties": {
    "addr:full":"307 W Parker Ave Bushnell FL 33513",
    "addr:housenumber":"307",
    "addr:postcode":"33513",
    "addr:street":"W Parker Ave",
    "iso:country":"US",
    "sg:address":"307 W Parker Ave",
    "sg:city":"Bushnell",
    "sg:classifiers":[
        {
            "category":"Wholesale",
            "subcategory":"Non-durable Goods",
            "type":"Manufacturing & Wholesale Goods"
        }
    ],
    "sg:phone":"+1 352 279 6914",
    "sg:postcode":"33513",
    "sg:province":"FL",
    "sg:tags":[
        "dry",
        "goods-wholesale"
    ],
    "wof:name":"Spe Tactical Supply",
    "wof:placetype":"venue"
},
  "geometry": {"coordinates":[-82.116214,28.669461],"type":"Point"}
}