{
  "type": "Feature",
  "properties": {
    "addr:full":"8650 Shenna Ct Orlando FL 32818",
    "addr:housenumber":"8650",
    "addr:postcode":"32818",
    "addr:street":"Shenna Ct",
    "iso:country":"US",
    "sg:address":"8650 Shenna Ct",
    "sg:city":"Orlando",
    "sg:classifiers":[
        {
            "category":"Utilities",
            "subcategory":"Refuse",
            "type":"Services"
        }
    ],
    "sg:phone":"+1 407 293 7554",
    "sg:postcode":"32818",
    "sg:province":"FL",
    "sg:tags":[
        "garbage",
        "collection"
    ],
    "wof:name":"Solan Trucking & Excavating",
    "wof:placetype":"venue"
},
  "geometry": {"coordinates":[-81.504396,28.565179],"type":"Point"}
}