{
  "type": "Feature",
  "properties": {
    "iso:country":"US",
    "sg:address":"10544 NW 26th St",
    "sg:city":"Doral",
    "sg:classifiers":[
        {
            "category":"Professional",
            "subcategory":"Business Services",
            "type":"Services"
        }
    ],
    "sg:phone":"+1 305 471 0202",
    "sg:postcode":"33172",
    "sg:province":"FL",
    "sg:tags":[
        "information",
        "bureau",
        "convention"
    ],
    "wof:name":"Puerto Rico Convention Bureau",
    "wof:placetype":"venue"
},
  "geometry": {"coordinates":[-80.367006,25.798019],"type":"Point"}
}