{
  "type": "Feature",
  "properties": {
    "iso:country":"US",
    "sg:address":"351 N State Rd 434",
    "sg:city":"Altamonte Spgs",
    "sg:classifiers":[
        {
            "category":"Professional",
            "subcategory":"Business Services",
            "type":"Services"
        },
        {
            "category":"Home & Garden",
            "subcategory":"Furniture",
            "type":"Retail Goods"
        }
    ],
    "sg:phone":"+1 407 682 3700",
    "sg:postcode":"32714",
    "sg:province":"FL",
    "sg:tags":[
        "interior",
        "consultant",
        "design",
        "decorator"
    ],
    "wof:name":"Robb & Stucky Fine Furniture",
    "wof:placetype":"venue"
},
  "geometry": {"coordinates":[-81.419,28.671569],"type":"Point"}
}