{
  "type": "Feature",
  "properties": {
    "addr:full":"38 N Hiawassee Rd Orlando FL 32835",
    "addr:housenumber":"38",
    "addr:postcode":"32835",
    "addr:street":"N Hiawassee Rd",
    "iso:country":"US",
    "sg:address":"38 N Hiawassee Rd",
    "sg:city":"Orlando",
    "sg:classifiers":[
        {
            "category":"Real Estate",
            "subcategory":"Real Estate Operator",
            "type":"Services"
        }
    ],
    "sg:phone":"+1 407 299 2477",
    "sg:postcode":"32835",
    "sg:province":"FL",
    "sg:tags":[
        "apartment"
    ],
    "wof:name":"South Hiawassee Village",
    "wof:placetype":"venue"
},
  "geometry": {"coordinates":[-81.47586699999999,28.541674],"type":"Point"}
}