{
  "type": "Feature",
  "properties": {
    "addr:full":"5100 Cranes Point Ct Orlando FL 32839",
    "addr:housenumber":"5100",
    "addr:postcode":"32839",
    "addr:street":"Cranes Point Ct",
    "iso:country":"US",
    "sg:address":"5100 Cranes Point Ct",
    "sg:city":"Orlando",
    "sg:classifiers":[
        {
            "category":"Professional",
            "subcategory":"Management & Consulting",
            "type":"Services"
        }
    ],
    "sg:phone":"+1 407 850 2221",
    "sg:postcode":"32839",
    "sg:province":"FL",
    "sg:tags":[
        "marketing",
        "consultant"
    ],
    "sg:website":"www.predatory.com",
    "wof:name":"America's Research Group",
    "wof:placetype":"venue"
},
  "geometry": {"coordinates":[-81.383145,28.486445],"type":"Point"}
}