{
  "type": "Feature",
  "properties": {
    "addr:full":"5498 Central Florida Pkwy Orlando FL 32821",
    "addr:housenumber":"5498",
    "addr:postcode":"32821",
    "addr:street":"Central Florida Pkwy",
    "iso:country":"US",
    "sg:address":"5498 Central Florida Pkwy",
    "sg:city":"Orlando",
    "sg:classifiers":[
        {
            "category":"Fast Food",
            "type":"Food & Drink"
        },
        {
            "category":"Restaurant",
            "type":"Food & Drink"
        }
    ],
    "sg:phone":"+1 407 238 0995",
    "sg:postcode":"32821",
    "sg:province":"FL",
    "sg:tags":[
        "hamburger",
        "hot",
        "dog",
        "american",
        "take",
        "chicken"
    ],
    "sg:website":"http://www.mcdonalds.com",
    "wof:name":"McDonald's",
    "wof:placetype":"venue"
},
  "geometry": {"coordinates":[-81.450737,28.40773],"type":"Point"}
}