{
  "type": "Feature",
  "properties": {
    "addr:full":"9304 NE 5th Ave Miami FL 33138",
    "addr:housenumber":"9304",
    "addr:postcode":"33138",
    "addr:street":"Ne 5Th Ave",
    "iso:country":"US",
    "sg:address":"9304 NE 5th Ave",
    "sg:city":"Miami",
    "sg:classifiers":[
        {
            "category":"Building & Trades",
            "subcategory":"Construction",
            "type":"Services"
        }
    ],
    "sg:phone":"+1 305 751 9950",
    "sg:postcode":"33138",
    "sg:province":"FL",
    "sg:tags":[
        "industrial"
    ],
    "wof:name":"Associated Concrete Industries",
    "wof:placetype":"venue"
},
  "geometry": {"coordinates":[-80.18730100000001,25.861656],"type":"Point"}
}