{
  "type": "Feature",
  "properties": {
    "iso:country":"US",
    "sg:address":"1400 E Las Olas Blvd",
    "sg:city":"Fort Lauderdale",
    "sg:classifiers":[
        {
            "category":"Personal",
            "subcategory":"Barber",
            "type":"Services"
        }
    ],
    "sg:phone":"+1 954 462 1351",
    "sg:postcode":"33301",
    "sg:province":"FL",
    "sg:tags":[
        "shop"
    ],
    "wof:name":"Las Olas Barber Shop Inc",
    "wof:placetype":"venue"
},
  "geometry": {"coordinates":[-80.129334,26.119306],"type":"Point"}
}