{
  "type": "Feature",
  "properties": {
    "iso:country":"US",
    "sg:address":"640 Glenview Blvd",
    "sg:city":"Daytona Beach",
    "sg:classifiers":[
        {
            "category":"Wholesale",
            "subcategory":"Apparel",
            "type":"Manufacturing & Wholesale Goods"
        }
    ],
    "sg:phone":"+1 386 248 3151",
    "sg:postcode":"32118",
    "sg:province":"FL",
    "sg:tags":[
        "wear"
    ],
    "wof:name":"Munchkin Mania",
    "wof:placetype":"venue"
},
  "geometry": {"coordinates":[-81.013623,29.237006],"type":"Point"}
}