{
  "type": "Feature",
  "properties": {
    "addr:full":"2119 W Beaver St Jacksonville FL 32209",
    "addr:housenumber":"2119",
    "addr:postcode":"32209",
    "addr:street":"W Beaver St",
    "iso:country":"US",
    "sg:address":"2119 W Beaver St",
    "sg:city":"Jacksonville",
    "sg:classifiers":[
        {
            "category":"Retail",
            "subcategory":"Repair Shop",
            "type":"Services"
        }
    ],
    "sg:phone":"+1 904 356 8819",
    "sg:postcode":"32209",
    "sg:province":"FL",
    "sg:tags":[
        "refrigeration"
    ],
    "wof:name":"Dans Air Conditioning",
    "wof:placetype":"venue"
},
  "geometry": {"coordinates":[-81.695097,30.333536],"type":"Point"}
}