{
  "type": "Feature",
  "properties": {
    "addr:full":"7566 Sun Tree Cir Orlando FL 32807",
    "addr:housenumber":"7566",
    "addr:postcode":"32807",
    "addr:street":"Sun Tree Cir",
    "iso:country":"US",
    "sg:address":"7566 Sun Tree Cir",
    "sg:city":"Orlando",
    "sg:classifiers":[
        {
            "category":"Arts & Performance",
            "subcategory":"Theater",
            "type":"Entertainment"
        }
    ],
    "sg:phone":"+1 407 208 9965",
    "sg:postcode":"32807",
    "sg:province":"FL",
    "sg:tags":[
        "theatrical"
    ],
    "wof:name":"Ej Entertainment",
    "wof:placetype":"venue"
},
  "geometry": {"coordinates":[-81.28801199999999,28.556607],"type":"Point"}
}