{
  "type": "Feature",
  "properties": {
    "iso:country":"US",
    "sg:address":"15900 W Park Ln",
    "sg:city":"Fort Pierce",
    "sg:classifiers":[
        {
            "category":"Building & Trades",
            "subcategory":"Construction",
            "type":"Services"
        }
    ],
    "sg:phone":"+1 772 489 8333",
    "sg:postcode":"34945",
    "sg:province":"FL",
    "sg:tags":[
        "general",
        "contractor"
    ],
    "wof:name":"W Jackson & Sons Construction",
    "wof:placetype":"venue"
},
  "geometry": {"coordinates":[-80.39327,27.432399],"type":"Point"}
}