{
  "type": "Feature",
  "properties": {
    "addr:full":"2500 W Lake Mary Blvd Ste 217 Lake Mary FL 32746",
    "addr:housenumber":"2500",
    "addr:postcode":"32746",
    "addr:street":"W Lake Mary Blvd Ste 217;Mary",
    "iso:country":"US",
    "sg:address":"2500 W Lake Mary Blvd Ste 217",
    "sg:city":"Lake Mary",
    "sg:classifiers":[
        {
            "category":"Health Services",
            "subcategory":"Doctor",
            "type":"Services"
        }
    ],
    "sg:phone":"+1 407 323 0064",
    "sg:postcode":"32746",
    "sg:province":"FL",
    "sg:tags":[
        "orthopedist"
    ],
    "wof:name":"Florida Orthopaedic Associates PA",
    "wof:placetype":"venue"
},
  "geometry": {"coordinates":[-81.32411,28.756537],"type":"Point"}
}