{
  "type": "Feature",
  "properties": {
    "addr:full":"10544 Skewlee Rd Thonotosassa FL 33592",
    "addr:housenumber":"10544",
    "addr:postcode":"33592",
    "addr:street":"Skewlee Rd",
    "iso:country":"US",
    "sg:address":"10544 Skewlee Rd",
    "sg:city":"Thonotosassa",
    "sg:classifiers":[
        {
            "category":"Building & Trades",
            "subcategory":"Construction",
            "type":"Services"
        }
    ],
    "sg:phone":"+1 813 655 8194",
    "sg:postcode":"33592",
    "sg:province":"FL",
    "sg:tags":[
        "floor",
        "installation",
        "contractor"
    ],
    "wof:name":"21st Century Hardwood Floors",
    "wof:placetype":"venue"
},
  "geometry": {"coordinates":[-82.301967,28.050797],"type":"Point"}
}