{
  "type": "Feature",
  "properties": {
    "addr:full":"85 Gulfstream Rd Dania FL 33004",
    "addr:housenumber":"85",
    "addr:postcode":"33004",
    "addr:street":"Gulfstream Rd",
    "iso:country":"US",
    "sg:address":"85 Gulfstream Rd",
    "sg:city":"Dania",
    "sg:classifiers":[
        {
            "category":"Manufacturing",
            "subcategory":"Apparel",
            "type":"Manufacturing & Wholesale Goods"
        },
        {
            "category":"Farming",
            "subcategory":"Fish & Marine Products",
            "type":"Manufacturing & Wholesale Goods"
        }
    ],
    "sg:phone":"+1 954 926 5538",
    "sg:postcode":"33004",
    "sg:province":"FL",
    "sg:tags":[
        "catching"
    ],
    "wof:name":"Atlas Marine Inc",
    "wof:placetype":"venue"
},
  "geometry": {"coordinates":[-80.13131199999999,26.052996],"type":"Point"}
}