{
  "type": "Feature",
  "properties": {
    "iso:country":"US",
    "sg:address":"59 NW 45th Ave",
    "sg:city":"Deerfield Beach",
    "sg:classifiers":[
        {
            "category":"Building & Trades",
            "subcategory":"Cleaning & Sanitation",
            "type":"Services"
        }
    ],
    "sg:phone":"+1 954 263 4867",
    "sg:postcode":"33442",
    "sg:province":"FL",
    "sg:tags":[
        "butler",
        "maid"
    ],
    "wof:name":"All USA Quality Maintenance",
    "wof:placetype":"venue"
},
  "geometry": {"coordinates":[-80.16592300000001,26.318409],"type":"Point"}
}