{
  "type": "Feature",
  "properties": {
    "iso:country":"US",
    "sg:address":"770 21st St NW",
    "sg:city":"Naples",
    "sg:classifiers":[
        {
            "category":"Building & Trades",
            "subcategory":"Construction",
            "type":"Services"
        }
    ],
    "sg:phone":"+1 239 353 9635",
    "sg:postcode":"34120",
    "sg:province":"FL",
    "sg:tags":[
        "carpenter"
    ],
    "wof:name":"Parent Co Framing Contractors",
    "wof:placetype":"venue"
},
  "geometry": {"coordinates":[-81.64900900000001,26.231587],"type":"Point"}
}