{
  "type": "Feature",
  "properties": {
    "addr:full":"181 Normandy Rd Casselberry FL 32707",
    "addr:housenumber":"181",
    "addr:postcode":"32707",
    "addr:street":"Normandy Rd",
    "iso:country":"US",
    "sg:address":"181 Normandy Rd",
    "sg:city":"Casselberry",
    "sg:classifiers":[
        {
            "category":"Retail",
            "subcategory":"Car Wash",
            "type":"Services"
        }
    ],
    "sg:phone":"+1 407 331 3537",
    "sg:postcode":"32707",
    "sg:province":"FL",
    "sg:tags":[
        "carwash"
    ],
    "wof:name":"Domestic Detailing By Dal",
    "wof:placetype":"venue"
},
  "geometry": {"coordinates":[-81.34150200000001,28.667032],"type":"Point"}
}