{
  "type": "Feature",
  "properties": {
    "iso:country":"US",
    "sg:address":"825 NE 6th Ave",
    "sg:city":"Delray Beach",
    "sg:classifiers":[
        {
            "category":"Health Services",
            "subcategory":"Chiropractor",
            "type":"Services"
        }
    ],
    "sg:phone":"+1 561 266 8870",
    "sg:postcode":"33483",
    "sg:province":"FL",
    "wof:name":"Advanced Back & Sleep Gllrys",
    "wof:placetype":"venue"
},
  "geometry": {"coordinates":[-80.06703400000001,26.476374],"type":"Point"}
}