{
  "type": "Feature",
  "properties": {
    "addr:full":"111 1st St Fort Myers FL 33907",
    "addr:housenumber":"111",
    "addr:postcode":"33907",
    "addr:street":"1St St",
    "iso:country":"US",
    "sg:address":"111 1st St",
    "sg:city":"Fort Myers",
    "sg:classifiers":[
        {
            "category":"Manufacturing",
            "subcategory":"Metals",
            "type":"Manufacturing & Wholesale Goods"
        }
    ],
    "sg:phone":"+1 239 277 1178",
    "sg:postcode":"33907",
    "sg:province":"FL",
    "sg:tags":[
        "ornamental",
        "work",
        "iron"
    ],
    "wof:name":"Accurate Metal Manufacturing",
    "wof:placetype":"venue"
},
  "geometry": {"coordinates":[-81.865765,26.57882],"type":"Point"}
}