{
  "type": "Feature",
  "properties": {
    "addr:full":"1844 SE Pruitt Rd Port St Lucie FL 34952",
    "addr:housenumber":"1844",
    "addr:postcode":"34952",
    "addr:street":"Se Pruitt Rd;St",
    "iso:country":"US",
    "sg:address":"1844 SE Pruitt Rd",
    "sg:city":"Port St Lucie",
    "sg:classifiers":[
        {
            "category":"Real Estate",
            "subcategory":"Real Estate Services",
            "type":"Services"
        }
    ],
    "sg:phone":"+1 772 398 6061",
    "sg:postcode":"34952",
    "sg:province":"FL",
    "sg:tags":[
        "company",
        "title"
    ],
    "wof:name":"Security First Title Partners",
    "wof:placetype":"venue"
},
  "geometry": {"coordinates":[-80.317734,27.259049],"type":"Point"}
}