{
  "type": "Feature",
  "properties": {
    "iso:country":"US",
    "sg:address":"20849 Sailfish Ln",
    "sg:city":"Miami",
    "sg:classifiers":[
        {
            "category":"Building & Trades",
            "subcategory":"Construction",
            "type":"Services"
        }
    ],
    "sg:phone":"+1 305 238 8276",
    "sg:postcode":"33189",
    "sg:province":"FL",
    "sg:tags":[
        "hanging",
        "contractor"
    ],
    "wof:name":"Jam Painting & Paper Hanging I",
    "wof:placetype":"venue"
},
  "geometry": {"coordinates":[-80.34624100000001,25.573452],"type":"Point"}
}