{
  "type": "Feature",
  "properties": {
    "addr:full":"234 Commercial Blvd Lauderdl By Sea FL 33308",
    "addr:housenumber":"234",
    "addr:postcode":"33308",
    "addr:street":"Commercial Blvd Lauderdl By Sea",
    "iso:country":"US",
    "sg:address":"234 Commercial Blvd",
    "sg:city":"Lauderdl By Sea",
    "sg:classifiers":[
        {
            "category":"Shopping",
            "subcategory":"Pharmacy",
            "type":"Retail Goods"
        }
    ],
    "sg:phone":"+1 954 938 0005",
    "sg:postcode":"33308",
    "sg:province":"FL",
    "wof:name":"Dr G's Pharmacy",
    "wof:placetype":"venue"
},
  "geometry": {"coordinates":[-80.10111999999999,26.189787],"type":"Point"}
}