{
  "type": "Feature",
  "properties": {
    "iso:country":"US",
    "sg:address":"243 W Park Ave",
    "sg:city":"Winter Park",
    "sg:classifiers":[
        {
            "category":"Restaurant",
            "type":"Food & Drink"
        }
    ],
    "sg:phone":"+1 407 628 2255",
    "sg:postcode":"32789",
    "sg:province":"FL",
    "sg:tags":[
        "eating"
    ],
    "wof:name":"American Vision Ice Inc",
    "wof:placetype":"venue"
},
  "geometry": {"coordinates":[-81.352253,28.595956],"type":"Point"}
}