{
  "type": "Feature",
  "properties": {
    "iso:country":"US",
    "sg:address":"2472 W 60th St",
    "sg:city":"Hialeah",
    "sg:classifiers":[
        {
            "category":"Professional",
            "subcategory":"Business Services",
            "type":"Services"
        }
    ],
    "sg:phone":"+1 786 497 2110",
    "sg:postcode":"33016",
    "sg:province":"FL",
    "sg:tags":[
        "cashing",
        "protection",
        "check",
        "system"
    ],
    "wof:name":"Sunny Enterprises LLC",
    "wof:placetype":"venue"
},
  "geometry": {"coordinates":[-80.333968,25.876931],"type":"Point"}
}