{
  "type": "Feature",
  "properties": {
    "iso:country":"US",
    "sg:address":"12630 Tradition Dr",
    "sg:city":"St Leo",
    "sg:classifiers":[
        {
            "category":"Building & Trades",
            "subcategory":"Construction",
            "type":"Services"
        }
    ],
    "sg:phone":"+1 352 588 0701",
    "sg:postcode":"33525",
    "sg:province":"FL",
    "sg:tags":[
        "home",
        "builder"
    ],
    "wof:name":"Classic Southern Homes",
    "wof:placetype":"venue"
},
  "geometry": {"coordinates":[-82.255349,28.342752],"type":"Point"}
}