{
  "type": "Feature",
  "properties": {
    "addr:full":"16211 Military Trl Delray Beach FL 33484",
    "addr:housenumber":"16211",
    "addr:postcode":"33484",
    "addr:street":"Military Trl",
    "iso:country":"US",
    "sg:address":"16211 Military Trl",
    "sg:city":"Delray Beach",
    "sg:classifiers":[
        {
            "category":"Autos & Motor Vehicles",
            "subcategory":"Fuel & Gas Station",
            "type":"Retail Goods"
        }
    ],
    "sg:phone":"+1 561 495 0619",
    "sg:postcode":"33484",
    "sg:province":"FL",
    "sg:tags":[
        "oil"
    ],
    "wof:name":"Murphy Oil USA Inc",
    "wof:placetype":"venue"
},
  "geometry": {"coordinates":[-80.122213,26.436448],"type":"Point"}
}