{
  "type": "Feature",
  "properties": {
    "addr:full":"7700 NW 79th Pl Ste 1 Miami FL 33166",
    "addr:housenumber":"7700",
    "addr:postcode":"33166",
    "addr:street":"Nw 79Th Pl Ste 1",
    "iso:country":"US",
    "sg:address":"7700 NW 79th Pl Ste 1",
    "sg:city":"Miami",
    "sg:classifiers":[
        {
            "category":"Professional",
            "subcategory":"Business Services",
            "type":"Services"
        }
    ],
    "sg:phone":"+1 305 592 1445",
    "sg:postcode":"33166",
    "sg:province":"FL",
    "sg:tags":[
        "delivery",
        "courier"
    ],
    "wof:name":"Monarch Delivery Service Inc",
    "wof:placetype":"venue"
},
  "geometry": {"coordinates":[-80.32831,25.844843],"type":"Point"}
}