{
  "type": "Feature",
  "properties": {
    "iso:country":"US",
    "sg:address":"13651 SW 143rd Ct # 3",
    "sg:city":"Miami",
    "sg:classifiers":[
        {
            "category":"Banks & Credit Unions",
            "subcategory":"Bank",
            "type":"Services"
        },
        {
            "category":"Shopping",
            "subcategory":"Antiques",
            "type":"Retail Goods"
        },
        {
            "category":"Shopping",
            "subcategory":"Used Merchandise",
            "type":"Retail Goods"
        }
    ],
    "sg:phone":"+1 305 233 7331",
    "sg:postcode":"33186",
    "sg:province":"FL",
    "sg:tags":[
        "second",
        "furniture",
        "hand"
    ],
    "sg:website":"http://www.pakobel.com",
    "wof:name":"Pakobel",
    "wof:placetype":"venue"
},
  "geometry": {"coordinates":[-80.42609400000001,25.640218],"type":"Point"}
}