{
  "type": "Feature",
  "properties": {
    "iso:country":"US",
    "sg:address":"8435 SW 102nd Pl",
    "sg:city":"Miami",
    "sg:classifiers":[
        {
            "category":"Professional",
            "subcategory":"Management & Consulting",
            "type":"Services"
        }
    ],
    "sg:phone":"+1 305 412 3607",
    "sg:postcode":"33173",
    "sg:province":"FL",
    "sg:tags":[
        "consultant"
    ],
    "wof:name":"R E Saumell & Assoc Inc",
    "wof:placetype":"venue"
},
  "geometry": {"coordinates":[-80.358907,25.6891],"type":"Point"}
}