{
  "type": "Feature",
  "properties": {
    "iso:country":"US",
    "sg:address":"772 Oak Dr",
    "sg:city":"Clermont",
    "sg:classifiers":[
        {
            "category":"Wholesale",
            "subcategory":"Non-durable Goods",
            "type":"Manufacturing & Wholesale Goods"
        }
    ],
    "sg:phone":"+1 352 394 4573",
    "sg:postcode":"34711",
    "sg:province":"FL",
    "wof:name":"Creative Enterprises",
    "wof:placetype":"venue"
},
  "geometry": {"coordinates":[-81.745453,28.544938],"type":"Point"}
}