{
  "type": "Feature",
  "properties": {
    "addr:full":"4263 Marseilles Ave Sarasota FL 34233",
    "addr:housenumber":"4263",
    "addr:postcode":"34233",
    "addr:street":"Marseilles Ave",
    "iso:country":"US",
    "sg:address":"4263 Marseilles Ave",
    "sg:city":"Sarasota",
    "sg:classifiers":[
        {
            "category":"Professional",
            "subcategory":"Management & Consulting",
            "type":"Services"
        }
    ],
    "sg:phone":"+1 402 525 7076",
    "sg:postcode":"34233",
    "sg:province":"FL",
    "wof:name":"M Harte & Associates Inc",
    "wof:placetype":"venue"
},
  "geometry": {"coordinates":[-82.455403,27.292092],"type":"Point"}
}