{
  "type": "Feature",
  "properties": {
    "iso:country":"US",
    "sg:address":"324 Sun Dial Ct",
    "sg:city":"Cocoa",
    "sg:classifiers":[
        {
            "category":"Professional",
            "subcategory":"Lawyer & Legal Services",
            "type":"Services"
        }
    ],
    "sg:phone":"+1 321 652 4337",
    "sg:postcode":"32926",
    "sg:province":"FL",
    "sg:tags":[
        "plan"
    ],
    "wof:name":"James Bennett & Andrew Small",
    "wof:placetype":"venue"
},
  "geometry": {"coordinates":[-80.78340900000001,28.360445],"type":"Point"}
}