{
  "type": "Feature",
  "properties": {
    "addr:full":"11200 NW 25th St Doral FL 33172",
    "addr:housenumber":"11200",
    "addr:postcode":"33172",
    "addr:street":"Nw 25Th St",
    "iso:country":"US",
    "sg:address":"11200 NW 25th St",
    "sg:city":"Doral",
    "sg:classifiers":[
        {
            "category":"Building & Trades",
            "subcategory":"Locksmith",
            "type":"Services"
        }
    ],
    "sg:phone":"+1 305 755 4370",
    "sg:postcode":"33172",
    "sg:province":"FL",
    "sg:tags":[
        "key"
    ],
    "wof:name":"A 24 Hour Emergency Locksmith",
    "wof:placetype":"venue"
},
  "geometry": {"coordinates":[-80.37709,25.796743],"type":"Point"}
}