{
  "type": "Feature",
  "properties": {
    "addr:full":"4199 Kean Rd Davie FL 33314",
    "addr:housenumber":"4199",
    "addr:postcode":"33314",
    "addr:street":"Kean Rd",
    "iso:country":"US",
    "sg:address":"4199 Kean Rd",
    "sg:city":"Davie",
    "sg:classifiers":[
        {
            "category":"Professional",
            "subcategory":"Business Services",
            "type":"Services"
        }
    ],
    "sg:phone":"+1 954 581 3310",
    "sg:postcode":"33314",
    "sg:province":"FL",
    "sg:tags":[
        "auction",
        "automobile",
        "salvaged"
    ],
    "wof:name":"Sadisco of Florida",
    "wof:placetype":"venue"
},
  "geometry": {"coordinates":[-80.214204,26.069907],"type":"Point"}
}