{
  "type": "Feature",
  "properties": {
    "iso:country":"US",
    "sg:address":"28913 US Hwy 19",
    "sg:city":"Clearwater",
    "sg:classifiers":[
        {
            "category":"Health Services",
            "subcategory":"Doctor",
            "type":"Services"
        }
    ],
    "sg:phone":"+1 727 772 8772",
    "sg:postcode":"33761",
    "sg:province":"FL",
    "wof:name":"E&G Family Dentistry",
    "wof:placetype":"venue"
},
  "geometry": {"coordinates":[-82.738135,28.034256],"type":"Point"}
}