{
  "type": "Feature",
  "properties": {
    "iso:country":"US",
    "sg:address":"95 NW 4th Ave",
    "sg:city":"Delray Beach",
    "sg:classifiers":[
        {
            "category":"Banks & Credit Unions",
            "subcategory":"Financial Services",
            "type":"Services"
        }
    ],
    "sg:phone":"+1 561 278 1169",
    "sg:postcode":"33444",
    "sg:province":"FL",
    "sg:tags":[
        "company",
        "holding"
    ],
    "wof:name":"Cds International Holdings",
    "wof:placetype":"venue"
},
  "geometry": {"coordinates":[-80.077096,26.461696],"type":"Point"}
}