{
  "type": "Feature",
  "properties": {
    "iso:country":"US",
    "sg:address":"442 Stonemont Dr",
    "sg:city":"Fort Lauderdale",
    "sg:classifiers":[
        {
            "category":"Arts & Performance",
            "subcategory":"Theater",
            "type":"Entertainment"
        }
    ],
    "sg:phone":"+1 954 389 0802",
    "sg:postcode":"33326",
    "sg:province":"FL",
    "sg:tags":[
        "magician",
        "group"
    ],
    "wof:name":"Top Hat Entertainment Gro",
    "wof:placetype":"venue"
},
  "geometry": {"coordinates":[-80.38919199999999,26.122132],"type":"Point"}
}