{
  "type": "Feature",
  "properties": {
    "addr:full":"34935 Huff Rd Eustis FL 32736",
    "addr:housenumber":"34935",
    "addr:postcode":"32736",
    "addr:street":"Huff Rd",
    "iso:country":"US",
    "sg:address":"34935 Huff Rd",
    "sg:city":"Eustis",
    "sg:classifiers":[
        {
            "category":"Home & Garden",
            "subcategory":"Garden Supply",
            "type":"Retail Goods"
        }
    ],
    "sg:phone":"+1 352 357 2643",
    "sg:postcode":"32736",
    "sg:province":"FL",
    "wof:name":"Seminole Springs Herb Farm",
    "wof:placetype":"venue"
},
  "geometry": {"coordinates":[-81.505571,28.873051],"type":"Point"}
}