{
  "type": "Feature",
  "properties": {
    "addr:full":"5247 Park Blvd Pinellas Park FL 33781",
    "addr:housenumber":"5247",
    "addr:postcode":"33781",
    "addr:street":"Park Blvd",
    "iso:country":"US",
    "sg:address":"5247 Park Blvd",
    "sg:city":"Pinellas Park",
    "sg:classifiers":[
        {
            "category":"Sports & Exercise",
            "subcategory":"Gym",
            "type":"Entertainment"
        }
    ],
    "sg:phone":"+1 727 544 9493",
    "sg:postcode":"33781",
    "sg:province":"FL",
    "sg:tags":[
        "spa",
        "health"
    ],
    "wof:name":"Qui Phi Day Spa",
    "wof:placetype":"venue"
},
  "geometry": {"coordinates":[-82.70587999999999,27.839292],"type":"Point"}
}