{
  "type": "Feature",
  "properties": {
    "iso:country":"US",
    "sg:address":"25 E 44th St",
    "sg:city":"Hialeah",
    "sg:classifiers":[
        {
            "category":"Shopping",
            "subcategory":"Crafts & Fabrics",
            "type":"Retail Goods"
        }
    ],
    "sg:phone":"+1 305 558 3050",
    "sg:postcode":"33013",
    "sg:province":"FL",
    "sg:tags":[
        "sewing",
        "machines-household"
    ],
    "sg:website":"http://www.singerco.com",
    "wof:name":"Singer Sewing Company",
    "wof:placetype":"venue"
},
  "geometry": {"coordinates":[-80.282854,25.862281],"type":"Point"}
}