{
  "type": "Feature",
  "properties": {
    "iso:country":"US",
    "sg:address":"100 E Tarpon Ave",
    "sg:city":"Tarpon Springs",
    "sg:classifiers":[
        {
            "category":"Banks & Credit Unions",
            "subcategory":"Bank",
            "type":"Services"
        }
    ],
    "sg:phone":"+1 727 944 4007",
    "sg:postcode":"34689",
    "sg:province":"FL",
    "sg:tags":[
        "loan",
        "real estate"
    ],
    "wof:name":"First Metropolitan Mortgage",
    "wof:placetype":"venue"
},
  "geometry": {"coordinates":[-82.755225,28.146165],"type":"Point"}
}