{
  "type": "Feature",
  "properties": {
    "addr:full":"9520 NW 58th St Miami FL 33178",
    "addr:housenumber":"9520",
    "addr:postcode":"33178",
    "addr:street":"Nw 58Th St",
    "iso:country":"US",
    "sg:address":"9520 NW 58th St",
    "sg:city":"Miami",
    "sg:classifiers":[
        {
            "category":"Real Estate",
            "subcategory":"Real Estate Agent",
            "type":"Services"
        }
    ],
    "sg:phone":"+1 305 640 3080",
    "sg:postcode":"33178",
    "sg:province":"FL",
    "wof:name":"American Demolition",
    "wof:placetype":"venue"
},
  "geometry": {"coordinates":[-80.346749,25.826268],"type":"Point"}
}