{
  "type": "Feature",
  "properties": {
    "iso:country":"US",
    "sg:address":"304 NW Flagler Ave",
    "sg:city":"Stuart",
    "sg:classifiers":[
        {
            "category":"Professional",
            "subcategory":"Business Services",
            "type":"Services"
        }
    ],
    "sg:phone":"+1 772 283 6390",
    "sg:postcode":"34994",
    "sg:province":"FL",
    "sg:tags":[
        "interior",
        "consultant",
        "design",
        "decorator"
    ],
    "wof:name":"Rowell Interiors",
    "wof:placetype":"venue"
},
  "geometry": {"coordinates":[-80.260268,27.209907],"type":"Point"}
}