{
  "type": "Feature",
  "properties": {
    "addr:full":"34 Rotonda Plz Rotonda West FL 33947",
    "addr:postcode":"33947",
    "addr:street":"34 Rotonda Plz",
    "iso:country":"US",
    "sg:address":"34 Rotonda Plz",
    "sg:city":"Rotonda West",
    "sg:classifiers":[
        {
            "category":"Building & Trades",
            "subcategory":"Construction",
            "type":"Services"
        }
    ],
    "sg:phone":"+1 941 697 6400",
    "sg:postcode":"33947",
    "sg:province":"FL",
    "sg:tags":[
        "contractor"
    ],
    "wof:name":"A James Construction Inc",
    "wof:placetype":"venue"
},
  "geometry": {"coordinates":[-82.27735,26.891418],"type":"Point"}
}