{
  "type": "Feature",
  "properties": {
    "addr:full":"15800 E Hwy 40 Silver Springs FL 34488",
    "addr:housenumber":"15800",
    "addr:postcode":"34488",
    "addr:street":"E Hwy 40",
    "iso:country":"US",
    "sg:address":"15800 E Hwy 40",
    "sg:city":"Silver Springs",
    "sg:classifiers":[
        {
            "category":"Real Estate",
            "subcategory":"Real Estate Agent",
            "type":"Services"
        }
    ],
    "sg:phone":"+1 352 625 2001",
    "sg:postcode":"34488",
    "sg:province":"FL",
    "wof:name":"Sun Realty & Assoc",
    "wof:placetype":"venue"
},
  "geometry": {"coordinates":[-81.89325599999999,29.184347],"type":"Point"}
}