{
  "type": "Feature",
  "properties": {
    "addr:full":"14563 Okeechobee Blvd Loxahatchee FL 33470",
    "addr:housenumber":"14563",
    "addr:postcode":"33470",
    "addr:street":"Okeechobee Blvd",
    "iso:country":"US",
    "sg:address":"14563 Okeechobee Blvd",
    "sg:city":"Loxahatchee",
    "sg:classifiers":[
        {
            "category":"Social Services",
            "subcategory":"Child Care",
            "type":"Services"
        }
    ],
    "sg:phone":"+1 561 753 6624",
    "sg:postcode":"33470",
    "sg:province":"FL",
    "sg:tags":[
        "kindergarten",
        "academic",
        "school",
        "day"
    ],
    "wof:name":"Noah's Ark Academy Inc",
    "wof:placetype":"venue"
},
  "geometry": {"coordinates":[-80.28124,26.706726],"type":"Point"}
}