{
  "type": "Feature",
  "properties": {
    "addr:full":"8634 Pensacola Blvd Pensacola FL 32534",
    "addr:housenumber":"8634",
    "addr:postcode":"32534",
    "addr:street":"Pensacola Blvd",
    "iso:country":"US",
    "sg:address":"8634 Pensacola Blvd",
    "sg:city":"Pensacola",
    "sg:classifiers":[
        {
            "category":"Government",
            "subcategory":"Fire Station",
            "type":"Public Place"
        }
    ],
    "sg:phone":"+1 850 475 5550",
    "sg:postcode":"32534",
    "sg:province":"FL",
    "sg:tags":[
        "county",
        "protection"
    ],
    "wof:name":"Ensley Fire Dept",
    "wof:placetype":"venue"
},
  "geometry": {"coordinates":[-87.273793,30.522575],"type":"Point"}
}