{
  "type": "Feature",
  "properties": {
    "addr:full":"570 US Hwy 90 E Jacksonville FL 32234",
    "addr:housenumber":"570",
    "addr:postcode":"32234",
    "addr:street":"Us Hwy 90 E",
    "iso:country":"US",
    "sg:address":"570 US Hwy 90 E",
    "sg:city":"Jacksonville",
    "sg:classifiers":[
        {
            "category":"Wholesale",
            "subcategory":"Electrical",
            "type":"Manufacturing & Wholesale Goods"
        }
    ],
    "sg:phone":"+1 904 266 0007",
    "sg:postcode":"32234",
    "sg:province":"FL",
    "sg:tags":[
        "electric",
        "motor"
    ],
    "wof:name":"Tesla Electric Armapure & Mch",
    "wof:placetype":"venue"
},
  "geometry": {"coordinates":[-81.96963599999999,30.302785],"type":"Point"}
}