{
  "type": "Feature",
  "properties": {
    "addr:full":"5628 Central Ave Saint Petersburg FL 33707",
    "addr:housenumber":"5628",
    "addr:postcode":"33707",
    "addr:street":"Central Ave",
    "iso:country":"US",
    "sg:address":"5628 Central Ave",
    "sg:city":"Saint Petersburg",
    "sg:classifiers":[
        {
            "category":"Health Services",
            "subcategory":"Doctor",
            "type":"Services"
        }
    ],
    "sg:phone":"+1 727 344 2681",
    "sg:postcode":"33707",
    "sg:province":"FL",
    "sg:tags":[
        "medical"
    ],
    "wof:name":"Paul Mares MD PA",
    "wof:placetype":"venue"
},
  "geometry": {"coordinates":[-82.710432,27.770809],"type":"Point"}
}