{
  "type": "Feature",
  "properties": {
    "iso:country":"US",
    "sg:address":"1143 N Lyle Ave",
    "sg:city":"Crystal River",
    "sg:classifiers":[
        {
            "category":"Professional",
            "subcategory":"Business Services",
            "type":"Services"
        }
    ],
    "sg:phone":"+1 352 563 2411",
    "sg:postcode":"34429",
    "sg:province":"FL",
    "sg:tags":[
        "drafting"
    ],
    "wof:name":"Residential Planning Solutions",
    "wof:placetype":"venue"
},
  "geometry": {"coordinates":[-82.526278,28.879994],"type":"Point"}
}