{
  "type": "Feature",
  "properties": {
    "iso:country":"US",
    "sg:address":"7660 Centurion Pkwy",
    "sg:city":"Jacksonville",
    "sg:classifiers":[
        {
            "category":"Professional",
            "subcategory":"Employment Agencies",
            "type":"Services"
        }
    ],
    "sg:phone":"+1 904 493 7350",
    "sg:postcode":"32256",
    "sg:province":"FL",
    "sg:tags":[
        "consultant",
        "search",
        "executive"
    ],
    "wof:name":"Recruitmax",
    "wof:placetype":"venue"
},
  "geometry": {"coordinates":[-81.545907,30.240374],"type":"Point"}
}