{
  "type": "Feature",
  "properties": {
    "addr:full":"6665 Lake Worth Rd Lake Worth FL 33467",
    "addr:housenumber":"6665",
    "addr:postcode":"33467",
    "addr:street":"Lake Worth Rd",
    "iso:country":"US",
    "sg:address":"6665 Lake Worth Rd",
    "sg:city":"Lake Worth",
    "sg:classifiers":[
        {
            "category":"Personal",
            "subcategory":"Beauty Salon",
            "type":"Services"
        }
    ],
    "sg:phone":"+1 561 439 5125",
    "sg:postcode":"33467",
    "sg:province":"FL",
    "sg:tags":[
        "shop"
    ],
    "wof:name":"Looking Good",
    "wof:placetype":"venue"
},
  "geometry": {"coordinates":[-80.151968,26.61775],"type":"Point"}
}