{
  "type": "Feature",
  "properties": {
    "iso:country":"US",
    "sg:address":"12086 Fort Caroline Rd Suite # 401",
    "sg:city":"Jacksonville",
    "sg:classifiers":[
        {
            "category":"Health Services",
            "subcategory":"Doctor",
            "type":"Services"
        }
    ],
    "sg:phone":"+1 904 565 1271",
    "sg:postcode":"32225",
    "sg:province":"FL",
    "sg:tags":[
        "physician",
        "pediatrics-emergency",
        "pediatrics",
        "family",
        "practice",
        "surgeons",
        "medicine",
        "surgeon"
    ],
    "wof:name":"All About Kids And Families Medical Center",
    "wof:placetype":"venue"
},
  "geometry": {"coordinates":[-81.50957099999999,30.378746],"type":"Point"}
}