{
  "type": "Feature",
  "properties": {
    "iso:country":"US",
    "sg:address":"5283 W Atlantic Ave",
    "sg:city":"Delray Beach",
    "sg:classifiers":[
        {
            "category":"Food & Beverages",
            "subcategory":"Groceries & Convenience Stores",
            "type":"Retail Goods"
        }
    ],
    "sg:phone":"+1 561 638 4765",
    "sg:postcode":"33484",
    "sg:province":"FL",
    "wof:name":"Handbag Market",
    "wof:placetype":"venue"
},
  "geometry": {"coordinates":[-80.126119,26.457895],"type":"Point"}
}