{
  "type": "Feature",
  "properties": {
    "addr:full":"12407 N 11th St Tampa FL 33612",
    "addr:housenumber":"12407",
    "addr:postcode":"33612",
    "addr:street":"N 11Th St",
    "iso:country":"US",
    "sg:address":"12407 N 11th St",
    "sg:city":"Tampa",
    "sg:classifiers":[
        {
            "category":"Real Estate",
            "subcategory":"Developer",
            "type":"Services"
        }
    ],
    "sg:phone":"+1 813 971 0238",
    "sg:postcode":"33612",
    "sg:province":"FL",
    "sg:tags":[
        "mobile",
        "home"
    ],
    "wof:name":"Regency Oaks",
    "wof:placetype":"venue"
},
  "geometry": {"coordinates":[-82.44833,28.060745],"type":"Point"}
}