{
  "type": "Feature",
  "properties": {
    "addr:full":"21460 SW 109th Ave Miami FL 33170",
    "addr:housenumber":"21460",
    "addr:postcode":"33170",
    "addr:street":"Sw 109Th Ave",
    "iso:country":"US",
    "sg:address":"21460 SW 109th Ave",
    "sg:city":"Miami",
    "sg:classifiers":[
        {
            "category":"Building & Trades",
            "subcategory":"Landscaping Services",
            "type":"Services"
        }
    ],
    "sg:phone":"+1 786 255 0925",
    "sg:postcode":"33170",
    "sg:province":"FL",
    "sg:tags":[
        "lawn",
        "tree",
        "maintenance"
    ],
    "wof:name":"M & B Lawn Maintenance Inc",
    "wof:placetype":"venue"
},
  "geometry": {"coordinates":[-80.36799600000001,25.553435],"type":"Point"}
}