{
  "type": "Feature",
  "properties": {
    "addr:full":"1420 SE 6th Ave Cape Coral FL 33990",
    "addr:housenumber":"1420",
    "addr:postcode":"33990",
    "addr:street":"Se 6Th Ave",
    "iso:country":"US",
    "sg:address":"1420 SE 6th Ave",
    "sg:city":"Cape Coral",
    "sg:classifiers":[
        {
            "category":"Building & Trades",
            "subcategory":"Cleaning & Sanitation",
            "type":"Services"
        }
    ],
    "sg:phone":"+1 239 340 8776",
    "sg:postcode":"33990",
    "sg:province":"FL",
    "sg:tags":[
        "janitor"
    ],
    "wof:name":"Barbara Hall's Cleaning Svc",
    "wof:placetype":"venue"
},
  "geometry": {"coordinates":[-81.96162200000001,26.626024],"type":"Point"}
}