{
  "type": "Feature",
  "properties": {
    "iso:country":"US",
    "sg:address":"1600 Carolwood Ct",
    "sg:city":"Tallahassee",
    "sg:classifiers":[
        {
            "category":"Building & Trades",
            "subcategory":"Cleaning & Sanitation",
            "type":"Services"
        },
        {
            "category":"Retail",
            "subcategory":"Laundry & Dry Cleaning",
            "type":"Services"
        }
    ],
    "sg:phone":"+1 850 350 0009",
    "sg:postcode":"32308",
    "sg:province":"FL",
    "sg:tags":[
        "cleaner",
        "contractor",
        "cleaning-industrial",
        "house"
    ],
    "wof:name":"Blessed Hands Cleaning Service",
    "wof:placetype":"venue"
},
  "geometry": {"coordinates":[-84.24889400000001,30.466782],"type":"Point"}
}