{
  "type": "Feature",
  "properties": {
    "iso:country":"US",
    "sg:address":"1715 Country Meadows Dr",
    "sg:city":"Sarasota",
    "sg:classifiers":[
        {
            "category":"Professional",
            "subcategory":"Business Services",
            "type":"Services"
        },
        {
            "category":"Shopping",
            "subcategory":"Gifts & Souvenirs",
            "type":"Retail Goods"
        }
    ],
    "sg:phone":"+1 941 359 0827",
    "sg:postcode":"34235",
    "sg:province":"FL",
    "sg:tags":[
        "inspection"
    ],
    "wof:name":"Hallmark Inspection Svcs Inc",
    "wof:placetype":"venue"
},
  "geometry": {"coordinates":[-82.47174099999999,27.352788],"type":"Point"}
}