{
  "type": "Feature",
  "properties": {
    "addr:full":"731 Isleton Dr Brandon FL 33511",
    "addr:housenumber":"731",
    "addr:postcode":"33511",
    "addr:street":"Isleton Dr",
    "iso:country":"US",
    "sg:address":"731 Isleton Dr",
    "sg:city":"Brandon",
    "sg:classifiers":[
        {
            "category":"Building & Trades",
            "subcategory":"Landscaping Services",
            "type":"Services"
        }
    ],
    "sg:phone":"+1 813 681 2252",
    "sg:postcode":"33511",
    "sg:province":"FL",
    "sg:tags":[
        "tree"
    ],
    "wof:name":"J & B Tree Svc",
    "wof:placetype":"venue"
},
  "geometry": {"coordinates":[-82.270009,27.883001],"type":"Point"}
}