{
  "type": "Feature",
  "properties": {
    "addr:full":"160 Promenade Way Jupiter FL 33458",
    "addr:housenumber":"160",
    "addr:postcode":"33458",
    "addr:street":"Promenade Way",
    "iso:country":"US",
    "sg:address":"160 Promenade Way",
    "sg:city":"Jupiter",
    "sg:classifiers":[
        {
            "category":"Shopping",
            "type":"Retail Goods"
        }
    ],
    "sg:phone":"+1 561 622 1819",
    "sg:postcode":"33458",
    "sg:province":"FL",
    "sg:tags":[
        "perfume"
    ],
    "wof:name":"Aramis & Designer Fragrances",
    "wof:placetype":"venue"
},
  "geometry": {"coordinates":[-80.105594,26.893866],"type":"Point"}
}