{
  "type": "Feature",
  "properties": {
    "iso:country":"US",
    "sg:address":"2300 Janie Poe Dr",
    "sg:city":"Sarasota",
    "sg:classifiers":[
        {
            "category":"Education",
            "subcategory":"Library",
            "type":"Public Place"
        }
    ],
    "sg:phone":"+1 941 366 6098",
    "sg:postcode":"34234",
    "sg:province":"FL",
    "wof:name":"Newtown Library",
    "wof:placetype":"venue"
},
  "geometry": {"coordinates":[-82.541884,27.357341],"type":"Point"}
}