{
  "type": "Feature",
  "properties": {
    "iso:country":"US",
    "sg:address":"261 15th St",
    "sg:city":"Daytona Beach",
    "sg:classifiers":[
        {
            "category":"Building & Trades",
            "subcategory":"Construction",
            "type":"Services"
        }
    ],
    "sg:phone":"+1 386 673 6936",
    "sg:postcode":"32117",
    "sg:province":"FL",
    "sg:tags":[
        "house"
    ],
    "wof:name":"Tiles By Dave",
    "wof:placetype":"venue"
},
  "geometry": {"coordinates":[-81.04513900000001,29.252268],"type":"Point"}
}