{
  "type": "Feature",
  "properties": {
    "addr:full":"18934 US Hwy 19 Hudson FL 34667",
    "addr:postcode":"18934;34667",
    "addr:street":"Us Hwy 19",
    "iso:country":"US",
    "sg:address":"18934 US Hwy 19",
    "sg:city":"Hudson",
    "sg:classifiers":[
        {
            "category":"Food & Beverages",
            "subcategory":"Groceries & Convenience Stores",
            "type":"Retail Goods"
        }
    ],
    "sg:phone":"+1 727 861 7308",
    "sg:postcode":"34667",
    "sg:province":"FL",
    "wof:name":"7-Eleven",
    "wof:placetype":"venue"
},
  "geometry": {"coordinates":[-82.640578,28.432011],"type":"Point"}
}