{
  "type": "Feature",
  "properties": {
    "iso:country":"US",
    "sg:address":"315 NE 16th Ter",
    "sg:city":"Fort Lauderdale",
    "sg:classifiers":[
        {
            "category":"Travel",
            "subcategory":"Hotels & Motels",
            "type":"Entertainment"
        }
    ],
    "sg:phone":"+1 954 527 0094",
    "sg:postcode":"33301",
    "sg:province":"FL",
    "sg:tags":[
        "operation"
    ],
    "wof:name":"Pineapple Point Guest House",
    "wof:placetype":"venue"
},
  "geometry": {"coordinates":[-80.12594799999999,26.12591],"type":"Point"}
}