{
  "type": "Feature",
  "properties": {
    "addr:full":"16301 NW 49th Ave Hialeah FL 33014",
    "addr:housenumber":"16301",
    "addr:postcode":"33014",
    "addr:street":"Nw 49Th Ave",
    "iso:country":"US",
    "sg:address":"16301 NW 49th Ave",
    "sg:city":"Hialeah",
    "sg:classifiers":[
        {
            "category":"Wholesale",
            "subcategory":"Home Furnishings",
            "type":"Manufacturing & Wholesale Goods"
        }
    ],
    "sg:phone":"+1 305 623 8302",
    "sg:postcode":"33014",
    "sg:province":"FL",
    "sg:tags":[
        "blind",
        "shade"
    ],
    "wof:name":"Arabel",
    "wof:placetype":"venue"
},
  "geometry": {"coordinates":[-80.28070099999999,25.921499],"type":"Point"}
}