{
  "type": "Feature",
  "properties": {
    "iso:country":"US",
    "sg:address":"34 Golden Rod Cir",
    "sg:city":"Santa Rosa Beach",
    "sg:classifiers":[
        {
            "category":"Restaurant",
            "type":"Food & Drink"
        }
    ],
    "sg:menulink":"http://www.allmenus.com/fl/freeport/267206-fish-out-of-water/menu/",
    "sg:phone":"+1 850 534 5050",
    "sg:postcode":"32459",
    "sg:province":"FL",
    "sg:tags":[
        "seafood",
        "american"
    ],
    "wof:name":"Fish out of Water",
    "wof:placetype":"venue"
},
  "geometry": {"coordinates":[-86.144705,30.321916],"type":"Point"}
}