{
  "type": "Feature",
  "properties": {
    "addr:full":"14749 Mahoe Ct Fort Myers FL 33908",
    "addr:housenumber":"14749",
    "addr:postcode":"33908",
    "addr:street":"Mahoe Ct",
    "iso:country":"US",
    "sg:address":"14749 Mahoe Ct",
    "sg:city":"Fort Myers",
    "sg:classifiers":[
        {
            "category":"Health Services",
            "subcategory":"Doctor",
            "type":"Services"
        }
    ],
    "sg:phone":"+1 239 481 2536",
    "sg:postcode":"33908",
    "sg:province":"FL",
    "sg:tags":[
        "medical"
    ],
    "wof:name":"Fred Hormozdi MD",
    "wof:placetype":"venue"
},
  "geometry": {"coordinates":[-81.931273,26.524931],"type":"Point"}
}