{
  "type": "Feature",
  "properties": {
    "addr:full":"7130 Fairway Dr Hialeah FL 33014",
    "addr:housenumber":"7130",
    "addr:postcode":"33014",
    "addr:street":"Fairway Dr",
    "iso:country":"US",
    "sg:address":"7130 Fairway Dr",
    "sg:city":"Hialeah",
    "sg:classifiers":[
        {
            "category":"Recreation",
            "type":"Entertainment"
        }
    ],
    "sg:phone":"+1 305 823 4116",
    "sg:postcode":"33014",
    "sg:province":"FL",
    "wof:name":"Traditional Karate Inc",
    "wof:placetype":"venue"
},
  "geometry": {"coordinates":[-80.314747,25.913116],"type":"Point"}
}