{
  "type": "Feature",
  "properties": {
    "addr:full":"2545 Estero Blvd Fort Myers Beach FL 33931",
    "addr:housenumber":"2545",
    "addr:postcode":"33931",
    "addr:street":"Estero Blvd",
    "iso:country":"US",
    "sg:address":"2545 Estero Blvd",
    "sg:city":"Fort Myers Beach",
    "sg:classifiers":[
        {
            "category":"Shopping",
            "subcategory":"Pharmacy",
            "type":"Retail Goods"
        }
    ],
    "sg:phone":"+1 239 463 5708",
    "sg:postcode":"33931",
    "sg:province":"FL",
    "wof:name":"CVS",
    "wof:placetype":"venue"
},
  "geometry": {"coordinates":[-81.941508,26.448302],"type":"Point"}
}