{
  "type": "Feature",
  "properties": {
    "addr:full":"3126 Kumquat Dr Edgewater FL 32141",
    "addr:housenumber":"3126",
    "addr:postcode":"32141",
    "addr:street":"Kumquat Dr",
    "iso:country":"US",
    "sg:address":"3126 Kumquat Dr",
    "sg:city":"Edgewater",
    "sg:classifiers":[
        {
            "category":"Recreation",
            "type":"Entertainment"
        }
    ],
    "sg:phone":"+1 386 478 1054",
    "sg:postcode":"32141",
    "sg:province":"FL",
    "sg:tags":[
        "psychic",
        "medium"
    ],
    "wof:name":"Ginny Spiritualist Reader",
    "wof:placetype":"venue"
},
  "geometry": {"coordinates":[-80.893984,28.942563],"type":"Point"}
}