{
  "type": "Feature",
  "properties": {
    "addr:full":"1304 S Florida Ave Lakeland FL 33803",
    "addr:housenumber":"1304",
    "addr:postcode":"33803",
    "addr:street":"S Florida Ave",
    "iso:country":"US",
    "sg:address":"1304 S Florida Ave",
    "sg:city":"Lakeland",
    "sg:classifiers":[
        {
            "category":"Retail",
            "subcategory":"Auto Repair",
            "type":"Services"
        }
    ],
    "sg:phone":"+1 863 413 1865",
    "sg:postcode":"33803",
    "sg:province":"FL",
    "sg:tags":[
        "repairing",
        "automotive",
        "automobile",
        "general"
    ],
    "wof:name":"Liberty Auto Clinic Inc",
    "wof:placetype":"venue"
},
  "geometry": {"coordinates":[-81.957021,28.027306],"type":"Point"}
}