{
  "type": "Feature",
  "properties": {
    "addr:full":"20137 Ocean Key Dr Boca Raton FL 33498",
    "addr:housenumber":"20137",
    "addr:postcode":"33498",
    "addr:street":"Ocean Key Dr",
    "iso:country":"US",
    "sg:address":"20137 Ocean Key Dr",
    "sg:city":"Boca Raton",
    "sg:classifiers":[
        {
            "category":"Professional",
            "subcategory":"Computer Services",
            "type":"Services"
        }
    ],
    "sg:phone":"+1 561 488 9600",
    "sg:postcode":"33498",
    "sg:province":"FL",
    "sg:tags":[
        "programing",
        "custom"
    ],
    "sg:website":"www.frowh.com",
    "wof:name":"Frowh Inc",
    "wof:placetype":"venue"
},
  "geometry": {"coordinates":[-80.21830199999999,26.375197],"type":"Point"}
}