{
  "type": "Feature",
  "properties": {
    "iso:country":"US",
    "sg:address":"9321 Memorial Park Rd",
    "sg:city":"West Palm Beach",
    "sg:classifiers":[
        {
            "category":"Retail",
            "subcategory":"Funeral Services",
            "type":"Services"
        }
    ],
    "sg:phone":"+1 561 627 2277",
    "sg:postcode":"33412",
    "sg:province":"FL",
    "wof:name":"SCI",
    "wof:placetype":"venue"
},
  "geometry": {"coordinates":[-80.21297,26.81541],"type":"Point"}
}