{
  "type": "Feature",
  "properties": {
    "addr:full":"3550 S Washington Ave Titusville FL 32780",
    "addr:housenumber":"3550",
    "addr:postcode":"32780",
    "addr:street":"S Washington Ave",
    "iso:country":"US",
    "sg:address":"3550 S Washington Ave",
    "sg:city":"Titusville",
    "sg:classifiers":[
        {
            "category":"Autos & Motor Vehicles",
            "subcategory":"Auto Supplies",
            "type":"Retail Goods"
        }
    ],
    "sg:phone":"+1 321 268 5772",
    "sg:postcode":"32780",
    "sg:province":"FL",
    "sg:tags":[
        "repair",
        "brake",
        "tire"
    ],
    "sg:website":"http://www.tirekingdom.com",
    "wof:name":"Tire Kingdom",
    "wof:placetype":"venue"
},
  "geometry": {"coordinates":[-80.799171,28.57588],"type":"Point"}
}