{
  "type": "Feature",
  "properties": {
    "addr:full":"1210 Waverly Rd Tallahassee FL 32312",
    "addr:housenumber":"1210",
    "addr:postcode":"32312",
    "addr:street":"Waverly Rd",
    "iso:country":"US",
    "sg:address":"1210 Waverly Rd",
    "sg:city":"Tallahassee",
    "sg:classifiers":[
        {
            "category":"Health Services",
            "subcategory":"Clinic",
            "type":"Services"
        }
    ],
    "sg:phone":"+1 850 575 9700",
    "sg:postcode":"32312",
    "sg:province":"FL",
    "wof:name":"Care Givers For Seniors",
    "wof:placetype":"venue"
},
  "geometry": {"coordinates":[-84.263043,30.481641],"type":"Point"}
}