{
  "type": "Feature",
  "properties": {
    "iso:country":"US",
    "sg:address":"7320 Johnson Rd",
    "sg:city":"Milton",
    "sg:classifiers":[
        {
            "category":"Shopping",
            "subcategory":"Computers & Home Electronics",
            "type":"Retail Goods"
        }
    ],
    "sg:phone":"+1 850 983 2270",
    "sg:postcode":"32583",
    "sg:province":"FL",
    "sg:tags":[
        "equipment",
        "dealer"
    ],
    "wof:name":"Heuristic Corp Inc",
    "wof:placetype":"venue"
},
  "geometry": {"coordinates":[-87.00899800000001,30.630214],"type":"Point"}
}