{
  "type": "Feature",
  "properties": {
    "addr:full":"7652 Ashley Park Ct Orlando FL 32835",
    "addr:housenumber":"7652",
    "addr:postcode":"32835",
    "addr:street":"Ashley Park Ct",
    "iso:country":"US",
    "sg:address":"7652 Ashley Park Ct",
    "sg:city":"Orlando",
    "sg:classifiers":[
        {
            "category":"Travel",
            "subcategory":"Hotels & Motels",
            "type":"Entertainment"
        }
    ],
    "sg:phone":"+1 407 295 1950",
    "sg:postcode":"32835",
    "sg:province":"FL",
    "sg:website":"www.alhi.com",
    "wof:name":"Associated Luxury Hotels Inc",
    "wof:placetype":"venue"
},
  "geometry": {"coordinates":[-81.485687,28.507589],"type":"Point"}
}