{
  "type": "Feature",
  "properties": {
    "iso:country":"US",
    "sg:address":"6640 Bird Rd",
    "sg:city":"Miami",
    "sg:classifiers":[
        {
            "category":"Home & Garden",
            "subcategory":"Carpets & Floor Coverings",
            "type":"Retail Goods"
        }
    ],
    "sg:phone":"+1 305 666 2727",
    "sg:postcode":"33155",
    "sg:province":"FL",
    "sg:tags":[
        "mattress"
    ],
    "wof:name":"Supra-Mattress Discount",
    "wof:placetype":"venue"
},
  "geometry": {"coordinates":[-80.3022,25.7334],"type":"Point"}
}