{
  "type": "Feature",
  "properties": {
    "iso:country":"US",
    "sg:address":"900 Armstrong Blvd",
    "sg:city":"Kissimmee",
    "sg:classifiers":[
        {
            "category":"Wholesale",
            "subcategory":"Non-durable Goods",
            "type":"Manufacturing & Wholesale Goods"
        }
    ],
    "sg:phone":"+1 407 847 6446",
    "sg:postcode":"34741",
    "sg:province":"FL",
    "sg:tags":[
        "outerwear",
        "mfg"
    ],
    "wof:name":"Stoneage Arts Inc",
    "wof:placetype":"venue"
},
  "geometry": {"coordinates":[-81.441143,28.29911],"type":"Point"}
}