{
  "type": "Feature",
  "properties": {
    "addr:full":"301 Springsong Rd Lithia FL 33547",
    "addr:housenumber":"301",
    "addr:postcode":"33547",
    "addr:street":"Springsong Rd",
    "iso:country":"US",
    "sg:address":"301 Springsong Rd",
    "sg:city":"Lithia",
    "sg:classifiers":[
        {
            "category":"Manufacturing",
            "subcategory":"Food",
            "type":"Manufacturing & Wholesale Goods"
        }
    ],
    "sg:phone":"+1 813 643 7191",
    "sg:postcode":"33547",
    "sg:province":"FL",
    "sg:tags":[
        "gourmet",
        "sauce",
        "mfg"
    ],
    "wof:name":"Howton Farms Gourmet Sauces",
    "wof:placetype":"venue"
},
  "geometry": {"coordinates":[-82.14580599999999,27.844107],"type":"Point"}
}