{
  "type": "Feature",
  "properties": {
    "iso:country":"US",
    "sg:address":"2820 N Side Dr",
    "sg:city":"Eustis",
    "sg:classifiers":[
        {
            "category":"Professional",
            "subcategory":"Computer Services",
            "type":"Services"
        },
        {
            "category":"Manufacturing",
            "subcategory":"Printing",
            "type":"Manufacturing & Wholesale Goods"
        }
    ],
    "sg:phone":"+1 352 589 1210",
    "sg:postcode":"32726",
    "sg:province":"FL",
    "sg:tags":[
        "prepackaged",
        "printer",
        "software"
    ],
    "wof:name":"D & P Consultants",
    "wof:placetype":"venue"
},
  "geometry": {"coordinates":[-81.653085,28.840223],"type":"Point"}
}