{
  "type": "Feature",
  "properties": {
    "iso:country":"US",
    "sg:address":"22 Crandon Blvd",
    "sg:city":"Key Biscayne",
    "sg:classifiers":[
        {
            "category":"Real Estate",
            "subcategory":"Real Estate Agent",
            "type":"Services"
        }
    ],
    "sg:phone":"+1 305 361 8800",
    "sg:postcode":"33149",
    "sg:province":"FL",
    "wof:name":"Metropolis Realty and Dev",
    "wof:placetype":"venue"
},
  "geometry": {"coordinates":[-80.16309099999999,25.696169],"type":"Point"}
}