{
  "type": "Feature",
  "properties": {
    "iso:country":"US",
    "sg:address":"1501 NW Boca Raton Blvd",
    "sg:city":"Boca Raton",
    "sg:classifiers":[
        {
            "category":"Personal",
            "subcategory":"Beauty Salon",
            "type":"Services"
        }
    ],
    "sg:phone":"+1 561 391 5375",
    "sg:postcode":"33432",
    "sg:province":"FL",
    "sg:tags":[
        "shop"
    ],
    "wof:name":"Orlando's For Hair & Nails",
    "wof:placetype":"venue"
},
  "geometry": {"coordinates":[-80.090197,26.364537],"type":"Point"}
}