{
  "type": "Feature",
  "properties": {
    "iso:country":"US",
    "sg:address":"2304 E Oakland Park Blvd",
    "sg:city":"Fort Lauderdale",
    "sg:classifiers":[
        {
            "category":"Retail",
            "subcategory":"Repair Shop",
            "type":"Services"
        }
    ],
    "sg:phone":"+1 954 446 7342",
    "sg:postcode":"33306",
    "sg:province":"FL",
    "sg:tags":[
        "lock",
        "locksmith"
    ],
    "wof:name":"7 Day Always Emergency Lcksmth",
    "wof:placetype":"venue"
},
  "geometry": {"coordinates":[-80.11520899999999,26.16723],"type":"Point"}
}