{
  "type": "Feature",
  "properties": {
    "iso:country":"US",
    "sg:address":"1979 Maryland Cir",
    "sg:city":"Tallahassee",
    "sg:classifiers":[
        {
            "category":"Building & Trades",
            "subcategory":"Construction",
            "type":"Services"
        }
    ],
    "sg:phone":"+1 850 576 7189",
    "sg:postcode":"32303",
    "sg:province":"FL",
    "sg:tags":[
        "contractor"
    ],
    "wof:name":"Five Star Building Corp I",
    "wof:placetype":"venue"
},
  "geometry": {"coordinates":[-84.347753,30.475612],"type":"Point"}
}