{
  "type": "Feature",
  "properties": {
    "addr:full":"1517 N L St Lake Worth FL 33460",
    "addr:housenumber":"1517",
    "addr:postcode":"33460",
    "addr:street":"N L St",
    "iso:country":"US",
    "sg:address":"1517 N L St",
    "sg:city":"Lake Worth",
    "sg:classifiers":[
        {
            "category":"Professional",
            "type":"Services"
        }
    ],
    "sg:phone":"+1 561 588 1963",
    "sg:postcode":"33460",
    "sg:province":"FL",
    "wof:name":"Jukka & Ann & Sanni & Jen",
    "wof:placetype":"venue"
},
  "geometry": {"coordinates":[-80.053687,26.634504],"type":"Point"}
}