{
  "type": "Feature",
  "properties": {
    "iso:country":"US",
    "sg:address":"2053 S US Hwy 1",
    "sg:city":"Fort Pierce",
    "sg:classifiers":[
        {
            "category":"Shopping",
            "subcategory":"Clothing, Apparel, & Fashions",
            "type":"Retail Goods"
        }
    ],
    "sg:phone":"+1 772 461 3553",
    "sg:postcode":"34950",
    "sg:province":"FL",
    "sg:tags":[
        "furnishing"
    ],
    "wof:name":"Men's Rags",
    "wof:placetype":"venue"
},
  "geometry": {"coordinates":[-80.32600499999999,27.428818],"type":"Point"}
}