{
  "type": "Feature",
  "properties": {
    "iso:country":"US",
    "sg:address":"1315 10th St",
    "sg:city":"Sarasota",
    "sg:classifiers":[
        {
            "category":"Professional",
            "type":"Services"
        }
    ],
    "sg:phone":"+1 941 366 0920",
    "sg:postcode":"34236",
    "sg:province":"FL",
    "sg:tags":[
        "establishment"
    ],
    "wof:name":"Ten Coconut",
    "wof:placetype":"venue"
},
  "geometry": {"coordinates":[-82.54267900000001,27.344911],"type":"Point"}
}