{
  "type": "Feature",
  "properties": {
    "addr:full":"3300 W Lake Mary Blvd Ste 100 Lake Mary FL 32746",
    "addr:housenumber":"3300",
    "addr:postcode":"32746",
    "addr:street":"W Lake Mary Blvd Ste 100;Mary",
    "iso:country":"US",
    "sg:address":"3300 W Lake Mary Blvd Ste 100",
    "sg:city":"Lake Mary",
    "sg:classifiers":[
        {
            "category":"Health Services",
            "subcategory":"Doctor",
            "type":"Services"
        }
    ],
    "sg:phone":"+1 407 302 3115",
    "sg:postcode":"32746",
    "sg:province":"FL",
    "wof:name":"Bougoulias Michael MD Family Medicine",
    "wof:placetype":"venue"
},
  "geometry": {"coordinates":[-81.33610299999999,28.756497],"type":"Point"}
}