{
  "type": "Feature",
  "properties": {
    "iso:country":"US",
    "sg:address":"201 Kings Ridge Loop",
    "sg:city":"Davenport",
    "sg:classifiers":[
        {
            "category":"Building & Trades",
            "subcategory":"Construction",
            "type":"Services"
        }
    ],
    "sg:phone":"+1 407 427 6608",
    "sg:postcode":"33897",
    "sg:province":"FL",
    "sg:tags":[
        "home",
        "trucking-light",
        "hauling",
        "improvement"
    ],
    "wof:name":"Pack Rat Hauling",
    "wof:placetype":"venue"
},
  "geometry": {"coordinates":[-81.664804,28.298239],"type":"Point"}
}