{
  "type": "Feature",
  "properties": {
    "iso:country":"US",
    "sg:address":"250 S 62nd Ave",
    "sg:city":"Hollywood",
    "sg:classifiers":[
        {
            "category":"Shopping",
            "subcategory":"Florist",
            "type":"Retail Goods"
        }
    ],
    "sg:phone":"+1 954 986 4442",
    "sg:postcode":"33023",
    "sg:province":"FL",
    "wof:name":"A B C Flowers",
    "wof:placetype":"venue"
},
  "geometry": {"coordinates":[-80.211572,26.008672],"type":"Point"}
}