{
  "type": "Feature",
  "properties": {
    "addr:full":"1350 Barth Rd Molino FL 32577",
    "addr:housenumber":"1350",
    "addr:postcode":"32577",
    "addr:street":"Barth Rd",
    "iso:country":"US",
    "sg:address":"1350 Barth Rd",
    "sg:city":"Molino",
    "sg:classifiers":[
        {
            "category":"Place Of Worship",
            "subcategory":"Church",
            "type":"Public Place"
        },
        {
            "category":"Place Of Worship",
            "type":"Public Place"
        }
    ],
    "sg:phone":"+1 850 587 5356",
    "sg:postcode":"32577",
    "sg:province":"FL",
    "sg:tags":[
        "churches-baptist-general",
        "churches-baptist"
    ],
    "wof:name":"White Lily Baptist Church",
    "wof:placetype":"venue"
},
  "geometry": {"coordinates":[-87.333572,30.761707],"type":"Point"}
}