{
  "type": "Feature",
  "properties": {
    "iso:country":"US",
    "sg:address":"2187 Chenille Ct",
    "sg:city":"Venice",
    "sg:classifiers":[
        {
            "category":"Banks & Credit Unions",
            "subcategory":"Financial Services",
            "type":"Services"
        }
    ],
    "sg:phone":"+1 941 375 8385",
    "sg:postcode":"34292",
    "sg:province":"FL",
    "sg:tags":[
        "purchasing"
    ],
    "wof:name":"Burke Enterprises",
    "wof:placetype":"venue"
},
  "geometry": {"coordinates":[-82.343299,27.08951],"type":"Point"}
}