{
  "type": "Feature",
  "properties": {
    "iso:country":"US",
    "sg:address":"5795 SW 45th St",
    "sg:city":"Fort Lauderdale",
    "sg:classifiers":[
        {
            "category":"Professional",
            "subcategory":"Management & Consulting",
            "type":"Services"
        }
    ],
    "sg:phone":"+1 954 581 2639",
    "sg:postcode":"33314",
    "sg:province":"FL",
    "wof:name":"American Express",
    "wof:placetype":"venue"
},
  "geometry": {"coordinates":[-80.224208,26.065966],"type":"Point"}
}