{
  "type": "Feature",
  "properties": {
    "addr:full":"4317 Venice Dr Land O Lakes FL 34639",
    "addr:housenumber":"4317",
    "addr:postcode":"34639",
    "addr:street":"Venice Dr",
    "iso:country":"US",
    "sg:address":"4317 Venice Dr",
    "sg:city":"Land O Lakes",
    "sg:classifiers":[
        {
            "category":"Retail",
            "subcategory":"Veterinary Services",
            "type":"Services"
        }
    ],
    "sg:phone":"+1 813 995 0501",
    "sg:postcode":"34639",
    "sg:province":"FL",
    "wof:name":"J A Gibson Dvm PA",
    "wof:placetype":"venue"
},
  "geometry": {"coordinates":[-82.433652,28.221594],"type":"Point"}
}