{
  "type": "Feature",
  "properties": {
    "addr:full":"110 Wood Ln Delray Beach FL 33444",
    "addr:housenumber":"110",
    "addr:postcode":"33444",
    "addr:street":"Wood Ln",
    "iso:country":"US",
    "sg:address":"110 Wood Ln",
    "sg:city":"Delray Beach",
    "sg:classifiers":[
        {
            "category":"Organizations",
            "subcategory":"Community Association",
            "type":"Services"
        }
    ],
    "sg:phone":"+1 561 276 2371",
    "sg:postcode":"33444",
    "sg:province":"FL",
    "wof:name":"Ye Little Wood Homeowners",
    "wof:placetype":"venue"
},
  "geometry": {"coordinates":[-80.075101,26.471243],"type":"Point"}
}