{
  "type": "Feature",
  "properties": {
    "iso:country":"US",
    "sg:address":"6720 NW 188th Ter",
    "sg:city":"Hialeah",
    "sg:classifiers":[
        {
            "category":"Professional",
            "type":"Services"
        }
    ],
    "sg:phone":"+1 305 624 6721",
    "sg:postcode":"33015",
    "sg:province":"FL",
    "wof:name":"Chalas Inc",
    "wof:placetype":"venue"
},
  "geometry": {"coordinates":[-80.307148,25.94459],"type":"Point"}
}