{
  "type": "Feature",
  "properties": {
    "iso:country":"US",
    "sg:address":"201 S Chickasaw Trl",
    "sg:city":"Orlando",
    "sg:classifiers":[
        {
            "category":"Banks & Credit Unions",
            "subcategory":"Investment Brokerage",
            "type":"Services"
        }
    ],
    "sg:phone":"+1 407 275 7590",
    "sg:postcode":"32825",
    "sg:province":"FL",
    "sg:tags":[
        "sorting",
        "bill",
        "wrapping",
        "machine",
        "coin",
        "counting"
    ],
    "wof:name":"Coinstar",
    "wof:placetype":"venue"
},
  "geometry": {"coordinates":[-81.27742600000001,28.540752],"type":"Point"}
}