{
  "type": "Feature",
  "properties": {
    "iso:country":"US",
    "sg:address":"303 Adams Ave",
    "sg:city":"Cape Canaveral",
    "sg:classifiers":[
        {
            "category":"Shopping",
            "subcategory":"Clothing, Apparel, & Fashions",
            "type":"Retail Goods"
        }
    ],
    "sg:phone":"+1 321 783 5731",
    "sg:postcode":"32920",
    "sg:province":"FL",
    "wof:name":"J T Sportswear",
    "wof:placetype":"venue"
},
  "geometry": {"coordinates":[-80.601378,28.390404],"type":"Point"}
}