{
  "type": "Feature",
  "properties": {
    "iso:country":"US",
    "sg:address":"9406 S Suncoast Blvd",
    "sg:city":"Homosassa",
    "sg:classifiers":[
        {
            "category":"Autos & Motor Vehicles",
            "subcategory":"Fuel & Gas Station",
            "type":"Retail Goods"
        }
    ],
    "sg:phone":"+1 352 382 7400",
    "sg:postcode":"34446",
    "sg:province":"FL",
    "sg:tags":[
        "oil"
    ],
    "wof:name":"Shell 2003",
    "wof:placetype":"venue"
},
  "geometry": {"coordinates":[-82.553009,28.729427],"type":"Point"}
}