{
  "type": "Feature",
  "properties": {
    "iso:country":"US",
    "sg:address":"222 W Comstock Ave Ste 210",
    "sg:city":"Winter Park",
    "sg:classifiers":[
        {
            "category":"Professional",
            "subcategory":"Lawyer & Legal Services",
            "type":"Services"
        }
    ],
    "sg:phone":"+1 407 599 4433",
    "sg:postcode":"32789",
    "sg:province":"FL",
    "sg:tags":[
        "divorce",
        "law",
        "family"
    ],
    "wof:name":"Mark Lang & Associates Attys",
    "wof:placetype":"venue"
},
  "geometry": {"coordinates":[-81.352501,28.594],"type":"Point"}
}