{
  "type": "Feature",
  "properties": {
    "addr:full":"18911 S Tamiami Trl Fort Myers FL 33908",
    "addr:housenumber":"18911",
    "addr:postcode":"fl 33908",
    "addr:street":"S Tamiami Trl",
    "iso:country":"US",
    "sg:address":"18911 S Tamiami Trl",
    "sg:city":"Fort Myers",
    "sg:classifiers":[
        {
            "category":"Personal",
            "subcategory":"Beauty Salon",
            "type":"Services"
        }
    ],
    "sg:phone":"+1 239 415 3506",
    "sg:postcode":"33908",
    "sg:province":"FL",
    "sg:tags":[
        "shop"
    ],
    "wof:name":"K Nails",
    "wof:placetype":"venue"
},
  "geometry": {"coordinates":[-81.831678,26.464651],"type":"Point"}
}