{
  "type": "Feature",
  "properties": {
    "iso:country":"US",
    "sg:address":"500 E Kennedy Blvd",
    "sg:city":"Tampa",
    "sg:classifiers":[
        {
            "category":"Professional",
            "subcategory":"Lawyer & Legal Services",
            "type":"Services"
        }
    ],
    "sg:phone":"+1 813 272 1259",
    "sg:postcode":"33602",
    "sg:province":"FL",
    "wof:name":"Koch & Associates PA",
    "wof:placetype":"venue"
},
  "geometry": {"coordinates":[-82.455409,27.948556],"type":"Point"}
}