{
  "type": "Feature",
  "properties": {
    "iso:country":"US",
    "sg:address":"3024 Addie Ln",
    "sg:city":"Jacksonville",
    "sg:classifiers":[
        {
            "category":"Retail",
            "subcategory":"Auto Repair",
            "type":"Services"
        }
    ],
    "sg:phone":"+1 904 262 2088",
    "sg:postcode":"32223",
    "sg:province":"FL",
    "sg:tags":[
        "body",
        "automobile",
        "painting"
    ],
    "wof:name":"Dent Removal By Premier Mobile",
    "wof:placetype":"venue"
},
  "geometry": {"coordinates":[-81.629193,30.163522],"type":"Point"}
}