{
  "type": "Feature",
  "properties": {
    "addr:full":"18744 Cortez Blvd Brooksville FL 34601",
    "addr:housenumber":"18744",
    "addr:postcode":"34601",
    "addr:street":"Cortez Blvd",
    "iso:country":"US",
    "sg:address":"18744 Cortez Blvd",
    "sg:city":"Brooksville",
    "sg:phone":"+1 352 796 7638",
    "sg:postcode":"34601",
    "sg:province":"FL",
    "sg:tags":[
        "oil"
    ],
    "wof:name":"Hernando Oil Co",
    "wof:placetype":"venue"
},
  "geometry": {"coordinates":[-82.420666,28.550376],"type":"Point"}
}