{
  "type": "Feature",
  "properties": {
    "addr:full":"235 NE 6th Ave Delray Beach FL 33483",
    "addr:housenumber":"235",
    "addr:postcode":"33483",
    "addr:street":"Ne 6Th Ave",
    "iso:country":"US",
    "sg:address":"235 NE 6th Ave",
    "sg:city":"Delray Beach",
    "sg:classifiers":[
        {
            "category":"Manufacturing",
            "subcategory":"Printing",
            "type":"Manufacturing & Wholesale Goods"
        }
    ],
    "sg:phone":"+1 561 266 9686",
    "sg:postcode":"33483",
    "sg:province":"FL",
    "sg:tags":[
        "publisher"
    ],
    "wof:name":"Ampersand Publishing Co Inc",
    "wof:placetype":"venue"
},
  "geometry": {"coordinates":[-80.067058,26.466506],"type":"Point"}
}