{
  "type": "Feature",
  "properties": {
    "addr:full":"2560 US Hwy 1 S St Augustine FL 32086",
    "addr:housenumber":"2560",
    "addr:postcode":"32086",
    "addr:street":"Us Hwy 1 S St",
    "iso:country":"US",
    "sg:address":"2560 US Hwy 1 S",
    "sg:city":"St Augustine",
    "sg:classifiers":[
        {
            "category":"Autos & Motor Vehicles",
            "subcategory":"Automobile Sales",
            "type":"Retail Goods"
        }
    ],
    "sg:phone":"+1 904 794 9666",
    "sg:postcode":"32086",
    "sg:province":"FL",
    "sg:tags":[
        "car",
        "dealer"
    ],
    "wof:name":"Cars Metics",
    "wof:placetype":"venue"
},
  "geometry": {"coordinates":[-81.322598,29.849732],"type":"Point"}
}