{
  "type": "Feature",
  "properties": {
    "iso:country":"US",
    "sg:address":"890 N State Rd 7",
    "sg:city":"Hollywood",
    "sg:classifiers":[
        {
            "category":"Shopping",
            "subcategory":"Pharmacy",
            "type":"Retail Goods"
        }
    ],
    "sg:phone":"+1 954 962 0228",
    "sg:postcode":"33021",
    "sg:province":"FL",
    "wof:name":"Walgreens",
    "wof:placetype":"venue"
},
  "geometry": {"coordinates":[-80.207959,26.01679],"type":"Point"}
}