{
  "type": "Feature",
  "properties": {
    "iso:country":"US",
    "sg:address":"3691 Webber St",
    "sg:city":"Sarasota",
    "sg:classifiers":[
        {
            "category":"Health Services",
            "subcategory":"Optometrist",
            "type":"Services"
        },
        {
            "category":"Shopping",
            "subcategory":"Optician",
            "type":"Retail Goods"
        },
        {
            "category":"Health Services",
            "subcategory":"Health Practitioner",
            "type":"Services"
        }
    ],
    "sg:phone":"+1 941 921 2020",
    "sg:postcode":"34232",
    "sg:province":"FL",
    "sg:tags":[
        "physician",
        "ophthalmology",
        "optical",
        "surgeons"
    ],
    "sg:website":"http://www.gulfcoasteyecenter.com",
    "wof:name":"Bovio, Steven OD PA",
    "wof:placetype":"venue"
},
  "geometry": {"coordinates":[-82.49628800000001,27.30827],"type":"Point"}
}