{
  "type": "Feature",
  "properties": {
    "iso:country":"US",
    "sg:address":"846 Riverside Dr",
    "sg:city":"Ormond Beach",
    "sg:classifiers":[
        {
            "category":"Building & Trades",
            "subcategory":"Construction",
            "type":"Services"
        }
    ],
    "sg:phone":"+1 386 673 9664",
    "sg:postcode":"32176",
    "sg:province":"FL",
    "sg:tags":[
        "general",
        "contractor"
    ],
    "wof:name":"Far East Builders",
    "wof:placetype":"venue"
},
  "geometry": {"coordinates":[-81.037402,29.268722],"type":"Point"}
}