{
  "type": "Feature",
  "properties": {
    "iso:country":"US",
    "sg:address":"2308 Tanglewood Dr",
    "sg:city":"Sarasota",
    "sg:classifiers":[
        {
            "category":"Government",
            "subcategory":"Office",
            "type":"Public Place"
        }
    ],
    "sg:phone":"+1 941 720 7791",
    "sg:postcode":"34239",
    "sg:province":"FL",
    "sg:tags":[
        "executive"
    ],
    "wof:name":"Home Smart Central",
    "wof:placetype":"venue"
},
  "geometry": {"coordinates":[-82.50796,27.31224],"type":"Point"}
}