{
  "type": "Feature",
  "properties": {
    "iso:country":"US",
    "sg:address":"17100 Collins Ave",
    "sg:city":"Sunny Isles Bch",
    "sg:classifiers":[
        {
            "category":"Restaurant",
            "type":"Food & Drink"
        }
    ],
    "sg:phone":"+1 305 948 2323",
    "sg:postcode":"33160",
    "sg:province":"FL",
    "wof:name":"Cambalache",
    "wof:placetype":"venue"
},
  "geometry": {"coordinates":[-80.121771,25.934951],"type":"Point"}
}