{
  "type": "Feature",
  "properties": {
    "iso:country":"US",
    "sg:address":"1075 US Hwy 1",
    "sg:city":"Vero Beach",
    "sg:classifiers":[
        {
            "category":"Retail",
            "subcategory":"Auto Repair",
            "type":"Services"
        }
    ],
    "sg:phone":"+1 772 770 9889",
    "sg:postcode":"32960",
    "sg:province":"FL",
    "sg:tags":[
        "repairing",
        "automobile"
    ],
    "sg:website":"www.verobeach.com",
    "wof:name":"Toyota/Scion/KIA Of Vero Beach",
    "wof:placetype":"venue"
},
  "geometry": {"coordinates":[-80.39383599999999,27.632302],"type":"Point"}
}