{
  "type": "Feature",
  "properties": {
    "iso:country":"US",
    "sg:address":"4769 NW 167th St",
    "sg:city":"Opa Locka",
    "sg:classifiers":[
        {
            "category":"Retail",
            "subcategory":"Repair Shop",
            "type":"Services"
        }
    ],
    "sg:phone":"+1 305 620 0670",
    "sg:postcode":"33055",
    "sg:province":"FL",
    "sg:tags":[
        "equipment",
        "electronic",
        "electrical",
        "supply"
    ],
    "wof:name":"Phillips Electronic Service",
    "wof:placetype":"venue"
},
  "geometry": {"coordinates":[-80.27759,25.925622],"type":"Point"}
}