{
  "type": "Feature",
  "properties": {
    "iso:country":"US",
    "sg:address":"13545 SW 63rd Ln",
    "sg:city":"Miami",
    "sg:classifiers":[
        {
            "category":"Shopping",
            "type":"Retail Goods"
        }
    ],
    "sg:phone":"+1 305 382 3588",
    "sg:postcode":"33183",
    "sg:province":"FL",
    "sg:tags":[
        "merchandise"
    ],
    "wof:name":"Graphics Mart Corp.",
    "wof:placetype":"venue"
},
  "geometry": {"coordinates":[-80.412678,25.708242],"type":"Point"}
}