{
  "type": "Feature",
  "properties": {
    "addr:full":"2928 Lowell Ct Casselberry FL 32707",
    "addr:housenumber":"2928",
    "addr:postcode":"32707",
    "addr:street":"Lowell Ct",
    "iso:country":"US",
    "sg:address":"2928 Lowell Ct",
    "sg:city":"Casselberry",
    "sg:classifiers":[
        {
            "category":"Autos & Motor Vehicles",
            "subcategory":"Auto Supplies",
            "type":"Retail Goods"
        }
    ],
    "sg:phone":"+1 401 252 8899",
    "sg:postcode":"32707",
    "sg:province":"FL",
    "sg:tags":[
        "automotive",
        "repair",
        "parking"
    ],
    "wof:name":"Lxc Performance Parts Inc",
    "wof:placetype":"venue"
},
  "geometry": {"coordinates":[-81.307241,28.648918],"type":"Point"}
}