{
  "type": "Feature",
  "properties": {
    "iso:country":"US",
    "sg:address":"8369 Edith Ave",
    "sg:city":"Milton",
    "sg:classifiers":[
        {
            "category":"Wholesale",
            "subcategory":"Machinery & Supplies",
            "type":"Manufacturing & Wholesale Goods"
        }
    ],
    "sg:phone":"+1 850 626 4500",
    "sg:postcode":"32570",
    "sg:province":"FL",
    "sg:tags":[
        "auto",
        "used",
        "motor",
        "vehicle"
    ],
    "wof:name":"Action Surplus & Salvage Inc",
    "wof:placetype":"venue"
},
  "geometry": {"coordinates":[-86.977243,30.669033],"type":"Point"}
}