{
  "type": "Feature",
  "properties": {
    "iso:country":"US",
    "sg:address":"2733 Middle River Dr",
    "sg:city":"Fort Lauderdale",
    "sg:classifiers":[
        {
            "category":"Travel",
            "subcategory":"Hotels & Motels",
            "type":"Entertainment"
        }
    ],
    "sg:phone":"+1 954 565 7775",
    "sg:postcode":"33306",
    "sg:province":"FL",
    "sg:tags":[
        "resort"
    ],
    "wof:name":"Bamboo Resort",
    "wof:placetype":"venue"
},
  "geometry": {"coordinates":[-80.11484299999999,26.162377],"type":"Point"}
}