{
  "type": "Feature",
  "properties": {
    "addr:full":"1803 SW 3rd Ave Okeechobee FL 34974",
    "addr:housenumber":"1803",
    "addr:postcode":"34974",
    "addr:street":"Sw 3Rd Ave",
    "iso:country":"US",
    "sg:address":"1803 SW 3rd Ave",
    "sg:city":"Okeechobee",
    "sg:classifiers":[
        {
            "category":"Organizations",
            "subcategory":"Religious Organization",
            "type":"Services"
        }
    ],
    "sg:phone":"+1 863 763 7770",
    "sg:postcode":"34974",
    "sg:province":"FL",
    "sg:tags":[
        "churches-non-denominational"
    ],
    "wof:name":"Word Of Faith",
    "wof:placetype":"venue"
},
  "geometry": {"coordinates":[-80.832171,27.226588],"type":"Point"}
}