{
  "type": "Feature",
  "properties": {
    "addr:full":"521 N Riverside Dr Pompano Beach FL 33062",
    "addr:housenumber":"521",
    "addr:postcode":"33062",
    "addr:street":"N Riverside Dr",
    "iso:country":"US",
    "sg:address":"521 N Riverside Dr",
    "sg:city":"Pompano Beach",
    "sg:classifiers":[
        {
            "category":"Organizations",
            "subcategory":"Community Association",
            "type":"Services"
        }
    ],
    "sg:phone":"+1 954 781 3600",
    "sg:postcode":"33062",
    "sg:province":"FL",
    "sg:tags":[
        "condo"
    ],
    "wof:name":"Silver Thtch Intrcoastal Condo",
    "wof:placetype":"venue"
},
  "geometry": {"coordinates":[-80.091156,26.240524],"type":"Point"}
}