{
  "type": "Feature",
  "properties": {
    "addr:full":"3723 E Co Hwy 30A Santa Rosa Beach FL 32459",
    "addr:housenumber":"3723",
    "addr:postcode":"32459",
    "addr:street":"E Co Hwy 30A;Rosa",
    "iso:country":"US",
    "sg:address":"3723 E Co Hwy 30A",
    "sg:city":"Santa Rosa Beach",
    "sg:classifiers":[
        {
            "category":"Shopping",
            "subcategory":"Computers & Home Electronics",
            "type":"Retail Goods"
        }
    ],
    "sg:phone":"+1 850 231 1571",
    "sg:postcode":"32459",
    "sg:province":"FL",
    "wof:name":"Seagrove Seacoast Video",
    "wof:placetype":"venue"
},
  "geometry": {"coordinates":[-86.11421300000001,30.313085],"type":"Point"}
}