{
  "type": "Feature",
  "properties": {
    "iso:country":"US",
    "sg:address":"3220 1st St",
    "sg:city":"Bradenton",
    "sg:classifiers":[
        {
            "category":"Health Services",
            "subcategory":"Doctor",
            "type":"Services"
        }
    ],
    "sg:phone":"+1 941 750 6505",
    "sg:postcode":"34208",
    "sg:province":"FL",
    "sg:tags":[
        "dentist"
    ],
    "wof:name":"Bradenton Dental Center",
    "wof:placetype":"venue"
},
  "geometry": {"coordinates":[-82.563056,27.470849],"type":"Point"}
}