{
  "type": "Feature",
  "properties": {
    "iso:country":"US",
    "sg:address":"1026 Snapper Ln",
    "sg:city":"Key Largo",
    "sg:classifiers":[
        {
            "category":"Shopping",
            "type":"Retail Goods"
        }
    ],
    "sg:phone":"+1 305 853 8052",
    "sg:postcode":"33037",
    "sg:province":"FL",
    "sg:tags":[
        "equipment",
        "electronic"
    ],
    "wof:name":"Interserve",
    "wof:placetype":"venue"
},
  "geometry": {"coordinates":[-80.48625800000001,25.047082],"type":"Point"}
}