{
  "type": "Feature",
  "properties": {
    "iso:country":"US",
    "sg:address":"113 Cavalier St",
    "sg:city":"Palm Bay",
    "sg:classifiers":[
        {
            "category":"Building & Trades",
            "subcategory":"Landscaping Services",
            "type":"Services"
        }
    ],
    "sg:phone":"+1 321 729 6368",
    "sg:postcode":"32909",
    "sg:province":"FL",
    "wof:name":"Richies Lawn Serv",
    "wof:placetype":"venue"
},
  "geometry": {"coordinates":[-80.649646,27.870239],"type":"Point"}
}