{
  "type": "Feature",
  "properties": {
    "iso:country":"US",
    "sg:address":"1076 Creekford Dr",
    "sg:city":"Fort Lauderdale",
    "sg:classifiers":[
        {
            "category":"Health Services",
            "subcategory":"Clinic",
            "type":"Services"
        }
    ],
    "sg:phone":"+1 954 384 8959",
    "sg:postcode":"33326",
    "sg:province":"FL",
    "wof:name":"Senter For Health & Rehab Inc",
    "wof:placetype":"venue"
},
  "geometry": {"coordinates":[-80.36619,26.107789],"type":"Point"}
}