{
  "type": "Feature",
  "properties": {
    "iso:country":"US",
    "sg:address":"15427 N Dale Mabry Hwy",
    "sg:city":"Tampa",
    "sg:classifiers":[
        {
            "category":"Health Services",
            "subcategory":"Clinic",
            "type":"Services"
        }
    ],
    "sg:phone":"+1 813 964 1354",
    "sg:postcode":"33618",
    "sg:province":"FL",
    "wof:name":"Florida Blood Svc",
    "wof:placetype":"venue"
},
  "geometry": {"coordinates":[-82.502533,28.090785],"type":"Point"}
}