{
  "type": "Feature",
  "properties": {
    "iso:country":"US",
    "sg:address":"3633 Cocoplum Cir",
    "sg:city":"Pompano Beach",
    "sg:classifiers":[
        {
            "category":"Wholesale",
            "subcategory":"Metals & Minerals",
            "type":"Manufacturing & Wholesale Goods"
        }
    ],
    "sg:phone":"+1 954 956 7485",
    "sg:postcode":"33063",
    "sg:province":"FL",
    "sg:tags":[
        "center"
    ],
    "wof:name":"F & J Steel Detailing Inc",
    "wof:placetype":"venue"
},
  "geometry": {"coordinates":[-80.190004,26.267688],"type":"Point"}
}