{
  "type": "Feature",
  "properties": {
    "iso:country":"US",
    "sg:address":"150 Roy Court Cir",
    "sg:city":"West Palm Beach",
    "sg:classifiers":[
        {
            "category":"Communications",
            "type":"Services"
        }
    ],
    "sg:phone":"+1 561 790 2004",
    "sg:postcode":"33411",
    "sg:province":"FL",
    "sg:tags":[
        "communication"
    ],
    "wof:name":"Media Works",
    "wof:placetype":"venue"
},
  "geometry": {"coordinates":[-80.23079799999999,26.726232],"type":"Point"}
}