{
  "type": "Feature",
  "properties": {
    "addr:full":"2201 S Ocean Dr Hollywood FL 33019",
    "addr:housenumber":"2201",
    "addr:postcode":"33019",
    "addr:street":"S Ocean Dr",
    "iso:country":"US",
    "sg:address":"2201 S Ocean Dr",
    "sg:city":"Hollywood",
    "sg:classifiers":[
        {
            "category":"Manufacturing",
            "subcategory":"Furniture",
            "type":"Manufacturing & Wholesale Goods"
        }
    ],
    "sg:phone":"+1 954 881 3124",
    "sg:postcode":"33019",
    "sg:province":"FL",
    "sg:tags":[
        "household",
        "wood",
        "mfg"
    ],
    "wof:name":"In2cad Inc",
    "wof:placetype":"venue"
},
  "geometry": {"coordinates":[-80.117957,25.998963],"type":"Point"}
}