{
  "type": "Feature",
  "properties": {
    "iso:country":"US",
    "sg:address":"36 W Crystal Lake St",
    "sg:city":"Orlando",
    "sg:classifiers":[
        {
            "category":"Retail",
            "subcategory":"Auto Repair",
            "type":"Services"
        }
    ],
    "sg:phone":"+1 407 425 0211",
    "sg:postcode":"32806",
    "sg:province":"FL",
    "sg:tags":[
        "repairing",
        "automobile"
    ],
    "wof:name":"R & S Performance",
    "wof:placetype":"venue"
},
  "geometry": {"coordinates":[-81.379762,28.514638],"type":"Point"}
}