{
  "type": "Feature",
  "properties": {
    "iso:country":"US",
    "sg:address":"5928 Corson Pl",
    "sg:city":"Lake Worth",
    "sg:classifiers":[
        {
            "category":"Building & Trades",
            "subcategory":"Construction",
            "type":"Services"
        }
    ],
    "sg:phone":"+1 561 541 6817",
    "sg:postcode":"33463",
    "sg:province":"FL",
    "sg:tags":[
        "maintenance",
        "contractor"
    ],
    "wof:name":"Aris Desir Maintenance",
    "wof:placetype":"venue"
},
  "geometry": {"coordinates":[-80.137845,26.601632],"type":"Point"}
}