{
  "type": "Feature",
  "properties": {
    "addr:full":"2080 Griffin Rd Fort Lauderdale FL 33312",
    "addr:housenumber":"2080",
    "addr:postcode":"33312",
    "addr:street":"Griffin Rd",
    "iso:country":"US",
    "sg:address":"2080 Griffin Rd",
    "sg:city":"Fort Lauderdale",
    "sg:classifiers":[
        {
            "category":"Autos & Motor Vehicles",
            "subcategory":"Fuel & Gas Station",
            "type":"Retail Goods"
        }
    ],
    "sg:phone":"+1 954 962 2777",
    "sg:postcode":"33312",
    "sg:province":"FL",
    "sg:tags":[
        "oil"
    ],
    "wof:name":"2080 Griffin Rd Amoco",
    "wof:placetype":"venue"
},
  "geometry": {"coordinates":[-80.16779699999999,26.062642],"type":"Point"}
}