{
  "type": "Feature",
  "properties": {
    "addr:full":"3100 Gulf To Bay Blvd Clearwater FL 33759",
    "addr:housenumber":"3100",
    "addr:postcode":"33759",
    "addr:street":"Gulf To Bay Blvd",
    "iso:country":"US",
    "sg:address":"3100 Gulf To Bay Blvd",
    "sg:city":"Clearwater",
    "sg:classifiers":[
        {
            "category":"Taxi",
            "type":"Transportation"
        }
    ],
    "sg:phone":"+1 727 442 3333",
    "sg:postcode":"33759",
    "sg:province":"FL",
    "sg:tags":[
        "taxicab"
    ],
    "wof:name":"Budget Taxi",
    "wof:placetype":"venue"
},
  "geometry": {"coordinates":[-82.709943,27.960687],"type":"Point"}
}