{
  "type": "Feature",
  "properties": {
    "iso:country":"US",
    "sg:address":"5117 Imperial Cove Rd",
    "sg:city":"Jacksonville",
    "sg:classifiers":[
        {
            "category":"Building & Trades",
            "subcategory":"Landscaping Services",
            "type":"Services"
        }
    ],
    "sg:phone":"+1 904 778 9691",
    "sg:postcode":"32210",
    "sg:province":"FL",
    "sg:tags":[
        "landscape"
    ],
    "wof:name":"Foxy Foliage Inc",
    "wof:placetype":"venue"
},
  "geometry": {"coordinates":[-81.701509,30.250433],"type":"Point"}
}