{
  "type": "Feature",
  "properties": {
    "addr:full":"561 NE 87th St Miami FL 33138",
    "addr:housenumber":"561",
    "addr:postcode":"33138",
    "addr:street":"Ne 87Th St",
    "iso:country":"US",
    "sg:address":"561 NE 87th St",
    "sg:city":"Miami",
    "sg:classifiers":[
        {
            "category":"Personal",
            "subcategory":"Beauty Salon",
            "type":"Services"
        }
    ],
    "sg:phone":"+1 305 758 2144",
    "sg:postcode":"33138",
    "sg:province":"FL",
    "sg:tags":[
        "shop"
    ],
    "wof:name":"Beautiful Touch",
    "wof:placetype":"venue"
},
  "geometry": {"coordinates":[-80.18702500000001,25.855205],"type":"Point"}
}