{
  "type": "Feature",
  "properties": {
    "iso:country":"US",
    "sg:address":"503 N Palmer St",
    "sg:city":"Plant City",
    "sg:classifiers":[
        {
            "category":"Organizations",
            "subcategory":"Religious Organization",
            "type":"Services"
        }
    ],
    "sg:phone":"+1 813 752 4104",
    "sg:postcode":"33563",
    "sg:province":"FL",
    "sg:tags":[
        "child",
        "day",
        "care"
    ],
    "wof:name":"First Batist Church Plant City",
    "wof:placetype":"venue"
},
  "geometry": {"coordinates":[-82.123133,28.018501],"type":"Point"}
}