{
  "type": "Feature",
  "properties": {
    "addr:full":"221 Longview Ave Kissimmee FL 34747",
    "addr:housenumber":"221",
    "addr:postcode":"34747",
    "addr:street":"Longview Ave",
    "iso:country":"US",
    "sg:address":"221 Longview Ave",
    "sg:city":"Kissimmee",
    "sg:classifiers":[
        {
            "category":"Building & Trades",
            "subcategory":"Locksmith",
            "type":"Services"
        }
    ],
    "sg:phone":"+1 321 939 0637",
    "sg:postcode":"34747",
    "sg:province":"FL",
    "sg:tags":[
        "key"
    ],
    "wof:name":"Lake Nona Locksmith",
    "wof:placetype":"venue"
},
  "geometry": {"coordinates":[-81.527315,28.328018],"type":"Point"}
}