{
  "type": "Feature",
  "properties": {
    "iso:country":"US",
    "sg:address":"685 N Atlantic Ave",
    "sg:city":"Cocoa Beach",
    "sg:classifiers":[
        {
            "category":"Building & Trades",
            "subcategory":"Construction",
            "type":"Services"
        }
    ],
    "sg:phone":"+1 321 784 2250",
    "sg:postcode":"32931",
    "sg:province":"FL",
    "sg:tags":[
        "coping",
        "plastering",
        "tiling",
        "pool",
        "swimming"
    ],
    "wof:name":"Ashley's Motor & Pump",
    "wof:placetype":"venue"
},
  "geometry": {"coordinates":[-80.610268,28.328176],"type":"Point"}
}