{
  "type": "Feature",
  "properties": {
    "addr:full":"802 Ingraham Ave Haines City FL 33844",
    "addr:housenumber":"802",
    "addr:postcode":"33844",
    "addr:street":"Ingraham Ave",
    "iso:country":"US",
    "sg:address":"802 Ingraham Ave",
    "sg:city":"Haines City",
    "sg:classifiers":[
        {
            "category":"Food & Beverages",
            "subcategory":"Groceries & Convenience Stores",
            "type":"Retail Goods"
        }
    ],
    "sg:phone":"+1 863 421 2664",
    "sg:postcode":"33844",
    "sg:province":"FL",
    "wof:name":"Sacketts",
    "wof:placetype":"venue"
},
  "geometry": {"coordinates":[-81.624168,28.109677],"type":"Point"}
}