{
  "type": "Feature",
  "properties": {
    "iso:country":"US",
    "sg:address":"735 Grove Ave",
    "sg:city":"Orlando",
    "sg:classifiers":[
        {
            "category":"Personal",
            "type":"Services"
        }
    ],
    "sg:phone":"+1 407 722 9998",
    "sg:postcode":"32805",
    "sg:province":"FL",
    "sg:tags":[
        "car",
        "loading",
        "unloading"
    ],
    "wof:name":"Immaulate Movers",
    "wof:placetype":"venue"
},
  "geometry": {"coordinates":[-81.395802,28.534089],"type":"Point"}
}