{
  "type": "Feature",
  "properties": {
    "iso:country":"US",
    "sg:address":"4039 Eagle Ridge Rd",
    "sg:city":"Fruitland Park",
    "sg:classifiers":[
        {
            "category":"Shopping",
            "subcategory":"Crafts & Fabrics",
            "type":"Retail Goods"
        }
    ],
    "sg:phone":"+1 352 728 1824",
    "sg:postcode":"34731",
    "sg:province":"FL",
    "sg:tags":[
        "sewing"
    ],
    "wof:name":"Angelthreads",
    "wof:placetype":"venue"
},
  "geometry": {"coordinates":[-81.88637799999999,28.88919],"type":"Point"}
}