{
  "type": "Feature",
  "properties": {
    "addr:full":"33143 US Hwy 19 N Palm Harbor FL 34684",
    "addr:postcode":"33143;34684",
    "addr:street":"Us Hwy 19 N",
    "iso:country":"US",
    "sg:address":"33143 US Hwy 19 N",
    "sg:city":"Palm Harbor",
    "sg:classifiers":[
        {
            "category":"Health Services",
            "subcategory":"Doctor",
            "type":"Services"
        }
    ],
    "sg:phone":"+1 727 785 8273",
    "sg:postcode":"34684",
    "sg:province":"FL",
    "wof:name":"Absolute Dental Care",
    "wof:placetype":"venue"
},
  "geometry": {"coordinates":[-82.738795,28.068458],"type":"Point"}
}