{
  "type": "Feature",
  "properties": {
    "addr:full":"13184 Heather Moss Dr Orlando FL 32837",
    "addr:housenumber":"13184",
    "addr:postcode":"32837",
    "addr:street":"Heather Moss Dr",
    "iso:country":"US",
    "sg:address":"13184 Heather Moss Dr",
    "sg:city":"Orlando",
    "sg:classifiers":[
        {
            "category":"Real Estate",
            "subcategory":"Real Estate Operator",
            "type":"Services"
        }
    ],
    "sg:phone":"+1 407 852 0101",
    "sg:postcode":"32837",
    "sg:province":"FL",
    "sg:tags":[
        "building",
        "apartment"
    ],
    "wof:name":"Colonial Grand At Heather Glen",
    "wof:placetype":"venue"
},
  "geometry": {"coordinates":[-81.431648,28.369523],"type":"Point"}
}