{
  "type": "Feature",
  "properties": {
    "addr:full":"8167 Hwy 90 Sneads FL 32460",
    "addr:housenumber":"8167",
    "addr:postcode":"32460",
    "addr:street":"Hwy 90",
    "iso:country":"US",
    "sg:address":"8167 Hwy 90",
    "sg:city":"Sneads",
    "sg:classifiers":[
        {
            "category":"Shopping",
            "subcategory":"Gifts & Souvenirs",
            "type":"Retail Goods"
        }
    ],
    "sg:phone":"+1 850 593 4438",
    "sg:postcode":"32460",
    "sg:province":"FL",
    "wof:name":"Designs Unlimited",
    "wof:placetype":"venue"
},
  "geometry": {"coordinates":[-84.90121499999999,30.708452],"type":"Point"}
}