{
  "type": "Feature",
  "properties": {
    "iso:country":"US",
    "sg:address":"2505 9th St W",
    "sg:city":"Bradenton",
    "sg:classifiers":[
        {
            "category":"Shopping",
            "subcategory":"Jewelry",
            "type":"Retail Goods"
        }
    ],
    "sg:phone":"+1 941 746 3274",
    "sg:postcode":"34205",
    "sg:province":"FL",
    "sg:tags":[
        "jeweler"
    ],
    "wof:name":"Joyeria Hispana",
    "wof:placetype":"venue"
},
  "geometry": {"coordinates":[-82.571179,27.477199],"type":"Point"}
}