{
  "type": "Feature",
  "properties": {
    "addr:full":"103 W Morgan St Brandon FL 33510",
    "addr:housenumber":"103",
    "addr:postcode":"33510",
    "addr:street":"W Morgan St",
    "iso:country":"US",
    "sg:address":"103 W Morgan St",
    "sg:city":"Brandon",
    "sg:classifiers":[
        {
            "category":"Personal",
            "subcategory":"Shoe Repair & Shine",
            "type":"Services"
        }
    ],
    "sg:phone":"+1 813 681 9327",
    "sg:postcode":"33510",
    "sg:province":"FL",
    "sg:tags":[
        "parlor"
    ],
    "wof:name":"Yi-Ole-Cobbler",
    "wof:placetype":"venue"
},
  "geometry": {"coordinates":[-82.28701100000001,27.940056],"type":"Point"}
}