{
  "type": "Feature",
  "properties": {
    "addr:full":"1700 SE 17th St Ocala FL 34471",
    "addr:housenumber":"1700",
    "addr:postcode":"34471",
    "addr:street":"Se 17Th St",
    "iso:country":"US",
    "sg:address":"1700 SE 17th St",
    "sg:city":"Ocala",
    "sg:classifiers":[
        {
            "category":"Banks & Credit Unions",
            "subcategory":"Investment Brokerage",
            "type":"Services"
        }
    ],
    "sg:phone":"+1 352 854 4148",
    "sg:postcode":"34471",
    "sg:province":"FL",
    "sg:tags":[
        "security"
    ],
    "wof:name":"AmSouth",
    "wof:placetype":"venue"
},
  "geometry": {"coordinates":[-82.113935,29.171605],"type":"Point"}
}