{
  "type": "Feature",
  "properties": {
    "addr:full":"15176 Landmark Cir S Jacksonville FL 32226",
    "addr:housenumber":"15176",
    "addr:postcode":"32226",
    "addr:street":"Landmark Cir S",
    "iso:country":"US",
    "sg:address":"15176 Landmark Cir S",
    "sg:city":"Jacksonville",
    "sg:classifiers":[
        {
            "category":"Professional",
            "subcategory":"Computer Services",
            "type":"Services"
        }
    ],
    "sg:phone":"+1 904 714 3674",
    "sg:postcode":"32226",
    "sg:province":"FL",
    "sg:tags":[
        "internet"
    ],
    "wof:name":"CBM Flash Websites",
    "wof:placetype":"venue"
},
  "geometry": {"coordinates":[-81.574062,30.517317],"type":"Point"}
}