{
  "type": "Feature",
  "properties": {
    "iso:country":"US",
    "sg:address":"9175 NW 40th Pl",
    "sg:city":"Sunrise",
    "sg:classifiers":[
        {
            "category":"Airline",
            "type":"Transportation"
        },
        {
            "category":"Travel",
            "subcategory":"Travel Agent",
            "type":"Entertainment"
        }
    ],
    "sg:phone":"+1 954 746 4233",
    "sg:postcode":"33351",
    "sg:province":"FL",
    "sg:tags":[
        "ticket",
        "agency"
    ],
    "wof:name":"Family Vacations",
    "wof:placetype":"venue"
},
  "geometry": {"coordinates":[-80.272859,26.175079],"type":"Point"}
}