{
  "type": "Feature",
  "properties": {
    "iso:country":"US",
    "sg:address":"4145 Fairford Dr",
    "sg:city":"New Port Richey",
    "sg:classifiers":[
        {
            "category":"Government",
            "subcategory":"Office",
            "type":"Public Place"
        },
        {
            "category":"Recreation",
            "type":"Entertainment"
        }
    ],
    "sg:phone":"+1 727 834 3286",
    "sg:postcode":"34652",
    "sg:province":"FL",
    "sg:tags":[
        "conservation",
        "parks"
    ],
    "wof:name":"Grove Park Community Center",
    "wof:placetype":"venue"
},
  "geometry": {"coordinates":[-82.733386,28.218944],"type":"Point"}
}