{
  "type": "Feature",
  "properties": {
    "addr:full":"3320 N W St Pensacola FL 32505",
    "addr:housenumber":"3320",
    "addr:postcode":"32505",
    "addr:street":"N W St",
    "iso:country":"US",
    "sg:address":"3320 N W St",
    "sg:city":"Pensacola",
    "sg:classifiers":[
        {
            "category":"Manufacturing",
            "subcategory":"Rubber & Plastics",
            "type":"Manufacturing & Wholesale Goods"
        },
        {
            "category":"Wholesale",
            "subcategory":"Machinery & Supplies",
            "type":"Manufacturing & Wholesale Goods"
        },
        {
            "category":"Professional",
            "subcategory":"Employment Agencies",
            "type":"Services"
        },
        {
            "category":"Shopping",
            "subcategory":"Crafts & Fabrics",
            "type":"Retail Goods"
        }
    ],
    "sg:phone":"+1 850 439 6544",
    "sg:postcode":"32505",
    "sg:province":"FL",
    "sg:tags":[
        "shop",
        "upholstery",
        "upholsterer",
        "foam",
        "supply-wholesale",
        "sponge",
        "manufacturer"
    ],
    "wof:name":"Grant's Foam & Fabric",
    "wof:placetype":"venue"
},
  "geometry": {"coordinates":[-87.24867,30.445263],"type":"Point"}
}