{
  "type": "Feature",
  "properties": {
    "iso:country":"US",
    "sg:address":"11201 Fisher Old Miller Rd",
    "sg:city":"Milton",
    "sg:classifiers":[
        {
            "category":"Professional",
            "type":"Services"
        }
    ],
    "sg:phone":"+1 850 626 2156",
    "sg:postcode":"32583",
    "sg:province":"FL",
    "wof:name":"Mark Kelly Inc",
    "wof:placetype":"venue"
},
  "geometry": {"coordinates":[-86.846765,30.626909],"type":"Point"}
}