{
  "type": "Feature",
  "properties": {
    "addr:full":"3141 SE Morningside Blvd Port Saint Lucie FL 34952",
    "addr:housenumber":"3141",
    "addr:postcode":"34952",
    "addr:street":"Se Morningside Blvd",
    "iso:country":"US",
    "sg:address":"3141 SE Morningside Blvd",
    "sg:city":"Port Saint Lucie",
    "sg:classifiers":[
        {
            "category":"Freight",
            "type":"Transportation"
        }
    ],
    "sg:phone":"+1 772 337 0000",
    "sg:postcode":"34952",
    "sg:province":"FL",
    "sg:tags":[
        "operator",
        "local",
        "trucking"
    ],
    "wof:name":"EZ Haulers Inc",
    "wof:placetype":"venue"
},
  "geometry": {"coordinates":[-80.315314,27.245635],"type":"Point"}
}