{
  "type": "Feature",
  "properties": {
    "iso:country":"US",
    "sg:address":"10235 W Sample Rd",
    "sg:city":"Coral Springs",
    "sg:classifiers":[
        {
            "category":"Insurance",
            "subcategory":"Insurance Agent",
            "type":"Services"
        }
    ],
    "sg:phone":"+1 954 753 0980",
    "sg:postcode":"33065",
    "sg:province":"FL",
    "sg:tags":[
        "agency"
    ],
    "wof:name":"Bill Daly Insurance Agency",
    "wof:placetype":"venue"
},
  "geometry": {"coordinates":[-80.263018,26.272692],"type":"Point"}
}