{
  "type": "Feature",
  "properties": {
    "iso:country":"US",
    "sg:address":"5519 Nettie Rd",
    "sg:city":"Jacksonville",
    "sg:classifiers":[
        {
            "category":"Manufacturing",
            "subcategory":"Printing",
            "type":"Manufacturing & Wholesale Goods"
        }
    ],
    "sg:phone":"+1 904 733 1392",
    "sg:postcode":"32207",
    "sg:province":"FL",
    "sg:tags":[
        "publishing"
    ],
    "wof:name":"Olpl of Jax FL Inc",
    "wof:placetype":"venue"
},
  "geometry": {"coordinates":[-81.631716,30.261159],"type":"Point"}
}