{
  "type": "Feature",
  "properties": {
    "iso:country":"US",
    "sg:address":"316 California Ave",
    "sg:city":"St Cloud",
    "sg:classifiers":[
        {
            "category":"Building & Trades",
            "subcategory":"Landscaping Services",
            "type":"Services"
        }
    ],
    "sg:phone":"+1 407 892 4926",
    "sg:postcode":"34769",
    "sg:province":"FL",
    "sg:tags":[
        "lawn",
        "maintenance",
        "grounds"
    ],
    "wof:name":"Matt Wilkes Lawn Care",
    "wof:placetype":"venue"
},
  "geometry": {"coordinates":[-81.294798,28.255233],"type":"Point"}
}