{
  "type": "Feature",
  "properties": {
    "addr:full":"5009 Turnpike Feeder Rd Fort Pierce FL 34951",
    "addr:housenumber":"5009",
    "addr:postcode":"34951",
    "addr:street":"Turnpike Feeder Rd",
    "iso:country":"US",
    "sg:address":"5009 Turnpike Feeder Rd",
    "sg:city":"Fort Pierce",
    "sg:classifiers":[
        {
            "category":"Shopping",
            "subcategory":"Pharmacy",
            "type":"Retail Goods"
        }
    ],
    "sg:phone":"+1 772 489 3700",
    "sg:postcode":"34951",
    "sg:province":"FL",
    "wof:name":"Butterfield Drugs",
    "wof:placetype":"venue"
},
  "geometry": {"coordinates":[-80.397445,27.525019],"type":"Point"}
}