{
  "type": "Feature",
  "properties": {
    "iso:country":"US",
    "sg:address":"821 Palm St",
    "sg:city":"Marco Island",
    "sg:classifiers":[
        {
            "category":"Recreation",
            "type":"Entertainment"
        }
    ],
    "sg:phone":"+1 239 642 7704",
    "sg:postcode":"34145",
    "sg:province":"FL",
    "wof:name":"Kahuna Katamarans Ltd Co",
    "wof:placetype":"venue"
},
  "geometry": {"coordinates":[-81.73052800000001,25.972156],"type":"Point"}
}