{
  "type": "Feature",
  "properties": {
    "addr:full":"12028 Green Emerald Ct Orlando FL 32837",
    "addr:housenumber":"12028",
    "addr:postcode":"32837",
    "addr:street":"Green Emerald Ct",
    "iso:country":"US",
    "sg:address":"12028 Green Emerald Ct",
    "sg:city":"Orlando",
    "sg:classifiers":[
        {
            "category":"Building & Trades",
            "subcategory":"Construction",
            "type":"Services"
        }
    ],
    "sg:phone":"+1 407 370 2205",
    "sg:postcode":"32837",
    "sg:province":"FL",
    "sg:tags":[
        "contractor"
    ],
    "wof:name":"M & G Stucco",
    "wof:placetype":"venue"
},
  "geometry": {"coordinates":[-81.428702,28.389888],"type":"Point"}
}