{
  "type": "Feature",
  "properties": {
    "iso:country":"US",
    "sg:address":"1190 Francis St",
    "sg:city":"St Augustine",
    "sg:classifiers":[
        {
            "category":"Building & Trades",
            "subcategory":"Construction",
            "type":"Services"
        }
    ],
    "sg:phone":"+1 904 669 2857",
    "sg:postcode":"32084",
    "sg:province":"FL",
    "sg:tags":[
        "home",
        "improvement"
    ],
    "wof:name":"Full Spectrum Construction",
    "wof:placetype":"venue"
},
  "geometry": {"coordinates":[-81.335076,29.902054],"type":"Point"}
}