{
  "type": "Feature",
  "properties": {
    "addr:full":"4014 Chase Ave Miami Beach FL 33140",
    "addr:housenumber":"4014",
    "addr:postcode":"33140",
    "addr:street":"Chase Ave",
    "iso:country":"US",
    "sg:address":"4014 Chase Ave",
    "sg:city":"Miami Beach",
    "sg:classifiers":[
        {
            "category":"Real Estate",
            "subcategory":"Real Estate Agent",
            "type":"Services"
        }
    ],
    "sg:phone":"+1 305 538 8866",
    "sg:postcode":"33140",
    "sg:province":"FL",
    "wof:name":"Miami Beach Real Est Svc Inc",
    "wof:placetype":"venue"
},
  "geometry": {"coordinates":[-80.13176300000001,25.813297],"type":"Point"}
}