{
  "type": "Feature",
  "properties": {
    "addr:full":"2614 Sherman St Hollywood FL 33020",
    "addr:housenumber":"2614",
    "addr:postcode":"33020",
    "addr:street":"Sherman St",
    "iso:country":"US",
    "sg:address":"2614 Sherman St",
    "sg:city":"Hollywood",
    "sg:classifiers":[
        {
            "category":"Recreation",
            "type":"Entertainment"
        }
    ],
    "sg:phone":"+1 954 929 4335",
    "sg:postcode":"33020",
    "sg:province":"FL",
    "sg:tags":[
        "diving",
        "scuba"
    ],
    "wof:name":"Scubafish Charters Inc",
    "wof:placetype":"venue"
},
  "geometry": {"coordinates":[-80.161466,26.03226],"type":"Point"}
}