{
  "type": "Feature",
  "properties": {
    "iso:country":"US",
    "sg:address":"420 Stan Dr",
    "sg:city":"Melbourne",
    "sg:classifiers":[
        {
            "category":"Manufacturing",
            "subcategory":"Tools & Machinery",
            "type":"Manufacturing & Wholesale Goods"
        }
    ],
    "sg:phone":"+1 321 728 2777",
    "sg:postcode":"32904",
    "sg:province":"FL",
    "sg:tags":[
        "machine",
        "shop"
    ],
    "wof:name":"Advanced Machining Cncpts Inc",
    "wof:placetype":"venue"
},
  "geometry": {"coordinates":[-80.693864,28.102086],"type":"Point"}
}