{
  "type": "Feature",
  "properties": {
    "iso:country":"US",
    "sg:address":"5351 Normandy Blvd",
    "sg:city":"Jacksonville",
    "sg:classifiers":[
        {
            "category":"Restaurant",
            "type":"Food & Drink"
        }
    ],
    "sg:menulink":"http://www.allmenus.com/fl/jacksonville/67556-subway/menu/",
    "sg:phone":"+1 904 786 6658",
    "sg:postcode":"32205",
    "sg:province":"FL",
    "sg:tags":[
        "american",
        "sandwich"
    ],
    "wof:name":"Subway",
    "wof:placetype":"venue"
},
  "geometry": {"coordinates":[-81.738381,30.309015],"type":"Point"}
}