{
  "type": "Feature",
  "properties": {
    "addr:full":"2618 Almond Dr Holiday FL 34691",
    "addr:housenumber":"2618",
    "addr:postcode":"34691",
    "addr:street":"Almond Dr",
    "iso:country":"US",
    "sg:address":"2618 Almond Dr",
    "sg:city":"Holiday",
    "sg:classifiers":[
        {
            "category":"Professional",
            "subcategory":"Business Services",
            "type":"Services"
        }
    ],
    "sg:phone":"+1 727 934 7292",
    "sg:postcode":"34691",
    "sg:province":"FL",
    "sg:tags":[
        "embroidery"
    ],
    "wof:name":"Molly's Stitching House",
    "wof:placetype":"venue"
},
  "geometry": {"coordinates":[-82.758939,28.196673],"type":"Point"}
}