{
  "type": "Feature",
  "properties": {
    "addr:full":"6090 Miramar Pkwy Hollywood FL 33023",
    "addr:housenumber":"6090",
    "addr:postcode":"33023",
    "addr:street":"Miramar Pkwy",
    "iso:country":"US",
    "sg:address":"6090 Miramar Pkwy",
    "sg:city":"Hollywood",
    "sg:classifiers":[
        {
            "category":"Restaurant",
            "type":"Food & Drink"
        }
    ],
    "sg:menulink":"http://www.allmenus.com/fl/miramar-pembroke-pines/189804-kfc---kentucky-fried-chicken/menu/",
    "sg:phone":"+1 305 987 7806",
    "sg:postcode":"33023",
    "sg:province":"FL",
    "sg:tags":[
        "american",
        "chicken"
    ],
    "wof:name":"KFC - Kentucky Fried Chicken",
    "wof:placetype":"venue"
},
  "geometry": {"coordinates":[-80.208338,25.984476],"type":"Point"}
}