{
  "type": "Feature",
  "properties": {
    "addr:full":"11007 Ulster Ct Tampa FL 33610",
    "addr:housenumber":"11007",
    "addr:postcode":"33610",
    "addr:street":"Ulster Ct",
    "iso:country":"US",
    "sg:address":"11007 Ulster Ct",
    "sg:city":"Tampa",
    "sg:classifiers":[
        {
            "category":"Professional",
            "subcategory":"Testing Lab",
            "type":"Services"
        }
    ],
    "sg:phone":"+1 813 978 9588",
    "sg:postcode":"33610",
    "sg:province":"FL",
    "sg:tags":[
        "repair",
        "electronics",
        "calibration"
    ],
    "wof:name":"Quality Testing Labratory",
    "wof:placetype":"venue"
},
  "geometry": {"coordinates":[-82.311639,27.989961],"type":"Point"}
}