{
  "type": "Feature",
  "properties": {
    "addr:full":"3901 Coconut Palm Dr Tampa FL 33619",
    "addr:housenumber":"3901",
    "addr:postcode":"33619",
    "addr:street":"Coconut Palm Dr",
    "iso:country":"US",
    "sg:address":"3901 Coconut Palm Dr",
    "sg:city":"Tampa",
    "sg:classifiers":[
        {
            "category":"Professional",
            "subcategory":"Computer Services",
            "type":"Services"
        }
    ],
    "sg:phone":"+1 813 630 1911",
    "sg:postcode":"33619",
    "sg:province":"FL",
    "sg:tags":[
        "design",
        "system"
    ],
    "wof:name":"Si Solutions LLC",
    "wof:placetype":"venue"
},
  "geometry": {"coordinates":[-82.349554,27.980058],"type":"Point"}
}