{
  "type": "Feature",
  "properties": {
    "addr:full":"632 S State Hwy 7 Margate FL 33068",
    "addr:housenumber":"632",
    "addr:postcode":"33068",
    "addr:street":"S State Hwy 7 Margate",
    "iso:country":"US",
    "sg:address":"632 S State Hwy 7",
    "sg:city":"Margate",
    "sg:classifiers":[
        {
            "category":"Banks & Credit Unions",
            "subcategory":"Bank",
            "type":"Services"
        }
    ],
    "sg:phone":"+1 954 979 2085",
    "sg:postcode":"33068",
    "sg:province":"FL",
    "sg:tags":[
        "loan",
        "mortgage",
        "real estate"
    ],
    "wof:name":"Transcontinental Lending Group",
    "wof:placetype":"venue"
},
  "geometry": {"coordinates":[-80.204421,26.222935],"type":"Point"}
}