{
  "type": "Feature",
  "properties": {
    "iso:country":"US",
    "sg:address":"16700 Cordova Ct",
    "sg:city":"Delray Beach",
    "sg:classifiers":[
        {
            "category":"Shopping",
            "subcategory":"Used Merchandise",
            "type":"Retail Goods"
        }
    ],
    "sg:phone":"+1 561 638 1399",
    "sg:postcode":"33484",
    "sg:province":"FL",
    "wof:name":"Hawkins Antiques & Art Gallery",
    "wof:placetype":"venue"
},
  "geometry": {"coordinates":[-80.12429,26.4285],"type":"Point"}
}