{
  "type": "Feature",
  "properties": {
    "addr:full":"3550 S US Hwy 1 Fort Pierce FL 34982",
    "addr:housenumber":"3550",
    "addr:postcode":"34982",
    "addr:street":"S Us Hwy 1",
    "iso:country":"US",
    "sg:address":"3550 S US Hwy 1",
    "sg:city":"Fort Pierce",
    "sg:classifiers":[
        {
            "category":"Professional",
            "subcategory":"Accounting & Tax Preparation",
            "type":"Services"
        }
    ],
    "sg:phone":"+1 772 489 5838",
    "sg:postcode":"34982",
    "sg:province":"FL",
    "wof:name":"Carmen Roman Agency",
    "wof:placetype":"venue"
},
  "geometry": {"coordinates":[-80.325805,27.403604],"type":"Point"}
}