{
  "type": "Feature",
  "properties": {
    "addr:full":"1480 Commerce Blvd Lake City FL 32055",
    "addr:housenumber":"1480",
    "addr:postcode":"32055",
    "addr:street":"Commerce Blvd",
    "iso:country":"US",
    "sg:address":"1480 Commerce Blvd",
    "sg:city":"Lake City",
    "sg:classifiers":[
        {
            "category":"Health Services",
            "subcategory":"Hospital",
            "type":"Services"
        }
    ],
    "sg:phone":"+1 386 758 3404",
    "sg:postcode":"32055",
    "sg:province":"FL",
    "wof:name":"Sleep Lab",
    "wof:placetype":"venue"
},
  "geometry": {"coordinates":[-82.685946,30.179967],"type":"Point"}
}