{
  "type": "Feature",
  "properties": {
    "iso:country":"US",
    "sg:address":"411 S Babcock St",
    "sg:city":"Melbourne",
    "sg:classifiers":[
        {
            "category":"Real Estate",
            "subcategory":"Architect",
            "type":"Services"
        }
    ],
    "sg:phone":"+1 321 727 9096",
    "sg:postcode":"32901",
    "sg:province":"FL",
    "sg:tags":[
        "architectural"
    ],
    "wof:name":"D Nagrodsky Architects",
    "wof:placetype":"venue"
},
  "geometry": {"coordinates":[-80.621769,28.103037],"type":"Point"}
}