{
  "type": "Feature",
  "properties": {
    "addr:full":"406 Limona Rd Brandon FL 33510",
    "addr:housenumber":"406",
    "addr:postcode":"33510",
    "addr:street":"Limona Rd",
    "iso:country":"US",
    "sg:address":"406 Limona Rd",
    "sg:city":"Brandon",
    "sg:classifiers":[
        {
            "category":"Building & Trades",
            "subcategory":"Construction",
            "type":"Services"
        }
    ],
    "sg:phone":"+1 813 657 9631",
    "sg:postcode":"33510",
    "sg:province":"FL",
    "sg:tags":[
        "material",
        "nonresidential"
    ],
    "wof:name":"ACI Building Systems Inc",
    "wof:placetype":"venue"
},
  "geometry": {"coordinates":[-82.304249,27.944993],"type":"Point"}
}