{
  "type": "Feature",
  "properties": {
    "addr:full":"1101 N Lake Destiny Rd Maitland FL 32751",
    "addr:housenumber":"1101",
    "addr:postcode":"32751",
    "addr:street":"N Lake Destiny Rd",
    "iso:country":"US",
    "sg:address":"1101 N Lake Destiny Rd",
    "sg:city":"Maitland",
    "sg:classifiers":[
        {
            "category":"Professional",
            "subcategory":"Lawyer & Legal Services",
            "type":"Services"
        }
    ],
    "sg:phone":"+1 407 667 8811",
    "sg:postcode":"32751",
    "sg:province":"FL",
    "sg:tags":[
        "attorney"
    ],
    "wof:name":"Holihan & Diaz",
    "wof:placetype":"venue"
},
  "geometry": {"coordinates":[-81.388328,28.638557],"type":"Point"}
}