{
  "type": "Feature",
  "properties": {
    "addr:full":"2917 S Atlantic Ave Daytona Beach FL 32118",
    "addr:housenumber":"2917",
    "addr:postcode":"32118",
    "addr:street":"S Atlantic Ave",
    "iso:country":"US",
    "sg:address":"2917 S Atlantic Ave",
    "sg:city":"Daytona Beach",
    "sg:classifiers":[
        {
            "category":"Real Estate",
            "subcategory":"Real Estate Agent",
            "type":"Services"
        }
    ],
    "sg:phone":"+1 386 760 2111",
    "sg:postcode":"32118",
    "sg:province":"FL",
    "wof:name":"Oceans 10 Condo Assocn Inc",
    "wof:placetype":"venue"
},
  "geometry": {"coordinates":[-80.979569,29.170781],"type":"Point"}
}