{
  "type": "Feature",
  "properties": {
    "iso:country":"US",
    "sg:address":"6824 Sugarbush Dr",
    "sg:city":"Orlando",
    "sg:classifiers":[
        {
            "category":"Building & Trades",
            "subcategory":"Electrical",
            "type":"Services"
        }
    ],
    "sg:phone":"+1 407 903 2997",
    "sg:postcode":"32819",
    "sg:province":"FL",
    "sg:tags":[
        "electric",
        "contractor"
    ],
    "wof:name":"Electric Machinery Entreprise",
    "wof:placetype":"venue"
},
  "geometry": {"coordinates":[-81.495845,28.462405],"type":"Point"}
}