{
  "type": "Feature",
  "properties": {
    "addr:full":"15739 71st Dr N Palm Beach Gardens FL 33418",
    "addr:housenumber":"15739",
    "addr:postcode":"33418",
    "addr:street":"71St Dr N",
    "iso:country":"US",
    "sg:address":"15739 71st Dr N",
    "sg:city":"Palm Beach Gardens",
    "sg:classifiers":[
        {
            "category":"Building & Trades",
            "subcategory":"Construction",
            "type":"Services"
        }
    ],
    "sg:phone":"+1 561 575 1051",
    "sg:postcode":"33418",
    "sg:province":"FL",
    "sg:tags":[
        "contractor"
    ],
    "wof:name":"Martin Joseph Gallagher",
    "wof:placetype":"venue"
},
  "geometry": {"coordinates":[-80.145734,26.907589],"type":"Point"}
}