{
  "type": "Feature",
  "properties": {
    "iso:country":"US",
    "sg:address":"2603 Chatham Cir",
    "sg:city":"Kissimmee",
    "sg:classifiers":[
        {
            "category":"Professional",
            "subcategory":"Management & Consulting",
            "type":"Services"
        }
    ],
    "sg:phone":"+1 407 396 4161",
    "sg:postcode":"34746",
    "sg:province":"FL",
    "wof:name":"Batini International",
    "wof:placetype":"venue"
},
  "geometry": {"coordinates":[-81.48254,28.322505],"type":"Point"}
}