{
  "type": "Feature",
  "properties": {
    "iso:country":"US",
    "sg:address":"7373 Biscayne Blvd",
    "sg:city":"Miami",
    "sg:classifiers":[
        {
            "category":"Personal",
            "type":"Services"
        }
    ],
    "sg:phone":"+1 305 298 4618",
    "sg:postcode":"33138",
    "sg:province":"FL",
    "sg:tags":[
        "party",
        "planning",
        "event",
        "wedding"
    ],
    "sg:website":"www.luxefete.com",
    "wof:name":"Luxefete",
    "wof:placetype":"venue"
},
  "geometry": {"coordinates":[-80.184434,25.843048],"type":"Point"}
}