{
  "type": "Feature",
  "properties": {
    "addr:full":"160 Scarlet Blvd Oldsmar FL 34677",
    "addr:housenumber":"160",
    "addr:postcode":"34677",
    "addr:street":"Scarlet Blvd",
    "iso:country":"US",
    "sg:address":"160 Scarlet Blvd",
    "sg:city":"Oldsmar",
    "sg:classifiers":[
        {
            "category":"Organizations",
            "subcategory":"Non-profit Organization",
            "type":"Services"
        },
        {
            "category":"Organizations",
            "subcategory":"Membership Organization",
            "type":"Services"
        }
    ],
    "sg:phone":"+1 813 891 9374",
    "sg:postcode":"34677",
    "sg:province":"FL",
    "sg:tags":[
        "charitable",
        "institution"
    ],
    "sg:website":"www.kidswishnetwork.org",
    "wof:name":"Kids Wish Network Inc",
    "wof:placetype":"venue"
},
  "geometry": {"coordinates":[-82.675766,28.041775],"type":"Point"}
}