{
  "type": "Feature",
  "properties": {
    "addr:full":"50 Goodlette Rd S Naples FL 34102",
    "addr:housenumber":"50",
    "addr:postcode":"34102",
    "addr:street":"Goodlette Rd S",
    "iso:country":"US",
    "sg:address":"50 Goodlette Rd S",
    "sg:city":"Naples",
    "sg:classifiers":[
        {
            "category":"Home & Garden",
            "subcategory":"Building Materials",
            "type":"Retail Goods"
        }
    ],
    "sg:phone":"+1 239 262 7670",
    "sg:postcode":"34102",
    "sg:province":"FL",
    "wof:name":"Barleys Wallcovering & Intr",
    "wof:placetype":"venue"
},
  "geometry": {"coordinates":[-81.79092799999999,26.147974],"type":"Point"}
}