{
  "type": "Feature",
  "properties": {
    "iso:country":"US",
    "sg:address":"125 E 49th St",
    "sg:city":"Hialeah",
    "sg:classifiers":[
        {
            "category":"Social Services",
            "subcategory":"Job Training",
            "type":"Services"
        }
    ],
    "sg:phone":"+1 305 556 9350",
    "sg:postcode":"33013",
    "sg:province":"FL",
    "sg:tags":[
        "rehabilitation"
    ],
    "wof:name":"Miami Spine & Rehab Inc",
    "wof:placetype":"venue"
},
  "geometry": {"coordinates":[-80.28005400000001,25.867064],"type":"Point"}
}