{
  "type": "Feature",
  "properties": {
    "iso:country":"US",
    "sg:address":"1031 N Federal Hwy",
    "sg:city":"Hollywood",
    "sg:classifiers":[
        {
            "category":"Restaurant",
            "type":"Food & Drink"
        }
    ],
    "sg:phone":"+1 954 929 2888",
    "sg:postcode":"33020",
    "sg:province":"FL",
    "wof:name":"Jacks Hollywood Diner",
    "wof:placetype":"venue"
},
  "geometry": {"coordinates":[-80.143152,26.01958],"type":"Point"}
}