{
  "type": "Feature",
  "properties": {
    "iso:country":"US",
    "sg:address":"5546 Buzzie Ln",
    "sg:city":"Middleburg",
    "sg:classifiers":[
        {
            "category":"Building & Trades",
            "subcategory":"Construction",
            "type":"Services"
        }
    ],
    "sg:phone":"+1 904 282 3916",
    "sg:postcode":"32068",
    "sg:province":"FL",
    "sg:tags":[
        "hanging",
        "contractor"
    ],
    "wof:name":"Aquaproof",
    "wof:placetype":"venue"
},
  "geometry": {"coordinates":[-81.963155,30.091425],"type":"Point"}
}