{
  "type": "Feature",
  "properties": {
    "iso:country":"US",
    "sg:address":"11530 Cleveland Ave",
    "sg:city":"Fort Myers",
    "sg:classifiers":[
        {
            "category":"Shopping",
            "subcategory":"Clothing, Apparel, & Fashions",
            "type":"Retail Goods"
        }
    ],
    "sg:phone":"+1 239 936 7114",
    "sg:postcode":"33907",
    "sg:province":"FL",
    "sg:tags":[
        "furnishing"
    ],
    "wof:name":"King James Big Or Tall",
    "wof:placetype":"venue"
},
  "geometry": {"coordinates":[-81.872137,26.571152],"type":"Point"}
}