{
  "type": "Feature",
  "properties": {
    "iso:country":"US",
    "sg:address":"7600 SW 104th St",
    "sg:city":"Miami",
    "sg:classifiers":[
        {
            "category":"Education",
            "subcategory":"Preschool",
            "type":"Public Place"
        },
        {
            "category":"Education",
            "subcategory":"School",
            "type":"Public Place"
        }
    ],
    "sg:phone":"+1 305 661 6020",
    "sg:postcode":"33156",
    "sg:province":"FL",
    "sg:tags":[
        "elementary"
    ],
    "sg:website":"www.umc.org",
    "wof:name":"Kendall United Methodist Church Pre-School",
    "wof:placetype":"venue"
},
  "geometry": {"coordinates":[-80.317802,25.674101],"type":"Point"}
}