{
  "type": "Feature",
  "properties": {
    "iso:country":"US",
    "sg:address":"6782 Viento Way",
    "sg:city":"Boca Raton",
    "sg:classifiers":[
        {
            "category":"Professional",
            "subcategory":"Accounting & Tax Preparation",
            "type":"Services"
        }
    ],
    "sg:phone":"+1 561 483 8668",
    "sg:postcode":"33433",
    "sg:province":"FL",
    "sg:tags":[
        "accountant"
    ],
    "wof:name":"Victor Mendelsohn CPA",
    "wof:placetype":"venue"
},
  "geometry": {"coordinates":[-80.15190200000001,26.366857],"type":"Point"}
}