{
  "type": "Feature",
  "properties": {
    "iso:country":"US",
    "sg:address":"241 W King St",
    "sg:city":"Saint Augustine",
    "sg:classifiers":[
        {
            "category":"Home & Garden",
            "subcategory":"Furniture",
            "type":"Retail Goods"
        }
    ],
    "sg:phone":"+1 904 823 9915",
    "sg:postcode":"32084",
    "sg:province":"FL",
    "sg:tags":[
        "reupholstering"
    ],
    "wof:name":"Reginalds Originals",
    "wof:placetype":"venue"
},
  "geometry": {"coordinates":[-81.329149,29.890544],"type":"Point"}
}