{
  "type": "Feature",
  "properties": {
    "iso:country":"US",
    "sg:address":"9520 SE Point Ter",
    "sg:city":"Jupiter",
    "sg:classifiers":[
        {
            "category":"Home & Garden",
            "subcategory":"Furniture",
            "type":"Retail Goods"
        }
    ],
    "sg:phone":"+1 561 746 2348",
    "sg:postcode":"33469",
    "sg:province":"FL",
    "sg:tags":[
        "store"
    ],
    "wof:name":"Walsh Dan Interior Trim",
    "wof:placetype":"venue"
},
  "geometry": {"coordinates":[-80.12624,26.97421],"type":"Point"}
}