{
  "type": "Feature",
  "properties": {
    "iso:country":"US",
    "sg:address":"204 James Ave",
    "sg:city":"Key Largo",
    "sg:classifiers":[
        {
            "category":"Manufacturing",
            "subcategory":"Signs",
            "type":"Manufacturing & Wholesale Goods"
        }
    ],
    "sg:phone":"+1 305 451 3584",
    "sg:postcode":"33037",
    "sg:province":"FL",
    "sg:tags":[
        "body",
        "auto",
        "specialty",
        "mfg"
    ],
    "wof:name":"C Padgett Signs",
    "wof:placetype":"venue"
},
  "geometry": {"coordinates":[-80.42859199999999,25.114722],"type":"Point"}
}