{
  "type": "Feature",
  "properties": {
    "addr:full":"1489 W Palmetto Park Rd Boca Raton FL 33486",
    "addr:housenumber":"1489",
    "addr:postcode":"33486",
    "addr:street":"W Palmetto Park Rd",
    "iso:country":"US",
    "sg:address":"1489 W Palmetto Park Rd",
    "sg:city":"Boca Raton",
    "sg:classifiers":[
        {
            "category":"Professional",
            "type":"Services"
        }
    ],
    "sg:phone":"+1 561 416 9479",
    "sg:postcode":"33486",
    "sg:province":"FL",
    "sg:tags":[
        "establishment"
    ],
    "wof:name":"United Global Tech Inc",
    "wof:placetype":"venue"
},
  "geometry": {"coordinates":[-80.112621,26.350818],"type":"Point"}
}