{
  "type": "Feature",
  "properties": {
    "addr:full":"6998 NW 51st St Miami FL 33166",
    "addr:housenumber":"6998",
    "addr:postcode":"33166",
    "addr:street":"Nw 51St St",
    "iso:country":"US",
    "sg:address":"6998 NW 51st St",
    "sg:city":"Miami",
    "sg:classifiers":[
        {
            "category":"Professional",
            "subcategory":"Business Services",
            "type":"Services"
        }
    ],
    "sg:phone":"+1 305 594 1145",
    "sg:postcode":"33166",
    "sg:province":"FL",
    "sg:tags":[
        "importer",
        "exporter"
    ],
    "wof:name":"Marpa Enterprise Inc",
    "wof:placetype":"venue"
},
  "geometry": {"coordinates":[-80.311021,25.81982],"type":"Point"}
}