{
  "type": "Feature",
  "properties": {
    "iso:country":"US",
    "sg:address":"4775 Collins Ave",
    "sg:city":"Miami Beach",
    "sg:classifiers":[
        {
            "category":"Banks & Credit Unions",
            "subcategory":"Financial Services",
            "type":"Services"
        }
    ],
    "sg:phone":"+1 305 538 2024",
    "sg:postcode":"33140",
    "sg:province":"FL",
    "sg:tags":[
        "company",
        "holding"
    ],
    "wof:name":"East Point Holdings LLC",
    "wof:placetype":"venue"
},
  "geometry": {"coordinates":[-80.122968,25.819265],"type":"Point"}
}