{
  "type": "Feature",
  "properties": {
    "iso:country":"US",
    "sg:address":"12115 28th St N",
    "sg:city":"St Petersburg",
    "sg:classifiers":[
        {
            "category":"Building & Trades",
            "subcategory":"Plumbing",
            "type":"Services"
        }
    ],
    "sg:phone":"+1 727 573 1440",
    "sg:postcode":"33716",
    "sg:province":"FL",
    "sg:tags":[
        "conditioning",
        "air",
        "system",
        "contractor"
    ],
    "wof:name":"Trane Co",
    "wof:placetype":"venue"
},
  "geometry": {"coordinates":[-82.670705,27.884479],"type":"Point"}
}