{
  "type": "Feature",
  "properties": {
    "addr:full":"525 NW 27th Ave Miami FL 33125",
    "addr:housenumber":"525",
    "addr:postcode":"33125",
    "addr:street":"Nw 27Th Ave",
    "iso:country":"US",
    "sg:address":"525 NW 27th Ave",
    "sg:city":"Miami",
    "sg:classifiers":[
        {
            "category":"Health Services",
            "subcategory":"Chiropractor",
            "type":"Services"
        },
        {
            "category":"Health Services",
            "subcategory":"Clinic",
            "type":"Services"
        }
    ],
    "sg:phone":"+1 305 646 0121",
    "sg:postcode":"33125",
    "sg:province":"FL",
    "wof:name":"Stop Pain Medical Center Inc",
    "wof:placetype":"venue"
},
  "geometry": {"coordinates":[-80.23921300000001,25.77723],"type":"Point"}
}