{
  "type": "Feature",
  "properties": {
    "addr:full":"4508 Old Orchard Dr Tampa FL 33618",
    "addr:housenumber":"4508",
    "addr:postcode":"33618",
    "addr:street":"Old Orchard Dr",
    "iso:country":"US",
    "sg:address":"4508 Old Orchard Dr",
    "sg:city":"Tampa",
    "sg:classifiers":[
        {
            "category":"Professional",
            "subcategory":"Secretarial Services",
            "type":"Services"
        }
    ],
    "sg:phone":"+1 813 968 2972",
    "sg:postcode":"33618",
    "sg:province":"FL",
    "sg:tags":[
        "transcription",
        "medical"
    ],
    "wof:name":"Festa Facilitators Inc",
    "wof:placetype":"venue"
},
  "geometry": {"coordinates":[-82.516014,28.061305],"type":"Point"}
}