{
  "type": "Feature",
  "properties": {
    "iso:country":"US",
    "sg:address":"12896 Citrus Grove Blvd",
    "sg:city":"West Palm Beach",
    "sg:classifiers":[
        {
            "category":"Wholesale",
            "subcategory":"Home Furnishings",
            "type":"Manufacturing & Wholesale Goods"
        }
    ],
    "sg:phone":"+1 561 795 1105",
    "sg:postcode":"33412",
    "sg:province":"FL",
    "wof:name":"Staging Places Renewing Spaces",
    "wof:placetype":"venue"
},
  "geometry": {"coordinates":[-80.243009,26.802099],"type":"Point"}
}