{
  "type": "Feature",
  "properties": {
    "addr:full":"1142 NE 91st St Miami FL 33138",
    "addr:housenumber":"1142",
    "addr:postcode":"33138",
    "addr:street":"Ne 91St St",
    "iso:country":"US",
    "sg:address":"1142 NE 91st St",
    "sg:city":"Miami",
    "sg:classifiers":[
        {
            "category":"Building & Trades",
            "subcategory":"Construction",
            "type":"Services"
        }
    ],
    "sg:phone":"+1 305 751 4658",
    "sg:postcode":"33138",
    "sg:province":"FL",
    "sg:tags":[
        "general",
        "contractor"
    ],
    "wof:name":"H R Reed Construction Inc",
    "wof:placetype":"venue"
},
  "geometry": {"coordinates":[-80.173136,25.859163],"type":"Point"}
}