{
  "type": "Feature",
  "properties": {
    "iso:country":"US",
    "sg:address":"34712 la Place Ct",
    "sg:city":"Eustis",
    "sg:classifiers":[
        {
            "category":"Professional",
            "subcategory":"Detective & Security Services",
            "type":"Services"
        }
    ],
    "sg:phone":"+1 352 483 0212",
    "sg:postcode":"32736",
    "sg:province":"FL",
    "sg:tags":[
        "information",
        "bureau"
    ],
    "wof:name":"Royal Services Of Central Florida",
    "wof:placetype":"venue"
},
  "geometry": {"coordinates":[-81.5665,28.851466],"type":"Point"}
}