{
  "type": "Feature",
  "properties": {
    "addr:full":"116 Mante Dr Kissimmee FL 34743",
    "addr:housenumber":"116",
    "addr:postcode":"34743",
    "addr:street":"Mante Dr",
    "iso:country":"US",
    "sg:address":"116 Mante Dr",
    "sg:city":"Kissimmee",
    "sg:classifiers":[
        {
            "category":"Retail",
            "subcategory":"Repair Shop",
            "type":"Services"
        }
    ],
    "sg:phone":"+1 407 348 9203",
    "sg:postcode":"34743",
    "sg:province":"FL",
    "wof:name":"Staley Jnne Field Representive",
    "wof:placetype":"venue"
},
  "geometry": {"coordinates":[-81.358707,28.332727],"type":"Point"}
}