{
  "type": "Feature",
  "properties": {
    "iso:country":"US",
    "sg:address":"6626 Kingspointe Pkwy",
    "sg:city":"Orlando",
    "sg:classifiers":[
        {
            "category":"Cinema",
            "subcategory":"Movie Theater",
            "type":"Entertainment"
        }
    ],
    "sg:phone":"+1 407 351 5600",
    "sg:postcode":"32819",
    "sg:province":"FL",
    "sg:tags":[
        "theatrical",
        "consultant"
    ],
    "wof:name":"J B P Entertainment Group",
    "wof:placetype":"venue"
},
  "geometry": {"coordinates":[-81.438829,28.453285],"type":"Point"}
}