{
  "type": "Feature",
  "properties": {
    "iso:country":"US",
    "sg:address":"4901 Cortez Cir",
    "sg:city":"Naples",
    "sg:classifiers":[
        {
            "category":"Building & Trades",
            "subcategory":"Construction",
            "type":"Services"
        }
    ],
    "sg:phone":"+1 239 417 0725",
    "sg:postcode":"34112",
    "sg:province":"FL",
    "sg:tags":[
        "painter"
    ],
    "wof:name":"Michael D Thompson's Art East",
    "wof:placetype":"venue"
},
  "geometry": {"coordinates":[-81.746213,26.109778],"type":"Point"}
}