{
  "type": "Feature",
  "properties": {
    "iso:country":"US",
    "sg:address":"915 Martin Luther King Jr Blvd",
    "sg:city":"Panama City",
    "sg:classifiers":[
        {
            "category":"Shopping",
            "subcategory":"Florist",
            "type":"Retail Goods"
        }
    ],
    "sg:phone":"+1 850 522 8688",
    "sg:postcode":"32401",
    "sg:province":"FL",
    "wof:name":"Rosa's Florist & Gift Shop",
    "wof:placetype":"venue"
},
  "geometry": {"coordinates":[-85.65037,30.164811],"type":"Point"}
}