{
  "type": "Feature",
  "properties": {
    "iso:country":"US",
    "sg:address":"1435 SW 13th St",
    "sg:city":"Miami",
    "sg:classifiers":[
        {
            "category":"Wholesale",
            "subcategory":"Computers",
            "type":"Manufacturing & Wholesale Goods"
        }
    ],
    "sg:phone":"+1 305 643 9770",
    "sg:postcode":"33145",
    "sg:province":"FL",
    "sg:tags":[
        "computer-wholesale",
        "manufacturer"
    ],
    "wof:name":"Ksl Globallink Inc",
    "wof:placetype":"venue"
},
  "geometry": {"coordinates":[-80.21830199999999,25.760792],"type":"Point"}
}