{
  "type": "Feature",
  "properties": {
    "iso:country":"US",
    "sg:address":"89389 Old Hwy",
    "sg:city":"Islamorada",
    "sg:classifiers":[
        {
            "category":"Health Services",
            "subcategory":"Doctor",
            "type":"Services"
        }
    ],
    "sg:phone":"+1 305 852 9245",
    "sg:postcode":"33036",
    "sg:province":"FL",
    "sg:tags":[
        "medicine",
        "physician",
        "practice",
        "surgeons",
        "family"
    ],
    "wof:name":"Dr Susan Gray",
    "wof:placetype":"venue"
},
  "geometry": {"coordinates":[-80.563862,24.96365],"type":"Point"}
}