{
  "type": "Feature",
  "properties": {
    "iso:country":"US",
    "sg:address":"25 W Flagler St Ste 800",
    "sg:city":"Miami",
    "sg:classifiers":[
        {
            "category":"Professional",
            "subcategory":"Lawyer & Legal Services",
            "type":"Services"
        }
    ],
    "sg:phone":"+1 305 358 2800",
    "sg:postcode":"33130",
    "sg:province":"FL",
    "wof:name":"Diaz Victor M Jr",
    "wof:placetype":"venue"
},
  "geometry": {"coordinates":[-80.194042,25.774159],"type":"Point"}
}