{
  "type": "Feature",
  "properties": {
    "iso:country":"US",
    "sg:address":"114 E Wright St",
    "sg:city":"Pensacola",
    "sg:classifiers":[
        {
            "category":"Building & Trades",
            "subcategory":"Electrical",
            "type":"Services"
        },
        {
            "category":"Wholesale",
            "subcategory":"Electrical",
            "type":"Manufacturing & Wholesale Goods"
        }
    ],
    "sg:phone":"+1 850 432 0479",
    "sg:postcode":"32501",
    "sg:province":"FL",
    "sg:tags":[
        "control",
        "contractor",
        "d",
        "temperature",
        "installing"
    ],
    "wof:name":"Systems Specialists Inc",
    "wof:placetype":"venue"
},
  "geometry": {"coordinates":[-87.21384999999999,30.417121],"type":"Point"}
}