{
  "type": "Feature",
  "properties": {
    "addr:full":"11 N Rosalind Ave Orlando FL 32801",
    "addr:housenumber":"11",
    "addr:postcode":"32801",
    "addr:street":"N Rosalind Ave",
    "iso:country":"US",
    "sg:address":"11 N Rosalind Ave",
    "sg:city":"Orlando",
    "sg:classifiers":[
        {
            "category":"Organizations",
            "subcategory":"Community Association",
            "type":"Services"
        }
    ],
    "sg:phone":"+1 407 422 7573",
    "sg:postcode":"32801",
    "sg:province":"FL",
    "wof:name":"Rosalind Club",
    "wof:placetype":"venue"
},
  "geometry": {"coordinates":[-81.375805,28.542387],"type":"Point"}
}