{
  "type": "Feature",
  "properties": {
    "iso:country":"US",
    "sg:address":"15412 Front Beach Rd",
    "sg:city":"Panama City",
    "sg:classifiers":[
        {
            "category":"Recreation",
            "type":"Entertainment"
        }
    ],
    "sg:phone":"+1 850 234 5271",
    "sg:postcode":"32413",
    "sg:province":"FL",
    "wof:name":"Gulf World Inc",
    "wof:placetype":"venue"
},
  "geometry": {"coordinates":[-85.877865,30.216365],"type":"Point"}
}