{
  "type": "Feature",
  "properties": {
    "addr:full":"5606 Woodbine Rd Milton FL 32571",
    "addr:housenumber":"5606",
    "addr:postcode":"32571",
    "addr:street":"Woodbine Rd",
    "iso:country":"US",
    "sg:address":"5606 Woodbine Rd",
    "sg:city":"Milton",
    "sg:classifiers":[
        {
            "category":"Health Services",
            "subcategory":"Doctor",
            "type":"Services"
        }
    ],
    "sg:phone":"+1 850 995 0125",
    "sg:postcode":"32571",
    "sg:province":"FL",
    "sg:tags":[
        "physician",
        "surgeon"
    ],
    "wof:name":"Five Points Family Practice",
    "wof:placetype":"venue"
},
  "geometry": {"coordinates":[-87.18183399999999,30.638633],"type":"Point"}
}