{
  "type": "Feature",
  "properties": {
    "addr:full":"3905 Aero Pl Lakeland FL 33811",
    "addr:housenumber":"3905",
    "addr:postcode":"33811",
    "addr:street":"Aero Pl",
    "iso:country":"US",
    "sg:address":"3905 Aero Pl",
    "sg:city":"Lakeland",
    "sg:classifiers":[
        {
            "category":"Airline",
            "type":"Transportation"
        }
    ],
    "sg:phone":"+1 863 648 5769",
    "sg:postcode":"33811",
    "sg:province":"FL",
    "sg:tags":[
        "company"
    ],
    "wof:name":"Atlantic Airlines Inc",
    "wof:placetype":"venue"
},
  "geometry": {"coordinates":[-82.025773,27.993262],"type":"Point"}
}