{
  "type": "Feature",
  "properties": {
    "addr:full":"5496 Rattlesnake Hammock Rd Naples FL 34113",
    "addr:housenumber":"5496",
    "addr:postcode":"34113",
    "addr:street":"Rattlesnake Hammock Rd",
    "iso:country":"US",
    "sg:address":"5496 Rattlesnake Hammock Rd",
    "sg:city":"Naples",
    "sg:classifiers":[
        {
            "category":"Food & Beverages",
            "subcategory":"Meat & Fish",
            "type":"Retail Goods"
        }
    ],
    "sg:phone":"+1 239 732 6399",
    "sg:postcode":"34113",
    "sg:province":"FL",
    "wof:name":"Daves Butcher Shop",
    "wof:placetype":"venue"
},
  "geometry": {"coordinates":[-81.73693400000001,26.109322],"type":"Point"}
}