{
  "type": "Feature",
  "properties": {
    "addr:full":"2321 N 57th Way Hollywood FL 33021",
    "addr:housenumber":"2321",
    "addr:postcode":"33021",
    "addr:street":"N 57Th Way",
    "iso:country":"US",
    "sg:address":"2321 N 57th Way",
    "sg:city":"Hollywood",
    "sg:classifiers":[
        {
            "category":"Insurance",
            "subcategory":"Insurance Agent",
            "type":"Services"
        }
    ],
    "sg:phone":"+1 954 963 2737",
    "sg:postcode":"33021",
    "sg:province":"FL",
    "wof:name":"Amb International Inc",
    "wof:placetype":"venue"
},
  "geometry": {"coordinates":[-80.203457,26.03213],"type":"Point"}
}