{
  "type": "Feature",
  "properties": {
    "iso:country":"US",
    "sg:address":"2875 S Ocean Blvd",
    "sg:city":"Palm Beach",
    "sg:classifiers":[
        {
            "category":"Professional",
            "subcategory":"Management & Consulting",
            "type":"Services"
        }
    ],
    "sg:phone":"+1 561 547 7732",
    "sg:postcode":"33480",
    "sg:province":"FL",
    "sg:tags":[
        "product",
        "design",
        "insurance",
        "market"
    ],
    "wof:name":"Cda of America Inc",
    "wof:placetype":"venue"
},
  "geometry": {"coordinates":[-80.03873299999999,26.619118],"type":"Point"}
}