{
  "type": "Feature",
  "properties": {
    "iso:country":"US",
    "sg:address":"537 NE 34th St",
    "sg:city":"Oakland Park",
    "sg:classifiers":[
        {
            "category":"Retail",
            "subcategory":"Repair Shop",
            "type":"Services"
        }
    ],
    "sg:phone":"+1 954 564 7000",
    "sg:postcode":"33334",
    "sg:province":"FL",
    "sg:tags":[
        "equipment",
        "conditioning",
        "air"
    ],
    "wof:name":"Airtronic & Appliance Systems",
    "wof:placetype":"venue"
},
  "geometry": {"coordinates":[-80.139117,26.169462],"type":"Point"}
}