{
  "type": "Feature",
  "properties": {
    "addr:full":"3101 Aviation Blvd Vero Beach FL 32960",
    "addr:housenumber":"3101",
    "addr:postcode":"32960",
    "addr:street":"Aviation Blvd",
    "iso:country":"US",
    "sg:address":"3101 Aviation Blvd",
    "sg:city":"Vero Beach",
    "sg:classifiers":[
        {
            "category":"Retail",
            "subcategory":"Repair Shop",
            "type":"Services"
        }
    ],
    "sg:phone":"+1 772 567 8560",
    "sg:postcode":"32960",
    "sg:province":"FL",
    "sg:tags":[
        "lock",
        "locksmith"
    ],
    "wof:name":"Benson's Lock Svc",
    "wof:placetype":"venue"
},
  "geometry": {"coordinates":[-80.41965999999999,27.64662],"type":"Point"}
}