{
  "type": "Feature",
  "properties": {
    "addr:full":"11450 Overseas Hwy Marathon FL 33050",
    "addr:housenumber":"11450",
    "addr:postcode":"33050",
    "addr:street":"Overseas Hwy",
    "iso:country":"US",
    "sg:address":"11450 Overseas Hwy",
    "sg:city":"Marathon",
    "sg:classifiers":[
        {
            "category":"Education",
            "subcategory":"Dance Studio",
            "type":"Public Place"
        }
    ],
    "sg:phone":"+1 305 743 0660",
    "sg:postcode":"33050",
    "sg:province":"FL",
    "sg:tags":[
        "instruction",
        "dancing"
    ],
    "wof:name":"Theo & Ganine's Dance Ctr",
    "wof:placetype":"venue"
},
  "geometry": {"coordinates":[-81.033434,24.729614],"type":"Point"}
}