{
  "type": "Feature",
  "properties": {
    "addr:full":"2701 Technology Cir Marianna FL 32448",
    "addr:housenumber":"2701",
    "addr:postcode":"32448",
    "addr:street":"Technology Cir",
    "iso:country":"US",
    "sg:address":"2701 Technology Cir",
    "sg:city":"Marianna",
    "sg:classifiers":[
        {
            "category":"Education",
            "subcategory":"School",
            "type":"Public Place"
        }
    ],
    "sg:phone":"+1 850 482 9666",
    "sg:postcode":"32448",
    "sg:province":"FL",
    "wof:name":"Jackson Acdemy Applied Tcholgy",
    "wof:placetype":"venue"
},
  "geometry": {"coordinates":[-85.25948099999999,30.76219],"type":"Point"}
}