{
  "type": "Feature",
  "properties": {
    "addr:full":"3990 W Flagler St Coral Gables FL 33134",
    "addr:housenumber":"3990",
    "addr:postcode":"33134",
    "addr:street":"W Flagler St",
    "iso:country":"US",
    "sg:address":"3990 W Flagler St",
    "sg:city":"Coral Gables",
    "sg:classifiers":[
        {
            "category":"Health Services",
            "subcategory":"Doctor",
            "type":"Services"
        }
    ],
    "sg:phone":"+1 305 476 0033",
    "sg:postcode":"33134",
    "sg:province":"FL",
    "sg:tags":[
        "clinic"
    ],
    "wof:name":"Brother Medical Ctr",
    "wof:placetype":"venue"
},
  "geometry": {"coordinates":[-80.261381,25.771644],"type":"Point"}
}