{
  "type": "Feature",
  "properties": {
    "addr:full":"14610 NW 26th Ave Opa Locka FL 33054",
    "addr:housenumber":"14610",
    "addr:postcode":"33054",
    "addr:street":"Nw 26Th Ave;Locka",
    "iso:country":"US",
    "sg:address":"14610 NW 26th Ave",
    "sg:city":"Opa Locka",
    "sg:classifiers":[
        {
            "category":"Autos & Motor Vehicles",
            "subcategory":"Auto Supplies",
            "type":"Retail Goods"
        }
    ],
    "sg:phone":"+1 305 953 0516",
    "sg:postcode":"33054",
    "sg:province":"FL",
    "sg:tags":[
        "automobile",
        "parts"
    ],
    "wof:name":"Inter American Auto Parts",
    "wof:placetype":"venue"
},
  "geometry": {"coordinates":[-80.24305,25.907162],"type":"Point"}
}