{
  "type": "Feature",
  "properties": {
    "addr:full":"1575 Agnes Ave SE Palm Bay FL 32909",
    "addr:housenumber":"1575",
    "addr:postcode":"32909",
    "addr:street":"Agnes Ave Se",
    "iso:country":"US",
    "sg:address":"1575 Agnes Ave SE",
    "sg:city":"Palm Bay",
    "sg:classifiers":[
        {
            "category":"Arena",
            "subcategory":"Sports Club",
            "type":"Entertainment"
        }
    ],
    "sg:phone":"+1 321 723 8111",
    "sg:postcode":"32909",
    "sg:province":"FL",
    "wof:name":"South Brevard Wrestling Club",
    "wof:placetype":"venue"
},
  "geometry": {"coordinates":[-80.62660099999999,27.96991],"type":"Point"}
}