{
  "type": "Feature",
  "properties": {
    "iso:country":"US",
    "sg:address":"2650 McCormick Dr",
    "sg:city":"Clearwater",
    "sg:classifiers":[
        {
            "category":"Banks & Credit Unions",
            "subcategory":"Investment Brokerage",
            "type":"Services"
        }
    ],
    "sg:phone":"+1 727 535 0584",
    "sg:postcode":"33759",
    "sg:province":"FL",
    "sg:tags":[
        "security"
    ],
    "wof:name":"Juran & Moody",
    "wof:placetype":"venue"
},
  "geometry": {"coordinates":[-82.728545,27.99933],"type":"Point"}
}