{
  "type": "Feature",
  "properties": {
    "iso:country":"US",
    "sg:address":"6607 Mansour Ln",
    "sg:city":"Daytona Beach",
    "sg:classifiers":[
        {
            "category":"Building & Trades",
            "subcategory":"Construction",
            "type":"Services"
        }
    ],
    "sg:phone":"+1 386 756 9005",
    "sg:postcode":"32128",
    "sg:province":"FL",
    "sg:tags":[
        "house"
    ],
    "wof:name":"Waters Edge Sales Center",
    "wof:placetype":"venue"
},
  "geometry": {"coordinates":[-81.038843,29.06288],"type":"Point"}
}