{
  "type": "Feature",
  "properties": {
    "iso:country":"US",
    "sg:address":"3146 Davis Blvd",
    "sg:city":"Naples",
    "sg:classifiers":[
        {
            "category":"Retail",
            "subcategory":"Auto Repair",
            "type":"Services"
        }
    ],
    "sg:phone":"+1 239 643 4101",
    "sg:postcode":"34104",
    "sg:province":"FL",
    "sg:tags":[
        "transmission"
    ],
    "wof:name":"A 1 A Transmission Inc",
    "wof:placetype":"venue"
},
  "geometry": {"coordinates":[-81.768846,26.138414],"type":"Point"}
}