{
  "type": "Feature",
  "properties": {
    "iso:country":"US",
    "sg:address":"440 Royal Palm Way",
    "sg:city":"Palm Beach",
    "sg:classifiers":[
        {
            "category":"Banks & Credit Unions",
            "subcategory":"Investment Brokerage",
            "type":"Services"
        }
    ],
    "sg:phone":"+1 561 659 9583",
    "sg:postcode":"33480",
    "sg:province":"FL",
    "wof:name":"Desco Investments Inc",
    "wof:placetype":"venue"
},
  "geometry": {"coordinates":[-80.04313,26.705702],"type":"Point"}
}