{
  "type": "Feature",
  "properties": {
    "iso:country":"US",
    "sg:address":"910 W 33rd Pl",
    "sg:city":"Hialeah",
    "sg:classifiers":[
        {
            "category":"Shopping",
            "type":"Retail Goods"
        }
    ],
    "sg:phone":"+1 305 822 1583",
    "sg:postcode":"33012",
    "sg:province":"FL",
    "sg:tags":[
        "merchandise"
    ],
    "wof:name":"Sergio Catering",
    "wof:placetype":"venue"
},
  "geometry": {"coordinates":[-80.302249,25.852298],"type":"Point"}
}