{
  "type": "Feature",
  "properties": {
    "iso:country":"US",
    "sg:address":"1900 Main St Ste 312",
    "sg:city":"Sarasota",
    "sg:classifiers":[
        {
            "category":"Professional",
            "subcategory":"Lawyer & Legal Services",
            "type":"Services"
        }
    ],
    "sg:phone":"+1 941 951 6266",
    "sg:postcode":"34236",
    "sg:province":"FL",
    "sg:tags":[
        "convention",
        "reporters-court"
    ],
    "wof:name":"Professional Reporters Inc",
    "wof:placetype":"venue"
},
  "geometry": {"coordinates":[-82.533028,27.336451],"type":"Point"}
}