{
  "type": "Feature",
  "properties": {
    "addr:full":"1100 E Bay Dr Largo FL 33770",
    "addr:housenumber":"1100",
    "addr:postcode":"33770",
    "addr:street":"E Bay Dr",
    "iso:country":"US",
    "sg:address":"1100 E Bay Dr",
    "sg:city":"Largo",
    "sg:classifiers":[
        {
            "category":"Organizations",
            "subcategory":"Community Association",
            "type":"Services"
        }
    ],
    "sg:phone":"+1 727 585 0794",
    "sg:postcode":"33770",
    "sg:province":"FL",
    "wof:name":"Willowbrook Association Inc",
    "wof:placetype":"venue"
},
  "geometry": {"coordinates":[-82.774913,27.916645],"type":"Point"}
}