{
  "type": "Feature",
  "properties": {
    "iso:country":"US",
    "sg:address":"2160 Howland Blvd",
    "sg:city":"Deltona",
    "sg:classifiers":[
        {
            "category":"Personal",
            "subcategory":"Beauty Salon",
            "type":"Services"
        }
    ],
    "sg:phone":"+1 386 789 7900",
    "sg:postcode":"32738",
    "sg:province":"FL",
    "sg:tags":[
        "nail",
        "manicuring"
    ],
    "wof:name":"Central Nails",
    "wof:placetype":"venue"
},
  "geometry": {"coordinates":[-81.189003,28.924101],"type":"Point"}
}