{
  "type": "Feature",
  "properties": {
    "iso:country":"US",
    "sg:address":"4915 Lyford Cay Rd",
    "sg:city":"Tampa",
    "sg:classifiers":[
        {
            "category":"Health Services",
            "subcategory":"Doctor",
            "type":"Services"
        }
    ],
    "sg:phone":"+1 813 286 2979",
    "sg:postcode":"33629",
    "sg:province":"FL",
    "sg:tags":[
        "medicine",
        "physician",
        "practice",
        "surgeons",
        "family"
    ],
    "wof:name":"Allan Goldman Md Pa",
    "wof:placetype":"venue"
},
  "geometry": {"coordinates":[-82.527941,27.930191],"type":"Point"}
}