{
  "type": "Feature",
  "properties": {
    "addr:full":"35407 Old Lake Unity Rd Fruitland Park FL 34731",
    "addr:housenumber":"35407",
    "addr:postcode":"34731",
    "addr:street":"Old Lake Unity Rd",
    "iso:country":"US",
    "sg:address":"35407 Old Lake Unity Rd",
    "sg:city":"Fruitland Park",
    "sg:classifiers":[
        {
            "category":"Retail",
            "subcategory":"Animal Services",
            "type":"Services"
        }
    ],
    "sg:phone":"+1 352 728 2966",
    "sg:postcode":"34731",
    "sg:province":"FL",
    "wof:name":"Total K9 Outfitters Inc",
    "wof:placetype":"venue"
},
  "geometry": {"coordinates":[-81.883109,28.865886],"type":"Point"}
}