{
  "type": "Feature",
  "properties": {
    "iso:country":"US",
    "sg:address":"485 W Dearborn St",
    "sg:city":"Englewood",
    "sg:classifiers":[
        {
            "category":"Shopping",
            "subcategory":"Jewelry",
            "type":"Retail Goods"
        }
    ],
    "sg:phone":"+1 941 474 1321",
    "sg:postcode":"34223",
    "sg:province":"FL",
    "sg:tags":[
        "repair"
    ],
    "wof:name":"Diamond Dolphin Jewelers Inc",
    "wof:placetype":"venue"
},
  "geometry": {"coordinates":[-82.36231100000001,26.96214],"type":"Point"}
}