{
  "type": "Feature",
  "properties": {
    "addr:full":"80 W 22nd St Hialeah FL 33010",
    "addr:housenumber":"80",
    "addr:postcode":"33010",
    "addr:street":"W 22Nd St",
    "iso:country":"US",
    "sg:address":"80 W 22nd St",
    "sg:city":"Hialeah",
    "sg:classifiers":[
        {
            "category":"Home & Garden",
            "subcategory":"Building Materials",
            "type":"Retail Goods"
        },
        {
            "category":"Wholesale",
            "subcategory":"Dairy",
            "type":"Manufacturing & Wholesale Goods"
        }
    ],
    "sg:phone":"+1 305 888 6553",
    "sg:postcode":"33010",
    "sg:province":"FL",
    "sg:tags":[
        "pumice",
        "product",
        "brick"
    ],
    "wof:name":"Florida Garcia Moneo Inc",
    "wof:placetype":"venue"
},
  "geometry": {"coordinates":[-80.28263099999999,25.841874],"type":"Point"}
}