{
  "type": "Feature",
  "properties": {
    "iso:country":"US",
    "sg:address":"4005 Kumquat Ave",
    "sg:city":"Miami",
    "sg:classifiers":[
        {
            "category":"Professional",
            "type":"Services"
        }
    ],
    "sg:phone":"+1 305 447 9889",
    "sg:postcode":"33133",
    "sg:province":"FL",
    "sg:tags":[
        "motion",
        "picture",
        "technician"
    ],
    "wof:name":"Kesser Image Library",
    "wof:placetype":"venue"
},
  "geometry": {"coordinates":[-80.25782599999999,25.724312],"type":"Point"}
}