{
  "type": "Feature",
  "properties": {
    "iso:country":"US",
    "sg:address":"3088 Aloma Ave",
    "sg:city":"Winter Park",
    "sg:classifiers":[
        {
            "category":"Restaurant",
            "type":"Food & Drink"
        }
    ],
    "sg:phone":"+1 407 673 3488",
    "sg:postcode":"32792",
    "sg:province":"FL",
    "sg:tags":[
        "eating"
    ],
    "wof:name":"Gators Dockside Winter Park",
    "wof:placetype":"venue"
},
  "geometry": {"coordinates":[-81.309178,28.604041],"type":"Point"}
}