{
  "type": "Feature",
  "properties": {
    "iso:country":"US",
    "sg:address":"9 Rotonda Cir",
    "sg:city":"Rotonda West",
    "sg:classifiers":[
        {
            "category":"Building & Trades",
            "subcategory":"Construction",
            "type":"Services"
        }
    ],
    "sg:phone":"+1 941 626 1230",
    "sg:postcode":"33947",
    "sg:province":"FL",
    "sg:tags":[
        "residential"
    ],
    "wof:name":"M&W Murray LLC",
    "wof:placetype":"venue"
},
  "geometry": {"coordinates":[-82.289446,26.87794],"type":"Point"}
}