{
  "type": "Feature",
  "properties": {
    "addr:full":"13155 Spring Hill Dr Brooksville FL 34609",
    "addr:housenumber":"13155",
    "addr:postcode":"34609",
    "addr:street":"Spring Hill Dr",
    "iso:country":"US",
    "sg:address":"13155 Spring Hill Dr",
    "sg:city":"Brooksville",
    "sg:classifiers":[
        {
            "category":"Personal",
            "subcategory":"Beauty Salon",
            "type":"Services"
        }
    ],
    "sg:phone":"+1 352 686 9509",
    "sg:postcode":"34609",
    "sg:province":"FL",
    "wof:name":"Tropical Image",
    "wof:placetype":"venue"
},
  "geometry": {"coordinates":[-82.51008899999999,28.46746],"type":"Point"}
}