{
  "type": "Feature",
  "properties": {
    "iso:country":"US",
    "sg:address":"3332 Griffin Rd",
    "sg:city":"Fort Lauderdale",
    "sg:classifiers":[
        {
            "category":"Insurance",
            "subcategory":"Insurance Agent",
            "type":"Services"
        }
    ],
    "sg:phone":"+1 954 981 1822",
    "sg:postcode":"33312",
    "sg:province":"FL",
    "wof:name":"Approved Long Term Care Inc",
    "wof:placetype":"venue"
},
  "geometry": {"coordinates":[-80.188743,26.062393],"type":"Point"}
}