{
  "type": "Feature",
  "properties": {
    "addr:full":"1963 Ibis Point Ln Jacksonville FL 32224",
    "addr:housenumber":"1963",
    "addr:postcode":"32224",
    "addr:street":"Ibis Point Ln",
    "iso:country":"US",
    "sg:address":"1963 Ibis Point Ln",
    "sg:city":"Jacksonville",
    "sg:classifiers":[
        {
            "category":"Home & Garden",
            "subcategory":"Carpets & Floor Coverings",
            "type":"Retail Goods"
        }
    ],
    "sg:phone":"+1 904 220 7332",
    "sg:postcode":"32224",
    "sg:province":"FL",
    "wof:name":"C & A Floor Coverings",
    "wof:placetype":"venue"
},
  "geometry": {"coordinates":[-81.44434,30.31367],"type":"Point"}
}