{
  "type": "Feature",
  "properties": {
    "addr:full":"8103 Back Beach Rd Panama City Bch FL 32407",
    "addr:housenumber":"8103",
    "addr:postcode":"32407",
    "addr:street":"Back Beach Rd",
    "iso:country":"US",
    "sg:address":"8103 Back Beach Rd",
    "sg:city":"Panama City Bch",
    "sg:classifiers":[
        {
            "category":"Building & Trades",
            "subcategory":"Equipment Rental",
            "type":"Services"
        }
    ],
    "sg:phone":"+1 850 872 9100",
    "sg:postcode":"32407",
    "sg:province":"FL",
    "sg:tags":[
        "yard"
    ],
    "wof:name":"Panhandle Paint Supply",
    "wof:placetype":"venue"
},
  "geometry": {"coordinates":[-85.77700299999999,30.188788],"type":"Point"}
}