{
  "type": "Feature",
  "properties": {
    "addr:full":"615 Green Dr Poinciana FL 34759",
    "addr:housenumber":"615",
    "addr:postcode":"34759",
    "addr:street":"Green Dr",
    "iso:country":"US",
    "sg:address":"615 Green Dr",
    "sg:city":"Poinciana",
    "sg:classifiers":[
        {
            "category":"Building & Trades",
            "subcategory":"Construction",
            "type":"Services"
        }
    ],
    "sg:phone":"+1 863 427 3605",
    "sg:postcode":"34759",
    "sg:province":"FL",
    "sg:tags":[
        "home",
        "builder"
    ],
    "wof:name":"Celebrity Homes",
    "wof:placetype":"venue"
},
  "geometry": {"coordinates":[-81.4594,28.137469],"type":"Point"}
}