{
  "type": "Feature",
  "properties": {
    "addr:full":"1414 Kingsley Ave Orange Park FL 32073",
    "addr:housenumber":"1414",
    "addr:postcode":"32073",
    "addr:street":"Kingsley Ave",
    "iso:country":"US",
    "sg:address":"1414 Kingsley Ave",
    "sg:city":"Orange Park",
    "sg:classifiers":[
        {
            "category":"Health Services",
            "subcategory":"Doctor",
            "type":"Services"
        }
    ],
    "sg:phone":"+1 904 269 3842",
    "sg:postcode":"32073",
    "sg:province":"FL",
    "sg:tags":[
        "dentist"
    ],
    "wof:name":"Greg A Archambault DMD",
    "wof:placetype":"venue"
},
  "geometry": {"coordinates":[-81.72908099999999,30.164804],"type":"Point"}
}