{
  "type": "Feature",
  "properties": {
    "iso:country":"US",
    "sg:address":"3146 W 76th St",
    "sg:city":"Hialeah",
    "sg:classifiers":[
        {
            "category":"Personal",
            "subcategory":"Beauty Salon",
            "type":"Services"
        }
    ],
    "sg:phone":"+1 305 231 1630",
    "sg:postcode":"33018",
    "sg:province":"FL",
    "wof:name":"Great Expectations Salons",
    "wof:placetype":"venue"
},
  "geometry": {"coordinates":[-80.347218,25.891429],"type":"Point"}
}