{
  "type": "Feature",
  "properties": {
    "addr:full":"1800 SW 19th Ave Williston FL 32696",
    "addr:housenumber":"1800",
    "addr:postcode":"32696",
    "addr:street":"Sw 19Th Ave",
    "iso:country":"US",
    "sg:address":"1800 SW 19th Ave",
    "sg:city":"Williston",
    "sg:classifiers":[
        {
            "category":"Recreation",
            "subcategory":"Water Park",
            "type":"Entertainment"
        },
        {
            "category":"Manufacturing",
            "subcategory":"Petroleum Products",
            "type":"Manufacturing & Wholesale Goods"
        }
    ],
    "sg:phone":"+1 352 529 0355",
    "sg:postcode":"32696",
    "sg:province":"FL",
    "sg:tags":[
        "equipment-wholesale",
        "equipment",
        "therapy",
        "oxygen",
        "manufacturer"
    ],
    "wof:name":"Us Respiratory",
    "wof:placetype":"venue"
},
  "geometry": {"coordinates":[-82.46901699999999,29.35976],"type":"Point"}
}