{
  "type": "Feature",
  "properties": {
    "addr:full":"8310 Congress St New Port Richey FL 34668",
    "addr:housenumber":"8310",
    "addr:postcode":"34668",
    "addr:street":"Congress St",
    "iso:country":"US",
    "sg:address":"8310 Congress St",
    "sg:city":"New Port Richey",
    "sg:classifiers":[
        {
            "category":"Retail",
            "subcategory":"Auto Repair",
            "type":"Services"
        }
    ],
    "sg:phone":"+1 727 845 4200",
    "sg:postcode":"34668",
    "sg:province":"FL",
    "sg:tags":[
        "repairing",
        "automobile",
        "automotive",
        "general"
    ],
    "wof:name":"Ultima Automotive Inc",
    "wof:placetype":"venue"
},
  "geometry": {"coordinates":[-82.70710800000001,28.277621],"type":"Point"}
}