{
  "type": "Feature",
  "properties": {
    "iso:country":"US",
    "sg:address":"13010 Fruitville Rd",
    "sg:city":"Sarasota",
    "sg:classifiers":[
        {
            "category":"Home & Garden",
            "subcategory":"Garden Supply",
            "type":"Retail Goods"
        }
    ],
    "sg:phone":"+1 941 371 2443",
    "sg:postcode":"34240",
    "sg:province":"FL",
    "sg:tags":[
        "tree"
    ],
    "wof:name":"Venture Tree Farms",
    "wof:placetype":"venue"
},
  "geometry": {"coordinates":[-82.32437299999999,27.338581],"type":"Point"}
}