{
  "type": "Feature",
  "properties": {
    "addr:full":"1302 W Sandalwood Dr Plant City FL 33563",
    "addr:housenumber":"1302",
    "addr:postcode":"33563",
    "addr:street":"W Sandalwood Dr",
    "iso:country":"US",
    "sg:address":"1302 W Sandalwood Dr",
    "sg:city":"Plant City",
    "sg:classifiers":[
        {
            "category":"Wholesale",
            "subcategory":"Plants",
            "type":"Manufacturing & Wholesale Goods"
        }
    ],
    "sg:phone":"+1 813 752 1306",
    "sg:postcode":"33563",
    "sg:province":"FL",
    "wof:name":"New Beginnings",
    "wof:placetype":"venue"
},
  "geometry": {"coordinates":[-82.13475099999999,27.99334],"type":"Point"}
}