{
  "type": "Feature",
  "properties": {
    "addr:full":"1911 Seward Ave Naples FL 34109",
    "addr:housenumber":"1911",
    "addr:postcode":"34109",
    "addr:street":"Seward Ave",
    "iso:country":"US",
    "sg:address":"1911 Seward Ave",
    "sg:city":"Naples",
    "sg:classifiers":[
        {
            "category":"Restaurant",
            "type":"Food & Drink"
        }
    ],
    "sg:phone":"+1 239 596 9005",
    "sg:postcode":"34109",
    "sg:province":"FL",
    "sg:tags":[
        "eating"
    ],
    "wof:name":"Island Cuban Cafe",
    "wof:placetype":"venue"
},
  "geometry": {"coordinates":[-81.779076,26.215545],"type":"Point"}
}