{
  "type": "Feature",
  "properties": {
    "addr:full":"761 John Ringling Blvd Sarasota FL 34236",
    "addr:housenumber":"761",
    "addr:postcode":"34236",
    "addr:street":"John Ringling Blvd",
    "iso:country":"US",
    "sg:address":"761 John Ringling Blvd",
    "sg:city":"Sarasota",
    "sg:classifiers":[
        {
            "category":"Recreation",
            "type":"Entertainment"
        }
    ],
    "sg:phone":"+1 941 922 3774",
    "sg:postcode":"34236",
    "sg:province":"FL",
    "sg:tags":[
        "charter",
        "boat"
    ],
    "wof:name":"Gulf Coast Charters",
    "wof:placetype":"venue"
},
  "geometry": {"coordinates":[-82.569529,27.322754],"type":"Point"}
}