{
  "type": "Feature",
  "properties": {
    "iso:country":"US",
    "sg:address":"1466 SW 45th Way",
    "sg:city":"Deerfield Beach",
    "sg:classifiers":[
        {
            "category":"Recreation",
            "type":"Entertainment"
        }
    ],
    "sg:phone":"+1 954 596 4843",
    "sg:postcode":"33442",
    "sg:province":"FL",
    "wof:name":"Deep Sea Images",
    "wof:placetype":"venue"
},
  "geometry": {"coordinates":[-80.166636,26.296002],"type":"Point"}
}