{
  "type": "Feature",
  "properties": {
    "addr:full":"1219 S East Ave Sarasota FL 34239",
    "addr:housenumber":"1219",
    "addr:postcode":"34239",
    "addr:street":"S East Ave",
    "iso:country":"US",
    "sg:address":"1219 S East Ave",
    "sg:city":"Sarasota",
    "sg:classifiers":[
        {
            "category":"Health Services",
            "subcategory":"Doctor",
            "type":"Services"
        }
    ],
    "sg:phone":"+1 941 955 0727",
    "sg:postcode":"34239",
    "sg:province":"FL",
    "sg:tags":[
        "physician",
        "surgeon"
    ],
    "wof:name":"Richard L Shriner MD",
    "wof:placetype":"venue"
},
  "geometry": {"coordinates":[-82.527734,27.322525],"type":"Point"}
}