{
  "type": "Feature",
  "properties": {
    "addr:full":"10120 SW 98th Ave Miami FL 33176",
    "addr:housenumber":"10120",
    "addr:postcode":"33176",
    "addr:street":"Sw 98Th Ave",
    "iso:country":"US",
    "sg:address":"10120 SW 98th Ave",
    "sg:city":"Miami",
    "sg:classifiers":[
        {
            "category":"Arts & Performance",
            "subcategory":"Theater",
            "type":"Entertainment"
        }
    ],
    "sg:phone":"+1 305 595 9990",
    "sg:postcode":"33176",
    "sg:province":"FL",
    "sg:tags":[
        "band",
        "orchestra"
    ],
    "wof:name":"Jerry Marshall Productions Inc",
    "wof:placetype":"venue"
},
  "geometry": {"coordinates":[-80.353545,25.67557],"type":"Point"}
}