{
  "type": "Feature",
  "properties": {
    "addr:full":"6669 54th Ave N St Petersburg FL 33709",
    "addr:housenumber":"6669",
    "addr:postcode":"33709",
    "addr:street":"54Th Ave N",
    "iso:country":"US",
    "sg:address":"6669 54th Ave N",
    "sg:city":"St Petersburg",
    "sg:classifiers":[
        {
            "category":"Real Estate",
            "subcategory":"Real Estate Agent",
            "type":"Services"
        }
    ],
    "sg:phone":"+1 727 546 4606",
    "sg:postcode":"33709",
    "sg:province":"FL",
    "sg:website":"www.c21sunshine.com",
    "wof:name":"Century 21 Sunshine Realty",
    "wof:placetype":"venue"
},
  "geometry": {"coordinates":[-82.730138,27.821036],"type":"Point"}
}