{
  "type": "Feature",
  "properties": {
    "iso:country":"US",
    "sg:address":"10124 Basin St",
    "sg:city":"New Port Richey",
    "sg:classifiers":[
        {
            "category":"Insurance",
            "subcategory":"Insurance Agent",
            "type":"Services"
        }
    ],
    "sg:phone":"+1 727 372 8231",
    "sg:postcode":"34655",
    "sg:province":"FL",
    "wof:name":"Kellogg Aviation Agency Inc",
    "wof:placetype":"venue"
},
  "geometry": {"coordinates":[-82.64784,28.202783],"type":"Point"}
}