{
  "type": "Feature",
  "properties": {
    "addr:full":"1390 Hall Rd Malabar FL 32950",
    "addr:housenumber":"1390",
    "addr:postcode":"32950",
    "addr:street":"Hall Rd",
    "iso:country":"US",
    "sg:address":"1390 Hall Rd",
    "sg:city":"Malabar",
    "sg:classifiers":[
        {
            "category":"Real Estate",
            "subcategory":"Real Estate Operator",
            "type":"Services"
        }
    ],
    "sg:phone":"+1 321 724 8930",
    "sg:postcode":"32950",
    "sg:province":"FL",
    "sg:tags":[
        "dwelling"
    ],
    "wof:name":"Clifford J & Karen G Dyke",
    "wof:placetype":"venue"
},
  "geometry": {"coordinates":[-80.595535,27.990965],"type":"Point"}
}