{
  "type": "Feature",
  "properties": {
    "iso:country":"US",
    "sg:address":"13821 NE 1st Ave",
    "sg:city":"Miami",
    "sg:classifiers":[
        {
            "category":"Social Services",
            "subcategory":"Job Training",
            "type":"Services"
        }
    ],
    "sg:phone":"+1 305 687 3630",
    "sg:postcode":"33161",
    "sg:province":"FL",
    "sg:tags":[
        "employment"
    ],
    "sg:website":"http://www.cascadedisability.com/",
    "wof:name":"Cascade Disability Management, Inc.",
    "wof:placetype":"venue"
},
  "geometry": {"coordinates":[-80.197164,25.901927],"type":"Point"}
}