{
  "type": "Feature",
  "properties": {
    "addr:full":"1053 A1a Beach Blvd Saint Augustine FL 32080",
    "addr:housenumber":"1053",
    "addr:postcode":"32080",
    "addr:street":"A1A Beach Blvd",
    "iso:country":"US",
    "sg:address":"1053 A1a Beach Blvd",
    "sg:city":"Saint Augustine",
    "sg:classifiers":[
        {
            "category":"Ice Cream",
            "type":"Food & Drink"
        }
    ],
    "sg:menulink":"http://www.allmenus.com/fl/st-augustine/230211-marble-slab-creamery/menu/",
    "sg:phone":"+1 904 461 3536",
    "sg:postcode":"32080",
    "sg:province":"FL",
    "sg:tags":[
        "american"
    ],
    "wof:name":"Marble Slab Creamery",
    "wof:placetype":"venue"
},
  "geometry": {"coordinates":[-81.271101,29.827867],"type":"Point"}
}