{
  "type": "Feature",
  "properties": {
    "iso:country":"US",
    "sg:address":"201 E Ocean Ave",
    "sg:city":"Lake Worth",
    "sg:classifiers":[
        {
            "category":"Building & Trades",
            "subcategory":"Construction",
            "type":"Services"
        }
    ],
    "sg:phone":"+1 561 588 0095",
    "sg:postcode":"33462",
    "sg:province":"FL",
    "sg:tags":[
        "residential",
        "housing",
        "commercial",
        "contractor"
    ],
    "wof:name":"Karl E Lindroos Properties",
    "wof:placetype":"venue"
},
  "geometry": {"coordinates":[-80.049342,26.584339],"type":"Point"}
}