{
  "type": "Feature",
  "properties": {
    "addr:full":"1516 Hillcrest St Orlando FL 32803",
    "addr:housenumber":"1516",
    "addr:postcode":"32803",
    "addr:street":"Hillcrest St",
    "iso:country":"US",
    "sg:address":"1516 Hillcrest St",
    "sg:city":"Orlando",
    "sg:classifiers":[
        {
            "category":"Real Estate",
            "subcategory":"Architect",
            "type":"Services"
        },
        {
            "category":"Building & Trades",
            "subcategory":"Construction",
            "type":"Services"
        }
    ],
    "sg:phone":"+1 407 894 3366",
    "sg:postcode":"32803",
    "sg:province":"FL",
    "sg:tags":[
        "designer",
        "architectural"
    ],
    "wof:name":"Gonzalez Heydrich Design Inc",
    "wof:placetype":"venue"
},
  "geometry": {"coordinates":[-81.361636,28.552141],"type":"Point"}
}