{
  "type": "Feature",
  "properties": {
    "iso:country":"US",
    "sg:address":"249 E 6th Ave",
    "sg:city":"Tallahassee",
    "sg:classifiers":[
        {
            "category":"Professional",
            "subcategory":"Lawyer & Legal Services",
            "type":"Services"
        }
    ],
    "sg:phone":"+1 850 222 7100",
    "sg:postcode":"32303",
    "sg:province":"FL",
    "sg:tags":[
        "attorney"
    ],
    "wof:name":"Desmond & Maceluch",
    "wof:placetype":"venue"
},
  "geometry": {"coordinates":[-84.279669,30.456285],"type":"Point"}
}