{
  "type": "Feature",
  "properties": {
    "iso:country":"US",
    "sg:address":"901 Central Florida Pkwy A6",
    "sg:city":"Orlando",
    "sg:classifiers":[
        {
            "category":"Manufacturing",
            "subcategory":"Buildings",
            "type":"Manufacturing & Wholesale Goods"
        },
        {
            "category":"Manufacturing",
            "subcategory":"Metals",
            "type":"Manufacturing & Wholesale Goods"
        }
    ],
    "sg:phone":"+1 407 296 9444",
    "sg:postcode":"32824",
    "sg:province":"FL",
    "sg:tags":[
        "steel",
        "erectors"
    ],
    "wof:name":"Ability Human Development Of American Corp",
    "wof:placetype":"venue"
},
  "geometry": {"coordinates":[-81.38888300000001,28.407667],"type":"Point"}
}