{
  "type": "Feature",
  "properties": {
    "iso:country":"US",
    "sg:address":"4001 N 29th Ave",
    "sg:city":"Hollywood",
    "sg:classifiers":[
        {
            "category":"Autos & Motor Vehicles",
            "subcategory":"Automobile Sales",
            "type":"Retail Goods"
        }
    ],
    "sg:phone":"+1 954 929 0784",
    "sg:postcode":"33020",
    "sg:province":"FL",
    "sg:tags":[
        "new",
        "car"
    ],
    "wof:name":"Hollywood Chrylser Plymouth",
    "wof:placetype":"venue"
},
  "geometry": {"coordinates":[-80.16583300000001,26.042712],"type":"Point"}
}