{
  "type": "Feature",
  "properties": {
    "addr:full":"5350 Mill Stream Ct Saint Cloud FL 34771",
    "addr:housenumber":"5350",
    "addr:postcode":"34771",
    "addr:street":"Mill Stream Ct",
    "iso:country":"US",
    "sg:address":"5350 Mill Stream Ct",
    "sg:city":"Saint Cloud",
    "sg:classifiers":[
        {
            "category":"Real Estate",
            "subcategory":"Real Estate Agent",
            "type":"Services"
        }
    ],
    "sg:phone":"+1 407 957 5767",
    "sg:postcode":"34771",
    "sg:province":"FL",
    "wof:name":"Promise Land Enterprises Inc",
    "wof:placetype":"venue"
},
  "geometry": {"coordinates":[-81.225697,28.328589],"type":"Point"}
}