{
  "type": "Feature",
  "properties": {
    "addr:full":"2285 W 80th St Ste 2 Hialeah FL 33016",
    "addr:housenumber":"2285",
    "addr:postcode":"33016",
    "addr:street":"W 80Th St Ste 2",
    "iso:country":"US",
    "sg:address":"2285 W 80th St Ste 2",
    "sg:city":"Hialeah",
    "sg:classifiers":[
        {
            "category":"Wholesale",
            "subcategory":"Non-durable Goods",
            "type":"Manufacturing & Wholesale Goods"
        }
    ],
    "sg:phone":"+1 305 818 6522",
    "sg:postcode":"33016",
    "sg:province":"FL",
    "sg:tags":[
        "merchandise-wholesale"
    ],
    "wof:name":"Mourad Import",
    "wof:placetype":"venue"
},
  "geometry": {"coordinates":[-80.329857,25.895149],"type":"Point"}
}