{
  "type": "Feature",
  "properties": {
    "addr:full":"2615 S Woodland Blvd Deland FL 32720",
    "addr:housenumber":"2615",
    "addr:postcode":"32720",
    "addr:street":"S Woodland Blvd",
    "iso:country":"US",
    "sg:address":"2615 S Woodland Blvd",
    "sg:city":"Deland",
    "sg:classifiers":[
        {
            "category":"Shopping",
            "subcategory":"Department Store",
            "type":"Retail Goods"
        }
    ],
    "sg:phone":"+1 386 822 9590",
    "sg:postcode":"32720",
    "sg:province":"FL",
    "sg:website":"www.tjmaxx.com",
    "wof:name":"T J Maxx",
    "wof:placetype":"venue"
},
  "geometry": {"coordinates":[-81.299301,28.9842],"type":"Point"}
}