{
  "type": "Feature",
  "properties": {
    "iso:country":"US",
    "sg:address":"9853 Tamiami Trl N",
    "sg:city":"Naples",
    "sg:classifiers":[
        {
            "category":"Banks & Credit Unions",
            "subcategory":"Bank",
            "type":"Services"
        }
    ],
    "sg:phone":"+1 239 596 8333",
    "sg:postcode":"34108",
    "sg:province":"FL",
    "sg:tags":[
        "cashing",
        "check"
    ],
    "wof:name":"Money Corner",
    "wof:placetype":"venue"
},
  "geometry": {"coordinates":[-81.801489,26.261071],"type":"Point"}
}