{
  "type": "Feature",
  "properties": {
    "addr:full":"4416 Cooper Rd Plant City FL 33565",
    "addr:housenumber":"4416",
    "addr:postcode":"33565",
    "addr:street":"Cooper Rd",
    "iso:country":"US",
    "sg:address":"4416 Cooper Rd",
    "sg:city":"Plant City",
    "sg:classifiers":[
        {
            "category":"Recreation",
            "type":"Entertainment"
        }
    ],
    "sg:phone":"+1 813 986 8812",
    "sg:postcode":"33565",
    "sg:province":"FL",
    "sg:tags":[
        "paint",
        "ball",
        "sport"
    ],
    "wof:name":"Herndon's Battle Supply",
    "wof:placetype":"venue"
},
  "geometry": {"coordinates":[-82.21614700000001,28.066306],"type":"Point"}
}