{
  "type": "Feature",
  "properties": {
    "iso:country":"US",
    "sg:address":"3450 SW 112th Pl",
    "sg:city":"Miami",
    "sg:classifiers":[
        {
            "category":"Shopping",
            "subcategory":"Clothing, Apparel, & Fashions",
            "type":"Retail Goods"
        }
    ],
    "sg:phone":"+1 305 223 2398",
    "sg:postcode":"33165",
    "sg:province":"FL",
    "wof:name":"Elite Fashion Design",
    "wof:placetype":"venue"
},
  "geometry": {"coordinates":[-80.37793499999999,25.737343],"type":"Point"}
}