{
  "type": "Feature",
  "properties": {
    "iso:country":"US",
    "sg:address":"141 Obrien Rd",
    "sg:city":"Casselberry",
    "sg:classifiers":[
        {
            "category":"Place Of Worship",
            "type":"Public Place"
        }
    ],
    "sg:phone":"+1 407 332 8151",
    "sg:postcode":"32730",
    "sg:province":"FL",
    "sg:tags":[
        "church"
    ],
    "wof:name":"Casselberry Four Square",
    "wof:placetype":"venue"
},
  "geometry": {"coordinates":[-81.35182,28.648649],"type":"Point"}
}