{
  "type": "Feature",
  "properties": {
    "iso:country":"US",
    "sg:address":"17 S Main St",
    "sg:city":"Lake Placid",
    "sg:classifiers":[
        {
            "category":"Personal",
            "subcategory":"Beauty Salon",
            "type":"Services"
        }
    ],
    "sg:phone":"+1 863 465 1292",
    "sg:postcode":"33852",
    "sg:province":"FL",
    "sg:tags":[
        "shop"
    ],
    "wof:name":"Hair Affair",
    "wof:placetype":"venue"
},
  "geometry": {"coordinates":[-81.366519,27.297025],"type":"Point"}
}