{
  "type": "Feature",
  "properties": {
    "addr:full":"3846 S Orlando Dr Sanford FL 32773",
    "addr:housenumber":"3846",
    "addr:postcode":"32773",
    "addr:street":"S Orlando Dr",
    "iso:country":"US",
    "sg:address":"3846 S Orlando Dr",
    "sg:city":"Sanford",
    "sg:classifiers":[
        {
            "category":"Building & Trades",
            "subcategory":"Landscaping Services",
            "type":"Services"
        }
    ],
    "sg:phone":"+1 407 328 8713",
    "sg:postcode":"32773",
    "sg:province":"FL",
    "sg:tags":[
        "landscape",
        "contractor"
    ],
    "wof:name":"Earth Tech Inc",
    "wof:placetype":"venue"
},
  "geometry": {"coordinates":[-81.287363,28.756407],"type":"Point"}
}