{
  "type": "Feature",
  "properties": {
    "addr:full":"1275 S Indies Cir Venice FL 34285",
    "addr:housenumber":"1275",
    "addr:postcode":"34285",
    "addr:street":"S Indies Cir",
    "iso:country":"US",
    "sg:address":"1275 S Indies Cir",
    "sg:city":"Venice",
    "sg:classifiers":[
        {
            "category":"Home & Garden",
            "subcategory":"Mobile Homes",
            "type":"Retail Goods"
        }
    ],
    "sg:phone":"+1 941 488 3433",
    "sg:postcode":"34285",
    "sg:province":"FL",
    "sg:tags":[
        "homes-repair"
    ],
    "wof:name":"Harry W Beeck",
    "wof:placetype":"venue"
},
  "geometry": {"coordinates":[-82.424573,27.11595],"type":"Point"}
}