{
  "type": "Feature",
  "properties": {
    "addr:full":"3201 E 4th Ave Hialeah FL 33013",
    "addr:housenumber":"3201",
    "addr:postcode":"33013",
    "addr:street":"E 4Th Ave",
    "iso:country":"US",
    "sg:address":"3201 E 4th Ave",
    "sg:city":"Hialeah",
    "sg:classifiers":[
        {
            "category":"Food & Beverages",
            "subcategory":"Groceries & Convenience Stores",
            "type":"Retail Goods"
        }
    ],
    "sg:phone":"+1 305 691 5538",
    "sg:postcode":"33013",
    "sg:province":"FL",
    "wof:name":"New Hialeah Supermarket",
    "wof:placetype":"venue"
},
  "geometry": {"coordinates":[-80.27469600000001,25.8515],"type":"Point"}
}