{
  "type": "Feature",
  "properties": {
    "addr:full":"2119 Jeanette St Tallahassee FL 32308",
    "addr:housenumber":"2119",
    "addr:postcode":"32308",
    "addr:street":"Jeanette St",
    "iso:country":"US",
    "sg:address":"2119 Jeanette St",
    "sg:city":"Tallahassee",
    "sg:classifiers":[
        {
            "category":"Real Estate",
            "subcategory":"Real Estate Agent",
            "type":"Services"
        }
    ],
    "sg:phone":"+1 850 386 6553",
    "sg:postcode":"32308",
    "sg:province":"FL",
    "wof:name":"Midtown Capital LLC",
    "wof:placetype":"venue"
},
  "geometry": {"coordinates":[-84.259843,30.468554],"type":"Point"}
}