{
  "type": "Feature",
  "properties": {
    "addr:full":"32 Northwest Blvd Miami FL 33126",
    "addr:housenumber":"32",
    "addr:postcode":"33126",
    "addr:street":"Northwest Blvd",
    "iso:country":"US",
    "sg:address":"32 Northwest Blvd",
    "sg:city":"Miami",
    "sg:classifiers":[
        {
            "category":"Building & Trades",
            "subcategory":"Locksmith",
            "type":"Services"
        }
    ],
    "sg:phone":"+1 786 718 1426",
    "sg:postcode":"33126",
    "sg:province":"FL",
    "sg:tags":[
        "key"
    ],
    "wof:name":"24 7 Locksmith",
    "wof:placetype":"venue"
},
  "geometry": {"coordinates":[-80.31429300000001,25.770908],"type":"Point"}
}