{
  "type": "Feature",
  "properties": {
    "addr:full":"716 N Wabash Ave Lakeland FL 33815",
    "addr:housenumber":"716",
    "addr:postcode":"33815",
    "addr:street":"N Wabash Ave",
    "iso:country":"US",
    "sg:address":"716 N Wabash Ave",
    "sg:city":"Lakeland",
    "sg:classifiers":[
        {
            "category":"Autos & Motor Vehicles",
            "subcategory":"Automobile Sales",
            "type":"Retail Goods"
        }
    ],
    "sg:phone":"+1 863 686 7422",
    "sg:postcode":"33815",
    "sg:province":"FL",
    "sg:tags":[
        "car",
        "dealer"
    ],
    "wof:name":"Express Auto Ctr",
    "wof:placetype":"venue"
},
  "geometry": {"coordinates":[-81.99025899999999,28.049636],"type":"Point"}
}