{
  "type": "Feature",
  "properties": {
    "iso:country":"US",
    "sg:address":"11950 SE Shell Ave",
    "sg:city":"Hobe Sound",
    "sg:classifiers":[
        {
            "category":"Manufacturing",
            "subcategory":"Lumber",
            "type":"Manufacturing & Wholesale Goods"
        }
    ],
    "sg:phone":"+1 772 546 6393",
    "sg:postcode":"33455",
    "sg:province":"FL",
    "sg:tags":[
        "mill"
    ],
    "wof:name":"V G Sands Inc",
    "wof:placetype":"venue"
},
  "geometry": {"coordinates":[-80.12740100000001,27.059918],"type":"Point"}
}