{
  "type": "Feature",
  "properties": {
    "addr:full":"28490 NE 55th Ave Okeechobee FL 34972",
    "addr:housenumber":"28490",
    "addr:postcode":"34972",
    "addr:street":"Ne 55Th Ave",
    "iso:country":"US",
    "sg:address":"28490 NE 55th Ave",
    "sg:city":"Okeechobee",
    "sg:classifiers":[
        {
            "category":"Farming",
            "subcategory":"Livestock Farm",
            "type":"Manufacturing & Wholesale Goods"
        }
    ],
    "sg:phone":"+1 863 763 5739",
    "sg:postcode":"34972",
    "sg:province":"FL",
    "sg:tags":[
        "apiary"
    ],
    "wof:name":"Southern Homesteads",
    "wof:placetype":"venue"
},
  "geometry": {"coordinates":[-80.76962,27.514746],"type":"Point"}
}