{
  "type": "Feature",
  "properties": {
    "iso:country":"US",
    "sg:address":"915 N Nova Rd",
    "sg:city":"Holly Hill",
    "sg:classifiers":[
        {
            "category":"Professional",
            "subcategory":"Lawyer & Legal Services",
            "type":"Services"
        }
    ],
    "sg:phone":"+1 386 257 2100",
    "sg:postcode":"32117",
    "sg:province":"FL",
    "sg:tags":[
        "attorney"
    ],
    "sg:website":"www.hillandponton.com",
    "wof:name":"Hill & Ponton Pa",
    "wof:placetype":"venue"
},
  "geometry": {"coordinates":[-81.04906,29.223326],"type":"Point"}
}