{
  "type": "Feature",
  "properties": {
    "iso:country":"US",
    "sg:address":"8131 Baymeadows Cir W",
    "sg:city":"Jacksonville",
    "sg:classifiers":[
        {
            "category":"Professional",
            "subcategory":"Employment Agencies",
            "type":"Services"
        }
    ],
    "sg:phone":"+1 904 394 1202",
    "sg:postcode":"32256",
    "sg:province":"FL",
    "sg:tags":[
        "help",
        "supply"
    ],
    "wof:name":"PhyCor Management Corp Florida",
    "wof:placetype":"venue"
},
  "geometry": {"coordinates":[-81.567481,30.228509],"type":"Point"}
}