{
  "type": "Feature",
  "properties": {
    "iso:country":"US",
    "sg:address":"617 Virginia Dr",
    "sg:city":"Orlando",
    "sg:classifiers":[
        {
            "category":"Professional",
            "subcategory":"Business Services",
            "type":"Services"
        }
    ],
    "sg:phone":"+1 407 897 3146",
    "sg:postcode":"32803",
    "sg:province":"FL",
    "sg:tags":[
        "interior",
        "consultant",
        "design",
        "decorator"
    ],
    "wof:name":"Cassone Home Style",
    "wof:placetype":"venue"
},
  "geometry": {"coordinates":[-81.368331,28.564072],"type":"Point"}
}