{
  "type": "Feature",
  "properties": {
    "iso:country":"US",
    "sg:address":"407 Lincoln Rd",
    "sg:city":"Miami Beach",
    "sg:classifiers":[
        {
            "category":"Professional",
            "subcategory":"Lawyer & Legal Services",
            "type":"Services"
        }
    ],
    "sg:phone":"+1 954 921 4700",
    "sg:postcode":"33139",
    "sg:province":"FL",
    "wof:name":"Kaplan S Richard Atty",
    "wof:placetype":"venue"
},
  "geometry": {"coordinates":[-80.13193699999999,25.790817],"type":"Point"}
}