{
  "type": "Feature",
  "properties": {
    "addr:full":"110 E Roberts St Orange City FL 32763",
    "addr:housenumber":"110",
    "addr:postcode":"32763",
    "addr:street":"E Roberts St",
    "iso:country":"US",
    "sg:address":"110 E Roberts St",
    "sg:city":"Orange City",
    "sg:classifiers":[
        {
            "category":"Retail",
            "subcategory":"Self-service Laundry",
            "type":"Services"
        }
    ],
    "sg:phone":"+1 386 775 0853",
    "sg:postcode":"32763",
    "sg:province":"FL",
    "sg:tags":[
        "coin"
    ],
    "wof:name":"Breezewood Laundry Inc",
    "wof:placetype":"venue"
},
  "geometry": {"coordinates":[-81.297985,28.924918],"type":"Point"}
}