{
  "type": "Feature",
  "properties": {
    "iso:country":"US",
    "sg:address":"212 Tinsley Rd",
    "sg:city":"Florahome",
    "sg:classifiers":[
        {
            "category":"Retail",
            "subcategory":"Animal Services",
            "type":"Services"
        }
    ],
    "sg:phone":"+1 386 659 1393",
    "sg:postcode":"32140",
    "sg:province":"FL",
    "wof:name":"High Stakes Farm",
    "wof:placetype":"venue"
},
  "geometry": {"coordinates":[-81.85933799999999,29.781216],"type":"Point"}
}