{
  "type": "Feature",
  "properties": {
    "iso:country":"US",
    "sg:address":"210 Bamboo Dr",
    "sg:city":"Sanford",
    "sg:classifiers":[
        {
            "category":"Manufacturing",
            "subcategory":"Buildings",
            "type":"Manufacturing & Wholesale Goods"
        },
        {
            "category":"Home & Garden",
            "subcategory":"Building Materials",
            "type":"Retail Goods"
        },
        {
            "category":"Building & Trades",
            "subcategory":"Construction",
            "type":"Services"
        }
    ],
    "sg:phone":"+1 407 688 1747",
    "sg:postcode":"32773",
    "sg:province":"FL",
    "sg:tags":[
        "concrete",
        "builder",
        "staining",
        "contractor"
    ],
    "wof:name":"B N G Construction",
    "wof:placetype":"venue"
},
  "geometry": {"coordinates":[-81.285954,28.748608],"type":"Point"}
}