{
  "type": "Feature",
  "properties": {
    "addr:full":"3195 N 36th Ave Hollywood FL 33021",
    "addr:housenumber":"3195",
    "addr:postcode":"33021",
    "addr:street":"N 36Th Ave",
    "iso:country":"US",
    "sg:address":"3195 N 36th Ave",
    "sg:city":"Hollywood",
    "sg:classifiers":[
        {
            "category":"Recreation",
            "type":"Entertainment"
        }
    ],
    "sg:phone":"+1 954 989 7979",
    "sg:postcode":"33021",
    "sg:province":"FL",
    "sg:tags":[
        "ticket"
    ],
    "wof:name":"A Great Place To Sit",
    "wof:placetype":"venue"
},
  "geometry": {"coordinates":[-80.180331,26.038673],"type":"Point"}
}