{
  "type": "Feature",
  "properties": {
    "iso:country":"US",
    "sg:address":"1162 NW 54th St",
    "sg:city":"Miami",
    "sg:classifiers":[
        {
            "category":"Shopping",
            "subcategory":"Mobile Phones",
            "type":"Retail Goods"
        }
    ],
    "sg:phone":"+1 305 757 4363",
    "sg:postcode":"33127",
    "sg:province":"FL",
    "sg:website":"www.radioshack.com",
    "wof:name":"Radioshack",
    "wof:placetype":"venue"
},
  "geometry": {"coordinates":[-80.21520200000001,25.8248],"type":"Point"}
}