{
  "type": "Feature",
  "properties": {
    "addr:full":"16199 US Hwy 331 S Freeport FL 32439",
    "addr:housenumber":"16199",
    "addr:postcode":"32439",
    "addr:street":"Us Hwy 331 S",
    "iso:country":"US",
    "sg:address":"16199 US Hwy 331 S",
    "sg:city":"Freeport",
    "sg:classifiers":[
        {
            "category":"Food & Beverages",
            "subcategory":"Liquor & Beverages",
            "type":"Retail Goods"
        }
    ],
    "sg:phone":"+1 850 243 4113",
    "sg:postcode":"32439",
    "sg:province":"FL",
    "sg:tags":[
        "alcoholic"
    ],
    "wof:name":"Cashs",
    "wof:placetype":"venue"
},
  "geometry": {"coordinates":[-86.121736,30.490015],"type":"Point"}
}