{
  "type": "Feature",
  "properties": {
    "addr:full":"2600 Lake Lucien Dr Maitland FL 32751",
    "addr:housenumber":"2600",
    "addr:postcode":"32751",
    "addr:street":"Lake Lucien Dr",
    "iso:country":"US",
    "sg:address":"2600 Lake Lucien Dr",
    "sg:city":"Maitland",
    "sg:classifiers":[
        {
            "category":"Education",
            "subcategory":"University",
            "type":"Public Place"
        }
    ],
    "sg:phone":"+1 407 660 2900",
    "sg:postcode":"32751",
    "sg:province":"FL",
    "sg:tags":[
        "college"
    ],
    "sg:website":"www.itt-tech.edu",
    "wof:name":"ITT Technical Institute",
    "wof:placetype":"venue"
},
  "geometry": {"coordinates":[-81.395754,28.630356],"type":"Point"}
}