{
  "type": "Feature",
  "properties": {
    "addr:full":"1885 Lee Rd Winter Park FL 32789",
    "addr:housenumber":"1885",
    "addr:postcode":"32789",
    "addr:street":"Lee Rd",
    "iso:country":"US",
    "sg:address":"1885 Lee Rd",
    "sg:city":"Winter Park",
    "sg:classifiers":[
        {
            "category":"Building & Trades",
            "subcategory":"Construction",
            "type":"Services"
        }
    ],
    "sg:phone":"+1 407 539 2522",
    "sg:postcode":"32789",
    "sg:province":"FL",
    "sg:tags":[
        "paving",
        "contractor"
    ],
    "wof:name":"J A Pavers",
    "wof:placetype":"venue"
},
  "geometry": {"coordinates":[-81.373,28.605997],"type":"Point"}
}