{
  "type": "Feature",
  "properties": {
    "iso:country":"US",
    "sg:address":"301 W Nine Mile Rd",
    "sg:city":"Pensacola",
    "sg:classifiers":[
        {
            "category":"Recreation",
            "type":"Entertainment"
        }
    ],
    "sg:phone":"+1 850 478 0680",
    "sg:postcode":"32534",
    "sg:province":"FL",
    "sg:tags":[
        "martial",
        "arts",
        "instruction"
    ],
    "wof:name":"Pensacola Tang Soo Do Academy",
    "wof:placetype":"venue"
},
  "geometry": {"coordinates":[-87.279409,30.533457],"type":"Point"}
}