{
  "type": "Feature",
  "properties": {
    "iso:country":"US",
    "sg:address":"1105 Lane Ave N",
    "sg:city":"Jacksonville",
    "sg:classifiers":[
        {
            "category":"Wholesale",
            "subcategory":"Machinery & Supplies",
            "type":"Manufacturing & Wholesale Goods"
        }
    ],
    "sg:phone":"+1 904 783 6000",
    "sg:postcode":"32254",
    "sg:province":"FL",
    "sg:tags":[
        "equipment",
        "industrial",
        "manufacturer",
        "pumps-wholesale"
    ],
    "sg:website":"http://www.arroyoprocess.com",
    "wof:name":"Arroyo Process Equipment Inc",
    "wof:placetype":"venue"
},
  "geometry": {"coordinates":[-81.752064,30.337213],"type":"Point"}
}