{
  "type": "Feature",
  "properties": {
    "iso:country":"US",
    "sg:address":"425 NW 12th Ave",
    "sg:city":"Miami",
    "sg:classifiers":[
        {
            "category":"Autos & Motor Vehicles",
            "subcategory":"Auto Supplies",
            "type":"Retail Goods"
        }
    ],
    "sg:phone":"+1 305 324 4994",
    "sg:postcode":"33128",
    "sg:province":"FL",
    "sg:tags":[
        "automobile",
        "parts"
    ],
    "wof:name":"Miami Auto Parts",
    "wof:placetype":"venue"
},
  "geometry": {"coordinates":[-80.21471200000001,25.778103],"type":"Point"}
}