{
  "type": "Feature",
  "properties": {
    "addr:full":"681 Hickory Manor Dr Jacksonville FL 32225",
    "addr:housenumber":"681",
    "addr:postcode":"32225",
    "addr:street":"Hickory Manor Dr",
    "iso:country":"US",
    "sg:address":"681 Hickory Manor Dr",
    "sg:city":"Jacksonville",
    "sg:classifiers":[
        {
            "category":"Building & Trades",
            "subcategory":"Construction",
            "type":"Services"
        }
    ],
    "sg:phone":"+1 904 221 3847",
    "sg:postcode":"32225",
    "sg:province":"FL",
    "sg:tags":[
        "house"
    ],
    "wof:name":"KB Home Handyman Services Inc",
    "wof:placetype":"venue"
},
  "geometry": {"coordinates":[-81.47653800000001,30.333394],"type":"Point"}
}