{
  "type": "Feature",
  "properties": {
    "iso:country":"US",
    "sg:address":"2047 Wilton Dr",
    "sg:city":"Wilton Manors",
    "sg:classifiers":[
        {
            "category":"Personal",
            "subcategory":"Beauty Salon",
            "type":"Services"
        }
    ],
    "sg:phone":"+1 954 630 3101",
    "sg:postcode":"33305",
    "sg:province":"FL",
    "wof:name":"Thomas Williamson",
    "wof:placetype":"venue"
},
  "geometry": {"coordinates":[-80.14036400000001,26.153675],"type":"Point"}
}