{
  "type": "Feature",
  "properties": {
    "iso:country":"US",
    "sg:address":"200 State Hwy 206 E",
    "sg:city":"Saint Augustine",
    "sg:classifiers":[
        {
            "category":"Freight",
            "type":"Transportation"
        }
    ],
    "sg:phone":"+1 904 797 6464",
    "sg:postcode":"32086",
    "sg:province":"FL",
    "sg:tags":[
        "general"
    ],
    "wof:name":"U-Store-It Mini Warehouse Co",
    "wof:placetype":"venue"
},
  "geometry": {"coordinates":[-81.307788,29.756619],"type":"Point"}
}