{
  "type": "Feature",
  "properties": {
    "iso:country":"US",
    "sg:address":"312 Shopping Center Dr",
    "sg:city":"Wildwood",
    "sg:classifiers":[
        {
            "category":"Professional",
            "subcategory":"Accounting & Tax Preparation",
            "type":"Services"
        }
    ],
    "sg:phone":"+1 352 748 6552",
    "sg:postcode":"34785",
    "sg:province":"FL",
    "sg:tags":[
        "return",
        "filing"
    ],
    "sg:website":"http://www.jacksonhewitt.com/",
    "wof:name":"Jackson Hewitt Tax Service",
    "wof:placetype":"venue"
},
  "geometry": {"coordinates":[-82.040733,28.860577],"type":"Point"}
}