{
  "type": "Feature",
  "properties": {
    "addr:full":"553 Milestone Blvd Cantonment FL 32533",
    "addr:housenumber":"553",
    "addr:postcode":"32533",
    "addr:street":"Milestone Blvd",
    "iso:country":"US",
    "sg:address":"553 Milestone Blvd",
    "sg:city":"Cantonment",
    "sg:classifiers":[
        {
            "category":"Real Estate",
            "subcategory":"Real Estate Services",
            "type":"Services"
        }
    ],
    "sg:phone":"+1 850 494 0333",
    "sg:postcode":"32533",
    "sg:province":"FL",
    "sg:tags":[
        "management"
    ],
    "wof:name":"Seascape Investment",
    "wof:placetype":"venue"
},
  "geometry": {"coordinates":[-87.307762,30.538121],"type":"Point"}
}