{
  "type": "Feature",
  "properties": {
    "iso:country":"US",
    "sg:address":"1908 S McCall Rd",
    "sg:city":"Englewood",
    "sg:classifiers":[
        {
            "category":"Autos & Motor Vehicles",
            "subcategory":"Automobile Sales",
            "type":"Retail Goods"
        }
    ],
    "sg:phone":"+1 941 475 5444",
    "sg:postcode":"34223",
    "sg:province":"FL",
    "sg:tags":[
        "car",
        "dealer"
    ],
    "sg:website":"www.bayharborford.com",
    "wof:name":"Bay Harbor Ford",
    "wof:placetype":"venue"
},
  "geometry": {"coordinates":[-82.33534,26.937798],"type":"Point"}
}