{
  "type": "Feature",
  "properties": {
    "addr:full":"100 Lake Hart Dr Orlando FL 32832",
    "addr:housenumber":"100",
    "addr:postcode":"32832",
    "addr:street":"Lake Hart Dr",
    "iso:country":"US",
    "sg:address":"100 Lake Hart Dr",
    "sg:city":"Orlando",
    "sg:classifiers":[
        {
            "category":"Organizations",
            "subcategory":"Religious Organization",
            "type":"Services"
        }
    ],
    "sg:phone":"+1 407 826 2000",
    "sg:postcode":"32832",
    "sg:province":"FL",
    "wof:name":"New Life Publications",
    "wof:placetype":"venue"
},
  "geometry": {"coordinates":[-81.202027,28.409288],"type":"Point"}
}