{
  "type": "Feature",
  "properties": {
    "addr:full":"289 Goolsby Blvd Deerfield Beach FL 33442",
    "addr:housenumber":"289",
    "addr:postcode":"33442",
    "addr:street":"Goolsby Blvd",
    "iso:country":"US",
    "sg:address":"289 Goolsby Blvd",
    "sg:city":"Deerfield Beach",
    "sg:classifiers":[
        {
            "category":"Building & Trades",
            "subcategory":"Plumbing",
            "type":"Services"
        }
    ],
    "sg:phone":"+1 954 421 8656",
    "sg:postcode":"33442",
    "sg:province":"FL",
    "sg:tags":[
        "conditioning",
        "air",
        "system",
        "contractor"
    ],
    "wof:name":"Cameron Jones Air Conditioning",
    "wof:placetype":"venue"
},
  "geometry": {"coordinates":[-80.12602,26.313519],"type":"Point"}
}