{
  "type": "Feature",
  "properties": {
    "addr:full":"800 Brickell Ave Miami FL 33131",
    "addr:housenumber":"800",
    "addr:postcode":"33131",
    "addr:street":"Brickell Ave",
    "iso:country":"US",
    "sg:address":"800 Brickell Ave",
    "sg:city":"Miami",
    "sg:classifiers":[
        {
            "category":"Professional",
            "subcategory":"Art Services",
            "type":"Services"
        },
        {
            "category":"Professional",
            "subcategory":"Business Services",
            "type":"Services"
        },
        {
            "category":"Building & Trades",
            "subcategory":"Construction",
            "type":"Services"
        },
        {
            "category":"Real Estate",
            "subcategory":"Architect",
            "type":"Services"
        }
    ],
    "sg:phone":"+1 305 372 5177",
    "sg:postcode":"33131",
    "sg:province":"FL",
    "sg:tags":[
        "development",
        "product",
        "designer",
        "designers-industrial",
        "marketing",
        "commercial",
        "design",
        "interior",
        "decorator"
    ],
    "wof:name":"Nichols Page Design Associates Inc",
    "wof:placetype":"venue"
},
  "geometry": {"coordinates":[-80.190918,25.766212],"type":"Point"}
}