{
  "type": "Feature",
  "properties": {
    "iso:country":"US",
    "sg:address":"1414 20th St",
    "sg:city":"Miami Beach",
    "sg:classifiers":[
        {
            "category":"Food & Beverages",
            "subcategory":"Liquor & Beverages",
            "type":"Retail Goods"
        }
    ],
    "sg:phone":"+1 305 538 2985",
    "sg:postcode":"33139",
    "sg:province":"FL",
    "sg:tags":[
        "beer",
        "spirit",
        "wine"
    ],
    "wof:name":"Azul Spirits & Wine & Liquor",
    "wof:placetype":"venue"
},
  "geometry": {"coordinates":[-80.14386,25.795401],"type":"Point"}
}