{
  "type": "Feature",
  "properties": {
    "iso:country":"US",
    "sg:address":"565 Teak Dr",
    "sg:city":"Melbourne",
    "sg:classifiers":[
        {
            "category":"Building & Trades",
            "subcategory":"Construction",
            "type":"Services"
        }
    ],
    "sg:phone":"+1 321 752 7633",
    "sg:postcode":"32935",
    "sg:province":"FL",
    "sg:tags":[
        "tile",
        "dealer"
    ],
    "wof:name":"David Sherwood Tile & Marble",
    "wof:placetype":"venue"
},
  "geometry": {"coordinates":[-80.642854,28.116214],"type":"Point"}
}