{
  "type": "Feature",
  "properties": {
    "addr:full":"10956 106th Ln N Largo FL 33773",
    "addr:housenumber":"10956",
    "addr:postcode":"33773",
    "addr:street":"106Th Ln N",
    "iso:country":"US",
    "sg:address":"10956 106th Ln N",
    "sg:city":"Largo",
    "sg:classifiers":[
        {
            "category":"Professional",
            "subcategory":"Management & Consulting",
            "type":"Services"
        }
    ],
    "sg:phone":"+1 727 394 0314",
    "sg:postcode":"33773",
    "sg:province":"FL",
    "sg:tags":[
        "public",
        "relations"
    ],
    "wof:name":"Cash Promotions Inc",
    "wof:placetype":"venue"
},
  "geometry": {"coordinates":[-82.78623399999999,27.872021],"type":"Point"}
}