{
  "type": "Feature",
  "properties": {
    "iso:country":"US",
    "sg:address":"1655 W 49th St",
    "sg:city":"Hialeah",
    "sg:classifiers":[
        {
            "category":"Shopping Center",
            "type":"Public Place"
        }
    ],
    "sg:phone":"+1 305 828 7779",
    "sg:postcode":"33012",
    "sg:province":"FL",
    "wof:name":"Westland Mall Dental",
    "wof:placetype":"venue"
},
  "geometry": {"coordinates":[-80.316457,25.866807],"type":"Point"}
}