{
  "type": "Feature",
  "properties": {
    "addr:full":"4393 Virginia Dr Orlando FL 32814",
    "addr:housenumber":"4393",
    "addr:postcode":"32814",
    "addr:street":"Virginia Dr",
    "iso:country":"US",
    "sg:address":"4393 Virginia Dr",
    "sg:city":"Orlando",
    "sg:classifiers":[
        {
            "category":"Shopping",
            "type":"Retail Goods"
        }
    ],
    "sg:phone":"+1 407 897 6608",
    "sg:postcode":"32814",
    "sg:province":"FL",
    "sg:tags":[
        "chemical"
    ],
    "wof:name":"BDP Innovative Chemicals",
    "wof:placetype":"venue"
},
  "geometry": {"coordinates":[-81.33252,28.56466],"type":"Point"}
}