{
  "type": "Feature",
  "properties": {
    "iso:country":"US",
    "sg:address":"5220 Cleveland Rd",
    "sg:city":"Jacksonville",
    "sg:classifiers":[
        {
            "category":"Organizations",
            "subcategory":"Religious Organization",
            "type":"Services"
        }
    ],
    "sg:phone":"+1 904 764 8854",
    "sg:postcode":"32209",
    "sg:province":"FL",
    "sg:tags":[
        "church"
    ],
    "wof:name":"Love Missionary Baptist Chr",
    "wof:placetype":"venue"
},
  "geometry": {"coordinates":[-81.707415,30.36642],"type":"Point"}
}