{
  "type": "Feature",
  "properties": {
    "iso:country":"US",
    "sg:address":"3750 Lakeside Village Ct",
    "sg:city":"Lakeland",
    "sg:classifiers":[
        {
            "category":"Restaurant",
            "type":"Food & Drink"
        }
    ],
    "sg:menulink":"http://www.allmenus.com/fl/lakeland/110036-chilis/menu/",
    "sg:phone":"+1 863 688 6210",
    "sg:postcode":"33803",
    "sg:province":"FL",
    "sg:tags":[
        "burger",
        "american",
        "sandwich",
        "tex-mex",
        "soup"
    ],
    "wof:name":"Chili's",
    "wof:placetype":"venue"
},
  "geometry": {"coordinates":[-81.976477,27.998591],"type":"Point"}
}