{
  "type": "Feature",
  "properties": {
    "iso:country":"US",
    "sg:address":"1138 Obispo Ave",
    "sg:city":"Miami",
    "sg:classifiers":[
        {
            "category":"Professional",
            "type":"Services"
        }
    ],
    "sg:phone":"+1 305 448 8799",
    "sg:postcode":"33134",
    "sg:province":"FL",
    "wof:name":"Har Core Inc",
    "wof:placetype":"venue"
},
  "geometry": {"coordinates":[-80.278609,25.755011],"type":"Point"}
}