{
  "type": "Feature",
  "properties": {
    "addr:full":"1 Colonial Club Dr Boynton Beach FL 33435",
    "addr:housenumber":"1",
    "addr:postcode":"33435",
    "addr:street":"Colonial Club Dr",
    "iso:country":"US",
    "sg:address":"1 Colonial Club Dr",
    "sg:city":"Boynton Beach",
    "sg:classifiers":[
        {
            "category":"Professional",
            "type":"Services"
        }
    ],
    "sg:phone":"+1 561 375 8541",
    "sg:postcode":"33435",
    "sg:province":"FL",
    "wof:name":"Susan Jean Horne P A",
    "wof:placetype":"venue"
},
  "geometry": {"coordinates":[-80.05941199999999,26.50087],"type":"Point"}
}