{
  "type": "Feature",
  "properties": {
    "addr:full":"2895 Collins Ave Miami FL 33140",
    "addr:housenumber":"2895",
    "addr:postcode":"33140",
    "addr:street":"Collins Ave",
    "iso:country":"US",
    "sg:address":"2895 Collins Ave",
    "sg:city":"Miami",
    "sg:classifiers":[
        {
            "category":"Travel",
            "subcategory":"Travel Agent",
            "type":"Entertainment"
        }
    ],
    "sg:phone":"+1 305 538 1555",
    "sg:postcode":"33140",
    "sg:province":"FL",
    "sg:tags":[
        "agency",
        "bureau"
    ],
    "wof:name":"Air World Travel Services Inc",
    "wof:placetype":"venue"
},
  "geometry": {"coordinates":[-80.12535099999999,25.804373],"type":"Point"}
}