{
  "type": "Feature",
  "properties": {
    "addr:full":"1324 Seven Springs Blvd New Port Richey FL 34655",
    "addr:housenumber":"1324",
    "addr:postcode":"34655",
    "addr:street":"Seven Springs Blvd",
    "iso:country":"US",
    "sg:address":"1324 Seven Springs Blvd",
    "sg:city":"New Port Richey",
    "sg:classifiers":[
        {
            "category":"Manufacturing",
            "subcategory":"Glass & Minerals",
            "type":"Manufacturing & Wholesale Goods"
        }
    ],
    "sg:phone":"+1 727 943 9945",
    "sg:postcode":"34655",
    "sg:province":"FL",
    "sg:tags":[
        "wool",
        "mfg"
    ],
    "wof:name":"Owens Corning",
    "wof:placetype":"venue"
},
  "geometry": {"coordinates":[-82.69888,28.184605],"type":"Point"}
}