{
  "type": "Feature",
  "properties": {
    "addr:full":"3963 Carambola Cir N Coconut Creek FL 33066",
    "addr:postcode":"3963;33066",
    "addr:street":"Carambola Cir N",
    "iso:country":"US",
    "sg:address":"3963 Carambola Cir N",
    "sg:city":"Coconut Creek",
    "sg:classifiers":[
        {
            "category":"Wholesale",
            "subcategory":"Machinery & Supplies",
            "type":"Manufacturing & Wholesale Goods"
        },
        {
            "category":"Wholesale",
            "subcategory":"Electrical",
            "type":"Manufacturing & Wholesale Goods"
        }
    ],
    "sg:phone":"+1 954 973 3665",
    "sg:postcode":"33066",
    "sg:province":"FL",
    "sg:tags":[
        "equipment",
        "plant",
        "industrial",
        "power"
    ],
    "wof:name":"Rickey Bocchini",
    "wof:placetype":"venue"
},
  "geometry": {"coordinates":[-80.18092,26.270751],"type":"Point"}
}