{
  "type": "Feature",
  "properties": {
    "iso:country":"US",
    "sg:address":"2150 NW 5th St",
    "sg:city":"Boca Raton",
    "sg:classifiers":[
        {
            "category":"Shopping",
            "subcategory":"Clothing, Apparel, & Fashions",
            "type":"Retail Goods"
        }
    ],
    "sg:phone":"+1 561 395 0319",
    "sg:postcode":"33486",
    "sg:province":"FL",
    "wof:name":"Uniforms 2000",
    "wof:placetype":"venue"
},
  "geometry": {"coordinates":[-80.127923,26.354874],"type":"Point"}
}