{
  "type": "Feature",
  "properties": {
    "addr:full":"4711 N Manhattan Ave Tampa FL 33614",
    "addr:housenumber":"4711",
    "addr:postcode":"33614",
    "addr:street":"N Manhattan Ave",
    "iso:country":"US",
    "sg:address":"4711 N Manhattan Ave",
    "sg:city":"Tampa",
    "sg:classifiers":[
        {
            "category":"Manufacturing",
            "subcategory":"Motor Vehicles & Parts",
            "type":"Manufacturing & Wholesale Goods"
        }
    ],
    "sg:phone":"+1 813 871 3273",
    "sg:postcode":"33614",
    "sg:province":"FL",
    "sg:tags":[
        "trailer",
        "mfg"
    ],
    "sg:website":"www.specialtytrailer.com",
    "wof:name":"Specialty Trailer Corp",
    "wof:placetype":"venue"
},
  "geometry": {"coordinates":[-82.51755199999999,27.987878],"type":"Point"}
}