{
  "type": "Feature",
  "properties": {
    "iso:country":"US",
    "sg:address":"4513 Diamond Cir N",
    "sg:city":"Sarasota",
    "sg:classifiers":[
        {
            "category":"Retail",
            "subcategory":"Self-service Laundry",
            "type":"Services"
        }
    ],
    "sg:phone":"+1 941 927 4993",
    "sg:postcode":"34233",
    "sg:province":"FL",
    "sg:tags":[
        "coin"
    ],
    "wof:name":"Paul F Nye Jr",
    "wof:placetype":"venue"
},
  "geometry": {"coordinates":[-82.47035099999999,27.291003],"type":"Point"}
}