{
  "type": "Feature",
  "properties": {
    "addr:full":"1125 Grant St West Palm Beach FL 33407",
    "addr:housenumber":"1125",
    "addr:postcode":"33407",
    "addr:street":"Grant St",
    "iso:country":"US",
    "sg:address":"1125 Grant St",
    "sg:city":"West Palm Beach",
    "sg:classifiers":[
        {
            "category":"Social Services",
            "subcategory":"Child Care",
            "type":"Services"
        }
    ],
    "sg:phone":"+1 561 832 3333",
    "sg:postcode":"33407",
    "sg:province":"FL",
    "wof:name":"Apostolic Children Academy",
    "wof:placetype":"venue"
},
  "geometry": {"coordinates":[-80.062264,26.731266],"type":"Point"}
}