{
  "type": "Feature",
  "properties": {
    "addr:full":"19356 SW 65th St Fort Lauderdale FL 33332",
    "addr:housenumber":"19356",
    "addr:postcode":"33332",
    "addr:street":"Sw 65Th St",
    "iso:country":"US",
    "sg:address":"19356 SW 65th St",
    "sg:city":"Fort Lauderdale",
    "sg:classifiers":[
        {
            "category":"Professional",
            "subcategory":"Computer Services",
            "type":"Services"
        }
    ],
    "sg:phone":"+1 954 252 1660",
    "sg:postcode":"33332",
    "sg:province":"FL",
    "sg:tags":[
        "internet"
    ],
    "wof:name":"Action Scooters",
    "wof:placetype":"venue"
},
  "geometry": {"coordinates":[-80.40588200000001,26.036921],"type":"Point"}
}