{
  "type": "Feature",
  "properties": {
    "iso:country":"US",
    "sg:address":"2320 1st St",
    "sg:city":"Fort Myers",
    "sg:classifiers":[
        {
            "category":"Real Estate",
            "subcategory":"Real Estate Operator",
            "type":"Services"
        }
    ],
    "sg:phone":"+1 239 461 8778",
    "sg:postcode":"33901",
    "sg:province":"FL",
    "sg:tags":[
        "apartment"
    ],
    "wof:name":"Franklin Arms Court",
    "wof:placetype":"venue"
},
  "geometry": {"coordinates":[-81.86840100000001,26.645],"type":"Point"}
}