{
  "type": "Feature",
  "properties": {
    "iso:country":"US",
    "sg:address":"728 SW Pine Island Rd",
    "sg:city":"Cape Coral",
    "sg:classifiers":[
        {
            "category":"Professional",
            "type":"Services"
        }
    ],
    "sg:phone":"+1 239 772 2800",
    "sg:postcode":"33991",
    "sg:province":"FL",
    "sg:tags":[
        "caterer"
    ],
    "wof:name":"I Like It Like That",
    "wof:placetype":"venue"
},
  "geometry": {"coordinates":[-81.991178,26.644464],"type":"Point"}
}