{
  "type": "Feature",
  "properties": {
    "iso:country":"US",
    "sg:address":"11525 US Hwy 92",
    "sg:city":"Seffner",
    "sg:classifiers":[
        {
            "category":"Home & Garden",
            "subcategory":"Mobile Homes",
            "type":"Retail Goods"
        }
    ],
    "sg:phone":"+1 813 626 1957",
    "sg:postcode":"33584",
    "sg:province":"FL",
    "wof:name":"Riley Mobile Homes Inc",
    "wof:placetype":"venue"
},
  "geometry": {"coordinates":[-82.303307,28.001578],"type":"Point"}
}