{
  "type": "Feature",
  "properties": {
    "addr:full":"1121 Overcash Dr Dunedin FL 34698",
    "addr:housenumber":"1121",
    "addr:postcode":"34698",
    "addr:street":"Overcash Dr",
    "iso:country":"US",
    "sg:address":"1121 Overcash Dr",
    "sg:city":"Dunedin",
    "sg:classifiers":[
        {
            "category":"Health Services",
            "subcategory":"Doctor",
            "type":"Services"
        }
    ],
    "sg:phone":"+1 727 734 0555",
    "sg:postcode":"34698",
    "sg:province":"FL",
    "sg:tags":[
        "physician",
        "surgeon"
    ],
    "wof:name":"Main Street Medical",
    "wof:placetype":"venue"
},
  "geometry": {"coordinates":[-82.75598100000001,28.019509],"type":"Point"}
}