{
  "type": "Feature",
  "properties": {
    "addr:full":"130 NE 62nd St Miami FL 33138",
    "addr:housenumber":"130",
    "addr:postcode":"33138",
    "addr:street":"Ne 62Nd St",
    "iso:country":"US",
    "sg:address":"130 NE 62nd St",
    "sg:city":"Miami",
    "sg:classifiers":[
        {
            "category":"Social Services",
            "type":"Services"
        }
    ],
    "sg:phone":"+1 305 759 3050",
    "sg:postcode":"33138",
    "sg:province":"FL",
    "sg:tags":[
        "organization",
        "welfare"
    ],
    "wof:name":"Catholic Charities-Archdiocese",
    "wof:placetype":"venue"
},
  "geometry": {"coordinates":[-80.19430699999999,25.832693],"type":"Point"}
}