{
  "type": "Feature",
  "properties": {
    "addr:full":"4828 N Armenia Ave Tampa FL 33603",
    "addr:housenumber":"4828",
    "addr:postcode":"33603",
    "addr:street":"N Armenia Ave",
    "iso:country":"US",
    "sg:address":"4828 N Armenia Ave",
    "sg:city":"Tampa",
    "sg:classifiers":[
        {
            "category":"Education",
            "subcategory":"Special Training",
            "type":"Public Place"
        }
    ],
    "sg:phone":"+1 813 353 1409",
    "sg:postcode":"33603",
    "sg:province":"FL",
    "sg:tags":[
        "instruction",
        "driving"
    ],
    "sg:website":"www.24-7trafficschoolofflorida.com",
    "wof:name":"Alberto Pastrana Financial Svc",
    "wof:placetype":"venue"
},
  "geometry": {"coordinates":[-82.48461,27.990492],"type":"Point"}
}