{
  "type": "Feature",
  "properties": {
    "iso:country":"US",
    "sg:address":"18978 NE 4th Ct",
    "sg:city":"Miami",
    "sg:classifiers":[
        {
            "category":"Shopping",
            "subcategory":"Stationery & Office Supplies",
            "type":"Retail Goods"
        }
    ],
    "sg:phone":"+1 305 770 2694",
    "sg:postcode":"33179",
    "sg:province":"FL",
    "wof:name":"Microjen Corp",
    "wof:placetype":"venue"
},
  "geometry": {"coordinates":[-80.19238799999999,25.950056],"type":"Point"}
}