{
  "type": "Feature",
  "properties": {
    "addr:full":"1158 Belden Ln Gulf Breeze FL 32563",
    "addr:housenumber":"1158",
    "addr:postcode":"32563",
    "addr:street":"Belden Ln",
    "iso:country":"US",
    "sg:address":"1158 Belden Ln",
    "sg:city":"Gulf Breeze",
    "sg:classifiers":[
        {
            "category":"Professional",
            "type":"Services"
        }
    ],
    "sg:phone":"+1 850 916 0842",
    "sg:postcode":"32563",
    "sg:province":"FL",
    "wof:name":"Labelle Laser Services Inc",
    "wof:placetype":"venue"
},
  "geometry": {"coordinates":[-87.111645,30.379399],"type":"Point"}
}