{
  "type": "Feature",
  "properties": {
    "addr:full":"1116 Peach Tree Dr Lake Placid FL 33852",
    "addr:housenumber":"1116",
    "addr:postcode":"33852",
    "addr:street":"Peach Tree Dr",
    "iso:country":"US",
    "sg:address":"1116 Peach Tree Dr",
    "sg:city":"Lake Placid",
    "sg:classifiers":[
        {
            "category":"Wholesale",
            "subcategory":"Farm Supplies",
            "type":"Manufacturing & Wholesale Goods"
        }
    ],
    "sg:phone":"+1 863 699 6281",
    "sg:postcode":"33852",
    "sg:province":"FL",
    "sg:tags":[
        "equipment",
        "greenhouse"
    ],
    "wof:name":"Seed-E-Z Seeder",
    "wof:placetype":"venue"
},
  "geometry": {"coordinates":[-81.416635,27.332407],"type":"Point"}
}