{
  "type": "Feature",
  "properties": {
    "iso:country":"US",
    "sg:address":"900 W 49th St",
    "sg:city":"Hialeah",
    "sg:classifiers":[
        {
            "category":"Banks & Credit Unions",
            "subcategory":"Bank",
            "type":"Services"
        }
    ],
    "sg:phone":"+1 305 822 6400",
    "sg:postcode":"33012",
    "sg:province":"FL",
    "sg:tags":[
        "loan",
        "real estate"
    ],
    "wof:name":"Match Funding Mortgage Inc",
    "wof:placetype":"venue"
},
  "geometry": {"coordinates":[-80.301322,25.866569],"type":"Point"}
}