{
  "type": "Feature",
  "properties": {
    "addr:full":"815 8th Ave W Palmetto FL 34221",
    "addr:housenumber":"815",
    "addr:postcode":"34221",
    "addr:street":"8Th Ave W",
    "iso:country":"US",
    "sg:address":"815 8th Ave W",
    "sg:city":"Palmetto",
    "sg:classifiers":[
        {
            "category":"Restaurant",
            "type":"Food & Drink"
        }
    ],
    "sg:phone":"+1 941 721 9525",
    "sg:postcode":"34221",
    "sg:province":"FL",
    "sg:tags":[
        "eating"
    ],
    "wof:name":"Popi's Place Too",
    "wof:placetype":"venue"
},
  "geometry": {"coordinates":[-82.572937,27.519141],"type":"Point"}
}