{
  "type": "Feature",
  "properties": {
    "addr:full":"2581 Lake Ave Miami Beach FL 33140",
    "addr:housenumber":"2581",
    "addr:postcode":"33140",
    "addr:street":"Lake Ave",
    "iso:country":"US",
    "sg:address":"2581 Lake Ave",
    "sg:city":"Miami Beach",
    "sg:classifiers":[
        {
            "category":"Professional",
            "type":"Services"
        }
    ],
    "sg:phone":"+1 305 695 8866",
    "sg:postcode":"33140",
    "sg:province":"FL",
    "sg:tags":[
        "establishment"
    ],
    "wof:name":"John Turchin",
    "wof:placetype":"venue"
},
  "geometry": {"coordinates":[-80.14206799999999,25.80207],"type":"Point"}
}