{
  "type": "Feature",
  "properties": {
    "addr:full":"380 N State Rd 434 Altamonte Spgs FL 32714",
    "addr:housenumber":"380",
    "addr:postcode":"32714",
    "addr:street":"N State Rd 434 Altamonte Spgs",
    "iso:country":"US",
    "sg:address":"380 N State Rd 434",
    "sg:city":"Altamonte Spgs",
    "sg:classifiers":[
        {
            "category":"Shopping",
            "subcategory":"Clothing, Apparel, & Fashions",
            "type":"Retail Goods"
        }
    ],
    "sg:phone":"+1 407 389 1481",
    "sg:postcode":"32714",
    "sg:province":"FL",
    "wof:name":"Dots Inc",
    "wof:placetype":"venue"
},
  "geometry": {"coordinates":[-81.41905800000001,28.673697],"type":"Point"}
}