{
  "type": "Feature",
  "properties": {
    "addr:full":"927 Heathercrest Lakeland FL 33813",
    "addr:housenumber":"927",
    "addr:postcode":"33813",
    "addr:street":"Heathercrest",
    "iso:country":"US",
    "sg:address":"927 Heathercrest",
    "sg:city":"Lakeland",
    "sg:classifiers":[
        {
            "category":"Building & Trades",
            "subcategory":"Construction",
            "type":"Services"
        }
    ],
    "sg:phone":"+1 863 644 7001",
    "sg:postcode":"33813",
    "sg:province":"FL",
    "sg:tags":[
        "house"
    ],
    "wof:name":"Certified Billing Contractor",
    "wof:placetype":"venue"
},
  "geometry": {"coordinates":[-81.946437,27.990714],"type":"Point"}
}