{
  "type": "Feature",
  "properties": {
    "addr:full":"6549 N Socrum Loop Rd Lakeland FL 33809",
    "addr:housenumber":"6549",
    "addr:postcode":"33809",
    "addr:street":"N Socrum Loop Rd",
    "iso:country":"US",
    "sg:address":"6549 N Socrum Loop Rd",
    "sg:city":"Lakeland",
    "sg:classifiers":[
        {
            "category":"Home & Garden",
            "subcategory":"Hardware",
            "type":"Retail Goods"
        }
    ],
    "sg:phone":"+1 863 859 9909",
    "sg:postcode":"33809",
    "sg:province":"FL",
    "wof:name":"Crowder Brothers of N Lakeland",
    "wof:placetype":"venue"
},
  "geometry": {"coordinates":[-81.94640699999999,28.126149],"type":"Point"}
}