{
  "type": "Feature",
  "properties": {
    "iso:country":"US",
    "sg:address":"4820 Executive Park Ct",
    "sg:city":"Jacksonville",
    "sg:classifiers":[
        {
            "category":"Manufacturing",
            "subcategory":"Rubber & Plastics",
            "type":"Manufacturing & Wholesale Goods"
        },
        {
            "category":"Shopping",
            "type":"Retail Goods"
        }
    ],
    "sg:phone":"+1 904 296 4711",
    "sg:postcode":"32216",
    "sg:province":"FL",
    "sg:tags":[
        "equipment",
        "clothing",
        "safety",
        "clothing-wholesale",
        "manufacturer"
    ],
    "wof:name":"Jbc Safety Plastic Inc",
    "wof:placetype":"venue"
},
  "geometry": {"coordinates":[-81.600678,30.252651],"type":"Point"}
}