{
  "type": "Feature",
  "properties": {
    "iso:country":"US",
    "sg:address":"4040 NE 2nd Ave Ste 313",
    "sg:city":"Miami",
    "sg:classifiers":[
        {
            "category":"Communications",
            "subcategory":"Newspaper",
            "type":"Services"
        }
    ],
    "sg:phone":"+1 305 571 7827",
    "sg:postcode":"33137",
    "sg:province":"FL",
    "sg:tags":[
        "magazine"
    ],
    "wof:name":"Home Miami Magazine Llc",
    "wof:placetype":"venue"
},
  "geometry": {"coordinates":[-80.191534,25.813785],"type":"Point"}
}