{
  "type": "Feature",
  "properties": {
    "iso:country":"US",
    "sg:address":"2248 Periwinkle Way",
    "sg:city":"Sanibel",
    "sg:classifiers":[
        {
            "category":"Personal",
            "subcategory":"Beauty Salon",
            "type":"Services"
        }
    ],
    "sg:phone":"+1 239 472 2468",
    "sg:postcode":"33957",
    "sg:province":"FL",
    "wof:name":"Hairs What's Hot",
    "wof:placetype":"venue"
},
  "geometry": {"coordinates":[-82.074691,26.437083],"type":"Point"}
}