{
  "type": "Feature",
  "properties": {
    "iso:country":"US",
    "sg:address":"2257 E Hillsborough Ave",
    "sg:city":"Tampa",
    "sg:classifiers":[
        {
            "category":"Wholesale",
            "subcategory":"Jewelry",
            "type":"Manufacturing & Wholesale Goods"
        }
    ],
    "sg:phone":"+1 813 231 5856",
    "sg:postcode":"33610",
    "sg:province":"FL",
    "sg:tags":[
        "jeweler"
    ],
    "wof:name":"N Y Wholesales",
    "wof:placetype":"venue"
},
  "geometry": {"coordinates":[-82.431845,27.99599],"type":"Point"}
}