{
  "type": "Feature",
  "properties": {
    "iso:country":"US",
    "sg:address":"2920 NW 44th Ave",
    "sg:city":"Lauderdale Lakes",
    "sg:classifiers":[
        {
            "category":"Building & Trades",
            "subcategory":"Landscaping Services",
            "type":"Services"
        }
    ],
    "sg:phone":"+1 954 730 0737",
    "sg:postcode":"33313",
    "sg:province":"FL",
    "sg:tags":[
        "tree"
    ],
    "wof:name":"Armstrong Arbor Tree Care Inc",
    "wof:placetype":"venue"
},
  "geometry": {"coordinates":[-80.2076,26.162965],"type":"Point"}
}