{
  "type": "Feature",
  "properties": {
    "iso:country":"US",
    "sg:address":"305 Alcazar Ave",
    "sg:city":"Coral Gables",
    "sg:classifiers":[
        {
            "category":"Real Estate",
            "subcategory":"Real Estate Services",
            "type":"Services"
        }
    ],
    "sg:phone":"+1 305 447 9091",
    "sg:postcode":"33134",
    "sg:province":"FL",
    "sg:tags":[
        "management",
        "property"
    ],
    "wof:name":"Vilar Property Management",
    "wof:placetype":"venue"
},
  "geometry": {"coordinates":[-80.260902,25.752899],"type":"Point"}
}