{
  "type": "Feature",
  "properties": {
    "addr:full":"16418 Hollow Tree Ln Loxahatchee FL 33470",
    "addr:housenumber":"16418",
    "addr:postcode":"33470",
    "addr:street":"Hollow Tree Ln",
    "iso:country":"US",
    "sg:address":"16418 Hollow Tree Ln",
    "sg:city":"Loxahatchee",
    "sg:classifiers":[
        {
            "category":"Building & Trades",
            "subcategory":"Construction",
            "type":"Services"
        }
    ],
    "sg:phone":"+1 561 798 3729",
    "sg:postcode":"33470",
    "sg:province":"FL",
    "sg:tags":[
        "house"
    ],
    "wof:name":"Lta Inc",
    "wof:placetype":"venue"
},
  "geometry": {"coordinates":[-80.307202,26.643843],"type":"Point"}
}