{
  "type": "Feature",
  "properties": {
    "addr:full":"5324 McIntosh Pt Sanford FL 32773",
    "addr:housenumber":"5324",
    "addr:postcode":"32773",
    "addr:street":"Mcintosh Pt",
    "iso:country":"US",
    "sg:address":"5324 McIntosh Pt",
    "sg:city":"Sanford",
    "sg:classifiers":[
        {
            "category":"Manufacturing",
            "subcategory":"Signs",
            "type":"Manufacturing & Wholesale Goods"
        }
    ],
    "sg:phone":"+1 407 330 0651",
    "sg:postcode":"32773",
    "sg:province":"FL",
    "sg:tags":[
        "specialty",
        "mfg"
    ],
    "sg:website":"www.innovativesigns.com",
    "wof:name":"Innovative Signs Inc",
    "wof:placetype":"venue"
},
  "geometry": {"coordinates":[-81.300039,28.73414],"type":"Point"}
}