{
  "type": "Feature",
  "properties": {
    "addr:full":"10590 London St Hollywood FL 33026",
    "addr:housenumber":"10590",
    "addr:postcode":"33026",
    "addr:street":"London St",
    "iso:country":"US",
    "sg:address":"10590 London St",
    "sg:city":"Hollywood",
    "sg:classifiers":[
        {
            "category":"Real Estate",
            "subcategory":"Real Estate Agent",
            "type":"Services"
        }
    ],
    "sg:phone":"+1 954 430 7252",
    "sg:postcode":"33026",
    "sg:province":"FL",
    "wof:name":"Mizrachi Realty LLC",
    "wof:placetype":"venue"
},
  "geometry": {"coordinates":[-80.289976,26.033538],"type":"Point"}
}