{
  "type": "Feature",
  "properties": {
    "iso:country":"US",
    "sg:address":"38530 Hart Dr",
    "sg:city":"Dade City",
    "sg:classifiers":[
        {
            "category":"Retail",
            "subcategory":"Repair Shop",
            "type":"Services"
        }
    ],
    "sg:phone":"+1 352 567 1107",
    "sg:postcode":"33523",
    "sg:province":"FL",
    "sg:tags":[
        "taxidermist"
    ],
    "wof:name":"Harts Taxidermy Studio",
    "wof:placetype":"venue"
},
  "geometry": {"coordinates":[-82.17491099999999,28.433321],"type":"Point"}
}