{
  "type": "Feature",
  "properties": {
    "addr:full":"401 Central Ave Saint Petersburg FL 33701",
    "addr:housenumber":"401",
    "addr:postcode":"33701",
    "addr:street":"Central Ave",
    "iso:country":"US",
    "sg:address":"401 Central Ave",
    "sg:city":"Saint Petersburg",
    "sg:classifiers":[
        {
            "category":"Banks & Credit Unions",
            "subcategory":"Bank",
            "type":"Services"
        }
    ],
    "sg:phone":"+1 727 821 3232",
    "sg:postcode":"33701",
    "sg:province":"FL",
    "sg:tags":[
        "national",
        "commercial"
    ],
    "wof:name":"Bank of America",
    "wof:placetype":"venue"
},
  "geometry": {"coordinates":[-82.640202,27.7712],"type":"Point"}
}