{
  "type": "Feature",
  "properties": {
    "iso:country":"US",
    "sg:address":"3000 SW 3rd Ave",
    "sg:city":"Miami",
    "sg:classifiers":[
        {
            "category":"Real Estate",
            "subcategory":"Real Estate Operator",
            "type":"Services"
        }
    ],
    "sg:phone":"+1 305 860 4440",
    "sg:postcode":"33129",
    "sg:province":"FL",
    "sg:tags":[
        "apartment"
    ],
    "wof:name":"Montserrat Apartments",
    "wof:placetype":"venue"
},
  "geometry": {"coordinates":[-80.21169999999999,25.753099],"type":"Point"}
}