{
  "type": "Feature",
  "properties": {
    "addr:full":"2865 45th St Vero Beach FL 32967",
    "addr:housenumber":"2865",
    "addr:postcode":"32967",
    "addr:street":"45Th St",
    "iso:country":"US",
    "sg:address":"2865 45th St",
    "sg:city":"Vero Beach",
    "sg:classifiers":[
        {
            "category":"Shopping",
            "subcategory":"Hobbies, Toys, & Games",
            "type":"Retail Goods"
        }
    ],
    "sg:phone":"+1 772 794 0252",
    "sg:postcode":"32967",
    "sg:province":"FL",
    "sg:tags":[
        "doll"
    ],
    "wof:name":"Elebe's Beauty Dolls",
    "wof:placetype":"venue"
},
  "geometry": {"coordinates":[-80.41466800000001,27.674918],"type":"Point"}
}