{
  "type": "Feature",
  "properties": {
    "iso:country":"US",
    "sg:address":"1109 N Main St",
    "sg:city":"Gainesville",
    "sg:classifiers":[
        {
            "category":"Professional",
            "type":"Services"
        }
    ],
    "sg:phone":"+1 352 375 1132",
    "sg:postcode":"32601",
    "sg:province":"FL",
    "wof:name":"Darnishias Goal Inc",
    "wof:placetype":"venue"
},
  "geometry": {"coordinates":[-82.324445,29.661924],"type":"Point"}
}