{
  "type": "Feature",
  "properties": {
    "addr:full":"8486 Navarre Pkwy Gulf Breeze FL 32566",
    "addr:housenumber":"8486",
    "addr:postcode":"32566",
    "addr:street":"Navarre Pkwy",
    "iso:country":"US",
    "sg:address":"8486 Navarre Pkwy",
    "sg:city":"Gulf Breeze",
    "sg:classifiers":[
        {
            "category":"Shopping",
            "subcategory":"Florist",
            "type":"Retail Goods"
        }
    ],
    "sg:phone":"+1 850 939 2288",
    "sg:postcode":"32566",
    "sg:province":"FL",
    "wof:name":"Navarre Beach Flower Boutique",
    "wof:placetype":"venue"
},
  "geometry": {"coordinates":[-86.869359,30.401553],"type":"Point"}
}