{
  "type": "Feature",
  "properties": {
    "iso:country":"US",
    "sg:address":"215 14th Ave",
    "sg:city":"Vero Beach",
    "sg:classifiers":[
        {
            "category":"Building & Trades",
            "subcategory":"Cleaning & Sanitation",
            "type":"Services"
        }
    ],
    "sg:phone":"+1 772 770 9378",
    "sg:postcode":"32962",
    "sg:province":"FL",
    "sg:tags":[
        "house"
    ],
    "wof:name":"Susan King Cleaning Svc",
    "wof:placetype":"venue"
},
  "geometry": {"coordinates":[-80.39975200000001,27.608296],"type":"Point"}
}