{
  "type": "Feature",
  "properties": {
    "addr:full":"600 S Us Highway 17 92 Longwood FL 32750",
    "addr:housenumber":"600;92",
    "addr:postcode":"32750",
    "addr:street":"S Us Highway 17",
    "iso:country":"US",
    "sg:address":"600 S Us Highway 17 92",
    "sg:city":"Longwood",
    "sg:classifiers":[
        {
            "category":"Deli",
            "type":"Food & Drink"
        },
        {
            "category":"Cafe",
            "type":"Food & Drink"
        }
    ],
    "sg:menulink":"http://www.allmenus.com/fl/casselberry-altamonte-springs/30458-homemade-cafe--pizzeria/menu/",
    "sg:phone":"+1 407 831 2223",
    "sg:postcode":"32750",
    "sg:province":"FL",
    "sg:tags":[
        "american"
    ],
    "wof:name":"Homemade Cafe & Pizzeria",
    "wof:placetype":"venue"
},
  "geometry": {"coordinates":[-81.32664800000001,28.706737],"type":"Point"}
}