{
  "type": "Feature",
  "properties": {
    "iso:country":"US",
    "sg:address":"333 E Cornelius Cir",
    "sg:city":"Sarasota",
    "sg:classifiers":[
        {
            "category":"Building & Trades",
            "subcategory":"Construction",
            "type":"Services"
        }
    ],
    "sg:phone":"+1 941 256 4070",
    "sg:postcode":"34232",
    "sg:province":"FL",
    "sg:tags":[
        "contractor"
    ],
    "wof:name":"Eduardo Gallegos Tile",
    "wof:placetype":"venue"
},
  "geometry": {"coordinates":[-82.494439,27.330697],"type":"Point"}
}