{
  "type": "Feature",
  "properties": {
    "iso:country":"US",
    "sg:address":"2067 S Federal Hwy",
    "sg:city":"Fort Lauderdale",
    "sg:classifiers":[
        {
            "category":"Marine",
            "type":"Transportation"
        }
    ],
    "sg:phone":"+1 954 653 0569",
    "sg:postcode":"33316",
    "sg:province":"FL",
    "sg:tags":[
        "water",
        "transport"
    ],
    "wof:name":"CU Charters",
    "wof:placetype":"venue"
},
  "geometry": {"coordinates":[-80.13665,26.096217],"type":"Point"}
}