{
  "type": "Feature",
  "properties": {
    "iso:country":"US",
    "sg:address":"8141 SE Skylark Ave",
    "sg:city":"Hobe Sound",
    "sg:classifiers":[
        {
            "category":"Banks & Credit Unions",
            "subcategory":"Financial Services",
            "type":"Services"
        }
    ],
    "sg:phone":"+1 772 692 4264",
    "sg:postcode":"33455",
    "sg:province":"FL",
    "sg:tags":[
        "investor"
    ],
    "wof:name":"Corian Investments Inc",
    "wof:placetype":"venue"
},
  "geometry": {"coordinates":[-80.155141,27.10594],"type":"Point"}
}