{
  "type": "Feature",
  "properties": {
    "addr:full":"1924 41st St SW Naples FL 34116",
    "addr:housenumber":"1924",
    "addr:postcode":"34116",
    "addr:street":"41St St Sw",
    "iso:country":"US",
    "sg:address":"1924 41st St SW",
    "sg:city":"Naples",
    "sg:classifiers":[
        {
            "category":"Building & Trades",
            "subcategory":"Construction",
            "type":"Services"
        }
    ],
    "sg:phone":"+1 239 643 6140",
    "sg:postcode":"34116",
    "sg:province":"FL",
    "sg:tags":[
        "coping",
        "plastering",
        "tiling",
        "pool",
        "swimming"
    ],
    "wof:name":"Plaster's Master Pool Svc",
    "wof:placetype":"venue"
},
  "geometry": {"coordinates":[-81.68942699999999,26.192618],"type":"Point"}
}