{
  "type": "Feature",
  "properties": {
    "addr:full":"1627 Silver Star Rd Orlando FL 32804",
    "addr:housenumber":"1627",
    "addr:postcode":"32804",
    "addr:street":"Silver Star Rd",
    "iso:country":"US",
    "sg:address":"1627 Silver Star Rd",
    "sg:city":"Orlando",
    "sg:classifiers":[
        {
            "category":"Retail",
            "subcategory":"Veterinary Services",
            "type":"Services"
        }
    ],
    "sg:phone":"+1 407 578 8383",
    "sg:postcode":"32804",
    "sg:province":"FL",
    "sg:tags":[
        "veterinarian"
    ],
    "wof:name":"Lake Olympia Veterinary Clinic",
    "wof:placetype":"venue"
},
  "geometry": {"coordinates":[-81.404651,28.578309],"type":"Point"}
}