{
  "type": "Feature",
  "properties": {
    "iso:country":"US",
    "sg:address":"1200 Old Stickney Point Rd",
    "sg:city":"Sarasota",
    "sg:classifiers":[
        {
            "category":"Bars & Pubs",
            "type":"Food & Drink"
        },
        {
            "category":"Restaurant",
            "type":"Food & Drink"
        }
    ],
    "sg:menulink":"http://www.allmenus.com/fl/sarasota/35058-captain-curts-crab--oyster-bar/menu/",
    "sg:phone":"+1 941 349 3885",
    "sg:postcode":"34242",
    "sg:province":"FL",
    "sg:tags":[
        "seafood",
        "american"
    ],
    "wof:name":"Captain Curt's Crab & Oyster Bar",
    "wof:placetype":"venue"
},
  "geometry": {"coordinates":[-82.534333,27.251836],"type":"Point"}
}