{
  "type": "Feature",
  "properties": {
    "iso:country":"US",
    "sg:address":"3750 Emergency Ln",
    "sg:city":"Sebring",
    "sg:classifiers":[
        {
            "category":"Health Services",
            "subcategory":"Health Practitioner",
            "type":"Services"
        }
    ],
    "sg:phone":"+1 863 471 6577",
    "sg:postcode":"33870",
    "sg:province":"FL",
    "sg:tags":[
        "therapist",
        "physical"
    ],
    "wof:name":"A Plus Occ & Ind Rehab",
    "wof:placetype":"venue"
},
  "geometry": {"coordinates":[-81.433015,27.463906],"type":"Point"}
}