{
  "type": "Feature",
  "properties": {
    "iso:country":"US",
    "sg:address":"4608 Lee Blvd",
    "sg:city":"Lehigh Acres",
    "sg:classifiers":[
        {
            "category":"Building & Trades",
            "subcategory":"Construction",
            "type":"Services"
        }
    ],
    "sg:phone":"+1 239 303 1214",
    "sg:postcode":"33971",
    "sg:province":"FL",
    "sg:tags":[
        "maintenance",
        "contractor"
    ],
    "wof:name":"Dennis Mead Maintenance",
    "wof:placetype":"venue"
},
  "geometry": {"coordinates":[-81.719942,26.616823],"type":"Point"}
}