{
  "type": "Feature",
  "properties": {
    "addr:full":"2 Leisure World Dr S Debary FL 32713",
    "addr:housenumber":"2",
    "addr:postcode":"32713",
    "addr:street":"Leisure World Dr S",
    "iso:country":"US",
    "sg:address":"2 Leisure World Dr S",
    "sg:city":"Debary",
    "sg:classifiers":[
        {
            "category":"Professional",
            "type":"Services"
        }
    ],
    "sg:phone":"+1 386 668 7149",
    "sg:postcode":"32713",
    "sg:province":"FL",
    "sg:tags":[
        "establishment"
    ],
    "wof:name":"Meadowlea Improvement Assoc",
    "wof:placetype":"venue"
},
  "geometry": {"coordinates":[-81.33161200000001,28.848975],"type":"Point"}
}