{
  "type": "Feature",
  "properties": {
    "addr:full":"5049 Ave D St Augustine FL 32095",
    "addr:housenumber":"5049",
    "addr:postcode":"32095",
    "addr:street":"Ave D St",
    "iso:country":"US",
    "sg:address":"5049 Ave D",
    "sg:city":"St Augustine",
    "sg:classifiers":[
        {
            "category":"Building & Trades",
            "subcategory":"Landscaping Services",
            "type":"Services"
        }
    ],
    "sg:phone":"+1 904 808 0648",
    "sg:postcode":"32095",
    "sg:province":"FL",
    "sg:tags":[
        "lawn",
        "maintenance",
        "grounds"
    ],
    "wof:name":"Jungle Lawn Care",
    "wof:placetype":"venue"
},
  "geometry": {"coordinates":[-81.345972,29.949768],"type":"Point"}
}