{
  "type": "Feature",
  "properties": {
    "iso:country":"US",
    "sg:address":"3201 S 25th St",
    "sg:city":"Fort Pierce",
    "sg:classifiers":[
        {
            "category":"Education",
            "subcategory":"School",
            "type":"Public Place"
        }
    ],
    "sg:phone":"+1 772 468 5885",
    "sg:postcode":"34981",
    "sg:province":"FL",
    "wof:name":"Forest Grove Middle School",
    "wof:placetype":"venue"
},
  "geometry": {"coordinates":[-80.34984,27.40805],"type":"Point"}
}