{
  "type": "Feature",
  "properties": {
    "addr:full":"6306 Benjamin Rd Tampa FL 33634",
    "addr:housenumber":"6306",
    "addr:postcode":"33634",
    "addr:street":"Benjamin Rd",
    "iso:country":"US",
    "sg:address":"6306 Benjamin Rd",
    "sg:city":"Tampa",
    "sg:classifiers":[
        {
            "category":"Professional",
            "subcategory":"Advertising",
            "type":"Services"
        }
    ],
    "sg:phone":"+1 813 249 6851",
    "sg:postcode":"33634",
    "sg:province":"FL",
    "sg:tags":[
        "mail",
        "commercial"
    ],
    "wof:name":"National Data & Mail Inc",
    "wof:placetype":"venue"
},
  "geometry": {"coordinates":[-82.54202100000001,28.006312],"type":"Point"}
}