{
  "type": "Feature",
  "properties": {
    "iso:country":"US",
    "sg:address":"1510 River Dr SW",
    "sg:city":"Ruskin",
    "sg:classifiers":[
        {
            "category":"Home & Garden",
            "subcategory":"Building Materials",
            "type":"Retail Goods"
        }
    ],
    "sg:phone":"+1 813 645 7485",
    "sg:postcode":"33570",
    "sg:province":"FL",
    "sg:tags":[
        "shutter"
    ],
    "wof:name":"Euro Shutters",
    "wof:placetype":"venue"
},
  "geometry": {"coordinates":[-82.45419099999999,27.712741],"type":"Point"}
}