{
  "type": "Feature",
  "properties": {
    "iso:country":"US",
    "sg:address":"17800 State Road 9",
    "sg:city":"Miami",
    "sg:classifiers":[
        {
            "category":"Bars & Pubs",
            "subcategory":"Nightclub",
            "type":"Food & Drink"
        }
    ],
    "sg:phone":"+1 305 999 9500",
    "sg:postcode":"33162",
    "sg:province":"FL",
    "sg:tags":[
        "nightlife"
    ],
    "wof:name":"Crazy Horse",
    "wof:placetype":"venue"
},
  "geometry": {"coordinates":[-80.196602,25.940701],"type":"Point"}
}