{
  "type": "Feature",
  "properties": {
    "iso:country":"US",
    "sg:address":"2860 SW 75th Ave",
    "sg:city":"Fort Lauderdale",
    "sg:classifiers":[
        {
            "category":"Real Estate",
            "subcategory":"Real Estate Agent",
            "type":"Services"
        }
    ],
    "sg:phone":"+1 954 916 6646",
    "sg:postcode":"33314",
    "sg:province":"FL",
    "wof:name":"Crystal Jaime",
    "wof:placetype":"venue"
},
  "geometry": {"coordinates":[-80.246717,26.090047],"type":"Point"}
}