{
  "type": "Feature",
  "properties": {
    "iso:country":"US",
    "sg:address":"11 Booth Blvd",
    "sg:city":"Safety Harbor",
    "sg:classifiers":[
        {
            "category":"Building & Trades",
            "subcategory":"Landscaping Services",
            "type":"Services"
        }
    ],
    "sg:phone":"+1 727 725 2428",
    "sg:postcode":"34695",
    "sg:province":"FL",
    "sg:tags":[
        "lawn",
        "maintenance",
        "grounds"
    ],
    "wof:name":"Day Sunny Lawn Care",
    "wof:placetype":"venue"
},
  "geometry": {"coordinates":[-82.708929,28.008896],"type":"Point"}
}