{
  "type": "Feature",
  "properties": {
    "iso:country":"US",
    "sg:address":"13850 Oneida Dr",
    "sg:city":"Delray Beach",
    "sg:classifiers":[
        {
            "category":"Freight",
            "type":"Transportation"
        }
    ],
    "sg:phone":"+1 561 445 4100",
    "sg:postcode":"33446",
    "sg:province":"FL",
    "wof:name":"A & B Car Service Inc",
    "wof:placetype":"venue"
},
  "geometry": {"coordinates":[-80.166269,26.471947],"type":"Point"}
}