{
  "type": "Feature",
  "properties": {
    "iso:country":"US",
    "sg:address":"3345 Fowler St",
    "sg:city":"Fort Myers",
    "sg:classifiers":[
        {
            "category":"Autos & Motor Vehicles",
            "subcategory":"Automobile Sales",
            "type":"Retail Goods"
        }
    ],
    "sg:phone":"+1 239 939 3030",
    "sg:postcode":"33901",
    "sg:province":"FL",
    "sg:tags":[
        "car",
        "dealer"
    ],
    "wof:name":"Palm City Corp",
    "wof:placetype":"venue"
},
  "geometry": {"coordinates":[-81.861869,26.61597],"type":"Point"}
}