{
  "type": "Feature",
  "properties": {
    "iso:country":"US",
    "sg:address":"14 Sovereign Way",
    "sg:city":"Fort Pierce",
    "sg:classifiers":[
        {
            "category":"Freight",
            "type":"Transportation"
        }
    ],
    "sg:phone":"+1 772 468 0737",
    "sg:postcode":"34949",
    "sg:province":"FL",
    "sg:tags":[
        "operator",
        "local",
        "trucking"
    ],
    "wof:name":"Scott Damato Trucking",
    "wof:placetype":"venue"
},
  "geometry": {"coordinates":[-80.31604799999999,27.514485],"type":"Point"}
}