{
  "type": "Feature",
  "properties": {
    "addr:full":"202 NE 10th Ave Cape Coral FL 33909",
    "addr:housenumber":"202",
    "addr:postcode":"33909",
    "addr:street":"Ne 10Th Ave",
    "iso:country":"US",
    "sg:address":"202 NE 10th Ave",
    "sg:city":"Cape Coral",
    "sg:classifiers":[
        {
            "category":"Shopping",
            "subcategory":"Used Merchandise",
            "type":"Retail Goods"
        }
    ],
    "sg:phone":"+1 239 772 1442",
    "sg:postcode":"33909",
    "sg:province":"FL",
    "sg:tags":[
        "antique"
    ],
    "wof:name":"Dunn In The Past Antiques",
    "wof:placetype":"venue"
},
  "geometry": {"coordinates":[-81.953856,26.654952],"type":"Point"}
}