{
  "type": "Feature",
  "properties": {
    "iso:country":"US",
    "sg:address":"1000 W 27th St",
    "sg:city":"Hialeah",
    "sg:classifiers":[
        {
            "category":"Retail",
            "subcategory":"Veterinary Services",
            "type":"Services"
        }
    ],
    "sg:phone":"+1 305 649 1234",
    "sg:postcode":"33010",
    "sg:province":"FL",
    "sg:tags":[
        "emergency",
        "hospital",
        "specialty",
        "clinic",
        "veterinarian"
    ],
    "sg:website":"http://www.knowlesanimalclinics.com",
    "wof:name":"Knowles Animal Clinics-",
    "wof:placetype":"venue"
},
  "geometry": {"coordinates":[-80.30223100000001,25.84618],"type":"Point"}
}