{
  "type": "Feature",
  "properties": {
    "iso:country":"US",
    "sg:address":"11936 Seminole Blvd",
    "sg:city":"Largo",
    "sg:classifiers":[
        {
            "category":"Recreation",
            "type":"Entertainment"
        }
    ],
    "sg:phone":"+1 727 644 0074",
    "sg:postcode":"33778",
    "sg:province":"FL",
    "sg:tags":[
        "martial",
        "arts",
        "instruction"
    ],
    "wof:name":"Fierce Tiger School Martial",
    "wof:placetype":"venue"
},
  "geometry": {"coordinates":[-82.78716300000001,27.883428],"type":"Point"}
}