{
  "type": "Feature",
  "properties": {
    "addr:full":"14941 N Dale Mabry Hwy Tampa FL 33618",
    "addr:housenumber":"14941",
    "addr:postcode":"33618",
    "addr:street":"N Dale Mabry Hwy",
    "iso:country":"US",
    "sg:address":"14941 N Dale Mabry Hwy",
    "sg:city":"Tampa",
    "sg:classifiers":[
        {
            "category":"Shopping",
            "subcategory":"Department Store",
            "type":"Retail Goods"
        }
    ],
    "sg:phone":"+1 813 968 3544",
    "sg:postcode":"33618",
    "sg:province":"FL",
    "sg:tags":[
        "discount"
    ],
    "wof:name":"Wal-Mart",
    "wof:placetype":"venue"
},
  "geometry": {"coordinates":[-82.50482599999999,28.08505],"type":"Point"}
}