{
  "type": "Feature",
  "properties": {
    "addr:full":"2918 Westcott Dr Palm Harbor FL 34684",
    "addr:housenumber":"2918",
    "addr:postcode":"34684",
    "addr:street":"Westcott Dr",
    "iso:country":"US",
    "sg:address":"2918 Westcott Dr",
    "sg:city":"Palm Harbor",
    "sg:classifiers":[
        {
            "category":"Professional",
            "type":"Services"
        }
    ],
    "sg:phone":"+1 727 787 4472",
    "sg:postcode":"34684",
    "sg:province":"FL",
    "sg:tags":[
        "establishment"
    ],
    "wof:name":"National Reporting Systems",
    "wof:placetype":"venue"
},
  "geometry": {"coordinates":[-82.724147,28.093698],"type":"Point"}
}