{
  "type": "Feature",
  "properties": {
    "addr:full":"3913 Whisper Grove Ct Valrico FL 33594",
    "addr:housenumber":"3913",
    "addr:postcode":"33594",
    "addr:street":"Whisper Grove Ct",
    "iso:country":"US",
    "sg:address":"3913 Whisper Grove Ct",
    "sg:city":"Valrico",
    "sg:classifiers":[
        {
            "category":"Professional",
            "type":"Services"
        }
    ],
    "sg:phone":"+1 813 655 4237",
    "sg:postcode":"33594",
    "sg:province":"FL",
    "wof:name":"John N Conrad Pa",
    "wof:placetype":"venue"
},
  "geometry": {"coordinates":[-82.232975,27.920787],"type":"Point"}
}