{
  "type": "Feature",
  "properties": {
    "iso:country":"US",
    "sg:address":"1735 Banana Rd",
    "sg:city":"Lakeland",
    "sg:classifiers":[
        {
            "category":"Building & Trades",
            "subcategory":"Construction",
            "type":"Services"
        }
    ],
    "sg:phone":"+1 863 859 6938",
    "sg:postcode":"33810",
    "sg:province":"FL",
    "sg:tags":[
        "hanging",
        "contractor"
    ],
    "wof:name":"Peacock Painting",
    "wof:placetype":"venue"
},
  "geometry": {"coordinates":[-81.986694,28.150168],"type":"Point"}
}