{
  "type": "Feature",
  "properties": {
    "addr:full":"1480 US Hwy 1 Titusville FL 32796",
    "addr:housenumber":"1480",
    "addr:postcode":"32796",
    "addr:street":"Us Hwy 1",
    "iso:country":"US",
    "sg:address":"1480 US Hwy 1",
    "sg:city":"Titusville",
    "sg:classifiers":[
        {
            "category":"Home & Garden",
            "subcategory":"Building Materials",
            "type":"Retail Goods"
        }
    ],
    "sg:phone":"+1 321 267 3831",
    "sg:postcode":"32796",
    "sg:province":"FL",
    "sg:tags":[
        "lumber",
        "supply"
    ],
    "wof:name":"Brevard Lumber Co Inc",
    "wof:placetype":"venue"
},
  "geometry": {"coordinates":[-80.829165,28.635652],"type":"Point"}
}