{
  "type": "Feature",
  "properties": {
    "addr:full":"10 Palm Harbor Village Way W Palm Coast FL 32137",
    "addr:housenumber":"10",
    "addr:postcode":"32137",
    "addr:street":"Palm;Village Way W",
    "iso:country":"US",
    "sg:address":"10 Palm Harbor Village Way W",
    "sg:city":"Palm Coast",
    "sg:classifiers":[
        {
            "category":"Restaurant",
            "type":"Food & Drink"
        }
    ],
    "sg:phone":"+1 386 447 1430",
    "sg:postcode":"32137",
    "sg:province":"FL",
    "sg:tags":[
        "eating"
    ],
    "wof:name":"Lucky Buffet Inc",
    "wof:placetype":"venue"
},
  "geometry": {"coordinates":[-81.21446899999999,29.558],"type":"Point"}
}