{
  "type": "Feature",
  "properties": {
    "iso:country":"US",
    "sg:address":"1059 Sanibel Ln",
    "sg:city":"Gulf Breeze",
    "sg:classifiers":[
        {
            "category":"Arts & Performance",
            "subcategory":"Theater",
            "type":"Entertainment"
        }
    ],
    "sg:phone":"+1 850 934 7647",
    "sg:postcode":"32563",
    "sg:province":"FL",
    "sg:tags":[
        "band",
        "orchestra"
    ],
    "wof:name":"Coconuts-Beach Party Band",
    "wof:placetype":"venue"
},
  "geometry": {"coordinates":[-87.111397,30.383001],"type":"Point"}
}