{
  "type": "Feature",
  "properties": {
    "iso:country":"US",
    "sg:address":"11495 Rocket Blvd",
    "sg:city":"Orlando",
    "sg:classifiers":[
        {
            "category":"Shopping",
            "type":"Retail Goods"
        }
    ],
    "sg:phone":"+1 407 854 7033",
    "sg:postcode":"32824",
    "sg:province":"FL",
    "sg:tags":[
        "frame",
        "custom"
    ],
    "wof:name":"Celebrations Art Framing",
    "wof:placetype":"venue"
},
  "geometry": {"coordinates":[-81.39067,28.405859],"type":"Point"}
}