{
  "type": "Feature",
  "properties": {
    "iso:country":"US",
    "sg:address":"1809 Brickell Ave",
    "sg:city":"Miami",
    "sg:classifiers":[
        {
            "category":"Building & Trades",
            "subcategory":"Locksmith",
            "type":"Services"
        }
    ],
    "sg:phone":"+1 305 415 8505",
    "sg:postcode":"33129",
    "sg:province":"FL",
    "sg:tags":[
        "key"
    ],
    "wof:name":"0 0 0 0 Emergency A Locksmith",
    "wof:placetype":"venue"
},
  "geometry": {"coordinates":[-80.19625499999999,25.755292],"type":"Point"}
}