{
  "type": "Feature",
  "properties": {
    "addr:full":"5561 S Orange Blossom Trl Orlando FL 32839",
    "addr:housenumber":"5561",
    "addr:postcode":"32839",
    "addr:street":"S Orange Blossom Trl",
    "iso:country":"US",
    "sg:address":"5561 S Orange Blossom Trl",
    "sg:city":"Orlando",
    "sg:classifiers":[
        {
            "category":"Professional",
            "type":"Services"
        }
    ],
    "sg:phone":"+1 407 859 7728",
    "sg:postcode":"32839",
    "sg:province":"FL",
    "sg:tags":[
        "equipment",
        "hydroponics",
        "supply"
    ],
    "wof:name":"Sunshine Hydroponics Garden",
    "wof:placetype":"venue"
},
  "geometry": {"coordinates":[-81.39663,28.478571],"type":"Point"}
}