{
  "type": "Feature",
  "properties": {
    "addr:full":"70 Biscayne Blvd Miami FL 33132",
    "addr:housenumber":"70",
    "addr:postcode":"33132",
    "addr:street":"Biscayne Blvd",
    "iso:country":"US",
    "sg:address":"70 Biscayne Blvd",
    "sg:city":"Miami",
    "sg:classifiers":[
        {
            "category":"Restaurant",
            "type":"Food & Drink"
        }
    ],
    "sg:phone":"+1 305 373 7803",
    "sg:postcode":"33132",
    "sg:province":"FL",
    "wof:name":"Nautica Grill",
    "wof:placetype":"venue"
},
  "geometry": {"coordinates":[-80.18736199999999,25.774583],"type":"Point"}
}