{
  "type": "Feature",
  "properties": {
    "iso:country":"US",
    "sg:address":"12606 N Nebraska Ave",
    "sg:city":"Tampa",
    "sg:classifiers":[
        {
            "category":"Autos & Motor Vehicles",
            "subcategory":"Auto Supplies",
            "type":"Retail Goods"
        }
    ],
    "sg:phone":"+1 813 866 3966",
    "sg:postcode":"33612",
    "sg:province":"FL",
    "sg:tags":[
        "automobile",
        "accessory"
    ],
    "wof:name":"Royalty Sounds",
    "wof:placetype":"venue"
},
  "geometry": {"coordinates":[-82.45122499999999,28.061896],"type":"Point"}
}