{
  "type": "Feature",
  "properties": {
    "iso:country":"US",
    "sg:address":"1541 Prosperity Farms Rd",
    "sg:city":"Lake Park",
    "sg:classifiers":[
        {
            "category":"Health Services",
            "subcategory":"Chiropractor",
            "type":"Services"
        }
    ],
    "sg:phone":"+1 561 863 8779",
    "sg:postcode":"33403",
    "sg:province":"FL",
    "wof:name":"A Alternative Approach Chiro",
    "wof:placetype":"venue"
},
  "geometry": {"coordinates":[-80.07432300000001,26.806137],"type":"Point"}
}