{
  "type": "Feature",
  "properties": {
    "iso:country":"US",
    "sg:address":"2434 Winterwood Cir E",
    "sg:city":"Jacksonville",
    "sg:classifiers":[
        {
            "category":"Building & Trades",
            "subcategory":"Landscaping Services",
            "type":"Services"
        }
    ],
    "sg:phone":"+1 904 783 9386",
    "sg:postcode":"32210",
    "sg:province":"FL",
    "wof:name":"Ralph T Holmes",
    "wof:placetype":"venue"
},
  "geometry": {"coordinates":[-81.777964,30.274564],"type":"Point"}
}