{
  "type": "Feature",
  "properties": {
    "addr:full":"5814 Frank Reeder Rd Pensacola FL 32526",
    "addr:housenumber":"5814",
    "addr:postcode":"32526",
    "addr:street":"Frank Reeder Rd",
    "iso:country":"US",
    "sg:address":"5814 Frank Reeder Rd",
    "sg:city":"Pensacola",
    "sg:classifiers":[
        {
            "category":"Building & Trades",
            "subcategory":"Construction",
            "type":"Services"
        }
    ],
    "sg:phone":"+1 850 484 8143",
    "sg:postcode":"32526",
    "sg:province":"FL",
    "sg:tags":[
        "contractor"
    ],
    "wof:name":"Allen P Keyes Tile Instl",
    "wof:placetype":"venue"
},
  "geometry": {"coordinates":[-87.380066,30.550286],"type":"Point"}
}