{
  "type": "Feature",
  "properties": {
    "iso:country":"US",
    "sg:address":"9906 Woodbay Dr",
    "sg:city":"Tampa",
    "sg:classifiers":[
        {
            "category":"Professional",
            "subcategory":"Engineering",
            "type":"Services"
        }
    ],
    "sg:phone":"+1 813 888 7690",
    "sg:postcode":"33626",
    "sg:province":"FL",
    "sg:tags":[
        "engineer"
    ],
    "wof:name":"Vector Technical Svc",
    "wof:placetype":"venue"
},
  "geometry": {"coordinates":[-82.630386,28.046653],"type":"Point"}
}