{
  "type": "Feature",
  "properties": {
    "iso:country":"US",
    "sg:address":"6861 SW 196th Ave",
    "sg:city":"Fort Lauderdale",
    "sg:classifiers":[
        {
            "category":"Retail",
            "subcategory":"Repair Shop",
            "type":"Services"
        }
    ],
    "sg:phone":"+1 954 434 8191",
    "sg:postcode":"33332",
    "sg:province":"FL",
    "sg:tags":[
        "ultrasonic",
        "cleaning",
        "sales"
    ],
    "wof:name":"Paragon Electronics",
    "wof:placetype":"venue"
},
  "geometry": {"coordinates":[-80.409429,26.031568],"type":"Point"}
}