{
  "type": "Feature",
  "properties": {
    "iso:country":"US",
    "sg:address":"1120 Holland Dr",
    "sg:city":"Boca Raton",
    "sg:classifiers":[
        {
            "category":"Health Services",
            "subcategory":"Chiropractor",
            "type":"Services"
        }
    ],
    "sg:phone":"+1 561 547 2210",
    "sg:postcode":"33487",
    "sg:province":"FL",
    "wof:name":"Health Chiropractic Assn",
    "wof:placetype":"venue"
},
  "geometry": {"coordinates":[-80.11268099999999,26.406735],"type":"Point"}
}