{
  "type": "Feature",
  "properties": {
    "addr:full":"10906 N Nebraska Ave Tampa FL 33612",
    "addr:housenumber":"10906",
    "addr:postcode":"33612",
    "addr:street":"N Nebraska Ave",
    "iso:country":"US",
    "sg:address":"10906 N Nebraska Ave",
    "sg:city":"Tampa",
    "sg:classifiers":[
        {
            "category":"Autos & Motor Vehicles",
            "subcategory":"Automobile Sales",
            "type":"Retail Goods"
        }
    ],
    "sg:phone":"+1 813 971 6855",
    "sg:postcode":"33612",
    "sg:province":"FL",
    "sg:tags":[
        "car",
        "dealer"
    ],
    "wof:name":"United Sales & Leasing Inc",
    "wof:placetype":"venue"
},
  "geometry": {"coordinates":[-82.45125400000001,28.049988],"type":"Point"}
}