{
  "type": "Feature",
  "properties": {
    "iso:country":"US",
    "sg:address":"1409 University Blvd N",
    "sg:city":"Jacksonville",
    "sg:classifiers":[
        {
            "category":"Organizations",
            "subcategory":"Religious Organization",
            "type":"Services"
        }
    ],
    "sg:phone":"+1 904 745 6000",
    "sg:postcode":"32211",
    "sg:province":"FL",
    "sg:tags":[
        "church"
    ],
    "wof:name":"Victory Chapel Christian",
    "wof:placetype":"venue"
},
  "geometry": {"coordinates":[-81.60279199999999,30.334742],"type":"Point"}
}