{
  "type": "Feature",
  "properties": {
    "addr:full":"4521 W Clifton St Tampa FL 33614",
    "addr:housenumber":"4521",
    "addr:postcode":"33614",
    "addr:street":"W Clifton St",
    "iso:country":"US",
    "sg:address":"4521 W Clifton St",
    "sg:city":"Tampa",
    "sg:classifiers":[
        {
            "category":"Building & Trades",
            "subcategory":"Plumbing",
            "type":"Services"
        }
    ],
    "sg:phone":"+1 813 884 8143",
    "sg:postcode":"33614",
    "sg:province":"FL",
    "sg:tags":[
        "plumber",
        "industrial",
        "contractors-commercial"
    ],
    "wof:name":"Griffin, Daniel A Plumbing",
    "wof:placetype":"venue"
},
  "geometry": {"coordinates":[-82.52046799999999,28.00096],"type":"Point"}
}