{
  "type": "Feature",
  "properties": {
    "iso:country":"US",
    "sg:address":"15761 New Hampshire Ct",
    "sg:city":"Fort Myers",
    "sg:classifiers":[
        {
            "category":"Health Services",
            "subcategory":"Doctor",
            "type":"Services"
        }
    ],
    "sg:phone":"+1 239 415 8377",
    "sg:postcode":"33908",
    "sg:province":"FL",
    "wof:name":"Lozano Alexander J MD",
    "wof:placetype":"venue"
},
  "geometry": {"coordinates":[-81.897589,26.513836],"type":"Point"}
}