{
  "type": "Feature",
  "properties": {
    "iso:country":"US",
    "sg:address":"4391 Colonial Blvd",
    "sg:city":"Fort Myers",
    "sg:classifiers":[
        {
            "category":"Manufacturing",
            "subcategory":"Tools & Machinery",
            "type":"Manufacturing & Wholesale Goods"
        }
    ],
    "sg:phone":"+1 239 936 6667",
    "sg:postcode":"33912",
    "sg:province":"FL",
    "sg:tags":[
        "equipment",
        "construction",
        "safety",
        "mfg"
    ],
    "wof:name":"Protection Services Inc",
    "wof:placetype":"venue"
},
  "geometry": {"coordinates":[-81.82713699999999,26.604442],"type":"Point"}
}