{
  "type": "Feature",
  "properties": {
    "iso:country":"US",
    "sg:address":"4532 S Manhattan Ave",
    "sg:city":"Tampa",
    "sg:classifiers":[
        {
            "category":"Personal",
            "subcategory":"Beauty Salon",
            "type":"Services"
        }
    ],
    "sg:phone":"+1 813 835 6300",
    "sg:postcode":"33611",
    "sg:province":"FL",
    "sg:tags":[
        "shop"
    ],
    "wof:name":"Matrix Nail Salon",
    "wof:placetype":"venue"
},
  "geometry": {"coordinates":[-82.518367,27.899717],"type":"Point"}
}