{
  "type": "Feature",
  "properties": {
    "addr:full":"2651 NW 19th Ave Fort Lauderdale FL 33311",
    "addr:housenumber":"2651",
    "addr:postcode":"33311",
    "addr:street":"Nw 19Th Ave",
    "iso:country":"US",
    "sg:address":"2651 NW 19th Ave",
    "sg:city":"Fort Lauderdale",
    "sg:classifiers":[
        {
            "category":"Manufacturing",
            "subcategory":"Retail Goods",
            "type":"Manufacturing & Wholesale Goods"
        }
    ],
    "sg:phone":"+1 954 733 0406",
    "sg:postcode":"33311",
    "sg:province":"FL",
    "sg:tags":[
        "product",
        "mfg"
    ],
    "wof:name":"Bee Keepers",
    "wof:placetype":"venue"
},
  "geometry": {"coordinates":[-80.168753,26.159368],"type":"Point"}
}