{
  "type": "Feature",
  "properties": {
    "addr:full":"7001 W Broward Blvd Plantation FL 33317",
    "addr:housenumber":"7001",
    "addr:postcode":"33317",
    "addr:street":"W Broward Blvd",
    "iso:country":"US",
    "sg:address":"7001 W Broward Blvd",
    "sg:city":"Plantation",
    "sg:classifiers":[
        {
            "category":"Banks & Credit Unions",
            "subcategory":"Bank",
            "type":"Services"
        },
        {
            "category":"Banks & Credit Unions",
            "subcategory":"Financial Services",
            "type":"Services"
        }
    ],
    "sg:phone":"+1 954 797 3950",
    "sg:postcode":"33317",
    "sg:province":"FL",
    "sg:tags":[
        "commercial",
        "loan",
        "internet",
        "saving",
        "banking"
    ],
    "sg:website":"https://www.bankofamerica.com/",
    "wof:name":"Bank of America",
    "wof:placetype":"venue"
},
  "geometry": {"coordinates":[-80.24137899999999,26.120939],"type":"Point"}
}