{
  "type": "Feature",
  "properties": {
    "addr:full":"261 Shalimar Dr Shalimar FL 32579",
    "addr:housenumber":"261",
    "addr:postcode":"32579",
    "addr:street":"Shalimar Dr",
    "iso:country":"US",
    "sg:address":"261 Shalimar Dr",
    "sg:city":"Shalimar",
    "sg:classifiers":[
        {
            "category":"Wholesale",
            "subcategory":"Machinery & Supplies",
            "type":"Manufacturing & Wholesale Goods"
        }
    ],
    "sg:phone":"+1 850 651 6332",
    "sg:postcode":"32579",
    "sg:province":"FL",
    "sg:tags":[
        "equipment",
        "industrial"
    ],
    "wof:name":"Sunbelt Engineering & Tooling",
    "wof:placetype":"venue"
},
  "geometry": {"coordinates":[-86.58396,30.445716],"type":"Point"}
}