{
  "type": "Feature",
  "properties": {
    "iso:country":"US",
    "sg:address":"1423 Sandpiper Ln",
    "sg:city":"Lantana",
    "sg:classifiers":[
        {
            "category":"Building & Trades",
            "subcategory":"Plumbing",
            "type":"Services"
        }
    ],
    "sg:phone":"+1 561 767 6020",
    "sg:postcode":"33462",
    "sg:province":"FL",
    "sg:tags":[
        "conditioning",
        "air",
        "system",
        "contractor"
    ],
    "wof:name":"Air Repair & Replacement Inc",
    "wof:placetype":"venue"
},
  "geometry": {"coordinates":[-80.05850599999999,26.573321],"type":"Point"}
}