{
  "type": "Feature",
  "properties": {
    "iso:country":"US",
    "sg:address":"2976 State Hwy 15",
    "sg:city":"Belle Glade",
    "sg:classifiers":[
        {
            "category":"Government",
            "subcategory":"Office",
            "type":"Public Place"
        }
    ],
    "sg:phone":"+1 561 996 4815",
    "sg:postcode":"33430",
    "sg:province":"FL",
    "wof:name":"Board Of County Commissioners",
    "wof:placetype":"venue"
},
  "geometry": {"coordinates":[-80.65985499999999,26.747188],"type":"Point"}
}