{
  "type": "Feature",
  "properties": {
    "addr:full":"7291 NW 74th St Medley FL 33166",
    "addr:housenumber":"7291",
    "addr:postcode":"33166",
    "addr:street":"Nw 74Th St",
    "iso:country":"US",
    "sg:address":"7291 NW 74th St",
    "sg:city":"Medley",
    "sg:classifiers":[
        {
            "category":"Communications",
            "subcategory":"Radio Station",
            "type":"Services"
        }
    ],
    "sg:phone":"+1 786 337 6784",
    "sg:postcode":"33166",
    "sg:province":"FL",
    "sg:tags":[
        "company",
        "broadcasting"
    ],
    "wof:name":"Sherjan Broadcasting Inc",
    "wof:placetype":"venue"
},
  "geometry": {"coordinates":[-80.314584,25.840793],"type":"Point"}
}