{
  "type": "Feature",
  "properties": {
    "addr:full":"7401 Coral Way Miami FL 33155",
    "addr:housenumber":"7401",
    "addr:postcode":"33155",
    "addr:street":"Coral Way",
    "iso:country":"US",
    "sg:address":"7401 Coral Way",
    "sg:city":"Miami",
    "sg:classifiers":[
        {
            "category":"Building & Trades",
            "subcategory":"Locksmith",
            "type":"Services"
        }
    ],
    "sg:phone":"+1 305 357 4942",
    "sg:postcode":"33155",
    "sg:province":"FL",
    "sg:tags":[
        "key"
    ],
    "wof:name":"1 24 Hour 7 Day Emerg Locksmith",
    "wof:placetype":"venue"
},
  "geometry": {"coordinates":[-80.31561000000001,25.748307],"type":"Point"}
}