{
  "type": "Feature",
  "properties": {
    "iso:country":"US",
    "sg:address":"1697 Kings Rd",
    "sg:city":"Jacksonville",
    "sg:classifiers":[
        {
            "category":"Health Services",
            "subcategory":"Doctor",
            "type":"Services"
        }
    ],
    "sg:phone":"+1 904 353 4079",
    "sg:postcode":"32209",
    "sg:province":"FL",
    "sg:tags":[
        "medical"
    ],
    "wof:name":"Commonwealth Family Pract",
    "wof:placetype":"venue"
},
  "geometry": {"coordinates":[-81.68324699999999,30.343867],"type":"Point"}
}