{
  "type": "Feature",
  "properties": {
    "iso:country":"US",
    "sg:address":"700 N Greenwood Ave",
    "sg:city":"Clearwater",
    "sg:classifiers":[
        {
            "category":"Food & Beverages",
            "subcategory":"Meat & Fish",
            "type":"Retail Goods"
        }
    ],
    "sg:phone":"+1 727 442 0962",
    "sg:postcode":"33755",
    "sg:province":"FL",
    "wof:name":"C & C Food Mart",
    "wof:placetype":"venue"
},
  "geometry": {"coordinates":[-82.79179499999999,27.973557],"type":"Point"}
}