{
  "type": "Feature",
  "properties": {
    "addr:full":"610 E 4th Ave Hialeah FL 33010",
    "addr:housenumber":"610",
    "addr:postcode":"33010",
    "addr:street":"E 4Th Ave",
    "iso:country":"US",
    "sg:address":"610 E 4th Ave",
    "sg:city":"Hialeah",
    "sg:classifiers":[
        {
            "category":"Health Services",
            "subcategory":"Doctor",
            "type":"Services"
        }
    ],
    "sg:phone":"+1 305 883 6161",
    "sg:postcode":"33010",
    "sg:province":"FL",
    "sg:tags":[
        "medical",
        "center"
    ],
    "wof:name":"Colonial Health Center Inc",
    "wof:placetype":"venue"
},
  "geometry": {"coordinates":[-80.27355799999999,25.827325],"type":"Point"}
}