{
  "type": "Feature",
  "properties": {
    "iso:country":"US",
    "sg:address":"422 South Central Avenue",
    "sg:city":"Apopka",
    "sg:classifiers":[
        {
            "category":"Professional",
            "subcategory":"Lawyer & Legal Services",
            "type":"Services"
        },
        {
            "category":"Building & Trades",
            "subcategory":"Construction",
            "type":"Services"
        }
    ],
    "sg:phone":"+1 407 406 9103",
    "sg:postcode":"32704",
    "sg:province":"FL",
    "sg:tags":[
        "repair",
        "installation",
        "assistance",
        "paralegal",
        "ceilings-supplies",
        "preservation",
        "restoration",
        "plan",
        "document"
    ],
    "sg:website":"http://allbrightcompanies.com",
    "wof:name":"All Bright Companies, INC.",
    "wof:placetype":"venue"
},
  "geometry": {"coordinates":[-81.51151400000001,28.672867],"type":"Point"}
}