{
  "type": "Feature",
  "properties": {
    "iso:country":"US",
    "sg:address":"7960 Pine Forest Rd",
    "sg:city":"Pensacola",
    "sg:classifiers":[
        {
            "category":"Restaurant",
            "type":"Food & Drink"
        }
    ],
    "sg:menulink":"http://www.allmenus.com/fl/pensacola/160439-burger-king/menu/",
    "sg:phone":"+1 850 944 2438",
    "sg:postcode":"32526",
    "sg:province":"FL",
    "sg:tags":[
        "burger",
        "american"
    ],
    "wof:name":"Burger King",
    "wof:placetype":"venue"
},
  "geometry": {"coordinates":[-87.31286799999999,30.518203],"type":"Point"}
}