{
  "type": "Feature",
  "properties": {
    "addr:full":"8620 Baymeadows Rd Jacksonville FL 32256",
    "addr:postcode":"8620;32256",
    "addr:street":"Baymeadows Rd",
    "iso:country":"US",
    "sg:address":"8620 Baymeadows Rd",
    "sg:city":"Jacksonville",
    "sg:classifiers":[
        {
            "category":"Utilities",
            "subcategory":"Cable",
            "type":"Services"
        }
    ],
    "sg:phone":"+1 904 737 2000",
    "sg:postcode":"32256",
    "sg:province":"FL",
    "sg:tags":[
        "satellite",
        "carrier"
    ],
    "wof:name":"All Star Satellite",
    "wof:placetype":"venue"
},
  "geometry": {"coordinates":[-81.580602,30.220713],"type":"Point"}
}