{
  "type": "Feature",
  "properties": {
    "iso:country":"US",
    "sg:address":"2345 Captain Dr",
    "sg:city":"Deltona",
    "sg:classifiers":[
        {
            "category":"Building & Trades",
            "subcategory":"Pest Control",
            "type":"Services"
        }
    ],
    "sg:phone":"+1 386 775 2847",
    "sg:postcode":"32738",
    "sg:province":"FL",
    "wof:name":"Buggers Pest Control Llc",
    "wof:placetype":"venue"
},
  "geometry": {"coordinates":[-81.20382600000001,28.953981],"type":"Point"}
}