{
  "type": "Feature",
  "properties": {
    "addr:full":"28090 Quails Nest Ln Bonita Springs FL 34135",
    "addr:postcode":"28090;34135",
    "addr:street":"Quails Nest Ln",
    "iso:country":"US",
    "sg:address":"28090 Quails Nest Ln",
    "sg:city":"Bonita Springs",
    "sg:classifiers":[
        {
            "category":"Travel",
            "subcategory":"Hotels & Motels",
            "type":"Entertainment"
        }
    ],
    "sg:phone":"+1 239 947 3366",
    "sg:postcode":"34135",
    "sg:province":"FL",
    "wof:name":"Days Inn",
    "wof:placetype":"venue"
},
  "geometry": {"coordinates":[-81.751632,26.330394],"type":"Point"}
}