{
  "type": "Feature",
  "properties": {
    "iso:country":"US",
    "sg:address":"22332 Vick St",
    "sg:city":"Port Charlotte",
    "sg:classifiers":[
        {
            "category":"Social Services",
            "subcategory":"Adult Care",
            "type":"Services"
        }
    ],
    "sg:phone":"+1 941 627 5388",
    "sg:postcode":"33980",
    "sg:province":"FL",
    "sg:tags":[
        "home",
        "residential"
    ],
    "wof:name":"Regents Club Retirement",
    "wof:placetype":"venue"
},
  "geometry": {"coordinates":[-82.080298,26.965337],"type":"Point"}
}