{
  "type": "Feature",
  "properties": {
    "addr:full":"8333 N Davis Hwy Pensacola FL 32514",
    "addr:housenumber":"8333",
    "addr:postcode":"32514",
    "addr:street":"N Davis Hwy",
    "iso:country":"US",
    "sg:address":"8333 N Davis Hwy",
    "sg:city":"Pensacola",
    "sg:classifiers":[
        {
            "category":"Personal",
            "subcategory":"Beauty Salon",
            "type":"Services"
        }
    ],
    "sg:phone":"+1 850 969 2710",
    "sg:postcode":"32514",
    "sg:province":"FL",
    "sg:tags":[
        "treatment",
        "skin"
    ],
    "wof:name":"Skin Care Ctr",
    "wof:placetype":"venue"
},
  "geometry": {"coordinates":[-87.216785,30.515496],"type":"Point"}
}