{
  "type": "Feature",
  "properties": {
    "iso:country":"US",
    "sg:address":"1971 W Lumsden Rd",
    "sg:city":"Brandon",
    "sg:classifiers":[
        {
            "category":"Manufacturing",
            "subcategory":"Tools & Machinery",
            "type":"Manufacturing & Wholesale Goods"
        }
    ],
    "sg:phone":"+1 813 654 6778",
    "sg:postcode":"33511",
    "sg:province":"FL",
    "sg:tags":[
        "photographic",
        "mfg"
    ],
    "wof:name":"Eugene W Rush",
    "wof:placetype":"venue"
},
  "geometry": {"coordinates":[-82.31572300000001,27.923237],"type":"Point"}
}