{
  "type": "Feature",
  "properties": {
    "iso:country":"US",
    "sg:address":"651 W Plymouth Ave",
    "sg:city":"Deland",
    "sg:classifiers":[
        {
            "category":"Health Services",
            "subcategory":"Clinic",
            "type":"Services"
        }
    ],
    "sg:phone":"+1 386 738 6811",
    "sg:postcode":"32720",
    "sg:province":"FL",
    "sg:tags":[
        "surgical",
        "center"
    ],
    "wof:name":"De Land Surgery Ctr",
    "wof:placetype":"venue"
},
  "geometry": {"coordinates":[-81.31523799999999,29.042702],"type":"Point"}
}