{
  "type": "Feature",
  "properties": {
    "addr:full":"3625 NW 82nd Ave Ste 303 Doral FL 33166",
    "addr:housenumber":"3625",
    "addr:postcode":"33166",
    "addr:street":"Nw 82Nd Ave Ste 303",
    "iso:country":"US",
    "sg:address":"3625 NW 82nd Ave Ste 303",
    "sg:city":"Doral",
    "sg:classifiers":[
        {
            "category":"Banks & Credit Unions",
            "subcategory":"Financial Services",
            "type":"Services"
        }
    ],
    "sg:phone":"+1 305 639 9858",
    "sg:postcode":"33166",
    "sg:province":"FL",
    "sg:tags":[
        "broker",
        "mortgage"
    ],
    "wof:name":"Genisis Mortgage Group Inc",
    "wof:placetype":"venue"
},
  "geometry": {"coordinates":[-80.3293,25.807301],"type":"Point"}
}