{
  "type": "Feature",
  "properties": {
    "addr:full":"200 S Tampa St Tampa FL 33602",
    "addr:housenumber":"200",
    "addr:postcode":"33602",
    "addr:street":"S Tampa St",
    "iso:country":"US",
    "sg:address":"200 S Tampa St",
    "sg:city":"Tampa",
    "sg:classifiers":[
        {
            "category":"Shopping",
            "subcategory":"Florist",
            "type":"Retail Goods"
        }
    ],
    "sg:phone":"+1 813 223 1946",
    "sg:postcode":"33602",
    "sg:province":"FL",
    "wof:name":"Jennies Flowers",
    "wof:placetype":"venue"
},
  "geometry": {"coordinates":[-82.45696100000001,27.943331],"type":"Point"}
}