{
  "type": "Feature",
  "properties": {
    "addr:full":"8340 SW 3rd Ct Pembroke Pines FL 33025",
    "addr:housenumber":"8340",
    "addr:postcode":"33025",
    "addr:street":"Sw 3Rd Ct",
    "iso:country":"US",
    "sg:address":"8340 SW 3rd Ct",
    "sg:city":"Pembroke Pines",
    "sg:classifiers":[
        {
            "category":"Building & Trades",
            "subcategory":"Construction",
            "type":"Services"
        }
    ],
    "sg:phone":"+1 954 442 5251",
    "sg:postcode":"33025",
    "sg:province":"FL",
    "sg:tags":[
        "general",
        "contractor"
    ],
    "wof:name":"Rawlins Construction Corp",
    "wof:placetype":"venue"
},
  "geometry": {"coordinates":[-80.253581,26.006865],"type":"Point"}
}