{
  "type": "Feature",
  "properties": {
    "iso:country":"US",
    "sg:address":"2759 NW 31st St",
    "sg:city":"Miami",
    "sg:classifiers":[
        {
            "category":"Shopping",
            "subcategory":"Computers & Home Electronics",
            "type":"Retail Goods"
        }
    ],
    "sg:phone":"+1 305 635 0071",
    "sg:postcode":"33142",
    "sg:province":"FL",
    "sg:tags":[
        "television",
        "radio"
    ],
    "wof:name":"Flagler TV",
    "wof:placetype":"venue"
},
  "geometry": {"coordinates":[-80.24159,25.804487],"type":"Point"}
}