{
  "type": "Feature",
  "properties": {
    "iso:country":"US",
    "sg:address":"140 Lake Ave",
    "sg:city":"Maitland",
    "sg:classifiers":[
        {
            "category":"Shopping",
            "subcategory":"Pets & Pet Supplies",
            "type":"Retail Goods"
        },
        {
            "category":"Retail",
            "subcategory":"Pet Boarding",
            "type":"Services"
        }
    ],
    "sg:phone":"+1 407 539 1373",
    "sg:postcode":"32751",
    "sg:province":"FL",
    "sg:tags":[
        "boarding/pet",
        "groomers",
        "sitting"
    ],
    "sg:website":"www.thevillagegroomerfl.com",
    "wof:name":"The Village Groomer of Maitland",
    "wof:placetype":"venue"
},
  "geometry": {"coordinates":[-81.365971,28.618539],"type":"Point"}
}