{
  "type": "Feature",
  "properties": {
    "addr:full":"1900 E 4th Ave Hialeah FL 33010",
    "addr:housenumber":"1900",
    "addr:postcode":"33010",
    "addr:street":"E 4Th Ave",
    "iso:country":"US",
    "sg:address":"1900 E 4th Ave",
    "sg:city":"Hialeah",
    "sg:classifiers":[
        {
            "category":"Personal",
            "subcategory":"Beauty Salon",
            "type":"Services"
        }
    ],
    "sg:phone":"+1 305 885 4764",
    "sg:postcode":"33010",
    "sg:province":"FL",
    "wof:name":"Rene Beauty Salon",
    "wof:placetype":"venue"
},
  "geometry": {"coordinates":[-80.273985,25.840142],"type":"Point"}
}