{
  "type": "Feature",
  "properties": {
    "iso:country":"US",
    "sg:address":"4450 Lola Dr",
    "sg:city":"Jacksonville",
    "sg:classifiers":[
        {
            "category":"Wholesale",
            "subcategory":"Construction Materials",
            "type":"Manufacturing & Wholesale Goods"
        }
    ],
    "sg:phone":"+1 904 771 2032",
    "sg:postcode":"32210",
    "sg:province":"FL",
    "sg:tags":[
        "sand",
        "gravel"
    ],
    "wof:name":"D & D Dirtin",
    "wof:placetype":"venue"
},
  "geometry": {"coordinates":[-81.789676,30.258288],"type":"Point"}
}