{
  "type": "Feature",
  "properties": {
    "iso:country":"US",
    "sg:address":"606 N 6th Ave",
    "sg:city":"Wauchula",
    "sg:classifiers":[
        {
            "category":"Manufacturing",
            "subcategory":"Printing",
            "type":"Manufacturing & Wholesale Goods"
        }
    ],
    "sg:phone":"+1 863 773 0200",
    "sg:postcode":"33873",
    "sg:province":"FL",
    "sg:tags":[
        "lithographic",
        "commercial"
    ],
    "wof:name":"Printers Choice",
    "wof:placetype":"venue"
},
  "geometry": {"coordinates":[-81.81304299999999,27.557629],"type":"Point"}
}