{
  "type": "Feature",
  "properties": {
    "iso:country":"US",
    "sg:address":"155 N Seminole Ave",
    "sg:city":"Lake Alfred",
    "sg:classifiers":[
        {
            "category":"Organizations",
            "subcategory":"Membership Organization",
            "type":"Services"
        }
    ],
    "sg:phone":"+1 863 956 5176",
    "sg:postcode":"33850",
    "sg:province":"FL",
    "wof:name":"Lake Alfred Lodge 192",
    "wof:placetype":"venue"
},
  "geometry": {"coordinates":[-81.72810200000001,28.092448],"type":"Point"}
}