{
  "type": "Feature",
  "properties": {
    "addr:full":"6733 4th St N St Petersburg FL 33702",
    "addr:housenumber":"6733",
    "addr:postcode":"33702",
    "addr:street":"4Th St N",
    "iso:country":"US",
    "sg:address":"6733 4th St N",
    "sg:city":"St Petersburg",
    "sg:classifiers":[
        {
            "category":"Travel",
            "subcategory":"Hotels & Motels",
            "type":"Entertainment"
        }
    ],
    "sg:phone":"+1 727 528 8820",
    "sg:postcode":"33702",
    "sg:province":"FL",
    "wof:name":"El Patio Motel",
    "wof:placetype":"venue"
},
  "geometry": {"coordinates":[-82.638611,27.834205],"type":"Point"}
}