{
  "type": "Feature",
  "properties": {
    "addr:full":"2535 Cat Cay Ln Fort Lauderdale FL 33312",
    "addr:postcode":"2535;33312",
    "addr:street":"Cat Cay Ln",
    "iso:country":"US",
    "sg:address":"2535 Cat Cay Ln",
    "sg:city":"Fort Lauderdale",
    "sg:classifiers":[
        {
            "category":"Building & Trades",
            "subcategory":"Construction",
            "type":"Services"
        }
    ],
    "sg:phone":"+1 954 791 7878",
    "sg:postcode":"33312",
    "sg:province":"FL",
    "sg:tags":[
        "general",
        "contractor"
    ],
    "wof:name":"Chatlos Construction Inc",
    "wof:placetype":"venue"
},
  "geometry": {"coordinates":[-80.189548,26.08968],"type":"Point"}
}