{
  "type": "Feature",
  "properties": {
    "addr:full":"389 Oakridge Rd Ormond Beach FL 32174",
    "addr:housenumber":"389",
    "addr:postcode":"32174",
    "addr:street":"Oakridge Rd",
    "iso:country":"US",
    "sg:address":"389 Oakridge Rd",
    "sg:city":"Ormond Beach",
    "sg:classifiers":[
        {
            "category":"Retail",
            "subcategory":"Auto Repair",
            "type":"Services"
        }
    ],
    "sg:phone":"+1 386 672 6687",
    "sg:postcode":"32174",
    "sg:province":"FL",
    "sg:tags":[
        "repairing",
        "automobile"
    ],
    "wof:name":"Aqua-Tech Irrigation",
    "wof:placetype":"venue"
},
  "geometry": {"coordinates":[-81.21663100000001,29.267446],"type":"Point"}
}