{
  "type": "Feature",
  "properties": {
    "iso:country":"US",
    "sg:address":"10219 Melanie Ave",
    "sg:city":"Jacksonville",
    "sg:classifiers":[
        {
            "category":"Building & Trades",
            "subcategory":"Construction",
            "type":"Services"
        }
    ],
    "sg:phone":"+1 904 768 6199",
    "sg:postcode":"32218",
    "sg:province":"FL",
    "sg:tags":[
        "contractor"
    ],
    "wof:name":"R&B Tile Marble & Granite",
    "wof:placetype":"venue"
},
  "geometry": {"coordinates":[-81.698038,30.420696],"type":"Point"}
}