{
  "type": "Feature",
  "properties": {
    "addr:full":"220 Coral Sand Dr Rockledge FL 32955",
    "addr:housenumber":"220",
    "addr:postcode":"32955",
    "addr:street":"Coral Sand Dr",
    "iso:country":"US",
    "sg:address":"220 Coral Sand Dr",
    "sg:city":"Rockledge",
    "sg:classifiers":[
        {
            "category":"Social Services",
            "type":"Services"
        }
    ],
    "sg:phone":"+1 321 632 5792",
    "sg:postcode":"32955",
    "sg:province":"FL",
    "sg:tags":[
        "counseling",
        "counselor",
        "marriage",
        "family"
    ],
    "sg:website":"www.fccbrevard.com",
    "wof:name":"Family Counseling Center",
    "wof:placetype":"venue"
},
  "geometry": {"coordinates":[-80.727172,28.340428],"type":"Point"}
}