{
  "type": "Feature",
  "properties": {
    "addr:full":"1074 NW 22nd St Miami FL 33127",
    "addr:housenumber":"1074",
    "addr:postcode":"33127",
    "addr:street":"Nw 22Nd St",
    "iso:country":"US",
    "sg:address":"1074 NW 22nd St",
    "sg:city":"Miami",
    "sg:classifiers":[
        {
            "category":"Building & Trades",
            "subcategory":"Equipment Rental",
            "type":"Services"
        },
        {
            "category":"Building & Trades",
            "subcategory":"Construction",
            "type":"Services"
        }
    ],
    "sg:phone":"+1 305 548 3384",
    "sg:postcode":"33127",
    "sg:province":"FL",
    "sg:tags":[
        "lift",
        "aerial",
        "scaffolding",
        "contractors'"
    ],
    "wof:name":"F & R Scaffolds Inc",
    "wof:placetype":"venue"
},
  "geometry": {"coordinates":[-80.21270800000001,25.797825],"type":"Point"}
}