{
  "type": "Feature",
  "properties": {
    "addr:full":"1814 W Shores Rd Melbourne FL 32935",
    "addr:housenumber":"1814",
    "addr:postcode":"32935",
    "addr:street":"W Shores Rd",
    "iso:country":"US",
    "sg:address":"1814 W Shores Rd",
    "sg:city":"Melbourne",
    "sg:classifiers":[
        {
            "category":"Shopping",
            "subcategory":"Clothing, Apparel, & Fashions",
            "type":"Retail Goods"
        }
    ],
    "sg:phone":"+1 321 242 5820",
    "sg:postcode":"32935",
    "sg:province":"FL",
    "wof:name":"Garys Big & Tall",
    "wof:placetype":"venue"
},
  "geometry": {"coordinates":[-80.650408,28.148377],"type":"Point"}
}