{
  "type": "Feature",
  "properties": {
    "iso:country":"US",
    "sg:address":"179 Southbay Dr",
    "sg:city":"Naples",
    "sg:classifiers":[
        {
            "category":"Restaurant",
            "type":"Food & Drink"
        }
    ],
    "sg:phone":"+1 239 566 1514",
    "sg:postcode":"34108",
    "sg:province":"FL",
    "sg:tags":[
        "eating"
    ],
    "wof:name":"Sea Witch Restaurant",
    "wof:placetype":"venue"
},
  "geometry": {"coordinates":[-81.821877,26.254681],"type":"Point"}
}