{
  "type": "Feature",
  "properties": {
    "addr:full":"3701 NE 163rd St North Miami Beach FL 33160",
    "addr:housenumber":"3701",
    "addr:postcode":"33160",
    "addr:street":"Ne 163Rd St",
    "iso:country":"US",
    "sg:address":"3701 NE 163rd St",
    "sg:city":"North Miami Beach",
    "sg:classifiers":[
        {
            "category":"Cinema",
            "subcategory":"Movie Theater",
            "type":"Entertainment"
        }
    ],
    "sg:phone":"+1 305 949 0064",
    "sg:postcode":"33160",
    "sg:province":"FL",
    "wof:name":"Intracoastal Cinema",
    "wof:placetype":"venue"
},
  "geometry": {"coordinates":[-80.132599,25.93],"type":"Point"}
}