{
  "type": "Feature",
  "properties": {
    "addr:full":"7715 NW 62nd St Miami FL 33166",
    "addr:housenumber":"7715",
    "addr:postcode":"33166",
    "addr:street":"Nw 62Nd St",
    "iso:country":"US",
    "sg:address":"7715 NW 62nd St",
    "sg:city":"Miami",
    "sg:classifiers":[
        {
            "category":"Home & Garden",
            "subcategory":"Carpets & Floor Coverings",
            "type":"Retail Goods"
        }
    ],
    "sg:phone":"+1 305 599 0052",
    "sg:postcode":"33166",
    "sg:province":"FL",
    "sg:tags":[
        "tile",
        "marble"
    ],
    "wof:name":"Palmetto Marble & Tile",
    "wof:placetype":"venue"
},
  "geometry": {"coordinates":[-80.322834,25.829916],"type":"Point"}
}