{
  "type": "Feature",
  "properties": {
    "iso:country":"US",
    "sg:address":"9405 S US Hwy 441",
    "sg:city":"Ocala",
    "sg:classifiers":[
        {
            "category":"Retail",
            "subcategory":"Auto Repair",
            "type":"Services"
        }
    ],
    "sg:phone":"+1 352 245 8467",
    "sg:postcode":"34480",
    "sg:province":"FL",
    "sg:tags":[
        "repairing",
        "automobile"
    ],
    "wof:name":"T & J's Shade Tree Motors",
    "wof:placetype":"venue"
},
  "geometry": {"coordinates":[-82.079601,29.085444],"type":"Point"}
}