{
  "type": "Feature",
  "properties": {
    "addr:full":"3101 W 7th Ave Hialeah FL 33012",
    "addr:housenumber":"3101",
    "addr:postcode":"33012",
    "addr:street":"W 7Th Ave",
    "iso:country":"US",
    "sg:address":"3101 W 7th Ave",
    "sg:city":"Hialeah",
    "sg:classifiers":[
        {
            "category":"Education",
            "subcategory":"Preschool",
            "type":"Public Place"
        },
        {
            "category":"Education",
            "subcategory":"School",
            "type":"Public Place"
        }
    ],
    "sg:phone":"+1 305 821 8848",
    "sg:postcode":"33012",
    "sg:province":"FL",
    "sg:tags":[
        "elementary"
    ],
    "wof:name":"Hernandez F Manny Rev",
    "wof:placetype":"venue"
},
  "geometry": {"coordinates":[-80.296402,25.8501],"type":"Point"}
}