{
  "type": "Feature",
  "properties": {
    "iso:country":"US",
    "sg:address":"5649 Boca Chica Ln",
    "sg:city":"Boca Raton",
    "sg:classifiers":[
        {
            "category":"Banks & Credit Unions",
            "subcategory":"Bank",
            "type":"Services"
        }
    ],
    "sg:phone":"+1 561 367 8484",
    "sg:postcode":"33433",
    "sg:province":"FL",
    "sg:tags":[
        "broker",
        "mortgage"
    ],
    "wof:name":"Beachside Mortgage Group Inc",
    "wof:placetype":"venue"
},
  "geometry": {"coordinates":[-80.131778,26.330468],"type":"Point"}
}