{
  "type": "Feature",
  "properties": {
    "addr:full":"266 Solana Rd Ponte Vedra Bch FL 32082",
    "addr:housenumber":"266",
    "addr:postcode":"32082",
    "addr:street":"Solana Rd",
    "iso:country":"US",
    "sg:address":"266 Solana Rd",
    "sg:city":"Ponte Vedra Bch",
    "sg:classifiers":[
        {
            "category":"Local Transit",
            "type":"Transportation"
        }
    ],
    "sg:phone":"+1 904 241 1678",
    "sg:postcode":"32082",
    "sg:province":"FL",
    "sg:tags":[
        "airport"
    ],
    "wof:name":"First Coast Personal Transprtn",
    "wof:placetype":"venue"
},
  "geometry": {"coordinates":[-81.388586,30.22725],"type":"Point"}
}