{
  "type": "Feature",
  "properties": {
    "iso:country":"US",
    "sg:address":"21013 SW 118th Ave",
    "sg:city":"Miami",
    "sg:classifiers":[
        {
            "category":"Manufacturing",
            "subcategory":"Glass & Minerals",
            "type":"Manufacturing & Wholesale Goods"
        }
    ],
    "sg:phone":"+1 786 242 3466",
    "sg:postcode":"33177",
    "sg:province":"FL",
    "sg:tags":[
        "concrete",
        "product",
        "mfg"
    ],
    "wof:name":"C&F Roof Tile & Loading",
    "wof:placetype":"venue"
},
  "geometry": {"coordinates":[-80.381925,25.570827],"type":"Point"}
}