{
  "type": "Feature",
  "properties": {
    "iso:country":"US",
    "sg:address":"9737 NW 41st St",
    "sg:city":"Doral",
    "sg:classifiers":[
        {
            "category":"Wholesale",
            "subcategory":"Construction Materials",
            "type":"Manufacturing & Wholesale Goods"
        },
        {
            "category":"Home & Garden",
            "subcategory":"Building Materials",
            "type":"Retail Goods"
        },
        {
            "category":"Building & Trades",
            "subcategory":"Construction",
            "type":"Services"
        }
    ],
    "sg:phone":"+1 305 597 9393",
    "sg:postcode":"33178",
    "sg:province":"FL",
    "sg:tags":[
        "concrete",
        "supply",
        "contractor",
        "equipment",
        "staining",
        "masonry"
    ],
    "wof:name":"Concrete Structures Inc",
    "wof:placetype":"venue"
},
  "geometry": {"coordinates":[-80.354028,25.811701],"type":"Point"}
}