{
  "type": "Feature",
  "properties": {
    "iso:country":"US",
    "sg:address":"3516 S Dixie Hwy",
    "sg:city":"West Palm Beach",
    "sg:classifiers":[
        {
            "category":"Home & Garden",
            "subcategory":"Home Furnishings",
            "type":"Retail Goods"
        }
    ],
    "sg:phone":"+1 561 833 3535",
    "sg:postcode":"33405",
    "sg:province":"FL",
    "sg:tags":[
        "curtain",
        "made",
        "drapery"
    ],
    "wof:name":"Palm Beach Designer Fabrics",
    "wof:placetype":"venue"
},
  "geometry": {"coordinates":[-80.054558,26.679849],"type":"Point"}
}