{
  "type": "Feature",
  "properties": {
    "iso:country":"US",
    "sg:address":"4054 S Ridgewood Ave",
    "sg:city":"Port Orange",
    "sg:classifiers":[
        {
            "category":"Shopping",
            "subcategory":"Music",
            "type":"Retail Goods"
        }
    ],
    "sg:phone":"+1 386 767 5441",
    "sg:postcode":"32127",
    "sg:province":"FL",
    "sg:tags":[
        "video",
        "disc",
        "tape",
        "cassette"
    ],
    "wof:name":"Video Time",
    "wof:placetype":"venue"
},
  "geometry": {"coordinates":[-80.986923,29.142312],"type":"Point"}
}