{
  "type": "Feature",
  "properties": {
    "iso:country":"US",
    "sg:address":"4125 NE 77 Ave",
    "sg:city":"Gainesville",
    "sg:classifiers":[
        {
            "category":"Retail",
            "subcategory":"Repair Shop",
            "type":"Services"
        }
    ],
    "sg:phone":"+1 352 373 3255",
    "sg:postcode":"32609",
    "sg:province":"FL",
    "sg:tags":[
        "appliance"
    ],
    "wof:name":"Burton's Appliance Svc",
    "wof:placetype":"venue"
},
  "geometry": {"coordinates":[-82.268641,29.724674],"type":"Point"}
}