{
  "type": "Feature",
  "properties": {
    "addr:full":"9210 Allwood Pl Orlando FL 32825",
    "addr:housenumber":"9210",
    "addr:postcode":"32825",
    "addr:street":"Allwood Pl",
    "iso:country":"US",
    "sg:address":"9210 Allwood Pl",
    "sg:city":"Orlando",
    "sg:classifiers":[
        {
            "category":"Manufacturing",
            "subcategory":"Toys & Sporting Goods",
            "type":"Manufacturing & Wholesale Goods"
        }
    ],
    "sg:phone":"+1 407 273 6588",
    "sg:postcode":"32825",
    "sg:province":"FL",
    "sg:tags":[
        "mfg"
    ],
    "wof:name":"Crafts Etc By Gail",
    "wof:placetype":"venue"
},
  "geometry": {"coordinates":[-81.25608800000001,28.538534],"type":"Point"}
}