{
  "type": "Feature",
  "properties": {
    "addr:full":"806 Chicago Ave Daytona Beach FL 32119",
    "addr:housenumber":"806",
    "addr:postcode":"32119",
    "addr:street":"Chicago Ave",
    "iso:country":"US",
    "sg:address":"806 Chicago Ave",
    "sg:city":"Daytona Beach",
    "sg:classifiers":[
        {
            "category":"Health Services",
            "subcategory":"Nursing And Care Facility",
            "type":"Services"
        }
    ],
    "sg:phone":"+1 386 761 5043",
    "sg:postcode":"32119",
    "sg:province":"FL",
    "wof:name":"Bettys Progressive Elder",
    "wof:placetype":"venue"
},
  "geometry": {"coordinates":[-81.01987800000001,29.176913],"type":"Point"}
}