{
  "type": "Feature",
  "properties": {
    "addr:full":"255 University Dr Coral Gables FL 33134",
    "addr:housenumber":"255",
    "addr:postcode":"33134",
    "addr:street":"University Dr",
    "iso:country":"US",
    "sg:address":"255 University Dr",
    "sg:city":"Coral Gables",
    "sg:classifiers":[
        {
            "category":"Professional",
            "subcategory":"Lawyer & Legal Services",
            "type":"Services"
        }
    ],
    "sg:phone":"+1 305 569 3005",
    "sg:postcode":"33134",
    "sg:province":"FL",
    "wof:name":"Law Offices of Mesa & Pereira PA",
    "wof:placetype":"venue"
},
  "geometry": {"coordinates":[-80.260002,25.743299],"type":"Point"}
}