{
  "type": "Feature",
  "properties": {
    "addr:full":"101 N Alabama Ave Deland FL 32724",
    "addr:housenumber":"101",
    "addr:postcode":"32724",
    "addr:street":"N Alabama Ave",
    "iso:country":"US",
    "sg:address":"101 N Alabama Ave",
    "sg:city":"Deland",
    "sg:classifiers":[
        {
            "category":"Government",
            "subcategory":"Police Station",
            "type":"Public Place"
        }
    ],
    "sg:phone":"+1 386 822 5014",
    "sg:postcode":"32724",
    "sg:province":"FL",
    "sg:tags":[
        "sheriff"
    ],
    "wof:name":"Volusia County Sheriff-Civil",
    "wof:placetype":"venue"
},
  "geometry": {"coordinates":[-81.30135300000001,29.028084],"type":"Point"}
}