{
  "type": "Feature",
  "properties": {
    "iso:country":"US",
    "sg:address":"3301 S Shamrock Rd",
    "sg:city":"Tampa",
    "sg:classifiers":[
        {
            "category":"Manufacturing",
            "subcategory":"Furniture",
            "type":"Manufacturing & Wholesale Goods"
        }
    ],
    "sg:phone":"+1 813 831 6412",
    "sg:postcode":"33629",
    "sg:province":"FL",
    "sg:tags":[
        "household",
        "wood",
        "mfg"
    ],
    "wof:name":"Island Wood Works Inc",
    "wof:placetype":"venue"
},
  "geometry": {"coordinates":[-82.523115,27.915063],"type":"Point"}
}