{
  "type": "Feature",
  "properties": {
    "iso:country":"US",
    "sg:address":"1605 Main St",
    "sg:city":"Sarasota",
    "sg:classifiers":[
        {
            "category":"Real Estate",
            "subcategory":"Real Estate Operator",
            "type":"Services"
        }
    ],
    "sg:phone":"+1 941 951 0198",
    "sg:postcode":"34236",
    "sg:province":"FL",
    "sg:tags":[
        "building",
        "parks"
    ],
    "wof:name":"Ellis Building",
    "wof:placetype":"venue"
},
  "geometry": {"coordinates":[-82.537598,27.336535],"type":"Point"}
}