{
  "type": "Feature",
  "properties": {
    "addr:full":"922 S Horry St Madison FL 32340",
    "addr:housenumber":"922",
    "addr:postcode":"32340",
    "addr:street":"S Horry St",
    "iso:country":"US",
    "sg:address":"922 S Horry St",
    "sg:city":"Madison",
    "sg:classifiers":[
        {
            "category":"Home & Garden",
            "subcategory":"Furniture",
            "type":"Retail Goods"
        }
    ],
    "sg:phone":"+1 850 973 3880",
    "sg:postcode":"32340",
    "sg:province":"FL",
    "sg:tags":[
        "household",
        "used",
        "merchandise"
    ],
    "wof:name":"Aust Enterprises",
    "wof:placetype":"venue"
},
  "geometry": {"coordinates":[-83.414035,30.462288],"type":"Point"}
}