{
  "type": "Feature",
  "properties": {
    "iso:country":"US",
    "sg:address":"202 S Park Ave",
    "sg:city":"Winter Park",
    "sg:classifiers":[
        {
            "category":"Shopping",
            "subcategory":"Clothing, Apparel, & Fashions",
            "type":"Retail Goods"
        }
    ],
    "sg:phone":"+1 407 645 4297",
    "sg:postcode":"32789",
    "sg:province":"FL",
    "sg:tags":[
        "accessory",
        "clothing",
        "women's"
    ],
    "wof:name":"Moda Park Avenue Boutique",
    "wof:placetype":"venue"
},
  "geometry": {"coordinates":[-81.350998,28.5968],"type":"Point"}
}