{
  "type": "Feature",
  "properties": {
    "addr:full":"2326 W 62nd St Hialeah FL 33016",
    "addr:housenumber":"2326",
    "addr:postcode":"33016",
    "addr:street":"W 62Nd St",
    "iso:country":"US",
    "sg:address":"2326 W 62nd St",
    "sg:city":"Hialeah",
    "sg:classifiers":[
        {
            "category":"Professional",
            "subcategory":"Art Services",
            "type":"Services"
        }
    ],
    "sg:phone":"+1 305 821 1931",
    "sg:postcode":"33016",
    "sg:province":"FL",
    "sg:tags":[
        "commercial",
        "design"
    ],
    "wof:name":"Ana Tellez",
    "wof:placetype":"venue"
},
  "geometry": {"coordinates":[-80.32975399999999,25.879671],"type":"Point"}
}