{
  "type": "Feature",
  "properties": {
    "iso:country":"US",
    "sg:address":"3111 S Crystal Lake Dr",
    "sg:city":"Orlando",
    "sg:classifiers":[
        {
            "category":"Utilities",
            "subcategory":"Telephone",
            "type":"Services"
        }
    ],
    "sg:phone":"+1 407 850 4348",
    "sg:postcode":"32806",
    "sg:province":"FL",
    "sg:tags":[
        "communication"
    ],
    "wof:name":"Vonage America",
    "wof:placetype":"venue"
},
  "geometry": {"coordinates":[-81.34325699999999,28.505429],"type":"Point"}
}