{
  "type": "Feature",
  "properties": {
    "addr:full":"1250 Mariner Blvd Spring Hill FL 34609",
    "addr:housenumber":"1250",
    "addr:postcode":"34609",
    "addr:street":"Mariner Blvd",
    "iso:country":"US",
    "sg:address":"1250 Mariner Blvd",
    "sg:city":"Spring Hill",
    "sg:classifiers":[
        {
            "category":"Health Services",
            "subcategory":"Doctor",
            "type":"Services"
        }
    ],
    "sg:phone":"+1 352 666 0202",
    "sg:postcode":"34609",
    "sg:province":"FL",
    "sg:tags":[
        "medical"
    ],
    "wof:name":"Armbruster Thomas J",
    "wof:placetype":"venue"
},
  "geometry": {"coordinates":[-82.539221,28.453338],"type":"Point"}
}