{
  "type": "Feature",
  "properties": {
    "iso:country":"US",
    "sg:address":"1560 S Deleon Ave",
    "sg:city":"Titusville",
    "sg:classifiers":[
        {
            "category":"Personal",
            "subcategory":"Beauty Salon",
            "type":"Services"
        }
    ],
    "sg:phone":"+1 321 480 3683",
    "sg:postcode":"32780",
    "sg:province":"FL",
    "wof:name":"Lincoln's Style Ctr",
    "wof:placetype":"venue"
},
  "geometry": {"coordinates":[-80.814353,28.597116],"type":"Point"}
}