{
  "type": "Feature",
  "properties": {
    "iso:country":"US",
    "sg:address":"625 Cassat Ave",
    "sg:city":"Jacksonville",
    "sg:classifiers":[
        {
            "category":"Place Of Worship",
            "subcategory":"Church",
            "type":"Public Place"
        },
        {
            "category":"Place Of Worship",
            "type":"Public Place"
        },
        {
            "category":"Social Services",
            "subcategory":"Child Care",
            "type":"Services"
        }
    ],
    "sg:phone":"+1 904 384 3900",
    "sg:postcode":"32205",
    "sg:province":"FL",
    "sg:tags":[
        "nursery",
        "day",
        "churches-non-denominational"
    ],
    "wof:name":"Christian Life Enrichment",
    "wof:placetype":"venue"
},
  "geometry": {"coordinates":[-81.73071299999999,30.316351],"type":"Point"}
}