{
  "type": "Feature",
  "properties": {
    "addr:full":"6900 N Waterway Dr Miami FL 33155",
    "addr:housenumber":"6900",
    "addr:postcode":"33155",
    "addr:street":"N Waterway Dr",
    "iso:country":"US",
    "sg:address":"6900 N Waterway Dr",
    "sg:city":"Miami",
    "sg:classifiers":[
        {
            "category":"Professional",
            "subcategory":"Engineering",
            "type":"Services"
        }
    ],
    "sg:phone":"+1 305 666 3958",
    "sg:postcode":"33155",
    "sg:province":"FL",
    "sg:tags":[
        "consulting",
        "structural",
        "engineer"
    ],
    "wof:name":"O J Jorgensen & Associates",
    "wof:placetype":"venue"
},
  "geometry": {"coordinates":[-80.306152,25.73996],"type":"Point"}
}