{
  "type": "Feature",
  "properties": {
    "addr:full":"7254 113th St Seminole FL 33772",
    "addr:housenumber":"7254",
    "addr:postcode":"33772",
    "addr:street":"113Th St",
    "iso:country":"US",
    "sg:address":"7254 113th St",
    "sg:city":"Seminole",
    "sg:classifiers":[
        {
            "category":"Recreation",
            "type":"Entertainment"
        }
    ],
    "sg:phone":"+1 727 391 2999",
    "sg:postcode":"33772",
    "sg:province":"FL",
    "sg:tags":[
        "ticket"
    ],
    "wof:name":"George Panagoulis Sebring",
    "wof:placetype":"venue"
},
  "geometry": {"coordinates":[-82.79539,27.838049],"type":"Point"}
}