{
  "type": "Feature",
  "properties": {
    "iso:country":"US",
    "sg:address":"3553 W 76th St",
    "sg:city":"Hialeah",
    "sg:classifiers":[
        {
            "category":"Food & Beverages",
            "subcategory":"Meat & Fish",
            "type":"Retail Goods"
        }
    ],
    "sg:phone":"+1 305 362 6610",
    "sg:postcode":"33018",
    "sg:province":"FL",
    "sg:tags":[
        "shop"
    ],
    "wof:name":"El Guajiro Grocery & Meat Market",
    "wof:placetype":"venue"
},
  "geometry": {"coordinates":[-80.355395,25.891626],"type":"Point"}
}