{
  "type": "Feature",
  "properties": {
    "iso:country":"US",
    "sg:address":"333 Holmes Ave",
    "sg:city":"Lake Placid",
    "sg:classifiers":[
        {
            "category":"Manufacturing",
            "subcategory":"Metals",
            "type":"Manufacturing & Wholesale Goods"
        }
    ],
    "sg:phone":"+1 863 465 9412",
    "sg:postcode":"33852",
    "sg:province":"FL",
    "sg:tags":[
        "copper",
        "foundry"
    ],
    "wof:name":"Performance Propellers Inc",
    "wof:placetype":"venue"
},
  "geometry": {"coordinates":[-81.334221,27.290744],"type":"Point"}
}