{
  "type": "Feature",
  "properties": {
    "iso:country":"US",
    "sg:address":"20110 Holland Ave",
    "sg:city":"Port Charlotte",
    "sg:classifiers":[
        {
            "category":"Building & Trades",
            "subcategory":"Construction",
            "type":"Services"
        }
    ],
    "sg:phone":"+1 941 235 3305",
    "sg:postcode":"33952",
    "sg:province":"FL",
    "sg:tags":[
        "carpentry",
        "contractor"
    ],
    "wof:name":"Scotts Custom Carpentry Inc",
    "wof:placetype":"venue"
},
  "geometry": {"coordinates":[-82.119474,27.012269],"type":"Point"}
}