{
  "type": "Feature",
  "properties": {
    "iso:country":"US",
    "sg:address":"1100 Oakbridge Pkwy",
    "sg:city":"Lakeland",
    "sg:classifiers":[
        {
            "category":"Building & Trades",
            "subcategory":"Construction",
            "type":"Services"
        }
    ],
    "sg:phone":"+1 863 644 9888",
    "sg:postcode":"33803",
    "sg:province":"FL",
    "sg:tags":[
        "floor",
        "laying",
        "contractor"
    ],
    "wof:name":"Mimart Inc",
    "wof:placetype":"venue"
},
  "geometry": {"coordinates":[-81.97035700000001,28.003801],"type":"Point"}
}