{
  "type": "Feature",
  "properties": {
    "iso:country":"US",
    "sg:address":"2101 NE Savannah Rd",
    "sg:city":"Jensen Beach",
    "sg:classifiers":[
        {
            "category":"Real Estate",
            "subcategory":"Real Estate Operator",
            "type":"Services"
        }
    ],
    "sg:phone":"+1 772 334 1414",
    "sg:postcode":"34957",
    "sg:province":"FL",
    "sg:tags":[
        "mobile",
        "home",
        "site",
        "community"
    ],
    "wof:name":"Pine Lake Village",
    "wof:placetype":"venue"
},
  "geometry": {"coordinates":[-80.23642,27.229335],"type":"Point"}
}