{
  "type": "Feature",
  "properties": {
    "iso:country":"US",
    "sg:address":"311 S Babcock St",
    "sg:city":"Melbourne",
    "sg:classifiers":[
        {
            "category":"Manufacturing",
            "subcategory":"Signs",
            "type":"Manufacturing & Wholesale Goods"
        }
    ],
    "sg:phone":"+1 321 723 7446",
    "sg:postcode":"32901",
    "sg:province":"FL",
    "sg:tags":[
        "specialty",
        "mfg"
    ],
    "wof:name":"Sign Quick",
    "wof:placetype":"venue"
},
  "geometry": {"coordinates":[-80.621773,28.104019],"type":"Point"}
}