{
  "type": "Feature",
  "properties": {
    "iso:country":"US",
    "sg:address":"38 Bay View Cove",
    "sg:city":"Niceville",
    "sg:classifiers":[
        {
            "category":"Professional",
            "subcategory":"Detective & Security Services",
            "type":"Services"
        }
    ],
    "sg:phone":"+1 850 897 9400",
    "sg:postcode":"32578",
    "sg:province":"FL",
    "sg:tags":[
        "guard",
        "patrol"
    ],
    "wof:name":"Windward Property Owners Assn",
    "wof:placetype":"venue"
},
  "geometry": {"coordinates":[-86.394327,30.454809],"type":"Point"}
}