{
  "type": "Feature",
  "properties": {
    "addr:full":"979 Cambridge Ct Kissimmee FL 34758",
    "addr:housenumber":"979",
    "addr:postcode":"34758",
    "addr:street":"Cambridge Ct",
    "iso:country":"US",
    "sg:address":"979 Cambridge Ct",
    "sg:city":"Kissimmee",
    "sg:classifiers":[
        {
            "category":"Retail",
            "subcategory":"Car Wash",
            "type":"Services"
        }
    ],
    "sg:phone":"+1 407 791 6079",
    "sg:postcode":"34758",
    "sg:province":"FL",
    "sg:tags":[
        "automobile",
        "detail",
        "clean"
    ],
    "wof:name":"William Taylor Auto Detailing",
    "wof:placetype":"venue"
},
  "geometry": {"coordinates":[-81.49883699999999,28.178035],"type":"Point"}
}