{
  "type": "Feature",
  "properties": {
    "addr:full":"5102 NW 4th Ter Miami FL 33126",
    "addr:housenumber":"5102",
    "addr:postcode":"33126",
    "addr:street":"Nw 4Th Ter",
    "iso:country":"US",
    "sg:address":"5102 NW 4th Ter",
    "sg:city":"Miami",
    "sg:classifiers":[
        {
            "category":"Professional",
            "subcategory":"Accounting & Tax Preparation",
            "type":"Services"
        }
    ],
    "sg:phone":"+1 305 529 0903",
    "sg:postcode":"33126",
    "sg:province":"FL",
    "sg:tags":[
        "bookkeeping",
        "general"
    ],
    "wof:name":"All USA Bookkeeping Svc Inc",
    "wof:placetype":"venue"
},
  "geometry": {"coordinates":[-80.280021,25.776],"type":"Point"}
}