{
  "type": "Feature",
  "properties": {
    "addr:full":"920 Delaney Ave Orlando FL 32806",
    "addr:housenumber":"920",
    "addr:postcode":"32806",
    "addr:street":"Delaney Ave",
    "iso:country":"US",
    "sg:address":"920 Delaney Ave",
    "sg:city":"Orlando",
    "sg:classifiers":[
        {
            "category":"Real Estate",
            "subcategory":"Real Estate Agent",
            "type":"Services"
        }
    ],
    "sg:phone":"+1 407 870 0084",
    "sg:postcode":"32806",
    "sg:province":"FL",
    "wof:name":"Walker Appraisal Svc",
    "wof:placetype":"venue"
},
  "geometry": {"coordinates":[-81.374033,28.530013],"type":"Point"}
}