{
  "type": "Feature",
  "properties": {
    "iso:country":"US",
    "sg:address":"972 W 79th Pl",
    "sg:city":"Hialeah",
    "sg:classifiers":[
        {
            "category":"Professional",
            "type":"Services"
        }
    ],
    "sg:phone":"+1 305 362 2694",
    "sg:postcode":"33014",
    "sg:province":"FL",
    "wof:name":"Mystic Urchin Inc",
    "wof:placetype":"venue"
},
  "geometry": {"coordinates":[-80.30089099999999,25.894949],"type":"Point"}
}