{
  "type": "Feature",
  "properties": {
    "iso:country":"US",
    "sg:address":"1725 N University Dr",
    "sg:city":"Coral Springs",
    "sg:classifiers":[
        {
            "category":"Health Services",
            "subcategory":"Health Practitioner",
            "type":"Services"
        }
    ],
    "sg:phone":"+1 954 755 0909",
    "sg:postcode":"33071",
    "sg:province":"FL",
    "sg:tags":[
        "psychologist"
    ],
    "wof:name":"Alan A Jaffe & Assoc",
    "wof:placetype":"venue"
},
  "geometry": {"coordinates":[-80.25284499999999,26.253284],"type":"Point"}
}