{
  "type": "Feature",
  "properties": {
    "iso:country":"US",
    "sg:address":"1551 Wilmington Dr",
    "sg:city":"Melbourne",
    "sg:classifiers":[
        {
            "category":"Home & Garden",
            "subcategory":"Building Materials",
            "type":"Retail Goods"
        },
        {
            "category":"Building & Trades",
            "subcategory":"Construction",
            "type":"Services"
        }
    ],
    "sg:phone":"+1 321 757 9882",
    "sg:postcode":"32940",
    "sg:province":"FL",
    "sg:tags":[
        "builder"
    ],
    "wof:name":"Mercedes Homes Inc",
    "wof:placetype":"venue"
},
  "geometry": {"coordinates":[-80.700551,28.200251],"type":"Point"}
}