{
  "type": "Feature",
  "properties": {
    "addr:full":"1816 SW 7th Ave Pompano Beach FL 33060",
    "addr:housenumber":"1816",
    "addr:postcode":"33060",
    "addr:street":"Sw 7Th Ave",
    "iso:country":"US",
    "sg:address":"1816 SW 7th Ave",
    "sg:city":"Pompano Beach",
    "sg:classifiers":[
        {
            "category":"Manufacturing",
            "subcategory":"Printing",
            "type":"Manufacturing & Wholesale Goods"
        }
    ],
    "sg:phone":"+1 954 943 6226",
    "sg:postcode":"33060",
    "sg:province":"FL",
    "sg:tags":[
        "commercial"
    ],
    "wof:name":"Advanced Plastic Cards",
    "wof:placetype":"venue"
},
  "geometry": {"coordinates":[-80.13129499999999,26.210019],"type":"Point"}
}