{
  "type": "Feature",
  "properties": {
    "iso:country":"US",
    "sg:address":"11579 56th Pl N",
    "sg:city":"West Palm Beach",
    "sg:classifiers":[
        {
            "category":"Professional",
            "subcategory":"Management & Consulting",
            "type":"Services"
        }
    ],
    "sg:phone":"+1 561 333 3667",
    "sg:postcode":"33411",
    "sg:province":"FL",
    "sg:tags":[
        "consultant",
        "business"
    ],
    "wof:name":"Jenco Enterprises Inc",
    "wof:placetype":"venue"
},
  "geometry": {"coordinates":[-80.225565,26.76026],"type":"Point"}
}