{
  "type": "Feature",
  "properties": {
    "iso:country":"US",
    "sg:address":"5832 Hunting Meadows Dr",
    "sg:city":"Crestview",
    "sg:classifiers":[
        {
            "category":"Professional",
            "subcategory":"Advertising",
            "type":"Services"
        },
        {
            "category":"Shopping",
            "subcategory":"Crafts & Fabrics",
            "type":"Retail Goods"
        },
        {
            "category":"Wholesale",
            "subcategory":"Toys & Hobbies",
            "type":"Manufacturing & Wholesale Goods"
        }
    ],
    "sg:phone":"+1 850 423 0178",
    "sg:postcode":"32536",
    "sg:province":"FL",
    "sg:tags":[
        "advertising-promotional",
        "embroidery-wholesale",
        "product",
        "embroidery"
    ],
    "wof:name":"Classic Traditions & Designs",
    "wof:placetype":"venue"
},
  "geometry": {"coordinates":[-86.57408100000001,30.7988],"type":"Point"}
}