{
  "type": "Feature",
  "properties": {
    "iso:country":"US",
    "sg:address":"7005 Montreal Dr",
    "sg:city":"Lakeland",
    "sg:classifiers":[
        {
            "category":"Real Estate",
            "subcategory":"Developer",
            "type":"Services"
        }
    ],
    "sg:phone":"+1 863 816 8967",
    "sg:postcode":"33810",
    "sg:province":"FL",
    "wof:name":"Fort Myers Development",
    "wof:placetype":"venue"
},
  "geometry": {"coordinates":[-82.00134199999999,28.133911],"type":"Point"}
}