{
  "type": "Feature",
  "properties": {
    "iso:country":"US",
    "sg:address":"3659 S Miami Ave Ste 4002",
    "sg:city":"Miami",
    "sg:classifiers":[
        {
            "category":"Health Services",
            "subcategory":"Doctor",
            "type":"Services"
        }
    ],
    "sg:phone":"+1 305 285 6933",
    "sg:postcode":"33133",
    "sg:province":"FL",
    "sg:tags":[
        "physician",
        "surgeon",
        "neurology",
        "surgeons"
    ],
    "wof:name":"Edwardo L Ivarra Md Pa",
    "wof:placetype":"venue"
},
  "geometry": {"coordinates":[-80.2159,25.743585],"type":"Point"}
}