{
  "type": "Feature",
  "properties": {
    "iso:country":"US",
    "sg:address":"5001 Co Rd 630",
    "sg:city":"Frostproof",
    "sg:classifiers":[
        {
            "category":"Farming",
            "subcategory":"Livestock Farm",
            "type":"Manufacturing & Wholesale Goods"
        }
    ],
    "sg:phone":"+1 863 635 4033",
    "sg:postcode":"33843",
    "sg:province":"FL",
    "sg:tags":[
        "feedlot",
        "cattle",
        "specialty",
        "beef",
        "animal"
    ],
    "wof:name":"F X Bar Ranch Inc",
    "wof:placetype":"venue"
},
  "geometry": {"coordinates":[-81.432597,27.766364],"type":"Point"}
}