{
  "type": "Feature",
  "properties": {
    "iso:country":"US",
    "sg:address":"26749 Bloomfield Ave",
    "sg:city":"Yalaha",
    "sg:classifiers":[
        {
            "category":"Shopping",
            "subcategory":"Music",
            "type":"Retail Goods"
        }
    ],
    "sg:phone":"+1 352 324 2156",
    "sg:postcode":"34797",
    "sg:province":"FL",
    "sg:tags":[
        "satellite",
        "re",
        "tape",
        "rent",
        "dish",
        "video"
    ],
    "wof:name":"Florida Video & Electronics",
    "wof:placetype":"venue"
},
  "geometry": {"coordinates":[-81.815378,28.736329],"type":"Point"}
}