{
  "type": "Feature",
  "properties": {
    "iso:country":"US",
    "sg:address":"4301 38th Ave N",
    "sg:city":"St Petersburg",
    "sg:classifiers":[
        {
            "category":"Organizations",
            "subcategory":"Religious Organization",
            "type":"Services"
        }
    ],
    "sg:phone":"+1 727 526 1592",
    "sg:postcode":"33713",
    "sg:province":"FL",
    "sg:tags":[
        "church"
    ],
    "wof:name":"Clearview Baptist Church",
    "wof:placetype":"venue"
},
  "geometry": {"coordinates":[-82.69280999999999,27.806441],"type":"Point"}
}