{
  "type": "Feature",
  "properties": {
    "iso:country":"US",
    "sg:address":"4001 S Ocean Dr",
    "sg:city":"Hollywood",
    "sg:classifiers":[
        {
            "category":"Restaurant",
            "type":"Food & Drink"
        },
        {
            "category":"Ice Cream",
            "type":"Food & Drink"
        }
    ],
    "sg:phone":"+1 954 454 4931",
    "sg:postcode":"33019",
    "sg:province":"FL",
    "sg:tags":[
        "frozen",
        "dessert"
    ],
    "wof:name":"Victoria's Flavors Unlimited",
    "wof:placetype":"venue"
},
  "geometry": {"coordinates":[-80.119238,25.986856],"type":"Point"}
}