{
  "type": "Feature",
  "properties": {
    "iso:country":"US",
    "sg:address":"151 Southhall Ln",
    "sg:city":"Maitland",
    "sg:classifiers":[
        {
            "category":"Professional",
            "subcategory":"Business Services",
            "type":"Services"
        }
    ],
    "sg:phone":"+1 407 660 0912",
    "sg:postcode":"32751",
    "sg:province":"FL",
    "sg:tags":[
        "information",
        "referral"
    ],
    "wof:name":"Hancock Information Group Inc",
    "wof:placetype":"venue"
},
  "geometry": {"coordinates":[-81.396428,28.628384],"type":"Point"}
}