{
  "type": "Feature",
  "properties": {
    "iso:country":"US",
    "sg:address":"701 N Dixie Fwy",
    "sg:city":"New Smyrna Beach",
    "sg:classifiers":[
        {
            "category":"Restaurant",
            "type":"Food & Drink"
        }
    ],
    "sg:phone":"+1 386 427 0414",
    "sg:postcode":"32168",
    "sg:province":"FL",
    "sg:tags":[
        "drinking",
        "eating"
    ],
    "sg:website":"www.blackbeardsinn.com",
    "wof:name":"Blackbeard's Inn",
    "wof:placetype":"venue"
},
  "geometry": {"coordinates":[-80.93168799999999,29.03621],"type":"Point"}
}