{
  "type": "Feature",
  "properties": {
    "iso:country":"US",
    "sg:address":"2213 Alaqua Dr",
    "sg:city":"Longwood",
    "sg:classifiers":[
        {
            "category":"Shopping",
            "subcategory":"Clothing, Apparel, & Fashions",
            "type":"Retail Goods"
        },
        {
            "category":"Wholesale",
            "subcategory":"Apparel",
            "type":"Manufacturing & Wholesale Goods"
        }
    ],
    "sg:phone":"+1 407 333 9517",
    "sg:postcode":"32779",
    "sg:province":"FL",
    "sg:tags":[
        "sportswear-wholesale",
        "sportswear",
        "manufacturer"
    ],
    "sg:website":"http://www.nsemblem.com",
    "wof:name":"National Sportswear & Emblem",
    "wof:placetype":"venue"
},
  "geometry": {"coordinates":[-81.400672,28.748287],"type":"Point"}
}