{
  "type": "Feature",
  "properties": {
    "iso:country":"US",
    "sg:address":"2685 Executive Park Dr",
    "sg:city":"Weston",
    "sg:classifiers":[
        {
            "category":"Health Services",
            "subcategory":"Hospital",
            "type":"Services"
        }
    ],
    "sg:phone":"+1 954 385 3456",
    "sg:postcode":"33331",
    "sg:province":"FL",
    "sg:tags":[
        "mental"
    ],
    "wof:name":"Bilingual Therapy Assoc",
    "wof:placetype":"venue"
},
  "geometry": {"coordinates":[-80.372803,26.085131],"type":"Point"}
}