{
  "type": "Feature",
  "properties": {
    "addr:full":"4 Walnut Cir Ormond Beach FL 32174",
    "addr:housenumber":"4",
    "addr:postcode":"32174",
    "addr:street":"Walnut Cir",
    "iso:country":"US",
    "sg:address":"4 Walnut Cir",
    "sg:city":"Ormond Beach",
    "sg:classifiers":[
        {
            "category":"Building & Trades",
            "subcategory":"Construction",
            "type":"Services"
        }
    ],
    "sg:phone":"+1 386 503 0039",
    "sg:postcode":"32174",
    "sg:province":"FL",
    "sg:tags":[
        "contractor"
    ],
    "wof:name":"Bruce Freund",
    "wof:placetype":"venue"
},
  "geometry": {"coordinates":[-81.117735,29.337226],"type":"Point"}
}