{
  "type": "Feature",
  "properties": {
    "addr:full":"3341 NE 29th Ave Lighthouse Point FL 33064",
    "addr:housenumber":"3341",
    "addr:postcode":"33064",
    "addr:street":"Ne 29Th Ave",
    "iso:country":"US",
    "sg:address":"3341 NE 29th Ave",
    "sg:city":"Lighthouse Point",
    "sg:classifiers":[
        {
            "category":"Building & Trades",
            "subcategory":"Construction",
            "type":"Services"
        }
    ],
    "sg:phone":"+1 954 941 7027",
    "sg:postcode":"33064",
    "sg:province":"FL",
    "sg:tags":[
        "contractor",
        "commercial",
        "tenant",
        "improvement"
    ],
    "wof:name":"Ashwood Construction Inc",
    "wof:placetype":"venue"
},
  "geometry": {"coordinates":[-80.083951,26.272888],"type":"Point"}
}