{
  "type": "Feature",
  "properties": {
    "iso:country":"US",
    "sg:address":"203 SW 85th Ter",
    "sg:city":"Pembroke Pines",
    "sg:classifiers":[
        {
            "category":"Professional",
            "type":"Services"
        }
    ],
    "sg:phone":"+1 954 436 6950",
    "sg:postcode":"33025",
    "sg:province":"FL",
    "sg:tags":[
        "establishment"
    ],
    "wof:name":"RLT",
    "wof:placetype":"venue"
},
  "geometry": {"coordinates":[-80.25604199999999,26.008262],"type":"Point"}
}