{
  "type": "Feature",
  "properties": {
    "iso:country":"US",
    "sg:address":"4302 Charro Ln",
    "sg:city":"Plant City",
    "sg:classifiers":[
        {
            "category":"Real Estate",
            "subcategory":"Real Estate Operator",
            "type":"Services"
        }
    ],
    "sg:phone":"+1 813 988 9596",
    "sg:postcode":"33565",
    "sg:province":"FL",
    "sg:tags":[
        "building",
        "mobile",
        "site",
        "home",
        "nonresidential"
    ],
    "wof:name":"Ridge Manor Properties Inc",
    "wof:placetype":"venue"
},
  "geometry": {"coordinates":[-82.231588,28.072066],"type":"Point"}
}