{
  "type": "Feature",
  "properties": {
    "addr:full":"2816 Del Prado Blvd S Ste 6 Cape Coral FL 33904",
    "addr:housenumber":"2816",
    "addr:postcode":"33904",
    "addr:street":"Del Prado Blvd S Ste 6",
    "iso:country":"US",
    "sg:address":"2816 Del Prado Blvd S Ste 6",
    "sg:city":"Cape Coral",
    "sg:classifiers":[
        {
            "category":"Shopping",
            "subcategory":"Florist",
            "type":"Retail Goods"
        }
    ],
    "sg:phone":"+1 239 540 2130",
    "sg:postcode":"33904",
    "sg:province":"FL",
    "wof:name":"Cape Coral Flowers & Gifts",
    "wof:placetype":"venue"
},
  "geometry": {"coordinates":[-81.941688,26.599288],"type":"Point"}
}