{
  "type": "Feature",
  "properties": {
    "addr:full":"10905 Satellite Blvd Orlando FL 32837",
    "addr:housenumber":"10905",
    "addr:postcode":"32837",
    "addr:street":"Satellite Blvd",
    "iso:country":"US",
    "sg:address":"10905 Satellite Blvd",
    "sg:city":"Orlando",
    "sg:classifiers":[
        {
            "category":"Shopping",
            "subcategory":"Gifts & Souvenirs",
            "type":"Retail Goods"
        }
    ],
    "sg:phone":"+1 407 855 0003",
    "sg:postcode":"32837",
    "sg:province":"FL",
    "wof:name":"A Basket & Floral Affair Inc",
    "wof:placetype":"venue"
},
  "geometry": {"coordinates":[-81.401557,28.407443],"type":"Point"}
}