{
  "type": "Feature",
  "properties": {
    "iso:country":"US",
    "sg:address":"6900 NW 9th Blvd",
    "sg:city":"Gainesville",
    "sg:classifiers":[
        {
            "category":"Health Services",
            "subcategory":"Doctor",
            "type":"Services"
        }
    ],
    "sg:phone":"+1 352 333 6680",
    "sg:postcode":"32605",
    "sg:province":"FL",
    "sg:tags":[
        "physician",
        "family",
        "practice",
        "surgeons",
        "medicine",
        "surgeon"
    ],
    "wof:name":"Thompson, David MD",
    "wof:placetype":"venue"
},
  "geometry": {"coordinates":[-82.414902,29.661631],"type":"Point"}
}