{
  "type": "Feature",
  "properties": {
    "iso:country":"US",
    "sg:address":"6436 Butte Ave",
    "sg:city":"New Port Richey",
    "sg:classifiers":[
        {
            "category":"Building & Trades",
            "subcategory":"Construction",
            "type":"Services"
        }
    ],
    "sg:phone":"+1 727 848 4430",
    "sg:postcode":"34653",
    "sg:province":"FL",
    "sg:tags":[
        "installation",
        "fence",
        "deck"
    ],
    "wof:name":"Allstate Fence & Deck",
    "wof:placetype":"venue"
},
  "geometry": {"coordinates":[-82.70845799999999,28.2222],"type":"Point"}
}