{
  "type": "Feature",
  "properties": {
    "addr:full":"7244 Biscayne Boulevard Miami FL 33138",
    "addr:housenumber":"7244",
    "addr:postcode":"33138",
    "addr:street":"Biscayne Boulevard",
    "iso:country":"US",
    "sg:address":"7244 Biscayne Boulevard",
    "sg:city":"Miami",
    "sg:classifiers":[
        {
            "category":"Restaurant",
            "type":"Food & Drink"
        }
    ],
    "sg:phone":"+1 305 754 3100",
    "sg:postcode":"33138",
    "sg:province":"FL",
    "sg:tags":[
        "sushi",
        "bar"
    ],
    "sg:website":"www.sushisquare.com",
    "wof:name":"Sushi Square",
    "wof:placetype":"venue"
},
  "geometry": {"coordinates":[-80.184397,25.842069],"type":"Point"}
}