{
  "type": "Feature",
  "properties": {
    "iso:country":"US",
    "sg:address":"206 NE Old Bridge Rd",
    "sg:city":"Mayo",
    "sg:classifiers":[
        {
            "category":"Place Of Worship",
            "subcategory":"Church",
            "type":"Public Place"
        },
        {
            "category":"Place Of Worship",
            "type":"Public Place"
        }
    ],
    "sg:phone":"+1 386 294 2837",
    "sg:postcode":"32066",
    "sg:province":"FL",
    "sg:tags":[
        "churches-baptist-general",
        "churches-baptist"
    ],
    "wof:name":"New Hope Baptist Church Of Laf",
    "wof:placetype":"venue"
},
  "geometry": {"coordinates":[-83.163602,30.093344],"type":"Point"}
}