{
  "type": "Feature",
  "properties": {
    "iso:country":"US",
    "sg:address":"2619 Chicago Ave",
    "sg:city":"Sebring",
    "sg:classifiers":[
        {
            "category":"Professional",
            "type":"Services"
        }
    ],
    "sg:phone":"+1 863 314 8646",
    "sg:postcode":"33870",
    "sg:province":"FL",
    "wof:name":"Stephens Brothers Inc",
    "wof:placetype":"venue"
},
  "geometry": {"coordinates":[-81.441185,27.483367],"type":"Point"}
}