{
  "type": "Feature",
  "properties": {
    "iso:country":"US",
    "sg:address":"2220 E 138th Ave",
    "sg:city":"Tampa",
    "sg:classifiers":[
        {
            "category":"Social Services",
            "subcategory":"Adult Care",
            "type":"Services"
        }
    ],
    "sg:phone":"+1 813 977 5241",
    "sg:postcode":"33613",
    "sg:province":"FL",
    "sg:tags":[
        "home",
        "group"
    ],
    "wof:name":"Northside Mental Health",
    "wof:placetype":"venue"
},
  "geometry": {"coordinates":[-82.43391200000001,28.072938],"type":"Point"}
}