{
  "type": "Feature",
  "properties": {
    "iso:country":"US",
    "sg:address":"5960 Central Ave",
    "sg:city":"St Petersburg",
    "sg:classifiers":[
        {
            "category":"Professional",
            "subcategory":"Lawyer & Legal Services",
            "type":"Services"
        }
    ],
    "sg:phone":"+1 727 381 9522",
    "sg:postcode":"33707",
    "sg:province":"FL",
    "sg:tags":[
        "attorney"
    ],
    "wof:name":"Melissa R Sharpsteen & Assoc",
    "wof:placetype":"venue"
},
  "geometry": {"coordinates":[-82.714996,27.770792],"type":"Point"}
}