{
  "type": "Feature",
  "properties": {
    "addr:full":"5433 9th Ave Fort Myers FL 33907",
    "addr:housenumber":"5433",
    "addr:postcode":"33907",
    "addr:street":"9Th Ave",
    "iso:country":"US",
    "sg:address":"5433 9th Ave",
    "sg:city":"Fort Myers",
    "sg:classifiers":[
        {
            "category":"Professional",
            "type":"Services"
        }
    ],
    "sg:phone":"+1 239 334 6086",
    "sg:postcode":"33907",
    "sg:province":"FL",
    "sg:tags":[
        "establishment"
    ],
    "wof:name":"Ambertow Inc",
    "wof:placetype":"venue"
},
  "geometry": {"coordinates":[-81.880683,26.572752],"type":"Point"}
}