{
  "type": "Feature",
  "properties": {
    "addr:full":"26 Pecan Course Cir Ocala FL 34472",
    "addr:housenumber":"26",
    "addr:postcode":"34472",
    "addr:street":"Pecan Course Cir",
    "iso:country":"US",
    "sg:address":"26 Pecan Course Cir",
    "sg:city":"Ocala",
    "sg:classifiers":[
        {
            "category":"Building & Trades",
            "subcategory":"Construction",
            "type":"Services"
        }
    ],
    "sg:phone":"+1 352 687 0054",
    "sg:postcode":"34472",
    "sg:province":"FL",
    "sg:tags":[
        "hanging",
        "contractor"
    ],
    "wof:name":"Venturas Painting Inc",
    "wof:placetype":"venue"
},
  "geometry": {"coordinates":[-82.04194,29.140841],"type":"Point"}
}