{
  "type": "Feature",
  "properties": {
    "iso:country":"US",
    "sg:address":"554 1st Ave N",
    "sg:city":"Saint Petersburg",
    "sg:classifiers":[
        {
            "category":"Home & Garden",
            "subcategory":"Hardware",
            "type":"Retail Goods"
        }
    ],
    "sg:phone":"+1 727 526 7016",
    "sg:postcode":"33701",
    "sg:province":"FL",
    "wof:name":"True Expressions Inc",
    "wof:placetype":"venue"
},
  "geometry": {"coordinates":[-82.640985,27.772008],"type":"Point"}
}