{
  "type": "Feature",
  "properties": {
    "iso:country":"US",
    "sg:address":"1014 W 51st Pl",
    "sg:city":"Hialeah",
    "sg:classifiers":[
        {
            "category":"Building & Trades",
            "subcategory":"Construction",
            "type":"Services"
        }
    ],
    "sg:phone":"+1 305 558 2417",
    "sg:postcode":"33012",
    "sg:province":"FL",
    "sg:tags":[
        "excavation",
        "contractor"
    ],
    "wof:name":"Brick & Paver Installation Cor",
    "wof:placetype":"venue"
},
  "geometry": {"coordinates":[-80.306785,25.868936],"type":"Point"}
}