{
  "type": "Feature",
  "properties": {
    "addr:full":"3259 Progress Dr Orlando FL 32826",
    "addr:housenumber":"3259",
    "addr:postcode":"32826",
    "addr:street":"Progress Dr",
    "iso:country":"US",
    "sg:address":"3259 Progress Dr",
    "sg:city":"Orlando",
    "sg:classifiers":[
        {
            "category":"Wholesale",
            "subcategory":"Electrical",
            "type":"Manufacturing & Wholesale Goods"
        }
    ],
    "sg:phone":"+1 407 823 8110",
    "sg:postcode":"32826",
    "sg:province":"FL",
    "sg:tags":[
        "generator"
    ],
    "wof:name":"Electrodynamics Assoc Inc",
    "wof:placetype":"venue"
},
  "geometry": {"coordinates":[-81.19944599999999,28.588167],"type":"Point"}
}