{
  "type": "Feature",
  "properties": {
    "iso:country":"US",
    "sg:address":"282 Wilshire Blvd",
    "sg:city":"Casselberry",
    "sg:classifiers":[
        {
            "category":"Real Estate",
            "subcategory":"Real Estate Agent",
            "type":"Services"
        }
    ],
    "sg:phone":"+1 407 331 4173",
    "sg:postcode":"32707",
    "sg:province":"FL",
    "wof:name":"Priority Properties Orlando",
    "wof:placetype":"venue"
},
  "geometry": {"coordinates":[-81.329204,28.650596],"type":"Point"}
}