{
  "type": "Feature",
  "properties": {
    "iso:country":"US",
    "sg:address":"754 Washington Ave",
    "sg:city":"Miami Beach",
    "sg:classifiers":[
        {
            "category":"Bars & Pubs",
            "subcategory":"Sports Bar",
            "type":"Food & Drink"
        },
        {
            "category":"Restaurant",
            "type":"Food & Drink"
        }
    ],
    "sg:phone":"+1 305 397 8284",
    "sg:postcode":"33139",
    "sg:province":"FL",
    "sg:tags":[
        "traditional",
        "american"
    ],
    "wof:name":"Frankie's South Beach Hide-A-Way",
    "wof:placetype":"venue"
},
  "geometry": {"coordinates":[-80.133489,25.778029],"type":"Point"}
}