{
  "type": "Feature",
  "properties": {
    "addr:full":"3785 US Hwy 19 Alt Palm Harbor FL 34683",
    "addr:housenumber":"3785",
    "addr:postcode":"34683",
    "addr:street":"Us Hwy 19",
    "iso:country":"US",
    "sg:address":"3785 US Hwy 19 Alt",
    "sg:city":"Palm Harbor",
    "sg:classifiers":[
        {
            "category":"Manufacturing",
            "subcategory":"Toys & Sporting Goods",
            "type":"Manufacturing & Wholesale Goods"
        }
    ],
    "sg:phone":"+1 727 938 9475",
    "sg:postcode":"34683",
    "sg:province":"FL",
    "sg:tags":[
        "equipment",
        "swimming",
        "pool",
        "supply"
    ],
    "wof:name":"Sophisticated Systems Inc",
    "wof:placetype":"venue"
},
  "geometry": {"coordinates":[-82.77056899999999,28.103962],"type":"Point"}
}