{
  "type": "Feature",
  "properties": {
    "addr:full":"2975 Gulf Breeze Pkwy Gulf Breeze FL 32563",
    "addr:housenumber":"2975",
    "addr:postcode":"32563",
    "addr:street":"Gulf Breeze Pkwy",
    "iso:country":"US",
    "sg:address":"2975 Gulf Breeze Pkwy",
    "sg:city":"Gulf Breeze",
    "sg:classifiers":[
        {
            "category":"Building & Trades",
            "subcategory":"Equipment Rental",
            "type":"Services"
        }
    ],
    "sg:phone":"+1 850 932 3505",
    "sg:postcode":"32563",
    "sg:province":"FL",
    "sg:tags":[
        "yard"
    ],
    "sg:website":"www.kentsspecialevents.com",
    "wof:name":"Kent's Special Events",
    "wof:placetype":"venue"
},
  "geometry": {"coordinates":[-87.096416,30.385243],"type":"Point"}
}