{
  "type": "Feature",
  "properties": {
    "iso:country":"US",
    "sg:address":"5900 SW 73rd St",
    "sg:city":"Miami",
    "sg:classifiers":[
        {
            "category":"Banks & Credit Unions",
            "subcategory":"Bank",
            "type":"Services"
        }
    ],
    "sg:phone":"+1 305 663 9779",
    "sg:postcode":"33143",
    "sg:province":"FL",
    "sg:tags":[
        "mortgage",
        "loan",
        "broker",
        "real estate"
    ],
    "wof:name":"Suncoast Mortgage Bankers Inc",
    "wof:placetype":"venue"
},
  "geometry": {"coordinates":[-80.29033,25.703305],"type":"Point"}
}