{
  "type": "Feature",
  "properties": {
    "iso:country":"US",
    "sg:address":"1503 San Marco Dr",
    "sg:city":"Ormond Beach",
    "sg:classifiers":[
        {
            "category":"Building & Trades",
            "subcategory":"Construction",
            "type":"Services"
        }
    ],
    "sg:phone":"+1 386 672 7575",
    "sg:postcode":"32174",
    "sg:province":"FL",
    "sg:tags":[
        "painter"
    ],
    "wof:name":"S & J Painting",
    "wof:placetype":"venue"
},
  "geometry": {"coordinates":[-81.111886,29.250829],"type":"Point"}
}