{
  "type": "Feature",
  "properties": {
    "addr:full":"8105 SW 158th Pl Miami FL 33193",
    "addr:housenumber":"8105",
    "addr:postcode":"33193",
    "addr:street":"Sw 158Th Pl",
    "iso:country":"US",
    "sg:address":"8105 SW 158th Pl",
    "sg:city":"Miami",
    "sg:classifiers":[
        {
            "category":"Insurance",
            "subcategory":"Insurance Agent",
            "type":"Services"
        }
    ],
    "sg:phone":"+1 305 382 4911",
    "sg:postcode":"33193",
    "sg:province":"FL",
    "wof:name":"Raskin Financial Inc",
    "wof:placetype":"venue"
},
  "geometry": {"coordinates":[-80.449314,25.69033],"type":"Point"}
}