{
  "type": "Feature",
  "properties": {
    "iso:country":"US",
    "sg:address":"11650 NW 102nd Rd",
    "sg:city":"Medley",
    "sg:classifiers":[
        {
            "category":"Professional",
            "subcategory":"Computer Services",
            "type":"Services"
        }
    ],
    "sg:phone":"+1 305 805 2025",
    "sg:postcode":"33178",
    "sg:province":"FL",
    "sg:tags":[
        "isp",
        "provider",
        "internet"
    ],
    "wof:name":"Broadband International Inc",
    "wof:placetype":"venue"
},
  "geometry": {"coordinates":[-80.36476500000001,25.871013],"type":"Point"}
}