{
  "type": "Feature",
  "properties": {
    "iso:country":"US",
    "sg:address":"2200 NW 45 Ave",
    "sg:city":"Gainesville",
    "sg:classifiers":[
        {
            "category":"Education",
            "subcategory":"School",
            "type":"Public Place"
        }
    ],
    "sg:phone":"+1 352 955 6765",
    "sg:postcode":"32605",
    "sg:province":"FL",
    "wof:name":"Norton Elementary School",
    "wof:placetype":"venue"
},
  "geometry": {"coordinates":[-82.355031,29.695824],"type":"Point"}
}