{
  "type": "Feature",
  "properties": {
    "iso:country":"US",
    "sg:address":"1473 Ammons Rd",
    "sg:city":"Ponce De Leon",
    "sg:classifiers":[
        {
            "category":"Education",
            "subcategory":"School",
            "type":"Public Place"
        }
    ],
    "sg:phone":"+1 850 836 4296",
    "sg:postcode":"32455",
    "sg:province":"FL",
    "wof:name":"Ponce De Leon Elementary Schl",
    "wof:placetype":"venue"
},
  "geometry": {"coordinates":[-85.961676,30.740562],"type":"Point"}
}