{
  "type": "Feature",
  "properties": {
    "iso:country":"US",
    "sg:address":"7206 Coquina Ave",
    "sg:city":"Fort Pierce",
    "sg:classifiers":[
        {
            "category":"Retail",
            "subcategory":"Repair Shop",
            "type":"Services"
        }
    ],
    "sg:phone":"+1 772 595 5875",
    "sg:postcode":"34951",
    "sg:province":"FL",
    "sg:tags":[
        "related"
    ],
    "wof:name":"Terry Milam Svc Repair",
    "wof:placetype":"venue"
},
  "geometry": {"coordinates":[-80.397035,27.553994],"type":"Point"}
}