{
  "type": "Feature",
  "properties": {
    "addr:full":"5170 Collins Rd Jacksonville FL 32244",
    "addr:housenumber":"5170",
    "addr:postcode":"32244",
    "addr:street":"Collins Rd",
    "iso:country":"US",
    "sg:address":"5170 Collins Rd",
    "sg:city":"Jacksonville",
    "sg:classifiers":[
        {
            "category":"Real Estate",
            "subcategory":"Real Estate Operator",
            "type":"Services"
        }
    ],
    "sg:phone":"+1 904 264 3700",
    "sg:postcode":"32244",
    "sg:province":"FL",
    "sg:tags":[
        "building",
        "apartment"
    ],
    "wof:name":"Collins Place Apartments",
    "wof:placetype":"venue"
},
  "geometry": {"coordinates":[-81.718441,30.197201],"type":"Point"}
}