{
  "type": "Feature",
  "properties": {
    "iso:country":"US",
    "sg:address":"911 Gulf Breeze Pkwy",
    "sg:city":"Gulf Breeze",
    "sg:classifiers":[
        {
            "category":"Retail",
            "subcategory":"Laundry & Dry Cleaning",
            "type":"Services"
        }
    ],
    "sg:phone":"+1 850 478 1682",
    "sg:postcode":"32561",
    "sg:province":"FL",
    "sg:tags":[
        "cleaners",
        "plant",
        "drycleaning"
    ],
    "wof:name":"Diamond Cleaners Inc",
    "wof:placetype":"venue"
},
  "geometry": {"coordinates":[-87.162389,30.357301],"type":"Point"}
}