{
  "type": "Feature",
  "properties": {
    "addr:full":"600 Gopher Ct Jacksonville FL 32259",
    "addr:housenumber":"600",
    "addr:postcode":"32259",
    "addr:street":"Gopher Ct",
    "iso:country":"US",
    "sg:address":"600 Gopher Ct",
    "sg:city":"Jacksonville",
    "sg:classifiers":[
        {
            "category":"Wholesale",
            "subcategory":"Computers",
            "type":"Manufacturing & Wholesale Goods"
        }
    ],
    "sg:phone":"+1 904 230 2918",
    "sg:postcode":"32259",
    "sg:province":"FL",
    "wof:name":"PM Distributing Inc",
    "wof:placetype":"venue"
},
  "geometry": {"coordinates":[-81.598778,30.092785],"type":"Point"}
}