{
  "type": "Feature",
  "properties": {
    "addr:full":"751 Dunlawton Ave Daytona Beach FL 32127",
    "addr:housenumber":"751",
    "addr:postcode":"32127",
    "addr:street":"Dunlawton Ave",
    "iso:country":"US",
    "sg:address":"751 Dunlawton Ave",
    "sg:city":"Daytona Beach",
    "sg:classifiers":[
        {
            "category":"Organizations",
            "subcategory":"Religious Organization",
            "type":"Services"
        }
    ],
    "sg:phone":"+1 386 761 9129",
    "sg:postcode":"32127",
    "sg:province":"FL",
    "sg:tags":[
        "church"
    ],
    "wof:name":"All Saints Lutheran Church",
    "wof:placetype":"venue"
},
  "geometry": {"coordinates":[-80.998728,29.136428],"type":"Point"}
}