{
  "type": "Feature",
  "properties": {
    "iso:country":"US",
    "sg:address":"9452 Sun Isle Dr NE",
    "sg:city":"Saint Petersburg",
    "sg:classifiers":[
        {
            "category":"Building & Trades",
            "subcategory":"Plumbing",
            "type":"Services"
        }
    ],
    "sg:phone":"+1 727 579 8807",
    "sg:postcode":"33702",
    "sg:province":"FL",
    "sg:tags":[
        "plumbing",
        "contractor"
    ],
    "wof:name":"Fields Plumbing Service Inc",
    "wof:placetype":"venue"
},
  "geometry": {"coordinates":[-82.631339,27.856902],"type":"Point"}
}