{
  "type": "Feature",
  "properties": {
    "iso:country":"US",
    "sg:address":"1821 Richards St",
    "sg:city":"Naples",
    "sg:classifiers":[
        {
            "category":"Building & Trades",
            "subcategory":"Construction",
            "type":"Services"
        }
    ],
    "sg:phone":"+1 239 354 2680",
    "sg:postcode":"34120",
    "sg:province":"FL",
    "sg:tags":[
        "painting",
        "painter",
        "contractor"
    ],
    "wof:name":"Tim Moore Painting Inc",
    "wof:placetype":"venue"
},
  "geometry": {"coordinates":[-81.657132,26.27309],"type":"Point"}
}