{
  "type": "Feature",
  "properties": {
    "addr:full":"120 University Park Dr Winter Park FL 32792",
    "addr:housenumber":"120",
    "addr:postcode":"32792",
    "addr:street":"University Park Dr",
    "iso:country":"US",
    "sg:address":"120 University Park Dr",
    "sg:city":"Winter Park",
    "sg:classifiers":[
        {
            "category":"Professional",
            "type":"Services"
        }
    ],
    "sg:phone":"+1 407 678 5886",
    "sg:postcode":"32792",
    "sg:province":"FL",
    "sg:tags":[
        "establishment"
    ],
    "wof:name":"Fhr",
    "wof:placetype":"venue"
},
  "geometry": {"coordinates":[-81.304568,28.596543],"type":"Point"}
}