{
  "type": "Feature",
  "properties": {
    "iso:country":"US",
    "sg:address":"2445 Pembroke Rd",
    "sg:city":"Hollywood",
    "sg:classifiers":[
        {
            "category":"Food & Beverages",
            "subcategory":"Groceries & Convenience Stores",
            "type":"Retail Goods"
        }
    ],
    "sg:phone":"+1 954 927 5151",
    "sg:postcode":"33020",
    "sg:province":"FL",
    "wof:name":"A Food Mart",
    "wof:placetype":"venue"
},
  "geometry": {"coordinates":[-80.164845,25.99623],"type":"Point"}
}