{
  "type": "Feature",
  "properties": {
    "addr:full":"1300 NW 29th St Miami FL 33142",
    "addr:housenumber":"1300",
    "addr:postcode":"33142",
    "addr:street":"Nw 29Th St",
    "iso:country":"US",
    "sg:address":"1300 NW 29th St",
    "sg:city":"Miami",
    "sg:classifiers":[
        {
            "category":"Shopping",
            "subcategory":"Party Supplies",
            "type":"Retail Goods"
        },
        {
            "category":"Personal",
            "type":"Services"
        }
    ],
    "sg:phone":"+1 305 336 9932",
    "sg:postcode":"33142",
    "sg:province":"FL",
    "sg:tags":[
        "planning",
        "event"
    ],
    "sg:website":"www.partyrentalcity.com",
    "wof:name":"Party Rental City",
    "wof:placetype":"venue"
},
  "geometry": {"coordinates":[-80.21763199999999,25.803004],"type":"Point"}
}