{
  "type": "Feature",
  "properties": {
    "addr:full":"25 NE 1st St Lake Butler FL 32054",
    "addr:housenumber":"25",
    "addr:postcode":"32054",
    "addr:street":"Ne 1St St",
    "iso:country":"US",
    "sg:address":"25 NE 1st St",
    "sg:city":"Lake Butler",
    "sg:classifiers":[
        {
            "category":"Government",
            "subcategory":"Office",
            "type":"Public Place"
        }
    ],
    "sg:phone":"+1 386 496 3661",
    "sg:postcode":"32054",
    "sg:province":"FL",
    "sg:tags":[
        "federal"
    ],
    "wof:name":"US Consolidated Farm Svc Agcy",
    "wof:placetype":"venue"
},
  "geometry": {"coordinates":[-82.337518,30.023829],"type":"Point"}
}