{
  "type": "Feature",
  "properties": {
    "iso:country":"US",
    "sg:address":"1656 NW 16th Ter",
    "sg:city":"Miami",
    "sg:classifiers":[
        {
            "category":"Professional",
            "subcategory":"Lawyer & Legal Services",
            "type":"Services"
        }
    ],
    "sg:phone":"+1 786 361 9127",
    "sg:postcode":"33125",
    "sg:province":"FL",
    "sg:tags":[
        "litigation"
    ],
    "wof:name":"Miami Criminal Lawyer",
    "wof:placetype":"venue"
},
  "geometry": {"coordinates":[-80.222741,25.790502],"type":"Point"}
}