{
  "type": "Feature",
  "properties": {
    "addr:full":"845 N Beach St Daytona Beach FL 32114",
    "addr:housenumber":"845",
    "addr:postcode":"32114",
    "addr:street":"N Beach St",
    "iso:country":"US",
    "sg:address":"845 N Beach St",
    "sg:city":"Daytona Beach",
    "sg:classifiers":[
        {
            "category":"Retail",
            "subcategory":"Auto Repair",
            "type":"Services"
        }
    ],
    "sg:phone":"+1 386 252 3903",
    "sg:postcode":"32114",
    "sg:province":"FL",
    "sg:tags":[
        "automobile",
        "customizing"
    ],
    "wof:name":"Kim's Auto Svc",
    "wof:placetype":"venue"
},
  "geometry": {"coordinates":[-81.026431,29.228029],"type":"Point"}
}