{
  "type": "Feature",
  "properties": {
    "addr:full":"8126 SW 1st Manor Pompano Beach FL 33071",
    "addr:housenumber":"8126",
    "addr:postcode":"33071",
    "addr:street":"Sw 1St Manor",
    "iso:country":"US",
    "sg:address":"8126 SW 1st Manor",
    "sg:city":"Pompano Beach",
    "sg:classifiers":[
        {
            "category":"Wholesale",
            "subcategory":"Vending Machines",
            "type":"Manufacturing & Wholesale Goods"
        }
    ],
    "sg:phone":"+1 954 755 7004",
    "sg:postcode":"33071",
    "sg:province":"FL",
    "sg:tags":[
        "operator"
    ],
    "wof:name":"E & A Vending Inc",
    "wof:placetype":"venue"
},
  "geometry": {"coordinates":[-80.234668,26.230885],"type":"Point"}
}