{
  "type": "Feature",
  "properties": {
    "iso:country":"US",
    "sg:address":"220 Oakhill Ave",
    "sg:city":"Fort Walton Beach",
    "sg:classifiers":[
        {
            "category":"Building & Trades",
            "subcategory":"Construction",
            "type":"Services"
        }
    ],
    "sg:phone":"+1 850 862 1482",
    "sg:postcode":"32547",
    "sg:province":"FL",
    "sg:tags":[
        "concrete",
        "contractor"
    ],
    "wof:name":"Archie Cleo Concrete Inc",
    "wof:placetype":"venue"
},
  "geometry": {"coordinates":[-86.636517,30.436699],"type":"Point"}
}