{
  "type": "Feature",
  "properties": {
    "addr:full":"6650 NW 47th St Pompano Beach FL 33067",
    "addr:housenumber":"6650",
    "addr:postcode":"33067",
    "addr:street":"Nw 47Th St",
    "iso:country":"US",
    "sg:address":"6650 NW 47th St",
    "sg:city":"Pompano Beach",
    "sg:classifiers":[
        {
            "category":"Building & Trades",
            "subcategory":"Electrical",
            "type":"Services"
        }
    ],
    "sg:phone":"+1 954 341 1714",
    "sg:postcode":"33067",
    "sg:province":"FL",
    "sg:tags":[
        "electrical",
        "contractor"
    ],
    "wof:name":"AHern Electrical Contractors",
    "wof:placetype":"venue"
},
  "geometry": {"coordinates":[-80.217324,26.287714],"type":"Point"}
}