{
  "type": "Feature",
  "properties": {
    "addr:full":"8201 S Tamiami Trl Sarasota FL 34238",
    "addr:housenumber":"8201",
    "addr:postcode":"34238",
    "addr:street":"S Tamiami Trl",
    "iso:country":"US",
    "sg:address":"8201 S Tamiami Trl",
    "sg:city":"Sarasota",
    "sg:classifiers":[
        {
            "category":"Personal",
            "subcategory":"Beauty Salon",
            "type":"Services"
        },
        {
            "category":"Personal",
            "subcategory":"Skin Care",
            "type":"Services"
        },
        {
            "category":"Personal",
            "subcategory":"Nail Salon",
            "type":"Services"
        }
    ],
    "sg:phone":"+1 941 922 6060",
    "sg:postcode":"34238",
    "sg:province":"FL",
    "wof:name":"Nails & Facials",
    "wof:placetype":"venue"
},
  "geometry": {"coordinates":[-82.497581,27.23332],"type":"Point"}
}