{
  "type": "Feature",
  "properties": {
    "addr:full":"208 S Central Ave Flagler Beach FL 32136",
    "addr:housenumber":"208",
    "addr:postcode":"32136",
    "addr:street":"S Central Ave",
    "iso:country":"US",
    "sg:address":"208 S Central Ave",
    "sg:city":"Flagler Beach",
    "sg:classifiers":[
        {
            "category":"Shopping",
            "subcategory":"Gifts & Souvenirs",
            "type":"Retail Goods"
        }
    ],
    "sg:phone":"+1 386 439 9949",
    "sg:postcode":"32136",
    "sg:province":"FL",
    "sg:tags":[
        "shop"
    ],
    "wof:name":"Island Paradise Gifts Inc",
    "wof:placetype":"venue"
},
  "geometry": {"coordinates":[-81.128,29.47996],"type":"Point"}
}