{
  "type": "Feature",
  "properties": {
    "iso:country":"US",
    "sg:address":"5815 Makoma Dr",
    "sg:city":"Orlando",
    "sg:classifiers":[
        {
            "category":"Education",
            "subcategory":"School",
            "type":"Public Place"
        }
    ],
    "sg:phone":"+1 407 859 9511",
    "sg:postcode":"32839",
    "sg:province":"FL",
    "wof:name":"South Orlando Christian Acad",
    "wof:placetype":"venue"
},
  "geometry": {"coordinates":[-81.39515,28.474736],"type":"Point"}
}