{
  "type": "Feature",
  "properties": {
    "iso:country":"US",
    "sg:address":"6674 Hibiscus St",
    "sg:city":"Bunnell",
    "sg:classifiers":[
        {
            "category":"Building & Trades",
            "subcategory":"Construction",
            "type":"Services"
        }
    ],
    "sg:phone":"+1 386 437 9760",
    "sg:postcode":"32110",
    "sg:province":"FL",
    "sg:tags":[
        "contractor"
    ],
    "wof:name":"S S C Services Flager County",
    "wof:placetype":"venue"
},
  "geometry": {"coordinates":[-81.423946,29.443995],"type":"Point"}
}