{
  "type": "Feature",
  "properties": {
    "iso:country":"US",
    "sg:address":"2700 NW 62nd St",
    "sg:city":"Fort Lauderdale",
    "sg:classifiers":[
        {
            "category":"Wholesale",
            "subcategory":"Sporting Goods",
            "type":"Manufacturing & Wholesale Goods"
        }
    ],
    "sg:phone":"+1 954 975 8095",
    "sg:postcode":"33309",
    "sg:province":"FL",
    "wof:name":"Mike Hale Company",
    "wof:placetype":"venue"
},
  "geometry": {"coordinates":[-80.18348,26.202565],"type":"Point"}
}