{
  "type": "Feature",
  "properties": {
    "iso:country":"US",
    "sg:address":"8844 Lantana Rd",
    "sg:city":"Lake Worth",
    "sg:classifiers":[
        {
            "category":"Food & Beverages",
            "subcategory":"Groceries & Convenience Stores",
            "type":"Retail Goods"
        }
    ],
    "sg:phone":"+1 561 965 0690",
    "sg:postcode":"33467",
    "sg:province":"FL",
    "wof:name":"USA Grocers",
    "wof:placetype":"venue"
},
  "geometry": {"coordinates":[-80.188074,26.590767],"type":"Point"}
}