{
  "type": "Feature",
  "properties": {
    "iso:country":"US",
    "sg:address":"5635 Havana Hwy",
    "sg:city":"Havana",
    "sg:classifiers":[
        {
            "category":"Building & Trades",
            "subcategory":"Construction",
            "type":"Services"
        }
    ],
    "sg:phone":"+1 850 539 5574",
    "sg:postcode":"32333",
    "sg:province":"FL",
    "sg:tags":[
        "house"
    ],
    "wof:name":"J M Padgham Construction",
    "wof:placetype":"venue"
},
  "geometry": {"coordinates":[-84.496247,30.587455],"type":"Point"}
}