{
  "type": "Feature",
  "properties": {
    "iso:country":"US",
    "sg:address":"4140 NE 6th Ave",
    "sg:city":"Oakland Park",
    "sg:classifiers":[
        {
            "category":"Real Estate",
            "subcategory":"Real Estate Agent",
            "type":"Services"
        }
    ],
    "sg:phone":"+1 954 564 7008",
    "sg:postcode":"33334",
    "sg:province":"FL",
    "sg:tags":[
        "inspection"
    ],
    "wof:name":"Coverall Home Inspection",
    "wof:placetype":"venue"
},
  "geometry": {"coordinates":[-80.13863000000001,26.177351],"type":"Point"}
}