{
  "type": "Feature",
  "properties": {
    "iso:country":"US",
    "sg:address":"4314 Pablo Oaks Ct",
    "sg:city":"Jacksonville",
    "sg:classifiers":[
        {
            "category":"Real Estate",
            "subcategory":"Developer",
            "type":"Services"
        }
    ],
    "sg:phone":"+1 904 992 3700",
    "sg:postcode":"32224",
    "sg:province":"FL",
    "sg:tags":[
        "development",
        "hotel",
        "management"
    ],
    "wof:name":"Landcom Inc",
    "wof:placetype":"venue"
},
  "geometry": {"coordinates":[-81.440335,30.26756],"type":"Point"}
}