{
  "type": "Feature",
  "properties": {
    "addr:full":"1876 NW 7th St Miami FL 33125",
    "addr:housenumber":"1876",
    "addr:postcode":"33125",
    "addr:street":"Nw 7Th St",
    "iso:country":"US",
    "sg:address":"1876 NW 7th St",
    "sg:city":"Miami",
    "sg:classifiers":[
        {
            "category":"Building & Trades",
            "subcategory":"Locksmith",
            "type":"Services"
        }
    ],
    "sg:phone":"+1 305 324 8800",
    "sg:postcode":"33125",
    "sg:province":"FL",
    "sg:tags":[
        "key"
    ],
    "wof:name":"Intergrated Security Systems",
    "wof:placetype":"venue"
},
  "geometry": {"coordinates":[-80.225998,25.780001],"type":"Point"}
}