{
  "type": "Feature",
  "properties": {
    "addr:full":"8592 Potter Park Dr Sarasota FL 34238",
    "addr:housenumber":"8592",
    "addr:postcode":"34238",
    "addr:street":"Potter Park Dr",
    "iso:country":"US",
    "sg:address":"8592 Potter Park Dr",
    "sg:city":"Sarasota",
    "sg:classifiers":[
        {
            "category":"Banks & Credit Unions",
            "subcategory":"Financial Services",
            "type":"Services"
        },
        {
            "category":"Banks & Credit Unions",
            "subcategory":"Bank",
            "type":"Services"
        }
    ],
    "sg:phone":"+1 941 926 9336",
    "sg:postcode":"34238",
    "sg:province":"FL",
    "sg:tags":[
        "trust",
        "company",
        "management"
    ],
    "wof:name":"Caldwell Trust",
    "wof:placetype":"venue"
},
  "geometry": {"coordinates":[-82.48929200000001,27.232405],"type":"Point"}
}