{
  "type": "Feature",
  "properties": {
    "iso:country":"US",
    "sg:address":"6603 Norwood Ave",
    "sg:city":"Jacksonville",
    "sg:classifiers":[
        {
            "category":"Retail",
            "subcategory":"Laundry & Dry Cleaning",
            "type":"Services"
        }
    ],
    "sg:phone":"+1 904 765 9511",
    "sg:postcode":"32208",
    "sg:province":"FL",
    "sg:tags":[
        "cleaners"
    ],
    "wof:name":"Morris Professional Dry Clnng",
    "wof:placetype":"venue"
},
  "geometry": {"coordinates":[-81.669355,30.378938],"type":"Point"}
}