{
  "type": "Feature",
  "properties": {
    "addr:full":"1111 Oakfield Dr Brandon FL 33511",
    "addr:housenumber":"1111",
    "addr:postcode":"33511",
    "addr:street":"Oakfield Dr",
    "iso:country":"US",
    "sg:address":"1111 Oakfield Dr",
    "sg:city":"Brandon",
    "sg:classifiers":[
        {
            "category":"Health Services",
            "subcategory":"Doctor",
            "type":"Services"
        }
    ],
    "sg:phone":"+1 813 643 0101",
    "sg:postcode":"33511",
    "sg:province":"FL",
    "sg:tags":[
        "physician",
        "surgeon",
        "medical"
    ],
    "wof:name":"Rainbow Pediatrics",
    "wof:placetype":"venue"
},
  "geometry": {"coordinates":[-82.299102,27.934029],"type":"Point"}
}