{
  "type": "Feature",
  "properties": {
    "iso:country":"US",
    "sg:address":"1014 Pennsylvania Ave",
    "sg:city":"Clearwater",
    "sg:classifiers":[
        {
            "category":"Organizations",
            "subcategory":"Non-profit Organization",
            "type":"Services"
        }
    ],
    "sg:phone":"+1 727 447 4461",
    "sg:postcode":"33755",
    "sg:province":"FL",
    "sg:tags":[
        "development",
        "community"
    ],
    "wof:name":"Mount Carmel Holdings",
    "wof:placetype":"venue"
},
  "geometry": {"coordinates":[-82.79324699999999,27.976722],"type":"Point"}
}