{
  "type": "Feature",
  "properties": {
    "iso:country":"US",
    "sg:address":"308 W Berckman St",
    "sg:city":"Fruitland Park",
    "sg:classifiers":[
        {
            "category":"Building & Trades",
            "subcategory":"Cleaning & Sanitation",
            "type":"Services"
        }
    ],
    "sg:phone":"+1 352 314 9070",
    "sg:postcode":"34731",
    "sg:province":"FL",
    "sg:tags":[
        "butler",
        "maid"
    ],
    "wof:name":"Daisy Maids",
    "wof:placetype":"venue"
},
  "geometry": {"coordinates":[-81.911869,28.857938],"type":"Point"}
}