{
  "type": "Feature",
  "properties": {
    "iso:country":"US",
    "sg:address":"422 W Waters Ave",
    "sg:city":"Tampa",
    "sg:classifiers":[
        {
            "category":"Shopping",
            "type":"Retail Goods"
        }
    ],
    "sg:phone":"+1 813 931 3713",
    "sg:postcode":"33604",
    "sg:province":"FL",
    "sg:tags":[
        "cosmetic",
        "perfume"
    ],
    "wof:name":"All Nations Beauty Supply",
    "wof:placetype":"venue"
},
  "geometry": {"coordinates":[-82.46404200000001,28.025272],"type":"Point"}
}