{
  "type": "Feature",
  "properties": {
    "iso:country":"US",
    "sg:address":"357 8th Ave N",
    "sg:city":"Saint Petersburg",
    "sg:classifiers":[
        {
            "category":"Banks & Credit Unions",
            "subcategory":"Financial Services",
            "type":"Services"
        }
    ],
    "sg:phone":"+1 727 866 6635",
    "sg:postcode":"33715",
    "sg:province":"FL",
    "sg:tags":[
        "investment",
        "closed"
    ],
    "wof:name":"Monte Cristo Capital Ventures",
    "wof:placetype":"venue"
},
  "geometry": {"coordinates":[-82.729046,27.690458],"type":"Point"}
}