{
  "type": "Feature",
  "properties": {
    "addr:full":"1801 Coral Way Miami FL 33145",
    "addr:housenumber":"1801",
    "addr:postcode":"33145",
    "addr:street":"Coral Way",
    "iso:country":"US",
    "sg:address":"1801 Coral Way",
    "sg:city":"Miami",
    "sg:classifiers":[
        {
            "category":"Manufacturing",
            "subcategory":"Petroleum Products",
            "type":"Manufacturing & Wholesale Goods"
        }
    ],
    "sg:phone":"+1 305 858 8652",
    "sg:postcode":"33145",
    "sg:province":"FL",
    "wof:name":"Global Trade International Group",
    "wof:placetype":"venue"
},
  "geometry": {"coordinates":[-80.224014,25.750875],"type":"Point"}
}