{
  "type": "Feature",
  "properties": {
    "iso:country":"US",
    "sg:address":"937 Greenbriar Dr",
    "sg:city":"Boynton Beach",
    "sg:classifiers":[
        {
            "category":"Professional",
            "type":"Services"
        }
    ],
    "sg:phone":"+1 561 734 4157",
    "sg:postcode":"33435",
    "sg:province":"FL",
    "wof:name":"Laingco Inc",
    "wof:placetype":"venue"
},
  "geometry": {"coordinates":[-80.05766199999999,26.520106],"type":"Point"}
}