{
  "type": "Feature",
  "properties": {
    "addr:full":"174 W Comstock Ave Winter Park FL 32789",
    "addr:housenumber":"174",
    "addr:postcode":"32789",
    "addr:street":"W Comstock Ave",
    "iso:country":"US",
    "sg:address":"174 W Comstock Ave",
    "sg:city":"Winter Park",
    "sg:classifiers":[
        {
            "category":"Professional",
            "subcategory":"Lawyer & Legal Services",
            "type":"Services"
        }
    ],
    "sg:phone":"+1 407 702 6635",
    "sg:postcode":"32789",
    "sg:province":"FL",
    "wof:name":"Chad Walters",
    "wof:placetype":"venue"
},
  "geometry": {"coordinates":[-81.351534,28.594063],"type":"Point"}
}