{
  "type": "Feature",
  "properties": {
    "iso:country":"US",
    "sg:address":"4922 NE 2nd Pl",
    "sg:city":"Ocala",
    "sg:classifiers":[
        {
            "category":"Professional",
            "subcategory":"Lawyer & Legal Services",
            "type":"Services"
        }
    ],
    "sg:phone":"+1 352 694 3530",
    "sg:postcode":"34470",
    "sg:province":"FL",
    "sg:tags":[
        "attorney",
        "criminal",
        "law"
    ],
    "wof:name":"Mcdaniel Fred",
    "wof:placetype":"venue"
},
  "geometry": {"coordinates":[-82.066557,29.189409],"type":"Point"}
}