{
  "type": "Feature",
  "properties": {
    "addr:full":"205 Anastasia Blvd St Augustine FL 32080",
    "addr:housenumber":"205",
    "addr:postcode":"32080",
    "addr:street":"Anastasia Blvd St",
    "iso:country":"US",
    "sg:address":"205 Anastasia Blvd",
    "sg:city":"St Augustine",
    "sg:classifiers":[
        {
            "category":"Restaurant",
            "type":"Food & Drink"
        }
    ],
    "sg:phone":"+1 904 829 6974",
    "sg:postcode":"32080",
    "sg:province":"FL",
    "sg:tags":[
        "eating"
    ],
    "wof:name":"O'Steen's Restaurant",
    "wof:placetype":"venue"
},
  "geometry": {"coordinates":[-81.301129,29.891868],"type":"Point"}
}