{
  "type": "Feature",
  "properties": {
    "addr:full":"8691 SW 102nd St Miami FL 33156",
    "addr:housenumber":"8691",
    "addr:postcode":"33156",
    "addr:street":"Sw 102Nd St",
    "iso:country":"US",
    "sg:address":"8691 SW 102nd St",
    "sg:city":"Miami",
    "sg:classifiers":[
        {
            "category":"Manufacturing",
            "subcategory":"Building Materials",
            "type":"Manufacturing & Wholesale Goods"
        }
    ],
    "sg:phone":"+1 305 884 4332",
    "sg:postcode":"33156",
    "sg:province":"FL",
    "sg:tags":[
        "mfg",
        "wood",
        "kitchen",
        "cabinet"
    ],
    "wof:name":"Miami Dade Cabinets Inc",
    "wof:placetype":"venue"
},
  "geometry": {"coordinates":[-80.33246,25.675431],"type":"Point"}
}