{
  "type": "Feature",
  "properties": {
    "iso:country":"US",
    "sg:address":"353 Airport Pulling Rd S",
    "sg:city":"Naples",
    "sg:classifiers":[
        {
            "category":"Building & Trades",
            "subcategory":"Construction",
            "type":"Services"
        },
        {
            "category":"Home & Garden",
            "subcategory":"Furniture",
            "type":"Retail Goods"
        }
    ],
    "sg:phone":"+1 239 643 2998",
    "sg:postcode":"34104",
    "sg:province":"FL",
    "sg:tags":[
        "cabinet",
        "work",
        "maker",
        "custom"
    ],
    "wof:name":"Mastercraft Cabinets Inc",
    "wof:placetype":"venue"
},
  "geometry": {"coordinates":[-81.76661900000001,26.148099],"type":"Point"}
}