{
  "type": "Feature",
  "properties": {
    "addr:full":"2530 NW 111th St Miami FL 33167",
    "addr:housenumber":"2530",
    "addr:postcode":"33167",
    "addr:street":"Nw 111Th St",
    "iso:country":"US",
    "sg:address":"2530 NW 111th St",
    "sg:city":"Miami",
    "sg:classifiers":[
        {
            "category":"Building & Trades",
            "subcategory":"Construction",
            "type":"Services"
        }
    ],
    "sg:phone":"+1 305 685 3069",
    "sg:postcode":"33167",
    "sg:province":"FL",
    "sg:tags":[
        "fence",
        "contractor"
    ],
    "wof:name":"Warren Fence Co Inc",
    "wof:placetype":"venue"
},
  "geometry": {"coordinates":[-80.24251599999999,25.8754],"type":"Point"}
}