{
  "type": "Feature",
  "properties": {
    "iso:country":"US",
    "sg:address":"3000 SW 3rd Ave",
    "sg:city":"Miami",
    "sg:classifiers":[
        {
            "category":"Professional",
            "subcategory":"Advertising",
            "type":"Services"
        }
    ],
    "sg:phone":"+1 305 856 4567",
    "sg:postcode":"33129",
    "sg:province":"FL",
    "sg:tags":[
        "agency"
    ],
    "wof:name":"Concept Cafe Advertising",
    "wof:placetype":"venue"
},
  "geometry": {"coordinates":[-80.21252200000001,25.752436],"type":"Point"}
}