{
  "type": "Feature",
  "properties": {
    "iso:country":"US",
    "sg:address":"9542 State Hwy 13",
    "sg:city":"Jacksonville",
    "sg:classifiers":[
        {
            "category":"Autos & Motor Vehicles",
            "subcategory":"Fuel & Gas Station",
            "type":"Retail Goods"
        }
    ],
    "sg:phone":"+1 904 731 0511",
    "sg:postcode":"32257",
    "sg:province":"FL",
    "sg:tags":[
        "station",
        "gasoline"
    ],
    "wof:name":"Gate Petroleum Company",
    "wof:placetype":"venue"
},
  "geometry": {"coordinates":[-81.617223,30.204227],"type":"Point"}
}