{
  "type": "Feature",
  "properties": {
    "iso:country":"US",
    "sg:address":"3860 N Federal Hwy",
    "sg:city":"Delray Beach",
    "sg:classifiers":[
        {
            "category":"Wholesale",
            "subcategory":"Auto Parts",
            "type":"Manufacturing & Wholesale Goods"
        }
    ],
    "sg:phone":"+1 561 243 2499",
    "sg:postcode":"33483",
    "sg:province":"FL",
    "sg:tags":[
        "supply"
    ],
    "wof:name":"Aluminum Toolboxes & Trailers",
    "wof:placetype":"venue"
},
  "geometry": {"coordinates":[-80.06051100000001,26.500522],"type":"Point"}
}