{
  "type": "Feature",
  "properties": {
    "iso:country":"US",
    "sg:address":"1210 Lafayette St",
    "sg:city":"Cape Coral",
    "sg:classifiers":[
        {
            "category":"Professional",
            "type":"Services"
        }
    ],
    "sg:phone":"+1 239 541 1477",
    "sg:postcode":"33904",
    "sg:province":"FL",
    "sg:tags":[
        "establishment"
    ],
    "wof:name":"Finderz Keeperz",
    "wof:placetype":"venue"
},
  "geometry": {"coordinates":[-81.94574900000001,26.561572],"type":"Point"}
}