{
  "type": "Feature",
  "properties": {
    "addr:full":"109 Windmill Way Longwood FL 32750",
    "addr:housenumber":"109",
    "addr:postcode":"32750",
    "addr:street":"Windmill Way",
    "iso:country":"US",
    "sg:address":"109 Windmill Way",
    "sg:city":"Longwood",
    "sg:classifiers":[
        {
            "category":"Military Area",
            "type":"Public Place"
        }
    ],
    "sg:phone":"+1 407 590 6151",
    "sg:postcode":"32750",
    "sg:province":"FL",
    "sg:tags":[
        "force",
        "armed",
        "recruiting"
    ],
    "wof:name":"The Guard-Us Group",
    "wof:placetype":"venue"
},
  "geometry": {"coordinates":[-81.37821099999999,28.704288],"type":"Point"}
}