{
  "type": "Feature",
  "properties": {
    "addr:full":"3669 Prospect Ave Riviera Beach FL 33404",
    "addr:housenumber":"3669",
    "addr:postcode":"33404",
    "addr:street":"Prospect Ave",
    "iso:country":"US",
    "sg:address":"3669 Prospect Ave",
    "sg:city":"Riviera Beach",
    "sg:classifiers":[
        {
            "category":"Retail",
            "subcategory":"Auto Repair",
            "type":"Services"
        }
    ],
    "sg:phone":"+1 561 841 5232",
    "sg:postcode":"33404",
    "sg:province":"FL",
    "sg:tags":[
        "body",
        "automobile",
        "painting"
    ],
    "wof:name":"Picasso Frame & Body",
    "wof:placetype":"venue"
},
  "geometry": {"coordinates":[-80.09315599999999,26.790435],"type":"Point"}
}