{
  "type": "Feature",
  "properties": {
    "addr:full":"3561 Davie Blvd Fort Lauderdale FL 33312",
    "addr:housenumber":"3561",
    "addr:postcode":"33312",
    "addr:street":"Davie Blvd",
    "iso:country":"US",
    "sg:address":"3561 Davie Blvd",
    "sg:city":"Fort Lauderdale",
    "sg:classifiers":[
        {
            "category":"Cinema",
            "subcategory":"Movie Rental",
            "type":"Entertainment"
        }
    ],
    "sg:phone":"+1 954 316 3851",
    "sg:postcode":"33312",
    "sg:province":"FL",
    "sg:tags":[
        "leasing",
        "video",
        "disc",
        "tape"
    ],
    "wof:name":"Techniques Video Store",
    "wof:placetype":"venue"
},
  "geometry": {"coordinates":[-80.19419000000001,26.104549],"type":"Point"}
}