{
  "type": "Feature",
  "properties": {
    "iso:country":"US",
    "sg:address":"4137 Wake Ave",
    "sg:city":"Sarasota",
    "sg:classifiers":[
        {
            "category":"Building & Trades",
            "subcategory":"Plumbing",
            "type":"Services"
        }
    ],
    "sg:phone":"+1 941 377 0112",
    "sg:postcode":"34241",
    "sg:province":"FL",
    "sg:tags":[
        "plumbing",
        "contractor"
    ],
    "wof:name":"Underhill Plumbing Inc",
    "wof:placetype":"venue"
},
  "geometry": {"coordinates":[-82.423907,27.294249],"type":"Point"}
}