{
  "type": "Feature",
  "properties": {
    "addr:full":"726 Park Ave West Palm Beach FL 33403",
    "addr:housenumber":"726",
    "addr:postcode":"33403",
    "addr:street":"Park Ave",
    "iso:country":"US",
    "sg:address":"726 Park Ave",
    "sg:city":"West Palm Beach",
    "sg:classifiers":[
        {
            "category":"Retail",
            "subcategory":"Repair Shop",
            "type":"Services"
        }
    ],
    "sg:phone":"+1 561 622 0000",
    "sg:postcode":"33403",
    "sg:province":"FL",
    "sg:tags":[
        "equipment",
        "video"
    ],
    "wof:name":"Video Services",
    "wof:placetype":"venue"
},
  "geometry": {"coordinates":[-80.06805900000001,26.798592],"type":"Point"}
}