{
  "type": "Feature",
  "properties": {
    "addr:full":"2101 SW Best St Port St Lucie FL 34984",
    "addr:housenumber":"2101",
    "addr:postcode":"34984",
    "addr:street":"Sw Best St;St",
    "iso:country":"US",
    "sg:address":"2101 SW Best St",
    "sg:city":"Port St Lucie",
    "sg:classifiers":[
        {
            "category":"Building & Trades",
            "subcategory":"Construction",
            "type":"Services"
        }
    ],
    "sg:phone":"+1 772 240 0854",
    "sg:postcode":"34984",
    "sg:province":"FL",
    "sg:tags":[
        "designer",
        "dealer",
        "pool",
        "swimming"
    ],
    "wof:name":"Absolute Best Pool Svc",
    "wof:placetype":"venue"
},
  "geometry": {"coordinates":[-80.34461899999999,27.27844],"type":"Point"}
}