{
  "type": "Feature",
  "properties": {
    "addr:full":"1124 NW 11th St Boynton Beach FL 33426",
    "addr:housenumber":"1124",
    "addr:postcode":"33426",
    "addr:street":"Nw 11Th St",
    "iso:country":"US",
    "sg:address":"1124 NW 11th St",
    "sg:city":"Boynton Beach",
    "sg:classifiers":[
        {
            "category":"Building & Trades",
            "subcategory":"Construction",
            "type":"Services"
        }
    ],
    "sg:phone":"+1 561 736 8161",
    "sg:postcode":"33426",
    "sg:province":"FL",
    "sg:tags":[
        "contractor"
    ],
    "wof:name":"Aljemar Tile & Stone In",
    "wof:placetype":"venue"
},
  "geometry": {"coordinates":[-80.084557,26.537167],"type":"Point"}
}