{
  "type": "Feature",
  "properties": {
    "iso:country":"US",
    "sg:address":"13538 Village Park Dr",
    "sg:city":"Orlando",
    "sg:classifiers":[
        {
            "category":"Home & Garden",
            "subcategory":"Kitchen Supply",
            "type":"Retail Goods"
        }
    ],
    "sg:phone":"+1 407 286 0396",
    "sg:postcode":"32837",
    "sg:province":"FL",
    "sg:tags":[
        "utensil",
        "cookware"
    ],
    "wof:name":"Rena Ware International",
    "wof:placetype":"venue"
},
  "geometry": {"coordinates":[-81.427082,28.368699],"type":"Point"}
}