{
  "type": "Feature",
  "properties": {
    "addr:full":"15470 S Roundtable Rd Fort Lauderdale FL 33331",
    "addr:housenumber":"15470",
    "addr:postcode":"33331",
    "addr:street":"S Roundtable Rd",
    "iso:country":"US",
    "sg:address":"15470 S Roundtable Rd",
    "sg:city":"Fort Lauderdale",
    "sg:classifiers":[
        {
            "category":"Wholesale",
            "subcategory":"Chemicals & Plastics",
            "type":"Manufacturing & Wholesale Goods"
        }
    ],
    "sg:phone":"+1 954 252 9445",
    "sg:postcode":"33331",
    "sg:province":"FL",
    "sg:tags":[
        "industrial"
    ],
    "wof:name":"Norchem Industrial Corp",
    "wof:placetype":"venue"
},
  "geometry": {"coordinates":[-80.35602900000001,26.057105],"type":"Point"}
}