{
  "type": "Feature",
  "properties": {
    "addr:full":"3804 Sydney Rd Plant City FL 33566",
    "addr:housenumber":"3804",
    "addr:postcode":"33566",
    "addr:street":"Sydney Rd",
    "iso:country":"US",
    "sg:address":"3804 Sydney Rd",
    "sg:city":"Plant City",
    "sg:classifiers":[
        {
            "category":"Wholesale",
            "subcategory":"Auto Parts",
            "type":"Manufacturing & Wholesale Goods"
        }
    ],
    "sg:phone":"+1 813 659 2948",
    "sg:postcode":"33566",
    "sg:province":"FL",
    "sg:tags":[
        "spring",
        "supply",
        "mfg"
    ],
    "wof:name":"Mtec International Ltd",
    "wof:placetype":"venue"
},
  "geometry": {"coordinates":[-82.161781,27.99177],"type":"Point"}
}