{
  "type": "Feature",
  "properties": {
    "iso:country":"US",
    "sg:address":"5901 Benjamin Center Dr",
    "sg:city":"Tampa",
    "sg:classifiers":[
        {
            "category":"Building & Trades",
            "subcategory":"Equipment Rental",
            "type":"Services"
        }
    ],
    "sg:phone":"+1 813 261 6900",
    "sg:postcode":"33634",
    "sg:province":"FL",
    "sg:tags":[
        "com",
        "parts",
        "electronic"
    ],
    "wof:name":"Total Audio Visual Services",
    "wof:placetype":"venue"
},
  "geometry": {"coordinates":[-82.53934599999999,28.006481],"type":"Point"}
}