{
  "type": "Feature",
  "properties": {
    "addr:full":"2057 NE 160th St North Miami Bch FL 33162",
    "addr:housenumber":"2057",
    "addr:postcode":"33162",
    "addr:street":"Ne 160Th St",
    "iso:country":"US",
    "sg:address":"2057 NE 160th St",
    "sg:city":"North Miami Bch",
    "sg:classifiers":[
        {
            "category":"Building & Trades",
            "subcategory":"Construction",
            "type":"Services"
        }
    ],
    "sg:phone":"+1 305 956 2929",
    "sg:postcode":"33162",
    "sg:province":"FL",
    "sg:tags":[
        "remodeling",
        "closet"
    ],
    "wof:name":"Organizers Unlimted",
    "wof:placetype":"venue"
},
  "geometry": {"coordinates":[-80.15920300000001,25.923375],"type":"Point"}
}