{
  "type": "Feature",
  "properties": {
    "iso:country":"US",
    "sg:address":"3633 Little Rd",
    "sg:city":"Trinity",
    "sg:classifiers":[
        {
            "category":"Health Services",
            "subcategory":"Doctor",
            "type":"Services"
        }
    ],
    "sg:phone":"+1 727 372 5547",
    "sg:postcode":"34655",
    "sg:province":"FL",
    "sg:tags":[
        "physician",
        "surgeon"
    ],
    "wof:name":"Angel M Rosario MD",
    "wof:placetype":"venue"
},
  "geometry": {"coordinates":[-82.666039,28.211648],"type":"Point"}
}