{
  "type": "Feature",
  "properties": {
    "iso:country":"US",
    "sg:address":"4057 NE 7th Ave",
    "sg:city":"Fort Lauderdale",
    "sg:classifiers":[
        {
            "category":"Wholesale",
            "subcategory":"Electrical",
            "type":"Manufacturing & Wholesale Goods"
        }
    ],
    "sg:phone":"+1 954 566 8118",
    "sg:postcode":"33334",
    "sg:province":"FL",
    "sg:tags":[
        "equipment",
        "electric",
        "supply"
    ],
    "wof:name":"Consolidated Electrical Distrs",
    "wof:placetype":"venue"
},
  "geometry": {"coordinates":[-80.137777,26.17787],"type":"Point"}
}