{
  "type": "Feature",
  "properties": {
    "iso:country":"US",
    "sg:address":"111 N Orange Ave",
    "sg:city":"Orlando",
    "sg:classifiers":[
        {
            "category":"Professional",
            "subcategory":"Lawyer & Legal Services",
            "type":"Services"
        }
    ],
    "sg:phone":"+1 407 481 1184",
    "sg:postcode":"32801",
    "sg:province":"FL",
    "sg:tags":[
        "attorney"
    ],
    "wof:name":"Paul Shoucair",
    "wof:placetype":"venue"
},
  "geometry": {"coordinates":[-81.37899899999999,28.544507],"type":"Point"}
}