{
  "type": "Feature",
  "properties": {
    "iso:country":"US",
    "sg:address":"948 SW 3rd St",
    "sg:city":"Miami",
    "sg:classifiers":[
        {
            "category":"Manufacturing",
            "subcategory":"Buildings",
            "type":"Manufacturing & Wholesale Goods"
        },
        {
            "category":"Building & Trades",
            "subcategory":"Construction",
            "type":"Services"
        }
    ],
    "sg:phone":"+1 305 548 0471",
    "sg:postcode":"33130",
    "sg:province":"FL",
    "sg:tags":[
        "home",
        "builder",
        "contractor"
    ],
    "wof:name":"Gilco Homes",
    "wof:placetype":"venue"
},
  "geometry": {"coordinates":[-80.210302,25.770711],"type":"Point"}
}