{
  "type": "Feature",
  "properties": {
    "iso:country":"US",
    "sg:address":"2070 NW 79th Ave",
    "sg:city":"Miami",
    "sg:classifiers":[
        {
            "category":"Freight",
            "type":"Transportation"
        }
    ],
    "sg:phone":"+1 305 592 0905",
    "sg:postcode":"33122",
    "sg:province":"FL",
    "sg:tags":[
        "arrangement"
    ],
    "wof:name":"Sdv USA Inc",
    "wof:placetype":"venue"
},
  "geometry": {"coordinates":[-80.324184,25.791659],"type":"Point"}
}