{
  "type": "Feature",
  "properties": {
    "addr:full":"4243 SW 55th Ave Fort Lauderdale FL 33314",
    "addr:housenumber":"4243",
    "addr:postcode":"33314",
    "addr:street":"Sw 55Th Ave",
    "iso:country":"US",
    "sg:address":"4243 SW 55th Ave",
    "sg:city":"Fort Lauderdale",
    "sg:classifiers":[
        {
            "category":"Professional",
            "subcategory":"Computer Services",
            "type":"Services"
        }
    ],
    "sg:phone":"+1 954 558 5903",
    "sg:postcode":"33314",
    "sg:province":"FL",
    "sg:tags":[
        "repair",
        "maintenance"
    ],
    "wof:name":"Tormarbu Techinical Support",
    "wof:placetype":"venue"
},
  "geometry": {"coordinates":[-80.22055899999999,26.068726],"type":"Point"}
}