{
  "type": "Feature",
  "properties": {
    "iso:country":"US",
    "sg:address":"27241 Bay Landing Dr",
    "sg:city":"Bonita Springs",
    "sg:classifiers":[
        {
            "category":"Real Estate",
            "subcategory":"Real Estate Agent",
            "type":"Services"
        }
    ],
    "sg:phone":"+1 239 949 9122",
    "sg:postcode":"34135",
    "sg:province":"FL",
    "sg:website":"www.carlabontenannualrentals.com",
    "wof:name":"Carla Bonten Rentals",
    "wof:placetype":"venue"
},
  "geometry": {"coordinates":[-81.806991,26.343477],"type":"Point"}
}