{
  "type": "Feature",
  "properties": {
    "addr:full":"4061 Drifting Sand Trl Destin FL 32541",
    "addr:housenumber":"4061",
    "addr:postcode":"32541",
    "addr:street":"Drifting Sand Trl",
    "iso:country":"US",
    "sg:address":"4061 Drifting Sand Trl",
    "sg:city":"Destin",
    "sg:classifiers":[
        {
            "category":"Building & Trades",
            "subcategory":"Construction",
            "type":"Services"
        }
    ],
    "sg:phone":"+1 850 837 0059",
    "sg:postcode":"32541",
    "sg:province":"FL",
    "sg:tags":[
        "house"
    ],
    "wof:name":"SL Builders Inc",
    "wof:placetype":"venue"
},
  "geometry": {"coordinates":[-86.45888100000001,30.393161],"type":"Point"}
}