{
  "type": "Feature",
  "properties": {
    "addr:full":"2979 Oak Tree Ln Tallahassee FL 32310",
    "addr:housenumber":"2979",
    "addr:postcode":"32310",
    "addr:street":"Oak Tree Ln",
    "iso:country":"US",
    "sg:address":"2979 Oak Tree Ln",
    "sg:city":"Tallahassee",
    "sg:classifiers":[
        {
            "category":"Building & Trades",
            "subcategory":"Construction",
            "type":"Services"
        }
    ],
    "sg:phone":"+1 850 574 6317",
    "sg:postcode":"32310",
    "sg:province":"FL",
    "sg:tags":[
        "wallcoverings-installation",
        "wallpaper",
        "painting",
        "contractor"
    ],
    "wof:name":"American Pride Painting Inc",
    "wof:placetype":"venue"
},
  "geometry": {"coordinates":[-84.537689,30.420031],"type":"Point"}
}