{
  "type": "Feature",
  "properties": {
    "iso:country":"US",
    "sg:address":"3639 Cortez Rd W Ste 200",
    "sg:city":"Bradenton",
    "sg:classifiers":[
        {
            "category":"Real Estate",
            "subcategory":"Real Estate Agent",
            "type":"Services"
        }
    ],
    "sg:phone":"+1 941 727 2800",
    "sg:postcode":"34210",
    "sg:province":"FL",
    "sg:website":"http://www.earlcowdrey.com",
    "wof:name":"Wagner Realty",
    "wof:placetype":"venue"
},
  "geometry": {"coordinates":[-82.599031,27.462385],"type":"Point"}
}