{
  "type": "Feature",
  "properties": {
    "addr:full":"223 Taylor St Punta Gorda FL 33950",
    "addr:housenumber":"223",
    "addr:postcode":"33950",
    "addr:street":"Taylor St",
    "iso:country":"US",
    "sg:address":"223 Taylor St",
    "sg:city":"Punta Gorda",
    "sg:classifiers":[
        {
            "category":"Professional",
            "subcategory":"Lawyer & Legal Services",
            "type":"Services"
        }
    ],
    "sg:phone":"+1 941 473 1700",
    "sg:postcode":"33950",
    "sg:province":"FL",
    "wof:name":"Melanie D High",
    "wof:placetype":"venue"
},
  "geometry": {"coordinates":[-82.05103099999999,26.934971],"type":"Point"}
}