{
  "type": "Feature",
  "properties": {
    "iso:country":"US",
    "sg:address":"3700 Rca Blvd",
    "sg:city":"Palm Beach Gdns",
    "sg:classifiers":[
        {
            "category":"Utilities",
            "subcategory":"Telephone",
            "type":"Services"
        }
    ],
    "sg:phone":"+1 561 799 1530",
    "sg:postcode":"33410",
    "sg:province":"FL",
    "sg:tags":[
        "telecommunication"
    ],
    "wof:name":"Supra Telecom",
    "wof:placetype":"venue"
},
  "geometry": {"coordinates":[-80.090993,26.837816],"type":"Point"}
}