{
  "type": "Feature",
  "properties": {
    "iso:country":"US",
    "sg:address":"6233 27th Ave N",
    "sg:city":"St Petersburg",
    "sg:classifiers":[
        {
            "category":"Building & Trades",
            "subcategory":"Construction",
            "type":"Services"
        }
    ],
    "sg:phone":"+1 727 576 6222",
    "sg:postcode":"33710",
    "sg:province":"FL",
    "sg:tags":[
        "plastering",
        "contractor"
    ],
    "wof:name":"A Plus Plastering",
    "wof:placetype":"venue"
},
  "geometry": {"coordinates":[-82.722499,27.796163],"type":"Point"}
}