{
  "type": "Feature",
  "properties": {
    "addr:full":"534 Cocoa Ln Orlando FL 32804",
    "addr:housenumber":"534",
    "addr:postcode":"32804",
    "addr:street":"Cocoa Ln",
    "iso:country":"US",
    "sg:address":"534 Cocoa Ln",
    "sg:city":"Orlando",
    "sg:classifiers":[
        {
            "category":"Health Services",
            "subcategory":"Health Practitioner",
            "type":"Services"
        }
    ],
    "sg:phone":"+1 407 835 3361",
    "sg:postcode":"32804",
    "sg:province":"FL",
    "sg:tags":[
        "nutritionist"
    ],
    "wof:name":"Jl Fitness",
    "wof:placetype":"venue"
},
  "geometry": {"coordinates":[-81.38614,28.588203],"type":"Point"}
}