{
  "type": "Feature",
  "properties": {
    "iso:country":"US",
    "sg:address":"2750 SW 112th Ave",
    "sg:city":"Miami",
    "sg:classifiers":[
        {
            "category":"Organizations",
            "subcategory":"Religious Organization",
            "type":"Services"
        }
    ],
    "sg:phone":"+1 305 559 7662",
    "sg:postcode":"33165",
    "sg:province":"FL",
    "sg:website":"www.iglesiabautistawestchester.com",
    "wof:name":"Iglesia Bautista De Westchester",
    "wof:placetype":"venue"
},
  "geometry": {"coordinates":[-80.37599899999999,25.743601],"type":"Point"}
}