{
  "type": "Feature",
  "properties": {
    "addr:full":"3270 Suntree Blvd Melbourne FL 32940",
    "addr:housenumber":"3270",
    "addr:postcode":"32940",
    "addr:street":"Suntree Blvd",
    "iso:country":"US",
    "sg:address":"3270 Suntree Blvd",
    "sg:city":"Melbourne",
    "sg:classifiers":[
        {
            "category":"Professional",
            "subcategory":"Management & Consulting",
            "type":"Services"
        }
    ],
    "sg:phone":"+1 321 255 3885",
    "sg:postcode":"32940",
    "sg:province":"FL",
    "sg:tags":[
        "consultant"
    ],
    "wof:name":"Prial Sheldon Consulting",
    "wof:placetype":"venue"
},
  "geometry": {"coordinates":[-80.678399,28.227919],"type":"Point"}
}