{
  "type": "Feature",
  "properties": {
    "iso:country":"US",
    "sg:address":"921 Indian River Ave",
    "sg:city":"Titusville",
    "sg:classifiers":[
        {
            "category":"Shopping",
            "subcategory":"Gifts & Souvenirs",
            "type":"Retail Goods"
        }
    ],
    "sg:phone":"+1 321 267 0827",
    "sg:postcode":"32780",
    "sg:province":"FL",
    "sg:tags":[
        "shop"
    ],
    "wof:name":"Indian River Dry Goods Co",
    "wof:placetype":"venue"
},
  "geometry": {"coordinates":[-80.80667800000001,28.606205],"type":"Point"}
}