{
  "type": "Feature",
  "properties": {
    "addr:full":"7845 Ellis Rd Melbourne FL 32904",
    "addr:housenumber":"7845",
    "addr:postcode":"32904",
    "addr:street":"Ellis Rd",
    "iso:country":"US",
    "sg:address":"7845 Ellis Rd",
    "sg:city":"Melbourne",
    "sg:classifiers":[
        {
            "category":"Professional",
            "type":"Services"
        }
    ],
    "sg:phone":"+1 321 956 3242",
    "sg:postcode":"32904",
    "sg:province":"FL",
    "sg:tags":[
        "establishment"
    ],
    "wof:name":"Telemedical Procedures Co",
    "wof:placetype":"venue"
},
  "geometry": {"coordinates":[-80.685068,28.099127],"type":"Point"}
}