{
  "type": "Feature",
  "properties": {
    "addr:full":"13330 Sorrento Rd Pensacola FL 32507",
    "addr:housenumber":"13330",
    "addr:postcode":"32507",
    "addr:street":"Sorrento Rd",
    "iso:country":"US",
    "sg:address":"13330 Sorrento Rd",
    "sg:city":"Pensacola",
    "sg:classifiers":[
        {
            "category":"Banks & Credit Unions",
            "subcategory":"Bank",
            "type":"Services"
        }
    ],
    "sg:phone":"+1 850 492 3405",
    "sg:postcode":"32507",
    "sg:province":"FL",
    "sg:tags":[
        "state",
        "commercial"
    ],
    "wof:name":"Warrington Bank",
    "wof:placetype":"venue"
},
  "geometry": {"coordinates":[-87.419032,30.322232],"type":"Point"}
}