{
  "type": "Feature",
  "properties": {
    "addr:full":"1200 5th Ave S Naples FL 34102",
    "addr:housenumber":"1200",
    "addr:postcode":"34102",
    "addr:street":"5Th Ave S",
    "iso:country":"US",
    "sg:address":"1200 5th Ave S",
    "sg:city":"Naples",
    "sg:classifiers":[
        {
            "category":"Restaurant",
            "type":"Food & Drink"
        }
    ],
    "sg:phone":"+1 239 261 1811",
    "sg:postcode":"34102",
    "sg:province":"FL",
    "sg:tags":[
        "eating"
    ],
    "wof:name":"Bills Pier On Fifth",
    "wof:placetype":"venue"
},
  "geometry": {"coordinates":[-81.78811399999999,26.140975],"type":"Point"}
}