{
  "type": "Feature",
  "properties": {
    "addr:full":"849 E Sugarland Hwy Clewiston FL 33440",
    "addr:housenumber":"849",
    "addr:postcode":"33440",
    "addr:street":"E Sugarland Hwy",
    "iso:country":"US",
    "sg:address":"849 E Sugarland Hwy",
    "sg:city":"Clewiston",
    "sg:classifiers":[
        {
            "category":"Autos & Motor Vehicles",
            "subcategory":"Auto Supplies",
            "type":"Retail Goods"
        }
    ],
    "sg:phone":"+1 863 983 4002",
    "sg:postcode":"33440",
    "sg:province":"FL",
    "wof:name":"Orosco Enterprises",
    "wof:placetype":"venue"
},
  "geometry": {"coordinates":[-80.91987899999999,26.754324],"type":"Point"}
}