{
  "type": "Feature",
  "properties": {
    "iso:country":"US",
    "sg:address":"4019 State Hwy 87",
    "sg:city":"Gulf Breeze",
    "sg:classifiers":[
        {
            "category":"Building & Trades",
            "subcategory":"Construction",
            "type":"Services"
        }
    ],
    "sg:phone":"+1 850 939 2180",
    "sg:postcode":"32566",
    "sg:province":"FL",
    "sg:tags":[
        "hanging",
        "contractor"
    ],
    "wof:name":"Cary Dederer Painting",
    "wof:placetype":"venue"
},
  "geometry": {"coordinates":[-86.910008,30.461807],"type":"Point"}
}