{
  "type": "Feature",
  "properties": {
    "iso:country":"US",
    "sg:address":"812 White Oak Ct",
    "sg:city":"Panama City",
    "sg:classifiers":[
        {
            "category":"Restaurant",
            "type":"Food & Drink"
        }
    ],
    "sg:phone":"+1 850 249 0303",
    "sg:postcode":"32408",
    "sg:province":"FL",
    "sg:tags":[
        "franchise",
        "pizza"
    ],
    "wof:name":"De Best Pizza Inc",
    "wof:placetype":"venue"
},
  "geometry": {"coordinates":[-85.77064,30.165603],"type":"Point"}
}