{
  "type": "Feature",
  "properties": {
    "addr:full":"2486 Ridgetop Ct Orange Park FL 32065",
    "addr:housenumber":"2486",
    "addr:postcode":"32065",
    "addr:street":"Ridgetop Ct",
    "iso:country":"US",
    "sg:address":"2486 Ridgetop Ct",
    "sg:city":"Orange Park",
    "sg:classifiers":[
        {
            "category":"Freight",
            "type":"Transportation"
        },
        {
            "category":"Professional",
            "subcategory":"Business Services",
            "type":"Services"
        }
    ],
    "sg:phone":"+1 904 276 8208",
    "sg:postcode":"32065",
    "sg:province":"FL",
    "sg:tags":[
        "delivery",
        "courier"
    ],
    "wof:name":"Bass Express Delivery Inc",
    "wof:placetype":"venue"
},
  "geometry": {"coordinates":[-81.771379,30.1511],"type":"Point"}
}