{
  "type": "Feature",
  "properties": {
    "addr:full":"17000 NE Morgan Tucker Rd Altha FL 32421",
    "addr:housenumber":"17000",
    "addr:postcode":"32421",
    "addr:street":"Ne Morgan Tucker Rd",
    "iso:country":"US",
    "sg:address":"17000 NE Morgan Tucker Rd",
    "sg:city":"Altha",
    "sg:classifiers":[
        {
            "category":"Building & Trades",
            "subcategory":"Plumbing",
            "type":"Services"
        }
    ],
    "sg:phone":"+1 850 674 3572",
    "sg:postcode":"32421",
    "sg:province":"FL",
    "sg:tags":[
        "plumber",
        "industrial",
        "contractors-commercial"
    ],
    "wof:name":"Plum Haven Plumbing",
    "wof:placetype":"venue"
},
  "geometry": {"coordinates":[-85.107339,30.501822],"type":"Point"}
}