{
  "type": "Feature",
  "properties": {
    "iso:country":"US",
    "sg:address":"2828 Casa Aloma Way Ste 700",
    "sg:city":"Winter Park",
    "sg:classifiers":[
        {
            "category":"Health Services",
            "subcategory":"Dentist",
            "type":"Services"
        }
    ],
    "sg:phone":"+1 407 678 4000",
    "sg:postcode":"32792",
    "sg:province":"FL",
    "wof:name":"Bilancione Carl D DMD",
    "wof:placetype":"venue"
},
  "geometry": {"coordinates":[-81.3116,28.613701],"type":"Point"}
}