{
  "type": "Feature",
  "properties": {
    "addr:full":"7879 W Commercial Blvd Tamarac FL 33351",
    "addr:housenumber":"7879",
    "addr:postcode":"33351",
    "addr:street":"W Commercial Blvd",
    "iso:country":"US",
    "sg:address":"7879 W Commercial Blvd",
    "sg:city":"Tamarac",
    "sg:classifiers":[
        {
            "category":"Banks & Credit Unions",
            "subcategory":"Bank",
            "type":"Services"
        },
        {
            "category":"Banks & Credit Unions",
            "subcategory":"Financial Services",
            "type":"Services"
        }
    ],
    "sg:phone":"+1 954 721 2206",
    "sg:postcode":"33351",
    "sg:province":"FL",
    "sg:tags":[
        "financing",
        "loan"
    ],
    "sg:website":"http://www.SunTrust.com",
    "wof:name":"SunTrust Bank - West Tamarac",
    "wof:placetype":"venue"
},
  "geometry": {"coordinates":[-80.25584000000001,26.193861],"type":"Point"}
}