{
  "type": "Feature",
  "properties": {
    "addr:full":"1549 Sunset Dr Coral Gables FL 33143",
    "addr:housenumber":"1549",
    "addr:postcode":"33143",
    "addr:street":"Sunset Dr",
    "iso:country":"US",
    "sg:address":"1549 Sunset Dr",
    "sg:city":"Coral Gables",
    "sg:classifiers":[
        {
            "category":"Building & Trades",
            "subcategory":"Locksmith",
            "type":"Services"
        }
    ],
    "sg:phone":"+1 786 228 5418",
    "sg:postcode":"33143",
    "sg:province":"FL",
    "sg:tags":[
        "key"
    ],
    "wof:name":"Always Affective Available Emergency Locksmith In Coral Gables",
    "wof:placetype":"venue"
},
  "geometry": {"coordinates":[-80.284105,25.704423],"type":"Point"}
}