{
  "type": "Feature",
  "properties": {
    "iso:country":"US",
    "sg:address":"4832 N Orange Blossom Trl A",
    "sg:city":"Orlando",
    "sg:classifiers":[
        {
            "category":"Professional",
            "type":"Services"
        },
        {
            "category":"Home & Garden",
            "subcategory":"Building Materials",
            "type":"Retail Goods"
        },
        {
            "category":"Building & Trades",
            "subcategory":"Construction",
            "type":"Services"
        },
        {
            "category":"Train Station",
            "subcategory":"Rail",
            "type":"Transportation"
        },
        {
            "category":"Sports & Exercise",
            "subcategory":"Swimming Pool",
            "type":"Entertainment"
        }
    ],
    "sg:phone":"+1 407 298 0096",
    "sg:postcode":"32810",
    "sg:province":"FL",
    "sg:tags":[
        "repair",
        "fence",
        "tubs-repair",
        "rails",
        "contractor",
        "hot",
        "railing",
        "spa",
        "accessory",
        "stairway",
        "fence-sales"
    ],
    "wof:name":"Coastal Craftsmen Aluminum Inc",
    "wof:placetype":"venue"
},
  "geometry": {"coordinates":[-81.418897,28.601604],"type":"Point"}
}