{
  "type": "Feature",
  "properties": {
    "iso:country":"US",
    "sg:address":"300 Biscayne Blvd",
    "sg:city":"Miami",
    "sg:classifiers":[
        {
            "category":"Health Services",
            "subcategory":"Doctor",
            "type":"Services"
        }
    ],
    "sg:phone":"+1 305 371 9880",
    "sg:postcode":"33132",
    "sg:province":"FL",
    "sg:tags":[
        "psychiatrist"
    ],
    "wof:name":"Caycedo Jorge H MD",
    "wof:placetype":"venue"
},
  "geometry": {"coordinates":[-80.188202,25.7773],"type":"Point"}
}