{
  "type": "Feature",
  "properties": {
    "iso:country":"US",
    "sg:address":"901 S Collins St",
    "sg:city":"Plant City",
    "sg:classifiers":[
        {
            "category":"Building & Trades",
            "subcategory":"Construction",
            "type":"Services"
        }
    ],
    "sg:phone":"+1 813 759 8780",
    "sg:postcode":"33563",
    "sg:province":"FL",
    "sg:tags":[
        "shed",
        "utility"
    ],
    "wof:name":"Wailer's Sheds & Garage Door",
    "wof:placetype":"venue"
},
  "geometry": {"coordinates":[-82.121298,28.006558],"type":"Point"}
}