{
  "type": "Feature",
  "properties": {
    "iso:country":"US",
    "sg:address":"796 NW 29th St",
    "sg:city":"Miami",
    "sg:classifiers":[
        {
            "category":"Place Of Worship",
            "subcategory":"Church",
            "type":"Public Place"
        },
        {
            "category":"Organizations",
            "subcategory":"Religious Organization",
            "type":"Services"
        }
    ],
    "sg:phone":"+1 305 638 3000",
    "sg:postcode":"33127",
    "sg:province":"FL",
    "sg:tags":[
        "churches-presbyterian"
    ],
    "wof:name":"Iglesia Presbiteriana Pan Americana",
    "wof:placetype":"venue"
},
  "geometry": {"coordinates":[-80.209503,25.8036],"type":"Point"}
}