{
  "type": "Feature",
  "properties": {
    "addr:full":"19781 SW 84th Ave Miami FL 33189",
    "addr:housenumber":"19781",
    "addr:postcode":"33189",
    "addr:street":"Sw 84Th Ave",
    "iso:country":"US",
    "sg:address":"19781 SW 84th Ave",
    "sg:city":"Miami",
    "sg:classifiers":[
        {
            "category":"Building & Trades",
            "subcategory":"Pest Control",
            "type":"Services"
        }
    ],
    "sg:phone":"+1 305 233 2673",
    "sg:postcode":"33189",
    "sg:province":"FL",
    "wof:name":"All Management Solutions",
    "wof:placetype":"venue"
},
  "geometry": {"coordinates":[-80.32633800000001,25.58237],"type":"Point"}
}