{
  "type": "Feature",
  "properties": {
    "iso:country":"US",
    "sg:address":"6902 W Hillsborough Ave",
    "sg:city":"Tampa",
    "sg:classifiers":[
        {
            "category":"Travel",
            "subcategory":"Hotels & Motels",
            "type":"Entertainment"
        }
    ],
    "sg:phone":"+1 800 424 6423",
    "sg:postcode":"33634",
    "sg:province":"FL",
    "sg:website":"http://www.suburbanhotels.com/hotel-tampa-florida-FL969?promo=yplocal",
    "wof:name":"Suburban Extended Stay Hotel Airport Tampa",
    "wof:placetype":"venue"
},
  "geometry": {"coordinates":[-82.55662700000001,27.99645],"type":"Point"}
}