{
  "type": "Feature",
  "properties": {
    "addr:full":"575 41st St S St Petersburg FL 33711",
    "addr:housenumber":"575",
    "addr:postcode":"33711",
    "addr:street":"41St St S",
    "iso:country":"US",
    "sg:address":"575 41st St S",
    "sg:city":"St Petersburg",
    "sg:classifiers":[
        {
            "category":"Education",
            "subcategory":"School",
            "type":"Public Place"
        }
    ],
    "sg:phone":"+1 727 893 2132",
    "sg:postcode":"33711",
    "sg:province":"FL",
    "sg:website":"www.pinellas.k12.fl.us",
    "wof:name":"Fairmont Park Elementary Schl",
    "wof:placetype":"venue"
},
  "geometry": {"coordinates":[-82.688952,27.765089],"type":"Point"}
}