{
  "type": "Feature",
  "properties": {
    "addr:full":"2601 Broadway Riviera Beach FL 33404",
    "addr:housenumber":"2601",
    "addr:postcode":"33404",
    "addr:street":"Broadway",
    "iso:country":"US",
    "sg:address":"2601 Broadway",
    "sg:city":"Riviera Beach",
    "sg:classifiers":[
        {
            "category":"Professional",
            "subcategory":"Accounting & Tax Preparation",
            "type":"Services"
        }
    ],
    "sg:phone":"+1 561 845 8335",
    "sg:postcode":"33404",
    "sg:province":"FL",
    "sg:tags":[
        "return",
        "filing"
    ],
    "wof:name":"Express Tax Svc",
    "wof:placetype":"venue"
},
  "geometry": {"coordinates":[-80.05478599999999,26.784155],"type":"Point"}
}