{
  "type": "Feature",
  "properties": {
    "iso:country":"US",
    "sg:address":"1701 Harcourt Dr",
    "sg:city":"Leesburg",
    "sg:classifiers":[
        {
            "category":"Building & Trades",
            "subcategory":"Cleaning & Sanitation",
            "type":"Services"
        }
    ],
    "sg:phone":"+1 352 787 6667",
    "sg:postcode":"34748",
    "sg:province":"FL",
    "sg:tags":[
        "maintenance"
    ],
    "wof:name":"D&L Communications",
    "wof:placetype":"venue"
},
  "geometry": {"coordinates":[-81.89232199999999,28.803998],"type":"Point"}
}