{
  "type": "Feature",
  "properties": {
    "iso:country":"US",
    "sg:address":"2800 W Commercial Blvd",
    "sg:city":"Fort Lauderdale",
    "sg:classifiers":[
        {
            "category":"Real Estate",
            "subcategory":"Real Estate Agent",
            "type":"Services"
        },
        {
            "category":"Recreation",
            "type":"Entertainment"
        }
    ],
    "sg:phone":"+1 954 484 9798",
    "sg:postcode":"33309",
    "sg:province":"FL",
    "sg:tags":[
        "authorities",
        "housing"
    ],
    "wof:name":"Tamarac Lakes South Club",
    "wof:placetype":"venue"
},
  "geometry": {"coordinates":[-80.18065,26.187334],"type":"Point"}
}