{
  "type": "Feature",
  "properties": {
    "iso:country":"US",
    "sg:address":"255 W Venice Ave",
    "sg:city":"Venice",
    "sg:classifiers":[
        {
            "category":"Shopping",
            "subcategory":"Gifts & Souvenirs",
            "type":"Retail Goods"
        }
    ],
    "sg:phone":"+1 941 488 3510",
    "sg:postcode":"34285",
    "sg:province":"FL",
    "sg:tags":[
        "shop",
        "novelty",
        "jewelry",
        "costume"
    ],
    "wof:name":"Sea Pleasures & Treasures",
    "wof:placetype":"venue"
},
  "geometry": {"coordinates":[-82.446707,27.099802],"type":"Point"}
}