{
  "type": "Feature",
  "properties": {
    "addr:full":"18328 Powell Rd Brooksville FL 34604",
    "addr:housenumber":"18328",
    "addr:postcode":"34604",
    "addr:street":"Powell Rd",
    "iso:country":"US",
    "sg:address":"18328 Powell Rd",
    "sg:city":"Brooksville",
    "sg:classifiers":[
        {
            "category":"Building & Trades",
            "subcategory":"Construction",
            "type":"Services"
        }
    ],
    "sg:phone":"+1 352 799 1623",
    "sg:postcode":"34604",
    "sg:province":"FL",
    "sg:tags":[
        "contractor"
    ],
    "wof:name":"David Ledbetters Fencing",
    "wof:placetype":"venue"
},
  "geometry": {"coordinates":[-82.425793,28.49197],"type":"Point"}
}