{
  "type": "Feature",
  "properties": {
    "iso:country":"US",
    "sg:address":"305 Alcazar Ave Ste 5",
    "sg:city":"Coral Gables",
    "sg:classifiers":[
        {
            "category":"Shopping",
            "subcategory":"Florist",
            "type":"Retail Goods"
        }
    ],
    "sg:phone":"+1 305 443 0121",
    "sg:postcode":"33134",
    "sg:province":"FL",
    "sg:website":"www.greenospot.com",
    "wof:name":"Green Spot",
    "wof:placetype":"venue"
},
  "geometry": {"coordinates":[-80.26097900000001,25.752848],"type":"Point"}
}