{
  "type": "Feature",
  "properties": {
    "addr:full":"4890 W Kennedy Blvd Tampa FL 33609",
    "addr:housenumber":"4890",
    "addr:postcode":"33609",
    "addr:street":"W Kennedy Blvd",
    "iso:country":"US",
    "sg:address":"4890 W Kennedy Blvd",
    "sg:city":"Tampa",
    "sg:classifiers":[
        {
            "category":"Utilities",
            "subcategory":"Telephone",
            "type":"Services"
        }
    ],
    "sg:phone":"+1 813 261 7030",
    "sg:postcode":"33609",
    "sg:province":"FL",
    "sg:tags":[
        "communications"
    ],
    "wof:name":"MCI",
    "wof:placetype":"venue"
},
  "geometry": {"coordinates":[-82.524652,27.944759],"type":"Point"}
}