{
  "type": "Feature",
  "properties": {
    "addr:full":"5028 SW 91 Dr Gainesville FL 32608",
    "addr:housenumber":"5028",
    "addr:postcode":"32608",
    "addr:street":"Sw 91 Dr",
    "iso:country":"US",
    "sg:address":"5028 SW 91 Dr",
    "sg:city":"Gainesville",
    "sg:classifiers":[
        {
            "category":"Building & Trades",
            "subcategory":"Pest Control",
            "type":"Services"
        }
    ],
    "sg:phone":"+1 352 371 2511",
    "sg:postcode":"32608",
    "sg:province":"FL",
    "wof:name":"Mosquito Net",
    "wof:placetype":"venue"
},
  "geometry": {"coordinates":[-82.43805999999999,29.606364],"type":"Point"}
}