{
  "type": "Feature",
  "properties": {
    "addr:full":"7416 Community Ct Hudson FL 34667",
    "addr:housenumber":"7416",
    "addr:postcode":"34667",
    "addr:street":"Community Ct",
    "iso:country":"US",
    "sg:address":"7416 Community Ct",
    "sg:city":"Hudson",
    "sg:classifiers":[
        {
            "category":"Professional",
            "subcategory":"Lawyer & Legal Services",
            "type":"Services"
        }
    ],
    "sg:phone":"+1 727 819 2256",
    "sg:postcode":"34667",
    "sg:province":"FL",
    "sg:tags":[
        "attorney"
    ],
    "wof:name":"Malcolm R Smith Attorney",
    "wof:placetype":"venue"
},
  "geometry": {"coordinates":[-82.691836,28.357975],"type":"Point"}
}