{
  "type": "Feature",
  "properties": {
    "addr:full":"5632 Land O Lakes Blvd Land O Lakes FL 34639",
    "addr:housenumber":"5632",
    "addr:postcode":"34639",
    "addr:street":"Land O Lakes Blvd Land",
    "iso:country":"US",
    "sg:address":"5632 Land O Lakes Blvd",
    "sg:city":"Land O Lakes",
    "sg:classifiers":[
        {
            "category":"Retail",
            "subcategory":"Auto Repair",
            "type":"Services"
        }
    ],
    "sg:phone":"+1 813 996 7079",
    "sg:postcode":"34639",
    "sg:province":"FL",
    "sg:tags":[
        "repairing",
        "automobile"
    ],
    "wof:name":"Lakes Auto",
    "wof:placetype":"venue"
},
  "geometry": {"coordinates":[-82.460059,28.239061],"type":"Point"}
}