{
  "type": "Feature",
  "properties": {
    "iso:country":"US",
    "sg:address":"2350 W 66 Ln",
    "sg:city":"Hialeah",
    "sg:classifiers":[
        {
            "category":"Airport",
            "type":"Transportation"
        }
    ],
    "sg:phone":"+1 305 698 7226",
    "sg:postcode":"33016",
    "sg:province":"FL",
    "wof:name":"United Survey",
    "wof:placetype":"venue"
},
  "geometry": {"coordinates":[-80.330732,25.882841],"type":"Point"}
}