{
  "type": "Feature",
  "properties": {
    "addr:full":"437 E Monroe St Jacksonville FL 32202",
    "addr:housenumber":"437",
    "addr:postcode":"32202",
    "addr:street":"E Monroe St",
    "iso:country":"US",
    "sg:address":"437 E Monroe St",
    "sg:city":"Jacksonville",
    "sg:classifiers":[
        {
            "category":"Real Estate",
            "subcategory":"Real Estate Agent",
            "type":"Services"
        }
    ],
    "sg:phone":"+1 904 358 6793",
    "sg:postcode":"32202",
    "sg:province":"FL",
    "sg:tags":[
        "management"
    ],
    "wof:name":"Duke Properties Inc",
    "wof:placetype":"venue"
},
  "geometry": {"coordinates":[-81.651355,30.32727],"type":"Point"}
}