{
  "type": "Feature",
  "properties": {
    "addr:full":"953 Sunshine Ln Altamonte Spgs FL 32714",
    "addr:housenumber":"953",
    "addr:postcode":"32714",
    "addr:street":"Sunshine Ln;Spgs",
    "iso:country":"US",
    "sg:address":"953 Sunshine Ln",
    "sg:city":"Altamonte Spgs",
    "sg:classifiers":[
        {
            "category":"Building & Trades",
            "subcategory":"Construction",
            "type":"Services"
        }
    ],
    "sg:phone":"+1 352 735 5008",
    "sg:postcode":"32714",
    "sg:province":"FL",
    "sg:tags":[
        "boring",
        "drilling",
        "contractor"
    ],
    "wof:name":"Hearn Drilling Svc Inc",
    "wof:placetype":"venue"
},
  "geometry": {"coordinates":[-81.420593,28.655555],"type":"Point"}
}