{
  "type": "Feature",
  "properties": {
    "addr:full":"8520 Government Dr New Port Richey FL 34654",
    "addr:housenumber":"8520",
    "addr:postcode":"34654",
    "addr:street":"Government Dr",
    "iso:country":"US",
    "sg:address":"8520 Government Dr",
    "sg:city":"New Port Richey",
    "sg:classifiers":[
        {
            "category":"Professional",
            "subcategory":"Lawyer & Legal Services",
            "type":"Services"
        }
    ],
    "sg:phone":"+1 727 847 2083",
    "sg:postcode":"34654",
    "sg:province":"FL",
    "sg:tags":[
        "attorney"
    ],
    "wof:name":"Jay W Moreland",
    "wof:placetype":"venue"
},
  "geometry": {"coordinates":[-82.67057,28.266592],"type":"Point"}
}