{
  "type": "Feature",
  "properties": {
    "iso:country":"US",
    "sg:address":"1534 Bloomingdale Ave",
    "sg:city":"Valrico",
    "sg:classifiers":[
        {
            "category":"Restaurant",
            "type":"Food & Drink"
        }
    ],
    "sg:phone":"+1 813 685 8012",
    "sg:postcode":"33596",
    "sg:province":"FL",
    "wof:name":"Domino's Pizza",
    "wof:placetype":"venue"
},
  "geometry": {"coordinates":[-82.25112,27.893663],"type":"Point"}
}