{
  "type": "Feature",
  "properties": {
    "iso:country":"US",
    "sg:address":"3435 10th St N",
    "sg:city":"Naples",
    "sg:classifiers":[
        {
            "category":"Professional",
            "subcategory":"Accounting & Tax Preparation",
            "type":"Services"
        }
    ],
    "sg:phone":"+1 239 649 1188",
    "sg:postcode":"34103",
    "sg:province":"FL",
    "sg:tags":[
        "accountant"
    ],
    "wof:name":"Gary D Hoffbauer Co",
    "wof:placetype":"venue"
},
  "geometry": {"coordinates":[-81.798497,26.187397],"type":"Point"}
}