{
  "type": "Feature",
  "properties": {
    "addr:full":"429 2nd St NW Winter Haven FL 33881",
    "addr:housenumber":"429",
    "addr:postcode":"33881",
    "addr:street":"2Nd St Nw",
    "iso:country":"US",
    "sg:address":"429 2nd St NW",
    "sg:city":"Winter Haven",
    "sg:classifiers":[
        {
            "category":"Health Services",
            "subcategory":"Doctor",
            "type":"Services"
        }
    ],
    "sg:phone":"+1 863 294 7558",
    "sg:postcode":"33881",
    "sg:province":"FL",
    "sg:tags":[
        "medical"
    ],
    "wof:name":"Nelson A Warner MD PA",
    "wof:placetype":"venue"
},
  "geometry": {"coordinates":[-81.72894700000001,28.026132],"type":"Point"}
}