{
  "type": "Feature",
  "properties": {
    "iso:country":"US",
    "sg:address":"10510 Bet Mark Ln",
    "sg:city":"Pensacola",
    "sg:classifiers":[
        {
            "category":"Recreation",
            "type":"Entertainment"
        }
    ],
    "sg:phone":"+1 850 474 6402",
    "sg:postcode":"32534",
    "sg:province":"FL",
    "sg:tags":[
        "parks"
    ],
    "wof:name":"Brosnaham Softball Complex",
    "wof:placetype":"venue"
},
  "geometry": {"coordinates":[-87.27457699999999,30.549844],"type":"Point"}
}