{
  "type": "Feature",
  "properties": {
    "iso:country":"US",
    "sg:address":"1925 Mizell Ave",
    "sg:city":"Winter Park",
    "sg:classifiers":[
        {
            "category":"Health Services",
            "subcategory":"Doctor",
            "type":"Services"
        }
    ],
    "sg:phone":"+1 407 644 3866",
    "sg:postcode":"32792",
    "sg:province":"FL",
    "sg:tags":[
        "physician",
        "surgeon"
    ],
    "wof:name":"Zahra G Promes MD",
    "wof:placetype":"venue"
},
  "geometry": {"coordinates":[-81.32619,28.595876],"type":"Point"}
}