{
  "type": "Feature",
  "properties": {
    "iso:country":"US",
    "sg:address":"4128 SW 5th Pl",
    "sg:city":"Cape Coral",
    "sg:classifiers":[
        {
            "category":"Wholesale",
            "subcategory":"Medical Equipment & Supplies",
            "type":"Manufacturing & Wholesale Goods"
        }
    ],
    "sg:phone":"+1 239 541 1860",
    "sg:postcode":"33914",
    "sg:province":"FL",
    "sg:tags":[
        "distribution",
        "sales"
    ],
    "wof:name":"Futurecare",
    "wof:placetype":"venue"
},
  "geometry": {"coordinates":[-81.986127,26.574143],"type":"Point"}
}