{
  "type": "Feature",
  "properties": {
    "iso:country":"US",
    "sg:address":"24 Bayou Dr",
    "sg:city":"Fort Walton Bch",
    "sg:classifiers":[
        {
            "category":"Social Services",
            "type":"Services"
        }
    ],
    "sg:phone":"+1 850 864 4242",
    "sg:postcode":"32547",
    "sg:province":"FL",
    "sg:tags":[
        "crisis",
        "intervention"
    ],
    "wof:name":"Children In Crisis Inc",
    "wof:placetype":"venue"
},
  "geometry": {"coordinates":[-86.610304,30.449007],"type":"Point"}
}