{
  "type": "Feature",
  "properties": {
    "iso:country":"US",
    "sg:address":"1610 SW 3rd Ave",
    "sg:city":"Okeechobee",
    "sg:classifiers":[
        {
            "category":"Professional",
            "subcategory":"Business Services",
            "type":"Services"
        }
    ],
    "sg:phone":"+1 863 467 8091",
    "sg:postcode":"34974",
    "sg:province":"FL",
    "wof:name":"Watford Auctioneer Co",
    "wof:placetype":"venue"
},
  "geometry": {"coordinates":[-80.83227599999999,27.228714],"type":"Point"}
}