{
  "type": "Feature",
  "properties": {
    "iso:country":"US",
    "sg:address":"7539 NW 52nd St",
    "sg:city":"Miami",
    "sg:classifiers":[
        {
            "category":"Wholesale",
            "subcategory":"Medical Equipment & Supplies",
            "type":"Manufacturing & Wholesale Goods"
        }
    ],
    "sg:phone":"+1 305 591 8888",
    "sg:postcode":"33166",
    "sg:province":"FL",
    "wof:name":"Imaging Specialists Group",
    "wof:placetype":"venue"
},
  "geometry": {"coordinates":[-80.319715,25.820833],"type":"Point"}
}