{
  "type": "Feature",
  "properties": {
    "iso:country":"US",
    "sg:address":"5309 Blanding Blvd",
    "sg:city":"Jacksonville",
    "sg:classifiers":[
        {
            "category":"Insurance",
            "subcategory":"Insurance Agent",
            "type":"Services"
        }
    ],
    "sg:phone":"+1 904 778 3600",
    "sg:postcode":"32210",
    "sg:province":"FL",
    "wof:name":"Bob Brooks Independent Auto",
    "wof:placetype":"venue"
},
  "geometry": {"coordinates":[-81.742987,30.248493],"type":"Point"}
}