{
  "type": "Feature",
  "properties": {
    "iso:country":"US",
    "sg:address":"2461 US Hwy 1 S",
    "sg:city":"St Augustine",
    "sg:classifiers":[
        {
            "category":"Building & Trades",
            "subcategory":"Equipment Rental",
            "type":"Services"
        }
    ],
    "sg:phone":"+1 904 794 2222",
    "sg:postcode":"32086",
    "sg:province":"FL",
    "sg:tags":[
        "own",
        "yard",
        "offer",
        "operates",
        "to",
        "rent",
        "which",
        "home",
        "electronic",
        "store"
    ],
    "wof:name":"Rent-A-Center",
    "wof:placetype":"venue"
},
  "geometry": {"coordinates":[-81.32281999999999,29.852171],"type":"Point"}
}