{
  "type": "Feature",
  "properties": {
    "iso:country":"US",
    "sg:address":"160 Redstone Ave W",
    "sg:city":"Crestview",
    "sg:classifiers":[
        {
            "category":"Manufacturing",
            "subcategory":"Glass & Minerals",
            "type":"Manufacturing & Wholesale Goods"
        },
        {
            "category":"Retail",
            "subcategory":"Auto Repair",
            "type":"Services"
        }
    ],
    "sg:phone":"+1 850 689 4567",
    "sg:postcode":"32536",
    "sg:province":"FL",
    "sg:tags":[
        "plate",
        "window",
        "windshield",
        "glass-auto"
    ],
    "sg:website":"http://www.lloydsglass.com",
    "wof:name":"Lloyds Auto Glass",
    "wof:placetype":"venue"
},
  "geometry": {"coordinates":[-86.56776499999999,30.73708],"type":"Point"}
}