{
  "type": "Feature",
  "properties": {
    "addr:full":"808 Virginia Dr Orlando FL 32803",
    "addr:housenumber":"808",
    "addr:postcode":"32803",
    "addr:street":"Virginia Dr",
    "iso:country":"US",
    "sg:address":"808 Virginia Dr",
    "sg:city":"Orlando",
    "sg:classifiers":[
        {
            "category":"Banks & Credit Unions",
            "subcategory":"Bank",
            "type":"Services"
        }
    ],
    "sg:phone":"+1 407 894 5565",
    "sg:postcode":"32803",
    "sg:province":"FL",
    "sg:tags":[
        "other",
        "plan",
        "card"
    ],
    "wof:name":"Retriever Payment Systems",
    "wof:placetype":"venue"
},
  "geometry": {"coordinates":[-81.366687,28.563989],"type":"Point"}
}