{
  "type": "Feature",
  "properties": {
    "iso:country":"US",
    "sg:address":"7030 W Palmetto Park Rd",
    "sg:city":"Boca Raton",
    "sg:classifiers":[
        {
            "category":"Restaurant",
            "type":"Food & Drink"
        }
    ],
    "sg:menulink":"http://www.allmenus.com/fl/boca-raton/187012-mcdonalds/menu/",
    "sg:phone":"+1 561 392 6768",
    "sg:postcode":"33433",
    "sg:province":"FL",
    "sg:tags":[
        "burger",
        "american"
    ],
    "wof:name":"McDonald's",
    "wof:placetype":"venue"
},
  "geometry": {"coordinates":[-80.155644,26.349593],"type":"Point"}
}