{
  "type": "Feature",
  "properties": {
    "addr:full":"3796 W Hillsboro Blvd Deerfield Beach FL 33442",
    "addr:housenumber":"3796",
    "addr:postcode":"33442",
    "addr:street":"W Hillsboro Blvd",
    "iso:country":"US",
    "sg:address":"3796 W Hillsboro Blvd",
    "sg:city":"Deerfield Beach",
    "sg:classifiers":[
        {
            "category":"Restaurant",
            "type":"Food & Drink"
        }
    ],
    "sg:menulink":"http://www.allmenus.com/fl/deerfield-beach/122693-quiznos-sub/menu/",
    "sg:phone":"+1 954 571 8686",
    "sg:postcode":"33442",
    "sg:province":"FL",
    "sg:tags":[
        "wrap",
        "american",
        "sandwich"
    ],
    "wof:name":"Quiznos Sub",
    "wof:placetype":"venue"
},
  "geometry": {"coordinates":[-80.155849,26.317738],"type":"Point"}
}