{
  "type": "Feature",
  "properties": {
    "addr:full":"424 Production Blvd Naples FL 34104",
    "addr:housenumber":"424",
    "addr:postcode":"34104",
    "addr:street":"Production Blvd",
    "iso:country":"US",
    "sg:address":"424 Production Blvd",
    "sg:city":"Naples",
    "sg:classifiers":[
        {
            "category":"Manufacturing",
            "subcategory":"Signs",
            "type":"Manufacturing & Wholesale Goods"
        }
    ],
    "sg:phone":"+1 239 435 1291",
    "sg:postcode":"34104",
    "sg:province":"FL",
    "sg:tags":[
        "specialty",
        "mfg"
    ],
    "wof:name":"Diegos Signs Inc",
    "wof:placetype":"venue"
},
  "geometry": {"coordinates":[-81.751479,26.157253],"type":"Point"}
}