{
  "type": "Feature",
  "properties": {
    "addr:full":"4311 NE 12th Ave Pompano Beach FL 33064",
    "addr:housenumber":"4311",
    "addr:postcode":"33064",
    "addr:street":"Ne 12Th Ave",
    "iso:country":"US",
    "sg:address":"4311 NE 12th Ave",
    "sg:city":"Pompano Beach",
    "sg:classifiers":[
        {
            "category":"Building & Trades",
            "subcategory":"Construction",
            "type":"Services"
        }
    ],
    "sg:phone":"+1 954 943 8343",
    "sg:postcode":"33064",
    "sg:province":"FL",
    "sg:tags":[
        "painting",
        "contractor"
    ],
    "wof:name":"Chadwick Paints",
    "wof:placetype":"venue"
},
  "geometry": {"coordinates":[-80.10715500000001,26.285236],"type":"Point"}
}