{
  "type": "Feature",
  "properties": {
    "addr:full":"6028 14th St W Bradenton FL 34207",
    "addr:housenumber":"6028",
    "addr:postcode":"34207",
    "addr:street":"14Th St W",
    "iso:country":"US",
    "sg:address":"6028 14th St W",
    "sg:city":"Bradenton",
    "sg:classifiers":[
        {
            "category":"Food & Beverages",
            "subcategory":"Specialty",
            "type":"Retail Goods"
        }
    ],
    "sg:phone":"+1 941 751 2261",
    "sg:postcode":"34207",
    "sg:province":"FL",
    "sg:tags":[
        "health",
        "diet"
    ],
    "wof:name":"GNC",
    "wof:placetype":"venue"
},
  "geometry": {"coordinates":[-82.575546,27.431747],"type":"Point"}
}