{
  "type": "Feature",
  "properties": {
    "addr:full":"750 Old Tree Line Trl De Land FL 32724",
    "addr:housenumber":"750",
    "addr:postcode":"32724",
    "addr:street":"Old Tree Line Trl",
    "iso:country":"US",
    "sg:address":"750 Old Tree Line Trl",
    "sg:city":"De Land",
    "sg:classifiers":[
        {
            "category":"Professional",
            "subcategory":"Management & Consulting",
            "type":"Services"
        }
    ],
    "sg:phone":"+1 386 740 1919",
    "sg:postcode":"32724",
    "sg:province":"FL",
    "sg:tags":[
        "business"
    ],
    "wof:name":"Bubeck Consultants Inc",
    "wof:placetype":"venue"
},
  "geometry": {"coordinates":[-81.31044199999999,29.095427],"type":"Point"}
}