{
  "type": "Feature",
  "properties": {
    "iso:country":"US",
    "sg:address":"599 Celebration Pl",
    "sg:city":"Kissimmee",
    "sg:classifiers":[
        {
            "category":"Building & Trades",
            "subcategory":"Construction",
            "type":"Services"
        }
    ],
    "sg:phone":"+1 407 566 1010",
    "sg:postcode":"34747",
    "sg:province":"FL",
    "sg:tags":[
        "contractor"
    ],
    "wof:name":"Cambridge Homes Celebration Operations Office",
    "wof:placetype":"venue"
},
  "geometry": {"coordinates":[-81.547302,28.3265],"type":"Point"}
}