{
  "type": "Feature",
  "properties": {
    "iso:country":"US",
    "sg:address":"1550 Main St",
    "sg:city":"Sarasota",
    "sg:classifiers":[
        {
            "category":"Restaurant",
            "type":"Food & Drink"
        }
    ],
    "sg:phone":"+1 941 362 7972",
    "sg:postcode":"34236",
    "sg:province":"FL",
    "wof:name":"New Faema",
    "wof:placetype":"venue"
},
  "geometry": {"coordinates":[-82.539579,27.336386],"type":"Point"}
}