{
  "type": "Feature",
  "properties": {
    "iso:country":"US",
    "sg:address":"850 SW 34th St",
    "sg:city":"Fort Lauderdale",
    "sg:classifiers":[
        {
            "category":"Building & Trades",
            "subcategory":"Equipment Rental",
            "type":"Services"
        }
    ],
    "sg:phone":"+1 954 359 5388",
    "sg:postcode":"33315",
    "sg:province":"FL",
    "sg:tags":[
        "aircraft",
        "leasing",
        "charter"
    ],
    "sg:website":"www.airfla.com",
    "wof:name":"Air Florida",
    "wof:placetype":"venue"
},
  "geometry": {"coordinates":[-80.151944,26.081542],"type":"Point"}
}