{
  "type": "Feature",
  "properties": {
    "addr:full":"4132 Okeechobee Rd Fort Pierce FL 34947",
    "addr:housenumber":"4132",
    "addr:postcode":"34947",
    "addr:street":"Okeechobee Rd",
    "iso:country":"US",
    "sg:address":"4132 Okeechobee Rd",
    "sg:city":"Fort Pierce",
    "sg:classifiers":[
        {
            "category":"Government",
            "subcategory":"Office",
            "type":"Public Place"
        }
    ],
    "sg:phone":"+1 772 462 1500",
    "sg:postcode":"34947",
    "sg:province":"FL",
    "wof:name":"St Lucie Cnty Supervisor-Elect",
    "wof:placetype":"venue"
},
  "geometry": {"coordinates":[-80.366793,27.426486],"type":"Point"}
}