{
  "type": "Feature",
  "properties": {
    "iso:country":"US",
    "sg:address":"1007 Franklin St",
    "sg:city":"Jacksonville",
    "sg:classifiers":[
        {
            "category":"Shopping",
            "type":"Retail Goods"
        }
    ],
    "sg:phone":"+1 904 355 0092",
    "sg:postcode":"32206",
    "sg:province":"FL",
    "sg:tags":[
        "cosmetic",
        "perfume"
    ],
    "wof:name":"Tiffany's Beauty Supply",
    "wof:placetype":"venue"
},
  "geometry": {"coordinates":[-81.63942,30.335502],"type":"Point"}
}