{
  "type": "Feature",
  "properties": {
    "iso:country":"US",
    "sg:address":"2195 NE 163rd St",
    "sg:city":"North Miami Bch",
    "sg:classifiers":[
        {
            "category":"Building & Trades",
            "subcategory":"Construction",
            "type":"Services"
        }
    ],
    "sg:phone":"+1 305 947 2779",
    "sg:postcode":"33162",
    "sg:province":"FL",
    "sg:tags":[
        "general",
        "contractor"
    ],
    "wof:name":"KEA Constructions",
    "wof:placetype":"venue"
},
  "geometry": {"coordinates":[-80.15768199999999,25.926124],"type":"Point"}
}