{
  "type": "Feature",
  "properties": {
    "iso:country":"US",
    "sg:address":"8050 Seminole Mall",
    "sg:city":"Seminole",
    "sg:classifiers":[
        {
            "category":"Professional",
            "subcategory":"Engineering",
            "type":"Services"
        }
    ],
    "sg:phone":"+1 727 319 8101",
    "sg:postcode":"33772",
    "sg:province":"FL",
    "wof:name":"Ema Engineers Inc",
    "wof:placetype":"venue"
},
  "geometry": {"coordinates":[-82.792351,27.842197],"type":"Point"}
}