{
  "type": "Feature",
  "properties": {
    "iso:country":"US",
    "sg:address":"7035 Phillips Hwy",
    "sg:city":"Jacksonville",
    "sg:classifiers":[
        {
            "category":"Food & Beverages",
            "subcategory":"Specialty",
            "type":"Retail Goods"
        }
    ],
    "sg:phone":"+1 904 296 9007",
    "sg:postcode":"32216",
    "sg:province":"FL",
    "sg:tags":[
        "water",
        "bulk",
        "company"
    ],
    "wof:name":"Total Water Management",
    "wof:placetype":"venue"
},
  "geometry": {"coordinates":[-81.600615,30.244777],"type":"Point"}
}