{
  "type": "Feature",
  "properties": {
    "addr:full":"1232 Airport Pulling Rd S Naples FL 34104",
    "addr:housenumber":"1232",
    "addr:postcode":"34104",
    "addr:street":"Airport Pulling Rd S",
    "iso:country":"US",
    "sg:address":"1232 Airport Pulling Rd S",
    "sg:city":"Naples",
    "sg:classifiers":[
        {
            "category":"Shopping",
            "subcategory":"Computers & Home Electronics",
            "type":"Retail Goods"
        }
    ],
    "sg:phone":"+1 239 430 1007",
    "sg:postcode":"34104",
    "sg:province":"FL",
    "sg:tags":[
        "marine"
    ],
    "wof:name":"Navtek Marine Electronics",
    "wof:placetype":"venue"
},
  "geometry": {"coordinates":[-81.76664,26.139764],"type":"Point"}
}