{
  "type": "Feature",
  "properties": {
    "addr:full":"601 Universe Blvd Juno Beach FL 33408",
    "addr:housenumber":"601",
    "addr:postcode":"33408",
    "addr:street":"Universe Blvd",
    "iso:country":"US",
    "sg:address":"601 Universe Blvd",
    "sg:city":"Juno Beach",
    "sg:classifiers":[
        {
            "category":"Health Services",
            "subcategory":"Nursing And Care Facility",
            "type":"Services"
        }
    ],
    "sg:phone":"+1 561 627 3800",
    "sg:postcode":"33408",
    "sg:province":"FL",
    "sg:tags":[
        "home",
        "retirement",
        "community"
    ],
    "sg:website":"www.thewaterford.com",
    "wof:name":"Waterford",
    "wof:placetype":"venue"
},
  "geometry": {"coordinates":[-80.056662,26.857899],"type":"Point"}
}