{
  "type": "Feature",
  "properties": {
    "iso:country":"US",
    "sg:address":"4595 Holly Lake Dr",
    "sg:city":"Lake Worth",
    "sg:classifiers":[
        {
            "category":"Shopping",
            "subcategory":"Hobbies, Toys, & Games",
            "type":"Retail Goods"
        }
    ],
    "sg:phone":"+1 561 968 0983",
    "sg:postcode":"33463",
    "sg:province":"FL",
    "sg:tags":[
        "craft"
    ],
    "wof:name":"Gerald Mc Kelvey Crafts",
    "wof:placetype":"venue"
},
  "geometry": {"coordinates":[-80.11497,26.610033],"type":"Point"}
}