{
  "type": "Feature",
  "properties": {
    "iso:country":"US",
    "sg:address":"1900 S Garden Grove Cir",
    "sg:city":"Vero Beach",
    "sg:classifiers":[
        {
            "category":"Real Estate",
            "subcategory":"Real Estate Operator",
            "type":"Services"
        }
    ],
    "sg:phone":"+1 772 569 8101",
    "sg:postcode":"32962",
    "sg:province":"FL",
    "sg:tags":[
        "building",
        "apartment"
    ],
    "wof:name":"Garden Grove Club",
    "wof:placetype":"venue"
},
  "geometry": {"coordinates":[-80.36726,27.56872],"type":"Point"}
}