{
  "type": "Feature",
  "properties": {
    "addr:full":"3262 SE Federal Hwy Stuart FL 34997",
    "addr:housenumber":"3262",
    "addr:postcode":"34997",
    "addr:street":"Se Federal Hwy",
    "iso:country":"US",
    "sg:address":"3262 SE Federal Hwy",
    "sg:city":"Stuart",
    "sg:classifiers":[
        {
            "category":"Utilities",
            "subcategory":"Telephone",
            "type":"Services"
        },
        {
            "category":"Shopping",
            "subcategory":"Mobile Phones",
            "type":"Retail Goods"
        },
        {
            "category":"Manufacturing",
            "subcategory":"Electronics",
            "type":"Manufacturing & Wholesale Goods"
        },
        {
            "category":"Shopping",
            "subcategory":"Computers & Home Electronics",
            "type":"Retail Goods"
        },
        {
            "category":"Communications",
            "type":"Services"
        }
    ],
    "sg:phone":"+1 772 283 2958",
    "sg:postcode":"34997",
    "sg:province":"FL",
    "sg:tags":[
        "sound",
        "television",
        "theater",
        "supply",
        "system",
        "equipment",
        "radio",
        "cellular",
        "telecommunications-equipment",
        "consumer",
        "store"
    ],
    "sg:website":"http://www.radioshack.com",
    "wof:name":"RadioShack",
    "wof:placetype":"venue"
},
  "geometry": {"coordinates":[-80.226337,27.164578],"type":"Point"}
}