{
  "type": "Feature",
  "properties": {
    "iso:country":"US",
    "sg:address":"1134 Warner Rd",
    "sg:city":"Green Cove Spgs",
    "sg:classifiers":[
        {
            "category":"Building & Trades",
            "subcategory":"Construction",
            "type":"Services"
        }
    ],
    "sg:phone":"+1 904 529 2435",
    "sg:postcode":"32043",
    "sg:province":"FL",
    "sg:tags":[
        "clearing",
        "land",
        "leveling"
    ],
    "wof:name":"Doyle Development Co",
    "wof:placetype":"venue"
},
  "geometry": {"coordinates":[-81.718389,29.857816],"type":"Point"}
}