{
  "type": "Feature",
  "properties": {
    "addr:full":"6528 Mount Plymouth Rd Apopka FL 32712",
    "addr:housenumber":"6528",
    "addr:postcode":"32712",
    "addr:street":"Mount Plymouth Rd",
    "iso:country":"US",
    "sg:address":"6528 Mount Plymouth Rd",
    "sg:city":"Apopka",
    "sg:classifiers":[
        {
            "category":"Real Estate",
            "subcategory":"Real Estate Agent",
            "type":"Services"
        }
    ],
    "sg:phone":"+1 407 889 3390",
    "sg:postcode":"32712",
    "sg:province":"FL",
    "wof:name":"C Phil Orr Realtor",
    "wof:placetype":"venue"
},
  "geometry": {"coordinates":[-81.52399699999999,28.770939],"type":"Point"}
}