{
  "type": "Feature",
  "properties": {
    "addr:full":"14032 Marquette Blvd Fort Myers FL 33905",
    "addr:housenumber":"14032",
    "addr:postcode":"33905",
    "addr:street":"Marquette Blvd",
    "iso:country":"US",
    "sg:address":"14032 Marquette Blvd",
    "sg:city":"Fort Myers",
    "sg:classifiers":[
        {
            "category":"Autos & Motor Vehicles",
            "subcategory":"Auto Supplies",
            "type":"Retail Goods"
        }
    ],
    "sg:phone":"+1 239 690 8327",
    "sg:postcode":"33905",
    "sg:province":"FL",
    "wof:name":"Pops Tiger Muffler Auto Svcs",
    "wof:placetype":"venue"
},
  "geometry": {"coordinates":[-81.727402,26.714363],"type":"Point"}
}