{
  "type": "Feature",
  "properties": {
    "iso:country":"US",
    "sg:address":"507 NE 38th St",
    "sg:city":"Miami",
    "sg:classifiers":[
        {
            "category":"Building & Trades",
            "subcategory":"Landscaping Services",
            "type":"Services"
        }
    ],
    "sg:phone":"+1 305 438 1432",
    "sg:postcode":"33137",
    "sg:province":"FL",
    "sg:tags":[
        "lawn",
        "garden"
    ],
    "wof:name":"Steven Ruggieri",
    "wof:placetype":"venue"
},
  "geometry": {"coordinates":[-80.187825,25.812582],"type":"Point"}
}