{
  "type": "Feature",
  "properties": {
    "addr:full":"2730 W Columbus Dr Tampa FL 33607",
    "addr:housenumber":"2730",
    "addr:postcode":"33607",
    "addr:street":"W Columbus Dr",
    "iso:country":"US",
    "sg:address":"2730 W Columbus Dr",
    "sg:city":"Tampa",
    "sg:classifiers":[
        {
            "category":"Home & Garden",
            "subcategory":"Garden Supply",
            "type":"Retail Goods"
        },
        {
            "category":"Shopping",
            "subcategory":"Party Supplies",
            "type":"Retail Goods"
        },
        {
            "category":"Wholesale",
            "subcategory":"Plants",
            "type":"Manufacturing & Wholesale Goods"
        },
        {
            "category":"Shopping",
            "subcategory":"Crafts & Fabrics",
            "type":"Retail Goods"
        },
        {
            "category":"Shopping",
            "subcategory":"Florist",
            "type":"Retail Goods"
        }
    ],
    "sg:phone":"+1 813 471 1111",
    "sg:postcode":"33607",
    "sg:province":"FL",
    "sg:tags":[
        "etc-retail",
        "etc-wholesale",
        "dried",
        "wedding",
        "trees-silk",
        "flowers"
    ],
    "sg:website":"http://jenniesflorist.com",
    "wof:name":"Jennie's Flowers",
    "wof:placetype":"venue"
},
  "geometry": {"coordinates":[-82.488021,27.966713],"type":"Point"}
}