{
  "type": "Feature",
  "properties": {
    "addr:full":"815 Eyrie Dr Oviedo FL 32765",
    "addr:housenumber":"815",
    "addr:postcode":"32765",
    "addr:street":"Eyrie Dr",
    "iso:country":"US",
    "sg:address":"815 Eyrie Dr",
    "sg:city":"Oviedo",
    "sg:classifiers":[
        {
            "category":"Shopping",
            "subcategory":"Computers & Home Electronics",
            "type":"Retail Goods"
        }
    ],
    "sg:phone":"+1 407 365 1595",
    "sg:postcode":"32765",
    "sg:province":"FL",
    "sg:tags":[
        "equipment",
        "dealer"
    ],
    "wof:name":"ASTI",
    "wof:placetype":"venue"
},
  "geometry": {"coordinates":[-81.22422299999999,28.656544],"type":"Point"}
}