{
  "type": "Feature",
  "properties": {
    "iso:country":"US",
    "sg:address":"7420 Kimberly Blvd",
    "sg:city":"Pompano Beach",
    "sg:classifiers":[
        {
            "category":"Shopping",
            "subcategory":"Gifts & Souvenirs",
            "type":"Retail Goods"
        }
    ],
    "sg:phone":"+1 954 718 4553",
    "sg:postcode":"33068",
    "sg:province":"FL",
    "wof:name":"Gifts Etc",
    "wof:placetype":"venue"
},
  "geometry": {"coordinates":[-80.22366599999999,26.217634],"type":"Point"}
}