{
  "type": "Feature",
  "properties": {
    "iso:country":"US",
    "sg:address":"803 Jenks Ave",
    "sg:city":"Panama City",
    "sg:classifiers":[
        {
            "category":"Insurance",
            "subcategory":"Insurance Agent",
            "type":"Services"
        }
    ],
    "sg:phone":"+1 850 522 5226",
    "sg:postcode":"32401",
    "sg:province":"FL",
    "wof:name":"Senior Benefit Svc",
    "wof:placetype":"venue"
},
  "geometry": {"coordinates":[-85.662665,30.164241],"type":"Point"}
}