{
  "type": "Feature",
  "properties": {
    "addr:full":"3124 Cottonwood Dr Crestview FL 32539",
    "addr:housenumber":"3124",
    "addr:postcode":"32539",
    "addr:street":"Cottonwood Dr",
    "iso:country":"US",
    "sg:address":"3124 Cottonwood Dr",
    "sg:city":"Crestview",
    "sg:classifiers":[
        {
            "category":"Wholesale",
            "subcategory":"Auto Parts",
            "type":"Manufacturing & Wholesale Goods"
        }
    ],
    "sg:phone":"+1 850 682 4470",
    "sg:postcode":"32539",
    "sg:province":"FL",
    "sg:tags":[
        "used"
    ],
    "wof:name":"Watsons Auto Salvage",
    "wof:placetype":"venue"
},
  "geometry": {"coordinates":[-86.53151099999999,30.816346],"type":"Point"}
}