{
  "type": "Feature",
  "properties": {
    "iso:country":"US",
    "sg:address":"18000 NW 7th Ave",
    "sg:city":"Miami",
    "sg:classifiers":[
        {
            "category":"Social Services",
            "subcategory":"Child Care",
            "type":"Services"
        }
    ],
    "sg:phone":"+1 305 651 1381",
    "sg:postcode":"33169",
    "sg:province":"FL",
    "sg:tags":[
        "day"
    ],
    "wof:name":"Baby Nursery",
    "wof:placetype":"venue"
},
  "geometry": {"coordinates":[-80.21313000000001,25.939566],"type":"Point"}
}