{
  "type": "Feature",
  "properties": {
    "iso:country":"US",
    "sg:address":"5031 E Hwy 22",
    "sg:city":"Panama City",
    "sg:classifiers":[
        {
            "category":"Personal",
            "subcategory":"Beauty Salon",
            "type":"Services"
        }
    ],
    "sg:phone":"+1 850 785 1868",
    "sg:postcode":"32404",
    "sg:province":"FL",
    "sg:tags":[
        "shop"
    ],
    "wof:name":"Kathy's Classic Touch",
    "wof:placetype":"venue"
},
  "geometry": {"coordinates":[-85.598857,30.153093],"type":"Point"}
}