{
  "type": "Feature",
  "properties": {
    "iso:country":"US",
    "sg:address":"1404 Points Rd",
    "sg:city":"West Palm Beach",
    "sg:classifiers":[
        {
            "category":"Autos & Motor Vehicles",
            "subcategory":"Automobile Sales",
            "type":"Retail Goods"
        }
    ],
    "sg:phone":"+1 561 242 5210",
    "sg:postcode":"33405",
    "sg:province":"FL",
    "sg:tags":[
        "car",
        "used",
        "dealer"
    ],
    "wof:name":"J C's Auto Sales Inc",
    "wof:placetype":"venue"
},
  "geometry": {"coordinates":[-80.07181799999999,26.68943],"type":"Point"}
}