{
  "type": "Feature",
  "properties": {
    "iso:country":"US",
    "sg:address":"1653 N Hiatus Rd",
    "sg:city":"Hollywood",
    "sg:classifiers":[
        {
            "category":"Real Estate",
            "subcategory":"Real Estate Agent",
            "type":"Services"
        }
    ],
    "sg:phone":"+1 954 431 3188",
    "sg:postcode":"33026",
    "sg:province":"FL",
    "wof:name":"Coldwell Banker",
    "wof:placetype":"venue"
},
  "geometry": {"coordinates":[-80.297911,26.025281],"type":"Point"}
}