{
  "type": "Feature",
  "properties": {
    "iso:country":"US",
    "sg:address":"6120 Powers Ave",
    "sg:city":"Jacksonville",
    "sg:classifiers":[
        {
            "category":"Retail",
            "subcategory":"Repair Shop",
            "type":"Services"
        }
    ],
    "sg:phone":"+1 904 737 5312",
    "sg:postcode":"32217",
    "sg:province":"FL",
    "sg:tags":[
        "appliance"
    ],
    "wof:name":"Authorized Appliance & Tool",
    "wof:placetype":"venue"
},
  "geometry": {"coordinates":[-81.62108000000001,30.262078],"type":"Point"}
}