{
  "type": "Feature",
  "properties": {
    "addr:full":"3191 W Tharpe St Tallahassee FL 32303",
    "addr:housenumber":"3191",
    "addr:postcode":"32303",
    "addr:street":"W Tharpe St",
    "iso:country":"US",
    "sg:address":"3191 W Tharpe St",
    "sg:city":"Tallahassee",
    "sg:classifiers":[
        {
            "category":"Wholesale",
            "subcategory":"Machinery & Supplies",
            "type":"Manufacturing & Wholesale Goods"
        }
    ],
    "sg:phone":"+1 850 575 8151",
    "sg:postcode":"32303",
    "sg:province":"FL",
    "sg:tags":[
        "industrial",
        "equipment",
        "used",
        "machinery-new",
        "supplies-wholesale"
    ],
    "wof:name":"Graphics Business Systems",
    "wof:placetype":"venue"
},
  "geometry": {"coordinates":[-84.354005,30.464156],"type":"Point"}
}