{
  "type": "Feature",
  "properties": {
    "addr:full":"18395 Gulf Blvd Indian Shores FL 33785",
    "addr:housenumber":"18395",
    "addr:postcode":"33785",
    "addr:street":"Gulf Blvd",
    "iso:country":"US",
    "sg:address":"18395 Gulf Blvd",
    "sg:city":"Indian Shores",
    "sg:classifiers":[
        {
            "category":"Banks & Credit Unions",
            "subcategory":"Investment Brokerage",
            "type":"Services"
        }
    ],
    "sg:phone":"+1 727 595 6055",
    "sg:postcode":"33785",
    "sg:province":"FL",
    "wof:name":"Investment Planning",
    "wof:placetype":"venue"
},
  "geometry": {"coordinates":[-82.837568,27.838924],"type":"Point"}
}