{
  "type": "Feature",
  "properties": {
    "iso:country":"US",
    "sg:address":"1881 SE Port St Lucie Blvd",
    "sg:city":"Port St Lucie",
    "sg:classifiers":[
        {
            "category":"Health Services",
            "subcategory":"Doctor",
            "type":"Services"
        }
    ],
    "sg:phone":"+1 772 398 3236",
    "sg:postcode":"34952",
    "sg:province":"FL",
    "sg:tags":[
        "physician",
        "surgeon"
    ],
    "wof:name":"Milan M Mukerji MD",
    "wof:placetype":"venue"
},
  "geometry": {"coordinates":[-80.29575699999999,27.27129],"type":"Point"}
}