{
  "type": "Feature",
  "properties": {
    "addr:full":"501 Industrial Ave Boynton Beach FL 33426",
    "addr:housenumber":"501",
    "addr:postcode":"33426",
    "addr:street":"Industrial Ave",
    "iso:country":"US",
    "sg:address":"501 Industrial Ave",
    "sg:city":"Boynton Beach",
    "sg:classifiers":[
        {
            "category":"Home & Garden",
            "subcategory":"Building Materials",
            "type":"Retail Goods"
        },
        {
            "category":"Manufacturing",
            "subcategory":"Glass & Minerals",
            "type":"Manufacturing & Wholesale Goods"
        }
    ],
    "sg:phone":"+1 561 369 3991",
    "sg:postcode":"33426",
    "sg:province":"FL",
    "sg:tags":[
        "precast",
        "stone",
        "mfg",
        "product",
        "concrete"
    ],
    "wof:name":"Stone Craft Systems Corp",
    "wof:placetype":"venue"
},
  "geometry": {"coordinates":[-80.07547599999999,26.531021],"type":"Point"}
}