{
  "type": "Feature",
  "properties": {
    "addr:full":"791 Palo Verde Ct Haverhill FL 33415",
    "addr:housenumber":"791",
    "addr:postcode":"33415",
    "addr:street":"Palo Verde Ct",
    "iso:country":"US",
    "sg:address":"791 Palo Verde Ct",
    "sg:city":"Haverhill",
    "sg:classifiers":[
        {
            "category":"Building & Trades",
            "subcategory":"Construction",
            "type":"Services"
        }
    ],
    "sg:phone":"+1 561 248 9561",
    "sg:postcode":"33415",
    "sg:province":"FL",
    "sg:tags":[
        "grading",
        "contractor"
    ],
    "wof:name":"Reynal Guerra Bobcat",
    "wof:placetype":"venue"
},
  "geometry": {"coordinates":[-80.122855,26.689346],"type":"Point"}
}