{
  "type": "Feature",
  "properties": {
    "addr:full":"1782 Fairview Shores Dr Orlando FL 32804",
    "addr:housenumber":"1782",
    "addr:postcode":"32804",
    "addr:street":"Fairview Shores Dr",
    "iso:country":"US",
    "sg:address":"1782 Fairview Shores Dr",
    "sg:city":"Orlando",
    "sg:classifiers":[
        {
            "category":"Organizations",
            "subcategory":"Community Association",
            "type":"Services"
        }
    ],
    "sg:phone":"+1 407 298 6969",
    "sg:postcode":"32804",
    "sg:province":"FL",
    "wof:name":"College Park Lions Club",
    "wof:placetype":"venue"
},
  "geometry": {"coordinates":[-81.408233,28.60028],"type":"Point"}
}