{
  "type": "Feature",
  "properties": {
    "iso:country":"US",
    "sg:address":"1180 Lisa Ln",
    "sg:city":"Bartow",
    "sg:classifiers":[
        {
            "category":"Restaurant",
            "type":"Food & Drink"
        }
    ],
    "sg:phone":"+1 863 533 2725",
    "sg:postcode":"33830",
    "sg:province":"FL",
    "wof:name":"John P Stansel Iii",
    "wof:placetype":"venue"
},
  "geometry": {"coordinates":[-81.83178599999999,27.87101],"type":"Point"}
}