{
  "type": "Feature",
  "properties": {
    "iso:country":"US",
    "sg:address":"8290 Bay Pines Blvd",
    "sg:city":"St Petersburg",
    "sg:classifiers":[
        {
            "category":"Autos & Motor Vehicles",
            "subcategory":"Automobile Sales",
            "type":"Retail Goods"
        }
    ],
    "sg:phone":"+1 727 343 2925",
    "sg:postcode":"33709",
    "sg:province":"FL",
    "sg:tags":[
        "car",
        "dealer"
    ],
    "wof:name":"Lindsey's Fine Rides & Clsscs",
    "wof:placetype":"venue"
},
  "geometry": {"coordinates":[-82.754087,27.809385],"type":"Point"}
}