{
  "type": "Feature",
  "properties": {
    "iso:country":"US",
    "sg:address":"4800 SE Federal Hwy",
    "sg:city":"Stuart",
    "sg:classifiers":[
        {
            "category":"Building & Trades",
            "subcategory":"Construction",
            "type":"Services"
        }
    ],
    "sg:phone":"+1 772 781 9222",
    "sg:postcode":"34997",
    "sg:province":"FL",
    "sg:tags":[
        "concrete",
        "contractor"
    ],
    "wof:name":"KARA Construction",
    "wof:placetype":"venue"
},
  "geometry": {"coordinates":[-80.21655800000001,27.149078],"type":"Point"}
}