{
  "type": "Feature",
  "properties": {
    "addr:full":"10146 Chumuckla Hwy Jay FL 32565",
    "addr:housenumber":"10146",
    "addr:postcode":"32565",
    "addr:street":"Chumuckla Hwy",
    "iso:country":"US",
    "sg:address":"10146 Chumuckla Hwy",
    "sg:city":"Jay",
    "sg:classifiers":[
        {
            "category":"Building & Trades",
            "subcategory":"Construction",
            "type":"Services"
        }
    ],
    "sg:phone":"+1 850 995 0268",
    "sg:postcode":"32565",
    "sg:province":"FL",
    "sg:tags":[
        "contractor"
    ],
    "wof:name":"AM Drywall Inc",
    "wof:placetype":"venue"
},
  "geometry": {"coordinates":[-87.20223799999999,30.795247],"type":"Point"}
}