{
  "type": "Feature",
  "properties": {
    "addr:full":"2311 SE Ocean Blvd Stuart FL 34996",
    "addr:housenumber":"2311",
    "addr:postcode":"34996",
    "addr:street":"Se Ocean Blvd",
    "iso:country":"US",
    "sg:address":"2311 SE Ocean Blvd",
    "sg:city":"Stuart",
    "sg:classifiers":[
        {
            "category":"Retail",
            "subcategory":"Veterinary Services",
            "type":"Services"
        }
    ],
    "sg:phone":"+1 772 288 1181",
    "sg:postcode":"34996",
    "sg:province":"FL",
    "wof:name":"East Ocean Animal Hospital",
    "wof:placetype":"venue"
},
  "geometry": {"coordinates":[-80.220759,27.196757],"type":"Point"}
}