{
  "type": "Feature",
  "properties": {
    "iso:country":"US",
    "sg:address":"804 E Altamonte Dr",
    "sg:city":"Altamonte Spgs",
    "sg:classifiers":[
        {
            "category":"Home & Garden",
            "subcategory":"Furniture",
            "type":"Retail Goods"
        }
    ],
    "sg:phone":"+1 407 339 8555",
    "sg:postcode":"32701",
    "sg:province":"FL",
    "sg:tags":[
        "bed"
    ],
    "wof:name":"Discount Mattress Barn",
    "wof:placetype":"venue"
},
  "geometry": {"coordinates":[-81.360893,28.663049],"type":"Point"}
}