{
  "type": "Feature",
  "properties": {
    "addr:full":"536 W 28th St Hialeah FL 33010",
    "addr:housenumber":"536",
    "addr:postcode":"33010",
    "addr:street":"W 28Th St",
    "iso:country":"US",
    "sg:address":"536 W 28th St",
    "sg:city":"Hialeah",
    "sg:classifiers":[
        {
            "category":"Shopping",
            "type":"Retail Goods"
        }
    ],
    "sg:phone":"+1 305 888 5667",
    "sg:postcode":"33010",
    "sg:province":"FL",
    "sg:tags":[
        "merchandise"
    ],
    "wof:name":"E/A Granite & Marble Corp",
    "wof:placetype":"venue"
},
  "geometry": {"coordinates":[-80.293567,25.847022],"type":"Point"}
}