{
  "type": "Feature",
  "properties": {
    "addr:full":"4006 E Hillsborough Ave Tampa FL 33610",
    "addr:housenumber":"4006",
    "addr:postcode":"33610",
    "addr:street":"E Hillsborough Ave",
    "iso:country":"US",
    "sg:address":"4006 E Hillsborough Ave",
    "sg:city":"Tampa",
    "sg:classifiers":[
        {
            "category":"Professional",
            "subcategory":"Detective & Security Services",
            "type":"Services"
        },
        {
            "category":"Wholesale",
            "subcategory":"Electrical",
            "type":"Manufacturing & Wholesale Goods"
        }
    ],
    "sg:phone":"+1 813 630 4650",
    "sg:postcode":"33610",
    "sg:province":"FL",
    "sg:tags":[
        "control",
        "installation",
        "monitoring",
        "system"
    ],
    "wof:name":"One Stop Security Inc",
    "wof:placetype":"venue"
},
  "geometry": {"coordinates":[-82.412267,27.996177],"type":"Point"}
}