{
  "type": "Feature",
  "properties": {
    "addr:full":"6460 Pensacola Blvd Pensacola FL 32505",
    "addr:housenumber":"6460",
    "addr:postcode":"32505",
    "addr:street":"Pensacola Blvd",
    "iso:country":"US",
    "sg:address":"6460 Pensacola Blvd",
    "sg:city":"Pensacola",
    "sg:phone":"+1 850 478 4555",
    "sg:postcode":"32505",
    "sg:province":"FL",
    "wof:name":"Chris Carroll Automotive",
    "wof:placetype":"venue"
},
  "geometry": {"coordinates":[-87.25610399999999,30.48288],"type":"Point"}
}