{
  "type": "Feature",
  "properties": {
    "iso:country":"US",
    "sg:address":"1100 5th St S",
    "sg:city":"Naples",
    "sg:classifiers":[
        {
            "category":"Home & Garden",
            "subcategory":"Hardware",
            "type":"Retail Goods"
        }
    ],
    "sg:phone":"+1 239 435 0734",
    "sg:postcode":"34102",
    "sg:province":"FL",
    "wof:name":"Ace Hardware",
    "wof:placetype":"venue"
},
  "geometry": {"coordinates":[-81.799117,26.132306],"type":"Point"}
}