{
  "type": "Feature",
  "properties": {
    "iso:country":"US",
    "sg:address":"10014 Griffin Rd",
    "sg:city":"Cooper City",
    "sg:classifiers":[
        {
            "category":"Retail",
            "subcategory":"Repair Shop",
            "type":"Services"
        }
    ],
    "sg:phone":"+1 954 446 7267",
    "sg:postcode":"33328",
    "sg:province":"FL",
    "sg:tags":[
        "lock",
        "locksmith"
    ],
    "wof:name":"24 Hour 7 Day Emergency",
    "wof:placetype":"venue"
},
  "geometry": {"coordinates":[-80.280362,26.064062],"type":"Point"}
}