{
  "type": "Feature",
  "properties": {
    "addr:full":"2328 Palm Ter West Palm Beach FL 33406",
    "addr:housenumber":"2328",
    "addr:postcode":"33406",
    "addr:street":"Palm Ter",
    "iso:country":"US",
    "sg:address":"2328 Palm Ter",
    "sg:city":"West Palm Beach",
    "sg:classifiers":[
        {
            "category":"Real Estate",
            "subcategory":"Real Estate Agent",
            "type":"Services"
        },
        {
            "category":"Real Estate",
            "subcategory":"Real Estate Operator",
            "type":"Services"
        }
    ],
    "sg:phone":"+1 561 649 8585",
    "sg:postcode":"33406",
    "sg:province":"FL",
    "sg:tags":[
        "credit",
        "property",
        "lessor",
        "business",
        "institution"
    ],
    "wof:name":"Banyan Property Management",
    "wof:placetype":"venue"
},
  "geometry": {"coordinates":[-80.077217,26.64295],"type":"Point"}
}