{
  "type": "Feature",
  "properties": {
    "iso:country":"US",
    "sg:address":"18109 Heron Walk Dr",
    "sg:city":"Tampa",
    "sg:classifiers":[
        {
            "category":"Wholesale",
            "subcategory":"Construction Materials",
            "type":"Manufacturing & Wholesale Goods"
        }
    ],
    "sg:phone":"+1 813 994 1866",
    "sg:postcode":"33647",
    "sg:province":"FL",
    "sg:tags":[
        "building",
        "prefabricated"
    ],
    "wof:name":"Vision Bldg Solutions L L C",
    "wof:placetype":"venue"
},
  "geometry": {"coordinates":[-82.310064,28.137723],"type":"Point"}
}