{
  "type": "Feature",
  "properties": {
    "addr:full":"9614 Maywood Dr Windermere FL 34786",
    "addr:housenumber":"9614",
    "addr:postcode":"34786",
    "addr:street":"Maywood Dr",
    "iso:country":"US",
    "sg:address":"9614 Maywood Dr",
    "sg:city":"Windermere",
    "sg:classifiers":[
        {
            "category":"Arts & Performance",
            "subcategory":"Theater",
            "type":"Entertainment"
        }
    ],
    "sg:phone":"+1 407 876 5000",
    "sg:postcode":"34786",
    "sg:province":"FL",
    "sg:tags":[
        "bureau"
    ],
    "sg:website":"www.pebshowproductions.com",
    "wof:name":"PEB Assoc",
    "wof:placetype":"venue"
},
  "geometry": {"coordinates":[-81.52145899999999,28.506124],"type":"Point"}
}