{
  "type": "Feature",
  "properties": {
    "iso:country":"US",
    "sg:address":"12826 Commodity Pl",
    "sg:city":"Tampa",
    "sg:classifiers":[
        {
            "category":"Health Services",
            "subcategory":"Health Practitioner",
            "type":"Services"
        }
    ],
    "sg:phone":"+1 813 569 0450",
    "sg:postcode":"33626",
    "sg:province":"FL",
    "sg:tags":[
        "nutritionist"
    ],
    "sg:website":"www.a1nutrition.com",
    "wof:name":"A1NUTRITION.COM",
    "wof:placetype":"venue"
},
  "geometry": {"coordinates":[-82.63381200000001,28.066179],"type":"Point"}
}