{
  "type": "Feature",
  "properties": {
    "iso:country":"US",
    "sg:address":"2000 Cambridge Dr",
    "sg:city":"Cocoa",
    "sg:classifiers":[
        {
            "category":"Education",
            "subcategory":"School",
            "type":"Public Place"
        }
    ],
    "sg:phone":"+1 321 633 3550",
    "sg:postcode":"32922",
    "sg:province":"FL",
    "wof:name":"Cambridge Elementary School",
    "wof:placetype":"venue"
},
  "geometry": {"coordinates":[-80.750445,28.382621],"type":"Point"}
}