{
  "type": "Feature",
  "properties": {
    "iso:country":"US",
    "sg:address":"1275 US Hwy 92",
    "sg:city":"Longwood",
    "sg:classifiers":[
        {
            "category":"Restaurant",
            "type":"Food & Drink"
        }
    ],
    "sg:phone":"+1 407 696 7775",
    "sg:postcode":"32750",
    "sg:province":"FL",
    "sg:tags":[
        "caterer"
    ],
    "wof:name":"Clay Oven Indian Restaurant",
    "wof:placetype":"venue"
},
  "geometry": {"coordinates":[-81.32874200000001,28.689154],"type":"Point"}
}