{
  "type": "Feature",
  "properties": {
    "iso:country":"US",
    "sg:address":"7655 Callan Ct",
    "sg:city":"New Port Richey",
    "sg:classifiers":[
        {
            "category":"Manufacturing",
            "subcategory":"Tools & Machinery",
            "type":"Manufacturing & Wholesale Goods"
        }
    ],
    "sg:phone":"+1 727 844 5505",
    "sg:postcode":"34654",
    "sg:province":"FL",
    "sg:tags":[
        "set",
        "mfg"
    ],
    "wof:name":"Tulip Enterprises Intl",
    "wof:placetype":"venue"
},
  "geometry": {"coordinates":[-82.664027,28.273617],"type":"Point"}
}