{
  "type": "Feature",
  "properties": {
    "iso:country":"US",
    "sg:address":"6911 Environ Blvd",
    "sg:city":"Fort Lauderdale",
    "sg:classifiers":[
        {
            "category":"Professional",
            "subcategory":"Employment Agencies",
            "type":"Services"
        }
    ],
    "sg:phone":"+1 954 485 0200",
    "sg:postcode":"33319",
    "sg:province":"FL",
    "wof:name":"David Strasberg & Assoc",
    "wof:placetype":"venue"
},
  "geometry": {"coordinates":[-80.244013,26.174204],"type":"Point"}
}