{
  "type": "Feature",
  "properties": {
    "iso:country":"US",
    "sg:address":"3341 Gerhardt St",
    "sg:city":"Sarasota",
    "sg:classifiers":[
        {
            "category":"Building & Trades",
            "subcategory":"Landscaping Services",
            "type":"Services"
        }
    ],
    "sg:phone":"+1 941 365 2159",
    "sg:postcode":"34237",
    "sg:province":"FL",
    "wof:name":"Stewart Stephen",
    "wof:placetype":"venue"
},
  "geometry": {"coordinates":[-82.502197,27.326646],"type":"Point"}
}