{
  "type": "Feature",
  "properties": {
    "addr:full":"1669 N Hiatus Rd Pembroke Pines FL 33026",
    "addr:housenumber":"1669",
    "addr:postcode":"33026",
    "addr:street":"N Hiatus Rd",
    "iso:country":"US",
    "sg:address":"1669 N Hiatus Rd",
    "sg:city":"Pembroke Pines",
    "sg:classifiers":[
        {
            "category":"Restaurant",
            "type":"Food & Drink"
        }
    ],
    "sg:phone":"+1 954 431 7688",
    "sg:postcode":"33026",
    "sg:province":"FL",
    "wof:name":"China City",
    "wof:placetype":"venue"
},
  "geometry": {"coordinates":[-80.29792999999999,26.025239],"type":"Point"}
}