{
  "type": "Feature",
  "properties": {
    "iso:country":"US",
    "sg:address":"3681 SW 52nd Ter",
    "sg:city":"Ocala",
    "sg:classifiers":[
        {
            "category":"Building & Trades",
            "subcategory":"Construction",
            "type":"Services"
        }
    ],
    "sg:phone":"+1 352 873 3500",
    "sg:postcode":"34474",
    "sg:province":"FL",
    "sg:tags":[
        "house"
    ],
    "wof:name":"G P Construction Co of Ocala",
    "wof:placetype":"venue"
},
  "geometry": {"coordinates":[-82.20785600000001,29.151366],"type":"Point"}
}