{
  "type": "Feature",
  "properties": {
    "addr:full":"119 Gardenia Ave Tavernier FL 33070",
    "addr:housenumber":"119",
    "addr:postcode":"33070",
    "addr:street":"Gardenia Ave",
    "iso:country":"US",
    "sg:address":"119 Gardenia Ave",
    "sg:city":"Tavernier",
    "sg:classifiers":[
        {
            "category":"Freight",
            "type":"Transportation"
        }
    ],
    "sg:phone":"+1 305 453 4533",
    "sg:postcode":"33070",
    "sg:province":"FL",
    "sg:tags":[
        "delivery"
    ],
    "wof:name":"Key Razy Cab Co",
    "wof:placetype":"venue"
},
  "geometry": {"coordinates":[-80.535175,25.003372],"type":"Point"}
}