{
  "type": "Feature",
  "properties": {
    "addr:full":"2491 Principal Row Orlando FL 32837",
    "addr:postcode":"2491;32837",
    "addr:street":"Principal Row",
    "iso:country":"US",
    "sg:address":"2491 Principal Row",
    "sg:city":"Orlando",
    "sg:classifiers":[
        {
            "category":"Retail",
            "subcategory":"Laundry & Dry Cleaning",
            "type":"Services"
        }
    ],
    "sg:phone":"+1 407 857 6566",
    "sg:postcode":"32837",
    "sg:province":"FL",
    "sg:tags":[
        "linen",
        "supply"
    ],
    "wof:name":"BBJ Rentals Inc",
    "wof:placetype":"venue"
},
  "geometry": {"coordinates":[-81.414801,28.426043],"type":"Point"}
}