{
  "type": "Feature",
  "properties": {
    "iso:country":"US",
    "sg:address":"3298 NW 9th Ave",
    "sg:city":"Fort Lauderdale",
    "sg:classifiers":[
        {
            "category":"Food & Beverages",
            "subcategory":"Groceries & Convenience Stores",
            "type":"Retail Goods"
        }
    ],
    "sg:phone":"+1 954 630 3787",
    "sg:postcode":"33309",
    "sg:province":"FL",
    "wof:name":"Food Stop",
    "wof:placetype":"venue"
},
  "geometry": {"coordinates":[-80.154447,26.167539],"type":"Point"}
}