{
  "type": "Feature",
  "properties": {
    "iso:country":"US",
    "sg:address":"9861 SW 12th Ter",
    "sg:city":"Miami",
    "sg:classifiers":[
        {
            "category":"Communications",
            "type":"Services"
        },
        {
            "category":"Professional",
            "subcategory":"Management & Consulting",
            "type":"Services"
        }
    ],
    "sg:phone":"+1 305 220 8887",
    "sg:postcode":"33174",
    "sg:province":"FL",
    "sg:tags":[
        "comm",
        "for",
        "special",
        "event"
    ],
    "wof:name":"Santa Cruz Communications Inc",
    "wof:placetype":"venue"
},
  "geometry": {"coordinates":[-80.35371000000001,25.757658],"type":"Point"}
}