{
  "type": "Feature",
  "properties": {
    "iso:country":"US",
    "sg:address":"4960 Glover Ln",
    "sg:city":"Baker",
    "sg:classifiers":[
        {
            "category":"Retail",
            "subcategory":"Animal Services",
            "type":"Services"
        }
    ],
    "sg:phone":"+1 850 537 6515",
    "sg:postcode":"32570",
    "sg:province":"FL",
    "sg:tags":[
        "horse",
        "training"
    ],
    "wof:name":"Colomont Training Center",
    "wof:placetype":"venue"
},
  "geometry": {"coordinates":[-87.06451199999999,30.621727],"type":"Point"}
}