{
  "type": "Feature",
  "properties": {
    "addr:full":"2355 Tamiami Trl N Naples FL 34103",
    "addr:housenumber":"2355",
    "addr:postcode":"34103",
    "addr:street":"Tamiami Trl N",
    "iso:country":"US",
    "sg:address":"2355 Tamiami Trl N",
    "sg:city":"Naples",
    "sg:classifiers":[
        {
            "category":"Fast Food",
            "type":"Food & Drink"
        },
        {
            "category":"Restaurant",
            "type":"Food & Drink"
        }
    ],
    "sg:phone":"+1 239 434 6116",
    "sg:postcode":"34103",
    "sg:province":"FL",
    "sg:tags":[
        "american",
        "style",
        "seafood",
        "family",
        "take"
    ],
    "sg:website":"http://www.redlobster.com",
    "wof:name":"Red Lobster",
    "wof:placetype":"venue"
},
  "geometry": {"coordinates":[-81.799858,26.176458],"type":"Point"}
}