{
  "type": "Feature",
  "properties": {
    "addr:full":"2041 Zip Code Pl West Palm Beach FL 33409",
    "addr:housenumber":"2041",
    "addr:postcode":"33409",
    "addr:street":"Zip Code Pl",
    "iso:country":"US",
    "sg:address":"2041 Zip Code Pl",
    "sg:city":"West Palm Beach",
    "sg:classifiers":[
        {
            "category":"Shopping",
            "subcategory":"Department Store",
            "type":"Retail Goods"
        }
    ],
    "sg:phone":"+1 561 697 5117",
    "sg:postcode":"33409",
    "sg:province":"FL",
    "sg:tags":[
        "shop"
    ],
    "sg:website":"www.pier1.com",
    "wof:name":"Pier 1 Imports",
    "wof:placetype":"venue"
},
  "geometry": {"coordinates":[-80.108937,26.709571],"type":"Point"}
}