{
  "type": "Feature",
  "properties": {
    "addr:full":"4301 Dancey Dr Wimauma FL 33598",
    "addr:housenumber":"4301",
    "addr:postcode":"33598",
    "addr:street":"Dancey Dr Wimauma",
    "iso:country":"US",
    "sg:address":"4301 Dancey Dr",
    "sg:city":"Wimauma",
    "sg:classifiers":[
        {
            "category":"Building & Trades",
            "subcategory":"Construction",
            "type":"Services"
        }
    ],
    "sg:phone":"+1 813 634 7433",
    "sg:postcode":"33598",
    "sg:province":"FL",
    "sg:tags":[
        "house"
    ],
    "wof:name":"G&J Home Services",
    "wof:placetype":"venue"
},
  "geometry": {"coordinates":[-82.361368,27.667792],"type":"Point"}
}