{
  "type": "Feature",
  "properties": {
    "iso:country":"US",
    "sg:address":"4063 Ponce de Leon Blvd",
    "sg:city":"Miami",
    "sg:classifiers":[
        {
            "category":"Professional",
            "subcategory":"Business Services",
            "type":"Services"
        }
    ],
    "sg:phone":"+1 305 446 2526",
    "sg:postcode":"33134",
    "sg:province":"FL",
    "wof:name":"Ana Heydrich",
    "wof:placetype":"venue"
},
  "geometry": {"coordinates":[-80.25843,25.733734],"type":"Point"}
}