{
  "type": "Feature",
  "properties": {
    "iso:country":"US",
    "sg:address":"102 Drennen Rd",
    "sg:city":"Orlando",
    "sg:classifiers":[
        {
            "category":"Sports & Exercise",
            "subcategory":"Golf",
            "type":"Entertainment"
        }
    ],
    "sg:phone":"+1 407 857 0964",
    "sg:postcode":"32806",
    "sg:province":"FL",
    "sg:tags":[
        "course"
    ],
    "wof:name":"Titania Golf",
    "wof:placetype":"venue"
},
  "geometry": {"coordinates":[-81.37925,28.502994],"type":"Point"}
}