{
  "type": "Feature",
  "properties": {
    "iso:country":"US",
    "sg:address":"4860 SE 32nd Ct",
    "sg:city":"Ocala",
    "sg:classifiers":[
        {
            "category":"Professional",
            "subcategory":"Business Services",
            "type":"Services"
        }
    ],
    "sg:phone":"+1 352 402 9998",
    "sg:postcode":"34480",
    "sg:province":"FL",
    "sg:tags":[
        "pool",
        "swimming"
    ],
    "wof:name":"Gary Arciero Pool Maintenance",
    "wof:placetype":"venue"
},
  "geometry": {"coordinates":[-82.092792,29.137627],"type":"Point"}
}