{
  "type": "Feature",
  "properties": {
    "iso:country":"US",
    "sg:address":"10092 Moss Rose Way",
    "sg:city":"Orlando",
    "sg:classifiers":[
        {
            "category":"Building & Trades",
            "subcategory":"Construction",
            "type":"Services"
        }
    ],
    "sg:phone":"+1 407 277 5711",
    "sg:postcode":"32832",
    "sg:province":"FL",
    "sg:tags":[
        "home",
        "builder"
    ],
    "wof:name":"Engle Homes",
    "wof:placetype":"venue"
},
  "geometry": {"coordinates":[-81.239422,28.419846],"type":"Point"}
}