{
  "type": "Feature",
  "properties": {
    "addr:full":"8390 NW 7th Ave Miami FL 33150",
    "addr:housenumber":"8390",
    "addr:postcode":"33150",
    "addr:street":"Nw 7Th Ave",
    "iso:country":"US",
    "sg:address":"8390 NW 7th Ave",
    "sg:city":"Miami",
    "sg:classifiers":[
        {
            "category":"Education",
            "subcategory":"School",
            "type":"Public Place"
        }
    ],
    "sg:phone":"+1 305 265 2714",
    "sg:postcode":"33150",
    "sg:province":"FL",
    "sg:tags":[
        "high",
        "middle",
        "elementary"
    ],
    "wof:name":"Miami-Dade County Public Schools",
    "wof:placetype":"venue"
},
  "geometry": {"coordinates":[-80.209469,25.851986],"type":"Point"}
}