{
  "type": "Feature",
  "properties": {
    "addr:full":"5250 34th St N St Petersburg FL 33714",
    "addr:housenumber":"5250",
    "addr:postcode":"33714",
    "addr:street":"34Th St N",
    "iso:country":"US",
    "sg:address":"5250 34th St N",
    "sg:city":"St Petersburg",
    "sg:classifiers":[
        {
            "category":"Retail",
            "subcategory":"Laundry & Dry Cleaning",
            "type":"Services"
        }
    ],
    "sg:phone":"+1 727 525 6364",
    "sg:postcode":"33714",
    "sg:province":"FL",
    "wof:name":"House Of Clean",
    "wof:placetype":"venue"
},
  "geometry": {"coordinates":[-82.67960100000001,27.819696],"type":"Point"}
}