{
  "type": "Feature",
  "properties": {
    "iso:country":"US",
    "sg:address":"208 W Guava St",
    "sg:city":"Lady Lake",
    "sg:classifiers":[
        {
            "category":"Restaurant",
            "type":"Food & Drink"
        }
    ],
    "sg:menulink":"http://www.allmenus.com/fl/fruitland-park-lady-lake/111795-subway/menu/",
    "sg:phone":"+1 352 750 4929",
    "sg:postcode":"32159",
    "sg:province":"FL",
    "sg:tags":[
        "american",
        "sandwich"
    ],
    "wof:name":"Subway",
    "wof:placetype":"venue"
},
  "geometry": {"coordinates":[-81.92371199999999,28.918618],"type":"Point"}
}