{
  "type": "Feature",
  "properties": {
    "iso:country":"US",
    "sg:address":"7307 Palm Beach Blvd",
    "sg:city":"Alva",
    "sg:classifiers":[
        {
            "category":"Home & Garden",
            "subcategory":"Building Materials",
            "type":"Retail Goods"
        }
    ],
    "sg:phone":"+1 239 728 2484",
    "sg:postcode":"33920",
    "sg:province":"FL",
    "sg:tags":[
        "lumber-used"
    ],
    "wof:name":"Alva Hardwood",
    "wof:placetype":"venue"
},
  "geometry": {"coordinates":[-81.615627,26.708885],"type":"Point"}
}