{
  "type": "Feature",
  "properties": {
    "addr:full":"185 SE 14th St Miami FL 33131",
    "addr:housenumber":"185",
    "addr:postcode":"33131",
    "addr:street":"Se 14Th St",
    "iso:country":"US",
    "sg:address":"185 SE 14th St",
    "sg:city":"Miami",
    "sg:classifiers":[
        {
            "category":"Professional",
            "subcategory":"Computer Services",
            "type":"Services"
        }
    ],
    "sg:phone":"+1 305 374 7821",
    "sg:postcode":"33131",
    "sg:province":"FL",
    "sg:tags":[
        "vortex",
        "audio",
        "replicator"
    ],
    "wof:name":"Fyberfonix Corporation",
    "wof:placetype":"venue"
},
  "geometry": {"coordinates":[-80.19070499999999,25.760132],"type":"Point"}
}