{
  "type": "Feature",
  "properties": {
    "addr:full":"17904 Cachet Isle Dr Tampa FL 33647",
    "addr:housenumber":"17904",
    "addr:postcode":"33647",
    "addr:street":"Cachet Isle Dr",
    "iso:country":"US",
    "sg:address":"17904 Cachet Isle Dr",
    "sg:city":"Tampa",
    "sg:classifiers":[
        {
            "category":"Health Services",
            "subcategory":"Doctor",
            "type":"Services"
        }
    ],
    "sg:phone":"+1 813 986 9660",
    "sg:postcode":"33647",
    "sg:province":"FL",
    "sg:tags":[
        "medical"
    ],
    "wof:name":"Comprhension Pain MGT Partners",
    "wof:placetype":"venue"
},
  "geometry": {"coordinates":[-82.300783,28.132725],"type":"Point"}
}