{
  "type": "Feature",
  "properties": {
    "addr:full":"314 Indian Trce Weston FL 33326",
    "addr:housenumber":"314",
    "addr:postcode":"33326",
    "addr:street":"Indian Trce",
    "iso:country":"US",
    "sg:address":"314 Indian Trce",
    "sg:city":"Weston",
    "sg:classifiers":[
        {
            "category":"Personal",
            "subcategory":"Beauty Salon",
            "type":"Services"
        }
    ],
    "sg:phone":"+1 954 384 1755",
    "sg:postcode":"33326",
    "sg:province":"FL",
    "sg:tags":[
        "hair",
        "stylist"
    ],
    "wof:name":"Zoila Hair & Spa",
    "wof:placetype":"venue"
},
  "geometry": {"coordinates":[-80.394238,26.119824],"type":"Point"}
}