{
  "type": "Feature",
  "properties": {
    "iso:country":"US",
    "sg:address":"5615 Seaboard Ave",
    "sg:city":"Jacksonville",
    "sg:classifiers":[
        {
            "category":"Personal",
            "subcategory":"Beauty Salon",
            "type":"Services"
        }
    ],
    "sg:phone":"+1 904 771 9393",
    "sg:postcode":"32244",
    "sg:province":"FL",
    "wof:name":"Millie's Hair Braiding",
    "wof:placetype":"venue"
},
  "geometry": {"coordinates":[-81.730577,30.24661],"type":"Point"}
}