{
  "type": "Feature",
  "properties": {
    "iso:country":"US",
    "sg:address":"609 Chatas Ct",
    "sg:city":"Lake Mary",
    "sg:classifiers":[
        {
            "category":"Communications",
            "subcategory":"Film & Video Production",
            "type":"Services"
        }
    ],
    "sg:phone":"+1 407 688 1144",
    "sg:postcode":"32746",
    "sg:province":"FL",
    "sg:tags":[
        "motion"
    ],
    "wof:name":"Burning Tongues Productions",
    "wof:placetype":"venue"
},
  "geometry": {"coordinates":[-81.330929,28.775419],"type":"Point"}
}