{
  "type": "Feature",
  "properties": {
    "iso:country":"US",
    "sg:address":"2305 Baileys Bluff Rd",
    "sg:city":"Holiday",
    "sg:classifiers":[
        {
            "category":"Recreation",
            "type":"Entertainment"
        }
    ],
    "sg:phone":"+1 727 942 4030",
    "sg:postcode":"34691",
    "sg:province":"FL",
    "sg:tags":[
        "parks"
    ],
    "wof:name":"Anclote Gulf Park",
    "wof:placetype":"venue"
},
  "geometry": {"coordinates":[-82.785169,28.18053],"type":"Point"}
}