{
  "type": "Feature",
  "properties": {
    "iso:country":"US",
    "sg:address":"38196 Medical Center Ave",
    "sg:city":"Zephyrhills",
    "sg:classifiers":[
        {
            "category":"Health Services",
            "subcategory":"Doctor",
            "type":"Services"
        }
    ],
    "sg:phone":"+1 813 779 9606",
    "sg:postcode":"33540",
    "sg:province":"FL",
    "sg:tags":[
        "osteopathic"
    ],
    "wof:name":"Anoop K Reddy MD PA",
    "wof:placetype":"venue"
},
  "geometry": {"coordinates":[-82.188188,28.263232],"type":"Point"}
}