{
  "type": "Feature",
  "properties": {
    "addr:full":"136 Doe Trl Jupiter FL 33458",
    "addr:housenumber":"136",
    "addr:postcode":"33458",
    "addr:street":"Doe Trl",
    "iso:country":"US",
    "sg:address":"136 Doe Trl",
    "sg:city":"Jupiter",
    "sg:classifiers":[
        {
            "category":"Shopping",
            "subcategory":"Gifts & Souvenirs",
            "type":"Retail Goods"
        }
    ],
    "sg:phone":"+1 561 596 4847",
    "sg:postcode":"33458",
    "sg:province":"FL",
    "sg:tags":[
        "announcement",
        "invitation"
    ],
    "wof:name":"Invitations Galore",
    "wof:placetype":"venue"
},
  "geometry": {"coordinates":[-80.128218,26.918288],"type":"Point"}
}