{
  "type": "Feature",
  "properties": {
    "addr:full":"3701 Central Ave Saint Petersburg FL 33713",
    "addr:housenumber":"3701",
    "addr:postcode":"33713",
    "addr:street":"Central Ave",
    "iso:country":"US",
    "sg:address":"3701 Central Ave",
    "sg:city":"Saint Petersburg",
    "sg:classifiers":[
        {
            "category":"Manufacturing",
            "subcategory":"Petroleum Products",
            "type":"Manufacturing & Wholesale Goods"
        },
        {
            "category":"Utilities",
            "subcategory":"Refuse",
            "type":"Services"
        }
    ],
    "sg:phone":"+1 727 327 8467",
    "sg:postcode":"33713",
    "sg:province":"FL",
    "sg:tags":[
        "refinery",
        "sanitary",
        "material",
        "system"
    ],
    "wof:name":"Howco Environmental Services",
    "wof:placetype":"venue"
},
  "geometry": {"coordinates":[-82.68482,27.770968],"type":"Point"}
}