{
  "type": "Feature",
  "properties": {
    "iso:country":"US",
    "sg:address":"3819 13th Ave N",
    "sg:city":"St Petersburg",
    "sg:classifiers":[
        {
            "category":"Retail",
            "subcategory":"Repair Shop",
            "type":"Services"
        }
    ],
    "sg:phone":"+1 727 321 8043",
    "sg:postcode":"33713",
    "sg:province":"FL",
    "sg:tags":[
        "lock",
        "locksmith"
    ],
    "wof:name":"A Ability Locksmiths",
    "wof:placetype":"venue"
},
  "geometry": {"coordinates":[-82.68607299999999,27.784651],"type":"Point"}
}