{
  "type": "Feature",
  "properties": {
    "iso:country":"US",
    "sg:address":"1209 N Parsons Ave",
    "sg:city":"Brandon",
    "sg:classifiers":[
        {
            "category":"Real Estate",
            "subcategory":"Real Estate Agent",
            "type":"Services"
        }
    ],
    "sg:phone":"+1 813 681 3310",
    "sg:postcode":"33510",
    "sg:province":"FL",
    "wof:name":"Olis Tyson Realty",
    "wof:placetype":"venue"
},
  "geometry": {"coordinates":[-82.285816,27.958161],"type":"Point"}
}