{
  "type": "Feature",
  "properties": {
    "addr:full":"3321 SW 27th Terrace Miami FL 33133",
    "addr:housenumber":"3321",
    "addr:postcode":"33133",
    "addr:street":"Sw 27Th Terrace",
    "iso:country":"US",
    "sg:address":"3321 SW 27th Terrace",
    "sg:city":"Miami",
    "sg:classifiers":[
        {
            "category":"Shopping",
            "subcategory":"Pets & Pet Supplies",
            "type":"Retail Goods"
        },
        {
            "category":"Retail",
            "subcategory":"Pet Boarding",
            "type":"Services"
        }
    ],
    "sg:phone":"+1 305 569 9433",
    "sg:postcode":"33133",
    "sg:province":"FL",
    "sg:tags":[
        "walker",
        "dog",
        "boarding/pet",
        "sitting"
    ],
    "sg:website":"www.poochandkittycare.com",
    "wof:name":"Pooch & Kitty Care Service, Inc",
    "wof:placetype":"venue"
},
  "geometry": {"coordinates":[-80.248448,25.74087],"type":"Point"}
}