{
  "type": "Feature",
  "properties": {
    "addr:full":"1001 Bluebird Ave Miami Springs FL 33166",
    "addr:housenumber":"1001",
    "addr:postcode":"33166",
    "addr:street":"Bluebird Ave",
    "iso:country":"US",
    "sg:address":"1001 Bluebird Ave",
    "sg:city":"Miami Springs",
    "sg:classifiers":[
        {
            "category":"Professional",
            "subcategory":"Advertising",
            "type":"Services"
        }
    ],
    "sg:phone":"+1 305 883 6464",
    "sg:postcode":"33166",
    "sg:province":"FL",
    "sg:tags":[
        "counselor",
        "agency"
    ],
    "wof:name":"Bodner Advertising",
    "wof:placetype":"venue"
},
  "geometry": {"coordinates":[-80.300074,25.833547],"type":"Point"}
}