{
  "type": "Feature",
  "properties": {
    "iso:country":"US",
    "sg:address":"156 Tuskawilla Rd Ste 2326",
    "sg:city":"Winter Springs",
    "sg:classifiers":[
        {
            "category":"Professional",
            "subcategory":"Lawyer & Legal Services",
            "type":"Services"
        },
        {
            "category":"Banks & Credit Unions",
            "subcategory":"Financial Services",
            "type":"Services"
        }
    ],
    "sg:phone":"+1 800 978 8813",
    "sg:postcode":"32708",
    "sg:province":"FL",
    "sg:tags":[
        "notary"
    ],
    "sg:website":"www.birchellins.com",
    "wof:name":"Birchell Insurance Agency",
    "wof:placetype":"venue"
},
  "geometry": {"coordinates":[-81.262818,28.695935],"type":"Point"}
}