{
  "type": "Feature",
  "properties": {
    "iso:country":"US",
    "sg:address":"8949 Cherrystone Ln",
    "sg:city":"Orlando",
    "sg:classifiers":[
        {
            "category":"Professional",
            "type":"Services"
        }
    ],
    "sg:phone":"+1 407 382 4485",
    "sg:postcode":"32825",
    "sg:province":"FL",
    "sg:tags":[
        "restaurant"
    ],
    "wof:name":"Dragon Fishing Co Inc",
    "wof:placetype":"venue"
},
  "geometry": {"coordinates":[-81.254424,28.555437],"type":"Point"}
}