{
  "type": "Feature",
  "properties": {
    "iso:country":"US",
    "sg:address":"2807 Center Court Dr",
    "sg:city":"Weston",
    "sg:classifiers":[
        {
            "category":"Wholesale",
            "subcategory":"Durable Goods & Equipment",
            "type":"Manufacturing & Wholesale Goods"
        }
    ],
    "sg:phone":"+1 954 217 9132",
    "sg:postcode":"33332",
    "sg:province":"FL",
    "sg:tags":[
        "importer"
    ],
    "wof:name":"Starland International Inc",
    "wof:placetype":"venue"
},
  "geometry": {"coordinates":[-80.39306000000001,26.094667],"type":"Point"}
}