{
  "type": "Feature",
  "properties": {
    "iso:country":"US",
    "sg:address":"3509 S Longfellow Cir",
    "sg:city":"Hollywood",
    "sg:classifiers":[
        {
            "category":"Real Estate",
            "subcategory":"Real Estate Operator",
            "type":"Services"
        }
    ],
    "sg:phone":"+1 954 964 7804",
    "sg:postcode":"33021",
    "sg:province":"FL",
    "sg:tags":[
        "apartment",
        "rental"
    ],
    "wof:name":"Cesar Montalvo",
    "wof:placetype":"venue"
},
  "geometry": {"coordinates":[-80.180851,26.024225],"type":"Point"}
}