{
  "type": "Feature",
  "properties": {
    "addr:full":"2419 Flamingo Ln Fort Lauderdale FL 33312",
    "addr:housenumber":"2419",
    "addr:postcode":"33312",
    "addr:street":"Flamingo Ln",
    "iso:country":"US",
    "sg:address":"2419 Flamingo Ln",
    "sg:city":"Fort Lauderdale",
    "sg:classifiers":[
        {
            "category":"Professional",
            "subcategory":"Computer Services",
            "type":"Services"
        }
    ],
    "sg:phone":"+1 954 797 2519",
    "sg:postcode":"33312",
    "sg:province":"FL",
    "sg:tags":[
        "programming",
        "system",
        "analysis"
    ],
    "wof:name":"Squawk Software Inc",
    "wof:placetype":"venue"
},
  "geometry": {"coordinates":[-80.191637,26.087866],"type":"Point"}
}