{
  "type": "Feature",
  "properties": {
    "iso:country":"US",
    "sg:address":"1900 McNab Ave",
    "sg:city":"Delray Beach",
    "sg:classifiers":[
        {
            "category":"Building & Trades",
            "subcategory":"Plumbing",
            "type":"Services"
        }
    ],
    "sg:phone":"+1 561 278 7125",
    "sg:postcode":"33444",
    "sg:province":"FL",
    "sg:tags":[
        "conditioning",
        "air",
        "system",
        "contractor"
    ],
    "sg:website":"www.climatecontrolservices.com",
    "wof:name":"Climate Control Svc Co",
    "wof:placetype":"venue"
},
  "geometry": {"coordinates":[-80.092913,26.460353],"type":"Point"}
}