{
  "type": "Feature",
  "properties": {
    "iso:country":"US",
    "sg:address":"5368 International Dr",
    "sg:city":"Orlando",
    "sg:classifiers":[
        {
            "category":"Shopping",
            "subcategory":"Clothing, Apparel, & Fashions",
            "type":"Retail Goods"
        }
    ],
    "sg:phone":"+1 407 354 3644",
    "sg:postcode":"32819",
    "sg:province":"FL",
    "wof:name":"Divers Outlet",
    "wof:placetype":"venue"
},
  "geometry": {"coordinates":[-81.451418,28.462523],"type":"Point"}
}