{
  "type": "Feature",
  "properties": {
    "addr:full":"1933 Northgate Blvd Sarasota FL 34234",
    "addr:housenumber":"1933",
    "addr:postcode":"34234",
    "addr:street":"Northgate Blvd",
    "iso:country":"US",
    "sg:address":"1933 Northgate Blvd",
    "sg:city":"Sarasota",
    "sg:classifiers":[
        {
            "category":"Shopping",
            "type":"Retail Goods"
        },
        {
            "category":"Professional",
            "subcategory":"Business Services",
            "type":"Services"
        }
    ],
    "sg:phone":"+1 941 929 9523",
    "sg:postcode":"34234",
    "sg:province":"FL",
    "wof:name":"Clear Voice Communication",
    "wof:placetype":"venue"
},
  "geometry": {"coordinates":[-82.531752,27.372178],"type":"Point"}
}