{
  "type": "Feature",
  "properties": {
    "iso:country":"US",
    "sg:address":"7235 Coral Way Ste 201",
    "sg:city":"Miami",
    "sg:classifiers":[
        {
            "category":"Health Services",
            "subcategory":"Doctor",
            "type":"Services"
        }
    ],
    "sg:phone":"+1 305 260 9602",
    "sg:postcode":"33155",
    "sg:province":"FL",
    "sg:tags":[
        "practice",
        "family"
    ],
    "wof:name":"H & T Benazet",
    "wof:placetype":"venue"
},
  "geometry": {"coordinates":[-80.312302,25.748199],"type":"Point"}
}