{
  "type": "Feature",
  "properties": {
    "addr:full":"400 E Wright St Pensacola FL 32501",
    "addr:housenumber":"400",
    "addr:postcode":"32501",
    "addr:street":"E Wright St",
    "iso:country":"US",
    "sg:address":"400 E Wright St",
    "sg:city":"Pensacola",
    "sg:classifiers":[
        {
            "category":"Personal",
            "type":"Services"
        }
    ],
    "sg:phone":"+1 850 434 3272",
    "sg:postcode":"32501",
    "sg:province":"FL",
    "wof:name":"Mighty Mudsharks",
    "wof:placetype":"venue"
},
  "geometry": {"coordinates":[-87.210977,30.417581],"type":"Point"}
}