{
  "type": "Feature",
  "properties": {
    "iso:country":"US",
    "sg:address":"814 Water Oaks Dr SW",
    "sg:city":"Winter Haven",
    "sg:classifiers":[
        {
            "category":"Retail",
            "subcategory":"Repair Shop",
            "type":"Services"
        }
    ],
    "sg:phone":"+1 863 324 9393",
    "sg:postcode":"33880",
    "sg:province":"FL",
    "sg:tags":[
        "appliance"
    ],
    "wof:name":"Ackenback Appliance Svc",
    "wof:placetype":"venue"
},
  "geometry": {"coordinates":[-81.72500599999999,27.969011],"type":"Point"}
}