{
  "type": "Feature",
  "properties": {
    "addr:full":"1801 Heim Rd Mt Dora FL 32757",
    "addr:housenumber":"1801",
    "addr:postcode":"32757",
    "addr:street":"Heim Rd",
    "iso:country":"US",
    "sg:address":"1801 Heim Rd",
    "sg:city":"Mt Dora",
    "sg:classifiers":[
        {
            "category":"Retail",
            "subcategory":"Auto Repair",
            "type":"Services"
        }
    ],
    "sg:phone":"+1 352 383 4444",
    "sg:postcode":"32757",
    "sg:province":"FL",
    "sg:tags":[
        "repairing",
        "automobile",
        "radiator"
    ],
    "wof:name":"Vroom Service",
    "wof:placetype":"venue"
},
  "geometry": {"coordinates":[-81.657843,28.807077],"type":"Point"}
}