{
  "type": "Feature",
  "properties": {
    "iso:country":"US",
    "sg:address":"1988 Wells Rd",
    "sg:city":"Orange Park",
    "sg:classifiers":[
        {
            "category":"Home & Garden",
            "subcategory":"Building Materials",
            "type":"Retail Goods"
        }
    ],
    "sg:phone":"+1 904 272 8884",
    "sg:postcode":"32073",
    "sg:province":"FL",
    "sg:tags":[
        "lumber"
    ],
    "sg:website":"www.84lumber.com",
    "wof:name":"84 Lumber Co",
    "wof:placetype":"venue"
},
  "geometry": {"coordinates":[-81.732737,30.186854],"type":"Point"}
}