{
  "type": "Feature",
  "properties": {
    "iso:country":"US",
    "sg:address":"3313 NE 32nd St",
    "sg:city":"Fort Lauderdale",
    "sg:classifiers":[
        {
            "category":"Real Estate",
            "subcategory":"Real Estate Agent",
            "type":"Services"
        }
    ],
    "sg:phone":"+1 954 563 1490",
    "sg:postcode":"33308",
    "sg:province":"FL",
    "wof:name":"Royal Palm Realty Group",
    "wof:placetype":"venue"
},
  "geometry": {"coordinates":[-80.10044000000001,26.168548],"type":"Point"}
}