{
  "type": "Feature",
  "properties": {
    "addr:full":"550 N Bumby Ave Orlando FL 32803",
    "addr:housenumber":"550",
    "addr:postcode":"32803",
    "addr:street":"N Bumby Ave",
    "iso:country":"US",
    "sg:address":"550 N Bumby Ave",
    "sg:city":"Orlando",
    "sg:classifiers":[
        {
            "category":"Wholesale",
            "subcategory":"Medical Equipment & Supplies",
            "type":"Manufacturing & Wholesale Goods"
        },
        {
            "category":"Health Services",
            "subcategory":"Clinic",
            "type":"Services"
        }
    ],
    "sg:phone":"+1 407 898 6577",
    "sg:postcode":"32803",
    "sg:province":"FL",
    "sg:tags":[
        "physician",
        "surgeon"
    ],
    "wof:name":"Bontan Medical Corporation",
    "wof:placetype":"venue"
},
  "geometry": {"coordinates":[-81.35208900000001,28.55107],"type":"Point"}
}