{
  "type": "Feature",
  "properties": {
    "iso:country":"US",
    "sg:address":"7224 60th Ave N",
    "sg:city":"Saint Petersburg",
    "sg:classifiers":[
        {
            "category":"Shopping",
            "subcategory":"Clothing, Apparel, & Fashions",
            "type":"Retail Goods"
        }
    ],
    "sg:phone":"+1 727 544 1287",
    "sg:postcode":"33709",
    "sg:province":"FL",
    "wof:name":"Just ME Painting",
    "wof:placetype":"venue"
},
  "geometry": {"coordinates":[-82.738174,27.825946],"type":"Point"}
}