{
  "type": "Feature",
  "properties": {
    "iso:country":"US",
    "sg:address":"4122 Gunn Hwy",
    "sg:city":"Tampa",
    "sg:classifiers":[
        {
            "category":"Retail",
            "subcategory":"Auto Repair",
            "type":"Services"
        }
    ],
    "sg:phone":"+1 813 963 0680",
    "sg:postcode":"33618",
    "sg:province":"FL",
    "sg:tags":[
        "repairing",
        "automobile"
    ],
    "wof:name":"National Auto Svc Ctr",
    "wof:placetype":"venue"
},
  "geometry": {"coordinates":[-82.510992,28.041864],"type":"Point"}
}