{
  "type": "Feature",
  "properties": {
    "iso:country":"US",
    "sg:address":"1803 Stella Ct N",
    "sg:city":"Lakeland",
    "sg:classifiers":[
        {
            "category":"Building & Trades",
            "subcategory":"Plumbing",
            "type":"Services"
        }
    ],
    "sg:phone":"+1 863 648 1668",
    "sg:postcode":"33813",
    "sg:province":"FL",
    "sg:tags":[
        "contractor"
    ],
    "wof:name":"St Jean Brothers AC & Htg",
    "wof:placetype":"venue"
},
  "geometry": {"coordinates":[-81.93071,27.979704],"type":"Point"}
}