{
  "type": "Feature",
  "properties": {
    "iso:country":"US",
    "sg:address":"10101 Chemstrand Rd",
    "sg:city":"Pensacola",
    "sg:classifiers":[
        {
            "category":"Travel",
            "subcategory":"Campground",
            "type":"Entertainment"
        }
    ],
    "sg:phone":"+1 850 969 0669",
    "sg:postcode":"32514",
    "sg:province":"FL",
    "sg:tags":[
        "trailer"
    ],
    "wof:name":"Soundside Properties",
    "wof:placetype":"venue"
},
  "geometry": {"coordinates":[-87.26227900000001,30.542476],"type":"Point"}
}