{
  "type": "Feature",
  "properties": {
    "iso:country":"US",
    "sg:address":"550 Bus Park Way",
    "sg:city":"Royal Palm Beach",
    "sg:classifiers":[
        {
            "category":"Home & Garden",
            "subcategory":"Furniture",
            "type":"Retail Goods"
        }
    ],
    "sg:phone":"+1 561 790 3368",
    "sg:postcode":"33411",
    "sg:province":"FL",
    "sg:tags":[
        "builder",
        "custom"
    ],
    "wof:name":"Cherokee Cabinets",
    "wof:placetype":"venue"
},
  "geometry": {"coordinates":[-80.203137,26.69933],"type":"Point"}
}