{
  "type": "Feature",
  "properties": {
    "addr:full":"1801 S 23rd St Fort Pierce FL 34950",
    "addr:housenumber":"1801",
    "addr:postcode":"34950",
    "addr:street":"S 23Rd St",
    "iso:country":"US",
    "sg:address":"1801 S 23rd St",
    "sg:city":"Fort Pierce",
    "sg:classifiers":[
        {
            "category":"Health Services",
            "subcategory":"Doctor",
            "type":"Services"
        }
    ],
    "sg:phone":"+1 772 465 5600",
    "sg:postcode":"34950",
    "sg:province":"FL",
    "sg:tags":[
        "physician",
        "surgeon"
    ],
    "wof:name":"Peter R Aldana MD",
    "wof:placetype":"venue"
},
  "geometry": {"coordinates":[-80.34735000000001,27.429554],"type":"Point"}
}