{
  "type": "Feature",
  "properties": {
    "iso:country":"US",
    "sg:address":"260 E Haines Blvd",
    "sg:city":"Lake Alfred",
    "sg:classifiers":[
        {
            "category":"Professional",
            "subcategory":"Management & Consulting",
            "type":"Services"
        }
    ],
    "sg:phone":"+1 863 956 4182",
    "sg:postcode":"33850",
    "sg:province":"FL",
    "sg:tags":[
        "consultant",
        "business"
    ],
    "wof:name":"Recreation Consultant",
    "wof:placetype":"venue"
},
  "geometry": {"coordinates":[-81.727557,28.091943],"type":"Point"}
}