{
  "type": "Feature",
  "properties": {
    "iso:country":"US",
    "sg:address":"4708 L B Mcleod Rd",
    "sg:city":"Orlando",
    "sg:classifiers":[
        {
            "category":"Professional",
            "subcategory":"Management & Consulting",
            "type":"Services"
        },
        {
            "category":"Professional",
            "subcategory":"Employment Agencies",
            "type":"Services"
        },
        {
            "category":"Social Services",
            "subcategory":"Adult Care",
            "type":"Services"
        }
    ],
    "sg:phone":"+1 407 872 0888",
    "sg:postcode":"32811",
    "sg:province":"FL",
    "sg:tags":[
        "consultant",
        "counselor",
        "resource",
        "human",
        "relation"
    ],
    "wof:name":"ABC Interactive",
    "wof:placetype":"venue"
},
  "geometry": {"coordinates":[-81.441581,28.507438],"type":"Point"}
}