{
  "type": "Feature",
  "properties": {
    "iso:country":"US",
    "sg:address":"6296 Via Palladium",
    "sg:city":"Boca Raton",
    "sg:classifiers":[
        {
            "category":"Restaurant",
            "type":"Food & Drink"
        }
    ],
    "sg:phone":"+1 561 361 7811",
    "sg:postcode":"33433",
    "sg:province":"FL",
    "sg:tags":[
        "eating"
    ],
    "wof:name":"Dorrians Afternoon Tea LLC",
    "wof:placetype":"venue"
},
  "geometry": {"coordinates":[-80.14209,26.336032],"type":"Point"}
}