{
  "type": "Feature",
  "properties": {
    "addr:full":"419 US Hwy 19 Palatka FL 32177",
    "addr:housenumber":"419",
    "addr:postcode":"32177",
    "addr:street":"Us Hwy 19",
    "iso:country":"US",
    "sg:address":"419 US Hwy 19",
    "sg:city":"Palatka",
    "sg:classifiers":[
        {
            "category":"Home & Garden",
            "subcategory":"Furniture",
            "type":"Retail Goods"
        }
    ],
    "sg:phone":"+1 386 328 4638",
    "sg:postcode":"32177",
    "sg:province":"FL",
    "wof:name":"Farmers Furniture",
    "wof:placetype":"venue"
},
  "geometry": {"coordinates":[-81.670102,29.65546],"type":"Point"}
}