{
  "type": "Feature",
  "properties": {
    "addr:full":"7203 Lake Marsha Dr Orlando FL 32819",
    "addr:housenumber":"7203",
    "addr:postcode":"32819",
    "addr:street":"Lake Marsha Dr",
    "iso:country":"US",
    "sg:address":"7203 Lake Marsha Dr",
    "sg:city":"Orlando",
    "sg:classifiers":[
        {
            "category":"Wholesale",
            "subcategory":"Electrical",
            "type":"Manufacturing & Wholesale Goods"
        }
    ],
    "sg:phone":"+1 407 354 1539",
    "sg:postcode":"32819",
    "sg:province":"FL",
    "sg:tags":[
        "electronic"
    ],
    "wof:name":"Jesico Trading Co",
    "wof:placetype":"venue"
},
  "geometry": {"coordinates":[-81.479444,28.482811],"type":"Point"}
}