{
  "type": "Feature",
  "properties": {
    "iso:country":"US",
    "sg:address":"8970 103rd St",
    "sg:city":"Jacksonville",
    "sg:classifiers":[
        {
            "category":"Recreation",
            "type":"Entertainment"
        }
    ],
    "sg:phone":"+1 904 778 2348",
    "sg:postcode":"32210",
    "sg:province":"FL",
    "wof:name":"First Coast Tae Kwondo",
    "wof:placetype":"venue"
},
  "geometry": {"coordinates":[-81.80131799999999,30.247532],"type":"Point"}
}