{
  "type": "Feature",
  "properties": {
    "addr:full":"11610 Quail Roost Dr Miami FL 33157",
    "addr:housenumber":"11610",
    "addr:postcode":"33157",
    "addr:street":"Quail Roost Dr",
    "iso:country":"US",
    "sg:address":"11610 Quail Roost Dr",
    "sg:city":"Miami",
    "sg:classifiers":[
        {
            "category":"Building & Trades",
            "subcategory":"Locksmith",
            "type":"Services"
        }
    ],
    "sg:phone":"+1 786 228 5626",
    "sg:postcode":"33157",
    "sg:province":"FL",
    "sg:tags":[
        "key"
    ],
    "wof:name":"Miami Always Affective Available Emergency Locksmith",
    "wof:placetype":"venue"
},
  "geometry": {"coordinates":[-80.379965,25.591725],"type":"Point"}
}