{
  "type": "Feature",
  "properties": {
    "iso:country":"US",
    "sg:address":"210 N Congress Ave",
    "sg:city":"Delray Beach",
    "sg:classifiers":[
        {
            "category":"Retail",
            "subcategory":"Auto Repair",
            "type":"Services"
        }
    ],
    "sg:phone":"+1 561 265 3444",
    "sg:postcode":"33445",
    "sg:province":"FL",
    "sg:tags":[
        "automotive",
        "general"
    ],
    "wof:name":"Congress Auto Service",
    "wof:placetype":"venue"
},
  "geometry": {"coordinates":[-80.09360100000001,26.466943],"type":"Point"}
}