{
  "type": "Feature",
  "properties": {
    "addr:full":"3407 Dunbar Dr Sarasota FL 34232",
    "addr:housenumber":"3407",
    "addr:postcode":"34232",
    "addr:street":"Dunbar Dr",
    "iso:country":"US",
    "sg:address":"3407 Dunbar Dr",
    "sg:city":"Sarasota",
    "sg:classifiers":[
        {
            "category":"Building & Trades",
            "subcategory":"Construction",
            "type":"Services"
        }
    ],
    "sg:phone":"+1 941 371 8989",
    "sg:postcode":"34232",
    "sg:province":"FL",
    "sg:tags":[
        "contractor"
    ],
    "wof:name":"Globe Painting Waterproof",
    "wof:placetype":"venue"
},
  "geometry": {"coordinates":[-82.482958,27.304209],"type":"Point"}
}