{
  "type": "Feature",
  "properties": {
    "addr:full":"4040 Central Florida Pkwy Orlando FL 32837",
    "addr:housenumber":"4040",
    "addr:postcode":"32837",
    "addr:street":"Central Florida Pkwy",
    "iso:country":"US",
    "sg:address":"4040 Central Florida Pkwy",
    "sg:city":"Orlando",
    "sg:classifiers":[
        {
            "category":"Retail",
            "subcategory":"Auto Rental",
            "type":"Services"
        }
    ],
    "sg:phone":"+1 407 393 4888",
    "sg:postcode":"32837",
    "sg:province":"FL",
    "sg:tags":[
        "renting",
        "automobile"
    ],
    "wof:name":"Hertz Rent A Car",
    "wof:placetype":"venue"
},
  "geometry": {"coordinates":[-81.428011,28.410224],"type":"Point"}
}