{
  "type": "Feature",
  "properties": {
    "iso:country":"US",
    "sg:address":"2825 SE 17th St",
    "sg:city":"Ocala",
    "sg:classifiers":[
        {
            "category":"Health Services",
            "subcategory":"Doctor",
            "type":"Services"
        }
    ],
    "sg:phone":"+1 352 620 0094",
    "sg:postcode":"34471",
    "sg:province":"FL",
    "sg:tags":[
        "dentist"
    ],
    "wof:name":"Lawrence J Sutton DDS",
    "wof:placetype":"venue"
},
  "geometry": {"coordinates":[-82.097741,29.171603],"type":"Point"}
}