{
  "type": "Feature",
  "properties": {
    "addr:full":"5727 SW 25th St Hollywood FL 33023",
    "addr:housenumber":"5727",
    "addr:postcode":"33023",
    "addr:street":"Sw 25Th St",
    "iso:country":"US",
    "sg:address":"5727 SW 25th St",
    "sg:city":"Hollywood",
    "sg:classifiers":[
        {
            "category":"Manufacturing",
            "subcategory":"Tools & Machinery",
            "type":"Manufacturing & Wholesale Goods"
        }
    ],
    "sg:phone":"+1 954 893 8644",
    "sg:postcode":"33023",
    "sg:province":"FL",
    "sg:tags":[
        "electric",
        "supply"
    ],
    "sg:website":"www.electricdepot.net",
    "wof:name":"Electric Depot",
    "wof:placetype":"venue"
},
  "geometry": {"coordinates":[-80.201463,25.987911],"type":"Point"}
}