{
  "type": "Feature",
  "properties": {
    "addr:full":"131 N Moon Ave Brandon FL 33510",
    "addr:housenumber":"131",
    "addr:postcode":"33510",
    "addr:street":"N Moon Ave",
    "iso:country":"US",
    "sg:address":"131 N Moon Ave",
    "sg:city":"Brandon",
    "sg:classifiers":[
        {
            "category":"Health Services",
            "subcategory":"Health Practitioner",
            "type":"Services"
        }
    ],
    "sg:phone":"+1 813 977 2677",
    "sg:postcode":"33510",
    "sg:province":"FL",
    "sg:tags":[
        "acupuncture"
    ],
    "wof:name":"Integrative Medicine Ctr",
    "wof:placetype":"venue"
},
  "geometry": {"coordinates":[-82.288252,27.939303],"type":"Point"}
}