{
  "type": "Feature",
  "properties": {
    "addr:full":"200 SW 15th St Fort Lauderdale FL 33315",
    "addr:housenumber":"200",
    "addr:postcode":"33315",
    "addr:street":"Sw 15Th St",
    "iso:country":"US",
    "sg:address":"200 SW 15th St",
    "sg:city":"Fort Lauderdale",
    "sg:classifiers":[
        {
            "category":"Freight",
            "type":"Transportation"
        }
    ],
    "sg:phone":"+1 954 767 8064",
    "sg:postcode":"33315",
    "sg:province":"FL",
    "sg:tags":[
        "commercial",
        "storage"
    ],
    "wof:name":"Croissant Park Self Storage",
    "wof:placetype":"venue"
},
  "geometry": {"coordinates":[-80.146958,26.102845],"type":"Point"}
}