{
  "type": "Feature",
  "properties": {
    "addr:full":"16500 Collins Ave Miami FL 33160",
    "addr:housenumber":"16500",
    "addr:postcode":"33160",
    "addr:street":"Collins Ave",
    "iso:country":"US",
    "sg:address":"16500 Collins Ave",
    "sg:city":"Miami",
    "sg:classifiers":[
        {
            "category":"Organizations",
            "subcategory":"Professional Association",
            "type":"Services"
        }
    ],
    "sg:phone":"+1 305 944 8233",
    "sg:postcode":"33160",
    "sg:province":"FL",
    "sg:tags":[
        "business"
    ],
    "wof:name":"Cham Leung Investment LLC",
    "wof:placetype":"venue"
},
  "geometry": {"coordinates":[-80.122249,25.927868],"type":"Point"}
}