{
  "type": "Feature",
  "properties": {
    "iso:country":"US",
    "sg:address":"2810 NW 10th St",
    "sg:city":"Ocala",
    "sg:classifiers":[
        {
            "category":"Home & Garden",
            "subcategory":"Mobile Homes",
            "type":"Retail Goods"
        }
    ],
    "sg:phone":"+1 352 351 1999",
    "sg:postcode":"34475",
    "sg:province":"FL",
    "wof:name":"Southern Comfort Mobile Hm Ctr",
    "wof:placetype":"venue"
},
  "geometry": {"coordinates":[-82.16976,29.197062],"type":"Point"}
}