{
  "type": "Feature",
  "properties": {
    "iso:country":"US",
    "sg:address":"2331 Sandlewood Dr",
    "sg:city":"Venice",
    "sg:classifiers":[
        {
            "category":"Real Estate",
            "subcategory":"Real Estate Agent",
            "type":"Services"
        }
    ],
    "sg:phone":"+1 941 408 8233",
    "sg:postcode":"34293",
    "sg:province":"FL",
    "sg:tags":[
        "inspection"
    ],
    "wof:name":"S & S House Detectives Inc",
    "wof:placetype":"venue"
},
  "geometry": {"coordinates":[-82.40666899999999,27.069384],"type":"Point"}
}