{
  "type": "Feature",
  "properties": {
    "addr:full":"7827 NW 44th St Lauderhill FL 33351",
    "addr:housenumber":"7827",
    "addr:postcode":"33351",
    "addr:street":"Nw 44Th St",
    "iso:country":"US",
    "sg:address":"7827 NW 44th St",
    "sg:city":"Lauderhill",
    "sg:classifiers":[
        {
            "category":"Shopping",
            "subcategory":"Gifts & Souvenirs",
            "type":"Retail Goods"
        }
    ],
    "sg:phone":"+1 954 749 2082",
    "sg:postcode":"33351",
    "sg:province":"FL",
    "sg:tags":[
        "shop"
    ],
    "wof:name":"20-1 Odds & Ends",
    "wof:placetype":"venue"
},
  "geometry": {"coordinates":[-80.25333500000001,26.179161],"type":"Point"}
}