{
  "type": "Feature",
  "properties": {
    "addr:full":"1783 S Ridgewood Ave South Daytona FL 32119",
    "addr:housenumber":"1783",
    "addr:postcode":"32119",
    "addr:street":"S Ridgewood Ave South",
    "iso:country":"US",
    "sg:address":"1783 S Ridgewood Ave",
    "sg:city":"South Daytona",
    "sg:classifiers":[
        {
            "category":"Utilities",
            "subcategory":"Mobile Phone",
            "type":"Services"
        }
    ],
    "sg:phone":"+1 386 767 7763",
    "sg:postcode":"32119",
    "sg:province":"FL",
    "sg:tags":[
        "telephone",
        "cellular"
    ],
    "sg:website":"www.maycomwireless.com",
    "wof:name":"May Com Communications",
    "wof:placetype":"venue"
},
  "geometry": {"coordinates":[-81.00453899999999,29.17646],"type":"Point"}
}