{
  "type": "Feature",
  "properties": {
    "addr:full":"7815 Charney Ln Boca Raton FL 33496",
    "addr:housenumber":"7815",
    "addr:postcode":"33496",
    "addr:street":"Charney Ln",
    "iso:country":"US",
    "sg:address":"7815 Charney Ln",
    "sg:city":"Boca Raton",
    "sg:classifiers":[
        {
            "category":"Professional",
            "type":"Services"
        }
    ],
    "sg:phone":"+1 561 488 4002",
    "sg:postcode":"33496",
    "sg:province":"FL",
    "wof:name":"Texcon Inc",
    "wof:placetype":"venue"
},
  "geometry": {"coordinates":[-80.166839,26.414548],"type":"Point"}
}