{
  "type": "Feature",
  "properties": {
    "iso:country":"US",
    "sg:address":"30800 Bermont Rd",
    "sg:city":"Punta Gorda",
    "sg:classifiers":[
        {
            "category":"Building & Trades",
            "subcategory":"Construction",
            "type":"Services"
        }
    ],
    "sg:phone":"+1 941 637 1035",
    "sg:postcode":"33982",
    "sg:province":"FL",
    "sg:tags":[
        "fill",
        "contractor"
    ],
    "wof:name":"Desrosiers Brothers Ents",
    "wof:placetype":"venue"
},
  "geometry": {"coordinates":[-81.94497200000001,26.946906],"type":"Point"}
}