{
  "type": "Feature",
  "properties": {
    "addr:full":"7070 College Pkwy Ste 1 Fort Myers FL 33907",
    "addr:housenumber":"7070",
    "addr:postcode":"myers fl 33907",
    "addr:street":"College Pkwy Ste 1",
    "iso:country":"US",
    "sg:address":"7070 College Pkwy Ste 1",
    "sg:city":"Fort Myers",
    "sg:classifiers":[
        {
            "category":"Food & Beverages",
            "subcategory":"Groceries & Convenience Stores",
            "type":"Retail Goods"
        }
    ],
    "sg:phone":"+1 239 369 2149",
    "sg:postcode":"33907",
    "sg:province":"FL",
    "wof:name":"Publix Super Markets",
    "wof:placetype":"venue"
},
  "geometry": {"coordinates":[-81.873497,26.5564],"type":"Point"}
}