{
  "type": "Feature",
  "properties": {
    "addr:full":"1045 S 78th St Tampa FL 33619",
    "addr:housenumber":"1045",
    "addr:postcode":"33619",
    "addr:street":"S 78Th St",
    "iso:country":"US",
    "sg:address":"1045 S 78th St",
    "sg:city":"Tampa",
    "sg:classifiers":[
        {
            "category":"Organizations",
            "subcategory":"Religious Organization",
            "type":"Services"
        }
    ],
    "sg:phone":"+1 813 626 8905",
    "sg:postcode":"33619",
    "sg:province":"FL",
    "sg:tags":[
        "church"
    ],
    "wof:name":"Keeney United Methodist Church",
    "wof:placetype":"venue"
},
  "geometry": {"coordinates":[-82.368735,27.938347],"type":"Point"}
}