{
  "type": "Feature",
  "properties": {
    "addr:full":"1025 Stoeber Ave Sarasota FL 34232",
    "addr:housenumber":"1025",
    "addr:postcode":"34232",
    "addr:street":"Stoeber Ave",
    "iso:country":"US",
    "sg:address":"1025 Stoeber Ave",
    "sg:city":"Sarasota",
    "sg:classifiers":[
        {
            "category":"Shopping",
            "subcategory":"Used Merchandise",
            "type":"Retail Goods"
        }
    ],
    "sg:phone":"+1 941 953 7944",
    "sg:postcode":"34232",
    "sg:province":"FL",
    "sg:tags":[
        "heating",
        "air",
        "also",
        "conditioner",
        "rebuilt",
        "unit"
    ],
    "wof:name":"Mechanical Rebuilders Inc",
    "wof:placetype":"venue"
},
  "geometry": {"coordinates":[-82.45674699999999,27.344511],"type":"Point"}
}