{
  "type": "Feature",
  "properties": {
    "iso:country":"US",
    "sg:address":"103 N Orange St",
    "sg:city":"New Smyrna Beach",
    "sg:classifiers":[
        {
            "category":"Professional",
            "subcategory":"Employment Agencies",
            "type":"Services"
        }
    ],
    "sg:phone":"+1 386 427 5557",
    "sg:postcode":"32168",
    "sg:province":"FL",
    "sg:tags":[
        "leasing",
        "help",
        "supply"
    ],
    "wof:name":"Garriques & Assoc Employee Lsg",
    "wof:placetype":"venue"
},
  "geometry": {"coordinates":[-80.925944,29.025085],"type":"Point"}
}