{
  "type": "Feature",
  "properties": {
    "addr:full":"614 N State Rd 7 Hollywood FL 33021",
    "addr:housenumber":"614;7",
    "addr:postcode":"33021",
    "addr:street":"N State Rd",
    "iso:country":"US",
    "sg:address":"614 N State Rd 7",
    "sg:city":"Hollywood",
    "sg:classifiers":[
        {
            "category":"Autos & Motor Vehicles",
            "subcategory":"Automobile Sales",
            "type":"Retail Goods"
        }
    ],
    "sg:phone":"+1 954 962 3715",
    "sg:postcode":"33021",
    "sg:province":"FL",
    "sg:tags":[
        "repair",
        "general"
    ],
    "wof:name":"Foreign Car Center",
    "wof:placetype":"venue"
},
  "geometry": {"coordinates":[-80.207913,26.015705],"type":"Point"}
}