{
  "type": "Feature",
  "properties": {
    "iso:country":"US",
    "sg:address":"6718 N Himes Ave",
    "sg:city":"Tampa",
    "sg:classifiers":[
        {
            "category":"Banks & Credit Unions",
            "subcategory":"Bank",
            "type":"Services"
        }
    ],
    "sg:phone":"+1 561 498 4330",
    "sg:postcode":"33614",
    "sg:province":"FL",
    "sg:tags":[
        "loan",
        "real estate"
    ],
    "wof:name":"Primary Residential Mortgage",
    "wof:placetype":"venue"
},
  "geometry": {"coordinates":[-82.500913,28.007817],"type":"Point"}
}