{
  "type": "Feature",
  "properties": {
    "addr:full":"2717 Scott St Hollywood FL 33020",
    "addr:housenumber":"2717",
    "addr:postcode":"33020",
    "addr:street":"Scott St",
    "iso:country":"US",
    "sg:address":"2717 Scott St",
    "sg:city":"Hollywood",
    "sg:classifiers":[
        {
            "category":"Real Estate",
            "subcategory":"Real Estate Agent",
            "type":"Services"
        }
    ],
    "sg:phone":"+1 954 922 3220",
    "sg:postcode":"33020",
    "sg:province":"FL",
    "wof:name":"Della International",
    "wof:placetype":"venue"
},
  "geometry": {"coordinates":[-80.164025,26.029626],"type":"Point"}
}