{
  "type": "Feature",
  "properties": {
    "addr:full":"3809 Sandstone Ct New Smyrna Beach FL 32169",
    "addr:housenumber":"3809",
    "addr:postcode":"32169",
    "addr:street":"Sandstone Ct",
    "iso:country":"US",
    "sg:address":"3809 Sandstone Ct",
    "sg:city":"New Smyrna Beach",
    "sg:classifiers":[
        {
            "category":"Building & Trades",
            "subcategory":"Construction",
            "type":"Services"
        }
    ],
    "sg:phone":"+1 386 689 1248",
    "sg:postcode":"32169",
    "sg:province":"FL",
    "sg:tags":[
        "layer",
        "carpet"
    ],
    "wof:name":"Darryl's Carpet & Tile",
    "wof:placetype":"venue"
},
  "geometry": {"coordinates":[-80.878165,29.004436],"type":"Point"}
}