{
  "type": "Feature",
  "properties": {
    "addr:full":"22 SE 4th St Boca Raton FL 33432",
    "addr:housenumber":"22",
    "addr:postcode":"33432",
    "addr:street":"Se 4Th St",
    "iso:country":"US",
    "sg:address":"22 SE 4th St",
    "sg:city":"Boca Raton",
    "sg:classifiers":[
        {
            "category":"Professional",
            "subcategory":"Advertising",
            "type":"Services"
        }
    ],
    "sg:phone":"+1 561 392 2805",
    "sg:postcode":"33432",
    "sg:province":"FL",
    "sg:tags":[
        "mailing",
        "shipping"
    ],
    "wof:name":"Mail Box Intl",
    "wof:placetype":"venue"
},
  "geometry": {"coordinates":[-80.086583,26.346107],"type":"Point"}
}