{
  "type": "Feature",
  "properties": {
    "iso:country":"US",
    "sg:address":"1450 S Lake Shipp Dr",
    "sg:city":"Winter Haven",
    "sg:classifiers":[
        {
            "category":"Food & Beverages",
            "subcategory":"Groceries & Convenience Stores",
            "type":"Retail Goods"
        }
    ],
    "sg:phone":"+1 863 299 2662",
    "sg:postcode":"33880",
    "sg:province":"FL",
    "wof:name":"Fine Food",
    "wof:placetype":"venue"
},
  "geometry": {"coordinates":[-81.74220099999999,27.997002],"type":"Point"}
}