{
  "type": "Feature",
  "properties": {
    "addr:full":"2724 Del Prado Blvd S Fl 1 Cape Coral FL 33904",
    "addr:housenumber":"2724;1",
    "addr:postcode":"33904",
    "addr:street":"Del Prado Blvd S Fl",
    "iso:country":"US",
    "sg:address":"2724 Del Prado Blvd S Fl 1",
    "sg:city":"Cape Coral",
    "sg:classifiers":[
        {
            "category":"Banks & Credit Unions",
            "subcategory":"Bank",
            "type":"Services"
        }
    ],
    "sg:phone":"+1 239 573 2201",
    "sg:postcode":"33904",
    "sg:province":"FL",
    "sg:website":"www.53.com",
    "wof:name":"Fifth Third Bank",
    "wof:placetype":"venue"
},
  "geometry": {"coordinates":[-81.941641,26.601434],"type":"Point"}
}