{
  "type": "Feature",
  "properties": {
    "addr:full":"3813 Oakwater Cir Orlando FL 32806",
    "addr:housenumber":"3813",
    "addr:postcode":"32806",
    "addr:street":"Oakwater Cir",
    "iso:country":"US",
    "sg:address":"3813 Oakwater Cir",
    "sg:city":"Orlando",
    "sg:classifiers":[
        {
            "category":"Health Services",
            "subcategory":"Doctor",
            "type":"Services"
        }
    ],
    "sg:phone":"+1 407 856 7226",
    "sg:postcode":"32806",
    "sg:province":"FL",
    "sg:tags":[
        "medical"
    ],
    "wof:name":"Pediatric Cardiology Cons PA",
    "wof:placetype":"venue"
},
  "geometry": {"coordinates":[-81.375846,28.500537],"type":"Point"}
}