{
  "type": "Feature",
  "properties": {
    "iso:country":"US",
    "sg:address":"4014 Tamiami Trl",
    "sg:city":"Sarasota",
    "sg:classifiers":[
        {
            "category":"Travel",
            "subcategory":"Hotels & Motels",
            "type":"Entertainment"
        }
    ],
    "sg:phone":"+1 941 355 4764",
    "sg:postcode":"34234",
    "sg:province":"FL",
    "wof:name":"Allamanda Motel",
    "wof:placetype":"venue"
},
  "geometry": {"coordinates":[-82.552559,27.370003],"type":"Point"}
}