{
  "type": "Feature",
  "properties": {
    "iso:country":"US",
    "sg:address":"6719 Gall Blvd",
    "sg:city":"Zephyrhills",
    "sg:classifiers":[
        {
            "category":"Health Services",
            "subcategory":"Doctor",
            "type":"Services"
        },
        {
            "category":"Health Services",
            "subcategory":"Health Practitioner",
            "type":"Services"
        }
    ],
    "sg:phone":"+1 813 783 1223",
    "sg:postcode":"33542",
    "sg:province":"FL",
    "sg:tags":[
        "physician",
        "ophthalmology",
        "surgeons",
        "surgeon"
    ],
    "wof:name":"Vitreous Retina Consultants",
    "wof:placetype":"venue"
},
  "geometry": {"coordinates":[-82.18821699999999,28.25556],"type":"Point"}
}