{
  "type": "Feature",
  "properties": {
    "iso:country":"US",
    "sg:address":"3500 N US Hwy 1",
    "sg:city":"Rockledge",
    "sg:classifiers":[
        {
            "category":"Food & Beverages",
            "subcategory":"Specialty",
            "type":"Retail Goods"
        }
    ],
    "sg:phone":"+1 321 631 1194",
    "sg:postcode":"32955",
    "sg:province":"FL",
    "sg:tags":[
        "store"
    ],
    "wof:name":"Mango Mrs & Co",
    "wof:placetype":"venue"
},
  "geometry": {"coordinates":[-80.699793,28.294268],"type":"Point"}
}