{
  "type": "Feature",
  "properties": {
    "addr:full":"4433 Englewood Ave Jacksonville FL 32207",
    "addr:housenumber":"4433",
    "addr:postcode":"32207",
    "addr:street":"Englewood Ave",
    "iso:country":"US",
    "sg:address":"4433 Englewood Ave",
    "sg:city":"Jacksonville",
    "sg:classifiers":[
        {
            "category":"Manufacturing",
            "subcategory":"Printing",
            "type":"Manufacturing & Wholesale Goods"
        }
    ],
    "sg:phone":"+1 904 731 3355",
    "sg:postcode":"32207",
    "sg:province":"FL",
    "sg:tags":[
        "screen"
    ],
    "wof:name":"Precision Screen Printing",
    "wof:placetype":"venue"
},
  "geometry": {"coordinates":[-81.61975700000001,30.278177],"type":"Point"}
}