{
  "type": "Feature",
  "properties": {
    "iso:country":"US",
    "sg:address":"7450 Reformation Rd",
    "sg:city":"Milton",
    "sg:classifiers":[
        {
            "category":"Building & Trades",
            "subcategory":"Plumbing",
            "type":"Services"
        }
    ],
    "sg:phone":"+1 850 626 8456",
    "sg:postcode":"32583",
    "sg:province":"FL",
    "sg:tags":[
        "contractor"
    ],
    "wof:name":"Eric Johnson Plumbing",
    "wof:placetype":"venue"
},
  "geometry": {"coordinates":[-87.011139,30.61128],"type":"Point"}
}