{
  "type": "Feature",
  "properties": {
    "addr:full":"12221 34th St N St Petersburg FL 33716",
    "addr:housenumber":"12221",
    "addr:postcode":"33716",
    "addr:street":"34Th St N",
    "iso:country":"US",
    "sg:address":"12221 34th St N",
    "sg:city":"St Petersburg",
    "sg:classifiers":[
        {
            "category":"Retail",
            "subcategory":"Auto Rental",
            "type":"Services"
        }
    ],
    "sg:phone":"+1 727 573 5080",
    "sg:postcode":"33716",
    "sg:province":"FL",
    "sg:tags":[
        "renting",
        "truck",
        "leasing"
    ],
    "sg:website":"www.penske.com",
    "wof:name":"Penske Truck Leasing",
    "wof:placetype":"venue"
},
  "geometry": {"coordinates":[-82.679802,27.885571],"type":"Point"}
}