{
  "type": "Feature",
  "properties": {
    "addr:full":"7820 SW 164th St Miami FL 33157",
    "addr:housenumber":"7820",
    "addr:postcode":"33157",
    "addr:street":"Sw 164Th St",
    "iso:country":"US",
    "sg:address":"7820 SW 164th St",
    "sg:city":"Miami",
    "sg:classifiers":[
        {
            "category":"Professional",
            "subcategory":"Management & Consulting",
            "type":"Services"
        }
    ],
    "sg:phone":"+1 305 235 4227",
    "sg:postcode":"33157",
    "sg:province":"FL",
    "sg:tags":[
        "business"
    ],
    "wof:name":"V&K Services Inc",
    "wof:placetype":"venue"
},
  "geometry": {"coordinates":[-80.322378,25.618276],"type":"Point"}
}