{
  "type": "Feature",
  "properties": {
    "addr:full":"2343 US Hwy 231 Panama City FL 32405",
    "addr:housenumber":"2343",
    "addr:postcode":"32405",
    "addr:street":"Us Hwy 231",
    "iso:country":"US",
    "sg:address":"2343 US Hwy 231",
    "sg:city":"Panama City",
    "sg:classifiers":[
        {
            "category":"Real Estate",
            "subcategory":"Real Estate Agent",
            "type":"Services"
        }
    ],
    "sg:phone":"+1 850 769 2448",
    "sg:postcode":"32405",
    "sg:province":"FL",
    "wof:name":"Simmons Real Estate",
    "wof:placetype":"venue"
},
  "geometry": {"coordinates":[-85.63233,30.195739],"type":"Point"}
}