{
  "type": "Feature",
  "properties": {
    "iso:country":"US",
    "sg:address":"620 SE 23rd Ln",
    "sg:city":"Homestead",
    "sg:classifiers":[
        {
            "category":"Insurance",
            "subcategory":"Insurance Agent",
            "type":"Services"
        }
    ],
    "sg:phone":"+1 305 270 1828",
    "sg:postcode":"33033",
    "sg:province":"FL",
    "sg:tags":[
        "accident"
    ],
    "wof:name":"Michael Andalman",
    "wof:placetype":"venue"
},
  "geometry": {"coordinates":[-80.443911,25.463265],"type":"Point"}
}