{
  "type": "Feature",
  "properties": {
    "iso:country":"US",
    "sg:address":"8351 Parkline Blvd",
    "sg:city":"Orlando",
    "sg:classifiers":[
        {
            "category":"Autos & Motor Vehicles",
            "subcategory":"Automobile Sales",
            "type":"Retail Goods"
        }
    ],
    "sg:phone":"+1 407 857 9784",
    "sg:postcode":"32809",
    "sg:province":"FL",
    "wof:name":"Chrysler Training Center",
    "wof:placetype":"venue"
},
  "geometry": {"coordinates":[-81.36323,28.44701],"type":"Point"}
}