{
  "type": "Feature",
  "properties": {
    "addr:full":"2548 N State Rd 7 Hollywood FL 33021",
    "addr:housenumber":"2548;7",
    "addr:postcode":"33021",
    "addr:street":"N State Rd",
    "iso:country":"US",
    "sg:address":"2548 N State Rd 7",
    "sg:city":"Hollywood",
    "sg:classifiers":[
        {
            "category":"Professional",
            "subcategory":"Advertising",
            "type":"Services"
        }
    ],
    "sg:phone":"+1 954 964 8585",
    "sg:postcode":"33021",
    "sg:province":"FL",
    "wof:name":"Promotional Innovative Adverti",
    "wof:placetype":"venue"
},
  "geometry": {"coordinates":[-80.208528,26.033903],"type":"Point"}
}