{
  "type": "Feature",
  "properties": {
    "iso:country":"US",
    "sg:address":"21464 Woodchuck Way",
    "sg:city":"Boca Raton",
    "sg:classifiers":[
        {
            "category":"Farming",
            "subcategory":"Farm & Veterinary Services",
            "type":"Manufacturing & Wholesale Goods"
        }
    ],
    "sg:phone":"+1 561 482 0082",
    "sg:postcode":"33428",
    "sg:province":"FL",
    "sg:tags":[
        "cotton",
        "ginning"
    ],
    "wof:name":"Gin Productions Incorporated",
    "wof:placetype":"venue"
},
  "geometry": {"coordinates":[-80.224932,26.356579],"type":"Point"}
}