{
  "type": "Feature",
  "properties": {
    "iso:country":"US",
    "sg:address":"3300 Cortez Rd W",
    "sg:city":"Bradenton",
    "sg:classifiers":[
        {
            "category":"Home & Garden",
            "subcategory":"Furniture",
            "type":"Retail Goods"
        },
        {
            "category":"Wholesale",
            "subcategory":"Furniture",
            "type":"Manufacturing & Wholesale Goods"
        },
        {
            "category":"Home & Garden",
            "subcategory":"Carpets & Floor Coverings",
            "type":"Retail Goods"
        }
    ],
    "sg:phone":"+1 941 755 2697",
    "sg:postcode":"34207",
    "sg:province":"FL",
    "sg:tags":[
        "manufacturer",
        "store",
        "furniture-wholesale",
        "mattress"
    ],
    "sg:website":"http://www.la-z-boy.com",
    "wof:name":"La-Z-Boy Furniture Galleries",
    "wof:placetype":"venue"
},
  "geometry": {"coordinates":[-82.594566,27.462509],"type":"Point"}
}