{
  "type": "Feature",
  "properties": {
    "addr:full":"303 Oakwood Ct Lake Mary FL 32746",
    "addr:housenumber":"303",
    "addr:postcode":"32746",
    "addr:street":"Oakwood Ct",
    "iso:country":"US",
    "sg:address":"303 Oakwood Ct",
    "sg:city":"Lake Mary",
    "sg:classifiers":[
        {
            "category":"Building & Trades",
            "subcategory":"Construction",
            "type":"Services"
        }
    ],
    "sg:phone":"+1 407 323 6163",
    "sg:postcode":"32746",
    "sg:province":"FL",
    "sg:tags":[
        "contractor"
    ],
    "wof:name":"Clarity Pools",
    "wof:placetype":"venue"
},
  "geometry": {"coordinates":[-81.31306499999999,28.737267],"type":"Point"}
}