{
  "type": "Feature",
  "properties": {
    "addr:full":"577 Crystal Dr Saint Petersburg FL 33708",
    "addr:housenumber":"577",
    "addr:postcode":"33708",
    "addr:street":"Crystal Dr",
    "iso:country":"US",
    "sg:address":"577 Crystal Dr",
    "sg:city":"Saint Petersburg",
    "sg:classifiers":[
        {
            "category":"Autos & Motor Vehicles",
            "subcategory":"Automobile Sales",
            "type":"Retail Goods"
        }
    ],
    "sg:phone":"+1 727 393 1733",
    "sg:postcode":"33708",
    "sg:province":"FL",
    "wof:name":"Mark Raper",
    "wof:placetype":"venue"
},
  "geometry": {"coordinates":[-82.782523,27.800185],"type":"Point"}
}