{
  "type": "Feature",
  "properties": {
    "iso:country":"US",
    "sg:address":"175 Houle Ave",
    "sg:city":"Sarasota",
    "sg:classifiers":[
        {
            "category":"Building & Trades",
            "subcategory":"Cleaning & Sanitation",
            "type":"Services"
        }
    ],
    "sg:phone":"+1 941 378 5054",
    "sg:postcode":"34232",
    "sg:province":"FL",
    "sg:tags":[
        "maintenance"
    ],
    "wof:name":"Maintenance Systems of US",
    "wof:placetype":"venue"
},
  "geometry": {"coordinates":[-82.470285,27.338879],"type":"Point"}
}