{
  "type": "Feature",
  "properties": {
    "iso:country":"US",
    "sg:address":"5401 W Waters Ave",
    "sg:city":"Tampa",
    "sg:classifiers":[
        {
            "category":"Banks & Credit Unions",
            "subcategory":"Bank",
            "type":"Services"
        }
    ],
    "sg:phone":"+1 813 872 1350",
    "sg:postcode":"33634",
    "sg:province":"FL",
    "wof:name":"Bank Of Tampa",
    "wof:placetype":"venue"
},
  "geometry": {"coordinates":[-82.53590699999999,28.025572],"type":"Point"}
}