{
  "type": "Feature",
  "properties": {
    "addr:full":"1700 Barefoot Williams Rd Naples FL 34113",
    "addr:housenumber":"1700",
    "addr:postcode":"34113",
    "addr:street":"Barefoot Williams Rd",
    "iso:country":"US",
    "sg:address":"1700 Barefoot Williams Rd",
    "sg:city":"Naples",
    "sg:classifiers":[
        {
            "category":"Travel",
            "subcategory":"Campground",
            "type":"Entertainment"
        }
    ],
    "sg:phone":"+1 239 774 5455",
    "sg:postcode":"34113",
    "sg:province":"FL",
    "sg:website":"www.napleskoa.com",
    "wof:name":"KOA Kampground-Naples/Marco",
    "wof:placetype":"venue"
},
  "geometry": {"coordinates":[-81.70925099999999,26.049611],"type":"Point"}
}