{
  "type": "Feature",
  "properties": {
    "iso:country":"US",
    "sg:address":"3372 NW Federal Hwy",
    "sg:city":"Jensen Beach",
    "sg:classifiers":[
        {
            "category":"Shopping",
            "subcategory":"Computers & Home Electronics",
            "type":"Retail Goods"
        }
    ],
    "sg:phone":"+1 772 692 0991",
    "sg:postcode":"34957",
    "sg:province":"FL",
    "sg:tags":[
        "game",
        "video",
        "software"
    ],
    "wof:name":"Electronics Boutique",
    "wof:placetype":"venue"
},
  "geometry": {"coordinates":[-80.26923499999999,27.237145],"type":"Point"}
}