{
  "type": "Feature",
  "properties": {
    "addr:full":"1000 N Ashley Dr Tampa FL 33602",
    "addr:housenumber":"1000",
    "addr:postcode":"33602",
    "addr:street":"N Ashley Dr",
    "iso:country":"US",
    "sg:address":"1000 N Ashley Dr",
    "sg:city":"Tampa",
    "sg:classifiers":[
        {
            "category":"Organizations",
            "subcategory":"Non-profit Organization",
            "type":"Services"
        }
    ],
    "sg:phone":"+1 813 233 2920",
    "sg:postcode":"33602",
    "sg:province":"FL",
    "sg:tags":[
        "disability"
    ],
    "wof:name":"Advocacy Center For Persons",
    "wof:placetype":"venue"
},
  "geometry": {"coordinates":[-82.46222299999999,27.952779],"type":"Point"}
}