{
  "type": "Feature",
  "properties": {
    "iso:country":"US",
    "sg:address":"2330 SW Williston Rd",
    "sg:city":"Gainesville",
    "sg:classifiers":[
        {
            "category":"Professional",
            "type":"Services"
        }
    ],
    "sg:phone":"+1 352 367 2490",
    "sg:postcode":"32608",
    "sg:province":"FL",
    "sg:tags":[
        "establishment"
    ],
    "wof:name":"Renaissance Butterflies I",
    "wof:placetype":"venue"
},
  "geometry": {"coordinates":[-82.35504899999999,29.613578],"type":"Point"}
}