{
  "type": "Feature",
  "properties": {
    "iso:country":"US",
    "sg:address":"3550 Ermine Path",
    "sg:city":"Palm Harbor",
    "sg:classifiers":[
        {
            "category":"Building & Trades",
            "subcategory":"Construction",
            "type":"Services"
        }
    ],
    "sg:phone":"+1 727 787 6289",
    "sg:postcode":"34684",
    "sg:province":"FL",
    "sg:tags":[
        "fence",
        "contractor"
    ],
    "wof:name":"A Lifeguard Pool Fence Systs",
    "wof:placetype":"venue"
},
  "geometry": {"coordinates":[-82.716421,28.07117],"type":"Point"}
}