{
  "type": "Feature",
  "properties": {
    "addr:full":"14165 SW Hwy 484 Dunnellon FL 34432",
    "addr:housenumber":"14165",
    "addr:postcode":"34432",
    "addr:street":"Sw Hwy 484",
    "iso:country":"US",
    "sg:address":"14165 SW Hwy 484",
    "sg:city":"Dunnellon",
    "sg:classifiers":[
        {
            "category":"Building & Trades",
            "subcategory":"Construction",
            "type":"Services"
        }
    ],
    "sg:phone":"+1 352 465 2116",
    "sg:postcode":"34432",
    "sg:province":"FL",
    "sg:tags":[
        "painter"
    ],
    "wof:name":"Birchfield's Painting Inc",
    "wof:placetype":"venue"
},
  "geometry": {"coordinates":[-82.354972,29.053551],"type":"Point"}
}