{
  "type": "Feature",
  "properties": {
    "addr:full":"408 SW Sycamore Dr Port St Lucie FL 34986",
    "addr:housenumber":"408",
    "addr:postcode":"34986",
    "addr:street":"Sw Sycamore Dr",
    "iso:country":"US",
    "sg:address":"408 SW Sycamore Dr",
    "sg:city":"Port St Lucie",
    "sg:classifiers":[
        {
            "category":"Freight",
            "type":"Transportation"
        }
    ],
    "sg:phone":"+1 772 871 9696",
    "sg:postcode":"34986",
    "sg:province":"FL",
    "sg:tags":[
        "mover"
    ],
    "wof:name":"Able To Move & Store Inc",
    "wof:placetype":"venue"
},
  "geometry": {"coordinates":[-80.392312,27.299052],"type":"Point"}
}