{
  "type": "Feature",
  "properties": {
    "iso:country":"US",
    "sg:address":"3160 W Hallandale Beach Blvd",
    "sg:city":"Hallandale",
    "sg:classifiers":[
        {
            "category":"Shopping",
            "subcategory":"Gifts & Souvenirs",
            "type":"Retail Goods"
        }
    ],
    "sg:phone":"+1 954 981 8100",
    "sg:postcode":"33009",
    "sg:province":"FL",
    "sg:tags":[
        "basket",
        "parcel"
    ],
    "wof:name":"Discount Flowers & Gifts",
    "wof:placetype":"venue"
},
  "geometry": {"coordinates":[-80.17180399999999,25.984842],"type":"Point"}
}