{
  "type": "Feature",
  "properties": {
    "addr:full":"609 E Central Blvd Orlando FL 32801",
    "addr:housenumber":"609",
    "addr:postcode":"32801",
    "addr:street":"E Central Blvd",
    "iso:country":"US",
    "sg:address":"609 E Central Blvd",
    "sg:city":"Orlando",
    "sg:classifiers":[
        {
            "category":"Professional",
            "subcategory":"Lawyer & Legal Services",
            "type":"Services"
        }
    ],
    "sg:phone":"+1 407 648 0020",
    "sg:postcode":"32801",
    "sg:province":"FL",
    "sg:tags":[
        "attorney"
    ],
    "wof:name":"Michael H Gibson",
    "wof:placetype":"venue"
},
  "geometry": {"coordinates":[-81.368549,28.542368],"type":"Point"}
}