{
  "type": "Feature",
  "properties": {
    "iso:country":"US",
    "sg:address":"1262 S Highland Ave",
    "sg:city":"Clearwater",
    "sg:classifiers":[
        {
            "category":"Food & Beverages",
            "subcategory":"Bakery",
            "type":"Retail Goods"
        }
    ],
    "sg:phone":"+1 727 446 1937",
    "sg:postcode":"33756",
    "sg:province":"FL",
    "wof:name":"Cinco Damayo Bakery",
    "wof:placetype":"venue"
},
  "geometry": {"coordinates":[-82.775218,27.950228],"type":"Point"}
}