{
  "type": "Feature",
  "properties": {
    "addr:full":"7061 State Rd 21 Keystone Heights FL 32656",
    "addr:housenumber":"7061;21",
    "addr:postcode":"32656",
    "addr:street":"State Rd;Heights",
    "iso:country":"US",
    "sg:address":"7061 State Rd 21",
    "sg:city":"Keystone Heights",
    "sg:classifiers":[
        {
            "category":"Bars & Pubs",
            "type":"Food & Drink"
        }
    ],
    "sg:phone":"+1 352 473 6892",
    "sg:postcode":"32656",
    "sg:province":"FL",
    "sg:tags":[
        "lounge",
        "cocktail"
    ],
    "wof:name":"Our Town Tavern",
    "wof:placetype":"venue"
},
  "geometry": {"coordinates":[-82.009427,29.808765],"type":"Point"}
}