{
  "type": "Feature",
  "properties": {
    "iso:country":"US",
    "sg:address":"6005 N Wickham Rd",
    "sg:city":"Melbourne",
    "sg:classifiers":[
        {
            "category":"Building & Trades",
            "subcategory":"Pest Control",
            "type":"Services"
        }
    ],
    "sg:phone":"+1 321 951 0444",
    "sg:postcode":"32940",
    "sg:province":"FL",
    "wof:name":"Universal Pest Svc Inc",
    "wof:placetype":"venue"
},
  "geometry": {"coordinates":[-80.67364499999999,28.216061],"type":"Point"}
}