{
  "type": "Feature",
  "properties": {
    "addr:full":"1321 77th St E Palmetto FL 34221",
    "addr:housenumber":"1321",
    "addr:postcode":"34221",
    "addr:street":"77Th St E",
    "iso:country":"US",
    "sg:address":"1321 77th St E",
    "sg:city":"Palmetto",
    "sg:classifiers":[
        {
            "category":"Building & Trades",
            "subcategory":"Construction",
            "type":"Services"
        }
    ],
    "sg:phone":"+1 727 894 6239",
    "sg:postcode":"34221",
    "sg:province":"FL",
    "sg:tags":[
        "steel",
        "repair",
        "erection",
        "mfg",
        "hardware",
        "welding",
        "structural"
    ],
    "wof:name":"Bay Machine Inc",
    "wof:placetype":"venue"
},
  "geometry": {"coordinates":[-82.55109400000001,27.582892],"type":"Point"}
}