{
  "type": "Feature",
  "properties": {
    "iso:country":"US",
    "sg:address":"512 NE 26th St",
    "sg:city":"Wilton Manors",
    "sg:classifiers":[
        {
            "category":"Organizations",
            "subcategory":"Religious Organization",
            "type":"Services"
        }
    ],
    "sg:phone":"+1 954 563 5784",
    "sg:postcode":"33305",
    "sg:province":"FL",
    "sg:tags":[
        "church"
    ],
    "wof:name":"Covenant Presbyterian Church",
    "wof:placetype":"venue"
},
  "geometry": {"coordinates":[-80.13839900000001,26.159287],"type":"Point"}
}