{
  "type": "Feature",
  "properties": {
    "addr:full":"15121 Tyler St Miami FL 33176",
    "addr:housenumber":"15121",
    "addr:postcode":"33176",
    "addr:street":"Tyler St",
    "iso:country":"US",
    "sg:address":"15121 Tyler St",
    "sg:city":"Miami",
    "sg:classifiers":[
        {
            "category":"Building & Trades",
            "subcategory":"Construction",
            "type":"Services"
        }
    ],
    "sg:phone":"+1 786 573 3161",
    "sg:postcode":"33176",
    "sg:province":"FL",
    "sg:tags":[
        "system",
        "contractor",
        "air conditioning"
    ],
    "wof:name":"Dream Enterprise Inc",
    "wof:placetype":"venue"
},
  "geometry": {"coordinates":[-80.371362,25.628458],"type":"Point"}
}