{
  "type": "Feature",
  "properties": {
    "iso:country":"US",
    "sg:address":"1161 SW 74th Ter",
    "sg:city":"Plantation",
    "sg:classifiers":[
        {
            "category":"Professional",
            "subcategory":"Art Services",
            "type":"Services"
        },
        {
            "category":"Professional",
            "subcategory":"Business Services",
            "type":"Services"
        }
    ],
    "sg:phone":"+1 954 791 1911",
    "sg:postcode":"33317",
    "sg:province":"FL",
    "sg:tags":[
        "development",
        "product",
        "designer",
        "designers-industrial",
        "marketing",
        "commercial",
        "design",
        "interior",
        "decorator"
    ],
    "wof:name":"Matthew Michael Interiors Inc",
    "wof:placetype":"venue"
},
  "geometry": {"coordinates":[-80.247156,26.106249],"type":"Point"}
}