{
  "type": "Feature",
  "properties": {
    "iso:country":"US",
    "sg:address":"487 Cox Rd",
    "sg:city":"Monticello",
    "sg:classifiers":[
        {
            "category":"Building & Trades",
            "subcategory":"Electrical",
            "type":"Services"
        }
    ],
    "sg:phone":"+1 850 973 0672",
    "sg:postcode":"32344",
    "sg:province":"FL",
    "sg:tags":[
        "electric",
        "contractor"
    ],
    "wof:name":"Bass Electrical Svc Of Madison",
    "wof:placetype":"venue"
},
  "geometry": {"coordinates":[-83.861885,30.578944],"type":"Point"}
}