{
  "type": "Feature",
  "properties": {
    "iso:country":"US",
    "sg:address":"591 NE 42nd Ct",
    "sg:city":"Fort Lauderdale",
    "sg:classifiers":[
        {
            "category":"Manufacturing",
            "subcategory":"Apparel",
            "type":"Manufacturing & Wholesale Goods"
        }
    ],
    "sg:phone":"+1 954 564 1033",
    "sg:postcode":"33334",
    "sg:province":"FL",
    "sg:tags":[
        "repair",
        "household",
        "furnishing",
        "mfg"
    ],
    "wof:name":"Gator Vinyl Repair & Uphl",
    "wof:placetype":"venue"
},
  "geometry": {"coordinates":[-80.140576,26.179206],"type":"Point"}
}