{
  "type": "Feature",
  "properties": {
    "iso:country":"US",
    "sg:address":"2119 10th Ave N",
    "sg:city":"Lake Worth",
    "sg:classifiers":[
        {
            "category":"Organizations",
            "subcategory":"Religious Organization",
            "type":"Services"
        }
    ],
    "sg:phone":"+1 561 969 9009",
    "sg:postcode":"33461",
    "sg:province":"FL",
    "sg:tags":[
        "church"
    ],
    "sg:website":"www.believersvictory.com",
    "wof:name":"Believers Victory Church Inc",
    "wof:placetype":"venue"
},
  "geometry": {"coordinates":[-80.07361,26.627952],"type":"Point"}
}