{
  "type": "Feature",
  "properties": {
    "iso:country":"US",
    "sg:address":"3201 NW 4th Ter",
    "sg:city":"Pompano Beach",
    "sg:classifiers":[
        {
            "category":"Wholesale",
            "subcategory":"Seafood",
            "type":"Manufacturing & Wholesale Goods"
        }
    ],
    "sg:phone":"+1 954 933 9828",
    "sg:postcode":"33064",
    "sg:province":"FL",
    "wof:name":"Sailfish Seafood",
    "wof:placetype":"venue"
},
  "geometry": {"coordinates":[-80.12964700000001,26.270288],"type":"Point"}
}