{
  "type": "Feature",
  "properties": {
    "addr:full":"9130 S Dadeland Blvd Dadeland Centre II, Suite 1010 Miami FL 33156",
    "addr:housenumber":"9130;suite 1010",
    "addr:postcode":"33156",
    "addr:street":"S Dadeland Blvd",
    "iso:country":"US",
    "sg:address":"9130 S Dadeland Blvd Dadeland Centre II, Suite 1010",
    "sg:city":"Miami",
    "sg:classifiers":[
        {
            "category":"Professional",
            "subcategory":"Lawyer & Legal Services",
            "type":"Services"
        }
    ],
    "sg:phone":"+1 305 670 1800",
    "sg:postcode":"33156",
    "sg:province":"FL",
    "sg:website":"www.duilawdefense.com",
    "wof:name":"Jonathan Blecher, Criminal Defense DUI Lawyer",
    "wof:placetype":"venue"
},
  "geometry": {"coordinates":[-80.314132,25.685662],"type":"Point"}
}