{
  "type": "Feature",
  "properties": {
    "addr:full":"7129 Curtiss Ave Sarasota FL 34231",
    "addr:housenumber":"7129",
    "addr:postcode":"34231",
    "addr:street":"Curtiss Ave",
    "iso:country":"US",
    "sg:address":"7129 Curtiss Ave",
    "sg:city":"Sarasota",
    "sg:classifiers":[
        {
            "category":"Health Services",
            "subcategory":"Doctor",
            "type":"Services"
        }
    ],
    "sg:phone":"+1 941 921 5208",
    "sg:postcode":"34231",
    "sg:province":"FL",
    "sg:tags":[
        "cardiology"
    ],
    "wof:name":"Pradeep V P",
    "wof:placetype":"venue"
},
  "geometry": {"coordinates":[-82.499218,27.251801],"type":"Point"}
}