{
  "type": "Feature",
  "properties": {
    "iso:country":"US",
    "sg:address":"1224 Palm Ridge Rd",
    "sg:city":"Sanibel",
    "sg:classifiers":[
        {
            "category":"Autos & Motor Vehicles",
            "subcategory":"Fuel & Gas Station",
            "type":"Retail Goods"
        }
    ],
    "sg:phone":"+1 800 889 5870",
    "sg:postcode":"33957",
    "sg:province":"FL",
    "sg:website":"http://www.hess.com",
    "wof:name":"Hess Corporation",
    "wof:placetype":"venue"
},
  "geometry": {"coordinates":[-82.076897,26.4365],"type":"Point"}
}