{
  "type": "Feature",
  "properties": {
    "addr:full":"8424 Lockwood Ridge Rd Sarasota FL 34243",
    "addr:housenumber":"8424",
    "addr:postcode":"34243",
    "addr:street":"Lockwood Ridge Rd",
    "iso:country":"US",
    "sg:address":"8424 Lockwood Ridge Rd",
    "sg:city":"Sarasota",
    "sg:classifiers":[
        {
            "category":"Food & Beverages",
            "subcategory":"Specialty",
            "type":"Retail Goods"
        },
        {
            "category":"Food & Beverages",
            "subcategory":"Fruits & Vegetables",
            "type":"Retail Goods"
        },
        {
            "category":"Shopping",
            "subcategory":"Pharmacy",
            "type":"Retail Goods"
        }
    ],
    "sg:phone":"+1 941 359 3779",
    "sg:postcode":"34243",
    "sg:province":"FL",
    "sg:tags":[
        "product",
        "wellness",
        "vitamin",
        "diet",
        "supplement",
        "health",
        "herb"
    ],
    "sg:website":"http://www.gnc.com",
    "wof:name":"GNC",
    "wof:placetype":"venue"
},
  "geometry": {"coordinates":[-82.50561399999999,27.389784],"type":"Point"}
}