{
  "type": "Feature",
  "properties": {
    "iso:country":"US",
    "sg:address":"640 NW 183rd St",
    "sg:city":"Miami",
    "sg:classifiers":[
        {
            "category":"Health Services",
            "subcategory":"Doctor",
            "type":"Services"
        }
    ],
    "sg:phone":"+1 305 655 2333",
    "sg:postcode":"33169",
    "sg:province":"FL",
    "sg:tags":[
        "medicine",
        "internal"
    ],
    "wof:name":"Unihealth of South Florida",
    "wof:placetype":"venue"
},
  "geometry": {"coordinates":[-80.2118,25.942301],"type":"Point"}
}