{
  "type": "Feature",
  "properties": {
    "addr:full":"335 Havendale Blvd Auburndale FL 33823",
    "addr:housenumber":"335",
    "addr:postcode":"33823",
    "addr:street":"Havendale Blvd",
    "iso:country":"US",
    "sg:address":"335 Havendale Blvd",
    "sg:city":"Auburndale",
    "sg:classifiers":[
        {
            "category":"Professional",
            "subcategory":"Business Services",
            "type":"Services"
        }
    ],
    "sg:phone":"+1 863 551 9299",
    "sg:postcode":"33823",
    "sg:province":"FL",
    "sg:tags":[
        "embroidery"
    ],
    "wof:name":"L & K Discount Uniforms",
    "wof:placetype":"venue"
},
  "geometry": {"coordinates":[-81.781808,28.057721],"type":"Point"}
}