{
  "type": "Feature",
  "properties": {
    "iso:country":"US",
    "sg:address":"2611 Cedar Bluff Ln",
    "sg:city":"Ocoee",
    "sg:classifiers":[
        {
            "category":"Professional",
            "subcategory":"Business Services",
            "type":"Services"
        }
    ],
    "sg:phone":"+1 407 295 9174",
    "sg:postcode":"34761",
    "sg:province":"FL",
    "sg:tags":[
        "interior",
        "consultant",
        "design",
        "decorator"
    ],
    "wof:name":"Valerie Walchek Designs",
    "wof:placetype":"venue"
},
  "geometry": {"coordinates":[-81.502793,28.57879],"type":"Point"}
}