{
  "type": "Feature",
  "properties": {
    "addr:full":"1524 SE 3rd Ave Fort Lauderdale FL 33316",
    "addr:housenumber":"1524",
    "addr:postcode":"33316",
    "addr:street":"Se 3Rd Ave",
    "iso:country":"US",
    "sg:address":"1524 SE 3rd Ave",
    "sg:city":"Fort Lauderdale",
    "sg:classifiers":[
        {
            "category":"Health Services",
            "subcategory":"Doctor",
            "type":"Services"
        }
    ],
    "sg:phone":"+1 954 763 6188",
    "sg:postcode":"33316",
    "sg:province":"FL",
    "sg:tags":[
        "medical"
    ],
    "wof:name":"Videona Bautista MD",
    "wof:placetype":"venue"
},
  "geometry": {"coordinates":[-80.139734,26.10265],"type":"Point"}
}