{
  "type": "Feature",
  "properties": {
    "iso:country":"US",
    "sg:address":"3500 Mystic Pointe Dr",
    "sg:city":"Aventura",
    "sg:classifiers":[
        {
            "category":"Building & Trades",
            "subcategory":"Locksmith",
            "type":"Services"
        }
    ],
    "sg:phone":"+1 305 407 1441",
    "sg:postcode":"33180",
    "sg:province":"FL",
    "sg:tags":[
        "key"
    ],
    "wof:name":"A-1 Locksmith",
    "wof:placetype":"venue"
},
  "geometry": {"coordinates":[-80.12917899999999,25.953313],"type":"Point"}
}