{
  "type": "Feature",
  "properties": {
    "addr:full":"420 Lincoln Rd Ste 225 Miami Beach FL 33139",
    "addr:housenumber":"420",
    "addr:postcode":"33139",
    "addr:street":"Lincoln Rd Ste 225",
    "iso:country":"US",
    "sg:address":"420 Lincoln Rd Ste 225",
    "sg:city":"Miami Beach",
    "sg:classifiers":[
        {
            "category":"Real Estate",
            "subcategory":"Real Estate Operator",
            "type":"Services"
        },
        {
            "category":"Real Estate",
            "subcategory":"Real Estate Agent",
            "type":"Services"
        }
    ],
    "sg:phone":"+1 305 502 1717",
    "sg:postcode":"33139",
    "sg:province":"FL",
    "sg:tags":[
        "apartment"
    ],
    "sg:website":"www.stuartdrossner.com",
    "wof:name":"Stuart Drossner",
    "wof:placetype":"venue"
},
  "geometry": {"coordinates":[-80.132507,25.790292],"type":"Point"}
}