{
  "type": "Feature",
  "properties": {
    "iso:country":"US",
    "sg:address":"175 Fontainebleau Blvd Ste 2G10",
    "sg:city":"Miami",
    "sg:classifiers":[
        {
            "category":"Banks & Credit Unions",
            "subcategory":"Financial Services",
            "type":"Services"
        }
    ],
    "sg:phone":"+1 305 228 8887",
    "sg:postcode":"33172",
    "sg:province":"FL",
    "sg:tags":[
        "broker",
        "mortgage"
    ],
    "wof:name":"Pronto Realty",
    "wof:placetype":"venue"
},
  "geometry": {"coordinates":[-80.33880000000001,25.770703],"type":"Point"}
}