{
  "type": "Feature",
  "properties": {
    "iso:country":"US",
    "sg:address":"801 W 49th St",
    "sg:city":"Hialeah",
    "sg:classifiers":[
        {
            "category":"Health Services",
            "subcategory":"Medical Lab",
            "type":"Services"
        }
    ],
    "sg:phone":"+1 305 822 6134",
    "sg:postcode":"33012",
    "sg:province":"FL",
    "sg:tags":[
        "laboratory",
        "dental"
    ],
    "wof:name":"Carmelo Dental Lab Inc",
    "wof:placetype":"venue"
},
  "geometry": {"coordinates":[-80.30341799999999,25.866647],"type":"Point"}
}