{
  "type": "Feature",
  "properties": {
    "addr:full":"600 Diamond Cir Naples FL 34110",
    "addr:housenumber":"600",
    "addr:postcode":"34110",
    "addr:street":"Diamond Cir",
    "iso:country":"US",
    "sg:address":"600 Diamond Cir",
    "sg:city":"Naples",
    "sg:classifiers":[
        {
            "category":"Building & Trades",
            "subcategory":"Construction",
            "type":"Services"
        }
    ],
    "sg:phone":"+1 239 949 4454",
    "sg:postcode":"34110",
    "sg:province":"FL",
    "sg:tags":[
        "home",
        "builder"
    ],
    "wof:name":"Diamond Lake",
    "wof:placetype":"venue"
},
  "geometry": {"coordinates":[-81.763621,26.273894],"type":"Point"}
}