{
  "type": "Feature",
  "properties": {
    "addr:full":"607 S Macdill Ave Tampa FL 33609",
    "addr:housenumber":"607",
    "addr:postcode":"33609",
    "addr:street":"S Macdill Ave",
    "iso:country":"US",
    "sg:address":"607 S Macdill Ave",
    "sg:city":"Tampa",
    "sg:classifiers":[
        {
            "category":"Personal",
            "subcategory":"Beauty Salon",
            "type":"Services"
        }
    ],
    "sg:phone":"+1 813 354 9467",
    "sg:postcode":"33609",
    "sg:province":"FL",
    "sg:tags":[
        "shop"
    ],
    "wof:name":"Mercie's Hair Studio",
    "wof:placetype":"venue"
},
  "geometry": {"coordinates":[-82.493397,27.937523],"type":"Point"}
}