{
  "type": "Feature",
  "properties": {
    "addr:full":"4411 W Vasconia St Tampa FL 33629",
    "addr:housenumber":"4411",
    "addr:postcode":"33629",
    "addr:street":"W Vasconia St",
    "iso:country":"US",
    "sg:address":"4411 W Vasconia St",
    "sg:city":"Tampa",
    "sg:classifiers":[
        {
            "category":"Shopping",
            "subcategory":"Jewelry",
            "type":"Retail Goods"
        },
        {
            "category":"Manufacturing",
            "subcategory":"Jewelry",
            "type":"Manufacturing & Wholesale Goods"
        }
    ],
    "sg:phone":"+1 813 831 4755",
    "sg:postcode":"33629",
    "sg:province":"FL",
    "sg:tags":[
        "designer",
        "jeweler"
    ],
    "wof:name":"Made Just For You",
    "wof:placetype":"venue"
},
  "geometry": {"coordinates":[-82.51803,27.91247],"type":"Point"}
}