{
  "type": "Feature",
  "properties": {
    "addr:full":"3015 Mercury Rd Jacksonville FL 32207",
    "addr:housenumber":"3015",
    "addr:postcode":"32207",
    "addr:street":"Mercury Rd",
    "iso:country":"US",
    "sg:address":"3015 Mercury Rd",
    "sg:city":"Jacksonville",
    "sg:classifiers":[
        {
            "category":"Wholesale",
            "subcategory":"Construction Materials",
            "type":"Manufacturing & Wholesale Goods"
        }
    ],
    "sg:phone":"+1 904 737 3233",
    "sg:postcode":"32207",
    "sg:province":"FL",
    "sg:tags":[
        "roofing"
    ],
    "sg:website":"www.sunniland.com",
    "wof:name":"Sunniland Corp",
    "wof:placetype":"venue"
},
  "geometry": {"coordinates":[-81.62508099999999,30.270132],"type":"Point"}
}