{
  "type": "Feature",
  "properties": {
    "addr:full":"2217 Lake Nally Woods Dr Gotha FL 34734",
    "addr:housenumber":"2217",
    "addr:postcode":"34734",
    "addr:street":"Lake Nally Woods Dr",
    "iso:country":"US",
    "sg:address":"2217 Lake Nally Woods Dr",
    "sg:city":"Gotha",
    "sg:classifiers":[
        {
            "category":"Building & Trades",
            "subcategory":"Electrical",
            "type":"Services"
        }
    ],
    "sg:phone":"+1 407 295 6999",
    "sg:postcode":"34734",
    "sg:province":"FL",
    "sg:tags":[
        "sound",
        "assembles",
        "design",
        "system"
    ],
    "wof:name":"Delta USA Inc",
    "wof:placetype":"venue"
},
  "geometry": {"coordinates":[-81.52231999999999,28.535019],"type":"Point"}
}