{
  "type": "Feature",
  "properties": {
    "iso:country":"US",
    "sg:address":"2668 Swamp Cabbage Ct",
    "sg:city":"Fort Myers",
    "sg:classifiers":[
        {
            "category":"Health Services",
            "subcategory":"Doctor",
            "type":"Services"
        }
    ],
    "sg:phone":"+1 239 275 7546",
    "sg:postcode":"33901",
    "sg:province":"FL",
    "sg:tags":[
        "surgeon",
        "cosmetic"
    ],
    "wof:name":"Dermatologic & Cosmetic Surgery Center Lc",
    "wof:placetype":"venue"
},
  "geometry": {"coordinates":[-81.8591,26.6012],"type":"Point"}
}