{
  "type": "Feature",
  "properties": {
    "addr:full":"2763 Westchester Dr S Clearwater FL 33761",
    "addr:housenumber":"2763",
    "addr:postcode":"33761",
    "addr:street":"Westchester Dr S",
    "iso:country":"US",
    "sg:address":"2763 Westchester Dr S",
    "sg:city":"Clearwater",
    "sg:classifiers":[
        {
            "category":"Real Estate",
            "subcategory":"Real Estate Operator",
            "type":"Services"
        }
    ],
    "sg:phone":"+1 727 796 3058",
    "sg:postcode":"33761",
    "sg:province":"FL",
    "sg:tags":[
        "building",
        "nonresidential"
    ],
    "wof:name":"Mt Acadia Properties Inc",
    "wof:placetype":"venue"
},
  "geometry": {"coordinates":[-82.72371099999999,28.02571],"type":"Point"}
}