{
  "type": "Feature",
  "properties": {
    "addr:full":"5757 8th St SW West Miami FL 33144",
    "addr:housenumber":"5757",
    "addr:postcode":"33144",
    "addr:street":"8Th St Sw",
    "iso:country":"US",
    "sg:address":"5757 8th St SW",
    "sg:city":"West Miami",
    "sg:classifiers":[
        {
            "category":"Professional",
            "type":"Services"
        }
    ],
    "sg:phone":"+1 305 262 2024",
    "sg:postcode":"33144",
    "sg:province":"FL",
    "sg:tags":[
        "establishment"
    ],
    "wof:name":"De Feria Enterprises Corp",
    "wof:placetype":"venue"
},
  "geometry": {"coordinates":[-80.288487,25.763621],"type":"Point"}
}