{
  "type": "Feature",
  "properties": {
    "iso:country":"US",
    "sg:address":"128 Tahiti St",
    "sg:city":"Naples",
    "sg:classifiers":[
        {
            "category":"Marine",
            "type":"Transportation"
        }
    ],
    "sg:phone":"+1 239 394 9055",
    "sg:postcode":"34113",
    "sg:province":"FL",
    "sg:tags":[
        "towing"
    ],
    "wof:name":"County Rescue Towing & Savage",
    "wof:placetype":"venue"
},
  "geometry": {"coordinates":[-81.729776,25.979692],"type":"Point"}
}