{
  "type": "Feature",
  "properties": {
    "iso:country":"US",
    "sg:address":"5052 Blue Heron Way",
    "sg:city":"Boca Raton",
    "sg:classifiers":[
        {
            "category":"Banks & Credit Unions",
            "subcategory":"Financial Services",
            "type":"Services"
        }
    ],
    "sg:phone":"+1 561 368 3353",
    "sg:postcode":"33431",
    "sg:province":"FL",
    "sg:tags":[
        "company",
        "holding"
    ],
    "wof:name":"FSB Bancshares Inc",
    "wof:placetype":"venue"
},
  "geometry": {"coordinates":[-80.072591,26.393996],"type":"Point"}
}