{
  "type": "Feature",
  "properties": {
    "iso:country":"US",
    "sg:address":"17080 Beach Rd",
    "sg:city":"Perry",
    "sg:classifiers":[
        {
            "category":"Real Estate",
            "subcategory":"Real Estate Agent",
            "type":"Services"
        }
    ],
    "sg:phone":"+1 850 578 2105",
    "sg:postcode":"32348",
    "sg:province":"FL",
    "wof:name":"Shamrock Realty",
    "wof:placetype":"venue"
},
  "geometry": {"coordinates":[-83.608733,29.875156],"type":"Point"}
}