{
  "type": "Feature",
  "properties": {
    "iso:country":"US",
    "sg:address":"310 Biscayne Ln",
    "sg:city":"Niceville",
    "sg:classifiers":[
        {
            "category":"Building & Trades",
            "subcategory":"Plumbing",
            "type":"Services"
        }
    ],
    "sg:phone":"+1 850 678 3789",
    "sg:postcode":"32578",
    "sg:province":"FL",
    "sg:tags":[
        "plumber",
        "industrial",
        "contractors-commercial"
    ],
    "wof:name":"Travis Junger Plumbing",
    "wof:placetype":"venue"
},
  "geometry": {"coordinates":[-86.472325,30.502782],"type":"Point"}
}