{
  "type": "Feature",
  "properties": {
    "iso:country":"US",
    "sg:address":"1391 NW 54th St",
    "sg:city":"Miami",
    "sg:classifiers":[
        {
            "category":"Building & Trades",
            "subcategory":"Construction",
            "type":"Services"
        }
    ],
    "sg:phone":"+1 305 757 8809",
    "sg:postcode":"33142",
    "sg:province":"FL",
    "sg:tags":[
        "home",
        "improvement"
    ],
    "wof:name":"CMF Painting Contracters Inc",
    "wof:placetype":"venue"
},
  "geometry": {"coordinates":[-80.218678,25.82469],"type":"Point"}
}