{
  "type": "Feature",
  "properties": {
    "iso:country":"US",
    "sg:address":"121 S 7th Ave",
    "sg:city":"Wauchula",
    "sg:classifiers":[
        {
            "category":"Farming",
            "subcategory":"Livestock Farm",
            "type":"Manufacturing & Wholesale Goods"
        }
    ],
    "sg:phone":"+1 863 773 9459",
    "sg:postcode":"33873",
    "sg:province":"FL",
    "sg:tags":[
        "animal",
        "general"
    ],
    "wof:name":"Sleepy K Ranch",
    "wof:placetype":"venue"
},
  "geometry": {"coordinates":[-81.812776,27.54711],"type":"Point"}
}