{
  "type": "Feature",
  "properties": {
    "addr:full":"3612 49th St N Saint Petersburg FL 33710",
    "addr:housenumber":"3612",
    "addr:postcode":"33710",
    "addr:street":"49Th St N",
    "iso:country":"US",
    "sg:address":"3612 49th St N",
    "sg:city":"Saint Petersburg",
    "sg:classifiers":[
        {
            "category":"Personal",
            "subcategory":"Beauty Salon",
            "type":"Services"
        }
    ],
    "sg:phone":"+1 727 525 2387",
    "sg:postcode":"33710",
    "sg:province":"FL",
    "sg:tags":[
        "shop"
    ],
    "wof:name":"Nails n Nails",
    "wof:placetype":"venue"
},
  "geometry": {"coordinates":[-82.700136,27.805545],"type":"Point"}
}