{
  "type": "Feature",
  "properties": {
    "iso:country":"US",
    "sg:address":"1065 NE 125th St",
    "sg:city":"North Miami",
    "sg:classifiers":[
        {
            "category":"Health Services",
            "subcategory":"Doctor",
            "type":"Services"
        },
        {
            "category":"Health Services",
            "subcategory":"Clinic",
            "type":"Services"
        }
    ],
    "sg:phone":"+1 305 891 0037",
    "sg:postcode":"33161",
    "sg:province":"FL",
    "sg:tags":[
        "counseling",
        "mental"
    ],
    "wof:name":"Gregg Alan MD",
    "wof:placetype":"venue"
},
  "geometry": {"coordinates":[-80.177299,25.890699],"type":"Point"}
}