{
  "type": "Feature",
  "properties": {
    "addr:full":"6115 Arlington Expy Jacksonville FL 32211",
    "addr:housenumber":"6115",
    "addr:postcode":"32211",
    "addr:street":"Arlington Expy",
    "iso:country":"US",
    "sg:address":"6115 Arlington Expy",
    "sg:city":"Jacksonville",
    "sg:classifiers":[
        {
            "category":"Retail",
            "subcategory":"Laundry & Dry Cleaning",
            "type":"Services"
        }
    ],
    "sg:phone":"+1 904 724 9000",
    "sg:postcode":"32211",
    "sg:province":"FL",
    "sg:tags":[
        "cleaners",
        "rug",
        "carpet"
    ],
    "wof:name":"Stanley Steemer Carpet Cleaner",
    "wof:placetype":"venue"
},
  "geometry": {"coordinates":[-81.594008,30.327718],"type":"Point"}
}