{
  "type": "Feature",
  "properties": {
    "iso:country":"US",
    "sg:address":"2280 W Citrus Rd",
    "sg:city":"Avon Park",
    "sg:classifiers":[
        {
            "category":"Building & Trades",
            "subcategory":"Construction",
            "type":"Services"
        }
    ],
    "sg:phone":"+1 863 452 0859",
    "sg:postcode":"33825",
    "sg:province":"FL",
    "sg:tags":[
        "tile",
        "dealer"
    ],
    "wof:name":"Sullivan Tile Inc",
    "wof:placetype":"venue"
},
  "geometry": {"coordinates":[-81.53601399999999,27.632082],"type":"Point"}
}