{
  "type": "Feature",
  "properties": {
    "iso:country":"US",
    "sg:address":"1701 Andrews Way",
    "sg:city":"Orange Park",
    "sg:classifiers":[
        {
            "category":"Building & Trades",
            "subcategory":"Construction",
            "type":"Services"
        }
    ],
    "sg:phone":"+1 904 215 3354",
    "sg:postcode":"32073",
    "sg:province":"FL",
    "sg:tags":[
        "house"
    ],
    "wof:name":"Ben S Marine Const",
    "wof:placetype":"venue"
},
  "geometry": {"coordinates":[-81.721171,30.182762],"type":"Point"}
}