{
  "type": "Feature",
  "properties": {
    "iso:country":"US",
    "sg:address":"6103 Deer Run",
    "sg:city":"Fort Myers",
    "sg:classifiers":[
        {
            "category":"Government",
            "subcategory":"Office",
            "type":"Public Place"
        }
    ],
    "sg:phone":"+1 239 489 1026",
    "sg:postcode":"33908",
    "sg:province":"FL",
    "sg:tags":[
        "administrative",
        "program",
        "health"
    ],
    "wof:name":"Krah Dr Rolf",
    "wof:placetype":"venue"
},
  "geometry": {"coordinates":[-81.864186,26.495945],"type":"Point"}
}