{
  "type": "Feature",
  "properties": {
    "addr:full":"4676 Dusk Ct Jacksonville FL 32207",
    "addr:housenumber":"4676",
    "addr:postcode":"32207",
    "addr:street":"Dusk Ct",
    "iso:country":"US",
    "sg:address":"4676 Dusk Ct",
    "sg:city":"Jacksonville",
    "sg:classifiers":[
        {
            "category":"Shopping",
            "subcategory":"Used Merchandise",
            "type":"Retail Goods"
        }
    ],
    "sg:phone":"+1 904 739 3051",
    "sg:postcode":"32207",
    "sg:province":"FL",
    "sg:tags":[
        "antique"
    ],
    "wof:name":"Susan C Berg Antiques & Art",
    "wof:placetype":"venue"
},
  "geometry": {"coordinates":[-81.626549,30.272117],"type":"Point"}
}