{
  "type": "Feature",
  "properties": {
    "addr:full":"19848 Planters Blvd Boca Raton FL 33434",
    "addr:housenumber":"19848",
    "addr:postcode":"33434",
    "addr:street":"Planters Blvd",
    "iso:country":"US",
    "sg:address":"19848 Planters Blvd",
    "sg:city":"Boca Raton",
    "sg:classifiers":[
        {
            "category":"Real Estate",
            "subcategory":"Real Estate Agent",
            "type":"Services"
        }
    ],
    "sg:phone":"+1 561 852 3583",
    "sg:postcode":"33434",
    "sg:province":"FL",
    "wof:name":"Wfl Associates Inc",
    "wof:placetype":"venue"
},
  "geometry": {"coordinates":[-80.15566099999999,26.381972],"type":"Point"}
}