{
  "type": "Feature",
  "properties": {
    "addr:full":"15760 SW 20th Avenue Rd Ocala FL 34473",
    "addr:housenumber":"15760",
    "addr:postcode":"34473",
    "addr:street":"Sw 20Th Avenue Rd",
    "iso:country":"US",
    "sg:address":"15760 SW 20th Avenue Rd",
    "sg:city":"Ocala",
    "sg:classifiers":[
        {
            "category":"Home & Garden",
            "subcategory":"Building Materials",
            "type":"Retail Goods"
        }
    ],
    "sg:phone":"+1 352 347 0938",
    "sg:postcode":"34473",
    "sg:province":"FL",
    "wof:name":"Ozzies Kamikaze Inc",
    "wof:placetype":"venue"
},
  "geometry": {"coordinates":[-82.13635600000001,28.976491],"type":"Point"}
}