{
  "type": "Feature",
  "properties": {
    "iso:country":"US",
    "sg:address":"6819 River Oaks Dr",
    "sg:city":"Orlando",
    "sg:classifiers":[
        {
            "category":"Building & Trades",
            "subcategory":"Landscaping Services",
            "type":"Services"
        }
    ],
    "sg:phone":"+1 407 290 9070",
    "sg:postcode":"32818",
    "sg:province":"FL",
    "sg:tags":[
        "landscape",
        "contractor"
    ],
    "wof:name":"Michelle Professional Lndscp",
    "wof:placetype":"venue"
},
  "geometry": {"coordinates":[-81.47162400000001,28.555459],"type":"Point"}
}