{
  "type": "Feature",
  "properties": {
    "iso:country":"US",
    "sg:address":"3003 S Congress Ave",
    "sg:city":"Lake Worth",
    "sg:classifiers":[
        {
            "category":"Professional",
            "subcategory":"Management & Consulting",
            "type":"Services"
        }
    ],
    "sg:phone":"+1 561 304 7881",
    "sg:postcode":"33461",
    "sg:province":"FL",
    "sg:tags":[
        "consultant",
        "business"
    ],
    "wof:name":"Fastrack Management & Cnsltng",
    "wof:placetype":"venue"
},
  "geometry": {"coordinates":[-80.088629,26.632437],"type":"Point"}
}