{
  "type": "Feature",
  "properties": {
    "addr:full":"2706 W Saint Isabell St Tampa FL 33607",
    "addr:housenumber":"2706",
    "addr:postcode":"33607",
    "addr:street":"W Saint Isabell St",
    "iso:country":"US",
    "sg:address":"2706 W Saint Isabell St",
    "sg:city":"Tampa",
    "sg:classifiers":[
        {
            "category":"Health Services",
            "subcategory":"Chiropractor",
            "type":"Services"
        }
    ],
    "sg:phone":"+1 813 514 1239",
    "sg:postcode":"33607",
    "sg:province":"FL",
    "wof:name":"Advanced Chiropractic",
    "wof:placetype":"venue"
},
  "geometry": {"coordinates":[-82.488737,27.978709],"type":"Point"}
}