{
  "type": "Feature",
  "properties": {
    "iso:country":"US",
    "sg:address":"377 Trier Rd NW",
    "sg:city":"Melbourne",
    "sg:classifiers":[
        {
            "category":"Building & Trades",
            "subcategory":"Cleaning & Sanitation",
            "type":"Services"
        }
    ],
    "sg:phone":"+1 321 951 4604",
    "sg:postcode":"32907",
    "sg:province":"FL",
    "sg:tags":[
        "janitor"
    ],
    "wof:name":"A M Cleaning Svc",
    "wof:placetype":"venue"
},
  "geometry": {"coordinates":[-80.67948699999999,28.030361],"type":"Point"}
}