{
  "type": "Feature",
  "properties": {
    "addr:full":"9625 Oaks St Tampa FL 33635",
    "addr:housenumber":"9625",
    "addr:postcode":"33635",
    "addr:street":"Oaks St",
    "iso:country":"US",
    "sg:address":"9625 Oaks St",
    "sg:city":"Tampa",
    "sg:classifiers":[
        {
            "category":"Home & Garden",
            "subcategory":"Furniture",
            "type":"Retail Goods"
        }
    ],
    "sg:phone":"+1 813 886 5972",
    "sg:postcode":"33635",
    "sg:province":"FL",
    "wof:name":"Allwood M Ormond",
    "wof:placetype":"venue"
},
  "geometry": {"coordinates":[-82.589568,28.035826],"type":"Point"}
}