{
  "type": "Feature",
  "properties": {
    "iso:country":"US",
    "sg:address":"1760 NW 3rd Ave",
    "sg:city":"Pompano Beach",
    "sg:classifiers":[
        {
            "category":"Building & Trades",
            "subcategory":"Construction",
            "type":"Services"
        }
    ],
    "sg:phone":"+1 954 784 1315",
    "sg:postcode":"33060",
    "sg:province":"FL",
    "sg:tags":[
        "residential"
    ],
    "wof:name":"General Property Improvement",
    "wof:placetype":"venue"
},
  "geometry": {"coordinates":[-80.127454,26.252598],"type":"Point"}
}