{
  "type": "Feature",
  "properties": {
    "iso:country":"US",
    "sg:address":"4110 Georgia Ave",
    "sg:city":"West Palm Beach",
    "sg:classifiers":[
        {
            "category":"Manufacturing",
            "subcategory":"Metals",
            "type":"Manufacturing & Wholesale Goods"
        }
    ],
    "sg:phone":"+1 561 655 4644",
    "sg:postcode":"33405",
    "sg:province":"FL",
    "sg:tags":[
        "foundry"
    ],
    "wof:name":"Luis Montoya Sculpture Studio",
    "wof:placetype":"venue"
},
  "geometry": {"coordinates":[-80.05855200000001,26.675011],"type":"Point"}
}