{
  "type": "Feature",
  "properties": {
    "iso:country":"US",
    "sg:address":"6535 5th St W",
    "sg:city":"Bradenton",
    "sg:classifiers":[
        {
            "category":"Personal",
            "type":"Services"
        }
    ],
    "sg:phone":"+1 941 727 7355",
    "sg:postcode":"34207",
    "sg:province":"FL",
    "sg:tags":[
        "party",
        "planning"
    ],
    "wof:name":"My Wedding Doves",
    "wof:placetype":"venue"
},
  "geometry": {"coordinates":[-82.567238,27.424354],"type":"Point"}
}