{
  "type": "Feature",
  "properties": {
    "addr:full":"707 W Main St Lake City FL 32054",
    "addr:housenumber":"707",
    "addr:postcode":"32054",
    "addr:street":"W Main St",
    "iso:country":"US",
    "sg:address":"707 W Main St",
    "sg:city":"Lake City",
    "sg:classifiers":[
        {
            "category":"Banks & Credit Unions",
            "subcategory":"Bank",
            "type":"Services"
        }
    ],
    "sg:phone":"+1 386 755 0600",
    "sg:postcode":"32054",
    "sg:province":"FL",
    "sg:website":"www.ffsb.com",
    "wof:name":"First Federal Savings Bank",
    "wof:placetype":"venue"
},
  "geometry": {"coordinates":[-82.34910600000001,30.024891],"type":"Point"}
}