{
  "type": "Feature",
  "properties": {
    "addr:full":"6824 SW 89th Ct Miami FL 33173",
    "addr:housenumber":"6824",
    "addr:postcode":"33173",
    "addr:street":"Sw 89Th Ct",
    "iso:country":"US",
    "sg:address":"6824 SW 89th Ct",
    "sg:city":"Miami",
    "sg:classifiers":[
        {
            "category":"Professional",
            "subcategory":"Business Services",
            "type":"Services"
        }
    ],
    "sg:phone":"+1 305 596 0350",
    "sg:postcode":"33173",
    "sg:province":"FL",
    "wof:name":"Spectre Developments",
    "wof:placetype":"venue"
},
  "geometry": {"coordinates":[-80.339566,25.705058],"type":"Point"}
}