{
  "type": "Feature",
  "properties": {
    "addr:full":"2020 State Hwy 44 Inverness FL 34453",
    "addr:housenumber":"2020",
    "addr:postcode":"34453",
    "addr:street":"State Hwy 44",
    "iso:country":"US",
    "sg:address":"2020 State Hwy 44",
    "sg:city":"Inverness",
    "sg:classifiers":[
        {
            "category":"Professional",
            "subcategory":"Advertising",
            "type":"Services"
        }
    ],
    "sg:phone":"+1 352 637 6666",
    "sg:postcode":"34453",
    "sg:province":"FL",
    "wof:name":"Adelphia",
    "wof:placetype":"venue"
},
  "geometry": {"coordinates":[-82.356314,28.838128],"type":"Point"}
}