{
  "type": "Feature",
  "properties": {
    "iso:country":"US",
    "sg:address":"407 Needles Dr",
    "sg:city":"Daytona Beach",
    "sg:classifiers":[
        {
            "category":"Professional",
            "subcategory":"Business Services",
            "type":"Services"
        }
    ],
    "sg:phone":"+1 386 767 3394",
    "sg:postcode":"32127",
    "sg:province":"FL",
    "wof:name":"Dbest Enterprises",
    "wof:placetype":"venue"
},
  "geometry": {"coordinates":[-80.992114,29.10062],"type":"Point"}
}