{
  "type": "Feature",
  "properties": {
    "iso:country":"US",
    "sg:address":"5000 N Canoe Creek Rd",
    "sg:city":"Kenansville",
    "sg:classifiers":[
        {
            "category":"Farming",
            "subcategory":"Livestock Farm",
            "type":"Manufacturing & Wholesale Goods"
        }
    ],
    "sg:phone":"+1 407 892 8045",
    "sg:postcode":"34739",
    "sg:province":"FL",
    "sg:tags":[
        "beef",
        "feedlot",
        "cattle"
    ],
    "wof:name":"Bear Hammock Ranch",
    "wof:placetype":"venue"
},
  "geometry": {"coordinates":[-81.219892,28.042889],"type":"Point"}
}