{
  "type": "Feature",
  "properties": {
    "addr:full":"2218 N Dixie Hwy Hollywood FL 33020",
    "addr:housenumber":"2218",
    "addr:postcode":"33020",
    "addr:street":"N Dixie Hwy",
    "iso:country":"US",
    "sg:address":"2218 N Dixie Hwy",
    "sg:city":"Hollywood",
    "sg:classifiers":[
        {
            "category":"Retail",
            "subcategory":"Auto Repair",
            "type":"Services"
        }
    ],
    "sg:phone":"+1 954 922 4653",
    "sg:postcode":"33020",
    "sg:province":"FL",
    "sg:tags":[
        "body",
        "automobile",
        "painting"
    ],
    "wof:name":"Russ & Bob's Body Shop",
    "wof:placetype":"venue"
},
  "geometry": {"coordinates":[-80.150025,26.031451],"type":"Point"}
}