{
  "type": "Feature",
  "properties": {
    "addr:full":"1200 W Cass St Tampa FL 33606",
    "addr:housenumber":"1200",
    "addr:postcode":"33606",
    "addr:street":"W Cass St",
    "iso:country":"US",
    "sg:address":"1200 W Cass St",
    "sg:city":"Tampa",
    "sg:classifiers":[
        {
            "category":"Professional",
            "subcategory":"Business Services",
            "type":"Services"
        }
    ],
    "sg:phone":"+1 813 774 4372",
    "sg:postcode":"33606",
    "sg:province":"FL",
    "sg:tags":[
        "specializing",
        "telecommunication"
    ],
    "wof:name":"Appliedlogx",
    "wof:placetype":"venue"
},
  "geometry": {"coordinates":[-82.471744,27.949873],"type":"Point"}
}