{
  "type": "Feature",
  "properties": {
    "iso:country":"US",
    "sg:address":"214 W 23rd St",
    "sg:city":"Panama City",
    "sg:classifiers":[
        {
            "category":"Restaurant",
            "type":"Food & Drink"
        }
    ],
    "sg:phone":"+1 850 784 1550",
    "sg:postcode":"32405",
    "sg:province":"FL",
    "wof:name":"Waffle Shoppe",
    "wof:placetype":"venue"
},
  "geometry": {"coordinates":[-85.665226,30.189751],"type":"Point"}
}