{
  "type": "Feature",
  "properties": {
    "addr:full":"100 W Graves Ave Orange City FL 32763",
    "addr:housenumber":"100",
    "addr:postcode":"32763",
    "addr:street":"W Graves Ave",
    "iso:country":"US",
    "sg:address":"100 W Graves Ave",
    "sg:city":"Orange City",
    "sg:classifiers":[
        {
            "category":"Restaurant",
            "type":"Food & Drink"
        }
    ],
    "sg:phone":"+1 386 775 0264",
    "sg:postcode":"32763",
    "sg:province":"FL",
    "wof:name":"Hair Cafe",
    "wof:placetype":"venue"
},
  "geometry": {"coordinates":[-81.298844,28.948455],"type":"Point"}
}