{
  "type": "Feature",
  "properties": {
    "iso:country":"US",
    "sg:address":"2081 Indigo Ter",
    "sg:city":"Dunedin",
    "sg:classifiers":[
        {
            "category":"Retail",
            "subcategory":"Auto Repair",
            "type":"Services"
        }
    ],
    "sg:phone":"+1 727 736 0713",
    "sg:postcode":"34698",
    "sg:province":"FL",
    "sg:tags":[
        "body",
        "painting",
        "repairing",
        "automobile"
    ],
    "wof:name":"Baraka Body Bazaar Inc",
    "wof:placetype":"venue"
},
  "geometry": {"coordinates":[-82.75199499999999,28.015275],"type":"Point"}
}