{
  "type": "Feature",
  "properties": {
    "addr:full":"10655 SW 184th Ter Miami FL 33157",
    "addr:housenumber":"10655",
    "addr:postcode":"33157",
    "addr:street":"Sw 184Th Ter",
    "iso:country":"US",
    "sg:address":"10655 SW 184th Ter",
    "sg:city":"Miami",
    "sg:classifiers":[
        {
            "category":"Building & Trades",
            "subcategory":"Plumbing",
            "type":"Services"
        }
    ],
    "sg:phone":"+1 305 233 8728",
    "sg:postcode":"33157",
    "sg:province":"FL",
    "sg:tags":[
        "specializing",
        "contractor",
        "commercial",
        "conditioning",
        "air"
    ],
    "wof:name":"Waters Mechanical Inc",
    "wof:placetype":"venue"
},
  "geometry": {"coordinates":[-80.361023,25.597968],"type":"Point"}
}