{
  "type": "Feature",
  "properties": {
    "iso:country":"US",
    "sg:address":"3745 S Congress Ave",
    "sg:city":"Lake Worth",
    "sg:classifiers":[
        {
            "category":"Wholesale",
            "subcategory":"Electrical",
            "type":"Manufacturing & Wholesale Goods"
        }
    ],
    "sg:phone":"+1 561 969 0920",
    "sg:postcode":"33461",
    "sg:province":"FL",
    "sg:tags":[
        "control",
        "security",
        "system"
    ],
    "wof:name":"Guardian Angels Security Svc",
    "wof:placetype":"venue"
},
  "geometry": {"coordinates":[-80.08895699999999,26.620241],"type":"Point"}
}