{
  "type": "Feature",
  "properties": {
    "iso:country":"US",
    "sg:address":"2583 Saturn Rd",
    "sg:city":"Brooksville",
    "sg:classifiers":[
        {
            "category":"Farming",
            "subcategory":"Livestock Farm",
            "type":"Manufacturing & Wholesale Goods"
        }
    ],
    "sg:phone":"+1 352 796 4727",
    "sg:postcode":"34604",
    "sg:province":"FL",
    "sg:tags":[
        "equine"
    ],
    "wof:name":"Sunspot Ranch",
    "wof:placetype":"venue"
},
  "geometry": {"coordinates":[-82.38354099999999,28.466511],"type":"Point"}
}