{
  "type": "Feature",
  "properties": {
    "addr:full":"2120 US Hwy 301 Tampa FL 33619",
    "addr:housenumber":"2120",
    "addr:postcode":"33619",
    "addr:street":"Us Hwy 301",
    "iso:country":"US",
    "sg:address":"2120 US Hwy 301",
    "sg:city":"Tampa",
    "sg:classifiers":[
        {
            "category":"Food & Beverages",
            "subcategory":"Specialty",
            "type":"Retail Goods"
        }
    ],
    "sg:phone":"+1 813 628 8477",
    "sg:postcode":"33619",
    "sg:province":"FL",
    "sg:tags":[
        "health",
        "diet"
    ],
    "wof:name":"Cancer Wellness Institute",
    "wof:placetype":"venue"
},
  "geometry": {"coordinates":[-82.360482,27.964883],"type":"Point"}
}