{
  "type": "Feature",
  "properties": {
    "addr:full":"2904 Orange Ave Fort Pierce FL 34947",
    "addr:housenumber":"2904",
    "addr:postcode":"34947",
    "addr:street":"Orange Ave",
    "iso:country":"US",
    "sg:address":"2904 Orange Ave",
    "sg:city":"Fort Pierce",
    "sg:classifiers":[
        {
            "category":"Retail",
            "subcategory":"Car Wash",
            "type":"Services"
        }
    ],
    "sg:phone":"+1 772 335 1185",
    "sg:postcode":"34947",
    "sg:province":"FL",
    "sg:tags":[
        "automobile",
        "detail",
        "clean"
    ],
    "wof:name":"Care Auto Detailer",
    "wof:placetype":"venue"
},
  "geometry": {"coordinates":[-80.35506100000001,27.447584],"type":"Point"}
}