{
  "type": "Feature",
  "properties": {
    "addr:full":"3808 S John Young Pkwy Orlando FL 32839",
    "addr:housenumber":"3808",
    "addr:postcode":"32839",
    "addr:street":"S John Young Pkwy",
    "iso:country":"US",
    "sg:address":"3808 S John Young Pkwy",
    "sg:city":"Orlando",
    "sg:classifiers":[
        {
            "category":"Insurance",
            "subcategory":"Hazard Insurance",
            "type":"Services"
        }
    ],
    "sg:phone":"+1 407 425 6889",
    "sg:postcode":"32839",
    "sg:province":"FL",
    "sg:tags":[
        "bond"
    ],
    "wof:name":"Checkout Time Bonding",
    "wof:placetype":"venue"
},
  "geometry": {"coordinates":[-81.41758400000001,28.504195],"type":"Point"}
}