{
  "type": "Feature",
  "properties": {
    "addr:full":"8894 SW 131st St Miami FL 33176",
    "addr:housenumber":"8894",
    "addr:postcode":"33176",
    "addr:street":"Sw 131St St",
    "iso:country":"US",
    "sg:address":"8894 SW 131st St",
    "sg:city":"Miami",
    "sg:classifiers":[
        {
            "category":"Retail",
            "subcategory":"Repair Shop",
            "type":"Services"
        }
    ],
    "sg:phone":"+1 305 233 3664",
    "sg:postcode":"33176",
    "sg:province":"FL",
    "sg:tags":[
        "lawn",
        "gardening",
        "mower",
        "equipment",
        "nursery",
        "yard"
    ],
    "wof:name":"Lawn Mower Shop the",
    "wof:placetype":"venue"
},
  "geometry": {"coordinates":[-80.33820299999999,25.648701],"type":"Point"}
}