{
  "type": "Feature",
  "properties": {
    "iso:country":"US",
    "sg:address":"4254 SW 161st Pl",
    "sg:city":"Miami",
    "sg:classifiers":[
        {
            "category":"Wholesale",
            "subcategory":"Machinery & Supplies",
            "type":"Manufacturing & Wholesale Goods"
        }
    ],
    "sg:phone":"+1 305 226 2381",
    "sg:postcode":"33185",
    "sg:province":"FL",
    "sg:tags":[
        "instrument",
        "scientific",
        "apparatus"
    ],
    "wof:name":"Bluepiont",
    "wof:placetype":"venue"
},
  "geometry": {"coordinates":[-80.455187,25.726484],"type":"Point"}
}