{
  "type": "Feature",
  "properties": {
    "addr:full":"1067 Shadick Dr Orange City FL 32763",
    "addr:housenumber":"1067",
    "addr:postcode":"32763",
    "addr:street":"Shadick Dr",
    "iso:country":"US",
    "sg:address":"1067 Shadick Dr",
    "sg:city":"Orange City",
    "sg:classifiers":[
        {
            "category":"Retail",
            "subcategory":"Repair Shop",
            "type":"Services"
        }
    ],
    "sg:phone":"+1 386 774 8331",
    "sg:postcode":"32763",
    "sg:province":"FL",
    "sg:tags":[
        "tool",
        "parts"
    ],
    "wof:name":"MICS",
    "wof:placetype":"venue"
},
  "geometry": {"coordinates":[-81.28438199999999,28.938709],"type":"Point"}
}