{
  "type": "Feature",
  "properties": {
    "addr:full":"4710 Dignan St Jacksonville FL 32254",
    "addr:housenumber":"4710",
    "addr:postcode":"32254",
    "addr:street":"Dignan St",
    "iso:country":"US",
    "sg:address":"4710 Dignan St",
    "sg:city":"Jacksonville",
    "sg:classifiers":[
        {
            "category":"Building & Trades",
            "subcategory":"Construction",
            "type":"Services"
        }
    ],
    "sg:phone":"+1 904 355 9500",
    "sg:postcode":"32254",
    "sg:province":"FL",
    "sg:tags":[
        "concrete",
        "pumping"
    ],
    "wof:name":"Pumpco",
    "wof:placetype":"venue"
},
  "geometry": {"coordinates":[-81.72766799999999,30.324423],"type":"Point"}
}