{
  "type": "Feature",
  "properties": {
    "iso:country":"US",
    "sg:address":"2145 W Washington St",
    "sg:city":"Orlando",
    "sg:classifiers":[
        {
            "category":"Autos & Motor Vehicles",
            "subcategory":"Automobile Sales",
            "type":"Retail Goods"
        }
    ],
    "sg:phone":"+1 407 835 8188",
    "sg:postcode":"32805",
    "sg:province":"FL",
    "sg:tags":[
        "car",
        "dealer"
    ],
    "wof:name":"Andre's Auto Sales & Svc",
    "wof:placetype":"venue"
},
  "geometry": {"coordinates":[-81.40934799999999,28.544557],"type":"Point"}
}