{
  "type": "Feature",
  "properties": {
    "addr:full":"116 S Park Ave Ste D Winter Park FL 32789",
    "addr:housenumber":"116",
    "addr:postcode":"32789",
    "addr:street":"S Park Ave Ste D",
    "iso:country":"US",
    "sg:address":"116 S Park Ave Ste D",
    "sg:city":"Winter Park",
    "sg:classifiers":[
        {
            "category":"Wholesale",
            "subcategory":"Stationery",
            "type":"Manufacturing & Wholesale Goods"
        },
        {
            "category":"Shopping",
            "subcategory":"Bridal",
            "type":"Retail Goods"
        }
    ],
    "sg:phone":"+1 407 629 6999",
    "sg:postcode":"32789",
    "sg:province":"FL",
    "sg:tags":[
        "card"
    ],
    "sg:website":"www.maureenhallinvitations.com",
    "wof:name":"Maureen H Hall Stationery & Invitations",
    "wof:placetype":"venue"
},
  "geometry": {"coordinates":[-81.350583,28.597486],"type":"Point"}
}