{
  "type": "Feature",
  "properties": {
    "addr:full":"6991 Chestnut Dr Cocoa FL 32927",
    "addr:housenumber":"6991",
    "addr:postcode":"32927",
    "addr:street":"Chestnut Dr",
    "iso:country":"US",
    "sg:address":"6991 Chestnut Dr",
    "sg:city":"Cocoa",
    "sg:classifiers":[
        {
            "category":"Building & Trades",
            "subcategory":"Construction",
            "type":"Services"
        }
    ],
    "sg:phone":"+1 321 639 6745",
    "sg:postcode":"32927",
    "sg:province":"FL",
    "sg:tags":[
        "contractor"
    ],
    "wof:name":"James E Ritter Tile",
    "wof:placetype":"venue"
},
  "geometry": {"coordinates":[-80.766856,28.445266],"type":"Point"}
}