{
  "type": "Feature",
  "properties": {
    "iso:country":"US",
    "sg:address":"1000 Ashbourne Cir",
    "sg:city":"Trinity",
    "sg:classifiers":[
        {
            "category":"Shopping",
            "subcategory":"Gifts & Souvenirs",
            "type":"Retail Goods"
        },
        {
            "category":"Shopping",
            "subcategory":"Crafts & Fabrics",
            "type":"Retail Goods"
        },
        {
            "category":"Manufacturing",
            "subcategory":"Pottery",
            "type":"Manufacturing & Wholesale Goods"
        }
    ],
    "sg:phone":"+1 727 375 8618",
    "sg:postcode":"34655",
    "sg:province":"FL",
    "sg:tags":[
        "shop",
        "products-decorative",
        "ceramics-equipment",
        "ceramic",
        "supply"
    ],
    "wof:name":"C & R Products Inc",
    "wof:placetype":"venue"
},
  "geometry": {"coordinates":[-82.62872299999999,28.177311],"type":"Point"}
}