{
  "type": "Feature",
  "properties": {
    "addr:full":"634 Beachland Blvd Vero Beach FL 32963",
    "addr:housenumber":"634",
    "addr:postcode":"32963",
    "addr:street":"Beachland Blvd",
    "iso:country":"US",
    "sg:address":"634 Beachland Blvd",
    "sg:city":"Vero Beach",
    "sg:classifiers":[
        {
            "category":"Manufacturing",
            "subcategory":"Printing",
            "type":"Manufacturing & Wholesale Goods"
        }
    ],
    "sg:phone":"+1 772 231 9520",
    "sg:postcode":"32963",
    "sg:province":"FL",
    "sg:tags":[
        "publisher",
        "periodical"
    ],
    "sg:website":"www.publishersalliance.com",
    "wof:name":"Publishers Alliance Corp",
    "wof:placetype":"venue"
},
  "geometry": {"coordinates":[-80.36113400000001,27.653318],"type":"Point"}
}