{
  "type": "Feature",
  "properties": {
    "addr:full":"8319 Embassy Blvd Port Richey FL 34668",
    "addr:housenumber":"8319",
    "addr:postcode":"34668",
    "addr:street":"Embassy Blvd",
    "iso:country":"US",
    "sg:address":"8319 Embassy Blvd",
    "sg:city":"Port Richey",
    "sg:classifiers":[
        {
            "category":"Health Services",
            "subcategory":"Optometrist",
            "type":"Services"
        }
    ],
    "sg:phone":"+1 727 819 0440",
    "sg:postcode":"34668",
    "sg:province":"FL",
    "wof:name":"Embassy Optical",
    "wof:placetype":"venue"
},
  "geometry": {"coordinates":[-82.676,28.291724],"type":"Point"}
}