{
  "type": "Feature",
  "properties": {
    "addr:full":"5600 Mary's Villa Rd Groveland FL 34736",
    "addr:housenumber":"5600",
    "addr:postcode":"34736",
    "addr:street":"Mary'S Villa Rd",
    "iso:country":"US",
    "sg:address":"5600 Mary's Villa Rd",
    "sg:city":"Groveland",
    "sg:classifiers":[
        {
            "category":"Home & Garden",
            "subcategory":"Carpets & Floor Coverings",
            "type":"Retail Goods"
        }
    ],
    "sg:phone":"+1 352 429 8889",
    "sg:postcode":"34736",
    "sg:province":"FL",
    "sg:tags":[
        "material"
    ],
    "wof:name":"Advanced Wood Flooring Systems",
    "wof:placetype":"venue"
},
  "geometry": {"coordinates":[-81.86065600000001,28.614655],"type":"Point"}
}