{
  "type": "Feature",
  "properties": {
    "iso:country":"US",
    "sg:address":"7349 Hwy 90",
    "sg:city":"Grand Ridge",
    "sg:classifiers":[
        {
            "category":"Recreation",
            "type":"Entertainment"
        }
    ],
    "sg:phone":"+1 850 592 6182",
    "sg:postcode":"32442",
    "sg:province":"FL",
    "wof:name":"Twin C Ranch Pony Rides",
    "wof:placetype":"venue"
},
  "geometry": {"coordinates":[-84.974906,30.718604],"type":"Point"}
}