{
  "type": "Feature",
  "properties": {
    "iso:country":"US",
    "sg:address":"15661 Younis Rd W",
    "sg:city":"Jacksonville",
    "sg:classifiers":[
        {
            "category":"Shopping",
            "subcategory":"Discount & Variety Stores",
            "type":"Retail Goods"
        }
    ],
    "sg:phone":"+1 904 768 6051",
    "sg:postcode":"32218",
    "sg:province":"FL",
    "sg:tags":[
        "merchandise",
        "general"
    ],
    "wof:name":"Charles B Underhill Internet",
    "wof:placetype":"venue"
},
  "geometry": {"coordinates":[-81.742738,30.517902],"type":"Point"}
}