{
  "type": "Feature",
  "properties": {
    "addr:full":"2773 NW 42nd Ave Pompano Beach FL 33066",
    "addr:housenumber":"2773",
    "addr:postcode":"33066",
    "addr:street":"Nw 42Nd Ave",
    "iso:country":"US",
    "sg:address":"2773 NW 42nd Ave",
    "sg:city":"Pompano Beach",
    "sg:classifiers":[
        {
            "category":"Professional",
            "type":"Services"
        }
    ],
    "sg:phone":"+1 954 973 2830",
    "sg:postcode":"33066",
    "sg:province":"FL",
    "wof:name":"L Shrontz Inc",
    "wof:placetype":"venue"
},
  "geometry": {"coordinates":[-80.182446,26.259998],"type":"Point"}
}