{
  "type": "Feature",
  "properties": {
    "addr:full":"4278 72nd Rd N Riviera Beach FL 33404",
    "addr:housenumber":"4278",
    "addr:postcode":"33404",
    "addr:street":"72Nd Rd N",
    "iso:country":"US",
    "sg:address":"4278 72nd Rd N",
    "sg:city":"Riviera Beach",
    "sg:classifiers":[
        {
            "category":"Real Estate",
            "subcategory":"Real Estate Agent",
            "type":"Services"
        },
        {
            "category":"Home & Garden",
            "subcategory":"Mobile Homes",
            "type":"Retail Goods"
        }
    ],
    "sg:phone":"+1 561 968 1919",
    "sg:postcode":"33404",
    "sg:province":"FL",
    "sg:tags":[
        "broker"
    ],
    "wof:name":"Real Mc Coy Mobile Inc",
    "wof:placetype":"venue"
},
  "geometry": {"coordinates":[-80.103492,26.784069],"type":"Point"}
}