{
  "type": "Feature",
  "properties": {
    "addr:full":"11293 SW 9th Ct Hollywood FL 33025",
    "addr:housenumber":"11293",
    "addr:postcode":"33025",
    "addr:street":"Sw 9Th Ct",
    "iso:country":"US",
    "sg:address":"11293 SW 9th Ct",
    "sg:city":"Hollywood",
    "sg:classifiers":[
        {
            "category":"Real Estate",
            "subcategory":"Real Estate Operator",
            "type":"Services"
        }
    ],
    "sg:phone":"+1 954 447 3090",
    "sg:postcode":"33025",
    "sg:province":"FL",
    "sg:tags":[
        "building",
        "nonresidential"
    ],
    "wof:name":"Rideli Properties LLC",
    "wof:placetype":"venue"
},
  "geometry": {"coordinates":[-80.29734999999999,26.000045],"type":"Point"}
}