{
  "type": "Feature",
  "properties": {
    "iso:country":"US",
    "sg:address":"13300 Panama City Beach Pkwy",
    "sg:city":"Panama City Bch",
    "sg:classifiers":[
        {
            "category":"Social Services",
            "subcategory":"Child Care",
            "type":"Services"
        }
    ],
    "sg:phone":"+1 850 233 1629",
    "sg:postcode":"32407",
    "sg:province":"FL",
    "wof:name":"Faith Christian Early Learning",
    "wof:placetype":"venue"
},
  "geometry": {"coordinates":[-85.841803,30.20659],"type":"Point"}
}