{
  "type": "Feature",
  "properties": {
    "addr:full":"11811 Royal Palm Blvd Coral Springs FL 33065",
    "addr:housenumber":"11811",
    "addr:postcode":"33065",
    "addr:street":"Royal Palm Blvd",
    "iso:country":"US",
    "sg:address":"11811 Royal Palm Blvd",
    "sg:city":"Coral Springs",
    "sg:classifiers":[
        {
            "category":"Professional",
            "subcategory":"Advertising",
            "type":"Services"
        }
    ],
    "sg:phone":"+1 954 346 6676",
    "sg:postcode":"33065",
    "sg:province":"FL",
    "sg:tags":[
        "mailing",
        "list",
        "direct",
        "mail"
    ],
    "wof:name":"Welcome Enterprises Inc",
    "wof:placetype":"venue"
},
  "geometry": {"coordinates":[-80.2835,26.259248],"type":"Point"}
}