{
  "type": "Feature",
  "properties": {
    "iso:country":"US",
    "sg:address":"202 W Boynton Beach Blvd",
    "sg:city":"Boynton Beach",
    "sg:classifiers":[
        {
            "category":"Social Services",
            "subcategory":"Child Care",
            "type":"Services"
        }
    ],
    "sg:phone":"+1 561 734 1880",
    "sg:postcode":"33435",
    "sg:province":"FL",
    "wof:name":"Lighthouse Academy",
    "wof:placetype":"venue"
},
  "geometry": {"coordinates":[-80.067216,26.528849],"type":"Point"}
}