{
  "type": "Feature",
  "properties": {
    "iso:country":"US",
    "sg:address":"22060 Old Dixie Hwy",
    "sg:city":"Miami",
    "sg:classifiers":[
        {
            "category":"Food & Beverages",
            "subcategory":"Groceries & Convenience Stores",
            "type":"Retail Goods"
        }
    ],
    "sg:phone":"+1 305 258 2776",
    "sg:postcode":"33170",
    "sg:province":"FL",
    "sg:tags":[
        "grocer"
    ],
    "wof:name":"Kelcey's Grocery",
    "wof:placetype":"venue"
},
  "geometry": {"coordinates":[-80.387067,25.56191],"type":"Point"}
}