{
  "type": "Feature",
  "properties": {
    "addr:full":"209 McClure Dr Gulf Breeze FL 32561",
    "addr:housenumber":"209",
    "addr:postcode":"32561",
    "addr:street":"Mcclure Dr",
    "iso:country":"US",
    "sg:address":"209 McClure Dr",
    "sg:city":"Gulf Breeze",
    "sg:classifiers":[
        {
            "category":"Building & Trades",
            "subcategory":"Construction",
            "type":"Services"
        }
    ],
    "sg:phone":"+1 850 261 6317",
    "sg:postcode":"32561",
    "sg:province":"FL",
    "sg:tags":[
        "house"
    ],
    "wof:name":"Stephen Pyles Construction",
    "wof:placetype":"venue"
},
  "geometry": {"coordinates":[-87.163077,30.363605],"type":"Point"}
}