{
  "type": "Feature",
  "properties": {
    "addr:full":"202 Bullard Pkwy Tampa FL 33617",
    "addr:housenumber":"202",
    "addr:postcode":"33617",
    "addr:street":"Bullard Pkwy",
    "iso:country":"US",
    "sg:address":"202 Bullard Pkwy",
    "sg:city":"Tampa",
    "sg:classifiers":[
        {
            "category":"Government",
            "subcategory":"Office",
            "type":"Public Place"
        }
    ],
    "sg:phone":"+1 813 989 7160",
    "sg:postcode":"33617",
    "sg:province":"FL",
    "sg:tags":[
        "library"
    ],
    "wof:name":"Public Library Cooperative",
    "wof:placetype":"venue"
},
  "geometry": {"coordinates":[-82.38939000000001,28.032573],"type":"Point"}
}