{
  "type": "Feature",
  "properties": {
    "addr:full":"6135 Gillot Blvd Port Charlotte FL 33981",
    "addr:postcode":"6135;33981",
    "addr:street":"Gillot Blvd",
    "iso:country":"US",
    "sg:address":"6135 Gillot Blvd",
    "sg:city":"Port Charlotte",
    "sg:classifiers":[
        {
            "category":"Building & Trades",
            "subcategory":"Construction",
            "type":"Services"
        }
    ],
    "sg:phone":"+1 941 697 9784",
    "sg:postcode":"33981",
    "sg:province":"FL",
    "sg:tags":[
        "house"
    ],
    "wof:name":"Terry Jayne",
    "wof:placetype":"venue"
},
  "geometry": {"coordinates":[-82.218301,26.946827],"type":"Point"}
}