{
  "type": "Feature",
  "properties": {
    "addr:full":"6136 Sanctuary Garden Blvd Port Orange FL 32128",
    "addr:housenumber":"6136",
    "addr:postcode":"32128",
    "addr:street":"Sanctuary Garden Blvd",
    "iso:country":"US",
    "sg:address":"6136 Sanctuary Garden Blvd",
    "sg:city":"Port Orange",
    "sg:classifiers":[
        {
            "category":"Professional",
            "subcategory":"Management & Consulting",
            "type":"Services"
        }
    ],
    "sg:phone":"+1 386 304 0170",
    "sg:postcode":"32128",
    "sg:province":"FL",
    "sg:tags":[
        "consultant",
        "business"
    ],
    "wof:name":"Ray C Huther & Assoc",
    "wof:placetype":"venue"
},
  "geometry": {"coordinates":[-81.030404,29.078446],"type":"Point"}
}