{
  "type": "Feature",
  "properties": {
    "addr:full":"9520 Brentwood Blvd Gulf Breeze FL 32566",
    "addr:housenumber":"9520",
    "addr:postcode":"32566",
    "addr:street":"Brentwood Blvd",
    "iso:country":"US",
    "sg:address":"9520 Brentwood Blvd",
    "sg:city":"Gulf Breeze",
    "sg:classifiers":[
        {
            "category":"Shopping",
            "subcategory":"Bicycles & Sporting Goods",
            "type":"Retail Goods"
        }
    ],
    "sg:phone":"+1 850 939 8186",
    "sg:postcode":"32566",
    "sg:province":"FL",
    "wof:name":"Equine Goods",
    "wof:placetype":"venue"
},
  "geometry": {"coordinates":[-86.82590500000001,30.413924],"type":"Point"}
}