{
  "type": "Feature",
  "properties": {
    "iso:country":"US",
    "sg:address":"2389 N State Rd 7",
    "sg:city":"Fort Lauderdale",
    "sg:classifiers":[
        {
            "category":"Restaurant",
            "type":"Food & Drink"
        }
    ],
    "sg:phone":"+1 954 730 7442",
    "sg:postcode":"33317",
    "sg:province":"FL",
    "sg:tags":[
        "eating"
    ],
    "wof:name":"Unique Chicken & Ribs",
    "wof:placetype":"venue"
},
  "geometry": {"coordinates":[-80.203065,26.158839],"type":"Point"}
}