{
  "type": "Feature",
  "properties": {
    "addr:full":"6732 Spring Rain Dr Orlando FL 32819",
    "addr:housenumber":"6732",
    "addr:postcode":"32819",
    "addr:street":"Spring Rain Dr",
    "iso:country":"US",
    "sg:address":"6732 Spring Rain Dr",
    "sg:city":"Orlando",
    "sg:classifiers":[
        {
            "category":"Wholesale",
            "subcategory":"Chemicals & Plastics",
            "type":"Manufacturing & Wholesale Goods"
        }
    ],
    "sg:phone":"+1 407 351 6230",
    "sg:postcode":"32819",
    "sg:province":"FL",
    "sg:tags":[
        "cleaning",
        "compound"
    ],
    "wof:name":"Walvoord Enterprises",
    "wof:placetype":"venue"
},
  "geometry": {"coordinates":[-81.48986499999999,28.461416],"type":"Point"}
}