{
  "type": "Feature",
  "properties": {
    "addr:full":"10122 Lindelaan Dr Tampa FL 33618",
    "addr:postcode":"10122;33618",
    "addr:street":"Lindelaan Dr",
    "iso:country":"US",
    "sg:address":"10122 Lindelaan Dr",
    "sg:city":"Tampa",
    "sg:classifiers":[
        {
            "category":"Banks & Credit Unions",
            "subcategory":"Investment Brokerage",
            "type":"Services"
        }
    ],
    "sg:phone":"+1 813 932 8990",
    "sg:postcode":"33618",
    "sg:province":"FL",
    "sg:tags":[
        "security"
    ],
    "wof:name":"General Funding & Equity Inc",
    "wof:placetype":"venue"
},
  "geometry": {"coordinates":[-82.497122,28.043915],"type":"Point"}
}