{
  "type": "Feature",
  "properties": {
    "addr:full":"137 Millport St NW Port Charlotte FL 33948",
    "addr:housenumber":"137",
    "addr:postcode":"33948",
    "addr:street":"Millport St Nw",
    "iso:country":"US",
    "sg:address":"137 Millport St NW",
    "sg:city":"Port Charlotte",
    "sg:classifiers":[
        {
            "category":"Arts & Performance",
            "subcategory":"Theater",
            "type":"Entertainment"
        }
    ],
    "sg:phone":"+1 941 624 0438",
    "sg:postcode":"33948",
    "sg:province":"FL",
    "sg:tags":[
        "live",
        "music"
    ],
    "wof:name":"D J Sankey Sank",
    "wof:placetype":"venue"
},
  "geometry": {"coordinates":[-82.12439500000001,26.976291],"type":"Point"}
}