{
  "type": "Feature",
  "properties": {
    "iso:country":"US",
    "sg:address":"6270 Riverwalk Ln",
    "sg:city":"Jupiter",
    "sg:classifiers":[
        {
            "category":"Professional",
            "subcategory":"Employment Agencies",
            "type":"Services"
        }
    ],
    "sg:phone":"+1 561 339 2927",
    "sg:postcode":"33458",
    "sg:province":"FL",
    "sg:tags":[
        "opportunity"
    ],
    "wof:name":"First Choice Nannies Inc",
    "wof:placetype":"venue"
},
  "geometry": {"coordinates":[-80.12979900000001,26.938674],"type":"Point"}
}