{
  "type": "Feature",
  "properties": {
    "addr:full":"7212 SW 8th St Miami FL 33144",
    "addr:housenumber":"7212",
    "addr:postcode":"33144",
    "addr:street":"Sw 8Th St",
    "iso:country":"US",
    "sg:address":"7212 SW 8th St",
    "sg:city":"Miami",
    "sg:classifiers":[
        {
            "category":"Restaurant",
            "type":"Food & Drink"
        },
        {
            "category":"Food & Beverages",
            "subcategory":"Meat & Fish",
            "type":"Retail Goods"
        }
    ],
    "sg:phone":"+1 305 264 1448",
    "sg:postcode":"33144",
    "sg:province":"FL",
    "sg:tags":[
        "market",
        "style",
        "caribbean",
        "seafood",
        "family"
    ],
    "wof:name":"Bahamas Fish Market",
    "wof:placetype":"venue"
},
  "geometry": {"coordinates":[-80.31199599999999,25.762899],"type":"Point"}
}