{
  "type": "Feature",
  "properties": {
    "iso:country":"US",
    "sg:address":"151 Cedar Ave E",
    "sg:city":"Crestview",
    "sg:classifiers":[
        {
            "category":"Government",
            "subcategory":"Court House",
            "type":"Public Place"
        }
    ],
    "sg:phone":"+1 850 689 5620",
    "sg:postcode":"32536",
    "sg:province":"FL",
    "sg:tags":[
        "state",
        "counsel"
    ],
    "wof:name":"State Attorney",
    "wof:placetype":"venue"
},
  "geometry": {"coordinates":[-86.572247,30.762025],"type":"Point"}
}