{
  "type": "Feature",
  "properties": {
    "addr:full":"19101 Mystic Pointe Dr Apt 1903 Aventura FL 33180",
    "addr:housenumber":"19101",
    "addr:postcode":"1903;33180",
    "addr:street":"Mystic Pointe Dr Apt",
    "iso:country":"US",
    "sg:address":"19101 Mystic Pointe Dr Apt 1903",
    "sg:city":"Aventura",
    "sg:classifiers":[
        {
            "category":"Personal",
            "type":"Services"
        }
    ],
    "sg:phone":"+1 954 448 6888",
    "sg:postcode":"33180",
    "sg:province":"FL",
    "sg:tags":[
        "mover"
    ],
    "wof:name":"Sunshine Marine and Movers of South Florida",
    "wof:placetype":"venue"
},
  "geometry": {"coordinates":[-80.12760400000001,25.9527],"type":"Point"}
}