{
  "type": "Feature",
  "properties": {
    "addr:full":"2063 Amesbury Cir Wellington FL 33414",
    "addr:housenumber":"2063",
    "addr:postcode":"33414",
    "addr:street":"Amesbury Cir",
    "iso:country":"US",
    "sg:address":"2063 Amesbury Cir",
    "sg:city":"Wellington",
    "sg:classifiers":[
        {
            "category":"Professional",
            "subcategory":"Business Services",
            "type":"Services"
        },
        {
            "category":"Building & Trades",
            "subcategory":"Construction",
            "type":"Services"
        }
    ],
    "sg:phone":"+1 561 790 0859",
    "sg:postcode":"33414",
    "sg:province":"FL",
    "sg:tags":[
        "heavy"
    ],
    "wof:name":"David J Lueke Inc",
    "wof:placetype":"venue"
},
  "geometry": {"coordinates":[-80.247331,26.650422],"type":"Point"}
}