{
  "type": "Feature",
  "properties": {
    "addr:full":"9925 Ulmerton Rd Largo FL 33771",
    "addr:housenumber":"9925",
    "addr:postcode":"33771",
    "addr:street":"Ulmerton Rd",
    "iso:country":"US",
    "sg:address":"9925 Ulmerton Rd",
    "sg:city":"Largo",
    "sg:classifiers":[
        {
            "category":"Organizations",
            "subcategory":"Religious Organization",
            "type":"Services"
        }
    ],
    "sg:phone":"+1 727 585 0372",
    "sg:postcode":"33771",
    "sg:province":"FL",
    "sg:tags":[
        "clergy"
    ],
    "wof:name":"Shafer Ed & A I Rev",
    "wof:placetype":"venue"
},
  "geometry": {"coordinates":[-82.775672,27.89469],"type":"Point"}
}