{
  "type": "Feature",
  "properties": {
    "addr:full":"6262 Little Lake Sawyer Dr Windermere FL 34786",
    "addr:housenumber":"6262",
    "addr:postcode":"34786",
    "addr:street":"Little Lake Sawyer Dr",
    "iso:country":"US",
    "sg:address":"6262 Little Lake Sawyer Dr",
    "sg:city":"Windermere",
    "sg:classifiers":[
        {
            "category":"Professional",
            "subcategory":"Business Services",
            "type":"Services"
        }
    ],
    "sg:phone":"+1 407 654 8880",
    "sg:postcode":"34786",
    "sg:province":"FL",
    "sg:tags":[
        "interior",
        "consultant",
        "design",
        "decorator"
    ],
    "wof:name":"Lord Enterprise",
    "wof:placetype":"venue"
},
  "geometry": {"coordinates":[-81.57857799999999,28.474795],"type":"Point"}
}