{
  "type": "Feature",
  "properties": {
    "addr:full":"604 N Ocean Blvd Pompano Beach FL 33062",
    "addr:housenumber":"604",
    "addr:postcode":"33062",
    "addr:street":"N Ocean Blvd",
    "iso:country":"US",
    "sg:address":"604 N Ocean Blvd",
    "sg:city":"Pompano Beach",
    "sg:classifiers":[
        {
            "category":"Building & Trades",
            "subcategory":"Construction",
            "type":"Services"
        },
        {
            "category":"Retail",
            "subcategory":"Auto Repair",
            "type":"Services"
        }
    ],
    "sg:phone":"+1 954 942 5428",
    "sg:postcode":"33062",
    "sg:province":"FL",
    "sg:tags":[
        "glass",
        "coating",
        "tinting",
        "contractor"
    ],
    "wof:name":"A Ladies Touch Window Tinting",
    "wof:placetype":"venue"
},
  "geometry": {"coordinates":[-80.087868,26.242752],"type":"Point"}
}