{
  "type": "Feature",
  "properties": {
    "addr:full":"730 S US Hwy 17 San Mateo FL 32187",
    "addr:housenumber":"730",
    "addr:postcode":"32187",
    "addr:street":"S Us Hwy 17",
    "iso:country":"US",
    "sg:address":"730 S US Hwy 17",
    "sg:city":"San Mateo",
    "sg:classifiers":[
        {
            "category":"Professional",
            "type":"Services"
        }
    ],
    "sg:phone":"+1 386 312 0933",
    "sg:postcode":"32187",
    "sg:province":"FL",
    "sg:tags":[
        "establishment"
    ],
    "wof:name":"John B Valdez Co",
    "wof:placetype":"venue"
},
  "geometry": {"coordinates":[-81.606233,29.589593],"type":"Point"}
}