{
  "type": "Feature",
  "properties": {
    "iso:country":"US",
    "sg:address":"12046 Normandy Blvd",
    "sg:city":"Jacksonville",
    "sg:classifiers":[
        {
            "category":"Place Of Worship",
            "type":"Public Place"
        }
    ],
    "sg:phone":"+1 904 786 0757",
    "sg:postcode":"32221",
    "sg:province":"FL",
    "sg:tags":[
        "church"
    ],
    "wof:name":"Good Shepherd UMC",
    "wof:placetype":"venue"
},
  "geometry": {"coordinates":[-81.866004,30.259247],"type":"Point"}
}