{
  "type": "Feature",
  "properties": {
    "iso:country":"US",
    "sg:address":"141 June Ct",
    "sg:city":"Marco Island",
    "sg:classifiers":[
        {
            "category":"Professional",
            "subcategory":"Accounting & Tax Preparation",
            "type":"Services"
        }
    ],
    "sg:phone":"+1 239 642 4700",
    "sg:postcode":"34145",
    "sg:province":"FL",
    "sg:tags":[
        "payroll"
    ],
    "wof:name":"ADP Payroll Svc",
    "wof:placetype":"venue"
},
  "geometry": {"coordinates":[-81.721418,25.939749],"type":"Point"}
}