{
  "type": "Feature",
  "properties": {
    "iso:country":"US",
    "sg:address":"15911 NE 18th Ct",
    "sg:city":"North Miami Bch",
    "sg:classifiers":[
        {
            "category":"Professional",
            "subcategory":"Accounting & Tax Preparation",
            "type":"Services"
        }
    ],
    "sg:phone":"+1 305 944 0276",
    "sg:postcode":"33162",
    "sg:province":"FL",
    "sg:tags":[
        "bookkeeping",
        "general"
    ],
    "wof:name":"D J Accounting & Tax Svc Inc",
    "wof:placetype":"venue"
},
  "geometry": {"coordinates":[-80.16318699999999,25.924028],"type":"Point"}
}