{
  "type": "Feature",
  "properties": {
    "addr:full":"110 W Rich Ave Deland FL 32720",
    "addr:housenumber":"110",
    "addr:postcode":"32720",
    "addr:street":"W Rich Ave",
    "iso:country":"US",
    "sg:address":"110 W Rich Ave",
    "sg:city":"Deland",
    "sg:classifiers":[
        {
            "category":"Professional",
            "subcategory":"Engineering",
            "type":"Services"
        }
    ],
    "sg:phone":"+1 386 740 1454",
    "sg:postcode":"32720",
    "sg:province":"FL",
    "sg:tags":[
        "engineer"
    ],
    "wof:name":"CSI Engineering",
    "wof:placetype":"venue"
},
  "geometry": {"coordinates":[-81.303631,29.029816],"type":"Point"}
}