{
  "type": "Feature",
  "properties": {
    "addr:full":"13020 State Hwy 80 Fort Myers FL 33905",
    "addr:housenumber":"13020",
    "addr:postcode":"myers fl 33905",
    "addr:street":"State Hwy 80",
    "iso:country":"US",
    "sg:address":"13020 State Hwy 80",
    "sg:city":"Fort Myers",
    "sg:classifiers":[
        {
            "category":"Retail",
            "subcategory":"Animal Services",
            "type":"Services"
        }
    ],
    "sg:phone":"+1 239 694 9462",
    "sg:postcode":"33905",
    "sg:province":"FL",
    "wof:name":"Dapper Dog",
    "wof:placetype":"venue"
},
  "geometry": {"coordinates":[-81.750359,26.703959],"type":"Point"}
}