{
  "type": "Feature",
  "properties": {
    "iso:country":"US",
    "sg:address":"12601 60th St N",
    "sg:city":"Clearwater",
    "sg:classifiers":[
        {
            "category":"Professional",
            "subcategory":"Engineering",
            "type":"Services"
        },
        {
            "category":"Home & Garden",
            "subcategory":"Building Materials",
            "type":"Retail Goods"
        },
        {
            "category":"Building & Trades",
            "subcategory":"Construction",
            "type":"Services"
        }
    ],
    "sg:phone":"+1 727 572 1485",
    "sg:postcode":"33760",
    "sg:province":"FL",
    "sg:tags":[
        "system",
        "specialty",
        "heating",
        "equipment",
        "contractor",
        "air conditioning"
    ],
    "sg:website":"http://find.trane.com/tcs-dealer-401507?utm_source=YP&utm_medium=banner&utm_campaign=TL",
    "wof:name":"Pinellas Comfort Systems Inc, D/B/A/ Pcs, Inc.",
    "wof:placetype":"venue"
},
  "geometry": {"coordinates":[-82.716133,27.88641],"type":"Point"}
}