{
  "type": "Feature",
  "properties": {
    "iso:country":"US",
    "sg:address":"12177 S Apopka Vineland Rd",
    "sg:city":"Orlando",
    "sg:classifiers":[
        {
            "category":"Retail",
            "subcategory":"Laundry & Dry Cleaning",
            "type":"Services"
        }
    ],
    "sg:phone":"+1 407 239 0883",
    "sg:postcode":"32836",
    "sg:province":"FL",
    "sg:tags":[
        "cleaner",
        "commercial"
    ],
    "wof:name":"Majestic Cleaners & Laundry",
    "wof:placetype":"venue"
},
  "geometry": {"coordinates":[-81.50628,28.388378],"type":"Point"}
}