{
  "type": "Feature",
  "properties": {
    "iso:country":"US",
    "sg:address":"2655 Andros Ln",
    "sg:city":"Kissimmee",
    "sg:classifiers":[
        {
            "category":"Real Estate",
            "subcategory":"Real Estate Services",
            "type":"Services"
        },
        {
            "category":"Travel",
            "subcategory":"Resort",
            "type":"Entertainment"
        }
    ],
    "sg:phone":"+1 407 557 8999",
    "sg:postcode":"34747",
    "sg:province":"FL",
    "sg:tags":[
        "sharing",
        "sale",
        "vacation",
        "plan",
        "time",
        "home",
        "rental"
    ],
    "wof:name":"MyOrlandoStay.com LLC",
    "wof:placetype":"venue"
},
  "geometry": {"coordinates":[-81.591386,28.323228],"type":"Point"}
}