{
  "type": "Feature",
  "properties": {
    "addr:full":"623 US Hwy 27 Sebring FL 33870",
    "addr:housenumber":"623",
    "addr:postcode":"33870",
    "addr:street":"Us Hwy 27",
    "iso:country":"US",
    "sg:address":"623 US Hwy 27",
    "sg:city":"Sebring",
    "sg:classifiers":[
        {
            "category":"Bars & Pubs",
            "type":"Food & Drink"
        }
    ],
    "sg:phone":"+1 863 471 6200",
    "sg:postcode":"33870",
    "sg:province":"FL",
    "sg:tags":[
        "drinking"
    ],
    "wof:name":"Why Not Of Sebring Inc",
    "wof:placetype":"venue"
},
  "geometry": {"coordinates":[-81.475302,27.47773],"type":"Point"}
}