{
  "type": "Feature",
  "properties": {
    "iso:country":"US",
    "sg:address":"15251 Roosevelt Blvd",
    "sg:city":"Clearwater",
    "sg:classifiers":[
        {
            "category":"Wholesale",
            "subcategory":"Machinery & Supplies",
            "type":"Manufacturing & Wholesale Goods"
        },
        {
            "category":"Manufacturing",
            "subcategory":"Metals",
            "type":"Manufacturing & Wholesale Goods"
        }
    ],
    "sg:phone":"+1 727 533 8282",
    "sg:postcode":"33760",
    "sg:province":"FL",
    "sg:tags":[
        "treating",
        "equipment",
        "heat",
        "industrial"
    ],
    "sg:website":"www.nelcoproducts.com",
    "wof:name":"Nelco Products Inc",
    "wof:placetype":"venue"
},
  "geometry": {"coordinates":[-82.70191800000001,27.910686],"type":"Point"}
}