{
  "type": "Feature",
  "properties": {
    "iso:country":"US",
    "sg:address":"1532 SE 47th St",
    "sg:city":"Cape Coral",
    "sg:classifiers":[
        {
            "category":"Social Services",
            "type":"Services"
        }
    ],
    "sg:phone":"+1 239 540 0056",
    "sg:postcode":"33904",
    "sg:province":"FL",
    "sg:tags":[
        "organization",
        "welfare"
    ],
    "wof:name":"Goodwill Industries",
    "wof:placetype":"venue"
},
  "geometry": {"coordinates":[-81.944469,26.564552],"type":"Point"}
}