{
  "type": "Feature",
  "properties": {
    "iso:country":"US",
    "sg:address":"778 Little John Dr",
    "sg:city":"Chipley",
    "sg:classifiers":[
        {
            "category":"Personal",
            "subcategory":"Beauty Salon",
            "type":"Services"
        }
    ],
    "sg:phone":"+1 850 415 6304",
    "sg:postcode":"32428",
    "sg:province":"FL",
    "wof:name":"Mace Lavonda",
    "wof:placetype":"venue"
},
  "geometry": {"coordinates":[-85.509843,30.773342],"type":"Point"}
}