{
  "type": "Feature",
  "properties": {
    "iso:country":"US",
    "sg:address":"2425 Sunrise Blvd",
    "sg:city":"Fort Myers",
    "sg:classifiers":[
        {
            "category":"Professional",
            "type":"Services"
        }
    ],
    "sg:phone":"+1 239 939 5327",
    "sg:postcode":"33907",
    "sg:province":"FL",
    "wof:name":"Sage Cottage Crafts",
    "wof:placetype":"venue"
},
  "geometry": {"coordinates":[-81.856656,26.563062],"type":"Point"}
}