{
  "type": "Feature",
  "properties": {
    "iso:country":"US",
    "sg:address":"6217 N Federal Hwy",
    "sg:city":"Fort Lauderdale",
    "sg:classifiers":[
        {
            "category":"Restaurant",
            "type":"Food & Drink"
        }
    ],
    "sg:phone":"+1 954 491 4149",
    "sg:postcode":"33308",
    "sg:province":"FL",
    "sg:tags":[
        "eating"
    ],
    "wof:name":"Subway",
    "wof:placetype":"venue"
},
  "geometry": {"coordinates":[-80.108225,26.206472],"type":"Point"}
}