{
  "type": "Feature",
  "properties": {
    "addr:full":"4100 Pga Blvd Palm Beach Gardens FL 33410",
    "addr:housenumber":"4100",
    "addr:postcode":"33410",
    "addr:street":"Pga Blvd",
    "iso:country":"US",
    "sg:address":"4100 Pga Blvd",
    "sg:city":"Palm Beach Gardens",
    "sg:classifiers":[
        {
            "category":"Shopping",
            "subcategory":"Department Store",
            "type":"Retail Goods"
        }
    ],
    "sg:phone":"+1 561 627 5575",
    "sg:postcode":"33410",
    "sg:province":"FL",
    "wof:name":"Loehmanns Holdings Inc",
    "wof:placetype":"venue"
},
  "geometry": {"coordinates":[-80.098438,26.842978],"type":"Point"}
}