{
  "type": "Feature",
  "properties": {
    "iso:country":"US",
    "sg:address":"1021 E Main St",
    "sg:city":"Pahokee",
    "sg:classifiers":[
        {
            "category":"Professional",
            "subcategory":"Computer Services",
            "type":"Services"
        }
    ],
    "sg:phone":"+1 561 924 3022",
    "sg:postcode":"33476",
    "sg:province":"FL",
    "sg:tags":[
        "developer"
    ],
    "wof:name":"Concessive Technologies Inc",
    "wof:placetype":"venue"
},
  "geometry": {"coordinates":[-80.646297,26.840096],"type":"Point"}
}