{
  "type": "Feature",
  "properties": {
    "addr:full":"3825 W Silver Springs Blvd Ocala FL 34475",
    "addr:housenumber":"3825",
    "addr:postcode":"34475",
    "addr:street":"W Silver Springs Blvd",
    "iso:country":"US",
    "sg:address":"3825 W Silver Springs Blvd",
    "sg:city":"Ocala",
    "sg:classifiers":[
        {
            "category":"Autos & Motor Vehicles",
            "subcategory":"Fuel & Gas Station",
            "type":"Retail Goods"
        }
    ],
    "sg:phone":"+1 352 629 5319",
    "sg:postcode":"34475",
    "sg:province":"FL",
    "sg:tags":[
        "oil"
    ],
    "wof:name":"Shell",
    "wof:placetype":"venue"
},
  "geometry": {"coordinates":[-82.18932,29.186484],"type":"Point"}
}