{
  "type": "Feature",
  "properties": {
    "iso:country":"US",
    "sg:address":"701 NW Federal Hwy",
    "sg:city":"Stuart",
    "sg:classifiers":[
        {
            "category":"Insurance",
            "subcategory":"Insurance Agent",
            "type":"Services"
        }
    ],
    "sg:phone":"+1 772 692 4386",
    "sg:postcode":"34994",
    "sg:province":"FL",
    "wof:name":"Primerica",
    "wof:placetype":"venue"
},
  "geometry": {"coordinates":[-80.262002,27.218022],"type":"Point"}
}