{
  "type": "Feature",
  "properties": {
    "iso:country":"US",
    "sg:address":"1501 NW 13th Ct",
    "sg:city":"Miami",
    "sg:classifiers":[
        {
            "category":"Organizations",
            "subcategory":"Labor Organization",
            "type":"Services"
        }
    ],
    "sg:phone":"+1 305 326 0050",
    "sg:postcode":"33125",
    "sg:province":"FL",
    "wof:name":"Service Employees Intl Union",
    "wof:placetype":"venue"
},
  "geometry": {"coordinates":[-80.217949,25.789908],"type":"Point"}
}