{
  "type": "Feature",
  "properties": {
    "iso:country":"US",
    "sg:address":"312 John Ringling Blvd",
    "sg:city":"Sarasota",
    "sg:classifiers":[
        {
            "category":"Restaurant",
            "type":"Food & Drink"
        }
    ],
    "sg:phone":"+1 941 388 3200",
    "sg:postcode":"34236",
    "sg:province":"FL",
    "sg:tags":[
        "parlor",
        "ice",
        "cream"
    ],
    "wof:name":"Kilwins Chocolate",
    "wof:placetype":"venue"
},
  "geometry": {"coordinates":[-82.577083,27.317822],"type":"Point"}
}