{
  "type": "Feature",
  "properties": {
    "iso:country":"US",
    "sg:address":"6462 San Casa Dr",
    "sg:city":"Englewood",
    "sg:classifiers":[
        {
            "category":"Freight",
            "type":"Transportation"
        }
    ],
    "sg:phone":"+1 941 474 7212",
    "sg:postcode":"34224",
    "sg:province":"FL",
    "sg:tags":[
        "general"
    ],
    "wof:name":"U Store It",
    "wof:placetype":"venue"
},
  "geometry": {"coordinates":[-82.31292000000001,26.932569],"type":"Point"}
}