{
  "type": "Feature",
  "properties": {
    "addr:full":"7305 Southside Dr Groveland FL 34736",
    "addr:housenumber":"7305",
    "addr:postcode":"34736",
    "addr:street":"Southside Dr",
    "iso:country":"US",
    "sg:address":"7305 Southside Dr",
    "sg:city":"Groveland",
    "sg:classifiers":[
        {
            "category":"Building & Trades",
            "subcategory":"Construction",
            "type":"Services"
        }
    ],
    "sg:phone":"+1 352 429 2916",
    "sg:postcode":"34736",
    "sg:province":"FL",
    "sg:tags":[
        "house"
    ],
    "wof:name":"Alex Home Improvement",
    "wof:placetype":"venue"
},
  "geometry": {"coordinates":[-81.83439199999999,28.554577],"type":"Point"}
}