{
  "type": "Feature",
  "properties": {
    "iso:country":"US",
    "sg:address":"7375 Utilities Rd",
    "sg:city":"Punta Gorda",
    "sg:classifiers":[
        {
            "category":"Airline",
            "type":"Transportation"
        }
    ],
    "sg:phone":"+1 800 238 5355",
    "sg:postcode":"33982",
    "sg:province":"FL",
    "sg:tags":[
        "courier",
        "air"
    ],
    "wof:name":"Federal Express Corporation",
    "wof:placetype":"venue"
},
  "geometry": {"coordinates":[-82.004684,26.924439],"type":"Point"}
}