{
  "type": "Feature",
  "properties": {
    "iso:country":"US",
    "sg:address":"4798 Alfresco St",
    "sg:city":"Boca Raton",
    "sg:classifiers":[
        {
            "category":"Wholesale",
            "subcategory":"Construction Materials",
            "type":"Manufacturing & Wholesale Goods"
        }
    ],
    "sg:phone":"+1 561 483 9814",
    "sg:postcode":"33428",
    "sg:province":"FL",
    "sg:tags":[
        "marble"
    ],
    "wof:name":"Shine Marble Restoration Inc",
    "wof:placetype":"venue"
},
  "geometry": {"coordinates":[-80.215734,26.347723],"type":"Point"}
}