{
  "type": "Feature",
  "properties": {
    "addr:full":"153 W 29th St Hialeah FL 33012",
    "addr:housenumber":"153",
    "addr:postcode":"33012",
    "addr:street":"W 29Th St",
    "iso:country":"US",
    "sg:address":"153 W 29th St",
    "sg:city":"Hialeah",
    "sg:classifiers":[
        {
            "category":"Shopping",
            "subcategory":"Clothing, Apparel, & Fashions",
            "type":"Retail Goods"
        }
    ],
    "sg:phone":"+1 305 888 6900",
    "sg:postcode":"33012",
    "sg:province":"FL",
    "sg:tags":[
        "hair",
        "cosmetic",
        "beauty",
        "supply"
    ],
    "sg:website":"www.antialbeauty.com",
    "wof:name":"Antial Beauty Supply",
    "wof:placetype":"venue"
},
  "geometry": {"coordinates":[-80.285202,25.848101],"type":"Point"}
}