{
  "type": "Feature",
  "properties": {
    "iso:country":"US",
    "sg:address":"124 Rodgers Blvd",
    "sg:city":"Chiefland",
    "sg:classifiers":[
        {
            "category":"Wholesale",
            "subcategory":"Non-durable Goods",
            "type":"Manufacturing & Wholesale Goods"
        }
    ],
    "sg:phone":"+1 352 493 0977",
    "sg:postcode":"32626",
    "sg:province":"FL",
    "sg:tags":[
        "department",
        "military",
        "export",
        "store",
        "supply"
    ],
    "wof:name":"Sears Authorized Ret Dlr Str",
    "wof:placetype":"venue"
},
  "geometry": {"coordinates":[-82.85966000000001,29.487886],"type":"Point"}
}