{
  "type": "Feature",
  "properties": {
    "addr:full":"1451 SW 7th St Delray Beach FL 33444",
    "addr:housenumber":"1451",
    "addr:postcode":"33444",
    "addr:street":"Sw 7Th St",
    "iso:country":"US",
    "sg:address":"1451 SW 7th St",
    "sg:city":"Delray Beach",
    "sg:classifiers":[
        {
            "category":"Organizations",
            "subcategory":"Professional Association",
            "type":"Services"
        }
    ],
    "sg:phone":"+1 561 279 9945",
    "sg:postcode":"33444",
    "sg:province":"FL",
    "wof:name":"Delray Teen Society",
    "wof:placetype":"venue"
},
  "geometry": {"coordinates":[-80.08796700000001,26.450652],"type":"Point"}
}