{
  "type": "Feature",
  "properties": {
    "addr:full":"2954 NW 60th St Fort Lauderdale FL 33309",
    "addr:housenumber":"2954",
    "addr:postcode":"33309",
    "addr:street":"Nw 60Th St",
    "iso:country":"US",
    "sg:address":"2954 NW 60th St",
    "sg:city":"Fort Lauderdale",
    "sg:classifiers":[
        {
            "category":"Wholesale",
            "subcategory":"Hardware",
            "type":"Manufacturing & Wholesale Goods"
        }
    ],
    "sg:phone":"+1 954 973 7133",
    "sg:postcode":"33309",
    "sg:province":"FL",
    "wof:name":"Tower Fasteners Co Inc",
    "wof:placetype":"venue"
},
  "geometry": {"coordinates":[-80.185519,26.200417],"type":"Point"}
}