{
  "type": "Feature",
  "properties": {
    "addr:full":"265 US Hwy 92 Longwood FL 32750",
    "addr:housenumber":"265",
    "addr:postcode":"32750",
    "addr:street":"Us Hwy 92",
    "iso:country":"US",
    "sg:address":"265 US Hwy 92",
    "sg:city":"Longwood",
    "sg:classifiers":[
        {
            "category":"Autos & Motor Vehicles",
            "subcategory":"Automobile Sales",
            "type":"Retail Goods"
        }
    ],
    "sg:phone":"+1 407 695 9100",
    "sg:postcode":"32750",
    "sg:province":"FL",
    "sg:tags":[
        "new",
        "used"
    ],
    "wof:name":"Fields BMW",
    "wof:placetype":"venue"
},
  "geometry": {"coordinates":[-81.326899,28.698358],"type":"Point"}
}