{
  "type": "Feature",
  "properties": {
    "iso:country":"US",
    "sg:address":"825 E Venice Ave",
    "sg:city":"Venice",
    "sg:classifiers":[
        {
            "category":"Home & Garden",
            "subcategory":"Carpets & Floor Coverings",
            "type":"Retail Goods"
        }
    ],
    "sg:phone":"+1 941 488 1810",
    "sg:postcode":"34285",
    "sg:province":"FL",
    "wof:name":"Montgomerys Carpetsplus",
    "wof:placetype":"venue"
},
  "geometry": {"coordinates":[-82.429917,27.099849],"type":"Point"}
}