{
  "type": "Feature",
  "properties": {
    "iso:country":"US",
    "sg:address":"4001 Hendricks Ave",
    "sg:city":"Jacksonville",
    "sg:classifiers":[
        {
            "category":"Organizations",
            "subcategory":"Membership Organization",
            "type":"Services"
        }
    ],
    "sg:phone":"+1 904 348 6325",
    "sg:postcode":"32207",
    "sg:province":"FL",
    "sg:tags":[
        "athletic"
    ],
    "sg:website":"www.hacaa.org",
    "wof:name":"Hendrick Ave Community Athltcs",
    "wof:placetype":"venue"
},
  "geometry": {"coordinates":[-81.650891,30.280417],"type":"Point"}
}