{
  "type": "Feature",
  "properties": {
    "iso:country":"US",
    "sg:address":"3000 SW 10th St",
    "sg:city":"Pompano Beach",
    "sg:classifiers":[
        {
            "category":"Building & Trades",
            "subcategory":"Construction",
            "type":"Services"
        }
    ],
    "sg:phone":"+1 954 984 9555",
    "sg:postcode":"33069",
    "sg:province":"FL",
    "sg:tags":[
        "concrete",
        "restoration",
        "cleaning",
        "repair"
    ],
    "sg:website":"www.structural.net",
    "wof:name":"Structural Preservation System",
    "wof:placetype":"venue"
},
  "geometry": {"coordinates":[-80.16531500000001,26.21583],"type":"Point"}
}