{
  "type": "Feature",
  "properties": {
    "iso:country":"US",
    "sg:address":"2235 Howland Blvd",
    "sg:city":"Deltona",
    "sg:classifiers":[
        {
            "category":"Taxi",
            "type":"Transportation"
        }
    ],
    "sg:phone":"+1 386 748 4092",
    "sg:postcode":"32738",
    "sg:province":"FL",
    "sg:tags":[
        "taxicab",
        "airport"
    ],
    "wof:name":"Red Cab",
    "wof:placetype":"venue"
},
  "geometry": {"coordinates":[-81.192599,28.926846],"type":"Point"}
}