{
  "type": "Feature",
  "properties": {
    "addr:full":"434 Bear Rd NW Fort Walton Bch FL 32547",
    "addr:housenumber":"434",
    "addr:postcode":"32547",
    "addr:street":"Bear Rd Nw Fort",
    "iso:country":"US",
    "sg:address":"434 Bear Rd NW",
    "sg:city":"Fort Walton Bch",
    "sg:classifiers":[
        {
            "category":"Organizations",
            "subcategory":"Non-profit Organization",
            "type":"Services"
        }
    ],
    "sg:phone":"+1 850 862 8885",
    "sg:postcode":"32547",
    "sg:province":"FL",
    "wof:name":"Horizon's Of Okaloosa Co Inc",
    "wof:placetype":"venue"
},
  "geometry": {"coordinates":[-86.62403500000001,30.455766],"type":"Point"}
}