{
  "type": "Feature",
  "properties": {
    "addr:full":"2 E Nine Mile Rd Pensacola FL 32534",
    "addr:housenumber":"2",
    "addr:postcode":"32534",
    "addr:street":"E Nine Mile Rd",
    "iso:country":"US",
    "sg:address":"2 E Nine Mile Rd",
    "sg:city":"Pensacola",
    "sg:classifiers":[
        {
            "category":"Restaurant",
            "type":"Food & Drink"
        }
    ],
    "sg:menulink":"http://www.allmenus.com/fl/pensacola/92063-firehouse-subs/menu/",
    "sg:phone":"+1 850 478 2334",
    "sg:postcode":"32534",
    "sg:province":"FL",
    "sg:tags":[
        "wrap",
        "american",
        "sandwich"
    ],
    "wof:name":"Firehouse Subs",
    "wof:placetype":"venue"
},
  "geometry": {"coordinates":[-87.273714,30.533296],"type":"Point"}
}