{
  "type": "Feature",
  "properties": {
    "addr:full":"100 Ponte Vedra Pointe Blvd Ponte Vedra Beach FL 32082",
    "addr:housenumber":"100",
    "addr:postcode":"32082",
    "addr:street":"Ponte Vedra Pointe Blvd",
    "iso:country":"US",
    "sg:address":"100 Ponte Vedra Pointe Blvd",
    "sg:city":"Ponte Vedra Beach",
    "sg:classifiers":[
        {
            "category":"Restaurant",
            "type":"Food & Drink"
        }
    ],
    "sg:menulink":"http://www.allmenus.com/fl/ponte-vedra/187624-mcdonalds/menu/",
    "sg:phone":"+1 904 273 7490",
    "sg:postcode":"32082",
    "sg:province":"FL",
    "sg:tags":[
        "burger",
        "american"
    ],
    "wof:name":"McDonald's",
    "wof:placetype":"venue"
},
  "geometry": {"coordinates":[-81.38084600000001,30.19243],"type":"Point"}
}