{
  "type": "Feature",
  "properties": {
    "iso:country":"US",
    "sg:address":"25201 Hyde Park Blvd",
    "sg:city":"Land O Lakes",
    "sg:classifiers":[
        {
            "category":"Professional",
            "subcategory":"Management & Consulting",
            "type":"Services"
        }
    ],
    "sg:phone":"+1 813 907 9263",
    "sg:postcode":"34639",
    "sg:province":"FL",
    "sg:tags":[
        "retail",
        "direct",
        "sales"
    ],
    "wof:name":"Stewart Venita",
    "wof:placetype":"venue"
},
  "geometry": {"coordinates":[-82.399254,28.201423],"type":"Point"}
}