{
  "type": "Feature",
  "properties": {
    "iso:country":"US",
    "sg:address":"5764 Wingate Dr",
    "sg:city":"Orlando",
    "sg:classifiers":[
        {
            "category":"Social Services",
            "subcategory":"Child Care",
            "type":"Services"
        }
    ],
    "sg:phone":"+1 407 352 2703",
    "sg:postcode":"32839",
    "sg:province":"FL",
    "wof:name":"Kiddos World Fam Day Care Inc",
    "wof:placetype":"venue"
},
  "geometry": {"coordinates":[-81.42441700000001,28.475465],"type":"Point"}
}