{
  "type": "Feature",
  "properties": {
    "addr:full":"14502 Salem Church Rd Dover FL 33527",
    "addr:housenumber":"14502",
    "addr:postcode":"33527",
    "addr:street":"Salem Church Rd",
    "iso:country":"US",
    "sg:address":"14502 Salem Church Rd",
    "sg:city":"Dover",
    "sg:classifiers":[
        {
            "category":"Building & Trades",
            "subcategory":"Construction",
            "type":"Services"
        }
    ],
    "sg:phone":"+1 813 659 0818",
    "sg:postcode":"33527",
    "sg:province":"FL",
    "sg:tags":[
        "house"
    ],
    "wof:name":"Hudnall Construction Inc",
    "wof:placetype":"venue"
},
  "geometry": {"coordinates":[-82.211842,27.961887],"type":"Point"}
}