{
  "type": "Feature",
  "properties": {
    "addr:full":"1114 Vizcaya Lake Rd Ocoee FL 34761",
    "addr:housenumber":"1114",
    "addr:postcode":"34761",
    "addr:street":"Vizcaya Lake Rd",
    "iso:country":"US",
    "sg:address":"1114 Vizcaya Lake Rd",
    "sg:city":"Ocoee",
    "sg:classifiers":[
        {
            "category":"Building & Trades",
            "subcategory":"Construction",
            "type":"Services"
        }
    ],
    "sg:phone":"+1 407 521 7054",
    "sg:postcode":"34761",
    "sg:province":"FL",
    "sg:tags":[
        "house"
    ],
    "wof:name":"Kem Construction Inc",
    "wof:placetype":"venue"
},
  "geometry": {"coordinates":[-81.509108,28.550808],"type":"Point"}
}