{
  "type": "Feature",
  "properties": {
    "addr:full":"514 Southern Ave Lakeland FL 33815",
    "addr:housenumber":"514",
    "addr:postcode":"33815",
    "addr:street":"Southern Ave",
    "iso:country":"US",
    "sg:address":"514 Southern Ave",
    "sg:city":"Lakeland",
    "sg:classifiers":[
        {
            "category":"Shopping",
            "subcategory":"Used Merchandise",
            "type":"Retail Goods"
        }
    ],
    "sg:phone":"+1 863 683 4980",
    "sg:postcode":"33815",
    "sg:province":"FL",
    "sg:tags":[
        "appliance"
    ],
    "wof:name":"Good's Used Appliances",
    "wof:placetype":"venue"
},
  "geometry": {"coordinates":[-81.985857,28.037841],"type":"Point"}
}