{
  "type": "Feature",
  "properties": {
    "addr:full":"2437 SE 17th St Ocala FL 34471",
    "addr:housenumber":"2437",
    "addr:postcode":"34471",
    "addr:street":"Se 17Th St",
    "iso:country":"US",
    "sg:address":"2437 SE 17th St",
    "sg:city":"Ocala",
    "sg:classifiers":[
        {
            "category":"Professional",
            "subcategory":"Management & Consulting",
            "type":"Services"
        }
    ],
    "sg:phone":"+1 352 351 1646",
    "sg:postcode":"34471",
    "sg:province":"FL",
    "wof:name":"Coke & Assoc",
    "wof:placetype":"venue"
},
  "geometry": {"coordinates":[-82.103692,29.171566],"type":"Point"}
}