{
  "type": "Feature",
  "properties": {
    "addr:full":"18495 Biscayne Blvd Aventura FL 33160",
    "addr:housenumber":"18495",
    "addr:postcode":"33160",
    "addr:street":"Biscayne Blvd",
    "iso:country":"US",
    "sg:address":"18495 Biscayne Blvd",
    "sg:city":"Aventura",
    "sg:classifiers":[
        {
            "category":"Shopping",
            "subcategory":"Department Store",
            "type":"Retail Goods"
        },
        {
            "category":"Shopping",
            "subcategory":"Clothing, Apparel, & Fashions",
            "type":"Retail Goods"
        },
        {
            "category":"Shopping",
            "subcategory":"Discount & Variety Stores",
            "type":"Retail Goods"
        }
    ],
    "sg:phone":"+1 305 933 8656",
    "sg:postcode":"33160",
    "sg:province":"FL",
    "sg:tags":[
        "rental",
        "sale",
        "women's",
        "wear",
        "apparel",
        "clothing",
        "boys'",
        "formal"
    ],
    "sg:website":"http://www.rossstores.com",
    "wof:name":"Ross Dress For Less",
    "wof:placetype":"venue"
},
  "geometry": {"coordinates":[-80.146901,25.94733],"type":"Point"}
}