{
  "type": "Feature",
  "properties": {
    "iso:country":"US",
    "sg:address":"1903 Leila Pl",
    "sg:city":"Lakeland",
    "sg:classifiers":[
        {
            "category":"Building & Trades",
            "subcategory":"Cleaning & Sanitation",
            "type":"Services"
        }
    ],
    "sg:phone":"+1 863 682 2858",
    "sg:postcode":"33805",
    "sg:province":"FL",
    "sg:tags":[
        "janitor"
    ],
    "wof:name":"Xtremely Clean Svc",
    "wof:placetype":"venue"
},
  "geometry": {"coordinates":[-81.922314,28.120879],"type":"Point"}
}