{
  "type": "Feature",
  "properties": {
    "addr:full":"8353 NW 17th Ave Miami FL 33147",
    "addr:housenumber":"8353",
    "addr:postcode":"33147",
    "addr:street":"Nw 17Th Ave",
    "iso:country":"US",
    "sg:address":"8353 NW 17th Ave",
    "sg:city":"Miami",
    "sg:classifiers":[
        {
            "category":"Personal",
            "subcategory":"Beauty Salon",
            "type":"Services"
        }
    ],
    "sg:phone":"+1 305 324 6456",
    "sg:postcode":"33147",
    "sg:province":"FL",
    "sg:tags":[
        "shop"
    ],
    "wof:name":"La Elegante Unisex II",
    "wof:placetype":"venue"
},
  "geometry": {"coordinates":[-80.22548,25.85158],"type":"Point"}
}