{
  "type": "Feature",
  "properties": {
    "iso:country":"US",
    "sg:address":"8413 NW 68th St",
    "sg:city":"Miami",
    "sg:classifiers":[
        {
            "category":"Wholesale",
            "subcategory":"Electrical",
            "type":"Manufacturing & Wholesale Goods"
        }
    ],
    "sg:phone":"+1 305 593 9994",
    "sg:postcode":"33166",
    "sg:province":"FL",
    "sg:tags":[
        "security",
        "product",
        "prevention"
    ],
    "wof:name":"VENELINT",
    "wof:placetype":"venue"
},
  "geometry": {"coordinates":[-80.33788699999999,25.835317],"type":"Point"}
}