{
  "type": "Feature",
  "properties": {
    "iso:country":"US",
    "sg:address":"6080 S Apopka Vineland Rd",
    "sg:city":"Orlando",
    "sg:classifiers":[
        {
            "category":"Health Services",
            "subcategory":"Doctor",
            "type":"Services"
        }
    ],
    "sg:phone":"+1 407 351 7083",
    "sg:postcode":"34786",
    "sg:province":"FL",
    "sg:tags":[
        "dentist"
    ],
    "wof:name":"Bay Hill Family Dentistry",
    "wof:placetype":"venue"
},
  "geometry": {"coordinates":[-81.507535,28.47235],"type":"Point"}
}