{
  "type": "Feature",
  "properties": {
    "iso:country":"US",
    "sg:address":"2100 NW 110th Ave",
    "sg:city":"Miami",
    "sg:classifiers":[
        {
            "category":"Home & Garden",
            "subcategory":"Furniture",
            "type":"Retail Goods"
        }
    ],
    "sg:phone":"+1 305 593 1990",
    "sg:postcode":"33172",
    "sg:province":"FL",
    "wof:name":"Rooms To Go",
    "wof:placetype":"venue"
},
  "geometry": {"coordinates":[-80.374334,25.793335],"type":"Point"}
}