{
  "type": "Feature",
  "properties": {
    "iso:country":"US",
    "sg:address":"1113 15th St SE",
    "sg:city":"Ruskin",
    "sg:classifiers":[
        {
            "category":"Building & Trades",
            "subcategory":"Construction",
            "type":"Services"
        }
    ],
    "sg:phone":"+1 813 645 1979",
    "sg:postcode":"33570",
    "sg:province":"FL",
    "sg:tags":[
        "farm",
        "house"
    ],
    "wof:name":"Sanchez Tropical",
    "wof:placetype":"venue"
},
  "geometry": {"coordinates":[-82.41476299999999,27.708854],"type":"Point"}
}