{
  "type": "Feature",
  "properties": {
    "addr:full":"2427 S Hiawassee Rd Orlando FL 32835",
    "addr:housenumber":"2427",
    "addr:postcode":"32835",
    "addr:street":"S Hiawassee Rd",
    "iso:country":"US",
    "sg:address":"2427 S Hiawassee Rd",
    "sg:city":"Orlando",
    "sg:classifiers":[
        {
            "category":"Personal",
            "subcategory":"Beauty Salon",
            "type":"Services"
        }
    ],
    "sg:phone":"+1 407 578 2077",
    "sg:postcode":"32835",
    "sg:province":"FL",
    "wof:name":"Hair Masters",
    "wof:placetype":"venue"
},
  "geometry": {"coordinates":[-81.48487799999999,28.515933],"type":"Point"}
}