{
  "type": "Feature",
  "properties": {
    "iso:country":"US",
    "sg:address":"416 1/2 N Orange Ave Unit 2",
    "sg:city":"Deland",
    "sg:classifiers":[
        {
            "category":"Shopping",
            "subcategory":"Bicycles & Sporting Goods",
            "type":"Retail Goods"
        }
    ],
    "sg:phone":"+1 386 736 7856",
    "sg:postcode":"32720",
    "sg:province":"FL",
    "wof:name":"A & F Sporting Goods",
    "wof:placetype":"venue"
},
  "geometry": {"coordinates":[-81.31432599999999,29.034304],"type":"Point"}
}