{
  "type": "Feature",
  "properties": {
    "addr:full":"10475 SE US Hwy 441 Belleview FL 34420",
    "addr:postcode":"10475;34420",
    "addr:street":"Se Us Hwy 441",
    "iso:country":"US",
    "sg:address":"10475 SE US Hwy 441",
    "sg:city":"Belleview",
    "sg:classifiers":[
        {
            "category":"Wholesale",
            "subcategory":"Medical Equipment & Supplies",
            "type":"Manufacturing & Wholesale Goods"
        },
        {
            "category":"Building & Trades",
            "subcategory":"Equipment Rental",
            "type":"Services"
        }
    ],
    "sg:phone":"+1 352 307 9191",
    "sg:postcode":"34420",
    "sg:province":"FL",
    "sg:tags":[
        "physician",
        "surgeon"
    ],
    "wof:name":"Comfort Care Medical Equip Inc",
    "wof:placetype":"venue"
},
  "geometry": {"coordinates":[-82.070948,29.070116],"type":"Point"}
}