{
  "type": "Feature",
  "properties": {
    "iso:country":"US",
    "sg:address":"712 E 5th St",
    "sg:city":"Jacksonville",
    "sg:classifiers":[
        {
            "category":"Social Services",
            "subcategory":"Child Care",
            "type":"Services"
        }
    ],
    "sg:phone":"+1 904 359 0101",
    "sg:postcode":"32206",
    "sg:province":"FL",
    "wof:name":"Valerie's Little Angels",
    "wof:placetype":"venue"
},
  "geometry": {"coordinates":[-81.643283,30.341908],"type":"Point"}
}