{
  "type": "Feature",
  "properties": {
    "iso:country":"US",
    "sg:address":"5519 Gemstone Rd",
    "sg:city":"Bascom",
    "sg:classifiers":[
        {
            "category":"Manufacturing",
            "subcategory":"Textiles",
            "type":"Manufacturing & Wholesale Goods"
        }
    ],
    "sg:phone":"+1 850 569 2392",
    "sg:postcode":"32423",
    "sg:province":"FL",
    "sg:tags":[
        "broker",
        "cotton"
    ],
    "wof:name":"Thomas Ditty",
    "wof:placetype":"venue"
},
  "geometry": {"coordinates":[-85.117997,30.963572],"type":"Point"}
}