{
  "type": "Feature",
  "properties": {
    "iso:country":"US",
    "sg:address":"3503 Westview Dr",
    "sg:city":"Naples",
    "sg:classifiers":[
        {
            "category":"Professional",
            "type":"Services"
        }
    ],
    "sg:phone":"+1 239 643 5407",
    "sg:postcode":"34104",
    "sg:province":"FL",
    "sg:tags":[
        "establishment"
    ],
    "wof:name":"Airborne Express",
    "wof:placetype":"venue"
},
  "geometry": {"coordinates":[-81.760645,26.150629],"type":"Point"}
}