{
  "type": "Feature",
  "properties": {
    "addr:full":"1 Stadium Dr Saint Petersburg FL 33705",
    "addr:housenumber":"1",
    "addr:postcode":"33705",
    "addr:street":"Stadium Dr",
    "iso:country":"US",
    "sg:address":"1 Stadium Dr",
    "sg:city":"Saint Petersburg",
    "sg:classifiers":[
        {
            "category":"Restaurant",
            "type":"Food & Drink"
        }
    ],
    "sg:phone":"+1 727 825 3361",
    "sg:postcode":"33705",
    "sg:province":"FL",
    "sg:tags":[
        "concession"
    ],
    "wof:name":"Sportservice Corporation",
    "wof:placetype":"venue"
},
  "geometry": {"coordinates":[-82.655928,27.766596],"type":"Point"}
}