{
  "type": "Feature",
  "properties": {
    "addr:full":"3805 Hillview Ct Land O Lakes FL 34639",
    "addr:housenumber":"3805",
    "addr:postcode":"34639",
    "addr:street":"Hillview Ct",
    "iso:country":"US",
    "sg:address":"3805 Hillview Ct",
    "sg:city":"Land O Lakes",
    "sg:classifiers":[
        {
            "category":"Professional",
            "subcategory":"Computer Services",
            "type":"Services"
        }
    ],
    "sg:phone":"+1 813 376 1104",
    "sg:postcode":"34639",
    "sg:province":"FL",
    "sg:tags":[
        "related"
    ],
    "wof:name":"Bcc of Tampa",
    "wof:placetype":"venue"
},
  "geometry": {"coordinates":[-82.42860899999999,28.212063],"type":"Point"}
}