{
  "type": "Feature",
  "properties": {
    "iso:country":"US",
    "sg:address":"1503 SE Riverside Dr",
    "sg:city":"Stuart",
    "sg:classifiers":[
        {
            "category":"Professional",
            "subcategory":"Management & Consulting",
            "type":"Services"
        }
    ],
    "sg:phone":"+1 772 219 0400",
    "sg:postcode":"34996",
    "sg:province":"FL",
    "sg:tags":[
        "marketing",
        "consultant"
    ],
    "wof:name":"Real World Group Inc",
    "wof:placetype":"venue"
},
  "geometry": {"coordinates":[-80.22704899999999,27.202798],"type":"Point"}
}