{
  "type": "Feature",
  "properties": {
    "iso:country":"US",
    "sg:address":"1600 Airport Blvd",
    "sg:city":"Pensacola",
    "sg:classifiers":[
        {
            "category":"Personal",
            "subcategory":"Beauty Salon",
            "type":"Services"
        }
    ],
    "sg:phone":"+1 850 477 8297",
    "sg:postcode":"32504",
    "sg:province":"FL",
    "wof:name":"Le Salon Miki Callahan & Co",
    "wof:placetype":"venue"
},
  "geometry": {"coordinates":[-87.20850799999999,30.480594],"type":"Point"}
}