{
  "type": "Feature",
  "properties": {
    "addr:full":"12020 McCormick Rd Jacksonville FL 32225",
    "addr:housenumber":"12020",
    "addr:postcode":"32225",
    "addr:street":"Mccormick Rd",
    "iso:country":"US",
    "sg:address":"12020 McCormick Rd",
    "sg:city":"Jacksonville",
    "sg:classifiers":[
        {
            "category":"Freight",
            "type":"Transportation"
        }
    ],
    "sg:phone":"+1 904 641 3000",
    "sg:postcode":"32225",
    "sg:province":"FL",
    "sg:tags":[
        "special",
        "general"
    ],
    "wof:name":"Monument Mini-Storage Inc",
    "wof:placetype":"venue"
},
  "geometry": {"coordinates":[-81.49709900000001,30.359899],"type":"Point"}
}