{
  "type": "Feature",
  "properties": {
    "addr:full":"204 51st Ave E Bradenton FL 34203",
    "addr:housenumber":"204",
    "addr:postcode":"34203",
    "addr:street":"51St Ave E",
    "iso:country":"US",
    "sg:address":"204 51st Ave E",
    "sg:city":"Bradenton",
    "sg:classifiers":[
        {
            "category":"Shopping",
            "subcategory":"Gifts & Souvenirs",
            "type":"Retail Goods"
        }
    ],
    "sg:phone":"+1 941 744 0248",
    "sg:postcode":"34203",
    "sg:province":"FL",
    "wof:name":"Lighthouse Keepers Closet",
    "wof:placetype":"venue"
},
  "geometry": {"coordinates":[-82.56105599999999,27.451158],"type":"Point"}
}