{
  "type": "Feature",
  "properties": {
    "iso:country":"US",
    "sg:address":"14 Bamboo Ln",
    "sg:city":"Jupiter",
    "sg:classifiers":[
        {
            "category":"Professional",
            "subcategory":"Secretarial Services",
            "type":"Services"
        }
    ],
    "sg:phone":"+1 561 747 7065",
    "sg:postcode":"33458",
    "sg:province":"FL",
    "sg:tags":[
        "typing"
    ],
    "wof:name":"Professional Typing Co",
    "wof:placetype":"venue"
},
  "geometry": {"coordinates":[-80.12250299999999,26.960604],"type":"Point"}
}