{
  "type": "Feature",
  "properties": {
    "addr:full":"743 E Memorial Blvd Lakeland FL 33801",
    "addr:housenumber":"743",
    "addr:postcode":"33801",
    "addr:street":"E Memorial Blvd",
    "iso:country":"US",
    "sg:address":"743 E Memorial Blvd",
    "sg:city":"Lakeland",
    "sg:classifiers":[
        {
            "category":"Restaurant",
            "type":"Food & Drink"
        }
    ],
    "sg:phone":"+1 863 686 2052",
    "sg:postcode":"33801",
    "sg:province":"FL",
    "wof:name":"Pan Ye's Restaurant",
    "wof:placetype":"venue"
},
  "geometry": {"coordinates":[-81.95057199999999,28.054943],"type":"Point"}
}