{
  "type": "Feature",
  "properties": {
    "iso:country":"US",
    "sg:address":"428 Collins Ave Ste 8",
    "sg:city":"Miami Beach",
    "sg:classifiers":[
        {
            "category":"Government",
            "subcategory":"City Hall",
            "type":"Public Place"
        }
    ],
    "sg:phone":"+1 786 253 2222",
    "sg:postcode":"33139",
    "sg:province":"FL",
    "sg:website":"fertileearth.org",
    "wof:name":"Fertile Earth",
    "wof:placetype":"venue"
},
  "geometry": {"coordinates":[-80.13314800000001,25.773955],"type":"Point"}
}