{
  "type": "Feature",
  "properties": {
    "iso:country":"US",
    "sg:address":"7318 Myrtle Rd",
    "sg:city":"Fort Myers",
    "sg:classifiers":[
        {
            "category":"Building & Trades",
            "subcategory":"Electrical",
            "type":"Services"
        }
    ],
    "sg:phone":"+1 239 267 7277",
    "sg:postcode":"33967",
    "sg:province":"FL",
    "sg:tags":[
        "electrical",
        "contractor"
    ],
    "wof:name":"Henderson Electric",
    "wof:placetype":"venue"
},
  "geometry": {"coordinates":[-81.829368,26.47044],"type":"Point"}
}