{
  "type": "Feature",
  "properties": {
    "iso:country":"US",
    "sg:address":"910 S 6th Ave",
    "sg:city":"Wauchula",
    "sg:classifiers":[
        {
            "category":"Real Estate",
            "subcategory":"Real Estate Services",
            "type":"Services"
        },
        {
            "category":"Insurance",
            "subcategory":"Hazard Insurance",
            "type":"Services"
        }
    ],
    "sg:phone":"+1 863 773 3251",
    "sg:postcode":"33873",
    "sg:province":"FL",
    "sg:tags":[
        "management",
        "commercial",
        "business"
    ],
    "wof:name":"Wachula Insurance Agency",
    "wof:placetype":"venue"
},
  "geometry": {"coordinates":[-81.80944100000001,27.536501],"type":"Point"}
}