{
  "type": "Feature",
  "properties": {
    "addr:full":"915 Harbor Lake Dr Safety Harbor FL 34695",
    "addr:housenumber":"915",
    "addr:postcode":"34695",
    "addr:street":"Harbor Lake Dr",
    "iso:country":"US",
    "sg:address":"915 Harbor Lake Dr",
    "sg:city":"Safety Harbor",
    "sg:classifiers":[
        {
            "category":"Retail",
            "subcategory":"Auto Repair",
            "type":"Services"
        }
    ],
    "sg:phone":"+1 727 723 8504",
    "sg:postcode":"34695",
    "sg:province":"FL",
    "sg:tags":[
        "repairing",
        "automobile"
    ],
    "wof:name":"Paragon Automotive",
    "wof:placetype":"venue"
},
  "geometry": {"coordinates":[-82.699647,27.999341],"type":"Point"}
}