{
  "type": "Feature",
  "properties": {
    "iso:country":"US",
    "sg:address":"3333 S Miami Ave",
    "sg:city":"Miami",
    "sg:classifiers":[
        {
            "category":"Social Services",
            "type":"Services"
        }
    ],
    "sg:phone":"+1 305 856 7075",
    "sg:postcode":"33133",
    "sg:province":"FL",
    "wof:name":"Youth Encounter",
    "wof:placetype":"venue"
},
  "geometry": {"coordinates":[-80.21066399999999,25.747214],"type":"Point"}
}