{
  "type": "Feature",
  "properties": {
    "iso:country":"US",
    "sg:address":"7889 NW 98th St",
    "sg:city":"Hialeah",
    "sg:classifiers":[
        {
            "category":"Organizations",
            "subcategory":"Professional Association",
            "type":"Services"
        }
    ],
    "sg:phone":"+1 305 556 5156",
    "sg:postcode":"33016",
    "sg:province":"FL",
    "sg:tags":[
        "pressure",
        "plastics-high",
        "laminate"
    ],
    "wof:name":"Advak Technologies Inc",
    "wof:placetype":"venue"
},
  "geometry": {"coordinates":[-80.325489,25.862511],"type":"Point"}
}