{
  "type": "Feature",
  "properties": {
    "addr:full":"5204 Hawks Nest Dr Milton FL 32570",
    "addr:housenumber":"5204",
    "addr:postcode":"32570",
    "addr:street":"Hawks Nest Dr",
    "iso:country":"US",
    "sg:address":"5204 Hawks Nest Dr",
    "sg:city":"Milton",
    "sg:classifiers":[
        {
            "category":"Building & Trades",
            "subcategory":"Cleaning & Sanitation",
            "type":"Services"
        }
    ],
    "sg:phone":"+1 850 982 1312",
    "sg:postcode":"32570",
    "sg:province":"FL",
    "sg:tags":[
        "janitor"
    ],
    "wof:name":"Special Touch Cleaning Svc",
    "wof:placetype":"venue"
},
  "geometry": {"coordinates":[-87.066968,30.624416],"type":"Point"}
}