{
  "type": "Feature",
  "properties": {
    "iso:country":"US",
    "sg:address":"811 NW 13th Ave",
    "sg:city":"Pompano Beach",
    "sg:classifiers":[
        {
            "category":"Wholesale",
            "subcategory":"Scrap",
            "type":"Manufacturing & Wholesale Goods"
        }
    ],
    "sg:phone":"+1 954 788 3805",
    "sg:postcode":"33069",
    "sg:province":"FL",
    "sg:tags":[
        "material",
        "metal",
        "iron"
    ],
    "wof:name":"Trademark Metals Recycling LLC",
    "wof:placetype":"venue"
},
  "geometry": {"coordinates":[-80.14190600000001,26.239324],"type":"Point"}
}