{
  "type": "Feature",
  "properties": {
    "addr:full":"7044 SW 8th St Miami FL 33144",
    "addr:housenumber":"7044",
    "addr:postcode":"33144",
    "addr:street":"Sw 8Th St",
    "iso:country":"US",
    "sg:address":"7044 SW 8th St",
    "sg:city":"Miami",
    "sg:classifiers":[
        {
            "category":"Shopping",
            "subcategory":"Party Supplies",
            "type":"Retail Goods"
        }
    ],
    "sg:phone":"+1 305 265 2002",
    "sg:postcode":"33144",
    "sg:province":"FL",
    "sg:tags":[
        "decoration",
        "rental"
    ],
    "sg:website":"http://www.rumorhasitpartyrentals.com",
    "wof:name":"Rumor Has It Party Rentals",
    "wof:placetype":"venue"
},
  "geometry": {"coordinates":[-80.309309,25.762913],"type":"Point"}
}