{
  "type": "Feature",
  "properties": {
    "iso:country":"US",
    "sg:address":"7483 Coral Way Ste 102",
    "sg:city":"Miami",
    "sg:classifiers":[
        {
            "category":"Health Services",
            "subcategory":"Doctor",
            "type":"Services"
        }
    ],
    "sg:phone":"+1 305 262 1636",
    "sg:postcode":"33155",
    "sg:province":"FL",
    "wof:name":"Mascaro Guari MD",
    "wof:placetype":"venue"
},
  "geometry": {"coordinates":[-80.316948,25.748311],"type":"Point"}
}