{
  "type": "Feature",
  "properties": {
    "addr:full":"10650 Stonebridge Blvd Boca Raton FL 33498",
    "addr:housenumber":"10650",
    "addr:postcode":"33498",
    "addr:street":"Stonebridge Blvd",
    "iso:country":"US",
    "sg:address":"10650 Stonebridge Blvd",
    "sg:city":"Boca Raton",
    "sg:classifiers":[
        {
            "category":"Professional",
            "subcategory":"Business Services",
            "type":"Services"
        }
    ],
    "sg:phone":"+1 561 488 3207",
    "sg:postcode":"33498",
    "sg:province":"FL",
    "sg:tags":[
        "interior",
        "consultant",
        "design",
        "decorator"
    ],
    "wof:name":"Shirlee Baer Interiors",
    "wof:placetype":"venue"
},
  "geometry": {"coordinates":[-80.210646,26.410176],"type":"Point"}
}