{
  "type": "Feature",
  "properties": {
    "addr:full":"533 N Nova Rd Ormond Beach FL 32174",
    "addr:housenumber":"533",
    "addr:postcode":"32174",
    "addr:street":"N Nova Rd",
    "iso:country":"US",
    "sg:address":"533 N Nova Rd",
    "sg:city":"Ormond Beach",
    "sg:classifiers":[
        {
            "category":"Professional",
            "subcategory":"Management & Consulting",
            "type":"Services"
        }
    ],
    "sg:phone":"+1 386 615 1106",
    "sg:postcode":"32174",
    "sg:province":"FL",
    "sg:tags":[
        "consultant",
        "medical"
    ],
    "wof:name":"Affiliated Healthcare",
    "wof:placetype":"venue"
},
  "geometry": {"coordinates":[-81.085165,29.288931],"type":"Point"}
}