{
  "type": "Feature",
  "properties": {
    "iso:country":"US",
    "sg:address":"3925 Clarcona Ocoee Rd",
    "sg:city":"Orlando",
    "sg:classifiers":[
        {
            "category":"Professional",
            "subcategory":"Employment Agencies",
            "type":"Services"
        }
    ],
    "sg:phone":"+1 407 298 3602",
    "sg:postcode":"32810",
    "sg:province":"FL",
    "wof:name":"Off The Edge Bartending Svc",
    "wof:placetype":"venue"
},
  "geometry": {"coordinates":[-81.42513700000001,28.614672],"type":"Point"}
}