{
  "type": "Feature",
  "properties": {
    "addr:full":"165 W Green St Englewood FL 34223",
    "addr:housenumber":"165",
    "addr:postcode":"34223",
    "addr:street":"W Green St",
    "iso:country":"US",
    "sg:address":"165 W Green St",
    "sg:city":"Englewood",
    "sg:classifiers":[
        {
            "category":"Professional",
            "subcategory":"Lawyer & Legal Services",
            "type":"Services"
        }
    ],
    "sg:phone":"+1 941 475 7922",
    "sg:postcode":"34223",
    "sg:province":"FL",
    "sg:tags":[
        "attorney"
    ],
    "wof:name":"Davids & Morland",
    "wof:placetype":"venue"
},
  "geometry": {"coordinates":[-82.355901,26.96112],"type":"Point"}
}