{
  "type": "Feature",
  "properties": {
    "addr:full":"1715 E Bay Dr Largo FL 33771",
    "addr:housenumber":"1715",
    "addr:postcode":"33771",
    "addr:street":"E Bay Dr",
    "iso:country":"US",
    "sg:address":"1715 E Bay Dr",
    "sg:city":"Largo",
    "sg:classifiers":[
        {
            "category":"Social Services",
            "type":"Services"
        }
    ],
    "sg:phone":"+1 727 449 8336",
    "sg:postcode":"33771",
    "sg:province":"FL",
    "wof:name":"Family Resources Inc",
    "wof:placetype":"venue"
},
  "geometry": {"coordinates":[-82.769042,27.916697],"type":"Point"}
}