{
  "type": "Feature",
  "properties": {
    "iso:country":"US",
    "sg:address":"6510 US Hwy 301",
    "sg:city":"Tampa",
    "sg:classifiers":[
        {
            "category":"Travel",
            "subcategory":"Hotels & Motels",
            "type":"Entertainment"
        }
    ],
    "sg:phone":"+1 813 628 0888",
    "sg:postcode":"33610",
    "sg:province":"FL",
    "sg:tags":[
        "operation"
    ],
    "wof:name":"Motel 6",
    "wof:placetype":"venue"
},
  "geometry": {"coordinates":[-82.35659699999999,28.002037],"type":"Point"}
}