{
  "type": "Feature",
  "properties": {
    "iso:country":"US",
    "sg:address":"850 Commerce St",
    "sg:city":"Miami Beach",
    "sg:classifiers":[
        {
            "category":"Shopping",
            "type":"Retail Goods"
        }
    ],
    "sg:phone":"+1 305 672 3111",
    "sg:postcode":"33139",
    "sg:province":"FL",
    "sg:tags":[
        "merchandise"
    ],
    "wof:name":"Ramos Sales",
    "wof:placetype":"venue"
},
  "geometry": {"coordinates":[-80.13625,25.769004],"type":"Point"}
}