{
  "type": "Feature",
  "properties": {
    "iso:country":"US",
    "sg:address":"232 State Road 436",
    "sg:city":"Casselberry",
    "sg:phone":"+1 407 260 5439",
    "sg:postcode":"32707",
    "sg:province":"FL",
    "sg:website":"http://www.klassykidz.com",
    "wof:name":"Klassy Kidz",
    "wof:placetype":"venue"
},
  "geometry": {"coordinates":[-81.33711099999999,28.65836],"type":"Point"}
}