{
  "type": "Feature",
  "properties": {
    "addr:full":"7552 Navarre Pkwy Navarre FL 32566",
    "addr:housenumber":"7552",
    "addr:postcode":"32566",
    "addr:street":"Navarre Pkwy",
    "iso:country":"US",
    "sg:address":"7552 Navarre Pkwy",
    "sg:city":"Navarre",
    "sg:classifiers":[
        {
            "category":"Personal",
            "subcategory":"Beauty Salon",
            "type":"Services"
        }
    ],
    "sg:phone":"+1 850 837 0088",
    "sg:postcode":"32566",
    "sg:province":"FL",
    "sg:tags":[
        "spa",
        "day"
    ],
    "wof:name":"Allegro Spa",
    "wof:placetype":"venue"
},
  "geometry": {"coordinates":[-86.91531000000001,30.402018],"type":"Point"}
}