{
  "type": "Feature",
  "properties": {
    "iso:country":"US",
    "sg:address":"2003 W Cypress Creek Rd",
    "sg:city":"Fort Lauderdale",
    "sg:classifiers":[
        {
            "category":"Communications",
            "type":"Services"
        }
    ],
    "sg:phone":"+1 954 771 0403",
    "sg:postcode":"33309",
    "sg:province":"FL",
    "sg:tags":[
        "datum"
    ],
    "wof:name":"Tier One Communications LLC",
    "wof:placetype":"venue"
},
  "geometry": {"coordinates":[-80.17132700000001,26.20292],"type":"Point"}
}