{
  "type": "Feature",
  "properties": {
    "addr:full":"101 Lakeshore Blvd Kissimmee FL 34741",
    "addr:housenumber":"101",
    "addr:postcode":"34741",
    "addr:street":"Lakeshore Blvd",
    "iso:country":"US",
    "sg:address":"101 Lakeshore Blvd",
    "sg:city":"Kissimmee",
    "sg:classifiers":[
        {
            "category":"Recreation",
            "type":"Entertainment"
        }
    ],
    "sg:phone":"+1 407 846 2814",
    "sg:postcode":"34741",
    "sg:province":"FL",
    "sg:tags":[
        "charter",
        "boat"
    ],
    "wof:name":"Captain Ray",
    "wof:placetype":"venue"
},
  "geometry": {"coordinates":[-81.405615,28.289682],"type":"Point"}
}