{
  "type": "Feature",
  "properties": {
    "addr:full":"514 20th Ave N Indian Rocks Beach FL 33785",
    "addr:housenumber":"514",
    "addr:postcode":"33785",
    "addr:street":"20Th Ave N",
    "iso:country":"US",
    "sg:address":"514 20th Ave N",
    "sg:city":"Indian Rocks Beach",
    "sg:classifiers":[
        {
            "category":"Real Estate",
            "subcategory":"Real Estate Operator",
            "type":"Services"
        }
    ],
    "sg:phone":"+1 727 596 3648",
    "sg:postcode":"33785",
    "sg:province":"FL",
    "sg:tags":[
        "building",
        "apartment"
    ],
    "wof:name":"Harocopos Properties Inc",
    "wof:placetype":"venue"
},
  "geometry": {"coordinates":[-82.83775900000001,27.901081],"type":"Point"}
}