{
  "type": "Feature",
  "properties": {
    "iso:country":"US",
    "sg:address":"7350 Sand Lake Commons Blvd",
    "sg:city":"Orlando",
    "sg:classifiers":[
        {
            "category":"Health Services",
            "subcategory":"Doctor",
            "type":"Services"
        }
    ],
    "sg:phone":"+1 407 354 3700",
    "sg:postcode":"32819",
    "sg:province":"FL",
    "sg:tags":[
        "physician",
        "surgeon"
    ],
    "sg:website":"www.orlandoortho.com",
    "wof:name":"Orlando Orthopaedic Ctr",
    "wof:placetype":"venue"
},
  "geometry": {"coordinates":[-81.47934100000001,28.431073],"type":"Point"}
}