{
  "type": "Feature",
  "properties": {
    "addr:full":"11350 SW 45th St Miami FL 33165",
    "addr:housenumber":"11350",
    "addr:postcode":"33165",
    "addr:street":"Sw 45Th St",
    "iso:country":"US",
    "sg:address":"11350 SW 45th St",
    "sg:city":"Miami",
    "sg:classifiers":[
        {
            "category":"Real Estate",
            "subcategory":"Real Estate Services",
            "type":"Services"
        }
    ],
    "sg:phone":"+1 305 553 1933",
    "sg:postcode":"33165",
    "sg:province":"FL",
    "sg:tags":[
        "home",
        "inspector"
    ],
    "wof:name":"Jay Baldwin's Moonlighting Pest Control - CLOSED",
    "wof:placetype":"venue"
},
  "geometry": {"coordinates":[-80.378601,25.725201],"type":"Point"}
}