{
  "type": "Feature",
  "properties": {
    "iso:country":"US",
    "sg:address":"2215 NW 79th Ave",
    "sg:city":"Doral",
    "sg:classifiers":[
        {
            "category":"Home & Garden",
            "subcategory":"Hardware",
            "type":"Retail Goods"
        },
        {
            "category":"Wholesale",
            "subcategory":"Home Furnishings",
            "type":"Manufacturing & Wholesale Goods"
        }
    ],
    "sg:phone":"+1 305 477 8020",
    "sg:postcode":"33122",
    "sg:province":"FL",
    "sg:tags":[
        "system",
        "equipment",
        "fixtures-wholesale",
        "lighting",
        "manufacturer"
    ],
    "wof:name":"Space Lighting",
    "wof:placetype":"venue"
},
  "geometry": {"coordinates":[-80.32417100000001,25.79349],"type":"Point"}
}