{
  "type": "Feature",
  "properties": {
    "addr:full":"Art Deco Welcome Center 1001 Ocean Dr Miami Beach FL 33139",
    "addr:housenumber":"1001",
    "addr:postcode":"33139",
    "addr:street":"Ocean Dr",
    "iso:country":"US",
    "sg:address":"Art Deco Welcome Center 1001 Ocean Dr",
    "sg:city":"Miami Beach",
    "sg:classifiers":[
        {
            "category":"Arts & Performance",
            "subcategory":"Arts Center",
            "type":"Entertainment"
        }
    ],
    "sg:postcode":"33139",
    "sg:province":"FL",
    "sg:website":"www.pinksnails.com/",
    "wof:name":"The Snails are Coming Exhibit Opening",
    "wof:placetype":"venue"
},
  "geometry": {"coordinates":[-80.130387,25.781078],"type":"Point"}
}