{
  "type": "Feature",
  "properties": {
    "iso:country":"US",
    "sg:address":"4220 SW 157th Ct",
    "sg:city":"Miami",
    "sg:classifiers":[
        {
            "category":"Professional",
            "type":"Services"
        }
    ],
    "sg:phone":"+1 305 559 5904",
    "sg:postcode":"33185",
    "sg:province":"FL",
    "wof:name":"Danubius Trans",
    "wof:placetype":"venue"
},
  "geometry": {"coordinates":[-80.451644,25.726274],"type":"Point"}
}