{
  "type": "Feature",
  "properties": {
    "iso:country":"US",
    "sg:address":"918 Santa Maria Blvd",
    "sg:city":"St Augustine",
    "sg:classifiers":[
        {
            "category":"Real Estate",
            "subcategory":"Real Estate Agent",
            "type":"Services"
        }
    ],
    "sg:phone":"+1 904 797 4814",
    "sg:postcode":"32086",
    "sg:province":"FL",
    "wof:name":"Sea Crest Realty Inc",
    "wof:placetype":"venue"
},
  "geometry": {"coordinates":[-81.322259,29.815385],"type":"Point"}
}