{
  "type": "Feature",
  "properties": {
    "iso:country":"US",
    "sg:address":"13758 78th Pl N",
    "sg:city":"West Palm Beach",
    "sg:classifiers":[
        {
            "category":"Health Services",
            "subcategory":"Doctor",
            "type":"Services"
        }
    ],
    "sg:phone":"+1 561 795 7022",
    "sg:postcode":"33412",
    "sg:province":"FL",
    "sg:tags":[
        "medical"
    ],
    "wof:name":"MD Roskovich Corp",
    "wof:placetype":"venue"
},
  "geometry": {"coordinates":[-80.257368,26.792502],"type":"Point"}
}