{
  "type": "Feature",
  "properties": {
    "iso:country":"US",
    "sg:address":"3519 Lenczyk Dr W",
    "sg:city":"Jacksonville",
    "sg:classifiers":[
        {
            "category":"Transit Center",
            "subcategory":"Passenger",
            "type":"Transportation"
        },
        {
            "category":"Local Transit",
            "type":"Transportation"
        }
    ],
    "sg:phone":"+1 904 744 2450",
    "sg:postcode":"32277",
    "sg:province":"FL",
    "sg:tags":[
        "line",
        "public"
    ],
    "wof:name":"Transportation",
    "wof:placetype":"venue"
},
  "geometry": {"coordinates":[-81.594053,30.363185],"type":"Point"}
}