{
  "type": "Feature",
  "properties": {
    "addr:full":"37941 Flowertree Ln Grand Island FL 32735",
    "addr:housenumber":"37941",
    "addr:postcode":"32735",
    "addr:street":"Flowertree Ln",
    "iso:country":"US",
    "sg:address":"37941 Flowertree Ln",
    "sg:city":"Grand Island",
    "sg:classifiers":[
        {
            "category":"Home & Garden",
            "subcategory":"Home Furnishings",
            "type":"Retail Goods"
        }
    ],
    "sg:phone":"+1 352 589 5860",
    "sg:postcode":"32735",
    "sg:province":"FL",
    "sg:tags":[
        "cutlery",
        "mfg"
    ],
    "wof:name":"Coutel Cutlery Inc",
    "wof:placetype":"venue"
},
  "geometry": {"coordinates":[-81.73738299999999,28.895933],"type":"Point"}
}