{
  "type": "Feature",
  "properties": {
    "iso:country":"US",
    "sg:address":"106 N Dixie Hwy",
    "sg:city":"Hollywood",
    "sg:classifiers":[
        {
            "category":"Autos & Motor Vehicles",
            "subcategory":"Auto Supplies",
            "type":"Retail Goods"
        },
        {
            "category":"Retail",
            "subcategory":"Auto Repair",
            "type":"Services"
        }
    ],
    "sg:phone":"+1 954 923 2311",
    "sg:postcode":"33020",
    "sg:province":"FL",
    "sg:tags":[
        "lube",
        "oil",
        "tire"
    ],
    "sg:website":"http://www.firestonecompleteautocare.com/?s_kwcid=IYP_NTL",
    "wof:name":"Firestone Complete Auto Care Store",
    "wof:placetype":"venue"
},
  "geometry": {"coordinates":[-80.149315,26.011645],"type":"Point"}
}