{
  "type": "Feature",
  "properties": {
    "iso:country":"US",
    "sg:address":"64 Leaver Dr",
    "sg:city":"Palm Coast",
    "sg:classifiers":[
        {
            "category":"Professional",
            "subcategory":"Business Services",
            "type":"Services"
        }
    ],
    "sg:phone":"+1 386 627 4279",
    "sg:postcode":"32137",
    "sg:province":"FL",
    "wof:name":"Everyday Errands Inc",
    "wof:placetype":"venue"
},
  "geometry": {"coordinates":[-81.277759,29.616822],"type":"Point"}
}