{
  "type": "Feature",
  "properties": {
    "iso:country":"US",
    "sg:address":"808 Ingraham Ave",
    "sg:city":"Haines City",
    "sg:classifiers":[
        {
            "category":"Food & Beverages",
            "subcategory":"Groceries & Convenience Stores",
            "type":"Retail Goods"
        }
    ],
    "sg:phone":"+1 863 419 9575",
    "sg:postcode":"33844",
    "sg:province":"FL",
    "wof:name":"Family Discount",
    "wof:placetype":"venue"
},
  "geometry": {"coordinates":[-81.624212,28.109675],"type":"Point"}
}