{
  "type": "Feature",
  "properties": {
    "addr:full":"2213 Janie Poe Dr Sarasota FL 34234",
    "addr:housenumber":"2213",
    "addr:postcode":"34234",
    "addr:street":"Janie Poe Dr",
    "iso:country":"US",
    "sg:address":"2213 Janie Poe Dr",
    "sg:city":"Sarasota",
    "sg:classifiers":[
        {
            "category":"Building & Trades",
            "subcategory":"Cleaning & Sanitation",
            "type":"Services"
        }
    ],
    "sg:phone":"+1 941 953 8271",
    "sg:postcode":"34234",
    "sg:province":"FL",
    "sg:tags":[
        "janitor"
    ],
    "wof:name":"Evelyn's Custodian Maintenance",
    "wof:placetype":"venue"
},
  "geometry": {"coordinates":[-82.542035,27.356589],"type":"Point"}
}