{
  "type": "Feature",
  "properties": {
    "addr:full":"17141 Grand Bay Dr Boca Raton FL 33496",
    "addr:housenumber":"17141",
    "addr:postcode":"33496",
    "addr:street":"Grand Bay Dr",
    "iso:country":"US",
    "sg:address":"17141 Grand Bay Dr",
    "sg:city":"Boca Raton",
    "sg:phone":"+1 561 912 1310",
    "sg:postcode":"33496",
    "sg:province":"FL",
    "sg:tags":[
        "equipment",
        "commercial"
    ],
    "wof:name":"Stortec Systems Co LLC",
    "wof:placetype":"venue"
},
  "geometry": {"coordinates":[-80.137276,26.421958],"type":"Point"}
}