{
  "type": "Feature",
  "properties": {
    "iso:country":"US",
    "sg:address":"535 Tamiami Trl",
    "sg:city":"Venice",
    "sg:classifiers":[
        {
            "category":"Food & Beverages",
            "subcategory":"Groceries & Convenience Stores",
            "type":"Retail Goods"
        }
    ],
    "sg:phone":"+1 941 484 3346",
    "sg:postcode":"34285",
    "sg:province":"FL",
    "sg:tags":[
        "grocer",
        "supermarket"
    ],
    "wof:name":"Publix Super Market 68",
    "wof:placetype":"venue"
},
  "geometry": {"coordinates":[-82.444275,27.091824],"type":"Point"}
}