{
  "type": "Feature",
  "properties": {
    "addr:full":"9380 Ulmerton Rd Largo FL 33771",
    "addr:housenumber":"9380",
    "addr:postcode":"33771",
    "addr:street":"Ulmerton Rd",
    "iso:country":"US",
    "sg:address":"9380 Ulmerton Rd",
    "sg:city":"Largo",
    "sg:classifiers":[
        {
            "category":"Manufacturing",
            "subcategory":"Metals",
            "type":"Manufacturing & Wholesale Goods"
        },
        {
            "category":"Building & Trades",
            "subcategory":"Construction",
            "type":"Services"
        }
    ],
    "sg:phone":"+1 727 586 0599",
    "sg:postcode":"33771",
    "sg:province":"FL",
    "sg:tags":[
        "steel",
        "repair",
        "erection",
        "met",
        "welding",
        "structural"
    ],
    "wof:name":"Seminole Machine & Welding Inc",
    "wof:placetype":"venue"
},
  "geometry": {"coordinates":[-82.76855500000001,27.894477],"type":"Point"}
}