{
  "type": "Feature",
  "properties": {
    "iso:country":"US",
    "sg:address":"15850 Paddock Dr",
    "sg:city":"Montverde",
    "sg:classifiers":[
        {
            "category":"Building & Trades",
            "subcategory":"Construction",
            "type":"Services"
        }
    ],
    "sg:phone":"+1 407 469 2122",
    "sg:postcode":"34756",
    "sg:province":"FL",
    "sg:tags":[
        "contractor"
    ],
    "wof:name":"Jones Contractors Inc",
    "wof:placetype":"venue"
},
  "geometry": {"coordinates":[-81.696798,28.587607],"type":"Point"}
}