{
  "type": "Feature",
  "properties": {
    "addr:full":"1361 Plover Ct Punta Gorda FL 33950",
    "addr:housenumber":"1361",
    "addr:postcode":"33950",
    "addr:street":"Plover Ct",
    "iso:country":"US",
    "sg:address":"1361 Plover Ct",
    "sg:city":"Punta Gorda",
    "sg:classifiers":[
        {
            "category":"Retail",
            "subcategory":"Repair Shop",
            "type":"Services"
        }
    ],
    "sg:phone":"+1 941 639 1980",
    "sg:postcode":"33950",
    "sg:province":"FL",
    "sg:tags":[
        "equipment",
        "magnetic",
        "marine",
        "calibration"
    ],
    "wof:name":"College Park Mar Calibrations",
    "wof:placetype":"venue"
},
  "geometry": {"coordinates":[-82.060259,26.897133],"type":"Point"}
}