{
  "type": "Feature",
  "properties": {
    "iso:country":"US",
    "sg:address":"18871 US Hwy 441",
    "sg:city":"Mount Dora",
    "sg:classifiers":[
        {
            "category":"Restaurant",
            "type":"Food & Drink"
        }
    ],
    "sg:phone":"+1 352 735 4376",
    "sg:postcode":"32757",
    "sg:province":"FL",
    "sg:tags":[
        "eating"
    ],
    "wof:name":"Subway",
    "wof:placetype":"venue"
},
  "geometry": {"coordinates":[-81.644706,28.824204],"type":"Point"}
}