{
  "type": "Feature",
  "properties": {
    "addr:full":"4200 Aurora St Miami FL 33146",
    "addr:housenumber":"4200",
    "addr:postcode":"33146",
    "addr:street":"Aurora St",
    "iso:country":"US",
    "sg:address":"4200 Aurora St",
    "sg:city":"Miami",
    "sg:classifiers":[
        {
            "category":"Real Estate",
            "subcategory":"Architect",
            "type":"Services"
        }
    ],
    "sg:phone":"+1 305 441 8220",
    "sg:postcode":"33146",
    "sg:province":"FL",
    "sg:tags":[
        "architectural"
    ],
    "wof:name":"Studio Schema",
    "wof:placetype":"venue"
},
  "geometry": {"coordinates":[-80.259349,25.732189],"type":"Point"}
}