{
  "type": "Feature",
  "properties": {
    "iso:country":"US",
    "sg:address":"4708 S Brush Hollow Loop",
    "sg:city":"Inverness",
    "sg:classifiers":[
        {
            "category":"Building & Trades",
            "subcategory":"Construction",
            "type":"Services"
        }
    ],
    "sg:phone":"+1 352 228 0370",
    "sg:postcode":"34450",
    "sg:province":"FL",
    "sg:tags":[
        "contractor"
    ],
    "wof:name":"Shawn Levinsteins Stucco",
    "wof:placetype":"venue"
},
  "geometry": {"coordinates":[-82.311227,28.794472],"type":"Point"}
}