{
  "type": "Feature",
  "properties": {
    "addr:full":"15101 Bent Creek Rd Wellington FL 33414",
    "addr:housenumber":"15101",
    "addr:postcode":"33414",
    "addr:street":"Bent Creek Rd",
    "iso:country":"US",
    "sg:address":"15101 Bent Creek Rd",
    "sg:city":"Wellington",
    "sg:classifiers":[
        {
            "category":"Education",
            "subcategory":"School",
            "type":"Public Place"
        }
    ],
    "sg:phone":"+1 561 792 5250",
    "sg:postcode":"33414",
    "sg:province":"FL",
    "wof:name":"Binks Forest Elementary School",
    "wof:placetype":"venue"
},
  "geometry": {"coordinates":[-80.285821,26.679908],"type":"Point"}
}