{
  "type": "Feature",
  "properties": {
    "iso:country":"US",
    "sg:address":"2552 N State Road 7",
    "sg:city":"Hollywood",
    "sg:classifiers":[
        {
            "category":"Social Services",
            "subcategory":"Adult Care",
            "type":"Services"
        }
    ],
    "sg:phone":"+1 954 893 7744",
    "sg:postcode":"33021",
    "sg:province":"FL",
    "sg:tags":[
        "centers-adult",
        "day"
    ],
    "wof:name":"Cypress Place",
    "wof:placetype":"venue"
},
  "geometry": {"coordinates":[-80.208405,26.032734],"type":"Point"}
}