{
  "type": "Feature",
  "properties": {
    "iso:country":"US",
    "sg:address":"123 Water St",
    "sg:city":"Apalachicola",
    "sg:classifiers":[
        {
            "category":"Food & Beverages",
            "subcategory":"Meat & Fish",
            "type":"Retail Goods"
        }
    ],
    "sg:phone":"+1 850 653 8044",
    "sg:postcode":"32320",
    "sg:province":"FL",
    "wof:name":"Seafood-2-Go",
    "wof:placetype":"venue"
},
  "geometry": {"coordinates":[-84.981402,29.725063],"type":"Point"}
}