{
  "type": "Feature",
  "properties": {
    "addr:full":"8823 SW 107th Ave Miami FL 33176",
    "addr:housenumber":"8823",
    "addr:postcode":"33176",
    "addr:street":"Sw 107Th Ave",
    "iso:country":"US",
    "sg:address":"8823 SW 107th Ave",
    "sg:city":"Miami",
    "sg:classifiers":[
        {
            "category":"Personal",
            "subcategory":"Nail Salon",
            "type":"Services"
        }
    ],
    "sg:phone":"+1 305 412 8126",
    "sg:postcode":"33176",
    "sg:province":"FL",
    "wof:name":"Star Nails",
    "wof:placetype":"venue"
},
  "geometry": {"coordinates":[-80.366096,25.6852],"type":"Point"}
}