{
  "type": "Feature",
  "properties": {
    "iso:country":"US",
    "sg:address":"1500 SW 1st Ave Apt 5",
    "sg:city":"Miami",
    "sg:classifiers":[
        {
            "category":"Shopping",
            "subcategory":"Music",
            "type":"Retail Goods"
        }
    ],
    "sg:phone":"+1 786 486 9288",
    "sg:postcode":"33129",
    "sg:province":"FL",
    "sg:tags":[
        "used",
        "tapes",
        "vintage",
        "records",
        "cd's",
        "store"
    ],
    "wof:name":"Gr Komplete Productions",
    "wof:placetype":"venue"
},
  "geometry": {"coordinates":[-80.19654800000001,25.76001],"type":"Point"}
}