{
  "type": "Feature",
  "properties": {
    "addr:full":"118 Vacation Dr Islamorada FL 33070",
    "addr:housenumber":"118",
    "addr:postcode":"33070",
    "addr:street":"Vacation Dr",
    "iso:country":"US",
    "sg:address":"118 Vacation Dr",
    "sg:city":"Islamorada",
    "sg:classifiers":[
        {
            "category":"Professional",
            "subcategory":"Computer Services",
            "type":"Services"
        }
    ],
    "sg:phone":"+1 305 852 5053",
    "sg:postcode":"33070",
    "sg:province":"FL",
    "sg:tags":[
        "website",
        "design"
    ],
    "wof:name":"Adventure Com Inc",
    "wof:placetype":"venue"
},
  "geometry": {"coordinates":[-80.55408,24.975819],"type":"Point"}
}