{
  "type": "Feature",
  "properties": {
    "iso:country":"US",
    "sg:address":"5750 Collins Ave",
    "sg:city":"Miami Beach",
    "sg:classifiers":[
        {
            "category":"Real Estate",
            "subcategory":"Real Estate Agent",
            "type":"Services"
        }
    ],
    "sg:phone":"+1 305 532 1212",
    "sg:postcode":"33140",
    "sg:province":"FL",
    "wof:name":"Gee Eskridge Realty",
    "wof:placetype":"venue"
},
  "geometry": {"coordinates":[-80.121572,25.832401],"type":"Point"}
}