{
  "type": "Feature",
  "properties": {
    "iso:country":"US",
    "sg:address":"1135 Magnolia Ave",
    "sg:city":"Daytona Beach",
    "sg:classifiers":[
        {
            "category":"Building & Trades",
            "subcategory":"Construction",
            "type":"Services"
        }
    ],
    "sg:phone":"+1 386 257 2514",
    "sg:postcode":"32114",
    "sg:province":"FL",
    "sg:tags":[
        "painter"
    ],
    "wof:name":"Casale Home Maintenance",
    "wof:placetype":"venue"
},
  "geometry": {"coordinates":[-81.045655,29.198894],"type":"Point"}
}