{
  "type": "Feature",
  "properties": {
    "addr:full":"15610 Premiere Dr Tampa FL 33624",
    "addr:postcode":"15610;33624",
    "addr:street":"Premiere Dr",
    "iso:country":"US",
    "sg:address":"15610 Premiere Dr",
    "sg:city":"Tampa",
    "sg:classifiers":[
        {
            "category":"Real Estate",
            "subcategory":"Real Estate Agent",
            "type":"Services"
        }
    ],
    "sg:phone":"+1 813 962 0806",
    "sg:postcode":"33624",
    "sg:province":"FL",
    "sg:tags":[
        "management"
    ],
    "wof:name":"Northdale Special Tax District",
    "wof:placetype":"venue"
},
  "geometry": {"coordinates":[-82.505573,28.095601],"type":"Point"}
}