{
  "type": "Feature",
  "properties": {
    "iso:country":"US",
    "sg:address":"5430 Eagles Point Cir",
    "sg:city":"Sarasota",
    "sg:classifiers":[
        {
            "category":"Wholesale",
            "subcategory":"Machinery & Supplies",
            "type":"Manufacturing & Wholesale Goods"
        }
    ],
    "sg:phone":"+1 941 922 3331",
    "sg:postcode":"34231",
    "sg:province":"FL",
    "sg:tags":[
        "product",
        "industrial",
        "export"
    ],
    "wof:name":"Awt International Inc",
    "wof:placetype":"venue"
},
  "geometry": {"coordinates":[-82.53699400000001,27.272266],"type":"Point"}
}