{
  "type": "Feature",
  "properties": {
    "addr:full":"21 Pigeon Dr Key Largo FL 33037",
    "addr:housenumber":"21",
    "addr:postcode":"33037",
    "addr:street":"Pigeon Dr",
    "iso:country":"US",
    "sg:address":"21 Pigeon Dr",
    "sg:city":"Key Largo",
    "sg:classifiers":[
        {
            "category":"Building & Trades",
            "subcategory":"Construction",
            "type":"Services"
        }
    ],
    "sg:phone":"+1 305 451 0764",
    "sg:postcode":"33037",
    "sg:province":"FL",
    "sg:tags":[
        "hanging",
        "contractor"
    ],
    "wof:name":"Powell Brothers Painting",
    "wof:placetype":"venue"
},
  "geometry": {"coordinates":[-80.38335600000001,25.163614],"type":"Point"}
}