{
  "type": "Feature",
  "properties": {
    "addr:full":"1606 W Silver Springs Blvd Ocala FL 34475",
    "addr:housenumber":"1606",
    "addr:postcode":"34475",
    "addr:street":"W Silver Springs Blvd",
    "iso:country":"US",
    "sg:address":"1606 W Silver Springs Blvd",
    "sg:city":"Ocala",
    "sg:classifiers":[
        {
            "category":"Real Estate",
            "subcategory":"Real Estate Agent",
            "type":"Services"
        }
    ],
    "sg:phone":"+1 352 732 5554",
    "sg:postcode":"34475",
    "sg:province":"FL",
    "wof:name":"5 Star Real Estate Svc",
    "wof:placetype":"venue"
},
  "geometry": {"coordinates":[-82.15314499999999,29.186178],"type":"Point"}
}