{
  "type": "Feature",
  "properties": {
    "iso:country":"US",
    "sg:address":"4001 Manatee Ave W",
    "sg:city":"Bradenton",
    "sg:classifiers":[
        {
            "category":"Shopping",
            "subcategory":"Bicycles & Sporting Goods",
            "type":"Retail Goods"
        }
    ],
    "sg:phone":"+1 941 746 6168",
    "sg:postcode":"34205",
    "sg:province":"FL",
    "sg:tags":[
        "apparel",
        "equipment",
        "golf"
    ],
    "wof:name":"Manatee Golf Inc",
    "wof:placetype":"venue"
},
  "geometry": {"coordinates":[-82.60208799999999,27.495708],"type":"Point"}
}