{
  "type": "Feature",
  "properties": {
    "iso:country":"US",
    "sg:address":"2713 Michigan Ave",
    "sg:city":"Kissimmee",
    "sg:classifiers":[
        {
            "category":"Professional",
            "subcategory":"Business Services",
            "type":"Services"
        }
    ],
    "sg:phone":"+1 407 518 0443",
    "sg:postcode":"34744",
    "sg:province":"FL",
    "sg:tags":[
        "event"
    ],
    "sg:website":"www.candoeventplanning.com",
    "wof:name":"CANDOEVENTPLANNING.COM",
    "wof:placetype":"venue"
},
  "geometry": {"coordinates":[-81.39114600000001,28.326716],"type":"Point"}
}