{
  "type": "Feature",
  "properties": {
    "iso:country":"US",
    "sg:address":"5460 5th St",
    "sg:city":"Saint Augustine",
    "sg:classifiers":[
        {
            "category":"Building & Trades",
            "subcategory":"Construction",
            "type":"Services"
        }
    ],
    "sg:phone":"+1 904 471 3804",
    "sg:postcode":"32080",
    "sg:province":"FL",
    "sg:tags":[
        "house"
    ],
    "wof:name":"Dotson Development",
    "wof:placetype":"venue"
},
  "geometry": {"coordinates":[-81.266597,29.792359],"type":"Point"}
}