{
  "type": "Feature",
  "properties": {
    "addr:full":"2405 Lucien Way Maitland FL 32751",
    "addr:housenumber":"2405",
    "addr:postcode":"32751",
    "addr:street":"Lucien Way",
    "iso:country":"US",
    "sg:address":"2405 Lucien Way",
    "sg:city":"Maitland",
    "sg:classifiers":[
        {
            "category":"Restaurant",
            "type":"Food & Drink"
        }
    ],
    "sg:menulink":"http://www.allmenus.com/fl/orlando/233963-natures-table/menu/",
    "sg:phone":"+1 407 919 3316",
    "sg:postcode":"32751",
    "sg:province":"FL",
    "sg:tags":[
        "smoothy",
        "sandwich",
        "salad",
        "juice",
        "soup",
        "american",
        "wrap"
    ],
    "wof:name":"Nature's Table",
    "wof:placetype":"venue"
},
  "geometry": {"coordinates":[-81.394222,28.623008],"type":"Point"}
}