{
  "type": "Feature",
  "properties": {
    "addr:full":"7001 142nd Ave N Largo FL 33771",
    "addr:housenumber":"7001",
    "addr:postcode":"33771",
    "addr:street":"142Nd Ave N",
    "iso:country":"US",
    "sg:address":"7001 142nd Ave N",
    "sg:city":"Largo",
    "sg:classifiers":[
        {
            "category":"Real Estate",
            "subcategory":"Developer",
            "type":"Services"
        },
        {
            "category":"Real Estate",
            "subcategory":"Real Estate Operator",
            "type":"Services"
        }
    ],
    "sg:phone":"+1 727 531 9149",
    "sg:postcode":"33771",
    "sg:province":"FL",
    "sg:tags":[
        "mobile",
        "home",
        "site"
    ],
    "wof:name":"Bay Shore Mfg Home Sales",
    "wof:placetype":"venue"
},
  "geometry": {"coordinates":[-82.733722,27.901114],"type":"Point"}
}