{
  "type": "Feature",
  "properties": {
    "addr:full":"6055 Youngerman Cir Jacksonville FL 32244",
    "addr:housenumber":"6055",
    "addr:postcode":"32244",
    "addr:street":"Youngerman Cir",
    "iso:country":"US",
    "sg:address":"6055 Youngerman Cir",
    "sg:city":"Jacksonville",
    "sg:classifiers":[
        {
            "category":"Retail",
            "subcategory":"Auto Rental",
            "type":"Services"
        }
    ],
    "sg:phone":"+1 904 813 8076",
    "sg:postcode":"32244",
    "sg:province":"FL",
    "sg:tags":[
        "limousine"
    ],
    "wof:name":"Dynasty Limousine of Orange Park",
    "wof:placetype":"venue"
},
  "geometry": {"coordinates":[-81.74092,30.19414],"type":"Point"}
}