{
  "type": "Feature",
  "properties": {
    "iso:country":"US",
    "sg:address":"727 Belvedere Rd",
    "sg:city":"West Palm Beach",
    "sg:classifiers":[
        {
            "category":"Retail",
            "subcategory":"Repair Shop",
            "type":"Services"
        }
    ],
    "sg:phone":"+1 561 832 3538",
    "sg:postcode":"33405",
    "sg:province":"FL",
    "sg:tags":[
        "pump",
        "motor"
    ],
    "wof:name":"Gordon Claude Sales & Service",
    "wof:placetype":"venue"
},
  "geometry": {"coordinates":[-80.060495,26.690483],"type":"Point"}
}