{
  "type": "Feature",
  "properties": {
    "iso:country":"US",
    "sg:address":"13571 McGregor Blvd",
    "sg:city":"Fort Myers",
    "sg:classifiers":[
        {
            "category":"Professional",
            "subcategory":"Accounting & Tax Preparation",
            "type":"Services"
        }
    ],
    "sg:phone":"+1 239 481 4444",
    "sg:postcode":"33919",
    "sg:province":"FL",
    "sg:tags":[
        "accountant"
    ],
    "wof:name":"Southwest Professional Services of SW Inc",
    "wof:placetype":"venue"
},
  "geometry": {"coordinates":[-81.914299,26.5462],"type":"Point"}
}