{
  "type": "Feature",
  "properties": {
    "addr:full":"4992 Cumberland Ln Spring Hill FL 34607",
    "addr:housenumber":"4992",
    "addr:postcode":"34607",
    "addr:street":"Cumberland Ln",
    "iso:country":"US",
    "sg:address":"4992 Cumberland Ln",
    "sg:city":"Spring Hill",
    "sg:classifiers":[
        {
            "category":"Real Estate",
            "subcategory":"Real Estate Operator",
            "type":"Services"
        }
    ],
    "sg:phone":"+1 352 596 0164",
    "sg:postcode":"34607",
    "sg:province":"FL",
    "sg:tags":[
        "property",
        "commercial",
        "lease"
    ],
    "wof:name":"Dennis Kelleher Inc",
    "wof:placetype":"venue"
},
  "geometry": {"coordinates":[-82.60126700000001,28.500626],"type":"Point"}
}