{
  "type": "Feature",
  "properties": {
    "iso:country":"US",
    "sg:address":"4934 US Hwy 19",
    "sg:city":"New Port Richey",
    "sg:classifiers":[
        {
            "category":"Insurance",
            "subcategory":"Insurance Agent",
            "type":"Services"
        }
    ],
    "sg:phone":"+1 727 846 7713",
    "sg:postcode":"34652",
    "sg:province":"FL",
    "wof:name":"Insurance II",
    "wof:placetype":"venue"
},
  "geometry": {"coordinates":[-82.729837,28.232091],"type":"Point"}
}