{
  "type": "Feature",
  "properties": {
    "iso:country":"US",
    "sg:address":"1200 S Woodland Blvd",
    "sg:city":"Deland",
    "sg:classifiers":[
        {
            "category":"Restaurant",
            "type":"Food & Drink"
        }
    ],
    "sg:phone":"+1 386 738 1777",
    "sg:postcode":"32720",
    "sg:province":"FL",
    "wof:name":"Sherry's Kitchen & Buffet",
    "wof:placetype":"venue"
},
  "geometry": {"coordinates":[-81.302902,29.0091],"type":"Point"}
}