{
  "type": "Feature",
  "properties": {
    "addr:full":"951 SW 17th Ave Delray Beach FL 33444",
    "addr:housenumber":"951",
    "addr:postcode":"33444",
    "addr:street":"Sw 17Th Ave",
    "iso:country":"US",
    "sg:address":"951 SW 17th Ave",
    "sg:city":"Delray Beach",
    "sg:classifiers":[
        {
            "category":"Manufacturing",
            "subcategory":"Food",
            "type":"Manufacturing & Wholesale Goods"
        }
    ],
    "sg:phone":"+1 561 276 3905",
    "sg:postcode":"33444",
    "sg:province":"FL",
    "sg:tags":[
        "sauce",
        "manufacturer"
    ],
    "wof:name":"Toms Barbeque Sauce",
    "wof:placetype":"venue"
},
  "geometry": {"coordinates":[-80.08929500000001,26.450004],"type":"Point"}
}