{
  "type": "Feature",
  "properties": {
    "iso:country":"US",
    "sg:address":"23165 Boca Club Colony Cir",
    "sg:city":"Boca Raton",
    "sg:classifiers":[
        {
            "category":"Professional",
            "subcategory":"Engineering",
            "type":"Services"
        }
    ],
    "sg:phone":"+1 561 368 3327",
    "sg:postcode":"33433",
    "sg:province":"FL",
    "sg:tags":[
        "engineer"
    ],
    "wof:name":"Global Engineering Conslt Inc",
    "wof:placetype":"venue"
},
  "geometry": {"coordinates":[-80.140664,26.334288],"type":"Point"}
}