{
  "type": "Feature",
  "properties": {
    "addr:full":"30 Lagorce Cir Miami Beach FL 33141",
    "addr:housenumber":"30",
    "addr:postcode":"33141",
    "addr:street":"Lagorce Cir",
    "iso:country":"US",
    "sg:address":"30 Lagorce Cir",
    "sg:city":"Miami Beach",
    "sg:classifiers":[
        {
            "category":"Professional",
            "type":"Services"
        }
    ],
    "sg:phone":"+1 305 868 0705",
    "sg:postcode":"33141",
    "sg:province":"FL",
    "wof:name":"Walter Staudinger Arts LLC",
    "wof:placetype":"venue"
},
  "geometry": {"coordinates":[-80.132127,25.847052],"type":"Point"}
}