{
  "type": "Feature",
  "properties": {
    "iso:country":"US",
    "sg:address":"14572 SW 160th Ct",
    "sg:city":"Miami",
    "sg:classifiers":[
        {
            "category":"Professional",
            "subcategory":"Business Services",
            "type":"Services"
        }
    ],
    "sg:phone":"+1 305 256 5977",
    "sg:postcode":"33196",
    "sg:province":"FL",
    "wof:name":"Enclosed Exposures Inc",
    "wof:placetype":"venue"
},
  "geometry": {"coordinates":[-80.453847,25.63114],"type":"Point"}
}