{
  "type": "Feature",
  "properties": {
    "iso:country":"US",
    "sg:address":"2326 Pelican Bay Ct",
    "sg:city":"Panama City",
    "sg:classifiers":[
        {
            "category":"Building & Trades",
            "subcategory":"Plumbing",
            "type":"Services"
        }
    ],
    "sg:phone":"+1 850 234 9488",
    "sg:postcode":"32408",
    "sg:province":"FL",
    "sg:tags":[
        "contractor"
    ],
    "wof:name":"Easom Plumbing Co Inc",
    "wof:placetype":"venue"
},
  "geometry": {"coordinates":[-85.73701800000001,30.15934],"type":"Point"}
}