{
  "type": "Feature",
  "properties": {
    "iso:country":"US",
    "sg:address":"439 E 8th St",
    "sg:city":"Jacksonville",
    "sg:classifiers":[
        {
            "category":"Manufacturing",
            "subcategory":"Printing",
            "type":"Manufacturing & Wholesale Goods"
        }
    ],
    "sg:phone":"+1 904 355 3673",
    "sg:postcode":"32206",
    "sg:province":"FL",
    "sg:tags":[
        "die",
        "work",
        "commercial",
        "mfg"
    ],
    "wof:name":"Atlantic East Coast Bindery",
    "wof:placetype":"venue"
},
  "geometry": {"coordinates":[-81.646823,30.345238],"type":"Point"}
}