{
  "type": "Feature",
  "properties": {
    "addr:full":"11606 Gerado Rd Jacksonville FL 32258",
    "addr:housenumber":"11606",
    "addr:postcode":"32258",
    "addr:street":"Gerado Rd",
    "iso:country":"US",
    "sg:address":"11606 Gerado Rd",
    "sg:city":"Jacksonville",
    "sg:classifiers":[
        {
            "category":"Building & Trades",
            "subcategory":"Construction",
            "type":"Services"
        }
    ],
    "sg:phone":"+1 904 886 9026",
    "sg:postcode":"32258",
    "sg:province":"FL",
    "sg:tags":[
        "dry wall",
        "contractor"
    ],
    "wof:name":"Mandarin Construction",
    "wof:placetype":"venue"
},
  "geometry": {"coordinates":[-81.549026,30.164886],"type":"Point"}
}