{
  "type": "Feature",
  "properties": {
    "iso:country":"US",
    "sg:address":"24329 Turkey Lake Rd",
    "sg:city":"Howey In The Hills",
    "sg:classifiers":[
        {
            "category":"Insurance",
            "subcategory":"Insurance Agent",
            "type":"Services"
        }
    ],
    "sg:phone":"+1 352 324 3126",
    "sg:postcode":"34737",
    "sg:province":"FL",
    "wof:name":"David E Raber",
    "wof:placetype":"venue"
},
  "geometry": {"coordinates":[-81.825716,28.71764],"type":"Point"}
}