{
  "type": "Feature",
  "properties": {
    "iso:country":"US",
    "sg:address":"3075 NW 107th Ave",
    "sg:city":"Doral",
    "sg:classifiers":[
        {
            "category":"Government",
            "subcategory":"Office",
            "type":"Public Place"
        }
    ],
    "sg:phone":"+1 305 591 1304",
    "sg:postcode":"33172",
    "sg:province":"FL",
    "sg:tags":[
        "state",
        "program",
        "health"
    ],
    "wof:name":"Health Alliance Of South Fl",
    "wof:placetype":"venue"
},
  "geometry": {"coordinates":[-80.369182,25.80215],"type":"Point"}
}