{
  "type": "Feature",
  "properties": {
    "addr:full":"827 8th Ave W Palmetto FL 34221",
    "addr:housenumber":"827",
    "addr:postcode":"34221",
    "addr:street":"8Th Ave W",
    "iso:country":"US",
    "sg:address":"827 8th Ave W",
    "sg:city":"Palmetto",
    "sg:classifiers":[
        {
            "category":"Personal",
            "subcategory":"Beauty Salon",
            "type":"Services"
        }
    ],
    "sg:phone":"+1 941 722 0131",
    "sg:postcode":"34221",
    "sg:province":"FL",
    "wof:name":"Hair Fashions By Jeannie",
    "wof:placetype":"venue"
},
  "geometry": {"coordinates":[-82.573018,27.520311],"type":"Point"}
}