{
  "type": "Feature",
  "properties": {
    "iso:country":"US",
    "sg:address":"3375 Franklin Ave",
    "sg:city":"Miami",
    "sg:classifiers":[
        {
            "category":"Banks & Credit Unions",
            "subcategory":"Bank",
            "type":"Services"
        }
    ],
    "sg:phone":"+1 305 774 0720",
    "sg:postcode":"33133",
    "sg:province":"FL",
    "sg:tags":[
        "mortgage"
    ],
    "wof:name":"Southern Mortgage Investr",
    "wof:placetype":"venue"
},
  "geometry": {"coordinates":[-80.247912,25.724838],"type":"Point"}
}