{
  "type": "Feature",
  "properties": {
    "iso:country":"US",
    "sg:address":"2202 Columbus Dr",
    "sg:city":"Brandon",
    "sg:classifiers":[
        {
            "category":"Building & Trades",
            "subcategory":"Construction",
            "type":"Services"
        }
    ],
    "sg:phone":"+1 813 626 7686",
    "sg:postcode":"33510",
    "sg:province":"FL",
    "wof:name":"Marks Gradall Service Inc",
    "wof:placetype":"venue"
},
  "geometry": {"coordinates":[-82.325812,27.966884],"type":"Point"}
}