{
  "type": "Feature",
  "properties": {
    "iso:country":"US",
    "sg:address":"2201 SE Indian St",
    "sg:city":"Stuart",
    "sg:classifiers":[
        {
            "category":"Manufacturing",
            "subcategory":"Rubber & Plastics",
            "type":"Manufacturing & Wholesale Goods"
        }
    ],
    "sg:phone":"+1 772 286 3663",
    "sg:postcode":"34997",
    "sg:province":"FL",
    "sg:tags":[
        "supply"
    ],
    "sg:website":"www.bentek.com",
    "wof:name":"Ben-Tek Products",
    "wof:placetype":"venue"
},
  "geometry": {"coordinates":[-80.225792,27.166494],"type":"Point"}
}