{
  "type": "Feature",
  "properties": {
    "iso:country":"US",
    "sg:address":"7101 NW 77th Ter",
    "sg:city":"Medley",
    "sg:classifiers":[
        {
            "category":"Marine",
            "type":"Transportation"
        },
        {
            "category":"Food & Beverages",
            "subcategory":"Meat & Fish",
            "type":"Retail Goods"
        }
    ],
    "sg:phone":"+1 305 884 7449",
    "sg:postcode":"33166",
    "sg:province":"FL",
    "sg:tags":[
        "equipment",
        "seafood",
        "market",
        "supply"
    ],
    "wof:name":"Tropical Marine Products",
    "wof:placetype":"venue"
},
  "geometry": {"coordinates":[-80.31290799999999,25.84404],"type":"Point"}
}