{
  "type": "Feature",
  "properties": {
    "iso:country":"US",
    "sg:address":"2201 NW 9th Pl",
    "sg:city":"Fort Lauderdale",
    "sg:classifiers":[
        {
            "category":"Building & Trades",
            "subcategory":"Landscaping Services",
            "type":"Services"
        }
    ],
    "sg:phone":"+1 954 709 1055",
    "sg:postcode":"33311",
    "sg:province":"FL",
    "sg:tags":[
        "landscape"
    ],
    "wof:name":"Dons Landscaping",
    "wof:placetype":"venue"
},
  "geometry": {"coordinates":[-80.173751,26.135673],"type":"Point"}
}