{
  "type": "Feature",
  "properties": {
    "iso:country":"US",
    "sg:address":"5894 NW 74th St",
    "sg:city":"Pompano Beach",
    "sg:classifiers":[
        {
            "category":"Organizations",
            "subcategory":"Community Association",
            "type":"Services"
        }
    ],
    "sg:phone":"+1 954 344 1889",
    "sg:postcode":"33067",
    "sg:province":"FL",
    "sg:tags":[
        "assoc",
        "homeowner"
    ],
    "wof:name":"Parkwood Ix Homeowners Assn",
    "wof:placetype":"venue"
},
  "geometry": {"coordinates":[-80.205393,26.322432],"type":"Point"}
}