{
  "type": "Feature",
  "properties": {
    "addr:full":"16701 NW 67th Ave Hialeah FL 33015",
    "addr:housenumber":"16701",
    "addr:postcode":"33015",
    "addr:street":"Nw 67Th Ave",
    "iso:country":"US",
    "sg:address":"16701 NW 67th Ave",
    "sg:city":"Hialeah",
    "sg:classifiers":[
        {
            "category":"Restaurant",
            "type":"Food & Drink"
        }
    ],
    "sg:menulink":"http://www.allmenus.com/fl/hialeah/187388-mcdonalds/menu/",
    "sg:phone":"+1 305 822 6232",
    "sg:postcode":"33015",
    "sg:province":"FL",
    "sg:tags":[
        "burger",
        "american"
    ],
    "wof:name":"McDonald's",
    "wof:placetype":"venue"
},
  "geometry": {"coordinates":[-80.309316,25.92515],"type":"Point"}
}