{
  "type": "Feature",
  "properties": {
    "iso:country":"US",
    "sg:address":"500 NE 185th St",
    "sg:city":"Miami",
    "sg:classifiers":[
        {
            "category":"Wholesale",
            "subcategory":"Groceries",
            "type":"Manufacturing & Wholesale Goods"
        }
    ],
    "sg:phone":"+1 305 655 3120",
    "sg:postcode":"33179",
    "sg:province":"FL",
    "sg:tags":[
        "frozen",
        "foods-wholesale"
    ],
    "wof:name":"Ship Elite Supply Inc",
    "wof:placetype":"venue"
},
  "geometry": {"coordinates":[-80.19086900000001,25.944961],"type":"Point"}
}