{
  "type": "Feature",
  "properties": {
    "iso:country":"US",
    "sg:address":"140 Avenida Messina",
    "sg:city":"Sarasota",
    "sg:phone":"+1 941 346 2750",
    "sg:postcode":"34242",
    "sg:province":"FL",
    "sg:website":"http://www.thebrokenegg.com",
    "wof:name":"Broken Egg Restaurant",
    "wof:placetype":"venue"
},
  "geometry": {"coordinates":[-82.565468,27.27598],"type":"Point"}
}