{
  "type": "Feature",
  "properties": {
    "addr:full":"922 E Brownlee St Starke FL 32091",
    "addr:housenumber":"922",
    "addr:postcode":"32091",
    "addr:street":"E Brownlee St",
    "iso:country":"US",
    "sg:address":"922 E Brownlee St",
    "sg:city":"Starke",
    "sg:classifiers":[
        {
            "category":"Personal",
            "subcategory":"Beauty Salon",
            "type":"Services"
        }
    ],
    "sg:phone":"+1 904 964 6903",
    "sg:postcode":"32091",
    "sg:province":"FL",
    "wof:name":"Lanes Hair & Design",
    "wof:placetype":"venue"
},
  "geometry": {"coordinates":[-82.099904,29.949585],"type":"Point"}
}