{
  "type": "Feature",
  "properties": {
    "iso:country":"US",
    "sg:address":"6160 37th St",
    "sg:city":"Vero Beach",
    "sg:classifiers":[
        {
            "category":"Professional",
            "type":"Services"
        }
    ],
    "sg:phone":"+1 772 562 7246",
    "sg:postcode":"32966",
    "sg:province":"FL",
    "sg:tags":[
        "inventor"
    ],
    "wof:name":"Robert E Knittel Novelty Shirt",
    "wof:placetype":"venue"
},
  "geometry": {"coordinates":[-80.45459099999999,27.660772],"type":"Point"}
}