{
  "type": "Feature",
  "properties": {
    "iso:country":"US",
    "sg:address":"709 NW 16th St",
    "sg:city":"Belle Glade",
    "sg:classifiers":[
        {
            "category":"Restaurant",
            "type":"Food & Drink"
        }
    ],
    "sg:phone":"+1 561 992 8662",
    "sg:postcode":"33430",
    "sg:province":"FL",
    "wof:name":"Sylvia's Cafeteria",
    "wof:placetype":"venue"
},
  "geometry": {"coordinates":[-80.683894,26.692591],"type":"Point"}
}