{
  "type": "Feature",
  "properties": {
    "addr:full":"2977 Jefferson St Marianna FL 32446",
    "addr:housenumber":"2977",
    "addr:postcode":"32446",
    "addr:street":"Jefferson St",
    "iso:country":"US",
    "sg:address":"2977 Jefferson St",
    "sg:city":"Marianna",
    "sg:classifiers":[
        {
            "category":"Insurance",
            "subcategory":"Insurance Agent",
            "type":"Services"
        }
    ],
    "sg:phone":"+1 850 526 4344",
    "sg:postcode":"32446",
    "sg:province":"FL",
    "wof:name":"AFLAC",
    "wof:placetype":"venue"
},
  "geometry": {"coordinates":[-85.22672,30.783011],"type":"Point"}
}