{
  "type": "Feature",
  "properties": {
    "addr:full":"6700 Carnation Way Port Richey FL 34668",
    "addr:housenumber":"6700",
    "addr:postcode":"34668",
    "addr:street":"Carnation Way",
    "iso:country":"US",
    "sg:address":"6700 Carnation Way",
    "sg:city":"Port Richey",
    "sg:classifiers":[
        {
            "category":"Wholesale",
            "subcategory":"Machinery & Supplies",
            "type":"Manufacturing & Wholesale Goods"
        }
    ],
    "sg:phone":"+1 727 455 8721",
    "sg:postcode":"34668",
    "sg:province":"FL",
    "sg:tags":[
        "industrial"
    ],
    "wof:name":"Snap-On Tools",
    "wof:placetype":"venue"
},
  "geometry": {"coordinates":[-82.70450200000001,28.286021],"type":"Point"}
}