{
  "type": "Feature",
  "properties": {
    "iso:country":"US",
    "sg:address":"741 S Pennsylvania Ave",
    "sg:city":"Winter Park",
    "sg:classifiers":[
        {
            "category":"Social Services",
            "subcategory":"Child Care",
            "type":"Services"
        },
        {
            "category":"Organizations",
            "subcategory":"Non-profit Organization",
            "type":"Services"
        }
    ],
    "sg:phone":"+1 407 647 0505",
    "sg:postcode":"32789",
    "sg:province":"FL",
    "sg:tags":[
        "elementary",
        "school",
        "day"
    ],
    "sg:website":"www.winterparkdaynursery.org",
    "wof:name":"Winter Park Day Nursery Inc",
    "wof:placetype":"venue"
},
  "geometry": {"coordinates":[-81.35659800000001,28.591499],"type":"Point"}
}