{
  "type": "Feature",
  "properties": {
    "iso:country":"US",
    "sg:address":"6384 Phillips Hwy",
    "sg:city":"Jacksonville",
    "sg:classifiers":[
        {
            "category":"Manufacturing",
            "subcategory":"Metals",
            "type":"Manufacturing & Wholesale Goods"
        },
        {
            "category":"Manufacturing",
            "subcategory":"Wood Products",
            "type":"Manufacturing & Wholesale Goods"
        }
    ],
    "sg:phone":"+1 904 730 0882",
    "sg:postcode":"32216",
    "sg:province":"FL",
    "sg:tags":[
        "installation",
        "fence",
        "mfg",
        "wooden",
        "fencing",
        "contractor"
    ],
    "wof:name":"Silverman Fence Mfg",
    "wof:placetype":"venue"
},
  "geometry": {"coordinates":[-81.610913,30.256869],"type":"Point"}
}