{
  "type": "Feature",
  "properties": {
    "iso:country":"US",
    "sg:address":"1607 10th Ave",
    "sg:city":"Vero Beach",
    "sg:classifiers":[
        {
            "category":"Retail",
            "subcategory":"Repair Shop",
            "type":"Services"
        }
    ],
    "sg:phone":"+1 772 562 2600",
    "sg:postcode":"32960",
    "sg:province":"FL",
    "sg:tags":[
        "used",
        "merchandise"
    ],
    "wof:name":"Sandman",
    "wof:placetype":"venue"
},
  "geometry": {"coordinates":[-80.393368,27.630513],"type":"Point"}
}