{
  "type": "Feature",
  "properties": {
    "iso:country":"US",
    "sg:address":"21808 State Rd 54",
    "sg:city":"Lutz",
    "sg:classifiers":[
        {
            "category":"Health Services",
            "subcategory":"Hospital",
            "type":"Services"
        }
    ],
    "sg:phone":"+1 813 909 2030",
    "sg:postcode":"33549",
    "sg:province":"FL",
    "sg:tags":[
        "mental"
    ],
    "wof:name":"Sunshine Youth Svc",
    "wof:placetype":"venue"
},
  "geometry": {"coordinates":[-82.45447,28.187637],"type":"Point"}
}