{
  "type": "Feature",
  "properties": {
    "addr:full":"1369 Riviera Dr Green Cove Spgs FL 32043",
    "addr:housenumber":"1369",
    "addr:postcode":"32043",
    "addr:street":"Riviera Dr Green Cove Spgs",
    "iso:country":"US",
    "sg:address":"1369 Riviera Dr",
    "sg:city":"Green Cove Spgs",
    "sg:classifiers":[
        {
            "category":"Building & Trades",
            "subcategory":"Plumbing",
            "type":"Services"
        }
    ],
    "sg:phone":"+1 904 529 0065",
    "sg:postcode":"32043",
    "sg:province":"FL",
    "sg:tags":[
        "conditioning",
        "air",
        "system",
        "contractor"
    ],
    "wof:name":"Quality Heating & Air",
    "wof:placetype":"venue"
},
  "geometry": {"coordinates":[-81.698573,30.026513],"type":"Point"}
}