{
  "type": "Feature",
  "properties": {
    "addr:full":"601 N Hart Blvd Orlando FL 32818",
    "addr:housenumber":"601",
    "addr:postcode":"32818",
    "addr:street":"N Hart Blvd",
    "iso:country":"US",
    "sg:address":"601 N Hart Blvd",
    "sg:city":"Orlando",
    "sg:classifiers":[
        {
            "category":"Professional",
            "subcategory":"Engineering",
            "type":"Services"
        }
    ],
    "sg:phone":"+1 407 521 4771",
    "sg:postcode":"32818",
    "sg:province":"FL",
    "sg:tags":[
        "civil",
        "engineer"
    ],
    "sg:website":"http://www.nadicinc.com",
    "wof:name":"Nadic Engineering Services Inc",
    "wof:placetype":"venue"
},
  "geometry": {"coordinates":[-81.47073,28.550933],"type":"Point"}
}