{
  "type": "Feature",
  "properties": {
    "addr:full":"1844 Park Ave Orange Park FL 32073",
    "addr:housenumber":"1844",
    "addr:postcode":"32073",
    "addr:street":"Park Ave",
    "iso:country":"US",
    "sg:address":"1844 Park Ave",
    "sg:city":"Orange Park",
    "sg:classifiers":[
        {
            "category":"Professional",
            "subcategory":"Computer Services",
            "type":"Services"
        }
    ],
    "sg:phone":"+1 904 264 8220",
    "sg:postcode":"32073",
    "sg:province":"FL",
    "sg:tags":[
        "programing",
        "custom"
    ],
    "wof:name":"Hutson Computer Service Inc",
    "wof:placetype":"venue"
},
  "geometry": {"coordinates":[-81.701396,30.169914],"type":"Point"}
}