{
  "type": "Feature",
  "properties": {
    "addr:full":"1311 Hancock Lone Palm Rd Orlando FL 32828",
    "addr:housenumber":"1311",
    "addr:postcode":"32828",
    "addr:street":"Hancock Lone Palm Rd",
    "iso:country":"US",
    "sg:address":"1311 Hancock Lone Palm Rd",
    "sg:city":"Orlando",
    "sg:classifiers":[
        {
            "category":"Wholesale",
            "subcategory":"Farm Supplies",
            "type":"Manufacturing & Wholesale Goods"
        }
    ],
    "sg:phone":"+1 407 273 1600",
    "sg:postcode":"32828",
    "sg:province":"FL",
    "sg:tags":[
        "feed"
    ],
    "wof:name":"East Orlando Feed",
    "wof:placetype":"venue"
},
  "geometry": {"coordinates":[-81.17809200000001,28.564816],"type":"Point"}
}