{
  "type": "Feature",
  "properties": {
    "iso:country":"US",
    "sg:address":"3665 Bee Ridge Rd Suite 200",
    "sg:city":"Sarasota",
    "sg:classifiers":[
        {
            "category":"Professional",
            "subcategory":"Computer Services",
            "type":"Services"
        }
    ],
    "sg:phone":"+1 941 312 2830",
    "sg:postcode":"34233",
    "sg:province":"FL",
    "sg:tags":[
        "mobile",
        "healthcare",
        "iphone",
        "blackberry",
        "hospitals"
    ],
    "sg:website":"http://www.voalte.com",
    "wof:name":"Voalt\u00e9",
    "wof:placetype":"venue"
},
  "geometry": {"coordinates":[-82.495437,27.298772],"type":"Point"}
}