{
  "type": "Feature",
  "properties": {
    "iso:country":"US",
    "sg:address":"15512 SW 152nd Ln",
    "sg:city":"Miami",
    "sg:classifiers":[
        {
            "category":"Professional",
            "subcategory":"Engineering",
            "type":"Services"
        }
    ],
    "sg:phone":"+1 305 234 7314",
    "sg:postcode":"33187",
    "sg:province":"FL",
    "sg:tags":[
        "refrigeration",
        "engineer"
    ],
    "wof:name":"J & B Refrigeration & A/C Corp.",
    "wof:placetype":"venue"
},
  "geometry": {"coordinates":[-80.444384,25.623978],"type":"Point"}
}