{
  "type": "Feature",
  "properties": {
    "addr:full":"947 McDonald Rd Port Orange FL 32129",
    "addr:housenumber":"947",
    "addr:postcode":"32129",
    "addr:street":"Mcdonald Rd",
    "iso:country":"US",
    "sg:address":"947 McDonald Rd",
    "sg:city":"Port Orange",
    "sg:classifiers":[
        {
            "category":"Shopping",
            "subcategory":"Bicycles & Sporting Goods",
            "type":"Retail Goods"
        }
    ],
    "sg:phone":"+1 386 767 4403",
    "sg:postcode":"32129",
    "sg:province":"FL",
    "sg:tags":[
        "equipment",
        "diver",
        "supply"
    ],
    "wof:name":"Discover Diving Dive Ctr",
    "wof:placetype":"venue"
},
  "geometry": {"coordinates":[-81.002804,29.147354],"type":"Point"}
}