{
  "type": "Feature",
  "properties": {
    "addr:full":"7215 Miami Lakes Dr Hialeah FL 33014",
    "addr:housenumber":"7215",
    "addr:postcode":"33014",
    "addr:street":"Miami Lakes Dr",
    "iso:country":"US",
    "sg:address":"7215 Miami Lakes Dr",
    "sg:city":"Hialeah",
    "sg:classifiers":[
        {
            "category":"Wholesale",
            "subcategory":"Computers",
            "type":"Manufacturing & Wholesale Goods"
        }
    ],
    "sg:phone":"+1 305 826 4343",
    "sg:postcode":"33014",
    "sg:province":"FL",
    "sg:tags":[
        "communication",
        "equipment"
    ],
    "wof:name":"Digicare Corp",
    "wof:placetype":"venue"
},
  "geometry": {"coordinates":[-80.317001,25.910019],"type":"Point"}
}