{
  "type": "Feature",
  "properties": {
    "addr:full":"1631 Providence Cir Orlando FL 32818",
    "addr:housenumber":"1631",
    "addr:postcode":"32818",
    "addr:street":"Providence Cir",
    "iso:country":"US",
    "sg:address":"1631 Providence Cir",
    "sg:city":"Orlando",
    "sg:classifiers":[
        {
            "category":"Professional",
            "subcategory":"Management & Consulting",
            "type":"Services"
        }
    ],
    "sg:phone":"+1 407 924 7500",
    "sg:postcode":"32818",
    "sg:province":"FL",
    "sg:tags":[
        "planning",
        "consultant",
        "space",
        "facility"
    ],
    "wof:name":"Lsa Geoup Inc",
    "wof:placetype":"venue"
},
  "geometry": {"coordinates":[-81.493909,28.565436],"type":"Point"}
}