{
  "type": "Feature",
  "properties": {
    "iso:country":"US",
    "sg:address":"165 N Jackson Rd",
    "sg:city":"Venice",
    "sg:classifiers":[
        {
            "category":"Organizations",
            "subcategory":"Community Association",
            "type":"Services"
        }
    ],
    "sg:phone":"+1 941 483 4830",
    "sg:postcode":"34292",
    "sg:province":"FL",
    "sg:tags":[
        "club"
    ],
    "wof:name":"Hungarian Christian Society",
    "wof:placetype":"venue"
},
  "geometry": {"coordinates":[-82.36008200000001,27.106178],"type":"Point"}
}