{
  "type": "Feature",
  "properties": {
    "iso:country":"US",
    "sg:address":"11315 Co Rd 2082",
    "sg:city":"Gainesville",
    "sg:classifiers":[
        {
            "category":"Building & Trades",
            "subcategory":"Plumbing",
            "type":"Services"
        }
    ],
    "sg:phone":"+1 352 215 2103",
    "sg:postcode":"32640",
    "sg:province":"FL",
    "sg:tags":[
        "conditioning",
        "air",
        "system",
        "contractor"
    ],
    "wof:name":"Harpers Heating & A/C",
    "wof:placetype":"venue"
},
  "geometry": {"coordinates":[-82.093328,29.590632],"type":"Point"}
}