{
  "type": "Feature",
  "properties": {
    "iso:country":"US",
    "sg:address":"622 S Colorado Ave",
    "sg:city":"Stuart",
    "sg:classifiers":[
        {
            "category":"Shopping",
            "subcategory":"Pharmacy",
            "type":"Retail Goods"
        }
    ],
    "sg:phone":"+1 772 287 3443",
    "sg:postcode":"34994",
    "sg:province":"FL",
    "wof:name":"Prescription Shop",
    "wof:placetype":"venue"
},
  "geometry": {"coordinates":[-80.252916,27.194802],"type":"Point"}
}