{
  "type": "Feature",
  "properties": {
    "iso:country":"US",
    "sg:address":"1750 SW 100th St",
    "sg:city":"Ocala",
    "sg:classifiers":[
        {
            "category":"Retail",
            "subcategory":"Animal Services",
            "type":"Services"
        }
    ],
    "sg:phone":"+1 352 237 7223",
    "sg:postcode":"34476",
    "sg:province":"FL",
    "wof:name":"Lazy Eight Farm",
    "wof:placetype":"venue"
},
  "geometry": {"coordinates":[-82.15630299999999,29.077022],"type":"Point"}
}