{
  "type": "Feature",
  "properties": {
    "iso:country":"US",
    "sg:address":"1720 E Hallandale Beach Blvd",
    "sg:city":"Hallandale Beach",
    "sg:classifiers":[
        {
            "category":"Wholesale",
            "subcategory":"Machinery & Supplies",
            "type":"Manufacturing & Wholesale Goods"
        },
        {
            "category":"Autos & Motor Vehicles",
            "subcategory":"Boat Sales",
            "type":"Retail Goods"
        },
        {
            "category":"Retail",
            "subcategory":"Repair Shop",
            "type":"Services"
        }
    ],
    "sg:phone":"+1 954 457 5081",
    "sg:postcode":"33009",
    "sg:province":"FL",
    "sg:tags":[
        "equipment",
        "transportation",
        "nautical"
    ],
    "wof:name":"Boat Owners Warehouse",
    "wof:placetype":"venue"
},
  "geometry": {"coordinates":[-80.129527,25.986003],"type":"Point"}
}