{
  "type": "Feature",
  "properties": {
    "iso:country":"US",
    "sg:address":"9325 S Magnolia Ave",
    "sg:city":"Ocala",
    "sg:classifiers":[
        {
            "category":"Farming",
            "subcategory":"Farm & Veterinary Services",
            "type":"Manufacturing & Wholesale Goods"
        }
    ],
    "sg:phone":"+1 352 237 5336",
    "sg:postcode":"34476",
    "sg:province":"FL",
    "sg:tags":[
        "livestock"
    ],
    "wof:name":"Fair Oaks",
    "wof:placetype":"venue"
},
  "geometry": {"coordinates":[-82.136111,29.086626],"type":"Point"}
}