{
  "type": "Feature",
  "properties": {
    "addr:full":"640 NE 19th Ave Deerfield Beach FL 33441",
    "addr:housenumber":"640",
    "addr:postcode":"33441",
    "addr:street":"Ne 19Th Ave",
    "iso:country":"US",
    "sg:address":"640 NE 19th Ave",
    "sg:city":"Deerfield Beach",
    "sg:classifiers":[
        {
            "category":"Real Estate",
            "subcategory":"Real Estate Agent",
            "type":"Services"
        }
    ],
    "sg:phone":"+1 954 422 8729",
    "sg:postcode":"33441",
    "sg:province":"FL",
    "wof:name":"Bellwether Realty LLC",
    "wof:placetype":"venue"
},
  "geometry": {"coordinates":[-80.07951799999999,26.320081],"type":"Point"}
}