{
  "type": "Feature",
  "properties": {
    "iso:country":"US",
    "sg:address":"5001 W Rio Vista Ave",
    "sg:city":"Tampa",
    "sg:classifiers":[
        {
            "category":"Building & Trades",
            "subcategory":"Construction",
            "type":"Services"
        }
    ],
    "sg:phone":"+1 813 888 8604",
    "sg:postcode":"33634",
    "sg:province":"FL",
    "sg:tags":[
        "windows"
    ],
    "wof:name":"Revco Remodeling Group Inc",
    "wof:placetype":"venue"
},
  "geometry": {"coordinates":[-82.52658599999999,27.999657],"type":"Point"}
}