{
  "type": "Feature",
  "properties": {
    "iso:country":"US",
    "sg:address":"1481 Cottonwood Trl",
    "sg:city":"Sarasota",
    "sg:classifiers":[
        {
            "category":"Professional",
            "subcategory":"Advertising",
            "type":"Services"
        }
    ],
    "sg:phone":"+1 941 379 0202",
    "sg:postcode":"34232",
    "sg:province":"FL",
    "sg:tags":[
        "counselor"
    ],
    "wof:name":"Begin Productions Inc",
    "wof:placetype":"venue"
},
  "geometry": {"coordinates":[-82.482078,27.317358],"type":"Point"}
}