{
  "type": "Feature",
  "properties": {
    "iso:country":"US",
    "sg:address":"1413 S Woodland Blvd",
    "sg:city":"Deland",
    "sg:classifiers":[
        {
            "category":"Retail",
            "subcategory":"Repair Shop",
            "type":"Services"
        },
        {
            "category":"Retail",
            "subcategory":"Auto Repair",
            "type":"Services"
        }
    ],
    "sg:phone":"+1 386 738 5022",
    "sg:postcode":"32720",
    "sg:province":"FL",
    "sg:tags":[
        "stereo",
        "installation",
        "automobile",
        "coating",
        "tinting",
        "glass",
        "automotive"
    ],
    "sg:website":"www.cartunesandtint.com",
    "wof:name":"Car Tunes & Tint",
    "wof:placetype":"venue"
},
  "geometry": {"coordinates":[-81.30239899999999,29.004299],"type":"Point"}
}