{
  "type": "Feature",
  "properties": {
    "iso:country":"US",
    "sg:address":"1420 N Atlantic Ave",
    "sg:city":"Daytona Beach",
    "sg:classifiers":[
        {
            "category":"Real Estate",
            "subcategory":"Real Estate Operator",
            "type":"Services"
        }
    ],
    "sg:phone":"+1 386 255 0790",
    "sg:postcode":"32118",
    "sg:province":"FL",
    "sg:tags":[
        "condominium"
    ],
    "wof:name":"Horizons Condominium",
    "wof:placetype":"venue"
},
  "geometry": {"coordinates":[-81.019874,29.251118],"type":"Point"}
}