{
  "type": "Feature",
  "properties": {
    "iso:country":"US",
    "sg:address":"2080 King St",
    "sg:city":"Cocoa",
    "sg:classifiers":[
        {
            "category":"Wholesale",
            "subcategory":"Machinery & Supplies",
            "type":"Manufacturing & Wholesale Goods"
        }
    ],
    "sg:phone":"+1 321 632 9026",
    "sg:postcode":"32926",
    "sg:province":"FL",
    "sg:tags":[
        "equipment",
        "industrial"
    ],
    "wof:name":"Jamesbury Distributors Inc",
    "wof:placetype":"venue"
},
  "geometry": {"coordinates":[-80.764293,28.355771],"type":"Point"}
}