{
  "type": "Feature",
  "properties": {
    "iso:country":"US",
    "sg:address":"773 4th Ave N",
    "sg:city":"Naples",
    "sg:classifiers":[
        {
            "category":"Health Services",
            "subcategory":"Doctor",
            "type":"Services"
        }
    ],
    "sg:phone":"+1 239 434 8119",
    "sg:postcode":"34102",
    "sg:province":"FL",
    "sg:tags":[
        "clinic"
    ],
    "wof:name":"Medical Cuban American",
    "wof:placetype":"venue"
},
  "geometry": {"coordinates":[-81.798602,26.151552],"type":"Point"}
}