{
  "type": "Feature",
  "properties": {
    "iso:country":"US",
    "sg:address":"3101 University Blvd S",
    "sg:city":"Jacksonville",
    "sg:classifiers":[
        {
            "category":"Banks & Credit Unions",
            "subcategory":"Investment Brokerage",
            "type":"Services"
        }
    ],
    "sg:phone":"+1 904 724 5116",
    "sg:postcode":"32216",
    "sg:province":"FL",
    "sg:tags":[
        "variable",
        "annuity",
        "company"
    ],
    "wof:name":"Variable Annuity Life Insur Co",
    "wof:placetype":"venue"
},
  "geometry": {"coordinates":[-81.60179599999999,30.294615],"type":"Point"}
}