{
  "type": "Feature",
  "properties": {
    "iso:country":"US",
    "sg:address":"6101 Waterway Bay Dr",
    "sg:city":"Fort Myers",
    "sg:classifiers":[
        {
            "category":"Manufacturing",
            "subcategory":"Printing",
            "type":"Manufacturing & Wholesale Goods"
        }
    ],
    "sg:phone":"+1 239 466 5646",
    "sg:postcode":"33908",
    "sg:province":"FL",
    "sg:tags":[
        "mfg"
    ],
    "wof:name":"Paradise Scrapbook Studio",
    "wof:placetype":"venue"
},
  "geometry": {"coordinates":[-81.85605099999999,26.489651],"type":"Point"}
}