{
  "type": "Feature",
  "properties": {
    "addr:full":"4983 State Hwy 87 Milton FL 32583",
    "addr:housenumber":"4983",
    "addr:postcode":"32583",
    "addr:street":"State Hwy 87",
    "iso:country":"US",
    "sg:address":"4983 State Hwy 87",
    "sg:city":"Milton",
    "sg:classifiers":[
        {
            "category":"Autos & Motor Vehicles",
            "subcategory":"Fuel & Gas Station",
            "type":"Retail Goods"
        }
    ],
    "sg:phone":"+1 850 623 8870",
    "sg:postcode":"32583",
    "sg:province":"FL",
    "sg:tags":[
        "oil"
    ],
    "wof:name":"Milton Interstate Shell",
    "wof:placetype":"venue"
},
  "geometry": {"coordinates":[-86.96099700000001,30.615531],"type":"Point"}
}