{
  "type": "Feature",
  "properties": {
    "iso:country":"US",
    "sg:address":"18860 Loxahatchee River Rd",
    "sg:city":"Jupiter",
    "sg:classifiers":[
        {
            "category":"Autos & Motor Vehicles",
            "subcategory":"Boat Sales",
            "type":"Retail Goods"
        },
        {
            "category":"Manufacturing",
            "subcategory":"Motor Vehicles & Parts",
            "type":"Manufacturing & Wholesale Goods"
        }
    ],
    "sg:phone":"+1 561 747 0511",
    "sg:postcode":"33458",
    "sg:province":"FL",
    "sg:tags":[
        "docking",
        "wa",
        "for",
        "supply",
        "personal",
        "mfg",
        "drive",
        "system",
        "equipment"
    ],
    "wof:name":"Sportport",
    "wof:placetype":"venue"
},
  "geometry": {"coordinates":[-80.121791,26.953688],"type":"Point"}
}