{
  "type": "Feature",
  "properties": {
    "iso:country":"US",
    "sg:address":"1230 Sweetwater Ln",
    "sg:city":"Naples",
    "sg:classifiers":[
        {
            "category":"Building & Trades",
            "subcategory":"Construction",
            "type":"Services"
        }
    ],
    "sg:phone":"+1 239 596 7465",
    "sg:postcode":"34110",
    "sg:province":"FL",
    "sg:tags":[
        "home",
        "builder"
    ],
    "wof:name":"Colonial Homes Inc",
    "wof:placetype":"venue"
},
  "geometry": {"coordinates":[-81.799819,26.314997],"type":"Point"}
}