{
  "type": "Feature",
  "properties": {
    "iso:country":"US",
    "sg:address":"15455 Warfield Hwy",
    "sg:city":"Indiantown",
    "sg:classifiers":[
        {
            "category":"Food & Beverages",
            "subcategory":"Groceries & Convenience Stores",
            "type":"Retail Goods"
        }
    ],
    "sg:phone":"+1 772 597 4008",
    "sg:postcode":"34956",
    "sg:province":"FL",
    "wof:name":"Moon & Moon Inc",
    "wof:placetype":"venue"
},
  "geometry": {"coordinates":[-80.46348399999999,27.018427],"type":"Point"}
}