{
  "type": "Feature",
  "properties": {
    "iso:country":"US",
    "sg:address":"851 S State Road 434",
    "sg:city":"Altamonte Springs",
    "sg:classifiers":[
        {
            "category":"Food & Beverages",
            "subcategory":"Liquor & Beverages",
            "type":"Retail Goods"
        }
    ],
    "sg:phone":"+1 407 522 0988",
    "sg:postcode":"32714",
    "sg:province":"FL",
    "sg:tags":[
        "beer",
        "spirit",
        "wine"
    ],
    "wof:name":"Liquor Emporium",
    "wof:placetype":"venue"
},
  "geometry": {"coordinates":[-81.41528599999999,28.650713],"type":"Point"}
}