{
  "type": "Feature",
  "properties": {
    "iso:country":"US",
    "sg:address":"151 NE 166th St",
    "sg:city":"Miami",
    "sg:classifiers":[
        {
            "category":"Real Estate",
            "subcategory":"Real Estate Services",
            "type":"Services"
        },
        {
            "category":"Building & Trades",
            "subcategory":"Cleaning & Sanitation",
            "type":"Services"
        }
    ],
    "sg:phone":"+1 305 949 5033",
    "sg:postcode":"33162",
    "sg:province":"FL",
    "sg:tags":[
        "maintenance",
        "cleaners-interior"
    ],
    "wof:name":"Reliable Cleaning",
    "wof:placetype":"venue"
},
  "geometry": {"coordinates":[-80.197272,25.927276],"type":"Point"}
}