{
  "type": "Feature",
  "properties": {
    "addr:full":"10808 US Hwy 98 Dade City FL 33525",
    "addr:housenumber":"10808",
    "addr:postcode":"33525",
    "addr:street":"Us Hwy 98",
    "iso:country":"US",
    "sg:address":"10808 US Hwy 98",
    "sg:city":"Dade City",
    "sg:classifiers":[
        {
            "category":"Real Estate",
            "subcategory":"Real Estate Operator",
            "type":"Services"
        }
    ],
    "sg:phone":"+1 352 523 0022",
    "sg:postcode":"33525",
    "sg:province":"FL",
    "sg:tags":[
        "mobile",
        "home",
        "site",
        "community"
    ],
    "wof:name":"Southfork Mobile Home Cmnty",
    "wof:placetype":"venue"
},
  "geometry": {"coordinates":[-82.179215,28.317195],"type":"Point"}
}