{
  "type": "Feature",
  "properties": {
    "iso:country":"US",
    "sg:address":"682 Maitland Ave Ste A",
    "sg:city":"Altamonte Springs",
    "sg:classifiers":[
        {
            "category":"Professional",
            "subcategory":"Accounting & Tax Preparation",
            "type":"Services"
        }
    ],
    "sg:phone":"+1 407 332 8311",
    "sg:postcode":"32701",
    "sg:province":"FL",
    "sg:tags":[
        "accountant"
    ],
    "wof:name":"Chokshi Accounting & Tax Services Inc",
    "wof:placetype":"venue"
},
  "geometry": {"coordinates":[-81.36611600000001,28.648399],"type":"Point"}
}