{
  "type": "Feature",
  "properties": {
    "addr:full":"5305 NW 35th Ct Miami FL 33142",
    "addr:housenumber":"5305",
    "addr:postcode":"33142",
    "addr:street":"Nw 35Th Ct",
    "iso:country":"US",
    "sg:address":"5305 NW 35th Ct",
    "sg:city":"Miami",
    "sg:classifiers":[
        {
            "category":"Wholesale",
            "subcategory":"Non-durable Goods",
            "type":"Manufacturing & Wholesale Goods"
        }
    ],
    "sg:phone":"+1 305 633 2945",
    "sg:postcode":"33142",
    "sg:province":"FL",
    "sg:tags":[
        "merchandise",
        "general"
    ],
    "wof:name":"Extrasport Inc",
    "wof:placetype":"venue"
},
  "geometry": {"coordinates":[-80.253798,25.822552],"type":"Point"}
}