{
  "type": "Feature",
  "properties": {
    "addr:full":"4440 Onorio St New Port Richey FL 34653",
    "addr:postcode":"4440;34653",
    "addr:street":"Onorio St",
    "iso:country":"US",
    "sg:address":"4440 Onorio St",
    "sg:city":"New Port Richey",
    "sg:classifiers":[
        {
            "category":"Home & Garden",
            "subcategory":"Carpets & Floor Coverings",
            "type":"Retail Goods"
        }
    ],
    "sg:phone":"+1 727 372 3996",
    "sg:postcode":"34653",
    "sg:province":"FL",
    "wof:name":"Luis Montero Carpet Service",
    "wof:placetype":"venue"
},
  "geometry": {"coordinates":[-82.690121,28.223325],"type":"Point"}
}