{
  "type": "Feature",
  "properties": {
    "addr:full":"475 W State Rd 436 Altamonte Springs FL 32714",
    "addr:housenumber":"475;436",
    "addr:postcode":"32714",
    "addr:street":"W State Rd",
    "iso:country":"US",
    "sg:address":"475 W State Rd 436",
    "sg:city":"Altamonte Springs",
    "sg:classifiers":[
        {
            "category":"Home & Garden",
            "subcategory":"Furniture",
            "type":"Retail Goods"
        }
    ],
    "sg:phone":"+1 407 865 9555",
    "sg:postcode":"32714",
    "sg:province":"FL",
    "wof:name":"Kids Quarters  Inc",
    "wof:placetype":"venue"
},
  "geometry": {"coordinates":[-81.398552,28.662017],"type":"Point"}
}