{
  "type": "Feature",
  "properties": {
    "addr:full":"3224 Preston St Lake Wales FL 33859",
    "addr:housenumber":"3224",
    "addr:postcode":"33859",
    "addr:street":"Preston St",
    "iso:country":"US",
    "sg:address":"3224 Preston St",
    "sg:city":"Lake Wales",
    "sg:classifiers":[
        {
            "category":"Building & Trades",
            "subcategory":"Plumbing",
            "type":"Services"
        }
    ],
    "sg:phone":"+1 863 412 5752",
    "sg:postcode":"33859",
    "sg:province":"FL",
    "sg:tags":[
        "contractor"
    ],
    "wof:name":"Manuel Palacios Contracting",
    "wof:placetype":"venue"
},
  "geometry": {"coordinates":[-81.64015999999999,27.919159],"type":"Point"}
}