{
  "type": "Feature",
  "properties": {
    "addr:full":"120 Contractors Way Lakeland FL 33801",
    "addr:housenumber":"120",
    "addr:postcode":"33801",
    "addr:street":"Contractors Way",
    "iso:country":"US",
    "sg:address":"120 Contractors Way",
    "sg:city":"Lakeland",
    "sg:classifiers":[
        {
            "category":"Building & Trades",
            "subcategory":"Construction",
            "type":"Services"
        }
    ],
    "sg:phone":"+1 863 667 3939",
    "sg:postcode":"33801",
    "sg:province":"FL",
    "sg:tags":[
        "maker",
        "cabinet"
    ],
    "wof:name":"Cabinet Installations Unltd",
    "wof:placetype":"venue"
},
  "geometry": {"coordinates":[-81.903229,28.042695],"type":"Point"}
}