{
  "type": "Feature",
  "properties": {
    "iso:country":"US",
    "sg:address":"21113 Johnson St",
    "sg:city":"Hollywood",
    "sg:classifiers":[
        {
            "category":"Shopping",
            "subcategory":"Gifts & Souvenirs",
            "type":"Retail Goods"
        }
    ],
    "sg:phone":"+1 954 538 3755",
    "sg:postcode":"33029",
    "sg:province":"FL",
    "wof:name":"Party Explosion",
    "wof:placetype":"venue"
},
  "geometry": {"coordinates":[-80.43089000000001,26.015183],"type":"Point"}
}