{
  "type": "Feature",
  "properties": {
    "iso:country":"US",
    "sg:address":"311 N Bayshore Dr",
    "sg:city":"Safety Harbor",
    "sg:classifiers":[
        {
            "category":"Banks & Credit Unions",
            "subcategory":"Bank",
            "type":"Services"
        }
    ],
    "sg:phone":"+1 727 216 4000",
    "sg:postcode":"34695",
    "sg:province":"FL",
    "sg:tags":[
        "equipment",
        "leasing"
    ],
    "wof:name":"Bay4 Capital LLC",
    "wof:placetype":"venue"
},
  "geometry": {"coordinates":[-82.686262,27.993075],"type":"Point"}
}