{
  "type": "Feature",
  "properties": {
    "addr:full":"4430 SW 24th Ave Fort Lauderdale FL 33312",
    "addr:housenumber":"4430",
    "addr:postcode":"33312",
    "addr:street":"Sw 24Th Ave",
    "iso:country":"US",
    "sg:address":"4430 SW 24th Ave",
    "sg:city":"Fort Lauderdale",
    "sg:classifiers":[
        {
            "category":"Shopping",
            "subcategory":"Crafts & Fabrics",
            "type":"Retail Goods"
        }
    ],
    "sg:phone":"+1 954 981 6297",
    "sg:postcode":"33312",
    "sg:province":"FL",
    "sg:tags":[
        "sewing"
    ],
    "wof:name":"Biscayne Fabrics Etc Inc",
    "wof:placetype":"venue"
},
  "geometry": {"coordinates":[-80.17316700000001,26.067473],"type":"Point"}
}