{
  "type": "Feature",
  "properties": {
    "iso:country":"US",
    "sg:address":"203 Courthouse Sq",
    "sg:city":"Inverness",
    "sg:classifiers":[
        {
            "category":"Professional",
            "subcategory":"Lawyer & Legal Services",
            "type":"Services"
        }
    ],
    "sg:phone":"+1 352 726 9111",
    "sg:postcode":"34450",
    "sg:province":"FL",
    "sg:tags":[
        "attorney"
    ],
    "wof:name":"Daniel J Snow P A",
    "wof:placetype":"venue"
},
  "geometry": {"coordinates":[-82.33068900000001,28.835681],"type":"Point"}
}