{
  "type": "Feature",
  "properties": {
    "iso:country":"US",
    "sg:address":"2596 W 84th St",
    "sg:city":"Hialeah",
    "sg:classifiers":[
        {
            "category":"Restaurant",
            "type":"Food & Drink"
        }
    ],
    "sg:phone":"+1 305 827 5366",
    "sg:postcode":"33016",
    "sg:province":"FL",
    "sg:tags":[
        "deli",
        "delicatessen"
    ],
    "wof:name":"Franky's Deli Warehouse",
    "wof:placetype":"venue"
},
  "geometry": {"coordinates":[-80.335999,25.8976],"type":"Point"}
}