{
  "type": "Feature",
  "properties": {
    "iso:country":"US",
    "sg:address":"138 Palm Coast Pkwy NE",
    "sg:city":"Palm Coast",
    "sg:classifiers":[
        {
            "category":"Professional",
            "type":"Services"
        }
    ],
    "sg:phone":"+1 386 671 0413",
    "sg:postcode":"32137",
    "sg:province":"FL",
    "sg:tags":[
        "communications"
    ],
    "wof:name":"Pagecom",
    "wof:placetype":"venue"
},
  "geometry": {"coordinates":[-81.19271999999999,29.564608],"type":"Point"}
}