{
  "type": "Feature",
  "properties": {
    "iso:country":"US",
    "sg:address":"309 N Howard Ave",
    "sg:city":"Tampa",
    "sg:classifiers":[
        {
            "category":"Food & Beverages",
            "subcategory":"Chocolate",
            "type":"Retail Goods"
        }
    ],
    "sg:phone":"+1 813 966 6029",
    "sg:postcode":"33606",
    "sg:province":"FL",
    "sg:tags":[
        "cooler"
    ],
    "wof:name":"Sunshine Distributors & Svcs.",
    "wof:placetype":"venue"
},
  "geometry": {"coordinates":[-82.48297100000001,27.94701],"type":"Point"}
}