{
  "type": "Feature",
  "properties": {
    "iso:country":"US",
    "sg:address":"225 Saint Joe Plaza Rd",
    "sg:city":"Palm Coast",
    "sg:classifiers":[
        {
            "category":"Retail",
            "subcategory":"Funeral Services",
            "type":"Services"
        }
    ],
    "sg:phone":"+1 386 447 1331",
    "sg:postcode":"32164",
    "sg:province":"FL",
    "sg:tags":[
        "director"
    ],
    "wof:name":"Craig Funeral Home",
    "wof:placetype":"venue"
},
  "geometry": {"coordinates":[-81.255826,29.552512],"type":"Point"}
}