{
  "type": "Feature",
  "properties": {
    "iso:country":"US",
    "sg:address":"329 Interstate Ct",
    "sg:city":"Sarasota",
    "sg:classifiers":[
        {
            "category":"Manufacturing",
            "subcategory":"Printing",
            "type":"Manufacturing & Wholesale Goods"
        }
    ],
    "sg:phone":"+1 941 371 7100",
    "sg:postcode":"34240",
    "sg:province":"FL",
    "sg:tags":[
        "publisher"
    ],
    "wof:name":"GMC Assoc",
    "wof:placetype":"venue"
},
  "geometry": {"coordinates":[-82.445381,27.332373],"type":"Point"}
}