{
  "type": "Feature",
  "properties": {
    "addr:full":"9801 NW 24th Ave Miami FL 33147",
    "addr:housenumber":"9801",
    "addr:postcode":"33147",
    "addr:street":"Nw 24Th Ave",
    "iso:country":"US",
    "sg:address":"9801 NW 24th Ave",
    "sg:city":"Miami",
    "sg:classifiers":[
        {
            "category":"Place Of Worship",
            "subcategory":"Church",
            "type":"Public Place"
        },
        {
            "category":"Place Of Worship",
            "type":"Public Place"
        },
        {
            "category":"Education",
            "subcategory":"School",
            "type":"Public Place"
        }
    ],
    "sg:phone":"+1 305 836 9747",
    "sg:postcode":"33147",
    "sg:province":"FL",
    "sg:tags":[
        "churches-baptist-general",
        "k-",
        "private",
        "churches-baptist"
    ],
    "wof:name":"Bible Baptist Church",
    "wof:placetype":"venue"
},
  "geometry": {"coordinates":[-80.238258,25.863791],"type":"Point"}
}