{
  "type": "Feature",
  "properties": {
    "addr:full":"3600 Aviation Blvd Vero Beach FL 32960",
    "addr:housenumber":"3600",
    "addr:postcode":"32960",
    "addr:street":"Aviation Blvd",
    "iso:country":"US",
    "sg:address":"3600 Aviation Blvd",
    "sg:city":"Vero Beach",
    "sg:classifiers":[
        {
            "category":"Utilities",
            "subcategory":"Telephone",
            "type":"Services"
        }
    ],
    "sg:phone":"+1 772 569 7550",
    "sg:postcode":"32960",
    "sg:province":"FL",
    "sg:tags":[
        "telecommunication"
    ],
    "wof:name":"BellSouth",
    "wof:placetype":"venue"
},
  "geometry": {"coordinates":[-80.420348,27.646906],"type":"Point"}
}