{
  "type": "Feature",
  "properties": {
    "addr:full":"1870 State Hwy 436 Winter Park FL 32792",
    "addr:housenumber":"1870",
    "addr:postcode":"32792",
    "addr:street":"State Hwy 436",
    "iso:country":"US",
    "sg:address":"1870 State Hwy 436",
    "sg:city":"Winter Park",
    "sg:classifiers":[
        {
            "category":"Restaurant",
            "type":"Food & Drink"
        }
    ],
    "sg:phone":"+1 407 679 1222",
    "sg:postcode":"32792",
    "sg:province":"FL",
    "sg:tags":[
        "drinking",
        "eating"
    ],
    "wof:name":"Roadhouse Grill",
    "wof:placetype":"venue"
},
  "geometry": {"coordinates":[-81.311251,28.615794],"type":"Point"}
}