{
  "type": "Feature",
  "properties": {
    "iso:country":"US",
    "sg:address":"2117 Cordes St",
    "sg:city":"Osprey",
    "sg:classifiers":[
        {
            "category":"Building & Trades",
            "subcategory":"Construction",
            "type":"Services"
        }
    ],
    "sg:phone":"+1 941 966 6276",
    "sg:postcode":"34229",
    "sg:province":"FL",
    "sg:tags":[
        "house"
    ],
    "wof:name":"Robert G Balint",
    "wof:placetype":"venue"
},
  "geometry": {"coordinates":[-82.48659000000001,27.210439],"type":"Point"}
}