{
  "type": "Feature",
  "properties": {
    "iso:country":"US",
    "sg:address":"1001 SW 139th Ave",
    "sg:city":"Miami",
    "sg:classifiers":[
        {
            "category":"Taxi",
            "type":"Transportation"
        }
    ],
    "sg:phone":"+1 305 228 0176",
    "sg:postcode":"33184",
    "sg:province":"FL",
    "sg:tags":[
        "taxicab"
    ],
    "wof:name":"Flecha Rent-A-Car",
    "wof:placetype":"venue"
},
  "geometry": {"coordinates":[-80.42076900000001,25.756968],"type":"Point"}
}