{
  "type": "Feature",
  "properties": {
    "iso:country":"US",
    "sg:address":"1100 Commercial Blvd",
    "sg:city":"Naples",
    "sg:classifiers":[
        {
            "category":"Professional",
            "subcategory":"Management & Consulting",
            "type":"Services"
        }
    ],
    "sg:phone":"+1 239 263 6363",
    "sg:postcode":"34104",
    "sg:province":"FL",
    "sg:tags":[
        "business"
    ],
    "wof:name":"Sprint",
    "wof:placetype":"venue"
},
  "geometry": {"coordinates":[-81.752844,26.1635],"type":"Point"}
}