{
  "type": "Feature",
  "properties": {
    "iso:country":"US",
    "sg:address":"2600 S Orange Ave",
    "sg:city":"Orlando",
    "sg:classifiers":[
        {
            "category":"Restaurant",
            "type":"Food & Drink"
        }
    ],
    "sg:menulink":"http://www.allmenus.com/fl/orlando/158573-arbys/menu/",
    "sg:phone":"+1 407 841 6276",
    "sg:postcode":"32806",
    "sg:province":"FL",
    "sg:tags":[
        "burger",
        "american"
    ],
    "wof:name":"Arby's",
    "wof:placetype":"venue"
},
  "geometry": {"coordinates":[-81.37668499999999,28.513592],"type":"Point"}
}