{
  "type": "Feature",
  "properties": {
    "iso:country":"US",
    "sg:address":"2405 Mc Rae Ave",
    "sg:city":"Orlando",
    "sg:classifiers":[
        {
            "category":"Health Services",
            "subcategory":"Doctor",
            "type":"Services"
        }
    ],
    "sg:phone":"+1 407 898 6004",
    "sg:postcode":"32803",
    "sg:province":"FL",
    "sg:tags":[
        "medical"
    ],
    "wof:name":"Princeton Professional Svcs",
    "wof:placetype":"venue"
},
  "geometry": {"coordinates":[-81.372159,28.574145],"type":"Point"}
}