{
  "type": "Feature",
  "properties": {
    "iso:country":"US",
    "sg:address":"36366 US Hwy 19 N",
    "sg:city":"Palm Harbor",
    "sg:classifiers":[
        {
            "category":"Manufacturing",
            "subcategory":"Printing",
            "type":"Manufacturing & Wholesale Goods"
        }
    ],
    "sg:phone":"+1 727 785 7577",
    "sg:postcode":"34684",
    "sg:province":"FL",
    "sg:tags":[
        "lithographic",
        "commercial"
    ],
    "wof:name":"Pip Med Network Inc",
    "wof:placetype":"venue"
},
  "geometry": {"coordinates":[-82.739841,28.10181],"type":"Point"}
}