{
  "type": "Feature",
  "properties": {
    "addr:full":"1819 Totten Rd Fort Pierce FL 34947",
    "addr:housenumber":"1819",
    "addr:postcode":"34947",
    "addr:street":"Totten Rd",
    "iso:country":"US",
    "sg:address":"1819 Totten Rd",
    "sg:city":"Fort Pierce",
    "sg:classifiers":[
        {
            "category":"Utilities",
            "subcategory":"Telephone",
            "type":"Services"
        }
    ],
    "sg:phone":"+1 772 466 2426",
    "sg:postcode":"34947",
    "sg:province":"FL",
    "sg:tags":[
        "telecommunication"
    ],
    "wof:name":"Mastec Of North America",
    "wof:placetype":"venue"
},
  "geometry": {"coordinates":[-80.364566,27.430878],"type":"Point"}
}