{
  "type": "Feature",
  "properties": {
    "iso:country":"US",
    "sg:address":"2395 Kentucky Ave",
    "sg:city":"Mims",
    "sg:classifiers":[
        {
            "category":"Organizations",
            "subcategory":"Religious Organization",
            "type":"Services"
        }
    ],
    "sg:phone":"+1 321 267 4436",
    "sg:postcode":"32754",
    "sg:province":"FL",
    "sg:tags":[
        "place",
        "worship",
        "church"
    ],
    "sg:website":"http://www.fbcmims.com",
    "wof:name":"First Baptist Church Of Mims",
    "wof:placetype":"venue"
},
  "geometry": {"coordinates":[-80.84716,28.662649],"type":"Point"}
}