{
  "type": "Feature",
  "properties": {
    "addr:full":"726-728 Lincoln Road Miami Beach FL 33139",
    "addr:housenumber":"726-728",
    "addr:postcode":"33139",
    "addr:street":"Lincoln Road",
    "iso:country":"US",
    "sg:address":"726-728 Lincoln Road",
    "sg:city":"Miami Beach",
    "sg:classifiers":[
        {
            "category":"Shopping",
            "subcategory":"Clothing, Apparel, & Fashions",
            "type":"Retail Goods"
        }
    ],
    "sg:phone":"+1 305 673 9806",
    "sg:postcode":"33139",
    "sg:province":"FL",
    "sg:tags":[
        "clothing",
        "women's"
    ],
    "sg:website":"www.jcrew.com",
    "wof:name":"J. Crew",
    "wof:placetype":"venue"
},
  "geometry": {"coordinates":[-80.13602899999999,25.790524],"type":"Point"}
}