{
  "type": "Feature",
  "properties": {
    "iso:country":"US",
    "sg:address":"3396 NW South River Dr",
    "sg:city":"Miami",
    "sg:classifiers":[
        {
            "category":"Retail",
            "subcategory":"Auto Repair",
            "type":"Services"
        }
    ],
    "sg:phone":"+1 305 638 8033",
    "sg:postcode":"33142",
    "sg:province":"FL",
    "sg:tags":[
        "automobile",
        "top",
        "upholstery",
        "covers",
        "seat"
    ],
    "wof:name":"Milos Auto Upholstery",
    "wof:placetype":"venue"
},
  "geometry": {"coordinates":[-80.250328,25.79896],"type":"Point"}
}