{
  "type": "Feature",
  "properties": {
    "iso:country":"US",
    "sg:address":"1141 Compass Row",
    "sg:city":"St Augustine",
    "sg:classifiers":[
        {
            "category":"Arts & Performance",
            "subcategory":"Theater",
            "type":"Entertainment"
        }
    ],
    "sg:phone":"+1 904 461 5611",
    "sg:postcode":"32080",
    "sg:province":"FL",
    "sg:tags":[
        "musician"
    ],
    "wof:name":"Have Harp Will Travel",
    "wof:placetype":"venue"
},
  "geometry": {"coordinates":[-81.287463,29.854088],"type":"Point"}
}