{
  "type": "Feature",
  "properties": {
    "iso:country":"US",
    "sg:address":"750 S Orange Blossom Trl",
    "sg:city":"Orlando",
    "sg:classifiers":[
        {
            "category":"Education",
            "subcategory":"Special Training",
            "type":"Public Place"
        }
    ],
    "sg:phone":"+1 407 650 9007",
    "sg:postcode":"32805",
    "sg:province":"FL",
    "sg:tags":[
        "instruction",
        "driving"
    ],
    "wof:name":"Action Auto Driving School",
    "wof:placetype":"venue"
},
  "geometry": {"coordinates":[-81.397237,28.533842],"type":"Point"}
}