{
  "type": "Feature",
  "properties": {
    "addr:full":"18700 Veterans Blvd Port Charlotte FL 33954",
    "addr:housenumber":"18700",
    "addr:postcode":"33954",
    "addr:street":"Veterans Blvd",
    "iso:country":"US",
    "sg:address":"18700 Veterans Blvd",
    "sg:city":"Port Charlotte",
    "sg:classifiers":[
        {
            "category":"Home & Garden",
            "subcategory":"Home Furnishings",
            "type":"Retail Goods"
        }
    ],
    "sg:phone":"+1 941 766 0277",
    "sg:postcode":"33954",
    "sg:province":"FL",
    "sg:tags":[
        "housewares"
    ],
    "wof:name":"Bed Bath & Beyond",
    "wof:placetype":"venue"
},
  "geometry": {"coordinates":[-82.14418999999999,27.013486],"type":"Point"}
}