{
  "type": "Feature",
  "properties": {
    "iso:country":"US",
    "sg:address":"680 Goodlette Rd N",
    "sg:city":"Naples",
    "sg:classifiers":[
        {
            "category":"Health Services",
            "subcategory":"Doctor",
            "type":"Services"
        }
    ],
    "sg:phone":"+1 239 213 0621",
    "sg:postcode":"34102",
    "sg:province":"FL",
    "sg:tags":[
        "physician",
        "surgeon"
    ],
    "wof:name":"Anchor Health Ctr",
    "wof:placetype":"venue"
},
  "geometry": {"coordinates":[-81.79086700000001,26.153744],"type":"Point"}
}