{
  "type": "Feature",
  "properties": {
    "iso:country":"US",
    "sg:address":"137 Buenaventura Blvd",
    "sg:city":"Kissimmee",
    "sg:classifiers":[
        {
            "category":"Food & Beverages",
            "subcategory":"Bakery",
            "type":"Retail Goods"
        }
    ],
    "sg:phone":"+1 407 348 3285",
    "sg:postcode":"34743",
    "sg:province":"FL",
    "wof:name":"LA Carreta Bakery & Deli",
    "wof:placetype":"venue"
},
  "geometry": {"coordinates":[-81.343379,28.322201],"type":"Point"}
}