{
  "type": "Feature",
  "properties": {
    "iso:country":"US",
    "sg:address":"4041 W Oakland Park Blvd",
    "sg:city":"Fort Lauderdale",
    "sg:classifiers":[
        {
            "category":"Organizations",
            "subcategory":"Religious Organization",
            "type":"Services"
        }
    ],
    "sg:phone":"+1 954 731 6109",
    "sg:postcode":"33313",
    "sg:province":"FL",
    "sg:tags":[
        "church"
    ],
    "wof:name":"Epispical Church",
    "wof:placetype":"venue"
},
  "geometry": {"coordinates":[-80.203585,26.164944],"type":"Point"}
}