{
  "type": "Feature",
  "properties": {
    "iso:country":"US",
    "sg:address":"407 Florida Ave",
    "sg:city":"Fort Pierce",
    "sg:classifiers":[
        {
            "category":"Shopping",
            "type":"Retail Goods"
        }
    ],
    "sg:phone":"+1 772 489 2298",
    "sg:postcode":"34950",
    "sg:province":"FL",
    "sg:tags":[
        "wedding",
        "supply"
    ],
    "wof:name":"Florida Avenue Hall",
    "wof:placetype":"venue"
},
  "geometry": {"coordinates":[-80.326896,27.440604],"type":"Point"}
}