{
  "type": "Feature",
  "properties": {
    "addr:full":"6495 Lake Worth Rd Lake Worth FL 33463",
    "addr:housenumber":"6495",
    "addr:postcode":"33463",
    "addr:street":"Lake Worth Rd",
    "iso:country":"US",
    "sg:address":"6495 Lake Worth Rd",
    "sg:city":"Lake Worth",
    "sg:classifiers":[
        {
            "category":"Restaurant",
            "type":"Food & Drink"
        }
    ],
    "sg:menulink":"http://www.allmenus.com/fl/lake-worth/160403-burger-king/menu/",
    "sg:phone":"+1 561 967 6643",
    "sg:postcode":"33463",
    "sg:province":"FL",
    "sg:tags":[
        "burger",
        "american"
    ],
    "wof:name":"Burger King",
    "wof:placetype":"venue"
},
  "geometry": {"coordinates":[-80.146193,26.619594],"type":"Point"}
}