{
  "type": "Feature",
  "properties": {
    "addr:full":"1463 NW 97th Ave Doral FL 33172",
    "addr:housenumber":"1463",
    "addr:postcode":"33172",
    "addr:street":"Nw 97Th Ave",
    "iso:country":"US",
    "sg:address":"1463 NW 97th Ave",
    "sg:city":"Doral",
    "sg:classifiers":[
        {
            "category":"Professional",
            "subcategory":"Accounting & Tax Preparation",
            "type":"Services"
        }
    ],
    "sg:phone":"+1 305 994 9393",
    "sg:postcode":"33172",
    "sg:province":"FL",
    "sg:tags":[
        "bookkeeping",
        "general"
    ],
    "wof:name":"Accounting Firm LLC",
    "wof:placetype":"venue"
},
  "geometry": {"coordinates":[-80.35277499999999,25.788709],"type":"Point"}
}