{
  "type": "Feature",
  "properties": {
    "iso:country":"US",
    "sg:address":"3534 NW Federal Hwy",
    "sg:city":"Jensen Beach",
    "sg:classifiers":[
        {
            "category":"Home & Garden",
            "subcategory":"Furniture",
            "type":"Retail Goods"
        }
    ],
    "sg:phone":"+1 772 692 9214",
    "sg:postcode":"34957",
    "sg:province":"FL",
    "sg:website":"www.havertys.com",
    "wof:name":"Havertys Furniture",
    "wof:placetype":"venue"
},
  "geometry": {"coordinates":[-80.269712,27.238565],"type":"Point"}
}