{
  "type": "Feature",
  "properties": {
    "addr:full":"841 SE 8th Ave Deerfield Beach FL 33441",
    "addr:housenumber":"841",
    "addr:postcode":"33441",
    "addr:street":"Se 8Th Ave",
    "iso:country":"US",
    "sg:address":"841 SE 8th Ave",
    "sg:city":"Deerfield Beach",
    "sg:classifiers":[
        {
            "category":"Health Services",
            "subcategory":"Doctor",
            "type":"Services"
        }
    ],
    "sg:phone":"+1 954 421 2122",
    "sg:postcode":"33441",
    "sg:province":"FL",
    "wof:name":"Martin Wexler DDS",
    "wof:placetype":"venue"
},
  "geometry": {"coordinates":[-80.094005,26.306333],"type":"Point"}
}