{
  "type": "Feature",
  "properties": {
    "iso:country":"US",
    "sg:address":"1908 SW 84th Ter",
    "sg:city":"Pompano Beach",
    "sg:classifiers":[
        {
            "category":"Building & Trades",
            "subcategory":"Construction",
            "type":"Services"
        }
    ],
    "sg:phone":"+1 954 726 1149",
    "sg:postcode":"33068",
    "sg:province":"FL",
    "sg:tags":[
        "contractor"
    ],
    "wof:name":"Mars Pools Inc",
    "wof:placetype":"venue"
},
  "geometry": {"coordinates":[-80.24128899999999,26.203364],"type":"Point"}
}