{
  "type": "Feature",
  "properties": {
    "addr:full":"3763 Davis Rd Lake Worth FL 33461",
    "addr:housenumber":"3763",
    "addr:postcode":"33461",
    "addr:street":"Davis Rd",
    "iso:country":"US",
    "sg:address":"3763 Davis Rd",
    "sg:city":"Lake Worth",
    "sg:classifiers":[
        {
            "category":"Real Estate",
            "subcategory":"Real Estate Operator",
            "type":"Services"
        }
    ],
    "sg:phone":"+1 561 795 7388",
    "sg:postcode":"33461",
    "sg:province":"FL",
    "sg:tags":[
        "building",
        "apartment"
    ],
    "wof:name":"Marias Apts",
    "wof:placetype":"venue"
},
  "geometry": {"coordinates":[-80.097121,26.621463],"type":"Point"}
}