{
  "type": "Feature",
  "properties": {
    "iso:country":"US",
    "sg:address":"2003 Blanding Blvd",
    "sg:city":"Jacksonville",
    "sg:classifiers":[
        {
            "category":"Bars & Pubs",
            "type":"Food & Drink"
        },
        {
            "category":"Bars & Pubs",
            "subcategory":"Nightclub",
            "type":"Food & Drink"
        }
    ],
    "sg:phone":"+1 904 389 8273",
    "sg:postcode":"32210",
    "sg:province":"FL",
    "sg:tags":[
        "club",
        "night"
    ],
    "wof:name":"Flash Dancers",
    "wof:placetype":"venue"
},
  "geometry": {"coordinates":[-81.725959,30.282098],"type":"Point"}
}