{
  "type": "Feature",
  "properties": {
    "iso:country":"US",
    "sg:address":"620 Cypress Ave",
    "sg:city":"Venice",
    "sg:classifiers":[
        {
            "category":"Retail",
            "subcategory":"Repair Shop",
            "type":"Services"
        }
    ],
    "sg:phone":"+1 941 484 3443",
    "sg:postcode":"34285",
    "sg:province":"FL",
    "sg:tags":[
        "refinishing",
        "furniture"
    ],
    "wof:name":"Artistic Furniture Restoration",
    "wof:placetype":"venue"
},
  "geometry": {"coordinates":[-82.434039,27.098775],"type":"Point"}
}