{
  "type": "Feature",
  "properties": {
    "iso:country":"US",
    "sg:address":"402 S North Lake Blvd",
    "sg:city":"Altamonte Spgs",
    "sg:classifiers":[
        {
            "category":"Professional",
            "subcategory":"Computer Services",
            "type":"Services"
        }
    ],
    "sg:phone":"+1 407 260 5218",
    "sg:postcode":"32701",
    "sg:province":"FL",
    "sg:tags":[
        "related",
        "internet"
    ],
    "wof:name":"General Internet Technologies",
    "wof:placetype":"venue"
},
  "geometry": {"coordinates":[-81.38519599999999,28.657662],"type":"Point"}
}