{
  "type": "Feature",
  "properties": {
    "addr:full":"1470 NW 107th Ave Ste U Doral FL 33172",
    "addr:housenumber":"1470",
    "addr:postcode":"33172",
    "addr:street":"Nw 107Th Ave Ste U",
    "iso:country":"US",
    "sg:address":"1470 NW 107th Ave Ste U",
    "sg:city":"Doral",
    "sg:classifiers":[
        {
            "category":"Professional",
            "subcategory":"Accounting & Tax Preparation",
            "type":"Services"
        }
    ],
    "sg:phone":"+1 305 477 3726",
    "sg:postcode":"33172",
    "sg:province":"FL",
    "sg:tags":[
        "accountant"
    ],
    "wof:name":"Pianelli & Associates Inc",
    "wof:placetype":"venue"
},
  "geometry": {"coordinates":[-80.36889600000001,25.7876],"type":"Point"}
}