{
  "type": "Feature",
  "properties": {
    "iso:country":"US",
    "sg:address":"713 SW 19th St",
    "sg:city":"Fort Lauderdale",
    "sg:classifiers":[
        {
            "category":"Professional",
            "subcategory":"Management & Consulting",
            "type":"Services"
        }
    ],
    "sg:phone":"+1 954 522 6139",
    "sg:postcode":"33315",
    "sg:province":"FL",
    "sg:tags":[
        "help",
        "supply"
    ],
    "wof:name":"Crew Quarters",
    "wof:placetype":"venue"
},
  "geometry": {"coordinates":[-80.149855,26.097325],"type":"Point"}
}