{
  "type": "Feature",
  "properties": {
    "addr:full":"3480 N Key Dr Fort Myers FL 33903",
    "addr:housenumber":"3480",
    "addr:postcode":"33903",
    "addr:street":"N Key Dr",
    "iso:country":"US",
    "sg:address":"3480 N Key Dr",
    "sg:city":"Fort Myers",
    "sg:classifiers":[
        {
            "category":"Real Estate",
            "subcategory":"Real Estate Operator",
            "type":"Services"
        },
        {
            "category":"Organizations",
            "subcategory":"Community Association",
            "type":"Services"
        }
    ],
    "sg:phone":"+1 239 997 1110",
    "sg:postcode":"33903",
    "sg:province":"FL",
    "sg:tags":[
        "condominium"
    ],
    "wof:name":"Schooner Bay Condo Association",
    "wof:placetype":"venue"
},
  "geometry": {"coordinates":[-81.888856,26.658546],"type":"Point"}
}