{
  "type": "Feature",
  "properties": {
    "iso:country":"US",
    "sg:address":"1019 Dr Martin Luther King Jr Blvd",
    "sg:city":"Seffner",
    "sg:classifiers":[
        {
            "category":"Wholesale",
            "subcategory":"Auto Parts",
            "type":"Manufacturing & Wholesale Goods"
        }
    ],
    "sg:phone":"+1 813 684 5559",
    "sg:postcode":"33584",
    "sg:province":"FL",
    "sg:tags":[
        "automobile",
        "supply"
    ],
    "wof:name":"Seffner Auto Repair",
    "wof:placetype":"venue"
},
  "geometry": {"coordinates":[-82.290279,27.981625],"type":"Point"}
}