{
  "type": "Feature",
  "properties": {
    "iso:country":"US",
    "sg:address":"5224 N Oceanshore Blvd",
    "sg:city":"Palm Coast",
    "sg:classifiers":[
        {
            "category":"Restaurant",
            "type":"Food & Drink"
        }
    ],
    "sg:phone":"+1 386 446 4337",
    "sg:postcode":"32137",
    "sg:province":"FL",
    "wof:name":"J T's Seafood Shack Inc",
    "wof:placetype":"venue"
},
  "geometry": {"coordinates":[-81.193906,29.5923],"type":"Point"}
}