{
  "type": "Feature",
  "properties": {
    "iso:country":"US",
    "sg:address":"9318 E Colonial Dr",
    "sg:city":"Orlando",
    "sg:classifiers":[
        {
            "category":"Recreation",
            "type":"Entertainment"
        }
    ],
    "sg:phone":"+1 407 208 9700",
    "sg:postcode":"32817",
    "sg:province":"FL",
    "sg:tags":[
        "martial",
        "arts",
        "instruction"
    ],
    "wof:name":"Bobby Dixons American Martial",
    "wof:placetype":"venue"
},
  "geometry": {"coordinates":[-81.258993,28.568282],"type":"Point"}
}