{
  "type": "Feature",
  "properties": {
    "iso:country":"US",
    "sg:address":"49 NW 12th Ave",
    "sg:city":"Miami",
    "sg:classifiers":[
        {
            "category":"Restaurant",
            "type":"Food & Drink"
        }
    ],
    "sg:phone":"+1 305 545 0403",
    "sg:postcode":"33128",
    "sg:province":"FL",
    "wof:name":"Diriangen Restaurant",
    "wof:placetype":"venue"
},
  "geometry": {"coordinates":[-80.214798,25.774099],"type":"Point"}
}