{
  "type": "Feature",
  "properties": {
    "iso:country":"US",
    "sg:address":"8204 103rd St",
    "sg:city":"Jacksonville",
    "sg:classifiers":[
        {
            "category":"Food & Beverages",
            "subcategory":"Groceries & Convenience Stores",
            "type":"Retail Goods"
        }
    ],
    "sg:phone":"+1 904 777 4339",
    "sg:postcode":"32210",
    "sg:province":"FL",
    "wof:name":"103 Express Mart",
    "wof:placetype":"venue"
},
  "geometry": {"coordinates":[-81.787616,30.247907],"type":"Point"}
}