{
  "type": "Feature",
  "properties": {
    "iso:country":"US",
    "sg:address":"1325 W Fletcher Ave",
    "sg:city":"Tampa",
    "sg:classifiers":[
        {
            "category":"Social Services",
            "type":"Services"
        }
    ],
    "sg:phone":"+1 813 907 9864",
    "sg:postcode":"33612",
    "sg:province":"FL",
    "wof:name":"Claudette R Krizek Lcsw",
    "wof:placetype":"venue"
},
  "geometry": {"coordinates":[-82.474006,28.069483],"type":"Point"}
}