{
  "type": "Feature",
  "properties": {
    "iso:country":"US",
    "sg:address":"3 Grove Isle Dr",
    "sg:city":"Miami",
    "sg:classifiers":[
        {
            "category":"Professional",
            "subcategory":"Business Services",
            "type":"Services"
        }
    ],
    "sg:phone":"+1 305 854 5576",
    "sg:postcode":"33133",
    "sg:province":"FL",
    "wof:name":"Sftg Associates International",
    "wof:placetype":"venue"
},
  "geometry": {"coordinates":[-80.22031800000001,25.735301],"type":"Point"}
}