{
  "type": "Feature",
  "properties": {
    "iso:country":"US",
    "sg:address":"262 Andalusia Ave",
    "sg:city":"Coral Gables",
    "sg:classifiers":[
        {
            "category":"Home & Garden",
            "subcategory":"Building Materials",
            "type":"Retail Goods"
        }
    ],
    "sg:phone":"+1 305 529 1441",
    "sg:postcode":"33134",
    "sg:province":"FL",
    "sg:tags":[
        "shutter"
    ],
    "wof:name":"All Miami Dade Hurricane",
    "wof:placetype":"venue"
},
  "geometry": {"coordinates":[-80.259501,25.748543],"type":"Point"}
}