{
  "type": "Feature",
  "properties": {
    "addr:full":"420 N Dixie Hwy Lantana FL 33462",
    "addr:housenumber":"420",
    "addr:postcode":"33462",
    "addr:street":"N Dixie Hwy",
    "iso:country":"US",
    "sg:address":"420 N Dixie Hwy",
    "sg:city":"Lantana",
    "sg:classifiers":[
        {
            "category":"Restaurant",
            "type":"Food & Drink"
        }
    ],
    "sg:phone":"+1 561 586 1554",
    "sg:postcode":"33462",
    "sg:province":"FL",
    "sg:tags":[
        "style",
        "family"
    ],
    "wof:name":"Brandy's Tropical Restaurant",
    "wof:placetype":"venue"
},
  "geometry": {"coordinates":[-80.051998,26.586842],"type":"Point"}
}