{
  "type": "Feature",
  "properties": {
    "addr:full":"38034 Medical Center Ave Zephyrhills FL 33540",
    "addr:housenumber":"38034",
    "addr:postcode":"33540",
    "addr:street":"Medical Center Ave",
    "iso:country":"US",
    "sg:address":"38034 Medical Center Ave",
    "sg:city":"Zephyrhills",
    "sg:classifiers":[
        {
            "category":"Health Services",
            "subcategory":"Doctor",
            "type":"Services"
        }
    ],
    "sg:phone":"+1 813 788 5531",
    "sg:postcode":"33540",
    "sg:province":"FL",
    "sg:tags":[
        "clinic",
        "medical"
    ],
    "wof:name":"South Florida Medical Group",
    "wof:placetype":"venue"
},
  "geometry": {"coordinates":[-82.18709699999999,28.262227],"type":"Point"}
}