{
  "type": "Feature",
  "properties": {
    "iso:country":"US",
    "sg:address":"19225 US Hwy 27",
    "sg:city":"Clermont",
    "sg:classifiers":[
        {
            "category":"Government",
            "subcategory":"Jail",
            "type":"Public Place"
        }
    ],
    "sg:phone":"+1 352 394 6146",
    "sg:postcode":"34715",
    "sg:province":"FL",
    "sg:tags":[
        "govt",
        "state",
        "institution"
    ],
    "wof:name":"Corrections Dept",
    "wof:placetype":"venue"
},
  "geometry": {"coordinates":[-81.76349500000001,28.626634],"type":"Point"}
}