{
  "type": "Feature",
  "properties": {
    "addr:full":"2631 W 77th Pl Hialeah FL 33016",
    "addr:housenumber":"2631",
    "addr:postcode":"33016",
    "addr:street":"W 77Th Pl",
    "iso:country":"US",
    "sg:address":"2631 W 77th Pl",
    "sg:city":"Hialeah",
    "sg:classifiers":[
        {
            "category":"Home & Garden",
            "subcategory":"Carpets & Floor Coverings",
            "type":"Retail Goods"
        }
    ],
    "sg:phone":"+1 305 823 0633",
    "sg:postcode":"33016",
    "sg:province":"FL",
    "sg:tags":[
        "dealer",
        "rug"
    ],
    "wof:name":"Carpet Enterprises",
    "wof:placetype":"venue"
},
  "geometry": {"coordinates":[-80.33670600000001,25.892837],"type":"Point"}
}