{
  "type": "Feature",
  "properties": {
    "iso:country":"US",
    "sg:address":"1018 Farwell Ave",
    "sg:city":"Orlando",
    "sg:classifiers":[
        {
            "category":"Insurance",
            "subcategory":"Insurance Agent",
            "type":"Services"
        }
    ],
    "sg:phone":"+1 407 282 5773",
    "sg:postcode":"32807",
    "sg:province":"FL",
    "wof:name":"William Phipps Insurance Agcy",
    "wof:placetype":"venue"
},
  "geometry": {"coordinates":[-81.29951800000001,28.559924],"type":"Point"}
}