{
  "type": "Feature",
  "properties": {
    "addr:full":"926 W Fletcher Ave Tampa FL 33612",
    "addr:housenumber":"926",
    "addr:postcode":"33612",
    "addr:street":"W Fletcher Ave",
    "iso:country":"US",
    "sg:address":"926 W Fletcher Ave",
    "sg:city":"Tampa",
    "sg:classifiers":[
        {
            "category":"Restaurant",
            "type":"Food & Drink"
        }
    ],
    "sg:menulink":"http://www.allmenus.com/fl/tampa/187764-mcdonalds/menu/",
    "sg:phone":"+1 813 960 9109",
    "sg:postcode":"33612",
    "sg:province":"FL",
    "sg:tags":[
        "burger",
        "american"
    ],
    "wof:name":"McDonald's",
    "wof:placetype":"venue"
},
  "geometry": {"coordinates":[-82.468611,28.068497],"type":"Point"}
}