{
  "type": "Feature",
  "properties": {
    "iso:country":"US",
    "sg:address":"7331 Collins Ave",
    "sg:city":"Miami Beach",
    "sg:classifiers":[
        {
            "category":"Shopping",
            "subcategory":"Shoes",
            "type":"Retail Goods"
        }
    ],
    "sg:phone":"+1 305 864 8282",
    "sg:postcode":"33141",
    "sg:province":"FL",
    "wof:name":"Classic Shoes",
    "wof:placetype":"venue"
},
  "geometry": {"coordinates":[-80.12078700000001,25.858072],"type":"Point"}
}