{
  "type": "Feature",
  "properties": {
    "iso:country":"US",
    "sg:address":"1918 Massachusetts Ave",
    "sg:city":"Englewood",
    "sg:classifiers":[
        {
            "category":"Travel",
            "subcategory":"Travel Agent",
            "type":"Entertainment"
        }
    ],
    "sg:phone":"+1 941 474 5690",
    "sg:postcode":"34224",
    "sg:province":"FL",
    "sg:tags":[
        "operator",
        "tour"
    ],
    "wof:name":"Cape Haze Outfitters",
    "wof:placetype":"venue"
},
  "geometry": {"coordinates":[-82.33126799999999,26.912855],"type":"Point"}
}