{
  "type": "Feature",
  "properties": {
    "iso:country":"US",
    "sg:address":"6214 Tamiami Trl N",
    "sg:city":"Naples",
    "sg:classifiers":[
        {
            "category":"Government",
            "subcategory":"Office",
            "type":"Public Place"
        }
    ],
    "sg:phone":"+1 239 592 9581",
    "sg:postcode":"34108",
    "sg:province":"FL",
    "sg:tags":[
        "federal",
        "human"
    ],
    "wof:name":"US Social Security Adm",
    "wof:placetype":"venue"
},
  "geometry": {"coordinates":[-81.800393,26.213416],"type":"Point"}
}