{
  "type": "Feature",
  "properties": {
    "addr:full":"1416 N Combee Rd Lakeland FL 33801",
    "addr:housenumber":"1416",
    "addr:postcode":"33801",
    "addr:street":"N Combee Rd",
    "iso:country":"US",
    "sg:address":"1416 N Combee Rd",
    "sg:city":"Lakeland",
    "sg:classifiers":[
        {
            "category":"Food & Beverages",
            "subcategory":"Groceries & Convenience Stores",
            "type":"Retail Goods"
        }
    ],
    "sg:phone":"+1 863 666 2586",
    "sg:postcode":"33801",
    "sg:province":"FL",
    "sg:tags":[
        "grocer"
    ],
    "wof:name":"M & J Foods Stores LLC",
    "wof:placetype":"venue"
},
  "geometry": {"coordinates":[-81.908126,28.062917],"type":"Point"}
}