{
  "type": "Feature",
  "properties": {
    "addr:full":"737 Valencia Ave Miami FL 33134",
    "addr:housenumber":"737",
    "addr:postcode":"33134",
    "addr:street":"Valencia Ave",
    "iso:country":"US",
    "sg:address":"737 Valencia Ave",
    "sg:city":"Miami",
    "sg:classifiers":[
        {
            "category":"Professional",
            "subcategory":"Business Services",
            "type":"Services"
        }
    ],
    "sg:phone":"+1 305 443 3441",
    "sg:postcode":"33134",
    "sg:province":"FL",
    "wof:name":"526 Catalonia Avenue Inc",
    "wof:placetype":"venue"
},
  "geometry": {"coordinates":[-80.268901,25.747161],"type":"Point"}
}