{
  "type": "Feature",
  "properties": {
    "iso:country":"US",
    "sg:address":"403 Sawgrass Corporate Pkwy",
    "sg:city":"Sunrise",
    "sg:classifiers":[
        {
            "category":"Health Services",
            "subcategory":"Clinic",
            "type":"Services"
        }
    ],
    "sg:phone":"+1 954 838 9405",
    "sg:postcode":"33325",
    "sg:province":"FL",
    "wof:name":"Costello's Health & Optimum",
    "wof:placetype":"venue"
},
  "geometry": {"coordinates":[-80.33021599999999,26.125715],"type":"Point"}
}