{
  "type": "Feature",
  "properties": {
    "addr:full":"819 Florida Ave St Cloud FL 34769",
    "addr:housenumber":"819",
    "addr:postcode":"34769",
    "addr:street":"Florida Ave",
    "iso:country":"US",
    "sg:address":"819 Florida Ave",
    "sg:city":"St Cloud",
    "sg:classifiers":[
        {
            "category":"Building & Trades",
            "subcategory":"Construction",
            "type":"Services"
        }
    ],
    "sg:phone":"+1 407 891 7111",
    "sg:postcode":"34769",
    "sg:province":"FL",
    "sg:tags":[
        "handyman"
    ],
    "wof:name":"Donald E Casselman Handyman",
    "wof:placetype":"venue"
},
  "geometry": {"coordinates":[-81.281087,28.24985],"type":"Point"}
}