{
  "type": "Feature",
  "properties": {
    "addr:full":"1773 SE 27th Loop St Ocala FL 34471",
    "addr:housenumber":"1773",
    "addr:postcode":"34471",
    "addr:street":"Se 27Th Loop St",
    "iso:country":"US",
    "sg:address":"1773 SE 27th Loop St",
    "sg:city":"Ocala",
    "sg:classifiers":[
        {
            "category":"Shopping",
            "subcategory":"Hobbies, Toys, & Games",
            "type":"Retail Goods"
        }
    ],
    "sg:phone":"+1 352 620 2649",
    "sg:postcode":"34471",
    "sg:province":"FL",
    "sg:tags":[
        "craft"
    ],
    "wof:name":"Creations By Virginia Hart",
    "wof:placetype":"venue"
},
  "geometry": {"coordinates":[-82.11642399999999,29.164002],"type":"Point"}
}