{
  "type": "Feature",
  "properties": {
    "addr:full":"4657 W Irlo Bronson Memorial Hwy Kissimmee FL 34746",
    "addr:housenumber":"4657",
    "addr:postcode":"34746",
    "addr:street":"W Irlo Bronson Memorial Hwy",
    "iso:country":"US",
    "sg:address":"4657 W Irlo Bronson Memorial Hwy",
    "sg:city":"Kissimmee",
    "sg:classifiers":[
        {
            "category":"Travel",
            "subcategory":"Hotels & Motels",
            "type":"Entertainment"
        }
    ],
    "sg:phone":"+1 407 809 4503",
    "sg:postcode":"34746",
    "sg:province":"FL",
    "sg:tags":[
        "lodging"
    ],
    "sg:website":"http://www.victoriainnmotel.com",
    "wof:name":"Victoria Inn Motel",
    "wof:placetype":"venue"
},
  "geometry": {"coordinates":[-81.46872,28.316215],"type":"Point"}
}