{
  "type": "Feature",
  "properties": {
    "iso:country":"US",
    "sg:address":"37 N Cleveland St",
    "sg:city":"Quincy",
    "sg:classifiers":[
        {
            "category":"Insurance",
            "subcategory":"Insurance Agent",
            "type":"Services"
        }
    ],
    "sg:phone":"+1 850 627 2523",
    "sg:postcode":"32351",
    "sg:province":"FL",
    "wof:name":"Insurance One",
    "wof:placetype":"venue"
},
  "geometry": {"coordinates":[-84.596068,30.587303],"type":"Point"}
}