{
  "type": "Feature",
  "properties": {
    "addr:full":"125 Industrial Loop W Orange Park FL 32073",
    "addr:housenumber":"125",
    "addr:postcode":"32073",
    "addr:street":"Industrial Loop W",
    "iso:country":"US",
    "sg:address":"125 Industrial Loop W",
    "sg:city":"Orange Park",
    "sg:classifiers":[
        {
            "category":"Retail",
            "subcategory":"Repair Shop",
            "type":"Services"
        }
    ],
    "sg:phone":"+1 904 910 5014",
    "sg:postcode":"32073",
    "sg:province":"FL",
    "sg:tags":[
        "welding"
    ],
    "sg:website":"www.marinewelding.com",
    "wof:name":"Specialized Marine Welding",
    "wof:placetype":"venue"
},
  "geometry": {"coordinates":[-81.71976100000001,30.180723],"type":"Point"}
}