{
  "type": "Feature",
  "properties": {
    "iso:country":"US",
    "sg:address":"4016 Henderson Blvd",
    "sg:city":"Tampa",
    "sg:classifiers":[
        {
            "category":"Banks & Credit Unions",
            "subcategory":"Financial Services",
            "type":"Services"
        }
    ],
    "sg:phone":"+1 813 287 8217",
    "sg:postcode":"33629",
    "sg:province":"FL",
    "sg:tags":[
        "company",
        "holding"
    ],
    "wof:name":"HMF Holding Corp",
    "wof:placetype":"venue"
},
  "geometry": {"coordinates":[-82.511723,27.928681],"type":"Point"}
}