{
  "type": "Feature",
  "properties": {
    "addr:full":"12290 SW 186 St Miami FL 33177",
    "addr:housenumber":"12290",
    "addr:postcode":"33177",
    "addr:street":"Sw 186 St",
    "iso:country":"US",
    "sg:address":"12290 SW 186 St",
    "sg:city":"Miami",
    "sg:classifiers":[
        {
            "category":"Personal",
            "subcategory":"Massage",
            "type":"Services"
        }
    ],
    "sg:phone":"+1 305 251 4463",
    "sg:postcode":"33177",
    "sg:province":"FL",
    "sg:website":"www.signature-massage.com",
    "wof:name":"Signature Massage Therapy",
    "wof:placetype":"venue"
},
  "geometry": {"coordinates":[-80.390855,25.594861],"type":"Point"}
}