{
  "type": "Feature",
  "properties": {
    "iso:country":"US",
    "sg:address":"1004 N Ponce de Leon Blvd",
    "sg:city":"St Augustine",
    "sg:classifiers":[
        {
            "category":"Real Estate",
            "subcategory":"Real Estate Agent",
            "type":"Services"
        }
    ],
    "sg:phone":"+1 904 829 0102",
    "sg:postcode":"32084",
    "sg:province":"FL",
    "wof:name":"Landmark Realty I",
    "wof:placetype":"venue"
},
  "geometry": {"coordinates":[-81.32013600000001,29.901472],"type":"Point"}
}