{
  "type": "Feature",
  "properties": {
    "iso:country":"US",
    "sg:address":"5334 Central Florida Pkwy",
    "sg:city":"Orlando",
    "sg:classifiers":[
        {
            "category":"Professional",
            "subcategory":"Printing & Photocopies",
            "type":"Services"
        }
    ],
    "sg:phone":"+1 407 238 9170",
    "sg:postcode":"32821",
    "sg:province":"FL",
    "sg:tags":[
        "duplicating",
        "copying"
    ],
    "wof:name":"Copy Graphic Ctr",
    "wof:placetype":"venue"
},
  "geometry": {"coordinates":[-81.449945,28.407814],"type":"Point"}
}