{
  "type": "Feature",
  "properties": {
    "iso:country":"US",
    "sg:address":"8120 Granada Blvd",
    "sg:city":"Orlando",
    "sg:classifiers":[
        {
            "category":"Landmark",
            "subcategory":"Tourist Information",
            "type":"Public Place"
        }
    ],
    "sg:phone":"+1 407 766 1565",
    "sg:postcode":"32836",
    "sg:province":"FL",
    "sg:tags":[
        "promoter",
        "tours-operators"
    ],
    "wof:name":"A Taxi & Tours",
    "wof:placetype":"venue"
},
  "geometry": {"coordinates":[-81.51225599999999,28.445558],"type":"Point"}
}