{
  "type": "Feature",
  "properties": {
    "iso:country":"US",
    "sg:address":"2110 Centerville Rd",
    "sg:city":"Tallahassee",
    "sg:classifiers":[
        {
            "category":"Professional",
            "subcategory":"Business Services",
            "type":"Services"
        },
        {
            "category":"Professional",
            "subcategory":"Computer Services",
            "type":"Services"
        }
    ],
    "sg:phone":"+1 850 877 2038",
    "sg:postcode":"32308",
    "sg:province":"FL",
    "sg:tags":[
        "information",
        "referral",
        "retrieval",
        "communication"
    ],
    "wof:name":"Medical Information Netwrk LLC",
    "wof:placetype":"venue"
},
  "geometry": {"coordinates":[-84.236276,30.478461],"type":"Point"}
}