{
  "type": "Feature",
  "properties": {
    "iso:country":"US",
    "sg:address":"1901 23rd St",
    "sg:city":"Vero Beach",
    "sg:classifiers":[
        {
            "category":"Organizations",
            "subcategory":"Religious Organization",
            "type":"Services"
        }
    ],
    "sg:phone":"+1 772 562 3633",
    "sg:postcode":"32960",
    "sg:province":"FL",
    "sg:tags":[
        "community",
        "church"
    ],
    "wof:name":"Community Church of Vero Beach",
    "wof:placetype":"venue"
},
  "geometry": {"coordinates":[-80.40487899999999,27.642149],"type":"Point"}
}