{
  "type": "Feature",
  "properties": {
    "iso:country":"US",
    "sg:address":"1331 Green Forest Ct",
    "sg:city":"Winter Garden",
    "sg:classifiers":[
        {
            "category":"Wholesale",
            "subcategory":"Hardware",
            "type":"Manufacturing & Wholesale Goods"
        }
    ],
    "sg:phone":"+1 407 656 2061",
    "sg:postcode":"34787",
    "sg:province":"FL",
    "sg:tags":[
        "fastener"
    ],
    "wof:name":"Fastenal Co",
    "wof:placetype":"venue"
},
  "geometry": {"coordinates":[-81.568766,28.547438],"type":"Point"}
}