{
  "type": "Feature",
  "properties": {
    "addr:full":"3007 Windy Hill Ln Tallahassee FL 32308",
    "addr:housenumber":"3007",
    "addr:postcode":"32308",
    "addr:street":"Windy Hill Ln",
    "iso:country":"US",
    "sg:address":"3007 Windy Hill Ln",
    "sg:city":"Tallahassee",
    "sg:classifiers":[
        {
            "category":"Shopping",
            "subcategory":"Gifts & Souvenirs",
            "type":"Retail Goods"
        }
    ],
    "sg:phone":"+1 850 385 4344",
    "sg:postcode":"32308",
    "sg:province":"FL",
    "wof:name":"Jaguar Tours",
    "wof:placetype":"venue"
},
  "geometry": {"coordinates":[-84.226558,30.497399],"type":"Point"}
}