{
  "type": "Feature",
  "properties": {
    "iso:country":"US",
    "sg:address":"495 W Perry St",
    "sg:city":"Englewood",
    "sg:classifiers":[
        {
            "category":"Building & Trades",
            "subcategory":"Construction",
            "type":"Services"
        }
    ],
    "sg:phone":"+1 941 544 6876",
    "sg:postcode":"34223",
    "sg:province":"FL",
    "sg:tags":[
        "painter"
    ],
    "wof:name":"Roy Dickinson Painting Svc",
    "wof:placetype":"venue"
},
  "geometry": {"coordinates":[-82.361265,26.963771],"type":"Point"}
}