{
  "type": "Feature",
  "properties": {
    "iso:country":"US",
    "sg:address":"6027 15th St E",
    "sg:city":"Bradenton",
    "sg:classifiers":[
        {
            "category":"Freight",
            "type":"Transportation"
        }
    ],
    "sg:phone":"+1 941 739 8234",
    "sg:postcode":"34203",
    "sg:province":"FL",
    "sg:tags":[
        "delivery"
    ],
    "wof:name":"Manatee Moving & Delivery Svc",
    "wof:placetype":"venue"
},
  "geometry": {"coordinates":[-82.546605,27.433063],"type":"Point"}
}