{
  "type": "Feature",
  "properties": {
    "iso:country":"US",
    "sg:address":"4216 Moncrief Rd",
    "sg:city":"Jacksonville",
    "sg:classifiers":[
        {
            "category":"Organizations",
            "subcategory":"Religious Organization",
            "type":"Services"
        }
    ],
    "sg:phone":"+1 904 764 5566",
    "sg:postcode":"32209",
    "sg:province":"FL",
    "sg:tags":[
        "church"
    ],
    "wof:name":"New Light Christian Church",
    "wof:placetype":"venue"
},
  "geometry": {"coordinates":[-81.679384,30.364557],"type":"Point"}
}