{
  "type": "Feature",
  "properties": {
    "addr:full":"9151 NW 24th Ct Sunrise FL 33322",
    "addr:housenumber":"9151",
    "addr:postcode":"33322",
    "addr:street":"Nw 24Th Ct",
    "iso:country":"US",
    "sg:address":"9151 NW 24th Ct",
    "sg:city":"Sunrise",
    "sg:classifiers":[
        {
            "category":"Professional",
            "subcategory":"Computer Services",
            "type":"Services"
        }
    ],
    "sg:phone":"+1 954 583 3311",
    "sg:postcode":"33322",
    "sg:province":"FL",
    "sg:tags":[
        "consultant",
        "designer"
    ],
    "wof:name":"Aztech Enterprises Inc",
    "wof:placetype":"venue"
},
  "geometry": {"coordinates":[-80.269009,26.154395],"type":"Point"}
}