{
  "type": "Feature",
  "properties": {
    "addr:full":"4325 S Atlantic Cir Fort Myers FL 33903",
    "addr:housenumber":"4325",
    "addr:postcode":"33903",
    "addr:street":"S Atlantic Cir",
    "iso:country":"US",
    "sg:address":"4325 S Atlantic Cir",
    "sg:city":"Fort Myers",
    "sg:classifiers":[
        {
            "category":"Professional",
            "subcategory":"Management & Consulting",
            "type":"Services"
        }
    ],
    "sg:phone":"+1 239 995 5081",
    "sg:postcode":"33903",
    "sg:province":"FL",
    "sg:tags":[
        "retail",
        "direct",
        "sales"
    ],
    "wof:name":"Jl Journey Inc",
    "wof:placetype":"venue"
},
  "geometry": {"coordinates":[-81.914584,26.641218],"type":"Point"}
}