{
  "type": "Feature",
  "properties": {
    "addr:full":"505 Palm St West Palm Beach FL 33401",
    "addr:housenumber":"505",
    "addr:postcode":"33401",
    "addr:street":"Palm St",
    "iso:country":"US",
    "sg:address":"505 Palm St",
    "sg:city":"West Palm Beach",
    "sg:classifiers":[
        {
            "category":"Government",
            "subcategory":"Office",
            "type":"Public Place"
        }
    ],
    "sg:phone":"+1 561 835 8878",
    "sg:postcode":"33401",
    "sg:province":"FL",
    "sg:tags":[
        "alcohol",
        "tobacco",
        "firearm"
    ],
    "wof:name":"ATF",
    "wof:placetype":"venue"
},
  "geometry": {"coordinates":[-80.056095,26.699414],"type":"Point"}
}