{
  "type": "Feature",
  "properties": {
    "iso:country":"US",
    "sg:address":"6051 W Irlo Bronsn Mmrl Hwy",
    "sg:city":"Kissimmee",
    "sg:classifiers":[
        {
            "category":"Travel",
            "subcategory":"Hotels & Motels",
            "type":"Entertainment"
        }
    ],
    "sg:phone":"+1 407 396 1748",
    "sg:postcode":"34747",
    "sg:province":"FL",
    "wof:name":"Hojo Inn Main Gate",
    "wof:placetype":"venue"
},
  "geometry": {"coordinates":[-81.52330000000001,28.332701],"type":"Point"}
}