{
  "type": "Feature",
  "properties": {
    "addr:full":"2221 Santa Barbara Blvd Cape Coral FL 33991",
    "addr:housenumber":"2221",
    "addr:postcode":"33991",
    "addr:street":"Santa Barbara Blvd",
    "iso:country":"US",
    "sg:address":"2221 Santa Barbara Blvd",
    "sg:city":"Cape Coral",
    "sg:classifiers":[
        {
            "category":"Shopping",
            "subcategory":"Gifts & Souvenirs",
            "type":"Retail Goods"
        }
    ],
    "sg:phone":"+1 239 242 6322",
    "sg:postcode":"33991",
    "sg:province":"FL",
    "sg:tags":[
        "shop"
    ],
    "wof:name":"Paper Dreams & More",
    "wof:placetype":"venue"
},
  "geometry": {"coordinates":[-81.974115,26.607705],"type":"Point"}
}