{
  "type": "Feature",
  "properties": {
    "addr:full":"4259 10th Ave N Lake Worth FL 33461",
    "addr:housenumber":"4259",
    "addr:postcode":"33461",
    "addr:street":"10Th Ave N",
    "iso:country":"US",
    "sg:address":"4259 10th Ave N",
    "sg:city":"Lake Worth",
    "sg:classifiers":[
        {
            "category":"Health Services",
            "subcategory":"Chiropractor",
            "type":"Services"
        },
        {
            "category":"Health Services",
            "subcategory":"Health Practitioner",
            "type":"Services"
        }
    ],
    "sg:phone":"+1 561 966 8800",
    "sg:postcode":"33461",
    "sg:province":"FL",
    "wof:name":"Florida Pain & Injury Centers",
    "wof:placetype":"venue"
},
  "geometry": {"coordinates":[-80.11228699999999,26.62954],"type":"Point"}
}