{
  "type": "Feature",
  "properties": {
    "iso:country":"US",
    "sg:address":"650 N University Dr",
    "sg:city":"Hollywood",
    "sg:classifiers":[
        {
            "category":"Shopping",
            "subcategory":"Stationery & Office Supplies",
            "type":"Retail Goods"
        }
    ],
    "sg:phone":"+1 954 433 2771",
    "sg:postcode":"33324",
    "sg:province":"FL",
    "wof:name":"Office Depot",
    "wof:placetype":"venue"
},
  "geometry": {"coordinates":[-80.248233,26.012313],"type":"Point"}
}