{
  "type": "Feature",
  "properties": {
    "addr:full":"428 N Jefferson St Perry FL 32347",
    "addr:housenumber":"428",
    "addr:postcode":"32347",
    "addr:street":"N Jefferson St",
    "iso:country":"US",
    "sg:address":"428 N Jefferson St",
    "sg:city":"Perry",
    "sg:classifiers":[
        {
            "category":"Government",
            "subcategory":"Office",
            "type":"Public Place"
        }
    ],
    "sg:phone":"+1 850 584 5627",
    "sg:postcode":"32347",
    "sg:province":"FL",
    "wof:name":"County Development Authority",
    "wof:placetype":"venue"
},
  "geometry": {"coordinates":[-83.58199500000001,30.120151],"type":"Point"}
}