{
  "type": "Feature",
  "properties": {
    "addr:full":"333 NW 79th St Miami FL 33150",
    "addr:housenumber":"333",
    "addr:postcode":"33150",
    "addr:street":"Nw 79Th St",
    "iso:country":"US",
    "sg:address":"333 NW 79th St",
    "sg:city":"Miami",
    "sg:classifiers":[
        {
            "category":"Autos & Motor Vehicles",
            "subcategory":"Automobile Sales",
            "type":"Retail Goods"
        }
    ],
    "sg:phone":"+1 305 756 0654",
    "sg:postcode":"33150",
    "sg:province":"FL",
    "sg:tags":[
        "car",
        "dealer"
    ],
    "wof:name":"Auto Collection USA",
    "wof:placetype":"venue"
},
  "geometry": {"coordinates":[-80.20214,25.847357],"type":"Point"}
}