{
  "type": "Feature",
  "properties": {
    "addr:full":"1601 Commerce Ave N St Petersburg FL 33716",
    "addr:housenumber":"1601",
    "addr:postcode":"33716",
    "addr:street":"Commerce Ave N",
    "iso:country":"US",
    "sg:address":"1601 Commerce Ave N",
    "sg:city":"St Petersburg",
    "sg:classifiers":[
        {
            "category":"Professional",
            "subcategory":"Engineering",
            "type":"Services"
        }
    ],
    "sg:phone":"+1 727 568 0366",
    "sg:postcode":"33716",
    "sg:province":"FL",
    "sg:tags":[
        "engineer"
    ],
    "sg:website":"www.atcassociates.com",
    "wof:name":"ATC Assoc Inc",
    "wof:placetype":"venue"
},
  "geometry": {"coordinates":[-82.65796,27.85935],"type":"Point"}
}