{
  "type": "Feature",
  "properties": {
    "addr:full":"2240 SW 34th St Fort Lauderdale FL 33312",
    "addr:housenumber":"2240",
    "addr:postcode":"33312",
    "addr:street":"Sw 34Th St",
    "iso:country":"US",
    "sg:address":"2240 SW 34th St",
    "sg:city":"Fort Lauderdale",
    "sg:classifiers":[
        {
            "category":"Manufacturing",
            "subcategory":"Metals",
            "type":"Manufacturing & Wholesale Goods"
        }
    ],
    "sg:phone":"+1 954 584 6400",
    "sg:postcode":"33312",
    "sg:province":"FL",
    "sg:tags":[
        "casting",
        "foundry",
        "aluminum",
        "mfg"
    ],
    "wof:name":"Gatto Furniture",
    "wof:placetype":"venue"
},
  "geometry": {"coordinates":[-80.172569,26.080283],"type":"Point"}
}