{
  "type": "Feature",
  "properties": {
    "iso:country":"US",
    "sg:address":"176 S Atlantic Ave",
    "sg:city":"Cocoa Beach",
    "sg:classifiers":[
        {
            "category":"Health Services",
            "subcategory":"Clinic",
            "type":"Services"
        }
    ],
    "sg:phone":"+1 321 784 5433",
    "sg:postcode":"32931",
    "sg:province":"FL",
    "sg:tags":[
        "wellness",
        "program"
    ],
    "wof:name":"New Lifestyle Inst & Wellness",
    "wof:placetype":"venue"
},
  "geometry": {"coordinates":[-80.609005,28.316229],"type":"Point"}
}