{
  "type": "Feature",
  "properties": {
    "addr:full":"7647 Clementine Way Orlando FL 32819",
    "addr:housenumber":"7647",
    "addr:postcode":"32819",
    "addr:street":"Clementine Way",
    "iso:country":"US",
    "sg:address":"7647 Clementine Way",
    "sg:city":"Orlando",
    "sg:classifiers":[
        {
            "category":"Professional",
            "subcategory":"Management & Consulting",
            "type":"Services"
        }
    ],
    "sg:phone":"+1 407 248 9036",
    "sg:postcode":"32819",
    "sg:province":"FL",
    "sg:tags":[
        "aviation",
        "consultant"
    ],
    "sg:website":"www.aviatdesign.com",
    "wof:name":"Aviat Design",
    "wof:placetype":"venue"
},
  "geometry": {"coordinates":[-81.491015,28.464274],"type":"Point"}
}