{
  "type": "Feature",
  "properties": {
    "iso:country":"US",
    "sg:address":"900 Juno Ocean Walk",
    "sg:city":"Juno Beach",
    "sg:classifiers":[
        {
            "category":"Building & Trades",
            "subcategory":"Construction",
            "type":"Services"
        }
    ],
    "sg:phone":"+1 561 627 4891",
    "sg:postcode":"33408",
    "sg:province":"FL",
    "sg:tags":[
        "screen",
        "enclosure"
    ],
    "wof:name":"ABC Aluminum & Environmental",
    "wof:placetype":"venue"
},
  "geometry": {"coordinates":[-80.061122,26.892793],"type":"Point"}
}