{
  "type": "Feature",
  "properties": {
    "addr:full":"10290 Rebel Rd Pensacola FL 32526",
    "addr:housenumber":"10290",
    "addr:postcode":"32526",
    "addr:street":"Rebel Rd",
    "iso:country":"US",
    "sg:address":"10290 Rebel Rd",
    "sg:city":"Pensacola",
    "sg:classifiers":[
        {
            "category":"Building & Trades",
            "subcategory":"Pest Control",
            "type":"Services"
        }
    ],
    "sg:phone":"+1 850 968 3223",
    "sg:postcode":"32526",
    "sg:province":"FL",
    "sg:tags":[
        "mothproofing"
    ],
    "wof:name":"Weed's Termite & Pest Control",
    "wof:placetype":"venue"
},
  "geometry": {"coordinates":[-87.388763,30.549207],"type":"Point"}
}