{
  "type": "Feature",
  "properties": {
    "iso:country":"US",
    "sg:address":"13150 Memorial Hwy",
    "sg:city":"Miami",
    "sg:classifiers":[
        {
            "category":"Building & Trades",
            "subcategory":"Cleaning & Sanitation",
            "type":"Services"
        }
    ],
    "sg:phone":"+1 305 899 7006",
    "sg:postcode":"33161",
    "sg:province":"FL",
    "sg:tags":[
        "janitor"
    ],
    "wof:name":"Max's Cleaning Svc",
    "wof:placetype":"venue"
},
  "geometry": {"coordinates":[-80.193989,25.897846],"type":"Point"}
}