{
  "type": "Feature",
  "properties": {
    "iso:country":"US",
    "sg:address":"1301 NW 89th Ct Ste 211",
    "sg:city":"Doral",
    "sg:classifiers":[
        {
            "category":"Food & Beverages",
            "subcategory":"Meat & Fish",
            "type":"Retail Goods"
        }
    ],
    "sg:phone":"+1 305 594 0467",
    "sg:postcode":"33172",
    "sg:province":"FL",
    "sg:tags":[
        "shop"
    ],
    "wof:name":"Packers Provision Company of Florida Inc",
    "wof:placetype":"venue"
},
  "geometry": {"coordinates":[-80.341103,25.785101],"type":"Point"}
}