{
  "type": "Feature",
  "properties": {
    "iso:country":"US",
    "sg:address":"11710 Plumosa Rd",
    "sg:city":"Tampa",
    "sg:classifiers":[
        {
            "category":"Insurance",
            "subcategory":"Insurance Agent",
            "type":"Services"
        }
    ],
    "sg:phone":"+1 813 960 9266",
    "sg:postcode":"33618",
    "sg:province":"FL",
    "wof:name":"Regional Insurance Mgt Group",
    "wof:placetype":"venue"
},
  "geometry": {"coordinates":[-82.49440800000001,28.056666],"type":"Point"}
}