{
  "type": "Feature",
  "properties": {
    "iso:country":"US",
    "sg:address":"1201 W Highway 50",
    "sg:city":"Clermont",
    "sg:classifiers":[
        {
            "category":"Banks & Credit Unions",
            "subcategory":"Atm",
            "type":"Services"
        },
        {
            "category":"Banks & Credit Unions",
            "subcategory":"Bank",
            "type":"Services"
        },
        {
            "category":"Banks & Credit Unions",
            "subcategory":"Financial Services",
            "type":"Services"
        }
    ],
    "sg:phone":"+1 352 394 8525",
    "sg:postcode":"34711",
    "sg:province":"FL",
    "sg:tags":[
        "commercial",
        "loan",
        "saving",
        "location",
        "mortgage"
    ],
    "sg:website":"http://www.rbccentura.com",
    "wof:name":"Rbc Bank",
    "wof:placetype":"venue"
},
  "geometry": {"coordinates":[-81.775604,28.552889],"type":"Point"}
}