{
  "type": "Feature",
  "properties": {
    "iso:country":"US",
    "sg:address":"1809 Laurel Oak Dr S",
    "sg:city":"Rockledge",
    "sg:classifiers":[
        {
            "category":"Organizations",
            "subcategory":"Non-profit Organization",
            "type":"Services"
        }
    ],
    "sg:phone":"+1 321 632 0744",
    "sg:postcode":"32955",
    "sg:province":"FL",
    "sg:tags":[
        "fund",
        "counselor",
        "raising"
    ],
    "wof:name":"Creative Fundraising Solutions",
    "wof:placetype":"venue"
},
  "geometry": {"coordinates":[-80.746056,28.318902],"type":"Point"}
}