{
  "type": "Feature",
  "properties": {
    "addr:full":"318 Herndon St Sebastian FL 32958",
    "addr:housenumber":"318",
    "addr:postcode":"32958",
    "addr:street":"Herndon St",
    "iso:country":"US",
    "sg:address":"318 Herndon St",
    "sg:city":"Sebastian",
    "sg:classifiers":[
        {
            "category":"Building & Trades",
            "subcategory":"Construction",
            "type":"Services"
        }
    ],
    "sg:phone":"+1 772 569 6604",
    "sg:postcode":"32958",
    "sg:province":"FL",
    "sg:tags":[
        "water",
        "pump",
        "well",
        "drilling",
        "contractor"
    ],
    "sg:website":"http://www.4welldrilling.com",
    "wof:name":"Bechtold Well Drilling Inc",
    "wof:placetype":"venue"
},
  "geometry": {"coordinates":[-80.488337,27.806339],"type":"Point"}
}