{
  "type": "Feature",
  "properties": {
    "iso:country":"US",
    "sg:address":"8505 Mills Dr",
    "sg:city":"Miami",
    "sg:classifiers":[
        {
            "category":"Education",
            "subcategory":"University",
            "type":"Public Place"
        }
    ],
    "sg:phone":"+1 305 279 4242",
    "sg:postcode":"33183",
    "sg:province":"FL",
    "sg:tags":[
        "college"
    ],
    "sg:website":"www.keiseruniversity.edu",
    "wof:name":"Keiser College",
    "wof:placetype":"venue"
},
  "geometry": {"coordinates":[-80.387001,25.6884],"type":"Point"}
}