{
  "type": "Feature",
  "properties": {
    "addr:full":"812 Halifax Dr Kissimmee FL 34758",
    "addr:housenumber":"812",
    "addr:postcode":"34758",
    "addr:street":"Halifax Dr",
    "iso:country":"US",
    "sg:address":"812 Halifax Dr",
    "sg:city":"Kissimmee",
    "sg:classifiers":[
        {
            "category":"Building & Trades",
            "subcategory":"Landscaping Services",
            "type":"Services"
        }
    ],
    "sg:phone":"+1 407 436 5511",
    "sg:postcode":"34758",
    "sg:province":"FL",
    "sg:tags":[
        "lawn",
        "maintenance",
        "grounds"
    ],
    "wof:name":"Jose Maldonado Lawn Svc",
    "wof:placetype":"venue"
},
  "geometry": {"coordinates":[-81.493351,28.174345],"type":"Point"}
}