{
  "type": "Feature",
  "properties": {
    "addr:full":"11030 SW 25th St Miami FL 33165",
    "addr:housenumber":"11030",
    "addr:postcode":"33165",
    "addr:street":"Sw 25Th St",
    "iso:country":"US",
    "sg:address":"11030 SW 25th St",
    "sg:city":"Miami",
    "sg:classifiers":[
        {
            "category":"Travel",
            "subcategory":"Travel Agent",
            "type":"Entertainment"
        }
    ],
    "sg:phone":"+1 305 266 8080",
    "sg:postcode":"33165",
    "sg:province":"FL",
    "sg:tags":[
        "agency",
        "bureau"
    ],
    "sg:website":"www.miamiworld.com",
    "wof:name":"Miami World Travel Inc",
    "wof:placetype":"venue"
},
  "geometry": {"coordinates":[-80.37419,25.745513],"type":"Point"}
}