{
  "type": "Feature",
  "properties": {
    "addr:full":"1500 Atlantic St Melbourne Beach FL 32951",
    "addr:housenumber":"1500",
    "addr:postcode":"32951",
    "addr:street":"Atlantic St",
    "iso:country":"US",
    "sg:address":"1500 Atlantic St",
    "sg:city":"Melbourne Beach",
    "sg:classifiers":[
        {
            "category":"Professional",
            "subcategory":"Engineering",
            "type":"Services"
        }
    ],
    "sg:phone":"+1 321 724 5430",
    "sg:postcode":"32951",
    "sg:province":"FL",
    "sg:tags":[
        "engineer"
    ],
    "wof:name":"Collins K Mc Kay Pe",
    "wof:placetype":"venue"
},
  "geometry": {"coordinates":[-80.554698,28.062552],"type":"Point"}
}