{
  "type": "Feature",
  "properties": {
    "iso:country":"US",
    "sg:address":"835 Shady Ln",
    "sg:city":"Bartow",
    "sg:classifiers":[
        {
            "category":"Building & Trades",
            "subcategory":"Landscaping Services",
            "type":"Services"
        }
    ],
    "sg:phone":"+1 863 533 1816",
    "sg:postcode":"33830",
    "sg:province":"FL",
    "wof:name":"Pierce Esta Adele",
    "wof:placetype":"venue"
},
  "geometry": {"coordinates":[-81.852717,27.906861],"type":"Point"}
}