{
  "type": "Feature",
  "properties": {
    "iso:country":"US",
    "sg:address":"715 Forest St",
    "sg:city":"Jacksonville",
    "sg:classifiers":[
        {
            "category":"Building & Trades",
            "subcategory":"Construction",
            "type":"Services"
        }
    ],
    "sg:phone":"+1 904 354 5820",
    "sg:postcode":"32204",
    "sg:province":"FL",
    "sg:tags":[
        "home",
        "improvement"
    ],
    "wof:name":"J E Crosby Co",
    "wof:placetype":"venue"
},
  "geometry": {"coordinates":[-81.675071,30.321805],"type":"Point"}
}