{
  "type": "Feature",
  "properties": {
    "addr:full":"133 W Leon Ln Cocoa Beach FL 32931",
    "addr:housenumber":"133",
    "addr:postcode":"32931",
    "addr:street":"W Leon Ln",
    "iso:country":"US",
    "sg:address":"133 W Leon Ln",
    "sg:city":"Cocoa Beach",
    "sg:classifiers":[
        {
            "category":"Freight",
            "type":"Transportation"
        }
    ],
    "sg:phone":"+1 321 868 1576",
    "sg:postcode":"32931",
    "sg:province":"FL",
    "wof:name":"CAM Transport",
    "wof:placetype":"venue"
},
  "geometry": {"coordinates":[-80.60875299999999,28.364528],"type":"Point"}
}