{
  "type": "Feature",
  "properties": {
    "addr:full":"4002 S Coolidge Ave Tampa FL 33611",
    "addr:housenumber":"4002",
    "addr:postcode":"33611",
    "addr:street":"S Coolidge Ave",
    "iso:country":"US",
    "sg:address":"4002 S Coolidge Ave",
    "sg:city":"Tampa",
    "sg:classifiers":[
        {
            "category":"Organizations",
            "subcategory":"Community Association",
            "type":"Services"
        }
    ],
    "sg:phone":"+1 813 837 9857",
    "sg:postcode":"33611",
    "sg:province":"FL",
    "sg:tags":[
        "club"
    ],
    "wof:name":"Boy's & Girl's Club Aquatic",
    "wof:placetype":"venue"
},
  "geometry": {"coordinates":[-82.517034,27.906593],"type":"Point"}
}