{
  "type": "Feature",
  "properties": {
    "iso:country":"US",
    "sg:address":"3831 Highway 4",
    "sg:city":"Jay",
    "sg:classifiers":[
        {
            "category":"Autos & Motor Vehicles",
            "subcategory":"Fuel & Gas Station",
            "type":"Retail Goods"
        },
        {
            "category":"Food & Beverages",
            "subcategory":"Groceries & Convenience Stores",
            "type":"Retail Goods"
        }
    ],
    "sg:phone":"+1 850 675 6840",
    "sg:postcode":"32565",
    "sg:province":"FL",
    "wof:name":"Exprezit Convenience Stores",
    "wof:placetype":"venue"
},
  "geometry": {"coordinates":[-87.12790800000001,30.952399],"type":"Point"}
}