{
  "type": "Feature",
  "properties": {
    "addr:full":"5440 70th Ave N Pinellas Park FL 33781",
    "addr:housenumber":"5440",
    "addr:postcode":"33781",
    "addr:street":"70Th Ave N",
    "iso:country":"US",
    "sg:address":"5440 70th Ave N",
    "sg:city":"Pinellas Park",
    "sg:classifiers":[
        {
            "category":"Manufacturing",
            "subcategory":"Metals",
            "type":"Manufacturing & Wholesale Goods"
        }
    ],
    "sg:phone":"+1 727 522 4653",
    "sg:postcode":"33781",
    "sg:province":"FL",
    "sg:tags":[
        "plating",
        "electroplating"
    ],
    "wof:name":"Superior Plating Inc",
    "wof:placetype":"venue"
},
  "geometry": {"coordinates":[-82.707975,27.835478],"type":"Point"}
}