{
  "type": "Feature",
  "properties": {
    "addr:full":"4367 Independence Ct Sarasota FL 34234",
    "addr:housenumber":"4367",
    "addr:postcode":"34234",
    "addr:street":"Independence Ct",
    "iso:country":"US",
    "sg:address":"4367 Independence Ct",
    "sg:city":"Sarasota",
    "sg:classifiers":[
        {
            "category":"Retail",
            "subcategory":"Photofinishing",
            "type":"Services"
        }
    ],
    "sg:phone":"+1 941 954 3100",
    "sg:postcode":"34234",
    "sg:province":"FL",
    "sg:tags":[
        "photo",
        "finishing"
    ],
    "wof:name":"Fot Booth Custom Framing",
    "wof:placetype":"venue"
},
  "geometry": {"coordinates":[-82.53731399999999,27.371955],"type":"Point"}
}