{
  "type": "Feature",
  "properties": {
    "addr:full":"3733 S Dixie Hwy West Palm Beach FL 33405",
    "addr:housenumber":"3733",
    "addr:postcode":"33405",
    "addr:street":"S Dixie Hwy",
    "iso:country":"US",
    "sg:address":"3733 S Dixie Hwy",
    "sg:city":"West Palm Beach",
    "sg:classifiers":[
        {
            "category":"Shopping",
            "subcategory":"Used Merchandise",
            "type":"Retail Goods"
        }
    ],
    "sg:phone":"+1 561 832 3611",
    "sg:postcode":"33405",
    "sg:province":"FL",
    "sg:tags":[
        "antique",
        "store"
    ],
    "sg:website":"www.galere.net",
    "wof:name":"Galere",
    "wof:placetype":"venue"
},
  "geometry": {"coordinates":[-80.05477399999999,26.677204],"type":"Point"}
}