{
  "type": "Feature",
  "properties": {
    "addr:full":"9151 N Davis Hwy Pensacola FL 32514",
    "addr:housenumber":"9151",
    "addr:postcode":"32514",
    "addr:street":"N Davis Hwy",
    "iso:country":"US",
    "sg:address":"9151 N Davis Hwy",
    "sg:city":"Pensacola",
    "sg:classifiers":[
        {
            "category":"Social Services",
            "subcategory":"Child Care",
            "type":"Services"
        }
    ],
    "sg:phone":"+1 850 476 9208",
    "sg:postcode":"32514",
    "sg:province":"FL",
    "wof:name":"Blessed Star Christian Prschl",
    "wof:placetype":"venue"
},
  "geometry": {"coordinates":[-87.20926900000001,30.52791],"type":"Point"}
}