{
  "type": "Feature",
  "properties": {
    "iso:country":"US",
    "sg:address":"4630 Delta Ave",
    "sg:city":"Jacksonville",
    "sg:classifiers":[
        {
            "category":"Professional",
            "type":"Services"
        }
    ],
    "sg:phone":"+1 904 387 4968",
    "sg:postcode":"32205",
    "sg:province":"FL",
    "sg:tags":[
        "establishment"
    ],
    "wof:name":"Content Design Group",
    "wof:placetype":"venue"
},
  "geometry": {"coordinates":[-81.725774,30.304552],"type":"Point"}
}