{
  "type": "Feature",
  "properties": {
    "iso:country":"US",
    "sg:address":"4440 Domestic Ave",
    "sg:city":"Naples",
    "sg:classifiers":[
        {
            "category":"Building & Trades",
            "subcategory":"Construction",
            "type":"Services"
        }
    ],
    "sg:phone":"+1 239 643 6610",
    "sg:postcode":"34104",
    "sg:province":"FL",
    "sg:tags":[
        "screen",
        "enclosure"
    ],
    "wof:name":"Faas Brothers Inc",
    "wof:placetype":"venue"
},
  "geometry": {"coordinates":[-81.757846,26.16245],"type":"Point"}
}