{
  "type": "Feature",
  "properties": {
    "iso:country":"US",
    "sg:address":"2225 SW 22nd St",
    "sg:city":"Coral Gables",
    "sg:classifiers":[
        {
            "category":"Autos & Motor Vehicles",
            "subcategory":"Auto Supplies",
            "type":"Retail Goods"
        }
    ],
    "sg:phone":"+1 305 856 5100",
    "sg:postcode":"33145",
    "sg:province":"FL",
    "sg:tags":[
        "automobile",
        "parts"
    ],
    "wof:name":"Rok Parts Of America Inc",
    "wof:placetype":"venue"
},
  "geometry": {"coordinates":[-80.231737,25.750627],"type":"Point"}
}