{
  "type": "Feature",
  "properties": {
    "addr:full":"815 State Hwy 206 E St Augustine FL 32086",
    "addr:housenumber":"815",
    "addr:postcode":"32086",
    "addr:street":"State Hwy 206 E St",
    "iso:country":"US",
    "sg:address":"815 State Hwy 206 E",
    "sg:city":"St Augustine",
    "sg:classifiers":[
        {
            "category":"Building & Trades",
            "subcategory":"Construction",
            "type":"Services"
        }
    ],
    "sg:phone":"+1 904 797 0201",
    "sg:postcode":"32086",
    "sg:province":"FL",
    "sg:tags":[
        "speculative",
        "general",
        "home",
        "contractor",
        "builder",
        "operative"
    ],
    "sg:website":"www.u-block.com",
    "wof:name":"Ruggeri Construction Co",
    "wof:placetype":"venue"
},
  "geometry": {"coordinates":[-81.287187,29.756771],"type":"Point"}
}