{
  "type": "Feature",
  "properties": {
    "iso:country":"US",
    "sg:address":"342 San Lorenzo Ave",
    "sg:city":"Coral Gables",
    "sg:classifiers":[
        {
            "category":"Shopping",
            "subcategory":"Clothing, Apparel, & Fashions",
            "type":"Retail Goods"
        }
    ],
    "sg:phone":"+1 305 441 2212",
    "sg:postcode":"33146",
    "sg:province":"FL",
    "wof:name":"Luca Luca",
    "wof:placetype":"venue"
},
  "geometry": {"coordinates":[-80.26172800000001,25.73204],"type":"Point"}
}