{
  "type": "Feature",
  "properties": {
    "iso:country":"US",
    "sg:address":"1115 Live Oak Ave",
    "sg:city":"Daytona Beach",
    "sg:classifiers":[
        {
            "category":"Travel",
            "subcategory":"Hotels & Motels",
            "type":"Entertainment"
        }
    ],
    "sg:phone":"+1 386 252 7428",
    "sg:postcode":"32114",
    "sg:province":"FL",
    "sg:tags":[
        "membership",
        "lodging"
    ],
    "wof:name":"Alpha Delta Kappa Sorority",
    "wof:placetype":"venue"
},
  "geometry": {"coordinates":[-81.044814,29.194813],"type":"Point"}
}