{
  "type": "Feature",
  "properties": {
    "iso:country":"US",
    "sg:address":"2310 61st St E",
    "sg:city":"Palmetto",
    "sg:classifiers":[
        {
            "category":"Building & Trades",
            "subcategory":"Construction",
            "type":"Services"
        }
    ],
    "sg:phone":"+1 941 745 2348",
    "sg:postcode":"34221",
    "sg:province":"FL",
    "sg:tags":[
        "roofing",
        "contractor"
    ],
    "wof:name":"D & R Roof Maintenance",
    "wof:placetype":"venue"
},
  "geometry": {"coordinates":[-82.540966,27.568149],"type":"Point"}
}