{
  "type": "Feature",
  "properties": {
    "iso:country":"US",
    "sg:address":"6858 NW 75th St",
    "sg:city":"Medley",
    "sg:classifiers":[
        {
            "category":"Wholesale",
            "subcategory":"Computers",
            "type":"Manufacturing & Wholesale Goods"
        },
        {
            "category":"Wholesale",
            "subcategory":"Durable Goods & Equipment",
            "type":"Manufacturing & Wholesale Goods"
        }
    ],
    "sg:phone":"+1 305 887 7791",
    "sg:postcode":"33166",
    "sg:province":"FL",
    "sg:tags":[
        "exporter",
        "electrical"
    ],
    "wof:name":"Amalgamated Trading Corp",
    "wof:placetype":"venue"
},
  "geometry": {"coordinates":[-80.307975,25.841557],"type":"Point"}
}