{
  "type": "Feature",
  "properties": {
    "iso:country":"US",
    "sg:address":"557 SW Fairway Ave",
    "sg:city":"Port St Lucie",
    "sg:classifiers":[
        {
            "category":"Shopping",
            "subcategory":"Clothing, Apparel, & Fashions",
            "type":"Retail Goods"
        }
    ],
    "sg:phone":"+1 772 621 4702",
    "sg:postcode":"34983",
    "sg:province":"FL",
    "wof:name":"Q B Fashions",
    "wof:placetype":"venue"
},
  "geometry": {"coordinates":[-80.36300900000001,27.296214],"type":"Point"}
}