{
  "type": "Feature",
  "properties": {
    "iso:country":"US",
    "sg:address":"2121 Ponce De Leon Blvd Ste 1050",
    "sg:city":"Coral Gables",
    "sg:classifiers":[
        {
            "category":"Professional",
            "subcategory":"Accounting & Tax Preparation",
            "type":"Services"
        }
    ],
    "sg:phone":"+1 305 444 2213",
    "sg:postcode":"33134",
    "sg:province":"FL",
    "sg:tags":[
        "accountant"
    ],
    "wof:name":"A & E Garcia PA",
    "wof:placetype":"venue"
},
  "geometry": {"coordinates":[-80.25797799999999,25.7533],"type":"Point"}
}