{
  "type": "Feature",
  "properties": {
    "addr:full":"428 Brickell St SE Palm Bay FL 32909",
    "addr:housenumber":"428",
    "addr:postcode":"32909",
    "addr:street":"Brickell St Se",
    "iso:country":"US",
    "sg:address":"428 Brickell St SE",
    "sg:city":"Palm Bay",
    "sg:classifiers":[
        {
            "category":"Real Estate",
            "subcategory":"Real Estate Agent",
            "type":"Services"
        }
    ],
    "sg:phone":"+1 321 676 0189",
    "sg:postcode":"32909",
    "sg:province":"FL",
    "wof:name":"Lawrence M Monari PA",
    "wof:placetype":"venue"
},
  "geometry": {"coordinates":[-80.66112800000001,27.98362],"type":"Point"}
}