{
  "type": "Feature",
  "properties": {
    "addr:full":"7305 SW 100th St Miami FL 33156",
    "addr:housenumber":"7305",
    "addr:postcode":"33156",
    "addr:street":"Sw 100Th St",
    "iso:country":"US",
    "sg:address":"7305 SW 100th St",
    "sg:city":"Miami",
    "sg:classifiers":[
        {
            "category":"Building & Trades",
            "subcategory":"Landscaping Services",
            "type":"Services"
        }
    ],
    "sg:phone":"+1 305 858 6307",
    "sg:postcode":"33156",
    "sg:province":"FL",
    "sg:tags":[
        "landscape",
        "contractor"
    ],
    "wof:name":"Grove Tree Service & Landscaping",
    "wof:placetype":"venue"
},
  "geometry": {"coordinates":[-80.31348,25.677668],"type":"Point"}
}