{
  "type": "Feature",
  "properties": {
    "addr:full":"18651 SW 39th Ct Hollywood FL 33029",
    "addr:housenumber":"18651",
    "addr:postcode":"33029",
    "addr:street":"Sw 39Th Ct",
    "iso:country":"US",
    "sg:address":"18651 SW 39th Ct",
    "sg:city":"Hollywood",
    "sg:classifiers":[
        {
            "category":"Banks & Credit Unions",
            "subcategory":"Bank",
            "type":"Services"
        }
    ],
    "sg:phone":"+1 954 432 8912",
    "sg:postcode":"33029",
    "sg:province":"FL",
    "sg:tags":[
        "mortgage"
    ],
    "wof:name":"Colonial First Mortgage Svcs",
    "wof:placetype":"venue"
},
  "geometry": {"coordinates":[-80.395991,25.971659],"type":"Point"}
}