{
  "type": "Feature",
  "properties": {
    "addr:full":"16524 NW 89th Pl Hialeah FL 33018",
    "addr:housenumber":"16524",
    "addr:postcode":"33018",
    "addr:street":"Nw 89Th Pl",
    "iso:country":"US",
    "sg:address":"16524 NW 89th Pl",
    "sg:city":"Hialeah",
    "sg:classifiers":[
        {
            "category":"Building & Trades",
            "subcategory":"Construction",
            "type":"Services"
        }
    ],
    "sg:phone":"+1 305 819 3561",
    "sg:postcode":"33018",
    "sg:province":"FL",
    "sg:tags":[
        "landscaping",
        "excavating",
        "demolition"
    ],
    "wof:name":"Gc Top Soil Corp",
    "wof:placetype":"venue"
},
  "geometry": {"coordinates":[-80.346861,25.923271],"type":"Point"}
}