{
  "type": "Feature",
  "properties": {
    "addr:full":"7305 W Flagler St Miami FL 33144",
    "addr:housenumber":"7305",
    "addr:postcode":"33144",
    "addr:street":"W Flagler St",
    "iso:country":"US",
    "sg:address":"7305 W Flagler St",
    "sg:city":"Miami",
    "sg:classifiers":[
        {
            "category":"Education",
            "subcategory":"Special Training",
            "type":"Public Place"
        }
    ],
    "sg:phone":"+1 305 476 0101",
    "sg:postcode":"33144",
    "sg:province":"FL",
    "sg:tags":[
        "school",
        "instruction",
        "traffic",
        "driving"
    ],
    "wof:name":"A A Auto Traffic School",
    "wof:placetype":"venue"
},
  "geometry": {"coordinates":[-80.313979,25.770194],"type":"Point"}
}