{
  "type": "Feature",
  "properties": {
    "iso:country":"US",
    "sg:address":"4928 Glamour Ln",
    "sg:city":"Orlando",
    "sg:classifiers":[
        {
            "category":"Building & Trades",
            "subcategory":"Construction",
            "type":"Services"
        },
        {
            "category":"Home & Garden",
            "subcategory":"Carpets & Floor Coverings",
            "type":"Retail Goods"
        }
    ],
    "sg:phone":"+1 407 754 3678",
    "sg:postcode":"32821",
    "sg:province":"FL",
    "sg:tags":[
        "flooring",
        "material",
        "specialty",
        "contractor",
        "tile-contractors"
    ],
    "wof:name":"Ranger Flooring",
    "wof:placetype":"venue"
},
  "geometry": {"coordinates":[-81.439562,28.418695],"type":"Point"}
}