{
  "type": "Feature",
  "properties": {
    "iso:country":"US",
    "sg:address":"2120 Duff Rd",
    "sg:city":"Lakeland",
    "sg:classifiers":[
        {
            "category":"Real Estate",
            "subcategory":"Real Estate Operator",
            "type":"Services"
        }
    ],
    "sg:phone":"+1 863 858 2868",
    "sg:postcode":"33810",
    "sg:province":"FL",
    "sg:tags":[
        "mobile",
        "home",
        "community"
    ],
    "wof:name":"Greenbriar Village",
    "wof:placetype":"venue"
},
  "geometry": {"coordinates":[-81.99126099999999,28.135431],"type":"Point"}
}