{
  "type": "Feature",
  "properties": {
    "iso:country":"US",
    "sg:address":"34521 Iris Blvd",
    "sg:city":"Zephyrhills",
    "sg:classifiers":[
        {
            "category":"Professional",
            "type":"Services"
        }
    ],
    "sg:phone":"+1 813 782 6590",
    "sg:postcode":"33541",
    "sg:province":"FL",
    "sg:tags":[
        "establishment"
    ],
    "wof:name":"Tippecanoe Village",
    "wof:placetype":"venue"
},
  "geometry": {"coordinates":[-82.245778,28.206721],"type":"Point"}
}