{
  "type": "Feature",
  "properties": {
    "iso:country":"US",
    "sg:address":"7615 N Kendall Dr",
    "sg:city":"Miami",
    "sg:classifiers":[
        {
            "category":"Shopping",
            "subcategory":"Shoes",
            "type":"Retail Goods"
        }
    ],
    "sg:phone":"+1 305 666 2817",
    "sg:postcode":"33156",
    "sg:province":"FL",
    "sg:tags":[
        "store"
    ],
    "sg:website":"www.naturalizer.com",
    "wof:name":"Naturalizer Shoe Store",
    "wof:placetype":"venue"
},
  "geometry": {"coordinates":[-80.318703,25.6884],"type":"Point"}
}