{
  "type": "Feature",
  "properties": {
    "addr:full":"1206 Baronwood Pl Brandon FL 33510",
    "addr:housenumber":"1206",
    "addr:postcode":"33510",
    "addr:street":"Baronwood Pl",
    "iso:country":"US",
    "sg:address":"1206 Baronwood Pl",
    "sg:city":"Brandon",
    "sg:classifiers":[
        {
            "category":"Arts & Performance",
            "subcategory":"Theater",
            "type":"Entertainment"
        }
    ],
    "sg:phone":"+1 813 689 6269",
    "sg:postcode":"33510",
    "sg:province":"FL",
    "sg:tags":[
        "producer"
    ],
    "wof:name":"Magic F/X",
    "wof:placetype":"venue"
},
  "geometry": {"coordinates":[-82.31816600000001,27.958764],"type":"Point"}
}