{
  "type": "Feature",
  "properties": {
    "iso:country":"US",
    "sg:address":"10915 Baymeadows Rd",
    "sg:city":"Jacksonville",
    "sg:classifiers":[
        {
            "category":"Shopping",
            "type":"Retail Goods"
        }
    ],
    "sg:phone":"+1 904 464 0400",
    "sg:postcode":"32256",
    "sg:province":"FL",
    "sg:tags":[
        "picture",
        "frame"
    ],
    "wof:name":"Fastframe",
    "wof:placetype":"venue"
},
  "geometry": {"coordinates":[-81.515379,30.215819],"type":"Point"}
}