{
  "type": "Feature",
  "properties": {
    "addr:full":"617 NE 125th St Miami FL 33161",
    "addr:housenumber":"617",
    "addr:postcode":"33161",
    "addr:street":"Ne 125Th St",
    "iso:country":"US",
    "sg:address":"617 NE 125th St",
    "sg:city":"Miami",
    "sg:classifiers":[
        {
            "category":"Home & Garden",
            "subcategory":"Building Materials",
            "type":"Retail Goods"
        }
    ],
    "sg:phone":"+1 305 891 2726",
    "sg:postcode":"33161",
    "sg:province":"FL",
    "sg:tags":[
        "shop",
        "glass",
        "window",
        "mirror",
        "plate"
    ],
    "wof:name":"Arco Glass & Mirror Corp",
    "wof:placetype":"venue"
},
  "geometry": {"coordinates":[-80.185776,25.890378],"type":"Point"}
}