{
  "type": "Feature",
  "properties": {
    "addr:full":"5815 S Orange Ave Orlando FL 32809",
    "addr:housenumber":"5815",
    "addr:postcode":"32809",
    "addr:street":"S Orange Ave",
    "iso:country":"US",
    "sg:address":"5815 S Orange Ave",
    "sg:city":"Orlando",
    "sg:classifiers":[
        {
            "category":"Shopping",
            "subcategory":"Clothing, Apparel, & Fashions",
            "type":"Retail Goods"
        }
    ],
    "sg:phone":"+1 407 851 6992",
    "sg:postcode":"32809",
    "sg:province":"FL",
    "wof:name":"Creative Wedding International",
    "wof:placetype":"venue"
},
  "geometry": {"coordinates":[-81.369415,28.473692],"type":"Point"}
}