{
  "type": "Feature",
  "properties": {
    "addr:full":"1896 Timarron Way Naples FL 34109",
    "addr:housenumber":"1896",
    "addr:postcode":"34109",
    "addr:street":"Timarron Way",
    "iso:country":"US",
    "sg:address":"1896 Timarron Way",
    "sg:city":"Naples",
    "sg:classifiers":[
        {
            "category":"Sports & Exercise",
            "subcategory":"Golf",
            "type":"Entertainment"
        }
    ],
    "sg:phone":"+1 239 596 4790",
    "sg:postcode":"34109",
    "sg:province":"FL",
    "sg:tags":[
        "course"
    ],
    "wof:name":"Golf Concept",
    "wof:placetype":"venue"
},
  "geometry": {"coordinates":[-81.773854,26.25731],"type":"Point"}
}