{
  "type": "Feature",
  "properties": {
    "iso:country":"US",
    "sg:address":"120 Niver St",
    "sg:city":"Daytona Beach",
    "sg:classifiers":[
        {
            "category":"Freight",
            "type":"Transportation"
        }
    ],
    "sg:phone":"+1 386 760 5638",
    "sg:postcode":"32127",
    "sg:province":"FL",
    "sg:tags":[
        "operator",
        "trucking"
    ],
    "wof:name":"Steven Hirsch Sr",
    "wof:placetype":"venue"
},
  "geometry": {"coordinates":[-80.976574,29.121648],"type":"Point"}
}