{
  "type": "Feature",
  "properties": {
    "addr:full":"7680 Matoaka Rd Sarasota FL 34243",
    "addr:postcode":"7680;34243",
    "addr:street":"Matoaka Rd",
    "iso:country":"US",
    "sg:address":"7680 Matoaka Rd",
    "sg:city":"Sarasota",
    "sg:classifiers":[
        {
            "category":"Insurance",
            "subcategory":"Insurance Agent",
            "type":"Services"
        }
    ],
    "sg:phone":"+1 941 359 6866",
    "sg:postcode":"34243",
    "sg:province":"FL",
    "sg:tags":[
        "accident"
    ],
    "wof:name":"Universal Health Care",
    "wof:placetype":"venue"
},
  "geometry": {"coordinates":[-82.529284,27.405797],"type":"Point"}
}