{
  "type": "Feature",
  "properties": {
    "addr:full":"1128 Royal Palm Beach Blvd West Palm Beach FL 33411",
    "addr:housenumber":"1128",
    "addr:postcode":"33411",
    "addr:street":"Royal Palm Beach Blvd",
    "iso:country":"US",
    "sg:address":"1128 Royal Palm Beach Blvd",
    "sg:city":"West Palm Beach",
    "sg:classifiers":[
        {
            "category":"Shopping",
            "type":"Retail Goods"
        }
    ],
    "sg:phone":"+1 561 792 0666",
    "sg:postcode":"33411",
    "sg:province":"FL",
    "sg:tags":[
        "alarm",
        "system",
        "sales"
    ],
    "wof:name":"ASAP",
    "wof:placetype":"venue"
},
  "geometry": {"coordinates":[-80.228859,26.711175],"type":"Point"}
}