{
  "type": "Feature",
  "properties": {
    "iso:country":"US",
    "sg:address":"12409 N Florida Ave",
    "sg:city":"Dunnellon",
    "sg:classifiers":[
        {
            "category":"Shopping",
            "subcategory":"Used Merchandise",
            "type":"Retail Goods"
        }
    ],
    "sg:phone":"+1 352 465 7957",
    "sg:postcode":"34434",
    "sg:province":"FL",
    "sg:tags":[
        "shop",
        "thrift"
    ],
    "wof:name":"Annie Johnson's This & That",
    "wof:placetype":"venue"
},
  "geometry": {"coordinates":[-82.465958,29.044646],"type":"Point"}
}