{
  "type": "Feature",
  "properties": {
    "addr:full":"4631 Brentwood Ave Jacksonville FL 32206",
    "addr:housenumber":"4631",
    "addr:postcode":"32206",
    "addr:street":"Brentwood Ave",
    "iso:country":"US",
    "sg:address":"4631 Brentwood Ave",
    "sg:city":"Jacksonville",
    "sg:classifiers":[
        {
            "category":"Communications",
            "subcategory":"Radio Station",
            "type":"Services"
        }
    ],
    "sg:phone":"+1 904 353 6933",
    "sg:postcode":"32206",
    "sg:province":"FL",
    "sg:tags":[
        "broadcast",
        "organization",
        "religious"
    ],
    "wof:name":"Sisters of Notre Dame Con",
    "wof:placetype":"venue"
},
  "geometry": {"coordinates":[-81.66211800000001,30.367966],"type":"Point"}
}