{
  "type": "Feature",
  "properties": {
    "addr:full":"731 Fenwick Dr Orlando FL 32825",
    "addr:housenumber":"731",
    "addr:postcode":"32825",
    "addr:street":"Fenwick Dr",
    "iso:country":"US",
    "sg:address":"731 Fenwick Dr",
    "sg:city":"Orlando",
    "sg:classifiers":[
        {
            "category":"Shopping",
            "subcategory":"Clothing, Apparel, & Fashions",
            "type":"Retail Goods"
        }
    ],
    "sg:phone":"+1 407 382 7072",
    "sg:postcode":"32825",
    "sg:province":"FL",
    "wof:name":"Capristan Fashion Design",
    "wof:placetype":"venue"
},
  "geometry": {"coordinates":[-81.279951,28.552384],"type":"Point"}
}