{
  "type": "Feature",
  "properties": {
    "iso:country":"US",
    "sg:address":"388 SW 12th Ave",
    "sg:city":"Deerfield Beach",
    "sg:classifiers":[
        {
            "category":"Professional",
            "subcategory":"Advertising",
            "type":"Services"
        }
    ],
    "sg:phone":"+1 954 360 9111",
    "sg:postcode":"33442",
    "sg:province":"FL",
    "sg:tags":[
        "agency"
    ],
    "wof:name":"Carrera and Partner Advg",
    "wof:placetype":"venue"
},
  "geometry": {"coordinates":[-80.119996,26.308525],"type":"Point"}
}