{
  "type": "Feature",
  "properties": {
    "addr:full":"8590 Hackney Prairie Rd Orlando FL 32818",
    "addr:housenumber":"8590",
    "addr:postcode":"32818",
    "addr:street":"Hackney Prairie Rd",
    "iso:country":"US",
    "sg:address":"8590 Hackney Prairie Rd",
    "sg:city":"Orlando",
    "sg:classifiers":[
        {
            "category":"Wholesale",
            "subcategory":"Machinery & Supplies",
            "type":"Manufacturing & Wholesale Goods"
        },
        {
            "category":"Food & Beverages",
            "subcategory":"Specialty",
            "type":"Retail Goods"
        }
    ],
    "sg:phone":"+1 407 291 7613",
    "sg:postcode":"32818",
    "sg:province":"FL",
    "sg:tags":[
        "water",
        "bulk",
        "company",
        "equipment"
    ],
    "wof:name":"Forest Oaks Water Treatment Pl",
    "wof:placetype":"venue"
},
  "geometry": {"coordinates":[-81.506508,28.599274],"type":"Point"}
}