{
  "type": "Feature",
  "properties": {
    "addr:full":"280 Wekiva Springs Rd Longwood FL 32779",
    "addr:housenumber":"280",
    "addr:postcode":"32779",
    "addr:street":"Wekiva Springs Rd",
    "iso:country":"US",
    "sg:address":"280 Wekiva Springs Rd",
    "sg:city":"Longwood",
    "sg:classifiers":[
        {
            "category":"Government",
            "subcategory":"Office",
            "type":"Public Place"
        }
    ],
    "sg:phone":"+1 407 629 6900",
    "sg:postcode":"32779",
    "sg:province":"FL",
    "sg:tags":[
        "entity"
    ],
    "wof:name":"Florida Gvrnmntal Utility Auth",
    "wof:placetype":"venue"
},
  "geometry": {"coordinates":[-81.41065999999999,28.693192],"type":"Point"}
}