{
  "type": "Feature",
  "properties": {
    "iso:country":"US",
    "sg:address":"325 Worth Ave",
    "sg:city":"Palm Beach",
    "sg:classifiers":[
        {
            "category":"Shopping",
            "subcategory":"Clothing, Apparel, & Fashions",
            "type":"Retail Goods"
        }
    ],
    "sg:phone":"+1 561 655 0203",
    "sg:postcode":"33480",
    "sg:province":"FL",
    "wof:name":"A U Cashmere Inc",
    "wof:placetype":"venue"
},
  "geometry": {"coordinates":[-80.038803,26.70087],"type":"Point"}
}