{
  "type": "Feature",
  "properties": {
    "iso:country":"US",
    "sg:address":"521 N Lecanto Hwy",
    "sg:city":"Lecanto",
    "sg:classifiers":[
        {
            "category":"Health Services",
            "subcategory":"Doctor",
            "type":"Services"
        },
        {
            "category":"Health Services",
            "subcategory":"Clinic",
            "type":"Services"
        }
    ],
    "sg:phone":"+1 352 746 0707",
    "sg:postcode":"34461",
    "sg:province":"FL",
    "sg:tags":[
        "physician",
        "oncology",
        "cancer",
        "surgeons",
        "hematology",
        "blood",
        "gynecologic",
        "treatment"
    ],
    "wof:name":"Cancer & Blood Disease Center",
    "wof:placetype":"venue"
},
  "geometry": {"coordinates":[-82.48823,28.868977],"type":"Point"}
}