{
  "type": "Feature",
  "properties": {
    "addr:full":"4255 Tamiami Trl N Naples FL 34103",
    "addr:housenumber":"4255",
    "addr:postcode":"34103",
    "addr:street":"Tamiami Trl N",
    "iso:country":"US",
    "sg:address":"4255 Tamiami Trl N",
    "sg:city":"Naples",
    "sg:classifiers":[
        {
            "category":"Bakery",
            "type":"Food & Drink"
        }
    ],
    "sg:menulink":"http://www.allmenus.com/fl/naples/101991-perkins-restaurant--bakery/menu/",
    "sg:phone":"+1 239 261 8009",
    "sg:postcode":"34103",
    "sg:province":"FL",
    "sg:tags":[
        "sandwich",
        "salad",
        "soup",
        "american",
        "pastry",
        "wrap"
    ],
    "wof:name":"Perkins Restaurant & Bakery",
    "wof:placetype":"venue"
},
  "geometry": {"coordinates":[-81.80035700000001,26.201159],"type":"Point"}
}