{
  "type": "Feature",
  "properties": {
    "addr:full":"213 E Polk Ave Auburndale FL 33823",
    "addr:housenumber":"213",
    "addr:postcode":"33823",
    "addr:street":"E Polk Ave",
    "iso:country":"US",
    "sg:address":"213 E Polk Ave",
    "sg:city":"Auburndale",
    "sg:classifiers":[
        {
            "category":"Freight",
            "type":"Transportation"
        }
    ],
    "sg:phone":"+1 863 318 3970",
    "sg:postcode":"33823",
    "sg:province":"FL",
    "sg:tags":[
        "operator",
        "trucking"
    ],
    "wof:name":"Sanchez Dml Inc",
    "wof:placetype":"venue"
},
  "geometry": {"coordinates":[-81.78125300000001,28.066347],"type":"Point"}
}