{
  "type": "Feature",
  "properties": {
    "addr:full":"3505 Cordgrass Dr Valrico FL 33596",
    "addr:housenumber":"3505",
    "addr:postcode":"33596",
    "addr:street":"Cordgrass Dr",
    "iso:country":"US",
    "sg:address":"3505 Cordgrass Dr",
    "sg:city":"Valrico",
    "sg:classifiers":[
        {
            "category":"Banks & Credit Unions",
            "subcategory":"Investment Brokerage",
            "type":"Services"
        }
    ],
    "sg:phone":"+1 813 657 5259",
    "sg:postcode":"33596",
    "sg:province":"FL",
    "sg:tags":[
        "advisory"
    ],
    "wof:name":"New Age Capital",
    "wof:placetype":"venue"
},
  "geometry": {"coordinates":[-82.20188400000001,27.891564],"type":"Point"}
}