{
  "type": "Feature",
  "properties": {
    "addr:full":"3111 N Surf Rd Hollywood FL 33019",
    "addr:housenumber":"3111",
    "addr:postcode":"33019",
    "addr:street":"N Surf Rd",
    "iso:country":"US",
    "sg:address":"3111 N Surf Rd",
    "sg:city":"Hollywood",
    "sg:classifiers":[
        {
            "category":"Bars & Pubs",
            "type":"Food & Drink"
        },
        {
            "category":"Restaurant",
            "type":"Food & Drink"
        },
        {
            "category":"Bars & Pubs",
            "subcategory":"Lounge",
            "type":"Food & Drink"
        }
    ],
    "sg:phone":"+1 954 927 5549",
    "sg:postcode":"33019",
    "sg:province":"FL",
    "sg:tags":[
        "brew",
        "seafood",
        "cocktail"
    ],
    "wof:name":"Oceans 11",
    "wof:placetype":"venue"
},
  "geometry": {"coordinates":[-80.114802,26.030378],"type":"Point"}
}