{
  "type": "Feature",
  "properties": {
    "iso:country":"US",
    "sg:address":"316 Patrick Cir",
    "sg:city":"Melbourne",
    "sg:classifiers":[
        {
            "category":"Building & Trades",
            "subcategory":"Construction",
            "type":"Services"
        }
    ],
    "sg:phone":"+1 321 727 1327",
    "sg:postcode":"32901",
    "sg:province":"FL",
    "sg:tags":[
        "contractor"
    ],
    "wof:name":"Jag Enterprises & Assoc Inc",
    "wof:placetype":"venue"
},
  "geometry": {"coordinates":[-80.627348,28.083902],"type":"Point"}
}