{
  "type": "Feature",
  "properties": {
    "iso:country":"US",
    "sg:address":"7600 Southland Blvd",
    "sg:city":"Orlando",
    "sg:classifiers":[
        {
            "category":"Professional",
            "subcategory":"Detective & Security Services",
            "type":"Services"
        }
    ],
    "sg:phone":"+1 407 208 9720",
    "sg:postcode":"32809",
    "sg:province":"FL",
    "sg:tags":[
        "car"
    ],
    "wof:name":"Tahir Bashar",
    "wof:placetype":"venue"
},
  "geometry": {"coordinates":[-81.40706900000001,28.452235],"type":"Point"}
}