{
  "type": "Feature",
  "properties": {
    "addr:full":"1101 SW 122nd Ave Miami FL 33184",
    "addr:housenumber":"1101",
    "addr:postcode":"33184",
    "addr:street":"Sw 122Nd Ave",
    "iso:country":"US",
    "sg:address":"1101 SW 122nd Ave",
    "sg:city":"Miami",
    "sg:classifiers":[
        {
            "category":"Communications",
            "type":"Services"
        }
    ],
    "sg:phone":"+1 305 207 4157",
    "sg:postcode":"33184",
    "sg:province":"FL",
    "sg:tags":[
        "communication"
    ],
    "wof:name":"Rdh Communications Inc",
    "wof:placetype":"venue"
},
  "geometry": {"coordinates":[-80.39258700000001,25.758159],"type":"Point"}
}