{
  "type": "Feature",
  "properties": {
    "addr:full":"3072 Cypress Gardens Rd Winter Haven FL 33884",
    "addr:housenumber":"3072",
    "addr:postcode":"33884",
    "addr:street":"Cypress Gardens Rd",
    "iso:country":"US",
    "sg:address":"3072 Cypress Gardens Rd",
    "sg:city":"Winter Haven",
    "sg:classifiers":[
        {
            "category":"Shopping",
            "subcategory":"Used Merchandise",
            "type":"Retail Goods"
        }
    ],
    "sg:phone":"+1 863 875 0344",
    "sg:postcode":"33884",
    "sg:province":"FL",
    "sg:tags":[
        "book",
        "rare",
        "dealer"
    ],
    "wof:name":"Book Rack",
    "wof:placetype":"venue"
},
  "geometry": {"coordinates":[-81.684321,27.996718],"type":"Point"}
}