{
  "type": "Feature",
  "properties": {
    "iso:country":"US",
    "sg:address":"41 Commerce St",
    "sg:city":"Apalachicola",
    "sg:classifiers":[
        {
            "category":"Real Estate",
            "subcategory":"Real Estate Services",
            "type":"Services"
        }
    ],
    "sg:phone":"+1 850 653 1300",
    "sg:postcode":"32320",
    "sg:province":"FL",
    "sg:tags":[
        "company",
        "title"
    ],
    "wof:name":"First Continental Title Svc",
    "wof:placetype":"venue"
},
  "geometry": {"coordinates":[-84.982828,29.726885],"type":"Point"}
}