{
  "type": "Feature",
  "properties": {
    "iso:country":"US",
    "sg:address":"1722 Sprucewood Ln",
    "sg:city":"Orlando",
    "sg:classifiers":[
        {
            "category":"Transit Center",
            "subcategory":"Freight",
            "type":"Transportation"
        },
        {
            "category":"Freight",
            "type":"Transportation"
        }
    ],
    "sg:phone":"+1 407 578 7898",
    "sg:postcode":"32818",
    "sg:province":"FL",
    "sg:tags":[
        "trucking-motor",
        "trucking"
    ],
    "wof:name":"Keaton Authur",
    "wof:placetype":"venue"
},
  "geometry": {"coordinates":[-81.47235499999999,28.561659],"type":"Point"}
}