{
  "type": "Feature",
  "properties": {
    "iso:country":"US",
    "sg:address":"3696 Tampa Rd",
    "sg:city":"Oldsmar",
    "sg:classifiers":[
        {
            "category":"Utilities",
            "subcategory":"Mobile Phone",
            "type":"Services"
        }
    ],
    "sg:phone":"+1 813 814 0560",
    "sg:postcode":"34677",
    "sg:province":"FL",
    "sg:tags":[
        "telephone",
        "cellular"
    ],
    "wof:name":"VIP Wireless",
    "wof:placetype":"venue"
},
  "geometry": {"coordinates":[-82.68147,28.044655],"type":"Point"}
}