{
  "type": "Feature",
  "properties": {
    "iso:country":"US",
    "sg:address":"1350 E Sunrise Blvd",
    "sg:city":"Fort Lauderdale",
    "sg:classifiers":[
        {
            "category":"Building & Trades",
            "subcategory":"Landscaping Services",
            "type":"Services"
        }
    ],
    "sg:phone":"+1 954 525 2911",
    "sg:postcode":"33304",
    "sg:province":"FL",
    "sg:tags":[
        "landscape"
    ],
    "wof:name":"Extreme Paradise",
    "wof:placetype":"venue"
},
  "geometry": {"coordinates":[-80.13010199999999,26.137088],"type":"Point"}
}