{
  "type": "Feature",
  "properties": {
    "addr:full":"1 Roscoe Blvd N Ponte Vedra Bch FL 32082",
    "addr:housenumber":"1",
    "addr:postcode":"32082",
    "addr:street":"Roscoe Blvd N",
    "iso:country":"US",
    "sg:address":"1 Roscoe Blvd N",
    "sg:city":"Ponte Vedra Bch",
    "sg:classifiers":[
        {
            "category":"Building & Trades",
            "subcategory":"Landscaping Services",
            "type":"Services"
        }
    ],
    "sg:phone":"+1 904 285 1479",
    "sg:postcode":"32082",
    "sg:province":"FL",
    "sg:tags":[
        "lawn",
        "landscape",
        "maintenance",
        "grounds"
    ],
    "wof:name":"Taylor Landscaping",
    "wof:placetype":"venue"
},
  "geometry": {"coordinates":[-81.401203,30.180391],"type":"Point"}
}