{
  "type": "Feature",
  "properties": {
    "iso:country":"US",
    "sg:address":"1870 Woodridge Ct",
    "sg:city":"Middleburg",
    "sg:classifiers":[
        {
            "category":"Freight",
            "type":"Transportation"
        }
    ],
    "sg:phone":"+1 904 291 1423",
    "sg:postcode":"32068",
    "sg:province":"FL",
    "sg:tags":[
        "operator",
        "local",
        "trucking"
    ],
    "wof:name":"Raymond Cotis Trucking",
    "wof:placetype":"venue"
},
  "geometry": {"coordinates":[-81.815608,30.084606],"type":"Point"}
}