{
  "type": "Feature",
  "properties": {
    "iso:country":"US",
    "sg:address":"1220 S Federal Hwy",
    "sg:city":"Fort Lauderdale",
    "sg:classifiers":[
        {
            "category":"Retail",
            "subcategory":"Car Wash",
            "type":"Services"
        }
    ],
    "sg:phone":"+1 954 522 7128",
    "sg:postcode":"33316",
    "sg:province":"FL",
    "sg:tags":[
        "carwash",
        "station",
        "gasoline"
    ],
    "wof:name":"Wash-A-Rama Inc",
    "wof:placetype":"venue"
},
  "geometry": {"coordinates":[-80.136814,26.107434],"type":"Point"}
}