{
  "type": "Feature",
  "properties": {
    "iso:country":"US",
    "sg:address":"897 Brunswick Ln",
    "sg:city":"Rockledge",
    "sg:classifiers":[
        {
            "category":"Shopping",
            "subcategory":"Stationery & Office Supplies",
            "type":"Retail Goods"
        }
    ],
    "sg:phone":"+1 321 631 3031",
    "sg:postcode":"32955",
    "sg:province":"FL",
    "sg:tags":[
        "equipment"
    ],
    "wof:name":"Barrett Office Machines",
    "wof:placetype":"venue"
},
  "geometry": {"coordinates":[-80.733284,28.316092],"type":"Point"}
}