{
  "type": "Feature",
  "properties": {
    "iso:country":"US",
    "sg:address":"137 Fellsmere Rd",
    "sg:city":"Sebastian",
    "sg:classifiers":[
        {
            "category":"Building & Trades",
            "subcategory":"Pest Control",
            "type":"Services"
        }
    ],
    "sg:phone":"+1 772 388 5136",
    "sg:postcode":"32958",
    "sg:province":"FL",
    "wof:name":"Sorrentinos Pest Control",
    "wof:placetype":"venue"
},
  "geometry": {"coordinates":[-80.4682,27.808049],"type":"Point"}
}