{
  "type": "Feature",
  "properties": {
    "addr:full":"118 Georgia Rd Lehigh Acres FL 33936",
    "addr:housenumber":"118",
    "addr:postcode":"33936",
    "addr:street":"Georgia Rd",
    "iso:country":"US",
    "sg:address":"118 Georgia Rd",
    "sg:city":"Lehigh Acres",
    "sg:classifiers":[
        {
            "category":"Professional",
            "subcategory":"Business Services",
            "type":"Services"
        }
    ],
    "sg:phone":"+1 239 303 9797",
    "sg:postcode":"33936",
    "sg:province":"FL",
    "wof:name":"Haag Enterprises Inc",
    "wof:placetype":"venue"
},
  "geometry": {"coordinates":[-81.64363899999999,26.605992],"type":"Point"}
}