{
  "type": "Feature",
  "properties": {
    "addr:full":"660 Royal Palm Beach Blvd Royal Palm Beach FL 33411",
    "addr:housenumber":"660",
    "addr:postcode":"33411",
    "addr:street":"Royal Palm Beach Blvd",
    "iso:country":"US",
    "sg:address":"660 Royal Palm Beach Blvd",
    "sg:city":"Royal Palm Beach",
    "sg:classifiers":[
        {
            "category":"Organizations",
            "subcategory":"Religious Organization",
            "type":"Services"
        }
    ],
    "sg:phone":"+1 561 793 1077",
    "sg:postcode":"33411",
    "sg:province":"FL",
    "sg:tags":[
        "church"
    ],
    "wof:name":"Royal Palm Covenant Church",
    "wof:placetype":"venue"
},
  "geometry": {"coordinates":[-80.230007,26.684596],"type":"Point"}
}