{
  "type": "Feature",
  "properties": {
    "addr:full":"2540 NE 77th Rd Wildwood FL 34785",
    "addr:housenumber":"2540",
    "addr:postcode":"34785",
    "addr:street":"Ne 77Th Rd",
    "iso:country":"US",
    "sg:address":"2540 NE 77th Rd",
    "sg:city":"Wildwood",
    "sg:classifiers":[
        {
            "category":"Building & Trades",
            "subcategory":"Construction",
            "type":"Services"
        }
    ],
    "sg:phone":"+1 352 748 2726",
    "sg:postcode":"34785",
    "sg:province":"FL",
    "sg:tags":[
        "contractor"
    ],
    "wof:name":"All Way Drywall Inc",
    "wof:placetype":"venue"
},
  "geometry": {"coordinates":[-82.060384,28.86917],"type":"Point"}
}