{
  "type": "Feature",
  "properties": {
    "addr:full":"815 Magnolia Dr West Palm Beach FL 33403",
    "addr:housenumber":"815",
    "addr:postcode":"33403",
    "addr:street":"Magnolia Dr",
    "iso:country":"US",
    "sg:address":"815 Magnolia Dr",
    "sg:city":"West Palm Beach",
    "sg:classifiers":[
        {
            "category":"Local Transit",
            "type":"Transportation"
        }
    ],
    "sg:phone":"+1 561 722 0927",
    "sg:postcode":"33403",
    "sg:province":"FL",
    "sg:tags":[
        "passenger"
    ],
    "wof:name":"South Florida Transit Inc",
    "wof:placetype":"venue"
},
  "geometry": {"coordinates":[-80.072112,26.804641],"type":"Point"}
}