{
  "type": "Feature",
  "properties": {
    "iso:country":"US",
    "sg:address":"7700 SW 100th St",
    "sg:city":"Miami",
    "sg:classifiers":[
        {
            "category":"Freight",
            "type":"Transportation"
        }
    ],
    "sg:phone":"+1 305 670 9501",
    "sg:postcode":"33156",
    "sg:province":"FL",
    "sg:tags":[
        "mover"
    ],
    "sg:website":"www.a1fargo.com",
    "wof:name":"A-1 Fargo Van & Storage Inc",
    "wof:placetype":"venue"
},
  "geometry": {"coordinates":[-80.320297,25.6777],"type":"Point"}
}