{
  "type": "Feature",
  "properties": {
    "iso:country":"US",
    "sg:address":"2770 NW 43rd St",
    "sg:city":"Gainesville",
    "sg:classifiers":[
        {
            "category":"Insurance",
            "subcategory":"Hazard Insurance",
            "type":"Services"
        }
    ],
    "sg:phone":"+1 352 367 1050",
    "sg:postcode":"32606",
    "sg:province":"FL",
    "wof:name":"Nantz Insurance Agency Inc",
    "wof:placetype":"venue"
},
  "geometry": {"coordinates":[-82.38896200000001,29.678449],"type":"Point"}
}