{
  "type": "Feature",
  "properties": {
    "addr:full":"4760 NW 102nd Ave Doral FL 33178",
    "addr:housenumber":"4760",
    "addr:postcode":"33178",
    "addr:street":"Nw 102Nd Ave",
    "iso:country":"US",
    "sg:address":"4760 NW 102nd Ave",
    "sg:city":"Doral",
    "sg:classifiers":[
        {
            "category":"Professional",
            "subcategory":"Computer Services",
            "type":"Services"
        }
    ],
    "sg:phone":"+1 305 597 1565",
    "sg:postcode":"33178",
    "sg:province":"FL",
    "sg:tags":[
        "consultant",
        "designer"
    ],
    "sg:website":"www.girint.com",
    "wof:name":"Gir International",
    "wof:placetype":"venue"
},
  "geometry": {"coordinates":[-80.359494,25.818168],"type":"Point"}
}