{
  "type": "Feature",
  "properties": {
    "iso:country":"US",
    "sg:address":"730 S Main St",
    "sg:city":"Wildwood",
    "sg:classifiers":[
        {
            "category":"Utilities",
            "subcategory":"Cable",
            "type":"Services"
        }
    ],
    "sg:phone":"+1 352 748 5064",
    "sg:postcode":"34785",
    "sg:province":"FL",
    "sg:tags":[
        "television"
    ],
    "wof:name":"Time Warner Cable",
    "wof:placetype":"venue"
},
  "geometry": {"coordinates":[-82.04534,28.851846],"type":"Point"}
}