{
  "type": "Feature",
  "properties": {
    "iso:country":"US",
    "sg:address":"11711 Okeechobee Blvd",
    "sg:city":"Royal Palm Beach",
    "sg:classifiers":[
        {
            "category":"Retail",
            "subcategory":"Repair Shop",
            "type":"Services"
        }
    ],
    "sg:phone":"+1 561 953 2110",
    "sg:postcode":"33411",
    "sg:province":"FL",
    "sg:tags":[
        "lock",
        "locksmith"
    ],
    "wof:name":"7 Day Anyplace Locksmith",
    "wof:placetype":"venue"
},
  "geometry": {"coordinates":[-80.210531,26.709515],"type":"Point"}
}