{
  "type": "Feature",
  "properties": {
    "iso:country":"US",
    "sg:address":"400 Lillian Dr",
    "sg:city":"Casselberry",
    "sg:classifiers":[
        {
            "category":"Professional",
            "subcategory":"Management & Consulting",
            "type":"Services"
        }
    ],
    "sg:phone":"+1 407 834 4555",
    "sg:postcode":"32730",
    "sg:province":"FL",
    "sg:tags":[
        "consultant"
    ],
    "wof:name":"Wilson Oyler Consulting Group",
    "wof:placetype":"venue"
},
  "geometry": {"coordinates":[-81.34930300000001,28.654874],"type":"Point"}
}