{
  "type": "Feature",
  "properties": {
    "iso:country":"US",
    "sg:address":"12720 NW 11th St",
    "sg:city":"Miami",
    "sg:classifiers":[
        {
            "category":"Wholesale",
            "subcategory":"Durable Goods & Equipment",
            "type":"Manufacturing & Wholesale Goods"
        }
    ],
    "sg:phone":"+1 305 229 9916",
    "sg:postcode":"33182",
    "sg:province":"FL",
    "sg:tags":[
        "exporter"
    ],
    "wof:name":"Multitrade Service & Invstmnt",
    "wof:placetype":"venue"
},
  "geometry": {"coordinates":[-80.401596,25.780994],"type":"Point"}
}