{
  "type": "Feature",
  "properties": {
    "iso:country":"US",
    "sg:address":"3480 SE 162nd Ct",
    "sg:city":"Ocklawaha",
    "sg:classifiers":[
        {
            "category":"Building & Trades",
            "subcategory":"Construction",
            "type":"Services"
        }
    ],
    "sg:phone":"+1 352 454 7915",
    "sg:postcode":"32179",
    "sg:province":"FL",
    "sg:tags":[
        "designer",
        "marine",
        "contractor"
    ],
    "wof:name":"Martin Butcher Marine Contr",
    "wof:placetype":"venue"
},
  "geometry": {"coordinates":[-81.884007,29.153353],"type":"Point"}
}