{
  "type": "Feature",
  "properties": {
    "iso:country":"US",
    "sg:address":"209 Maple St",
    "sg:city":"Wewahitchka",
    "sg:classifiers":[
        {
            "category":"Retail",
            "subcategory":"Repair Shop",
            "type":"Services"
        }
    ],
    "sg:phone":"+1 850 819 0774",
    "sg:postcode":"32465",
    "sg:province":"FL",
    "sg:tags":[
        "equipment",
        "conditioning",
        "air"
    ],
    "wof:name":"Allen Roberts AC & Refrigertn",
    "wof:placetype":"venue"
},
  "geometry": {"coordinates":[-85.18534699999999,30.107391],"type":"Point"}
}