{
  "type": "Feature",
  "properties": {
    "iso:country":"US",
    "sg:address":"717 Waterway Dr",
    "sg:city":"North Palm Beach",
    "sg:classifiers":[
        {
            "category":"Professional",
            "subcategory":"Accounting & Tax Preparation",
            "type":"Services"
        }
    ],
    "sg:phone":"+1 561 626 7644",
    "sg:postcode":"33408",
    "sg:province":"FL",
    "wof:name":"Charlene M Sholl CPA",
    "wof:placetype":"venue"
},
  "geometry": {"coordinates":[-80.069647,26.818435],"type":"Point"}
}