{
  "type": "Feature",
  "properties": {
    "iso:country":"US",
    "sg:address":"1114 John Sims Pkwy",
    "sg:city":"Niceville",
    "sg:classifiers":[
        {
            "category":"Building & Trades",
            "subcategory":"Plumbing",
            "type":"Services"
        }
    ],
    "sg:phone":"+1 850 678 7250",
    "sg:postcode":"32578",
    "sg:province":"FL",
    "sg:tags":[
        "contractor"
    ],
    "wof:name":"Five DS LLC",
    "wof:placetype":"venue"
},
  "geometry": {"coordinates":[-86.464082,30.515749],"type":"Point"}
}