{
  "type": "Feature",
  "properties": {
    "iso:country":"US",
    "sg:address":"2051 S US Hwy 1",
    "sg:city":"Fort Pierce",
    "sg:classifiers":[
        {
            "category":"Shopping",
            "subcategory":"Used Merchandise",
            "type":"Retail Goods"
        }
    ],
    "sg:phone":"+1 772 466 1797",
    "sg:postcode":"34950",
    "sg:province":"FL",
    "sg:tags":[
        "shop",
        "thrift"
    ],
    "wof:name":"Hospice Of The Treasure Coast",
    "wof:placetype":"venue"
},
  "geometry": {"coordinates":[-80.32600499999999,27.428795],"type":"Point"}
}