{
  "type": "Feature",
  "properties": {
    "iso:country":"US",
    "sg:address":"4635 N University Dr",
    "sg:city":"Pompano Beach",
    "sg:classifiers":[
        {
            "category":"Shopping",
            "subcategory":"Bicycles & Sporting Goods",
            "type":"Retail Goods"
        }
    ],
    "sg:phone":"+1 954 227 1900",
    "sg:postcode":"33067",
    "sg:province":"FL",
    "sg:tags":[
        "used",
        "merchandise"
    ],
    "wof:name":"Play It Again Sports",
    "wof:placetype":"venue"
},
  "geometry": {"coordinates":[-80.249951,26.289635],"type":"Point"}
}