{
  "type": "Feature",
  "properties": {
    "iso:country":"US",
    "sg:address":"5256 Berrien Ave",
    "sg:city":"Spring Hill",
    "sg:classifiers":[
        {
            "category":"Shopping",
            "subcategory":"Clothing, Apparel, & Fashions",
            "type":"Retail Goods"
        }
    ],
    "sg:phone":"+1 352 683 2153",
    "sg:postcode":"34608",
    "sg:province":"FL",
    "sg:tags":[
        "wear"
    ],
    "wof:name":"OH Baby Boutique",
    "wof:placetype":"venue"
},
  "geometry": {"coordinates":[-82.531023,28.508509],"type":"Point"}
}