{
  "type": "Feature",
  "properties": {
    "iso:country":"US",
    "sg:address":"2955 SW 78th Ave",
    "sg:city":"Miami",
    "sg:classifiers":[
        {
            "category":"Marine",
            "type":"Transportation"
        }
    ],
    "sg:phone":"+1 305 962 9008",
    "sg:postcode":"33155",
    "sg:province":"FL",
    "sg:tags":[
        "towing"
    ],
    "wof:name":"Exotic Yacht Works",
    "wof:placetype":"venue"
},
  "geometry": {"coordinates":[-80.321873,25.74172],"type":"Point"}
}