{
  "type": "Feature",
  "properties": {
    "addr:full":"1130 NW 54th St Fort Lauderdale FL 33309",
    "addr:housenumber":"1130",
    "addr:postcode":"33309",
    "addr:street":"Nw 54Th St",
    "iso:country":"US",
    "sg:address":"1130 NW 54th St",
    "sg:city":"Fort Lauderdale",
    "sg:classifiers":[
        {
            "category":"Building & Trades",
            "subcategory":"Construction",
            "type":"Services"
        }
    ],
    "sg:phone":"+1 954 771 8686",
    "sg:postcode":"33309",
    "sg:province":"FL",
    "sg:tags":[
        "contractor"
    ],
    "wof:name":"Aqua Tech Pool Renovation",
    "wof:placetype":"venue"
},
  "geometry": {"coordinates":[-80.158332,26.19341],"type":"Point"}
}