{
  "type": "Feature",
  "properties": {
    "iso:country":"US",
    "sg:address":"2642 21st Ave SE",
    "sg:city":"Ruskin",
    "sg:classifiers":[
        {
            "category":"Building & Trades",
            "subcategory":"Landscaping Services",
            "type":"Services"
        }
    ],
    "sg:phone":"+1 813 645 7150",
    "sg:postcode":"33570",
    "sg:province":"FL",
    "sg:tags":[
        "sod",
        "sodding"
    ],
    "wof:name":"Meza Sod & Landscaping",
    "wof:placetype":"venue"
},
  "geometry": {"coordinates":[-82.39932,27.694936],"type":"Point"}
}