{
  "type": "Feature",
  "properties": {
    "iso:country":"US",
    "sg:address":"1025 SW 3rd St",
    "sg:city":"Hallandale Beach",
    "sg:classifiers":[
        {
            "category":"Utilities",
            "subcategory":"Refuse",
            "type":"Services"
        }
    ],
    "sg:phone":"+1 954 454 5115",
    "sg:postcode":"33009",
    "sg:province":"FL",
    "sg:tags":[
        "garbage",
        "collection"
    ],
    "wof:name":"Debbie Dumpster",
    "wof:placetype":"venue"
},
  "geometry": {"coordinates":[-80.163324,25.981386],"type":"Point"}
}