{
  "type": "Feature",
  "properties": {
    "iso:country":"US",
    "sg:address":"304 3rd St S",
    "sg:city":"St Petersburg",
    "sg:classifiers":[
        {
            "category":"Retail",
            "subcategory":"Laundry & Dry Cleaning",
            "type":"Services"
        }
    ],
    "sg:phone":"+1 727 823 4648",
    "sg:postcode":"33701",
    "sg:province":"FL",
    "sg:tags":[
        "cleaners"
    ],
    "wof:name":"East Bay Dry Cleaner",
    "wof:placetype":"venue"
},
  "geometry": {"coordinates":[-82.637018,27.767957],"type":"Point"}
}