{
  "type": "Feature",
  "properties": {
    "addr:full":"72 Valencia St St Augustine FL 32084",
    "addr:housenumber":"72",
    "addr:postcode":"32084",
    "addr:street":"Valencia St",
    "iso:country":"US",
    "sg:address":"72 Valencia St",
    "sg:city":"St Augustine",
    "sg:classifiers":[
        {
            "category":"Health Services",
            "subcategory":"Doctor",
            "type":"Services"
        }
    ],
    "sg:phone":"+1 904 829 2032",
    "sg:postcode":"32084",
    "sg:province":"FL",
    "sg:tags":[
        "dentist"
    ],
    "wof:name":"Dental Concepts-St Augustine",
    "wof:placetype":"venue"
},
  "geometry": {"coordinates":[-81.319436,29.893295],"type":"Point"}
}