{
  "type": "Feature",
  "properties": {
    "addr:full":"754 Malabar Rd SE Palm Bay FL 32907",
    "addr:housenumber":"754",
    "addr:postcode":"32907",
    "addr:street":"Malabar Rd Se",
    "iso:country":"US",
    "sg:address":"754 Malabar Rd SE",
    "sg:city":"Palm Bay",
    "sg:classifiers":[
        {
            "category":"Real Estate",
            "subcategory":"Real Estate Agent",
            "type":"Services"
        }
    ],
    "sg:phone":"+1 321 723 5609",
    "sg:postcode":"32907",
    "sg:province":"FL",
    "wof:name":"Teresa M Suarez Realtor",
    "wof:placetype":"venue"
},
  "geometry": {"coordinates":[-80.651669,27.998721],"type":"Point"}
}