{
  "type": "Feature",
  "properties": {
    "addr:full":"2020 W 26th St Jacksonville FL 32209",
    "addr:housenumber":"2020",
    "addr:postcode":"32209",
    "addr:street":"W 26Th St",
    "iso:country":"US",
    "sg:address":"2020 W 26th St",
    "sg:city":"Jacksonville",
    "sg:classifiers":[
        {
            "category":"Shopping",
            "subcategory":"Crafts & Fabrics",
            "type":"Retail Goods"
        }
    ],
    "sg:phone":"+1 904 798 3581",
    "sg:postcode":"32209",
    "sg:province":"FL",
    "wof:name":"Sara Lee Knit Products",
    "wof:placetype":"venue"
},
  "geometry": {"coordinates":[-81.694776,30.359629],"type":"Point"}
}