{
  "type": "Feature",
  "properties": {
    "iso:country":"US",
    "sg:address":"3514 Lake Worth Rd",
    "sg:city":"Lake Worth",
    "sg:classifiers":[
        {
            "category":"Shopping",
            "subcategory":"Tobacco",
            "type":"Retail Goods"
        }
    ],
    "sg:phone":"+1 561 357 7474",
    "sg:postcode":"33461",
    "sg:province":"FL",
    "sg:tags":[
        "product"
    ],
    "wof:name":"Purple Haze Inc",
    "wof:placetype":"venue"
},
  "geometry": {"coordinates":[-80.095354,26.617781],"type":"Point"}
}