{
  "type": "Feature",
  "properties": {
    "addr:full":"3522 W 71 Ter Hialeah FL 33018",
    "addr:housenumber":"3522",
    "addr:postcode":"33018",
    "addr:street":"W 71 Ter",
    "iso:country":"US",
    "sg:address":"3522 W 71 Ter",
    "sg:city":"Hialeah",
    "sg:classifiers":[
        {
            "category":"Freight",
            "type":"Transportation"
        }
    ],
    "sg:phone":"+1 305 828 0120",
    "sg:postcode":"33018",
    "sg:province":"FL",
    "sg:tags":[
        "operator",
        "local",
        "trucking"
    ],
    "wof:name":"Oma Trucking Inc",
    "wof:placetype":"venue"
},
  "geometry": {"coordinates":[-80.354223,25.88615],"type":"Point"}
}