{
  "type": "Feature",
  "properties": {
    "iso:country":"US",
    "sg:address":"1303 N Cruise Blvd",
    "sg:city":"Miami",
    "sg:phone":"+1 305 350 4004",
    "sg:postcode":"33132",
    "sg:province":"FL",
    "wof:name":"Bags Inc",
    "wof:placetype":"venue"
},
  "geometry": {"coordinates":[-80.171936,25.776593],"type":"Point"}
}