{
  "type": "Feature",
  "properties": {
    "addr:full":"4414 N Combee Rd Lakeland FL 33805",
    "addr:housenumber":"4414",
    "addr:postcode":"33805",
    "addr:street":"N Combee Rd",
    "iso:country":"US",
    "sg:address":"4414 N Combee Rd",
    "sg:city":"Lakeland",
    "sg:classifiers":[
        {
            "category":"Farming",
            "subcategory":"Nursery",
            "type":"Manufacturing & Wholesale Goods"
        }
    ],
    "sg:phone":"+1 863 606 0317",
    "sg:postcode":"33805",
    "sg:province":"FL",
    "sg:tags":[
        "ornamental"
    ],
    "wof:name":"Nursery Depot",
    "wof:placetype":"venue"
},
  "geometry": {"coordinates":[-81.90566699999999,28.094671],"type":"Point"}
}