{
  "type": "Feature",
  "properties": {
    "iso:country":"US",
    "sg:address":"10700 SW 60th St",
    "sg:city":"Miami",
    "sg:classifiers":[
        {
            "category":"Government",
            "subcategory":"Post Office",
            "type":"Public Place"
        }
    ],
    "sg:phone":"+1 305 274 4066",
    "sg:postcode":"33173",
    "sg:province":"FL",
    "sg:tags":[
        "delivery",
        "courier"
    ],
    "wof:name":"Secure Express Courier Se",
    "wof:placetype":"venue"
},
  "geometry": {"coordinates":[-80.366722,25.71196],"type":"Point"}
}