{
  "type": "Feature",
  "properties": {
    "iso:country":"US",
    "sg:address":"243 N Florida Ave",
    "sg:city":"Lakeland",
    "sg:classifiers":[
        {
            "category":"Shopping",
            "subcategory":"Used Merchandise",
            "type":"Retail Goods"
        }
    ],
    "sg:phone":"+1 863 687 0298",
    "sg:postcode":"33801",
    "sg:province":"FL",
    "sg:tags":[
        "store"
    ],
    "wof:name":"Susina Antique",
    "wof:placetype":"venue"
},
  "geometry": {"coordinates":[-81.95717500000001,28.045597],"type":"Point"}
}