{
  "type": "Feature",
  "properties": {
    "addr:full":"8153 Citrus Park Town Center Mall Tampa FL 33625",
    "addr:housenumber":"8153",
    "addr:postcode":"33625",
    "addr:street":"Citrus Park Town;Mall",
    "iso:country":"US",
    "sg:address":"8153 Citrus Park Town Center Mall",
    "sg:city":"Tampa",
    "sg:classifiers":[
        {
            "category":"Personal",
            "subcategory":"Beauty Salon",
            "type":"Services"
        },
        {
            "category":"Personal",
            "subcategory":"Barber",
            "type":"Services"
        }
    ],
    "sg:phone":"+1 813 926 6556",
    "sg:postcode":"33625",
    "sg:province":"FL",
    "sg:tags":[
        "hair",
        "stylist"
    ],
    "sg:website":"http://www.mastercuts.com",
    "wof:name":"MasterCuts",
    "wof:placetype":"venue"
},
  "geometry": {"coordinates":[-82.576509,28.066928],"type":"Point"}
}