{
  "type": "Feature",
  "properties": {
    "iso:country":"US",
    "sg:address":"312 S Old Dixie Hwy",
    "sg:city":"Jupiter",
    "sg:classifiers":[
        {
            "category":"Wholesale",
            "subcategory":"Photographic Equipment",
            "type":"Manufacturing & Wholesale Goods"
        }
    ],
    "sg:phone":"+1 561 743 8600",
    "sg:postcode":"33458",
    "sg:province":"FL",
    "sg:tags":[
        "audio"
    ],
    "wof:name":"Alto Technologies Corp",
    "wof:placetype":"venue"
},
  "geometry": {"coordinates":[-80.09436599999999,26.930416],"type":"Point"}
}