{
  "type": "Feature",
  "properties": {
    "iso:country":"US",
    "sg:address":"209 Jasper St",
    "sg:city":"Bushnell",
    "sg:classifiers":[
        {
            "category":"Building & Trades",
            "subcategory":"Plumbing",
            "type":"Services"
        }
    ],
    "sg:phone":"+1 352 793 4481",
    "sg:postcode":"33513",
    "sg:province":"FL",
    "sg:tags":[
        "electrical",
        "contractor"
    ],
    "wof:name":"Dillard B Boyatt",
    "wof:placetype":"venue"
},
  "geometry": {"coordinates":[-82.100272,28.664794],"type":"Point"}
}