{
  "type": "Feature",
  "properties": {
    "iso:country":"US",
    "sg:address":"3125 Drane Field Rd",
    "sg:city":"Lakeland",
    "sg:classifiers":[
        {
            "category":"Manufacturing",
            "subcategory":"Tools & Machinery",
            "type":"Manufacturing & Wholesale Goods"
        }
    ],
    "sg:phone":"+1 863 619 8100",
    "sg:postcode":"33811",
    "sg:province":"FL",
    "sg:tags":[
        "dental",
        "mfg",
        "supply"
    ],
    "wof:name":"Omnia Incorporated",
    "wof:placetype":"venue"
},
  "geometry": {"coordinates":[-82.00338000000001,27.996712],"type":"Point"}
}