{
  "type": "Feature",
  "properties": {
    "addr:full":"1645 NW 107th Ave Miami FL 33172",
    "addr:housenumber":"1645",
    "addr:postcode":"33172",
    "addr:street":"Nw 107Th Ave",
    "iso:country":"US",
    "sg:address":"1645 NW 107th Ave",
    "sg:city":"Miami",
    "sg:classifiers":[
        {
            "category":"Shopping",
            "subcategory":"Hobbies, Toys, & Games",
            "type":"Retail Goods"
        }
    ],
    "sg:phone":"+1 305 593 1517",
    "sg:postcode":"33172",
    "sg:province":"FL",
    "sg:tags":[
        "toy",
        "store"
    ],
    "sg:website":"www.toysrus.com",
    "wof:name":"Toys R Us",
    "wof:placetype":"venue"
},
  "geometry": {"coordinates":[-80.368509,25.790058],"type":"Point"}
}