{
  "type": "Feature",
  "properties": {
    "iso:country":"US",
    "sg:address":"15041 Dunbarton Pl",
    "sg:city":"Hialeah",
    "sg:classifiers":[
        {
            "category":"Building & Trades",
            "subcategory":"Equipment Rental",
            "type":"Services"
        }
    ],
    "sg:phone":"+1 305 888 7667",
    "sg:postcode":"33016",
    "sg:province":"FL",
    "sg:tags":[
        "party",
        "supply"
    ],
    "wof:name":"Party Works Of Miami Inc",
    "wof:placetype":"venue"
},
  "geometry": {"coordinates":[-80.340069,25.910054],"type":"Point"}
}