{
  "type": "Feature",
  "properties": {
    "iso:country":"US",
    "sg:address":"515 W Jefferson St",
    "sg:city":"Quincy",
    "sg:classifiers":[
        {
            "category":"Government",
            "subcategory":"Office",
            "type":"Public Place"
        }
    ],
    "sg:phone":"+1 850 875 8230",
    "sg:postcode":"32351",
    "sg:province":"FL",
    "sg:tags":[
        "county",
        "resource"
    ],
    "wof:name":"Gadsden Co Human Svc",
    "wof:placetype":"venue"
},
  "geometry": {"coordinates":[-84.58273800000001,30.588042],"type":"Point"}
}