{
  "type": "Feature",
  "properties": {
    "iso:country":"US",
    "sg:address":"120 Chipola Rd",
    "sg:city":"Cocoa Beach",
    "sg:classifiers":[
        {
            "category":"Bars & Pubs",
            "type":"Food & Drink"
        }
    ],
    "sg:phone":"+1 321 799 2171",
    "sg:postcode":"32931",
    "sg:province":"FL",
    "sg:tags":[
        "drinking"
    ],
    "wof:name":"Nanncys Guys & Dolls",
    "wof:placetype":"venue"
},
  "geometry": {"coordinates":[-80.615852,28.316086],"type":"Point"}
}