{
  "type": "Feature",
  "properties": {
    "addr:full":"54 Camelot Ridge Dr Brandon FL 33511",
    "addr:housenumber":"54",
    "addr:postcode":"33511",
    "addr:street":"Camelot Ridge Dr",
    "iso:country":"US",
    "sg:address":"54 Camelot Ridge Dr",
    "sg:city":"Brandon",
    "sg:classifiers":[
        {
            "category":"Arena",
            "subcategory":"Sports Club",
            "type":"Entertainment"
        }
    ],
    "sg:phone":"+1 813 689 8938",
    "sg:postcode":"33511",
    "sg:province":"FL",
    "sg:tags":[
        "health"
    ],
    "sg:website":"http://www.pvd-ri.com",
    "wof:name":"Christian Wellness Instit",
    "wof:placetype":"venue"
},
  "geometry": {"coordinates":[-82.28851299999999,27.881107],"type":"Point"}
}