{
  "type": "Feature",
  "properties": {
    "addr:full":"100 Pine Ln West Palm Beach FL 33411",
    "addr:housenumber":"100",
    "addr:postcode":"33411",
    "addr:street":"Pine Ln",
    "iso:country":"US",
    "sg:address":"100 Pine Ln",
    "sg:city":"West Palm Beach",
    "sg:classifiers":[
        {
            "category":"Banks & Credit Unions",
            "subcategory":"Bank",
            "type":"Services"
        }
    ],
    "sg:phone":"+1 561 792 5562",
    "sg:postcode":"33411",
    "sg:province":"FL",
    "sg:tags":[
        "federal",
        "agency"
    ],
    "wof:name":"American Industrial & Trade",
    "wof:placetype":"venue"
},
  "geometry": {"coordinates":[-80.22992000000001,26.712996],"type":"Point"}
}