{
  "type": "Feature",
  "properties": {
    "addr:full":"6112 33rd St E Bradenton FL 34203",
    "addr:housenumber":"6112",
    "addr:postcode":"34203",
    "addr:street":"33Rd St",
    "iso:country":"US",
    "sg:address":"6112 33rd St E",
    "sg:city":"Bradenton",
    "sg:classifiers":[
        {
            "category":"Building & Trades",
            "subcategory":"Construction",
            "type":"Services"
        }
    ],
    "sg:phone":"+1 941 756 5044",
    "sg:postcode":"34203",
    "sg:province":"FL",
    "sg:tags":[
        "general",
        "contractor"
    ],
    "wof:name":"Burghardt & Burghardt",
    "wof:placetype":"venue"
},
  "geometry": {"coordinates":[-82.52194299999999,27.432261],"type":"Point"}
}