{
  "type": "Feature",
  "properties": {
    "iso:country":"US",
    "sg:address":"8518 103rd St",
    "sg:city":"Jacksonville",
    "sg:classifiers":[
        {
            "category":"Building & Trades",
            "subcategory":"Construction",
            "type":"Services"
        }
    ],
    "sg:phone":"+1 904 771 5816",
    "sg:postcode":"32210",
    "sg:province":"FL",
    "sg:tags":[
        "home",
        "builder",
        "nonresidential"
    ],
    "sg:website":"www.sidhigginbotham.com",
    "wof:name":"Sid Higginbotham Builder Inc",
    "wof:placetype":"venue"
},
  "geometry": {"coordinates":[-81.79365900000001,30.247699],"type":"Point"}
}