{
  "type": "Feature",
  "properties": {
    "iso:country":"US",
    "sg:address":"10605 NW 7th Ave",
    "sg:city":"Miami",
    "sg:classifiers":[
        {
            "category":"Home & Garden",
            "subcategory":"Furniture",
            "type":"Retail Goods"
        }
    ],
    "sg:phone":"+1 305 759 5650",
    "sg:postcode":"33150",
    "sg:province":"FL",
    "wof:name":"Korner Furniture Inc",
    "wof:placetype":"venue"
},
  "geometry": {"coordinates":[-80.209999,25.872815],"type":"Point"}
}