{
  "type": "Feature",
  "properties": {
    "iso:country":"US",
    "sg:address":"7200 Lake Ellenor Dr",
    "sg:city":"Orlando",
    "sg:classifiers":[
        {
            "category":"Professional",
            "subcategory":"Advertising",
            "type":"Services"
        }
    ],
    "sg:phone":"+1 407 826 0835",
    "sg:postcode":"32809",
    "sg:province":"FL",
    "sg:tags":[
        "agency"
    ],
    "wof:name":"Nationwide Advertising Service",
    "wof:placetype":"venue"
},
  "geometry": {"coordinates":[-81.40348,28.461847],"type":"Point"}
}