{
  "type": "Feature",
  "properties": {
    "iso:country":"US",
    "sg:address":"9910 Castleton St",
    "sg:city":"Orlando",
    "sg:classifiers":[
        {
            "category":"Wholesale",
            "subcategory":"Machinery & Supplies",
            "type":"Manufacturing & Wholesale Goods"
        }
    ],
    "sg:phone":"+1 407 657 8949",
    "sg:postcode":"32817",
    "sg:province":"FL",
    "sg:tags":[
        "equipment",
        "establishment"
    ],
    "wof:name":"Dattoma Palulis Pressure Clean",
    "wof:placetype":"venue"
},
  "geometry": {"coordinates":[-81.24563999999999,28.591126],"type":"Point"}
}