{
  "type": "Feature",
  "properties": {
    "addr:full":"6730 Memorial Hwy Tampa FL 33615",
    "addr:housenumber":"6730",
    "addr:postcode":"33615",
    "addr:street":"Memorial Hwy",
    "iso:country":"US",
    "sg:address":"6730 Memorial Hwy",
    "sg:city":"Tampa",
    "sg:classifiers":[
        {
            "category":"Home & Garden",
            "subcategory":"Building Materials",
            "type":"Retail Goods"
        }
    ],
    "sg:phone":"+1 813 888 7111",
    "sg:postcode":"33615",
    "sg:province":"FL",
    "sg:website":"www.homedepot.com",
    "wof:name":"Home Depot",
    "wof:placetype":"venue"
},
  "geometry": {"coordinates":[-82.581412,27.996126],"type":"Point"}
}