{
  "type": "Feature",
  "properties": {
    "iso:country":"US",
    "sg:address":"46 Mitchell Ave",
    "sg:city":"Orange Park",
    "sg:classifiers":[
        {
            "category":"Freight",
            "type":"Transportation"
        }
    ],
    "sg:phone":"+1 904 264 5474",
    "sg:postcode":"32073",
    "sg:province":"FL",
    "sg:tags":[
        "operator",
        "local",
        "trucking"
    ],
    "wof:name":"Bonnie Showman",
    "wof:placetype":"venue"
},
  "geometry": {"coordinates":[-81.734729,30.157587],"type":"Point"}
}