{
  "type": "Feature",
  "properties": {
    "iso:country":"US",
    "sg:address":"13990 NE 6th Ave",
    "sg:city":"North Miami",
    "sg:classifiers":[
        {
            "category":"Airline",
            "type":"Transportation"
        }
    ],
    "sg:phone":"+1 786 413 0033",
    "sg:postcode":"33161",
    "sg:province":"FL",
    "sg:tags":[
        "shuttle",
        "airport"
    ],
    "wof:name":"Extreme Exotic Car Rentals",
    "wof:placetype":"venue"
},
  "geometry": {"coordinates":[-80.18719900000001,25.903901],"type":"Point"}
}