{
  "type": "Feature",
  "properties": {
    "iso:country":"US",
    "sg:address":"1209 E Oakwood St",
    "sg:city":"Tarpon Springs",
    "sg:classifiers":[
        {
            "category":"Organizations",
            "subcategory":"Religious Organization",
            "type":"Services"
        }
    ],
    "sg:phone":"+1 727 937 4885",
    "sg:postcode":"34689",
    "sg:province":"FL",
    "sg:tags":[
        "church"
    ],
    "wof:name":"Greek Congregation-Tarpon Spgs",
    "wof:placetype":"venue"
},
  "geometry": {"coordinates":[-82.73427100000001,28.142106],"type":"Point"}
}