{
  "type": "Feature",
  "properties": {
    "iso:country":"US",
    "sg:address":"141 NE 3rd Ave Ste 401",
    "sg:city":"Miami",
    "sg:classifiers":[
        {
            "category":"Landmark",
            "subcategory":"Tourist Information",
            "type":"Public Place"
        }
    ],
    "sg:phone":"+1 305 379 5400",
    "sg:postcode":"33132",
    "sg:province":"FL",
    "sg:tags":[
        "tour"
    ],
    "wof:name":"Happy Tours International",
    "wof:placetype":"venue"
},
  "geometry": {"coordinates":[-80.188576,25.776098],"type":"Point"}
}