{
  "type": "Feature",
  "properties": {
    "iso:country":"US",
    "sg:address":"5686 Youngquist Rd",
    "sg:city":"Fort Myers",
    "sg:classifiers":[
        {
            "category":"Building & Trades",
            "subcategory":"Construction",
            "type":"Services"
        },
        {
            "category":"Home & Garden",
            "subcategory":"Furniture",
            "type":"Retail Goods"
        }
    ],
    "sg:phone":"+1 239 489 2292",
    "sg:postcode":"33912",
    "sg:province":"FL",
    "sg:tags":[
        "maker",
        "cabinet"
    ],
    "wof:name":"Grumney Custom Cabinetry",
    "wof:placetype":"venue"
},
  "geometry": {"coordinates":[-81.85945100000001,26.510858],"type":"Point"}
}