{
  "type": "Feature",
  "properties": {
    "iso:country":"US",
    "sg:address":"5801 Dahlia Dr",
    "sg:city":"Orlando",
    "sg:classifiers":[
        {
            "category":"Professional",
            "subcategory":"Accounting & Tax Preparation",
            "type":"Services"
        }
    ],
    "sg:phone":"+1 407 678 0048",
    "sg:postcode":"32807",
    "sg:province":"FL",
    "sg:tags":[
        "return"
    ],
    "wof:name":"M & R Incone Tax Service",
    "wof:placetype":"venue"
},
  "geometry": {"coordinates":[-81.30855099999999,28.54577],"type":"Point"}
}