{
  "type": "Feature",
  "properties": {
    "iso:country":"US",
    "sg:address":"9021 SW 156th St",
    "sg:city":"Miami",
    "sg:classifiers":[
        {
            "category":"Professional",
            "subcategory":"Management & Consulting",
            "type":"Services"
        }
    ],
    "sg:phone":"+1 305 378 4612",
    "sg:postcode":"33157",
    "sg:province":"FL",
    "wof:name":"Ongay Consulting",
    "wof:placetype":"venue"
},
  "geometry": {"coordinates":[-80.341336,25.62526],"type":"Point"}
}