{
  "type": "Feature",
  "properties": {
    "addr:full":"11701 NW 102nd Rd Medley FL 33178",
    "addr:housenumber":"11701",
    "addr:postcode":"33178",
    "addr:street":"Nw 102Nd Rd",
    "iso:country":"US",
    "sg:address":"11701 NW 102nd Rd",
    "sg:city":"Medley",
    "sg:classifiers":[
        {
            "category":"Freight",
            "type":"Transportation"
        }
    ],
    "sg:phone":"+1 305 863 9005",
    "sg:postcode":"33178",
    "sg:province":"FL",
    "wof:name":"Rodi Cargo Intl",
    "wof:placetype":"venue"
},
  "geometry": {"coordinates":[-80.365915,25.872054],"type":"Point"}
}