{
  "type": "Feature",
  "properties": {
    "addr:full":"3711 SW 4th Cir Ocala FL 34474",
    "addr:housenumber":"3711",
    "addr:postcode":"34474",
    "addr:street":"Sw 4Th Cir",
    "iso:country":"US",
    "sg:address":"3711 SW 4th Cir",
    "sg:city":"Ocala",
    "sg:classifiers":[
        {
            "category":"Building & Trades",
            "subcategory":"Landscaping Services",
            "type":"Services"
        }
    ],
    "sg:phone":"+1 352 854 7781",
    "sg:postcode":"34474",
    "sg:province":"FL",
    "wof:name":"Kowalski Tree Svc & Lawn Care",
    "wof:placetype":"venue"
},
  "geometry": {"coordinates":[-82.136742,29.137144],"type":"Point"}
}