{
  "type": "Feature",
  "properties": {
    "iso:country":"US",
    "sg:address":"11602 Westchase Golf Dr",
    "sg:city":"Tampa",
    "sg:classifiers":[
        {
            "category":"Sports & Exercise",
            "subcategory":"Golf",
            "type":"Entertainment"
        }
    ],
    "sg:phone":"+1 813 854 4415",
    "sg:postcode":"33626",
    "sg:province":"FL",
    "sg:tags":[
        "course"
    ],
    "wof:name":"Westchase Golf Club",
    "wof:placetype":"venue"
},
  "geometry": {"coordinates":[-82.616482,28.048032],"type":"Point"}
}