{
  "type": "Feature",
  "properties": {
    "iso:country":"US",
    "sg:address":"1701 S 23rd St",
    "sg:city":"Fort Pierce",
    "sg:classifiers":[
        {
            "category":"Social Services",
            "type":"Services"
        }
    ],
    "sg:phone":"+1 772 467 6000",
    "sg:postcode":"34950",
    "sg:province":"FL",
    "sg:tags":[
        "government"
    ],
    "wof:name":"Childrens Medical Svc",
    "wof:placetype":"venue"
},
  "geometry": {"coordinates":[-80.34739999999999,27.430149],"type":"Point"}
}