{
  "type": "Feature",
  "properties": {
    "iso:country":"US",
    "sg:address":"1931 N Carpenter Rd",
    "sg:city":"Titusville",
    "sg:classifiers":[
        {
            "category":"Shopping",
            "subcategory":"Department Store",
            "type":"Retail Goods"
        }
    ],
    "sg:phone":"+1 321 269 4187",
    "sg:postcode":"32796",
    "sg:province":"FL",
    "sg:tags":[
        "shop"
    ],
    "wof:name":"Wholesale Warehouse Express",
    "wof:placetype":"venue"
},
  "geometry": {"coordinates":[-80.865116,28.649141],"type":"Point"}
}