{
  "type": "Feature",
  "properties": {
    "iso:country":"US",
    "sg:address":"298 Fareham Dr",
    "sg:city":"Venice",
    "sg:classifiers":[
        {
            "category":"Food & Beverages",
            "subcategory":"Groceries & Convenience Stores",
            "type":"Retail Goods"
        }
    ],
    "sg:phone":"+1 941 497 2314",
    "sg:postcode":"34293",
    "sg:province":"FL",
    "wof:name":"Holy Kings Oil & Foods Inc",
    "wof:placetype":"venue"
},
  "geometry": {"coordinates":[-82.354179,27.050237],"type":"Point"}
}