{
  "type": "Feature",
  "properties": {
    "iso:country":"US",
    "sg:address":"949 S Main St",
    "sg:city":"Belle Glade",
    "sg:classifiers":[
        {
            "category":"Retail",
            "subcategory":"Repair Shop",
            "type":"Services"
        }
    ],
    "sg:phone":"+1 561 953 5174",
    "sg:postcode":"33430",
    "sg:province":"FL",
    "sg:tags":[
        "lock",
        "locksmith"
    ],
    "wof:name":"7 Day Always Emergency Lcksmth",
    "wof:placetype":"venue"
},
  "geometry": {"coordinates":[-80.670371,26.673984],"type":"Point"}
}