{
  "type": "Feature",
  "properties": {
    "iso:country":"US",
    "sg:address":"3389 W Woolbright Rd",
    "sg:city":"Boynton Beach",
    "sg:classifiers":[
        {
            "category":"Health Services",
            "subcategory":"Doctor",
            "type":"Services"
        }
    ],
    "sg:phone":"+1 561 733 0033",
    "sg:postcode":"33436",
    "sg:province":"FL",
    "sg:tags":[
        "medical"
    ],
    "wof:name":"Albrecht Joni",
    "wof:placetype":"venue"
},
  "geometry": {"coordinates":[-80.10035000000001,26.513437],"type":"Point"}
}