{
  "type": "Feature",
  "properties": {
    "addr:full":"25348 Canterbury Dr Lake Wales FL 33898",
    "addr:housenumber":"25348",
    "addr:postcode":"33898",
    "addr:street":"Canterbury Dr",
    "iso:country":"US",
    "sg:address":"25348 Canterbury Dr",
    "sg:city":"Lake Wales",
    "sg:classifiers":[
        {
            "category":"Shopping",
            "type":"Retail Goods"
        }
    ],
    "sg:phone":"+1 863 692 0004",
    "sg:postcode":"33898",
    "sg:province":"FL",
    "sg:tags":[
        "miscellaneous",
        "store"
    ],
    "wof:name":"Limoges Stamps",
    "wof:placetype":"venue"
},
  "geometry": {"coordinates":[-81.20529000000001,27.774824],"type":"Point"}
}