{
  "type": "Feature",
  "properties": {
    "iso:country":"US",
    "sg:address":"4049 Baden Dr",
    "sg:city":"Holiday",
    "sg:classifiers":[
        {
            "category":"Professional",
            "subcategory":"Business Services",
            "type":"Services"
        }
    ],
    "sg:phone":"+1 727 934 1330",
    "sg:postcode":"34691",
    "sg:province":"FL",
    "sg:tags":[
        "bail",
        "bond"
    ],
    "wof:name":"Coast To Coast Bail Bonds",
    "wof:placetype":"venue"
},
  "geometry": {"coordinates":[-82.74177400000001,28.195859],"type":"Point"}
}