{
  "type": "Feature",
  "properties": {
    "addr:full":"225 E Robinson St Orlando FL 32801",
    "addr:housenumber":"225",
    "addr:postcode":"32801",
    "addr:street":"E Robinson St",
    "iso:country":"US",
    "sg:address":"225 E Robinson St",
    "sg:city":"Orlando",
    "sg:classifiers":[
        {
            "category":"Professional",
            "subcategory":"Computer Services",
            "type":"Services"
        }
    ],
    "sg:phone":"+1 407 648 4775",
    "sg:postcode":"32801",
    "sg:province":"FL",
    "sg:tags":[
        "consultant",
        "designer"
    ],
    "wof:name":"Decision Support Technologies",
    "wof:placetype":"venue"
},
  "geometry": {"coordinates":[-81.37298,28.545783],"type":"Point"}
}