{
  "type": "Feature",
  "properties": {
    "addr:full":"300 SW 14th St Pompano Beach FL 33060",
    "addr:housenumber":"300",
    "addr:postcode":"33060",
    "addr:street":"Sw 14Th St",
    "iso:country":"US",
    "sg:address":"300 SW 14th St",
    "sg:city":"Pompano Beach",
    "sg:classifiers":[
        {
            "category":"Manufacturing",
            "subcategory":"Food",
            "type":"Manufacturing & Wholesale Goods"
        }
    ],
    "sg:phone":"+1 954 946 6826",
    "sg:postcode":"33060",
    "sg:province":"FL",
    "sg:tags":[
        "mfg"
    ],
    "wof:name":"Rick Moore Distributing I",
    "wof:placetype":"venue"
},
  "geometry": {"coordinates":[-80.127126,26.212295],"type":"Point"}
}