{
  "type": "Feature",
  "properties": {
    "addr:full":"633 Dunlawton Ave Daytona Beach FL 32127",
    "addr:housenumber":"633",
    "addr:postcode":"32127",
    "addr:street":"Dunlawton Ave",
    "iso:country":"US",
    "sg:address":"633 Dunlawton Ave",
    "sg:city":"Daytona Beach",
    "sg:classifiers":[
        {
            "category":"Health Services",
            "subcategory":"Doctor",
            "type":"Services"
        }
    ],
    "sg:phone":"+1 386 756 1937",
    "sg:postcode":"32127",
    "sg:province":"FL",
    "sg:tags":[
        "physician",
        "medical",
        "surgeon"
    ],
    "wof:name":"Neena P Chopra MD",
    "wof:placetype":"venue"
},
  "geometry": {"coordinates":[-80.996662,29.139285],"type":"Point"}
}