{
  "type": "Feature",
  "properties": {
    "addr:full":"30669 US Hwy 19 N Palm Harbor FL 34684",
    "addr:postcode":"30669;34684",
    "addr:street":"Us Hwy 19 N",
    "iso:country":"US",
    "sg:address":"30669 US Hwy 19 N",
    "sg:city":"Palm Harbor",
    "sg:classifiers":[
        {
            "category":"Shopping",
            "subcategory":"Clothing, Apparel, & Fashions",
            "type":"Retail Goods"
        }
    ],
    "sg:phone":"+1 727 786 7329",
    "sg:postcode":"34684",
    "sg:province":"FL",
    "wof:name":"Fashion Bug",
    "wof:placetype":"venue"
},
  "geometry": {"coordinates":[-82.738545,28.049524],"type":"Point"}
}