{
  "type": "Feature",
  "properties": {
    "iso:country":"US",
    "sg:address":"3430 Garden St",
    "sg:city":"Titusville",
    "sg:classifiers":[
        {
            "category":"Autos & Motor Vehicles",
            "subcategory":"Automobile Sales",
            "type":"Retail Goods"
        }
    ],
    "sg:phone":"+1 321 385 1380",
    "sg:postcode":"32796",
    "sg:province":"FL",
    "sg:tags":[
        "car",
        "dealer"
    ],
    "wof:name":"KLM Automotive",
    "wof:placetype":"venue"
},
  "geometry": {"coordinates":[-80.848815,28.617674],"type":"Point"}
}