{
  "type": "Feature",
  "properties": {
    "addr:full":"770 E 9th St Hialeah FL 33010",
    "addr:housenumber":"770",
    "addr:postcode":"33010",
    "addr:street":"E 9Th St",
    "iso:country":"US",
    "sg:address":"770 E 9th St",
    "sg:city":"Hialeah",
    "sg:classifiers":[
        {
            "category":"Cinema",
            "subcategory":"Movie Rental",
            "type":"Entertainment"
        }
    ],
    "sg:phone":"+1 305 885 5116",
    "sg:postcode":"33010",
    "sg:province":"FL",
    "sg:tags":[
        "game",
        "video"
    ],
    "sg:website":"www.blockbuster.com",
    "wof:name":"Blockbuster Video",
    "wof:placetype":"venue"
},
  "geometry": {"coordinates":[-80.266098,25.8304],"type":"Point"}
}