{
  "type": "Feature",
  "properties": {
    "addr:full":"3305 N Stirrup Dr Beverly Hills FL 34465",
    "addr:housenumber":"3305",
    "addr:postcode":"34465",
    "addr:street":"N Stirrup Dr",
    "iso:country":"US",
    "sg:address":"3305 N Stirrup Dr",
    "sg:city":"Beverly Hills",
    "sg:classifiers":[
        {
            "category":"Shopping",
            "subcategory":"Florist",
            "type":"Retail Goods"
        }
    ],
    "sg:phone":"+1 352 527 9786",
    "sg:postcode":"34465",
    "sg:province":"FL",
    "wof:name":"Robyn's Garden",
    "wof:placetype":"venue"
},
  "geometry": {"coordinates":[-82.533079,28.910549],"type":"Point"}
}