{
  "type": "Feature",
  "properties": {
    "iso:country":"US",
    "sg:address":"319 E Phoenix Ave",
    "sg:city":"Lake Placid",
    "sg:classifiers":[
        {
            "category":"Building & Trades",
            "subcategory":"Landscaping Services",
            "type":"Services"
        }
    ],
    "sg:phone":"+1 863 465 9596",
    "sg:postcode":"33852",
    "sg:province":"FL",
    "wof:name":"Wendell Smith",
    "wof:placetype":"venue"
},
  "geometry": {"coordinates":[-81.35866799999999,27.306901],"type":"Point"}
}