{
  "type": "Feature",
  "properties": {
    "iso:country":"US",
    "sg:address":"6121 Collins Rd",
    "sg:city":"Jacksonville",
    "sg:classifiers":[
        {
            "category":"Building & Trades",
            "subcategory":"Construction",
            "type":"Services"
        }
    ],
    "sg:phone":"+1 904 573 6703",
    "sg:postcode":"32244",
    "sg:province":"FL",
    "sg:tags":[
        "floor",
        "laying",
        "contractor"
    ],
    "wof:name":"Camp Marble & Stone",
    "wof:placetype":"venue"
},
  "geometry": {"coordinates":[-81.74363700000001,30.20444],"type":"Point"}
}