{
  "type": "Feature",
  "properties": {
    "addr:full":"520 Brockway Ave Orlando FL 32807",
    "addr:housenumber":"520",
    "addr:postcode":"32807",
    "addr:street":"Brockway Ave",
    "iso:country":"US",
    "sg:address":"520 Brockway Ave",
    "sg:city":"Orlando",
    "sg:classifiers":[
        {
            "category":"Building & Trades",
            "subcategory":"Construction",
            "type":"Services"
        }
    ],
    "sg:phone":"+1 407 281 4601",
    "sg:postcode":"32807",
    "sg:province":"FL",
    "sg:tags":[
        "concrete",
        "contractor"
    ],
    "wof:name":"Lopez Manuel Con Resurfacing",
    "wof:placetype":"venue"
},
  "geometry": {"coordinates":[-81.29477300000001,28.535432],"type":"Point"}
}