{
  "type": "Feature",
  "properties": {
    "iso:country":"US",
    "sg:address":"6151 Washington St",
    "sg:city":"Hollywood",
    "sg:classifiers":[
        {
            "category":"Organizations",
            "subcategory":"Non-profit Organization",
            "type":"Services"
        }
    ],
    "sg:phone":"+1 954 963 2229",
    "sg:postcode":"33023",
    "sg:province":"FL",
    "sg:tags":[
        "alternative",
        "abortion",
        "social"
    ],
    "wof:name":"Emergency Pregnancy Services",
    "wof:placetype":"venue"
},
  "geometry": {"coordinates":[-80.211065,26.002725],"type":"Point"}
}