{
  "type": "Feature",
  "properties": {
    "iso:country":"US",
    "sg:address":"14808 SW 136th St",
    "sg:city":"Miami",
    "sg:classifiers":[
        {
            "category":"Manufacturing",
            "subcategory":"Leather Goods",
            "type":"Manufacturing & Wholesale Goods"
        }
    ],
    "sg:phone":"+1 305 234 9000",
    "sg:postcode":"33196",
    "sg:province":"FL",
    "sg:website":"www.jpourse.com",
    "wof:name":"Ourse USA Inc",
    "wof:placetype":"venue"
},
  "geometry": {"coordinates":[-80.431434,25.640511],"type":"Point"}
}