{
  "type": "Feature",
  "properties": {
    "addr:full":"6950 Phillips Hwy Jacksonville FL 32216",
    "addr:housenumber":"6950",
    "addr:postcode":"32216",
    "addr:street":"Phillips Hwy",
    "iso:country":"US",
    "sg:address":"6950 Phillips Hwy",
    "sg:city":"Jacksonville",
    "sg:classifiers":[
        {
            "category":"Building & Trades",
            "subcategory":"Cleaning & Sanitation",
            "type":"Services"
        },
        {
            "category":"Professional",
            "subcategory":"Detective & Security Services",
            "type":"Services"
        }
    ],
    "sg:phone":"+1 904 332 6642",
    "sg:postcode":"32216",
    "sg:province":"FL",
    "sg:tags":[
        "car",
        "janitor",
        "maintenance"
    ],
    "wof:name":"Sunstates Security",
    "wof:placetype":"venue"
},
  "geometry": {"coordinates":[-81.602228,30.246425],"type":"Point"}
}