{
  "type": "Feature",
  "properties": {
    "addr:full":"7909 Canyon Lake Cir Orlando FL 32835",
    "addr:housenumber":"7909",
    "addr:postcode":"32835",
    "addr:street":"Canyon Lake Cir",
    "iso:country":"US",
    "sg:address":"7909 Canyon Lake Cir",
    "sg:city":"Orlando",
    "sg:classifiers":[
        {
            "category":"Freight",
            "type":"Transportation"
        }
    ],
    "sg:phone":"+1 407 293 0856",
    "sg:postcode":"32835",
    "sg:province":"FL",
    "wof:name":"Ennio Melilli",
    "wof:placetype":"venue"
},
  "geometry": {"coordinates":[-81.488612,28.528629],"type":"Point"}
}