{
  "type": "Feature",
  "properties": {
    "addr:full":"8486 Nashua Dr Palm Beach Gardens FL 33418",
    "addr:housenumber":"8486",
    "addr:postcode":"33418",
    "addr:street":"Nashua Dr",
    "iso:country":"US",
    "sg:address":"8486 Nashua Dr",
    "sg:city":"Palm Beach Gardens",
    "sg:classifiers":[
        {
            "category":"Building & Trades",
            "subcategory":"Plumbing",
            "type":"Services"
        }
    ],
    "sg:phone":"+1 561 627 1137",
    "sg:postcode":"33418",
    "sg:province":"FL",
    "sg:tags":[
        "conditioning",
        "air",
        "system",
        "contractor"
    ],
    "wof:name":"Traversair Inc",
    "wof:placetype":"venue"
},
  "geometry": {"coordinates":[-80.116552,26.799491],"type":"Point"}
}