{
  "type": "Feature",
  "properties": {
    "iso:country":"US",
    "sg:address":"10474 Northcliffe Blvd",
    "sg:city":"Spring Hill",
    "sg:classifiers":[
        {
            "category":"Personal",
            "type":"Services"
        }
    ],
    "sg:phone":"+1 352 686 9770",
    "sg:postcode":"34608",
    "sg:province":"FL",
    "sg:tags":[
        "control",
        "weight"
    ],
    "wof:name":"New U Medical Weight Loss Clnc",
    "wof:placetype":"venue"
},
  "geometry": {"coordinates":[-82.546757,28.493676],"type":"Point"}
}