{
  "type": "Feature",
  "properties": {
    "iso:country":"US",
    "sg:address":"624 S F St",
    "sg:city":"Lake Worth",
    "sg:classifiers":[
        {
            "category":"Manufacturing",
            "subcategory":"Electronics",
            "type":"Manufacturing & Wholesale Goods"
        }
    ],
    "sg:phone":"+1 561 586 4171",
    "sg:postcode":"33460",
    "sg:province":"FL",
    "sg:tags":[
        "repair",
        "sheet",
        "mfg",
        "component",
        "metalwork",
        "welding"
    ],
    "wof:name":"Metal Dexterity Co Inc",
    "wof:placetype":"venue"
},
  "geometry": {"coordinates":[-80.06052699999999,26.607772],"type":"Point"}
}