{
  "type": "Feature",
  "properties": {
    "iso:country":"US",
    "sg:address":"4104 Hayes St",
    "sg:city":"Hollywood",
    "sg:classifiers":[
        {
            "category":"Wholesale",
            "subcategory":"Machinery & Supplies",
            "type":"Manufacturing & Wholesale Goods"
        }
    ],
    "sg:phone":"+1 954 454 4401",
    "sg:postcode":"33021",
    "sg:province":"FL",
    "sg:tags":[
        "aircraft",
        "parts"
    ],
    "wof:name":"Southern Air Support",
    "wof:placetype":"venue"
},
  "geometry": {"coordinates":[-80.185771,26.019813],"type":"Point"}
}