{
  "type": "Feature",
  "properties": {
    "addr:full":"51 NE 2nd Ave Delray Beach FL 33444",
    "addr:housenumber":"51",
    "addr:postcode":"33444",
    "addr:street":"Ne 2Nd Ave",
    "iso:country":"US",
    "sg:address":"51 NE 2nd Ave",
    "sg:city":"Delray Beach",
    "sg:classifiers":[
        {
            "category":"Shopping",
            "subcategory":"Photographic Equipment",
            "type":"Retail Goods"
        }
    ],
    "sg:phone":"+1 561 276 7766",
    "sg:postcode":"33444",
    "sg:province":"FL",
    "sg:tags":[
        "camera",
        "supply"
    ],
    "wof:name":"Pro Shop For Photographers",
    "wof:placetype":"venue"
},
  "geometry": {"coordinates":[-80.071029,26.462537],"type":"Point"}
}