{
  "type": "Feature",
  "properties": {
    "addr:full":"21 E Keen St Kissimmee FL 34744",
    "addr:housenumber":"21",
    "addr:postcode":"34744",
    "addr:street":"E Keen St",
    "iso:country":"US",
    "sg:address":"21 E Keen St",
    "sg:city":"Kissimmee",
    "sg:classifiers":[
        {
            "category":"Organizations",
            "subcategory":"Community Association",
            "type":"Services"
        }
    ],
    "sg:phone":"+1 407 846 4141",
    "sg:postcode":"34744",
    "sg:province":"FL",
    "wof:name":"Disabled American Veterans",
    "wof:placetype":"venue"
},
  "geometry": {"coordinates":[-81.401799,28.325425],"type":"Point"}
}