{
  "type": "Feature",
  "properties": {
    "addr:full":"300 N Lake Destiny Rd Maitland FL 32751",
    "addr:housenumber":"300",
    "addr:postcode":"32751",
    "addr:street":"N Lake Destiny Rd",
    "iso:country":"US",
    "sg:address":"300 N Lake Destiny Rd",
    "sg:city":"Maitland",
    "sg:classifiers":[
        {
            "category":"Health Services",
            "subcategory":"Doctor",
            "type":"Services"
        }
    ],
    "sg:phone":"+1 407 381 7364",
    "sg:postcode":"32751",
    "sg:province":"FL",
    "sg:tags":[
        "physician",
        "pediatrics-emergency",
        "pediatrics",
        "surgeons",
        "medicine",
        "surgeon"
    ],
    "wof:name":"Thielhelm Jennifer MD Pediatrics",
    "wof:placetype":"venue"
},
  "geometry": {"coordinates":[-81.388957,28.629308],"type":"Point"}
}