{
  "type": "Feature",
  "properties": {
    "iso:country":"US",
    "sg:address":"1436 Firewheel Dr",
    "sg:city":"Zephyrhills",
    "sg:classifiers":[
        {
            "category":"Banks & Credit Unions",
            "subcategory":"Investment Brokerage",
            "type":"Services"
        }
    ],
    "sg:phone":"+1 813 991 7112",
    "sg:postcode":"33543",
    "sg:province":"FL",
    "sg:tags":[
        "security"
    ],
    "wof:name":"Suppiah Inc",
    "wof:placetype":"venue"
},
  "geometry": {"coordinates":[-82.330269,28.178077],"type":"Point"}
}