{
  "type": "Feature",
  "properties": {
    "addr:full":"3810 5th St E Bradenton FL 34208",
    "addr:housenumber":"3810",
    "addr:postcode":"34208",
    "addr:street":"5Th St",
    "iso:country":"US",
    "sg:address":"3810 5th St E",
    "sg:city":"Bradenton",
    "sg:classifiers":[
        {
            "category":"Retail",
            "subcategory":"Repair Shop",
            "type":"Services"
        },
        {
            "category":"Food & Beverages",
            "subcategory":"Groceries & Convenience Stores",
            "type":"Retail Goods"
        }
    ],
    "sg:phone":"+1 941 755 9252",
    "sg:postcode":"34208",
    "sg:province":"FL",
    "sg:tags":[
        "major",
        "refinishing",
        "appliance",
        "refrigerant",
        "small",
        "freezers-repair",
        "refrigerator",
        "recovery"
    ],
    "wof:name":"Cobb Enterprises Appliance Repair",
    "wof:placetype":"venue"
},
  "geometry": {"coordinates":[-82.558922,27.465975],"type":"Point"}
}