{
  "type": "Feature",
  "properties": {
    "addr:full":"2007 SW 103rd Ct Miami FL 33165",
    "addr:housenumber":"2007",
    "addr:postcode":"33165",
    "addr:street":"Sw 103Rd Ct",
    "iso:country":"US",
    "sg:address":"2007 SW 103rd Ct",
    "sg:city":"Miami",
    "sg:classifiers":[
        {
            "category":"Professional",
            "type":"Services"
        }
    ],
    "sg:phone":"+1 305 220 6611",
    "sg:postcode":"33165",
    "sg:province":"FL",
    "wof:name":"Billmed USA Inc",
    "wof:placetype":"venue"
},
  "geometry": {"coordinates":[-80.36219,25.749952],"type":"Point"}
}