{
  "type": "Feature",
  "properties": {
    "iso:country":"US",
    "sg:address":"6810 NW 20th Ave",
    "sg:city":"Fort Lauderdale",
    "sg:classifiers":[
        {
            "category":"Home & Garden",
            "subcategory":"Home Furnishings",
            "type":"Retail Goods"
        }
    ],
    "sg:phone":"+1 954 970 4949",
    "sg:postcode":"33309",
    "sg:province":"FL",
    "wof:name":"Rolling Security Shutter Corp",
    "wof:placetype":"venue"
},
  "geometry": {"coordinates":[-80.170406,26.20726],"type":"Point"}
}