{
  "type": "Feature",
  "properties": {
    "iso:country":"US",
    "sg:address":"2631 1st St",
    "sg:city":"Fort Myers",
    "sg:classifiers":[
        {
            "category":"Travel",
            "subcategory":"Hotels & Motels",
            "type":"Entertainment"
        }
    ],
    "sg:phone":"+1 239 334 2135",
    "sg:postcode":"33916",
    "sg:province":"FL",
    "wof:name":"Ta Ki Ki Motel",
    "wof:placetype":"venue"
},
  "geometry": {"coordinates":[-81.859497,26.6502],"type":"Point"}
}