{
  "type": "Feature",
  "properties": {
    "iso:country":"US",
    "sg:address":"2944 S Florida Ave",
    "sg:city":"Lakeland",
    "sg:classifiers":[
        {
            "category":"Manufacturing",
            "subcategory":"Printing",
            "type":"Manufacturing & Wholesale Goods"
        }
    ],
    "sg:phone":"+1 863 680 2809",
    "sg:postcode":"33803",
    "sg:province":"FL",
    "sg:tags":[
        "printer"
    ],
    "wof:name":"L & M Printing",
    "wof:placetype":"venue"
},
  "geometry": {"coordinates":[-81.95694899999999,28.010528],"type":"Point"}
}