{
  "type": "Feature",
  "properties": {
    "iso:country":"US",
    "sg:address":"2787 State Rd 62",
    "sg:city":"Bowling Green",
    "sg:classifiers":[
        {
            "category":"Arts & Performance",
            "subcategory":"Theater",
            "type":"Entertainment"
        }
    ],
    "sg:phone":"+1 863 533 0565",
    "sg:postcode":"33834",
    "sg:province":"FL",
    "sg:tags":[
        "group"
    ],
    "wof:name":"Gulf State Quartet",
    "wof:placetype":"venue"
},
  "geometry": {"coordinates":[-81.891621,27.594831],"type":"Point"}
}