{
  "type": "Feature",
  "properties": {
    "addr:full":"26543 SW 122nd Pl Homestead FL 33032",
    "addr:housenumber":"26543",
    "addr:postcode":"33032",
    "addr:street":"Sw 122Nd Pl",
    "iso:country":"US",
    "sg:address":"26543 SW 122nd Pl",
    "sg:city":"Homestead",
    "sg:classifiers":[
        {
            "category":"Social Services",
            "subcategory":"Child Care",
            "type":"Services"
        }
    ],
    "sg:phone":"+1 305 258 9168",
    "sg:postcode":"33032",
    "sg:province":"FL",
    "sg:tags":[
        "day"
    ],
    "wof:name":"Community Enrichment Inc",
    "wof:placetype":"venue"
},
  "geometry": {"coordinates":[-80.389658,25.520094],"type":"Point"}
}