{
  "type": "Feature",
  "properties": {
    "iso:country":"US",
    "sg:address":"15315 S Dixie Hwy",
    "sg:city":"Miami",
    "sg:classifiers":[
        {
            "category":"Shopping",
            "subcategory":"Gifts & Souvenirs",
            "type":"Retail Goods"
        },
        {
            "category":"Professional",
            "subcategory":"Printing & Photocopies",
            "type":"Services"
        }
    ],
    "sg:phone":"+1 786 242 4086",
    "sg:postcode":"33157",
    "sg:province":"FL",
    "sg:tags":[
        "shop",
        "medal",
        "plaque",
        "trophies"
    ],
    "wof:name":"Trophy City Inc",
    "wof:placetype":"venue"
},
  "geometry": {"coordinates":[-80.34142300000001,25.627951],"type":"Point"}
}