{
  "type": "Feature",
  "properties": {
    "addr:full":"3108 104th Ave E Parrish FL 34219",
    "addr:housenumber":"3108",
    "addr:postcode":"34219",
    "addr:street":"104Th Ave E Parrish",
    "iso:country":"US",
    "sg:address":"3108 104th Ave E",
    "sg:city":"Parrish",
    "sg:classifiers":[
        {
            "category":"Retail",
            "subcategory":"Portrait Studio",
            "type":"Services"
        }
    ],
    "sg:phone":"+1 941 447 4705",
    "sg:postcode":"34219",
    "sg:province":"FL",
    "sg:tags":[
        "photo"
    ],
    "wof:name":"Lawless Studios",
    "wof:placetype":"venue"
},
  "geometry": {"coordinates":[-82.45809800000001,27.537233],"type":"Point"}
}