{
  "type": "Feature",
  "properties": {
    "iso:country":"US",
    "sg:address":"8367 SW 137th Ave",
    "sg:city":"Miami",
    "sg:classifiers":[
        {
            "category":"Professional",
            "type":"Services"
        }
    ],
    "sg:phone":"+1 305 386 8022",
    "sg:postcode":"33183",
    "sg:province":"FL",
    "wof:name":"CK Golf Inc",
    "wof:placetype":"venue"
},
  "geometry": {"coordinates":[-80.41590100000001,25.689034],"type":"Point"}
}