{
  "type": "Feature",
  "properties": {
    "iso:country":"US",
    "sg:address":"1876 Stella Ct S",
    "sg:city":"Lakeland",
    "sg:classifiers":[
        {
            "category":"Building & Trades",
            "subcategory":"Construction",
            "type":"Services"
        }
    ],
    "sg:phone":"+1 863 644 1381",
    "sg:postcode":"33813",
    "sg:province":"FL",
    "sg:tags":[
        "contractor"
    ],
    "wof:name":"Martinez Brick Work",
    "wof:placetype":"venue"
},
  "geometry": {"coordinates":[-81.931748,27.978753],"type":"Point"}
}