{
  "type": "Feature",
  "properties": {
    "iso:country":"US",
    "sg:address":"3432 Kossuth Ave",
    "sg:city":"Milton",
    "sg:classifiers":[
        {
            "category":"Building & Trades",
            "subcategory":"Landscaping Services",
            "type":"Services"
        }
    ],
    "sg:phone":"+1 850 995 0783",
    "sg:postcode":"32583",
    "sg:province":"FL",
    "wof:name":"Lambeths T Lawn Handymn Serv",
    "wof:placetype":"venue"
},
  "geometry": {"coordinates":[-87.117456,30.559029],"type":"Point"}
}