{
  "type": "Feature",
  "properties": {
    "iso:country":"US",
    "sg:address":"1757 N Temple Ave",
    "sg:city":"Starke",
    "sg:classifiers":[
        {
            "category":"Travel",
            "subcategory":"Hotels & Motels",
            "type":"Entertainment"
        }
    ],
    "sg:phone":"+1 904 964 5332",
    "sg:postcode":"32091",
    "sg:province":"FL",
    "sg:tags":[
        "operation"
    ],
    "wof:name":"Bradford Motel & Campground",
    "wof:placetype":"venue"
},
  "geometry": {"coordinates":[-82.10466,29.963009],"type":"Point"}
}