{
  "type": "Feature",
  "properties": {
    "iso:country":"US",
    "sg:address":"3700 NW 21st St",
    "sg:city":"Fort Lauderdale",
    "sg:classifiers":[
        {
            "category":"Manufacturing",
            "subcategory":"Apparel",
            "type":"Manufacturing & Wholesale Goods"
        }
    ],
    "sg:phone":"+1 954 484 2375",
    "sg:postcode":"33311",
    "sg:province":"FL",
    "sg:tags":[
        "dress",
        "mfg"
    ],
    "wof:name":"Brenda D Jones",
    "wof:placetype":"venue"
},
  "geometry": {"coordinates":[-80.197827,26.152807],"type":"Point"}
}