{
  "type": "Feature",
  "properties": {
    "iso:country":"US",
    "sg:address":"8320 Hanley Rd",
    "sg:city":"Tampa",
    "sg:classifiers":[
        {
            "category":"Banks & Credit Unions",
            "subcategory":"Bank",
            "type":"Services"
        }
    ],
    "sg:phone":"+1 813 885 4776",
    "sg:postcode":"33634",
    "sg:province":"FL",
    "sg:tags":[
        "national"
    ],
    "wof:name":"Bank Of America",
    "wof:placetype":"venue"
},
  "geometry": {"coordinates":[-82.562376,28.024378],"type":"Point"}
}