{
  "type": "Feature",
  "properties": {
    "iso:country":"US",
    "sg:address":"6905 Escobar Ct",
    "sg:city":"Boca Raton",
    "sg:classifiers":[
        {
            "category":"Organizations",
            "subcategory":"Professional Association",
            "type":"Services"
        },
        {
            "category":"Organizations",
            "subcategory":"Community Association",
            "type":"Services"
        }
    ],
    "sg:phone":"+1 561 394 7669",
    "sg:postcode":"33433",
    "sg:province":"FL",
    "wof:name":"Tiburon 11 Homeowners Assn",
    "wof:placetype":"venue"
},
  "geometry": {"coordinates":[-80.153026,26.35527],"type":"Point"}
}