{
  "type": "Feature",
  "properties": {
    "addr:full":"4708 Pleasant St Palm Harbor FL 34683",
    "addr:housenumber":"4708",
    "addr:postcode":"34683",
    "addr:street":"Pleasant St",
    "iso:country":"US",
    "sg:address":"4708 Pleasant St",
    "sg:city":"Palm Harbor",
    "sg:classifiers":[
        {
            "category":"Building & Trades",
            "subcategory":"Construction",
            "type":"Services"
        }
    ],
    "sg:phone":"+1 727 934 4695",
    "sg:postcode":"34683",
    "sg:province":"FL",
    "sg:tags":[
        "roofing",
        "contractor"
    ],
    "wof:name":"Mickey's Roof Svc Inc",
    "wof:placetype":"venue"
},
  "geometry": {"coordinates":[-82.761742,28.119202],"type":"Point"}
}