{
  "type": "Feature",
  "properties": {
    "addr:full":"4137 NW 135th St Opa Locka FL 33054",
    "addr:housenumber":"4137",
    "addr:postcode":"33054",
    "addr:street":"Nw 135Th St;Locka",
    "iso:country":"US",
    "sg:address":"4137 NW 135th St",
    "sg:city":"Opa Locka",
    "sg:classifiers":[
        {
            "category":"Real Estate",
            "subcategory":"Real Estate Operator",
            "type":"Services"
        }
    ],
    "sg:phone":"+1 305 681 3545",
    "sg:postcode":"33054",
    "sg:province":"FL",
    "sg:tags":[
        "building",
        "nonresidential"
    ],
    "wof:name":"T M C Center Inc",
    "wof:placetype":"venue"
},
  "geometry": {"coordinates":[-80.263879,25.896601],"type":"Point"}
}