{
  "type": "Feature",
  "properties": {
    "iso:country":"US",
    "sg:address":"13126 NE 3rd Ct",
    "sg:city":"North Miami",
    "sg:classifiers":[
        {
            "category":"Wholesale",
            "subcategory":"Durable Goods & Equipment",
            "type":"Manufacturing & Wholesale Goods"
        }
    ],
    "sg:phone":"+1 305 891 0307",
    "sg:postcode":"33161",
    "sg:province":"FL",
    "sg:tags":[
        "exporter"
    ],
    "wof:name":"Barroso Vet Supply Inc",
    "wof:placetype":"venue"
},
  "geometry": {"coordinates":[-80.191812,25.895596],"type":"Point"}
}