{
  "type": "Feature",
  "properties": {
    "addr:full":"1810 NW 23 Blvd Gainesville FL 32605",
    "addr:housenumber":"1810",
    "addr:postcode":"32605",
    "addr:street":"Nw 23 Blvd",
    "iso:country":"US",
    "sg:address":"1810 NW 23 Blvd",
    "sg:city":"Gainesville",
    "sg:classifiers":[
        {
            "category":"Real Estate",
            "subcategory":"Real Estate Operator",
            "type":"Services"
        }
    ],
    "sg:phone":"+1 352 372 2225",
    "sg:postcode":"32605",
    "sg:province":"FL",
    "sg:tags":[
        "building",
        "apartment"
    ],
    "wof:name":"Covered Bridge Apartments",
    "wof:placetype":"venue"
},
  "geometry": {"coordinates":[-82.346943,29.675041],"type":"Point"}
}