{
  "type": "Feature",
  "properties": {
    "addr:full":"7640 NW 61st Ter Pompano Beach FL 33067",
    "addr:housenumber":"7640",
    "addr:postcode":"33067",
    "addr:street":"Nw 61St Ter",
    "iso:country":"US",
    "sg:address":"7640 NW 61st Ter",
    "sg:city":"Pompano Beach",
    "sg:classifiers":[
        {
            "category":"Professional",
            "subcategory":"Business Services",
            "type":"Services"
        }
    ],
    "sg:phone":"+1 954 650 6398",
    "sg:postcode":"33067",
    "sg:province":"FL",
    "wof:name":"American Dream Inspectors",
    "wof:placetype":"venue"
},
  "geometry": {"coordinates":[-80.20845300000001,26.325628],"type":"Point"}
}