{
  "type": "Feature",
  "properties": {
    "addr:full":"400 N Miami Ave Miami FL 33128",
    "addr:housenumber":"400",
    "addr:postcode":"33128",
    "addr:street":"N Miami Ave",
    "iso:country":"US",
    "sg:address":"400 N Miami Ave",
    "sg:city":"Miami",
    "sg:classifiers":[
        {
            "category":"Building & Trades",
            "subcategory":"Construction",
            "type":"Services"
        }
    ],
    "sg:phone":"+1 305 358 5771",
    "sg:postcode":"33128",
    "sg:province":"FL",
    "sg:tags":[
        "general",
        "contractor"
    ],
    "wof:name":"Airside Construction Svc",
    "wof:placetype":"venue"
},
  "geometry": {"coordinates":[-80.19379499999999,25.77891],"type":"Point"}
}