{
  "type": "Feature",
  "properties": {
    "iso:country":"US",
    "sg:address":"4921 Wedgewood Way",
    "sg:city":"West Palm Beach",
    "sg:classifiers":[
        {
            "category":"Real Estate",
            "subcategory":"Real Estate Operator",
            "type":"Services"
        }
    ],
    "sg:phone":"+1 561 683 1631",
    "sg:postcode":"33417",
    "sg:province":"FL",
    "wof:name":"Wedgewood Apts",
    "wof:placetype":"venue"
},
  "geometry": {"coordinates":[-80.11784,26.702158],"type":"Point"}
}