{
  "type": "Feature",
  "properties": {
    "iso:country":"US",
    "sg:address":"202 W Main St Ste 101",
    "sg:city":"Wauchula",
    "sg:classifiers":[
        {
            "category":"Coffee & Tea",
            "type":"Food & Drink"
        },
        {
            "category":"Restaurant",
            "type":"Food & Drink"
        }
    ],
    "sg:phone":"+1 863 767 9004",
    "sg:postcode":"33873",
    "sg:province":"FL",
    "sg:tags":[
        "espresso"
    ],
    "wof:name":"Java Cafe",
    "wof:placetype":"venue"
},
  "geometry": {"coordinates":[-81.813024,27.547334],"type":"Point"}
}