{
  "type": "Feature",
  "properties": {
    "addr:full":"8964 NW 54th St Fort Lauderdale FL 33351",
    "addr:housenumber":"8964",
    "addr:postcode":"33351",
    "addr:street":"Nw 54Th St",
    "iso:country":"US",
    "sg:address":"8964 NW 54th St",
    "sg:city":"Fort Lauderdale",
    "sg:classifiers":[
        {
            "category":"Building & Trades",
            "subcategory":"Construction",
            "type":"Services"
        }
    ],
    "sg:phone":"+1 954 746 2533",
    "sg:postcode":"33351",
    "sg:province":"FL",
    "sg:tags":[
        "house"
    ],
    "wof:name":"Apex Construction & Engineerin",
    "wof:placetype":"venue"
},
  "geometry": {"coordinates":[-80.270005,26.190385],"type":"Point"}
}