{
  "type": "Feature",
  "properties": {
    "iso:country":"US",
    "sg:address":"5210 7th St",
    "sg:city":"Zephyrhills",
    "sg:classifiers":[
        {
            "category":"Personal",
            "subcategory":"Beauty Salon",
            "type":"Services"
        }
    ],
    "sg:phone":"+1 813 782 2115",
    "sg:postcode":"33542",
    "sg:province":"FL",
    "sg:tags":[
        "hair",
        "stylist"
    ],
    "wof:name":"Kut & Kurl Beauty Salon",
    "wof:placetype":"venue"
},
  "geometry": {"coordinates":[-82.18043400000001,28.233008],"type":"Point"}
}