{
  "type": "Feature",
  "properties": {
    "iso:country":"US",
    "sg:address":"1810 SW 100th Ave",
    "sg:city":"Hollywood",
    "sg:classifiers":[
        {
            "category":"Manufacturing",
            "subcategory":"Rubber & Plastics",
            "type":"Manufacturing & Wholesale Goods"
        },
        {
            "category":"Manufacturing",
            "subcategory":"Tools & Machinery",
            "type":"Manufacturing & Wholesale Goods"
        }
    ],
    "sg:phone":"+1 954 431 3675",
    "sg:postcode":"33025",
    "sg:province":"FL",
    "sg:tags":[
        "machine",
        "shop",
        "product",
        "mfg"
    ],
    "wof:name":"Sutter Tool Company",
    "wof:placetype":"venue"
},
  "geometry": {"coordinates":[-80.277703,25.991137],"type":"Point"}
}