{
  "type": "Feature",
  "properties": {
    "iso:country":"US",
    "sg:address":"75 N Pace Blvd",
    "sg:city":"Pensacola",
    "sg:classifiers":[
        {
            "category":"Professional",
            "type":"Services"
        }
    ],
    "sg:phone":"+1 850 505 5611",
    "sg:postcode":"32505",
    "sg:province":"FL",
    "wof:name":"Southern Co Svc",
    "wof:placetype":"venue"
},
  "geometry": {"coordinates":[-87.241648,30.413225],"type":"Point"}
}