{
  "type": "Feature",
  "properties": {
    "addr:full":"7611 State Rd 52 Hudson FL 34667",
    "addr:housenumber":"7611;52",
    "addr:postcode":"34667",
    "addr:street":"State Rd",
    "iso:country":"US",
    "sg:address":"7611 State Rd 52",
    "sg:city":"Hudson",
    "sg:classifiers":[
        {
            "category":"Food & Beverages",
            "subcategory":"Groceries & Convenience Stores",
            "type":"Retail Goods"
        }
    ],
    "sg:phone":"+1 727 819 9485",
    "sg:postcode":"34667",
    "sg:province":"FL",
    "wof:name":"Victory BP",
    "wof:placetype":"venue"
},
  "geometry": {"coordinates":[-82.689813,28.331323],"type":"Point"}
}