{
  "type": "Feature",
  "properties": {
    "addr:full":"5640 NW 105th Ct Apt 210 Doral FL 33178",
    "addr:housenumber":"5640;210",
    "addr:postcode":"33178",
    "addr:street":"Nw 105Th Ct Apt",
    "iso:country":"US",
    "sg:address":"5640 NW 105th Ct Apt 210",
    "sg:city":"Doral",
    "sg:classifiers":[
        {
            "category":"Communications",
            "subcategory":"Television Station",
            "type":"Services"
        }
    ],
    "sg:phone":"+1 786 331 9136",
    "sg:postcode":"33178",
    "sg:province":"FL",
    "sg:tags":[
        "network"
    ],
    "wof:name":"Colatel Inc",
    "wof:placetype":"venue"
},
  "geometry": {"coordinates":[-80.366727,25.824319],"type":"Point"}
}