{
  "type": "Feature",
  "properties": {
    "iso:country":"US",
    "sg:address":"2943 Dogwood St",
    "sg:city":"Marianna",
    "sg:classifiers":[
        {
            "category":"Social Services",
            "subcategory":"Child Care",
            "type":"Services"
        }
    ],
    "sg:phone":"+1 850 482 2269",
    "sg:postcode":"32446",
    "sg:province":"FL",
    "sg:tags":[
        "day"
    ],
    "wof:name":"Junes Day Care Center",
    "wof:placetype":"venue"
},
  "geometry": {"coordinates":[-85.218396,30.779263],"type":"Point"}
}