{
  "type": "Feature",
  "properties": {
    "iso:country":"US",
    "sg:address":"212 S Old Dixie Hwy",
    "sg:city":"Jupiter",
    "sg:classifiers":[
        {
            "category":"Real Estate",
            "subcategory":"Real Estate Services",
            "type":"Services"
        }
    ],
    "sg:phone":"+1 561 745 7004",
    "sg:postcode":"33458",
    "sg:province":"FL",
    "sg:tags":[
        "company",
        "title"
    ],
    "wof:name":"Jupiter Tequesta Comm Title",
    "wof:placetype":"venue"
},
  "geometry": {"coordinates":[-80.094323,26.931352],"type":"Point"}
}