{
  "type": "Feature",
  "properties": {
    "addr:full":"4910 Helton Ln Pensacola FL 32526",
    "addr:postcode":"4910;32526",
    "addr:street":"Helton Ln",
    "iso:country":"US",
    "sg:address":"4910 Helton Ln",
    "sg:city":"Pensacola",
    "sg:classifiers":[
        {
            "category":"Professional",
            "type":"Services"
        }
    ],
    "sg:phone":"+1 850 944 8254",
    "sg:postcode":"32526",
    "sg:province":"FL",
    "sg:tags":[
        "establishment"
    ],
    "wof:name":"Pf Net",
    "wof:placetype":"venue"
},
  "geometry": {"coordinates":[-87.33044700000001,30.490579],"type":"Point"}
}