{
  "type": "Feature",
  "properties": {
    "iso:country":"US",
    "sg:address":"106 E Lake Ave",
    "sg:city":"Auburndale",
    "sg:classifiers":[
        {
            "category":"Shopping",
            "subcategory":"Used Merchandise",
            "type":"Retail Goods"
        }
    ],
    "sg:phone":"+1 863 967 7102",
    "sg:postcode":"33823",
    "sg:province":"FL",
    "sg:tags":[
        "shop",
        "consignment"
    ],
    "wof:name":"Dance The Night Away Btq",
    "wof:placetype":"venue"
},
  "geometry": {"coordinates":[-81.78774,28.065373],"type":"Point"}
}