{
  "type": "Feature",
  "properties": {
    "addr:full":"10657 SE 125th St Belleview FL 34420",
    "addr:housenumber":"10657",
    "addr:postcode":"34420",
    "addr:street":"Se 125Th St",
    "iso:country":"US",
    "sg:address":"10657 SE 125th St",
    "sg:city":"Belleview",
    "sg:classifiers":[
        {
            "category":"Professional",
            "subcategory":"Research",
            "type":"Services"
        },
        {
            "category":"Building & Trades",
            "subcategory":"Construction",
            "type":"Services"
        }
    ],
    "sg:phone":"+1 352 288 4121",
    "sg:postcode":"34420",
    "sg:province":"FL",
    "sg:tags":[
        "environmental",
        "ecological",
        "contractor"
    ],
    "wof:name":"Environmental Restoration Spec",
    "wof:placetype":"venue"
},
  "geometry": {"coordinates":[-81.976529,29.040726],"type":"Point"}
}