{
  "type": "Feature",
  "properties": {
    "iso:country":"US",
    "sg:address":"2769 SE Highway 70",
    "sg:city":"Arcadia",
    "sg:classifiers":[
        {
            "category":"Autos & Motor Vehicles",
            "subcategory":"Fuel & Gas Station",
            "type":"Retail Goods"
        }
    ],
    "sg:phone":"+1 863 491 5065",
    "sg:postcode":"34266",
    "sg:province":"FL",
    "wof:name":"Murphy Usa 06902",
    "wof:placetype":"venue"
},
  "geometry": {"coordinates":[-81.82871799999999,27.208872],"type":"Point"}
}