{
  "type": "Feature",
  "properties": {
    "iso:country":"US",
    "sg:address":"4901 Lillian Hwy",
    "sg:city":"Pensacola",
    "sg:classifiers":[
        {
            "category":"Food & Beverages",
            "subcategory":"Groceries & Convenience Stores",
            "type":"Retail Goods"
        }
    ],
    "sg:phone":"+1 850 456 7118",
    "sg:postcode":"32506",
    "sg:province":"FL",
    "wof:name":"Happy 7 Food Store",
    "wof:placetype":"venue"
},
  "geometry": {"coordinates":[-87.28438199999999,30.42645],"type":"Point"}
}