{
  "type": "Feature",
  "properties": {
    "addr:full":"900 W Call St Tallahassee FL 32304",
    "addr:housenumber":"900",
    "addr:postcode":"32304",
    "addr:street":"W Call St",
    "iso:country":"US",
    "sg:address":"900 W Call St",
    "sg:city":"Tallahassee",
    "sg:classifiers":[
        {
            "category":"Education",
            "subcategory":"College",
            "type":"Public Place"
        }
    ],
    "sg:phone":"+1 850 644 6700",
    "sg:postcode":"32304",
    "sg:province":"FL",
    "sg:tags":[
        "university"
    ],
    "wof:name":"Department of Oceanography",
    "wof:placetype":"venue"
},
  "geometry": {"coordinates":[-84.300027,30.444464],"type":"Point"}
}