{
  "type": "Feature",
  "properties": {
    "iso:country":"US",
    "sg:address":"6250 N Lockwood Ridge Rd",
    "sg:city":"Sarasota",
    "sg:classifiers":[
        {
            "category":"Banks & Credit Unions",
            "subcategory":"Bank",
            "type":"Services"
        }
    ],
    "sg:phone":"+1 941 359 7040",
    "sg:postcode":"34243",
    "sg:province":"FL",
    "sg:tags":[
        "loan",
        "real estate"
    ],
    "wof:name":"Countrywide Full Spectrum",
    "wof:placetype":"venue"
},
  "geometry": {"coordinates":[-82.505548,27.388389],"type":"Point"}
}