{
  "type": "Feature",
  "properties": {
    "iso:country":"US",
    "sg:address":"917 N Dixie Hwy",
    "sg:city":"Lake Worth",
    "sg:classifiers":[
        {
            "category":"Professional",
            "subcategory":"Lawyer & Legal Services",
            "type":"Services"
        }
    ],
    "sg:phone":"+1 561 582 4080",
    "sg:postcode":"33460",
    "sg:province":"FL",
    "sg:tags":[
        "attorney"
    ],
    "wof:name":"Williams & Ehrlich",
    "wof:placetype":"venue"
},
  "geometry": {"coordinates":[-80.05702599999999,26.627394],"type":"Point"}
}