{
  "type": "Feature",
  "properties": {
    "iso:country":"US",
    "sg:address":"7229 W 24th Ave",
    "sg:city":"Hialeah",
    "sg:classifiers":[
        {
            "category":"Health Services",
            "subcategory":"Medical Lab",
            "type":"Services"
        }
    ],
    "sg:phone":"+1 305 264 7742",
    "sg:postcode":"33016",
    "sg:province":"FL",
    "sg:tags":[
        "laboratory"
    ],
    "wof:name":"M D Diagnostic Lab Inc",
    "wof:placetype":"venue"
},
  "geometry": {"coordinates":[-80.331761,25.887725],"type":"Point"}
}