{
  "type": "Feature",
  "properties": {
    "addr:full":"7830 NW 71st St Miami FL 33166",
    "addr:housenumber":"7830",
    "addr:postcode":"33166",
    "addr:street":"Nw 71St St",
    "iso:country":"US",
    "sg:address":"7830 NW 71st St",
    "sg:city":"Miami",
    "sg:classifiers":[
        {
            "category":"Professional",
            "subcategory":"Advertising",
            "type":"Services"
        }
    ],
    "sg:phone":"+1 786 845 8318",
    "sg:postcode":"33166",
    "sg:province":"FL",
    "sg:tags":[
        "product",
        "agency",
        "advertising-promotional",
        "specialty"
    ],
    "wof:name":"United Promotions Corp",
    "wof:placetype":"venue"
},
  "geometry": {"coordinates":[-80.328166,25.837992],"type":"Point"}
}