{
  "type": "Feature",
  "properties": {
    "iso:country":"US",
    "sg:address":"8779 Forest Hills Dr",
    "sg:city":"Pompano Beach",
    "sg:classifiers":[
        {
            "category":"Utilities",
            "subcategory":"Telephone",
            "type":"Services"
        }
    ],
    "sg:phone":"+1 954 201 6487",
    "sg:postcode":"33065",
    "sg:province":"FL",
    "sg:tags":[
        "web",
        "hosting"
    ],
    "wof:name":"Primary Web Hosting",
    "wof:placetype":"venue"
},
  "geometry": {"coordinates":[-80.23846,26.266946],"type":"Point"}
}