{
  "type": "Feature",
  "properties": {
    "iso:country":"US",
    "sg:address":"280 Moll Dr",
    "sg:city":"Santa Rosa Beach",
    "sg:classifiers":[
        {
            "category":"Retail",
            "subcategory":"Auto Repair",
            "type":"Services"
        }
    ],
    "sg:phone":"+1 850 267 2828",
    "sg:postcode":"32459",
    "sg:province":"FL",
    "sg:tags":[
        "general"
    ],
    "wof:name":"Coastal Auto Repair",
    "wof:placetype":"venue"
},
  "geometry": {"coordinates":[-86.23759200000001,30.370557],"type":"Point"}
}