{
  "type": "Feature",
  "properties": {
    "addr:full":"2510 SW 3rd Ave Fort Lauderdale FL 33315",
    "addr:housenumber":"2510",
    "addr:postcode":"33315",
    "addr:street":"Sw 3Rd Ave",
    "iso:country":"US",
    "sg:address":"2510 SW 3rd Ave",
    "sg:city":"Fort Lauderdale",
    "sg:classifiers":[
        {
            "category":"Autos & Motor Vehicles",
            "subcategory":"Automobile Sales",
            "type":"Retail Goods"
        }
    ],
    "sg:phone":"+1 954 768 0600",
    "sg:postcode":"33315",
    "sg:province":"FL",
    "wof:name":"Invest-A-Car",
    "wof:placetype":"venue"
},
  "geometry": {"coordinates":[-80.144614,26.090919],"type":"Point"}
}