{
  "type": "Feature",
  "properties": {
    "iso:country":"US",
    "sg:address":"517 Thornhill Rd",
    "sg:city":"Fort Walton Beach",
    "sg:classifiers":[
        {
            "category":"Manufacturing",
            "subcategory":"Printing",
            "type":"Manufacturing & Wholesale Goods"
        }
    ],
    "sg:phone":"+1 850 862 4069",
    "sg:postcode":"32547",
    "sg:province":"FL",
    "sg:tags":[
        "photo",
        "book",
        "studio",
        "portrait"
    ],
    "wof:name":"Lighthouse People The",
    "wof:placetype":"venue"
},
  "geometry": {"coordinates":[-86.61147,30.441213],"type":"Point"}
}