{
  "type": "Feature",
  "properties": {
    "iso:country":"US",
    "sg:address":"1533 Cape Coral Pkwy W",
    "sg:city":"Cape Coral",
    "sg:classifiers":[
        {
            "category":"Banks & Credit Unions",
            "subcategory":"Bank",
            "type":"Services"
        }
    ],
    "sg:phone":"+1 239 945 8600",
    "sg:postcode":"33914",
    "sg:province":"FL",
    "sg:website":"www.suntrust.com",
    "wof:name":"Suntrust",
    "wof:placetype":"venue"
},
  "geometry": {"coordinates":[-82.000801,26.562901],"type":"Point"}
}