{
  "type": "Feature",
  "properties": {
    "iso:country":"US",
    "sg:address":"301 N Brevard Ave",
    "sg:city":"Arcadia",
    "sg:classifiers":[
        {
            "category":"Restaurant",
            "type":"Food & Drink"
        },
        {
            "category":"Food & Beverages",
            "subcategory":"Groceries & Convenience Stores",
            "type":"Retail Goods"
        }
    ],
    "sg:phone":"+1 863 494 7707",
    "sg:postcode":"34266",
    "sg:province":"FL",
    "sg:tags":[
        "shop",
        "sandwich"
    ],
    "wof:name":"As Giant Sandwiches Of Arcadia",
    "wof:placetype":"venue"
},
  "geometry": {"coordinates":[-81.85682300000001,27.220045],"type":"Point"}
}