{
  "type": "Feature",
  "properties": {
    "iso:country":"US",
    "sg:address":"9801 Lyman St",
    "sg:city":"Pensacola",
    "sg:classifiers":[
        {
            "category":"Building & Trades",
            "subcategory":"Pest Control",
            "type":"Services"
        }
    ],
    "sg:phone":"+1 850 474 0500",
    "sg:postcode":"32534",
    "sg:province":"FL",
    "sg:tags":[
        "farm",
        "bee",
        "specialty",
        "animal",
        "removal"
    ],
    "wof:name":"Morgan's Termite & Pest Control LLC",
    "wof:placetype":"venue"
},
  "geometry": {"coordinates":[-87.282188,30.539049],"type":"Point"}
}