{
  "type": "Feature",
  "properties": {
    "addr:full":"221 SE 4th St Boynton Beach FL 33435",
    "addr:housenumber":"221",
    "addr:postcode":"33435",
    "addr:street":"Se 4Th St",
    "iso:country":"US",
    "sg:address":"221 SE 4th St",
    "sg:city":"Boynton Beach",
    "sg:classifiers":[
        {
            "category":"Building & Trades",
            "subcategory":"Construction",
            "type":"Services"
        }
    ],
    "sg:phone":"+1 561 364 7735",
    "sg:postcode":"33435",
    "sg:province":"FL",
    "sg:tags":[
        "paving",
        "contractor"
    ],
    "wof:name":"Atlantic Shores Seal Coating",
    "wof:placetype":"venue"
},
  "geometry": {"coordinates":[-80.059421,26.527041],"type":"Point"}
}