{
  "type": "Feature",
  "properties": {
    "addr:full":"915 NE 8th Ave Hallandale FL 33009",
    "addr:housenumber":"915",
    "addr:postcode":"33009",
    "addr:street":"Ne 8Th Ave",
    "iso:country":"US",
    "sg:address":"915 NE 8th Ave",
    "sg:city":"Hallandale",
    "sg:classifiers":[
        {
            "category":"Professional",
            "type":"Services"
        }
    ],
    "sg:phone":"+1 954 458 9932",
    "sg:postcode":"33009",
    "sg:province":"FL",
    "wof:name":"Windmill Soap Co",
    "wof:placetype":"venue"
},
  "geometry": {"coordinates":[-80.140691,25.995764],"type":"Point"}
}