{
  "type": "Feature",
  "properties": {
    "iso:country":"US",
    "sg:address":"12555 NW 17th Ave",
    "sg:city":"Miami",
    "sg:classifiers":[
        {
            "category":"Social Services",
            "subcategory":"Child Care",
            "type":"Services"
        }
    ],
    "sg:phone":"+1 305 687 1979",
    "sg:postcode":"33167",
    "sg:province":"FL",
    "sg:tags":[
        "day"
    ],
    "wof:name":"Libby's Kiddie Care",
    "wof:placetype":"venue"
},
  "geometry": {"coordinates":[-80.227097,25.8892],"type":"Point"}
}