{
  "type": "Feature",
  "properties": {
    "iso:country":"US",
    "sg:address":"13975 NW 58th Ct",
    "sg:city":"Hialeah",
    "sg:classifiers":[
        {
            "category":"Professional",
            "subcategory":"Management & Consulting",
            "type":"Services"
        }
    ],
    "sg:phone":"+1 305 827 4717",
    "sg:postcode":"33014",
    "sg:province":"FL",
    "sg:tags":[
        "marketing",
        "program"
    ],
    "wof:name":"Inke Marketing",
    "wof:placetype":"venue"
},
  "geometry": {"coordinates":[-80.29538599999999,25.901627],"type":"Point"}
}