{
  "type": "Feature",
  "properties": {
    "iso:country":"US",
    "sg:address":"707 Tamiami Trl",
    "sg:city":"Venice",
    "sg:classifiers":[
        {
            "category":"Autos & Motor Vehicles",
            "subcategory":"Automobile Sales",
            "type":"Retail Goods"
        }
    ],
    "sg:phone":"+1 941 966 0008",
    "sg:postcode":"34285",
    "sg:province":"FL",
    "sg:tags":[
        "car",
        "dealer"
    ],
    "wof:name":"Brian's Auto Co",
    "wof:placetype":"venue"
},
  "geometry": {"coordinates":[-82.440657,27.086584],"type":"Point"}
}