{
  "type": "Feature",
  "properties": {
    "iso:country":"US",
    "sg:address":"1 Ave A",
    "sg:city":"Fort Pierce",
    "sg:classifiers":[
        {
            "category":"Autos & Motor Vehicles",
            "subcategory":"Boat Sales",
            "type":"Retail Goods"
        }
    ],
    "sg:phone":"+1 772 466 0866",
    "sg:postcode":"34950",
    "sg:province":"FL",
    "sg:tags":[
        "yacht"
    ],
    "wof:name":"CYS Yacht Management",
    "wof:placetype":"venue"
},
  "geometry": {"coordinates":[-80.32432,27.4488],"type":"Point"}
}