{
  "type": "Feature",
  "properties": {
    "addr:full":"202 20th Street Ocean Marathon FL 33050",
    "addr:housenumber":"202",
    "addr:postcode":"33050",
    "addr:street":"20Th Street",
    "iso:country":"US",
    "sg:address":"202 20th Street Ocean",
    "sg:city":"Marathon",
    "sg:classifiers":[
        {
            "category":"Retail",
            "subcategory":"Auto Repair",
            "type":"Services"
        }
    ],
    "sg:phone":"+1 305 743 0520",
    "sg:postcode":"33050",
    "sg:province":"FL",
    "sg:tags":[
        "wrecker"
    ],
    "wof:name":"Paradise Towing",
    "wof:placetype":"venue"
},
  "geometry": {"coordinates":[-81.104958,24.708036],"type":"Point"}
}