{
  "type": "Feature",
  "properties": {
    "addr:full":"200 Biscayne Blvd Ste 600A Miami FL 33131",
    "addr:housenumber":"200",
    "addr:postcode":"33131",
    "addr:street":"Biscayne Blvd Ste 600A",
    "iso:country":"US",
    "sg:address":"200 Biscayne Blvd Ste 600A",
    "sg:city":"Miami",
    "sg:classifiers":[
        {
            "category":"Government",
            "subcategory":"Post Office",
            "type":"Public Place"
        }
    ],
    "sg:phone":"+1 305 374 0319",
    "sg:postcode":"33131",
    "sg:province":"FL",
    "sg:website":"www.uspostoffice.com",
    "wof:name":"US Post Office",
    "wof:placetype":"venue"
},
  "geometry": {"coordinates":[-80.18760899999999,25.772601],"type":"Point"}
}