{
  "type": "Feature",
  "properties": {
    "iso:country":"US",
    "sg:address":"4545 Pecan Dr",
    "sg:city":"Lakeland",
    "sg:classifiers":[
        {
            "category":"Communications",
            "type":"Services"
        },
        {
            "category":"Building & Trades",
            "subcategory":"Electrical",
            "type":"Services"
        }
    ],
    "sg:phone":"+1 863 660 7916",
    "sg:postcode":"33810",
    "sg:province":"FL",
    "sg:tags":[
        "television",
        "systems-repair",
        "cable",
        "telephone",
        "contractor",
        "equipment"
    ],
    "wof:name":"All American Telcom Services",
    "wof:placetype":"venue"
},
  "geometry": {"coordinates":[-82.044062,28.10138],"type":"Point"}
}