{
  "type": "Feature",
  "properties": {
    "iso:country":"US",
    "sg:address":"8007 Parramore Rd",
    "sg:city":"Jacksonville",
    "sg:classifiers":[
        {
            "category":"Building & Trades",
            "subcategory":"Landscaping Services",
            "type":"Services"
        }
    ],
    "sg:phone":"+1 904 778 1030",
    "sg:postcode":"32244",
    "sg:province":"FL",
    "sg:tags":[
        "landscape",
        "contractor"
    ],
    "wof:name":"Tree Amigos The Outdoor Svc",
    "wof:placetype":"venue"
},
  "geometry": {"coordinates":[-81.756119,30.200513],"type":"Point"}
}