{
  "type": "Feature",
  "properties": {
    "addr:full":"16101 NW 54th Ave Hialeah FL 33014",
    "addr:housenumber":"16101",
    "addr:postcode":"33014",
    "addr:street":"Nw 54Th Ave",
    "iso:country":"US",
    "sg:address":"16101 NW 54th Ave",
    "sg:city":"Hialeah",
    "sg:classifiers":[
        {
            "category":"Building & Trades",
            "subcategory":"Construction",
            "type":"Services"
        },
        {
            "category":"Home & Garden",
            "subcategory":"Carpets & Floor Coverings",
            "type":"Retail Goods"
        }
    ],
    "sg:phone":"+1 305 624 7777",
    "sg:postcode":"33014",
    "sg:province":"FL",
    "sg:tags":[
        "dry",
        "contractor",
        "material",
        "laying",
        "nonresidential"
    ],
    "wof:name":"Lotspeich Company Inc",
    "wof:placetype":"venue"
},
  "geometry": {"coordinates":[-80.28843999999999,25.921239],"type":"Point"}
}