{
  "type": "Feature",
  "properties": {
    "iso:country":"US",
    "sg:address":"18290 Collins Ave",
    "sg:city":"Miami",
    "sg:classifiers":[
        {
            "category":"Bars & Pubs",
            "type":"Food & Drink"
        }
    ],
    "sg:phone":"+1 305 682 8400",
    "sg:postcode":"33160",
    "sg:province":"FL",
    "wof:name":"Porterhouse Bar & Grill",
    "wof:placetype":"venue"
},
  "geometry": {"coordinates":[-80.12121500000001,25.943741],"type":"Point"}
}