{
  "type": "Feature",
  "properties": {
    "iso:country":"US",
    "sg:address":"531 W 65th Ter",
    "sg:city":"Hialeah",
    "sg:classifiers":[
        {
            "category":"Building & Trades",
            "subcategory":"Plumbing",
            "type":"Services"
        }
    ],
    "sg:phone":"+1 305 556 6818",
    "sg:postcode":"33012",
    "sg:province":"FL",
    "sg:tags":[
        "contractor"
    ],
    "wof:name":"Class Mechanical Contractors",
    "wof:placetype":"venue"
},
  "geometry": {"coordinates":[-80.29393,25.882079],"type":"Point"}
}