{
  "type": "Feature",
  "properties": {
    "addr:full":"10226 NW 47th St Fort Lauderdale FL 33351",
    "addr:housenumber":"10226",
    "addr:postcode":"33351",
    "addr:street":"Nw 47Th St",
    "iso:country":"US",
    "sg:address":"10226 NW 47th St",
    "sg:city":"Fort Lauderdale",
    "sg:classifiers":[
        {
            "category":"Wholesale",
            "subcategory":"Office Equipment",
            "type":"Manufacturing & Wholesale Goods"
        },
        {
            "category":"Shopping",
            "subcategory":"Computers & Home Electronics",
            "type":"Retail Goods"
        }
    ],
    "sg:phone":"+1 954 748 6009",
    "sg:postcode":"33351",
    "sg:province":"FL",
    "sg:tags":[
        "specializing",
        "supply",
        "duplicating",
        "machine",
        "copying",
        "mail",
        "order"
    ],
    "wof:name":"Ecom Data Products Inc",
    "wof:placetype":"venue"
},
  "geometry": {"coordinates":[-80.285678,26.183363],"type":"Point"}
}