{
  "type": "Feature",
  "properties": {
    "iso:country":"US",
    "sg:address":"13311 SW 82nd St",
    "sg:city":"Miami",
    "sg:classifiers":[
        {
            "category":"Wholesale",
            "subcategory":"Office Equipment",
            "type":"Manufacturing & Wholesale Goods"
        }
    ],
    "sg:phone":"+1 305 382 2215",
    "sg:postcode":"33183",
    "sg:province":"FL",
    "wof:name":"Global Works Inc",
    "wof:placetype":"venue"
},
  "geometry": {"coordinates":[-80.41073900000001,25.691306],"type":"Point"}
}