{
  "type": "Feature",
  "properties": {
    "addr:full":"11 Russman Ln Palm Coast FL 32164",
    "addr:housenumber":"11",
    "addr:postcode":"32164",
    "addr:street":"Russman Ln",
    "iso:country":"US",
    "sg:address":"11 Russman Ln",
    "sg:city":"Palm Coast",
    "sg:classifiers":[
        {
            "category":"Building & Trades",
            "subcategory":"Construction",
            "type":"Services"
        }
    ],
    "sg:phone":"+1 386 586 0029",
    "sg:postcode":"32164",
    "sg:province":"FL",
    "sg:tags":[
        "contractor"
    ],
    "wof:name":"Souder Carpentry",
    "wof:placetype":"venue"
},
  "geometry": {"coordinates":[-81.24803199999999,29.513802],"type":"Point"}
}