{
  "type": "Feature",
  "properties": {
    "addr:full":"4470 NW 79th Ave Miami FL 33166",
    "addr:housenumber":"4470",
    "addr:postcode":"33166",
    "addr:street":"Nw 79Th Ave",
    "iso:country":"US",
    "sg:address":"4470 NW 79th Ave",
    "sg:city":"Miami",
    "sg:classifiers":[
        {
            "category":"Freight",
            "type":"Transportation"
        }
    ],
    "sg:phone":"+1 305 456 3093",
    "sg:postcode":"33166",
    "sg:province":"FL",
    "sg:tags":[
        "operator",
        "local",
        "trucking"
    ],
    "wof:name":"Guardados Deliveries Inc",
    "wof:placetype":"venue"
},
  "geometry": {"coordinates":[-80.32549899999999,25.813611],"type":"Point"}
}