{
  "type": "Feature",
  "properties": {
    "addr:full":"14326 NW 158th Ave Alachua FL 32615",
    "addr:housenumber":"14326",
    "addr:postcode":"32615",
    "addr:street":"Nw 158Th Ave",
    "iso:country":"US",
    "sg:address":"14326 NW 158th Ave",
    "sg:city":"Alachua",
    "sg:classifiers":[
        {
            "category":"Place Of Worship",
            "subcategory":"Church",
            "type":"Public Place"
        },
        {
            "category":"Place Of Worship",
            "type":"Public Place"
        }
    ],
    "sg:phone":"+1 386 462 4811",
    "sg:postcode":"32615",
    "sg:province":"FL",
    "sg:tags":[
        "churches-interdenominational",
        "churches-various",
        "denomination"
    ],
    "wof:name":"Crusaders For Christ Church Inc",
    "wof:placetype":"venue"
},
  "geometry": {"coordinates":[-82.497983,29.799642],"type":"Point"}
}