{
  "type": "Feature",
  "properties": {
    "iso:country":"US",
    "sg:address":"5846 Lake Grove Dr",
    "sg:city":"Lakeland",
    "sg:classifiers":[
        {
            "category":"Building & Trades",
            "subcategory":"Construction",
            "type":"Services"
        }
    ],
    "sg:phone":"+1 863 859 1474",
    "sg:postcode":"33809",
    "sg:province":"FL",
    "sg:tags":[
        "house"
    ],
    "wof:name":"Bakersfield Bldg Cnstr & Main",
    "wof:placetype":"venue"
},
  "geometry": {"coordinates":[-81.965951,28.117874],"type":"Point"}
}