{
  "type": "Feature",
  "properties": {
    "addr:full":"4984 E Colonial Dr Orlando FL 32803",
    "addr:housenumber":"4984",
    "addr:postcode":"32803",
    "addr:street":"E Colonial Dr",
    "iso:country":"US",
    "sg:address":"4984 E Colonial Dr",
    "sg:city":"Orlando",
    "sg:classifiers":[
        {
            "category":"Shopping",
            "subcategory":"Gifts & Souvenirs",
            "type":"Retail Goods"
        }
    ],
    "sg:phone":"+1 407 895 9253",
    "sg:postcode":"32803",
    "sg:province":"FL",
    "sg:tags":[
        "shop"
    ],
    "wof:name":"Mistiko",
    "wof:placetype":"venue"
},
  "geometry": {"coordinates":[-81.32662000000001,28.55329],"type":"Point"}
}