{
  "type": "Feature",
  "properties": {
    "addr:full":"13321 SW 47th St Miami FL 33175",
    "addr:housenumber":"13321",
    "addr:postcode":"33175",
    "addr:street":"Sw 47Th St",
    "iso:country":"US",
    "sg:address":"13321 SW 47th St",
    "sg:city":"Miami",
    "sg:classifiers":[
        {
            "category":"Building & Trades",
            "subcategory":"Construction",
            "type":"Services"
        }
    ],
    "sg:phone":"+1 305 559 7388",
    "sg:postcode":"33175",
    "sg:province":"FL",
    "sg:tags":[
        "contractor"
    ],
    "wof:name":"V & A Pool",
    "wof:placetype":"venue"
},
  "geometry": {"coordinates":[-80.411316,25.721412],"type":"Point"}
}