{
  "type": "Feature",
  "properties": {
    "addr:full":"2664 Gilmore St Jacksonville FL 32204",
    "addr:housenumber":"2664",
    "addr:postcode":"32204",
    "addr:street":"Gilmore St",
    "iso:country":"US",
    "sg:address":"2664 Gilmore St",
    "sg:city":"Jacksonville",
    "sg:classifiers":[
        {
            "category":"Building & Trades",
            "subcategory":"Construction",
            "type":"Services"
        }
    ],
    "sg:phone":"+1 904 381 7087",
    "sg:postcode":"32204",
    "sg:province":"FL",
    "sg:tags":[
        "contractor"
    ],
    "wof:name":"Riverside Contracting Co",
    "wof:placetype":"venue"
},
  "geometry": {"coordinates":[-81.69341900000001,30.318332],"type":"Point"}
}