{
  "type": "Feature",
  "properties": {
    "iso:country":"US",
    "sg:address":"1257 Sussex Dr",
    "sg:city":"Pompano Beach",
    "sg:classifiers":[
        {
            "category":"Professional",
            "type":"Services"
        }
    ],
    "sg:phone":"+1 954 718 1758",
    "sg:postcode":"33068",
    "sg:province":"FL",
    "wof:name":"Specialty Merchandise Products",
    "wof:placetype":"venue"
},
  "geometry": {"coordinates":[-80.232291,26.212631],"type":"Point"}
}