{
  "type": "Feature",
  "properties": {
    "iso:country":"US",
    "sg:address":"425 NW 54th St",
    "sg:city":"Miami",
    "sg:classifiers":[
        {
            "category":"Autos & Motor Vehicles",
            "subcategory":"Automobile Sales",
            "type":"Retail Goods"
        },
        {
            "category":"Retail",
            "subcategory":"Auto Repair",
            "type":"Services"
        }
    ],
    "sg:phone":"+1 305 754 3773",
    "sg:postcode":"33127",
    "sg:province":"FL",
    "sg:tags":[
        "body",
        "used",
        "shop",
        "cars-wholesale",
        "dealers-used",
        "car",
        "painting",
        "repairing"
    ],
    "wof:name":"Monte Carlo Cars Collection Corp",
    "wof:placetype":"venue"
},
  "geometry": {"coordinates":[-80.20320100000001,25.825001],"type":"Point"}
}