{
  "type": "Feature",
  "properties": {
    "iso:country":"US",
    "sg:address":"441 S 11th St",
    "sg:city":"Lake Wales",
    "sg:classifiers":[
        {
            "category":"Health Services",
            "subcategory":"Doctor",
            "type":"Services"
        }
    ],
    "sg:phone":"+1 863 676 7904",
    "sg:postcode":"33853",
    "sg:province":"FL",
    "sg:tags":[
        "physician",
        "surgeon"
    ],
    "wof:name":"Lake Wales Eye Ctr",
    "wof:placetype":"venue"
},
  "geometry": {"coordinates":[-81.564588,27.896182],"type":"Point"}
}