{
  "type": "Feature",
  "properties": {
    "iso:country":"US",
    "sg:address":"550 Biltmore Way",
    "sg:city":"Miami",
    "sg:classifiers":[
        {
            "category":"Banks & Credit Unions",
            "subcategory":"Financial Services",
            "type":"Services"
        }
    ],
    "sg:phone":"+1 305 447 9299",
    "sg:postcode":"33134",
    "sg:province":"FL",
    "sg:tags":[
        "investor"
    ],
    "wof:name":"Worth Investments Inc",
    "wof:placetype":"venue"
},
  "geometry": {"coordinates":[-80.265821,25.748154],"type":"Point"}
}