{
  "type": "Feature",
  "properties": {
    "addr:full":"2940 Forsyth Rd Winter Park FL 32792",
    "addr:housenumber":"2940",
    "addr:postcode":"32792",
    "addr:street":"Forsyth Rd",
    "iso:country":"US",
    "sg:address":"2940 Forsyth Rd",
    "sg:city":"Winter Park",
    "sg:classifiers":[
        {
            "category":"Wholesale",
            "subcategory":"Groceries",
            "type":"Manufacturing & Wholesale Goods"
        }
    ],
    "sg:phone":"+1 407 678 5500",
    "sg:postcode":"32792",
    "sg:province":"FL",
    "sg:tags":[
        "confectionery",
        "candy"
    ],
    "wof:name":"Awfully Good Candy",
    "wof:placetype":"venue"
},
  "geometry": {"coordinates":[-81.29471100000001,28.58611],"type":"Point"}
}