{
  "type": "Feature",
  "properties": {
    "iso:country":"US",
    "sg:address":"330 Winston Creek Pkwy",
    "sg:city":"Lakeland",
    "sg:classifiers":[
        {
            "category":"Manufacturing",
            "subcategory":"Textiles",
            "type":"Manufacturing & Wholesale Goods"
        }
    ],
    "sg:phone":"+1 863 683 7781",
    "sg:postcode":"33810",
    "sg:province":"FL",
    "sg:tags":[
        "mill",
        "fabric"
    ],
    "wof:name":"Kl Composites Inc",
    "wof:placetype":"venue"
},
  "geometry": {"coordinates":[-82.03148299999999,28.041397],"type":"Point"}
}