{
  "type": "Feature",
  "properties": {
    "iso:country":"US",
    "sg:address":"91 E Merritt Island Cswy",
    "sg:city":"Merritt Island",
    "sg:classifiers":[
        {
            "category":"Insurance",
            "subcategory":"Insurance Agent",
            "type":"Services"
        }
    ],
    "sg:phone":"+1 321 452 8328",
    "sg:postcode":"32952",
    "sg:province":"FL",
    "wof:name":"Blue Cross & Blue Shield",
    "wof:placetype":"venue"
},
  "geometry": {"coordinates":[-80.69956500000001,28.356922],"type":"Point"}
}