{
  "type": "Feature",
  "properties": {
    "addr:full":"470 Hornsby Ln Kenansville FL 34739",
    "addr:housenumber":"470",
    "addr:postcode":"34739",
    "addr:street":"Hornsby Ln",
    "iso:country":"US",
    "sg:address":"470 Hornsby Ln",
    "sg:city":"Kenansville",
    "sg:classifiers":[
        {
            "category":"Personal",
            "subcategory":"Hair Removal",
            "type":"Services"
        }
    ],
    "sg:phone":"+1 407 436 1677",
    "sg:postcode":"34739",
    "sg:province":"FL",
    "sg:tags":[
        "removing"
    ],
    "wof:name":"Florida Hair Solutions & Day",
    "wof:placetype":"venue"
},
  "geometry": {"coordinates":[-81.03987600000001,27.873325],"type":"Point"}
}