{
  "type": "Feature",
  "properties": {
    "addr:full":"1343 Main St Sarasota FL 34236",
    "addr:housenumber":"1343",
    "addr:postcode":"34236",
    "addr:street":"Main St",
    "iso:country":"US",
    "sg:address":"1343 Main St",
    "sg:city":"Sarasota",
    "sg:classifiers":[
        {
            "category":"Travel",
            "subcategory":"Travel Agent",
            "type":"Entertainment"
        }
    ],
    "sg:phone":"+1 941 365 2520",
    "sg:postcode":"34236",
    "sg:province":"FL",
    "sg:tags":[
        "agency"
    ],
    "wof:name":"American Express",
    "wof:placetype":"venue"
},
  "geometry": {"coordinates":[-82.54329300000001,27.335842],"type":"Point"}
}