{
  "type": "Feature",
  "properties": {
    "addr:full":"621 Choctaw Dr Destin FL 32541",
    "addr:housenumber":"621",
    "addr:postcode":"32541",
    "addr:street":"Choctaw Dr",
    "iso:country":"US",
    "sg:address":"621 Choctaw Dr",
    "sg:city":"Destin",
    "sg:classifiers":[
        {
            "category":"Real Estate",
            "subcategory":"Real Estate Agent",
            "type":"Services"
        }
    ],
    "sg:phone":"+1 850 650 4444",
    "sg:postcode":"32541",
    "sg:province":"FL",
    "wof:name":"Paradise Properties",
    "wof:placetype":"venue"
},
  "geometry": {"coordinates":[-86.49166200000001,30.386889],"type":"Point"}
}