{
  "type": "Feature",
  "properties": {
    "iso:country":"US",
    "sg:address":"706 Herbert St",
    "sg:city":"Port Orange",
    "sg:classifiers":[
        {
            "category":"Building & Trades",
            "subcategory":"Construction",
            "type":"Services"
        }
    ],
    "sg:phone":"+1 386 788 5330",
    "sg:postcode":"32129",
    "sg:province":"FL",
    "sg:tags":[
        "mobile",
        "home"
    ],
    "wof:name":"Tim Dyson Business Svc",
    "wof:placetype":"venue"
},
  "geometry": {"coordinates":[-81.001137,29.142732],"type":"Point"}
}