{
  "type": "Feature",
  "properties": {
    "addr:full":"19499 NW 2nd Ave Miami FL 33169",
    "addr:housenumber":"19499",
    "addr:postcode":"33169",
    "addr:street":"Nw 2Nd Ave",
    "iso:country":"US",
    "sg:address":"19499 NW 2nd Ave",
    "sg:city":"Miami",
    "sg:classifiers":[
        {
            "category":"Autos & Motor Vehicles",
            "subcategory":"Fuel & Gas Station",
            "type":"Retail Goods"
        }
    ],
    "sg:phone":"+1 305 651 6062",
    "sg:postcode":"33169",
    "sg:province":"FL",
    "sg:tags":[
        "station",
        "gasoline"
    ],
    "wof:name":"B P Corporation North America",
    "wof:placetype":"venue"
},
  "geometry": {"coordinates":[-80.205502,25.95161],"type":"Point"}
}