{
  "type": "Feature",
  "properties": {
    "iso:country":"US",
    "sg:address":"5373 Hiatus Rd",
    "sg:city":"Fort Lauderdale",
    "sg:classifiers":[
        {
            "category":"Professional",
            "subcategory":"Business Services",
            "type":"Services"
        }
    ],
    "sg:phone":"+1 954 749 0320",
    "sg:postcode":"33351",
    "sg:province":"FL",
    "sg:tags":[
        "micro",
        "film",
        "scanning"
    ],
    "wof:name":"Lorien Technologies Inc",
    "wof:placetype":"venue"
},
  "geometry": {"coordinates":[-80.28806400000001,26.1916],"type":"Point"}
}