{
  "type": "Feature",
  "properties": {
    "addr:full":"8096 69th Ln Pinellas Park FL 33781",
    "addr:housenumber":"8096",
    "addr:postcode":"33781",
    "addr:street":"69Th Ln",
    "iso:country":"US",
    "sg:address":"8096 69th Ln",
    "sg:city":"Pinellas Park",
    "sg:classifiers":[
        {
            "category":"Building & Trades",
            "subcategory":"Construction",
            "type":"Services"
        }
    ],
    "sg:phone":"+1 727 545 5264",
    "sg:postcode":"33781",
    "sg:province":"FL",
    "sg:tags":[
        "hanging",
        "contractor"
    ],
    "wof:name":"Ross Custom Painting Inc",
    "wof:placetype":"venue"
},
  "geometry": {"coordinates":[-82.734579,27.844993],"type":"Point"}
}