{
  "type": "Feature",
  "properties": {
    "iso:country":"US",
    "sg:address":"9822 Little Rd",
    "sg:city":"New Port Richey",
    "sg:classifiers":[
        {
            "category":"Ice Cream",
            "type":"Food & Drink"
        }
    ],
    "sg:menulink":"http://www.allmenus.com/fl/port-richey/221390-carvel/menu/",
    "sg:phone":"+1 727 863 1237",
    "sg:postcode":"34654",
    "sg:province":"FL",
    "sg:tags":[
        "american"
    ],
    "wof:name":"Carvel",
    "wof:placetype":"venue"
},
  "geometry": {"coordinates":[-82.671453,28.299006],"type":"Point"}
}