{
  "type": "Feature",
  "properties": {
    "addr:full":"1733 Morgans Mill Cir Orlando FL 32825",
    "addr:housenumber":"1733",
    "addr:postcode":"32825",
    "addr:street":"Morgans Mill Cir",
    "iso:country":"US",
    "sg:address":"1733 Morgans Mill Cir",
    "sg:city":"Orlando",
    "sg:classifiers":[
        {
            "category":"Utilities",
            "subcategory":"Telephone",
            "type":"Services"
        }
    ],
    "sg:phone":"+1 407 207 4011",
    "sg:postcode":"32825",
    "sg:province":"FL",
    "sg:tags":[
        "communications"
    ],
    "wof:name":"Reale Enterprises Inc",
    "wof:placetype":"venue"
},
  "geometry": {"coordinates":[-81.273804,28.522776],"type":"Point"}
}