{
  "type": "Feature",
  "properties": {
    "addr:full":"2769 Coral Way Coral Gables FL 33145",
    "addr:housenumber":"2769",
    "addr:postcode":"33145",
    "addr:street":"Coral Way",
    "iso:country":"US",
    "sg:address":"2769 Coral Way",
    "sg:city":"Coral Gables",
    "sg:classifiers":[
        {
            "category":"Deli",
            "type":"Food & Drink"
        }
    ],
    "sg:phone":"+1 305 567 1513",
    "sg:postcode":"33145",
    "sg:province":"FL",
    "wof:name":"Pan Factory",
    "wof:placetype":"venue"
},
  "geometry": {"coordinates":[-80.239304,25.750299],"type":"Point"}
}