{
  "type": "Feature",
  "properties": {
    "iso:country":"US",
    "sg:address":"8125 Monetary Dr",
    "sg:city":"Riviera Beach",
    "sg:classifiers":[
        {
            "category":"Wholesale",
            "subcategory":"Electrical",
            "type":"Manufacturing & Wholesale Goods"
        }
    ],
    "sg:phone":"+1 561 881 1177",
    "sg:postcode":"33404",
    "sg:province":"FL",
    "sg:tags":[
        "equipment",
        "lighting",
        "system"
    ],
    "sg:website":"www.watsonlighting.com",
    "wof:name":"John Watson Landscape Illmntn",
    "wof:placetype":"venue"
},
  "geometry": {"coordinates":[-80.09517200000001,26.796464],"type":"Point"}
}