{
  "type": "Feature",
  "properties": {
    "addr:full":"1729 S Woodland Blvd De Land FL 32720",
    "addr:housenumber":"1729",
    "addr:postcode":"32720",
    "addr:street":"S Woodland Blvd",
    "iso:country":"US",
    "sg:address":"1729 S Woodland Blvd",
    "sg:city":"De Land",
    "sg:classifiers":[
        {
            "category":"Retail",
            "subcategory":"Auto Repair",
            "type":"Services"
        }
    ],
    "sg:phone":"+1 386 734 2212",
    "sg:postcode":"32720",
    "sg:province":"FL",
    "sg:tags":[
        "shop",
        "automotive"
    ],
    "wof:name":"Dyno Tune Center",
    "wof:placetype":"venue"
},
  "geometry": {"coordinates":[-81.302525,28.998479],"type":"Point"}
}