{
  "type": "Feature",
  "properties": {
    "iso:country":"US",
    "sg:address":"1885 N Pine Island Rd",
    "sg:city":"Fort Lauderdale",
    "sg:classifiers":[
        {
            "category":"Food & Beverages",
            "subcategory":"Groceries & Convenience Stores",
            "type":"Retail Goods"
        }
    ],
    "sg:phone":"+1 954 474 2999",
    "sg:postcode":"33322",
    "sg:province":"FL",
    "sg:tags":[
        "grocer"
    ],
    "wof:name":"Winn-Dixie",
    "wof:placetype":"venue"
},
  "geometry": {"coordinates":[-80.269482,26.144462],"type":"Point"}
}