{
  "type": "Feature",
  "properties": {
    "addr:full":"1421 NE 42nd St Fort Lauderdale FL 33334",
    "addr:housenumber":"1421",
    "addr:postcode":"33334",
    "addr:street":"Ne 42Nd St",
    "iso:country":"US",
    "sg:address":"1421 NE 42nd St",
    "sg:city":"Fort Lauderdale",
    "sg:classifiers":[
        {
            "category":"Personal",
            "subcategory":"Beauty Salon",
            "type":"Services"
        }
    ],
    "sg:phone":"+1 954 567 9490",
    "sg:postcode":"33334",
    "sg:province":"FL",
    "sg:tags":[
        "shop"
    ],
    "wof:name":"Shanas Hair Design",
    "wof:placetype":"venue"
},
  "geometry": {"coordinates":[-80.129136,26.179189],"type":"Point"}
}