{
  "type": "Feature",
  "properties": {
    "iso:country":"US",
    "sg:address":"12230 NW 21st Ct",
    "sg:city":"Miami",
    "sg:classifiers":[
        {
            "category":"Building & Trades",
            "subcategory":"Construction",
            "type":"Services"
        }
    ],
    "sg:phone":"+1 305 769 7677",
    "sg:postcode":"33167",
    "sg:province":"FL",
    "sg:tags":[
        "house"
    ],
    "wof:name":"Deco Remodeling Services Corp",
    "wof:placetype":"venue"
},
  "geometry": {"coordinates":[-80.233237,25.884527],"type":"Point"}
}