{
  "type": "Feature",
  "properties": {
    "iso:country":"US",
    "sg:address":"5701 Collins Ave",
    "sg:city":"Miami Beach",
    "sg:classifiers":[
        {
            "category":"Professional",
            "subcategory":"Computer Services",
            "type":"Services"
        }
    ],
    "sg:phone":"+1 305 252 6114",
    "sg:postcode":"33140",
    "sg:province":"FL",
    "sg:tags":[
        "programing",
        "custom"
    ],
    "wof:name":"Store On Net Inc",
    "wof:placetype":"venue"
},
  "geometry": {"coordinates":[-80.122152,25.824271],"type":"Point"}
}