{
  "type": "Feature",
  "properties": {
    "iso:country":"US",
    "sg:address":"13902 N Dale Mabry Hwy",
    "sg:city":"Tampa",
    "sg:classifiers":[
        {
            "category":"Wholesale",
            "subcategory":"Electrical",
            "type":"Manufacturing & Wholesale Goods"
        },
        {
            "category":"Building & Trades",
            "subcategory":"Electrical",
            "type":"Services"
        }
    ],
    "sg:phone":"+1 813 960 2270",
    "sg:postcode":"33618",
    "sg:province":"FL",
    "sg:tags":[
        "fan",
        "fans-industrial",
        "part",
        "commercial",
        "blower"
    ],
    "wof:name":"Derek Embody & Co",
    "wof:placetype":"venue"
},
  "geometry": {"coordinates":[-82.50686,28.07237],"type":"Point"}
}