{
  "type": "Feature",
  "properties": {
    "addr:full":"159 S Cochran Rd Geneva FL 32732",
    "addr:housenumber":"159",
    "addr:postcode":"32732",
    "addr:street":"S Cochran Rd",
    "iso:country":"US",
    "sg:address":"159 S Cochran Rd",
    "sg:city":"Geneva",
    "sg:classifiers":[
        {
            "category":"Building & Trades",
            "subcategory":"Construction",
            "type":"Services"
        }
    ],
    "sg:phone":"+1 407 349 9143",
    "sg:postcode":"32732",
    "sg:province":"FL",
    "sg:tags":[
        "contractor"
    ],
    "wof:name":"Kevin Zeman Construction",
    "wof:placetype":"venue"
},
  "geometry": {"coordinates":[-81.14417,28.734487],"type":"Point"}
}