{
  "type": "Feature",
  "properties": {
    "iso:country":"US",
    "sg:address":"16380 NW 84th Ave",
    "sg:city":"Hialeah",
    "sg:classifiers":[
        {
            "category":"Building & Trades",
            "subcategory":"Locksmith",
            "type":"Services"
        }
    ],
    "sg:phone":"+1 305 827 9384",
    "sg:postcode":"33016",
    "sg:province":"FL",
    "sg:tags":[
        "key"
    ],
    "wof:name":"Cal Security Enterprises Inc",
    "wof:placetype":"venue"
},
  "geometry": {"coordinates":[-80.33753400000001,25.922217],"type":"Point"}
}