{
  "type": "Feature",
  "properties": {
    "addr:full":"5051 18th Ave N Saint Petersburg FL 33710",
    "addr:housenumber":"5051",
    "addr:postcode":"33710",
    "addr:street":"18Th Ave N",
    "iso:country":"US",
    "sg:address":"5051 18th Ave N",
    "sg:city":"Saint Petersburg",
    "sg:classifiers":[
        {
            "category":"Home & Garden",
            "subcategory":"Furniture",
            "type":"Retail Goods"
        }
    ],
    "sg:phone":"+1 727 321 3666",
    "sg:postcode":"33710",
    "sg:province":"FL",
    "wof:name":"Gil Lrson Cstm Crfted Cabinets",
    "wof:placetype":"venue"
},
  "geometry": {"coordinates":[-82.702202,27.789137],"type":"Point"}
}