{
  "type": "Feature",
  "properties": {
    "addr:full":"841 Drive Buick Ave Orlando FL 32808",
    "addr:housenumber":"841",
    "addr:postcode":"32808",
    "addr:street":"Drive Buick Ave",
    "iso:country":"US",
    "sg:address":"841 Drive Buick Ave",
    "sg:city":"Orlando",
    "sg:classifiers":[
        {
            "category":"Wholesale",
            "subcategory":"Auto Parts",
            "type":"Manufacturing & Wholesale Goods"
        }
    ],
    "sg:phone":"+1 407 294 1261",
    "sg:postcode":"32808",
    "sg:province":"FL",
    "sg:tags":[
        "tire"
    ],
    "wof:name":"Carrolls Tires",
    "wof:placetype":"venue"
},
  "geometry": {"coordinates":[-81.426751,28.55394],"type":"Point"}
}