{
  "type": "Feature",
  "properties": {
    "iso:country":"US",
    "sg:address":"820 NW 2nd Ave",
    "sg:city":"Pompano Beach",
    "sg:classifiers":[
        {
            "category":"Organizations",
            "subcategory":"Religious Organization",
            "type":"Services"
        }
    ],
    "sg:phone":"+1 954 943 1377",
    "sg:postcode":"33060",
    "sg:province":"FL",
    "sg:tags":[
        "church"
    ],
    "wof:name":"Abyssnian Baptst Church Christ",
    "wof:placetype":"venue"
},
  "geometry": {"coordinates":[-80.124849,26.239975],"type":"Point"}
}