{
  "type": "Feature",
  "properties": {
    "addr:full":"801 Pine Village Ln Naples FL 34108",
    "addr:housenumber":"801",
    "addr:postcode":"34108",
    "addr:street":"Pine Village Ln",
    "iso:country":"US",
    "sg:address":"801 Pine Village Ln",
    "sg:city":"Naples",
    "sg:classifiers":[
        {
            "category":"Building & Trades",
            "subcategory":"Landscaping Services",
            "type":"Services"
        }
    ],
    "sg:phone":"+1 239 596 7046",
    "sg:postcode":"34108",
    "sg:province":"FL",
    "sg:tags":[
        "lawn",
        "maintenance",
        "grounds"
    ],
    "wof:name":"Heritage Lawn & Landscapes",
    "wof:placetype":"venue"
},
  "geometry": {"coordinates":[-81.802111,26.229063],"type":"Point"}
}