{
  "type": "Feature",
  "properties": {
    "addr:full":"3020 NE 15th Ter Fort Lauderdale FL 33334",
    "addr:housenumber":"3020",
    "addr:postcode":"33334",
    "addr:street":"Ne 15Th Ter",
    "iso:country":"US",
    "sg:address":"3020 NE 15th Ter",
    "sg:city":"Fort Lauderdale",
    "sg:classifiers":[
        {
            "category":"Manufacturing",
            "subcategory":"Printing",
            "type":"Manufacturing & Wholesale Goods"
        }
    ],
    "sg:phone":"+1 954 768 9444",
    "sg:postcode":"33334",
    "sg:province":"FL",
    "sg:tags":[
        "lithographic",
        "commercial"
    ],
    "wof:name":"Print On Demand",
    "wof:placetype":"venue"
},
  "geometry": {"coordinates":[-80.127004,26.165148],"type":"Point"}
}