{
  "type": "Feature",
  "properties": {
    "addr:full":"3307 Dereck Ct Winter Park FL 32792",
    "addr:housenumber":"3307",
    "addr:postcode":"32792",
    "addr:street":"Dereck Ct",
    "iso:country":"US",
    "sg:address":"3307 Dereck Ct",
    "sg:city":"Winter Park",
    "sg:classifiers":[
        {
            "category":"Manufacturing",
            "subcategory":"Tools & Machinery",
            "type":"Manufacturing & Wholesale Goods"
        }
    ],
    "sg:phone":"+1 407 677 7165",
    "sg:postcode":"32792",
    "sg:province":"FL",
    "sg:tags":[
        "turbine",
        "wind",
        "mfg"
    ],
    "wof:name":"Windmills of Holland Inc",
    "wof:placetype":"venue"
},
  "geometry": {"coordinates":[-81.288242,28.630721],"type":"Point"}
}