{
  "type": "Feature",
  "properties": {
    "iso:country":"US",
    "sg:address":"6644 Rowan Rd",
    "sg:city":"New Port Richey",
    "sg:classifiers":[
        {
            "category":"Shopping",
            "subcategory":"Computers & Home Electronics",
            "type":"Retail Goods"
        }
    ],
    "sg:phone":"+1 727 853 0256",
    "sg:postcode":"34653",
    "sg:province":"FL",
    "sg:tags":[
        "communications"
    ],
    "wof:name":"Fleeman Anderson & Bird Corp",
    "wof:placetype":"venue"
},
  "geometry": {"coordinates":[-82.699029,28.256318],"type":"Point"}
}