{
  "type": "Feature",
  "properties": {
    "addr:full":"205 S Charlene Dr Panama City FL 32404",
    "addr:housenumber":"205",
    "addr:postcode":"32404",
    "addr:street":"S Charlene Dr",
    "iso:country":"US",
    "sg:address":"205 S Charlene Dr",
    "sg:city":"Panama City",
    "sg:classifiers":[
        {
            "category":"Building & Trades",
            "subcategory":"Construction",
            "type":"Services"
        }
    ],
    "sg:phone":"+1 850 871 4860",
    "sg:postcode":"32404",
    "sg:province":"FL",
    "sg:tags":[
        "water",
        "well",
        "drilling"
    ],
    "wof:name":"Fontaine Drilling",
    "wof:placetype":"venue"
},
  "geometry": {"coordinates":[-85.581863,30.139134],"type":"Point"}
}