{
  "type": "Feature",
  "properties": {
    "addr:full":"6134 Hollywood Blvd Pembroke Pines FL 33024",
    "addr:housenumber":"6134",
    "addr:postcode":"33024",
    "addr:street":"Hollywood Blvd",
    "iso:country":"US",
    "sg:address":"6134 Hollywood Blvd",
    "sg:city":"Pembroke Pines",
    "sg:classifiers":[
        {
            "category":"Professional",
            "subcategory":"Business Services",
            "type":"Services"
        }
    ],
    "sg:phone":"+1 305 624 7822",
    "sg:postcode":"33024",
    "sg:province":"FL",
    "sg:tags":[
        "paging",
        "answering"
    ],
    "wof:name":"A-Ring-A-Ding Telephone",
    "wof:placetype":"venue"
},
  "geometry": {"coordinates":[-80.210538,26.01004],"type":"Point"}
}