{
  "type": "Feature",
  "properties": {
    "addr:full":"1020 11th Pl Vero Beach FL 32960",
    "addr:housenumber":"1020",
    "addr:postcode":"32960",
    "addr:street":"11Th Pl",
    "iso:country":"US",
    "sg:address":"1020 11th Pl",
    "sg:city":"Vero Beach",
    "sg:classifiers":[
        {
            "category":"Building & Trades",
            "subcategory":"Construction",
            "type":"Services"
        }
    ],
    "sg:phone":"+1 772 569 0936",
    "sg:postcode":"32960",
    "sg:province":"FL",
    "sg:tags":[
        "maker",
        "cabinet"
    ],
    "wof:name":"Jim Baird Custom Cabinets",
    "wof:placetype":"venue"
},
  "geometry": {"coordinates":[-80.39274399999999,27.622244],"type":"Point"}
}