{
  "type": "Feature",
  "properties": {
    "iso:country":"US",
    "sg:address":"5850 8th St SW",
    "sg:city":"West Miami",
    "sg:classifiers":[
        {
            "category":"Wholesale",
            "subcategory":"Medical Equipment & Supplies",
            "type":"Manufacturing & Wholesale Goods"
        }
    ],
    "sg:phone":"+1 305 265 8683",
    "sg:postcode":"33144",
    "sg:province":"FL",
    "sg:tags":[
        "physician",
        "surgeon"
    ],
    "wof:name":"M A Medical Supply Inc",
    "wof:placetype":"venue"
},
  "geometry": {"coordinates":[-80.29127,25.763469],"type":"Point"}
}