{
  "type": "Feature",
  "properties": {
    "iso:country":"US",
    "sg:address":"1118 SW 1st St",
    "sg:city":"Miami",
    "sg:classifiers":[
        {
            "category":"Wholesale",
            "subcategory":"Non-durable Goods",
            "type":"Manufacturing & Wholesale Goods"
        }
    ],
    "sg:phone":"+1 305 324 5906",
    "sg:postcode":"33130",
    "sg:province":"FL",
    "sg:tags":[
        "dry",
        "goods-wholesale"
    ],
    "wof:name":"Pool Star Supply",
    "wof:placetype":"venue"
},
  "geometry": {"coordinates":[-80.21323700000001,25.772561],"type":"Point"}
}