{
  "type": "Feature",
  "properties": {
    "iso:country":"US",
    "sg:address":"3241 Thomas St",
    "sg:city":"Jacksonville",
    "sg:classifiers":[
        {
            "category":"Building & Trades",
            "subcategory":"Construction",
            "type":"Services"
        }
    ],
    "sg:phone":"+1 904 384 9386",
    "sg:postcode":"32254",
    "sg:province":"FL",
    "sg:tags":[
        "hanging",
        "contractor"
    ],
    "wof:name":"Cmd Painting Service",
    "wof:placetype":"venue"
},
  "geometry": {"coordinates":[-81.711096,30.326653],"type":"Point"}
}