{
  "type": "Feature",
  "properties": {
    "addr:full":"11100 4th St N St Petersburg FL 33716",
    "addr:housenumber":"11100",
    "addr:postcode":"33716",
    "addr:street":"4Th St N",
    "iso:country":"US",
    "sg:address":"11100 4th St N",
    "sg:city":"St Petersburg",
    "sg:classifiers":[
        {
            "category":"Food & Beverages",
            "subcategory":"Groceries & Convenience Stores",
            "type":"Retail Goods"
        }
    ],
    "sg:phone":"+1 727 577 7095",
    "sg:postcode":"33716",
    "sg:province":"FL",
    "sg:tags":[
        "grocer"
    ],
    "wof:name":"Winn-Dixie",
    "wof:placetype":"venue"
},
  "geometry": {"coordinates":[-82.63878699999999,27.873797],"type":"Point"}
}