{
  "type": "Feature",
  "properties": {
    "iso:country":"US",
    "sg:address":"918 SE 25th St",
    "sg:city":"Hialeah",
    "sg:classifiers":[
        {
            "category":"Banks & Credit Unions",
            "subcategory":"Bank",
            "type":"Services"
        }
    ],
    "sg:phone":"+1 305 691 2247",
    "sg:postcode":"33019",
    "sg:province":"FL",
    "sg:tags":[
        "cashing",
        "check"
    ],
    "wof:name":"Hialeah Check Cashing",
    "wof:placetype":"venue"
},
  "geometry": {"coordinates":[-80.124618,26.092113],"type":"Point"}
}