{
  "type": "Feature",
  "properties": {
    "addr:full":"2922 York Rd Saint James City FL 33956",
    "addr:housenumber":"2922",
    "addr:postcode":"33956",
    "addr:street":"York Rd",
    "iso:country":"US",
    "sg:address":"2922 York Rd",
    "sg:city":"Saint James City",
    "sg:classifiers":[
        {
            "category":"Taxi",
            "type":"Transportation"
        }
    ],
    "sg:phone":"+1 239 283 7777",
    "sg:postcode":"33956",
    "sg:province":"FL",
    "sg:tags":[
        "taxicab"
    ],
    "wof:name":"Pine Island Taxi & Limo Inc",
    "wof:placetype":"venue"
},
  "geometry": {"coordinates":[-82.083613,26.503747],"type":"Point"}
}