{
  "type": "Feature",
  "properties": {
    "iso:country":"US",
    "sg:address":"795 NE 127th St",
    "sg:city":"North Miami",
    "sg:classifiers":[
        {
            "category":"Health Services",
            "subcategory":"Chiropractor",
            "type":"Services"
        }
    ],
    "sg:phone":"+1 305 895 6408",
    "sg:postcode":"33161",
    "sg:province":"FL",
    "wof:name":"Chiropractic Radiology Consultant",
    "wof:placetype":"venue"
},
  "geometry": {"coordinates":[-80.18289900000001,25.8923],"type":"Point"}
}