{
  "type": "Feature",
  "properties": {
    "iso:country":"US",
    "sg:address":"3661 S Miami Ave",
    "sg:city":"Miami",
    "sg:classifiers":[
        {
            "category":"Health Services",
            "subcategory":"Doctor",
            "type":"Services"
        }
    ],
    "sg:phone":"+1 305 854 0302",
    "sg:postcode":"33133",
    "sg:province":"FL",
    "sg:tags":[
        "physician",
        "surgeon",
        "anesthesiology",
        "surgeons"
    ],
    "wof:name":"Biscayne Anesthesia Group",
    "wof:placetype":"venue"
},
  "geometry": {"coordinates":[-80.215945,25.743553],"type":"Point"}
}