{
  "type": "Feature",
  "properties": {
    "addr:full":"12832 SW 209th St Miami FL 33177",
    "addr:housenumber":"12832",
    "addr:postcode":"33177",
    "addr:street":"Sw 209Th St",
    "iso:country":"US",
    "sg:address":"12832 SW 209th St",
    "sg:city":"Miami",
    "sg:classifiers":[
        {
            "category":"Building & Trades",
            "subcategory":"Construction",
            "type":"Services"
        }
    ],
    "sg:phone":"+1 305 238 4281",
    "sg:postcode":"33177",
    "sg:province":"FL",
    "sg:tags":[
        "roofing",
        "contractor"
    ],
    "wof:name":"Bulls Eye Roofing",
    "wof:placetype":"venue"
},
  "geometry": {"coordinates":[-80.399818,25.572569],"type":"Point"}
}