{
  "type": "Feature",
  "properties": {
    "addr:full":"100 Juniper Ln Longwood FL 32779",
    "addr:housenumber":"100",
    "addr:postcode":"32779",
    "addr:street":"Juniper Ln",
    "iso:country":"US",
    "sg:address":"100 Juniper Ln",
    "sg:city":"Longwood",
    "sg:classifiers":[
        {
            "category":"Professional",
            "subcategory":"Printing & Photocopies",
            "type":"Services"
        }
    ],
    "sg:phone":"+1 407 619 5813",
    "sg:postcode":"32779",
    "sg:province":"FL",
    "sg:tags":[
        "photographers-commercial"
    ],
    "wof:name":"Jj Hill Photography",
    "wof:placetype":"venue"
},
  "geometry": {"coordinates":[-81.39579000000001,28.694429],"type":"Point"}
}