{
  "type": "Feature",
  "properties": {
    "addr:full":"2215 N Commerce Pkwy Weston FL 33326",
    "addr:housenumber":"2215",
    "addr:postcode":"33326",
    "addr:street":"N Commerce Pkwy",
    "iso:country":"US",
    "sg:address":"2215 N Commerce Pkwy",
    "sg:city":"Weston",
    "sg:classifiers":[
        {
            "category":"Shopping",
            "subcategory":"Pets & Pet Supplies",
            "type":"Retail Goods"
        },
        {
            "category":"Retail",
            "subcategory":"Animal Services",
            "type":"Services"
        }
    ],
    "sg:phone":"+1 954 217 7050",
    "sg:postcode":"33326",
    "sg:province":"FL",
    "sg:tags":[
        "grooming",
        "specialty"
    ],
    "wof:name":"Just About Dogs & Cats Corp",
    "wof:placetype":"venue"
},
  "geometry": {"coordinates":[-80.370525,26.09139],"type":"Point"}
}