{
  "type": "Feature",
  "properties": {
    "addr:full":"2478 Inland Cove Rd Palm Beach Gardens FL 33410",
    "addr:housenumber":"2478",
    "addr:postcode":"33410",
    "addr:street":"Inland Cove Rd",
    "iso:country":"US",
    "sg:address":"2478 Inland Cove Rd",
    "sg:city":"Palm Beach Gardens",
    "sg:classifiers":[
        {
            "category":"Shopping",
            "type":"Retail Goods"
        }
    ],
    "sg:phone":"+1 561 624 9774",
    "sg:postcode":"33410",
    "sg:province":"FL",
    "sg:tags":[
        "merchandise"
    ],
    "wof:name":"Work of Arts",
    "wof:placetype":"venue"
},
  "geometry": {"coordinates":[-80.071732,26.858704],"type":"Point"}
}