{
  "type": "Feature",
  "properties": {
    "addr:full":"1331 S Killian Dr Palm Beach Gdns FL 33403",
    "addr:housenumber":"1331",
    "addr:postcode":"33403",
    "addr:street":"S Killian Dr Palm",
    "iso:country":"US",
    "sg:address":"1331 S Killian Dr",
    "sg:city":"Palm Beach Gdns",
    "sg:classifiers":[
        {
            "category":"Manufacturing",
            "subcategory":"Tools & Machinery",
            "type":"Manufacturing & Wholesale Goods"
        }
    ],
    "sg:phone":"+1 561 848 3333",
    "sg:postcode":"33403",
    "sg:province":"FL",
    "sg:tags":[
        "lift",
        "boat"
    ],
    "wof:name":"Vogell Marine Inc",
    "wof:placetype":"venue"
},
  "geometry": {"coordinates":[-80.081733,26.804455],"type":"Point"}
}