{
  "type": "Feature",
  "properties": {
    "iso:country":"US",
    "sg:address":"1203 W Highway 50",
    "sg:city":"Clermont",
    "sg:classifiers":[
        {
            "category":"Social Services",
            "type":"Services"
        },
        {
            "category":"Organizations",
            "subcategory":"Non-profit Organization",
            "type":"Services"
        }
    ],
    "sg:phone":"+1 407 243 8330",
    "sg:postcode":"34711",
    "sg:province":"FL",
    "sg:tags":[
        "charity",
        "foundations-educational",
        "philanthropic",
        "research"
    ],
    "sg:website":"http://www.habitat.org",
    "wof:name":"Habitat for Humanity",
    "wof:placetype":"venue"
},
  "geometry": {"coordinates":[-81.77574199999999,28.552942],"type":"Point"}
}