{
  "type": "Feature",
  "properties": {
    "addr:full":"1620 Lakeshore Cir Fort Lauderdale FL 33326",
    "addr:housenumber":"1620",
    "addr:postcode":"33326",
    "addr:street":"Lakeshore Cir",
    "iso:country":"US",
    "sg:address":"1620 Lakeshore Cir",
    "sg:city":"Fort Lauderdale",
    "sg:classifiers":[
        {
            "category":"Insurance",
            "subcategory":"Life Insurance",
            "type":"Services"
        }
    ],
    "sg:phone":"+1 954 384 1017",
    "sg:postcode":"33326",
    "sg:province":"FL",
    "sg:tags":[
        "carrier"
    ],
    "wof:name":"P R CLU",
    "wof:placetype":"venue"
},
  "geometry": {"coordinates":[-80.370225,26.099225],"type":"Point"}
}