{
  "type": "Feature",
  "properties": {
    "iso:country":"US",
    "sg:address":"9595 Sunbeam Center Dr",
    "sg:city":"Jacksonville",
    "sg:classifiers":[
        {
            "category":"Wholesale",
            "subcategory":"Electrical",
            "type":"Manufacturing & Wholesale Goods"
        }
    ],
    "sg:phone":"+1 904 262 6601",
    "sg:postcode":"32257",
    "sg:province":"FL",
    "sg:tags":[
        "construction",
        "supply"
    ],
    "wof:name":"Duval Electrical & Breaker Sls",
    "wof:placetype":"venue"
},
  "geometry": {"coordinates":[-81.58157,30.204304],"type":"Point"}
}