{
  "type": "Feature",
  "properties": {
    "addr:full":"455 NW 47th Ave Miami FL 33126",
    "addr:housenumber":"455",
    "addr:postcode":"33126",
    "addr:street":"Nw 47Th Ave",
    "iso:country":"US",
    "sg:address":"455 NW 47th Ave",
    "sg:city":"Miami",
    "sg:classifiers":[
        {
            "category":"Government",
            "subcategory":"Office",
            "type":"Public Place"
        }
    ],
    "sg:phone":"+1 305 461 7203",
    "sg:postcode":"33126",
    "sg:province":"FL",
    "sg:tags":[
        "conservation",
        "wildlife",
        "land",
        "local",
        "mineral"
    ],
    "wof:name":"Parks & Recreation Dept",
    "wof:placetype":"venue"
},
  "geometry": {"coordinates":[-80.271807,25.777176],"type":"Point"}
}