{
  "type": "Feature",
  "properties": {
    "addr:full":"11117 N Okeechobee Rd Hialeah FL 33018",
    "addr:housenumber":"11117",
    "addr:postcode":"33018",
    "addr:street":"N Okeechobee Rd",
    "iso:country":"US",
    "sg:address":"11117 N Okeechobee Rd",
    "sg:city":"Hialeah",
    "sg:classifiers":[
        {
            "category":"Manufacturing",
            "subcategory":"Furniture",
            "type":"Manufacturing & Wholesale Goods"
        }
    ],
    "sg:phone":"+1 305 887 9990",
    "sg:postcode":"33018",
    "sg:province":"FL",
    "sg:tags":[
        "sales"
    ],
    "wof:name":"Artistic Kitchen Interiors",
    "wof:placetype":"venue"
},
  "geometry": {"coordinates":[-80.347314,25.872626],"type":"Point"}
}