{
  "type": "Feature",
  "properties": {
    "iso:country":"US",
    "sg:address":"14350 NW 24th Ave",
    "sg:city":"Opa Locka",
    "sg:classifiers":[
        {
            "category":"Retail",
            "subcategory":"Auto Repair",
            "type":"Services"
        }
    ],
    "sg:phone":"+1 305 688 0446",
    "sg:postcode":"33054",
    "sg:province":"FL",
    "sg:tags":[
        "truck"
    ],
    "wof:name":"A & S Quality Tune Inc",
    "wof:placetype":"venue"
},
  "geometry": {"coordinates":[-80.239915,25.905425],"type":"Point"}
}