{
  "type": "Feature",
  "properties": {
    "addr:full":"5920 Collins Rd Jacksonville FL 32244",
    "addr:housenumber":"5920",
    "addr:postcode":"32244",
    "addr:street":"Collins Rd",
    "iso:country":"US",
    "sg:address":"5920 Collins Rd",
    "sg:city":"Jacksonville",
    "sg:classifiers":[
        {
            "category":"Organizations",
            "subcategory":"Community Association",
            "type":"Services"
        }
    ],
    "sg:phone":"+1 904 771 6732",
    "sg:postcode":"32244",
    "sg:province":"FL",
    "sg:tags":[
        "fraternal"
    ],
    "wof:name":"Elks Lodge",
    "wof:placetype":"venue"
},
  "geometry": {"coordinates":[-81.73447,30.20299],"type":"Point"}
}