{
  "type": "Feature",
  "properties": {
    "addr:full":"3484 Chase Ave Miami Beach FL 33140",
    "addr:housenumber":"3484",
    "addr:postcode":"33140",
    "addr:street":"Chase Ave",
    "iso:country":"US",
    "sg:address":"3484 Chase Ave",
    "sg:city":"Miami Beach",
    "sg:classifiers":[
        {
            "category":"Shopping",
            "subcategory":"Musical Instruments",
            "type":"Retail Goods"
        }
    ],
    "sg:phone":"+1 305 538 1771",
    "sg:postcode":"33140",
    "sg:province":"FL",
    "wof:name":"South Beach Music Exchange",
    "wof:placetype":"venue"
},
  "geometry": {"coordinates":[-80.13262400000001,25.810095],"type":"Point"}
}