{
  "type": "Feature",
  "properties": {
    "iso:country":"US",
    "sg:address":"1400 Cassat Ave",
    "sg:city":"Jacksonville",
    "sg:classifiers":[
        {
            "category":"Insurance",
            "subcategory":"Insurance Agent",
            "type":"Services"
        }
    ],
    "sg:phone":"+1 904 384 6443",
    "sg:postcode":"32205",
    "sg:province":"FL",
    "wof:name":"Allstate Insurance",
    "wof:placetype":"venue"
},
  "geometry": {"coordinates":[-81.73044899999999,30.295621],"type":"Point"}
}