{
  "type": "Feature",
  "properties": {
    "iso:country":"US",
    "sg:address":"110 W Pasco Ln",
    "sg:city":"Cocoa Beach",
    "sg:classifiers":[
        {
            "category":"Building & Trades",
            "subcategory":"Construction",
            "type":"Services"
        }
    ],
    "sg:phone":"+1 321 784 5413",
    "sg:postcode":"32931",
    "sg:province":"FL",
    "sg:tags":[
        "house"
    ],
    "wof:name":"Anthony Clark Construction",
    "wof:placetype":"venue"
},
  "geometry": {"coordinates":[-80.609396,28.363957],"type":"Point"}
}