{
  "type": "Feature",
  "properties": {
    "iso:country":"US",
    "sg:address":"5200 NW 64th Ter",
    "sg:city":"Lauderhill",
    "sg:classifiers":[
        {
            "category":"Real Estate",
            "subcategory":"Real Estate Services",
            "type":"Services"
        },
        {
            "category":"Real Estate",
            "subcategory":"Real Estate Agent",
            "type":"Services"
        }
    ],
    "sg:phone":"+1 954 457 8700",
    "sg:postcode":"33319",
    "sg:province":"FL",
    "sg:tags":[
        "management"
    ],
    "wof:name":"Irving Group Inc",
    "wof:placetype":"venue"
},
  "geometry": {"coordinates":[-80.236603,26.19042],"type":"Point"}
}