{
  "type": "Feature",
  "properties": {
    "iso:country":"US",
    "sg:address":"3700 S Hopkins Ave",
    "sg:city":"Titusville",
    "sg:classifiers":[
        {
            "category":"Manufacturing",
            "subcategory":"Electronics",
            "type":"Manufacturing & Wholesale Goods"
        },
        {
            "category":"Professional",
            "subcategory":"Printing & Photocopies",
            "type":"Services"
        }
    ],
    "sg:phone":"+1 321 267 9294",
    "sg:postcode":"32780",
    "sg:province":"FL",
    "sg:tags":[
        "printers-equipment",
        "services-commercial",
        "supply"
    ],
    "sg:website":"http://www.finelineprint.net",
    "wof:name":"Fineline Printing",
    "wof:placetype":"venue"
},
  "geometry": {"coordinates":[-80.803543,28.57205],"type":"Point"}
}