{
  "type": "Feature",
  "properties": {
    "addr:full":"105 Waynel Cir SE Fort Walton Bch FL 32548",
    "addr:housenumber":"105",
    "addr:postcode":"32548",
    "addr:street":"Waynel Cir Se Fort",
    "iso:country":"US",
    "sg:address":"105 Waynel Cir SE",
    "sg:city":"Fort Walton Bch",
    "sg:classifiers":[
        {
            "category":"Building & Trades",
            "subcategory":"Construction",
            "type":"Services"
        }
    ],
    "sg:phone":"+1 850 243 3280",
    "sg:postcode":"32548",
    "sg:province":"FL",
    "sg:tags":[
        "tile",
        "dealer",
        "contractor"
    ],
    "wof:name":"Hembree Tile",
    "wof:placetype":"venue"
},
  "geometry": {"coordinates":[-86.596509,30.409708],"type":"Point"}
}