{
  "type": "Feature",
  "properties": {
    "addr:full":"1592 SE Village Green Dr Port St Lucie FL 34952",
    "addr:housenumber":"1592",
    "addr:postcode":"34952",
    "addr:street":"Se Village Green Dr",
    "iso:country":"US",
    "sg:address":"1592 SE Village Green Dr",
    "sg:city":"Port St Lucie",
    "sg:classifiers":[
        {
            "category":"Manufacturing",
            "subcategory":"Furniture",
            "type":"Manufacturing & Wholesale Goods"
        },
        {
            "category":"Building & Trades",
            "subcategory":"Construction",
            "type":"Services"
        }
    ],
    "sg:phone":"+1 772 335 5980",
    "sg:postcode":"34952",
    "sg:province":"FL",
    "sg:tags":[
        "cabinet",
        "maker",
        "mfg"
    ],
    "wof:name":"B & M Cabinets",
    "wof:placetype":"venue"
},
  "geometry": {"coordinates":[-80.304315,27.305845],"type":"Point"}
}