{
  "type": "Feature",
  "properties": {
    "iso:country":"US",
    "sg:address":"4531 Oak Fair Blvd",
    "sg:city":"Tampa",
    "sg:classifiers":[
        {
            "category":"Freight",
            "type":"Transportation"
        }
    ],
    "sg:phone":"+1 813 612 9372",
    "sg:postcode":"33610",
    "sg:province":"FL",
    "sg:tags":[
        "distance",
        "trucking-heavy",
        "hauling",
        "long",
        "trucking"
    ],
    "wof:name":"Ralph Transfer Co Inc",
    "wof:placetype":"venue"
},
  "geometry": {"coordinates":[-82.35644000000001,27.987211],"type":"Point"}
}