{
  "type": "Feature",
  "properties": {
    "addr:full":"389 US Hwy 92 Longwood FL 32750",
    "addr:housenumber":"389",
    "addr:postcode":"32750",
    "addr:street":"Us Hwy 92",
    "iso:country":"US",
    "sg:address":"389 US Hwy 92",
    "sg:city":"Longwood",
    "sg:classifiers":[
        {
            "category":"Autos & Motor Vehicles",
            "subcategory":"Auto Supplies",
            "type":"Retail Goods"
        }
    ],
    "sg:phone":"+1 407 699 5309",
    "sg:postcode":"32750",
    "sg:province":"FL",
    "sg:tags":[
        "automotive",
        "parts",
        "tire"
    ],
    "wof:name":"Two Guys Discount Tire Battery",
    "wof:placetype":"venue"
},
  "geometry": {"coordinates":[-81.326792,28.701465],"type":"Point"}
}