{
  "type": "Feature",
  "properties": {
    "iso:country":"US",
    "sg:address":"5101 Le Tourneau Cir",
    "sg:city":"Tampa",
    "sg:classifiers":[
        {
            "category":"Organizations",
            "subcategory":"Non-profit Organization",
            "type":"Services"
        },
        {
            "category":"Professional",
            "subcategory":"Business Services",
            "type":"Services"
        }
    ],
    "sg:phone":"+1 813 664 0410",
    "sg:postcode":"33610",
    "sg:province":"FL",
    "sg:tags":[
        "fund",
        "counselor",
        "raising"
    ],
    "sg:website":"www.advantagefundraising.com",
    "wof:name":"Advantage Fund Raising",
    "wof:placetype":"venue"
},
  "geometry": {"coordinates":[-82.397666,27.994262],"type":"Point"}
}