{
  "type": "Feature",
  "properties": {
    "addr:full":"2600 W Flagler St Miami FL 33135",
    "addr:housenumber":"2600",
    "addr:postcode":"33135",
    "addr:street":"W Flagler St",
    "iso:country":"US",
    "sg:address":"2600 W Flagler St",
    "sg:city":"Miami",
    "sg:classifiers":[
        {
            "category":"Shopping",
            "subcategory":"Pharmacy",
            "type":"Retail Goods"
        }
    ],
    "sg:phone":"+1 305 541 1818",
    "sg:postcode":"33135",
    "sg:province":"FL",
    "wof:name":"United Healthcare",
    "wof:placetype":"venue"
},
  "geometry": {"coordinates":[-80.238652,25.772273],"type":"Point"}
}