{
  "type": "Feature",
  "properties": {
    "addr:full":"20 Mayfair Dr Crawfordville FL 32327",
    "addr:housenumber":"20",
    "addr:postcode":"32327",
    "addr:street":"Mayfair Dr",
    "iso:country":"US",
    "sg:address":"20 Mayfair Dr",
    "sg:city":"Crawfordville",
    "sg:classifiers":[
        {
            "category":"Building & Trades",
            "subcategory":"Construction",
            "type":"Services"
        }
    ],
    "sg:phone":"+1 850 926 5217",
    "sg:postcode":"32327",
    "sg:province":"FL",
    "sg:tags":[
        "contractor",
        "painting",
        "hanging"
    ],
    "wof:name":"Ison Painting",
    "wof:placetype":"venue"
},
  "geometry": {"coordinates":[-84.375405,30.221419],"type":"Point"}
}