{
  "type": "Feature",
  "properties": {
    "addr:full":"411 Reid Ave Port St Joe FL 32456",
    "addr:housenumber":"411",
    "addr:postcode":"32456",
    "addr:street":"Reid Ave",
    "iso:country":"US",
    "sg:address":"411 Reid Ave",
    "sg:city":"Port St Joe",
    "sg:classifiers":[
        {
            "category":"Professional",
            "subcategory":"Research",
            "type":"Services"
        }
    ],
    "sg:phone":"+1 850 227 3488",
    "sg:postcode":"32456",
    "sg:province":"FL",
    "wof:name":"Ecological Research Conslnt",
    "wof:placetype":"venue"
},
  "geometry": {"coordinates":[-85.302537,29.812102],"type":"Point"}
}