{
  "type": "Feature",
  "properties": {
    "addr:full":"1029 Barnwell Rd Fernandina Beach FL 32034",
    "addr:housenumber":"1029",
    "addr:postcode":"32034",
    "addr:street":"Barnwell Rd",
    "iso:country":"US",
    "sg:address":"1029 Barnwell Rd",
    "sg:city":"Fernandina Beach",
    "sg:classifiers":[
        {
            "category":"Building & Trades",
            "subcategory":"Construction",
            "type":"Services"
        }
    ],
    "sg:phone":"+1 904 261 8588",
    "sg:postcode":"32034",
    "sg:province":"FL",
    "sg:tags":[
        "contractor"
    ],
    "wof:name":"Claxton Contracting Inc",
    "wof:placetype":"venue"
},
  "geometry": {"coordinates":[-81.516898,30.631743],"type":"Point"}
}