{
  "type": "Feature",
  "properties": {
    "addr:full":"2100 N Powerline Rd Pompano Beach FL 33069",
    "addr:housenumber":"2100",
    "addr:postcode":"33069",
    "addr:street":"N Powerline Rd",
    "iso:country":"US",
    "sg:address":"2100 N Powerline Rd",
    "sg:city":"Pompano Beach",
    "sg:classifiers":[
        {
            "category":"Shopping",
            "subcategory":"Clothing, Apparel, & Fashions",
            "type":"Retail Goods"
        }
    ],
    "sg:phone":"+1 954 960 0148",
    "sg:postcode":"33069",
    "sg:province":"FL",
    "sg:tags":[
        "t"
    ],
    "wof:name":"Silk Screen Machine Co",
    "wof:placetype":"venue"
},
  "geometry": {"coordinates":[-80.15169899999999,26.257434],"type":"Point"}
}