{
  "type": "Feature",
  "properties": {
    "iso:country":"US",
    "sg:address":"1221 Nelson St",
    "sg:city":"Dunedin",
    "sg:classifiers":[
        {
            "category":"Building & Trades",
            "subcategory":"Construction",
            "type":"Services"
        }
    ],
    "sg:phone":"+1 727 733 5316",
    "sg:postcode":"34698",
    "sg:province":"FL",
    "sg:tags":[
        "contractor"
    ],
    "wof:name":"Accurate Lines Inc",
    "wof:placetype":"venue"
},
  "geometry": {"coordinates":[-82.774849,28.045469],"type":"Point"}
}