{
  "type": "Feature",
  "properties": {
    "addr:full":"410 Main St Safety Harbor FL 34695",
    "addr:housenumber":"410",
    "addr:postcode":"34695",
    "addr:street":"Main St",
    "iso:country":"US",
    "sg:address":"410 Main St",
    "sg:city":"Safety Harbor",
    "sg:classifiers":[
        {
            "category":"Personal",
            "subcategory":"Beauty Salon",
            "type":"Services"
        }
    ],
    "sg:phone":"+1 727 734 9629",
    "sg:postcode":"34695",
    "sg:province":"FL",
    "wof:name":"Hair By Timmie",
    "wof:placetype":"venue"
},
  "geometry": {"coordinates":[-82.692132,27.990718],"type":"Point"}
}