{
  "type": "Feature",
  "properties": {
    "iso:country":"US",
    "sg:address":"8032 Lone Star Rd",
    "sg:city":"Jacksonville",
    "sg:classifiers":[
        {
            "category":"Retail",
            "subcategory":"Laundry & Dry Cleaning",
            "type":"Services"
        }
    ],
    "sg:phone":"+1 904 724 0180",
    "sg:postcode":"32211",
    "sg:province":"FL",
    "sg:tags":[
        "cleaners"
    ],
    "wof:name":"C J Cleaners",
    "wof:placetype":"venue"
},
  "geometry": {"coordinates":[-81.57168299999999,30.33757],"type":"Point"}
}