{
  "type": "Feature",
  "properties": {
    "addr:full":"1833 E Edgewood Dr Lakeland FL 33803",
    "addr:housenumber":"1833",
    "addr:postcode":"33803",
    "addr:street":"E Edgewood Dr",
    "iso:country":"US",
    "sg:address":"1833 E Edgewood Dr",
    "sg:city":"Lakeland",
    "sg:classifiers":[
        {
            "category":"Restaurant",
            "type":"Food & Drink"
        }
    ],
    "sg:phone":"+1 863 688 9616",
    "sg:postcode":"33803",
    "sg:province":"FL",
    "sg:tags":[
        "eating"
    ],
    "wof:name":"Mario's Italian Restaurant",
    "wof:placetype":"venue"
},
  "geometry": {"coordinates":[-81.92769,28.011251],"type":"Point"}
}