{
  "type": "Feature",
  "properties": {
    "addr:full":"6105 Royal Birkdale Dr Lake Worth FL 33463",
    "addr:housenumber":"6105",
    "addr:postcode":"33463",
    "addr:street":"Royal Birkdale Dr",
    "iso:country":"US",
    "sg:address":"6105 Royal Birkdale Dr",
    "sg:city":"Lake Worth",
    "sg:classifiers":[
        {
            "category":"Shopping",
            "type":"Retail Goods"
        }
    ],
    "sg:phone":"+1 561 963 2278",
    "sg:postcode":"33463",
    "sg:province":"FL",
    "sg:tags":[
        "merchandise"
    ],
    "wof:name":"Secure Call",
    "wof:placetype":"venue"
},
  "geometry": {"coordinates":[-80.13921999999999,26.581701],"type":"Point"}
}