{
  "type": "Feature",
  "properties": {
    "iso:country":"US",
    "sg:address":"3776 Barrancas Ave",
    "sg:city":"Pensacola",
    "sg:classifiers":[
        {
            "category":"Personal",
            "type":"Services"
        },
        {
            "category":"Personal",
            "subcategory":"Tattoo Parlor",
            "type":"Services"
        }
    ],
    "sg:phone":"+1 850 455 6595",
    "sg:postcode":"32507",
    "sg:province":"FL",
    "sg:tags":[
        "tattooing"
    ],
    "wof:name":"Electric Graffiti",
    "wof:placetype":"venue"
},
  "geometry": {"coordinates":[-87.264707,30.391348],"type":"Point"}
}