{
  "type": "Feature",
  "properties": {
    "addr:full":"652 Capital Cir NE Ste C Tallahassee FL 32301",
    "addr:housenumber":"652",
    "addr:postcode":"32301",
    "addr:street":"Capital Cir Ne Ste C",
    "iso:country":"US",
    "sg:address":"652 Capital Cir NE Ste C",
    "sg:city":"Tallahassee",
    "sg:classifiers":[
        {
            "category":"Personal",
            "type":"Services"
        },
        {
            "category":"Professional",
            "subcategory":"Detective & Security Services",
            "type":"Services"
        },
        {
            "category":"Manufacturing",
            "subcategory":"Electronics",
            "type":"Manufacturing & Wholesale Goods"
        },
        {
            "category":"Shopping",
            "subcategory":"Computers & Home Electronics",
            "type":"Retail Goods"
        },
        {
            "category":"Manufacturing",
            "subcategory":"Building Materials",
            "type":"Manufacturing & Wholesale Goods"
        }
    ],
    "sg:phone":"+1 850 942 1400",
    "sg:postcode":"32301",
    "sg:province":"FL",
    "sg:tags":[
        "control",
        "monitoring",
        "fire",
        "consultant",
        "alarm",
        "system",
        "surveillance",
        "systems-wholesale",
        "equipment",
        "equipment-wholesale",
        "medical",
        "manufacturer"
    ],
    "sg:website":"http://www.certifiedsecuritysystems.com",
    "wof:name":"Certified Security Systems",
    "wof:placetype":"venue"
},
  "geometry": {"coordinates":[-84.226634,30.444985],"type":"Point"}
}