{
  "type": "Feature",
  "properties": {
    "addr:full":"5721 Maple Rd Sebring FL 33875",
    "addr:housenumber":"5721",
    "addr:postcode":"33875",
    "addr:street":"Maple Rd",
    "iso:country":"US",
    "sg:address":"5721 Maple Rd",
    "sg:city":"Sebring",
    "sg:classifiers":[
        {
            "category":"Building & Trades",
            "subcategory":"Landscaping Services",
            "type":"Services"
        }
    ],
    "sg:phone":"+1 863 314 0446",
    "sg:postcode":"33875",
    "sg:province":"FL",
    "sg:tags":[
        "lawn",
        "garden"
    ],
    "wof:name":"Perfection Lawn Care",
    "wof:placetype":"venue"
},
  "geometry": {"coordinates":[-81.488517,27.437127],"type":"Point"}
}