{
  "type": "Feature",
  "properties": {
    "addr:full":"26641 Mondon Hill Rd Brooksville FL 34601",
    "addr:postcode":"26641;34601",
    "addr:street":"Mondon Hill Rd",
    "iso:country":"US",
    "sg:address":"26641 Mondon Hill Rd",
    "sg:city":"Brooksville",
    "sg:classifiers":[
        {
            "category":"Shopping",
            "subcategory":"Computers & Home Electronics",
            "type":"Retail Goods"
        }
    ],
    "sg:phone":"+1 352 796 5299",
    "sg:postcode":"34601",
    "sg:province":"FL",
    "wof:name":"Success Enterprises",
    "wof:placetype":"venue"
},
  "geometry": {"coordinates":[-82.300855,28.542386],"type":"Point"}
}