{
  "type": "Feature",
  "properties": {
    "addr:full":"1807 W Brainerd St Pensacola FL 32501",
    "addr:housenumber":"1807",
    "addr:postcode":"32501",
    "addr:street":"W Brainerd St",
    "iso:country":"US",
    "sg:address":"1807 W Brainerd St",
    "sg:city":"Pensacola",
    "sg:classifiers":[
        {
            "category":"Food & Beverages",
            "subcategory":"Groceries & Convenience Stores",
            "type":"Retail Goods"
        }
    ],
    "sg:phone":"+1 850 433 5041",
    "sg:postcode":"32501",
    "sg:province":"FL",
    "wof:name":"J & E Soda Fountain",
    "wof:placetype":"venue"
},
  "geometry": {"coordinates":[-87.238784,30.424536],"type":"Point"}
}