{
  "type": "Feature",
  "properties": {
    "addr:full":"410 Deltona Blvd Deltona FL 32725",
    "addr:housenumber":"410",
    "addr:postcode":"32725",
    "addr:street":"Deltona Blvd",
    "iso:country":"US",
    "sg:address":"410 Deltona Blvd",
    "sg:city":"Deltona",
    "sg:classifiers":[
        {
            "category":"Restaurant",
            "type":"Food & Drink"
        }
    ],
    "sg:menulink":"http://www.allmenus.com/fl/deltona/187119-mcdonalds/menu/",
    "sg:phone":"+1 407 860 2219",
    "sg:postcode":"32725",
    "sg:province":"FL",
    "sg:tags":[
        "burger",
        "american"
    ],
    "wof:name":"McDonald's",
    "wof:placetype":"venue"
},
  "geometry": {"coordinates":[-81.280908,28.873466],"type":"Point"}
}