{
  "type": "Feature",
  "properties": {
    "iso:country":"US",
    "sg:address":"9028 Old Kings Rd",
    "sg:city":"Jacksonville",
    "sg:classifiers":[
        {
            "category":"Freight",
            "type":"Transportation"
        }
    ],
    "sg:phone":"+1 904 764 7392",
    "sg:postcode":"32219",
    "sg:province":"FL",
    "sg:tags":[
        "operator",
        "trucking"
    ],
    "wof:name":"OQuinn Truck Lines Inc",
    "wof:placetype":"venue"
},
  "geometry": {"coordinates":[-81.75840599999999,30.411158],"type":"Point"}
}