{
  "type": "Feature",
  "properties": {
    "iso:country":"US",
    "sg:address":"6850 Hundred Acre Dr",
    "sg:city":"Cocoa",
    "sg:classifiers":[
        {
            "category":"Structure",
            "subcategory":"Office Building",
            "type":"Public Place"
        }
    ],
    "sg:phone":"+1 321 632 8718",
    "sg:postcode":"32927",
    "sg:province":"FL",
    "sg:tags":[
        "park"
    ],
    "wof:name":"National Property Tracking Systems",
    "wof:placetype":"venue"
},
  "geometry": {"coordinates":[-80.819548,28.478344],"type":"Point"}
}