{
  "type": "Feature",
  "properties": {
    "iso:country":"US",
    "sg:address":"14901 N Blvd",
    "sg:city":"Tampa",
    "sg:classifiers":[
        {
            "category":"Organizations",
            "subcategory":"Religious Organization",
            "type":"Services"
        }
    ],
    "sg:phone":"+1 813 961 6401",
    "sg:postcode":"33613",
    "sg:province":"FL",
    "sg:tags":[
        "church"
    ],
    "wof:name":"North Boulevard Church-Christ",
    "wof:placetype":"venue"
},
  "geometry": {"coordinates":[-82.46780699999999,28.0848],"type":"Point"}
}