{
  "type": "Feature",
  "properties": {
    "addr:full":"9000 Honeywell Rd Gibsonton FL 33534",
    "addr:housenumber":"9000",
    "addr:postcode":"33534",
    "addr:street":"Honeywell Rd",
    "iso:country":"US",
    "sg:address":"9000 Honeywell Rd",
    "sg:city":"Gibsonton",
    "sg:classifiers":[
        {
            "category":"Organizations",
            "subcategory":"Non-profit Organization",
            "type":"Services"
        }
    ],
    "sg:phone":"+1 813 677 1138",
    "sg:postcode":"33534",
    "sg:province":"FL",
    "wof:name":"Women Of The Moose",
    "wof:placetype":"venue"
},
  "geometry": {"coordinates":[-82.356587,27.837144],"type":"Point"}
}