{
  "type": "Feature",
  "properties": {
    "iso:country":"US",
    "sg:address":"9275 NW 32nd Ave",
    "sg:city":"Miami",
    "sg:classifiers":[
        {
            "category":"Organizations",
            "subcategory":"Religious Organization",
            "type":"Services"
        }
    ],
    "sg:phone":"+1 305 694 9631",
    "sg:postcode":"33147",
    "sg:province":"FL",
    "sg:tags":[
        "church"
    ],
    "wof:name":"Now Faith Deliverance",
    "wof:placetype":"venue"
},
  "geometry": {"coordinates":[-80.250283,25.857477],"type":"Point"}
}