{
  "type": "Feature",
  "properties": {
    "addr:full":"2101 Legion Rd Sneads FL 32460",
    "addr:housenumber":"2101",
    "addr:postcode":"32460",
    "addr:street":"Legion Rd",
    "iso:country":"US",
    "sg:address":"2101 Legion Rd",
    "sg:city":"Sneads",
    "sg:classifiers":[
        {
            "category":"Organizations",
            "subcategory":"Community Association",
            "type":"Services"
        }
    ],
    "sg:phone":"+1 850 593 6009",
    "sg:postcode":"32460",
    "sg:province":"FL",
    "sg:tags":[
        "military"
    ],
    "wof:name":"American Legion",
    "wof:placetype":"venue"
},
  "geometry": {"coordinates":[-84.911231,30.720229],"type":"Point"}
}