{
  "type": "Feature",
  "properties": {
    "addr:full":"19575 Biscayne Blvd Ste 810 Miami FL 33180",
    "addr:housenumber":"19575",
    "addr:postcode":"33180",
    "addr:street":"Biscayne Blvd Ste 810",
    "iso:country":"US",
    "sg:address":"19575 Biscayne Blvd Ste 810",
    "sg:city":"Miami",
    "sg:classifiers":[
        {
            "category":"Shopping",
            "subcategory":"Clothing, Apparel, & Fashions",
            "type":"Retail Goods"
        }
    ],
    "sg:phone":"+1 305 466 3390",
    "sg:postcode":"33180",
    "sg:province":"FL",
    "sg:tags":[
        "accessory",
        "clothing",
        "women's"
    ],
    "sg:website":"shop.misssixty.com",
    "wof:name":"Miss Sixty",
    "wof:placetype":"venue"
},
  "geometry": {"coordinates":[-80.14664399999999,25.957889],"type":"Point"}
}