{
  "type": "Feature",
  "properties": {
    "iso:country":"US",
    "sg:address":"2431 Aloma Ave",
    "sg:city":"Winter Park",
    "sg:classifiers":[
        {
            "category":"Wholesale",
            "subcategory":"Machinery & Supplies",
            "type":"Manufacturing & Wholesale Goods"
        }
    ],
    "sg:phone":"+1 407 657 6673",
    "sg:postcode":"32792",
    "sg:province":"FL",
    "sg:tags":[
        "equipment",
        "system",
        "vacuum"
    ],
    "wof:name":"Leybold-Heraeus Inc",
    "wof:placetype":"venue"
},
  "geometry": {"coordinates":[-81.320427,28.601476],"type":"Point"}
}