{
  "type": "Feature",
  "properties": {
    "iso:country":"US",
    "sg:address":"1601 Sanderling Ct",
    "sg:city":"Brandon",
    "sg:classifiers":[
        {
            "category":"Arts & Performance",
            "subcategory":"Theater",
            "type":"Entertainment"
        }
    ],
    "sg:phone":"+1 813 643 8353",
    "sg:postcode":"33511",
    "sg:province":"FL",
    "sg:tags":[
        "group"
    ],
    "wof:name":"Diva DMusica",
    "wof:placetype":"venue"
},
  "geometry": {"coordinates":[-82.31637499999999,27.912713],"type":"Point"}
}