{
  "type": "Feature",
  "properties": {
    "addr:full":"4218 Cleveland Ave Fort Myers FL 33901",
    "addr:housenumber":"4218",
    "addr:postcode":"33901",
    "addr:street":"Cleveland Ave",
    "iso:country":"US",
    "sg:address":"4218 Cleveland Ave",
    "sg:city":"Fort Myers",
    "sg:classifiers":[
        {
            "category":"Insurance",
            "subcategory":"Insurance Agent",
            "type":"Services"
        }
    ],
    "sg:phone":"+1 239 275 1118",
    "sg:postcode":"33901",
    "sg:province":"FL",
    "wof:name":"GE Financial",
    "wof:placetype":"venue"
},
  "geometry": {"coordinates":[-81.871888,26.601502],"type":"Point"}
}