{
  "type": "Feature",
  "properties": {
    "iso:country":"US",
    "sg:address":"4943 SW 75th Ave",
    "sg:city":"Miami",
    "sg:classifiers":[
        {
            "category":"Shopping",
            "subcategory":"Pharmacy",
            "type":"Retail Goods"
        }
    ],
    "sg:phone":"+1 305 663 1002",
    "sg:postcode":"33155",
    "sg:province":"FL",
    "sg:tags":[
        "drugstore"
    ],
    "sg:website":"www.13fi.com",
    "wof:name":"Roberto Suris Gc Corp",
    "wof:placetype":"venue"
},
  "geometry": {"coordinates":[-80.316597,25.7239],"type":"Point"}
}