{
  "type": "Feature",
  "properties": {
    "addr:full":"10191 W Sunrise Blvd Plantation FL 33322",
    "addr:housenumber":"10191",
    "addr:postcode":"33322",
    "addr:street":"W Sunrise Blvd",
    "iso:country":"US",
    "sg:address":"10191 W Sunrise Blvd",
    "sg:city":"Plantation",
    "sg:classifiers":[
        {
            "category":"Personal",
            "subcategory":"Beauty Salon",
            "type":"Services"
        }
    ],
    "sg:phone":"+1 954 749 2829",
    "sg:postcode":"33322",
    "sg:province":"FL",
    "wof:name":"Shimi's Day Spa",
    "wof:placetype":"venue"
},
  "geometry": {"coordinates":[-80.297166,26.145831],"type":"Point"}
}