{
  "type": "Feature",
  "properties": {
    "addr:full":"4531 36th St Orlando FL 32811",
    "addr:housenumber":"4531",
    "addr:postcode":"32811",
    "addr:street":"36Th St",
    "iso:country":"US",
    "sg:address":"4531 36th St",
    "sg:city":"Orlando",
    "sg:classifiers":[
        {
            "category":"Wholesale",
            "subcategory":"Medical Equipment & Supplies",
            "type":"Manufacturing & Wholesale Goods"
        },
        {
            "category":"Shopping",
            "subcategory":"Pharmacy",
            "type":"Retail Goods"
        }
    ],
    "sg:phone":"+1 407 438 8810",
    "sg:postcode":"32811",
    "sg:province":"FL",
    "sg:tags":[
        "physician",
        "refinishing",
        "health",
        "home",
        "surgeon",
        "equipment-repairing",
        "care"
    ],
    "wof:name":"WOM World Of Medicine USA Inc",
    "wof:placetype":"venue"
},
  "geometry": {"coordinates":[-81.437719,28.502542],"type":"Point"}
}