{
  "type": "Feature",
  "properties": {
    "addr:full":"1820 Del Prado Blvd S Cape Coral FL 33990",
    "addr:housenumber":"1820",
    "addr:postcode":"33990",
    "addr:street":"Del Prado Blvd S",
    "iso:country":"US",
    "sg:address":"1820 Del Prado Blvd S",
    "sg:city":"Cape Coral",
    "sg:classifiers":[
        {
            "category":"Autos & Motor Vehicles",
            "subcategory":"Auto Supplies",
            "type":"Retail Goods"
        }
    ],
    "sg:phone":"+1 239 772 0060",
    "sg:postcode":"33990",
    "sg:province":"FL",
    "sg:tags":[
        "tire"
    ],
    "sg:website":"www.midasflorida.com",
    "wof:name":"Midas Auto Service Experts",
    "wof:placetype":"venue"
},
  "geometry": {"coordinates":[-81.941101,26.618799],"type":"Point"}
}