{
  "type": "Feature",
  "properties": {
    "addr:full":"910 SW 75th Ave Miami FL 33144",
    "addr:housenumber":"910",
    "addr:postcode":"33144",
    "addr:street":"Sw 75Th Ave",
    "iso:country":"US",
    "sg:address":"910 SW 75th Ave",
    "sg:city":"Miami",
    "sg:classifiers":[
        {
            "category":"Community Center",
            "type":"Public Place"
        }
    ],
    "sg:phone":"+1 305 261 4167",
    "sg:postcode":"33144",
    "sg:province":"FL",
    "sg:tags":[
        "medical"
    ],
    "wof:name":"R. A. Wellness Medical Center, Inc.",
    "wof:placetype":"venue"
},
  "geometry": {"coordinates":[-80.317386,25.761154],"type":"Point"}
}