{
  "type": "Feature",
  "properties": {
    "addr:full":"19 Fairway Rd Jacksonville Beach FL 32250",
    "addr:housenumber":"19",
    "addr:postcode":"32250",
    "addr:street":"Fairway Rd",
    "iso:country":"US",
    "sg:address":"19 Fairway Rd",
    "sg:city":"Jacksonville Beach",
    "sg:classifiers":[
        {
            "category":"Freight",
            "type":"Transportation"
        }
    ],
    "sg:phone":"+1 904 241 7955",
    "sg:postcode":"32250",
    "sg:province":"FL",
    "sg:tags":[
        "operator",
        "local",
        "trucking"
    ],
    "wof:name":"Bills Pack & Go",
    "wof:placetype":"venue"
},
  "geometry": {"coordinates":[-81.406682,30.271714],"type":"Point"}
}