{
  "type": "Feature",
  "properties": {
    "addr:full":"3121 Beach Blvd S Saint Petersburg FL 33707",
    "addr:housenumber":"3121",
    "addr:postcode":"33707",
    "addr:street":"Beach Blvd S",
    "iso:country":"US",
    "sg:address":"3121 Beach Blvd S",
    "sg:city":"Saint Petersburg",
    "sg:classifiers":[
        {
            "category":"Restaurant",
            "type":"Food & Drink"
        }
    ],
    "sg:menulink":"http://www.allmenus.com/fl/st-petersburg/37972-elements-global-cuisine/menu/",
    "sg:phone":"+1 727 343 9894",
    "sg:postcode":"33707",
    "sg:province":"FL",
    "sg:tags":[
        "american"
    ],
    "wof:name":"Elements Global Cuisine",
    "wof:placetype":"venue"
},
  "geometry": {"coordinates":[-82.70783900000001,27.738274],"type":"Point"}
}