{
  "type": "Feature",
  "properties": {
    "addr:full":"4625 Pine Island Rd NW Cape Coral FL 33993",
    "addr:housenumber":"4625",
    "addr:postcode":"33993",
    "addr:street":"Pine Island Rd Nw",
    "iso:country":"US",
    "sg:address":"4625 Pine Island Rd NW",
    "sg:city":"Cape Coral",
    "sg:classifiers":[
        {
            "category":"Shopping",
            "type":"Retail Goods"
        }
    ],
    "sg:phone":"+1 239 283 6006",
    "sg:postcode":"33993",
    "sg:province":"FL",
    "sg:tags":[
        "art",
        "gallery",
        "merchandise",
        "dealer"
    ],
    "wof:name":"Wildchild Gallery",
    "wof:placetype":"venue"
},
  "geometry": {"coordinates":[-82.071462,26.628558],"type":"Point"}
}