{
  "type": "Feature",
  "properties": {
    "iso:country":"US",
    "sg:address":"891 E Palmetto Park Rd",
    "sg:city":"Boca Raton",
    "sg:classifiers":[
        {
            "category":"Personal",
            "subcategory":"Beauty Salon",
            "type":"Services"
        }
    ],
    "sg:phone":"+1 561 368 8077",
    "sg:postcode":"33432",
    "sg:province":"FL",
    "wof:name":"Carissima Hairstylists",
    "wof:placetype":"venue"
},
  "geometry": {"coordinates":[-80.072918,26.350711],"type":"Point"}
}