{
  "type": "Feature",
  "properties": {
    "iso:country":"US",
    "sg:address":"1475 SW 8th St Apt 505",
    "sg:city":"Miami",
    "sg:classifiers":[
        {
            "category":"Autos & Motor Vehicles",
            "subcategory":"Automobile Sales",
            "type":"Retail Goods"
        }
    ],
    "sg:phone":"+1 305 860 6180",
    "sg:postcode":"33135",
    "sg:province":"FL",
    "sg:tags":[
        "new",
        "used",
        "car"
    ],
    "wof:name":"Fins Motors, Inc.",
    "wof:placetype":"venue"
},
  "geometry": {"coordinates":[-80.219131,25.765731],"type":"Point"}
}