{
  "type": "Feature",
  "properties": {
    "iso:country":"US",
    "sg:address":"3338 Tyrone Blvd N",
    "sg:city":"St Petersburg",
    "sg:classifiers":[
        {
            "category":"Personal",
            "subcategory":"Beauty Salon",
            "type":"Services"
        }
    ],
    "sg:phone":"+1 727 347 7315",
    "sg:postcode":"33710",
    "sg:province":"FL",
    "wof:name":"Simply Stuning Salon",
    "wof:placetype":"venue"
},
  "geometry": {"coordinates":[-82.737298,27.799152],"type":"Point"}
}