{
  "type": "Feature",
  "properties": {
    "addr:full":"500 Lucas Pl Merritt Island FL 32953",
    "addr:housenumber":"500",
    "addr:postcode":"32953",
    "addr:street":"Lucas Pl",
    "iso:country":"US",
    "sg:address":"500 Lucas Pl",
    "sg:city":"Merritt Island",
    "sg:classifiers":[
        {
            "category":"Building & Trades",
            "subcategory":"Cleaning & Sanitation",
            "type":"Services"
        }
    ],
    "sg:phone":"+1 321 453 1803",
    "sg:postcode":"32953",
    "sg:province":"FL",
    "sg:tags":[
        "maintenance"
    ],
    "wof:name":"James Headley Sub Contractor",
    "wof:placetype":"venue"
},
  "geometry": {"coordinates":[-80.713374,28.37574],"type":"Point"}
}