{
  "type": "Feature",
  "properties": {
    "iso:country":"US",
    "sg:address":"5218 NW 15th St",
    "sg:city":"Margate",
    "sg:classifiers":[
        {
            "category":"Autos & Motor Vehicles",
            "subcategory":"Automobile Sales",
            "type":"Retail Goods"
        }
    ],
    "sg:phone":"+1 954 582 9192",
    "sg:postcode":"33063",
    "sg:province":"FL",
    "sg:tags":[
        "dealers-used",
        "car",
        "used",
        "cars-wholesale",
        "new"
    ],
    "wof:name":"Munsta Auto Sale",
    "wof:placetype":"venue"
},
  "geometry": {"coordinates":[-80.196516,26.248598],"type":"Point"}
}