{
  "type": "Feature",
  "properties": {
    "iso:country":"US",
    "sg:address":"1548 Yancy St",
    "sg:city":"Port Charlotte",
    "sg:classifiers":[
        {
            "category":"Building & Trades",
            "subcategory":"Construction",
            "type":"Services"
        }
    ],
    "sg:phone":"+1 941 235 0117",
    "sg:postcode":"33952",
    "sg:province":"FL",
    "sg:tags":[
        "concrete",
        "contractor"
    ],
    "wof:name":"Anthony L Jones Construction",
    "wof:placetype":"venue"
},
  "geometry": {"coordinates":[-82.107167,27.002635],"type":"Point"}
}