{
  "type": "Feature",
  "properties": {
    "iso:country":"US",
    "sg:address":"902 E Blount St",
    "sg:city":"Pensacola",
    "sg:classifiers":[
        {
            "category":"Banks & Credit Unions",
            "subcategory":"Bank",
            "type":"Services"
        }
    ],
    "sg:phone":"+1 850 429 1530",
    "sg:postcode":"32503",
    "sg:province":"FL",
    "sg:tags":[
        "loan",
        "real estate"
    ],
    "wof:name":"Long Beach Mortgage",
    "wof:placetype":"venue"
},
  "geometry": {"coordinates":[-87.207162,30.430059],"type":"Point"}
}