{
  "type": "Feature",
  "properties": {
    "addr:full":"12311 SE 115th Ave Belleview FL 34420",
    "addr:postcode":"12311;34420",
    "addr:street":"Se 115Th Ave",
    "iso:country":"US",
    "sg:address":"12311 SE 115th Ave",
    "sg:city":"Belleview",
    "sg:classifiers":[
        {
            "category":"Building & Trades",
            "subcategory":"Landscaping Services",
            "type":"Services"
        }
    ],
    "sg:phone":"+1 352 288 0556",
    "sg:postcode":"34420",
    "sg:province":"FL",
    "wof:name":"Eller Ron Nuilawn Care Servic",
    "wof:placetype":"venue"
},
  "geometry": {"coordinates":[-81.96225099999999,29.044029],"type":"Point"}
}