{
  "type": "Feature",
  "properties": {
    "iso:country":"US",
    "sg:address":"4101 Pine Tree Dr Ste D",
    "sg:city":"Miami Beach",
    "sg:classifiers":[
        {
            "category":"Organizations",
            "subcategory":"Religious Organization",
            "type":"Services"
        }
    ],
    "sg:phone":"+1 305 531 0049",
    "sg:postcode":"33140",
    "sg:province":"FL",
    "wof:name":"Girls'town or Chadash",
    "wof:placetype":"venue"
},
  "geometry": {"coordinates":[-80.126503,25.813601],"type":"Point"}
}