{
  "type": "Feature",
  "properties": {
    "iso:country":"US",
    "sg:address":"3101 N H St",
    "sg:city":"Pensacola",
    "sg:classifiers":[
        {
            "category":"Social Services",
            "type":"Services"
        }
    ],
    "sg:phone":"+1 850 432 9357",
    "sg:postcode":"32501",
    "sg:province":"FL",
    "sg:tags":[
        "senior",
        "citizen"
    ],
    "wof:name":"Council On Aging Of West Fl",
    "wof:placetype":"venue"
},
  "geometry": {"coordinates":[-87.23181,30.44144],"type":"Point"}
}