{
  "type": "Feature",
  "properties": {
    "iso:country":"US",
    "sg:address":"11137 W Colonial Dr",
    "sg:city":"Ocoee",
    "sg:classifiers":[
        {
            "category":"Retail",
            "subcategory":"Self-service Laundry",
            "type":"Services"
        }
    ],
    "sg:phone":"+1 407 877 2772",
    "sg:postcode":"34761",
    "sg:province":"FL",
    "sg:tags":[
        "coin"
    ],
    "wof:name":"Ocoee Laundry",
    "wof:placetype":"venue"
},
  "geometry": {"coordinates":[-81.54444100000001,28.551682],"type":"Point"}
}