{
  "type": "Feature",
  "properties": {
    "addr:full":"335 8th Ave NE St Petersburg FL 33701",
    "addr:housenumber":"335",
    "addr:postcode":"33701",
    "addr:street":"8Th Ave Ne",
    "iso:country":"US",
    "sg:address":"335 8th Ave NE",
    "sg:city":"St Petersburg",
    "sg:classifiers":[
        {
            "category":"Travel",
            "subcategory":"Hotels & Motels",
            "type":"Entertainment"
        }
    ],
    "sg:phone":"+1 727 822 8622",
    "sg:postcode":"33701",
    "sg:province":"FL",
    "sg:tags":[
        "breakfast",
        "accommodation",
        "bed"
    ],
    "sg:website":"www.dickenshouse.com",
    "wof:name":"Dickens House",
    "wof:placetype":"venue"
},
  "geometry": {"coordinates":[-82.630212,27.78045],"type":"Point"}
}