{
  "type": "Feature",
  "properties": {
    "addr:full":"14114 US Hwy 19 Hudson FL 34667",
    "addr:housenumber":"14114",
    "addr:postcode":"34667",
    "addr:street":"Us Hwy 19",
    "iso:country":"US",
    "sg:address":"14114 US Hwy 19",
    "sg:city":"Hudson",
    "sg:classifiers":[
        {
            "category":"Restaurant",
            "type":"Food & Drink"
        }
    ],
    "sg:phone":"+1 727 862 3131",
    "sg:postcode":"34667",
    "sg:province":"FL",
    "wof:name":"Hong Kong",
    "wof:placetype":"venue"
},
  "geometry": {"coordinates":[-82.695189,28.362163],"type":"Point"}
}