{
  "type": "Feature",
  "properties": {
    "addr:full":"16647 SW 90th St Miami FL 33196",
    "addr:housenumber":"16647",
    "addr:postcode":"33196",
    "addr:street":"Sw 90Th St",
    "iso:country":"US",
    "sg:address":"16647 SW 90th St",
    "sg:city":"Miami",
    "sg:classifiers":[
        {
            "category":"Wholesale",
            "subcategory":"Home Furnishings",
            "type":"Manufacturing & Wholesale Goods"
        }
    ],
    "sg:phone":"+1 305 383 7832",
    "sg:postcode":"33196",
    "sg:province":"FL",
    "wof:name":"Joes Quality Carpeting",
    "wof:placetype":"venue"
},
  "geometry": {"coordinates":[-80.461776,25.682217],"type":"Point"}
}