{
  "type": "Feature",
  "properties": {
    "addr:full":"5327 Pointe Vista Cir Orlando FL 32839",
    "addr:housenumber":"5327",
    "addr:postcode":"32839",
    "addr:street":"Pointe Vista Cir",
    "iso:country":"US",
    "sg:address":"5327 Pointe Vista Cir",
    "sg:city":"Orlando",
    "sg:classifiers":[
        {
            "category":"Building & Trades",
            "subcategory":"Construction",
            "type":"Services"
        }
    ],
    "sg:phone":"+1 407 826 0389",
    "sg:postcode":"32839",
    "sg:province":"FL",
    "sg:tags":[
        "contractor"
    ],
    "wof:name":"Nicole M Joubert Contractor",
    "wof:placetype":"venue"
},
  "geometry": {"coordinates":[-81.405941,28.485043],"type":"Point"}
}