{
  "type": "Feature",
  "properties": {
    "addr:full":"680 Wild Acres Rd Osteen FL 32764",
    "addr:housenumber":"680",
    "addr:postcode":"32764",
    "addr:street":"Wild Acres Rd",
    "iso:country":"US",
    "sg:address":"680 Wild Acres Rd",
    "sg:city":"Osteen",
    "sg:classifiers":[
        {
            "category":"Professional",
            "subcategory":"Computer Services",
            "type":"Services"
        }
    ],
    "sg:phone":"+1 407 328 9081",
    "sg:postcode":"32764",
    "sg:province":"FL",
    "sg:tags":[
        "website",
        "design"
    ],
    "wof:name":"Caveman Concepts",
    "wof:placetype":"venue"
},
  "geometry": {"coordinates":[-81.148685,28.822124],"type":"Point"}
}