{
  "type": "Feature",
  "properties": {
    "addr:full":"635 N Main St Williston FL 32696",
    "addr:housenumber":"635",
    "addr:postcode":"32696",
    "addr:street":"N Main St",
    "iso:country":"US",
    "sg:address":"635 N Main St",
    "sg:city":"Williston",
    "sg:classifiers":[
        {
            "category":"Manufacturing",
            "subcategory":"Watercraft",
            "type":"Manufacturing & Wholesale Goods"
        }
    ],
    "sg:phone":"+1 352 528 6115",
    "sg:postcode":"32696",
    "sg:province":"FL",
    "sg:tags":[
        "physical",
        "commercial",
        "research"
    ],
    "wof:name":"Montery Boats",
    "wof:placetype":"venue"
},
  "geometry": {"coordinates":[-82.44940800000001,29.396863],"type":"Point"}
}