{
  "type": "Feature",
  "properties": {
    "addr:full":"12601 SW 72nd St Miami FL 33183",
    "addr:housenumber":"12601",
    "addr:postcode":"33183",
    "addr:street":"Sw 72Nd St",
    "iso:country":"US",
    "sg:address":"12601 SW 72nd St",
    "sg:city":"Miami",
    "sg:classifiers":[
        {
            "category":"Organizations",
            "subcategory":"Religious Organization",
            "type":"Services"
        }
    ],
    "sg:phone":"+1 305 596 4498",
    "sg:postcode":"33183",
    "sg:province":"FL",
    "sg:tags":[
        "clergy"
    ],
    "wof:name":"Parsons Robert L Jr Rev",
    "wof:placetype":"venue"
},
  "geometry": {"coordinates":[-80.397499,25.7005],"type":"Point"}
}