{
  "type": "Feature",
  "properties": {
    "addr:full":"1656 Edgewood Ave W Jacksonville FL 32208",
    "addr:housenumber":"1656",
    "addr:postcode":"32208",
    "addr:street":"Edgewood Ave W",
    "iso:country":"US",
    "sg:address":"1656 Edgewood Ave W",
    "sg:city":"Jacksonville",
    "sg:classifiers":[
        {
            "category":"Social Services",
            "subcategory":"Child Care",
            "type":"Services"
        }
    ],
    "sg:phone":"+1 904 768 1580",
    "sg:postcode":"32208",
    "sg:province":"FL",
    "wof:name":"Good Shepherd School & Day",
    "wof:placetype":"venue"
},
  "geometry": {"coordinates":[-81.68499300000001,30.387499],"type":"Point"}
}