{
  "type": "Feature",
  "properties": {
    "iso:country":"US",
    "sg:address":"1499 Belcher Rd S",
    "sg:city":"Largo",
    "sg:classifiers":[
        {
            "category":"Banks & Credit Unions",
            "subcategory":"Bank",
            "type":"Services"
        }
    ],
    "sg:phone":"+1 727 535 0400",
    "sg:postcode":"33771",
    "sg:province":"FL",
    "sg:tags":[
        "federal"
    ],
    "wof:name":"Florida Central Credit Union",
    "wof:placetype":"venue"
},
  "geometry": {"coordinates":[-82.745853,27.907189],"type":"Point"}
}