{
  "type": "Feature",
  "properties": {
    "iso:country":"US",
    "sg:address":"1507 Lake Dr",
    "sg:city":"Cocoa",
    "sg:classifiers":[
        {
            "category":"Building & Trades",
            "subcategory":"Landscaping Services",
            "type":"Services"
        }
    ],
    "sg:phone":"+1 321 632 6017",
    "sg:postcode":"32922",
    "sg:province":"FL",
    "sg:tags":[
        "lawn",
        "maintenance",
        "grounds"
    ],
    "wof:name":"Terri Ann Mc Coy Yard Care",
    "wof:placetype":"venue"
},
  "geometry": {"coordinates":[-80.75494500000001,28.360212],"type":"Point"}
}