{
  "type": "Feature",
  "properties": {
    "addr:full":"103800 Overseas Hwy Key Largo FL 33037",
    "addr:housenumber":"103800",
    "addr:postcode":"33037",
    "addr:street":"Overseas Hwy",
    "iso:country":"US",
    "sg:address":"103800 Overseas Hwy",
    "sg:city":"Key Largo",
    "sg:classifiers":[
        {
            "category":"Restaurant",
            "type":"Food & Drink"
        }
    ],
    "sg:phone":"+1 305 453 0029",
    "sg:postcode":"33037",
    "sg:province":"FL",
    "sg:website":"www.marriottkeylargo.com",
    "wof:name":"Gus' Grille",
    "wof:placetype":"venue"
},
  "geometry": {"coordinates":[-80.397052,25.144225],"type":"Point"}
}