{
  "type": "Feature",
  "properties": {
    "iso:country":"US",
    "sg:address":"17055 Alps St",
    "sg:city":"Winter Garden",
    "sg:classifiers":[
        {
            "category":"Freight",
            "type":"Transportation"
        }
    ],
    "sg:phone":"+1 407 656 0719",
    "sg:postcode":"34787",
    "sg:province":"FL",
    "sg:tags":[
        "courier"
    ],
    "wof:name":"Billys Package Express",
    "wof:placetype":"venue"
},
  "geometry": {"coordinates":[-81.641699,28.483551],"type":"Point"}
}