{
  "type": "Feature",
  "properties": {
    "iso:country":"US",
    "sg:address":"304 S Belcher Rd",
    "sg:city":"Clearwater",
    "sg:classifiers":[
        {
            "category":"Banks & Credit Unions",
            "subcategory":"Investment Brokerage",
            "type":"Services"
        },
        {
            "category":"Insurance",
            "subcategory":"Hazard Insurance",
            "type":"Services"
        }
    ],
    "sg:phone":"+1 727 596 1805",
    "sg:postcode":"33765",
    "sg:province":"FL",
    "sg:tags":[
        "commercial",
        "agent",
        "business",
        "resume"
    ],
    "wof:name":"Dean Rosko & Associates",
    "wof:placetype":"venue"
},
  "geometry": {"coordinates":[-82.746132,27.9622],"type":"Point"}
}