{
  "type": "Feature",
  "properties": {
    "addr:full":"2958 Aventura Blvd Miami FL 33180",
    "addr:housenumber":"2958",
    "addr:postcode":"33180",
    "addr:street":"Aventura Blvd",
    "iso:country":"US",
    "sg:address":"2958 Aventura Blvd",
    "sg:city":"Miami",
    "sg:classifiers":[
        {
            "category":"Banks & Credit Unions",
            "subcategory":"Investment Brokerage",
            "type":"Services"
        },
        {
            "category":"Banks & Credit Unions",
            "subcategory":"Bank",
            "type":"Services"
        },
        {
            "category":"Banks & Credit Unions",
            "subcategory":"Financial Services",
            "type":"Services"
        }
    ],
    "sg:phone":"+1 305 933 0228",
    "sg:postcode":"33180",
    "sg:province":"FL",
    "sg:tags":[
        "retirement",
        "annuity",
        "broker",
        "plan",
        "bond",
        "insurance",
        "stock"
    ],
    "sg:website":"http://www.spencerwinston.com",
    "wof:name":"Spencer-Winston Securities Corp",
    "wof:placetype":"venue"
},
  "geometry": {"coordinates":[-80.141964,25.96],"type":"Point"}
}