{
  "type": "Feature",
  "properties": {
    "addr:full":"5783 Mining Ter Jacksonville FL 32257",
    "addr:postcode":"5783;32257",
    "addr:street":"Ter",
    "iso:country":"US",
    "sg:address":"5783 Mining Ter",
    "sg:city":"Jacksonville",
    "sg:classifiers":[
        {
            "category":"Manufacturing",
            "subcategory":"Tools & Machinery",
            "type":"Manufacturing & Wholesale Goods"
        }
    ],
    "sg:phone":"+1 904 292 0654",
    "sg:postcode":"32257",
    "sg:province":"FL",
    "sg:tags":[
        "sell",
        "repair",
        "jacks",
        "pallet"
    ],
    "wof:name":"A-1 Pallet Jack",
    "wof:placetype":"venue"
},
  "geometry": {"coordinates":[-81.568397,30.1844],"type":"Point"}
}