{
  "type": "Feature",
  "properties": {
    "iso:country":"US",
    "sg:address":"9231 NW 13th Pl",
    "sg:city":"Gainesville",
    "sg:classifiers":[
        {
            "category":"Real Estate",
            "subcategory":"Real Estate Agent",
            "type":"Services"
        }
    ],
    "sg:phone":"+1 352 332 2921",
    "sg:postcode":"32606",
    "sg:province":"FL",
    "sg:tags":[
        "appraiser"
    ],
    "wof:name":"Hayes Appraisal Svc",
    "wof:placetype":"venue"
},
  "geometry": {"coordinates":[-82.441565,29.665313],"type":"Point"}
}