{
  "type": "Feature",
  "properties": {
    "iso:country":"US",
    "sg:address":"1047 E Atlantic Ave",
    "sg:city":"Delray Beach",
    "sg:classifiers":[
        {
            "category":"Real Estate",
            "subcategory":"Real Estate Agent",
            "type":"Services"
        }
    ],
    "sg:phone":"+1 561 330 6065",
    "sg:postcode":"33483",
    "sg:province":"FL",
    "wof:name":"Atlantic International Realty",
    "wof:placetype":"venue"
},
  "geometry": {"coordinates":[-80.062117,26.461754],"type":"Point"}
}