{
  "type": "Feature",
  "properties": {
    "addr:full":"64 S Federal Hwy Boca Raton FL 33432",
    "addr:housenumber":"64",
    "addr:postcode":"33432",
    "addr:street":"S Federal Hwy",
    "iso:country":"US",
    "sg:address":"64 S Federal Hwy",
    "sg:city":"Boca Raton",
    "sg:classifiers":[
        {
            "category":"Home & Garden",
            "subcategory":"Furniture",
            "type":"Retail Goods"
        }
    ],
    "sg:phone":"+1 561 368 2337",
    "sg:postcode":"33432",
    "sg:province":"FL",
    "sg:tags":[
        "bedding"
    ],
    "wof:name":"Oceanside Bedding Inc",
    "wof:placetype":"venue"
},
  "geometry": {"coordinates":[-80.086325,26.348945],"type":"Point"}
}