{
  "type": "Feature",
  "properties": {
    "addr:full":"880 23rd St SW Naples FL 34117",
    "addr:housenumber":"880",
    "addr:postcode":"34117",
    "addr:street":"23Rd St Sw",
    "iso:country":"US",
    "sg:address":"880 23rd St SW",
    "sg:city":"Naples",
    "sg:classifiers":[
        {
            "category":"Building & Trades",
            "subcategory":"Landscaping Services",
            "type":"Services"
        }
    ],
    "sg:phone":"+1 239 348 1631",
    "sg:postcode":"34117",
    "sg:province":"FL",
    "sg:tags":[
        "lawn",
        "garden"
    ],
    "wof:name":"Darwin Cevallos Lawn Care",
    "wof:placetype":"venue"
},
  "geometry": {"coordinates":[-81.652823,26.216785],"type":"Point"}
}