{
  "type": "Feature",
  "properties": {
    "addr:full":"5123 W Rio Vista Ave Tampa FL 33634",
    "addr:housenumber":"5123",
    "addr:postcode":"33634",
    "addr:street":"W Rio Vista Ave",
    "iso:country":"US",
    "sg:address":"5123 W Rio Vista Ave",
    "sg:city":"Tampa",
    "sg:classifiers":[
        {
            "category":"Manufacturing",
            "subcategory":"Tools & Machinery",
            "type":"Manufacturing & Wholesale Goods"
        }
    ],
    "sg:phone":"+1 813 873 0632",
    "sg:postcode":"33634",
    "sg:province":"FL",
    "sg:tags":[
        "sprinkler"
    ],
    "wof:name":"Astec Fire Sprinklers",
    "wof:placetype":"venue"
},
  "geometry": {"coordinates":[-82.52637300000001,27.999726],"type":"Point"}
}