{
  "type": "Feature",
  "properties": {
    "addr:full":"5000 Clark Rd Sarasota FL 34233",
    "addr:housenumber":"5000",
    "addr:postcode":"34233",
    "addr:street":"Clark Rd",
    "iso:country":"US",
    "sg:address":"5000 Clark Rd",
    "sg:city":"Sarasota",
    "sg:classifiers":[
        {
            "category":"Retail",
            "subcategory":"Laundry & Dry Cleaning",
            "type":"Services"
        }
    ],
    "sg:phone":"+1 941 922 9134",
    "sg:postcode":"34233",
    "sg:province":"FL",
    "sg:tags":[
        "cleaners"
    ],
    "wof:name":"Classic Cleaners",
    "wof:placetype":"venue"
},
  "geometry": {"coordinates":[-82.47286099999999,27.269245],"type":"Point"}
}