{
  "type": "Feature",
  "properties": {
    "iso:country":"US",
    "sg:address":"1951 Cassat Ave",
    "sg:city":"Jacksonville",
    "sg:classifiers":[
        {
            "category":"Arts & Performance",
            "subcategory":"Theater",
            "type":"Entertainment"
        }
    ],
    "sg:phone":"+1 904 384 3912",
    "sg:postcode":"32210",
    "sg:province":"FL",
    "sg:tags":[
        "producer"
    ],
    "wof:name":"Reggae Central",
    "wof:placetype":"venue"
},
  "geometry": {"coordinates":[-81.730271,30.282292],"type":"Point"}
}