{
  "type": "Feature",
  "properties": {
    "iso:country":"US",
    "sg:address":"5757 SW 8th St",
    "sg:city":"West Miami",
    "sg:classifiers":[
        {
            "category":"Restaurant",
            "type":"Food & Drink"
        }
    ],
    "sg:phone":"+1 305 267 1885",
    "sg:postcode":"33144",
    "sg:province":"FL",
    "sg:tags":[
        "basque",
        "spanish"
    ],
    "wof:name":"Casa Rey",
    "wof:placetype":"venue"
},
  "geometry": {"coordinates":[-80.28919999999999,25.7635],"type":"Point"}
}