{
  "type": "Feature",
  "properties": {
    "addr:full":"25314 NW State Rd 73 Altha FL 32421",
    "addr:housenumber":"25314;73",
    "addr:postcode":"32421",
    "addr:street":"Nw State Rd",
    "iso:country":"US",
    "sg:address":"25314 NW State Rd 73",
    "sg:city":"Altha",
    "sg:classifiers":[
        {
            "category":"Food & Beverages",
            "subcategory":"Groceries & Convenience Stores",
            "type":"Retail Goods"
        }
    ],
    "sg:phone":"+1 850 762 3316",
    "sg:postcode":"32421",
    "sg:province":"FL",
    "sg:tags":[
        "grocer"
    ],
    "wof:name":"Shelton's Store",
    "wof:placetype":"venue"
},
  "geometry": {"coordinates":[-85.18366399999999,30.564456],"type":"Point"}
}