{
  "type": "Feature",
  "properties": {
    "iso:country":"US",
    "sg:address":"1356 NW Boca Raton Blvd",
    "sg:city":"Boca Raton",
    "sg:classifiers":[
        {
            "category":"Manufacturing",
            "subcategory":"Wood Products",
            "type":"Manufacturing & Wholesale Goods"
        }
    ],
    "sg:phone":"+1 561 392 2476",
    "sg:postcode":"33432",
    "sg:province":"FL",
    "wof:name":"Statements Inc",
    "wof:placetype":"venue"
},
  "geometry": {"coordinates":[-80.090087,26.363385],"type":"Point"}
}