{
  "type": "Feature",
  "properties": {
    "iso:country":"US",
    "sg:address":"2726 37th St E",
    "sg:city":"Palmetto",
    "sg:classifiers":[
        {
            "category":"Building & Trades",
            "subcategory":"Landscaping Services",
            "type":"Services"
        }
    ],
    "sg:phone":"+1 941 723 9457",
    "sg:postcode":"34221",
    "sg:province":"FL",
    "sg:tags":[
        "ornamental",
        "nursery",
        "landscape"
    ],
    "wof:name":"R E Whigham Nursery Inc",
    "wof:placetype":"venue"
},
  "geometry": {"coordinates":[-82.53689300000001,27.547079],"type":"Point"}
}