{
  "type": "Feature",
  "properties": {
    "iso:country":"US",
    "sg:address":"7013 Ramoth Dr",
    "sg:city":"Jacksonville",
    "sg:classifiers":[
        {
            "category":"Manufacturing",
            "subcategory":"Textiles",
            "type":"Manufacturing & Wholesale Goods"
        }
    ],
    "sg:phone":"+1 904 251 9263",
    "sg:postcode":"32226",
    "sg:province":"FL",
    "sg:tags":[
        "mfg"
    ],
    "wof:name":"Rug Art Inc",
    "wof:placetype":"venue"
},
  "geometry": {"coordinates":[-81.494755,30.394063],"type":"Point"}
}