{
  "type": "Feature",
  "properties": {
    "addr:full":"4810 Dignan St Jacksonville FL 32254",
    "addr:housenumber":"4810",
    "addr:postcode":"32254",
    "addr:street":"Dignan St",
    "iso:country":"US",
    "sg:address":"4810 Dignan St",
    "sg:city":"Jacksonville",
    "sg:classifiers":[
        {
            "category":"Freight",
            "type":"Transportation"
        }
    ],
    "sg:phone":"+1 904 384 9880",
    "sg:postcode":"32254",
    "sg:province":"FL",
    "sg:tags":[
        "cartage",
        "trucking"
    ],
    "wof:name":"Priority Transportation",
    "wof:placetype":"venue"
},
  "geometry": {"coordinates":[-81.72987999999999,30.324367],"type":"Point"}
}