{
  "type": "Feature",
  "properties": {
    "iso:country":"US",
    "sg:address":"35 SE 1st Ave",
    "sg:city":"Ocala",
    "sg:classifiers":[
        {
            "category":"Banks & Credit Unions",
            "subcategory":"Bank",
            "type":"Services"
        }
    ],
    "sg:phone":"+1 352 620 1115",
    "sg:postcode":"34471",
    "sg:province":"FL",
    "wof:name":"Bank Of America",
    "wof:placetype":"venue"
},
  "geometry": {"coordinates":[-82.13595599999999,29.185775],"type":"Point"}
}