{
  "type": "Feature",
  "properties": {
    "iso:country":"US",
    "sg:address":"10002 N Florida Ave",
    "sg:city":"Tampa",
    "sg:classifiers":[
        {
            "category":"Autos & Motor Vehicles",
            "subcategory":"Fuel & Gas Station",
            "type":"Retail Goods"
        }
    ],
    "sg:phone":"+1 813 933 2200",
    "sg:postcode":"33612",
    "sg:province":"FL",
    "sg:tags":[
        "oil"
    ],
    "wof:name":"Mobil",
    "wof:placetype":"venue"
},
  "geometry": {"coordinates":[-82.459509,28.043615],"type":"Point"}
}