{
  "type": "Feature",
  "properties": {
    "iso:country":"US",
    "sg:address":"705 Sebastian Blvd Eastbound",
    "sg:city":"Sebastian",
    "sg:classifiers":[
        {
            "category":"Banks & Credit Unions",
            "subcategory":"Investment Brokerage",
            "type":"Services"
        }
    ],
    "sg:phone":"+1 772 581 0721",
    "sg:postcode":"32958",
    "sg:province":"FL",
    "sg:tags":[
        "security"
    ],
    "wof:name":"Edward Jones Investments",
    "wof:placetype":"venue"
},
  "geometry": {"coordinates":[-80.48592499999999,27.792],"type":"Point"}
}