{
  "type": "Feature",
  "properties": {
    "iso:country":"US",
    "sg:address":"230 Blanding Blvd",
    "sg:city":"Orange Park",
    "sg:classifiers":[
        {
            "category":"Recreation",
            "type":"Entertainment"
        }
    ],
    "sg:phone":"+1 904 272 5600",
    "sg:postcode":"32073",
    "sg:province":"FL",
    "wof:name":"Skate Station",
    "wof:placetype":"venue"
},
  "geometry": {"coordinates":[-81.74414899999999,30.176129],"type":"Point"}
}