{
  "type": "Feature",
  "properties": {
    "iso:country":"US",
    "sg:address":"1340 NW 51st Ter",
    "sg:city":"Miami",
    "sg:classifiers":[
        {
            "category":"Social Services",
            "subcategory":"Child Care",
            "type":"Services"
        }
    ],
    "sg:phone":"+1 305 759 3373",
    "sg:postcode":"33142",
    "sg:province":"FL",
    "sg:tags":[
        "day"
    ],
    "wof:name":"McIntosh Academy Inc",
    "wof:placetype":"venue"
},
  "geometry": {"coordinates":[-80.219059,25.822268],"type":"Point"}
}