{
  "type": "Feature",
  "properties": {
    "iso:country":"US",
    "sg:address":"3941 W Kennedy Blvd",
    "sg:city":"Tampa",
    "sg:classifiers":[
        {
            "category":"Building & Trades",
            "subcategory":"Construction",
            "type":"Services"
        }
    ],
    "sg:phone":"+1 813 878 9787",
    "sg:postcode":"33609",
    "sg:province":"FL",
    "sg:tags":[
        "home",
        "builder"
    ],
    "wof:name":"New Homes Inc",
    "wof:placetype":"venue"
},
  "geometry": {"coordinates":[-82.509156,27.944899],"type":"Point"}
}