{
  "type": "Feature",
  "properties": {
    "iso:country":"US",
    "sg:address":"6460 E Rogers Cir",
    "sg:city":"Boca Raton",
    "sg:classifiers":[
        {
            "category":"Manufacturing",
            "subcategory":"Tools & Machinery",
            "type":"Manufacturing & Wholesale Goods"
        }
    ],
    "sg:phone":"+1 561 368 9888",
    "sg:postcode":"33487",
    "sg:province":"FL",
    "sg:tags":[
        "machine",
        "shop"
    ],
    "wof:name":"Omega One Research Inc",
    "wof:placetype":"venue"
},
  "geometry": {"coordinates":[-80.106534,26.405287],"type":"Point"}
}