{
  "type": "Feature",
  "properties": {
    "addr:full":"1540 Lakeview Dr Sebring FL 33870",
    "addr:housenumber":"1540",
    "addr:postcode":"33870",
    "addr:street":"Lakeview Dr",
    "iso:country":"US",
    "sg:address":"1540 Lakeview Dr",
    "sg:city":"Sebring",
    "sg:classifiers":[
        {
            "category":"Shopping",
            "subcategory":"Department Store",
            "type":"Retail Goods"
        },
        {
            "category":"Shopping",
            "subcategory":"Discount & Variety Stores",
            "type":"Retail Goods"
        },
        {
            "category":"Shopping",
            "type":"Retail Goods"
        },
        {
            "category":"Food & Beverages",
            "subcategory":"Groceries & Convenience Stores",
            "type":"Retail Goods"
        }
    ],
    "sg:phone":"+1 863 382 3233",
    "sg:postcode":"33870",
    "sg:province":"FL",
    "sg:tags":[
        "merchandise"
    ],
    "sg:website":"http://www.dollargeneral.com",
    "wof:name":"Dollar General",
    "wof:placetype":"venue"
},
  "geometry": {"coordinates":[-81.439921,27.483469],"type":"Point"}
}