{
  "type": "Feature",
  "properties": {
    "iso:country":"US",
    "sg:address":"4009 Palm Tree Blvd",
    "sg:city":"Cape Coral",
    "sg:classifiers":[
        {
            "category":"Real Estate",
            "subcategory":"Real Estate Operator",
            "type":"Services"
        }
    ],
    "sg:phone":"+1 239 542 5999",
    "sg:postcode":"33904",
    "sg:province":"FL",
    "sg:tags":[
        "condominium"
    ],
    "wof:name":"Banyan Trace Master Condo Assc",
    "wof:placetype":"venue"
},
  "geometry": {"coordinates":[-81.96641099999999,26.576734],"type":"Point"}
}