{
  "type": "Feature",
  "properties": {
    "iso:country":"US",
    "sg:address":"1714 Costa del Sol",
    "sg:city":"Boca Raton",
    "sg:classifiers":[
        {
            "category":"Building & Trades",
            "subcategory":"Pest Control",
            "type":"Services"
        }
    ],
    "sg:phone":"+1 561 620 2606",
    "sg:postcode":"33432",
    "sg:province":"FL",
    "wof:name":"Hometown Pest Control Inc",
    "wof:placetype":"venue"
},
  "geometry": {"coordinates":[-80.089412,26.367431],"type":"Point"}
}