{
  "type": "Feature",
  "properties": {
    "addr:full":"5010 Tampa West Blvd Tampa FL 33634",
    "addr:housenumber":"5010",
    "addr:postcode":"33634",
    "addr:street":"Tampa West Blvd",
    "iso:country":"US",
    "sg:address":"5010 Tampa West Blvd",
    "sg:city":"Tampa",
    "sg:classifiers":[
        {
            "category":"Professional",
            "subcategory":"Computer Services",
            "type":"Services"
        }
    ],
    "sg:phone":"+1 813 886 8321",
    "sg:postcode":"33634",
    "sg:province":"FL",
    "sg:tags":[
        "sharing",
        "processing",
        "related",
        "time"
    ],
    "wof:name":"Boss",
    "wof:placetype":"venue"
},
  "geometry": {"coordinates":[-82.527795,28.017752],"type":"Point"}
}