{
  "type": "Feature",
  "properties": {
    "iso:country":"US",
    "sg:address":"4801 W Chisholm St",
    "sg:city":"Tampa",
    "sg:classifiers":[
        {
            "category":"Real Estate",
            "subcategory":"Real Estate Agent",
            "type":"Services"
        }
    ],
    "sg:phone":"+1 813 835 4682",
    "sg:postcode":"33616",
    "sg:province":"FL",
    "sg:tags":[
        "investment"
    ],
    "wof:name":"Walker Properties Inc",
    "wof:placetype":"venue"
},
  "geometry": {"coordinates":[-82.526972,27.864673],"type":"Point"}
}