{
  "type": "Feature",
  "properties": {
    "addr:full":"14613 Livingston Ave Lutz FL 33559",
    "addr:housenumber":"14613",
    "addr:postcode":"33559",
    "addr:street":"Livingston Ave",
    "iso:country":"US",
    "sg:address":"14613 Livingston Ave",
    "sg:city":"Lutz",
    "sg:classifiers":[
        {
            "category":"Personal",
            "subcategory":"Beauty Salon",
            "type":"Services"
        }
    ],
    "sg:phone":"+1 813 979 0601",
    "sg:postcode":"33559",
    "sg:province":"FL",
    "sg:tags":[
        "manicuring"
    ],
    "wof:name":"Excel Nail",
    "wof:placetype":"venue"
},
  "geometry": {"coordinates":[-82.43077700000001,28.082373],"type":"Point"}
}