{
  "type": "Feature",
  "properties": {
    "addr:full":"3326 Dr Martin Luther King Blvd Fort Myers FL 33916",
    "addr:housenumber":"3326",
    "addr:postcode":"33916",
    "addr:street":"Dr Martin Luther King Blvd",
    "iso:country":"US",
    "sg:address":"3326 Dr Martin Luther King Blvd",
    "sg:city":"Fort Myers",
    "sg:classifiers":[
        {
            "category":"Government",
            "subcategory":"Office",
            "type":"Public Place"
        }
    ],
    "sg:phone":"+1 239 337 4111",
    "sg:postcode":"33916",
    "sg:province":"FL",
    "sg:tags":[
        "village"
    ],
    "wof:name":"Fort Myers Community Redev",
    "wof:placetype":"venue"
},
  "geometry": {"coordinates":[-81.84583600000001,26.640894],"type":"Point"}
}