{
  "type": "Feature",
  "properties": {
    "addr:full":"405 SW 10th Ave Okeechobee FL 34974",
    "addr:housenumber":"405",
    "addr:postcode":"34974",
    "addr:street":"Sw 10Th Ave",
    "iso:country":"US",
    "sg:address":"405 SW 10th Ave",
    "sg:city":"Okeechobee",
    "sg:classifiers":[
        {
            "category":"Place Of Worship",
            "subcategory":"Church",
            "type":"Public Place"
        },
        {
            "category":"Place Of Worship",
            "type":"Public Place"
        },
        {
            "category":"Organizations",
            "subcategory":"Religious Organization",
            "type":"Services"
        }
    ],
    "sg:phone":"+1 863 763 5300",
    "sg:postcode":"34974",
    "sg:province":"FL",
    "sg:tags":[
        "churches-pentecostal-independent",
        "churches-pentecostal"
    ],
    "sg:website":"http://www.upci.org",
    "wof:name":"United Pentecostal Church Inc",
    "wof:placetype":"venue"
},
  "geometry": {"coordinates":[-80.841393,27.239996],"type":"Point"}
}