{
  "type": "Feature",
  "properties": {
    "addr:full":"1605 N Palm Dr Avon Park FL 33825",
    "addr:housenumber":"1605",
    "addr:postcode":"33825",
    "addr:street":"N Palm Dr",
    "iso:country":"US",
    "sg:address":"1605 N Palm Dr",
    "sg:city":"Avon Park",
    "sg:classifiers":[
        {
            "category":"Professional",
            "subcategory":"Management & Consulting",
            "type":"Services"
        }
    ],
    "sg:phone":"+1 863 453 4111",
    "sg:postcode":"33825",
    "sg:province":"FL",
    "sg:tags":[
        "marketing",
        "anchor",
        "fence",
        "for"
    ],
    "wof:name":"Dhb International Inc",
    "wof:placetype":"venue"
},
  "geometry": {"coordinates":[-81.511436,27.617439],"type":"Point"}
}