{
  "type": "Feature",
  "properties": {
    "iso:country":"US",
    "sg:address":"14342 SW 163rd St",
    "sg:city":"Miami",
    "sg:classifiers":[
        {
            "category":"Communications",
            "subcategory":"Film & Video Production",
            "type":"Services"
        }
    ],
    "sg:phone":"+1 305 971 8391",
    "sg:postcode":"33177",
    "sg:province":"FL",
    "sg:tags":[
        "motion"
    ],
    "wof:name":"Effective Musical Productions",
    "wof:placetype":"venue"
},
  "geometry": {"coordinates":[-80.42507500000001,25.615862],"type":"Point"}
}