{
  "type": "Feature",
  "properties": {
    "addr:full":"4402 SW 84th Ter Fort Lauderdale FL 33328",
    "addr:housenumber":"4402",
    "addr:postcode":"33328",
    "addr:street":"Sw 84Th Ter",
    "iso:country":"US",
    "sg:address":"4402 SW 84th Ter",
    "sg:city":"Fort Lauderdale",
    "sg:classifiers":[
        {
            "category":"Professional",
            "type":"Services"
        }
    ],
    "sg:phone":"+1 954 473 9749",
    "sg:postcode":"33328",
    "sg:province":"FL",
    "wof:name":"Ocean Networks Inc",
    "wof:placetype":"venue"
},
  "geometry": {"coordinates":[-80.259658,26.067064],"type":"Point"}
}