{
  "type": "Feature",
  "properties": {
    "iso:country":"US",
    "sg:address":"571 Haverty Ct",
    "sg:city":"Rockledge",
    "sg:classifiers":[
        {
            "category":"Professional",
            "subcategory":"Engineering",
            "type":"Services"
        }
    ],
    "sg:phone":"+1 321 633 4522",
    "sg:postcode":"32955",
    "sg:province":"FL",
    "sg:tags":[
        "engineer"
    ],
    "wof:name":"DCC Engineering",
    "wof:placetype":"venue"
},
  "geometry": {"coordinates":[-80.72129200000001,28.315699],"type":"Point"}
}