{
  "type": "Feature",
  "properties": {
    "iso:country":"US",
    "sg:address":"5321 N State Rd 7",
    "sg:city":"Tamarac",
    "sg:classifiers":[
        {
            "category":"Home & Garden",
            "subcategory":"Building Materials",
            "type":"Retail Goods"
        }
    ],
    "sg:phone":"+1 954 739 2020",
    "sg:postcode":"33319",
    "sg:province":"FL",
    "sg:tags":[
        "door"
    ],
    "wof:name":"All Discount Doors",
    "wof:placetype":"venue"
},
  "geometry": {"coordinates":[-80.203906,26.190781],"type":"Point"}
}