{
  "type": "Feature",
  "properties": {
    "iso:country":"US",
    "sg:address":"12100 Dividing Oaks Trl W",
    "sg:city":"Jacksonville",
    "sg:classifiers":[
        {
            "category":"Building & Trades",
            "subcategory":"Electrical",
            "type":"Services"
        },
        {
            "category":"Shopping",
            "subcategory":"Computers & Home Electronics",
            "type":"Retail Goods"
        }
    ],
    "sg:phone":"+1 904 781 8888",
    "sg:postcode":"32223",
    "sg:province":"FL",
    "sg:tags":[
        "satellite",
        "installation",
        "stereo",
        "system",
        "equipment",
        "television"
    ],
    "wof:name":"Jacksonville Satellite Inc",
    "wof:placetype":"venue"
},
  "geometry": {"coordinates":[-81.62763200000001,30.149403],"type":"Point"}
}