{
  "type": "Feature",
  "properties": {
    "iso:country":"US",
    "sg:address":"7184 NW 77th Ter",
    "sg:city":"Miami",
    "sg:classifiers":[
        {
            "category":"Professional",
            "subcategory":"Business Services",
            "type":"Services"
        }
    ],
    "sg:phone":"+1 305 889 0111",
    "sg:postcode":"33166",
    "sg:province":"FL",
    "wof:name":"Fuji Aluminum & Screen",
    "wof:placetype":"venue"
},
  "geometry": {"coordinates":[-80.31081500000001,25.843831],"type":"Point"}
}