{
  "type": "Feature",
  "properties": {
    "iso:country":"US",
    "sg:address":"149 S Orlando Ave",
    "sg:city":"Cocoa Beach",
    "sg:classifiers":[
        {
            "category":"Organizations",
            "subcategory":"Community Association",
            "type":"Services"
        }
    ],
    "sg:phone":"+1 321 783 0339",
    "sg:postcode":"32931",
    "sg:province":"FL",
    "sg:tags":[
        "fraternal"
    ],
    "wof:name":"Canaveral Lodge 339 F & AM",
    "wof:placetype":"venue"
},
  "geometry": {"coordinates":[-80.60999099999999,28.315728],"type":"Point"}
}