{
  "type": "Feature",
  "properties": {
    "addr:full":"8134 Country Run Pkwy Orlando FL 32818",
    "addr:housenumber":"8134",
    "addr:postcode":"32818",
    "addr:street":"Country Run Pkwy",
    "iso:country":"US",
    "sg:address":"8134 Country Run Pkwy",
    "sg:city":"Orlando",
    "sg:classifiers":[
        {
            "category":"Shopping",
            "subcategory":"Computers & Home Electronics",
            "type":"Retail Goods"
        }
    ],
    "sg:phone":"+1 407 290 1977",
    "sg:postcode":"32818",
    "sg:province":"FL",
    "sg:tags":[
        "equipment",
        "dealer"
    ],
    "wof:name":"Bezaleel Diaz Computer Repair",
    "wof:placetype":"venue"
},
  "geometry": {"coordinates":[-81.49623699999999,28.595761],"type":"Point"}
}