{
  "type": "Feature",
  "properties": {
    "iso:country":"US",
    "sg:address":"899 State Road 436",
    "sg:city":"Casselberry",
    "sg:classifiers":[
        {
            "category":"Restaurant",
            "type":"Food & Drink"
        }
    ],
    "sg:phone":"+1 407 831 3008",
    "sg:postcode":"32707",
    "sg:province":"FL",
    "sg:tags":[
        "style",
        "family",
        "lunch",
        "american",
        "brunch",
        "breakfast"
    ],
    "wof:name":"Country Fixin's Restaurant",
    "wof:placetype":"venue"
},
  "geometry": {"coordinates":[-81.326257,28.649693],"type":"Point"}
}