{
  "type": "Feature",
  "properties": {
    "iso:country":"US",
    "sg:address":"522 Doric Ct",
    "sg:city":"Tarpon Springs",
    "sg:classifiers":[
        {
            "category":"Health Services",
            "subcategory":"Nursing And Care Facility",
            "type":"Services"
        }
    ],
    "sg:phone":"+1 727 938 6102",
    "sg:postcode":"34689",
    "sg:province":"FL",
    "sg:tags":[
        "home",
        "retirement",
        "community"
    ],
    "wof:name":"Serenity On The Bayou",
    "wof:placetype":"venue"
},
  "geometry": {"coordinates":[-82.768873,28.150928],"type":"Point"}
}