{
  "type": "Feature",
  "properties": {
    "iso:country":"US",
    "sg:address":"539 Johns Pass Ave",
    "sg:city":"Saint Petersburg",
    "sg:classifiers":[
        {
            "category":"Banks & Credit Unions",
            "subcategory":"Financial Services",
            "type":"Services"
        }
    ],
    "sg:phone":"+1 727 392 3263",
    "sg:postcode":"33708",
    "sg:province":"FL",
    "sg:tags":[
        "investor"
    ],
    "wof:name":"Eva J Dixon Eductl Foundation",
    "wof:placetype":"venue"
},
  "geometry": {"coordinates":[-82.78013199999999,27.800024],"type":"Point"}
}