{
  "type": "Feature",
  "properties": {
    "addr:full":"1115 Driggers Rd Lakeland FL 33809",
    "addr:housenumber":"1115",
    "addr:postcode":"33809",
    "addr:street":"Driggers Rd",
    "iso:country":"US",
    "sg:address":"1115 Driggers Rd",
    "sg:city":"Lakeland",
    "sg:classifiers":[
        {
            "category":"Personal",
            "subcategory":"Beauty Salon",
            "type":"Services"
        }
    ],
    "sg:phone":"+1 863 816 1381",
    "sg:postcode":"33809",
    "sg:province":"FL",
    "sg:tags":[
        "shop"
    ],
    "wof:name":"Jean Matel & Co",
    "wof:placetype":"venue"
},
  "geometry": {"coordinates":[-81.934727,28.158411],"type":"Point"}
}