{
  "type": "Feature",
  "properties": {
    "iso:country":"US",
    "sg:address":"4540 N Federal Hwy",
    "sg:city":"Pompano Beach",
    "sg:classifiers":[
        {
            "category":"Banks & Credit Unions",
            "subcategory":"Bank",
            "type":"Services"
        }
    ],
    "sg:phone":"+1 954 946 2224",
    "sg:postcode":"33064",
    "sg:province":"FL",
    "sg:tags":[
        "automobile",
        "retail",
        "leasing",
        "equipment"
    ],
    "wof:name":"Jenkins Leasing",
    "wof:placetype":"venue"
},
  "geometry": {"coordinates":[-80.09575,26.287342],"type":"Point"}
}