{
  "type": "Feature",
  "properties": {
    "addr:full":"14490 SW 199th St Miami FL 33177",
    "addr:housenumber":"14490",
    "addr:postcode":"33177",
    "addr:street":"Sw 199Th St",
    "iso:country":"US",
    "sg:address":"14490 SW 199th St",
    "sg:city":"Miami",
    "sg:classifiers":[
        {
            "category":"Freight",
            "type":"Transportation"
        }
    ],
    "sg:phone":"+1 305 254 9353",
    "sg:postcode":"33177",
    "sg:province":"FL",
    "sg:tags":[
        "trucking"
    ],
    "wof:name":"Git R Done Transportation Inc",
    "wof:placetype":"venue"
},
  "geometry": {"coordinates":[-80.42841,25.584063],"type":"Point"}
}