{
  "type": "Feature",
  "properties": {
    "iso:country":"US",
    "sg:address":"6412 NW 82nd Ave",
    "sg:city":"Miami",
    "sg:classifiers":[
        {
            "category":"Professional",
            "type":"Services"
        }
    ],
    "sg:phone":"+1 305 591 8119",
    "sg:postcode":"33166",
    "sg:province":"FL",
    "wof:name":"Smith Falchetti LLC",
    "wof:placetype":"venue"
},
  "geometry": {"coordinates":[-80.330037,25.831868],"type":"Point"}
}