{
  "type": "Feature",
  "properties": {
    "iso:country":"US",
    "sg:address":"1511 Virginia Ave",
    "sg:city":"Lynn Haven",
    "sg:classifiers":[
        {
            "category":"Manufacturing",
            "subcategory":"Chemicals & Compounds",
            "type":"Manufacturing & Wholesale Goods"
        }
    ],
    "sg:phone":"+1 850 265 4988",
    "sg:postcode":"32444",
    "sg:province":"FL",
    "sg:tags":[
        "preparation",
        "mfg"
    ],
    "wof:name":"Spiva Manufacturing",
    "wof:placetype":"venue"
},
  "geometry": {"coordinates":[-85.65447,30.234758],"type":"Point"}
}