{
  "type": "Feature",
  "properties": {
    "iso:country":"US",
    "sg:address":"2478 Sand Lake Rd",
    "sg:city":"Orlando",
    "sg:classifiers":[
        {
            "category":"Building & Trades",
            "subcategory":"Cleaning & Sanitation",
            "type":"Services"
        }
    ],
    "sg:phone":"+1 407 363 9555",
    "sg:postcode":"32809",
    "sg:province":"FL",
    "sg:tags":[
        "janitor"
    ],
    "wof:name":"R M Cleaning",
    "wof:placetype":"venue"
},
  "geometry": {"coordinates":[-81.41462799999999,28.450358],"type":"Point"}
}