{
  "type": "Feature",
  "properties": {
    "iso:country":"US",
    "sg:address":"404 W Jefferson St",
    "sg:city":"Quincy",
    "sg:classifiers":[
        {
            "category":"Insurance",
            "subcategory":"Hazard Insurance",
            "type":"Services"
        },
        {
            "category":"Insurance",
            "subcategory":"Life Insurance",
            "type":"Services"
        }
    ],
    "sg:phone":"+1 850 627 7681",
    "sg:postcode":"32351",
    "sg:province":"FL",
    "wof:name":"Public Utilities Dept",
    "wof:placetype":"venue"
},
  "geometry": {"coordinates":[-84.58152800000001,30.588131],"type":"Point"}
}