{
  "type": "Feature",
  "properties": {
    "iso:country":"US",
    "sg:address":"4942 Co Rd 300",
    "sg:city":"Lake Panasoffkee",
    "sg:classifiers":[
        {
            "category":"Building & Trades",
            "subcategory":"Cleaning & Sanitation",
            "type":"Services"
        }
    ],
    "sg:phone":"+1 352 568 1935",
    "sg:postcode":"33538",
    "sg:province":"FL",
    "sg:tags":[
        "maintenance"
    ],
    "wof:name":"L & L Facility Maintenance",
    "wof:placetype":"venue"
},
  "geometry": {"coordinates":[-82.180396,28.828478],"type":"Point"}
}