{
  "type": "Feature",
  "properties": {
    "addr:full":"1547 5th St Daytona Beach FL 32117",
    "addr:housenumber":"1547",
    "addr:postcode":"32117",
    "addr:street":"5Th St",
    "iso:country":"US",
    "sg:address":"1547 5th St",
    "sg:city":"Daytona Beach",
    "sg:classifiers":[
        {
            "category":"Building & Trades",
            "subcategory":"Cleaning & Sanitation",
            "type":"Services"
        }
    ],
    "sg:phone":"+1 386 255 9959",
    "sg:postcode":"32117",
    "sg:province":"FL",
    "sg:tags":[
        "janitor"
    ],
    "wof:name":"R & M Enterprises Of Daytona",
    "wof:placetype":"venue"
},
  "geometry": {"coordinates":[-81.070334,29.223082],"type":"Point"}
}