{
  "type": "Feature",
  "properties": {
    "addr:full":"3600 SW Wood Creek Trl Palm City FL 34990",
    "addr:housenumber":"3600",
    "addr:postcode":"34990",
    "addr:street":"Sw Wood Creek Trl",
    "iso:country":"US",
    "sg:address":"3600 SW Wood Creek Trl",
    "sg:city":"Palm City",
    "sg:classifiers":[
        {
            "category":"Shopping",
            "subcategory":"Catalog Store",
            "type":"Retail Goods"
        }
    ],
    "sg:phone":"+1 772 283 6195",
    "sg:postcode":"34990",
    "sg:province":"FL",
    "sg:tags":[
        "mail",
        "house"
    ],
    "wof:name":"Velvet Underground",
    "wof:placetype":"venue"
},
  "geometry": {"coordinates":[-80.305042,27.188288],"type":"Point"}
}