{
  "type": "Feature",
  "properties": {
    "iso:country":"US",
    "sg:address":"5701 Sunset Dr",
    "sg:city":"South Miami",
    "sg:classifiers":[
        {
            "category":"Shopping",
            "subcategory":"Clothing, Apparel, & Fashions",
            "type":"Retail Goods"
        }
    ],
    "sg:phone":"+1 305 668 2929",
    "sg:postcode":"33143",
    "sg:province":"FL",
    "sg:tags":[
        "accessory",
        "clothing",
        "women's"
    ],
    "wof:name":"Arden B",
    "wof:placetype":"venue"
},
  "geometry": {"coordinates":[-80.2864,25.704399],"type":"Point"}
}