{
  "type": "Feature",
  "properties": {
    "iso:country":"US",
    "sg:address":"24109 Mink Rd",
    "sg:city":"Astor",
    "sg:classifiers":[
        {
            "category":"Manufacturing",
            "subcategory":"Printing",
            "type":"Manufacturing & Wholesale Goods"
        }
    ],
    "sg:phone":"+1 352 759 3114",
    "sg:postcode":"32102",
    "sg:province":"FL",
    "sg:tags":[
        "commercial"
    ],
    "wof:name":"Graphics Express",
    "wof:placetype":"venue"
},
  "geometry": {"coordinates":[-81.54114,29.178465],"type":"Point"}
}