{
  "type": "Feature",
  "properties": {
    "iso:country":"US",
    "sg:address":"13703 SW 20th St",
    "sg:city":"Miami",
    "sg:classifiers":[
        {
            "category":"Banks & Credit Unions",
            "subcategory":"Financial Services",
            "type":"Services"
        }
    ],
    "sg:phone":"+1 305 207 8080",
    "sg:postcode":"33175",
    "sg:province":"FL",
    "sg:tags":[
        "investor"
    ],
    "wof:name":"1140 Towers Investment Inc",
    "wof:placetype":"venue"
},
  "geometry": {"coordinates":[-80.417312,25.748989],"type":"Point"}
}