{
  "type": "Feature",
  "properties": {
    "addr:full":"1 SW Osceola St Ste 3 Stuart FL 34994",
    "addr:housenumber":"1",
    "addr:postcode":"34994",
    "addr:street":"Sw Osceola St Ste 3",
    "iso:country":"US",
    "sg:address":"1 SW Osceola St Ste 3",
    "sg:city":"Stuart",
    "sg:classifiers":[
        {
            "category":"Professional",
            "subcategory":"Business Services",
            "type":"Services"
        },
        {
            "category":"Professional",
            "subcategory":"Art Services",
            "type":"Services"
        }
    ],
    "sg:phone":"+1 772 220 1388",
    "sg:postcode":"34994",
    "sg:province":"FL",
    "sg:tags":[
        "development",
        "product",
        "graphic",
        "designers-industrial",
        "artist",
        "marketing",
        "commercial",
        "designer",
        "design"
    ],
    "wof:name":"Baron Graphics Limited",
    "wof:placetype":"venue"
},
  "geometry": {"coordinates":[-80.252792,27.198509],"type":"Point"}
}