{
  "type": "Feature",
  "properties": {
    "iso:country":"US",
    "sg:address":"2311 11th Ave SE",
    "sg:city":"Ruskin",
    "sg:classifiers":[
        {
            "category":"Organizations",
            "subcategory":"Non-profit Organization",
            "type":"Services"
        }
    ],
    "sg:phone":"+1 813 641 1411",
    "sg:postcode":"33570",
    "sg:province":"FL",
    "sg:tags":[
        "charitable",
        "institution"
    ],
    "wof:name":"Christians Along The Way",
    "wof:placetype":"venue"
},
  "geometry": {"coordinates":[-82.403561,27.709345],"type":"Point"}
}