{
  "type": "Feature",
  "properties": {
    "addr:full":"3399 NW 72nd Ave Miami FL 33122",
    "addr:housenumber":"3399",
    "addr:postcode":"33122",
    "addr:street":"Nw 72Nd Ave",
    "iso:country":"US",
    "sg:address":"3399 NW 72nd Ave",
    "sg:city":"Miami",
    "sg:classifiers":[
        {
            "category":"Professional",
            "subcategory":"Accounting & Tax Preparation",
            "type":"Services"
        }
    ],
    "sg:phone":"+1 305 597 5190",
    "sg:postcode":"33122",
    "sg:province":"FL",
    "sg:tags":[
        "accountant"
    ],
    "wof:name":"Morel Rafael CPA",
    "wof:placetype":"venue"
},
  "geometry": {"coordinates":[-80.31300400000001,25.806101],"type":"Point"}
}