{
  "type": "Feature",
  "properties": {
    "addr:full":"108 1st St St Augustine FL 32080",
    "addr:housenumber":"108",
    "addr:postcode":"32080",
    "addr:street":"1St St",
    "iso:country":"US",
    "sg:address":"108 1st St",
    "sg:city":"St Augustine",
    "sg:classifiers":[
        {
            "category":"Professional",
            "subcategory":"Lawyer & Legal Services",
            "type":"Services"
        }
    ],
    "sg:phone":"+1 904 461 9161",
    "sg:postcode":"32080",
    "sg:province":"FL",
    "sg:tags":[
        "plan"
    ],
    "wof:name":"Pre-Paid Legal Svc Inc",
    "wof:placetype":"venue"
},
  "geometry": {"coordinates":[-81.26752999999999,29.845348],"type":"Point"}
}