{
  "type": "Feature",
  "properties": {
    "addr:full":"3525 N Cocoa Blvd Cocoa FL 32926",
    "addr:housenumber":"3525",
    "addr:postcode":"32926",
    "addr:street":"N Cocoa Blvd",
    "iso:country":"US",
    "sg:address":"3525 N Cocoa Blvd",
    "sg:city":"Cocoa",
    "sg:classifiers":[
        {
            "category":"Freight",
            "type":"Transportation"
        }
    ],
    "sg:phone":"+1 321 639 0010",
    "sg:postcode":"32926",
    "sg:province":"FL",
    "sg:tags":[
        "dry",
        "bulk",
        "operator",
        "trucking"
    ],
    "wof:name":"Transport Service Co",
    "wof:placetype":"venue"
},
  "geometry": {"coordinates":[-80.755236,28.409],"type":"Point"}
}