{
  "type": "Feature",
  "properties": {
    "iso:country":"US",
    "sg:address":"975 Florida Central Pkwy",
    "sg:city":"Longwood",
    "sg:classifiers":[
        {
            "category":"Building & Trades",
            "subcategory":"Construction",
            "type":"Services"
        }
    ],
    "sg:phone":"+1 407 699 9960",
    "sg:postcode":"32750",
    "sg:province":"FL",
    "sg:tags":[
        "installation",
        "heating",
        "devices",
        "solar",
        "pool",
        "swimming"
    ],
    "wof:name":"Florida Solar Technologies",
    "wof:placetype":"venue"
},
  "geometry": {"coordinates":[-81.354238,28.690494],"type":"Point"}
}