{
  "type": "Feature",
  "properties": {
    "iso:country":"US",
    "sg:address":"4222 Lanai Dr",
    "sg:city":"Sarasota",
    "sg:classifiers":[
        {
            "category":"Professional",
            "type":"Services"
        }
    ],
    "sg:phone":"+1 941 343 9230",
    "sg:postcode":"34241",
    "sg:province":"FL",
    "wof:name":"Sunset Ripper Inc",
    "wof:placetype":"venue"
},
  "geometry": {"coordinates":[-82.44141500000001,27.293339],"type":"Point"}
}