{
  "type": "Feature",
  "properties": {
    "iso:country":"US",
    "sg:address":"157 N Division St",
    "sg:city":"Oviedo",
    "sg:classifiers":[
        {
            "category":"Place Of Worship",
            "subcategory":"Church",
            "type":"Public Place"
        }
    ],
    "sg:phone":"+1 407 365 1538",
    "sg:postcode":"32765",
    "sg:province":"FL",
    "sg:tags":[
        "churches-baptist"
    ],
    "wof:name":"Fountainhead Missionary Church",
    "wof:placetype":"venue"
},
  "geometry": {"coordinates":[-81.204357,28.672733],"type":"Point"}
}