{
  "type": "Feature",
  "properties": {
    "addr:full":"283 Altamonte Springs Dr Altamonte Spgs FL 32701",
    "addr:housenumber":"283",
    "addr:postcode":"32701",
    "addr:street":"Altamonte Springs Dr Altamonte Spgs",
    "iso:country":"US",
    "sg:address":"283 Altamonte Springs Dr",
    "sg:city":"Altamonte Spgs",
    "sg:classifiers":[
        {
            "category":"Professional",
            "subcategory":"Management & Consulting",
            "type":"Services"
        }
    ],
    "sg:phone":"+1 407 767 8999",
    "sg:postcode":"32701",
    "sg:province":"FL",
    "sg:tags":[
        "consultant",
        "publishing"
    ],
    "wof:name":"Thomson Financial Publishing",
    "wof:placetype":"venue"
},
  "geometry": {"coordinates":[-81.382335,28.661738],"type":"Point"}
}