{
  "type": "Feature",
  "properties": {
    "addr:full":"365 Alcazar Ave Coral Gables FL 33134",
    "addr:housenumber":"365",
    "addr:postcode":"33134",
    "addr:street":"Alcazar Ave",
    "iso:country":"US",
    "sg:address":"365 Alcazar Ave",
    "sg:city":"Coral Gables",
    "sg:classifiers":[
        {
            "category":"Health Services",
            "subcategory":"Doctor",
            "type":"Services"
        }
    ],
    "sg:phone":"+1 305 445 0441",
    "sg:postcode":"33134",
    "sg:province":"FL",
    "wof:name":"Lanz Miguel J MD",
    "wof:placetype":"venue"
},
  "geometry": {"coordinates":[-80.262604,25.7526],"type":"Point"}
}