{
  "type": "Feature",
  "properties": {
    "iso:country":"US",
    "sg:address":"301 S Disston Ave",
    "sg:city":"Tarpon Springs",
    "sg:classifiers":[
        {
            "category":"Organizations",
            "subcategory":"Community Association",
            "type":"Services"
        }
    ],
    "sg:phone":"+1 727 943 4743",
    "sg:postcode":"34689",
    "sg:province":"FL",
    "sg:tags":[
        "military"
    ],
    "wof:name":"Pinellas County Welfare Dept",
    "wof:placetype":"venue"
},
  "geometry": {"coordinates":[-82.748361,28.143179],"type":"Point"}
}