{
  "type": "Feature",
  "properties": {
    "addr:full":"5674 Ada St Cocoa FL 32927",
    "addr:housenumber":"5674",
    "addr:postcode":"32927",
    "addr:street":"Ada St",
    "iso:country":"US",
    "sg:address":"5674 Ada St",
    "sg:city":"Cocoa",
    "sg:classifiers":[
        {
            "category":"Building & Trades",
            "subcategory":"Construction",
            "type":"Services"
        }
    ],
    "sg:phone":"+1 321 403 3732",
    "sg:postcode":"32927",
    "sg:province":"FL",
    "sg:tags":[
        "contractor"
    ],
    "wof:name":"Kevin Benish Contractor",
    "wof:placetype":"venue"
},
  "geometry": {"coordinates":[-80.818067,28.470566],"type":"Point"}
}