{
  "type": "Feature",
  "properties": {
    "addr:full":"2385 Orange Blossom Dr Naples FL 34109",
    "addr:housenumber":"2385",
    "addr:postcode":"34109",
    "addr:street":"Orange Blossom Dr",
    "iso:country":"US",
    "sg:address":"2385 Orange Blossom Dr",
    "sg:city":"Naples",
    "sg:classifiers":[
        {
            "category":"Education",
            "subcategory":"Library",
            "type":"Public Place"
        },
        {
            "category":"Government",
            "subcategory":"Office",
            "type":"Public Place"
        }
    ],
    "sg:phone":"+1 239 593 3511",
    "sg:postcode":"34109",
    "sg:province":"FL",
    "sg:tags":[
        "township",
        "government-city",
        "village"
    ],
    "sg:website":"http://www.collier-lib.org",
    "wof:name":"Collier County Headquarters Library",
    "wof:placetype":"venue"
},
  "geometry": {"coordinates":[-81.770138,26.232756],"type":"Point"}
}