{
  "type": "Feature",
  "properties": {
    "iso:country":"US",
    "sg:address":"3814 S 1st St",
    "sg:city":"Lake City",
    "sg:classifiers":[
        {
            "category":"Building & Trades",
            "subcategory":"Construction",
            "type":"Services"
        }
    ],
    "sg:phone":"+1 386 752 3115",
    "sg:postcode":"32025",
    "sg:province":"FL",
    "sg:tags":[
        "siding",
        "contractor"
    ],
    "wof:name":"Martin Exteriors",
    "wof:placetype":"venue"
},
  "geometry": {"coordinates":[-82.64297000000001,30.159528],"type":"Point"}
}