{
  "type": "Feature",
  "properties": {
    "addr:full":"446 Tamiami Trl S Venice FL 34285",
    "addr:housenumber":"446",
    "addr:postcode":"34285",
    "addr:street":"Tamiami Trl S",
    "iso:country":"US",
    "sg:address":"446 Tamiami Trl S",
    "sg:city":"Venice",
    "sg:classifiers":[
        {
            "category":"Banks & Credit Unions",
            "subcategory":"Bank",
            "type":"Services"
        },
        {
            "category":"Banks & Credit Unions",
            "subcategory":"Financial Services",
            "type":"Services"
        }
    ],
    "sg:phone":"+1 941 484 1556",
    "sg:postcode":"34285",
    "sg:province":"FL",
    "sg:tags":[
        "commercial",
        "loan",
        "saving",
        "mortgage"
    ],
    "sg:website":"https://www.wachovia.com/?DCMP=KNL-CPS-DS-Directory-0703&HBX_PK=Banks&HBX_OU=71",
    "wof:name":"Wachovia Bank",
    "wof:placetype":"venue"
},
  "geometry": {"coordinates":[-82.44435,27.093248],"type":"Point"}
}