{
  "type": "Feature",
  "properties": {
    "addr:full":"12150 Carriage Ln West Palm Beach FL 33414",
    "addr:housenumber":"12150",
    "addr:postcode":"33414",
    "addr:street":"Carriage Ln",
    "iso:country":"US",
    "sg:address":"12150 Carriage Ln",
    "sg:city":"West Palm Beach",
    "sg:classifiers":[
        {
            "category":"Building & Trades",
            "subcategory":"Construction",
            "type":"Services"
        }
    ],
    "sg:phone":"+1 561 798 0216",
    "sg:postcode":"33414",
    "sg:province":"FL",
    "sg:tags":[
        "house",
        "nonresidential"
    ],
    "wof:name":"J E Kleen General Contractor",
    "wof:placetype":"venue"
},
  "geometry": {"coordinates":[-80.23781700000001,26.672392],"type":"Point"}
}