{
  "type": "Feature",
  "properties": {
    "addr:full":"4780 SE 33rd Ave Ocala FL 34480",
    "addr:housenumber":"4780",
    "addr:postcode":"34480",
    "addr:street":"Se 33Rd Ave",
    "iso:country":"US",
    "sg:address":"4780 SE 33rd Ave",
    "sg:city":"Ocala",
    "sg:classifiers":[
        {
            "category":"Building & Trades",
            "subcategory":"Construction",
            "type":"Services"
        }
    ],
    "sg:phone":"+1 352 427 3832",
    "sg:postcode":"34480",
    "sg:province":"FL",
    "sg:tags":[
        "restoration",
        "cleaning",
        "patio",
        "deck"
    ],
    "wof:name":"Wayne Hickman Pressure Clean",
    "wof:placetype":"venue"
},
  "geometry": {"coordinates":[-82.09326299999999,29.142422],"type":"Point"}
}