{
  "type": "Feature",
  "properties": {
    "iso:country":"US",
    "sg:address":"1425 S Osprey Ave",
    "sg:city":"Sarasota",
    "sg:classifiers":[
        {
            "category":"Health Services",
            "subcategory":"Doctor",
            "type":"Services"
        }
    ],
    "sg:phone":"+1 941 362 9110",
    "sg:postcode":"34239",
    "sg:province":"FL",
    "sg:tags":[
        "dentist"
    ],
    "wof:name":"Jefferson M Pecora DDS",
    "wof:placetype":"venue"
},
  "geometry": {"coordinates":[-82.533703,27.320327],"type":"Point"}
}