{
  "type": "Feature",
  "properties": {
    "addr:full":"12726 NW 18th Pl Pompano Beach FL 33071",
    "addr:housenumber":"12726",
    "addr:postcode":"33071",
    "addr:street":"Nw 18Th Pl",
    "iso:country":"US",
    "sg:address":"12726 NW 18th Pl",
    "sg:city":"Pompano Beach",
    "sg:classifiers":[
        {
            "category":"Professional",
            "subcategory":"Lawyer & Legal Services",
            "type":"Services"
        }
    ],
    "sg:phone":"+1 954 341 3597",
    "sg:postcode":"33071",
    "sg:province":"FL",
    "wof:name":"Ronni Eileen Roth PA",
    "wof:placetype":"venue"
},
  "geometry": {"coordinates":[-80.295986,26.253575],"type":"Point"}
}