{
  "type": "Feature",
  "properties": {
    "iso:country":"US",
    "sg:address":"3910 S Dale Mabry Hwy",
    "sg:city":"Tampa",
    "sg:classifiers":[
        {
            "category":"Restaurant",
            "type":"Food & Drink"
        }
    ],
    "sg:menulink":"http://www.allmenus.com/fl/tampa/65348-cicis-pizza-buffet/menu/",
    "sg:phone":"+1 813 832 3334",
    "sg:postcode":"33611",
    "sg:province":"FL",
    "sg:tags":[
        "american",
        "pizza"
    ],
    "wof:name":"CiCi's Pizza Buffet",
    "wof:placetype":"venue"
},
  "geometry": {"coordinates":[-82.50606000000001,27.906371],"type":"Point"}
}