{
  "type": "Feature",
  "properties": {
    "addr:full":"116 S Semoran Blvd Winter Park FL 32792",
    "addr:housenumber":"116",
    "addr:postcode":"32792",
    "addr:street":"S Semoran Blvd",
    "iso:country":"US",
    "sg:address":"116 S Semoran Blvd",
    "sg:city":"Winter Park",
    "sg:classifiers":[
        {
            "category":"Shopping",
            "subcategory":"Bicycles & Sporting Goods",
            "type":"Retail Goods"
        }
    ],
    "sg:phone":"+1 407 671 3048",
    "sg:postcode":"32792",
    "sg:province":"FL",
    "sg:tags":[
        "equipment",
        "exercise"
    ],
    "sg:website":"www.fitnessshowcase.com",
    "wof:name":"Fitness Showcase Inc",
    "wof:placetype":"venue"
},
  "geometry": {"coordinates":[-81.307489,28.594843],"type":"Point"}
}