{
  "type": "Feature",
  "properties": {
    "iso:country":"US",
    "sg:address":"16251 Bristol Pointe Dr",
    "sg:city":"Delray Beach",
    "sg:classifiers":[
        {
            "category":"Professional",
            "subcategory":"Employment Agencies",
            "type":"Services"
        }
    ],
    "sg:phone":"+1 561 301 6870",
    "sg:postcode":"33446",
    "sg:province":"FL",
    "wof:name":"Telecom Butler SA",
    "wof:placetype":"venue"
},
  "geometry": {"coordinates":[-80.150094,26.435881],"type":"Point"}
}