{
  "type": "Feature",
  "properties": {
    "addr:full":"20099 SW 326th St Homestead FL 33030",
    "addr:housenumber":"20099",
    "addr:postcode":"33030",
    "addr:street":"Sw 326Th St",
    "iso:country":"US",
    "sg:address":"20099 SW 326th St",
    "sg:city":"Homestead",
    "sg:classifiers":[
        {
            "category":"Insurance",
            "subcategory":"Insurance Agent",
            "type":"Services"
        }
    ],
    "sg:phone":"+1 305 245 0526",
    "sg:postcode":"33030",
    "sg:province":"FL",
    "wof:name":"Independant Insur Adjusters",
    "wof:placetype":"venue"
},
  "geometry": {"coordinates":[-80.51354000000001,25.4642],"type":"Point"}
}