{
  "type": "Feature",
  "properties": {
    "addr:full":"2220 Hempel Ave Winter Garden FL 34734",
    "addr:postcode":"2220;34734",
    "addr:street":"Hempel Ave",
    "iso:country":"US",
    "sg:address":"2220 Hempel Ave",
    "sg:city":"Winter Garden",
    "sg:classifiers":[
        {
            "category":"Recreation",
            "type":"Entertainment"
        }
    ],
    "sg:phone":"+1 407 290 8049",
    "sg:postcode":"34734",
    "sg:province":"FL",
    "sg:tags":[
        "martial",
        "arts",
        "instruction"
    ],
    "wof:name":"Traditional Martial Arts Ctr",
    "wof:placetype":"venue"
},
  "geometry": {"coordinates":[-81.522927,28.532963],"type":"Point"}
}