{
  "type": "Feature",
  "properties": {
    "iso:country":"US",
    "sg:address":"525 NW Le Jeune Rd",
    "sg:city":"Miami",
    "sg:classifiers":[
        {
            "category":"Restaurant",
            "type":"Food & Drink"
        }
    ],
    "sg:phone":"+1 305 646 0380",
    "sg:postcode":"33126",
    "sg:province":"FL",
    "sg:tags":[
        "spanish"
    ],
    "wof:name":"Madrid Restaurant Tapas Y Vinos",
    "wof:placetype":"venue"
},
  "geometry": {"coordinates":[-80.26386100000001,25.777403],"type":"Point"}
}