{
  "type": "Feature",
  "properties": {
    "iso:country":"US",
    "sg:address":"4 E Port Rd",
    "sg:city":"West Palm Beach",
    "sg:classifiers":[
        {
            "category":"Organizations",
            "subcategory":"Professional Association",
            "type":"Services"
        }
    ],
    "sg:phone":"+1 561 842 7939",
    "sg:postcode":"33404",
    "sg:province":"FL",
    "sg:tags":[
        "business"
    ],
    "wof:name":"Journal of Commerce",
    "wof:placetype":"venue"
},
  "geometry": {"coordinates":[-80.053466,26.768008],"type":"Point"}
}