{
  "type": "Feature",
  "properties": {
    "iso:country":"US",
    "sg:address":"19910 Dinner Key Dr",
    "sg:city":"Boca Raton",
    "sg:classifiers":[
        {
            "category":"Professional",
            "subcategory":"Computer Services",
            "type":"Services"
        }
    ],
    "sg:phone":"+1 561 883 9815",
    "sg:postcode":"33498",
    "sg:province":"FL",
    "sg:tags":[
        "related"
    ],
    "wof:name":"5052 Advisors Inc",
    "wof:placetype":"venue"
},
  "geometry": {"coordinates":[-80.21278,26.379083],"type":"Point"}
}