{
  "type": "Feature",
  "properties": {
    "iso:country":"US",
    "sg:address":"1580 SW 191st Ter",
    "sg:city":"Hollywood",
    "sg:classifiers":[
        {
            "category":"Wholesale",
            "subcategory":"Non-durable Goods",
            "type":"Manufacturing & Wholesale Goods"
        }
    ],
    "sg:phone":"+1 954 442 4653",
    "sg:postcode":"33029",
    "sg:province":"FL",
    "sg:tags":[
        "surplus",
        "inventory"
    ],
    "wof:name":"Alufy International Inc",
    "wof:placetype":"venue"
},
  "geometry": {"coordinates":[-80.403189,25.995786],"type":"Point"}
}