{
  "type": "Feature",
  "properties": {
    "iso:country":"US",
    "sg:address":"3006 Pinedale Ave",
    "sg:city":"Lakeland",
    "sg:classifiers":[
        {
            "category":"Building & Trades",
            "subcategory":"Construction",
            "type":"Services"
        }
    ],
    "sg:phone":"+1 863 683 4836",
    "sg:postcode":"33803",
    "sg:province":"FL",
    "sg:tags":[
        "general",
        "contractor"
    ],
    "wof:name":"R L Construction & Title",
    "wof:placetype":"venue"
},
  "geometry": {"coordinates":[-81.932856,28.00953],"type":"Point"}
}