{
  "type": "Feature",
  "properties": {
    "addr:full":"7446 Brunswick Cir Boynton Beach FL 33472",
    "addr:housenumber":"7446",
    "addr:postcode":"33472",
    "addr:street":"Brunswick Cir",
    "iso:country":"US",
    "sg:address":"7446 Brunswick Cir",
    "sg:city":"Boynton Beach",
    "sg:classifiers":[
        {
            "category":"Banks & Credit Unions",
            "subcategory":"Bank",
            "type":"Services"
        }
    ],
    "sg:phone":"+1 561 733 8850",
    "sg:postcode":"33472",
    "sg:province":"FL",
    "sg:tags":[
        "loan",
        "real estate"
    ],
    "wof:name":"E Z Cash Mortgage",
    "wof:placetype":"venue"
},
  "geometry": {"coordinates":[-80.158041,26.544364],"type":"Point"}
}