{
  "type": "Feature",
  "properties": {
    "addr:full":"1011 N 23rd St Fort Pierce FL 34950",
    "addr:housenumber":"1011",
    "addr:postcode":"34950",
    "addr:street":"N 23Rd St",
    "iso:country":"US",
    "sg:address":"1011 N 23rd St",
    "sg:city":"Fort Pierce",
    "sg:classifiers":[
        {
            "category":"Social Services",
            "type":"Services"
        }
    ],
    "sg:phone":"+1 772 460 7868",
    "sg:postcode":"34950",
    "sg:province":"FL",
    "sg:tags":[
        "youth",
        "organization",
        "center"
    ],
    "wof:name":"Boy's & Girls Club Of St Lucie",
    "wof:placetype":"venue"
},
  "geometry": {"coordinates":[-80.347869,27.460151],"type":"Point"}
}