{
  "type": "Feature",
  "properties": {
    "addr:full":"757 Creekwater Ter Lake Mary FL 32746",
    "addr:housenumber":"757",
    "addr:postcode":"32746",
    "addr:street":"Creekwater Ter;Mary",
    "iso:country":"US",
    "sg:address":"757 Creekwater Ter",
    "sg:city":"Lake Mary",
    "sg:classifiers":[
        {
            "category":"Food & Beverages",
            "subcategory":"Groceries & Convenience Stores",
            "type":"Retail Goods"
        }
    ],
    "sg:phone":"+1 407 330 2822",
    "sg:postcode":"32746",
    "sg:province":"FL",
    "wof:name":"Market Choice Inc",
    "wof:placetype":"venue"
},
  "geometry": {"coordinates":[-81.34486099999999,28.750268],"type":"Point"}
}