{
  "type": "Feature",
  "properties": {
    "addr:full":"4400 Dixie Hwy NE Palm Bay FL 32905",
    "addr:housenumber":"4400",
    "addr:postcode":"32905",
    "addr:street":"Dixie Hwy Ne",
    "iso:country":"US",
    "sg:address":"4400 Dixie Hwy NE",
    "sg:city":"Palm Bay",
    "sg:classifiers":[
        {
            "category":"Education",
            "subcategory":"School",
            "type":"Public Place"
        }
    ],
    "sg:phone":"+1 321 253 8926",
    "sg:postcode":"32905",
    "sg:province":"FL",
    "wof:name":"Milestones Community School",
    "wof:placetype":"venue"
},
  "geometry": {"coordinates":[-80.57783999999999,28.031046],"type":"Point"}
}