{
  "type": "Feature",
  "properties": {
    "iso:country":"US",
    "sg:address":"6931 Longmeade Ln",
    "sg:city":"Orlando",
    "sg:classifiers":[
        {
            "category":"Restaurant",
            "type":"Food & Drink"
        }
    ],
    "sg:phone":"+1 407 306 8388",
    "sg:postcode":"32822",
    "sg:province":"FL",
    "sg:tags":[
        "eating"
    ],
    "wof:name":"Tasty Dogs",
    "wof:placetype":"venue"
},
  "geometry": {"coordinates":[-81.296683,28.490279],"type":"Point"}
}