{
  "type": "Feature",
  "properties": {
    "iso:country":"US",
    "sg:address":"1400 S Woodland Blvd",
    "sg:city":"Deland",
    "sg:classifiers":[
        {
            "category":"Restaurant",
            "type":"Food & Drink"
        }
    ],
    "sg:phone":"+1 386 734 4471",
    "sg:postcode":"32720",
    "sg:province":"FL",
    "sg:website":"www.arbys.com",
    "wof:name":"Arby's",
    "wof:placetype":"venue"
},
  "geometry": {"coordinates":[-81.306999,28.9991],"type":"Point"}
}