{
  "type": "Feature",
  "properties": {
    "addr:full":"5211 NE 2nd Ave Miami FL 33137",
    "addr:housenumber":"5211",
    "addr:postcode":"33137",
    "addr:street":"Ne 2Nd Ave",
    "iso:country":"US",
    "sg:address":"5211 NE 2nd Ave",
    "sg:city":"Miami",
    "sg:classifiers":[
        {
            "category":"Health Services",
            "subcategory":"Doctor",
            "type":"Services"
        }
    ],
    "sg:phone":"+1 305 751 1293",
    "sg:postcode":"33137",
    "sg:province":"FL",
    "sg:tags":[
        "clinic"
    ],
    "wof:name":"Sunrise Medical Ctr",
    "wof:placetype":"venue"
},
  "geometry": {"coordinates":[-80.191761,25.824491],"type":"Point"}
}