{
  "type": "Feature",
  "properties": {
    "addr:full":"9001 Pembroke Rd Hollywood FL 33025",
    "addr:housenumber":"9001",
    "addr:postcode":"33025",
    "addr:street":"Pembroke Rd",
    "iso:country":"US",
    "sg:address":"9001 Pembroke Rd",
    "sg:city":"Hollywood",
    "sg:classifiers":[
        {
            "category":"Food & Beverages",
            "subcategory":"Groceries & Convenience Stores",
            "type":"Retail Goods"
        }
    ],
    "sg:phone":"+1 954 437 9744",
    "sg:postcode":"33025",
    "sg:province":"FL",
    "wof:name":"Kingston Caribbean Market Pl",
    "wof:placetype":"venue"
},
  "geometry": {"coordinates":[-80.26421000000001,25.994287],"type":"Point"}
}