{
  "type": "Feature",
  "properties": {
    "iso:country":"US",
    "sg:address":"9850 16th St N",
    "sg:city":"Saint Petersburg",
    "sg:classifiers":[
        {
            "category":"Wholesale",
            "subcategory":"Electrical",
            "type":"Manufacturing & Wholesale Goods"
        }
    ],
    "sg:phone":"+1 727 576 0550",
    "sg:postcode":"33716",
    "sg:province":"FL",
    "sg:tags":[
        "electronic"
    ],
    "wof:name":"New Advantage",
    "wof:placetype":"venue"
},
  "geometry": {"coordinates":[-82.65523899999999,27.860023],"type":"Point"}
}