{
  "type": "Feature",
  "properties": {
    "iso:country":"US",
    "sg:address":"3572 Hwy 69",
    "sg:city":"Grand Ridge",
    "sg:classifiers":[
        {
            "category":"Building & Trades",
            "subcategory":"Construction",
            "type":"Services"
        }
    ],
    "sg:phone":"+1 850 592 4431",
    "sg:postcode":"32442",
    "sg:province":"FL",
    "sg:tags":[
        "house"
    ],
    "wof:name":"Jerry L Neeel Construction",
    "wof:placetype":"venue"
},
  "geometry": {"coordinates":[-85.04861699999999,30.821883],"type":"Point"}
}