{
  "type": "Feature",
  "properties": {
    "iso:country":"US",
    "sg:address":"831 S Ponce de Leon Blvd",
    "sg:city":"St Augustine",
    "sg:classifiers":[
        {
            "category":"Shopping",
            "subcategory":"Gifts & Souvenirs",
            "type":"Retail Goods"
        },
        {
            "category":"Shopping",
            "subcategory":"Clothing, Apparel, & Fashions",
            "type":"Retail Goods"
        }
    ],
    "sg:phone":"+1 904 823 9499",
    "sg:postcode":"32084",
    "sg:province":"FL",
    "sg:tags":[
        "lingerie"
    ],
    "wof:name":"Fantasy Lane",
    "wof:placetype":"venue"
},
  "geometry": {"coordinates":[-81.32514500000001,29.881699],"type":"Point"}
}