{
  "type": "Feature",
  "properties": {
    "iso:country":"US",
    "sg:address":"815 N Pine Hills Rd",
    "sg:city":"Orlando",
    "sg:classifiers":[
        {
            "category":"Health Services",
            "subcategory":"Chiropractor",
            "type":"Services"
        }
    ],
    "sg:phone":"+1 407 294 8889",
    "sg:postcode":"32808",
    "sg:province":"FL",
    "sg:tags":[
        "chiropractic"
    ],
    "wof:name":"First Chiropractic Clinic",
    "wof:placetype":"venue"
},
  "geometry": {"coordinates":[-81.447549,28.554783],"type":"Point"}
}