{
  "type": "Feature",
  "properties": {
    "addr:full":"8001 US Hwy 19 Pinellas Park FL 33714",
    "addr:housenumber":"8001",
    "addr:postcode":"33714",
    "addr:street":"Us Hwy 19",
    "iso:country":"US",
    "sg:address":"8001 US Hwy 19",
    "sg:city":"Pinellas Park",
    "sg:classifiers":[
        {
            "category":"Shopping",
            "subcategory":"Department Store",
            "type":"Retail Goods"
        }
    ],
    "sg:phone":"+1 727 576 1770",
    "sg:postcode":"33714",
    "sg:province":"FL",
    "sg:website":"www.walmart.com",
    "wof:name":"Wal-Mart Supercenter",
    "wof:placetype":"venue"
},
  "geometry": {"coordinates":[-82.688954,27.846563],"type":"Point"}
}