{
  "type": "Feature",
  "properties": {
    "iso:country":"US",
    "sg:address":"1594 Willow Bend Way",
    "sg:city":"Tallahassee",
    "sg:classifiers":[
        {
            "category":"Retail",
            "subcategory":"Car Wash",
            "type":"Services"
        }
    ],
    "sg:phone":"+1 850 878 2524",
    "sg:postcode":"32301",
    "sg:province":"FL",
    "sg:tags":[
        "automobile",
        "detail",
        "clean"
    ],
    "wof:name":"Blue Sun Mobile Detailing",
    "wof:placetype":"venue"
},
  "geometry": {"coordinates":[-84.249619,30.416951],"type":"Point"}
}