{
  "type": "Feature",
  "properties": {
    "addr:full":"7441 Forrest St Hollywood FL 33024",
    "addr:housenumber":"7441",
    "addr:postcode":"33024",
    "addr:street":"Forrest St",
    "iso:country":"US",
    "sg:address":"7441 Forrest St",
    "sg:city":"Hollywood",
    "sg:classifiers":[
        {
            "category":"Shopping",
            "subcategory":"Books",
            "type":"Retail Goods"
        }
    ],
    "sg:phone":"+1 954 962 1131",
    "sg:postcode":"33024",
    "sg:province":"FL",
    "wof:name":"Book em Donna Travel",
    "wof:placetype":"venue"
},
  "geometry": {"coordinates":[-80.237934,26.035732],"type":"Point"}
}