{
  "type": "Feature",
  "properties": {
    "addr:full":"3201 SW 34th Ave Ocala FL 34474",
    "addr:housenumber":"3201",
    "addr:postcode":"34474",
    "addr:street":"Sw 34Th Ave",
    "iso:country":"US",
    "sg:address":"3201 SW 34th Ave",
    "sg:city":"Ocala",
    "sg:classifiers":[
        {
            "category":"Farming",
            "subcategory":"Livestock Farm",
            "type":"Manufacturing & Wholesale Goods"
        }
    ],
    "sg:phone":"+1 352 873 9400",
    "sg:postcode":"34474",
    "sg:province":"FL",
    "sg:tags":[
        "ranch"
    ],
    "wof:name":"R P Ranch",
    "wof:placetype":"venue"
},
  "geometry": {"coordinates":[-82.177684,29.154715],"type":"Point"}
}