{
  "type": "Feature",
  "properties": {
    "iso:country":"US",
    "sg:address":"2230 SE 19th Pl",
    "sg:city":"Cape Coral",
    "sg:classifiers":[
        {
            "category":"Banks & Credit Unions",
            "subcategory":"Bank",
            "type":"Services"
        }
    ],
    "sg:phone":"+1 239 573 5107",
    "sg:postcode":"33990",
    "sg:province":"FL",
    "sg:tags":[
        "broker",
        "mortgage"
    ],
    "wof:name":"Lending Specialist Group Inc",
    "wof:placetype":"venue"
},
  "geometry": {"coordinates":[-81.932829,26.610427],"type":"Point"}
}