{
  "type": "Feature",
  "properties": {
    "iso:country":"US",
    "sg:address":"1598 Manor Way",
    "sg:city":"De Land",
    "sg:classifiers":[
        {
            "category":"Museum",
            "type":"Entertainment"
        }
    ],
    "sg:phone":"+1 386 985 9342",
    "sg:postcode":"32720",
    "sg:province":"FL",
    "sg:tags":[
        "gallery"
    ],
    "wof:name":"Tropical Silks",
    "wof:placetype":"venue"
},
  "geometry": {"coordinates":[-81.34943,29.100033],"type":"Point"}
}