{
  "type": "Feature",
  "properties": {
    "addr:full":"9143 Phillips Hwy Jacksonville FL 32256",
    "addr:housenumber":"9143",
    "addr:postcode":"32256",
    "addr:street":"Phillips Hwy",
    "iso:country":"US",
    "sg:address":"9143 Phillips Hwy",
    "sg:city":"Jacksonville",
    "sg:classifiers":[
        {
            "category":"Banks & Credit Unions",
            "subcategory":"Bank",
            "type":"Services"
        }
    ],
    "sg:phone":"+1 904 363 1002",
    "sg:postcode":"32256",
    "sg:province":"FL",
    "sg:tags":[
        "mortgage"
    ],
    "wof:name":"Wells Fargo",
    "wof:placetype":"venue"
},
  "geometry": {"coordinates":[-81.573516,30.201524],"type":"Point"}
}