{
  "type": "Feature",
  "properties": {
    "iso:country":"US",
    "sg:address":"110 Baywood Ave",
    "sg:city":"Longwood",
    "sg:classifiers":[
        {
            "category":"Manufacturing",
            "subcategory":"Printing",
            "type":"Manufacturing & Wholesale Goods"
        }
    ],
    "sg:phone":"+1 407 834 2011",
    "sg:postcode":"32750",
    "sg:province":"FL",
    "sg:tags":[
        "commercial"
    ],
    "wof:name":"Copy Van Printing Pegboard",
    "wof:placetype":"venue"
},
  "geometry": {"coordinates":[-81.339958,28.718248],"type":"Point"}
}