{
  "type": "Feature",
  "properties": {
    "iso:country":"US",
    "sg:address":"11260 SW 52nd Ter",
    "sg:city":"Miami",
    "sg:classifiers":[
        {
            "category":"Building & Trades",
            "subcategory":"Plumbing",
            "type":"Services"
        }
    ],
    "sg:phone":"+1 305 279 2326",
    "sg:postcode":"33165",
    "sg:province":"FL",
    "wof:name":"Arko Plumbing",
    "wof:placetype":"venue"
},
  "geometry": {"coordinates":[-80.376699,25.718058],"type":"Point"}
}