{
  "type": "Feature",
  "properties": {
    "iso:country":"US",
    "sg:address":"8801 Grow Dr",
    "sg:city":"Pensacola",
    "sg:classifiers":[
        {
            "category":"Manufacturing",
            "subcategory":"Food",
            "type":"Manufacturing & Wholesale Goods"
        }
    ],
    "sg:phone":"+1 850 243 3932",
    "sg:postcode":"32514",
    "sg:province":"FL",
    "sg:tags":[
        "soft",
        "grocery",
        "drink",
        "comm",
        "mfg"
    ],
    "wof:name":"Pepsico",
    "wof:placetype":"venue"
},
  "geometry": {"coordinates":[-87.190056,30.522646],"type":"Point"}
}