{
  "type": "Feature",
  "properties": {
    "iso:country":"US",
    "sg:address":"12994 Beacon Cove Ln",
    "sg:city":"Fort Myers",
    "sg:classifiers":[
        {
            "category":"Wholesale",
            "subcategory":"Apparel",
            "type":"Manufacturing & Wholesale Goods"
        }
    ],
    "sg:phone":"+1 239 482 4851",
    "sg:postcode":"33919",
    "sg:province":"FL",
    "sg:tags":[
        "shoes"
    ],
    "wof:name":"Lioness Intl Corp of SW Fla",
    "wof:placetype":"venue"
},
  "geometry": {"coordinates":[-81.918104,26.553252],"type":"Point"}
}