{
  "type": "Feature",
  "properties": {
    "iso:country":"US",
    "sg:address":"141 W Granada Blvd",
    "sg:city":"Ormond Beach",
    "sg:classifiers":[
        {
            "category":"Food & Beverages",
            "subcategory":"Specialty",
            "type":"Retail Goods"
        }
    ],
    "sg:phone":"+1 386 672 6004",
    "sg:postcode":"32174",
    "sg:province":"FL",
    "sg:tags":[
        "health",
        "diet"
    ],
    "wof:name":"Living Waters Discount Health",
    "wof:placetype":"venue"
},
  "geometry": {"coordinates":[-81.05945699999999,29.284254],"type":"Point"}
}