{
  "type": "Feature",
  "properties": {
    "iso:country":"US",
    "sg:address":"181 Sabal Palm Dr Ste 101",
    "sg:city":"Longwood",
    "sg:classifiers":[
        {
            "category":"Professional",
            "subcategory":"Employment Agencies",
            "type":"Services"
        },
        {
            "category":"Shopping",
            "subcategory":"Pharmacy",
            "type":"Retail Goods"
        }
    ],
    "sg:phone":"+1 407 682 3211",
    "sg:postcode":"32779",
    "sg:province":"FL",
    "sg:tags":[
        "drugstore"
    ],
    "wof:name":"Healthcare Consultants Pharmacy Staff",
    "wof:placetype":"venue"
},
  "geometry": {"coordinates":[-81.416,28.703699],"type":"Point"}
}