{
  "type": "Feature",
  "properties": {
    "iso:country":"US",
    "sg:address":"20533 Biscayne Blvd",
    "sg:city":"Miami",
    "sg:classifiers":[
        {
            "category":"Home & Garden",
            "subcategory":"Furniture",
            "type":"Retail Goods"
        }
    ],
    "sg:phone":"+1 305 935 0001",
    "sg:postcode":"33180",
    "sg:province":"FL",
    "wof:name":"Albaraka Partners Inc",
    "wof:placetype":"venue"
},
  "geometry": {"coordinates":[-80.145946,25.966192],"type":"Point"}
}