{
  "type": "Feature",
  "properties": {
    "addr:full":"2935 N Bay Rd Miami Beach FL 33140",
    "addr:housenumber":"2935",
    "addr:postcode":"33140",
    "addr:street":"N Bay Rd",
    "iso:country":"US",
    "sg:address":"2935 N Bay Rd",
    "sg:city":"Miami Beach",
    "sg:classifiers":[
        {
            "category":"Manufacturing",
            "subcategory":"Tools & Machinery",
            "type":"Manufacturing & Wholesale Goods"
        }
    ],
    "sg:phone":"+1 305 672 5280",
    "sg:postcode":"33140",
    "sg:province":"FL",
    "sg:tags":[
        "mfg",
        "ophthalmic"
    ],
    "wof:name":"Optor of Florida Mfg & Trdg",
    "wof:placetype":"venue"
},
  "geometry": {"coordinates":[-80.136517,25.808714],"type":"Point"}
}