{
  "type": "Feature",
  "properties": {
    "iso:country":"US",
    "sg:address":"3351 Phonetia Dr",
    "sg:city":"Deltona",
    "sg:classifiers":[
        {
            "category":"Professional",
            "subcategory":"Detective & Security Services",
            "type":"Services"
        }
    ],
    "sg:phone":"+1 386 801 5962",
    "sg:postcode":"32738",
    "sg:province":"FL",
    "sg:tags":[
        "information",
        "bureau"
    ],
    "wof:name":"Comodo Service Corp",
    "wof:placetype":"venue"
},
  "geometry": {"coordinates":[-81.17019999999999,28.880645],"type":"Point"}
}