{
  "type": "Feature",
  "properties": {
    "iso:country":"US",
    "sg:address":"8220 Kristel Cir",
    "sg:city":"Port Richey",
    "sg:classifiers":[
        {
            "category":"Building & Trades",
            "subcategory":"Landscaping Services",
            "type":"Services"
        }
    ],
    "sg:phone":"+1 727 938 0747",
    "sg:postcode":"34668",
    "sg:province":"FL",
    "wof:name":"First Choice Lawn Care",
    "wof:placetype":"venue"
},
  "geometry": {"coordinates":[-82.67909,28.28221],"type":"Point"}
}