{
  "type": "Feature",
  "properties": {
    "addr:full":"1630 S Federal Hwy Delray Beach FL 33483",
    "addr:housenumber":"1630",
    "addr:postcode":"33483",
    "addr:street":"S Federal Hwy",
    "iso:country":"US",
    "sg:address":"1630 S Federal Hwy",
    "sg:city":"Delray Beach",
    "sg:classifiers":[
        {
            "category":"Shopping",
            "subcategory":"Books",
            "type":"Retail Goods"
        }
    ],
    "sg:phone":"+1 561 243 3395",
    "sg:postcode":"33483",
    "sg:province":"FL",
    "sg:tags":[
        "bookstore"
    ],
    "sg:website":"www.booksamillion.com",
    "wof:name":"Books-A-Million",
    "wof:placetype":"venue"
},
  "geometry": {"coordinates":[-80.071155,26.440064],"type":"Point"}
}