{
  "type": "Feature",
  "properties": {
    "iso:country":"US",
    "sg:address":"150 E Columbia Ln",
    "sg:city":"Cocoa Beach",
    "sg:classifiers":[
        {
            "category":"Retail",
            "subcategory":"Animal Services",
            "type":"Services"
        }
    ],
    "sg:phone":"+1 321 799 4027",
    "sg:postcode":"32931",
    "sg:province":"FL",
    "wof:name":"Shear Canine",
    "wof:placetype":"venue"
},
  "geometry": {"coordinates":[-80.60661899999999,28.35888],"type":"Point"}
}