{
  "type": "Feature",
  "properties": {
    "addr:full":"718 Powell Dr Niceville FL 32578",
    "addr:housenumber":"718",
    "addr:postcode":"32578",
    "addr:street":"Powell Dr",
    "iso:country":"US",
    "sg:address":"718 Powell Dr",
    "sg:city":"Niceville",
    "sg:classifiers":[
        {
            "category":"Building & Trades",
            "subcategory":"Construction",
            "type":"Services"
        }
    ],
    "sg:phone":"+1 850 729 2908",
    "sg:postcode":"32578",
    "sg:province":"FL",
    "sg:tags":[
        "house"
    ],
    "wof:name":"Pd & B",
    "wof:placetype":"venue"
},
  "geometry": {"coordinates":[-86.478127,30.522513],"type":"Point"}
}