{
  "type": "Feature",
  "properties": {
    "iso:country":"US",
    "sg:address":"530 Nokomis Ave S",
    "sg:city":"Venice",
    "sg:classifiers":[
        {
            "category":"Health Services",
            "subcategory":"Doctor",
            "type":"Services"
        }
    ],
    "sg:phone":"+1 941 486 6120",
    "sg:postcode":"34285",
    "sg:province":"FL",
    "sg:tags":[
        "medical"
    ],
    "wof:name":"William H Wagner MD",
    "wof:placetype":"venue"
},
  "geometry": {"coordinates":[-82.445599,27.090551],"type":"Point"}
}