{
  "type": "Feature",
  "properties": {
    "iso:country":"US",
    "sg:address":"101 W 1st St Ste C",
    "sg:city":"Sanford",
    "sg:classifiers":[
        {
            "category":"Professional",
            "subcategory":"Lawyer & Legal Services",
            "type":"Services"
        }
    ],
    "sg:phone":"+1 407 324 2200",
    "sg:postcode":"32771",
    "sg:province":"FL",
    "sg:tags":[
        "attorney",
        "law",
        "family",
        "divorce",
        "practice",
        "criminal",
        "bankruptcy"
    ],
    "wof:name":"Colegrove Richard A Attorney At Law",
    "wof:placetype":"venue"
},
  "geometry": {"coordinates":[-81.26799800000001,28.811729],"type":"Point"}
}