{
  "type": "Feature",
  "properties": {
    "addr:full":"855 E 8th Ave Hialeah FL 33010",
    "addr:housenumber":"855",
    "addr:postcode":"33010",
    "addr:street":"E 8Th Ave",
    "iso:country":"US",
    "sg:address":"855 E 8th Ave",
    "sg:city":"Hialeah",
    "sg:classifiers":[
        {
            "category":"Shopping",
            "subcategory":"Pharmacy",
            "type":"Retail Goods"
        }
    ],
    "sg:phone":"+1 305 888 5598",
    "sg:postcode":"33010",
    "sg:province":"FL",
    "sg:tags":[
        "drugstore"
    ],
    "sg:website":"www.cvs.com",
    "wof:name":"Cvs Pharmacy",
    "wof:placetype":"venue"
},
  "geometry": {"coordinates":[-80.26532,25.830114],"type":"Point"}
}