{
  "type": "Feature",
  "properties": {
    "iso:country":"US",
    "sg:address":"2400 Wahnish Way",
    "sg:city":"Tallahassee",
    "sg:classifiers":[
        {
            "category":"Education",
            "subcategory":"University",
            "type":"Public Place"
        }
    ],
    "sg:phone":"+1 850 599 3256",
    "sg:postcode":"32310",
    "sg:province":"FL",
    "sg:tags":[
        "college"
    ],
    "sg:website":"http://www.famu.edu",
    "wof:name":"Florida A & M University",
    "wof:placetype":"venue"
},
  "geometry": {"coordinates":[-84.28967299999999,30.417248],"type":"Point"}
}