{
  "type": "Feature",
  "properties": {
    "addr:full":"8690 SW 137th Ct Miami FL 33183",
    "addr:housenumber":"8690",
    "addr:postcode":"33183",
    "addr:street":"Sw 137Th Ct",
    "iso:country":"US",
    "sg:address":"8690 SW 137th Ct",
    "sg:city":"Miami",
    "sg:classifiers":[
        {
            "category":"Home & Garden",
            "subcategory":"Building Materials",
            "type":"Retail Goods"
        }
    ],
    "sg:phone":"+1 305 595 5880",
    "sg:postcode":"33183",
    "sg:province":"FL",
    "sg:tags":[
        "paint"
    ],
    "sg:website":"www.o-geepaint.com",
    "wof:name":"O-Gee Paint Co",
    "wof:placetype":"venue"
},
  "geometry": {"coordinates":[-80.417715,25.68657],"type":"Point"}
}