{
  "type": "Feature",
  "properties": {
    "addr:full":"11900 SW 222nd St Miami FL 33170",
    "addr:housenumber":"11900",
    "addr:postcode":"33170",
    "addr:street":"Sw 222Nd St",
    "iso:country":"US",
    "sg:address":"11900 SW 222nd St",
    "sg:city":"Miami",
    "sg:classifiers":[
        {
            "category":"Utilities",
            "subcategory":"Telephone",
            "type":"Services"
        }
    ],
    "sg:phone":"+1 305 257 3095",
    "sg:postcode":"33170",
    "sg:province":"FL",
    "sg:tags":[
        "company"
    ],
    "wof:name":"Mastec Ifitl",
    "wof:placetype":"venue"
},
  "geometry": {"coordinates":[-80.385347,25.560805],"type":"Point"}
}