{
  "type": "Feature",
  "properties": {
    "addr:full":"1440 Coral Ridge Dr Pompano Beach FL 33071",
    "addr:housenumber":"1440",
    "addr:postcode":"33071",
    "addr:street":"Coral Ridge Dr",
    "iso:country":"US",
    "sg:address":"1440 Coral Ridge Dr",
    "sg:city":"Pompano Beach",
    "sg:classifiers":[
        {
            "category":"Professional",
            "subcategory":"Management & Consulting",
            "type":"Services"
        }
    ],
    "sg:phone":"+1 954 755 7094",
    "sg:postcode":"33071",
    "sg:province":"FL",
    "sg:tags":[
        "business"
    ],
    "wof:name":"Susan Larue Design Services",
    "wof:placetype":"venue"
},
  "geometry": {"coordinates":[-80.279893,26.249047],"type":"Point"}
}