{
  "type": "Feature",
  "properties": {
    "iso:country":"US",
    "sg:address":"25 Homestead Rd S",
    "sg:city":"Lehigh Acres",
    "sg:classifiers":[
        {
            "category":"Shopping",
            "type":"Retail Goods"
        }
    ],
    "sg:phone":"+1 239 369 6717",
    "sg:postcode":"33936",
    "sg:province":"FL",
    "sg:tags":[
        "pool",
        "supply"
    ],
    "wof:name":"Pool Keepers Plus Inc",
    "wof:placetype":"venue"
},
  "geometry": {"coordinates":[-81.639927,26.597914],"type":"Point"}
}