{
  "type": "Feature",
  "properties": {
    "iso:country":"US",
    "sg:address":"2470 W. Us Hwy 90",
    "sg:city":"Lake City",
    "sg:classifiers":[
        {
            "category":"Restaurant",
            "type":"Food & Drink"
        }
    ],
    "sg:menulink":"http://www.allmenus.com/fl/lake-city/158311-el-potro/menu/",
    "sg:phone":"+1 386 758 3100",
    "sg:postcode":"32055",
    "sg:province":"FL",
    "sg:tags":[
        "mexican"
    ],
    "wof:name":"El Potro",
    "wof:placetype":"venue"
},
  "geometry": {"coordinates":[-82.65630400000001,30.183482],"type":"Point"}
}