{
  "type": "Feature",
  "properties": {
    "addr:full":"214 Avant Ave Sarasota FL 34232",
    "addr:housenumber":"214",
    "addr:postcode":"34232",
    "addr:street":"Avant Ave",
    "iso:country":"US",
    "sg:address":"214 Avant Ave",
    "sg:city":"Sarasota",
    "sg:classifiers":[
        {
            "category":"Professional",
            "subcategory":"Management & Consulting",
            "type":"Services"
        }
    ],
    "sg:phone":"+1 941 371 7752",
    "sg:postcode":"34232",
    "sg:province":"FL",
    "sg:tags":[
        "personnel",
        "consultant"
    ],
    "wof:name":"Pharmaceutical Mgmt Res",
    "wof:placetype":"venue"
},
  "geometry": {"coordinates":[-82.469076,27.338543],"type":"Point"}
}