{
  "type": "Feature",
  "properties": {
    "iso:country":"US",
    "sg:address":"1966 NE 163rd St",
    "sg:city":"North Miami Bch",
    "sg:classifiers":[
        {
            "category":"Personal",
            "subcategory":"Beauty Salon",
            "type":"Services"
        }
    ],
    "sg:phone":"+1 305 947 0931",
    "sg:postcode":"33162",
    "sg:province":"FL",
    "wof:name":"Elisa & Sal Haircutters",
    "wof:placetype":"venue"
},
  "geometry": {"coordinates":[-80.161089,25.925927],"type":"Point"}
}