{
  "type": "Feature",
  "properties": {
    "addr:full":"9367 Gotha Rd Windermere FL 34786",
    "addr:housenumber":"9367",
    "addr:postcode":"34786",
    "addr:street":"Gotha Rd",
    "iso:country":"US",
    "sg:address":"9367 Gotha Rd",
    "sg:city":"Windermere",
    "sg:classifiers":[
        {
            "category":"Restaurant",
            "type":"Food & Drink"
        }
    ],
    "sg:phone":"+1 407 299 0229",
    "sg:postcode":"34786",
    "sg:province":"FL",
    "sg:tags":[
        "mexican"
    ],
    "wof:name":"Papi's Tacos",
    "wof:placetype":"venue"
},
  "geometry": {"coordinates":[-81.515514,28.52776],"type":"Point"}
}