{
  "type": "Feature",
  "properties": {
    "iso:country":"US",
    "sg:address":"28 Columbia Dr",
    "sg:city":"Tampa",
    "sg:classifiers":[
        {
            "category":"Organizations",
            "subcategory":"Membership Organization",
            "type":"Services"
        }
    ],
    "sg:phone":"+1 813 258 6430",
    "sg:postcode":"33606",
    "sg:province":"FL",
    "sg:tags":[
        "charitable"
    ],
    "wof:name":"Ronald Mc Donald Houses",
    "wof:placetype":"venue"
},
  "geometry": {"coordinates":[-82.459047,27.936516],"type":"Point"}
}