{
  "type": "Feature",
  "properties": {
    "iso:country":"US",
    "sg:address":"2301 SW 13th St",
    "sg:city":"Miami",
    "sg:classifiers":[
        {
            "category":"Recreation",
            "type":"Entertainment"
        }
    ],
    "sg:postcode":"33145",
    "sg:province":"FL",
    "sg:tags":[
        "park"
    ],
    "wof:name":"Bryan Park",
    "wof:placetype":"venue"
},
  "geometry": {"coordinates":[-80.23254,25.760391],"type":"Point"}
}