{
  "type": "Feature",
  "properties": {
    "iso:country":"US",
    "sg:address":"107 S 34th St",
    "sg:city":"Tampa",
    "sg:classifiers":[
        {
            "category":"Utilities",
            "subcategory":"Recycling",
            "type":"Services"
        }
    ],
    "sg:phone":"+1 813 248 1457",
    "sg:postcode":"33605",
    "sg:province":"FL",
    "sg:tags":[
        "disposal",
        "waste",
        "equipment"
    ],
    "wof:name":"Wheelabrator Mckay Bay Inc.",
    "wof:placetype":"venue"
},
  "geometry": {"coordinates":[-82.42231,27.946509],"type":"Point"}
}