{
  "type": "Feature",
  "properties": {
    "addr:full":"8214 Westridge Dr Tampa FL 33615",
    "addr:housenumber":"8214",
    "addr:postcode":"33615",
    "addr:street":"Westridge Dr",
    "iso:country":"US",
    "sg:address":"8214 Westridge Dr",
    "sg:city":"Tampa",
    "sg:classifiers":[
        {
            "category":"Restaurant",
            "type":"Food & Drink"
        }
    ],
    "sg:phone":"+1 813 889 9369",
    "sg:postcode":"33615",
    "sg:province":"FL",
    "sg:tags":[
        "eating"
    ],
    "wof:name":"A & J Restaurants Inc",
    "wof:placetype":"venue"
},
  "geometry": {"coordinates":[-82.571682,28.023765],"type":"Point"}
}