{
  "type": "Feature",
  "properties": {
    "iso:country":"US",
    "sg:address":"1901 Clifford St",
    "sg:city":"Fort Myers",
    "sg:classifiers":[
        {
            "category":"Real Estate",
            "subcategory":"Real Estate Agent",
            "type":"Services"
        }
    ],
    "sg:phone":"+1 239 332 7378",
    "sg:postcode":"33901",
    "sg:province":"FL",
    "wof:name":"Thomas J Propertie",
    "wof:placetype":"venue"
},
  "geometry": {"coordinates":[-81.877269,26.639091],"type":"Point"}
}