{
  "type": "Feature",
  "properties": {
    "addr:full":"20609 Biscayne Blvd Miami FL 33180",
    "addr:housenumber":"20609",
    "addr:postcode":"33180",
    "addr:street":"Biscayne Blvd",
    "iso:country":"US",
    "sg:address":"20609 Biscayne Blvd",
    "sg:city":"Miami",
    "sg:classifiers":[
        {
            "category":"Shopping",
            "subcategory":"Hobbies, Toys, & Games",
            "type":"Retail Goods"
        }
    ],
    "sg:phone":"+1 305 937 2100",
    "sg:postcode":"33180",
    "sg:province":"FL",
    "sg:tags":[
        "arts",
        "craft"
    ],
    "wof:name":"Michaels 9823",
    "wof:placetype":"venue"
},
  "geometry": {"coordinates":[-80.14502899999999,25.967757],"type":"Point"}
}