{
  "type": "Feature",
  "properties": {
    "addr:full":"4052 Hollis Ave Port Charlotte FL 33953",
    "addr:housenumber":"4052",
    "addr:postcode":"33953",
    "addr:street":"Hollis Ave",
    "iso:country":"US",
    "sg:address":"4052 Hollis Ave",
    "sg:city":"Port Charlotte",
    "sg:classifiers":[
        {
            "category":"Real Estate",
            "subcategory":"Real Estate Operator",
            "type":"Services"
        }
    ],
    "sg:phone":"+1 941 625 1006",
    "sg:postcode":"33953",
    "sg:province":"FL",
    "sg:tags":[
        "mobile",
        "home",
        "community"
    ],
    "wof:name":"Vizcaya Lakes",
    "wof:placetype":"venue"
},
  "geometry": {"coordinates":[-82.207763,26.971966],"type":"Point"}
}