{
  "type": "Feature",
  "properties": {
    "addr:full":"4010 Hollow Crossing Dr Orlando FL 32817",
    "addr:housenumber":"4010",
    "addr:postcode":"32817",
    "addr:street":"Hollow Crossing Dr",
    "iso:country":"US",
    "sg:address":"4010 Hollow Crossing Dr",
    "sg:city":"Orlando",
    "sg:classifiers":[
        {
            "category":"Food & Beverages",
            "subcategory":"Groceries & Convenience Stores",
            "type":"Retail Goods"
        }
    ],
    "sg:phone":"+1 407 657 8210",
    "sg:postcode":"32817",
    "sg:province":"FL",
    "wof:name":"Soorya Food Inc",
    "wof:placetype":"venue"
},
  "geometry": {"coordinates":[-81.245428,28.594567],"type":"Point"}
}