{
  "type": "Feature",
  "properties": {
    "iso:country":"US",
    "sg:address":"10 NW 42nd Ave",
    "sg:city":"Miami",
    "sg:classifiers":[
        {
            "category":"Airport",
            "type":"Transportation"
        }
    ],
    "sg:phone":"+1 305 446 2288",
    "sg:postcode":"33126",
    "sg:province":"FL",
    "sg:tags":[
        "support",
        "airline"
    ],
    "wof:name":"Business Representation Intl",
    "wof:placetype":"venue"
},
  "geometry": {"coordinates":[-80.263797,25.772475],"type":"Point"}
}