{
  "type": "Feature",
  "properties": {
    "iso:country":"US",
    "sg:address":"922 Clint Moore Rd",
    "sg:city":"Boca Raton",
    "sg:classifiers":[
        {
            "category":"Building & Trades",
            "subcategory":"Construction",
            "type":"Services"
        }
    ],
    "sg:phone":"+1 561 997 2636",
    "sg:postcode":"33487",
    "sg:province":"FL",
    "sg:tags":[
        "restore",
        "marble",
        "install",
        "wholesale"
    ],
    "wof:name":"Marble Kare",
    "wof:placetype":"venue"
},
  "geometry": {"coordinates":[-80.10332200000001,26.40817],"type":"Point"}
}