{
  "type": "Feature",
  "properties": {
    "addr:full":"1803 32nd St W Bradenton FL 34205",
    "addr:housenumber":"1803",
    "addr:postcode":"34205",
    "addr:street":"32Nd St W",
    "iso:country":"US",
    "sg:address":"1803 32nd St W",
    "sg:city":"Bradenton",
    "sg:classifiers":[
        {
            "category":"Professional",
            "type":"Services"
        }
    ],
    "sg:phone":"+1 941 749 7050",
    "sg:postcode":"34205",
    "sg:province":"FL",
    "wof:name":"Softouch Data Systems Inc",
    "wof:placetype":"venue"
},
  "geometry": {"coordinates":[-82.593704,27.482902],"type":"Point"}
}