{
  "type": "Feature",
  "properties": {
    "addr:full":"901 NE 17th St Fort Lauderdale FL 33305",
    "addr:housenumber":"901",
    "addr:postcode":"33305",
    "addr:street":"Ne 17Th St",
    "iso:country":"US",
    "sg:address":"901 NE 17th St",
    "sg:city":"Fort Lauderdale",
    "sg:classifiers":[
        {
            "category":"Social Services",
            "subcategory":"Adult Care",
            "type":"Services"
        }
    ],
    "sg:phone":"+1 954 764 5419",
    "sg:postcode":"33305",
    "sg:province":"FL",
    "sg:tags":[
        "incidental",
        "health",
        "rehabilitation",
        "center"
    ],
    "wof:name":"Stepping Stone",
    "wof:placetype":"venue"
},
  "geometry": {"coordinates":[-80.13242099999999,26.149673],"type":"Point"}
}