{
  "type": "Feature",
  "properties": {
    "addr:full":"401 Lake Shore Dr Lake Park FL 33403",
    "addr:housenumber":"401",
    "addr:postcode":"33403",
    "addr:street":"Lake Shore Dr",
    "iso:country":"US",
    "sg:address":"401 Lake Shore Dr",
    "sg:city":"Lake Park",
    "sg:classifiers":[
        {
            "category":"Professional",
            "type":"Services"
        }
    ],
    "sg:phone":"+1 561 863 0685",
    "sg:postcode":"33403",
    "sg:province":"FL",
    "sg:tags":[
        "establishment"
    ],
    "wof:name":"Lake Harbor Towers",
    "wof:placetype":"venue"
},
  "geometry": {"coordinates":[-80.05324299999999,26.796443],"type":"Point"}
}