{
  "type": "Feature",
  "properties": {
    "addr:full":"6600 NW 27th Ave Miami FL 33147",
    "addr:housenumber":"6600",
    "addr:postcode":"33147",
    "addr:street":"Nw 27Th Ave",
    "iso:country":"US",
    "sg:address":"6600 NW 27th Ave",
    "sg:city":"Miami",
    "sg:classifiers":[
        {
            "category":"Organizations",
            "subcategory":"Non-profit Organization",
            "type":"Services"
        }
    ],
    "sg:phone":"+1 305 835 8835",
    "sg:postcode":"33147",
    "sg:province":"FL",
    "sg:tags":[
        "service/non-profit",
        "community"
    ],
    "wof:name":"The Admit Program",
    "wof:placetype":"venue"
},
  "geometry": {"coordinates":[-80.24152599999999,25.834282],"type":"Point"}
}