{
  "type": "Feature",
  "properties": {
    "addr:full":"3581 Fowler St Fort Myers FL 33901",
    "addr:housenumber":"3581",
    "addr:postcode":"33901",
    "addr:street":"Fowler St",
    "iso:country":"US",
    "sg:address":"3581 Fowler St",
    "sg:city":"Fort Myers",
    "sg:classifiers":[
        {
            "category":"Shopping",
            "subcategory":"Clothing, Apparel, & Fashions",
            "type":"Retail Goods"
        }
    ],
    "sg:phone":"+1 239 275 6005",
    "sg:postcode":"33901",
    "sg:province":"FL",
    "sg:tags":[
        "uniform"
    ],
    "wof:name":"Sunshine School Uniforms",
    "wof:placetype":"venue"
},
  "geometry": {"coordinates":[-81.861818,26.613265],"type":"Point"}
}