{
  "type": "Feature",
  "properties": {
    "iso:country":"US",
    "sg:address":"19271 SW 24th St",
    "sg:city":"Miramar",
    "sg:classifiers":[
        {
            "category":"Retail",
            "subcategory":"Portrait Studio",
            "type":"Services"
        }
    ],
    "sg:phone":"+1 954 432 9044",
    "sg:postcode":"33029",
    "sg:province":"FL",
    "sg:tags":[
        "photographer"
    ],
    "wof:name":"Debbi Demont Photography",
    "wof:placetype":"venue"
},
  "geometry": {"coordinates":[-80.39725799999999,25.986346],"type":"Point"}
}