{
  "type": "Feature",
  "properties": {
    "addr:full":"4220 Gunn Hwy Tampa FL 33618",
    "addr:housenumber":"4220",
    "addr:postcode":"33618",
    "addr:street":"Gunn Hwy",
    "iso:country":"US",
    "sg:address":"4220 Gunn Hwy",
    "sg:city":"Tampa",
    "sg:classifiers":[
        {
            "category":"Food & Beverages",
            "subcategory":"Groceries & Convenience Stores",
            "type":"Retail Goods"
        },
        {
            "category":"Autos & Motor Vehicles",
            "subcategory":"Fuel & Gas Station",
            "type":"Retail Goods"
        }
    ],
    "sg:phone":"+1 813 968 5103",
    "sg:postcode":"33618",
    "sg:province":"FL",
    "sg:tags":[
        "station",
        "gasoline"
    ],
    "wof:name":"Racetrac",
    "wof:placetype":"venue"
},
  "geometry": {"coordinates":[-82.509108,28.040334],"type":"Point"}
}