{
  "type": "Feature",
  "properties": {
    "addr:full":"1120 N 28th St Tampa FL 33605",
    "addr:housenumber":"1120",
    "addr:postcode":"33605",
    "addr:street":"N 28Th St",
    "iso:country":"US",
    "sg:address":"1120 N 28th St",
    "sg:city":"Tampa",
    "sg:classifiers":[
        {
            "category":"Manufacturing",
            "subcategory":"Building Materials",
            "type":"Manufacturing & Wholesale Goods"
        }
    ],
    "sg:phone":"+1 813 354 0161",
    "sg:postcode":"33605",
    "sg:province":"FL",
    "sg:tags":[
        "distributor",
        "mfg",
        "cabinet"
    ],
    "wof:name":"Acclaim Cabinets Inc",
    "wof:placetype":"venue"
},
  "geometry": {"coordinates":[-82.428139,27.955585],"type":"Point"}
}