{
  "type": "Feature",
  "properties": {
    "iso:country":"US",
    "sg:address":"2322 E Oakland Park Blvd",
    "sg:city":"Fort Lauderdale",
    "sg:classifiers":[
        {
            "category":"Real Estate",
            "subcategory":"Real Estate Agent",
            "type":"Services"
        }
    ],
    "sg:phone":"+1 954 566 3839",
    "sg:postcode":"33306",
    "sg:province":"FL",
    "wof:name":"Florida Georgia RE Corp",
    "wof:placetype":"venue"
},
  "geometry": {"coordinates":[-80.115357,26.167225],"type":"Point"}
}