{
  "type": "Feature",
  "properties": {
    "iso:country":"US",
    "sg:address":"224 Texas Pkwy",
    "sg:city":"Crestview",
    "sg:classifiers":[
        {
            "category":"Personal",
            "subcategory":"Beauty Salon",
            "type":"Services"
        }
    ],
    "sg:phone":"+1 850 682 0352",
    "sg:postcode":"32536",
    "sg:province":"FL",
    "wof:name":"The Blonde Bellagio",
    "wof:placetype":"venue"
},
  "geometry": {"coordinates":[-86.567995,30.768135],"type":"Point"}
}