{
  "type": "Feature",
  "properties": {
    "iso:country":"US",
    "sg:address":"403 River Prado",
    "sg:city":"Fort Pierce",
    "sg:classifiers":[
        {
            "category":"Shopping",
            "subcategory":"Beauty & Cosmetics",
            "type":"Retail Goods"
        }
    ],
    "sg:phone":"+1 772 461 8211",
    "sg:postcode":"34946",
    "sg:province":"FL",
    "sg:tags":[
        "merchandise"
    ],
    "wof:name":"Merle Norman Cosmetics",
    "wof:placetype":"venue"
},
  "geometry": {"coordinates":[-80.343688,27.511235],"type":"Point"}
}