{
  "type": "Feature",
  "properties": {
    "iso:country":"US",
    "sg:address":"116 S Tennessee Ave",
    "sg:city":"Lakeland",
    "sg:classifiers":[
        {
            "category":"Professional",
            "subcategory":"Accounting & Tax Preparation",
            "type":"Services"
        }
    ],
    "sg:phone":"+1 863 686 1317",
    "sg:postcode":"33801",
    "sg:province":"FL",
    "sg:tags":[
        "accountant"
    ],
    "wof:name":"Marvin Anthony Assoc Inc",
    "wof:placetype":"venue"
},
  "geometry": {"coordinates":[-81.95611,28.043117],"type":"Point"}
}