{
  "type": "Feature",
  "properties": {
    "iso:country":"US",
    "sg:address":"3136 John P Curci Dr",
    "sg:city":"Hallandale",
    "sg:classifiers":[
        {
            "category":"Shopping",
            "subcategory":"Photographic Equipment",
            "type":"Retail Goods"
        }
    ],
    "sg:phone":"+1 954 981 1101",
    "sg:postcode":"33009",
    "sg:province":"FL",
    "sg:tags":[
        "photo",
        "supply"
    ],
    "wof:name":"Paskal Lighting",
    "wof:placetype":"venue"
},
  "geometry": {"coordinates":[-80.17242,25.987814],"type":"Point"}
}