{
  "type": "Feature",
  "properties": {
    "iso:country":"US",
    "sg:address":"259 E Enid Dr",
    "sg:city":"Key Biscayne",
    "sg:classifiers":[
        {
            "category":"Building & Trades",
            "subcategory":"Construction",
            "type":"Services"
        }
    ],
    "sg:phone":"+1 305 551 5625",
    "sg:postcode":"33149",
    "sg:province":"FL",
    "sg:tags":[
        "specializing",
        "home",
        "general",
        "family",
        "contractor"
    ],
    "wof:name":"All Type Construction Services",
    "wof:placetype":"venue"
},
  "geometry": {"coordinates":[-80.161136,25.689281],"type":"Point"}
}