{
  "type": "Feature",
  "properties": {
    "addr:full":"1127 Barth Rd Molino FL 32577",
    "addr:housenumber":"1127",
    "addr:postcode":"32577",
    "addr:street":"Barth Rd",
    "iso:country":"US",
    "sg:address":"1127 Barth Rd",
    "sg:city":"Molino",
    "sg:classifiers":[
        {
            "category":"Organizations",
            "subcategory":"Religious Organization",
            "type":"Services"
        }
    ],
    "sg:phone":"+1 850 587 4152",
    "sg:postcode":"32577",
    "sg:province":"FL",
    "sg:tags":[
        "church"
    ],
    "wof:name":"Barth First Born Church",
    "wof:placetype":"venue"
},
  "geometry": {"coordinates":[-87.330962,30.761548],"type":"Point"}
}