{
  "type": "Feature",
  "properties": {
    "addr:full":"676 Hastings St Boca Raton FL 33487",
    "addr:housenumber":"676",
    "addr:postcode":"33487",
    "addr:street":"Hastings St",
    "iso:country":"US",
    "sg:address":"676 Hastings St",
    "sg:city":"Boca Raton",
    "sg:classifiers":[
        {
            "category":"Professional",
            "type":"Services"
        }
    ],
    "sg:phone":"+1 561 826 0991",
    "sg:postcode":"33487",
    "sg:province":"FL",
    "sg:tags":[
        "establishment"
    ],
    "wof:name":"Florida Freeze",
    "wof:placetype":"venue"
},
  "geometry": {"coordinates":[-80.075616,26.403687],"type":"Point"}
}