{
  "type": "Feature",
  "properties": {
    "iso:country":"US",
    "sg:address":"7820 Camino Real",
    "sg:city":"Miami",
    "sg:classifiers":[
        {
            "category":"Professional",
            "subcategory":"Secretarial Services",
            "type":"Services"
        },
        {
            "category":"Professional",
            "subcategory":"Employment Agencies",
            "type":"Services"
        },
        {
            "category":"Organizations",
            "subcategory":"Professional Association",
            "type":"Services"
        }
    ],
    "sg:phone":"+1 305 412 1613",
    "sg:postcode":"33143",
    "sg:province":"FL",
    "sg:tags":[
        "transcription",
        "typing"
    ],
    "wof:name":"Eli Geralt Corporation",
    "wof:placetype":"venue"
},
  "geometry": {"coordinates":[-80.319596,25.693964],"type":"Point"}
}