{
  "type": "Feature",
  "properties": {
    "iso:country":"US",
    "sg:address":"6823 N Florida Ave",
    "sg:city":"Tampa",
    "sg:classifiers":[
        {
            "category":"Autos & Motor Vehicles",
            "subcategory":"Automobile Sales",
            "type":"Retail Goods"
        }
    ],
    "sg:phone":"+1 813 231 5117",
    "sg:postcode":"33604",
    "sg:province":"FL",
    "sg:tags":[
        "car",
        "dealer"
    ],
    "wof:name":"Tampa Bay Auto Sales",
    "wof:placetype":"venue"
},
  "geometry": {"coordinates":[-82.459458,28.010663],"type":"Point"}
}