{
  "type": "Feature",
  "properties": {
    "addr:full":"5995 NW 82nd Ave Miami FL 33166",
    "addr:housenumber":"5995",
    "addr:postcode":"33166",
    "addr:street":"Nw 82Nd Ave",
    "iso:country":"US",
    "sg:address":"5995 NW 82nd Ave",
    "sg:city":"Miami",
    "sg:classifiers":[
        {
            "category":"Wholesale",
            "subcategory":"Machinery & Supplies",
            "type":"Manufacturing & Wholesale Goods"
        }
    ],
    "sg:phone":"+1 305 599 0712",
    "sg:postcode":"33166",
    "sg:province":"FL",
    "sg:tags":[
        "equipment",
        "industrial",
        "transportation"
    ],
    "wof:name":"South American Technology USA",
    "wof:placetype":"venue"
},
  "geometry": {"coordinates":[-80.329729,25.826447],"type":"Point"}
}