{
  "type": "Feature",
  "properties": {
    "addr:full":"123 Corporation Way Venice FL 34285",
    "addr:housenumber":"123",
    "addr:postcode":"34285",
    "addr:street":"Corporation Way",
    "iso:country":"US",
    "sg:address":"123 Corporation Way",
    "sg:city":"Venice",
    "sg:classifiers":[
        {
            "category":"Wholesale",
            "subcategory":"Sporting Goods",
            "type":"Manufacturing & Wholesale Goods"
        }
    ],
    "sg:phone":"+1 941 485 7637",
    "sg:postcode":"34285",
    "sg:province":"FL",
    "sg:tags":[
        "tackle",
        "fishing"
    ],
    "wof:name":"Hook Line & Sinker",
    "wof:placetype":"venue"
},
  "geometry": {"coordinates":[-82.42277199999999,27.085431],"type":"Point"}
}