{
  "type": "Feature",
  "properties": {
    "iso:country":"US",
    "sg:address":"521 SE 2nd St",
    "sg:city":"Ocala",
    "sg:classifiers":[
        {
            "category":"Real Estate",
            "subcategory":"Surveying",
            "type":"Services"
        }
    ],
    "sg:phone":"+1 352 694 7777",
    "sg:postcode":"34471",
    "sg:province":"FL",
    "wof:name":"Bill Bley & Assoc Inc",
    "wof:placetype":"venue"
},
  "geometry": {"coordinates":[-82.132076,29.184813],"type":"Point"}
}