{
  "type": "Feature",
  "properties": {
    "addr:full":"2455 Foxwood Rd S Orange Park FL 32073",
    "addr:housenumber":"2455",
    "addr:postcode":"32073",
    "addr:street":"Foxwood Rd S",
    "iso:country":"US",
    "sg:address":"2455 Foxwood Rd S",
    "sg:city":"Orange Park",
    "sg:classifiers":[
        {
            "category":"Building & Trades",
            "subcategory":"Construction",
            "type":"Services"
        }
    ],
    "sg:phone":"+1 904 264 4645",
    "sg:postcode":"32073",
    "sg:province":"FL",
    "sg:tags":[
        "carpenter"
    ],
    "wof:name":"Abacus Carpentry LLC",
    "wof:placetype":"venue"
},
  "geometry": {"coordinates":[-81.731824,30.156593],"type":"Point"}
}