{
  "type": "Feature",
  "properties": {
    "iso:country":"US",
    "sg:address":"6957 E Fowler Ave",
    "sg:city":"Tampa",
    "sg:classifiers":[
        {
            "category":"Health Services",
            "subcategory":"Clinic",
            "type":"Services"
        },
        {
            "category":"Health Services",
            "subcategory":"Doctor",
            "type":"Services"
        }
    ],
    "sg:phone":"+1 813 914 9355",
    "sg:postcode":"33617",
    "sg:province":"FL",
    "sg:tags":[
        "physician",
        "surgeon"
    ],
    "wof:name":"Florida Center For Wellness",
    "wof:placetype":"venue"
},
  "geometry": {"coordinates":[-82.374605,28.054298],"type":"Point"}
}