{
  "type": "Feature",
  "properties": {
    "iso:country":"US",
    "sg:address":"928 W Brandon Blvd",
    "sg:city":"Brandon",
    "sg:classifiers":[
        {
            "category":"Professional",
            "subcategory":"Business Services",
            "type":"Services"
        }
    ],
    "sg:phone":"+1 813 661 2218",
    "sg:postcode":"33511",
    "sg:province":"FL",
    "sg:tags":[
        "salon",
        "tanning"
    ],
    "wof:name":"Advance Tanning",
    "wof:placetype":"venue"
},
  "geometry": {"coordinates":[-82.29816599999999,27.937839],"type":"Point"}
}