{
  "type": "Feature",
  "properties": {
    "iso:country":"US",
    "sg:address":"102 Myrtle Ridge Rd",
    "sg:city":"Lutz",
    "sg:classifiers":[
        {
            "category":"Health Services",
            "subcategory":"Doctor",
            "type":"Services"
        }
    ],
    "sg:phone":"+1 813 909 7102",
    "sg:postcode":"33549",
    "sg:province":"FL",
    "sg:tags":[
        "physician",
        "family",
        "practice",
        "surgeons",
        "medicine",
        "surgeon"
    ],
    "sg:website":"http://www.myrtleridge.com",
    "wof:name":"Myrtle Ridge Family Medicine",
    "wof:placetype":"venue"
},
  "geometry": {"coordinates":[-82.462191,28.123079],"type":"Point"}
}