{
  "type": "Feature",
  "properties": {
    "addr:full":"2703 Rosselle St Jacksonville FL 32205",
    "addr:housenumber":"2703",
    "addr:postcode":"32205",
    "addr:street":"Rosselle St",
    "iso:country":"US",
    "sg:address":"2703 Rosselle St",
    "sg:city":"Jacksonville",
    "sg:classifiers":[
        {
            "category":"Retail",
            "subcategory":"Auto Repair",
            "type":"Services"
        }
    ],
    "sg:phone":"+1 904 389 7878",
    "sg:postcode":"32205",
    "sg:province":"FL",
    "sg:tags":[
        "body",
        "automobile",
        "painting"
    ],
    "wof:name":"Ivey Paint & Body",
    "wof:placetype":"venue"
},
  "geometry": {"coordinates":[-81.697976,30.31929],"type":"Point"}
}