{
  "type": "Feature",
  "properties": {
    "addr:full":"100 SE 2nd St Miami FL 33131",
    "addr:housenumber":"100",
    "addr:postcode":"33131",
    "addr:street":"Se 2Nd St",
    "iso:country":"US",
    "sg:address":"100 SE 2nd St",
    "sg:city":"Miami",
    "sg:classifiers":[
        {
            "category":"Professional",
            "subcategory":"Lawyer & Legal Services",
            "type":"Services"
        }
    ],
    "sg:phone":"+1 305 789 9263",
    "sg:postcode":"33131",
    "sg:province":"FL",
    "wof:name":"Brooke Peter M Atty",
    "wof:placetype":"venue"
},
  "geometry": {"coordinates":[-80.191902,25.772499],"type":"Point"}
}