{
  "type": "Feature",
  "properties": {
    "addr:full":"185 NE 4th Ave Delray Beach FL 33483",
    "addr:housenumber":"185",
    "addr:postcode":"33483",
    "addr:street":"Ne 4Th Ave",
    "iso:country":"US",
    "sg:address":"185 NE 4th Ave",
    "sg:city":"Delray Beach",
    "sg:classifiers":[
        {
            "category":"Real Estate",
            "subcategory":"Real Estate Agent",
            "type":"Services"
        }
    ],
    "sg:phone":"+1 561 272 9958",
    "sg:postcode":"33483",
    "sg:province":"FL",
    "wof:name":"Southpoint Realty",
    "wof:placetype":"venue"
},
  "geometry": {"coordinates":[-80.06903800000001,26.463737],"type":"Point"}
}