{
  "type": "Feature",
  "properties": {
    "iso:country":"US",
    "sg:address":"5820 NW 57th Ct",
    "sg:city":"Ocala",
    "sg:classifiers":[
        {
            "category":"Professional",
            "subcategory":"Accounting & Tax Preparation",
            "type":"Services"
        }
    ],
    "sg:phone":"+1 352 351 0725",
    "sg:postcode":"34482",
    "sg:province":"FL",
    "sg:tags":[
        "return",
        "filing"
    ],
    "wof:name":"John H Brignall Tax Svc",
    "wof:placetype":"venue"
},
  "geometry": {"coordinates":[-82.215001,29.248846],"type":"Point"}
}