{
  "type": "Feature",
  "properties": {
    "addr:full":"12965 SW 112th Ave Miami FL 33176",
    "addr:housenumber":"12965",
    "addr:postcode":"33176",
    "addr:street":"Sw 112Th Ave",
    "iso:country":"US",
    "sg:address":"12965 SW 112th Ave",
    "sg:city":"Miami",
    "sg:classifiers":[
        {
            "category":"Health Services",
            "subcategory":"Clinic",
            "type":"Services"
        },
        {
            "category":"Community Center",
            "type":"Public Place"
        }
    ],
    "sg:phone":"+1 305 259 0013",
    "sg:postcode":"33176",
    "sg:province":"FL",
    "sg:tags":[
        "counseling",
        "medical",
        "mental"
    ],
    "wof:name":"Holistic Counseling, Reiki, Hypnosis And Energy Healing",
    "wof:placetype":"venue"
},
  "geometry": {"coordinates":[-80.374793,25.648142],"type":"Point"}
}