{
  "type": "Feature",
  "properties": {
    "iso:country":"US",
    "sg:address":"103 Delvalle St",
    "sg:city":"Melbourne Beach",
    "sg:classifiers":[
        {
            "category":"Building & Trades",
            "subcategory":"Plumbing",
            "type":"Services"
        }
    ],
    "sg:phone":"+1 321 951 4619",
    "sg:postcode":"32951",
    "sg:province":"FL",
    "sg:tags":[
        "contractor"
    ],
    "wof:name":"Rainbow The Umbrella Company",
    "wof:placetype":"venue"
},
  "geometry": {"coordinates":[-80.50017699999999,27.94667],"type":"Point"}
}