{
  "type": "Feature",
  "properties": {
    "iso:country":"US",
    "sg:address":"1914 SW 26th St",
    "sg:city":"Cape Coral",
    "sg:classifiers":[
        {
            "category":"Professional",
            "type":"Services"
        }
    ],
    "sg:phone":"+1 239 549 7933",
    "sg:postcode":"33914",
    "sg:province":"FL",
    "wof:name":"Mynewhomepixcom",
    "wof:placetype":"venue"
},
  "geometry": {"coordinates":[-82.01326400000001,26.604281],"type":"Point"}
}