{
  "type": "Feature",
  "properties": {
    "iso:country":"US",
    "sg:address":"309 Lincoln Rd",
    "sg:city":"Miami Beach",
    "sg:classifiers":[
        {
            "category":"Shopping",
            "subcategory":"Clothing, Apparel, & Fashions",
            "type":"Retail Goods"
        }
    ],
    "sg:phone":"+1 305 538 2245",
    "sg:postcode":"33139",
    "sg:province":"FL",
    "sg:tags":[
        "clothing",
        "women's"
    ],
    "wof:name":"Bikini Village of South Beach",
    "wof:placetype":"venue"
},
  "geometry": {"coordinates":[-80.130805,25.790703],"type":"Point"}
}