{
  "type": "Feature",
  "properties": {
    "addr:full":"1266 1st St Sarasota FL 34236",
    "addr:housenumber":"1266",
    "addr:postcode":"34236",
    "addr:street":"1St St",
    "iso:country":"US",
    "sg:address":"1266 1st St",
    "sg:city":"Sarasota",
    "sg:classifiers":[
        {
            "category":"Professional",
            "subcategory":"Business Services",
            "type":"Services"
        }
    ],
    "sg:phone":"+1 941 955 7358",
    "sg:postcode":"34236",
    "sg:province":"FL",
    "sg:tags":[
        "interior",
        "consultant",
        "design",
        "decorator"
    ],
    "sg:website":"www.themaddoxgroup.com",
    "wof:name":"Maddox Group",
    "wof:placetype":"venue"
},
  "geometry": {"coordinates":[-82.543745,27.337259],"type":"Point"}
}