{
  "type": "Feature",
  "properties": {
    "addr:full":"2395 NW Fork Rd Stuart FL 34994",
    "addr:housenumber":"2395",
    "addr:postcode":"34994",
    "addr:street":"Nw Fork Rd",
    "iso:country":"US",
    "sg:address":"2395 NW Fork Rd",
    "sg:city":"Stuart",
    "sg:classifiers":[
        {
            "category":"Real Estate",
            "subcategory":"Real Estate Services",
            "type":"Services"
        },
        {
            "category":"Real Estate",
            "subcategory":"Real Estate Agent",
            "type":"Services"
        }
    ],
    "sg:phone":"+1 772 692 0585",
    "sg:postcode":"34994",
    "sg:province":"FL",
    "sg:tags":[
        "buyer",
        "broker"
    ],
    "wof:name":"Behrle Realty",
    "wof:placetype":"venue"
},
  "geometry": {"coordinates":[-80.274708,27.221231],"type":"Point"}
}