{
  "type": "Feature",
  "properties": {
    "iso:country":"US",
    "sg:address":"901 S Federal Hwy",
    "sg:city":"Lake Worth",
    "sg:classifiers":[
        {
            "category":"Travel",
            "subcategory":"Hotels & Motels",
            "type":"Entertainment"
        }
    ],
    "sg:phone":"+1 561 588 8110",
    "sg:postcode":"33460",
    "sg:province":"FL",
    "sg:tags":[
        "operation"
    ],
    "sg:website":"www.new-sungate.com",
    "wof:name":"New Sun Gate Motel",
    "wof:placetype":"venue"
},
  "geometry": {"coordinates":[-80.05230899999999,26.603628],"type":"Point"}
}