{
  "type": "Feature",
  "properties": {
    "iso:country":"US",
    "sg:address":"5633 Sarah Ave",
    "sg:city":"Sarasota",
    "sg:classifiers":[
        {
            "category":"Building & Trades",
            "subcategory":"Electrical",
            "type":"Services"
        }
    ],
    "sg:phone":"+1 941 921 7816",
    "sg:postcode":"34233",
    "sg:province":"FL",
    "sg:tags":[
        "home",
        "automation",
        "electrical",
        "electric",
        "contractor"
    ],
    "wof:name":"Horne Systems & Designs Inc",
    "wof:placetype":"venue"
},
  "geometry": {"coordinates":[-82.477594,27.271437],"type":"Point"}
}