{
  "type": "Feature",
  "properties": {
    "iso:country":"US",
    "sg:address":"805 SE 1st Way",
    "sg:city":"Deerfield Beach",
    "sg:classifiers":[
        {
            "category":"Manufacturing",
            "subcategory":"Printing",
            "type":"Manufacturing & Wholesale Goods"
        }
    ],
    "sg:phone":"+1 954 722 0685",
    "sg:postcode":"33441",
    "sg:province":"FL",
    "sg:tags":[
        "publisher"
    ],
    "wof:name":"Win Ward Ways",
    "wof:placetype":"venue"
},
  "geometry": {"coordinates":[-80.101668,26.307218],"type":"Point"}
}