{
  "type": "Feature",
  "properties": {
    "iso:country":"US",
    "sg:address":"1920 W Bay Dr",
    "sg:city":"Largo",
    "sg:classifiers":[
        {
            "category":"Health Services",
            "subcategory":"Doctor",
            "type":"Services"
        }
    ],
    "sg:phone":"+1 727 584 1344",
    "sg:postcode":"33770",
    "sg:province":"FL",
    "sg:tags":[
        "physician",
        "surgeon"
    ],
    "wof:name":"Salah F Al-Andary MD",
    "wof:placetype":"venue"
},
  "geometry": {"coordinates":[-82.8087,27.916833],"type":"Point"}
}