{
  "type": "Feature",
  "properties": {
    "addr:full":"8200 Vineland Ave Orlando FL 32821",
    "addr:housenumber":"8200",
    "addr:postcode":"32821",
    "addr:street":"Vineland Ave",
    "iso:country":"US",
    "sg:address":"8200 Vineland Ave",
    "sg:city":"Orlando",
    "sg:classifiers":[
        {
            "category":"Shopping",
            "subcategory":"Luggage & Leather Goods",
            "type":"Retail Goods"
        }
    ],
    "sg:phone":"+1 407 465 1443",
    "sg:postcode":"32821",
    "sg:province":"FL",
    "wof:name":"Samsonite",
    "wof:placetype":"venue"
},
  "geometry": {"coordinates":[-81.49289,28.389257],"type":"Point"}
}