{
  "type": "Feature",
  "properties": {
    "addr:full":"21304 W Dixie Hwy Miami FL 33180",
    "addr:housenumber":"21304",
    "addr:postcode":"33180",
    "addr:street":"W Dixie Hwy",
    "iso:country":"US",
    "sg:address":"21304 W Dixie Hwy",
    "sg:city":"Miami",
    "sg:classifiers":[
        {
            "category":"Manufacturing",
            "subcategory":"Buildings",
            "type":"Manufacturing & Wholesale Goods"
        },
        {
            "category":"Building & Trades",
            "subcategory":"Construction",
            "type":"Services"
        }
    ],
    "sg:phone":"+1 305 933 5467",
    "sg:postcode":"33180",
    "sg:province":"FL",
    "sg:tags":[
        "industrial",
        "altering",
        "consultant",
        "builder",
        "contractor",
        "contractors-commercial",
        "home",
        "remodeling"
    ],
    "sg:website":"http://www.arkidesign.com",
    "wof:name":"Sila Construction Inc",
    "wof:placetype":"venue"
},
  "geometry": {"coordinates":[-80.148011,25.972901],"type":"Point"}
}