{
  "type": "Feature",
  "properties": {
    "addr:full":"2666 Irma Lake Dr West Palm Beach FL 33411",
    "addr:housenumber":"2666",
    "addr:postcode":"33411",
    "addr:street":"Irma Lake Dr",
    "iso:country":"US",
    "sg:address":"2666 Irma Lake Dr",
    "sg:city":"West Palm Beach",
    "sg:classifiers":[
        {
            "category":"Building & Trades",
            "subcategory":"Construction",
            "type":"Services"
        }
    ],
    "sg:phone":"+1 561 687 4571",
    "sg:postcode":"33411",
    "sg:province":"FL",
    "sg:tags":[
        "house"
    ],
    "wof:name":"Little Home Repairs Inc",
    "wof:placetype":"venue"
},
  "geometry": {"coordinates":[-80.15645499999999,26.718479],"type":"Point"}
}