{
  "type": "Feature",
  "properties": {
    "iso:country":"US",
    "sg:address":"848 N Beach St",
    "sg:city":"Daytona Beach",
    "sg:classifiers":[
        {
            "category":"Autos & Motor Vehicles",
            "subcategory":"Fuel & Gas Station",
            "type":"Retail Goods"
        }
    ],
    "sg:phone":"+1 386 252 2123",
    "sg:postcode":"32114",
    "sg:province":"FL",
    "sg:tags":[
        "oil"
    ],
    "wof:name":"Joy Food Store Inc",
    "wof:placetype":"venue"
},
  "geometry": {"coordinates":[-81.02648499999999,29.227981],"type":"Point"}
}