{
  "type": "Feature",
  "properties": {
    "iso:country":"US",
    "sg:address":"896 N Federal Hwy",
    "sg:city":"Pompano Beach",
    "sg:classifiers":[
        {
            "category":"Shopping",
            "subcategory":"Computers & Home Electronics",
            "type":"Retail Goods"
        }
    ],
    "sg:phone":"+1 954 942 2877",
    "sg:postcode":"33062",
    "sg:province":"FL",
    "sg:tags":[
        "software"
    ],
    "wof:name":"Tech 4U",
    "wof:placetype":"venue"
},
  "geometry": {"coordinates":[-80.102563,26.239126],"type":"Point"}
}