{
  "type": "Feature",
  "properties": {
    "iso:country":"US",
    "sg:address":"859 Monroe Harbor Pl",
    "sg:city":"Sanford",
    "sg:classifiers":[
        {
            "category":"Taxi",
            "type":"Transportation"
        },
        {
            "category":"Airport",
            "type":"Transportation"
        }
    ],
    "sg:phone":"+1 407 410 7001",
    "sg:postcode":"32773",
    "sg:province":"FL",
    "wof:name":"Midnight Taxi",
    "wof:placetype":"venue"
},
  "geometry": {"coordinates":[-81.274546,28.749595],"type":"Point"}
}