{
  "type": "Feature",
  "properties": {
    "addr:full":"27152 W Dixie Hwy Homestead FL 33032",
    "addr:housenumber":"27152",
    "addr:postcode":"33032",
    "addr:street":"W Dixie Hwy",
    "iso:country":"US",
    "sg:address":"27152 W Dixie Hwy",
    "sg:city":"Homestead",
    "sg:classifiers":[
        {
            "category":"Food & Beverages",
            "subcategory":"Specialty",
            "type":"Retail Goods"
        }
    ],
    "sg:phone":"+1 305 245 0203",
    "sg:postcode":"33032",
    "sg:province":"FL",
    "wof:name":"GNC",
    "wof:placetype":"venue"
},
  "geometry": {"coordinates":[-80.43174500000001,25.516297],"type":"Point"}
}