{
  "type": "Feature",
  "properties": {
    "addr:full":"12310 NW 7th Ave Miami FL 33168",
    "addr:housenumber":"12310",
    "addr:postcode":"33168",
    "addr:street":"Nw 7Th Ave",
    "iso:country":"US",
    "sg:address":"12310 NW 7th Ave",
    "sg:city":"Miami",
    "sg:classifiers":[
        {
            "category":"Restaurant",
            "type":"Food & Drink"
        }
    ],
    "sg:phone":"+1 305 681 6113",
    "sg:postcode":"33168",
    "sg:province":"FL",
    "sg:tags":[
        "eating"
    ],
    "wof:name":"Chens Chinese Food",
    "wof:placetype":"venue"
},
  "geometry": {"coordinates":[-80.210869,25.888178],"type":"Point"}
}