{
  "type": "Feature",
  "properties": {
    "iso:country":"US",
    "sg:address":"5101 W Lemon St",
    "sg:city":"Tampa",
    "sg:classifiers":[
        {
            "category":"Real Estate",
            "subcategory":"Developer",
            "type":"Services"
        }
    ],
    "sg:phone":"+1 813 282 8620",
    "sg:postcode":"33609",
    "sg:province":"FL",
    "wof:name":"Bargene Development",
    "wof:placetype":"venue"
},
  "geometry": {"coordinates":[-82.53281800000001,27.950428],"type":"Point"}
}