{
  "type": "Feature",
  "properties": {
    "iso:country":"US",
    "sg:address":"1406 Capital Cir NE",
    "sg:city":"Tallahassee",
    "sg:classifiers":[
        {
            "category":"Shopping",
            "subcategory":"Bicycles & Sporting Goods",
            "type":"Retail Goods"
        }
    ],
    "sg:phone":"+1 850 877 9815",
    "sg:postcode":"32308",
    "sg:province":"FL",
    "sg:tags":[
        "gun",
        "gunsmith"
    ],
    "wof:name":"LRM Custom Firearms",
    "wof:placetype":"venue"
},
  "geometry": {"coordinates":[-84.228071,30.460056],"type":"Point"}
}