{
  "type": "Feature",
  "properties": {
    "iso:country":"US",
    "sg:address":"9144 Caroline Ridge Ln N",
    "sg:city":"Jacksonville",
    "sg:classifiers":[
        {
            "category":"Professional",
            "subcategory":"Detective & Security Services",
            "type":"Services"
        }
    ],
    "sg:phone":"+1 904 221 5296",
    "sg:postcode":"32225",
    "sg:province":"FL",
    "sg:tags":[
        "car"
    ],
    "wof:name":"Jaguar Security Inc",
    "wof:placetype":"venue"
},
  "geometry": {"coordinates":[-81.55153900000001,30.3572],"type":"Point"}
}