{
  "type": "Feature",
  "properties": {
    "iso:country":"US",
    "sg:address":"2706 US Hwy 19 Alt",
    "sg:city":"Palm Harbor",
    "sg:classifiers":[
        {
            "category":"Professional",
            "subcategory":"Employment Agencies",
            "type":"Services"
        }
    ],
    "sg:phone":"+1 727 787 3550",
    "sg:postcode":"34683",
    "sg:province":"FL",
    "sg:tags":[
        "consultant",
        "search",
        "executive"
    ],
    "wof:name":"Davis-Hill Co",
    "wof:placetype":"venue"
},
  "geometry": {"coordinates":[-82.77252300000001,28.092748],"type":"Point"}
}