{
  "type": "Feature",
  "properties": {
    "addr:full":"27 Wickliffe Dr Naples FL 34110",
    "addr:housenumber":"27",
    "addr:postcode":"34110",
    "addr:street":"Wickliffe Dr",
    "iso:country":"US",
    "sg:address":"27 Wickliffe Dr",
    "sg:city":"Naples",
    "sg:classifiers":[
        {
            "category":"Building & Trades",
            "subcategory":"Electrical",
            "type":"Services"
        }
    ],
    "sg:phone":"+1 239 596 2663",
    "sg:postcode":"34110",
    "sg:province":"FL",
    "sg:tags":[
        "electrician"
    ],
    "wof:name":"Hutch Electric Inc",
    "wof:placetype":"venue"
},
  "geometry": {"coordinates":[-81.767613,26.275004],"type":"Point"}
}