{
  "type": "Feature",
  "properties": {
    "iso:country":"US",
    "sg:address":"136 Hawthorne Rd SE",
    "sg:city":"Winter Haven",
    "sg:classifiers":[
        {
            "category":"Travel",
            "subcategory":"Travel Agent",
            "type":"Entertainment"
        }
    ],
    "sg:phone":"+1 863 324 7468",
    "sg:postcode":"33884",
    "sg:province":"FL",
    "sg:tags":[
        "tours",
        "promoter"
    ],
    "wof:name":"Rock's Guide Svc",
    "wof:placetype":"venue"
},
  "geometry": {"coordinates":[-81.679085,27.999456],"type":"Point"}
}