{
  "type": "Feature",
  "properties": {
    "iso:country":"US",
    "sg:address":"8484 NW 23rd Manor",
    "sg:city":"Pompano Beach",
    "sg:classifiers":[
        {
            "category":"Health Services",
            "subcategory":"Clinic",
            "type":"Services"
        }
    ],
    "sg:phone":"+1 954 341 5687",
    "sg:postcode":"33065",
    "sg:province":"FL",
    "sg:tags":[
        "home",
        "care"
    ],
    "wof:name":"Health Relief Resources I",
    "wof:placetype":"venue"
},
  "geometry": {"coordinates":[-80.238051,26.259937],"type":"Point"}
}