{
  "type": "Feature",
  "properties": {
    "addr:full":"914 SW Gatlin Blvd Port St Lucie FL 34953",
    "addr:housenumber":"914",
    "addr:postcode":"34953",
    "addr:street":"Sw Gatlin Blvd",
    "iso:country":"US",
    "sg:address":"914 SW Gatlin Blvd",
    "sg:city":"Port St Lucie",
    "sg:classifiers":[
        {
            "category":"Shopping",
            "subcategory":"Florist",
            "type":"Retail Goods"
        }
    ],
    "sg:phone":"+1 772 336 4347",
    "sg:postcode":"34953",
    "sg:province":"FL",
    "wof:name":"Flowers By Susan",
    "wof:placetype":"venue"
},
  "geometry": {"coordinates":[-80.376231,27.258782],"type":"Point"}
}