{
  "type": "Feature",
  "properties": {
    "addr:full":"15894 Brothers Ct Ste 1 Fort Myers FL 33912",
    "addr:housenumber":"15894",
    "addr:postcode":"myers fl 33912",
    "addr:street":"Brothers Ct Ste 1",
    "iso:country":"US",
    "sg:address":"15894 Brothers Ct Ste 1",
    "sg:city":"Fort Myers",
    "sg:classifiers":[
        {
            "category":"Real Estate",
            "subcategory":"Architect",
            "type":"Services"
        }
    ],
    "sg:phone":"+1 239 267 4400",
    "sg:postcode":"33912",
    "sg:province":"FL",
    "wof:name":"Crespo Design & Drafting",
    "wof:placetype":"venue"
},
  "geometry": {"coordinates":[-81.85827500000001,26.511024],"type":"Point"}
}