{
  "type": "Feature",
  "properties": {
    "addr:full":"1510 W Church St Orlando FL 32805",
    "addr:housenumber":"1510",
    "addr:postcode":"32805",
    "addr:street":"W Church St",
    "iso:country":"US",
    "sg:address":"1510 W Church St",
    "sg:city":"Orlando",
    "sg:classifiers":[
        {
            "category":"Wholesale",
            "subcategory":"Electrical",
            "type":"Manufacturing & Wholesale Goods"
        }
    ],
    "sg:phone":"+1 407 425 7333",
    "sg:postcode":"32805",
    "sg:province":"FL",
    "sg:tags":[
        "equipment",
        "electric",
        "supply"
    ],
    "wof:name":"City Electric Supply Co",
    "wof:placetype":"venue"
},
  "geometry": {"coordinates":[-81.39954400000001,28.540095],"type":"Point"}
}