{
  "type": "Feature",
  "properties": {
    "addr:full":"8240 Stockton Way Tampa FL 33647",
    "addr:housenumber":"8240",
    "addr:postcode":"33647",
    "addr:street":"Stockton Way",
    "iso:country":"US",
    "sg:address":"8240 Stockton Way",
    "sg:city":"Tampa",
    "sg:classifiers":[
        {
            "category":"Internet Cafe",
            "subcategory":"None",
            "type":"Food & Drink"
        }
    ],
    "sg:phone":"+1 813 787 4127",
    "sg:postcode":"33647",
    "sg:province":"FL",
    "sg:tags":[
        "product"
    ],
    "wof:name":"Apexity Web Services",
    "wof:placetype":"venue"
},
  "geometry": {"coordinates":[-82.37214299999999,28.139247],"type":"Point"}
}