{
  "type": "Feature",
  "properties": {
    "addr:full":"8137 Lake Crowell Cir Orlando FL 32836",
    "addr:housenumber":"8137",
    "addr:postcode":"32836",
    "addr:street":"Lake Crowell Cir",
    "iso:country":"US",
    "sg:address":"8137 Lake Crowell Cir",
    "sg:city":"Orlando",
    "sg:classifiers":[
        {
            "category":"Professional",
            "subcategory":"Art Services",
            "type":"Services"
        }
    ],
    "sg:phone":"+1 407 370 2673",
    "sg:postcode":"32836",
    "sg:province":"FL",
    "sg:tags":[
        "artist"
    ],
    "sg:website":"www.storyboards-east.com",
    "wof:name":"Animatics & Storyboards Inc",
    "wof:placetype":"venue"
},
  "geometry": {"coordinates":[-81.49369299999999,28.422085],"type":"Point"}
}