{
  "type": "Feature",
  "properties": {
    "iso:country":"US",
    "sg:address":"1326 Malabar Rd SE",
    "sg:city":"Palm Bay",
    "sg:classifiers":[
        {
            "category":"Professional",
            "subcategory":"Lawyer & Legal Services",
            "type":"Services"
        },
        {
            "category":"Real Estate",
            "subcategory":"Real Estate Agent",
            "type":"Services"
        }
    ],
    "sg:phone":"+1 321 723 3163",
    "sg:postcode":"32907",
    "sg:province":"FL",
    "sg:tags":[
        "attorney"
    ],
    "wof:name":"Farm & Grove Realty Co Inc",
    "wof:placetype":"venue"
},
  "geometry": {"coordinates":[-80.63132899999999,27.998384],"type":"Point"}
}