{
  "type": "Feature",
  "properties": {
    "iso:country":"US",
    "sg:address":"1319 New York Ave",
    "sg:city":"Lynn Haven",
    "sg:classifiers":[
        {
            "category":"Shopping",
            "subcategory":"Used Merchandise",
            "type":"Retail Goods"
        }
    ],
    "sg:phone":"+1 850 265 4445",
    "sg:postcode":"32444",
    "sg:province":"FL",
    "sg:tags":[
        "antique"
    ],
    "wof:name":"Kristi's Place",
    "wof:placetype":"venue"
},
  "geometry": {"coordinates":[-85.650997,30.237917],"type":"Point"}
}