{
  "type": "Feature",
  "properties": {
    "iso:country":"US",
    "sg:address":"3305 Commerce Blvd",
    "sg:city":"Kissimmee",
    "sg:classifiers":[
        {
            "category":"Wholesale",
            "subcategory":"Durable Goods & Equipment",
            "type":"Manufacturing & Wholesale Goods"
        }
    ],
    "sg:phone":"+1 407 932 3688",
    "sg:postcode":"34741",
    "sg:province":"FL",
    "sg:tags":[
        "instrument",
        "scientific"
    ],
    "wof:name":"Index Instruments Us Inc",
    "wof:placetype":"venue"
},
  "geometry": {"coordinates":[-81.437031,28.299891],"type":"Point"}
}