{
  "type": "Feature",
  "properties": {
    "addr:full":"2800 Placida Rd Ste 115 Englewood FL 34224",
    "addr:postcode":"2800;34224",
    "addr:street":"Placida Rd Ste 115",
    "iso:country":"US",
    "sg:address":"2800 Placida Rd Ste 115",
    "sg:city":"Englewood",
    "sg:classifiers":[
        {
            "category":"Professional",
            "subcategory":"Printing & Photocopies",
            "type":"Services"
        }
    ],
    "sg:phone":"+1 941 697 4949",
    "sg:postcode":"34224",
    "sg:province":"FL",
    "sg:tags":[
        "services-commercial"
    ],
    "wof:name":"Color Copy Ctr Secretarial Svc",
    "wof:placetype":"venue"
},
  "geometry": {"coordinates":[-82.327461,26.91427],"type":"Point"}
}