{
  "type": "Feature",
  "properties": {
    "iso:country":"US",
    "sg:address":"13485 Barcelona Lake Cir",
    "sg:city":"Delray Beach",
    "sg:classifiers":[
        {
            "category":"Manufacturing",
            "subcategory":"Apparel",
            "type":"Manufacturing & Wholesale Goods"
        }
    ],
    "sg:phone":"+1 561 637 9986",
    "sg:postcode":"33446",
    "sg:province":"FL",
    "sg:tags":[
        "clothing",
        "mfg"
    ],
    "wof:name":"Hli Inc",
    "wof:placetype":"venue"
},
  "geometry": {"coordinates":[-80.160438,26.476264],"type":"Point"}
}