{
  "type": "Feature",
  "properties": {
    "addr:full":"3900 NW 79th Ave Doral FL 33166",
    "addr:housenumber":"3900",
    "addr:postcode":"33166",
    "addr:street":"Nw 79Th Ave",
    "iso:country":"US",
    "sg:address":"3900 NW 79th Ave",
    "sg:city":"Doral",
    "sg:classifiers":[
        {
            "category":"Insurance",
            "subcategory":"Insurance Agent",
            "type":"Services"
        }
    ],
    "sg:phone":"+1 305 592 7316",
    "sg:postcode":"33166",
    "sg:province":"FL",
    "sg:tags":[
        "adjuster"
    ],
    "wof:name":"GAB Robins",
    "wof:placetype":"venue"
},
  "geometry": {"coordinates":[-80.32535799999999,25.81056],"type":"Point"}
}