{
  "type": "Feature",
  "properties": {
    "addr:full":"4950 SW 75th Ln Miami FL 33143",
    "addr:housenumber":"4950",
    "addr:postcode":"33143",
    "addr:street":"Sw 75Th Ln",
    "iso:country":"US",
    "sg:address":"4950 SW 75th Ln",
    "sg:city":"Miami",
    "sg:classifiers":[
        {
            "category":"Social Services",
            "type":"Services"
        }
    ],
    "sg:phone":"+1 305 662 9963",
    "sg:postcode":"33143",
    "sg:province":"FL",
    "wof:name":"Esperance Counseling Services",
    "wof:placetype":"venue"
},
  "geometry": {"coordinates":[-80.272166,25.701454],"type":"Point"}
}