{
  "type": "Feature",
  "properties": {
    "addr:full":"1521 Genoa St Miami FL 33134",
    "addr:housenumber":"1521",
    "addr:postcode":"33134",
    "addr:street":"Genoa St",
    "iso:country":"US",
    "sg:address":"1521 Genoa St",
    "sg:city":"Miami",
    "sg:classifiers":[
        {
            "category":"Professional",
            "subcategory":"Lawyer & Legal Services",
            "type":"Services"
        }
    ],
    "sg:phone":"+1 305 443 7318",
    "sg:postcode":"33134",
    "sg:province":"FL",
    "sg:tags":[
        "attorney"
    ],
    "wof:name":"Terry J Forman Law Office",
    "wof:placetype":"venue"
},
  "geometry": {"coordinates":[-80.280513,25.757023],"type":"Point"}
}