{
  "type": "Feature",
  "properties": {
    "iso:country":"US",
    "sg:address":"37 W Silver Star Rd",
    "sg:city":"Ocoee",
    "sg:classifiers":[
        {
            "category":"Personal",
            "subcategory":"Beauty Salon",
            "type":"Services"
        }
    ],
    "sg:phone":"+1 407 905 9944",
    "sg:postcode":"34761",
    "sg:province":"FL",
    "wof:name":"Girasoles Hair Salon",
    "wof:placetype":"venue"
},
  "geometry": {"coordinates":[-81.544624,28.573817],"type":"Point"}
}