{
  "type": "Feature",
  "properties": {
    "addr:full":"3661 S Miami Ave Miami FL 33133",
    "addr:housenumber":"3661",
    "addr:postcode":"33133",
    "addr:street":"S Miami Ave",
    "iso:country":"US",
    "sg:address":"3661 S Miami Ave",
    "sg:city":"Miami",
    "sg:classifiers":[
        {
            "category":"Health Services",
            "subcategory":"Doctor",
            "type":"Services"
        }
    ],
    "sg:phone":"+1 305 860 6260",
    "sg:postcode":"33133",
    "sg:province":"FL",
    "sg:tags":[
        "medicine",
        "physician",
        "surgeon",
        "surgeons",
        "emergency"
    ],
    "wof:name":"Carlos, Alonso MD PA",
    "wof:placetype":"venue"
},
  "geometry": {"coordinates":[-80.215945,25.743553],"type":"Point"}
}