{
  "type": "Feature",
  "properties": {
    "iso:country":"US",
    "sg:address":"730 W Hallandale Beach Blvd",
    "sg:city":"Hallandale Beach",
    "sg:classifiers":[
        {
            "category":"Communications",
            "subcategory":"Film & Video Production",
            "type":"Services"
        },
        {
            "category":"Shopping",
            "subcategory":"Music",
            "type":"Retail Goods"
        }
    ],
    "sg:phone":"+1 954 456 6110",
    "sg:postcode":"33009",
    "sg:province":"FL",
    "sg:tags":[
        "motion",
        "cassette",
        "disc",
        "tape"
    ],
    "wof:name":"Video Creations",
    "wof:placetype":"venue"
},
  "geometry": {"coordinates":[-80.157928,25.985412],"type":"Point"}
}