{
  "type": "Feature",
  "properties": {
    "addr:full":"4140 Morning Pl Sarasota FL 34231",
    "addr:housenumber":"4140",
    "addr:postcode":"34231",
    "addr:street":"Morning Pl",
    "iso:country":"US",
    "sg:address":"4140 Morning Pl",
    "sg:city":"Sarasota",
    "sg:classifiers":[
        {
            "category":"Home & Garden",
            "subcategory":"Carpets & Floor Coverings",
            "type":"Retail Goods"
        }
    ],
    "sg:phone":"+1 941 924 6760",
    "sg:postcode":"34231",
    "sg:province":"FL",
    "wof:name":"George Scheel Carpet",
    "wof:placetype":"venue"
},
  "geometry": {"coordinates":[-82.50014,27.294533],"type":"Point"}
}