{
  "type": "Feature",
  "properties": {
    "addr:full":"2600 Junction Rd Apopka FL 32712",
    "addr:housenumber":"2600",
    "addr:postcode":"32712",
    "addr:street":"Junction Rd",
    "iso:country":"US",
    "sg:address":"2600 Junction Rd",
    "sg:city":"Apopka",
    "sg:classifiers":[
        {
            "category":"Farming",
            "subcategory":"Nursery",
            "type":"Manufacturing & Wholesale Goods"
        }
    ],
    "sg:phone":"+1 407 886 5288",
    "sg:postcode":"32712",
    "sg:province":"FL",
    "sg:tags":[
        "plant",
        "grower"
    ],
    "wof:name":"American Greenhouses",
    "wof:placetype":"venue"
},
  "geometry": {"coordinates":[-81.589524,28.72555],"type":"Point"}
}