{
  "type": "Feature",
  "properties": {
    "iso:country":"US",
    "sg:address":"6441 SW 28th St",
    "sg:city":"Miami",
    "sg:classifiers":[
        {
            "category":"Wholesale",
            "subcategory":"Non-durable Goods",
            "type":"Manufacturing & Wholesale Goods"
        }
    ],
    "sg:phone":"+1 305 663 7153",
    "sg:postcode":"33155",
    "sg:province":"FL",
    "wof:name":"Ham Import & Export Corp",
    "wof:placetype":"venue"
},
  "geometry": {"coordinates":[-80.300667,25.744351],"type":"Point"}
}