{
  "type": "Feature",
  "properties": {
    "iso:country":"US",
    "sg:address":"19597 NE 10th Ave Ste C",
    "sg:city":"Miami",
    "sg:classifiers":[
        {
            "category":"Manufacturing",
            "subcategory":"Textiles",
            "type":"Manufacturing & Wholesale Goods"
        }
    ],
    "sg:phone":"+1 305 770 4005",
    "sg:postcode":"33179",
    "sg:province":"FL",
    "sg:tags":[
        "fabrics-wholesale",
        "manufacturer"
    ],
    "wof:name":"Lg-Tec",
    "wof:placetype":"venue"
},
  "geometry": {"coordinates":[-80.181877,25.955371],"type":"Point"}
}