{
  "type": "Feature",
  "properties": {
    "addr:full":"1000 S Collier Blvd Marco Island FL 34145",
    "addr:housenumber":"1000;collier blvd",
    "addr:postcode":"34145",
    "addr:street":"S",
    "iso:country":"US",
    "sg:address":"1000 S Collier Blvd",
    "sg:city":"Marco Island",
    "sg:classifiers":[
        {
            "category":"Health Services",
            "subcategory":"Doctor",
            "type":"Services"
        }
    ],
    "sg:phone":"+1 239 642 0076",
    "sg:postcode":"34145",
    "sg:province":"FL",
    "sg:tags":[
        "physician",
        "surgeon"
    ],
    "wof:name":"Amir H Neyestani MD",
    "wof:placetype":"venue"
},
  "geometry": {"coordinates":[-81.723308,25.910556],"type":"Point"}
}