{
  "type": "Feature",
  "properties": {
    "iso:country":"US",
    "sg:address":"19956 NW 2nd Ave",
    "sg:city":"Miami",
    "sg:classifiers":[
        {
            "category":"Retail",
            "subcategory":"Veterinary Services",
            "type":"Services"
        }
    ],
    "sg:phone":"+1 954 885 8410",
    "sg:postcode":"33169",
    "sg:province":"FL",
    "sg:tags":[
        "veterinarian"
    ],
    "wof:name":"Pet Health Care Center",
    "wof:placetype":"venue"
},
  "geometry": {"coordinates":[-80.205704,25.9583],"type":"Point"}
}