{
  "type": "Feature",
  "properties": {
    "iso:country":"US",
    "sg:address":"4075 S Ridgewood Ave",
    "sg:city":"Daytona Beach",
    "sg:classifiers":[
        {
            "category":"Autos & Motor Vehicles",
            "subcategory":"Fuel & Gas Station",
            "type":"Retail Goods"
        }
    ],
    "sg:phone":"+1 386 761 9543",
    "sg:postcode":"32127",
    "sg:province":"FL",
    "sg:tags":[
        "grocery",
        "station",
        "gasoline"
    ],
    "wof:name":"Shell",
    "wof:placetype":"venue"
},
  "geometry": {"coordinates":[-80.98674,29.142274],"type":"Point"}
}