{
  "type": "Feature",
  "properties": {
    "addr:full":"6231 Hansel Ave Orlando FL 32809",
    "addr:housenumber":"6231",
    "addr:postcode":"32809",
    "addr:street":"Hansel Ave",
    "iso:country":"US",
    "sg:address":"6231 Hansel Ave",
    "sg:city":"Orlando",
    "sg:classifiers":[
        {
            "category":"Local Transit",
            "type":"Transportation"
        }
    ],
    "sg:phone":"+1 407 240 7433",
    "sg:postcode":"32809",
    "sg:province":"FL",
    "sg:tags":[
        "limousine"
    ],
    "wof:name":"Apollo Transportation",
    "wof:placetype":"venue"
},
  "geometry": {"coordinates":[-81.36772499999999,28.469622],"type":"Point"}
}