{
  "type": "Feature",
  "properties": {
    "iso:country":"US",
    "sg:address":"2768 E Oakland Park Blvd",
    "sg:city":"Fort Lauderdale",
    "sg:classifiers":[
        {
            "category":"Cafe",
            "type":"Food & Drink"
        }
    ],
    "sg:menulink":"http://www.allmenus.com/fl/fort-lauderdale/273836-cafe-seville/menu/",
    "sg:phone":"+1 954 565 1148",
    "sg:postcode":"33306",
    "sg:province":"FL",
    "sg:tags":[
        "spanish"
    ],
    "wof:name":"Cafe Seville",
    "wof:placetype":"venue"
},
  "geometry": {"coordinates":[-80.10977,26.167169],"type":"Point"}
}