{
  "type": "Feature",
  "properties": {
    "iso:country":"US",
    "sg:address":"2623 Green Crossing Dr",
    "sg:city":"Tallahassee",
    "sg:classifiers":[
        {
            "category":"Professional",
            "subcategory":"Management & Consulting",
            "type":"Services"
        }
    ],
    "sg:phone":"+1 850 878 9524",
    "sg:postcode":"32309",
    "sg:province":"FL",
    "sg:tags":[
        "business"
    ],
    "wof:name":"Cloud Consulting Inc",
    "wof:placetype":"venue"
},
  "geometry": {"coordinates":[-84.16389700000001,30.49875],"type":"Point"}
}