{
  "type": "Feature",
  "properties": {
    "iso:country":"US",
    "sg:address":"2614 Regency Oak Ln",
    "sg:city":"Orlando",
    "sg:classifiers":[
        {
            "category":"Wholesale",
            "subcategory":"Electrical",
            "type":"Manufacturing & Wholesale Goods"
        }
    ],
    "sg:phone":"+1 407 568 0919",
    "sg:postcode":"32833",
    "sg:province":"FL",
    "sg:tags":[
        "electronic"
    ],
    "wof:name":"L D C",
    "wof:placetype":"venue"
},
  "geometry": {"coordinates":[-81.080586,28.507158],"type":"Point"}
}