{
  "type": "Feature",
  "properties": {
    "addr:full":"2728 Sack Dr E Jacksonville FL 32216",
    "addr:housenumber":"2728",
    "addr:postcode":"32216",
    "addr:street":"Sack Dr E",
    "iso:country":"US",
    "sg:address":"2728 Sack Dr E",
    "sg:city":"Jacksonville",
    "sg:classifiers":[
        {
            "category":"Building & Trades",
            "subcategory":"Construction",
            "type":"Services"
        }
    ],
    "sg:phone":"+1 904 731 0210",
    "sg:postcode":"32216",
    "sg:province":"FL",
    "sg:tags":[
        "maintenance",
        "contractor"
    ],
    "wof:name":"Florida Maintenance & Constr",
    "wof:placetype":"venue"
},
  "geometry": {"coordinates":[-81.60017499999999,30.274519],"type":"Point"}
}