{
  "type": "Feature",
  "properties": {
    "addr:full":"2914 W Gandy Blvd Tampa FL 33611",
    "addr:housenumber":"2914",
    "addr:postcode":"33611",
    "addr:street":"W Gandy Blvd",
    "iso:country":"US",
    "sg:address":"2914 W Gandy Blvd",
    "sg:city":"Tampa",
    "sg:classifiers":[
        {
            "category":"Restaurant",
            "type":"Food & Drink"
        }
    ],
    "sg:phone":"+1 813 902 8237",
    "sg:postcode":"33611",
    "sg:province":"FL",
    "sg:tags":[
        "eating"
    ],
    "wof:name":"Mad Mushroom Pizza Inc",
    "wof:placetype":"venue"
},
  "geometry": {"coordinates":[-82.49153099999999,27.893574],"type":"Point"}
}