{
  "type": "Feature",
  "properties": {
    "iso:country":"US",
    "sg:address":"541 State Rd 434 W",
    "sg:city":"Winter Springs",
    "sg:classifiers":[
        {
            "category":"Restaurant",
            "type":"Food & Drink"
        }
    ],
    "sg:phone":"+1 407 327 8943",
    "sg:postcode":"32708",
    "sg:province":"FL",
    "sg:tags":[
        "italian"
    ],
    "wof:name":"Tony Papa Italian Restaurant",
    "wof:placetype":"venue"
},
  "geometry": {"coordinates":[-81.31083099999999,28.69831],"type":"Point"}
}