{
  "type": "Feature",
  "properties": {
    "addr:full":"9225 Ulmerton Rd Largo FL 33771",
    "addr:housenumber":"9225",
    "addr:postcode":"33771",
    "addr:street":"Ulmerton Rd",
    "iso:country":"US",
    "sg:address":"9225 Ulmerton Rd",
    "sg:city":"Largo",
    "sg:classifiers":[
        {
            "category":"Wholesale",
            "subcategory":"Machinery & Supplies",
            "type":"Manufacturing & Wholesale Goods"
        }
    ],
    "sg:phone":"+1 727 536 5558",
    "sg:postcode":"33771",
    "sg:province":"FL",
    "sg:tags":[
        "equipment",
        "safety",
        "clothing"
    ],
    "wof:name":"Carlwood Safety Inc",
    "wof:placetype":"venue"
},
  "geometry": {"coordinates":[-82.76754200000001,27.894605],"type":"Point"}
}