{
  "type": "Feature",
  "properties": {
    "iso:country":"US",
    "sg:address":"40728 Us Highway 19 N",
    "sg:city":"Tarpon Springs",
    "sg:classifiers":[
        {
            "category":"Restaurant",
            "type":"Food & Drink"
        }
    ],
    "sg:menulink":"http://www.allmenus.com/fl/tarpon-springs/187765-mcdonalds/menu/",
    "sg:phone":"+1 727 943 8721",
    "sg:postcode":"34689",
    "sg:province":"FL",
    "sg:tags":[
        "burger",
        "american"
    ],
    "wof:name":"McDonald's",
    "wof:placetype":"venue"
},
  "geometry": {"coordinates":[-82.741097,28.142188],"type":"Point"}
}