{
  "type": "Feature",
  "properties": {
    "iso:country":"US",
    "sg:address":"2700 Power Mill Ct",
    "sg:city":"Tallahassee",
    "sg:classifiers":[
        {
            "category":"Building & Trades",
            "subcategory":"Construction",
            "type":"Services"
        }
    ],
    "sg:phone":"+1 850 942 5933",
    "sg:postcode":"32301",
    "sg:province":"FL",
    "sg:tags":[
        "dry wall",
        "contractor"
    ],
    "wof:name":"Artistic Perfection Drywall",
    "wof:placetype":"venue"
},
  "geometry": {"coordinates":[-84.23128800000001,30.450246],"type":"Point"}
}