{
  "type": "Feature",
  "properties": {
    "addr:full":"935 N Semoran Blvd Orlando FL 32807",
    "addr:housenumber":"935",
    "addr:postcode":"32807",
    "addr:street":"N Semoran Blvd",
    "iso:country":"US",
    "sg:address":"935 N Semoran Blvd",
    "sg:city":"Orlando",
    "sg:classifiers":[
        {
            "category":"Home & Garden",
            "subcategory":"Furniture",
            "type":"Retail Goods"
        }
    ],
    "sg:phone":"+1 407 331 6650",
    "sg:postcode":"32807",
    "sg:province":"FL",
    "sg:tags":[
        "mattress"
    ],
    "wof:name":"Mattress Giant",
    "wof:placetype":"venue"
},
  "geometry": {"coordinates":[-81.310721,28.558408],"type":"Point"}
}