{
  "type": "Feature",
  "properties": {
    "addr:full":"2400 N Forsyth Rd Orlando FL 32807",
    "addr:housenumber":"2400",
    "addr:postcode":"32807",
    "addr:street":"N Forsyth Rd",
    "iso:country":"US",
    "sg:address":"2400 N Forsyth Rd",
    "sg:city":"Orlando",
    "sg:classifiers":[
        {
            "category":"Building & Trades",
            "subcategory":"Construction",
            "type":"Services"
        }
    ],
    "sg:phone":"+1 407 657 5533",
    "sg:postcode":"32807",
    "sg:province":"FL",
    "sg:tags":[
        "system",
        "contractor",
        "air conditioning"
    ],
    "wof:name":"Mike Singletary Air Cond",
    "wof:placetype":"venue"
},
  "geometry": {"coordinates":[-81.29454800000001,28.57909],"type":"Point"}
}