{
  "type": "Feature",
  "properties": {
    "iso:country":"US",
    "sg:address":"5110 Meldon Cir",
    "sg:city":"Sarasota",
    "sg:classifiers":[
        {
            "category":"Building & Trades",
            "subcategory":"Electrical",
            "type":"Services"
        }
    ],
    "sg:phone":"+1 941 379 4412",
    "sg:postcode":"34232",
    "sg:province":"FL",
    "sg:tags":[
        "electrical",
        "contractor"
    ],
    "wof:name":"Jeff Pfohler Electric Inc",
    "wof:placetype":"venue"
},
  "geometry": {"coordinates":[-82.467114,27.340685],"type":"Point"}
}