{
  "type": "Feature",
  "properties": {
    "iso:country":"US",
    "sg:address":"10122 Montague St",
    "sg:city":"Tampa",
    "sg:classifiers":[
        {
            "category":"Wholesale",
            "subcategory":"Electrical",
            "type":"Manufacturing & Wholesale Goods"
        }
    ],
    "sg:phone":"+1 813 792 9373",
    "sg:postcode":"33626",
    "sg:province":"FL",
    "sg:tags":[
        "equipment",
        "telecommunication"
    ],
    "wof:name":"Castech Corporation",
    "wof:placetype":"venue"
},
  "geometry": {"coordinates":[-82.597112,28.044042],"type":"Point"}
}