{
  "type": "Feature",
  "properties": {
    "iso:country":"US",
    "sg:address":"2205 NW 79th St",
    "sg:city":"Miami",
    "sg:classifiers":[
        {
            "category":"Retail",
            "subcategory":"Self-service Laundry",
            "type":"Services"
        }
    ],
    "sg:phone":"+1 305 693 4540",
    "sg:postcode":"33147",
    "sg:province":"FL",
    "wof:name":"Laundromart",
    "wof:placetype":"venue"
},
  "geometry": {"coordinates":[-80.234375,25.846324],"type":"Point"}
}