{
  "type": "Feature",
  "properties": {
    "iso:country":"US",
    "sg:address":"3764 SW Pheasant Run",
    "sg:city":"Palm City",
    "sg:classifiers":[
        {
            "category":"Sports & Exercise",
            "subcategory":"Race Track",
            "type":"Entertainment"
        }
    ],
    "sg:phone":"+1 772 220 3861",
    "sg:postcode":"34990",
    "sg:province":"FL",
    "sg:tags":[
        "operation",
        "racing",
        "or"
    ],
    "wof:name":"PH Stable Inc",
    "wof:placetype":"venue"
},
  "geometry": {"coordinates":[-80.30406499999999,27.17188],"type":"Point"}
}