{
  "type": "Feature",
  "properties": {
    "addr:full":"1209 Tangelo Isle Fort Lauderdale FL 33315",
    "addr:housenumber":"1209",
    "addr:postcode":"33315",
    "addr:street":"Tangelo Isle",
    "iso:country":"US",
    "sg:address":"1209 Tangelo Isle",
    "sg:city":"Fort Lauderdale",
    "sg:classifiers":[
        {
            "category":"Manufacturing",
            "subcategory":"Tools & Machinery",
            "type":"Manufacturing & Wholesale Goods"
        }
    ],
    "sg:phone":"+1 954 527 5282",
    "sg:postcode":"33315",
    "sg:province":"FL",
    "sg:tags":[
        "equipment",
        "mfg",
        "design",
        "desalination"
    ],
    "wof:name":"Sea-Ro Inc",
    "wof:placetype":"venue"
},
  "geometry": {"coordinates":[-80.157511,26.10153],"type":"Point"}
}