{
  "type": "Feature",
  "properties": {
    "iso:country":"US",
    "sg:address":"31 NE 3rd Ave",
    "sg:city":"Miami",
    "sg:classifiers":[
        {
            "category":"Travel",
            "subcategory":"Travel Agent",
            "type":"Entertainment"
        }
    ],
    "sg:phone":"+1 305 381 7750",
    "sg:postcode":"33132",
    "sg:province":"FL",
    "sg:tags":[
        "agency"
    ],
    "wof:name":"Travelink Network Inc",
    "wof:placetype":"venue"
},
  "geometry": {"coordinates":[-80.188543,25.774924],"type":"Point"}
}