{
  "type": "Feature",
  "properties": {
    "addr:full":"12385 SW 73rd Ave Miami FL 33156",
    "addr:housenumber":"12385",
    "addr:postcode":"33156",
    "addr:street":"Sw 73Rd Ave",
    "iso:country":"US",
    "sg:address":"12385 SW 73rd Ave",
    "sg:city":"Miami",
    "sg:classifiers":[
        {
            "category":"Professional",
            "subcategory":"Management & Consulting",
            "type":"Services"
        }
    ],
    "sg:phone":"+1 305 256 0575",
    "sg:postcode":"33156",
    "sg:province":"FL",
    "sg:tags":[
        "consultant",
        "motel",
        "coach",
        "business",
        "hotel"
    ],
    "sg:website":"http://www.crafullhouse.com",
    "wof:name":"Cra Full House",
    "wof:placetype":"venue"
},
  "geometry": {"coordinates":[-80.31253100000001,25.655877],"type":"Point"}
}