{
  "type": "Feature",
  "properties": {
    "iso:country":"US",
    "sg:address":"2334 SE 37 Rd",
    "sg:city":"Bushnell",
    "sg:classifiers":[
        {
            "category":"Building & Trades",
            "subcategory":"Landscaping Services",
            "type":"Services"
        }
    ],
    "sg:phone":"+1 352 568 1789",
    "sg:postcode":"33513",
    "sg:province":"FL",
    "wof:name":"Johns Mowing Service",
    "wof:placetype":"venue"
},
  "geometry": {"coordinates":[-82.058756,28.696775],"type":"Point"}
}