{
  "type": "Feature",
  "properties": {
    "addr:full":"906 Marlene Dr Ocoee FL 34761",
    "addr:housenumber":"906",
    "addr:postcode":"34761",
    "addr:street":"Marlene Dr",
    "iso:country":"US",
    "sg:address":"906 Marlene Dr",
    "sg:city":"Ocoee",
    "sg:classifiers":[
        {
            "category":"Freight",
            "type":"Transportation"
        }
    ],
    "sg:phone":"+1 407 877 2667",
    "sg:postcode":"34761",
    "sg:province":"FL",
    "sg:tags":[
        "operator",
        "local",
        "trucking"
    ],
    "wof:name":"Norman B Robinson",
    "wof:placetype":"venue"
},
  "geometry": {"coordinates":[-81.527187,28.592372],"type":"Point"}
}