{
  "type": "Feature",
  "properties": {
    "addr:full":"5860 14th St W Bradenton FL 34207",
    "addr:housenumber":"5860",
    "addr:postcode":"34207",
    "addr:street":"14Th St W",
    "iso:country":"US",
    "sg:address":"5860 14th St W",
    "sg:city":"Bradenton",
    "sg:classifiers":[
        {
            "category":"Professional",
            "subcategory":"Business Services",
            "type":"Services"
        },
        {
            "category":"Banks & Credit Unions",
            "subcategory":"Bank",
            "type":"Services"
        }
    ],
    "sg:phone":"+1 941 753 5500",
    "sg:postcode":"34207",
    "sg:province":"FL",
    "sg:tags":[
        "depository",
        "banking",
        "check",
        "cashing"
    ],
    "wof:name":"Check n Go",
    "wof:placetype":"venue"
},
  "geometry": {"coordinates":[-82.575517,27.437989],"type":"Point"}
}