{
  "type": "Feature",
  "properties": {
    "addr:full":"1283 NE 120th St Ocala FL 34479",
    "addr:housenumber":"1283",
    "addr:postcode":"34479",
    "addr:street":"Ne 120Th St",
    "iso:country":"US",
    "sg:address":"1283 NE 120th St",
    "sg:city":"Ocala",
    "sg:classifiers":[
        {
            "category":"Wholesale",
            "subcategory":"Computers",
            "type":"Manufacturing & Wholesale Goods"
        }
    ],
    "sg:phone":"+1 352 840 0112",
    "sg:postcode":"34479",
    "sg:province":"FL",
    "wof:name":"Baden Corp",
    "wof:placetype":"venue"
},
  "geometry": {"coordinates":[-82.12351,29.32278],"type":"Point"}
}