{
  "type": "Feature",
  "properties": {
    "iso:country":"US",
    "sg:address":"4700 Millenia Blvd",
    "sg:city":"Orlando",
    "sg:classifiers":[
        {
            "category":"Real Estate",
            "subcategory":"Real Estate Services",
            "type":"Services"
        },
        {
            "category":"Banks & Credit Unions",
            "subcategory":"Bank",
            "type":"Services"
        },
        {
            "category":"Banks & Credit Unions",
            "subcategory":"Financial Services",
            "type":"Services"
        }
    ],
    "sg:phone":"+1 407 581 6060",
    "sg:postcode":"32839",
    "sg:province":"FL",
    "sg:tags":[
        "commercial",
        "loan",
        "processing",
        "saving"
    ],
    "wof:name":"Cnlbank",
    "wof:placetype":"venue"
},
  "geometry": {"coordinates":[-81.440613,28.48514],"type":"Point"}
}