{
  "type": "Feature",
  "properties": {
    "iso:country":"US",
    "sg:address":"6343 Via de Sonrisa del Sur",
    "sg:city":"Boca Raton",
    "sg:classifiers":[
        {
            "category":"Health Services",
            "subcategory":"Nursing And Care Facility",
            "type":"Services"
        }
    ],
    "sg:phone":"+1 561 392 2772",
    "sg:postcode":"33433",
    "sg:province":"FL",
    "sg:tags":[
        "home",
        "convalescent"
    ],
    "wof:name":"Stratford Court & Brighton Gdn",
    "wof:placetype":"venue"
},
  "geometry": {"coordinates":[-80.145341,26.330484],"type":"Point"}
}