{
  "type": "Feature",
  "properties": {
    "addr:full":"1321 NW 14th St Ste 607 Miami FL 33125",
    "addr:housenumber":"1321",
    "addr:postcode":"33125",
    "addr:street":"Nw 14Th St Ste 607",
    "iso:country":"US",
    "sg:address":"1321 NW 14th St Ste 607",
    "sg:city":"Miami",
    "sg:classifiers":[
        {
            "category":"Health Services",
            "subcategory":"Doctor",
            "type":"Services"
        }
    ],
    "sg:phone":"+1 305 326 0776",
    "sg:postcode":"33125",
    "sg:province":"FL",
    "sg:tags":[
        "psychiatrist"
    ],
    "wof:name":"Mantero-Atienza Emilio MD",
    "wof:placetype":"venue"
},
  "geometry": {"coordinates":[-80.21779600000001,25.7875],"type":"Point"}
}