{
  "type": "Feature",
  "properties": {
    "addr:full":"12689 Challenger Pkwy Orlando FL 32826",
    "addr:housenumber":"12689",
    "addr:postcode":"fl 32826",
    "addr:street":"Challenger Pkwy",
    "iso:country":"US",
    "sg:address":"12689 Challenger Pkwy",
    "sg:city":"Orlando",
    "sg:classifiers":[
        {
            "category":"Education",
            "subcategory":"Special Training",
            "type":"Public Place"
        }
    ],
    "sg:phone":"+1 407 380 2425",
    "sg:postcode":"32826",
    "sg:province":"FL",
    "sg:tags":[
        "program"
    ],
    "wof:name":"Saab Training Inc",
    "wof:placetype":"venue"
},
  "geometry": {"coordinates":[-81.20354399999999,28.572902],"type":"Point"}
}