{
  "type": "Feature",
  "properties": {
    "iso:country":"US",
    "sg:address":"1416 Ohio Ave N",
    "sg:city":"Live Oak",
    "sg:classifiers":[
        {
            "category":"Education",
            "subcategory":"College",
            "type":"Public Place"
        }
    ],
    "sg:phone":"+1 386 364 7952",
    "sg:postcode":"32064",
    "sg:province":"FL",
    "sg:tags":[
        "academic",
        "school"
    ],
    "wof:name":"Employment Connections",
    "wof:placetype":"venue"
},
  "geometry": {"coordinates":[-82.978324,30.306522],"type":"Point"}
}