{
  "type": "Feature",
  "properties": {
    "iso:country":"US",
    "sg:address":"925 W Washington St",
    "sg:city":"Monticello",
    "sg:classifiers":[
        {
            "category":"Professional",
            "subcategory":"Accounting & Tax Preparation",
            "type":"Services"
        }
    ],
    "sg:phone":"+1 850 997 3082",
    "sg:postcode":"32344",
    "sg:province":"FL",
    "sg:tags":[
        "accountant"
    ],
    "wof:name":"Watson & Assoc",
    "wof:placetype":"venue"
},
  "geometry": {"coordinates":[-83.878147,30.54511],"type":"Point"}
}