{
  "type": "Feature",
  "properties": {
    "addr:full":"6857 S 102nd Pl Boynton Beach FL 33437",
    "addr:housenumber":"6857",
    "addr:postcode":"33437",
    "addr:street":"S 102Nd Pl",
    "iso:country":"US",
    "sg:address":"6857 S 102nd Pl",
    "sg:city":"Boynton Beach",
    "sg:classifiers":[
        {
            "category":"Home & Garden",
            "subcategory":"Garden Supply",
            "type":"Retail Goods"
        }
    ],
    "sg:phone":"+1 561 737 8629",
    "sg:postcode":"33437",
    "sg:province":"FL",
    "sg:tags":[
        "sprinkler"
    ],
    "wof:name":"Womack Sprinkler Svc",
    "wof:placetype":"venue"
},
  "geometry": {"coordinates":[-80.15286,26.523976],"type":"Point"}
}