{
  "type": "Feature",
  "properties": {
    "iso:country":"US",
    "sg:address":"9835 SW 72nd St",
    "sg:city":"Miami",
    "sg:classifiers":[
        {
            "category":"Professional",
            "subcategory":"Employment Agencies",
            "type":"Services"
        }
    ],
    "sg:phone":"+1 305 273 3580",
    "sg:postcode":"33173",
    "sg:province":"FL",
    "sg:tags":[
        "opportunity"
    ],
    "wof:name":"Medical Staffing Network Inc",
    "wof:placetype":"venue"
},
  "geometry": {"coordinates":[-80.352492,25.701637],"type":"Point"}
}