{
  "type": "Feature",
  "properties": {
    "addr:full":"3285 NW 7th Ave Miami FL 33127",
    "addr:housenumber":"3285",
    "addr:postcode":"33127",
    "addr:street":"Nw 7Th Ave",
    "iso:country":"US",
    "sg:address":"3285 NW 7th Ave",
    "sg:city":"Miami",
    "sg:classifiers":[
        {
            "category":"Professional",
            "subcategory":"Business Services",
            "type":"Services"
        }
    ],
    "sg:phone":"+1 305 637 5085",
    "sg:postcode":"33127",
    "sg:province":"FL",
    "sg:tags":[
        "import",
        "importer",
        "representative"
    ],
    "wof:name":"Lamour",
    "wof:placetype":"venue"
},
  "geometry": {"coordinates":[-80.20742300000001,25.807066],"type":"Point"}
}