{
  "type": "Feature",
  "properties": {
    "addr:full":"1891 Capital Cir NE Tallahassee FL 32308",
    "addr:housenumber":"1891",
    "addr:postcode":"32308",
    "addr:street":"Capital Cir Ne",
    "iso:country":"US",
    "sg:address":"1891 Capital Cir NE",
    "sg:city":"Tallahassee",
    "sg:classifiers":[
        {
            "category":"Home & Garden",
            "subcategory":"Household Appliances",
            "type":"Retail Goods"
        }
    ],
    "sg:phone":"+1 850 402 1192",
    "sg:postcode":"32308",
    "sg:province":"FL",
    "wof:name":"Oreck",
    "wof:placetype":"venue"
},
  "geometry": {"coordinates":[-84.229928,30.466251],"type":"Point"}
}