{
  "type": "Feature",
  "properties": {
    "iso:country":"US",
    "sg:address":"4028 Bryan Blvd",
    "sg:city":"Plantation",
    "sg:classifiers":[
        {
            "category":"Food & Beverages",
            "subcategory":"Specialty",
            "type":"Retail Goods"
        }
    ],
    "sg:phone":"+1 954 583 0094",
    "sg:postcode":"33317",
    "sg:province":"FL",
    "sg:tags":[
        "health",
        "diet"
    ],
    "wof:name":"Scarborough's Health Foods",
    "wof:placetype":"venue"
},
  "geometry": {"coordinates":[-80.203917,26.119918],"type":"Point"}
}