{
  "type": "Feature",
  "properties": {
    "iso:country":"US",
    "sg:address":"1513 Commerce Blvd",
    "sg:city":"Lake City",
    "sg:classifiers":[
        {
            "category":"Restaurant",
            "type":"Food & Drink"
        }
    ],
    "sg:phone":"+1 386 755 1511",
    "sg:postcode":"32025",
    "sg:province":"FL",
    "sg:tags":[
        "parlor",
        "ice",
        "cream"
    ],
    "wof:name":"TCBY",
    "wof:placetype":"venue"
},
  "geometry": {"coordinates":[-82.680982,30.175057],"type":"Point"}
}