{
  "type": "Feature",
  "properties": {
    "iso:country":"US",
    "sg:address":"6901 22nd Ave N",
    "sg:city":"St Petersburg",
    "sg:classifiers":[
        {
            "category":"Food & Beverages",
            "subcategory":"Bakery",
            "type":"Retail Goods"
        }
    ],
    "sg:phone":"+1 727 347 1531",
    "sg:postcode":"33710",
    "sg:province":"FL",
    "sg:tags":[
        "pretzel"
    ],
    "wof:name":"Auntie Anne's Hand Rolled Soft",
    "wof:placetype":"venue"
},
  "geometry": {"coordinates":[-82.735962,27.791873],"type":"Point"}
}