{
  "type": "Feature",
  "properties": {
    "addr:full":"15700 SW 88th St Miami FL 33196",
    "addr:housenumber":"15700",
    "addr:postcode":"33196",
    "addr:street":"Sw 88Th St",
    "iso:country":"US",
    "sg:address":"15700 SW 88th St",
    "sg:city":"Miami",
    "sg:classifiers":[
        {
            "category":"Shopping",
            "subcategory":"Pharmacy",
            "type":"Retail Goods"
        }
    ],
    "sg:phone":"+1 305 385 2626",
    "sg:postcode":"33196",
    "sg:province":"FL",
    "wof:name":"Eckerd",
    "wof:placetype":"venue"
},
  "geometry": {"coordinates":[-80.44600800000001,25.68445],"type":"Point"}
}