{
  "type": "Feature",
  "properties": {
    "iso:country":"US",
    "sg:address":"2040 State Hwy 207",
    "sg:city":"St Augustine",
    "sg:classifiers":[
        {
            "category":"Organizations",
            "subcategory":"Religious Organization",
            "type":"Services"
        }
    ],
    "sg:phone":"+1 904 819 9970",
    "sg:postcode":"32086",
    "sg:province":"FL",
    "sg:tags":[
        "church"
    ],
    "wof:name":"Family Worship Center",
    "wof:placetype":"venue"
},
  "geometry": {"coordinates":[-81.370369,29.835894],"type":"Point"}
}