{
  "type": "Feature",
  "properties": {
    "addr:full":"8500 NW 177th St Hialeah FL 33015",
    "addr:housenumber":"8500",
    "addr:postcode":"33015",
    "addr:street":"Nw 177Th St",
    "iso:country":"US",
    "sg:address":"8500 NW 177th St",
    "sg:city":"Hialeah",
    "sg:classifiers":[
        {
            "category":"Freight",
            "type":"Transportation"
        }
    ],
    "sg:phone":"+1 305 884 6363",
    "sg:postcode":"33015",
    "sg:province":"FL",
    "sg:tags":[
        "storage",
        "rental",
        "portable",
        "unit"
    ],
    "wof:name":"Mobile Storage Group Inc",
    "wof:placetype":"venue"
},
  "geometry": {"coordinates":[-80.341398,25.934314],"type":"Point"}
}