{
  "type": "Feature",
  "properties": {
    "iso:country":"US",
    "sg:address":"20225 NE 34th Ct",
    "sg:city":"Miami",
    "sg:classifiers":[
        {
            "category":"Industrial Area",
            "type":"Public Place"
        }
    ],
    "sg:phone":"+1 305 937 6279",
    "sg:postcode":"33180",
    "sg:province":"FL",
    "sg:tags":[
        "consultant"
    ],
    "wof:name":"Gulf Atlantic Industries Of America Inc",
    "wof:placetype":"venue"
},
  "geometry": {"coordinates":[-80.13391900000001,25.965068],"type":"Point"}
}