{
  "type": "Feature",
  "properties": {
    "iso:country":"US",
    "sg:address":"8525 SW 92nd St",
    "sg:city":"Miami",
    "sg:classifiers":[
        {
            "category":"Health Services",
            "subcategory":"Doctor",
            "type":"Services"
        }
    ],
    "sg:phone":"+1 305 275 9990",
    "sg:postcode":"33156",
    "sg:province":"FL",
    "sg:tags":[
        "physician",
        "surgeon"
    ],
    "wof:name":"Popp Hernandez MD",
    "wof:placetype":"venue"
},
  "geometry": {"coordinates":[-80.333935,25.684545],"type":"Point"}
}