{
  "type": "Feature",
  "properties": {
    "iso:country":"US",
    "sg:address":"4100 Hollywood Blvd Ste 2",
    "sg:city":"Hollywood",
    "sg:classifiers":[
        {
            "category":"Health Services",
            "subcategory":"Doctor",
            "type":"Services"
        }
    ],
    "sg:phone":"+1 954 518 4100",
    "sg:postcode":"33021",
    "sg:province":"FL",
    "sg:tags":[
        "gynecology",
        "physician",
        "surgeon",
        "surgeons",
        "obstetrics"
    ],
    "wof:name":"Weiss, Simon Md",
    "wof:placetype":"venue"
},
  "geometry": {"coordinates":[-80.184585,26.011305],"type":"Point"}
}