{
  "type": "Feature",
  "properties": {
    "iso:country":"US",
    "sg:address":"868 Blountstown Hwy",
    "sg:city":"Tallahassee",
    "sg:classifiers":[
        {
            "category":"Retail",
            "subcategory":"Auto Repair",
            "type":"Services"
        }
    ],
    "sg:phone":"+1 850 575 3330",
    "sg:postcode":"32304",
    "sg:province":"FL",
    "sg:tags":[
        "repairing",
        "automobile"
    ],
    "wof:name":"Campbell's Auto & Air",
    "wof:placetype":"venue"
},
  "geometry": {"coordinates":[-84.34677499999999,30.446808],"type":"Point"}
}