{
  "type": "Feature",
  "properties": {
    "iso:country":"US",
    "sg:address":"21589 Windham Run",
    "sg:city":"Estero",
    "sg:classifiers":[
        {
            "category":"Professional",
            "subcategory":"Computer Services",
            "type":"Services"
        }
    ],
    "sg:phone":"+1 239 948 4931",
    "sg:postcode":"33928",
    "sg:province":"FL",
    "sg:tags":[
        "internet"
    ],
    "wof:name":"Nautilus Internet Dev & Design",
    "wof:placetype":"venue"
},
  "geometry": {"coordinates":[-81.774905,26.428885],"type":"Point"}
}