{
  "type": "Feature",
  "properties": {
    "addr:full":"767 NW 41st St Miami FL 33127",
    "addr:housenumber":"767",
    "addr:postcode":"33127",
    "addr:street":"Nw 41St St",
    "iso:country":"US",
    "sg:address":"767 NW 41st St",
    "sg:city":"Miami",
    "sg:classifiers":[
        {
            "category":"Real Estate",
            "subcategory":"Real Estate Agent",
            "type":"Services"
        }
    ],
    "sg:phone":"+1 305 865 5257",
    "sg:postcode":"33127",
    "sg:province":"FL",
    "sg:tags":[
        "buying"
    ],
    "wof:name":"Revesz Estate Buyers Inc",
    "wof:placetype":"venue"
},
  "geometry": {"coordinates":[-80.208637,25.813838],"type":"Point"}
}