{
  "type": "Feature",
  "properties": {
    "iso:country":"US",
    "sg:address":"41 Belvidere Pl",
    "sg:city":"Babson Park",
    "sg:classifiers":[
        {
            "category":"Building & Trades",
            "subcategory":"Construction",
            "type":"Services"
        }
    ],
    "sg:phone":"+1 863 638 1829",
    "sg:postcode":"33827",
    "sg:province":"FL",
    "sg:tags":[
        "contractor"
    ],
    "wof:name":"Kirbys Tile Inc",
    "wof:placetype":"venue"
},
  "geometry": {"coordinates":[-81.53187200000001,27.820295],"type":"Point"}
}