{
  "type": "Feature",
  "properties": {
    "iso:country":"US",
    "sg:address":"213 W Venice Ave",
    "sg:city":"Venice",
    "sg:classifiers":[
        {
            "category":"Shopping",
            "subcategory":"Stationery & Office Supplies",
            "type":"Retail Goods"
        }
    ],
    "sg:phone":"+1 941 488 8300",
    "sg:postcode":"34285",
    "sg:province":"FL",
    "sg:tags":[
        "stationer"
    ],
    "wof:name":"Paper Pad",
    "wof:placetype":"venue"
},
  "geometry": {"coordinates":[-82.447481,27.099806],"type":"Point"}
}