{
  "type": "Feature",
  "properties": {
    "addr:full":"300 Brigham Rd NW Winter Haven FL 33881",
    "addr:housenumber":"300",
    "addr:postcode":"33881",
    "addr:street":"Brigham Rd Nw",
    "iso:country":"US",
    "sg:address":"300 Brigham Rd NW",
    "sg:city":"Winter Haven",
    "sg:classifiers":[
        {
            "category":"Retail",
            "subcategory":"Auto Repair",
            "type":"Services"
        }
    ],
    "sg:phone":"+1 863 956 8343",
    "sg:postcode":"33881",
    "sg:province":"FL",
    "sg:tags":[
        "general"
    ],
    "wof:name":"Emmons Enterprises Inc",
    "wof:placetype":"venue"
},
  "geometry": {"coordinates":[-81.732767,28.064369],"type":"Point"}
}