{
  "type": "Feature",
  "properties": {
    "addr:full":"2451 N McMullen Booth Rd Clearwater FL 33759",
    "addr:housenumber":"2451",
    "addr:postcode":"33759",
    "addr:street":"N Mcmullen Booth Rd",
    "iso:country":"US",
    "sg:address":"2451 N McMullen Booth Rd",
    "sg:city":"Clearwater",
    "sg:classifiers":[
        {
            "category":"Shopping",
            "subcategory":"Computers & Home Electronics",
            "type":"Retail Goods"
        }
    ],
    "sg:phone":"+1 727 712 3629",
    "sg:postcode":"33759",
    "sg:province":"FL",
    "sg:tags":[
        "software"
    ],
    "sg:website":"www.penta.com",
    "wof:name":"Penta Technologies",
    "wof:placetype":"venue"
},
  "geometry": {"coordinates":[-82.70884700000001,28.009195],"type":"Point"}
}