{
  "type": "Feature",
  "properties": {
    "iso:country":"US",
    "sg:address":"2399 W 52nd St",
    "sg:city":"Hialeah",
    "sg:classifiers":[
        {
            "category":"Shopping",
            "subcategory":"Pharmacy",
            "type":"Retail Goods"
        }
    ],
    "sg:phone":"+1 305 822 4884",
    "sg:postcode":"33016",
    "sg:province":"FL",
    "sg:tags":[
        "drugstore"
    ],
    "wof:name":"Sedano's Pharmacy & Discount",
    "wof:placetype":"venue"
},
  "geometry": {"coordinates":[-80.332199,25.869699],"type":"Point"}
}