{
  "type": "Feature",
  "properties": {
    "addr:full":"22266 Edgewater Dr Port Charlotte FL 33980",
    "addr:housenumber":"22266",
    "addr:postcode":"33980",
    "addr:street":"Edgewater Dr",
    "iso:country":"US",
    "sg:address":"22266 Edgewater Dr",
    "sg:city":"Port Charlotte",
    "sg:classifiers":[
        {
            "category":"Utilities",
            "subcategory":"Cable",
            "type":"Services"
        }
    ],
    "sg:phone":"+1 941 625 2981",
    "sg:postcode":"33980",
    "sg:province":"FL",
    "sg:tags":[
        "television"
    ],
    "wof:name":"Comcast Corporation",
    "wof:placetype":"venue"
},
  "geometry": {"coordinates":[-82.08118399999999,26.964316],"type":"Point"}
}