{
  "type": "Feature",
  "properties": {
    "iso:country":"US",
    "sg:address":"741 Altamira St NW",
    "sg:city":"Palm Bay",
    "sg:classifiers":[
        {
            "category":"Building & Trades",
            "subcategory":"Construction",
            "type":"Services"
        }
    ],
    "sg:phone":"+1 321 768 7948",
    "sg:postcode":"32907",
    "sg:province":"FL",
    "sg:tags":[
        "floor",
        "installation",
        "covering"
    ],
    "wof:name":"Floors Unlimited Of Brevard",
    "wof:placetype":"venue"
},
  "geometry": {"coordinates":[-80.692055,28.005814],"type":"Point"}
}