{
  "type": "Feature",
  "properties": {
    "iso:country":"US",
    "sg:address":"733 Breakers Ave",
    "sg:city":"Fort Lauderdale",
    "sg:classifiers":[
        {
            "category":"Social Services",
            "type":"Services"
        }
    ],
    "sg:phone":"+1 954 568 7901",
    "sg:postcode":"33304",
    "sg:province":"FL",
    "wof:name":"Young Professionals For Covent",
    "wof:placetype":"venue"
},
  "geometry": {"coordinates":[-80.104919,26.133695],"type":"Point"}
}