{
  "type": "Feature",
  "properties": {
    "iso:country":"US",
    "sg:address":"101 Jeanette Way",
    "sg:city":"Jupiter",
    "sg:classifiers":[
        {
            "category":"Shopping",
            "subcategory":"Clothing, Apparel, & Fashions",
            "type":"Retail Goods"
        }
    ],
    "sg:phone":"+1 561 748 9980",
    "sg:postcode":"33458",
    "sg:province":"FL",
    "sg:tags":[
        "family"
    ],
    "wof:name":"Stax Sales",
    "wof:placetype":"venue"
},
  "geometry": {"coordinates":[-80.135093,26.956645],"type":"Point"}
}