{
  "type": "Feature",
  "properties": {
    "addr:full":"2912 Green St Marianna FL 32446",
    "addr:housenumber":"2912",
    "addr:postcode":"32446",
    "addr:street":"Green St",
    "iso:country":"US",
    "sg:address":"2912 Green St",
    "sg:city":"Marianna",
    "sg:classifiers":[
        {
            "category":"Real Estate",
            "subcategory":"Real Estate Agent",
            "type":"Services"
        }
    ],
    "sg:phone":"+1 850 526 4030",
    "sg:postcode":"32446",
    "sg:province":"FL",
    "wof:name":"Chipola Area Board Of Realtors",
    "wof:placetype":"venue"
},
  "geometry": {"coordinates":[-85.227524,30.776471],"type":"Point"}
}