{
  "type": "Feature",
  "properties": {
    "iso:country":"US",
    "sg:address":"17464 NW 10th St",
    "sg:city":"Pembroke Pines",
    "sg:classifiers":[
        {
            "category":"Wholesale",
            "subcategory":"Plants",
            "type":"Manufacturing & Wholesale Goods"
        }
    ],
    "sg:phone":"+1 305 406 2925",
    "sg:postcode":"33029",
    "sg:province":"FL",
    "sg:tags":[
        "florist"
    ],
    "wof:name":"Zurel America",
    "wof:placetype":"venue"
},
  "geometry": {"coordinates":[-80.38009700000001,26.013417],"type":"Point"}
}