{
  "type": "Feature",
  "properties": {
    "addr:full":"581 10th St E Palmetto FL 34221",
    "addr:housenumber":"581",
    "addr:postcode":"34221",
    "addr:street":"10Th St E",
    "iso:country":"US",
    "sg:address":"581 10th St E",
    "sg:city":"Palmetto",
    "sg:classifiers":[
        {
            "category":"Shopping",
            "subcategory":"Music",
            "type":"Retail Goods"
        }
    ],
    "sg:phone":"+1 941 729 3331",
    "sg:postcode":"34221",
    "sg:province":"FL",
    "sg:tags":[
        "video",
        "disc",
        "tape",
        "cassette"
    ],
    "wof:name":"Distribuidora Alcobi Inc",
    "wof:placetype":"venue"
},
  "geometry": {"coordinates":[-82.56013900000001,27.521055],"type":"Point"}
}