{
  "type": "Feature",
  "properties": {
    "addr:full":"1227 E Lafayette St Tallahassee FL 32301",
    "addr:housenumber":"1227",
    "addr:postcode":"32301",
    "addr:street":"E Lafayette St",
    "iso:country":"US",
    "sg:address":"1227 E Lafayette St",
    "sg:city":"Tallahassee",
    "sg:classifiers":[
        {
            "category":"Home & Garden",
            "subcategory":"Furniture",
            "type":"Retail Goods"
        }
    ],
    "sg:phone":"+1 850 671 3212",
    "sg:postcode":"32301",
    "sg:province":"FL",
    "wof:name":"Unique & Beautiful Things",
    "wof:placetype":"venue"
},
  "geometry": {"coordinates":[-84.26238499999999,30.43559],"type":"Point"}
}