{
  "type": "Feature",
  "properties": {
    "addr:full":"15638 Eastbourn Dr Odessa FL 33556",
    "addr:housenumber":"15638",
    "addr:postcode":"33556",
    "addr:street":"Eastbourn Dr",
    "iso:country":"US",
    "sg:address":"15638 Eastbourn Dr",
    "sg:city":"Odessa",
    "sg:classifiers":[
        {
            "category":"Real Estate",
            "subcategory":"Real Estate Agent",
            "type":"Services"
        }
    ],
    "sg:phone":"+1 813 926 8600",
    "sg:postcode":"33556",
    "sg:province":"FL",
    "wof:name":"Bill Bach Realty",
    "wof:placetype":"venue"
},
  "geometry": {"coordinates":[-82.63282700000001,28.091868],"type":"Point"}
}