{
  "type": "Feature",
  "properties": {
    "addr:full":"8601 4th St N St Petersburg FL 33702",
    "addr:housenumber":"8601",
    "addr:postcode":"33702",
    "addr:street":"4Th St N",
    "iso:country":"US",
    "sg:address":"8601 4th St N",
    "sg:city":"St Petersburg",
    "sg:classifiers":[
        {
            "category":"Health Services",
            "subcategory":"Clinic",
            "type":"Services"
        },
        {
            "category":"Health Services",
            "subcategory":"Doctor",
            "type":"Services"
        }
    ],
    "sg:phone":"+1 727 577 3069",
    "sg:postcode":"33702",
    "sg:province":"FL",
    "sg:tags":[
        "physician",
        "surgeon"
    ],
    "wof:name":"Posicare Inc",
    "wof:placetype":"venue"
},
  "geometry": {"coordinates":[-82.638769,27.851613],"type":"Point"}
}