{
  "type": "Feature",
  "properties": {
    "addr:full":"2142 NW 20th St Miami FL 33142",
    "addr:housenumber":"2142",
    "addr:postcode":"33142",
    "addr:street":"Nw 20Th St",
    "iso:country":"US",
    "sg:address":"2142 NW 20th St",
    "sg:city":"Miami",
    "sg:classifiers":[
        {
            "category":"Restaurant",
            "type":"Food & Drink"
        }
    ],
    "sg:phone":"+1 305 324 8666",
    "sg:postcode":"33142",
    "sg:province":"FL",
    "wof:name":"Medero Cafeteria",
    "wof:placetype":"venue"
},
  "geometry": {"coordinates":[-80.230301,25.7945],"type":"Point"}
}