{
  "type": "Feature",
  "properties": {
    "iso:country":"US",
    "sg:address":"280 Melody Ln W",
    "sg:city":"Casselberry",
    "sg:classifiers":[
        {
            "category":"Wholesale",
            "subcategory":"Auto Parts",
            "type":"Manufacturing & Wholesale Goods"
        }
    ],
    "sg:phone":"+1 407 260 6363",
    "sg:postcode":"32707",
    "sg:province":"FL",
    "sg:tags":[
        "used",
        "supply"
    ],
    "wof:name":"Macs Used Auto Parts Inc",
    "wof:placetype":"venue"
},
  "geometry": {"coordinates":[-81.340239,28.672275],"type":"Point"}
}