{
  "type": "Feature",
  "properties": {
    "addr:full":"7430 Commerce Pl Sarasota FL 34243",
    "addr:housenumber":"7430",
    "addr:postcode":"34243",
    "addr:street":"Commerce Pl",
    "iso:country":"US",
    "sg:address":"7430 Commerce Pl",
    "sg:city":"Sarasota",
    "sg:classifiers":[
        {
            "category":"Wholesale",
            "subcategory":"Fruits & Vegetables",
            "type":"Manufacturing & Wholesale Goods"
        }
    ],
    "sg:phone":"+1 941 358 0022",
    "sg:postcode":"34243",
    "sg:province":"FL",
    "wof:name":"Minute Man Produce",
    "wof:placetype":"venue"
},
  "geometry": {"coordinates":[-82.548835,27.408186],"type":"Point"}
}