{
  "type": "Feature",
  "properties": {
    "addr:full":"3450 Palencia Dr Tampa FL 33618",
    "addr:postcode":"3450;33618",
    "addr:street":"Palencia Dr",
    "iso:country":"US",
    "sg:address":"3450 Palencia Dr",
    "sg:city":"Tampa",
    "sg:classifiers":[
        {
            "category":"Retail",
            "subcategory":"Auto Repair",
            "type":"Services"
        }
    ],
    "sg:phone":"+1 813 932 8339",
    "sg:postcode":"33618",
    "sg:province":"FL",
    "sg:tags":[
        "automobile",
        "customizing"
    ],
    "wof:name":"W M Auto Boutique",
    "wof:placetype":"venue"
},
  "geometry": {"coordinates":[-82.501926,28.087357],"type":"Point"}
}