{
  "type": "Feature",
  "properties": {
    "iso:country":"US",
    "sg:address":"616 Bonita Rd",
    "sg:city":"Winter Springs",
    "sg:classifiers":[
        {
            "category":"Insurance",
            "subcategory":"Insurance Agent",
            "type":"Services"
        }
    ],
    "sg:phone":"+1 407 327 5366",
    "sg:postcode":"32708",
    "sg:province":"FL",
    "wof:name":"Employee Benefit Design Inc",
    "wof:placetype":"venue"
},
  "geometry": {"coordinates":[-81.291856,28.693645],"type":"Point"}
}