{
  "type": "Feature",
  "properties": {
    "iso:country":"US",
    "sg:address":"621 SW 57th Ave",
    "sg:city":"Miami",
    "sg:classifiers":[
        {
            "category":"Personal",
            "subcategory":"Beauty Salon",
            "type":"Services"
        }
    ],
    "sg:phone":"+1 305 266 4004",
    "sg:postcode":"33144",
    "sg:province":"FL",
    "sg:tags":[
        "cosmetologist"
    ],
    "wof:name":"Pretty & Pink Beauty Salon",
    "wof:placetype":"venue"
},
  "geometry": {"coordinates":[-80.28795599999999,25.765671],"type":"Point"}
}