{
  "type": "Feature",
  "properties": {
    "iso:country":"US",
    "sg:address":"7955 W 28th Ave",
    "sg:city":"Hialeah",
    "sg:classifiers":[
        {
            "category":"Home & Garden",
            "subcategory":"Building Materials",
            "type":"Retail Goods"
        }
    ],
    "sg:phone":"+1 305 825 4933",
    "sg:postcode":"33016",
    "sg:province":"FL",
    "sg:tags":[
        "shutter"
    ],
    "wof:name":"Aluminum Express Inc",
    "wof:placetype":"venue"
},
  "geometry": {"coordinates":[-80.340035,25.894425],"type":"Point"}
}