{
  "type": "Feature",
  "properties": {
    "addr:full":"715 US Hwy 41 Ruskin FL 33570",
    "addr:housenumber":"715",
    "addr:postcode":"33570",
    "addr:street":"Us Hwy 41",
    "iso:country":"US",
    "sg:address":"715 US Hwy 41",
    "sg:city":"Ruskin",
    "sg:classifiers":[
        {
            "category":"Retail",
            "subcategory":"Veterinary Services",
            "type":"Services"
        }
    ],
    "sg:phone":"+1 813 645 6411",
    "sg:postcode":"33570",
    "sg:province":"FL",
    "sg:tags":[
        "veterinarian"
    ],
    "wof:name":"Ruskin Animal Hospital",
    "wof:placetype":"venue"
},
  "geometry": {"coordinates":[-82.433761,27.725108],"type":"Point"}
}