{
  "type": "Feature",
  "properties": {
    "addr:full":"2523 Cathay Ct Tallahassee FL 32308",
    "addr:housenumber":"2523",
    "addr:postcode":"32308",
    "addr:street":"Cathay Ct",
    "iso:country":"US",
    "sg:address":"2523 Cathay Ct",
    "sg:city":"Tallahassee",
    "sg:classifiers":[
        {
            "category":"Organizations",
            "subcategory":"Membership Organization",
            "type":"Services"
        }
    ],
    "sg:phone":"+1 850 385 0791",
    "sg:postcode":"32308",
    "sg:province":"FL",
    "wof:name":"United Cerebral Palsy",
    "wof:placetype":"venue"
},
  "geometry": {"coordinates":[-84.226197,30.488266],"type":"Point"}
}