{
  "type": "Feature",
  "properties": {
    "iso:country":"US",
    "sg:address":"2651 2nd Ave N",
    "sg:city":"St Petersburg",
    "sg:classifiers":[
        {
            "category":"Building & Trades",
            "subcategory":"Cleaning & Sanitation",
            "type":"Services"
        }
    ],
    "sg:phone":"+1 727 488 4555",
    "sg:postcode":"33713",
    "sg:province":"FL",
    "sg:tags":[
        "janitor"
    ],
    "wof:name":"A-1 Janitorial Inc",
    "wof:placetype":"venue"
},
  "geometry": {"coordinates":[-82.66929,27.77294],"type":"Point"}
}