{
  "type": "Feature",
  "properties": {
    "addr:full":"402 Havendale Blvd Auburndale FL 33823",
    "addr:housenumber":"402",
    "addr:postcode":"33823",
    "addr:street":"Havendale Blvd",
    "iso:country":"US",
    "sg:address":"402 Havendale Blvd",
    "sg:city":"Auburndale",
    "sg:classifiers":[
        {
            "category":"Restaurant",
            "type":"Food & Drink"
        }
    ],
    "sg:menulink":"http://www.allmenus.com/fl/winter-haven-auburndale/181196-green-tea/menu/",
    "sg:phone":"+1 863 965 8838",
    "sg:postcode":"33823",
    "sg:province":"FL",
    "sg:tags":[
        "asian",
        "chinese"
    ],
    "wof:name":"Green Tea",
    "wof:placetype":"venue"
},
  "geometry": {"coordinates":[-81.77851200000001,28.055268],"type":"Point"}
}