{
  "type": "Feature",
  "properties": {
    "iso:country":"US",
    "sg:address":"13771 Okeechobee Blvd",
    "sg:city":"Loxahatchee",
    "sg:classifiers":[
        {
            "category":"Place Of Worship",
            "type":"Public Place"
        }
    ],
    "sg:phone":"+1 561 792 9322",
    "sg:postcode":"33470",
    "sg:province":"FL",
    "sg:tags":[
        "church"
    ],
    "wof:name":"Jesus Our Savior Church Inc",
    "wof:placetype":"venue"
},
  "geometry": {"coordinates":[-80.261968,26.706394],"type":"Point"}
}