{
  "type": "Feature",
  "properties": {
    "addr:full":"4344 US Hwy 1 Vero Beach FL 32967",
    "addr:housenumber":"4344",
    "addr:postcode":"32967",
    "addr:street":"Us Hwy 1",
    "iso:country":"US",
    "sg:address":"4344 US Hwy 1",
    "sg:city":"Vero Beach",
    "sg:classifiers":[
        {
            "category":"Building & Trades",
            "subcategory":"Construction",
            "type":"Services"
        }
    ],
    "sg:phone":"+1 772 564 0560",
    "sg:postcode":"32967",
    "sg:province":"FL",
    "sg:tags":[
        "company"
    ],
    "wof:name":"Grand Harbor Construction",
    "wof:placetype":"venue"
},
  "geometry": {"coordinates":[-80.40625799999999,27.670149],"type":"Point"}
}