{
  "type": "Feature",
  "properties": {
    "iso:country":"US",
    "sg:address":"5208 Plantation Dr",
    "sg:city":"Lakeland",
    "sg:classifiers":[
        {
            "category":"Shopping",
            "subcategory":"Discount & Variety Stores",
            "type":"Retail Goods"
        }
    ],
    "sg:phone":"+1 863 619 5717",
    "sg:postcode":"33811",
    "sg:province":"FL",
    "sg:tags":[
        "merchandising",
        "merchandise"
    ],
    "wof:name":"A S Klowne",
    "wof:placetype":"venue"
},
  "geometry": {"coordinates":[-82.05123399999999,27.945939],"type":"Point"}
}