{
  "type": "Feature",
  "properties": {
    "addr:full":"12890 Commodity Pl Tampa FL 33626",
    "addr:housenumber":"12890",
    "addr:postcode":"33626",
    "addr:street":"Commodity Pl",
    "iso:country":"US",
    "sg:address":"12890 Commodity Pl",
    "sg:city":"Tampa",
    "sg:classifiers":[
        {
            "category":"Health Services",
            "subcategory":"Doctor",
            "type":"Services"
        },
        {
            "category":"Health Services",
            "subcategory":"Hospital",
            "type":"Services"
        }
    ],
    "sg:phone":"+1 813 901 8225",
    "sg:postcode":"33626",
    "sg:province":"FL",
    "sg:tags":[
        "consultant",
        "medical",
        "practice",
        "nursing",
        "home"
    ],
    "sg:website":"http://www.mypmgs.com",
    "wof:name":"Practice Management & Growth Solutions",
    "wof:placetype":"venue"
},
  "geometry": {"coordinates":[-82.63527499999999,28.065533],"type":"Point"}
}