{
  "type": "Feature",
  "properties": {
    "addr:full":"1832 Lakeview Point Rd Quincy FL 32351",
    "addr:housenumber":"1832",
    "addr:postcode":"32351",
    "addr:street":"Lakeview Point Rd",
    "iso:country":"US",
    "sg:address":"1832 Lakeview Point Rd",
    "sg:city":"Quincy",
    "sg:classifiers":[
        {
            "category":"Food & Beverages",
            "subcategory":"Groceries & Convenience Stores",
            "type":"Retail Goods"
        }
    ],
    "sg:phone":"+1 850 627 9800",
    "sg:postcode":"32351",
    "sg:province":"FL",
    "sg:tags":[
        "product"
    ],
    "wof:name":"Russo's Fine Italian Food",
    "wof:placetype":"venue"
},
  "geometry": {"coordinates":[-84.601417,30.436928],"type":"Point"}
}