{
  "type": "Feature",
  "properties": {
    "addr:full":"2494 Spring Creek Rd Marianna FL 32448",
    "addr:housenumber":"2494",
    "addr:postcode":"32448",
    "addr:street":"Spring Creek Rd",
    "iso:country":"US",
    "sg:address":"2494 Spring Creek Rd",
    "sg:city":"Marianna",
    "sg:classifiers":[
        {
            "category":"Government",
            "subcategory":"Office",
            "type":"Public Place"
        }
    ],
    "sg:phone":"+1 850 482 9533",
    "sg:postcode":"32448",
    "sg:province":"FL",
    "sg:website":"http://www.dc.state.fl.us",
    "wof:name":"George W Sweeney",
    "wof:placetype":"venue"
},
  "geometry": {"coordinates":[-85.19443699999999,30.749286],"type":"Point"}
}