{
  "type": "Feature",
  "properties": {
    "addr:full":"6500 Columbia Ave Lake Worth FL 33467",
    "addr:housenumber":"6500",
    "addr:postcode":"33467",
    "addr:street":"Columbia Ave",
    "iso:country":"US",
    "sg:address":"6500 Columbia Ave",
    "sg:city":"Lake Worth",
    "sg:classifiers":[
        {
            "category":"Farming",
            "subcategory":"Farm",
            "type":"Manufacturing & Wholesale Goods"
        }
    ],
    "sg:phone":"+1 561 434 6086",
    "sg:postcode":"33467",
    "sg:province":"FL",
    "wof:name":"Smith Farm Masters",
    "wof:placetype":"venue"
},
  "geometry": {"coordinates":[-80.169151,26.576],"type":"Point"}
}