{
  "type": "Feature",
  "properties": {
    "addr:full":"222 Ariana Ave Auburndale FL 33823",
    "addr:housenumber":"222",
    "addr:postcode":"33823",
    "addr:street":"Ariana Ave",
    "iso:country":"US",
    "sg:address":"222 Ariana Ave",
    "sg:city":"Auburndale",
    "sg:classifiers":[
        {
            "category":"Social Services",
            "subcategory":"Child Care",
            "type":"Services"
        }
    ],
    "sg:phone":"+1 863 968 0848",
    "sg:postcode":"33823",
    "sg:province":"FL",
    "wof:name":"Little Bloodhound Preschool",
    "wof:placetype":"venue"
},
  "geometry": {"coordinates":[-81.79274100000001,28.064247],"type":"Point"}
}