{
  "type": "Feature",
  "properties": {
    "addr:full":"4714 N Thatcher Ave Tampa FL 33614",
    "addr:housenumber":"4714",
    "addr:postcode":"33614",
    "addr:street":"N Thatcher Ave",
    "iso:country":"US",
    "sg:address":"4714 N Thatcher Ave",
    "sg:city":"Tampa",
    "sg:classifiers":[
        {
            "category":"Manufacturing",
            "subcategory":"Chemicals & Compounds",
            "type":"Manufacturing & Wholesale Goods"
        }
    ],
    "sg:phone":"+1 813 875 3106",
    "sg:postcode":"33614",
    "sg:province":"FL",
    "sg:tags":[
        "mfg",
        "printing",
        "ink"
    ],
    "wof:name":"JK&m Ink",
    "wof:placetype":"venue"
},
  "geometry": {"coordinates":[-82.514487,27.988651],"type":"Point"}
}