{
  "type": "Feature",
  "properties": {
    "iso:country":"US",
    "sg:address":"150 Art Ln",
    "sg:city":"Sanford",
    "sg:classifiers":[
        {
            "category":"Professional",
            "type":"Services"
        }
    ],
    "sg:phone":"+1 407 328 3172",
    "sg:postcode":"32773",
    "sg:province":"FL",
    "wof:name":"Ida Idea Corp",
    "wof:placetype":"venue"
},
  "geometry": {"coordinates":[-81.299181,28.757908],"type":"Point"}
}