{
  "type": "Feature",
  "properties": {
    "iso:country":"US",
    "sg:address":"4051 E 8th Ave",
    "sg:city":"Hialeah",
    "sg:classifiers":[
        {
            "category":"Health Services",
            "subcategory":"Doctor",
            "type":"Services"
        }
    ],
    "sg:phone":"+1 305 693 1914",
    "sg:postcode":"33013",
    "sg:province":"FL",
    "sg:tags":[
        "physician",
        "surgeon"
    ],
    "wof:name":"Ricardo A Marino MD",
    "wof:placetype":"venue"
},
  "geometry": {"coordinates":[-80.26656699999999,25.859506],"type":"Point"}
}