{
  "type": "Feature",
  "properties": {
    "iso:country":"US",
    "sg:address":"607 Tremont St",
    "sg:city":"Sarasota",
    "sg:classifiers":[
        {
            "category":"Banks & Credit Unions",
            "subcategory":"Bank",
            "type":"Services"
        }
    ],
    "sg:phone":"+1 941 346 8555",
    "sg:postcode":"34242",
    "sg:province":"FL",
    "sg:tags":[
        "loan",
        "real estate"
    ],
    "wof:name":"United Mortgage Svc",
    "wof:placetype":"venue"
},
  "geometry": {"coordinates":[-82.557391,27.285759],"type":"Point"}
}