{
  "type": "Feature",
  "properties": {
    "addr:full":"4063 N Goldenrod Rd Winter Park FL 32792",
    "addr:housenumber":"4063",
    "addr:postcode":"32792",
    "addr:street":"N Goldenrod Rd",
    "iso:country":"US",
    "sg:address":"4063 N Goldenrod Rd",
    "sg:city":"Winter Park",
    "sg:classifiers":[
        {
            "category":"Health Services",
            "subcategory":"Podiatrist",
            "type":"Services"
        }
    ],
    "sg:phone":"+1 407 679 6002",
    "sg:postcode":"32792",
    "sg:province":"FL",
    "wof:name":"Loretta Henderson DPM",
    "wof:placetype":"venue"
},
  "geometry": {"coordinates":[-81.286536,28.597835],"type":"Point"}
}