{
  "type": "Feature",
  "properties": {
    "iso:country":"US",
    "sg:address":"36615 Scottsdale Dr",
    "sg:city":"Grand Island",
    "sg:classifiers":[
        {
            "category":"Professional",
            "subcategory":"Business Services",
            "type":"Services"
        }
    ],
    "sg:phone":"+1 352 357 7100",
    "sg:postcode":"32735",
    "sg:province":"FL",
    "sg:tags":[
        "arbitration"
    ],
    "wof:name":"Ernest C Aulls",
    "wof:placetype":"venue"
},
  "geometry": {"coordinates":[-81.748527,28.880533],"type":"Point"}
}