{
  "type": "Feature",
  "properties": {
    "addr:full":"11340 114th Ave Largo FL 33778",
    "addr:housenumber":"11340",
    "addr:postcode":"33778",
    "addr:street":"114Th Ave",
    "iso:country":"US",
    "sg:address":"11340 114th Ave",
    "sg:city":"Largo",
    "sg:classifiers":[
        {
            "category":"Shopping",
            "subcategory":"Computers & Home Electronics",
            "type":"Retail Goods"
        }
    ],
    "sg:phone":"+1 727 395 0474",
    "sg:postcode":"33778",
    "sg:province":"FL",
    "wof:name":"Sellers Computers",
    "wof:placetype":"venue"
},
  "geometry": {"coordinates":[-82.796542,27.876353],"type":"Point"}
}