{
  "type": "Feature",
  "properties": {
    "iso:country":"US",
    "sg:address":"12980 SW 142nd Ter",
    "sg:city":"Miami",
    "sg:classifiers":[
        {
            "category":"Health Services",
            "subcategory":"Doctor",
            "type":"Services"
        }
    ],
    "sg:phone":"+1 305 558 1440",
    "sg:postcode":"33186",
    "sg:province":"FL",
    "sg:tags":[
        "medicine",
        "physician",
        "practice",
        "surgeons",
        "family"
    ],
    "wof:name":"Rafael V Mora Md Pa",
    "wof:placetype":"venue"
},
  "geometry": {"coordinates":[-80.403471,25.635228],"type":"Point"}
}