{
  "type": "Feature",
  "properties": {
    "addr:full":"415 Idlewood Dr Ormond Beach FL 32176",
    "addr:housenumber":"415",
    "addr:postcode":"32176",
    "addr:street":"Idlewood Dr",
    "iso:country":"US",
    "sg:address":"415 Idlewood Dr",
    "sg:city":"Ormond Beach",
    "sg:classifiers":[
        {
            "category":"Building & Trades",
            "subcategory":"Construction",
            "type":"Services"
        }
    ],
    "sg:phone":"+1 386 672 3815",
    "sg:postcode":"32176",
    "sg:province":"FL",
    "sg:tags":[
        "house"
    ],
    "wof:name":"Flores Builders Inc",
    "wof:placetype":"venue"
},
  "geometry": {"coordinates":[-81.04840799999999,29.300879],"type":"Point"}
}