{
  "type": "Feature",
  "properties": {
    "iso:country":"US",
    "sg:address":"16420 Old US Hwy 41",
    "sg:city":"Fort Myers",
    "sg:classifiers":[
        {
            "category":"Building & Trades",
            "subcategory":"Construction",
            "type":"Services"
        }
    ],
    "sg:phone":"+1 239 481 7143",
    "sg:postcode":"33912",
    "sg:province":"FL",
    "sg:tags":[
        "designer",
        "marine",
        "contractor"
    ],
    "sg:website":"www.stemicmarine.com",
    "wof:name":"Stemic Enterprises Inc",
    "wof:placetype":"venue"
},
  "geometry": {"coordinates":[-81.853989,26.504503],"type":"Point"}
}