{
  "type": "Feature",
  "properties": {
    "iso:country":"US",
    "sg:address":"2638 SW 28th Lane",
    "sg:city":"Coconut Grove",
    "sg:classifiers":[
        {
            "category":"Professional",
            "type":"Services"
        },
        {
            "category":"Shopping",
            "type":"Retail Goods"
        }
    ],
    "sg:phone":"+1 305 443 0112",
    "sg:postcode":"33146",
    "sg:province":"FL",
    "sg:tags":[
        "planning",
        "event"
    ],
    "sg:website":"www.cateringsupplies.com",
    "wof:name":"Catering Supplies Corporation",
    "wof:placetype":"venue"
},
  "geometry": {"coordinates":[-80.237106,25.741024],"type":"Point"}
}