{
  "type": "Feature",
  "properties": {
    "iso:country":"US",
    "sg:address":"4314 Tideview Dr",
    "sg:city":"Jacksonville Beach",
    "sg:classifiers":[
        {
            "category":"Building & Trades",
            "subcategory":"Construction",
            "type":"Services"
        }
    ],
    "sg:phone":"+1 904 223 4903",
    "sg:postcode":"32250",
    "sg:province":"FL",
    "wof:name":"Ikena Construction",
    "wof:placetype":"venue"
},
  "geometry": {"coordinates":[-81.434814,30.264577],"type":"Point"}
}