{
  "type": "Feature",
  "properties": {
    "iso:country":"US",
    "sg:address":"2511 W Church St",
    "sg:city":"Orlando",
    "sg:classifiers":[
        {
            "category":"Health Services",
            "subcategory":"Doctor",
            "type":"Services"
        }
    ],
    "sg:phone":"+1 407 578 9142",
    "sg:postcode":"32805",
    "sg:province":"FL",
    "sg:tags":[
        "physician",
        "surgeon",
        "general"
    ],
    "wof:name":"Omni-Care Medical Center",
    "wof:placetype":"venue"
},
  "geometry": {"coordinates":[-81.41390199999999,28.539954],"type":"Point"}
}