{
  "type": "Feature",
  "properties": {
    "iso:country":"US",
    "sg:address":"1335 Del Prado Blvd S",
    "sg:city":"Cape Coral",
    "sg:classifiers":[
        {
            "category":"Autos & Motor Vehicles",
            "subcategory":"Auto Supplies",
            "type":"Retail Goods"
        },
        {
            "category":"Retail",
            "subcategory":"Auto Repair",
            "type":"Services"
        }
    ],
    "sg:phone":"+1 239 574 3313",
    "sg:postcode":"33990",
    "sg:province":"FL",
    "sg:tags":[
        "tire"
    ],
    "sg:website":"www.tuffy.com/Find-A-Tuffy.Html",
    "wof:name":"Tuffy Auto Service Centers",
    "wof:placetype":"venue"
},
  "geometry": {"coordinates":[-81.94042899999999,26.627134],"type":"Point"}
}