{
  "type": "Feature",
  "properties": {
    "addr:full":"371 Main St Enterprise FL 32725",
    "addr:housenumber":"371",
    "addr:postcode":"32725",
    "addr:street":"Main St",
    "iso:country":"US",
    "sg:address":"371 Main St",
    "sg:city":"Enterprise",
    "sg:classifiers":[
        {
            "category":"Social Services",
            "subcategory":"Child Care",
            "type":"Services"
        }
    ],
    "sg:phone":"+1 386 668 5883",
    "sg:postcode":"32725",
    "sg:province":"FL",
    "wof:name":"Wee Kare Child Care Ctr",
    "wof:placetype":"venue"
},
  "geometry": {"coordinates":[-81.26616,28.872143],"type":"Point"}
}