{
  "type": "Feature",
  "properties": {
    "addr:full":"2614 SE Export Ave Port Saint Lucie FL 34952",
    "addr:housenumber":"2614",
    "addr:postcode":"34952",
    "addr:street":"Se Export Ave",
    "iso:country":"US",
    "sg:address":"2614 SE Export Ave",
    "sg:city":"Port Saint Lucie",
    "sg:classifiers":[
        {
            "category":"Building & Trades",
            "subcategory":"Landscaping Services",
            "type":"Services"
        }
    ],
    "sg:phone":"+1 772 335 3639",
    "sg:postcode":"34952",
    "sg:province":"FL",
    "wof:name":"8 To 5 Lawn Maintenance",
    "wof:placetype":"venue"
},
  "geometry": {"coordinates":[-80.26923600000001,27.266385],"type":"Point"}
}