{
  "type": "Feature",
  "properties": {
    "iso:country":"US",
    "sg:address":"7603 42nd Ave W",
    "sg:city":"Bradenton",
    "sg:classifiers":[
        {
            "category":"Shopping",
            "subcategory":"Florist",
            "type":"Retail Goods"
        }
    ],
    "sg:phone":"+1 941 794 0862",
    "sg:postcode":"34209",
    "sg:province":"FL",
    "wof:name":"Delore's Flowers",
    "wof:placetype":"venue"
},
  "geometry": {"coordinates":[-82.63863499999999,27.464856],"type":"Point"}
}