{
  "type": "Feature",
  "properties": {
    "iso:country":"US",
    "sg:address":"4609 Lake Worth Rd",
    "sg:city":"Greenacres",
    "sg:classifiers":[
        {
            "category":"Personal",
            "subcategory":"Beauty Salon",
            "type":"Services"
        }
    ],
    "sg:phone":"+1 561 966 4609",
    "sg:postcode":"33463",
    "sg:province":"FL",
    "sg:tags":[
        "hair",
        "stylist"
    ],
    "wof:name":"Eliza & Janet's Hair Salon",
    "wof:placetype":"venue"
},
  "geometry": {"coordinates":[-80.115635,26.618594],"type":"Point"}
}