{
  "type": "Feature",
  "properties": {
    "iso:country":"US",
    "sg:address":"1925 10th Ave N",
    "sg:city":"Lake Worth",
    "sg:classifiers":[
        {
            "category":"Shopping",
            "type":"Retail Goods"
        }
    ],
    "sg:phone":"+1 561 582 6500",
    "sg:postcode":"33461",
    "sg:province":"FL",
    "sg:tags":[
        "body",
        "auto",
        "merchandise"
    ],
    "sg:website":"www.actionmobilityproducts.com",
    "wof:name":"Action Mobility Products & Svc",
    "wof:placetype":"venue"
},
  "geometry": {"coordinates":[-80.072018,26.62791],"type":"Point"}
}