{
  "type": "Feature",
  "properties": {
    "addr:full":"156 Harston Ct Lake Mary FL 32746",
    "addr:housenumber":"156",
    "addr:postcode":"32746",
    "addr:street":"Harston Ct",
    "iso:country":"US",
    "sg:address":"156 Harston Ct",
    "sg:city":"Lake Mary",
    "sg:classifiers":[
        {
            "category":"Shopping",
            "type":"Retail Goods"
        }
    ],
    "sg:phone":"+1 407 804 0855",
    "sg:postcode":"32746",
    "sg:province":"FL",
    "sg:tags":[
        "merchandise"
    ],
    "wof:name":"Pain Control Products Medical",
    "wof:placetype":"venue"
},
  "geometry": {"coordinates":[-81.39935699999999,28.763814],"type":"Point"}
}