{
  "type": "Feature",
  "properties": {
    "iso:country":"US",
    "sg:address":"4941 SW 185th Ave",
    "sg:city":"Hollywood",
    "sg:classifiers":[
        {
            "category":"Real Estate",
            "subcategory":"Real Estate Agent",
            "type":"Services"
        }
    ],
    "sg:phone":"+1 954 254 8632",
    "sg:postcode":"33029",
    "sg:province":"FL",
    "wof:name":"Surata LLC",
    "wof:placetype":"venue"
},
  "geometry": {"coordinates":[-80.391994,25.961867],"type":"Point"}
}