{
  "type": "Feature",
  "properties": {
    "iso:country":"US",
    "sg:address":"3742 Sabal Springs Blvd",
    "sg:city":"Fort Myers",
    "sg:classifiers":[
        {
            "category":"Food & Beverages",
            "subcategory":"Liquor & Beverages",
            "type":"Retail Goods"
        }
    ],
    "sg:phone":"+1 239 567 0021",
    "sg:postcode":"33917",
    "sg:province":"FL",
    "sg:tags":[
        "alcoholic"
    ],
    "wof:name":"Ye Olde Wine Cellar",
    "wof:placetype":"venue"
},
  "geometry": {"coordinates":[-81.899379,26.725403],"type":"Point"}
}