{
  "type": "Feature",
  "properties": {
    "addr:full":"5340 E Silver Springs Blvd Silver Springs FL 34488",
    "addr:housenumber":"5340",
    "addr:postcode":"34488",
    "addr:street":"E Silver Springs Blvd",
    "iso:country":"US",
    "sg:address":"5340 E Silver Springs Blvd",
    "sg:city":"Silver Springs",
    "sg:classifiers":[
        {
            "category":"Recreation",
            "type":"Entertainment"
        }
    ],
    "sg:phone":"+1 352 351 8664",
    "sg:postcode":"34488",
    "sg:province":"FL",
    "sg:tags":[
        "martial",
        "arts",
        "instruction"
    ],
    "wof:name":"Cuong NHU Karate Of Ocala",
    "wof:placetype":"venue"
},
  "geometry": {"coordinates":[-82.05996500000001,29.214309],"type":"Point"}
}