{
  "type": "Feature",
  "properties": {
    "addr:full":"3410 Palm Ave Hialeah FL 33012",
    "addr:housenumber":"3410",
    "addr:postcode":"33012",
    "addr:street":"Palm Ave",
    "iso:country":"US",
    "sg:address":"3410 Palm Ave",
    "sg:city":"Hialeah",
    "sg:classifiers":[
        {
            "category":"Insurance",
            "subcategory":"Insurance Agent",
            "type":"Services"
        },
        {
            "category":"Insurance",
            "subcategory":"Hazard Insurance",
            "type":"Services"
        }
    ],
    "sg:phone":"+1 305 884 6868",
    "sg:postcode":"33012",
    "sg:province":"FL",
    "sg:tags":[
        "auto",
        "recreational",
        "motorcycle",
        "vehicle",
        "marine",
        "boat"
    ],
    "wof:name":"Segura Insurance",
    "wof:placetype":"venue"
},
  "geometry": {"coordinates":[-80.28253599999999,25.853104],"type":"Point"}
}