{
  "type": "Feature",
  "properties": {
    "addr:full":"3725 SE Ocean Blvd Stuart FL 34996",
    "addr:housenumber":"3725",
    "addr:postcode":"34996",
    "addr:street":"Se Ocean Blvd",
    "iso:country":"US",
    "sg:address":"3725 SE Ocean Blvd",
    "sg:city":"Stuart",
    "sg:classifiers":[
        {
            "category":"Professional",
            "subcategory":"Business Services",
            "type":"Services"
        }
    ],
    "sg:phone":"+1 800 777 1089",
    "sg:postcode":"34996",
    "sg:province":"FL",
    "sg:tags":[
        "company",
        "holding"
    ],
    "wof:name":"Poma Financial Group Inc",
    "wof:placetype":"venue"
},
  "geometry": {"coordinates":[-80.200564,27.202818],"type":"Point"}
}