{
  "type": "Feature",
  "properties": {
    "iso:country":"US",
    "sg:address":"173 NW 11th St",
    "sg:city":"Miami",
    "sg:classifiers":[
        {
            "category":"Food & Beverages",
            "subcategory":"Liquor & Beverages",
            "type":"Retail Goods"
        }
    ],
    "sg:phone":"+1 305 375 0200",
    "sg:postcode":"33136",
    "sg:province":"FL",
    "sg:tags":[
        "beer",
        "spirit",
        "store",
        "wine"
    ],
    "wof:name":"Ideal Package Store",
    "wof:placetype":"venue"
},
  "geometry": {"coordinates":[-80.1978,25.7845],"type":"Point"}
}