{
  "type": "Feature",
  "properties": {
    "addr:full":"243 NW South River Dr Miami FL 33128",
    "addr:housenumber":"243",
    "addr:postcode":"33128",
    "addr:street":"Nw South River Dr",
    "iso:country":"US",
    "sg:address":"243 NW South River Dr",
    "sg:city":"Miami",
    "sg:classifiers":[
        {
            "category":"Recreation",
            "subcategory":"Marina",
            "type":"Entertainment"
        }
    ],
    "sg:phone":"+1 305 325 1023",
    "sg:postcode":"33128",
    "sg:province":"FL",
    "wof:name":"LA Coloma Marina Inc",
    "wof:placetype":"venue"
},
  "geometry": {"coordinates":[-80.204392,25.776356],"type":"Point"}
}