{
  "type": "Feature",
  "properties": {
    "iso:country":"US",
    "sg:address":"918 S Missouri Ave",
    "sg:city":"Clearwater",
    "sg:classifiers":[
        {
            "category":"Insurance",
            "subcategory":"Insurance Agent",
            "type":"Services"
        }
    ],
    "sg:phone":"+1 727 446 7735",
    "sg:postcode":"33756",
    "sg:province":"FL",
    "sg:tags":[
        "homeowner"
    ],
    "wof:name":"Gotta Havit Auto Insurance",
    "wof:placetype":"venue"
},
  "geometry": {"coordinates":[-82.787689,27.956113],"type":"Point"}
}