{
  "type": "Feature",
  "properties": {
    "iso:country":"US",
    "sg:address":"1025 5th Ave N",
    "sg:city":"Naples",
    "sg:classifiers":[
        {
            "category":"Professional",
            "subcategory":"Lawyer & Legal Services",
            "type":"Services"
        }
    ],
    "sg:phone":"+1 239 434 6644",
    "sg:postcode":"34102",
    "sg:province":"FL",
    "wof:name":"Michael A Baviello Jr",
    "wof:placetype":"venue"
},
  "geometry": {"coordinates":[-81.792486,26.153306],"type":"Point"}
}