{
  "type": "Feature",
  "properties": {
    "iso:country":"US",
    "sg:address":"3803 1st St",
    "sg:city":"Bradenton",
    "sg:classifiers":[
        {
            "category":"Restaurant",
            "type":"Food & Drink"
        }
    ],
    "sg:menulink":"http://www.allmenus.com/fl/bradenton/160301-burger-king/menu/",
    "sg:phone":"+1 941 748 6186",
    "sg:postcode":"34208",
    "sg:province":"FL",
    "sg:tags":[
        "burger",
        "american"
    ],
    "wof:name":"Burger King",
    "wof:placetype":"venue"
},
  "geometry": {"coordinates":[-82.562853,27.464752],"type":"Point"}
}