{
  "type": "Feature",
  "properties": {
    "addr:full":"2073 Victory Garden Ln Tallahassee FL 32301",
    "addr:housenumber":"2073",
    "addr:postcode":"32301",
    "addr:street":"Victory Garden Ln",
    "iso:country":"US",
    "sg:address":"2073 Victory Garden Ln",
    "sg:city":"Tallahassee",
    "sg:classifiers":[
        {
            "category":"Professional",
            "subcategory":"Computer Services",
            "type":"Services"
        }
    ],
    "sg:phone":"+1 850 219 1273",
    "sg:postcode":"32301",
    "sg:province":"FL",
    "sg:tags":[
        "consultant",
        "designer"
    ],
    "wof:name":"Venus Technologies Inc",
    "wof:placetype":"venue"
},
  "geometry": {"coordinates":[-84.239288,30.444137],"type":"Point"}
}