{
  "type": "Feature",
  "properties": {
    "addr:full":"11905 NE 2nd Ave Miami FL 33161",
    "addr:housenumber":"11905",
    "addr:postcode":"33161",
    "addr:street":"Ne 2Nd Ave",
    "iso:country":"US",
    "sg:address":"11905 NE 2nd Ave",
    "sg:city":"Miami",
    "sg:classifiers":[
        {
            "category":"Social Services",
            "subcategory":"Child Care",
            "type":"Services"
        }
    ],
    "sg:phone":"+1 305 891 7202",
    "sg:postcode":"33161",
    "sg:province":"FL",
    "sg:tags":[
        "nursery",
        "day"
    ],
    "wof:name":"Saint Lawernce Learning Center",
    "wof:placetype":"venue"
},
  "geometry": {"coordinates":[-80.194383,25.884534],"type":"Point"}
}