{
  "type": "Feature",
  "properties": {
    "addr:full":"1040 Bayview Dr Fort Lauderdale FL 33304",
    "addr:housenumber":"1040",
    "addr:postcode":"33304",
    "addr:street":"Bayview Dr",
    "iso:country":"US",
    "sg:address":"1040 Bayview Dr",
    "sg:city":"Fort Lauderdale",
    "sg:classifiers":[
        {
            "category":"Deli",
            "type":"Food & Drink"
        }
    ],
    "sg:menulink":"http://www.allmenus.com/fl/fort-lauderdale/126030-blimpie-subs--sandwiches/menu/",
    "sg:phone":"+1 954 537 3388",
    "sg:postcode":"33304",
    "sg:province":"FL",
    "sg:tags":[
        "wrap",
        "american",
        "sandwich"
    ],
    "wof:name":"Blimpie Subs & Sandwiches",
    "wof:placetype":"venue"
},
  "geometry": {"coordinates":[-80.11483699999999,26.139252],"type":"Point"}
}