{
  "type": "Feature",
  "properties": {
    "iso:country":"US",
    "sg:address":"823 NW 133rd Ct",
    "sg:city":"Miami",
    "sg:classifiers":[
        {
            "category":"Shopping",
            "subcategory":"Computers & Home Electronics",
            "type":"Retail Goods"
        }
    ],
    "sg:phone":"+1 305 613 9313",
    "sg:postcode":"33182",
    "sg:province":"FL",
    "sg:tags":[
        "printer",
        "supply"
    ],
    "wof:name":"A & C Forms Solutions, Inc.",
    "wof:placetype":"venue"
},
  "geometry": {"coordinates":[-80.411827,25.77746],"type":"Point"}
}