{
  "type": "Feature",
  "properties": {
    "iso:country":"US",
    "sg:address":"41 SW Ave B",
    "sg:city":"Belle Glade",
    "sg:classifiers":[
        {
            "category":"Banks & Credit Unions",
            "subcategory":"Bank",
            "type":"Services"
        }
    ],
    "sg:phone":"+1 561 996 4441",
    "sg:postcode":"33430",
    "sg:province":"FL",
    "wof:name":"Wachovia Bank",
    "wof:placetype":"venue"
},
  "geometry": {"coordinates":[-80.668207,26.684997],"type":"Point"}
}