{
  "type": "Feature",
  "properties": {
    "iso:country":"US",
    "sg:address":"5217 Washington Rd",
    "sg:city":"Delray Beach",
    "sg:classifiers":[
        {
            "category":"Arts & Performance",
            "subcategory":"Theater",
            "type":"Entertainment"
        }
    ],
    "sg:phone":"+1 561 495 0009",
    "sg:postcode":"33484",
    "sg:province":"FL",
    "sg:tags":[
        "live",
        "music"
    ],
    "wof:name":"Imys Corp",
    "wof:placetype":"venue"
},
  "geometry": {"coordinates":[-80.125608,26.452567],"type":"Point"}
}