{
  "type": "Feature",
  "properties": {
    "iso:country":"US",
    "sg:address":"4223 Del Prado Blvd S",
    "sg:city":"Cape Coral",
    "sg:classifiers":[
        {
            "category":"Professional",
            "subcategory":"Lawyer & Legal Services",
            "type":"Services"
        }
    ],
    "sg:phone":"+1 239 540 7111",
    "sg:postcode":"33904",
    "sg:province":"FL",
    "wof:name":"Dell & Schaefer Accident Attorneys",
    "wof:placetype":"venue"
},
  "geometry": {"coordinates":[-81.943703,26.573099],"type":"Point"}
}