{
  "type": "Feature",
  "properties": {
    "iso:country":"US",
    "sg:address":"1300 Executive Center Dr",
    "sg:city":"Tallahassee",
    "sg:classifiers":[
        {
            "category":"Health Services",
            "subcategory":"Clinic",
            "type":"Services"
        }
    ],
    "sg:phone":"+1 850 656 8945",
    "sg:postcode":"32301",
    "sg:province":"FL",
    "wof:name":"Portamedic Health Surveys",
    "wof:placetype":"venue"
},
  "geometry": {"coordinates":[-84.235584,30.425151],"type":"Point"}
}