{
  "type": "Feature",
  "properties": {
    "iso:country":"US",
    "sg:address":"5940 Frond Way",
    "sg:city":"Ruskin",
    "sg:classifiers":[
        {
            "category":"Health Services",
            "subcategory":"Clinic",
            "type":"Services"
        }
    ],
    "sg:phone":"+1 813 641 0066",
    "sg:postcode":"33572",
    "sg:province":"FL",
    "wof:name":"Apollo Healthcare Svc",
    "wof:placetype":"venue"
},
  "geometry": {"coordinates":[-82.39869299999999,27.762871],"type":"Point"}
}