{
  "type": "Feature",
  "properties": {
    "addr:full":"22 Edgewood Ave S Jacksonville FL 32254",
    "addr:housenumber":"22",
    "addr:postcode":"32254",
    "addr:street":"Edgewood Ave S",
    "iso:country":"US",
    "sg:address":"22 Edgewood Ave S",
    "sg:city":"Jacksonville",
    "sg:classifiers":[
        {
            "category":"Autos & Motor Vehicles",
            "subcategory":"Auto Supplies",
            "type":"Retail Goods"
        }
    ],
    "sg:phone":"+1 904 568 7849",
    "sg:postcode":"32254",
    "sg:province":"FL",
    "sg:tags":[
        "battery"
    ],
    "wof:name":"Touchdown Batteries Inc",
    "wof:placetype":"venue"
},
  "geometry": {"coordinates":[-81.73093799999999,30.327067],"type":"Point"}
}