{
  "type": "Feature",
  "properties": {
    "addr:full":"390 Frances Ave Casselberry FL 32707",
    "addr:housenumber":"390",
    "addr:postcode":"32707",
    "addr:street":"Frances Ave",
    "iso:country":"US",
    "sg:address":"390 Frances Ave",
    "sg:city":"Casselberry",
    "sg:classifiers":[
        {
            "category":"Building & Trades",
            "subcategory":"Landscaping Services",
            "type":"Services"
        }
    ],
    "sg:phone":"+1 407 696 5459",
    "sg:postcode":"32707",
    "sg:province":"FL",
    "sg:tags":[
        "landscape"
    ],
    "wof:name":"Michael French",
    "wof:placetype":"venue"
},
  "geometry": {"coordinates":[-81.327853,28.676866],"type":"Point"}
}