{
  "type": "Feature",
  "properties": {
    "iso:country":"US",
    "sg:address":"465 11th Ave N",
    "sg:city":"Jacksonville Bch",
    "sg:classifiers":[
        {
            "category":"Organizations",
            "subcategory":"Religious Organization",
            "type":"Services"
        }
    ],
    "sg:phone":"+1 904 249 4091",
    "sg:postcode":"32250",
    "sg:province":"FL",
    "sg:tags":[
        "church"
    ],
    "sg:website":"www.spbts.net",
    "wof:name":"St Paul's By The Sea Episcopal",
    "wof:placetype":"venue"
},
  "geometry": {"coordinates":[-81.39568800000001,30.299145],"type":"Point"}
}