{
  "type": "Feature",
  "properties": {
    "addr:full":"1015 Illinois Ave Palm Harbor FL 34683",
    "addr:housenumber":"1015",
    "addr:postcode":"34683",
    "addr:street":"Illinois Ave",
    "iso:country":"US",
    "sg:address":"1015 Illinois Ave",
    "sg:city":"Palm Harbor",
    "sg:classifiers":[
        {
            "category":"Professional",
            "type":"Services"
        },
        {
            "category":"Retail",
            "subcategory":"Auto Repair",
            "type":"Services"
        }
    ],
    "sg:phone":"+1 727 772 8833",
    "sg:postcode":"34683",
    "sg:province":"FL",
    "sg:tags":[
        "general"
    ],
    "wof:name":"Capital Service Center Inc",
    "wof:placetype":"venue"
},
  "geometry": {"coordinates":[-82.766124,28.074516],"type":"Point"}
}