{
  "type": "Feature",
  "properties": {
    "iso:country":"US",
    "sg:address":"26133 US Hwy 19",
    "sg:city":"Clearwater",
    "sg:classifiers":[
        {
            "category":"Health Services",
            "subcategory":"Health Practitioner",
            "type":"Services"
        }
    ],
    "sg:phone":"+1 727 796 8927",
    "sg:postcode":"33763",
    "sg:province":"FL",
    "sg:tags":[
        "dietitian"
    ],
    "wof:name":"Dietetic Consulting Svc",
    "wof:placetype":"venue"
},
  "geometry": {"coordinates":[-82.73128699999999,28.009355],"type":"Point"}
}