{
  "type": "Feature",
  "properties": {
    "iso:country":"US",
    "sg:address":"1467 SW 17th Ter",
    "sg:city":"Miami",
    "sg:classifiers":[
        {
            "category":"Manufacturing",
            "subcategory":"Rubber & Plastics",
            "type":"Manufacturing & Wholesale Goods"
        }
    ],
    "sg:phone":"+1 305 858 5507",
    "sg:postcode":"33145",
    "sg:province":"FL",
    "sg:tags":[
        "compounding",
        "resin",
        "custom"
    ],
    "wof:name":"Apu Inc",
    "wof:placetype":"venue"
},
  "geometry": {"coordinates":[-80.219576,25.756574],"type":"Point"}
}