{
  "type": "Feature",
  "properties": {
    "iso:country":"US",
    "sg:address":"5010 W Mockingbird St",
    "sg:city":"Homosassa",
    "sg:classifiers":[
        {
            "category":"Place Of Worship",
            "type":"Public Place"
        }
    ],
    "sg:phone":"+1 352 302 3098",
    "sg:postcode":"34446",
    "sg:province":"FL",
    "sg:tags":[
        "church"
    ],
    "wof:name":"The Church Of Jesus Christ Of West Central Flori",
    "wof:placetype":"venue"
},
  "geometry": {"coordinates":[-82.514652,28.773099],"type":"Point"}
}