{
  "type": "Feature",
  "properties": {
    "addr:full":"6700 Crosswinds Dr N St Petersburg FL 33710",
    "addr:housenumber":"6700",
    "addr:postcode":"33710",
    "addr:street":"Crosswinds Dr N",
    "iso:country":"US",
    "sg:address":"6700 Crosswinds Dr N",
    "sg:city":"St Petersburg",
    "sg:classifiers":[
        {
            "category":"Health Services",
            "subcategory":"Doctor",
            "type":"Services"
        }
    ],
    "sg:phone":"+1 727 344 4651",
    "sg:postcode":"33710",
    "sg:province":"FL",
    "sg:tags":[
        "physician",
        "surgeon"
    ],
    "wof:name":"Gulfcoast Ob/Gyn",
    "wof:placetype":"venue"
},
  "geometry": {"coordinates":[-82.731297,27.789913],"type":"Point"}
}