{
  "type": "Feature",
  "properties": {
    "addr:full":"10510 127th Ave Largo FL 33773",
    "addr:housenumber":"10510",
    "addr:postcode":"33773",
    "addr:street":"127Th Ave",
    "iso:country":"US",
    "sg:address":"10510 127th Ave",
    "sg:city":"Largo",
    "sg:classifiers":[
        {
            "category":"Retail",
            "subcategory":"Auto Repair",
            "type":"Services"
        }
    ],
    "sg:phone":"+1 727 734 0109",
    "sg:postcode":"33773",
    "sg:province":"FL",
    "sg:tags":[
        "repairing",
        "automobile"
    ],
    "wof:name":"Poole Drilling Co Inc",
    "wof:placetype":"venue"
},
  "geometry": {"coordinates":[-82.78473,27.888122],"type":"Point"}
}