{
  "type": "Feature",
  "properties": {
    "iso:country":"US",
    "sg:address":"21301 S Tamiami Trl # 320",
    "sg:city":"Estero",
    "sg:classifiers":[
        {
            "category":"Professional",
            "subcategory":"Detective & Security Services",
            "type":"Services"
        }
    ],
    "sg:phone":"+1 239 207 6515",
    "sg:postcode":"33928",
    "sg:province":"FL",
    "sg:tags":[
        "information",
        "bureau"
    ],
    "wof:name":"Supplemental Instructional Services Inc",
    "wof:placetype":"venue"
},
  "geometry": {"coordinates":[-81.810597,26.4299],"type":"Point"}
}