{
  "type": "Feature",
  "properties": {
    "addr:full":"1574 SE 3rd Ct Deerfield Beach FL 33441",
    "addr:housenumber":"1574",
    "addr:postcode":"33441",
    "addr:street":"Se 3Rd Ct",
    "iso:country":"US",
    "sg:address":"1574 SE 3rd Ct",
    "sg:city":"Deerfield Beach",
    "sg:classifiers":[
        {
            "category":"Professional",
            "subcategory":"Accounting & Tax Preparation",
            "type":"Services"
        }
    ],
    "sg:phone":"+1 954 420 0051",
    "sg:postcode":"33441",
    "sg:province":"FL",
    "wof:name":"Genesis Services Corp",
    "wof:placetype":"venue"
},
  "geometry": {"coordinates":[-80.08514599999999,26.313503],"type":"Point"}
}