{
  "type": "Feature",
  "properties": {
    "addr:full":"4062 NE 7th Ave Oakland Park FL 33334",
    "addr:housenumber":"4062",
    "addr:postcode":"33334",
    "addr:street":"Ne 7Th Ave",
    "iso:country":"US",
    "sg:address":"4062 NE 7th Ave",
    "sg:city":"Oakland Park",
    "sg:classifiers":[
        {
            "category":"Retail",
            "subcategory":"Repair Shop",
            "type":"Services"
        }
    ],
    "sg:phone":"+1 954 565 2216",
    "sg:postcode":"33334",
    "sg:province":"FL",
    "sg:tags":[
        "instrument",
        "musical"
    ],
    "wof:name":"Alpha Kinetix Repair Svc",
    "wof:placetype":"venue"
},
  "geometry": {"coordinates":[-80.137626,26.177824],"type":"Point"}
}