{
  "type": "Feature",
  "properties": {
    "iso:country":"US",
    "sg:address":"1915 Airport Blvd",
    "sg:city":"Melbourne",
    "sg:classifiers":[
        {
            "category":"Real Estate",
            "subcategory":"Real Estate Agent",
            "type":"Services"
        }
    ],
    "sg:phone":"+1 321 725 0006",
    "sg:postcode":"32901",
    "sg:province":"FL",
    "wof:name":"Interstate Properties Inc",
    "wof:placetype":"venue"
},
  "geometry": {"coordinates":[-80.627028,28.079706],"type":"Point"}
}