{
  "type": "Feature",
  "properties": {
    "iso:country":"US",
    "sg:address":"4205 Belfort Rd",
    "sg:city":"Jacksonville",
    "sg:classifiers":[
        {
            "category":"Health Services",
            "subcategory":"Doctor",
            "type":"Services"
        }
    ],
    "sg:phone":"+1 904 296 2992",
    "sg:postcode":"32216",
    "sg:province":"FL",
    "sg:tags":[
        "medical"
    ],
    "wof:name":"Michelle McLanaham MD PA",
    "wof:placetype":"venue"
},
  "geometry": {"coordinates":[-81.584174,30.252653],"type":"Point"}
}