{
  "type": "Feature",
  "properties": {
    "addr:full":"200 Lincoln Rd Miami Beach FL 33139",
    "addr:housenumber":"200",
    "addr:postcode":"33139",
    "addr:street":"Lincoln Rd",
    "iso:country":"US",
    "sg:address":"200 Lincoln Rd",
    "sg:city":"Miami Beach",
    "sg:classifiers":[
        {
            "category":"Shopping",
            "subcategory":"Department Store",
            "type":"Retail Goods"
        }
    ],
    "sg:phone":"+1 305 531 9766",
    "sg:postcode":"33139",
    "sg:province":"FL",
    "sg:website":"www.alvinsisland.com/",
    "wof:name":"Alvin's Island Tropical Department Store",
    "wof:placetype":"venue"
},
  "geometry": {"coordinates":[-80.13014800000001,25.790435],"type":"Point"}
}