{
  "type": "Feature",
  "properties": {
    "iso:country":"US",
    "sg:address":"1231 Commons Ct",
    "sg:city":"Clermont",
    "sg:classifiers":[
        {
            "category":"Building & Trades",
            "subcategory":"Construction",
            "type":"Services"
        }
    ],
    "sg:phone":"+1 352 394 0393",
    "sg:postcode":"34711",
    "sg:province":"FL",
    "sg:tags":[
        "management"
    ],
    "wof:name":"Full Phase Construction",
    "wof:placetype":"venue"
},
  "geometry": {"coordinates":[-81.734234,28.567263],"type":"Point"}
}