{
  "type": "Feature",
  "properties": {
    "iso:country":"US",
    "sg:address":"10295 SE 159th St",
    "sg:city":"Summerfield",
    "sg:classifiers":[
        {
            "category":"Professional",
            "subcategory":"Art Services",
            "type":"Services"
        }
    ],
    "sg:phone":"+1 352 387 1121",
    "sg:postcode":"34491",
    "sg:province":"FL",
    "sg:tags":[
        "designer",
        "display",
        "producer"
    ],
    "wof:name":"Contractors Design Center",
    "wof:placetype":"venue"
},
  "geometry": {"coordinates":[-81.98217,28.990665],"type":"Point"}
}