{
  "type": "Feature",
  "properties": {
    "iso:country":"US",
    "sg:address":"200 NW 21st St",
    "sg:city":"Miami",
    "sg:classifiers":[
        {
            "category":"Home & Garden",
            "subcategory":"Furniture",
            "type":"Retail Goods"
        }
    ],
    "sg:phone":"+1 305 887 5859",
    "sg:postcode":"33127",
    "sg:province":"FL",
    "wof:name":"Lyns Furniture",
    "wof:placetype":"venue"
},
  "geometry": {"coordinates":[-80.20044,25.796782],"type":"Point"}
}