{
  "type": "Feature",
  "properties": {
    "iso:country":"US",
    "sg:address":"8400 SW 14th St",
    "sg:city":"Miami",
    "sg:classifiers":[
        {
            "category":"Building & Trades",
            "subcategory":"Electrical",
            "type":"Services"
        }
    ],
    "sg:phone":"+1 305 260 4989",
    "sg:postcode":"33144",
    "sg:province":"FL",
    "sg:tags":[
        "electrical",
        "contractor"
    ],
    "wof:name":"Electrical Masters Inc",
    "wof:placetype":"venue"
},
  "geometry": {"coordinates":[-80.33257399999999,25.756768],"type":"Point"}
}