{
  "type": "Feature",
  "properties": {
    "iso:country":"US",
    "sg:address":"505 Palm St",
    "sg:city":"West Palm Beach",
    "sg:classifiers":[
        {
            "category":"Professional",
            "subcategory":"Management & Consulting",
            "type":"Services"
        }
    ],
    "sg:phone":"+1 561 835 0073",
    "sg:postcode":"33401",
    "sg:province":"FL",
    "wof:name":"American Financial Advisor",
    "wof:placetype":"venue"
},
  "geometry": {"coordinates":[-80.056095,26.699414],"type":"Point"}
}