{
  "type": "Feature",
  "properties": {
    "iso:country":"US",
    "sg:address":"9730 W Sample Rd",
    "sg:city":"Coral Springs",
    "sg:classifiers":[
        {
            "category":"Banks & Credit Unions",
            "subcategory":"Bank",
            "type":"Services"
        }
    ],
    "sg:phone":"+1 954 771 6300",
    "sg:postcode":"33065",
    "sg:province":"FL",
    "sg:tags":[
        "other",
        "plan",
        "card"
    ],
    "wof:name":"Bank Card Processing-Retriever",
    "wof:placetype":"venue"
},
  "geometry": {"coordinates":[-80.256517,26.272456],"type":"Point"}
}