{
  "type": "Feature",
  "properties": {
    "addr:full":"4624 Thornlea Rd Orlando FL 32817",
    "addr:housenumber":"4624",
    "addr:postcode":"32817",
    "addr:street":"Thornlea Rd",
    "iso:country":"US",
    "sg:address":"4624 Thornlea Rd",
    "sg:city":"Orlando",
    "sg:classifiers":[
        {
            "category":"Shopping",
            "type":"Retail Goods"
        }
    ],
    "sg:phone":"+1 407 678 7822",
    "sg:postcode":"32817",
    "sg:province":"FL",
    "sg:tags":[
        "equipment",
        "telephone",
        "supply"
    ],
    "sg:website":"www.telephonesuperstore.com",
    "wof:name":"TELEPHONESUPERSTORE.COM",
    "wof:placetype":"venue"
},
  "geometry": {"coordinates":[-81.27578699999999,28.604999],"type":"Point"}
}