{
  "type": "Feature",
  "properties": {
    "iso:country":"US",
    "sg:address":"2326 W 78th St",
    "sg:city":"Hialeah",
    "sg:classifiers":[
        {
            "category":"Wholesale",
            "subcategory":"Medical Equipment & Supplies",
            "type":"Manufacturing & Wholesale Goods"
        },
        {
            "category":"Retail",
            "subcategory":"Repair Shop",
            "type":"Services"
        }
    ],
    "sg:phone":"+1 305 558 6511",
    "sg:postcode":"33016",
    "sg:province":"FL",
    "sg:tags":[
        "biomedical",
        "related"
    ],
    "wof:name":"Alternative Biomedical Svcs",
    "wof:placetype":"venue"
},
  "geometry": {"coordinates":[-80.330353,25.893228],"type":"Point"}
}