{
  "type": "Feature",
  "properties": {
    "addr:full":"244 W Story Rd Winter Garden FL 34787",
    "addr:housenumber":"244",
    "addr:postcode":"34787",
    "addr:street":"W Story Rd",
    "iso:country":"US",
    "sg:address":"244 W Story Rd",
    "sg:city":"Winter Garden",
    "sg:classifiers":[
        {
            "category":"Food & Beverages",
            "subcategory":"Groceries & Convenience Stores",
            "type":"Retail Goods"
        }
    ],
    "sg:phone":"+1 407 654 0944",
    "sg:postcode":"34787",
    "sg:province":"FL",
    "wof:name":"Story Food Mart",
    "wof:placetype":"venue"
},
  "geometry": {"coordinates":[-81.59173800000001,28.558266],"type":"Point"}
}