{
  "type": "Feature",
  "properties": {
    "addr:full":"9501 Avenel Ln Port Saint Lucie FL 34986",
    "addr:housenumber":"9501",
    "addr:postcode":"34986",
    "addr:street":"Avenel Ln",
    "iso:country":"US",
    "sg:address":"9501 Avenel Ln",
    "sg:city":"Port Saint Lucie",
    "sg:classifiers":[
        {
            "category":"Manufacturing",
            "subcategory":"Rubber & Plastics",
            "type":"Manufacturing & Wholesale Goods"
        }
    ],
    "sg:phone":"+1 772 489 0001",
    "sg:postcode":"34986",
    "sg:province":"FL",
    "sg:tags":[
        "cargo",
        "mfg",
        "airbags",
        "containment"
    ],
    "wof:name":"Mincor",
    "wof:placetype":"venue"
},
  "geometry": {"coordinates":[-80.42260899999999,27.336832],"type":"Point"}
}