{
  "type": "Feature",
  "properties": {
    "addr:full":"725 Xanadu Pl Jupiter FL 33477",
    "addr:housenumber":"725",
    "addr:postcode":"33477",
    "addr:street":"Xanadu Pl",
    "iso:country":"US",
    "sg:address":"725 Xanadu Pl",
    "sg:city":"Jupiter",
    "sg:classifiers":[
        {
            "category":"Manufacturing",
            "subcategory":"Printing",
            "type":"Manufacturing & Wholesale Goods"
        }
    ],
    "sg:phone":"+1 561 655 1080",
    "sg:postcode":"33477",
    "sg:province":"FL",
    "sg:tags":[
        "lithographic",
        "commercial"
    ],
    "wof:name":"Zip Print",
    "wof:placetype":"venue"
},
  "geometry": {"coordinates":[-80.07138399999999,26.924836],"type":"Point"}
}