{
  "type": "Feature",
  "properties": {
    "iso:country":"US",
    "sg:address":"5802 Makoma Dr",
    "sg:city":"Orlando",
    "sg:classifiers":[
        {
            "category":"Organizations",
            "subcategory":"Religious Organization",
            "type":"Services"
        }
    ],
    "sg:phone":"+1 407 888 8919",
    "sg:postcode":"32839",
    "sg:province":"FL",
    "wof:name":"Newness International Prayer",
    "wof:placetype":"venue"
},
  "geometry": {"coordinates":[-81.395297,28.474508],"type":"Point"}
}