{
  "type": "Feature",
  "properties": {
    "iso:country":"US",
    "sg:address":"401 Biscayne Blvd Miamarina Slip B20",
    "sg:city":"Miami",
    "sg:classifiers":[
        {
            "category":"Recreation",
            "subcategory":"Boat Charter",
            "type":"Entertainment"
        },
        {
            "category":"Recreation",
            "subcategory":"Fishing",
            "type":"Entertainment"
        }
    ],
    "sg:phone":"+1 786 486 7200",
    "sg:postcode":"33130",
    "sg:province":"FL",
    "sg:tags":[
        "boating"
    ],
    "sg:website":"www.fishjumanji.com",
    "wof:name":"Miami Deep Sea Fishing Trips - Jumanji",
    "wof:placetype":"venue"
},
  "geometry": {"coordinates":[-80.188001,25.778435],"type":"Point"}
}