{
  "type": "Feature",
  "properties": {
    "iso:country":"US",
    "sg:address":"4175 1st Ave NW",
    "sg:city":"Naples",
    "sg:classifiers":[
        {
            "category":"Farming",
            "subcategory":"Farm",
            "type":"Manufacturing & Wholesale Goods"
        }
    ],
    "sg:phone":"+1 239 658 2865",
    "sg:postcode":"34119",
    "sg:province":"FL",
    "wof:name":"Harvey Farms",
    "wof:placetype":"venue"
},
  "geometry": {"coordinates":[-81.69806199999999,26.23058],"type":"Point"}
}