{
  "type": "Feature",
  "properties": {
    "addr:full":"2131 S Semoran Blvd Orlando FL 32822",
    "addr:housenumber":"2131",
    "addr:postcode":"32822",
    "addr:street":"S Semoran Blvd",
    "iso:country":"US",
    "sg:address":"2131 S Semoran Blvd",
    "sg:city":"Orlando",
    "sg:classifiers":[
        {
            "category":"Fast Food",
            "type":"Food & Drink"
        },
        {
            "category":"Restaurant",
            "type":"Food & Drink"
        },
        {
            "category":"Food & Beverages",
            "subcategory":"Groceries & Convenience Stores",
            "type":"Retail Goods"
        }
    ],
    "sg:phone":"+1 407 884 9559",
    "sg:postcode":"32822",
    "sg:province":"FL",
    "sg:tags":[
        "shop",
        "american",
        "sandwich",
        "take"
    ],
    "wof:name":"Subway",
    "wof:placetype":"venue"
},
  "geometry": {"coordinates":[-81.310249,28.517729],"type":"Point"}
}