{
  "type": "Feature",
  "properties": {
    "addr:full":"4525 Capital Cir NW Tallahassee FL 32303",
    "addr:housenumber":"4525",
    "addr:postcode":"32303",
    "addr:street":"Capital Cir Nw",
    "iso:country":"US",
    "sg:address":"4525 Capital Cir NW",
    "sg:city":"Tallahassee",
    "sg:classifiers":[
        {
            "category":"Manufacturing",
            "subcategory":"Building Materials",
            "type":"Manufacturing & Wholesale Goods"
        }
    ],
    "sg:phone":"+1 850 562 5168",
    "sg:postcode":"32303",
    "sg:province":"FL",
    "sg:tags":[
        "mfg",
        "wood",
        "kitchen",
        "cabinet"
    ],
    "wof:name":"Gene Plant",
    "wof:placetype":"venue"
},
  "geometry": {"coordinates":[-84.36641,30.51485],"type":"Point"}
}