{
  "type": "Feature",
  "properties": {
    "iso:country":"US",
    "sg:address":"437 Perdida Ave",
    "sg:city":"Edgewater",
    "sg:classifiers":[
        {
            "category":"Freight",
            "type":"Transportation"
        }
    ],
    "sg:phone":"+1 386 409 8464",
    "sg:postcode":"32132",
    "sg:province":"FL",
    "sg:tags":[
        "operator",
        "local",
        "trucking"
    ],
    "wof:name":"Load All Trucking",
    "wof:placetype":"venue"
},
  "geometry": {"coordinates":[-80.9158,29.001225],"type":"Point"}
}