{
  "type": "Feature",
  "properties": {
    "iso:country":"US",
    "sg:address":"5051 L B Mcleod Rd",
    "sg:city":"Orlando",
    "sg:classifiers":[
        {
            "category":"Manufacturing",
            "subcategory":"Chemicals & Compounds",
            "type":"Manufacturing & Wholesale Goods"
        }
    ],
    "sg:phone":"+1 407 649 8433",
    "sg:postcode":"32811",
    "sg:province":"FL",
    "sg:tags":[
        "control",
        "pest",
        "equipment",
        "supply"
    ],
    "sg:website":"http://www.sndcoffee.com",
    "wof:name":"Univar USA Inc",
    "wof:placetype":"venue"
},
  "geometry": {"coordinates":[-81.443579,28.505689],"type":"Point"}
}