{
  "type": "Feature",
  "properties": {
    "iso:country":"US",
    "sg:address":"241 Royal Palm Way",
    "sg:city":"Palm Beach",
    "sg:classifiers":[
        {
            "category":"Banks & Credit Unions",
            "subcategory":"Bank",
            "type":"Services"
        }
    ],
    "sg:phone":"+1 561 659 7028",
    "sg:postcode":"33480",
    "sg:province":"FL",
    "wof:name":"Citigroup Private Bank",
    "wof:placetype":"venue"
},
  "geometry": {"coordinates":[-80.037847,26.705726],"type":"Point"}
}