{
  "type": "Feature",
  "properties": {
    "addr:full":"2801 N Palm Aire Dr Pompano Beach FL 33069",
    "addr:housenumber":"2801",
    "addr:postcode":"33069",
    "addr:street":"N Palm Aire Dr",
    "iso:country":"US",
    "sg:address":"2801 N Palm Aire Dr",
    "sg:city":"Pompano Beach",
    "sg:classifiers":[
        {
            "category":"Arts & Performance",
            "subcategory":"Theater",
            "type":"Entertainment"
        }
    ],
    "sg:phone":"+1 954 969 8184",
    "sg:postcode":"33069",
    "sg:province":"FL",
    "sg:tags":[
        "theatrical"
    ],
    "wof:name":"Manifest Corp Inc",
    "wof:placetype":"venue"
},
  "geometry": {"coordinates":[-80.16341,26.22151],"type":"Point"}
}