{
  "type": "Feature",
  "properties": {
    "iso:country":"US",
    "sg:address":"9704 SW 40th St",
    "sg:city":"Miami",
    "sg:classifiers":[
        {
            "category":"Personal",
            "subcategory":"Beauty Salon",
            "type":"Services"
        }
    ],
    "sg:phone":"+1 305 480 7731",
    "sg:postcode":"33165",
    "sg:province":"FL",
    "sg:tags":[
        "hair"
    ],
    "wof:name":"Styles & Cuts",
    "wof:placetype":"venue"
},
  "geometry": {"coordinates":[-80.35189800000001,25.7327],"type":"Point"}
}