{
  "type": "Feature",
  "properties": {
    "addr:full":"9108 Blairmoor Rd Tampa FL 33635",
    "addr:housenumber":"9108",
    "addr:postcode":"33635",
    "addr:street":"Blairmoor Rd",
    "iso:country":"US",
    "sg:address":"9108 Blairmoor Rd",
    "sg:city":"Tampa",
    "sg:classifiers":[
        {
            "category":"Building & Trades",
            "subcategory":"Construction",
            "type":"Services"
        }
    ],
    "sg:phone":"+1 813 889 8593",
    "sg:postcode":"33635",
    "sg:province":"FL",
    "sg:tags":[
        "house"
    ],
    "wof:name":"Larry E Stroup",
    "wof:placetype":"venue"
},
  "geometry": {"coordinates":[-82.59094899999999,28.028376],"type":"Point"}
}