{
  "type": "Feature",
  "properties": {
    "addr:full":"5701 Sunset Dr Ste 219 South Miami FL 33143",
    "addr:housenumber":"5701",
    "addr:postcode":"33143",
    "addr:street":"Sunset Dr Ste 219",
    "iso:country":"US",
    "sg:address":"5701 Sunset Dr Ste 219",
    "sg:city":"South Miami",
    "sg:classifiers":[
        {
            "category":"Shopping",
            "subcategory":"Optician",
            "type":"Retail Goods"
        }
    ],
    "sg:phone":"+1 305 667 7313",
    "sg:postcode":"33143",
    "sg:province":"FL",
    "sg:tags":[
        "eyewear"
    ],
    "wof:name":"Optical Elements Inc",
    "wof:placetype":"venue"
},
  "geometry": {"coordinates":[-80.2864,25.704399],"type":"Point"}
}