{
  "type": "Feature",
  "properties": {
    "addr:full":"11020 Peppertree Ln Port Richey FL 34668",
    "addr:housenumber":"11020",
    "addr:postcode":"34668",
    "addr:street":"Peppertree Ln",
    "iso:country":"US",
    "sg:address":"11020 Peppertree Ln",
    "sg:city":"Port Richey",
    "sg:classifiers":[
        {
            "category":"Wholesale",
            "subcategory":"Construction Materials",
            "type":"Manufacturing & Wholesale Goods"
        }
    ],
    "sg:phone":"+1 727 869 3685",
    "sg:postcode":"34668",
    "sg:province":"FL",
    "sg:tags":[
        "fence"
    ],
    "wof:name":"Extreme Fence",
    "wof:placetype":"venue"
},
  "geometry": {"coordinates":[-82.670429,28.317618],"type":"Point"}
}