{
  "type": "Feature",
  "properties": {
    "iso:country":"US",
    "sg:address":"3321 SW 58th St",
    "sg:city":"Fort Lauderdale",
    "sg:classifiers":[
        {
            "category":"Health Services",
            "subcategory":"Doctor",
            "type":"Services"
        }
    ],
    "sg:phone":"+1 954 961 8254",
    "sg:postcode":"33312",
    "sg:province":"FL",
    "sg:tags":[
        "medical"
    ],
    "wof:name":"Eisenberg Family Partnership",
    "wof:placetype":"venue"
},
  "geometry": {"coordinates":[-80.189927,26.049763],"type":"Point"}
}