{
  "type": "Feature",
  "properties": {
    "addr:full":"10710 SW 211th St Miami FL 33189",
    "addr:housenumber":"10710",
    "addr:postcode":"33189",
    "addr:street":"Sw 211Th St",
    "iso:country":"US",
    "sg:address":"10710 SW 211th St",
    "sg:city":"Miami",
    "sg:classifiers":[
        {
            "category":"Government",
            "subcategory":"Court House",
            "type":"Public Place"
        }
    ],
    "sg:phone":"+1 305 252 5848",
    "sg:postcode":"33189",
    "sg:province":"FL",
    "sg:tags":[
        "county"
    ],
    "wof:name":"Dade County Judge",
    "wof:placetype":"venue"
},
  "geometry": {"coordinates":[-80.364127,25.572664],"type":"Point"}
}