{
  "type": "Feature",
  "properties": {
    "iso:country":"US",
    "sg:address":"7795 W Flagler St",
    "sg:city":"Miami",
    "sg:classifiers":[
        {
            "category":"Shopping",
            "subcategory":"Clothing, Apparel, & Fashions",
            "type":"Retail Goods"
        },
        {
            "category":"Shopping",
            "subcategory":"Baby Store",
            "type":"Retail Goods"
        },
        {
            "category":"Shopping",
            "subcategory":"Used Merchandise",
            "type":"Retail Goods"
        }
    ],
    "sg:phone":"+1 305 269 0809",
    "sg:postcode":"33144",
    "sg:province":"FL",
    "sg:tags":[
        "infant",
        "vintage",
        "men's",
        "women's",
        "children's",
        "consignment",
        "wear",
        "apparel",
        "maternity",
        "girls'",
        "clothing",
        "boys'",
        "clothes"
    ],
    "sg:website":"www.oldnavy.com",
    "wof:name":"Old Navy",
    "wof:placetype":"venue"
},
  "geometry": {"coordinates":[-80.324203,25.769899],"type":"Point"}
}