{
  "type": "Feature",
  "properties": {
    "iso:country":"US",
    "sg:address":"101 Ipswich St",
    "sg:city":"Boca Raton",
    "sg:classifiers":[
        {
            "category":"Organizations",
            "subcategory":"Religious Organization",
            "type":"Services"
        }
    ],
    "sg:phone":"+1 561 997 7944",
    "sg:postcode":"33487",
    "sg:province":"FL",
    "sg:tags":[
        "church"
    ],
    "wof:name":"God's Place",
    "wof:placetype":"venue"
},
  "geometry": {"coordinates":[-80.076722,26.40292],"type":"Point"}
}