{
  "type": "Feature",
  "properties": {
    "iso:country":"US",
    "sg:address":"1950 Palm Beach Trace Dr",
    "sg:city":"West Palm Beach",
    "sg:classifiers":[
        {
            "category":"Banks & Credit Unions",
            "subcategory":"Bank",
            "type":"Services"
        }
    ],
    "sg:phone":"+1 561 683 9300",
    "sg:postcode":"33411",
    "sg:province":"FL",
    "wof:name":"Wachovia Bank",
    "wof:placetype":"venue"
},
  "geometry": {"coordinates":[-80.22630700000001,26.713005],"type":"Point"}
}