{
  "type": "Feature",
  "properties": {
    "addr:full":"6219 Compass Ln Tampa FL 33611",
    "addr:housenumber":"6219",
    "addr:postcode":"33611",
    "addr:street":"Compass Ln",
    "iso:country":"US",
    "sg:address":"6219 Compass Ln",
    "sg:city":"Tampa",
    "sg:classifiers":[
        {
            "category":"Building & Trades",
            "subcategory":"Construction",
            "type":"Services"
        }
    ],
    "sg:phone":"+1 813 831 1652",
    "sg:postcode":"33611",
    "sg:province":"FL",
    "sg:tags":[
        "contractor"
    ],
    "wof:name":"Bradshaw Pool Service",
    "wof:placetype":"venue"
},
  "geometry": {"coordinates":[-82.502752,27.877395],"type":"Point"}
}