{
  "type": "Feature",
  "properties": {
    "iso:country":"US",
    "sg:address":"7340 225th St E",
    "sg:city":"Bradenton",
    "sg:classifiers":[
        {
            "category":"Manufacturing",
            "subcategory":"Tools & Machinery",
            "type":"Manufacturing & Wholesale Goods"
        }
    ],
    "sg:phone":"+1 941 322 1461",
    "sg:postcode":"34211",
    "sg:province":"FL",
    "sg:tags":[
        "electrical",
        "mfg"
    ],
    "wof:name":"C&D Engineering",
    "wof:placetype":"venue"
},
  "geometry": {"coordinates":[-82.310878,27.45723],"type":"Point"}
}