{
  "type": "Feature",
  "properties": {
    "iso:country":"US",
    "sg:address":"13525 SW 288th St",
    "sg:city":"Homestead",
    "sg:classifiers":[
        {
            "category":"Building & Trades",
            "subcategory":"Construction",
            "type":"Services"
        }
    ],
    "sg:phone":"+1 305 246 4306",
    "sg:postcode":"33033",
    "sg:province":"FL",
    "sg:tags":[
        "concrete",
        "contractor"
    ],
    "wof:name":"Diversified Cnstr Restoration",
    "wof:placetype":"venue"
},
  "geometry": {"coordinates":[-80.411725,25.499679],"type":"Point"}
}