{
  "type": "Feature",
  "properties": {
    "iso:country":"US",
    "sg:address":"11177 SW 8th St",
    "sg:city":"Pembroke Pines",
    "sg:classifiers":[
        {
            "category":"Wholesale",
            "subcategory":"Machinery & Supplies",
            "type":"Manufacturing & Wholesale Goods"
        }
    ],
    "sg:phone":"+1 954 704 3407",
    "sg:postcode":"33025",
    "sg:province":"FL",
    "sg:tags":[
        "equipment",
        "safety",
        "clothing"
    ],
    "wof:name":"Ami USA Corp",
    "wof:placetype":"venue"
},
  "geometry": {"coordinates":[-80.294661,26.000885],"type":"Point"}
}