{
  "type": "Feature",
  "properties": {
    "iso:country":"US",
    "sg:address":"601 del Prado Blvd N",
    "sg:city":"Cape Coral",
    "sg:classifiers":[
        {
            "category":"Real Estate",
            "subcategory":"Real Estate Agent",
            "type":"Services"
        }
    ],
    "sg:phone":"+1 239 242 2250",
    "sg:postcode":"33909",
    "sg:province":"FL",
    "wof:name":"Currier Cheetah FE",
    "wof:placetype":"venue"
},
  "geometry": {"coordinates":[-81.940989,26.663964],"type":"Point"}
}