{
  "type": "Feature",
  "properties": {
    "addr:full":"2350 NW 94th Ave Coral Springs FL 33065",
    "addr:housenumber":"2350",
    "addr:postcode":"33065",
    "addr:street":"Nw 94Th Ave",
    "iso:country":"US",
    "sg:address":"2350 NW 94th Ave",
    "sg:city":"Coral Springs",
    "sg:classifiers":[
        {
            "category":"Shopping",
            "subcategory":"Computers & Home Electronics",
            "type":"Retail Goods"
        }
    ],
    "sg:phone":"+1 954 340 7402",
    "sg:postcode":"33065",
    "sg:province":"FL",
    "sg:tags":[
        "software"
    ],
    "wof:name":"Stansfield Group Corp",
    "wof:placetype":"venue"
},
  "geometry": {"coordinates":[-80.251739,26.261708],"type":"Point"}
}