{
  "type": "Feature",
  "properties": {
    "iso:country":"US",
    "sg:address":"7035 W Cam Real",
    "sg:city":"Boca Raton",
    "sg:classifiers":[
        {
            "category":"Autos & Motor Vehicles",
            "subcategory":"Fuel & Gas Station",
            "type":"Retail Goods"
        }
    ],
    "sg:phone":"+1 561 392 2700",
    "sg:postcode":"33433",
    "sg:province":"FL",
    "sg:tags":[
        "oil"
    ],
    "wof:name":"Boca Raton Chevron",
    "wof:placetype":"venue"
},
  "geometry": {"coordinates":[-80.154442,26.343935],"type":"Point"}
}