{
  "type": "Feature",
  "properties": {
    "iso:country":"US",
    "sg:address":"4302 Gator Trace Dr",
    "sg:city":"Fort Pierce",
    "sg:classifiers":[
        {
            "category":"Sports & Exercise",
            "subcategory":"Golf",
            "type":"Entertainment"
        }
    ],
    "sg:phone":"+1 772 464 7442",
    "sg:postcode":"34982",
    "sg:province":"FL",
    "sg:tags":[
        "course"
    ],
    "wof:name":"Gator Trace Golf & Country Clb",
    "wof:placetype":"venue"
},
  "geometry": {"coordinates":[-80.31720799999999,27.3848],"type":"Point"}
}