{
  "type": "Feature",
  "properties": {
    "iso:country":"US",
    "sg:address":"5450 W Hillsboro Blvd",
    "sg:city":"Coconut Creek",
    "sg:classifiers":[
        {
            "category":"Health Services",
            "subcategory":"Health Practitioner",
            "type":"Services"
        }
    ],
    "sg:phone":"+1 954 725 9125",
    "sg:postcode":"33073",
    "sg:province":"FL",
    "sg:tags":[
        "therapist",
        "physical"
    ],
    "wof:name":"Therapuetic Resources Inc",
    "wof:placetype":"venue"
},
  "geometry": {"coordinates":[-80.19671700000001,26.317621],"type":"Point"}
}