{
  "type": "Feature",
  "properties": {
    "iso:country":"US",
    "sg:address":"834 Verona Lake Dr",
    "sg:city":"Weston",
    "sg:classifiers":[
        {
            "category":"Health Services",
            "subcategory":"Chiropractor",
            "type":"Services"
        }
    ],
    "sg:phone":"+1 954 486 0566",
    "sg:postcode":"33326",
    "sg:province":"FL",
    "wof:name":"Chiropractic Powerline",
    "wof:placetype":"venue"
},
  "geometry": {"coordinates":[-80.387165,26.129133],"type":"Point"}
}