{
  "type": "Feature",
  "properties": {
    "addr:full":"2904 Nassau St Sarasota FL 34231",
    "addr:housenumber":"2904",
    "addr:postcode":"34231",
    "addr:street":"Nassau St",
    "iso:country":"US",
    "sg:address":"2904 Nassau St",
    "sg:city":"Sarasota",
    "sg:classifiers":[
        {
            "category":"Health Services",
            "subcategory":"Medical Lab",
            "type":"Services"
        }
    ],
    "sg:phone":"+1 941 925 0688",
    "sg:postcode":"34231",
    "sg:province":"FL",
    "sg:tags":[
        "laboratory",
        "dental"
    ],
    "wof:name":"Precision Cast Partials",
    "wof:placetype":"venue"
},
  "geometry": {"coordinates":[-82.513069,27.289186],"type":"Point"}
}