{
  "type": "Feature",
  "properties": {
    "iso:country":"US",
    "sg:address":"1028 NW 124th Ter",
    "sg:city":"Fort Lauderdale",
    "sg:classifiers":[
        {
            "category":"Restaurant",
            "type":"Food & Drink"
        }
    ],
    "sg:phone":"+1 954 846 8788",
    "sg:postcode":"33323",
    "sg:province":"FL",
    "sg:tags":[
        "eating"
    ],
    "wof:name":"Venture Cafe Inc",
    "wof:placetype":"venue"
},
  "geometry": {"coordinates":[-80.31494000000001,26.132513],"type":"Point"}
}