{
  "type": "Feature",
  "properties": {
    "addr:full":"3949 Palm Beach Point Blvd West Palm Beach FL 33414",
    "addr:housenumber":"3949",
    "addr:postcode":"33414",
    "addr:street":"Palm Beach Point Blvd",
    "iso:country":"US",
    "sg:address":"3949 Palm Beach Point Blvd",
    "sg:city":"West Palm Beach",
    "sg:classifiers":[
        {
            "category":"Wholesale",
            "subcategory":"Construction Materials",
            "type":"Manufacturing & Wholesale Goods"
        }
    ],
    "sg:phone":"+1 561 753 6102",
    "sg:postcode":"33414",
    "sg:province":"FL",
    "sg:tags":[
        "building",
        "granite",
        "stone"
    ],
    "wof:name":"Granit Unlimited Inc",
    "wof:placetype":"venue"
},
  "geometry": {"coordinates":[-80.29527299999999,26.624883],"type":"Point"}
}