{
  "type": "Feature",
  "properties": {
    "addr:full":"1074 E Venice Ave Venice FL 34285",
    "addr:housenumber":"1074",
    "addr:postcode":"34285",
    "addr:street":"E Venice Ave",
    "iso:country":"US",
    "sg:address":"1074 E Venice Ave",
    "sg:city":"Venice",
    "sg:classifiers":[
        {
            "category":"Health Services",
            "subcategory":"Doctor",
            "type":"Services"
        }
    ],
    "sg:phone":"+1 941 488 5366",
    "sg:postcode":"34285",
    "sg:province":"FL",
    "sg:tags":[
        "medical"
    ],
    "wof:name":"Intervential Pain Medicine",
    "wof:placetype":"venue"
},
  "geometry": {"coordinates":[-82.425341,27.099659],"type":"Point"}
}