{
  "type": "Feature",
  "properties": {
    "addr:full":"440 4th Pl SW Vero Beach FL 32962",
    "addr:housenumber":"440",
    "addr:postcode":"32962",
    "addr:street":"4Th Pl Sw",
    "iso:country":"US",
    "sg:address":"440 4th Pl SW",
    "sg:city":"Vero Beach",
    "sg:classifiers":[
        {
            "category":"Home & Garden",
            "subcategory":"Furniture",
            "type":"Retail Goods"
        }
    ],
    "sg:phone":"+1 772 770 3334",
    "sg:postcode":"32962",
    "sg:province":"FL",
    "sg:tags":[
        "cabinet"
    ],
    "wof:name":"Creative Cabinets & Designs",
    "wof:placetype":"venue"
},
  "geometry": {"coordinates":[-80.382775,27.594875],"type":"Point"}
}