{
  "type": "Feature",
  "properties": {
    "addr:full":"18917 Crescent Rd Odessa FL 33556",
    "addr:housenumber":"18917",
    "addr:postcode":"33556",
    "addr:street":"Crescent Rd",
    "iso:country":"US",
    "sg:address":"18917 Crescent Rd",
    "sg:city":"Odessa",
    "sg:classifiers":[
        {
            "category":"Retail",
            "subcategory":"Auto Repair",
            "type":"Services"
        }
    ],
    "sg:phone":"+1 813 932 9097",
    "sg:postcode":"33556",
    "sg:province":"FL",
    "sg:tags":[
        "equipment",
        "steering",
        "system"
    ],
    "wof:name":"Tampa Steering Columns Repair",
    "wof:placetype":"venue"
},
  "geometry": {"coordinates":[-82.58763399999999,28.151331],"type":"Point"}
}