{
  "type": "Feature",
  "properties": {
    "addr:full":"16241 Epsom Dr E Loxahatchee FL 33470",
    "addr:housenumber":"16241",
    "addr:postcode":"33470",
    "addr:street":"Epsom Dr E",
    "iso:country":"US",
    "sg:address":"16241 Epsom Dr E",
    "sg:city":"Loxahatchee",
    "sg:classifiers":[
        {
            "category":"Wholesale",
            "subcategory":"Non-durable Goods",
            "type":"Manufacturing & Wholesale Goods"
        }
    ],
    "sg:phone":"+1 561 798 9123",
    "sg:postcode":"33470",
    "sg:province":"FL",
    "wof:name":"Popular Distributors Inc",
    "wof:placetype":"venue"
},
  "geometry": {"coordinates":[-80.30582,26.697527],"type":"Point"}
}