{
  "type": "Feature",
  "properties": {
    "addr:full":"130 Bomar Ct Longwood FL 32750",
    "addr:housenumber":"130",
    "addr:postcode":"32750",
    "addr:street":"Bomar Ct",
    "iso:country":"US",
    "sg:address":"130 Bomar Ct",
    "sg:city":"Longwood",
    "sg:classifiers":[
        {
            "category":"Building & Trades",
            "subcategory":"Construction",
            "type":"Services"
        }
    ],
    "sg:phone":"+1 407 788 8536",
    "sg:postcode":"32750",
    "sg:province":"FL",
    "sg:tags":[
        "insulation",
        "heat",
        "contractor"
    ],
    "wof:name":"Insealators Of Orlando LLC",
    "wof:placetype":"venue"
},
  "geometry": {"coordinates":[-81.32847599999999,28.706333],"type":"Point"}
}