{
  "type": "Feature",
  "properties": {
    "addr:full":"1880 Old Dixie Hwy Vero Beach FL 32960",
    "addr:housenumber":"1880",
    "addr:postcode":"32960",
    "addr:street":"Old Dixie Hwy",
    "iso:country":"US",
    "sg:address":"1880 Old Dixie Hwy",
    "sg:city":"Vero Beach",
    "sg:phone":"+1 772 299 4390",
    "sg:postcode":"32960",
    "sg:province":"FL",
    "sg:tags":[
        "equipment",
        "commercial"
    ],
    "wof:name":"Innovative Concept",
    "wof:placetype":"venue"
},
  "geometry": {"coordinates":[-80.397994,27.635482],"type":"Point"}
}