{
  "type": "Feature",
  "properties": {
    "iso:country":"US",
    "sg:address":"791 SE 1st Ave",
    "sg:city":"South Bay",
    "sg:classifiers":[
        {
            "category":"Recreation",
            "type":"Entertainment"
        }
    ],
    "sg:phone":"+1 561 996 1155",
    "sg:postcode":"33493",
    "sg:province":"FL",
    "sg:tags":[
        "parks"
    ],
    "wof:name":"Tanner Park",
    "wof:placetype":"venue"
},
  "geometry": {"coordinates":[-80.71177,26.657741],"type":"Point"}
}