{
  "type": "Feature",
  "properties": {
    "addr:full":"2212 2nd St NW Winter Haven FL 33881",
    "addr:housenumber":"2212",
    "addr:postcode":"33881",
    "addr:street":"2Nd St Nw",
    "iso:country":"US",
    "sg:address":"2212 2nd St NW",
    "sg:city":"Winter Haven",
    "sg:classifiers":[
        {
            "category":"Building & Trades",
            "subcategory":"Construction",
            "type":"Services"
        }
    ],
    "sg:phone":"+1 863 293 1911",
    "sg:postcode":"33881",
    "sg:province":"FL",
    "sg:tags":[
        "concrete",
        "contractor"
    ],
    "wof:name":"Bennett Brothers",
    "wof:placetype":"venue"
},
  "geometry": {"coordinates":[-81.72832200000001,28.046689],"type":"Point"}
}