{
  "type": "Feature",
  "properties": {
    "iso:country":"US",
    "sg:address":"17735 SW 27th Ct",
    "sg:city":"Hollywood",
    "sg:classifiers":[
        {
            "category":"Wholesale",
            "subcategory":"Electrical",
            "type":"Manufacturing & Wholesale Goods"
        }
    ],
    "sg:phone":"+1 954 432 3672",
    "sg:postcode":"33029",
    "sg:province":"FL",
    "sg:tags":[
        "electronic"
    ],
    "wof:name":"Drummer Boy Sound Productions",
    "wof:placetype":"venue"
},
  "geometry": {"coordinates":[-80.386216,25.985422],"type":"Point"}
}