{
  "type": "Feature",
  "properties": {
    "iso:country":"US",
    "sg:address":"3500 NW Boca Raton Blvd",
    "sg:city":"Boca Raton",
    "sg:classifiers":[
        {
            "category":"Shopping",
            "type":"Retail Goods"
        }
    ],
    "sg:phone":"+1 561 395 7211",
    "sg:postcode":"33431",
    "sg:province":"FL",
    "sg:tags":[
        "art",
        "gallery",
        "dealer"
    ],
    "wof:name":"Ksg Graphics Corp",
    "wof:placetype":"venue"
},
  "geometry": {"coordinates":[-80.08502799999999,26.386098],"type":"Point"}
}