{
  "type": "Feature",
  "properties": {
    "addr:full":"10535 SW 109th Ct Miami FL 33176",
    "addr:housenumber":"10535",
    "addr:postcode":"33176",
    "addr:street":"Sw 109Th Ct",
    "iso:country":"US",
    "sg:address":"10535 SW 109th Ct",
    "sg:city":"Miami",
    "sg:classifiers":[
        {
            "category":"Real Estate",
            "subcategory":"Real Estate Operator",
            "type":"Services"
        }
    ],
    "sg:phone":"+1 305 233 5917",
    "sg:postcode":"33176",
    "sg:province":"FL",
    "sg:tags":[
        "apartment"
    ],
    "wof:name":"D & I Bests Rentals Inc",
    "wof:placetype":"venue"
},
  "geometry": {"coordinates":[-80.373062,25.671448],"type":"Point"}
}