{
  "type": "Feature",
  "properties": {
    "iso:country":"US",
    "sg:address":"10370 Pocket Ln",
    "sg:city":"Orlando",
    "sg:classifiers":[
        {
            "category":"Real Estate",
            "subcategory":"Real Estate Agent",
            "type":"Services"
        }
    ],
    "sg:phone":"+1 407 876 4294",
    "sg:postcode":"32836",
    "sg:province":"FL",
    "sg:tags":[
        "appraiser"
    ],
    "wof:name":"Residential Valuation Service",
    "wof:placetype":"venue"
},
  "geometry": {"coordinates":[-81.514428,28.416094],"type":"Point"}
}