{
  "type": "Feature",
  "properties": {
    "iso:country":"US",
    "sg:address":"605 Coconut Palm Rd",
    "sg:city":"Vero Beach",
    "sg:classifiers":[
        {
            "category":"Professional",
            "type":"Services"
        }
    ],
    "sg:phone":"+1 772 231 9227",
    "sg:postcode":"32963",
    "sg:province":"FL",
    "wof:name":"Marjorie Penny Inc",
    "wof:placetype":"venue"
},
  "geometry": {"coordinates":[-80.378691,27.693027],"type":"Point"}
}