{
  "type": "Feature",
  "properties": {
    "addr:full":"10255 NW 116th Way Medley FL 33178",
    "addr:housenumber":"10255",
    "addr:postcode":"33178",
    "addr:street":"Nw 116Th Way",
    "iso:country":"US",
    "sg:address":"10255 NW 116th Way",
    "sg:city":"Medley",
    "sg:classifiers":[
        {
            "category":"Freight",
            "type":"Transportation"
        },
        {
            "category":"Wholesale",
            "subcategory":"Durable Goods & Equipment",
            "type":"Manufacturing & Wholesale Goods"
        }
    ],
    "sg:phone":"+1 305 591 3900",
    "sg:postcode":"33178",
    "sg:province":"FL",
    "sg:tags":[
        "cargo",
        "importer",
        "commercial",
        "transport"
    ],
    "sg:website":"www.shipco.com",
    "wof:name":"Shipco Transport Inc",
    "wof:placetype":"venue"
},
  "geometry": {"coordinates":[-80.36299,25.871842],"type":"Point"}
}