{
  "type": "Feature",
  "properties": {
    "iso:country":"US",
    "sg:address":"600 E Donegan Ave",
    "sg:city":"Kissimmee",
    "sg:classifiers":[
        {
            "category":"Freight",
            "type":"Transportation"
        }
    ],
    "sg:phone":"+1 407 846 8551",
    "sg:postcode":"34744",
    "sg:province":"FL",
    "sg:tags":[
        "general"
    ],
    "wof:name":"Attic",
    "wof:placetype":"venue"
},
  "geometry": {"coordinates":[-81.39770300000001,28.318928],"type":"Point"}
}