{
  "type": "Feature",
  "properties": {
    "addr:full":"16419 US Hwy 301 Dade City FL 33523",
    "addr:housenumber":"16419",
    "addr:postcode":"33523",
    "addr:street":"Us Hwy 301",
    "iso:country":"US",
    "sg:address":"16419 US Hwy 301",
    "sg:city":"Dade City",
    "sg:classifiers":[
        {
            "category":"Retail",
            "subcategory":"Auto Repair",
            "type":"Services"
        }
    ],
    "sg:phone":"+1 352 567 1815",
    "sg:postcode":"33523",
    "sg:province":"FL",
    "sg:tags":[
        "repairing",
        "automobile"
    ],
    "wof:name":"Integrity Automotive Repair",
    "wof:placetype":"venue"
},
  "geometry": {"coordinates":[-82.19539399999999,28.39434],"type":"Point"}
}