{
  "type": "Feature",
  "properties": {
    "iso:country":"US",
    "sg:address":"400 Kings Point Dr",
    "sg:city":"Sunny Isles Beach",
    "sg:classifiers":[
        {
            "category":"Personal",
            "type":"Services"
        }
    ],
    "sg:phone":"+1 305 260 6203",
    "sg:postcode":"33160",
    "sg:province":"FL",
    "sg:tags":[
        "mover"
    ],
    "sg:website":"www.sunnyislesmovingservices.com",
    "wof:name":"Sunny Isles Moving Services",
    "wof:placetype":"venue"
},
  "geometry": {"coordinates":[-80.12739000000001,25.92364],"type":"Point"}
}