{
  "type": "Feature",
  "properties": {
    "iso:country":"US",
    "sg:address":"11540 Walsingham Rd",
    "sg:city":"Largo",
    "sg:classifiers":[
        {
            "category":"Retail",
            "subcategory":"Repair Shop",
            "type":"Services"
        }
    ],
    "sg:phone":"+1 727 399 8384",
    "sg:postcode":"33778",
    "sg:province":"FL",
    "sg:tags":[
        "appliance",
        "used",
        "electrical",
        "refrigeration"
    ],
    "wof:name":"Jerry S Major Appliance Svc",
    "wof:placetype":"venue"
},
  "geometry": {"coordinates":[-82.795547,27.88008],"type":"Point"}
}