{
  "type": "Feature",
  "properties": {
    "iso:country":"US",
    "sg:address":"6708 Deering Cir",
    "sg:city":"Sarasota",
    "sg:classifiers":[
        {
            "category":"Building & Trades",
            "subcategory":"Electrical",
            "type":"Services"
        }
    ],
    "sg:phone":"+1 941 378 4622",
    "sg:postcode":"34240",
    "sg:province":"FL",
    "sg:tags":[
        "electrical",
        "contractor"
    ],
    "wof:name":"Empty Nest Home Protection",
    "wof:placetype":"venue"
},
  "geometry": {"coordinates":[-82.437029,27.31394],"type":"Point"}
}