{
  "type": "Feature",
  "properties": {
    "iso:country":"US",
    "sg:address":"734 Legion Dr",
    "sg:city":"Destin",
    "sg:classifiers":[
        {
            "category":"Manufacturing",
            "subcategory":"Apparel",
            "type":"Manufacturing & Wholesale Goods"
        }
    ],
    "sg:phone":"+1 850 269 7743",
    "sg:postcode":"32541",
    "sg:province":"FL",
    "wof:name":"B & J Designs",
    "wof:placetype":"venue"
},
  "geometry": {"coordinates":[-86.483693,30.396977],"type":"Point"}
}