{
  "type": "Feature",
  "properties": {
    "addr:full":"4015 NW 79th Ave Doral FL 33166",
    "addr:housenumber":"4015",
    "addr:postcode":"33166",
    "addr:street":"Nw 79Th Ave",
    "iso:country":"US",
    "sg:address":"4015 NW 79th Ave",
    "sg:city":"Doral",
    "sg:classifiers":[
        {
            "category":"Home & Garden",
            "subcategory":"Building Materials",
            "type":"Retail Goods"
        }
    ],
    "sg:phone":"+1 305 418 1761",
    "sg:postcode":"33166",
    "sg:province":"FL",
    "sg:tags":[
        "glass",
        "window",
        "plate"
    ],
    "wof:name":"A & A Glass America",
    "wof:placetype":"venue"
},
  "geometry": {"coordinates":[-80.325287,25.811311],"type":"Point"}
}