{
  "type": "Feature",
  "properties": {
    "iso:country":"US",
    "sg:address":"6901 Edgewater Dr",
    "sg:city":"Miami",
    "sg:classifiers":[
        {
            "category":"Professional",
            "subcategory":"Art Services",
            "type":"Services"
        }
    ],
    "sg:phone":"+1 305 667 8188",
    "sg:postcode":"33133",
    "sg:province":"FL",
    "sg:tags":[
        "photography",
        "commercial"
    ],
    "wof:name":"Cole Derek Photographer",
    "wof:placetype":"venue"
},
  "geometry": {"coordinates":[-80.251786,25.706038],"type":"Point"}
}