{
  "type": "Feature",
  "properties": {
    "iso:country":"US",
    "sg:address":"52 Graham Ave",
    "sg:city":"Oviedo",
    "sg:classifiers":[
        {
            "category":"Personal",
            "subcategory":"Beauty Salon",
            "type":"Services"
        }
    ],
    "sg:phone":"+1 407 977 9773",
    "sg:postcode":"32765",
    "sg:province":"FL",
    "wof:name":"Edge Salon",
    "wof:placetype":"venue"
},
  "geometry": {"coordinates":[-81.209526,28.66966],"type":"Point"}
}