{
  "type": "Feature",
  "properties": {
    "addr:full":"2301 Tamiami Trl Nokomis FL 34275",
    "addr:housenumber":"2301",
    "addr:postcode":"34275",
    "addr:street":"Tamiami Trl",
    "iso:country":"US",
    "sg:address":"2301 Tamiami Trl",
    "sg:city":"Nokomis",
    "sg:classifiers":[
        {
            "category":"Banks & Credit Unions",
            "subcategory":"Investment Brokerage",
            "type":"Services"
        }
    ],
    "sg:phone":"+1 941 966 6200",
    "sg:postcode":"34275",
    "sg:province":"FL",
    "sg:tags":[
        "advisory",
        "financial"
    ],
    "wof:name":"Primerica",
    "wof:placetype":"venue"
},
  "geometry": {"coordinates":[-82.47153,27.1587],"type":"Point"}
}