{
  "type": "Feature",
  "properties": {
    "addr:full":"218 SW 46th Ter Cape Coral FL 33914",
    "addr:housenumber":"218",
    "addr:postcode":"33914",
    "addr:street":"Sw 46Th Ter",
    "iso:country":"US",
    "sg:address":"218 SW 46th Ter",
    "sg:city":"Cape Coral",
    "sg:classifiers":[
        {
            "category":"Shopping",
            "subcategory":"Computers & Home Electronics",
            "type":"Retail Goods"
        }
    ],
    "sg:phone":"+1 239 542 3234",
    "sg:postcode":"33914",
    "sg:province":"FL",
    "sg:tags":[
        "parts",
        "supply"
    ],
    "wof:name":"Lamb Computers",
    "wof:placetype":"venue"
},
  "geometry": {"coordinates":[-81.97871499999999,26.565604],"type":"Point"}
}