{
  "type": "Feature",
  "properties": {
    "iso:country":"US",
    "sg:address":"1075 Town Center Dr",
    "sg:city":"Orange City",
    "sg:classifiers":[
        {
            "category":"Health Services",
            "subcategory":"Doctor",
            "type":"Services"
        }
    ],
    "sg:phone":"+1 386 917 0333",
    "sg:postcode":"32763",
    "sg:province":"FL",
    "wof:name":"Pulmonary Practice Associates",
    "wof:placetype":"venue"
},
  "geometry": {"coordinates":[-81.28767499999999,28.906257],"type":"Point"}
}