{
  "type": "Feature",
  "properties": {
    "addr:full":"427 Geneva Dr Oviedo FL 32765",
    "addr:housenumber":"427",
    "addr:postcode":"32765",
    "addr:street":"Geneva Dr",
    "iso:country":"US",
    "sg:address":"427 Geneva Dr",
    "sg:city":"Oviedo",
    "sg:classifiers":[
        {
            "category":"Food & Beverages",
            "subcategory":"Groceries & Convenience Stores",
            "type":"Retail Goods"
        }
    ],
    "sg:phone":"+1 407 366 9343",
    "sg:postcode":"32765",
    "sg:province":"FL",
    "wof:name":"Geneva Food Mart Inc",
    "wof:placetype":"venue"
},
  "geometry": {"coordinates":[-81.200362,28.67667],"type":"Point"}
}