{
  "type": "Feature",
  "properties": {
    "iso:country":"US",
    "sg:address":"888 1st Ave N",
    "sg:city":"Naples",
    "sg:classifiers":[
        {
            "category":"Personal",
            "subcategory":"Beauty Salon",
            "type":"Services"
        }
    ],
    "sg:phone":"+1 239 403 8008",
    "sg:postcode":"34102",
    "sg:province":"FL",
    "wof:name":"Gemini Moon",
    "wof:placetype":"venue"
},
  "geometry": {"coordinates":[-81.796824,26.148271],"type":"Point"}
}