{
  "type": "Feature",
  "properties": {
    "addr:full":"4050 Tampa Rd Oldsmar FL 34677",
    "addr:housenumber":"4050",
    "addr:postcode":"34677",
    "addr:street":"Tampa Rd",
    "iso:country":"US",
    "sg:address":"4050 Tampa Rd",
    "sg:city":"Oldsmar",
    "sg:classifiers":[
        {
            "category":"Health Services",
            "subcategory":"Chiropractor",
            "type":"Services"
        }
    ],
    "sg:phone":"+1 813 818 7499",
    "sg:postcode":"34677",
    "sg:province":"FL",
    "wof:name":"Conforti Chiropractic & Wellne",
    "wof:placetype":"venue"
},
  "geometry": {"coordinates":[-82.654352,28.035653],"type":"Point"}
}