{
  "type": "Feature",
  "properties": {
    "addr:full":"6007 Walbridge St Orlando FL 32809",
    "addr:housenumber":"6007",
    "addr:postcode":"32809",
    "addr:street":"Walbridge St",
    "iso:country":"US",
    "sg:address":"6007 Walbridge St",
    "sg:city":"Orlando",
    "sg:classifiers":[
        {
            "category":"Professional",
            "subcategory":"Secretarial Services",
            "type":"Services"
        }
    ],
    "sg:phone":"+1 407 352 3304",
    "sg:postcode":"32809",
    "sg:province":"FL",
    "sg:tags":[
        "processing",
        "word"
    ],
    "wof:name":"LNRS Word Processing Svc",
    "wof:placetype":"venue"
},
  "geometry": {"coordinates":[-81.433978,28.470066],"type":"Point"}
}