{
  "type": "Feature",
  "properties": {
    "addr:full":"5819 US Hwy 19 New Port Richey FL 34652",
    "addr:housenumber":"5819",
    "addr:postcode":"34652",
    "addr:street":"Us Hwy 19",
    "iso:country":"US",
    "sg:address":"5819 US Hwy 19",
    "sg:city":"New Port Richey",
    "sg:classifiers":[
        {
            "category":"Autos & Motor Vehicles",
            "subcategory":"Automobile Sales",
            "type":"Retail Goods"
        }
    ],
    "sg:phone":"+1 727 815 9611",
    "sg:postcode":"34652",
    "sg:province":"FL",
    "sg:tags":[
        "car",
        "dealer"
    ],
    "wof:name":"Friendly KIA & Isuzu",
    "wof:placetype":"venue"
},
  "geometry": {"coordinates":[-82.72782100000001,28.242252],"type":"Point"}
}