{
  "type": "Feature",
  "properties": {
    "iso:country":"US",
    "sg:address":"2625 SW 75th St Apt 323",
    "sg:city":"Gainesville",
    "sg:classifiers":[
        {
            "category":"Home & Garden",
            "subcategory":"Carpets & Floor Coverings",
            "type":"Retail Goods"
        }
    ],
    "sg:phone":"+1 352 331 6157",
    "sg:postcode":"32608",
    "sg:province":"FL",
    "sg:tags":[
        "distributor",
        "rug",
        "manufacturer"
    ],
    "wof:name":"Pristine Clean Carpets Inc",
    "wof:placetype":"venue"
},
  "geometry": {"coordinates":[-82.422479,29.628727],"type":"Point"}
}