{
  "type": "Feature",
  "properties": {
    "iso:country":"US",
    "sg:address":"206 SE Villas St",
    "sg:city":"Stuart",
    "sg:classifiers":[
        {
            "category":"Building & Trades",
            "subcategory":"Construction",
            "type":"Services"
        }
    ],
    "sg:phone":"+1 772 463 0966",
    "sg:postcode":"34994",
    "sg:province":"FL",
    "sg:tags":[
        "house"
    ],
    "wof:name":"Sheppard Renovations Inc",
    "wof:placetype":"venue"
},
  "geometry": {"coordinates":[-80.25111800000001,27.187177],"type":"Point"}
}