{
  "type": "Feature",
  "properties": {
    "addr:full":"126 Lakeridge Dr Panama City FL 32405",
    "addr:housenumber":"126",
    "addr:postcode":"32405",
    "addr:street":"Lakeridge Dr",
    "iso:country":"US",
    "sg:address":"126 Lakeridge Dr",
    "sg:city":"Panama City",
    "sg:classifiers":[
        {
            "category":"Building & Trades",
            "subcategory":"Landscaping Services",
            "type":"Services"
        }
    ],
    "sg:phone":"+1 850 785 6534",
    "sg:postcode":"32405",
    "sg:province":"FL",
    "wof:name":"Landscaping Services",
    "wof:placetype":"venue"
},
  "geometry": {"coordinates":[-85.654307,30.211528],"type":"Point"}
}