{
  "type": "Feature",
  "properties": {
    "iso:country":"US",
    "sg:address":"19032 SW 113th Pl",
    "sg:city":"Miami",
    "sg:classifiers":[
        {
            "category":"Building & Trades",
            "subcategory":"Construction",
            "type":"Services"
        }
    ],
    "sg:phone":"+1 305 259 1656",
    "sg:postcode":"33157",
    "sg:province":"FL",
    "sg:tags":[
        "plastering",
        "contractor"
    ],
    "wof:name":"S & G Plastering Corp",
    "wof:placetype":"venue"
},
  "geometry": {"coordinates":[-80.37632000000001,25.590127],"type":"Point"}
}