{
  "type": "Feature",
  "properties": {
    "iso:country":"US",
    "sg:address":"340 Royal Poinciana Way",
    "sg:city":"Palm Beach",
    "sg:classifiers":[
        {
            "category":"Professional",
            "type":"Services"
        }
    ],
    "sg:phone":"+1 561 833 4211",
    "sg:postcode":"33480",
    "sg:province":"FL",
    "wof:name":"Pentacorp Inc",
    "wof:placetype":"venue"
},
  "geometry": {"coordinates":[-80.042129,26.718039],"type":"Point"}
}