{
  "type": "Feature",
  "properties": {
    "iso:country":"US",
    "sg:address":"160 NW 79th Ave",
    "sg:city":"Miami",
    "sg:classifiers":[
        {
            "category":"Autos & Motor Vehicles",
            "subcategory":"Automobile Sales",
            "type":"Retail Goods"
        }
    ],
    "sg:phone":"+1 305 751 3161",
    "sg:postcode":"33126",
    "sg:province":"FL",
    "sg:tags":[
        "car",
        "dealer"
    ],
    "wof:name":"Green Light Car Corp",
    "wof:placetype":"venue"
},
  "geometry": {"coordinates":[-80.324286,25.771242],"type":"Point"}
}