{
  "type": "Feature",
  "properties": {
    "addr:full":"14552 Global Cir Orlando FL 32821",
    "addr:postcode":"14552;32821",
    "addr:street":"Global Cir",
    "iso:country":"US",
    "sg:address":"14552 Global Cir",
    "sg:city":"Orlando",
    "sg:classifiers":[
        {
            "category":"Professional",
            "subcategory":"Management & Consulting",
            "type":"Services"
        }
    ],
    "sg:phone":"+1 407 238 2382",
    "sg:postcode":"32821",
    "sg:province":"FL",
    "wof:name":"Solstice Management Inc",
    "wof:placetype":"venue"
},
  "geometry": {"coordinates":[-81.50028500000001,28.351715],"type":"Point"}
}