{
  "type": "Feature",
  "properties": {
    "addr:full":"741 W 83rd St Hialeah FL 33014",
    "addr:housenumber":"741",
    "addr:postcode":"33014",
    "addr:street":"W 83Rd St",
    "iso:country":"US",
    "sg:address":"741 W 83rd St",
    "sg:city":"Hialeah",
    "sg:classifiers":[
        {
            "category":"Building & Trades",
            "subcategory":"Landscaping Services",
            "type":"Services"
        }
    ],
    "sg:phone":"+1 305 557 7799",
    "sg:postcode":"33014",
    "sg:province":"FL",
    "wof:name":"US Lawns of Miami",
    "wof:placetype":"venue"
},
  "geometry": {"coordinates":[-80.29942800000001,25.897988],"type":"Point"}
}