{
  "type": "Feature",
  "properties": {
    "iso:country":"US",
    "sg:address":"4430 Orchid Blvd",
    "sg:city":"Cape Coral",
    "sg:classifiers":[
        {
            "category":"Professional",
            "subcategory":"Accounting & Tax Preparation",
            "type":"Services"
        }
    ],
    "sg:phone":"+1 239 549 2140",
    "sg:postcode":"33904",
    "sg:province":"FL",
    "sg:tags":[
        "accountant"
    ],
    "wof:name":"Macy Stephen CPA PA",
    "wof:placetype":"venue"
},
  "geometry": {"coordinates":[-81.941399,26.5702],"type":"Point"}
}