{
  "type": "Feature",
  "properties": {
    "iso:country":"US",
    "sg:address":"811 S Lakeside Ave",
    "sg:city":"Lakeland",
    "sg:classifiers":[
        {
            "category":"Manufacturing",
            "subcategory":"Buildings",
            "type":"Manufacturing & Wholesale Goods"
        },
        {
            "category":"Social Services",
            "subcategory":"Retirement Home",
            "type":"Services"
        },
        {
            "category":"Building & Trades",
            "subcategory":"Construction",
            "type":"Services"
        }
    ],
    "sg:phone":"+1 863 802 3568",
    "sg:postcode":"33815",
    "sg:province":"FL",
    "sg:tags":[
        "builder",
        "convalescent",
        "nursing",
        "contractor"
    ],
    "wof:name":"Florida Presbyterian Homes",
    "wof:placetype":"venue"
},
  "geometry": {"coordinates":[-81.961197,28.034555],"type":"Point"}
}