{
  "type": "Feature",
  "properties": {
    "iso:country":"US",
    "sg:address":"1989 Dolphin Blvd S",
    "sg:city":"Gulfport",
    "sg:classifiers":[
        {
            "category":"Banks & Credit Unions",
            "subcategory":"Bank",
            "type":"Services"
        }
    ],
    "sg:phone":"+1 727 346 0100",
    "sg:postcode":"33707",
    "sg:province":"FL",
    "sg:tags":[
        "loan",
        "mortgage",
        "real estate"
    ],
    "sg:website":"www.kymcomortgage.com",
    "wof:name":"Kymco Mortgage Inc",
    "wof:placetype":"venue"
},
  "geometry": {"coordinates":[-82.726675,27.749664],"type":"Point"}
}