{
  "type": "Feature",
  "properties": {
    "addr:full":"2869 SW 69th Ct Miami FL 33155",
    "addr:housenumber":"2869",
    "addr:postcode":"33155",
    "addr:street":"Sw 69Th Ct",
    "iso:country":"US",
    "sg:address":"2869 SW 69th Ct",
    "sg:city":"Miami",
    "sg:classifiers":[
        {
            "category":"Building & Trades",
            "subcategory":"Construction",
            "type":"Services"
        }
    ],
    "sg:phone":"+1 305 266 2313",
    "sg:postcode":"33155",
    "sg:province":"FL",
    "sg:tags":[
        "contractor"
    ],
    "wof:name":"Halmac Development Inc",
    "wof:placetype":"venue"
},
  "geometry": {"coordinates":[-80.308368,25.743451],"type":"Point"}
}