{
  "type": "Feature",
  "properties": {
    "addr:full":"106 Pierce Ave Cape Canaveral FL 32920",
    "addr:housenumber":"106",
    "addr:postcode":"32920",
    "addr:street":"Pierce Ave",
    "iso:country":"US",
    "sg:address":"106 Pierce Ave",
    "sg:city":"Cape Canaveral",
    "sg:classifiers":[
        {
            "category":"Wholesale",
            "subcategory":"Electrical",
            "type":"Manufacturing & Wholesale Goods"
        }
    ],
    "sg:phone":"+1 321 783 9545",
    "sg:postcode":"32920",
    "sg:province":"FL",
    "sg:tags":[
        "equipment",
        "electronic",
        "supply"
    ],
    "wof:name":"Intercoastal Technologies",
    "wof:placetype":"venue"
},
  "geometry": {"coordinates":[-80.604265,28.382339],"type":"Point"}
}