{
  "type": "Feature",
  "properties": {
    "iso:country":"US",
    "sg:address":"35332 Johns Ln",
    "sg:city":"Eustis",
    "sg:classifiers":[
        {
            "category":"Building & Trades",
            "subcategory":"Construction",
            "type":"Services"
        }
    ],
    "sg:phone":"+1 352 516 0184",
    "sg:postcode":"32736",
    "sg:province":"FL",
    "sg:tags":[
        "land",
        "up",
        "clean"
    ],
    "wof:name":"Banks Ground Service Inc",
    "wof:placetype":"venue"
},
  "geometry": {"coordinates":[-81.51993400000001,28.872049],"type":"Point"}
}