{
  "type": "Feature",
  "properties": {
    "iso:country":"US",
    "sg:address":"421 N Reus St",
    "sg:city":"Pensacola",
    "sg:classifiers":[
        {
            "category":"Government",
            "subcategory":"Office",
            "type":"Public Place"
        }
    ],
    "sg:phone":"+1 850 433 2977",
    "sg:postcode":"32501",
    "sg:province":"FL",
    "sg:tags":[
        "county"
    ],
    "sg:website":"www.ecclt.com",
    "wof:name":"Escambia County Comm Land Trst",
    "wof:placetype":"venue"
},
  "geometry": {"coordinates":[-87.22179300000001,30.417419],"type":"Point"}
}