{
  "type": "Feature",
  "properties": {
    "iso:country":"US",
    "sg:address":"577 NW 135th Ter",
    "sg:city":"Fort Lauderdale",
    "sg:classifiers":[
        {
            "category":"Utilities",
            "subcategory":"Mobile Phone",
            "type":"Services"
        }
    ],
    "sg:phone":"+1 954 846 0473",
    "sg:postcode":"33325",
    "sg:province":"FL",
    "sg:tags":[
        "wireless",
        "telephone"
    ],
    "wof:name":"1a Wireless",
    "wof:placetype":"venue"
},
  "geometry": {"coordinates":[-80.329402,26.12792],"type":"Point"}
}