{
  "type": "Feature",
  "properties": {
    "iso:country":"US",
    "sg:address":"8542 Sunnydale Ln",
    "sg:city":"Lakeland",
    "sg:classifiers":[
        {
            "category":"Building & Trades",
            "subcategory":"Landscaping Services",
            "type":"Services"
        }
    ],
    "sg:phone":"+1 863 559 1920",
    "sg:postcode":"33809",
    "sg:province":"FL",
    "sg:tags":[
        "landscape",
        "contractor"
    ],
    "wof:name":"Decorative Concrete Landscape",
    "wof:placetype":"venue"
},
  "geometry": {"coordinates":[-81.96100300000001,28.156208],"type":"Point"}
}