{
  "type": "Feature",
  "properties": {
    "addr:full":"3435 E Colonial Dr Ste C-16 Orlando FL 32803",
    "addr:housenumber":"3435",
    "addr:postcode":"32803",
    "addr:street":"E Colonial Dr Ste C-16",
    "iso:country":"US",
    "sg:address":"3435 E Colonial Dr Ste C-16",
    "sg:city":"Orlando",
    "sg:classifiers":[
        {
            "category":"Shopping",
            "subcategory":"Shoes",
            "type":"Retail Goods"
        }
    ],
    "sg:phone":"+1 407 898 5737",
    "sg:postcode":"32803",
    "sg:province":"FL",
    "sg:tags":[
        "store"
    ],
    "sg:website":"http://www.journeyskidz.com/",
    "wof:name":"Journeys Kidz",
    "wof:placetype":"venue"
},
  "geometry": {"coordinates":[-81.340709,28.553459],"type":"Point"}
}