{
  "type": "Feature",
  "properties": {
    "iso:country":"US",
    "sg:address":"7518 Collins Ct",
    "sg:city":"Jacksonville",
    "sg:classifiers":[
        {
            "category":"Local Transit",
            "type":"Transportation"
        }
    ],
    "sg:phone":"+1 904 779 9847",
    "sg:postcode":"32244",
    "sg:province":"FL",
    "wof:name":"Peggy Dee Ward",
    "wof:placetype":"venue"
},
  "geometry": {"coordinates":[-81.791072,30.204953],"type":"Point"}
}