{
  "type": "Feature",
  "properties": {
    "addr:full":"2729 Briarpatch Dr Valrico FL 33596",
    "addr:housenumber":"2729",
    "addr:postcode":"33596",
    "addr:street":"Briarpatch Dr",
    "iso:country":"US",
    "sg:address":"2729 Briarpatch Dr",
    "sg:city":"Valrico",
    "sg:classifiers":[
        {
            "category":"Freight",
            "type":"Transportation"
        }
    ],
    "sg:phone":"+1 813 764 0055",
    "sg:postcode":"33596",
    "sg:province":"FL",
    "sg:tags":[
        "operator",
        "local",
        "trucking"
    ],
    "wof:name":"Home Sweet Home Moving & More",
    "wof:placetype":"venue"
},
  "geometry": {"coordinates":[-82.239025,27.906335],"type":"Point"}
}