{
  "type": "Feature",
  "properties": {
    "iso:country":"US",
    "sg:address":"3300 SW 46th Ave",
    "sg:city":"Fort Lauderdale",
    "sg:classifiers":[
        {
            "category":"Home & Garden",
            "subcategory":"Garden Supply",
            "type":"Retail Goods"
        }
    ],
    "sg:phone":"+1 954 584 3465",
    "sg:postcode":"33314",
    "sg:province":"FL",
    "wof:name":"Prestige Growers Inc",
    "wof:placetype":"venue"
},
  "geometry": {"coordinates":[-80.20777699999999,26.08095],"type":"Point"}
}