{
  "type": "Feature",
  "properties": {
    "addr:full":"3813 Ironwood Ct Sarasota FL 34243",
    "addr:housenumber":"3813",
    "addr:postcode":"34243",
    "addr:street":"Ironwood Ct",
    "iso:country":"US",
    "sg:address":"3813 Ironwood Ct",
    "sg:city":"Sarasota",
    "sg:classifiers":[
        {
            "category":"Professional",
            "type":"Services"
        }
    ],
    "sg:phone":"+1 941 351 8633",
    "sg:postcode":"34243",
    "sg:province":"FL",
    "sg:tags":[
        "establishment"
    ],
    "wof:name":"Scott Kuiken",
    "wof:placetype":"venue"
},
  "geometry": {"coordinates":[-82.491772,27.384457],"type":"Point"}
}