{
  "type": "Feature",
  "properties": {
    "iso:country":"US",
    "sg:address":"509 Finger Lakes Pl",
    "sg:city":"Seffner",
    "sg:classifiers":[
        {
            "category":"Building & Trades",
            "subcategory":"Landscaping Services",
            "type":"Services"
        }
    ],
    "sg:phone":"+1 813 982 1820",
    "sg:postcode":"33584",
    "sg:province":"FL",
    "sg:tags":[
        "landscape",
        "contractor"
    ],
    "sg:website":"http://www.landscapepros.org",
    "wof:name":"Landscape Pros Inc",
    "wof:placetype":"venue"
},
  "geometry": {"coordinates":[-82.26593699999999,28.002024],"type":"Point"}
}