{
  "type": "Feature",
  "properties": {
    "addr:full":"31 W Nine Mile Rd Pensacola FL 32534",
    "addr:housenumber":"31",
    "addr:postcode":"32534",
    "addr:street":"W Nine Mile Rd",
    "iso:country":"US",
    "sg:address":"31 W Nine Mile Rd",
    "sg:city":"Pensacola",
    "sg:classifiers":[
        {
            "category":"Restaurant",
            "type":"Food & Drink"
        }
    ],
    "sg:phone":"+1 850 476 2729",
    "sg:postcode":"32534",
    "sg:province":"FL",
    "sg:tags":[
        "seafood"
    ],
    "wof:name":"Myras Catfish Seafood In",
    "wof:placetype":"venue"
},
  "geometry": {"coordinates":[-87.27421,30.533125],"type":"Point"}
}