{
  "type": "Feature",
  "properties": {
    "iso:country":"US",
    "sg:address":"1719 Dewey Mgquire Rd",
    "sg:city":"Perry",
    "sg:classifiers":[
        {
            "category":"Recreation",
            "subcategory":"Marina",
            "type":"Entertainment"
        }
    ],
    "sg:phone":"+1 850 584 8484",
    "sg:postcode":"32348",
    "sg:province":"FL",
    "sg:tags":[
        "repairing",
        "boat"
    ],
    "wof:name":"Sportsmen's Repair",
    "wof:placetype":"venue"
},
  "geometry": {"coordinates":[-83.56661699999999,30.037013],"type":"Point"}
}