{
  "type": "Feature",
  "properties": {
    "addr:full":"5950 Beneva Rd Sarasota FL 34233",
    "addr:housenumber":"5950",
    "addr:postcode":"34233",
    "addr:street":"Beneva Rd",
    "iso:country":"US",
    "sg:address":"5950 Beneva Rd",
    "sg:city":"Sarasota",
    "sg:classifiers":[
        {
            "category":"Banks & Credit Unions",
            "subcategory":"Bank",
            "type":"Services"
        }
    ],
    "sg:phone":"+1 941 921 3968",
    "sg:postcode":"34233",
    "sg:province":"FL",
    "wof:name":"Riverside National Bank",
    "wof:placetype":"venue"
},
  "geometry": {"coordinates":[-82.49769000000001,27.267959],"type":"Point"}
}