{
  "type": "Feature",
  "properties": {
    "addr:full":"22 Salamanca Ave Miami FL 33134",
    "addr:housenumber":"22",
    "addr:postcode":"33134",
    "addr:street":"Salamanca Ave",
    "iso:country":"US",
    "sg:address":"22 Salamanca Ave",
    "sg:city":"Miami",
    "sg:classifiers":[
        {
            "category":"Wholesale",
            "subcategory":"Non-durable Goods",
            "type":"Manufacturing & Wholesale Goods"
        }
    ],
    "sg:phone":"+1 305 443 6057",
    "sg:postcode":"33134",
    "sg:province":"FL",
    "wof:name":"Meja Corp",
    "wof:placetype":"venue"
},
  "geometry": {"coordinates":[-80.256638,25.758987],"type":"Point"}
}