{
  "type": "Feature",
  "properties": {
    "iso:country":"US",
    "sg:address":"16541 NW 27th Ave",
    "sg:city":"Opa Locka",
    "sg:classifiers":[
        {
            "category":"Autos & Motor Vehicles",
            "subcategory":"Auto Supplies",
            "type":"Retail Goods"
        }
    ],
    "sg:phone":"+1 305 620 1992",
    "sg:postcode":"33054",
    "sg:province":"FL",
    "sg:tags":[
        "tire"
    ],
    "wof:name":"Clean Ride Tires",
    "wof:placetype":"venue"
},
  "geometry": {"coordinates":[-80.24433399999999,25.924851],"type":"Point"}
}