{
  "type": "Feature",
  "properties": {
    "iso:country":"US",
    "sg:address":"1605 State Hwy 37",
    "sg:city":"Mulberry",
    "sg:classifiers":[
        {
            "category":"Manufacturing",
            "subcategory":"Retail Goods",
            "type":"Manufacturing & Wholesale Goods"
        }
    ],
    "sg:phone":"+1 863 529 5330",
    "sg:postcode":"33860",
    "sg:province":"FL",
    "sg:tags":[
        "manufacturer"
    ],
    "wof:name":"Great American Ramp Step",
    "wof:placetype":"venue"
},
  "geometry": {"coordinates":[-81.973732,27.907896],"type":"Point"}
}