{
  "type": "Feature",
  "properties": {
    "addr:full":"1131 S Orange Ave Orlando FL 32806",
    "addr:housenumber":"1131",
    "addr:postcode":"32806",
    "addr:street":"S Orange Ave",
    "iso:country":"US",
    "sg:address":"1131 S Orange Ave",
    "sg:city":"Orlando",
    "sg:classifiers":[
        {
            "category":"Shopping",
            "type":"Retail Goods"
        }
    ],
    "sg:phone":"+1 407 999 8977",
    "sg:postcode":"32806",
    "sg:province":"FL",
    "sg:tags":[
        "prosthesis",
        "orthopedic",
        "prod"
    ],
    "wof:name":"ABC Prosthetics & Orthotics",
    "wof:placetype":"venue"
},
  "geometry": {"coordinates":[-81.376403,28.528768],"type":"Point"}
}