{
  "type": "Feature",
  "properties": {
    "iso:country":"US",
    "sg:address":"1232 Viscaya Pkwy",
    "sg:city":"Cape Coral",
    "sg:classifiers":[
        {
            "category":"Autos & Motor Vehicles",
            "subcategory":"Automobile Sales",
            "type":"Retail Goods"
        }
    ],
    "sg:phone":"+1 239 242 0113",
    "sg:postcode":"33990",
    "sg:province":"FL",
    "sg:tags":[
        "car",
        "dealer"
    ],
    "wof:name":"Jagger Motors Inc",
    "wof:placetype":"venue"
},
  "geometry": {"coordinates":[-81.948211,26.636037],"type":"Point"}
}