{
  "type": "Feature",
  "properties": {
    "iso:country":"US",
    "sg:address":"402 S Kentucky Ave",
    "sg:city":"Lakeland",
    "sg:classifiers":[
        {
            "category":"Organizations",
            "subcategory":"Membership Organization",
            "type":"Services"
        }
    ],
    "sg:phone":"+1 863 499 2385",
    "sg:postcode":"33801",
    "sg:province":"FL",
    "wof:name":"Divison of Blind Services",
    "wof:placetype":"venue"
},
  "geometry": {"coordinates":[-81.954994,28.039316],"type":"Point"}
}