{
  "type": "Feature",
  "properties": {
    "iso:country":"US",
    "sg:address":"2441 S Orange Ave",
    "sg:city":"Orlando",
    "sg:classifiers":[
        {
            "category":"Restaurant",
            "type":"Food & Drink"
        }
    ],
    "sg:phone":"+1 407 540 0208",
    "sg:postcode":"32806",
    "sg:province":"FL",
    "sg:tags":[
        "barbecue",
        "soul"
    ],
    "sg:website":"http://www.conwaysbbq.com",
    "wof:name":"Conway's BBQ",
    "wof:placetype":"venue"
},
  "geometry": {"coordinates":[-81.376367,28.515293],"type":"Point"}
}