{
  "type": "Feature",
  "properties": {
    "addr:full":"1402 Farrindon Cir Lake Mary FL 32746",
    "addr:housenumber":"1402",
    "addr:postcode":"32746",
    "addr:street":"Farrindon Cir",
    "iso:country":"US",
    "sg:address":"1402 Farrindon Cir",
    "sg:city":"Lake Mary",
    "sg:classifiers":[
        {
            "category":"Professional",
            "subcategory":"Management & Consulting",
            "type":"Services"
        }
    ],
    "sg:phone":"+1 407 882 0231",
    "sg:postcode":"32746",
    "sg:province":"FL",
    "sg:tags":[
        "consultant",
        "business"
    ],
    "wof:name":"R & E Mc Neil Inc",
    "wof:placetype":"venue"
},
  "geometry": {"coordinates":[-81.38084600000001,28.758201],"type":"Point"}
}