{
  "type": "Feature",
  "properties": {
    "iso:country":"US",
    "sg:address":"8415 E Fowler Ave",
    "sg:city":"Tampa",
    "sg:classifiers":[
        {
            "category":"Home & Garden",
            "subcategory":"Mobile Homes",
            "type":"Retail Goods"
        }
    ],
    "sg:phone":"+1 813 985 8820",
    "sg:postcode":"33592",
    "sg:province":"FL",
    "wof:name":"Park Place Manufactured Hsing",
    "wof:placetype":"venue"
},
  "geometry": {"coordinates":[-82.360688,28.05425],"type":"Point"}
}