{
  "type": "Feature",
  "properties": {
    "iso:country":"US",
    "sg:address":"705 10th Ave SW",
    "sg:city":"Vero Beach",
    "sg:classifiers":[
        {
            "category":"Food & Beverages",
            "subcategory":"Liquor & Beverages",
            "type":"Retail Goods"
        }
    ],
    "sg:phone":"+1 772 299 0001",
    "sg:postcode":"32962",
    "sg:province":"FL",
    "sg:tags":[
        "alcoholic"
    ],
    "wof:name":"Central County Liquors Inc",
    "wof:placetype":"venue"
},
  "geometry": {"coordinates":[-80.393817,27.59029],"type":"Point"}
}