{
  "type": "Feature",
  "properties": {
    "iso:country":"US",
    "sg:address":"7521 High Ridge Rd",
    "sg:city":"Boynton Beach",
    "sg:classifiers":[
        {
            "category":"Manufacturing",
            "subcategory":"Apparel",
            "type":"Manufacturing & Wholesale Goods"
        }
    ],
    "sg:phone":"+1 561 547 2458",
    "sg:postcode":"33426",
    "sg:province":"FL",
    "sg:tags":[
        "embroidery"
    ],
    "wof:name":"Embroidery Loft",
    "wof:placetype":"venue"
},
  "geometry": {"coordinates":[-80.074921,26.564766],"type":"Point"}
}