{
  "type": "Feature",
  "properties": {
    "iso:country":"US",
    "sg:address":"1519 SW 6th Ct",
    "sg:city":"Boca Raton",
    "sg:classifiers":[
        {
            "category":"Shopping",
            "subcategory":"Gifts & Souvenirs",
            "type":"Retail Goods"
        }
    ],
    "sg:phone":"+1 561 392 7838",
    "sg:postcode":"33486",
    "sg:province":"FL",
    "sg:tags":[
        "basket",
        "fruit"
    ],
    "sg:website":"www.flcitrusexpress.com",
    "wof:name":"Flcitrusexpress.Com Inc",
    "wof:placetype":"venue"
},
  "geometry": {"coordinates":[-80.098642,26.333112],"type":"Point"}
}