{
  "type": "Feature",
  "properties": {
    "addr:full":"4750 E 11th Ave Hialeah FL 33013",
    "addr:housenumber":"4750",
    "addr:postcode":"33013",
    "addr:street":"E 11Th Ave",
    "iso:country":"US",
    "sg:address":"4750 E 11th Ave",
    "sg:city":"Hialeah",
    "sg:classifiers":[
        {
            "category":"Wholesale",
            "subcategory":"Medical Equipment & Supplies",
            "type":"Manufacturing & Wholesale Goods"
        },
        {
            "category":"Shopping",
            "subcategory":"Pets & Pet Supplies",
            "type":"Retail Goods"
        },
        {
            "category":"Retail",
            "subcategory":"Veterinary Services",
            "type":"Services"
        }
    ],
    "sg:phone":"+1 305 681 4486",
    "sg:postcode":"33013",
    "sg:province":"FL",
    "sg:tags":[
        "product",
        "supply-wholesale",
        "health",
        "animal",
        "veterinarian",
        "store"
    ],
    "sg:website":"http://www.engler-engineering.com",
    "wof:name":"Vet-Sonic Inc",
    "wof:placetype":"venue"
},
  "geometry": {"coordinates":[-80.26058999999999,25.865979],"type":"Point"}
}