{
  "type": "Feature",
  "properties": {
    "iso:country":"US",
    "sg:address":"1297 Murray Dr",
    "sg:city":"Jacksonville",
    "sg:classifiers":[
        {
            "category":"Building & Trades",
            "subcategory":"Landscaping Services",
            "type":"Services"
        }
    ],
    "sg:phone":"+1 904 388 7207",
    "sg:postcode":"32205",
    "sg:province":"FL",
    "wof:name":"John Felker Lawn Services",
    "wof:placetype":"venue"
},
  "geometry": {"coordinates":[-81.726226,30.300646],"type":"Point"}
}