{
  "type": "Feature",
  "properties": {
    "addr:full":"27 Marie Cir Crawfordville FL 32327",
    "addr:housenumber":"27",
    "addr:postcode":"32327",
    "addr:street":"Marie Cir",
    "iso:country":"US",
    "sg:address":"27 Marie Cir",
    "sg:city":"Crawfordville",
    "sg:classifiers":[
        {
            "category":"Social Services",
            "type":"Services"
        }
    ],
    "sg:phone":"+1 850 926 6268",
    "sg:postcode":"32327",
    "sg:province":"FL",
    "wof:name":"New Hope Charities Inc",
    "wof:placetype":"venue"
},
  "geometry": {"coordinates":[-84.360107,30.186773],"type":"Point"}
}