{
  "type": "Feature",
  "properties": {
    "iso:country":"US",
    "sg:address":"735 S Beneva Rd",
    "sg:city":"Sarasota",
    "sg:classifiers":[
        {
            "category":"Home & Garden",
            "subcategory":"Garden Supply",
            "type":"Retail Goods"
        }
    ],
    "sg:phone":"+1 941 366 4954",
    "sg:postcode":"34232",
    "sg:province":"FL",
    "wof:name":"Farm & Garden Supply",
    "wof:placetype":"venue"
},
  "geometry": {"coordinates":[-82.497398,27.329009],"type":"Point"}
}