{
  "type": "Feature",
  "properties": {
    "addr:full":"4325 40th St W Bradenton FL 34205",
    "addr:housenumber":"4325",
    "addr:postcode":"34205",
    "addr:street":"40Th St W",
    "iso:country":"US",
    "sg:address":"4325 40th St W",
    "sg:city":"Bradenton",
    "sg:classifiers":[
        {
            "category":"Real Estate",
            "subcategory":"Real Estate Operator",
            "type":"Services"
        }
    ],
    "sg:phone":"+1 941 753 7353",
    "sg:postcode":"34205",
    "sg:province":"FL",
    "sg:tags":[
        "apartment"
    ],
    "wof:name":"Aaron Lake Apartments",
    "wof:placetype":"venue"
},
  "geometry": {"coordinates":[-82.60159299999999,27.463112],"type":"Point"}
}