{
  "type": "Feature",
  "properties": {
    "iso:country":"US",
    "sg:address":"6288 Lee Ann Ln",
    "sg:city":"Naples",
    "sg:classifiers":[
        {
            "category":"Retail",
            "subcategory":"Auto Repair",
            "type":"Services"
        }
    ],
    "sg:phone":"+1 239 566 1443",
    "sg:postcode":"34109",
    "sg:province":"FL",
    "sg:tags":[
        "repairing",
        "automobile",
        "general"
    ],
    "wof:name":"Sunset Auto Repair Inc",
    "wof:placetype":"venue"
},
  "geometry": {"coordinates":[-81.776977,26.219529],"type":"Point"}
}