{
  "type": "Feature",
  "properties": {
    "addr:full":"27 Oscar Hill Rd Tarpon Springs FL 34689",
    "addr:housenumber":"27",
    "addr:postcode":"34689",
    "addr:street":"Oscar Hill Rd",
    "iso:country":"US",
    "sg:address":"27 Oscar Hill Rd",
    "sg:city":"Tarpon Springs",
    "sg:classifiers":[
        {
            "category":"Recreation",
            "type":"Entertainment"
        }
    ],
    "sg:phone":"+1 727 934 5503",
    "sg:postcode":"34689",
    "sg:province":"FL",
    "sg:tags":[
        "charter",
        "yacht",
        "boat"
    ],
    "wof:name":"Seacoast Yacht Charters Inc",
    "wof:placetype":"venue"
},
  "geometry": {"coordinates":[-82.758898,28.159106],"type":"Point"}
}