{
  "type": "Feature",
  "properties": {
    "iso:country":"US",
    "sg:address":"505 Harbor Dr S",
    "sg:city":"Venice",
    "sg:classifiers":[
        {
            "category":"Home & Garden",
            "subcategory":"Building Materials",
            "type":"Retail Goods"
        }
    ],
    "sg:phone":"+1 941 922 8772",
    "sg:postcode":"34285",
    "sg:province":"FL",
    "sg:tags":[
        "glass",
        "window",
        "plate"
    ],
    "wof:name":"Mortenson Glass Co",
    "wof:placetype":"venue"
},
  "geometry": {"coordinates":[-82.45002599999999,27.090452],"type":"Point"}
}