{
  "type": "Feature",
  "properties": {
    "iso:country":"US",
    "sg:address":"228 E 4th St",
    "sg:city":"Panama City",
    "sg:classifiers":[
        {
            "category":"Professional",
            "subcategory":"Lawyer & Legal Services",
            "type":"Services"
        }
    ],
    "sg:phone":"+1 850 763 8466",
    "sg:postcode":"32401",
    "sg:province":"FL",
    "sg:tags":[
        "attorney"
    ],
    "wof:name":"Timothy C Campbell Law Offices",
    "wof:placetype":"venue"
},
  "geometry": {"coordinates":[-85.65871799999999,30.155151],"type":"Point"}
}