{
  "type": "Feature",
  "properties": {
    "iso:country":"US",
    "sg:address":"7630 SW 146th Ave",
    "sg:city":"Miami",
    "sg:classifiers":[
        {
            "category":"Professional",
            "type":"Services"
        }
    ],
    "sg:phone":"+1 305 386 5377",
    "sg:postcode":"33183",
    "sg:province":"FL",
    "wof:name":"Vicnel Inc",
    "wof:placetype":"venue"
},
  "geometry": {"coordinates":[-80.42908799999999,25.69552],"type":"Point"}
}