{
  "type": "Feature",
  "properties": {
    "addr:full":"10507 31st Ave E Palmetto FL 34221",
    "addr:housenumber":"10507",
    "addr:postcode":"34221",
    "addr:street":"31St Ave E",
    "iso:country":"US",
    "sg:address":"10507 31st Ave E",
    "sg:city":"Palmetto",
    "sg:classifiers":[
        {
            "category":"Farming",
            "subcategory":"Nursery",
            "type":"Manufacturing & Wholesale Goods"
        }
    ],
    "sg:phone":"+1 941 721 0900",
    "sg:postcode":"34221",
    "sg:province":"FL",
    "sg:tags":[
        "ornamental",
        "product"
    ],
    "wof:name":"T & B Turf Inc",
    "wof:placetype":"venue"
},
  "geometry": {"coordinates":[-82.532545,27.608752],"type":"Point"}
}