{
  "type": "Feature",
  "properties": {
    "addr:full":"35 Valdiva St Punta Gorda FL 33983",
    "addr:housenumber":"35",
    "addr:postcode":"33983",
    "addr:street":"Valdiva St",
    "iso:country":"US",
    "sg:address":"35 Valdiva St",
    "sg:city":"Punta Gorda",
    "sg:classifiers":[
        {
            "category":"Shopping",
            "type":"Retail Goods"
        }
    ],
    "sg:phone":"+1 941 629 9547",
    "sg:postcode":"33983",
    "sg:province":"FL",
    "sg:tags":[
        "miscellaneous",
        "store"
    ],
    "wof:name":"Baby Barrier Pool Fence Co",
    "wof:placetype":"venue"
},
  "geometry": {"coordinates":[-82.021343,27.030918],"type":"Point"}
}