{
  "type": "Feature",
  "properties": {
    "iso:country":"US",
    "sg:address":"22 Merrick Way",
    "sg:city":"Miami",
    "sg:classifiers":[
        {
            "category":"Restaurant",
            "type":"Food & Drink"
        }
    ],
    "sg:menulink":"http://www.allmenus.com/fl/miami/241516-house-of-india/menu/",
    "sg:phone":"+1 305 444 2348",
    "sg:postcode":"33134",
    "sg:province":"FL",
    "sg:tags":[
        "indian",
        "asian"
    ],
    "wof:name":"House Of India",
    "wof:placetype":"venue"
},
  "geometry": {"coordinates":[-80.25525500000001,25.750441],"type":"Point"}
}