{
  "type": "Feature",
  "properties": {
    "addr:full":"698 NW 51st St Boca Raton FL 33431",
    "addr:housenumber":"698",
    "addr:postcode":"33431",
    "addr:street":"Nw 51St St",
    "iso:country":"US",
    "sg:address":"698 NW 51st St",
    "sg:city":"Boca Raton",
    "sg:classifiers":[
        {
            "category":"Coffee & Tea",
            "type":"Food & Drink"
        }
    ],
    "sg:menulink":"http://www.allmenus.com/fl/boca-raton/117035-starbucks-coffee/menu/",
    "sg:phone":"+1 561 981 8312",
    "sg:postcode":"33431",
    "sg:province":"FL",
    "sg:tags":[
        "american"
    ],
    "wof:name":"Starbucks Coffee",
    "wof:placetype":"venue"
},
  "geometry": {"coordinates":[-80.098243,26.394232],"type":"Point"}
}