{
  "type": "Feature",
  "properties": {
    "iso:country":"US",
    "sg:address":"9240 SW 34th St",
    "sg:city":"Miami",
    "sg:classifiers":[
        {
            "category":"Shopping",
            "subcategory":"Jewelry",
            "type":"Retail Goods"
        },
        {
            "category":"Manufacturing",
            "subcategory":"Jewelry",
            "type":"Manufacturing & Wholesale Goods"
        },
        {
            "category":"Retail",
            "subcategory":"Repair Shop",
            "type":"Services"
        }
    ],
    "sg:phone":"+1 305 552 6223",
    "sg:postcode":"33165",
    "sg:province":"FL",
    "sg:tags":[
        "repairing",
        "jeweler",
        "designer",
        "clock"
    ],
    "wof:name":"D'alonso Jewelers Inc",
    "wof:placetype":"venue"
},
  "geometry": {"coordinates":[-80.344551,25.73834],"type":"Point"}
}