{
  "type": "Feature",
  "properties": {
    "addr:full":"14001 Perdido Key Dr Pensacola FL 32507",
    "addr:housenumber":"14001",
    "addr:postcode":"32507",
    "addr:street":"Perdido Key Dr",
    "iso:country":"US",
    "sg:address":"14001 Perdido Key Dr",
    "sg:city":"Pensacola",
    "sg:classifiers":[
        {
            "category":"Real Estate",
            "subcategory":"Real Estate Agent",
            "type":"Services"
        }
    ],
    "sg:phone":"+1 850 492 0165",
    "sg:postcode":"32507",
    "sg:province":"FL",
    "wof:name":"Perdido Key Abbott Realty Sls",
    "wof:placetype":"venue"
},
  "geometry": {"coordinates":[-87.427381,30.305593],"type":"Point"}
}