{
  "type": "Feature",
  "properties": {
    "addr:full":"531 Amber St Pensacola FL 32503",
    "addr:housenumber":"531",
    "addr:postcode":"32503",
    "addr:street":"Amber St",
    "iso:country":"US",
    "sg:address":"531 Amber St",
    "sg:city":"Pensacola",
    "sg:classifiers":[
        {
            "category":"Building & Trades",
            "subcategory":"Construction",
            "type":"Services"
        }
    ],
    "sg:phone":"+1 850 473 1071",
    "sg:postcode":"32503",
    "sg:province":"FL",
    "sg:tags":[
        "nonresidential"
    ],
    "wof:name":"Pattersons Construction",
    "wof:placetype":"venue"
},
  "geometry": {"coordinates":[-87.222689,30.470484],"type":"Point"}
}