{
  "type": "Feature",
  "properties": {
    "iso:country":"US",
    "sg:address":"950 Blanding Blvd",
    "sg:city":"Orange Park",
    "sg:classifiers":[
        {
            "category":"Shopping",
            "type":"Retail Goods"
        }
    ],
    "sg:phone":"+1 904 272 4045",
    "sg:postcode":"32065",
    "sg:province":"FL",
    "sg:tags":[
        "pet",
        "shop",
        "store"
    ],
    "wof:name":"Pet World",
    "wof:placetype":"venue"
},
  "geometry": {"coordinates":[-81.774845,30.137595],"type":"Point"}
}