{
  "type": "Feature",
  "properties": {
    "addr:full":"1209 3rd St S Naples FL 34102",
    "addr:housenumber":"1209",
    "addr:postcode":"34102",
    "addr:street":"3Rd St S",
    "iso:country":"US",
    "sg:address":"1209 3rd St S",
    "sg:city":"Naples",
    "sg:classifiers":[
        {
            "category":"Shopping",
            "subcategory":"Clothing, Apparel, & Fashions",
            "type":"Retail Goods"
        }
    ],
    "sg:phone":"+1 239 649 4454",
    "sg:postcode":"34102",
    "sg:province":"FL",
    "wof:name":"Leggiadro",
    "wof:placetype":"venue"
},
  "geometry": {"coordinates":[-81.801711,26.131056],"type":"Point"}
}