{
  "type": "Feature",
  "properties": {
    "addr:full":"18921 NE 2nd Ave Miami FL 33179",
    "addr:housenumber":"18921",
    "addr:postcode":"33179",
    "addr:street":"Ne 2Nd Ave",
    "iso:country":"US",
    "sg:address":"18921 NE 2nd Ave",
    "sg:city":"Miami",
    "sg:classifiers":[
        {
            "category":"Health Services",
            "subcategory":"Doctor",
            "type":"Services"
        }
    ],
    "sg:phone":"+1 305 652 7824",
    "sg:postcode":"33179",
    "sg:province":"FL",
    "wof:name":"Doctors Health Group of South Florida",
    "wof:placetype":"venue"
},
  "geometry": {"coordinates":[-80.197101,25.94843],"type":"Point"}
}