{
  "type": "Feature",
  "properties": {
    "iso:country":"US",
    "sg:address":"10175 SW Green Ridge Ln",
    "sg:city":"Palm City",
    "sg:classifiers":[
        {
            "category":"Building & Trades",
            "subcategory":"Pest Control",
            "type":"Services"
        }
    ],
    "sg:phone":"+1 772 287 9193",
    "sg:postcode":"34990",
    "sg:province":"FL",
    "wof:name":"Ambassador Pest Managemen",
    "wof:placetype":"venue"
},
  "geometry": {"coordinates":[-80.30898000000001,27.08289],"type":"Point"}
}