{
  "type": "Feature",
  "properties": {
    "iso:country":"US",
    "sg:address":"1400 E Robinson St",
    "sg:city":"Orlando",
    "sg:classifiers":[
        {
            "category":"Health Services",
            "subcategory":"Clinic",
            "type":"Services"
        },
        {
            "category":"Personal",
            "type":"Services"
        },
        {
            "category":"Health Services",
            "subcategory":"Health Practitioner",
            "type":"Services"
        },
        {
            "category":"Health Services",
            "subcategory":"Chiropractor",
            "type":"Services"
        }
    ],
    "sg:phone":"+1 407 896 6546",
    "sg:postcode":"32801",
    "sg:province":"FL",
    "sg:tags":[
        "control",
        "weight",
        "chiropractic",
        "consultant",
        "welfare",
        "program",
        "fitness"
    ],
    "sg:website":"http://www.hendersonchiroclinic.com",
    "wof:name":"Henderson Chiropractic Clinic PA",
    "wof:placetype":"venue"
},
  "geometry": {"coordinates":[-81.362267,28.54582],"type":"Point"}
}