{
  "type": "Feature",
  "properties": {
    "iso:country":"US",
    "sg:address":"23045 Preserve Ct",
    "sg:city":"Lutz",
    "sg:classifiers":[
        {
            "category":"Insurance",
            "subcategory":"Insurance Agent",
            "type":"Services"
        }
    ],
    "sg:phone":"+1 813 948 6327",
    "sg:postcode":"33549",
    "sg:province":"FL",
    "wof:name":"Health Insurance Processing",
    "wof:placetype":"venue"
},
  "geometry": {"coordinates":[-82.434771,28.177375],"type":"Point"}
}