{
  "type": "Feature",
  "properties": {
    "addr:full":"1910 N Flamingo Rd Pembroke Pines FL 33028",
    "addr:housenumber":"1910",
    "addr:postcode":"33028",
    "addr:street":"N Flamingo Rd",
    "iso:country":"US",
    "sg:address":"1910 N Flamingo Rd",
    "sg:city":"Pembroke Pines",
    "sg:classifiers":[
        {
            "category":"Shopping",
            "subcategory":"Crafts & Fabrics",
            "type":"Retail Goods"
        }
    ],
    "sg:phone":"+1 954 602 1926",
    "sg:postcode":"33028",
    "sg:province":"FL",
    "sg:tags":[
        "accessory",
        "costume",
        "trimmings"
    ],
    "wof:name":"Elias Fabrics",
    "wof:placetype":"venue"
},
  "geometry": {"coordinates":[-80.31254300000001,26.024416],"type":"Point"}
}