{
  "type": "Feature",
  "properties": {
    "addr:full":"501 N Federal Hwy Boynton Beach FL 33435",
    "addr:housenumber":"501",
    "addr:postcode":"33435",
    "addr:street":"N Federal Hwy",
    "iso:country":"US",
    "sg:address":"501 N Federal Hwy",
    "sg:city":"Boynton Beach",
    "sg:classifiers":[
        {
            "category":"Personal",
            "subcategory":"Beauty Salon",
            "type":"Services"
        }
    ],
    "sg:phone":"+1 561 752 8388",
    "sg:postcode":"33435",
    "sg:province":"FL",
    "sg:tags":[
        "shop"
    ],
    "wof:name":"Hermithe Booz",
    "wof:placetype":"venue"
},
  "geometry": {"coordinates":[-80.05815200000001,26.531536],"type":"Point"}
}