{
  "type": "Feature",
  "properties": {
    "iso:country":"US",
    "sg:address":"9021 Biscayne Blvd",
    "sg:city":"Miami Shores",
    "sg:classifiers":[
        {
            "category":"Restaurant",
            "type":"Food & Drink"
        }
    ],
    "sg:phone":"+1 305 758 1322",
    "sg:postcode":"33138",
    "sg:province":"FL",
    "sg:tags":[
        "eating"
    ],
    "wof:name":"Joy Yang Restaurant",
    "wof:placetype":"venue"
},
  "geometry": {"coordinates":[-80.183398,25.858681],"type":"Point"}
}