{
  "type": "Feature",
  "properties": {
    "iso:country":"US",
    "sg:address":"4600 Military Trl Ste 219",
    "sg:city":"Jupiter",
    "sg:classifiers":[
        {
            "category":"Health Services",
            "subcategory":"Dentist",
            "type":"Services"
        }
    ],
    "sg:phone":"+1 561 844 0715",
    "sg:postcode":"33458",
    "sg:province":"FL",
    "wof:name":"Smiles General &",
    "wof:placetype":"venue"
},
  "geometry": {"coordinates":[-80.10332699999999,26.892234],"type":"Point"}
}