{
  "type": "Feature",
  "properties": {
    "iso:country":"US",
    "sg:address":"16000 Chamberlin Pkwy",
    "sg:city":"Fort Myers",
    "sg:classifiers":[
        {
            "category":"Airport",
            "type":"Transportation"
        }
    ],
    "sg:phone":"+1 239 768 1000",
    "sg:postcode":"33913",
    "sg:province":"FL",
    "sg:tags":[
        "executive"
    ],
    "wof:name":"Southwest Florida Intl Airport",
    "wof:placetype":"venue"
},
  "geometry": {"coordinates":[-81.76271699999999,26.539013],"type":"Point"}
}