{
  "type": "Feature",
  "properties": {
    "addr:full":"2122 Whitfield Park Ave Sarasota FL 34243",
    "addr:housenumber":"2122",
    "addr:postcode":"34243",
    "addr:street":"Whitfield Park Ave",
    "iso:country":"US",
    "sg:address":"2122 Whitfield Park Ave",
    "sg:city":"Sarasota",
    "sg:classifiers":[
        {
            "category":"Manufacturing",
            "subcategory":"Metals",
            "type":"Manufacturing & Wholesale Goods"
        }
    ],
    "sg:phone":"+1 941 756 8129",
    "sg:postcode":"34243",
    "sg:province":"FL",
    "sg:tags":[
        "building",
        "prefabricated",
        "mfg"
    ],
    "wof:name":"Structures Unlimited",
    "wof:placetype":"venue"
},
  "geometry": {"coordinates":[-82.536485,27.420035],"type":"Point"}
}