{
  "type": "Feature",
  "properties": {
    "iso:country":"US",
    "sg:address":"3866 Prospect Ave",
    "sg:city":"Riviera Beach",
    "sg:classifiers":[
        {
            "category":"Building & Trades",
            "subcategory":"Cleaning & Sanitation",
            "type":"Services"
        }
    ],
    "sg:phone":"+1 561 863 7782",
    "sg:postcode":"33404",
    "sg:province":"FL",
    "wof:name":"Service Master Co",
    "wof:placetype":"venue"
},
  "geometry": {"coordinates":[-80.098348,26.790613],"type":"Point"}
}