{
  "type": "Feature",
  "properties": {
    "addr:full":"113 E College Ave Tallahassee FL 32301",
    "addr:housenumber":"113",
    "addr:postcode":"32301",
    "addr:street":"E College Ave",
    "iso:country":"US",
    "sg:address":"113 E College Ave",
    "sg:city":"Tallahassee",
    "sg:classifiers":[
        {
            "category":"Professional",
            "subcategory":"Management & Consulting",
            "type":"Services"
        }
    ],
    "sg:phone":"+1 850 523 1500",
    "sg:postcode":"32301",
    "sg:province":"FL",
    "sg:tags":[
        "lobbyist"
    ],
    "wof:name":"KIRK Consulting Group Inc",
    "wof:placetype":"venue"
},
  "geometry": {"coordinates":[-84.277126,30.440663],"type":"Point"}
}