{
  "type": "Feature",
  "properties": {
    "addr:full":"2254 Clara Kee Blvd Tallahassee FL 32303",
    "addr:housenumber":"2254",
    "addr:postcode":"32303",
    "addr:street":"Clara Kee Blvd",
    "iso:country":"US",
    "sg:address":"2254 Clara Kee Blvd",
    "sg:city":"Tallahassee",
    "sg:classifiers":[
        {
            "category":"Professional",
            "type":"Services"
        },
        {
            "category":"Personal",
            "type":"Services"
        }
    ],
    "sg:phone":"+1 850 562 2422",
    "sg:postcode":"32303",
    "sg:province":"FL",
    "sg:tags":[
        "mover",
        "material",
        "moving",
        "services-labor"
    ],
    "wof:name":"Precision Moving",
    "wof:placetype":"venue"
},
  "geometry": {"coordinates":[-84.343817,30.51556],"type":"Point"}
}