{
  "type": "Feature",
  "properties": {
    "iso:country":"US",
    "sg:address":"2891 Tamiami Trl",
    "sg:city":"Naples",
    "sg:classifiers":[
        {
            "category":"Retail",
            "subcategory":"Auto Repair",
            "type":"Services"
        }
    ],
    "sg:phone":"+1 239 530 7788",
    "sg:postcode":"34112",
    "sg:province":"FL",
    "sg:tags":[
        "automotive"
    ],
    "wof:name":"Everglade Auto Inc",
    "wof:placetype":"venue"
},
  "geometry": {"coordinates":[-81.772069,26.131087],"type":"Point"}
}