{
  "type": "Feature",
  "properties": {
    "iso:country":"US",
    "sg:address":"4915 US Hwy 92",
    "sg:city":"Lakeland",
    "sg:classifiers":[
        {
            "category":"Organizations",
            "subcategory":"Religious Organization",
            "type":"Services"
        }
    ],
    "sg:phone":"+1 863 665 4756",
    "sg:postcode":"33801",
    "sg:province":"FL",
    "sg:tags":[
        "church"
    ],
    "wof:name":"Carter's Baptist Church",
    "wof:placetype":"venue"
},
  "geometry": {"coordinates":[-81.860303,28.047887],"type":"Point"}
}