{
  "type": "Feature",
  "properties": {
    "addr:full":"9165 NW 31st Ave Miami FL 33147",
    "addr:housenumber":"9165",
    "addr:postcode":"33147",
    "addr:street":"Nw 31St Ave",
    "iso:country":"US",
    "sg:address":"9165 NW 31st Ave",
    "sg:city":"Miami",
    "sg:classifiers":[
        {
            "category":"Communications",
            "subcategory":"Film & Video Production",
            "type":"Services"
        }
    ],
    "sg:phone":"+1 305 696 5567",
    "sg:postcode":"33147",
    "sg:province":"FL",
    "sg:tags":[
        "motion"
    ],
    "wof:name":"Shining Star Video Productions",
    "wof:placetype":"venue"
},
  "geometry": {"coordinates":[-80.248176,25.856739],"type":"Point"}
}