{
  "type": "Feature",
  "properties": {
    "iso:country":"US",
    "sg:address":"18205 Biscayne Blvd",
    "sg:city":"Aventura",
    "sg:classifiers":[
        {
            "category":"Place Of Worship",
            "subcategory":"Church",
            "type":"Public Place"
        }
    ],
    "sg:phone":"+1 305 936 8163",
    "sg:postcode":"33160",
    "sg:province":"FL",
    "sg:tags":[
        "churches-jehovah's",
        "witness"
    ],
    "wof:name":"Kingdom Solution",
    "wof:placetype":"venue"
},
  "geometry": {"coordinates":[-80.14787200000001,25.944139],"type":"Point"}
}