{
  "type": "Feature",
  "properties": {
    "addr:full":"7900 Peters Rd Fort Lauderdale FL 33324",
    "addr:housenumber":"7900",
    "addr:postcode":"33324",
    "addr:street":"Peters Rd",
    "iso:country":"US",
    "sg:address":"7900 Peters Rd",
    "sg:city":"Fort Lauderdale",
    "sg:classifiers":[
        {
            "category":"Insurance",
            "subcategory":"Hazard Insurance",
            "type":"Services"
        }
    ],
    "sg:phone":"+1 954 916 0474",
    "sg:postcode":"33324",
    "sg:province":"FL",
    "sg:tags":[
        "carrier",
        "public"
    ],
    "wof:name":"F D I C",
    "wof:placetype":"venue"
},
  "geometry": {"coordinates":[-80.25388,26.105298],"type":"Point"}
}