{
  "type": "Feature",
  "properties": {
    "iso:country":"US",
    "sg:address":"101 Southhall Ln",
    "sg:city":"Maitland",
    "sg:classifiers":[
        {
            "category":"Real Estate",
            "subcategory":"Real Estate Operator",
            "type":"Services"
        }
    ],
    "sg:phone":"+1 407 667 4850",
    "sg:postcode":"32751",
    "sg:province":"FL",
    "sg:tags":[
        "property",
        "lessor"
    ],
    "wof:name":"H Q Global Workplaces Inc",
    "wof:placetype":"venue"
},
  "geometry": {"coordinates":[-81.396467,28.62717],"type":"Point"}
}