{
  "type": "Feature",
  "properties": {
    "iso:country":"US",
    "sg:address":"635 US Hwy 231",
    "sg:city":"Panama City",
    "sg:classifiers":[
        {
            "category":"Personal",
            "subcategory":"Beauty Salon",
            "type":"Services"
        }
    ],
    "sg:phone":"+1 850 763 4647",
    "sg:postcode":"32405",
    "sg:province":"FL",
    "sg:tags":[
        "shop"
    ],
    "wof:name":"Strands Hair Studio",
    "wof:placetype":"venue"
},
  "geometry": {"coordinates":[-85.65047,30.182765],"type":"Point"}
}