{
  "type": "Feature",
  "properties": {
    "iso:country":"US",
    "sg:address":"4201 Vineland Rd",
    "sg:city":"Orlando",
    "sg:classifiers":[
        {
            "category":"Travel",
            "subcategory":"Travel Agent",
            "type":"Entertainment"
        }
    ],
    "sg:phone":"+1 407 648 9390",
    "sg:postcode":"32811",
    "sg:province":"FL",
    "sg:tags":[
        "agency",
        "bureau"
    ],
    "sg:website":"www.windermeretravel.com",
    "wof:name":"Windermere Travel Inc",
    "wof:placetype":"venue"
},
  "geometry": {"coordinates":[-81.432901,28.498312],"type":"Point"}
}