{
  "type": "Feature",
  "properties": {
    "addr:full":"8355 SW 184th Ter Miami FL 33157",
    "addr:housenumber":"8355",
    "addr:postcode":"33157",
    "addr:street":"Sw 184Th Ter",
    "iso:country":"US",
    "sg:address":"8355 SW 184th Ter",
    "sg:city":"Miami",
    "sg:classifiers":[
        {
            "category":"Professional",
            "subcategory":"Computer Services",
            "type":"Services"
        }
    ],
    "sg:phone":"+1 786 242 9339",
    "sg:postcode":"33157",
    "sg:province":"FL",
    "sg:tags":[
        "design",
        "system"
    ],
    "wof:name":"Pedro Souss",
    "wof:placetype":"venue"
},
  "geometry": {"coordinates":[-80.326705,25.597424],"type":"Point"}
}