{
  "type": "Feature",
  "properties": {
    "addr:full":"812 6th St Miami Beach FL 33139",
    "addr:housenumber":"812",
    "addr:postcode":"33139",
    "addr:street":"6Th St",
    "iso:country":"US",
    "sg:address":"812 6th St",
    "sg:city":"Miami Beach",
    "sg:classifiers":[
        {
            "category":"Food & Beverages",
            "subcategory":"Groceries & Convenience Stores",
            "type":"Retail Goods"
        }
    ],
    "sg:phone":"+1 305 673 8884",
    "sg:postcode":"33139",
    "sg:province":"FL",
    "sg:tags":[
        "grocer"
    ],
    "wof:name":"Meridian Food Market",
    "wof:placetype":"venue"
},
  "geometry": {"coordinates":[-80.13649700000001,25.7759],"type":"Point"}
}