{
  "type": "Feature",
  "properties": {
    "addr:full":"3802 E Columbus Dr Tampa FL 33605",
    "addr:housenumber":"3802",
    "addr:postcode":"33605",
    "addr:street":"E Columbus Dr",
    "iso:country":"US",
    "sg:address":"3802 E Columbus Dr",
    "sg:city":"Tampa",
    "sg:classifiers":[
        {
            "category":"Wholesale",
            "subcategory":"Dairy",
            "type":"Manufacturing & Wholesale Goods"
        }
    ],
    "sg:phone":"+1 813 621 3233",
    "sg:postcode":"33605",
    "sg:province":"FL",
    "sg:tags":[
        "product"
    ],
    "sg:website":"www.instantwhipflorida.com",
    "wof:name":"Southeast Dairy Processors Inc",
    "wof:placetype":"venue"
},
  "geometry": {"coordinates":[-82.415021,27.966826],"type":"Point"}
}