{
  "type": "Feature",
  "properties": {
    "addr:full":"1 Curtiss Pkwy Miami Springs FL 33166",
    "addr:housenumber":"1",
    "addr:postcode":"33166",
    "addr:street":"Curtiss Pkwy",
    "iso:country":"US",
    "sg:address":"1 Curtiss Pkwy",
    "sg:city":"Miami Springs",
    "sg:classifiers":[
        {
            "category":"Sports & Exercise",
            "subcategory":"Gym",
            "type":"Entertainment"
        }
    ],
    "sg:phone":"+1 305 882 0204",
    "sg:postcode":"33166",
    "sg:province":"FL",
    "sg:tags":[
        "trainer"
    ],
    "wof:name":"A B Womens Fitness",
    "wof:placetype":"venue"
},
  "geometry": {"coordinates":[-80.280691,25.821954],"type":"Point"}
}