{
  "type": "Feature",
  "properties": {
    "addr:full":"2500 NW 79th Ave Ste 166 Doral FL 33122",
    "addr:housenumber":"2500",
    "addr:postcode":"33122",
    "addr:street":"Nw 79Th Ave Ste 166",
    "iso:country":"US",
    "sg:address":"2500 NW 79th Ave Ste 166",
    "sg:city":"Doral",
    "sg:classifiers":[
        {
            "category":"Building & Trades",
            "subcategory":"Construction",
            "type":"Services"
        }
    ],
    "sg:phone":"+1 305 552 7026",
    "sg:postcode":"33122",
    "sg:province":"FL",
    "sg:tags":[
        "contractor"
    ],
    "sg:website":"www.concretefloorsolutions.com",
    "wof:name":"Concrete Floor Solutions",
    "wof:placetype":"venue"
},
  "geometry": {"coordinates":[-80.325102,25.79695],"type":"Point"}
}