{
  "type": "Feature",
  "properties": {
    "iso:country":"US",
    "sg:address":"2790 Michigan Ave",
    "sg:city":"Kissimmee",
    "sg:classifiers":[
        {
            "category":"Wholesale",
            "subcategory":"Non-durable Goods",
            "type":"Manufacturing & Wholesale Goods"
        }
    ],
    "sg:phone":"+1 407 343 5539",
    "sg:postcode":"34744",
    "sg:province":"FL",
    "wof:name":"Ramon Wholesale Merchandise",
    "wof:placetype":"venue"
},
  "geometry": {"coordinates":[-81.39134799999999,28.328992],"type":"Point"}
}