{
  "type": "Feature",
  "properties": {
    "addr:full":"29813 State Rd 54 Wesley Chapel FL 33543",
    "addr:housenumber":"29813;54",
    "addr:postcode":"33543",
    "addr:street":"State Rd",
    "iso:country":"US",
    "sg:address":"29813 State Rd 54",
    "sg:city":"Wesley Chapel",
    "sg:classifiers":[
        {
            "category":"Sports & Exercise",
            "subcategory":"Gym",
            "type":"Entertainment"
        }
    ],
    "sg:phone":"+1 813 907 2774",
    "sg:postcode":"33543",
    "sg:province":"FL",
    "sg:tags":[
        "club",
        "health",
        "studio",
        "gymnasium"
    ],
    "wof:name":"Wesley Chapel Fitness",
    "wof:placetype":"venue"
},
  "geometry": {"coordinates":[-82.319474,28.240585],"type":"Point"}
}