{
  "type": "Feature",
  "properties": {
    "iso:country":"US",
    "sg:address":"P.O. Box 651294, Miami, FL 33265",
    "sg:city":"Miami",
    "sg:classifiers":[
        {
            "category":"Professional",
            "subcategory":"Computer Services",
            "type":"Services"
        }
    ],
    "sg:phone":"+1 305 752 7700",
    "sg:postcode":"33265",
    "sg:province":"FL",
    "sg:tags":[
        "bracelets-handmade",
        "rings-at-bargain-prices",
        "necklaces-for-teenagers"
    ],
    "sg:website":"http://www.chickieglam.com",
    "wof:name":"Chickieglam Inc.",
    "wof:placetype":"venue"
},
  "geometry": {"coordinates":[-80.458168,25.558428],"type":"Point"}
}