{
  "type": "Feature",
  "properties": {
    "iso:country":"US",
    "sg:address":"205 S Hoover Blvd",
    "sg:city":"Tampa",
    "sg:classifiers":[
        {
            "category":"Autos & Motor Vehicles",
            "subcategory":"Auto Supplies",
            "type":"Retail Goods"
        }
    ],
    "sg:phone":"+1 813 636 8111",
    "sg:postcode":"33609",
    "sg:province":"FL",
    "wof:name":"Restructure Partners LLC",
    "wof:placetype":"venue"
},
  "geometry": {"coordinates":[-82.53448,27.941519],"type":"Point"}
}