{
  "type": "Feature",
  "properties": {
    "addr:full":"635 W Lumsden Rd Brandon FL 33511",
    "addr:housenumber":"635",
    "addr:postcode":"33511",
    "addr:street":"W Lumsden Rd",
    "iso:country":"US",
    "sg:address":"635 W Lumsden Rd",
    "sg:city":"Brandon",
    "sg:classifiers":[
        {
            "category":"Professional",
            "subcategory":"Computer Services",
            "type":"Services"
        },
        {
            "category":"Professional",
            "subcategory":"Art Services",
            "type":"Services"
        },
        {
            "category":"Internet Cafe",
            "subcategory":"None",
            "type":"Food & Drink"
        }
    ],
    "sg:phone":"+1 813 684 6803",
    "sg:postcode":"33511",
    "sg:province":"FL",
    "sg:tags":[
        "product",
        "designer",
        "consultant",
        "system",
        "graphic",
        "software"
    ],
    "sg:website":"http://www.acsits.com",
    "wof:name":"Acs-Connect",
    "wof:placetype":"venue"
},
  "geometry": {"coordinates":[-82.292312,27.923101],"type":"Point"}
}