{
  "type": "Feature",
  "properties": {
    "addr:full":"12404 W Dixie Hwy North Miami FL 33161",
    "addr:housenumber":"12404",
    "addr:postcode":"33161",
    "addr:street":"W Dixie Hwy",
    "iso:country":"US",
    "sg:address":"12404 W Dixie Hwy",
    "sg:city":"North Miami",
    "sg:classifiers":[
        {
            "category":"Health Services",
            "subcategory":"Doctor",
            "type":"Services"
        }
    ],
    "sg:phone":"+1 305 893 4801",
    "sg:postcode":"33161",
    "sg:province":"FL",
    "sg:tags":[
        "surgeon",
        "oral"
    ],
    "wof:name":"Rosenberg Howard G DDS",
    "wof:placetype":"venue"
},
  "geometry": {"coordinates":[-80.188202,25.889299],"type":"Point"}
}