{
  "type": "Feature",
  "properties": {
    "iso:country":"US",
    "sg:address":"6800 W 24th Ave",
    "sg:city":"Hialeah",
    "sg:classifiers":[
        {
            "category":"Building & Trades",
            "subcategory":"Locksmith",
            "type":"Services"
        }
    ],
    "sg:phone":"+1 305 423 0160",
    "sg:postcode":"33016",
    "sg:province":"FL",
    "sg:tags":[
        "key"
    ],
    "wof:name":"7 Days Emergency Locksmith Service of",
    "wof:placetype":"venue"
},
  "geometry": {"coordinates":[-80.331822,25.884327],"type":"Point"}
}