{
  "type": "Feature",
  "properties": {
    "iso:country":"US",
    "sg:address":"11620 Quail Roost Dr",
    "sg:city":"Miami",
    "sg:classifiers":[
        {
            "category":"Restaurant",
            "type":"Food & Drink"
        }
    ],
    "sg:phone":"+1 305 253 4422",
    "sg:postcode":"33157",
    "sg:province":"FL",
    "wof:name":"Sabana Grande",
    "wof:placetype":"venue"
},
  "geometry": {"coordinates":[-80.379997,25.5917],"type":"Point"}
}