{
  "type": "Feature",
  "properties": {
    "iso:country":"US",
    "sg:address":"1701 NE 28th Ter",
    "sg:city":"Pompano Beach",
    "sg:classifiers":[
        {
            "category":"Local Transit",
            "type":"Transportation"
        }
    ],
    "sg:phone":"+1 954 941 7433",
    "sg:postcode":"33062",
    "sg:province":"FL",
    "sg:tags":[
        "passenger",
        "limousine"
    ],
    "wof:name":"Atlantic Coast Limousine",
    "wof:placetype":"venue"
},
  "geometry": {"coordinates":[-80.09341999999999,26.253972],"type":"Point"}
}