{
  "type": "Feature",
  "properties": {
    "iso:country":"US",
    "sg:address":"17386 66th St",
    "sg:city":"Live Oak",
    "sg:classifiers":[
        {
            "category":"Building & Trades",
            "subcategory":"Construction",
            "type":"Services"
        }
    ],
    "sg:phone":"+1 386 362 6250",
    "sg:postcode":"32060",
    "sg:province":"FL",
    "sg:tags":[
        "commercial"
    ],
    "wof:name":"Finish Trades Inc",
    "wof:placetype":"venue"
},
  "geometry": {"coordinates":[-83.108752,30.330099],"type":"Point"}
}