{
  "type": "Feature",
  "properties": {
    "iso:country":"US",
    "sg:address":"19333 Collins Ave",
    "sg:city":"Miami",
    "sg:classifiers":[
        {
            "category":"Real Estate",
            "subcategory":"Real Estate Agent",
            "type":"Services"
        },
        {
            "category":"Real Estate",
            "subcategory":"Real Estate Operator",
            "type":"Services"
        }
    ],
    "sg:phone":"+1 305 931 1232",
    "sg:postcode":"33160",
    "sg:province":"FL",
    "sg:tags":[
        "condominium"
    ],
    "wof:name":"Ocean I Condominium",
    "wof:placetype":"venue"
},
  "geometry": {"coordinates":[-80.120542,25.954955],"type":"Point"}
}