{
  "type": "Feature",
  "properties": {
    "iso:country":"US",
    "sg:address":"2462 Lake Debra Dr Suite 2202",
    "sg:city":"Orlando",
    "sg:classifiers":[
        {
            "category":"Local Transit",
            "type":"Transportation"
        }
    ],
    "sg:phone":"+1 407 370 9516",
    "sg:postcode":"32835",
    "sg:province":"FL",
    "sg:tags":[
        "public"
    ],
    "wof:name":"Limo Orlando Airport Limousine Transportation Services",
    "wof:placetype":"venue"
},
  "geometry": {"coordinates":[-81.477643,28.513096],"type":"Point"}
}