{
  "type": "Feature",
  "properties": {
    "iso:country":"US",
    "sg:address":"5091 Red Gum Rd",
    "sg:city":"Tallahassee",
    "sg:classifiers":[
        {
            "category":"Home & Garden",
            "subcategory":"Carpets & Floor Coverings",
            "type":"Retail Goods"
        }
    ],
    "sg:phone":"+1 850 575 5596",
    "sg:postcode":"32303",
    "sg:province":"FL",
    "sg:tags":[
        "material"
    ],
    "wof:name":"Down On All Floors",
    "wof:placetype":"venue"
},
  "geometry": {"coordinates":[-84.36611499999999,30.551688],"type":"Point"}
}