{
  "type": "Feature",
  "properties": {
    "iso:country":"US",
    "sg:address":"1781 NW 129th Ter",
    "sg:city":"Miami",
    "sg:classifiers":[
        {
            "category":"Manufacturing",
            "subcategory":"Electronics",
            "type":"Manufacturing & Wholesale Goods"
        }
    ],
    "sg:phone":"+1 305 681 5833",
    "sg:postcode":"33167",
    "sg:province":"FL",
    "sg:tags":[
        "parts",
        "electronic",
        "apparatus",
        "mfg"
    ],
    "wof:name":"Wavebusters of Florida Inc",
    "wof:placetype":"venue"
},
  "geometry": {"coordinates":[-80.228407,25.892923],"type":"Point"}
}