{
  "type": "Feature",
  "properties": {
    "addr:full":"12219 NW 35th St Pompano Beach FL 33065",
    "addr:housenumber":"12219",
    "addr:postcode":"33065",
    "addr:street":"Nw 35Th St",
    "iso:country":"US",
    "sg:address":"12219 NW 35th St",
    "sg:city":"Pompano Beach",
    "sg:classifiers":[
        {
            "category":"Shopping",
            "subcategory":"Clothing, Apparel, & Fashions",
            "type":"Retail Goods"
        }
    ],
    "sg:phone":"+1 954 753 0323",
    "sg:postcode":"33065",
    "sg:province":"FL",
    "wof:name":"Custom Tee Shirts",
    "wof:placetype":"venue"
},
  "geometry": {"coordinates":[-80.29083300000001,26.274448],"type":"Point"}
}