{
  "type": "Feature",
  "properties": {
    "iso:country":"US",
    "sg:address":"7109 Lake Worth Rd",
    "sg:city":"Wellington",
    "sg:classifiers":[
        {
            "category":"Professional",
            "subcategory":"Lawyer & Legal Services",
            "type":"Services"
        }
    ],
    "sg:phone":"+1 561 649 2711",
    "sg:postcode":"33467",
    "sg:province":"FL",
    "sg:tags":[
        "attorney"
    ],
    "wof:name":"Hoffman Clendining & Harding",
    "wof:placetype":"venue"
},
  "geometry": {"coordinates":[-80.159814,26.617688],"type":"Point"}
}