{
  "type": "Feature",
  "properties": {
    "iso:country":"US",
    "sg:address":"1825 Knox Ave",
    "sg:city":"Sanford",
    "sg:classifiers":[
        {
            "category":"Organizations",
            "subcategory":"Religious Organization",
            "type":"Services"
        }
    ],
    "sg:phone":"+1 407 322 5771",
    "sg:postcode":"32771",
    "sg:province":"FL",
    "sg:tags":[
        "church"
    ],
    "wof:name":"Step Of Faith Inc",
    "wof:placetype":"venue"
},
  "geometry": {"coordinates":[-81.298647,28.794578],"type":"Point"}
}