{
  "type": "Feature",
  "properties": {
    "iso:country":"US",
    "sg:address":"1666 W 40th St",
    "sg:city":"Hialeah",
    "sg:classifiers":[
        {
            "category":"Shopping",
            "subcategory":"Clothing, Apparel, & Fashions",
            "type":"Retail Goods"
        },
        {
            "category":"Professional",
            "subcategory":"Printing & Photocopies",
            "type":"Services"
        },
        {
            "category":"Manufacturing",
            "subcategory":"Apparel",
            "type":"Manufacturing & Wholesale Goods"
        }
    ],
    "sg:phone":"+1 305 822 2508",
    "sg:postcode":"33012",
    "sg:province":"FL",
    "sg:tags":[
        "screen",
        "clothing-men's-wholesale",
        "t-shirt",
        "clothing",
        "store",
        "manufacturer"
    ],
    "wof:name":"Interntional Sportshirts Miami",
    "wof:placetype":"venue"
},
  "geometry": {"coordinates":[-80.314672,25.85807],"type":"Point"}
}