{
  "type": "Feature",
  "properties": {
    "iso:country":"US",
    "sg:address":"4808 SW 28th Ter",
    "sg:city":"Fort Lauderdale",
    "sg:classifiers":[
        {
            "category":"Retail",
            "subcategory":"Repair Shop",
            "type":"Services"
        }
    ],
    "sg:phone":"+1 954 987 2888",
    "sg:postcode":"33312",
    "sg:province":"FL",
    "sg:tags":[
        "rad",
        "merchandise"
    ],
    "wof:name":"Pet of Gold",
    "wof:placetype":"venue"
},
  "geometry": {"coordinates":[-80.178837,26.057302],"type":"Point"}
}