{
  "type": "Feature",
  "properties": {
    "iso:country":"US",
    "sg:address":"16243 E Lullwater Dr",
    "sg:city":"Panama City",
    "sg:classifiers":[
        {
            "category":"Building & Trades",
            "subcategory":"Construction",
            "type":"Services"
        }
    ],
    "sg:phone":"+1 888 297 3684",
    "sg:postcode":"32413",
    "sg:province":"FL",
    "sg:tags":[
        "residential",
        "renovation",
        "general"
    ],
    "wof:name":"North Bay Partners LC",
    "wof:placetype":"venue"
},
  "geometry": {"coordinates":[-85.88128500000001,30.222698],"type":"Point"}
}