{
  "type": "Feature",
  "properties": {
    "iso:country":"US",
    "sg:address":"4910 14th St W",
    "sg:city":"Bradenton",
    "sg:classifiers":[
        {
            "category":"Health Services",
            "subcategory":"Nursing And Care Facility",
            "type":"Services"
        },
        {
            "category":"Health Services",
            "subcategory":"Health Practitioner",
            "type":"Services"
        },
        {
            "category":"Health Services",
            "subcategory":"Hospice",
            "type":"Services"
        }
    ],
    "sg:phone":"+1 941 896 7875",
    "sg:postcode":"34207",
    "sg:province":"FL",
    "sg:tags":[
        "home",
        "eldercare-home"
    ],
    "wof:name":"Simple Living Home Care Inc",
    "wof:placetype":"venue"
},
  "geometry": {"coordinates":[-82.575371,27.454189],"type":"Point"}
}