{
  "type": "Feature",
  "properties": {
    "iso:country":"US",
    "sg:address":"1432 1st St",
    "sg:city":"Sarasota",
    "sg:classifiers":[
        {
            "category":"Professional",
            "subcategory":"Lawyer & Legal Services",
            "type":"Services"
        }
    ],
    "sg:phone":"+1 941 954 7750",
    "sg:postcode":"34236",
    "sg:province":"FL",
    "sg:tags":[
        "attorney"
    ],
    "sg:website":"www.dooleydrakelaw.com",
    "wof:name":"Dooley & Drake PA",
    "wof:placetype":"venue"
},
  "geometry": {"coordinates":[-82.541239,27.337185],"type":"Point"}
}