{
  "type": "Feature",
  "properties": {
    "iso:country":"US",
    "sg:address":"4425 Idlewood Dr",
    "sg:city":"Pensacola",
    "sg:classifiers":[
        {
            "category":"Building & Trades",
            "subcategory":"Construction",
            "type":"Services"
        }
    ],
    "sg:phone":"+1 850 457 1798",
    "sg:postcode":"32506",
    "sg:province":"FL",
    "sg:tags":[
        "siding",
        "contractor"
    ],
    "wof:name":"Thomas Brand Siding Co Inc",
    "wof:placetype":"venue"
},
  "geometry": {"coordinates":[-87.272977,30.412518],"type":"Point"}
}