{
  "type": "Feature",
  "properties": {
    "addr:full":"3243 Regal Crest Dr Longwood FL 32779",
    "addr:housenumber":"3243",
    "addr:postcode":"32779",
    "addr:street":"Regal Crest Dr",
    "iso:country":"US",
    "sg:address":"3243 Regal Crest Dr",
    "sg:city":"Longwood",
    "sg:classifiers":[
        {
            "category":"Real Estate",
            "subcategory":"Real Estate Agent",
            "type":"Services"
        }
    ],
    "sg:phone":"+1 407 771 4982",
    "sg:postcode":"32779",
    "sg:province":"FL",
    "wof:name":"Hagan Tim & Alana PA",
    "wof:placetype":"venue"
},
  "geometry": {"coordinates":[-81.397296,28.753375],"type":"Point"}
}