{
  "type": "Feature",
  "properties": {
    "iso:country":"US",
    "sg:address":"5640 Taylor Rd",
    "sg:city":"Naples",
    "sg:classifiers":[
        {
            "category":"Autos & Motor Vehicles",
            "subcategory":"Auto Supplies",
            "type":"Retail Goods"
        }
    ],
    "sg:phone":"+1 239 597 7500",
    "sg:postcode":"34109",
    "sg:province":"FL",
    "sg:tags":[
        "automobile",
        "accessory"
    ],
    "wof:name":"Wheel Outlet III Corp",
    "wof:placetype":"venue"
},
  "geometry": {"coordinates":[-81.783214,26.214919],"type":"Point"}
}