{
  "type": "Feature",
  "properties": {
    "addr:full":"7 Alafaya Woods Blvd Oviedo FL 32765",
    "addr:housenumber":"7",
    "addr:postcode":"32765",
    "addr:street":"Alafaya Woods Blvd",
    "iso:country":"US",
    "sg:address":"7 Alafaya Woods Blvd",
    "sg:city":"Oviedo",
    "sg:classifiers":[
        {
            "category":"Restaurant",
            "type":"Food & Drink"
        }
    ],
    "sg:menulink":"http://www.allmenus.com/fl/oviedo/285134-sams-pizza/menu/",
    "sg:phone":"+1 407 977 1200",
    "sg:postcode":"32765",
    "sg:province":"FL",
    "sg:tags":[
        "american",
        "pizza"
    ],
    "wof:name":"Sam's Pizza",
    "wof:placetype":"venue"
},
  "geometry": {"coordinates":[-81.20793999999999,28.64932],"type":"Point"}
}