{
  "type": "Feature",
  "properties": {
    "addr:full":"2757 Andes Way St Cloud FL 34769",
    "addr:housenumber":"2757",
    "addr:postcode":"34769",
    "addr:street":"Andes Way",
    "iso:country":"US",
    "sg:address":"2757 Andes Way",
    "sg:city":"St Cloud",
    "sg:classifiers":[
        {
            "category":"Building & Trades",
            "subcategory":"Construction",
            "type":"Services"
        }
    ],
    "sg:phone":"+1 407 957 1881",
    "sg:postcode":"34769",
    "sg:province":"FL",
    "sg:tags":[
        "home",
        "builder"
    ],
    "wof:name":"Villas Del Castillo",
    "wof:placetype":"venue"
},
  "geometry": {"coordinates":[-81.278682,28.23257],"type":"Point"}
}