{
  "type": "Feature",
  "properties": {
    "iso:country":"US",
    "sg:address":"5340 Dominica Cir",
    "sg:city":"Sarasota",
    "sg:classifiers":[
        {
            "category":"Professional",
            "subcategory":"Computer Services",
            "type":"Services"
        },
        {
            "category":"Internet Cafe",
            "subcategory":"None",
            "type":"Food & Drink"
        }
    ],
    "sg:phone":"+1 941 377 1371",
    "sg:postcode":"34233",
    "sg:province":"FL",
    "sg:tags":[
        "product",
        "software"
    ],
    "wof:name":"Gp Enterprise Systems, Inc.",
    "wof:placetype":"venue"
},
  "geometry": {"coordinates":[-82.462164,27.286351],"type":"Point"}
}