{
  "type": "Feature",
  "properties": {
    "iso:country":"US",
    "sg:address":"720 SW 17th St",
    "sg:city":"Ocala",
    "sg:classifiers":[
        {
            "category":"Home & Garden",
            "subcategory":"Furniture",
            "type":"Retail Goods"
        }
    ],
    "sg:phone":"+1 352 351 8117",
    "sg:postcode":"34471",
    "sg:province":"FL",
    "sg:tags":[
        "top",
        "counter"
    ],
    "wof:name":"Wesley's Tops & Distribution",
    "wof:placetype":"venue"
},
  "geometry": {"coordinates":[-82.146485,29.171706],"type":"Point"}
}