{
  "type": "Feature",
  "properties": {
    "iso:country":"US",
    "sg:address":"900 State Road 436",
    "sg:city":"Casselberry",
    "sg:classifiers":[
        {
            "category":"Restaurant",
            "type":"Food & Drink"
        }
    ],
    "sg:phone":"+1 407 834 4421",
    "sg:postcode":"32707",
    "sg:province":"FL",
    "sg:tags":[
        "mexican",
        "tex-mex"
    ],
    "sg:website":"www.donpablos.com",
    "wof:name":"Don Pablo's",
    "wof:placetype":"venue"
},
  "geometry": {"coordinates":[-81.325897,28.649401],"type":"Point"}
}