{
  "type": "Feature",
  "properties": {
    "iso:country":"US",
    "sg:address":"201 E 2nd St",
    "sg:city":"Avon Park",
    "sg:classifiers":[
        {
            "category":"Social Services",
            "subcategory":"Child Care",
            "type":"Services"
        }
    ],
    "sg:phone":"+1 863 453 0004",
    "sg:postcode":"33825",
    "sg:province":"FL",
    "sg:tags":[
        "day"
    ],
    "wof:name":"Small World Learning Center",
    "wof:placetype":"venue"
},
  "geometry": {"coordinates":[-81.49654,27.582909],"type":"Point"}
}