{
  "type": "Feature",
  "properties": {
    "addr:full":"1180 San Pedro Ave Coral Gables FL 33156",
    "addr:housenumber":"1180",
    "addr:postcode":"33156",
    "addr:street":"San Pedro Ave",
    "iso:country":"US",
    "sg:address":"1180 San Pedro Ave",
    "sg:city":"Coral Gables",
    "sg:classifiers":[
        {
            "category":"Health Services",
            "subcategory":"Doctor",
            "type":"Services"
        }
    ],
    "sg:phone":"+1 305 666 3517",
    "sg:postcode":"33156",
    "sg:province":"FL",
    "sg:tags":[
        "surgeon",
        "oral"
    ],
    "wof:name":"Arnold Richard M DDS",
    "wof:placetype":"venue"
},
  "geometry": {"coordinates":[-80.277496,25.6525],"type":"Point"}
}