{
  "type": "Feature",
  "properties": {
    "iso:country":"US",
    "sg:address":"12053 SW 117th Ave",
    "sg:city":"Miami",
    "sg:classifiers":[
        {
            "category":"Personal",
            "subcategory":"Nail Salon",
            "type":"Services"
        }
    ],
    "sg:phone":"+1 305 378 1433",
    "sg:postcode":"33186",
    "sg:province":"FL",
    "wof:name":"Vivi Nails",
    "wof:placetype":"venue"
},
  "geometry": {"coordinates":[-80.38310300000001,25.655536],"type":"Point"}
}