{
  "type": "Feature",
  "properties": {
    "addr:full":"10151 University Blvd Orlando FL 32817",
    "addr:housenumber":"10151",
    "addr:postcode":"32817",
    "addr:street":"University Blvd",
    "iso:country":"US",
    "sg:address":"10151 University Blvd",
    "sg:city":"Orlando",
    "sg:classifiers":[
        {
            "category":"Health Services",
            "subcategory":"Hospital",
            "type":"Services"
        }
    ],
    "sg:phone":"+1 407 758 4916",
    "sg:postcode":"32817",
    "sg:province":"FL",
    "sg:tags":[
        "equipment",
        "supply"
    ],
    "wof:name":"Sci",
    "wof:placetype":"venue"
},
  "geometry": {"coordinates":[-81.24235400000001,28.597572],"type":"Point"}
}