{
  "type": "Feature",
  "properties": {
    "iso:country":"US",
    "sg:address":"804 Watt Dr",
    "sg:city":"Tallahassee",
    "sg:classifiers":[
        {
            "category":"Building & Trades",
            "subcategory":"Electrical",
            "type":"Services"
        }
    ],
    "sg:phone":"+1 850 422 1302",
    "sg:postcode":"32303",
    "sg:province":"FL",
    "sg:tags":[
        "industrial",
        "electrician",
        "contractors-commercial",
        "electric"
    ],
    "wof:name":"T8 Lighting Inc",
    "wof:placetype":"venue"
},
  "geometry": {"coordinates":[-84.293898,30.470128],"type":"Point"}
}