{
  "type": "Feature",
  "properties": {
    "addr:full":"2205 Cheryl Ct Melbourne FL 32935",
    "addr:housenumber":"2205",
    "addr:postcode":"32935",
    "addr:street":"Cheryl Ct",
    "iso:country":"US",
    "sg:address":"2205 Cheryl Ct",
    "sg:city":"Melbourne",
    "sg:classifiers":[
        {
            "category":"Real Estate",
            "subcategory":"Real Estate Agent",
            "type":"Services"
        }
    ],
    "sg:phone":"+1 321 757 0478",
    "sg:postcode":"32935",
    "sg:province":"FL",
    "sg:tags":[
        "inspection"
    ],
    "wof:name":"Brian A Mc Elwain Home Inspctn",
    "wof:placetype":"venue"
},
  "geometry": {"coordinates":[-80.655456,28.126097],"type":"Point"}
}