{
  "type": "Feature",
  "properties": {
    "addr:full":"3245 College Ave Davie FL 33314",
    "addr:housenumber":"3245",
    "addr:postcode":"33314",
    "addr:street":"College Ave",
    "iso:country":"US",
    "sg:address":"3245 College Ave",
    "sg:city":"Davie",
    "sg:classifiers":[
        {
            "category":"Government",
            "subcategory":"Office",
            "type":"Public Place"
        }
    ],
    "sg:phone":"+1 954 370 3725",
    "sg:postcode":"33314",
    "sg:province":"FL",
    "wof:name":"Broward County Co-Op Extension",
    "wof:placetype":"venue"
},
  "geometry": {"coordinates":[-80.239107,26.077704],"type":"Point"}
}