{
  "type": "Feature",
  "properties": {
    "iso:country":"US",
    "sg:address":"2152 NE Rose Walk Ter",
    "sg:city":"Stuart",
    "sg:classifiers":[
        {
            "category":"Organizations",
            "subcategory":"Community Association",
            "type":"Services"
        }
    ],
    "sg:phone":"+1 772 225 3928",
    "sg:postcode":"34996",
    "sg:province":"FL",
    "wof:name":"Rosewalk Estates Owners Assn",
    "wof:placetype":"venue"
},
  "geometry": {"coordinates":[-80.185202,27.230735],"type":"Point"}
}