{
  "type": "Feature",
  "properties": {
    "iso:country":"US",
    "sg:address":"652 S Military Trl",
    "sg:city":"Deerfield Beach",
    "sg:classifiers":[
        {
            "category":"Professional",
            "subcategory":"Engineering",
            "type":"Services"
        }
    ],
    "sg:phone":"+1 954 421 3349",
    "sg:postcode":"33442",
    "sg:province":"FL",
    "sg:tags":[
        "construction",
        "consulting",
        "management",
        "engineer"
    ],
    "sg:website":"www.cooperconsultingeng.com",
    "wof:name":"Cooper Consulting Engineers",
    "wof:placetype":"venue"
},
  "geometry": {"coordinates":[-80.126963,26.309654],"type":"Point"}
}