{
  "type": "Feature",
  "properties": {
    "iso:country":"US",
    "sg:address":"1158 Stroup Rd",
    "sg:city":"Kissimmee",
    "sg:classifiers":[
        {
            "category":"Shopping",
            "type":"Retail Goods"
        }
    ],
    "sg:phone":"+1 407 343 9726",
    "sg:postcode":"34744",
    "sg:province":"FL",
    "sg:tags":[
        "merchandise"
    ],
    "wof:name":"Backyard Country Store Inc",
    "wof:placetype":"venue"
},
  "geometry": {"coordinates":[-81.358902,28.277577],"type":"Point"}
}