{
  "type": "Feature",
  "properties": {
    "iso:country":"US",
    "sg:address":"6600 NW 12th Ave",
    "sg:city":"Fort Lauderdale",
    "sg:classifiers":[
        {
            "category":"Retail",
            "subcategory":"Repair Shop",
            "type":"Services"
        }
    ],
    "sg:phone":"+1 954 689 3730",
    "sg:postcode":"33309",
    "sg:province":"FL",
    "sg:tags":[
        "tank",
        "cleaning"
    ],
    "wof:name":"Atlantic Industrial Svc",
    "wof:placetype":"venue"
},
  "geometry": {"coordinates":[-80.159875,26.208512],"type":"Point"}
}