{
  "type": "Feature",
  "properties": {
    "addr:full":"1308 Sierra Cir Kissimmee FL 34744",
    "addr:housenumber":"1308",
    "addr:postcode":"34744",
    "addr:street":"Sierra Cir",
    "iso:country":"US",
    "sg:address":"1308 Sierra Cir",
    "sg:city":"Kissimmee",
    "sg:classifiers":[
        {
            "category":"Insurance",
            "subcategory":"Insurance Agent",
            "type":"Services"
        }
    ],
    "sg:phone":"+1 407 870 7370",
    "sg:postcode":"34744",
    "sg:province":"FL",
    "sg:tags":[
        "accident"
    ],
    "wof:name":"Alvarado Insurance Service",
    "wof:placetype":"venue"
},
  "geometry": {"coordinates":[-81.39045299999999,28.311197],"type":"Point"}
}