{
  "type": "Feature",
  "properties": {
    "iso:country":"US",
    "sg:address":"3209 Coral Lake Dr",
    "sg:city":"Pompano Beach",
    "sg:classifiers":[
        {
            "category":"Professional",
            "subcategory":"Management & Consulting",
            "type":"Services"
        }
    ],
    "sg:phone":"+1 954 340 4782",
    "sg:postcode":"33065",
    "sg:province":"FL",
    "sg:tags":[
        "business"
    ],
    "wof:name":"Ivaroop Inc",
    "wof:placetype":"venue"
},
  "geometry": {"coordinates":[-80.23765400000001,26.270461],"type":"Point"}
}