{
  "type": "Feature",
  "properties": {
    "addr:full":"327 Ave C SE Winter Haven FL 33880",
    "addr:housenumber":"327",
    "addr:postcode":"33880",
    "addr:street":"Ave C Se",
    "iso:country":"US",
    "sg:address":"327 Ave C SE",
    "sg:city":"Winter Haven",
    "sg:classifiers":[
        {
            "category":"Shopping",
            "subcategory":"Books",
            "type":"Retail Goods"
        }
    ],
    "sg:phone":"+1 863 324 7789",
    "sg:postcode":"33880",
    "sg:province":"FL",
    "wof:name":"Gifts of Grace",
    "wof:placetype":"venue"
},
  "geometry": {"coordinates":[-81.72407699999999,28.018516],"type":"Point"}
}