{
  "type": "Feature",
  "properties": {
    "addr:full":"2224 W 8th Ct Hialeah FL 33010",
    "addr:housenumber":"2224",
    "addr:postcode":"33010",
    "addr:street":"W 8Th Ct",
    "iso:country":"US",
    "sg:address":"2224 W 8th Ct",
    "sg:city":"Hialeah",
    "sg:classifiers":[
        {
            "category":"Manufacturing",
            "subcategory":"Apparel",
            "type":"Manufacturing & Wholesale Goods"
        }
    ],
    "sg:phone":"+1 305 883 8119",
    "sg:postcode":"33010",
    "sg:province":"FL",
    "sg:tags":[
        "mfg"
    ],
    "wof:name":"USF Trimming Corporation",
    "wof:placetype":"venue"
},
  "geometry": {"coordinates":[-80.299184,25.84211],"type":"Point"}
}