{
  "type": "Feature",
  "properties": {
    "iso:country":"US",
    "sg:address":"709 S 50th St",
    "sg:city":"Tampa",
    "sg:classifiers":[
        {
            "category":"Autos & Motor Vehicles",
            "subcategory":"Auto Supplies",
            "type":"Retail Goods"
        }
    ],
    "sg:phone":"+1 813 248 6181",
    "sg:postcode":"33619",
    "sg:province":"FL",
    "sg:tags":[
        "tire"
    ],
    "wof:name":"Sparling Tire & Rim",
    "wof:placetype":"venue"
},
  "geometry": {"coordinates":[-82.401888,27.942514],"type":"Point"}
}