{
  "type": "Feature",
  "properties": {
    "iso:country":"US",
    "sg:address":"544 John St",
    "sg:city":"Lake Helen",
    "sg:classifiers":[
        {
            "category":"Manufacturing",
            "subcategory":"Tools & Machinery",
            "type":"Manufacturing & Wholesale Goods"
        }
    ],
    "sg:phone":"+1 386 228 0912",
    "sg:postcode":"32744",
    "sg:province":"FL",
    "sg:tags":[
        "equipment",
        "peripheral",
        "computer",
        "mfg"
    ],
    "wof:name":"Moore Data Services Inc",
    "wof:placetype":"venue"
},
  "geometry": {"coordinates":[-81.241052,28.995717],"type":"Point"}
}