{
  "type": "Feature",
  "properties": {
    "addr:full":"2170 SE 17th St Fort Lauderdale FL 33316",
    "addr:housenumber":"2170",
    "addr:postcode":"33316",
    "addr:street":"Se 17Th St",
    "iso:country":"US",
    "sg:address":"2170 SE 17th St",
    "sg:city":"Fort Lauderdale",
    "sg:classifiers":[
        {
            "category":"Real Estate",
            "subcategory":"Real Estate Agent",
            "type":"Services"
        }
    ],
    "sg:phone":"+1 954 523 4777",
    "sg:postcode":"33316",
    "sg:province":"FL",
    "sg:website":"www.tricomrealty.com",
    "wof:name":"Tricom",
    "wof:placetype":"venue"
},
  "geometry": {"coordinates":[-80.11670700000001,26.100707],"type":"Point"}
}