{
  "type": "Feature",
  "properties": {
    "addr:full":"2344 Markingham Rd Maitland FL 32751",
    "addr:housenumber":"2344",
    "addr:postcode":"32751",
    "addr:street":"Markingham Rd",
    "iso:country":"US",
    "sg:address":"2344 Markingham Rd",
    "sg:city":"Maitland",
    "sg:classifiers":[
        {
            "category":"Professional",
            "subcategory":"Management & Consulting",
            "type":"Services"
        }
    ],
    "sg:phone":"+1 407 339 5624",
    "sg:postcode":"32751",
    "sg:province":"FL",
    "wof:name":"Caring Legal Nurse Consultants",
    "wof:placetype":"venue"
},
  "geometry": {"coordinates":[-81.336214,28.643964],"type":"Point"}
}