{
  "type": "Feature",
  "properties": {
    "iso:country":"US",
    "sg:address":"3576 NW 32nd St",
    "sg:city":"Miami",
    "sg:classifiers":[
        {
            "category":"Wholesale",
            "subcategory":"Scrap",
            "type":"Manufacturing & Wholesale Goods"
        }
    ],
    "sg:phone":"+1 305 635 7488",
    "sg:postcode":"33142",
    "sg:province":"FL",
    "sg:tags":[
        "metals-wholesale",
        "metal"
    ],
    "wof:name":"On Site Metals Of Florida",
    "wof:placetype":"venue"
},
  "geometry": {"coordinates":[-80.25428599999999,25.804971],"type":"Point"}
}