{
  "type": "Feature",
  "properties": {
    "iso:country":"US",
    "sg:address":"531 NE 39th St",
    "sg:city":"Miami",
    "sg:classifiers":[
        {
            "category":"Professional",
            "subcategory":"Detective & Security Services",
            "type":"Services"
        }
    ],
    "sg:phone":"+1 305 576 8446",
    "sg:postcode":"33137",
    "sg:province":"FL",
    "sg:tags":[
        "control",
        "monitoring",
        "system"
    ],
    "wof:name":"Paradise Park Alarm Line",
    "wof:placetype":"venue"
},
  "geometry": {"coordinates":[-80.188084,25.813396],"type":"Point"}
}