{
  "type": "Feature",
  "properties": {
    "addr:full":"451 Harbor Dr N Indian Rocks Beach FL 33785",
    "addr:housenumber":"451",
    "addr:postcode":"33785",
    "addr:street":"Harbor Dr N",
    "iso:country":"US",
    "sg:address":"451 Harbor Dr N",
    "sg:city":"Indian Rocks Beach",
    "sg:classifiers":[
        {
            "category":"Banks & Credit Unions",
            "subcategory":"Financial Services",
            "type":"Services"
        }
    ],
    "sg:phone":"+1 727 517 8971",
    "sg:postcode":"33785",
    "sg:province":"FL",
    "sg:tags":[
        "investment",
        "closed"
    ],
    "wof:name":"J&A Property Investments Inc",
    "wof:placetype":"venue"
},
  "geometry": {"coordinates":[-82.836108,27.906215],"type":"Point"}
}