{
  "type": "Feature",
  "properties": {
    "iso:country":"US",
    "sg:address":"2000 SW 27th Ave",
    "sg:city":"Miami",
    "sg:classifiers":[
        {
            "category":"Health Services",
            "subcategory":"Doctor",
            "type":"Services"
        }
    ],
    "sg:phone":"+1 305 461 2010",
    "sg:postcode":"33145",
    "sg:province":"FL",
    "wof:name":"Lamas Ana M MD",
    "wof:placetype":"venue"
},
  "geometry": {"coordinates":[-80.23840300000001,25.7526],"type":"Point"}
}