{
  "type": "Feature",
  "properties": {
    "addr:full":"540 McDonald Ave Auburndale FL 33823",
    "addr:housenumber":"540",
    "addr:postcode":"33823",
    "addr:street":"Mcdonald Ave",
    "iso:country":"US",
    "sg:address":"540 McDonald Ave",
    "sg:city":"Auburndale",
    "sg:classifiers":[
        {
            "category":"Professional",
            "subcategory":"Engineering",
            "type":"Services"
        }
    ],
    "sg:phone":"+1 863 551 9365",
    "sg:postcode":"33823",
    "sg:province":"FL",
    "wof:name":"Glt & Associates Finishing",
    "wof:placetype":"venue"
},
  "geometry": {"coordinates":[-81.79597200000001,28.061704],"type":"Point"}
}