{
  "type": "Feature",
  "properties": {
    "addr:full":"9425 Meadowood Dr Fort Pierce FL 34951",
    "addr:housenumber":"9425",
    "addr:postcode":"34951",
    "addr:street":"Meadowood Dr",
    "iso:country":"US",
    "sg:address":"9425 Meadowood Dr",
    "sg:city":"Fort Pierce",
    "sg:classifiers":[
        {
            "category":"Recreation",
            "type":"Entertainment"
        },
        {
            "category":"Shopping",
            "subcategory":"Bicycles & Sporting Goods",
            "type":"Retail Goods"
        }
    ],
    "sg:phone":"+1 772 466 4116",
    "sg:postcode":"34951",
    "sg:province":"FL",
    "sg:tags":[
        "course",
        "golf"
    ],
    "wof:name":"Panther Woods Country Club",
    "wof:placetype":"venue"
},
  "geometry": {"coordinates":[-80.42457899999999,27.488709],"type":"Point"}
}