{
  "type": "Feature",
  "properties": {
    "iso:country":"US",
    "sg:address":"325 W Wade St",
    "sg:city":"Trenton",
    "sg:classifiers":[
        {
            "category":"Health Services",
            "subcategory":"Chiropractor",
            "type":"Services"
        }
    ],
    "sg:phone":"+1 352 463 8120",
    "sg:postcode":"32693",
    "sg:province":"FL",
    "sg:tags":[
        "chiropractic"
    ],
    "wof:name":"Vaughan, Robert L Jr Dc",
    "wof:placetype":"venue"
},
  "geometry": {"coordinates":[-82.82053999999999,29.613365],"type":"Point"}
}