{
  "type": "Feature",
  "properties": {
    "addr:full":"1716 Saint Johns Bluff Rd S Jacksonville FL 32246",
    "addr:housenumber":"1716",
    "addr:postcode":"32246",
    "addr:street":"Saint Johns Bluff Rd",
    "iso:country":"US",
    "sg:address":"1716 Saint Johns Bluff Rd S",
    "sg:city":"Jacksonville",
    "sg:classifiers":[
        {
            "category":"Retail",
            "subcategory":"Repair Shop",
            "type":"Services"
        }
    ],
    "sg:phone":"+1 904 641 9766",
    "sg:postcode":"32246",
    "sg:province":"FL",
    "sg:tags":[
        "welding"
    ],
    "wof:name":"Terry's Welding & Fabrication",
    "wof:placetype":"venue"
},
  "geometry": {"coordinates":[-81.52334999999999,30.32083],"type":"Point"}
}