{
  "type": "Feature",
  "properties": {
    "addr:full":"3528 Thomasville Rd Tallahassee FL 32309",
    "addr:housenumber":"3528",
    "addr:postcode":"32309",
    "addr:street":"Thomasville Rd",
    "iso:country":"US",
    "sg:address":"3528 Thomasville Rd",
    "sg:city":"Tallahassee",
    "sg:classifiers":[
        {
            "category":"Banks & Credit Unions",
            "subcategory":"Bank",
            "type":"Services"
        }
    ],
    "sg:phone":"+1 850 671 0650",
    "sg:postcode":"32309",
    "sg:province":"FL",
    "sg:tags":[
        "state",
        "commercial"
    ],
    "wof:name":"Capital City Bank",
    "wof:placetype":"venue"
},
  "geometry": {"coordinates":[-84.247018,30.51045],"type":"Point"}
}