{
  "type": "Feature",
  "properties": {
    "iso:country":"US",
    "sg:address":"5795 Mining Ter",
    "sg:city":"Jacksonville",
    "sg:classifiers":[
        {
            "category":"Building & Trades",
            "subcategory":"Construction",
            "type":"Services"
        }
    ],
    "sg:phone":"+1 904 739 6047",
    "sg:postcode":"32257",
    "sg:province":"FL",
    "sg:tags":[
        "fire",
        "restoration",
        "damage"
    ],
    "wof:name":"Paul Davis Restoration Of N Fl",
    "wof:placetype":"venue"
},
  "geometry": {"coordinates":[-81.56923,30.184006],"type":"Point"}
}