{
  "type": "Feature",
  "properties": {
    "addr:full":"578 Volusia Ave Daytona Beach FL 32114",
    "addr:housenumber":"578",
    "addr:postcode":"32114",
    "addr:street":"Volusia Ave",
    "iso:country":"US",
    "sg:address":"578 Volusia Ave",
    "sg:city":"Daytona Beach",
    "sg:classifiers":[
        {
            "category":"Shopping",
            "subcategory":"Jewelry",
            "type":"Retail Goods"
        }
    ],
    "sg:phone":"+1 386 255 1948",
    "sg:postcode":"32114",
    "sg:province":"FL",
    "wof:name":"Gordons Jewelers 4257",
    "wof:placetype":"venue"
},
  "geometry": {"coordinates":[-81.027911,29.208832],"type":"Point"}
}