{
  "type": "Feature",
  "properties": {
    "iso:country":"US",
    "sg:address":"3007 5th St",
    "sg:city":"Marianna",
    "sg:classifiers":[
        {
            "category":"Organizations",
            "subcategory":"Religious Organization",
            "type":"Services"
        }
    ],
    "sg:phone":"+1 850 482 3734",
    "sg:postcode":"32446",
    "sg:province":"FL",
    "sg:tags":[
        "church"
    ],
    "wof:name":"St Anne's Catholic Church",
    "wof:placetype":"venue"
},
  "geometry": {"coordinates":[-85.23782199999999,30.783913],"type":"Point"}
}