{
  "type": "Feature",
  "properties": {
    "addr:full":"2349 Ainsworth Ave Deltona FL 32738",
    "addr:housenumber":"2349",
    "addr:postcode":"32738",
    "addr:street":"Ainsworth Ave",
    "iso:country":"US",
    "sg:address":"2349 Ainsworth Ave",
    "sg:city":"Deltona",
    "sg:classifiers":[
        {
            "category":"Building & Trades",
            "subcategory":"Construction",
            "type":"Services"
        }
    ],
    "sg:phone":"+1 386 532 2233",
    "sg:postcode":"32738",
    "sg:province":"FL",
    "sg:tags":[
        "wallcoverings-installation",
        "wallpaper",
        "painting",
        "contractor"
    ],
    "wof:name":"Byron Butler Painting",
    "wof:placetype":"venue"
},
  "geometry": {"coordinates":[-81.177515,28.929011],"type":"Point"}
}