{
  "type": "Feature",
  "properties": {
    "addr:full":"1030 90th Ave Vero Beach FL 32966",
    "addr:housenumber":"1030",
    "addr:postcode":"32966",
    "addr:street":"90Th Ave",
    "iso:country":"US",
    "sg:address":"1030 90th Ave",
    "sg:city":"Vero Beach",
    "sg:classifiers":[
        {
            "category":"Shopping",
            "subcategory":"Florist",
            "type":"Retail Goods"
        }
    ],
    "sg:phone":"+1 772 563 0070",
    "sg:postcode":"32966",
    "sg:province":"FL",
    "wof:name":"Indian River Orchids",
    "wof:placetype":"venue"
},
  "geometry": {"coordinates":[-80.512344,27.61956],"type":"Point"}
}