{
  "type": "Feature",
  "properties": {
    "iso:country":"US",
    "sg:address":"742 SW Hibiscus St",
    "sg:city":"Port Saint Lucie",
    "sg:classifiers":[
        {
            "category":"Building & Trades",
            "subcategory":"Landscaping Services",
            "type":"Services"
        }
    ],
    "sg:phone":"+1 772 873 9406",
    "sg:postcode":"34983",
    "sg:province":"FL",
    "wof:name":"Lawn Care & More",
    "wof:placetype":"venue"
},
  "geometry": {"coordinates":[-80.36118399999999,27.310514],"type":"Point"}
}