{
  "type": "Feature",
  "properties": {
    "iso:country":"US",
    "sg:address":"553 S Duncan Ave",
    "sg:city":"Clearwater",
    "sg:classifiers":[
        {
            "category":"Real Estate",
            "subcategory":"Real Estate Agent",
            "type":"Services"
        }
    ],
    "sg:phone":"+1 727 789 0555",
    "sg:postcode":"33756",
    "sg:province":"FL",
    "wof:name":"Julia Galpin Realty",
    "wof:placetype":"venue"
},
  "geometry": {"coordinates":[-82.766823,27.959788],"type":"Point"}
}