{
  "type": "Feature",
  "properties": {
    "iso:country":"US",
    "sg:address":"2525 N Hiatus Rd",
    "sg:city":"Hollywood",
    "sg:classifiers":[
        {
            "category":"Travel",
            "subcategory":"Travel Agent",
            "type":"Entertainment"
        }
    ],
    "sg:phone":"+1 954 431 7771",
    "sg:postcode":"33026",
    "sg:province":"FL",
    "sg:tags":[
        "agency"
    ],
    "wof:name":"Sunburst Travel Inc",
    "wof:placetype":"venue"
},
  "geometry": {"coordinates":[-80.296734,26.029706],"type":"Point"}
}