{
  "type": "Feature",
  "properties": {
    "addr:full":"4204 N Mac Dill Ave Tampa FL 33607",
    "addr:housenumber":"4204",
    "addr:postcode":"33607",
    "addr:street":"N Mac Dill Ave",
    "iso:country":"US",
    "sg:address":"4204 N Mac Dill Ave",
    "sg:city":"Tampa",
    "sg:classifiers":[
        {
            "category":"Health Services",
            "subcategory":"Clinic",
            "type":"Services"
        }
    ],
    "sg:phone":"+1 813 871 3202",
    "sg:postcode":"33607",
    "sg:province":"FL",
    "sg:tags":[
        "kidney",
        "dialysis",
        "center"
    ],
    "wof:name":"Gambro Hlthcare Ptent Svcs Inc",
    "wof:placetype":"venue"
},
  "geometry": {"coordinates":[-82.493039,27.976964],"type":"Point"}
}