{
  "type": "Feature",
  "properties": {
    "iso:country":"US",
    "sg:address":"1800 W Waters Ave",
    "sg:city":"Tampa",
    "sg:classifiers":[
        {
            "category":"Organizations",
            "subcategory":"Religious Organization",
            "type":"Services"
        }
    ],
    "sg:phone":"+1 813 932 3418",
    "sg:postcode":"33604",
    "sg:province":"FL",
    "sg:tags":[
        "church"
    ],
    "wof:name":"Evangel Tabernacle",
    "wof:placetype":"venue"
},
  "geometry": {"coordinates":[-82.478088,28.025329],"type":"Point"}
}