{
  "type": "Feature",
  "properties": {
    "iso:country":"US",
    "sg:address":"5400 Touchstone Dr",
    "sg:city":"Orlando",
    "sg:classifiers":[
        {
            "category":"Home & Garden",
            "subcategory":"Home Furnishings",
            "type":"Retail Goods"
        }
    ],
    "sg:phone":"+1 407 248 9288",
    "sg:postcode":"32819",
    "sg:province":"FL",
    "sg:tags":[
        "housewares",
        "domestic"
    ],
    "wof:name":"Bed Bath & Beyond Inc",
    "wof:placetype":"venue"
},
  "geometry": {"coordinates":[-81.45041500000001,28.466687],"type":"Point"}
}