{
  "type": "Feature",
  "properties": {
    "addr:full":"12201 Moss Dr Fort Myers FL 33908",
    "addr:housenumber":"12201",
    "addr:postcode":"33908",
    "addr:street":"Moss Dr",
    "iso:country":"US",
    "sg:address":"12201 Moss Dr",
    "sg:city":"Fort Myers",
    "sg:classifiers":[
        {
            "category":"Professional",
            "type":"Services"
        }
    ],
    "sg:phone":"+1 239 454 4751",
    "sg:postcode":"33908",
    "sg:province":"FL",
    "wof:name":"D Dockside Maintence",
    "wof:placetype":"venue"
},
  "geometry": {"coordinates":[-81.952922,26.514926],"type":"Point"}
}