{
  "type": "Feature",
  "properties": {
    "addr:full":"6183 Pinehurst Dr Spring Hill FL 34606",
    "addr:housenumber":"6183",
    "addr:postcode":"34606",
    "addr:street":"Pinehurst Dr",
    "iso:country":"US",
    "sg:address":"6183 Pinehurst Dr",
    "sg:city":"Spring Hill",
    "sg:classifiers":[
        {
            "category":"Shopping",
            "type":"Retail Goods"
        }
    ],
    "sg:phone":"+1 352 686 8028",
    "sg:postcode":"34606",
    "sg:province":"FL",
    "wof:name":"R & R",
    "wof:placetype":"venue"
},
  "geometry": {"coordinates":[-82.616711,28.461857],"type":"Point"}
}