{
  "type": "Feature",
  "properties": {
    "addr:full":"2704 N Howard Ave Tampa FL 33607",
    "addr:housenumber":"2704",
    "addr:postcode":"33607",
    "addr:street":"N Howard Ave",
    "iso:country":"US",
    "sg:address":"2704 N Howard Ave",
    "sg:city":"Tampa",
    "sg:classifiers":[
        {
            "category":"Personal",
            "subcategory":"Beauty Salon",
            "type":"Services"
        }
    ],
    "sg:phone":"+1 813 251 9030",
    "sg:postcode":"33607",
    "sg:province":"FL",
    "wof:name":"Sylvia's Hair Design Studio",
    "wof:placetype":"venue"
},
  "geometry": {"coordinates":[-82.482888,27.965205],"type":"Point"}
}