{
  "type": "Feature",
  "properties": {
    "iso:country":"US",
    "sg:address":"1051 E 52nd St",
    "sg:city":"Hialeah",
    "sg:classifiers":[
        {
            "category":"Retail",
            "subcategory":"Repair Shop",
            "type":"Services"
        }
    ],
    "sg:phone":"+1 305 687 4011",
    "sg:postcode":"33013",
    "sg:province":"FL",
    "sg:tags":[
        "welding"
    ],
    "wof:name":"4101 Shop",
    "wof:placetype":"venue"
},
  "geometry": {"coordinates":[-80.260896,25.869987],"type":"Point"}
}