{
  "type": "Feature",
  "properties": {
    "iso:country":"US",
    "sg:address":"1221 Carolina Ave",
    "sg:city":"St Cloud",
    "sg:classifiers":[
        {
            "category":"Travel",
            "subcategory":"Hotels & Motels",
            "type":"Entertainment"
        }
    ],
    "sg:phone":"+1 407 957 0668",
    "sg:postcode":"34769",
    "sg:province":"FL",
    "wof:name":"Day-Zee Inn",
    "wof:placetype":"venue"
},
  "geometry": {"coordinates":[-81.273354,28.246242],"type":"Point"}
}