{
  "type": "Feature",
  "properties": {
    "iso:country":"US",
    "sg:address":"6121 58th St N",
    "sg:city":"Saint Petersburg",
    "sg:classifiers":[
        {
            "category":"Building & Trades",
            "subcategory":"Construction",
            "type":"Services"
        }
    ],
    "sg:phone":"+1 727 546 8686",
    "sg:postcode":"33709",
    "sg:province":"FL",
    "sg:tags":[
        "contractor"
    ],
    "wof:name":"Delisle Drapery Service",
    "wof:placetype":"venue"
},
  "geometry": {"coordinates":[-82.71225200000001,27.82699],"type":"Point"}
}