{
  "type": "Feature",
  "properties": {
    "addr:full":"10140 Atlantic Blvd Jacksonville FL 32225",
    "addr:housenumber":"10140",
    "addr:postcode":"32225",
    "addr:street":"Atlantic Blvd",
    "iso:country":"US",
    "sg:address":"10140 Atlantic Blvd",
    "sg:city":"Jacksonville",
    "sg:classifiers":[
        {
            "category":"Autos & Motor Vehicles",
            "subcategory":"Boat Sales",
            "type":"Retail Goods"
        }
    ],
    "sg:phone":"+1 904 338 9970",
    "sg:postcode":"32225",
    "sg:province":"FL",
    "wof:name":"Marinemax Southeast Florida",
    "wof:placetype":"venue"
},
  "geometry": {"coordinates":[-81.536986,30.322978],"type":"Point"}
}