{
  "type": "Feature",
  "properties": {
    "addr:full":"13899 Biscayne Blvd Ste 133 North Miami Beach FL 33181",
    "addr:housenumber":"13899",
    "addr:postcode":"33181",
    "addr:street":"Biscayne Blvd Ste 133",
    "iso:country":"US",
    "sg:address":"13899 Biscayne Blvd Ste 133",
    "sg:city":"North Miami Beach",
    "sg:classifiers":[
        {
            "category":"Personal",
            "subcategory":"Hair Removal",
            "type":"Services"
        },
        {
            "category":"Personal",
            "subcategory":"Skin Care",
            "type":"Services"
        }
    ],
    "sg:phone":"+1 954 524 9285",
    "sg:postcode":"33181",
    "sg:province":"FL",
    "sg:website":"www.loriabeauty.com",
    "wof:name":"Loria Beauty",
    "wof:placetype":"venue"
},
  "geometry": {"coordinates":[-80.15825100000001,25.903918],"type":"Point"}
}