{
  "type": "Feature",
  "properties": {
    "iso:country":"US",
    "sg:address":"13375 SW 128th St",
    "sg:city":"Miami",
    "sg:classifiers":[
        {
            "category":"Health Services",
            "subcategory":"Doctor",
            "type":"Services"
        }
    ],
    "sg:phone":"+1 305 255 5106",
    "sg:postcode":"33186",
    "sg:province":"FL",
    "sg:tags":[
        "physician",
        "surgeon"
    ],
    "wof:name":"House Call Doctor-South Fl",
    "wof:placetype":"venue"
},
  "geometry": {"coordinates":[-80.41108199999999,25.648525],"type":"Point"}
}