{
  "type": "Feature",
  "properties": {
    "iso:country":"US",
    "sg:address":"3375 E 4th Ave",
    "sg:city":"Hialeah",
    "sg:classifiers":[
        {
            "category":"Wholesale",
            "subcategory":"Auto Parts",
            "type":"Manufacturing & Wholesale Goods"
        }
    ],
    "sg:phone":"+1 305 694 0177",
    "sg:postcode":"33013",
    "sg:province":"FL",
    "sg:tags":[
        "tire"
    ],
    "wof:name":"Boris Tires",
    "wof:placetype":"venue"
},
  "geometry": {"coordinates":[-80.27480300000001,25.8528],"type":"Point"}
}