{
  "type": "Feature",
  "properties": {
    "iso:country":"US",
    "sg:address":"20533 Biscayne Blvd",
    "sg:city":"Miami",
    "sg:classifiers":[
        {
            "category":"Professional",
            "subcategory":"Computer Services",
            "type":"Services"
        }
    ],
    "sg:phone":"+1 305 216 0277",
    "sg:postcode":"33180",
    "sg:province":"FL",
    "sg:tags":[
        "prepackaged",
        "software"
    ],
    "wof:name":"Intouch Customer Software",
    "wof:placetype":"venue"
},
  "geometry": {"coordinates":[-80.145946,25.966192],"type":"Point"}
}