{
  "type": "Feature",
  "properties": {
    "iso:country":"US",
    "sg:address":"315 S B St",
    "sg:city":"Pensacola",
    "sg:classifiers":[
        {
            "category":"Restaurant",
            "type":"Food & Drink"
        }
    ],
    "sg:phone":"+1 850 438 9712",
    "sg:postcode":"32501",
    "sg:province":"FL",
    "sg:tags":[
        "eating",
        "caterer"
    ],
    "wof:name":"Charlie's Eatery & Catering",
    "wof:placetype":"venue"
},
  "geometry": {"coordinates":[-87.227619,30.406369],"type":"Point"}
}