{
  "type": "Feature",
  "properties": {
    "addr:full":"400 N Ashley Dr Tampa FL 33602",
    "addr:housenumber":"400",
    "addr:postcode":"33602",
    "addr:street":"N Ashley Dr",
    "iso:country":"US",
    "sg:address":"400 N Ashley Dr",
    "sg:city":"Tampa",
    "sg:classifiers":[
        {
            "category":"Professional",
            "subcategory":"Accounting & Tax Preparation",
            "type":"Services"
        }
    ],
    "sg:phone":"+1 813 223 5577",
    "sg:postcode":"33602",
    "sg:province":"FL",
    "sg:tags":[
        "accountant"
    ],
    "wof:name":"Wheeler Herman Harvey & Lagor",
    "wof:placetype":"venue"
},
  "geometry": {"coordinates":[-82.45999999999999,27.947827],"type":"Point"}
}