{
  "type": "Feature",
  "properties": {
    "iso:country":"US",
    "sg:address":"6827 E Hwy 22",
    "sg:city":"Panama City",
    "sg:classifiers":[
        {
            "category":"Government",
            "subcategory":"Post Office",
            "type":"Public Place"
        }
    ],
    "sg:phone":"+1 850 000 1111",
    "sg:postcode":"32404",
    "sg:province":"FL",
    "wof:name":"US Post Office",
    "wof:placetype":"venue"
},
  "geometry": {"coordinates":[-85.572186,30.152993],"type":"Point"}
}