{
  "type": "Feature",
  "properties": {
    "addr:full":"1005 SW 2 Ave Gainesville FL 32601",
    "addr:housenumber":"1005",
    "addr:postcode":"32601",
    "addr:street":"Sw 2 Ave",
    "iso:country":"US",
    "sg:address":"1005 SW 2 Ave",
    "sg:city":"Gainesville",
    "sg:classifiers":[
        {
            "category":"Professional",
            "subcategory":"Lawyer & Legal Services",
            "type":"Services"
        }
    ],
    "sg:phone":"+1 352 375 9041",
    "sg:postcode":"32601",
    "sg:province":"FL",
    "wof:name":"Skipper and Day",
    "wof:placetype":"venue"
},
  "geometry": {"coordinates":[-82.33709,29.650182],"type":"Point"}
}