{
  "type": "Feature",
  "properties": {
    "iso:country":"US",
    "sg:address":"4125 Cleveland Ave",
    "sg:city":"Fort Myers",
    "sg:classifiers":[
        {
            "category":"Professional",
            "subcategory":"Business Services",
            "type":"Services"
        }
    ],
    "sg:phone":"+1 239 275 0908",
    "sg:postcode":"33901",
    "sg:province":"FL",
    "sg:tags":[
        "fabric",
        "store",
        "embroidery"
    ],
    "wof:name":"Stitch by Stitch",
    "wof:placetype":"venue"
},
  "geometry": {"coordinates":[-81.871544,26.602743],"type":"Point"}
}