{
  "type": "Feature",
  "properties": {
    "iso:country":"US",
    "sg:address":"1504 W Bearss Ave",
    "sg:city":"Tampa",
    "sg:classifiers":[
        {
            "category":"Wholesale",
            "subcategory":"Machinery & Supplies",
            "type":"Manufacturing & Wholesale Goods"
        }
    ],
    "sg:phone":"+1 813 866 8000",
    "sg:postcode":"33613",
    "sg:province":"FL",
    "sg:tags":[
        "instrument",
        "surveying"
    ],
    "wof:name":"International Surveying Equip",
    "wof:placetype":"venue"
},
  "geometry": {"coordinates":[-82.47739199999999,28.089541],"type":"Point"}
}