{
  "type": "Feature",
  "properties": {
    "iso:country":"US",
    "sg:address":"866 SE Damask Ave",
    "sg:city":"Port Saint Lucie",
    "sg:classifiers":[
        {
            "category":"Building & Trades",
            "subcategory":"Construction",
            "type":"Services"
        }
    ],
    "sg:phone":"+1 772 340 3352",
    "sg:postcode":"34983",
    "sg:province":"FL",
    "sg:tags":[
        "house",
        "contractor"
    ],
    "wof:name":"Oasis General Contracting",
    "wof:placetype":"venue"
},
  "geometry": {"coordinates":[-80.32589400000001,27.293048],"type":"Point"}
}