{
  "type": "Feature",
  "properties": {
    "iso:country":"US",
    "sg:address":"8429 Tuttle Ave",
    "sg:city":"Sarasota",
    "sg:classifiers":[
        {
            "category":"Food & Beverages",
            "subcategory":"Liquor & Beverages",
            "type":"Retail Goods"
        }
    ],
    "sg:phone":"+1 941 360 3018",
    "sg:postcode":"34243",
    "sg:province":"FL",
    "sg:tags":[
        "alcoholic"
    ],
    "wof:name":"University Liquor & Wine Inc",
    "wof:placetype":"venue"
},
  "geometry": {"coordinates":[-82.513756,27.390969],"type":"Point"}
}