{
  "type": "Feature",
  "properties": {
    "addr:full":"2600 Harden Blvd Lakeland FL 33803",
    "addr:housenumber":"2600",
    "addr:postcode":"33803",
    "addr:street":"Harden Blvd",
    "iso:country":"US",
    "sg:address":"2600 Harden Blvd",
    "sg:city":"Lakeland",
    "sg:classifiers":[
        {
            "category":"Shopping",
            "subcategory":"Clothing, Apparel, & Fashions",
            "type":"Retail Goods"
        }
    ],
    "sg:phone":"+1 863 682 7485",
    "sg:postcode":"33803",
    "sg:province":"FL",
    "sg:tags":[
        "alteration"
    ],
    "wof:name":"S R Davis",
    "wof:placetype":"venue"
},
  "geometry": {"coordinates":[-81.97359299999999,28.018627],"type":"Point"}
}