{
  "type": "Feature",
  "properties": {
    "iso:country":"US",
    "sg:address":"16456 Rainbow Meadows Ct",
    "sg:city":"Fort Myers",
    "sg:classifiers":[
        {
            "category":"Building & Trades",
            "subcategory":"Construction",
            "type":"Services"
        }
    ],
    "sg:phone":"+1 239 433 5490",
    "sg:postcode":"33908",
    "sg:province":"FL",
    "sg:tags":[
        "screen",
        "subcontractor",
        "enclosure"
    ],
    "wof:name":"Ted Watts Construction Inc",
    "wof:placetype":"venue"
},
  "geometry": {"coordinates":[-81.90703600000001,26.504637],"type":"Point"}
}