{
  "type": "Feature",
  "properties": {
    "iso:country":"US",
    "sg:address":"5440 N State Rd 7",
    "sg:city":"Fort Lauderdale",
    "sg:classifiers":[
        {
            "category":"Professional",
            "subcategory":"Accounting & Tax Preparation",
            "type":"Services"
        }
    ],
    "sg:phone":"+1 954 739 5438",
    "sg:postcode":"33319",
    "sg:province":"FL",
    "sg:tags":[
        "return",
        "filing"
    ],
    "wof:name":"Abaco Financial & Tax Svc",
    "wof:placetype":"venue"
},
  "geometry": {"coordinates":[-80.20376400000001,26.192745],"type":"Point"}
}