{
  "type": "Feature",
  "properties": {
    "iso:country":"US",
    "sg:address":"3481 NW 44th St",
    "sg:city":"Fort Lauderdale",
    "sg:classifiers":[
        {
            "category":"Real Estate",
            "subcategory":"Real Estate Operator",
            "type":"Services"
        }
    ],
    "sg:phone":"+1 954 733 8424",
    "sg:postcode":"33309",
    "sg:province":"FL",
    "sg:tags":[
        "building",
        "apartment"
    ],
    "wof:name":"Summer Lake Apartments",
    "wof:placetype":"venue"
},
  "geometry": {"coordinates":[-80.195232,26.180195],"type":"Point"}
}