{
  "type": "Feature",
  "properties": {
    "addr:full":"2000 Dundee Rd Winter Haven FL 33884",
    "addr:housenumber":"2000",
    "addr:postcode":"33884",
    "addr:street":"Dundee Rd",
    "iso:country":"US",
    "sg:address":"2000 Dundee Rd",
    "sg:city":"Winter Haven",
    "sg:classifiers":[
        {
            "category":"Building & Trades",
            "subcategory":"Pest Control",
            "type":"Services"
        }
    ],
    "sg:phone":"+1 863 291 4370",
    "sg:postcode":"33884",
    "sg:province":"FL",
    "sg:tags":[
        "farm",
        "sp",
        "animal",
        "supply"
    ],
    "wof:name":"Honey Hut",
    "wof:placetype":"venue"
},
  "geometry": {"coordinates":[-81.694762,28.022412],"type":"Point"}
}