{
  "type": "Feature",
  "properties": {
    "iso:country":"US",
    "sg:address":"1728 NW 9th Ave",
    "sg:city":"Okeechobee",
    "sg:classifiers":[
        {
            "category":"Health Services",
            "subcategory":"Doctor",
            "type":"Services"
        }
    ],
    "sg:phone":"+1 863 467 7477",
    "sg:postcode":"34972",
    "sg:province":"FL",
    "sg:tags":[
        "clinic"
    ],
    "wof:name":"Planned Parenthood",
    "wof:placetype":"venue"
},
  "geometry": {"coordinates":[-80.83797199999999,27.262221],"type":"Point"}
}