{
  "type": "Feature",
  "properties": {
    "iso:country":"US",
    "sg:address":"4350 66th St N",
    "sg:city":"Saint Petersburg",
    "sg:classifiers":[
        {
            "category":"Restaurant",
            "type":"Food & Drink"
        }
    ],
    "sg:menulink":"http://www.allmenus.com/fl/st-petersburg/37775-pizza-hut/menu/",
    "sg:phone":"+1 727 544 4000",
    "sg:postcode":"33709",
    "sg:province":"FL",
    "sg:tags":[
        "american",
        "pizza"
    ],
    "wof:name":"Pizza Hut",
    "wof:placetype":"venue"
},
  "geometry": {"coordinates":[-82.72868,27.811697],"type":"Point"}
}