{
  "type": "Feature",
  "properties": {
    "addr:full":"1630 Broadway Riviera Beach FL 33404",
    "addr:housenumber":"1630",
    "addr:postcode":"33404",
    "addr:street":"Broadway",
    "iso:country":"US",
    "sg:address":"1630 Broadway",
    "sg:city":"Riviera Beach",
    "sg:classifiers":[
        {
            "category":"Personal",
            "subcategory":"Beauty Salon",
            "type":"Services"
        }
    ],
    "sg:phone":"+1 561 848 1967",
    "sg:postcode":"33404",
    "sg:province":"FL",
    "wof:name":"Yesmine Unisex Salon",
    "wof:placetype":"venue"
},
  "geometry": {"coordinates":[-80.05488200000001,26.776797],"type":"Point"}
}