{
  "type": "Feature",
  "properties": {
    "addr:full":"7200 Alvina Way Orlando FL 32822",
    "addr:postcode":"7200;32822",
    "addr:street":"Alvina Way",
    "iso:country":"US",
    "sg:address":"7200 Alvina Way",
    "sg:city":"Orlando",
    "sg:classifiers":[
        {
            "category":"Wholesale",
            "subcategory":"Construction Materials",
            "type":"Manufacturing & Wholesale Goods"
        },
        {
            "category":"Home & Garden",
            "subcategory":"Building Materials",
            "type":"Retail Goods"
        }
    ],
    "sg:phone":"+1 407 702 4142",
    "sg:postcode":"32822",
    "sg:province":"FL",
    "sg:tags":[
        "windows-wholesale",
        "window",
        "manufacturer"
    ],
    "wof:name":"Knight Windows & Doors, Inc",
    "wof:placetype":"venue"
},
  "geometry": {"coordinates":[-81.290722,28.518559],"type":"Point"}
}