{
  "type": "Feature",
  "properties": {
    "addr:full":"1720 Cox Rd Cocoa FL 32926",
    "addr:housenumber":"1720",
    "addr:postcode":"32926",
    "addr:street":"Cox Rd",
    "iso:country":"US",
    "sg:address":"1720 Cox Rd",
    "sg:city":"Cocoa",
    "sg:classifiers":[
        {
            "category":"Organizations",
            "subcategory":"Religious Organization",
            "type":"Services"
        }
    ],
    "sg:phone":"+1 321 638 0890",
    "sg:postcode":"32926",
    "sg:province":"FL",
    "sg:tags":[
        "church"
    ],
    "sg:website":"www.nwbcofcocoa.org",
    "wof:name":"Northwest Baptist Church",
    "wof:placetype":"venue"
},
  "geometry": {"coordinates":[-80.78792900000001,28.388634],"type":"Point"}
}