{
  "type": "Feature",
  "properties": {
    "addr:full":"2115 2nd St Lee FL 32060",
    "addr:housenumber":"2115",
    "addr:postcode":"32060",
    "addr:street":"2Nd St",
    "iso:country":"US",
    "sg:address":"2115 2nd St",
    "sg:city":"Lee",
    "sg:classifiers":[
        {
            "category":"Government",
            "subcategory":"Office",
            "type":"Public Place"
        }
    ],
    "sg:phone":"+1 239 335 2221",
    "sg:postcode":"32060",
    "sg:province":"FL",
    "sg:tags":[
        "executive"
    ],
    "wof:name":"Admin County",
    "wof:placetype":"venue"
},
  "geometry": {"coordinates":[-83.008854,30.307888],"type":"Point"}
}