{
  "type": "Feature",
  "properties": {
    "addr:full":"370 NE 97th St Miami FL 33138",
    "addr:housenumber":"370",
    "addr:postcode":"33138",
    "addr:street":"Ne 97Th St",
    "iso:country":"US",
    "sg:address":"370 NE 97th St",
    "sg:city":"Miami",
    "sg:classifiers":[
        {
            "category":"Professional",
            "type":"Services"
        }
    ],
    "sg:phone":"+1 305 633 5622",
    "sg:postcode":"33138",
    "sg:province":"FL",
    "wof:name":"Resurrections Inc",
    "wof:placetype":"venue"
},
  "geometry": {"coordinates":[-80.190712,25.864393],"type":"Point"}
}