{
  "type": "Feature",
  "properties": {
    "iso:country":"US",
    "sg:address":"2920 Lowell Ct",
    "sg:city":"Casselberry",
    "sg:classifiers":[
        {
            "category":"Professional",
            "subcategory":"Management & Consulting",
            "type":"Services"
        }
    ],
    "sg:phone":"+1 407 388 1811",
    "sg:postcode":"32707",
    "sg:province":"FL",
    "sg:tags":[
        "public",
        "relations"
    ],
    "wof:name":"Wyche & Associates",
    "wof:placetype":"venue"
},
  "geometry": {"coordinates":[-81.307241,28.648951],"type":"Point"}
}