{
  "type": "Feature",
  "properties": {
    "iso:country":"US",
    "sg:address":"3100 Country Club Ln",
    "sg:city":"Hallandale",
    "sg:classifiers":[
        {
            "category":"Retail",
            "subcategory":"Funeral Services",
            "type":"Services"
        }
    ],
    "sg:phone":"+1 954 322 8400",
    "sg:postcode":"33009",
    "sg:province":"FL",
    "sg:tags":[
        "director"
    ],
    "wof:name":"Willow Cove Funeral Home",
    "wof:placetype":"venue"
},
  "geometry": {"coordinates":[-80.166645,25.974038],"type":"Point"}
}