{
  "type": "Feature",
  "properties": {
    "iso:country":"US",
    "sg:address":"927 Hickory St",
    "sg:city":"Altamonte Spgs",
    "sg:classifiers":[
        {
            "category":"Building & Trades",
            "subcategory":"Construction",
            "type":"Services"
        }
    ],
    "sg:phone":"+1 407 260 2800",
    "sg:postcode":"32701",
    "sg:province":"FL",
    "sg:tags":[
        "enclosure",
        "pool",
        "swimming"
    ],
    "sg:website":"www.floridapoolscreens.com",
    "wof:name":"Florida Pool Enclosures Inc",
    "wof:placetype":"venue"
},
  "geometry": {"coordinates":[-81.359842,28.673029],"type":"Point"}
}