{
  "type": "Feature",
  "properties": {
    "iso:country":"US",
    "sg:address":"7300 NW 19th St",
    "sg:city":"Miami",
    "sg:classifiers":[
        {
            "category":"Professional",
            "subcategory":"Management & Consulting",
            "type":"Services"
        }
    ],
    "sg:phone":"+1 305 715 6100",
    "sg:postcode":"33126",
    "sg:province":"FL",
    "sg:tags":[
        "fuel"
    ],
    "wof:name":"Lincoln Re Risk Management",
    "wof:placetype":"venue"
},
  "geometry": {"coordinates":[-80.317446,25.79107],"type":"Point"}
}