{
  "type": "Feature",
  "properties": {
    "addr:full":"697 Vistawilla Dr Winter Springs FL 32708",
    "addr:housenumber":"697",
    "addr:postcode":"32708",
    "addr:street":"Vistawilla Dr",
    "iso:country":"US",
    "sg:address":"697 Vistawilla Dr",
    "sg:city":"Winter Springs",
    "sg:classifiers":[
        {
            "category":"Building & Trades",
            "subcategory":"Cleaning & Sanitation",
            "type":"Services"
        }
    ],
    "sg:phone":"+1 407 366 2222",
    "sg:postcode":"32708",
    "sg:province":"FL",
    "sg:tags":[
        "carpet"
    ],
    "wof:name":"Discount Carpet Cleaning Plus",
    "wof:placetype":"venue"
},
  "geometry": {"coordinates":[-81.24045599999999,28.683007],"type":"Point"}
}