{
  "type": "Feature",
  "properties": {
    "iso:country":"US",
    "sg:address":"1660 Medical Blvd",
    "sg:city":"Naples",
    "sg:classifiers":[
        {
            "category":"Health Services",
            "subcategory":"Doctor",
            "type":"Services"
        }
    ],
    "sg:phone":"+1 239 596 1995",
    "sg:postcode":"34110",
    "sg:province":"FL",
    "sg:tags":[
        "physician",
        "surgeon",
        "medical"
    ],
    "wof:name":"Francisco A Smith MD PA",
    "wof:placetype":"venue"
},
  "geometry": {"coordinates":[-81.789025,26.27363],"type":"Point"}
}