{
  "type": "Feature",
  "properties": {
    "addr:full":"3535 NW 60th St Miami FL 33142",
    "addr:housenumber":"3535",
    "addr:postcode":"33142",
    "addr:street":"Nw 60Th St",
    "iso:country":"US",
    "sg:address":"3535 NW 60th St",
    "sg:city":"Miami",
    "sg:classifiers":[
        {
            "category":"Manufacturing",
            "subcategory":"Chemicals & Compounds",
            "type":"Manufacturing & Wholesale Goods"
        }
    ],
    "sg:phone":"+1 305 638 5006",
    "sg:postcode":"33142",
    "sg:province":"FL",
    "sg:tags":[
        "lithographing",
        "ink"
    ],
    "wof:name":"KOHL & Madden",
    "wof:placetype":"venue"
},
  "geometry": {"coordinates":[-80.256677,25.828996],"type":"Point"}
}