{
  "type": "Feature",
  "properties": {
    "iso:country":"US",
    "sg:address":"6157 NW 167th St",
    "sg:city":"Hialeah",
    "sg:classifiers":[
        {
            "category":"Professional",
            "type":"Services"
        }
    ],
    "sg:phone":"+1 786 639 0041",
    "sg:postcode":"33015",
    "sg:province":"FL",
    "sg:tags":[
        "establishment"
    ],
    "wof:name":"Simg Technologies",
    "wof:placetype":"venue"
},
  "geometry": {"coordinates":[-80.304258,25.925207],"type":"Point"}
}