{
  "type": "Feature",
  "properties": {
    "addr:full":"3948 W Fieldwood Ct Lecanto FL 34461",
    "addr:housenumber":"3948",
    "addr:postcode":"34461",
    "addr:street":"W Fieldwood Ct",
    "iso:country":"US",
    "sg:address":"3948 W Fieldwood Ct",
    "sg:city":"Lecanto",
    "sg:classifiers":[
        {
            "category":"Building & Trades",
            "subcategory":"Construction",
            "type":"Services"
        }
    ],
    "sg:phone":"+1 352 726 5337",
    "sg:postcode":"34461",
    "sg:province":"FL",
    "sg:tags":[
        "house",
        "ma"
    ],
    "wof:name":"Bart Howard Inc",
    "wof:placetype":"venue"
},
  "geometry": {"coordinates":[-82.499185,28.844508],"type":"Point"}
}