{
  "type": "Feature",
  "properties": {
    "iso:country":"US",
    "sg:address":"21 Oscar Hill Rd",
    "sg:city":"Tarpon Springs",
    "sg:classifiers":[
        {
            "category":"Retail",
            "subcategory":"Auto Repair",
            "type":"Services"
        }
    ],
    "sg:phone":"+1 727 772 7474",
    "sg:postcode":"34689",
    "sg:province":"FL",
    "sg:tags":[
        "automotive"
    ],
    "wof:name":"Window Tint By Matt & Ed",
    "wof:placetype":"venue"
},
  "geometry": {"coordinates":[-82.759049,28.159106],"type":"Point"}
}