{
  "type": "Feature",
  "properties": {
    "addr:full":"1098 NE Kubin Ave Jensen Beach FL 34957",
    "addr:housenumber":"1098",
    "addr:postcode":"34957",
    "addr:street":"Ne Kubin Ave",
    "iso:country":"US",
    "sg:address":"1098 NE Kubin Ave",
    "sg:city":"Jensen Beach",
    "sg:classifiers":[
        {
            "category":"Utilities",
            "subcategory":"Refuse",
            "type":"Services"
        }
    ],
    "sg:phone":"+1 772 466 4004",
    "sg:postcode":"34957",
    "sg:province":"FL",
    "sg:tags":[
        "system"
    ],
    "wof:name":"Freedom Waste Services Corp",
    "wof:placetype":"venue"
},
  "geometry": {"coordinates":[-80.241765,27.218392],"type":"Point"}
}