{
  "type": "Feature",
  "properties": {
    "addr:full":"320 Main St Dunedin FL 34698",
    "addr:housenumber":"320",
    "addr:postcode":"34698",
    "addr:street":"Main St",
    "iso:country":"US",
    "sg:address":"320 Main St",
    "sg:city":"Dunedin",
    "sg:classifiers":[
        {
            "category":"Shopping",
            "subcategory":"Clothing, Apparel, & Fashions",
            "type":"Retail Goods"
        }
    ],
    "sg:phone":"+1 727 736 6565",
    "sg:postcode":"34698",
    "sg:province":"FL",
    "wof:name":"Cassi & Co",
    "wof:placetype":"venue"
},
  "geometry": {"coordinates":[-82.78909299999999,28.012034],"type":"Point"}
}