{
  "type": "Feature",
  "properties": {
    "addr:full":"611 Babcock Ave Lake Wales FL 33853",
    "addr:housenumber":"611",
    "addr:postcode":"33853",
    "addr:street":"Babcock Ave",
    "iso:country":"US",
    "sg:address":"611 Babcock Ave",
    "sg:city":"Lake Wales",
    "sg:classifiers":[
        {
            "category":"Shopping",
            "subcategory":"Clothing, Apparel, & Fashions",
            "type":"Retail Goods"
        }
    ],
    "sg:phone":"+1 863 676 7579",
    "sg:postcode":"33853",
    "sg:province":"FL",
    "wof:name":"Design Fashions By Alice",
    "wof:placetype":"venue"
},
  "geometry": {"coordinates":[-81.608474,27.916255],"type":"Point"}
}