{
  "type": "Feature",
  "properties": {
    "iso:country":"US",
    "sg:address":"1814 SW 22nd Ave",
    "sg:city":"Miami",
    "sg:classifiers":[
        {
            "category":"Restaurant",
            "type":"Food & Drink"
        }
    ],
    "sg:phone":"+1 305 856 8505",
    "sg:postcode":"33145",
    "sg:province":"FL",
    "sg:tags":[
        "italian"
    ],
    "wof:name":"Fresco Pizza Italian Food",
    "wof:placetype":"venue"
},
  "geometry": {"coordinates":[-80.230304,25.755096],"type":"Point"}
}