{
  "type": "Feature",
  "properties": {
    "iso:country":"US",
    "sg:address":"3094 NW 27th Ave",
    "sg:city":"Miami",
    "sg:classifiers":[
        {
            "category":"Autos & Motor Vehicles",
            "subcategory":"Auto Supplies",
            "type":"Retail Goods"
        }
    ],
    "sg:phone":"+1 305 633 4501",
    "sg:postcode":"33142",
    "sg:province":"FL",
    "sg:tags":[
        "tire"
    ],
    "wof:name":"Highspeed",
    "wof:placetype":"venue"
},
  "geometry": {"coordinates":[-80.239998,25.8043],"type":"Point"}
}