{
  "type": "Feature",
  "properties": {
    "iso:country":"US",
    "sg:address":"14417 Hanging Moss Cir",
    "sg:city":"Tampa",
    "sg:classifiers":[
        {
            "category":"Restaurant",
            "type":"Food & Drink"
        }
    ],
    "sg:phone":"+1 813 978 0868",
    "sg:postcode":"33613",
    "sg:province":"FL",
    "wof:name":"Cody's Restaurant",
    "wof:placetype":"venue"
},
  "geometry": {"coordinates":[-82.412902,28.077233],"type":"Point"}
}