{
  "type": "Feature",
  "properties": {
    "addr:full":"623 E Atlantic Blvd Pompano Beach FL 33060",
    "addr:housenumber":"623",
    "addr:postcode":"33060",
    "addr:street":"E Atlantic Blvd",
    "iso:country":"US",
    "sg:address":"623 E Atlantic Blvd",
    "sg:city":"Pompano Beach",
    "sg:classifiers":[
        {
            "category":"Professional",
            "subcategory":"Business Services",
            "type":"Services"
        }
    ],
    "sg:phone":"+1 954 942 0521",
    "sg:postcode":"33060",
    "sg:province":"FL",
    "sg:tags":[
        "water",
        "treatment"
    ],
    "wof:name":"TDI Processing Of S Florida",
    "wof:placetype":"venue"
},
  "geometry": {"coordinates":[-80.116832,26.231757],"type":"Point"}
}