{
  "type": "Feature",
  "properties": {
    "iso:country":"US",
    "sg:address":"781 SW 75th Ter",
    "sg:city":"Fort Lauderdale",
    "sg:classifiers":[
        {
            "category":"Airline",
            "type":"Transportation"
        }
    ],
    "sg:phone":"+1 954 584 6254",
    "sg:postcode":"33317",
    "sg:province":"FL",
    "sg:tags":[
        "courier",
        "air"
    ],
    "wof:name":"Aarons Aviation & Imaging",
    "wof:placetype":"venue"
},
  "geometry": {"coordinates":[-80.249539,26.113805],"type":"Point"}
}