{
  "type": "Feature",
  "properties": {
    "iso:country":"US",
    "sg:address":"16201 SW 88th St",
    "sg:city":"Miami",
    "sg:classifiers":[
        {
            "category":"Restaurant",
            "type":"Food & Drink"
        }
    ],
    "sg:phone":"+1 305 752 1877",
    "sg:postcode":"33196",
    "sg:province":"FL",
    "sg:tags":[
        "chicken",
        "mexican"
    ],
    "sg:website":"http://www.pollotropical.com",
    "wof:name":"Pollo Tropical",
    "wof:placetype":"venue"
},
  "geometry": {"coordinates":[-80.454048,25.6842],"type":"Point"}
}