{
  "type": "Feature",
  "properties": {
    "addr:full":"2139 S Ridgewood Ave South Daytona FL 32119",
    "addr:housenumber":"2139",
    "addr:postcode":"32119",
    "addr:street":"S Ridgewood Ave South",
    "iso:country":"US",
    "sg:address":"2139 S Ridgewood Ave",
    "sg:city":"South Daytona",
    "sg:classifiers":[
        {
            "category":"Personal",
            "subcategory":"Beauty Salon",
            "type":"Services"
        }
    ],
    "sg:phone":"+1 386 756 1751",
    "sg:postcode":"32119",
    "sg:province":"FL",
    "wof:name":"Anita Simon",
    "wof:placetype":"venue"
},
  "geometry": {"coordinates":[-81.00226000000001,29.172199],"type":"Point"}
}