{
  "type": "Feature",
  "properties": {
    "iso:country":"US",
    "sg:address":"15901 SW 177th Ave",
    "sg:city":"Miami",
    "sg:classifiers":[
        {
            "category":"Wholesale",
            "subcategory":"Plants",
            "type":"Manufacturing & Wholesale Goods"
        }
    ],
    "sg:phone":"+1 305 251 5844",
    "sg:postcode":"33187",
    "sg:province":"FL",
    "sg:tags":[
        "nursery",
        "tree"
    ],
    "wof:name":"Benjamina Nursery",
    "wof:placetype":"venue"
},
  "geometry": {"coordinates":[-80.479249,25.617959],"type":"Point"}
}