{
  "type": "Feature",
  "properties": {
    "addr:full":"808 SE 12th Ct Fort Lauderdale FL 33316",
    "addr:housenumber":"808",
    "addr:postcode":"33316",
    "addr:street":"Se 12Th Ct",
    "iso:country":"US",
    "sg:address":"808 SE 12th Ct",
    "sg:city":"Fort Lauderdale",
    "sg:classifiers":[
        {
            "category":"Organizations",
            "subcategory":"Community Association",
            "type":"Services"
        }
    ],
    "sg:phone":"+1 954 728 9568",
    "sg:postcode":"33316",
    "sg:province":"FL",
    "wof:name":"Fireside Twnhomes Condominiums",
    "wof:placetype":"venue"
},
  "geometry": {"coordinates":[-80.133999,26.106731],"type":"Point"}
}