{
  "type": "Feature",
  "properties": {
    "iso:country":"US",
    "sg:address":"3401 Lake Tiny Cir",
    "sg:city":"Orlando",
    "sg:classifiers":[
        {
            "category":"Social Services",
            "subcategory":"Child Care",
            "type":"Services"
        }
    ],
    "sg:phone":"+1 407 299 8095",
    "sg:postcode":"32818",
    "sg:province":"FL",
    "sg:tags":[
        "day"
    ],
    "wof:name":"Family Daycare",
    "wof:placetype":"venue"
},
  "geometry": {"coordinates":[-81.47136399999999,28.587212],"type":"Point"}
}