{
  "type": "Feature",
  "properties": {
    "iso:country":"US",
    "sg:address":"8393 Blountstown Hwy",
    "sg:city":"Tallahassee",
    "sg:classifiers":[
        {
            "category":"Personal",
            "subcategory":"Beauty Salon",
            "type":"Services"
        }
    ],
    "sg:phone":"+1 850 576 9927",
    "sg:postcode":"32310",
    "sg:province":"FL",
    "sg:tags":[
        "hair",
        "stylist"
    ],
    "wof:name":"Judy's Hair Styling",
    "wof:placetype":"venue"
},
  "geometry": {"coordinates":[-84.41891200000001,30.442617],"type":"Point"}
}