{
  "type": "Feature",
  "properties": {
    "iso:country":"US",
    "sg:address":"2100 E Oakland Park Blvd",
    "sg:city":"Fort Lauderdale",
    "sg:classifiers":[
        {
            "category":"Restaurant",
            "type":"Food & Drink"
        }
    ],
    "sg:phone":"+1 954 566 5226",
    "sg:postcode":"33306",
    "sg:province":"FL",
    "sg:tags":[
        "eating"
    ],
    "wof:name":"Umberto's Restaurant & Pizza",
    "wof:placetype":"venue"
},
  "geometry": {"coordinates":[-80.119658,26.167195],"type":"Point"}
}