{
  "type": "Feature",
  "properties": {
    "addr:full":"2234 Weston Rd Fort Lauderdale FL 33326",
    "addr:housenumber":"2234",
    "addr:postcode":"33326",
    "addr:street":"Weston Rd",
    "iso:country":"US",
    "sg:address":"2234 Weston Rd",
    "sg:city":"Fort Lauderdale",
    "sg:classifiers":[
        {
            "category":"Manufacturing",
            "subcategory":"Tools & Machinery",
            "type":"Manufacturing & Wholesale Goods"
        }
    ],
    "sg:phone":"+1 954 217 3991",
    "sg:postcode":"33326",
    "sg:province":"FL",
    "sg:tags":[
        "mfg",
        "ophthalmic"
    ],
    "wof:name":"Shwake Enterprises Inc",
    "wof:placetype":"venue"
},
  "geometry": {"coordinates":[-80.371743,26.090396],"type":"Point"}
}