{
  "type": "Feature",
  "properties": {
    "addr:full":"10238 Evergreen Hill Dr Tampa FL 33647",
    "addr:housenumber":"10238",
    "addr:postcode":"33647",
    "addr:street":"Evergreen Hill Dr",
    "iso:country":"US",
    "sg:address":"10238 Evergreen Hill Dr",
    "sg:city":"Tampa",
    "sg:classifiers":[
        {
            "category":"Health Services",
            "subcategory":"Medical Lab",
            "type":"Services"
        }
    ],
    "sg:phone":"+1 813 907 3833",
    "sg:postcode":"33647",
    "sg:province":"FL",
    "sg:tags":[
        "laboratory",
        "dental"
    ],
    "wof:name":"Ross Dental Studio",
    "wof:placetype":"venue"
},
  "geometry": {"coordinates":[-82.32191400000001,28.131318],"type":"Point"}
}