{
  "type": "Feature",
  "properties": {
    "iso:country":"US",
    "sg:address":"196 SW 22nd Rd",
    "sg:city":"Miami",
    "sg:classifiers":[
        {
            "category":"Building & Trades",
            "subcategory":"Locksmith",
            "type":"Services"
        }
    ],
    "sg:phone":"+1 305 390 0279",
    "sg:postcode":"33129",
    "sg:province":"FL",
    "sg:tags":[
        "key"
    ],
    "wof:name":"Aabc Locksmith 24 7",
    "wof:placetype":"venue"
},
  "geometry": {"coordinates":[-80.203828,25.756369],"type":"Point"}
}