{
  "type": "Feature",
  "properties": {
    "addr:full":"14365 SW 119th Ave Miami FL 33186",
    "addr:housenumber":"14365",
    "addr:postcode":"33186",
    "addr:street":"Sw 119Th Ave",
    "iso:country":"US",
    "sg:address":"14365 SW 119th Ave",
    "sg:city":"Miami",
    "sg:classifiers":[
        {
            "category":"Home & Garden",
            "subcategory":"Hardware",
            "type":"Retail Goods"
        }
    ],
    "sg:phone":"+1 305 969 8470",
    "sg:postcode":"33186",
    "sg:province":"FL",
    "sg:tags":[
        "closet",
        "accessory"
    ],
    "wof:name":"The Closet Factory",
    "wof:placetype":"venue"
},
  "geometry": {"coordinates":[-80.386821,25.63466],"type":"Point"}
}