{
  "type": "Feature",
  "properties": {
    "iso:country":"US",
    "sg:address":"5015 Crill Ave",
    "sg:city":"Palatka",
    "sg:classifiers":[
        {
            "category":"Shopping",
            "subcategory":"Florist",
            "type":"Retail Goods"
        }
    ],
    "sg:phone":"+1 386 328 3583",
    "sg:postcode":"32177",
    "sg:province":"FL",
    "wof:name":"Flowers By Louis",
    "wof:placetype":"venue"
},
  "geometry": {"coordinates":[-81.68157100000001,29.641178],"type":"Point"}
}