{
  "type": "Feature",
  "properties": {
    "iso:country":"US",
    "sg:address":"1275 S Broadway Ave",
    "sg:city":"Bartow",
    "sg:classifiers":[
        {
            "category":"Education",
            "subcategory":"School",
            "type":"Public Place"
        }
    ],
    "sg:phone":"+1 863 534 7450",
    "sg:postcode":"33830",
    "sg:province":"FL",
    "wof:name":"Bartow Adult School",
    "wof:placetype":"venue"
},
  "geometry": {"coordinates":[-81.84312799999999,27.878819],"type":"Point"}
}