{
  "type": "Feature",
  "properties": {
    "iso:country":"US",
    "sg:address":"15 S Golfview Rd",
    "sg:city":"Lake Worth",
    "sg:classifiers":[
        {
            "category":"Recreation",
            "type":"Entertainment"
        }
    ],
    "sg:phone":"+1 561 547 0681",
    "sg:postcode":"33460",
    "sg:province":"FL",
    "sg:tags":[
        "guide"
    ],
    "wof:name":"Riggins Too",
    "wof:placetype":"venue"
},
  "geometry": {"coordinates":[-80.04853,26.6146],"type":"Point"}
}