{
  "type": "Feature",
  "properties": {
    "iso:country":"US",
    "sg:address":"2198 Princeton St",
    "sg:city":"Sarasota",
    "sg:classifiers":[
        {
            "category":"Wholesale",
            "subcategory":"Machinery & Supplies",
            "type":"Manufacturing & Wholesale Goods"
        }
    ],
    "sg:phone":"+1 941 954 5922",
    "sg:postcode":"34237",
    "sg:province":"FL",
    "sg:tags":[
        "industrial"
    ],
    "wof:name":"Evoclix",
    "wof:placetype":"venue"
},
  "geometry": {"coordinates":[-82.528285,27.346377],"type":"Point"}
}