{
  "type": "Feature",
  "properties": {
    "iso:country":"US",
    "sg:address":"4611 N Pearl St",
    "sg:city":"Jacksonville",
    "sg:classifiers":[
        {
            "category":"Place Of Worship",
            "type":"Public Place"
        }
    ],
    "sg:phone":"+1 904 354 7426",
    "sg:postcode":"32206",
    "sg:province":"FL",
    "sg:tags":[
        "church"
    ],
    "wof:name":"Central Metropolitan Christian Methodist Episcopal Church",
    "wof:placetype":"venue"
},
  "geometry": {"coordinates":[-81.656616,30.366741],"type":"Point"}
}