{
  "type": "Feature",
  "properties": {
    "iso:country":"US",
    "sg:address":"109 S Pressview Ave",
    "sg:city":"Longwood",
    "sg:classifiers":[
        {
            "category":"Social Services",
            "subcategory":"Child Care",
            "type":"Services"
        }
    ],
    "sg:phone":"+1 407 830 1655",
    "sg:postcode":"32750",
    "sg:province":"FL",
    "sg:tags":[
        "day"
    ],
    "wof:name":"Baby Days Infant Care Inc",
    "wof:placetype":"venue"
},
  "geometry": {"coordinates":[-81.37779999999999,28.6968],"type":"Point"}
}