{
  "type": "Feature",
  "properties": {
    "iso:country":"US",
    "sg:address":"113 Bailey Dr",
    "sg:city":"Niceville",
    "sg:classifiers":[
        {
            "category":"Building & Trades",
            "subcategory":"Construction",
            "type":"Services"
        }
    ],
    "sg:phone":"+1 850 729 0014",
    "sg:postcode":"32578",
    "sg:province":"FL",
    "sg:tags":[
        "contractor"
    ],
    "wof:name":"Jorgensen Contract Svc",
    "wof:placetype":"venue"
},
  "geometry": {"coordinates":[-86.465422,30.515465],"type":"Point"}
}