{
  "type": "Feature",
  "properties": {
    "addr:full":"4601 Saufley Field Rd Pensacola FL 32526",
    "addr:housenumber":"4601",
    "addr:postcode":"32526",
    "addr:street":"Saufley Field Rd",
    "iso:country":"US",
    "sg:address":"4601 Saufley Field Rd",
    "sg:city":"Pensacola",
    "sg:classifiers":[
        {
            "category":"Manufacturing",
            "subcategory":"Buildings",
            "type":"Manufacturing & Wholesale Goods"
        },
        {
            "category":"Building & Trades",
            "subcategory":"Construction",
            "type":"Services"
        }
    ],
    "sg:phone":"+1 850 341 2452",
    "sg:postcode":"32526",
    "sg:province":"FL",
    "sg:tags":[
        "home",
        "builder",
        "industrial",
        "contractors-commercial",
        "contractor"
    ],
    "wof:name":"Jimmie Shane Murphy",
    "wof:placetype":"venue"
},
  "geometry": {"coordinates":[-87.305351,30.46121],"type":"Point"}
}