{
  "type": "Feature",
  "properties": {
    "iso:country":"US",
    "sg:address":"1130 Ponce de Leon Blvd",
    "sg:city":"Clearwater",
    "sg:classifiers":[
        {
            "category":"Health Services",
            "subcategory":"Doctor",
            "type":"Services"
        }
    ],
    "sg:phone":"+1 727 581 4800",
    "sg:postcode":"33756",
    "sg:province":"FL",
    "sg:tags":[
        "clinic"
    ],
    "wof:name":"Belleair Surgery Ctr",
    "wof:placetype":"venue"
},
  "geometry": {"coordinates":[-82.797881,27.935223],"type":"Point"}
}