{
  "type": "Feature",
  "properties": {
    "iso:country":"US",
    "sg:address":"1200 Vermont Ave",
    "sg:city":"St Cloud",
    "sg:classifiers":[
        {
            "category":"Education",
            "subcategory":"School",
            "type":"Public Place"
        }
    ],
    "sg:phone":"+1 407 891 3160",
    "sg:postcode":"34769",
    "sg:province":"FL",
    "sg:website":"www.osceola.k12.fl.us",
    "wof:name":"Ross E Jeffries Elementary",
    "wof:placetype":"venue"
},
  "geometry": {"coordinates":[-81.29252099999999,28.247031],"type":"Point"}
}