{
  "type": "Feature",
  "properties": {
    "iso:country":"US",
    "sg:address":"6538 Collins Ave Ste 395",
    "sg:city":"Miami Beach",
    "sg:classifiers":[
        {
            "category":"Social Services",
            "subcategory":"Job Training",
            "type":"Services"
        }
    ],
    "sg:phone":"+1 305 867 7770",
    "sg:postcode":"33140",
    "sg:province":"FL",
    "sg:tags":[
        "career",
        "counseling"
    ],
    "sg:website":"www.tab-southbroward.com/TAB-Sbr...",
    "wof:name":"The Alternative Board",
    "wof:placetype":"venue"
},
  "geometry": {"coordinates":[-80.120679,25.848726],"type":"Point"}
}