{
  "type": "Feature",
  "properties": {
    "addr:full":"1420 S Florida Ave Lakeland FL 33803",
    "addr:housenumber":"1420",
    "addr:postcode":"33803",
    "addr:street":"S Florida Ave",
    "iso:country":"US",
    "sg:address":"1420 S Florida Ave",
    "sg:city":"Lakeland",
    "sg:classifiers":[
        {
            "category":"Real Estate",
            "subcategory":"Real Estate Operator",
            "type":"Services"
        }
    ],
    "sg:phone":"+1 863 687 8020",
    "sg:postcode":"33803",
    "sg:province":"FL",
    "sg:tags":[
        "building",
        "apartment"
    ],
    "wof:name":"Hidden Oaks of Central FL",
    "wof:placetype":"venue"
},
  "geometry": {"coordinates":[-81.957024,28.026451],"type":"Point"}
}