{
  "type": "Feature",
  "properties": {
    "addr:full":"7148 Curry Ford Rd Orlando FL 32822",
    "addr:housenumber":"7148",
    "addr:postcode":"32822",
    "addr:street":"Curry Ford Rd",
    "iso:country":"US",
    "sg:address":"7148 Curry Ford Rd",
    "sg:city":"Orlando",
    "sg:classifiers":[
        {
            "category":"Health Services",
            "subcategory":"Podiatrist",
            "type":"Services"
        }
    ],
    "sg:phone":"+1 407 275 5440",
    "sg:postcode":"32822",
    "sg:province":"FL",
    "sg:tags":[
        "physician",
        "surgeons"
    ],
    "sg:website":"http://www.orlandofootandankle.com",
    "wof:name":"Moats David B Dpm",
    "wof:placetype":"venue"
},
  "geometry": {"coordinates":[-81.29190699999999,28.516618],"type":"Point"}
}