{
  "type": "Feature",
  "properties": {
    "iso:country":"US",
    "sg:address":"8625 Stirling Rd",
    "sg:city":"Cooper City",
    "sg:classifiers":[
        {
            "category":"Shopping",
            "subcategory":"Pharmacy",
            "type":"Retail Goods"
        }
    ],
    "sg:phone":"+1 954 252 7488",
    "sg:postcode":"33328",
    "sg:province":"FL",
    "sg:tags":[
        "photofinishing",
        "laboratory"
    ],
    "sg:website":"www.walgreens.com",
    "wof:name":"Walgreens",
    "wof:placetype":"venue"
},
  "geometry": {"coordinates":[-80.26555,26.045147],"type":"Point"}
}