{
  "type": "Feature",
  "properties": {
    "iso:country":"US",
    "sg:address":"6123 Phillips Hwy",
    "sg:city":"Jacksonville",
    "sg:classifiers":[
        {
            "category":"Retail",
            "subcategory":"Repair Shop",
            "type":"Services"
        },
        {
            "category":"Shopping",
            "subcategory":"Computers & Home Electronics",
            "type":"Retail Goods"
        },
        {
            "category":"Manufacturing",
            "subcategory":"Motor Vehicles & Parts",
            "type":"Manufacturing & Wholesale Goods"
        },
        {
            "category":"Professional",
            "subcategory":"Printing & Photocopies",
            "type":"Services"
        },
        {
            "category":"Shopping",
            "subcategory":"Stationery & Office Supplies",
            "type":"Retail Goods"
        },
        {
            "category":"Manufacturing",
            "subcategory":"Printing",
            "type":"Manufacturing & Wholesale Goods"
        }
    ],
    "sg:phone":"+1 904 739 0540",
    "sg:postcode":"32207",
    "sg:province":"FL",
    "sg:tags":[
        "renting",
        "fax",
        "leasing",
        "form",
        "copier",
        "printers-business",
        "machine",
        "equipment",
        "copy",
        "supplies-wholesale",
        "manufacturer"
    ],
    "sg:website":"http://www.sissines.com",
    "wof:name":"Sissines Office Systems",
    "wof:placetype":"venue"
},
  "geometry": {"coordinates":[-81.642872,30.301314],"type":"Point"}
}