{
  "type": "Feature",
  "properties": {
    "iso:country":"US",
    "sg:address":"2100 Bruton Blvd",
    "sg:city":"Orlando",
    "sg:classifiers":[
        {
            "category":"Banks & Credit Unions",
            "subcategory":"Bank",
            "type":"Services"
        }
    ],
    "sg:phone":"+1 407 650 0606",
    "sg:postcode":"32805",
    "sg:province":"FL",
    "sg:tags":[
        "loan",
        "real estate"
    ],
    "wof:name":"Rappahannock Equity Group Inc",
    "wof:placetype":"venue"
},
  "geometry": {"coordinates":[-81.426053,28.513835],"type":"Point"}
}