{
  "type": "Feature",
  "properties": {
    "addr:full":"1515 Cricket Club Cir # 305 Orlando FL 32828",
    "addr:housenumber":"1515",
    "addr:postcode":"32828",
    "addr:street":"Club Cir # 305",
    "iso:country":"US",
    "sg:address":"1515 Cricket Club Cir # 305",
    "sg:city":"Orlando",
    "sg:classifiers":[
        {
            "category":"Manufacturing",
            "subcategory":"Food",
            "type":"Manufacturing & Wholesale Goods"
        },
        {
            "category":"Food & Beverages",
            "subcategory":"Groceries & Convenience Stores",
            "type":"Retail Goods"
        }
    ],
    "sg:phone":"+1 917 515 5341",
    "sg:postcode":"32828",
    "sg:province":"FL",
    "sg:tags":[
        "product"
    ],
    "wof:name":"La Mont's Bar & Grill",
    "wof:placetype":"venue"
},
  "geometry": {"coordinates":[-81.19811300000001,28.562142],"type":"Point"}
}