{
  "type": "Feature",
  "properties": {
    "iso:country":"US",
    "sg:address":"10971 NW 3rd St",
    "sg:city":"Plantation",
    "sg:classifiers":[
        {
            "category":"Freight",
            "type":"Transportation"
        }
    ],
    "sg:phone":"+1 954 915 9877",
    "sg:postcode":"33324",
    "sg:province":"FL",
    "sg:tags":[
        "broker",
        "trucking"
    ],
    "wof:name":"American Logistics USA",
    "wof:placetype":"venue"
},
  "geometry": {"coordinates":[-80.29571199999999,26.123737],"type":"Point"}
}