{
  "type": "Feature",
  "properties": {
    "addr:full":"2801 John Anderson Hwy Flagler Beach FL 32136",
    "addr:housenumber":"2801",
    "addr:postcode":"32136",
    "addr:street":"John Anderson Hwy Flagler",
    "iso:country":"US",
    "sg:address":"2801 John Anderson Hwy",
    "sg:city":"Flagler Beach",
    "sg:classifiers":[
        {
            "category":"Real Estate",
            "subcategory":"Real Estate Agent",
            "type":"Services"
        }
    ],
    "sg:phone":"+1 386 437 3787",
    "sg:postcode":"32136",
    "sg:province":"FL",
    "sg:tags":[
        "management"
    ],
    "wof:name":"Von Bulow Property Management",
    "wof:placetype":"venue"
},
  "geometry": {"coordinates":[-81.135621,29.452245],"type":"Point"}
}