{
  "type": "Feature",
  "properties": {
    "addr:full":"624 Renaissance Pointe Altamonte Springs FL 32714",
    "addr:housenumber":"624",
    "addr:postcode":"32714",
    "addr:street":"Renaissance Pointe Altamonte Springs",
    "iso:country":"US",
    "sg:address":"624 Renaissance Pointe",
    "sg:city":"Altamonte Springs",
    "sg:classifiers":[
        {
            "category":"Wholesale",
            "subcategory":"Home Furnishings",
            "type":"Manufacturing & Wholesale Goods"
        }
    ],
    "sg:phone":"+1 407 532 5304",
    "sg:postcode":"32714",
    "sg:province":"FL",
    "wof:name":"Jose L Orlandini",
    "wof:placetype":"venue"
},
  "geometry": {"coordinates":[-81.41717800000001,28.646686],"type":"Point"}
}