{
  "type": "Feature",
  "properties": {
    "iso:country":"US",
    "sg:address":"14100 SW 152nd Pl",
    "sg:city":"Miami",
    "sg:classifiers":[
        {
            "category":"Real Estate",
            "subcategory":"Developer",
            "type":"Services"
        }
    ],
    "sg:phone":"+1 305 252 9092",
    "sg:postcode":"33196",
    "sg:province":"FL",
    "wof:name":"GBP Development Corp",
    "wof:placetype":"venue"
},
  "geometry": {"coordinates":[-80.44098,25.635911],"type":"Point"}
}