{
  "type": "Feature",
  "properties": {
    "addr:full":"3434 Dr Martin Luther King Jr Dr Pensacola FL 32503",
    "addr:housenumber":"3434",
    "addr:postcode":"32503",
    "addr:street":"Dr Martin Luther King Jr Dr",
    "iso:country":"US",
    "sg:address":"3434 Dr Martin Luther King Jr Dr",
    "sg:city":"Pensacola",
    "sg:classifiers":[
        {
            "category":"Taxi",
            "type":"Transportation"
        },
        {
            "category":"Airport",
            "type":"Transportation"
        }
    ],
    "sg:phone":"+1 850 433 3333",
    "sg:postcode":"32503",
    "sg:province":"FL",
    "wof:name":"Tucker Transportation",
    "wof:placetype":"venue"
},
  "geometry": {"coordinates":[-87.216916,30.447202],"type":"Point"}
}