{
  "type": "Feature",
  "properties": {
    "addr:full":"7737 NW 197th St Hialeah FL 33015",
    "addr:housenumber":"7737",
    "addr:postcode":"33015",
    "addr:street":"Nw 197Th St",
    "iso:country":"US",
    "sg:address":"7737 NW 197th St",
    "sg:city":"Hialeah",
    "sg:classifiers":[
        {
            "category":"Personal",
            "type":"Services"
        },
        {
            "category":"Professional",
            "subcategory":"Art Services",
            "type":"Services"
        }
    ],
    "sg:phone":"+1 305 816 7626",
    "sg:postcode":"33015",
    "sg:province":"FL",
    "sg:tags":[
        "photography",
        "videography",
        "wedding"
    ],
    "wof:name":"Studio 2.8 Photography, Inc",
    "wof:placetype":"venue"
},
  "geometry": {"coordinates":[-80.32781900000001,25.952299],"type":"Point"}
}