{
  "type": "Feature",
  "properties": {
    "addr:full":"3401 NW 18th Ave Miami FL 33142",
    "addr:housenumber":"3401",
    "addr:postcode":"33142",
    "addr:street":"Nw 18Th Ave",
    "iso:country":"US",
    "sg:address":"3401 NW 18th Ave",
    "sg:city":"Miami",
    "sg:classifiers":[
        {
            "category":"Food & Beverages",
            "subcategory":"Groceries & Convenience Stores",
            "type":"Retail Goods"
        }
    ],
    "sg:phone":"+1 305 634 4492",
    "sg:postcode":"33142",
    "sg:province":"FL",
    "wof:name":"Winn-Dixie Stores Inc",
    "wof:placetype":"venue"
},
  "geometry": {"coordinates":[-80.225886,25.808584],"type":"Point"}
}