{
  "type": "Feature",
  "properties": {
    "iso:country":"US",
    "sg:address":"75 E Broadway St",
    "sg:city":"Fort Meade",
    "sg:classifiers":[
        {
            "category":"Education",
            "subcategory":"Library",
            "type":"Public Place"
        }
    ],
    "sg:phone":"+1 863 285 8287",
    "sg:postcode":"33841",
    "sg:province":"FL",
    "sg:tags":[
        "executive"
    ],
    "wof:name":"Fort Meade Public Library",
    "wof:placetype":"venue"
},
  "geometry": {"coordinates":[-81.801098,27.752073],"type":"Point"}
}