{
  "type": "Feature",
  "properties": {
    "addr:full":"10701 N Kendall Dr Miami FL 33176",
    "addr:housenumber":"10701",
    "addr:postcode":"33176",
    "addr:street":"N Kendall Dr",
    "iso:country":"US",
    "sg:address":"10701 N Kendall Dr",
    "sg:city":"Miami",
    "sg:classifiers":[
        {
            "category":"Autos & Motor Vehicles",
            "subcategory":"Auto Supplies",
            "type":"Retail Goods"
        }
    ],
    "sg:phone":"+1 305 598 8526",
    "sg:postcode":"33176",
    "sg:province":"FL",
    "sg:tags":[
        "glass"
    ],
    "sg:website":"www.safelite.com",
    "wof:name":"Safelite Auto Glass",
    "wof:placetype":"venue"
},
  "geometry": {"coordinates":[-80.366501,25.686899],"type":"Point"}
}