{
  "type": "Feature",
  "properties": {
    "iso:country":"US",
    "sg:address":"1310 W Charter St",
    "sg:city":"Tampa",
    "sg:classifiers":[
        {
            "category":"Insurance",
            "subcategory":"Insurance Agent",
            "type":"Services"
        }
    ],
    "sg:phone":"+1 813 277 9888",
    "sg:postcode":"33602",
    "sg:province":"FL",
    "wof:name":"Mark Katz PA",
    "wof:placetype":"venue"
},
  "geometry": {"coordinates":[-82.478646,27.970208],"type":"Point"}
}