{
  "type": "Feature",
  "properties": {
    "addr:full":"3046 Shell Mound Blvd Fort Myers Beach FL 33931",
    "addr:housenumber":"3046",
    "addr:postcode":"33931",
    "addr:street":"Shell Mound Blvd",
    "iso:country":"US",
    "sg:address":"3046 Shell Mound Blvd",
    "sg:city":"Fort Myers Beach",
    "sg:classifiers":[
        {
            "category":"Building & Trades",
            "subcategory":"Electrical",
            "type":"Services"
        }
    ],
    "sg:phone":"+1 239 463 7300",
    "sg:postcode":"33931",
    "sg:province":"FL",
    "sg:tags":[
        "electrical",
        "electric",
        "contractor"
    ],
    "wof:name":"M D Electric",
    "wof:placetype":"venue"
},
  "geometry": {"coordinates":[-81.93240900000001,26.445929],"type":"Point"}
}