{
  "type": "Feature",
  "properties": {
    "iso:country":"US",
    "sg:address":"1033 18th St",
    "sg:city":"Orlando",
    "sg:classifiers":[
        {
            "category":"Building & Trades",
            "subcategory":"Construction",
            "type":"Services"
        }
    ],
    "sg:phone":"+1 407 426 7475",
    "sg:postcode":"32805",
    "sg:province":"FL",
    "sg:tags":[
        "contractor"
    ],
    "wof:name":"Al Kubaisi Tile Co",
    "wof:placetype":"venue"
},
  "geometry": {"coordinates":[-81.39664500000001,28.522837],"type":"Point"}
}