{
  "type": "Feature",
  "properties": {
    "addr:full":"8795 NW 27th Ave Miami FL 33147",
    "addr:housenumber":"8795",
    "addr:postcode":"33147",
    "addr:street":"Nw 27Th Ave",
    "iso:country":"US",
    "sg:address":"8795 NW 27th Ave",
    "sg:city":"Miami",
    "sg:classifiers":[
        {
            "category":"Shopping",
            "subcategory":"Used Merchandise",
            "type":"Retail Goods"
        }
    ],
    "sg:phone":"+1 305 836 9956",
    "sg:postcode":"33147",
    "sg:province":"FL",
    "wof:name":"Free Pond",
    "wof:placetype":"venue"
},
  "geometry": {"coordinates":[-80.24194900000001,25.854227],"type":"Point"}
}