{
  "type": "Feature",
  "properties": {
    "iso:country":"US",
    "sg:address":"10350 NW 112th Ave",
    "sg:city":"Medley",
    "sg:classifiers":[
        {
            "category":"Real Estate",
            "subcategory":"Real Estate Services",
            "type":"Services"
        }
    ],
    "sg:phone":"+1 305 863 6615",
    "sg:postcode":"33178",
    "sg:province":"FL",
    "wof:name":"Codina Real Estate",
    "wof:placetype":"venue"
},
  "geometry": {"coordinates":[-80.368202,25.825199],"type":"Point"}
}