{
  "type": "Feature",
  "properties": {
    "addr:full":"15171 SW 109th Ter Miami FL 33196",
    "addr:housenumber":"15171",
    "addr:postcode":"33196",
    "addr:street":"Sw 109Th Ter",
    "iso:country":"US",
    "sg:address":"15171 SW 109th Ter",
    "sg:city":"Miami",
    "sg:classifiers":[
        {
            "category":"Building & Trades",
            "subcategory":"Cleaning & Sanitation",
            "type":"Services"
        }
    ],
    "sg:phone":"+1 305 380 1455",
    "sg:postcode":"33196",
    "sg:province":"FL",
    "sg:tags":[
        "janitor",
        "maintenance"
    ],
    "wof:name":"AFA Cleaning Service Corp",
    "wof:placetype":"venue"
},
  "geometry": {"coordinates":[-80.44031200000001,25.664709],"type":"Point"}
}