{
  "type": "Feature",
  "properties": {
    "iso:country":"US",
    "sg:address":"8121 Canaveral Blvd",
    "sg:city":"Cape Canaveral",
    "sg:classifiers":[
        {
            "category":"Shopping",
            "subcategory":"Florist",
            "type":"Retail Goods"
        }
    ],
    "sg:phone":"+1 321 783 4600",
    "sg:postcode":"32920",
    "sg:province":"FL",
    "wof:name":"Cape Florist Inc",
    "wof:placetype":"venue"
},
  "geometry": {"coordinates":[-80.604193,28.39255],"type":"Point"}
}