{
  "type": "Feature",
  "properties": {
    "addr:full":"1755 N Broadway Ave Bartow FL 33830",
    "addr:housenumber":"1755",
    "addr:postcode":"33830",
    "addr:street":"N Broadway Ave",
    "iso:country":"US",
    "sg:address":"1755 N Broadway Ave",
    "sg:city":"Bartow",
    "sg:classifiers":[
        {
            "category":"Retail",
            "subcategory":"Auto Rental",
            "type":"Services"
        }
    ],
    "sg:phone":"+1 863 533 5167",
    "sg:postcode":"33830",
    "sg:province":"FL",
    "sg:tags":[
        "passenger",
        "car"
    ],
    "wof:name":"Enterprise Rent-A-Car",
    "wof:placetype":"venue"
},
  "geometry": {"coordinates":[-81.843531,27.910542],"type":"Point"}
}