{
  "type": "Feature",
  "properties": {
    "iso:country":"US",
    "sg:address":"13890 NW 6th Ct",
    "sg:city":"North Miami",
    "sg:classifiers":[
        {
            "category":"Retail",
            "subcategory":"Auto Rental",
            "type":"Services"
        }
    ],
    "sg:phone":"+1 305 688 2288",
    "sg:postcode":"33168",
    "sg:province":"FL",
    "sg:tags":[
        "renting",
        "automobile"
    ],
    "wof:name":"Miami Limo & Car Rental Sales",
    "wof:placetype":"venue"
},
  "geometry": {"coordinates":[-80.210509,25.90178],"type":"Point"}
}