{
  "type": "Feature",
  "properties": {
    "addr:full":"352 Jasmine Rd Saint Augustine FL 32086",
    "addr:housenumber":"352",
    "addr:postcode":"32086",
    "addr:street":"Jasmine Rd",
    "iso:country":"US",
    "sg:address":"352 Jasmine Rd",
    "sg:city":"Saint Augustine",
    "sg:classifiers":[
        {
            "category":"Building & Trades",
            "subcategory":"Pest Control",
            "type":"Services"
        }
    ],
    "sg:phone":"+1 904 794 0957",
    "sg:postcode":"32086",
    "sg:province":"FL",
    "wof:name":"Pest Extinction Services",
    "wof:placetype":"venue"
},
  "geometry": {"coordinates":[-81.31651100000001,29.836403],"type":"Point"}
}