{
  "type": "Feature",
  "properties": {
    "addr:full":"3960 SW 8th St Coral Gables FL 33134",
    "addr:housenumber":"3960",
    "addr:postcode":"33134",
    "addr:street":"Sw 8Th St",
    "iso:country":"US",
    "sg:address":"3960 SW 8th St",
    "sg:city":"Coral Gables",
    "sg:classifiers":[
        {
            "category":"Food & Beverages",
            "subcategory":"Groceries & Convenience Stores",
            "type":"Retail Goods"
        }
    ],
    "sg:phone":"+1 305 446 1533",
    "sg:postcode":"33134",
    "sg:province":"FL",
    "sg:website":"www.7-eleven.com",
    "wof:name":"7-Eleven Food Stores",
    "wof:placetype":"venue"
},
  "geometry": {"coordinates":[-80.260597,25.764601],"type":"Point"}
}