{
  "type": "Feature",
  "properties": {
    "iso:country":"US",
    "sg:address":"14206 Manatee Springs Rd",
    "sg:city":"Orlando",
    "sg:classifiers":[
        {
            "category":"Shopping",
            "subcategory":"Gifts & Souvenirs",
            "type":"Retail Goods"
        }
    ],
    "sg:phone":"+1 407 509 2185",
    "sg:postcode":"32828",
    "sg:province":"FL",
    "wof:name":"Power Card Inc",
    "wof:placetype":"venue"
},
  "geometry": {"coordinates":[-81.13937199999999,28.51558],"type":"Point"}
}