{
  "type": "Feature",
  "properties": {
    "addr:full":"538 Sabal Palm Dr West Palm Beach FL 33403",
    "addr:housenumber":"538",
    "addr:postcode":"33403",
    "addr:street":"Sabal Palm Dr",
    "iso:country":"US",
    "sg:address":"538 Sabal Palm Dr",
    "sg:city":"West Palm Beach",
    "sg:classifiers":[
        {
            "category":"Travel",
            "subcategory":"Travel Agent",
            "type":"Entertainment"
        }
    ],
    "sg:phone":"+1 561 844 6109",
    "sg:postcode":"33403",
    "sg:province":"FL",
    "sg:tags":[
        "agency"
    ],
    "wof:name":"Visions of Travel",
    "wof:placetype":"venue"
},
  "geometry": {"coordinates":[-80.063441,26.805482],"type":"Point"}
}