{
  "type": "Feature",
  "properties": {
    "addr:full":"1830 del Prado Blvd S Cape Coral FL 33990",
    "addr:housenumber":"1830",
    "addr:postcode":"33990",
    "addr:street":"Del Prado Blvd S",
    "iso:country":"US",
    "sg:address":"1830 del Prado Blvd S",
    "sg:city":"Cape Coral",
    "sg:classifiers":[
        {
            "category":"Retail",
            "subcategory":"Repair Shop",
            "type":"Services"
        }
    ],
    "sg:phone":"+1 239 772 0011",
    "sg:postcode":"33990",
    "sg:province":"FL",
    "sg:tags":[
        "electrical"
    ],
    "wof:name":"Coastal Appliance Service",
    "wof:placetype":"venue"
},
  "geometry": {"coordinates":[-81.940853,26.619769],"type":"Point"}
}