{
  "type": "Feature",
  "properties": {
    "iso:country":"US",
    "sg:address":"229 Saint Joe Plaza Rd",
    "sg:city":"Palm Coast",
    "sg:classifiers":[
        {
            "category":"Arts & Performance",
            "subcategory":"Theater",
            "type":"Entertainment"
        }
    ],
    "sg:phone":"+1 386 446 6414",
    "sg:postcode":"32164",
    "sg:province":"FL",
    "wof:name":"Picture Show III Of Palm Coast",
    "wof:placetype":"venue"
},
  "geometry": {"coordinates":[-81.255763,29.55251],"type":"Point"}
}