{
  "type": "Feature",
  "properties": {
    "iso:country":"US",
    "sg:address":"135 Cumberland Park Dr",
    "sg:city":"St Augustine",
    "sg:classifiers":[
        {
            "category":"Wholesale",
            "subcategory":"Construction Materials",
            "type":"Manufacturing & Wholesale Goods"
        }
    ],
    "sg:phone":"+1 904 826 3353",
    "sg:postcode":"32095",
    "sg:province":"FL",
    "sg:tags":[
        "marble"
    ],
    "wof:name":"Integrity Marble & Granite",
    "wof:placetype":"venue"
},
  "geometry": {"coordinates":[-81.48706799999999,30.073039],"type":"Point"}
}