{
  "type": "Feature",
  "properties": {
    "iso:country":"US",
    "sg:address":"31201 State Hwy 44",
    "sg:city":"Eustis",
    "sg:classifiers":[
        {
            "category":"Wholesale",
            "subcategory":"Auto Parts",
            "type":"Manufacturing & Wholesale Goods"
        }
    ],
    "sg:phone":"+1 352 589 4134",
    "sg:postcode":"32736",
    "sg:province":"FL",
    "sg:tags":[
        "used"
    ],
    "wof:name":"Buds Auto Parts",
    "wof:placetype":"venue"
},
  "geometry": {"coordinates":[-81.439677,28.931371],"type":"Point"}
}