{
  "type": "Feature",
  "properties": {
    "addr:full":"14747 Baltusrol Dr Orlando FL 32828",
    "addr:housenumber":"14747",
    "addr:postcode":"32828",
    "addr:street":"Baltusrol Dr",
    "iso:country":"US",
    "sg:address":"14747 Baltusrol Dr",
    "sg:city":"Orlando",
    "sg:classifiers":[
        {
            "category":"Utilities",
            "subcategory":"Natural Gas",
            "type":"Services"
        },
        {
            "category":"Organizations",
            "subcategory":"Religious Organization",
            "type":"Services"
        }
    ],
    "sg:phone":"+1 407 234 0270",
    "sg:postcode":"32828",
    "sg:province":"FL",
    "sg:tags":[
        "firework",
        "fireworks-public",
        "display"
    ],
    "wof:name":"Creative Pyrotechnics",
    "wof:placetype":"venue"
},
  "geometry": {"coordinates":[-81.169515,28.532181],"type":"Point"}
}