{
  "type": "Feature",
  "properties": {
    "addr:full":"421 W Robinson St Orlando FL 32801",
    "addr:housenumber":"421",
    "addr:postcode":"32801",
    "addr:street":"W Robinson St",
    "iso:country":"US",
    "sg:address":"421 W Robinson St",
    "sg:city":"Orlando",
    "sg:classifiers":[
        {
            "category":"Real Estate",
            "subcategory":"Developer",
            "type":"Services"
        }
    ],
    "sg:phone":"+1 407 256 7839",
    "sg:postcode":"32801",
    "sg:province":"FL",
    "wof:name":"Urban Development Co",
    "wof:placetype":"venue"
},
  "geometry": {"coordinates":[-81.38458300000001,28.545691],"type":"Point"}
}