{
  "type": "Feature",
  "properties": {
    "addr:full":"18470 SW 206th St Miami FL 33187",
    "addr:housenumber":"18470",
    "addr:postcode":"33187",
    "addr:street":"Sw 206Th St",
    "iso:country":"US",
    "sg:address":"18470 SW 206th St",
    "sg:city":"Miami",
    "sg:classifiers":[
        {
            "category":"Shopping",
            "subcategory":"Crafts & Fabrics",
            "type":"Retail Goods"
        }
    ],
    "sg:phone":"+1 305 238 5615",
    "sg:postcode":"33187",
    "sg:province":"FL",
    "sg:tags":[
        "supplies-wholesale",
        "florists'",
        "manufacturer"
    ],
    "wof:name":"Mislow Orchids",
    "wof:placetype":"venue"
},
  "geometry": {"coordinates":[-80.491004,25.574101],"type":"Point"}
}