{
  "type": "Feature",
  "properties": {
    "addr:full":"1938 Laurel St Sarasota FL 34236",
    "addr:housenumber":"1938",
    "addr:postcode":"34236",
    "addr:street":"Laurel St",
    "iso:country":"US",
    "sg:address":"1938 Laurel St",
    "sg:city":"Sarasota",
    "sg:classifiers":[
        {
            "category":"Shopping",
            "subcategory":"Music",
            "type":"Retail Goods"
        }
    ],
    "sg:phone":"+1 941 316 1043",
    "sg:postcode":"34236",
    "sg:province":"FL",
    "sg:tags":[
        "executive"
    ],
    "wof:name":"Vital Records Dept",
    "wof:placetype":"venue"
},
  "geometry": {"coordinates":[-82.530969,27.332621],"type":"Point"}
}