{
  "type": "Feature",
  "properties": {
    "iso:country":"US",
    "sg:address":"5300 Inlet Way",
    "sg:city":"Fort Pierce",
    "sg:classifiers":[
        {
            "category":"Building & Trades",
            "subcategory":"Plumbing",
            "type":"Services"
        }
    ],
    "sg:phone":"+1 772 468 0021",
    "sg:postcode":"34949",
    "sg:province":"FL",
    "sg:tags":[
        "contractor"
    ],
    "wof:name":"B & R Plumbing Inc",
    "wof:placetype":"venue"
},
  "geometry": {"coordinates":[-80.315377,27.529982],"type":"Point"}
}