{
  "type": "Feature",
  "properties": {
    "iso:country":"US",
    "sg:address":"333 3rd Rd",
    "sg:city":"Key Largo",
    "sg:classifiers":[
        {
            "category":"Shopping",
            "subcategory":"Computers & Home Electronics",
            "type":"Retail Goods"
        }
    ],
    "sg:phone":"+1 305 451 4560",
    "sg:postcode":"33037",
    "sg:province":"FL",
    "sg:tags":[
        "equipment",
        "dealer"
    ],
    "sg:website":"www.barebunns.com",
    "wof:name":"Mac Intosh Systems Solutions",
    "wof:placetype":"venue"
},
  "geometry": {"coordinates":[-80.39420800000001,25.14366],"type":"Point"}
}