{
  "type": "Feature",
  "properties": {
    "addr:full":"4 W Dania Beach Blvd Dania FL 33004",
    "addr:housenumber":"4",
    "addr:postcode":"33004",
    "addr:street":"W Dania Beach Blvd",
    "iso:country":"US",
    "sg:address":"4 W Dania Beach Blvd",
    "sg:city":"Dania",
    "sg:classifiers":[
        {
            "category":"Wholesale",
            "subcategory":"Electrical",
            "type":"Manufacturing & Wholesale Goods"
        }
    ],
    "sg:phone":"+1 954 924 9365",
    "sg:postcode":"33004",
    "sg:province":"FL",
    "sg:tags":[
        "accounting",
        "security",
        "electronic",
        "system",
        "time"
    ],
    "wof:name":"Time Management Systems Inc",
    "wof:placetype":"venue"
},
  "geometry": {"coordinates":[-80.144443,26.052209],"type":"Point"}
}