{
  "type": "Feature",
  "properties": {
    "addr:full":"7849 N Tamiami Trl Sarasota FL 34243",
    "addr:housenumber":"7849",
    "addr:postcode":"34243",
    "addr:street":"N Tamiami Trl",
    "iso:country":"US",
    "sg:address":"7849 N Tamiami Trl",
    "sg:city":"Sarasota",
    "sg:classifiers":[
        {
            "category":"Shopping",
            "subcategory":"Used Merchandise",
            "type":"Retail Goods"
        }
    ],
    "sg:phone":"+1 941 355 0229",
    "sg:postcode":"34243",
    "sg:province":"FL",
    "sg:tags":[
        "shop",
        "thrift"
    ],
    "wof:name":"Pelican Mans Bird Sanct Thrift",
    "wof:placetype":"venue"
},
  "geometry": {"coordinates":[-82.564937,27.400555],"type":"Point"}
}