{
  "type": "Feature",
  "properties": {
    "addr:full":"1806 Elsa St Orlando FL 32806",
    "addr:housenumber":"1806",
    "addr:postcode":"32806",
    "addr:street":"Elsa St",
    "iso:country":"US",
    "sg:address":"1806 Elsa St",
    "sg:city":"Orlando",
    "sg:classifiers":[
        {
            "category":"Manufacturing",
            "subcategory":"Furniture",
            "type":"Manufacturing & Wholesale Goods"
        }
    ],
    "sg:phone":"+1 407 857 4882",
    "sg:postcode":"32806",
    "sg:province":"FL",
    "sg:tags":[
        "material",
        "fixture",
        "millwork",
        "display"
    ],
    "wof:name":"Custom Wood Products",
    "wof:placetype":"venue"
},
  "geometry": {"coordinates":[-81.340896,28.521764],"type":"Point"}
}