{
  "type": "Feature",
  "properties": {
    "iso:country":"US",
    "sg:address":"168 Cedar Ave",
    "sg:city":"Orange City",
    "sg:classifiers":[
        {
            "category":"Building & Trades",
            "subcategory":"Construction",
            "type":"Services"
        }
    ],
    "sg:phone":"+1 386 747 4186",
    "sg:postcode":"32763",
    "sg:province":"FL",
    "sg:tags":[
        "masonry",
        "contractor"
    ],
    "wof:name":"Brian Pitzer Masonry",
    "wof:placetype":"venue"
},
  "geometry": {"coordinates":[-81.302233,28.93174],"type":"Point"}
}