{
  "type": "Feature",
  "properties": {
    "iso:country":"US",
    "sg:address":"12000 Research Pkwy",
    "sg:city":"Orlando",
    "sg:classifiers":[
        {
            "category":"Manufacturing",
            "subcategory":"Aerospace",
            "type":"Manufacturing & Wholesale Goods"
        },
        {
            "category":"Autos & Motor Vehicles",
            "subcategory":"Recreational Vehicle Sales",
            "type":"Retail Goods"
        }
    ],
    "sg:phone":"+1 407 249 8334",
    "sg:postcode":"32826",
    "sg:province":"FL",
    "sg:tags":[
        "equipment",
        "aircraft",
        "part",
        "supplies-wholesale",
        "manufacturer"
    ],
    "wof:name":"Northrop Grumman IT",
    "wof:placetype":"venue"
},
  "geometry": {"coordinates":[-81.20257100000001,28.588721],"type":"Point"}
}