{
  "type": "Feature",
  "properties": {
    "addr:full":"1720 S Mccall Rd Englewood FL 34223",
    "addr:housenumber":"1720",
    "addr:postcode":"34223",
    "addr:street":"S Mccall Rd",
    "iso:country":"US",
    "sg:address":"1720 S Mccall Rd",
    "sg:city":"Englewood",
    "sg:classifiers":[
        {
            "category":"Restaurant",
            "type":"Food & Drink"
        }
    ],
    "sg:menulink":"http://www.allmenus.com/fl/grove-city-rotonda/237199-hungry-howies-pizza/menu/",
    "sg:phone":"+1 941 475 8384",
    "sg:postcode":"34223",
    "sg:province":"FL",
    "sg:tags":[
        "wrap",
        "american",
        "sandwich",
        "pizza"
    ],
    "wof:name":"Hungry Howie's Pizza",
    "wof:placetype":"venue"
},
  "geometry": {"coordinates":[-82.33960500000001,26.938545],"type":"Point"}
}