{
  "type": "Feature",
  "properties": {
    "iso:country":"US",
    "sg:address":"4681 Island Reef Dr",
    "sg:city":"Wellington",
    "sg:classifiers":[
        {
            "category":"Professional",
            "subcategory":"Business Services",
            "type":"Services"
        }
    ],
    "sg:phone":"+1 561 383 8258",
    "sg:postcode":"33449",
    "sg:province":"FL",
    "sg:tags":[
        "holding"
    ],
    "wof:name":"Blue Creek Holdings",
    "wof:placetype":"venue"
},
  "geometry": {"coordinates":[-80.22748300000001,26.611553],"type":"Point"}
}