{
  "type": "Feature",
  "properties": {
    "addr:full":"13987 94th Ave Seminole FL 33776",
    "addr:housenumber":"13987",
    "addr:postcode":"33776",
    "addr:street":"94Th Ave",
    "iso:country":"US",
    "sg:address":"13987 94th Ave",
    "sg:city":"Seminole",
    "sg:classifiers":[
        {
            "category":"Professional",
            "subcategory":"Management & Consulting",
            "type":"Services"
        }
    ],
    "sg:phone":"+1 727 593 3067",
    "sg:postcode":"33776",
    "sg:province":"FL",
    "sg:tags":[
        "environmental",
        "ecological",
        "consultant"
    ],
    "wof:name":"Vern Roberts Environmental Training, Inc.",
    "wof:placetype":"venue"
},
  "geometry": {"coordinates":[-82.832067,27.85843],"type":"Point"}
}