{
  "type": "Feature",
  "properties": {
    "addr:full":"22536 Swordfish Dr Boca Raton FL 33428",
    "addr:postcode":"22536;33428",
    "addr:street":"Swordfish Dr",
    "iso:country":"US",
    "sg:address":"22536 Swordfish Dr",
    "sg:city":"Boca Raton",
    "sg:classifiers":[
        {
            "category":"Retail",
            "subcategory":"Funeral Services",
            "type":"Services"
        }
    ],
    "sg:phone":"+1 561 477 1018",
    "sg:postcode":"33428",
    "sg:province":"FL",
    "wof:name":"Gary Panach Funeral Home & Cre",
    "wof:placetype":"venue"
},
  "geometry": {"coordinates":[-80.238782,26.343187],"type":"Point"}
}