{
  "type": "Feature",
  "properties": {
    "iso:country":"US",
    "sg:address":"928 Edgewood Ave S",
    "sg:city":"Jacksonville",
    "sg:classifiers":[
        {
            "category":"Professional",
            "subcategory":"Computer Services",
            "type":"Services"
        }
    ],
    "sg:phone":"+1 904 425 4448",
    "sg:postcode":"32205",
    "sg:province":"FL",
    "wof:name":"H & H Innovative Technologies",
    "wof:placetype":"venue"
},
  "geometry": {"coordinates":[-81.718284,30.312317],"type":"Point"}
}