{
  "type": "Feature",
  "properties": {
    "iso:country":"US",
    "sg:address":"5039 State Rd 54",
    "sg:city":"New Port Richey",
    "sg:classifiers":[
        {
            "category":"Food & Beverages",
            "subcategory":"Liquor & Beverages",
            "type":"Retail Goods"
        }
    ],
    "sg:phone":"+1 727 849 6411",
    "sg:postcode":"34652",
    "sg:province":"FL",
    "sg:tags":[
        "alcoholic"
    ],
    "wof:name":"A & D Beverage Station Inc",
    "wof:placetype":"venue"
},
  "geometry": {"coordinates":[-82.73081000000001,28.217038],"type":"Point"}
}