{
  "type": "Feature",
  "properties": {
    "addr:full":"162 2nd St SW Winter Haven FL 33880",
    "addr:housenumber":"162",
    "addr:postcode":"33880",
    "addr:street":"2Nd St Sw",
    "iso:country":"US",
    "sg:address":"162 2nd St SW",
    "sg:city":"Winter Haven",
    "sg:classifiers":[
        {
            "category":"Professional",
            "subcategory":"Lawyer & Legal Services",
            "type":"Services"
        }
    ],
    "sg:phone":"+1 863 299 4040",
    "sg:postcode":"33880",
    "sg:province":"FL",
    "sg:tags":[
        "security",
        "counselor",
        "rep",
        "social"
    ],
    "wof:name":"Jordan Social Security Conslnt",
    "wof:placetype":"venue"
},
  "geometry": {"coordinates":[-81.728905,28.022063],"type":"Point"}
}