{
  "type": "Feature",
  "properties": {
    "addr:full":"22124 Aquila St Boca Raton FL 33428",
    "addr:postcode":"22124;33428",
    "addr:street":"Aquila St",
    "iso:country":"US",
    "sg:address":"22124 Aquila St",
    "sg:city":"Boca Raton",
    "sg:classifiers":[
        {
            "category":"Freight",
            "type":"Transportation"
        }
    ],
    "sg:phone":"+1 561 756 3089",
    "sg:postcode":"33428",
    "sg:province":"FL",
    "sg:tags":[
        "trucking"
    ],
    "wof:name":"Jose Botero Trucking",
    "wof:placetype":"venue"
},
  "geometry": {"coordinates":[-80.21521300000001,26.346588],"type":"Point"}
}