{
  "type": "Feature",
  "properties": {
    "addr:full":"4969 Alamanda Dr Melbourne FL 32940",
    "addr:housenumber":"4969",
    "addr:postcode":"32940",
    "addr:street":"Alamanda Dr",
    "iso:country":"US",
    "sg:address":"4969 Alamanda Dr",
    "sg:city":"Melbourne",
    "sg:classifiers":[
        {
            "category":"Professional",
            "subcategory":"Employment Agencies",
            "type":"Services"
        }
    ],
    "sg:phone":"+1 321 254 4423",
    "sg:postcode":"32940",
    "sg:province":"FL",
    "sg:tags":[
        "consultant",
        "search",
        "executive"
    ],
    "sg:website":"www.mcmillanassoc.com",
    "wof:name":"Mc Millan Assoc",
    "wof:placetype":"venue"
},
  "geometry": {"coordinates":[-80.685276,28.190276],"type":"Point"}
}