{
  "type": "Feature",
  "properties": {
    "addr:full":"2800 Placida Rd Englewood FL 34224",
    "addr:postcode":"2800;34224",
    "addr:street":"Placida Rd",
    "iso:country":"US",
    "sg:address":"2800 Placida Rd",
    "sg:city":"Englewood",
    "sg:classifiers":[
        {
            "category":"Communications",
            "type":"Services"
        }
    ],
    "sg:phone":"+1 941 698 1661",
    "sg:postcode":"34224",
    "sg:province":"FL",
    "sg:tags":[
        "communication"
    ],
    "wof:name":"Atlantic Telecom",
    "wof:placetype":"venue"
},
  "geometry": {"coordinates":[-82.32702399999999,26.913384],"type":"Point"}
}