{
  "type": "Feature",
  "properties": {
    "addr:full":"1829 W State Road 434 Longwood FL 32750",
    "addr:housenumber":"1829",
    "addr:postcode":"32750",
    "addr:street":"W State Road 434",
    "iso:country":"US",
    "sg:address":"1829 W State Road 434",
    "sg:city":"Longwood",
    "sg:classifiers":[
        {
            "category":"Shopping",
            "subcategory":"Jewelry",
            "type":"Retail Goods"
        }
    ],
    "sg:phone":"+1 407 332 9333",
    "sg:postcode":"32750",
    "sg:province":"FL",
    "sg:website":"www.orlandosecretjewelers.com/",
    "wof:name":"Orlando's Secret Jewelers",
    "wof:placetype":"venue"
},
  "geometry": {"coordinates":[-81.38531399999999,28.692722],"type":"Point"}
}