{
  "type": "Feature",
  "properties": {
    "addr:full":"12 NW 69th Ave Miami FL 33126",
    "addr:housenumber":"12",
    "addr:postcode":"33126",
    "addr:street":"Nw 69Th Ave",
    "iso:country":"US",
    "sg:address":"12 NW 69th Ave",
    "sg:city":"Miami",
    "sg:classifiers":[
        {
            "category":"Shopping",
            "type":"Retail Goods"
        }
    ],
    "sg:phone":"+1 305 260 7711",
    "sg:postcode":"33126",
    "sg:province":"FL",
    "sg:tags":[
        "pet",
        "food",
        "supply"
    ],
    "wof:name":"Puppy Toy USA Inc",
    "wof:placetype":"venue"
},
  "geometry": {"coordinates":[-80.30772,25.770845],"type":"Point"}
}