{
  "type": "Feature",
  "properties": {
    "iso:country":"US",
    "sg:address":"13985 SW 25th Ter",
    "sg:city":"Miami",
    "sg:classifiers":[
        {
            "category":"Retail",
            "subcategory":"Auto Repair",
            "type":"Services"
        }
    ],
    "sg:phone":"+1 305 223 4540",
    "sg:postcode":"33175",
    "sg:province":"FL",
    "sg:tags":[
        "mobile",
        "towing"
    ],
    "wof:name":"Rolling Auto Service",
    "wof:placetype":"venue"
},
  "geometry": {"coordinates":[-80.420644,25.74393],"type":"Point"}
}