{
  "type": "Feature",
  "properties": {
    "iso:country":"US",
    "sg:address":"1740 Palm Ave",
    "sg:city":"Hialeah",
    "sg:classifiers":[
        {
            "category":"Shopping",
            "subcategory":"Mobile Phones",
            "type":"Retail Goods"
        }
    ],
    "sg:phone":"+1 305 885 7985",
    "sg:postcode":"33010",
    "sg:province":"FL",
    "wof:name":"Telecomunicaciones Express Inc",
    "wof:placetype":"venue"
},
  "geometry": {"coordinates":[-80.282078,25.83762],"type":"Point"}
}