{
  "type": "Feature",
  "properties": {
    "addr:full":"361 N Central Ave Umatilla FL 32784",
    "addr:housenumber":"361",
    "addr:postcode":"32784",
    "addr:street":"N Central Ave",
    "iso:country":"US",
    "sg:address":"361 N Central Ave",
    "sg:city":"Umatilla",
    "sg:classifiers":[
        {
            "category":"Insurance",
            "subcategory":"Insurance Agent",
            "type":"Services"
        }
    ],
    "sg:phone":"+1 352 669 7999",
    "sg:postcode":"32784",
    "sg:province":"FL",
    "wof:name":"Laing Insurance Inc",
    "wof:placetype":"venue"
},
  "geometry": {"coordinates":[-81.665255,28.936786],"type":"Point"}
}