{
  "type": "Feature",
  "properties": {
    "iso:country":"US",
    "sg:address":"1927 Laurel St",
    "sg:city":"Sarasota",
    "sg:classifiers":[
        {
            "category":"Wholesale",
            "subcategory":"Construction Materials",
            "type":"Manufacturing & Wholesale Goods"
        }
    ],
    "sg:phone":"+1 941 952 0004",
    "sg:postcode":"34236",
    "sg:province":"FL",
    "sg:tags":[
        "glass"
    ],
    "wof:name":"Specified Archtectural Systems",
    "wof:placetype":"venue"
},
  "geometry": {"coordinates":[-82.53229899999999,27.332697],"type":"Point"}
}