{
  "type": "Feature",
  "properties": {
    "iso:country":"US",
    "sg:address":"810 Wadsworth St",
    "sg:city":"Tallahassee",
    "sg:classifiers":[
        {
            "category":"Utilities",
            "subcategory":"Telephone",
            "type":"Services"
        }
    ],
    "sg:phone":"+1 850 224 5465",
    "sg:postcode":"32304",
    "sg:province":"FL",
    "sg:tags":[
        "company"
    ],
    "wof:name":"Telephone Operating Systems",
    "wof:placetype":"venue"
},
  "geometry": {"coordinates":[-84.304968,30.449335],"type":"Point"}
}