{
  "type": "Feature",
  "properties": {
    "iso:country":"US",
    "sg:address":"5402 Phillips Hwy",
    "sg:city":"Jacksonville",
    "sg:classifiers":[
        {
            "category":"Building & Trades",
            "subcategory":"Equipment Rental",
            "type":"Services"
        }
    ],
    "sg:phone":"+1 904 636 6336",
    "sg:postcode":"32207",
    "sg:province":"FL",
    "sg:tags":[
        "yard"
    ],
    "sg:website":"www.ur.com",
    "wof:name":"United Rentals",
    "wof:placetype":"venue"
},
  "geometry": {"coordinates":[-81.620093,30.26839],"type":"Point"}
}