{
  "type": "Feature",
  "properties": {
    "iso:country":"US",
    "sg:address":"1400 SW 6th Ct",
    "sg:city":"Pompano Beach",
    "sg:classifiers":[
        {
            "category":"Wholesale",
            "subcategory":"Fruits & Vegetables",
            "type":"Manufacturing & Wholesale Goods"
        }
    ],
    "sg:phone":"+1 954 784 1464",
    "sg:postcode":"33069",
    "sg:province":"FL",
    "sg:tags":[
        "shipper"
    ],
    "wof:name":"Southern Specialties",
    "wof:placetype":"venue"
},
  "geometry": {"coordinates":[-80.143406,26.221614],"type":"Point"}
}