{
  "type": "Feature",
  "properties": {
    "addr:full":"42 NW 27th Ave Miami FL 33125",
    "addr:housenumber":"42",
    "addr:postcode":"33125",
    "addr:street":"Nw 27Th Ave",
    "iso:country":"US",
    "sg:address":"42 NW 27th Ave",
    "sg:city":"Miami",
    "sg:classifiers":[
        {
            "category":"Travel",
            "subcategory":"Travel Agent",
            "type":"Entertainment"
        }
    ],
    "sg:phone":"+1 305 644 0122",
    "sg:postcode":"33125",
    "sg:province":"FL",
    "sg:tags":[
        "agency"
    ],
    "wof:name":"Enjoy Orlando Inc",
    "wof:placetype":"venue"
},
  "geometry": {"coordinates":[-80.239225,25.77323],"type":"Point"}
}