{
  "type": "Feature",
  "properties": {
    "iso:country":"US",
    "sg:address":"5472 Laurel Ridge Ln",
    "sg:city":"Naples",
    "sg:classifiers":[
        {
            "category":"Building & Trades",
            "subcategory":"Cleaning & Sanitation",
            "type":"Services"
        }
    ],
    "sg:phone":"+1 239 293 9349",
    "sg:postcode":"34116",
    "sg:province":"FL",
    "sg:tags":[
        "house"
    ],
    "wof:name":"Anyeli Ramos Cleaning Svc",
    "wof:placetype":"venue"
},
  "geometry": {"coordinates":[-81.718349,26.199063],"type":"Point"}
}