{
  "type": "Feature",
  "properties": {
    "iso:country":"US",
    "sg:address":"11370 NW 1st Pl",
    "sg:city":"Pompano Beach",
    "sg:classifiers":[
        {
            "category":"Professional",
            "subcategory":"Computer Services",
            "type":"Services"
        }
    ],
    "sg:phone":"+1 954 755 7187",
    "sg:postcode":"33071",
    "sg:province":"FL",
    "sg:tags":[
        "prepackaged",
        "software"
    ],
    "wof:name":"Software USA Inc",
    "wof:placetype":"venue"
},
  "geometry": {"coordinates":[-80.27760600000001,26.233536],"type":"Point"}
}