{
  "type": "Feature",
  "properties": {
    "iso:country":"US",
    "sg:address":"8271 S Dixie Hwy",
    "sg:city":"Miami",
    "sg:classifiers":[
        {
            "category":"Retail",
            "subcategory":"Veterinary Services",
            "type":"Services"
        }
    ],
    "sg:phone":"+1 305 662 4202",
    "sg:postcode":"33143",
    "sg:province":"FL",
    "sg:tags":[
        "veterinarian"
    ],
    "wof:name":"Ferran Robert DVM Cva DVM",
    "wof:placetype":"venue"
},
  "geometry": {"coordinates":[-80.302696,25.6933],"type":"Point"}
}