{
  "type": "Feature",
  "properties": {
    "iso:country":"US",
    "sg:address":"3420 19th Ave SW",
    "sg:city":"Naples",
    "sg:classifiers":[
        {
            "category":"Building & Trades",
            "subcategory":"Construction",
            "type":"Services"
        }
    ],
    "sg:phone":"+1 239 348 9583",
    "sg:postcode":"34117",
    "sg:province":"FL",
    "sg:tags":[
        "contractor"
    ],
    "wof:name":"A1a Tile Service Inc",
    "wof:placetype":"venue"
},
  "geometry": {"coordinates":[-81.680933,26.194193],"type":"Point"}
}