{
  "type": "Feature",
  "properties": {
    "addr:full":"19355 Turnberry Way Miami FL 33180",
    "addr:housenumber":"19355",
    "addr:postcode":"33180",
    "addr:street":"Turnberry Way",
    "iso:country":"US",
    "sg:address":"19355 Turnberry Way",
    "sg:city":"Miami",
    "sg:classifiers":[
        {
            "category":"Professional",
            "type":"Services"
        }
    ],
    "sg:phone":"+1 305 932 3002",
    "sg:postcode":"33180",
    "sg:province":"FL",
    "sg:tags":[
        "establishment"
    ],
    "wof:name":"S L Alternative",
    "wof:placetype":"venue"
},
  "geometry": {"coordinates":[-80.12705099999999,25.956976],"type":"Point"}
}