{
  "type": "Feature",
  "properties": {
    "addr:full":"617 Lake Clay Dr S Lake Placid FL 33852",
    "addr:housenumber":"617",
    "addr:postcode":"33852",
    "addr:street":"Lake Clay Dr S;Placid",
    "iso:country":"US",
    "sg:address":"617 Lake Clay Dr S",
    "sg:city":"Lake Placid",
    "sg:classifiers":[
        {
            "category":"Professional",
            "subcategory":"Engineering",
            "type":"Services"
        }
    ],
    "sg:phone":"+1 863 465 6555",
    "sg:postcode":"33852",
    "sg:province":"FL",
    "sg:tags":[
        "engineer"
    ],
    "wof:name":"Captec Engineering",
    "wof:placetype":"venue"
},
  "geometry": {"coordinates":[-81.356596,27.302795],"type":"Point"}
}