{
  "type": "Feature",
  "properties": {
    "addr:full":"4280 SW 64th Ave Davie FL 33314",
    "addr:housenumber":"4280",
    "addr:postcode":"33314",
    "addr:street":"Sw 64Th Ave",
    "iso:country":"US",
    "sg:address":"4280 SW 64th Ave",
    "sg:city":"Davie",
    "sg:classifiers":[
        {
            "category":"Retail",
            "subcategory":"Portrait Studio",
            "type":"Services"
        }
    ],
    "sg:phone":"+1 954 587 3429",
    "sg:postcode":"33314",
    "sg:province":"FL",
    "sg:tags":[
        "photographer"
    ],
    "wof:name":"Countryside Portrait Studio",
    "wof:placetype":"venue"
},
  "geometry": {"coordinates":[-80.232156,26.06895],"type":"Point"}
}