{
  "type": "Feature",
  "properties": {
    "addr:full":"501 Blairstone Rd # 4102 Tallahassee FL 32301",
    "addr:housenumber":"501",
    "addr:postcode":"32301",
    "addr:street":"Blairstone Rd # 4102",
    "iso:country":"US",
    "sg:address":"501 Blairstone Rd # 4102",
    "sg:city":"Tallahassee",
    "sg:classifiers":[
        {
            "category":"Shopping",
            "subcategory":"Jewelry",
            "type":"Retail Goods"
        }
    ],
    "sg:phone":"+1 850 216 2952",
    "sg:postcode":"32301",
    "sg:province":"FL",
    "sg:tags":[
        "precious",
        "semi-precious",
        "stone"
    ],
    "wof:name":"Arcane India",
    "wof:placetype":"venue"
},
  "geometry": {"coordinates":[-84.24942799999999,30.44169],"type":"Point"}
}