{
  "type": "Feature",
  "properties": {
    "addr:full":"1891 Porter Lake Dr Sarasota FL 34240",
    "addr:housenumber":"1891",
    "addr:postcode":"34240",
    "addr:street":"Porter Lake Dr",
    "iso:country":"US",
    "sg:address":"1891 Porter Lake Dr",
    "sg:city":"Sarasota",
    "sg:classifiers":[
        {
            "category":"Shopping",
            "type":"Retail Goods"
        }
    ],
    "sg:phone":"+1 941 343 9395",
    "sg:postcode":"34240",
    "sg:province":"FL",
    "sg:tags":[
        "equipment",
        "pool",
        "swimming"
    ],
    "wof:name":"Pools By Brady",
    "wof:placetype":"venue"
},
  "geometry": {"coordinates":[-82.447287,27.311688],"type":"Point"}
}