{
  "type": "Feature",
  "properties": {
    "iso:country":"US",
    "sg:address":"9516 Cortez Rd W Ste 9",
    "sg:city":"Bradenton",
    "sg:classifiers":[
        {
            "category":"Banks & Credit Unions",
            "subcategory":"Bank",
            "type":"Services"
        },
        {
            "category":"Professional",
            "subcategory":"Business Services",
            "type":"Services"
        },
        {
            "category":"Shopping",
            "subcategory":"Used Merchandise",
            "type":"Retail Goods"
        }
    ],
    "sg:phone":"+1 941 794 1402",
    "sg:postcode":"34210",
    "sg:province":"FL",
    "sg:tags":[
        "shop",
        "auction",
        "second",
        "resale",
        "hand"
    ],
    "wof:name":"Palama Sola Thrift & Gift",
    "wof:placetype":"venue"
},
  "geometry": {"coordinates":[-82.658036,27.461716],"type":"Point"}
}