{
  "type": "Feature",
  "properties": {
    "iso:country":"US",
    "sg:address":"4 Main St",
    "sg:city":"Titusville",
    "sg:classifiers":[
        {
            "category":"Organizations",
            "subcategory":"Professional Association",
            "type":"Services"
        }
    ],
    "sg:phone":"+1 321 385 0404",
    "sg:postcode":"32796",
    "sg:province":"FL",
    "wof:name":"WIN Vet",
    "wof:placetype":"venue"
},
  "geometry": {"coordinates":[-80.80701999999999,28.61266],"type":"Point"}
}