{
  "type": "Feature",
  "properties": {
    "iso:country":"US",
    "sg:address":"135 N Rodriquez St",
    "sg:city":"Saint Augustine",
    "sg:classifiers":[
        {
            "category":"Organizations",
            "subcategory":"Religious Organization",
            "type":"Services"
        }
    ],
    "sg:phone":"+1 904 824 6500",
    "sg:postcode":"32084",
    "sg:province":"FL",
    "wof:name":"New Saint James Msnry Bptst",
    "wof:placetype":"venue"
},
  "geometry": {"coordinates":[-81.33461,29.890717],"type":"Point"}
}