{
  "type": "Feature",
  "properties": {
    "iso:country":"US",
    "sg:address":"7821 Broadmoor Pines Blvd",
    "sg:city":"Sarasota",
    "sg:classifiers":[
        {
            "category":"Banks & Credit Unions",
            "subcategory":"Investment Brokerage",
            "type":"Services"
        }
    ],
    "sg:phone":"+1 941 355 1733",
    "sg:postcode":"34243",
    "sg:province":"FL",
    "sg:tags":[
        "advisory"
    ],
    "wof:name":"LMI Corporation of Delaware",
    "wof:placetype":"venue"
},
  "geometry": {"coordinates":[-82.485221,27.399837],"type":"Point"}
}