{
  "type": "Feature",
  "properties": {
    "iso:country":"US",
    "sg:address":"1709 S 31st St",
    "sg:city":"Fort Pierce",
    "sg:classifiers":[
        {
            "category":"Health Services",
            "subcategory":"Medical Lab",
            "type":"Services"
        }
    ],
    "sg:phone":"+1 772 461 2422",
    "sg:postcode":"34947",
    "sg:province":"FL",
    "sg:tags":[
        "laboratory"
    ],
    "wof:name":"Watford Dental Lab",
    "wof:placetype":"venue"
},
  "geometry": {"coordinates":[-80.35638400000001,27.431666],"type":"Point"}
}