{
  "type": "Feature",
  "properties": {
    "iso:country":"US",
    "sg:address":"2202 N Young Blvd",
    "sg:city":"Chiefland",
    "sg:classifiers":[
        {
            "category":"Manufacturing",
            "subcategory":"Printing",
            "type":"Manufacturing & Wholesale Goods"
        },
        {
            "category":"Shopping",
            "subcategory":"Gifts & Souvenirs",
            "type":"Retail Goods"
        }
    ],
    "sg:phone":"+1 352 493 1921",
    "sg:postcode":"32626",
    "sg:province":"FL",
    "sg:tags":[
        "shop",
        "mfg"
    ],
    "wof:name":"Captured Moments",
    "wof:placetype":"venue"
},
  "geometry": {"coordinates":[-82.87157999999999,29.50263],"type":"Point"}
}