{
  "type": "Feature",
  "properties": {
    "iso:country":"US",
    "sg:address":"2121 Tanglewood Dr",
    "sg:city":"Orange City",
    "sg:classifiers":[
        {
            "category":"Building & Trades",
            "subcategory":"Construction",
            "type":"Services"
        }
    ],
    "sg:phone":"+1 386 956 0532",
    "sg:postcode":"32763",
    "sg:province":"FL",
    "sg:tags":[
        "concrete",
        "contractor"
    ],
    "wof:name":"Timothy Evans Concrete",
    "wof:placetype":"venue"
},
  "geometry": {"coordinates":[-81.303978,28.963529],"type":"Point"}
}