{
  "type": "Feature",
  "properties": {
    "iso:country":"US",
    "sg:address":"5427 Water St",
    "sg:city":"New Port Richey",
    "sg:classifiers":[
        {
            "category":"Communications",
            "subcategory":"Film & Video Production",
            "type":"Services"
        }
    ],
    "sg:phone":"+1 727 817 1102",
    "sg:postcode":"34652",
    "sg:province":"FL",
    "sg:tags":[
        "laboratory"
    ],
    "wof:name":"Physicians Stat Laboratory",
    "wof:placetype":"venue"
},
  "geometry": {"coordinates":[-82.722188,28.23798],"type":"Point"}
}