{
  "type": "Feature",
  "properties": {
    "addr:full":"13155 SW 134th St Ste 111 Miami FL 33186",
    "addr:housenumber":"13155",
    "addr:postcode":"33186",
    "addr:street":"Sw 134Th St Ste 111",
    "iso:country":"US",
    "sg:address":"13155 SW 134th St Ste 111",
    "sg:city":"Miami",
    "sg:classifiers":[
        {
            "category":"Professional",
            "subcategory":"Printing & Photocopies",
            "type":"Services"
        }
    ],
    "sg:phone":"+1 786 293 2098",
    "sg:postcode":"33186",
    "sg:province":"FL",
    "sg:tags":[
        "photographers-commercial"
    ],
    "wof:name":"Mcmairs Photography",
    "wof:placetype":"venue"
},
  "geometry": {"coordinates":[-80.406047,25.642999],"type":"Point"}
}