{
  "type": "Feature",
  "properties": {
    "addr:full":"18114 Crawley Rd Odessa FL 33556",
    "addr:housenumber":"18114",
    "addr:postcode":"33556",
    "addr:street":"Crawley Rd",
    "iso:country":"US",
    "sg:address":"18114 Crawley Rd",
    "sg:city":"Odessa",
    "sg:classifiers":[
        {
            "category":"Manufacturing",
            "subcategory":"Tools & Machinery",
            "type":"Manufacturing & Wholesale Goods"
        }
    ],
    "sg:phone":"+1 813 920 4617",
    "sg:postcode":"33556",
    "sg:province":"FL",
    "sg:tags":[
        "machine",
        "manufacturer"
    ],
    "wof:name":"Sterling Instrument And Supply",
    "wof:placetype":"venue"
},
  "geometry": {"coordinates":[-82.601038,28.137986],"type":"Point"}
}