{
  "type": "Feature",
  "properties": {
    "iso:country":"US",
    "sg:address":"1325 Bruton Blvd",
    "sg:city":"Orlando",
    "sg:classifiers":[
        {
            "category":"Personal",
            "subcategory":"Barber",
            "type":"Services"
        }
    ],
    "sg:phone":"+1 407 292 5823",
    "sg:postcode":"32805",
    "sg:province":"FL",
    "wof:name":"Roy's VIP HAIR Care",
    "wof:placetype":"venue"
},
  "geometry": {"coordinates":[-81.425985,28.524919],"type":"Point"}
}