{
  "type": "Feature",
  "properties": {
    "iso:country":"US",
    "sg:address":"1900 Sunset Harbour Dr",
    "sg:city":"Miami Beach",
    "sg:classifiers":[
        {
            "category":"Recreation",
            "subcategory":"Boat Charter",
            "type":"Entertainment"
        }
    ],
    "sg:phone":"+1 305 358 0745",
    "sg:postcode":"33139",
    "sg:province":"FL",
    "sg:tags":[
        "boating"
    ],
    "sg:website":"www.TheAdvantaged.com",
    "wof:name":"The Advantaged Yacht Charters & Sales",
    "wof:placetype":"venue"
},
  "geometry": {"coordinates":[-80.14440999999999,25.793233],"type":"Point"}
}