{
  "type": "Feature",
  "properties": {
    "iso:country":"US",
    "sg:address":"1460 SE 10th St",
    "sg:city":"Stuart",
    "sg:classifiers":[
        {
            "category":"Building & Trades",
            "subcategory":"Construction",
            "type":"Services"
        }
    ],
    "sg:phone":"+1 772 283 6492",
    "sg:postcode":"34994",
    "sg:province":"FL",
    "sg:tags":[
        "contractor"
    ],
    "wof:name":"BRB Masonry Inc",
    "wof:placetype":"venue"
},
  "geometry": {"coordinates":[-80.22788799999999,27.190134],"type":"Point"}
}