{
  "type": "Feature",
  "properties": {
    "addr:full":"20432 NE 16th Pl Miami FL 33179",
    "addr:housenumber":"20432",
    "addr:postcode":"33179",
    "addr:street":"Ne 16Th Pl",
    "iso:country":"US",
    "sg:address":"20432 NE 16th Pl",
    "sg:city":"Miami",
    "sg:classifiers":[
        {
            "category":"Wholesale",
            "subcategory":"Durable Goods & Equipment",
            "type":"Manufacturing & Wholesale Goods"
        }
    ],
    "sg:phone":"+1 305 651 6519",
    "sg:postcode":"33179",
    "sg:province":"FL",
    "sg:tags":[
        "music"
    ],
    "wof:name":"ECM Records & Distribution",
    "wof:placetype":"venue"
},
  "geometry": {"coordinates":[-80.168977,25.964413],"type":"Point"}
}