{
  "type": "Feature",
  "properties": {
    "addr:full":"2303 NE Jacksonville Rd Ocala FL 34470",
    "addr:housenumber":"2303",
    "addr:postcode":"34470",
    "addr:street":"Ne Jacksonville Rd",
    "iso:country":"US",
    "sg:address":"2303 NE Jacksonville Rd",
    "sg:city":"Ocala",
    "sg:classifiers":[
        {
            "category":"Government",
            "subcategory":"Office",
            "type":"Public Place"
        }
    ],
    "sg:phone":"+1 352 732 9840",
    "sg:postcode":"34470",
    "sg:province":"FL",
    "sg:tags":[
        "federal",
        "planning",
        "dev"
    ],
    "wof:name":"USDA Rural Development",
    "wof:placetype":"venue"
},
  "geometry": {"coordinates":[-82.127441,29.211472],"type":"Point"}
}