{
  "type": "Feature",
  "properties": {
    "iso:country":"US",
    "sg:address":"2411 SW 13th St",
    "sg:city":"Gainesville",
    "sg:classifiers":[
        {
            "category":"Retail",
            "subcategory":"Laundry & Dry Cleaning",
            "type":"Services"
        }
    ],
    "sg:phone":"+1 352 336 0720",
    "sg:postcode":"32608",
    "sg:province":"FL",
    "wof:name":"A-Best Coin Laundry & Dry Clng",
    "wof:placetype":"venue"
},
  "geometry": {"coordinates":[-82.339292,29.631918],"type":"Point"}
}