{
  "type": "Feature",
  "properties": {
    "addr:full":"3350 SW 148th Ave Hollywood FL 33027",
    "addr:housenumber":"3350",
    "addr:postcode":"33027",
    "addr:street":"Sw 148Th Ave",
    "iso:country":"US",
    "sg:address":"3350 SW 148th Ave",
    "sg:city":"Hollywood",
    "sg:classifiers":[
        {
            "category":"Banks & Credit Unions",
            "subcategory":"Bank",
            "type":"Services"
        }
    ],
    "sg:phone":"+1 954 874 1633",
    "sg:postcode":"33027",
    "sg:province":"FL",
    "sg:tags":[
        "broker",
        "mortgage"
    ],
    "wof:name":"Premier Mortgage Funding Inc",
    "wof:placetype":"venue"
},
  "geometry": {"coordinates":[-80.34381,25.975973],"type":"Point"}
}