{
  "type": "Feature",
  "properties": {
    "addr:full":"6812 Hanging Moss Rd Orlando FL 32807",
    "addr:postcode":"6812;32807",
    "addr:street":"Hanging Moss Rd",
    "iso:country":"US",
    "sg:address":"6812 Hanging Moss Rd",
    "sg:city":"Orlando",
    "sg:classifiers":[
        {
            "category":"Professional",
            "subcategory":"Advertising",
            "type":"Services"
        }
    ],
    "sg:phone":"+1 407 679 2111",
    "sg:postcode":"32807",
    "sg:province":"FL",
    "sg:tags":[
        "counselor"
    ],
    "wof:name":"Itvip Marketing Jt",
    "wof:placetype":"venue"
},
  "geometry": {"coordinates":[-81.298879,28.578934],"type":"Point"}
}