{
  "type": "Feature",
  "properties": {
    "addr:full":"6365 E Colonial Dr Orlando FL 32807",
    "addr:housenumber":"6365",
    "addr:postcode":"32807",
    "addr:street":"E Colonial Dr",
    "iso:country":"US",
    "sg:address":"6365 E Colonial Dr",
    "sg:city":"Orlando",
    "sg:classifiers":[
        {
            "category":"Autos & Motor Vehicles",
            "subcategory":"Automobile Sales",
            "type":"Retail Goods"
        },
        {
            "category":"Retail",
            "subcategory":"Auto Rental",
            "type":"Services"
        }
    ],
    "sg:phone":"+1 407 658 0210",
    "sg:postcode":"32807",
    "sg:province":"FL",
    "sg:tags":[
        "car",
        "leasing",
        "truck"
    ],
    "sg:website":"http://budget.com/IYP_tl",
    "wof:name":"Budget Rent A Car",
    "wof:placetype":"venue"
},
  "geometry": {"coordinates":[-81.301357,28.563827],"type":"Point"}
}