{
  "type": "Feature",
  "properties": {
    "addr:full":"6145 W 26th Ct Hialeah FL 33016",
    "addr:housenumber":"6145",
    "addr:postcode":"33016",
    "addr:street":"W 26Th Ct",
    "iso:country":"US",
    "sg:address":"6145 W 26th Ct",
    "sg:city":"Hialeah",
    "sg:classifiers":[
        {
            "category":"Travel",
            "subcategory":"Travel Agent",
            "type":"Entertainment"
        }
    ],
    "sg:phone":"+1 305 824 8762",
    "sg:postcode":"33016",
    "sg:province":"FL",
    "sg:tags":[
        "agency"
    ],
    "wof:name":"World Travel Master Inc",
    "wof:placetype":"venue"
},
  "geometry": {"coordinates":[-80.337395,25.877909],"type":"Point"}
}