{
  "type": "Feature",
  "properties": {
    "iso:country":"US",
    "sg:address":"4545 Burlington Ave N",
    "sg:city":"Saint Petersburg",
    "sg:classifiers":[
        {
            "category":"Restaurant",
            "type":"Food & Drink"
        }
    ],
    "sg:phone":"+1 727 328 1366",
    "sg:postcode":"33713",
    "sg:province":"FL",
    "sg:tags":[
        "eating"
    ],
    "wof:name":"Coffee Cottage",
    "wof:placetype":"venue"
},
  "geometry": {"coordinates":[-82.695251,27.77377],"type":"Point"}
}