{
  "type": "Feature",
  "properties": {
    "addr:full":"525 E Strawbridge Ave Melbourne FL 32901",
    "addr:housenumber":"525",
    "addr:postcode":"32901",
    "addr:street":"E Strawbridge Ave",
    "iso:country":"US",
    "sg:address":"525 E Strawbridge Ave",
    "sg:city":"Melbourne",
    "sg:classifiers":[
        {
            "category":"Professional",
            "subcategory":"Lawyer & Legal Services",
            "type":"Services"
        }
    ],
    "sg:phone":"+1 321 725 5525",
    "sg:postcode":"32901",
    "sg:province":"FL",
    "wof:name":"High Stack",
    "wof:placetype":"venue"
},
  "geometry": {"coordinates":[-80.611774,28.079363],"type":"Point"}
}