{
  "type": "Feature",
  "properties": {
    "addr:full":"7020 Georgia Ave West Palm Beach FL 33405",
    "addr:housenumber":"7020",
    "addr:postcode":"33405",
    "addr:street":"Georgia Ave",
    "iso:country":"US",
    "sg:address":"7020 Georgia Ave",
    "sg:city":"West Palm Beach",
    "sg:classifiers":[
        {
            "category":"Building & Trades",
            "subcategory":"Construction",
            "type":"Services"
        }
    ],
    "sg:phone":"+1 561 547 1040",
    "sg:postcode":"33405",
    "sg:province":"FL",
    "sg:tags":[
        "concrete",
        "work"
    ],
    "wof:name":"Sure Shot Shot Blasting",
    "wof:placetype":"venue"
},
  "geometry": {"coordinates":[-80.05921600000001,26.646395],"type":"Point"}
}