{
  "type": "Feature",
  "properties": {
    "iso:country":"US",
    "sg:address":"1419 Misty Glen Ln",
    "sg:city":"Brandon",
    "sg:classifiers":[
        {
            "category":"Retail",
            "subcategory":"Repair Shop",
            "type":"Services"
        }
    ],
    "sg:phone":"+1 813 610 9514",
    "sg:postcode":"33510",
    "sg:province":"FL",
    "sg:tags":[
        "air",
        "system",
        "conditioning"
    ],
    "wof:name":"Indoor Air Management",
    "wof:placetype":"venue"
},
  "geometry": {"coordinates":[-82.29966899999999,27.965107],"type":"Point"}
}