{
  "type": "Feature",
  "properties": {
    "addr:full":"13200 SW 54th Ct Hollywood FL 33027",
    "addr:housenumber":"13200",
    "addr:postcode":"33027",
    "addr:street":"Sw 54Th Ct",
    "iso:country":"US",
    "sg:address":"13200 SW 54th Ct",
    "sg:city":"Hollywood",
    "sg:classifiers":[
        {
            "category":"Shopping",
            "subcategory":"Computers & Home Electronics",
            "type":"Retail Goods"
        }
    ],
    "sg:phone":"+1 305 829 4053",
    "sg:postcode":"33027",
    "sg:province":"FL",
    "wof:name":"Maurice Trading Inc",
    "wof:placetype":"venue"
},
  "geometry": {"coordinates":[-80.32241399999999,25.957552],"type":"Point"}
}