{
  "type": "Feature",
  "properties": {
    "iso:country":"US",
    "sg:address":"1933 Island Walk Dr",
    "sg:city":"Orlando",
    "sg:classifiers":[
        {
            "category":"Professional",
            "subcategory":"Management & Consulting",
            "type":"Services"
        }
    ],
    "sg:phone":"+1 407 857 7781",
    "sg:postcode":"32824",
    "sg:province":"FL",
    "sg:tags":[
        "consultant",
        "business"
    ],
    "wof:name":"Hospitality Safeguards Inc",
    "wof:placetype":"venue"
},
  "geometry": {"coordinates":[-81.352914,28.367439],"type":"Point"}
}