{
  "type": "Feature",
  "properties": {
    "addr:full":"103 Orchid Cay Dr Palm Beach Gardens FL 33418",
    "addr:housenumber":"103",
    "addr:postcode":"33418",
    "addr:street":"Orchid Cay Dr",
    "iso:country":"US",
    "sg:address":"103 Orchid Cay Dr",
    "sg:city":"Palm Beach Gardens",
    "sg:classifiers":[
        {
            "category":"Professional",
            "subcategory":"Management & Consulting",
            "type":"Services"
        }
    ],
    "sg:phone":"+1 561 694 8499",
    "sg:postcode":"33418",
    "sg:province":"FL",
    "sg:tags":[
        "business"
    ],
    "wof:name":"Berg Consulting Group Inc",
    "wof:placetype":"venue"
},
  "geometry": {"coordinates":[-80.11618,26.823725],"type":"Point"}
}