{
  "type": "Feature",
  "properties": {
    "addr:full":"18553 SW 104th Ave Miami FL 33157",
    "addr:housenumber":"18553",
    "addr:postcode":"33157",
    "addr:street":"Sw 104Th Ave",
    "iso:country":"US",
    "sg:address":"18553 SW 104th Ave",
    "sg:city":"Miami",
    "sg:classifiers":[
        {
            "category":"Building & Trades",
            "subcategory":"Electrical",
            "type":"Services"
        }
    ],
    "sg:phone":"+1 305 971 0570",
    "sg:postcode":"33157",
    "sg:province":"FL",
    "sg:tags":[
        "electric",
        "contractor"
    ],
    "wof:name":"Sure Electrical Contractors",
    "wof:placetype":"venue"
},
  "geometry": {"coordinates":[-80.360287,25.59616],"type":"Point"}
}