{
  "type": "Feature",
  "properties": {
    "iso:country":"US",
    "sg:address":"20052 Bowman Rd",
    "sg:city":"Spring Hill",
    "sg:classifiers":[
        {
            "category":"Farming",
            "subcategory":"Farm",
            "type":"Manufacturing & Wholesale Goods"
        }
    ],
    "sg:phone":"+1 352 796 1416",
    "sg:postcode":"34610",
    "sg:province":"FL",
    "sg:tags":[
        "crop",
        "general"
    ],
    "wof:name":"Field of Dreams Farms Inc",
    "wof:placetype":"venue"
},
  "geometry": {"coordinates":[-82.482714,28.419135],"type":"Point"}
}