{
  "type": "Feature",
  "properties": {
    "addr:full":"2629 Crawfordville Hwy Crawfordville FL 32327",
    "addr:housenumber":"2629",
    "addr:postcode":"32327",
    "addr:street":"Crawfordville Hwy",
    "iso:country":"US",
    "sg:address":"2629 Crawfordville Hwy",
    "sg:city":"Crawfordville",
    "sg:classifiers":[
        {
            "category":"Banks & Credit Unions",
            "subcategory":"Bank",
            "type":"Services"
        }
    ],
    "sg:phone":"+1 850 926 2225",
    "sg:postcode":"32327",
    "sg:province":"FL",
    "wof:name":"Wakulla Bank",
    "wof:placetype":"venue"
},
  "geometry": {"coordinates":[-84.371408,30.193368],"type":"Point"}
}