{
  "type": "Feature",
  "properties": {
    "addr:full":"200 E Government St Pensacola FL 32502",
    "addr:housenumber":"200",
    "addr:postcode":"32502",
    "addr:street":"E Government St",
    "iso:country":"US",
    "sg:address":"200 E Government St",
    "sg:city":"Pensacola",
    "sg:classifiers":[
        {
            "category":"Professional",
            "subcategory":"Lawyer & Legal Services",
            "type":"Services"
        }
    ],
    "sg:phone":"+1 850 438 3338",
    "sg:postcode":"32502",
    "sg:province":"FL",
    "sg:tags":[
        "attorney"
    ],
    "wof:name":"Bilbrey & Cowan",
    "wof:placetype":"venue"
},
  "geometry": {"coordinates":[-87.210494,30.410034],"type":"Point"}
}