{
  "type": "Feature",
  "properties": {
    "addr:full":"25406 Cortez Blvd Brooksville FL 34601",
    "addr:housenumber":"25406",
    "addr:postcode":"34601",
    "addr:street":"Cortez Blvd",
    "iso:country":"US",
    "sg:address":"25406 Cortez Blvd",
    "sg:city":"Brooksville",
    "sg:classifiers":[
        {
            "category":"Shopping",
            "subcategory":"Pets & Pet Supplies",
            "type":"Retail Goods"
        },
        {
            "category":"Building & Trades",
            "subcategory":"Construction",
            "type":"Services"
        }
    ],
    "sg:phone":"+1 352 799 8002",
    "sg:postcode":"34601",
    "sg:province":"FL",
    "sg:tags":[
        "feed",
        "fence-sales",
        "supplement",
        "concentrate",
        "contractor"
    ],
    "wof:name":"Wagon Wheel Feed & Hardware Inc",
    "wof:placetype":"venue"
},
  "geometry": {"coordinates":[-82.314106,28.52552],"type":"Point"}
}