{
  "type": "Feature",
  "properties": {
    "iso:country":"US",
    "sg:address":"50 E Central Blvd",
    "sg:city":"Orlando",
    "sg:classifiers":[
        {
            "category":"Restaurant",
            "type":"Food & Drink"
        }
    ],
    "sg:menulink":"http://www.allmenus.com/fl/orlando/35536-crooked-bayou/menu/",
    "sg:phone":"+1 407 839 5852",
    "sg:postcode":"32801",
    "sg:province":"FL",
    "sg:tags":[
        "seafood",
        "american"
    ],
    "wof:name":"Crooked Bayou",
    "wof:placetype":"venue"
},
  "geometry": {"coordinates":[-81.37815999999999,28.542147],"type":"Point"}
}