{
  "type": "Feature",
  "properties": {
    "iso:country":"US",
    "sg:address":"2482 SE Garden Ter",
    "sg:city":"Port Saint Lucie",
    "sg:classifiers":[
        {
            "category":"Personal",
            "subcategory":"Barber",
            "type":"Services"
        }
    ],
    "sg:phone":"+1 772 398 6209",
    "sg:postcode":"34952",
    "sg:province":"FL",
    "sg:tags":[
        "shop"
    ],
    "wof:name":"City Center Barbershop",
    "wof:placetype":"venue"
},
  "geometry": {"coordinates":[-80.277196,27.268284],"type":"Point"}
}