{
  "type": "Feature",
  "properties": {
    "iso:country":"US",
    "sg:address":"2510 Stuart St",
    "sg:city":"Tallahassee",
    "sg:classifiers":[
        {
            "category":"Real Estate",
            "subcategory":"Real Estate Services",
            "type":"Services"
        },
        {
            "category":"Real Estate",
            "subcategory":"Real Estate Agent",
            "type":"Services"
        }
    ],
    "sg:phone":"+1 850 701 0011",
    "sg:postcode":"32304",
    "sg:province":"FL",
    "sg:tags":[
        "management"
    ],
    "wof:name":"Legacy Realty Inc",
    "wof:placetype":"venue"
},
  "geometry": {"coordinates":[-84.33060999999999,30.455574],"type":"Point"}
}