{
  "type": "Feature",
  "properties": {
    "iso:country":"US",
    "sg:address":"15590 SW 46th Ln",
    "sg:city":"Miami",
    "sg:classifiers":[
        {
            "category":"Freight",
            "type":"Transportation"
        }
    ],
    "sg:phone":"+1 305 207 7960",
    "sg:postcode":"33185",
    "sg:province":"FL",
    "sg:tags":[
        "operator",
        "local",
        "trucking"
    ],
    "wof:name":"Absolute Freight Transport",
    "wof:placetype":"venue"
},
  "geometry": {"coordinates":[-80.446094,25.72116],"type":"Point"}
}