{
  "type": "Feature",
  "properties": {
    "iso:country":"US",
    "sg:address":"4019 NW 25th St",
    "sg:city":"Miami",
    "sg:classifiers":[
        {
            "category":"Wholesale",
            "subcategory":"Electrical",
            "type":"Manufacturing & Wholesale Goods"
        }
    ],
    "sg:phone":"+1 305 874 7020",
    "sg:postcode":"33142",
    "sg:province":"FL",
    "sg:tags":[
        "equipment"
    ],
    "wof:name":"Evalautocom",
    "wof:placetype":"venue"
},
  "geometry": {"coordinates":[-80.262804,25.79864],"type":"Point"}
}