{
  "type": "Feature",
  "properties": {
    "addr:full":"4912 Sunset Blvd Port Richey FL 34668",
    "addr:housenumber":"4912",
    "addr:postcode":"34668",
    "addr:street":"Sunset Blvd",
    "iso:country":"US",
    "sg:address":"4912 Sunset Blvd",
    "sg:city":"Port Richey",
    "sg:classifiers":[
        {
            "category":"Freight",
            "type":"Transportation"
        }
    ],
    "sg:phone":"+1 813 637 8252",
    "sg:postcode":"34668",
    "sg:province":"FL",
    "sg:tags":[
        "consultant"
    ],
    "wof:name":"J Hoster Mobility",
    "wof:placetype":"venue"
},
  "geometry": {"coordinates":[-82.730351,28.271772],"type":"Point"}
}