{
  "type": "Feature",
  "properties": {
    "addr:full":"2126 Redleaf Dr Brandon FL 33510",
    "addr:housenumber":"2126",
    "addr:postcode":"33510",
    "addr:street":"Redleaf Dr",
    "iso:country":"US",
    "sg:address":"2126 Redleaf Dr",
    "sg:city":"Brandon",
    "sg:classifiers":[
        {
            "category":"Retail",
            "subcategory":"Laundry & Dry Cleaning",
            "type":"Services"
        }
    ],
    "sg:phone":"+1 813 643 8335",
    "sg:postcode":"33510",
    "sg:province":"FL",
    "sg:tags":[
        "cleaners",
        "rug",
        "carpet"
    ],
    "wof:name":"Magic Carpet Systems Inc",
    "wof:placetype":"venue"
},
  "geometry": {"coordinates":[-82.309786,27.975858],"type":"Point"}
}