{
  "type": "Feature",
  "properties": {
    "iso:country":"US",
    "sg:address":"742 Squirrel Ct",
    "sg:city":"Kissimmee",
    "sg:classifiers":[
        {
            "category":"Professional",
            "subcategory":"Business Services",
            "type":"Services"
        }
    ],
    "sg:phone":"+1 407 932 3904",
    "sg:postcode":"34759",
    "sg:province":"FL",
    "wof:name":"Abreah Enterprises",
    "wof:placetype":"venue"
},
  "geometry": {"coordinates":[-81.46431,28.112584],"type":"Point"}
}