{
  "type": "Feature",
  "properties": {
    "iso:country":"US",
    "sg:address":"501 NE 1st Ave Ste 300",
    "sg:city":"Miami",
    "sg:classifiers":[
        {
            "category":"Professional",
            "subcategory":"Lawyer & Legal Services",
            "type":"Services"
        }
    ],
    "sg:phone":"+1 954 462 6377",
    "sg:postcode":"33132",
    "sg:province":"FL",
    "wof:name":"Kutner Rubinoff Bush & Lerner PA",
    "wof:placetype":"venue"
},
  "geometry": {"coordinates":[-80.19210099999999,25.779301],"type":"Point"}
}