{
  "type": "Feature",
  "properties": {
    "addr:full":"3221 D Rd Loxahatchee FL 33470",
    "addr:housenumber":"3221",
    "addr:postcode":"33470",
    "addr:street":"D Rd",
    "iso:country":"US",
    "sg:address":"3221 D Rd",
    "sg:city":"Loxahatchee",
    "sg:classifiers":[
        {
            "category":"Farming",
            "subcategory":"Nursery",
            "type":"Manufacturing & Wholesale Goods"
        },
        {
            "category":"Shopping",
            "subcategory":"Crafts & Fabrics",
            "type":"Retail Goods"
        }
    ],
    "sg:phone":"+1 561 333 6889",
    "sg:postcode":"33470",
    "sg:province":"FL",
    "sg:tags":[
        "florists'",
        "supply",
        "nurseries-plants",
        "tree",
        "nursery-wholesale",
        "equipment",
        "growers'",
        "florist",
        "supplies-wholesale",
        "grower",
        "manufacturer"
    ],
    "wof:name":"D'asign Source",
    "wof:placetype":"venue"
},
  "geometry": {"coordinates":[-80.272847,26.724796],"type":"Point"}
}