{
  "type": "Feature",
  "properties": {
    "addr:full":"1735 23rd Ave N St Petersburg FL 33713",
    "addr:housenumber":"1735",
    "addr:postcode":"33713",
    "addr:street":"23Rd Ave N",
    "iso:country":"US",
    "sg:address":"1735 23rd Ave N",
    "sg:city":"St Petersburg",
    "sg:classifiers":[
        {
            "category":"Professional",
            "subcategory":"Business Services",
            "type":"Services"
        }
    ],
    "sg:phone":"+1 727 894 6546",
    "sg:postcode":"33713",
    "sg:province":"FL",
    "sg:tags":[
        "embroidery"
    ],
    "wof:name":"Always Stitchin",
    "wof:placetype":"venue"
},
  "geometry": {"coordinates":[-82.65874599999999,27.792972],"type":"Point"}
}