{
  "type": "Feature",
  "properties": {
    "iso:country":"US",
    "sg:address":"880 Jupiter Park Dr",
    "sg:city":"Jupiter",
    "sg:classifiers":[
        {
            "category":"Wholesale",
            "subcategory":"Medical Equipment & Supplies",
            "type":"Manufacturing & Wholesale Goods"
        }
    ],
    "sg:phone":"+1 561 744 3991",
    "sg:postcode":"33458",
    "sg:province":"FL",
    "sg:tags":[
        "dental"
    ],
    "sg:website":"www.henryschein.com",
    "wof:name":"Sullivan-Schein Dental",
    "wof:placetype":"venue"
},
  "geometry": {"coordinates":[-80.143649,26.926664],"type":"Point"}
}