{
  "type": "Feature",
  "properties": {
    "addr:full":"226 Cypress Ln Lake Worth FL 33461",
    "addr:housenumber":"226",
    "addr:postcode":"33461",
    "addr:street":"Cypress Ln",
    "iso:country":"US",
    "sg:address":"226 Cypress Ln",
    "sg:city":"Lake Worth",
    "sg:classifiers":[
        {
            "category":"Utilities",
            "subcategory":"Water",
            "type":"Services"
        }
    ],
    "sg:phone":"+1 561 965 4022",
    "sg:postcode":"33461",
    "sg:province":"FL",
    "sg:tags":[
        "dept"
    ],
    "wof:name":"Water Dept",
    "wof:placetype":"venue"
},
  "geometry": {"coordinates":[-80.095608,26.641504],"type":"Point"}
}