{
  "type": "Feature",
  "properties": {
    "iso:country":"US",
    "sg:address":"153 NE 1st Rd",
    "sg:city":"Homestead",
    "sg:classifiers":[
        {
            "category":"Communications",
            "subcategory":"Television Station",
            "type":"Services"
        }
    ],
    "sg:phone":"+1 305 247 4292",
    "sg:postcode":"33030",
    "sg:province":"FL",
    "sg:tags":[
        "satellite",
        "cable"
    ],
    "wof:name":"Globecast North America",
    "wof:placetype":"venue"
},
  "geometry": {"coordinates":[-80.47318300000001,25.471617],"type":"Point"}
}