{
  "type": "Feature",
  "properties": {
    "addr:full":"1744 N Fort Harrison Ave Clearwater FL 33755",
    "addr:housenumber":"1744",
    "addr:postcode":"33755",
    "addr:street":"N Fort Harrison Ave",
    "iso:country":"US",
    "sg:address":"1744 N Fort Harrison Ave",
    "sg:city":"Clearwater",
    "sg:classifiers":[
        {
            "category":"Travel",
            "subcategory":"Hotels & Motels",
            "type":"Entertainment"
        }
    ],
    "sg:phone":"+1 727 449 8688",
    "sg:postcode":"33755",
    "sg:province":"FL",
    "wof:name":"Pleasant Inn",
    "wof:placetype":"venue"
},
  "geometry": {"coordinates":[-82.796038,27.984481],"type":"Point"}
}