{
  "type": "Feature",
  "properties": {
    "addr:full":"4905 US Hwy 1 Mims FL 32754",
    "addr:housenumber":"4905",
    "addr:postcode":"32754",
    "addr:street":"Us Hwy 1 Mims",
    "iso:country":"US",
    "sg:address":"4905 US Hwy 1",
    "sg:city":"Mims",
    "sg:classifiers":[
        {
            "category":"Shopping",
            "subcategory":"Computers & Home Electronics",
            "type":"Retail Goods"
        }
    ],
    "sg:phone":"+1 321 267 7880",
    "sg:postcode":"32754",
    "sg:province":"FL",
    "wof:name":"SOS Computer Services",
    "wof:placetype":"venue"
},
  "geometry": {"coordinates":[-80.867099,28.734],"type":"Point"}
}