{
  "type": "Feature",
  "properties": {
    "iso:country":"US",
    "sg:address":"1123 NE 5th St",
    "sg:city":"Crystal River",
    "sg:classifiers":[
        {
            "category":"Retail",
            "subcategory":"Car Wash",
            "type":"Services"
        }
    ],
    "sg:phone":"+1 352 795 4361",
    "sg:postcode":"34429",
    "sg:province":"FL",
    "sg:tags":[
        "polishing",
        "washing"
    ],
    "wof:name":"Hands On Car Wash",
    "wof:placetype":"venue"
},
  "geometry": {"coordinates":[-82.57317,28.898406],"type":"Point"}
}