{
  "type": "Feature",
  "properties": {
    "iso:country":"US",
    "sg:address":"11022 NW 14th St",
    "sg:city":"Pompano Beach",
    "sg:classifiers":[
        {
            "category":"Banks & Credit Unions",
            "subcategory":"Financial Services",
            "type":"Services"
        }
    ],
    "sg:phone":"+1 954 752 1896",
    "sg:postcode":"33071",
    "sg:province":"FL",
    "sg:tags":[
        "trust",
        "management"
    ],
    "wof:name":"Ann I Grace Realty Trust",
    "wof:placetype":"venue"
},
  "geometry": {"coordinates":[-80.272645,26.24859],"type":"Point"}
}