{
  "type": "Feature",
  "properties": {
    "iso:country":"US",
    "sg:address":"1634 SE 47th St",
    "sg:city":"Cape Coral",
    "sg:classifiers":[
        {
            "category":"Banks & Credit Unions",
            "subcategory":"Bank",
            "type":"Services"
        }
    ],
    "sg:phone":"+1 239 549 7835",
    "sg:postcode":"33904",
    "sg:province":"FL",
    "sg:tags":[
        "loan",
        "real estate"
    ],
    "wof:name":"Paradise Home Builders",
    "wof:placetype":"venue"
},
  "geometry": {"coordinates":[-81.94081,26.564544],"type":"Point"}
}