{
  "type": "Feature",
  "properties": {
    "iso:country":"US",
    "sg:address":"3541 NE Jacksonville Rd",
    "sg:city":"Ocala",
    "sg:classifiers":[
        {
            "category":"Restaurant",
            "type":"Food & Drink"
        }
    ],
    "sg:phone":"+1 352 629 1771",
    "sg:postcode":"34479",
    "sg:province":"FL",
    "sg:tags":[
        "eating"
    ],
    "wof:name":"Family Affair Restaurant Inc",
    "wof:placetype":"venue"
},
  "geometry": {"coordinates":[-82.123598,29.223673],"type":"Point"}
}