{
  "type": "Feature",
  "properties": {
    "addr:full":"2730 Crane's Cove Dr Kissimmee FL 34741",
    "addr:postcode":"2730;34741",
    "addr:street":"Crane'S Cove Dr",
    "iso:country":"US",
    "sg:address":"2730 Crane's Cove Dr",
    "sg:city":"Kissimmee",
    "sg:classifiers":[
        {
            "category":"Banks & Credit Unions",
            "subcategory":"Financial Services",
            "type":"Services"
        }
    ],
    "sg:phone":"+1 407 933 0511",
    "sg:postcode":"34741",
    "sg:province":"FL",
    "sg:tags":[
        "investor"
    ],
    "wof:name":"Eshquez Investment Co",
    "wof:placetype":"venue"
},
  "geometry": {"coordinates":[-81.43272399999999,28.345554],"type":"Point"}
}