{
  "type": "Feature",
  "properties": {
    "addr:full":"1001 E Atlantic Ave Delray Beach FL 33483",
    "addr:housenumber":"1001",
    "addr:postcode":"33483",
    "addr:street":"E Atlantic Ave",
    "iso:country":"US",
    "sg:address":"1001 E Atlantic Ave",
    "sg:city":"Delray Beach",
    "sg:classifiers":[
        {
            "category":"Banks & Credit Unions",
            "subcategory":"Bank",
            "type":"Services"
        }
    ],
    "sg:phone":"+1 561 279 0060",
    "sg:postcode":"33483",
    "sg:province":"FL",
    "wof:name":"Bank Of America",
    "wof:placetype":"venue"
},
  "geometry": {"coordinates":[-80.061832,26.461681],"type":"Point"}
}