{
  "type": "Feature",
  "properties": {
    "iso:country":"US",
    "sg:address":"4151 US Hwy 92",
    "sg:city":"Sanford",
    "sg:classifiers":[
        {
            "category":"Railroad",
            "type":"Transportation"
        }
    ],
    "sg:phone":"+1 407 330 0321",
    "sg:postcode":"32771",
    "sg:province":"FL",
    "wof:name":"Chasis Seaboard Expansion",
    "wof:placetype":"venue"
},
  "geometry": {"coordinates":[-81.324412,28.835906],"type":"Point"}
}