{
  "type": "Feature",
  "properties": {
    "addr:full":"607 SW Curry St Port Saint Lucie FL 34983",
    "addr:housenumber":"607",
    "addr:postcode":"34983",
    "addr:street":"Sw Curry St",
    "iso:country":"US",
    "sg:address":"607 SW Curry St",
    "sg:city":"Port Saint Lucie",
    "sg:classifiers":[
        {
            "category":"Building & Trades",
            "subcategory":"Pest Control",
            "type":"Services"
        }
    ],
    "sg:phone":"+1 772 340 2469",
    "sg:postcode":"34983",
    "sg:province":"FL",
    "wof:name":"Genuine Pest Control",
    "wof:placetype":"venue"
},
  "geometry": {"coordinates":[-80.356264,27.311663],"type":"Point"}
}