{
  "type": "Feature",
  "properties": {
    "iso:country":"US",
    "sg:address":"205 Davie Blvd",
    "sg:city":"Fort Lauderdale",
    "sg:classifiers":[
        {
            "category":"Communications",
            "subcategory":"Film & Video Production",
            "type":"Services"
        }
    ],
    "sg:phone":"+1 954 527 0108",
    "sg:postcode":"33315",
    "sg:province":"FL",
    "sg:tags":[
        "taping"
    ],
    "wof:name":"AVP Video",
    "wof:placetype":"venue"
},
  "geometry": {"coordinates":[-80.14706700000001,26.107436],"type":"Point"}
}