{
  "type": "Feature",
  "properties": {
    "iso:country":"US",
    "sg:address":"7750 Beneva Rd",
    "sg:city":"Sarasota",
    "sg:classifiers":[
        {
            "category":"Organizations",
            "subcategory":"Religious Organization",
            "type":"Services"
        }
    ],
    "sg:phone":"+1 941 924 4664",
    "sg:postcode":"34238",
    "sg:province":"FL",
    "sg:tags":[
        "church"
    ],
    "sg:website":"www.faithsarasota.com",
    "wof:name":"Faith Lutheran CHURCH-Elca",
    "wof:placetype":"venue"
},
  "geometry": {"coordinates":[-82.49757,27.241849],"type":"Point"}
}