{
  "type": "Feature",
  "properties": {
    "iso:country":"US",
    "sg:address":"2731 Co Rd 381",
    "sg:city":"Wewahitchka",
    "sg:classifiers":[
        {
            "category":"Government",
            "subcategory":"Fire Station",
            "type":"Public Place"
        }
    ],
    "sg:phone":"+1 850 639 3099",
    "sg:postcode":"32465",
    "sg:province":"FL",
    "sg:tags":[
        "firefighting"
    ],
    "wof:name":"Dalkeith Volunteer Fire Dept",
    "wof:placetype":"venue"
},
  "geometry": {"coordinates":[-85.168222,30.030327],"type":"Point"}
}