{
  "type": "Feature",
  "properties": {
    "addr:full":"1255 SW 101st Ter Hollywood FL 33025",
    "addr:housenumber":"1255",
    "addr:postcode":"33025",
    "addr:street":"Sw 101St Ter",
    "iso:country":"US",
    "sg:address":"1255 SW 101st Ter",
    "sg:city":"Hollywood",
    "sg:classifiers":[
        {
            "category":"Professional",
            "type":"Services"
        }
    ],
    "sg:phone":"+1 954 322 3829",
    "sg:postcode":"33025",
    "sg:province":"FL",
    "wof:name":"Eco Moda Intl Bus Corp",
    "wof:placetype":"venue"
},
  "geometry": {"coordinates":[-80.28056599999999,25.99634],"type":"Point"}
}