{
  "type": "Feature",
  "properties": {
    "iso:country":"US",
    "sg:address":"7801 22nd Ave N",
    "sg:city":"St Petersburg",
    "sg:classifiers":[
        {
            "category":"Education",
            "subcategory":"Library",
            "type":"Public Place"
        }
    ],
    "sg:phone":"+1 727 893 7930",
    "sg:postcode":"33710",
    "sg:province":"FL",
    "wof:name":"St Petersburg Library",
    "wof:placetype":"venue"
},
  "geometry": {"coordinates":[-82.746475,27.792362],"type":"Point"}
}