{
  "type": "Feature",
  "properties": {
    "iso:country":"US",
    "sg:address":"4156 Brookmyra Dr",
    "sg:city":"Orlando",
    "sg:classifiers":[
        {
            "category":"Health Services",
            "subcategory":"Doctor",
            "type":"Services"
        }
    ],
    "sg:phone":"+1 407 855 2619",
    "sg:postcode":"32837",
    "sg:province":"FL",
    "sg:tags":[
        "physician",
        "surgeon"
    ],
    "wof:name":"Infectious Disease Consultant",
    "wof:placetype":"venue"
},
  "geometry": {"coordinates":[-81.433887,28.360695],"type":"Point"}
}