{
  "type": "Feature",
  "properties": {
    "addr:full":"4221 NW 19 St Gainesville FL 32605",
    "addr:housenumber":"4221",
    "addr:postcode":"32605",
    "addr:street":"Nw 19 St",
    "iso:country":"US",
    "sg:address":"4221 NW 19 St",
    "sg:city":"Gainesville",
    "sg:classifiers":[
        {
            "category":"Communications",
            "subcategory":"Radio Station",
            "type":"Services"
        }
    ],
    "sg:phone":"+1 352 373 4912",
    "sg:postcode":"32605",
    "sg:province":"FL",
    "sg:tags":[
        "educational"
    ],
    "wof:name":"Benjamin Hebblethwaite",
    "wof:placetype":"venue"
},
  "geometry": {"coordinates":[-82.347223,29.693781],"type":"Point"}
}