{
  "type": "Feature",
  "properties": {
    "iso:country":"US",
    "sg:address":"1749 Harpoon Dr",
    "sg:city":"Holiday",
    "sg:classifiers":[
        {
            "category":"Organizations",
            "subcategory":"Professional Association",
            "type":"Services"
        }
    ],
    "sg:phone":"+1 727 934 2616",
    "sg:postcode":"34690",
    "sg:province":"FL",
    "sg:tags":[
        "business",
        "trade"
    ],
    "wof:name":"Forest Hills Civic Assoc",
    "wof:placetype":"venue"
},
  "geometry": {"coordinates":[-82.725227,28.184367],"type":"Point"}
}