{
  "type": "Feature",
  "properties": {
    "iso:country":"US",
    "sg:address":"3219 Co Rd 630",
    "sg:city":"Fort Meade",
    "sg:classifiers":[
        {
            "category":"Retail",
            "subcategory":"Auto Repair",
            "type":"Services"
        }
    ],
    "sg:phone":"+1 863 285 8370",
    "sg:postcode":"33841",
    "sg:province":"FL",
    "sg:tags":[
        "transmission"
    ],
    "wof:name":"Florida Gas Transmission Co",
    "wof:placetype":"venue"
},
  "geometry": {"coordinates":[-81.74600700000001,27.747978],"type":"Point"}
}