{
  "type": "Feature",
  "properties": {
    "addr:full":"580 Cox Rd Cocoa FL 32926",
    "addr:housenumber":"580",
    "addr:postcode":"32926",
    "addr:street":"Cox Rd",
    "iso:country":"US",
    "sg:address":"580 Cox Rd",
    "sg:city":"Cocoa",
    "sg:classifiers":[
        {
            "category":"Building & Trades",
            "subcategory":"Plumbing",
            "type":"Services"
        },
        {
            "category":"Building & Trades",
            "subcategory":"Construction",
            "type":"Services"
        }
    ],
    "sg:phone":"+1 321 632 7707",
    "sg:postcode":"32926",
    "sg:province":"FL",
    "sg:tags":[
        "bathroom",
        "industrial",
        "remodeling",
        "plumber",
        "contractors-commercial"
    ],
    "wof:name":"Sawyer Plumbing Of Brevard, Inc",
    "wof:placetype":"venue"
},
  "geometry": {"coordinates":[-80.787982,28.365766],"type":"Point"}
}