{
  "type": "Feature",
  "properties": {
    "addr:full":"5535 SW 8th St Coral Gables FL 33134",
    "addr:housenumber":"5535",
    "addr:postcode":"33134",
    "addr:street":"Sw 8Th St",
    "iso:country":"US",
    "sg:address":"5535 SW 8th St",
    "sg:city":"Coral Gables",
    "sg:classifiers":[
        {
            "category":"Home & Garden",
            "subcategory":"Carpets & Floor Coverings",
            "type":"Retail Goods"
        }
    ],
    "sg:phone":"+1 305 266 5535",
    "sg:postcode":"33134",
    "sg:province":"FL",
    "sg:tags":[
        "carpeting"
    ],
    "wof:name":"Oscar Carpet",
    "wof:placetype":"venue"
},
  "geometry": {"coordinates":[-80.28469800000001,25.763599],"type":"Point"}
}