{
  "type": "Feature",
  "properties": {
    "addr:full":"4605 Myla Ln West Palm Beach FL 33417",
    "addr:housenumber":"4605",
    "addr:postcode":"33417",
    "addr:street":"Myla Ln",
    "iso:country":"US",
    "sg:address":"4605 Myla Ln",
    "sg:city":"West Palm Beach",
    "sg:classifiers":[
        {
            "category":"Building & Trades",
            "subcategory":"Cleaning & Sanitation",
            "type":"Services"
        }
    ],
    "sg:phone":"+1 561 640 0043",
    "sg:postcode":"33417",
    "sg:province":"FL",
    "sg:tags":[
        "janitor"
    ],
    "wof:name":"At Your Svc",
    "wof:placetype":"venue"
},
  "geometry": {"coordinates":[-80.114024,26.702719],"type":"Point"}
}