{
  "type": "Feature",
  "properties": {
    "addr:full":"3651 W Hillsborough Ave Tampa FL 33614",
    "addr:housenumber":"3651",
    "addr:postcode":"33614",
    "addr:street":"W Hillsborough Ave",
    "iso:country":"US",
    "sg:address":"3651 W Hillsborough Ave",
    "sg:city":"Tampa",
    "sg:classifiers":[
        {
            "category":"Restaurant",
            "type":"Food & Drink"
        }
    ],
    "sg:phone":"+1 813 871 3466",
    "sg:postcode":"33614",
    "sg:province":"FL",
    "wof:name":"Dino's",
    "wof:placetype":"venue"
},
  "geometry": {"coordinates":[-82.50248499999999,27.996016],"type":"Point"}
}