{
  "type": "Feature",
  "properties": {
    "iso:country":"US",
    "sg:address":"15 Shumard St",
    "sg:city":"Osprey",
    "sg:classifiers":[
        {
            "category":"Building & Trades",
            "subcategory":"Construction",
            "type":"Services"
        }
    ],
    "sg:phone":"+1 941 966 6771",
    "sg:postcode":"34229",
    "sg:province":"FL",
    "sg:tags":[
        "builder",
        "operative"
    ],
    "wof:name":"Bfm Home Designers and Builder",
    "wof:placetype":"venue"
},
  "geometry": {"coordinates":[-82.490348,27.196853],"type":"Point"}
}