{
  "type": "Feature",
  "properties": {
    "iso:country":"US",
    "sg:address":"2663 2nd St",
    "sg:city":"Fort Myers",
    "sg:classifiers":[
        {
            "category":"Organizations",
            "subcategory":"Religious Organization",
            "type":"Services"
        }
    ],
    "sg:phone":"+1 239 334 9125",
    "sg:postcode":"33916",
    "sg:province":"FL",
    "wof:name":"Free At Last Ministry",
    "wof:placetype":"venue"
},
  "geometry": {"coordinates":[-81.857789,26.6473],"type":"Point"}
}