{
  "type": "Feature",
  "properties": {
    "iso:country":"US",
    "sg:address":"1884 N Co Hwy 393",
    "sg:city":"Santa Rosa Beach",
    "sg:classifiers":[
        {
            "category":"Banks & Credit Unions",
            "subcategory":"Bank",
            "type":"Services"
        }
    ],
    "sg:phone":"+1 850 278 0400",
    "sg:postcode":"32459",
    "sg:province":"FL",
    "wof:name":"Trustmark National Bank",
    "wof:placetype":"venue"
},
  "geometry": {"coordinates":[-86.22826499999999,30.40319],"type":"Point"}
}