{
  "type": "Feature",
  "properties": {
    "iso:country":"US",
    "sg:address":"2967 Vineland Rd",
    "sg:city":"Kissimmee",
    "sg:classifiers":[
        {
            "category":"Professional",
            "subcategory":"Engineering",
            "type":"Services"
        }
    ],
    "sg:phone":"+1 407 396 0071",
    "sg:postcode":"34746",
    "sg:province":"FL",
    "sg:tags":[
        "engineer"
    ],
    "wof:name":"H W Lochner Inc",
    "wof:placetype":"venue"
},
  "geometry": {"coordinates":[-81.480603,28.338551],"type":"Point"}
}