{
  "type": "Feature",
  "properties": {
    "iso:country":"US",
    "sg:address":"3285 Westwood Dr",
    "sg:city":"Titusville",
    "sg:classifiers":[
        {
            "category":"Shopping",
            "subcategory":"Bicycles & Sporting Goods",
            "type":"Retail Goods"
        }
    ],
    "sg:phone":"+1 321 383 0470",
    "sg:postcode":"32796",
    "sg:province":"FL",
    "wof:name":"H 20 Pipesports",
    "wof:placetype":"venue"
},
  "geometry": {"coordinates":[-80.84617799999999,28.644492],"type":"Point"}
}