{
  "type": "Feature",
  "properties": {
    "iso:country":"US",
    "sg:address":"3790 Tamiami Trl N",
    "sg:city":"Naples",
    "sg:classifiers":[
        {
            "category":"Home & Garden",
            "subcategory":"Furniture",
            "type":"Retail Goods"
        }
    ],
    "sg:phone":"+1 239 262 8182",
    "sg:postcode":"34103",
    "sg:province":"FL",
    "wof:name":"Thomasville Home Furnishings",
    "wof:placetype":"venue"
},
  "geometry": {"coordinates":[-81.79997400000001,26.190555],"type":"Point"}
}