{
  "type": "Feature",
  "properties": {
    "addr:full":"1401 W 7th St West Palm Beach FL 33404",
    "addr:housenumber":"1401",
    "addr:postcode":"33404",
    "addr:street":"W 7Th St",
    "iso:country":"US",
    "sg:address":"1401 W 7th St",
    "sg:city":"West Palm Beach",
    "sg:classifiers":[
        {
            "category":"Building & Trades",
            "subcategory":"Construction",
            "type":"Services"
        }
    ],
    "sg:phone":"+1 561 863 9964",
    "sg:postcode":"33404",
    "sg:province":"FL",
    "wof:name":"Grady Parker Paving Inc",
    "wof:placetype":"venue"
},
  "geometry": {"coordinates":[-80.07518899999999,26.768939],"type":"Point"}
}