{
  "type": "Feature",
  "properties": {
    "iso:country":"US",
    "sg:address":"2001 Normandy Cir",
    "sg:city":"West Palm Beach",
    "sg:classifiers":[
        {
            "category":"Professional",
            "type":"Services"
        }
    ],
    "sg:phone":"+1 561 686 6447",
    "sg:postcode":"33409",
    "sg:province":"FL",
    "sg:tags":[
        "establishment"
    ],
    "wof:name":"Normandy Village POA",
    "wof:placetype":"venue"
},
  "geometry": {"coordinates":[-80.091183,26.731036],"type":"Point"}
}