{
  "type": "Feature",
  "properties": {
    "iso:country":"US",
    "sg:address":"525 Forest Way",
    "sg:city":"Longboat Key",
    "sg:classifiers":[
        {
            "category":"Retail",
            "subcategory":"Laundry & Dry Cleaning",
            "type":"Services"
        }
    ],
    "sg:phone":"+1 941 383 6312",
    "sg:postcode":"34228",
    "sg:province":"FL",
    "sg:tags":[
        "cleaners"
    ],
    "wof:name":"White Sands Cleaners",
    "wof:placetype":"venue"
},
  "geometry": {"coordinates":[-82.662069,27.416218],"type":"Point"}
}