{
  "type": "Feature",
  "properties": {
    "addr:full":"5500 S Dixie Hwy West Palm Beach FL 33405",
    "addr:housenumber":"5500",
    "addr:postcode":"33405",
    "addr:street":"S Dixie Hwy",
    "iso:country":"US",
    "sg:address":"5500 S Dixie Hwy",
    "sg:city":"West Palm Beach",
    "sg:classifiers":[
        {
            "category":"Retail",
            "subcategory":"Laundry & Dry Cleaning",
            "type":"Services"
        }
    ],
    "sg:phone":"+1 561 588 8645",
    "sg:postcode":"33405",
    "sg:province":"FL",
    "sg:tags":[
        "cleaners"
    ],
    "sg:website":"www.spartancleaners.com",
    "wof:name":"Spartan Cleaners",
    "wof:placetype":"venue"
},
  "geometry": {"coordinates":[-80.055544,26.66464],"type":"Point"}
}