{
  "type": "Feature",
  "properties": {
    "addr:full":"5845 Palmer Blvd Sarasota FL 34232",
    "addr:housenumber":"5845",
    "addr:postcode":"34232",
    "addr:street":"Palmer Blvd",
    "iso:country":"US",
    "sg:address":"5845 Palmer Blvd",
    "sg:city":"Sarasota",
    "sg:classifiers":[
        {
            "category":"Retail",
            "subcategory":"Auto Repair",
            "type":"Services"
        }
    ],
    "sg:phone":"+1 941 371 9418",
    "sg:postcode":"34232",
    "sg:province":"FL",
    "sg:tags":[
        "recreational",
        "vehicle"
    ],
    "wof:name":"Adventure Rv Inc",
    "wof:placetype":"venue"
},
  "geometry": {"coordinates":[-82.449995,27.326575],"type":"Point"}
}