{
  "type": "Feature",
  "properties": {
    "addr:full":"220 Holloway Dr Fort Lauderdale FL 33317",
    "addr:housenumber":"220",
    "addr:postcode":"33317",
    "addr:street":"Holloway Dr",
    "iso:country":"US",
    "sg:address":"220 Holloway Dr",
    "sg:city":"Fort Lauderdale",
    "sg:classifiers":[
        {
            "category":"Real Estate",
            "subcategory":"Real Estate Agent",
            "type":"Services"
        }
    ],
    "sg:phone":"+1 954 721 4172",
    "sg:postcode":"33317",
    "sg:province":"FL",
    "sg:tags":[
        "building",
        "apartment"
    ],
    "wof:name":"Stratford Gardens Apartments",
    "wof:placetype":"venue"
},
  "geometry": {"coordinates":[-80.235016,26.126542],"type":"Point"}
}