{
  "type": "Feature",
  "properties": {
    "addr:full":"2175 Lake Ave SE Largo FL 33771",
    "addr:housenumber":"2175",
    "addr:postcode":"33771",
    "addr:street":"Lake Ave Se",
    "iso:country":"US",
    "sg:address":"2175 Lake Ave SE",
    "sg:city":"Largo",
    "sg:classifiers":[
        {
            "category":"Building & Trades",
            "subcategory":"Construction",
            "type":"Services"
        }
    ],
    "sg:phone":"+1 727 586 4118",
    "sg:postcode":"33771",
    "sg:province":"FL",
    "sg:tags":[
        "specializing",
        "home",
        "remodeling",
        "room",
        "contractor"
    ],
    "wof:name":"Osinga Construction Inc",
    "wof:placetype":"venue"
},
  "geometry": {"coordinates":[-82.77074,27.894898],"type":"Point"}
}