{
  "type": "Feature",
  "properties": {
    "addr:full":"838 Navy St Fort Walton Bch FL 32547",
    "addr:housenumber":"838",
    "addr:postcode":"32547",
    "addr:street":"Navy St",
    "iso:country":"US",
    "sg:address":"838 Navy St",
    "sg:city":"Fort Walton Bch",
    "sg:classifiers":[
        {
            "category":"Retail",
            "subcategory":"Auto Repair",
            "type":"Services"
        }
    ],
    "sg:phone":"+1 850 862 6868",
    "sg:postcode":"32547",
    "sg:province":"FL",
    "sg:tags":[
        "repairing",
        "automobile"
    ],
    "wof:name":"Neese Automotive",
    "wof:placetype":"venue"
},
  "geometry": {"coordinates":[-86.626632,30.447085],"type":"Point"}
}