{
  "type": "Feature",
  "properties": {
    "iso:country":"US",
    "sg:address":"1319 N Observatory Dr",
    "sg:city":"Orlando",
    "sg:classifiers":[
        {
            "category":"Freight",
            "type":"Transportation"
        }
    ],
    "sg:phone":"+1 407 297 3871",
    "sg:postcode":"32818",
    "sg:province":"FL",
    "sg:tags":[
        "operator",
        "local",
        "trucking"
    ],
    "wof:name":"Mike Hauling Inc",
    "wof:placetype":"venue"
},
  "geometry": {"coordinates":[-81.46860100000001,28.55921],"type":"Point"}
}