{
  "type": "Feature",
  "properties": {
    "iso:country":"US",
    "sg:address":"2335 NW 107th Ave",
    "sg:city":"Doral",
    "sg:classifiers":[
        {
            "category":"Health Services",
            "subcategory":"Doctor",
            "type":"Services"
        }
    ],
    "sg:phone":"+1 305 418 2242",
    "sg:postcode":"33172",
    "sg:province":"FL",
    "sg:tags":[
        "physician",
        "surgeon"
    ],
    "wof:name":"Euro Med Group",
    "wof:placetype":"venue"
},
  "geometry": {"coordinates":[-80.36899,25.795796],"type":"Point"}
}