{
  "type": "Feature",
  "properties": {
    "iso:country":"US",
    "sg:address":"1133 SE 24th Ter",
    "sg:city":"Ocala",
    "sg:classifiers":[
        {
            "category":"Wholesale",
            "subcategory":"Metals & Minerals",
            "type":"Manufacturing & Wholesale Goods"
        }
    ],
    "sg:phone":"+1 352 690 7116",
    "sg:postcode":"34471",
    "sg:province":"FL",
    "sg:tags":[
        "steel",
        "warehouse"
    ],
    "wof:name":"Accro Met Inc",
    "wof:placetype":"venue"
},
  "geometry": {"coordinates":[-82.103909,29.179504],"type":"Point"}
}