{
  "type": "Feature",
  "properties": {
    "addr:full":"8354 NE 33rd Ct Anthony FL 32617",
    "addr:housenumber":"8354",
    "addr:postcode":"32617",
    "addr:street":"Ne 33Rd Ct",
    "iso:country":"US",
    "sg:address":"8354 NE 33rd Ct",
    "sg:city":"Anthony",
    "sg:classifiers":[
        {
            "category":"Shopping",
            "subcategory":"Computers & Home Electronics",
            "type":"Retail Goods"
        }
    ],
    "sg:phone":"+1 352 622 4551",
    "sg:postcode":"32617",
    "sg:province":"FL",
    "wof:name":"Lightspeed Computer Service",
    "wof:placetype":"venue"
},
  "geometry": {"coordinates":[-82.090929,29.269805],"type":"Point"}
}