{
  "type": "Feature",
  "properties": {
    "iso:country":"US",
    "sg:address":"1375 NW 97th Ave",
    "sg:city":"Miami",
    "sg:classifiers":[
        {
            "category":"Freight",
            "type":"Transportation"
        }
    ],
    "sg:phone":"+1 305 222 0401",
    "sg:postcode":"33172",
    "sg:province":"FL",
    "sg:tags":[
        "arrangement"
    ],
    "wof:name":"Kalpatronics",
    "wof:placetype":"venue"
},
  "geometry": {"coordinates":[-80.35279800000001,25.789512],"type":"Point"}
}