{
  "type": "Feature",
  "properties": {
    "addr:full":"1028 Apollo Beach Blvd Apollo Beach FL 33572",
    "addr:housenumber":"1028",
    "addr:postcode":"33572",
    "addr:street":"Apollo Beach Blvd",
    "iso:country":"US",
    "sg:address":"1028 Apollo Beach Blvd",
    "sg:city":"Apollo Beach",
    "sg:classifiers":[
        {
            "category":"Organizations",
            "subcategory":"Professional Association",
            "type":"Services"
        },
        {
            "category":"Organizations",
            "subcategory":"Community Association",
            "type":"Services"
        }
    ],
    "sg:phone":"+1 813 645 4090",
    "sg:postcode":"33572",
    "sg:province":"FL",
    "wof:name":"Anchor Point Condominium Assn",
    "wof:placetype":"venue"
},
  "geometry": {"coordinates":[-82.41631599999999,27.776581],"type":"Point"}
}