{
  "type": "Feature",
  "properties": {
    "iso:country":"US",
    "sg:address":"2470 NW 102nd Pl",
    "sg:city":"Miami",
    "sg:classifiers":[
        {
            "category":"Wholesale",
            "subcategory":"Non-durable Goods",
            "type":"Manufacturing & Wholesale Goods"
        }
    ],
    "sg:phone":"+1 305 594 3993",
    "sg:postcode":"33172",
    "sg:province":"FL",
    "sg:tags":[
        "merchandise",
        "general"
    ],
    "wof:name":"Venus Trading Inc",
    "wof:placetype":"venue"
},
  "geometry": {"coordinates":[-80.362717,25.793729],"type":"Point"}
}