{
  "type": "Feature",
  "properties": {
    "iso:country":"US",
    "sg:address":"9500 NW 77th Ave Ste 27",
    "sg:city":"Hialeah",
    "sg:classifiers":[
        {
            "category":"Banks & Credit Unions",
            "subcategory":"Financial Services",
            "type":"Services"
        }
    ],
    "sg:phone":"+1 305 512 4579",
    "sg:postcode":"33016",
    "sg:province":"FL",
    "sg:tags":[
        "broker",
        "mortgage"
    ],
    "wof:name":"Ruga Bay Mortgage Corp",
    "wof:placetype":"venue"
},
  "geometry": {"coordinates":[-80.323212,25.859815],"type":"Point"}
}