{
  "type": "Feature",
  "properties": {
    "iso:country":"US",
    "sg:address":"2771 Overseas Hwy",
    "sg:city":"Marathon",
    "sg:classifiers":[
        {
            "category":"Shopping",
            "subcategory":"Used Merchandise",
            "type":"Retail Goods"
        }
    ],
    "sg:phone":"+1 305 743 6506",
    "sg:postcode":"33050",
    "sg:province":"FL",
    "sg:tags":[
        "appliance"
    ],
    "wof:name":"Double D Used Furniture & Appl",
    "wof:placetype":"venue"
},
  "geometry": {"coordinates":[-81.09882500000001,24.710002],"type":"Point"}
}