{
  "type": "Feature",
  "properties": {
    "iso:country":"US",
    "sg:address":"6200 SW 73rd St",
    "sg:city":"South Miami",
    "sg:classifiers":[
        {
            "category":"Social Services",
            "type":"Services"
        }
    ],
    "sg:phone":"+1 786 662 8130",
    "sg:postcode":"33143",
    "sg:province":"FL",
    "sg:tags":[
        "organization",
        "welfare"
    ],
    "wof:name":"AARP Volunteer Information",
    "wof:placetype":"venue"
},
  "geometry": {"coordinates":[-80.293831,25.703008],"type":"Point"}
}