{
  "type": "Feature",
  "properties": {
    "iso:country":"US",
    "sg:address":"4737 Mile Stretch Dr",
    "sg:city":"Holiday",
    "sg:classifiers":[
        {
            "category":"Government",
            "subcategory":"Post Office",
            "type":"Public Place"
        }
    ],
    "sg:phone":"+1 727 937 2207",
    "sg:postcode":"34690",
    "sg:province":"FL",
    "sg:tags":[
        "postal",
        "us"
    ],
    "wof:name":"US Post Office",
    "wof:placetype":"venue"
},
  "geometry": {"coordinates":[-82.734132,28.188052],"type":"Point"}
}