{
  "type": "Feature",
  "properties": {
    "addr:full":"2005 SE Cove Rd Stuart FL 34997",
    "addr:housenumber":"2005",
    "addr:postcode":"34997",
    "addr:street":"Se Cove Rd",
    "iso:country":"US",
    "sg:address":"2005 SE Cove Rd",
    "sg:city":"Stuart",
    "sg:classifiers":[
        {
            "category":"Wholesale",
            "subcategory":"Plants",
            "type":"Manufacturing & Wholesale Goods"
        }
    ],
    "sg:phone":"+1 772 287 1318",
    "sg:postcode":"34997",
    "sg:province":"FL",
    "sg:tags":[
        "supply"
    ],
    "wof:name":"Willoughby Land Co",
    "wof:placetype":"venue"
},
  "geometry": {"coordinates":[-80.229207,27.125329],"type":"Point"}
}