{
  "type": "Feature",
  "properties": {
    "iso:country":"US",
    "sg:address":"5437 Airport Pulling Rd N",
    "sg:city":"Naples",
    "sg:classifiers":[
        {
            "category":"Food & Beverages",
            "subcategory":"Groceries & Convenience Stores",
            "type":"Retail Goods"
        }
    ],
    "sg:phone":"+1 239 254 7855",
    "sg:postcode":"34109",
    "sg:province":"FL",
    "sg:tags":[
        "grocer"
    ],
    "wof:name":"Eurepoean Food Market",
    "wof:placetype":"venue"
},
  "geometry": {"coordinates":[-81.768466,26.214912],"type":"Point"}
}