{
  "type": "Feature",
  "properties": {
    "addr:full":"3009 Gulf To Bay Blvd Clearwater FL 33759",
    "addr:housenumber":"3009",
    "addr:postcode":"33759",
    "addr:street":"Gulf To Bay Blvd",
    "iso:country":"US",
    "sg:address":"3009 Gulf To Bay Blvd",
    "sg:city":"Clearwater",
    "sg:classifiers":[
        {
            "category":"Autos & Motor Vehicles",
            "subcategory":"Fuel & Gas Station",
            "type":"Retail Goods"
        }
    ],
    "sg:phone":"+1 727 723 7875",
    "sg:postcode":"33759",
    "sg:province":"FL",
    "sg:tags":[
        "oil"
    ],
    "wof:name":"Clearwater BP",
    "wof:placetype":"venue"
},
  "geometry": {"coordinates":[-82.711916,27.960602],"type":"Point"}
}