{
  "type": "Feature",
  "properties": {
    "iso:country":"US",
    "sg:address":"1301 S Federal Hwy",
    "sg:city":"Lake Worth",
    "sg:classifiers":[
        {
            "category":"Manufacturing",
            "subcategory":"Tools & Machinery",
            "type":"Manufacturing & Wholesale Goods"
        }
    ],
    "sg:phone":"+1 561 585 0291",
    "sg:postcode":"33460",
    "sg:province":"FL",
    "sg:tags":[
        "construction",
        "mfg"
    ],
    "wof:name":"Steamroller Inc",
    "wof:placetype":"venue"
},
  "geometry": {"coordinates":[-80.05247799999999,26.598802],"type":"Point"}
}