{
  "type": "Feature",
  "properties": {
    "addr:full":"4240 W 16th Ave Hialeah FL 33012",
    "addr:housenumber":"4240",
    "addr:postcode":"33012",
    "addr:street":"W 16Th Ave",
    "iso:country":"US",
    "sg:address":"4240 W 16th Ave",
    "sg:city":"Hialeah",
    "sg:classifiers":[
        {
            "category":"Health Services",
            "subcategory":"Doctor",
            "type":"Services"
        }
    ],
    "sg:phone":"+1 305 823 1882",
    "sg:postcode":"33012",
    "sg:province":"FL",
    "sg:tags":[
        "surgeon",
        "oral"
    ],
    "wof:name":"Soler Rosa Maria DDS",
    "wof:placetype":"venue"
},
  "geometry": {"coordinates":[-80.314598,25.860201],"type":"Point"}
}