{
  "type": "Feature",
  "properties": {
    "iso:country":"US",
    "sg:address":"306 Ocoee Apopka Rd",
    "sg:city":"Winter Garden",
    "sg:classifiers":[
        {
            "category":"Professional",
            "type":"Services"
        }
    ],
    "sg:phone":"+1 407 654 0239",
    "sg:postcode":"34761",
    "sg:province":"FL",
    "wof:name":"Cross Country Svc Inc",
    "wof:placetype":"venue"
},
  "geometry": {"coordinates":[-81.55072800000001,28.575424],"type":"Point"}
}