{
  "type": "Feature",
  "properties": {
    "addr:full":"5309 17th St W Bradenton FL 34207",
    "addr:housenumber":"5309",
    "addr:postcode":"34207",
    "addr:street":"17Th St W",
    "iso:country":"US",
    "sg:address":"5309 17th St W",
    "sg:city":"Bradenton",
    "sg:classifiers":[
        {
            "category":"Building & Trades",
            "subcategory":"Construction",
            "type":"Services"
        }
    ],
    "sg:phone":"+1 941 727 9202",
    "sg:postcode":"34207",
    "sg:province":"FL",
    "sg:tags":[
        "utility",
        "contractor"
    ],
    "wof:name":"B & E Utility Contractors",
    "wof:placetype":"venue"
},
  "geometry": {"coordinates":[-82.579459,27.444198],"type":"Point"}
}