{
  "type": "Feature",
  "properties": {
    "addr:full":"1380 W 15th St West Palm Beach FL 33404",
    "addr:housenumber":"1380",
    "addr:postcode":"33404",
    "addr:street":"W 15Th St",
    "iso:country":"US",
    "sg:address":"1380 W 15th St",
    "sg:city":"West Palm Beach",
    "sg:classifiers":[
        {
            "category":"Building & Trades",
            "subcategory":"Construction",
            "type":"Services"
        }
    ],
    "sg:phone":"+1 561 842 8880",
    "sg:postcode":"33404",
    "sg:province":"FL",
    "sg:tags":[
        "insulation",
        "fireproofing",
        "waterproofing",
        "contractor"
    ],
    "wof:name":"Gulfcoast Insul & Gar Doors",
    "wof:placetype":"venue"
},
  "geometry": {"coordinates":[-80.07797600000001,26.776492],"type":"Point"}
}