{
  "type": "Feature",
  "properties": {
    "iso:country":"US",
    "sg:address":"241 SE 2nd St",
    "sg:city":"Belle Glade",
    "sg:classifiers":[
        {
            "category":"Health Services",
            "subcategory":"Nursing And Care Facility",
            "type":"Services"
        }
    ],
    "sg:phone":"+1 561 366 8003",
    "sg:postcode":"33430",
    "sg:province":"FL",
    "sg:tags":[
        "home",
        "institution"
    ],
    "wof:name":"Haitian Center For Family Svc",
    "wof:placetype":"venue"
},
  "geometry": {"coordinates":[-80.665216,26.684493],"type":"Point"}
}