{
  "type": "Feature",
  "properties": {
    "iso:country":"US",
    "sg:address":"13390 SW 91st Ter",
    "sg:city":"Miami",
    "sg:classifiers":[
        {
            "category":"Building & Trades",
            "subcategory":"Construction",
            "type":"Services"
        }
    ],
    "sg:phone":"+1 305 388 6597",
    "sg:postcode":"33186",
    "sg:province":"FL",
    "sg:tags":[
        "general",
        "contractor"
    ],
    "wof:name":"Ovi Construction Inc",
    "wof:placetype":"venue"
},
  "geometry": {"coordinates":[-80.41156100000001,25.682857],"type":"Point"}
}