{
  "type": "Feature",
  "properties": {
    "iso:country":"US",
    "sg:address":"8253 US Hwy 1",
    "sg:city":"Port Saint Lucie",
    "sg:classifiers":[
        {
            "category":"Professional",
            "subcategory":"Testing Lab",
            "type":"Services"
        }
    ],
    "sg:phone":"+1 772 343 8006",
    "sg:postcode":"34982",
    "sg:province":"FL",
    "sg:tags":[
        "laboratory"
    ],
    "wof:name":"Flowers Chemical Labs Inc",
    "wof:placetype":"venue"
},
  "geometry": {"coordinates":[-80.31414100000001,27.315352],"type":"Point"}
}