{
  "type": "Feature",
  "properties": {
    "addr:full":"6500 N State Rd 7 Coconut Creek FL 33073",
    "addr:housenumber":"6500;7",
    "addr:postcode":"33073",
    "addr:street":"N State Rd",
    "iso:country":"US",
    "sg:address":"6500 N State Rd 7",
    "sg:city":"Coconut Creek",
    "sg:classifiers":[
        {
            "category":"Banks & Credit Unions",
            "subcategory":"Bank",
            "type":"Services"
        }
    ],
    "sg:phone":"+1 954 698 9056",
    "sg:postcode":"33073",
    "sg:province":"FL",
    "sg:tags":[
        "federal",
        "savings",
        "institution"
    ],
    "wof:name":"Washington Mutual Bank",
    "wof:placetype":"venue"
},
  "geometry": {"coordinates":[-80.202217,26.308837],"type":"Point"}
}