{
  "type": "Feature",
  "properties": {
    "iso:country":"US",
    "sg:address":"1623 Michigan Ave",
    "sg:city":"Miami Beach",
    "sg:classifiers":[
        {
            "category":"Personal",
            "subcategory":"Beauty Salon",
            "type":"Services"
        },
        {
            "category":"Personal",
            "subcategory":"Hair Removal",
            "type":"Services"
        },
        {
            "category":"Personal",
            "subcategory":"Nail Salon",
            "type":"Services"
        }
    ],
    "sg:phone":"+1 305 672 0871",
    "sg:postcode":"33139",
    "sg:province":"FL",
    "wof:name":"Ego Trip Salon",
    "wof:placetype":"venue"
},
  "geometry": {"coordinates":[-80.138755,25.789823],"type":"Point"}
}