{
  "type": "Feature",
  "properties": {
    "addr:full":"3141 E Fawn Ct Inverness FL 34452",
    "addr:housenumber":"3141",
    "addr:postcode":"34452",
    "addr:street":"E Fawn Ct",
    "iso:country":"US",
    "sg:address":"3141 E Fawn Ct",
    "sg:city":"Inverness",
    "sg:classifiers":[
        {
            "category":"Shopping",
            "subcategory":"Hobbies, Toys, & Games",
            "type":"Retail Goods"
        }
    ],
    "sg:phone":"+1 352 344 1643",
    "sg:postcode":"34452",
    "sg:province":"FL",
    "sg:tags":[
        "decor"
    ],
    "wof:name":"Whimsical Porcelain",
    "wof:placetype":"venue"
},
  "geometry": {"coordinates":[-82.385514,28.842867],"type":"Point"}
}