{
  "type": "Feature",
  "properties": {
    "iso:country":"US",
    "sg:address":"4320 Dundee Rd",
    "sg:city":"Winter Haven",
    "sg:classifiers":[
        {
            "category":"Travel",
            "subcategory":"Campground",
            "type":"Entertainment"
        }
    ],
    "sg:phone":"+1 863 324 2624",
    "sg:postcode":"33884",
    "sg:province":"FL",
    "wof:name":"East Haven Rv Park",
    "wof:placetype":"venue"
},
  "geometry": {"coordinates":[-81.663726,28.022371],"type":"Point"}
}