{
  "type": "Feature",
  "properties": {
    "iso:country":"US",
    "sg:address":"11595 Kelly Rd",
    "sg:city":"Fort Myers",
    "sg:classifiers":[
        {
            "category":"Banks & Credit Unions",
            "subcategory":"Financial Services",
            "type":"Services"
        }
    ],
    "sg:phone":"+1 239 466 8682",
    "sg:postcode":"33908",
    "sg:province":"FL",
    "sg:tags":[
        "holding",
        "real estate"
    ],
    "wof:name":"Sunset Concepts LLC",
    "wof:placetype":"venue"
},
  "geometry": {"coordinates":[-81.944335,26.508832],"type":"Point"}
}