{
  "type": "Feature",
  "properties": {
    "addr:full":"409 Brown Pl Crestview FL 32539",
    "addr:housenumber":"409",
    "addr:postcode":"32539",
    "addr:street":"Brown Pl",
    "iso:country":"US",
    "sg:address":"409 Brown Pl",
    "sg:city":"Crestview",
    "sg:classifiers":[
        {
            "category":"Building & Trades",
            "subcategory":"Construction",
            "type":"Services"
        }
    ],
    "sg:phone":"+1 850 683 9933",
    "sg:postcode":"32539",
    "sg:province":"FL",
    "sg:tags":[
        "concrete",
        "contractor"
    ],
    "wof:name":"McCloud Concrete Inc",
    "wof:placetype":"venue"
},
  "geometry": {"coordinates":[-86.549943,30.715671],"type":"Point"}
}