{
  "type": "Feature",
  "properties": {
    "addr:full":"1536 S Dixie Hwy Coral Gables FL 33146",
    "addr:housenumber":"1536",
    "addr:postcode":"33146",
    "addr:street":"S Dixie Hwy",
    "iso:country":"US",
    "sg:address":"1536 S Dixie Hwy",
    "sg:city":"Coral Gables",
    "sg:classifiers":[
        {
            "category":"Shopping",
            "subcategory":"Computers & Home Electronics",
            "type":"Retail Goods"
        }
    ],
    "sg:phone":"+1 305 665 4299",
    "sg:postcode":"33146",
    "sg:province":"FL",
    "sg:website":"www.soundcomponents.com",
    "wof:name":"Sound Components",
    "wof:placetype":"venue"
},
  "geometry": {"coordinates":[-80.28363,25.708738],"type":"Point"}
}