{
  "type": "Feature",
  "properties": {
    "iso:country":"US",
    "sg:address":"4302 Alton Rd Ste 530",
    "sg:city":"Miami Beach",
    "sg:classifiers":[
        {
            "category":"Health Services",
            "subcategory":"Doctor",
            "type":"Services"
        }
    ],
    "sg:phone":"+1 305 531 9992",
    "sg:postcode":"33140",
    "sg:province":"FL",
    "sg:tags":[
        "cardiologist"
    ],
    "wof:name":"Heilbron Roy MD PA Phys",
    "wof:placetype":"venue"
},
  "geometry": {"coordinates":[-80.127403,25.821501],"type":"Point"}
}