{
  "type": "Feature",
  "properties": {
    "addr:full":"7240 SW 41st Ct Davie FL 33314",
    "addr:housenumber":"7240",
    "addr:postcode":"33314",
    "addr:street":"Sw 41St Ct",
    "iso:country":"US",
    "sg:address":"7240 SW 41st Ct",
    "sg:city":"Davie",
    "sg:classifiers":[
        {
            "category":"Home & Garden",
            "subcategory":"Building Materials",
            "type":"Retail Goods"
        }
    ],
    "sg:phone":"+1 954 476 3535",
    "sg:postcode":"33314",
    "sg:province":"FL",
    "sg:tags":[
        "shutter"
    ],
    "wof:name":"A & C Hurrican Shutters & More",
    "wof:placetype":"venue"
},
  "geometry": {"coordinates":[-80.24430700000001,26.070765],"type":"Point"}
}