{
  "type": "Feature",
  "properties": {
    "addr:full":"3121 SW 3rd St Ocala FL 34474",
    "addr:housenumber":"3121",
    "addr:postcode":"34474",
    "addr:street":"Sw 3Rd St",
    "iso:country":"US",
    "sg:address":"3121 SW 3rd St",
    "sg:city":"Ocala",
    "sg:classifiers":[
        {
            "category":"Home & Garden",
            "subcategory":"Building Materials",
            "type":"Retail Goods"
        }
    ],
    "sg:phone":"+1 352 620 8830",
    "sg:postcode":"34474",
    "sg:province":"FL",
    "sg:tags":[
        "door",
        "gate",
        "operating",
        "devices"
    ],
    "wof:name":"Omega Door Co",
    "wof:placetype":"venue"
},
  "geometry": {"coordinates":[-82.17691600000001,29.184293],"type":"Point"}
}