{
  "type": "Feature",
  "properties": {
    "addr:full":"7780 W Irlo Bronson Memorial Hwy Kissimmee FL 34747",
    "addr:housenumber":"7780",
    "addr:postcode":"34747",
    "addr:street":"W Irlo Bronson Memorial Hwy",
    "iso:country":"US",
    "sg:address":"7780 W Irlo Bronson Memorial Hwy",
    "sg:city":"Kissimmee",
    "sg:classifiers":[
        {
            "category":"Restaurant",
            "type":"Food & Drink"
        }
    ],
    "sg:menulink":"http://www.allmenus.com/fl/kissimmee/128082-red-lobster/menu/",
    "sg:phone":"+1 321 677 0191",
    "sg:postcode":"34747",
    "sg:province":"FL",
    "sg:tags":[
        "seafood",
        "american"
    ],
    "wof:name":"Red Lobster",
    "wof:placetype":"venue"
},
  "geometry": {"coordinates":[-81.596807,28.339809],"type":"Point"}
}