{
  "type": "Feature",
  "properties": {
    "addr:full":"10800 Benbow Dr New Port Richey FL 34654",
    "addr:housenumber":"10800",
    "addr:postcode":"34654",
    "addr:street":"Benbow Dr",
    "iso:country":"US",
    "sg:address":"10800 Benbow Dr",
    "sg:city":"New Port Richey",
    "sg:classifiers":[
        {
            "category":"Building & Trades",
            "subcategory":"Cleaning & Sanitation",
            "type":"Services"
        }
    ],
    "sg:phone":"+1 727 267 1669",
    "sg:postcode":"34654",
    "sg:province":"FL",
    "sg:tags":[
        "property",
        "maintenance"
    ],
    "wof:name":"Floyd Perry Maintenance",
    "wof:placetype":"venue"
},
  "geometry": {"coordinates":[-82.62447400000001,28.314359],"type":"Point"}
}