{
  "type": "Feature",
  "properties": {
    "iso:country":"US",
    "sg:address":"1070 E Tee Cir",
    "sg:city":"Bartow",
    "sg:classifiers":[
        {
            "category":"Education",
            "subcategory":"Special Training",
            "type":"Public Place"
        }
    ],
    "sg:phone":"+1 863 533 3450",
    "sg:postcode":"33830",
    "sg:province":"FL",
    "sg:tags":[
        "instruction",
        "driving"
    ],
    "wof:name":"Wynn's Driving School",
    "wof:placetype":"venue"
},
  "geometry": {"coordinates":[-81.81855400000001,27.888843],"type":"Point"}
}