{
  "type": "Feature",
  "properties": {
    "addr:full":"1225 E Lime St Lakeland FL 33801",
    "addr:housenumber":"1225",
    "addr:postcode":"33801",
    "addr:street":"E Lime St",
    "iso:country":"US",
    "sg:address":"1225 E Lime St",
    "sg:city":"Lakeland",
    "sg:classifiers":[
        {
            "category":"Education",
            "subcategory":"School",
            "type":"Public Place"
        }
    ],
    "sg:phone":"+1 863 499 2950",
    "sg:postcode":"33801",
    "sg:province":"FL",
    "sg:website":"www.polk-fl.net",
    "wof:name":"Lime Street Elementary School",
    "wof:placetype":"venue"
},
  "geometry": {"coordinates":[-81.939463,28.040484],"type":"Point"}
}