{
  "type": "Feature",
  "properties": {
    "addr:full":"2601 River Ridge Dr Orlando FL 32825",
    "addr:housenumber":"2601",
    "addr:postcode":"32825",
    "addr:street":"River Ridge Dr",
    "iso:country":"US",
    "sg:address":"2601 River Ridge Dr",
    "sg:city":"Orlando",
    "sg:classifiers":[
        {
            "category":"Utilities",
            "subcategory":"Mobile Phone",
            "type":"Services"
        }
    ],
    "sg:phone":"+1 407 380 3577",
    "sg:postcode":"32825",
    "sg:province":"FL",
    "sg:tags":[
        "telephone",
        "cellular"
    ],
    "wof:name":"Ultimate Business Solutions",
    "wof:placetype":"venue"
},
  "geometry": {"coordinates":[-81.242604,28.516049],"type":"Point"}
}