{
  "type": "Feature",
  "properties": {
    "iso:country":"US",
    "sg:address":"10525 SW 113th Pl",
    "sg:city":"Miami",
    "sg:classifiers":[
        {
            "category":"Professional",
            "subcategory":"Management & Consulting",
            "type":"Services"
        }
    ],
    "sg:phone":"+1 305 670 6897",
    "sg:postcode":"33176",
    "sg:province":"FL",
    "wof:name":"Moring Advisory Services Inc",
    "wof:placetype":"venue"
},
  "geometry": {"coordinates":[-80.37742299999999,25.671104],"type":"Point"}
}