{
  "type": "Feature",
  "properties": {
    "iso:country":"US",
    "sg:address":"145 W Crystal Lake Ave",
    "sg:city":"Lake Mary",
    "sg:classifiers":[
        {
            "category":"Professional",
            "subcategory":"Research",
            "type":"Services"
        }
    ],
    "sg:phone":"+1 407 322 0514",
    "sg:postcode":"32746",
    "sg:province":"FL",
    "sg:tags":[
        "nonphysical",
        "commercial"
    ],
    "wof:name":"Rh Goble Enterprises Inc",
    "wof:placetype":"venue"
},
  "geometry": {"coordinates":[-81.32228499999999,28.758935],"type":"Point"}
}