{
  "type": "Feature",
  "properties": {
    "iso:country":"US",
    "sg:address":"601 Brickell Key Dr",
    "sg:city":"Miami",
    "sg:classifiers":[
        {
            "category":"Building & Trades",
            "subcategory":"Locksmith",
            "type":"Services"
        }
    ],
    "sg:phone":"+1 305 908 8154",
    "sg:postcode":"33131",
    "sg:province":"FL",
    "sg:tags":[
        "key"
    ],
    "wof:name":"1 Alpha Emergency Locksmith",
    "wof:placetype":"venue"
},
  "geometry": {"coordinates":[-80.185388,25.766898],"type":"Point"}
}