{
  "type": "Feature",
  "properties": {
    "addr:full":"13569 Isabell Ave Port Charlotte FL 33981",
    "addr:housenumber":"13569",
    "addr:postcode":"33981",
    "addr:street":"Isabell Ave",
    "iso:country":"US",
    "sg:address":"13569 Isabell Ave",
    "sg:city":"Port Charlotte",
    "sg:classifiers":[
        {
            "category":"Retail",
            "subcategory":"Car Wash",
            "type":"Services"
        }
    ],
    "sg:phone":"+1 941 697 7432",
    "sg:postcode":"33981",
    "sg:province":"FL",
    "sg:tags":[
        "carwash"
    ],
    "wof:name":"George D Karaffa Pressure Wash",
    "wof:placetype":"venue"
},
  "geometry": {"coordinates":[-82.223575,26.941148],"type":"Point"}
}