{
  "type": "Feature",
  "properties": {
    "iso:country":"US",
    "sg:address":"2162 Lois Blvd",
    "sg:city":"Winter Haven",
    "sg:classifiers":[
        {
            "category":"Utilities",
            "subcategory":"Cable",
            "type":"Services"
        }
    ],
    "sg:phone":"+1 863 551 1738",
    "sg:postcode":"33850",
    "sg:province":"FL",
    "sg:tags":[
        "television"
    ],
    "sg:website":"www.obvc.com",
    "wof:name":"Ohio Valley Digital Comm",
    "wof:placetype":"venue"
},
  "geometry": {"coordinates":[-81.756665,28.079207],"type":"Point"}
}