{
  "type": "Feature",
  "properties": {
    "addr:full":"13201 S Orange Ave Orlando FL 32824",
    "addr:housenumber":"13201",
    "addr:postcode":"32824",
    "addr:street":"S Orange Ave",
    "iso:country":"US",
    "sg:address":"13201 S Orange Ave",
    "sg:city":"Orlando",
    "sg:classifiers":[
        {
            "category":"Professional",
            "subcategory":"Business Services",
            "type":"Services"
        }
    ],
    "sg:phone":"+1 407 240 1100",
    "sg:postcode":"32824",
    "sg:province":"FL",
    "sg:tags":[
        "exporter"
    ],
    "wof:name":"Kenco Logistic Svc",
    "wof:placetype":"venue"
},
  "geometry": {"coordinates":[-81.377409,28.373664],"type":"Point"}
}