{
  "type": "Feature",
  "properties": {
    "addr:full":"23 Wild Cat Ln Ormond Beach FL 32174",
    "addr:housenumber":"23",
    "addr:postcode":"32174",
    "addr:street":"Wild Cat Ln",
    "iso:country":"US",
    "sg:address":"23 Wild Cat Ln",
    "sg:city":"Ormond Beach",
    "sg:classifiers":[
        {
            "category":"Wholesale",
            "subcategory":"Medical Equipment & Supplies",
            "type":"Manufacturing & Wholesale Goods"
        }
    ],
    "sg:phone":"+1 386 676 2423",
    "sg:postcode":"32174",
    "sg:province":"FL",
    "sg:tags":[
        "physician",
        "surgeon"
    ],
    "wof:name":"Kingsley & Assoc",
    "wof:placetype":"venue"
},
  "geometry": {"coordinates":[-81.103072,29.330526],"type":"Point"}
}