{
  "type": "Feature",
  "properties": {
    "iso:country":"US",
    "sg:address":"451 E Altamonte Dr Ste 2157",
    "sg:city":"Altamonte Springs",
    "sg:classifiers":[
        {
            "category":"Shopping",
            "subcategory":"Jewelry",
            "type":"Retail Goods"
        }
    ],
    "sg:phone":"+1 407 830 6881",
    "sg:postcode":"32701",
    "sg:province":"FL",
    "sg:website":"www.mayorsjewelers.com",
    "wof:name":"Mayors Jewelers",
    "wof:placetype":"venue"
},
  "geometry": {"coordinates":[-81.37599400000001,28.663939],"type":"Point"}
}