{
  "type": "Feature",
  "properties": {
    "addr:full":"2700 Mayan Dr Fort Lauderdale FL 33316",
    "addr:housenumber":"2700",
    "addr:postcode":"33316",
    "addr:street":"Mayan Dr",
    "iso:country":"US",
    "sg:address":"2700 Mayan Dr",
    "sg:city":"Fort Lauderdale",
    "sg:classifiers":[
        {
            "category":"Organizations",
            "subcategory":"Religious Organization",
            "type":"Services"
        }
    ],
    "sg:phone":"+1 954 523 6472",
    "sg:postcode":"33316",
    "sg:province":"FL",
    "sg:tags":[
        "church"
    ],
    "sg:website":"www.thechurchbythesea.org",
    "wof:name":"Church By The Sea Inc",
    "wof:placetype":"venue"
},
  "geometry": {"coordinates":[-80.111954,26.101243],"type":"Point"}
}