{
  "type": "Feature",
  "properties": {
    "iso:country":"US",
    "sg:address":"140 NW 87th Ave",
    "sg:city":"Miami",
    "sg:classifiers":[
        {
            "category":"Building & Trades",
            "subcategory":"Landscaping Services",
            "type":"Services"
        }
    ],
    "sg:phone":"+1 305 223 2221",
    "sg:postcode":"33172",
    "sg:province":"FL",
    "sg:tags":[
        "lawn",
        "maintenance"
    ],
    "wof:name":"Trimmm Lawns & Landscaping",
    "wof:placetype":"venue"
},
  "geometry": {"coordinates":[-80.337372,25.771558],"type":"Point"}
}