{
  "type": "Feature",
  "properties": {
    "addr:full":"4188 Cambridge St Kissimmee FL 34746",
    "addr:housenumber":"4188",
    "addr:postcode":"34746",
    "addr:street":"Cambridge St",
    "iso:country":"US",
    "sg:address":"4188 Cambridge St",
    "sg:city":"Kissimmee",
    "sg:classifiers":[
        {
            "category":"Health Services",
            "subcategory":"Doctor",
            "type":"Services"
        }
    ],
    "sg:phone":"+1 407 343 5511",
    "sg:postcode":"34746",
    "sg:province":"FL",
    "sg:tags":[
        "physician",
        "surgeon"
    ],
    "wof:name":"Florida University Of Medicine",
    "wof:placetype":"venue"
},
  "geometry": {"coordinates":[-81.447525,28.259654],"type":"Point"}
}