{
  "type": "Feature",
  "properties": {
    "addr:full":"6925 Potomac Cir Riverview FL 33578",
    "addr:housenumber":"6925",
    "addr:postcode":"33578",
    "addr:street":"Potomac Cir",
    "iso:country":"US",
    "sg:address":"6925 Potomac Cir",
    "sg:city":"Riverview",
    "sg:classifiers":[
        {
            "category":"Professional",
            "subcategory":"Management & Consulting",
            "type":"Services"
        }
    ],
    "sg:phone":"+1 813 672 8936",
    "sg:postcode":"33578",
    "sg:province":"FL",
    "sg:tags":[
        "consultant",
        "business"
    ],
    "wof:name":"R & D Professional Consulting",
    "wof:placetype":"venue"
},
  "geometry": {"coordinates":[-82.332724,27.879599],"type":"Point"}
}