{
  "type": "Feature",
  "properties": {
    "addr:full":"522 Mercer Ave Panama City FL 32401",
    "addr:housenumber":"522",
    "addr:postcode":"32401",
    "addr:street":"Mercer Ave",
    "iso:country":"US",
    "sg:address":"522 Mercer Ave",
    "sg:city":"Panama City",
    "sg:classifiers":[
        {
            "category":"Insurance",
            "subcategory":"Insurance Agent",
            "type":"Services"
        }
    ],
    "sg:phone":"+1 850 763 1783",
    "sg:postcode":"32401",
    "sg:province":"FL",
    "wof:name":"Northern Life",
    "wof:placetype":"venue"
},
  "geometry": {"coordinates":[-85.663242,30.15845],"type":"Point"}
}