{
  "type": "Feature",
  "properties": {
    "iso:country":"US",
    "sg:address":"222 Industrial Blvd",
    "sg:city":"Naples",
    "sg:classifiers":[
        {
            "category":"Building & Trades",
            "subcategory":"Electrical",
            "type":"Services"
        }
    ],
    "sg:phone":"+1 239 430 4756",
    "sg:postcode":"34104",
    "sg:province":"FL",
    "sg:tags":[
        "electric",
        "contractor"
    ],
    "wof:name":"R Bogart & Assoc Inc",
    "wof:placetype":"venue"
},
  "geometry": {"coordinates":[-81.75904199999999,26.156577],"type":"Point"}
}