{
  "type": "Feature",
  "properties": {
    "addr:full":"4440 Thomastown Dr Milton FL 32571",
    "addr:postcode":"4440;32571",
    "addr:street":"Thomastown Dr",
    "iso:country":"US",
    "sg:address":"4440 Thomastown Dr",
    "sg:city":"Milton",
    "sg:classifiers":[
        {
            "category":"Travel",
            "subcategory":"Campground",
            "type":"Entertainment"
        }
    ],
    "sg:phone":"+1 850 994 3473",
    "sg:postcode":"32571",
    "sg:province":"FL",
    "sg:tags":[
        "attendant",
        "park"
    ],
    "wof:name":"James W Hatcher",
    "wof:placetype":"venue"
},
  "geometry": {"coordinates":[-87.137154,30.633128],"type":"Point"}
}