{
  "type": "Feature",
  "properties": {
    "iso:country":"US",
    "sg:address":"415 W Vine St",
    "sg:city":"Kissimmee",
    "sg:classifiers":[
        {
            "category":"Communications",
            "subcategory":"Radio Station",
            "type":"Services"
        }
    ],
    "sg:phone":"+1 407 518 7150",
    "sg:postcode":"34741",
    "sg:province":"FL",
    "sg:tags":[
        "company",
        "broadcasting"
    ],
    "wof:name":"Radio Genesis",
    "wof:placetype":"venue"
},
  "geometry": {"coordinates":[-81.408703,28.304639],"type":"Point"}
}