{
  "type": "Feature",
  "properties": {
    "addr:full":"4463 New Market Rd Niceville FL 32578",
    "addr:housenumber":"4463",
    "addr:postcode":"32578",
    "addr:street":"New Market Rd",
    "iso:country":"US",
    "sg:address":"4463 New Market Rd",
    "sg:city":"Niceville",
    "sg:classifiers":[
        {
            "category":"Building & Trades",
            "subcategory":"Construction",
            "type":"Services"
        }
    ],
    "sg:phone":"+1 850 678 1514",
    "sg:postcode":"32578",
    "sg:province":"FL",
    "sg:tags":[
        "carpentry",
        "contractor"
    ],
    "wof:name":"Boisjolie Scott Trim Carpenter",
    "wof:placetype":"venue"
},
  "geometry": {"coordinates":[-86.420766,30.512048],"type":"Point"}
}