{
  "type": "Feature",
  "properties": {
    "addr:full":"6731 N Armenia Ave Tampa FL 33604",
    "addr:housenumber":"6731",
    "addr:postcode":"33604",
    "addr:street":"N Armenia Ave",
    "iso:country":"US",
    "sg:address":"6731 N Armenia Ave",
    "sg:city":"Tampa",
    "sg:classifiers":[
        {
            "category":"Retail",
            "subcategory":"Repair Shop",
            "type":"Services"
        }
    ],
    "sg:phone":"+1 813 932 3583",
    "sg:postcode":"33604",
    "sg:province":"FL",
    "sg:tags":[
        "appliance"
    ],
    "sg:website":"www.ricksacelecapp.com",
    "wof:name":"Rick's Appliance",
    "wof:placetype":"venue"
},
  "geometry": {"coordinates":[-82.48430999999999,28.007785],"type":"Point"}
}