{
  "type": "Feature",
  "properties": {
    "iso:country":"US",
    "sg:address":"495 Woodfern Ave",
    "sg:city":"Mary Esther",
    "sg:classifiers":[
        {
            "category":"Building & Trades",
            "subcategory":"Landscaping Services",
            "type":"Services"
        }
    ],
    "sg:phone":"+1 850 244 7436",
    "sg:postcode":"32569",
    "sg:province":"FL",
    "sg:tags":[
        "lawn",
        "maintenance",
        "grounds"
    ],
    "wof:name":"Radical Rick's Lawn Care",
    "wof:placetype":"venue"
},
  "geometry": {"coordinates":[-86.793505,30.413043],"type":"Point"}
}