{
  "type": "Feature",
  "properties": {
    "addr:full":"4907 N Florida Ave Tampa FL 33603",
    "addr:housenumber":"4907",
    "addr:postcode":"33603",
    "addr:street":"N Florida Ave",
    "iso:country":"US",
    "sg:address":"4907 N Florida Ave",
    "sg:city":"Tampa",
    "sg:classifiers":[
        {
            "category":"Manufacturing",
            "subcategory":"Printing",
            "type":"Manufacturing & Wholesale Goods"
        }
    ],
    "sg:phone":"+1 813 612 7746",
    "sg:postcode":"33603",
    "sg:province":"FL",
    "sg:tags":[
        "commercial"
    ],
    "wof:name":"Tampa Printing Co",
    "wof:placetype":"venue"
},
  "geometry": {"coordinates":[-82.45934,27.99136],"type":"Point"}
}