{
  "type": "Feature",
  "properties": {
    "iso:country":"US",
    "sg:address":"216 S Atlantic Ave",
    "sg:city":"Ormond Beach",
    "sg:classifiers":[
        {
            "category":"Building & Trades",
            "subcategory":"Cleaning & Sanitation",
            "type":"Services"
        }
    ],
    "sg:phone":"+1 386 672 2989",
    "sg:postcode":"32176",
    "sg:province":"FL",
    "sg:tags":[
        "house"
    ],
    "wof:name":"Stardust International",
    "wof:placetype":"venue"
},
  "geometry": {"coordinates":[-81.03790600000001,29.28735],"type":"Point"}
}