{
  "type": "Feature",
  "properties": {
    "iso:country":"US",
    "sg:address":"3000 S Mellonville Ave",
    "sg:city":"Sanford",
    "sg:classifiers":[
        {
            "category":"Manufacturing",
            "subcategory":"Tools & Machinery",
            "type":"Manufacturing & Wholesale Goods"
        }
    ],
    "sg:phone":"+1 407 321 2901",
    "sg:postcode":"32773",
    "sg:province":"FL",
    "sg:tags":[
        "equipment",
        "irrigation",
        "system"
    ],
    "wof:name":"Toro Co",
    "wof:placetype":"venue"
},
  "geometry": {"coordinates":[-81.256193,28.774286],"type":"Point"}
}