{
  "type": "Feature",
  "properties": {
    "iso:country":"US",
    "sg:address":"3210 el Camino Real",
    "sg:city":"West Palm Beach",
    "sg:classifiers":[
        {
            "category":"Shopping",
            "subcategory":"Bicycles & Sporting Goods",
            "type":"Retail Goods"
        }
    ],
    "sg:phone":"+1 561 640 9028",
    "sg:postcode":"33409",
    "sg:province":"FL",
    "wof:name":"Daniel T&M Enterprise Inc",
    "wof:placetype":"venue"
},
  "geometry": {"coordinates":[-80.102396,26.744915],"type":"Point"}
}