{
  "type": "Feature",
  "properties": {
    "iso:country":"US",
    "sg:address":"265 S Wickham Rd",
    "sg:city":"Melbourne",
    "sg:classifiers":[
        {
            "category":"Professional",
            "type":"Services"
        }
    ],
    "sg:phone":"+1 321 723 4334",
    "sg:postcode":"32904",
    "sg:province":"FL",
    "sg:tags":[
        "establishment"
    ],
    "wof:name":"Pain Enterprises Inc",
    "wof:placetype":"venue"
},
  "geometry": {"coordinates":[-80.672579,28.102889],"type":"Point"}
}