{
  "type": "Feature",
  "properties": {
    "iso:country":"US",
    "sg:address":"1868 W Flagler St",
    "sg:city":"Miami",
    "sg:classifiers":[
        {
            "category":"Shopping",
            "subcategory":"Crafts & Fabrics",
            "type":"Retail Goods"
        },
        {
            "category":"Shopping",
            "subcategory":"Florist",
            "type":"Retail Goods"
        }
    ],
    "sg:phone":"+1 305 631 8311",
    "sg:postcode":"33135",
    "sg:province":"FL",
    "sg:tags":[
        "supply"
    ],
    "wof:name":"Geranios Flower",
    "wof:placetype":"venue"
},
  "geometry": {"coordinates":[-80.226173,25.77272],"type":"Point"}
}