{
  "type": "Feature",
  "properties": {
    "iso:country":"US",
    "sg:address":"3809 Idlewood Dr",
    "sg:city":"Pensacola",
    "sg:classifiers":[
        {
            "category":"Building & Trades",
            "subcategory":"Construction",
            "type":"Services"
        }
    ],
    "sg:phone":"+1 850 433 3923",
    "sg:postcode":"32505",
    "sg:province":"FL",
    "sg:tags":[
        "heavy"
    ],
    "wof:name":"Dennis Bourgeois",
    "wof:placetype":"venue"
},
  "geometry": {"coordinates":[-87.260571,30.416377],"type":"Point"}
}