{
  "type": "Feature",
  "properties": {
    "addr:full":"408 Takoma St Orlando FL 32811",
    "addr:housenumber":"408",
    "addr:postcode":"32811",
    "addr:street":"Takoma St",
    "iso:country":"US",
    "sg:address":"408 Takoma St",
    "sg:city":"Orlando",
    "sg:classifiers":[
        {
            "category":"Building & Trades",
            "subcategory":"Landscaping Services",
            "type":"Services"
        }
    ],
    "sg:phone":"+1 407 290 9070",
    "sg:postcode":"32811",
    "sg:province":"FL",
    "sg:tags":[
        "consultant",
        "lawn",
        "designer",
        "landscape",
        "contractor"
    ],
    "wof:name":"Michelle Professional Landscape Care Services",
    "wof:placetype":"venue"
},
  "geometry": {"coordinates":[-81.444655,28.546654],"type":"Point"}
}