{
  "type": "Feature",
  "properties": {
    "addr:full":"2655 Capital Cir NE Tallahassee FL 32308",
    "addr:housenumber":"2655",
    "addr:postcode":"32308",
    "addr:street":"Capital Cir Ne",
    "iso:country":"US",
    "sg:address":"2655 Capital Cir NE",
    "sg:city":"Tallahassee",
    "sg:classifiers":[
        {
            "category":"Wholesale",
            "subcategory":"Motor Vehicles",
            "type":"Manufacturing & Wholesale Goods"
        }
    ],
    "sg:phone":"+1 850 668 5082",
    "sg:postcode":"32308",
    "sg:province":"FL",
    "wof:name":"Ralph A Swatts Jr",
    "wof:placetype":"venue"
},
  "geometry": {"coordinates":[-84.237447,30.485807],"type":"Point"}
}