{
  "type": "Feature",
  "properties": {
    "addr:full":"9280 Bay Plaza Blvd Tampa FL 33619",
    "addr:housenumber":"9280",
    "addr:postcode":"33619",
    "addr:street":"Bay Plaza Blvd",
    "iso:country":"US",
    "sg:address":"9280 Bay Plaza Blvd",
    "sg:city":"Tampa",
    "sg:classifiers":[
        {
            "category":"Professional",
            "subcategory":"Accounting & Tax Preparation",
            "type":"Services"
        }
    ],
    "sg:phone":"+1 813 663 9628",
    "sg:postcode":"33619",
    "sg:province":"FL",
    "sg:tags":[
        "accountant"
    ],
    "wof:name":"Ann Marie Boehm CPA Pa",
    "wof:placetype":"venue"
},
  "geometry": {"coordinates":[-82.348164,27.946904],"type":"Point"}
}