{
  "type": "Feature",
  "properties": {
    "iso:country":"US",
    "sg:address":"625 N Washington Blvd",
    "sg:city":"Sarasota",
    "sg:classifiers":[
        {
            "category":"Health Services",
            "subcategory":"Chiropractor",
            "type":"Services"
        }
    ],
    "sg:phone":"+1 941 363 9000",
    "sg:postcode":"34236",
    "sg:province":"FL",
    "wof:name":"Simple Relief Wellness Ctr",
    "wof:placetype":"venue"
},
  "geometry": {"coordinates":[-82.53106,27.341901],"type":"Point"}
}