{
  "type": "Feature",
  "properties": {
    "iso:country":"US",
    "sg:address":"5422 W Buckskin Dr",
    "sg:city":"Beverly Hills",
    "sg:classifiers":[
        {
            "category":"Building & Trades",
            "subcategory":"Construction",
            "type":"Services"
        }
    ],
    "sg:phone":"+1 352 746 7337",
    "sg:postcode":"34465",
    "sg:province":"FL",
    "sg:tags":[
        "home",
        "builder"
    ],
    "wof:name":"Lexington Homes Inc",
    "wof:placetype":"venue"
},
  "geometry": {"coordinates":[-82.52390800000001,28.928599],"type":"Point"}
}