{
  "type": "Feature",
  "properties": {
    "addr:full":"401 N Church Ave Mulberry FL 33860",
    "addr:housenumber":"401",
    "addr:postcode":"33860",
    "addr:street":"N Church Ave",
    "iso:country":"US",
    "sg:address":"401 N Church Ave",
    "sg:city":"Mulberry",
    "sg:classifiers":[
        {
            "category":"Restaurant",
            "type":"Food & Drink"
        }
    ],
    "sg:phone":"+1 863 646 8667",
    "sg:postcode":"33860",
    "sg:province":"FL",
    "sg:tags":[
        "pizza"
    ],
    "wof:name":"Toppers Of Florida",
    "wof:placetype":"venue"
},
  "geometry": {"coordinates":[-81.973602,27.897631],"type":"Point"}
}