{
  "type": "Feature",
  "properties": {
    "addr:full":"7900 NW 3rd Pl Fort Lauderdale FL 33324",
    "addr:housenumber":"7900",
    "addr:postcode":"33324",
    "addr:street":"Nw 3Rd Pl",
    "iso:country":"US",
    "sg:address":"7900 NW 3rd Pl",
    "sg:city":"Fort Lauderdale",
    "sg:classifiers":[
        {
            "category":"Shopping",
            "subcategory":"Photographic Equipment",
            "type":"Retail Goods"
        }
    ],
    "sg:phone":"+1 954 452 1877",
    "sg:postcode":"33324",
    "sg:province":"FL",
    "sg:tags":[
        "supply"
    ],
    "wof:name":"Concord Camera Corp",
    "wof:placetype":"venue"
},
  "geometry": {"coordinates":[-80.255228,26.126224],"type":"Point"}
}