{
  "type": "Feature",
  "properties": {
    "iso:country":"US",
    "sg:address":"8429 SW 137th Ave",
    "sg:city":"Miami",
    "sg:classifiers":[
        {
            "category":"Place Of Worship",
            "subcategory":"Church",
            "type":"Public Place"
        },
        {
            "category":"Place Of Worship",
            "type":"Public Place"
        }
    ],
    "sg:phone":"+1 305 382 2186",
    "sg:postcode":"33183",
    "sg:province":"FL",
    "sg:tags":[
        "churches-non-denominational"
    ],
    "wof:name":"International Church Florida",
    "wof:placetype":"venue"
},
  "geometry": {"coordinates":[-80.416239,25.688086],"type":"Point"}
}