{
  "type": "Feature",
  "properties": {
    "iso:country":"US",
    "sg:address":"162 NE Twylite Ter",
    "sg:city":"Port Saint Lucie",
    "sg:classifiers":[
        {
            "category":"Personal",
            "subcategory":"Beauty Salon",
            "type":"Services"
        }
    ],
    "sg:phone":"+1 772 871 9570",
    "sg:postcode":"34983",
    "sg:province":"FL",
    "sg:tags":[
        "shop"
    ],
    "wof:name":"Alfred Keller Kuts",
    "wof:placetype":"venue"
},
  "geometry": {"coordinates":[-80.346082,27.336303],"type":"Point"}
}