{
  "type": "Feature",
  "properties": {
    "iso:country":"US",
    "sg:address":"12752 SW 91st St",
    "sg:city":"Miami",
    "sg:classifiers":[
        {
            "category":"Shopping",
            "subcategory":"Florist",
            "type":"Retail Goods"
        }
    ],
    "sg:phone":"+1 305 387 3888",
    "sg:postcode":"33186",
    "sg:province":"FL",
    "wof:name":"Florist Supplier",
    "wof:placetype":"venue"
},
  "geometry": {"coordinates":[-80.401704,25.682594],"type":"Point"}
}