{
  "type": "Feature",
  "properties": {
    "iso:country":"US",
    "sg:address":"1224 Dahomey St",
    "sg:city":"Sebring",
    "sg:classifiers":[
        {
            "category":"Professional",
            "type":"Services"
        }
    ],
    "sg:phone":"+1 863 385 3878",
    "sg:postcode":"33875",
    "sg:province":"FL",
    "sg:tags":[
        "establishment"
    ],
    "wof:name":"Sudan Interior Mission",
    "wof:placetype":"venue"
},
  "geometry": {"coordinates":[-81.454796,27.461624],"type":"Point"}
}