{
  "type": "Feature",
  "properties": {
    "addr:full":"426 NE 8th Ave Fort Lauderdale FL 33301",
    "addr:housenumber":"426",
    "addr:postcode":"33301",
    "addr:street":"Ne 8Th Ave",
    "iso:country":"US",
    "sg:address":"426 NE 8th Ave",
    "sg:city":"Fort Lauderdale",
    "sg:classifiers":[
        {
            "category":"Banks & Credit Unions",
            "subcategory":"Bank",
            "type":"Services"
        }
    ],
    "sg:phone":"+1 954 765 3846",
    "sg:postcode":"33301",
    "sg:province":"FL",
    "sg:tags":[
        "national",
        "commercial"
    ],
    "wof:name":"Jamie Bargas",
    "wof:placetype":"venue"
},
  "geometry": {"coordinates":[-80.135316,26.127565],"type":"Point"}
}