{
  "type": "Feature",
  "properties": {
    "iso:country":"US",
    "sg:address":"706 Lemongrass Ln",
    "sg:city":"Wellington",
    "sg:classifiers":[
        {
            "category":"Building & Trades",
            "subcategory":"Construction",
            "type":"Services"
        }
    ],
    "sg:phone":"+1 561 798 3563",
    "sg:postcode":"33414",
    "sg:province":"FL",
    "sg:tags":[
        "excavating",
        "contractor"
    ],
    "wof:name":"S & V Enterprises Inc",
    "wof:placetype":"venue"
},
  "geometry": {"coordinates":[-80.272977,26.670721],"type":"Point"}
}