{
  "type": "Feature",
  "properties": {
    "iso:country":"US",
    "sg:address":"5009 Tampa West Blvd",
    "sg:city":"Tampa",
    "sg:classifiers":[
        {
            "category":"Organizations",
            "subcategory":"Non-profit Organization",
            "type":"Services"
        },
        {
            "category":"Wholesale",
            "subcategory":"Groceries",
            "type":"Manufacturing & Wholesale Goods"
        }
    ],
    "sg:phone":"+1 813 888 9824",
    "sg:postcode":"33634",
    "sg:province":"FL",
    "sg:tags":[
        "product",
        "gift",
        "food",
        "novelty",
        "fund",
        "counselor",
        "raising"
    ],
    "sg:website":"www.americanfundraisingsvc.com",
    "wof:name":"American Fundraising Services",
    "wof:placetype":"venue"
},
  "geometry": {"coordinates":[-82.527765,28.017902],"type":"Point"}
}