{
  "type": "Feature",
  "properties": {
    "addr:full":"900 S Highland Ave Clearwater FL 33756",
    "addr:housenumber":"900",
    "addr:postcode":"33756",
    "addr:street":"S Highland Ave",
    "iso:country":"US",
    "sg:address":"900 S Highland Ave",
    "sg:city":"Clearwater",
    "sg:classifiers":[
        {
            "category":"Professional",
            "subcategory":"Employment Agencies",
            "type":"Services"
        }
    ],
    "sg:phone":"+1 727 449 0953",
    "sg:postcode":"33756",
    "sg:province":"FL",
    "wof:name":"Caring Nurses Assisted Living",
    "wof:placetype":"venue"
},
  "geometry": {"coordinates":[-82.77516799999999,27.953412],"type":"Point"}
}