{
  "type": "Feature",
  "properties": {
    "addr:full":"11362 San Jose Blvd Jacksonville FL 32223",
    "addr:housenumber":"11362",
    "addr:postcode":"32223",
    "addr:street":"San Jose Blvd",
    "iso:country":"US",
    "sg:address":"11362 San Jose Blvd",
    "sg:city":"Jacksonville",
    "sg:classifiers":[
        {
            "category":"Shopping",
            "type":"Retail Goods"
        }
    ],
    "sg:phone":"+1 904 338 9236",
    "sg:postcode":"32223",
    "sg:province":"FL",
    "sg:tags":[
        "hearing",
        "equipment",
        "supply",
        "impaired"
    ],
    "wof:name":"Jacksonville Hearing & Balance",
    "wof:placetype":"venue"
},
  "geometry": {"coordinates":[-81.62999499999999,30.169788],"type":"Point"}
}