{
  "type": "Feature",
  "properties": {
    "addr:full":"1557 Eagle View Rd Osteen FL 32764",
    "addr:housenumber":"1557",
    "addr:postcode":"32764",
    "addr:street":"Eagle View Rd",
    "iso:country":"US",
    "sg:address":"1557 Eagle View Rd",
    "sg:city":"Osteen",
    "sg:classifiers":[
        {
            "category":"Building & Trades",
            "subcategory":"Landscaping Services",
            "type":"Services"
        }
    ],
    "sg:phone":"+1 407 322 0571",
    "sg:postcode":"32764",
    "sg:province":"FL",
    "sg:tags":[
        "landscape"
    ],
    "wof:name":"Eagle View Landscaping",
    "wof:placetype":"venue"
},
  "geometry": {"coordinates":[-81.07266799999999,28.87002],"type":"Point"}
}