{
  "type": "Feature",
  "properties": {
    "iso:country":"US",
    "sg:address":"3235 Howey Rd",
    "sg:city":"Sebring",
    "sg:classifiers":[
        {
            "category":"Freight",
            "type":"Transportation"
        }
    ],
    "sg:phone":"+1 863 382 6548",
    "sg:postcode":"33872",
    "sg:province":"FL",
    "sg:tags":[
        "operator",
        "local",
        "trucking"
    ],
    "wof:name":"Steerhead Ranch Hauling",
    "wof:placetype":"venue"
},
  "geometry": {"coordinates":[-81.496028,27.48541],"type":"Point"}
}