{
  "type": "Feature",
  "properties": {
    "iso:country":"US",
    "sg:address":"6620 Suemac Pl",
    "sg:city":"Jacksonville",
    "sg:classifiers":[
        {
            "category":"Manufacturing",
            "subcategory":"Rubber & Plastics",
            "type":"Manufacturing & Wholesale Goods"
        }
    ],
    "sg:phone":"+1 904 781 8028",
    "sg:postcode":"32254",
    "sg:province":"FL",
    "sg:tags":[
        "unsupported",
        "mfg"
    ],
    "wof:name":"P C L Packaging",
    "wof:placetype":"venue"
},
  "geometry": {"coordinates":[-81.758562,30.329291],"type":"Point"}
}