{
  "type": "Feature",
  "properties": {
    "iso:country":"US",
    "sg:address":"833 Mississippi Ave",
    "sg:city":"Saint Cloud",
    "sg:classifiers":[
        {
            "category":"Building & Trades",
            "subcategory":"Construction",
            "type":"Services"
        }
    ],
    "sg:phone":"+1 407 892 1624",
    "sg:postcode":"34769",
    "sg:province":"FL",
    "sg:tags":[
        "floor",
        "laying",
        "contractor"
    ],
    "wof:name":"First American Flrg & Rmdlg",
    "wof:placetype":"venue"
},
  "geometry": {"coordinates":[-81.268818,28.250044],"type":"Point"}
}