{
  "type": "Feature",
  "properties": {
    "iso:country":"US",
    "sg:address":"922 King St",
    "sg:city":"Cocoa",
    "sg:classifiers":[
        {
            "category":"Shopping",
            "subcategory":"Stationery & Office Supplies",
            "type":"Retail Goods"
        }
    ],
    "sg:phone":"+1 321 636 8801",
    "sg:postcode":"32922",
    "sg:province":"FL",
    "sg:tags":[
        "business"
    ],
    "wof:name":"Phoenix Typing Services",
    "wof:placetype":"venue"
},
  "geometry": {"coordinates":[-80.74227500000001,28.355783],"type":"Point"}
}