{
  "type": "Feature",
  "properties": {
    "iso:country":"US",
    "sg:address":"73 Harbor Dr",
    "sg:city":"Key Biscayne",
    "sg:classifiers":[
        {
            "category":"Retail",
            "subcategory":"Laundry & Dry Cleaning",
            "type":"Services"
        }
    ],
    "sg:phone":"+1 305 365 0207",
    "sg:postcode":"33149",
    "sg:province":"FL",
    "sg:tags":[
        "cleaner"
    ],
    "wof:name":"Master Clean Cleaner",
    "wof:placetype":"venue"
},
  "geometry": {"coordinates":[-80.163399,25.6992],"type":"Point"}
}