{
  "type": "Feature",
  "properties": {
    "addr:full":"1901 SW 162nd Ave Hollywood FL 33027",
    "addr:housenumber":"1901",
    "addr:postcode":"33027",
    "addr:street":"Sw 162Nd Ave",
    "iso:country":"US",
    "sg:address":"1901 SW 162nd Ave",
    "sg:city":"Hollywood",
    "sg:classifiers":[
        {
            "category":"Freight",
            "type":"Transportation"
        }
    ],
    "sg:phone":"+1 954 442 4340",
    "sg:postcode":"33027",
    "sg:province":"FL",
    "sg:tags":[
        "owner",
        "operator",
        "travel",
        "agency",
        "trucking"
    ],
    "wof:name":"Los Andes Travel",
    "wof:placetype":"venue"
},
  "geometry": {"coordinates":[-80.362241,25.990966],"type":"Point"}
}