{
  "type": "Feature",
  "properties": {
    "iso:country":"US",
    "sg:address":"7320 NW 70th St",
    "sg:city":"Miami",
    "sg:classifiers":[
        {
            "category":"Freight",
            "type":"Transportation"
        }
    ],
    "sg:phone":"+1 305 888 6664",
    "sg:postcode":"33166",
    "sg:province":"FL",
    "sg:tags":[
        "operator",
        "trucking"
    ],
    "wof:name":"Ace Terminal 56",
    "wof:placetype":"venue"
},
  "geometry": {"coordinates":[-80.31703899999999,25.837114],"type":"Point"}
}