{
  "type": "Feature",
  "properties": {
    "iso:country":"US",
    "sg:address":"3947 State Hwy 105",
    "sg:city":"Jacksonville",
    "sg:classifiers":[
        {
            "category":"Utilities",
            "subcategory":"Refuse",
            "type":"Services"
        }
    ],
    "sg:phone":"+1 904 384 7546",
    "sg:postcode":"32226",
    "sg:province":"FL",
    "sg:tags":[
        "disposal",
        "hazardous",
        "industrial",
        "waste",
        "removal"
    ],
    "wof:name":"Iwe",
    "wof:placetype":"venue"
},
  "geometry": {"coordinates":[-81.57722699999999,30.412246],"type":"Point"}
}