{
  "type": "Feature",
  "properties": {
    "addr:full":"4000 Melissas Ln Middleburg FL 32068",
    "addr:housenumber":"4000",
    "addr:postcode":"32068",
    "addr:street":"Melissas Ln",
    "iso:country":"US",
    "sg:address":"4000 Melissas Ln",
    "sg:city":"Middleburg",
    "sg:classifiers":[
        {
            "category":"Building & Trades",
            "subcategory":"Construction",
            "type":"Services"
        }
    ],
    "sg:phone":"+1 904 406 2854",
    "sg:postcode":"32068",
    "sg:province":"FL",
    "sg:tags":[
        "contractor"
    ],
    "wof:name":"Silvester Stucco Inc",
    "wof:placetype":"venue"
},
  "geometry": {"coordinates":[-81.867999,30.123149],"type":"Point"}
}