{
  "type": "Feature",
  "properties": {
    "iso:country":"US",
    "sg:address":"1975 S Ocean Dr",
    "sg:city":"Hallandale",
    "sg:classifiers":[
        {
            "category":"Restaurant",
            "type":"Food & Drink"
        }
    ],
    "sg:menulink":"http://www.allmenus.com/fl/hallandale-beach/24248-josephs-on-the-water/menu/",
    "sg:phone":"+1 954 455 6996",
    "sg:postcode":"33009",
    "sg:province":"FL",
    "sg:tags":[
        "seafood",
        "american"
    ],
    "wof:name":"Joseph's On The Water",
    "wof:placetype":"venue"
},
  "geometry": {"coordinates":[-80.12014600000001,25.979486],"type":"Point"}
}