{
  "type": "Feature",
  "properties": {
    "iso:country":"US",
    "sg:address":"3838 Fancy Farms Rd",
    "sg:city":"Plant City",
    "sg:classifiers":[
        {
            "category":"Farming",
            "subcategory":"Berry Farm",
            "type":"Manufacturing & Wholesale Goods"
        }
    ],
    "sg:phone":"+1 813 754 4852",
    "sg:postcode":"33566",
    "sg:province":"FL",
    "sg:tags":[
        "strawberry"
    ],
    "wof:name":"Fancy Farms Inc",
    "wof:placetype":"venue"
},
  "geometry": {"coordinates":[-82.05899599999999,27.99299],"type":"Point"}
}