{
  "type": "Feature",
  "properties": {
    "iso:country":"US",
    "sg:address":"1000 N Powerline Rd",
    "sg:city":"Pompano Beach",
    "sg:classifiers":[
        {
            "category":"Shopping",
            "subcategory":"Music",
            "type":"Retail Goods"
        }
    ],
    "sg:phone":"+1 954 977 3833",
    "sg:postcode":"33069",
    "sg:province":"FL",
    "sg:tags":[
        "video",
        "disc",
        "tape",
        "cassette"
    ],
    "wof:name":"Cinema Video",
    "wof:placetype":"venue"
},
  "geometry": {"coordinates":[-80.151359,26.242341],"type":"Point"}
}