{
  "type": "Feature",
  "properties": {
    "addr:full":"19151 Dixie Hwy Miami FL 33157",
    "addr:housenumber":"19151",
    "addr:postcode":"33157",
    "addr:street":"Dixie Hwy",
    "iso:country":"US",
    "sg:address":"19151 Dixie Hwy",
    "sg:city":"Miami",
    "sg:classifiers":[
        {
            "category":"Professional",
            "subcategory":"Accounting & Tax Preparation",
            "type":"Services"
        }
    ],
    "sg:phone":"+1 305 238 8980",
    "sg:postcode":"33157",
    "sg:province":"FL",
    "sg:tags":[
        "return"
    ],
    "wof:name":"H & R Block",
    "wof:placetype":"venue"
},
  "geometry": {"coordinates":[-80.35776199999999,25.591284],"type":"Point"}
}