{
  "type": "Feature",
  "properties": {
    "iso:country":"US",
    "sg:address":"7845 NW 57th St",
    "sg:city":"Doral",
    "sg:classifiers":[
        {
            "category":"Professional",
            "subcategory":"Engineering",
            "type":"Services"
        }
    ],
    "sg:phone":"+1 305 994 3566",
    "sg:postcode":"33166",
    "sg:province":"FL",
    "sg:tags":[
        "engineer"
    ],
    "wof:name":"Connecticut Engineering Corp",
    "wof:placetype":"venue"
},
  "geometry": {"coordinates":[-80.32494699999999,25.825375],"type":"Point"}
}