{
  "type": "Feature",
  "properties": {
    "iso:country":"US",
    "sg:address":"3410 Raulerson Rd",
    "sg:city":"St Augustine",
    "sg:classifiers":[
        {
            "category":"Building & Trades",
            "subcategory":"Pest Control",
            "type":"Services"
        }
    ],
    "sg:phone":"+1 904 824 0011",
    "sg:postcode":"32092",
    "sg:province":"FL",
    "wof:name":"A 1 Trapper Man",
    "wof:placetype":"venue"
},
  "geometry": {"coordinates":[-81.441366,29.903462],"type":"Point"}
}