{
  "type": "Feature",
  "properties": {
    "addr:full":"6401 S West Shore Blvd Tampa FL 33616",
    "addr:housenumber":"6401",
    "addr:postcode":"33616",
    "addr:street":"S West Shore Blvd",
    "iso:country":"US",
    "sg:address":"6401 S West Shore Blvd",
    "sg:city":"Tampa",
    "sg:classifiers":[
        {
            "category":"Shopping",
            "subcategory":"Bicycles & Sporting Goods",
            "type":"Retail Goods"
        }
    ],
    "sg:phone":"+1 813 832 9168",
    "sg:postcode":"33616",
    "sg:province":"FL",
    "wof:name":"Universe Sport Management",
    "wof:placetype":"venue"
},
  "geometry": {"coordinates":[-82.526938,27.874703],"type":"Point"}
}