{
  "type": "Feature",
  "properties": {
    "iso:country":"US",
    "sg:address":"262 Corsair Ave",
    "sg:city":"Fort Lauderdale",
    "sg:classifiers":[
        {
            "category":"Building & Trades",
            "subcategory":"Construction",
            "type":"Services"
        }
    ],
    "sg:phone":"+1 954 491 3601",
    "sg:postcode":"33308",
    "sg:province":"FL",
    "sg:tags":[
        "business",
        "contractor"
    ],
    "wof:name":"Tl Ziel Pools Inc",
    "wof:placetype":"venue"
},
  "geometry": {"coordinates":[-80.100004,26.193865],"type":"Point"}
}