{
  "type": "Feature",
  "properties": {
    "addr:full":"700 E Lake Rd Palm Harbor FL 34685",
    "addr:housenumber":"700",
    "addr:postcode":"34685",
    "addr:street":"E Lake Rd",
    "iso:country":"US",
    "sg:address":"700 E Lake Rd",
    "sg:city":"Palm Harbor",
    "sg:classifiers":[
        {
            "category":"Retail",
            "subcategory":"Photofinishing",
            "type":"Services"
        }
    ],
    "sg:phone":"+1 727 787 6083",
    "sg:postcode":"34685",
    "sg:province":"FL",
    "sg:tags":[
        "laboratory"
    ],
    "wof:name":"Eckerd Express Photo",
    "wof:placetype":"venue"
},
  "geometry": {"coordinates":[-82.70471999999999,28.071312],"type":"Point"}
}