{
  "type": "Feature",
  "properties": {
    "addr:full":"10370 Trailwood Cir Jupiter FL 33478",
    "addr:housenumber":"10370",
    "addr:postcode":"33478",
    "addr:street":"Trailwood Cir",
    "iso:country":"US",
    "sg:address":"10370 Trailwood Cir",
    "sg:city":"Jupiter",
    "sg:classifiers":[
        {
            "category":"Professional",
            "subcategory":"Engineering",
            "type":"Services"
        }
    ],
    "sg:phone":"+1 561 575 2041",
    "sg:postcode":"33478",
    "sg:province":"FL",
    "sg:tags":[
        "engineer"
    ],
    "wof:name":"D Greg Braun Consulting",
    "wof:placetype":"venue"
},
  "geometry": {"coordinates":[-80.200964,26.941074],"type":"Point"}
}