{
  "type": "Feature",
  "properties": {
    "iso:country":"US",
    "sg:address":"5750 2nd Ave",
    "sg:city":"Key West",
    "sg:classifiers":[
        {
            "category":"Manufacturing",
            "subcategory":"Building Materials",
            "type":"Manufacturing & Wholesale Goods"
        },
        {
            "category":"Building & Trades",
            "subcategory":"Construction",
            "type":"Services"
        }
    ],
    "sg:phone":"+1 305 294 4279",
    "sg:postcode":"33040",
    "sg:province":"FL",
    "sg:tags":[
        "carpentry",
        "contractor"
    ],
    "wof:name":"Hansen & Bringle Cabinets",
    "wof:placetype":"venue"
},
  "geometry": {"coordinates":[-81.741315,24.571025],"type":"Point"}
}