{
  "type": "Feature",
  "properties": {
    "addr:full":"955 Jasmine Dr Delray Beach FL 33483",
    "addr:housenumber":"955",
    "addr:postcode":"33483",
    "addr:street":"Jasmine Dr",
    "iso:country":"US",
    "sg:address":"955 Jasmine Dr",
    "sg:city":"Delray Beach",
    "sg:classifiers":[
        {
            "category":"Professional",
            "subcategory":"Management & Consulting",
            "type":"Services"
        }
    ],
    "sg:phone":"+1 561 276 4734",
    "sg:postcode":"33483",
    "sg:province":"FL",
    "wof:name":"Atlantic Real Estates MGT",
    "wof:placetype":"venue"
},
  "geometry": {"coordinates":[-80.06669599999999,26.426217],"type":"Point"}
}