{
  "type": "Feature",
  "properties": {
    "addr:full":"1660 W 40th St Hialeah FL 33012",
    "addr:housenumber":"1660",
    "addr:postcode":"33012",
    "addr:street":"W 40Th St",
    "iso:country":"US",
    "sg:address":"1660 W 40th St",
    "sg:city":"Hialeah",
    "sg:classifiers":[
        {
            "category":"Wholesale",
            "subcategory":"Auto Parts",
            "type":"Manufacturing & Wholesale Goods"
        }
    ],
    "sg:phone":"+1 305 825 7505",
    "sg:postcode":"33012",
    "sg:province":"FL",
    "sg:tags":[
        "automobile"
    ],
    "wof:name":"Advanced Automotive Technology",
    "wof:placetype":"venue"
},
  "geometry": {"coordinates":[-80.31754599999999,25.858025],"type":"Point"}
}