{
  "type": "Feature",
  "properties": {
    "addr:full":"9084 Crystal Springs Rd Jacksonville FL 32221",
    "addr:housenumber":"9084",
    "addr:postcode":"32221",
    "addr:street":"Crystal Springs Rd",
    "iso:country":"US",
    "sg:address":"9084 Crystal Springs Rd",
    "sg:city":"Jacksonville",
    "sg:classifiers":[
        {
            "category":"Utilities",
            "subcategory":"Refuse",
            "type":"Services"
        }
    ],
    "sg:phone":"+1 904 781 7662",
    "sg:postcode":"32221",
    "sg:province":"FL",
    "sg:tags":[
        "garbage",
        "collection"
    ],
    "wof:name":"Moody's Rolloffs & Cleanup Inc",
    "wof:placetype":"venue"
},
  "geometry": {"coordinates":[-81.806957,30.30219],"type":"Point"}
}