{
  "type": "Feature",
  "properties": {
    "iso:country":"US",
    "sg:address":"2725 SW 10th St",
    "sg:city":"Fort Lauderdale",
    "sg:classifiers":[
        {
            "category":"Real Estate",
            "subcategory":"Real Estate Operator",
            "type":"Services"
        }
    ],
    "sg:phone":"+1 954 962 3237",
    "sg:postcode":"33312",
    "sg:province":"FL",
    "sg:tags":[
        "apartment",
        "rental"
    ],
    "wof:name":"Catherine Brodie",
    "wof:placetype":"venue"
},
  "geometry": {"coordinates":[-80.179126,26.109724],"type":"Point"}
}