{
  "type": "Feature",
  "properties": {
    "addr:full":"4201 Baymeadows Rd Jacksonville FL 32217",
    "addr:housenumber":"4201",
    "addr:postcode":"32217",
    "addr:street":"Baymeadows Rd",
    "iso:country":"US",
    "sg:address":"4201 Baymeadows Rd",
    "sg:city":"Jacksonville",
    "sg:classifiers":[
        {
            "category":"Banks & Credit Unions",
            "subcategory":"Bank",
            "type":"Services"
        }
    ],
    "sg:phone":"+1 904 730 5603",
    "sg:postcode":"32217",
    "sg:province":"FL",
    "sg:tags":[
        "mortgage",
        "loan",
        "broker",
        "real estate"
    ],
    "sg:website":"www.macofjax.com",
    "wof:name":"Mortgage Acceptance Corp",
    "wof:placetype":"venue"
},
  "geometry": {"coordinates":[-81.60929,30.21893],"type":"Point"}
}