{
  "type": "Feature",
  "properties": {
    "iso:country":"US",
    "sg:address":"619 N Grandview Ave",
    "sg:city":"Daytona Beach",
    "sg:classifiers":[
        {
            "category":"Professional",
            "subcategory":"Lawyer & Legal Services",
            "type":"Services"
        }
    ],
    "sg:phone":"+1 386 257 1529",
    "sg:postcode":"32118",
    "sg:province":"FL",
    "sg:tags":[
        "attorney"
    ],
    "wof:name":"Polsky Larry Mark Law Office",
    "wof:placetype":"venue"
},
  "geometry": {"coordinates":[-81.01421000000001,29.236519],"type":"Point"}
}