{
  "type": "Feature",
  "properties": {
    "addr:full":"4126 NW 21st St Lauderhill FL 33313",
    "addr:housenumber":"4126",
    "addr:postcode":"33313",
    "addr:street":"Nw 21St St",
    "iso:country":"US",
    "sg:address":"4126 NW 21st St",
    "sg:city":"Lauderhill",
    "sg:classifiers":[
        {
            "category":"Real Estate",
            "subcategory":"Real Estate Agent",
            "type":"Services"
        }
    ],
    "sg:phone":"+1 954 318 0737",
    "sg:postcode":"33313",
    "sg:province":"FL",
    "wof:name":"Realty Golden Sands",
    "wof:placetype":"venue"
},
  "geometry": {"coordinates":[-80.205499,26.153686],"type":"Point"}
}