{
  "type": "Feature",
  "properties": {
    "iso:country":"US",
    "sg:address":"6751 SW 13th St",
    "sg:city":"Miami",
    "sg:classifiers":[
        {
            "category":"Transit Center",
            "subcategory":"Freight",
            "type":"Transportation"
        }
    ],
    "sg:phone":"+1 954 966 2878",
    "sg:postcode":"33144",
    "sg:province":"FL",
    "sg:tags":[
        "container",
        "broker"
    ],
    "wof:name":"Transport Network",
    "wof:placetype":"venue"
},
  "geometry": {"coordinates":[-80.304777,25.758684],"type":"Point"}
}