{
  "type": "Feature",
  "properties": {
    "addr:full":"880 S Atlantic Ave Ormond Beach FL 32176",
    "addr:housenumber":"880",
    "addr:postcode":"32176",
    "addr:street":"S Atlantic Ave",
    "iso:country":"US",
    "sg:address":"880 S Atlantic Ave",
    "sg:city":"Ormond Beach",
    "sg:classifiers":[
        {
            "category":"Restaurant",
            "type":"Food & Drink"
        }
    ],
    "sg:menulink":"http://www.allmenus.com/fl/north-peninsula/13870-olive-garden-italian-restaurant/menu/",
    "sg:phone":"+1 386 673 3027",
    "sg:postcode":"32176",
    "sg:province":"FL",
    "sg:tags":[
        "italian"
    ],
    "wof:name":"Olive Garden Italian Restaurant",
    "wof:placetype":"venue"
},
  "geometry": {"coordinates":[-81.030771,29.270502],"type":"Point"}
}