{
  "type": "Feature",
  "properties": {
    "iso:country":"US",
    "sg:address":"6511 Aqueduct Ct",
    "sg:city":"Tallahassee",
    "sg:classifiers":[
        {
            "category":"Professional",
            "subcategory":"Detective & Security Services",
            "type":"Services"
        }
    ],
    "sg:phone":"+1 561 376 4630",
    "sg:postcode":"32309",
    "sg:province":"FL",
    "sg:tags":[
        "investigator"
    ],
    "wof:name":"Eli Thomasevich & Assoc",
    "wof:placetype":"venue"
},
  "geometry": {"coordinates":[-84.179457,30.545868],"type":"Point"}
}