{
  "type": "Feature",
  "properties": {
    "addr:full":"2377 Roanoke Ct Lake Mary FL 32746",
    "addr:housenumber":"2377",
    "addr:postcode":"32746",
    "addr:street":"Roanoke Ct",
    "iso:country":"US",
    "sg:address":"2377 Roanoke Ct",
    "sg:city":"Lake Mary",
    "sg:classifiers":[
        {
            "category":"Professional",
            "subcategory":"Management & Consulting",
            "type":"Services"
        }
    ],
    "sg:phone":"+1 407 679 6437",
    "sg:postcode":"32746",
    "sg:province":"FL",
    "sg:tags":[
        "consultant",
        "safety"
    ],
    "wof:name":"Integrated Safety",
    "wof:placetype":"venue"
},
  "geometry": {"coordinates":[-81.335686,28.732512],"type":"Point"}
}