{
  "type": "Feature",
  "properties": {
    "iso:country":"US",
    "sg:address":"1445 Banks Rd",
    "sg:city":"Margate",
    "sg:classifiers":[
        {
            "category":"Organizations",
            "subcategory":"Professional Association",
            "type":"Services"
        }
    ],
    "sg:phone":"+1 954 582 0592",
    "sg:postcode":"33063",
    "sg:province":"FL",
    "sg:tags":[
        "mail-order",
        "fulfillment"
    ],
    "wof:name":"Raya T McCray Enterprise Inc",
    "wof:placetype":"venue"
},
  "geometry": {"coordinates":[-80.194354,26.247319],"type":"Point"}
}