{
  "type": "Feature",
  "properties": {
    "iso:country":"US",
    "sg:address":"1316 Clearglades Dr",
    "sg:city":"Wesley Chapel",
    "sg:classifiers":[
        {
            "category":"Organizations",
            "subcategory":"Religious Organization",
            "type":"Services"
        }
    ],
    "sg:phone":"+1 813 933 7953",
    "sg:postcode":"33543",
    "sg:province":"FL",
    "sg:tags":[
        "church"
    ],
    "wof:name":"House Of Prayer",
    "wof:placetype":"venue"
},
  "geometry": {"coordinates":[-82.348029,28.178646],"type":"Point"}
}