{
  "type": "Feature",
  "properties": {
    "iso:country":"US",
    "sg:address":"4301 SW 75th Ave",
    "sg:city":"Miami",
    "sg:classifiers":[
        {
            "category":"Retail",
            "subcategory":"Portrait Studio",
            "type":"Services"
        }
    ],
    "sg:phone":"+1 305 269 0180",
    "sg:postcode":"33155",
    "sg:province":"FL",
    "sg:tags":[
        "photographer"
    ],
    "wof:name":"Photocom",
    "wof:placetype":"venue"
},
  "geometry": {"coordinates":[-80.31673600000001,25.725577],"type":"Point"}
}