{
  "type": "Feature",
  "properties": {
    "iso:country":"US",
    "sg:address":"2 S Orange Ave Ste 100",
    "sg:city":"Orlando",
    "sg:classifiers":[
        {
            "category":"Banks & Credit Unions",
            "subcategory":"Bank",
            "type":"Services"
        }
    ],
    "sg:phone":"+1 800 377 0800",
    "sg:postcode":"32801",
    "sg:province":"FL",
    "sg:tags":[
        "saving",
        "commercial"
    ],
    "sg:website":"http://www.bpop.com",
    "wof:name":"Banco Popular",
    "wof:placetype":"venue"
},
  "geometry": {"coordinates":[-81.37904399999999,28.54213],"type":"Point"}
}