{
  "type": "Feature",
  "properties": {
    "addr:full":"1200 Oceanview Ave Marathon FL 33050",
    "addr:housenumber":"1200",
    "addr:postcode":"33050",
    "addr:street":"Oceanview Ave",
    "iso:country":"US",
    "sg:address":"1200 Oceanview Ave",
    "sg:city":"Marathon",
    "sg:classifiers":[
        {
            "category":"Autos & Motor Vehicles",
            "subcategory":"Boat Sales",
            "type":"Retail Goods"
        }
    ],
    "sg:phone":"+1 305 743 5317",
    "sg:postcode":"33050",
    "sg:province":"FL",
    "sg:tags":[
        "gasoline",
        "station",
        "marine",
        "supply"
    ],
    "wof:name":"Burdines Waterfront",
    "wof:placetype":"venue"
},
  "geometry": {"coordinates":[-81.10968099999999,24.703429],"type":"Point"}
}