{
  "type": "Feature",
  "properties": {
    "iso:country":"US",
    "sg:address":"4105 Pine Tree Pl",
    "sg:city":"Cocoa",
    "sg:classifiers":[
        {
            "category":"Building & Trades",
            "subcategory":"Construction",
            "type":"Services"
        }
    ],
    "sg:phone":"+1 321 544 1597",
    "sg:postcode":"32926",
    "sg:province":"FL",
    "sg:tags":[
        "carpentry",
        "contractor"
    ],
    "wof:name":"Tracey Hull Construction",
    "wof:placetype":"venue"
},
  "geometry": {"coordinates":[-80.78936899999999,28.375123],"type":"Point"}
}