{
  "type": "Feature",
  "properties": {
    "iso:country":"US",
    "sg:address":"1212 Markley Dr",
    "sg:city":"Largo",
    "sg:classifiers":[
        {
            "category":"Health Services",
            "subcategory":"Clinic",
            "type":"Services"
        }
    ],
    "sg:phone":"+1 727 518 7178",
    "sg:postcode":"33770",
    "sg:province":"FL",
    "sg:tags":[
        "welfare"
    ],
    "wof:name":"Florida Medical Education Speakers Netwo",
    "wof:placetype":"venue"
},
  "geometry": {"coordinates":[-82.774095,27.925657],"type":"Point"}
}