{
  "type": "Feature",
  "properties": {
    "iso:country":"US",
    "sg:address":"13651 W Dixie Hwy",
    "sg:city":"North Miami",
    "sg:classifiers":[
        {
            "category":"Travel",
            "subcategory":"Travel Agent",
            "type":"Entertainment"
        }
    ],
    "sg:phone":"+1 305 899 1011",
    "sg:postcode":"33161",
    "sg:province":"FL",
    "sg:tags":[
        "agency",
        "bureau"
    ],
    "wof:name":"Elka Travel",
    "wof:placetype":"venue"
},
  "geometry": {"coordinates":[-80.175991,25.902535],"type":"Point"}
}