{
  "type": "Feature",
  "properties": {
    "addr:full":"2874 NW 79th Ave Miami FL 33122",
    "addr:housenumber":"2874",
    "addr:postcode":"33122",
    "addr:street":"Nw 79Th Ave",
    "iso:country":"US",
    "sg:address":"2874 NW 79th Ave",
    "sg:city":"Miami",
    "sg:classifiers":[
        {
            "category":"Wholesale",
            "subcategory":"Plants",
            "type":"Manufacturing & Wholesale Goods"
        }
    ],
    "sg:phone":"+1 786 497 5020",
    "sg:postcode":"33122",
    "sg:province":"FL",
    "sg:tags":[
        "supply"
    ],
    "wof:name":"Farm Masters Inc",
    "wof:placetype":"venue"
},
  "geometry": {"coordinates":[-80.325053,25.797544],"type":"Point"}
}