{
  "type": "Feature",
  "properties": {
    "addr:full":"4140 Memorial Blue Star Hwy Chattahoochee FL 32324",
    "addr:housenumber":"4140",
    "addr:postcode":"32324",
    "addr:street":"Memorial Blue Star Hwy",
    "iso:country":"US",
    "sg:address":"4140 Memorial Blue Star Hwy",
    "sg:city":"Chattahoochee",
    "sg:classifiers":[
        {
            "category":"Organizations",
            "subcategory":"Religious Organization",
            "type":"Services"
        }
    ],
    "sg:phone":"+1 850 663 8713",
    "sg:postcode":"32324",
    "sg:province":"FL",
    "wof:name":"Holy Rock House Of Prayer Inc",
    "wof:placetype":"venue"
},
  "geometry": {"coordinates":[-84.799499,30.701223],"type":"Point"}
}