{
  "type": "Feature",
  "properties": {
    "addr:full":"1150 NE Dixie Hwy Jensen Beach FL 34957",
    "addr:housenumber":"1150",
    "addr:postcode":"34957",
    "addr:street":"Ne Dixie Hwy",
    "iso:country":"US",
    "sg:address":"1150 NE Dixie Hwy",
    "sg:city":"Jensen Beach",
    "sg:classifiers":[
        {
            "category":"Retail",
            "subcategory":"Animal Services",
            "type":"Services"
        }
    ],
    "sg:phone":"+1 772 232 0444",
    "sg:postcode":"34957",
    "sg:province":"FL",
    "sg:tags":[
        "pet",
        "grooming",
        "washing"
    ],
    "wof:name":"Hair Of The Dog",
    "wof:placetype":"venue"
},
  "geometry": {"coordinates":[-80.236946,27.219503],"type":"Point"}
}