{
  "type": "Feature",
  "properties": {
    "addr:full":"401 Coral Way Coral Gables FL 33134",
    "addr:housenumber":"401",
    "addr:postcode":"33134",
    "addr:street":"Coral Way",
    "iso:country":"US",
    "sg:address":"401 Coral Way",
    "sg:city":"Coral Gables",
    "sg:classifiers":[
        {
            "category":"Health Services",
            "subcategory":"Dentist",
            "type":"Services"
        }
    ],
    "sg:phone":"+1 305 648 9190",
    "sg:postcode":"33134",
    "sg:province":"FL",
    "wof:name":"Bird Juan C DMD PA",
    "wof:placetype":"venue"
},
  "geometry": {"coordinates":[-80.2632,25.749637],"type":"Point"}
}