{
  "type": "Feature",
  "properties": {
    "iso:country":"US",
    "sg:address":"1402 Clearlake Rd",
    "sg:city":"Cocoa",
    "sg:classifiers":[
        {
            "category":"Manufacturing",
            "subcategory":"Buildings",
            "type":"Manufacturing & Wholesale Goods"
        },
        {
            "category":"Building & Trades",
            "subcategory":"Construction",
            "type":"Services"
        }
    ],
    "sg:phone":"+1 321 323 6613",
    "sg:postcode":"32922",
    "sg:province":"FL",
    "sg:tags":[
        "roofing",
        "industrial",
        "builder",
        "contractor",
        "contractors-commercial",
        "home"
    ],
    "wof:name":"Rock Home Improvements",
    "wof:placetype":"venue"
},
  "geometry": {"coordinates":[-80.755043,28.37994],"type":"Point"}
}