{
  "type": "Feature",
  "properties": {
    "addr:full":"10056 NW 51st Ter Doral FL 33178",
    "addr:housenumber":"10056",
    "addr:postcode":"33178",
    "addr:street":"Nw 51St Ter",
    "iso:country":"US",
    "sg:address":"10056 NW 51st Ter",
    "sg:city":"Doral",
    "sg:classifiers":[
        {
            "category":"Real Estate",
            "subcategory":"Real Estate Agent",
            "type":"Services"
        }
    ],
    "sg:phone":"+1 305 251 3000",
    "sg:postcode":"33178",
    "sg:province":"FL",
    "wof:name":"Real Corp",
    "wof:placetype":"venue"
},
  "geometry": {"coordinates":[-80.357669,25.819844],"type":"Point"}
}