{
  "type": "Feature",
  "properties": {
    "addr:full":"10540 Portal Xing Bradenton FL 34211",
    "addr:housenumber":"10540",
    "addr:postcode":"34211",
    "addr:street":"Portal Xing",
    "iso:country":"US",
    "sg:address":"10540 Portal Xing",
    "sg:city":"Bradenton",
    "sg:classifiers":[
        {
            "category":"Real Estate",
            "subcategory":"Developer",
            "type":"Services"
        },
        {
            "category":"Professional",
            "type":"Services"
        }
    ],
    "sg:phone":"+1 941 744 2460",
    "sg:postcode":"34211",
    "sg:province":"FL",
    "wof:name":"Blackpoint Group LLC",
    "wof:placetype":"venue"
},
  "geometry": {"coordinates":[-82.437561,27.481886],"type":"Point"}
}