{
  "type": "Feature",
  "properties": {
    "addr:full":"5997 NW 73rd Ct Parkland FL 33067",
    "addr:housenumber":"5997",
    "addr:postcode":"33067",
    "addr:street":"Nw 73Rd Ct",
    "iso:country":"US",
    "sg:address":"5997 NW 73rd Ct",
    "sg:city":"Parkland",
    "sg:classifiers":[
        {
            "category":"Professional",
            "subcategory":"Engineering",
            "type":"Services"
        }
    ],
    "sg:phone":"+1 954 755 6018",
    "sg:postcode":"33067",
    "sg:province":"FL",
    "sg:tags":[
        "engineer"
    ],
    "wof:name":"Abaco Engineering",
    "wof:placetype":"venue"
},
  "geometry": {"coordinates":[-80.206278,26.321504],"type":"Point"}
}