{
  "type": "Feature",
  "properties": {
    "addr:full":"3468 E Semoran Blvd Apopka FL 32703",
    "addr:housenumber":"3468 e",
    "addr:postcode":"32703",
    "addr:street":"Semoran Blvd",
    "iso:country":"US",
    "sg:address":"3468 E Semoran Blvd",
    "sg:city":"Apopka",
    "sg:classifiers":[
        {
            "category":"Retail",
            "subcategory":"Animal Services",
            "type":"Services"
        }
    ],
    "sg:phone":"+1 407 786 1010",
    "sg:postcode":"32703",
    "sg:province":"FL",
    "sg:tags":[
        "pet",
        "boarding",
        "sitting"
    ],
    "wof:name":"Camp Bow Wow Inc",
    "wof:placetype":"venue"
},
  "geometry": {"coordinates":[-81.45612,28.672176],"type":"Point"}
}