{
  "type": "Feature",
  "properties": {
    "addr:full":"350 NW 36th St Miami FL 33127",
    "addr:housenumber":"350",
    "addr:postcode":"33127",
    "addr:street":"Nw 36Th St",
    "iso:country":"US",
    "sg:address":"350 NW 36th St",
    "sg:city":"Miami",
    "sg:classifiers":[
        {
            "category":"Retail",
            "subcategory":"Auto Repair",
            "type":"Services"
        }
    ],
    "sg:phone":"+1 305 573 0598",
    "sg:postcode":"33127",
    "sg:province":"FL",
    "sg:tags":[
        "automobile",
        "machine",
        "shop"
    ],
    "wof:name":"Vega General Mechanic",
    "wof:placetype":"venue"
},
  "geometry": {"coordinates":[-80.201944,25.810234],"type":"Point"}
}