{
  "type": "Feature",
  "properties": {
    "iso:country":"US",
    "sg:address":"921 10th Ave N",
    "sg:city":"St Petersburg",
    "sg:classifiers":[
        {
            "category":"Organizations",
            "subcategory":"Religious Organization",
            "type":"Services"
        }
    ],
    "sg:phone":"+1 727 822 1498",
    "sg:postcode":"33705",
    "sg:province":"FL",
    "sg:tags":[
        "church"
    ],
    "wof:name":"Inglesia Cristiana Vida Nueva",
    "wof:placetype":"venue"
},
  "geometry": {"coordinates":[-82.647536,27.782221],"type":"Point"}
}