{
  "type": "Feature",
  "properties": {
    "addr:full":"915 N Lime Ave Sarasota FL 34237",
    "addr:housenumber":"915",
    "addr:postcode":"34237",
    "addr:street":"N Lime Ave",
    "iso:country":"US",
    "sg:address":"915 N Lime Ave",
    "sg:city":"Sarasota",
    "sg:classifiers":[
        {
            "category":"Retail",
            "subcategory":"Auto Repair",
            "type":"Services"
        }
    ],
    "sg:phone":"+1 941 365 5920",
    "sg:postcode":"34237",
    "sg:province":"FL",
    "sg:tags":[
        "repairing",
        "automobile",
        "general"
    ],
    "wof:name":"Dad's Garage",
    "wof:placetype":"venue"
},
  "geometry": {"coordinates":[-82.524247,27.34488],"type":"Point"}
}