{
  "type": "Feature",
  "properties": {
    "addr:full":"1250 Tamiami Trl N Naples FL 34102",
    "addr:housenumber":"1250",
    "addr:postcode":"34102",
    "addr:street":"Tamiami Trl N",
    "iso:country":"US",
    "sg:address":"1250 Tamiami Trl N",
    "sg:city":"Naples",
    "sg:classifiers":[
        {
            "category":"Professional",
            "subcategory":"Lawyer & Legal Services",
            "type":"Services"
        }
    ],
    "sg:phone":"+1 239 263 8357",
    "sg:postcode":"34102",
    "sg:province":"FL",
    "sg:tags":[
        "attorney"
    ],
    "wof:name":"Thomas W Franchino Pa",
    "wof:placetype":"venue"
},
  "geometry": {"coordinates":[-81.798295,26.163721],"type":"Point"}
}