{
  "type": "Feature",
  "properties": {
    "addr:full":"3982 W 16th Ave Hialeah FL 33012",
    "addr:housenumber":"3982",
    "addr:postcode":"33012",
    "addr:street":"W 16Th Ave",
    "iso:country":"US",
    "sg:address":"3982 W 16th Ave",
    "sg:city":"Hialeah",
    "sg:classifiers":[
        {
            "category":"Personal",
            "subcategory":"Nail Salon",
            "type":"Services"
        }
    ],
    "sg:phone":"+1 305 821 5989",
    "sg:postcode":"33012",
    "sg:province":"FL",
    "wof:name":"Le Nails",
    "wof:placetype":"venue"
},
  "geometry": {"coordinates":[-80.314499,25.858],"type":"Point"}
}