{
  "type": "Feature",
  "properties": {
    "addr:full":"5325 8th St Zephyrhills FL 33542",
    "addr:housenumber":"5325",
    "addr:postcode":"33542",
    "addr:street":"8Th St",
    "iso:country":"US",
    "sg:address":"5325 8th St",
    "sg:city":"Zephyrhills",
    "sg:classifiers":[
        {
            "category":"Organizations",
            "subcategory":"Community Association",
            "type":"Services"
        }
    ],
    "sg:phone":"+1 813 783 7012",
    "sg:postcode":"33542",
    "sg:province":"FL",
    "sg:tags":[
        "military"
    ],
    "wof:name":"Disabled American Veterans",
    "wof:placetype":"venue"
},
  "geometry": {"coordinates":[-82.18034,28.234924],"type":"Point"}
}