{
  "type": "Feature",
  "properties": {
    "iso:country":"US",
    "sg:address":"2130 N Dover Rd",
    "sg:city":"Dover",
    "sg:classifiers":[
        {
            "category":"Manufacturing",
            "subcategory":"Signs",
            "type":"Manufacturing & Wholesale Goods"
        }
    ],
    "sg:phone":"+1 813 659 0178",
    "sg:postcode":"33527",
    "sg:province":"FL",
    "sg:tags":[
        "advertising",
        "specialty"
    ],
    "wof:name":"Alpha Sign Graphic & Lettering",
    "wof:placetype":"venue"
},
  "geometry": {"coordinates":[-82.219797,27.975615],"type":"Point"}
}