{
  "type": "Feature",
  "properties": {
    "addr:full":"4815 Keene Rd Plant City FL 33565",
    "addr:housenumber":"4815",
    "addr:postcode":"33565",
    "addr:street":"Keene Rd",
    "iso:country":"US",
    "sg:address":"4815 Keene Rd",
    "sg:city":"Plant City",
    "sg:classifiers":[
        {
            "category":"Education",
            "subcategory":"School",
            "type":"Public Place"
        }
    ],
    "sg:phone":"+1 813 757 9333",
    "sg:postcode":"33565",
    "sg:province":"FL",
    "sg:tags":[
        "elementary"
    ],
    "wof:name":"Knights Elementary School",
    "wof:placetype":"venue"
},
  "geometry": {"coordinates":[-82.15447399999999,28.074688],"type":"Point"}
}