{
  "type": "Feature",
  "properties": {
    "iso:country":"US",
    "sg:address":"655 104th Ave N",
    "sg:city":"Naples",
    "sg:classifiers":[
        {
            "category":"Organizations",
            "subcategory":"Professional Association",
            "type":"Services"
        }
    ],
    "sg:phone":"+1 239 596 2222",
    "sg:postcode":"34108",
    "sg:province":"FL",
    "wof:name":"Naples Park Area Assn",
    "wof:placetype":"venue"
},
  "geometry": {"coordinates":[-81.81139,26.266103],"type":"Point"}
}