{
  "type": "Feature",
  "properties": {
    "addr:full":"5500 82nd Ter Pinellas Park FL 33781",
    "addr:housenumber":"5500",
    "addr:postcode":"33781",
    "addr:street":"82Nd Ter;Park",
    "iso:country":"US",
    "sg:address":"5500 82nd Ter",
    "sg:city":"Pinellas Park",
    "sg:classifiers":[
        {
            "category":"Building & Trades",
            "subcategory":"Construction",
            "type":"Services"
        }
    ],
    "sg:phone":"+1 727 545 0411",
    "sg:postcode":"33781",
    "sg:province":"FL",
    "sg:tags":[
        "hanging",
        "contractor"
    ],
    "wof:name":"Angels Painting Contractor",
    "wof:placetype":"venue"
},
  "geometry": {"coordinates":[-82.7116,27.847136],"type":"Point"}
}