{
  "type": "Feature",
  "properties": {
    "iso:country":"US",
    "sg:address":"4802 Sleepy Hollow Ln",
    "sg:city":"Plant City",
    "sg:classifiers":[
        {
            "category":"Building & Trades",
            "subcategory":"Construction",
            "type":"Services"
        }
    ],
    "sg:phone":"+1 813 752 8800",
    "sg:postcode":"33565",
    "sg:province":"FL",
    "sg:tags":[
        "contractor"
    ],
    "wof:name":"Yokell Sales & Construction",
    "wof:placetype":"venue"
},
  "geometry": {"coordinates":[-82.144609,28.075126],"type":"Point"}
}