{
  "type": "Feature",
  "properties": {
    "addr:full":"17221 Tiffany Shore Dr Lutz FL 33549",
    "addr:housenumber":"17221",
    "addr:postcode":"33549",
    "addr:street":"Tiffany Shore Dr",
    "iso:country":"US",
    "sg:address":"17221 Tiffany Shore Dr",
    "sg:city":"Lutz",
    "sg:classifiers":[
        {
            "category":"Professional",
            "subcategory":"Computer Services",
            "type":"Services"
        },
        {
            "category":"Wholesale",
            "subcategory":"Computers",
            "type":"Manufacturing & Wholesale Goods"
        }
    ],
    "sg:phone":"+1 813 340 1555",
    "sg:postcode":"33549",
    "sg:province":"FL",
    "sg:tags":[
        "equipment",
        "software"
    ],
    "wof:name":"Panther Technologies, Inc.",
    "wof:placetype":"venue"
},
  "geometry": {"coordinates":[-82.455275,28.116204],"type":"Point"}
}