{
  "type": "Feature",
  "properties": {
    "iso:country":"US",
    "sg:address":"148 San Cristobal Ave",
    "sg:city":"East Palatka",
    "sg:classifiers":[
        {
            "category":"Professional",
            "subcategory":"Computer Services",
            "type":"Services"
        }
    ],
    "sg:phone":"+1 386 328 6408",
    "sg:postcode":"32131",
    "sg:province":"FL",
    "sg:tags":[
        "development",
        "educational",
        "software"
    ],
    "wof:name":"Apply Networks Corporation",
    "wof:placetype":"venue"
},
  "geometry": {"coordinates":[-81.583714,29.634045],"type":"Point"}
}