{
  "type": "Feature",
  "properties": {
    "addr:full":"4820 Manatee Ave W Bradenton FL 34209",
    "addr:housenumber":"4820",
    "addr:postcode":"34209",
    "addr:street":"Manatee Ave W",
    "iso:country":"US",
    "sg:address":"4820 Manatee Ave W",
    "sg:city":"Bradenton",
    "sg:classifiers":[
        {
            "category":"Insurance",
            "subcategory":"Insurance Agent",
            "type":"Services"
        }
    ],
    "sg:phone":"+1 941 748 1221",
    "sg:postcode":"34209",
    "sg:province":"FL",
    "wof:name":"Allstate",
    "wof:placetype":"venue"
},
  "geometry": {"coordinates":[-82.609341,27.495948],"type":"Point"}
}