{
  "type": "Feature",
  "properties": {
    "iso:country":"US",
    "sg:address":"1140 Holland Dr",
    "sg:city":"Boca Raton",
    "sg:classifiers":[
        {
            "category":"Manufacturing",
            "subcategory":"Printing",
            "type":"Manufacturing & Wholesale Goods"
        }
    ],
    "sg:phone":"+1 352 375 3705",
    "sg:postcode":"33487",
    "sg:province":"FL",
    "sg:tags":[
        "periodical"
    ],
    "wof:name":"Upbeat Seniors",
    "wof:placetype":"venue"
},
  "geometry": {"coordinates":[-80.11374600000001,26.406806],"type":"Point"}
}