{
  "type": "Feature",
  "properties": {
    "iso:country":"US",
    "sg:address":"2100 Pullman Cir",
    "sg:city":"Pensacola",
    "sg:classifiers":[
        {
            "category":"Manufacturing",
            "subcategory":"Signs",
            "type":"Manufacturing & Wholesale Goods"
        }
    ],
    "sg:phone":"+1 850 456 2158",
    "sg:postcode":"32526",
    "sg:province":"FL",
    "wof:name":"American Lighting & Signs",
    "wof:placetype":"venue"
},
  "geometry": {"coordinates":[-87.29082099999999,30.451597],"type":"Point"}
}