{
  "type": "Feature",
  "properties": {
    "iso:country":"US",
    "sg:address":"10164 NW 47th St",
    "sg:city":"Sunrise",
    "sg:classifiers":[
        {
            "category":"Wholesale",
            "subcategory":"Metals & Minerals",
            "type":"Manufacturing & Wholesale Goods"
        }
    ],
    "sg:phone":"+1 954 746 9155",
    "sg:postcode":"33351",
    "sg:province":"FL",
    "sg:tags":[
        "specialty"
    ],
    "wof:name":"SSMF Inc",
    "wof:placetype":"venue"
},
  "geometry": {"coordinates":[-80.28613199999999,26.183363],"type":"Point"}
}