{
  "type": "Feature",
  "properties": {
    "addr:full":"577 Interstate Blvd Sarasota FL 34240",
    "addr:housenumber":"577",
    "addr:postcode":"34240",
    "addr:street":"Interstate Blvd",
    "iso:country":"US",
    "sg:address":"577 Interstate Blvd",
    "sg:city":"Sarasota",
    "sg:classifiers":[
        {
            "category":"Wholesale",
            "subcategory":"Machinery & Supplies",
            "type":"Manufacturing & Wholesale Goods"
        }
    ],
    "sg:phone":"+1 941 379 4207",
    "sg:postcode":"34240",
    "sg:province":"FL",
    "sg:tags":[
        "equipment",
        "pneumatic",
        "industrial",
        "component"
    ],
    "wof:name":"Florida Numatics Inc",
    "wof:placetype":"venue"
},
  "geometry": {"coordinates":[-82.446496,27.332074],"type":"Point"}
}