{
  "type": "Feature",
  "properties": {
    "iso:country":"US",
    "sg:address":"2990 W 84th St",
    "sg:city":"Hialeah",
    "sg:classifiers":[
        {
            "category":"Retail",
            "subcategory":"Storage",
            "type":"Services"
        }
    ],
    "sg:phone":"+1 305 826 2980",
    "sg:postcode":"33018",
    "sg:province":"FL",
    "sg:tags":[
        "self"
    ],
    "sg:website":"www.extraspace.com/Storage/Facil...",
    "wof:name":"Extra Space Storage",
    "wof:placetype":"venue"
},
  "geometry": {"coordinates":[-80.345024,25.897467],"type":"Point"}
}