{
  "type": "Feature",
  "properties": {
    "addr:full":"5700 Hood St Hollywood FL 33021",
    "addr:housenumber":"5700",
    "addr:postcode":"33021",
    "addr:street":"Hood St",
    "iso:country":"US",
    "sg:address":"5700 Hood St",
    "sg:city":"Hollywood",
    "sg:classifiers":[
        {
            "category":"Building & Trades",
            "subcategory":"Cleaning & Sanitation",
            "type":"Services"
        }
    ],
    "sg:phone":"+1 954 894 3393",
    "sg:postcode":"33021",
    "sg:province":"FL",
    "sg:tags":[
        "janitor"
    ],
    "wof:name":"South Florida Boss Bldg Svc",
    "wof:placetype":"venue"
},
  "geometry": {"coordinates":[-80.20223900000001,26.032959],"type":"Point"}
}