{
  "type": "Feature",
  "properties": {
    "addr:full":"2806 42nd St W Bradenton FL 34205",
    "addr:housenumber":"2806",
    "addr:postcode":"34205",
    "addr:street":"42Nd St W",
    "iso:country":"US",
    "sg:address":"2806 42nd St W",
    "sg:city":"Bradenton",
    "sg:classifiers":[
        {
            "category":"Building & Trades",
            "subcategory":"Cleaning & Sanitation",
            "type":"Services"
        }
    ],
    "sg:phone":"+1 941 756 3195",
    "sg:postcode":"34205",
    "sg:province":"FL",
    "sg:tags":[
        "house"
    ],
    "wof:name":"Anthro Cleaning Svc",
    "wof:placetype":"venue"
},
  "geometry": {"coordinates":[-82.603576,27.4757],"type":"Point"}
}