{
  "type": "Feature",
  "properties": {
    "addr:full":"11655 Dixie Hwy Miami FL 33156",
    "addr:housenumber":"11655",
    "addr:postcode":"33156",
    "addr:street":"Dixie Hwy",
    "iso:country":"US",
    "sg:address":"11655 Dixie Hwy",
    "sg:city":"Miami",
    "sg:classifiers":[
        {
            "category":"Shopping",
            "type":"Retail Goods"
        }
    ],
    "sg:phone":"+1 305 969 1993",
    "sg:postcode":"33156",
    "sg:province":"FL",
    "sg:tags":[
        "merchandise"
    ],
    "wof:name":"Blackies Surf Shop",
    "wof:placetype":"venue"
},
  "geometry": {"coordinates":[-80.323971,25.666138],"type":"Point"}
}