{
  "type": "Feature",
  "properties": {
    "iso:country":"US",
    "sg:address":"2669 Gulf To Bay Blvd",
    "sg:city":"Clearwater",
    "sg:classifiers":[
        {
            "category":"Home & Garden",
            "subcategory":"Home Furnishings",
            "type":"Retail Goods"
        }
    ],
    "sg:phone":"+1 727 726 3890",
    "sg:postcode":"33759",
    "sg:province":"FL",
    "sg:tags":[
        "linen"
    ],
    "wof:name":"Linens 'n Things",
    "wof:placetype":"venue"
},
  "geometry": {"coordinates":[-82.728931,27.960478],"type":"Point"}
}