{
  "type": "Feature",
  "properties": {
    "addr:full":"7575 Dr Phillips Blvd # 250 Orlando FL 32819",
    "addr:housenumber":"7575",
    "addr:postcode":"32819",
    "addr:street":"Dr Phillips Blvd # 250",
    "iso:country":"US",
    "sg:address":"7575 Dr Phillips Blvd # 250",
    "sg:city":"Orlando",
    "sg:classifiers":[
        {
            "category":"Real Estate",
            "subcategory":"Real Estate Services",
            "type":"Services"
        },
        {
            "category":"Real Estate",
            "subcategory":"Real Estate Agent",
            "type":"Services"
        }
    ],
    "sg:phone":"+1 407 352 4020",
    "sg:postcode":"32819",
    "sg:province":"FL",
    "sg:tags":[
        "buyer",
        "consultant",
        "broker"
    ],
    "wof:name":"R.E. Group Of Florida",
    "wof:placetype":"venue"
},
  "geometry": {"coordinates":[-81.487968,28.451521],"type":"Point"}
}