{
  "type": "Feature",
  "properties": {
    "addr:full":"1204 NW 13th St Gainesville FL 32601",
    "addr:housenumber":"1204",
    "addr:postcode":"32601",
    "addr:street":"Nw 13Th St",
    "iso:country":"US",
    "sg:address":"1204 NW 13th St",
    "sg:city":"Gainesville",
    "sg:classifiers":[
        {
            "category":"Government",
            "subcategory":"Office",
            "type":"Public Place"
        }
    ],
    "sg:phone":"+1 352 378 8114",
    "sg:postcode":"32601",
    "sg:province":"FL",
    "sg:tags":[
        "federal",
        "affairs",
        "govt",
        "admin"
    ],
    "wof:name":"Us Veterans Affairs Dept",
    "wof:placetype":"venue"
},
  "geometry": {"coordinates":[-82.339235,29.664827],"type":"Point"}
}