{
  "type": "Feature",
  "properties": {
    "iso:country":"US",
    "sg:address":"217 Long Lake Rd",
    "sg:city":"Hawthorne",
    "sg:classifiers":[
        {
            "category":"Shopping",
            "subcategory":"News",
            "type":"Retail Goods"
        }
    ],
    "sg:phone":"+1 352 475 3088",
    "sg:postcode":"32640",
    "sg:province":"FL",
    "sg:tags":[
        "magazine"
    ],
    "wof:name":"Common Sense Press",
    "wof:placetype":"venue"
},
  "geometry": {"coordinates":[-81.98713600000001,29.6669],"type":"Point"}
}