{
  "type": "Feature",
  "properties": {
    "addr:full":"4012 Kimpton Pl Largo FL 33771",
    "addr:postcode":"4012;33771",
    "addr:street":"Kimpton Pl",
    "iso:country":"US",
    "sg:address":"4012 Kimpton Pl",
    "sg:city":"Largo",
    "sg:classifiers":[
        {
            "category":"Arts & Performance",
            "subcategory":"Theater",
            "type":"Entertainment"
        }
    ],
    "sg:phone":"+1 727 539 1580",
    "sg:postcode":"33771",
    "sg:province":"FL",
    "sg:tags":[
        "entertainer",
        "business"
    ],
    "wof:name":"A Fit Production",
    "wof:placetype":"venue"
},
  "geometry": {"coordinates":[-82.744891,27.909404],"type":"Point"}
}