{
  "type": "Feature",
  "properties": {
    "iso:country":"US",
    "sg:address":"2337 Industrial Dr",
    "sg:city":"Panama City",
    "sg:classifiers":[
        {
            "category":"Food & Beverages",
            "subcategory":"Specialty",
            "type":"Retail Goods"
        }
    ],
    "sg:phone":"+1 850 763 0100",
    "sg:postcode":"32405",
    "sg:province":"FL",
    "sg:tags":[
        "tea",
        "coffee"
    ],
    "wof:name":"Community Coffee Svc LLC",
    "wof:placetype":"venue"
},
  "geometry": {"coordinates":[-85.633967,30.187321],"type":"Point"}
}