{
  "type": "Feature",
  "properties": {
    "addr:full":"585 NW 60th Ct Miami FL 33126",
    "addr:housenumber":"585",
    "addr:postcode":"33126",
    "addr:street":"Nw 60Th Ct",
    "iso:country":"US",
    "sg:address":"585 NW 60th Ct",
    "sg:city":"Miami",
    "sg:classifiers":[
        {
            "category":"Shopping",
            "type":"Retail Goods"
        }
    ],
    "sg:phone":"+1 305 266 8940",
    "sg:postcode":"33126",
    "sg:province":"FL",
    "sg:tags":[
        "merchandise"
    ],
    "wof:name":"Ww Aquarium Co",
    "wof:placetype":"venue"
},
  "geometry": {"coordinates":[-80.29450300000001,25.777024],"type":"Point"}
}