{
  "type": "Feature",
  "properties": {
    "iso:country":"US",
    "sg:address":"8410 Front Beach Rd",
    "sg:city":"Panama City",
    "sg:classifiers":[
        {
            "category":"Professional",
            "type":"Services"
        }
    ],
    "sg:phone":"+1 850 234 2664",
    "sg:postcode":"32407",
    "sg:province":"FL",
    "wof:name":"Beach Equipment Svc",
    "wof:placetype":"venue"
},
  "geometry": {"coordinates":[-85.78049300000001,30.183784],"type":"Point"}
}