{
  "type": "Feature",
  "properties": {
    "iso:country":"US",
    "sg:address":"3281 Day Ave",
    "sg:city":"Miami",
    "sg:classifiers":[
        {
            "category":"Health Services",
            "subcategory":"Clinic",
            "type":"Services"
        },
        {
            "category":"Health Services",
            "subcategory":"Health Practitioner",
            "type":"Services"
        }
    ],
    "sg:phone":"+1 954 326 2450",
    "sg:postcode":"33133",
    "sg:province":"FL",
    "sg:tags":[
        "therapist",
        "therapy",
        "physical"
    ],
    "wof:name":"Find Therapy On-Line Corp",
    "wof:placetype":"venue"
},
  "geometry": {"coordinates":[-80.247001,25.731586],"type":"Point"}
}