{
  "type": "Feature",
  "properties": {
    "addr:full":"15203 SW 104th St Miami FL 33196",
    "addr:housenumber":"15203",
    "addr:postcode":"33196",
    "addr:street":"Sw 104Th St",
    "iso:country":"US",
    "sg:address":"15203 SW 104th St",
    "sg:city":"Miami",
    "sg:classifiers":[
        {
            "category":"Autos & Motor Vehicles",
            "subcategory":"Fuel & Gas Station",
            "type":"Retail Goods"
        },
        {
            "category":"Autos & Motor Vehicles",
            "subcategory":"Auto Supplies",
            "type":"Retail Goods"
        }
    ],
    "sg:phone":"+1 305 388 1021",
    "sg:postcode":"33196",
    "sg:province":"FL",
    "sg:tags":[
        "lube",
        "oil"
    ],
    "sg:website":"http://www.selubes.com",
    "wof:name":"Mobil Express Lube",
    "wof:placetype":"venue"
},
  "geometry": {"coordinates":[-80.442356,25.670045],"type":"Point"}
}