{
  "type": "Feature",
  "properties": {
    "addr:full":"14873 NE 20th Ave Miami FL 33181",
    "addr:housenumber":"14873",
    "addr:postcode":"33181",
    "addr:street":"Ne 20Th Ave",
    "iso:country":"US",
    "sg:address":"14873 NE 20th Ave",
    "sg:city":"Miami",
    "sg:classifiers":[
        {
            "category":"Utilities",
            "subcategory":"Cable",
            "type":"Services"
        }
    ],
    "sg:phone":"+1 305 949 8898",
    "sg:postcode":"33181",
    "sg:province":"FL",
    "sg:tags":[
        "satellite",
        "digital",
        "network",
        "telecommunication"
    ],
    "wof:name":"Turnkey Communications Inc",
    "wof:placetype":"venue"
},
  "geometry": {"coordinates":[-80.159218,25.912987],"type":"Point"}
}