{
  "type": "Feature",
  "properties": {
    "addr:full":"203 Martin Cir Royal Palm Beach FL 33411",
    "addr:housenumber":"203",
    "addr:postcode":"33411",
    "addr:street":"Martin Cir",
    "iso:country":"US",
    "sg:address":"203 Martin Cir",
    "sg:city":"Royal Palm Beach",
    "sg:classifiers":[
        {
            "category":"Building & Trades",
            "subcategory":"Construction",
            "type":"Services"
        }
    ],
    "sg:phone":"+1 561 793 8067",
    "sg:postcode":"33411",
    "sg:province":"FL",
    "sg:tags":[
        "tile",
        "dealer"
    ],
    "wof:name":"Charron Tile",
    "wof:placetype":"venue"
},
  "geometry": {"coordinates":[-80.211747,26.700309],"type":"Point"}
}