{
  "type": "Feature",
  "properties": {
    "addr:full":"1055 Saxon Blvd Orange City FL 32763",
    "addr:housenumber":"1055",
    "addr:postcode":"32763",
    "addr:street":"Saxon Blvd",
    "iso:country":"US",
    "sg:address":"1055 Saxon Blvd",
    "sg:city":"Orange City",
    "sg:classifiers":[
        {
            "category":"Health Services",
            "subcategory":"Hospital",
            "type":"Services"
        }
    ],
    "sg:phone":"+1 386 917 5230",
    "sg:postcode":"32763",
    "sg:province":"FL",
    "wof:name":"Florida Hospital Fish Memorial Daibetes Outreach",
    "wof:placetype":"venue"
},
  "geometry": {"coordinates":[-81.283897,28.911501],"type":"Point"}
}