{
  "type": "Feature",
  "properties": {
    "iso:country":"US",
    "sg:address":"6305 Chancellor Dr",
    "sg:city":"Orlando",
    "sg:classifiers":[
        {
            "category":"Manufacturing",
            "subcategory":"Printing",
            "type":"Manufacturing & Wholesale Goods"
        }
    ],
    "sg:phone":"+1 407 843 3141",
    "sg:postcode":"32809",
    "sg:province":"FL",
    "sg:tags":[
        "commercial",
        "lithographic"
    ],
    "sg:website":"www.designerspressinc.com",
    "wof:name":"Designer's Press Inc",
    "wof:placetype":"venue"
},
  "geometry": {"coordinates":[-81.41373400000001,28.467885],"type":"Point"}
}