{
  "type": "Feature",
  "properties": {
    "addr:full":"3461 66th Ave Pinellas Park FL 33781",
    "addr:housenumber":"3461",
    "addr:postcode":"33781",
    "addr:street":"66Th Ave",
    "iso:country":"US",
    "sg:address":"3461 66th Ave",
    "sg:city":"Pinellas Park",
    "sg:classifiers":[
        {
            "category":"Personal",
            "subcategory":"Beauty Salon",
            "type":"Services"
        }
    ],
    "sg:phone":"+1 813 835 4929",
    "sg:postcode":"33781",
    "sg:province":"FL",
    "sg:tags":[
        "shop",
        "equipment",
        "establishment"
    ],
    "wof:name":"Nail World",
    "wof:placetype":"venue"
},
  "geometry": {"coordinates":[-82.680798,27.832058],"type":"Point"}
}