{
  "type": "Feature",
  "properties": {
    "iso:country":"US",
    "sg:address":"1600 Algonquin Trl",
    "sg:city":"Maitland",
    "sg:classifiers":[
        {
            "category":"Real Estate",
            "subcategory":"Real Estate Services",
            "type":"Services"
        },
        {
            "category":"Banks & Credit Unions",
            "subcategory":"Financial Services",
            "type":"Services"
        }
    ],
    "sg:phone":"+1 407 599 1062",
    "sg:postcode":"32751",
    "sg:province":"FL",
    "sg:tags":[
        "loan",
        "processing"
    ],
    "wof:name":"Banks Mortgage Corp",
    "wof:placetype":"venue"
},
  "geometry": {"coordinates":[-81.35111999999999,28.62941],"type":"Point"}
}