{
  "type": "Feature",
  "properties": {
    "addr:full":"2101 NE 159th St North Miami Bch FL 33162",
    "addr:housenumber":"2101",
    "addr:postcode":"33162",
    "addr:street":"Ne 159Th St",
    "iso:country":"US",
    "sg:address":"2101 NE 159th St",
    "sg:city":"North Miami Bch",
    "sg:classifiers":[
        {
            "category":"Government",
            "subcategory":"Office",
            "type":"Public Place"
        }
    ],
    "sg:phone":"+1 305 948 2936",
    "sg:postcode":"33162",
    "sg:province":"FL",
    "sg:tags":[
        "village"
    ],
    "wof:name":"N Miami Beach Public Svc Opns",
    "wof:placetype":"venue"
},
  "geometry": {"coordinates":[-80.155919,25.922432],"type":"Point"}
}