{
  "type": "Feature",
  "properties": {
    "iso:country":"US",
    "sg:address":"1219 S East Ave",
    "sg:city":"Sarasota",
    "sg:classifiers":[
        {
            "category":"Health Services",
            "subcategory":"Doctor",
            "type":"Services"
        }
    ],
    "sg:phone":"+1 941 366 6775",
    "sg:postcode":"34239",
    "sg:province":"FL",
    "sg:tags":[
        "physician",
        "surgeon"
    ],
    "wof:name":"First Physicians Group",
    "wof:placetype":"venue"
},
  "geometry": {"coordinates":[-82.527734,27.322525],"type":"Point"}
}