{
  "type": "Feature",
  "properties": {
    "addr:full":"5718 NW 73rd Ave Tamarac FL 33321",
    "addr:housenumber":"5718",
    "addr:postcode":"33321",
    "addr:street":"Nw 73Rd Ave",
    "iso:country":"US",
    "sg:address":"5718 NW 73rd Ave",
    "sg:city":"Tamarac",
    "sg:classifiers":[
        {
            "category":"Banks & Credit Unions",
            "subcategory":"Bank",
            "type":"Services"
        }
    ],
    "sg:phone":"+1 954 771 7358",
    "sg:postcode":"33321",
    "sg:province":"FL",
    "sg:tags":[
        "financing"
    ],
    "wof:name":"American Lease Financing Inc",
    "wof:placetype":"venue"
},
  "geometry": {"coordinates":[-80.24764,26.196026],"type":"Point"}
}