{
  "type": "Feature",
  "properties": {
    "iso:country":"US",
    "sg:address":"3624 SE 1st Pl",
    "sg:city":"Cape Coral",
    "sg:classifiers":[
        {
            "category":"Recreation",
            "subcategory":"Arcade",
            "type":"Entertainment"
        }
    ],
    "sg:phone":"+1 239 540 4188",
    "sg:postcode":"33904",
    "sg:province":"FL",
    "sg:tags":[
        "device",
        "operator",
        "amusement"
    ],
    "wof:name":"ICM & G Corporation",
    "wof:placetype":"venue"
},
  "geometry": {"coordinates":[-81.971098,26.585586],"type":"Point"}
}