{
  "type": "Feature",
  "properties": {
    "iso:country":"US",
    "sg:address":"8921 SW 25th St",
    "sg:city":"Miami",
    "sg:classifiers":[
        {
            "category":"Shopping",
            "type":"Retail Goods"
        }
    ],
    "sg:phone":"+1 305 559 0132",
    "sg:postcode":"33165",
    "sg:province":"FL",
    "sg:tags":[
        "merchandise"
    ],
    "wof:name":"Franmart",
    "wof:placetype":"venue"
},
  "geometry": {"coordinates":[-80.34128800000001,25.746405],"type":"Point"}
}