{
  "type": "Feature",
  "properties": {
    "iso:country":"US",
    "sg:address":"492 New Hope Dr",
    "sg:city":"Altamonte Springs",
    "sg:classifiers":[
        {
            "category":"Professional",
            "subcategory":"Business Services",
            "type":"Services"
        }
    ],
    "sg:phone":"+1 407 869 0500",
    "sg:postcode":"32714",
    "sg:province":"FL",
    "wof:name":"Southern Eqp & Appraisal Co",
    "wof:placetype":"venue"
},
  "geometry": {"coordinates":[-81.400893,28.673116],"type":"Point"}
}