{
  "type": "Feature",
  "properties": {
    "iso:country":"US",
    "sg:address":"3850 NW 114 Ave",
    "sg:city":"Miami",
    "sg:classifiers":[
        {
            "category":"Place Of Worship",
            "subcategory":"Temple",
            "type":"Public Place"
        }
    ],
    "sg:postcode":"33178",
    "sg:province":"FL",
    "sg:tags":[
        "hindu"
    ],
    "wof:name":"Sai Baba Temple",
    "wof:placetype":"venue"
},
  "geometry": {"coordinates":[-80.381835,25.809423],"type":"Point"}
}