{
  "type": "Feature",
  "properties": {
    "iso:country":"US",
    "sg:address":"224 Flamingo Dr",
    "sg:city":"Sanford",
    "sg:classifiers":[
        {
            "category":"Manufacturing",
            "subcategory":"Chemicals & Compounds",
            "type":"Manufacturing & Wholesale Goods"
        }
    ],
    "sg:phone":"+1 407 617 3430",
    "sg:postcode":"32773",
    "sg:province":"FL",
    "sg:tags":[
        "product",
        "mfg"
    ],
    "wof:name":"Stain Masters",
    "wof:placetype":"venue"
},
  "geometry": {"coordinates":[-81.28712899999999,28.746565],"type":"Point"}
}