{
  "type": "Feature",
  "properties": {
    "addr:full":"947 Dixon Blvd Cocoa FL 32922",
    "addr:housenumber":"947",
    "addr:postcode":"32922",
    "addr:street":"Dixon Blvd",
    "iso:country":"US",
    "sg:address":"947 Dixon Blvd",
    "sg:city":"Cocoa",
    "sg:classifiers":[
        {
            "category":"Food & Beverages",
            "subcategory":"Groceries & Convenience Stores",
            "type":"Retail Goods"
        }
    ],
    "sg:phone":"+1 321 636 5317",
    "sg:postcode":"32922",
    "sg:province":"FL",
    "wof:name":"7-Eleven",
    "wof:placetype":"venue"
},
  "geometry": {"coordinates":[-80.740899,28.375197],"type":"Point"}
}