{
  "type": "Feature",
  "properties": {
    "addr:full":"1376 26th Ave Vero Beach FL 32960",
    "addr:housenumber":"1376",
    "addr:postcode":"32960",
    "addr:street":"26Th Ave",
    "iso:country":"US",
    "sg:address":"1376 26th Ave",
    "sg:city":"Vero Beach",
    "sg:classifiers":[
        {
            "category":"Shopping",
            "subcategory":"Clothing, Apparel, & Fashions",
            "type":"Retail Goods"
        }
    ],
    "sg:phone":"+1 772 567 4930",
    "sg:postcode":"32960",
    "sg:province":"FL",
    "wof:name":"Alterations More By Charlotte",
    "wof:placetype":"venue"
},
  "geometry": {"coordinates":[-80.41231500000001,27.626068],"type":"Point"}
}