{
  "type": "Feature",
  "properties": {
    "iso:country":"US",
    "sg:address":"5749 Main St",
    "sg:city":"New Port Richey",
    "sg:classifiers":[
        {
            "category":"Professional",
            "subcategory":"Advertising",
            "type":"Services"
        }
    ],
    "sg:phone":"+1 727 815 3700",
    "sg:postcode":"34652",
    "sg:province":"FL",
    "wof:name":"Smith's Great Escapes Intl",
    "wof:placetype":"venue"
},
  "geometry": {"coordinates":[-82.71901699999999,28.250301],"type":"Point"}
}