{
  "type": "Feature",
  "properties": {
    "iso:country":"US",
    "sg:address":"3020 SW 38th Ave",
    "sg:city":"Miami",
    "sg:classifiers":[
        {
            "category":"Manufacturing",
            "subcategory":"Metals",
            "type":"Manufacturing & Wholesale Goods"
        },
        {
            "category":"Building & Trades",
            "subcategory":"Plumbing",
            "type":"Services"
        }
    ],
    "sg:phone":"+1 305 446 0166",
    "sg:postcode":"33146",
    "sg:province":"FL",
    "sg:tags":[
        "plate",
        "sheet",
        "mfg",
        "work",
        "fabricated",
        "contractor",
        "metalwork"
    ],
    "sg:website":"http://www.doudney.com",
    "wof:name":"Doudney Sheet Metal Works",
    "wof:placetype":"venue"
},
  "geometry": {"coordinates":[-80.256001,25.734732],"type":"Point"}
}