{
  "type": "Feature",
  "properties": {
    "iso:country":"US",
    "sg:address":"2310 State Hwy 16",
    "sg:city":"St Augustine",
    "sg:classifiers":[
        {
            "category":"Travel",
            "subcategory":"Hotels & Motels",
            "type":"Entertainment"
        }
    ],
    "sg:phone":"+1 904 823 8636",
    "sg:postcode":"32084",
    "sg:province":"FL",
    "wof:name":"Holiday Inn Express St Agstne",
    "wof:placetype":"venue"
},
  "geometry": {"coordinates":[-81.404746,29.915882],"type":"Point"}
}