{
  "type": "Feature",
  "properties": {
    "iso:country":"US",
    "sg:address":"4540 Santa Cruz Ct",
    "sg:city":"Orlando",
    "sg:classifiers":[
        {
            "category":"Shopping",
            "subcategory":"Hobbies, Toys, & Games",
            "type":"Retail Goods"
        }
    ],
    "sg:phone":"+1 407 298 2306",
    "sg:postcode":"32808",
    "sg:province":"FL",
    "sg:tags":[
        "craft",
        "gallery"
    ],
    "wof:name":"Kathleen J Stephens",
    "wof:placetype":"venue"
},
  "geometry": {"coordinates":[-81.44110499999999,28.570476],"type":"Point"}
}