{
  "type": "Feature",
  "properties": {
    "iso:country":"US",
    "sg:address":"3001 E Osborne Ave",
    "sg:city":"Tampa",
    "sg:phone":"+1 813 239 1432",
    "sg:postcode":"33610",
    "sg:province":"FL",
    "wof:name":"Terri Lee Cafe",
    "wof:placetype":"venue"
},
  "geometry": {"coordinates":[-82.42643,27.98876],"type":"Point"}
}