{
  "type": "Feature",
  "properties": {
    "addr:full":"515 E Altamonte Dr Altamonte Springs FL 32701",
    "addr:housenumber":"515",
    "addr:postcode":"32701",
    "addr:street":"E Altamonte Dr",
    "iso:country":"US",
    "sg:address":"515 E Altamonte Dr",
    "sg:city":"Altamonte Springs",
    "sg:classifiers":[
        {
            "category":"Shopping",
            "subcategory":"Stationery & Office Supplies",
            "type":"Retail Goods"
        },
        {
            "category":"Wholesale",
            "subcategory":"Computers",
            "type":"Manufacturing & Wholesale Goods"
        }
    ],
    "sg:phone":"+1 407 830 6100",
    "sg:postcode":"32701",
    "sg:province":"FL",
    "sg:tags":[
        "equipment"
    ],
    "sg:website":"www.officedepot.com",
    "wof:name":"Office Depot",
    "wof:placetype":"venue"
},
  "geometry": {"coordinates":[-81.372803,28.6639],"type":"Point"}
}