{
  "type": "Feature",
  "properties": {
    "addr:full":"2060 Dobbs Rd St Augustine FL 32086",
    "addr:housenumber":"2060",
    "addr:postcode":"32086",
    "addr:street":"Dobbs Rd St",
    "iso:country":"US",
    "sg:address":"2060 Dobbs Rd",
    "sg:city":"St Augustine",
    "sg:classifiers":[
        {
            "category":"Retail",
            "subcategory":"Auto Repair",
            "type":"Services"
        }
    ],
    "sg:phone":"+1 904 829 5259",
    "sg:postcode":"32086",
    "sg:province":"FL",
    "sg:tags":[
        "repairing",
        "automobile",
        "automotive"
    ],
    "wof:name":"Jerry's MB",
    "wof:placetype":"venue"
},
  "geometry": {"coordinates":[-81.33470699999999,29.865432],"type":"Point"}
}