{
  "type": "Feature",
  "properties": {
    "iso:country":"US",
    "sg:address":"13926 Landstar Blvd",
    "sg:city":"Orlando",
    "sg:classifiers":[
        {
            "category":"Retail",
            "subcategory":"Laundry & Dry Cleaning",
            "type":"Services"
        }
    ],
    "sg:phone":"+1 407 854 5578",
    "sg:postcode":"32824",
    "sg:province":"FL",
    "sg:tags":[
        "cleaners"
    ],
    "wof:name":"Landstar Cleaners",
    "wof:placetype":"venue"
},
  "geometry": {"coordinates":[-81.361306,28.353376],"type":"Point"}
}