{
  "type": "Feature",
  "properties": {
    "addr:full":"1333 Santa Barbara Blvd Cape Coral FL 33991",
    "addr:housenumber":"1333",
    "addr:postcode":"33991",
    "addr:street":"Santa Barbara Blvd",
    "iso:country":"US",
    "sg:address":"1333 Santa Barbara Blvd",
    "sg:city":"Cape Coral",
    "sg:classifiers":[
        {
            "category":"Professional",
            "type":"Services"
        }
    ],
    "sg:phone":"+1 239 574 2971",
    "sg:postcode":"33991",
    "sg:province":"FL",
    "sg:tags":[
        "establishment"
    ],
    "wof:name":"Rehabworks",
    "wof:placetype":"venue"
},
  "geometry": {"coordinates":[-81.974057,26.628224],"type":"Point"}
}