{
  "type": "Feature",
  "properties": {
    "addr:full":"105 W Main Ave Defuniak Springs FL 32435",
    "addr:housenumber":"105",
    "addr:postcode":"32435",
    "addr:street":"W Main Ave",
    "iso:country":"US",
    "sg:address":"105 W Main Ave",
    "sg:city":"Defuniak Springs",
    "sg:classifiers":[
        {
            "category":"Social Services",
            "type":"Services"
        }
    ],
    "sg:phone":"+1 850 892 4718",
    "sg:postcode":"32435",
    "sg:province":"FL",
    "sg:tags":[
        "senior",
        "citizen"
    ],
    "wof:name":"Walton Council On Aging",
    "wof:placetype":"venue"
},
  "geometry": {"coordinates":[-86.11790000000001,30.72022],"type":"Point"}
}