{
  "type": "Feature",
  "properties": {
    "addr:full":"3920 W Navy Blvd Pensacola FL 32507",
    "addr:housenumber":"3920",
    "addr:postcode":"32507",
    "addr:street":"W Navy Blvd",
    "iso:country":"US",
    "sg:address":"3920 W Navy Blvd",
    "sg:city":"Pensacola",
    "sg:classifiers":[
        {
            "category":"Wholesale",
            "subcategory":"Electrical",
            "type":"Manufacturing & Wholesale Goods"
        }
    ],
    "sg:phone":"+1 850 458 5646",
    "sg:postcode":"32507",
    "sg:province":"FL",
    "sg:tags":[
        "refuse",
        "system"
    ],
    "wof:name":"Red River Service Corp",
    "wof:placetype":"venue"
},
  "geometry": {"coordinates":[-87.272268,30.408131],"type":"Point"}
}