{
  "type": "Feature",
  "properties": {
    "iso:country":"US",
    "sg:address":"2137 Luana Dr E",
    "sg:city":"Jacksonville",
    "sg:classifiers":[
        {
            "category":"Professional",
            "type":"Services"
        }
    ],
    "sg:phone":"+1 904 645 8657",
    "sg:postcode":"32246",
    "sg:province":"FL",
    "sg:tags":[
        "wholesale"
    ],
    "wof:name":"Browns Government Contg Svcs",
    "wof:placetype":"venue"
},
  "geometry": {"coordinates":[-81.515045,30.311996],"type":"Point"}
}