{
  "type": "Feature",
  "properties": {
    "addr:full":"2944 University Blvd W Jacksonville FL 32217",
    "addr:housenumber":"2944",
    "addr:postcode":"32217",
    "addr:street":"University Blvd W",
    "iso:country":"US",
    "sg:address":"2944 University Blvd W",
    "sg:city":"Jacksonville",
    "sg:classifiers":[
        {
            "category":"Wholesale",
            "subcategory":"Home Furnishings",
            "type":"Manufacturing & Wholesale Goods"
        }
    ],
    "sg:phone":"+1 904 731 9990",
    "sg:postcode":"32217",
    "sg:province":"FL",
    "wof:name":"Fine Fabricators",
    "wof:placetype":"venue"
},
  "geometry": {"coordinates":[-81.62887000000001,30.260859],"type":"Point"}
}