{
  "type": "Feature",
  "properties": {
    "addr:full":"5878 Hwy 231 Campbellton FL 32426",
    "addr:housenumber":"5878",
    "addr:postcode":"32426",
    "addr:street":"Hwy 231",
    "iso:country":"US",
    "sg:address":"5878 Hwy 231",
    "sg:city":"Campbellton",
    "sg:classifiers":[
        {
            "category":"Food & Beverages",
            "subcategory":"Fruits & Vegetables",
            "type":"Retail Goods"
        }
    ],
    "sg:phone":"+1 850 263 8800",
    "sg:postcode":"32426",
    "sg:province":"FL",
    "sg:tags":[
        "produce"
    ],
    "wof:name":"Davis & Davis Convenience",
    "wof:placetype":"venue"
},
  "geometry": {"coordinates":[-85.40788000000001,30.99283],"type":"Point"}
}