{
  "type": "Feature",
  "properties": {
    "iso:country":"US",
    "sg:address":"34 Industrial St NW",
    "sg:city":"Fort Walton Bch",
    "sg:classifiers":[
        {
            "category":"Freight",
            "type":"Transportation"
        }
    ],
    "sg:phone":"+1 850 243 6125",
    "sg:postcode":"32548",
    "sg:province":"FL",
    "sg:tags":[
        "mover"
    ],
    "wof:name":"Campbell Moving & Storage Co",
    "wof:placetype":"venue"
},
  "geometry": {"coordinates":[-86.616319,30.415823],"type":"Point"}
}