{
  "type": "Feature",
  "properties": {
    "addr:full":"3661 NW 48th Ter Miami FL 33142",
    "addr:housenumber":"3661",
    "addr:postcode":"33142",
    "addr:street":"Nw 48Th Ter",
    "iso:country":"US",
    "sg:address":"3661 NW 48th Ter",
    "sg:city":"Miami",
    "sg:classifiers":[
        {
            "category":"Building & Trades",
            "subcategory":"Construction",
            "type":"Services"
        }
    ],
    "sg:phone":"+1 305 634 5194",
    "sg:postcode":"33142",
    "sg:province":"FL",
    "sg:tags":[
        "roofing",
        "contractor"
    ],
    "wof:name":"Aleluya Roofing Company",
    "wof:placetype":"venue"
},
  "geometry": {"coordinates":[-80.255196,25.818331],"type":"Point"}
}