{
  "type": "Feature",
  "properties": {
    "iso:country":"US",
    "sg:address":"1005 S Florida Ave",
    "sg:city":"Inverness",
    "sg:classifiers":[
        {
            "category":"Building & Trades",
            "subcategory":"Construction",
            "type":"Services"
        }
    ],
    "sg:phone":"+1 352 637 1904",
    "sg:postcode":"34450",
    "sg:province":"FL",
    "sg:tags":[
        "contractor"
    ],
    "sg:website":"www.emlpools.sanjuanpools.com",
    "wof:name":"Easy Modern Living Inc",
    "wof:placetype":"venue"
},
  "geometry": {"coordinates":[-82.316495,28.819342],"type":"Point"}
}