{
  "type": "Feature",
  "properties": {
    "addr:full":"3897 Talah Dr Palm Harbor FL 34684",
    "addr:housenumber":"3897",
    "addr:postcode":"34684",
    "addr:street":"Talah Dr",
    "iso:country":"US",
    "sg:address":"3897 Talah Dr",
    "sg:city":"Palm Harbor",
    "sg:classifiers":[
        {
            "category":"Retail",
            "subcategory":"Car Wash",
            "type":"Services"
        }
    ],
    "sg:phone":"+1 727 784 5687",
    "sg:postcode":"34684",
    "sg:province":"FL",
    "sg:tags":[
        "carwash"
    ],
    "wof:name":"Causeway Beach Wash",
    "wof:placetype":"venue"
},
  "geometry": {"coordinates":[-82.714404,28.081114],"type":"Point"}
}