{
  "type": "Feature",
  "properties": {
    "addr:full":"1859 N Pine Island Rd Fort Lauderdale FL 33322",
    "addr:housenumber":"1859",
    "addr:postcode":"33322",
    "addr:street":"N Pine Island Rd",
    "iso:country":"US",
    "sg:address":"1859 N Pine Island Rd",
    "sg:city":"Fort Lauderdale",
    "sg:classifiers":[
        {
            "category":"Building & Trades",
            "subcategory":"Pest Control",
            "type":"Services"
        }
    ],
    "sg:phone":"+1 954 472 3113",
    "sg:postcode":"33322",
    "sg:province":"FL",
    "wof:name":"Bug Solutions",
    "wof:placetype":"venue"
},
  "geometry": {"coordinates":[-80.269273,26.144773],"type":"Point"}
}