{
  "type": "Feature",
  "properties": {
    "iso:country":"US",
    "sg:address":"4141 SW 6th St",
    "sg:city":"Coral Gables",
    "sg:classifiers":[
        {
            "category":"Health Services",
            "subcategory":"Doctor",
            "type":"Services"
        }
    ],
    "sg:phone":"+1 305 443 5031",
    "sg:postcode":"33134",
    "sg:province":"FL",
    "wof:name":"Fraga Lazaro MD PA",
    "wof:placetype":"venue"
},
  "geometry": {"coordinates":[-80.263199,25.7658],"type":"Point"}
}