{
  "type": "Feature",
  "properties": {
    "iso:country":"US",
    "sg:address":"248 Coral Dr",
    "sg:city":"Cape Canaveral",
    "sg:classifiers":[
        {
            "category":"Professional",
            "subcategory":"Accounting & Tax Preparation",
            "type":"Services"
        }
    ],
    "sg:phone":"+1 321 783 6620",
    "sg:postcode":"32920",
    "sg:province":"FL",
    "sg:tags":[
        "accountant"
    ],
    "wof:name":"M K Bookeeping Service",
    "wof:placetype":"venue"
},
  "geometry": {"coordinates":[-80.600959,28.399902],"type":"Point"}
}