{
  "type": "Feature",
  "properties": {
    "iso:country":"US",
    "sg:address":"910 Britt Ct",
    "sg:city":"Altamonte Spgs",
    "sg:classifiers":[
        {
            "category":"Shopping",
            "subcategory":"Clothing, Apparel, & Fashions",
            "type":"Retail Goods"
        }
    ],
    "sg:phone":"+1 407 831 7673",
    "sg:postcode":"32701",
    "sg:province":"FL",
    "sg:tags":[
        "alteration"
    ],
    "wof:name":"Rose Cleaners & Alterations",
    "wof:placetype":"venue"
},
  "geometry": {"coordinates":[-81.350836,28.676636],"type":"Point"}
}