{
  "type": "Feature",
  "properties": {
    "iso:country":"US",
    "sg:address":"138 N 11th St",
    "sg:city":"Haines City",
    "sg:classifiers":[
        {
            "category":"Government",
            "subcategory":"Fire Station",
            "type":"Public Place"
        }
    ],
    "sg:phone":"+1 863 421 3611",
    "sg:postcode":"33844",
    "sg:province":"FL",
    "sg:tags":[
        "department"
    ],
    "wof:name":"Haines City Fire Dept",
    "wof:placetype":"venue"
},
  "geometry": {"coordinates":[-81.622674,28.108691],"type":"Point"}
}