{
  "type": "Feature",
  "properties": {
    "iso:country":"US",
    "sg:address":"100 Lovers Ln",
    "sg:city":"Fort Myers Beach",
    "sg:classifiers":[
        {
            "category":"Real Estate",
            "subcategory":"Real Estate Agent",
            "type":"Services"
        }
    ],
    "sg:phone":"+1 239 765 9699",
    "sg:postcode":"33931",
    "sg:province":"FL",
    "wof:name":"Florida Gulf Investment",
    "wof:placetype":"venue"
},
  "geometry": {"coordinates":[-81.937848,26.447941],"type":"Point"}
}