{
  "type": "Feature",
  "properties": {
    "iso:country":"US",
    "sg:address":"2405 Orangedale Rd",
    "sg:city":"Lakeland",
    "sg:classifiers":[
        {
            "category":"Building & Trades",
            "subcategory":"Landscaping Services",
            "type":"Services"
        }
    ],
    "sg:phone":"+1 863 984 8710",
    "sg:postcode":"33809",
    "sg:province":"FL",
    "wof:name":"Jack E Williams",
    "wof:placetype":"venue"
},
  "geometry": {"coordinates":[-81.908175,28.152349],"type":"Point"}
}