{
  "type": "Feature",
  "properties": {
    "iso:country":"US",
    "sg:address":"1310 SW 67th Way",
    "sg:city":"Hollywood",
    "sg:classifiers":[
        {
            "category":"Wholesale",
            "subcategory":"Farm Supplies",
            "type":"Manufacturing & Wholesale Goods"
        }
    ],
    "sg:phone":"+1 954 270 8795",
    "sg:postcode":"33023",
    "sg:province":"FL",
    "sg:tags":[
        "raw",
        "product",
        "material"
    ],
    "wof:name":"A-1 Distributors Inc",
    "wof:placetype":"venue"
},
  "geometry": {"coordinates":[-80.222555,25.997905],"type":"Point"}
}