{
  "type": "Feature",
  "properties": {
    "addr:full":"739 Randolph St Eastpoint FL 32328",
    "addr:housenumber":"739",
    "addr:postcode":"32328",
    "addr:street":"Randolph St",
    "iso:country":"US",
    "sg:address":"739 Randolph St",
    "sg:city":"Eastpoint",
    "sg:classifiers":[
        {
            "category":"Building & Trades",
            "subcategory":"Construction",
            "type":"Services"
        }
    ],
    "sg:phone":"+1 850 927 3038",
    "sg:postcode":"32328",
    "sg:province":"FL",
    "sg:tags":[
        "carpentry",
        "contractor"
    ],
    "wof:name":"Hogshark Carpentry Inc",
    "wof:placetype":"venue"
},
  "geometry": {"coordinates":[-84.87952799999999,29.660458],"type":"Point"}
}