{
  "type": "Feature",
  "properties": {
    "iso:country":"US",
    "sg:address":"3170 Egremont Dr",
    "sg:city":"West Palm Beach",
    "sg:classifiers":[
        {
            "category":"Building & Trades",
            "subcategory":"Landscaping Services",
            "type":"Services"
        }
    ],
    "sg:phone":"+1 561 723 8881",
    "sg:postcode":"33406",
    "sg:province":"FL",
    "sg:tags":[
        "lawn",
        "maintenance",
        "grounds"
    ],
    "wof:name":"Mario Gomez Lawn Svc",
    "wof:placetype":"venue"
},
  "geometry": {"coordinates":[-80.091302,26.661174],"type":"Point"}
}