{
  "type": "Feature",
  "properties": {
    "addr:full":"4187 Dairy Ct Daytona Beach FL 32127",
    "addr:housenumber":"4187",
    "addr:postcode":"32127",
    "addr:street":"Dairy Ct",
    "iso:country":"US",
    "sg:address":"4187 Dairy Ct",
    "sg:city":"Daytona Beach",
    "sg:classifiers":[
        {
            "category":"Home & Garden",
            "subcategory":"Building Materials",
            "type":"Retail Goods"
        }
    ],
    "sg:phone":"+1 386 760 4344",
    "sg:postcode":"32127",
    "sg:province":"FL",
    "wof:name":"Dovi Aluminum Window Services",
    "wof:placetype":"venue"
},
  "geometry": {"coordinates":[-80.992165,29.136526],"type":"Point"}
}