{
  "type": "Feature",
  "properties": {
    "iso:country":"US",
    "sg:address":"410 Palmetto Pl",
    "sg:city":"Indialantic",
    "sg:classifiers":[
        {
            "category":"Professional",
            "subcategory":"Business Services",
            "type":"Services"
        }
    ],
    "sg:phone":"+1 321 676 1769",
    "sg:postcode":"32903",
    "sg:province":"FL",
    "sg:tags":[
        "interior",
        "full",
        "design"
    ],
    "wof:name":"Porter Baxter Interior Design",
    "wof:placetype":"venue"
},
  "geometry": {"coordinates":[-80.573714,28.08001],"type":"Point"}
}