{
  "type": "Feature",
  "properties": {
    "iso:country":"US",
    "sg:address":"664 Oaks Creek Ct",
    "sg:city":"Osprey",
    "sg:classifiers":[
        {
            "category":"Banks & Credit Unions",
            "subcategory":"Financial Services",
            "type":"Services"
        }
    ],
    "sg:phone":"+1 941 966 2793",
    "sg:postcode":"34229",
    "sg:province":"FL",
    "sg:tags":[
        "trust",
        "management"
    ],
    "wof:name":"Ann M Gamble Trust",
    "wof:placetype":"venue"
},
  "geometry": {"coordinates":[-82.47632400000001,27.202621],"type":"Point"}
}