{
  "type": "Feature",
  "properties": {
    "iso:country":"US",
    "sg:address":"1003 63rd Ave E",
    "sg:city":"Bradenton",
    "sg:classifiers":[
        {
            "category":"Organizations",
            "subcategory":"Religious Organization",
            "type":"Services"
        }
    ],
    "sg:phone":"+1 941 755 6624",
    "sg:postcode":"34203",
    "sg:province":"FL",
    "sg:tags":[
        "church",
        "care",
        "day",
        "child"
    ],
    "wof:name":"Church of God Day Care",
    "wof:placetype":"venue"
},
  "geometry": {"coordinates":[-82.553608,27.429363],"type":"Point"}
}