{
  "type": "Feature",
  "properties": {
    "addr:full":"5360 Ehrlich Rd Tampa FL 33624",
    "addr:postcode":"5360;33624",
    "addr:street":"Ehrlich Rd",
    "iso:country":"US",
    "sg:address":"5360 Ehrlich Rd",
    "sg:city":"Tampa",
    "sg:classifiers":[
        {
            "category":"Shopping",
            "subcategory":"Clothing, Apparel, & Fashions",
            "type":"Retail Goods"
        }
    ],
    "sg:phone":"+1 813 908 9791",
    "sg:postcode":"33624",
    "sg:province":"FL",
    "sg:tags":[
        "family",
        "store"
    ],
    "wof:name":"Bealls Outlet 348",
    "wof:placetype":"venue"
},
  "geometry": {"coordinates":[-82.539058,28.084596],"type":"Point"}
}