{
  "type": "Feature",
  "properties": {
    "iso:country":"US",
    "sg:address":"755 Forsyth St",
    "sg:city":"Boca Raton",
    "sg:classifiers":[
        {
            "category":"Professional",
            "subcategory":"Business Services",
            "type":"Services"
        }
    ],
    "sg:phone":"+1 561 997 8866",
    "sg:postcode":"33487",
    "sg:province":"FL",
    "sg:tags":[
        "consultant",
        "printing",
        "broker"
    ],
    "wof:name":"International Travel Media",
    "wof:placetype":"venue"
},
  "geometry": {"coordinates":[-80.070466,26.405691],"type":"Point"}
}