{
  "type": "Feature",
  "properties": {
    "addr:full":"13161 56th Ct Unit 508 Clearwater FL 33760",
    "addr:housenumber":"13161;508",
    "addr:postcode":"33760",
    "addr:street":"56Th Ct Unit",
    "iso:country":"US",
    "sg:address":"13161 56th Ct Unit 508",
    "sg:city":"Clearwater",
    "sg:classifiers":[
        {
            "category":"Wholesale",
            "subcategory":"Painting Supplies",
            "type":"Manufacturing & Wholesale Goods"
        },
        {
            "category":"Shopping",
            "subcategory":"Crafts & Fabrics",
            "type":"Retail Goods"
        }
    ],
    "sg:phone":"+1 727 573 1991",
    "sg:postcode":"33760",
    "sg:province":"FL",
    "sg:tags":[
        "goods-wholesale",
        "art",
        "manufacturer"
    ],
    "wof:name":"Media Art",
    "wof:placetype":"venue"
},
  "geometry": {"coordinates":[-82.71052400000001,27.89151],"type":"Point"}
}