{
  "type": "Feature",
  "properties": {
    "iso:country":"US",
    "sg:address":"2135 NW 1st Ave",
    "sg:city":"Miami",
    "sg:classifiers":[
        {
            "category":"Arts & Performance",
            "subcategory":"Arts Center",
            "type":"Entertainment"
        }
    ],
    "sg:postcode":"33127",
    "sg:province":"FL",
    "sg:website":"www.genart.org/miami",
    "wof:name":"Gen Art Vanguard",
    "wof:placetype":"venue"
},
  "geometry": {"coordinates":[-80.196506,25.797427],"type":"Point"}
}