{
  "type": "Feature",
  "properties": {
    "iso:country":"US",
    "sg:address":"121 Phinney Trailer Park Rd",
    "sg:city":"Palatka",
    "sg:classifiers":[
        {
            "category":"Building & Trades",
            "subcategory":"Plumbing",
            "type":"Services"
        }
    ],
    "sg:phone":"+1 386 328 7455",
    "sg:postcode":"32177",
    "sg:province":"FL",
    "sg:tags":[
        "conditioning",
        "air",
        "system",
        "contractor"
    ],
    "wof:name":"All Seasons Heating & AC",
    "wof:placetype":"venue"
},
  "geometry": {"coordinates":[-81.67277300000001,29.641943],"type":"Point"}
}