{
  "type": "Feature",
  "properties": {
    "addr:full":"1227 SE 9th Ter Cape Coral FL 33990",
    "addr:housenumber":"1227",
    "addr:postcode":"33990",
    "addr:street":"Se 9Th Ter",
    "iso:country":"US",
    "sg:address":"1227 SE 9th Ter",
    "sg:city":"Cape Coral",
    "sg:classifiers":[
        {
            "category":"Building & Trades",
            "subcategory":"Construction",
            "type":"Services"
        }
    ],
    "sg:phone":"+1 239 458 1840",
    "sg:postcode":"33990",
    "sg:province":"FL",
    "sg:tags":[
        "contractor"
    ],
    "wof:name":"Gulf Coast Rebath",
    "wof:placetype":"venue"
},
  "geometry": {"coordinates":[-81.947429,26.63512],"type":"Point"}
}