{
  "type": "Feature",
  "properties": {
    "addr:full":"6090 SW 109th St Miami FL 33156",
    "addr:housenumber":"6090",
    "addr:postcode":"33156",
    "addr:street":"Sw 109Th St",
    "iso:country":"US",
    "sg:address":"6090 SW 109th St",
    "sg:city":"Miami",
    "sg:classifiers":[
        {
            "category":"Professional",
            "subcategory":"Management & Consulting",
            "type":"Services"
        }
    ],
    "sg:phone":"+1 305 284 9860",
    "sg:postcode":"33156",
    "sg:province":"FL",
    "sg:tags":[
        "business"
    ],
    "wof:name":"H A Klukas Consulnt",
    "wof:placetype":"venue"
},
  "geometry": {"coordinates":[-80.29159199999999,25.669714],"type":"Point"}
}