{
  "type": "Feature",
  "properties": {
    "iso:country":"US",
    "sg:address":"2275 S Federal Hwy",
    "sg:city":"Delray Beach",
    "sg:classifiers":[
        {
            "category":"Personal",
            "subcategory":"Beauty Salon",
            "type":"Services"
        }
    ],
    "sg:phone":"+1 561 272 1377",
    "sg:postcode":"33483",
    "sg:province":"FL",
    "sg:tags":[
        "shop"
    ],
    "wof:name":"Refuge For Hair",
    "wof:placetype":"venue"
},
  "geometry": {"coordinates":[-80.07199799999999,26.433804],"type":"Point"}
}