{
  "type": "Feature",
  "properties": {
    "iso:country":"US",
    "sg:address":"11311 SW 25th Ct",
    "sg:city":"Fort Lauderdale",
    "sg:classifiers":[
        {
            "category":"Personal",
            "type":"Services"
        }
    ],
    "sg:phone":"+1 954 424 2024",
    "sg:postcode":"33325",
    "sg:province":"FL",
    "wof:name":"Cory Properties Inc",
    "wof:placetype":"venue"
},
  "geometry": {"coordinates":[-80.299902,26.088548],"type":"Point"}
}