{
  "type": "Feature",
  "properties": {
    "addr:full":"304 Poinciana Dr Gulf Breeze FL 32561",
    "addr:housenumber":"304",
    "addr:postcode":"32561",
    "addr:street":"Poinciana Dr",
    "iso:country":"US",
    "sg:address":"304 Poinciana Dr",
    "sg:city":"Gulf Breeze",
    "sg:classifiers":[
        {
            "category":"Bars & Pubs",
            "type":"Food & Drink"
        }
    ],
    "sg:phone":"+1 850 916 9808",
    "sg:postcode":"32561",
    "sg:province":"FL",
    "sg:tags":[
        "drinking"
    ],
    "wof:name":"Paddy OLearys Irish Pub",
    "wof:placetype":"venue"
},
  "geometry": {"coordinates":[-87.174881,30.360203],"type":"Point"}
}