{
  "type": "Feature",
  "properties": {
    "addr:full":"3111 Mahan Dr Tallahassee FL 32308",
    "addr:housenumber":"3111",
    "addr:postcode":"32308",
    "addr:street":"Mahan Dr",
    "iso:country":"US",
    "sg:address":"3111 Mahan Dr",
    "sg:city":"Tallahassee",
    "sg:classifiers":[
        {
            "category":"Shopping",
            "subcategory":"Hobbies, Toys, & Games",
            "type":"Retail Goods"
        }
    ],
    "sg:phone":"+1 850 671 2030",
    "sg:postcode":"32308",
    "sg:province":"FL",
    "sg:tags":[
        "model",
        "supply"
    ],
    "wof:name":"Hobbytown USA",
    "wof:placetype":"venue"
},
  "geometry": {"coordinates":[-84.226101,30.460671],"type":"Point"}
}