{
  "type": "Feature",
  "properties": {
    "addr:full":"12936 SE Suzanne Dr Hobe Sound FL 33455",
    "addr:postcode":"12936;33455",
    "addr:street":"Se Suzanne Dr",
    "iso:country":"US",
    "sg:address":"12936 SE Suzanne Dr",
    "sg:city":"Hobe Sound",
    "sg:classifiers":[
        {
            "category":"Retail",
            "subcategory":"Repair Shop",
            "type":"Services"
        }
    ],
    "sg:phone":"+1 772 546 6653",
    "sg:postcode":"33455",
    "sg:province":"FL",
    "sg:tags":[
        "installs",
        "industrial",
        "machinery"
    ],
    "wof:name":"Specialty Machine Repair Inc",
    "wof:placetype":"venue"
},
  "geometry": {"coordinates":[-80.153228,27.047552],"type":"Point"}
}