{
  "type": "Feature",
  "properties": {
    "iso:country":"US",
    "sg:address":"9455 Collins Ave",
    "sg:city":"Surfside",
    "sg:classifiers":[
        {
            "category":"Professional",
            "subcategory":"Management & Consulting",
            "type":"Services"
        }
    ],
    "sg:phone":"+1 305 865 9064",
    "sg:postcode":"33154",
    "sg:province":"FL",
    "sg:tags":[
        "consultant",
        "automation"
    ],
    "wof:name":"General Automation Inc",
    "wof:placetype":"venue"
},
  "geometry": {"coordinates":[-80.122412,25.884277],"type":"Point"}
}