{
  "type": "Feature",
  "properties": {
    "iso:country":"US",
    "sg:address":"7114 60th Way N",
    "sg:city":"Pinellas Park",
    "sg:classifiers":[
        {
            "category":"Building & Trades",
            "subcategory":"Landscaping Services",
            "type":"Services"
        }
    ],
    "sg:phone":"+1 727 545 2002",
    "sg:postcode":"33781",
    "sg:province":"FL",
    "wof:name":"Perfect Cut Lawn Service",
    "wof:placetype":"venue"
},
  "geometry": {"coordinates":[-82.717106,27.837783],"type":"Point"}
}