{
  "type": "Feature",
  "properties": {
    "addr:full":"1150 Skees Rd West Palm Beach FL 33411",
    "addr:housenumber":"1150",
    "addr:postcode":"33411",
    "addr:street":"Skees Rd",
    "iso:country":"US",
    "sg:address":"1150 Skees Rd",
    "sg:city":"West Palm Beach",
    "sg:classifiers":[
        {
            "category":"Freight",
            "type":"Transportation"
        }
    ],
    "sg:phone":"+1 561 687 4662",
    "sg:postcode":"33411",
    "sg:province":"FL",
    "sg:tags":[
        "operator",
        "local",
        "trucking"
    ],
    "wof:name":"Leos Trucking General Hauling",
    "wof:placetype":"venue"
},
  "geometry": {"coordinates":[-80.15770500000001,26.694315],"type":"Point"}
}