{
  "type": "Feature",
  "properties": {
    "addr:full":"502 Gulf Shore Dr Destin FL 32541",
    "addr:housenumber":"502",
    "addr:postcode":"32541",
    "addr:street":"Gulf Shore Dr",
    "iso:country":"US",
    "sg:address":"502 Gulf Shore Dr",
    "sg:city":"Destin",
    "sg:classifiers":[
        {
            "category":"Organizations",
            "subcategory":"Professional Association",
            "type":"Services"
        }
    ],
    "sg:phone":"+1 850 837 2522",
    "sg:postcode":"32541",
    "sg:province":"FL",
    "sg:website":"www.islander-resort.com",
    "wof:name":"Islander Owners Assn",
    "wof:placetype":"venue"
},
  "geometry": {"coordinates":[-86.503209,30.387771],"type":"Point"}
}