{
  "type": "Feature",
  "properties": {
    "iso:country":"US",
    "sg:address":"8225 SW 63rd Pl",
    "sg:city":"Miami",
    "sg:classifiers":[
        {
            "category":"Wholesale",
            "subcategory":"Medical Equipment & Supplies",
            "type":"Manufacturing & Wholesale Goods"
        },
        {
            "category":"Shopping",
            "subcategory":"Pets & Pet Supplies",
            "type":"Retail Goods"
        },
        {
            "category":"Retail",
            "subcategory":"Veterinary Services",
            "type":"Services"
        }
    ],
    "sg:phone":"+1 305 665 6481",
    "sg:postcode":"33143",
    "sg:province":"FL",
    "sg:tags":[
        "product",
        "supply-wholesale",
        "health",
        "animal",
        "veterinarian"
    ],
    "wof:name":"Amerivet",
    "wof:placetype":"venue"
},
  "geometry": {"coordinates":[-80.296466,25.694614],"type":"Point"}
}