{
  "type": "Feature",
  "properties": {
    "iso:country":"US",
    "sg:address":"3558 SW Archer Rd",
    "sg:city":"Gainesville",
    "sg:classifiers":[
        {
            "category":"Retail",
            "subcategory":"Veterinary Services",
            "type":"Services"
        }
    ],
    "sg:phone":"+1 352 372 6603",
    "sg:postcode":"32608",
    "sg:province":"FL",
    "sg:tags":[
        "veterinarian",
        "specialty"
    ],
    "wof:name":"Hall De Vries Kimberly DVM",
    "wof:placetype":"venue"
},
  "geometry": {"coordinates":[-82.391037,29.61483],"type":"Point"}
}