{
  "type": "Feature",
  "properties": {
    "addr:full":"2401 S Orange Blossom Trl Orlando FL 32805",
    "addr:housenumber":"2401",
    "addr:postcode":"32805",
    "addr:street":"S Orange Blossom Trl",
    "iso:country":"US",
    "sg:address":"2401 S Orange Blossom Trl",
    "sg:city":"Orlando",
    "sg:classifiers":[
        {
            "category":"Retail",
            "subcategory":"Repair Shop",
            "type":"Services"
        }
    ],
    "sg:phone":"+1 407 650 0607",
    "sg:postcode":"32805",
    "sg:province":"FL",
    "wof:name":"Cycle One Corp",
    "wof:placetype":"venue"
},
  "geometry": {"coordinates":[-81.397025,28.516385],"type":"Point"}
}