{
  "type": "Feature",
  "properties": {
    "addr:full":"6677 Caroline St Milton FL 32570",
    "addr:housenumber":"6677",
    "addr:postcode":"32570",
    "addr:street":"Caroline St",
    "iso:country":"US",
    "sg:address":"6677 Caroline St",
    "sg:city":"Milton",
    "sg:classifiers":[
        {
            "category":"Autos & Motor Vehicles",
            "subcategory":"Auto Supplies",
            "type":"Retail Goods"
        },
        {
            "category":"Wholesale",
            "subcategory":"Electrical",
            "type":"Manufacturing & Wholesale Goods"
        },
        {
            "category":"Wholesale",
            "subcategory":"Auto Parts",
            "type":"Manufacturing & Wholesale Goods"
        }
    ],
    "sg:phone":"+1 850 623 2239",
    "sg:postcode":"32570",
    "sg:province":"FL",
    "sg:tags":[
        "battery",
        "automobile",
        "accessory",
        "equipment",
        "truck",
        "engines-supplies"
    ],
    "sg:website":"http://ad.doubleclick.net/clk;221862232;45455595;j?http://www.carquest.com/carquest/store_locator.html",
    "wof:name":"CARQUEST Auto Parts",
    "wof:placetype":"venue"
},
  "geometry": {"coordinates":[-87.045242,30.621479],"type":"Point"}
}