{
  "type": "Feature",
  "properties": {
    "addr:full":"2424 50th Ave N Saint Petersburg FL 33714",
    "addr:housenumber":"2424",
    "addr:postcode":"33714",
    "addr:street":"50Th Ave N",
    "iso:country":"US",
    "sg:address":"2424 50th Ave N",
    "sg:city":"Saint Petersburg",
    "sg:classifiers":[
        {
            "category":"Real Estate",
            "subcategory":"Real Estate Agent",
            "type":"Services"
        }
    ],
    "sg:phone":"+1 727 528 7952",
    "sg:postcode":"33714",
    "sg:province":"FL",
    "sg:tags":[
        "property",
        "management"
    ],
    "wof:name":"Landguard Properties",
    "wof:placetype":"venue"
},
  "geometry": {"coordinates":[-82.666251,27.817395],"type":"Point"}
}