{
  "type": "Feature",
  "properties": {
    "iso:country":"US",
    "sg:address":"300 Aragon Ave",
    "sg:city":"Coral Gables",
    "sg:classifiers":[
        {
            "category":"Professional",
            "subcategory":"Lawyer & Legal Services",
            "type":"Services"
        }
    ],
    "sg:phone":"+1 305 442 1919",
    "sg:postcode":"33134",
    "sg:province":"FL",
    "sg:tags":[
        "litigation"
    ],
    "wof:name":"Walter A P Jr PA Atty",
    "wof:placetype":"venue"
},
  "geometry": {"coordinates":[-80.260696,25.750299],"type":"Point"}
}