{
  "type": "Feature",
  "properties": {
    "iso:country":"US",
    "sg:address":"6266 NE Jacksonville Rd",
    "sg:city":"Ocala",
    "sg:classifiers":[
        {
            "category":"Personal",
            "subcategory":"Beauty Salon",
            "type":"Services"
        }
    ],
    "sg:phone":"+1 352 236 5600",
    "sg:postcode":"34479",
    "sg:province":"FL",
    "wof:name":"Salon 301",
    "wof:placetype":"venue"
},
  "geometry": {"coordinates":[-82.115797,29.251788],"type":"Point"}
}