{
  "type": "Feature",
  "properties": {
    "addr:full":"1130 Washington Ave Miami Beach FL 33139",
    "addr:housenumber":"1130",
    "addr:postcode":"33139",
    "addr:street":"Washington Ave",
    "iso:country":"US",
    "sg:address":"1130 Washington Ave",
    "sg:city":"Miami Beach",
    "sg:classifiers":[
        {
            "category":"Government",
            "subcategory":"City Hall",
            "type":"Public Place"
        }
    ],
    "sg:postcode":"33139",
    "sg:province":"FL",
    "wof:name":"Miami Beach County Clerk",
    "wof:placetype":"venue"
},
  "geometry": {"coordinates":[-80.13256,25.782264],"type":"Point"}
}