{
  "type": "Feature",
  "properties": {
    "iso:country":"US",
    "sg:address":"1026 Buenaventura Blvd",
    "sg:city":"Kissimmee",
    "sg:classifiers":[
        {
            "category":"Banks & Credit Unions",
            "subcategory":"Bank",
            "type":"Services"
        }
    ],
    "sg:phone":"+1 407 348 4443",
    "sg:postcode":"34743",
    "sg:province":"FL",
    "sg:tags":[
        "loan",
        "real estate"
    ],
    "wof:name":"Aabanco Mortgage Corp",
    "wof:placetype":"venue"
},
  "geometry": {"coordinates":[-81.36274899999999,28.346617],"type":"Point"}
}