{
  "type": "Feature",
  "properties": {
    "iso:country":"US",
    "sg:address":"6907 SW 22nd Ct",
    "sg:city":"Miramar",
    "sg:classifiers":[
        {
            "category":"Professional",
            "subcategory":"Printing & Photocopies",
            "type":"Services"
        }
    ],
    "sg:phone":"+1 305 525 4821",
    "sg:postcode":"33023",
    "sg:province":"FL",
    "sg:tags":[
        "lithographer"
    ],
    "wof:name":"Printing Specialties",
    "wof:placetype":"venue"
},
  "geometry": {"coordinates":[-80.225863,25.989747],"type":"Point"}
}