{
  "type": "Feature",
  "properties": {
    "iso:country":"US",
    "sg:address":"8585 SW Highway 200",
    "sg:city":"Ocala",
    "sg:classifiers":[
        {
            "category":"Fast Food",
            "type":"Food & Drink"
        },
        {
            "category":"Restaurant",
            "type":"Food & Drink"
        }
    ],
    "sg:phone":"+1 352 873 4760",
    "sg:postcode":"34481",
    "sg:province":"FL",
    "sg:tags":[
        "style",
        "hamburger",
        "family",
        "dog",
        "hot",
        "american"
    ],
    "sg:website":"http://www.checkers.com",
    "wof:name":"Checkers Drive In Restaurant",
    "wof:placetype":"venue"
},
  "geometry": {"coordinates":[-82.261292,29.075363],"type":"Point"}
}