{
  "type": "Feature",
  "properties": {
    "iso:country":"US",
    "sg:address":"1242 W 44th Pl",
    "sg:city":"Hialeah",
    "sg:classifiers":[
        {
            "category":"Personal",
            "subcategory":"Barber",
            "type":"Services"
        }
    ],
    "sg:phone":"+1 305 820 2992",
    "sg:postcode":"33012",
    "sg:province":"FL",
    "wof:name":"Jim's Barber Shop & High Quality Fades",
    "wof:placetype":"venue"
},
  "geometry": {"coordinates":[-80.30729700000001,25.8626],"type":"Point"}
}