{
  "type": "Feature",
  "properties": {
    "addr:full":"2082 Ward's Office Ln Avon Park FL 33825",
    "addr:housenumber":"2082",
    "addr:postcode":"33825",
    "addr:street":"Office Ln",
    "iso:country":"US",
    "sg:address":"2082 Ward's Office Ln",
    "sg:city":"Avon Park",
    "sg:classifiers":[
        {
            "category":"Wholesale",
            "subcategory":"Plants",
            "type":"Manufacturing & Wholesale Goods"
        }
    ],
    "sg:phone":"+1 863 453 6631",
    "sg:postcode":"33825",
    "sg:province":"FL",
    "sg:tags":[
        "nursery",
        "tree"
    ],
    "wof:name":"Ward's Citrus Nursery Inc",
    "wof:placetype":"venue"
},
  "geometry": {"coordinates":[-81.463847,27.593753],"type":"Point"}
}