{
  "type": "Feature",
  "properties": {
    "iso:country":"US",
    "sg:address":"1000 Olde Doubloon Dr",
    "sg:city":"Vero Beach",
    "sg:classifiers":[
        {
            "category":"Communications",
            "subcategory":"Radio Station",
            "type":"Services"
        }
    ],
    "sg:phone":"+1 772 231 8928",
    "sg:postcode":"32963",
    "sg:province":"FL",
    "sg:tags":[
        "broadcast"
    ],
    "wof:name":"Gore Communications of Florida",
    "wof:placetype":"venue"
},
  "geometry": {"coordinates":[-80.34772,27.62024],"type":"Point"}
}