{
  "type": "Feature",
  "properties": {
    "iso:country":"US",
    "sg:address":"5900 Rock Island Rd",
    "sg:city":"Tamarac",
    "sg:classifiers":[
        {
            "category":"Banks & Credit Unions",
            "subcategory":"Bank",
            "type":"Services"
        }
    ],
    "sg:phone":"+1 954 973 3277",
    "sg:postcode":"33319",
    "sg:province":"FL",
    "sg:tags":[
        "commercial",
        "national",
        "saving"
    ],
    "sg:website":"https://www.bankofamerica.com/",
    "wof:name":"Bank of America",
    "wof:placetype":"venue"
},
  "geometry": {"coordinates":[-80.21993999999999,26.197229],"type":"Point"}
}