{
  "type": "Feature",
  "properties": {
    "addr:full":"5910 Bible Camp Rd Groveland FL 34736",
    "addr:housenumber":"5910",
    "addr:postcode":"34736",
    "addr:street":"Bible Camp Rd",
    "iso:country":"US",
    "sg:address":"5910 Bible Camp Rd",
    "sg:city":"Groveland",
    "sg:classifiers":[
        {
            "category":"Social Services",
            "subcategory":"Child Care",
            "type":"Services"
        },
        {
            "category":"Education",
            "subcategory":"School",
            "type":"Public Place"
        }
    ],
    "sg:phone":"+1 352 429 4491",
    "sg:postcode":"34736",
    "sg:province":"FL",
    "sg:tags":[
        "nursery",
        "private",
        "k-",
        "day"
    ],
    "wof:name":"Over The Rainbow Daycare",
    "wof:placetype":"venue"
},
  "geometry": {"coordinates":[-81.85708200000001,28.574799],"type":"Point"}
}