{
  "type": "Feature",
  "properties": {
    "iso:country":"US",
    "sg:address":"6120 Edgewater Dr",
    "sg:city":"Orlando",
    "sg:classifiers":[
        {
            "category":"Home & Garden",
            "subcategory":"Building Materials",
            "type":"Retail Goods"
        }
    ],
    "sg:phone":"+1 407 822 0603",
    "sg:postcode":"32810",
    "sg:province":"FL",
    "sg:tags":[
        "glass",
        "window",
        "plate"
    ],
    "wof:name":"Action Glass",
    "wof:placetype":"venue"
},
  "geometry": {"coordinates":[-81.418746,28.613037],"type":"Point"}
}