{
  "type": "Feature",
  "properties": {
    "iso:country":"US",
    "sg:address":"2780 NW 87th Ln",
    "sg:city":"Fort Lauderdale",
    "sg:classifiers":[
        {
            "category":"Wholesale",
            "subcategory":"Machinery & Supplies",
            "type":"Manufacturing & Wholesale Goods"
        }
    ],
    "sg:phone":"+1 954 741 1211",
    "sg:postcode":"33322",
    "sg:province":"FL",
    "sg:tags":[
        "equipment",
        "establishment"
    ],
    "wof:name":"Jz Pressure Cleaning",
    "wof:placetype":"venue"
},
  "geometry": {"coordinates":[-80.266993,26.158475],"type":"Point"}
}