{
  "type": "Feature",
  "properties": {
    "iso:country":"US",
    "sg:address":"132 W Venice Ave",
    "sg:city":"Venice",
    "sg:classifiers":[
        {
            "category":"Food & Beverages",
            "subcategory":"Specialty",
            "type":"Retail Goods"
        }
    ],
    "sg:phone":"+1 941 486 8020",
    "sg:postcode":"34285",
    "sg:province":"FL",
    "wof:name":"Evergreen Nutrition",
    "wof:placetype":"venue"
},
  "geometry": {"coordinates":[-82.445088,27.099938],"type":"Point"}
}