{
  "type": "Feature",
  "properties": {
    "iso:country":"US",
    "sg:address":"4033 Bounce Dr",
    "sg:city":"Orlando",
    "sg:classifiers":[
        {
            "category":"Professional",
            "subcategory":"Management & Consulting",
            "type":"Services"
        }
    ],
    "sg:phone":"+1 407 381 0012",
    "sg:postcode":"32812",
    "sg:province":"FL",
    "wof:name":"Quill Communications Inc",
    "wof:placetype":"venue"
},
  "geometry": {"coordinates":[-81.324888,28.492555],"type":"Point"}
}