{
  "type": "Feature",
  "properties": {
    "addr:full":"4520 Oak Fair Blvd Tampa FL 33610",
    "addr:housenumber":"4520",
    "addr:postcode":"33610",
    "addr:street":"Oak Fair Blvd",
    "iso:country":"US",
    "sg:address":"4520 Oak Fair Blvd",
    "sg:city":"Tampa",
    "sg:classifiers":[
        {
            "category":"Government",
            "subcategory":"Jail",
            "type":"Public Place"
        }
    ],
    "sg:phone":"+1 813 744 8555",
    "sg:postcode":"33610",
    "sg:province":"FL",
    "sg:tags":[
        "support",
        "correctional",
        "institution",
        "facility"
    ],
    "wof:name":"Region V",
    "wof:placetype":"venue"
},
  "geometry": {"coordinates":[-82.356572,27.987226],"type":"Point"}
}