{
  "type": "Feature",
  "properties": {
    "iso:country":"US",
    "sg:address":"5580 Bee Ridge Rd Bldg B",
    "sg:city":"Sarasota",
    "sg:classifiers":[
        {
            "category":"Health Services",
            "subcategory":"Doctor",
            "type":"Services"
        },
        {
            "category":"Health Services",
            "subcategory":"Nursing And Care Facility",
            "type":"Services"
        }
    ],
    "sg:phone":"+1 941 921 3500",
    "sg:postcode":"34233",
    "sg:province":"FL",
    "sg:tags":[
        "physician",
        "management",
        "pain",
        "surgeons"
    ],
    "wof:name":"Sarasota Pain Management",
    "wof:placetype":"venue"
},
  "geometry": {"coordinates":[-82.459416,27.298731],"type":"Point"}
}