{
  "type": "Feature",
  "properties": {
    "addr:full":"1079 95th St Bay Harbor Islands FL 33154",
    "addr:housenumber":"1079",
    "addr:postcode":"33154",
    "addr:street":"95Th St",
    "iso:country":"US",
    "sg:address":"1079 95th St",
    "sg:city":"Bay Harbor Islands",
    "sg:classifiers":[
        {
            "category":"Building & Trades",
            "subcategory":"Locksmith",
            "type":"Services"
        }
    ],
    "sg:phone":"+1 305 415 8012",
    "sg:postcode":"33154",
    "sg:province":"FL",
    "sg:tags":[
        "key"
    ],
    "wof:name":"0 0 0 24 Hour A Emergency A Locksmith",
    "wof:placetype":"venue"
},
  "geometry": {"coordinates":[-80.131072,25.885873],"type":"Point"}
}