{
  "type": "Feature",
  "properties": {
    "addr:full":"18 Hwy 40 E Inglis FL 34449",
    "addr:postcode":"34449",
    "addr:street":"18 Hwy 40 E",
    "iso:country":"US",
    "sg:address":"18 Hwy 40 E",
    "sg:city":"Inglis",
    "sg:classifiers":[
        {
            "category":"Education",
            "subcategory":"College",
            "type":"Public Place"
        }
    ],
    "sg:phone":"+1 352 447 6214",
    "sg:postcode":"34449",
    "sg:province":"FL",
    "sg:tags":[
        "academic",
        "school"
    ],
    "wof:name":"Liberty Baptist Bible College",
    "wof:placetype":"venue"
},
  "geometry": {"coordinates":[-82.66899100000001,29.030291],"type":"Point"}
}