{
  "type": "Feature",
  "properties": {
    "iso:country":"US",
    "sg:address":"3150 NW 17th St",
    "sg:city":"Fort Lauderdale",
    "sg:classifiers":[
        {
            "category":"Manufacturing",
            "subcategory":"Motor Vehicles & Parts",
            "type":"Manufacturing & Wholesale Goods"
        }
    ],
    "sg:phone":"+1 954 581 9973",
    "sg:postcode":"33311",
    "sg:province":"FL",
    "sg:tags":[
        "repair",
        "general",
        "auto",
        "mfg"
    ],
    "wof:name":"J DS Service Center",
    "wof:placetype":"venue"
},
  "geometry": {"coordinates":[-80.18778,26.147874],"type":"Point"}
}