{
  "type": "Feature",
  "properties": {
    "addr:full":"9050 US Hwy 98 Pensacola FL 32506",
    "addr:housenumber":"9050",
    "addr:postcode":"32506",
    "addr:street":"Us Hwy 98",
    "iso:country":"US",
    "sg:address":"9050 US Hwy 98",
    "sg:city":"Pensacola",
    "sg:classifiers":[
        {
            "category":"Building & Trades",
            "subcategory":"Cleaning & Sanitation",
            "type":"Services"
        }
    ],
    "sg:phone":"+1 850 291 0744",
    "sg:postcode":"32506",
    "sg:province":"FL",
    "sg:tags":[
        "supply"
    ],
    "wof:name":"Contract Cleaning Services By",
    "wof:placetype":"venue"
},
  "geometry": {"coordinates":[-87.33823599999999,30.40334],"type":"Point"}
}