{
  "type": "Feature",
  "properties": {
    "addr:full":"4317 Fortune Pl Melbourne FL 32904",
    "addr:housenumber":"4317",
    "addr:postcode":"32904",
    "addr:street":"Fortune Pl",
    "iso:country":"US",
    "sg:address":"4317 Fortune Pl",
    "sg:city":"Melbourne",
    "sg:classifiers":[
        {
            "category":"Utilities",
            "subcategory":"Refuse",
            "type":"Services"
        },
        {
            "category":"Building & Trades",
            "subcategory":"Construction",
            "type":"Services"
        }
    ],
    "sg:phone":"+1 321 722 2455",
    "sg:postcode":"32904",
    "sg:province":"FL",
    "sg:tags":[
        "disposal",
        "waste",
        "system",
        "contractor"
    ],
    "wof:name":"Onyx Environmental Services",
    "wof:placetype":"venue"
},
  "geometry": {"coordinates":[-80.697768,28.094848],"type":"Point"}
}