{
  "type": "Feature",
  "properties": {
    "addr:full":"30120 Oak Rd Punta Gorda FL 33982",
    "addr:housenumber":"30120",
    "addr:postcode":"33982",
    "addr:street":"Oak Rd",
    "iso:country":"US",
    "sg:address":"30120 Oak Rd",
    "sg:city":"Punta Gorda",
    "sg:classifiers":[
        {
            "category":"Building & Trades",
            "subcategory":"Landscaping Services",
            "type":"Services"
        }
    ],
    "sg:phone":"+1 941 505 5690",
    "sg:postcode":"33982",
    "sg:province":"FL",
    "wof:name":"Timmy Adams Lawn Service",
    "wof:placetype":"venue"
},
  "geometry": {"coordinates":[-81.955736,26.989812],"type":"Point"}
}