{
  "type": "Feature",
  "properties": {
    "iso:country":"US",
    "sg:address":"4125 Ocean Beach Blvd",
    "sg:city":"Cocoa Beach",
    "sg:classifiers":[
        {
            "category":"Banks & Credit Unions",
            "subcategory":"Bank",
            "type":"Services"
        }
    ],
    "sg:phone":"+1 321 799 4769",
    "sg:postcode":"32931",
    "sg:province":"FL",
    "sg:tags":[
        "loan",
        "real estate"
    ],
    "wof:name":"All Family Mortgage",
    "wof:placetype":"venue"
},
  "geometry": {"coordinates":[-80.605898,28.35647],"type":"Point"}
}