{
  "type": "Feature",
  "properties": {
    "addr:full":"4590 Selvitz Rd Fort Pierce FL 34981",
    "addr:housenumber":"4590",
    "addr:postcode":"34981",
    "addr:street":"Selvitz Rd",
    "iso:country":"US",
    "sg:address":"4590 Selvitz Rd",
    "sg:city":"Fort Pierce",
    "sg:classifiers":[
        {
            "category":"Organizations",
            "subcategory":"Non-profit Organization",
            "type":"Services"
        }
    ],
    "sg:phone":"+1 772 464 7575",
    "sg:postcode":"34981",
    "sg:province":"FL",
    "sg:tags":[
        "info",
        "addiction",
        "abuse",
        "treatment",
        "drug"
    ],
    "wof:name":"Drug Abuse Treatment Assoc",
    "wof:placetype":"venue"
},
  "geometry": {"coordinates":[-80.366495,27.383341],"type":"Point"}
}