{
  "type": "Feature",
  "properties": {
    "iso:country":"US",
    "sg:address":"4868 NE 12th Ave",
    "sg:city":"Fort Lauderdale",
    "sg:classifiers":[
        {
            "category":"Building & Trades",
            "subcategory":"Cleaning & Sanitation",
            "type":"Services"
        }
    ],
    "sg:phone":"+1 954 938 0028",
    "sg:postcode":"33334",
    "sg:province":"FL",
    "sg:tags":[
        "janitor"
    ],
    "wof:name":"Custom Building Cleaning Svcs",
    "wof:placetype":"venue"
},
  "geometry": {"coordinates":[-80.13108200000001,26.185249],"type":"Point"}
}