{
  "type": "Feature",
  "properties": {
    "iso:country":"US",
    "sg:address":"1933 Ayrshire Pl",
    "sg:city":"Oviedo",
    "sg:classifiers":[
        {
            "category":"Real Estate",
            "subcategory":"Real Estate Operator",
            "type":"Services"
        }
    ],
    "sg:phone":"+1 407 365 1650",
    "sg:postcode":"32765",
    "sg:province":"FL",
    "sg:tags":[
        "property",
        "lessor"
    ],
    "wof:name":"United Investment Corp",
    "wof:placetype":"venue"
},
  "geometry": {"coordinates":[-81.213612,28.642856],"type":"Point"}
}