{
  "type": "Feature",
  "properties": {
    "iso:country":"US",
    "sg:address":"701 Lake Port Blvd",
    "sg:city":"Leesburg",
    "sg:classifiers":[
        {
            "category":"Personal",
            "subcategory":"Beauty Salon",
            "type":"Services"
        }
    ],
    "sg:phone":"+1 352 326 4438",
    "sg:postcode":"34748",
    "sg:province":"FL",
    "sg:tags":[
        "shop"
    ],
    "wof:name":"Salon On Square",
    "wof:placetype":"venue"
},
  "geometry": {"coordinates":[-81.86078500000001,28.80558],"type":"Point"}
}