{
  "type": "Feature",
  "properties": {
    "addr:full":"9005 US Hwy 98 Pensacola FL 32506",
    "addr:housenumber":"9005",
    "addr:postcode":"32506",
    "addr:street":"Us Hwy 98",
    "iso:country":"US",
    "sg:address":"9005 US Hwy 98",
    "sg:city":"Pensacola",
    "sg:classifiers":[
        {
            "category":"Bars & Pubs",
            "type":"Food & Drink"
        }
    ],
    "sg:phone":"+1 850 453 1337",
    "sg:postcode":"32506",
    "sg:province":"FL",
    "sg:tags":[
        "drinking"
    ],
    "wof:name":"Fox Trap Club",
    "wof:placetype":"venue"
},
  "geometry": {"coordinates":[-87.33494899999999,30.403298],"type":"Point"}
}