{
  "type": "Feature",
  "properties": {
    "addr:full":"4790 NW 7th St Miami FL 33126",
    "addr:housenumber":"4790",
    "addr:postcode":"33126",
    "addr:street":"Nw 7Th St",
    "iso:country":"US",
    "sg:address":"4790 NW 7th St",
    "sg:city":"Miami",
    "sg:classifiers":[
        {
            "category":"Professional",
            "subcategory":"Lawyer & Legal Services",
            "type":"Services"
        }
    ],
    "sg:phone":"+1 305 446 3389",
    "sg:postcode":"33126",
    "sg:province":"FL",
    "sg:tags":[
        "research"
    ],
    "wof:name":"My Office",
    "wof:placetype":"venue"
},
  "geometry": {"coordinates":[-80.273113,25.778573],"type":"Point"}
}