{
  "type": "Feature",
  "properties": {
    "addr:full":"3201 Mobile Hwy Pensacola FL 32505",
    "addr:housenumber":"3201",
    "addr:postcode":"32505",
    "addr:street":"Mobile Hwy",
    "iso:country":"US",
    "sg:address":"3201 Mobile Hwy",
    "sg:city":"Pensacola",
    "sg:classifiers":[
        {
            "category":"Food & Beverages",
            "subcategory":"Groceries & Convenience Stores",
            "type":"Retail Goods"
        },
        {
            "category":"Food & Beverages",
            "subcategory":"Specialty",
            "type":"Retail Goods"
        }
    ],
    "sg:phone":"+1 850 433 5734",
    "sg:postcode":"32505",
    "sg:province":"FL",
    "sg:tags":[
        "product",
        "oriental",
        "chinese"
    ],
    "wof:name":"Chau's Oriental Food Store",
    "wof:placetype":"venue"
},
  "geometry": {"coordinates":[-87.25443199999999,30.422293],"type":"Point"}
}