{
  "type": "Feature",
  "properties": {
    "iso:country":"US",
    "sg:address":"410 E Park Ave",
    "sg:city":"High Springs",
    "sg:classifiers":[
        {
            "category":"Recreation",
            "type":"Entertainment"
        }
    ],
    "sg:phone":"+1 386 454 1853",
    "sg:postcode":"32626",
    "sg:province":"FL",
    "sg:tags":[
        "parks"
    ],
    "sg:website":"www.floridastateparks.org",
    "wof:name":"O'Leno State Park",
    "wof:placetype":"venue"
},
  "geometry": {"coordinates":[-82.855124,29.478794],"type":"Point"}
}