{
  "type": "Feature",
  "properties": {
    "iso:country":"US",
    "sg:address":"919 Chickadee Dr",
    "sg:city":"Venice",
    "sg:classifiers":[
        {
            "category":"Structure",
            "subcategory":"Office Building",
            "type":"Public Place"
        }
    ],
    "sg:phone":"+1 941 493 3348",
    "sg:postcode":"34285",
    "sg:province":"FL",
    "sg:tags":[
        "park"
    ],
    "wof:name":"Pfahler Properties Inc",
    "wof:placetype":"venue"
},
  "geometry": {"coordinates":[-82.415001,27.08794],"type":"Point"}
}