{
  "type": "Feature",
  "properties": {
    "iso:country":"US",
    "sg:address":"1750 Buena Vista Dr",
    "sg:city":"Eustis",
    "sg:classifiers":[
        {
            "category":"Retail",
            "subcategory":"Animal Services",
            "type":"Services"
        }
    ],
    "sg:phone":"+1 352 483 3326",
    "sg:postcode":"32726",
    "sg:province":"FL",
    "wof:name":"Reginas Pet Sitting Service",
    "wof:placetype":"venue"
},
  "geometry": {"coordinates":[-81.672729,28.837062],"type":"Point"}
}