{
  "type": "Feature",
  "properties": {
    "addr:full":"4467 SW 75th Ave Miami FL 33155",
    "addr:housenumber":"4467",
    "addr:postcode":"33155",
    "addr:street":"Sw 75Th Ave",
    "iso:country":"US",
    "sg:address":"4467 SW 75th Ave",
    "sg:city":"Miami",
    "sg:classifiers":[
        {
            "category":"Shopping",
            "subcategory":"Used Merchandise",
            "type":"Retail Goods"
        }
    ],
    "sg:phone":"+1 305 265 8538",
    "sg:postcode":"33155",
    "sg:province":"FL",
    "sg:tags":[
        "antique"
    ],
    "wof:name":"Ideas & More Inc",
    "wof:placetype":"venue"
},
  "geometry": {"coordinates":[-80.316778,25.727097],"type":"Point"}
}