{
  "type": "Feature",
  "properties": {
    "iso:country":"US",
    "sg:address":"4089 S McCall Rd",
    "sg:city":"Englewood",
    "sg:classifiers":[
        {
            "category":"Retail",
            "subcategory":"Veterinary Services",
            "type":"Services"
        }
    ],
    "sg:phone":"+1 941 474 6393",
    "sg:postcode":"34224",
    "sg:province":"FL",
    "sg:tags":[
        "hospital",
        "veterinarian",
        "animal"
    ],
    "wof:name":"Sunnybrook Animal & Bird Hosp",
    "wof:placetype":"venue"
},
  "geometry": {"coordinates":[-82.272603,26.93266],"type":"Point"}
}