{
  "type": "Feature",
  "properties": {
    "iso:country":"US",
    "sg:address":"551 E Melrose Cir",
    "sg:city":"Fort Lauderdale",
    "sg:classifiers":[
        {
            "category":"Professional",
            "subcategory":"Business Services",
            "type":"Services"
        }
    ],
    "sg:phone":"+1 954 732 7314",
    "sg:postcode":"33312",
    "sg:province":"FL",
    "sg:tags":[
        "recording",
        "studio"
    ],
    "wof:name":"Studio I Recordings",
    "wof:placetype":"venue"
},
  "geometry": {"coordinates":[-80.19273099999999,26.112064],"type":"Point"}
}