{
  "type": "Feature",
  "properties": {
    "addr:full":"14 Coastal Hwy Panacea FL 32346",
    "addr:housenumber":"14",
    "addr:postcode":"32346",
    "addr:street":"Coastal Hwy",
    "iso:country":"US",
    "sg:address":"14 Coastal Hwy",
    "sg:city":"Panacea",
    "sg:classifiers":[
        {
            "category":"Real Estate",
            "subcategory":"Developer",
            "type":"Services"
        }
    ],
    "sg:phone":"+1 850 984 5251",
    "sg:postcode":"32346",
    "sg:province":"FL",
    "sg:tags":[
        "house",
        "construction"
    ],
    "wof:name":"Mc Millan Land & Construction",
    "wof:placetype":"venue"
},
  "geometry": {"coordinates":[-84.38327099999999,29.977745],"type":"Point"}
}