{
  "type": "Feature",
  "properties": {
    "iso:country":"US",
    "sg:address":"16500 Quarter Horse Ct",
    "sg:city":"Montverde",
    "sg:classifiers":[
        {
            "category":"Shopping",
            "subcategory":"Hobbies, Toys, & Games",
            "type":"Retail Goods"
        }
    ],
    "sg:phone":"+1 407 469 3990",
    "sg:postcode":"34756",
    "sg:province":"FL",
    "wof:name":"Camilles",
    "wof:placetype":"venue"
},
  "geometry": {"coordinates":[-81.705578,28.587501],"type":"Point"}
}