{
  "type": "Feature",
  "properties": {
    "addr:full":"4081 Yucatan Cir Port Charlotte FL 33948",
    "addr:housenumber":"4081",
    "addr:postcode":"33948",
    "addr:street":"Yucatan Cir",
    "iso:country":"US",
    "sg:address":"4081 Yucatan Cir",
    "sg:city":"Port Charlotte",
    "sg:classifiers":[
        {
            "category":"Shopping",
            "subcategory":"Used Merchandise",
            "type":"Retail Goods"
        }
    ],
    "sg:phone":"+1 941 764 8430",
    "sg:postcode":"33948",
    "sg:province":"FL",
    "wof:name":"A Antique Center Orange County",
    "wof:placetype":"venue"
},
  "geometry": {"coordinates":[-82.136171,26.971443],"type":"Point"}
}