{
  "type": "Feature",
  "properties": {
    "iso:country":"US",
    "sg:address":"1 W Sample Rd",
    "sg:city":"Pompano Beach",
    "sg:classifiers":[
        {
            "category":"Health Services",
            "subcategory":"Doctor",
            "type":"Services"
        }
    ],
    "sg:phone":"+1 954 782 2442",
    "sg:postcode":"33064",
    "sg:province":"FL",
    "sg:tags":[
        "medical"
    ],
    "wof:name":"Harold H Rosen MD",
    "wof:placetype":"venue"
},
  "geometry": {"coordinates":[-80.12193000000001,26.275129],"type":"Point"}
}