{
  "type": "Feature",
  "properties": {
    "addr:full":"6787 Miller Dr Miami FL 33155",
    "addr:housenumber":"6787",
    "addr:postcode":"33155",
    "addr:street":"Miller Dr",
    "iso:country":"US",
    "sg:address":"6787 Miller Dr",
    "sg:city":"Miami",
    "sg:classifiers":[
        {
            "category":"Shopping",
            "type":"Retail Goods"
        }
    ],
    "sg:phone":"+1 305 663 9634",
    "sg:postcode":"33155",
    "sg:province":"FL",
    "sg:tags":[
        "miscellaneous",
        "store"
    ],
    "wof:name":"Try-Cycling Consignments",
    "wof:placetype":"venue"
},
  "geometry": {"coordinates":[-80.302712,25.718399],"type":"Point"}
}