{
  "type": "Feature",
  "properties": {
    "iso:country":"US",
    "sg:address":"2858 Remington Green Cir",
    "sg:city":"Tallahassee",
    "sg:classifiers":[
        {
            "category":"Insurance",
            "subcategory":"Insurance Agent",
            "type":"Services"
        }
    ],
    "sg:phone":"+1 850 893 8292",
    "sg:postcode":"32308",
    "sg:province":"FL",
    "sg:tags":[
        "personal"
    ],
    "wof:name":"Spitzer Philip R CLU Ch Fc",
    "wof:placetype":"venue"
},
  "geometry": {"coordinates":[-84.24394100000001,30.490353],"type":"Point"}
}