{
  "type": "Feature",
  "properties": {
    "addr:full":"1950 20th St Vero Beach FL 32960",
    "addr:housenumber":"1950",
    "addr:postcode":"32960",
    "addr:street":"20Th St",
    "iso:country":"US",
    "sg:address":"1950 20th St",
    "sg:city":"Vero Beach",
    "sg:classifiers":[
        {
            "category":"Retail",
            "subcategory":"Funeral Services",
            "type":"Services"
        }
    ],
    "sg:phone":"+1 772 567 9998",
    "sg:postcode":"32960",
    "sg:province":"FL",
    "sg:tags":[
        "director"
    ],
    "wof:name":"Seawinds Funeral Home",
    "wof:placetype":"venue"
},
  "geometry": {"coordinates":[-80.40498599999999,27.63877],"type":"Point"}
}