{
  "type": "Feature",
  "properties": {
    "addr:full":"135 Marlin Dr Ormond Beach FL 32176",
    "addr:housenumber":"135",
    "addr:postcode":"32176",
    "addr:street":"Marlin Dr",
    "iso:country":"US",
    "sg:address":"135 Marlin Dr",
    "sg:city":"Ormond Beach",
    "sg:classifiers":[
        {
            "category":"Building & Trades",
            "subcategory":"Landscaping Services",
            "type":"Services"
        }
    ],
    "sg:phone":"+1 386 441 5174",
    "sg:postcode":"32176",
    "sg:province":"FL",
    "wof:name":"Daves Yard Maintenance",
    "wof:placetype":"venue"
},
  "geometry": {"coordinates":[-81.078458,29.36795],"type":"Point"}
}