{
  "type": "Feature",
  "properties": {
    "iso:country":"US",
    "sg:address":"8044 Cloverglen Cir",
    "sg:city":"Orlando",
    "sg:classifiers":[
        {
            "category":"Building & Trades",
            "subcategory":"Construction",
            "type":"Services"
        }
    ],
    "sg:phone":"+1 407 291 0122",
    "sg:postcode":"32818",
    "sg:province":"FL",
    "sg:tags":[
        "contractor"
    ],
    "wof:name":"Glenn Conyers Ceilings",
    "wof:placetype":"venue"
},
  "geometry": {"coordinates":[-81.496244,28.597023],"type":"Point"}
}