{
  "type": "Feature",
  "properties": {
    "addr:full":"8542 Kingfisher Way Pensacola FL 32534",
    "addr:housenumber":"8542",
    "addr:postcode":"32534",
    "addr:street":"Kingfisher Way",
    "iso:country":"US",
    "sg:address":"8542 Kingfisher Way",
    "sg:city":"Pensacola",
    "sg:classifiers":[
        {
            "category":"Building & Trades",
            "subcategory":"Construction",
            "type":"Services"
        }
    ],
    "sg:phone":"+1 850 474 9110",
    "sg:postcode":"32534",
    "sg:province":"FL",
    "sg:tags":[
        "restoration",
        "cleaning",
        "patio",
        "deck"
    ],
    "wof:name":"Pro Tech Systems",
    "wof:placetype":"venue"
},
  "geometry": {"coordinates":[-87.308634,30.520578],"type":"Point"}
}