{
  "type": "Feature",
  "properties": {
    "addr:full":"275 SW 38th Ct Coral Gables FL 33134",
    "addr:housenumber":"275",
    "addr:postcode":"33134",
    "addr:street":"Sw 38Th Ct",
    "iso:country":"US",
    "sg:address":"275 SW 38th Ct",
    "sg:city":"Coral Gables",
    "sg:classifiers":[
        {
            "category":"Building & Trades",
            "subcategory":"Pest Control",
            "type":"Services"
        }
    ],
    "sg:phone":"+1 305 443 7795",
    "sg:postcode":"33134",
    "sg:province":"FL",
    "wof:name":"Albi-Tech Pest Eliminators",
    "wof:placetype":"venue"
},
  "geometry": {"coordinates":[-80.258707,25.769603],"type":"Point"}
}