{
  "type": "Feature",
  "properties": {
    "iso:country":"US",
    "sg:address":"1879 SW 31st Ave",
    "sg:city":"Hallandale",
    "sg:phone":"+1 954 989 9608",
    "sg:postcode":"33009",
    "sg:province":"FL",
    "sg:tags":[
        "equipment",
        "wholesale",
        "hotel",
        "supply"
    ],
    "wof:name":"Hospitality Purchasing Network",
    "wof:placetype":"venue"
},
  "geometry": {"coordinates":[-80.168633,25.994446],"type":"Point"}
}