{
  "type": "Feature",
  "properties": {
    "addr:full":"13435 S McCall Rd Port Charlotte FL 33981",
    "addr:housenumber":"13435",
    "addr:postcode":"33981",
    "addr:street":"S Mccall Rd",
    "iso:country":"US",
    "sg:address":"13435 S McCall Rd",
    "sg:city":"Port Charlotte",
    "sg:classifiers":[
        {
            "category":"Shopping",
            "type":"Retail Goods"
        }
    ],
    "sg:phone":"+1 941 698 9600",
    "sg:postcode":"33981",
    "sg:province":"FL",
    "sg:tags":[
        "merchandise"
    ],
    "wof:name":"UPS Store 4198",
    "wof:placetype":"venue"
},
  "geometry": {"coordinates":[-82.226411,26.933287],"type":"Point"}
}