{
  "type": "Feature",
  "properties": {
    "iso:country":"US",
    "sg:address":"1 Knights Key Blvd",
    "sg:city":"Marathon",
    "sg:classifiers":[
        {
            "category":"Organizations",
            "subcategory":"Religious Organization",
            "type":"Services"
        }
    ],
    "sg:phone":"+1 305 289 0230",
    "sg:postcode":"33050",
    "sg:province":"FL",
    "wof:name":"River City Maritime Ministries",
    "wof:placetype":"venue"
},
  "geometry": {"coordinates":[-81.119569,24.706128],"type":"Point"}
}