{
  "type": "Feature",
  "properties": {
    "iso:country":"US",
    "sg:address":"8770 SW 132nd St",
    "sg:city":"Miami",
    "sg:classifiers":[
        {
            "category":"Retail",
            "subcategory":"Auto Repair",
            "type":"Services"
        }
    ],
    "sg:phone":"+1 305 238 4003",
    "sg:postcode":"33176",
    "sg:province":"FL",
    "sg:tags":[
        "body",
        "automobile",
        "painting"
    ],
    "wof:name":"T & D Coach Works",
    "wof:placetype":"venue"
},
  "geometry": {"coordinates":[-80.33498899999999,25.647428],"type":"Point"}
}