{
  "type": "Feature",
  "properties": {
    "addr:full":"1876 Barber Rd Sarasota FL 34240",
    "addr:housenumber":"1876",
    "addr:postcode":"34240",
    "addr:street":"Barber Rd",
    "iso:country":"US",
    "sg:address":"1876 Barber Rd",
    "sg:city":"Sarasota",
    "sg:classifiers":[
        {
            "category":"Retail",
            "subcategory":"Repair Shop",
            "type":"Services"
        }
    ],
    "sg:phone":"+1 941 378 4222",
    "sg:postcode":"34240",
    "sg:province":"FL",
    "sg:tags":[
        "appliance"
    ],
    "sg:website":"www.asofla.com",
    "wof:name":"Appliance Service of Florida",
    "wof:placetype":"venue"
},
  "geometry": {"coordinates":[-82.444794,27.318205],"type":"Point"}
}