{
  "type": "Feature",
  "properties": {
    "iso:country":"US",
    "sg:address":"8611 NW 54th St",
    "sg:city":"Doral",
    "sg:classifiers":[
        {
            "category":"Wholesale",
            "subcategory":"Durable Goods & Equipment",
            "type":"Manufacturing & Wholesale Goods"
        }
    ],
    "sg:phone":"+1 305 406 0287",
    "sg:postcode":"33166",
    "sg:province":"FL",
    "sg:tags":[
        "exporter"
    ],
    "wof:name":"Sprintbox Services 2005 LLC",
    "wof:placetype":"venue"
},
  "geometry": {"coordinates":[-80.33766199999999,25.822641],"type":"Point"}
}