{
  "type": "Feature",
  "properties": {
    "addr:full":"14206 SW 136th St Miami FL 33186",
    "addr:housenumber":"14206",
    "addr:postcode":"33186",
    "addr:street":"Sw 136Th St",
    "iso:country":"US",
    "sg:address":"14206 SW 136th St",
    "sg:city":"Miami",
    "sg:classifiers":[
        {
            "category":"Manufacturing",
            "subcategory":"Printing",
            "type":"Manufacturing & Wholesale Goods"
        }
    ],
    "sg:phone":"+1 305 256 8798",
    "sg:postcode":"33186",
    "sg:province":"FL",
    "sg:tags":[
        "printer"
    ],
    "wof:name":"Galliano Studios",
    "wof:placetype":"venue"
},
  "geometry": {"coordinates":[-80.428286,25.640696],"type":"Point"}
}