{
  "type": "Feature",
  "properties": {
    "iso:country":"US",
    "sg:address":"1201 NW 16th St",
    "sg:city":"Miami",
    "sg:classifiers":[
        {
            "category":"Health Services",
            "subcategory":"Hospital",
            "type":"Services"
        }
    ],
    "sg:phone":"+1 305 324 4455",
    "sg:postcode":"33125",
    "sg:province":"FL",
    "wof:name":"Miami Veterans Affairs Medical Center",
    "wof:placetype":"venue"
},
  "geometry": {"coordinates":[-80.215149,25.790461],"type":"Point"}
}