{
  "type": "Feature",
  "properties": {
    "iso:country":"US",
    "sg:address":"12609 Shady Ln SW",
    "sg:city":"Wellington",
    "sg:classifiers":[
        {
            "category":"Building & Trades",
            "subcategory":"Cleaning & Sanitation",
            "type":"Services"
        }
    ],
    "sg:phone":"+1 561 452 1762",
    "sg:postcode":"33471",
    "sg:province":"FL",
    "sg:tags":[
        "janitor"
    ],
    "wof:name":"Daniel Rigg Cleaning Svc",
    "wof:placetype":"venue"
},
  "geometry": {"coordinates":[-81.298207,26.797365],"type":"Point"}
}