{
  "type": "Feature",
  "properties": {
    "iso:country":"US",
    "sg:address":"10226 NW 50th St",
    "sg:city":"Fort Lauderdale",
    "sg:classifiers":[
        {
            "category":"Wholesale",
            "subcategory":"Machinery & Supplies",
            "type":"Manufacturing & Wholesale Goods"
        },
        {
            "category":"Building & Trades",
            "subcategory":"Plumbing",
            "type":"Services"
        }
    ],
    "sg:phone":"+1 954 572 3443",
    "sg:postcode":"33351",
    "sg:province":"FL",
    "sg:tags":[
        "specializing",
        "fire",
        "contractor",
        "system",
        "sprinkler"
    ],
    "wof:name":"Absolute Fire Protection Inc",
    "wof:placetype":"venue"
},
  "geometry": {"coordinates":[-80.285813,26.186431],"type":"Point"}
}