{
  "type": "Feature",
  "properties": {
    "addr:full":"1185 3rd St S Naples FL 34102",
    "addr:housenumber":"1185",
    "addr:postcode":"34102",
    "addr:street":"3Rd St S",
    "iso:country":"US",
    "sg:address":"1185 3rd St S",
    "sg:city":"Naples",
    "sg:classifiers":[
        {
            "category":"Shopping",
            "subcategory":"Jewelry",
            "type":"Retail Goods"
        }
    ],
    "sg:phone":"+1 239 643 8900",
    "sg:postcode":"34102",
    "sg:province":"FL",
    "sg:tags":[
        "jeweler"
    ],
    "wof:name":"Unique Boutique",
    "wof:placetype":"venue"
},
  "geometry": {"coordinates":[-81.801903,26.132873],"type":"Point"}
}