{
  "type": "Feature",
  "properties": {
    "iso:country":"US",
    "sg:address":"9940 SW 168th Ter",
    "sg:city":"Miami",
    "sg:classifiers":[
        {
            "category":"Retail",
            "subcategory":"Auto Repair",
            "type":"Services"
        }
    ],
    "sg:phone":"+1 305 233 9300",
    "sg:postcode":"33157",
    "sg:province":"FL",
    "sg:tags":[
        "body",
        "shop"
    ],
    "wof:name":"Active Autowerke",
    "wof:placetype":"venue"
},
  "geometry": {"coordinates":[-80.352203,25.613199],"type":"Point"}
}