{
  "type": "Feature",
  "properties": {
    "iso:country":"US",
    "sg:address":"5659 Red Bug Lake Rd",
    "sg:city":"Winter Springs",
    "sg:classifiers":[
        {
            "category":"Health Services",
            "subcategory":"Dentist",
            "type":"Services"
        }
    ],
    "sg:phone":"+1 407 696 6700",
    "sg:postcode":"32708",
    "sg:province":"FL",
    "sg:website":"theadvanceddental.com",
    "wof:name":"Advanced Dental Care",
    "wof:placetype":"venue"
},
  "geometry": {"coordinates":[-81.26973599999999,28.647557],"type":"Point"}
}