{
  "type": "Feature",
  "properties": {
    "iso:country":"US",
    "sg:address":"23220 Avacado Ave",
    "sg:city":"Port Charlotte",
    "sg:classifiers":[
        {
            "category":"Organizations",
            "subcategory":"Religious Organization",
            "type":"Services"
        }
    ],
    "sg:phone":"+1 941 766 1971",
    "sg:postcode":"33980",
    "sg:province":"FL",
    "sg:tags":[
        "church"
    ],
    "wof:name":"World Of Pentecost Church",
    "wof:placetype":"venue"
},
  "geometry": {"coordinates":[-82.06725299999999,27.002875],"type":"Point"}
}