{
  "type": "Feature",
  "properties": {
    "addr:full":"19250 SW 87th Ave Miami FL 33157",
    "addr:housenumber":"19250",
    "addr:postcode":"33157",
    "addr:street":"Sw 87Th Ave",
    "iso:country":"US",
    "sg:address":"19250 SW 87th Ave",
    "sg:city":"Miami",
    "sg:classifiers":[
        {
            "category":"Restaurant",
            "type":"Food & Drink"
        }
    ],
    "sg:phone":"+1 305 251 4309",
    "sg:postcode":"33157",
    "sg:province":"FL",
    "sg:tags":[
        "eating"
    ],
    "wof:name":"Thai Folk Art From Menca Inc",
    "wof:placetype":"venue"
},
  "geometry": {"coordinates":[-80.332004,25.587502],"type":"Point"}
}