{
  "type": "Feature",
  "properties": {
    "iso:country":"US",
    "sg:address":"303 SE 17th St 309-217",
    "sg:city":"Ocala",
    "sg:classifiers":[
        {
            "category":"Health Services",
            "subcategory":"Clinic",
            "type":"Services"
        },
        {
            "category":"Health Services",
            "subcategory":"Health Practitioner",
            "type":"Services"
        }
    ],
    "sg:phone":"+1 352 629 0025",
    "sg:postcode":"34471",
    "sg:province":"FL",
    "sg:tags":[
        "therapist",
        "therapy",
        "physical"
    ],
    "wof:name":"Advanced Physical Therapy Of Central Florida, Inc.",
    "wof:placetype":"venue"
},
  "geometry": {"coordinates":[-82.134359,29.171679],"type":"Point"}
}