{
  "type": "Feature",
  "properties": {
    "iso:country":"US",
    "sg:address":"3201 SW 87th Ct",
    "sg:city":"Miami",
    "sg:classifiers":[
        {
            "category":"Health Services",
            "subcategory":"Doctor",
            "type":"Services"
        }
    ],
    "sg:phone":"+1 305 220 2606",
    "sg:postcode":"33165",
    "sg:province":"FL",
    "sg:tags":[
        "physician",
        "surgeon"
    ],
    "wof:name":"Vidal N Lopez MD",
    "wof:placetype":"venue"
},
  "geometry": {"coordinates":[-80.336522,25.738515],"type":"Point"}
}