{
  "type": "Feature",
  "properties": {
    "iso:country":"US",
    "sg:address":"15369 S Dixie Hwy",
    "sg:city":"Miami",
    "sg:classifiers":[
        {
            "category":"Shopping",
            "subcategory":"Bicycles & Sporting Goods",
            "type":"Retail Goods"
        }
    ],
    "sg:phone":"+1 305 378 6433",
    "sg:postcode":"33157",
    "sg:province":"FL",
    "sg:website":"www.alfsgolf.com",
    "wof:name":"Alf's Golf Shop",
    "wof:placetype":"venue"
},
  "geometry": {"coordinates":[-80.34139999999999,25.6276],"type":"Point"}
}