{
  "type": "Feature",
  "properties": {
    "addr:full":"131 Ellis Dr Tavernier FL 33070",
    "addr:housenumber":"131",
    "addr:postcode":"33070",
    "addr:street":"Ellis Dr",
    "iso:country":"US",
    "sg:address":"131 Ellis Dr",
    "sg:city":"Tavernier",
    "sg:classifiers":[
        {
            "category":"Home & Garden",
            "subcategory":"Furniture",
            "type":"Retail Goods"
        }
    ],
    "sg:phone":"+1 305 852 8611",
    "sg:postcode":"33070",
    "sg:province":"FL",
    "sg:tags":[
        "builder",
        "custom"
    ],
    "wof:name":"Back Country Boat Works",
    "wof:placetype":"venue"
},
  "geometry": {"coordinates":[-80.513178,25.015563],"type":"Point"}
}