{
  "type": "Feature",
  "properties": {
    "iso:country":"US",
    "sg:address":"11222 Quail Roost Dr",
    "sg:city":"Miami",
    "sg:classifiers":[
        {
            "category":"Banks & Credit Unions",
            "subcategory":"Bank",
            "type":"Services"
        }
    ],
    "sg:phone":"+1 786 573 5454",
    "sg:postcode":"33157",
    "sg:province":"FL",
    "wof:name":"Faa Credit Union",
    "wof:placetype":"venue"
},
  "geometry": {"coordinates":[-80.375552,25.594581],"type":"Point"}
}