{
  "type": "Feature",
  "properties": {
    "iso:country":"US",
    "sg:address":"6340 46th Ave N",
    "sg:city":"Kenneth City",
    "sg:classifiers":[
        {
            "category":"Social Services",
            "subcategory":"Adult Care",
            "type":"Services"
        },
        {
            "category":"Health Services",
            "subcategory":"Nursing And Care Facility",
            "type":"Services"
        }
    ],
    "sg:phone":"+1 727 547 9566",
    "sg:postcode":"33709",
    "sg:province":"FL",
    "sg:tags":[
        "residential"
    ],
    "wof:name":"Lexington Terrace",
    "wof:placetype":"venue"
},
  "geometry": {"coordinates":[-82.724644,27.813578],"type":"Point"}
}