{
  "type": "Feature",
  "properties": {
    "iso:country":"US",
    "sg:address":"120 N Central Ave",
    "sg:city":"Oviedo",
    "sg:classifiers":[
        {
            "category":"Organizations",
            "subcategory":"Non-profit Organization",
            "type":"Services"
        }
    ],
    "sg:phone":"+1 407 366 5046",
    "sg:postcode":"32765",
    "sg:province":"FL",
    "sg:tags":[
        "information",
        "alcoholism",
        "treatment"
    ],
    "wof:name":"Human Svc & Resources",
    "wof:placetype":"venue"
},
  "geometry": {"coordinates":[-81.208369,28.672301],"type":"Point"}
}