{
  "type": "Feature",
  "properties": {
    "iso:country":"US",
    "sg:address":"14 Anchor Dr",
    "sg:city":"Key Largo",
    "sg:classifiers":[
        {
            "category":"Real Estate",
            "subcategory":"Real Estate Operator",
            "type":"Services"
        }
    ],
    "sg:phone":"+1 305 367 8003",
    "sg:postcode":"33037",
    "sg:province":"FL",
    "sg:tags":[
        "condominium"
    ],
    "wof:name":"No Greef LLC",
    "wof:placetype":"venue"
},
  "geometry": {"coordinates":[-80.274261,25.323019],"type":"Point"}
}