{
  "type": "Feature",
  "properties": {
    "iso:country":"US",
    "sg:address":"541 NE Blvd",
    "sg:city":"Gainesville",
    "sg:classifiers":[
        {
            "category":"Wholesale",
            "subcategory":"Durable Goods & Equipment",
            "type":"Manufacturing & Wholesale Goods"
        }
    ],
    "sg:phone":"+1 352 372 4100",
    "sg:postcode":"32601",
    "sg:province":"FL",
    "sg:tags":[
        "instrumentation",
        "scientific"
    ],
    "wof:name":"Advanced Surface Tech Inc",
    "wof:placetype":"venue"
},
  "geometry": {"coordinates":[-82.319529,29.65571],"type":"Point"}
}