{
  "type": "Feature",
  "properties": {
    "iso:country":"US",
    "sg:address":"530 N Palmetto Ave",
    "sg:city":"Sanford",
    "sg:classifiers":[
        {
            "category":"Restaurant",
            "type":"Food & Drink"
        }
    ],
    "sg:menulink":"http://www.allmenus.com/fl/sanford/262309-wolfys/menu/",
    "sg:phone":"+1 407 322 2150",
    "sg:postcode":"32771",
    "sg:province":"FL",
    "sg:tags":[
        "american"
    ],
    "wof:name":"Wolfys",
    "wof:placetype":"venue"
},
  "geometry": {"coordinates":[-81.26497000000001,28.816278],"type":"Point"}
}