{
  "type": "Feature",
  "properties": {
    "addr:full":"528 Palm St West Palm Beach FL 33401",
    "addr:housenumber":"528",
    "addr:postcode":"33401",
    "addr:street":"Palm St",
    "iso:country":"US",
    "sg:address":"528 Palm St",
    "sg:city":"West Palm Beach",
    "sg:classifiers":[
        {
            "category":"Professional",
            "type":"Services"
        }
    ],
    "sg:phone":"+1 561 659 8031",
    "sg:postcode":"33401",
    "sg:province":"FL",
    "wof:name":"Historic West Palm Beach Inc",
    "wof:placetype":"venue"
},
  "geometry": {"coordinates":[-80.056805,26.699285],"type":"Point"}
}