{
  "type": "Feature",
  "properties": {
    "addr:full":"445 NE 8th Ave Ocala FL 34470",
    "addr:housenumber":"445",
    "addr:postcode":"34470",
    "addr:street":"Ne 8Th Ave",
    "iso:country":"US",
    "sg:address":"445 NE 8th Ave",
    "sg:city":"Ocala",
    "sg:classifiers":[
        {
            "category":"Professional",
            "subcategory":"Lawyer & Legal Services",
            "type":"Services"
        }
    ],
    "sg:phone":"+1 352 732 8622",
    "sg:postcode":"34470",
    "sg:province":"FL",
    "sg:tags":[
        "attorney"
    ],
    "wof:name":"Landt Wiechens Lapeer & Ayres",
    "wof:placetype":"venue"
},
  "geometry": {"coordinates":[-82.129806,29.191557],"type":"Point"}
}