{
  "type": "Feature",
  "properties": {
    "iso:country":"US",
    "sg:address":"8000 Governors Square Blvd",
    "sg:city":"Hialeah",
    "sg:classifiers":[
        {
            "category":"Travel",
            "subcategory":"Travel Agent",
            "type":"Entertainment"
        }
    ],
    "sg:phone":"+1 305 512 7280",
    "sg:postcode":"33016",
    "sg:province":"FL",
    "sg:tags":[
        "agency",
        "bureau"
    ],
    "wof:name":"Maxxium Travel Retail Americas",
    "wof:placetype":"venue"
},
  "geometry": {"coordinates":[-80.330291,25.907739],"type":"Point"}
}