{
  "type": "Feature",
  "properties": {
    "iso:country":"US",
    "sg:address":"3808 Tamiami Trl",
    "sg:city":"Sarasota",
    "sg:classifiers":[
        {
            "category":"Professional",
            "subcategory":"Management & Consulting",
            "type":"Services"
        }
    ],
    "sg:phone":"+1 941 358 6488",
    "sg:postcode":"34234",
    "sg:province":"FL",
    "sg:tags":[
        "consultant",
        "training"
    ],
    "wof:name":"Medical Training School Inc",
    "wof:placetype":"venue"
},
  "geometry": {"coordinates":[-82.552103,27.368619],"type":"Point"}
}