{
  "type": "Feature",
  "properties": {
    "iso:country":"US",
    "sg:address":"1306 S Dale Mabry Hwy",
    "sg:city":"Tampa",
    "sg:classifiers":[
        {
            "category":"Shopping",
            "subcategory":"Florist",
            "type":"Retail Goods"
        }
    ],
    "sg:phone":"+1 813 254 6261",
    "sg:postcode":"33629",
    "sg:province":"FL",
    "sg:website":"www.palmaceiaflorist.com",
    "wof:name":"Palma Ceia Florist",
    "wof:placetype":"venue"
},
  "geometry": {"coordinates":[-82.505746,27.931209],"type":"Point"}
}