{
  "type": "Feature",
  "properties": {
    "iso:country":"US",
    "sg:address":"169 Southwinds Dr",
    "sg:city":"Sanibel",
    "sg:classifiers":[
        {
            "category":"Shopping",
            "subcategory":"Gifts & Souvenirs",
            "type":"Retail Goods"
        }
    ],
    "sg:phone":"+1 239 472 9166",
    "sg:postcode":"33957",
    "sg:province":"FL",
    "sg:tags":[
        "shop"
    ],
    "wof:name":"Ile Crocodile Inc",
    "wof:placetype":"venue"
},
  "geometry": {"coordinates":[-82.06833,26.426921],"type":"Point"}
}