{
  "type": "Feature",
  "properties": {
    "iso:country":"US",
    "sg:address":"3773 Central Ave",
    "sg:city":"St Petersburg",
    "sg:classifiers":[
        {
            "category":"Insurance",
            "subcategory":"Insurance Agent",
            "type":"Services"
        }
    ],
    "sg:phone":"+1 727 327 1218",
    "sg:postcode":"33713",
    "sg:province":"FL",
    "wof:name":"PSL Corp",
    "wof:placetype":"venue"
},
  "geometry": {"coordinates":[-82.683944,27.771065],"type":"Point"}
}