{
  "type": "Feature",
  "properties": {
    "addr:full":"223 SW 42nd St Cape Coral FL 33914",
    "addr:housenumber":"223",
    "addr:postcode":"33914",
    "addr:street":"Sw 42Nd St",
    "iso:country":"US",
    "sg:address":"223 SW 42nd St",
    "sg:city":"Cape Coral",
    "sg:classifiers":[
        {
            "category":"Building & Trades",
            "subcategory":"Electrical",
            "type":"Services"
        },
        {
            "category":"Wholesale",
            "subcategory":"Electrical",
            "type":"Manufacturing & Wholesale Goods"
        }
    ],
    "sg:phone":"+1 239 549 4078",
    "sg:postcode":"33914",
    "sg:province":"FL",
    "sg:tags":[
        "control",
        "security",
        "system",
        "contractor"
    ],
    "wof:name":"Custom Wiring Specialities",
    "wof:placetype":"venue"
},
  "geometry": {"coordinates":[-81.978903,26.574452],"type":"Point"}
}