{
  "type": "Feature",
  "properties": {
    "addr:full":"65 Hinson Cir Havana FL 32333",
    "addr:housenumber":"65",
    "addr:postcode":"32333",
    "addr:street":"Hinson Cir",
    "iso:country":"US",
    "sg:address":"65 Hinson Cir",
    "sg:city":"Havana",
    "sg:classifiers":[
        {
            "category":"Personal",
            "subcategory":"Beauty Salon",
            "type":"Services"
        }
    ],
    "sg:phone":"+1 850 539 1115",
    "sg:postcode":"32333",
    "sg:province":"FL",
    "wof:name":"Golden Hair Salon",
    "wof:placetype":"venue"
},
  "geometry": {"coordinates":[-84.414265,30.655121],"type":"Point"}
}