{
  "type": "Feature",
  "properties": {
    "addr:full":"177 E Mitchell Hammock Rd Oviedo FL 32765",
    "addr:housenumber":"177",
    "addr:postcode":"32765",
    "addr:street":"E Mitchell Hammock Rd",
    "iso:country":"US",
    "sg:address":"177 E Mitchell Hammock Rd",
    "sg:city":"Oviedo",
    "sg:classifiers":[
        {
            "category":"Personal",
            "subcategory":"Beauty Salon",
            "type":"Services"
        }
    ],
    "sg:phone":"+1 407 971 2999",
    "sg:postcode":"32765",
    "sg:province":"FL",
    "wof:name":"Esbi II International Sal",
    "wof:placetype":"venue"
},
  "geometry": {"coordinates":[-81.206484,28.655857],"type":"Point"}
}