{
  "type": "Feature",
  "properties": {
    "iso:country":"US",
    "sg:address":"20685 NE 2nd Ave",
    "sg:city":"Miami",
    "sg:classifiers":[
        {
            "category":"Retail",
            "subcategory":"Laundry & Dry Cleaning",
            "type":"Services"
        }
    ],
    "sg:phone":"+1 786 478 5891",
    "sg:postcode":"33179",
    "sg:province":"FL",
    "sg:tags":[
        "commercial"
    ],
    "wof:name":"K 4 Cyber Inc.",
    "wof:placetype":"venue"
},
  "geometry": {"coordinates":[-80.19817,25.965539],"type":"Point"}
}