{
  "type": "Feature",
  "properties": {
    "iso:country":"US",
    "sg:address":"605 Brickell",
    "sg:city":"Miami",
    "sg:classifiers":[
        {
            "category":"Restaurant",
            "type":"Food & Drink"
        }
    ],
    "sg:menulink":"http://www.allmenus.com/fl/miami/21676-brasserie-brickell-key/menu/",
    "sg:phone":"+1 305 577 0907",
    "sg:postcode":"33131",
    "sg:province":"FL",
    "sg:tags":[
        "italian"
    ],
    "wof:name":"Brasserie Brickell Key",
    "wof:placetype":"venue"
},
  "geometry": {"coordinates":[-80.18518400000001,25.766543],"type":"Point"}
}