{
  "type": "Feature",
  "properties": {
    "iso:country":"US",
    "sg:address":"3315 Tamiami Trl",
    "sg:city":"Punta Gorda",
    "sg:classifiers":[
        {
            "category":"Manufacturing",
            "subcategory":"Metals",
            "type":"Manufacturing & Wholesale Goods"
        }
    ],
    "sg:phone":"+1 941 637 1233",
    "sg:postcode":"33950",
    "sg:province":"FL",
    "sg:tags":[
        "brass"
    ],
    "wof:name":"Harmon Brass Products",
    "wof:placetype":"venue"
},
  "geometry": {"coordinates":[-82.04580300000001,26.914124],"type":"Point"}
}