{
  "type": "Feature",
  "properties": {
    "addr:full":"6134 NW 74th Ave Miami FL 33166",
    "addr:housenumber":"6134",
    "addr:postcode":"33166",
    "addr:street":"Nw 74Th Ave",
    "iso:country":"US",
    "sg:address":"6134 NW 74th Ave",
    "sg:city":"Miami",
    "sg:classifiers":[
        {
            "category":"Manufacturing",
            "subcategory":"Paper Products",
            "type":"Manufacturing & Wholesale Goods"
        }
    ],
    "sg:phone":"+1 305 594 5799",
    "sg:postcode":"33166",
    "sg:province":"FL",
    "sg:tags":[
        "bag"
    ],
    "wof:name":"Miami Paper & Plastic Corp",
    "wof:placetype":"venue"
},
  "geometry": {"coordinates":[-80.31787199999999,25.83073],"type":"Point"}
}