{
  "type": "Feature",
  "properties": {
    "addr:full":"230 Power Ct Sanford FL 32771",
    "addr:housenumber":"230",
    "addr:postcode":"32771",
    "addr:street":"Power Ct",
    "iso:country":"US",
    "sg:address":"230 Power Ct",
    "sg:city":"Sanford",
    "sg:classifiers":[
        {
            "category":"Wholesale",
            "subcategory":"Machinery & Supplies",
            "type":"Manufacturing & Wholesale Goods"
        },
        {
            "category":"Building & Trades",
            "subcategory":"Construction",
            "type":"Services"
        }
    ],
    "sg:phone":"+1 407 330 9612",
    "sg:postcode":"32771",
    "sg:province":"FL",
    "sg:tags":[
        "rug",
        "carpet",
        "cleaning",
        "contractor"
    ],
    "wof:name":"Decon Environmental & Engineer",
    "wof:placetype":"venue"
},
  "geometry": {"coordinates":[-81.329705,28.815541],"type":"Point"}
}