{
  "type": "Feature",
  "properties": {
    "addr:full":"1800 E Colonial Dr Orlando FL 32803",
    "addr:housenumber":"1800",
    "addr:postcode":"32803",
    "addr:street":"E Colonial Dr",
    "iso:country":"US",
    "sg:address":"1800 E Colonial Dr",
    "sg:city":"Orlando",
    "sg:classifiers":[
        {
            "category":"Home & Garden",
            "subcategory":"Furniture",
            "type":"Retail Goods"
        }
    ],
    "sg:phone":"+1 407 893 5200",
    "sg:postcode":"32803",
    "sg:province":"FL",
    "wof:name":"World Import Half Price Furn",
    "wof:placetype":"venue"
},
  "geometry": {"coordinates":[-81.35723299999999,28.553141],"type":"Point"}
}