{
  "type": "Feature",
  "properties": {
    "addr:full":"14376 Beach Blvd Jacksonville FL 32250",
    "addr:housenumber":"14376",
    "addr:postcode":"32250",
    "addr:street":"Beach Blvd",
    "iso:country":"US",
    "sg:address":"14376 Beach Blvd",
    "sg:city":"Jacksonville",
    "sg:classifiers":[
        {
            "category":"Restaurant",
            "type":"Food & Drink"
        }
    ],
    "sg:phone":"+1 904 223 3900",
    "sg:postcode":"32250",
    "sg:province":"FL",
    "sg:tags":[
        "eating"
    ],
    "sg:website":"www.pizzahut.com",
    "wof:name":"Pizza Hut",
    "wof:placetype":"venue"
},
  "geometry": {"coordinates":[-81.43433400000001,30.287854],"type":"Point"}
}