{
  "type": "Feature",
  "properties": {
    "iso:country":"US",
    "sg:address":"202 NW 9th Ave",
    "sg:city":"Boynton Beach",
    "sg:classifiers":[
        {
            "category":"Organizations",
            "subcategory":"Religious Organization",
            "type":"Services"
        }
    ],
    "sg:phone":"+1 561 733 9346",
    "sg:postcode":"33435",
    "sg:province":"FL",
    "sg:tags":[
        "church"
    ],
    "wof:name":"Deliverance Holy Temple",
    "wof:placetype":"venue"
},
  "geometry": {"coordinates":[-80.06742,26.534642],"type":"Point"}
}