{
  "type": "Feature",
  "properties": {
    "iso:country":"US",
    "sg:address":"11979 SW 81st Ln",
    "sg:city":"Miami",
    "sg:classifiers":[
        {
            "category":"Home & Garden",
            "subcategory":"Building Materials",
            "type":"Retail Goods"
        }
    ],
    "sg:phone":"+1 603 888 6806",
    "sg:postcode":"33183",
    "sg:province":"FL",
    "sg:tags":[
        "window",
        "wood"
    ],
    "wof:name":"Thermocom, Incorporated",
    "wof:placetype":"venue"
},
  "geometry": {"coordinates":[-80.38734599999999,25.692051],"type":"Point"}
}