{
  "type": "Feature",
  "properties": {
    "addr:full":"1423 Johnson Rd Auburndale FL 33823",
    "addr:housenumber":"1423",
    "addr:postcode":"33823",
    "addr:street":"Johnson Rd",
    "iso:country":"US",
    "sg:address":"1423 Johnson Rd",
    "sg:city":"Auburndale",
    "sg:classifiers":[
        {
            "category":"Building & Trades",
            "subcategory":"Construction",
            "type":"Services"
        }
    ],
    "sg:phone":"+1 863 984 1345",
    "sg:postcode":"33823",
    "sg:province":"FL",
    "sg:tags":[
        "roofing",
        "contractor"
    ],
    "wof:name":"Sun State Roofing & Sheet Inc",
    "wof:placetype":"venue"
},
  "geometry": {"coordinates":[-81.822351,28.119204],"type":"Point"}
}