{
  "type": "Feature",
  "properties": {
    "iso:country":"US",
    "sg:address":"7300 SW 41st St",
    "sg:city":"Miami",
    "sg:classifiers":[
        {
            "category":"Freight",
            "type":"Transportation"
        }
    ],
    "sg:phone":"+1 305 266 8300",
    "sg:postcode":"33155",
    "sg:province":"FL",
    "sg:tags":[
        "warehouse"
    ],
    "wof:name":"Gables Honda",
    "wof:placetype":"venue"
},
  "geometry": {"coordinates":[-80.31503499999999,25.732291],"type":"Point"}
}