{
  "type": "Feature",
  "properties": {
    "addr:full":"3601 Gatlin Rd Milton FL 32583",
    "addr:housenumber":"3601",
    "addr:postcode":"32583",
    "addr:street":"Gatlin Rd",
    "iso:country":"US",
    "sg:address":"3601 Gatlin Rd",
    "sg:city":"Milton",
    "sg:classifiers":[
        {
            "category":"Building & Trades",
            "subcategory":"Construction",
            "type":"Services"
        }
    ],
    "sg:phone":"+1 850 994 0897",
    "sg:postcode":"32583",
    "sg:province":"FL",
    "sg:tags":[
        "concrete",
        "contractor"
    ],
    "wof:name":"Mike Kaylor Concrete LLC",
    "wof:placetype":"venue"
},
  "geometry": {"coordinates":[-87.103948,30.568341],"type":"Point"}
}