{
  "type": "Feature",
  "properties": {
    "addr:full":"13726 75th Ave Seminole FL 33776",
    "addr:housenumber":"13726",
    "addr:postcode":"33776",
    "addr:street":"75Th Ave",
    "iso:country":"US",
    "sg:address":"13726 75th Ave",
    "sg:city":"Seminole",
    "sg:classifiers":[
        {
            "category":"Shopping",
            "subcategory":"Computers & Home Electronics",
            "type":"Retail Goods"
        }
    ],
    "sg:phone":"+1 727 393 6421",
    "sg:postcode":"33776",
    "sg:province":"FL",
    "wof:name":"Lz Computers",
    "wof:placetype":"venue"
},
  "geometry": {"coordinates":[-82.829776,27.840804],"type":"Point"}
}