{
  "type": "Feature",
  "properties": {
    "addr:full":"864 South Sun Drive Lake Mary FL 32746",
    "addr:housenumber":"864",
    "addr:postcode":"32746",
    "addr:street":"South Sun Drive",
    "iso:country":"US",
    "sg:address":"864 South Sun Drive",
    "sg:city":"Lake Mary",
    "sg:classifiers":[
        {
            "category":"Food & Beverages",
            "subcategory":"Bakery",
            "type":"Retail Goods"
        }
    ],
    "sg:phone":"+1 407 936 3270",
    "sg:postcode":"32746",
    "sg:province":"FL",
    "sg:tags":[
        "sandwich"
    ],
    "sg:website":"www.panerabread.com",
    "wof:name":"Panera Bread",
    "wof:placetype":"venue"
},
  "geometry": {"coordinates":[-81.352687,28.754981],"type":"Point"}
}