{
  "type": "Feature",
  "properties": {
    "addr:full":"1815 NW North River Dr Miami FL 33125",
    "addr:housenumber":"1815",
    "addr:postcode":"33125",
    "addr:street":"Nw North River Dr",
    "iso:country":"US",
    "sg:address":"1815 NW North River Dr",
    "sg:city":"Miami",
    "sg:classifiers":[
        {
            "category":"Sports & Exercise",
            "subcategory":"Sports Center",
            "type":"Entertainment"
        },
        {
            "category":"Organizations",
            "subcategory":"Community Association",
            "type":"Services"
        }
    ],
    "sg:phone":"+1 305 324 5565",
    "sg:postcode":"33125",
    "sg:province":"FL",
    "sg:tags":[
        "club",
        "amateur",
        "team"
    ],
    "wof:name":"Casa De Los De Santa Martha Ortigueira Inc",
    "wof:placetype":"venue"
},
  "geometry": {"coordinates":[-80.225403,25.7876],"type":"Point"}
}