{
  "type": "Feature",
  "properties": {
    "iso:country":"US",
    "sg:address":"513 Parkwoods Ct",
    "sg:city":"Altamonte Springs",
    "sg:classifiers":[
        {
            "category":"Professional",
            "subcategory":"Management & Consulting",
            "type":"Services"
        }
    ],
    "sg:phone":"+1 407 774 0672",
    "sg:postcode":"32714",
    "sg:province":"FL",
    "wof:name":"Rw Mindrup & Associates",
    "wof:placetype":"venue"
},
  "geometry": {"coordinates":[-81.40968700000001,28.671751],"type":"Point"}
}