{
  "type": "Feature",
  "properties": {
    "addr:full":"2880 Race Track Rd Jacksonville FL 32259",
    "addr:housenumber":"2880",
    "addr:postcode":"32259",
    "addr:street":"Race Track Rd",
    "iso:country":"US",
    "sg:address":"2880 Race Track Rd",
    "sg:city":"Jacksonville",
    "sg:classifiers":[
        {
            "category":"Restaurant",
            "type":"Food & Drink"
        }
    ],
    "sg:phone":"+1 904 287 3664",
    "sg:postcode":"32259",
    "sg:province":"FL",
    "wof:name":"Wendy's",
    "wof:placetype":"venue"
},
  "geometry": {"coordinates":[-81.58558499999999,30.113386],"type":"Point"}
}