{
  "type": "Feature",
  "properties": {
    "addr:full":"39 S Federal Hwy Deerfield Beach FL 33441",
    "addr:housenumber":"39",
    "addr:postcode":"33441",
    "addr:street":"S Federal Hwy",
    "iso:country":"US",
    "sg:address":"39 S Federal Hwy",
    "sg:city":"Deerfield Beach",
    "sg:classifiers":[
        {
            "category":"Shopping",
            "subcategory":"Used Merchandise",
            "type":"Retail Goods"
        }
    ],
    "sg:phone":"+1 954 596 5059",
    "sg:postcode":"33441",
    "sg:province":"FL",
    "wof:name":"Inner Wisdom Bookstand",
    "wof:placetype":"venue"
},
  "geometry": {"coordinates":[-80.091245,26.315747],"type":"Point"}
}