{
  "type": "Feature",
  "properties": {
    "addr:full":"1044 Pine Ridge Rd Naples FL 34108",
    "addr:housenumber":"1044",
    "addr:postcode":"34108",
    "addr:street":"Pine Ridge Rd",
    "iso:country":"US",
    "sg:address":"1044 Pine Ridge Rd",
    "sg:city":"Naples",
    "sg:classifiers":[
        {
            "category":"Personal",
            "subcategory":"Beauty Salon",
            "type":"Services"
        }
    ],
    "sg:phone":"+1 239 403 9797",
    "sg:postcode":"34108",
    "sg:province":"FL",
    "wof:name":"Manuela's European Salon & Spa",
    "wof:placetype":"venue"
},
  "geometry": {"coordinates":[-81.79920300000001,26.21118],"type":"Point"}
}