{
  "type": "Feature",
  "properties": {
    "iso:country":"US",
    "sg:address":"2340 Soutel Dr",
    "sg:city":"Jacksonville",
    "sg:classifiers":[
        {
            "category":"Social Services",
            "subcategory":"Child Care",
            "type":"Services"
        }
    ],
    "sg:phone":"+1 904 766 7685",
    "sg:postcode":"32208",
    "sg:province":"FL",
    "wof:name":"Crown Of Glory Enterprises Inc",
    "wof:placetype":"venue"
},
  "geometry": {"coordinates":[-81.69273699999999,30.407615],"type":"Point"}
}