{
  "type": "Feature",
  "properties": {
    "addr:full":"6360 Sunset Dr Miami FL 33143",
    "addr:housenumber":"6360",
    "addr:postcode":"33143",
    "addr:street":"Sunset Dr",
    "iso:country":"US",
    "sg:address":"6360 Sunset Dr",
    "sg:city":"Miami",
    "sg:classifiers":[
        {
            "category":"Health Services",
            "subcategory":"Optometrist",
            "type":"Services"
        },
        {
            "category":"Shopping",
            "subcategory":"Optician",
            "type":"Retail Goods"
        }
    ],
    "sg:phone":"+1 305 667 1407",
    "sg:postcode":"33143",
    "sg:province":"FL",
    "sg:tags":[
        "eyewear"
    ],
    "wof:name":"Judith Flores-Guerra O D",
    "wof:placetype":"venue"
},
  "geometry": {"coordinates":[-80.2967,25.704],"type":"Point"}
}