{
  "type": "Feature",
  "properties": {
    "iso:country":"US",
    "sg:address":"1242 Bell Ave",
    "sg:city":"Fort Pierce",
    "sg:classifiers":[
        {
            "category":"Building & Trades",
            "subcategory":"Construction",
            "type":"Services"
        }
    ],
    "sg:phone":"+1 772 489 6117",
    "sg:postcode":"34982",
    "sg:province":"FL",
    "sg:tags":[
        "water",
        "well",
        "drilling"
    ],
    "wof:name":"Scott's Drilling Inc",
    "wof:placetype":"venue"
},
  "geometry": {"coordinates":[-80.337368,27.39634],"type":"Point"}
}