{
  "type": "Feature",
  "properties": {
    "iso:country":"US",
    "sg:address":"313 S Ridgewood Dr",
    "sg:city":"Sebring",
    "sg:classifiers":[
        {
            "category":"Shopping",
            "subcategory":"Books",
            "type":"Retail Goods"
        }
    ],
    "sg:phone":"+1 863 382 2697",
    "sg:postcode":"33870",
    "sg:province":"FL",
    "sg:tags":[
        "dealer"
    ],
    "wof:name":"Kidz Treehouse Bookstore",
    "wof:placetype":"venue"
},
  "geometry": {"coordinates":[-81.44205700000001,27.492845],"type":"Point"}
}