{
  "type": "Feature",
  "properties": {
    "iso:country":"US",
    "sg:address":"226 Apollo Beach Blvd",
    "sg:city":"Apollo Beach",
    "sg:classifiers":[
        {
            "category":"Food & Beverages",
            "subcategory":"Meat & Fish",
            "type":"Retail Goods"
        }
    ],
    "sg:phone":"+1 813 645 2379",
    "sg:postcode":"33572",
    "sg:province":"FL",
    "sg:tags":[
        "grocery"
    ],
    "wof:name":"Apollo Meats",
    "wof:placetype":"venue"
},
  "geometry": {"coordinates":[-82.394581,27.771575],"type":"Point"}
}