{
  "type": "Feature",
  "properties": {
    "iso:country":"US",
    "sg:address":"7780 NW 53rd St",
    "sg:city":"Miami",
    "sg:classifiers":[
        {
            "category":"Professional",
            "type":"Services"
        },
        {
            "category":"Retail",
            "subcategory":"Animal Services",
            "type":"Services"
        }
    ],
    "sg:phone":"+1 305 471 9557",
    "sg:postcode":"33166",
    "sg:province":"FL",
    "sg:tags":[
        "quarantine",
        "establishment",
        "monkey",
        "for",
        "facility"
    ],
    "wof:name":"Primate Products Inc",
    "wof:placetype":"venue"
},
  "geometry": {"coordinates":[-80.322413,25.821608],"type":"Point"}
}