{
  "type": "Feature",
  "properties": {
    "iso:country":"US",
    "sg:address":"350 N North Lake Blvd",
    "sg:city":"Altamonte Springs",
    "sg:classifiers":[
        {
            "category":"Travel",
            "subcategory":"Travel Agent",
            "type":"Entertainment"
        }
    ],
    "sg:phone":"+1 407 332 0707",
    "sg:postcode":"32701",
    "sg:province":"FL",
    "wof:name":"US Airways",
    "wof:placetype":"venue"
},
  "geometry": {"coordinates":[-81.380921,28.668204],"type":"Point"}
}