{
  "type": "Feature",
  "properties": {
    "addr:full":"9208 Martini Dr Hudson FL 34667",
    "addr:housenumber":"9208",
    "addr:postcode":"34667",
    "addr:street":"Martini Dr",
    "iso:country":"US",
    "sg:address":"9208 Martini Dr",
    "sg:city":"Hudson",
    "sg:classifiers":[
        {
            "category":"Manufacturing",
            "subcategory":"Printing",
            "type":"Manufacturing & Wholesale Goods"
        }
    ],
    "sg:phone":"+1 727 697 2622",
    "sg:postcode":"34667",
    "sg:province":"FL",
    "sg:tags":[
        "typesetting"
    ],
    "wof:name":"Tropical Sunset Typesetting",
    "wof:placetype":"venue"
},
  "geometry": {"coordinates":[-82.66274,28.402269],"type":"Point"}
}