{
  "type": "Feature",
  "properties": {
    "iso:country":"US",
    "sg:address":"1765 Tree Blvd",
    "sg:city":"St Augustine",
    "sg:classifiers":[
        {
            "category":"Utilities",
            "subcategory":"Mobile Phone",
            "type":"Services"
        }
    ],
    "sg:phone":"+1 904 826 0229",
    "sg:postcode":"32086",
    "sg:province":"FL",
    "sg:tags":[
        "telephone",
        "cellular"
    ],
    "wof:name":"Maycom Communications",
    "wof:placetype":"venue"
},
  "geometry": {"coordinates":[-81.331537,29.868326],"type":"Point"}
}