{
  "type": "Feature",
  "properties": {
    "iso:country":"US",
    "sg:address":"9500 Toni Dr",
    "sg:city":"Miami",
    "sg:classifiers":[
        {
            "category":"Shopping",
            "subcategory":"Clothing, Apparel, & Fashions",
            "type":"Retail Goods"
        }
    ],
    "sg:phone":"+1 305 233 4269",
    "sg:postcode":"33157",
    "sg:province":"FL",
    "sg:tags":[
        "garment"
    ],
    "wof:name":"J T Apparel Inc",
    "wof:placetype":"venue"
},
  "geometry": {"coordinates":[-80.345991,25.587417],"type":"Point"}
}