{
  "type": "Feature",
  "properties": {
    "addr:full":"1960 Blackfoot Trl St Cloud FL 34771",
    "addr:housenumber":"1960",
    "addr:postcode":"34771",
    "addr:street":"Blackfoot Trl",
    "iso:country":"US",
    "sg:address":"1960 Blackfoot Trl",
    "sg:city":"St Cloud",
    "sg:classifiers":[
        {
            "category":"Retail",
            "subcategory":"Repair Shop",
            "type":"Services"
        }
    ],
    "sg:phone":"+1 407 892 7445",
    "sg:postcode":"34771",
    "sg:province":"FL",
    "sg:tags":[
        "equipment",
        "telephone",
        "system"
    ],
    "wof:name":"Quality Phone Svc Of Florida",
    "wof:placetype":"venue"
},
  "geometry": {"coordinates":[-81.149548,28.249424],"type":"Point"}
}