{
  "type": "Feature",
  "properties": {
    "addr:full":"3047 Pelican Pl Clearwater FL 33762",
    "addr:housenumber":"3047",
    "addr:postcode":"33762",
    "addr:street":"Pelican Pl",
    "iso:country":"US",
    "sg:address":"3047 Pelican Pl",
    "sg:city":"Clearwater",
    "sg:classifiers":[
        {
            "category":"Utilities",
            "subcategory":"Telephone",
            "type":"Services"
        },
        {
            "category":"Professional",
            "subcategory":"Computer Services",
            "type":"Services"
        }
    ],
    "sg:phone":"+1 727 572 0313",
    "sg:postcode":"33762",
    "sg:province":"FL",
    "sg:tags":[
        "communications",
        "datum",
        "internet"
    ],
    "sg:website":"www.pharmcast.com",
    "wof:name":"G F Communications",
    "wof:placetype":"venue"
},
  "geometry": {"coordinates":[-82.675246,27.90691],"type":"Point"}
}