{
  "type": "Feature",
  "properties": {
    "iso:country":"US",
    "sg:address":"2559 E Sunrise Blvd",
    "sg:city":"Fort Lauderdale",
    "sg:classifiers":[
        {
            "category":"Personal",
            "subcategory":"Beauty Salon",
            "type":"Services"
        }
    ],
    "sg:phone":"+1 954 564 1911",
    "sg:postcode":"33304",
    "sg:province":"FL",
    "wof:name":"Benedetto Hair Design",
    "wof:placetype":"venue"
},
  "geometry": {"coordinates":[-80.111935,26.137959],"type":"Point"}
}