{
  "type": "Feature",
  "properties": {
    "addr:full":"12479 Research Pkwy Orlando FL 32826",
    "addr:housenumber":"12479",
    "addr:postcode":"32826",
    "addr:street":"Research Pkwy",
    "iso:country":"US",
    "sg:address":"12479 Research Pkwy",
    "sg:city":"Orlando",
    "sg:classifiers":[
        {
            "category":"Real Estate",
            "subcategory":"Real Estate Agent",
            "type":"Services"
        }
    ],
    "sg:phone":"+1 407 823 8563",
    "sg:postcode":"32826",
    "sg:province":"FL",
    "wof:name":"Lincoln Property Co",
    "wof:placetype":"venue"
},
  "geometry": {"coordinates":[-81.194591,28.588227],"type":"Point"}
}