{
  "type": "Feature",
  "properties": {
    "addr:full":"1170 Tree Swallow Dr Ste 318 Winter Springs FL 32708",
    "addr:housenumber":"1170",
    "addr:postcode":"32708",
    "addr:street":"Tree Swallow Dr Ste 318",
    "iso:country":"US",
    "sg:address":"1170 Tree Swallow Dr Ste 318",
    "sg:city":"Winter Springs",
    "sg:classifiers":[
        {
            "category":"Building & Trades",
            "subcategory":"Landscaping Services",
            "type":"Services"
        }
    ],
    "sg:phone":"+1 407 902 9819",
    "sg:postcode":"32708",
    "sg:province":"FL",
    "sg:website":"www.staygreenlawncare.com",
    "wof:name":"StayGreen Lawn Care",
    "wof:placetype":"venue"
},
  "geometry": {"coordinates":[-81.26395100000001,28.69878],"type":"Point"}
}