{
  "type": "Feature",
  "properties": {
    "iso:country":"US",
    "sg:address":"1850 40th Ave",
    "sg:city":"Vero Beach",
    "sg:classifiers":[
        {
            "category":"Retail",
            "subcategory":"Auto Repair",
            "type":"Services"
        }
    ],
    "sg:phone":"+1 772 564 9225",
    "sg:postcode":"32960",
    "sg:province":"FL",
    "sg:tags":[
        "general"
    ],
    "wof:name":"Import Car Service",
    "wof:placetype":"venue"
},
  "geometry": {"coordinates":[-80.426607,27.637488],"type":"Point"}
}