{
  "type": "Feature",
  "properties": {
    "iso:country":"US",
    "sg:address":"5250 Town Center Cir",
    "sg:city":"Boca Raton",
    "sg:classifiers":[
        {
            "category":"Coffee & Tea",
            "type":"Food & Drink"
        }
    ],
    "sg:menulink":"http://www.allmenus.com/fl/boca-raton/116997-starbucks-coffee/menu/",
    "sg:phone":"+1 561 347 9710",
    "sg:postcode":"33486",
    "sg:province":"FL",
    "sg:tags":[
        "american"
    ],
    "wof:name":"Starbucks Coffee",
    "wof:placetype":"venue"
},
  "geometry": {"coordinates":[-80.123924,26.362843],"type":"Point"}
}