{
  "type": "Feature",
  "properties": {
    "addr:full":"799 Brickell Plz Miami FL 33131",
    "addr:housenumber":"799",
    "addr:postcode":"33131",
    "addr:street":"Brickell Plz",
    "iso:country":"US",
    "sg:address":"799 Brickell Plz",
    "sg:city":"Miami",
    "sg:classifiers":[
        {
            "category":"Professional",
            "subcategory":"Lawyer & Legal Services",
            "type":"Services"
        }
    ],
    "sg:phone":"+1 305 374 1131",
    "sg:postcode":"33131",
    "sg:province":"FL",
    "wof:name":"Lewis Richard C Atty",
    "wof:placetype":"venue"
},
  "geometry": {"coordinates":[-80.192398,25.764799],"type":"Point"}
}