{
  "type": "Feature",
  "properties": {
    "addr:full":"1536 Kingsley Ave Orange Park FL 32073",
    "addr:housenumber":"1536",
    "addr:postcode":"32073",
    "addr:street":"Kingsley Ave",
    "iso:country":"US",
    "sg:address":"1536 Kingsley Ave",
    "sg:city":"Orange Park",
    "sg:classifiers":[
        {
            "category":"Professional",
            "type":"Services"
        }
    ],
    "sg:phone":"+1 904 296 4246",
    "sg:postcode":"32073",
    "sg:province":"FL",
    "sg:tags":[
        "establishment"
    ],
    "wof:name":"Omni Labor Resource",
    "wof:placetype":"venue"
},
  "geometry": {"coordinates":[-81.730155,30.164368],"type":"Point"}
}