{
  "type": "Feature",
  "properties": {
    "addr:full":"11450 NW 34th St Doral FL 33178",
    "addr:housenumber":"11450",
    "addr:postcode":"33178",
    "addr:street":"Nw 34Th St",
    "iso:country":"US",
    "sg:address":"11450 NW 34th St",
    "sg:city":"Doral",
    "sg:classifiers":[
        {
            "category":"Personal",
            "type":"Services"
        }
    ],
    "sg:phone":"+1 305 477 2300",
    "sg:postcode":"33178",
    "sg:province":"FL",
    "sg:tags":[
        "mover"
    ],
    "wof:name":"Tumi International Movers Inc",
    "wof:placetype":"venue"
},
  "geometry": {"coordinates":[-80.382103,25.805099],"type":"Point"}
}