{
  "type": "Feature",
  "properties": {
    "iso:country":"US",
    "sg:address":"7811 Coral Way Ste 135",
    "sg:city":"Miami",
    "sg:classifiers":[
        {
            "category":"Wholesale",
            "subcategory":"Office Equipment",
            "type":"Manufacturing & Wholesale Goods"
        }
    ],
    "sg:phone":"+1 305 227 6108",
    "sg:postcode":"33155",
    "sg:province":"FL",
    "sg:tags":[
        "furniture"
    ],
    "wof:name":"O2 Pech Equipment",
    "wof:placetype":"venue"
},
  "geometry": {"coordinates":[-80.322068,25.748116],"type":"Point"}
}