{
  "type": "Feature",
  "properties": {
    "iso:country":"US",
    "sg:address":"3922 NE 28th Ct",
    "sg:city":"Ocala",
    "sg:classifiers":[
        {
            "category":"Autos & Motor Vehicles",
            "subcategory":"Automobile Sales",
            "type":"Retail Goods"
        }
    ],
    "sg:phone":"+1 352 368 4041",
    "sg:postcode":"34479",
    "sg:province":"FL",
    "sg:tags":[
        "new",
        "used",
        "car"
    ],
    "wof:name":"Gentry Turners Motor Spots",
    "wof:placetype":"venue"
},
  "geometry": {"coordinates":[-82.09882500000001,29.227274],"type":"Point"}
}