{
  "type": "Feature",
  "properties": {
    "iso:country":"US",
    "sg:address":"640 Apex Rd",
    "sg:city":"Sarasota",
    "sg:classifiers":[
        {
            "category":"Manufacturing",
            "subcategory":"Printing",
            "type":"Manufacturing & Wholesale Goods"
        }
    ],
    "sg:phone":"+1 941 343 0110",
    "sg:postcode":"34240",
    "sg:province":"FL",
    "sg:tags":[
        "multimedia"
    ],
    "wof:name":"Media Mamba",
    "wof:placetype":"venue"
},
  "geometry": {"coordinates":[-82.441543,27.330989],"type":"Point"}
}