{
  "type": "Feature",
  "properties": {
    "iso:country":"US",
    "sg:address":"1307 Betmar Blvd",
    "sg:city":"Fort Myers",
    "sg:classifiers":[
        {
            "category":"Real Estate",
            "subcategory":"Real Estate Agent",
            "type":"Services"
        }
    ],
    "sg:phone":"+1 239 995 7095",
    "sg:postcode":"33903",
    "sg:province":"FL",
    "wof:name":"Shirley H Thomas Real Estate",
    "wof:placetype":"venue"
},
  "geometry": {"coordinates":[-81.895203,26.671391],"type":"Point"}
}