{
  "type": "Feature",
  "properties": {
    "iso:country":"US",
    "sg:address":"10 NE 2nd St",
    "sg:city":"Delray Beach",
    "sg:classifiers":[
        {
            "category":"Health Services",
            "subcategory":"Podiatrist",
            "type":"Services"
        }
    ],
    "sg:phone":"+1 561 272 7171",
    "sg:postcode":"33444",
    "sg:province":"FL",
    "wof:name":"Pineapple Podiatry",
    "wof:placetype":"venue"
},
  "geometry": {"coordinates":[-80.072245,26.46522],"type":"Point"}
}