{
  "type": "Feature",
  "properties": {
    "addr:full":"12929 Cortez Blvd Brooksville FL 34613",
    "addr:housenumber":"12929",
    "addr:postcode":"34613",
    "addr:street":"Cortez Blvd",
    "iso:country":"US",
    "sg:address":"12929 Cortez Blvd",
    "sg:city":"Brooksville",
    "sg:classifiers":[
        {
            "category":"Restaurant",
            "type":"Food & Drink"
        }
    ],
    "sg:menulink":"http://www.allmenus.com/fl/spring-hill/169138-wendys/menu/",
    "sg:phone":"+1 352 596 4868",
    "sg:postcode":"34613",
    "sg:province":"FL",
    "sg:tags":[
        "burger",
        "american",
        "soup"
    ],
    "wof:name":"Wendy's",
    "wof:placetype":"venue"
},
  "geometry": {"coordinates":[-82.511146,28.533716],"type":"Point"}
}