{
  "type": "Feature",
  "properties": {
    "iso:country":"US",
    "sg:address":"824 W Palm Dr",
    "sg:city":"Homestead",
    "sg:classifiers":[
        {
            "category":"Organizations",
            "subcategory":"Religious Organization",
            "type":"Services"
        }
    ],
    "sg:phone":"+1 305 248 2273",
    "sg:postcode":"33034",
    "sg:province":"FL",
    "sg:tags":[
        "school"
    ],
    "wof:name":"First Assembly Christn Academy",
    "wof:placetype":"venue"
},
  "geometry": {"coordinates":[-80.490037,25.447732],"type":"Point"}
}