{
  "type": "Feature",
  "properties": {
    "addr:full":"3141 Drew St Clearwater FL 33759",
    "addr:housenumber":"3141",
    "addr:postcode":"33759",
    "addr:street":"Drew St",
    "iso:country":"US",
    "sg:address":"3141 Drew St",
    "sg:city":"Clearwater",
    "sg:classifiers":[
        {
            "category":"Professional",
            "subcategory":"Management & Consulting",
            "type":"Services"
        },
        {
            "category":"Banks & Credit Unions",
            "subcategory":"Financial Services",
            "type":"Services"
        }
    ],
    "sg:phone":"+1 727 797 0538",
    "sg:postcode":"33759",
    "sg:province":"FL",
    "sg:tags":[
        "consultant",
        "financing",
        "planning",
        "loan"
    ],
    "wof:name":"Allcare Finance",
    "wof:placetype":"venue"
},
  "geometry": {"coordinates":[-82.706372,27.96792],"type":"Point"}
}