{
  "type": "Feature",
  "properties": {
    "iso:country":"US",
    "sg:address":"6391 NW 61st St",
    "sg:city":"Ocala",
    "sg:classifiers":[
        {
            "category":"Building & Trades",
            "subcategory":"Landscaping Services",
            "type":"Services"
        }
    ],
    "sg:phone":"+1 352 622 5312",
    "sg:postcode":"34482",
    "sg:province":"FL",
    "wof:name":"Ramon Lawn Care Services",
    "wof:placetype":"venue"
},
  "geometry": {"coordinates":[-82.22233300000001,29.250373],"type":"Point"}
}