{
  "type": "Feature",
  "properties": {
    "addr:full":"644 Camellia Terrace Dr Neptune Beach FL 32266",
    "addr:housenumber":"644",
    "addr:postcode":"32266",
    "addr:street":"Camellia Terrace Dr",
    "iso:country":"US",
    "sg:address":"644 Camellia Terrace Dr",
    "sg:city":"Neptune Beach",
    "sg:classifiers":[
        {
            "category":"Building & Trades",
            "subcategory":"Construction",
            "type":"Services"
        }
    ],
    "sg:phone":"+1 904 249 0261",
    "sg:postcode":"32266",
    "sg:province":"FL",
    "sg:tags":[
        "contractor"
    ],
    "wof:name":"Mac Spray Inc",
    "wof:placetype":"venue"
},
  "geometry": {"coordinates":[-81.41049700000001,30.318508],"type":"Point"}
}