{
  "type": "Feature",
  "properties": {
    "addr:full":"7517 N Kendall Dr Miami FL 33156",
    "addr:housenumber":"7517",
    "addr:postcode":"33156",
    "addr:street":"N Kendall Dr",
    "iso:country":"US",
    "sg:address":"7517 N Kendall Dr",
    "sg:city":"Miami",
    "sg:classifiers":[
        {
            "category":"Shopping",
            "subcategory":"Clothing, Apparel, & Fashions",
            "type":"Retail Goods"
        }
    ],
    "sg:phone":"+1 305 668 9606",
    "sg:postcode":"33156",
    "sg:province":"FL",
    "sg:tags":[
        "accessory",
        "clothing",
        "women's"
    ],
    "sg:website":"www.guess.com",
    "wof:name":"Guess Inc",
    "wof:placetype":"venue"
},
  "geometry": {"coordinates":[-80.31549800000001,25.688499],"type":"Point"}
}