{
  "type": "Feature",
  "properties": {
    "addr:full":"3655 E Bay Dr Largo FL 33771",
    "addr:housenumber":"3655",
    "addr:postcode":"33771",
    "addr:street":"E Bay Dr",
    "iso:country":"US",
    "sg:address":"3655 E Bay Dr",
    "sg:city":"Largo",
    "sg:phone":"+1 727 507 7400",
    "sg:postcode":"33771",
    "sg:province":"FL",
    "wof:name":"Sushi Spot",
    "wof:placetype":"venue"
},
  "geometry": {"coordinates":[-82.74880899999999,27.916383],"type":"Point"}
}