{
  "type": "Feature",
  "properties": {
    "iso:country":"US",
    "sg:address":"301 Broadway",
    "sg:city":"Riviera Beach",
    "sg:classifiers":[
        {
            "category":"Government",
            "subcategory":"Office",
            "type":"Public Place"
        }
    ],
    "sg:phone":"+1 561 882 3200",
    "sg:postcode":"33404",
    "sg:province":"FL",
    "sg:tags":[
        "state",
        "program",
        "health"
    ],
    "wof:name":"Health Dept",
    "wof:placetype":"venue"
},
  "geometry": {"coordinates":[-80.055262,26.765554],"type":"Point"}
}