{
  "type": "Feature",
  "properties": {
    "iso:country":"US",
    "sg:address":"9551 SW 27th Dr",
    "sg:city":"Miami",
    "sg:classifiers":[
        {
            "category":"Shopping",
            "subcategory":"Clothing, Apparel, & Fashions",
            "type":"Retail Goods"
        }
    ],
    "sg:phone":"+1 305 220 2688",
    "sg:postcode":"33165",
    "sg:province":"FL",
    "sg:tags":[
        "accessory",
        "clothing",
        "women's"
    ],
    "wof:name":"Mily's Designers",
    "wof:placetype":"venue"
},
  "geometry": {"coordinates":[-80.349197,25.744101],"type":"Point"}
}