{
  "type": "Feature",
  "properties": {
    "iso:country":"US",
    "sg:address":"853 Main St",
    "sg:city":"Chipley",
    "sg:classifiers":[
        {
            "category":"Autos & Motor Vehicles",
            "subcategory":"Auto Supplies",
            "type":"Retail Goods"
        }
    ],
    "sg:phone":"+1 850 638 1384",
    "sg:postcode":"32428",
    "sg:province":"FL",
    "sg:tags":[
        "alternator",
        "generator"
    ],
    "wof:name":"R & M Electric Svc",
    "wof:placetype":"venue"
},
  "geometry": {"coordinates":[-85.53901,30.793419],"type":"Point"}
}