{
  "type": "Feature",
  "properties": {
    "iso:country":"US",
    "sg:address":"9623 Palm River Rd",
    "sg:city":"Tampa",
    "sg:classifiers":[
        {
            "category":"Building & Trades",
            "subcategory":"Landscaping Services",
            "type":"Services"
        }
    ],
    "sg:phone":"+1 813 663 0091",
    "sg:postcode":"33619",
    "sg:province":"FL",
    "wof:name":"All American Lawn & Tree",
    "wof:placetype":"venue"
},
  "geometry": {"coordinates":[-82.34710800000001,27.941047],"type":"Point"}
}