{
  "type": "Feature",
  "properties": {
    "iso:country":"US",
    "sg:address":"15331 Harbor Dr",
    "sg:city":"Saint Petersburg",
    "sg:classifiers":[
        {
            "category":"Banks & Credit Unions",
            "subcategory":"Financial Services",
            "type":"Services"
        }
    ],
    "sg:phone":"+1 727 895 7227",
    "sg:postcode":"33708",
    "sg:province":"FL",
    "sg:tags":[
        "trust",
        "investment"
    ],
    "wof:name":"Judy A Schmidt Trust",
    "wof:placetype":"venue"
},
  "geometry": {"coordinates":[-82.80356999999999,27.805169],"type":"Point"}
}