{
  "type": "Feature",
  "properties": {
    "iso:country":"US",
    "sg:address":"1790 Highway A1a",
    "sg:city":"Satellite Beach",
    "sg:classifiers":[
        {
            "category":"Restaurant",
            "type":"Food & Drink"
        }
    ],
    "sg:menulink":"http://www.allmenus.com/fl/indialantic-melbourne-beach/253611-the-dove-restaurant-/menu/",
    "sg:phone":"+1 321 777 5817",
    "sg:postcode":"32937",
    "sg:province":"FL",
    "sg:tags":[
        "pasta",
        "seafood",
        "american",
        "salad",
        "italian"
    ],
    "wof:name":"The Dove Restaurant ",
    "wof:placetype":"venue"
},
  "geometry": {"coordinates":[-80.585812,28.157798],"type":"Point"}
}