{
  "type": "Feature",
  "properties": {
    "addr:full":"1735 Oviedo Marketplace Blvd Oviedo FL 32765",
    "addr:housenumber":"1735",
    "addr:postcode":"32765",
    "addr:street":"Oviedo Marketplace Blvd",
    "iso:country":"US",
    "sg:address":"1735 Oviedo Marketplace Blvd",
    "sg:city":"Oviedo",
    "sg:classifiers":[
        {
            "category":"Building & Trades",
            "subcategory":"Cleaning & Sanitation",
            "type":"Services"
        },
        {
            "category":"Shopping",
            "subcategory":"Gifts & Souvenirs",
            "type":"Retail Goods"
        }
    ],
    "sg:phone":"+1 407 977 2915",
    "sg:postcode":"32765",
    "sg:province":"FL",
    "sg:tags":[
        "stationery",
        "maintenance",
        "greeting",
        "card"
    ],
    "sg:website":"www.carltoncards.com",
    "wof:name":"Carlton Cards",
    "wof:placetype":"venue"
},
  "geometry": {"coordinates":[-81.236321,28.659885],"type":"Point"}
}