{
  "type": "Feature",
  "properties": {
    "iso:country":"US",
    "sg:address":"1465 NW 21st Ter",
    "sg:city":"Miami",
    "sg:classifiers":[
        {
            "category":"Food & Beverages",
            "subcategory":"Specialty",
            "type":"Retail Goods"
        },
        {
            "category":"Food & Beverages",
            "subcategory":"Ethnic Foods",
            "type":"Retail Goods"
        },
        {
            "category":"Wholesale",
            "subcategory":"Groceries",
            "type":"Manufacturing & Wholesale Goods"
        },
        {
            "category":"Manufacturing",
            "subcategory":"Food",
            "type":"Manufacturing & Wholesale Goods"
        },
        {
            "category":"Food & Beverages",
            "subcategory":"Groceries & Convenience Stores",
            "type":"Retail Goods"
        }
    ],
    "sg:phone":"+1 305 324 0231",
    "sg:postcode":"33142",
    "sg:province":"FL",
    "sg:tags":[
        "product",
        "products-wholesale",
        "sauce",
        "grocers-wholesale",
        "condiment",
        "grocers-ethnic"
    ],
    "sg:website":"http://www.kingstonmiami.com",
    "wof:name":"Kingston-Miami Trading Company",
    "wof:placetype":"venue"
},
  "geometry": {"coordinates":[-80.220596,25.7966],"type":"Point"}
}