{
  "type": "Feature",
  "properties": {
    "iso:country":"US",
    "sg:address":"818 W Oak St",
    "sg:city":"Kissimmee",
    "sg:classifiers":[
        {
            "category":"Health Services",
            "subcategory":"Doctor",
            "type":"Services"
        }
    ],
    "sg:phone":"+1 321 624 3233",
    "sg:postcode":"34741",
    "sg:province":"FL",
    "sg:tags":[
        "physician",
        "family",
        "practice",
        "surgeons",
        "medicine",
        "surgeon"
    ],
    "wof:name":"Greg Saric MD",
    "wof:placetype":"venue"
},
  "geometry": {"coordinates":[-81.412063,28.300879],"type":"Point"}
}