{
  "type": "Feature",
  "properties": {
    "addr:full":"409 E Zarragossa St Pensacola FL 32502",
    "addr:housenumber":"409",
    "addr:postcode":"32502",
    "addr:street":"E Zarragossa St",
    "iso:country":"US",
    "sg:address":"409 E Zarragossa St",
    "sg:city":"Pensacola",
    "sg:classifiers":[
        {
            "category":"Professional",
            "subcategory":"Business Services",
            "type":"Services"
        }
    ],
    "sg:phone":"+1 850 477 6771",
    "sg:postcode":"32502",
    "sg:province":"FL",
    "wof:name":"Andy & Associates",
    "wof:placetype":"venue"
},
  "geometry": {"coordinates":[-87.209183,30.409105],"type":"Point"}
}