{
  "type": "Feature",
  "properties": {
    "iso:country":"US",
    "sg:address":"662 NE Horizon Ln",
    "sg:city":"Port Saint Lucie",
    "sg:classifiers":[
        {
            "category":"Building & Trades",
            "subcategory":"Construction",
            "type":"Services"
        }
    ],
    "sg:phone":"+1 772 878 2522",
    "sg:postcode":"34983",
    "sg:province":"FL",
    "sg:tags":[
        "house"
    ],
    "wof:name":"Turner Homes",
    "wof:placetype":"venue"
},
  "geometry": {"coordinates":[-80.346203,27.331758],"type":"Point"}
}