{
  "type": "Feature",
  "properties": {
    "iso:country":"US",
    "sg:address":"4431 Davie Rd",
    "sg:city":"Davie",
    "sg:classifiers":[
        {
            "category":"Manufacturing",
            "subcategory":"Printing",
            "type":"Manufacturing & Wholesale Goods"
        }
    ],
    "sg:phone":"+1 954 791 5441",
    "sg:postcode":"33314",
    "sg:province":"FL",
    "sg:tags":[
        "decal"
    ],
    "wof:name":"F & M Expressions Unlimited",
    "wof:placetype":"venue"
},
  "geometry": {"coordinates":[-80.232912,26.066997],"type":"Point"}
}