{
  "type": "Feature",
  "properties": {
    "addr:full":"3726 Jeremy Ln Lakeland FL 33810",
    "addr:housenumber":"3726",
    "addr:postcode":"33810",
    "addr:street":"Jeremy Ln",
    "iso:country":"US",
    "sg:address":"3726 Jeremy Ln",
    "sg:city":"Lakeland",
    "sg:classifiers":[
        {
            "category":"Building & Trades",
            "subcategory":"Construction",
            "type":"Services"
        }
    ],
    "sg:phone":"+1 863 859 2607",
    "sg:postcode":"33810",
    "sg:province":"FL",
    "sg:tags":[
        "specializing",
        "contractor",
        "installation",
        "epoxy",
        "floor"
    ],
    "wof:name":"Powell Poly Tech Smless Srfces",
    "wof:placetype":"venue"
},
  "geometry": {"coordinates":[-82.022041,28.11018],"type":"Point"}
}