{
  "type": "Feature",
  "properties": {
    "addr:full":"1486 Casey Ln Daytona Beach FL 32129",
    "addr:housenumber":"1486",
    "addr:postcode":"32129",
    "addr:street":"Casey Ln",
    "iso:country":"US",
    "sg:address":"1486 Casey Ln",
    "sg:city":"Daytona Beach",
    "sg:classifiers":[
        {
            "category":"Building & Trades",
            "subcategory":"Construction",
            "type":"Services"
        }
    ],
    "sg:phone":"+1 386 767 6630",
    "sg:postcode":"32129",
    "sg:province":"FL",
    "sg:tags":[
        "steel",
        "erection",
        "structural"
    ],
    "wof:name":"Delta Rebar Reinforcing Svcs",
    "wof:placetype":"venue"
},
  "geometry": {"coordinates":[-81.039117,29.12335],"type":"Point"}
}