{
  "type": "Feature",
  "properties": {
    "iso:country":"US",
    "sg:address":"1012 Pearce Dr",
    "sg:city":"Clearwater",
    "sg:classifiers":[
        {
            "category":"Real Estate",
            "subcategory":"Real Estate Agent",
            "type":"Services"
        }
    ],
    "sg:phone":"+1 727 724 8236",
    "sg:postcode":"33764",
    "sg:province":"FL",
    "wof:name":"HMC Hotel & Property MGT",
    "wof:placetype":"venue"
},
  "geometry": {"coordinates":[-82.72745399999999,27.955243],"type":"Point"}
}