{
  "type": "Feature",
  "properties": {
    "iso:country":"US",
    "sg:address":"3200 S Andrews Ave",
    "sg:city":"Fort Lauderdale",
    "sg:classifiers":[
        {
            "category":"Wholesale",
            "subcategory":"Hardware",
            "type":"Manufacturing & Wholesale Goods"
        }
    ],
    "sg:phone":"+1 954 772 2266",
    "sg:postcode":"33316",
    "sg:province":"FL",
    "sg:tags":[
        "marine"
    ],
    "wof:name":"Tropical Marine Air Cond Inc",
    "wof:placetype":"venue"
},
  "geometry": {"coordinates":[-80.138617,26.084469],"type":"Point"}
}