{
  "type": "Feature",
  "properties": {
    "iso:country":"US",
    "sg:address":"1000 SW 74th Ave",
    "sg:city":"Miami",
    "sg:classifiers":[
        {
            "category":"Building & Trades",
            "subcategory":"Locksmith",
            "type":"Services"
        }
    ],
    "sg:phone":"+1 305 423 2998",
    "sg:postcode":"33144",
    "sg:province":"FL",
    "sg:tags":[
        "key"
    ],
    "wof:name":"Emergency A 24 Locksmith",
    "wof:placetype":"venue"
},
  "geometry": {"coordinates":[-80.315879,25.760739],"type":"Point"}
}