{
  "type": "Feature",
  "properties": {
    "iso:country":"US",
    "sg:address":"3643 5th Ave N",
    "sg:city":"Saint Petersburg",
    "sg:classifiers":[
        {
            "category":"Shopping",
            "type":"Retail Goods"
        }
    ],
    "sg:phone":"+1 727 321 9664",
    "sg:postcode":"33713",
    "sg:province":"FL",
    "sg:tags":[
        "communications",
        "equipment"
    ],
    "wof:name":"Tampa Bay Communications Inc",
    "wof:placetype":"venue"
},
  "geometry": {"coordinates":[-82.683148,27.777359],"type":"Point"}
}