{
  "type": "Feature",
  "properties": {
    "addr:full":"35000 Emerald Coast Pkwy Destin FL 32541",
    "addr:housenumber":"35000",
    "addr:postcode":"32541",
    "addr:street":"Emerald Coast Pkwy",
    "iso:country":"US",
    "sg:address":"35000 Emerald Coast Pkwy",
    "sg:city":"Destin",
    "sg:classifiers":[
        {
            "category":"Real Estate",
            "subcategory":"Real Estate Services",
            "type":"Services"
        },
        {
            "category":"Real Estate",
            "subcategory":"Real Estate Agent",
            "type":"Services"
        }
    ],
    "sg:phone":"+1 850 837 4774",
    "sg:postcode":"32541",
    "sg:province":"FL",
    "sg:tags":[
        "buyer",
        "broker"
    ],
    "sg:website":"http://www.resortquestgulfcoast.com",
    "wof:name":"ResortQuest Real Estate",
    "wof:placetype":"venue"
},
  "geometry": {"coordinates":[-86.40919,30.387567],"type":"Point"}
}