{
  "type": "Feature",
  "properties": {
    "addr:full":"1201 Atlantic Ave Fernandina Beach FL 32034",
    "addr:housenumber":"1201",
    "addr:postcode":"32034",
    "addr:street":"Atlantic Ave",
    "iso:country":"US",
    "sg:address":"1201 Atlantic Ave",
    "sg:city":"Fernandina Beach",
    "sg:classifiers":[
        {
            "category":"Education",
            "subcategory":"Special Training",
            "type":"Public Place"
        }
    ],
    "sg:phone":"+1 904 321 5829",
    "sg:postcode":"32034",
    "sg:province":"FL",
    "sg:tags":[
        "school",
        "adult"
    ],
    "wof:name":"Adult Education",
    "wof:placetype":"venue"
},
  "geometry": {"coordinates":[-81.454826,30.670328],"type":"Point"}
}