{
  "type": "Feature",
  "properties": {
    "addr:full":"1722 SE 14th Ter Cape Coral FL 33990",
    "addr:housenumber":"1722",
    "addr:postcode":"33990",
    "addr:street":"Se 14Th Ter",
    "iso:country":"US",
    "sg:address":"1722 SE 14th Ter",
    "sg:city":"Cape Coral",
    "sg:classifiers":[
        {
            "category":"Shopping",
            "subcategory":"Computers & Home Electronics",
            "type":"Retail Goods"
        }
    ],
    "sg:phone":"+1 239 772 0382",
    "sg:postcode":"33990",
    "sg:province":"FL",
    "wof:name":"Certified Computer Services",
    "wof:placetype":"venue"
},
  "geometry": {"coordinates":[-81.9345,26.625995],"type":"Point"}
}