{
  "type": "Feature",
  "properties": {
    "iso:country":"US",
    "sg:address":"1700 Ryan Dr",
    "sg:city":"Lutz",
    "sg:classifiers":[
        {
            "category":"Professional",
            "subcategory":"Art Services",
            "type":"Services"
        },
        {
            "category":"Building & Trades",
            "subcategory":"Construction",
            "type":"Services"
        }
    ],
    "sg:phone":"+1 813 862 3984",
    "sg:postcode":"33549",
    "sg:province":"FL",
    "sg:tags":[
        "faux",
        "finishing",
        "painting",
        "contractor"
    ],
    "wof:name":"A La Cart",
    "wof:placetype":"venue"
},
  "geometry": {"coordinates":[-82.43956799999999,28.16329],"type":"Point"}
}