{
  "type": "Feature",
  "properties": {
    "addr:full":"451 E Altamonte Dr Altamonte Springs FL 32701",
    "addr:housenumber":"451",
    "addr:postcode":"32701",
    "addr:street":"E Altamonte Dr",
    "iso:country":"US",
    "sg:address":"451 E Altamonte Dr",
    "sg:city":"Altamonte Springs",
    "sg:classifiers":[
        {
            "category":"Shopping",
            "type":"Retail Goods"
        }
    ],
    "sg:phone":"+1 407 767 6201",
    "sg:postcode":"32701",
    "sg:province":"FL",
    "sg:tags":[
        "merchandise"
    ],
    "wof:name":"Miracle-Ear",
    "wof:placetype":"venue"
},
  "geometry": {"coordinates":[-81.374043,28.66385],"type":"Point"}
}