{
  "type": "Feature",
  "properties": {
    "addr:full":"27 Rosedown Blvd De Bary FL 32713",
    "addr:housenumber":"27",
    "addr:postcode":"32713",
    "addr:street":"Rosedown Blvd De",
    "iso:country":"US",
    "sg:address":"27 Rosedown Blvd",
    "sg:city":"De Bary",
    "sg:classifiers":[
        {
            "category":"Building & Trades",
            "subcategory":"Construction",
            "type":"Services"
        }
    ],
    "sg:phone":"+1 386 668 1253",
    "sg:postcode":"32713",
    "sg:province":"FL",
    "sg:tags":[
        "residential"
    ],
    "wof:name":"Lee Enterprises of Volusia",
    "wof:placetype":"venue"
},
  "geometry": {"coordinates":[-81.326556,28.892838],"type":"Point"}
}