{
  "type": "Feature",
  "properties": {
    "addr:full":"699 102nd Ave N Naples FL 34108",
    "addr:housenumber":"699",
    "addr:postcode":"34108",
    "addr:street":"102Nd Ave N",
    "iso:country":"US",
    "sg:address":"699 102nd Ave N",
    "sg:city":"Naples",
    "sg:classifiers":[
        {
            "category":"Education",
            "subcategory":"Vocational School",
            "type":"Public Place"
        }
    ],
    "sg:phone":"+1 239 513 1322",
    "sg:postcode":"34108",
    "sg:province":"FL",
    "sg:tags":[
        "processing",
        "datum"
    ],
    "wof:name":"Techknow Tutor",
    "wof:placetype":"venue"
},
  "geometry": {"coordinates":[-81.813389,26.264293],"type":"Point"}
}