{
  "type": "Feature",
  "properties": {
    "addr:full":"3620 W Silver Springs Blvd Ocala FL 34475",
    "addr:housenumber":"3620",
    "addr:postcode":"34475",
    "addr:street":"W Silver Springs Blvd",
    "iso:country":"US",
    "sg:address":"3620 W Silver Springs Blvd",
    "sg:city":"Ocala",
    "sg:classifiers":[
        {
            "category":"Travel",
            "subcategory":"Hotels & Motels",
            "type":"Entertainment"
        }
    ],
    "sg:phone":"+1 352 629 0091",
    "sg:postcode":"34475",
    "sg:province":"FL",
    "sg:website":"http://www.daysinn.com",
    "wof:name":"Days Inn",
    "wof:placetype":"venue"
},
  "geometry": {"coordinates":[-82.182084,29.186264],"type":"Point"}
}