{
  "type": "Feature",
  "properties": {
    "addr:full":"538 US Hwy 98 Destin FL 32541",
    "addr:housenumber":"538",
    "addr:postcode":"32541",
    "addr:street":"Us Hwy 98",
    "iso:country":"US",
    "sg:address":"538 US Hwy 98",
    "sg:city":"Destin",
    "sg:classifiers":[
        {
            "category":"Restaurant",
            "type":"Food & Drink"
        }
    ],
    "sg:phone":"+1 850 837 2506",
    "sg:postcode":"32541",
    "sg:province":"FL",
    "wof:name":"Harbor Docks",
    "wof:placetype":"venue"
},
  "geometry": {"coordinates":[-86.49882700000001,30.392788],"type":"Point"}
}