{
  "type": "Feature",
  "properties": {
    "addr:full":"125 Alabama Ave Saint Cloud FL 34769",
    "addr:housenumber":"125",
    "addr:postcode":"34769",
    "addr:street":"Alabama Ave",
    "iso:country":"US",
    "sg:address":"125 Alabama Ave",
    "sg:city":"Saint Cloud",
    "sg:classifiers":[
        {
            "category":"Building & Trades",
            "subcategory":"Construction",
            "type":"Services"
        }
    ],
    "sg:phone":"+1 407 957 0865",
    "sg:postcode":"34769",
    "sg:province":"FL",
    "sg:tags":[
        "hanging",
        "contractor"
    ],
    "wof:name":"Mario G Garcia Painting",
    "wof:placetype":"venue"
},
  "geometry": {"coordinates":[-81.295801,28.258284],"type":"Point"}
}