{
  "type": "Feature",
  "properties": {
    "addr:full":"1246 Sweetwater Ln Naples FL 34110",
    "addr:housenumber":"1246",
    "addr:postcode":"34110",
    "addr:street":"Sweetwater Ln",
    "iso:country":"US",
    "sg:address":"1246 Sweetwater Ln",
    "sg:city":"Naples",
    "sg:classifiers":[
        {
            "category":"Home & Garden",
            "subcategory":"Home Furnishings",
            "type":"Retail Goods"
        }
    ],
    "sg:phone":"+1 239 254 8811",
    "sg:postcode":"34110",
    "sg:province":"FL",
    "sg:tags":[
        "venetian",
        "blind"
    ],
    "wof:name":"Caribbean Co Window",
    "wof:placetype":"venue"
},
  "geometry": {"coordinates":[-81.799671,26.315197],"type":"Point"}
}