{
  "type": "Feature",
  "properties": {
    "iso:country":"US",
    "sg:address":"4375 Southside Blvd",
    "sg:city":"Jacksonville",
    "sg:classifiers":[
        {
            "category":"Home & Garden",
            "subcategory":"Furniture",
            "type":"Retail Goods"
        }
    ],
    "sg:phone":"+1 904 645 5151",
    "sg:postcode":"32216",
    "sg:province":"FL",
    "wof:name":"Kids By Beds & More",
    "wof:placetype":"venue"
},
  "geometry": {"coordinates":[-81.558774,30.26911],"type":"Point"}
}