{
  "type": "Feature",
  "properties": {
    "iso:country":"US",
    "sg:address":"400 S Andrews Ave",
    "sg:city":"Fort Lauderdale",
    "sg:classifiers":[
        {
            "category":"Professional",
            "subcategory":"Lawyer & Legal Services",
            "type":"Services"
        }
    ],
    "sg:phone":"+1 954 766 8856",
    "sg:postcode":"33316",
    "sg:province":"FL",
    "wof:name":"Hammer Steve J Law Offices PA",
    "wof:placetype":"venue"
},
  "geometry": {"coordinates":[-80.14330099999999,26.116249],"type":"Point"}
}