{
  "type": "Feature",
  "properties": {
    "addr:full":"4650 Wilde Lake Blvd Pensacola FL 32526",
    "addr:housenumber":"4650",
    "addr:postcode":"32526",
    "addr:street":"Wilde Lake Blvd",
    "iso:country":"US",
    "sg:address":"4650 Wilde Lake Blvd",
    "sg:city":"Pensacola",
    "sg:classifiers":[
        {
            "category":"Building & Trades",
            "subcategory":"Construction",
            "type":"Services"
        }
    ],
    "sg:phone":"+1 850 944 0855",
    "sg:postcode":"32526",
    "sg:province":"FL",
    "sg:tags":[
        "home",
        "builder"
    ],
    "wof:name":"Gary Holt Homes",
    "wof:placetype":"venue"
},
  "geometry": {"coordinates":[-87.330339,30.52],"type":"Point"}
}