{
  "type": "Feature",
  "properties": {
    "iso:country":"US",
    "sg:address":"210 E Eau Gallie Blvd",
    "sg:city":"Indian Hrbr Bch",
    "sg:classifiers":[
        {
            "category":"Restaurant",
            "type":"Food & Drink"
        }
    ],
    "sg:phone":"+1 321 773 1330",
    "sg:postcode":"32937",
    "sg:province":"FL",
    "wof:name":"Deep Fun Inc",
    "wof:placetype":"venue"
},
  "geometry": {"coordinates":[-80.595394,28.138636],"type":"Point"}
}