{
  "type": "Feature",
  "properties": {
    "iso:country":"US",
    "sg:address":"26 Bayberry Branch Rd",
    "sg:city":"Casselberry",
    "sg:classifiers":[
        {
            "category":"Banks & Credit Unions",
            "subcategory":"Financial Services",
            "type":"Services"
        }
    ],
    "sg:phone":"+1 407 830 0994",
    "sg:postcode":"32707",
    "sg:province":"FL",
    "sg:tags":[
        "trust",
        "management"
    ],
    "wof:name":"Beatrice M Belknap Trust",
    "wof:placetype":"venue"
},
  "geometry": {"coordinates":[-81.33265400000001,28.660377],"type":"Point"}
}