{
  "type": "Feature",
  "properties": {
    "addr:full":"328 W Bearss Ave Tampa FL 33613",
    "addr:housenumber":"328",
    "addr:postcode":"33613",
    "addr:street":"W Bearss Ave",
    "iso:country":"US",
    "sg:address":"328 W Bearss Ave",
    "sg:city":"Tampa",
    "sg:classifiers":[
        {
            "category":"Personal",
            "type":"Services"
        }
    ],
    "sg:phone":"+1 813 960 2049",
    "sg:postcode":"33613",
    "sg:province":"FL",
    "sg:tags":[
        "therapist",
        "massage"
    ],
    "wof:name":"A Clinical Massage Therapy",
    "wof:placetype":"venue"
},
  "geometry": {"coordinates":[-82.45998899999999,28.087972],"type":"Point"}
}