{
  "type": "Feature",
  "properties": {
    "iso:country":"US",
    "sg:address":"1750 Sunshadow Dr",
    "sg:city":"Casselberry",
    "sg:classifiers":[
        {
            "category":"Personal",
            "subcategory":"Beauty Salon",
            "type":"Services"
        }
    ],
    "sg:phone":"+1 407 699 3010",
    "sg:postcode":"32707",
    "sg:province":"FL",
    "wof:name":"Hair Masters",
    "wof:placetype":"venue"
},
  "geometry": {"coordinates":[-81.320263,28.695559],"type":"Point"}
}