{
  "type": "Feature",
  "properties": {
    "addr:full":"400 Ocean Trail Way Jupiter FL 33477",
    "addr:housenumber":"400",
    "addr:postcode":"33477",
    "addr:street":"Ocean Trail Way",
    "iso:country":"US",
    "sg:address":"400 Ocean Trail Way",
    "sg:city":"Jupiter",
    "sg:classifiers":[
        {
            "category":"Professional",
            "subcategory":"Lawyer & Legal Services",
            "type":"Services"
        }
    ],
    "sg:phone":"+1 561 746 4982",
    "sg:postcode":"33477",
    "sg:province":"FL",
    "wof:name":"Delrusso Alessandra Luini Dr",
    "wof:placetype":"venue"
},
  "geometry": {"coordinates":[-80.070149,26.936851],"type":"Point"}
}