{
  "type": "Feature",
  "properties": {
    "addr:full":"37350 Neighbors Path Zephyrhills FL 33542",
    "addr:postcode":"37350;33542",
    "addr:street":"Neighbors Path",
    "iso:country":"US",
    "sg:address":"37350 Neighbors Path",
    "sg:city":"Zephyrhills",
    "sg:classifiers":[
        {
            "category":"Communications",
            "type":"Services"
        }
    ],
    "sg:phone":"+1 813 788 9509",
    "sg:postcode":"33542",
    "sg:province":"FL",
    "sg:tags":[
        "communication"
    ],
    "wof:name":"Identityone Communications",
    "wof:placetype":"venue"
},
  "geometry": {"coordinates":[-82.199257,28.253863],"type":"Point"}
}