{
  "type": "Feature",
  "properties": {
    "iso:country":"US",
    "sg:address":"7774 NW 71st St",
    "sg:city":"Miami",
    "sg:classifiers":[
        {
            "category":"Professional",
            "type":"Services"
        }
    ],
    "sg:phone":"+1 305 593 5796",
    "sg:postcode":"33166",
    "sg:province":"FL",
    "sg:tags":[
        "establishment"
    ],
    "wof:name":"Mercury Trading Corp",
    "wof:placetype":"venue"
},
  "geometry": {"coordinates":[-80.32243,25.838018],"type":"Point"}
}