{
  "type": "Feature",
  "properties": {
    "addr:full":"8105 Southgate Blvd Pompano Beach FL 33068",
    "addr:housenumber":"8105",
    "addr:postcode":"33068",
    "addr:street":"Southgate Blvd",
    "iso:country":"US",
    "sg:address":"8105 Southgate Blvd",
    "sg:city":"Pompano Beach",
    "sg:classifiers":[
        {
            "category":"Professional",
            "type":"Services"
        }
    ],
    "sg:phone":"+1 954 720 2547",
    "sg:postcode":"33068",
    "sg:province":"FL",
    "wof:name":"First Ashia Inc",
    "wof:placetype":"venue"
},
  "geometry": {"coordinates":[-80.239672,26.228606],"type":"Point"}
}