{
  "type": "Feature",
  "properties": {
    "addr:full":"13910 Lake Candlewood Ct Hialeah FL 33014",
    "addr:housenumber":"13910",
    "addr:postcode":"33014",
    "addr:street":"Lake Candlewood Ct",
    "iso:country":"US",
    "sg:address":"13910 Lake Candlewood Ct",
    "sg:city":"Hialeah",
    "sg:classifiers":[
        {
            "category":"Real Estate",
            "subcategory":"Real Estate Services",
            "type":"Services"
        },
        {
            "category":"Banks & Credit Unions",
            "subcategory":"Financial Services",
            "type":"Services"
        }
    ],
    "sg:phone":"+1 305 556 1117",
    "sg:postcode":"33014",
    "sg:province":"FL",
    "sg:tags":[
        "loan",
        "processing"
    ],
    "wof:name":"Florida Ocean Mortgage Corp",
    "wof:placetype":"venue"
},
  "geometry": {"coordinates":[-80.30080100000001,25.899483],"type":"Point"}
}