{
  "type": "Feature",
  "properties": {
    "addr:full":"1400 NW 36th St Miami FL 33142",
    "addr:housenumber":"1400",
    "addr:postcode":"33142",
    "addr:street":"Nw 36Th St",
    "iso:country":"US",
    "sg:address":"1400 NW 36th St",
    "sg:city":"Miami",
    "sg:classifiers":[
        {
            "category":"Professional",
            "subcategory":"Management & Consulting",
            "type":"Services"
        }
    ],
    "sg:phone":"+1 305 638 6223",
    "sg:postcode":"33142",
    "sg:province":"FL",
    "sg:tags":[
        "agricultural",
        "consultant"
    ],
    "sg:website":"http://www.miamidade.gov",
    "wof:name":"Human Services Dept",
    "wof:placetype":"venue"
},
  "geometry": {"coordinates":[-80.21981,25.809681],"type":"Point"}
}