{
  "type": "Feature",
  "properties": {
    "addr:full":"3200 W Colonial Dr Orlando FL 32808",
    "addr:housenumber":"3200",
    "addr:postcode":"32808",
    "addr:street":"W Colonial Dr",
    "iso:country":"US",
    "sg:address":"3200 W Colonial Dr",
    "sg:city":"Orlando",
    "sg:classifiers":[
        {
            "category":"Professional",
            "subcategory":"Employment Agencies",
            "type":"Services"
        },
        {
            "category":"Organizations",
            "subcategory":"Professional Association",
            "type":"Services"
        }
    ],
    "sg:phone":"+1 407 294 0119",
    "sg:postcode":"32808",
    "sg:province":"FL",
    "sg:tags":[
        "employer"
    ],
    "wof:name":"Grand Avenue Ecdc",
    "wof:placetype":"venue"
},
  "geometry": {"coordinates":[-81.415909,28.552679],"type":"Point"}
}