{
  "type": "Feature",
  "properties": {
    "iso:country":"US",
    "sg:address":"501 Village Green Pkwy",
    "sg:city":"Bradenton",
    "sg:classifiers":[
        {
            "category":"Banks & Credit Unions",
            "subcategory":"Investment Brokerage",
            "type":"Services"
        }
    ],
    "sg:phone":"+1 941 761 7200",
    "sg:postcode":"34209",
    "sg:province":"FL",
    "sg:tags":[
        "consultant",
        "planning",
        "financial"
    ],
    "wof:name":"Sundial Advisory Group",
    "wof:placetype":"venue"
},
  "geometry": {"coordinates":[-82.63328799999999,27.494963],"type":"Point"}
}