{
  "type": "Feature",
  "properties": {
    "iso:country":"US",
    "sg:address":"14900 E Orange Lake Blvd",
    "sg:city":"Kissimmee",
    "sg:classifiers":[
        {
            "category":"Shopping",
            "subcategory":"Catalog Store",
            "type":"Retail Goods"
        }
    ],
    "sg:phone":"+1 863 424 2774",
    "sg:postcode":"34747",
    "sg:province":"FL",
    "sg:tags":[
        "mail",
        "house"
    ],
    "wof:name":"Taffy Enterprises",
    "wof:placetype":"venue"
},
  "geometry": {"coordinates":[-81.62455199999999,28.348605],"type":"Point"}
}