{
  "type": "Feature",
  "properties": {
    "addr:full":"6802 W Hillsborough Ave Tampa FL 33634",
    "addr:housenumber":"6802",
    "addr:postcode":"33634",
    "addr:street":"W Hillsborough Ave",
    "iso:country":"US",
    "sg:address":"6802 W Hillsborough Ave",
    "sg:city":"Tampa",
    "sg:classifiers":[
        {
            "category":"Real Estate",
            "subcategory":"Real Estate Agent",
            "type":"Services"
        }
    ],
    "sg:phone":"+1 813 882 6500",
    "sg:postcode":"33634",
    "sg:province":"FL",
    "sg:tags":[
        "broker"
    ],
    "wof:name":"Land Ho",
    "wof:placetype":"venue"
},
  "geometry": {"coordinates":[-82.55551199999999,27.996465],"type":"Point"}
}