{
  "type": "Feature",
  "properties": {
    "iso:country":"US",
    "sg:address":"189 S Orange Ave Ste 1850",
    "sg:city":"Orlando",
    "sg:classifiers":[
        {
            "category":"Professional",
            "subcategory":"Advertising",
            "type":"Services"
        }
    ],
    "sg:phone":"+1 407 879 7909",
    "sg:postcode":"32801",
    "sg:province":"FL",
    "sg:tags":[
        "telemarketing"
    ],
    "wof:name":"T R Document Services LLC",
    "wof:placetype":"venue"
},
  "geometry": {"coordinates":[-81.37902,28.540438],"type":"Point"}
}