{
  "type": "Feature",
  "properties": {
    "iso:country":"US",
    "sg:address":"2152 NE 162nd St",
    "sg:city":"North Miami Bch",
    "sg:classifiers":[
        {
            "category":"Retail",
            "subcategory":"Repair Shop",
            "type":"Services"
        }
    ],
    "sg:phone":"+1 305 948 6200",
    "sg:postcode":"33162",
    "sg:province":"FL",
    "sg:tags":[
        "equipment"
    ],
    "sg:website":"www.juicedispensers.com",
    "wof:name":"A & A Discount Svc",
    "wof:placetype":"venue"
},
  "geometry": {"coordinates":[-80.156847,25.925094],"type":"Point"}
}