{
  "type": "Feature",
  "properties": {
    "iso:country":"US",
    "sg:address":"13865 S Dixie Hwy",
    "sg:city":"Miami",
    "sg:classifiers":[
        {
            "category":"Real Estate",
            "subcategory":"Real Estate Services",
            "type":"Services"
        },
        {
            "category":"Real Estate",
            "subcategory":"Real Estate Agent",
            "type":"Services"
        }
    ],
    "sg:phone":"+1 305 233 0208",
    "sg:postcode":"33176",
    "sg:province":"FL",
    "sg:tags":[
        "management",
        "commercial"
    ],
    "wof:name":"Birlidis V Properties",
    "wof:placetype":"venue"
},
  "geometry": {"coordinates":[-80.33531000000001,25.641161],"type":"Point"}
}