{
  "type": "Feature",
  "properties": {
    "iso:country":"US",
    "sg:address":"1802 59th St W",
    "sg:city":"Bradenton",
    "sg:classifiers":[
        {
            "category":"Shopping",
            "type":"Retail Goods"
        }
    ],
    "sg:phone":"+1 941 792 1828",
    "sg:postcode":"34209",
    "sg:province":"FL",
    "sg:tags":[
        "repair",
        "electrical",
        "merchandise"
    ],
    "wof:name":"Suncoast Hearing Service Ctr",
    "wof:placetype":"venue"
},
  "geometry": {"coordinates":[-82.620574,27.484128],"type":"Point"}
}