{
  "type": "Feature",
  "properties": {
    "iso:country":"US",
    "sg:address":"317 W Oak St",
    "sg:city":"Arcadia",
    "sg:classifiers":[
        {
            "category":"Retail",
            "subcategory":"Portrait Studio",
            "type":"Services"
        }
    ],
    "sg:phone":"+1 863 993 2771",
    "sg:postcode":"34266",
    "sg:province":"FL",
    "sg:tags":[
        "photographer"
    ],
    "wof:name":"Precious Moments Photography",
    "wof:placetype":"venue"
},
  "geometry": {"coordinates":[-81.864535,27.216802],"type":"Point"}
}