{
  "type": "Feature",
  "properties": {
    "iso:country":"US",
    "sg:address":"7174 Cypress Dr",
    "sg:city":"Fort Myers",
    "sg:classifiers":[
        {
            "category":"Food & Beverages",
            "subcategory":"Groceries & Convenience Stores",
            "type":"Retail Goods"
        }
    ],
    "sg:phone":"+1 239 278 0873",
    "sg:postcode":"33907",
    "sg:province":"FL",
    "wof:name":"Family Discount Food Store",
    "wof:placetype":"venue"
},
  "geometry": {"coordinates":[-81.875298,26.569099],"type":"Point"}
}