{
  "type": "Feature",
  "properties": {
    "iso:country":"US",
    "sg:address":"2179 N Spring Garden Ave",
    "sg:city":"Deland",
    "sg:classifiers":[
        {
            "category":"Place Of Worship",
            "subcategory":"Church",
            "type":"Public Place"
        },
        {
            "category":"Place Of Worship",
            "type":"Public Place"
        }
    ],
    "sg:phone":"+1 386 736 7100",
    "sg:postcode":"32720",
    "sg:province":"FL",
    "sg:tags":[
        "bible",
        "churches-open"
    ],
    "wof:name":"Deland Open Bible Ministry Center",
    "wof:placetype":"venue"
},
  "geometry": {"coordinates":[-81.325227,29.065879],"type":"Point"}
}