{
  "type": "Feature",
  "properties": {
    "iso:country":"US",
    "sg:address":"1240 S Palm Ave",
    "sg:city":"Homosassa",
    "sg:classifiers":[
        {
            "category":"Building & Trades",
            "subcategory":"Construction",
            "type":"Services"
        }
    ],
    "sg:phone":"+1 352 795 9480",
    "sg:postcode":"34448",
    "sg:province":"FL",
    "sg:tags":[
        "contractor"
    ],
    "wof:name":"Benge & Warner Drywall In",
    "wof:placetype":"venue"
},
  "geometry": {"coordinates":[-82.573313,28.845249],"type":"Point"}
}