{
  "type": "Feature",
  "properties": {
    "iso:country":"US",
    "sg:address":"4025 Arrow Ave",
    "sg:city":"Sarasota",
    "sg:classifiers":[
        {
            "category":"Building & Trades",
            "subcategory":"Construction",
            "type":"Services"
        }
    ],
    "sg:phone":"+1 941 377 9499",
    "sg:postcode":"34232",
    "sg:province":"FL",
    "sg:tags":[
        "contractor"
    ],
    "wof:name":"Colemans Wow",
    "wof:placetype":"venue"
},
  "geometry": {"coordinates":[-82.486557,27.329944],"type":"Point"}
}