{
  "type": "Feature",
  "properties": {
    "iso:country":"US",
    "sg:address":"3550 S US Hwy 1",
    "sg:city":"Fort Pierce",
    "sg:classifiers":[
        {
            "category":"Retail",
            "subcategory":"Repair Shop",
            "type":"Services"
        }
    ],
    "sg:phone":"+1 772 335 3890",
    "sg:postcode":"34982",
    "sg:province":"FL",
    "sg:tags":[
        "electrical"
    ],
    "wof:name":"Katy-Bill Corp",
    "wof:placetype":"venue"
},
  "geometry": {"coordinates":[-80.325805,27.403604],"type":"Point"}
}