{
  "type": "Feature",
  "properties": {
    "iso:country":"US",
    "sg:address":"3839 N Monroe St",
    "sg:city":"Tallahassee",
    "sg:classifiers":[
        {
            "category":"Restaurant",
            "type":"Food & Drink"
        }
    ],
    "sg:phone":"+1 850 562 5733",
    "sg:postcode":"32303",
    "sg:province":"FL",
    "wof:name":"Tropical Smoothie Cafe",
    "wof:placetype":"venue"
},
  "geometry": {"coordinates":[-84.33216400000001,30.506066],"type":"Point"}
}