{
  "type": "Feature",
  "properties": {
    "addr:full":"915 NW 1st Ave Ofc Miami FL 33136",
    "addr:housenumber":"915",
    "addr:postcode":"33136",
    "addr:street":"Nw 1St Ave",
    "iso:country":"US",
    "sg:address":"915 NW 1st Ave Ofc",
    "sg:city":"Miami",
    "sg:classifiers":[
        {
            "category":"Professional",
            "subcategory":"Business Services",
            "type":"Services"
        }
    ],
    "sg:phone":"+1 305 377 1952",
    "sg:postcode":"33136",
    "sg:province":"FL",
    "sg:tags":[
        "mail",
        "messenger",
        "shipping"
    ],
    "wof:name":"Cummings Postal & Package Center",
    "wof:placetype":"venue"
},
  "geometry": {"coordinates":[-80.195875,25.782946],"type":"Point"}
}