{
  "type": "Feature",
  "properties": {
    "addr:full":"9046 4th St N Saint Petersburg FL 33702",
    "addr:housenumber":"9046",
    "addr:postcode":"33702",
    "addr:street":"4Th St N",
    "iso:country":"US",
    "sg:address":"9046 4th St N",
    "sg:city":"Saint Petersburg",
    "sg:classifiers":[
        {
            "category":"Travel",
            "subcategory":"Hotels & Motels",
            "type":"Entertainment"
        }
    ],
    "sg:phone":"+1 727 576 1369",
    "sg:postcode":"33702",
    "sg:province":"FL",
    "wof:name":"Grant Motel & Apartments",
    "wof:placetype":"venue"
},
  "geometry": {"coordinates":[-82.638859,27.854816],"type":"Point"}
}