{
  "type": "Feature",
  "properties": {
    "addr:full":"11071 SW 155th Pl Miami FL 33196",
    "addr:housenumber":"11071",
    "addr:postcode":"33196",
    "addr:street":"Sw 155Th Pl",
    "iso:country":"US",
    "sg:address":"11071 SW 155th Pl",
    "sg:city":"Miami",
    "sg:classifiers":[
        {
            "category":"Professional",
            "type":"Services"
        }
    ],
    "sg:phone":"+1 305 663 9842",
    "sg:postcode":"33196",
    "sg:province":"FL",
    "wof:name":"Etnia Creations Inc",
    "wof:placetype":"venue"
},
  "geometry": {"coordinates":[-80.44804000000001,25.664581],"type":"Point"}
}