{
  "type": "Feature",
  "properties": {
    "addr:full":"6240 Trent St Pensacola FL 32503",
    "addr:housenumber":"6240",
    "addr:postcode":"32503",
    "addr:street":"Trent St",
    "iso:country":"US",
    "sg:address":"6240 Trent St",
    "sg:city":"Pensacola",
    "sg:classifiers":[
        {
            "category":"Building & Trades",
            "subcategory":"Construction",
            "type":"Services"
        }
    ],
    "sg:phone":"+1 850 478 3278",
    "sg:postcode":"32503",
    "sg:province":"FL",
    "sg:tags":[
        "contractor"
    ],
    "wof:name":"Csanyi Drywall Specialties",
    "wof:placetype":"venue"
},
  "geometry": {"coordinates":[-87.253486,30.492588],"type":"Point"}
}