{
  "type": "Feature",
  "properties": {
    "addr:full":"1013 N Federal Hwy Fort Lauderdale FL 33304",
    "addr:housenumber":"1013",
    "addr:postcode":"33304",
    "addr:street":"N Federal Hwy",
    "iso:country":"US",
    "sg:address":"1013 N Federal Hwy",
    "sg:city":"Fort Lauderdale",
    "sg:classifiers":[
        {
            "category":"Professional",
            "subcategory":"Advertising",
            "type":"Services"
        }
    ],
    "sg:phone":"+1 954 828 1515",
    "sg:postcode":"33304",
    "sg:province":"FL",
    "sg:tags":[
        "distribution"
    ],
    "wof:name":"Cobalt Friction Technologies",
    "wof:placetype":"venue"
},
  "geometry": {"coordinates":[-80.121212,26.137861],"type":"Point"}
}