{
  "type": "Feature",
  "properties": {
    "addr:full":"528 S 8th St Fernandina Beach FL 32034",
    "addr:housenumber":"528",
    "addr:postcode":"32034",
    "addr:street":"S 8Th St",
    "iso:country":"US",
    "sg:address":"528 S 8th St",
    "sg:city":"Fernandina Beach",
    "sg:classifiers":[
        {
            "category":"Food & Beverages",
            "subcategory":"Groceries & Convenience Stores",
            "type":"Retail Goods"
        }
    ],
    "sg:phone":"+1 904 491 6300",
    "sg:postcode":"32034",
    "sg:province":"FL",
    "sg:tags":[
        "grocer"
    ],
    "wof:name":"LA Rancherita",
    "wof:placetype":"venue"
},
  "geometry": {"coordinates":[-81.45975300000001,30.664056],"type":"Point"}
}