{
  "type": "Feature",
  "properties": {
    "addr:full":"23 N A St Pensacola FL 32501",
    "addr:housenumber":"23",
    "addr:postcode":"32501",
    "addr:street":"N A St",
    "iso:country":"US",
    "sg:address":"23 N A St",
    "sg:city":"Pensacola",
    "sg:classifiers":[
        {
            "category":"Organizations",
            "subcategory":"Religious Organization",
            "type":"Services"
        }
    ],
    "sg:phone":"+1 850 470 0703",
    "sg:postcode":"32501",
    "sg:province":"FL",
    "sg:tags":[
        "church"
    ],
    "wof:name":"Cornerstone Abundant Life Chr",
    "wof:placetype":"venue"
},
  "geometry": {"coordinates":[-87.226111,30.412344],"type":"Point"}
}