{
  "type": "Feature",
  "properties": {
    "iso:country":"US",
    "sg:address":"3705 Murrell Rd",
    "sg:city":"Rockledge",
    "sg:classifiers":[
        {
            "category":"Restaurant",
            "type":"Food & Drink"
        }
    ],
    "sg:menulink":"http://www.allmenus.com/fl/cocoa-rockledge/87292-little-caesars-pizza/menu/",
    "sg:phone":"+1 321 635 9965",
    "sg:postcode":"32955",
    "sg:province":"FL",
    "sg:tags":[
        "american",
        "pizza"
    ],
    "wof:name":"Little Caesar's Pizza",
    "wof:placetype":"venue"
},
  "geometry": {"coordinates":[-80.72153400000001,28.296378],"type":"Point"}
}