{
  "type": "Feature",
  "properties": {
    "iso:country":"US",
    "sg:address":"1015 S G St",
    "sg:city":"Lake Worth",
    "sg:classifiers":[
        {
            "category":"Restaurant",
            "type":"Food & Drink"
        }
    ],
    "sg:phone":"+1 561 585 6126",
    "sg:postcode":"33460",
    "sg:province":"FL",
    "sg:tags":[
        "eating"
    ],
    "wof:name":"Jackson Country Style Ribs",
    "wof:placetype":"venue"
},
  "geometry": {"coordinates":[-80.05986799999999,26.602802],"type":"Point"}
}