{
  "type": "Feature",
  "properties": {
    "iso:country":"US",
    "sg:address":"4183 N US Hwy 1",
    "sg:city":"Melbourne",
    "sg:classifiers":[
        {
            "category":"Building & Trades",
            "subcategory":"Construction",
            "type":"Services"
        }
    ],
    "sg:phone":"+1 321 626 7899",
    "sg:postcode":"32935",
    "sg:province":"FL",
    "sg:tags":[
        "carpentry",
        "contractor"
    ],
    "wof:name":"Dennis Horton",
    "wof:placetype":"venue"
},
  "geometry": {"coordinates":[-80.647457,28.172776],"type":"Point"}
}