{
  "type": "Feature",
  "properties": {
    "addr:full":"1739 Ruby Rd Tallahassee FL 32303",
    "addr:housenumber":"1739",
    "addr:postcode":"32303",
    "addr:street":"Ruby Rd",
    "iso:country":"US",
    "sg:address":"1739 Ruby Rd",
    "sg:city":"Tallahassee",
    "sg:classifiers":[
        {
            "category":"Food & Beverages",
            "subcategory":"Liquor & Beverages",
            "type":"Retail Goods"
        }
    ],
    "sg:phone":"+1 850 562 3492",
    "sg:postcode":"32303",
    "sg:province":"FL",
    "sg:tags":[
        "lounge",
        "alcoholic"
    ],
    "wof:name":"Colonial Liquors",
    "wof:placetype":"venue"
},
  "geometry": {"coordinates":[-84.322428,30.491298],"type":"Point"}
}