{
  "type": "Feature",
  "properties": {
    "iso:country":"US",
    "sg:address":"18731 SW 308th St",
    "sg:city":"Homestead",
    "sg:classifiers":[
        {
            "category":"Autos & Motor Vehicles",
            "subcategory":"Auto Supplies",
            "type":"Retail Goods"
        }
    ],
    "sg:phone":"+1 305 248 1279",
    "sg:postcode":"33030",
    "sg:province":"FL",
    "sg:tags":[
        "automobile",
        "part"
    ],
    "wof:name":"Jose Hernandez",
    "wof:placetype":"venue"
},
  "geometry": {"coordinates":[-80.49435,25.480706],"type":"Point"}
}