{
  "type": "Feature",
  "properties": {
    "iso:country":"US",
    "sg:address":"2549 SW 23rd Cranbrook Pl",
    "sg:city":"Boynton Beach",
    "sg:classifiers":[
        {
            "category":"Manufacturing",
            "subcategory":"Tools & Machinery",
            "type":"Manufacturing & Wholesale Goods"
        }
    ],
    "sg:phone":"+1 561 740 1995",
    "sg:postcode":"33436",
    "sg:province":"FL",
    "sg:tags":[
        "electrical",
        "mfg"
    ],
    "wof:name":"American College of Angiology",
    "wof:placetype":"venue"
},
  "geometry": {"coordinates":[-80.09442300000001,26.503633],"type":"Point"}
}