{
  "type": "Feature",
  "properties": {
    "addr:full":"6175 Beach Blvd Jacksonville FL 32216",
    "addr:housenumber":"6175",
    "addr:postcode":"32216",
    "addr:street":"Beach Blvd",
    "iso:country":"US",
    "sg:address":"6175 Beach Blvd",
    "sg:city":"Jacksonville",
    "sg:classifiers":[
        {
            "category":"Retail",
            "subcategory":"Auto Rental",
            "type":"Services"
        }
    ],
    "sg:phone":"+1 904 720 0905",
    "sg:postcode":"32216",
    "sg:province":"FL",
    "sg:tags":[
        "renting",
        "truck",
        "leasing"
    ],
    "wof:name":"Budget Truck Rental",
    "wof:placetype":"venue"
},
  "geometry": {"coordinates":[-81.597854,30.291414],"type":"Point"}
}