{
  "type": "Feature",
  "properties": {
    "iso:country":"US",
    "sg:address":"250 Bird Rd Ste 320",
    "sg:city":"Coral Gables",
    "sg:classifiers":[
        {
            "category":"Professional",
            "subcategory":"Lawyer & Legal Services",
            "type":"Services"
        }
    ],
    "sg:phone":"+1 305 461 3077",
    "sg:postcode":"33146",
    "sg:province":"FL",
    "wof:name":"Crimarco George",
    "wof:placetype":"venue"
},
  "geometry": {"coordinates":[-80.260098,25.734571],"type":"Point"}
}