{
  "type": "Feature",
  "properties": {
    "addr:full":"2716 Rew Cir Ocoee FL 34761",
    "addr:housenumber":"2716",
    "addr:postcode":"34761",
    "addr:street":"Rew Cir",
    "iso:country":"US",
    "sg:address":"2716 Rew Cir",
    "sg:city":"Ocoee",
    "sg:classifiers":[
        {
            "category":"Banks & Credit Unions",
            "subcategory":"Investment Brokerage",
            "type":"Services"
        }
    ],
    "sg:phone":"+1 407 656 9600",
    "sg:postcode":"34761",
    "sg:province":"FL",
    "sg:tags":[
        "advisory",
        "financial"
    ],
    "wof:name":"Meehan Capital Management Grp",
    "wof:placetype":"venue"
},
  "geometry": {"coordinates":[-81.537126,28.549871],"type":"Point"}
}