{
  "type": "Feature",
  "properties": {
    "iso:country":"US",
    "sg:address":"3560 Cooper Trl",
    "sg:city":"Kissimmee",
    "sg:classifiers":[
        {
            "category":"Home & Garden",
            "subcategory":"Building Materials",
            "type":"Retail Goods"
        }
    ],
    "sg:phone":"+1 407 343 1700",
    "sg:postcode":"34746",
    "sg:province":"FL",
    "wof:name":"Guaranteed Metal Building Repair",
    "wof:placetype":"venue"
},
  "geometry": {"coordinates":[-81.44691400000001,28.188525],"type":"Point"}
}