{
  "type": "Feature",
  "properties": {
    "iso:country":"US",
    "sg:address":"12765 Forest Hill Blvd",
    "sg:city":"Wellington",
    "sg:classifiers":[
        {
            "category":"Professional",
            "subcategory":"Computer Services",
            "type":"Services"
        }
    ],
    "sg:phone":"+1 561 791 1221",
    "sg:postcode":"33414",
    "sg:province":"FL",
    "sg:tags":[
        "consultant",
        "designer",
        "datum",
        "system"
    ],
    "wof:name":"Unique Data Systems",
    "wof:placetype":"venue"
},
  "geometry": {"coordinates":[-80.24771800000001,26.672681],"type":"Point"}
}