{
  "type": "Feature",
  "properties": {
    "addr:full":"21 NW 46th Ave Ocala FL 34482",
    "addr:housenumber":"21",
    "addr:postcode":"34482",
    "addr:street":"Nw 46Th Ave",
    "iso:country":"US",
    "sg:address":"21 NW 46th Ave",
    "sg:city":"Ocala",
    "sg:classifiers":[
        {
            "category":"Building & Trades",
            "subcategory":"Construction",
            "type":"Services"
        }
    ],
    "sg:phone":"+1 352 732 6125",
    "sg:postcode":"34482",
    "sg:province":"FL",
    "sg:tags":[
        "contractor"
    ],
    "wof:name":"Wayne D Enos Contractor",
    "wof:placetype":"venue"
},
  "geometry": {"coordinates":[-82.19726799999999,29.189528],"type":"Point"}
}