{
  "type": "Feature",
  "properties": {
    "iso:country":"US",
    "sg:address":"400 E 13th St",
    "sg:city":"Hialeah",
    "sg:classifiers":[
        {
            "category":"Wholesale",
            "subcategory":"Computers",
            "type":"Manufacturing & Wholesale Goods"
        }
    ],
    "sg:phone":"+1 305 553 5800",
    "sg:postcode":"33010",
    "sg:province":"FL",
    "sg:tags":[
        "physical",
        "commercial",
        "research"
    ],
    "wof:name":"CTS System",
    "wof:placetype":"venue"
},
  "geometry": {"coordinates":[-80.271744,25.833854],"type":"Point"}
}