{
  "type": "Feature",
  "properties": {
    "addr:full":"1215 Alton Rd Miami Beach FL 33139",
    "addr:housenumber":"1215",
    "addr:postcode":"33139",
    "addr:street":"Alton Rd",
    "iso:country":"US",
    "sg:address":"1215 Alton Rd",
    "sg:city":"Miami Beach",
    "sg:classifiers":[
        {
            "category":"Professional",
            "subcategory":"Lawyer & Legal Services",
            "type":"Services"
        }
    ],
    "sg:phone":"+1 305 672 7675",
    "sg:postcode":"33139",
    "sg:province":"FL",
    "wof:name":"Sevin Norman M Atty",
    "wof:placetype":"venue"
},
  "geometry": {"coordinates":[-80.141098,25.7831],"type":"Point"}
}