{
  "type": "Feature",
  "properties": {
    "addr:full":"4790 SW 83rd Ter Fort Lauderdale FL 33328",
    "addr:housenumber":"4790",
    "addr:postcode":"33328",
    "addr:street":"Sw 83Rd Ter",
    "iso:country":"US",
    "sg:address":"4790 SW 83rd Ter",
    "sg:city":"Fort Lauderdale",
    "sg:classifiers":[
        {
            "category":"Retail",
            "subcategory":"Auto Repair",
            "type":"Services"
        }
    ],
    "sg:phone":"+1 954 434 0387",
    "sg:postcode":"33328",
    "sg:province":"FL",
    "sg:tags":[
        "automotive",
        "general",
        "sup"
    ],
    "wof:name":"Knapps Garage Inc",
    "wof:placetype":"venue"
},
  "geometry": {"coordinates":[-80.258678,26.064509],"type":"Point"}
}