{
  "type": "Feature",
  "properties": {
    "iso:country":"US",
    "sg:address":"151 N Airport Rd",
    "sg:city":"Tavernier",
    "sg:classifiers":[
        {
            "category":"Shopping",
            "subcategory":"Used Merchandise",
            "type":"Retail Goods"
        }
    ],
    "sg:phone":"+1 305 853 7276",
    "sg:postcode":"33070",
    "sg:province":"FL",
    "sg:tags":[
        "clothing"
    ],
    "wof:name":"P Roger Corp",
    "wof:placetype":"venue"
},
  "geometry": {"coordinates":[-80.53436499999999,25.005058],"type":"Point"}
}