{
  "type": "Feature",
  "properties": {
    "iso:country":"US",
    "sg:address":"510 Key Royale Dr",
    "sg:city":"Bradenton Beach",
    "sg:classifiers":[
        {
            "category":"Manufacturing",
            "subcategory":"Printing",
            "type":"Manufacturing & Wholesale Goods"
        }
    ],
    "sg:phone":"+1 941 778 1945",
    "sg:postcode":"34217",
    "sg:province":"FL",
    "sg:tags":[
        "publishing"
    ],
    "wof:name":"Bulldog Publishing",
    "wof:placetype":"venue"
},
  "geometry": {"coordinates":[-82.71306199999999,27.516676],"type":"Point"}
}