{
  "type": "Feature",
  "properties": {
    "iso:country":"US",
    "sg:address":"5880 Macy Ave",
    "sg:city":"Jacksonville",
    "sg:classifiers":[
        {
            "category":"Retail",
            "subcategory":"Repair Shop",
            "type":"Services"
        }
    ],
    "sg:phone":"+1 904 744 0322",
    "sg:postcode":"32211",
    "sg:province":"FL",
    "sg:tags":[
        "small",
        "appliance",
        "electrical",
        "refrigerator"
    ],
    "wof:name":"Graham's Appliance Service",
    "wof:placetype":"venue"
},
  "geometry": {"coordinates":[-81.59889699999999,30.335884],"type":"Point"}
}