{
  "type": "Feature",
  "properties": {
    "iso:country":"US",
    "sg:address":"6223 US Hwy 90",
    "sg:city":"Milton",
    "sg:classifiers":[
        {
            "category":"Wholesale",
            "subcategory":"Office Equipment",
            "type":"Manufacturing & Wholesale Goods"
        }
    ],
    "sg:phone":"+1 850 981 9649",
    "sg:postcode":"32570",
    "sg:province":"FL",
    "sg:tags":[
        "credit"
    ],
    "wof:name":"Total Merchant Svc",
    "wof:placetype":"venue"
},
  "geometry": {"coordinates":[-87.076421,30.602368],"type":"Point"}
}