{
  "type": "Feature",
  "properties": {
    "iso:country":"US",
    "sg:address":"1552 Palm View Rd",
    "sg:city":"Sarasota",
    "sg:classifiers":[
        {
            "category":"Arena",
            "subcategory":"Sports Club",
            "type":"Entertainment"
        },
        {
            "category":"Sports & Exercise",
            "subcategory":"Sports Center",
            "type":"Entertainment"
        },
        {
            "category":"Sports & Exercise",
            "subcategory":"Golf",
            "type":"Entertainment"
        }
    ],
    "sg:phone":"+1 941 371 3680",
    "sg:postcode":"34240",
    "sg:province":"FL",
    "sg:tags":[
        "course",
        "range",
        "practice"
    ],
    "wof:name":"Oak Ford Golf Club",
    "wof:placetype":"venue"
},
  "geometry": {"coordinates":[-82.314982,27.317172],"type":"Point"}
}