{
  "type": "Feature",
  "properties": {
    "iso:country":"US",
    "sg:address":"6115 Kipps Colony Dr W",
    "sg:city":"Saint Petersburg",
    "sg:classifiers":[
        {
            "category":"Professional",
            "subcategory":"Management & Consulting",
            "type":"Services"
        }
    ],
    "sg:phone":"+1 727 345 3057",
    "sg:postcode":"33707",
    "sg:province":"FL",
    "sg:tags":[
        "planning",
        "meeting",
        "event",
        "convention"
    ],
    "wof:name":"Meetings Designs Inc",
    "wof:placetype":"venue"
},
  "geometry": {"coordinates":[-82.72380699999999,27.74251],"type":"Point"}
}