{
  "type": "Feature",
  "properties": {
    "iso:country":"US",
    "sg:address":"China Grill 404 Washington Ave",
    "sg:city":"Miami",
    "sg:classifiers":[
        {
            "category":"Restaurant",
            "type":"Food & Drink"
        }
    ],
    "sg:phone":"+1 305 534 2211",
    "sg:postcode":"33139",
    "sg:province":"FL",
    "sg:tags":[
        "sushi",
        "bar"
    ],
    "sg:website":"www.chinagrillmgt.com/chinaMI",
    "wof:name":"Dragon",
    "wof:placetype":"venue"
},
  "geometry": {"coordinates":[-80.134404,25.773669],"type":"Point"}
}