{
  "type": "Feature",
  "properties": {
    "iso:country":"US",
    "sg:address":"5802 Bay Front Dr",
    "sg:city":"Panama City",
    "sg:classifiers":[
        {
            "category":"Building & Trades",
            "subcategory":"Landscaping Services",
            "type":"Services"
        }
    ],
    "sg:phone":"+1 850 527 7483",
    "sg:postcode":"32404",
    "sg:province":"FL",
    "sg:tags":[
        "landscape",
        "contractor"
    ],
    "wof:name":"At Your Svc Of Bay Count Inc",
    "wof:placetype":"venue"
},
  "geometry": {"coordinates":[-85.588613,30.118267],"type":"Point"}
}