{
  "type": "Feature",
  "properties": {
    "addr:full":"845 University Blvd N Jacksonville FL 32211",
    "addr:housenumber":"845",
    "addr:postcode":"32211",
    "addr:street":"University Blvd N",
    "iso:country":"US",
    "sg:address":"845 University Blvd N",
    "sg:city":"Jacksonville",
    "sg:classifiers":[
        {
            "category":"Bars & Pubs",
            "subcategory":"Nightclub",
            "type":"Food & Drink"
        }
    ],
    "sg:phone":"+1 904 743 1845",
    "sg:postcode":"32211",
    "sg:province":"FL",
    "sg:tags":[
        "club",
        "night"
    ],
    "wof:name":"Rain Nightclub",
    "wof:placetype":"venue"
},
  "geometry": {"coordinates":[-81.603765,30.329216],"type":"Point"}
}