{
  "type": "Feature",
  "properties": {
    "addr:full":"1532 Semoran Blvd Winter Park FL 32792",
    "addr:housenumber":"1532",
    "addr:postcode":"32792",
    "addr:street":"Semoran Blvd",
    "iso:country":"US",
    "sg:address":"1532 Semoran Blvd",
    "sg:city":"Winter Park",
    "sg:classifiers":[
        {
            "category":"Retail",
            "subcategory":"Auto Rental",
            "type":"Services"
        }
    ],
    "sg:phone":"+1 407 886 5075",
    "sg:postcode":"32792",
    "sg:province":"FL",
    "sg:tags":[
        "renting",
        "automobile"
    ],
    "wof:name":"Budget Rent A Car",
    "wof:placetype":"venue"
},
  "geometry": {"coordinates":[-81.31538500000001,28.624803],"type":"Point"}
}