{
  "type": "Feature",
  "properties": {
    "iso:country":"US",
    "sg:address":"900 Anita St",
    "sg:city":"Fort Pierce",
    "sg:classifiers":[
        {
            "category":"Shopping",
            "subcategory":"Clothing, Apparel, & Fashions",
            "type":"Retail Goods"
        }
    ],
    "sg:phone":"+1 772 464 6246",
    "sg:postcode":"34982",
    "sg:province":"FL",
    "sg:tags":[
        "dance",
        "square"
    ],
    "wof:name":"Sandy's Square Dance Boutique",
    "wof:placetype":"venue"
},
  "geometry": {"coordinates":[-80.332066,27.36924],"type":"Point"}
}