{
  "type": "Feature",
  "properties": {
    "addr:full":"9121 SW 113th Place Cir E Miami FL 33176",
    "addr:housenumber":"9121",
    "addr:postcode":"33176",
    "addr:street":"Sw 113Th Place Cir E",
    "iso:country":"US",
    "sg:address":"9121 SW 113th Place Cir E",
    "sg:city":"Miami",
    "sg:classifiers":[
        {
            "category":"Professional",
            "subcategory":"Accounting & Tax Preparation",
            "type":"Services"
        }
    ],
    "sg:phone":"+1 305 271 9298",
    "sg:postcode":"33176",
    "sg:province":"FL",
    "wof:name":"Newman & Co",
    "wof:placetype":"venue"
},
  "geometry": {"coordinates":[-80.378539,25.683854],"type":"Point"}
}