{
  "type": "Feature",
  "properties": {
    "iso:country":"US",
    "sg:address":"8055 NW 77th Ct",
    "sg:city":"Medley",
    "sg:classifiers":[
        {
            "category":"Wholesale",
            "subcategory":"Toys & Hobbies",
            "type":"Manufacturing & Wholesale Goods"
        }
    ],
    "sg:phone":"+1 305 888 3151",
    "sg:postcode":"33166",
    "sg:province":"FL",
    "sg:tags":[
        "wholesaler"
    ],
    "sg:website":"www.regalcorp.com",
    "wof:name":"Regal Corp",
    "wof:placetype":"venue"
},
  "geometry": {"coordinates":[-80.322811,25.846894],"type":"Point"}
}