{
  "type": "Feature",
  "properties": {
    "iso:country":"US",
    "sg:address":"6405 Blanding Blvd",
    "sg:city":"Jacksonville",
    "sg:classifiers":[
        {
            "category":"Food & Beverages",
            "subcategory":"Groceries & Convenience Stores",
            "type":"Retail Goods"
        }
    ],
    "sg:phone":"+1 904 771 4392",
    "sg:postcode":"32244",
    "sg:province":"FL",
    "wof:name":"Lil' Champ Food Store",
    "wof:placetype":"venue"
},
  "geometry": {"coordinates":[-81.738545,30.230144],"type":"Point"}
}