{
  "type": "Feature",
  "properties": {
    "iso:country":"US",
    "sg:address":"533 Rock Dr",
    "sg:city":"Tallahassee",
    "sg:classifiers":[
        {
            "category":"Building & Trades",
            "subcategory":"Construction",
            "type":"Services"
        }
    ],
    "sg:phone":"+1 850 574 1748",
    "sg:postcode":"32310",
    "sg:province":"FL",
    "sg:tags":[
        "home",
        "improvement"
    ],
    "wof:name":"Robert Lee Mc Grath Carpentry",
    "wof:placetype":"venue"
},
  "geometry": {"coordinates":[-84.407532,30.442083],"type":"Point"}
}