{
  "type": "Feature",
  "properties": {
    "iso:country":"US",
    "sg:address":"150 Valley Cir",
    "sg:city":"Ponte Vedra Beach",
    "sg:classifiers":[
        {
            "category":"Restaurant",
            "type":"Food & Drink"
        }
    ],
    "sg:menulink":"http://www.allmenus.com/fl/ponte-vedra/43472-bogey-grille/menu/",
    "sg:phone":"+1 904 285 5524",
    "sg:postcode":"32082",
    "sg:province":"FL",
    "sg:tags":[
        "american"
    ],
    "wof:name":"Bogey Grille",
    "wof:placetype":"venue"
},
  "geometry": {"coordinates":[-81.381191,30.191363],"type":"Point"}
}