{
  "type": "Feature",
  "properties": {
    "iso:country":"US",
    "sg:address":"150 E Palmetto Park Rd",
    "sg:city":"Boca Raton",
    "sg:classifiers":[
        {
            "category":"Manufacturing",
            "subcategory":"Wood Products",
            "type":"Manufacturing & Wholesale Goods"
        }
    ],
    "sg:phone":"+1 561 750 4450",
    "sg:postcode":"33432",
    "sg:province":"FL",
    "sg:tags":[
        "molecular",
        "separation"
    ],
    "wof:name":"DDS Technologies Usa Inc",
    "wof:placetype":"venue"
},
  "geometry": {"coordinates":[-80.084585,26.350445],"type":"Point"}
}