{
  "type": "Feature",
  "properties": {
    "addr:full":"118 18th St S St Petersburg FL 33712",
    "addr:housenumber":"118",
    "addr:postcode":"33712",
    "addr:street":"18Th St S",
    "iso:country":"US",
    "sg:address":"118 18th St S",
    "sg:city":"St Petersburg",
    "sg:classifiers":[
        {
            "category":"Professional",
            "subcategory":"Business Services",
            "type":"Services"
        }
    ],
    "sg:phone":"+1 727 896 7900",
    "sg:postcode":"33712",
    "sg:province":"FL",
    "wof:name":"Warren Business Products",
    "wof:placetype":"venue"
},
  "geometry": {"coordinates":[-82.65762100000001,27.769544],"type":"Point"}
}