{
  "type": "Feature",
  "properties": {
    "addr:full":"8475 S Tamiami Trl Sarasota FL 34238",
    "addr:housenumber":"8475",
    "addr:postcode":"34238",
    "addr:street":"S Tamiami Trl",
    "iso:country":"US",
    "sg:address":"8475 S Tamiami Trl",
    "sg:city":"Sarasota",
    "sg:classifiers":[
        {
            "category":"Professional",
            "subcategory":"Business Services",
            "type":"Services"
        }
    ],
    "sg:phone":"+1 941 924 6500",
    "sg:postcode":"34238",
    "sg:province":"FL",
    "sg:tags":[
        "pool",
        "swimming"
    ],
    "wof:name":"HQH Pool Svc",
    "wof:placetype":"venue"
},
  "geometry": {"coordinates":[-82.49375999999999,27.227672],"type":"Point"}
}