{
  "type": "Feature",
  "properties": {
    "iso:country":"US",
    "sg:address":"615 N Highway 17",
    "sg:city":"Debary",
    "sg:classifiers":[
        {
            "category":"Education",
            "subcategory":"University",
            "type":"Public Place"
        }
    ],
    "sg:phone":"+1 386 320 0090",
    "sg:postcode":"32713",
    "sg:province":"FL",
    "sg:tags":[
        "college"
    ],
    "wof:name":"Angley College",
    "wof:placetype":"venue"
},
  "geometry": {"coordinates":[-81.303549,28.908314],"type":"Point"}
}