{
  "type": "Feature",
  "properties": {
    "iso:country":"US",
    "sg:address":"17891 Durrance Rd",
    "sg:city":"Fort Myers",
    "sg:classifiers":[
        {
            "category":"Manufacturing",
            "subcategory":"Glass & Minerals",
            "type":"Manufacturing & Wholesale Goods"
        }
    ],
    "sg:phone":"+1 239 543 6422",
    "sg:postcode":"33917",
    "sg:province":"FL",
    "sg:tags":[
        "ready",
        "concrete",
        "mfg"
    ],
    "wof:name":"Site Mix of Florida",
    "wof:placetype":"venue"
},
  "geometry": {"coordinates":[-81.79349999999999,26.723136],"type":"Point"}
}