{
  "type": "Feature",
  "properties": {
    "addr:full":"925 Lincoln Rd. Miami Beach FL 33139",
    "addr:housenumber":"925",
    "addr:postcode":"33139",
    "addr:street":"Lincoln Rd.",
    "iso:country":"US",
    "sg:address":"925 Lincoln Rd.",
    "sg:city":"Miami Beach",
    "sg:classifiers":[
        {
            "category":"Shopping",
            "subcategory":"Clothing, Apparel, & Fashions",
            "type":"Retail Goods"
        }
    ],
    "sg:phone":"+1 305 673 0722",
    "sg:postcode":"33139",
    "sg:province":"FL",
    "sg:tags":[
        "men's",
        "clothing",
        "accessory",
        "women's"
    ],
    "sg:website":"www.originalpenguin.com",
    "wof:name":"Original Penguin",
    "wof:placetype":"venue"
},
  "geometry": {"coordinates":[-80.138271,25.790516],"type":"Point"}
}