{
  "type": "Feature",
  "properties": {
    "iso:country":"US",
    "sg:address":"2001 Mickler St",
    "sg:city":"Callahan",
    "sg:classifiers":[
        {
            "category":"Real Estate",
            "subcategory":"Real Estate Services",
            "type":"Services"
        },
        {
            "category":"Real Estate",
            "subcategory":"Real Estate Agent",
            "type":"Services"
        }
    ],
    "sg:phone":"+1 904 879 1008",
    "sg:postcode":"32011",
    "sg:province":"FL",
    "sg:tags":[
        "buyer",
        "management",
        "broker"
    ],
    "wof:name":"First Coast Realty Inc",
    "wof:placetype":"venue"
},
  "geometry": {"coordinates":[-81.832449,30.560572],"type":"Point"}
}