{
  "type": "Feature",
  "properties": {
    "iso:country":"US",
    "sg:address":"2282 W Co Hwy 30A",
    "sg:city":"Santa Rosa Beach",
    "sg:classifiers":[
        {
            "category":"Real Estate",
            "subcategory":"Real Estate Agent",
            "type":"Services"
        }
    ],
    "sg:phone":"+1 850 622 2367",
    "sg:postcode":"32459",
    "sg:province":"FL",
    "wof:name":"30a Realty",
    "wof:placetype":"venue"
},
  "geometry": {"coordinates":[-86.20437,30.340649],"type":"Point"}
}