{
  "type": "Feature",
  "properties": {
    "iso:country":"US",
    "sg:address":"908 W Hallandale Beach Blvd",
    "sg:city":"Hallandale Beach",
    "sg:classifiers":[
        {
            "category":"Home & Garden",
            "subcategory":"Furniture",
            "type":"Retail Goods"
        }
    ],
    "sg:phone":"+1 954 456 1200",
    "sg:postcode":"33009",
    "sg:province":"FL",
    "sg:tags":[
        "household"
    ],
    "wof:name":"Wickerama Inc",
    "wof:placetype":"venue"
},
  "geometry": {"coordinates":[-80.159694,25.985304],"type":"Point"}
}