{
  "type": "Feature",
  "properties": {
    "addr:full":"4334 Land O Lakes Blvd Land O Lakes FL 34639",
    "addr:housenumber":"4334",
    "addr:postcode":"34639",
    "addr:street":"Land O Lakes Blvd Land",
    "iso:country":"US",
    "sg:address":"4334 Land O Lakes Blvd",
    "sg:city":"Land O Lakes",
    "sg:classifiers":[
        {
            "category":"Manufacturing",
            "subcategory":"Printing",
            "type":"Manufacturing & Wholesale Goods"
        }
    ],
    "sg:phone":"+1 813 948 2566",
    "sg:postcode":"34639",
    "sg:province":"FL",
    "sg:tags":[
        "commercial",
        "m",
        "specialty",
        "mfg"
    ],
    "wof:name":"Club Air Sportswear Inc",
    "wof:placetype":"venue"
},
  "geometry": {"coordinates":[-82.457678,28.226042],"type":"Point"}
}