{
  "type": "Feature",
  "properties": {
    "iso:country":"US",
    "sg:address":"6951 NW 18th Ct",
    "sg:city":"Pompano Beach",
    "sg:classifiers":[
        {
            "category":"Wholesale",
            "subcategory":"Motor Vehicles",
            "type":"Manufacturing & Wholesale Goods"
        }
    ],
    "sg:phone":"+1 954 709 4886",
    "sg:postcode":"33063",
    "sg:province":"FL",
    "wof:name":"John Liptak Inc",
    "wof:placetype":"venue"
},
  "geometry": {"coordinates":[-80.219729,26.251243],"type":"Point"}
}