{
  "type": "Feature",
  "properties": {
    "addr:full":"291 S Collier Blvd Marco Island FL 34145",
    "addr:housenumber":"291;collier blvd",
    "addr:postcode":"34145",
    "addr:street":"S",
    "iso:country":"US",
    "sg:address":"291 S Collier Blvd",
    "sg:city":"Marco Island",
    "sg:classifiers":[
        {
            "category":"Personal",
            "subcategory":"Beauty Salon",
            "type":"Services"
        }
    ],
    "sg:phone":"+1 239 394 4489",
    "sg:postcode":"34145",
    "sg:province":"FL",
    "sg:tags":[
        "shop"
    ],
    "wof:name":"Jeannette's Hair Designs",
    "wof:placetype":"venue"
},
  "geometry": {"coordinates":[-81.72917099999999,25.931389],"type":"Point"}
}