{
  "type": "Feature",
  "properties": {
    "iso:country":"US",
    "sg:address":"929 W 29th St",
    "sg:city":"Hialeah",
    "sg:classifiers":[
        {
            "category":"Autos & Motor Vehicles",
            "subcategory":"Auto Supplies",
            "type":"Retail Goods"
        }
    ],
    "sg:phone":"+1 305 885 0868",
    "sg:postcode":"33012",
    "sg:province":"FL",
    "sg:tags":[
        "automotive",
        "parts"
    ],
    "wof:name":"Linper 1 Discount Auto Parts",
    "wof:placetype":"venue"
},
  "geometry": {"coordinates":[-80.30177399999999,25.84807],"type":"Point"}
}