{
  "type": "Feature",
  "properties": {
    "iso:country":"US",
    "sg:address":"1785 F I M Blvd",
    "sg:city":"Fort Walton Bch",
    "sg:classifiers":[
        {
            "category":"Retail",
            "subcategory":"Auto Repair",
            "type":"Services"
        }
    ],
    "sg:phone":"+1 850 864 0880",
    "sg:postcode":"32547",
    "sg:province":"FL",
    "sg:tags":[
        "body",
        "automobile",
        "painting"
    ],
    "wof:name":"A-K's Paint Body & Restoration",
    "wof:placetype":"venue"
},
  "geometry": {"coordinates":[-86.64838899999999,30.468208],"type":"Point"}
}