{
  "type": "Feature",
  "properties": {
    "addr:full":"5680 Wayside Dr Sanford FL 32771",
    "addr:housenumber":"5680",
    "addr:postcode":"32771",
    "addr:street":"Wayside Dr",
    "iso:country":"US",
    "sg:address":"5680 Wayside Dr",
    "sg:city":"Sanford",
    "sg:classifiers":[
        {
            "category":"Social Services",
            "subcategory":"Child Care",
            "type":"Services"
        }
    ],
    "sg:phone":"+1 407 328 8260",
    "sg:postcode":"32771",
    "sg:province":"FL",
    "sg:tags":[
        "day"
    ],
    "wof:name":"Paola Woods Child Care",
    "wof:placetype":"venue"
},
  "geometry": {"coordinates":[-81.362509,28.808261],"type":"Point"}
}