{
  "type": "Feature",
  "properties": {
    "addr:full":"1850 Blue Heron Blvd W West Palm Beach FL 33404",
    "addr:housenumber":"1850",
    "addr:postcode":"33404",
    "addr:street":"Blue Heron Blvd W",
    "iso:country":"US",
    "sg:address":"1850 Blue Heron Blvd W",
    "sg:city":"West Palm Beach",
    "sg:classifiers":[
        {
            "category":"Restaurant",
            "type":"Food & Drink"
        }
    ],
    "sg:menulink":"http://www.allmenus.com/fl/riviera-beach/61037-quiznos-sub/menu/",
    "sg:phone":"+1 561 844 4991",
    "sg:postcode":"33404",
    "sg:province":"FL",
    "sg:tags":[
        "wrap",
        "american",
        "sandwich"
    ],
    "wof:name":"Quiznos Sub",
    "wof:placetype":"venue"
},
  "geometry": {"coordinates":[-80.08548,26.781681],"type":"Point"}
}