{
  "type": "Feature",
  "properties": {
    "iso:country":"US",
    "sg:address":"9796 SW 147th Ct",
    "sg:city":"Miami",
    "sg:classifiers":[
        {
            "category":"Wholesale",
            "subcategory":"Medical Equipment & Supplies",
            "type":"Manufacturing & Wholesale Goods"
        }
    ],
    "sg:phone":"+1 305 298 3226",
    "sg:postcode":"33196",
    "sg:province":"FL",
    "sg:tags":[
        "exporter"
    ],
    "wof:name":"Detroit International Corp",
    "wof:placetype":"venue"
},
  "geometry": {"coordinates":[-80.43339400000001,25.676079],"type":"Point"}
}