{
  "type": "Feature",
  "properties": {
    "addr:full":"11421 SW 72nd Ct Miami FL 33156",
    "addr:housenumber":"11421",
    "addr:postcode":"33156",
    "addr:street":"Sw 72Nd Ct",
    "iso:country":"US",
    "sg:address":"11421 SW 72nd Ct",
    "sg:city":"Miami",
    "sg:classifiers":[
        {
            "category":"Professional",
            "type":"Services"
        }
    ],
    "sg:phone":"+1 305 233 6785",
    "sg:postcode":"33156",
    "sg:province":"FL",
    "wof:name":"Deux Lapins Inc",
    "wof:placetype":"venue"
},
  "geometry": {"coordinates":[-80.311288,25.663388],"type":"Point"}
}