{
  "type": "Feature",
  "properties": {
    "iso:country":"US",
    "sg:address":"724 Pasadena Ave S",
    "sg:city":"Saint Petersburg",
    "sg:classifiers":[
        {
            "category":"Shopping",
            "type":"Retail Goods"
        }
    ],
    "sg:phone":"+1 727 347 8419",
    "sg:postcode":"33707",
    "sg:province":"FL",
    "sg:tags":[
        "merchandise"
    ],
    "wof:name":"Wet Pet Inc",
    "wof:placetype":"venue"
},
  "geometry": {"coordinates":[-82.734796,27.762801],"type":"Point"}
}