{
  "type": "Feature",
  "properties": {
    "iso:country":"US",
    "sg:address":"2887 NE 35th Ct",
    "sg:city":"Fort Lauderdale",
    "sg:classifiers":[
        {
            "category":"Professional",
            "subcategory":"Engineering",
            "type":"Services"
        }
    ],
    "sg:phone":"+1 954 630 8220",
    "sg:postcode":"33308",
    "sg:province":"FL",
    "wof:name":"Mar Cnstruction Communications",
    "wof:placetype":"venue"
},
  "geometry": {"coordinates":[-80.10814000000001,26.171595],"type":"Point"}
}