{
  "type": "Feature",
  "properties": {
    "iso:country":"US",
    "sg:address":"4811 NW 167th St",
    "sg:city":"Opa Locka",
    "sg:classifiers":[
        {
            "category":"Shopping",
            "subcategory":"Florist",
            "type":"Retail Goods"
        }
    ],
    "sg:phone":"+1 305 625 2379",
    "sg:postcode":"33055",
    "sg:province":"FL",
    "wof:name":"Baby Florist and Services",
    "wof:placetype":"venue"
},
  "geometry": {"coordinates":[-80.279701,25.925501],"type":"Point"}
}