{
  "type": "Feature",
  "properties": {
    "iso:country":"US",
    "sg:address":"1525 Old Chemstrand Rd",
    "sg:city":"Cantonment",
    "sg:phone":"+1 850 432 5939",
    "sg:postcode":"32533",
    "sg:province":"FL",
    "sg:website":"http://www.mrsteamercarpetcleaner.com",
    "wof:name":"Mr Steamer Carpet Cleaner",
    "wof:placetype":"venue"
},
  "geometry": {"coordinates":[-87.289733,30.582207],"type":"Point"}
}