{
  "type": "Feature",
  "properties": {
    "addr:full":"1469 NW 23rd St Miami FL 33142",
    "addr:housenumber":"1469",
    "addr:postcode":"33142",
    "addr:street":"Nw 23Rd St",
    "iso:country":"US",
    "sg:address":"1469 NW 23rd St",
    "sg:city":"Miami",
    "sg:classifiers":[
        {
            "category":"Manufacturing",
            "subcategory":"Building Materials",
            "type":"Manufacturing & Wholesale Goods"
        }
    ],
    "sg:phone":"+1 305 634 3333",
    "sg:postcode":"33142",
    "sg:province":"FL",
    "sg:tags":[
        "mfg",
        "wood",
        "kitchen",
        "cabinet"
    ],
    "wof:name":"Viciedo Carpenter Corporation",
    "wof:placetype":"venue"
},
  "geometry": {"coordinates":[-80.220108,25.798627],"type":"Point"}
}