{
  "type": "Feature",
  "properties": {
    "iso:country":"US",
    "sg:address":"8726 NW 25 St Ste 15",
    "sg:city":"Doral",
    "sg:classifiers":[
        {
            "category":"Restaurant",
            "type":"Food & Drink"
        }
    ],
    "sg:phone":"+1 305 477 8188",
    "sg:postcode":"33172",
    "sg:province":"FL",
    "sg:tags":[
        "chinese"
    ],
    "wof:name":"Qianlong Chinese Restaurant",
    "wof:placetype":"venue"
},
  "geometry": {"coordinates":[-80.337416,25.796856],"type":"Point"}
}