{
  "type": "Feature",
  "properties": {
    "iso:country":"US",
    "sg:address":"6050 Babcock St SE",
    "sg:city":"Palm Bay",
    "sg:classifiers":[
        {
            "category":"Banks & Credit Unions",
            "subcategory":"Investment Brokerage",
            "type":"Services"
        }
    ],
    "sg:phone":"+1 321 872 0500",
    "sg:postcode":"32909",
    "sg:province":"FL",
    "sg:tags":[
        "advisory",
        "financial"
    ],
    "wof:name":"Pam Bay Financial Corp",
    "wof:placetype":"venue"
},
  "geometry": {"coordinates":[-80.621938,27.997941],"type":"Point"}
}