{
  "type": "Feature",
  "properties": {
    "addr:full":"16821 Panama City Beach Pkwy Panama City Bch FL 32413",
    "addr:housenumber":"16821",
    "addr:postcode":"32413",
    "addr:street":"Panama;Beach Pkwy",
    "iso:country":"US",
    "sg:address":"16821 Panama City Beach Pkwy",
    "sg:city":"Panama City Bch",
    "sg:classifiers":[
        {
            "category":"Real Estate",
            "subcategory":"Real Estate Operator",
            "type":"Services"
        }
    ],
    "sg:phone":"+1 850 249 9974",
    "sg:postcode":"32413",
    "sg:province":"FL",
    "sg:tags":[
        "condominium"
    ],
    "wof:name":"Sunset Realty Resort Mgmt",
    "wof:placetype":"venue"
},
  "geometry": {"coordinates":[-85.899411,30.234039],"type":"Point"}
}