{
  "type": "Feature",
  "properties": {
    "iso:country":"US",
    "sg:address":"1601 NE 191st St",
    "sg:city":"Miami",
    "sg:classifiers":[
        {
            "category":"Professional",
            "subcategory":"Management & Consulting",
            "type":"Services"
        }
    ],
    "sg:phone":"+1 305 493 9588",
    "sg:postcode":"33179",
    "sg:province":"FL",
    "sg:tags":[
        "business"
    ],
    "wof:name":"NGL-USA Industrial Products",
    "wof:placetype":"venue"
},
  "geometry": {"coordinates":[-80.17310999999999,25.951202],"type":"Point"}
}