{
  "type": "Feature",
  "properties": {
    "addr:full":"3950 W Hwy 326 Ocala FL 34482",
    "addr:housenumber":"3950",
    "addr:postcode":"34482",
    "addr:street":"W Hwy 326",
    "iso:country":"US",
    "sg:address":"3950 W Hwy 326",
    "sg:city":"Ocala",
    "sg:classifiers":[
        {
            "category":"Wholesale",
            "subcategory":"Machinery & Supplies",
            "type":"Manufacturing & Wholesale Goods"
        }
    ],
    "sg:phone":"+1 352 840 0070",
    "sg:postcode":"34482",
    "sg:province":"FL",
    "sg:tags":[
        "engine"
    ],
    "wof:name":"Ocala Freightliner",
    "wof:placetype":"venue"
},
  "geometry": {"coordinates":[-82.180812,29.266849],"type":"Point"}
}