{
  "type": "Feature",
  "properties": {
    "addr:full":"7890 NE 10th Ave Miami FL 33138",
    "addr:housenumber":"7890",
    "addr:postcode":"33138",
    "addr:street":"Ne 10Th Ave",
    "iso:country":"US",
    "sg:address":"7890 NE 10th Ave",
    "sg:city":"Miami",
    "sg:classifiers":[
        {
            "category":"Professional",
            "type":"Services"
        }
    ],
    "sg:phone":"+1 305 867 2235",
    "sg:postcode":"33138",
    "sg:province":"FL",
    "wof:name":"Vertigogo Inc",
    "wof:placetype":"venue"
},
  "geometry": {"coordinates":[-80.17647700000001,25.847028],"type":"Point"}
}