{
  "type": "Feature",
  "properties": {
    "iso:country":"US",
    "sg:address":"25 Seabreeze Ave",
    "sg:city":"Delray Beach",
    "sg:classifiers":[
        {
            "category":"Social Services",
            "type":"Services"
        }
    ],
    "sg:phone":"+1 561 266 9499",
    "sg:postcode":"33483",
    "sg:province":"FL",
    "sg:tags":[
        "youth",
        "organization",
        "center"
    ],
    "wof:name":"Youth Leadership Development",
    "wof:placetype":"venue"
},
  "geometry": {"coordinates":[-80.061342,26.463135],"type":"Point"}
}