{
  "type": "Feature",
  "properties": {
    "iso:country":"US",
    "sg:address":"2600 E Colonial Dr",
    "sg:city":"Orlando",
    "sg:classifiers":[
        {
            "category":"Restaurant",
            "type":"Food & Drink"
        }
    ],
    "sg:menulink":"http://www.allmenus.com/fl/orlando/90667-houlihans/menu/",
    "sg:phone":"+1 407 894 3009",
    "sg:postcode":"32803",
    "sg:province":"FL",
    "sg:tags":[
        "new",
        "american"
    ],
    "wof:name":"Houlihan's",
    "wof:placetype":"venue"
},
  "geometry": {"coordinates":[-81.349645,28.552695],"type":"Point"}
}