{
  "type": "Feature",
  "properties": {
    "addr:full":"711 SE 1st Ave Hallandale Beach FL 33009",
    "addr:housenumber":"711",
    "addr:postcode":"33009",
    "addr:street":"Se 1St Ave",
    "iso:country":"US",
    "sg:address":"711 SE 1st Ave",
    "sg:city":"Hallandale Beach",
    "sg:classifiers":[
        {
            "category":"Banks & Credit Unions",
            "subcategory":"Bank",
            "type":"Services"
        }
    ],
    "sg:phone":"+1 954 935 0037",
    "sg:postcode":"33009",
    "sg:province":"FL",
    "sg:tags":[
        "loan",
        "mortgage",
        "real estate"
    ],
    "sg:website":"www.q-mortgage.com",
    "wof:name":"Q Mortgage & Investments Inc",
    "wof:placetype":"venue"
},
  "geometry": {"coordinates":[-80.14765800000001,25.977293],"type":"Point"}
}