{
  "type": "Feature",
  "properties": {
    "addr:full":"4059 Centerville Rd Tallahassee FL 32308",
    "addr:housenumber":"4059",
    "addr:postcode":"32308",
    "addr:street":"Centerville Rd",
    "iso:country":"US",
    "sg:address":"4059 Centerville Rd",
    "sg:city":"Tallahassee",
    "sg:classifiers":[
        {
            "category":"Building & Trades",
            "subcategory":"Cleaning & Sanitation",
            "type":"Services"
        }
    ],
    "sg:phone":"+1 850 656 2877",
    "sg:postcode":"32308",
    "sg:province":"FL",
    "sg:tags":[
        "butler",
        "maid"
    ],
    "wof:name":"All About Cleaning Crew",
    "wof:placetype":"venue"
},
  "geometry": {"coordinates":[-84.210964,30.493356],"type":"Point"}
}