{
  "type": "Feature",
  "properties": {
    "addr:full":"20 Marco Lake Dr Marco Island FL 34145",
    "addr:housenumber":"20",
    "addr:postcode":"34145",
    "addr:street":"Marco Lake Dr",
    "iso:country":"US",
    "sg:address":"20 Marco Lake Dr",
    "sg:city":"Marco Island",
    "sg:classifiers":[
        {
            "category":"Health Services",
            "subcategory":"Medical Lab",
            "type":"Services"
        }
    ],
    "sg:phone":"+1 239 389 6956",
    "sg:postcode":"34145",
    "sg:province":"FL",
    "sg:tags":[
        "laboratory"
    ],
    "wof:name":"RKS Dental Lab Of Marco",
    "wof:placetype":"venue"
},
  "geometry": {"coordinates":[-81.720011,25.949114],"type":"Point"}
}