{
  "type": "Feature",
  "properties": {
    "iso:country":"US",
    "sg:address":"5340 Pine St",
    "sg:city":"Hampton",
    "sg:classifiers":[
        {
            "category":"Place Of Worship",
            "type":"Public Place"
        }
    ],
    "sg:phone":"+1 352 468 2232",
    "sg:postcode":"32044",
    "sg:province":"FL",
    "sg:tags":[
        "church"
    ],
    "wof:name":"Victory Baptist Chapel",
    "wof:placetype":"venue"
},
  "geometry": {"coordinates":[-82.134336,29.862949],"type":"Point"}
}