{
  "type": "Feature",
  "properties": {
    "addr:full":"96749 Blackrock Rd Yulee FL 32097",
    "addr:postcode":"96749;32097",
    "addr:street":"Blackrock Rd",
    "iso:country":"US",
    "sg:address":"96749 Blackrock Rd",
    "sg:city":"Yulee",
    "sg:classifiers":[
        {
            "category":"Building & Trades",
            "subcategory":"Landscaping Services",
            "type":"Services"
        }
    ],
    "sg:phone":"+1 904 491 1783",
    "sg:postcode":"32097",
    "sg:province":"FL",
    "sg:tags":[
        "lawn"
    ],
    "wof:name":"Black Rock Landscape",
    "wof:placetype":"venue"
},
  "geometry": {"coordinates":[-81.534569,30.66547],"type":"Point"}
}