{
  "type": "Feature",
  "properties": {
    "iso:country":"US",
    "sg:address":"6525 Circle Blvd",
    "sg:city":"New Port Richey",
    "sg:classifiers":[
        {
            "category":"Building & Trades",
            "subcategory":"Construction",
            "type":"Services"
        }
    ],
    "sg:phone":"+1 727 842 6532",
    "sg:postcode":"34652",
    "sg:province":"FL",
    "sg:tags":[
        "house"
    ],
    "wof:name":"Ej Construction",
    "wof:placetype":"venue"
},
  "geometry": {"coordinates":[-82.719683,28.252745],"type":"Point"}
}