{
  "type": "Feature",
  "properties": {
    "iso:country":"US",
    "sg:address":"20211 NE 15th Ct",
    "sg:city":"Miami",
    "sg:classifiers":[
        {
            "category":"Professional",
            "subcategory":"Business Services",
            "type":"Services"
        },
        {
            "category":"Professional",
            "subcategory":"Management & Consulting",
            "type":"Services"
        }
    ],
    "sg:phone":"+1 305 651 2367",
    "sg:postcode":"33179",
    "sg:province":"FL",
    "sg:tags":[
        "event"
    ],
    "sg:website":"www.advantagedms.com",
    "wof:name":"Advantage Destination Mtg Svc",
    "wof:placetype":"venue"
},
  "geometry": {"coordinates":[-80.170975,25.961535],"type":"Point"}
}