{
  "type": "Feature",
  "properties": {
    "iso:country":"US",
    "sg:address":"318 Arapaho Trl",
    "sg:city":"Winter Springs",
    "sg:classifiers":[
        {
            "category":"Shopping",
            "type":"Retail Goods"
        }
    ],
    "sg:phone":"+1 407 327 8083",
    "sg:postcode":"32708",
    "sg:province":"FL",
    "sg:tags":[
        "merchandise"
    ],
    "wof:name":"Bobs Bargain Store",
    "wof:placetype":"venue"
},
  "geometry": {"coordinates":[-81.26838100000001,28.699651],"type":"Point"}
}