{
  "type": "Feature",
  "properties": {
    "iso:country":"US",
    "sg:address":"2040 Colonial Blvd",
    "sg:city":"Fort Myers",
    "sg:classifiers":[
        {
            "category":"Education",
            "subcategory":"Vocational School",
            "type":"Public Place"
        }
    ],
    "sg:phone":"+1 239 278 1311",
    "sg:postcode":"33907",
    "sg:province":"FL",
    "sg:tags":[
        "cosmetology"
    ],
    "sg:website":"www.sunstate.edu",
    "wof:name":"Sunstate Academy",
    "wof:placetype":"venue"
},
  "geometry": {"coordinates":[-81.87123699999999,26.596772],"type":"Point"}
}