{
  "type": "Feature",
  "properties": {
    "iso:country":"US",
    "sg:address":"7216 SW 57th Ave",
    "sg:city":"South Miami",
    "sg:classifiers":[
        {
            "category":"Shopping",
            "subcategory":"Clothing, Apparel, & Fashions",
            "type":"Retail Goods"
        }
    ],
    "sg:phone":"+1 305 666 9655",
    "sg:postcode":"33143",
    "sg:province":"FL",
    "sg:tags":[
        "children's",
        "clothing"
    ],
    "wof:name":"Little Feet and More",
    "wof:placetype":"venue"
},
  "geometry": {"coordinates":[-80.2855,25.7041],"type":"Point"}
}