{
  "type": "Feature",
  "properties": {
    "iso:country":"US",
    "sg:address":"4809 Griffin Blvd",
    "sg:city":"Fort Myers",
    "sg:classifiers":[
        {
            "category":"Professional",
            "subcategory":"Management & Consulting",
            "type":"Services"
        }
    ],
    "sg:phone":"+1 239 482 2050",
    "sg:postcode":"33908",
    "sg:province":"FL",
    "sg:tags":[
        "consultant",
        "medical",
        "legal"
    ],
    "wof:name":"Corporate Compliance Cnsltng",
    "wof:placetype":"venue"
},
  "geometry": {"coordinates":[-81.93214999999999,26.538943],"type":"Point"}
}