{
  "type": "Feature",
  "properties": {
    "iso:country":"US",
    "sg:address":"21902 State Hwy 46",
    "sg:city":"Mount Dora",
    "sg:classifiers":[
        {
            "category":"Manufacturing",
            "subcategory":"Tools & Machinery",
            "type":"Manufacturing & Wholesale Goods"
        }
    ],
    "sg:phone":"+1 352 383 1222",
    "sg:postcode":"32757",
    "sg:province":"FL",
    "sg:tags":[
        "process",
        "control",
        "mfg",
        "instrument",
        "con"
    ],
    "wof:name":"Miller Pipeline Corporation",
    "wof:placetype":"venue"
},
  "geometry": {"coordinates":[-81.59479899999999,28.800581],"type":"Point"}
}