{
  "type": "Feature",
  "properties": {
    "iso:country":"US",
    "sg:address":"4527 120th St",
    "sg:city":"Jacksonville",
    "sg:classifiers":[
        {
            "category":"Bars & Pubs",
            "type":"Food & Drink"
        }
    ],
    "sg:phone":"+1 904 778 8675",
    "sg:postcode":"32244",
    "sg:province":"FL",
    "sg:tags":[
        "drinking"
    ],
    "wof:name":"Murray's Tavern",
    "wof:placetype":"venue"
},
  "geometry": {"coordinates":[-81.70080799999999,30.232394],"type":"Point"}
}