{
  "type": "Feature",
  "properties": {
    "iso:country":"US",
    "sg:address":"2 N Federal Hwy",
    "sg:city":"Fort Lauderdale",
    "sg:classifiers":[
        {
            "category":"Building & Trades",
            "subcategory":"Electrical",
            "type":"Services"
        }
    ],
    "sg:phone":"+1 954 727 9010",
    "sg:postcode":"33301",
    "sg:province":"FL",
    "sg:tags":[
        "electric",
        "contractor"
    ],
    "wof:name":"Stryker Electric The Waverly",
    "wof:placetype":"venue"
},
  "geometry": {"coordinates":[-80.137255,26.123368],"type":"Point"}
}