{
  "type": "Feature",
  "properties": {
    "iso:country":"US",
    "sg:address":"849 Deltona Blvd",
    "sg:city":"Deltona",
    "sg:classifiers":[
        {
            "category":"Shopping",
            "subcategory":"Florist",
            "type":"Retail Goods"
        }
    ],
    "sg:phone":"+1 386 860 2629",
    "sg:postcode":"32725",
    "sg:province":"FL",
    "wof:name":"Deltona Floral",
    "wof:placetype":"venue"
},
  "geometry": {"coordinates":[-81.2771,28.8857],"type":"Point"}
}