{
  "type": "Feature",
  "properties": {
    "iso:country":"US",
    "sg:address":"1960 SR-44",
    "sg:city":"New Smyrna Beach",
    "sg:classifiers":[
        {
            "category":"Restaurant",
            "type":"Food & Drink"
        }
    ],
    "sg:menulink":"http://www.allmenus.com/fl/new-smyrna-beach/89436-el-azteca/menu/",
    "sg:phone":"+1 386 427 2567",
    "sg:postcode":"32168",
    "sg:province":"FL",
    "sg:tags":[
        "mexican"
    ],
    "wof:name":"El Azteca",
    "wof:placetype":"venue"
},
  "geometry": {"coordinates":[-80.94789,29.013432],"type":"Point"}
}