{
  "type": "Feature",
  "properties": {
    "iso:country":"US",
    "sg:address":"19803 NE 12th Pl",
    "sg:city":"Miami",
    "sg:classifiers":[
        {
            "category":"Utilities",
            "subcategory":"Electric",
            "type":"Services"
        }
    ],
    "sg:phone":"+1 305 653 6659",
    "sg:postcode":"33179",
    "sg:province":"FL",
    "sg:tags":[
        "equipment",
        "supplies-repair",
        "electronic",
        "equipment-repair"
    ],
    "wof:name":"Ckm Electronics Inc",
    "wof:placetype":"venue"
},
  "geometry": {"coordinates":[-80.176242,25.957123],"type":"Point"}
}