{
  "type": "Feature",
  "properties": {
    "iso:country":"US",
    "sg:address":"220 71st St",
    "sg:city":"Miami Beach",
    "sg:classifiers":[
        {
            "category":"Wholesale",
            "subcategory":"Electrical",
            "type":"Manufacturing & Wholesale Goods"
        }
    ],
    "sg:phone":"+1 305 868 8383",
    "sg:postcode":"33141",
    "sg:province":"FL",
    "sg:tags":[
        "control",
        "security",
        "system"
    ],
    "wof:name":"Security Deception Detection",
    "wof:placetype":"venue"
},
  "geometry": {"coordinates":[-80.121251,25.856031],"type":"Point"}
}