{
  "type": "Feature",
  "properties": {
    "addr:full":"15860 SW 143rd Ave Miami FL 33177",
    "addr:housenumber":"15860",
    "addr:postcode":"33177",
    "addr:street":"Sw 143Rd Ave",
    "iso:country":"US",
    "sg:address":"15860 SW 143rd Ave",
    "sg:city":"Miami",
    "sg:classifiers":[
        {
            "category":"Government",
            "subcategory":"Post Office",
            "type":"Public Place"
        }
    ],
    "sg:phone":"+1 305 971 6579",
    "sg:postcode":"33177",
    "sg:province":"FL",
    "sg:tags":[
        "delivery",
        "courier"
    ],
    "wof:name":"Fusion Courier Inc",
    "wof:placetype":"venue"
},
  "geometry": {"coordinates":[-80.423964,25.620381],"type":"Point"}
}