{
  "type": "Feature",
  "properties": {
    "addr:full":"9402 N US Hwy 1 Sebastian FL 32958",
    "addr:housenumber":"9402",
    "addr:postcode":"32958",
    "addr:street":"N Us Hwy 1",
    "iso:country":"US",
    "sg:address":"9402 N US Hwy 1",
    "sg:city":"Sebastian",
    "sg:classifiers":[
        {
            "category":"Shopping",
            "subcategory":"Bicycles & Sporting Goods",
            "type":"Retail Goods"
        }
    ],
    "sg:phone":"+1 772 589 7234",
    "sg:postcode":"32958",
    "sg:province":"FL",
    "wof:name":"Bike Depot",
    "wof:placetype":"venue"
},
  "geometry": {"coordinates":[-80.44283,27.76548],"type":"Point"}
}