{
  "type": "Feature",
  "properties": {
    "addr:full":"14365 S US Hwy 441 Summerfield FL 34420",
    "addr:housenumber":"14365",
    "addr:postcode":"34420",
    "addr:street":"S Us Hwy 441",
    "iso:country":"US",
    "sg:address":"14365 S US Hwy 441",
    "sg:city":"Summerfield",
    "sg:classifiers":[
        {
            "category":"Sports & Exercise",
            "subcategory":"Race Track",
            "type":"Entertainment"
        }
    ],
    "sg:phone":"+1 352 347 2640",
    "sg:postcode":"34420",
    "sg:province":"FL",
    "wof:name":"Spinney Racing",
    "wof:placetype":"venue"
},
  "geometry": {"coordinates":[-82.009883,29.012632],"type":"Point"}
}