{
  "type": "Feature",
  "properties": {
    "addr:full":"11800 Mills Dr Miami FL 33183",
    "addr:housenumber":"11800",
    "addr:postcode":"33183",
    "addr:street":"Mills Dr",
    "iso:country":"US",
    "sg:address":"11800 Mills Dr",
    "sg:city":"Miami",
    "sg:classifiers":[
        {
            "category":"Shopping",
            "subcategory":"Department Store",
            "type":"Retail Goods"
        }
    ],
    "sg:phone":"+1 305 596 6221",
    "sg:postcode":"33183",
    "sg:province":"FL",
    "sg:website":"http://www.kohls.com",
    "wof:name":"Kohl's",
    "wof:placetype":"venue"
},
  "geometry": {"coordinates":[-80.385841,25.68709],"type":"Point"}
}