{
  "type": "Feature",
  "properties": {
    "addr:full":"3013 del Prado Blvd S Cape Coral FL 33904",
    "addr:housenumber":"3013",
    "addr:postcode":"33904",
    "addr:street":"Del Prado Blvd S",
    "iso:country":"US",
    "sg:address":"3013 del Prado Blvd S",
    "sg:city":"Cape Coral",
    "sg:classifiers":[
        {
            "category":"Insurance",
            "subcategory":"Title Insurance",
            "type":"Services"
        }
    ],
    "sg:phone":"+1 239 573 6022",
    "sg:postcode":"33904",
    "sg:province":"FL",
    "wof:name":"First American Title Co",
    "wof:placetype":"venue"
},
  "geometry": {"coordinates":[-81.9415,26.596273],"type":"Point"}
}