{
  "type": "Feature",
  "properties": {
    "iso:country":"US",
    "sg:address":"8510 NW 68th St",
    "sg:city":"Miami",
    "sg:classifiers":[
        {
            "category":"Building & Trades",
            "subcategory":"Construction",
            "type":"Services"
        }
    ],
    "sg:phone":"+1 305 592 8181",
    "sg:postcode":"33166",
    "sg:province":"FL",
    "sg:tags":[
        "foundation",
        "contractor"
    ],
    "wof:name":"H J Foundation Inc",
    "wof:placetype":"venue"
},
  "geometry": {"coordinates":[-80.33670600000001,25.835176],"type":"Point"}
}