{
  "type": "Feature",
  "properties": {
    "iso:country":"US",
    "sg:address":"401 Biscayne Blvd Ste N100",
    "sg:city":"Miami",
    "sg:classifiers":[
        {
            "category":"Restaurant",
            "type":"Food & Drink"
        }
    ],
    "sg:phone":"+1 305 375 0666",
    "sg:postcode":"33132",
    "sg:province":"FL",
    "sg:tags":[
        "american",
        "latin"
    ],
    "sg:website":"www.beststeakinmiami.com/",
    "wof:name":"Los Ranchos Restaurant",
    "wof:placetype":"venue"
},
  "geometry": {"coordinates":[-80.185952,25.77639],"type":"Point"}
}