{
  "type": "Feature",
  "properties": {
    "iso:country":"US",
    "sg:address":"10167 Camelback Ln",
    "sg:city":"Boca Raton",
    "sg:classifiers":[
        {
            "category":"Professional",
            "subcategory":"Management & Consulting",
            "type":"Services"
        }
    ],
    "sg:phone":"+1 561 479 2294",
    "sg:postcode":"33498",
    "sg:province":"FL",
    "sg:tags":[
        "consultant",
        "training"
    ],
    "wof:name":"Listing Master Co",
    "wof:placetype":"venue"
},
  "geometry": {"coordinates":[-80.206126,26.37703],"type":"Point"}
}