{
  "type": "Feature",
  "properties": {
    "iso:country":"US",
    "sg:address":"7826 Saddle Creek Trl",
    "sg:city":"Sarasota",
    "sg:classifiers":[
        {
            "category":"Sports & Exercise",
            "subcategory":"Golf",
            "type":"Entertainment"
        }
    ],
    "sg:phone":"+1 941 922 7880",
    "sg:postcode":"34241",
    "sg:province":"FL",
    "sg:tags":[
        "course"
    ],
    "wof:name":"Winter Golf Pass",
    "wof:placetype":"venue"
},
  "geometry": {"coordinates":[-82.378435,27.261111],"type":"Point"}
}