{
  "type": "Feature",
  "properties": {
    "addr:full":"6085C Deacon Rd Sarasota FL 34238",
    "addr:housenumber":"6085c",
    "addr:postcode":"34238",
    "addr:street":"Deacon Rd",
    "iso:country":"US",
    "sg:address":"6085C Deacon Rd",
    "sg:city":"Sarasota",
    "sg:classifiers":[
        {
            "category":"Autos & Motor Vehicles",
            "subcategory":"Auto Supplies",
            "type":"Retail Goods"
        },
        {
            "category":"Retail",
            "subcategory":"Auto Repair",
            "type":"Services"
        }
    ],
    "sg:phone":"+1 941 922 0624",
    "sg:postcode":"34238",
    "sg:province":"FL",
    "sg:tags":[
        "body",
        "automobile",
        "truck",
        "painting",
        "repairing"
    ],
    "wof:name":"Beautiful Bodies Auto",
    "wof:placetype":"venue"
},
  "geometry": {"coordinates":[-82.477836,27.266239],"type":"Point"}
}