{
  "type": "Feature",
  "properties": {
    "addr:full":"2000 5th Ave N St Petersburg FL 33713",
    "addr:housenumber":"2000",
    "addr:postcode":"33713",
    "addr:street":"5Th Ave N",
    "iso:country":"US",
    "sg:address":"2000 5th Ave N",
    "sg:city":"St Petersburg",
    "sg:classifiers":[
        {
            "category":"Health Services",
            "subcategory":"Doctor",
            "type":"Services"
        }
    ],
    "sg:phone":"+1 727 894 3065",
    "sg:postcode":"33713",
    "sg:province":"FL",
    "sg:tags":[
        "dentist"
    ],
    "wof:name":"Lawrence N Klein DDS",
    "wof:placetype":"venue"
},
  "geometry": {"coordinates":[-82.66105399999999,27.777464],"type":"Point"}
}