{
  "type": "Feature",
  "properties": {
    "iso:country":"US",
    "sg:address":"10362A SE 52nd Ct",
    "sg:city":"Belleview",
    "sg:classifiers":[
        {
            "category":"Building & Trades",
            "subcategory":"Landscaping Services",
            "type":"Services"
        }
    ],
    "sg:phone":"+1 352 347 1489",
    "sg:postcode":"34420",
    "sg:province":"FL",
    "sg:tags":[
        "tree"
    ],
    "wof:name":"Osborne Collin Tree Svc",
    "wof:placetype":"venue"
},
  "geometry": {"coordinates":[-82.06176000000001,29.072103],"type":"Point"}
}