{
  "type": "Feature",
  "properties": {
    "iso:country":"US",
    "sg:address":"910 25th St E",
    "sg:city":"Bradenton",
    "sg:classifiers":[
        {
            "category":"Retail",
            "subcategory":"Repair Shop",
            "type":"Services"
        }
    ],
    "sg:phone":"+1 941 746 3868",
    "sg:postcode":"34208",
    "sg:province":"FL",
    "sg:tags":[
        "upholsterer"
    ],
    "wof:name":"Allison's Upholstery",
    "wof:placetype":"venue"
},
  "geometry": {"coordinates":[-82.533467,27.490351],"type":"Point"}
}