{
  "type": "Feature",
  "properties": {
    "addr:full":"3909 Riverview Blvd Bradenton FL 34209",
    "addr:housenumber":"3909",
    "addr:postcode":"34209",
    "addr:street":"Riverview Blvd",
    "iso:country":"US",
    "sg:address":"3909 Riverview Blvd",
    "sg:city":"Bradenton",
    "sg:classifiers":[
        {
            "category":"Building & Trades",
            "subcategory":"Construction",
            "type":"Services"
        }
    ],
    "sg:phone":"+1 941 747 5799",
    "sg:postcode":"34209",
    "sg:province":"FL",
    "sg:tags":[
        "contractor"
    ],
    "wof:name":"Kirby Tile",
    "wof:placetype":"venue"
},
  "geometry": {"coordinates":[-82.600515,27.501494],"type":"Point"}
}