{
  "type": "Feature",
  "properties": {
    "iso:country":"US",
    "sg:address":"2915 W Navy Blvd",
    "sg:city":"Pensacola",
    "sg:classifiers":[
        {
            "category":"Home & Garden",
            "subcategory":"Home Furnishings",
            "type":"Retail Goods"
        }
    ],
    "sg:phone":"+1 850 432 4983",
    "sg:postcode":"32505",
    "sg:province":"FL",
    "sg:tags":[
        "linen"
    ],
    "wof:name":"Gulf Coast Linen & Rental",
    "wof:placetype":"venue"
},
  "geometry": {"coordinates":[-87.25087000000001,30.412246],"type":"Point"}
}