{
  "type": "Feature",
  "properties": {
    "iso:country":"US",
    "sg:address":"500 N Washington Ave",
    "sg:city":"Titusville",
    "sg:classifiers":[
        {
            "category":"Health Services",
            "subcategory":"Medical Lab",
            "type":"Services"
        }
    ],
    "sg:phone":"+1 321 383 0262",
    "sg:postcode":"32796",
    "sg:province":"FL",
    "sg:tags":[
        "laboratory"
    ],
    "wof:name":"Brevard Community Laboratory",
    "wof:placetype":"venue"
},
  "geometry": {"coordinates":[-80.813919,28.619365],"type":"Point"}
}