{
  "type": "Feature",
  "properties": {
    "iso:country":"US",
    "sg:address":"5131 Brandeis Cir S",
    "sg:city":"Sarasota",
    "sg:classifiers":[
        {
            "category":"Retail",
            "subcategory":"Animal Services",
            "type":"Services"
        }
    ],
    "sg:phone":"+1 941 355 4605",
    "sg:postcode":"34243",
    "sg:province":"FL",
    "sg:tags":[
        "wire",
        "pet",
        "haired",
        "fox",
        "breeder",
        "terrier"
    ],
    "wof:name":"Carole Beattie",
    "wof:placetype":"venue"
},
  "geometry": {"coordinates":[-82.496995,27.38914],"type":"Point"}
}