{
  "type": "Feature",
  "properties": {
    "addr:full":"11307 N Main St Jacksonville FL 32218",
    "addr:housenumber":"11307",
    "addr:postcode":"32218",
    "addr:street":"N Main St",
    "iso:country":"US",
    "sg:address":"11307 N Main St",
    "sg:city":"Jacksonville",
    "sg:classifiers":[
        {
            "category":"Autos & Motor Vehicles",
            "subcategory":"Fuel & Gas Station",
            "type":"Retail Goods"
        },
        {
            "category":"Food & Beverages",
            "subcategory":"Groceries & Convenience Stores",
            "type":"Retail Goods"
        }
    ],
    "sg:phone":"+1 904 757 3848",
    "sg:postcode":"32218",
    "sg:province":"FL",
    "sg:website":"http://www.southeast-petro.com",
    "wof:name":"Sunshine Food Mart",
    "wof:placetype":"venue"
},
  "geometry": {"coordinates":[-81.641143,30.441457],"type":"Point"}
}