{
  "type": "Feature",
  "properties": {
    "iso:country":"US",
    "sg:address":"3014 S Woodland Blvd",
    "sg:city":"Deland",
    "sg:classifiers":[
        {
            "category":"Communications",
            "type":"Services"
        }
    ],
    "sg:phone":"+1 386 775 2850",
    "sg:postcode":"32720",
    "sg:province":"FL",
    "wof:name":"Aalcom Communications Bruce",
    "wof:placetype":"venue"
},
  "geometry": {"coordinates":[-81.299007,28.973136],"type":"Point"}
}