{
  "type": "Feature",
  "properties": {
    "iso:country":"US",
    "sg:address":"940 Ocean Dr",
    "sg:city":"Miami Beach",
    "sg:classifiers":[
        {
            "category":"Restaurant",
            "type":"Food & Drink"
        }
    ],
    "sg:phone":"+1 305 531 3500",
    "sg:postcode":"33139",
    "sg:province":"FL",
    "sg:tags":[
        "eating"
    ],
    "wof:name":"Paparazzi Di Roma",
    "wof:placetype":"venue"
},
  "geometry": {"coordinates":[-80.13082300000001,25.779891],"type":"Point"}
}