{
  "type": "Feature",
  "properties": {
    "iso:country":"US",
    "sg:address":"2409 Ramblewood Ct",
    "sg:city":"Tallahassee",
    "sg:classifiers":[
        {
            "category":"Organizations",
            "subcategory":"Professional Association",
            "type":"Services"
        }
    ],
    "sg:phone":"+1 850 386 5245",
    "sg:postcode":"32303",
    "sg:province":"FL",
    "wof:name":"Florida Association Of Dive",
    "wof:placetype":"venue"
},
  "geometry": {"coordinates":[-84.302992,30.476089],"type":"Point"}
}