{
  "type": "Feature",
  "properties": {
    "iso:country":"US",
    "sg:address":"12555 N Miami Ave",
    "sg:city":"North Miami",
    "sg:classifiers":[
        {
            "category":"Building & Trades",
            "subcategory":"Cleaning & Sanitation",
            "type":"Services"
        }
    ],
    "sg:phone":"+1 305 754 9308",
    "sg:postcode":"33168",
    "sg:province":"FL",
    "sg:tags":[
        "janitor"
    ],
    "wof:name":"Jean's Services",
    "wof:placetype":"venue"
},
  "geometry": {"coordinates":[-80.19868099999999,25.891564],"type":"Point"}
}