{
  "type": "Feature",
  "properties": {
    "addr:full":"12351 W Colonial Dr Winter Garden FL 34787",
    "addr:housenumber":"12351",
    "addr:postcode":"34787",
    "addr:street":"W Colonial Dr",
    "iso:country":"US",
    "sg:address":"12351 W Colonial Dr",
    "sg:city":"Winter Garden",
    "sg:classifiers":[
        {
            "category":"Restaurant",
            "type":"Food & Drink"
        }
    ],
    "sg:phone":"+1 407 877 6776",
    "sg:postcode":"34787",
    "sg:province":"FL",
    "sg:tags":[
        "out"
    ],
    "wof:name":"House Of Adobo",
    "wof:placetype":"venue"
},
  "geometry": {"coordinates":[-81.565079,28.551139],"type":"Point"}
}