{
  "type": "Feature",
  "properties": {
    "addr:full":"6034 Lake Grasmere Way Fort Myers FL 33908",
    "addr:housenumber":"6034",
    "addr:postcode":"33908",
    "addr:street":"Lake Grasmere Way",
    "iso:country":"US",
    "sg:address":"6034 Lake Grasmere Way",
    "sg:city":"Fort Myers",
    "sg:classifiers":[
        {
            "category":"Professional",
            "subcategory":"Accounting & Tax Preparation",
            "type":"Services"
        }
    ],
    "sg:phone":"+1 239 481 6323",
    "sg:postcode":"33908",
    "sg:province":"FL",
    "sg:tags":[
        "accountant"
    ],
    "wof:name":"Chuffo Accounting Inc",
    "wof:placetype":"venue"
},
  "geometry": {"coordinates":[-81.85761599999999,26.486428],"type":"Point"}
}