{
  "type": "Feature",
  "properties": {
    "addr:full":"4900 Palmetto Dr Fort Pierce FL 34982",
    "addr:housenumber":"4900",
    "addr:postcode":"34982",
    "addr:street":"Palmetto Dr",
    "iso:country":"US",
    "sg:address":"4900 Palmetto Dr",
    "sg:city":"Fort Pierce",
    "sg:classifiers":[
        {
            "category":"Personal",
            "subcategory":"Beauty Salon",
            "type":"Services"
        }
    ],
    "sg:phone":"+1 772 460 0309",
    "sg:postcode":"34982",
    "sg:province":"FL",
    "sg:tags":[
        "shop"
    ],
    "wof:name":"Dees Salon Inc",
    "wof:placetype":"venue"
},
  "geometry": {"coordinates":[-80.312483,27.374009],"type":"Point"}
}