{
  "type": "Feature",
  "properties": {
    "iso:country":"US",
    "sg:address":"1976 SW Ranch Trl",
    "sg:city":"Stuart",
    "sg:classifiers":[
        {
            "category":"Building & Trades",
            "subcategory":"Plumbing",
            "type":"Services"
        }
    ],
    "sg:phone":"+1 772 283 6935",
    "sg:postcode":"34997",
    "sg:province":"FL",
    "sg:tags":[
        "specializing",
        "contractor",
        "heating",
        "pool",
        "air"
    ],
    "wof:name":"Hydro Thermal Systems Inc",
    "wof:placetype":"venue"
},
  "geometry": {"coordinates":[-80.278248,27.095267],"type":"Point"}
}