{
  "type": "Feature",
  "properties": {
    "addr:full":"5945 W Hallandale Beach Blvd Hollywood FL 33023",
    "addr:housenumber":"5945",
    "addr:postcode":"33023",
    "addr:street":"W Hallandale Beach Blvd",
    "iso:country":"US",
    "sg:address":"5945 W Hallandale Beach Blvd",
    "sg:city":"Hollywood",
    "sg:classifiers":[
        {
            "category":"Organizations",
            "subcategory":"Religious Organization",
            "type":"Services"
        }
    ],
    "sg:phone":"+1 954 986 0389",
    "sg:postcode":"33023",
    "sg:province":"FL",
    "sg:tags":[
        "church"
    ],
    "wof:name":"True Vine Christian Center",
    "wof:placetype":"venue"
},
  "geometry": {"coordinates":[-80.20585800000001,25.984722],"type":"Point"}
}