{
  "type": "Feature",
  "properties": {
    "addr:full":"11657 Beach Blvd Jacksonville FL 32246",
    "addr:housenumber":"11657",
    "addr:postcode":"32246",
    "addr:street":"Beach Blvd",
    "iso:country":"US",
    "sg:address":"11657 Beach Blvd",
    "sg:city":"Jacksonville",
    "sg:classifiers":[
        {
            "category":"Food & Beverages",
            "subcategory":"Bakery",
            "type":"Retail Goods"
        }
    ],
    "sg:phone":"+1 904 998 2255",
    "sg:postcode":"32246",
    "sg:province":"FL",
    "sg:website":"www.dunkindonuts.com",
    "wof:name":"Dunkin Donuts",
    "wof:placetype":"venue"
},
  "geometry": {"coordinates":[-81.517606,30.287086],"type":"Point"}
}