{
  "type": "Feature",
  "properties": {
    "iso:country":"US",
    "sg:address":"330 US Hwy 27",
    "sg:city":"South Bay",
    "sg:classifiers":[
        {
            "category":"Wholesale",
            "subcategory":"Non-durable Goods",
            "type":"Manufacturing & Wholesale Goods"
        }
    ],
    "sg:phone":"+1 561 996 6455",
    "sg:postcode":"33493",
    "sg:province":"FL",
    "sg:tags":[
        "ice"
    ],
    "wof:name":"Agice",
    "wof:placetype":"venue"
},
  "geometry": {"coordinates":[-80.712515,26.64657],"type":"Point"}
}