{
  "type": "Feature",
  "properties": {
    "iso:country":"US",
    "sg:address":"782 NW 42nd Ave Ste 530",
    "sg:city":"Miami",
    "sg:classifiers":[
        {
            "category":"Professional",
            "subcategory":"Lawyer & Legal Services",
            "type":"Services"
        }
    ],
    "sg:phone":"+1 305 442 1439",
    "sg:postcode":"33126",
    "sg:province":"FL",
    "wof:name":"Bujan Jesus F Atty",
    "wof:placetype":"venue"
},
  "geometry": {"coordinates":[-80.264099,25.7796],"type":"Point"}
}