{
  "type": "Feature",
  "properties": {
    "iso:country":"US",
    "sg:address":"12484 SW 119th Pl",
    "sg:city":"Miami",
    "sg:classifiers":[
        {
            "category":"Shopping",
            "subcategory":"Computers & Home Electronics",
            "type":"Retail Goods"
        }
    ],
    "sg:phone":"+1 786 293 2755",
    "sg:postcode":"33186",
    "sg:province":"FL",
    "sg:tags":[
        "software"
    ],
    "wof:name":"Precise Software Solutions",
    "wof:placetype":"venue"
},
  "geometry": {"coordinates":[-80.38846599999999,25.651415],"type":"Point"}
}