{
  "type": "Feature",
  "properties": {
    "addr:full":"5314 N Falkenburg Rd Tampa FL 33610",
    "addr:housenumber":"5314",
    "addr:postcode":"33610",
    "addr:street":"N Falkenburg Rd",
    "iso:country":"US",
    "sg:address":"5314 N Falkenburg Rd",
    "sg:city":"Tampa",
    "sg:classifiers":[
        {
            "category":"Retail",
            "subcategory":"Repair Shop",
            "type":"Services"
        },
        {
            "category":"Home & Garden",
            "subcategory":"Building Materials",
            "type":"Retail Goods"
        },
        {
            "category":"Building & Trades",
            "subcategory":"Construction",
            "type":"Services"
        }
    ],
    "sg:phone":"+1 813 631 1008",
    "sg:postcode":"33610",
    "sg:province":"FL",
    "sg:tags":[
        "bathroom",
        "altering",
        "handyman",
        "contractor",
        "fix-it",
        "maintenance",
        "improvement",
        "remodeling"
    ],
    "sg:website":"http://handymanconnectiontampafl.com",
    "wof:name":"Handyman Connection",
    "wof:placetype":"venue"
},
  "geometry": {"coordinates":[-82.33519099999999,27.993159],"type":"Point"}
}