{
  "type": "Feature",
  "properties": {
    "iso:country":"US",
    "sg:address":"2315 SE Aviation Way",
    "sg:city":"Stuart",
    "sg:classifiers":[
        {
            "category":"Autos & Motor Vehicles",
            "subcategory":"Automobile Sales",
            "type":"Retail Goods"
        }
    ],
    "sg:phone":"+1 772 781 1950",
    "sg:postcode":"34996",
    "sg:province":"FL",
    "sg:tags":[
        "aircraft"
    ],
    "wof:name":"East Coast Jet Ctr",
    "wof:placetype":"venue"
},
  "geometry": {"coordinates":[-80.224442,27.172163],"type":"Point"}
}