{
  "type": "Feature",
  "properties": {
    "iso:country":"US",
    "sg:address":"10130 Trailwood Cir",
    "sg:city":"Jupiter",
    "sg:classifiers":[
        {
            "category":"Shopping",
            "subcategory":"Clothing, Apparel, & Fashions",
            "type":"Retail Goods"
        }
    ],
    "sg:phone":"+1 561 741 4009",
    "sg:postcode":"33478",
    "sg:province":"FL",
    "sg:tags":[
        "infant",
        "wear"
    ],
    "wof:name":"Kimmie & Heidi Designs Inc",
    "wof:placetype":"venue"
},
  "geometry": {"coordinates":[-80.20021800000001,26.937555],"type":"Point"}
}