{
  "type": "Feature",
  "properties": {
    "iso:country":"US",
    "sg:address":"10338 S Forestline Ave",
    "sg:city":"Inverness",
    "sg:classifiers":[
        {
            "category":"Health Services",
            "subcategory":"Clinic",
            "type":"Services"
        }
    ],
    "sg:phone":"+1 352 344 4060",
    "sg:postcode":"34452",
    "sg:province":"FL",
    "sg:tags":[
        "osteopathic"
    ],
    "wof:name":"Let Bob Defebbo Do It",
    "wof:placetype":"venue"
},
  "geometry": {"coordinates":[-82.383306,28.719094],"type":"Point"}
}