{
  "type": "Feature",
  "properties": {
    "iso:country":"US",
    "sg:address":"6404 7th Avenue Cir W",
    "sg:city":"Bradenton",
    "sg:classifiers":[
        {
            "category":"Real Estate",
            "subcategory":"Real Estate Services",
            "type":"Services"
        },
        {
            "category":"Building & Trades",
            "subcategory":"Construction",
            "type":"Services"
        },
        {
            "category":"Real Estate",
            "subcategory":"Real Estate Operator",
            "type":"Services"
        }
    ],
    "sg:phone":"+1 941 761 0444",
    "sg:postcode":"34209",
    "sg:province":"FL",
    "sg:tags":[
        "management",
        "apartment",
        "condominium"
    ],
    "wof:name":"Hidden Lake Condominiums",
    "wof:placetype":"venue"
},
  "geometry": {"coordinates":[-82.62834599999999,27.493696],"type":"Point"}
}