{
  "type": "Feature",
  "properties": {
    "iso:country":"US",
    "sg:address":"3028 Riverdale Rd",
    "sg:city":"Orlando",
    "sg:classifiers":[
        {
            "category":"Communications",
            "type":"Services"
        }
    ],
    "sg:phone":"+1 407 657 1201",
    "sg:postcode":"32817",
    "sg:province":"FL",
    "sg:tags":[
        "equipment",
        "satellite",
        "system"
    ],
    "wof:name":"W & W Installations",
    "wof:placetype":"venue"
},
  "geometry": {"coordinates":[-81.226969,28.590792],"type":"Point"}
}