{
  "type": "Feature",
  "properties": {
    "iso:country":"US",
    "sg:address":"933 Lee Rd",
    "sg:city":"Orlando",
    "sg:classifiers":[
        {
            "category":"Professional",
            "type":"Services"
        }
    ],
    "sg:phone":"+1 407 628 9984",
    "sg:postcode":"32810",
    "sg:province":"FL",
    "wof:name":"Kalfa US Inc",
    "wof:placetype":"venue"
},
  "geometry": {"coordinates":[-81.39682000000001,28.605887],"type":"Point"}
}