{
  "type": "Feature",
  "properties": {
    "addr:full":"2145 W Pensacola St Tallahassee FL 32304",
    "addr:housenumber":"2145",
    "addr:postcode":"32304",
    "addr:street":"W Pensacola St",
    "iso:country":"US",
    "sg:address":"2145 W Pensacola St",
    "sg:city":"Tallahassee",
    "sg:classifiers":[
        {
            "category":"Organizations",
            "subcategory":"Religious Organization",
            "type":"Services"
        }
    ],
    "sg:phone":"+1 850 576 3124",
    "sg:postcode":"32304",
    "sg:province":"FL",
    "wof:name":"Calvary United Methdst Church",
    "wof:placetype":"venue"
},
  "geometry": {"coordinates":[-84.322722,30.440769],"type":"Point"}
}