{
  "type": "Feature",
  "properties": {
    "iso:country":"US",
    "sg:address":"415 NW 28th St",
    "sg:city":"Miami",
    "sg:phone":"+1 305 576 0760",
    "sg:postcode":"33127",
    "sg:province":"FL",
    "sg:tags":[
        "transmission",
        "facsimile"
    ],
    "wof:name":"Fax Line",
    "wof:placetype":"venue"
},
  "geometry": {"coordinates":[-80.20214799999999,25.802888],"type":"Point"}
}