{
  "type": "Feature",
  "properties": {
    "addr:full":"180 NE 164th St Miami FL 33162",
    "addr:housenumber":"180",
    "addr:postcode":"33162",
    "addr:street":"Ne 164Th St",
    "iso:country":"US",
    "sg:address":"180 NE 164th St",
    "sg:city":"Miami",
    "sg:classifiers":[
        {
            "category":"Real Estate",
            "subcategory":"Real Estate Agent",
            "type":"Services"
        }
    ],
    "sg:phone":"+1 305 947 1963",
    "sg:postcode":"33162",
    "sg:province":"FL",
    "wof:name":"Reasonable Enterprise Inc",
    "wof:placetype":"venue"
},
  "geometry": {"coordinates":[-80.199462,25.925274],"type":"Point"}
}