{
  "type": "Feature",
  "properties": {
    "iso:country":"US",
    "sg:address":"706 S Dixie Hwy",
    "sg:city":"Coral Gables",
    "sg:classifiers":[
        {
            "category":"Health Services",
            "subcategory":"Health Practitioner",
            "type":"Services"
        }
    ],
    "sg:phone":"+1 305 662 5585",
    "sg:postcode":"33146",
    "sg:province":"FL",
    "sg:tags":[
        "acupuncture"
    ],
    "wof:name":"Acupuncture Specialist",
    "wof:placetype":"venue"
},
  "geometry": {"coordinates":[-80.266762,25.722442],"type":"Point"}
}