{
  "type": "Feature",
  "properties": {
    "iso:country":"US",
    "sg:address":"1730 Lee Rd",
    "sg:city":"Orlando",
    "sg:classifiers":[
        {
            "category":"Autos & Motor Vehicles",
            "subcategory":"Automobile Sales",
            "type":"Retail Goods"
        }
    ],
    "sg:phone":"+1 407 296 9525",
    "sg:postcode":"32810",
    "sg:province":"FL",
    "sg:tags":[
        "car",
        "dealer"
    ],
    "wof:name":"Global Auto Inc",
    "wof:placetype":"venue"
},
  "geometry": {"coordinates":[-81.405866,28.604671],"type":"Point"}
}