{
  "type": "Feature",
  "properties": {
    "iso:country":"US",
    "sg:address":"629 Dundee Rd",
    "sg:city":"Dundee",
    "sg:classifiers":[
        {
            "category":"Retail",
            "subcategory":"Auto Repair",
            "type":"Services"
        }
    ],
    "sg:phone":"+1 863 439 5626",
    "sg:postcode":"33838",
    "sg:province":"FL",
    "sg:tags":[
        "repairing",
        "automotive",
        "automobile"
    ],
    "wof:name":"Quality Quick Lube",
    "wof:placetype":"venue"
},
  "geometry": {"coordinates":[-81.630719,28.018587],"type":"Point"}
}