{
  "type": "Feature",
  "properties": {
    "iso:country":"US",
    "sg:address":"14307 SW 96th St",
    "sg:city":"Miami",
    "sg:classifiers":[
        {
            "category":"Banks & Credit Unions",
            "subcategory":"Financial Services",
            "type":"Services"
        }
    ],
    "sg:phone":"+1 305 385 1638",
    "sg:postcode":"33186",
    "sg:province":"FL",
    "sg:tags":[
        "investor"
    ],
    "wof:name":"Olmedo Investments Corp",
    "wof:placetype":"venue"
},
  "geometry": {"coordinates":[-80.423832,25.679386],"type":"Point"}
}