{
  "type": "Feature",
  "properties": {
    "iso:country":"US",
    "sg:address":"8302 NW 103rd St",
    "sg:city":"Hialeah",
    "sg:classifiers":[
        {
            "category":"Personal",
            "type":"Services"
        }
    ],
    "sg:phone":"+1 305 827 4646",
    "sg:postcode":"33016",
    "sg:province":"FL",
    "sg:tags":[
        "party",
        "planning",
        "event"
    ],
    "sg:website":"www.glamourbanquethall.com",
    "wof:name":"Glamour Banquet Hall",
    "wof:placetype":"venue"
},
  "geometry": {"coordinates":[-80.332078,25.869163],"type":"Point"}
}