{
  "type": "Feature",
  "properties": {
    "iso:country":"US",
    "sg:address":"11752 NW 7th Ave",
    "sg:city":"Miami",
    "sg:classifiers":[
        {
            "category":"Personal",
            "subcategory":"Beauty Salon",
            "type":"Services"
        }
    ],
    "sg:phone":"+1 305 769 3149",
    "sg:postcode":"33168",
    "sg:province":"FL",
    "sg:tags":[
        "shop"
    ],
    "wof:name":"Exquisite Hair Care",
    "wof:placetype":"venue"
},
  "geometry": {"coordinates":[-80.210606,25.882616],"type":"Point"}
}