{
  "type": "Feature",
  "properties": {
    "addr:full":"31 Whirlaway Dr Palm Coast FL 32164",
    "addr:housenumber":"31",
    "addr:postcode":"32164",
    "addr:street":"Whirlaway Dr",
    "iso:country":"US",
    "sg:address":"31 Whirlaway Dr",
    "sg:city":"Palm Coast",
    "sg:classifiers":[
        {
            "category":"Wholesale",
            "subcategory":"Durable Goods & Equipment",
            "type":"Manufacturing & Wholesale Goods"
        }
    ],
    "sg:phone":"+1 386 446 9989",
    "sg:postcode":"32164",
    "sg:province":"FL",
    "sg:tags":[
        "importer"
    ],
    "wof:name":"G & W Imports",
    "wof:placetype":"venue"
},
  "geometry": {"coordinates":[-81.241786,29.52616],"type":"Point"}
}