{
  "type": "Feature",
  "properties": {
    "iso:country":"US",
    "sg:address":"708 Fishermans Wharf",
    "sg:city":"Fort Myers Beach",
    "sg:classifiers":[
        {
            "category":"Autos & Motor Vehicles",
            "subcategory":"Boat Sales",
            "type":"Retail Goods"
        }
    ],
    "sg:phone":"+1 239 765 1010",
    "sg:postcode":"33931",
    "sg:province":"FL",
    "sg:tags":[
        "dealer",
        "sales"
    ],
    "wof:name":"Performance Boats-Hurricane",
    "wof:placetype":"venue"
},
  "geometry": {"coordinates":[-81.952397,26.459036],"type":"Point"}
}