{
  "type": "Feature",
  "properties": {
    "iso:country":"US",
    "sg:address":"710 10th St",
    "sg:city":"West Palm Beach",
    "sg:classifiers":[
        {
            "category":"Autos & Motor Vehicles",
            "subcategory":"Auto Supplies",
            "type":"Retail Goods"
        }
    ],
    "sg:phone":"+1 561 844 5277",
    "sg:postcode":"33403",
    "sg:province":"FL",
    "sg:tags":[
        "parts"
    ],
    "wof:name":"Discount Auto Parts 199",
    "wof:placetype":"venue"
},
  "geometry": {"coordinates":[-80.07261,26.799674],"type":"Point"}
}