{
  "type": "Feature",
  "properties": {
    "addr:full":"2135 NW 1st Ave Ocala FL 34475",
    "addr:housenumber":"2135",
    "addr:postcode":"34475",
    "addr:street":"Nw 1St Ave",
    "iso:country":"US",
    "sg:address":"2135 NW 1st Ave",
    "sg:city":"Ocala",
    "sg:classifiers":[
        {
            "category":"Personal",
            "subcategory":"Beauty Salon",
            "type":"Services"
        }
    ],
    "sg:phone":"+1 352 622 5241",
    "sg:postcode":"34475",
    "sg:province":"FL",
    "wof:name":"Audreys Braids",
    "wof:placetype":"venue"
},
  "geometry": {"coordinates":[-82.136803,29.20887],"type":"Point"}
}