{
  "type": "Feature",
  "properties": {
    "iso:country":"US",
    "sg:address":"1411 Clearlake Rd",
    "sg:city":"Cocoa",
    "sg:classifiers":[
        {
            "category":"Bars & Pubs",
            "type":"Food & Drink"
        }
    ],
    "sg:phone":"+1 321 633 7255",
    "sg:postcode":"32922",
    "sg:province":"FL",
    "wof:name":"Habits",
    "wof:placetype":"venue"
},
  "geometry": {"coordinates":[-80.755098,28.380367],"type":"Point"}
}