{
  "type": "Feature",
  "properties": {
    "addr:full":"309 South Ave Fort Walton Bch FL 32547",
    "addr:housenumber":"309",
    "addr:postcode":"32547",
    "addr:street":"South Ave Fort",
    "iso:country":"US",
    "sg:address":"309 South Ave",
    "sg:city":"Fort Walton Bch",
    "sg:classifiers":[
        {
            "category":"Building & Trades",
            "subcategory":"Construction",
            "type":"Services"
        }
    ],
    "sg:phone":"+1 850 862 2290",
    "sg:postcode":"32547",
    "sg:province":"FL",
    "sg:tags":[
        "painter"
    ],
    "wof:name":"Bass Painting",
    "wof:placetype":"venue"
},
  "geometry": {"coordinates":[-86.60788100000001,30.434437],"type":"Point"}
}