{
  "type": "Feature",
  "properties": {
    "iso:country":"US",
    "sg:address":"1335 W Brandon Blvd",
    "sg:city":"Brandon",
    "sg:classifiers":[
        {
            "category":"Shopping",
            "subcategory":"Shoes",
            "type":"Retail Goods"
        }
    ],
    "sg:phone":"+1 813 685 3030",
    "sg:postcode":"33511",
    "sg:province":"FL",
    "wof:name":"Payless Shoesource 1256",
    "wof:placetype":"venue"
},
  "geometry": {"coordinates":[-82.303532,27.937705],"type":"Point"}
}