{
  "type": "Feature",
  "properties": {
    "addr:full":"8506 Gunn Hwy Odessa FL 33556",
    "addr:housenumber":"8506",
    "addr:postcode":"33556",
    "addr:street":"Gunn Hwy",
    "iso:country":"US",
    "sg:address":"8506 Gunn Hwy",
    "sg:city":"Odessa",
    "sg:classifiers":[
        {
            "category":"Restaurant",
            "type":"Food & Drink"
        }
    ],
    "sg:menulink":"http://www.allmenus.com/fl/citrus-park-fern-lake/187502-mcdonalds/menu/",
    "sg:phone":"+1 813 920 5422",
    "sg:postcode":"33556",
    "sg:province":"FL",
    "sg:tags":[
        "burger",
        "american"
    ],
    "wof:name":"McDonald's",
    "wof:placetype":"venue"
},
  "geometry": {"coordinates":[-82.579522,28.085523],"type":"Point"}
}