{
  "type": "Feature",
  "properties": {
    "iso:country":"US",
    "sg:address":"13 Juniper Dr",
    "sg:city":"Davenport",
    "sg:classifiers":[
        {
            "category":"Organizations",
            "subcategory":"Community Association",
            "type":"Services"
        }
    ],
    "sg:phone":"+1 863 424 2342",
    "sg:postcode":"33837",
    "sg:province":"FL",
    "wof:name":"Edgehill Cmnty Recreation Assn",
    "wof:placetype":"venue"
},
  "geometry": {"coordinates":[-81.63535299999999,28.19884],"type":"Point"}
}