{
  "type": "Feature",
  "properties": {
    "addr:full":"4200 Georgia Ave West Palm Beach FL 33405",
    "addr:housenumber":"4200",
    "addr:postcode":"33405",
    "addr:street":"Georgia Ave",
    "iso:country":"US",
    "sg:address":"4200 Georgia Ave",
    "sg:city":"West Palm Beach",
    "sg:classifiers":[
        {
            "category":"Retail",
            "subcategory":"Auto Repair",
            "type":"Services"
        }
    ],
    "sg:phone":"+1 561 833 3132",
    "sg:postcode":"33405",
    "sg:province":"FL",
    "sg:tags":[
        "body",
        "automobile",
        "painting"
    ],
    "wof:name":"Worthmore Auto Body & Painting",
    "wof:placetype":"venue"
},
  "geometry": {"coordinates":[-80.058652,26.672259],"type":"Point"}
}