{
  "type": "Feature",
  "properties": {
    "iso:country":"US",
    "sg:address":"104 US Hwy 27",
    "sg:city":"Avon Park",
    "sg:classifiers":[
        {
            "category":"Personal",
            "subcategory":"Beauty Salon",
            "type":"Services"
        }
    ],
    "sg:phone":"+1 863 453 4806",
    "sg:postcode":"33825",
    "sg:province":"FL",
    "sg:tags":[
        "manicuring"
    ],
    "wof:name":"Crystal Nails",
    "wof:placetype":"venue"
},
  "geometry": {"coordinates":[-81.514499,27.594598],"type":"Point"}
}