{
  "type": "Feature",
  "properties": {
    "addr:full":"2573 NW 74th Ave Miami FL 33122",
    "addr:housenumber":"2573",
    "addr:postcode":"33122",
    "addr:street":"Nw 74Th Ave",
    "iso:country":"US",
    "sg:address":"2573 NW 74th Ave",
    "sg:city":"Miami",
    "sg:classifiers":[
        {
            "category":"Wholesale",
            "subcategory":"Drugs",
            "type":"Manufacturing & Wholesale Goods"
        }
    ],
    "sg:phone":"+1 305 593 9470",
    "sg:postcode":"33122",
    "sg:province":"FL",
    "sg:tags":[
        "perfume"
    ],
    "wof:name":"A & M Fragrances Inc",
    "wof:placetype":"venue"
},
  "geometry": {"coordinates":[-80.316964,25.797521],"type":"Point"}
}