{
  "type": "Feature",
  "properties": {
    "iso:country":"US",
    "sg:address":"3514 Mahan Dr",
    "sg:city":"Tallahassee",
    "sg:classifiers":[
        {
            "category":"Retail",
            "subcategory":"Veterinary Services",
            "type":"Services"
        }
    ],
    "sg:phone":"+1 850 878 4799",
    "sg:postcode":"32308",
    "sg:province":"FL",
    "wof:name":"Carter Frances Dvm",
    "wof:placetype":"venue"
},
  "geometry": {"coordinates":[-84.21858899999999,30.46353],"type":"Point"}
}