{
  "type": "Feature",
  "properties": {
    "addr:full":"11501 NW 15th Ln Ocala FL 34482",
    "addr:housenumber":"11501",
    "addr:postcode":"34482",
    "addr:street":"Nw 15Th Ln",
    "iso:country":"US",
    "sg:address":"11501 NW 15th Ln",
    "sg:city":"Ocala",
    "sg:classifiers":[
        {
            "category":"Building & Trades",
            "subcategory":"Landscaping Services",
            "type":"Services"
        }
    ],
    "sg:phone":"+1 352 873 3987",
    "sg:postcode":"34482",
    "sg:province":"FL",
    "wof:name":"Dustin Whitts Lawn Care",
    "wof:placetype":"venue"
},
  "geometry": {"coordinates":[-82.312648,29.20359],"type":"Point"}
}