{
  "type": "Feature",
  "properties": {
    "addr:full":"1252 8th St Daytona Beach FL 32117",
    "addr:housenumber":"1252",
    "addr:postcode":"32117",
    "addr:street":"8Th St",
    "iso:country":"US",
    "sg:address":"1252 8th St",
    "sg:city":"Daytona Beach",
    "sg:classifiers":[
        {
            "category":"Bars & Pubs",
            "type":"Food & Drink"
        }
    ],
    "sg:phone":"+1 386 258 5327",
    "sg:postcode":"32117",
    "sg:province":"FL",
    "sg:tags":[
        "drinking"
    ],
    "wof:name":"Okeenans Pub",
    "wof:placetype":"venue"
},
  "geometry": {"coordinates":[-81.06264299999999,29.228911],"type":"Point"}
}