{
  "type": "Feature",
  "properties": {
    "iso:country":"US",
    "sg:address":"1428 S Lake Ave",
    "sg:city":"Apopka",
    "sg:classifiers":[
        {
            "category":"Organizations",
            "subcategory":"Religious Organization",
            "type":"Services"
        }
    ],
    "sg:phone":"+1 407 889 9931",
    "sg:postcode":"32703",
    "sg:province":"FL",
    "sg:tags":[
        "church"
    ],
    "wof:name":"Apopka First Haitian Church",
    "wof:placetype":"venue"
},
  "geometry": {"coordinates":[-81.513507,28.657965],"type":"Point"}
}