{
  "type": "Feature",
  "properties": {
    "addr:full":"1907 SE Hillmoor Dr Port Saint Lucie FL 34952",
    "addr:housenumber":"1907",
    "addr:postcode":"34952",
    "addr:street":"Se Hillmoor Dr",
    "iso:country":"US",
    "sg:address":"1907 SE Hillmoor Dr",
    "sg:city":"Port Saint Lucie",
    "sg:classifiers":[
        {
            "category":"Professional",
            "subcategory":"Management & Consulting",
            "type":"Services"
        }
    ],
    "sg:phone":"+1 772 340 2511",
    "sg:postcode":"34952",
    "sg:province":"FL",
    "wof:name":"E and C Marketing",
    "wof:placetype":"venue"
},
  "geometry": {"coordinates":[-80.29486799999999,27.287034],"type":"Point"}
}