{
  "type": "Feature",
  "properties": {
    "addr:full":"11301 SW 74th Ter Miami FL 33173",
    "addr:housenumber":"11301",
    "addr:postcode":"33173",
    "addr:street":"Sw 74Th Ter",
    "iso:country":"US",
    "sg:address":"11301 SW 74th Ter",
    "sg:city":"Miami",
    "sg:classifiers":[
        {
            "category":"Health Services",
            "subcategory":"Clinic",
            "type":"Services"
        }
    ],
    "sg:phone":"+1 305 595 8716",
    "sg:postcode":"33173",
    "sg:province":"FL",
    "wof:name":"Marmy Medical Service Inc",
    "wof:placetype":"venue"
},
  "geometry": {"coordinates":[-80.37634799999999,25.698525],"type":"Point"}
}