{
  "type": "Feature",
  "properties": {
    "iso:country":"US",
    "sg:address":"1030 E Lafayette St",
    "sg:city":"Tallahassee",
    "sg:classifiers":[
        {
            "category":"Manufacturing",
            "subcategory":"Printing",
            "type":"Manufacturing & Wholesale Goods"
        }
    ],
    "sg:phone":"+1 850 942 1232",
    "sg:postcode":"32301",
    "sg:province":"FL",
    "sg:tags":[
        "multimedia"
    ],
    "sg:website":"www.pnmi.com",
    "wof:name":"Paragon New Media Inc",
    "wof:placetype":"venue"
},
  "geometry": {"coordinates":[-84.266687,30.436472],"type":"Point"}
}