{
  "type": "Feature",
  "properties": {
    "addr:full":"6135 NW 167th St Ste E-24 Hialeah FL 33015",
    "addr:housenumber":"6135",
    "addr:postcode":"33015",
    "addr:street":"Nw 167Th St Ste E-24",
    "iso:country":"US",
    "sg:address":"6135 NW 167th St Ste E-24",
    "sg:city":"Hialeah",
    "sg:classifiers":[
        {
            "category":"Shopping",
            "subcategory":"Jewelry",
            "type":"Retail Goods"
        }
    ],
    "sg:phone":"+1 305 556 1696",
    "sg:postcode":"33015",
    "sg:province":"FL",
    "sg:website":"www.pmxg.com",
    "wof:name":"Precious Metals Xchange Group",
    "wof:placetype":"venue"
},
  "geometry": {"coordinates":[-80.301489,25.925187],"type":"Point"}
}