{
  "type": "Feature",
  "properties": {
    "iso:country":"US",
    "sg:address":"1227 Del Prado Blvd S",
    "sg:city":"Cape Coral",
    "sg:classifiers":[
        {
            "category":"Health Services",
            "subcategory":"Dentist",
            "type":"Services"
        }
    ],
    "sg:phone":"+1 239 574 2161",
    "sg:postcode":"33990",
    "sg:province":"FL",
    "wof:name":"All Smiles Dental Care",
    "wof:placetype":"venue"
},
  "geometry": {"coordinates":[-81.942802,26.6341],"type":"Point"}
}