{
  "type": "Feature",
  "properties": {
    "iso:country":"US",
    "sg:address":"8905 Front Beach Rd",
    "sg:city":"Panama City",
    "sg:classifiers":[
        {
            "category":"Retail",
            "subcategory":"Animal Services",
            "type":"Services"
        }
    ],
    "sg:phone":"+1 850 235 2877",
    "sg:postcode":"32407",
    "sg:province":"FL",
    "sg:tags":[
        "veterinary"
    ],
    "wof:name":"Animal Care Center",
    "wof:placetype":"venue"
},
  "geometry": {"coordinates":[-85.785715,30.18218],"type":"Point"}
}