{
  "type": "Feature",
  "properties": {
    "iso:country":"US",
    "sg:address":"4804 Paleo Pines Cir",
    "sg:city":"Fort Pierce",
    "sg:classifiers":[
        {
            "category":"Building & Trades",
            "subcategory":"Construction",
            "type":"Services"
        }
    ],
    "sg:phone":"+1 772 460 6667",
    "sg:postcode":"34951",
    "sg:province":"FL",
    "sg:tags":[
        "house"
    ],
    "wof:name":"Dial Contruction Service",
    "wof:placetype":"venue"
},
  "geometry": {"coordinates":[-80.38759400000001,27.525235],"type":"Point"}
}