{
  "type": "Feature",
  "properties": {
    "iso:country":"US",
    "sg:address":"4895 W Spencer Field Rd",
    "sg:city":"Milton",
    "sg:classifiers":[
        {
            "category":"Food & Beverages",
            "subcategory":"Groceries & Convenience Stores",
            "type":"Retail Goods"
        }
    ],
    "sg:phone":"+1 850 994 5356",
    "sg:postcode":"32571",
    "sg:province":"FL",
    "sg:tags":[
        "station",
        "gasoline"
    ],
    "wof:name":"Korner KWIK Stop",
    "wof:placetype":"venue"
},
  "geometry": {"coordinates":[-87.14865399999999,30.612878],"type":"Point"}
}