{
  "type": "Feature",
  "properties": {
    "iso:country":"US",
    "sg:address":"4830 E 11th Ave",
    "sg:city":"Hialeah",
    "sg:classifiers":[
        {
            "category":"Retail",
            "subcategory":"Auto Repair",
            "type":"Services"
        }
    ],
    "sg:phone":"+1 305 681 2639",
    "sg:postcode":"33013",
    "sg:province":"FL",
    "sg:tags":[
        "body",
        "automobile",
        "painting"
    ],
    "wof:name":"Le Bridge Paint & Body Shop",
    "wof:placetype":"venue"
},
  "geometry": {"coordinates":[-80.260683,25.866144],"type":"Point"}
}