{
  "type": "Feature",
  "properties": {
    "addr:full":"1672 W 79th St Hialeah FL 33014",
    "addr:housenumber":"1672",
    "addr:postcode":"33014",
    "addr:street":"W 79Th St",
    "iso:country":"US",
    "sg:address":"1672 W 79th St",
    "sg:city":"Hialeah",
    "sg:classifiers":[
        {
            "category":"Health Services",
            "subcategory":"Doctor",
            "type":"Services"
        }
    ],
    "sg:phone":"+1 305 819 6300",
    "sg:postcode":"33014",
    "sg:province":"FL",
    "sg:tags":[
        "physician",
        "surgeon"
    ],
    "wof:name":"Pan American Cac Medical Ctr",
    "wof:placetype":"venue"
},
  "geometry": {"coordinates":[-80.319287,25.89439],"type":"Point"}
}