{
  "type": "Feature",
  "properties": {
    "addr:full":"7789 NW 48th St Miami FL 33166",
    "addr:housenumber":"7789",
    "addr:postcode":"33166",
    "addr:street":"Nw 48Th St",
    "iso:country":"US",
    "sg:address":"7789 NW 48th St",
    "sg:city":"Miami",
    "sg:classifiers":[
        {
            "category":"Government",
            "subcategory":"Office",
            "type":"Public Place"
        }
    ],
    "sg:phone":"+1 305 592 1920",
    "sg:postcode":"33166",
    "sg:province":"FL",
    "sg:tags":[
        "recruiting"
    ],
    "wof:name":"Miami Recruiting Station",
    "wof:placetype":"venue"
},
  "geometry": {"coordinates":[-80.32529,25.817267],"type":"Point"}
}