{
  "type": "Feature",
  "properties": {
    "addr:full":"1936 NW 54th Ave Margate FL 33063",
    "addr:housenumber":"1936",
    "addr:postcode":"33063",
    "addr:street":"Nw 54Th Ave Margate",
    "iso:country":"US",
    "sg:address":"1936 NW 54th Ave",
    "sg:city":"Margate",
    "sg:classifiers":[
        {
            "category":"Building & Trades",
            "subcategory":"Plumbing",
            "type":"Services"
        }
    ],
    "sg:phone":"+1 954 977 6697",
    "sg:postcode":"33063",
    "sg:province":"FL",
    "sg:tags":[
        "plumbing",
        "contractor"
    ],
    "wof:name":"A 1 Plumbing Masters Inc",
    "wof:placetype":"venue"
},
  "geometry": {"coordinates":[-80.19810099999999,26.251939],"type":"Point"}
}