{
  "type": "Feature",
  "properties": {
    "iso:country":"US",
    "sg:address":"5849 Okeechobee Rd",
    "sg:city":"West Palm Beach",
    "sg:classifiers":[
        {
            "category":"Utilities",
            "subcategory":"Refuse",
            "type":"Services"
        }
    ],
    "sg:phone":"+1 561 478 1935",
    "sg:postcode":"33417",
    "sg:province":"FL",
    "sg:tags":[
        "garbage",
        "collection"
    ],
    "wof:name":"Premiere Waste Management Inc",
    "wof:placetype":"venue"
},
  "geometry": {"coordinates":[-80.133662,26.707345],"type":"Point"}
}