{
  "type": "Feature",
  "properties": {
    "iso:country":"US",
    "sg:address":"501 Hidden Pines Blvd",
    "sg:city":"New Smyrna Beach",
    "sg:classifiers":[
        {
            "category":"Real Estate",
            "subcategory":"Real Estate Agent",
            "type":"Services"
        }
    ],
    "sg:phone":"+1 386 689 3133",
    "sg:postcode":"32168",
    "sg:province":"FL",
    "wof:name":"Re/Max",
    "wof:placetype":"venue"
},
  "geometry": {"coordinates":[-80.956063,29.00637],"type":"Point"}
}