{
  "type": "Feature",
  "properties": {
    "addr:full":"5106 N Armenia Ave Tampa FL 33603",
    "addr:housenumber":"5106",
    "addr:postcode":"33603",
    "addr:street":"N Armenia Ave",
    "iso:country":"US",
    "sg:address":"5106 N Armenia Ave",
    "sg:city":"Tampa",
    "sg:classifiers":[
        {
            "category":"Shopping",
            "subcategory":"Pharmacy",
            "type":"Retail Goods"
        }
    ],
    "sg:phone":"+1 813 870 1931",
    "sg:postcode":"33603",
    "sg:province":"FL",
    "wof:name":"Rehab Therapy Works",
    "wof:placetype":"venue"
},
  "geometry": {"coordinates":[-82.484534,27.993735],"type":"Point"}
}