{
  "type": "Feature",
  "properties": {
    "addr:full":"215 SW 42nd Ave Coral Gables FL 33134",
    "addr:housenumber":"215",
    "addr:postcode":"33134",
    "addr:street":"Sw 42Nd Ave",
    "iso:country":"US",
    "sg:address":"215 SW 42nd Ave",
    "sg:city":"Coral Gables",
    "sg:classifiers":[
        {
            "category":"Real Estate",
            "subcategory":"Real Estate Operator",
            "type":"Services"
        }
    ],
    "sg:phone":"+1 305 445 9664",
    "sg:postcode":"33134",
    "sg:province":"FL",
    "sg:tags":[
        "condominium"
    ],
    "wof:name":"Le Jeune Palza Condominiums",
    "wof:placetype":"venue"
},
  "geometry": {"coordinates":[-80.263502,25.769949],"type":"Point"}
}