{
  "type": "Feature",
  "properties": {
    "addr:full":"217 Oakland Ave Sanford FL 32773",
    "addr:housenumber":"217",
    "addr:postcode":"32773",
    "addr:street":"Oakland Ave",
    "iso:country":"US",
    "sg:address":"217 Oakland Ave",
    "sg:city":"Sanford",
    "sg:classifiers":[
        {
            "category":"Building & Trades",
            "subcategory":"Landscaping Services",
            "type":"Services"
        }
    ],
    "sg:phone":"+1 407 323 0352",
    "sg:postcode":"32773",
    "sg:province":"FL",
    "wof:name":"Baussard Stve Cmplte Lwn Svc",
    "wof:placetype":"venue"
},
  "geometry": {"coordinates":[-81.285471,28.748839],"type":"Point"}
}