{
  "type": "Feature",
  "properties": {
    "addr:full":"5846 NW 24th Ter Boca Raton FL 33496",
    "addr:housenumber":"5846",
    "addr:postcode":"33496",
    "addr:street":"Nw 24Th Ter",
    "iso:country":"US",
    "sg:address":"5846 NW 24th Ter",
    "sg:city":"Boca Raton",
    "sg:classifiers":[
        {
            "category":"Wholesale",
            "subcategory":"Groceries",
            "type":"Manufacturing & Wholesale Goods"
        }
    ],
    "sg:phone":"+1 561 997 6551",
    "sg:postcode":"33496",
    "sg:province":"FL",
    "sg:tags":[
        "distributor"
    ],
    "wof:name":"Valu Trading Group Inc",
    "wof:placetype":"venue"
},
  "geometry": {"coordinates":[-80.133386,26.401316],"type":"Point"}
}