{
  "type": "Feature",
  "properties": {
    "iso:country":"US",
    "sg:address":"12181 NW 73rd St",
    "sg:city":"Parkland",
    "sg:classifiers":[
        {
            "category":"Banks & Credit Unions",
            "subcategory":"Bank",
            "type":"Services"
        }
    ],
    "sg:phone":"+1 954 975 5519",
    "sg:postcode":"33076",
    "sg:province":"FL",
    "sg:tags":[
        "loan",
        "real estate"
    ],
    "wof:name":"Customs Mortgages & Invstmnt",
    "wof:placetype":"venue"
},
  "geometry": {"coordinates":[-80.28870999999999,26.321976],"type":"Point"}
}