{
  "type": "Feature",
  "properties": {
    "addr:full":"3863 Bayshore Dr Naples FL 34112",
    "addr:housenumber":"3863",
    "addr:postcode":"34112",
    "addr:street":"Bayshore Dr",
    "iso:country":"US",
    "sg:address":"3863 Bayshore Dr",
    "sg:city":"Naples",
    "sg:classifiers":[
        {
            "category":"Food & Beverages",
            "subcategory":"Liquor & Beverages",
            "type":"Retail Goods"
        }
    ],
    "sg:phone":"+1 239 775 3333",
    "sg:postcode":"34112",
    "sg:province":"FL",
    "sg:tags":[
        "beer",
        "ale",
        "alcoholic"
    ],
    "wof:name":"A To Z Discount Beverage Inc",
    "wof:placetype":"venue"
},
  "geometry": {"coordinates":[-81.77052500000001,26.119263],"type":"Point"}
}