{
  "type": "Feature",
  "properties": {
    "iso:country":"US",
    "sg:address":"7360 Coral Way Ste 8",
    "sg:city":"Miami",
    "sg:classifiers":[
        {
            "category":"Health Services",
            "subcategory":"Hospital",
            "type":"Services"
        }
    ],
    "sg:phone":"+1 305 264 3129",
    "sg:postcode":"33155",
    "sg:province":"FL",
    "wof:name":"Westchester General Hospital",
    "wof:placetype":"venue"
},
  "geometry": {"coordinates":[-80.314729,25.747863],"type":"Point"}
}