{
  "type": "Feature",
  "properties": {
    "addr:full":"2257 Pine Ridge Rd Naples FL 34109",
    "addr:housenumber":"2257",
    "addr:postcode":"34109",
    "addr:street":"Pine Ridge Rd",
    "iso:country":"US",
    "sg:address":"2257 Pine Ridge Rd",
    "sg:city":"Naples",
    "sg:classifiers":[
        {
            "category":"Restaurant",
            "type":"Food & Drink"
        }
    ],
    "sg:menulink":"http://www.allmenus.com/fl/naples/163619-rallys/menu/",
    "sg:phone":"+1 239 591 8988",
    "sg:postcode":"34109",
    "sg:province":"FL",
    "sg:tags":[
        "sandwich",
        "dog",
        "burger",
        "hot",
        "wrap",
        "american"
    ],
    "wof:name":"Rally's",
    "wof:placetype":"venue"
},
  "geometry": {"coordinates":[-81.772983,26.211947],"type":"Point"}
}