{
  "type": "Feature",
  "properties": {
    "addr:full":"3800 Commonwealth Blvd Tallahassee FL 32303",
    "addr:housenumber":"3800",
    "addr:postcode":"32303",
    "addr:street":"Commonwealth Blvd",
    "iso:country":"US",
    "sg:address":"3800 Commonwealth Blvd",
    "sg:city":"Tallahassee",
    "sg:classifiers":[
        {
            "category":"Utilities",
            "subcategory":"Recycling",
            "type":"Services"
        }
    ],
    "sg:phone":"+1 850 245 2315",
    "sg:postcode":"32303",
    "sg:province":"FL",
    "sg:tags":[
        "disposal",
        "waste",
        "equipment"
    ],
    "sg:website":"http://www.bluespringflorida.com",
    "wof:name":"Florida Department Of Environmental Protection",
    "wof:placetype":"venue"
},
  "geometry": {"coordinates":[-84.35774000000001,30.475891],"type":"Point"}
}