{
  "type": "Feature",
  "properties": {
    "addr:full":"6419 W Newberry Rd Gainesville FL 32605",
    "addr:housenumber":"6419",
    "addr:postcode":"32605",
    "addr:street":"W Newberry Rd",
    "iso:country":"US",
    "sg:address":"6419 W Newberry Rd",
    "sg:city":"Gainesville",
    "sg:classifiers":[
        {
            "category":"Home & Garden",
            "subcategory":"Home Furnishings",
            "type":"Retail Goods"
        },
        {
            "category":"Home & Garden",
            "subcategory":"Carpets & Floor Coverings",
            "type":"Retail Goods"
        }
    ],
    "sg:phone":"+1 352 505 1133",
    "sg:postcode":"32605",
    "sg:province":"FL",
    "sg:tags":[
        "bedroom",
        "set",
        "bed",
        "mattress"
    ],
    "sg:website":"http://www.selectcomfort.com",
    "wof:name":"Select Comfort",
    "wof:placetype":"venue"
},
  "geometry": {"coordinates":[-82.421425,29.65961],"type":"Point"}
}