{
  "type": "Feature",
  "properties": {
    "iso:country":"US",
    "sg:address":"3811 Chelsea St",
    "sg:city":"Orlando",
    "sg:classifiers":[
        {
            "category":"Professional",
            "subcategory":"Business Services",
            "type":"Services"
        }
    ],
    "sg:phone":"+1 407 898 8064",
    "sg:postcode":"32803",
    "sg:province":"FL",
    "sg:tags":[
        "organizing"
    ],
    "wof:name":"Organize",
    "wof:placetype":"venue"
},
  "geometry": {"coordinates":[-81.33578,28.562949],"type":"Point"}
}