{
  "type": "Feature",
  "properties": {
    "addr:full":"10121 SW 71st Ct Ocala FL 34476",
    "addr:housenumber":"10121",
    "addr:postcode":"34476",
    "addr:street":"Sw 71St Ct",
    "iso:country":"US",
    "sg:address":"10121 SW 71st Ct",
    "sg:city":"Ocala",
    "sg:classifiers":[
        {
            "category":"Building & Trades",
            "subcategory":"Construction",
            "type":"Services"
        }
    ],
    "sg:phone":"+1 352 291 6688",
    "sg:postcode":"34476",
    "sg:province":"FL",
    "sg:tags":[
        "dry wall",
        "contractor"
    ],
    "wof:name":"Oglesby Drywall Corp",
    "wof:placetype":"venue"
},
  "geometry": {"coordinates":[-82.23786200000001,29.071227],"type":"Point"}
}