{
  "type": "Feature",
  "properties": {
    "iso:country":"US",
    "sg:address":"4901 34th St N",
    "sg:city":"St Petersburg",
    "sg:classifiers":[
        {
            "category":"Travel",
            "subcategory":"Hotels & Motels",
            "type":"Entertainment"
        }
    ],
    "sg:phone":"+1 727 528 6404",
    "sg:postcode":"33714",
    "sg:province":"FL",
    "sg:tags":[
        "breakfast",
        "accommodation",
        "bed"
    ],
    "wof:name":"Bed & Mattress Outlet",
    "wof:placetype":"venue"
},
  "geometry": {"coordinates":[-82.679439,27.8174],"type":"Point"}
}