{
  "type": "Feature",
  "properties": {
    "iso:country":"US",
    "sg:address":"1393 SW 1st St Ste 200",
    "sg:city":"Miami",
    "sg:classifiers":[
        {
            "category":"Professional",
            "subcategory":"Lawyer & Legal Services",
            "type":"Services"
        }
    ],
    "sg:phone":"+1 305 541 7940",
    "sg:postcode":"33135",
    "sg:province":"FL",
    "wof:name":"Bergholm Edward Jr Atty",
    "wof:placetype":"venue"
},
  "geometry": {"coordinates":[-80.218002,25.7724],"type":"Point"}
}