{
  "type": "Feature",
  "properties": {
    "iso:country":"US",
    "sg:address":"5567 Doug Taylor Cir",
    "sg:city":"St James City",
    "sg:classifiers":[
        {
            "category":"Home & Garden",
            "subcategory":"Building Materials",
            "type":"Retail Goods"
        }
    ],
    "sg:phone":"+1 239 283 5859",
    "sg:postcode":"33956",
    "sg:province":"FL",
    "sg:tags":[
        "plumbing",
        "fixture",
        "supply"
    ],
    "wof:name":"Tropical Kitchen By Frank",
    "wof:placetype":"venue"
},
  "geometry": {"coordinates":[-82.11450000000001,26.608431],"type":"Point"}
}