{
  "type": "Feature",
  "properties": {
    "addr:full":"1801 SW 23rd Ter Miami FL 33145",
    "addr:housenumber":"1801",
    "addr:postcode":"33145",
    "addr:street":"Sw 23Rd Ter",
    "iso:country":"US",
    "sg:address":"1801 SW 23rd Ter",
    "sg:city":"Miami",
    "sg:classifiers":[
        {
            "category":"Professional",
            "subcategory":"Business Services",
            "type":"Services"
        }
    ],
    "sg:phone":"+1 305 854 7502",
    "sg:postcode":"33145",
    "sg:province":"FL",
    "sg:tags":[
        "appraiser"
    ],
    "wof:name":"EAL Appraisals",
    "wof:placetype":"venue"
},
  "geometry": {"coordinates":[-80.225971,25.748317],"type":"Point"}
}