{
  "type": "Feature",
  "properties": {
    "addr:full":"790 E Eau Gallie Blvd Indian Hrbr Bch FL 32937",
    "addr:housenumber":"790",
    "addr:postcode":"32937",
    "addr:street":"E Eau Gallie Blvd",
    "iso:country":"US",
    "sg:address":"790 E Eau Gallie Blvd",
    "sg:city":"Indian Hrbr Bch",
    "sg:classifiers":[
        {
            "category":"Autos & Motor Vehicles",
            "subcategory":"Auto Supplies",
            "type":"Retail Goods"
        }
    ],
    "sg:phone":"+1 321 773 3838",
    "sg:postcode":"32937",
    "sg:province":"FL",
    "sg:tags":[
        "automobile",
        "parts"
    ],
    "wof:name":"Touch Class Auto & Truck Acc",
    "wof:placetype":"venue"
},
  "geometry": {"coordinates":[-80.586737,28.138696],"type":"Point"}
}