{
  "type": "Feature",
  "properties": {
    "iso:country":"US",
    "sg:address":"20 S Palm Ave",
    "sg:city":"Sarasota",
    "sg:classifiers":[
        {
            "category":"Shopping",
            "type":"Retail Goods"
        }
    ],
    "sg:phone":"+1 941 365 7414",
    "sg:postcode":"34236",
    "sg:province":"FL",
    "sg:tags":[
        "art",
        "gallery",
        "merchandise",
        "dealer"
    ],
    "wof:name":"Galleria Silecchia",
    "wof:placetype":"venue"
},
  "geometry": {"coordinates":[-82.54356799999999,27.335324],"type":"Point"}
}