{
  "type": "Feature",
  "properties": {
    "iso:country":"US",
    "sg:address":"141 Sage Brush Trl",
    "sg:city":"Ormond Beach",
    "sg:classifiers":[
        {
            "category":"Professional",
            "subcategory":"Management & Consulting",
            "type":"Services"
        }
    ],
    "sg:phone":"+1 386 673 8235",
    "sg:postcode":"32174",
    "sg:province":"FL",
    "wof:name":"Sur Management Svcs A Div A",
    "wof:placetype":"venue"
},
  "geometry": {"coordinates":[-81.09893599999999,29.267877],"type":"Point"}
}