{
  "type": "Feature",
  "properties": {
    "iso:country":"US",
    "sg:address":"350 S Lake Destiny Rd",
    "sg:city":"Orlando",
    "sg:classifiers":[
        {
            "category":"Professional",
            "subcategory":"Management & Consulting",
            "type":"Services"
        }
    ],
    "sg:phone":"+1 407 660 2224",
    "sg:postcode":"32810",
    "sg:province":"FL",
    "sg:tags":[
        "fuel"
    ],
    "wof:name":"First Team Management",
    "wof:placetype":"venue"
},
  "geometry": {"coordinates":[-81.38804399999999,28.611749],"type":"Point"}
}