{
  "type": "Feature",
  "properties": {
    "iso:country":"US",
    "sg:address":"5040 Clark Rd",
    "sg:city":"Sarasota",
    "sg:classifiers":[
        {
            "category":"Personal",
            "subcategory":"Beauty Salon",
            "type":"Services"
        }
    ],
    "sg:phone":"+1 941 926 2583",
    "sg:postcode":"34233",
    "sg:province":"FL",
    "sg:website":"www.supercuts.com",
    "wof:name":"Supercuts",
    "wof:placetype":"venue"
},
  "geometry": {"coordinates":[-82.46692899999999,27.269219],"type":"Point"}
}