{
  "type": "Feature",
  "properties": {
    "iso:country":"US",
    "sg:address":"5904 Lemos Ct",
    "sg:city":"Orlando",
    "sg:classifiers":[
        {
            "category":"Freight",
            "type":"Transportation"
        }
    ],
    "sg:phone":"+1 407 578 2285",
    "sg:postcode":"32808",
    "sg:province":"FL",
    "wof:name":"Jean Alexis Transportation",
    "wof:placetype":"venue"
},
  "geometry": {"coordinates":[-81.46053999999999,28.608394],"type":"Point"}
}