{
  "type": "Feature",
  "properties": {
    "addr:full":"111 W Dakin Ave Kissimmee FL 34741",
    "addr:housenumber":"111",
    "addr:postcode":"34741",
    "addr:street":"W Dakin Ave",
    "iso:country":"US",
    "sg:address":"111 W Dakin Ave",
    "sg:city":"Kissimmee",
    "sg:classifiers":[
        {
            "category":"Railroad",
            "type":"Transportation"
        }
    ],
    "sg:phone":"+1 407 933 1170",
    "sg:postcode":"34741",
    "sg:province":"FL",
    "sg:tags":[
        "operator",
        "rail",
        "government"
    ],
    "wof:name":"Amtrak",
    "wof:placetype":"venue"
},
  "geometry": {"coordinates":[-81.40554400000001,28.294065],"type":"Point"}
}