{
  "type": "Feature",
  "properties": {
    "iso:country":"US",
    "sg:address":"1311 Seminola Blvd",
    "sg:city":"Casselberry",
    "sg:classifiers":[
        {
            "category":"Building & Trades",
            "subcategory":"Plumbing",
            "type":"Services"
        }
    ],
    "sg:phone":"+1 407 695 1995",
    "sg:postcode":"32707",
    "sg:province":"FL",
    "sg:tags":[
        "plumber"
    ],
    "wof:name":"Plumbing Connection",
    "wof:placetype":"venue"
},
  "geometry": {"coordinates":[-81.31143400000001,28.674748],"type":"Point"}
}