{
  "type": "Feature",
  "properties": {
    "addr:full":"13659 12th Pl N Loxahatchee FL 33470",
    "addr:housenumber":"13659",
    "addr:postcode":"33470",
    "addr:street":"12Th Pl N",
    "iso:country":"US",
    "sg:address":"13659 12th Pl N",
    "sg:city":"Loxahatchee",
    "sg:classifiers":[
        {
            "category":"Building & Trades",
            "subcategory":"Landscaping Services",
            "type":"Services"
        }
    ],
    "sg:phone":"+1 561 753 0216",
    "sg:postcode":"33470",
    "sg:province":"FL",
    "sg:tags":[
        "landscape",
        "contractor"
    ],
    "wof:name":"Family Tree",
    "wof:placetype":"venue"
},
  "geometry": {"coordinates":[-80.26067,26.695789],"type":"Point"}
}