{
  "type": "Feature",
  "properties": {
    "iso:country":"US",
    "sg:address":"10855 SW 72nd St Ste 16",
    "sg:city":"Miami",
    "sg:classifiers":[
        {
            "category":"Banks & Credit Unions",
            "subcategory":"Bank",
            "type":"Services"
        },
        {
            "category":"Shopping",
            "subcategory":"Used Merchandise",
            "type":"Retail Goods"
        }
    ],
    "sg:phone":"+1 305 403 1919",
    "sg:postcode":"33173",
    "sg:province":"FL",
    "sg:tags":[
        "resale",
        "shop",
        "second",
        "hand"
    ],
    "wof:name":"Affordable Thin Gs And More",
    "wof:placetype":"venue"
},
  "geometry": {"coordinates":[-80.368809,25.701066],"type":"Point"}
}