{
  "type": "Feature",
  "properties": {
    "iso:country":"US",
    "sg:address":"1000 Pinewood Ct",
    "sg:city":"Green Cove Springs",
    "sg:classifiers":[
        {
            "category":"Real Estate",
            "subcategory":"Real Estate Operator",
            "type":"Services"
        }
    ],
    "sg:phone":"+1 904 284 3548",
    "sg:postcode":"32043",
    "sg:province":"FL",
    "sg:tags":[
        "building",
        "apartment"
    ],
    "wof:name":"Pinewood Apts Ltd",
    "wof:placetype":"venue"
},
  "geometry": {"coordinates":[-81.69710499999999,29.980597],"type":"Point"}
}