{
  "type": "Feature",
  "properties": {
    "iso:country":"US",
    "sg:address":"815 Mimosa Dr",
    "sg:city":"Altamonte Springs",
    "sg:classifiers":[
        {
            "category":"Wholesale",
            "subcategory":"Farm Supplies",
            "type":"Manufacturing & Wholesale Goods"
        }
    ],
    "sg:phone":"+1 407 774 7513",
    "sg:postcode":"32714",
    "sg:province":"FL",
    "sg:tags":[
        "specializing",
        "pesticide",
        "representative",
        "mfg"
    ],
    "wof:name":"Fiag",
    "wof:placetype":"venue"
},
  "geometry": {"coordinates":[-81.422619,28.677152],"type":"Point"}
}