{
  "type": "Feature",
  "properties": {
    "iso:country":"US",
    "sg:address":"2910 SE Waaler St",
    "sg:city":"Stuart",
    "sg:classifiers":[
        {
            "category":"Autos & Motor Vehicles",
            "subcategory":"Motorcycle Sales",
            "type":"Retail Goods"
        }
    ],
    "sg:phone":"+1 772 232 0223",
    "sg:postcode":"34997",
    "sg:province":"FL",
    "sg:tags":[
        "scooter"
    ],
    "wof:name":"Keys Cycle North",
    "wof:placetype":"venue"
},
  "geometry": {"coordinates":[-80.213871,27.152442],"type":"Point"}
}