{
  "type": "Feature",
  "properties": {
    "iso:country":"US",
    "sg:address":"2751 W Atlantic Blvd",
    "sg:city":"Pompano Beach",
    "sg:classifiers":[
        {
            "category":"Banks & Credit Unions",
            "subcategory":"Bank",
            "type":"Services"
        }
    ],
    "sg:phone":"+1 954 968 6323",
    "sg:postcode":"33069",
    "sg:province":"FL",
    "sg:tags":[
        "depository",
        "banking"
    ],
    "wof:name":"Atlantic Check Cashing",
    "wof:placetype":"venue"
},
  "geometry": {"coordinates":[-80.160427,26.231315],"type":"Point"}
}