{
  "type": "Feature",
  "properties": {
    "addr:full":"821 Scenic View Cir Clermont FL 34715",
    "addr:housenumber":"821",
    "addr:postcode":"34715",
    "addr:street":"Scenic View Cir",
    "iso:country":"US",
    "sg:address":"821 Scenic View Cir",
    "sg:city":"Clermont",
    "sg:classifiers":[
        {
            "category":"Building & Trades",
            "subcategory":"Construction",
            "type":"Services"
        }
    ],
    "sg:phone":"+1 352 267 4746",
    "sg:postcode":"34715",
    "sg:province":"FL",
    "wof:name":"Bradley Underground Inc",
    "wof:placetype":"venue"
},
  "geometry": {"coordinates":[-81.726904,28.568891],"type":"Point"}
}