{
  "type": "Feature",
  "properties": {
    "iso:country":"US",
    "sg:address":"1613 Pine Lake Rd",
    "sg:city":"Orlando",
    "sg:classifiers":[
        {
            "category":"Building & Trades",
            "subcategory":"Construction",
            "type":"Services"
        }
    ],
    "sg:phone":"+1 407 445 1947",
    "sg:postcode":"32808",
    "sg:province":"FL",
    "sg:tags":[
        "hanging",
        "contractor"
    ],
    "wof:name":"Dennis Bomar Inc",
    "wof:placetype":"venue"
},
  "geometry": {"coordinates":[-81.445746,28.567908],"type":"Point"}
}