{
  "type": "Feature",
  "properties": {
    "addr:full":"1618 Peruvian Ln Winter Park FL 32792",
    "addr:postcode":"1618;32792",
    "addr:street":"Peruvian Ln",
    "iso:country":"US",
    "sg:address":"1618 Peruvian Ln",
    "sg:city":"Winter Park",
    "sg:classifiers":[
        {
            "category":"Professional",
            "subcategory":"Management & Consulting",
            "type":"Services"
        }
    ],
    "sg:phone":"+1 407 657 2699",
    "sg:postcode":"32792",
    "sg:province":"FL",
    "sg:tags":[
        "party",
        "planning"
    ],
    "wof:name":"De Vous A Moi",
    "wof:placetype":"venue"
},
  "geometry": {"coordinates":[-81.301424,28.612228],"type":"Point"}
}