{
  "type": "Feature",
  "properties": {
    "iso:country":"US",
    "sg:address":"7031B State Road 52",
    "sg:city":"Hudson",
    "sg:classifiers":[
        {
            "category":"Building & Trades",
            "subcategory":"Pest Control",
            "type":"Services"
        }
    ],
    "sg:phone":"+1 866 801 8793",
    "sg:postcode":"34667",
    "sg:province":"FL",
    "sg:tags":[
        "removal",
        "industrial",
        "services-commercial",
        "termite",
        "bee"
    ],
    "sg:website":"http://www.trulynolen.com/?campid=8",
    "wof:name":"Truly Nolen",
    "wof:placetype":"venue"
},
  "geometry": {"coordinates":[-82.699116,28.33142],"type":"Point"}
}