{
  "type": "Feature",
  "properties": {
    "iso:country":"US",
    "sg:address":"1352 SW 1st Way",
    "sg:city":"Deerfield Beach",
    "sg:classifiers":[
        {
            "category":"Building & Trades",
            "subcategory":"Electrical",
            "type":"Services"
        }
    ],
    "sg:phone":"+1 954 428 0535",
    "sg:postcode":"33441",
    "sg:province":"FL",
    "sg:tags":[
        "electric",
        "contractor"
    ],
    "wof:name":"Shoreline Electric Inc",
    "wof:placetype":"venue"
},
  "geometry": {"coordinates":[-80.104902,26.303068],"type":"Point"}
}