{
  "type": "Feature",
  "properties": {
    "iso:country":"US",
    "sg:address":"1883 NW 20th St",
    "sg:city":"Miami",
    "sg:classifiers":[
        {
            "category":"Shopping",
            "subcategory":"Clothing, Apparel, & Fashions",
            "type":"Retail Goods"
        }
    ],
    "sg:phone":"+1 305 549 5557",
    "sg:postcode":"33142",
    "sg:province":"FL",
    "sg:tags":[
        "designer"
    ],
    "wof:name":"Mana Fashions",
    "wof:placetype":"venue"
},
  "geometry": {"coordinates":[-80.227046,25.79465],"type":"Point"}
}