{
  "type": "Feature",
  "properties": {
    "iso:country":"US",
    "sg:address":"225 Coronado Dr",
    "sg:city":"Clearwater",
    "sg:classifiers":[
        {
            "category":"Travel",
            "subcategory":"Hotels & Motels",
            "type":"Entertainment"
        }
    ],
    "sg:phone":"+1 727 442 9404",
    "sg:postcode":"33767",
    "sg:province":"FL",
    "wof:name":"Golden Villa Apartment Motel",
    "wof:placetype":"venue"
},
  "geometry": {"coordinates":[-82.828216,27.974052],"type":"Point"}
}