{
  "type": "Feature",
  "properties": {
    "addr:full":"2118 Coral Point Dr Cape Coral FL 33990",
    "addr:housenumber":"2118",
    "addr:postcode":"33990",
    "addr:street":"Coral Point Dr",
    "iso:country":"US",
    "sg:address":"2118 Coral Point Dr",
    "sg:city":"Cape Coral",
    "sg:classifiers":[
        {
            "category":"Retail",
            "subcategory":"Repair Shop",
            "type":"Services"
        }
    ],
    "sg:phone":"+1 239 549 0855",
    "sg:postcode":"33990",
    "sg:province":"FL",
    "sg:tags":[
        "jewelry"
    ],
    "wof:name":"Al's Jewelers",
    "wof:placetype":"venue"
},
  "geometry": {"coordinates":[-81.931484,26.622592],"type":"Point"}
}