{
  "type": "Feature",
  "properties": {
    "iso:country":"US",
    "sg:address":"50 N Tampa Ave",
    "sg:city":"Orlando",
    "sg:classifiers":[
        {
            "category":"Building & Trades",
            "subcategory":"Construction",
            "type":"Services"
        }
    ],
    "sg:phone":"+1 407 648 0599",
    "sg:postcode":"32805",
    "sg:province":"FL",
    "sg:tags":[
        "maker",
        "cabinet"
    ],
    "wof:name":"Mines Cabinets",
    "wof:placetype":"venue"
},
  "geometry": {"coordinates":[-81.405612,28.543734],"type":"Point"}
}