{
  "type": "Feature",
  "properties": {
    "iso:country":"US",
    "sg:address":"2569 Countryside Blvd",
    "sg:city":"Clearwater",
    "sg:classifiers":[
        {
            "category":"Restaurant",
            "type":"Food & Drink"
        }
    ],
    "sg:menulink":"http://www.allmenus.com/fl/clearwater/231227-first-watch/menu/",
    "sg:phone":"+1 727 712 8769",
    "sg:postcode":"33761",
    "sg:province":"FL",
    "sg:tags":[
        "american"
    ],
    "wof:name":"First Watch",
    "wof:placetype":"venue"
},
  "geometry": {"coordinates":[-82.733694,28.015211],"type":"Point"}
}