{
  "type": "Feature",
  "properties": {
    "iso:country":"US",
    "sg:address":"3103 73rd Ave E",
    "sg:city":"Ellenton",
    "sg:classifiers":[
        {
            "category":"Building & Trades",
            "subcategory":"Construction",
            "type":"Services"
        }
    ],
    "sg:phone":"+1 941 776 3185",
    "sg:postcode":"34222",
    "sg:province":"FL",
    "sg:tags":[
        "contractor"
    ],
    "wof:name":"Balls Quality Tile Inc",
    "wof:placetype":"venue"
},
  "geometry": {"coordinates":[-82.489897,27.540685],"type":"Point"}
}