{
  "type": "Feature",
  "properties": {
    "addr:full":"1012 N Ocean Blvd Pompano Beach FL 33062",
    "addr:housenumber":"1012",
    "addr:postcode":"33062",
    "addr:street":"N Ocean Blvd",
    "iso:country":"US",
    "sg:address":"1012 N Ocean Blvd",
    "sg:city":"Pompano Beach",
    "sg:classifiers":[
        {
            "category":"Banks & Credit Unions",
            "subcategory":"Financial Services",
            "type":"Services"
        }
    ],
    "sg:phone":"+1 954 943 8004",
    "sg:postcode":"33062",
    "sg:province":"FL",
    "sg:tags":[
        "investor"
    ],
    "wof:name":"Deerfield Investment Corp",
    "wof:placetype":"venue"
},
  "geometry": {"coordinates":[-80.086989,26.247432],"type":"Point"}
}