{
  "type": "Feature",
  "properties": {
    "iso:country":"US",
    "sg:address":"2750 Renegade Dr",
    "sg:city":"Orlando",
    "sg:classifiers":[
        {
            "category":"Real Estate",
            "subcategory":"Developer",
            "type":"Services"
        }
    ],
    "sg:phone":"+1 407 296 9591",
    "sg:postcode":"32818",
    "sg:province":"FL",
    "wof:name":"Pack Land Developments",
    "wof:placetype":"venue"
},
  "geometry": {"coordinates":[-81.47989800000001,28.580011],"type":"Point"}
}