{
  "type": "Feature",
  "properties": {
    "addr:full":"250 Westshore Plz Tampa FL 33609",
    "addr:housenumber":"250",
    "addr:postcode":"33609",
    "addr:street":"Westshore Plz",
    "iso:country":"US",
    "sg:address":"250 Westshore Plz",
    "sg:city":"Tampa",
    "sg:classifiers":[
        {
            "category":"Shopping",
            "subcategory":"Optical Goods",
            "type":"Retail Goods"
        }
    ],
    "sg:phone":"+1 813 287 8592",
    "sg:postcode":"33609",
    "sg:province":"FL",
    "sg:tags":[
        "sun",
        "goggles",
        "sunglasses"
    ],
    "wof:name":"NYS Collections",
    "wof:placetype":"venue"
},
  "geometry": {"coordinates":[-82.527401,27.946751],"type":"Point"}
}