{
  "type": "Feature",
  "properties": {
    "addr:full":"12 Florence Blvd Debary FL 32713",
    "addr:housenumber":"12",
    "addr:postcode":"32713",
    "addr:street":"Florence Blvd",
    "iso:country":"US",
    "sg:address":"12 Florence Blvd",
    "sg:city":"Debary",
    "sg:classifiers":[
        {
            "category":"Building & Trades",
            "subcategory":"Locksmith",
            "type":"Services"
        }
    ],
    "sg:phone":"+1 386 456 9011",
    "sg:postcode":"32713",
    "sg:province":"FL",
    "sg:tags":[
        "key"
    ],
    "wof:name":"Aplus Locksmith Co",
    "wof:placetype":"venue"
},
  "geometry": {"coordinates":[-81.304165,28.912973],"type":"Point"}
}