{
  "type": "Feature",
  "properties": {
    "iso:country":"US",
    "sg:address":"2928 Valerie Ave",
    "sg:city":"Apopka",
    "sg:classifiers":[
        {
            "category":"Wholesale",
            "subcategory":"Plants",
            "type":"Manufacturing & Wholesale Goods"
        },
        {
            "category":"Farming",
            "subcategory":"Nursery",
            "type":"Manufacturing & Wholesale Goods"
        }
    ],
    "sg:phone":"+1 407 889 2993",
    "sg:postcode":"32712",
    "sg:province":"FL",
    "sg:tags":[
        "ornamental",
        "tree"
    ],
    "wof:name":"Holy Land Foliage Inc",
    "wof:placetype":"venue"
},
  "geometry": {"coordinates":[-81.50290800000001,28.727154],"type":"Point"}
}