{
  "type": "Feature",
  "properties": {
    "addr:full":"1761 State Hwy 60 Valrico FL 33594",
    "addr:housenumber":"1761",
    "addr:postcode":"33594",
    "addr:street":"State Hwy 60",
    "iso:country":"US",
    "sg:address":"1761 State Hwy 60",
    "sg:city":"Valrico",
    "sg:classifiers":[
        {
            "category":"Retail",
            "subcategory":"Laundry & Dry Cleaning",
            "type":"Services"
        }
    ],
    "sg:phone":"+1 813 651 9562",
    "sg:postcode":"33594",
    "sg:province":"FL",
    "sg:tags":[
        "cleaners"
    ],
    "wof:name":"Jon Turner",
    "wof:placetype":"venue"
},
  "geometry": {"coordinates":[-82.259846,27.937787],"type":"Point"}
}