{
  "type": "Feature",
  "properties": {
    "iso:country":"US",
    "sg:address":"134 S Gornto Lake Rd",
    "sg:city":"Brandon",
    "sg:phone":"+1 813 661 6005",
    "sg:postcode":"33511",
    "sg:province":"FL",
    "sg:website":"http://www.starbuffet.com",
    "wof:name":"Buddyfreddys Brandon Ltd",
    "wof:placetype":"venue"
},
  "geometry": {"coordinates":[-82.318637,27.937029],"type":"Point"}
}