{
  "type": "Feature",
  "properties": {
    "addr:full":"2703 S Federal Hwy Boynton Beach FL 33435",
    "addr:housenumber":"2703",
    "addr:postcode":"33435",
    "addr:street":"S Federal Hwy",
    "iso:country":"US",
    "sg:address":"2703 S Federal Hwy",
    "sg:city":"Boynton Beach",
    "sg:classifiers":[
        {
            "category":"Travel",
            "subcategory":"Hotels & Motels",
            "type":"Entertainment"
        }
    ],
    "sg:phone":"+1 561 732 8440",
    "sg:postcode":"33435",
    "sg:province":"FL",
    "wof:name":"Loraine Motel Apartments",
    "wof:placetype":"venue"
},
  "geometry": {"coordinates":[-80.060013,26.504204],"type":"Point"}
}