{
  "type": "Feature",
  "properties": {
    "iso:country":"US",
    "sg:address":"3911 NW 26th St",
    "sg:city":"Miami",
    "sg:classifiers":[
        {
            "category":"Retail",
            "subcategory":"Auto Repair",
            "type":"Services"
        }
    ],
    "sg:phone":"+1 305 870 0115",
    "sg:postcode":"33142",
    "sg:province":"FL",
    "wof:name":"Fim Auto Repair Corp",
    "wof:placetype":"venue"
},
  "geometry": {"coordinates":[-80.26009000000001,25.799764],"type":"Point"}
}