{
  "type": "Feature",
  "properties": {
    "iso:country":"US",
    "sg:address":"2741 SE South Blackwell Dr",
    "sg:city":"Port Saint Lucie",
    "sg:classifiers":[
        {
            "category":"Building & Trades",
            "subcategory":"Construction",
            "type":"Services"
        }
    ],
    "sg:phone":"+1 772 398 8032",
    "sg:postcode":"34952",
    "sg:province":"FL",
    "sg:tags":[
        "home",
        "residential",
        "contractor",
        "general",
        "carpentry"
    ],
    "wof:name":"Genesis Construciton Inc",
    "wof:placetype":"venue"
},
  "geometry": {"coordinates":[-80.257694,27.264175],"type":"Point"}
}