{
  "type": "Feature",
  "properties": {
    "addr:full":"716 King St Jacksonville FL 32204",
    "addr:housenumber":"716",
    "addr:postcode":"32204",
    "addr:street":"King St",
    "iso:country":"US",
    "sg:address":"716 King St",
    "sg:city":"Jacksonville",
    "sg:classifiers":[
        {
            "category":"Manufacturing",
            "subcategory":"Metals",
            "type":"Manufacturing & Wholesale Goods"
        }
    ],
    "sg:phone":"+1 904 981 2728",
    "sg:postcode":"32204",
    "sg:province":"FL",
    "sg:tags":[
        "abrasive",
        "product",
        "fabricated",
        "mfg"
    ],
    "wof:name":"R & J Enterprises",
    "wof:placetype":"venue"
},
  "geometry": {"coordinates":[-81.697002,30.317923],"type":"Point"}
}