{
  "type": "Feature",
  "properties": {
    "iso:country":"US",
    "sg:address":"21401 NW 2nd Ave",
    "sg:city":"Miami",
    "sg:classifiers":[
        {
            "category":"Shopping",
            "subcategory":"Department Store",
            "type":"Retail Goods"
        }
    ],
    "sg:phone":"+1 305 654 5918",
    "sg:postcode":"33169",
    "sg:province":"FL",
    "sg:website":"http://www.rossstores.com/",
    "wof:name":"Ross Dress for Less",
    "wof:placetype":"venue"
},
  "geometry": {"coordinates":[-80.206064,25.972596],"type":"Point"}
}