{
  "type": "Feature",
  "properties": {
    "addr:full":"5626 Gulf Dr Holmes Beach FL 34217",
    "addr:housenumber":"5626",
    "addr:postcode":"34217",
    "addr:street":"Gulf Dr",
    "iso:country":"US",
    "sg:address":"5626 Gulf Dr",
    "sg:city":"Holmes Beach",
    "sg:classifiers":[
        {
            "category":"Travel",
            "subcategory":"Hotels & Motels",
            "type":"Entertainment"
        }
    ],
    "sg:phone":"+1 941 778 5444",
    "sg:postcode":"34217",
    "sg:province":"FL",
    "sg:tags":[
        "breakfast",
        "accommodation",
        "bed"
    ],
    "sg:website":"www.harringtonhouse.com",
    "wof:name":"Harrington House B & B",
    "wof:placetype":"venue"
},
  "geometry": {"coordinates":[-82.71933,27.508797],"type":"Point"}
}