{
  "type": "Feature",
  "properties": {
    "addr:full":"1021 King St Jacksonville FL 32204",
    "addr:housenumber":"1021",
    "addr:postcode":"32204",
    "addr:street":"King St",
    "iso:country":"US",
    "sg:address":"1021 King St",
    "sg:city":"Jacksonville",
    "sg:classifiers":[
        {
            "category":"Shopping",
            "subcategory":"Used Merchandise",
            "type":"Retail Goods"
        }
    ],
    "sg:phone":"+1 904 389 9110",
    "sg:postcode":"32204",
    "sg:province":"FL",
    "wof:name":"This Old Warehouse",
    "wof:placetype":"venue"
},
  "geometry": {"coordinates":[-81.69495499999999,30.312518],"type":"Point"}
}