{
  "type": "Feature",
  "properties": {
    "iso:country":"US",
    "sg:address":"3516 NW 28th Ct",
    "sg:city":"Fort Lauderdale",
    "sg:classifiers":[
        {
            "category":"Building & Trades",
            "subcategory":"Landscaping Services",
            "type":"Services"
        }
    ],
    "sg:phone":"+1 954 485 6136",
    "sg:postcode":"33311",
    "sg:province":"FL",
    "sg:tags":[
        "landscape"
    ],
    "wof:name":"Milnet Metayer Landscaping & L",
    "wof:placetype":"venue"
},
  "geometry": {"coordinates":[-80.19471799999999,26.160841],"type":"Point"}
}