{
  "type": "Feature",
  "properties": {
    "addr:full":"8030 Hwy 77 Panama City FL 32409",
    "addr:housenumber":"8030",
    "addr:postcode":"32409",
    "addr:street":"Hwy 77",
    "iso:country":"US",
    "sg:address":"8030 Hwy 77",
    "sg:city":"Panama City",
    "sg:classifiers":[
        {
            "category":"Building & Trades",
            "subcategory":"Construction",
            "type":"Services"
        }
    ],
    "sg:phone":"+1 850 265 5316",
    "sg:postcode":"32409",
    "sg:province":"FL",
    "sg:tags":[
        "heavy"
    ],
    "wof:name":"R D Hauling Inc",
    "wof:placetype":"venue"
},
  "geometry": {"coordinates":[-85.648016,30.302487],"type":"Point"}
}