{
  "type": "Feature",
  "properties": {
    "addr:full":"3001 Harbor Dr Fort Lauderdale FL 33316",
    "addr:housenumber":"3001",
    "addr:postcode":"33316",
    "addr:street":"Harbor Dr",
    "iso:country":"US",
    "sg:address":"3001 Harbor Dr",
    "sg:city":"Fort Lauderdale",
    "sg:classifiers":[
        {
            "category":"Travel",
            "subcategory":"Travel Agent",
            "type":"Entertainment"
        }
    ],
    "sg:phone":"+1 954 567 3567",
    "sg:postcode":"33316",
    "sg:province":"FL",
    "sg:tags":[
        "agency"
    ],
    "wof:name":"Millennia Cruises Inc",
    "wof:placetype":"venue"
},
  "geometry": {"coordinates":[-80.10826299999999,26.108739],"type":"Point"}
}