{
  "type": "Feature",
  "properties": {
    "addr:full":"2800 N US Hwy 17/92 Longwood FL 32750",
    "addr:housenumber":"2800;92",
    "addr:postcode":"32750",
    "addr:street":"N Us Hwy 17 /",
    "iso:country":"US",
    "sg:address":"2800 N US Hwy 17/92",
    "sg:city":"Longwood",
    "sg:classifiers":[
        {
            "category":"Freight",
            "type":"Transportation"
        }
    ],
    "sg:phone":"+1 407 839 0599",
    "sg:postcode":"32750",
    "sg:province":"FL",
    "sg:tags":[
        "trucking"
    ],
    "wof:name":"Tucker Transport",
    "wof:placetype":"venue"
},
  "geometry": {"coordinates":[-81.318275,28.722023],"type":"Point"}
}