{
  "type": "Feature",
  "properties": {
    "addr:full":"5317 Rowe Trl Milton FL 32571",
    "addr:housenumber":"5317",
    "addr:postcode":"32571",
    "addr:street":"Rowe Trl",
    "iso:country":"US",
    "sg:address":"5317 Rowe Trl",
    "sg:city":"Milton",
    "sg:classifiers":[
        {
            "category":"Building & Trades",
            "subcategory":"Construction",
            "type":"Services"
        }
    ],
    "sg:phone":"+1 850 484 4322",
    "sg:postcode":"32571",
    "sg:province":"FL",
    "sg:tags":[
        "roofing",
        "contractor"
    ],
    "wof:name":"Lowery Roofing Systems",
    "wof:placetype":"venue"
},
  "geometry": {"coordinates":[-87.188047,30.625562],"type":"Point"}
}