{
  "type": "Feature",
  "properties": {
    "addr:full":"16304 S Hwy 25 Weirsdale FL 34498",
    "addr:housenumber":"16304",
    "addr:postcode":"34498",
    "addr:street":"S Hwy 25 Weirsdale",
    "iso:country":"US",
    "sg:address":"16304 S Hwy 25",
    "sg:city":"Weirsdale",
    "sg:classifiers":[
        {
            "category":"Food & Beverages",
            "subcategory":"Groceries & Convenience Stores",
            "type":"Retail Goods"
        }
    ],
    "sg:phone":"+1 352 821 2179",
    "sg:postcode":"34498",
    "sg:province":"FL",
    "sg:tags":[
        "grocer"
    ],
    "wof:name":"Weirsdale Grocery",
    "wof:placetype":"venue"
},
  "geometry": {"coordinates":[-81.920863,28.985581],"type":"Point"}
}