{
  "type": "Feature",
  "properties": {
    "addr:full":"1961 SE Gena Rd Port Saint Lucie FL 34952",
    "addr:housenumber":"1961",
    "addr:postcode":"34952",
    "addr:street":"Se Gena Rd",
    "iso:country":"US",
    "sg:address":"1961 SE Gena Rd",
    "sg:city":"Port Saint Lucie",
    "sg:classifiers":[
        {
            "category":"Building & Trades",
            "subcategory":"Plumbing",
            "type":"Services"
        }
    ],
    "sg:phone":"+1 772 335 8220",
    "sg:postcode":"34952",
    "sg:province":"FL",
    "sg:tags":[
        "plumbing",
        "contractor"
    ],
    "wof:name":"Drainmaster Inc",
    "wof:placetype":"venue"
},
  "geometry": {"coordinates":[-80.292484,27.272233],"type":"Point"}
}