{
  "type": "Feature",
  "properties": {
    "addr:full":"5215 Glover Ln Baker FL 32570",
    "addr:housenumber":"5215",
    "addr:postcode":"32570",
    "addr:street":"Glover Ln",
    "iso:country":"US",
    "sg:address":"5215 Glover Ln",
    "sg:city":"Baker",
    "sg:classifiers":[
        {
            "category":"Manufacturing",
            "subcategory":"Retail Goods",
            "type":"Manufacturing & Wholesale Goods"
        }
    ],
    "sg:phone":"+1 850 537 6404",
    "sg:postcode":"32570",
    "sg:province":"FL",
    "sg:tags":[
        "product",
        "mfg"
    ],
    "wof:name":"Garys Custom Cabinets",
    "wof:placetype":"venue"
},
  "geometry": {"coordinates":[-87.06425900000001,30.625245],"type":"Point"}
}