{
  "type": "Feature",
  "properties": {
    "iso:country":"US",
    "sg:address":"800 West Ave",
    "sg:city":"Miami Beach",
    "sg:classifiers":[
        {
            "category":"Professional",
            "subcategory":"Business Services",
            "type":"Services"
        }
    ],
    "sg:phone":"+1 305 674 7474",
    "sg:postcode":"33139",
    "sg:province":"FL",
    "sg:tags":[
        "interior",
        "consultant",
        "design",
        "decorator"
    ],
    "sg:website":"www.conceptouno.com",
    "wof:name":"Concepto Uno",
    "wof:placetype":"venue"
},
  "geometry": {"coordinates":[-80.14208000000001,25.776752],"type":"Point"}
}