{
  "type": "Feature",
  "properties": {
    "iso:country":"US",
    "sg:address":"11701 NW 100th Rd",
    "sg:city":"Medley",
    "sg:classifiers":[
        {
            "category":"Freight",
            "type":"Transportation"
        }
    ],
    "sg:phone":"+1 305 883 4735",
    "sg:postcode":"33178",
    "sg:province":"FL",
    "sg:tags":[
        "operator",
        "cartage",
        "local",
        "trucking"
    ],
    "sg:website":"www.pentrans.com",
    "wof:name":"Penser Transportation Inc",
    "wof:placetype":"venue"
},
  "geometry": {"coordinates":[-80.362262,25.875638],"type":"Point"}
}