{
  "type": "Feature",
  "properties": {
    "iso:country":"US",
    "sg:address":"555 E 11th St",
    "sg:city":"Hialeah",
    "sg:classifiers":[
        {
            "category":"Organizations",
            "subcategory":"Religious Organization",
            "type":"Services"
        }
    ],
    "sg:phone":"+1 305 885 1629",
    "sg:postcode":"33010",
    "sg:province":"FL",
    "sg:tags":[
        "church"
    ],
    "wof:name":"First Presbyterian Church",
    "wof:placetype":"venue"
},
  "geometry": {"coordinates":[-80.27063699999999,25.832159],"type":"Point"}
}