{
  "type": "Feature",
  "properties": {
    "addr:full":"19071 SW 49th Pl Dunnellon FL 34432",
    "addr:housenumber":"19071",
    "addr:postcode":"34432",
    "addr:street":"Sw 49Th Pl",
    "iso:country":"US",
    "sg:address":"19071 SW 49th Pl",
    "sg:city":"Dunnellon",
    "sg:classifiers":[
        {
            "category":"Transit Center",
            "subcategory":"Freight",
            "type":"Transportation"
        },
        {
            "category":"Freight",
            "type":"Transportation"
        }
    ],
    "sg:phone":"+1 352 489 9211",
    "sg:postcode":"34432",
    "sg:province":"FL",
    "sg:tags":[
        "local",
        "trucking-motor",
        "trucking"
    ],
    "wof:name":"Farrout Trucking",
    "wof:placetype":"venue"
},
  "geometry": {"coordinates":[-82.437332,29.138726],"type":"Point"}
}