{
  "type": "Feature",
  "properties": {
    "iso:country":"US",
    "sg:address":"5144 City St",
    "sg:city":"Orlando",
    "sg:classifiers":[
        {
            "category":"Shopping",
            "subcategory":"Catalog Store",
            "type":"Retail Goods"
        }
    ],
    "sg:phone":"+1 407 251 4446",
    "sg:postcode":"32839",
    "sg:province":"FL",
    "sg:tags":[
        "house",
        "auto",
        "mail"
    ],
    "wof:name":"All Power Supply Inc",
    "wof:placetype":"venue"
},
  "geometry": {"coordinates":[-81.41476900000001,28.492248],"type":"Point"}
}