{
  "type": "Feature",
  "properties": {
    "iso:country":"US",
    "sg:address":"10058 Diamond Lake Dr",
    "sg:city":"Boynton Beach",
    "sg:classifiers":[
        {
            "category":"Professional",
            "subcategory":"Lawyer & Legal Services",
            "type":"Services"
        }
    ],
    "sg:phone":"+1 561 742 0252",
    "sg:postcode":"33437",
    "sg:province":"FL",
    "wof:name":"Morton Kosto",
    "wof:placetype":"venue"
},
  "geometry": {"coordinates":[-80.141383,26.527407],"type":"Point"}
}