{
  "type": "Feature",
  "properties": {
    "addr:full":"10712 Florence Ave Thonotosassa FL 33592",
    "addr:housenumber":"10712",
    "addr:postcode":"33592",
    "addr:street":"Florence Ave",
    "iso:country":"US",
    "sg:address":"10712 Florence Ave",
    "sg:city":"Thonotosassa",
    "sg:classifiers":[
        {
            "category":"Building & Trades",
            "subcategory":"Construction",
            "type":"Services"
        }
    ],
    "sg:phone":"+1 813 986 7772",
    "sg:postcode":"33592",
    "sg:province":"FL",
    "sg:tags":[
        "residential",
        "stucco",
        "contractor"
    ],
    "wof:name":"Tomlinson Brothers Constr Co",
    "wof:placetype":"venue"
},
  "geometry": {"coordinates":[-82.29488600000001,28.065419],"type":"Point"}
}