{
  "type": "Feature",
  "properties": {
    "iso:country":"US",
    "sg:address":"339 N State Rd 7",
    "sg:city":"Fort Lauderdale",
    "sg:classifiers":[
        {
            "category":"Retail",
            "subcategory":"Laundry & Dry Cleaning",
            "type":"Services"
        }
    ],
    "sg:phone":"+1 954 587 1960",
    "sg:postcode":"33317",
    "sg:province":"FL",
    "sg:tags":[
        "drycleaning",
        "plant",
        "except",
        "rug"
    ],
    "wof:name":"Valeteria Dry Cleaners",
    "wof:placetype":"venue"
},
  "geometry": {"coordinates":[-80.20220999999999,26.124534],"type":"Point"}
}