{
  "type": "Feature",
  "properties": {
    "iso:country":"US",
    "sg:address":"126 Del Prado Blvd N Ste 101",
    "sg:city":"Cape Coral",
    "sg:classifiers":[
        {
            "category":"Health Services",
            "subcategory":"Doctor",
            "type":"Services"
        }
    ],
    "sg:phone":"+1 239 772 3295",
    "sg:postcode":"33909",
    "sg:province":"FL",
    "sg:tags":[
        "practice",
        "family"
    ],
    "wof:name":"Krishnan Lakshmi MD",
    "wof:placetype":"venue"
},
  "geometry": {"coordinates":[-81.941028,26.65452],"type":"Point"}
}