{
  "type": "Feature",
  "properties": {
    "iso:country":"US",
    "sg:address":"322 N Mars Ave",
    "sg:city":"Clearwater",
    "sg:classifiers":[
        {
            "category":"Place Of Worship",
            "type":"Public Place"
        }
    ],
    "sg:phone":"+1 727 743 2689",
    "sg:postcode":"33755",
    "sg:province":"FL",
    "sg:tags":[
        "church"
    ],
    "wof:name":"Liga Infantil Hispana Inc",
    "wof:placetype":"venue"
},
  "geometry": {"coordinates":[-82.763997,27.96935],"type":"Point"}
}