{
  "type": "Feature",
  "properties": {
    "iso:country":"US",
    "sg:address":"1451 NW 1st Ct",
    "sg:city":"Boca Raton",
    "sg:classifiers":[
        {
            "category":"Home & Garden",
            "subcategory":"Building Materials",
            "type":"Retail Goods"
        }
    ],
    "sg:phone":"+1 561 361 3010",
    "sg:postcode":"33432",
    "sg:province":"FL",
    "wof:name":"Millwork Depot Inc",
    "wof:placetype":"venue"
},
  "geometry": {"coordinates":[-80.08744,26.363294],"type":"Point"}
}