{
  "type": "Feature",
  "properties": {
    "addr:full":"5640 Pleasant Valley Ln Delray Beach FL 33484",
    "addr:housenumber":"5640",
    "addr:postcode":"33484",
    "addr:street":"Pleasant Valley Ln",
    "iso:country":"US",
    "sg:address":"5640 Pleasant Valley Ln",
    "sg:city":"Delray Beach",
    "sg:classifiers":[
        {
            "category":"Wholesale",
            "subcategory":"Auto Parts",
            "type":"Manufacturing & Wholesale Goods"
        }
    ],
    "sg:phone":"+1 561 381 3992",
    "sg:postcode":"33484",
    "sg:province":"FL",
    "sg:tags":[
        "motor",
        "air"
    ],
    "wof:name":"Dynaforce Division",
    "wof:placetype":"venue"
},
  "geometry": {"coordinates":[-80.131686,26.430622],"type":"Point"}
}