{
  "type": "Feature",
  "properties": {
    "iso:country":"US",
    "sg:address":"1616 SW 11th Ct",
    "sg:city":"Fort Lauderdale",
    "sg:classifiers":[
        {
            "category":"Real Estate",
            "subcategory":"Real Estate Agent",
            "type":"Services"
        }
    ],
    "sg:phone":"+1 954 762 9434",
    "sg:postcode":"33312",
    "sg:province":"FL",
    "sg:tags":[
        "investment"
    ],
    "wof:name":"Robersons Inc 777",
    "wof:placetype":"venue"
},
  "geometry": {"coordinates":[-80.16479,26.107772],"type":"Point"}
}