{
  "type": "Feature",
  "properties": {
    "iso:country":"US",
    "sg:address":"21311 NE 23rd Ave",
    "sg:city":"Miami",
    "sg:classifiers":[
        {
            "category":"Home & Garden",
            "subcategory":"Building Materials",
            "type":"Retail Goods"
        }
    ],
    "sg:phone":"+1 305 354 4554",
    "sg:postcode":"33180",
    "sg:province":"FL",
    "wof:name":"Ceramica America Inc",
    "wof:placetype":"venue"
},
  "geometry": {"coordinates":[-80.156071,25.97213],"type":"Point"}
}