{
  "type": "Feature",
  "properties": {
    "addr:full":"4767 NW 167th St Opa Locka FL 33055",
    "addr:housenumber":"4767",
    "addr:postcode":"33055",
    "addr:street":"Nw 167Th St;Locka",
    "iso:country":"US",
    "sg:address":"4767 NW 167th St",
    "sg:city":"Opa Locka",
    "sg:classifiers":[
        {
            "category":"Shopping",
            "subcategory":"Discount & Variety Stores",
            "type":"Retail Goods"
        }
    ],
    "sg:phone":"+1 305 624 0640",
    "sg:postcode":"33055",
    "sg:province":"FL",
    "sg:tags":[
        "merchandise",
        "general"
    ],
    "wof:name":"Evas 99 Store",
    "wof:placetype":"venue"
},
  "geometry": {"coordinates":[-80.27763299999999,25.925624],"type":"Point"}
}