{
  "type": "Feature",
  "properties": {
    "addr:full":"5694 Lincoln Cir E Lake Worth FL 33463",
    "addr:housenumber":"5694",
    "addr:postcode":"33463",
    "addr:street":"Lincoln Cir E",
    "iso:country":"US",
    "sg:address":"5694 Lincoln Cir E",
    "sg:city":"Lake Worth",
    "sg:classifiers":[
        {
            "category":"Personal",
            "subcategory":"Beauty Salon",
            "type":"Services"
        }
    ],
    "sg:phone":"+1 561 968 8271",
    "sg:postcode":"33463",
    "sg:province":"FL",
    "sg:tags":[
        "shop"
    ],
    "wof:name":"Cuts Unlimited Total Services",
    "wof:placetype":"venue"
},
  "geometry": {"coordinates":[-80.13524099999999,26.594979],"type":"Point"}
}