{
  "type": "Feature",
  "properties": {
    "addr:full":"17912 Pepper Tree Ln Lutz FL 33548",
    "addr:housenumber":"17912",
    "addr:postcode":"33548",
    "addr:street":"Pepper Tree Ln",
    "iso:country":"US",
    "sg:address":"17912 Pepper Tree Ln",
    "sg:city":"Lutz",
    "sg:classifiers":[
        {
            "category":"Retail",
            "subcategory":"Animal Services",
            "type":"Services"
        }
    ],
    "sg:phone":"+1 813 963 3776",
    "sg:postcode":"33548",
    "sg:province":"FL",
    "sg:tags":[
        "pet",
        "training"
    ],
    "wof:name":"B Paws-Itive Pet Dog Training",
    "wof:placetype":"venue"
},
  "geometry": {"coordinates":[-82.479642,28.134631],"type":"Point"}
}