{
  "type": "Feature",
  "properties": {
    "iso:country":"US",
    "sg:address":"3151 W Hallandale Beach Blvd",
    "sg:city":"Hallandale",
    "sg:classifiers":[
        {
            "category":"Building & Trades",
            "subcategory":"Locksmith",
            "type":"Services"
        }
    ],
    "sg:phone":"+1 954 744 7081",
    "sg:postcode":"33009",
    "sg:province":"FL",
    "sg:tags":[
        "locksmiths-commercial",
        "industrial",
        "key",
        "lock"
    ],
    "wof:name":"1 Best Lock And Key Of South Fl",
    "wof:placetype":"venue"
},
  "geometry": {"coordinates":[-80.170799,25.984871],"type":"Point"}
}