{
  "type": "Feature",
  "properties": {
    "addr:full":"119 Oak Leaf Ln Longwood FL 32779",
    "addr:housenumber":"119",
    "addr:postcode":"32779",
    "addr:street":"Oak Leaf Ln",
    "iso:country":"US",
    "sg:address":"119 Oak Leaf Ln",
    "sg:city":"Longwood",
    "sg:classifiers":[
        {
            "category":"Wholesale",
            "subcategory":"Durable Goods & Equipment",
            "type":"Manufacturing & Wholesale Goods"
        }
    ],
    "sg:phone":"+1 407 786 6756",
    "sg:postcode":"32779",
    "sg:province":"FL",
    "sg:tags":[
        "shop",
        "french",
        "gift"
    ],
    "wof:name":"Paris Soleil Inc",
    "wof:placetype":"venue"
},
  "geometry": {"coordinates":[-81.442229,28.698392],"type":"Point"}
}