{
  "type": "Feature",
  "properties": {
    "addr:full":"524 S Hopkins Ave Titusville FL 32796",
    "addr:housenumber":"524",
    "addr:postcode":"32796",
    "addr:street":"S Hopkins Ave",
    "iso:country":"US",
    "sg:address":"524 S Hopkins Ave",
    "sg:city":"Titusville",
    "sg:classifiers":[
        {
            "category":"Retail",
            "subcategory":"Repair Shop",
            "type":"Services"
        }
    ],
    "sg:phone":"+1 321 269 3340",
    "sg:postcode":"32796",
    "sg:province":"FL",
    "sg:tags":[
        "good",
        "mfg"
    ],
    "wof:name":"Roto-Rooter",
    "wof:placetype":"venue"
},
  "geometry": {"coordinates":[-80.80841700000001,28.609457],"type":"Point"}
}