{
  "type": "Feature",
  "properties": {
    "addr:full":"465 SE 1st Ave Delray Beach FL 33444",
    "addr:housenumber":"465",
    "addr:postcode":"33444",
    "addr:street":"Se 1St Ave",
    "iso:country":"US",
    "sg:address":"465 SE 1st Ave",
    "sg:city":"Delray Beach",
    "sg:classifiers":[
        {
            "category":"Retail",
            "subcategory":"Auto Repair",
            "type":"Services"
        }
    ],
    "sg:phone":"+1 561 243 6431",
    "sg:postcode":"33444",
    "sg:province":"FL",
    "sg:tags":[
        "repairing",
        "automobile"
    ],
    "wof:name":"Edwin's Auto Repair",
    "wof:placetype":"venue"
},
  "geometry": {"coordinates":[-80.072596,26.453265],"type":"Point"}
}