{
  "type": "Feature",
  "properties": {
    "iso:country":"US",
    "sg:address":"2076 Ridgelane Rd",
    "sg:city":"Clearwater",
    "sg:classifiers":[
        {
            "category":"Building & Trades",
            "subcategory":"Cleaning & Sanitation",
            "type":"Services"
        }
    ],
    "sg:phone":"+1 727 776 6464",
    "sg:postcode":"33755",
    "sg:province":"FL",
    "sg:tags":[
        "janitor"
    ],
    "wof:name":"Miracle Workers",
    "wof:placetype":"venue"
},
  "geometry": {"coordinates":[-82.77775099999999,27.995797],"type":"Point"}
}