{
  "type": "Feature",
  "properties": {
    "iso:country":"US",
    "sg:address":"3620 NW 94th Ave",
    "sg:city":"Hollywood",
    "sg:classifiers":[
        {
            "category":"Restaurant",
            "type":"Food & Drink"
        }
    ],
    "sg:phone":"+1 954 438 0376",
    "sg:postcode":"33024",
    "sg:province":"FL",
    "sg:tags":[
        "pizza"
    ],
    "wof:name":"Salvatore Pizza & Pasta",
    "wof:placetype":"venue"
},
  "geometry": {"coordinates":[-80.27195500000001,26.039847],"type":"Point"}
}