{
  "type": "Feature",
  "properties": {
    "addr:full":"501 Evelyn Ave Lakeland FL 33801",
    "addr:housenumber":"501",
    "addr:postcode":"33801",
    "addr:street":"Evelyn Ave",
    "iso:country":"US",
    "sg:address":"501 Evelyn Ave",
    "sg:city":"Lakeland",
    "sg:classifiers":[
        {
            "category":"Government",
            "subcategory":"Office",
            "type":"Public Place"
        }
    ],
    "sg:phone":"+1 863 834 8773",
    "sg:postcode":"33801",
    "sg:province":"FL",
    "sg:tags":[
        "city",
        "program"
    ],
    "wof:name":"Lakeland Solid Waste Mgmt",
    "wof:placetype":"venue"
},
  "geometry": {"coordinates":[-81.941862,28.048883],"type":"Point"}
}