{
  "type": "Feature",
  "properties": {
    "addr:full":"484 21st St Vero Beach FL 32960",
    "addr:housenumber":"484",
    "addr:postcode":"32960",
    "addr:street":"21St St",
    "iso:country":"US",
    "sg:address":"484 21st St",
    "sg:city":"Vero Beach",
    "sg:classifiers":[
        {
            "category":"Bars & Pubs",
            "type":"Food & Drink"
        },
        {
            "category":"Restaurant",
            "type":"Food & Drink"
        }
    ],
    "sg:phone":"+1 772 567 3838",
    "sg:postcode":"32960",
    "sg:province":"FL",
    "sg:tags":[
        "eating"
    ],
    "wof:name":"Kelley's Irish Pub",
    "wof:placetype":"venue"
},
  "geometry": {"coordinates":[-80.383145,27.639806],"type":"Point"}
}