{
  "type": "Feature",
  "properties": {
    "iso:country":"US",
    "sg:address":"4575 Laredo Ave",
    "sg:city":"Fort Myers",
    "sg:classifiers":[
        {
            "category":"Building & Trades",
            "subcategory":"Construction",
            "type":"Services"
        }
    ],
    "sg:phone":"+1 239 334 7383",
    "sg:postcode":"33905",
    "sg:province":"FL",
    "sg:tags":[
        "company"
    ],
    "wof:name":"Marcobay Construction",
    "wof:placetype":"venue"
},
  "geometry": {"coordinates":[-81.816575,26.645433],"type":"Point"}
}