{
  "type": "Feature",
  "properties": {
    "addr:full":"1001 W Jasmine Dr Lake Park FL 33403",
    "addr:housenumber":"1001",
    "addr:postcode":"33403",
    "addr:street":"W Jasmine Dr",
    "iso:country":"US",
    "sg:address":"1001 W Jasmine Dr",
    "sg:city":"Lake Park",
    "sg:classifiers":[
        {
            "category":"Home & Garden",
            "subcategory":"Household Appliances",
            "type":"Retail Goods"
        }
    ],
    "sg:phone":"+1 561 844 0365",
    "sg:postcode":"33403",
    "sg:province":"FL",
    "sg:tags":[
        "machine",
        "sewing"
    ],
    "wof:name":"Sewing & Vacuum Ctr",
    "wof:placetype":"venue"
},
  "geometry": {"coordinates":[-80.074218,26.800901],"type":"Point"}
}