{
  "type": "Feature",
  "properties": {
    "addr:full":"100 Cessna Blvd Port Orange FL 32128",
    "addr:housenumber":"100",
    "addr:postcode":"32128",
    "addr:street":"Cessna Blvd",
    "iso:country":"US",
    "sg:address":"100 Cessna Blvd",
    "sg:city":"Port Orange",
    "sg:classifiers":[
        {
            "category":"Restaurant",
            "type":"Food & Drink"
        }
    ],
    "sg:phone":"+1 386 756 8811",
    "sg:postcode":"32128",
    "sg:province":"FL",
    "wof:name":"Downwind Cafe",
    "wof:placetype":"venue"
},
  "geometry": {"coordinates":[-81.04071399999999,29.077433],"type":"Point"}
}