{
  "type": "Feature",
  "properties": {
    "iso:country":"US",
    "sg:address":"5061 14th Ave SW",
    "sg:city":"Naples",
    "sg:classifiers":[
        {
            "category":"Building & Trades",
            "subcategory":"Construction",
            "type":"Services"
        }
    ],
    "sg:phone":"+1 239 597 4200",
    "sg:postcode":"34116",
    "sg:province":"FL",
    "sg:tags":[
        "coping",
        "plastering",
        "tiling",
        "pool",
        "swimming"
    ],
    "wof:name":"Paradise Pools Of Naples Inc",
    "wof:placetype":"venue"
},
  "geometry": {"coordinates":[-81.708808,26.203074],"type":"Point"}
}