{
  "type": "Feature",
  "properties": {
    "iso:country":"US",
    "sg:address":"6126 Turnbury Park Dr",
    "sg:city":"Sarasota",
    "sg:classifiers":[
        {
            "category":"Professional",
            "subcategory":"Business Services",
            "type":"Services"
        }
    ],
    "sg:phone":"+1 941 906 1777",
    "sg:postcode":"34243",
    "sg:province":"FL",
    "sg:tags":[
        "interior",
        "consultant",
        "design",
        "decorator"
    ],
    "wof:name":"Tradewinds Interiors Inc",
    "wof:placetype":"venue"
},
  "geometry": {"coordinates":[-82.48662400000001,27.390962],"type":"Point"}
}