{
  "type": "Feature",
  "properties": {
    "iso:country":"US",
    "sg:address":"6027 9th St N",
    "sg:city":"St Petersburg",
    "sg:classifiers":[
        {
            "category":"Health Services",
            "subcategory":"Doctor",
            "type":"Services"
        }
    ],
    "sg:phone":"+1 727 521 1616",
    "sg:postcode":"33703",
    "sg:province":"FL",
    "sg:tags":[
        "dentist"
    ],
    "wof:name":"Family Dentistry",
    "wof:placetype":"venue"
},
  "geometry": {"coordinates":[-82.64678000000001,27.825367],"type":"Point"}
}