{
  "type": "Feature",
  "properties": {
    "iso:country":"US",
    "sg:address":"2604 Lowell Cir",
    "sg:city":"Melbourne",
    "sg:classifiers":[
        {
            "category":"Professional",
            "subcategory":"Computer Services",
            "type":"Services"
        }
    ],
    "sg:phone":"+1 321 242 8611",
    "sg:postcode":"32935",
    "sg:province":"FL",
    "sg:tags":[
        "product",
        "developer"
    ],
    "wof:name":"Squires Engineering Inc",
    "wof:placetype":"venue"
},
  "geometry": {"coordinates":[-80.66874,28.154292],"type":"Point"}
}