{
  "type": "Feature",
  "properties": {
    "iso:country":"US",
    "sg:address":"113 Towne Center Cir",
    "sg:city":"Sanford",
    "sg:classifiers":[
        {
            "category":"Shopping",
            "subcategory":"Clothing, Apparel, & Fashions",
            "type":"Retail Goods"
        }
    ],
    "sg:phone":"+1 407 320 1892",
    "sg:postcode":"32771",
    "sg:province":"FL",
    "wof:name":"Charlotte Russe",
    "wof:placetype":"venue"
},
  "geometry": {"coordinates":[-81.33688600000001,28.80948],"type":"Point"}
}