{
  "type": "Feature",
  "properties": {
    "iso:country":"US",
    "sg:address":"2103 S US Hwy 1",
    "sg:city":"Fort Pierce",
    "sg:classifiers":[
        {
            "category":"Shopping",
            "subcategory":"Shoes",
            "type":"Retail Goods"
        }
    ],
    "sg:phone":"+1 772 465 7231",
    "sg:postcode":"34950",
    "sg:province":"FL",
    "wof:name":"999 & Up Discount Shoe Factory",
    "wof:placetype":"venue"
},
  "geometry": {"coordinates":[-80.32600499999999,27.425385],"type":"Point"}
}