{
  "type": "Feature",
  "properties": {
    "iso:country":"US",
    "sg:address":"9961 NW 18th St",
    "sg:city":"Hollywood",
    "sg:classifiers":[
        {
            "category":"Banks & Credit Unions",
            "subcategory":"Financial Services",
            "type":"Services"
        },
        {
            "category":"Travel",
            "subcategory":"Travel Agent",
            "type":"Entertainment"
        }
    ],
    "sg:phone":"+1 954 430 8808",
    "sg:postcode":"33024",
    "sg:province":"FL",
    "sg:tags":[
        "agency",
        "bureau"
    ],
    "wof:name":"C & C Galaxy Travel Inc",
    "wof:placetype":"venue"
},
  "geometry": {"coordinates":[-80.278103,26.023381],"type":"Point"}
}