{
  "type": "Feature",
  "properties": {
    "iso:country":"US",
    "sg:address":"1221 Shady Ln",
    "sg:city":"Lake Wales",
    "sg:classifiers":[
        {
            "category":"Recreation",
            "type":"Entertainment"
        }
    ],
    "sg:phone":"+1 863 692 1668",
    "sg:postcode":"33898",
    "sg:province":"FL",
    "sg:tags":[
        "guide"
    ],
    "wof:name":"Bass Champions Guide Svc",
    "wof:placetype":"venue"
},
  "geometry": {"coordinates":[-81.211697,27.817701],"type":"Point"}
}