{
  "type": "Feature",
  "properties": {
    "iso:country":"US",
    "sg:address":"4123 W Vine St",
    "sg:city":"Kissimmee",
    "sg:classifiers":[
        {
            "category":"Restaurant",
            "type":"Food & Drink"
        }
    ],
    "sg:menulink":"http://www.allmenus.com/fl/kissimmee/44051-logans-roadhouse/menu/",
    "sg:phone":"+1 407 390 0500",
    "sg:postcode":"34741",
    "sg:province":"FL",
    "sg:tags":[
        "american",
        "steakhouse"
    ],
    "wof:name":"Logan's Roadhouse",
    "wof:placetype":"venue"
},
  "geometry": {"coordinates":[-81.446735,28.30446],"type":"Point"}
}