{
  "type": "Feature",
  "properties": {
    "iso:country":"US",
    "sg:address":"4201 L B McLeod Rd",
    "sg:city":"Orlando",
    "sg:classifiers":[
        {
            "category":"Building & Trades",
            "subcategory":"Equipment Rental",
            "type":"Services"
        }
    ],
    "sg:phone":"+1 407 648 0686",
    "sg:postcode":"32811",
    "sg:province":"FL",
    "sg:tags":[
        "heavy",
        "construction"
    ],
    "wof:name":"Prime Industrial",
    "wof:placetype":"venue"
},
  "geometry": {"coordinates":[-81.42815,28.508821],"type":"Point"}
}