{
  "type": "Feature",
  "properties": {
    "iso:country":"US",
    "sg:address":"7520 W 7th Ave",
    "sg:city":"Hialeah",
    "sg:classifiers":[
        {
            "category":"Building & Trades",
            "subcategory":"Construction",
            "type":"Services"
        }
    ],
    "sg:phone":"+1 305 696 8855",
    "sg:postcode":"33014",
    "sg:province":"FL",
    "sg:tags":[
        "demolition",
        "contractor"
    ],
    "wof:name":"Florida Demolition Incorporated",
    "wof:placetype":"venue"
},
  "geometry": {"coordinates":[-80.297804,25.890828],"type":"Point"}
}