{
  "type": "Feature",
  "properties": {
    "iso:country":"US",
    "sg:address":"22353 Rodeo Dr",
    "sg:city":"Brooksville",
    "sg:classifiers":[
        {
            "category":"Shopping",
            "subcategory":"Computers & Home Electronics",
            "type":"Retail Goods"
        }
    ],
    "sg:phone":"+1 352 799 5535",
    "sg:postcode":"34602",
    "sg:province":"FL",
    "sg:tags":[
        "equipment",
        "satellite",
        "system"
    ],
    "wof:name":"Supreme Satellite Svc",
    "wof:placetype":"venue"
},
  "geometry": {"coordinates":[-82.357753,28.455893],"type":"Point"}
}