{
  "type": "Feature",
  "properties": {
    "addr:full":"12251 Taft St Hollywood FL 33026",
    "addr:housenumber":"12251",
    "addr:postcode":"33026",
    "addr:street":"Taft St",
    "iso:country":"US",
    "sg:address":"12251 Taft St",
    "sg:city":"Hollywood",
    "sg:classifiers":[
        {
            "category":"Professional",
            "subcategory":"Research",
            "type":"Services"
        },
        {
            "category":"Health Services",
            "subcategory":"Doctor",
            "type":"Services"
        }
    ],
    "sg:phone":"+1 954 322 1600",
    "sg:postcode":"33026",
    "sg:province":"FL",
    "sg:tags":[
        "nonphysical",
        "clinic",
        "commercial"
    ],
    "wof:name":"Broward Research Group",
    "wof:placetype":"venue"
},
  "geometry": {"coordinates":[-80.310754,26.022505],"type":"Point"}
}