{
  "type": "Feature",
  "properties": {
    "iso:country":"US",
    "sg:address":"900 E Atlantic Ave",
    "sg:city":"Delray Beach",
    "sg:classifiers":[
        {
            "category":"Shopping",
            "subcategory":"Jewelry",
            "type":"Retail Goods"
        }
    ],
    "sg:phone":"+1 561 278 3346",
    "sg:postcode":"33483",
    "sg:province":"FL",
    "sg:tags":[
        "jeweler"
    ],
    "wof:name":"J B Smith & Son Jewelers",
    "wof:placetype":"venue"
},
  "geometry": {"coordinates":[-80.06260899999999,26.461678],"type":"Point"}
}