{
  "type": "Feature",
  "properties": {
    "iso:country":"US",
    "sg:address":"4578 Hiatus Rd",
    "sg:city":"Fort Lauderdale",
    "sg:classifiers":[
        {
            "category":"Manufacturing",
            "subcategory":"Furniture",
            "type":"Manufacturing & Wholesale Goods"
        },
        {
            "category":"Home & Garden",
            "subcategory":"Furniture",
            "type":"Retail Goods"
        }
    ],
    "sg:phone":"+1 954 572 4758",
    "sg:postcode":"33351",
    "sg:province":"FL",
    "wof:name":"Alfa Concepts",
    "wof:placetype":"venue"
},
  "geometry": {"coordinates":[-80.290826,26.180298],"type":"Point"}
}