{
  "type": "Feature",
  "properties": {
    "iso:country":"US",
    "sg:address":"3317 N W St",
    "sg:city":"Pensacola",
    "sg:classifiers":[
        {
            "category":"Shopping",
            "subcategory":"Gifts & Souvenirs",
            "type":"Retail Goods"
        },
        {
            "category":"Shopping",
            "subcategory":"Party Supplies",
            "type":"Retail Goods"
        },
        {
            "category":"Home & Garden",
            "subcategory":"Home Furnishings",
            "type":"Retail Goods"
        },
        {
            "category":"Personal",
            "type":"Services"
        },
        {
            "category":"Shopping",
            "subcategory":"Florist",
            "type":"Retail Goods"
        }
    ],
    "sg:phone":"+1 850 472 0332",
    "sg:postcode":"32505",
    "sg:province":"FL",
    "sg:tags":[
        "shop",
        "decor",
        "planning",
        "delivery",
        "balloons-retail",
        "wedding",
        "basket",
        "event"
    ],
    "sg:website":"http://www.bloomsandbotanicals.com",
    "wof:name":"Distinctive Blooms And Botanical",
    "wof:placetype":"venue"
},
  "geometry": {"coordinates":[-87.24866900000001,30.445261],"type":"Point"}
}