{
  "type": "Feature",
  "properties": {
    "addr:full":"5914 SW 25th St Hollywood FL 33023",
    "addr:housenumber":"5914",
    "addr:postcode":"33023",
    "addr:street":"Sw 25Th St",
    "iso:country":"US",
    "sg:address":"5914 SW 25th St",
    "sg:city":"Hollywood",
    "sg:classifiers":[
        {
            "category":"Building & Trades",
            "subcategory":"Construction",
            "type":"Services"
        }
    ],
    "sg:phone":"+1 954 981 5077",
    "sg:postcode":"33023",
    "sg:province":"FL",
    "sg:tags":[
        "installation",
        "carpet"
    ],
    "wof:name":"Marlins Carpet Service Inc",
    "wof:placetype":"venue"
},
  "geometry": {"coordinates":[-80.20546299999999,25.987861],"type":"Point"}
}