{
  "type": "Feature",
  "properties": {
    "addr:full":"4325 W Kennedy Blvd Tampa FL 33609",
    "addr:housenumber":"4325",
    "addr:postcode":"33609",
    "addr:street":"W Kennedy Blvd",
    "iso:country":"US",
    "sg:address":"4325 W Kennedy Blvd",
    "sg:city":"Tampa",
    "sg:classifiers":[
        {
            "category":"Personal",
            "subcategory":"Beauty Salon",
            "type":"Services"
        }
    ],
    "sg:phone":"+1 813 207 0467",
    "sg:postcode":"33609",
    "sg:province":"FL",
    "sg:tags":[
        "shop",
        "manicuring"
    ],
    "wof:name":"Tampa's Nails",
    "wof:placetype":"venue"
},
  "geometry": {"coordinates":[-82.51804,27.944919],"type":"Point"}
}