{
  "type": "Feature",
  "properties": {
    "addr:full":"8019 N Himes Ave Tampa FL 33614",
    "addr:housenumber":"8019",
    "addr:postcode":"33614",
    "addr:street":"N Himes Ave",
    "iso:country":"US",
    "sg:address":"8019 N Himes Ave",
    "sg:city":"Tampa",
    "sg:classifiers":[
        {
            "category":"Professional",
            "subcategory":"Management & Consulting",
            "type":"Services"
        }
    ],
    "sg:phone":"+1 813 935 5087",
    "sg:postcode":"33614",
    "sg:province":"FL",
    "wof:name":"Paul Samson",
    "wof:placetype":"venue"
},
  "geometry": {"coordinates":[-82.50068,28.025268],"type":"Point"}
}