{
  "type": "Feature",
  "properties": {
    "addr:full":"665 S Orange Ave Sarasota FL 34236",
    "addr:housenumber":"665",
    "addr:postcode":"34236",
    "addr:street":"S Orange Ave",
    "iso:country":"US",
    "sg:address":"665 S Orange Ave",
    "sg:city":"Sarasota",
    "sg:classifiers":[
        {
            "category":"Real Estate",
            "subcategory":"Real Estate Agent",
            "type":"Services"
        }
    ],
    "sg:phone":"+1 941 951 1558",
    "sg:postcode":"34236",
    "sg:province":"FL",
    "wof:name":"Luxury Homelinks",
    "wof:placetype":"venue"
},
  "geometry": {"coordinates":[-82.538541,27.330516],"type":"Point"}
}