{
  "type": "Feature",
  "properties": {
    "addr:full":"150 SE 6th Ave #41 Homestead FL 33030",
    "addr:housenumber":"150;41",
    "addr:postcode":"33030",
    "addr:street":"Se 6Th Ave #",
    "iso:country":"US",
    "sg:address":"150 SE 6th Ave #41",
    "sg:city":"Homestead",
    "sg:classifiers":[
        {
            "category":"Communications",
            "subcategory":"Television Station",
            "type":"Services"
        }
    ],
    "sg:phone":"+1 786 245 4720",
    "sg:postcode":"33030",
    "sg:province":"FL",
    "sg:tags":[
        "satellite",
        "cable"
    ],
    "wof:name":"Dish Homestead- Satellite TV",
    "wof:placetype":"venue"
},
  "geometry": {"coordinates":[-80.468987,25.46853],"type":"Point"}
}