{
  "type": "Feature",
  "properties": {
    "iso:country":"US",
    "sg:address":"801 NE 167th St",
    "sg:city":"Miami",
    "sg:classifiers":[
        {
            "category":"Wholesale",
            "subcategory":"Drugs",
            "type":"Manufacturing & Wholesale Goods"
        },
        {
            "category":"Shopping",
            "type":"Retail Goods"
        }
    ],
    "sg:phone":"+1 305 770 2040",
    "sg:postcode":"33162",
    "sg:province":"FL",
    "sg:tags":[
        "cosmetic",
        "perfume"
    ],
    "wof:name":"Aledian Corp",
    "wof:placetype":"venue"
},
  "geometry": {"coordinates":[-80.182897,25.928668],"type":"Point"}
}