{
  "type": "Feature",
  "properties": {
    "addr:full":"3420 Knights Station Rd Lakeland FL 33810",
    "addr:housenumber":"3420",
    "addr:postcode":"33810",
    "addr:street":"Knights Station Rd",
    "iso:country":"US",
    "sg:address":"3420 Knights Station Rd",
    "sg:city":"Lakeland",
    "sg:classifiers":[
        {
            "category":"Manufacturing",
            "subcategory":"Signs",
            "type":"Manufacturing & Wholesale Goods"
        },
        {
            "category":"Professional",
            "subcategory":"Business Services",
            "type":"Services"
        }
    ],
    "sg:phone":"+1 863 858 2611",
    "sg:postcode":"33810",
    "sg:province":"FL",
    "sg:tags":[
        "specialty",
        "mfg"
    ],
    "wof:name":"Driggers Signs LLC",
    "wof:placetype":"venue"
},
  "geometry": {"coordinates":[-82.01638199999999,28.080441],"type":"Point"}
}