{
  "type": "Feature",
  "properties": {
    "addr:full":"2941 Dawn Rd Jacksonville FL 32207",
    "addr:housenumber":"2941",
    "addr:postcode":"32207",
    "addr:street":"Dawn Rd",
    "iso:country":"US",
    "sg:address":"2941 Dawn Rd",
    "sg:city":"Jacksonville",
    "sg:classifiers":[
        {
            "category":"Building & Trades",
            "subcategory":"Landscaping Services",
            "type":"Services"
        },
        {
            "category":"Building & Trades",
            "subcategory":"Pest Control",
            "type":"Services"
        }
    ],
    "sg:phone":"+1 904 739 9916",
    "sg:postcode":"32207",
    "sg:province":"FL",
    "sg:tags":[
        "lawn",
        "termite",
        "maintenance"
    ],
    "sg:website":"http://www.pestfree.com",
    "wof:name":"Brandon Pest Control",
    "wof:placetype":"venue"
},
  "geometry": {"coordinates":[-81.626306,30.269353],"type":"Point"}
}