{
  "type": "Feature",
  "properties": {
    "iso:country":"US",
    "sg:address":"519 N Newnan St",
    "sg:city":"Jacksonville",
    "sg:classifiers":[
        {
            "category":"Professional",
            "subcategory":"Lawyer & Legal Services",
            "type":"Services"
        }
    ],
    "sg:phone":"+1 904 355 5633",
    "sg:postcode":"32202",
    "sg:province":"FL",
    "sg:tags":[
        "attorney",
        "criminal",
        "family",
        "duo",
        "personal",
        "divorce",
        "injury",
        "dwi",
        "law"
    ],
    "sg:website":"http://www.smithandhainelaw.com",
    "wof:name":"Smith & Haine PA",
    "wof:placetype":"venue"
},
  "geometry": {"coordinates":[-81.654433,30.3296],"type":"Point"}
}