{
  "type": "Feature",
  "properties": {
    "iso:country":"US",
    "sg:address":"2075 S Woodland Blvd",
    "sg:city":"Deland",
    "sg:classifiers":[
        {
            "category":"Autos & Motor Vehicles",
            "subcategory":"Motorcycle Sales",
            "type":"Retail Goods"
        }
    ],
    "sg:phone":"+1 386 734 9747",
    "sg:postcode":"32720",
    "sg:province":"FL",
    "sg:website":"www.pompanopats.com",
    "wof:name":"Pompano Pats Motorcycles",
    "wof:placetype":"venue"
},
  "geometry": {"coordinates":[-81.30189900000001,28.992108],"type":"Point"}
}