{
  "type": "Feature",
  "properties": {
    "iso:country":"US",
    "sg:address":"3300 SW 14th Pl",
    "sg:city":"Boynton Beach",
    "sg:classifiers":[
        {
            "category":"Food & Beverages",
            "subcategory":"Specialty",
            "type":"Retail Goods"
        }
    ],
    "sg:phone":"+1 561 364 2707",
    "sg:postcode":"33426",
    "sg:province":"FL",
    "sg:tags":[
        "water",
        "bulk",
        "company"
    ],
    "wof:name":"American Investment Property",
    "wof:placetype":"venue"
},
  "geometry": {"coordinates":[-80.088035,26.495494],"type":"Point"}
}