{
  "type": "Feature",
  "properties": {
    "iso:country":"US",
    "sg:address":"422 N Wabash Ave",
    "sg:city":"Lakeland",
    "sg:classifiers":[
        {
            "category":"Wholesale",
            "subcategory":"Auto Parts",
            "type":"Manufacturing & Wholesale Goods"
        }
    ],
    "sg:phone":"+1 863 682 4616",
    "sg:postcode":"33815",
    "sg:province":"FL",
    "sg:tags":[
        "engine"
    ],
    "wof:name":"Lawnmower Specialties",
    "wof:placetype":"venue"
},
  "geometry": {"coordinates":[-81.99019199999999,28.046352],"type":"Point"}
}