{
  "type": "Feature",
  "properties": {
    "iso:country":"US",
    "sg:address":"2711 SW 37th Ave",
    "sg:city":"Coconut Grove",
    "sg:classifiers":[
        {
            "category":"Shopping",
            "subcategory":"Pharmacy",
            "type":"Retail Goods"
        }
    ],
    "sg:phone":"+1 305 441 2425",
    "sg:postcode":"33133",
    "sg:province":"FL",
    "sg:tags":[
        "drugstore"
    ],
    "wof:name":"Cerver Pharmacy",
    "wof:placetype":"venue"
},
  "geometry": {"coordinates":[-80.25407199999999,25.740802],"type":"Point"}
}