{
  "type": "Feature",
  "properties": {
    "iso:country":"US",
    "sg:address":"1519 US Hwy 27",
    "sg:city":"Lake Placid",
    "sg:classifiers":[
        {
            "category":"Food & Beverages",
            "subcategory":"Groceries & Convenience Stores",
            "type":"Retail Goods"
        }
    ],
    "sg:phone":"+1 863 465 0416",
    "sg:postcode":"33852",
    "sg:province":"FL",
    "sg:tags":[
        "supermarket",
        "chain"
    ],
    "wof:name":"Casn N Carry Store 1879",
    "wof:placetype":"venue"
},
  "geometry": {"coordinates":[-81.37581400000001,27.326403],"type":"Point"}
}