{
  "type": "Feature",
  "properties": {
    "addr:full":"2120 52nd St S Gulfport FL 33707",
    "addr:housenumber":"2120",
    "addr:postcode":"33707",
    "addr:street":"52Nd St S",
    "iso:country":"US",
    "sg:address":"2120 52nd St S",
    "sg:city":"Gulfport",
    "sg:classifiers":[
        {
            "category":"Professional",
            "subcategory":"Lawyer & Legal Services",
            "type":"Services"
        }
    ],
    "sg:phone":"+1 727 327 4586",
    "sg:postcode":"33707",
    "sg:province":"FL",
    "sg:tags":[
        "attorney"
    ],
    "wof:name":"James O'Neill Law Office",
    "wof:placetype":"venue"
},
  "geometry": {"coordinates":[-82.70374,27.748479],"type":"Point"}
}