{
  "type": "Feature",
  "properties": {
    "addr:full":"8888 SW 136th St Miami FL 33176",
    "addr:housenumber":"8888",
    "addr:postcode":"33176",
    "addr:street":"Sw 136Th St",
    "iso:country":"US",
    "sg:address":"8888 SW 136th St",
    "sg:city":"Miami",
    "sg:classifiers":[
        {
            "category":"Shopping",
            "subcategory":"Gifts & Souvenirs",
            "type":"Retail Goods"
        }
    ],
    "sg:phone":"+1 305 256 1725",
    "sg:postcode":"33176",
    "sg:province":"FL",
    "wof:name":"Gibson Greetings",
    "wof:placetype":"venue"
},
  "geometry": {"coordinates":[-80.336241,25.643664],"type":"Point"}
}