{
  "type": "Feature",
  "properties": {
    "addr:full":"245 SE 1st St Ste 440 Miami FL 33131",
    "addr:housenumber":"245",
    "addr:postcode":"33131",
    "addr:street":"Se 1St St Ste 440",
    "iso:country":"US",
    "sg:address":"245 SE 1st St Ste 440",
    "sg:city":"Miami",
    "sg:classifiers":[
        {
            "category":"Professional",
            "subcategory":"Business Services",
            "type":"Services"
        }
    ],
    "sg:phone":"+1 305 381 8399",
    "sg:postcode":"33131",
    "sg:province":"FL",
    "sg:tags":[
        "delivery",
        "courier"
    ],
    "wof:name":"Lightning Courier Corp",
    "wof:placetype":"venue"
},
  "geometry": {"coordinates":[-80.189245,25.773471],"type":"Point"}
}