{
  "type": "Feature",
  "properties": {
    "iso:country":"US",
    "sg:address":"201 S Biscayne Blvd 28th Floor",
    "sg:city":"Miami",
    "sg:classifiers":[
        {
            "category":"Professional",
            "subcategory":"Computer Services",
            "type":"Services"
        }
    ],
    "sg:phone":"+1 305 808 3293",
    "sg:postcode":"33131",
    "sg:province":"FL",
    "sg:tags":[
        "data",
        "recovery"
    ],
    "sg:website":"http://www.harddriverecoverymiami.com",
    "wof:name":"Miami Data Recovery",
    "wof:placetype":"venue"
},
  "geometry": {"coordinates":[-80.19493,25.766354],"type":"Point"}
}