{
  "type": "Feature",
  "properties": {
    "iso:country":"US",
    "sg:address":"1034 Riviera St",
    "sg:city":"Jacksonville",
    "sg:classifiers":[
        {
            "category":"Retail",
            "subcategory":"Portrait Studio",
            "type":"Services"
        }
    ],
    "sg:phone":"+1 904 387 0910",
    "sg:postcode":"32207",
    "sg:province":"FL",
    "sg:tags":[
        "photographer"
    ],
    "wof:name":"Pho-Dog-Raphy",
    "wof:placetype":"venue"
},
  "geometry": {"coordinates":[-81.65948,30.307507],"type":"Point"}
}