{
  "type": "Feature",
  "properties": {
    "iso:country":"US",
    "sg:address":"11919 SW 272nd Ter",
    "sg:city":"Homestead",
    "sg:classifiers":[
        {
            "category":"Professional",
            "type":"Services"
        }
    ],
    "sg:phone":"+1 305 258 0458",
    "sg:postcode":"33032",
    "sg:province":"FL",
    "wof:name":"Women of Virtue Inc",
    "wof:placetype":"venue"
},
  "geometry": {"coordinates":[-80.383432,25.514394],"type":"Point"}
}