{
  "type": "Feature",
  "properties": {
    "iso:country":"US",
    "sg:address":"6275 Highway 90",
    "sg:city":"Milton",
    "sg:classifiers":[
        {
            "category":"Shopping",
            "subcategory":"Department Store",
            "type":"Retail Goods"
        }
    ],
    "sg:phone":"+1 850 981 0011",
    "sg:postcode":"32570",
    "sg:province":"FL",
    "sg:website":"http://www.bealls.com/",
    "wof:name":"Bealls Department Store",
    "wof:placetype":"venue"
},
  "geometry": {"coordinates":[-87.061522,30.607668],"type":"Point"}
}