{
  "type": "Feature",
  "properties": {
    "addr:full":"435 26th Ave N Saint Petersburg FL 33704",
    "addr:housenumber":"435",
    "addr:postcode":"33704",
    "addr:street":"26Th Ave N",
    "iso:country":"US",
    "sg:address":"435 26th Ave N",
    "sg:city":"Saint Petersburg",
    "sg:classifiers":[
        {
            "category":"Real Estate",
            "subcategory":"Real Estate Agent",
            "type":"Services"
        }
    ],
    "sg:phone":"+1 727 502 9304",
    "sg:postcode":"33704",
    "sg:province":"FL",
    "wof:name":"Bill Gatlin",
    "wof:placetype":"venue"
},
  "geometry": {"coordinates":[-82.63996299999999,27.795829],"type":"Point"}
}