{
  "type": "Feature",
  "properties": {
    "iso:country":"US",
    "sg:address":"7118 Barclay Ave",
    "sg:city":"Brooksville",
    "sg:classifiers":[
        {
            "category":"Building & Trades",
            "subcategory":"Construction",
            "type":"Services"
        }
    ],
    "sg:phone":"+1 352 683 2422",
    "sg:postcode":"34609",
    "sg:province":"FL",
    "sg:tags":[
        "concrete",
        "contractor"
    ],
    "wof:name":"Executive Curbing",
    "wof:placetype":"venue"
},
  "geometry": {"coordinates":[-82.49169000000001,28.531132],"type":"Point"}
}