{
  "type": "Feature",
  "properties": {
    "addr:full":"9705 Hickory Hollow Rd Leesburg FL 34788",
    "addr:housenumber":"9705",
    "addr:postcode":"34788",
    "addr:street":"Hickory Hollow Rd",
    "iso:country":"US",
    "sg:address":"9705 Hickory Hollow Rd",
    "sg:city":"Leesburg",
    "sg:classifiers":[
        {
            "category":"Building & Trades",
            "subcategory":"Landscaping Services",
            "type":"Services"
        }
    ],
    "sg:phone":"+1 352 323 1672",
    "sg:postcode":"34788",
    "sg:province":"FL",
    "sg:tags":[
        "lawn",
        "maintenance",
        "grounds"
    ],
    "wof:name":"C & J Lawn Svc",
    "wof:placetype":"venue"
},
  "geometry": {"coordinates":[-81.79669,28.870291],"type":"Point"}
}