{
  "type": "Feature",
  "properties": {
    "addr:full":"99620 Overseas Hwy Key Largo FL 33037",
    "addr:housenumber":"99620",
    "addr:postcode":"33037",
    "addr:street":"Overseas Hwy",
    "iso:country":"US",
    "sg:address":"99620 Overseas Hwy",
    "sg:city":"Key Largo",
    "sg:classifiers":[
        {
            "category":"Autos & Motor Vehicles",
            "subcategory":"Fuel & Gas Station",
            "type":"Retail Goods"
        }
    ],
    "sg:phone":"+1 305 451 2018",
    "sg:postcode":"33037",
    "sg:province":"FL",
    "sg:tags":[
        "filling",
        "station",
        "gasoline",
        "convenience",
        "store"
    ],
    "wof:name":"Tinys of Key Largo",
    "wof:placetype":"venue"
},
  "geometry": {"coordinates":[-80.441469,25.093781],"type":"Point"}
}