{
  "type": "Feature",
  "properties": {
    "iso:country":"US",
    "sg:address":"1963 Virginia Ave",
    "sg:city":"Clearwater",
    "sg:classifiers":[
        {
            "category":"Building & Trades",
            "subcategory":"Construction",
            "type":"Services"
        }
    ],
    "sg:phone":"+1 727 734 2145",
    "sg:postcode":"33763",
    "sg:province":"FL",
    "sg:tags":[
        "cabinet"
    ],
    "wof:name":"Bcs Cabinet Magic",
    "wof:placetype":"venue"
},
  "geometry": {"coordinates":[-82.75753400000001,28.004602],"type":"Point"}
}