{
  "type": "Feature",
  "properties": {
    "iso:country":"US",
    "sg:address":"21073 Powerline Rd",
    "sg:city":"Boca Raton",
    "sg:classifiers":[
        {
            "category":"Wholesale",
            "subcategory":"Jewelry",
            "type":"Manufacturing & Wholesale Goods"
        }
    ],
    "sg:phone":"+1 561 477 8760",
    "sg:postcode":"33433",
    "sg:province":"FL",
    "sg:tags":[
        "beads"
    ],
    "sg:website":"www.irismoon.com",
    "wof:name":"Boca Beads",
    "wof:placetype":"venue"
},
  "geometry": {"coordinates":[-80.147542,26.364726],"type":"Point"}
}