{
  "type": "Feature",
  "properties": {
    "addr:full":"4929 SW 74th Ct Miami FL 33155",
    "addr:housenumber":"4929",
    "addr:postcode":"33155",
    "addr:street":"Sw 74Th Ct",
    "iso:country":"US",
    "sg:address":"4929 SW 74th Ct",
    "sg:city":"Miami",
    "sg:classifiers":[
        {
            "category":"Health Services",
            "subcategory":"Nursing And Care Facility",
            "type":"Services"
        },
        {
            "category":"Health Services",
            "subcategory":"Health Practitioner",
            "type":"Services"
        },
        {
            "category":"Health Services",
            "subcategory":"Hospice",
            "type":"Services"
        }
    ],
    "sg:phone":"+1 305 665 9919",
    "sg:postcode":"33155",
    "sg:province":"FL",
    "sg:tags":[
        "home",
        "eldercare-home"
    ],
    "wof:name":"Preferred Home Health Care Inc",
    "wof:placetype":"venue"
},
  "geometry": {"coordinates":[-80.315231,25.7248],"type":"Point"}
}