{
  "type": "Feature",
  "properties": {
    "addr:full":"109 2nd St Fort Myers FL 33907",
    "addr:housenumber":"109",
    "addr:postcode":"33907",
    "addr:street":"2Nd St",
    "iso:country":"US",
    "sg:address":"109 2nd St",
    "sg:city":"Fort Myers",
    "sg:classifiers":[
        {
            "category":"Home & Garden",
            "subcategory":"Carpets & Floor Coverings",
            "type":"Retail Goods"
        }
    ],
    "sg:phone":"+1 239 939 5151",
    "sg:postcode":"33907",
    "sg:province":"FL",
    "sg:tags":[
        "carpeting"
    ],
    "wof:name":"Custom Floors of Ft Myers Inc",
    "wof:placetype":"venue"
},
  "geometry": {"coordinates":[-81.864098,26.578199],"type":"Point"}
}