{
  "type": "Feature",
  "properties": {
    "addr:full":"1619 Sun City Center Plz Sun City Center FL 33573",
    "addr:housenumber":"1619",
    "addr:postcode":"33573",
    "addr:street":"Sun;Plz",
    "iso:country":"US",
    "sg:address":"1619 Sun City Center Plz",
    "sg:city":"Sun City Center",
    "sg:classifiers":[
        {
            "category":"Home & Garden",
            "subcategory":"Hardware",
            "type":"Retail Goods"
        }
    ],
    "sg:phone":"+1 813 634 5363",
    "sg:postcode":"33573",
    "sg:province":"FL",
    "wof:name":"SCC Hardware",
    "wof:placetype":"venue"
},
  "geometry": {"coordinates":[-82.355228,27.712671],"type":"Point"}
}