{
  "type": "Feature",
  "properties": {
    "iso:country":"US",
    "sg:address":"254 W Voorhis Ave",
    "sg:city":"Deland",
    "sg:classifiers":[
        {
            "category":"Real Estate",
            "subcategory":"Real Estate Services",
            "type":"Services"
        },
        {
            "category":"Professional",
            "subcategory":"Research",
            "type":"Services"
        },
        {
            "category":"Insurance",
            "subcategory":"Title Insurance",
            "type":"Services"
        }
    ],
    "sg:phone":"+1 386 738 9197",
    "sg:postcode":"32720",
    "sg:province":"FL",
    "sg:tags":[
        "abstracter"
    ],
    "wof:name":"Downtown Title Services",
    "wof:placetype":"venue"
},
  "geometry": {"coordinates":[-81.306473,29.024509],"type":"Point"}
}