{
  "type": "Feature",
  "properties": {
    "iso:country":"US",
    "sg:address":"2041 SW 70th Ave",
    "sg:city":"Davie",
    "sg:classifiers":[
        {
            "category":"Building & Trades",
            "subcategory":"Plumbing",
            "type":"Services"
        }
    ],
    "sg:phone":"+1 954 577 3651",
    "sg:postcode":"33317",
    "sg:province":"FL",
    "sg:tags":[
        "plumber"
    ],
    "sg:website":"http://www.britefutureplumbing.com",
    "wof:name":"Brite Future Plumbing",
    "wof:placetype":"venue"
},
  "geometry": {"coordinates":[-80.237961,26.094241],"type":"Point"}
}