{
  "type": "Feature",
  "properties": {
    "iso:country":"US",
    "sg:address":"924 State Hwy 19 N",
    "sg:city":"Palatka",
    "sg:classifiers":[
        {
            "category":"Professional",
            "subcategory":"Accounting & Tax Preparation",
            "type":"Services"
        }
    ],
    "sg:phone":"+1 386 328 4504",
    "sg:postcode":"32177",
    "sg:province":"FL",
    "sg:tags":[
        "return",
        "filing"
    ],
    "wof:name":"Sadler Bookkeeping Svc",
    "wof:placetype":"venue"
},
  "geometry": {"coordinates":[-81.676428,29.64016],"type":"Point"}
}