{
  "type": "Feature",
  "properties": {
    "iso:country":"US",
    "sg:address":"3404 Clifden Dr",
    "sg:city":"Tallahassee",
    "sg:classifiers":[
        {
            "category":"Home & Garden",
            "subcategory":"Home Furnishings",
            "type":"Retail Goods"
        }
    ],
    "sg:phone":"+1 866 839 4770",
    "sg:postcode":"32309",
    "sg:province":"FL",
    "sg:tags":[
        "draperies",
        "curtain",
        "window",
        "treatment"
    ],
    "wof:name":"Budget Blinds of Tallahassee",
    "wof:placetype":"venue"
},
  "geometry": {"coordinates":[-84.19029,30.534185],"type":"Point"}
}