{
  "type": "Feature",
  "properties": {
    "addr:full":"6701 Osteen Rd New Port Richey FL 34653",
    "addr:housenumber":"6701",
    "addr:postcode":"34653",
    "addr:street":"Osteen Rd",
    "iso:country":"US",
    "sg:address":"6701 Osteen Rd",
    "sg:city":"New Port Richey",
    "sg:classifiers":[
        {
            "category":"Real Estate",
            "subcategory":"Real Estate Operator",
            "type":"Services"
        }
    ],
    "sg:phone":"+1 727 848 1212",
    "sg:postcode":"34653",
    "sg:province":"FL",
    "sg:tags":[
        "building",
        "apartment"
    ],
    "wof:name":"Orangewood Lakes Apartments",
    "wof:placetype":"venue"
},
  "geometry": {"coordinates":[-82.682574,28.258786],"type":"Point"}
}