{
  "type": "Feature",
  "properties": {
    "addr:full":"18919 Titus Rd Hudson FL 34667",
    "addr:housenumber":"18919",
    "addr:postcode":"34667",
    "addr:street":"Titus Rd",
    "iso:country":"US",
    "sg:address":"18919 Titus Rd",
    "sg:city":"Hudson",
    "sg:classifiers":[
        {
            "category":"Retail",
            "subcategory":"Auto Repair",
            "type":"Services"
        }
    ],
    "sg:phone":"+1 727 862 1968",
    "sg:postcode":"34667",
    "sg:province":"FL",
    "sg:tags":[
        "transmission"
    ],
    "wof:name":"Joe's Reliable Transmission",
    "wof:placetype":"venue"
},
  "geometry": {"coordinates":[-82.61020600000001,28.432223],"type":"Point"}
}