{
  "type": "Feature",
  "properties": {
    "addr:full":"10500 NW 37th St Miami FL 33178",
    "addr:housenumber":"10500",
    "addr:postcode":"33178",
    "addr:street":"Nw 37Th St",
    "iso:country":"US",
    "sg:address":"10500 NW 37th St",
    "sg:city":"Miami",
    "sg:classifiers":[
        {
            "category":"Autos & Motor Vehicles",
            "subcategory":"Auto Supplies",
            "type":"Retail Goods"
        }
    ],
    "sg:phone":"+1 305 593 6160",
    "sg:postcode":"33178",
    "sg:province":"FL",
    "sg:tags":[
        "wholesale",
        "parts"
    ],
    "wof:name":"International Prfmce Whse Ipw",
    "wof:placetype":"venue"
},
  "geometry": {"coordinates":[-80.383956,25.808725],"type":"Point"}
}