{
  "type": "Feature",
  "properties": {
    "iso:country":"US",
    "sg:address":"7244 NW 70th St",
    "sg:city":"Miami",
    "sg:classifiers":[
        {
            "category":"Wholesale",
            "subcategory":"Auto Parts",
            "type":"Manufacturing & Wholesale Goods"
        }
    ],
    "sg:phone":"+1 305 805 2010",
    "sg:postcode":"33166",
    "sg:province":"FL",
    "sg:tags":[
        "engine"
    ],
    "wof:name":"BTMC Corp Miami",
    "wof:placetype":"venue"
},
  "geometry": {"coordinates":[-80.31518,25.837032],"type":"Point"}
}