{
  "type": "Feature",
  "properties": {
    "iso:country":"US",
    "sg:address":"6444 52nd Ave N",
    "sg:city":"St Petersburg",
    "sg:classifiers":[
        {
            "category":"Building & Trades",
            "subcategory":"Landscaping Services",
            "type":"Services"
        }
    ],
    "sg:phone":"+1 727 544 3537",
    "sg:postcode":"33709",
    "sg:province":"FL",
    "sg:tags":[
        "tree"
    ],
    "wof:name":"Triangle Tree Svc & Landscpng",
    "wof:placetype":"venue"
},
  "geometry": {"coordinates":[-82.720597,27.819523],"type":"Point"}
}