{
  "type": "Feature",
  "properties": {
    "addr:full":"3850 Newberry Rd Gainesville FL 32607",
    "addr:housenumber":"3850",
    "addr:postcode":"32607",
    "addr:street":"Newberry Rd",
    "iso:country":"US",
    "sg:address":"3850 Newberry Rd",
    "sg:city":"Gainesville",
    "sg:classifiers":[
        {
            "category":"Autos & Motor Vehicles",
            "subcategory":"Fuel & Gas Station",
            "type":"Retail Goods"
        }
    ],
    "sg:phone":"+1 352 373 5900",
    "sg:postcode":"32607",
    "sg:province":"FL",
    "sg:tags":[
        "oil"
    ],
    "wof:name":"Shell First Coast Energy",
    "wof:placetype":"venue"
},
  "geometry": {"coordinates":[-82.382109,29.652832],"type":"Point"}
}