{
  "type": "Feature",
  "properties": {
    "iso:country":"US",
    "sg:address":"160 SW Pine Island Rd",
    "sg:city":"Cape Coral",
    "sg:classifiers":[
        {
            "category":"Wholesale",
            "subcategory":"Durable Goods & Equipment",
            "type":"Manufacturing & Wholesale Goods"
        }
    ],
    "sg:phone":"+1 239 464 4332",
    "sg:postcode":"33991",
    "sg:province":"FL",
    "wof:name":"Vinyl Graphic Designs",
    "wof:placetype":"venue"
},
  "geometry": {"coordinates":[-81.975281,26.651493],"type":"Point"}
}