{
  "type": "Feature",
  "properties": {
    "iso:country":"US",
    "sg:address":"2262 SE Flanders Rd",
    "sg:city":"Port St Lucie",
    "sg:classifiers":[
        {
            "category":"Professional",
            "subcategory":"Lawyer & Legal Services",
            "type":"Services"
        }
    ],
    "sg:phone":"+1 772 221 9063",
    "sg:postcode":"34952",
    "sg:province":"FL",
    "sg:tags":[
        "attorney"
    ],
    "wof:name":"Rory Little",
    "wof:placetype":"venue"
},
  "geometry": {"coordinates":[-80.29418200000001,27.276095],"type":"Point"}
}