{
  "type": "Feature",
  "properties": {
    "addr:full":"2507 Utopia Dr Hollywood FL 33023",
    "addr:housenumber":"2507",
    "addr:postcode":"33023",
    "addr:street":"Utopia Dr",
    "iso:country":"US",
    "sg:address":"2507 Utopia Dr",
    "sg:city":"Hollywood",
    "sg:classifiers":[
        {
            "category":"Organizations",
            "subcategory":"Religious Organization",
            "type":"Services"
        }
    ],
    "sg:phone":"+1 954 989 4711",
    "sg:postcode":"33023",
    "sg:province":"FL",
    "wof:name":"Miramar United Methdst Church",
    "wof:placetype":"venue"
},
  "geometry": {"coordinates":[-80.246746,25.984394],"type":"Point"}
}