{
  "type": "Feature",
  "properties": {
    "addr:full":"2000 Cabo San Lucas Dr Orlando FL 32839",
    "addr:housenumber":"2000",
    "addr:postcode":"32839",
    "addr:street":"Cabo San Lucas Dr",
    "iso:country":"US",
    "sg:address":"2000 Cabo San Lucas Dr",
    "sg:city":"Orlando",
    "sg:classifiers":[
        {
            "category":"Building & Trades",
            "subcategory":"Construction",
            "type":"Services"
        }
    ],
    "sg:phone":"+1 407 851 0322",
    "sg:postcode":"32839",
    "sg:province":"FL",
    "sg:tags":[
        "floor",
        "laying",
        "contractor"
    ],
    "wof:name":"Lanten Meraneel",
    "wof:placetype":"venue"
},
  "geometry": {"coordinates":[-81.408753,28.485757],"type":"Point"}
}