{
  "type": "Feature",
  "properties": {
    "addr:full":"1200 W Granada Blvd Ormond Beach FL 32174",
    "addr:housenumber":"1200",
    "addr:postcode":"32174",
    "addr:street":"W Granada Blvd",
    "iso:country":"US",
    "sg:address":"1200 W Granada Blvd",
    "sg:city":"Ormond Beach",
    "sg:classifiers":[
        {
            "category":"Health Services",
            "subcategory":"Clinic",
            "type":"Services"
        }
    ],
    "sg:phone":"+1 386 615 1056",
    "sg:postcode":"32174",
    "sg:province":"FL",
    "sg:tags":[
        "organization",
        "maintenance"
    ],
    "wof:name":"Metropolitan Health Network",
    "wof:placetype":"venue"
},
  "geometry": {"coordinates":[-81.10216,29.267263],"type":"Point"}
}