{
  "type": "Feature",
  "properties": {
    "iso:country":"US",
    "sg:address":"3149 Duncan Rd",
    "sg:city":"Punta Gorda",
    "sg:classifiers":[
        {
            "category":"Building & Trades",
            "subcategory":"Plumbing",
            "type":"Services"
        }
    ],
    "sg:phone":"+1 941 575 1644",
    "sg:postcode":"33982",
    "sg:province":"FL",
    "sg:tags":[
        "conditioning",
        "air",
        "system",
        "contractor"
    ],
    "wof:name":"D J's Comfort Control",
    "wof:placetype":"venue"
},
  "geometry": {"coordinates":[-81.95915100000001,26.987801],"type":"Point"}
}