{
  "type": "Feature",
  "properties": {
    "iso:country":"US",
    "sg:address":"1024 Del Prado Blvd S",
    "sg:city":"Cape Coral",
    "sg:classifiers":[
        {
            "category":"Retail",
            "subcategory":"Auto Repair",
            "type":"Services"
        }
    ],
    "sg:phone":"+1 239 574 5550",
    "sg:postcode":"33990",
    "sg:province":"FL",
    "wof:name":"Tony's Auto Air & Car Care Center",
    "wof:placetype":"venue"
},
  "geometry": {"coordinates":[-81.941002,26.6325],"type":"Point"}
}