{
  "type": "Feature",
  "properties": {
    "iso:country":"US",
    "sg:address":"1005 Hospital Rd",
    "sg:city":"Fort Walton Bch",
    "sg:classifiers":[
        {
            "category":"Health Services",
            "subcategory":"Hospital",
            "type":"Services"
        }
    ],
    "sg:phone":"+1 850 863 8100",
    "sg:postcode":"32547",
    "sg:province":"FL",
    "sg:tags":[
        "medical",
        "center"
    ],
    "wof:name":"White-Wilson Medical Ctr",
    "wof:placetype":"venue"
},
  "geometry": {"coordinates":[-86.63403,30.456204],"type":"Point"}
}