{
  "type": "Feature",
  "properties": {
    "addr:full":"7291 W Atlantic Ave Delray Beach FL 33446",
    "addr:housenumber":"7291",
    "addr:postcode":"33446",
    "addr:street":"W Atlantic Ave",
    "iso:country":"US",
    "sg:address":"7291 W Atlantic Ave",
    "sg:city":"Delray Beach",
    "sg:classifiers":[
        {
            "category":"Shopping",
            "subcategory":"Clothing, Apparel, & Fashions",
            "type":"Retail Goods"
        }
    ],
    "sg:phone":"+1 561 498 1026",
    "sg:postcode":"33446",
    "sg:province":"FL",
    "wof:name":"Fashion Faze",
    "wof:placetype":"venue"
},
  "geometry": {"coordinates":[-80.159367,26.453846],"type":"Point"}
}