{
  "type": "Feature",
  "properties": {
    "addr:full":"320 N 24th St Haines City FL 33844",
    "addr:housenumber":"320",
    "addr:postcode":"33844",
    "addr:street":"N 24Th St",
    "iso:country":"US",
    "sg:address":"320 N 24th St",
    "sg:city":"Haines City",
    "sg:classifiers":[
        {
            "category":"Building & Trades",
            "subcategory":"Construction",
            "type":"Services"
        }
    ],
    "sg:phone":"+1 863 422 1908",
    "sg:postcode":"33844",
    "sg:province":"FL",
    "sg:tags":[
        "house"
    ],
    "wof:name":"Cornerstone Construction",
    "wof:placetype":"venue"
},
  "geometry": {"coordinates":[-81.61154500000001,28.111844],"type":"Point"}
}