{
  "type": "Feature",
  "properties": {
    "addr:full":"55 E Granada Blvd Daytona Beach FL 32176",
    "addr:housenumber":"55",
    "addr:postcode":"32176",
    "addr:street":"E Granada Blvd",
    "iso:country":"US",
    "sg:address":"55 E Granada Blvd",
    "sg:city":"Daytona Beach",
    "sg:classifiers":[
        {
            "category":"Government",
            "subcategory":"Post Office",
            "type":"Public Place"
        }
    ],
    "sg:phone":"+1 386 677 3839",
    "sg:postcode":"32176",
    "sg:province":"FL",
    "sg:tags":[
        "postal",
        "us"
    ],
    "wof:name":"US Post Office",
    "wof:placetype":"venue"
},
  "geometry": {"coordinates":[-81.04668599999999,29.289378],"type":"Point"}
}