{
  "type": "Feature",
  "properties": {
    "addr:full":"5051 Kestral Park Dr Sarasota FL 34231",
    "addr:housenumber":"5051",
    "addr:postcode":"34231",
    "addr:street":"Kestral Park Dr",
    "iso:country":"US",
    "sg:address":"5051 Kestral Park Dr",
    "sg:city":"Sarasota",
    "sg:classifiers":[
        {
            "category":"Organizations",
            "subcategory":"Professional Association",
            "type":"Services"
        }
    ],
    "sg:phone":"+1 941 924 0899",
    "sg:postcode":"34231",
    "sg:province":"FL",
    "wof:name":"Polish American Club-Sarasota",
    "wof:placetype":"venue"
},
  "geometry": {"coordinates":[-82.534299,27.278917],"type":"Point"}
}