{
  "type": "Feature",
  "properties": {
    "iso:country":"US",
    "sg:address":"9274 Troon Lakes Dr",
    "sg:city":"Naples",
    "sg:classifiers":[
        {
            "category":"Banks & Credit Unions",
            "subcategory":"Financial Services",
            "type":"Services"
        }
    ],
    "sg:phone":"+1 239 254 1674",
    "sg:postcode":"34109",
    "sg:province":"FL",
    "sg:tags":[
        "investment"
    ],
    "wof:name":"Dr G Grosskopf",
    "wof:placetype":"venue"
},
  "geometry": {"coordinates":[-81.772875,26.251801],"type":"Point"}
}