{
  "type": "Feature",
  "properties": {
    "addr:full":"215 W State Rd 434 Longwood FL 32750",
    "addr:housenumber":"215;434",
    "addr:postcode":"32750",
    "addr:street":"W State Rd",
    "iso:country":"US",
    "sg:address":"215 W State Rd 434",
    "sg:city":"Longwood",
    "sg:classifiers":[
        {
            "category":"Shopping",
            "subcategory":"Clothing, Apparel, & Fashions",
            "type":"Retail Goods"
        }
    ],
    "sg:phone":"+1 407 831 3393",
    "sg:postcode":"32750",
    "sg:province":"FL",
    "sg:tags":[
        "farm",
        "horse",
        "western",
        "wear"
    ],
    "wof:name":"Saddle Up Western Store",
    "wof:placetype":"venue"
},
  "geometry": {"coordinates":[-81.34742199999999,28.697873],"type":"Point"}
}