{
  "type": "Feature",
  "properties": {
    "addr:full":"10900 Orangewood Blvd Orlando FL 32821",
    "addr:housenumber":"10900",
    "addr:postcode":"32821",
    "addr:street":"Orangewood Blvd",
    "iso:country":"US",
    "sg:address":"10900 Orangewood Blvd",
    "sg:city":"Orlando",
    "sg:classifiers":[
        {
            "category":"Banks & Credit Unions",
            "subcategory":"Bank",
            "type":"Services"
        }
    ],
    "sg:phone":"+1 407 420 2800",
    "sg:postcode":"32821",
    "sg:province":"FL",
    "sg:tags":[
        "national"
    ],
    "wof:name":"Bank Of America",
    "wof:placetype":"venue"
},
  "geometry": {"coordinates":[-81.44591,28.405493],"type":"Point"}
}