{
  "type": "Feature",
  "properties": {
    "addr:full":"4402 Melton Ave Tampa FL 33614",
    "addr:housenumber":"4402",
    "addr:postcode":"33614",
    "addr:street":"Melton Ave",
    "iso:country":"US",
    "sg:address":"4402 Melton Ave",
    "sg:city":"Tampa",
    "sg:classifiers":[
        {
            "category":"Insurance",
            "subcategory":"Hazard Insurance",
            "type":"Services"
        }
    ],
    "sg:phone":"+1 813 874 5909",
    "sg:postcode":"33614",
    "sg:province":"FL",
    "sg:tags":[
        "bond"
    ],
    "wof:name":"Anthony Burke Bailbonds",
    "wof:placetype":"venue"
},
  "geometry": {"coordinates":[-82.485595,27.983034],"type":"Point"}
}