{
  "type": "Feature",
  "properties": {
    "addr:full":"5450 Hansel Ave Orlando FL 32809",
    "addr:housenumber":"5450",
    "addr:postcode":"32809",
    "addr:street":"Hansel Ave",
    "iso:country":"US",
    "sg:address":"5450 Hansel Ave",
    "sg:city":"Orlando",
    "sg:classifiers":[
        {
            "category":"Education",
            "subcategory":"Special Training",
            "type":"Public Place"
        }
    ],
    "sg:phone":"+1 407 240 5559",
    "sg:postcode":"32809",
    "sg:province":"FL",
    "sg:tags":[
        "grooming",
        "dog",
        "school"
    ],
    "wof:name":"Central Fla Schl of Dog Grming",
    "wof:placetype":"venue"
},
  "geometry": {"coordinates":[-81.371337,28.481683],"type":"Point"}
}