{
  "type": "Feature",
  "properties": {
    "iso:country":"US",
    "sg:address":"1910 SE Tiffany Ave",
    "sg:city":"Port Saint Lucie",
    "sg:classifiers":[
        {
            "category":"Social Services",
            "subcategory":"Child Care",
            "type":"Services"
        }
    ],
    "sg:phone":"+1 772 335 2339",
    "sg:postcode":"34952",
    "sg:province":"FL",
    "sg:tags":[
        "day"
    ],
    "wof:name":"Tender Loving Care Pet Sitting",
    "wof:placetype":"venue"
},
  "geometry": {"coordinates":[-80.293541,27.292157],"type":"Point"}
}