{
  "type": "Feature",
  "properties": {
    "iso:country":"US",
    "sg:address":"1223 Haymarket Dr",
    "sg:city":"Lakeland",
    "sg:classifiers":[
        {
            "category":"Building & Trades",
            "subcategory":"Construction",
            "type":"Services"
        }
    ],
    "sg:phone":"+1 863 853 3089",
    "sg:postcode":"33809",
    "sg:province":"FL",
    "sg:tags":[
        "home",
        "improvement"
    ],
    "wof:name":"Ry-Lin Ent",
    "wof:placetype":"venue"
},
  "geometry": {"coordinates":[-81.93685000000001,28.136948],"type":"Point"}
}