{
  "type": "Feature",
  "properties": {
    "addr:full":"7262 NW 54th St Miami FL 33166",
    "addr:housenumber":"7262",
    "addr:postcode":"54th;33166",
    "addr:street":"Nw;St",
    "iso:country":"US",
    "sg:address":"7262 NW 54th St",
    "sg:city":"Miami",
    "sg:classifiers":[
        {
            "category":"Wholesale",
            "subcategory":"Electrical",
            "type":"Manufacturing & Wholesale Goods"
        }
    ],
    "sg:phone":"+1 305 889 1127",
    "sg:postcode":"33166",
    "sg:province":"FL",
    "sg:tags":[
        "control",
        "security",
        "system"
    ],
    "wof:name":"Epcom",
    "wof:placetype":"venue"
},
  "geometry": {"coordinates":[-80.314663,25.822471],"type":"Point"}
}