{
  "type": "Feature",
  "properties": {
    "iso:country":"US",
    "sg:address":"2728 Trinidad St",
    "sg:city":"Sarasota",
    "sg:classifiers":[
        {
            "category":"Manufacturing",
            "subcategory":"Retail Goods",
            "type":"Manufacturing & Wholesale Goods"
        }
    ],
    "sg:phone":"+1 941 922 1758",
    "sg:postcode":"34231",
    "sg:province":"FL",
    "sg:tags":[
        "product",
        "mfg"
    ],
    "wof:name":"Srq Industries Inc",
    "wof:placetype":"venue"
},
  "geometry": {"coordinates":[-82.516531,27.288542],"type":"Point"}
}