{
  "type": "Feature",
  "properties": {
    "addr:full":"1512 Vassar St Orlando FL 32804",
    "addr:housenumber":"1512",
    "addr:postcode":"32804",
    "addr:street":"Vassar St",
    "iso:country":"US",
    "sg:address":"1512 Vassar St",
    "sg:city":"Orlando",
    "sg:classifiers":[
        {
            "category":"Home & Garden",
            "subcategory":"Building Materials",
            "type":"Retail Goods"
        }
    ],
    "sg:phone":"+1 407 601 6833",
    "sg:postcode":"32804",
    "sg:province":"FL",
    "sg:tags":[
        "awning",
        "canopy"
    ],
    "wof:name":"Abc Awnings",
    "wof:placetype":"venue"
},
  "geometry": {"coordinates":[-81.40261099999999,28.572769],"type":"Point"}
}