{
  "type": "Feature",
  "properties": {
    "iso:country":"US",
    "sg:address":"105 Tern Trace Ct",
    "sg:city":"Jacksonville",
    "sg:classifiers":[
        {
            "category":"Professional",
            "subcategory":"Business Services",
            "type":"Services"
        }
    ],
    "sg:phone":"+1 904 287 1255",
    "sg:postcode":"32259",
    "sg:province":"FL",
    "sg:website":"www.echohockey.com",
    "wof:name":"East Coast Hockey Organization",
    "wof:placetype":"venue"
},
  "geometry": {"coordinates":[-81.59903799999999,30.112319],"type":"Point"}
}