{
  "type": "Feature",
  "properties": {
    "iso:country":"US",
    "sg:address":"2909 S 25th St",
    "sg:city":"Fort Pierce",
    "sg:classifiers":[
        {
            "category":"Social Services",
            "subcategory":"Adult Care",
            "type":"Services"
        }
    ],
    "sg:phone":"+1 772 466 1919",
    "sg:postcode":"34981",
    "sg:province":"FL",
    "sg:tags":[
        "home",
        "residential"
    ],
    "wof:name":"Lake Forest Park Retirement",
    "wof:placetype":"venue"
},
  "geometry": {"coordinates":[-80.349864,27.41434],"type":"Point"}
}