{
  "type": "Feature",
  "properties": {
    "addr:full":"9685 S Horseshoe Rd Tallahassee FL 32317",
    "addr:housenumber":"9685",
    "addr:postcode":"32317",
    "addr:street":"S Horseshoe Rd",
    "iso:country":"US",
    "sg:address":"9685 S Horseshoe Rd",
    "sg:city":"Tallahassee",
    "sg:classifiers":[
        {
            "category":"Banks & Credit Unions",
            "subcategory":"Financial Services",
            "type":"Services"
        }
    ],
    "sg:phone":"+1 850 878 3725",
    "sg:postcode":"32317",
    "sg:province":"FL",
    "sg:tags":[
        "investor"
    ],
    "wof:name":"Boomerang Investments",
    "wof:placetype":"venue"
},
  "geometry": {"coordinates":[-84.10914099999999,30.446605],"type":"Point"}
}