{
  "type": "Feature",
  "properties": {
    "iso:country":"US",
    "sg:address":"1415 E Sunrise Blvd",
    "sg:city":"Fort Lauderdale",
    "sg:classifiers":[
        {
            "category":"Real Estate",
            "subcategory":"Real Estate Agent",
            "type":"Services"
        }
    ],
    "sg:phone":"+1 954 468 0469",
    "sg:postcode":"33304",
    "sg:province":"FL",
    "sg:tags":[
        "property",
        "management"
    ],
    "wof:name":"Sentinel Real Estate Fund",
    "wof:placetype":"venue"
},
  "geometry": {"coordinates":[-80.128809,26.137274],"type":"Point"}
}