{
  "type": "Feature",
  "properties": {
    "addr:full":"11451 Sugar Maple Pl S Jacksonville FL 32225",
    "addr:housenumber":"11451",
    "addr:postcode":"32225",
    "addr:street":"Sugar Maple Pl",
    "iso:country":"US",
    "sg:address":"11451 Sugar Maple Pl S",
    "sg:city":"Jacksonville",
    "sg:classifiers":[
        {
            "category":"Professional",
            "type":"Services"
        }
    ],
    "sg:phone":"+1 904 564 1686",
    "sg:postcode":"32225",
    "sg:province":"FL",
    "wof:name":"Kenneth Ponton Inc",
    "wof:placetype":"venue"
},
  "geometry": {"coordinates":[-81.51454699999999,30.384302],"type":"Point"}
}