{
  "type": "Feature",
  "properties": {
    "iso:country":"US",
    "sg:address":"701 NE Sanchez Ave",
    "sg:city":"Ocala",
    "sg:classifiers":[
        {
            "category":"Shopping",
            "subcategory":"Gifts & Souvenirs",
            "type":"Retail Goods"
        }
    ],
    "sg:phone":"+1 352 401 3900",
    "sg:postcode":"34470",
    "sg:province":"FL",
    "sg:tags":[
        "shop"
    ],
    "wof:name":"Discover More Store",
    "wof:placetype":"venue"
},
  "geometry": {"coordinates":[-82.131187,29.19389],"type":"Point"}
}