{
  "type": "Feature",
  "properties": {
    "iso:country":"US",
    "sg:address":"2031 SW 70th Ave",
    "sg:city":"Davie",
    "sg:classifiers":[
        {
            "category":"Manufacturing",
            "subcategory":"Wood Products",
            "type":"Manufacturing & Wholesale Goods"
        },
        {
            "category":"Home & Garden",
            "subcategory":"Furniture",
            "type":"Retail Goods"
        }
    ],
    "sg:phone":"+1 954 306 6720",
    "sg:postcode":"33317",
    "sg:province":"FL",
    "sg:tags":[
        "equipment-household",
        "millwork",
        "kitchen",
        "cabinet"
    ],
    "wof:name":"Timberland Millwork Inc",
    "wof:placetype":"venue"
},
  "geometry": {"coordinates":[-80.23786699999999,26.094553],"type":"Point"}
}