{
  "type": "Feature",
  "properties": {
    "addr:full":"746 36th Ave Vero Beach FL 32968",
    "addr:housenumber":"746",
    "addr:postcode":"32968",
    "addr:street":"36Th Ave",
    "iso:country":"US",
    "sg:address":"746 36th Ave",
    "sg:city":"Vero Beach",
    "sg:classifiers":[
        {
            "category":"Professional",
            "subcategory":"Engineering",
            "type":"Services"
        }
    ],
    "sg:phone":"+1 772 778 1286",
    "sg:postcode":"32968",
    "sg:province":"FL",
    "wof:name":"Gene R Ohl",
    "wof:placetype":"venue"
},
  "geometry": {"coordinates":[-80.42323500000001,27.613665],"type":"Point"}
}