{
  "type": "Feature",
  "properties": {
    "iso:country":"US",
    "sg:address":"1970 Lake Worth Rd",
    "sg:city":"Lake Worth",
    "sg:classifiers":[
        {
            "category":"Shopping",
            "type":"Retail Goods"
        }
    ],
    "sg:phone":"+1 561 493 4713",
    "sg:postcode":"33461",
    "sg:province":"FL",
    "sg:tags":[
        "cosmetic",
        "perfume"
    ],
    "wof:name":"Young World II",
    "wof:placetype":"venue"
},
  "geometry": {"coordinates":[-80.072373,26.616944],"type":"Point"}
}