{
  "type": "Feature",
  "properties": {
    "iso:country":"US",
    "sg:address":"2043 SE Federal Hwy",
    "sg:city":"Fort Pierce",
    "sg:classifiers":[
        {
            "category":"Building & Trades",
            "subcategory":"Equipment Rental",
            "type":"Services"
        }
    ],
    "sg:phone":"+1 772 461 0600",
    "sg:postcode":"34994",
    "sg:province":"FL",
    "sg:tags":[
        "rent",
        "furniture"
    ],
    "wof:name":"Aaarons",
    "wof:placetype":"venue"
},
  "geometry": {"coordinates":[-80.239295,27.180554],"type":"Point"}
}