{
  "type": "Feature",
  "properties": {
    "addr:full":"725 4th St Vero Beach FL 32962",
    "addr:housenumber":"725",
    "addr:postcode":"32962",
    "addr:street":"4Th St",
    "iso:country":"US",
    "sg:address":"725 4th St",
    "sg:city":"Vero Beach",
    "sg:classifiers":[
        {
            "category":"Building & Trades",
            "subcategory":"Construction",
            "type":"Services"
        }
    ],
    "sg:phone":"+1 772 569 1847",
    "sg:postcode":"32962",
    "sg:province":"FL",
    "sg:tags":[
        "painter"
    ],
    "wof:name":"Charles E Cappelen Painting",
    "wof:placetype":"venue"
},
  "geometry": {"coordinates":[-80.384925,27.608819],"type":"Point"}
}