{
  "type": "Feature",
  "properties": {
    "iso:country":"US",
    "sg:address":"4620 Seminole Ave SW",
    "sg:city":"Labelle",
    "sg:classifiers":[
        {
            "category":"Building & Trades",
            "subcategory":"Construction",
            "type":"Services"
        }
    ],
    "sg:phone":"+1 863 675 2801",
    "sg:postcode":"33935",
    "sg:province":"FL",
    "sg:tags":[
        "water",
        "well",
        "drilling"
    ],
    "wof:name":"Wendell's Pump & Sprinklers",
    "wof:placetype":"venue"
},
  "geometry": {"coordinates":[-81.474823,26.776262],"type":"Point"}
}