{
  "type": "Feature",
  "properties": {
    "iso:country":"US",
    "sg:address":"11323 Marjory Ave",
    "sg:city":"Tampa",
    "sg:classifiers":[
        {
            "category":"Manufacturing",
            "subcategory":"Building Materials",
            "type":"Manufacturing & Wholesale Goods"
        }
    ],
    "sg:phone":"+1 813 376 1468",
    "sg:postcode":"33612",
    "sg:province":"FL",
    "sg:tags":[
        "mfg",
        "wood",
        "kitchen",
        "cabinet"
    ],
    "wof:name":"Ernesto Ozzy Cabinet Inc",
    "wof:placetype":"venue"
},
  "geometry": {"coordinates":[-82.46556099999999,28.05284],"type":"Point"}
}