{
  "type": "Feature",
  "properties": {
    "iso:country":"US",
    "sg:address":"14321 SW 38th Ter",
    "sg:city":"Miami",
    "sg:classifiers":[
        {
            "category":"Health Services",
            "subcategory":"Health Practitioner",
            "type":"Services"
        }
    ],
    "sg:phone":"+1 305 551 7139",
    "sg:postcode":"33175",
    "sg:province":"FL",
    "sg:tags":[
        "hypnotist"
    ],
    "wof:name":"Luis R Serrano Hypnotherapy",
    "wof:placetype":"venue"
},
  "geometry": {"coordinates":[-80.426025,25.731665],"type":"Point"}
}