{
  "type": "Feature",
  "properties": {
    "addr:full":"18667 SW 107th Ave Miami FL 33157",
    "addr:housenumber":"18667",
    "addr:postcode":"33157",
    "addr:street":"Sw 107Th Ave",
    "iso:country":"US",
    "sg:address":"18667 SW 107th Ave",
    "sg:city":"Miami",
    "sg:classifiers":[
        {
            "category":"Food & Beverages",
            "subcategory":"Bakery",
            "type":"Retail Goods"
        }
    ],
    "sg:phone":"+1 305 253 8943",
    "sg:postcode":"33157",
    "sg:province":"FL",
    "sg:tags":[
        "baker"
    ],
    "wof:name":"Jamican Bakery & Wholesale",
    "wof:placetype":"venue"
},
  "geometry": {"coordinates":[-80.36425199999999,25.593353],"type":"Point"}
}