{
  "type": "Feature",
  "properties": {
    "iso:country":"US",
    "sg:address":"254 W State Road 436",
    "sg:city":"Altamonte Springs",
    "sg:classifiers":[
        {
            "category":"Banks & Credit Unions",
            "subcategory":"Bank",
            "type":"Services"
        }
    ],
    "sg:phone":"+1 407 869 6607",
    "sg:postcode":"32714",
    "sg:province":"FL",
    "wof:name":"Southern Community Bank of Central Florida",
    "wof:placetype":"venue"
},
  "geometry": {"coordinates":[-81.394302,28.6619],"type":"Point"}
}