{
  "type": "Feature",
  "properties": {
    "addr:full":"578 Wilmer Ave Orlando FL 32808",
    "addr:housenumber":"578",
    "addr:postcode":"32808",
    "addr:street":"Wilmer Ave",
    "iso:country":"US",
    "sg:address":"578 Wilmer Ave",
    "sg:city":"Orlando",
    "sg:classifiers":[
        {
            "category":"Shopping",
            "type":"Retail Goods"
        }
    ],
    "sg:phone":"+1 407 521 9596",
    "sg:postcode":"32808",
    "sg:province":"FL",
    "sg:tags":[
        "cosmetic",
        "perfume"
    ],
    "wof:name":"City Nail & Beauty Supply",
    "wof:placetype":"venue"
},
  "geometry": {"coordinates":[-81.448898,28.550985],"type":"Point"}
}