{
  "type": "Feature",
  "properties": {
    "iso:country":"US",
    "sg:address":"4327 Enterprise Ave",
    "sg:city":"Naples",
    "sg:classifiers":[
        {
            "category":"Building & Trades",
            "subcategory":"Pest Control",
            "type":"Services"
        }
    ],
    "sg:phone":"+1 239 643 0368",
    "sg:postcode":"34104",
    "sg:province":"FL",
    "wof:name":"Barker Spray Services",
    "wof:placetype":"venue"
},
  "geometry": {"coordinates":[-81.75537199999999,26.160821],"type":"Point"}
}