{
  "type": "Feature",
  "properties": {
    "iso:country":"US",
    "sg:address":"3919 Vistula Dr",
    "sg:city":"Chipley",
    "sg:classifiers":[
        {
            "category":"Organizations",
            "subcategory":"Religious Organization",
            "type":"Services"
        }
    ],
    "sg:phone":"+1 850 773 3302",
    "sg:postcode":"32428",
    "sg:province":"FL",
    "wof:name":"Vestiarki Sisters of Jesus",
    "wof:placetype":"venue"
},
  "geometry": {"coordinates":[-85.621736,30.542472],"type":"Point"}
}