{
  "type": "Feature",
  "properties": {
    "iso:country":"US",
    "sg:address":"2708 E Fowler Ave",
    "sg:city":"Tampa",
    "sg:classifiers":[
        {
            "category":"Professional",
            "subcategory":"Accounting & Tax Preparation",
            "type":"Services"
        }
    ],
    "sg:phone":"+1 813 972 8135",
    "sg:postcode":"33612",
    "sg:province":"FL",
    "sg:tags":[
        "return",
        "preparation-business"
    ],
    "sg:website":"http://www.hrblock.com",
    "wof:name":"H&R Block Eastern Enterprises Inc",
    "wof:placetype":"venue"
},
  "geometry": {"coordinates":[-82.428687,28.054557],"type":"Point"}
}