{
  "type": "Feature",
  "properties": {
    "iso:country":"US",
    "sg:address":"4532 SE 14th Pl",
    "sg:city":"Cape Coral",
    "sg:classifiers":[
        {
            "category":"Professional",
            "type":"Services"
        }
    ],
    "sg:phone":"+1 239 549 4679",
    "sg:postcode":"33904",
    "sg:province":"FL",
    "sg:tags":[
        "establishment"
    ],
    "wof:name":"Amerigroup Florida Inc",
    "wof:placetype":"venue"
},
  "geometry": {"coordinates":[-81.94631699999999,26.56936],"type":"Point"}
}