{
  "type": "Feature",
  "properties": {
    "addr:full":"3419 SW 8th St Miami FL 33135",
    "addr:housenumber":"3419",
    "addr:postcode":"33135",
    "addr:street":"Sw 8Th St",
    "iso:country":"US",
    "sg:address":"3419 SW 8th St",
    "sg:city":"Miami",
    "sg:classifiers":[
        {
            "category":"Shopping",
            "subcategory":"Jewelry",
            "type":"Retail Goods"
        }
    ],
    "sg:phone":"+1 305 648 3808",
    "sg:postcode":"33135",
    "sg:province":"FL",
    "wof:name":"Joyeria El Sol De Miami",
    "wof:placetype":"venue"
},
  "geometry": {"coordinates":[-80.25122399999999,25.764933],"type":"Point"}
}