{
  "type": "Feature",
  "properties": {
    "iso:country":"US",
    "sg:address":"711 N Grandview Ave",
    "sg:city":"Daytona Beach",
    "sg:classifiers":[
        {
            "category":"Shopping",
            "subcategory":"Discount & Variety Stores",
            "type":"Retail Goods"
        }
    ],
    "sg:phone":"+1 386 235 4991",
    "sg:postcode":"32118",
    "sg:province":"FL",
    "sg:tags":[
        "merchandise",
        "general"
    ],
    "wof:name":"Addison D Lebedz Retail",
    "wof:placetype":"venue"
},
  "geometry": {"coordinates":[-81.015069,29.238341],"type":"Point"}
}