{
  "type": "Feature",
  "properties": {
    "addr:full":"12116 Cortez Blvd Brooksville FL 34613",
    "addr:housenumber":"12116",
    "addr:postcode":"34613",
    "addr:street":"Cortez Blvd",
    "iso:country":"US",
    "sg:address":"12116 Cortez Blvd",
    "sg:city":"Brooksville",
    "sg:classifiers":[
        {
            "category":"Shopping",
            "subcategory":"Department Store",
            "type":"Retail Goods"
        }
    ],
    "sg:phone":"+1 352 596 1750",
    "sg:postcode":"34613",
    "sg:province":"FL",
    "sg:tags":[
        "shop"
    ],
    "wof:name":"Discount Canadian Meds Direct",
    "wof:placetype":"venue"
},
  "geometry": {"coordinates":[-82.52126699999999,28.533652],"type":"Point"}
}