{
  "type": "Feature",
  "properties": {
    "iso:country":"US",
    "sg:address":"680 Camp Rd",
    "sg:city":"Cocoa",
    "sg:classifiers":[
        {
            "category":"Freight",
            "type":"Transportation"
        }
    ],
    "sg:phone":"+1 321 633 6343",
    "sg:postcode":"32927",
    "sg:province":"FL",
    "sg:tags":[
        "operator",
        "local",
        "trucking"
    ],
    "wof:name":"Lawrence Trucking",
    "wof:placetype":"venue"
},
  "geometry": {"coordinates":[-80.778347,28.446799],"type":"Point"}
}