{
  "type": "Feature",
  "properties": {
    "addr:full":"8141 Field Harvest Ct Jacksonville FL 32244",
    "addr:housenumber":"8141",
    "addr:postcode":"32244",
    "addr:street":"Field Harvest Ct",
    "iso:country":"US",
    "sg:address":"8141 Field Harvest Ct",
    "sg:city":"Jacksonville",
    "sg:classifiers":[
        {
            "category":"Shopping",
            "subcategory":"Gifts & Souvenirs",
            "type":"Retail Goods"
        }
    ],
    "sg:phone":"+1 904 573 6763",
    "sg:postcode":"32244",
    "sg:province":"FL",
    "wof:name":"Collandra & Collandra Trading",
    "wof:placetype":"venue"
},
  "geometry": {"coordinates":[-81.800057,30.197958],"type":"Point"}
}