{
  "type": "Feature",
  "properties": {
    "iso:country":"US",
    "sg:address":"4465 Fanny Bass Ln",
    "sg:city":"St Cloud",
    "sg:classifiers":[
        {
            "category":"Building & Trades",
            "subcategory":"Construction",
            "type":"Services"
        }
    ],
    "sg:phone":"+1 407 908 0746",
    "sg:postcode":"34772",
    "sg:province":"FL",
    "sg:tags":[
        "carpenter"
    ],
    "wof:name":"KSI Inc",
    "wof:placetype":"venue"
},
  "geometry": {"coordinates":[-81.27591,28.15355],"type":"Point"}
}