{
  "type": "Feature",
  "properties": {
    "iso:country":"US",
    "sg:address":"13176 Cooper Rd",
    "sg:city":"Spring Hill",
    "sg:classifiers":[
        {
            "category":"Building & Trades",
            "subcategory":"Plumbing",
            "type":"Services"
        }
    ],
    "sg:phone":"+1 352 686 3289",
    "sg:postcode":"34609",
    "sg:province":"FL",
    "sg:tags":[
        "plumbing",
        "contractor"
    ],
    "wof:name":"Rustys Plumbing Services Inc",
    "wof:placetype":"venue"
},
  "geometry": {"coordinates":[-82.51264399999999,28.455635],"type":"Point"}
}