{
  "type": "Feature",
  "properties": {
    "addr:full":"19501 Biscayne Blvd Miami FL 33180",
    "addr:housenumber":"19501",
    "addr:postcode":"33180",
    "addr:street":"Biscayne Blvd",
    "iso:country":"US",
    "sg:address":"19501 Biscayne Blvd",
    "sg:city":"Miami",
    "sg:classifiers":[
        {
            "category":"Restaurant",
            "type":"Food & Drink"
        }
    ],
    "sg:menulink":"http://www.allmenus.com/fl/miami/95792-charleys-grilled-subs/menu/",
    "sg:phone":"+1 305 428 3923",
    "sg:postcode":"33180",
    "sg:province":"FL",
    "sg:tags":[
        "wrap",
        "american",
        "sandwich"
    ],
    "wof:name":"Charley's Grilled Subs",
    "wof:placetype":"venue"
},
  "geometry": {"coordinates":[-80.146787,25.956979],"type":"Point"}
}