{
  "type": "Feature",
  "properties": {
    "iso:country":"US",
    "sg:address":"3522 53rd Ave W",
    "sg:city":"Bradenton",
    "sg:classifiers":[
        {
            "category":"Restaurant",
            "type":"Food & Drink"
        }
    ],
    "sg:phone":"+1 941 714 0600",
    "sg:postcode":"34210",
    "sg:province":"FL",
    "sg:tags":[
        "eating"
    ],
    "wof:name":"Cowdog Pizza",
    "wof:placetype":"venue"
},
  "geometry": {"coordinates":[-82.59935900000001,27.447621],"type":"Point"}
}