{
  "type": "Feature",
  "properties": {
    "iso:country":"US",
    "sg:address":"6777 NW 7th Ave Ste 2",
    "sg:city":"Miami",
    "sg:classifiers":[
        {
            "category":"Health Services",
            "subcategory":"Doctor",
            "type":"Services"
        }
    ],
    "sg:phone":"+1 305 754 9823",
    "sg:postcode":"33150",
    "sg:province":"FL",
    "sg:tags":[
        "physician",
        "reproductive",
        "endocrinology",
        "surgeons",
        "surgeon",
        "metabolism",
        "diabetes"
    ],
    "wof:name":"Carrington Selwyn MD",
    "wof:placetype":"venue"
},
  "geometry": {"coordinates":[-80.208702,25.8368],"type":"Point"}
}