{
  "type": "Feature",
  "properties": {
    "addr:full":"3691 NW 20th St Miami FL 33142",
    "addr:housenumber":"3691",
    "addr:postcode":"33142",
    "addr:street":"Nw 20Th St",
    "iso:country":"US",
    "sg:address":"3691 NW 20th St",
    "sg:city":"Miami",
    "sg:classifiers":[
        {
            "category":"Professional",
            "subcategory":"Business Services",
            "type":"Services"
        }
    ],
    "sg:phone":"+1 305 636 2846",
    "sg:postcode":"33142",
    "sg:province":"FL",
    "sg:tags":[
        "fund",
        "promotion",
        "raising"
    ],
    "wof:name":"Caribbean Nautical Promotions",
    "wof:placetype":"venue"
},
  "geometry": {"coordinates":[-80.255872,25.793933],"type":"Point"}
}