{
  "type": "Feature",
  "properties": {
    "addr:full":"917 Warbler Ct Daytona Beach FL 32127",
    "addr:housenumber":"917",
    "addr:postcode":"32127",
    "addr:street":"Warbler Ct",
    "iso:country":"US",
    "sg:address":"917 Warbler Ct",
    "sg:city":"Daytona Beach",
    "sg:classifiers":[
        {
            "category":"Professional",
            "subcategory":"Business Services",
            "type":"Services"
        }
    ],
    "sg:phone":"+1 386 788 7317",
    "sg:postcode":"32127",
    "sg:province":"FL",
    "wof:name":"Orlando Fitness & Raquet Club",
    "wof:placetype":"venue"
},
  "geometry": {"coordinates":[-81.010792,29.114575],"type":"Point"}
}