{
  "type": "Feature",
  "properties": {
    "addr:full":"12530 Indian Rocks Rd Largo FL 33774",
    "addr:housenumber":"12530",
    "addr:postcode":"33774",
    "addr:street":"Indian Rocks Rd",
    "iso:country":"US",
    "sg:address":"12530 Indian Rocks Rd",
    "sg:city":"Largo",
    "sg:classifiers":[
        {
            "category":"Personal",
            "subcategory":"Barber",
            "type":"Services"
        }
    ],
    "sg:phone":"+1 727 596 3533",
    "sg:postcode":"33774",
    "sg:province":"FL",
    "sg:tags":[
        "shop",
        "salon",
        "beauty"
    ],
    "wof:name":"Vidal Hair Design",
    "wof:placetype":"venue"
},
  "geometry": {"coordinates":[-82.83242300000001,27.887136],"type":"Point"}
}