{
  "type": "Feature",
  "properties": {
    "iso:country":"US",
    "sg:address":"2430 E Commercial Blvd",
    "sg:city":"Fort Lauderdale",
    "sg:classifiers":[
        {
            "category":"Banks & Credit Unions",
            "subcategory":"Bank",
            "type":"Services"
        }
    ],
    "sg:phone":"+1 954 771 2712",
    "sg:postcode":"33308",
    "sg:province":"FL",
    "sg:tags":[
        "loan"
    ],
    "wof:name":"Construction Lending Group",
    "wof:placetype":"venue"
},
  "geometry": {"coordinates":[-80.111752,26.189523],"type":"Point"}
}