{
  "type": "Feature",
  "properties": {
    "addr:full":"2380 SW 28th St Miami FL 33133",
    "addr:housenumber":"2380",
    "addr:postcode":"33133",
    "addr:street":"Sw 28Th St",
    "iso:country":"US",
    "sg:address":"2380 SW 28th St",
    "sg:city":"Miami",
    "sg:classifiers":[
        {
            "category":"Shopping",
            "subcategory":"Optical Goods",
            "type":"Retail Goods"
        }
    ],
    "sg:phone":"+1 305 285 2414",
    "sg:postcode":"33133",
    "sg:province":"FL",
    "wof:name":"Grove Optical LLC",
    "wof:placetype":"venue"
},
  "geometry": {"coordinates":[-80.232697,25.739337],"type":"Point"}
}