{
  "type": "Feature",
  "properties": {
    "iso:country":"US",
    "sg:address":"7534 Lake Worth Rd",
    "sg:city":"Wellington",
    "sg:classifiers":[
        {
            "category":"Shopping",
            "subcategory":"Pharmacy",
            "type":"Retail Goods"
        }
    ],
    "sg:phone":"+1 561 964 1363",
    "sg:postcode":"33467",
    "sg:province":"FL",
    "wof:name":"Eckerd",
    "wof:placetype":"venue"
},
  "geometry": {"coordinates":[-80.16973400000001,26.617363],"type":"Point"}
}