{
  "type": "Feature",
  "properties": {
    "addr:full":"1380 5th Ave N Naples FL 34102",
    "addr:housenumber":"1380",
    "addr:postcode":"34102",
    "addr:street":"5Th Ave N",
    "iso:country":"US",
    "sg:address":"1380 5th Ave N",
    "sg:city":"Naples",
    "sg:classifiers":[
        {
            "category":"Organizations",
            "subcategory":"Religious Organization",
            "type":"Services"
        }
    ],
    "sg:phone":"+1 239 263 6860",
    "sg:postcode":"34102",
    "sg:province":"FL",
    "sg:tags":[
        "church"
    ],
    "wof:name":"Triumph The Church & Kingdom",
    "wof:placetype":"venue"
},
  "geometry": {"coordinates":[-81.788906,26.153517],"type":"Point"}
}