{
  "type": "Feature",
  "properties": {
    "iso:country":"US",
    "sg:address":"11868 N Williams St",
    "sg:city":"Dunnellon",
    "sg:classifiers":[
        {
            "category":"Autos & Motor Vehicles",
            "subcategory":"Auto Supplies",
            "type":"Retail Goods"
        }
    ],
    "sg:phone":"+1 352 489 2277",
    "sg:postcode":"34432",
    "sg:province":"FL",
    "sg:tags":[
        "automobile",
        "used"
    ],
    "wof:name":"J & R Auto Sales",
    "wof:placetype":"venue"
},
  "geometry": {"coordinates":[-82.459706,29.051325],"type":"Point"}
}