{
  "type": "Feature",
  "properties": {
    "addr:full":"3811 Watercrest Dr Longwood FL 32779",
    "addr:housenumber":"3811",
    "addr:postcode":"32779",
    "addr:street":"Watercrest Dr",
    "iso:country":"US",
    "sg:address":"3811 Watercrest Dr",
    "sg:city":"Longwood",
    "sg:classifiers":[
        {
            "category":"Professional",
            "subcategory":"Business Services",
            "type":"Services"
        }
    ],
    "sg:phone":"+1 407 862 7212",
    "sg:postcode":"32779",
    "sg:province":"FL",
    "sg:tags":[
        "convention",
        "meeting",
        "facility"
    ],
    "wof:name":"All About Events",
    "wof:placetype":"venue"
},
  "geometry": {"coordinates":[-81.441833,28.712073],"type":"Point"}
}