{
  "type": "Feature",
  "properties": {
    "addr:full":"251 Tamiami Trl Venice FL 34285",
    "addr:housenumber":"251",
    "addr:postcode":"34285",
    "addr:street":"Tamiami Trl",
    "iso:country":"US",
    "sg:address":"251 Tamiami Trl",
    "sg:city":"Venice",
    "sg:classifiers":[
        {
            "category":"Social Services",
            "type":"Services"
        }
    ],
    "sg:phone":"+1 941 408 8992",
    "sg:postcode":"34285",
    "sg:province":"FL",
    "sg:tags":[
        "counselor",
        "marriage",
        "family"
    ],
    "wof:name":"Foundation Of Faith Family",
    "wof:placetype":"venue"
},
  "geometry": {"coordinates":[-82.44423,27.097033],"type":"Point"}
}