{
  "type": "Feature",
  "properties": {
    "iso:country":"US",
    "sg:address":"8010 Anderson Rd",
    "sg:city":"Tampa",
    "sg:classifiers":[
        {
            "category":"Manufacturing",
            "subcategory":"Printing",
            "type":"Manufacturing & Wholesale Goods"
        }
    ],
    "sg:phone":"+1 813 888 6811",
    "sg:postcode":"33634",
    "sg:province":"FL",
    "sg:tags":[
        "printer",
        "offset"
    ],
    "sg:website":"www.quicksilverprinting.com",
    "wof:name":"Quicksilver Printing & Copying",
    "wof:placetype":"venue"
},
  "geometry": {"coordinates":[-82.534053,28.017074],"type":"Point"}
}