{
  "type": "Feature",
  "properties": {
    "iso:country":"US",
    "sg:address":"4626 Moncrief Village E",
    "sg:city":"Jacksonville",
    "sg:classifiers":[
        {
            "category":"Personal",
            "subcategory":"Beauty Salon",
            "type":"Services"
        }
    ],
    "sg:phone":"+1 904 764 9234",
    "sg:postcode":"32209",
    "sg:province":"FL",
    "wof:name":"Johnny's Hair Cutting",
    "wof:placetype":"venue"
},
  "geometry": {"coordinates":[-81.684319,30.366984],"type":"Point"}
}