{
  "type": "Feature",
  "properties": {
    "addr:full":"1006 Ariana St Lakeland FL 33803",
    "addr:housenumber":"1006",
    "addr:postcode":"33803",
    "addr:street":"Ariana St",
    "iso:country":"US",
    "sg:address":"1006 Ariana St",
    "sg:city":"Lakeland",
    "sg:classifiers":[
        {
            "category":"Organizations",
            "subcategory":"Religious Organization",
            "type":"Services"
        }
    ],
    "sg:phone":"+1 863 683 3161",
    "sg:postcode":"33803",
    "sg:province":"FL",
    "sg:tags":[
        "church"
    ],
    "wof:name":"Luz De Salvacion",
    "wof:placetype":"venue"
},
  "geometry": {"coordinates":[-81.97007000000001,28.025881],"type":"Point"}
}