{
  "type": "Feature",
  "properties": {
    "addr:full":"9444 2nd Ave Orlando FL 32824",
    "addr:housenumber":"9444",
    "addr:postcode":"32824",
    "addr:street":"2Nd Ave",
    "iso:country":"US",
    "sg:address":"9444 2nd Ave",
    "sg:city":"Orlando",
    "sg:classifiers":[
        {
            "category":"Home & Garden",
            "subcategory":"Household Appliances",
            "type":"Retail Goods"
        }
    ],
    "sg:phone":"+1 407 855 2075",
    "sg:postcode":"32824",
    "sg:province":"FL",
    "sg:tags":[
        "appliances-major-used"
    ],
    "wof:name":"Beck's Appliances",
    "wof:placetype":"venue"
},
  "geometry": {"coordinates":[-81.36743199999999,28.42968],"type":"Point"}
}