{
  "type": "Feature",
  "properties": {
    "addr:full":"138 W Granada Blvd Ormond Beach FL 32174",
    "addr:housenumber":"138",
    "addr:postcode":"32174",
    "addr:street":"W Granada Blvd",
    "iso:country":"US",
    "sg:address":"138 W Granada Blvd",
    "sg:city":"Ormond Beach",
    "sg:classifiers":[
        {
            "category":"Food & Beverages",
            "subcategory":"Bakery",
            "type":"Retail Goods"
        }
    ],
    "sg:phone":"+1 386 673 8317",
    "sg:postcode":"32174",
    "sg:province":"FL",
    "sg:tags":[
        "product",
        "mfg"
    ],
    "wof:name":"Dunkin Donuts",
    "wof:placetype":"venue"
},
  "geometry": {"coordinates":[-81.05967099999999,29.283985],"type":"Point"}
}