{
  "type": "Feature",
  "properties": {
    "iso:country":"US",
    "sg:address":"5719 N University Dr",
    "sg:city":"Tamarac",
    "sg:classifiers":[
        {
            "category":"Food & Beverages",
            "subcategory":"Specialty",
            "type":"Retail Goods"
        }
    ],
    "sg:phone":"+1 954 726 2500",
    "sg:postcode":"33321",
    "sg:province":"FL",
    "sg:tags":[
        "vitamin"
    ],
    "wof:name":"Simply Natural Of Tamarac",
    "wof:placetype":"venue"
},
  "geometry": {"coordinates":[-80.252134,26.196722],"type":"Point"}
}