{
  "type": "Feature",
  "properties": {
    "iso:country":"US",
    "sg:address":"5901 Boggs Ford Rd",
    "sg:city":"Daytona Beach",
    "sg:classifiers":[
        {
            "category":"Restaurant",
            "type":"Food & Drink"
        }
    ],
    "sg:phone":"+1 386 322 5288",
    "sg:postcode":"32127",
    "sg:province":"FL",
    "sg:tags":[
        "eating"
    ],
    "wof:name":"His & Her Catering",
    "wof:placetype":"venue"
},
  "geometry": {"coordinates":[-81.022266,29.098385],"type":"Point"}
}