{
  "type": "Feature",
  "properties": {
    "addr:full":"1100 Southern Blvd West Palm Beach FL 33405",
    "addr:housenumber":"1100",
    "addr:postcode":"33405",
    "addr:street":"Southern Blvd",
    "iso:country":"US",
    "sg:address":"1100 Southern Blvd",
    "sg:city":"West Palm Beach",
    "sg:classifiers":[
        {
            "category":"Travel",
            "subcategory":"Campground",
            "type":"Entertainment"
        }
    ],
    "sg:phone":"+1 561 835 7025",
    "sg:postcode":"33405",
    "sg:province":"FL",
    "sg:tags":[
        "camp"
    ],
    "wof:name":"City W Palm Parks & Recreation",
    "wof:placetype":"venue"
},
  "geometry": {"coordinates":[-80.063627,26.675871],"type":"Point"}
}