{
  "type": "Feature",
  "properties": {
    "iso:country":"US",
    "sg:address":"1971 54th Ave N",
    "sg:city":"St Petersburg",
    "sg:classifiers":[
        {
            "category":"Building & Trades",
            "subcategory":"Plumbing",
            "type":"Services"
        }
    ],
    "sg:phone":"+1 727 521 2323",
    "sg:postcode":"33714",
    "sg:province":"FL",
    "sg:tags":[
        "product",
        "management",
        "energy",
        "system"
    ],
    "wof:name":"Florida Energy AC Inc",
    "wof:placetype":"venue"
},
  "geometry": {"coordinates":[-82.65973200000001,27.821234],"type":"Point"}
}