{
  "type": "Feature",
  "properties": {
    "addr:full":"770 Gulf Shore Dr Destin FL 32541",
    "addr:housenumber":"770",
    "addr:postcode":"32541",
    "addr:street":"Gulf Shore Dr",
    "iso:country":"US",
    "sg:address":"770 Gulf Shore Dr",
    "sg:city":"Destin",
    "sg:classifiers":[
        {
            "category":"Professional",
            "subcategory":"Business Services",
            "type":"Services"
        }
    ],
    "sg:phone":"+1 850 654 1230",
    "sg:postcode":"32541",
    "sg:province":"FL",
    "sg:tags":[
        "association"
    ],
    "wof:name":"Holiday Isle Towers Homeowners",
    "wof:placetype":"venue"
},
  "geometry": {"coordinates":[-86.483087,30.384726],"type":"Point"}
}