{
  "type": "Feature",
  "properties": {
    "addr:full":"3121 Jim Lee Rd Tallahassee FL 32301",
    "addr:housenumber":"3121",
    "addr:postcode":"32301",
    "addr:street":"Jim Lee Rd",
    "iso:country":"US",
    "sg:address":"3121 Jim Lee Rd",
    "sg:city":"Tallahassee",
    "sg:classifiers":[
        {
            "category":"Organizations",
            "subcategory":"Religious Organization",
            "type":"Services"
        }
    ],
    "sg:phone":"+1 850 878 7780",
    "sg:postcode":"32301",
    "sg:province":"FL",
    "sg:tags":[
        "church"
    ],
    "wof:name":"Seventh-Day Adventist Church",
    "wof:placetype":"venue"
},
  "geometry": {"coordinates":[-84.26392800000001,30.41254],"type":"Point"}
}