{
  "type": "Feature",
  "properties": {
    "iso:country":"US",
    "sg:address":"9281 87th Pl S",
    "sg:city":"Boynton Beach",
    "sg:classifiers":[
        {
            "category":"Wholesale",
            "subcategory":"Plants",
            "type":"Manufacturing & Wholesale Goods"
        }
    ],
    "sg:phone":"+1 561 737 1490",
    "sg:postcode":"33472",
    "sg:province":"FL",
    "sg:tags":[
        "nursery",
        "tree",
        "flower",
        "stock"
    ],
    "wof:name":"Boynton Botanicals LLC",
    "wof:placetype":"venue"
},
  "geometry": {"coordinates":[-80.195178,26.546424],"type":"Point"}
}