{
  "type": "Feature",
  "properties": {
    "iso:country":"US",
    "sg:address":"9019 Long Lake Ave",
    "sg:city":"Brooksville",
    "sg:classifiers":[
        {
            "category":"Building & Trades",
            "subcategory":"Construction",
            "type":"Services"
        }
    ],
    "sg:phone":"+1 352 279 6887",
    "sg:postcode":"34613",
    "sg:province":"FL",
    "sg:tags":[
        "residential",
        "contractor"
    ],
    "wof:name":"Choice Builders Corporation",
    "wof:placetype":"venue"
},
  "geometry": {"coordinates":[-82.575727,28.548223],"type":"Point"}
}