{
  "type": "Feature",
  "properties": {
    "addr:full":"1325 S Killian Dr West Palm Beach FL 33403",
    "addr:housenumber":"1325",
    "addr:postcode":"33403",
    "addr:street":"S Killian Dr",
    "iso:country":"US",
    "sg:address":"1325 S Killian Dr",
    "sg:city":"West Palm Beach",
    "sg:classifiers":[
        {
            "category":"Autos & Motor Vehicles",
            "subcategory":"Automobile Sales",
            "type":"Retail Goods"
        }
    ],
    "sg:phone":"+1 561 844 3351",
    "sg:postcode":"33403",
    "sg:province":"FL",
    "sg:tags":[
        "used"
    ],
    "wof:name":"GTS Motorcars Inc",
    "wof:placetype":"venue"
},
  "geometry": {"coordinates":[-80.08198,26.804496],"type":"Point"}
}