{
  "type": "Feature",
  "properties": {
    "addr:full":"908 Garden Gate Cir Pensacola FL 32504",
    "addr:housenumber":"908",
    "addr:postcode":"32504",
    "addr:street":"Garden Gate Cir",
    "iso:country":"US",
    "sg:address":"908 Garden Gate Cir",
    "sg:city":"Pensacola",
    "sg:classifiers":[
        {
            "category":"Health Services",
            "subcategory":"Doctor",
            "type":"Services"
        }
    ],
    "sg:phone":"+1 850 476 0003",
    "sg:postcode":"32504",
    "sg:province":"FL",
    "sg:tags":[
        "physician",
        "surgeon"
    ],
    "wof:name":"Wilson Family Medical Ctr",
    "wof:placetype":"venue"
},
  "geometry": {"coordinates":[-87.219905,30.481465],"type":"Point"}
}