{
  "type": "Feature",
  "properties": {
    "iso:country":"US",
    "sg:address":"4370 112th Ter N",
    "sg:city":"Clearwater",
    "sg:classifiers":[
        {
            "category":"Wholesale",
            "subcategory":"Home Furnishings",
            "type":"Manufacturing & Wholesale Goods"
        }
    ],
    "sg:phone":"+1 727 573 7676",
    "sg:postcode":"33762",
    "sg:province":"FL",
    "sg:tags":[
        "pressure",
        "plastics-vacuum",
        "thermoforming"
    ],
    "sg:website":"http://www.tse-ok.com",
    "wof:name":"Tse-Okulen Americas",
    "wof:placetype":"venue"
},
  "geometry": {"coordinates":[-82.69257899999999,27.874306],"type":"Point"}
}