{
  "type": "Feature",
  "properties": {
    "addr:full":"1809 E Colonial Dr Orlando FL 32803",
    "addr:housenumber":"1809",
    "addr:postcode":"32803",
    "addr:street":"E Colonial Dr",
    "iso:country":"US",
    "sg:address":"1809 E Colonial Dr",
    "sg:city":"Orlando",
    "sg:classifiers":[
        {
            "category":"Shopping",
            "subcategory":"Photographic Equipment",
            "type":"Retail Goods"
        }
    ],
    "sg:phone":"+1 407 896 2050",
    "sg:postcode":"32803",
    "sg:province":"FL",
    "sg:tags":[
        "portrait",
        "supply",
        "studio",
        "photo"
    ],
    "wof:name":"Fotographic Services",
    "wof:placetype":"venue"
},
  "geometry": {"coordinates":[-81.35730700000001,28.553214],"type":"Point"}
}