{
  "type": "Feature",
  "properties": {
    "iso:country":"US",
    "sg:address":"5315 SW 81 Ter",
    "sg:city":"Gainesville",
    "sg:classifiers":[
        {
            "category":"Building & Trades",
            "subcategory":"Pest Control",
            "type":"Services"
        }
    ],
    "sg:phone":"+1 352 372 3922",
    "sg:postcode":"32608",
    "sg:province":"FL",
    "sg:tags":[
        "trapper",
        "animal"
    ],
    "wof:name":"Critter Control",
    "wof:placetype":"venue"
},
  "geometry": {"coordinates":[-82.429214,29.622035],"type":"Point"}
}