{
  "type": "Feature",
  "properties": {
    "iso:country":"US",
    "sg:address":"1371 E Vine St",
    "sg:city":"Kissimmee",
    "sg:classifiers":[
        {
            "category":"Personal",
            "subcategory":"Beauty Salon",
            "type":"Services"
        }
    ],
    "sg:phone":"+1 407 933 2277",
    "sg:postcode":"34744",
    "sg:province":"FL",
    "sg:tags":[
        "shop"
    ],
    "wof:name":"E-Nails",
    "wof:placetype":"venue"
},
  "geometry": {"coordinates":[-81.38882099999999,28.304282],"type":"Point"}
}