{
  "type": "Feature",
  "properties": {
    "iso:country":"US",
    "sg:address":"1281 Tallevast Rd",
    "sg:city":"Sarasota",
    "sg:classifiers":[
        {
            "category":"Wholesale",
            "subcategory":"Apparel",
            "type":"Manufacturing & Wholesale Goods"
        }
    ],
    "sg:phone":"+1 941 355 0611",
    "sg:postcode":"34243",
    "sg:province":"FL",
    "sg:tags":[
        "clothing"
    ],
    "wof:name":"Natural Discoveries Sales",
    "wof:placetype":"venue"
},
  "geometry": {"coordinates":[-82.55087899999999,27.403868],"type":"Point"}
}