{
  "type": "Feature",
  "properties": {
    "iso:country":"US",
    "sg:address":"2600 Iroquois Cir",
    "sg:city":"West Palm Beach",
    "sg:classifiers":[
        {
            "category":"Banks & Credit Unions",
            "subcategory":"Investment Brokerage",
            "type":"Services"
        }
    ],
    "sg:phone":"+1 561 616 0009",
    "sg:postcode":"33409",
    "sg:province":"FL",
    "sg:tags":[
        "consultant",
        "planning",
        "financial"
    ],
    "wof:name":"AIG Advisor Group",
    "wof:placetype":"venue"
},
  "geometry": {"coordinates":[-80.100413,26.740109],"type":"Point"}
}