{
  "type": "Feature",
  "properties": {
    "iso:country":"US",
    "sg:address":"4286 Walnut St",
    "sg:city":"West Palm Beach",
    "sg:classifiers":[
        {
            "category":"Real Estate",
            "subcategory":"Real Estate Agent",
            "type":"Services"
        }
    ],
    "sg:phone":"+1 561 965 0242",
    "sg:postcode":"33406",
    "sg:province":"FL",
    "wof:name":"Patsy Martin",
    "wof:placetype":"venue"
},
  "geometry": {"coordinates":[-80.108116,26.657426],"type":"Point"}
}