{
  "type": "Feature",
  "properties": {
    "iso:country":"US",
    "sg:address":"361 Terminal Ave",
    "sg:city":"Polk City",
    "sg:classifiers":[
        {
            "category":"Organizations",
            "subcategory":"Religious Organization",
            "type":"Services"
        }
    ],
    "sg:phone":"+1 863 984 9489",
    "sg:postcode":"33868",
    "sg:province":"FL",
    "sg:tags":[
        "church"
    ],
    "wof:name":"Britt Chapel Church-God-Faith",
    "wof:placetype":"venue"
},
  "geometry": {"coordinates":[-81.80944700000001,28.1849],"type":"Point"}
}