{
  "type": "Feature",
  "properties": {
    "iso:country":"US",
    "sg:address":"4340 Golden Gem Rd",
    "sg:city":"Apopka",
    "sg:classifiers":[
        {
            "category":"Farming",
            "subcategory":"Nursery",
            "type":"Manufacturing & Wholesale Goods"
        }
    ],
    "sg:phone":"+1 407 814 7770",
    "sg:postcode":"32712",
    "sg:province":"FL",
    "sg:tags":[
        "tree",
        "grower",
        "nursery-wholesale",
        "nurseries-plants"
    ],
    "wof:name":"Donna Redders Plants",
    "wof:placetype":"venue"
},
  "geometry": {"coordinates":[-81.576616,28.74808],"type":"Point"}
}