{
  "type": "Feature",
  "properties": {
    "iso:country":"US",
    "sg:address":"14875 NW 77th Ave",
    "sg:city":"Hialeah",
    "sg:classifiers":[
        {
            "category":"Professional",
            "subcategory":"Engineering",
            "type":"Services"
        }
    ],
    "sg:phone":"+1 305 364 3770",
    "sg:postcode":"33014",
    "sg:province":"FL",
    "sg:tags":[
        "engineer"
    ],
    "wof:name":"Behar-Ybarra & Assoc Of Fl Inc",
    "wof:placetype":"venue"
},
  "geometry": {"coordinates":[-80.32428,25.908932],"type":"Point"}
}