{
  "type": "Feature",
  "properties": {
    "iso:country":"US",
    "sg:address":"1749 NE 26th St",
    "sg:city":"Fort Lauderdale",
    "sg:classifiers":[
        {
            "category":"Professional",
            "subcategory":"Lawyer & Legal Services",
            "type":"Services"
        }
    ],
    "sg:phone":"+1 954 568 6115",
    "sg:postcode":"33305",
    "sg:province":"FL",
    "wof:name":"Zaden Richard Law Office",
    "wof:placetype":"venue"
},
  "geometry": {"coordinates":[-80.12487,26.159733],"type":"Point"}
}