{
  "type": "Feature",
  "properties": {
    "iso:country":"US",
    "sg:address":"3132 Ponce De Leon Blvd",
    "sg:city":"Coral Gables",
    "sg:classifiers":[
        {
            "category":"Professional",
            "subcategory":"Lawyer & Legal Services",
            "type":"Services"
        }
    ],
    "sg:phone":"+1 305 441 0440",
    "sg:postcode":"33134",
    "sg:province":"FL",
    "sg:tags":[
        "notary"
    ],
    "sg:website":"www.aronfeld.com",
    "wof:name":"Aronfeld Trial Lawyers, P.A.",
    "wof:placetype":"venue"
},
  "geometry": {"coordinates":[-80.25859800000001,25.743299],"type":"Point"}
}