{
  "type": "Feature",
  "properties": {
    "iso:country":"US",
    "sg:address":"3430 Hickory Creek Rd",
    "sg:city":"Deltona",
    "sg:classifiers":[
        {
            "category":"Manufacturing",
            "subcategory":"Tools & Machinery",
            "type":"Manufacturing & Wholesale Goods"
        }
    ],
    "sg:phone":"+1 407 402 2828",
    "sg:postcode":"32738",
    "sg:province":"FL",
    "sg:tags":[
        "control",
        "environmental",
        "mfg"
    ],
    "wof:name":"Florida Environmental Cnstr",
    "wof:placetype":"venue"
},
  "geometry": {"coordinates":[-81.15882000000001,28.922498],"type":"Point"}
}