{
  "type": "Feature",
  "properties": {
    "iso:country":"US",
    "sg:address":"1822 SE Pruitt Rd",
    "sg:city":"Port St Lucie",
    "sg:classifiers":[
        {
            "category":"Health Services",
            "subcategory":"Doctor",
            "type":"Services"
        }
    ],
    "sg:phone":"+1 772 337 2393",
    "sg:postcode":"34952",
    "sg:province":"FL",
    "sg:tags":[
        "physician",
        "surgeon"
    ],
    "wof:name":"Treasure Coast Ear Nose & Thrt",
    "wof:placetype":"venue"
},
  "geometry": {"coordinates":[-80.317735,27.259019],"type":"Point"}
}