{
  "type": "Feature",
  "properties": {
    "iso:country":"US",
    "sg:address":"75 E 6th St",
    "sg:city":"Hialeah",
    "sg:classifiers":[
        {
            "category":"Government",
            "subcategory":"Office",
            "type":"Public Place"
        }
    ],
    "sg:phone":"+1 305 887 2525",
    "sg:postcode":"33010",
    "sg:province":"FL",
    "sg:tags":[
        "housing",
        "contractor",
        "cost",
        "low",
        "provides",
        "gen"
    ],
    "wof:name":"Hialeah Housing Authority",
    "wof:placetype":"venue"
},
  "geometry": {"coordinates":[-80.280828,25.827277],"type":"Point"}
}