{
  "type": "Feature",
  "properties": {
    "addr:full":"1581 Powell St Longwood FL 32750",
    "addr:housenumber":"1581",
    "addr:postcode":"32750",
    "addr:street":"Powell St",
    "iso:country":"US",
    "sg:address":"1581 Powell St",
    "sg:city":"Longwood",
    "sg:classifiers":[
        {
            "category":"Building & Trades",
            "subcategory":"Construction",
            "type":"Services"
        }
    ],
    "sg:phone":"+1 407 831 7190",
    "sg:postcode":"32750",
    "sg:province":"FL",
    "sg:tags":[
        "irrigation",
        "contractor"
    ],
    "wof:name":"Aquarius Sprinklers Longwood",
    "wof:placetype":"venue"
},
  "geometry": {"coordinates":[-81.37145099999999,28.696777],"type":"Point"}
}