{
  "type": "Feature",
  "properties": {
    "iso:country":"US",
    "sg:address":"1925 SE Federal Hwy ",
    "sg:city":"Stuart",
    "sg:classifiers":[
        {
            "category":"Restaurant",
            "type":"Food & Drink"
        }
    ],
    "sg:menulink":"http://www.allmenus.com/fl/stuart/38540-marios/menu/",
    "sg:phone":"+1 772 283 6660",
    "sg:postcode":"34994",
    "sg:province":"FL",
    "sg:tags":[
        "italian"
    ],
    "wof:name":"Mario's",
    "wof:placetype":"venue"
},
  "geometry": {"coordinates":[-80.24006799999999,27.181398],"type":"Point"}
}