{
  "type": "Feature",
  "properties": {
    "addr:full":"8928 Normandy Blvd Jacksonville FL 32221",
    "addr:housenumber":"8928",
    "addr:postcode":"32221",
    "addr:street":"Normandy Blvd",
    "iso:country":"US",
    "sg:address":"8928 Normandy Blvd",
    "sg:city":"Jacksonville",
    "sg:classifiers":[
        {
            "category":"Retail",
            "subcategory":"Auto Repair",
            "type":"Services"
        }
    ],
    "sg:phone":"+1 904 783 6966",
    "sg:postcode":"32221",
    "sg:province":"FL",
    "sg:tags":[
        "repairing",
        "automobile",
        "general"
    ],
    "wof:name":"Normandy Car & Truck Center",
    "wof:placetype":"venue"
},
  "geometry": {"coordinates":[-81.80300200000001,30.285961],"type":"Point"}
}