{
  "type": "Feature",
  "properties": {
    "addr:full":"12125 Barbara Rd Brooksville FL 34610",
    "addr:housenumber":"12125",
    "addr:postcode":"34610",
    "addr:street":"Barbara Rd",
    "iso:country":"US",
    "sg:address":"12125 Barbara Rd",
    "sg:city":"Brooksville",
    "sg:classifiers":[
        {
            "category":"Food & Beverages",
            "subcategory":"Fruits & Vegetables",
            "type":"Retail Goods"
        }
    ],
    "sg:phone":"+1 813 995 0164",
    "sg:postcode":"34610",
    "sg:province":"FL",
    "sg:tags":[
        "produce"
    ],
    "wof:name":"Deskins Kent Groves Produce",
    "wof:placetype":"venue"
},
  "geometry": {"coordinates":[-82.530856,28.333047],"type":"Point"}
}