{
  "type": "Feature",
  "properties": {
    "iso:country":"US",
    "sg:address":"985 Seaway Dr",
    "sg:city":"Fort Pierce",
    "sg:classifiers":[
        {
            "category":"Professional",
            "subcategory":"Management & Consulting",
            "type":"Services"
        }
    ],
    "sg:phone":"+1 772 468 6110",
    "sg:postcode":"34949",
    "sg:province":"FL",
    "sg:tags":[
        "consultant"
    ],
    "wof:name":"National Management Service",
    "wof:placetype":"venue"
},
  "geometry": {"coordinates":[-80.306499,27.463164],"type":"Point"}
}