{
  "type": "Feature",
  "properties": {
    "iso:country":"US",
    "sg:address":"724 W Vine St",
    "sg:city":"Kissimmee",
    "sg:classifiers":[
        {
            "category":"Shopping",
            "subcategory":"Music",
            "type":"Retail Goods"
        }
    ],
    "sg:phone":"+1 407 846 8461",
    "sg:postcode":"34741",
    "sg:province":"FL",
    "sg:tags":[
        "compact",
        "record",
        "disc",
        "tape"
    ],
    "wof:name":"LA Pachanga",
    "wof:placetype":"venue"
},
  "geometry": {"coordinates":[-81.411928,28.304561],"type":"Point"}
}