{
  "type": "Feature",
  "properties": {
    "iso:country":"US",
    "sg:address":"19145 Dixie Hwy",
    "sg:city":"Miami",
    "sg:classifiers":[
        {
            "category":"Restaurant",
            "type":"Food & Drink"
        }
    ],
    "sg:phone":"+1 305 253 7778",
    "sg:postcode":"33157",
    "sg:province":"FL",
    "wof:name":"Miami Wings",
    "wof:placetype":"venue"
},
  "geometry": {"coordinates":[-80.357857,25.591128],"type":"Point"}
}