{
  "type": "Feature",
  "properties": {
    "iso:country":"US",
    "sg:address":"4545 NW 103rd Ave",
    "sg:city":"Fort Lauderdale",
    "sg:classifiers":[
        {
            "category":"Shopping",
            "type":"Retail Goods"
        }
    ],
    "sg:phone":"+1 954 742 4220",
    "sg:postcode":"33351",
    "sg:province":"FL",
    "sg:tags":[
        "electronics",
        "sales"
    ],
    "wof:name":"Storewowcom",
    "wof:placetype":"venue"
},
  "geometry": {"coordinates":[-80.287302,26.179149],"type":"Point"}
}