{
  "type": "Feature",
  "properties": {
    "iso:country":"US",
    "sg:address":"2053 Cornell St",
    "sg:city":"Sarasota",
    "sg:classifiers":[
        {
            "category":"Manufacturing",
            "subcategory":"Printing",
            "type":"Manufacturing & Wholesale Goods"
        }
    ],
    "sg:phone":"+1 941 366 3250",
    "sg:postcode":"34237",
    "sg:province":"FL",
    "sg:tags":[
        "services-commercial",
        "commercial"
    ],
    "wof:name":"Arcadia Printing",
    "wof:placetype":"venue"
},
  "geometry": {"coordinates":[-82.53022300000001,27.345633],"type":"Point"}
}