{
  "type": "Feature",
  "properties": {
    "iso:country":"US",
    "sg:address":"528 SE 13th Ave",
    "sg:city":"Deerfield Beach",
    "sg:classifiers":[
        {
            "category":"Professional",
            "subcategory":"Lawyer & Legal Services",
            "type":"Services"
        }
    ],
    "sg:phone":"+1 954 354 3544",
    "sg:postcode":"33441",
    "sg:province":"FL",
    "sg:tags":[
        "attorney"
    ],
    "wof:name":"Wellborn Esquire Esq",
    "wof:placetype":"venue"
},
  "geometry": {"coordinates":[-80.086084,26.309875],"type":"Point"}
}