{
  "type": "Feature",
  "properties": {
    "addr:full":"1450 NW 108th Ave Fort Lauderdale FL 33322",
    "addr:housenumber":"1450",
    "addr:postcode":"33322",
    "addr:street":"Nw 108Th Ave",
    "iso:country":"US",
    "sg:address":"1450 NW 108th Ave",
    "sg:city":"Fort Lauderdale",
    "sg:classifiers":[
        {
            "category":"Wholesale",
            "subcategory":"Construction Materials",
            "type":"Manufacturing & Wholesale Goods"
        }
    ],
    "sg:phone":"+1 954 815 3145",
    "sg:postcode":"33322",
    "sg:province":"FL",
    "wof:name":"Eacs Inc",
    "wof:placetype":"venue"
},
  "geometry": {"coordinates":[-80.29464,26.143699],"type":"Point"}
}