{
  "type": "Feature",
  "properties": {
    "iso:country":"US",
    "sg:address":"4599 W Oxford St",
    "sg:city":"Citrus Springs",
    "sg:classifiers":[
        {
            "category":"Building & Trades",
            "subcategory":"Electrical",
            "type":"Services"
        }
    ],
    "sg:phone":"+1 352 465 2070",
    "sg:postcode":"34433",
    "sg:province":"FL",
    "sg:tags":[
        "installation"
    ],
    "wof:name":"William P Tamse Installation",
    "wof:placetype":"venue"
},
  "geometry": {"coordinates":[-82.512153,29.008077],"type":"Point"}
}