{
  "type": "Feature",
  "properties": {
    "iso:country":"US",
    "sg:address":"1777 Tamiami Trl",
    "sg:city":"Port Charlotte",
    "sg:classifiers":[
        {
            "category":"Restaurant",
            "type":"Food & Drink"
        }
    ],
    "sg:phone":"+1 941 625 0773",
    "sg:postcode":"33948",
    "sg:province":"FL",
    "sg:website":"www.obees.com",
    "wof:name":"Obee's Franchise Systems Inc",
    "wof:placetype":"venue"
},
  "geometry": {"coordinates":[-82.13638899999999,27.008276],"type":"Point"}
}