{
  "type": "Feature",
  "properties": {
    "addr:full":"601 S Ponce de Leon Blvd St Augustine FL 32084",
    "addr:housenumber":"601",
    "addr:postcode":"32084",
    "addr:street":"S Ponce De Leon Blvd St",
    "iso:country":"US",
    "sg:address":"601 S Ponce de Leon Blvd",
    "sg:city":"St Augustine",
    "sg:classifiers":[
        {
            "category":"Shopping",
            "type":"Retail Goods"
        }
    ],
    "sg:phone":"+1 904 829 0873",
    "sg:postcode":"32084",
    "sg:province":"FL",
    "sg:tags":[
        "art",
        "gallery",
        "dealer"
    ],
    "wof:name":"Sculptural Stone & Woodworks",
    "wof:placetype":"venue"
},
  "geometry": {"coordinates":[-81.324776,29.883818],"type":"Point"}
}