{
  "type": "Feature",
  "properties": {
    "iso:country":"US",
    "sg:address":"26811 S Bay Dr",
    "sg:city":"Bonita Springs",
    "sg:classifiers":[
        {
            "category":"Professional",
            "subcategory":"Lawyer & Legal Services",
            "type":"Services"
        }
    ],
    "sg:phone":"+1 239 947 6816",
    "sg:postcode":"34134",
    "sg:province":"FL",
    "sg:tags":[
        "attorney"
    ],
    "wof:name":"Bond Schoeneck & King",
    "wof:placetype":"venue"
},
  "geometry": {"coordinates":[-81.808177,26.351363],"type":"Point"}
}