{
  "type": "Feature",
  "properties": {
    "iso:country":"US",
    "sg:address":"3500 NW 52nd St",
    "sg:city":"Miami",
    "sg:classifiers":[
        {
            "category":"Retail",
            "subcategory":"Auto Repair",
            "type":"Services"
        }
    ],
    "sg:phone":"+1 305 638 0307",
    "sg:postcode":"33142",
    "sg:province":"FL",
    "sg:tags":[
        "body",
        "automobile",
        "painting"
    ],
    "wof:name":"Southern Motors Body Shop",
    "wof:placetype":"venue"
},
  "geometry": {"coordinates":[-80.25385199999999,25.821658],"type":"Point"}
}