{
  "type": "Feature",
  "properties": {
    "addr:full":"811 E Las Olas Blvd Fort Lauderdale FL 33301",
    "addr:housenumber":"811",
    "addr:postcode":"33301",
    "addr:street":"E Las Olas Blvd",
    "iso:country":"US",
    "sg:address":"811 E Las Olas Blvd",
    "sg:city":"Fort Lauderdale",
    "sg:classifiers":[
        {
            "category":"Manufacturing",
            "subcategory":"Jewelry",
            "type":"Manufacturing & Wholesale Goods"
        }
    ],
    "sg:phone":"+1 954 467 2033",
    "sg:postcode":"33301",
    "sg:province":"FL",
    "sg:tags":[
        "precious",
        "metal",
        "mfg"
    ],
    "wof:name":"Designs By Slack Inc",
    "wof:placetype":"venue"
},
  "geometry": {"coordinates":[-80.13416599999999,26.119365],"type":"Point"}
}