{
  "type": "Feature",
  "properties": {
    "addr:full":"5348 E Ohio Ave Sanford FL 32771",
    "addr:housenumber":"5348",
    "addr:postcode":"32771",
    "addr:street":"E Ohio Ave",
    "iso:country":"US",
    "sg:address":"5348 E Ohio Ave",
    "sg:city":"Sanford",
    "sg:classifiers":[
        {
            "category":"Professional",
            "subcategory":"Advertising",
            "type":"Services"
        }
    ],
    "sg:phone":"+1 407 323 7614",
    "sg:postcode":"32771",
    "sg:province":"FL",
    "sg:tags":[
        "agency"
    ],
    "wof:name":"Horse Report",
    "wof:placetype":"venue"
},
  "geometry": {"coordinates":[-81.353747,28.829021],"type":"Point"}
}