{
  "type": "Feature",
  "properties": {
    "iso:country":"US",
    "sg:address":"19593 NE 10th Ave",
    "sg:city":"Miami",
    "sg:classifiers":[
        {
            "category":"Organizations",
            "subcategory":"Non-profit Organization",
            "type":"Services"
        }
    ],
    "sg:phone":"+1 305 655 1515",
    "sg:postcode":"33179",
    "sg:province":"FL",
    "sg:tags":[
        "fund",
        "counselor",
        "raising"
    ],
    "wof:name":"Every Penny Counts",
    "wof:placetype":"venue"
},
  "geometry": {"coordinates":[-80.181871,25.955861],"type":"Point"}
}