{
  "type": "Feature",
  "properties": {
    "addr:full":"1575 W Detroit Blvd Pensacola FL 32534",
    "addr:housenumber":"1575",
    "addr:postcode":"32534",
    "addr:street":"W Detroit Blvd",
    "iso:country":"US",
    "sg:address":"1575 W Detroit Blvd",
    "sg:city":"Pensacola",
    "sg:classifiers":[
        {
            "category":"Professional",
            "subcategory":"Management & Consulting",
            "type":"Services"
        }
    ],
    "sg:phone":"+1 850 232 9379",
    "sg:postcode":"32534",
    "sg:province":"FL",
    "sg:tags":[
        "business"
    ],
    "wof:name":"J Soft Consulting Inc",
    "wof:placetype":"venue"
},
  "geometry": {"coordinates":[-87.291804,30.519124],"type":"Point"}
}