{
  "type": "Feature",
  "properties": {
    "iso:country":"US",
    "sg:address":"12750 Old Fannin Rd",
    "sg:city":"Chiefland",
    "sg:classifiers":[
        {
            "category":"Communications",
            "subcategory":"Radio Station",
            "type":"Services"
        }
    ],
    "sg:phone":"+1 352 493 4940",
    "sg:postcode":"32626",
    "sg:province":"FL",
    "sg:tags":[
        "broadcasting"
    ],
    "wof:name":"Wlqh",
    "wof:placetype":"venue"
},
  "geometry": {"coordinates":[-82.89299099999999,29.530721],"type":"Point"}
}