{
  "type": "Feature",
  "properties": {
    "addr:full":"12447 S Orange Blossom Trl Orlando FL 32837",
    "addr:housenumber":"12447",
    "addr:postcode":"32837",
    "addr:street":"S Orange Blossom Trl",
    "iso:country":"US",
    "sg:address":"12447 S Orange Blossom Trl",
    "sg:city":"Orlando",
    "sg:classifiers":[
        {
            "category":"Shopping",
            "subcategory":"Computers & Home Electronics",
            "type":"Retail Goods"
        }
    ],
    "sg:phone":"+1 407 858 0322",
    "sg:postcode":"32837",
    "sg:province":"FL",
    "sg:tags":[
        "equipment",
        "satellite",
        "system"
    ],
    "wof:name":"Satellite Dish & Comm",
    "wof:placetype":"venue"
},
  "geometry": {"coordinates":[-81.404472,28.383372],"type":"Point"}
}