{
  "type": "Feature",
  "properties": {
    "iso:country":"US",
    "sg:address":"8081 129th Ct",
    "sg:city":"Sebastian",
    "sg:classifiers":[
        {
            "category":"Place Of Worship",
            "subcategory":"Church",
            "type":"Public Place"
        },
        {
            "category":"Place Of Worship",
            "type":"Public Place"
        }
    ],
    "sg:phone":"+1 772 589 3035",
    "sg:postcode":"32958",
    "sg:province":"FL",
    "sg:tags":[
        "churches-methodist"
    ],
    "wof:name":"Roseland United Methodist Church",
    "wof:placetype":"venue"
},
  "geometry": {"coordinates":[-80.493793,27.830991],"type":"Point"}
}