{
  "type": "Feature",
  "properties": {
    "addr:full":"3364 S University Dr Miramar FL 33025",
    "addr:housenumber":"3364",
    "addr:postcode":"33025",
    "addr:street":"S University Dr",
    "iso:country":"US",
    "sg:address":"3364 S University Dr",
    "sg:city":"Miramar",
    "sg:classifiers":[
        {
            "category":"Restaurant",
            "type":"Food & Drink"
        }
    ],
    "sg:phone":"+1 954 435 3365",
    "sg:postcode":"33025",
    "sg:province":"FL",
    "wof:name":"Subway Sandwiches & Salads",
    "wof:placetype":"venue"
},
  "geometry": {"coordinates":[-80.247028,25.976984],"type":"Point"}
}