{
  "type": "Feature",
  "properties": {
    "addr:full":"363 Tahitian Dr Ellenton FL 34222",
    "addr:housenumber":"363",
    "addr:postcode":"34222",
    "addr:street":"Tahitian Dr",
    "iso:country":"US",
    "sg:address":"363 Tahitian Dr",
    "sg:city":"Ellenton",
    "sg:classifiers":[
        {
            "category":"Shopping",
            "subcategory":"Hobbies, Toys, & Games",
            "type":"Retail Goods"
        }
    ],
    "sg:phone":"+1 941 722 2663",
    "sg:postcode":"34222",
    "sg:province":"FL",
    "sg:tags":[
        "house",
        "doll",
        "accessory"
    ],
    "wof:name":"Creative Mini Mart",
    "wof:placetype":"venue"
},
  "geometry": {"coordinates":[-82.488343,27.542907],"type":"Point"}
}