{
  "type": "Feature",
  "properties": {
    "iso:country":"US",
    "sg:address":"1300 Herbert St",
    "sg:city":"Daytona Beach",
    "sg:classifiers":[
        {
            "category":"Education",
            "subcategory":"School",
            "type":"Public Place"
        }
    ],
    "sg:phone":"+1 386 322 7550",
    "sg:postcode":"32129",
    "sg:province":"FL",
    "wof:name":"Silver Sands Middle School",
    "wof:placetype":"venue"
},
  "geometry": {"coordinates":[-81.020534,29.132628],"type":"Point"}
}