{
  "type": "Feature",
  "properties": {
    "addr:full":"125 56th Ave S St Petersburg FL 33705",
    "addr:housenumber":"125",
    "addr:postcode":"33705",
    "addr:street":"56Th Ave S",
    "iso:country":"US",
    "sg:address":"125 56th Ave S",
    "sg:city":"St Petersburg",
    "sg:classifiers":[
        {
            "category":"Health Services",
            "subcategory":"Nursing And Care Facility",
            "type":"Services"
        }
    ],
    "sg:phone":"+1 727 867 2131",
    "sg:postcode":"33705",
    "sg:province":"FL",
    "sg:tags":[
        "home",
        "retirement",
        "community"
    ],
    "sg:website":"www.westminsterretirement.com",
    "wof:name":"Westminster Shores",
    "wof:placetype":"venue"
},
  "geometry": {"coordinates":[-82.634619,27.717272],"type":"Point"}
}