{
  "type": "Feature",
  "properties": {
    "iso:country":"US",
    "sg:address":"1012 N Ocean Blvd",
    "sg:city":"Pompano Beach",
    "sg:classifiers":[
        {
            "category":"Manufacturing",
            "subcategory":"Paper Products",
            "type":"Manufacturing & Wholesale Goods"
        }
    ],
    "sg:phone":"+1 954 545 3600",
    "sg:postcode":"33062",
    "sg:province":"FL",
    "sg:tags":[
        "packaging",
        "mfg"
    ],
    "wof:name":"Advertising Packg Assn Intl",
    "wof:placetype":"venue"
},
  "geometry": {"coordinates":[-80.086989,26.247432],"type":"Point"}
}