{
  "type": "Feature",
  "properties": {
    "iso:country":"US",
    "sg:address":"10513 Waterview Ct",
    "sg:city":"Tampa",
    "sg:classifiers":[
        {
            "category":"Manufacturing",
            "subcategory":"Rubber & Plastics",
            "type":"Manufacturing & Wholesale Goods"
        }
    ],
    "sg:phone":"+1 813 854 5298",
    "sg:postcode":"33615",
    "sg:province":"FL",
    "sg:tags":[
        "product"
    ],
    "wof:name":"Impact Container Systems Inc",
    "wof:placetype":"venue"
},
  "geometry": {"coordinates":[-82.603959,28.003811],"type":"Point"}
}