{
  "type": "Feature",
  "properties": {
    "iso:country":"US",
    "sg:address":"4284 Elvis Presley Dr",
    "sg:city":"Milton",
    "sg:classifiers":[
        {
            "category":"Building & Trades",
            "subcategory":"Construction",
            "type":"Services"
        }
    ],
    "sg:phone":"+1 850 380 0638",
    "sg:postcode":"32583",
    "sg:province":"FL",
    "sg:tags":[
        "floor",
        "laying",
        "contractor"
    ],
    "wof:name":"Mike McNaughton Flooring",
    "wof:placetype":"venue"
},
  "geometry": {"coordinates":[-86.959917,30.59149],"type":"Point"}
}