{
  "type": "Feature",
  "properties": {
    "addr:full":"1413 S Patrick Dr Indian Hrbr Bch FL 32937",
    "addr:housenumber":"1413",
    "addr:postcode":"32937",
    "addr:street":"S Patrick Dr Indian Hrbr",
    "iso:country":"US",
    "sg:address":"1413 S Patrick Dr",
    "sg:city":"Indian Hrbr Bch",
    "sg:classifiers":[
        {
            "category":"Real Estate",
            "subcategory":"Real Estate Operator",
            "type":"Services"
        }
    ],
    "sg:phone":"+1 321 773 2368",
    "sg:postcode":"32937",
    "sg:province":"FL",
    "sg:tags":[
        "building",
        "parks"
    ],
    "wof:name":"Beach Harbor Office Bldg",
    "wof:placetype":"venue"
},
  "geometry": {"coordinates":[-80.605879,28.17228],"type":"Point"}
}