{
  "type": "Feature",
  "properties": {
    "iso:country":"US",
    "sg:address":"3283 S John Young Pkwy",
    "sg:city":"Kissimmee",
    "sg:classifiers":[
        {
            "category":"Wholesale",
            "subcategory":"Sporting Goods",
            "type":"Manufacturing & Wholesale Goods"
        }
    ],
    "sg:phone":"+1 407 935 0009",
    "sg:postcode":"34746",
    "sg:province":"FL",
    "sg:tags":[
        "equipment",
        "pool",
        "swimming"
    ],
    "wof:name":"Pool Hut",
    "wof:placetype":"venue"
},
  "geometry": {"coordinates":[-81.435242,28.261114],"type":"Point"}
}