{
  "type": "Feature",
  "properties": {
    "iso:country":"US",
    "sg:address":"9617 Cinnamon Ct",
    "sg:city":"Parkland",
    "sg:classifiers":[
        {
            "category":"Restaurant",
            "type":"Food & Drink"
        }
    ],
    "sg:phone":"+1 954 796 0389",
    "sg:postcode":"33076",
    "sg:province":"FL",
    "sg:tags":[
        "pizza"
    ],
    "wof:name":"Pizza Time, Inc.",
    "wof:placetype":"venue"
},
  "geometry": {"coordinates":[-80.25502299999999,26.32742],"type":"Point"}
}