{
  "type": "Feature",
  "properties": {
    "iso:country":"US",
    "sg:address":"2216 E Fletcher Ave",
    "sg:city":"Tampa",
    "sg:classifiers":[
        {
            "category":"Restaurant",
            "type":"Food & Drink"
        }
    ],
    "sg:menulink":"http://www.allmenus.com/fl/tampa/174794-popeyes-chicken--biscuits/menu/",
    "sg:phone":"+1 813 979 1936",
    "sg:postcode":"33612",
    "sg:province":"FL",
    "sg:tags":[
        "american",
        "wing"
    ],
    "wof:name":"Popeyes Chicken & Biscuits",
    "wof:placetype":"venue"
},
  "geometry": {"coordinates":[-82.433801,28.069629],"type":"Point"}
}