{
  "type": "Feature",
  "properties": {
    "iso:country":"US",
    "sg:address":"1630 Sandalwood Blvd",
    "sg:city":"Jacksonville",
    "sg:classifiers":[
        {
            "category":"Social Services",
            "subcategory":"Child Care",
            "type":"Services"
        }
    ],
    "sg:phone":"+1 904 998 4666",
    "sg:postcode":"32246",
    "sg:province":"FL",
    "wof:name":"Great Foundations Child Dev",
    "wof:placetype":"venue"
},
  "geometry": {"coordinates":[-81.51666899999999,30.324219],"type":"Point"}
}