{
  "type": "Feature",
  "properties": {
    "addr:full":"9622 Pines Blvd Pembroke Pines FL 33024",
    "addr:housenumber":"9622",
    "addr:postcode":"33024",
    "addr:street":"Pines Blvd",
    "iso:country":"US",
    "sg:address":"9622 Pines Blvd",
    "sg:city":"Pembroke Pines",
    "sg:classifiers":[
        {
            "category":"Personal",
            "subcategory":"Beauty Salon",
            "type":"Services"
        }
    ],
    "sg:phone":"+1 954 441 2227",
    "sg:postcode":"33024",
    "sg:province":"FL",
    "sg:tags":[
        "treatment",
        "skin"
    ],
    "wof:name":"To Please Hair Salon",
    "wof:placetype":"venue"
},
  "geometry": {"coordinates":[-80.27359300000001,26.00842],"type":"Point"}
}