{
  "type": "Feature",
  "properties": {
    "iso:country":"US",
    "sg:address":"5445 Collins Ave",
    "sg:city":"Miami Beach",
    "sg:classifiers":[
        {
            "category":"Professional",
            "subcategory":"Art Services",
            "type":"Services"
        }
    ],
    "sg:phone":"+1 305 865 1827",
    "sg:postcode":"33140",
    "sg:province":"FL",
    "sg:tags":[
        "commercial",
        "design"
    ],
    "wof:name":"Zitron Inc",
    "wof:placetype":"venue"
},
  "geometry": {"coordinates":[-80.12290299999999,25.818851],"type":"Point"}
}