{
  "type": "Feature",
  "properties": {
    "addr:full":"226 Wilshire Blvd Casselberry FL 32707",
    "addr:housenumber":"226",
    "addr:postcode":"32707",
    "addr:street":"Wilshire Blvd",
    "iso:country":"US",
    "sg:address":"226 Wilshire Blvd",
    "sg:city":"Casselberry",
    "sg:classifiers":[
        {
            "category":"Building & Trades",
            "subcategory":"Pest Control",
            "type":"Services"
        }
    ],
    "sg:phone":"+1 407 331 8312",
    "sg:postcode":"32707",
    "sg:province":"FL",
    "wof:name":"Prism",
    "wof:placetype":"venue"
},
  "geometry": {"coordinates":[-81.32964699999999,28.650215],"type":"Point"}
}