{
  "type": "Feature",
  "properties": {
    "iso:country":"US",
    "sg:address":"415 Mary Esther Cutoff NW",
    "sg:city":"Fort Walton Bch",
    "sg:classifiers":[
        {
            "category":"Food & Beverages",
            "subcategory":"Specialty",
            "type":"Retail Goods"
        }
    ],
    "sg:phone":"+1 850 244 3688",
    "sg:postcode":"32548",
    "sg:province":"FL",
    "sg:tags":[
        "health",
        "diet"
    ],
    "wof:name":"Tropical Smoothie",
    "wof:placetype":"venue"
},
  "geometry": {"coordinates":[-86.643193,30.425473],"type":"Point"}
}