{
  "type": "Feature",
  "properties": {
    "iso:country":"US",
    "sg:address":"2452 NE 3rd St",
    "sg:city":"Ocala",
    "sg:classifiers":[
        {
            "category":"Real Estate",
            "subcategory":"Real Estate Agent",
            "type":"Services"
        }
    ],
    "sg:phone":"+1 352 867 7653",
    "sg:postcode":"34470",
    "sg:province":"FL",
    "sg:website":"www.tricountyrealtygroup.com",
    "wof:name":"Tri County Realty",
    "wof:placetype":"venue"
},
  "geometry": {"coordinates":[-82.106098,29.189594],"type":"Point"}
}