{
  "type": "Feature",
  "properties": {
    "addr:full":"2401 W Bay Dr Largo FL 33770",
    "addr:housenumber":"2401",
    "addr:postcode":"33770",
    "addr:street":"W Bay Dr",
    "iso:country":"US",
    "sg:address":"2401 W Bay Dr",
    "sg:city":"Largo",
    "sg:classifiers":[
        {
            "category":"Food & Beverages",
            "subcategory":"Specialty",
            "type":"Retail Goods"
        }
    ],
    "sg:phone":"+1 727 559 0179",
    "sg:postcode":"33770",
    "sg:province":"FL",
    "sg:tags":[
        "product",
        "health",
        "diet"
    ],
    "wof:name":"Key2health Inc",
    "wof:placetype":"venue"
},
  "geometry": {"coordinates":[-82.812759,27.916771],"type":"Point"}
}