{
  "type": "Feature",
  "properties": {
    "iso:country":"US",
    "sg:address":"1 Buffalo Meadow Ln",
    "sg:city":"Palm Coast",
    "sg:classifiers":[
        {
            "category":"Building & Trades",
            "subcategory":"Construction",
            "type":"Services"
        }
    ],
    "sg:phone":"+1 386 445 4140",
    "sg:postcode":"32137",
    "sg:province":"FL",
    "sg:tags":[
        "resurfacing",
        "floor",
        "laying",
        "refinishing",
        "contractor"
    ],
    "sg:website":"www.qualitycraftwoodfloors.net",
    "wof:name":"Quality Craft Wood Floors Inc",
    "wof:placetype":"venue"
},
  "geometry": {"coordinates":[-81.25776999999999,29.5947],"type":"Point"}
}