{
  "type": "Feature",
  "properties": {
    "iso:country":"US",
    "sg:address":"333 W 41st St Ste 208",
    "sg:city":"Miami Beach",
    "sg:classifiers":[
        {
            "category":"Banks & Credit Unions",
            "subcategory":"Investment Brokerage",
            "type":"Services"
        }
    ],
    "sg:phone":"+1 305 531 3456",
    "sg:postcode":"33140",
    "sg:province":"FL",
    "sg:tags":[
        "investing"
    ],
    "wof:name":"Global Bouillion Exchange",
    "wof:placetype":"venue"
},
  "geometry": {"coordinates":[-80.127092,25.813906],"type":"Point"}
}