{
  "type": "Feature",
  "properties": {
    "iso:country":"US",
    "sg:address":"1390 Brickell Ave Ste 104",
    "sg:city":"Miami",
    "sg:classifiers":[
        {
            "category":"Professional",
            "subcategory":"Business Services",
            "type":"Services"
        }
    ],
    "sg:phone":"+1 305 379 6651",
    "sg:postcode":"33131",
    "sg:province":"FL",
    "sg:tags":[
        "consultant",
        "coach"
    ],
    "wof:name":"Biff Consulting Group Corp",
    "wof:placetype":"venue"
},
  "geometry": {"coordinates":[-80.19225400000001,25.76046],"type":"Point"}
}