{
  "type": "Feature",
  "properties": {
    "addr:full":"4815 123rd Trl N West Palm Beach FL 33411",
    "addr:housenumber":"4815",
    "addr:postcode":"33411",
    "addr:street":"123Rd Trl N",
    "iso:country":"US",
    "sg:address":"4815 123rd Trl N",
    "sg:city":"West Palm Beach",
    "sg:classifiers":[
        {
            "category":"Freight",
            "type":"Transportation"
        }
    ],
    "sg:phone":"+1 561 791 8843",
    "sg:postcode":"33411",
    "sg:province":"FL",
    "sg:tags":[
        "operator",
        "local",
        "trucking"
    ],
    "wof:name":"K and S Trucking Inc",
    "wof:placetype":"venue"
},
  "geometry": {"coordinates":[-80.237601,26.748275],"type":"Point"}
}