{
  "type": "Feature",
  "properties": {
    "iso:country":"US",
    "sg:address":"511 S Bonita Ave",
    "sg:city":"Panama City",
    "sg:classifiers":[
        {
            "category":"Professional",
            "type":"Services"
        }
    ],
    "sg:phone":"+1 850 913 8186",
    "sg:postcode":"32401",
    "sg:province":"FL",
    "wof:name":"Almax Services Inc",
    "wof:placetype":"venue"
},
  "geometry": {"coordinates":[-85.640986,30.138486],"type":"Point"}
}