{
  "type": "Feature",
  "properties": {
    "iso:country":"US",
    "sg:address":"829 Lincoln Rd",
    "sg:city":"Miami Beach",
    "sg:classifiers":[
        {
            "category":"Shopping",
            "subcategory":"Shoes",
            "type":"Retail Goods"
        }
    ],
    "sg:phone":"+1 305 695 9585",
    "sg:postcode":"33139",
    "sg:province":"FL",
    "sg:tags":[
        "store"
    ],
    "wof:name":"Sobe Shoe Company",
    "wof:placetype":"venue"
},
  "geometry": {"coordinates":[-80.1371,25.7904],"type":"Point"}
}