{
  "type": "Feature",
  "properties": {
    "addr:full":"1408 N West Shore Blvd Tampa FL 33607",
    "addr:housenumber":"1408",
    "addr:postcode":"33607",
    "addr:street":"N West Shore Blvd",
    "iso:country":"US",
    "sg:address":"1408 N West Shore Blvd",
    "sg:city":"Tampa",
    "sg:classifiers":[
        {
            "category":"Professional",
            "subcategory":"Advertising",
            "type":"Services"
        }
    ],
    "sg:phone":"+1 813 289 8666",
    "sg:postcode":"33607",
    "sg:province":"FL",
    "sg:tags":[
        "mail"
    ],
    "sg:website":"www.advo.com",
    "wof:name":"ADVO Inc",
    "wof:placetype":"venue"
},
  "geometry": {"coordinates":[-82.52421099999999,27.955824],"type":"Point"}
}