{
  "type": "Feature",
  "properties": {
    "iso:country":"US",
    "sg:address":"5524 Van Dyke Rd",
    "sg:city":"Lutz",
    "sg:classifiers":[
        {
            "category":"Autos & Motor Vehicles",
            "subcategory":"Fuel & Gas Station",
            "type":"Retail Goods"
        },
        {
            "category":"Food & Beverages",
            "subcategory":"Groceries & Convenience Stores",
            "type":"Retail Goods"
        }
    ],
    "sg:phone":"+1 813 963 6423",
    "sg:postcode":"33558",
    "sg:province":"FL",
    "wof:name":"The Convenience Store",
    "wof:placetype":"venue"
},
  "geometry": {"coordinates":[-82.53026699999999,28.127901],"type":"Point"}
}