{
  "type": "Feature",
  "properties": {
    "addr:full":"2002 Dellwood Ave Jacksonville FL 32204",
    "addr:housenumber":"2002",
    "addr:postcode":"32204",
    "addr:street":"Dellwood Ave",
    "iso:country":"US",
    "sg:address":"2002 Dellwood Ave",
    "sg:city":"Jacksonville",
    "sg:classifiers":[
        {
            "category":"Shopping",
            "subcategory":"Computers & Home Electronics",
            "type":"Retail Goods"
        }
    ],
    "sg:phone":"+1 904 353 9040",
    "sg:postcode":"32204",
    "sg:province":"FL",
    "sg:tags":[
        "software"
    ],
    "wof:name":"Schnauss Computer Svc",
    "wof:placetype":"venue"
},
  "geometry": {"coordinates":[-81.684432,30.317774],"type":"Point"}
}