{
  "type": "Feature",
  "properties": {
    "addr:full":"17452 Meadow Ln Lutz FL 33558",
    "addr:housenumber":"17452",
    "addr:postcode":"33558",
    "addr:street":"Meadow Ln",
    "iso:country":"US",
    "sg:address":"17452 Meadow Ln",
    "sg:city":"Lutz",
    "sg:classifiers":[
        {
            "category":"Real Estate",
            "subcategory":"Surveying",
            "type":"Services"
        }
    ],
    "sg:phone":"+1 813 792 1158",
    "sg:postcode":"33558",
    "sg:province":"FL",
    "sg:tags":[
        "surveyor"
    ],
    "wof:name":"Summit Surveying Svc Inc",
    "wof:placetype":"venue"
},
  "geometry": {"coordinates":[-82.527483,28.178562],"type":"Point"}
}