{
  "type": "Feature",
  "properties": {
    "addr:full":"21900 SW 134th Ave Miami FL 33170",
    "addr:housenumber":"21900",
    "addr:postcode":"33170",
    "addr:street":"Sw 134Th Ave",
    "iso:country":"US",
    "sg:address":"21900 SW 134th Ave",
    "sg:city":"Miami",
    "sg:classifiers":[
        {
            "category":"Farming",
            "subcategory":"Nursery",
            "type":"Manufacturing & Wholesale Goods"
        }
    ],
    "sg:phone":"+1 305 258 3625",
    "sg:postcode":"33170",
    "sg:province":"FL",
    "sg:tags":[
        "landscape",
        "contractor"
    ],
    "wof:name":"Richard Higgins Landscaping",
    "wof:placetype":"venue"
},
  "geometry": {"coordinates":[-80.408946,25.562341],"type":"Point"}
}