{
  "type": "Feature",
  "properties": {
    "iso:country":"US",
    "sg:address":"9941 W Jessamine St",
    "sg:city":"Miami",
    "sg:classifiers":[
        {
            "category":"Professional",
            "subcategory":"Business Services",
            "type":"Services"
        }
    ],
    "sg:phone":"+1 305 256 5827",
    "sg:postcode":"33157",
    "sg:province":"FL",
    "sg:tags":[
        "holding"
    ],
    "wof:name":"Icarus Holdings",
    "wof:placetype":"venue"
},
  "geometry": {"coordinates":[-80.353993,25.603346],"type":"Point"}
}