{
  "type": "Feature",
  "properties": {
    "addr:full":"7614 Cedar Hurst Ct Lake Worth FL 33467",
    "addr:housenumber":"7614",
    "addr:postcode":"33467",
    "addr:street":"Cedar Hurst Ct",
    "iso:country":"US",
    "sg:address":"7614 Cedar Hurst Ct",
    "sg:city":"Lake Worth",
    "sg:classifiers":[
        {
            "category":"Professional",
            "subcategory":"Advertising",
            "type":"Services"
        }
    ],
    "sg:phone":"+1 561 963 5965",
    "sg:postcode":"33467",
    "sg:province":"FL",
    "sg:tags":[
        "agency"
    ],
    "wof:name":"Gardener Group Inc",
    "wof:placetype":"venue"
},
  "geometry": {"coordinates":[-80.165958,26.56089],"type":"Point"}
}