{
  "type": "Feature",
  "properties": {
    "iso:country":"US",
    "sg:address":"3081 E Commercial Blvd",
    "sg:city":"Fort Lauderdale",
    "sg:classifiers":[
        {
            "category":"Communications",
            "subcategory":"Film & Video Production",
            "type":"Services"
        }
    ],
    "sg:phone":"+1 954 771 1993",
    "sg:postcode":"33308",
    "sg:province":"FL",
    "sg:tags":[
        "taping"
    ],
    "wof:name":"Pro Leisure Inc",
    "wof:placetype":"venue"
},
  "geometry": {"coordinates":[-80.104524,26.189867],"type":"Point"}
}