{
  "type": "Feature",
  "properties": {
    "iso:country":"US",
    "sg:address":"1858 Lime Tree Dr",
    "sg:city":"Edgewater",
    "sg:classifiers":[
        {
            "category":"Wholesale",
            "subcategory":"Metals & Minerals",
            "type":"Manufacturing & Wholesale Goods"
        }
    ],
    "sg:phone":"+1 386 427 6576",
    "sg:postcode":"32141",
    "sg:province":"FL",
    "sg:tags":[
        "aluminum"
    ],
    "wof:name":"Rick's Aluminum Co",
    "wof:placetype":"venue"
},
  "geometry": {"coordinates":[-80.905767,28.967101],"type":"Point"}
}