{
  "type": "Feature",
  "properties": {
    "addr:full":"5303 Hill Dr Zephyrhills FL 33542",
    "addr:housenumber":"5303",
    "addr:postcode":"33542",
    "addr:street":"Hill Dr",
    "iso:country":"US",
    "sg:address":"5303 Hill Dr",
    "sg:city":"Zephyrhills",
    "sg:classifiers":[
        {
            "category":"Building & Trades",
            "subcategory":"Construction",
            "type":"Services"
        }
    ],
    "sg:phone":"+1 813 715 1754",
    "sg:postcode":"33542",
    "sg:province":"FL",
    "sg:tags":[
        "floor",
        "laying",
        "contractor"
    ],
    "wof:name":"Garrison Flooring Installation",
    "wof:placetype":"venue"
},
  "geometry": {"coordinates":[-82.196634,28.235777],"type":"Point"}
}