{
  "type": "Feature",
  "properties": {
    "iso:country":"US",
    "sg:address":"3045 Davis Blvd",
    "sg:city":"Naples",
    "sg:classifiers":[
        {
            "category":"Organizations",
            "subcategory":"Professional Association",
            "type":"Services"
        }
    ],
    "sg:phone":"+1 239 793 5955",
    "sg:postcode":"34104",
    "sg:province":"FL",
    "wof:name":"Naples Haitian Assn Inc",
    "wof:placetype":"venue"
},
  "geometry": {"coordinates":[-81.76789599999999,26.138575],"type":"Point"}
}