{
  "type": "Feature",
  "properties": {
    "iso:country":"US",
    "sg:address":"3649 W Waters Ave",
    "sg:city":"Tampa",
    "sg:classifiers":[
        {
            "category":"Education",
            "subcategory":"Dance Studio",
            "type":"Public Place"
        }
    ],
    "sg:phone":"+1 813 935 3502",
    "sg:postcode":"33614",
    "sg:province":"FL",
    "sg:tags":[
        "instruction",
        "dancing"
    ],
    "wof:name":"Elsa Pardo Dance Ctr",
    "wof:placetype":"venue"
},
  "geometry": {"coordinates":[-82.50242900000001,28.02551],"type":"Point"}
}