{
  "type": "Feature",
  "properties": {
    "iso:country":"US",
    "sg:address":"15721 New Hampshire Ct",
    "sg:city":"Fort Myers",
    "sg:classifiers":[
        {
            "category":"Health Services",
            "subcategory":"Doctor",
            "type":"Services"
        }
    ],
    "sg:phone":"+1 239 936 4107",
    "sg:postcode":"33908",
    "sg:province":"FL",
    "sg:tags":[
        "physician",
        "surgeon"
    ],
    "wof:name":"Fort Myers Ear Nose & Throat",
    "wof:placetype":"venue"
},
  "geometry": {"coordinates":[-81.89766899999999,26.513758],"type":"Point"}
}