{
  "type": "Feature",
  "properties": {
    "iso:country":"US",
    "sg:address":"2012 NE 164th St",
    "sg:city":"North Miami Beach",
    "sg:classifiers":[
        {
            "category":"Personal",
            "subcategory":"Beauty Salon",
            "type":"Services"
        }
    ],
    "sg:phone":"+1 305 947 3467",
    "sg:postcode":"33162",
    "sg:province":"FL",
    "sg:tags":[
        "hair"
    ],
    "sg:website":"www.jackiesunisexbeautysalon.com",
    "wof:name":"Jackie's Unisex Beauty Salon",
    "wof:placetype":"venue"
},
  "geometry": {"coordinates":[-80.15920300000001,25.927],"type":"Point"}
}