{
  "type": "Feature",
  "properties": {
    "iso:country":"US",
    "sg:address":"1903 Capri Rd",
    "sg:city":"Valrico",
    "sg:classifiers":[
        {
            "category":"Utilities",
            "subcategory":"Telephone",
            "type":"Services"
        }
    ],
    "sg:phone":"+1 813 571 7354",
    "sg:postcode":"33594",
    "sg:province":"FL",
    "sg:tags":[
        "communication",
        "datum"
    ],
    "sg:website":"www.full-duplex.net",
    "wof:name":"Full Duplex Communications",
    "wof:placetype":"venue"
},
  "geometry": {"coordinates":[-82.25290800000001,27.950021],"type":"Point"}
}