{
  "type": "Feature",
  "properties": {
    "iso:country":"US",
    "sg:address":"3957 Hendricks Ave",
    "sg:city":"Jacksonville",
    "sg:classifiers":[
        {
            "category":"Retail",
            "subcategory":"Laundry & Dry Cleaning",
            "type":"Services"
        },
        {
            "category":"Retail",
            "subcategory":"Repair Shop",
            "type":"Services"
        },
        {
            "category":"Home & Garden",
            "subcategory":"Carpets & Floor Coverings",
            "type":"Retail Goods"
        }
    ],
    "sg:phone":"+1 904 398 7847",
    "sg:postcode":"32207",
    "sg:province":"FL",
    "sg:tags":[
        "cleaner",
        "pads",
        "accessory",
        "rug",
        "lining"
    ],
    "sg:website":"http://orientalrughouse.com",
    "wof:name":"ORH/ Oriental Rug House",
    "wof:placetype":"venue"
},
  "geometry": {"coordinates":[-81.650993,30.281783],"type":"Point"}
}