{
  "type": "Feature",
  "properties": {
    "addr:full":"1199 3rd St S Naples FL 34102",
    "addr:housenumber":"1199",
    "addr:postcode":"34102",
    "addr:street":"3Rd St S",
    "iso:country":"US",
    "sg:address":"1199 3rd St S",
    "sg:city":"Naples",
    "sg:classifiers":[
        {
            "category":"Shopping",
            "type":"Retail Goods"
        }
    ],
    "sg:phone":"+1 239 261 7581",
    "sg:postcode":"34102",
    "sg:province":"FL",
    "sg:tags":[
        "art",
        "gallery",
        "dealer"
    ],
    "wof:name":"Darvish Collection Of Fine Art",
    "wof:placetype":"venue"
},
  "geometry": {"coordinates":[-81.802025,26.133204],"type":"Point"}
}