{
  "type": "Feature",
  "properties": {
    "addr:full":"5131 Heron Ct Pompano Beach FL 33073",
    "addr:housenumber":"5131",
    "addr:postcode":"33073",
    "addr:street":"Heron Ct",
    "iso:country":"US",
    "sg:address":"5131 Heron Ct",
    "sg:city":"Pompano Beach",
    "sg:classifiers":[
        {
            "category":"Building & Trades",
            "subcategory":"Construction",
            "type":"Services"
        }
    ],
    "sg:phone":"+1 954 418 8349",
    "sg:postcode":"33073",
    "sg:province":"FL",
    "sg:tags":[
        "hanging",
        "contractor"
    ],
    "wof:name":"Atlantic Coast Painting",
    "wof:placetype":"venue"
},
  "geometry": {"coordinates":[-80.195024,26.310948],"type":"Point"}
}