{
  "type": "Feature",
  "properties": {
    "iso:country":"US",
    "sg:address":"512 W Central Blvd",
    "sg:city":"Orlando",
    "sg:classifiers":[
        {
            "category":"Social Services",
            "subcategory":"Child Care",
            "type":"Services"
        }
    ],
    "sg:phone":"+1 407 422 5291",
    "sg:postcode":"32801",
    "sg:province":"FL",
    "sg:tags":[
        "nursery"
    ],
    "wof:name":"Orlando Day Nursery Assn",
    "wof:placetype":"venue"
},
  "geometry": {"coordinates":[-81.386775,28.541927],"type":"Point"}
}