{
  "type": "Feature",
  "properties": {
    "addr:full":"905 US Hwy 1 West Palm Beach FL 33403",
    "addr:housenumber":"905",
    "addr:postcode":"33403",
    "addr:street":"Us Hwy 1",
    "iso:country":"US",
    "sg:address":"905 US Hwy 1",
    "sg:city":"West Palm Beach",
    "sg:classifiers":[
        {
            "category":"Education",
            "subcategory":"Dance Studio",
            "type":"Public Place"
        }
    ],
    "sg:phone":"+1 561 863 5163",
    "sg:postcode":"33403",
    "sg:province":"FL",
    "sg:tags":[
        "instruction",
        "dancing"
    ],
    "wof:name":"Fred Astaire Dance Studio",
    "wof:placetype":"venue"
},
  "geometry": {"coordinates":[-80.054962,26.800981],"type":"Point"}
}