{
  "type": "Feature",
  "properties": {
    "iso:country":"US",
    "sg:address":"9076 Alfred Blvd",
    "sg:city":"Punta Gorda",
    "sg:classifiers":[
        {
            "category":"Building & Trades",
            "subcategory":"Construction",
            "type":"Services"
        }
    ],
    "sg:phone":"+1 941 575 6009",
    "sg:postcode":"33982",
    "sg:province":"FL",
    "sg:tags":[
        "sewer",
        "contractor"
    ],
    "wof:name":"Precison Lift Stations Inc",
    "wof:placetype":"venue"
},
  "geometry": {"coordinates":[-81.967074,26.900161],"type":"Point"}
}