{
  "type": "Feature",
  "properties": {
    "iso:country":"US",
    "sg:address":"3637 NE 168th St",
    "sg:city":"Miami",
    "sg:classifiers":[
        {
            "category":"Banks & Credit Unions",
            "subcategory":"Bank",
            "type":"Services"
        }
    ],
    "sg:phone":"+1 786 897 7252",
    "sg:postcode":"33160",
    "sg:province":"FL",
    "sg:tags":[
        "broker",
        "mortgage"
    ],
    "wof:name":"GGC Guastella Group Corp",
    "wof:placetype":"venue"
},
  "geometry": {"coordinates":[-80.13301199999999,25.934906],"type":"Point"}
}