{
  "type": "Feature",
  "properties": {
    "iso:country":"US",
    "sg:address":"7578 SE Maricamp Rd",
    "sg:city":"Ocala",
    "sg:classifiers":[
        {
            "category":"Food & Beverages",
            "subcategory":"Groceries & Convenience Stores",
            "type":"Retail Goods"
        }
    ],
    "sg:phone":"+1 352 687 8200",
    "sg:postcode":"34472",
    "sg:province":"FL",
    "sg:tags":[
        "grocer"
    ],
    "wof:name":"Publix Super Market",
    "wof:placetype":"venue"
},
  "geometry": {"coordinates":[-82.02076,29.111984],"type":"Point"}
}