{
  "type": "Feature",
  "properties": {
    "iso:country":"US",
    "sg:address":"6985 Scarboro Dr",
    "sg:city":"Fort Myers",
    "sg:classifiers":[
        {
            "category":"Personal",
            "type":"Services"
        }
    ],
    "sg:phone":"+1 239 482 6848",
    "sg:postcode":"33919",
    "sg:province":"FL",
    "sg:tags":[
        "miscellaneous"
    ],
    "wof:name":"Val's Service",
    "wof:placetype":"venue"
},
  "geometry": {"coordinates":[-81.90133,26.525069],"type":"Point"}
}