{
  "type": "Feature",
  "properties": {
    "iso:country":"US",
    "sg:address":"1601 NE 163rd St",
    "sg:city":"North Miami Bch",
    "sg:classifiers":[
        {
            "category":"Real Estate",
            "subcategory":"Real Estate Agent",
            "type":"Services"
        }
    ],
    "sg:phone":"+1 305 638 2452",
    "sg:postcode":"33162",
    "sg:province":"FL",
    "sg:tags":[
        "management"
    ],
    "wof:name":"Newport Management",
    "wof:placetype":"venue"
},
  "geometry": {"coordinates":[-80.16600699999999,25.925842],"type":"Point"}
}