{
  "type": "Feature",
  "properties": {
    "addr:full":"9450 Listow Ter Boynton Beach FL 33472",
    "addr:postcode":"9450;33472",
    "addr:street":"Listow Ter",
    "iso:country":"US",
    "sg:address":"9450 Listow Ter",
    "sg:city":"Boynton Beach",
    "sg:classifiers":[
        {
            "category":"Building & Trades",
            "subcategory":"Construction",
            "type":"Services"
        }
    ],
    "sg:phone":"+1 561 742 5992",
    "sg:postcode":"33472",
    "sg:province":"FL",
    "sg:tags":[
        "builder",
        "patio",
        "deck"
    ],
    "wof:name":"A Chatt Away LLC",
    "wof:placetype":"venue"
},
  "geometry": {"coordinates":[-80.19718,26.554626],"type":"Point"}
}