{
  "type": "Feature",
  "properties": {
    "addr:full":"16828 Silver Shores Ln Odessa FL 33556",
    "addr:housenumber":"16828",
    "addr:postcode":"33556",
    "addr:street":"Silver Shores Ln",
    "iso:country":"US",
    "sg:address":"16828 Silver Shores Ln",
    "sg:city":"Odessa",
    "sg:classifiers":[
        {
            "category":"Restaurant",
            "type":"Food & Drink"
        }
    ],
    "sg:phone":"+1 813 920 9978",
    "sg:postcode":"33556",
    "sg:province":"FL",
    "sg:tags":[
        "american"
    ],
    "wof:name":"Benedicts Restaurant",
    "wof:placetype":"venue"
},
  "geometry": {"coordinates":[-82.640005,28.113846],"type":"Point"}
}