{
  "type": "Feature",
  "properties": {
    "addr:full":"13208 SW 8th St Miami FL 33184",
    "addr:housenumber":"13208",
    "addr:postcode":"33184",
    "addr:street":"Sw 8Th St",
    "iso:country":"US",
    "sg:address":"13208 SW 8th St",
    "sg:city":"Miami",
    "sg:classifiers":[
        {
            "category":"Personal",
            "subcategory":"Massage",
            "type":"Services"
        }
    ],
    "sg:phone":"+1 305 222 9992",
    "sg:postcode":"33184",
    "sg:province":"FL",
    "sg:tags":[
        "therapist"
    ],
    "wof:name":"South Dade Massage",
    "wof:placetype":"venue"
},
  "geometry": {"coordinates":[-80.40997400000001,25.760871],"type":"Point"}
}