{
  "type": "Feature",
  "properties": {
    "addr:full":"10206 Devonshire Lake Dr Tampa FL 33647",
    "addr:housenumber":"10206",
    "addr:postcode":"33647",
    "addr:street":"Devonshire Lake Dr",
    "iso:country":"US",
    "sg:address":"10206 Devonshire Lake Dr",
    "sg:city":"Tampa",
    "sg:classifiers":[
        {
            "category":"Professional",
            "type":"Services"
        }
    ],
    "sg:phone":"+1 813 973 7165",
    "sg:postcode":"33647",
    "sg:province":"FL",
    "wof:name":"Adfap LLC",
    "wof:placetype":"venue"
},
  "geometry": {"coordinates":[-82.318776,28.140057],"type":"Point"}
}