{
  "type": "Feature",
  "properties": {
    "iso:country":"US",
    "sg:address":"1609 SW 67th Ave",
    "sg:city":"Miami",
    "sg:classifiers":[
        {
            "category":"Wholesale",
            "subcategory":"Apparel",
            "type":"Manufacturing & Wholesale Goods"
        }
    ],
    "sg:phone":"+1 305 260 0633",
    "sg:postcode":"33155",
    "sg:province":"FL",
    "sg:tags":[
        "clothing"
    ],
    "wof:name":"Manuel Fornaris",
    "wof:placetype":"venue"
},
  "geometry": {"coordinates":[-80.30359799999999,25.753972],"type":"Point"}
}