{
  "type": "Feature",
  "properties": {
    "addr:full":"8910 Front Beach Rd Panama City FL 32407",
    "addr:housenumber":"8910",
    "addr:postcode":"32407",
    "addr:street":"Front Beach Rd",
    "iso:country":"US",
    "sg:address":"8910 Front Beach Rd",
    "sg:city":"Panama City",
    "sg:classifiers":[
        {
            "category":"Organizations",
            "subcategory":"Religious Organization",
            "type":"Services"
        }
    ],
    "sg:phone":"+1 850 234 2521",
    "sg:postcode":"32407",
    "sg:province":"FL",
    "sg:tags":[
        "church"
    ],
    "wof:name":"Beach Church Of Christ",
    "wof:placetype":"venue"
},
  "geometry": {"coordinates":[-85.785926,30.18243],"type":"Point"}
}