{
  "type": "Feature",
  "properties": {
    "addr:full":"1153 SE Pruitt Rd Port St Lucie FL 34952",
    "addr:housenumber":"1153",
    "addr:postcode":"34952",
    "addr:street":"Se Pruitt Rd;St",
    "iso:country":"US",
    "sg:address":"1153 SE Pruitt Rd",
    "sg:city":"Port St Lucie",
    "sg:classifiers":[
        {
            "category":"Personal",
            "subcategory":"Tanning Parlor",
            "type":"Services"
        }
    ],
    "sg:phone":"+1 772 335 3881",
    "sg:postcode":"34952",
    "sg:province":"FL",
    "sg:tags":[
        "salon"
    ],
    "wof:name":"Tropical Tanning Zone Inc",
    "wof:placetype":"venue"
},
  "geometry": {"coordinates":[-80.317618,27.258096],"type":"Point"}
}