{
  "type": "Feature",
  "properties": {
    "iso:country":"US",
    "sg:address":"2542 SW 27th Ave",
    "sg:city":"Miami",
    "sg:classifiers":[
        {
            "category":"Restaurant",
            "type":"Food & Drink"
        },
        {
            "category":"Food & Beverages",
            "subcategory":"Bakery",
            "type":"Retail Goods"
        }
    ],
    "sg:phone":"+1 305 443 6672",
    "sg:postcode":"33133",
    "sg:province":"FL",
    "sg:tags":[
        "cuban",
        "sandwich"
    ],
    "wof:name":"Mary Coin Laundry/Deli's",
    "wof:placetype":"venue"
},
  "geometry": {"coordinates":[-80.238197,25.7446],"type":"Point"}
}