{
  "type": "Feature",
  "properties": {
    "iso:country":"US",
    "sg:address":"2581 Palm Ave",
    "sg:city":"Fort Myers",
    "sg:classifiers":[
        {
            "category":"Social Services",
            "type":"Services"
        }
    ],
    "sg:phone":"+1 239 337 0955",
    "sg:postcode":"33916",
    "sg:province":"FL",
    "sg:tags":[
        "organization",
        "welfare"
    ],
    "wof:name":"Salvation Army",
    "wof:placetype":"venue"
},
  "geometry": {"coordinates":[-81.85616400000001,26.633321],"type":"Point"}
}