{
  "type": "Feature",
  "properties": {
    "iso:country":"US",
    "sg:address":"200 Capital Cir SE",
    "sg:city":"Tallahassee",
    "sg:classifiers":[
        {
            "category":"Home & Garden",
            "subcategory":"Carpets & Floor Coverings",
            "type":"Retail Goods"
        }
    ],
    "sg:phone":"+1 850 878 1442",
    "sg:postcode":"32305",
    "sg:province":"FL",
    "sg:tags":[
        "furniture"
    ],
    "wof:name":"Rug & Carpet Outlet",
    "wof:placetype":"venue"
},
  "geometry": {"coordinates":[-84.282326,30.375989],"type":"Point"}
}