{
  "type": "Feature",
  "properties": {
    "iso:country":"US",
    "sg:address":"20295 NE 29th Ct",
    "sg:city":"Miami",
    "sg:classifiers":[
        {
            "category":"Health Services",
            "subcategory":"Doctor",
            "type":"Services"
        }
    ],
    "sg:phone":"+1 305 932 7366",
    "sg:postcode":"33180",
    "sg:province":"FL",
    "sg:tags":[
        "medical"
    ],
    "wof:name":"Kenneth Hodor Dr",
    "wof:placetype":"venue"
},
  "geometry": {"coordinates":[-80.142366,25.962264],"type":"Point"}
}