{
  "type": "Feature",
  "properties": {
    "iso:country":"US",
    "sg:address":"1605 Euclid Ave",
    "sg:city":"Miami Beach",
    "sg:classifiers":[
        {
            "category":"Real Estate",
            "subcategory":"Real Estate Operator",
            "type":"Services"
        }
    ],
    "sg:phone":"+1 305 673 2988",
    "sg:postcode":"33139",
    "sg:province":"FL",
    "sg:tags":[
        "condominium"
    ],
    "wof:name":"Norma Condominium",
    "wof:placetype":"venue"
},
  "geometry": {"coordinates":[-80.13533099999999,25.789883],"type":"Point"}
}