{
  "type": "Feature",
  "properties": {
    "iso:country":"US",
    "sg:address":"804 Palmetto St",
    "sg:city":"Clearwater",
    "sg:classifiers":[
        {
            "category":"Organizations",
            "subcategory":"Religious Organization",
            "type":"Services"
        }
    ],
    "sg:phone":"+1 727 446 3576",
    "sg:postcode":"33755",
    "sg:province":"FL",
    "sg:tags":[
        "church"
    ],
    "wof:name":"Alpha & Omega Inc",
    "wof:placetype":"venue"
},
  "geometry": {"coordinates":[-82.795393,27.97552],"type":"Point"}
}