{
  "type": "Feature",
  "properties": {
    "addr:full":"10119 Ringling St New Port Richey FL 34655",
    "addr:postcode":"10119;34655",
    "addr:street":"Ringling St",
    "iso:country":"US",
    "sg:address":"10119 Ringling St",
    "sg:city":"New Port Richey",
    "sg:classifiers":[
        {
            "category":"Building & Trades",
            "subcategory":"Landscaping Services",
            "type":"Services"
        }
    ],
    "sg:phone":"+1 727 372 3700",
    "sg:postcode":"34655",
    "sg:province":"FL",
    "sg:tags":[
        "tree"
    ],
    "wof:name":"A Cushman Tree Svc",
    "wof:placetype":"venue"
},
  "geometry": {"coordinates":[-82.646902,28.209742],"type":"Point"}
}