{
  "type": "Feature",
  "properties": {
    "addr:full":"2350 SW 84th Ave Miramar FL 33025",
    "addr:housenumber":"2350",
    "addr:postcode":"33025",
    "addr:street":"Sw 84Th Ave",
    "iso:country":"US",
    "sg:address":"2350 SW 84th Ave",
    "sg:city":"Miramar",
    "sg:classifiers":[
        {
            "category":"Building & Trades",
            "subcategory":"Construction",
            "type":"Services"
        }
    ],
    "sg:phone":"+1 954 441 7424",
    "sg:postcode":"33025",
    "sg:province":"FL",
    "sg:tags":[
        "company"
    ],
    "wof:name":"Bea Construction",
    "wof:placetype":"venue"
},
  "geometry": {"coordinates":[-80.254143,25.988673],"type":"Point"}
}