{
  "type": "Feature",
  "properties": {
    "iso:country":"US",
    "sg:address":"2202 Curry Ford Rd",
    "sg:city":"Orlando",
    "sg:classifiers":[
        {
            "category":"Professional",
            "subcategory":"Computer Services",
            "type":"Services"
        }
    ],
    "sg:phone":"+1 407 898 0152",
    "sg:postcode":"32806",
    "sg:province":"FL",
    "sg:tags":[
        "repair"
    ],
    "wof:name":"Eldatapronet",
    "wof:placetype":"venue"
},
  "geometry": {"coordinates":[-81.352941,28.524013],"type":"Point"}
}