{
  "type": "Feature",
  "properties": {
    "addr:full":"3400 Burns Rd Palm Beach Gardens FL 33410",
    "addr:housenumber":"3400",
    "addr:postcode":"33410",
    "addr:street":"Burns Rd",
    "iso:country":"US",
    "sg:address":"3400 Burns Rd",
    "sg:city":"Palm Beach Gardens",
    "sg:classifiers":[
        {
            "category":"Health Services",
            "subcategory":"Doctor",
            "type":"Services"
        }
    ],
    "sg:phone":"+1 561 694 1101",
    "sg:postcode":"33410",
    "sg:province":"FL",
    "sg:tags":[
        "physician",
        "surgeon",
        "medical"
    ],
    "wof:name":"Jose R De Olazabal MD",
    "wof:placetype":"venue"
},
  "geometry": {"coordinates":[-80.089676,26.830586],"type":"Point"}
}