{
  "type": "Feature",
  "properties": {
    "iso:country":"US",
    "sg:address":"227 SE 3rd St",
    "sg:city":"Dania",
    "sg:classifiers":[
        {
            "category":"Building & Trades",
            "subcategory":"Construction",
            "type":"Services"
        }
    ],
    "sg:phone":"+1 954 926 7666",
    "sg:postcode":"33004",
    "sg:province":"FL",
    "sg:tags":[
        "kitchen",
        "contractor"
    ],
    "wof:name":"Kitchen Tune-Up",
    "wof:placetype":"venue"
},
  "geometry": {"coordinates":[-80.139954,26.046886],"type":"Point"}
}