{
  "type": "Feature",
  "properties": {
    "iso:country":"US",
    "sg:address":"3089 Bluebrook Dr",
    "sg:city":"Winter Park",
    "sg:classifiers":[
        {
            "category":"Professional",
            "subcategory":"Computer Services",
            "type":"Services"
        }
    ],
    "sg:phone":"+1 407 678 9513",
    "sg:postcode":"32792",
    "sg:province":"FL",
    "sg:tags":[
        "datum"
    ],
    "wof:name":"Pitt Interactive Inc",
    "wof:placetype":"venue"
},
  "geometry": {"coordinates":[-81.28429300000001,28.588021],"type":"Point"}
}