{
  "type": "Feature",
  "properties": {
    "addr:full":"540 SW 78th Pl Miami FL 33144",
    "addr:housenumber":"540",
    "addr:postcode":"33144",
    "addr:street":"Sw 78Th Pl",
    "iso:country":"US",
    "sg:address":"540 SW 78th Pl",
    "sg:city":"Miami",
    "sg:classifiers":[
        {
            "category":"Building & Trades",
            "subcategory":"Construction",
            "type":"Services"
        }
    ],
    "sg:phone":"+1 305 262 8089",
    "sg:postcode":"33144",
    "sg:province":"FL",
    "sg:tags":[
        "carpentry",
        "contractor"
    ],
    "wof:name":"Victor Garage Doors Inc",
    "wof:placetype":"venue"
},
  "geometry": {"coordinates":[-80.323627,25.763477],"type":"Point"}
}