{
  "type": "Feature",
  "properties": {
    "iso:country":"US",
    "sg:address":"8072 Old Kings Rd S",
    "sg:city":"Jacksonville",
    "sg:classifiers":[
        {
            "category":"Autos & Motor Vehicles",
            "subcategory":"Fuel & Gas Station",
            "type":"Retail Goods"
        }
    ],
    "sg:phone":"+1 904 733 5998",
    "sg:postcode":"32217",
    "sg:province":"FL",
    "sg:tags":[
        "oil"
    ],
    "wof:name":"J & T's Food Store",
    "wof:placetype":"venue"
},
  "geometry": {"coordinates":[-81.60448599999999,30.233269],"type":"Point"}
}