{
  "type": "Feature",
  "properties": {
    "addr:full":"2689 Kerwood Cir Orlando FL 32810",
    "addr:housenumber":"2689",
    "addr:postcode":"32810",
    "addr:street":"Kerwood Cir",
    "iso:country":"US",
    "sg:address":"2689 Kerwood Cir",
    "sg:city":"Orlando",
    "sg:classifiers":[
        {
            "category":"Building & Trades",
            "subcategory":"Construction",
            "type":"Services"
        }
    ],
    "sg:phone":"+1 407 522 6467",
    "sg:postcode":"32810",
    "sg:province":"FL",
    "sg:tags":[
        "floor",
        "laying",
        "contractor"
    ],
    "wof:name":"AAA Duran Flooring Inc",
    "wof:placetype":"venue"
},
  "geometry": {"coordinates":[-81.412252,28.621897],"type":"Point"}
}