{
  "type": "Feature",
  "properties": {
    "iso:country":"US",
    "sg:address":"70 NW 36th St",
    "sg:city":"Miami",
    "sg:classifiers":[
        {
            "category":"Autos & Motor Vehicles",
            "subcategory":"Automobile Sales",
            "type":"Retail Goods"
        },
        {
            "category":"Retail",
            "subcategory":"Auto Repair",
            "type":"Services"
        }
    ],
    "sg:phone":"+1 305 576 1398",
    "sg:postcode":"33127",
    "sg:province":"FL",
    "sg:tags":[
        "dealers-used",
        "car",
        "used",
        "cars-wholesale"
    ],
    "sg:website":"http://www.universalautocenter.com",
    "wof:name":"Universal Auto Center",
    "wof:placetype":"venue"
},
  "geometry": {"coordinates":[-80.196461,25.810392],"type":"Point"}
}