{
  "type": "Feature",
  "properties": {
    "addr:full":"8260 NW 27th St Ste 410 Doral FL 33122",
    "addr:housenumber":"8260",
    "addr:postcode":"33122",
    "addr:street":"Nw 27Th St Ste 410",
    "iso:country":"US",
    "sg:address":"8260 NW 27th St Ste 410",
    "sg:city":"Doral",
    "sg:classifiers":[
        {
            "category":"Shopping",
            "subcategory":"Stationery & Office Supplies",
            "type":"Retail Goods"
        },
        {
            "category":"Professional",
            "subcategory":"Employment Agencies",
            "type":"Services"
        },
        {
            "category":"Manufacturing",
            "subcategory":"Paper Products",
            "type":"Manufacturing & Wholesale Goods"
        }
    ],
    "sg:phone":"+1 305 717 6004",
    "sg:postcode":"33122",
    "sg:province":"FL",
    "sg:tags":[
        "labels-wholesale",
        "labels-plastic",
        "metal",
        "label",
        "foil",
        "manufacturer"
    ],
    "sg:website":"http://www.tradesmeninternational.com",
    "wof:name":"Tradesmen International",
    "wof:placetype":"venue"
},
  "geometry": {"coordinates":[-80.331001,25.798401],"type":"Point"}
}