{
  "type": "Feature",
  "properties": {
    "iso:country":"US",
    "sg:address":"3717 Lydia Estates Dr N",
    "sg:city":"Jacksonville",
    "sg:classifiers":[
        {
            "category":"Shopping",
            "subcategory":"Clothing, Apparel, & Fashions",
            "type":"Retail Goods"
        }
    ],
    "sg:phone":"+1 904 713 8437",
    "sg:postcode":"32218",
    "sg:province":"FL",
    "wof:name":"Shahada Menswear",
    "wof:placetype":"venue"
},
  "geometry": {"coordinates":[-81.707911,30.438066],"type":"Point"}
}