{
  "type": "Feature",
  "properties": {
    "iso:country":"US",
    "sg:address":"526 N G St",
    "sg:city":"Lake Worth",
    "sg:classifiers":[
        {
            "category":"Retail",
            "subcategory":"Repair Shop",
            "type":"Services"
        }
    ],
    "sg:phone":"+1 561 586 4334",
    "sg:postcode":"33460",
    "sg:province":"FL",
    "sg:tags":[
        "warranty",
        "cooler",
        "water",
        "sales",
        "doe"
    ],
    "wof:name":"Douglas Jim Water Cooler Svc",
    "wof:placetype":"venue"
},
  "geometry": {"coordinates":[-80.059038,26.622435],"type":"Point"}
}