{
  "type": "Feature",
  "properties": {
    "iso:country":"US",
    "sg:address":"123 N Kentucky Ave",
    "sg:city":"Lakeland",
    "sg:classifiers":[
        {
            "category":"Professional",
            "subcategory":"Lawyer & Legal Services",
            "type":"Services"
        }
    ],
    "sg:phone":"+1 863 802 4015",
    "sg:postcode":"33801",
    "sg:province":"FL",
    "wof:name":"Sites William D Law Offices",
    "wof:placetype":"venue"
},
  "geometry": {"coordinates":[-81.955118,28.044834],"type":"Point"}
}