{
  "type": "Feature",
  "properties": {
    "addr:full":"301 Flagler Ave New Smyrna Beach FL 32169",
    "addr:housenumber":"301",
    "addr:postcode":"32169",
    "addr:street":"Flagler Ave",
    "iso:country":"US",
    "sg:address":"301 Flagler Ave",
    "sg:city":"New Smyrna Beach",
    "sg:classifiers":[
        {
            "category":"Real Estate",
            "subcategory":"Real Estate Agent",
            "type":"Services"
        }
    ],
    "sg:phone":"+1 386 427 2622",
    "sg:postcode":"32169",
    "sg:province":"FL",
    "wof:name":"Prudential Florida Real Estate",
    "wof:placetype":"venue"
},
  "geometry": {"coordinates":[-80.898731,29.038555],"type":"Point"}
}