{
  "type": "Feature",
  "properties": {
    "iso:country":"US",
    "sg:address":"1560 Monica Joy Cir",
    "sg:city":"Longwood",
    "sg:classifiers":[
        {
            "category":"Building & Trades",
            "subcategory":"Plumbing",
            "type":"Services"
        }
    ],
    "sg:phone":"+1 407 869 9449",
    "sg:postcode":"32779",
    "sg:province":"FL",
    "sg:tags":[
        "plumbing",
        "contractor"
    ],
    "wof:name":"STAR MANAGEMENT",
    "wof:placetype":"venue"
},
  "geometry": {"coordinates":[-81.43107500000001,28.686577],"type":"Point"}
}