{
  "type": "Feature",
  "properties": {
    "iso:country":"US",
    "sg:address":"2135 W Dale Cir",
    "sg:city":"De Land",
    "sg:classifiers":[
        {
            "category":"Building & Trades",
            "subcategory":"Construction",
            "type":"Services"
        }
    ],
    "sg:phone":"+1 386 738 3470",
    "sg:postcode":"32720",
    "sg:province":"FL",
    "sg:tags":[
        "house"
    ],
    "wof:name":"Home Improvement Plus & Repair",
    "wof:placetype":"venue"
},
  "geometry": {"coordinates":[-81.31354,28.979093],"type":"Point"}
}