{
  "type": "Feature",
  "properties": {
    "iso:country":"US",
    "sg:address":"441 E Central Ave",
    "sg:city":"Winter Haven",
    "sg:classifiers":[
        {
            "category":"Real Estate",
            "subcategory":"Real Estate Agent",
            "type":"Services"
        }
    ],
    "sg:phone":"+1 863 299 5878",
    "sg:postcode":"33880",
    "sg:province":"FL",
    "sg:tags":[
        "broker"
    ],
    "sg:website":"www.jbcleaves.com",
    "wof:name":"Judy B Cleaves Properties Inc",
    "wof:placetype":"venue"
},
  "geometry": {"coordinates":[-81.72155100000001,28.0223],"type":"Point"}
}