{
  "type": "Feature",
  "properties": {
    "iso:country":"US",
    "sg:address":"17400 SW 180th Ave",
    "sg:city":"Miami",
    "sg:classifiers":[
        {
            "category":"Building & Trades",
            "subcategory":"Landscaping Services",
            "type":"Services"
        }
    ],
    "sg:phone":"+1 305 234 7960",
    "sg:postcode":"33187",
    "sg:province":"FL",
    "sg:tags":[
        "designer",
        "landscape"
    ],
    "wof:name":"Nursery & Pond Co",
    "wof:placetype":"venue"
},
  "geometry": {"coordinates":[-80.484768,25.60335],"type":"Point"}
}