{
  "type": "Feature",
  "properties": {
    "addr:full":"1375 Monroe St Fort Myers FL 33901",
    "addr:housenumber":"1375",
    "addr:postcode":"33901",
    "addr:street":"Monroe St",
    "iso:country":"US",
    "sg:address":"1375 Monroe St",
    "sg:city":"Fort Myers",
    "sg:classifiers":[
        {
            "category":"Banks & Credit Unions",
            "subcategory":"Bank",
            "type":"Services"
        }
    ],
    "sg:phone":"+1 239 334 4203",
    "sg:postcode":"33901",
    "sg:province":"FL",
    "sg:tags":[
        "loan",
        "real estate"
    ],
    "wof:name":"Huntington Mortgage Co",
    "wof:placetype":"venue"
},
  "geometry": {"coordinates":[-81.872445,26.64461],"type":"Point"}
}