{
  "type": "Feature",
  "properties": {
    "addr:full":"2671 Florida St West Palm Beach FL 33406",
    "addr:housenumber":"2671",
    "addr:postcode":"33406",
    "addr:street":"Florida St",
    "iso:country":"US",
    "sg:address":"2671 Florida St",
    "sg:city":"West Palm Beach",
    "sg:classifiers":[
        {
            "category":"Government",
            "subcategory":"Office",
            "type":"Public Place"
        }
    ],
    "sg:phone":"+1 561 684 0687",
    "sg:postcode":"33406",
    "sg:province":"FL",
    "sg:tags":[
        "management"
    ],
    "wof:name":"Ragar Imp Ex Inc",
    "wof:placetype":"venue"
},
  "geometry": {"coordinates":[-80.083693,26.667089],"type":"Point"}
}