{
  "type": "Feature",
  "properties": {
    "iso:country":"US",
    "sg:address":"26850 S Bay Dr",
    "sg:city":"Bonita Springs",
    "sg:classifiers":[
        {
            "category":"Health Services",
            "subcategory":"Health Practitioner",
            "type":"Services"
        }
    ],
    "sg:phone":"+1 239 390 7118",
    "sg:postcode":"34134",
    "sg:province":"FL",
    "sg:tags":[
        "therapist",
        "physical"
    ],
    "wof:name":"Outreach Program Inc",
    "wof:placetype":"venue"
},
  "geometry": {"coordinates":[-81.808942,26.350911],"type":"Point"}
}