{
  "type": "Feature",
  "properties": {
    "iso:country":"US",
    "sg:address":"7316 SW 45th St",
    "sg:city":"Miami",
    "sg:classifiers":[
        {
            "category":"Retail",
            "subcategory":"Auto Repair",
            "type":"Services"
        }
    ],
    "sg:phone":"+1 305 267 0516",
    "sg:postcode":"33155",
    "sg:province":"FL",
    "wof:name":"G P Auto Works",
    "wof:placetype":"venue"
},
  "geometry": {"coordinates":[-80.314301,25.7286],"type":"Point"}
}