{
  "type": "Feature",
  "properties": {
    "iso:country":"US",
    "sg:address":"4428 Golf Ridge Dr",
    "sg:city":"Elkton",
    "sg:classifiers":[
        {
            "category":"Building & Trades",
            "subcategory":"Construction",
            "type":"Services"
        }
    ],
    "sg:phone":"+1 904 819 9081",
    "sg:postcode":"32033",
    "sg:province":"FL",
    "sg:tags":[
        "home",
        "builder"
    ],
    "wof:name":"KB Home",
    "wof:placetype":"venue"
},
  "geometry": {"coordinates":[-81.37982599999999,29.813129],"type":"Point"}
}