{
  "type": "Feature",
  "properties": {
    "addr:full":"3020 N Main St Gainesville FL 32609",
    "addr:housenumber":"3020",
    "addr:postcode":"32609",
    "addr:street":"N Main St",
    "iso:country":"US",
    "sg:address":"3020 N Main St",
    "sg:city":"Gainesville",
    "sg:classifiers":[
        {
            "category":"Retail",
            "subcategory":"Auto Repair",
            "type":"Services"
        }
    ],
    "sg:phone":"+1 352 376 6752",
    "sg:postcode":"32609",
    "sg:province":"FL",
    "sg:tags":[
        "repairing",
        "automobile"
    ],
    "wof:name":"Myers Service Ctr",
    "wof:placetype":"venue"
},
  "geometry": {"coordinates":[-82.319451,29.68201],"type":"Point"}
}