{
  "type": "Feature",
  "properties": {
    "iso:country":"US",
    "sg:address":"1121 Sun Century Rd",
    "sg:city":"Naples",
    "sg:classifiers":[
        {
            "category":"Freight",
            "type":"Transportation"
        }
    ],
    "sg:phone":"+1 239 593 8090",
    "sg:postcode":"34110",
    "sg:province":"FL",
    "sg:tags":[
        "mover"
    ],
    "wof:name":"Gulf Shore Moving & Crating",
    "wof:placetype":"venue"
},
  "geometry": {"coordinates":[-81.792429,26.305576],"type":"Point"}
}