{
  "type": "Feature",
  "properties": {
    "iso:country":"US",
    "sg:address":"7611 W Newberry Rd",
    "sg:city":"Gainesville",
    "sg:classifiers":[
        {
            "category":"Restaurant",
            "type":"Food & Drink"
        }
    ],
    "sg:menulink":"http://www.allmenus.com/fl/gainesville/93487-waffle-house/menu/",
    "sg:phone":"+1 352 332 5666",
    "sg:postcode":"32606",
    "sg:province":"FL",
    "sg:tags":[
        "american"
    ],
    "wof:name":"Waffle House",
    "wof:placetype":"venue"
},
  "geometry": {"coordinates":[-82.42273299999999,29.65963],"type":"Point"}
}