{
  "type": "Feature",
  "properties": {
    "addr:full":"349 Caen Ct Kissimmee FL 34759",
    "addr:housenumber":"349",
    "addr:postcode":"34759",
    "addr:street":"Caen Ct",
    "iso:country":"US",
    "sg:address":"349 Caen Ct",
    "sg:city":"Kissimmee",
    "sg:classifiers":[
        {
            "category":"Building & Trades",
            "subcategory":"Construction",
            "type":"Services"
        }
    ],
    "sg:phone":"+1 407 414 9193",
    "sg:postcode":"34759",
    "sg:province":"FL",
    "sg:tags":[
        "fence",
        "contractor"
    ],
    "wof:name":"Luis A Gerena Fences",
    "wof:placetype":"venue"
},
  "geometry": {"coordinates":[-81.449105,28.124155],"type":"Point"}
}