{
  "type": "Feature",
  "properties": {
    "addr:full":"17102 Carrington Park Dr Tampa FL 33647",
    "addr:housenumber":"17102",
    "addr:postcode":"33647",
    "addr:street":"Carrington Park Dr",
    "iso:country":"US",
    "sg:address":"17102 Carrington Park Dr",
    "sg:city":"Tampa",
    "sg:classifiers":[
        {
            "category":"Airport",
            "type":"Transportation"
        }
    ],
    "sg:phone":"+1 813 631 9050",
    "sg:postcode":"33647",
    "sg:province":"FL",
    "sg:tags":[
        "aircraft",
        "maintenance"
    ],
    "wof:name":"Ed Helicopter Svc Inc",
    "wof:placetype":"venue"
},
  "geometry": {"coordinates":[-82.381709,28.117127],"type":"Point"}
}