{
  "type": "Feature",
  "properties": {
    "iso:country":"US",
    "sg:address":"123 Tilton Dr",
    "sg:city":"San Mateo",
    "sg:classifiers":[
        {
            "category":"Farming",
            "subcategory":"Farm",
            "type":"Manufacturing & Wholesale Goods"
        }
    ],
    "sg:phone":"+1 386 328 3439",
    "sg:postcode":"32187",
    "sg:province":"FL",
    "sg:tags":[
        "crop",
        "general"
    ],
    "wof:name":"Bar C Ranch",
    "wof:placetype":"venue"
},
  "geometry": {"coordinates":[-81.549081,29.588721],"type":"Point"}
}