{
  "type": "Feature",
  "properties": {
    "iso:country":"US",
    "sg:address":"9537 Fargo Dr",
    "sg:city":"Hudson",
    "sg:classifiers":[
        {
            "category":"Travel",
            "subcategory":"Travel Agent",
            "type":"Entertainment"
        }
    ],
    "sg:phone":"+1 727 226 1109",
    "sg:postcode":"34667",
    "sg:province":"FL",
    "sg:tags":[
        "agency",
        "services-commercial"
    ],
    "wof:name":"Vacation Escape Online",
    "wof:placetype":"venue"
},
  "geometry": {"coordinates":[-82.65712600000001,28.373864],"type":"Point"}
}