{
  "type": "Feature",
  "properties": {
    "iso:country":"US",
    "sg:address":"399 Central Florida Pkwy Unit C",
    "sg:city":"Orlando",
    "sg:classifiers":[
        {
            "category":"Farming",
            "subcategory":"Fish & Marine Products",
            "type":"Manufacturing & Wholesale Goods"
        },
        {
            "category":"Manufacturing",
            "subcategory":"Glass & Minerals",
            "type":"Manufacturing & Wholesale Goods"
        }
    ],
    "sg:phone":"+1 407 967 1993",
    "sg:postcode":"32824",
    "sg:province":"FL",
    "sg:tags":[
        "fiberglass",
        "material"
    ],
    "wof:name":"Martins Manufacturing and Fabrication LLC",
    "wof:placetype":"venue"
},
  "geometry": {"coordinates":[-81.38279,28.407681],"type":"Point"}
}