{
  "type": "Feature",
  "properties": {
    "iso:country":"US",
    "sg:address":"1102 E Altamonte Dr",
    "sg:city":"Altamonte Springs",
    "sg:classifiers":[
        {
            "category":"Retail",
            "subcategory":"Repair Shop",
            "type":"Services"
        },
        {
            "category":"Shopping",
            "subcategory":"Crafts & Fabrics",
            "type":"Retail Goods"
        },
        {
            "category":"Building & Trades",
            "subcategory":"Construction",
            "type":"Services"
        }
    ],
    "sg:phone":"+1 407 767 0789",
    "sg:postcode":"32701",
    "sg:province":"FL",
    "sg:tags":[
        "interior",
        "reupholstery",
        "design",
        "store",
        "furniture"
    ],
    "sg:website":"www.calicocorners.com",
    "wof:name":"Calico Corners",
    "wof:placetype":"venue"
},
  "geometry": {"coordinates":[-81.35340100000001,28.662901],"type":"Point"}
}