{
  "type": "Feature",
  "properties": {
    "addr:full":"6415 W Colonial Dr Orlando FL 32818",
    "addr:housenumber":"6415",
    "addr:postcode":"32818",
    "addr:street":"W Colonial Dr",
    "iso:country":"US",
    "sg:address":"6415 W Colonial Dr",
    "sg:city":"Orlando",
    "sg:classifiers":[
        {
            "category":"Restaurant",
            "type":"Food & Drink"
        },
        {
            "category":"Food & Beverages",
            "subcategory":"Meat & Fish",
            "type":"Retail Goods"
        }
    ],
    "sg:phone":"+1 407 292 2722",
    "sg:postcode":"32818",
    "sg:province":"FL",
    "sg:tags":[
        "seafood",
        "market"
    ],
    "wof:name":"Seafood Heaven",
    "wof:placetype":"venue"
},
  "geometry": {"coordinates":[-81.470822,28.55212],"type":"Point"}
}