{
  "type": "Feature",
  "properties": {
    "iso:country":"US",
    "sg:address":"4911 8th Ave S",
    "sg:city":"Gulfport",
    "sg:phone":"+1 727 321 3421",
    "sg:postcode":"33707",
    "sg:province":"FL",
    "sg:tags":[
        "wholesale",
        "good",
        "gasoline",
        "oil",
        "trade"
    ],
    "sg:website":"www.fuelsmith.com",
    "wof:name":"Co-Op Fuels & Lubricants Inc",
    "wof:placetype":"venue"
},
  "geometry": {"coordinates":[-82.70100499999999,27.762432],"type":"Point"}
}