{
  "type": "Feature",
  "properties": {
    "addr:full":"12382 NW 98th Ave Hialeah FL 33018",
    "addr:housenumber":"12382",
    "addr:postcode":"33018",
    "addr:street":"Nw 98Th Ave",
    "iso:country":"US",
    "sg:address":"12382 NW 98th Ave",
    "sg:city":"Hialeah",
    "sg:classifiers":[
        {
            "category":"Manufacturing",
            "subcategory":"Building Materials",
            "type":"Manufacturing & Wholesale Goods"
        }
    ],
    "sg:phone":"+1 305 821 4825",
    "sg:postcode":"33018",
    "sg:province":"FL",
    "sg:tags":[
        "mfg",
        "wood",
        "kitchen",
        "cabinet"
    ],
    "wof:name":"Kitchen Cabinet Inc",
    "wof:placetype":"venue"
},
  "geometry": {"coordinates":[-80.35754300000001,25.884695],"type":"Point"}
}