{
  "type": "Feature",
  "properties": {
    "addr:full":"801 Brickell Ave Miami FL 33131",
    "addr:housenumber":"801",
    "addr:postcode":"33131",
    "addr:street":"Brickell Ave",
    "iso:country":"US",
    "sg:address":"801 Brickell Ave",
    "sg:city":"Miami",
    "sg:classifiers":[
        {
            "category":"Professional",
            "subcategory":"Management & Consulting",
            "type":"Services"
        }
    ],
    "sg:phone":"+1 305 789 6632",
    "sg:postcode":"33131",
    "sg:province":"FL",
    "sg:tags":[
        "commercial",
        "real estate"
    ],
    "wof:name":"St Augustine Real Advs Inc",
    "wof:placetype":"venue"
},
  "geometry": {"coordinates":[-80.19095299999999,25.765055],"type":"Point"}
}