{
  "type": "Feature",
  "properties": {
    "addr:full":"3201 Huntington Place Dr Sarasota FL 34237",
    "addr:housenumber":"3201",
    "addr:postcode":"34237",
    "addr:street":"Huntington Place Dr",
    "iso:country":"US",
    "sg:address":"3201 Huntington Place Dr",
    "sg:city":"Sarasota",
    "sg:classifiers":[
        {
            "category":"Real Estate",
            "subcategory":"Real Estate Operator",
            "type":"Services"
        }
    ],
    "sg:phone":"+1 941 951 1033",
    "sg:postcode":"34237",
    "sg:province":"FL",
    "sg:tags":[
        "building",
        "apartment"
    ],
    "wof:name":"Huntington Place",
    "wof:placetype":"venue"
},
  "geometry": {"coordinates":[-82.501492,27.34789],"type":"Point"}
}