{
  "type": "Feature",
  "properties": {
    "addr:full":"2061 Piedmont Park Blvd Apopka FL 32703",
    "addr:housenumber":"2061",
    "addr:postcode":"32703",
    "addr:street":"Piedmont Park Blvd",
    "iso:country":"US",
    "sg:address":"2061 Piedmont Park Blvd",
    "sg:city":"Apopka",
    "sg:classifiers":[
        {
            "category":"Building & Trades",
            "subcategory":"Landscaping Services",
            "type":"Services"
        }
    ],
    "sg:phone":"+1 407 814 9714",
    "sg:postcode":"32703",
    "sg:province":"FL",
    "wof:name":"Maintaining Edge Lawn Care & M",
    "wof:placetype":"venue"
},
  "geometry": {"coordinates":[-81.472645,28.650943],"type":"Point"}
}