{
  "type": "Feature",
  "properties": {
    "addr:full":"1701 SW 44th Ave Fort Lauderdale FL 33317",
    "addr:housenumber":"1701",
    "addr:postcode":"33317",
    "addr:street":"Sw 44Th Ave",
    "iso:country":"US",
    "sg:address":"1701 SW 44th Ave",
    "sg:city":"Fort Lauderdale",
    "sg:classifiers":[
        {
            "category":"Building & Trades",
            "subcategory":"Landscaping Services",
            "type":"Services"
        }
    ],
    "sg:phone":"+1 954 579 0984",
    "sg:postcode":"33317",
    "sg:province":"FL",
    "wof:name":"Roberts Lawn Service",
    "wof:placetype":"venue"
},
  "geometry": {"coordinates":[-80.20925699999999,26.097053],"type":"Point"}
}