{
  "type": "Feature",
  "properties": {
    "iso:country":"US",
    "sg:address":"420 4th Ct",
    "sg:city":"Vero Beach",
    "sg:classifiers":[
        {
            "category":"Health Services",
            "subcategory":"Nursing And Care Facility",
            "type":"Services"
        }
    ],
    "sg:phone":"+1 772 794 1778",
    "sg:postcode":"32962",
    "sg:province":"FL",
    "sg:tags":[
        "skilled"
    ],
    "wof:name":"Clare Bridge Cottage Vero Bch",
    "wof:placetype":"venue"
},
  "geometry": {"coordinates":[-80.382262,27.636289],"type":"Point"}
}