{
  "type": "Feature",
  "properties": {
    "addr:full":"3100 Areca Ave Naples FL 34112",
    "addr:postcode":"3100;34112",
    "addr:street":"Areca Ave",
    "iso:country":"US",
    "sg:address":"3100 Areca Ave",
    "sg:city":"Naples",
    "sg:classifiers":[
        {
            "category":"Retail",
            "subcategory":"Animal Services",
            "type":"Services"
        }
    ],
    "sg:phone":"+1 239 821 3324",
    "sg:postcode":"34112",
    "sg:province":"FL",
    "sg:tags":[
        "pet",
        "grooming",
        "washing"
    ],
    "wof:name":"K 9 Kuts Mobile Dog Grooming",
    "wof:placetype":"venue"
},
  "geometry": {"coordinates":[-81.76703999999999,26.121482],"type":"Point"}
}