{
  "type": "Feature",
  "properties": {
    "addr:full":"217 Lincoln Rd Miami FL 33139",
    "addr:housenumber":"217",
    "addr:postcode":"33139",
    "addr:street":"Lincoln Rd",
    "iso:country":"US",
    "sg:address":"217 Lincoln Rd",
    "sg:city":"Miami",
    "sg:classifiers":[
        {
            "category":"Shopping",
            "subcategory":"Clothing, Apparel, & Fashions",
            "type":"Retail Goods"
        }
    ],
    "sg:phone":"+1 305 673 4045",
    "sg:postcode":"33139",
    "sg:province":"FL",
    "sg:tags":[
        "clothing",
        "women's"
    ],
    "sg:website":"www.justmensclothing.com",
    "wof:name":"Moda Xpress",
    "wof:placetype":"venue"
},
  "geometry": {"coordinates":[-80.130228,25.790716],"type":"Point"}
}