{
  "type": "Feature",
  "properties": {
    "iso:country":"US",
    "sg:address":"7452 Faculty Dr",
    "sg:city":"Orlando",
    "sg:classifiers":[
        {
            "category":"Professional",
            "subcategory":"Business Services",
            "type":"Services"
        }
    ],
    "sg:phone":"+1 407 671 3237",
    "sg:postcode":"32807",
    "sg:province":"FL",
    "sg:tags":[
        "interior",
        "consultant",
        "design",
        "decorator"
    ],
    "wof:name":"Custom Sewn Products",
    "wof:placetype":"venue"
},
  "geometry": {"coordinates":[-81.28745499999999,28.582323],"type":"Point"}
}