{
  "type": "Feature",
  "properties": {
    "iso:country":"US",
    "sg:address":"4940 Oak Island Rd",
    "sg:city":"Orlando",
    "sg:classifiers":[
        {
            "category":"Building & Trades",
            "subcategory":"Construction",
            "type":"Services"
        }
    ],
    "sg:phone":"+1 407 251 9977",
    "sg:postcode":"32809",
    "sg:province":"FL",
    "sg:tags":[
        "warehouse",
        "industrial"
    ],
    "wof:name":"Snl Construction",
    "wof:placetype":"venue"
},
  "geometry": {"coordinates":[-81.35227399999999,28.487261],"type":"Point"}
}