{
  "type": "Feature",
  "properties": {
    "iso:country":"US",
    "sg:address":"3557 US Hwy 441",
    "sg:city":"Okeechobee",
    "sg:classifiers":[
        {
            "category":"Retail",
            "subcategory":"Laundry & Dry Cleaning",
            "type":"Services"
        }
    ],
    "sg:phone":"+1 863 763 6686",
    "sg:postcode":"34974",
    "sg:province":"FL",
    "wof:name":"North Lake Wash Bowl",
    "wof:placetype":"venue"
},
  "geometry": {"coordinates":[-80.792332,27.209925],"type":"Point"}
}