{
  "type": "Feature",
  "properties": {
    "iso:country":"US",
    "sg:address":"3233 Commerce Pl",
    "sg:city":"West Palm Beach",
    "sg:classifiers":[
        {
            "category":"Real Estate",
            "subcategory":"Real Estate Services",
            "type":"Services"
        }
    ],
    "sg:phone":"+1 561 688 0665",
    "sg:postcode":"33407",
    "sg:province":"FL",
    "wof:name":"First American Title Ins Co",
    "wof:placetype":"venue"
},
  "geometry": {"coordinates":[-80.10105,26.761563],"type":"Point"}
}