{
  "type": "Feature",
  "properties": {
    "addr:full":"1111 NE 25th Ave Ocala FL 34470",
    "addr:housenumber":"1111",
    "addr:postcode":"34470",
    "addr:street":"Ne 25Th Ave",
    "iso:country":"US",
    "sg:address":"1111 NE 25th Ave",
    "sg:city":"Ocala",
    "sg:classifiers":[
        {
            "category":"Professional",
            "subcategory":"Lawyer & Legal Services",
            "type":"Services"
        }
    ],
    "sg:phone":"+1 352 401 7671",
    "sg:postcode":"34470",
    "sg:province":"FL",
    "sg:tags":[
        "attorney"
    ],
    "wof:name":"James P Tarquin Law Offices",
    "wof:placetype":"venue"
},
  "geometry": {"coordinates":[-82.10321,29.199599],"type":"Point"}
}