{
  "type": "Feature",
  "properties": {
    "addr:full":"1675 S John Rodes Blvd Melbourne FL 32904",
    "addr:housenumber":"1675",
    "addr:postcode":"32904",
    "addr:street":"S John Rodes Blvd",
    "iso:country":"US",
    "sg:address":"1675 S John Rodes Blvd",
    "sg:city":"Melbourne",
    "sg:classifiers":[
        {
            "category":"Autos & Motor Vehicles",
            "subcategory":"Automobile Sales",
            "type":"Retail Goods"
        }
    ],
    "sg:phone":"+1 321 729 6177",
    "sg:postcode":"32904",
    "sg:province":"FL",
    "wof:name":"Hams Auto Center",
    "wof:placetype":"venue"
},
  "geometry": {"coordinates":[-80.700254,28.079347],"type":"Point"}
}