{
  "type": "Feature",
  "properties": {
    "addr:full":"401 State Hwy 26 Melrose FL 32666",
    "addr:housenumber":"401",
    "addr:postcode":"32666",
    "addr:street":"State Hwy 26",
    "iso:country":"US",
    "sg:address":"401 State Hwy 26",
    "sg:city":"Melrose",
    "sg:classifiers":[
        {
            "category":"Education",
            "subcategory":"School",
            "type":"Public Place"
        }
    ],
    "sg:phone":"+1 352 475 2060",
    "sg:postcode":"32666",
    "sg:province":"FL",
    "sg:website":"www.putnamschools.org",
    "wof:name":"Melrose Elementary School",
    "wof:placetype":"venue"
},
  "geometry": {"coordinates":[-82.03934,29.71021],"type":"Point"}
}