{
  "type": "Feature",
  "properties": {
    "iso:country":"US",
    "sg:address":"823 Navy St",
    "sg:city":"Fort Walton Bch",
    "sg:classifiers":[
        {
            "category":"Shopping",
            "type":"Retail Goods"
        },
        {
            "category":"Wholesale",
            "subcategory":"Durable Goods & Equipment",
            "type":"Manufacturing & Wholesale Goods"
        }
    ],
    "sg:phone":"+1 850 862 7812",
    "sg:postcode":"32547",
    "sg:province":"FL",
    "sg:tags":[
        "fire",
        "extinguisher"
    ],
    "sg:website":"www.bcfiresafety.com",
    "wof:name":"B & C Fire Safety Inc",
    "wof:placetype":"venue"
},
  "geometry": {"coordinates":[-86.626498,30.446452],"type":"Point"}
}