{
  "type": "Feature",
  "properties": {
    "addr:full":"2345 Success Dr Odessa FL 33556",
    "addr:housenumber":"2345",
    "addr:postcode":"33556",
    "addr:street":"Success Dr",
    "iso:country":"US",
    "sg:address":"2345 Success Dr",
    "sg:city":"Odessa",
    "sg:classifiers":[
        {
            "category":"Building & Trades",
            "subcategory":"Electrical",
            "type":"Services"
        }
    ],
    "sg:phone":"+1 727 372 6620",
    "sg:postcode":"33556",
    "sg:province":"FL",
    "sg:tags":[
        "electrical",
        "electric",
        "contractor"
    ],
    "wof:name":"Cavalry Electric Company Inc",
    "wof:placetype":"venue"
},
  "geometry": {"coordinates":[-82.62645000000001,28.191608],"type":"Point"}
}