{
  "type": "Feature",
  "properties": {
    "addr:full":"3070 Pga Blvd Navarre FL 32566",
    "addr:housenumber":"3070",
    "addr:postcode":"32566",
    "addr:street":"Pga Blvd",
    "iso:country":"US",
    "sg:address":"3070 Pga Blvd",
    "sg:city":"Navarre",
    "sg:classifiers":[
        {
            "category":"Restaurant",
            "type":"Food & Drink"
        }
    ],
    "sg:phone":"+1 850 939 5400",
    "sg:postcode":"32566",
    "sg:province":"FL",
    "wof:name":"Abner's Restaurant",
    "wof:placetype":"venue"
},
  "geometry": {"coordinates":[-86.923613,30.437872],"type":"Point"}
}