{
  "type": "Feature",
  "properties": {
    "addr:full":"2300 Milton Ln Deland FL 32724",
    "addr:housenumber":"2300",
    "addr:postcode":"32724",
    "addr:street":"Milton Ln",
    "iso:country":"US",
    "sg:address":"2300 Milton Ln",
    "sg:city":"Deland",
    "sg:classifiers":[
        {
            "category":"Shopping",
            "subcategory":"Hobbies, Toys, & Games",
            "type":"Retail Goods"
        }
    ],
    "sg:phone":"+1 386 738 7150",
    "sg:postcode":"32724",
    "sg:province":"FL",
    "sg:tags":[
        "craft"
    ],
    "wof:name":"Country Crafts & Gifts",
    "wof:placetype":"venue"
},
  "geometry": {"coordinates":[-81.255724,29.048087],"type":"Point"}
}