{
  "type": "Feature",
  "properties": {
    "iso:country":"US",
    "sg:address":"404 N Barrie Rd",
    "sg:city":"Avon Park",
    "sg:classifiers":[
        {
            "category":"Building & Trades",
            "subcategory":"Cleaning & Sanitation",
            "type":"Services"
        }
    ],
    "sg:phone":"+1 863 452 9099",
    "sg:postcode":"33825",
    "sg:province":"FL",
    "sg:tags":[
        "janitor"
    ],
    "wof:name":"Timothy Caldwell Cleaning Svc",
    "wof:placetype":"venue"
},
  "geometry": {"coordinates":[-81.53730400000001,27.59984],"type":"Point"}
}