{
  "type": "Feature",
  "properties": {
    "iso:country":"US",
    "sg:address":"1769 NW 79th Ave",
    "sg:city":"Miami",
    "sg:classifiers":[
        {
            "category":"Insurance",
            "subcategory":"Insurance Agent",
            "type":"Services"
        }
    ],
    "sg:phone":"+1 305 715 0090",
    "sg:postcode":"33126",
    "sg:province":"FL",
    "sg:tags":[
        "adjuster"
    ],
    "wof:name":"Statewide Adjusters Inc",
    "wof:placetype":"venue"
},
  "geometry": {"coordinates":[-80.323988,25.7901],"type":"Point"}
}