{
  "type": "Feature",
  "properties": {
    "addr:full":"1295 SE Dixie Cutoff Rd Stuart FL 34994",
    "addr:housenumber":"1295",
    "addr:postcode":"34994",
    "addr:street":"Se Dixie Cutoff Rd",
    "iso:country":"US",
    "sg:address":"1295 SE Dixie Cutoff Rd",
    "sg:city":"Stuart",
    "sg:classifiers":[
        {
            "category":"Building & Trades",
            "subcategory":"Construction",
            "type":"Services"
        }
    ],
    "sg:phone":"+1 772 220 3625",
    "sg:postcode":"34994",
    "sg:province":"FL",
    "sg:tags":[
        "designer",
        "marine",
        "contractor"
    ],
    "wof:name":"Plaza Marine",
    "wof:placetype":"venue"
},
  "geometry": {"coordinates":[-80.245304,27.186668],"type":"Point"}
}