{
  "type": "Feature",
  "properties": {
    "iso:country":"US",
    "sg:address":"7911 NW 72nd Ave",
    "sg:city":"Medley",
    "sg:classifiers":[
        {
            "category":"Wholesale",
            "subcategory":"Medical Equipment & Supplies",
            "type":"Manufacturing & Wholesale Goods"
        }
    ],
    "sg:phone":"+1 305 231 7177",
    "sg:postcode":"33166",
    "sg:province":"FL",
    "sg:tags":[
        "physician",
        "surgeon"
    ],
    "wof:name":"Goldstar Medical & Hosp Supply",
    "wof:placetype":"venue"
},
  "geometry": {"coordinates":[-80.314283,25.846408],"type":"Point"}
}