{
  "type": "Feature",
  "properties": {
    "addr:full":"12651 Metro Pkwy Fort Myers FL 33966",
    "addr:housenumber":"12651",
    "addr:postcode":"33966",
    "addr:street":"Metro Pkwy",
    "iso:country":"US",
    "sg:address":"12651 Metro Pkwy",
    "sg:city":"Fort Myers",
    "sg:classifiers":[
        {
            "category":"Building & Trades",
            "subcategory":"Construction",
            "type":"Services"
        }
    ],
    "sg:phone":"+1 239 561 7500",
    "sg:postcode":"33966",
    "sg:province":"FL",
    "sg:tags":[
        "house",
        "general",
        "contractor"
    ],
    "sg:website":"www.advantagebuilders.com",
    "wof:name":"Advantage Builders",
    "wof:placetype":"venue"
},
  "geometry": {"coordinates":[-81.852611,26.548805],"type":"Point"}
}