{
  "type": "Feature",
  "properties": {
    "iso:country":"US",
    "sg:address":"112 NW 12th St",
    "sg:city":"Homestead",
    "sg:classifiers":[
        {
            "category":"Social Services",
            "type":"Services"
        }
    ],
    "sg:phone":"+1 305 248 2024",
    "sg:postcode":"33030",
    "sg:province":"FL",
    "sg:tags":[
        "youth",
        "organization",
        "center"
    ],
    "wof:name":"American Red Cross",
    "wof:placetype":"venue"
},
  "geometry": {"coordinates":[-80.481335,25.481608],"type":"Point"}
}