{
  "type": "Feature",
  "properties": {
    "iso:country":"US",
    "sg:address":"1450 Madruga Ave",
    "sg:city":"Coral Gables",
    "sg:classifiers":[
        {
            "category":"Health Services",
            "subcategory":"Health Practitioner",
            "type":"Services"
        }
    ],
    "sg:phone":"+1 305 662 6222",
    "sg:postcode":"33146",
    "sg:province":"FL",
    "sg:tags":[
        "psychologist"
    ],
    "wof:name":"Peyton Lumpkin White PHD",
    "wof:placetype":"venue"
},
  "geometry": {"coordinates":[-80.281899,25.709291],"type":"Point"}
}