{
  "type": "Feature",
  "properties": {
    "addr:full":"1882 Tyler St Hollywood FL 33020",
    "addr:housenumber":"1882",
    "addr:postcode":"33020",
    "addr:street":"Tyler St",
    "iso:country":"US",
    "sg:address":"1882 Tyler St",
    "sg:city":"Hollywood",
    "sg:classifiers":[
        {
            "category":"Sports & Exercise",
            "subcategory":"Gym",
            "type":"Entertainment"
        }
    ],
    "sg:phone":"+1 954 922 4208",
    "sg:postcode":"33020",
    "sg:province":"FL",
    "sg:tags":[
        "pilate"
    ],
    "wof:name":"Zen Pilates Oasis",
    "wof:placetype":"venue"
},
  "geometry": {"coordinates":[-80.144025,26.012413],"type":"Point"}
}