{
  "type": "Feature",
  "properties": {
    "iso:country":"US",
    "sg:address":"2800 Hurst Rd",
    "sg:city":"Auburndale",
    "sg:classifiers":[
        {
            "category":"Real Estate",
            "subcategory":"Real Estate Operator",
            "type":"Services"
        }
    ],
    "sg:phone":"+1 863 967 4893",
    "sg:postcode":"33823",
    "sg:province":"FL",
    "sg:tags":[
        "apartment"
    ],
    "wof:name":"Mt Vernon Apartments",
    "wof:placetype":"venue"
},
  "geometry": {"coordinates":[-81.81725299999999,28.033119],"type":"Point"}
}