{
  "type": "Feature",
  "properties": {
    "iso:country":"US",
    "sg:address":"1800 Penn St",
    "sg:city":"Melbourne",
    "sg:classifiers":[
        {
            "category":"Manufacturing",
            "subcategory":"Tools & Machinery",
            "type":"Manufacturing & Wholesale Goods"
        }
    ],
    "sg:phone":"+1 321 728 0481",
    "sg:postcode":"32901",
    "sg:province":"FL",
    "sg:tags":[
        "industry",
        "aerospace"
    ],
    "sg:website":"www.titan.com",
    "wof:name":"Titan Corp",
    "wof:placetype":"venue"
},
  "geometry": {"coordinates":[-80.653385,28.088496],"type":"Point"}
}