{
  "type": "Feature",
  "properties": {
    "iso:country":"US",
    "sg:address":"1230 S Myrtle Ave",
    "sg:city":"Clearwater",
    "sg:classifiers":[
        {
            "category":"Professional",
            "subcategory":"Lawyer & Legal Services",
            "type":"Services"
        }
    ],
    "sg:phone":"+1 727 449 1600",
    "sg:postcode":"33756",
    "sg:province":"FL",
    "sg:tags":[
        "attorney"
    ],
    "wof:name":"J Marvin Guthrie PA",
    "wof:placetype":"venue"
},
  "geometry": {"coordinates":[-82.795894,27.951923],"type":"Point"}
}