{
  "type": "Feature",
  "properties": {
    "iso:country":"US",
    "sg:address":"1190 Wendy Ct",
    "sg:city":"Spring Hill",
    "sg:classifiers":[
        {
            "category":"Retail",
            "subcategory":"Auto Repair",
            "type":"Services"
        }
    ],
    "sg:phone":"+1 352 688 2102",
    "sg:postcode":"34607",
    "sg:province":"FL",
    "sg:tags":[
        "collision"
    ],
    "wof:name":"Justices Springhill Collision",
    "wof:placetype":"venue"
},
  "geometry": {"coordinates":[-82.633235,28.450177],"type":"Point"}
}