{
  "type": "Feature",
  "properties": {
    "iso:country":"US",
    "sg:address":"20911 Johnson St",
    "sg:city":"Pembroke Pines",
    "sg:classifiers":[
        {
            "category":"Utilities",
            "subcategory":"Electric",
            "type":"Services"
        }
    ],
    "sg:phone":"+1 954 443 1232",
    "sg:postcode":"33029",
    "sg:province":"FL",
    "sg:tags":[
        "company"
    ],
    "wof:name":"Tonal Power LLC",
    "wof:placetype":"venue"
},
  "geometry": {"coordinates":[-80.432502,26.015162],"type":"Point"}
}