{
  "type": "Feature",
  "properties": {
    "iso:country":"US",
    "sg:address":"6063 NW 31st Ave",
    "sg:city":"Fort Lauderdale",
    "sg:classifiers":[
        {
            "category":"Food & Beverages",
            "subcategory":"Groceries & Convenience Stores",
            "type":"Retail Goods"
        }
    ],
    "sg:phone":"+1 954 972 9869",
    "sg:postcode":"33309",
    "sg:province":"FL",
    "wof:name":"Super Stop Food Stores",
    "wof:placetype":"venue"
},
  "geometry": {"coordinates":[-80.187994,26.20121],"type":"Point"}
}