{
  "type": "Feature",
  "properties": {
    "addr:full":"112 N Depot Dr Fort Pierce FL 34950",
    "addr:housenumber":"112",
    "addr:postcode":"34950",
    "addr:street":"N Depot Dr",
    "iso:country":"US",
    "sg:address":"112 N Depot Dr",
    "sg:city":"Fort Pierce",
    "sg:classifiers":[
        {
            "category":"Manufacturing",
            "subcategory":"Printing",
            "type":"Manufacturing & Wholesale Goods"
        }
    ],
    "sg:phone":"+1 772 595 0268",
    "sg:postcode":"34950",
    "sg:province":"FL",
    "sg:tags":[
        "book"
    ],
    "wof:name":"Long Wind Publishing LLC",
    "wof:placetype":"venue"
},
  "geometry": {"coordinates":[-80.325211,27.448367],"type":"Point"}
}