{
  "type": "Feature",
  "properties": {
    "iso:country":"US",
    "sg:address":"19955 NE 38th Ave",
    "sg:city":"Miami",
    "sg:classifiers":[
        {
            "category":"Banks & Credit Unions",
            "subcategory":"Bank",
            "type":"Services"
        }
    ],
    "sg:phone":"+1 305 932 8455",
    "sg:postcode":"33180",
    "sg:province":"FL",
    "sg:tags":[
        "personal",
        "institution"
    ],
    "wof:name":"Rkb Equity Inc",
    "wof:placetype":"venue"
},
  "geometry": {"coordinates":[-80.12441200000001,25.970143],"type":"Point"}
}