{
  "type": "Feature",
  "properties": {
    "iso:country":"US",
    "sg:address":"700 Savage Ct",
    "sg:city":"Longwood",
    "sg:classifiers":[
        {
            "category":"Wholesale",
            "subcategory":"Machinery & Supplies",
            "type":"Manufacturing & Wholesale Goods"
        },
        {
            "category":"Wholesale",
            "subcategory":"Office Equipment",
            "type":"Manufacturing & Wholesale Goods"
        }
    ],
    "sg:phone":"+1 407 331 8280",
    "sg:postcode":"32750",
    "sg:province":"FL",
    "sg:tags":[
        "machine",
        "embroidering"
    ],
    "wof:name":"American International Machine",
    "wof:placetype":"venue"
},
  "geometry": {"coordinates":[-81.36009199999999,28.696428],"type":"Point"}
}