{
  "type": "Feature",
  "properties": {
    "addr:full":"37321 Northside Dr Zephyrhills FL 33541",
    "addr:housenumber":"37321",
    "addr:postcode":"33541",
    "addr:street":"Northside Dr",
    "iso:country":"US",
    "sg:address":"37321 Northside Dr",
    "sg:city":"Zephyrhills",
    "sg:classifiers":[
        {
            "category":"Bus Charters",
            "type":"Transportation"
        }
    ],
    "sg:phone":"+1 813 782 7476",
    "sg:postcode":"33541",
    "sg:province":"FL",
    "sg:tags":[
        "rental"
    ],
    "wof:name":"Zephyr Coach Svc",
    "wof:placetype":"venue"
},
  "geometry": {"coordinates":[-82.197929,28.268405],"type":"Point"}
}