{
  "type": "Feature",
  "properties": {
    "iso:country":"US",
    "sg:address":"14040 Furman Ave",
    "sg:city":"Orlando",
    "sg:classifiers":[
        {
            "category":"Building & Trades",
            "subcategory":"Electrical",
            "type":"Services"
        }
    ],
    "sg:phone":"+1 407 384 6929",
    "sg:postcode":"32826",
    "sg:province":"FL",
    "sg:tags":[
        "electrical",
        "contractor"
    ],
    "wof:name":"Muscos Quality Alarms",
    "wof:placetype":"venue"
},
  "geometry": {"coordinates":[-81.176844,28.590385],"type":"Point"}
}