{
  "type": "Feature",
  "properties": {
    "addr:full":"361 Duxbury Ave NE Port Charlotte FL 33952",
    "addr:housenumber":"361",
    "addr:postcode":"33952",
    "addr:street":"Duxbury Ave Ne",
    "iso:country":"US",
    "sg:address":"361 Duxbury Ave NE",
    "sg:city":"Port Charlotte",
    "sg:classifiers":[
        {
            "category":"Organizations",
            "subcategory":"Religious Organization",
            "type":"Services"
        }
    ],
    "sg:phone":"+1 941 625 7738",
    "sg:postcode":"33952",
    "sg:province":"FL",
    "sg:tags":[
        "clergy"
    ],
    "wof:name":"Ray S Rutterback",
    "wof:placetype":"venue"
},
  "geometry": {"coordinates":[-82.08911000000001,26.970675],"type":"Point"}
}