{
  "type": "Feature",
  "properties": {
    "addr:full":"1416 Prospect St Palatka FL 32177",
    "addr:housenumber":"1416",
    "addr:postcode":"32177",
    "addr:street":"Prospect St",
    "iso:country":"US",
    "sg:address":"1416 Prospect St",
    "sg:city":"Palatka",
    "sg:classifiers":[
        {
            "category":"Building & Trades",
            "subcategory":"Landscaping Services",
            "type":"Services"
        }
    ],
    "sg:phone":"+1 386 328 0035",
    "sg:postcode":"32177",
    "sg:province":"FL",
    "wof:name":"Griffins Lawn Care Service",
    "wof:placetype":"venue"
},
  "geometry": {"coordinates":[-81.652761,29.636166],"type":"Point"}
}