{
  "type": "Feature",
  "properties": {
    "iso:country":"US",
    "sg:address":"4610 NW 102nd Pl",
    "sg:city":"Miami",
    "sg:classifiers":[
        {
            "category":"Wholesale",
            "subcategory":"Non-durable Goods",
            "type":"Manufacturing & Wholesale Goods"
        }
    ],
    "sg:phone":"+1 305 593 9310",
    "sg:postcode":"33178",
    "sg:province":"FL",
    "wof:name":"Habitat Trading America Corp",
    "wof:placetype":"venue"
},
  "geometry": {"coordinates":[-80.36251300000001,25.815661],"type":"Point"}
}