{
  "type": "Feature",
  "properties": {
    "iso:country":"US",
    "sg:address":"906 SW 9th Street Cir",
    "sg:city":"Boca Raton",
    "sg:classifiers":[
        {
            "category":"Wholesale",
            "subcategory":"Electrical",
            "type":"Manufacturing & Wholesale Goods"
        }
    ],
    "sg:phone":"+1 561 338 7518",
    "sg:postcode":"33486",
    "sg:province":"FL",
    "sg:tags":[
        "fire",
        "alarm",
        "system"
    ],
    "wof:name":"Boca Terrace Condo Fire Alarm",
    "wof:placetype":"venue"
},
  "geometry": {"coordinates":[-80.125046,26.340613],"type":"Point"}
}