{
  "type": "Feature",
  "properties": {
    "iso:country":"US",
    "sg:address":"101 Baywood Ave",
    "sg:city":"Clearwater",
    "sg:classifiers":[
        {
            "category":"Building & Trades",
            "subcategory":"Construction",
            "type":"Services"
        }
    ],
    "sg:phone":"+1 727 797 6910",
    "sg:postcode":"33765",
    "sg:province":"FL",
    "sg:tags":[
        "concrete",
        "contractor"
    ],
    "wof:name":"Concrete Repair International",
    "wof:placetype":"venue"
},
  "geometry": {"coordinates":[-82.739176,27.966371],"type":"Point"}
}