{
  "type": "Feature",
  "properties": {
    "addr:full":"2313 US Hwy 27 Fruitland Park FL 34731",
    "addr:housenumber":"2313",
    "addr:postcode":"34731",
    "addr:street":"Us Hwy 27",
    "iso:country":"US",
    "sg:address":"2313 US Hwy 27",
    "sg:city":"Fruitland Park",
    "sg:classifiers":[
        {
            "category":"Retail",
            "subcategory":"Auto Rental",
            "type":"Services"
        }
    ],
    "sg:phone":"+1 352 365 2598",
    "sg:postcode":"34731",
    "sg:province":"FL",
    "sg:tags":[
        "renting",
        "truck",
        "leasing"
    ],
    "wof:name":"U-Haul Co",
    "wof:placetype":"venue"
},
  "geometry": {"coordinates":[-81.90670799999999,28.877925],"type":"Point"}
}