{
  "type": "Feature",
  "properties": {
    "iso:country":"US",
    "sg:address":"2100 E Hallandale Beach Blvd",
    "sg:city":"Hallandale",
    "sg:classifiers":[
        {
            "category":"Professional",
            "subcategory":"Lawyer & Legal Services",
            "type":"Services"
        }
    ],
    "sg:phone":"+1 954 458 8655",
    "sg:postcode":"33009",
    "sg:province":"FL",
    "wof:name":"Lawrence S Tolchinsky",
    "wof:placetype":"venue"
},
  "geometry": {"coordinates":[-80.128423,25.986045],"type":"Point"}
}