{
  "type": "Feature",
  "properties": {
    "iso:country":"US",
    "sg:address":"1749 NE Ave H",
    "sg:city":"Belle Glade",
    "sg:classifiers":[
        {
            "category":"Building & Trades",
            "subcategory":"Electrical",
            "type":"Services"
        }
    ],
    "sg:phone":"+1 561 996 1785",
    "sg:postcode":"33430",
    "sg:province":"FL",
    "sg:tags":[
        "electrical",
        "contractor"
    ],
    "wof:name":"Thomas Electric",
    "wof:placetype":"venue"
},
  "geometry": {"coordinates":[-80.649861,26.693599],"type":"Point"}
}