{
  "type": "Feature",
  "properties": {
    "iso:country":"US",
    "sg:address":"1835 NW 112th Ave Ste 173",
    "sg:city":"Miami",
    "sg:classifiers":[
        {
            "category":"Banks & Credit Unions",
            "subcategory":"Investment Brokerage",
            "type":"Services"
        }
    ],
    "sg:phone":"+1 305 591 2732",
    "sg:postcode":"33172",
    "sg:province":"FL",
    "sg:tags":[
        "trust"
    ],
    "wof:name":"The Chabela Foundation Inc",
    "wof:placetype":"venue"
},
  "geometry": {"coordinates":[-80.376637,25.790197],"type":"Point"}
}