{
  "type": "Feature",
  "properties": {
    "iso:country":"US",
    "sg:address":"1675 W 49th St",
    "sg:city":"Hialeah",
    "sg:classifiers":[
        {
            "category":"Shopping",
            "subcategory":"Clothing, Apparel, & Fashions",
            "type":"Retail Goods"
        },
        {
            "category":"Shopping",
            "subcategory":"Adult",
            "type":"Retail Goods"
        }
    ],
    "sg:phone":"+1 305 820 2407",
    "sg:postcode":"33012",
    "sg:province":"FL",
    "sg:tags":[
        "girdle",
        "corset",
        "bra"
    ],
    "wof:name":"Women's Secrets",
    "wof:placetype":"venue"
},
  "geometry": {"coordinates":[-80.317108,25.866671],"type":"Point"}
}