{
  "type": "Feature",
  "properties": {
    "iso:country":"US",
    "sg:address":"227 Phoenetia Ave",
    "sg:city":"Coral Gables",
    "sg:classifiers":[
        {
            "category":"Shopping",
            "subcategory":"Clothing, Apparel, & Fashions",
            "type":"Retail Goods"
        }
    ],
    "sg:phone":"+1 305 443 9712",
    "sg:postcode":"33134",
    "sg:province":"FL",
    "wof:name":"Metamorfossis Fashion Inc",
    "wof:placetype":"venue"
},
  "geometry": {"coordinates":[-80.26029800000001,25.76134],"type":"Point"}
}