{
  "type": "Feature",
  "properties": {
    "addr:full":"1391 S Gettysburg Dr Homosassa FL 34448",
    "addr:housenumber":"1391",
    "addr:postcode":"34448",
    "addr:street":"S Gettysburg Dr",
    "iso:country":"US",
    "sg:address":"1391 S Gettysburg Dr",
    "sg:city":"Homosassa",
    "sg:classifiers":[
        {
            "category":"Organizations",
            "subcategory":"Non-profit Organization",
            "type":"Services"
        }
    ],
    "sg:phone":"+1 352 628 9802",
    "sg:postcode":"34448",
    "sg:province":"FL",
    "wof:name":"Cathedral Of Faith In Action",
    "wof:placetype":"venue"
},
  "geometry": {"coordinates":[-82.534374,28.842731],"type":"Point"}
}