{
  "type": "Feature",
  "properties": {
    "addr:full":"3438 Market St Pensacola FL 32505",
    "addr:housenumber":"3438",
    "addr:postcode":"32505",
    "addr:street":"Market St",
    "iso:country":"US",
    "sg:address":"3438 Market St",
    "sg:city":"Pensacola",
    "sg:classifiers":[
        {
            "category":"Organizations",
            "subcategory":"Religious Organization",
            "type":"Services"
        }
    ],
    "sg:phone":"+1 850 438 1371",
    "sg:postcode":"32505",
    "sg:province":"FL",
    "sg:tags":[
        "church"
    ],
    "wof:name":"Pleasant Hill Baptist Church",
    "wof:placetype":"venue"
},
  "geometry": {"coordinates":[-87.25366099999999,30.446717],"type":"Point"}
}