{
  "type": "Feature",
  "properties": {
    "addr:full":"3315 SW Archer Rd Gainesville FL 32608",
    "addr:housenumber":"3315",
    "addr:postcode":"32608",
    "addr:street":"Sw Archer Rd",
    "iso:country":"US",
    "sg:address":"3315 SW Archer Rd",
    "sg:city":"Gainesville",
    "sg:classifiers":[
        {
            "category":"Shopping",
            "subcategory":"Computers & Home Electronics",
            "type":"Retail Goods"
        }
    ],
    "sg:phone":"+1 352 375 7062",
    "sg:postcode":"32608",
    "sg:province":"FL",
    "wof:name":"Radio Shack",
    "wof:placetype":"venue"
},
  "geometry": {"coordinates":[-82.361721,29.632223],"type":"Point"}
}