{
  "type": "Feature",
  "properties": {
    "iso:country":"US",
    "sg:address":"8410 SW 98th St",
    "sg:city":"Miami",
    "sg:classifiers":[
        {
            "category":"Communications",
            "type":"Services"
        }
    ],
    "sg:phone":"+1 305 598 8143",
    "sg:postcode":"33156",
    "sg:province":"FL",
    "wof:name":"Celka Optic Communications",
    "wof:placetype":"venue"
},
  "geometry": {"coordinates":[-80.33134099999999,25.679088],"type":"Point"}
}