{
  "type": "Feature",
  "properties": {
    "iso:country":"US",
    "sg:address":"2401 SW 62nd Ave",
    "sg:city":"Hollywood",
    "sg:classifiers":[
        {
            "category":"Professional",
            "type":"Services"
        }
    ],
    "sg:phone":"+1 954 963 7105",
    "sg:postcode":"33023",
    "sg:province":"FL",
    "wof:name":"Benavides",
    "wof:placetype":"venue"
},
  "geometry": {"coordinates":[-80.210853,25.988059],"type":"Point"}
}