{
  "type": "Feature",
  "properties": {
    "addr:full":"7621 W Colonial Dr Orlando FL 32818",
    "addr:housenumber":"7621",
    "addr:postcode":"32818",
    "addr:street":"W Colonial Dr",
    "iso:country":"US",
    "sg:address":"7621 W Colonial Dr",
    "sg:city":"Orlando",
    "sg:classifiers":[
        {
            "category":"Shopping",
            "subcategory":"Bicycles & Sporting Goods",
            "type":"Retail Goods"
        }
    ],
    "sg:phone":"+1 407 445 6633",
    "sg:postcode":"32818",
    "sg:province":"FL",
    "wof:name":"Play It Again Sports",
    "wof:placetype":"venue"
},
  "geometry": {"coordinates":[-81.48754,28.552054],"type":"Point"}
}