{
  "type": "Feature",
  "properties": {
    "addr:full":"130 S Ridgewood Dr Sebring FL 33870",
    "addr:housenumber":"130",
    "addr:postcode":"33870",
    "addr:street":"S Ridgewood Dr",
    "iso:country":"US",
    "sg:address":"130 S Ridgewood Dr",
    "sg:city":"Sebring",
    "sg:classifiers":[
        {
            "category":"Professional",
            "type":"Services"
        }
    ],
    "sg:phone":"+1 863 382 7703",
    "sg:postcode":"33870",
    "sg:province":"FL",
    "sg:tags":[
        "establishment"
    ],
    "wof:name":"Stratonet",
    "wof:placetype":"venue"
},
  "geometry": {"coordinates":[-81.441168,27.495057],"type":"Point"}
}