{
  "type": "Feature",
  "properties": {
    "iso:country":"US",
    "sg:address":"206 Joel Blvd",
    "sg:city":"Lehigh Acres",
    "sg:classifiers":[
        {
            "category":"Organizations",
            "subcategory":"Religious Organization",
            "type":"Services"
        }
    ],
    "sg:phone":"+1 239 369 3726",
    "sg:postcode":"33972",
    "sg:province":"FL",
    "sg:tags":[
        "church"
    ],
    "wof:name":"All Faiths Church",
    "wof:placetype":"venue"
},
  "geometry": {"coordinates":[-81.606126,26.607535],"type":"Point"}
}