{
  "type": "Feature",
  "properties": {
    "addr:full":"8725 Arlington Expy Jacksonville FL 32211",
    "addr:housenumber":"8725",
    "addr:postcode":"32211",
    "addr:street":"Arlington Expy",
    "iso:country":"US",
    "sg:address":"8725 Arlington Expy",
    "sg:city":"Jacksonville",
    "sg:classifiers":[
        {
            "category":"Autos & Motor Vehicles",
            "subcategory":"Boat Sales",
            "type":"Retail Goods"
        }
    ],
    "sg:phone":"+1 904 338 9970",
    "sg:postcode":"32211",
    "sg:province":"FL",
    "sg:tags":[
        "dealer",
        "sales"
    ],
    "wof:name":"Marine Max Inc",
    "wof:placetype":"venue"
},
  "geometry": {"coordinates":[-81.56178800000001,30.324644],"type":"Point"}
}