{
  "type": "Feature",
  "properties": {
    "addr:full":"117 N Kings Ave Brandon FL 33510",
    "addr:housenumber":"117",
    "addr:postcode":"33510",
    "addr:street":"N Kings Ave",
    "iso:country":"US",
    "sg:address":"117 N Kings Ave",
    "sg:city":"Brandon",
    "sg:classifiers":[
        {
            "category":"Shopping",
            "subcategory":"Clothing, Apparel, & Fashions",
            "type":"Retail Goods"
        }
    ],
    "sg:phone":"+1 813 651 9484",
    "sg:postcode":"33510",
    "sg:province":"FL",
    "sg:tags":[
        "personal"
    ],
    "wof:name":"Custom Hair",
    "wof:placetype":"venue"
},
  "geometry": {"coordinates":[-82.29386100000001,27.938016],"type":"Point"}
}