{
  "type": "Feature",
  "properties": {
    "addr:full":"12604 Tamiami Trl Naples FL 34113",
    "addr:housenumber":"12604",
    "addr:postcode":"34113",
    "addr:street":"Tamiami Trl",
    "iso:country":"US",
    "sg:address":"12604 Tamiami Trl",
    "sg:city":"Naples",
    "sg:classifiers":[
        {
            "category":"Banks & Credit Unions",
            "subcategory":"Bank",
            "type":"Services"
        }
    ],
    "sg:phone":"+1 239 732 3630",
    "sg:postcode":"34113",
    "sg:province":"FL",
    "wof:name":"Wachovia Bank",
    "wof:placetype":"venue"
},
  "geometry": {"coordinates":[-81.69914300000001,26.063276],"type":"Point"}
}