{
  "type": "Feature",
  "properties": {
    "iso:country":"US",
    "sg:address":"8407 US Hwy 19",
    "sg:city":"Port Richey",
    "sg:classifiers":[
        {
            "category":"Autos & Motor Vehicles",
            "subcategory":"Automobile Sales",
            "type":"Retail Goods"
        }
    ],
    "sg:phone":"+1 727 815 3722",
    "sg:postcode":"34668",
    "sg:province":"FL",
    "sg:tags":[
        "new",
        "used"
    ],
    "wof:name":"Daewoo of Port Richey",
    "wof:placetype":"venue"
},
  "geometry": {"coordinates":[-82.71951,28.277419],"type":"Point"}
}