{
  "type": "Feature",
  "properties": {
    "iso:country":"US",
    "sg:address":"4435 Lemon St",
    "sg:city":"Cocoa",
    "sg:classifiers":[
        {
            "category":"Building & Trades",
            "subcategory":"Construction",
            "type":"Services"
        }
    ],
    "sg:phone":"+1 321 433 1880",
    "sg:postcode":"32926",
    "sg:province":"FL",
    "sg:tags":[
        "house"
    ],
    "wof:name":"Brent B Lay Home Repair",
    "wof:placetype":"venue"
},
  "geometry": {"coordinates":[-80.82203699999999,28.423234],"type":"Point"}
}