{
  "type": "Feature",
  "properties": {
    "iso:country":"US",
    "sg:address":"400 N Navy Blvd",
    "sg:city":"Pensacola",
    "sg:classifiers":[
        {
            "category":"Shopping",
            "subcategory":"Discount & Variety Stores",
            "type":"Retail Goods"
        }
    ],
    "sg:phone":"+1 850 453 2504",
    "sg:postcode":"32507",
    "sg:province":"FL",
    "wof:name":"Dollar General",
    "wof:placetype":"venue"
},
  "geometry": {"coordinates":[-87.278026,30.393981],"type":"Point"}
}