{
  "type": "Feature",
  "properties": {
    "addr:full":"3170 Metro Pkwy Fort Myers FL 33916",
    "addr:postcode":"3170;33916",
    "addr:street":"Metro Pkwy",
    "iso:country":"US",
    "sg:address":"3170 Metro Pkwy",
    "sg:city":"Fort Myers",
    "sg:classifiers":[
        {
            "category":"Manufacturing",
            "subcategory":"Tools & Machinery",
            "type":"Manufacturing & Wholesale Goods"
        }
    ],
    "sg:phone":"+1 239 337 2116",
    "sg:postcode":"33916",
    "sg:province":"FL",
    "sg:tags":[
        "control",
        "mfg",
        "lab",
        "instrument",
        "analytical",
        "laboratory"
    ],
    "sg:website":"www.hfscientific.com",
    "wof:name":"H F Scientific Inc",
    "wof:placetype":"venue"
},
  "geometry": {"coordinates":[-81.85202099999999,26.619671],"type":"Point"}
}