{
  "type": "Feature",
  "properties": {
    "addr:full":"10427 NW 28th Ave Miami FL 33147",
    "addr:housenumber":"10427",
    "addr:postcode":"33147",
    "addr:street":"Nw 28Th Ave",
    "iso:country":"US",
    "sg:address":"10427 NW 28th Ave",
    "sg:city":"Miami",
    "sg:classifiers":[
        {
            "category":"Professional",
            "subcategory":"Management & Consulting",
            "type":"Services"
        }
    ],
    "sg:phone":"+1 786 281 0464",
    "sg:postcode":"33147",
    "sg:province":"FL",
    "sg:tags":[
        "consultant"
    ],
    "wof:name":"Jcs Events",
    "wof:placetype":"venue"
},
  "geometry": {"coordinates":[-80.243556,25.86928],"type":"Point"}
}