{
  "type": "Feature",
  "properties": {
    "iso:country":"US",
    "sg:address":"3680 NE 21st Way",
    "sg:city":"Pompano Beach",
    "sg:classifiers":[
        {
            "category":"Food & Beverages",
            "subcategory":"Groceries & Convenience Stores",
            "type":"Retail Goods"
        }
    ],
    "sg:phone":"+1 954 784 8778",
    "sg:postcode":"33064",
    "sg:province":"FL",
    "wof:name":"Lighthouse Farms",
    "wof:placetype":"venue"
},
  "geometry": {"coordinates":[-80.09472599999999,26.277225],"type":"Point"}
}