{
  "type": "Feature",
  "properties": {
    "iso:country":"US",
    "sg:address":"9091 Van Fleet Rd",
    "sg:city":"Polk City",
    "sg:classifiers":[
        {
            "category":"Mining & Drilling",
            "type":"Manufacturing & Wholesale Goods"
        }
    ],
    "sg:phone":"+1 863 984 1226",
    "sg:postcode":"33868",
    "sg:province":"FL",
    "sg:tags":[
        "stone"
    ],
    "wof:name":"Vulcan Materials Co",
    "wof:placetype":"venue"
},
  "geometry": {"coordinates":[-81.780867,28.302722],"type":"Point"}
}