{
  "type": "Feature",
  "properties": {
    "iso:country":"US",
    "sg:address":"9560 SW 40th St",
    "sg:city":"Miami",
    "sg:classifiers":[
        {
            "category":"Insurance",
            "subcategory":"Hazard Insurance",
            "type":"Services"
        }
    ],
    "sg:phone":"+1 305 554 7088",
    "sg:postcode":"33165",
    "sg:province":"FL",
    "sg:website":"www.brightwayinsurance.com/locat...",
    "wof:name":"Brightway Insurance",
    "wof:placetype":"venue"
},
  "geometry": {"coordinates":[-80.349827,25.732669],"type":"Point"}
}