{
  "type": "Feature",
  "properties": {
    "addr:full":"2410 W Pensacola St Tallahassee FL 32304",
    "addr:housenumber":"2410",
    "addr:postcode":"32304",
    "addr:street":"W Pensacola St",
    "iso:country":"US",
    "sg:address":"2410 W Pensacola St",
    "sg:city":"Tallahassee",
    "sg:classifiers":[
        {
            "category":"Food & Beverages",
            "subcategory":"Groceries & Convenience Stores",
            "type":"Retail Goods"
        }
    ],
    "sg:phone":"+1 850 576 3366",
    "sg:postcode":"32304",
    "sg:province":"FL",
    "wof:name":"Westwood Shell",
    "wof:placetype":"venue"
},
  "geometry": {"coordinates":[-84.327682,30.441169],"type":"Point"}
}