{
  "type": "Feature",
  "properties": {
    "iso:country":"US",
    "sg:address":"2350 Sunset Dr",
    "sg:city":"New Smyrna Beach",
    "sg:classifiers":[
        {
            "category":"Organizations",
            "subcategory":"Community Association",
            "type":"Services"
        }
    ],
    "sg:phone":"+1 386 423 1789",
    "sg:postcode":"32168",
    "sg:province":"FL",
    "sg:tags":[
        "military"
    ],
    "wof:name":"Veterans Of Foreign Wars",
    "wof:placetype":"venue"
},
  "geometry": {"coordinates":[-80.959722,29.055979],"type":"Point"}
}