{
  "type": "Feature",
  "properties": {
    "iso:country":"US",
    "sg:address":"3400 S Dixie Hwy",
    "sg:city":"Miami",
    "sg:classifiers":[
        {
            "category":"Professional",
            "type":"Services"
        },
        {
            "category":"Personal",
            "type":"Services"
        }
    ],
    "sg:phone":"+1 305 731 2317",
    "sg:postcode":"33133",
    "sg:province":"FL",
    "sg:tags":[
        "industrial",
        "organ",
        "material",
        "movers-commercial",
        "moving",
        "services-labor",
        "mover",
        "piano"
    ],
    "sg:website":"http://www.topmovingcompany4u.com",
    "wof:name":"Professional Movers Miami",
    "wof:placetype":"venue"
},
  "geometry": {"coordinates":[-80.25001899999999,25.735435],"type":"Point"}
}