{
  "type": "Feature",
  "properties": {
    "iso:country":"US",
    "sg:address":"922 Myakka Ct NE",
    "sg:city":"Saint Petersburg",
    "sg:classifiers":[
        {
            "category":"Social Services",
            "subcategory":"Child Care",
            "type":"Services"
        }
    ],
    "sg:phone":"+1 727 522 8980",
    "sg:postcode":"33702",
    "sg:province":"FL",
    "sg:tags":[
        "school",
        "day"
    ],
    "wof:name":"Sunshine Preschool",
    "wof:placetype":"venue"
},
  "geometry": {"coordinates":[-82.62266700000001,27.843532],"type":"Point"}
}