{
  "type": "Feature",
  "properties": {
    "iso:country":"US",
    "sg:address":"95 Merrick Way",
    "sg:city":"Coral Gables",
    "sg:classifiers":[
        {
            "category":"Professional",
            "subcategory":"Management & Consulting",
            "type":"Services"
        }
    ],
    "sg:phone":"+1 305 443 2251",
    "sg:postcode":"33134",
    "sg:province":"FL",
    "sg:tags":[
        "fuel"
    ],
    "wof:name":"Latin America Media Management",
    "wof:placetype":"venue"
},
  "geometry": {"coordinates":[-80.255725,25.75083],"type":"Point"}
}