{
  "type": "Feature",
  "properties": {
    "iso:country":"US",
    "sg:address":"865 W 72nd St",
    "sg:city":"Hialeah",
    "sg:classifiers":[
        {
            "category":"Freight",
            "type":"Transportation"
        }
    ],
    "sg:phone":"+1 305 456 3251",
    "sg:postcode":"33014",
    "sg:province":"FL",
    "sg:tags":[
        "trucking"
    ],
    "wof:name":"W Martinez Trucking Corp",
    "wof:placetype":"venue"
},
  "geometry": {"coordinates":[-80.301742,25.887918],"type":"Point"}
}