{
  "type": "Feature",
  "properties": {
    "addr:full":"2347 Abscott St Port Charlotte FL 33952",
    "addr:housenumber":"2347",
    "addr:postcode":"33952",
    "addr:street":"Abscott St",
    "iso:country":"US",
    "sg:address":"2347 Abscott St",
    "sg:city":"Port Charlotte",
    "sg:classifiers":[
        {
            "category":"Wholesale",
            "subcategory":"Vending Machines",
            "type":"Manufacturing & Wholesale Goods"
        }
    ],
    "sg:phone":"+1 941 627 5439",
    "sg:postcode":"33952",
    "sg:province":"FL",
    "sg:tags":[
        "operator"
    ],
    "wof:name":"Nancy E Dolan",
    "wof:placetype":"venue"
},
  "geometry": {"coordinates":[-82.070976,26.993712],"type":"Point"}
}