{
  "type": "Feature",
  "properties": {
    "addr:full":"36413 State Rd 54 Zephyrhills FL 33541",
    "addr:housenumber":"36413;54",
    "addr:postcode":"33541",
    "addr:street":"State Rd",
    "iso:country":"US",
    "sg:address":"36413 State Rd 54",
    "sg:city":"Zephyrhills",
    "sg:classifiers":[
        {
            "category":"Building & Trades",
            "subcategory":"Construction",
            "type":"Services"
        }
    ],
    "sg:phone":"+1 813 782 0825",
    "sg:postcode":"33541",
    "sg:province":"FL",
    "sg:tags":[
        "contractor"
    ],
    "wof:name":"Ryman Construction Inc",
    "wof:placetype":"venue"
},
  "geometry": {"coordinates":[-82.21594899999999,28.229988],"type":"Point"}
}