{
  "type": "Feature",
  "properties": {
    "addr:full":"940 Pinto Cir Nokomis FL 34275",
    "addr:housenumber":"940",
    "addr:postcode":"34275",
    "addr:street":"Pinto Cir",
    "iso:country":"US",
    "sg:address":"940 Pinto Cir",
    "sg:city":"Nokomis",
    "sg:classifiers":[
        {
            "category":"Building & Trades",
            "subcategory":"Construction",
            "type":"Services"
        }
    ],
    "sg:phone":"+1 941 485 6404",
    "sg:postcode":"34275",
    "sg:province":"FL",
    "sg:tags":[
        "concrete",
        "masonry",
        "work"
    ],
    "wof:name":"Deming Concrete & Masonry",
    "wof:placetype":"venue"
},
  "geometry": {"coordinates":[-82.444706,27.144405],"type":"Point"}
}