{
  "type": "Feature",
  "properties": {
    "iso:country":"US",
    "sg:address":"12705 N Dale Mabry Hwy",
    "sg:city":"Tampa",
    "sg:classifiers":[
        {
            "category":"Restaurant",
            "type":"Food & Drink"
        }
    ],
    "sg:menulink":"http://www.allmenus.com/fl/tampa/106433-boston-market/menu/",
    "sg:phone":"+1 813 960 8116",
    "sg:postcode":"33618",
    "sg:province":"FL",
    "sg:tags":[
        "barbecue",
        "american",
        "soup"
    ],
    "wof:name":"Boston Market",
    "wof:placetype":"venue"
},
  "geometry": {"coordinates":[-82.50310500000001,28.062627],"type":"Point"}
}