{
  "type": "Feature",
  "properties": {
    "iso:country":"US",
    "sg:address":"777 NW 72nd Ave",
    "sg:city":"Miami",
    "sg:classifiers":[
        {
            "category":"Home & Garden",
            "subcategory":"Home Furnishings",
            "type":"Retail Goods"
        }
    ],
    "sg:phone":"+1 305 261 7343",
    "sg:postcode":"33126",
    "sg:province":"FL",
    "sg:tags":[
        "bath",
        "kitchen"
    ],
    "wof:name":"Press Housewares Corp",
    "wof:placetype":"venue"
},
  "geometry": {"coordinates":[-80.31240099999999,25.7773],"type":"Point"}
}