{
  "type": "Feature",
  "properties": {
    "addr:full":"8747 SW 40th St Miami FL 33165",
    "addr:housenumber":"8747",
    "addr:postcode":"33165",
    "addr:street":"Sw 40Th St",
    "iso:country":"US",
    "sg:address":"8747 SW 40th St",
    "sg:city":"Miami",
    "sg:classifiers":[
        {
            "category":"Restaurant",
            "type":"Food & Drink"
        }
    ],
    "sg:phone":"+1 305 207 0555",
    "sg:postcode":"33165",
    "sg:province":"FL",
    "sg:tags":[
        "hot",
        "dog"
    ],
    "wof:name":"Arbetter's Hot Dogs",
    "wof:placetype":"venue"
},
  "geometry": {"coordinates":[-80.33699799999999,25.733],"type":"Point"}
}