{
  "type": "Feature",
  "properties": {
    "iso:country":"US",
    "sg:address":"305 N Riverside Dr",
    "sg:city":"Indialantic",
    "sg:classifiers":[
        {
            "category":"Retail",
            "subcategory":"Animal Services",
            "type":"Services"
        }
    ],
    "sg:phone":"+1 321 956 9958",
    "sg:postcode":"32903",
    "sg:province":"FL",
    "sg:tags":[
        "pet",
        "cleaning",
        "sitting"
    ],
    "wof:name":"Patsy Oliphant Enterprises",
    "wof:placetype":"venue"
},
  "geometry": {"coordinates":[-80.575936,28.091211],"type":"Point"}
}