{
  "type": "Feature",
  "properties": {
    "iso:country":"US",
    "sg:address":"1995 Barrancas Ave",
    "sg:city":"Pensacola",
    "sg:classifiers":[
        {
            "category":"Home & Garden",
            "subcategory":"Building Materials",
            "type":"Retail Goods"
        },
        {
            "category":"Building & Trades",
            "subcategory":"Construction",
            "type":"Services"
        }
    ],
    "sg:phone":"+1 850 432 1716",
    "sg:postcode":"32501",
    "sg:province":"FL",
    "sg:tags":[
        "industrial",
        "door",
        "fence",
        "devices",
        "contractor",
        "operating",
        "gate"
    ],
    "wof:name":"Atlantic Industrial Fence Inc",
    "wof:placetype":"venue"
},
  "geometry": {"coordinates":[-87.24081099999999,30.404069],"type":"Point"}
}