{
  "type": "Feature",
  "properties": {
    "iso:country":"US",
    "sg:address":"839 Palermo Ave",
    "sg:city":"Coral Gables",
    "sg:classifiers":[
        {
            "category":"Building & Trades",
            "subcategory":"Locksmith",
            "type":"Services"
        }
    ],
    "sg:phone":"+1 786 228 5691",
    "sg:postcode":"33134",
    "sg:province":"FL",
    "sg:tags":[
        "key"
    ],
    "wof:name":"Coral Gables Locksmith",
    "wof:placetype":"venue"
},
  "geometry": {"coordinates":[-80.272104,25.744272],"type":"Point"}
}