{
  "type": "Feature",
  "properties": {
    "iso:country":"US",
    "sg:address":"306 E Oak Ave",
    "sg:city":"Tampa",
    "sg:classifiers":[
        {
            "category":"Health Services",
            "subcategory":"Health Practitioner",
            "type":"Services"
        }
    ],
    "sg:phone":"+1 813 228 0911",
    "sg:postcode":"33602",
    "sg:province":"FL",
    "sg:tags":[
        "psychotherapist"
    ],
    "wof:name":"Lynne Santiago Lmhc",
    "wof:placetype":"venue"
},
  "geometry": {"coordinates":[-82.45663999999999,27.96136],"type":"Point"}
}