{
  "type": "Feature",
  "properties": {
    "iso:country":"US",
    "sg:address":"2039 W Pensacola St",
    "sg:city":"Tallahassee",
    "sg:classifiers":[
        {
            "category":"Restaurant",
            "type":"Food & Drink"
        }
    ],
    "sg:phone":"+1 850 575 3870",
    "sg:postcode":"32304",
    "sg:province":"FL",
    "wof:name":"Jamaican Way Restaurant",
    "wof:placetype":"venue"
},
  "geometry": {"coordinates":[-84.318744,30.440581],"type":"Point"}
}