{
  "type": "Feature",
  "properties": {
    "iso:country":"US",
    "sg:address":"9702 Sunderson St",
    "sg:city":"Orlando",
    "sg:classifiers":[
        {
            "category":"Autos & Motor Vehicles",
            "subcategory":"Fuel & Gas Station",
            "type":"Retail Goods"
        }
    ],
    "sg:phone":"+1 407 281 6719",
    "sg:postcode":"32825",
    "sg:province":"FL",
    "sg:tags":[
        "convenience",
        "station",
        "gasoline",
        "store"
    ],
    "wof:name":"Ortega Brithers Shell",
    "wof:placetype":"venue"
},
  "geometry": {"coordinates":[-81.24582100000001,28.532222],"type":"Point"}
}