{
  "type": "Feature",
  "properties": {
    "iso:country":"US",
    "sg:address":"3103 Glascow Ct",
    "sg:city":"Milton",
    "sg:classifiers":[
        {
            "category":"Professional",
            "subcategory":"Management & Consulting",
            "type":"Services"
        }
    ],
    "sg:phone":"+1 850 463 5567",
    "sg:postcode":"32583",
    "sg:province":"FL",
    "sg:tags":[
        "aviation",
        "consultant"
    ],
    "wof:name":"Byerley Aviation Inc",
    "wof:placetype":"venue"
},
  "geometry": {"coordinates":[-87.080383,30.547734],"type":"Point"}
}