{
  "type": "Feature",
  "properties": {
    "iso:country":"US",
    "sg:address":"1183 N State Road 7",
    "sg:city":"Hollywood",
    "sg:classifiers":[
        {
            "category":"Autos & Motor Vehicles",
            "subcategory":"Auto Supplies",
            "type":"Retail Goods"
        }
    ],
    "sg:phone":"+1 954 964 1118",
    "sg:postcode":"33021",
    "sg:province":"FL",
    "sg:tags":[
        "tire"
    ],
    "wof:name":"Rent-N-Roll",
    "wof:placetype":"venue"
},
  "geometry": {"coordinates":[-80.208011,26.020228],"type":"Point"}
}