{
  "type": "Feature",
  "properties": {
    "addr:full":"8000 W Broward Blvd Plantation FL 33317",
    "addr:housenumber":"8000",
    "addr:postcode":"33317",
    "addr:street":"W Broward Blvd",
    "iso:country":"US",
    "sg:address":"8000 W Broward Blvd",
    "sg:city":"Plantation",
    "sg:classifiers":[
        {
            "category":"Wholesale",
            "subcategory":"Groceries",
            "type":"Manufacturing & Wholesale Goods"
        }
    ],
    "sg:phone":"+1 954 474 8848",
    "sg:postcode":"33317",
    "sg:province":"FL",
    "sg:tags":[
        "pretzel"
    ],
    "wof:name":"Auntie Anne's Hand Rolled Soft",
    "wof:placetype":"venue"
},
  "geometry": {"coordinates":[-80.254075,26.120739],"type":"Point"}
}