{
  "type": "Feature",
  "properties": {
    "addr:full":"1305 Willow Springs Ct Longwood FL 32750",
    "addr:housenumber":"1305",
    "addr:postcode":"32750",
    "addr:street":"Willow Springs Ct",
    "iso:country":"US",
    "sg:address":"1305 Willow Springs Ct",
    "sg:city":"Longwood",
    "sg:classifiers":[
        {
            "category":"Building & Trades",
            "subcategory":"Construction",
            "type":"Services"
        }
    ],
    "sg:phone":"+1 407 265 1731",
    "sg:postcode":"32750",
    "sg:province":"FL",
    "sg:tags":[
        "contractor"
    ],
    "wof:name":"American Installation",
    "wof:placetype":"venue"
},
  "geometry": {"coordinates":[-81.36911000000001,28.713555],"type":"Point"}
}