{
  "type": "Feature",
  "properties": {
    "iso:country":"US",
    "sg:address":"801 S Olive Ave #436",
    "sg:city":"West Palm Beach",
    "sg:classifiers":[
        {
            "category":"Professional",
            "subcategory":"Computer Services",
            "type":"Services"
        }
    ],
    "sg:phone":"+1 561 214 4016",
    "sg:postcode":"33401",
    "sg:province":"FL",
    "sg:tags":[
        "professional-reference",
        "employment",
        "headhunting",
        "2-0"
    ],
    "sg:website":"http://www.referencebot.com",
    "wof:name":"ReferenceBot",
    "wof:placetype":"venue"
},
  "geometry": {"coordinates":[-80.052097,26.705448],"type":"Point"}
}