{
  "type": "Feature",
  "properties": {
    "iso:country":"US",
    "sg:address":"8521 Cypress Dr S",
    "sg:city":"Fort Myers",
    "sg:classifiers":[
        {
            "category":"Building & Trades",
            "subcategory":"Cleaning & Sanitation",
            "type":"Services"
        },
        {
            "category":"Building & Trades",
            "subcategory":"Construction",
            "type":"Services"
        }
    ],
    "sg:phone":"+1 239 340 2088",
    "sg:postcode":"33967",
    "sg:province":"FL",
    "sg:tags":[
        "maintenance",
        "contractor"
    ],
    "wof:name":"Illuminations Inc",
    "wof:placetype":"venue"
},
  "geometry": {"coordinates":[-81.805803,26.475462],"type":"Point"}
}