{
  "type": "Feature",
  "properties": {
    "addr:full":"882 Corbin Rd Chipley FL 32428",
    "addr:housenumber":"882",
    "addr:postcode":"32428",
    "addr:street":"Corbin Rd",
    "iso:country":"US",
    "sg:address":"882 Corbin Rd",
    "sg:city":"Chipley",
    "sg:classifiers":[
        {
            "category":"Building & Trades",
            "subcategory":"Electrical",
            "type":"Services"
        }
    ],
    "sg:phone":"+1 850 638 9132",
    "sg:postcode":"32428",
    "sg:province":"FL",
    "sg:tags":[
        "electrical",
        "contractor"
    ],
    "wof:name":"David W Birge",
    "wof:placetype":"venue"
},
  "geometry": {"coordinates":[-85.475134,30.723794],"type":"Point"}
}