{
  "type": "Feature",
  "properties": {
    "iso:country":"US",
    "sg:address":"3333 Ave I",
    "sg:city":"Riviera Beach",
    "sg:classifiers":[
        {
            "category":"Health Services",
            "subcategory":"Hospital",
            "type":"Services"
        },
        {
            "category":"Organizations",
            "subcategory":"Professional Association",
            "type":"Services"
        }
    ],
    "sg:phone":"+1 561 863 9848",
    "sg:postcode":"33404",
    "sg:province":"FL",
    "sg:tags":[
        "affairs",
        "mental",
        "community"
    ],
    "wof:name":"Federation Of Families Of Palm",
    "wof:placetype":"venue"
},
  "geometry": {"coordinates":[-80.066328,26.789174],"type":"Point"}
}