{
  "type": "Feature",
  "properties": {
    "iso:country":"US",
    "sg:address":"2046 Champions Way",
    "sg:city":"Pompano Beach",
    "sg:classifiers":[
        {
            "category":"Real Estate",
            "subcategory":"Real Estate Agent",
            "type":"Services"
        }
    ],
    "sg:phone":"+1 954 718 0777",
    "sg:postcode":"33068",
    "sg:province":"FL",
    "wof:name":"Reward Real Estate Inc",
    "wof:placetype":"venue"
},
  "geometry": {"coordinates":[-80.222503,26.202453],"type":"Point"}
}