{
  "type": "Feature",
  "properties": {
    "iso:country":"US",
    "sg:address":"5861 Riverside Dr",
    "sg:city":"Pompano Beach",
    "sg:classifiers":[
        {
            "category":"Shopping",
            "subcategory":"Music",
            "type":"Retail Goods"
        }
    ],
    "sg:phone":"+1 954 346 2282",
    "sg:postcode":"33067",
    "sg:province":"FL",
    "wof:name":"12 Steps Are For Everyone",
    "wof:placetype":"venue"
},
  "geometry": {"coordinates":[-80.23661199999999,26.301031],"type":"Point"}
}