{
  "type": "Feature",
  "properties": {
    "iso:country":"US",
    "sg:address":"2818 NW 112th Ave",
    "sg:city":"Doral",
    "sg:classifiers":[
        {
            "category":"Home & Garden",
            "subcategory":"Building Materials",
            "type":"Retail Goods"
        }
    ],
    "sg:phone":"+1 305 406 1593",
    "sg:postcode":"33172",
    "sg:province":"FL",
    "wof:name":"Emac America LLC",
    "wof:placetype":"venue"
},
  "geometry": {"coordinates":[-80.377234,25.799987],"type":"Point"}
}