{
  "type": "Feature",
  "properties": {
    "addr:full":"4270 Progress Ave Naples FL 34104",
    "addr:housenumber":"4270",
    "addr:postcode":"34104",
    "addr:street":"Progress Ave",
    "iso:country":"US",
    "sg:address":"4270 Progress Ave",
    "sg:city":"Naples",
    "sg:classifiers":[
        {
            "category":"Building & Trades",
            "subcategory":"Construction",
            "type":"Services"
        }
    ],
    "sg:phone":"+1 239 649 4435",
    "sg:postcode":"34104",
    "sg:province":"FL",
    "sg:tags":[
        "general",
        "contractor"
    ],
    "wof:name":"Manhardt Inc",
    "wof:placetype":"venue"
},
  "geometry": {"coordinates":[-81.755715,26.164294],"type":"Point"}
}