{
  "type": "Feature",
  "properties": {
    "addr:full":"7201 N University Dr Fort Lauderdale FL 33321",
    "addr:housenumber":"7201",
    "addr:postcode":"33321",
    "addr:street":"N University Dr",
    "iso:country":"US",
    "sg:address":"7201 N University Dr",
    "sg:city":"Fort Lauderdale",
    "sg:classifiers":[
        {
            "category":"Health Services",
            "subcategory":"Clinic",
            "type":"Services"
        }
    ],
    "sg:phone":"+1 954 724 6444",
    "sg:postcode":"33321",
    "sg:province":"FL",
    "sg:tags":[
        "home"
    ],
    "wof:name":"Columbia HCA",
    "wof:placetype":"venue"
},
  "geometry": {"coordinates":[-80.252464,26.212106],"type":"Point"}
}