{
  "type": "Feature",
  "properties": {
    "iso:country":"US",
    "sg:address":"13308 Casa Verde Cir",
    "sg:city":"Astatula",
    "sg:classifiers":[
        {
            "category":"Education",
            "subcategory":"Special Training",
            "type":"Public Place"
        }
    ],
    "sg:phone":"+1 352 978 9520",
    "sg:postcode":"34705",
    "sg:province":"FL",
    "sg:tags":[
        "educational"
    ],
    "wof:name":"Venture International Academy. Inc.",
    "wof:placetype":"venue"
},
  "geometry": {"coordinates":[-81.736397,28.718174],"type":"Point"}
}