{
  "type": "Feature",
  "properties": {
    "iso:country":"US",
    "sg:address":"2327 NE 19th Dr",
    "sg:city":"Gainesville",
    "sg:classifiers":[
        {
            "category":"Manufacturing",
            "subcategory":"Metals",
            "type":"Manufacturing & Wholesale Goods"
        }
    ],
    "sg:phone":"+1 352 373 0384",
    "sg:postcode":"32609",
    "sg:province":"FL",
    "sg:tags":[
        "steel"
    ],
    "wof:name":"Gainesville Welding & Fab",
    "wof:placetype":"venue"
},
  "geometry": {"coordinates":[-82.299577,29.67679],"type":"Point"}
}