{
  "type": "Feature",
  "properties": {
    "iso:country":"US",
    "sg:address":"2220 Corporation Blvd",
    "sg:city":"Naples",
    "sg:classifiers":[
        {
            "category":"Manufacturing",
            "subcategory":"Building Materials",
            "type":"Manufacturing & Wholesale Goods"
        }
    ],
    "sg:phone":"+1 239 566 7945",
    "sg:postcode":"34109",
    "sg:province":"FL",
    "sg:tags":[
        "molding"
    ],
    "wof:name":"Moulding Factory",
    "wof:placetype":"venue"
},
  "geometry": {"coordinates":[-81.775864,26.222791],"type":"Point"}
}