{
  "type": "Feature",
  "properties": {
    "addr:full":"1441 Tamiami Trl Port Charlotte FL 33948",
    "addr:housenumber":"1441",
    "addr:postcode":"33948",
    "addr:street":"Tamiami Trl",
    "iso:country":"US",
    "sg:address":"1441 Tamiami Trl",
    "sg:city":"Port Charlotte",
    "sg:classifiers":[
        {
            "category":"Shopping",
            "type":"Retail Goods"
        }
    ],
    "sg:phone":"+1 941 235 1538",
    "sg:postcode":"33948",
    "sg:province":"FL",
    "sg:tags":[
        "telephone",
        "cellular"
    ],
    "wof:name":"PCS Div Inc",
    "wof:placetype":"venue"
},
  "geometry": {"coordinates":[-82.142602,27.011002],"type":"Point"}
}