{
  "type": "Feature",
  "properties": {
    "iso:country":"US",
    "sg:address":"2705 W Tharpe St",
    "sg:city":"Tallahassee",
    "sg:classifiers":[
        {
            "category":"Education",
            "subcategory":"School",
            "type":"Public Place"
        }
    ],
    "sg:phone":"+1 850 385 3834",
    "sg:postcode":"32303",
    "sg:province":"FL",
    "wof:name":"Magnolia School Inc",
    "wof:placetype":"venue"
},
  "geometry": {"coordinates":[-84.33831499999999,30.465297],"type":"Point"}
}