{
  "type": "Feature",
  "properties": {
    "iso:country":"US",
    "sg:address":"7667 Starkey Rd",
    "sg:city":"Largo",
    "sg:classifiers":[
        {
            "category":"Professional",
            "subcategory":"Accounting & Tax Preparation",
            "type":"Services"
        }
    ],
    "sg:phone":"+1 727 393 4393",
    "sg:postcode":"33777",
    "sg:province":"FL",
    "sg:tags":[
        "return",
        "filing"
    ],
    "wof:name":"Tax Authority Inc",
    "wof:placetype":"venue"
},
  "geometry": {"coordinates":[-82.76224999999999,27.842166],"type":"Point"}
}