{
  "type": "Feature",
  "properties": {
    "iso:country":"US",
    "sg:address":"N25 47.160 W80 09.187",
    "sg:city":"Miami Beach",
    "sg:classifiers":[
        {
            "category":"Landmark",
            "subcategory":"Historic",
            "type":"Public Place"
        }
    ],
    "sg:postcode":"33140",
    "sg:province":"FL",
    "sg:tags":[
        "building",
        "historical"
    ],
    "wof:name":"Flagler Monument Island",
    "wof:placetype":"venue"
},
  "geometry": {"coordinates":[-80.13112599999999,25.821981],"type":"Point"}
}