{
  "type": "Feature",
  "properties": {
    "iso:country":"US",
    "sg:address":"2525 Harbor Blvd",
    "sg:city":"Port Charlotte",
    "sg:classifiers":[
        {
            "category":"Health Services",
            "subcategory":"Doctor",
            "type":"Services"
        }
    ],
    "sg:phone":"+1 941 629 2922",
    "sg:postcode":"33952",
    "sg:province":"FL",
    "sg:tags":[
        "pediatrician"
    ],
    "wof:name":"Norma C Villareal MD PA",
    "wof:placetype":"venue"
},
  "geometry": {"coordinates":[-82.096841,26.989335],"type":"Point"}
}