{
  "type": "Feature",
  "properties": {
    "iso:country":"US",
    "sg:address":"11760 SW 40th St",
    "sg:city":"Miami",
    "sg:classifiers":[
        {
            "category":"Health Services",
            "subcategory":"Doctor",
            "type":"Services"
        }
    ],
    "sg:phone":"+1 305 227 3388",
    "sg:postcode":"33175",
    "sg:province":"FL",
    "sg:tags":[
        "physician",
        "surgeon"
    ],
    "wof:name":"Rodolfo Martinez Pa",
    "wof:placetype":"venue"
},
  "geometry": {"coordinates":[-80.38654,25.731986],"type":"Point"}
}