{
  "type": "Feature",
  "properties": {
    "addr:full":"7616 University Gardens Dr Winter Park FL 32792",
    "addr:housenumber":"7616",
    "addr:postcode":"32792",
    "addr:street":"University Gardens Dr",
    "iso:country":"US",
    "sg:address":"7616 University Gardens Dr",
    "sg:city":"Winter Park",
    "sg:classifiers":[
        {
            "category":"Professional",
            "subcategory":"Computer Services",
            "type":"Services"
        }
    ],
    "sg:phone":"+1 407 679 2983",
    "sg:postcode":"32792",
    "sg:province":"FL",
    "sg:tags":[
        "programing",
        "custom"
    ],
    "wof:name":"Micro Systems Consulting",
    "wof:placetype":"venue"
},
  "geometry": {"coordinates":[-81.28315499999999,28.593298],"type":"Point"}
}