{
  "type": "Feature",
  "properties": {
    "addr:full":"125 Melody Ln W Casselberry FL 32707",
    "addr:housenumber":"125",
    "addr:postcode":"32707",
    "addr:street":"Melody Ln W",
    "iso:country":"US",
    "sg:address":"125 Melody Ln W",
    "sg:city":"Casselberry",
    "sg:classifiers":[
        {
            "category":"Recreation",
            "type":"Entertainment"
        }
    ],
    "sg:phone":"+1 407 262 7720",
    "sg:postcode":"32707",
    "sg:province":"FL",
    "sg:tags":[
        "parks"
    ],
    "sg:website":"www.casselberry.org",
    "wof:name":"Casselberry Parks & Recreation",
    "wof:placetype":"venue"
},
  "geometry": {"coordinates":[-81.338633,28.67245],"type":"Point"}
}