{
  "type": "Feature",
  "properties": {
    "addr:full":"4085 Tamiami Trl N Naples FL 34103",
    "addr:housenumber":"4085",
    "addr:postcode":"34103",
    "addr:street":"Tamiami Trl N",
    "iso:country":"US",
    "sg:address":"4085 Tamiami Trl N",
    "sg:city":"Naples",
    "sg:classifiers":[
        {
            "category":"Health Services",
            "subcategory":"Doctor",
            "type":"Services"
        }
    ],
    "sg:phone":"+1 239 261 3082",
    "sg:postcode":"34103",
    "sg:province":"FL",
    "sg:tags":[
        "physician",
        "surgeon"
    ],
    "wof:name":"Naples Dermatology & Skin Cncr",
    "wof:placetype":"venue"
},
  "geometry": {"coordinates":[-81.80014,26.193897],"type":"Point"}
}