{
  "type": "Feature",
  "properties": {
    "iso:country":"US",
    "sg:address":"2722 NE 4th St",
    "sg:city":"Pompano Beach",
    "sg:classifiers":[
        {
            "category":"Manufacturing",
            "subcategory":"Furniture",
            "type":"Manufacturing & Wholesale Goods"
        }
    ],
    "sg:phone":"+1 954 941 1073",
    "sg:postcode":"33062",
    "sg:province":"FL",
    "sg:tags":[
        "mfg"
    ],
    "wof:name":"Total Restoration of Sout",
    "wof:placetype":"venue"
},
  "geometry": {"coordinates":[-80.096801,26.235239],"type":"Point"}
}