{
  "type": "Feature",
  "properties": {
    "addr:full":"510 E Sadie St Brandon FL 33510",
    "addr:housenumber":"510",
    "addr:postcode":"33510",
    "addr:street":"E Sadie St",
    "iso:country":"US",
    "sg:address":"510 E Sadie St",
    "sg:city":"Brandon",
    "sg:classifiers":[
        {
            "category":"Community Center",
            "type":"Public Place"
        }
    ],
    "sg:phone":"+1 813 744 5617",
    "sg:postcode":"33510",
    "sg:province":"FL",
    "sg:tags":[
        "recreation"
    ],
    "sg:website":"http://www.sao13th.com",
    "wof:name":"Parks & Recreation Dept",
    "wof:placetype":"venue"
},
  "geometry": {"coordinates":[-82.279495,27.94153],"type":"Point"}
}