{
  "type": "Feature",
  "properties": {
    "iso:country":"US",
    "sg:address":"2085 W 76th St",
    "sg:city":"Hialeah",
    "sg:classifiers":[
        {
            "category":"Restaurant",
            "type":"Food & Drink"
        }
    ],
    "sg:phone":"+1 305 823 1242",
    "sg:postcode":"33016",
    "sg:province":"FL",
    "sg:tags":[
        "eating"
    ],
    "wof:name":"Happy City Chinese Restaurant",
    "wof:placetype":"venue"
},
  "geometry": {"coordinates":[-80.32499900000001,25.891597],"type":"Point"}
}