{
  "type": "Feature",
  "properties": {
    "addr:full":"1200 Silverstone Ave Orlando FL 32806",
    "addr:housenumber":"1200",
    "addr:postcode":"32806",
    "addr:street":"Silverstone Ave",
    "iso:country":"US",
    "sg:address":"1200 Silverstone Ave",
    "sg:city":"Orlando",
    "sg:classifiers":[
        {
            "category":"Wholesale",
            "subcategory":"Non-durable Goods",
            "type":"Manufacturing & Wholesale Goods"
        }
    ],
    "sg:phone":"+1 407 523 6458",
    "sg:postcode":"32806",
    "sg:province":"FL",
    "sg:tags":[
        "dry",
        "goods-wholesale"
    ],
    "wof:name":"Millar Distribution",
    "wof:placetype":"venue"
},
  "geometry": {"coordinates":[-81.333977,28.52709],"type":"Point"}
}