{
  "type": "Feature",
  "properties": {
    "addr:full":"1980 Atlantic St Melbourne Beach FL 32951",
    "addr:housenumber":"1980",
    "addr:postcode":"32951",
    "addr:street":"Atlantic St",
    "iso:country":"US",
    "sg:address":"1980 Atlantic St",
    "sg:city":"Melbourne Beach",
    "sg:classifiers":[
        {
            "category":"Professional",
            "subcategory":"Lawyer & Legal Services",
            "type":"Services"
        }
    ],
    "sg:phone":"+1 321 783 8440",
    "sg:postcode":"32951",
    "sg:province":"FL",
    "wof:name":"Dacosta Stephannie",
    "wof:placetype":"venue"
},
  "geometry": {"coordinates":[-80.552196,28.056705],"type":"Point"}
}