{
  "type": "Feature",
  "properties": {
    "iso:country":"US",
    "sg:address":"4451 Camrose Ln",
    "sg:city":"West Palm Beach",
    "sg:classifiers":[
        {
            "category":"Wholesale",
            "subcategory":"Durable Goods & Equipment",
            "type":"Manufacturing & Wholesale Goods"
        }
    ],
    "sg:phone":"+1 561 687 5088",
    "sg:postcode":"33417",
    "sg:province":"FL",
    "wof:name":"Carlos Carraca Import & Export",
    "wof:placetype":"venue"
},
  "geometry": {"coordinates":[-80.116276,26.741292],"type":"Point"}
}