{
  "type": "Feature",
  "properties": {
    "iso:country":"US",
    "sg:address":"578 Valderia Dr",
    "sg:city":"Orange Park",
    "sg:classifiers":[
        {
            "category":"Retail",
            "subcategory":"Auto Repair",
            "type":"Services"
        }
    ],
    "sg:phone":"+1 904 278 2623",
    "sg:postcode":"32073",
    "sg:province":"FL",
    "sg:tags":[
        "body"
    ],
    "wof:name":"Precision Pot Met Restoration",
    "wof:placetype":"venue"
},
  "geometry": {"coordinates":[-81.73949500000001,30.169549],"type":"Point"}
}