{
  "type": "Feature",
  "properties": {
    "iso:country":"US",
    "sg:address":"4090 Hodges Blvd Unit 102",
    "sg:city":"Jacksonville",
    "sg:classifiers":[
        {
            "category":"Communications",
            "subcategory":"Film & Video Production",
            "type":"Services"
        },
        {
            "category":"Shopping",
            "subcategory":"Computers & Home Electronics",
            "type":"Retail Goods"
        },
        {
            "category":"Marine",
            "type":"Transportation"
        }
    ],
    "sg:phone":"+1 904 383 7240",
    "sg:postcode":"32224",
    "sg:province":"FL",
    "sg:tags":[
        "repair",
        "stereo",
        "equipment-installation",
        "supply",
        "multimedia",
        "equipment",
        "equipment-dealers",
        "audio"
    ],
    "wof:name":"One Off Customs",
    "wof:placetype":"venue"
},
  "geometry": {"coordinates":[-81.464218,30.269369],"type":"Point"}
}