{
  "type": "Feature",
  "properties": {
    "addr:full":"1301 SW 142nd Ave Hollywood FL 33027",
    "addr:housenumber":"1301",
    "addr:postcode":"33027",
    "addr:street":"Sw 142Nd Ave",
    "iso:country":"US",
    "sg:address":"1301 SW 142nd Ave",
    "sg:city":"Hollywood",
    "sg:classifiers":[
        {
            "category":"Wholesale",
            "subcategory":"Chemicals & Plastics",
            "type":"Manufacturing & Wholesale Goods"
        }
    ],
    "sg:phone":"+1 954 704 9474",
    "sg:postcode":"33027",
    "sg:province":"FL",
    "wof:name":"Samuel Karp & Company",
    "wof:placetype":"venue"
},
  "geometry": {"coordinates":[-80.33259700000001,25.999316],"type":"Point"}
}