{
  "type": "Feature",
  "properties": {
    "addr:full":"6210 Shirley St Naples FL 34109",
    "addr:housenumber":"6210",
    "addr:postcode":"34109",
    "addr:street":"Shirley St",
    "iso:country":"US",
    "sg:address":"6210 Shirley St",
    "sg:city":"Naples",
    "sg:classifiers":[
        {
            "category":"Freight",
            "type":"Transportation"
        }
    ],
    "sg:phone":"+1 239 594 0014",
    "sg:postcode":"34109",
    "sg:province":"FL",
    "sg:tags":[
        "special"
    ],
    "wof:name":"Adkos LLC",
    "wof:placetype":"venue"
},
  "geometry": {"coordinates":[-81.781567,26.2214],"type":"Point"}
}