{
  "type": "Feature",
  "properties": {
    "addr:full":"6682 Time Square Ave # 103 Orlando FL 32835",
    "addr:housenumber":"6682",
    "addr:postcode":"32835",
    "addr:street":"Time Square Ave # 103",
    "iso:country":"US",
    "sg:address":"6682 Time Square Ave # 103",
    "sg:city":"Orlando",
    "sg:classifiers":[
        {
            "category":"Wholesale",
            "subcategory":"Non-durable Goods",
            "type":"Manufacturing & Wholesale Goods"
        }
    ],
    "sg:phone":"+1 407 313 6252",
    "sg:postcode":"32835",
    "sg:province":"FL",
    "sg:tags":[
        "merchandise-wholesale"
    ],
    "wof:name":"Chw International Trading & Co",
    "wof:placetype":"venue"
},
  "geometry": {"coordinates":[-81.473719,28.507637],"type":"Point"}
}