{
  "type": "Feature",
  "properties": {
    "addr:full":"450 S Lake Ave Groveland FL 34736",
    "addr:housenumber":"450",
    "addr:postcode":"34736",
    "addr:street":"S Lake Ave",
    "iso:country":"US",
    "sg:address":"450 S Lake Ave",
    "sg:city":"Groveland",
    "sg:classifiers":[
        {
            "category":"Government",
            "subcategory":"Office",
            "type":"Public Place"
        }
    ],
    "sg:phone":"+1 352 429 3573",
    "sg:postcode":"34736",
    "sg:province":"FL",
    "wof:name":"Supervisor Of Elections",
    "wof:placetype":"venue"
},
  "geometry": {"coordinates":[-81.858357,28.557736],"type":"Point"}
}