{
  "type": "Feature",
  "properties": {
    "iso:country":"US",
    "sg:address":"4305 Spanish Trl",
    "sg:city":"Pensacola",
    "sg:classifiers":[
        {
            "category":"Personal",
            "subcategory":"Beauty Salon",
            "type":"Services"
        }
    ],
    "sg:phone":"+1 850 469 9939",
    "sg:postcode":"32504",
    "sg:province":"FL",
    "wof:name":"Bella Mia",
    "wof:placetype":"venue"
},
  "geometry": {"coordinates":[-87.175758,30.467147],"type":"Point"}
}