{
  "type": "Feature",
  "properties": {
    "iso:country":"US",
    "sg:address":"12905 SW 88th St",
    "sg:city":"Miami",
    "sg:classifiers":[
        {
            "category":"Banks & Credit Unions",
            "subcategory":"Bank",
            "type":"Services"
        }
    ],
    "sg:phone":"+1 305 752 1275",
    "sg:postcode":"33186",
    "sg:province":"FL",
    "sg:tags":[
        "saving",
        "commercial"
    ],
    "sg:website":"http://www.bankunited.com",
    "wof:name":"Bankunited",
    "wof:placetype":"venue"
},
  "geometry": {"coordinates":[-80.40192500000001,25.68592],"type":"Point"}
}