{
  "type": "Feature",
  "properties": {
    "iso:country":"US",
    "sg:address":"311 6th Ave N",
    "sg:city":"Safety Harbor",
    "sg:classifiers":[
        {
            "category":"Shopping",
            "subcategory":"Discount & Variety Stores",
            "type":"Retail Goods"
        }
    ],
    "sg:phone":"+1 727 797 3108",
    "sg:postcode":"34695",
    "sg:province":"FL",
    "wof:name":"Variety Shots",
    "wof:placetype":"venue"
},
  "geometry": {"coordinates":[-82.69331099999999,27.993495],"type":"Point"}
}