{
  "type": "Feature",
  "properties": {
    "iso:country":"US",
    "sg:address":"4337 W US Hwy 90",
    "sg:city":"Lake City",
    "sg:classifiers":[
        {
            "category":"Personal",
            "subcategory":"Beauty Salon",
            "type":"Services"
        }
    ],
    "sg:phone":"+1 386 719 6446",
    "sg:postcode":"32055",
    "sg:province":"FL",
    "sg:tags":[
        "manicuring"
    ],
    "wof:name":"Regal Nails",
    "wof:placetype":"venue"
},
  "geometry": {"coordinates":[-82.681664,30.180313],"type":"Point"}
}