{
  "type": "Feature",
  "properties": {
    "addr:full":"170 Bowie Ln Kissimmee FL 34743",
    "addr:housenumber":"170",
    "addr:postcode":"34743",
    "addr:street":"Bowie Ln",
    "iso:country":"US",
    "sg:address":"170 Bowie Ln",
    "sg:city":"Kissimmee",
    "sg:classifiers":[
        {
            "category":"Professional",
            "subcategory":"Management & Consulting",
            "type":"Services"
        }
    ],
    "sg:phone":"+1 407 346 0722",
    "sg:postcode":"34743",
    "sg:province":"FL",
    "sg:tags":[
        "fuel"
    ],
    "wof:name":"Salazar Management Inc",
    "wof:placetype":"venue"
},
  "geometry": {"coordinates":[-81.340295,28.324523],"type":"Point"}
}