{
  "type": "Feature",
  "properties": {
    "addr:full":"3551 Kingston St N Saint Petersburg FL 33713",
    "addr:housenumber":"3551",
    "addr:postcode":"33713",
    "addr:street":"Kingston St N",
    "iso:country":"US",
    "sg:address":"3551 Kingston St N",
    "sg:city":"Saint Petersburg",
    "sg:classifiers":[
        {
            "category":"Building & Trades",
            "subcategory":"Construction",
            "type":"Services"
        }
    ],
    "sg:phone":"+1 727 527 9735",
    "sg:postcode":"33713",
    "sg:province":"FL",
    "sg:tags":[
        "house"
    ],
    "wof:name":"Tomas Construction",
    "wof:placetype":"venue"
},
  "geometry": {"coordinates":[-82.68458099999999,27.803273],"type":"Point"}
}