{
  "type": "Feature",
  "properties": {
    "addr:full":"5012 15th St E Bradenton FL 34203",
    "addr:housenumber":"5012",
    "addr:postcode":"34203",
    "addr:street":"15Th St",
    "iso:country":"US",
    "sg:address":"5012 15th St E",
    "sg:city":"Bradenton",
    "sg:classifiers":[
        {
            "category":"Restaurant",
            "type":"Food & Drink"
        }
    ],
    "sg:phone":"+1 941 739 7118",
    "sg:postcode":"34203",
    "sg:province":"FL",
    "sg:tags":[
        "delicatessen"
    ],
    "wof:name":"Cookie's Cafe & Catering",
    "wof:placetype":"venue"
},
  "geometry": {"coordinates":[-82.546584,27.452642],"type":"Point"}
}