{
  "type": "Feature",
  "properties": {
    "iso:country":"US",
    "sg:address":"10239 Garden Alcove Dr",
    "sg:city":"Tampa",
    "sg:classifiers":[
        {
            "category":"Organizations",
            "subcategory":"Labor Organization",
            "type":"Services"
        }
    ],
    "sg:phone":"+1 813 907 7124",
    "sg:postcode":"33647",
    "sg:province":"FL",
    "wof:name":"Sweetgrass Equestrian Lc",
    "wof:placetype":"venue"
},
  "geometry": {"coordinates":[-82.316371,28.139464],"type":"Point"}
}