{
  "type": "Feature",
  "properties": {
    "iso:country":"US",
    "sg:address":"516 Bayview Pkwy",
    "sg:city":"Nokomis",
    "sg:classifiers":[
        {
            "category":"Building & Trades",
            "subcategory":"Construction",
            "type":"Services"
        }
    ],
    "sg:phone":"+1 941 488 2304",
    "sg:postcode":"34275",
    "sg:province":"FL",
    "sg:tags":[
        "hanging",
        "contractor"
    ],
    "wof:name":"Depew Gary Painting",
    "wof:placetype":"venue"
},
  "geometry": {"coordinates":[-82.462518,27.115987],"type":"Point"}
}