{
  "type": "Feature",
  "properties": {
    "iso:country":"US",
    "sg:address":"701 4th St",
    "sg:city":"Miami Beach",
    "sg:classifiers":[
        {
            "category":"Professional",
            "type":"Services"
        }
    ],
    "sg:phone":"+1 305 534 5701",
    "sg:postcode":"33139",
    "sg:province":"FL",
    "sg:website":"www.captureintegration.com",
    "wof:name":"Capture Integration",
    "wof:placetype":"venue"
},
  "geometry": {"coordinates":[-80.135453,25.773767],"type":"Point"}
}