{
  "type": "Feature",
  "properties": {
    "iso:country":"US",
    "sg:address":"7544 W McNab Rd",
    "sg:city":"North Lauderdale",
    "sg:classifiers":[
        {
            "category":"Retail",
            "subcategory":"Auto Repair",
            "type":"Services"
        }
    ],
    "sg:phone":"+1 954 720 9883",
    "sg:postcode":"33068",
    "sg:province":"FL",
    "sg:tags":[
        "repairing",
        "automobile",
        "general"
    ],
    "sg:website":"www.asecarcare.com",
    "wof:name":"Ase Car Care Specialists",
    "wof:placetype":"venue"
},
  "geometry": {"coordinates":[-80.228049,26.208362],"type":"Point"}
}