{
  "type": "Feature",
  "properties": {
    "addr:full":"418 S Tamiami Trl Osprey FL 34229",
    "addr:housenumber":"418",
    "addr:postcode":"34229",
    "addr:street":"S Tamiami Trl Osprey",
    "iso:country":"US",
    "sg:address":"418 S Tamiami Trl",
    "sg:city":"Osprey",
    "sg:classifiers":[
        {
            "category":"Autos & Motor Vehicles",
            "subcategory":"Fuel & Gas Station",
            "type":"Retail Goods"
        }
    ],
    "sg:phone":"+1 941 493 3232",
    "sg:postcode":"34229",
    "sg:province":"FL",
    "wof:name":"Gulf Coast Advisory Group",
    "wof:placetype":"venue"
},
  "geometry": {"coordinates":[-82.487737,27.190215],"type":"Point"}
}