{
  "type": "Feature",
  "properties": {
    "addr:full":"17620 NE 7th Pl Miami FL 33162",
    "addr:housenumber":"17620",
    "addr:postcode":"33162",
    "addr:street":"Ne 7Th Pl",
    "iso:country":"US",
    "sg:address":"17620 NE 7th Pl",
    "sg:city":"Miami",
    "sg:classifiers":[
        {
            "category":"Professional",
            "subcategory":"Business Services",
            "type":"Services"
        }
    ],
    "sg:phone":"+1 305 249 6860",
    "sg:postcode":"33162",
    "sg:province":"FL",
    "sg:tags":[
        "liquidator"
    ],
    "wof:name":"Joseph Liquidations",
    "wof:placetype":"venue"
},
  "geometry": {"coordinates":[-80.185028,25.936824],"type":"Point"}
}