{
  "type": "Feature",
  "properties": {
    "iso:country":"US",
    "sg:address":"2490 Broad St",
    "sg:city":"Brooksville",
    "sg:classifiers":[
        {
            "category":"Manufacturing",
            "subcategory":"Buildings",
            "type":"Manufacturing & Wholesale Goods"
        }
    ],
    "sg:phone":"+1 352 799 8584",
    "sg:postcode":"34604",
    "sg:province":"FL",
    "sg:tags":[
        "prefab"
    ],
    "wof:name":"Sylvan Grove Clubhouse",
    "wof:placetype":"venue"
},
  "geometry": {"coordinates":[-82.44308599999999,28.467563],"type":"Point"}
}