{
  "type": "Feature",
  "properties": {
    "addr:full":"7420 N Devon Dr Fort Lauderdale FL 33321",
    "addr:housenumber":"7420",
    "addr:postcode":"33321",
    "addr:street":"N Devon Dr",
    "iso:country":"US",
    "sg:address":"7420 N Devon Dr",
    "sg:city":"Fort Lauderdale",
    "sg:classifiers":[
        {
            "category":"Building & Trades",
            "subcategory":"Construction",
            "type":"Services"
        }
    ],
    "sg:phone":"+1 954 821 4696",
    "sg:postcode":"33321",
    "sg:province":"FL",
    "sg:tags":[
        "hardware",
        "floor",
        "laying",
        "contractor"
    ],
    "wof:name":"L Slater Inc",
    "wof:placetype":"venue"
},
  "geometry": {"coordinates":[-80.294634,26.218206],"type":"Point"}
}