{
  "type": "Feature",
  "properties": {
    "iso:country":"US",
    "sg:address":"7500 NW 25th St",
    "sg:city":"Miami",
    "sg:classifiers":[
        {
            "category":"Freight",
            "type":"Transportation"
        }
    ],
    "sg:phone":"+1 305 591 4680",
    "sg:postcode":"33122",
    "sg:province":"FL",
    "sg:tags":[
        "household",
        "appliance",
        "general"
    ],
    "wof:name":"Sears Roebuck and Co Inc",
    "wof:placetype":"venue"
},
  "geometry": {"coordinates":[-80.320548,25.797041],"type":"Point"}
}