{
  "type": "Feature",
  "properties": {
    "addr:full":"2331 Wilton Dr Fort Lauderdale FL 33305",
    "addr:housenumber":"2331",
    "addr:postcode":"33305",
    "addr:street":"Wilton Dr",
    "iso:country":"US",
    "sg:address":"2331 Wilton Dr",
    "sg:city":"Fort Lauderdale",
    "sg:classifiers":[
        {
            "category":"Personal",
            "subcategory":"Beauty Salon",
            "type":"Services"
        }
    ],
    "sg:phone":"+1 954 564 2323",
    "sg:postcode":"33305",
    "sg:province":"FL",
    "sg:tags":[
        "shop"
    ],
    "wof:name":"Tracy L Carroll Salon",
    "wof:placetype":"venue"
},
  "geometry": {"coordinates":[-80.13556199999999,26.157891],"type":"Point"}
}