{
  "type": "Feature",
  "properties": {
    "iso:country":"US",
    "sg:address":"1459 Sanibel Ln",
    "sg:city":"Gulf Breeze",
    "sg:classifiers":[
        {
            "category":"Building & Trades",
            "subcategory":"Construction",
            "type":"Services"
        }
    ],
    "sg:phone":"+1 850 529 0075",
    "sg:postcode":"32563",
    "sg:province":"FL",
    "sg:tags":[
        "handyman"
    ],
    "wof:name":"Handyman Solutions",
    "wof:placetype":"venue"
},
  "geometry": {"coordinates":[-87.111401,30.384335],"type":"Point"}
}