{
  "type": "Feature",
  "properties": {
    "addr:full":"18793 125th Ave N Jupiter FL 33478",
    "addr:housenumber":"18793",
    "addr:postcode":"33478",
    "addr:street":"125Th Ave N",
    "iso:country":"US",
    "sg:address":"18793 125th Ave N",
    "sg:city":"Jupiter",
    "sg:classifiers":[
        {
            "category":"Building & Trades",
            "subcategory":"Plumbing",
            "type":"Services"
        }
    ],
    "sg:phone":"+1 561 684 6383",
    "sg:postcode":"33478",
    "sg:province":"FL",
    "sg:tags":[
        "contractor"
    ],
    "wof:name":"Rayman Air Conditioning",
    "wof:placetype":"venue"
},
  "geometry": {"coordinates":[-80.231094,26.953838],"type":"Point"}
}