{
  "type": "Feature",
  "properties": {
    "iso:country":"US",
    "sg:address":"3301 54th Ave N",
    "sg:city":"Saint Petersburg",
    "sg:classifiers":[
        {
            "category":"Bars & Pubs",
            "type":"Food & Drink"
        }
    ],
    "sg:phone":"+1 727 522 5615",
    "sg:postcode":"33714",
    "sg:province":"FL",
    "sg:tags":[
        "drinking"
    ],
    "wof:name":"The Den",
    "wof:placetype":"venue"
},
  "geometry": {"coordinates":[-82.67953199999999,27.821075],"type":"Point"}
}