{
  "type": "Feature",
  "properties": {
    "iso:country":"US",
    "sg:address":"280 SW 14th Ave",
    "sg:city":"Pompano Beach",
    "sg:classifiers":[
        {
            "category":"Home & Garden",
            "subcategory":"Building Materials",
            "type":"Retail Goods"
        }
    ],
    "sg:phone":"+1 954 783 0110",
    "sg:postcode":"33069",
    "sg:province":"FL",
    "wof:name":"Kinco Ltd",
    "wof:placetype":"venue"
},
  "geometry": {"coordinates":[-80.142152,26.227449],"type":"Point"}
}