{
  "type": "Feature",
  "properties": {
    "iso:country":"US",
    "sg:address":"2101 Starkey Rd",
    "sg:city":"Largo",
    "sg:classifiers":[
        {
            "category":"Retail",
            "subcategory":"Auto Repair",
            "type":"Services"
        }
    ],
    "sg:phone":"+1 727 535 3487",
    "sg:postcode":"33771",
    "sg:province":"FL",
    "sg:tags":[
        "repairing",
        "automobile"
    ],
    "wof:name":"Mecanica Extrema",
    "wof:placetype":"venue"
},
  "geometry": {"coordinates":[-82.76233000000001,27.899641],"type":"Point"}
}