{
  "type": "Feature",
  "properties": {
    "addr:full":"3185 Boutwell Rd Lake Worth FL 33461",
    "addr:postcode":"3185;33461",
    "addr:street":"Boutwell Rd",
    "iso:country":"US",
    "sg:address":"3185 Boutwell Rd",
    "sg:city":"Lake Worth",
    "sg:classifiers":[
        {
            "category":"Government",
            "subcategory":"Jail",
            "type":"Public Place"
        }
    ],
    "sg:phone":"+1 561 547 0701",
    "sg:postcode":"33461",
    "sg:province":"FL",
    "sg:tags":[
        "correctional",
        "institution"
    ],
    "wof:name":"West Palm Beach Probation Off",
    "wof:placetype":"venue"
},
  "geometry": {"coordinates":[-80.075554,26.629534],"type":"Point"}
}