{
  "type": "Feature",
  "properties": {
    "iso:country":"US",
    "sg:address":"8389 Taylor Field Rd",
    "sg:city":"Jacksonville",
    "sg:classifiers":[
        {
            "category":"Building & Trades",
            "subcategory":"Construction",
            "type":"Services"
        }
    ],
    "sg:phone":"+1 904 778 4827",
    "sg:postcode":"32244",
    "sg:province":"FL",
    "sg:tags":[
        "concrete",
        "contractor"
    ],
    "wof:name":"Big Country Concrete",
    "wof:placetype":"venue"
},
  "geometry": {"coordinates":[-81.793262,30.211144],"type":"Point"}
}