{
  "type": "Feature",
  "properties": {
    "iso:country":"US",
    "sg:address":"3451 Bonita Bay Blvd",
    "sg:city":"Bonita Springs",
    "sg:classifiers":[
        {
            "category":"Professional",
            "subcategory":"Lawyer & Legal Services",
            "type":"Services"
        }
    ],
    "sg:phone":"+1 239 498 6222",
    "sg:postcode":"34134",
    "sg:province":"FL",
    "sg:tags":[
        "attorney"
    ],
    "wof:name":"Henderson Franklin Starnes",
    "wof:placetype":"venue"
},
  "geometry": {"coordinates":[-81.809445,26.347021],"type":"Point"}
}