{
  "type": "Feature",
  "properties": {
    "iso:country":"US",
    "sg:address":"4109 Driskell Rd",
    "sg:city":"Milton",
    "sg:classifiers":[
        {
            "category":"Travel",
            "subcategory":"Campground",
            "type":"Entertainment"
        }
    ],
    "sg:phone":"+1 850 983 2067",
    "sg:postcode":"32583",
    "sg:province":"FL",
    "sg:tags":[
        "camp"
    ],
    "wof:name":"Ski-Land Fish Camp",
    "wof:placetype":"venue"
},
  "geometry": {"coordinates":[-86.99039500000001,30.58333],"type":"Point"}
}