{
  "type": "Feature",
  "properties": {
    "iso:country":"US",
    "sg:address":"3938 Britton Plz",
    "sg:city":"Tampa",
    "sg:classifiers":[
        {
            "category":"Cinema",
            "subcategory":"Movie Theater",
            "type":"Entertainment"
        }
    ],
    "sg:phone":"+1 813 839 1600",
    "sg:postcode":"33611",
    "sg:province":"FL",
    "wof:name":"Five Star Cinemas",
    "wof:placetype":"venue"
},
  "geometry": {"coordinates":[-82.50514800000001,27.90647],"type":"Point"}
}