{
  "type": "Feature",
  "properties": {
    "iso:country":"US",
    "sg:address":"10126 W Flagler St",
    "sg:city":"Miami",
    "sg:classifiers":[
        {
            "category":"Insurance",
            "subcategory":"Insurance Agent",
            "type":"Services"
        }
    ],
    "sg:phone":"+1 305 485 0116",
    "sg:postcode":"33174",
    "sg:province":"FL",
    "wof:name":"Sardy's Insurance",
    "wof:placetype":"venue"
},
  "geometry": {"coordinates":[-80.360715,25.768686],"type":"Point"}
}