{
  "type": "Feature",
  "properties": {
    "iso:country":"US",
    "sg:address":"120 Northside Plz",
    "sg:city":"Miami",
    "sg:classifiers":[
        {
            "category":"Education",
            "subcategory":"Special Training",
            "type":"Public Place"
        }
    ],
    "sg:phone":"+1 305 836 0070",
    "sg:postcode":"33147",
    "sg:province":"FL",
    "sg:tags":[
        "tutoring"
    ],
    "wof:name":"Ombudsman Educational Svc",
    "wof:placetype":"venue"
},
  "geometry": {"coordinates":[-80.243083,25.849422],"type":"Point"}
}