{
  "type": "Feature",
  "properties": {
    "addr:full":"82 E Johnson Ave Pensacola FL 32534",
    "addr:housenumber":"82",
    "addr:postcode":"32534",
    "addr:street":"E Johnson Ave",
    "iso:country":"US",
    "sg:address":"82 E Johnson Ave",
    "sg:city":"Pensacola",
    "sg:classifiers":[
        {
            "category":"Retail",
            "subcategory":"Repair Shop",
            "type":"Services"
        }
    ],
    "sg:phone":"+1 850 473 0777",
    "sg:postcode":"32534",
    "sg:province":"FL",
    "sg:tags":[
        "appliance"
    ],
    "wof:name":"All American Appliance Svc Co",
    "wof:placetype":"venue"
},
  "geometry": {"coordinates":[-87.264025,30.519667],"type":"Point"}
}