{
  "type": "Feature",
  "properties": {
    "iso:country":"US",
    "sg:address":"245 SE 1st St",
    "sg:city":"Miami",
    "sg:classifiers":[
        {
            "category":"Professional",
            "type":"Services"
        }
    ],
    "sg:phone":"+1 305 371 3557",
    "sg:postcode":"33131",
    "sg:province":"FL",
    "sg:tags":[
        "establishment"
    ],
    "wof:name":"Hiram Enterprises Co",
    "wof:placetype":"venue"
},
  "geometry": {"coordinates":[-80.18946,25.773497],"type":"Point"}
}