{
  "type": "Feature",
  "properties": {
    "iso:country":"US",
    "sg:address":"11 Triangle Park",
    "sg:city":"Lake Placid",
    "sg:classifiers":[
        {
            "category":"Retail",
            "subcategory":"Laundry & Dry Cleaning",
            "type":"Services"
        },
        {
            "category":"Shopping",
            "subcategory":"Clothing, Apparel, & Fashions",
            "type":"Retail Goods"
        }
    ],
    "sg:phone":"+1 863 699 9901",
    "sg:postcode":"33852",
    "sg:province":"FL",
    "sg:tags":[
        "alteration"
    ],
    "wof:name":"Anna's Alterations",
    "wof:placetype":"venue"
},
  "geometry": {"coordinates":[-81.354445,27.29881],"type":"Point"}
}