{
  "type": "Feature",
  "properties": {
    "addr:full":"4626 Mirabella Ct St Pete Beach FL 33706",
    "addr:housenumber":"4626",
    "addr:postcode":"33706",
    "addr:street":"Mirabella Ct St Pete Beach",
    "iso:country":"US",
    "sg:address":"4626 Mirabella Ct",
    "sg:city":"St Pete Beach",
    "sg:classifiers":[
        {
            "category":"Professional",
            "subcategory":"Computer Services",
            "type":"Services"
        }
    ],
    "sg:phone":"+1 727 360 7672",
    "sg:postcode":"33706",
    "sg:province":"FL",
    "sg:tags":[
        "consultant"
    ],
    "wof:name":"Allen J Cohen & Assoc Inc",
    "wof:placetype":"venue"
},
  "geometry": {"coordinates":[-82.737791,27.722522],"type":"Point"}
}