{
  "type": "Feature",
  "properties": {
    "addr:full":"7730 W Hillsborough Ave Tampa FL 33615",
    "addr:housenumber":"7730",
    "addr:postcode":"33615",
    "addr:street":"W Hillsborough Ave",
    "iso:country":"US",
    "sg:address":"7730 W Hillsborough Ave",
    "sg:city":"Tampa",
    "sg:classifiers":[
        {
            "category":"Insurance",
            "subcategory":"Insurance Agent",
            "type":"Services"
        }
    ],
    "sg:phone":"+1 813 884 8680",
    "sg:postcode":"33615",
    "sg:province":"FL",
    "wof:name":"Routt Insurance & Travel",
    "wof:placetype":"venue"
},
  "geometry": {"coordinates":[-82.56700600000001,27.99653],"type":"Point"}
}