{
  "type": "Feature",
  "properties": {
    "addr:full":"1000 W Osceola Pkwy Kissimmee FL 34741",
    "addr:housenumber":"1000",
    "addr:postcode":"34741",
    "addr:street":"W Osceola Pkwy",
    "iso:country":"US",
    "sg:address":"1000 W Osceola Pkwy",
    "sg:city":"Kissimmee",
    "sg:classifiers":[
        {
            "category":"Banks & Credit Unions",
            "subcategory":"Bank",
            "type":"Services"
        }
    ],
    "sg:phone":"+1 407 846 2678",
    "sg:postcode":"34741",
    "sg:province":"FL",
    "wof:name":"First National Bank",
    "wof:placetype":"venue"
},
  "geometry": {"coordinates":[-81.406029,28.33718],"type":"Point"}
}