{
  "type": "Feature",
  "properties": {
    "addr:full":"1056 Oakpoint Cir Apopka FL 32712",
    "addr:housenumber":"1056",
    "addr:postcode":"32712",
    "addr:street":"Oakpoint Cir",
    "iso:country":"US",
    "sg:address":"1056 Oakpoint Cir",
    "sg:city":"Apopka",
    "sg:classifiers":[
        {
            "category":"Shopping",
            "subcategory":"Books",
            "type":"Retail Goods"
        }
    ],
    "sg:phone":"+1 407 884 0065",
    "sg:postcode":"32712",
    "sg:province":"FL",
    "wof:name":"Terminal Consent",
    "wof:placetype":"venue"
},
  "geometry": {"coordinates":[-81.49435,28.692344],"type":"Point"}
}