{
  "type": "Feature",
  "properties": {
    "iso:country":"US",
    "sg:address":"825 Wright Dr",
    "sg:city":"Lake Worth",
    "sg:classifiers":[
        {
            "category":"Banks & Credit Unions",
            "subcategory":"Bank",
            "type":"Services"
        }
    ],
    "sg:phone":"+1 561 586 1126",
    "sg:postcode":"33461",
    "sg:province":"FL",
    "sg:tags":[
        "loan",
        "real estate"
    ],
    "wof:name":"Florida Mortgage Pro Inc",
    "wof:placetype":"venue"
},
  "geometry": {"coordinates":[-80.07189,26.604925],"type":"Point"}
}