{
  "type": "Feature",
  "properties": {
    "addr:full":"1605 Main St. Suite 700 Sarasota FL 34236",
    "addr:housenumber":"1605",
    "addr:postcode":"34236",
    "addr:street":"Main St. Suite 700",
    "iso:country":"US",
    "sg:address":"1605 Main St. Suite 700",
    "sg:city":"Sarasota",
    "sg:classifiers":[
        {
            "category":"Professional",
            "subcategory":"Computer Services",
            "type":"Services"
        }
    ],
    "sg:postcode":"34236",
    "sg:province":"FL",
    "sg:tags":[
        "social-networking",
        "online-communities",
        "events",
        "conferences"
    ],
    "sg:website":"http://www.leebug.com",
    "wof:name":"Leebug",
    "wof:placetype":"venue"
},
  "geometry": {"coordinates":[-82.537598,27.336535],"type":"Point"}
}