{
  "type": "Feature",
  "properties": {
    "addr:full":"520 NW 72nd Ln Miami FL 33150",
    "addr:housenumber":"520",
    "addr:postcode":"33150",
    "addr:street":"Nw 72Nd Ln",
    "iso:country":"US",
    "sg:address":"520 NW 72nd Ln",
    "sg:city":"Miami",
    "sg:classifiers":[
        {
            "category":"Government",
            "subcategory":"Office",
            "type":"Public Place"
        }
    ],
    "sg:phone":"+1 305 751 7061",
    "sg:postcode":"33150",
    "sg:province":"FL",
    "wof:name":"Dade County Project STOPP",
    "wof:placetype":"venue"
},
  "geometry": {"coordinates":[-80.203656,25.842374],"type":"Point"}
}