{
  "type": "Feature",
  "properties": {
    "addr:full":"1112 Lake Dr Cocoa FL 32922",
    "addr:housenumber":"1112",
    "addr:postcode":"32922",
    "addr:street":"Lake Dr",
    "iso:country":"US",
    "sg:address":"1112 Lake Dr",
    "sg:city":"Cocoa",
    "sg:classifiers":[
        {
            "category":"Personal",
            "subcategory":"Tattoo Parlor",
            "type":"Services"
        }
    ],
    "sg:phone":"+1 321 636 0600",
    "sg:postcode":"32922",
    "sg:province":"FL",
    "sg:tags":[
        "tattooing"
    ],
    "wof:name":"Electric Eye Tattoo Studio",
    "wof:placetype":"venue"
},
  "geometry": {"coordinates":[-80.74485900000001,28.356139],"type":"Point"}
}