{
  "type": "Feature",
  "properties": {
    "iso:country":"US",
    "sg:address":"201 Osceola Ave",
    "sg:city":"Daytona Beach",
    "sg:classifiers":[
        {
            "category":"Organizations",
            "subcategory":"Religious Organization",
            "type":"Services"
        }
    ],
    "sg:phone":"+1 386 258 7788",
    "sg:postcode":"32114",
    "sg:province":"FL",
    "sg:tags":[
        "church"
    ],
    "sg:website":"www.halifaxbaptist.org",
    "wof:name":"Halifax Baptist Association",
    "wof:placetype":"venue"
},
  "geometry": {"coordinates":[-81.011403,29.189593],"type":"Point"}
}