{
  "type": "Feature",
  "properties": {
    "addr:full":"1535 Ridge Ave Daytona Beach FL 32117",
    "addr:housenumber":"1535",
    "addr:postcode":"32117",
    "addr:street":"Ridge Ave",
    "iso:country":"US",
    "sg:address":"1535 Ridge Ave",
    "sg:city":"Daytona Beach",
    "sg:classifiers":[
        {
            "category":"Building & Trades",
            "subcategory":"Construction",
            "type":"Services"
        }
    ],
    "sg:phone":"+1 386 677 7345",
    "sg:postcode":"32117",
    "sg:province":"FL",
    "sg:tags":[
        "contractor"
    ],
    "wof:name":"Jeffs Stucco & Plastering",
    "wof:placetype":"venue"
},
  "geometry": {"coordinates":[-81.044983,29.254943],"type":"Point"}
}