{
  "type": "Feature",
  "properties": {
    "iso:country":"US",
    "sg:address":"8050 Spyglass Hill Rd",
    "sg:city":"Melbourne",
    "sg:classifiers":[
        {
            "category":"Health Services",
            "subcategory":"Nursing And Care Facility",
            "type":"Services"
        }
    ],
    "sg:phone":"+1 321 752 1000",
    "sg:postcode":"32940",
    "sg:province":"FL",
    "sg:tags":[
        "home",
        "convalescent"
    ],
    "sg:website":"www.wuesthoff.org",
    "wof:name":"Wuesthoff Progressive Care Ctr",
    "wof:placetype":"venue"
},
  "geometry": {"coordinates":[-80.70168,28.237354],"type":"Point"}
}