{
  "type": "Feature",
  "properties": {
    "addr:full":"555 NE 15th St Ste 102 Miami FL 33132",
    "addr:housenumber":"555",
    "addr:postcode":"33132",
    "addr:street":"Ne 15Th St Ste 102",
    "iso:country":"US",
    "sg:address":"555 NE 15th St Ste 102",
    "sg:city":"Miami",
    "sg:classifiers":[
        {
            "category":"Professional",
            "subcategory":"Management & Consulting",
            "type":"Services"
        }
    ],
    "sg:phone":"+1 305 373 6084",
    "sg:postcode":"33132",
    "sg:province":"FL",
    "sg:tags":[
        "consultant"
    ],
    "wof:name":"Cruise Services Internati",
    "wof:placetype":"venue"
},
  "geometry": {"coordinates":[-80.185795,25.789659],"type":"Point"}
}