{
  "type": "Feature",
  "properties": {
    "iso:country":"US",
    "sg:address":"610 N Brevard Ave",
    "sg:city":"Arcadia",
    "sg:classifiers":[
        {
            "category":"Autos & Motor Vehicles",
            "subcategory":"Fuel & Gas Station",
            "type":"Retail Goods"
        }
    ],
    "sg:phone":"+1 863 494 7062",
    "sg:postcode":"34266",
    "sg:province":"FL",
    "wof:name":"George's Highway Shell",
    "wof:placetype":"venue"
},
  "geometry": {"coordinates":[-81.855797,27.224322],"type":"Point"}
}