{
  "type": "Feature",
  "properties": {
    "addr:full":"3700 Lakeside Dr Miramar FL 33027",
    "addr:housenumber":"3700",
    "addr:postcode":"33027",
    "addr:street":"Lakeside Dr",
    "iso:country":"US",
    "sg:address":"3700 Lakeside Dr",
    "sg:city":"Miramar",
    "sg:classifiers":[
        {
            "category":"Real Estate",
            "subcategory":"Real Estate Services",
            "type":"Services"
        }
    ],
    "sg:phone":"+1 954 438 2110",
    "sg:postcode":"33027",
    "sg:province":"FL",
    "sg:tags":[
        "company",
        "title"
    ],
    "wof:name":"Champion Title & Trust Corp",
    "wof:placetype":"venue"
},
  "geometry": {"coordinates":[-80.346062,25.976007],"type":"Point"}
}