{
  "type": "Feature",
  "properties": {
    "iso:country":"US",
    "sg:address":"18400 NE 5th Ave",
    "sg:city":"Miami",
    "sg:classifiers":[
        {
            "category":"Professional",
            "subcategory":"Business Services",
            "type":"Services"
        }
    ],
    "sg:phone":"+1 305 653 5255",
    "sg:postcode":"33179",
    "sg:province":"FL",
    "sg:tags":[
        "development",
        "product",
        "designers-industrial",
        "marketing",
        "commercial",
        "design"
    ],
    "wof:name":"Jeanmarie Interiors",
    "wof:placetype":"venue"
},
  "geometry": {"coordinates":[-80.18891000000001,25.942526],"type":"Point"}
}