{
  "type": "Feature",
  "properties": {
    "iso:country":"US",
    "sg:address":"900 N Atlantic Ave",
    "sg:city":"Cocoa Beach",
    "sg:classifiers":[
        {
            "category":"Wholesale",
            "subcategory":"Hardware",
            "type":"Manufacturing & Wholesale Goods"
        }
    ],
    "sg:phone":"+1 321 783 8800",
    "sg:postcode":"32931",
    "sg:province":"FL",
    "sg:tags":[
        "equipment",
        "energy",
        "solar"
    ],
    "wof:name":"Solar Club",
    "wof:placetype":"venue"
},
  "geometry": {"coordinates":[-80.61051500000001,28.33231],"type":"Point"}
}