{
  "type": "Feature",
  "properties": {
    "iso:country":"US",
    "sg:address":"13474 Southern Way",
    "sg:city":"Windermere",
    "sg:classifiers":[
        {
            "category":"Building & Trades",
            "subcategory":"Construction",
            "type":"Services"
        }
    ],
    "sg:phone":"+1 407 654 5900",
    "sg:postcode":"34786",
    "sg:province":"FL",
    "sg:tags":[
        "contractor"
    ],
    "wof:name":"M J Smith Builders Inc",
    "wof:placetype":"venue"
},
  "geometry": {"coordinates":[-81.581896,28.48676],"type":"Point"}
}