{
  "type": "Feature",
  "properties": {
    "addr:full":"807 Bryson Loop Lakeland FL 33809",
    "addr:housenumber":"807",
    "addr:postcode":"33809",
    "addr:street":"Bryson Loop",
    "iso:country":"US",
    "sg:address":"807 Bryson Loop",
    "sg:city":"Lakeland",
    "sg:classifiers":[
        {
            "category":"Professional",
            "subcategory":"Management & Consulting",
            "type":"Services"
        }
    ],
    "sg:phone":"+1 863 640 3230",
    "sg:postcode":"33809",
    "sg:province":"FL",
    "sg:tags":[
        "photography",
        "commercial"
    ],
    "wof:name":"Billin Consulting",
    "wof:placetype":"venue"
},
  "geometry": {"coordinates":[-81.939049,28.134589],"type":"Point"}
}