{
  "type": "Feature",
  "properties": {
    "iso:country":"US",
    "sg:address":"2944 S Kirkman Rd",
    "sg:city":"Orlando",
    "sg:classifiers":[
        {
            "category":"Restaurant",
            "type":"Food & Drink"
        }
    ],
    "sg:menulink":"http://www.allmenus.com/fl/orlando/187529-mcdonalds/menu/",
    "sg:phone":"+1 407 296 6265",
    "sg:postcode":"32811",
    "sg:province":"FL",
    "sg:tags":[
        "burger",
        "american"
    ],
    "wof:name":"McDonald's",
    "wof:placetype":"venue"
},
  "geometry": {"coordinates":[-81.459789,28.511449],"type":"Point"}
}