{
  "type": "Feature",
  "properties": {
    "iso:country":"US",
    "sg:address":"227 5th Ave",
    "sg:city":"Melbourne Beach",
    "sg:classifiers":[
        {
            "category":"Professional",
            "subcategory":"Employment Agencies",
            "type":"Services"
        }
    ],
    "sg:phone":"+1 321 951 0934",
    "sg:postcode":"32951",
    "sg:province":"FL",
    "wof:name":"Staffing4u Careers4u Inc",
    "wof:placetype":"venue"
},
  "geometry": {"coordinates":[-80.557564,28.063432],"type":"Point"}
}