{
  "type": "Feature",
  "properties": {
    "iso:country":"US",
    "sg:address":"2120 Dennis St",
    "sg:city":"Jacksonville",
    "sg:classifiers":[
        {
            "category":"Home & Garden",
            "subcategory":"Carpets & Floor Coverings",
            "type":"Retail Goods"
        }
    ],
    "sg:phone":"+1 904 356 6283",
    "sg:postcode":"32204",
    "sg:province":"FL",
    "sg:tags":[
        "rigger"
    ],
    "wof:name":"Agents House International",
    "wof:placetype":"venue"
},
  "geometry": {"coordinates":[-81.683789,30.330039],"type":"Point"}
}