{
  "type": "Feature",
  "properties": {
    "iso:country":"US",
    "sg:address":"1357 Seminole Dr",
    "sg:city":"Fort Lauderdale",
    "sg:classifiers":[
        {
            "category":"Real Estate",
            "subcategory":"Real Estate Agent",
            "type":"Services"
        }
    ],
    "sg:phone":"+1 954 565 8867",
    "sg:postcode":"33304",
    "sg:province":"FL",
    "wof:name":"Shoppes of Wiles Road LLC",
    "wof:placetype":"venue"
},
  "geometry": {"coordinates":[-80.11127399999999,26.142567],"type":"Point"}
}