{
  "type": "Feature",
  "properties": {
    "addr:full":"4416 W Wyoming Ave Tampa FL 33616",
    "addr:housenumber":"4416",
    "addr:postcode":"33616",
    "addr:street":"W Wyoming Ave",
    "iso:country":"US",
    "sg:address":"4416 W Wyoming Ave",
    "sg:city":"Tampa",
    "sg:classifiers":[
        {
            "category":"Building & Trades",
            "subcategory":"Construction",
            "type":"Services"
        }
    ],
    "sg:phone":"+1 813 839 8784",
    "sg:postcode":"33616",
    "sg:province":"FL",
    "sg:tags":[
        "steel",
        "erection",
        "structural"
    ],
    "wof:name":"Southern Rebar Inc",
    "wof:placetype":"venue"
},
  "geometry": {"coordinates":[-82.522158,27.88238],"type":"Point"}
}