{
  "type": "Feature",
  "properties": {
    "addr:full":"4225 Woodbine Rd Pace FL 32571",
    "addr:housenumber":"4225",
    "addr:postcode":"32571",
    "addr:street":"Woodbine Rd",
    "iso:country":"US",
    "sg:address":"4225 Woodbine Rd",
    "sg:city":"Pace",
    "sg:classifiers":[
        {
            "category":"Health Services",
            "subcategory":"Doctor",
            "type":"Services"
        }
    ],
    "sg:phone":"+1 850 995 0875",
    "sg:postcode":"32571",
    "sg:province":"FL",
    "sg:tags":[
        "physician",
        "surgeon"
    ],
    "wof:name":"Robert A Althar Facs",
    "wof:placetype":"venue"
},
  "geometry": {"coordinates":[-87.181746,30.623116],"type":"Point"}
}