{
  "type": "Feature",
  "properties": {
    "iso:country":"US",
    "sg:address":"16979 Old US Hwy 41",
    "sg:city":"Naples",
    "sg:classifiers":[
        {
            "category":"Real Estate",
            "subcategory":"Developer",
            "type":"Services"
        }
    ],
    "sg:phone":"+1 239 566 1303",
    "sg:postcode":"34110",
    "sg:province":"FL",
    "wof:name":"North Naples Golf Range",
    "wof:placetype":"venue"
},
  "geometry": {"coordinates":[-81.789508,26.315495],"type":"Point"}
}