{
  "type": "Feature",
  "properties": {
    "iso:country":"US",
    "sg:address":"10475 NW 7 AVENUE",
    "sg:city":"Miami",
    "sg:classifiers":[
        {
            "category":"Insurance",
            "subcategory":"Hazard Insurance",
            "type":"Services"
        }
    ],
    "sg:phone":"+1 305 754 8700",
    "sg:postcode":"33150",
    "sg:province":"FL",
    "sg:website":"www.prestigeinsurancespecialists...",
    "wof:name":"Prestige Insurance Specialists",
    "wof:placetype":"venue"
},
  "geometry": {"coordinates":[-80.20996700000001,25.870708],"type":"Point"}
}