{
  "type": "Feature",
  "properties": {
    "addr:full":"2516 Templewood Dr Holiday FL 34690",
    "addr:housenumber":"2516",
    "addr:postcode":"34690",
    "addr:street":"Templewood Dr",
    "iso:country":"US",
    "sg:address":"2516 Templewood Dr",
    "sg:city":"Holiday",
    "sg:classifiers":[
        {
            "category":"Building & Trades",
            "subcategory":"Landscaping Services",
            "type":"Services"
        }
    ],
    "sg:phone":"+1 727 645 1715",
    "sg:postcode":"34690",
    "sg:province":"FL",
    "sg:tags":[
        "stump",
        "tree",
        "grinding",
        "removal",
        "arborist"
    ],
    "wof:name":"Michael Cornett Tree Service",
    "wof:placetype":"venue"
},
  "geometry": {"coordinates":[-82.73546,28.195464],"type":"Point"}
}