{
  "type": "Feature",
  "properties": {
    "iso:country":"US",
    "sg:address":"6440 Fort King Rd",
    "sg:city":"Zephyrhills",
    "sg:classifiers":[
        {
            "category":"Home & Garden",
            "subcategory":"Building Materials",
            "type":"Retail Goods"
        },
        {
            "category":"Wholesale",
            "subcategory":"Metals & Minerals",
            "type":"Manufacturing & Wholesale Goods"
        }
    ],
    "sg:phone":"+1 813 782 3513",
    "sg:postcode":"33542",
    "sg:province":"FL",
    "sg:tags":[
        "aluminum"
    ],
    "wof:name":"Bahr's Aluminum & Hardware Inc",
    "wof:placetype":"venue"
},
  "geometry": {"coordinates":[-82.190842,28.251132],"type":"Point"}
}