{
  "type": "Feature",
  "properties": {
    "addr:full":"6975 66th St Pinellas Park FL 33781",
    "addr:housenumber":"6975",
    "addr:postcode":"33781",
    "addr:street":"66Th St",
    "iso:country":"US",
    "sg:address":"6975 66th St",
    "sg:city":"Pinellas Park",
    "sg:classifiers":[
        {
            "category":"Restaurant",
            "type":"Food & Drink"
        }
    ],
    "sg:menulink":"http://www.allmenus.com/fl/st-petersburg/82161-dominos-pizza/menu/",
    "sg:phone":"+1 727 541 7793",
    "sg:postcode":"33781",
    "sg:province":"FL",
    "sg:tags":[
        "american",
        "wing",
        "pizza"
    ],
    "wof:name":"Domino's Pizza",
    "wof:placetype":"venue"
},
  "geometry": {"coordinates":[-82.728357,27.835193],"type":"Point"}
}