{
  "type": "Feature",
  "properties": {
    "iso:country":"US",
    "sg:address":"1651 Keyway Rd",
    "sg:city":"Englewood",
    "sg:classifiers":[
        {
            "category":"Retail",
            "subcategory":"Laundry & Dry Cleaning",
            "type":"Services"
        }
    ],
    "sg:phone":"+1 941 485 7781",
    "sg:postcode":"34223",
    "sg:province":"FL",
    "sg:tags":[
        "cleaners",
        "rug",
        "carpet"
    ],
    "wof:name":"Crystal Carpet Cleaners",
    "wof:placetype":"venue"
},
  "geometry": {"coordinates":[-82.391375,27.006513],"type":"Point"}
}