{
  "type": "Feature",
  "properties": {
    "iso:country":"US",
    "sg:address":"1308 14th St W",
    "sg:city":"Bradenton",
    "sg:classifiers":[
        {
            "category":"Autos & Motor Vehicles",
            "subcategory":"Automobile Sales",
            "type":"Retail Goods"
        }
    ],
    "sg:phone":"+1 941 747 3441",
    "sg:postcode":"34205",
    "sg:province":"FL",
    "sg:tags":[
        "used",
        "classic"
    ],
    "wof:name":"Chandler's Classic Cars",
    "wof:placetype":"venue"
},
  "geometry": {"coordinates":[-82.575371,27.487297],"type":"Point"}
}