{
  "type": "Feature",
  "properties": {
    "iso:country":"US",
    "sg:address":"958 Explorer Cove",
    "sg:city":"Altamonte Spgs",
    "sg:classifiers":[
        {
            "category":"Manufacturing",
            "subcategory":"Building Materials",
            "type":"Manufacturing & Wholesale Goods"
        }
    ],
    "sg:phone":"+1 407 831 8383",
    "sg:postcode":"32701",
    "sg:province":"FL",
    "sg:tags":[
        "bathroom",
        "mfg",
        "cabinet",
        "wood",
        "kitchen",
        "vanity"
    ],
    "wof:name":"Advanced Euro Inc",
    "wof:placetype":"venue"
},
  "geometry": {"coordinates":[-81.35816699999999,28.68265],"type":"Point"}
}