{
  "type": "Feature",
  "properties": {
    "iso:country":"US",
    "sg:address":"4430 Tomlinson Cir",
    "sg:city":"Orlando",
    "sg:classifiers":[
        {
            "category":"Shopping",
            "subcategory":"Books",
            "type":"Retail Goods"
        },
        {
            "category":"Wholesale",
            "subcategory":"Books, Periodicals, & Newspapers",
            "type":"Manufacturing & Wholesale Goods"
        }
    ],
    "sg:phone":"+1 407 381 9316",
    "sg:postcode":"32829",
    "sg:province":"FL",
    "sg:tags":[
        "books-wholesale",
        "store",
        "manufacturer"
    ],
    "wof:name":"Levy Books",
    "wof:placetype":"venue"
},
  "geometry": {"coordinates":[-81.26118099999999,28.490938],"type":"Point"}
}