{
  "type": "Feature",
  "properties": {
    "addr:full":"2351 Mango Ave Sarasota FL 34234",
    "addr:housenumber":"2351",
    "addr:postcode":"34234",
    "addr:street":"Mango Ave",
    "iso:country":"US",
    "sg:address":"2351 Mango Ave",
    "sg:city":"Sarasota",
    "sg:classifiers":[
        {
            "category":"Building & Trades",
            "subcategory":"Cleaning & Sanitation",
            "type":"Services"
        }
    ],
    "sg:phone":"+1 941 504 4965",
    "sg:postcode":"34234",
    "sg:province":"FL",
    "sg:tags":[
        "house"
    ],
    "wof:name":"Patricia Smith All Occasions",
    "wof:placetype":"venue"
},
  "geometry": {"coordinates":[-82.526376,27.357263],"type":"Point"}
}