{
  "type": "Feature",
  "properties": {
    "iso:country":"US",
    "sg:address":"4838 Bonton Dr",
    "sg:city":"Holiday",
    "sg:classifiers":[
        {
            "category":"Personal",
            "subcategory":"Beauty Salon",
            "type":"Services"
        }
    ],
    "sg:phone":"+1 727 937 7557",
    "sg:postcode":"34690",
    "sg:province":"FL",
    "sg:tags":[
        "hair",
        "stylist"
    ],
    "wof:name":"Ann's Hair Styles Etc",
    "wof:placetype":"venue"
},
  "geometry": {"coordinates":[-82.73356800000001,28.191958],"type":"Point"}
}