{
  "type": "Feature",
  "properties": {
    "iso:country":"US",
    "sg:address":"1528 NW 26th St",
    "sg:city":"Miami",
    "sg:classifiers":[
        {
            "category":"Taxi",
            "type":"Transportation"
        }
    ],
    "sg:phone":"+1 305 633 3130",
    "sg:postcode":"33142",
    "sg:province":"FL",
    "sg:tags":[
        "delivery"
    ],
    "wof:name":"Jacques Thenor",
    "wof:placetype":"venue"
},
  "geometry": {"coordinates":[-80.221761,25.800345],"type":"Point"}
}