{
  "type": "Feature",
  "properties": {
    "addr:full":"451 41st St W Palmetto FL 34221",
    "addr:housenumber":"451",
    "addr:postcode":"34221",
    "addr:street":"41St St W",
    "iso:country":"US",
    "sg:address":"451 41st St W",
    "sg:city":"Palmetto",
    "sg:classifiers":[
        {
            "category":"Shopping",
            "subcategory":"Clothing, Apparel, & Fashions",
            "type":"Retail Goods"
        }
    ],
    "sg:phone":"+1 941 729 9469",
    "sg:postcode":"34221",
    "sg:province":"FL",
    "wof:name":"Mary E Luebcke",
    "wof:placetype":"venue"
},
  "geometry": {"coordinates":[-82.568625,27.550877],"type":"Point"}
}