{
  "type": "Feature",
  "properties": {
    "addr:full":"510 Ivanhoe Way Casselberry FL 32707",
    "addr:housenumber":"510",
    "addr:postcode":"32707",
    "addr:street":"Ivanhoe Way",
    "iso:country":"US",
    "sg:address":"510 Ivanhoe Way",
    "sg:city":"Casselberry",
    "sg:classifiers":[
        {
            "category":"Building & Trades",
            "subcategory":"Electrical",
            "type":"Services"
        }
    ],
    "sg:phone":"+1 407 830 4876",
    "sg:postcode":"32707",
    "sg:province":"FL",
    "sg:tags":[
        "electric",
        "contractor"
    ],
    "wof:name":"GNF Electric",
    "wof:placetype":"venue"
},
  "geometry": {"coordinates":[-81.314459,28.657782],"type":"Point"}
}