{
  "type": "Feature",
  "properties": {
    "addr:full":"180 Vining Ct Ormond Beach FL 32176",
    "addr:housenumber":"180",
    "addr:postcode":"32176",
    "addr:street":"Vining Ct",
    "iso:country":"US",
    "sg:address":"180 Vining Ct",
    "sg:city":"Ormond Beach",
    "sg:classifiers":[
        {
            "category":"Professional",
            "subcategory":"Lawyer & Legal Services",
            "type":"Services"
        }
    ],
    "sg:phone":"+1 386 673 5787",
    "sg:postcode":"32176",
    "sg:province":"FL",
    "sg:tags":[
        "attorney"
    ],
    "wof:name":"Sharon B Logan Pa",
    "wof:placetype":"venue"
},
  "geometry": {"coordinates":[-81.041217,29.289802],"type":"Point"}
}