{
  "type": "Feature",
  "properties": {
    "iso:country":"US",
    "sg:address":"2070 Raymond Dr",
    "sg:city":"St Cloud",
    "sg:classifiers":[
        {
            "category":"Building & Trades",
            "subcategory":"Cleaning & Sanitation",
            "type":"Services"
        }
    ],
    "sg:phone":"+1 407 891 9155",
    "sg:postcode":"34769",
    "sg:province":"FL",
    "wof:name":"Nitty Gritty Cleaning Co",
    "wof:placetype":"venue"
},
  "geometry": {"coordinates":[-81.2911,28.22931],"type":"Point"}
}