{
  "type": "Feature",
  "properties": {
    "iso:country":"US",
    "sg:address":"1910 Courtney Dr",
    "sg:city":"Fort Myers",
    "sg:classifiers":[
        {
            "category":"Health Services",
            "subcategory":"Hospital",
            "type":"Services"
        }
    ],
    "sg:phone":"+1 239 939 0808",
    "sg:postcode":"33901",
    "sg:province":"FL",
    "wof:name":"Pink Bazaar Thrift Shop",
    "wof:placetype":"venue"
},
  "geometry": {"coordinates":[-81.874199,26.601999],"type":"Point"}
}