{
  "type": "Feature",
  "properties": {
    "iso:country":"US",
    "sg:address":"865 Westport Dr",
    "sg:city":"Rockledge",
    "sg:classifiers":[
        {
            "category":"Building & Trades",
            "subcategory":"Landscaping Services",
            "type":"Services"
        }
    ],
    "sg:phone":"+1 321 635 9739",
    "sg:postcode":"32955",
    "sg:province":"FL",
    "wof:name":"Mid Tree & Lawn Service Inc",
    "wof:placetype":"venue"
},
  "geometry": {"coordinates":[-80.72996500000001,28.317784],"type":"Point"}
}