{
  "type": "Feature",
  "properties": {
    "iso:country":"US",
    "sg:address":"6050 Universal Blvd",
    "sg:city":"Orlando",
    "sg:classifiers":[
        {
            "category":"Cafe",
            "type":"Food & Drink"
        }
    ],
    "sg:menulink":"http://www.allmenus.com/fl/southwest-orange/3338-hard-rock-cafe/menu/",
    "sg:phone":"+1 407 351 7625",
    "sg:postcode":"32819",
    "sg:province":"FL",
    "sg:tags":[
        "american"
    ],
    "wof:name":"Hard Rock Cafe",
    "wof:placetype":"venue"
},
  "geometry": {"coordinates":[-81.467491,28.473775],"type":"Point"}
}