{
  "type": "Feature",
  "properties": {
    "iso:country":"US",
    "sg:address":"1308 10th St",
    "sg:city":"Saint Cloud",
    "sg:classifiers":[
        {
            "category":"Professional",
            "subcategory":"Business Services",
            "type":"Services"
        }
    ],
    "sg:phone":"+1 407 957 6888",
    "sg:postcode":"34769",
    "sg:province":"FL",
    "wof:name":"Nighthawk Recovery Inc",
    "wof:placetype":"venue"
},
  "geometry": {"coordinates":[-81.28362799999999,28.249037],"type":"Point"}
}