{
  "type": "Feature",
  "properties": {
    "iso:country":"US",
    "sg:address":"1295 W Highway 50",
    "sg:city":"Clermont",
    "sg:classifiers":[
        {
            "category":"Home & Garden",
            "subcategory":"Garden Supply",
            "type":"Retail Goods"
        },
        {
            "category":"Professional",
            "type":"Services"
        }
    ],
    "sg:phone":"+1 352 432 7100",
    "sg:postcode":"34711",
    "sg:province":"FL",
    "sg:tags":[
        "fertilizer",
        "fertilizing"
    ],
    "wof:name":"Howard Fertilizer",
    "wof:placetype":"venue"
},
  "geometry": {"coordinates":[-81.779982,28.554491],"type":"Point"}
}