{
  "type": "Feature",
  "properties": {
    "iso:country":"US",
    "sg:address":"449 E 13th St",
    "sg:city":"Hialeah",
    "sg:classifiers":[
        {
            "category":"Wholesale",
            "subcategory":"Non-durable Goods",
            "type":"Manufacturing & Wholesale Goods"
        }
    ],
    "sg:phone":"+1 305 805 2075",
    "sg:postcode":"33010",
    "sg:province":"FL",
    "wof:name":"M Chigin Distributor",
    "wof:placetype":"venue"
},
  "geometry": {"coordinates":[-80.27261799999999,25.833901],"type":"Point"}
}