{
  "type": "Feature",
  "properties": {
    "iso:country":"US",
    "sg:address":"107 E Church St",
    "sg:city":"Deland",
    "sg:classifiers":[
        {
            "category":"Professional",
            "subcategory":"Lawyer & Legal Services",
            "type":"Services"
        }
    ],
    "sg:phone":"+1 386 736 1223",
    "sg:postcode":"32724",
    "sg:province":"FL",
    "sg:website":"www.delandattorney.com",
    "wof:name":"De Parry Astrid PA",
    "wof:placetype":"venue"
},
  "geometry": {"coordinates":[-81.30239899999999,29.030899],"type":"Point"}
}