{
  "type": "Feature",
  "properties": {
    "addr:full":"7362 Habbersham Dr Orlando FL 32818",
    "addr:housenumber":"7362",
    "addr:postcode":"32818",
    "addr:street":"Habbersham Dr",
    "iso:country":"US",
    "sg:address":"7362 Habbersham Dr",
    "sg:city":"Orlando",
    "sg:classifiers":[
        {
            "category":"Coffee & Tea",
            "type":"Food & Drink"
        },
        {
            "category":"Restaurant",
            "type":"Food & Drink"
        }
    ],
    "sg:phone":"+1 407 296 6838",
    "sg:postcode":"32818",
    "sg:province":"FL",
    "sg:tags":[
        "espresso"
    ],
    "wof:name":"Pride Rock Cafe",
    "wof:placetype":"venue"
},
  "geometry": {"coordinates":[-81.48183,28.588799],"type":"Point"}
}