{
  "type": "Feature",
  "properties": {
    "addr:full":"10152 Atlantic Blvd Jacksonville FL 32225",
    "addr:housenumber":"10152",
    "addr:postcode":"32225",
    "addr:street":"Atlantic Blvd",
    "iso:country":"US",
    "sg:address":"10152 Atlantic Blvd",
    "sg:city":"Jacksonville",
    "sg:classifiers":[
        {
            "category":"Banks & Credit Unions",
            "subcategory":"Bank",
            "type":"Services"
        }
    ],
    "sg:phone":"+1 904 725 7733",
    "sg:postcode":"32225",
    "sg:province":"FL",
    "sg:tags":[
        "cashing",
        "money",
        "order",
        "sales",
        "check"
    ],
    "wof:name":"ACE Cash Express",
    "wof:placetype":"venue"
},
  "geometry": {"coordinates":[-81.537327,30.322932],"type":"Point"}
}