{
  "type": "Feature",
  "properties": {
    "iso:country":"US",
    "sg:address":"2820 Lorene Dr",
    "sg:city":"Lake Worth",
    "sg:classifiers":[
        {
            "category":"Building & Trades",
            "subcategory":"Construction",
            "type":"Services"
        }
    ],
    "sg:phone":"+1 561 718 8491",
    "sg:postcode":"33461",
    "sg:province":"FL",
    "sg:tags":[
        "house"
    ],
    "wof:name":"Prime Shell Contractors Inc",
    "wof:placetype":"venue"
},
  "geometry": {"coordinates":[-80.087247,26.635404],"type":"Point"}
}