{
  "type": "Feature",
  "properties": {
    "iso:country":"US",
    "sg:address":"8051 W 24th Ave Ste 14",
    "sg:city":"Hialeah",
    "sg:classifiers":[
        {
            "category":"Shopping",
            "subcategory":"Florist",
            "type":"Retail Goods"
        }
    ],
    "sg:phone":"+1 305 822 6860",
    "sg:postcode":"33016",
    "sg:province":"FL",
    "wof:name":"Master Floral Design",
    "wof:placetype":"venue"
},
  "geometry": {"coordinates":[-80.331819,25.895747],"type":"Point"}
}