{
  "type": "Feature",
  "properties": {
    "addr:full":"3736 12th St W Lehigh Acres FL 33971",
    "addr:housenumber":"3736",
    "addr:postcode":"33971",
    "addr:street":"12Th St W",
    "iso:country":"US",
    "sg:address":"3736 12th St W",
    "sg:city":"Lehigh Acres",
    "sg:classifiers":[
        {
            "category":"Building & Trades",
            "subcategory":"Construction",
            "type":"Services"
        }
    ],
    "sg:phone":"+1 239 694 6004",
    "sg:postcode":"33971",
    "sg:province":"FL",
    "sg:tags":[
        "dry wall",
        "contractor"
    ],
    "wof:name":"Dodson Drywall Inc",
    "wof:placetype":"venue"
},
  "geometry": {"coordinates":[-81.694097,26.624308],"type":"Point"}
}