{
  "type": "Feature",
  "properties": {
    "iso:country":"US",
    "sg:address":"3827 SW 8th St",
    "sg:city":"Coral Gables",
    "sg:classifiers":[
        {
            "category":"Health Services",
            "subcategory":"Health Practitioner",
            "type":"Services"
        }
    ],
    "sg:phone":"+1 305 461 9828",
    "sg:postcode":"33134",
    "sg:province":"FL",
    "sg:tags":[
        "acupuncture"
    ],
    "wof:name":"Life Force Healing Center",
    "wof:placetype":"venue"
},
  "geometry": {"coordinates":[-80.258499,25.7645],"type":"Point"}
}