{
  "type": "Feature",
  "properties": {
    "iso:country":"US",
    "sg:address":"3917 Hendricks Cir",
    "sg:city":"Molino",
    "sg:classifiers":[
        {
            "category":"Building & Trades",
            "subcategory":"Construction",
            "type":"Services"
        }
    ],
    "sg:phone":"+1 850 587 3790",
    "sg:postcode":"32565",
    "sg:province":"FL",
    "sg:tags":[
        "house"
    ],
    "wof:name":"Jr Hendricks Const",
    "wof:placetype":"venue"
},
  "geometry": {"coordinates":[-87.14664500000001,30.947508],"type":"Point"}
}