{
  "type": "Feature",
  "properties": {
    "addr:full":"603 E Fort King St Ocala FL 34471",
    "addr:housenumber":"603",
    "addr:postcode":"34471",
    "addr:street":"E Fort King St",
    "iso:country":"US",
    "sg:address":"603 E Fort King St",
    "sg:city":"Ocala",
    "sg:classifiers":[
        {
            "category":"Manufacturing",
            "subcategory":"Furniture",
            "type":"Manufacturing & Wholesale Goods"
        }
    ],
    "sg:phone":"+1 352 368 6993",
    "sg:postcode":"34471",
    "sg:province":"FL",
    "sg:tags":[
        "outdoor",
        "aluminum",
        "patio",
        "mfg"
    ],
    "wof:name":"Tropic Craft Inc",
    "wof:placetype":"venue"
},
  "geometry": {"coordinates":[-82.131152,29.185555],"type":"Point"}
}