{
  "type": "Feature",
  "properties": {
    "iso:country":"US",
    "sg:address":"2874 Villa Woods Cir",
    "sg:city":"Gulf Breeze",
    "sg:classifiers":[
        {
            "category":"Building & Trades",
            "subcategory":"Construction",
            "type":"Services"
        }
    ],
    "sg:phone":"+1 850 916 9513",
    "sg:postcode":"32563",
    "sg:province":"FL",
    "sg:tags":[
        "residential"
    ],
    "wof:name":"Dale Deville",
    "wof:placetype":"venue"
},
  "geometry": {"coordinates":[-87.110271,30.381295],"type":"Point"}
}