{
  "type": "Feature",
  "properties": {
    "addr:full":"55 SE 2nd Ave Delray Beach FL 33444",
    "addr:housenumber":"55",
    "addr:postcode":"33444",
    "addr:street":"Se 2Nd Ave",
    "iso:country":"US",
    "sg:address":"55 SE 2nd Ave",
    "sg:city":"Delray Beach",
    "sg:classifiers":[
        {
            "category":"Real Estate",
            "subcategory":"Developer",
            "type":"Services"
        }
    ],
    "sg:phone":"+1 561 276 9458",
    "sg:postcode":"33444",
    "sg:province":"FL",
    "wof:name":"Gaison Grove Square LLC",
    "wof:placetype":"venue"
},
  "geometry": {"coordinates":[-80.070989,26.460828],"type":"Point"}
}