{
  "type": "Feature",
  "properties": {
    "addr:full":"116 Magnolia Ave Green Cove Spgs FL 32043",
    "addr:housenumber":"116",
    "addr:postcode":"32043",
    "addr:street":"Magnolia Ave Green Cove Spgs",
    "iso:country":"US",
    "sg:address":"116 Magnolia Ave",
    "sg:city":"Green Cove Spgs",
    "sg:classifiers":[
        {
            "category":"Shopping",
            "subcategory":"Used Merchandise",
            "type":"Retail Goods"
        }
    ],
    "sg:phone":"+1 904 284 4343",
    "sg:postcode":"32043",
    "sg:province":"FL",
    "sg:tags":[
        "antique",
        "collectible",
        "craft"
    ],
    "wof:name":"Olde Towne Antiques",
    "wof:placetype":"venue"
},
  "geometry": {"coordinates":[-81.678048,29.992862],"type":"Point"}
}