{
  "type": "Feature",
  "properties": {
    "iso:country":"US",
    "sg:address":"1551 SW 27th Ave",
    "sg:city":"Miami",
    "sg:classifiers":[
        {
            "category":"Building & Trades",
            "subcategory":"Locksmith",
            "type":"Services"
        }
    ],
    "sg:phone":"+1 305 755 4119",
    "sg:postcode":"33145",
    "sg:province":"FL",
    "sg:tags":[
        "key"
    ],
    "wof:name":"All Day All Night Emergency Locksmith",
    "wof:placetype":"venue"
},
  "geometry": {"coordinates":[-80.238327,25.758247],"type":"Point"}
}