{
  "type": "Feature",
  "properties": {
    "iso:country":"US",
    "sg:address":"231 E Flagler St Ste 3",
    "sg:city":"Miami",
    "sg:classifiers":[
        {
            "category":"Shopping",
            "subcategory":"Used Merchandise",
            "type":"Retail Goods"
        }
    ],
    "sg:phone":"+1 305 371 4655",
    "sg:postcode":"33131",
    "sg:province":"FL",
    "sg:tags":[
        "vintage",
        "consignment"
    ],
    "wof:name":"Benge Inc",
    "wof:placetype":"venue"
},
  "geometry": {"coordinates":[-80.189301,25.7743],"type":"Point"}
}