{
  "type": "Feature",
  "properties": {
    "addr:full":"4900 S Rio Grande Ave 11D Orlando FL 32839",
    "addr:housenumber":"4900;11d",
    "addr:postcode":"32839",
    "addr:street":"S;Grande Ave",
    "iso:country":"US",
    "sg:address":"4900 S Rio Grande Ave 11D",
    "sg:city":"Orlando",
    "sg:classifiers":[
        {
            "category":"Government",
            "subcategory":"Office",
            "type":"Public Place"
        }
    ],
    "sg:phone":"+1 407 859 6388",
    "sg:postcode":"32839",
    "sg:province":"FL",
    "wof:name":"Clive Lee Enterprises Inc",
    "wof:placetype":"venue"
},
  "geometry": {"coordinates":[-81.40091,28.490583],"type":"Point"}
}