{
  "type": "Feature",
  "properties": {
    "addr:full":"29520 SW 199th Ave Homestead FL 33030",
    "addr:housenumber":"29520",
    "addr:postcode":"33030",
    "addr:street":"Sw 199Th Ave",
    "iso:country":"US",
    "sg:address":"29520 SW 199th Ave",
    "sg:city":"Homestead",
    "sg:classifiers":[
        {
            "category":"Banks & Credit Unions",
            "subcategory":"Investment Brokerage",
            "type":"Services"
        }
    ],
    "sg:phone":"+1 305 248 4044",
    "sg:postcode":"33030",
    "sg:province":"FL",
    "sg:tags":[
        "advisory"
    ],
    "wof:name":"May Fr & Co",
    "wof:placetype":"venue"
},
  "geometry": {"coordinates":[-80.51401799999999,25.494423],"type":"Point"}
}