{
  "type": "Feature",
  "properties": {
    "iso:country":"US",
    "sg:address":"10630 NW 28th Pl",
    "sg:city":"Fort Lauderdale",
    "sg:classifiers":[
        {
            "category":"Manufacturing",
            "subcategory":"Tobacco Products",
            "type":"Manufacturing & Wholesale Goods"
        }
    ],
    "sg:phone":"+1 954 748 3785",
    "sg:postcode":"33322",
    "sg:province":"FL",
    "sg:tags":[
        "cigar",
        "mfg"
    ],
    "wof:name":"Brisas Cigar Co",
    "wof:placetype":"venue"
},
  "geometry": {"coordinates":[-80.291324,26.159647],"type":"Point"}
}