{
  "type": "Feature",
  "properties": {
    "iso:country":"US",
    "sg:address":"1320 N Semoran Blvd",
    "sg:city":"Orlando",
    "sg:classifiers":[
        {
            "category":"Organizations",
            "subcategory":"Religious Organization",
            "type":"Services"
        }
    ],
    "sg:phone":"+1 407 273 8363",
    "sg:postcode":"32807",
    "sg:province":"FL",
    "wof:name":"Islamic Society Central Fla",
    "wof:placetype":"venue"
},
  "geometry": {"coordinates":[-81.310951,28.563496],"type":"Point"}
}