{
  "type": "Feature",
  "properties": {
    "iso:country":"US",
    "sg:address":"19 Grandmont St",
    "sg:city":"Port Charlotte",
    "sg:classifiers":[
        {
            "category":"Building & Trades",
            "subcategory":"Plumbing",
            "type":"Services"
        }
    ],
    "sg:phone":"+1 941 743 0122",
    "sg:postcode":"33954",
    "sg:province":"FL",
    "sg:tags":[
        "contractor"
    ],
    "wof:name":"Cypress Plumbing",
    "wof:placetype":"venue"
},
  "geometry": {"coordinates":[-82.120092,27.032292],"type":"Point"}
}