{
  "type": "Feature",
  "properties": {
    "addr:full":"1010 S Magnolia Dr Tallahassee FL 32301",
    "addr:housenumber":"1010",
    "addr:postcode":"32301",
    "addr:street":"S Magnolia Dr",
    "iso:country":"US",
    "sg:address":"1010 S Magnolia Dr",
    "sg:city":"Tallahassee",
    "sg:classifiers":[
        {
            "category":"Retail",
            "subcategory":"Repair Shop",
            "type":"Services"
        }
    ],
    "sg:phone":"+1 850 656 0063",
    "sg:postcode":"32301",
    "sg:province":"FL",
    "sg:tags":[
        "television",
        "radio"
    ],
    "wof:name":"Lou's TV",
    "wof:placetype":"venue"
},
  "geometry": {"coordinates":[-84.261898,30.434477],"type":"Point"}
}