{
  "type": "Feature",
  "properties": {
    "iso:country":"US",
    "sg:address":"151 2nd Ave N",
    "sg:city":"St Petersburg",
    "sg:classifiers":[
        {
            "category":"Cinema",
            "subcategory":"Movie Theater",
            "type":"Entertainment"
        }
    ],
    "sg:phone":"+1 727 502 0965",
    "sg:postcode":"33701",
    "sg:province":"FL",
    "wof:name":"Muvico Baywalk 20",
    "wof:placetype":"venue"
},
  "geometry": {"coordinates":[-82.634776,27.773613],"type":"Point"}
}