{
  "type": "Feature",
  "properties": {
    "iso:country":"US",
    "sg:address":"12399 Pembroke Rd",
    "sg:city":"Pembroke Pines",
    "sg:classifiers":[
        {
            "category":"Professional",
            "subcategory":"Computer Services",
            "type":"Services"
        }
    ],
    "sg:phone":"+1 954 435 4272",
    "sg:postcode":"33025",
    "sg:province":"FL",
    "sg:tags":[
        "internet"
    ],
    "wof:name":"Abaco Systems",
    "wof:placetype":"venue"
},
  "geometry": {"coordinates":[-80.31161299999999,25.993304],"type":"Point"}
}