{
  "type": "Feature",
  "properties": {
    "iso:country":"US",
    "sg:address":"414 5th Ave",
    "sg:city":"Indialantic",
    "sg:classifiers":[
        {
            "category":"Personal",
            "subcategory":"Beauty Salon",
            "type":"Services"
        },
        {
            "category":"Personal",
            "subcategory":"Barber",
            "type":"Services"
        },
        {
            "category":"Personal",
            "subcategory":"Nail Salon",
            "type":"Services"
        }
    ],
    "sg:phone":"+1 321 952 2811",
    "sg:postcode":"32903",
    "sg:province":"FL",
    "sg:tags":[
        "hair",
        "stylist"
    ],
    "wof:name":"Island Salon Nails By Diane",
    "wof:placetype":"venue"
},
  "geometry": {"coordinates":[-80.573205,28.089721],"type":"Point"}
}