{
  "type": "Feature",
  "properties": {
    "iso:country":"US",
    "sg:address":"2234 Lake Ruby Rd",
    "sg:city":"De Land",
    "sg:classifiers":[
        {
            "category":"Building & Trades",
            "subcategory":"Electrical",
            "type":"Services"
        }
    ],
    "sg:phone":"+1 386 738 1995",
    "sg:postcode":"32724",
    "sg:province":"FL",
    "sg:tags":[
        "electrical",
        "contractor"
    ],
    "wof:name":"Modern Home Technology",
    "wof:placetype":"venue"
},
  "geometry": {"coordinates":[-81.258729,29.039729],"type":"Point"}
}