{
  "type": "Feature",
  "properties": {
    "addr:full":"11820 NE 13th Ave Miami FL 33161",
    "addr:housenumber":"11820",
    "addr:postcode":"33161",
    "addr:street":"Ne 13Th Ave",
    "iso:country":"US",
    "sg:address":"11820 NE 13th Ave",
    "sg:city":"Miami",
    "sg:classifiers":[
        {
            "category":"Education",
            "subcategory":"School",
            "type":"Public Place"
        }
    ],
    "sg:phone":"+1 305 893 9876",
    "sg:postcode":"33161",
    "sg:province":"FL",
    "sg:tags":[
        "kindergarten"
    ],
    "wof:name":"Von Wedel Montessori School",
    "wof:placetype":"venue"
},
  "geometry": {"coordinates":[-80.17192,25.884265],"type":"Point"}
}