{
  "type": "Feature",
  "properties": {
    "iso:country":"US",
    "sg:address":"6290 Arbor Ave",
    "sg:city":"Fort Myers",
    "sg:classifiers":[
        {
            "category":"Building & Trades",
            "subcategory":"Plumbing",
            "type":"Services"
        }
    ],
    "sg:phone":"+1 239 694 4124",
    "sg:postcode":"33905",
    "sg:province":"FL",
    "sg:tags":[
        "contractor"
    ],
    "wof:name":"Corey L Sellers LLC",
    "wof:placetype":"venue"
},
  "geometry": {"coordinates":[-81.72666099999999,26.652611],"type":"Point"}
}