{
  "type": "Feature",
  "properties": {
    "iso:country":"US",
    "sg:address":"7401 19th Ave N",
    "sg:city":"Saint Petersburg",
    "sg:classifiers":[
        {
            "category":"Building & Trades",
            "subcategory":"Plumbing",
            "type":"Services"
        }
    ],
    "sg:phone":"+1 727 347 6656",
    "sg:postcode":"33710",
    "sg:province":"FL",
    "sg:tags":[
        "contractor"
    ],
    "wof:name":"Armor Air Conditioning Inc",
    "wof:placetype":"venue"
},
  "geometry": {"coordinates":[-82.74157,27.789714],"type":"Point"}
}