{
  "type": "Feature",
  "properties": {
    "iso:country":"US",
    "sg:address":"816 Manatee Ave E",
    "sg:city":"Bradenton",
    "sg:classifiers":[
        {
            "category":"Manufacturing",
            "subcategory":"Lumber",
            "type":"Manufacturing & Wholesale Goods"
        }
    ],
    "sg:phone":"+1 941 747 7888",
    "sg:postcode":"34208",
    "sg:province":"FL",
    "sg:tags":[
        "hardwood",
        "mill",
        "mfg"
    ],
    "wof:name":"Creative Closets",
    "wof:placetype":"venue"
},
  "geometry": {"coordinates":[-82.55494,27.495108],"type":"Point"}
}