{
  "type": "Feature",
  "properties": {
    "addr:full":"504 E Venice Ave Venice FL 34285",
    "addr:housenumber":"504",
    "addr:postcode":"34285",
    "addr:street":"E Venice Ave",
    "iso:country":"US",
    "sg:address":"504 E Venice Ave",
    "sg:city":"Venice",
    "sg:classifiers":[
        {
            "category":"Manufacturing",
            "subcategory":"Metals",
            "type":"Manufacturing & Wholesale Goods"
        },
        {
            "category":"Home & Garden",
            "subcategory":"Building Materials",
            "type":"Retail Goods"
        }
    ],
    "sg:phone":"+1 941 488 0263",
    "sg:postcode":"34285",
    "sg:province":"FL",
    "sg:tags":[
        "plate",
        "mfg",
        "glass",
        "window",
        "sanitary",
        "ware"
    ],
    "sg:website":"www.heritageglassinc.com",
    "wof:name":"Heritage Shower Doors Inc",
    "wof:placetype":"venue"
},
  "geometry": {"coordinates":[-82.43542100000001,27.099723],"type":"Point"}
}