{
  "type": "Feature",
  "properties": {
    "addr:full":"2325 N Orange Blossom Trl Orlando FL 32804",
    "addr:housenumber":"2325",
    "addr:postcode":"32804",
    "addr:street":"N Orange Blossom Trl",
    "iso:country":"US",
    "sg:address":"2325 N Orange Blossom Trl",
    "sg:city":"Orlando",
    "sg:classifiers":[
        {
            "category":"Home & Garden",
            "subcategory":"Home Furnishings",
            "type":"Retail Goods"
        }
    ],
    "sg:phone":"+1 407 841 4330",
    "sg:postcode":"32804",
    "sg:province":"FL",
    "sg:tags":[
        "shower",
        "glass",
        "enclosure",
        "mirror"
    ],
    "wof:name":"Acme Glass",
    "wof:placetype":"venue"
},
  "geometry": {"coordinates":[-81.406435,28.573805],"type":"Point"}
}