{
  "type": "Feature",
  "properties": {
    "addr:full":"120 Broadway Kissimmee FL 34741",
    "addr:housenumber":"120",
    "addr:postcode":"34741",
    "addr:street":"Broadway",
    "iso:country":"US",
    "sg:address":"120 Broadway",
    "sg:city":"Kissimmee",
    "sg:classifiers":[
        {
            "category":"Professional",
            "subcategory":"Lawyer & Legal Services",
            "type":"Services"
        }
    ],
    "sg:phone":"+1 407 933 2777",
    "sg:postcode":"34741",
    "sg:province":"FL",
    "sg:tags":[
        "practice",
        "attorney",
        "criminal",
        "law"
    ],
    "wof:name":"Robert Edge",
    "wof:placetype":"venue"
},
  "geometry": {"coordinates":[-81.40687800000001,28.292736],"type":"Point"}
}