{
  "type": "Feature",
  "properties": {
    "iso:country":"US",
    "sg:address":"8 Filbert Ln",
    "sg:city":"Palm Coast",
    "sg:classifiers":[
        {
            "category":"Building & Trades",
            "subcategory":"Construction",
            "type":"Services"
        }
    ],
    "sg:phone":"+1 386 447 8110",
    "sg:postcode":"32137",
    "sg:province":"FL",
    "sg:tags":[
        "carpenter"
    ],
    "wof:name":"Jaeger Construction",
    "wof:placetype":"venue"
},
  "geometry": {"coordinates":[-81.21727799999999,29.566181],"type":"Point"}
}