{
  "type": "Feature",
  "properties": {
    "addr:full":"2021 Tallevast Rd Ste B Sarasota FL 34243",
    "addr:housenumber":"2021",
    "addr:postcode":"34243",
    "addr:street":"Tallevast Rd Ste B",
    "iso:country":"US",
    "sg:address":"2021 Tallevast Rd Ste B",
    "sg:city":"Sarasota",
    "sg:classifiers":[
        {
            "category":"Manufacturing",
            "subcategory":"Metals",
            "type":"Manufacturing & Wholesale Goods"
        },
        {
            "category":"Building & Trades",
            "subcategory":"Construction",
            "type":"Services"
        }
    ],
    "sg:phone":"+1 941 355 2663",
    "sg:postcode":"34243",
    "sg:province":"FL",
    "sg:tags":[
        "steel",
        "detailers",
        "welder",
        "erectors",
        "structural"
    ],
    "wof:name":"Just Steel Inc.",
    "wof:placetype":"venue"
},
  "geometry": {"coordinates":[-82.539682,27.403561],"type":"Point"}
}