{
  "type": "Feature",
  "properties": {
    "addr:full":"2348 NW 7th St Miami FL 33125",
    "addr:housenumber":"2348",
    "addr:postcode":"33125",
    "addr:street":"Nw 7Th St",
    "iso:country":"US",
    "sg:address":"2348 NW 7th St",
    "sg:city":"Miami",
    "sg:classifiers":[
        {
            "category":"Health Services",
            "subcategory":"Clinic",
            "type":"Services"
        },
        {
            "category":"Community Center",
            "type":"Public Place"
        }
    ],
    "sg:phone":"+1 305 541 2888",
    "sg:postcode":"33125",
    "sg:province":"FL",
    "sg:tags":[
        "medical"
    ],
    "wof:name":"Purity Medical Center Inc",
    "wof:placetype":"venue"
},
  "geometry": {"coordinates":[-80.23441200000001,25.779483],"type":"Point"}
}