{
  "type": "Feature",
  "properties": {
    "iso:country":"US",
    "sg:address":"33619 E Lake Joanna Dr",
    "sg:city":"Eustis",
    "sg:classifiers":[
        {
            "category":"Banks & Credit Unions",
            "subcategory":"Investment Brokerage",
            "type":"Services"
        }
    ],
    "sg:phone":"+1 352 383 7230",
    "sg:postcode":"32736",
    "sg:province":"FL",
    "sg:tags":[
        "advisory"
    ],
    "wof:name":"Clement Investment Group Limited",
    "wof:placetype":"venue"
},
  "geometry": {"coordinates":[-81.640867,28.837382],"type":"Point"}
}