{
  "type": "Feature",
  "properties": {
    "iso:country":"US",
    "sg:address":"2501 S Sanford Ave",
    "sg:city":"Sanford",
    "sg:classifiers":[
        {
            "category":"Autos & Motor Vehicles",
            "subcategory":"Automobile Sales",
            "type":"Retail Goods"
        }
    ],
    "sg:phone":"+1 407 302 0076",
    "sg:postcode":"32773",
    "sg:province":"FL",
    "sg:tags":[
        "car",
        "used",
        "dealer"
    ],
    "wof:name":"Best Auto Exchange Inc",
    "wof:placetype":"venue"
},
  "geometry": {"coordinates":[-81.26477,28.784433],"type":"Point"}
}