{
  "type": "Feature",
  "properties": {
    "iso:country":"US",
    "sg:address":"6472 NW 5th Way",
    "sg:city":"Fort Lauderdale",
    "sg:classifiers":[
        {
            "category":"Restaurant",
            "type":"Food & Drink"
        }
    ],
    "sg:phone":"+1 954 772 5880",
    "sg:postcode":"33309",
    "sg:province":"FL",
    "wof:name":"Park Place Restaurant",
    "wof:placetype":"venue"
},
  "geometry": {"coordinates":[-80.15041600000001,26.207145],"type":"Point"}
}