{
  "type": "Feature",
  "properties": {
    "addr:full":"14500 60th St N Clearwater FL 33760",
    "addr:housenumber":"14500",
    "addr:postcode":"33760",
    "addr:street":"60Th St N",
    "iso:country":"US",
    "sg:address":"14500 60th St N",
    "sg:city":"Clearwater",
    "sg:classifiers":[
        {
            "category":"Retail",
            "subcategory":"Auto Repair",
            "type":"Services"
        }
    ],
    "sg:phone":"+1 727 535 9872",
    "sg:postcode":"33760",
    "sg:province":"FL",
    "sg:tags":[
        "body",
        "automobile",
        "painting"
    ],
    "wof:name":"Enterprise Auto Painting",
    "wof:placetype":"venue"
},
  "geometry": {"coordinates":[-82.718424,27.901904],"type":"Point"}
}