{
  "type": "Feature",
  "properties": {
    "addr:full":"2103 E Randolph Cir Tallahassee FL 32308",
    "addr:housenumber":"2103",
    "addr:postcode":"32308",
    "addr:street":"E Randolph Cir",
    "iso:country":"US",
    "sg:address":"2103 E Randolph Cir",
    "sg:city":"Tallahassee",
    "sg:classifiers":[
        {
            "category":"Professional",
            "subcategory":"Business Services",
            "type":"Services"
        }
    ],
    "sg:phone":"+1 850 385 9244",
    "sg:postcode":"32308",
    "sg:province":"FL",
    "sg:tags":[
        "interior",
        "consultant",
        "design",
        "decorator"
    ],
    "wof:name":"Park Avenue Design",
    "wof:placetype":"venue"
},
  "geometry": {"coordinates":[-84.258742,30.467971],"type":"Point"}
}