{
  "type": "Feature",
  "properties": {
    "iso:country":"US",
    "sg:address":"4394 Palm Beach Blvd",
    "sg:city":"Fort Myers",
    "sg:classifiers":[
        {
            "category":"Health Services",
            "subcategory":"Doctor",
            "type":"Services"
        }
    ],
    "sg:phone":"+1 239 690 1817",
    "sg:postcode":"33905",
    "sg:province":"FL",
    "sg:tags":[
        "clinic"
    ],
    "wof:name":"B & J Management",
    "wof:placetype":"venue"
},
  "geometry": {"coordinates":[-81.825339,26.669004],"type":"Point"}
}