{
  "type": "Feature",
  "properties": {
    "iso:country":"US",
    "sg:address":"2116 W Central Blvd",
    "sg:city":"Orlando",
    "sg:classifiers":[
        {
            "category":"Professional",
            "subcategory":"Art Services",
            "type":"Services"
        }
    ],
    "sg:phone":"+1 407 423 0253",
    "sg:postcode":"32805",
    "sg:province":"FL",
    "sg:tags":[
        "commercial",
        "design",
        "mfg"
    ],
    "wof:name":"T & M Signs",
    "wof:placetype":"venue"
},
  "geometry": {"coordinates":[-81.40792399999999,28.54185],"type":"Point"}
}