{
  "type": "Feature",
  "properties": {
    "addr:full":"2426 Bee Ridge Rd Sarasota FL 34239",
    "addr:housenumber":"2426",
    "addr:postcode":"34239",
    "addr:street":"Bee Ridge Rd",
    "iso:country":"US",
    "sg:address":"2426 Bee Ridge Rd",
    "sg:city":"Sarasota",
    "sg:classifiers":[
        {
            "category":"Health Services",
            "subcategory":"Doctor",
            "type":"Services"
        }
    ],
    "sg:phone":"+1 941 922 3438",
    "sg:postcode":"34239",
    "sg:province":"FL",
    "sg:tags":[
        "clinic"
    ],
    "wof:name":"Acupuncture Anywhere",
    "wof:placetype":"venue"
},
  "geometry": {"coordinates":[-82.520838,27.298755],"type":"Point"}
}