{
  "type": "Feature",
  "properties": {
    "iso:country":"US",
    "sg:address":"4969 International Dr",
    "sg:city":"Orlando",
    "sg:classifiers":[
        {
            "category":"Fast Food",
            "type":"Food & Drink"
        },
        {
            "category":"Restaurant",
            "type":"Food & Drink"
        }
    ],
    "sg:phone":"+1 407 352 8362",
    "sg:postcode":"32819",
    "sg:province":"FL",
    "sg:tags":[
        "american"
    ],
    "sg:website":"http://www.fiveguys.com",
    "wof:name":"Five Guys Burgers & Fries",
    "wof:placetype":"venue"
},
  "geometry": {"coordinates":[-81.44953,28.474056],"type":"Point"}
}