{
  "type": "Feature",
  "properties": {
    "addr:full":"4026 Dowling Rd Middleburg FL 32068",
    "addr:housenumber":"4026",
    "addr:postcode":"32068",
    "addr:street":"Dowling Rd",
    "iso:country":"US",
    "sg:address":"4026 Dowling Rd",
    "sg:city":"Middleburg",
    "sg:classifiers":[
        {
            "category":"Professional",
            "subcategory":"Management & Consulting",
            "type":"Services"
        }
    ],
    "sg:phone":"+1 904 282 1531",
    "sg:postcode":"32068",
    "sg:province":"FL",
    "sg:tags":[
        "development",
        "training",
        "research"
    ],
    "wof:name":"IMG",
    "wof:placetype":"venue"
},
  "geometry": {"coordinates":[-81.850414,30.022376],"type":"Point"}
}