{
  "type": "Feature",
  "properties": {
    "iso:country":"US",
    "sg:address":"The Shops at Sunset Place 5701 Sunset Dr Ste 258",
    "sg:city":"South Miami",
    "sg:classifiers":[
        {
            "category":"Personal",
            "subcategory":"Hair Removal",
            "type":"Services"
        }
    ],
    "sg:phone":"+1 305 722 6467",
    "sg:postcode":"33134",
    "sg:province":"FL",
    "sg:website":"www.infinitywaxing.com",
    "wof:name":"Infinity Waxing Center",
    "wof:placetype":"venue"
},
  "geometry": {"coordinates":[-80.285438,25.704496],"type":"Point"}
}