{
  "type": "Feature",
  "properties": {
    "iso:country":"US",
    "sg:address":"9013 Spence Ct",
    "sg:city":"Gotha",
    "sg:classifiers":[
        {
            "category":"Communications",
            "subcategory":"Film & Video Production",
            "type":"Services"
        }
    ],
    "sg:phone":"+1 407 298 9016",
    "sg:postcode":"34734",
    "sg:province":"FL",
    "sg:tags":[
        "medium",
        "broker",
        "taping"
    ],
    "wof:name":"KVG Studios",
    "wof:placetype":"venue"
},
  "geometry": {"coordinates":[-81.50770300000001,28.538023],"type":"Point"}
}