{
  "type": "Feature",
  "properties": {
    "addr:full":"291 Cypress Way W Naples FL 34110",
    "addr:housenumber":"291",
    "addr:postcode":"34110",
    "addr:street":"Cypress Way W",
    "iso:country":"US",
    "sg:address":"291 Cypress Way W",
    "sg:city":"Naples",
    "sg:classifiers":[
        {
            "category":"Building & Trades",
            "subcategory":"Construction",
            "type":"Services"
        }
    ],
    "sg:phone":"+1 239 597 7072",
    "sg:postcode":"34110",
    "sg:province":"FL",
    "sg:tags":[
        "house",
        "nonresidential"
    ],
    "wof:name":"Scholtz & Scholtz Inc",
    "wof:placetype":"venue"
},
  "geometry": {"coordinates":[-81.783708,26.281739],"type":"Point"}
}