{
  "type": "Feature",
  "properties": {
    "iso:country":"US",
    "sg:address":"1189 Hideaway Dr N",
    "sg:city":"Jacksonville",
    "sg:classifiers":[
        {
            "category":"Wholesale",
            "subcategory":"Scrap",
            "type":"Manufacturing & Wholesale Goods"
        }
    ],
    "sg:phone":"+1 904 230 8011",
    "sg:postcode":"32259",
    "sg:province":"FL",
    "sg:tags":[
        "recycling",
        "center"
    ],
    "wof:name":"First Coast Recycling",
    "wof:placetype":"venue"
},
  "geometry": {"coordinates":[-81.612146,30.095048],"type":"Point"}
}