{
  "type": "Feature",
  "properties": {
    "addr:full":"1760 SW 140th Ct Miami FL 33175",
    "addr:housenumber":"1760",
    "addr:postcode":"33175",
    "addr:street":"Sw 140Th Ct",
    "iso:country":"US",
    "sg:address":"1760 SW 140th Ct",
    "sg:city":"Miami",
    "sg:classifiers":[
        {
            "category":"Professional",
            "subcategory":"Business Services",
            "type":"Services"
        }
    ],
    "sg:phone":"+1 305 225 4828",
    "sg:postcode":"33175",
    "sg:province":"FL",
    "wof:name":"MI Viejo San Juan Restaurant",
    "wof:placetype":"venue"
},
  "geometry": {"coordinates":[-80.422932,25.750897],"type":"Point"}
}