{
  "type": "Feature",
  "properties": {
    "iso:country":"US",
    "sg:address":"26508 Us Highway 19 N",
    "sg:city":"Clearwater",
    "sg:classifiers":[
        {
            "category":"Restaurant",
            "type":"Food & Drink"
        }
    ],
    "sg:menulink":"http://www.allmenus.com/fl/clearwater/267719-arigato/menu/",
    "sg:phone":"+1 727 799 0202",
    "sg:postcode":"33761",
    "sg:province":"FL",
    "sg:tags":[
        "japanese",
        "asian"
    ],
    "wof:name":"Arigato",
    "wof:placetype":"venue"
},
  "geometry": {"coordinates":[-82.736836,28.013152],"type":"Point"}
}