{
  "type": "Feature",
  "properties": {
    "addr:full":"36 E Noble Ave Williston FL 32696",
    "addr:housenumber":"36",
    "addr:postcode":"32696",
    "addr:street":"E Noble Ave",
    "iso:country":"US",
    "sg:address":"36 E Noble Ave",
    "sg:city":"Williston",
    "sg:classifiers":[
        {
            "category":"Sports & Exercise",
            "subcategory":"Gym",
            "type":"Entertainment"
        }
    ],
    "sg:phone":"+1 352 528 2213",
    "sg:postcode":"32696",
    "sg:province":"FL",
    "sg:tags":[
        "club",
        "health",
        "studio",
        "gymnasium"
    ],
    "wof:name":"Curves For Women",
    "wof:placetype":"venue"
},
  "geometry": {"coordinates":[-82.446866,29.387493],"type":"Point"}
}