{
  "type": "Feature",
  "properties": {
    "iso:country":"US",
    "sg:address":"11260 Palm Beach Blvd",
    "sg:city":"Fort Myers",
    "sg:classifiers":[
        {
            "category":"Building & Trades",
            "subcategory":"Construction",
            "type":"Services"
        }
    ],
    "sg:phone":"+1 239 693 1400",
    "sg:postcode":"33905",
    "sg:province":"FL",
    "sg:tags":[
        "specializing",
        "underground",
        "utility",
        "contractor"
    ],
    "wof:name":"Stevens & Layton Inc",
    "wof:placetype":"venue"
},
  "geometry": {"coordinates":[-81.771407,26.698161],"type":"Point"}
}