{
  "type": "Feature",
  "properties": {
    "addr:full":"2972 Bridlewood Dr Palm Harbor FL 34683",
    "addr:housenumber":"2972",
    "addr:postcode":"34683",
    "addr:street":"Bridlewood Dr",
    "iso:country":"US",
    "sg:address":"2972 Bridlewood Dr",
    "sg:city":"Palm Harbor",
    "sg:classifiers":[
        {
            "category":"Shopping",
            "subcategory":"Gifts & Souvenirs",
            "type":"Retail Goods"
        }
    ],
    "sg:phone":"+1 727 784 3141",
    "sg:postcode":"34683",
    "sg:province":"FL",
    "wof:name":"Southern Sawdust Craft Company",
    "wof:placetype":"venue"
},
  "geometry": {"coordinates":[-82.762107,28.094911],"type":"Point"}
}