{
  "type": "Feature",
  "properties": {
    "iso:country":"US",
    "sg:address":"2614 Runyon Cir",
    "sg:city":"Orlando",
    "sg:classifiers":[
        {
            "category":"Professional",
            "subcategory":"Business Services",
            "type":"Services"
        }
    ],
    "sg:phone":"+1 407 251 0289",
    "sg:postcode":"32837",
    "sg:province":"FL",
    "wof:name":"J R Cowan Enterprises Inc",
    "wof:placetype":"venue"
},
  "geometry": {"coordinates":[-81.41591,28.365544],"type":"Point"}
}