{
  "type": "Feature",
  "properties": {
    "addr:full":"6831 NW 11th Pl Gainesville FL 32605",
    "addr:housenumber":"6831",
    "addr:postcode":"32605",
    "addr:street":"Nw 11Th Pl",
    "iso:country":"US",
    "sg:address":"6831 NW 11th Pl",
    "sg:city":"Gainesville",
    "sg:classifiers":[
        {
            "category":"Health Services",
            "subcategory":"Doctor",
            "type":"Services"
        },
        {
            "category":"Health Services",
            "subcategory":"Health Practitioner",
            "type":"Services"
        }
    ],
    "sg:phone":"+1 352 331 7337",
    "sg:postcode":"32605",
    "sg:province":"FL",
    "sg:tags":[
        "physician",
        "ophthalmology",
        "surgeons",
        "surgeon"
    ],
    "sg:website":"http://www.worldclasseyecare.com",
    "wof:name":"North Florida Eye Center PA",
    "wof:placetype":"venue"
},
  "geometry": {"coordinates":[-82.415511,29.663604],"type":"Point"}
}