{
  "type": "Feature",
  "properties": {
    "addr:full":"9 Lazy Hollow Wildwood FL 34785",
    "addr:housenumber":"9",
    "addr:postcode":"34785",
    "addr:street":"Lazy Hollow",
    "iso:country":"US",
    "sg:address":"9 Lazy Hollow",
    "sg:city":"Wildwood",
    "sg:classifiers":[
        {
            "category":"Building & Trades",
            "subcategory":"Construction",
            "type":"Services"
        }
    ],
    "sg:phone":"+1 352 748 5983",
    "sg:postcode":"34785",
    "sg:province":"FL",
    "sg:tags":[
        "handyman"
    ],
    "wof:name":"Robert Finnecy's Repair",
    "wof:placetype":"venue"
},
  "geometry": {"coordinates":[-82.00104899999999,28.8142],"type":"Point"}
}