{
  "type": "Feature",
  "properties": {
    "iso:country":"US",
    "sg:address":"412 Shores Blvd",
    "sg:city":"St Augustine",
    "sg:classifiers":[
        {
            "category":"Professional",
            "subcategory":"Accounting & Tax Preparation",
            "type":"Services"
        }
    ],
    "sg:phone":"+1 904 794 5678",
    "sg:postcode":"32086",
    "sg:province":"FL",
    "sg:tags":[
        "consultant"
    ],
    "wof:name":"Gene Adams Assoc",
    "wof:placetype":"venue"
},
  "geometry": {"coordinates":[-81.304737,29.818025],"type":"Point"}
}