{
  "type": "Feature",
  "properties": {
    "addr:full":"9980 Griffin Rd Fort Lauderdale FL 33328",
    "addr:housenumber":"9980",
    "addr:postcode":"33328",
    "addr:street":"Griffin Rd",
    "iso:country":"US",
    "sg:address":"9980 Griffin Rd",
    "sg:city":"Fort Lauderdale",
    "sg:classifiers":[
        {
            "category":"Retail",
            "subcategory":"Laundry & Dry Cleaning",
            "type":"Services"
        }
    ],
    "sg:phone":"+1 954 434 4469",
    "sg:postcode":"33328",
    "sg:province":"FL",
    "sg:tags":[
        "drycleaning",
        "plant"
    ],
    "wof:name":"Plaza Cleaners",
    "wof:placetype":"venue"
},
  "geometry": {"coordinates":[-80.28626199999999,26.063961],"type":"Point"}
}