{
  "type": "Feature",
  "properties": {
    "iso:country":"US",
    "sg:address":"2138 W Brandon Blvd",
    "sg:city":"Brandon",
    "sg:classifiers":[
        {
            "category":"Retail",
            "subcategory":"Auto Repair",
            "type":"Services"
        }
    ],
    "sg:phone":"+1 813 653 4191",
    "sg:postcode":"33511",
    "sg:province":"FL",
    "sg:tags":[
        "repairing",
        "automobile"
    ],
    "sg:website":"www.amoilexpress.com",
    "wof:name":"America's Oil Express",
    "wof:placetype":"venue"
},
  "geometry": {"coordinates":[-82.31989,27.937974],"type":"Point"}
}