{
  "type": "Feature",
  "properties": {
    "iso:country":"US",
    "sg:address":"6533 N Socrum Loop Rd",
    "sg:city":"Lakeland",
    "sg:classifiers":[
        {
            "category":"Personal",
            "subcategory":"Beauty Salon",
            "type":"Services"
        }
    ],
    "sg:phone":"+1 863 815 2969",
    "sg:postcode":"33809",
    "sg:province":"FL",
    "sg:tags":[
        "manicuring"
    ],
    "wof:name":"Master Nails",
    "wof:placetype":"venue"
},
  "geometry": {"coordinates":[-81.946406,28.126334],"type":"Point"}
}