{
  "type": "Feature",
  "properties": {
    "iso:country":"US",
    "sg:address":"7901 NW 176th St",
    "sg:city":"Hialeah",
    "sg:classifiers":[
        {
            "category":"Recreation",
            "type":"Entertainment"
        },
        {
            "category":"Building & Trades",
            "subcategory":"Landscaping Services",
            "type":"Services"
        }
    ],
    "sg:phone":"+1 305 825 8189",
    "sg:postcode":"33015",
    "sg:province":"FL",
    "sg:tags":[
        "park",
        "pool",
        "amusement",
        "swimming"
    ],
    "sg:website":"www.miamidadecounty.com",
    "wof:name":"Norman & Jean Reach Park",
    "wof:placetype":"venue"
},
  "geometry": {"coordinates":[-80.33169700000001,25.933488],"type":"Point"}
}