{
  "type": "Feature",
  "properties": {
    "iso:country":"US",
    "sg:address":"135 W Dundee Ave",
    "sg:city":"De Leon Springs",
    "sg:classifiers":[
        {
            "category":"Building & Trades",
            "subcategory":"Construction",
            "type":"Services"
        }
    ],
    "sg:phone":"+1 386 985 2243",
    "sg:postcode":"32130",
    "sg:province":"FL",
    "sg:tags":[
        "maintenance",
        "contractor"
    ],
    "wof:name":"Markert Building Maintenance",
    "wof:placetype":"venue"
},
  "geometry": {"coordinates":[-81.348045,29.11016],"type":"Point"}
}