{
  "type": "Feature",
  "properties": {
    "addr:full":"1503 Pine St Niceville FL 32578",
    "addr:housenumber":"1503",
    "addr:postcode":"32578",
    "addr:street":"Pine St",
    "iso:country":"US",
    "sg:address":"1503 Pine St",
    "sg:city":"Niceville",
    "sg:classifiers":[
        {
            "category":"Building & Trades",
            "subcategory":"Construction",
            "type":"Services"
        }
    ],
    "sg:phone":"+1 850 678 9138",
    "sg:postcode":"32578",
    "sg:province":"FL",
    "sg:tags":[
        "wallpaper"
    ],
    "wof:name":"Kim Lee Smith Wallpapering",
    "wof:placetype":"venue"
},
  "geometry": {"coordinates":[-86.407372,30.482944],"type":"Point"}
}