{
  "type": "Feature",
  "properties": {
    "iso:country":"US",
    "sg:address":"12307 SW 224th St",
    "sg:city":"Miami",
    "sg:classifiers":[
        {
            "category":"Shopping",
            "subcategory":"Clothing, Apparel, & Fashions",
            "type":"Retail Goods"
        }
    ],
    "sg:phone":"+1 305 257 5535",
    "sg:postcode":"33170",
    "sg:province":"FL",
    "sg:tags":[
        "item",
        "boutique"
    ],
    "wof:name":"D'Esther Corp",
    "wof:placetype":"venue"
},
  "geometry": {"coordinates":[-80.392505,25.558869],"type":"Point"}
}