{
  "type": "Feature",
  "properties": {
    "iso:country":"US",
    "sg:address":"2164 S Ridgewood Ave",
    "sg:city":"Daytona Beach",
    "sg:classifiers":[
        {
            "category":"Retail",
            "subcategory":"Auto Repair",
            "type":"Services"
        }
    ],
    "sg:phone":"+1 386 760 8828",
    "sg:postcode":"32119",
    "sg:province":"FL",
    "sg:tags":[
        "general"
    ],
    "wof:name":"Reliable Auto Repair Service I",
    "wof:placetype":"venue"
},
  "geometry": {"coordinates":[-81.000739,29.169731],"type":"Point"}
}