{
  "type": "Feature",
  "properties": {
    "iso:country":"US",
    "sg:address":"3506 W Baker St",
    "sg:city":"Plant City",
    "sg:classifiers":[
        {
            "category":"Retail",
            "subcategory":"Self-service Laundry",
            "type":"Services"
        }
    ],
    "sg:phone":"+1 813 752 2944",
    "sg:postcode":"33563",
    "sg:province":"FL",
    "wof:name":"Baker's Street Laundry",
    "wof:placetype":"venue"
},
  "geometry": {"coordinates":[-82.15701199999999,28.019598],"type":"Point"}
}