{
  "type": "Feature",
  "properties": {
    "iso:country":"US",
    "sg:address":"3238 Lake Washington Rd",
    "sg:city":"Melbourne",
    "sg:classifiers":[
        {
            "category":"Personal",
            "subcategory":"Beauty Salon",
            "type":"Services"
        }
    ],
    "sg:phone":"+1 321 254 5566",
    "sg:postcode":"32934",
    "sg:province":"FL",
    "sg:tags":[
        "hair",
        "stylist"
    ],
    "sg:website":"http://www.jenniferjameshaircolorxperts.com",
    "wof:name":"Jennifer James Hair Color Xperts",
    "wof:placetype":"venue"
},
  "geometry": {"coordinates":[-80.675984,28.146601],"type":"Point"}
}