{
  "type": "Feature",
  "properties": {
    "addr:full":"1810 E Robin Ave Sebring FL 33870",
    "addr:housenumber":"1810",
    "addr:postcode":"33870",
    "addr:street":"E Robin Ave",
    "iso:country":"US",
    "sg:address":"1810 E Robin Ave",
    "sg:city":"Sebring",
    "sg:classifiers":[
        {
            "category":"Retail",
            "subcategory":"Repair Shop",
            "type":"Services"
        }
    ],
    "sg:phone":"+1 863 382 2884",
    "sg:postcode":"33870",
    "sg:province":"FL",
    "wof:name":"Barbara J Klusacek",
    "wof:placetype":"venue"
},
  "geometry": {"coordinates":[-81.482955,27.495764],"type":"Point"}
}