{
  "type": "Feature",
  "properties": {
    "iso:country":"US",
    "sg:address":"8030 NW 103rd St",
    "sg:city":"Hialeah",
    "sg:classifiers":[
        {
            "category":"Manufacturing",
            "subcategory":"Lumber",
            "type":"Manufacturing & Wholesale Goods"
        }
    ],
    "sg:phone":"+1 305 556 6188",
    "sg:postcode":"33016",
    "sg:province":"FL",
    "sg:tags":[
        "fencing"
    ],
    "wof:name":"Barroso Railing Inc",
    "wof:placetype":"venue"
},
  "geometry": {"coordinates":[-80.327825,25.868398],"type":"Point"}
}