{
  "type": "Feature",
  "properties": {
    "iso:country":"US",
    "sg:address":"1500 W Cypress Creek Rd",
    "sg:city":"Fort Lauderdale",
    "sg:classifiers":[
        {
            "category":"Wholesale",
            "subcategory":"Groceries",
            "type":"Manufacturing & Wholesale Goods"
        }
    ],
    "sg:phone":"+1 877 502 7326",
    "sg:postcode":"33309",
    "sg:province":"FL",
    "sg:tags":[
        "food",
        "distributes",
        "snack"
    ],
    "wof:name":"International Sweets Inc",
    "wof:placetype":"venue"
},
  "geometry": {"coordinates":[-80.169973,26.20288],"type":"Point"}
}