{
  "type": "Feature",
  "properties": {
    "addr:full":"1880 W Hillsboro Blvd Deerfield Beach FL 33442",
    "addr:housenumber":"1880",
    "addr:postcode":"33442",
    "addr:street":"W Hillsboro Blvd",
    "iso:country":"US",
    "sg:address":"1880 W Hillsboro Blvd",
    "sg:city":"Deerfield Beach",
    "sg:classifiers":[
        {
            "category":"Health Services",
            "subcategory":"Doctor",
            "type":"Services"
        }
    ],
    "sg:phone":"+1 954 426 3494",
    "sg:postcode":"33442",
    "sg:province":"FL",
    "sg:tags":[
        "physician",
        "surgeon",
        "medical"
    ],
    "wof:name":"Buchbinder Dermatology Center",
    "wof:placetype":"venue"
},
  "geometry": {"coordinates":[-80.129057,26.31795],"type":"Point"}
}