{
  "type": "Feature",
  "properties": {
    "addr:full":"220 N Westmonte Dr Altamonte Springs FL 32714",
    "addr:housenumber":"220",
    "addr:postcode":"32714",
    "addr:street":"N Westmonte Dr",
    "iso:country":"US",
    "sg:address":"220 N Westmonte Dr",
    "sg:city":"Altamonte Springs",
    "sg:classifiers":[
        {
            "category":"Health Services",
            "subcategory":"Clinic",
            "type":"Services"
        }
    ],
    "sg:phone":"+1 407 331 8885",
    "sg:postcode":"32714",
    "sg:province":"FL",
    "sg:tags":[
        "loss",
        "weight"
    ],
    "wof:name":"Transformation International Weight Loss Center",
    "wof:placetype":"venue"
},
  "geometry": {"coordinates":[-81.393998,28.666325],"type":"Point"}
}