{
  "type": "Feature",
  "properties": {
    "iso:country":"US",
    "sg:address":"5397 NW 13th Ave",
    "sg:city":"Miami",
    "sg:classifiers":[
        {
            "category":"Personal",
            "subcategory":"Beauty Salon",
            "type":"Services"
        }
    ],
    "sg:phone":"+1 305 757 3023",
    "sg:postcode":"33142",
    "sg:province":"FL",
    "sg:tags":[
        "shop"
    ],
    "wof:name":"Hope's Beauty Salon",
    "wof:placetype":"venue"
},
  "geometry": {"coordinates":[-80.218216,25.823906],"type":"Point"}
}