{
  "type": "Feature",
  "properties": {
    "iso:country":"US",
    "sg:address":"3764 Peachtree Way",
    "sg:city":"Niceville",
    "sg:classifiers":[
        {
            "category":"Building & Trades",
            "subcategory":"Construction",
            "type":"Services"
        }
    ],
    "sg:phone":"+1 850 678 5668",
    "sg:postcode":"32578",
    "sg:province":"FL",
    "sg:tags":[
        "carpenter"
    ],
    "wof:name":"Greig Mc Clure Handyman",
    "wof:placetype":"venue"
},
  "geometry": {"coordinates":[-86.480665,30.532756],"type":"Point"}
}