{
  "type": "Feature",
  "properties": {
    "addr:full":"10731 el Paso Dr Riverview FL 33569",
    "addr:housenumber":"10731",
    "addr:postcode":"33569",
    "addr:street":"El Paso Dr",
    "iso:country":"US",
    "sg:address":"10731 el Paso Dr",
    "sg:city":"Riverview",
    "sg:classifiers":[
        {
            "category":"Real Estate",
            "subcategory":"Developer",
            "type":"Services"
        },
        {
            "category":"Real Estate",
            "subcategory":"Real Estate Operator",
            "type":"Services"
        }
    ],
    "sg:phone":"+1 813 677 4778",
    "sg:postcode":"33569",
    "sg:province":"FL",
    "sg:tags":[
        "mobile",
        "home",
        "site"
    ],
    "wof:name":"Hacienda Heights Mobile HM Pk",
    "wof:placetype":"venue"
},
  "geometry": {"coordinates":[-82.323134,27.842723],"type":"Point"}
}