{
  "type": "Feature",
  "properties": {
    "addr:full":"1809 60th St S Saint Petersburg FL 33707",
    "addr:housenumber":"1809",
    "addr:postcode":"33707",
    "addr:street":"60Th St S",
    "iso:country":"US",
    "sg:address":"1809 60th St S",
    "sg:city":"Saint Petersburg",
    "sg:classifiers":[
        {
            "category":"Manufacturing",
            "subcategory":"Jewelry",
            "type":"Manufacturing & Wholesale Goods"
        }
    ],
    "sg:phone":"+1 727 345 1528",
    "sg:postcode":"33707",
    "sg:province":"FL",
    "sg:tags":[
        "manufacture"
    ],
    "wof:name":"Ann Allen Handcrafted Jewelry",
    "wof:placetype":"venue"
},
  "geometry": {"coordinates":[-82.71616400000001,27.752214],"type":"Point"}
}