{
  "type": "Feature",
  "properties": {
    "iso:country":"US",
    "sg:address":"3661 S Miami Ave",
    "sg:city":"Miami",
    "sg:classifiers":[
        {
            "category":"Health Services",
            "subcategory":"Doctor",
            "type":"Services"
        }
    ],
    "sg:phone":"+1 305 856 4598",
    "sg:postcode":"33133",
    "sg:province":"FL",
    "sg:tags":[
        "physician",
        "surgeon"
    ],
    "wof:name":"Madrigal Marilu MD",
    "wof:placetype":"venue"
},
  "geometry": {"coordinates":[-80.216548,25.742965],"type":"Point"}
}