{
  "type": "Feature",
  "properties": {
    "addr:full":"10095 Beach Blvd Jacksonville FL 32246",
    "addr:housenumber":"10095",
    "addr:postcode":"32246",
    "addr:street":"Beach Blvd",
    "iso:country":"US",
    "sg:address":"10095 Beach Blvd",
    "sg:city":"Jacksonville",
    "sg:classifiers":[
        {
            "category":"Home & Garden",
            "subcategory":"Furniture",
            "type":"Retail Goods"
        }
    ],
    "sg:phone":"+1 904 642 7576",
    "sg:postcode":"32246",
    "sg:province":"FL",
    "sg:tags":[
        "cabinet"
    ],
    "wof:name":"Smoky Mountain Cabinets",
    "wof:placetype":"venue"
},
  "geometry": {"coordinates":[-81.551553,30.286683],"type":"Point"}
}