{
  "type": "Feature",
  "properties": {
    "addr:full":"2365 NE 26th St Fort Lauderdale FL 33305",
    "addr:housenumber":"2365",
    "addr:postcode":"33305",
    "addr:street":"Ne 26Th St",
    "iso:country":"US",
    "sg:address":"2365 NE 26th St",
    "sg:city":"Fort Lauderdale",
    "sg:classifiers":[
        {
            "category":"Shopping",
            "subcategory":"Clothing, Apparel, & Fashions",
            "type":"Retail Goods"
        }
    ],
    "sg:phone":"+1 954 561 2755",
    "sg:postcode":"33305",
    "sg:province":"FL",
    "wof:name":"Casual Male Big & Tall 9448",
    "wof:placetype":"venue"
},
  "geometry": {"coordinates":[-80.11745000000001,26.159869],"type":"Point"}
}