{
  "type": "Feature",
  "properties": {
    "addr:full":"6145 Park Blvd Pinellas Park FL 33781",
    "addr:housenumber":"6145",
    "addr:postcode":"33781",
    "addr:street":"Park Blvd",
    "iso:country":"US",
    "sg:address":"6145 Park Blvd",
    "sg:city":"Pinellas Park",
    "sg:classifiers":[
        {
            "category":"Personal",
            "subcategory":"Beauty Salon",
            "type":"Services"
        }
    ],
    "sg:phone":"+1 727 544 3810",
    "sg:postcode":"33781",
    "sg:province":"FL",
    "sg:tags":[
        "shop"
    ],
    "wof:name":"Traditions Btq & Hair Salon",
    "wof:placetype":"venue"
},
  "geometry": {"coordinates":[-82.71922600000001,27.839251],"type":"Point"}
}