{
  "type": "Feature",
  "properties": {
    "iso:country":"US",
    "sg:address":"10011 Seminole Blvd",
    "sg:city":"Seminole",
    "sg:classifiers":[
        {
            "category":"Health Services",
            "subcategory":"Doctor",
            "type":"Services"
        }
    ],
    "sg:phone":"+1 727 581 4551",
    "sg:postcode":"33772",
    "sg:province":"FL",
    "sg:tags":[
        "physician",
        "surgeon"
    ],
    "wof:name":"A Place For Women",
    "wof:placetype":"venue"
},
  "geometry": {"coordinates":[-82.78706099999999,27.86383],"type":"Point"}
}