{
  "type": "Feature",
  "properties": {
    "iso:country":"US",
    "sg:address":"1040 Commercial Dr",
    "sg:city":"Tallahassee",
    "sg:classifiers":[
        {
            "category":"Manufacturing",
            "subcategory":"Signs",
            "type":"Manufacturing & Wholesale Goods"
        }
    ],
    "sg:phone":"+1 850 222 6937",
    "sg:postcode":"32310",
    "sg:province":"FL",
    "sg:tags":[
        "specialty",
        "mfg"
    ],
    "wof:name":"Concepts In Design",
    "wof:placetype":"venue"
},
  "geometry": {"coordinates":[-84.293927,30.432909],"type":"Point"}
}