{
  "type": "Feature",
  "properties": {
    "iso:country":"US",
    "sg:address":"923 King St",
    "sg:city":"Cocoa",
    "sg:classifiers":[
        {
            "category":"Food & Beverages",
            "subcategory":"Groceries & Convenience Stores",
            "type":"Retail Goods"
        }
    ],
    "sg:phone":"+1 321 504 7971",
    "sg:postcode":"32922",
    "sg:province":"FL",
    "wof:name":"Sunrise Food Mart",
    "wof:placetype":"venue"
},
  "geometry": {"coordinates":[-80.74227399999999,28.355633],"type":"Point"}
}