{
  "type": "Feature",
  "properties": {
    "addr:full":"8700 Gulf Pines Dr Milton FL 32583",
    "addr:housenumber":"8700",
    "addr:postcode":"32583",
    "addr:street":"Gulf Pines Dr",
    "iso:country":"US",
    "sg:address":"8700 Gulf Pines Dr",
    "sg:city":"Milton",
    "sg:classifiers":[
        {
            "category":"Travel",
            "subcategory":"Campground",
            "type":"Entertainment"
        }
    ],
    "sg:phone":"+1 850 623 0808",
    "sg:postcode":"32583",
    "sg:province":"FL",
    "sg:website":"www.gulfpinesrv.com",
    "wof:name":"Gulf Pines RV Park",
    "wof:placetype":"venue"
},
  "geometry": {"coordinates":[-86.959711,30.620651],"type":"Point"}
}