{
  "type": "Feature",
  "properties": {
    "iso:country":"US",
    "sg:address":"2200 N Federal Hwy",
    "sg:city":"Boca Raton",
    "sg:classifiers":[
        {
            "category":"Real Estate",
            "subcategory":"Real Estate Agent",
            "type":"Services"
        }
    ],
    "sg:phone":"+1 561 395 5599",
    "sg:postcode":"33431",
    "sg:province":"FL",
    "wof:name":"Charles Simon Realty Inc",
    "wof:placetype":"venue"
},
  "geometry": {"coordinates":[-80.077517,26.368701],"type":"Point"}
}