{
  "type": "Feature",
  "properties": {
    "iso:country":"US",
    "sg:address":"4812 SW 74th Ct",
    "sg:city":"Miami",
    "sg:classifiers":[
        {
            "category":"Real Estate",
            "subcategory":"Architect",
            "type":"Services"
        }
    ],
    "sg:phone":"+1 305 662 1008",
    "sg:postcode":"33155",
    "sg:province":"FL",
    "sg:tags":[
        "architectural"
    ],
    "wof:name":"Cad Studio Architecture",
    "wof:placetype":"venue"
},
  "geometry": {"coordinates":[-80.31529999999999,25.724199],"type":"Point"}
}