{
  "type": "Feature",
  "properties": {
    "iso:country":"US",
    "sg:address":"14233 el Pico St",
    "sg:city":"Winter Garden",
    "sg:classifiers":[
        {
            "category":"Professional",
            "subcategory":"Management & Consulting",
            "type":"Services"
        }
    ],
    "sg:phone":"+1 407 239 9182",
    "sg:postcode":"34787",
    "sg:province":"FL",
    "sg:tags":[
        "party",
        "planning"
    ],
    "wof:name":"Cookie & Candy Clown Co",
    "wof:placetype":"venue"
},
  "geometry": {"coordinates":[-81.63668199999999,28.360152],"type":"Point"}
}