{
  "type": "Feature",
  "properties": {
    "iso:country":"US",
    "sg:address":"205 N Collier Blvd",
    "sg:city":"Marco Island",
    "sg:classifiers":[
        {
            "category":"Banks & Credit Unions",
            "subcategory":"Bank",
            "type":"Services"
        }
    ],
    "sg:phone":"+1 239 642 7102",
    "sg:postcode":"34145",
    "sg:province":"FL",
    "sg:tags":[
        "mortgage"
    ],
    "wof:name":"Coastal Mortgage",
    "wof:placetype":"venue"
},
  "geometry": {"coordinates":[-81.73254300000001,25.942101],"type":"Point"}
}