{
  "type": "Feature",
  "properties": {
    "addr:full":"2527 SW 177th Ave Hollywood FL 33029",
    "addr:housenumber":"2527",
    "addr:postcode":"33029",
    "addr:street":"Sw 177Th Ave",
    "iso:country":"US",
    "sg:address":"2527 SW 177th Ave",
    "sg:city":"Hollywood",
    "sg:classifiers":[
        {
            "category":"Freight",
            "type":"Transportation"
        }
    ],
    "sg:phone":"+1 954 443 3804",
    "sg:postcode":"33029",
    "sg:province":"FL",
    "sg:tags":[
        "operator",
        "local",
        "trucking"
    ],
    "wof:name":"Elimar of South Florida",
    "wof:placetype":"venue"
},
  "geometry": {"coordinates":[-80.387128,25.986034],"type":"Point"}
}