{
  "type": "Feature",
  "properties": {
    "iso:country":"US",
    "sg:address":"10125 Spyglass Ln",
    "sg:city":"Port Saint Lucie",
    "sg:classifiers":[
        {
            "category":"Professional",
            "subcategory":"Engineering",
            "type":"Services"
        }
    ],
    "sg:phone":"+1 703 855 7980",
    "sg:postcode":"34986",
    "sg:province":"FL",
    "sg:tags":[
        "consulting"
    ],
    "wof:name":"Contract Solutions LLC",
    "wof:placetype":"venue"
},
  "geometry": {"coordinates":[-80.42782,27.316162],"type":"Point"}
}