{
  "type": "Feature",
  "properties": {
    "addr:full":"770 Clearlake Rd Cocoa FL 32922",
    "addr:housenumber":"770",
    "addr:postcode":"32922",
    "addr:street":"Clearlake Rd",
    "iso:country":"US",
    "sg:address":"770 Clearlake Rd",
    "sg:city":"Cocoa",
    "sg:classifiers":[
        {
            "category":"Freight",
            "type":"Transportation"
        }
    ],
    "sg:phone":"+1 321 636 2847",
    "sg:postcode":"32922",
    "sg:province":"FL",
    "sg:tags":[
        "commercial",
        "storage"
    ],
    "wof:name":"Clifton Store-All",
    "wof:placetype":"venue"
},
  "geometry": {"coordinates":[-80.75506799999999,28.363757],"type":"Point"}
}