{
  "type": "Feature",
  "properties": {
    "addr:full":"394 E Altamonte Dr Altamonte Spgs FL 32701",
    "addr:housenumber":"394",
    "addr:postcode":"32701",
    "addr:street":"E Altamonte Dr;Spgs",
    "iso:country":"US",
    "sg:address":"394 E Altamonte Dr",
    "sg:city":"Altamonte Spgs",
    "sg:classifiers":[
        {
            "category":"Autos & Motor Vehicles",
            "subcategory":"Auto Supplies",
            "type":"Retail Goods"
        }
    ],
    "sg:phone":"+1 407 830 5860",
    "sg:postcode":"32701",
    "sg:province":"FL",
    "sg:tags":[
        "automobile",
        "parts"
    ],
    "sg:website":"www.advanceautoparts.com",
    "wof:name":"Discount Auto Parts Inc",
    "wof:placetype":"venue"
},
  "geometry": {"coordinates":[-81.37829499999999,28.66365],"type":"Point"}
}