{
  "type": "Feature",
  "properties": {
    "iso:country":"US",
    "sg:address":"10200 Betsy Pkwy",
    "sg:city":"Saint James City",
    "sg:classifiers":[
        {
            "category":"Manufacturing",
            "subcategory":"Chemicals & Compounds",
            "type":"Manufacturing & Wholesale Goods"
        }
    ],
    "sg:phone":"+1 239 283 1222",
    "sg:postcode":"33956",
    "sg:province":"FL",
    "sg:tags":[
        "preparation",
        "mfg"
    ],
    "wof:name":"Lifetime Solutions",
    "wof:placetype":"venue"
},
  "geometry": {"coordinates":[-82.113094,26.608619],"type":"Point"}
}