{
  "type": "Feature",
  "properties": {
    "iso:country":"US",
    "sg:address":"7118 S Semoran Blvd",
    "sg:city":"Orlando",
    "sg:classifiers":[
        {
            "category":"Bars & Pubs",
            "type":"Food & Drink"
        },
        {
            "category":"Restaurant",
            "type":"Food & Drink"
        },
        {
            "category":"Fast Food",
            "type":"Food & Drink"
        }
    ],
    "sg:phone":"+1 407 855 7000",
    "sg:postcode":"32822",
    "sg:province":"FL",
    "sg:tags":[
        "grill",
        "hamburger",
        "american",
        "dog",
        "lunch",
        "hot",
        "take",
        "brunch",
        "breakfast"
    ],
    "sg:website":"http://www.tgifridays.com",
    "wof:name":"T.G.I. Friday's",
    "wof:placetype":"venue"
},
  "geometry": {"coordinates":[-81.31014999999999,28.46026],"type":"Point"}
}