{
  "type": "Feature",
  "properties": {
    "iso:country":"US",
    "sg:address":"851 5th Ave S",
    "sg:city":"Naples",
    "sg:classifiers":[
        {
            "category":"Shopping",
            "subcategory":"Computers & Home Electronics",
            "type":"Retail Goods"
        }
    ],
    "sg:phone":"+1 239 430 1550",
    "sg:postcode":"34102",
    "sg:province":"FL",
    "sg:tags":[
        "related"
    ],
    "wof:name":"New Vision Consulting Inc",
    "wof:placetype":"venue"
},
  "geometry": {"coordinates":[-81.79542499999999,26.141875],"type":"Point"}
}