{
  "type": "Feature",
  "properties": {
    "iso:country":"US",
    "sg:address":"10397 SE US Hwy 441",
    "sg:city":"Belleview",
    "sg:classifiers":[
        {
            "category":"Food & Beverages",
            "subcategory":"Groceries & Convenience Stores",
            "type":"Retail Goods"
        }
    ],
    "sg:phone":"+1 352 307 8255",
    "sg:postcode":"34420",
    "sg:province":"FL",
    "sg:tags":[
        "supermarket"
    ],
    "wof:name":"Winn-Dixie Stores Inc",
    "wof:placetype":"venue"
},
  "geometry": {"coordinates":[-82.07145,29.071041],"type":"Point"}
}