{
  "type": "Feature",
  "properties": {
    "addr:full":"1700 Mason Ave Daytona Beach FL 32117",
    "addr:housenumber":"1700",
    "addr:postcode":"32117",
    "addr:street":"Mason Ave",
    "iso:country":"US",
    "sg:address":"1700 Mason Ave",
    "sg:city":"Daytona Beach",
    "sg:classifiers":[
        {
            "category":"Autos & Motor Vehicles",
            "subcategory":"Automobile Sales",
            "type":"Retail Goods"
        }
    ],
    "sg:phone":"+1 386 274 1200",
    "sg:postcode":"32117",
    "sg:province":"FL",
    "sg:tags":[
        "car",
        "dealer"
    ],
    "sg:website":"www.lynchimports.com",
    "wof:name":"Lynch Imports",
    "wof:placetype":"venue"
},
  "geometry": {"coordinates":[-81.06534499999999,29.212284],"type":"Point"}
}