{
  "type": "Feature",
  "properties": {
    "iso:country":"US",
    "sg:address":"3825 Taft St",
    "sg:city":"Hollywood",
    "sg:classifiers":[
        {
            "category":"Professional",
            "subcategory":"Computer Services",
            "type":"Services"
        }
    ],
    "sg:phone":"+1 954 893 9843",
    "sg:postcode":"33021",
    "sg:province":"FL",
    "sg:tags":[
        "programing",
        "custom"
    ],
    "wof:name":"Sapient Technologies",
    "wof:placetype":"venue"
},
  "geometry": {"coordinates":[-80.183325,26.025493],"type":"Point"}
}