{
  "type": "Feature",
  "properties": {
    "addr:full":"8350 NW 52nd Ter Doral FL 33166",
    "addr:housenumber":"8350",
    "addr:postcode":"33166",
    "addr:street":"Nw 52Nd Ter",
    "iso:country":"US",
    "sg:address":"8350 NW 52nd Ter",
    "sg:city":"Doral",
    "sg:classifiers":[
        {
            "category":"Wholesale",
            "subcategory":"Machinery & Supplies",
            "type":"Manufacturing & Wholesale Goods"
        }
    ],
    "sg:phone":"+1 305 888 5524",
    "sg:postcode":"33166",
    "sg:province":"FL",
    "sg:tags":[
        "contractor"
    ],
    "wof:name":"PSW Sur",
    "wof:placetype":"venue"
},
  "geometry": {"coordinates":[-80.332488,25.820022],"type":"Point"}
}