{
  "type": "Feature",
  "properties": {
    "addr:full":"8047 Lakeland St Jacksonville FL 32221",
    "addr:housenumber":"8047",
    "addr:postcode":"32221",
    "addr:street":"Lakeland St",
    "iso:country":"US",
    "sg:address":"8047 Lakeland St",
    "sg:city":"Jacksonville",
    "sg:classifiers":[
        {
            "category":"Real Estate",
            "subcategory":"Real Estate Agent",
            "type":"Services"
        }
    ],
    "sg:phone":"+1 904 781 6084",
    "sg:postcode":"32221",
    "sg:province":"FL",
    "wof:name":"Jack L Reichenbach Realty",
    "wof:placetype":"venue"
},
  "geometry": {"coordinates":[-81.782691,30.31437],"type":"Point"}
}