{
  "type": "Feature",
  "properties": {
    "iso:country":"US",
    "sg:address":"4599 Park Blvd",
    "sg:city":"Pinellas Park",
    "sg:classifiers":[
        {
            "category":"Restaurant",
            "type":"Food & Drink"
        }
    ],
    "sg:phone":"+1 727 549 0122",
    "sg:postcode":"33781",
    "sg:province":"FL",
    "sg:tags":[
        "eating"
    ],
    "sg:website":"www.yumbrand.com",
    "wof:name":"Taco Bell",
    "wof:placetype":"venue"
},
  "geometry": {"coordinates":[-82.693889,27.839222],"type":"Point"}
}