{
  "type": "Feature",
  "properties": {
    "iso:country":"US",
    "sg:address":"2401 University Pkwy Ste 204",
    "sg:city":"Sarasota",
    "sg:classifiers":[
        {
            "category":"Health Services",
            "subcategory":"Doctor",
            "type":"Services"
        }
    ],
    "sg:phone":"+1 941 351 6131",
    "sg:postcode":"34243",
    "sg:province":"FL",
    "sg:tags":[
        "physician",
        "reconstructive",
        "surgeons",
        "cosmetic",
        "plastic",
        "surgery",
        "surgeon"
    ],
    "wof:name":"Parkway Plastic Surgeons",
    "wof:placetype":"venue"
},
  "geometry": {"coordinates":[-82.522003,27.38896],"type":"Point"}
}