{
  "type": "Feature",
  "properties": {
    "iso:country":"US",
    "sg:address":"1245 Seminole Ave",
    "sg:city":"Longwood",
    "sg:classifiers":[
        {
            "category":"Professional",
            "type":"Services"
        }
    ],
    "sg:phone":"+1 407 830 6742",
    "sg:postcode":"32750",
    "sg:province":"FL",
    "wof:name":"Sallee Services",
    "wof:placetype":"venue"
},
  "geometry": {"coordinates":[-81.362015,28.683559],"type":"Point"}
}