{
  "type": "Feature",
  "properties": {
    "iso:country":"US",
    "sg:address":"3168 SW 24th St",
    "sg:city":"Miami",
    "sg:classifiers":[
        {
            "category":"Manufacturing",
            "subcategory":"Tools & Machinery",
            "type":"Manufacturing & Wholesale Goods"
        }
    ],
    "sg:phone":"+1 305 567 0528",
    "sg:postcode":"33145",
    "sg:province":"FL",
    "sg:tags":[
        "repair",
        "washer"
    ],
    "wof:name":"Tic TAC Toe Corp",
    "wof:placetype":"venue"
},
  "geometry": {"coordinates":[-80.24431300000001,25.746382],"type":"Point"}
}