{
  "type": "Feature",
  "properties": {
    "addr:full":"301 W Bay St Jacksonville FL 32202",
    "addr:housenumber":"301",
    "addr:postcode":"32202",
    "addr:street":"W Bay St",
    "iso:country":"US",
    "sg:address":"301 W Bay St",
    "sg:city":"Jacksonville",
    "sg:classifiers":[
        {
            "category":"Utilities",
            "subcategory":"Telephone",
            "type":"Services"
        },
        {
            "category":"Retail",
            "subcategory":"Auto Repair",
            "type":"Services"
        }
    ],
    "sg:phone":"+1 904 350 2646",
    "sg:postcode":"32202",
    "sg:province":"FL",
    "sg:tags":[
        "automotive",
        "company",
        "communications"
    ],
    "wof:name":"Bell South",
    "wof:placetype":"venue"
},
  "geometry": {"coordinates":[-81.662988,30.327322],"type":"Point"}
}