{
  "type": "Feature",
  "properties": {
    "iso:country":"US",
    "sg:address":"1001 N Highway A1a Alt",
    "sg:city":"Jupiter",
    "sg:classifiers":[
        {
            "category":"Real Estate",
            "subcategory":"Real Estate Services",
            "type":"Services"
        },
        {
            "category":"Real Estate",
            "subcategory":"Real Estate Agent",
            "type":"Services"
        }
    ],
    "sg:phone":"+1 561 744 0054",
    "sg:postcode":"33477",
    "sg:province":"FL",
    "sg:tags":[
        "management"
    ],
    "sg:website":"http://www.julierosenthal.com",
    "wof:name":"Property Brokers Internatinal",
    "wof:placetype":"venue"
},
  "geometry": {"coordinates":[-80.092855,26.94385],"type":"Point"}
}