{
  "type": "Feature",
  "properties": {
    "iso:country":"US",
    "sg:address":"1771 W Minnesota Ave",
    "sg:city":"Deland",
    "sg:classifiers":[
        {
            "category":"Social Services",
            "subcategory":"Adult Care",
            "type":"Services"
        }
    ],
    "sg:phone":"+1 386 736 7231",
    "sg:postcode":"32720",
    "sg:province":"FL",
    "sg:tags":[
        "home",
        "residential"
    ],
    "wof:name":"Oak Manor",
    "wof:placetype":"venue"
},
  "geometry": {"coordinates":[-81.34451900000001,29.03497],"type":"Point"}
}