{
  "type": "Feature",
  "properties": {
    "iso:country":"US",
    "sg:address":"1190 W Osceola Pkwy",
    "sg:city":"Kissimmee",
    "sg:classifiers":[
        {
            "category":"Restaurant",
            "type":"Food & Drink"
        }
    ],
    "sg:menulink":"http://www.allmenus.com/fl/kissimmee/240154-panda-express/menu/",
    "sg:phone":"+1 407 870 0363",
    "sg:postcode":"34741",
    "sg:province":"FL",
    "sg:tags":[
        "asian",
        "chinese"
    ],
    "wof:name":"Panda Express",
    "wof:placetype":"venue"
},
  "geometry": {"coordinates":[-81.415761,28.34186],"type":"Point"}
}