{
  "type": "Feature",
  "properties": {
    "iso:country":"US",
    "sg:address":"299 E Broward Blvd",
    "sg:city":"Fort Lauderdale",
    "sg:classifiers":[
        {
            "category":"Professional",
            "subcategory":"Printing & Photocopies",
            "type":"Services"
        }
    ],
    "sg:phone":"+1 954 764 3225",
    "sg:postcode":"33301",
    "sg:province":"FL",
    "sg:tags":[
        "duplicating",
        "copying"
    ],
    "wof:name":"C Magic Graphics Inc",
    "wof:placetype":"venue"
},
  "geometry": {"coordinates":[-80.14152,26.12228],"type":"Point"}
}