{
  "type": "Feature",
  "properties": {
    "iso:country":"US",
    "sg:address":"3415 Pelican Ln",
    "sg:city":"Orlando",
    "sg:classifiers":[
        {
            "category":"Education",
            "subcategory":"Special Training",
            "type":"Public Place"
        }
    ],
    "sg:phone":"+1 321 206 8924",
    "sg:postcode":"32803",
    "sg:province":"FL",
    "sg:tags":[
        "career",
        "vocational",
        "counseling"
    ],
    "wof:name":"Dana A Lessne",
    "wof:placetype":"venue"
},
  "geometry": {"coordinates":[-81.342221,28.561372],"type":"Point"}
}