{
  "type": "Feature",
  "properties": {
    "addr:full":"1697 Oak Dr Gulf Breeze FL 32563",
    "addr:housenumber":"1697",
    "addr:postcode":"32563",
    "addr:street":"Oak Dr",
    "iso:country":"US",
    "sg:address":"1697 Oak Dr",
    "sg:city":"Gulf Breeze",
    "sg:classifiers":[
        {
            "category":"Building & Trades",
            "subcategory":"Landscaping Services",
            "type":"Services"
        }
    ],
    "sg:phone":"+1 850 932 9311",
    "sg:postcode":"32563",
    "sg:province":"FL",
    "sg:tags":[
        "landscape"
    ],
    "wof:name":"Accent Gardens",
    "wof:placetype":"venue"
},
  "geometry": {"coordinates":[-86.991124,30.394164],"type":"Point"}
}