{
  "type": "Feature",
  "properties": {
    "addr:full":"96 Melanie Ln Middleburg FL 32068",
    "addr:housenumber":"96",
    "addr:postcode":"32068",
    "addr:street":"Melanie Ln",
    "iso:country":"US",
    "sg:address":"96 Melanie Ln",
    "sg:city":"Middleburg",
    "sg:classifiers":[
        {
            "category":"Building & Trades",
            "subcategory":"Construction",
            "type":"Services"
        }
    ],
    "sg:phone":"+1 904 291 7094",
    "sg:postcode":"32068",
    "sg:province":"FL",
    "sg:tags":[
        "contractor"
    ],
    "wof:name":"James L Baggett Home Imprv",
    "wof:placetype":"venue"
},
  "geometry": {"coordinates":[-81.92974100000001,30.081691],"type":"Point"}
}