{
  "type": "Feature",
  "properties": {
    "iso:country":"US",
    "sg:address":"316 Elm St",
    "sg:city":"Hollywood",
    "sg:classifiers":[
        {
            "category":"Real Estate",
            "subcategory":"Real Estate Operator",
            "type":"Services"
        }
    ],
    "sg:phone":"+1 954 922 1713",
    "sg:postcode":"33019",
    "sg:province":"FL",
    "sg:tags":[
        "apartment"
    ],
    "wof:name":"Elm Apartment",
    "wof:placetype":"venue"
},
  "geometry": {"coordinates":[-80.114306,26.049074],"type":"Point"}
}