{
  "type": "Feature",
  "properties": {
    "iso:country":"US",
    "sg:address":"125 S Swoope Ave",
    "sg:city":"Maitland",
    "sg:classifiers":[
        {
            "category":"Professional",
            "subcategory":"Management & Consulting",
            "type":"Services"
        }
    ],
    "sg:phone":"+1 407 647 4754",
    "sg:postcode":"32751",
    "sg:province":"FL",
    "sg:tags":[
        "marketing",
        "consultant"
    ],
    "wof:name":"I P Licensensing Group",
    "wof:placetype":"venue"
},
  "geometry": {"coordinates":[-81.361942,28.627297],"type":"Point"}
}