{
  "type": "Feature",
  "properties": {
    "addr:full":"1140 W 50th St Hialeah FL 33012",
    "addr:housenumber":"1140",
    "addr:postcode":"33012",
    "addr:street":"W 50Th St",
    "iso:country":"US",
    "sg:address":"1140 W 50th St",
    "sg:city":"Hialeah",
    "sg:classifiers":[
        {
            "category":"Personal",
            "subcategory":"Beauty Salon",
            "type":"Services"
        }
    ],
    "sg:phone":"+1 305 819 7712",
    "sg:postcode":"33012",
    "sg:province":"FL",
    "sg:tags":[
        "shop",
        "treatment",
        "skin"
    ],
    "wof:name":"Dermalife Aesthetic Center",
    "wof:placetype":"venue"
},
  "geometry": {"coordinates":[-80.30466800000001,25.867554],"type":"Point"}
}