{
  "type": "Feature",
  "properties": {
    "addr:full":"1029 Caliente Dr Jacksonville FL 32211",
    "addr:housenumber":"1029",
    "addr:postcode":"32211",
    "addr:street":"Caliente Dr",
    "iso:country":"US",
    "sg:address":"1029 Caliente Dr",
    "sg:city":"Jacksonville",
    "sg:classifiers":[
        {
            "category":"Real Estate",
            "subcategory":"Real Estate Operator",
            "type":"Services"
        }
    ],
    "sg:phone":"+1 904 762 9009",
    "sg:postcode":"32211",
    "sg:province":"FL",
    "sg:tags":[
        "apartment"
    ],
    "wof:name":"Seleus Apartments LLC",
    "wof:placetype":"venue"
},
  "geometry": {"coordinates":[-81.604587,30.331155],"type":"Point"}
}