{
  "type": "Feature",
  "properties": {
    "addr:full":"4250 Alafaya Trl Oviedo FL 32765",
    "addr:postcode":"4250;32765",
    "addr:street":"Alafaya Trl",
    "iso:country":"US",
    "sg:address":"4250 Alafaya Trl",
    "sg:city":"Oviedo",
    "sg:classifiers":[
        {
            "category":"Real Estate",
            "subcategory":"Real Estate Agent",
            "type":"Services"
        }
    ],
    "sg:phone":"+1 407 365 3634",
    "sg:postcode":"32765",
    "sg:province":"FL",
    "sg:website":"www.signature.net",
    "wof:name":"Signature Realty & Dev Inc",
    "wof:placetype":"venue"
},
  "geometry": {"coordinates":[-81.20770400000001,28.615143],"type":"Point"}
}