{
  "type": "Feature",
  "properties": {
    "iso:country":"US",
    "sg:address":"10291 NW 43rd St",
    "sg:city":"Pompano Beach",
    "sg:classifiers":[
        {
            "category":"Manufacturing",
            "subcategory":"Printing",
            "type":"Manufacturing & Wholesale Goods"
        }
    ],
    "sg:phone":"+1 954 344 1244",
    "sg:postcode":"33065",
    "sg:province":"FL",
    "sg:tags":[
        "publishing"
    ],
    "wof:name":"Leigh & Assoc Inc",
    "wof:placetype":"venue"
},
  "geometry": {"coordinates":[-80.263211,26.284068],"type":"Point"}
}