{
  "type": "Feature",
  "properties": {
    "iso:country":"US",
    "sg:address":"363 E 1st Ave",
    "sg:city":"Hialeah",
    "sg:classifiers":[
        {
            "category":"Manufacturing",
            "subcategory":"Signs",
            "type":"Manufacturing & Wholesale Goods"
        }
    ],
    "sg:phone":"+1 305 884 8838",
    "sg:postcode":"33010",
    "sg:province":"FL",
    "sg:tags":[
        "advertising",
        "specialty"
    ],
    "wof:name":"Signs USA Telephones",
    "wof:placetype":"venue"
},
  "geometry": {"coordinates":[-80.27932,25.824861],"type":"Point"}
}