{
  "type": "Feature",
  "properties": {
    "iso:country":"US",
    "sg:address":"3425 Collins Ave",
    "sg:city":"Miami Beach",
    "sg:classifiers":[
        {
            "category":"Building & Trades",
            "subcategory":"Locksmith",
            "type":"Services"
        }
    ],
    "sg:phone":"+1 786 228 5768",
    "sg:postcode":"33140",
    "sg:province":"FL",
    "sg:tags":[
        "key"
    ],
    "wof:name":"Emergency Locksmith On Collins Ave",
    "wof:placetype":"venue"
},
  "geometry": {"coordinates":[-80.12381499999999,25.808565],"type":"Point"}
}