{
  "type": "Feature",
  "properties": {
    "iso:country":"US",
    "sg:address":"9072 Abbott Ave",
    "sg:city":"Surfside",
    "sg:classifiers":[
        {
            "category":"Professional",
            "subcategory":"Business Services",
            "type":"Services"
        }
    ],
    "sg:phone":"+1 305 868 3688",
    "sg:postcode":"33154",
    "sg:province":"FL",
    "sg:tags":[
        "organizing",
        "services-household"
    ],
    "wof:name":"Llorente Family Management Company",
    "wof:placetype":"venue"
},
  "geometry": {"coordinates":[-80.12358399999999,25.877428],"type":"Point"}
}