{
  "type": "Feature",
  "properties": {
    "addr:full":"10613 Woodland Dr Hudson FL 34669",
    "addr:housenumber":"10613",
    "addr:postcode":"34669",
    "addr:street":"Woodland Dr",
    "iso:country":"US",
    "sg:address":"10613 Woodland Dr",
    "sg:city":"Hudson",
    "sg:classifiers":[
        {
            "category":"Building & Trades",
            "subcategory":"Construction",
            "type":"Services"
        }
    ],
    "sg:phone":"+1 727 856 2533",
    "sg:postcode":"34669",
    "sg:province":"FL",
    "sg:tags":[
        "system",
        "contractor",
        "air conditioning"
    ],
    "wof:name":"Fred's Heat & Air Conditioning",
    "wof:placetype":"venue"
},
  "geometry": {"coordinates":[-82.638214,28.357073],"type":"Point"}
}