{
  "type": "Feature",
  "properties": {
    "iso:country":"US",
    "sg:address":"19646 Saltsdale Rd",
    "sg:city":"Umatilla",
    "sg:classifiers":[
        {
            "category":"Autos & Motor Vehicles",
            "subcategory":"Automobile Sales",
            "type":"Retail Goods"
        },
        {
            "category":"Autos & Motor Vehicles",
            "subcategory":"Auto Supplies",
            "type":"Retail Goods"
        }
    ],
    "sg:phone":"+1 352 669 2344",
    "sg:postcode":"32784",
    "sg:province":"FL",
    "sg:tags":[
        "part",
        "salvage"
    ],
    "wof:name":"Bronco Dale's Auto & Truck Salvage 4x4s",
    "wof:placetype":"venue"
},
  "geometry": {"coordinates":[-81.632274,28.931802],"type":"Point"}
}