{
  "type": "Feature",
  "properties": {
    "iso:country":"US",
    "sg:address":"10300 Southside Blvd",
    "sg:city":"Jacksonville",
    "sg:classifiers":[
        {
            "category":"Bakery",
            "type":"Food & Drink"
        }
    ],
    "sg:menulink":"http://www.allmenus.com/fl/jacksonville/219825-auntie-annes-pretzels/menu/",
    "sg:phone":"+1 904 538 9424",
    "sg:postcode":"32256",
    "sg:province":"FL",
    "sg:tags":[
        "american",
        "pastry"
    ],
    "wof:name":"Auntie Anne's Pretzels",
    "wof:placetype":"venue"
},
  "geometry": {"coordinates":[-81.55182499999999,30.185734],"type":"Point"}
}