{
  "type": "Feature",
  "properties": {
    "addr:full":"1425 Tuskawilla Rd Winter Springs FL 32708",
    "addr:postcode":"1425;32708",
    "addr:street":"Tuskawilla Rd",
    "iso:country":"US",
    "sg:address":"1425 Tuskawilla Rd",
    "sg:city":"Winter Springs",
    "sg:classifiers":[
        {
            "category":"Banks & Credit Unions",
            "subcategory":"Bank",
            "type":"Services"
        }
    ],
    "sg:phone":"+1 407 696 6886",
    "sg:postcode":"32708",
    "sg:province":"FL",
    "sg:website":"www.wachovia.com",
    "wof:name":"Southtrust Bank",
    "wof:placetype":"venue"
},
  "geometry": {"coordinates":[-81.26860000000001,28.643499],"type":"Point"}
}