{
  "type": "Feature",
  "properties": {
    "addr:full":"493 Winding Creek Pl Longwood FL 32779",
    "addr:housenumber":"493",
    "addr:postcode":"32779",
    "addr:street":"Winding Creek Pl",
    "iso:country":"US",
    "sg:address":"493 Winding Creek Pl",
    "sg:city":"Longwood",
    "sg:classifiers":[
        {
            "category":"Shopping",
            "subcategory":"Gifts & Souvenirs",
            "type":"Retail Goods"
        }
    ],
    "sg:phone":"+1 407 682 1184",
    "sg:postcode":"32779",
    "sg:province":"FL",
    "wof:name":"Papybus Altamonte Springs",
    "wof:placetype":"venue"
},
  "geometry": {"coordinates":[-81.40562,28.697095],"type":"Point"}
}