{
  "type": "Feature",
  "properties": {
    "iso:country":"US",
    "sg:address":"9466 Navarre Pkwy",
    "sg:city":"Gulf Breeze",
    "sg:classifiers":[
        {
            "category":"Cinema",
            "subcategory":"Movie Rental",
            "type":"Entertainment"
        }
    ],
    "sg:phone":"+1 850 936 5501",
    "sg:postcode":"32566",
    "sg:province":"FL",
    "sg:tags":[
        "video",
        "tape"
    ],
    "wof:name":"Advanced Audio Video & Securi",
    "wof:placetype":"venue"
},
  "geometry": {"coordinates":[-86.826627,30.409664],"type":"Point"}
}