{
  "type": "Feature",
  "properties": {
    "addr:full":"1616 New Point Comfort Rd Englewood FL 34223",
    "addr:housenumber":"1616",
    "addr:postcode":"34223",
    "addr:street":"Comfort Rd",
    "iso:country":"US",
    "sg:address":"1616 New Point Comfort Rd",
    "sg:city":"Englewood",
    "sg:classifiers":[
        {
            "category":"Professional",
            "subcategory":"Accounting & Tax Preparation",
            "type":"Services"
        }
    ],
    "sg:phone":"+1 941 474 7724",
    "sg:postcode":"34223",
    "sg:province":"FL",
    "sg:tags":[
        "accountant"
    ],
    "wof:name":"Susan L Corzilius",
    "wof:placetype":"venue"
},
  "geometry": {"coordinates":[-82.342539,26.933603],"type":"Point"}
}