{
  "type": "Feature",
  "properties": {
    "addr:full":"7950 NW 53rd St Miami FL 33166",
    "addr:housenumber":"7950",
    "addr:postcode":"33166",
    "addr:street":"Nw 53Rd St",
    "iso:country":"US",
    "sg:address":"7950 NW 53rd St",
    "sg:city":"Miami",
    "sg:classifiers":[
        {
            "category":"Banks & Credit Unions",
            "subcategory":"Bank",
            "type":"Services"
        }
    ],
    "sg:phone":"+1 305 463 9930",
    "sg:postcode":"33166",
    "sg:province":"FL",
    "sg:tags":[
        "loan",
        "real estate"
    ],
    "wof:name":"New Century Mortgage",
    "wof:placetype":"venue"
},
  "geometry": {"coordinates":[-80.326263,25.821558],"type":"Point"}
}