{
  "type": "Feature",
  "properties": {
    "addr:full":"2408 Drummond Ave Panama City FL 32405",
    "addr:housenumber":"2408",
    "addr:postcode":"32405",
    "addr:street":"Drummond Ave",
    "iso:country":"US",
    "sg:address":"2408 Drummond Ave",
    "sg:city":"Panama City",
    "sg:classifiers":[
        {
            "category":"Building & Trades",
            "subcategory":"Electrical",
            "type":"Services"
        }
    ],
    "sg:phone":"+1 850 522 0943",
    "sg:postcode":"32405",
    "sg:province":"FL",
    "sg:tags":[
        "electric",
        "contractor"
    ],
    "wof:name":"B & S Electric Svc",
    "wof:placetype":"venue"
},
  "geometry": {"coordinates":[-85.70966199999999,30.19243],"type":"Point"}
}