{
  "type": "Feature",
  "properties": {
    "addr:full":"21914 Old Bridge Trl Boca Raton FL 33428",
    "addr:housenumber":"21914",
    "addr:postcode":"33428",
    "addr:street":"Old Bridge Trl",
    "iso:country":"US",
    "sg:address":"21914 Old Bridge Trl",
    "sg:city":"Boca Raton",
    "sg:classifiers":[
        {
            "category":"Professional",
            "type":"Services"
        }
    ],
    "sg:phone":"+1 561 477 0401",
    "sg:postcode":"33428",
    "sg:province":"FL",
    "wof:name":"Rosacometta USA Inc",
    "wof:placetype":"venue"
},
  "geometry": {"coordinates":[-80.21508300000001,26.350572],"type":"Point"}
}