{
  "type": "Feature",
  "properties": {
    "iso:country":"US",
    "sg:address":"20533 Biscayne Blvd",
    "sg:city":"Miami",
    "sg:classifiers":[
        {
            "category":"Wholesale",
            "subcategory":"Medical Equipment & Supplies",
            "type":"Manufacturing & Wholesale Goods"
        }
    ],
    "sg:phone":"+1 305 653 9028",
    "sg:postcode":"33180",
    "sg:province":"FL",
    "wof:name":"Unimed Imaging",
    "wof:placetype":"venue"
},
  "geometry": {"coordinates":[-80.145946,25.966192],"type":"Point"}
}