{
  "type": "Feature",
  "properties": {
    "addr:full":"2014 Drew St Clearwater FL 33765",
    "addr:housenumber":"2014",
    "addr:postcode":"33765",
    "addr:street":"Drew St",
    "iso:country":"US",
    "sg:address":"2014 Drew St",
    "sg:city":"Clearwater",
    "sg:classifiers":[
        {
            "category":"Health Services",
            "subcategory":"Clinic",
            "type":"Services"
        }
    ],
    "sg:phone":"+1 727 445 7100",
    "sg:postcode":"33765",
    "sg:province":"FL",
    "sg:tags":[
        "home"
    ],
    "wof:name":"Utopia Home Care Inc",
    "wof:placetype":"venue"
},
  "geometry": {"coordinates":[-82.75292,27.968042],"type":"Point"}
}