{
  "type": "Feature",
  "properties": {
    "iso:country":"US",
    "sg:address":"6056 Ulmerton Rd",
    "sg:city":"Clearwater",
    "sg:classifiers":[
        {
            "category":"Building & Trades",
            "subcategory":"Construction",
            "type":"Services"
        }
    ],
    "sg:phone":"+1 727 524 6235",
    "sg:postcode":"33760",
    "sg:province":"FL",
    "sg:tags":[
        "electrical",
        "contractor"
    ],
    "wof:name":"Knight Enterprises",
    "wof:placetype":"venue"
},
  "geometry": {"coordinates":[-82.720231,27.893744],"type":"Point"}
}