{
  "type": "Feature",
  "properties": {
    "addr:full":"1650 S Dixie Hwy Boca Raton FL 33432",
    "addr:housenumber":"1650",
    "addr:postcode":"33432",
    "addr:street":"S Dixie Hwy",
    "iso:country":"US",
    "sg:address":"1650 S Dixie Hwy",
    "sg:city":"Boca Raton",
    "sg:classifiers":[
        {
            "category":"Travel",
            "subcategory":"Travel Agent",
            "type":"Entertainment"
        }
    ],
    "sg:phone":"+1 561 395 4224",
    "sg:postcode":"33432",
    "sg:province":"FL",
    "sg:tags":[
        "tournament",
        "golf",
        "booking"
    ],
    "wof:name":"Junior Champions Tour",
    "wof:placetype":"venue"
},
  "geometry": {"coordinates":[-80.09020099999999,26.334854],"type":"Point"}
}