{
  "type": "Feature",
  "properties": {
    "iso:country":"US",
    "sg:address":"16 Winston Dr",
    "sg:city":"Clearwater",
    "sg:classifiers":[
        {
            "category":"Professional",
            "subcategory":"Business Services",
            "type":"Services"
        }
    ],
    "sg:phone":"+1 727 584 2883",
    "sg:postcode":"33756",
    "sg:province":"FL",
    "wof:name":"Worldwide Licensing",
    "wof:placetype":"venue"
},
  "geometry": {"coordinates":[-82.82541500000001,27.925007],"type":"Point"}
}