{
  "type": "Feature",
  "properties": {
    "iso:country":"US",
    "sg:address":"242 NW 10th St",
    "sg:city":"Ocala",
    "sg:classifiers":[
        {
            "category":"Shopping",
            "subcategory":"Clothing, Apparel, & Fashions",
            "type":"Retail Goods"
        }
    ],
    "sg:phone":"+1 352 351 8868",
    "sg:postcode":"34475",
    "sg:province":"FL",
    "sg:tags":[
        "beauty",
        "supply"
    ],
    "wof:name":"Ebony Fashion & Beauty Supply",
    "wof:placetype":"venue"
},
  "geometry": {"coordinates":[-82.140147,29.196946],"type":"Point"}
}