{
  "type": "Feature",
  "properties": {
    "iso:country":"US",
    "sg:address":"104 E Central Blvd",
    "sg:city":"Cape Canaveral",
    "sg:classifiers":[
        {
            "category":"Building & Trades",
            "subcategory":"Cleaning & Sanitation",
            "type":"Services"
        }
    ],
    "sg:phone":"+1 321 783 6932",
    "sg:postcode":"32920",
    "sg:province":"FL",
    "sg:tags":[
        "maintenance"
    ],
    "wof:name":"Blizzard Janitorial",
    "wof:placetype":"venue"
},
  "geometry": {"coordinates":[-80.603279,28.396154],"type":"Point"}
}