{
  "type": "Feature",
  "properties": {
    "iso:country":"US",
    "sg:address":"13551 Biscayne Blvd",
    "sg:city":"Aventura",
    "sg:classifiers":[
        {
            "category":"Restaurant",
            "type":"Food & Drink"
        }
    ],
    "sg:phone":"+1 305 947 4242",
    "sg:postcode":"33160",
    "sg:province":"FL",
    "sg:tags":[
        "asian",
        "pan",
        "japanese"
    ],
    "wof:name":"Sushi Sake Nmb Inc",
    "wof:placetype":"venue"
},
  "geometry": {"coordinates":[-80.14851,25.94279],"type":"Point"}
}