{
  "type": "Feature",
  "properties": {
    "addr:full":"857 E Bloomingdale Ave Brandon FL 33511",
    "addr:housenumber":"857",
    "addr:postcode":"33511",
    "addr:street":"E Bloomingdale Ave",
    "iso:country":"US",
    "sg:address":"857 E Bloomingdale Ave",
    "sg:city":"Brandon",
    "sg:classifiers":[
        {
            "category":"Shopping",
            "type":"Retail Goods"
        }
    ],
    "sg:phone":"+1 813 655 6400",
    "sg:postcode":"33511",
    "sg:province":"FL",
    "sg:tags":[
        "art",
        "framing"
    ],
    "wof:name":"Fastframe",
    "wof:placetype":"venue"
},
  "geometry": {"coordinates":[-82.27221900000001,27.893564],"type":"Point"}
}