{
  "type": "Feature",
  "properties": {
    "addr:full":"305 SW 7th Ter Gainesville FL 32601",
    "addr:housenumber":"305",
    "addr:postcode":"32601",
    "addr:street":"Sw 7Th Ter",
    "iso:country":"US",
    "sg:address":"305 SW 7th Ter",
    "sg:city":"Gainesville",
    "sg:phone":"+1 352 335 8008",
    "sg:postcode":"32601",
    "sg:province":"FL",
    "wof:name":"Dubas Rick DC",
    "wof:placetype":"venue"
},
  "geometry": {"coordinates":[-82.332329,29.649318],"type":"Point"}
}