{
  "type": "Feature",
  "properties": {
    "iso:country":"US",
    "sg:address":"1014 71st St",
    "sg:city":"Miami Beach",
    "sg:classifiers":[
        {
            "category":"Food & Beverages",
            "subcategory":"Fruits & Vegetables",
            "type":"Retail Goods"
        }
    ],
    "sg:phone":"+1 305 868 8009",
    "sg:postcode":"33141",
    "sg:province":"FL",
    "sg:tags":[
        "smoothie",
        "juice",
        "bar"
    ],
    "wof:name":"Juices & Bites",
    "wof:placetype":"venue"
},
  "geometry": {"coordinates":[-80.129402,25.855],"type":"Point"}
}