{
  "type": "Feature",
  "properties": {
    "addr:full":"7380 NW 44th Ct Fort Lauderdale FL 33319",
    "addr:housenumber":"7380",
    "addr:postcode":"33319",
    "addr:street":"Nw 44Th Ct",
    "iso:country":"US",
    "sg:address":"7380 NW 44th Ct",
    "sg:city":"Fort Lauderdale",
    "sg:classifiers":[
        {
            "category":"Wholesale",
            "subcategory":"Stationery",
            "type":"Manufacturing & Wholesale Goods"
        },
        {
            "category":"Manufacturing",
            "subcategory":"Paper Products",
            "type":"Manufacturing & Wholesale Goods"
        }
    ],
    "sg:phone":"+1 954 572 4991",
    "sg:postcode":"33319",
    "sg:province":"FL",
    "sg:tags":[
        "datum",
        "processing",
        "coated",
        "laminated",
        "supply"
    ],
    "wof:name":"Contract Supply Corporation",
    "wof:placetype":"venue"
},
  "geometry": {"coordinates":[-80.248192,26.178785],"type":"Point"}
}