{
  "type": "Feature",
  "properties": {
    "addr:full":"2754 NW 193rd Ter Opa Locka FL 33056",
    "addr:housenumber":"2754",
    "addr:postcode":"33056",
    "addr:street":"Nw 193Rd Ter;Locka",
    "iso:country":"US",
    "sg:address":"2754 NW 193rd Ter",
    "sg:city":"Opa Locka",
    "sg:classifiers":[
        {
            "category":"Professional",
            "type":"Services"
        }
    ],
    "sg:phone":"+1 305 622 9490",
    "sg:postcode":"33056",
    "sg:province":"FL",
    "sg:tags":[
        "establishment"
    ],
    "wof:name":"Flos Caf",
    "wof:placetype":"venue"
},
  "geometry": {"coordinates":[-80.247451,25.949354],"type":"Point"}
}