{
  "type": "Feature",
  "properties": {
    "iso:country":"US",
    "sg:address":"9600 NW 25th St",
    "sg:city":"Doral",
    "sg:classifiers":[
        {
            "category":"Travel",
            "subcategory":"Travel Agent",
            "type":"Entertainment"
        }
    ],
    "sg:phone":"+1 305 639 3408",
    "sg:postcode":"33172",
    "sg:province":"FL",
    "sg:tags":[
        "agency",
        "bureau"
    ],
    "sg:website":"www.kekastvl.com",
    "wof:name":"Keka's Travel Agency",
    "wof:placetype":"venue"
},
  "geometry": {"coordinates":[-80.353081,25.796864],"type":"Point"}
}