{
  "type": "Feature",
  "properties": {
    "iso:country":"US",
    "sg:address":"327 SW 1st Ave",
    "sg:city":"Boynton Beach",
    "sg:classifiers":[
        {
            "category":"Professional",
            "subcategory":"Management & Consulting",
            "type":"Services"
        }
    ],
    "sg:phone":"+1 561 732 2530",
    "sg:postcode":"33435",
    "sg:province":"FL",
    "wof:name":"Dental Solutions",
    "wof:placetype":"venue"
},
  "geometry": {"coordinates":[-80.068425,26.52634],"type":"Point"}
}