{
  "type": "Feature",
  "properties": {
    "iso:country":"US",
    "sg:address":"5650 Red Bug Lake Rd",
    "sg:city":"Winter Springs",
    "sg:classifiers":[
        {
            "category":"Shopping",
            "subcategory":"Pharmacy",
            "type":"Retail Goods"
        }
    ],
    "sg:phone":"+1 407 699 0781",
    "sg:postcode":"32708",
    "sg:province":"FL",
    "sg:tags":[
        "drugstore"
    ],
    "sg:website":"www.cvs.com",
    "wof:name":"CVS",
    "wof:placetype":"venue"
},
  "geometry": {"coordinates":[-81.271698,28.6476],"type":"Point"}
}