{
  "type": "Feature",
  "properties": {
    "iso:country":"US",
    "sg:address":"13914 18th Pl E",
    "sg:city":"Bradenton",
    "sg:classifiers":[
        {
            "category":"Professional",
            "subcategory":"Computer Services",
            "type":"Services"
        }
    ],
    "sg:phone":"+1 941 708 8939",
    "sg:postcode":"34212",
    "sg:province":"FL",
    "sg:website":"www.ebayalternative.com",
    "wof:name":"P C Expertise Inc",
    "wof:placetype":"venue"
},
  "geometry": {"coordinates":[-82.40406900000001,27.482905],"type":"Point"}
}