{
  "type": "Feature",
  "properties": {
    "addr:full":"2725 SW 27th Ave Miami FL 33133",
    "addr:housenumber":"2725",
    "addr:postcode":"33133",
    "addr:street":"Sw 27Th Ave",
    "iso:country":"US",
    "sg:address":"2725 SW 27th Ave",
    "sg:city":"Miami",
    "sg:classifiers":[
        {
            "category":"Real Estate",
            "subcategory":"Architect",
            "type":"Services"
        }
    ],
    "sg:phone":"+1 305 937 1970",
    "sg:postcode":"33133",
    "sg:province":"FL",
    "sg:tags":[
        "architectural"
    ],
    "wof:name":"Harvey J Ehrlich Architect PA",
    "wof:placetype":"venue"
},
  "geometry": {"coordinates":[-80.237824,25.741238],"type":"Point"}
}