{
  "type": "Feature",
  "properties": {
    "iso:country":"US",
    "sg:address":"7061 Grand National Dr",
    "sg:city":"Orlando",
    "sg:classifiers":[
        {
            "category":"Arena",
            "subcategory":"Sports Club",
            "type":"Entertainment"
        }
    ],
    "sg:phone":"+1 407 352 5988",
    "sg:postcode":"32819",
    "sg:province":"FL",
    "sg:tags":[
        "soccer"
    ],
    "wof:name":"Brusa International Soccer",
    "wof:placetype":"venue"
},
  "geometry": {"coordinates":[-81.456153,28.458715],"type":"Point"}
}