{
  "type": "Feature",
  "properties": {
    "iso:country":"US",
    "sg:address":"1405 Kingsley Ave",
    "sg:city":"Orange Park",
    "sg:classifiers":[
        {
            "category":"Insurance",
            "subcategory":"Insurance Agent",
            "type":"Services"
        }
    ],
    "sg:phone":"+1 904 215 2121",
    "sg:postcode":"32073",
    "sg:province":"FL",
    "wof:name":"Jane Diloreto Insurance Agency",
    "wof:placetype":"venue"
},
  "geometry": {"coordinates":[-81.729652,30.164632],"type":"Point"}
}