{
  "type": "Feature",
  "properties": {
    "iso:country":"US",
    "sg:address":"4366 Independence Ct",
    "sg:city":"Sarasota",
    "sg:classifiers":[
        {
            "category":"Home & Garden",
            "subcategory":"Furniture",
            "type":"Retail Goods"
        }
    ],
    "sg:phone":"+1 941 359 1121",
    "sg:postcode":"34234",
    "sg:province":"FL",
    "wof:name":"Independence Imports",
    "wof:placetype":"venue"
},
  "geometry": {"coordinates":[-82.53733699999999,27.371806],"type":"Point"}
}