{
  "type": "Feature",
  "properties": {
    "iso:country":"US",
    "sg:address":"640 John Sims Pkwy E",
    "sg:city":"Niceville",
    "sg:classifiers":[
        {
            "category":"Autos & Motor Vehicles",
            "subcategory":"Automobile Sales",
            "type":"Retail Goods"
        },
        {
            "category":"Retail",
            "subcategory":"Auto Rental",
            "type":"Services"
        }
    ],
    "sg:phone":"+1 850 678 4550",
    "sg:postcode":"32578",
    "sg:province":"FL",
    "sg:tags":[
        "car",
        "used",
        "cars-wholesale",
        "dealers-used"
    ],
    "wof:name":"Price King Rent A Car",
    "wof:placetype":"venue"
},
  "geometry": {"coordinates":[-86.472792,30.517399],"type":"Point"}
}