{
  "type": "Feature",
  "properties": {
    "iso:country":"US",
    "sg:address":"18280 Panther Trail Ln",
    "sg:city":"Fort Myers",
    "sg:classifiers":[
        {
            "category":"Building & Trades",
            "subcategory":"Cleaning & Sanitation",
            "type":"Services"
        }
    ],
    "sg:phone":"+1 239 731 7106",
    "sg:postcode":"33917",
    "sg:province":"FL",
    "sg:tags":[
        "janitor"
    ],
    "wof:name":"Best Blind Cleaning",
    "wof:placetype":"venue"
},
  "geometry": {"coordinates":[-81.83159499999999,26.729331],"type":"Point"}
}