{
  "type": "Feature",
  "properties": {
    "iso:country":"US",
    "sg:address":"6640 Congress St",
    "sg:city":"New Port Richey",
    "sg:classifiers":[
        {
            "category":"Professional",
            "subcategory":"Lawyer & Legal Services",
            "type":"Services"
        }
    ],
    "sg:phone":"+1 727 848 8892",
    "sg:postcode":"34653",
    "sg:province":"FL",
    "sg:tags":[
        "attorney"
    ],
    "wof:name":"Mc Pherson Law Offices",
    "wof:placetype":"venue"
},
  "geometry": {"coordinates":[-82.707189,28.253794],"type":"Point"}
}