{
  "type": "Feature",
  "properties": {
    "iso:country":"US",
    "sg:address":"7400 Biscayne Blvd",
    "sg:city":"Miami",
    "sg:classifiers":[
        {
            "category":"Food & Beverages",
            "subcategory":"Groceries & Convenience Stores",
            "type":"Retail Goods"
        }
    ],
    "sg:phone":"+1 305 400 8459",
    "sg:postcode":"33138",
    "sg:province":"FL",
    "wof:name":"Rafiul Food Store",
    "wof:placetype":"venue"
},
  "geometry": {"coordinates":[-80.18458200000001,25.84311],"type":"Point"}
}