{
  "type": "Feature",
  "properties": {
    "addr:full":"200 S Banana River Dr Merritt Island FL 32952",
    "addr:housenumber":"200",
    "addr:postcode":"32952",
    "addr:street":"S Banana River Dr",
    "iso:country":"US",
    "sg:address":"200 S Banana River Dr",
    "sg:city":"Merritt Island",
    "sg:classifiers":[
        {
            "category":"Home & Garden",
            "subcategory":"Garden Supply",
            "type":"Retail Goods"
        }
    ],
    "sg:phone":"+1 321 453 0105",
    "sg:postcode":"32952",
    "sg:province":"FL",
    "sg:tags":[
        "sprinkler"
    ],
    "wof:name":"Dave's Sprinklers",
    "wof:placetype":"venue"
},
  "geometry": {"coordinates":[-80.662244,28.356249],"type":"Point"}
}