{
  "type": "Feature",
  "properties": {
    "iso:country":"US",
    "sg:address":"10468 Roxbury Ln",
    "sg:city":"Jacksonville",
    "sg:classifiers":[
        {
            "category":"Freight",
            "type":"Transportation"
        }
    ],
    "sg:phone":"+1 904 292 0035",
    "sg:postcode":"32257",
    "sg:province":"FL",
    "sg:tags":[
        "delivery"
    ],
    "wof:name":"William Anderson's Delivery",
    "wof:placetype":"venue"
},
  "geometry": {"coordinates":[-81.59295899999999,30.185782],"type":"Point"}
}