{
  "type": "Feature",
  "properties": {
    "addr:full":"2305 53rd Ave W Bradenton FL 34207",
    "addr:housenumber":"2305",
    "addr:postcode":"34207",
    "addr:street":"53Rd Ave W",
    "iso:country":"US",
    "sg:address":"2305 53rd Ave W",
    "sg:city":"Bradenton",
    "sg:classifiers":[
        {
            "category":"Real Estate",
            "subcategory":"Real Estate Agent",
            "type":"Services"
        }
    ],
    "sg:phone":"+1 941 756 8818",
    "sg:postcode":"34207",
    "sg:province":"FL",
    "sg:website":"www.irongaterealty.com",
    "wof:name":"Irongate Realty Inc",
    "wof:placetype":"venue"
},
  "geometry": {"coordinates":[-82.58549499999999,27.447842],"type":"Point"}
}