{
  "type": "Feature",
  "properties": {
    "iso:country":"US",
    "sg:address":"1924 Dovefield Pl",
    "sg:city":"Brandon",
    "sg:classifiers":[
        {
            "category":"Manufacturing",
            "subcategory":"Signs",
            "type":"Manufacturing & Wholesale Goods"
        }
    ],
    "sg:phone":"+1 813 685 6006",
    "sg:postcode":"33510",
    "sg:province":"FL",
    "sg:tags":[
        "specialty",
        "mfg"
    ],
    "wof:name":"Scooters Signs & Graphics",
    "wof:placetype":"venue"
},
  "geometry": {"coordinates":[-82.31634099999999,27.967402],"type":"Point"}
}