{
  "type": "Feature",
  "properties": {
    "iso:country":"US",
    "sg:address":"9416 Debbie Ln",
    "sg:city":"Port Richey",
    "sg:classifiers":[
        {
            "category":"Building & Trades",
            "subcategory":"Landscaping Services",
            "type":"Services"
        }
    ],
    "sg:phone":"+1 727 863 5005",
    "sg:postcode":"34669",
    "sg:province":"FL",
    "sg:tags":[
        "landscape"
    ],
    "wof:name":"Douglas Wharran",
    "wof:placetype":"venue"
},
  "geometry": {"coordinates":[-82.659415,28.35464],"type":"Point"}
}