{
  "type": "Feature",
  "properties": {
    "iso:country":"US",
    "sg:address":"1820 N Main St",
    "sg:city":"Kissimmee",
    "sg:classifiers":[
        {
            "category":"Food & Beverages",
            "subcategory":"Groceries & Convenience Stores",
            "type":"Retail Goods"
        }
    ],
    "sg:phone":"+1 407 932 2211",
    "sg:postcode":"34744",
    "sg:province":"FL",
    "sg:tags":[
        "grocer"
    ],
    "wof:name":"KASH N' Karry",
    "wof:placetype":"venue"
},
  "geometry": {"coordinates":[-81.40382,28.3074],"type":"Point"}
}