{
  "type": "Feature",
  "properties": {
    "iso:country":"US",
    "sg:address":"2100 SW 123rd Ct",
    "sg:city":"Miami",
    "sg:classifiers":[
        {
            "category":"Wholesale",
            "subcategory":"Groceries",
            "type":"Manufacturing & Wholesale Goods"
        }
    ],
    "sg:phone":"+1 305 485 5910",
    "sg:postcode":"33175",
    "sg:province":"FL",
    "sg:tags":[
        "food",
        "products-wholesale"
    ],
    "wof:name":"Willy Products & Produce Inc",
    "wof:placetype":"venue"
},
  "geometry": {"coordinates":[-80.39469699999999,25.747266],"type":"Point"}
}