{
  "type": "Feature",
  "properties": {
    "addr:full":"1901 E Colonial Dr Orlando FL 32803",
    "addr:housenumber":"1901",
    "addr:postcode":"32803",
    "addr:street":"E Colonial Dr",
    "iso:country":"US",
    "sg:address":"1901 E Colonial Dr",
    "sg:city":"Orlando",
    "sg:classifiers":[
        {
            "category":"Restaurant",
            "type":"Food & Drink"
        }
    ],
    "sg:menulink":"http://www.allmenus.com/fl/orlando/46428-chans-chinese-cuisine/menu/",
    "sg:phone":"+1 407 896 0093",
    "sg:postcode":"32803",
    "sg:province":"FL",
    "sg:tags":[
        "asian",
        "chinese"
    ],
    "wof:name":"Chan's Chinese Cuisine",
    "wof:placetype":"venue"
},
  "geometry": {"coordinates":[-81.357024,28.553619],"type":"Point"}
}