{
  "type": "Feature",
  "properties": {
    "iso:country":"US",
    "sg:address":"76347 Veterans Way Ste 2105",
    "sg:city":"Yulee",
    "sg:classifiers":[
        {
            "category":"Government",
            "subcategory":"Court House",
            "type":"Public Place"
        },
        {
            "category":"Government",
            "subcategory":"Office",
            "type":"Public Place"
        }
    ],
    "sg:phone":"+1 904 548 4700",
    "sg:postcode":"32097",
    "sg:province":"FL",
    "sg:tags":[
        "justice"
    ],
    "wof:name":"State Attorney Circuit Court",
    "wof:placetype":"venue"
},
  "geometry": {"coordinates":[-81.63093000000001,30.612555],"type":"Point"}
}