{
  "type": "Feature",
  "properties": {
    "addr:full":"1235 Clearlake Rd Cocoa FL 32922",
    "addr:housenumber":"1235",
    "addr:postcode":"32922",
    "addr:street":"Clearlake Rd",
    "iso:country":"US",
    "sg:address":"1235 Clearlake Rd",
    "sg:city":"Cocoa",
    "sg:classifiers":[
        {
            "category":"Autos & Motor Vehicles",
            "subcategory":"Automobile Sales",
            "type":"Retail Goods"
        }
    ],
    "sg:phone":"+1 321 639 0022",
    "sg:postcode":"32922",
    "sg:province":"FL",
    "sg:tags":[
        "used"
    ],
    "wof:name":"Koala-T Cars Inc",
    "wof:placetype":"venue"
},
  "geometry": {"coordinates":[-80.75509700000001,28.37716],"type":"Point"}
}