{
  "type": "Feature",
  "properties": {
    "addr:full":"11710 NW South River Dr Miami FL 33178",
    "addr:housenumber":"11710",
    "addr:postcode":"33178",
    "addr:street":"Nw South River Dr",
    "iso:country":"US",
    "sg:address":"11710 NW South River Dr",
    "sg:city":"Miami",
    "sg:classifiers":[
        {
            "category":"Personal",
            "type":"Services"
        }
    ],
    "sg:phone":"+1 305 887 9917",
    "sg:postcode":"33178",
    "sg:province":"FL",
    "sg:tags":[
        "house",
        "sitting"
    ],
    "wof:name":"Mothers Sitting Services",
    "wof:placetype":"venue"
},
  "geometry": {"coordinates":[-80.358698,25.880045],"type":"Point"}
}