{
  "type": "Feature",
  "properties": {
    "iso:country":"US",
    "sg:address":"1304 Avenue N",
    "sg:city":"Haines City",
    "sg:classifiers":[
        {
            "category":"Bars & Pubs",
            "type":"Food & Drink"
        },
        {
            "category":"Restaurant",
            "type":"Food & Drink"
        }
    ],
    "sg:phone":"+1 863 422 5881",
    "sg:postcode":"33844",
    "sg:province":"FL",
    "sg:tags":[
        "drinking"
    ],
    "wof:name":"Mary's Place",
    "wof:placetype":"venue"
},
  "geometry": {"coordinates":[-81.620019,28.126444],"type":"Point"}
}