{
  "type": "Feature",
  "properties": {
    "iso:country":"US",
    "sg:address":"3409 W Co Hwy 30A",
    "sg:city":"Santa Rosa Beach",
    "sg:classifiers":[
        {
            "category":"Real Estate",
            "subcategory":"Real Estate Agent",
            "type":"Services"
        }
    ],
    "sg:phone":"+1 850 213 5250",
    "sg:postcode":"32459",
    "sg:province":"FL",
    "wof:name":"Draper Lake",
    "wof:placetype":"venue"
},
  "geometry": {"coordinates":[-86.214322,30.348828],"type":"Point"}
}