{
  "type": "Feature",
  "properties": {
    "addr:full":"5211 Haines Rd N St Petersburg FL 33714",
    "addr:housenumber":"5211",
    "addr:postcode":"33714",
    "addr:street":"Haines Rd N",
    "iso:country":"US",
    "sg:address":"5211 Haines Rd N",
    "sg:city":"St Petersburg",
    "sg:classifiers":[
        {
            "category":"Home & Garden",
            "subcategory":"Building Materials",
            "type":"Retail Goods"
        }
    ],
    "sg:phone":"+1 727 526 3723",
    "sg:postcode":"33714",
    "sg:province":"FL",
    "sg:tags":[
        "windows"
    ],
    "wof:name":"Del Windows Inc",
    "wof:placetype":"venue"
},
  "geometry": {"coordinates":[-82.667537,27.819824],"type":"Point"}
}