{
  "type": "Feature",
  "properties": {
    "iso:country":"US",
    "sg:address":"315 Racetrack Rd NE",
    "sg:city":"Fort Walton Bch",
    "sg:classifiers":[
        {
            "category":"Insurance",
            "subcategory":"Insurance Agent",
            "type":"Services"
        }
    ],
    "sg:phone":"+1 850 863 2137",
    "sg:postcode":"32547",
    "sg:province":"FL",
    "wof:name":"Larson Agency",
    "wof:placetype":"venue"
},
  "geometry": {"coordinates":[-86.603081,30.443902],"type":"Point"}
}