{
  "type": "Feature",
  "properties": {
    "iso:country":"US",
    "sg:address":"5802 E Fowler Ave",
    "sg:city":"Tampa",
    "sg:classifiers":[
        {
            "category":"Building & Trades",
            "subcategory":"Construction",
            "type":"Services"
        }
    ],
    "sg:phone":"+1 813 404 8466",
    "sg:postcode":"33617",
    "sg:province":"FL",
    "sg:tags":[
        "course",
        "golf"
    ],
    "wof:name":"Golf Spectrum Inc",
    "wof:placetype":"venue"
},
  "geometry": {"coordinates":[-82.39146,28.054413],"type":"Point"}
}