{
  "type": "Feature",
  "properties": {
    "iso:country":"US",
    "sg:address":"4300 70th Ave N",
    "sg:city":"Pinellas Park",
    "sg:classifiers":[
        {
            "category":"Building & Trades",
            "subcategory":"Construction",
            "type":"Services"
        }
    ],
    "sg:phone":"+1 727 215 9341",
    "sg:postcode":"33781",
    "sg:province":"FL",
    "sg:tags":[
        "house"
    ],
    "wof:name":"Thomas Leasure",
    "wof:placetype":"venue"
},
  "geometry": {"coordinates":[-82.693878,27.835556],"type":"Point"}
}