{
  "type": "Feature",
  "properties": {
    "addr:full":"6676 SE 147th St Summerfield FL 34491",
    "addr:housenumber":"6676",
    "addr:postcode":"34491",
    "addr:street":"Se 147Th St",
    "iso:country":"US",
    "sg:address":"6676 SE 147th St",
    "sg:city":"Summerfield",
    "sg:classifiers":[
        {
            "category":"Autos & Motor Vehicles",
            "subcategory":"Automobile Sales",
            "type":"Retail Goods"
        }
    ],
    "sg:phone":"+1 352 307 2004",
    "sg:postcode":"34491",
    "sg:province":"FL",
    "wof:name":"Mid-Florida Auto Body",
    "wof:placetype":"venue"
},
  "geometry": {"coordinates":[-82.03652099999999,29.008634],"type":"Point"}
}