{
  "type": "Feature",
  "properties": {
    "addr:full":"1136 NE Pine Island Rd Cape Coral FL 33909",
    "addr:housenumber":"1136",
    "addr:postcode":"33909",
    "addr:street":"Ne Pine Island Rd",
    "iso:country":"US",
    "sg:address":"1136 NE Pine Island Rd",
    "sg:city":"Cape Coral",
    "sg:classifiers":[
        {
            "category":"Banks & Credit Unions",
            "subcategory":"Bank",
            "type":"Services"
        }
    ],
    "sg:phone":"+1 239 458 4800",
    "sg:postcode":"33909",
    "sg:province":"FL",
    "sg:tags":[
        "loan",
        "broker",
        "real estate",
        "mtg"
    ],
    "wof:name":"Southern State Mortgage Inc",
    "wof:placetype":"venue"
},
  "geometry": {"coordinates":[-81.947484,26.664314],"type":"Point"}
}