{
  "type": "Feature",
  "properties": {
    "iso:country":"US",
    "sg:address":"1492 Charles Blvd NE",
    "sg:city":"Cape Canaveral",
    "sg:classifiers":[
        {
            "category":"Travel",
            "subcategory":"Travel Agent",
            "type":"Entertainment"
        }
    ],
    "sg:phone":"+1 321 799 0638",
    "sg:postcode":"32907",
    "sg:province":"FL",
    "sg:tags":[
        "cruise"
    ],
    "wof:name":"Carnival Cruise Lines",
    "wof:placetype":"venue"
},
  "geometry": {"coordinates":[-80.628446,28.00442],"type":"Point"}
}