{
  "type": "Feature",
  "properties": {
    "iso:country":"US",
    "sg:address":"210 Palmetto St",
    "sg:city":"New Smyrna Beach",
    "sg:classifiers":[
        {
            "category":"Building & Trades",
            "subcategory":"Cleaning & Sanitation",
            "type":"Services"
        }
    ],
    "sg:phone":"+1 386 423 3993",
    "sg:postcode":"32168",
    "sg:province":"FL",
    "sg:tags":[
        "window"
    ],
    "wof:name":"F-N-A Window Cleaning Inc",
    "wof:placetype":"venue"
},
  "geometry": {"coordinates":[-80.92363899999999,29.022639],"type":"Point"}
}