{
  "type": "Feature",
  "properties": {
    "addr:full":"19 Northwest Ave Miami FL 33101",
    "addr:housenumber":"19",
    "addr:postcode":"33101",
    "addr:street":"Northwest Ave",
    "iso:country":"US",
    "sg:address":"19 Northwest Ave",
    "sg:city":"Miami",
    "sg:classifiers":[
        {
            "category":"Building & Trades",
            "subcategory":"Locksmith",
            "type":"Services"
        }
    ],
    "sg:phone":"+1 786 718 1445",
    "sg:postcode":"33101",
    "sg:province":"FL",
    "sg:tags":[
        "key"
    ],
    "wof:name":"0 Locksmith",
    "wof:placetype":"venue"
},
  "geometry": {"coordinates":[-80.31356,25.770684],"type":"Point"}
}