{
  "type": "Feature",
  "properties": {
    "iso:country":"US",
    "sg:address":"105 N Mellonville Ave",
    "sg:city":"Sanford",
    "sg:classifiers":[
        {
            "category":"Building & Trades",
            "subcategory":"Landscaping Services",
            "type":"Services"
        }
    ],
    "sg:phone":"+1 407 323 9543",
    "sg:postcode":"32771",
    "sg:province":"FL",
    "sg:tags":[
        "landscape",
        "contractor"
    ],
    "wof:name":"De Young Skees Inc",
    "wof:placetype":"venue"
},
  "geometry": {"coordinates":[-81.254694,28.812462],"type":"Point"}
}