{
  "type": "Feature",
  "properties": {
    "addr:full":"6210 NW 124th St Gainesville FL 32653",
    "addr:housenumber":"6210",
    "addr:postcode":"32653",
    "addr:street":"Nw 124Th St",
    "iso:country":"US",
    "sg:address":"6210 NW 124th St",
    "sg:city":"Gainesville",
    "sg:classifiers":[
        {
            "category":"Building & Trades",
            "subcategory":"Construction",
            "type":"Services"
        }
    ],
    "sg:phone":"+1 386 418 0185",
    "sg:postcode":"32653",
    "sg:province":"FL",
    "sg:tags":[
        "portable",
        "manufacturer"
    ],
    "wof:name":"Pro Built Inc",
    "wof:placetype":"venue"
},
  "geometry": {"coordinates":[-82.474301,29.711756],"type":"Point"}
}