{
  "type": "Feature",
  "properties": {
    "iso:country":"US",
    "sg:address":"1116 Rita Ln",
    "sg:city":"Niceville",
    "sg:classifiers":[
        {
            "category":"Arts & Performance",
            "subcategory":"Theater",
            "type":"Entertainment"
        }
    ],
    "sg:phone":"+1 850 678 5131",
    "sg:postcode":"32578",
    "sg:province":"FL",
    "sg:tags":[
        "bureau"
    ],
    "wof:name":"Northwest Florida Volleyball",
    "wof:placetype":"venue"
},
  "geometry": {"coordinates":[-86.46967600000001,30.526406],"type":"Point"}
}