{
  "type": "Feature",
  "properties": {
    "addr:full":"5252 State Rd 54 New Port Richey FL 34652",
    "addr:housenumber":"5252;54",
    "addr:postcode":"34652",
    "addr:street":"State Rd",
    "iso:country":"US",
    "sg:address":"5252 State Rd 54",
    "sg:city":"New Port Richey",
    "sg:classifiers":[
        {
            "category":"Building & Trades",
            "subcategory":"Landscaping Services",
            "type":"Services"
        }
    ],
    "sg:phone":"+1 727 858 8804",
    "sg:postcode":"34652",
    "sg:province":"FL",
    "wof:name":"Purnell Landscape & Tree",
    "wof:placetype":"venue"
},
  "geometry": {"coordinates":[-82.72341900000001,28.217003],"type":"Point"}
}