{
  "type": "Feature",
  "properties": {
    "addr:full":"7130 S Orange Blossom Trl Orlando FL 32809",
    "addr:housenumber":"7130",
    "addr:postcode":"32809",
    "addr:street":"S Orange Blossom Trl",
    "iso:country":"US",
    "sg:address":"7130 S Orange Blossom Trl",
    "sg:city":"Orlando",
    "sg:classifiers":[
        {
            "category":"Professional",
            "subcategory":"Detective & Security Services",
            "type":"Services"
        }
    ],
    "sg:phone":"+1 407 251 3080",
    "sg:postcode":"32809",
    "sg:province":"FL",
    "sg:tags":[
        "guard",
        "patrol"
    ],
    "sg:website":"www.excelsiordefense.com",
    "wof:name":"Excelsior Defense Inc",
    "wof:placetype":"venue"
},
  "geometry": {"coordinates":[-81.397969,28.460687],"type":"Point"}
}