{
  "type": "Feature",
  "properties": {
    "iso:country":"US",
    "sg:address":"3443 Tamiami Trl",
    "sg:city":"Port Charlotte",
    "sg:classifiers":[
        {
            "category":"Professional",
            "subcategory":"Research",
            "type":"Services"
        }
    ],
    "sg:phone":"+1 941 235 1548",
    "sg:postcode":"33952",
    "sg:province":"FL",
    "sg:tags":[
        "development",
        "laboratory"
    ],
    "wof:name":"Pulmanory Studies",
    "wof:placetype":"venue"
},
  "geometry": {"coordinates":[-82.09610499999999,26.979471],"type":"Point"}
}