{
  "type": "Feature",
  "properties": {
    "iso:country":"US",
    "sg:address":"207 Springview Dr",
    "sg:city":"Sanford",
    "sg:classifiers":[
        {
            "category":"Professional",
            "subcategory":"Computer Services",
            "type":"Services"
        }
    ],
    "sg:phone":"+1 407 323 7399",
    "sg:postcode":"32773",
    "sg:province":"FL",
    "sg:tags":[
        "networking",
        "sales"
    ],
    "wof:name":"Iwp",
    "wof:placetype":"venue"
},
  "geometry": {"coordinates":[-81.309999,28.761858],"type":"Point"}
}