{
  "type": "Feature",
  "properties": {
    "addr:full":"1039 Wyndham Lakes Dr Odessa FL 33556",
    "addr:housenumber":"1039",
    "addr:postcode":"33556",
    "addr:street":"Wyndham Lakes Dr",
    "iso:country":"US",
    "sg:address":"1039 Wyndham Lakes Dr",
    "sg:city":"Odessa",
    "sg:classifiers":[
        {
            "category":"Freight",
            "type":"Transportation"
        }
    ],
    "sg:phone":"+1 813 792 9268",
    "sg:postcode":"33556",
    "sg:province":"FL",
    "sg:tags":[
        "operator",
        "local",
        "trucking"
    ],
    "wof:name":"Sawyer S Trucking Inc",
    "wof:placetype":"venue"
},
  "geometry": {"coordinates":[-82.583668,28.174909],"type":"Point"}
}