{
  "type": "Feature",
  "properties": {
    "iso:country":"US",
    "sg:address":"1676 N Q St",
    "sg:city":"Pensacola",
    "sg:classifiers":[
        {
            "category":"Organizations",
            "subcategory":"Religious Organization",
            "type":"Services"
        }
    ],
    "sg:phone":"+1 850 432 9935",
    "sg:postcode":"32505",
    "sg:province":"FL",
    "sg:tags":[
        "church"
    ],
    "wof:name":"New Birth Baptist Church",
    "wof:placetype":"venue"
},
  "geometry": {"coordinates":[-87.242952,30.428529],"type":"Point"}
}