{
  "type": "Feature",
  "properties": {
    "addr:full":"947 Brickell Avenue Miami FL 33131",
    "addr:housenumber":"947",
    "addr:postcode":"33131",
    "addr:street":"Brickell Avenue",
    "iso:country":"US",
    "sg:address":"947 Brickell Avenue",
    "sg:city":"Miami",
    "sg:classifiers":[
        {
            "category":"Restaurant",
            "type":"Food & Drink"
        }
    ],
    "sg:phone":"+1 786 220 7930",
    "sg:postcode":"33131",
    "sg:province":"FL",
    "sg:tags":[
        "peruvian"
    ],
    "wof:name":"El Gran Inka",
    "wof:placetype":"venue"
},
  "geometry": {"coordinates":[-80.190967,25.76463],"type":"Point"}
}