{
  "type": "Feature",
  "properties": {
    "addr:full":"1111 18th Ave S Saint Petersburg FL 33705",
    "addr:housenumber":"1111",
    "addr:postcode":"33705",
    "addr:street":"18Th Ave S",
    "iso:country":"US",
    "sg:address":"1111 18th Ave S",
    "sg:city":"Saint Petersburg",
    "sg:classifiers":[
        {
            "category":"Education",
            "subcategory":"Library",
            "type":"Public Place"
        }
    ],
    "sg:phone":"+1 727 893 7113",
    "sg:postcode":"33705",
    "sg:province":"FL",
    "sg:tags":[
        "executive"
    ],
    "wof:name":"James Weldon Johnson BR Lib",
    "wof:placetype":"venue"
},
  "geometry": {"coordinates":[-82.650672,27.752094],"type":"Point"}
}