{
  "type": "Feature",
  "properties": {
    "addr:full":"807 NE Park St Okeechobee FL 34972",
    "addr:housenumber":"807",
    "addr:postcode":"34972",
    "addr:street":"Ne Park St",
    "iso:country":"US",
    "sg:address":"807 NE Park St",
    "sg:city":"Okeechobee",
    "sg:classifiers":[
        {
            "category":"Home & Garden",
            "subcategory":"Mobile Homes",
            "type":"Retail Goods"
        }
    ],
    "sg:phone":"+1 863 763 1126",
    "sg:postcode":"34972",
    "sg:province":"FL",
    "sg:tags":[
        "manufactured",
        "sales",
        "house"
    ],
    "wof:name":"Rick Wemier",
    "wof:placetype":"venue"
},
  "geometry": {"coordinates":[-80.821607,27.24383],"type":"Point"}
}