{
  "type": "Feature",
  "properties": {
    "addr:full":"3410 SW College Rd Ocala FL 34474",
    "addr:housenumber":"3410",
    "addr:postcode":"34474",
    "addr:street":"Sw College Rd",
    "iso:country":"US",
    "sg:address":"3410 SW College Rd",
    "sg:city":"Ocala",
    "sg:phone":"+1 352 873 1133",
    "sg:postcode":"34474",
    "sg:province":"FL",
    "sg:website":"http://www.lonestarsteakhouse.com",
    "wof:name":"Lone Star Steakhouse & Saloon",
    "wof:placetype":"venue"
},
  "geometry": {"coordinates":[-82.17905,29.156203],"type":"Point"}
}