{
  "type": "Feature",
  "properties": {
    "addr:full":"10500 NW 50th St Fort Lauderdale FL 33351",
    "addr:housenumber":"10500",
    "addr:postcode":"33351",
    "addr:street":"Nw 50Th St",
    "iso:country":"US",
    "sg:address":"10500 NW 50th St",
    "sg:city":"Fort Lauderdale",
    "sg:classifiers":[
        {
            "category":"Banks & Credit Unions",
            "subcategory":"Investment Brokerage",
            "type":"Services"
        }
    ],
    "sg:phone":"+1 954 572 0599",
    "sg:postcode":"33351",
    "sg:province":"FL",
    "sg:tags":[
        "brokerage",
        "leasing"
    ],
    "wof:name":"Belmont Financial Services",
    "wof:placetype":"venue"
},
  "geometry": {"coordinates":[-80.288775,26.186408],"type":"Point"}
}