{
  "type": "Feature",
  "properties": {
    "iso:country":"US",
    "sg:address":"5415 11th Street Cir E",
    "sg:city":"Bradenton",
    "sg:classifiers":[
        {
            "category":"Organizations",
            "subcategory":"Religious Organization",
            "type":"Services"
        }
    ],
    "sg:phone":"+1 941 756 7558",
    "sg:postcode":"34203",
    "sg:province":"FL",
    "sg:tags":[
        "church"
    ],
    "sg:website":"www.gccnet.org",
    "wof:name":"Grace Community Church",
    "wof:placetype":"venue"
},
  "geometry": {"coordinates":[-82.552694,27.445172],"type":"Point"}
}