{
  "type": "Feature",
  "properties": {
    "addr:full":"155 S Charles Richard Beall Blvd Debary FL 32713",
    "addr:housenumber":"155",
    "addr:postcode":"32713",
    "addr:street":"S Charles Richard Beall Blvd",
    "iso:country":"US",
    "sg:address":"155 S Charles Richard Beall Blvd",
    "sg:city":"Debary",
    "sg:classifiers":[
        {
            "category":"Education",
            "subcategory":"Special Training",
            "type":"Public Place"
        }
    ],
    "sg:phone":"+1 386 668 5553",
    "sg:postcode":"32713",
    "sg:province":"FL",
    "sg:tags":[
        "school",
        "instruction",
        "art"
    ],
    "wof:name":"Debary Art League",
    "wof:placetype":"venue"
},
  "geometry": {"coordinates":[-81.311188,28.877593],"type":"Point"}
}