{
  "type": "Feature",
  "properties": {
    "iso:country":"US",
    "sg:address":"3501 S Florida Ave",
    "sg:city":"Lakeland",
    "sg:classifiers":[
        {
            "category":"Health Services",
            "subcategory":"Optometrist",
            "type":"Services"
        }
    ],
    "sg:phone":"+1 863 648 1973",
    "sg:postcode":"33803",
    "sg:province":"FL",
    "wof:name":"Olesen Clayton Od",
    "wof:placetype":"venue"
},
  "geometry": {"coordinates":[-81.957077,28.0007],"type":"Point"}
}