{
  "type": "Feature",
  "properties": {
    "addr:full":"320 N Stark Ave Orange City FL 32763",
    "addr:housenumber":"320",
    "addr:postcode":"32763",
    "addr:street":"N Stark Ave",
    "iso:country":"US",
    "sg:address":"320 N Stark Ave",
    "sg:city":"Orange City",
    "sg:classifiers":[
        {
            "category":"Building & Trades",
            "subcategory":"Construction",
            "type":"Services"
        }
    ],
    "sg:phone":"+1 386 775 3423",
    "sg:postcode":"32763",
    "sg:province":"FL",
    "sg:tags":[
        "contractor"
    ],
    "wof:name":"Wizard of Tile & Stone Inc",
    "wof:placetype":"venue"
},
  "geometry": {"coordinates":[-81.311381,28.951459],"type":"Point"}
}