{
  "type": "Feature",
  "properties": {
    "iso:country":"US",
    "sg:address":"1468 NW 126th Ave",
    "sg:city":"Fort Lauderdale",
    "sg:classifiers":[
        {
            "category":"Travel",
            "subcategory":"Travel Agent",
            "type":"Entertainment"
        }
    ],
    "sg:phone":"+1 954 845 0090",
    "sg:postcode":"33323",
    "sg:province":"FL",
    "sg:tags":[
        "agency"
    ],
    "wof:name":"Nancy Polansky Inc",
    "wof:placetype":"venue"
},
  "geometry": {"coordinates":[-80.318083,26.140962],"type":"Point"}
}