{
  "type": "Feature",
  "properties": {
    "addr:full":"914 Cochran Dr Lake Worth FL 33461",
    "addr:housenumber":"914",
    "addr:postcode":"33461",
    "addr:street":"Cochran Dr",
    "iso:country":"US",
    "sg:address":"914 Cochran Dr",
    "sg:city":"Lake Worth",
    "sg:classifiers":[
        {
            "category":"Building & Trades",
            "subcategory":"Construction",
            "type":"Services"
        }
    ],
    "sg:phone":"+1 561 582 5310",
    "sg:postcode":"33461",
    "sg:province":"FL",
    "sg:tags":[
        "roofing",
        "contractor"
    ],
    "wof:name":"Beaver Roofing Inc",
    "wof:placetype":"venue"
},
  "geometry": {"coordinates":[-80.07008,26.604319],"type":"Point"}
}