{
  "type": "Feature",
  "properties": {
    "addr:full":"1639 E Cape Coral Pkwy Cape Coral FL 33904",
    "addr:housenumber":"1639",
    "addr:postcode":"33904",
    "addr:street":"E Cape Coral Pkwy",
    "iso:country":"US",
    "sg:address":"1639 E Cape Coral Pkwy",
    "sg:city":"Cape Coral",
    "sg:classifiers":[
        {
            "category":"Wholesale",
            "subcategory":"Home Furnishings",
            "type":"Manufacturing & Wholesale Goods"
        }
    ],
    "sg:phone":"+1 239 541 9989",
    "sg:postcode":"33904",
    "sg:province":"FL",
    "wof:name":"Vertical Blinds Plus Corp",
    "wof:placetype":"venue"
},
  "geometry": {"coordinates":[-81.94251,26.562585],"type":"Point"}
}