{
  "type": "Feature",
  "properties": {
    "iso:country":"US",
    "sg:address":"940 Alameda Way",
    "sg:city":"Sarasota",
    "sg:classifiers":[
        {
            "category":"Banks & Credit Unions",
            "subcategory":"Financial Services",
            "type":"Services"
        }
    ],
    "sg:phone":"+1 941 954 1113",
    "sg:postcode":"34234",
    "sg:province":"FL",
    "sg:tags":[
        "investor"
    ],
    "wof:name":"Saah Investments Inc",
    "wof:placetype":"venue"
},
  "geometry": {"coordinates":[-82.551483,27.353829],"type":"Point"}
}