{
  "type": "Feature",
  "properties": {
    "iso:country":"US",
    "sg:address":"14720 113th Ave N",
    "sg:city":"Largo",
    "sg:classifiers":[
        {
            "category":"Real Estate",
            "subcategory":"Developer",
            "type":"Services"
        }
    ],
    "sg:phone":"+1 727 596 7448",
    "sg:postcode":"33774",
    "sg:province":"FL",
    "sg:tags":[
        "mobile",
        "home"
    ],
    "wof:name":"Gulfview Mobile Home Park",
    "wof:placetype":"venue"
},
  "geometry": {"coordinates":[-82.843232,27.875682],"type":"Point"}
}