{
  "type": "Feature",
  "properties": {
    "iso:country":"US",
    "sg:address":"20206 NE 45th Pl",
    "sg:city":"Hawthorne",
    "sg:classifiers":[
        {
            "category":"Building & Trades",
            "subcategory":"Construction",
            "type":"Services"
        }
    ],
    "sg:phone":"+1 352 475 5628",
    "sg:postcode":"32640",
    "sg:province":"FL",
    "sg:tags":[
        "contractor",
        "grading"
    ],
    "wof:name":"Neals Land Clearing & Excavati",
    "wof:placetype":"venue"
},
  "geometry": {"coordinates":[-82.108316,29.695727],"type":"Point"}
}