{
  "type": "Feature",
  "properties": {
    "iso:country":"US",
    "sg:address":"101 High Vista Dr",
    "sg:city":"Davenport",
    "sg:classifiers":[
        {
            "category":"Professional",
            "type":"Services"
        }
    ],
    "sg:phone":"+1 863 424 9611",
    "sg:postcode":"33837",
    "sg:province":"FL",
    "sg:tags":[
        "establishment"
    ],
    "wof:name":"Ridgewood Lakes Activity",
    "wof:placetype":"venue"
},
  "geometry": {"coordinates":[-81.615104,28.177501],"type":"Point"}
}