{
  "type": "Feature",
  "properties": {
    "iso:country":"US",
    "sg:address":"14087 SW 48th Ln",
    "sg:city":"Miami",
    "sg:classifiers":[
        {
            "category":"Shopping",
            "subcategory":"Gifts & Souvenirs",
            "type":"Retail Goods"
        }
    ],
    "sg:phone":"+1 305 221 9442",
    "sg:postcode":"33175",
    "sg:province":"FL",
    "wof:name":"Miami Sino Expo Inc",
    "wof:placetype":"venue"
},
  "geometry": {"coordinates":[-80.42218699999999,25.720708],"type":"Point"}
}