{
  "type": "Feature",
  "properties": {
    "addr:full":"417 Brandon Town Center Mall Brandon FL 33511",
    "addr:housenumber":"417",
    "addr:postcode":"33511",
    "addr:street":"Brandon Town;Mall",
    "iso:country":"US",
    "sg:address":"417 Brandon Town Center Mall",
    "sg:city":"Brandon",
    "sg:classifiers":[
        {
            "category":"Shopping",
            "type":"Retail Goods"
        }
    ],
    "sg:phone":"+1 813 263 4499",
    "sg:postcode":"33511",
    "sg:province":"FL",
    "sg:tags":[
        "cosmetic",
        "perfume"
    ],
    "wof:name":"H & H Svc Inc",
    "wof:placetype":"venue"
},
  "geometry": {"coordinates":[-82.325452,27.931364],"type":"Point"}
}