{
  "type": "Feature",
  "properties": {
    "addr:full":"2332 17th St Sarasota FL 34234",
    "addr:housenumber":"2332",
    "addr:postcode":"34234",
    "addr:street":"17Th St",
    "iso:country":"US",
    "sg:address":"2332 17th St",
    "sg:city":"Sarasota",
    "sg:classifiers":[
        {
            "category":"Health Services",
            "subcategory":"Medical Lab",
            "type":"Services"
        }
    ],
    "sg:phone":"+1 941 331 4370",
    "sg:postcode":"34234",
    "sg:province":"FL",
    "sg:tags":[
        "laboratory",
        "dental"
    ],
    "wof:name":"Abba Dental Inc",
    "wof:placetype":"venue"
},
  "geometry": {"coordinates":[-82.518308,27.352202],"type":"Point"}
}