{
  "type": "Feature",
  "properties": {
    "iso:country":"US",
    "sg:address":"2720 Mars Dr",
    "sg:city":"Titusville",
    "sg:classifiers":[
        {
            "category":"Professional",
            "subcategory":"Management & Consulting",
            "type":"Services"
        },
        {
            "category":"Professional",
            "subcategory":"Advertising",
            "type":"Services"
        }
    ],
    "sg:phone":"+1 321 269 2429",
    "sg:postcode":"32796",
    "sg:province":"FL",
    "sg:tags":[
        "marketing",
        "program",
        "consultant"
    ],
    "wof:name":"Covin Marketing",
    "wof:placetype":"venue"
},
  "geometry": {"coordinates":[-80.836162,28.628251],"type":"Point"}
}