{
  "type": "Feature",
  "properties": {
    "addr:full":"2612 NW 10th St Ocala FL 34475",
    "addr:housenumber":"2612",
    "addr:postcode":"34475",
    "addr:street":"Nw 10Th St",
    "iso:country":"US",
    "sg:address":"2612 NW 10th St",
    "sg:city":"Ocala",
    "sg:classifiers":[
        {
            "category":"Autos & Motor Vehicles",
            "subcategory":"Auto Supplies",
            "type":"Retail Goods"
        }
    ],
    "sg:phone":"+1 352 368 1992",
    "sg:postcode":"34475",
    "sg:province":"FL",
    "sg:tags":[
        "automobile",
        "part"
    ],
    "sg:website":"http://www.easternimports.com",
    "wof:name":"Eastern Imports, Inc.",
    "wof:placetype":"venue"
},
  "geometry": {"coordinates":[-82.167389,29.196979],"type":"Point"}
}