{
  "type": "Feature",
  "properties": {
    "addr:full":"253 Barefoot Beach Blvd Bonita Springs FL 34134",
    "addr:housenumber":"253",
    "addr:postcode":"34134",
    "addr:street":"Barefoot Beach Blvd",
    "iso:country":"US",
    "sg:address":"253 Barefoot Beach Blvd",
    "sg:city":"Bonita Springs",
    "sg:classifiers":[
        {
            "category":"Local Transit",
            "type":"Transportation"
        }
    ],
    "sg:phone":"+1 239 495 3517",
    "sg:postcode":"34134",
    "sg:province":"FL",
    "sg:tags":[
        "handicapped"
    ],
    "wof:name":"Going Your Way",
    "wof:placetype":"venue"
},
  "geometry": {"coordinates":[-81.840087,26.319537],"type":"Point"}
}