{
  "type": "Feature",
  "properties": {
    "addr:full":"860 Washington Ave Miami Beach FL 33139",
    "addr:housenumber":"860",
    "addr:postcode":"33139",
    "addr:street":"Washington Ave",
    "iso:country":"US",
    "sg:address":"860 Washington Ave",
    "sg:city":"Miami Beach",
    "sg:classifiers":[
        {
            "category":"Restaurant",
            "type":"Food & Drink"
        }
    ],
    "sg:phone":"+1 305 695 1802",
    "sg:postcode":"33139",
    "sg:province":"FL",
    "sg:tags":[
        "eating"
    ],
    "wof:name":"Tokyo Bowl Japanese Restaurant",
    "wof:placetype":"venue"
},
  "geometry": {"coordinates":[-80.133286,25.778791],"type":"Point"}
}