{
  "type": "Feature",
  "properties": {
    "iso:country":"US",
    "sg:address":"2310 W Bay Dr",
    "sg:city":"Largo",
    "sg:classifiers":[
        {
            "category":"Health Services",
            "subcategory":"Health Practitioner",
            "type":"Services"
        }
    ],
    "sg:phone":"+1 727 518 8115",
    "sg:postcode":"33770",
    "sg:province":"FL",
    "wof:name":"Foundation Physical Therapy",
    "wof:placetype":"venue"
},
  "geometry": {"coordinates":[-82.812659,27.916835],"type":"Point"}
}