{
  "type": "Feature",
  "properties": {
    "iso:country":"US",
    "sg:address":"5876 Red Bug Lake Rd",
    "sg:city":"Winter Springs",
    "sg:classifiers":[
        {
            "category":"Personal",
            "subcategory":"Beauty Salon",
            "type":"Services"
        }
    ],
    "sg:phone":"+1 407 696 0096",
    "sg:postcode":"32708",
    "sg:province":"FL",
    "sg:tags":[
        "shop"
    ],
    "wof:name":"Friends Hair Design Inc",
    "wof:placetype":"venue"
},
  "geometry": {"coordinates":[-81.26468300000001,28.647675],"type":"Point"}
}