{
  "type": "Feature",
  "properties": {
    "iso:country":"US",
    "sg:address":"5420 Touchstone Dr",
    "sg:city":"Orlando",
    "sg:classifiers":[
        {
            "category":"Shopping",
            "subcategory":"Luggage & Leather Goods",
            "type":"Retail Goods"
        }
    ],
    "sg:phone":"+1 407 352 6201",
    "sg:postcode":"32819",
    "sg:province":"FL",
    "wof:name":"Gifts & Luggage Outlet",
    "wof:placetype":"venue"
},
  "geometry": {"coordinates":[-81.451195,28.466612],"type":"Point"}
}