{
  "type": "Feature",
  "properties": {
    "iso:country":"US",
    "sg:address":"1836 W 27th St",
    "sg:city":"Jacksonville",
    "sg:classifiers":[
        {
            "category":"Personal",
            "subcategory":"Beauty Salon",
            "type":"Services"
        }
    ],
    "sg:phone":"+1 904 768 0586",
    "sg:postcode":"32209",
    "sg:province":"FL",
    "wof:name":"Angela Hair Salon",
    "wof:placetype":"venue"
},
  "geometry": {"coordinates":[-81.687138,30.360716],"type":"Point"}
}