{
  "type": "Feature",
  "properties": {
    "iso:country":"US",
    "sg:address":"3620 Shinnecock Ln",
    "sg:city":"Green Cove Springs",
    "sg:classifiers":[
        {
            "category":"Real Estate",
            "subcategory":"Developer",
            "type":"Services"
        }
    ],
    "sg:phone":"+1 904 284 8598",
    "sg:postcode":"32043",
    "sg:province":"FL",
    "wof:name":"Callahan Investment Services",
    "wof:placetype":"venue"
},
  "geometry": {"coordinates":[-81.71437400000001,30.006395],"type":"Point"}
}