{
  "type": "Feature",
  "properties": {
    "addr:full":"2400 C H Arnold Rd St Augustine FL 32092",
    "addr:housenumber":"2400 c h",
    "addr:postcode":"32092",
    "addr:street":"Arnold Rd St",
    "iso:country":"US",
    "sg:address":"2400 C H Arnold Rd",
    "sg:city":"St Augustine",
    "sg:classifiers":[
        {
            "category":"Home & Garden",
            "subcategory":"Building Materials",
            "type":"Retail Goods"
        }
    ],
    "sg:phone":"+1 904 285 1494",
    "sg:postcode":"32092",
    "sg:province":"FL",
    "sg:tags":[
        "glass",
        "leaded"
    ],
    "wof:name":"Alemanda Artworks",
    "wof:placetype":"venue"
},
  "geometry": {"coordinates":[-81.533925,29.922321],"type":"Point"}
}