{
  "type": "Feature",
  "properties": {
    "addr:full":"3529 S Tuttle Ave Sarasota FL 34239",
    "addr:housenumber":"3529",
    "addr:postcode":"34239",
    "addr:street":"S Tuttle Ave",
    "iso:country":"US",
    "sg:address":"3529 S Tuttle Ave",
    "sg:city":"Sarasota",
    "sg:classifiers":[
        {
            "category":"Health Services",
            "subcategory":"Chiropractor",
            "type":"Services"
        }
    ],
    "sg:phone":"+1 941 924 7228",
    "sg:postcode":"34239",
    "sg:province":"FL",
    "wof:name":"Family Chiropractic",
    "wof:placetype":"venue"
},
  "geometry": {"coordinates":[-82.514087,27.302088],"type":"Point"}
}