{
  "type": "Feature",
  "properties": {
    "iso:country":"US",
    "sg:address":"205 SW 12th Ct",
    "sg:city":"Fort Lauderdale",
    "sg:classifiers":[
        {
            "category":"Professional",
            "subcategory":"Art Services",
            "type":"Services"
        }
    ],
    "sg:phone":"+1 954 467 9728",
    "sg:postcode":"33315",
    "sg:province":"FL",
    "sg:tags":[
        "photographer"
    ],
    "wof:name":"Apogee Photographic",
    "wof:placetype":"venue"
},
  "geometry": {"coordinates":[-80.14555,26.106644],"type":"Point"}
}