{
  "type": "Feature",
  "properties": {
    "addr:full":"790 Co Rd 482 N Bushnell FL 33538",
    "addr:housenumber":"790",
    "addr:postcode":"33538",
    "addr:street":"Co Rd 482 N",
    "iso:country":"US",
    "sg:address":"790 Co Rd 482 N",
    "sg:city":"Bushnell",
    "sg:classifiers":[
        {
            "category":"Professional",
            "type":"Services"
        }
    ],
    "sg:phone":"+1 352 568 1891",
    "sg:postcode":"33538",
    "sg:province":"FL",
    "sg:tags":[
        "establishment"
    ],
    "wof:name":"Waldbridge Aldinder",
    "wof:placetype":"venue"
},
  "geometry": {"coordinates":[-82.12068499999999,28.763646],"type":"Point"}
}