{
  "type": "Feature",
  "properties": {
    "iso:country":"US",
    "sg:address":"142 N Lake Dr",
    "sg:city":"Leesburg",
    "sg:classifiers":[
        {
            "category":"Shopping",
            "subcategory":"Hobbies, Toys, & Games",
            "type":"Retail Goods"
        }
    ],
    "sg:phone":"+1 352 589 9058",
    "sg:postcode":"34788",
    "sg:province":"FL",
    "sg:tags":[
        "craft"
    ],
    "wof:name":"Carol's Crafts",
    "wof:placetype":"venue"
},
  "geometry": {"coordinates":[-81.76944899999999,28.871281],"type":"Point"}
}