{
  "type": "Feature",
  "properties": {
    "iso:country":"US",
    "sg:address":"18935 NW 10th St",
    "sg:city":"Hollywood",
    "sg:classifiers":[
        {
            "category":"Building & Trades",
            "subcategory":"Plumbing",
            "type":"Services"
        }
    ],
    "sg:phone":"+1 954 920 4900",
    "sg:postcode":"33029",
    "sg:province":"FL",
    "sg:tags":[
        "plumbing",
        "contractor"
    ],
    "wof:name":"Blue Line Plumbing Inc",
    "wof:placetype":"venue"
},
  "geometry": {"coordinates":[-80.400727,26.012509],"type":"Point"}
}