{
  "type": "Feature",
  "properties": {
    "addr:full":"1717 NW 82nd Ave Doral FL 33126",
    "addr:housenumber":"1717",
    "addr:postcode":"33126",
    "addr:street":"Nw 82Nd Ave",
    "iso:country":"US",
    "sg:address":"1717 NW 82nd Ave",
    "sg:city":"Doral",
    "sg:classifiers":[
        {
            "category":"Professional",
            "subcategory":"Business Services",
            "type":"Services"
        }
    ],
    "sg:phone":"+1 305 418 9066",
    "sg:postcode":"33126",
    "sg:province":"FL",
    "sg:tags":[
        "importer",
        "exporter",
        "export",
        "representative"
    ],
    "wof:name":"Lucero International Inc",
    "wof:placetype":"venue"
},
  "geometry": {"coordinates":[-80.32867,25.78999],"type":"Point"}
}