{
  "type": "Feature",
  "properties": {
    "iso:country":"US",
    "sg:address":"5309 Marlene Ave",
    "sg:city":"Jacksonville",
    "sg:classifiers":[
        {
            "category":"Manufacturing",
            "subcategory":"Motor Vehicles & Parts",
            "type":"Manufacturing & Wholesale Goods"
        }
    ],
    "sg:phone":"+1 904 768 5631",
    "sg:postcode":"32210",
    "sg:province":"FL",
    "sg:tags":[
        "car",
        "safety",
        "racing",
        "for",
        "mfg"
    ],
    "wof:name":"T A K Enterprises Inc",
    "wof:placetype":"venue"
},
  "geometry": {"coordinates":[-81.73858199999999,30.284705],"type":"Point"}
}