{
  "type": "Feature",
  "properties": {
    "addr:full":"1510 9th St W Bradenton FL 34205",
    "addr:housenumber":"1510",
    "addr:postcode":"34205",
    "addr:street":"9Th St W",
    "iso:country":"US",
    "sg:address":"1510 9th St W",
    "sg:city":"Bradenton",
    "sg:classifiers":[
        {
            "category":"Autos & Motor Vehicles",
            "subcategory":"Auto Supplies",
            "type":"Retail Goods"
        },
        {
            "category":"Manufacturing",
            "subcategory":"Motor Vehicles & Parts",
            "type":"Manufacturing & Wholesale Goods"
        },
        {
            "category":"Wholesale",
            "subcategory":"Auto Parts",
            "type":"Manufacturing & Wholesale Goods"
        },
        {
            "category":"Retail",
            "subcategory":"Auto Repair",
            "type":"Services"
        }
    ],
    "sg:phone":"+1 941 748 3912",
    "sg:postcode":"34205",
    "sg:province":"FL",
    "sg:tags":[
        "body",
        "shop",
        "automobile",
        "supply-wholesale",
        "equipment",
        "service-equipment",
        "painting",
        "repairing",
        "manufacturer"
    ],
    "wof:name":"Final Finish Automotive Paint & Supplies Inc",
    "wof:placetype":"venue"
},
  "geometry": {"coordinates":[-82.571215,27.485946],"type":"Point"}
}