{
  "type": "Feature",
  "properties": {
    "addr:full":"5400 SW College Rd Ste 30 Ocala FL 34474",
    "addr:housenumber":"5400;30",
    "addr:postcode":"34474",
    "addr:street":"Sw College Rd Ste",
    "iso:country":"US",
    "sg:address":"5400 SW College Rd Ste 30",
    "sg:city":"Ocala",
    "sg:classifiers":[
        {
            "category":"Retail",
            "subcategory":"Laundry & Dry Cleaning",
            "type":"Services"
        }
    ],
    "sg:phone":"+1 352 861 1355",
    "sg:postcode":"34474",
    "sg:province":"FL",
    "sg:tags":[
        "cleaner",
        "commercial"
    ],
    "wof:name":"200 One Hour Cleaners",
    "wof:placetype":"venue"
},
  "geometry": {"coordinates":[-82.20408500000001,29.131325],"type":"Point"}
}