{
  "type": "Feature",
  "properties": {
    "iso:country":"US",
    "sg:address":"3461 E Colonial Dr",
    "sg:city":"Orlando",
    "sg:classifiers":[
        {
            "category":"Shopping",
            "subcategory":"Optical Goods",
            "type":"Retail Goods"
        }
    ],
    "sg:phone":"+1 407 898 8040",
    "sg:postcode":"32803",
    "sg:province":"FL",
    "wof:name":"Pearle Vision",
    "wof:placetype":"venue"
},
  "geometry": {"coordinates":[-81.341976,28.553437],"type":"Point"}
}