{
  "type": "Feature",
  "properties": {
    "iso:country":"US",
    "sg:address":"850 N Lake Ave",
    "sg:city":"Lakeland",
    "sg:classifiers":[
        {
            "category":"Social Services",
            "subcategory":"Child Care",
            "type":"Services"
        }
    ],
    "sg:phone":"+1 863 603 0830",
    "sg:postcode":"33801",
    "sg:province":"FL",
    "wof:name":"King & Queen Learning Ctr",
    "wof:placetype":"venue"
},
  "geometry": {"coordinates":[-81.949141,28.052685],"type":"Point"}
}