{
  "type": "Feature",
  "properties": {
    "addr:full":"130 SE Ave E Belle Glade FL 33430",
    "addr:housenumber":"130",
    "addr:postcode":"33430",
    "addr:street":"Se Ave E Belle Glade",
    "iso:country":"US",
    "sg:address":"130 SE Ave E",
    "sg:city":"Belle Glade",
    "sg:classifiers":[
        {
            "category":"Organizations",
            "subcategory":"Religious Organization",
            "type":"Services"
        }
    ],
    "sg:phone":"+1 561 993 9090",
    "sg:postcode":"33430",
    "sg:province":"FL",
    "sg:tags":[
        "church"
    ],
    "wof:name":"Morija SDA",
    "wof:placetype":"venue"
},
  "geometry": {"coordinates":[-80.666496,26.682164],"type":"Point"}
}