{
  "type": "Feature",
  "properties": {
    "iso:country":"US",
    "sg:address":"4040 Brookfield Ct",
    "sg:city":"Jacksonville",
    "sg:classifiers":[
        {
            "category":"Professional",
            "subcategory":"Computer Services",
            "type":"Services"
        }
    ],
    "sg:phone":"+1 904 880 0592",
    "sg:postcode":"32257",
    "sg:province":"FL",
    "sg:tags":[
        "design",
        "system"
    ],
    "wof:name":"Jennifer Fone Web Design",
    "wof:placetype":"venue"
},
  "geometry": {"coordinates":[-81.610783,30.197063],"type":"Point"}
}