{
  "type": "Feature",
  "properties": {
    "iso:country":"US",
    "sg:address":"13691 Metro Pkwy",
    "sg:city":"Fort Myers",
    "sg:classifiers":[
        {
            "category":"Health Services",
            "subcategory":"Doctor",
            "type":"Services"
        }
    ],
    "sg:phone":"+1 239 768 5544",
    "sg:postcode":"33912",
    "sg:province":"FL",
    "sg:tags":[
        "physician",
        "medical",
        "surgeon"
    ],
    "wof:name":"Physicians Med",
    "wof:placetype":"venue"
},
  "geometry": {"coordinates":[-81.852334,26.545636],"type":"Point"}
}