{
  "type": "Feature",
  "properties": {
    "iso:country":"US",
    "sg:address":"130 5th St",
    "sg:city":"Naples",
    "sg:classifiers":[
        {
            "category":"Restaurant",
            "type":"Food & Drink"
        }
    ],
    "sg:phone":"+1 239 774 2539",
    "sg:postcode":"34113",
    "sg:province":"FL",
    "sg:tags":[
        "eating"
    ],
    "wof:name":"Migniu Corp",
    "wof:placetype":"venue"
},
  "geometry": {"coordinates":[-81.726922,26.075791],"type":"Point"}
}