{
  "type": "Feature",
  "properties": {
    "iso:country":"US",
    "sg:address":"5418 Firenze Dr",
    "sg:city":"Boynton Beach",
    "sg:classifiers":[
        {
            "category":"Shopping",
            "subcategory":"Computers & Home Electronics",
            "type":"Retail Goods"
        }
    ],
    "sg:phone":"+1 561 736 0170",
    "sg:postcode":"33437",
    "sg:province":"FL",
    "sg:tags":[
        "installs",
        "intercom",
        "s",
        "radio",
        "vacuum"
    ],
    "wof:name":"Residential Systmes Srvs Inc",
    "wof:placetype":"venue"
},
  "geometry": {"coordinates":[-80.12896000000001,26.532182],"type":"Point"}
}