{
  "type": "Feature",
  "properties": {
    "iso:country":"US",
    "sg:address":"144 Miracle Strip Pkwy",
    "sg:city":"Fort Walton Bch",
    "sg:classifiers":[
        {
            "category":"Shopping",
            "subcategory":"Jewelry",
            "type":"Retail Goods"
        }
    ],
    "sg:phone":"+1 850 243 4405",
    "sg:postcode":"32548",
    "sg:province":"FL",
    "sg:tags":[
        "jeweler"
    ],
    "wof:name":"Merlin's Inc Custom Jewelry &",
    "wof:placetype":"venue"
},
  "geometry": {"coordinates":[-86.608311,30.403739],"type":"Point"}
}