{
  "type": "Feature",
  "properties": {
    "iso:country":"US",
    "sg:address":"7757 Griswold St",
    "sg:city":"Lantana",
    "sg:classifiers":[
        {
            "category":"Building & Trades",
            "subcategory":"Cleaning & Sanitation",
            "type":"Services"
        }
    ],
    "sg:phone":"+1 561 689 3007",
    "sg:postcode":"33462",
    "sg:province":"FL",
    "sg:tags":[
        "repairing",
        "window",
        "shades"
    ],
    "wof:name":"H R Window Treatments",
    "wof:placetype":"venue"
},
  "geometry": {"coordinates":[-80.057975,26.558242],"type":"Point"}
}