{
  "type": "Feature",
  "properties": {
    "addr:full":"5040 Keystone Dr Gulf Breeze FL 32563",
    "addr:housenumber":"5040",
    "addr:postcode":"32563",
    "addr:street":"Keystone Dr",
    "iso:country":"US",
    "sg:address":"5040 Keystone Dr",
    "sg:city":"Gulf Breeze",
    "sg:classifiers":[
        {
            "category":"Building & Trades",
            "subcategory":"Plumbing",
            "type":"Services"
        }
    ],
    "sg:phone":"+1 850 932 8474",
    "sg:postcode":"32563",
    "sg:province":"FL",
    "sg:tags":[
        "conditioning",
        "air",
        "system",
        "contractor"
    ],
    "wof:name":"Breeze Heating & Air Cond",
    "wof:placetype":"venue"
},
  "geometry": {"coordinates":[-87.006246,30.404806],"type":"Point"}
}