{
  "type": "Feature",
  "properties": {
    "iso:country":"US",
    "sg:address":"2166 S Orange Blossom Trl",
    "sg:city":"Apopka",
    "sg:classifiers":[
        {
            "category":"Building & Trades",
            "subcategory":"Construction",
            "type":"Services"
        }
    ],
    "sg:phone":"+1 407 947 5057",
    "sg:postcode":"32703",
    "sg:province":"FL",
    "sg:tags":[
        "excavation",
        "contractor"
    ],
    "wof:name":"Brothers Excavating",
    "wof:placetype":"venue"
},
  "geometry": {"coordinates":[-81.46048999999999,28.645176],"type":"Point"}
}