{
  "type": "Feature",
  "properties": {
    "iso:country":"US",
    "sg:address":"15053 S Dixie Hwy",
    "sg:city":"Miami",
    "sg:classifiers":[
        {
            "category":"Health Services",
            "subcategory":"Doctor",
            "type":"Services"
        }
    ],
    "sg:phone":"+1 305 252 4923",
    "sg:postcode":"33176",
    "sg:province":"FL",
    "sg:tags":[
        "practice",
        "family"
    ],
    "wof:name":"Bennett Shaughn C DO",
    "wof:placetype":"venue"
},
  "geometry": {"coordinates":[-80.340284,25.629966],"type":"Point"}
}