{
  "type": "Feature",
  "properties": {
    "iso:country":"US",
    "sg:address":"494 Maple Ave",
    "sg:city":"Fort Pierce",
    "sg:classifiers":[
        {
            "category":"Professional",
            "subcategory":"Accounting & Tax Preparation",
            "type":"Services"
        }
    ],
    "sg:phone":"+1 772 466 6454",
    "sg:postcode":"34982",
    "sg:province":"FL",
    "wof:name":"David Kinser Accounting Inc",
    "wof:placetype":"venue"
},
  "geometry": {"coordinates":[-80.32699599999999,27.420258],"type":"Point"}
}