{
  "type": "Feature",
  "properties": {
    "addr:full":"6550 NW 48th Ter Ocala FL 34482",
    "addr:housenumber":"6550",
    "addr:postcode":"34482",
    "addr:street":"Nw 48Th Ter",
    "iso:country":"US",
    "sg:address":"6550 NW 48th Ter",
    "sg:city":"Ocala",
    "sg:classifiers":[
        {
            "category":"Freight",
            "type":"Transportation"
        }
    ],
    "sg:phone":"+1 352 620 0223",
    "sg:postcode":"34482",
    "sg:province":"FL",
    "sg:tags":[
        "operator",
        "local",
        "trucking"
    ],
    "wof:name":"Greenmaster Lawncare & Hauling",
    "wof:placetype":"venue"
},
  "geometry": {"coordinates":[-82.20118100000001,29.255206],"type":"Point"}
}