{
  "type": "Feature",
  "properties": {
    "iso:country":"US",
    "sg:address":"4843 Donnybrook Ave",
    "sg:city":"Jacksonville",
    "sg:classifiers":[
        {
            "category":"Building & Trades",
            "subcategory":"Construction",
            "type":"Services"
        }
    ],
    "sg:phone":"+1 904 764 3728",
    "sg:postcode":"32208",
    "sg:province":"FL",
    "sg:tags":[
        "residential"
    ],
    "wof:name":"Mercer Mary Bush",
    "wof:placetype":"venue"
},
  "geometry": {"coordinates":[-81.726556,30.403139],"type":"Point"}
}