{
  "type": "Feature",
  "properties": {
    "addr:full":"16645 Fishhawk Blvd Lithia FL 33547",
    "addr:postcode":"16645;33547",
    "addr:street":"Fishhawk Blvd",
    "iso:country":"US",
    "sg:address":"16645 Fishhawk Blvd",
    "sg:city":"Lithia",
    "sg:classifiers":[
        {
            "category":"Banks & Credit Unions",
            "subcategory":"Bank",
            "type":"Services"
        },
        {
            "category":"Banks & Credit Unions",
            "subcategory":"Financial Services",
            "type":"Services"
        }
    ],
    "sg:phone":"+1 800 734 4667",
    "sg:postcode":"33547",
    "sg:province":"FL",
    "sg:tags":[
        "saving",
        "loan",
        "commercial"
    ],
    "sg:website":"http://www.regionsbank.com",
    "wof:name":"Regions Bank",
    "wof:placetype":"venue"
},
  "geometry": {"coordinates":[-82.203335,27.860316],"type":"Point"}
}