{
  "type": "Feature",
  "properties": {
    "iso:country":"US",
    "sg:address":"2624 Lincoln Ave",
    "sg:city":"Miami",
    "sg:classifiers":[
        {
            "category":"Wholesale",
            "subcategory":"Stationery",
            "type":"Manufacturing & Wholesale Goods"
        }
    ],
    "sg:phone":"+1 305 854 7220",
    "sg:postcode":"33133",
    "sg:province":"FL",
    "sg:tags":[
        "card"
    ],
    "sg:website":"www.byobliss.com",
    "wof:name":"Byo Bliss",
    "wof:placetype":"venue"
},
  "geometry": {"coordinates":[-80.23659000000001,25.73312],"type":"Point"}
}