{
  "type": "Feature",
  "properties": {
    "iso:country":"US",
    "sg:address":"13146 150th Ct N",
    "sg:city":"Jupiter",
    "sg:classifiers":[
        {
            "category":"Building & Trades",
            "subcategory":"Construction",
            "type":"Services"
        }
    ],
    "sg:phone":"+1 561 748 9823",
    "sg:postcode":"33478",
    "sg:province":"FL",
    "sg:tags":[
        "contractor"
    ],
    "wof:name":"Accurate Drywall & Home",
    "wof:placetype":"venue"
},
  "geometry": {"coordinates":[-80.24253,26.899142],"type":"Point"}
}