{
  "type": "Feature",
  "properties": {
    "iso:country":"US",
    "sg:address":"10035 Collins Hole Rd",
    "sg:city":"Tallahassee",
    "sg:classifiers":[
        {
            "category":"Place Of Worship",
            "type":"Public Place"
        }
    ],
    "sg:phone":"+1 850 894 8856",
    "sg:postcode":"32312",
    "sg:province":"FL",
    "sg:tags":[
        "church"
    ],
    "wof:name":"Amber Grace & Associates, Inc.",
    "wof:placetype":"venue"
},
  "geometry": {"coordinates":[-84.26656800000001,30.613905],"type":"Point"}
}