{
  "type": "Feature",
  "properties": {
    "iso:country":"US",
    "sg:address":"32046 Pike St",
    "sg:city":"Tavares",
    "sg:classifiers":[
        {
            "category":"Building & Trades",
            "subcategory":"Construction",
            "type":"Services"
        }
    ],
    "sg:phone":"+1 352 455 0694",
    "sg:postcode":"32778",
    "sg:province":"FL",
    "sg:tags":[
        "repair",
        "handyman",
        "maintenance",
        "home"
    ],
    "sg:website":"http://www.platinumtrashoutservice.com",
    "wof:name":"Platinum Trashout Service",
    "wof:placetype":"venue"
},
  "geometry": {"coordinates":[-81.77126,28.816577],"type":"Point"}
}