{
  "type": "Feature",
  "properties": {
    "iso:country":"US",
    "sg:address":"4759 NW 103rd Ave",
    "sg:city":"Sunrise",
    "sg:classifiers":[
        {
            "category":"Building & Trades",
            "subcategory":"Electrical",
            "type":"Services"
        }
    ],
    "sg:phone":"+1 954 578 8688",
    "sg:postcode":"33351",
    "sg:province":"FL",
    "sg:tags":[
        "installation"
    ],
    "wof:name":"Y2k Installation",
    "wof:placetype":"venue"
},
  "geometry": {"coordinates":[-80.287492,26.185153],"type":"Point"}
}