{
  "type": "Feature",
  "properties": {
    "iso:country":"US",
    "sg:address":"2459 E Commercial Blvd",
    "sg:city":"Fort Lauderdale",
    "sg:classifiers":[
        {
            "category":"Health Services",
            "subcategory":"Doctor",
            "type":"Services"
        }
    ],
    "sg:phone":"+1 954 776 0820",
    "sg:postcode":"33308",
    "sg:province":"FL",
    "sg:tags":[
        "cardiologist"
    ],
    "wof:name":"Cariovascular & Thoracic Surge",
    "wof:placetype":"venue"
},
  "geometry": {"coordinates":[-80.112032,26.189668],"type":"Point"}
}