{
  "type": "Feature",
  "properties": {
    "addr:full":"1422 S Wiggins Rd Plant City FL 33566",
    "addr:housenumber":"1422",
    "addr:postcode":"33566",
    "addr:street":"S Wiggins Rd",
    "iso:country":"US",
    "sg:address":"1422 S Wiggins Rd",
    "sg:city":"Plant City",
    "sg:classifiers":[
        {
            "category":"Building & Trades",
            "subcategory":"Landscaping Services",
            "type":"Services"
        }
    ],
    "sg:phone":"+1 813 659 3883",
    "sg:postcode":"33566",
    "sg:province":"FL",
    "sg:tags":[
        "lawn",
        "maintenance",
        "grounds"
    ],
    "wof:name":"Classic Lawn & Landscape Mntnc",
    "wof:placetype":"venue"
},
  "geometry": {"coordinates":[-82.06795700000001,28.004102],"type":"Point"}
}