{
  "type": "Feature",
  "properties": {
    "addr:full":"2660 NW 3rd Ave Miami FL 33127",
    "addr:housenumber":"2660",
    "addr:postcode":"33127",
    "addr:street":"Nw 3Rd Ave",
    "iso:country":"US",
    "sg:address":"2660 NW 3rd Ave",
    "sg:city":"Miami",
    "sg:classifiers":[
        {
            "category":"Manufacturing",
            "subcategory":"Rubber & Plastics",
            "type":"Manufacturing & Wholesale Goods"
        }
    ],
    "sg:phone":"+1 305 576 3626",
    "sg:postcode":"33127",
    "sg:province":"FL",
    "sg:tags":[
        "shoe",
        "store"
    ],
    "sg:website":"www.goldbannerusa.com",
    "wof:name":"Gold Banner USA Inc",
    "wof:placetype":"venue"
},
  "geometry": {"coordinates":[-80.200996,25.802],"type":"Point"}
}