{
  "type": "Feature",
  "properties": {
    "iso:country":"US",
    "sg:address":"14230 SW 139th Ct",
    "sg:city":"Miami",
    "sg:classifiers":[
        {
            "category":"Autos & Motor Vehicles",
            "subcategory":"Auto Supplies",
            "type":"Retail Goods"
        },
        {
            "category":"Retail",
            "subcategory":"Auto Repair",
            "type":"Services"
        }
    ],
    "sg:phone":"+1 305 233 4504",
    "sg:postcode":"33186",
    "sg:province":"FL",
    "sg:tags":[
        "automobile",
        "part",
        "truck"
    ],
    "sg:website":"http://clickserve.dartsearch.net/link/click?lid=43000000313868752&ds_s_kwgid=58000000006820725&ds_e_matchtype={MatchType}&ds_e_kwdid={OrderItemId}&ds_e_adid={AdId}&ds_url_v=2",
    "wof:name":"Avi's Car Service",
    "wof:placetype":"venue"
},
  "geometry": {"coordinates":[-80.419937,25.63362],"type":"Point"}
}