{
  "type": "Feature",
  "properties": {
    "addr:full":"6421 Baylor Ave Keystone Heights FL 32656",
    "addr:housenumber":"6421",
    "addr:postcode":"32656",
    "addr:street":"Baylor Ave",
    "iso:country":"US",
    "sg:address":"6421 Baylor Ave",
    "sg:city":"Keystone Heights",
    "sg:classifiers":[
        {
            "category":"Building & Trades",
            "subcategory":"Construction",
            "type":"Services"
        }
    ],
    "sg:phone":"+1 352 473 2592",
    "sg:postcode":"32656",
    "sg:province":"FL",
    "sg:tags":[
        "hanging",
        "contractor"
    ],
    "wof:name":"Inc",
    "wof:placetype":"venue"
},
  "geometry": {"coordinates":[-82.020004,29.782821],"type":"Point"}
}