{
  "type": "Feature",
  "properties": {
    "iso:country":"US",
    "sg:address":"2126 Pierce St",
    "sg:city":"Hollywood",
    "sg:classifiers":[
        {
            "category":"Manufacturing",
            "subcategory":"Textiles",
            "type":"Manufacturing & Wholesale Goods"
        }
    ],
    "sg:phone":"+1 954 921 1861",
    "sg:postcode":"33020",
    "sg:province":"FL",
    "sg:tags":[
        "b",
        "mfg",
        "shades",
        "bedspread",
        "upholstery",
        "drapery",
        "cotton"
    ],
    "sg:website":"www.distinctiveworkroom.com",
    "wof:name":"Distinctive Creations",
    "wof:placetype":"venue"
},
  "geometry": {"coordinates":[-80.154224,26.016118],"type":"Point"}
}