{
  "type": "Feature",
  "properties": {
    "addr:full":"3452 Lake Lynda Dr Orlando FL 32817",
    "addr:housenumber":"3452",
    "addr:postcode":"32817",
    "addr:street":"Lake Lynda Dr",
    "iso:country":"US",
    "sg:address":"3452 Lake Lynda Dr",
    "sg:city":"Orlando",
    "sg:classifiers":[
        {
            "category":"Professional",
            "subcategory":"Research",
            "type":"Services"
        }
    ],
    "sg:phone":"+1 407 282 5131",
    "sg:postcode":"32817",
    "sg:province":"FL",
    "wof:name":"Gadrian Corporation",
    "wof:placetype":"venue"
},
  "geometry": {"coordinates":[-81.221609,28.59889],"type":"Point"}
}