{
  "type": "Feature",
  "properties": {
    "iso:country":"US",
    "sg:address":"371 Symphony Way",
    "sg:city":"Freeport",
    "sg:classifiers":[
        {
            "category":"Professional",
            "subcategory":"Detective & Security Services",
            "type":"Services"
        }
    ],
    "sg:phone":"+1 850 855 2400",
    "sg:postcode":"32439",
    "sg:province":"FL",
    "sg:tags":[
        "information",
        "bureau"
    ],
    "wof:name":"Harrison Home And Condo Services",
    "wof:placetype":"venue"
},
  "geometry": {"coordinates":[-86.158297,30.490453],"type":"Point"}
}