{
  "type": "Feature",
  "properties": {
    "addr:full":"3410 Stall Rd Tampa FL 33618",
    "addr:housenumber":"3410",
    "addr:postcode":"33618",
    "addr:street":"Stall Rd",
    "iso:country":"US",
    "sg:address":"3410 Stall Rd",
    "sg:city":"Tampa",
    "sg:classifiers":[
        {
            "category":"Social Services",
            "subcategory":"Job Training",
            "type":"Services"
        }
    ],
    "sg:phone":"+1 813 960 4782",
    "sg:postcode":"33618",
    "sg:province":"FL",
    "wof:name":"Edwards Rehab Sys",
    "wof:placetype":"venue"
},
  "geometry": {"coordinates":[-82.499469,28.062566],"type":"Point"}
}