{
  "type": "Feature",
  "properties": {
    "iso:country":"US",
    "sg:address":"11354 Quail Roost Dr",
    "sg:city":"Miami",
    "sg:classifiers":[
        {
            "category":"Insurance",
            "subcategory":"Insurance Agent",
            "type":"Services"
        },
        {
            "category":"Insurance",
            "subcategory":"Hazard Insurance",
            "type":"Services"
        }
    ],
    "sg:phone":"+1 305 233 6638",
    "sg:postcode":"33157",
    "sg:province":"FL",
    "sg:tags":[
        "auto",
        "recreational",
        "motorcycle",
        "vehicle",
        "marine",
        "boat"
    ],
    "wof:name":"Statewide Insurance, Inc.",
    "wof:placetype":"venue"
},
  "geometry": {"coordinates":[-80.377557,25.593433],"type":"Point"}
}