{
  "type": "Feature",
  "properties": {
    "iso:country":"US",
    "sg:address":"2960 Tampa Rd",
    "sg:city":"Palm Harbor",
    "sg:classifiers":[
        {
            "category":"Health Services",
            "subcategory":"Nursing And Care Facility",
            "type":"Services"
        }
    ],
    "sg:phone":"+1 727 781 8686",
    "sg:postcode":"34684",
    "sg:province":"FL",
    "wof:name":"Balmoral Retirement Community",
    "wof:placetype":"venue"
},
  "geometry": {"coordinates":[-82.729068,28.06727],"type":"Point"}
}