{
  "type": "Feature",
  "properties": {
    "addr:full":"547 N Volusia Ave Orange City FL 32763",
    "addr:housenumber":"547",
    "addr:postcode":"32763",
    "addr:street":"N Volusia Ave",
    "iso:country":"US",
    "sg:address":"547 N Volusia Ave",
    "sg:city":"Orange City",
    "sg:classifiers":[
        {
            "category":"Retail",
            "subcategory":"Auto Repair",
            "type":"Services"
        }
    ],
    "sg:phone":"+1 386 774 2055",
    "sg:postcode":"32763",
    "sg:province":"FL",
    "sg:tags":[
        "repairing",
        "automobile"
    ],
    "wof:name":"Tri County Septic Svc",
    "wof:placetype":"venue"
},
  "geometry": {"coordinates":[-81.29894299999999,28.953399],"type":"Point"}
}