{
  "type": "Feature",
  "properties": {
    "iso:country":"US",
    "sg:address":"160 NW Monroe Cir N",
    "sg:city":"Saint Petersburg",
    "sg:classifiers":[
        {
            "category":"Wholesale",
            "subcategory":"Metals & Minerals",
            "type":"Manufacturing & Wholesale Goods"
        }
    ],
    "sg:phone":"+1 727 527 4095",
    "sg:postcode":"33702",
    "sg:province":"FL",
    "sg:tags":[
        "steel"
    ],
    "wof:name":"Imbriani Steel Co",
    "wof:placetype":"venue"
},
  "geometry": {"coordinates":[-82.64080300000001,27.831143],"type":"Point"}
}