{
  "type": "Feature",
  "properties": {
    "iso:country":"US",
    "sg:address":"1035 Anastasia Blvd",
    "sg:city":"St Augustine",
    "sg:classifiers":[
        {
            "category":"Shopping",
            "type":"Retail Goods"
        }
    ],
    "sg:phone":"+1 904 471 6294",
    "sg:postcode":"32080",
    "sg:province":"FL",
    "sg:tags":[
        "equipment",
        "pool",
        "swimming"
    ],
    "wof:name":"Pinch-A-Penny Pool & Patio Spa",
    "wof:placetype":"venue"
},
  "geometry": {"coordinates":[-81.286762,29.880648],"type":"Point"}
}