{
  "type": "Feature",
  "properties": {
    "iso:country":"US",
    "sg:address":"3401 NW 73rd St",
    "sg:city":"Miami",
    "sg:classifiers":[
        {
            "category":"Autos & Motor Vehicles",
            "subcategory":"Auto Supplies",
            "type":"Retail Goods"
        }
    ],
    "sg:phone":"+1 305 691 1313",
    "sg:postcode":"33147",
    "sg:province":"FL",
    "sg:tags":[
        "automobile",
        "parts",
        "accessory",
        "part",
        "accessories-wholesale",
        "manufacturer"
    ],
    "wof:name":"Partsmax",
    "wof:placetype":"venue"
},
  "geometry": {"coordinates":[-80.253094,25.84011],"type":"Point"}
}