{
  "type": "Feature",
  "properties": {
    "iso:country":"US",
    "sg:address":"2885 Tamiami Trl",
    "sg:city":"Port Charlotte",
    "sg:classifiers":[
        {
            "category":"Health Services",
            "subcategory":"Doctor",
            "type":"Services"
        }
    ],
    "sg:phone":"+1 941 627 5155",
    "sg:postcode":"33952",
    "sg:province":"FL",
    "sg:tags":[
        "medical"
    ],
    "wof:name":"Issa Baroudi Dr",
    "wof:placetype":"venue"
},
  "geometry": {"coordinates":[-82.107872,26.988393],"type":"Point"}
}