{
  "type": "Feature",
  "properties": {
    "iso:country":"US",
    "sg:address":"5319 Via Maior",
    "sg:city":"Orlando",
    "sg:classifiers":[
        {
            "category":"Banks & Credit Unions",
            "subcategory":"Bank",
            "type":"Services"
        }
    ],
    "sg:phone":"+1 407 522 7374",
    "sg:postcode":"32808",
    "sg:province":"FL",
    "sg:tags":[
        "mortgage"
    ],
    "wof:name":"US Mortgage Concepts",
    "wof:placetype":"venue"
},
  "geometry": {"coordinates":[-81.454886,28.584206],"type":"Point"}
}