{
  "type": "Feature",
  "properties": {
    "iso:country":"US",
    "sg:address":"5108 15th St E",
    "sg:city":"Bradenton",
    "sg:classifiers":[
        {
            "category":"Shopping",
            "subcategory":"Department Store",
            "type":"Retail Goods"
        }
    ],
    "sg:phone":"+1 941 751 9960",
    "sg:postcode":"34203",
    "sg:province":"FL",
    "sg:tags":[
        "shop"
    ],
    "sg:website":"www.biglots.com",
    "wof:name":"Big Lots",
    "wof:placetype":"venue"
},
  "geometry": {"coordinates":[-82.546752,27.449498],"type":"Point"}
}