{
  "type": "Feature",
  "properties": {
    "iso:country":"US",
    "sg:address":"12041 SW 117th Ct",
    "sg:city":"Miami",
    "sg:classifiers":[
        {
            "category":"Building & Trades",
            "subcategory":"Construction",
            "type":"Services"
        }
    ],
    "sg:phone":"+1 305 232 3000",
    "sg:postcode":"33186",
    "sg:province":"FL",
    "sg:tags":[
        "system",
        "contractor",
        "heating",
        "air conditioning",
        "conditioning/hvac"
    ],
    "sg:website":"http://www.kendaleair.com",
    "wof:name":"Kendale Air Conditioning Inc",
    "wof:placetype":"venue"
},
  "geometry": {"coordinates":[-80.384597,25.65603],"type":"Point"}
}