{
  "type": "Feature",
  "properties": {
    "addr:full":"1959 Wisteria St Sarasota FL 34239",
    "addr:housenumber":"1959",
    "addr:postcode":"34239",
    "addr:street":"Wisteria St",
    "iso:country":"US",
    "sg:address":"1959 Wisteria St",
    "sg:city":"Sarasota",
    "sg:classifiers":[
        {
            "category":"Retail",
            "subcategory":"Repair Shop",
            "type":"Services"
        }
    ],
    "sg:phone":"+1 941 957 1837",
    "sg:postcode":"34239",
    "sg:province":"FL",
    "sg:tags":[
        "refrigeration"
    ],
    "wof:name":"Able Air & Appliance Inc",
    "wof:placetype":"venue"
},
  "geometry": {"coordinates":[-82.53257499999999,27.313175],"type":"Point"}
}