{
  "type": "Feature",
  "properties": {
    "iso:country":"US",
    "sg:address":"4911 Hidden Heights Trl",
    "sg:city":"Saint Cloud",
    "sg:classifiers":[
        {
            "category":"Farming",
            "subcategory":"Nursery",
            "type":"Manufacturing & Wholesale Goods"
        }
    ],
    "sg:phone":"+1 407 957 2650",
    "sg:postcode":"34771",
    "sg:province":"FL",
    "sg:tags":[
        "ornamental"
    ],
    "wof:name":"Kaye B Saute",
    "wof:placetype":"venue"
},
  "geometry": {"coordinates":[-81.246152,28.267932],"type":"Point"}
}