{
  "type": "Feature",
  "properties": {
    "addr:full":"3929 SW 69th Ave Gainesville FL 32608",
    "addr:housenumber":"3929",
    "addr:postcode":"32608",
    "addr:street":"Sw 69Th Ave",
    "iso:country":"US",
    "sg:address":"3929 SW 69th Ave",
    "sg:city":"Gainesville",
    "sg:classifiers":[
        {
            "category":"Science Facility",
            "type":"Public Place"
        }
    ],
    "sg:phone":"+1 352 377 2988",
    "sg:postcode":"32608",
    "sg:province":"FL",
    "sg:tags":[
        "development",
        "laboratories-research"
    ],
    "wof:name":"Rodob Drug Research Inc.",
    "wof:placetype":"venue"
},
  "geometry": {"coordinates":[-82.379052,29.589822],"type":"Point"}
}