{
  "type": "Feature",
  "properties": {
    "addr:full":"5445 W Cypress St Tampa FL 33607",
    "addr:housenumber":"5445",
    "addr:postcode":"33607",
    "addr:street":"W Cypress St",
    "iso:country":"US",
    "sg:address":"5445 W Cypress St",
    "sg:city":"Tampa",
    "sg:classifiers":[
        {
            "category":"Professional",
            "subcategory":"Computer Services",
            "type":"Services"
        }
    ],
    "sg:phone":"+1 813 639 1981",
    "sg:postcode":"33607",
    "sg:province":"FL",
    "wof:name":"Netcubed Corp",
    "wof:placetype":"venue"
},
  "geometry": {"coordinates":[-82.535978,27.952505],"type":"Point"}
}