{
  "type": "Feature",
  "properties": {
    "addr:full":"4600 Summerlin Rd Ste C5 Fort Myers FL 33919",
    "addr:postcode":"4600;myers;33919",
    "addr:street":"Summerlin Rd Ste C5",
    "iso:country":"US",
    "sg:address":"4600 Summerlin Rd Ste C5",
    "sg:city":"Fort Myers",
    "sg:classifiers":[
        {
            "category":"Restaurant",
            "type":"Food & Drink"
        }
    ],
    "sg:phone":"+1 239 275 6404",
    "sg:postcode":"33919",
    "sg:province":"FL",
    "sg:tags":[
        "chinese"
    ],
    "wof:name":"Magic Wok",
    "wof:placetype":"venue"
},
  "geometry": {"coordinates":[-81.884045,26.595906],"type":"Point"}
}