{
  "type": "Feature",
  "properties": {
    "addr:full":"1662 NE Pine Island Rd Cape Coral FL 33909",
    "addr:housenumber":"1662",
    "addr:postcode":"33909",
    "addr:street":"Ne Pine Island Rd",
    "iso:country":"US",
    "sg:address":"1662 NE Pine Island Rd",
    "sg:city":"Cape Coral",
    "sg:classifiers":[
        {
            "category":"Restaurant",
            "type":"Food & Drink"
        }
    ],
    "sg:menulink":"http://www.allmenus.com/fl/cape-coral/158647-arbys/menu/",
    "sg:phone":"+1 239 458 2644",
    "sg:postcode":"33909",
    "sg:province":"FL",
    "sg:tags":[
        "burger",
        "american"
    ],
    "wof:name":"Arby's",
    "wof:placetype":"venue"
},
  "geometry": {"coordinates":[-81.939482,26.668426],"type":"Point"}
}