{
  "type": "Feature",
  "properties": {
    "addr:full":"135 Shady Pkwy Sarasota FL 34232",
    "addr:housenumber":"135",
    "addr:postcode":"34232",
    "addr:street":"Shady Pkwy",
    "iso:country":"US",
    "sg:address":"135 Shady Pkwy",
    "sg:city":"Sarasota",
    "sg:classifiers":[
        {
            "category":"Professional",
            "subcategory":"Management & Consulting",
            "type":"Services"
        }
    ],
    "sg:phone":"+1 941 371 7638",
    "sg:postcode":"34232",
    "sg:province":"FL",
    "sg:tags":[
        "business"
    ],
    "wof:name":"Lifeworks Consulting",
    "wof:placetype":"venue"
},
  "geometry": {"coordinates":[-82.47095,27.336176],"type":"Point"}
}