{
  "type": "Feature",
  "properties": {
    "addr:full":"285 W Central Pkwy Ste 1708 Altamonte Springs FL 32714",
    "addr:housenumber":"285",
    "addr:postcode":"1708;32714",
    "addr:street":"W Central Pkwy Ste",
    "iso:country":"US",
    "sg:address":"285 W Central Pkwy Ste 1708",
    "sg:city":"Altamonte Springs",
    "sg:classifiers":[
        {
            "category":"Shopping",
            "subcategory":"Computers & Home Electronics",
            "type":"Retail Goods"
        }
    ],
    "sg:phone":"+1 407 786 8855",
    "sg:postcode":"32714",
    "sg:province":"FL",
    "wof:name":"Southern Business Communication",
    "wof:placetype":"venue"
},
  "geometry": {"coordinates":[-81.39398,28.672907],"type":"Point"}
}