{
  "type": "Feature",
  "properties": {
    "addr:full":"3900 NE 18th Ave Oakland Park FL 33334",
    "addr:housenumber":"3900",
    "addr:postcode":"33334",
    "addr:street":"Ne 18Th Ave",
    "iso:country":"US",
    "sg:address":"3900 NE 18th Ave",
    "sg:city":"Oakland Park",
    "sg:classifiers":[
        {
            "category":"Professional",
            "type":"Services"
        }
    ],
    "sg:phone":"+1 954 563 8627",
    "sg:postcode":"33334",
    "sg:province":"FL",
    "sg:tags":[
        "establishment"
    ],
    "wof:name":"Cobbles East Townhouse",
    "wof:placetype":"venue"
},
  "geometry": {"coordinates":[-80.122231,26.175949],"type":"Point"}
}