{
  "type": "Feature",
  "properties": {
    "iso:country":"US",
    "sg:address":"1920 SW 57th Ave",
    "sg:city":"Miami",
    "sg:classifiers":[
        {
            "category":"Restaurant",
            "type":"Food & Drink"
        }
    ],
    "sg:phone":"+1 305 265 1910",
    "sg:postcode":"33155",
    "sg:province":"FL",
    "sg:tags":[
        "american",
        "latin"
    ],
    "wof:name":"Mamma Mia",
    "wof:placetype":"venue"
},
  "geometry": {"coordinates":[-80.287475,25.7534],"type":"Point"}
}