{
  "type": "Feature",
  "properties": {
    "addr:full":"2960 Plummer Cove Rd Jacksonville FL 32223",
    "addr:housenumber":"2960",
    "addr:postcode":"32223",
    "addr:street":"Plummer Cove Rd",
    "iso:country":"US",
    "sg:address":"2960 Plummer Cove Rd",
    "sg:city":"Jacksonville",
    "sg:classifiers":[
        {
            "category":"Place Of Worship",
            "type":"Public Place"
        }
    ],
    "sg:phone":"+1 904 288 8808",
    "sg:postcode":"32223",
    "sg:province":"FL",
    "sg:tags":[
        "church"
    ],
    "sg:website":"http://www.gracechapel.com",
    "wof:name":"Grace Chapel Chistian Fellowship",
    "wof:placetype":"venue"
},
  "geometry": {"coordinates":[-81.630889,30.181012],"type":"Point"}
}