{
  "type": "Feature",
  "properties": {
    "iso:country":"US",
    "sg:address":"741 S Eloise St",
    "sg:city":"Lake City",
    "sg:classifiers":[
        {
            "category":"Building & Trades",
            "subcategory":"Construction",
            "type":"Services"
        }
    ],
    "sg:phone":"+1 386 755 4690",
    "sg:postcode":"32025",
    "sg:province":"FL",
    "sg:tags":[
        "contractor"
    ],
    "wof:name":"First Coast Tower",
    "wof:placetype":"venue"
},
  "geometry": {"coordinates":[-82.617132,30.18414],"type":"Point"}
}