{
  "type": "Feature",
  "properties": {
    "iso:country":"US",
    "sg:address":"5200 Tamiami Trl N",
    "sg:city":"Naples",
    "sg:classifiers":[
        {
            "category":"Health Services",
            "subcategory":"Doctor",
            "type":"Services"
        }
    ],
    "sg:phone":"+1 239 263 6766",
    "sg:postcode":"34103",
    "sg:province":"FL",
    "sg:tags":[
        "physician",
        "surgeon"
    ],
    "sg:website":"www.cosmeticsurgeons.com",
    "wof:name":"Newgate Surgery Ctr",
    "wof:placetype":"venue"
},
  "geometry": {"coordinates":[-81.800421,26.211242],"type":"Point"}
}