{
  "type": "Feature",
  "properties": {
    "addr:full":"2071 Emerson St Jacksonville FL 32207",
    "addr:housenumber":"2071",
    "addr:postcode":"32207",
    "addr:street":"Emerson St",
    "iso:country":"US",
    "sg:address":"2071 Emerson St",
    "sg:city":"Jacksonville",
    "sg:classifiers":[
        {
            "category":"Wholesale",
            "subcategory":"Electrical",
            "type":"Manufacturing & Wholesale Goods"
        }
    ],
    "sg:phone":"+1 904 396 5600",
    "sg:postcode":"32207",
    "sg:province":"FL",
    "sg:tags":[
        "alarm",
        "burglar",
        "system"
    ],
    "wof:name":"Systems Depot",
    "wof:placetype":"venue"
},
  "geometry": {"coordinates":[-81.639842,30.284926],"type":"Point"}
}