{
  "type": "Feature",
  "properties": {
    "iso:country":"US",
    "sg:address":"3014 Woodruff Dr",
    "sg:city":"Orlando",
    "sg:classifiers":[
        {
            "category":"Retail",
            "subcategory":"Repair Shop",
            "type":"Services"
        }
    ],
    "sg:phone":"+1 407 859 6418",
    "sg:postcode":"32837",
    "sg:province":"FL",
    "sg:tags":[
        "welding"
    ],
    "wof:name":"Brian Matta Welding",
    "wof:placetype":"venue"
},
  "geometry": {"coordinates":[-81.420745,28.404035],"type":"Point"}
}