{
  "type": "Feature",
  "properties": {
    "addr:full":"12755 SW Highway 484 Dunnellon FL 34432",
    "addr:housenumber":"12755",
    "addr:postcode":"34432",
    "addr:street":"Sw Highway 484",
    "iso:country":"US",
    "sg:address":"12755 SW Highway 484",
    "sg:city":"Dunnellon",
    "sg:classifiers":[
        {
            "category":"Building & Trades",
            "subcategory":"Construction",
            "type":"Services"
        }
    ],
    "sg:phone":"+1 352 489 2711",
    "sg:postcode":"34432",
    "sg:province":"FL",
    "sg:tags":[
        "contractor",
        "fence-sales"
    ],
    "wof:name":"JNT Fence Company",
    "wof:placetype":"venue"
},
  "geometry": {"coordinates":[-82.33133599999999,29.053538],"type":"Point"}
}