{
  "type": "Feature",
  "properties": {
    "addr:full":"8346 96th Ct Vero Beach FL 32967",
    "addr:housenumber":"8346",
    "addr:postcode":"32967",
    "addr:street":"96Th Ct",
    "iso:country":"US",
    "sg:address":"8346 96th Ct",
    "sg:city":"Vero Beach",
    "sg:classifiers":[
        {
            "category":"Building & Trades",
            "subcategory":"Construction",
            "type":"Services"
        }
    ],
    "sg:phone":"+1 772 581 2901",
    "sg:postcode":"32967",
    "sg:province":"FL",
    "sg:tags":[
        "concrete",
        "contractor"
    ],
    "wof:name":"DSC",
    "wof:placetype":"venue"
},
  "geometry": {"coordinates":[-80.524569,27.746356],"type":"Point"}
}