{
  "type": "Feature",
  "properties": {
    "iso:country":"US",
    "sg:address":"949 Whelk Dr",
    "sg:city":"Sanibel",
    "sg:classifiers":[
        {
            "category":"Banks & Credit Unions",
            "subcategory":"Investment Brokerage",
            "type":"Services"
        }
    ],
    "sg:phone":"+1 239 472 5338",
    "sg:postcode":"33957",
    "sg:province":"FL",
    "sg:tags":[
        "advisory"
    ],
    "wof:name":"Interamerican Capital Partners",
    "wof:placetype":"venue"
},
  "geometry": {"coordinates":[-82.03628500000001,26.445441],"type":"Point"}
}