{
  "type": "Feature",
  "properties": {
    "addr:full":"146 2nd St S Saint Petersburg FL 33701",
    "addr:housenumber":"146",
    "addr:postcode":"33701",
    "addr:street":"2Nd St S",
    "iso:country":"US",
    "sg:address":"146 2nd St S",
    "sg:city":"Saint Petersburg",
    "sg:classifiers":[
        {
            "category":"Banks & Credit Unions",
            "subcategory":"Bank",
            "type":"Services"
        }
    ],
    "sg:phone":"+1 727 821 2232",
    "sg:postcode":"33701",
    "sg:province":"FL",
    "sg:tags":[
        "consumer",
        "finance",
        "institution"
    ],
    "wof:name":"E Trade Consumer Finance Corp",
    "wof:placetype":"venue"
},
  "geometry": {"coordinates":[-82.635441,27.769876],"type":"Point"}
}