{
  "type": "Feature",
  "properties": {
    "iso:country":"US",
    "sg:address":"20020 Veterans Blvd",
    "sg:city":"Port Charlotte",
    "sg:classifiers":[
        {
            "category":"Shopping",
            "subcategory":"Pharmacy",
            "type":"Retail Goods"
        }
    ],
    "sg:phone":"+1 941 625 1530",
    "sg:postcode":"33954",
    "sg:province":"FL",
    "wof:name":"Southwest FL Infusion",
    "wof:placetype":"venue"
},
  "geometry": {"coordinates":[-82.052375,27.022028],"type":"Point"}
}