{
  "type": "Feature",
  "properties": {
    "iso:country":"US",
    "sg:address":"5850 Lakehurst Dr",
    "sg:city":"Orlando",
    "sg:classifiers":[
        {
            "category":"Retail",
            "subcategory":"Animal Services",
            "type":"Services"
        }
    ],
    "sg:phone":"+1 407 351 0292",
    "sg:postcode":"32819",
    "sg:province":"FL",
    "sg:tags":[
        "training",
        "dog"
    ],
    "sg:website":"www.petbehavior.com",
    "wof:name":"Pet Behavior Inc",
    "wof:placetype":"venue"
},
  "geometry": {"coordinates":[-81.460937,28.455262],"type":"Point"}
}