{
  "type": "Feature",
  "properties": {
    "iso:country":"US",
    "sg:address":"5417 Madison Rd",
    "sg:city":"Delray Beach",
    "sg:classifiers":[
        {
            "category":"Wholesale",
            "subcategory":"Stationery",
            "type":"Manufacturing & Wholesale Goods"
        }
    ],
    "sg:phone":"+1 561 495 2079",
    "sg:postcode":"33484",
    "sg:province":"FL",
    "sg:tags":[
        "processing",
        "datum",
        "supply"
    ],
    "wof:name":"Troy R Barber Financial Svc",
    "wof:placetype":"venue"
},
  "geometry": {"coordinates":[-80.12924700000001,26.451671],"type":"Point"}
}