{
  "type": "Feature",
  "properties": {
    "iso:country":"US",
    "sg:address":"15835 US Hwy 331 S",
    "sg:city":"Freeport",
    "sg:classifiers":[
        {
            "category":"Banks & Credit Unions",
            "subcategory":"Bank",
            "type":"Services"
        }
    ],
    "sg:phone":"+1 850 835 2143",
    "sg:postcode":"32439",
    "sg:province":"FL",
    "sg:tags":[
        "national",
        "commercial"
    ],
    "wof:name":"Bankshares Corp Niceville",
    "wof:placetype":"venue"
},
  "geometry": {"coordinates":[-86.135159,30.50168],"type":"Point"}
}