{
  "type": "Feature",
  "properties": {
    "addr:full":"1500 Main St Sarasota FL 34236",
    "addr:housenumber":"1500",
    "addr:postcode":"34236",
    "addr:street":"Main St",
    "iso:country":"US",
    "sg:address":"1500 Main St",
    "sg:city":"Sarasota",
    "sg:classifiers":[
        {
            "category":"Restaurant",
            "type":"Food & Drink"
        }
    ],
    "sg:menulink":"http://www.allmenus.com/fl/sarasota/160099-burger-king/menu/",
    "sg:phone":"+1 941 953 6300",
    "sg:postcode":"34236",
    "sg:province":"FL",
    "sg:tags":[
        "burger",
        "american"
    ],
    "wof:name":"Burger King",
    "wof:placetype":"venue"
},
  "geometry": {"coordinates":[-82.540576,27.336451],"type":"Point"}
}