{
  "type": "Feature",
  "properties": {
    "addr:full":"315 Buchanan Ave Cape Canaveral FL 32920",
    "addr:housenumber":"315",
    "addr:postcode":"32920",
    "addr:street":"Buchanan Ave",
    "iso:country":"US",
    "sg:address":"315 Buchanan Ave",
    "sg:city":"Cape Canaveral",
    "sg:classifiers":[
        {
            "category":"Insurance",
            "subcategory":"Insurance Agent",
            "type":"Services"
        }
    ],
    "sg:phone":"+1 321 799 1652",
    "sg:postcode":"32920",
    "sg:province":"FL",
    "wof:name":"Alice Nielsen",
    "wof:placetype":"venue"
},
  "geometry": {"coordinates":[-80.601375,28.381464],"type":"Point"}
}