{
  "type": "Feature",
  "properties": {
    "iso:country":"US",
    "sg:address":"3066 Craig Ter",
    "sg:city":"Crestview",
    "sg:classifiers":[
        {
            "category":"Food & Beverages",
            "subcategory":"Farmers Market",
            "type":"Retail Goods"
        }
    ],
    "sg:phone":"+1 850 682 3401",
    "sg:postcode":"32539",
    "sg:province":"FL",
    "sg:tags":[
        "beekeeper"
    ],
    "wof:name":"Honey Bundrick Farms",
    "wof:placetype":"venue"
},
  "geometry": {"coordinates":[-86.535657,30.77534],"type":"Point"}
}