{
  "type": "Feature",
  "properties": {
    "iso:country":"US",
    "sg:address":"116 Via Duomo",
    "sg:city":"New Smyrna Beach",
    "sg:classifiers":[
        {
            "category":"Retail",
            "subcategory":"Auto Repair",
            "type":"Services"
        }
    ],
    "sg:phone":"+1 386 423 7692",
    "sg:postcode":"32169",
    "sg:province":"FL",
    "sg:tags":[
        "body"
    ],
    "wof:name":"Rogers Auto Body Inc",
    "wof:placetype":"venue"
},
  "geometry": {"coordinates":[-80.911182,29.041477],"type":"Point"}
}