{
  "type": "Feature",
  "properties": {
    "iso:country":"US",
    "sg:address":"2171 Estero Blvd",
    "sg:city":"Fort Myers Beach",
    "sg:classifiers":[
        {
            "category":"Travel",
            "subcategory":"Hotels & Motels",
            "type":"Entertainment"
        }
    ],
    "sg:phone":"+1 239 463 3155",
    "sg:postcode":"33931",
    "sg:province":"FL",
    "sg:tags":[
        "resort"
    ],
    "wof:name":"Periwinkle Motel",
    "wof:placetype":"venue"
},
  "geometry": {"coordinates":[-81.94217399999999,26.448455],"type":"Point"}
}