{
  "type": "Feature",
  "properties": {
    "addr:full":"15903 Benton Ct Tampa FL 33647",
    "addr:housenumber":"15903",
    "addr:postcode":"33647",
    "addr:street":"Benton Ct",
    "iso:country":"US",
    "sg:address":"15903 Benton Ct",
    "sg:city":"Tampa",
    "sg:classifiers":[
        {
            "category":"Wholesale",
            "subcategory":"Home Furnishings",
            "type":"Manufacturing & Wholesale Goods"
        }
    ],
    "sg:phone":"+1 813 971 3821",
    "sg:postcode":"33647",
    "sg:province":"FL",
    "wof:name":"L G & Associates",
    "wof:placetype":"venue"
},
  "geometry": {"coordinates":[-82.366157,28.093101],"type":"Point"}
}