{
  "type": "Feature",
  "properties": {
    "iso:country":"US",
    "sg:address":"1166 S Nova Rd",
    "sg:city":"Ormond Beach",
    "sg:classifiers":[
        {
            "category":"Autos & Motor Vehicles",
            "subcategory":"Auto Supplies",
            "type":"Retail Goods"
        },
        {
            "category":"Wholesale",
            "subcategory":"Auto Parts",
            "type":"Manufacturing & Wholesale Goods"
        }
    ],
    "sg:phone":"+1 386 673 5801",
    "sg:postcode":"32174",
    "sg:province":"FL",
    "sg:tags":[
        "automobile"
    ],
    "wof:name":"Nova North Auto Parts Inc",
    "wof:placetype":"venue"
},
  "geometry": {"coordinates":[-81.070238,29.251189],"type":"Point"}
}