{
  "type": "Feature",
  "properties": {
    "iso:country":"US",
    "sg:address":"5780 W Atlantic Ave",
    "sg:city":"Delray Beach",
    "sg:classifiers":[
        {
            "category":"Organizations",
            "subcategory":"Religious Organization",
            "type":"Services"
        }
    ],
    "sg:phone":"+1 561 498 3536",
    "sg:postcode":"33484",
    "sg:province":"FL",
    "wof:name":"Temple Emeth",
    "wof:placetype":"venue"
},
  "geometry": {"coordinates":[-80.13576500000001,26.456667],"type":"Point"}
}