{
  "type": "Feature",
  "properties": {
    "addr:full":"1810 1st St Bradenton FL 34205",
    "addr:housenumber":"1810",
    "addr:postcode":"34205",
    "addr:street":"1St St",
    "iso:country":"US",
    "sg:address":"1810 1st St",
    "sg:city":"Bradenton",
    "sg:classifiers":[
        {
            "category":"Utilities",
            "subcategory":"Sewage",
            "type":"Services"
        }
    ],
    "sg:phone":"+1 941 708 6350",
    "sg:postcode":"34205",
    "sg:province":"FL",
    "sg:tags":[
        "system",
        "sewerage"
    ],
    "wof:name":"Wastewater Treatment Plant",
    "wof:placetype":"venue"
},
  "geometry": {"coordinates":[-82.56344900000001,27.483003],"type":"Point"}
}