{
  "type": "Feature",
  "properties": {
    "addr:full":"142 Sapelo Rd Jacksonville FL 32216",
    "addr:housenumber":"142",
    "addr:postcode":"32216",
    "addr:street":"Sapelo Rd",
    "iso:country":"US",
    "sg:address":"142 Sapelo Rd",
    "sg:city":"Jacksonville",
    "sg:classifiers":[
        {
            "category":"Professional",
            "subcategory":"Business Services",
            "type":"Services"
        }
    ],
    "sg:phone":"+1 904 726 8222",
    "sg:postcode":"32216",
    "sg:province":"FL",
    "wof:name":"Hole of The Pigeon Studio",
    "wof:placetype":"venue"
},
  "geometry": {"coordinates":[-81.59099500000001,30.311544],"type":"Point"}
}