{
  "type": "Feature",
  "properties": {
    "iso:country":"US",
    "sg:address":"2210 W 10th St",
    "sg:city":"Jacksonville",
    "sg:classifiers":[
        {
            "category":"Organizations",
            "subcategory":"Community Association",
            "type":"Services"
        }
    ],
    "sg:phone":"+1 904 356 6517",
    "sg:postcode":"32209",
    "sg:province":"FL",
    "sg:tags":[
        "fraternal"
    ],
    "wof:name":"Prince Hall Masons A F & A M",
    "wof:placetype":"venue"
},
  "geometry": {"coordinates":[-81.698177,30.348537],"type":"Point"}
}