{
  "type": "Feature",
  "properties": {
    "addr:full":"6385 Presidential Ct Fort Myers FL 33919",
    "addr:housenumber":"6385",
    "addr:postcode":"33919",
    "addr:street":"Presidential Ct",
    "iso:country":"US",
    "sg:address":"6385 Presidential Ct",
    "sg:city":"Fort Myers",
    "sg:classifiers":[
        {
            "category":"Professional",
            "subcategory":"Business Services",
            "type":"Services"
        }
    ],
    "sg:phone":"+1 239 481 4976",
    "sg:postcode":"33919",
    "sg:province":"FL",
    "sg:tags":[
        "interior",
        "consultant",
        "design",
        "decorator"
    ],
    "wof:name":"Decorating Den Interiors",
    "wof:placetype":"venue"
},
  "geometry": {"coordinates":[-81.887863,26.557824],"type":"Point"}
}