{
  "type": "Feature",
  "properties": {
    "addr:full":"1218 Washington Ave Miami Beach FL 33139",
    "addr:housenumber":"1218",
    "addr:postcode":"33139",
    "addr:street":"Washington Ave",
    "iso:country":"US",
    "sg:address":"1218 Washington Ave",
    "sg:city":"Miami Beach",
    "sg:classifiers":[
        {
            "category":"Arts & Performance",
            "subcategory":"Art Gallery",
            "type":"Entertainment"
        }
    ],
    "sg:phone":"+1 305 531 0204",
    "sg:postcode":"33139",
    "sg:province":"FL",
    "sg:website":"miamitattooco.com",
    "wof:name":"Miami Tattoo Co.",
    "wof:placetype":"venue"
},
  "geometry": {"coordinates":[-80.132355,25.783283],"type":"Point"}
}