{
  "type": "Feature",
  "properties": {
    "addr:full":"57 NW 36th St Miami FL 33127",
    "addr:housenumber":"57",
    "addr:postcode":"33127",
    "addr:street":"Nw 36Th St",
    "iso:country":"US",
    "sg:address":"57 NW 36th St",
    "sg:city":"Miami",
    "sg:classifiers":[
        {
            "category":"Wholesale",
            "subcategory":"Auto Parts",
            "type":"Manufacturing & Wholesale Goods"
        }
    ],
    "sg:phone":"+1 305 576 9802",
    "sg:postcode":"33127",
    "sg:province":"FL",
    "sg:tags":[
        "automobile",
        "rebuilt",
        "repair"
    ],
    "wof:name":"Mercedes Auto Center",
    "wof:placetype":"venue"
},
  "geometry": {"coordinates":[-80.196489,25.810634],"type":"Point"}
}