{
  "type": "Feature",
  "properties": {
    "addr:full":"9200 S Dadeland Blvd Ste 825 Miami FL 33156",
    "addr:housenumber":"9200",
    "addr:postcode":"33156",
    "addr:street":"S Dadeland Blvd Ste 825",
    "iso:country":"US",
    "sg:address":"9200 S Dadeland Blvd Ste 825",
    "sg:city":"Miami",
    "sg:classifiers":[
        {
            "category":"Professional",
            "subcategory":"Lawyer & Legal Services",
            "type":"Services"
        }
    ],
    "sg:phone":"+1 305 670 1161",
    "sg:postcode":"33156",
    "sg:province":"FL",
    "wof:name":"Quintairos McCumber Prieto Wood & Boyer",
    "wof:placetype":"venue"
},
  "geometry": {"coordinates":[-80.315399,25.6838],"type":"Point"}
}