{
  "type": "Feature",
  "properties": {
    "iso:country":"US",
    "sg:address":"570 E Horatio Ave",
    "sg:city":"Maitland",
    "sg:classifiers":[
        {
            "category":"Health Services",
            "subcategory":"Doctor",
            "type":"Services"
        }
    ],
    "sg:phone":"+1 407 478 4848",
    "sg:postcode":"32751",
    "sg:province":"FL",
    "wof:name":"Center For Physicians Care Inc",
    "wof:placetype":"venue"
},
  "geometry": {"coordinates":[-81.360826,28.627291],"type":"Point"}
}