{
  "type": "Feature",
  "properties": {
    "addr:full":"1125 S University Dr Plantation FL 33324",
    "addr:housenumber":"1125",
    "addr:postcode":"33324",
    "addr:street":"S University Dr",
    "iso:country":"US",
    "sg:address":"1125 S University Dr",
    "sg:city":"Plantation",
    "sg:classifiers":[
        {
            "category":"Health Services",
            "subcategory":"Doctor",
            "type":"Services"
        }
    ],
    "sg:phone":"+1 954 474 5567",
    "sg:postcode":"33324",
    "sg:province":"FL",
    "sg:tags":[
        "dentist"
    ],
    "wof:name":"Steven P Bogdanoff DDS",
    "wof:placetype":"venue"
},
  "geometry": {"coordinates":[-80.25017099999999,26.106803],"type":"Point"}
}