{
  "type": "Feature",
  "properties": {
    "addr:full":"3281 Hypoluxo Rd Lake Worth FL 33462",
    "addr:housenumber":"3281",
    "addr:postcode":"33462",
    "addr:street":"Hypoluxo Rd",
    "iso:country":"US",
    "sg:address":"3281 Hypoluxo Rd",
    "sg:city":"Lake Worth",
    "sg:classifiers":[
        {
            "category":"Shopping",
            "subcategory":"Jewelry",
            "type":"Retail Goods"
        }
    ],
    "sg:phone":"+1 561 439 2917",
    "sg:postcode":"33462",
    "sg:province":"FL",
    "sg:tags":[
        "jeweler"
    ],
    "wof:name":"Little Treasure Group",
    "wof:placetype":"venue"
},
  "geometry": {"coordinates":[-80.093802,26.572015],"type":"Point"}
}