{
  "type": "Feature",
  "properties": {
    "iso:country":"US",
    "sg:address":"722 Via Formia",
    "sg:city":"Punta Gorda",
    "sg:classifiers":[
        {
            "category":"Manufacturing",
            "subcategory":"Metals",
            "type":"Manufacturing & Wholesale Goods"
        }
    ],
    "sg:phone":"+1 941 505 0203",
    "sg:postcode":"33950",
    "sg:province":"FL",
    "sg:tags":[
        "building",
        "prefabricated"
    ],
    "wof:name":"Dll Inc",
    "wof:placetype":"venue"
},
  "geometry": {"coordinates":[-82.057354,26.920159],"type":"Point"}
}