{
  "type": "Feature",
  "properties": {
    "addr:full":"6296 Corporate Ct Ste A201 Fort Myers FL 33919",
    "addr:housenumber":"6296",
    "addr:postcode":"fort myers;33919",
    "addr:street":"Corporate Ct Ste A201",
    "iso:country":"US",
    "sg:address":"6296 Corporate Ct Ste A201",
    "sg:city":"Fort Myers",
    "sg:classifiers":[
        {
            "category":"Building & Trades",
            "subcategory":"Construction",
            "type":"Services"
        }
    ],
    "sg:phone":"+1 239 489 4118",
    "sg:postcode":"33919",
    "sg:province":"FL",
    "sg:tags":[
        "painter"
    ],
    "wof:name":"Bonheur Painting Coatings of Florida Inc",
    "wof:placetype":"venue"
},
  "geometry": {"coordinates":[-81.9011,26.5536],"type":"Point"}
}