{
  "type": "Feature",
  "properties": {
    "iso:country":"US",
    "sg:address":"7100 W Cam Real",
    "sg:city":"Boca Raton",
    "sg:classifiers":[
        {
            "category":"Organizations",
            "subcategory":"Professional Association",
            "type":"Services"
        }
    ],
    "sg:phone":"+1 561 226 2530",
    "sg:postcode":"33433",
    "sg:province":"FL",
    "sg:tags":[
        "business"
    ],
    "wof:name":"Adult Chamber of Commerce",
    "wof:placetype":"venue"
},
  "geometry": {"coordinates":[-80.15418699999999,26.343796],"type":"Point"}
}