{
  "type": "Feature",
  "properties": {
    "addr:full":"6008 Raintree Trl Fort Pierce FL 34982",
    "addr:housenumber":"6008",
    "addr:postcode":"34982",
    "addr:street":"Raintree Trl",
    "iso:country":"US",
    "sg:address":"6008 Raintree Trl",
    "sg:city":"Fort Pierce",
    "sg:classifiers":[
        {
            "category":"Shopping",
            "subcategory":"Discount & Variety Stores",
            "type":"Retail Goods"
        }
    ],
    "sg:phone":"+1 772 461 2067",
    "sg:postcode":"34982",
    "sg:province":"FL",
    "sg:tags":[
        "merchandise",
        "general"
    ],
    "wof:name":"Allen Mc Arthur's Sales",
    "wof:placetype":"venue"
},
  "geometry": {"coordinates":[-80.303213,27.354612],"type":"Point"}
}