{
  "type": "Feature",
  "properties": {
    "iso:country":"US",
    "sg:address":"451 N Catherine St",
    "sg:city":"Jacksonville",
    "sg:classifiers":[
        {
            "category":"Government",
            "subcategory":"Jail",
            "type":"Public Place"
        }
    ],
    "sg:phone":"+1 904 630 2858",
    "sg:postcode":"32202",
    "sg:province":"FL",
    "sg:tags":[
        "govt",
        "city",
        "institution"
    ],
    "wof:name":"Community Corrections Div",
    "wof:placetype":"venue"
},
  "geometry": {"coordinates":[-81.649387,30.327952],"type":"Point"}
}