{
  "type": "Feature",
  "properties": {
    "iso:country":"US",
    "sg:address":"510 Douglas Ave",
    "sg:city":"Altamonte Springs",
    "sg:classifiers":[
        {
            "category":"Utilities",
            "subcategory":"Cable",
            "type":"Services"
        }
    ],
    "sg:phone":"+1 407 788 8933",
    "sg:postcode":"32714",
    "sg:province":"FL",
    "sg:tags":[
        "television"
    ],
    "wof:name":"Tvmax Inc",
    "wof:placetype":"venue"
},
  "geometry": {"coordinates":[-81.390424,28.671495],"type":"Point"}
}