{
  "type": "Feature",
  "properties": {
    "iso:country":"US",
    "sg:address":"4110 Southpoint Blvd",
    "sg:city":"Jacksonville",
    "sg:classifiers":[
        {
            "category":"Professional",
            "subcategory":"Management & Consulting",
            "type":"Services"
        }
    ],
    "sg:phone":"+1 904 332 0990",
    "sg:postcode":"32216",
    "sg:province":"FL",
    "sg:tags":[
        "construction"
    ],
    "wof:name":"PSA Construction's Inc",
    "wof:placetype":"venue"
},
  "geometry": {"coordinates":[-81.58955400000001,30.2548],"type":"Point"}
}