{
  "type": "Feature",
  "properties": {
    "addr:full":"710 7th St NW Naples FL 34120",
    "addr:housenumber":"710",
    "addr:postcode":"34120",
    "addr:street":"7Th St Nw",
    "iso:country":"US",
    "sg:address":"710 7th St NW",
    "sg:city":"Naples",
    "sg:classifiers":[
        {
            "category":"Building & Trades",
            "subcategory":"Construction",
            "type":"Services"
        }
    ],
    "sg:phone":"+1 239 352 0976",
    "sg:postcode":"34120",
    "sg:province":"FL",
    "sg:tags":[
        "contractor"
    ],
    "wof:name":"Darren Skiba Corp",
    "wof:placetype":"venue"
},
  "geometry": {"coordinates":[-81.62087699999999,26.229726],"type":"Point"}
}