{
  "type": "Feature",
  "properties": {
    "iso:country":"US",
    "sg:address":"6818 Graphic Dr",
    "sg:city":"Port Richey",
    "sg:classifiers":[
        {
            "category":"Retail",
            "subcategory":"Auto Repair",
            "type":"Services"
        }
    ],
    "sg:phone":"+1 727 862 6341",
    "sg:postcode":"34668",
    "sg:province":"FL",
    "sg:tags":[
        "repairing",
        "automobile"
    ],
    "wof:name":"Paramount Auto Repair",
    "wof:placetype":"venue"
},
  "geometry": {"coordinates":[-82.701865,28.304101],"type":"Point"}
}