{
  "type": "Feature",
  "properties": {
    "addr:full":"4701 S Semoran Blvd Orlando FL 32822",
    "addr:housenumber":"4701",
    "addr:postcode":"32822",
    "addr:street":"S Semoran Blvd",
    "iso:country":"US",
    "sg:address":"4701 S Semoran Blvd",
    "sg:city":"Orlando",
    "sg:classifiers":[
        {
            "category":"Food & Beverages",
            "subcategory":"Groceries & Convenience Stores",
            "type":"Retail Goods"
        }
    ],
    "sg:phone":"+1 407 207 3535",
    "sg:postcode":"32822",
    "sg:province":"FL",
    "sg:tags":[
        "gasoline"
    ],
    "wof:name":"Hess Express Shop III",
    "wof:placetype":"venue"
},
  "geometry": {"coordinates":[-81.310197,28.493167],"type":"Point"}
}