{
  "type": "Feature",
  "properties": {
    "addr:full":"3355 NW 167th St Opa Locka FL 33056",
    "addr:housenumber":"3355",
    "addr:postcode":"33056",
    "addr:street":"Nw 167Th St;Locka",
    "iso:country":"US",
    "sg:address":"3355 NW 167th St",
    "sg:city":"Opa Locka",
    "sg:classifiers":[
        {
            "category":"Building & Trades",
            "subcategory":"Construction",
            "type":"Services"
        }
    ],
    "sg:phone":"+1 305 474 4838",
    "sg:postcode":"33056",
    "sg:province":"FL",
    "sg:tags":[
        "resurfacing",
        "laying",
        "refinishing",
        "floor"
    ],
    "wof:name":"Floors Today",
    "wof:placetype":"venue"
},
  "geometry": {"coordinates":[-80.258171,25.926201],"type":"Point"}
}