{
  "type": "Feature",
  "properties": {
    "iso:country":"US",
    "sg:address":"204 Baisden Rd",
    "sg:city":"Jacksonville",
    "sg:classifiers":[
        {
            "category":"Building & Trades",
            "subcategory":"Construction",
            "type":"Services"
        }
    ],
    "sg:phone":"+1 904 757 8212",
    "sg:postcode":"32218",
    "sg:province":"FL",
    "sg:tags":[
        "carpentry",
        "contractor"
    ],
    "wof:name":"Robert Edwards Custom Finisher",
    "wof:placetype":"venue"
},
  "geometry": {"coordinates":[-81.635141,30.43909],"type":"Point"}
}