{
  "type": "Feature",
  "properties": {
    "addr:full":"8531 S Tamiami Trl Sarasota FL 34238",
    "addr:housenumber":"8531",
    "addr:postcode":"34238",
    "addr:street":"S Tamiami Trl",
    "iso:country":"US",
    "sg:address":"8531 S Tamiami Trl",
    "sg:city":"Sarasota",
    "sg:classifiers":[
        {
            "category":"Personal",
            "subcategory":"Beauty Salon",
            "type":"Services"
        }
    ],
    "sg:phone":"+1 941 925 4147",
    "sg:postcode":"34238",
    "sg:province":"FL",
    "sg:tags":[
        "shop"
    ],
    "wof:name":"Avishar Hair Design",
    "wof:placetype":"venue"
},
  "geometry": {"coordinates":[-82.493509,27.226978],"type":"Point"}
}