{
  "type": "Feature",
  "properties": {
    "iso:country":"US",
    "sg:address":"2001 E Hillsborough Ave A-5",
    "sg:city":"Tampa",
    "sg:classifiers":[
        {
            "category":"Personal",
            "subcategory":"Nail Salon",
            "type":"Services"
        }
    ],
    "sg:phone":"+1 813 239 3664",
    "sg:postcode":"33610",
    "sg:province":"FL",
    "wof:name":"Club Nails",
    "wof:placetype":"venue"
},
  "geometry": {"coordinates":[-82.43678300000001,27.99609],"type":"Point"}
}