{
  "type": "Feature",
  "properties": {
    "addr:full":"3100 SW 128th Ave Miami FL 33175",
    "addr:housenumber":"3100",
    "addr:postcode":"33175",
    "addr:street":"Sw 128Th Ave",
    "iso:country":"US",
    "sg:address":"3100 SW 128th Ave",
    "sg:city":"Miami",
    "sg:classifiers":[
        {
            "category":"Travel",
            "subcategory":"Travel Agent",
            "type":"Entertainment"
        }
    ],
    "sg:phone":"+1 305 225 8022",
    "sg:postcode":"33175",
    "sg:province":"FL",
    "sg:tags":[
        "agency",
        "bureau"
    ],
    "wof:name":"Dream Travel",
    "wof:placetype":"venue"
},
  "geometry": {"coordinates":[-80.401945,25.738221],"type":"Point"}
}