{
  "type": "Feature",
  "properties": {
    "addr:full":"925 Old Federal Hwy Hallandale Beach FL 33009",
    "addr:housenumber":"925",
    "addr:postcode":"33009",
    "addr:street":"Old Federal Hwy",
    "iso:country":"US",
    "sg:address":"925 Old Federal Hwy",
    "sg:city":"Hallandale Beach",
    "sg:classifiers":[
        {
            "category":"Personal",
            "type":"Services"
        }
    ],
    "sg:phone":"+1 954 455 5004",
    "sg:postcode":"33009",
    "sg:province":"FL",
    "sg:tags":[
        "electrolysis"
    ],
    "wof:name":"Aventura Electrolysis & Skin",
    "wof:placetype":"venue"
},
  "geometry": {"coordinates":[-80.147318,25.975694],"type":"Point"}
}