{
  "type": "Feature",
  "properties": {
    "iso:country":"US",
    "sg:address":"9195 Boggy Creek Rd",
    "sg:city":"Orlando",
    "sg:classifiers":[
        {
            "category":"Food & Beverages",
            "subcategory":"Liquor & Beverages",
            "type":"Retail Goods"
        }
    ],
    "sg:phone":"+1 407 438 7670",
    "sg:postcode":"32824",
    "sg:province":"FL",
    "sg:tags":[
        "distributor",
        "frozen",
        "beer",
        "packaged"
    ],
    "wof:name":"Del Tropico Fd Bev of N Amer",
    "wof:placetype":"venue"
},
  "geometry": {"coordinates":[-81.34873,28.436812],"type":"Point"}
}