{
  "type": "Feature",
  "properties": {
    "iso:country":"US",
    "sg:address":"3120 Carol Ave",
    "sg:city":"Lake Worth",
    "sg:classifiers":[
        {
            "category":"Wholesale",
            "subcategory":"Machinery & Supplies",
            "type":"Manufacturing & Wholesale Goods"
        }
    ],
    "sg:phone":"+1 561 964 3717",
    "sg:postcode":"33461",
    "sg:province":"FL",
    "sg:tags":[
        "tractor"
    ],
    "wof:name":"Fernandez Lucianio",
    "wof:placetype":"venue"
},
  "geometry": {"coordinates":[-80.09160199999999,26.634088],"type":"Point"}
}