{
  "type": "Feature",
  "properties": {
    "iso:country":"US",
    "sg:address":"1100 SW 8 Ave",
    "sg:city":"Gainesville",
    "sg:classifiers":[
        {
            "category":"Health Services",
            "subcategory":"Doctor",
            "type":"Services"
        }
    ],
    "sg:phone":"+1 352 377 0206",
    "sg:postcode":"32601",
    "sg:province":"FL",
    "sg:tags":[
        "physician",
        "surgeon"
    ],
    "wof:name":"Bruce A Richards MD",
    "wof:placetype":"venue"
},
  "geometry": {"coordinates":[-82.33705999999999,29.644921],"type":"Point"}
}