{
  "type": "Feature",
  "properties": {
    "iso:country":"US",
    "sg:address":"3397 Clarine Way E",
    "sg:city":"Dunedin",
    "sg:classifiers":[
        {
            "category":"Manufacturing",
            "subcategory":"Toys & Sporting Goods",
            "type":"Manufacturing & Wholesale Goods"
        },
        {
            "category":"Shopping",
            "subcategory":"Hobbies, Toys, & Games",
            "type":"Retail Goods"
        }
    ],
    "sg:phone":"+1 727 798 4050",
    "sg:postcode":"34698",
    "sg:province":"FL",
    "sg:tags":[
        "toys-wholesale",
        "store",
        "manufacturer"
    ],
    "wof:name":"Chatterchix, Inc.",
    "wof:placetype":"venue"
},
  "geometry": {"coordinates":[-82.745392,28.045076],"type":"Point"}
}