{
  "type": "Feature",
  "properties": {
    "iso:country":"US",
    "sg:address":"9215 SW 9th Ter",
    "sg:city":"Miami",
    "sg:classifiers":[
        {
            "category":"Manufacturing",
            "subcategory":"Metals",
            "type":"Manufacturing & Wholesale Goods"
        }
    ],
    "sg:phone":"+1 305 227 1015",
    "sg:postcode":"33174",
    "sg:province":"FL",
    "sg:tags":[
        "bronze"
    ],
    "wof:name":"Matthews Bronze Intl",
    "wof:placetype":"venue"
},
  "geometry": {"coordinates":[-80.34596999999999,25.76057],"type":"Point"}
}