{
  "type": "Feature",
  "properties": {
    "iso:country":"US",
    "sg:address":"11133 Cobblefield Rd",
    "sg:city":"Lake Worth",
    "sg:classifiers":[
        {
            "category":"Banks & Credit Unions",
            "subcategory":"Financial Services",
            "type":"Services"
        }
    ],
    "sg:phone":"+1 561 784 5778",
    "sg:postcode":"33449",
    "sg:province":"FL",
    "sg:tags":[
        "investor"
    ],
    "wof:name":"Merigold Investments Inc",
    "wof:placetype":"venue"
},
  "geometry": {"coordinates":[-80.223997,26.614619],"type":"Point"}
}