{
  "type": "Feature",
  "properties": {
    "addr:full":"1551 79th St Causeway Miami Beach FL 33141",
    "addr:housenumber":"1551",
    "addr:postcode":"33141",
    "addr:street":"79Th St Causeway",
    "iso:country":"US",
    "sg:address":"1551 79th St Causeway",
    "sg:city":"Miami Beach",
    "sg:classifiers":[
        {
            "category":"Restaurant",
            "type":"Food & Drink"
        }
    ],
    "sg:phone":"+1 305 868 7085",
    "sg:postcode":"33141",
    "sg:province":"FL",
    "sg:tags":[
        "seafood"
    ],
    "sg:website":"www.crabhouseseafood.com",
    "wof:name":"The Crab House",
    "wof:placetype":"venue"
},
  "geometry": {"coordinates":[-80.15321400000001,25.848816],"type":"Point"}
}