{
  "type": "Feature",
  "properties": {
    "addr:full":"8441 SW Hwy 200 Ocala FL 34481",
    "addr:housenumber":"8441",
    "addr:postcode":"34481",
    "addr:street":"Sw Hwy 200",
    "iso:country":"US",
    "sg:address":"8441 SW Hwy 200",
    "sg:city":"Ocala",
    "sg:classifiers":[
        {
            "category":"Restaurant",
            "type":"Food & Drink"
        }
    ],
    "sg:phone":"+1 352 629 0527",
    "sg:postcode":"34481",
    "sg:province":"FL",
    "wof:name":"Mason Jar",
    "wof:placetype":"venue"
},
  "geometry": {"coordinates":[-82.239693,29.096372],"type":"Point"}
}