{
  "type": "Feature",
  "properties": {
    "iso:country":"US",
    "sg:address":"2010 Westmont St",
    "sg:city":"Jacksonville",
    "sg:classifiers":[
        {
            "category":"Retail",
            "subcategory":"Car Wash",
            "type":"Services"
        }
    ],
    "sg:phone":"+1 904 396 7731",
    "sg:postcode":"32207",
    "sg:province":"FL",
    "sg:tags":[
        "automobile",
        "detail",
        "clean"
    ],
    "wof:name":"Phillips Total Car Care/Dtlng",
    "wof:placetype":"venue"
},
  "geometry": {"coordinates":[-81.64162399999999,30.298799],"type":"Point"}
}