{
  "type": "Feature",
  "properties": {
    "addr:full":"10309 Royal Palm Blvd Coral Springs FL 33065",
    "addr:housenumber":"10309",
    "addr:postcode":"33065",
    "addr:street":"Royal Palm Blvd",
    "iso:country":"US",
    "sg:address":"10309 Royal Palm Blvd",
    "sg:city":"Coral Springs",
    "sg:classifiers":[
        {
            "category":"Restaurant",
            "type":"Food & Drink"
        }
    ],
    "sg:phone":"+1 954 753 1111",
    "sg:postcode":"33065",
    "sg:province":"FL",
    "wof:name":"Red Pepper Chinese Cuisine",
    "wof:placetype":"venue"
},
  "geometry": {"coordinates":[-80.26012299999999,26.259234],"type":"Point"}
}