{
  "type": "Feature",
  "properties": {
    "addr:full":"7367 Secret Woods Trl Jacksonville FL 32216",
    "addr:housenumber":"7367",
    "addr:postcode":"32216",
    "addr:street":"Secret Woods Trl",
    "iso:country":"US",
    "sg:address":"7367 Secret Woods Trl",
    "sg:city":"Jacksonville",
    "sg:classifiers":[
        {
            "category":"Restaurant",
            "type":"Food & Drink"
        }
    ],
    "sg:phone":"+1 904 739 3264",
    "sg:postcode":"32216",
    "sg:province":"FL",
    "sg:tags":[
        "caterer"
    ],
    "wof:name":"Mister M's Catering",
    "wof:placetype":"venue"
},
  "geometry": {"coordinates":[-81.584248,30.270747],"type":"Point"}
}