{
  "type": "Feature",
  "properties": {
    "iso:country":"US",
    "sg:address":"8715 SW 57th St",
    "sg:city":"Cooper City",
    "sg:classifiers":[
        {
            "category":"Wholesale",
            "subcategory":"Machinery & Supplies",
            "type":"Manufacturing & Wholesale Goods"
        },
        {
            "category":"Manufacturing",
            "subcategory":"Paper Products",
            "type":"Manufacturing & Wholesale Goods"
        }
    ],
    "sg:phone":"+1 954 252 7423",
    "sg:postcode":"33328",
    "sg:province":"FL",
    "sg:tags":[
        "cargo",
        "container",
        "mfg",
        "packaging",
        "sensitive",
        "thermal",
        "freight"
    ],
    "wof:name":"American Thermal Wizards Intl",
    "wof:placetype":"venue"
},
  "geometry": {"coordinates":[-80.260768,26.049982],"type":"Point"}
}