{
  "type": "Feature",
  "properties": {
    "iso:country":"US",
    "sg:address":"10977 W Beaver St",
    "sg:city":"Jacksonville",
    "sg:classifiers":[
        {
            "category":"Retail",
            "subcategory":"Repair Shop",
            "type":"Services"
        },
        {
            "category":"Retail",
            "subcategory":"Auto Repair",
            "type":"Services"
        }
    ],
    "sg:phone":"+1 904 786 3021",
    "sg:postcode":"32220",
    "sg:province":"FL",
    "sg:tags":[
        "automobile",
        "used",
        "related",
        "general"
    ],
    "wof:name":"Allens Collision Repair",
    "wof:placetype":"venue"
},
  "geometry": {"coordinates":[-81.842921,30.315465],"type":"Point"}
}