{
  "type": "Feature",
  "properties": {
    "iso:country":"US",
    "sg:address":"2301 N 40th St",
    "sg:city":"Tampa",
    "sg:classifiers":[
        {
            "category":"Retail",
            "subcategory":"Funeral Services",
            "type":"Services"
        }
    ],
    "sg:phone":"+1 813 238 6531",
    "sg:postcode":"33605",
    "sg:province":"FL",
    "sg:tags":[
        "burial",
        "vault"
    ],
    "wof:name":"Annette's Burial Vault & Monument Service",
    "wof:placetype":"venue"
},
  "geometry": {"coordinates":[-82.414124,27.96397],"type":"Point"}
}