{
  "type": "Feature",
  "properties": {
    "iso:country":"US",
    "sg:address":"1721 Marsh Run",
    "sg:city":"Naples",
    "sg:classifiers":[
        {
            "category":"Shopping",
            "subcategory":"Discount & Variety Stores",
            "type":"Retail Goods"
        }
    ],
    "sg:phone":"+1 239 860 6666",
    "sg:postcode":"34109",
    "sg:province":"FL",
    "sg:tags":[
        "merchandise",
        "general"
    ],
    "wof:name":"Barry Wampler Retailer",
    "wof:placetype":"venue"
},
  "geometry": {"coordinates":[-81.7824,26.255216],"type":"Point"}
}