{
  "type": "Feature",
  "properties": {
    "addr:full":"10872 Wilderness Ct Orlando FL 32821",
    "addr:housenumber":"10872",
    "addr:postcode":"32821",
    "addr:street":"Wilderness Ct",
    "iso:country":"US",
    "sg:address":"10872 Wilderness Ct",
    "sg:city":"Orlando",
    "sg:classifiers":[
        {
            "category":"Building & Trades",
            "subcategory":"Electrical",
            "type":"Services"
        }
    ],
    "sg:phone":"+1 407 363 2880",
    "sg:postcode":"32821",
    "sg:province":"FL",
    "wof:name":"Carlos A Caruso Installation",
    "wof:placetype":"venue"
},
  "geometry": {"coordinates":[-81.451278,28.408758],"type":"Point"}
}