{
  "type": "Feature",
  "properties": {
    "iso:country":"US",
    "sg:address":"3675 S West Shore Blvd",
    "sg:city":"Tampa",
    "sg:classifiers":[
        {
            "category":"Manufacturing",
            "subcategory":"Metals",
            "type":"Manufacturing & Wholesale Goods"
        },
        {
            "category":"Manufacturing",
            "subcategory":"Building Materials",
            "type":"Manufacturing & Wholesale Goods"
        }
    ],
    "sg:phone":"+1 813 839 7555",
    "sg:postcode":"33629",
    "sg:province":"FL",
    "sg:tags":[
        "doors-wholesale",
        "door",
        "manufacturer"
    ],
    "sg:website":"http://www.thewoodendoor.com",
    "wof:name":"The Wooden Door",
    "wof:placetype":"venue"
},
  "geometry": {"coordinates":[-82.526713,27.909503],"type":"Point"}
}