{
  "type": "Feature",
  "properties": {
    "addr:full":"311 SE Osceola St Stuart FL 34994",
    "addr:housenumber":"311",
    "addr:postcode":"34994",
    "addr:street":"Se Osceola St",
    "iso:country":"US",
    "sg:address":"311 SE Osceola St",
    "sg:city":"Stuart",
    "sg:classifiers":[
        {
            "category":"Autos & Motor Vehicles",
            "subcategory":"Boat Sales",
            "type":"Retail Goods"
        }
    ],
    "sg:phone":"+1 772 220 8586",
    "sg:postcode":"34994",
    "sg:province":"FL",
    "sg:tags":[
        "yacht"
    ],
    "wof:name":"Baia Yacht North American Inc",
    "wof:placetype":"venue"
},
  "geometry": {"coordinates":[-80.248688,27.19851],"type":"Point"}
}