{
  "type": "Feature",
  "properties": {
    "iso:country":"US",
    "sg:address":"30938 Oakmont Ave",
    "sg:city":"Sorrento",
    "sg:classifiers":[
        {
            "category":"Wholesale",
            "subcategory":"Construction Materials",
            "type":"Manufacturing & Wholesale Goods"
        },
        {
            "category":"Home & Garden",
            "subcategory":"Building Materials",
            "type":"Retail Goods"
        }
    ],
    "sg:phone":"+1 352 383 1519",
    "sg:postcode":"32776",
    "sg:province":"FL",
    "sg:tags":[
        "windows-wholesale",
        "window",
        "manufacturer"
    ],
    "wof:name":"My Window Man",
    "wof:placetype":"venue"
},
  "geometry": {"coordinates":[-81.52572600000001,28.800003],"type":"Point"}
}