{
  "type": "Feature",
  "properties": {
    "addr:full":"5230 SW 29th Ter Fort Lauderdale FL 33312",
    "addr:housenumber":"5230",
    "addr:postcode":"33312",
    "addr:street":"Sw 29Th Ter",
    "iso:country":"US",
    "sg:address":"5230 SW 29th Ter",
    "sg:city":"Fort Lauderdale",
    "sg:classifiers":[
        {
            "category":"Manufacturing",
            "subcategory":"Glass & Minerals",
            "type":"Manufacturing & Wholesale Goods"
        }
    ],
    "sg:phone":"+1 954 981 5056",
    "sg:postcode":"33312",
    "sg:province":"FL",
    "sg:tags":[
        "ready",
        "concrete",
        "mfg"
    ],
    "wof:name":"Mix An Control Inc",
    "wof:placetype":"venue"
},
  "geometry": {"coordinates":[-80.180089,26.055945],"type":"Point"}
}