{
  "type": "Feature",
  "properties": {
    "addr:full":"5345 Ortega Blvd Jacksonville FL 32210",
    "addr:housenumber":"5345",
    "addr:postcode":"32210",
    "addr:street":"Ortega Blvd",
    "iso:country":"US",
    "sg:address":"5345 Ortega Blvd",
    "sg:city":"Jacksonville",
    "sg:classifiers":[
        {
            "category":"Real Estate",
            "subcategory":"Developer",
            "type":"Services"
        }
    ],
    "sg:phone":"+1 904 388 8285",
    "sg:postcode":"32210",
    "sg:province":"FL",
    "wof:name":"Gayle Conyers",
    "wof:placetype":"venue"
},
  "geometry": {"coordinates":[-81.697716,30.251507],"type":"Point"}
}