{
  "type": "Feature",
  "properties": {
    "addr:full":"1612 Shirl Ln Jacksonville FL 32207",
    "addr:housenumber":"1612",
    "addr:postcode":"32207",
    "addr:street":"Shirl Ln",
    "iso:country":"US",
    "sg:address":"1612 Shirl Ln",
    "sg:city":"Jacksonville",
    "sg:classifiers":[
        {
            "category":"Communications",
            "subcategory":"Film & Video Production",
            "type":"Services"
        }
    ],
    "sg:phone":"+1 904 737 2500",
    "sg:postcode":"32207",
    "sg:province":"FL",
    "wof:name":"Goodwin Production Services",
    "wof:placetype":"venue"
},
  "geometry": {"coordinates":[-81.64545,30.265135],"type":"Point"}
}