{
  "type": "Feature",
  "properties": {
    "addr:full":"3423 8th St SW Miami FL 33135",
    "addr:housenumber":"3423",
    "addr:postcode":"33135",
    "addr:street":"8Th St Sw",
    "iso:country":"US",
    "sg:address":"3423 8th St SW",
    "sg:city":"Miami",
    "sg:classifiers":[
        {
            "category":"Insurance",
            "subcategory":"Insurance Agent",
            "type":"Services"
        }
    ],
    "sg:phone":"+1 305 446 8072",
    "sg:postcode":"33135",
    "sg:province":"FL",
    "wof:name":"Medero Insurance Services Inc",
    "wof:placetype":"venue"
},
  "geometry": {"coordinates":[-80.25187200000001,25.764848],"type":"Point"}
}