{
  "type": "Feature",
  "properties": {
    "iso:country":"US",
    "sg:address":"7605 E Broadway Ave",
    "sg:city":"Tampa",
    "sg:classifiers":[
        {
            "category":"Freight",
            "type":"Transportation"
        }
    ],
    "sg:phone":"+1 813 621 6757",
    "sg:postcode":"33619",
    "sg:province":"FL",
    "sg:tags":[
        "operator",
        "hauling",
        "trucking"
    ],
    "wof:name":"S T D Enterprises",
    "wof:placetype":"venue"
},
  "geometry": {"coordinates":[-82.36988700000001,27.966695],"type":"Point"}
}