{
  "type": "Feature",
  "properties": {
    "iso:country":"US",
    "sg:address":"1800 Northgate Blvd",
    "sg:city":"Sarasota",
    "sg:classifiers":[
        {
            "category":"Retail",
            "subcategory":"Portrait Studio",
            "type":"Services"
        }
    ],
    "sg:phone":"+1 941 351 3131",
    "sg:postcode":"34234",
    "sg:province":"FL",
    "sg:tags":[
        "photographer"
    ],
    "wof:name":"Sharp Photography",
    "wof:placetype":"venue"
},
  "geometry": {"coordinates":[-82.533805,27.372116],"type":"Point"}
}