{
  "type": "Feature",
  "properties": {
    "iso:country":"US",
    "sg:address":"4821 S Landings Dr",
    "sg:city":"Fort Myers",
    "sg:classifiers":[
        {
            "category":"Manufacturing",
            "subcategory":"Rubber & Plastics",
            "type":"Manufacturing & Wholesale Goods"
        }
    ],
    "sg:phone":"+1 239 482 1626",
    "sg:postcode":"33919",
    "sg:province":"FL",
    "sg:tags":[
        "laminated",
        "mfg"
    ],
    "wof:name":"Chesterfield Clockworks",
    "wof:placetype":"venue"
},
  "geometry": {"coordinates":[-81.920805,26.552569],"type":"Point"}
}