{
  "type": "Feature",
  "properties": {
    "iso:country":"US",
    "sg:address":"2405 S Florida Ave",
    "sg:city":"Lakeland",
    "sg:classifiers":[
        {
            "category":"Personal",
            "subcategory":"Tattoo Parlor",
            "type":"Services"
        }
    ],
    "sg:phone":"+1 863 687 6900",
    "sg:postcode":"33803",
    "sg:province":"FL",
    "sg:tags":[
        "body",
        "tattooing",
        "piercing"
    ],
    "sg:website":"http://www.atomictattoos.com",
    "wof:name":"Atomic Tattoos Studio 8",
    "wof:placetype":"venue"
},
  "geometry": {"coordinates":[-81.95705599999999,28.015648],"type":"Point"}
}