{
  "type": "Feature",
  "properties": {
    "iso:country":"US",
    "sg:address":"1500 Co Rd 1",
    "sg:city":"Dunedin",
    "sg:classifiers":[
        {
            "category":"Real Estate",
            "subcategory":"Developer",
            "type":"Services"
        },
        {
            "category":"Organizations",
            "subcategory":"Community Association",
            "type":"Services"
        }
    ],
    "sg:phone":"+1 727 733 5522",
    "sg:postcode":"34698",
    "sg:province":"FL",
    "sg:tags":[
        "mobile",
        "home"
    ],
    "wof:name":"Lake Highlander Mobile Home Pk",
    "wof:placetype":"venue"
},
  "geometry": {"coordinates":[-82.762818,28.028506],"type":"Point"}
}