{
  "type": "Feature",
  "properties": {
    "addr:full":"1112 Oxbridge Ln Ormond Beach FL 32174",
    "addr:housenumber":"1112",
    "addr:postcode":"32174",
    "addr:street":"Oxbridge Ln",
    "iso:country":"US",
    "sg:address":"1112 Oxbridge Ln",
    "sg:city":"Ormond Beach",
    "sg:classifiers":[
        {
            "category":"Building & Trades",
            "subcategory":"Construction",
            "type":"Services"
        }
    ],
    "sg:phone":"+1 386 437 0044",
    "sg:postcode":"32174",
    "sg:province":"FL",
    "sg:tags":[
        "hanging",
        "contractor"
    ],
    "wof:name":"Easy Photo Painting",
    "wof:placetype":"venue"
},
  "geometry": {"coordinates":[-81.149389,29.371261],"type":"Point"}
}