{
  "type": "Feature",
  "properties": {
    "iso:country":"US",
    "sg:address":"1629 E Edgewood Dr",
    "sg:city":"Lakeland",
    "sg:classifiers":[
        {
            "category":"Social Services",
            "subcategory":"Child Care",
            "type":"Services"
        }
    ],
    "sg:phone":"+1 863 688 5122",
    "sg:postcode":"33803",
    "sg:province":"FL",
    "wof:name":"Smart Start Kidcare",
    "wof:placetype":"venue"
},
  "geometry": {"coordinates":[-81.93112600000001,28.011241],"type":"Point"}
}