{
  "type": "Feature",
  "properties": {
    "iso:country":"US",
    "sg:address":"1452 Breck Dr",
    "sg:city":"Tallahassee",
    "sg:classifiers":[
        {
            "category":"Government",
            "subcategory":"Office",
            "type":"Public Place"
        }
    ],
    "sg:phone":"+1 850 878 3016",
    "sg:postcode":"32305",
    "sg:province":"FL",
    "wof:name":"Hawkins Jessie Lee",
    "wof:placetype":"venue"
},
  "geometry": {"coordinates":[-84.30426199999999,30.389261],"type":"Point"}
}