{
  "type": "Feature",
  "properties": {
    "iso:country":"US",
    "sg:address":"1001 NW 62nd St",
    "sg:city":"Fort Lauderdale",
    "sg:classifiers":[
        {
            "category":"Banks & Credit Unions",
            "subcategory":"Bank",
            "type":"Services"
        }
    ],
    "sg:phone":"+1 954 771 0528",
    "sg:postcode":"33309",
    "sg:province":"FL",
    "sg:tags":[
        "broker",
        "mortgage"
    ],
    "wof:name":"Windsor Capital Mortgage Corp",
    "wof:placetype":"venue"
},
  "geometry": {"coordinates":[-80.15970799999999,26.203169],"type":"Point"}
}