{
  "type": "Feature",
  "properties": {
    "iso:country":"US",
    "sg:address":"35 Palmer St",
    "sg:city":"St Augustine",
    "sg:classifiers":[
        {
            "category":"Organizations",
            "subcategory":"Non-profit Organization",
            "type":"Services"
        }
    ],
    "sg:phone":"+1 904 829 2461",
    "sg:postcode":"32084",
    "sg:province":"FL",
    "wof:name":"Missing Children Alert Program",
    "wof:placetype":"venue"
},
  "geometry": {"coordinates":[-81.329559,29.893196],"type":"Point"}
}