{
  "type": "Feature",
  "properties": {
    "iso:country":"US",
    "sg:address":"150 153rd Ave",
    "sg:city":"Saint Petersburg",
    "sg:classifiers":[
        {
            "category":"Building & Trades",
            "subcategory":"Construction",
            "type":"Services"
        }
    ],
    "sg:phone":"+1 727 394 7179",
    "sg:postcode":"33708",
    "sg:province":"FL",
    "sg:tags":[
        "contractor"
    ],
    "wof:name":"150 Building Condominium Assn",
    "wof:placetype":"venue"
},
  "geometry": {"coordinates":[-82.802564,27.804486],"type":"Point"}
}