{
  "type": "Feature",
  "properties": {
    "addr:full":"3515 SW 39th Blvd Gainesville FL 32608",
    "addr:housenumber":"3515",
    "addr:postcode":"32608",
    "addr:street":"Sw 39Th Blvd",
    "iso:country":"US",
    "sg:address":"3515 SW 39th Blvd",
    "sg:city":"Gainesville",
    "sg:classifiers":[
        {
            "category":"Real Estate",
            "subcategory":"Real Estate Operator",
            "type":"Services"
        }
    ],
    "sg:phone":"+1 352 372 8100",
    "sg:postcode":"32608",
    "sg:province":"FL",
    "sg:tags":[
        "apartment"
    ],
    "wof:name":"Greenwich Green Apartments",
    "wof:placetype":"venue"
},
  "geometry": {"coordinates":[-82.37974699999999,29.619901],"type":"Point"}
}