{
  "type": "Feature",
  "properties": {
    "iso:country":"US",
    "sg:address":"1516 Border St",
    "sg:city":"Pensacola",
    "sg:classifiers":[
        {
            "category":"Retail",
            "subcategory":"Auto Repair",
            "type":"Services"
        }
    ],
    "sg:phone":"+1 850 458 9368",
    "sg:postcode":"32505",
    "sg:province":"FL",
    "sg:tags":[
        "general"
    ],
    "wof:name":"Auto Care",
    "wof:placetype":"venue"
},
  "geometry": {"coordinates":[-87.26324700000001,30.433319],"type":"Point"}
}