{
  "type": "Feature",
  "properties": {
    "addr:full":"3002 State Hwy 540 Winter Haven FL 33880",
    "addr:housenumber":"3002",
    "addr:postcode":"33880",
    "addr:street":"State Hwy 540",
    "iso:country":"US",
    "sg:address":"3002 State Hwy 540",
    "sg:city":"Winter Haven",
    "sg:classifiers":[
        {
            "category":"Restaurant",
            "type":"Food & Drink"
        }
    ],
    "sg:phone":"+1 863 294 9334",
    "sg:postcode":"33880",
    "sg:province":"FL",
    "wof:name":"Hungry Howie's Pizza & Subs",
    "wof:placetype":"venue"
},
  "geometry": {"coordinates":[-81.76409,28.004011],"type":"Point"}
}