{
  "type": "Feature",
  "properties": {
    "iso:country":"US",
    "sg:address":"2777 Miccosukee Rd",
    "sg:city":"Tallahassee",
    "sg:classifiers":[
        {
            "category":"Real Estate",
            "subcategory":"Real Estate Agent",
            "type":"Services"
        }
    ],
    "sg:phone":"+1 850 219 1440",
    "sg:postcode":"32308",
    "sg:province":"FL",
    "sg:website":"www.anchortallahassee.com",
    "wof:name":"Anchor Realty & Mortgage",
    "wof:placetype":"venue"
},
  "geometry": {"coordinates":[-84.2351,30.46691],"type":"Point"}
}