{
  "type": "Feature",
  "properties": {
    "iso:country":"US",
    "sg:address":"7155 N Blue Angel Pkwy",
    "sg:city":"Pensacola",
    "sg:classifiers":[
        {
            "category":"Building & Trades",
            "subcategory":"Construction",
            "type":"Services"
        }
    ],
    "sg:phone":"+1 850 944 4340",
    "sg:postcode":"32526",
    "sg:province":"FL",
    "sg:tags":[
        "house"
    ],
    "wof:name":"Herschel Horne Guardian",
    "wof:placetype":"venue"
},
  "geometry": {"coordinates":[-87.308252,30.486684],"type":"Point"}
}