{
  "type": "Feature",
  "properties": {
    "addr:full":"440 S Dixie Hwy Coral Gables FL 33146",
    "addr:housenumber":"440",
    "addr:postcode":"33146",
    "addr:street":"S Dixie Hwy",
    "iso:country":"US",
    "sg:address":"440 S Dixie Hwy",
    "sg:city":"Coral Gables",
    "sg:classifiers":[
        {
            "category":"Restaurant",
            "type":"Food & Drink"
        }
    ],
    "sg:phone":"+1 305 665 7020",
    "sg:postcode":"33146",
    "sg:province":"FL",
    "sg:tags":[
        "sushi",
        "bar",
        "japanese"
    ],
    "sg:website":"sakuragables.com/",
    "wof:name":"Sakura Gables Japanese Restaurant",
    "wof:placetype":"venue"
},
  "geometry": {"coordinates":[-80.2621,25.7262],"type":"Point"}
}