{
  "type": "Feature",
  "properties": {
    "iso:country":"US",
    "sg:address":"7333 Beach Blvd",
    "sg:city":"Jacksonville",
    "sg:classifiers":[
        {
            "category":"Real Estate",
            "subcategory":"Real Estate Operator",
            "type":"Services"
        }
    ],
    "sg:phone":"+1 904 725 8633",
    "sg:postcode":"32216",
    "sg:province":"FL",
    "sg:tags":[
        "dwelling"
    ],
    "wof:name":"Southbrook Condominium Assoc",
    "wof:placetype":"venue"
},
  "geometry": {"coordinates":[-81.58215199999999,30.288997],"type":"Point"}
}