{
  "type": "Feature",
  "properties": {
    "iso:country":"US",
    "sg:address":"1620 Mayflower Ct",
    "sg:city":"Winter Park",
    "sg:classifiers":[
        {
            "category":"Health Services",
            "subcategory":"Health Practitioner",
            "type":"Services"
        }
    ],
    "sg:phone":"+1 407 673 3633",
    "sg:postcode":"32792",
    "sg:province":"FL",
    "sg:tags":[
        "therapist",
        "therapy",
        "physical"
    ],
    "wof:name":"Rehab Advantage",
    "wof:placetype":"venue"
},
  "geometry": {"coordinates":[-81.319604,28.603477],"type":"Point"}
}