{
  "type": "Feature",
  "properties": {
    "iso:country":"US",
    "sg:address":"1721 Blanding Blvd",
    "sg:city":"Jacksonville",
    "sg:classifiers":[
        {
            "category":"Building & Trades",
            "subcategory":"Landscaping Services",
            "type":"Services"
        }
    ],
    "sg:phone":"+1 904 388 2700",
    "sg:postcode":"32210",
    "sg:province":"FL",
    "sg:tags":[
        "tree"
    ],
    "wof:name":"Hamilton Lawn & Tree Svc",
    "wof:placetype":"venue"
},
  "geometry": {"coordinates":[-81.724096,30.287672],"type":"Point"}
}