{
  "type": "Feature",
  "properties": {
    "iso:country":"US",
    "sg:address":"7500 NW 25th St",
    "sg:city":"Miami",
    "sg:classifiers":[
        {
            "category":"Shopping",
            "type":"Retail Goods"
        }
    ],
    "sg:phone":"+1 305 477 4250",
    "sg:postcode":"33122",
    "sg:province":"FL",
    "sg:tags":[
        "miscellaneous",
        "store"
    ],
    "wof:name":"Great American Hanger Co",
    "wof:placetype":"venue"
},
  "geometry": {"coordinates":[-80.320548,25.797041],"type":"Point"}
}