{
  "type": "Feature",
  "properties": {
    "iso:country":"US",
    "sg:address":"4333 NW 27th Ave",
    "sg:city":"Miami",
    "sg:classifiers":[
        {
            "category":"Government",
            "subcategory":"Department Of Motor Vehicles",
            "type":"Public Place"
        }
    ],
    "sg:phone":"+1 305 633 0585",
    "sg:postcode":"33142",
    "sg:province":"FL",
    "sg:tags":[
        "refrigeration",
        "truck",
        "equipment"
    ],
    "wof:name":"Thermo King Of Miami",
    "wof:placetype":"venue"
},
  "geometry": {"coordinates":[-80.24035600000001,25.814647],"type":"Point"}
}