{
  "type": "Feature",
  "properties": {
    "iso:country":"US",
    "sg:address":"8579 Woodbriar Dr",
    "sg:city":"Sarasota",
    "sg:classifiers":[
        {
            "category":"Home & Garden",
            "subcategory":"Home Furnishings",
            "type":"Retail Goods"
        }
    ],
    "sg:phone":"+1 941 925 8580",
    "sg:postcode":"34238",
    "sg:province":"FL",
    "wof:name":"Myron Mendelson Suncoast Solar",
    "wof:placetype":"venue"
},
  "geometry": {"coordinates":[-82.472532,27.229136],"type":"Point"}
}