{
  "type": "Feature",
  "properties": {
    "iso:country":"US",
    "sg:address":"4451 Park Blvd",
    "sg:city":"Pinellas Park",
    "sg:classifiers":[
        {
            "category":"Shopping",
            "subcategory":"Used Merchandise",
            "type":"Retail Goods"
        }
    ],
    "sg:phone":"+1 727 545 1945",
    "sg:postcode":"33781",
    "sg:province":"FL",
    "wof:name":"Mazza Tim Furnitures",
    "wof:placetype":"venue"
},
  "geometry": {"coordinates":[-82.69549499999999,27.839293],"type":"Point"}
}