{
  "type": "Feature",
  "properties": {
    "addr:full":"5325 N Lagoon Dr Panama City FL 32408",
    "addr:housenumber":"5325",
    "addr:postcode":"32408",
    "addr:street":"N Lagoon Dr",
    "iso:country":"US",
    "sg:address":"5325 N Lagoon Dr",
    "sg:city":"Panama City",
    "sg:classifiers":[
        {
            "category":"Recreation",
            "type":"Entertainment"
        }
    ],
    "sg:phone":"+1 850 233 8888",
    "sg:postcode":"32408",
    "sg:province":"FL",
    "sg:tags":[
        "guide"
    ],
    "wof:name":"A Reel Commocean Charters",
    "wof:placetype":"venue"
},
  "geometry": {"coordinates":[-85.742693,30.148222],"type":"Point"}
}