{
  "type": "Feature",
  "properties": {
    "iso:country":"US",
    "sg:address":"235 Alcazar Ave",
    "sg:city":"Coral Gables",
    "sg:classifiers":[
        {
            "category":"Cinema",
            "subcategory":"Movie Theater",
            "type":"Entertainment"
        }
    ],
    "sg:phone":"+1 305 445 8877",
    "sg:postcode":"33134",
    "sg:province":"FL",
    "wof:name":"Avante Theatre",
    "wof:placetype":"venue"
},
  "geometry": {"coordinates":[-80.258904,25.752899],"type":"Point"}
}