{
  "type": "Feature",
  "properties": {
    "iso:country":"US",
    "sg:address":"2259 N Washington Blvd",
    "sg:city":"Sarasota",
    "sg:classifiers":[
        {
            "category":"Organizations",
            "subcategory":"Religious Organization",
            "type":"Services"
        }
    ],
    "sg:phone":"+1 941 366 9505",
    "sg:postcode":"34234",
    "sg:province":"FL",
    "sg:tags":[
        "church"
    ],
    "wof:name":"Grace & Mercy Christian Ctr",
    "wof:placetype":"venue"
},
  "geometry": {"coordinates":[-82.530548,27.357062],"type":"Point"}
}