{
  "type": "Feature",
  "properties": {
    "addr:full":"906 Ferndell Rd Orlando FL 32808",
    "addr:housenumber":"906",
    "addr:postcode":"32808",
    "addr:street":"Ferndell Rd",
    "iso:country":"US",
    "sg:address":"906 Ferndell Rd",
    "sg:city":"Orlando",
    "sg:classifiers":[
        {
            "category":"Shopping",
            "subcategory":"Discount & Variety Stores",
            "type":"Retail Goods"
        }
    ],
    "sg:phone":"+1 407 578 9225",
    "sg:postcode":"32808",
    "sg:province":"FL",
    "sg:tags":[
        "merchandise",
        "general"
    ],
    "wof:name":"Gary Pinto Retail Stores",
    "wof:placetype":"venue"
},
  "geometry": {"coordinates":[-81.455904,28.558231],"type":"Point"}
}