{
  "type": "Feature",
  "properties": {
    "addr:full":"3311 7th St Sarasota FL 34237",
    "addr:housenumber":"3311",
    "addr:postcode":"34237",
    "addr:street":"7Th St",
    "iso:country":"US",
    "sg:address":"3311 7th St",
    "sg:city":"Sarasota",
    "sg:classifiers":[
        {
            "category":"Recreation",
            "type":"Entertainment"
        },
        {
            "category":"Manufacturing",
            "subcategory":"Printing",
            "type":"Manufacturing & Wholesale Goods"
        }
    ],
    "sg:phone":"+1 941 954 4563",
    "sg:postcode":"34237",
    "sg:province":"FL",
    "sg:tags":[
        "publishing",
        "guide"
    ],
    "wof:name":"Reelin & Chillin Charters Inc",
    "wof:placetype":"venue"
},
  "geometry": {"coordinates":[-82.503291,27.341878],"type":"Point"}
}