{
  "type": "Feature",
  "properties": {
    "iso:country":"US",
    "sg:address":"220 Live Oaks Blvd",
    "sg:city":"Casselberry",
    "sg:classifiers":[
        {
            "category":"Health Services",
            "subcategory":"Clinic",
            "type":"Services"
        }
    ],
    "sg:phone":"+1 407 767 0039",
    "sg:postcode":"32707",
    "sg:province":"FL",
    "sg:tags":[
        "information",
        "alcoholism",
        "treatment"
    ],
    "wof:name":"Phyllis Oliva Human Service",
    "wof:placetype":"venue"
},
  "geometry": {"coordinates":[-81.34464,28.664548],"type":"Point"}
}