{
  "type": "Feature",
  "properties": {
    "iso:country":"US",
    "sg:address":"13920 58th St N",
    "sg:city":"Clearwater",
    "sg:classifiers":[
        {
            "category":"Shopping",
            "subcategory":"Computers & Home Electronics",
            "type":"Retail Goods"
        }
    ],
    "sg:phone":"+1 727 530 3796",
    "sg:postcode":"33760",
    "sg:province":"FL",
    "sg:tags":[
        "software"
    ],
    "wof:name":"Cash Management Solutions",
    "wof:placetype":"venue"
},
  "geometry": {"coordinates":[-82.712729,27.898915],"type":"Point"}
}