{
  "type": "Feature",
  "properties": {
    "addr:full":"1809 Home Ave Sebring FL 33870",
    "addr:housenumber":"1809",
    "addr:postcode":"33870",
    "addr:street":"Home Ave",
    "iso:country":"US",
    "sg:address":"1809 Home Ave",
    "sg:city":"Sebring",
    "sg:classifiers":[
        {
            "category":"Organizations",
            "subcategory":"Community Association",
            "type":"Services"
        }
    ],
    "sg:phone":"+1 863 385 5415",
    "sg:postcode":"33870",
    "sg:province":"FL",
    "sg:tags":[
        "fraternal"
    ],
    "wof:name":"Sebring Lodge # 249 F & AM",
    "wof:placetype":"venue"
},
  "geometry": {"coordinates":[-81.45384199999999,27.512875],"type":"Point"}
}