{
  "type": "Feature",
  "properties": {
    "iso:country":"US",
    "sg:address":"6 Bannerwood Ln",
    "sg:city":"Palm Coast",
    "sg:classifiers":[
        {
            "category":"Building & Trades",
            "subcategory":"Construction",
            "type":"Services"
        }
    ],
    "sg:phone":"+1 386 447 3709",
    "sg:postcode":"32137",
    "sg:province":"FL",
    "sg:tags":[
        "residential",
        "painting",
        "renovation",
        "contractor"
    ],
    "wof:name":"Professional Construction Svc",
    "wof:placetype":"venue"
},
  "geometry": {"coordinates":[-81.239627,29.569536],"type":"Point"}
}