{
  "type": "Feature",
  "properties": {
    "iso:country":"US",
    "sg:address":"223 Altamonte Commerce Blvd",
    "sg:city":"Altamonte Springs",
    "sg:classifiers":[
        {
            "category":"Wholesale",
            "subcategory":"Auto Parts",
            "type":"Manufacturing & Wholesale Goods"
        }
    ],
    "sg:phone":"+1 407 862 7546",
    "sg:postcode":"32714",
    "sg:province":"FL",
    "wof:name":"Floristar Inc",
    "wof:placetype":"venue"
},
  "geometry": {"coordinates":[-81.39071199999999,28.673641],"type":"Point"}
}