{
  "type": "Feature",
  "properties": {
    "iso:country":"US",
    "sg:address":"4016 Niles Way",
    "sg:city":"St Cloud",
    "sg:classifiers":[
        {
            "category":"Wholesale",
            "subcategory":"Machinery & Supplies",
            "type":"Manufacturing & Wholesale Goods"
        }
    ],
    "sg:phone":"+1 407 957 0000",
    "sg:postcode":"34769",
    "sg:province":"FL",
    "sg:tags":[
        "cleaning"
    ],
    "wof:name":"Hair's Pressure Wash",
    "wof:placetype":"venue"
},
  "geometry": {"coordinates":[-81.31482200000001,28.23711],"type":"Point"}
}