{
  "type": "Feature",
  "properties": {
    "iso:country":"US",
    "sg:address":"7345 SW 41st St",
    "sg:city":"Miami",
    "sg:classifiers":[
        {
            "category":"Wholesale",
            "subcategory":"Home Furnishings",
            "type":"Manufacturing & Wholesale Goods"
        },
        {
            "category":"Wholesale",
            "subcategory":"Electrical",
            "type":"Manufacturing & Wholesale Goods"
        }
    ],
    "sg:phone":"+1 305 261 2848",
    "sg:postcode":"33155",
    "sg:province":"FL",
    "sg:tags":[
        "lighting",
        "lamp",
        "fixture",
        "shades",
        "supply"
    ],
    "wof:name":"E D Lighting Inc",
    "wof:placetype":"venue"
},
  "geometry": {"coordinates":[-80.314215,25.732395],"type":"Point"}
}