{
  "type": "Feature",
  "properties": {
    "addr:full":"301 W Mary Jess Rd Orlando FL 32839",
    "addr:housenumber":"301",
    "addr:postcode":"32839",
    "addr:street":"W Mary Jess Rd",
    "iso:country":"US",
    "sg:address":"301 W Mary Jess Rd",
    "sg:city":"Orlando",
    "sg:classifiers":[
        {
            "category":"Wholesale",
            "subcategory":"Machinery & Supplies",
            "type":"Manufacturing & Wholesale Goods"
        }
    ],
    "sg:phone":"+1 407 852 9033",
    "sg:postcode":"32839",
    "sg:province":"FL",
    "sg:tags":[
        "dry wall",
        "contractor"
    ],
    "wof:name":"Drywall Supply",
    "wof:placetype":"venue"
},
  "geometry": {"coordinates":[-81.375326,28.480093],"type":"Point"}
}