{
  "type": "Feature",
  "properties": {
    "iso:country":"US",
    "sg:address":"3826 Covey Ct",
    "sg:city":"Lakeland",
    "sg:classifiers":[
        {
            "category":"Wholesale",
            "subcategory":"Metals & Minerals",
            "type":"Manufacturing & Wholesale Goods"
        }
    ],
    "sg:phone":"+1 863 646 8062",
    "sg:postcode":"33812",
    "sg:province":"FL",
    "sg:tags":[
        "industrial",
        "center",
        "supply"
    ],
    "wof:name":"Andersen Engineering Corp",
    "wof:placetype":"venue"
},
  "geometry": {"coordinates":[-81.887739,27.960422],"type":"Point"}
}