{
  "type": "Feature",
  "properties": {
    "addr:full":"14143 Stonegate Dr Tampa FL 33624",
    "addr:housenumber":"14143",
    "addr:postcode":"33624",
    "addr:street":"Stonegate Dr",
    "iso:country":"US",
    "sg:address":"14143 Stonegate Dr",
    "sg:city":"Tampa",
    "sg:classifiers":[
        {
            "category":"Insurance",
            "subcategory":"Hazard Insurance",
            "type":"Services"
        }
    ],
    "sg:phone":"+1 813 960 0325",
    "sg:postcode":"33624",
    "sg:province":"FL",
    "wof:name":"Family Benefit",
    "wof:placetype":"venue"
},
  "geometry": {"coordinates":[-82.534339,28.081521],"type":"Point"}
}