{
  "type": "Feature",
  "properties": {
    "addr:full":"1901 9th St W Bradenton FL 34205",
    "addr:housenumber":"1901",
    "addr:postcode":"34205",
    "addr:street":"9Th St W",
    "iso:country":"US",
    "sg:address":"1901 9th St W",
    "sg:city":"Bradenton",
    "sg:classifiers":[
        {
            "category":"Insurance",
            "subcategory":"Insurance Agent",
            "type":"Services"
        }
    ],
    "sg:phone":"+1 941 747 6822",
    "sg:postcode":"34205",
    "sg:province":"FL",
    "sg:tags":[
        "agency"
    ],
    "wof:name":"Cuahonte Insurance Inc",
    "wof:placetype":"venue"
},
  "geometry": {"coordinates":[-82.571235,27.482027],"type":"Point"}
}