{
  "type": "Feature",
  "properties": {
    "iso:country":"US",
    "sg:address":"2250 Irene St",
    "sg:city":"Jacksonville",
    "sg:classifiers":[
        {
            "category":"Government",
            "subcategory":"Office",
            "type":"Public Place"
        }
    ],
    "sg:phone":"+1 904 360 5406",
    "sg:postcode":"32204",
    "sg:province":"FL",
    "sg:tags":[
        "transportation"
    ],
    "wof:name":"Motor Carrier Compliance",
    "wof:placetype":"venue"
},
  "geometry": {"coordinates":[-81.688113,30.321609],"type":"Point"}
}