{
  "type": "Feature",
  "properties": {
    "addr:full":"5421 Little Rd New Port Richey FL 34655",
    "addr:housenumber":"5421",
    "addr:postcode":"34655",
    "addr:street":"Little Rd",
    "iso:country":"US",
    "sg:address":"5421 Little Rd",
    "sg:city":"New Port Richey",
    "sg:classifiers":[
        {
            "category":"Bakery",
            "type":"Food & Drink"
        },
        {
            "category":"Coffee & Tea",
            "type":"Food & Drink"
        },
        {
            "category":"Bagels",
            "type":"Food & Drink"
        },
        {
            "category":"Donuts",
            "type":"Food & Drink"
        }
    ],
    "sg:menulink":"http://www.allmenus.com/fl/new-port-richey/138054-dunkin-donuts/menu/",
    "sg:phone":"+1 727 376 2161",
    "sg:postcode":"34655",
    "sg:province":"FL",
    "sg:tags":[
        "american",
        "pastry"
    ],
    "wof:name":"Dunkin' Donuts",
    "wof:placetype":"venue"
},
  "geometry": {"coordinates":[-82.67095,28.237138],"type":"Point"}
}