{
  "type": "Feature",
  "properties": {
    "iso:country":"US",
    "sg:address":"2800 Discovery Dr",
    "sg:city":"Orlando",
    "sg:classifiers":[
        {
            "category":"Professional",
            "subcategory":"Research",
            "type":"Services"
        }
    ],
    "sg:phone":"+1 407 384 1600",
    "sg:postcode":"32826",
    "sg:province":"FL",
    "sg:tags":[
        "laboratory"
    ],
    "wof:name":"Alcon",
    "wof:placetype":"venue"
},
  "geometry": {"coordinates":[-81.192578,28.584637],"type":"Point"}
}