{
  "type": "Feature",
  "properties": {
    "iso:country":"US",
    "sg:address":"59 Dorset Dr",
    "sg:city":"Kissimmee",
    "sg:classifiers":[
        {
            "category":"Home & Garden",
            "subcategory":"Building Materials",
            "type":"Retail Goods"
        },
        {
            "category":"Home & Garden",
            "subcategory":"Home Furnishings",
            "type":"Retail Goods"
        }
    ],
    "sg:phone":"+1 407 933 1746",
    "sg:postcode":"34758",
    "sg:province":"FL",
    "sg:tags":[
        "installation",
        "drapery"
    ],
    "wof:name":"Fifth Avenue Installations Inc",
    "wof:placetype":"venue"
},
  "geometry": {"coordinates":[-81.490554,28.172091],"type":"Point"}
}