{
  "type": "Feature",
  "properties": {
    "iso:country":"US",
    "sg:address":"22110 Kimble Ave",
    "sg:city":"Port Charlotte",
    "sg:classifiers":[
        {
            "category":"Health Services",
            "subcategory":"Doctor",
            "type":"Services"
        }
    ],
    "sg:phone":"+1 941 627 5151",
    "sg:postcode":"33952",
    "sg:province":"FL",
    "sg:tags":[
        "physician",
        "surgeon"
    ],
    "wof:name":"Seshadri & Seshadri",
    "wof:placetype":"venue"
},
  "geometry": {"coordinates":[-82.087239,26.976271],"type":"Point"}
}