{
  "type": "Feature",
  "properties": {
    "addr:full":"161 Alder Ave Altamonte Springs FL 32714",
    "addr:housenumber":"161",
    "addr:postcode":"32714",
    "addr:street":"Alder Ave",
    "iso:country":"US",
    "sg:address":"161 Alder Ave",
    "sg:city":"Altamonte Springs",
    "sg:classifiers":[
        {
            "category":"Building & Trades",
            "subcategory":"Construction",
            "type":"Services"
        }
    ],
    "sg:phone":"+1 407 788 6695",
    "sg:postcode":"32714",
    "sg:province":"FL",
    "sg:tags":[
        "hanging",
        "contractor"
    ],
    "wof:name":"David Carlson Painting",
    "wof:placetype":"venue"
},
  "geometry": {"coordinates":[-81.424868,28.670839],"type":"Point"}
}