{
  "type": "Feature",
  "properties": {
    "iso:country":"US",
    "sg:address":"2080 Ocean Ridge Cir",
    "sg:city":"Vero Beach",
    "sg:classifiers":[
        {
            "category":"Real Estate",
            "subcategory":"Real Estate Agent",
            "type":"Services"
        }
    ],
    "sg:phone":"+1 772 569 3537",
    "sg:postcode":"32963",
    "sg:province":"FL",
    "wof:name":"Barrier Island Real Estate",
    "wof:placetype":"venue"
},
  "geometry": {"coordinates":[-80.33643600000001,27.600016],"type":"Point"}
}