{
  "type": "Feature",
  "properties": {
    "iso:country":"US",
    "sg:address":"5971 110th Way N",
    "sg:city":"Seminole",
    "sg:classifiers":[
        {
            "category":"Building & Trades",
            "subcategory":"Construction",
            "type":"Services"
        }
    ],
    "sg:phone":"+1 727 320 9663",
    "sg:postcode":"33772",
    "sg:province":"FL",
    "sg:tags":[
        "restoration",
        "cleaning",
        "patio",
        "deck"
    ],
    "wof:name":"Rifle Restoration Inc",
    "wof:placetype":"venue"
},
  "geometry": {"coordinates":[-82.791539,27.826472],"type":"Point"}
}