{
  "type": "Feature",
  "properties": {
    "addr:full":"168 NE 2nd Ave Delray Beach FL 33444",
    "addr:housenumber":"168",
    "addr:postcode":"33444",
    "addr:street":"Ne 2Nd Ave",
    "iso:country":"US",
    "sg:address":"168 NE 2nd Ave",
    "sg:city":"Delray Beach",
    "sg:classifiers":[
        {
            "category":"Retail",
            "subcategory":"Portrait Studio",
            "type":"Services"
        }
    ],
    "sg:phone":"+1 561 274 0007",
    "sg:postcode":"33444",
    "sg:province":"FL",
    "sg:tags":[
        "photographer"
    ],
    "wof:name":"Kevro Imaging",
    "wof:placetype":"venue"
},
  "geometry": {"coordinates":[-80.071212,26.464038],"type":"Point"}
}