{
  "type": "Feature",
  "properties": {
    "addr:full":"6814 Heritage Dr Port Saint Lucie FL 34952",
    "addr:housenumber":"6814",
    "addr:postcode":"34952",
    "addr:street":"Heritage Dr",
    "iso:country":"US",
    "sg:address":"6814 Heritage Dr",
    "sg:city":"Port Saint Lucie",
    "sg:classifiers":[
        {
            "category":"School Buses",
            "type":"Transportation"
        }
    ],
    "sg:phone":"+1 772 464 6411",
    "sg:postcode":"34952",
    "sg:province":"FL",
    "wof:name":"EDS",
    "wof:placetype":"venue"
},
  "geometry": {"coordinates":[-80.327648,27.340491],"type":"Point"}
}