{
  "type": "Feature",
  "properties": {
    "addr:full":"313 Havendale Blvd Auburndale FL 33823",
    "addr:housenumber":"313",
    "addr:postcode":"33823",
    "addr:street":"Havendale Blvd",
    "iso:country":"US",
    "sg:address":"313 Havendale Blvd",
    "sg:city":"Auburndale",
    "sg:classifiers":[
        {
            "category":"Building & Trades",
            "subcategory":"Cleaning & Sanitation",
            "type":"Services"
        }
    ],
    "sg:phone":"+1 863 968 1863",
    "sg:postcode":"33823",
    "sg:province":"FL",
    "sg:tags":[
        "janitor"
    ],
    "wof:name":"Cleaning Zone",
    "wof:placetype":"venue"
},
  "geometry": {"coordinates":[-81.781723,28.057644],"type":"Point"}
}