{
  "type": "Feature",
  "properties": {
    "iso:country":"US",
    "sg:address":"110 Wekiva Park Dr",
    "sg:city":"Sanford",
    "sg:classifiers":[
        {
            "category":"Building & Trades",
            "subcategory":"Construction",
            "type":"Services"
        }
    ],
    "sg:phone":"+1 407 268 9104",
    "sg:postcode":"32771",
    "sg:province":"FL",
    "sg:tags":[
        "general",
        "contractor"
    ],
    "wof:name":"Zuriel Inc",
    "wof:placetype":"venue"
},
  "geometry": {"coordinates":[-81.416166,28.817359],"type":"Point"}
}