{
  "type": "Feature",
  "properties": {
    "iso:country":"US",
    "sg:address":"1057 S Hiawassee Rd",
    "sg:city":"Orlando",
    "sg:classifiers":[
        {
            "category":"Shopping",
            "subcategory":"Hobbies, Toys, & Games",
            "type":"Retail Goods"
        }
    ],
    "sg:phone":"+1 321 239 7281",
    "sg:postcode":"32835",
    "sg:province":"FL",
    "sg:tags":[
        "toy",
        "store",
        "supply"
    ],
    "wof:name":"Abc Toys Corp",
    "wof:placetype":"venue"
},
  "geometry": {"coordinates":[-81.473538,28.52776],"type":"Point"}
}