{
  "type": "Feature",
  "properties": {
    "iso:country":"US",
    "sg:address":"398 E 33rd St Ste 201",
    "sg:city":"Hialeah",
    "sg:classifiers":[
        {
            "category":"Banks & Credit Unions",
            "subcategory":"Financial Services",
            "type":"Services"
        }
    ],
    "sg:phone":"+1 305 883 2227",
    "sg:postcode":"33013",
    "sg:province":"FL",
    "sg:tags":[
        "broker",
        "mortgage"
    ],
    "wof:name":"American Money Market Inc",
    "wof:placetype":"venue"
},
  "geometry": {"coordinates":[-80.27480300000001,25.852301],"type":"Point"}
}