{
  "type": "Feature",
  "properties": {
    "iso:country":"US",
    "sg:address":"12323 SE 87th Ct",
    "sg:city":"Belleview",
    "sg:classifiers":[
        {
            "category":"Arts & Performance",
            "subcategory":"Theater",
            "type":"Entertainment"
        }
    ],
    "sg:phone":"+1 352 817 3530",
    "sg:postcode":"34420",
    "sg:province":"FL",
    "sg:tags":[
        "group"
    ],
    "wof:name":"Beckys Private Pleasures",
    "wof:placetype":"venue"
},
  "geometry": {"coordinates":[-82.008422,29.043317],"type":"Point"}
}