{
  "type": "Feature",
  "properties": {
    "iso:country":"US",
    "sg:address":"1655 20th St",
    "sg:city":"Vero Beach",
    "sg:classifiers":[
        {
            "category":"Real Estate",
            "subcategory":"Real Estate Agent",
            "type":"Services"
        }
    ],
    "sg:phone":"+1 772 569 3053",
    "sg:postcode":"32960",
    "sg:province":"FL",
    "sg:tags":[
        "investment"
    ],
    "wof:name":"27 South Realestate Investors",
    "wof:placetype":"venue"
},
  "geometry": {"coordinates":[-80.4019,27.638564],"type":"Point"}
}