{
  "type": "Feature",
  "properties": {
    "iso:country":"US",
    "sg:address":"3801 NE 207th St",
    "sg:city":"Miami",
    "sg:classifiers":[
        {
            "category":"Government",
            "subcategory":"Office",
            "type":"Public Place"
        }
    ],
    "sg:phone":"+1 305 932 4102",
    "sg:postcode":"33180",
    "sg:province":"FL",
    "sg:tags":[
        "state",
        "program",
        "health"
    ],
    "wof:name":"Health Care Consulting Group",
    "wof:placetype":"venue"
},
  "geometry": {"coordinates":[-80.12638099999999,25.967946],"type":"Point"}
}