{
  "type": "Feature",
  "properties": {
    "iso:country":"US",
    "sg:address":"7135 US Hwy 1",
    "sg:city":"Cocoa",
    "sg:classifiers":[
        {
            "category":"Shopping",
            "subcategory":"Pharmacy",
            "type":"Retail Goods"
        }
    ],
    "sg:phone":"+1 321 631 0300",
    "sg:postcode":"32927",
    "sg:province":"FL",
    "sg:tags":[
        "drug",
        "store"
    ],
    "wof:name":"Family Drug Mart",
    "wof:placetype":"venue"
},
  "geometry": {"coordinates":[-80.76709200000001,28.472888],"type":"Point"}
}