{
  "type": "Feature",
  "properties": {
    "iso:country":"US",
    "sg:address":"5005 17th Ave S",
    "sg:city":"Gulfport",
    "sg:classifiers":[
        {
            "category":"Autos & Motor Vehicles",
            "subcategory":"Auto Supplies",
            "type":"Retail Goods"
        }
    ],
    "sg:phone":"+1 727 321 3638",
    "sg:postcode":"33707",
    "sg:province":"FL",
    "sg:tags":[
        "equipment",
        "racing",
        "car",
        "automobile"
    ],
    "wof:name":"Don Wright Automotive Parts",
    "wof:placetype":"venue"
},
  "geometry": {"coordinates":[-82.70072,27.75384],"type":"Point"}
}