{
  "type": "Feature",
  "properties": {
    "addr:full":"44 W Flagler St Miami FL 33130",
    "addr:housenumber":"44",
    "addr:postcode":"33130",
    "addr:street":"W Flagler St",
    "iso:country":"US",
    "sg:address":"44 W Flagler St",
    "sg:city":"Miami",
    "sg:classifiers":[
        {
            "category":"Professional",
            "subcategory":"Lawyer & Legal Services",
            "type":"Services"
        }
    ],
    "sg:phone":"+1 305 379 8435",
    "sg:postcode":"33130",
    "sg:province":"FL",
    "sg:tags":[
        "attorney",
        "worker",
        "benefit",
        "labor",
        "compensation",
        "employee",
        "law",
        "employment"
    ],
    "wof:name":"Peter S Schwedock PA",
    "wof:placetype":"venue"
},
  "geometry": {"coordinates":[-80.19452200000001,25.774094],"type":"Point"}
}