{
  "type": "Feature",
  "properties": {
    "iso:country":"US",
    "sg:address":"11700 SW 88th St",
    "sg:city":"Miami",
    "sg:classifiers":[
        {
            "category":"Banks & Credit Unions",
            "subcategory":"Bank",
            "type":"Services"
        }
    ],
    "sg:phone":"+1 305 274 5711",
    "sg:postcode":"33186",
    "sg:province":"FL",
    "sg:website":"www.suntrust.com",
    "wof:name":"Suntrust",
    "wof:placetype":"venue"
},
  "geometry": {"coordinates":[-80.384704,25.686143],"type":"Point"}
}