{
  "type": "Feature",
  "properties": {
    "iso:country":"US",
    "sg:address":"4453 Scenic Lake Dr",
    "sg:city":"Orlando",
    "sg:classifiers":[
        {
            "category":"Shopping",
            "subcategory":"Bicycles & Sporting Goods",
            "type":"Retail Goods"
        }
    ],
    "sg:phone":"+1 407 253 2315",
    "sg:postcode":"32808",
    "sg:province":"FL",
    "wof:name":"Women Of Strength & Dignity In",
    "wof:placetype":"venue"
},
  "geometry": {"coordinates":[-81.437451,28.595365],"type":"Point"}
}