{
  "type": "Feature",
  "properties": {
    "iso:country":"US",
    "sg:address":"8656 Eleuthera Ct",
    "sg:city":"Fort Myers",
    "sg:classifiers":[
        {
            "category":"Social Services",
            "type":"Services"
        }
    ],
    "sg:phone":"+1 239 936 6933",
    "sg:postcode":"33907",
    "sg:province":"FL",
    "wof:name":"Leisure Estates Homeowner",
    "wof:placetype":"venue"
},
  "geometry": {"coordinates":[-81.8642,26.568389],"type":"Point"}
}