{
  "type": "Feature",
  "properties": {
    "addr:full":"5555 Collins Ave Miami Beach FL 33140",
    "addr:housenumber":"5555",
    "addr:postcode":"33140",
    "addr:street":"Collins Ave",
    "iso:country":"US",
    "sg:address":"5555 Collins Ave",
    "sg:city":"Miami Beach",
    "sg:classifiers":[
        {
            "category":"Professional",
            "subcategory":"Advertising",
            "type":"Services"
        }
    ],
    "sg:phone":"+1 305 867 9307",
    "sg:postcode":"33140",
    "sg:province":"FL",
    "sg:tags":[
        "distribution"
    ],
    "wof:name":"America Distributors Inc",
    "wof:placetype":"venue"
},
  "geometry": {"coordinates":[-80.12268299999999,25.819981],"type":"Point"}
}