{
  "type": "Feature",
  "properties": {
    "iso:country":"US",
    "sg:address":"519 Tamiami Trl",
    "sg:city":"Venice",
    "sg:classifiers":[
        {
            "category":"Shopping",
            "subcategory":"Pharmacy",
            "type":"Retail Goods"
        }
    ],
    "sg:phone":"+1 941 497 2278",
    "sg:postcode":"34285",
    "sg:province":"FL",
    "sg:tags":[
        "drug",
        "store"
    ],
    "wof:name":"Walgreens",
    "wof:placetype":"venue"
},
  "geometry": {"coordinates":[-82.444278,27.091643],"type":"Point"}
}