{
  "type": "Feature",
  "properties": {
    "addr:full":"16 Central Dr Lake Wales FL 33859",
    "addr:housenumber":"16",
    "addr:postcode":"33859",
    "addr:street":"Central Dr",
    "iso:country":"US",
    "sg:address":"16 Central Dr",
    "sg:city":"Lake Wales",
    "sg:classifiers":[
        {
            "category":"Freight",
            "type":"Transportation"
        }
    ],
    "sg:phone":"+1 863 638 4630",
    "sg:postcode":"33859",
    "sg:province":"FL",
    "sg:tags":[
        "hauling",
        "trucking"
    ],
    "wof:name":"Highlander Enterprises Inc",
    "wof:placetype":"venue"
},
  "geometry": {"coordinates":[-81.59120299999999,27.828005],"type":"Point"}
}