{
  "type": "Feature",
  "properties": {
    "iso:country":"US",
    "sg:address":"11680 SW 92nd St",
    "sg:city":"Miami",
    "sg:classifiers":[
        {
            "category":"Transit Center",
            "subcategory":"Freight",
            "type":"Transportation"
        },
        {
            "category":"Professional",
            "subcategory":"Advertising",
            "type":"Services"
        }
    ],
    "sg:phone":"+1 305 596 1152",
    "sg:postcode":"33176",
    "sg:province":"FL",
    "sg:tags":[
        "outdoor"
    ],
    "wof:name":"The Ad Mobile",
    "wof:placetype":"venue"
},
  "geometry": {"coordinates":[-80.38454299999999,25.683085],"type":"Point"}
}