{
  "type": "Feature",
  "properties": {
    "addr:full":"1219 SW Curtis St Port Saint Lucie FL 34983",
    "addr:housenumber":"1219",
    "addr:postcode":"34983",
    "addr:street":"Sw Curtis St",
    "iso:country":"US",
    "sg:address":"1219 SW Curtis St",
    "sg:city":"Port Saint Lucie",
    "sg:classifiers":[
        {
            "category":"Restaurant",
            "type":"Food & Drink"
        }
    ],
    "sg:phone":"+1 772 878 3634",
    "sg:postcode":"34983",
    "sg:province":"FL",
    "sg:tags":[
        "eating"
    ],
    "wof:name":"WY Subs Inc",
    "wof:placetype":"venue"
},
  "geometry": {"coordinates":[-80.355321,27.301733],"type":"Point"}
}