{
  "type": "Feature",
  "properties": {
    "iso:country":"US",
    "sg:address":"2502 Ranchland Acres Rd",
    "sg:city":"Lakeland",
    "sg:classifiers":[
        {
            "category":"Building & Trades",
            "subcategory":"Construction",
            "type":"Services"
        }
    ],
    "sg:phone":"+1 863 738 0240",
    "sg:postcode":"33809",
    "sg:province":"FL",
    "sg:tags":[
        "hanging",
        "contractor"
    ],
    "wof:name":"Fletchers Painting Service",
    "wof:placetype":"venue"
},
  "geometry": {"coordinates":[-82.002184,28.2204],"type":"Point"}
}