{
  "type": "Feature",
  "properties": {
    "addr:full":"5915 State Road 674 Wimauma FL 33598",
    "addr:housenumber":"5915",
    "addr:postcode":"33598",
    "addr:street":"State Road 674 Wimauma",
    "iso:country":"US",
    "sg:address":"5915 State Road 674",
    "sg:city":"Wimauma",
    "sg:classifiers":[
        {
            "category":"Autos & Motor Vehicles",
            "subcategory":"Auto Supplies",
            "type":"Retail Goods"
        }
    ],
    "sg:phone":"+1 813 634 6054",
    "sg:postcode":"33598",
    "sg:province":"FL",
    "sg:tags":[
        "tire"
    ],
    "wof:name":"Falcon Service",
    "wof:placetype":"venue"
},
  "geometry": {"coordinates":[-82.29766100000001,27.712435],"type":"Point"}
}