{
  "type": "Feature",
  "properties": {
    "iso:country":"US",
    "sg:address":"812 NE 9th Ave",
    "sg:city":"Ocala",
    "sg:classifiers":[
        {
            "category":"Building & Trades",
            "subcategory":"Landscaping Services",
            "type":"Services"
        }
    ],
    "sg:phone":"+1 352 351 6187",
    "sg:postcode":"34470",
    "sg:province":"FL",
    "sg:tags":[
        "tree"
    ],
    "wof:name":"Always Trimming Tree Specs",
    "wof:placetype":"venue"
},
  "geometry": {"coordinates":[-82.128702,29.194307],"type":"Point"}
}