{
  "type": "Feature",
  "properties": {
    "iso:country":"US",
    "sg:address":"7821 N Dale Mabry Hwy",
    "sg:city":"Tampa",
    "sg:classifiers":[
        {
            "category":"Banks & Credit Unions",
            "subcategory":"Bank",
            "type":"Services"
        }
    ],
    "sg:phone":"+1 813 908 5979",
    "sg:postcode":"33614",
    "sg:province":"FL",
    "sg:tags":[
        "loan",
        "real estate"
    ],
    "wof:name":"Eden Rock Mortgage",
    "wof:placetype":"venue"
},
  "geometry": {"coordinates":[-82.50489,28.019715],"type":"Point"}
}