{
  "type": "Feature",
  "properties": {
    "addr:full":"115 E Brandon Blvd Brandon FL 33511",
    "addr:housenumber":"115",
    "addr:postcode":"33511",
    "addr:street":"E Brandon Blvd",
    "iso:country":"US",
    "sg:address":"115 E Brandon Blvd",
    "sg:city":"Brandon",
    "sg:classifiers":[
        {
            "category":"Shopping",
            "subcategory":"Books",
            "type":"Retail Goods"
        }
    ],
    "sg:phone":"+1 813 655 7838",
    "sg:postcode":"33511",
    "sg:province":"FL",
    "sg:tags":[
        "comic"
    ],
    "wof:name":"Milllenium Comics",
    "wof:placetype":"venue"
},
  "geometry": {"coordinates":[-82.284648,27.93767],"type":"Point"}
}