{
  "type": "Feature",
  "properties": {
    "iso:country":"US",
    "sg:address":"17695 Oakwood Ave",
    "sg:city":"Boca Raton",
    "sg:classifiers":[
        {
            "category":"Building & Trades",
            "subcategory":"Construction",
            "type":"Services"
        }
    ],
    "sg:phone":"+1 561 994 0238",
    "sg:postcode":"33487",
    "sg:province":"FL",
    "sg:tags":[
        "house"
    ],
    "wof:name":"Alpha South Construction",
    "wof:placetype":"venue"
},
  "geometry": {"coordinates":[-80.110615,26.413814],"type":"Point"}
}