{
  "type": "Feature",
  "properties": {
    "iso:country":"US",
    "sg:address":"4869 Okeechobee Rd",
    "sg:city":"West Palm Beach",
    "sg:classifiers":[
        {
            "category":"Professional",
            "type":"Services"
        }
    ],
    "sg:phone":"+1 561 697 1858",
    "sg:postcode":"33417",
    "sg:province":"FL",
    "sg:tags":[
        "establishment"
    ],
    "wof:name":"Zzzz Line",
    "wof:placetype":"venue"
},
  "geometry": {"coordinates":[-80.114756,26.706985],"type":"Point"}
}