{
  "type": "Feature",
  "properties": {
    "iso:country":"US",
    "sg:address":"9821 SW 2nd St",
    "sg:city":"Hollywood",
    "sg:classifiers":[
        {
            "category":"Shopping",
            "subcategory":"Clothing, Apparel, & Fashions",
            "type":"Retail Goods"
        }
    ],
    "sg:phone":"+1 954 275 2640",
    "sg:postcode":"33025",
    "sg:province":"FL",
    "sg:tags":[
        "business"
    ],
    "wof:name":"Styles Jiannys Inc",
    "wof:placetype":"venue"
},
  "geometry": {"coordinates":[-80.277198,26.005587],"type":"Point"}
}