{
  "type": "Feature",
  "properties": {
    "iso:country":"US",
    "sg:address":"261 NE 1st St",
    "sg:city":"Miami",
    "sg:classifiers":[
        {
            "category":"Communications",
            "type":"Services"
        }
    ],
    "sg:phone":"+1 305 577 0366",
    "sg:postcode":"33132",
    "sg:province":"FL",
    "sg:tags":[
        "carrier"
    ],
    "wof:name":"Co-Nexus Access Inc",
    "wof:placetype":"venue"
},
  "geometry": {"coordinates":[-80.189019,25.775328],"type":"Point"}
}