{
  "type": "Feature",
  "properties": {
    "iso:country":"US",
    "sg:address":"11579 Sedgemore Dr N",
    "sg:city":"Jacksonville",
    "sg:classifiers":[
        {
            "category":"Building & Trades",
            "subcategory":"Equipment Rental",
            "type":"Services"
        }
    ],
    "sg:phone":"+1 904 268 2623",
    "sg:postcode":"32223",
    "sg:province":"FL",
    "sg:tags":[
        "crane"
    ],
    "wof:name":"Florida Tree Surgery",
    "wof:placetype":"venue"
},
  "geometry": {"coordinates":[-81.637565,30.166462],"type":"Point"}
}