{
  "type": "Feature",
  "properties": {
    "addr:full":"8401 Astronaut Blvd Cape Canaveral FL 32920",
    "addr:housenumber":"8401",
    "addr:postcode":"32920",
    "addr:street":"Astronaut Blvd",
    "iso:country":"US",
    "sg:address":"8401 Astronaut Blvd",
    "sg:city":"Cape Canaveral",
    "sg:classifiers":[
        {
            "category":"Retail",
            "subcategory":"Auto Rental",
            "type":"Services"
        }
    ],
    "sg:phone":"+1 321 784 0634",
    "sg:postcode":"32920",
    "sg:province":"FL",
    "sg:tags":[
        "renting",
        "truck",
        "leasing"
    ],
    "wof:name":"Budget Truck Rental",
    "wof:placetype":"venue"
},
  "geometry": {"coordinates":[-80.608981,28.392512],"type":"Point"}
}