{
  "type": "Feature",
  "properties": {
    "iso:country":"US",
    "sg:address":"4733 NE 12th Ave",
    "sg:city":"Oakland Park",
    "sg:classifiers":[
        {
            "category":"Professional",
            "subcategory":"Advertising",
            "type":"Services"
        }
    ],
    "sg:phone":"+1 954 267 0450",
    "sg:postcode":"33334",
    "sg:province":"FL",
    "sg:tags":[
        "distribution"
    ],
    "sg:website":"www.rti.com",
    "wof:name":"Restaurant Technologies",
    "wof:placetype":"venue"
},
  "geometry": {"coordinates":[-80.13126200000001,26.186235],"type":"Point"}
}