{
  "type": "Feature",
  "properties": {
    "iso:country":"US",
    "sg:address":"2759 Saint Johns Bluff Rd S",
    "sg:city":"Jacksonville",
    "sg:classifiers":[
        {
            "category":"Building & Trades",
            "subcategory":"Electrical",
            "type":"Services"
        }
    ],
    "sg:phone":"+1 904 645 0026",
    "sg:postcode":"32246",
    "sg:province":"FL",
    "sg:tags":[
        "electrical",
        "contractor"
    ],
    "wof:name":"Coastal Electric Company Fla",
    "wof:placetype":"venue"
},
  "geometry": {"coordinates":[-81.525801,30.299027],"type":"Point"}
}