{
  "type": "Feature",
  "properties": {
    "addr:full":"3595 Saint Gaudens Rd Miami FL 33133",
    "addr:housenumber":"3595",
    "addr:postcode":"33133",
    "addr:street":"Saint Gaudens Rd",
    "iso:country":"US",
    "sg:address":"3595 Saint Gaudens Rd",
    "sg:city":"Miami",
    "sg:classifiers":[
        {
            "category":"Communications",
            "subcategory":"Television Station",
            "type":"Services"
        }
    ],
    "sg:phone":"+1 305 461 0011",
    "sg:postcode":"33133",
    "sg:province":"FL",
    "sg:tags":[
        "distributor",
        "program",
        "producer"
    ],
    "wof:name":"Children's Media Resource Inc",
    "wof:placetype":"venue"
},
  "geometry": {"coordinates":[-80.251963,25.7184],"type":"Point"}
}