{
  "type": "Feature",
  "properties": {
    "iso:country":"US",
    "sg:address":"383 NE 69th St",
    "sg:city":"Miami",
    "sg:classifiers":[
        {
            "category":"Home & Garden",
            "subcategory":"Home Furnishings",
            "type":"Retail Goods"
        }
    ],
    "sg:phone":"+1 305 674 0940",
    "sg:postcode":"33138",
    "sg:province":"FL",
    "sg:tags":[
        "mirror"
    ],
    "wof:name":"Indoor Mirror & Glass",
    "wof:placetype":"venue"
},
  "geometry": {"coordinates":[-80.19015899999999,25.838285],"type":"Point"}
}