{
  "type": "Feature",
  "properties": {
    "addr:full":"103 Lewis St Fort Walton Bch FL 32547",
    "addr:housenumber":"103",
    "addr:postcode":"32547",
    "addr:street":"Lewis St",
    "iso:country":"US",
    "sg:address":"103 Lewis St",
    "sg:city":"Fort Walton Bch",
    "sg:classifiers":[
        {
            "category":"Government",
            "subcategory":"Office",
            "type":"Public Place"
        }
    ],
    "sg:phone":"+1 850 833 9160",
    "sg:postcode":"32547",
    "sg:province":"FL",
    "sg:tags":[
        "state",
        "inspection"
    ],
    "wof:name":"Pro Regulation Dept",
    "wof:placetype":"venue"
},
  "geometry": {"coordinates":[-86.638164,30.43957],"type":"Point"}
}