{
  "type": "Feature",
  "properties": {
    "iso:country":"US",
    "sg:address":"1250 Reed Canal Rd",
    "sg:city":"Port Orange",
    "sg:classifiers":[
        {
            "category":"Building & Trades",
            "subcategory":"Construction",
            "type":"Services"
        }
    ],
    "sg:phone":"+1 386 763 8153",
    "sg:postcode":"32129",
    "sg:province":"FL",
    "sg:tags":[
        "general",
        "contractor"
    ],
    "wof:name":"SSW & Bush Contractors",
    "wof:placetype":"venue"
},
  "geometry": {"coordinates":[-81.023173,29.15231],"type":"Point"}
}