{
  "type": "Feature",
  "properties": {
    "iso:country":"US",
    "sg:address":"2242 Sarno Rd",
    "sg:city":"Melbourne",
    "sg:phone":"+1 321 242 5966",
    "sg:postcode":"32935",
    "sg:province":"FL",
    "sg:website":"http://www.fiestaazteca.com",
    "wof:name":"Fiesta Azteca Mexican Restaurant",
    "wof:placetype":"venue"
},
  "geometry": {"coordinates":[-80.65796,28.12167],"type":"Point"}
}