{
  "type": "Feature",
  "properties": {
    "addr:full":"4144 W Main St Wauchula FL 33873",
    "addr:housenumber":"4144",
    "addr:postcode":"33873",
    "addr:street":"W Main St",
    "iso:country":"US",
    "sg:address":"4144 W Main St",
    "sg:city":"Wauchula",
    "sg:classifiers":[
        {
            "category":"Farming",
            "subcategory":"Farm",
            "type":"Manufacturing & Wholesale Goods"
        }
    ],
    "sg:phone":"+1 863 735 8593",
    "sg:postcode":"33873",
    "sg:province":"FL",
    "sg:tags":[
        "crop",
        "general"
    ],
    "wof:name":"Moore Farms Inc",
    "wof:placetype":"venue"
},
  "geometry": {"coordinates":[-81.871534,27.493983],"type":"Point"}
}