{
  "type": "Feature",
  "properties": {
    "iso:country":"US",
    "sg:address":"4300 Alton Rd",
    "sg:city":"Miami Beach",
    "sg:classifiers":[
        {
            "category":"Health Services",
            "subcategory":"Doctor",
            "type":"Services"
        }
    ],
    "sg:phone":"+1 305 538 0339",
    "sg:postcode":"33140",
    "sg:province":"FL",
    "sg:tags":[
        "medical"
    ],
    "wof:name":"Herbert L Rothman MD PA",
    "wof:placetype":"venue"
},
  "geometry": {"coordinates":[-80.13758799999999,25.815531],"type":"Point"}
}