{
  "type": "Feature",
  "properties": {
    "iso:country":"US",
    "sg:address":"7111 Grand National Dr",
    "sg:city":"Orlando",
    "sg:classifiers":[
        {
            "category":"Shopping",
            "subcategory":"Stationery & Office Supplies",
            "type":"Retail Goods"
        },
        {
            "category":"Wholesale",
            "subcategory":"Office Equipment",
            "type":"Manufacturing & Wholesale Goods"
        }
    ],
    "sg:phone":"+1 407 264 0299",
    "sg:postcode":"32819",
    "sg:province":"FL",
    "sg:tags":[
        "register",
        "autographic"
    ],
    "wof:name":"North American Office Solutions",
    "wof:placetype":"venue"
},
  "geometry": {"coordinates":[-81.45622299999999,28.458235],"type":"Point"}
}