{
  "type": "Feature",
  "properties": {
    "iso:country":"US",
    "sg:address":"12354 SW 263rd Ter",
    "sg:city":"Homestead",
    "sg:classifiers":[
        {
            "category":"Building & Trades",
            "subcategory":"Electrical",
            "type":"Services"
        }
    ],
    "sg:phone":"+1 305 258 2016",
    "sg:postcode":"33032",
    "sg:province":"FL",
    "sg:tags":[
        "installation"
    ],
    "wof:name":"Jeffrey A Bellville Instltn",
    "wof:placetype":"venue"
},
  "geometry": {"coordinates":[-80.39150600000001,25.522667],"type":"Point"}
}