{
  "type": "Feature",
  "properties": {
    "iso:country":"US",
    "sg:address":"359 Ellamar Rd",
    "sg:city":"West Palm Beach",
    "sg:classifiers":[
        {
            "category":"Professional",
            "subcategory":"Business Services",
            "type":"Services"
        }
    ],
    "sg:phone":"+1 561 628 4153",
    "sg:postcode":"33405",
    "sg:province":"FL",
    "wof:name":"Patton Technology Solutions",
    "wof:placetype":"venue"
},
  "geometry": {"coordinates":[-80.053635,26.662632],"type":"Point"}
}