{
  "type": "Feature",
  "properties": {
    "iso:country":"US",
    "sg:address":"9601 NE 2nd Ave",
    "sg:city":"Miami Shores",
    "sg:classifiers":[
        {
            "category":"Building & Trades",
            "subcategory":"Locksmith",
            "type":"Services"
        }
    ],
    "sg:phone":"+1 305 424 5079",
    "sg:postcode":"33138",
    "sg:province":"FL",
    "sg:tags":[
        "key"
    ],
    "wof:name":"0 # 0 & 0 1 Emergency A 24 Hour A Locksmith",
    "wof:placetype":"venue"
},
  "geometry": {"coordinates":[-80.19327800000001,25.86357],"type":"Point"}
}