{
  "type": "Feature",
  "properties": {
    "iso:country":"US",
    "sg:address":"810 N Ridgewood Dr",
    "sg:city":"Sebring",
    "sg:classifiers":[
        {
            "category":"Building & Trades",
            "subcategory":"Construction",
            "type":"Services"
        }
    ],
    "sg:phone":"+1 863 385 3309",
    "sg:postcode":"33870",
    "sg:province":"FL",
    "sg:tags":[
        "roofing",
        "contractor"
    ],
    "wof:name":"Patriot Roofing",
    "wof:placetype":"venue"
},
  "geometry": {"coordinates":[-81.438694,27.502739],"type":"Point"}
}