{
  "type": "Feature",
  "properties": {
    "addr:full":"6412 14th St W Bradenton FL 34207",
    "addr:housenumber":"6412",
    "addr:postcode":"34207",
    "addr:street":"14Th St W",
    "iso:country":"US",
    "sg:address":"6412 14th St W",
    "sg:city":"Bradenton",
    "sg:classifiers":[
        {
            "category":"Recreation",
            "type":"Entertainment"
        }
    ],
    "sg:phone":"+1 941 753 3399",
    "sg:postcode":"34207",
    "sg:province":"FL",
    "wof:name":"Cheer Nation",
    "wof:placetype":"venue"
},
  "geometry": {"coordinates":[-82.57556,27.427757],"type":"Point"}
}