{
  "type": "Feature",
  "properties": {
    "addr:full":"810 Pinebrook Rd Venice FL 34285",
    "addr:housenumber":"810",
    "addr:postcode":"34285",
    "addr:street":"Pinebrook Rd",
    "iso:country":"US",
    "sg:address":"810 Pinebrook Rd",
    "sg:city":"Venice",
    "sg:classifiers":[
        {
            "category":"Banks & Credit Unions",
            "subcategory":"Investment Brokerage",
            "type":"Services"
        }
    ],
    "sg:phone":"+1 941 484 3983",
    "sg:postcode":"34285",
    "sg:province":"FL",
    "sg:tags":[
        "security"
    ],
    "wof:name":"Edward Jones Co",
    "wof:placetype":"venue"
},
  "geometry": {"coordinates":[-82.417374,27.100858],"type":"Point"}
}