{
  "type": "Feature",
  "properties": {
    "iso:country":"US",
    "sg:address":"1145 Golfview Ave",
    "sg:city":"Bartow",
    "sg:classifiers":[
        {
            "category":"Real Estate",
            "subcategory":"Real Estate Agent",
            "type":"Services"
        }
    ],
    "sg:phone":"+1 863 534 3107",
    "sg:postcode":"33830",
    "sg:province":"FL",
    "wof:name":"Maxie Washington Jr",
    "wof:placetype":"venue"
},
  "geometry": {"coordinates":[-81.822456,27.885054],"type":"Point"}
}