{
  "type": "Feature",
  "properties": {
    "addr:full":"369 Century Dr Marco Island FL 34145",
    "addr:housenumber":"369",
    "addr:postcode":"34145",
    "addr:street":"Century Dr",
    "iso:country":"US",
    "sg:address":"369 Century Dr",
    "sg:city":"Marco Island",
    "sg:classifiers":[
        {
            "category":"Wholesale",
            "subcategory":"Office Equipment",
            "type":"Manufacturing & Wholesale Goods"
        }
    ],
    "sg:phone":"+1 239 642 0088",
    "sg:postcode":"34145",
    "sg:province":"FL",
    "sg:tags":[
        "product",
        "copy",
        "machine",
        "used",
        "new",
        "retail"
    ],
    "wof:name":"Trigon Laser Technology",
    "wof:placetype":"venue"
},
  "geometry": {"coordinates":[-81.73284200000001,25.945936],"type":"Point"}
}