{
  "type": "Feature",
  "properties": {
    "addr:full":"9307 120th Way Seminole FL 33772",
    "addr:housenumber":"9307",
    "addr:postcode":"33772",
    "addr:street":"120Th Way",
    "iso:country":"US",
    "sg:address":"9307 120th Way",
    "sg:city":"Seminole",
    "sg:classifiers":[
        {
            "category":"Professional",
            "subcategory":"Employment Agencies",
            "type":"Services"
        }
    ],
    "sg:phone":"+1 727 399 8448",
    "sg:postcode":"33772",
    "sg:province":"FL",
    "sg:tags":[
        "opportunity"
    ],
    "wof:name":"Executive Search",
    "wof:placetype":"venue"
},
  "geometry": {"coordinates":[-82.805582,27.858239],"type":"Point"}
}