{
  "type": "Feature",
  "properties": {
    "addr:full":"100 Long Point Rd Melbourne Beach FL 32951",
    "addr:housenumber":"100",
    "addr:postcode":"32951",
    "addr:street":"Long Point Rd",
    "iso:country":"US",
    "sg:address":"100 Long Point Rd",
    "sg:city":"Melbourne Beach",
    "sg:classifiers":[
        {
            "category":"Shopping",
            "subcategory":"Bicycles & Sporting Goods",
            "type":"Retail Goods"
        }
    ],
    "sg:phone":"+1 321 984 4131",
    "sg:postcode":"32951",
    "sg:province":"FL",
    "wof:name":"Long Point Bait & Tackle",
    "wof:placetype":"venue"
},
  "geometry": {"coordinates":[-80.460292,27.882965],"type":"Point"}
}