{
  "type": "Feature",
  "properties": {
    "iso:country":"US",
    "sg:address":"561 E Duval St",
    "sg:city":"Lake City",
    "sg:classifiers":[
        {
            "category":"Retail",
            "subcategory":"Auto Repair",
            "type":"Services"
        }
    ],
    "sg:phone":"+1 386 758 0038",
    "sg:postcode":"32055",
    "sg:province":"FL",
    "sg:tags":[
        "automotive"
    ],
    "wof:name":"Cedric Crays Performance",
    "wof:placetype":"venue"
},
  "geometry": {"coordinates":[-82.63254499999999,30.189363],"type":"Point"}
}