{
  "type": "Feature",
  "properties": {
    "addr:full":"2141 Loch Rane Blvd Orange Park FL 32073",
    "addr:housenumber":"2141",
    "addr:postcode":"32073",
    "addr:street":"Loch Rane Blvd",
    "iso:country":"US",
    "sg:address":"2141 Loch Rane Blvd",
    "sg:city":"Orange Park",
    "sg:classifiers":[
        {
            "category":"Organizations",
            "subcategory":"Religious Organization",
            "type":"Services"
        }
    ],
    "sg:phone":"+1 904 213 1082",
    "sg:postcode":"32073",
    "sg:province":"FL",
    "sg:tags":[
        "church"
    ],
    "wof:name":"St Paul Church",
    "wof:placetype":"venue"
},
  "geometry": {"coordinates":[-81.74903999999999,30.16446],"type":"Point"}
}