{
  "type": "Feature",
  "properties": {
    "addr:full":"342 NW Archer Ave Port Saint Lucie FL 34983",
    "addr:housenumber":"342",
    "addr:postcode":"34983",
    "addr:street":"Nw Archer Ave",
    "iso:country":"US",
    "sg:address":"342 NW Archer Ave",
    "sg:city":"Port Saint Lucie",
    "sg:classifiers":[
        {
            "category":"Freight",
            "type":"Transportation"
        }
    ],
    "sg:phone":"+1 772 871 6744",
    "sg:postcode":"34983",
    "sg:province":"FL",
    "sg:tags":[
        "operator",
        "local",
        "trucking"
    ],
    "wof:name":"Sicnarf Reliable Courier",
    "wof:placetype":"venue"
},
  "geometry": {"coordinates":[-80.357749,27.337105],"type":"Point"}
}