{
  "type": "Feature",
  "properties": {
    "iso:country":"US",
    "sg:address":"2711 W Sunrise Blvd",
    "sg:city":"Fort Lauderdale",
    "sg:classifiers":[
        {
            "category":"Retail",
            "subcategory":"Repair Shop",
            "type":"Services"
        }
    ],
    "sg:phone":"+1 954 446 7146",
    "sg:postcode":"33311",
    "sg:province":"FL",
    "sg:tags":[
        "lock",
        "locksmith"
    ],
    "wof:name":"Emergency Locksmiths",
    "wof:placetype":"venue"
},
  "geometry": {"coordinates":[-80.180313,26.13638],"type":"Point"}
}