{
  "type": "Feature",
  "properties": {
    "iso:country":"US",
    "sg:address":"4724 Golden Gate Pkwy",
    "sg:city":"Naples",
    "sg:classifiers":[
        {
            "category":"Organizations",
            "subcategory":"Religious Organization",
            "type":"Services"
        }
    ],
    "sg:phone":"+1 239 793 3965",
    "sg:postcode":"34116",
    "sg:province":"FL",
    "sg:tags":[
        "a",
        "christian",
        "bilingual",
        "church"
    ],
    "wof:name":"Ministerio Mision Posible",
    "wof:placetype":"venue"
},
  "geometry": {"coordinates":[-81.702461,26.183216],"type":"Point"}
}