{
  "type": "Feature",
  "properties": {
    "addr:full":"3261 Leprechaun Ln Palm Harbor FL 34683",
    "addr:housenumber":"3261",
    "addr:postcode":"34683",
    "addr:street":"Leprechaun Ln",
    "iso:country":"US",
    "sg:address":"3261 Leprechaun Ln",
    "sg:city":"Palm Harbor",
    "sg:classifiers":[
        {
            "category":"Wholesale",
            "subcategory":"Chemicals & Plastics",
            "type":"Manufacturing & Wholesale Goods"
        }
    ],
    "sg:phone":"+1 727 786 2979",
    "sg:postcode":"34683",
    "sg:province":"FL",
    "wof:name":"Auto Trust Inc",
    "wof:placetype":"venue"
},
  "geometry": {"coordinates":[-82.75209599999999,28.099675],"type":"Point"}
}