{
  "type": "Feature",
  "properties": {
    "addr:full":"3619 Percival Ave Miami FL 33133",
    "addr:housenumber":"3619",
    "addr:postcode":"33133",
    "addr:street":"Percival Ave",
    "iso:country":"US",
    "sg:address":"3619 Percival Ave",
    "sg:city":"Miami",
    "sg:classifiers":[
        {
            "category":"Health Services",
            "subcategory":"Doctor",
            "type":"Services"
        }
    ],
    "sg:phone":"+1 305 461 5371",
    "sg:postcode":"33133",
    "sg:province":"FL",
    "sg:tags":[
        "medical"
    ],
    "wof:name":"Dazelle D Simpson MD PA",
    "wof:placetype":"venue"
},
  "geometry": {"coordinates":[-80.253389,25.730501],"type":"Point"}
}