{
  "type": "Feature",
  "properties": {
    "iso:country":"US",
    "sg:address":"505 Jason Dr",
    "sg:city":"Lady Lake",
    "sg:classifiers":[
        {
            "category":"Banks & Credit Unions",
            "subcategory":"Investment Brokerage",
            "type":"Services"
        }
    ],
    "sg:phone":"+1 352 750 0977",
    "sg:postcode":"32159",
    "sg:province":"FL",
    "sg:tags":[
        "a",
        "firm",
        "operates",
        "as",
        "brokerage",
        "security",
        "insurance"
    ],
    "wof:name":"Calton & Associates Inc",
    "wof:placetype":"venue"
},
  "geometry": {"coordinates":[-81.933857,28.941159],"type":"Point"}
}