{
  "type": "Feature",
  "properties": {
    "iso:country":"US",
    "sg:address":"1335 SW 86th Ct",
    "sg:city":"Miami",
    "sg:classifiers":[
        {
            "category":"Home & Garden",
            "subcategory":"Furniture",
            "type":"Retail Goods"
        }
    ],
    "sg:phone":"+1 305 264 8925",
    "sg:postcode":"33144",
    "sg:province":"FL",
    "sg:tags":[
        "cabinet"
    ],
    "wof:name":"Cabinet Shack Inc",
    "wof:placetype":"venue"
},
  "geometry": {"coordinates":[-80.334901,25.757507],"type":"Point"}
}