{
  "type": "Feature",
  "properties": {
    "iso:country":"US",
    "sg:address":"1217 Pleasantview Dr",
    "sg:city":"Apopka",
    "sg:classifiers":[
        {
            "category":"Building & Trades",
            "subcategory":"Construction",
            "type":"Services"
        }
    ],
    "sg:phone":"+1 407 886 4268",
    "sg:postcode":"32703",
    "sg:province":"FL",
    "sg:tags":[
        "repair",
        "handyman",
        "maintenance",
        "home"
    ],
    "wof:name":"Dave Clark",
    "wof:placetype":"venue"
},
  "geometry": {"coordinates":[-81.487987,28.65956],"type":"Point"}
}