{
  "type": "Feature",
  "properties": {
    "iso:country":"US",
    "sg:address":"7230 Lake Circle Dr",
    "sg:city":"Margate",
    "sg:classifiers":[
        {
            "category":"Real Estate",
            "subcategory":"Real Estate Services",
            "type":"Services"
        }
    ],
    "sg:phone":"+1 954 971 1719",
    "sg:postcode":"33063",
    "sg:province":"FL",
    "sg:tags":[
        "management",
        "condominium"
    ],
    "wof:name":"Operating Association For Palm Lakes Condominium Inc",
    "wof:placetype":"venue"
},
  "geometry": {"coordinates":[-80.22389699999999,26.233541],"type":"Point"}
}