{
  "type": "Feature",
  "properties": {
    "addr:full":"2495 W 80th St Hialeah FL 33016",
    "addr:housenumber":"2495",
    "addr:postcode":"33016",
    "addr:street":"W 80Th St",
    "iso:country":"US",
    "sg:address":"2495 W 80th St",
    "sg:city":"Hialeah",
    "sg:classifiers":[
        {
            "category":"Manufacturing",
            "subcategory":"Printing",
            "type":"Manufacturing & Wholesale Goods"
        }
    ],
    "sg:phone":"+1 305 556 5355",
    "sg:postcode":"33016",
    "sg:province":"FL",
    "sg:tags":[
        "news",
        "publication"
    ],
    "wof:name":"ATC Distribution Svc",
    "wof:placetype":"venue"
},
  "geometry": {"coordinates":[-80.333752,25.895243],"type":"Point"}
}