{
  "type": "Feature",
  "properties": {
    "addr:full":"61 Willow Rd Jupiter FL 33469",
    "addr:housenumber":"61",
    "addr:postcode":"33469",
    "addr:street":"Willow Rd",
    "iso:country":"US",
    "sg:address":"61 Willow Rd",
    "sg:city":"Jupiter",
    "sg:classifiers":[
        {
            "category":"Building & Trades",
            "subcategory":"Construction",
            "type":"Services"
        }
    ],
    "sg:phone":"+1 561 743 5922",
    "sg:postcode":"33469",
    "sg:province":"FL",
    "sg:tags":[
        "contractor"
    ],
    "wof:name":"Bonardi Drywall",
    "wof:placetype":"venue"
},
  "geometry": {"coordinates":[-80.091668,26.96082],"type":"Point"}
}