{
  "type": "Feature",
  "properties": {
    "iso:country":"US",
    "sg:address":"5805 Blue Lagoon Dr",
    "sg:city":"Miami",
    "sg:classifiers":[
        {
            "category":"Wholesale",
            "subcategory":"Apparel",
            "type":"Manufacturing & Wholesale Goods"
        }
    ],
    "sg:phone":"+1 305 260 0949",
    "sg:postcode":"33126",
    "sg:province":"FL",
    "sg:tags":[
        "dry"
    ],
    "wof:name":"Norinco North America Inc",
    "wof:placetype":"venue"
},
  "geometry": {"coordinates":[-80.290279,25.782366],"type":"Point"}
}