{
  "type": "Feature",
  "properties": {
    "iso:country":"US",
    "sg:address":"1116 Gifford Ave S",
    "sg:city":"Lehigh Acres",
    "sg:classifiers":[
        {
            "category":"Building & Trades",
            "subcategory":"Construction",
            "type":"Services"
        }
    ],
    "sg:phone":"+1 239 368 5842",
    "sg:postcode":"33936",
    "sg:province":"FL",
    "sg:tags":[
        "house"
    ],
    "wof:name":"Professional Repairs & Rmdlg",
    "wof:placetype":"venue"
},
  "geometry": {"coordinates":[-81.646901,26.58541],"type":"Point"}
}