{
  "type": "Feature",
  "properties": {
    "iso:country":"US",
    "sg:address":"6241 Ridge Rd",
    "sg:city":"Port Richey",
    "sg:classifiers":[
        {
            "category":"Shopping",
            "type":"Retail Goods"
        }
    ],
    "sg:phone":"+1 727 842 6343",
    "sg:postcode":"34668",
    "sg:province":"FL",
    "sg:tags":[
        "machinery",
        "merchandise"
    ],
    "wof:name":"Ace Pump Co Inc",
    "wof:placetype":"venue"
},
  "geometry": {"coordinates":[-82.71050200000001,28.280687],"type":"Point"}
}