{
  "type": "Feature",
  "properties": {
    "iso:country":"US",
    "sg:address":"5771 NE 14th Ave",
    "sg:city":"Fort Lauderdale",
    "sg:classifiers":[
        {
            "category":"Wholesale",
            "subcategory":"Machinery & Supplies",
            "type":"Manufacturing & Wholesale Goods"
        },
        {
            "category":"Autos & Motor Vehicles",
            "subcategory":"Automobile Sales",
            "type":"Retail Goods"
        }
    ],
    "sg:phone":"+1 954 717 9997",
    "sg:postcode":"33334",
    "sg:province":"FL",
    "sg:tags":[
        "equipment",
        "aircraft",
        "parts"
    ],
    "sg:website":"www.xsgroup.com",
    "wof:name":"X S Group Inc",
    "wof:placetype":"venue"
},
  "geometry": {"coordinates":[-80.131561,26.201575],"type":"Point"}
}