{
  "type": "Feature",
  "properties": {
    "addr:full":"8801 N Kendall Dr Miami FL 33176",
    "addr:housenumber":"8801",
    "addr:postcode":"33176",
    "addr:street":"N Kendall Dr",
    "iso:country":"US",
    "sg:address":"8801 N Kendall Dr",
    "sg:city":"Miami",
    "sg:classifiers":[
        {
            "category":"Wholesale",
            "subcategory":"Toys & Hobbies",
            "type":"Manufacturing & Wholesale Goods"
        }
    ],
    "sg:phone":"+1 305 630 9257",
    "sg:postcode":"33176",
    "sg:province":"FL",
    "sg:tags":[
        "wholesaler"
    ],
    "wof:name":"Miami Wholesales",
    "wof:placetype":"venue"
},
  "geometry": {"coordinates":[-80.336991,25.687992],"type":"Point"}
}