{
  "type": "Feature",
  "properties": {
    "addr:full":"7820 113th St Seminole FL 33772",
    "addr:housenumber":"7820",
    "addr:postcode":"33772",
    "addr:street":"113Th St",
    "iso:country":"US",
    "sg:address":"7820 113th St",
    "sg:city":"Seminole",
    "sg:classifiers":[
        {
            "category":"Restaurant",
            "type":"Food & Drink"
        }
    ],
    "sg:menulink":"http://www.allmenus.com/fl/boca-ciega/152641-boston-market/menu/",
    "sg:phone":"+1 727 319 3911",
    "sg:postcode":"33772",
    "sg:province":"FL",
    "sg:tags":[
        "barbecue",
        "american",
        "soup"
    ],
    "wof:name":"Boston Market",
    "wof:placetype":"venue"
},
  "geometry": {"coordinates":[-82.795765,27.842724],"type":"Point"}
}