{
  "type": "Feature",
  "properties": {
    "addr:full":"7432 Wimpole Dr New Port Richey FL 34655",
    "addr:housenumber":"7432",
    "addr:postcode":"34655",
    "addr:street":"Wimpole Dr",
    "iso:country":"US",
    "sg:address":"7432 Wimpole Dr",
    "sg:city":"New Port Richey",
    "sg:classifiers":[
        {
            "category":"Local Transit",
            "type":"Transportation"
        }
    ],
    "sg:phone":"+1 727 376 2400",
    "sg:postcode":"34655",
    "sg:province":"FL",
    "wof:name":"TLC Transportation Svc",
    "wof:placetype":"venue"
},
  "geometry": {"coordinates":[-82.69681799999999,28.19455],"type":"Point"}
}