{
  "type": "Feature",
  "properties": {
    "iso:country":"US",
    "sg:address":"1248 E Fowler Ave",
    "sg:city":"Tampa",
    "sg:classifiers":[
        {
            "category":"Food & Beverages",
            "subcategory":"Meat & Fish",
            "type":"Retail Goods"
        }
    ],
    "sg:phone":"+1 813 971 8447",
    "sg:postcode":"33612",
    "sg:province":"FL",
    "wof:name":"Origi Hon Baked Ham Co",
    "wof:placetype":"venue"
},
  "geometry": {"coordinates":[-82.445834,28.054588],"type":"Point"}
}