{
  "type": "Feature",
  "properties": {
    "iso:country":"US",
    "sg:address":"3505 NW 17th Ave",
    "sg:city":"Miami",
    "sg:classifiers":[
        {
            "category":"Shopping",
            "subcategory":"Clothing, Apparel, & Fashions",
            "type":"Retail Goods"
        },
        {
            "category":"Personal",
            "type":"Services"
        }
    ],
    "sg:phone":"+1 305 635 8575",
    "sg:postcode":"33142",
    "sg:province":"FL",
    "sg:tags":[
        "tailor",
        "alteration",
        "sewing"
    ],
    "wof:name":"Aquino Tailor",
    "wof:placetype":"venue"
},
  "geometry": {"coordinates":[-80.223682,25.808724],"type":"Point"}
}