{
  "type": "Feature",
  "properties": {
    "iso:country":"US",
    "sg:address":"900 Manatee Way",
    "sg:city":"Hollywood",
    "sg:classifiers":[
        {
            "category":"Professional",
            "subcategory":"Management & Consulting",
            "type":"Services"
        }
    ],
    "sg:phone":"+1 954 458 9564",
    "sg:postcode":"33019",
    "sg:province":"FL",
    "sg:tags":[
        "retail",
        "direct",
        "sales"
    ],
    "wof:name":"Natures Best Inc",
    "wof:placetype":"venue"
},
  "geometry": {"coordinates":[-80.123577,26.002856],"type":"Point"}
}