{
  "type": "Feature",
  "properties": {
    "addr:full":"650 SE Monterey Rd Stuart FL 34994",
    "addr:housenumber":"650",
    "addr:postcode":"34994",
    "addr:street":"Se Monterey Rd",
    "iso:country":"US",
    "sg:address":"650 SE Monterey Rd",
    "sg:city":"Stuart",
    "sg:classifiers":[
        {
            "category":"Shopping",
            "subcategory":"Clothing, Apparel, & Fashions",
            "type":"Retail Goods"
        }
    ],
    "sg:phone":"+1 772 286 0099",
    "sg:postcode":"34994",
    "sg:province":"FL",
    "sg:tags":[
        "tack",
        "boot",
        "western",
        "english"
    ],
    "wof:name":"West of Ol England Inc",
    "wof:placetype":"venue"
},
  "geometry": {"coordinates":[-80.244356,27.175691],"type":"Point"}
}