{
  "type": "Feature",
  "properties": {
    "addr:full":"550 NE 43rd St Boca Raton FL 33431",
    "addr:housenumber":"550",
    "addr:postcode":"33431",
    "addr:street":"Ne 43Rd St",
    "iso:country":"US",
    "sg:address":"550 NE 43rd St",
    "sg:city":"Boca Raton",
    "sg:classifiers":[
        {
            "category":"Real Estate",
            "subcategory":"Real Estate Operator",
            "type":"Services"
        }
    ],
    "sg:phone":"+1 561 368 9760",
    "sg:postcode":"33431",
    "sg:province":"FL",
    "sg:tags":[
        "apartment"
    ],
    "wof:name":"Boca Winds Apartments",
    "wof:placetype":"venue"
},
  "geometry": {"coordinates":[-80.077472,26.388323],"type":"Point"}
}