{
  "type": "Feature",
  "properties": {
    "iso:country":"US",
    "sg:address":"18789 Biscayne Blvd",
    "sg:city":"Aventura",
    "sg:classifiers":[
        {
            "category":"Shopping",
            "subcategory":"Bridal",
            "type":"Retail Goods"
        }
    ],
    "sg:phone":"+1 305 682 1687",
    "sg:postcode":"33180",
    "sg:province":"FL",
    "wof:name":"Nelly's Fashions",
    "wof:placetype":"venue"
},
  "geometry": {"coordinates":[-80.146698,25.949499],"type":"Point"}
}