{
  "type": "Feature",
  "properties": {
    "iso:country":"US",
    "sg:address":"7200 Aloma Ave Ste D",
    "sg:city":"Winter Park",
    "sg:classifiers":[
        {
            "category":"Banks & Credit Unions",
            "subcategory":"Bank",
            "type":"Services"
        }
    ],
    "sg:phone":"+1 407 678 3443",
    "sg:postcode":"32792",
    "sg:province":"FL",
    "wof:name":"Tran Tony Insurance Agency",
    "wof:placetype":"venue"
},
  "geometry": {"coordinates":[-81.292503,28.607599],"type":"Point"}
}