{
  "type": "Feature",
  "properties": {
    "addr:full":"2850 Allen Hill Ave Melbourne FL 32940",
    "addr:housenumber":"2850",
    "addr:postcode":"32940",
    "addr:street":"Allen Hill Ave",
    "iso:country":"US",
    "sg:address":"2850 Allen Hill Ave",
    "sg:city":"Melbourne",
    "sg:classifiers":[
        {
            "category":"Shopping",
            "subcategory":"Bicycles & Sporting Goods",
            "type":"Retail Goods"
        }
    ],
    "sg:phone":"+1 321 799 9822",
    "sg:postcode":"32940",
    "sg:province":"FL",
    "sg:tags":[
        "surfboard"
    ],
    "wof:name":"Lightwave Surfboards",
    "wof:placetype":"venue"
},
  "geometry": {"coordinates":[-80.66642299999999,28.213787],"type":"Point"}
}