{
  "type": "Feature",
  "properties": {
    "iso:country":"US",
    "sg:address":"415 Parque Dr",
    "sg:city":"Ormond Beach",
    "sg:classifiers":[
        {
            "category":"Building & Trades",
            "subcategory":"Construction",
            "type":"Services"
        }
    ],
    "sg:phone":"+1 386 672 9949",
    "sg:postcode":"32174",
    "sg:province":"FL",
    "sg:tags":[
        "maker",
        "cabinet"
    ],
    "wof:name":"B K Custom Kitchen Cabinets",
    "wof:placetype":"venue"
},
  "geometry": {"coordinates":[-81.05898000000001,29.273738],"type":"Point"}
}