{
  "type": "Feature",
  "properties": {
    "addr:full":"5509 Grand Blvd New Port Richey FL 34652",
    "addr:housenumber":"5509",
    "addr:postcode":"34652",
    "addr:street":"Grand Blvd",
    "iso:country":"US",
    "sg:address":"5509 Grand Blvd",
    "sg:city":"New Port Richey",
    "sg:classifiers":[
        {
            "category":"Professional",
            "type":"Services"
        }
    ],
    "sg:phone":"+1 727 843 4040",
    "sg:postcode":"34652",
    "sg:province":"FL",
    "sg:tags":[
        "establishment"
    ],
    "wof:name":"Atlas Insurance Marketing",
    "wof:placetype":"venue"
},
  "geometry": {"coordinates":[-82.719621,28.239285],"type":"Point"}
}