{
  "type": "Feature",
  "properties": {
    "addr:full":"1715 NE 51st St Pompano Beach FL 33064",
    "addr:housenumber":"1715",
    "addr:postcode":"33064",
    "addr:street":"Ne 51St St",
    "iso:country":"US",
    "sg:address":"1715 NE 51st St",
    "sg:city":"Pompano Beach",
    "sg:classifiers":[
        {
            "category":"Travel",
            "subcategory":"Travel Agent",
            "type":"Entertainment"
        }
    ],
    "sg:phone":"+1 954 421 6438",
    "sg:postcode":"33064",
    "sg:province":"FL",
    "sg:tags":[
        "agency",
        "bureau"
    ],
    "wof:name":"Waterfalls Expeditions Corp",
    "wof:placetype":"venue"
},
  "geometry": {"coordinates":[-80.098184,26.293847],"type":"Point"}
}