{
  "type": "Feature",
  "properties": {
    "addr:full":"715 5th St E Bradenton FL 34208",
    "addr:housenumber":"715",
    "addr:postcode":"34208",
    "addr:street":"5Th St",
    "iso:country":"US",
    "sg:address":"715 5th St E",
    "sg:city":"Bradenton",
    "sg:classifiers":[
        {
            "category":"Manufacturing",
            "subcategory":"Metals",
            "type":"Manufacturing & Wholesale Goods"
        }
    ],
    "sg:phone":"+1 941 708 0393",
    "sg:postcode":"34208",
    "sg:province":"FL",
    "sg:tags":[
        "repair",
        "product",
        "primary",
        "mfg"
    ],
    "wof:name":"Gulfcoast Marine Power",
    "wof:placetype":"venue"
},
  "geometry": {"coordinates":[-82.559021,27.493422],"type":"Point"}
}