{
  "type": "Feature",
  "properties": {
    "addr:full":"5709 Luckasavage Rd Plant City FL 33567",
    "addr:housenumber":"5709",
    "addr:postcode":"33567",
    "addr:street":"Luckasavage Rd",
    "iso:country":"US",
    "sg:address":"5709 Luckasavage Rd",
    "sg:city":"Plant City",
    "sg:classifiers":[
        {
            "category":"Farming",
            "subcategory":"Farm & Veterinary Services",
            "type":"Manufacturing & Wholesale Goods"
        }
    ],
    "sg:phone":"+1 813 737 4845",
    "sg:postcode":"33567",
    "sg:province":"FL",
    "sg:tags":[
        "haying",
        "mowing"
    ],
    "wof:name":"Rosa Eckerfield Mowing Haying",
    "wof:placetype":"venue"
},
  "geometry": {"coordinates":[-82.16226899999999,27.935973],"type":"Point"}
}