{
  "type": "Feature",
  "properties": {
    "iso:country":"US",
    "sg:address":"500 S Hunt Club Blvd",
    "sg:city":"Apopka",
    "sg:classifiers":[
        {
            "category":"Banks & Credit Unions",
            "subcategory":"Bank",
            "type":"Services"
        }
    ],
    "sg:phone":"+1 407 869 8069",
    "sg:postcode":"32703",
    "sg:province":"FL",
    "sg:tags":[
        "commercial"
    ],
    "wof:name":"Peoples First Community Bank",
    "wof:placetype":"venue"
},
  "geometry": {"coordinates":[-81.449816,28.670966],"type":"Point"}
}