{
  "type": "Feature",
  "properties": {
    "iso:country":"US",
    "sg:address":"16701 NW 49th Ct",
    "sg:city":"Opa Locka",
    "sg:classifiers":[
        {
            "category":"Building & Trades",
            "subcategory":"Electrical",
            "type":"Services"
        }
    ],
    "sg:phone":"+1 305 624 5704",
    "sg:postcode":"33055",
    "sg:province":"FL",
    "sg:tags":[
        "electrical",
        "contractor"
    ],
    "wof:name":"Enterprise Electric Inc",
    "wof:placetype":"venue"
},
  "geometry": {"coordinates":[-80.281786,25.926409],"type":"Point"}
}