{
  "type": "Feature",
  "properties": {
    "iso:country":"US",
    "sg:address":"1336 Corsino St",
    "sg:city":"Winter Garden",
    "sg:classifiers":[
        {
            "category":"Freight",
            "type":"Transportation"
        }
    ],
    "sg:phone":"+1 407 877 7866",
    "sg:postcode":"34787",
    "sg:province":"FL",
    "wof:name":"Danielle Express Shipping",
    "wof:placetype":"venue"
},
  "geometry": {"coordinates":[-81.56093300000001,28.588078],"type":"Point"}
}