{
  "type": "Feature",
  "properties": {
    "iso:country":"US",
    "sg:address":"711 W Amelia St",
    "sg:city":"Orlando",
    "sg:classifiers":[
        {
            "category":"Professional",
            "subcategory":"Engineering",
            "type":"Services"
        }
    ],
    "sg:phone":"+1 407 398 6575",
    "sg:postcode":"32805",
    "sg:province":"FL",
    "sg:tags":[
        "consulting",
        "engineer"
    ],
    "wof:name":"Tekontrol Inc",
    "wof:placetype":"venue"
},
  "geometry": {"coordinates":[-81.389128,28.549311],"type":"Point"}
}