{
  "type": "Feature",
  "properties": {
    "addr:full":"5915 Abercorn Dr Orlando FL 32812",
    "addr:housenumber":"5915",
    "addr:postcode":"32812",
    "addr:street":"Abercorn Dr",
    "iso:country":"US",
    "sg:address":"5915 Abercorn Dr",
    "sg:city":"Orlando",
    "sg:classifiers":[
        {
            "category":"Professional",
            "subcategory":"Art Services",
            "type":"Services"
        }
    ],
    "sg:phone":"+1 407 277 4139",
    "sg:postcode":"32812",
    "sg:province":"FL",
    "sg:tags":[
        "graphic",
        "design",
        "t",
        "cu",
        "retail"
    ],
    "wof:name":"One Nation Graphics",
    "wof:placetype":"venue"
},
  "geometry": {"coordinates":[-81.310965,28.487505],"type":"Point"}
}