{
  "type": "Feature",
  "properties": {
    "iso:country":"US",
    "sg:address":"50 159th Ave",
    "sg:city":"Redington Beach",
    "sg:classifiers":[
        {
            "category":"Building & Trades",
            "subcategory":"Construction",
            "type":"Services"
        }
    ],
    "sg:phone":"+1 727 392 9650",
    "sg:postcode":"33708",
    "sg:province":"FL",
    "sg:tags":[
        "roofing",
        "contractor"
    ],
    "wof:name":"All Roofing",
    "wof:placetype":"venue"
},
  "geometry": {"coordinates":[-82.811538,27.809099],"type":"Point"}
}