{
  "type": "Feature",
  "properties": {
    "iso:country":"US",
    "sg:address":"1307 Somerville Rd",
    "sg:city":"Jacksonville",
    "sg:classifiers":[
        {
            "category":"Professional",
            "type":"Services"
        }
    ],
    "sg:phone":"+1 904 398 6262",
    "sg:postcode":"32207",
    "sg:province":"FL",
    "wof:name":"Albert J Vogel Inc",
    "wof:placetype":"venue"
},
  "geometry": {"coordinates":[-81.625501,30.30786],"type":"Point"}
}