{
  "type": "Feature",
  "properties": {
    "addr:full":"124 E Nine Mile Rd Pensacola FL 32534",
    "addr:housenumber":"124",
    "addr:postcode":"32534",
    "addr:street":"E Nine Mile Rd",
    "iso:country":"US",
    "sg:address":"124 E Nine Mile Rd",
    "sg:city":"Pensacola",
    "sg:classifiers":[
        {
            "category":"Utilities",
            "subcategory":"Telephone",
            "type":"Services"
        }
    ],
    "sg:phone":"+1 850 494 0301",
    "sg:postcode":"32534",
    "sg:province":"FL",
    "sg:tags":[
        "company"
    ],
    "wof:name":"Express Phone Svc",
    "wof:placetype":"venue"
},
  "geometry": {"coordinates":[-87.269954,30.533206],"type":"Point"}
}