{
  "type": "Feature",
  "properties": {
    "iso:country":"US",
    "sg:address":"116 SE 61st Ct",
    "sg:city":"Ocala",
    "sg:classifiers":[
        {
            "category":"Professional",
            "subcategory":"Computer Services",
            "type":"Services"
        }
    ],
    "sg:phone":"+1 352 624 3367",
    "sg:postcode":"34472",
    "sg:province":"FL",
    "sg:tags":[
        "website",
        "design"
    ],
    "wof:name":"Central Florida Computing",
    "wof:placetype":"venue"
},
  "geometry": {"coordinates":[-82.04933699999999,29.185049],"type":"Point"}
}