{
  "type": "Feature",
  "properties": {
    "addr:full":"1957 W 60th St Hialeah FL 33012",
    "addr:housenumber":"1957",
    "addr:postcode":"33012",
    "addr:street":"W 60Th St",
    "iso:country":"US",
    "sg:address":"1957 W 60th St",
    "sg:city":"Hialeah",
    "sg:classifiers":[
        {
            "category":"Health Services",
            "subcategory":"Doctor",
            "type":"Services"
        }
    ],
    "sg:phone":"+1 305 825 8170",
    "sg:postcode":"33012",
    "sg:province":"FL",
    "sg:tags":[
        "physician",
        "surgeon"
    ],
    "wof:name":"Care Family Ctr",
    "wof:placetype":"venue"
},
  "geometry": {"coordinates":[-80.32253900000001,25.877073],"type":"Point"}
}