{
  "type": "Feature",
  "properties": {
    "iso:country":"US",
    "sg:address":"14140 8th St",
    "sg:city":"Dade City",
    "sg:classifiers":[
        {
            "category":"Food & Beverages",
            "subcategory":"Specialty",
            "type":"Retail Goods"
        },
        {
            "category":"Shopping",
            "subcategory":"Pharmacy",
            "type":"Retail Goods"
        }
    ],
    "sg:phone":"+1 352 523 0044",
    "sg:postcode":"33525",
    "sg:province":"FL",
    "sg:tags":[
        "eating",
        "health",
        "diet"
    ],
    "wof:name":"Nancy's Natural Foods",
    "wof:placetype":"venue"
},
  "geometry": {"coordinates":[-82.19008700000001,28.364397],"type":"Point"}
}