{
  "type": "Feature",
  "properties": {
    "addr:full":"6015 31st St E Bradenton FL 34203",
    "addr:housenumber":"6015",
    "addr:postcode":"34203",
    "addr:street":"31St St",
    "iso:country":"US",
    "sg:address":"6015 31st St E",
    "sg:city":"Bradenton",
    "sg:classifiers":[
        {
            "category":"Wholesale",
            "subcategory":"Machinery & Supplies",
            "type":"Manufacturing & Wholesale Goods"
        }
    ],
    "sg:phone":"+1 941 739 0607",
    "sg:postcode":"34203",
    "sg:province":"FL",
    "sg:tags":[
        "packaging",
        "equipment"
    ],
    "wof:name":"Cermex North America",
    "wof:placetype":"venue"
},
  "geometry": {"coordinates":[-82.52486,27.433045],"type":"Point"}
}