{
  "type": "Feature",
  "properties": {
    "iso:country":"US",
    "sg:address":"1935 E Edgewood Dr",
    "sg:city":"Lakeland",
    "sg:classifiers":[
        {
            "category":"Professional",
            "subcategory":"Accounting & Tax Preparation",
            "type":"Services"
        }
    ],
    "sg:phone":"+1 863 686 0897",
    "sg:postcode":"33803",
    "sg:province":"FL",
    "wof:name":"Kenneth C Hutto CPA",
    "wof:placetype":"venue"
},
  "geometry": {"coordinates":[-81.92714100000001,28.011249],"type":"Point"}
}