{
  "type": "Feature",
  "properties": {
    "iso:country":"US",
    "sg:address":"38453 5th Ave",
    "sg:city":"Zephyrhills",
    "sg:classifiers":[
        {
            "category":"Professional",
            "subcategory":"Lawyer & Legal Services",
            "type":"Services"
        }
    ],
    "sg:phone":"+1 866 958 9518",
    "sg:postcode":"33542",
    "sg:province":"FL",
    "sg:tags":[
        "attorney",
        "property",
        "damage",
        "accident"
    ],
    "sg:website":"http://www.hudginslawfirm.com/",
    "wof:name":"Hudgins Law Firm",
    "wof:placetype":"venue"
},
  "geometry": {"coordinates":[-82.180483,28.234042],"type":"Point"}
}