{
  "type": "Feature",
  "properties": {
    "iso:country":"US",
    "sg:address":"12120 NW 20th Ct",
    "sg:city":"Miami",
    "sg:classifiers":[
        {
            "category":"Autos & Motor Vehicles",
            "subcategory":"Automobile Sales",
            "type":"Retail Goods"
        }
    ],
    "sg:phone":"+1 305 953 1588",
    "sg:postcode":"33167",
    "sg:province":"FL",
    "sg:tags":[
        "car",
        "dealer"
    ],
    "wof:name":"4 Ft Plex Auto & Hm Rstrtn",
    "wof:placetype":"venue"
},
  "geometry": {"coordinates":[-80.232529,25.885527],"type":"Point"}
}