{
  "type": "Feature",
  "properties": {
    "iso:country":"US",
    "sg:address":"818 N Federal Hwy",
    "sg:city":"Lake Worth",
    "sg:classifiers":[
        {
            "category":"Professional",
            "subcategory":"Management & Consulting",
            "type":"Services"
        }
    ],
    "sg:phone":"+1 561 582 4027",
    "sg:postcode":"33460",
    "sg:province":"FL",
    "sg:tags":[
        "consultant"
    ],
    "wof:name":"Julia Brown Ma Consulting",
    "wof:placetype":"venue"
},
  "geometry": {"coordinates":[-80.051996,26.625971],"type":"Point"}
}