{
  "type": "Feature",
  "properties": {
    "iso:country":"US",
    "sg:address":"16557 NE 8th Ave",
    "sg:city":"Miami",
    "sg:classifiers":[
        {
            "category":"Shopping",
            "subcategory":"Department Store",
            "type":"Retail Goods"
        }
    ],
    "sg:phone":"+1 305 945 8350",
    "sg:postcode":"33162",
    "sg:province":"FL",
    "sg:tags":[
        "shop"
    ],
    "wof:name":"New Dollar Idia",
    "wof:placetype":"venue"
},
  "geometry": {"coordinates":[-80.184155,25.92845],"type":"Point"}
}