{
  "type": "Feature",
  "properties": {
    "iso:country":"US",
    "sg:address":"12794 Forest Hill Blvd",
    "sg:city":"Wellington",
    "sg:classifiers":[
        {
            "category":"Insurance",
            "subcategory":"Insurance Agent",
            "type":"Services"
        }
    ],
    "sg:phone":"+1 561 422 5936",
    "sg:postcode":"33414",
    "sg:province":"FL",
    "wof:name":"Barker Insurance",
    "wof:placetype":"venue"
},
  "geometry": {"coordinates":[-80.247632,26.672907],"type":"Point"}
}