{
  "type": "Feature",
  "properties": {
    "addr:full":"4065 Haverhill Rd N West Palm Beach FL 33417",
    "addr:housenumber":"4065",
    "addr:postcode":"33417",
    "addr:street":"Haverhill Rd N",
    "iso:country":"US",
    "sg:address":"4065 Haverhill Rd N",
    "sg:city":"West Palm Beach",
    "sg:classifiers":[
        {
            "category":"Bakery",
            "type":"Food & Drink"
        },
        {
            "category":"Coffee & Tea",
            "type":"Food & Drink"
        },
        {
            "category":"Bagels",
            "type":"Food & Drink"
        },
        {
            "category":"Donuts",
            "type":"Food & Drink"
        }
    ],
    "sg:menulink":"http://www.allmenus.com/fl/west-palm-beach/138142-dunkin-donuts/menu/",
    "sg:phone":"+1 561 686 2438",
    "sg:postcode":"33417",
    "sg:province":"FL",
    "sg:tags":[
        "american",
        "pastry"
    ],
    "wof:name":"Dunkin' Donuts",
    "wof:placetype":"venue"
},
  "geometry": {"coordinates":[-80.118207,26.73741],"type":"Point"}
}