{
  "type": "Feature",
  "properties": {
    "iso:country":"US",
    "sg:address":"763 W Flagler St",
    "sg:city":"Miami",
    "sg:classifiers":[
        {
            "category":"Health Services",
            "subcategory":"Doctor",
            "type":"Services"
        }
    ],
    "sg:phone":"+1 305 324 6312",
    "sg:postcode":"33130",
    "sg:province":"FL",
    "wof:name":"J Danilo Callejas DDS",
    "wof:placetype":"venue"
},
  "geometry": {"coordinates":[-80.206762,25.773827],"type":"Point"}
}