{
  "type": "Feature",
  "properties": {
    "iso:country":"US",
    "sg:address":"680 5th Ave S",
    "sg:city":"Naples",
    "sg:classifiers":[
        {
            "category":"Shopping",
            "type":"Retail Goods"
        },
        {
            "category":"Museum",
            "type":"Entertainment"
        }
    ],
    "sg:phone":"+1 239 430 9200",
    "sg:postcode":"34102",
    "sg:province":"FL",
    "sg:tags":[
        "art",
        "gallery",
        "dealer"
    ],
    "wof:name":"Gallery On Fifth",
    "wof:placetype":"venue"
},
  "geometry": {"coordinates":[-81.797843,26.141442],"type":"Point"}
}