{
  "type": "Feature",
  "properties": {
    "iso:country":"US",
    "sg:address":"3920 Pensacola Dr",
    "sg:city":"Lantana",
    "sg:classifiers":[
        {
            "category":"Building & Trades",
            "subcategory":"Construction",
            "type":"Services"
        }
    ],
    "sg:phone":"+1 561 642 3007",
    "sg:postcode":"33462",
    "sg:province":"FL",
    "sg:tags":[
        "wallpaper"
    ],
    "wof:name":"Colorbrite Painting",
    "wof:placetype":"venue"
},
  "geometry": {"coordinates":[-80.10378900000001,26.582707],"type":"Point"}
}