{
  "type": "Feature",
  "properties": {
    "addr:full":"29165 Clover Ln Big Pine Key FL 33043",
    "addr:housenumber":"29165",
    "addr:postcode":"33043",
    "addr:street":"Clover Ln",
    "iso:country":"US",
    "sg:address":"29165 Clover Ln",
    "sg:city":"Big Pine Key",
    "sg:classifiers":[
        {
            "category":"Manufacturing",
            "subcategory":"Signs",
            "type":"Manufacturing & Wholesale Goods"
        }
    ],
    "sg:phone":"+1 321 452 6215",
    "sg:postcode":"33043",
    "sg:province":"FL",
    "sg:tags":[
        "advertising",
        "specialty"
    ],
    "wof:name":"City Signs Of Key West Inc",
    "wof:placetype":"venue"
},
  "geometry": {"coordinates":[-81.37693299999999,24.688178],"type":"Point"}
}