{
  "type": "Feature",
  "properties": {
    "iso:country":"US",
    "sg:address":"6416 N Florida Ave",
    "sg:city":"Tampa",
    "sg:classifiers":[
        {
            "category":"Bars & Pubs",
            "subcategory":"Nightclub",
            "type":"Food & Drink"
        }
    ],
    "sg:phone":"+1 813 234 1267",
    "sg:postcode":"33604",
    "sg:province":"FL",
    "sg:tags":[
        "club",
        "night"
    ],
    "wof:name":"Recuerdos Bar",
    "wof:placetype":"venue"
},
  "geometry": {"coordinates":[-82.459473,28.005791],"type":"Point"}
}