{
  "type": "Feature",
  "properties": {
    "iso:country":"US",
    "sg:address":"4771 Bayou Blvd",
    "sg:city":"Pensacola",
    "sg:classifiers":[
        {
            "category":"Coffee & Tea",
            "type":"Food & Drink"
        }
    ],
    "sg:menulink":"http://www.allmenus.com/fl/pensacola/121477-the-coffee-beanery/menu/",
    "sg:phone":"+1 850 475 8048",
    "sg:postcode":"32503",
    "sg:province":"FL",
    "sg:tags":[
        "american",
        "diner"
    ],
    "wof:name":"The Coffee Beanery",
    "wof:placetype":"venue"
},
  "geometry": {"coordinates":[-87.208128,30.471063],"type":"Point"}
}