{
  "type": "Feature",
  "properties": {
    "addr:full":"2061 SE Pyramid Rd Port Saint Lucie FL 34952",
    "addr:housenumber":"2061",
    "addr:postcode":"34952",
    "addr:street":"Se Pyramid Rd",
    "iso:country":"US",
    "sg:address":"2061 SE Pyramid Rd",
    "sg:city":"Port Saint Lucie",
    "sg:classifiers":[
        {
            "category":"Travel",
            "subcategory":"Travel Agent",
            "type":"Entertainment"
        }
    ],
    "sg:phone":"+1 772 335 9049",
    "sg:postcode":"34952",
    "sg:province":"FL",
    "sg:tags":[
        "conducted",
        "tours"
    ],
    "wof:name":"Jbs Galaxsea Tours & Cruises",
    "wof:placetype":"venue"
},
  "geometry": {"coordinates":[-80.287963,27.255539],"type":"Point"}
}