{
  "type": "Feature",
  "properties": {
    "addr:full":"3728 Phillips Hwy Jacksonville FL 32207",
    "addr:housenumber":"3728",
    "addr:postcode":"32207",
    "addr:street":"Phillips Hwy",
    "iso:country":"US",
    "sg:address":"3728 Phillips Hwy",
    "sg:city":"Jacksonville",
    "sg:classifiers":[
        {
            "category":"Professional",
            "subcategory":"Detective & Security Services",
            "type":"Services"
        }
    ],
    "sg:phone":"+1 904 346 0488",
    "sg:postcode":"32207",
    "sg:province":"FL",
    "sg:tags":[
        "guard"
    ],
    "wof:name":"River City Security Services",
    "wof:placetype":"venue"
},
  "geometry": {"coordinates":[-81.62900399999999,30.28108],"type":"Point"}
}