{
  "type": "Feature",
  "properties": {
    "iso:country":"US",
    "sg:address":"2941 SW 87th Ave",
    "sg:city":"Fort Lauderdale",
    "sg:classifiers":[
        {
            "category":"Restaurant",
            "type":"Food & Drink"
        }
    ],
    "sg:phone":"+1 954 423 9791",
    "sg:postcode":"33328",
    "sg:province":"FL",
    "sg:tags":[
        "eating"
    ],
    "wof:name":"Reed Catering Inc",
    "wof:placetype":"venue"
},
  "geometry": {"coordinates":[-80.263186,26.085803],"type":"Point"}
}