{
  "type": "Feature",
  "properties": {
    "addr:full":"5617 S Orange Ave Orlando FL 32809",
    "addr:housenumber":"5617",
    "addr:postcode":"32809",
    "addr:street":"S Orange Ave",
    "iso:country":"US",
    "sg:address":"5617 S Orange Ave",
    "sg:city":"Orlando",
    "sg:classifiers":[
        {
            "category":"Shopping",
            "subcategory":"Clothing, Apparel, & Fashions",
            "type":"Retail Goods"
        }
    ],
    "sg:phone":"+1 407 251 8040",
    "sg:postcode":"32809",
    "sg:province":"FL",
    "sg:tags":[
        "shop",
        "bridal"
    ],
    "wof:name":"Bride's Paradise & Party Crtns",
    "wof:placetype":"venue"
},
  "geometry": {"coordinates":[-81.370086,28.475451],"type":"Point"}
}