{
  "type": "Feature",
  "properties": {
    "iso:country":"US",
    "sg:address":"34 N 14th St Pl",
    "sg:city":"Fernandina Beach",
    "sg:classifiers":[
        {
            "category":"Professional",
            "subcategory":"Lawyer & Legal Services",
            "type":"Services"
        }
    ],
    "sg:phone":"+1 904 277 4600",
    "sg:postcode":"32034",
    "sg:province":"FL",
    "sg:tags":[
        "attorney"
    ],
    "wof:name":"Deirdre A Wallace Law Offices",
    "wof:placetype":"venue"
},
  "geometry": {"coordinates":[-81.44862999999999,30.68502],"type":"Point"}
}