{
  "type": "Feature",
  "properties": {
    "iso:country":"US",
    "sg:address":"164 W Royal Palm Rd",
    "sg:city":"Boca Raton",
    "sg:classifiers":[
        {
            "category":"Building & Trades",
            "subcategory":"Electrical",
            "type":"Services"
        }
    ],
    "sg:phone":"+1 561 394 9969",
    "sg:postcode":"33432",
    "sg:province":"FL",
    "sg:tags":[
        "equipment",
        "telecommunication"
    ],
    "sg:website":"www.usalertllc.com",
    "wof:name":"Us Alert",
    "wof:placetype":"venue"
},
  "geometry": {"coordinates":[-80.08892899999999,26.3494],"type":"Point"}
}