{
  "type": "Feature",
  "properties": {
    "iso:country":"US",
    "sg:address":"1821 SW 5th St",
    "sg:city":"Miami",
    "sg:classifiers":[
        {
            "category":"Building & Trades",
            "subcategory":"Construction",
            "type":"Services"
        }
    ],
    "sg:phone":"+1 305 642 9453",
    "sg:postcode":"33135",
    "sg:province":"FL",
    "sg:tags":[
        "contractor"
    ],
    "wof:name":"Ysy Roofing Corp",
    "wof:placetype":"venue"
},
  "geometry": {"coordinates":[-80.22634499999999,25.76829],"type":"Point"}
}