{
  "type": "Feature",
  "properties": {
    "addr:full":"1280 W Lantana Rd Lantana FL 33462",
    "addr:housenumber":"1280",
    "addr:postcode":"33462",
    "addr:street":"W Lantana Rd",
    "iso:country":"US",
    "sg:address":"1280 W Lantana Rd",
    "sg:city":"Lantana",
    "sg:classifiers":[
        {
            "category":"Health Services",
            "subcategory":"Optometrist",
            "type":"Services"
        }
    ],
    "sg:phone":"+1 561 582 3383",
    "sg:postcode":"33462",
    "sg:province":"FL",
    "sg:tags":[
        "good",
        "optical",
        "store",
        "retail"
    ],
    "sg:website":"www.eyecaredoctors.com",
    "wof:name":"Eye Care Professionals",
    "wof:placetype":"venue"
},
  "geometry": {"coordinates":[-80.05946400000001,26.586879],"type":"Point"}
}