{
  "type": "Feature",
  "properties": {
    "iso:country":"US",
    "sg:address":"4185 W Lake Mary Blvd",
    "sg:city":"Lake Mary",
    "sg:classifiers":[
        {
            "category":"Wholesale",
            "subcategory":"Non-durable Goods",
            "type":"Manufacturing & Wholesale Goods"
        }
    ],
    "sg:phone":"+1 407 804 8918",
    "sg:postcode":"32746",
    "sg:province":"FL",
    "wof:name":"Eccho Italia Inc",
    "wof:placetype":"venue"
},
  "geometry": {"coordinates":[-81.349231,28.756093],"type":"Point"}
}