{
  "type": "Feature",
  "properties": {
    "iso:country":"US",
    "sg:address":"1155 S Dale Mabry Hwy",
    "sg:city":"Tampa",
    "sg:classifiers":[
        {
            "category":"Restaurant",
            "type":"Food & Drink"
        }
    ],
    "sg:menulink":"http://www.allmenus.com/fl/tampa/272529-fuji-sushi/menu/",
    "sg:phone":"+1 813 282 9098",
    "sg:postcode":"33629",
    "sg:province":"FL",
    "sg:tags":[
        "sushi",
        "japanese",
        "asian"
    ],
    "wof:name":"Fuji Sushi",
    "wof:placetype":"venue"
},
  "geometry": {"coordinates":[-82.505977,27.932481],"type":"Point"}
}