{
  "type": "Feature",
  "properties": {
    "iso:country":"US",
    "sg:address":"3709 Argon Dr",
    "sg:city":"Tampa",
    "sg:classifiers":[
        {
            "category":"Shopping",
            "subcategory":"Catalog Store",
            "type":"Retail Goods"
        }
    ],
    "sg:phone":"+1 813 621 6645",
    "sg:postcode":"33619",
    "sg:province":"FL",
    "sg:tags":[
        "mail",
        "house"
    ],
    "wof:name":"Sherris Domestic Dragons",
    "wof:placetype":"venue"
},
  "geometry": {"coordinates":[-82.364592,27.980575],"type":"Point"}
}