{
  "type": "Feature",
  "properties": {
    "iso:country":"US",
    "sg:address":"1602A Washington Ave",
    "sg:city":"Miami Beach",
    "sg:classifiers":[
        {
            "category":"Personal",
            "subcategory":"Nail Salon",
            "type":"Services"
        }
    ],
    "sg:phone":"+1 305 674 0068",
    "sg:postcode":"33139",
    "sg:province":"FL",
    "wof:name":"Tootsie's Nail Salon & Boutique",
    "wof:placetype":"venue"
},
  "geometry": {"coordinates":[-80.131888,25.789436],"type":"Point"}
}