{
  "type": "Feature",
  "properties": {
    "addr:full":"4022 Winthrop St Sarasota FL 34232",
    "addr:housenumber":"4022",
    "addr:postcode":"34232",
    "addr:street":"Winthrop St",
    "iso:country":"US",
    "sg:address":"4022 Winthrop St",
    "sg:city":"Sarasota",
    "sg:classifiers":[
        {
            "category":"Organizations",
            "subcategory":"Labor Organization",
            "type":"Services"
        }
    ],
    "sg:phone":"+1 941 378 9600",
    "sg:postcode":"34232",
    "sg:province":"FL",
    "wof:name":"APWU",
    "wof:placetype":"venue"
},
  "geometry": {"coordinates":[-82.485961,27.301824],"type":"Point"}
}