{
  "type": "Feature",
  "properties": {
    "iso:country":"US",
    "sg:address":"740 Clay St",
    "sg:city":"Winter Park",
    "sg:classifiers":[
        {
            "category":"Manufacturing",
            "subcategory":"Printing",
            "type":"Manufacturing & Wholesale Goods"
        }
    ],
    "sg:phone":"+1 407 740 6076",
    "sg:postcode":"32789",
    "sg:province":"FL",
    "sg:tags":[
        "print",
        "lithographic",
        "design",
        "typeset"
    ],
    "wof:name":"Florida Printing & Design Inc",
    "wof:placetype":"venue"
},
  "geometry": {"coordinates":[-81.37333,28.590393],"type":"Point"}
}