{
  "type": "Feature",
  "properties": {
    "iso:country":"US",
    "sg:address":"15681 S Apopka Vineland Rd",
    "sg:city":"Orlando",
    "sg:classifiers":[
        {
            "category":"Home & Garden",
            "subcategory":"Home Furnishings",
            "type":"Retail Goods"
        }
    ],
    "sg:phone":"+1 407 238 2793",
    "sg:postcode":"32821",
    "sg:province":"FL",
    "sg:tags":[
        "linen"
    ],
    "wof:name":"Springmaid Wamsutta",
    "wof:placetype":"venue"
},
  "geometry": {"coordinates":[-81.48857099999999,28.348136],"type":"Point"}
}