{
  "type": "Feature",
  "properties": {
    "addr:full":"15003 Southfork Dr Tampa FL 33624",
    "addr:postcode":"15003;33624",
    "addr:street":"Southfork Dr",
    "iso:country":"US",
    "sg:address":"15003 Southfork Dr",
    "sg:city":"Tampa",
    "sg:classifiers":[
        {
            "category":"Manufacturing",
            "subcategory":"Metals",
            "type":"Manufacturing & Wholesale Goods"
        }
    ],
    "sg:phone":"+1 813 265 4566",
    "sg:postcode":"33624",
    "sg:province":"FL",
    "sg:tags":[
        "product",
        "primary",
        "mfg"
    ],
    "wof:name":"Weather Guard Building Pdts",
    "wof:placetype":"venue"
},
  "geometry": {"coordinates":[-82.51326899999999,28.087124],"type":"Point"}
}