{
  "type": "Feature",
  "properties": {
    "addr:full":"12225 N Florida Ave Tampa FL 33612",
    "addr:housenumber":"12225",
    "addr:postcode":"33612",
    "addr:street":"N Florida Ave",
    "iso:country":"US",
    "sg:address":"12225 N Florida Ave",
    "sg:city":"Tampa",
    "sg:classifiers":[
        {
            "category":"Shopping",
            "subcategory":"Musical Instruments",
            "type":"Retail Goods"
        }
    ],
    "sg:phone":"+1 813 931 0781",
    "sg:postcode":"33612",
    "sg:province":"FL",
    "sg:tags":[
        "music",
        "dealer"
    ],
    "wof:name":"Look Hear Music & Movies",
    "wof:placetype":"venue"
},
  "geometry": {"coordinates":[-82.459293,28.058977],"type":"Point"}
}