{
  "type": "Feature",
  "properties": {
    "addr:full":"9471 SW 97th St Miami FL 33176",
    "addr:housenumber":"9471",
    "addr:postcode":"33176",
    "addr:street":"Sw 97Th St",
    "iso:country":"US",
    "sg:address":"9471 SW 97th St",
    "sg:city":"Miami",
    "sg:classifiers":[
        {
            "category":"Professional",
            "subcategory":"Management & Consulting",
            "type":"Services"
        },
        {
            "category":"Banks & Credit Unions",
            "subcategory":"Financial Services",
            "type":"Services"
        }
    ],
    "sg:phone":"+1 305 274 9143",
    "sg:postcode":"33176",
    "sg:province":"FL",
    "sg:tags":[
        "consultant",
        "financing",
        "planning",
        "planner"
    ],
    "wof:name":"Paul S Soule Enterprises Inc",
    "wof:placetype":"venue"
},
  "geometry": {"coordinates":[-80.348752,25.679374],"type":"Point"}
}