{
  "type": "Feature",
  "properties": {
    "iso:country":"US",
    "sg:address":"6416 Lake Suzzanne Pl",
    "sg:city":"Panama City",
    "sg:classifiers":[
        {
            "category":"Building & Trades",
            "subcategory":"Construction",
            "type":"Services"
        }
    ],
    "sg:phone":"+1 850 747 1260",
    "sg:postcode":"32404",
    "sg:province":"FL",
    "sg:tags":[
        "house"
    ],
    "wof:name":"Marcum Home Improvement Inc",
    "wof:placetype":"venue"
},
  "geometry": {"coordinates":[-85.525958,30.264444],"type":"Point"}
}