{
  "type": "Feature",
  "properties": {
    "iso:country":"US",
    "sg:address":"2621 Miranda Way S",
    "sg:city":"Saint Petersburg",
    "sg:classifiers":[
        {
            "category":"Building & Trades",
            "subcategory":"Electrical",
            "type":"Services"
        }
    ],
    "sg:phone":"+1 727 866 3712",
    "sg:postcode":"33712",
    "sg:province":"FL",
    "sg:tags":[
        "electrical",
        "contractor"
    ],
    "wof:name":"Southeastern Electrical",
    "wof:placetype":"venue"
},
  "geometry": {"coordinates":[-82.66938500000001,27.735514],"type":"Point"}
}