{
  "type": "Feature",
  "properties": {
    "addr:full":"7051 W Waters Ave Tampa FL 33634",
    "addr:housenumber":"7051",
    "addr:postcode":"33634",
    "addr:street":"W Waters Ave",
    "iso:country":"US",
    "sg:address":"7051 W Waters Ave",
    "sg:city":"Tampa",
    "sg:classifiers":[
        {
            "category":"Social Services",
            "subcategory":"Job Training",
            "type":"Services"
        }
    ],
    "sg:phone":"+1 813 806 3997",
    "sg:postcode":"33634",
    "sg:province":"FL",
    "sg:tags":[
        "rehabilitation"
    ],
    "wof:name":"Healthsouth Rehabilitation Ctr",
    "wof:placetype":"venue"
},
  "geometry": {"coordinates":[-82.55886599999999,28.025797],"type":"Point"}
}