{
  "type": "Feature",
  "properties": {
    "iso:country":"US",
    "sg:address":"1021 S Combee Rd",
    "sg:city":"Lakeland",
    "sg:classifiers":[
        {
            "category":"Insurance",
            "subcategory":"Insurance Agent",
            "type":"Services"
        }
    ],
    "sg:phone":"+1 863 665 3834",
    "sg:postcode":"33801",
    "sg:province":"FL",
    "wof:name":"Indianapolis Life Insurance Co",
    "wof:placetype":"venue"
},
  "geometry": {"coordinates":[-81.907932,28.03284],"type":"Point"}
}