{
  "type": "Feature",
  "properties": {
    "iso:country":"US",
    "sg:address":"13443 Ashford Wood Ct W",
    "sg:city":"Jacksonville",
    "sg:classifiers":[
        {
            "category":"Wholesale",
            "subcategory":"Non-durable Goods",
            "type":"Manufacturing & Wholesale Goods"
        }
    ],
    "sg:phone":"+1 904 645 6237",
    "sg:postcode":"32218",
    "sg:province":"FL",
    "wof:name":"Sunshine Promotions Inc",
    "wof:placetype":"venue"
},
  "geometry": {"coordinates":[-81.606289,30.479463],"type":"Point"}
}