{
  "type": "Feature",
  "properties": {
    "iso:country":"US",
    "sg:address":"14340 Bedford Ct",
    "sg:city":"Fort Lauderdale",
    "sg:classifiers":[
        {
            "category":"Professional",
            "subcategory":"Management & Consulting",
            "type":"Services"
        }
    ],
    "sg:phone":"+1 954 424 1403",
    "sg:postcode":"33325",
    "sg:province":"FL",
    "sg:tags":[
        "business"
    ],
    "wof:name":"Physician Consultant Services",
    "wof:placetype":"venue"
},
  "geometry": {"coordinates":[-80.34002700000001,26.1031],"type":"Point"}
}