{
  "type": "Feature",
  "properties": {
    "addr:full":"17541 Johnstown Ct Fort Myers FL 33967",
    "addr:housenumber":"17541",
    "addr:postcode":"33967",
    "addr:street":"Johnstown Ct",
    "iso:country":"US",
    "sg:address":"17541 Johnstown Ct",
    "sg:city":"Fort Myers",
    "sg:classifiers":[
        {
            "category":"Professional",
            "type":"Services"
        }
    ],
    "sg:phone":"+1 239 590 3964",
    "sg:postcode":"33967",
    "sg:province":"FL",
    "wof:name":"Matthias Luecke Inc",
    "wof:placetype":"venue"
},
  "geometry": {"coordinates":[-81.81487,26.480203],"type":"Point"}
}