{
  "type": "Feature",
  "properties": {
    "addr:full":"2424 Harrell Rd Orlando FL 32817",
    "addr:housenumber":"2424",
    "addr:postcode":"32817",
    "addr:street":"Harrell Rd",
    "iso:country":"US",
    "sg:address":"2424 Harrell Rd",
    "sg:city":"Orlando",
    "sg:classifiers":[
        {
            "category":"Real Estate",
            "subcategory":"Developer",
            "type":"Services"
        }
    ],
    "sg:phone":"+1 407 671 3919",
    "sg:postcode":"32817",
    "sg:province":"FL",
    "sg:tags":[
        "cemetery"
    ],
    "wof:name":"Chapel Hill Cemetery",
    "wof:placetype":"venue"
},
  "geometry": {"coordinates":[-81.26976999999999,28.578532],"type":"Point"}
}