{
  "type": "Feature",
  "properties": {
    "iso:country":"US",
    "sg:address":"1516 Wisconsin Ave",
    "sg:city":"Palm Harbor",
    "sg:classifiers":[
        {
            "category":"Retail",
            "subcategory":"Animal Services",
            "type":"Services"
        }
    ],
    "sg:phone":"+1 727 784 5082",
    "sg:postcode":"34683",
    "sg:province":"FL",
    "sg:tags":[
        "pet",
        "boarding",
        "sitting"
    ],
    "wof:name":"Dogs R Us",
    "wof:placetype":"venue"
},
  "geometry": {"coordinates":[-82.75810799999999,28.075339],"type":"Point"}
}