{
  "type": "Feature",
  "properties": {
    "iso:country":"US",
    "sg:address":"3710 W Watrous Ave",
    "sg:city":"Tampa",
    "sg:classifiers":[
        {
            "category":"Manufacturing",
            "subcategory":"Apparel",
            "type":"Manufacturing & Wholesale Goods"
        }
    ],
    "sg:phone":"+1 813 258 1681",
    "sg:postcode":"33629",
    "sg:province":"FL",
    "sg:tags":[
        "mfg"
    ],
    "wof:name":"Anne S Custom Windows",
    "wof:placetype":"venue"
},
  "geometry": {"coordinates":[-82.505621,27.93199],"type":"Point"}
}