{
  "type": "Feature",
  "properties": {
    "iso:country":"US",
    "sg:address":"1710 Virginia Dr",
    "sg:city":"Orlando",
    "sg:classifiers":[
        {
            "category":"Building & Trades",
            "subcategory":"Construction",
            "type":"Services"
        }
    ],
    "sg:phone":"+1 407 894 7416",
    "sg:postcode":"32803",
    "sg:province":"FL",
    "sg:tags":[
        "contractor"
    ],
    "wof:name":"Eric G Honer Interior Desdign",
    "wof:placetype":"venue"
},
  "geometry": {"coordinates":[-81.358632,28.563965],"type":"Point"}
}