{
  "type": "Feature",
  "properties": {
    "iso:country":"US",
    "sg:address":"1405 Alden Rd",
    "sg:city":"Orlando",
    "sg:classifiers":[
        {
            "category":"Freight",
            "type":"Transportation"
        }
    ],
    "sg:phone":"+1 407 895 0907",
    "sg:postcode":"32803",
    "sg:province":"FL",
    "sg:tags":[
        "delivery"
    ],
    "wof:name":"Coastal Delivery",
    "wof:placetype":"venue"
},
  "geometry": {"coordinates":[-81.37205,28.565302],"type":"Point"}
}