{
  "type": "Feature",
  "properties": {
    "addr:full":"8221 State Road 674 Wimauma FL 33598",
    "addr:housenumber":"8221",
    "addr:postcode":"33598",
    "addr:street":"State Road 674 Wimauma",
    "iso:country":"US",
    "sg:address":"8221 State Road 674",
    "sg:city":"Wimauma",
    "sg:classifiers":[
        {
            "category":"Farming",
            "subcategory":"Farm",
            "type":"Manufacturing & Wholesale Goods"
        }
    ],
    "sg:phone":"+1 813 833 2545",
    "sg:postcode":"33598",
    "sg:province":"FL",
    "wof:name":"Colorfield Farms, Inc.",
    "wof:placetype":"venue"
},
  "geometry": {"coordinates":[-82.25174800000001,27.704951],"type":"Point"}
}