{
  "type": "Feature",
  "properties": {
    "iso:country":"US",
    "sg:address":"202 Howard St",
    "sg:city":"Niceville",
    "sg:classifiers":[
        {
            "category":"Building & Trades",
            "subcategory":"Construction",
            "type":"Services"
        }
    ],
    "sg:phone":"+1 850 897 3292",
    "sg:postcode":"32578",
    "sg:province":"FL",
    "sg:tags":[
        "hanging",
        "contractor"
    ],
    "wof:name":"Satisfaction Painting",
    "wof:placetype":"venue"
},
  "geometry": {"coordinates":[-86.393204,30.460761],"type":"Point"}
}