{
  "type": "Feature",
  "properties": {
    "addr:full":"2174 W Nine Mile Rd Pensacola FL 32534",
    "addr:housenumber":"2174",
    "addr:postcode":"32534",
    "addr:street":"W Nine Mile Rd",
    "iso:country":"US",
    "sg:address":"2174 W Nine Mile Rd",
    "sg:city":"Pensacola",
    "sg:classifiers":[
        {
            "category":"Cafe",
            "type":"Food & Drink"
        }
    ],
    "sg:menulink":"http://www.allmenus.com/fl/pensacola/39867-petrellas-italian-cafe/menu/",
    "sg:phone":"+1 850 471 9444",
    "sg:postcode":"32534",
    "sg:province":"FL",
    "sg:tags":[
        "italian"
    ],
    "wof:name":"Petrellas Italian Cafe",
    "wof:placetype":"venue"
},
  "geometry": {"coordinates":[-87.317303,30.534322],"type":"Point"}
}