{
  "type": "Feature",
  "properties": {
    "iso:country":"US",
    "sg:address":"1115 NW 14th St",
    "sg:city":"Miami",
    "sg:classifiers":[
        {
            "category":"Professional",
            "subcategory":"Research",
            "type":"Services"
        }
    ],
    "sg:phone":"+1 305 243 3080",
    "sg:postcode":"33136",
    "sg:province":"FL",
    "sg:tags":[
        "information",
        "medical"
    ],
    "wof:name":"Andrew A Maudsley",
    "wof:placetype":"venue"
},
  "geometry": {"coordinates":[-80.212807,25.787661],"type":"Point"}
}