{
  "type": "Feature",
  "properties": {
    "addr:full":"2531 24th St Sarasota FL 34234",
    "addr:housenumber":"2531",
    "addr:postcode":"34234",
    "addr:street":"24Th St",
    "iso:country":"US",
    "sg:address":"2531 24th St",
    "sg:city":"Sarasota",
    "sg:classifiers":[
        {
            "category":"Manufacturing",
            "subcategory":"Glass & Minerals",
            "type":"Manufacturing & Wholesale Goods"
        }
    ],
    "sg:phone":"+1 941 296 5012",
    "sg:postcode":"34234",
    "sg:province":"FL",
    "sg:tags":[
        "glass-wholesale",
        "shape",
        "circle",
        "special",
        "manufacturer"
    ],
    "wof:name":"Speedy Auto Glass",
    "wof:placetype":"venue"
},
  "geometry": {"coordinates":[-82.520059,27.357982],"type":"Point"}
}