{
  "type": "Feature",
  "properties": {
    "iso:country":"US",
    "sg:address":"12759 NW 15th St",
    "sg:city":"Sunrise",
    "sg:classifiers":[
        {
            "category":"Food & Beverages",
            "subcategory":"Liquor & Beverages",
            "type":"Retail Goods"
        }
    ],
    "sg:phone":"+1 954 846 0868",
    "sg:postcode":"33323",
    "sg:province":"FL",
    "sg:tags":[
        "bottler",
        "beverages-distributors"
    ],
    "wof:name":"Thomas J Cola",
    "wof:placetype":"venue"
},
  "geometry": {"coordinates":[-80.322316,26.14111],"type":"Point"}
}