{
  "type": "Feature",
  "properties": {
    "iso:country":"US",
    "sg:address":"3480 Pinetree St",
    "sg:city":"Port Charlotte",
    "sg:classifiers":[
        {
            "category":"Retail",
            "subcategory":"Laundry & Dry Cleaning",
            "type":"Services"
        }
    ],
    "sg:phone":"+1 941 625 4963",
    "sg:postcode":"33952",
    "sg:province":"FL",
    "sg:tags":[
        "cleaners",
        "rug",
        "carpet"
    ],
    "wof:name":"West Coast Carpet & Upholstery",
    "wof:placetype":"venue"
},
  "geometry": {"coordinates":[-82.109345,26.976108],"type":"Point"}
}