{
  "type": "Feature",
  "properties": {
    "iso:country":"US",
    "sg:address":"4141 Deleon St",
    "sg:city":"Fort Myers",
    "sg:classifiers":[
        {
            "category":"Organizations",
            "subcategory":"Religious Organization",
            "type":"Services"
        }
    ],
    "sg:phone":"+1 239 936 2200",
    "sg:postcode":"33901",
    "sg:province":"FL",
    "wof:name":"Wesley Mem Untd Methdst Church",
    "wof:placetype":"venue"
},
  "geometry": {"coordinates":[-81.876943,26.600972],"type":"Point"}
}