{
  "type": "Feature",
  "properties": {
    "addr:full":"3988 Millenia Blvd Orlando FL 32839",
    "addr:housenumber":"3988",
    "addr:postcode":"32839",
    "addr:street":"Millenia Blvd",
    "iso:country":"US",
    "sg:address":"3988 Millenia Blvd",
    "sg:city":"Orlando",
    "sg:classifiers":[
        {
            "category":"Real Estate",
            "subcategory":"Real Estate Agent",
            "type":"Services"
        }
    ],
    "sg:phone":"+1 407 351 6300",
    "sg:postcode":"32839",
    "sg:province":"FL",
    "wof:name":"Bell Terre Development",
    "wof:placetype":"venue"
},
  "geometry": {"coordinates":[-81.426688,28.493943],"type":"Point"}
}