{
  "type": "Feature",
  "properties": {
    "iso:country":"US",
    "sg:address":"8505 Old Dixie Hwy",
    "sg:city":"Wabasso",
    "sg:classifiers":[
        {
            "category":"Wholesale",
            "subcategory":"Construction Materials",
            "type":"Manufacturing & Wholesale Goods"
        }
    ],
    "sg:phone":"+1 772 388 9886",
    "sg:postcode":"32970",
    "sg:province":"FL",
    "sg:tags":[
        "building"
    ],
    "wof:name":"Florida Building Distributions",
    "wof:placetype":"venue"
},
  "geometry": {"coordinates":[-80.436284,27.748829],"type":"Point"}
}