{
  "type": "Feature",
  "properties": {
    "addr:full":"2576 S Volusia Ave Orange City FL 32763",
    "addr:housenumber":"2576",
    "addr:postcode":"32763",
    "addr:street":"S Volusia Ave",
    "iso:country":"US",
    "sg:address":"2576 S Volusia Ave",
    "sg:city":"Orange City",
    "sg:classifiers":[
        {
            "category":"Banks & Credit Unions",
            "subcategory":"Bank",
            "type":"Services"
        }
    ],
    "sg:phone":"+1 386 774 6600",
    "sg:postcode":"32763",
    "sg:province":"FL",
    "sg:tags":[
        "loan",
        "real estate"
    ],
    "wof:name":"Debra Kay's Mortgage Svc",
    "wof:placetype":"venue"
},
  "geometry": {"coordinates":[-81.301179,28.917038],"type":"Point"}
}