{
  "type": "Feature",
  "properties": {
    "iso:country":"US",
    "sg:address":"354 W Michigan Ave",
    "sg:city":"Deland",
    "sg:classifiers":[
        {
            "category":"Retail",
            "subcategory":"Auto Repair",
            "type":"Services"
        }
    ],
    "sg:phone":"+1 386 738 0393",
    "sg:postcode":"32720",
    "sg:province":"FL",
    "sg:tags":[
        "body",
        "shop"
    ],
    "wof:name":"Body Shop Total Car Care",
    "wof:placetype":"venue"
},
  "geometry": {"coordinates":[-81.309898,29.0336],"type":"Point"}
}