{
  "type": "Feature",
  "properties": {
    "addr:full":"562 Bitterwood Ct Kissimmee FL 34743",
    "addr:housenumber":"562",
    "addr:postcode":"34743",
    "addr:street":"Bitterwood Ct",
    "iso:country":"US",
    "sg:address":"562 Bitterwood Ct",
    "sg:city":"Kissimmee",
    "sg:classifiers":[
        {
            "category":"Building & Trades",
            "subcategory":"Construction",
            "type":"Services"
        }
    ],
    "sg:phone":"+1 407 568 6656",
    "sg:postcode":"34743",
    "sg:province":"FL",
    "sg:tags":[
        "house"
    ],
    "wof:name":"All Pro Renovations Inc",
    "wof:placetype":"venue"
},
  "geometry": {"coordinates":[-81.361288,28.331859],"type":"Point"}
}