{
  "type": "Feature",
  "properties": {
    "iso:country":"US",
    "sg:address":"718 SW 42nd Ave",
    "sg:city":"Plantation",
    "sg:classifiers":[
        {
            "category":"Retail",
            "subcategory":"Car Wash",
            "type":"Services"
        }
    ],
    "sg:phone":"+1 954 732 5971",
    "sg:postcode":"33317",
    "sg:province":"FL",
    "sg:tags":[
        "automobile",
        "detail",
        "clean"
    ],
    "wof:name":"Suds Custom Mobile Detailing",
    "wof:placetype":"venue"
},
  "geometry": {"coordinates":[-80.204425,26.111767],"type":"Point"}
}