{
  "type": "Feature",
  "properties": {
    "iso:country":"US",
    "sg:address":"1031 NE 72nd St",
    "sg:city":"Miami",
    "sg:classifiers":[
        {
            "category":"Shopping",
            "type":"Retail Goods"
        }
    ],
    "sg:phone":"+1 305 756 5226",
    "sg:postcode":"33138",
    "sg:province":"FL",
    "sg:tags":[
        "art",
        "merchandise"
    ],
    "wof:name":"Worlds Art Village Inc",
    "wof:placetype":"venue"
},
  "geometry": {"coordinates":[-80.17600400000001,25.841212],"type":"Point"}
}