{
  "type": "Feature",
  "properties": {
    "addr:full":"505 W Pensacola St Tallahassee FL 32301",
    "addr:housenumber":"505",
    "addr:postcode":"32301",
    "addr:street":"W Pensacola St",
    "iso:country":"US",
    "sg:address":"505 W Pensacola St",
    "sg:city":"Tallahassee",
    "sg:classifiers":[
        {
            "category":"Building & Trades",
            "subcategory":"Equipment Rental",
            "type":"Services"
        }
    ],
    "sg:phone":"+1 850 222 7019",
    "sg:postcode":"32301",
    "sg:province":"FL",
    "sg:tags":[
        "audio",
        "leasing"
    ],
    "wof:name":"American Audio Visual",
    "wof:placetype":"venue"
},
  "geometry": {"coordinates":[-84.29072499999999,30.438671],"type":"Point"}
}