{
  "type": "Feature",
  "properties": {
    "iso:country":"US",
    "sg:address":"6005 Stirling Rd",
    "sg:city":"Davie",
    "sg:classifiers":[
        {
            "category":"Retail",
            "subcategory":"Repair Shop",
            "type":"Services"
        }
    ],
    "sg:phone":"+1 888 877 4892",
    "sg:postcode":"33314",
    "sg:province":"FL",
    "sg:tags":[
        "television",
        "radio-service"
    ],
    "sg:website":"http://local.ingenio.com/Listings/Details.aspx?NUM=a%3a9572977%3a13%3a4859924%3a14%3a0%3a7",
    "wof:name":"TV Man USA",
    "wof:placetype":"venue"
},
  "geometry": {"coordinates":[-80.22694199999999,26.046208],"type":"Point"}
}