{
  "type": "Feature",
  "properties": {
    "iso:country":"US",
    "sg:address":"300 Harbour Dr",
    "sg:city":"Vero Beach",
    "sg:classifiers":[
        {
            "category":"Real Estate",
            "subcategory":"Real Estate Operator",
            "type":"Services"
        }
    ],
    "sg:phone":"+1 772 231 2766",
    "sg:postcode":"32963",
    "sg:province":"FL",
    "sg:tags":[
        "condominium"
    ],
    "wof:name":"Porpoise Bay Villas Condo",
    "wof:placetype":"venue"
},
  "geometry": {"coordinates":[-80.333547,27.589915],"type":"Point"}
}