{
  "type": "Feature",
  "properties": {
    "addr:full":"16304 SW 97th St Miami FL 33196",
    "addr:housenumber":"16304",
    "addr:postcode":"33196",
    "addr:street":"Sw 97Th St",
    "iso:country":"US",
    "sg:address":"16304 SW 97th St",
    "sg:city":"Miami",
    "sg:classifiers":[
        {
            "category":"Wholesale",
            "subcategory":"Electrical",
            "type":"Manufacturing & Wholesale Goods"
        }
    ],
    "sg:phone":"+1 305 408 6900",
    "sg:postcode":"33196",
    "sg:province":"FL",
    "sg:tags":[
        "equipment",
        "electric",
        "supply"
    ],
    "wof:name":"Easy Electronic",
    "wof:placetype":"venue"
},
  "geometry": {"coordinates":[-80.459767,25.675503],"type":"Point"}
}