{
  "type": "Feature",
  "properties": {
    "addr:full":"5410 Pine Hills Cir Orlando FL 32808",
    "addr:housenumber":"5410",
    "addr:postcode":"32808",
    "addr:street":"Pine Hills Cir",
    "iso:country":"US",
    "sg:address":"5410 Pine Hills Cir",
    "sg:city":"Orlando",
    "sg:classifiers":[
        {
            "category":"Autos & Motor Vehicles",
            "subcategory":"Fuel & Gas Station",
            "type":"Retail Goods"
        }
    ],
    "sg:phone":"+1 407 292 7238",
    "sg:postcode":"32808",
    "sg:province":"FL",
    "sg:tags":[
        "terminal",
        "truck"
    ],
    "wof:name":"Pioneers At Work Inc",
    "wof:placetype":"venue"
},
  "geometry": {"coordinates":[-81.45178900000001,28.609946],"type":"Point"}
}