{
  "type": "Feature",
  "properties": {
    "iso:country":"US",
    "sg:address":"8364 Eldridge Rd",
    "sg:city":"Spring Hill",
    "sg:classifiers":[
        {
            "category":"Retail",
            "subcategory":"Repair Shop",
            "type":"Services"
        }
    ],
    "sg:phone":"+1 352 279 0901",
    "sg:postcode":"34608",
    "sg:province":"FL",
    "wof:name":"Hawg Doctor Inc",
    "wof:placetype":"venue"
},
  "geometry": {"coordinates":[-82.579767,28.450071],"type":"Point"}
}