{
  "type": "Feature",
  "properties": {
    "iso:country":"US",
    "sg:address":"1091 Cooper Dr",
    "sg:city":"Naples",
    "sg:classifiers":[
        {
            "category":"Professional",
            "subcategory":"Employment Agencies",
            "type":"Services"
        }
    ],
    "sg:phone":"+1 239 659 0466",
    "sg:postcode":"34103",
    "sg:province":"FL",
    "sg:tags":[
        "help",
        "supply"
    ],
    "wof:name":"Chore Wizard Inc",
    "wof:placetype":"venue"
},
  "geometry": {"coordinates":[-81.79693899999999,26.189854],"type":"Point"}
}