{
  "type": "Feature",
  "properties": {
    "iso:country":"US",
    "sg:address":"7991 Johnson St",
    "sg:city":"Pembroke Pines",
    "sg:classifiers":[
        {
            "category":"Health Services",
            "subcategory":"Clinic",
            "type":"Services"
        }
    ],
    "sg:phone":"+1 954 983 3800",
    "sg:postcode":"33024",
    "sg:province":"FL",
    "sg:tags":[
        "home"
    ],
    "sg:website":"www.compassionatehomecare.com",
    "wof:name":"Compassionate Home Care Netwrk",
    "wof:placetype":"venue"
},
  "geometry": {"coordinates":[-80.248284,26.016522],"type":"Point"}
}