{
  "type": "Feature",
  "properties": {
    "addr:full":"337 Lincoln Rd Miami Beach FL 33139",
    "addr:housenumber":"337",
    "addr:postcode":"33139",
    "addr:street":"Lincoln Rd",
    "iso:country":"US",
    "sg:address":"337 Lincoln Rd",
    "sg:city":"Miami Beach",
    "sg:classifiers":[
        {
            "category":"Utilities",
            "subcategory":"Mobile Phone",
            "type":"Services"
        }
    ],
    "sg:phone":"+1 305 532 9427",
    "sg:postcode":"33139",
    "sg:province":"FL",
    "sg:tags":[
        "telephone",
        "cellular"
    ],
    "wof:name":"Hardash",
    "wof:placetype":"venue"
},
  "geometry": {"coordinates":[-80.13149300000001,25.790758],"type":"Point"}
}