{
  "type": "Feature",
  "properties": {
    "addr:full":"9350 Royal Ct Bonita Springs FL 34135",
    "addr:housenumber":"9350",
    "addr:postcode":"34135",
    "addr:street":"Royal Ct",
    "iso:country":"US",
    "sg:address":"9350 Royal Ct",
    "sg:city":"Bonita Springs",
    "sg:classifiers":[
        {
            "category":"Organizations",
            "subcategory":"Religious Organization",
            "type":"Services"
        }
    ],
    "sg:phone":"+1 239 498 6128",
    "sg:postcode":"34135",
    "sg:province":"FL",
    "sg:tags":[
        "church"
    ],
    "sg:website":"www.onegod.dk3.com",
    "wof:name":"United Pentecostal Church",
    "wof:placetype":"venue"
},
  "geometry": {"coordinates":[-81.794802,26.354994],"type":"Point"}
}