{
  "type": "Feature",
  "properties": {
    "addr:full":"1910 SW 134th Ave Miami FL 33175",
    "addr:housenumber":"1910",
    "addr:postcode":"33175",
    "addr:street":"Sw 134Th Ave",
    "iso:country":"US",
    "sg:address":"1910 SW 134th Ave",
    "sg:city":"Miami",
    "sg:classifiers":[
        {
            "category":"Building & Trades",
            "subcategory":"Construction",
            "type":"Services"
        }
    ],
    "sg:phone":"+1 305 225 5571",
    "sg:postcode":"33175",
    "sg:province":"FL",
    "sg:tags":[
        "roofing",
        "contractor"
    ],
    "wof:name":"Mainland Construction Co",
    "wof:placetype":"venue"
},
  "geometry": {"coordinates":[-80.41306,25.749253],"type":"Point"}
}