{
  "type": "Feature",
  "properties": {
    "iso:country":"US",
    "sg:address":"6342 Arlington Expy",
    "sg:city":"Jacksonville",
    "sg:classifiers":[
        {
            "category":"Local Transit",
            "type":"Transportation"
        }
    ],
    "sg:phone":"+1 904 721 6769",
    "sg:postcode":"32211",
    "sg:province":"FL",
    "sg:tags":[
        "limousine"
    ],
    "wof:name":"P & B Charter Limousine Svc",
    "wof:placetype":"venue"
},
  "geometry": {"coordinates":[-81.593384,30.327575],"type":"Point"}
}