{
  "type": "Feature",
  "properties": {
    "iso:country":"US",
    "sg:address":"5113 SE 4th St",
    "sg:city":"Ocala",
    "sg:classifiers":[
        {
            "category":"Shopping",
            "subcategory":"Discount & Variety Stores",
            "type":"Retail Goods"
        }
    ],
    "sg:phone":"+1 352 624 8929",
    "sg:postcode":"34471",
    "sg:province":"FL",
    "sg:tags":[
        "merchandise",
        "general"
    ],
    "wof:name":"Barbara Mizell Retailer",
    "wof:placetype":"venue"
},
  "geometry": {"coordinates":[-82.063019,29.183025],"type":"Point"}
}