{
  "type": "Feature",
  "properties": {
    "iso:country":"US",
    "sg:address":"207 Circle S",
    "sg:city":"Sebring",
    "sg:classifiers":[
        {
            "category":"Home & Garden",
            "subcategory":"Furniture",
            "type":"Retail Goods"
        },
        {
            "category":"Shopping",
            "subcategory":"Gifts & Souvenirs",
            "type":"Retail Goods"
        }
    ],
    "sg:phone":"+1 863 402 8271",
    "sg:postcode":"33870",
    "sg:province":"FL",
    "sg:tags":[
        "shop"
    ],
    "wof:name":"Iris & Butterflies Inc",
    "wof:placetype":"venue"
},
  "geometry": {"coordinates":[-81.44075599999999,27.495457],"type":"Point"}
}