{
  "type": "Feature",
  "properties": {
    "addr:full":"230 NE 70th St Miami FL 33138",
    "addr:housenumber":"230",
    "addr:postcode":"33138",
    "addr:street":"Ne 70Th St",
    "iso:country":"US",
    "sg:address":"230 NE 70th St",
    "sg:city":"Miami",
    "sg:classifiers":[
        {
            "category":"Manufacturing",
            "subcategory":"Metals",
            "type":"Manufacturing & Wholesale Goods"
        }
    ],
    "sg:phone":"+1 305 751 5161",
    "sg:postcode":"33138",
    "sg:province":"FL",
    "sg:tags":[
        "work",
        "iron"
    ],
    "wof:name":"Miami Artistic Marble",
    "wof:placetype":"venue"
},
  "geometry": {"coordinates":[-80.19184199999999,25.839199],"type":"Point"}
}