{
  "type": "Feature",
  "properties": {
    "iso:country":"US",
    "sg:address":"914 NW Laurel Cir",
    "sg:city":"Sebastian",
    "sg:classifiers":[
        {
            "category":"Personal",
            "type":"Services"
        }
    ],
    "sg:phone":"+1 772 664 1227",
    "sg:postcode":"32976",
    "sg:province":"FL",
    "wof:name":"Tandem Tunes Inc",
    "wof:placetype":"venue"
},
  "geometry": {"coordinates":[-80.523135,27.881681],"type":"Point"}
}