{
  "type": "Feature",
  "properties": {
    "addr:full":"8411 Kause Rd Pensacola FL 32506",
    "addr:housenumber":"8411",
    "addr:postcode":"32506",
    "addr:street":"Kause Rd",
    "iso:country":"US",
    "sg:address":"8411 Kause Rd",
    "sg:city":"Pensacola",
    "sg:classifiers":[
        {
            "category":"Home & Garden",
            "subcategory":"Hardware",
            "type":"Retail Goods"
        }
    ],
    "sg:phone":"+1 850 457 0685",
    "sg:postcode":"32506",
    "sg:province":"FL",
    "wof:name":"Hendricks Wayne",
    "wof:placetype":"venue"
},
  "geometry": {"coordinates":[-87.32321399999999,30.411835],"type":"Point"}
}