{
  "type": "Feature",
  "properties": {
    "addr:full":"15818 NW 11th St Hollywood FL 33028",
    "addr:housenumber":"15818",
    "addr:postcode":"33028",
    "addr:street":"Nw 11Th St",
    "iso:country":"US",
    "sg:address":"15818 NW 11th St",
    "sg:city":"Hollywood",
    "sg:classifiers":[
        {
            "category":"Real Estate",
            "subcategory":"Real Estate Agent",
            "type":"Services"
        }
    ],
    "sg:phone":"+1 754 246 0277",
    "sg:postcode":"33028",
    "sg:province":"FL",
    "wof:name":"Enterprise Grouping Inc",
    "wof:placetype":"venue"
},
  "geometry": {"coordinates":[-80.355642,26.016803],"type":"Point"}
}