{
  "type": "Feature",
  "properties": {
    "iso:country":"US",
    "sg:address":"1118 13th St",
    "sg:city":"Saint Cloud",
    "sg:classifiers":[
        {
            "category":"Autos & Motor Vehicles",
            "subcategory":"Automobile Sales",
            "type":"Retail Goods"
        }
    ],
    "sg:phone":"+1 407 892 2141",
    "sg:postcode":"34769",
    "sg:province":"FL",
    "wof:name":"Poffenbugh Frd-Lincoln-Mercury",
    "wof:placetype":"venue"
},
  "geometry": {"coordinates":[-81.28139299999999,28.246067],"type":"Point"}
}