{
  "type": "Feature",
  "properties": {
    "iso:country":"US",
    "sg:address":"14 Hardie Ln",
    "sg:city":"Fort Walton Bch",
    "sg:classifiers":[
        {
            "category":"Building & Trades",
            "subcategory":"Construction",
            "type":"Services"
        }
    ],
    "sg:phone":"+1 850 582 7587",
    "sg:postcode":"32547",
    "sg:province":"FL",
    "sg:tags":[
        "handyman"
    ],
    "wof:name":"Hubert Carpenter Handyman Svc",
    "wof:placetype":"venue"
},
  "geometry": {"coordinates":[-86.625743,30.441573],"type":"Point"}
}