{
  "type": "Feature",
  "properties": {
    "iso:country":"US",
    "sg:address":"23950 SW 132nd Ave",
    "sg:city":"Homestead",
    "sg:classifiers":[
        {
            "category":"Manufacturing",
            "subcategory":"Glass & Minerals",
            "type":"Manufacturing & Wholesale Goods"
        }
    ],
    "sg:phone":"+1 305 258 3662",
    "sg:postcode":"33032",
    "sg:province":"FL",
    "sg:tags":[
        "ready",
        "mixed",
        "mfg",
        "concrete"
    ],
    "wof:name":"Continental Florida Materials",
    "wof:placetype":"venue"
},
  "geometry": {"coordinates":[-80.404759,25.543419],"type":"Point"}
}