{
  "type": "Feature",
  "properties": {
    "addr:full":"2430 Mont Claire Ct Naples FL 34109",
    "addr:postcode":"2430;34109",
    "addr:street":"Mont Claire Ct",
    "iso:country":"US",
    "sg:address":"2430 Mont Claire Ct",
    "sg:city":"Naples",
    "sg:classifiers":[
        {
            "category":"Real Estate",
            "subcategory":"Real Estate Operator",
            "type":"Services"
        }
    ],
    "sg:phone":"+1 239 591 1963",
    "sg:postcode":"34109",
    "sg:province":"FL",
    "sg:tags":[
        "condominium"
    ],
    "wof:name":"Mont Claire Condominium Assn",
    "wof:placetype":"venue"
},
  "geometry": {"coordinates":[-81.776978,26.250325],"type":"Point"}
}