{
  "type": "Feature",
  "properties": {
    "iso:country":"US",
    "sg:address":"110 Vista Ave",
    "sg:city":"Eustis",
    "sg:classifiers":[
        {
            "category":"Communications",
            "subcategory":"Film & Video Production",
            "type":"Services"
        }
    ],
    "sg:phone":"+1 352 735 6116",
    "sg:postcode":"32726",
    "sg:province":"FL",
    "sg:tags":[
        "tv",
        "radio",
        "services-commercial",
        "companies-film"
    ],
    "sg:website":"http://www.videocopies.com",
    "wof:name":"Video Craft",
    "wof:placetype":"venue"
},
  "geometry": {"coordinates":[-81.65641599999999,28.82818],"type":"Point"}
}