{
  "type": "Feature",
  "properties": {
    "iso:country":"US",
    "sg:address":"85 Bay Woods Dr",
    "sg:city":"Safety Harbor",
    "sg:classifiers":[
        {
            "category":"Insurance",
            "subcategory":"Insurance Agent",
            "type":"Services"
        }
    ],
    "sg:phone":"+1 727 725 2490",
    "sg:postcode":"34695",
    "sg:province":"FL",
    "wof:name":"Michael Mc Namee",
    "wof:placetype":"venue"
},
  "geometry": {"coordinates":[-82.694621,28.014942],"type":"Point"}
}