{
  "type": "Feature",
  "properties": {
    "iso:country":"US",
    "sg:address":"316 SE 1st St",
    "sg:city":"Boynton Beach",
    "sg:classifiers":[
        {
            "category":"Retail",
            "subcategory":"Laundry & Dry Cleaning",
            "type":"Services"
        }
    ],
    "sg:phone":"+1 561 865 2077",
    "sg:postcode":"33435",
    "sg:province":"FL",
    "sg:tags":[
        "garment",
        "agent"
    ],
    "wof:name":"Sew Good Alterations",
    "wof:placetype":"venue"
},
  "geometry": {"coordinates":[-80.061983,26.524675],"type":"Point"}
}