{
  "type": "Feature",
  "properties": {
    "addr:full":"130 NE 2 Ave Miami FL 33132",
    "addr:housenumber":"130",
    "addr:postcode":"33132",
    "addr:street":"Ne 2 Ave",
    "iso:country":"US",
    "sg:address":"130 NE 2 Ave",
    "sg:city":"Miami",
    "sg:classifiers":[
        {
            "category":"Building & Trades",
            "subcategory":"Cleaning & Sanitation",
            "type":"Services"
        }
    ],
    "sg:phone":"+1 305 249 1516",
    "sg:postcode":"33132",
    "sg:province":"FL",
    "sg:tags":[
        "carpet"
    ],
    "sg:website":"www.bestchoicecarpetcleaning.com",
    "wof:name":"Mr T Carpet Upholstery & Tile Cleaning",
    "wof:placetype":"venue"
},
  "geometry": {"coordinates":[-80.190404,25.775777],"type":"Point"}
}