{
  "type": "Feature",
  "properties": {
    "iso:country":"US",
    "sg:address":"3078 Aviation Ave",
    "sg:city":"Miami",
    "sg:classifiers":[
        {
            "category":"Organizations",
            "subcategory":"Community Association",
            "type":"Services"
        }
    ],
    "sg:phone":"+1 305 856 1063",
    "sg:postcode":"33133",
    "sg:province":"FL",
    "sg:tags":[
        "management",
        "condominium"
    ],
    "wof:name":"Aviation Townhouse Inc",
    "wof:placetype":"venue"
},
  "geometry": {"coordinates":[-80.23549800000001,25.734538],"type":"Point"}
}