{
  "type": "Feature",
  "properties": {
    "addr:full":"6251 N Oriole Blvd Delray Beach FL 33484",
    "addr:housenumber":"6251",
    "addr:postcode":"33484",
    "addr:street":"N Oriole Blvd",
    "iso:country":"US",
    "sg:address":"6251 N Oriole Blvd",
    "sg:city":"Delray Beach",
    "sg:classifiers":[
        {
            "category":"Restaurant",
            "type":"Food & Drink"
        }
    ],
    "sg:phone":"+1 561 496 2393",
    "sg:postcode":"33484",
    "sg:province":"FL",
    "sg:tags":[
        "eating"
    ],
    "wof:name":"Le Cafe",
    "wof:placetype":"venue"
},
  "geometry": {"coordinates":[-80.143497,26.464443],"type":"Point"}
}