{
  "type": "Feature",
  "properties": {
    "iso:country":"US",
    "sg:address":"116 W Bloomingdale Ave",
    "sg:city":"Brandon",
    "sg:classifiers":[
        {
            "category":"Insurance",
            "subcategory":"Insurance Agent",
            "type":"Services"
        }
    ],
    "sg:phone":"+1 813 685 1796",
    "sg:postcode":"33511",
    "sg:province":"FL",
    "wof:name":"Emerald Financial Svc",
    "wof:placetype":"venue"
},
  "geometry": {"coordinates":[-82.288443,27.893704],"type":"Point"}
}