{
  "type": "Feature",
  "properties": {
    "addr:full":"11836 Little Creek Ln Jacksonville FL 32223",
    "addr:housenumber":"11836",
    "addr:postcode":"32223",
    "addr:street":"Little Creek Ln",
    "iso:country":"US",
    "sg:address":"11836 Little Creek Ln",
    "sg:city":"Jacksonville",
    "sg:classifiers":[
        {
            "category":"Building & Trades",
            "subcategory":"Construction",
            "type":"Services"
        }
    ],
    "sg:phone":"+1 904 292 4000",
    "sg:postcode":"32223",
    "sg:province":"FL",
    "sg:tags":[
        "irrigation",
        "yard",
        "drainage"
    ],
    "wof:name":"Ed Hebert & Associates Inc",
    "wof:placetype":"venue"
},
  "geometry": {"coordinates":[-81.64402,30.170143],"type":"Point"}
}