{
  "type": "Feature",
  "properties": {
    "addr:full":"820 25th St West Palm Beach FL 33407",
    "addr:housenumber":"820",
    "addr:postcode":"33407",
    "addr:street":"25Th St",
    "iso:country":"US",
    "sg:address":"820 25th St",
    "sg:city":"West Palm Beach",
    "sg:classifiers":[
        {
            "category":"Autos & Motor Vehicles",
            "subcategory":"Auto Supplies",
            "type":"Retail Goods"
        }
    ],
    "sg:phone":"+1 561 833 6742",
    "sg:postcode":"33407",
    "sg:province":"FL",
    "sg:tags":[
        "tire"
    ],
    "wof:name":"Economy Tire",
    "wof:placetype":"venue"
},
  "geometry": {"coordinates":[-80.060436,26.736359],"type":"Point"}
}