{
  "type": "Feature",
  "properties": {
    "iso:country":"US",
    "sg:address":"101 3rd St N",
    "sg:city":"Jacksonville",
    "sg:classifiers":[
        {
            "category":"Freight",
            "type":"Transportation"
        }
    ],
    "sg:phone":"+1 904 220 5503",
    "sg:postcode":"32250",
    "sg:province":"FL",
    "sg:tags":[
        "mover"
    ],
    "wof:name":"San Pablo Movers",
    "wof:placetype":"venue"
},
  "geometry": {"coordinates":[-81.39214699999999,30.290035],"type":"Point"}
}