{
  "type": "Feature",
  "properties": {
    "iso:country":"US",
    "sg:address":"17195 U.S. Hwy 441",
    "sg:city":"Mount Dora",
    "sg:classifiers":[
        {
            "category":"Ice Cream",
            "type":"Food & Drink"
        }
    ],
    "sg:menulink":"http://www.allmenus.com/fl/apopka/293559-the-big-twist/menu/",
    "sg:phone":"+1 352 589 8978",
    "sg:postcode":"32757",
    "sg:province":"FL",
    "wof:name":"The Big Twist",
    "wof:placetype":"venue"
},
  "geometry": {"coordinates":[-81.669735,28.820878],"type":"Point"}
}