{
  "type": "Feature",
  "properties": {
    "addr:full":"1036 Seba St Jacksonville FL 32205",
    "addr:housenumber":"1036",
    "addr:postcode":"32205",
    "addr:street":"Seba St",
    "iso:country":"US",
    "sg:address":"1036 Seba St",
    "sg:city":"Jacksonville",
    "sg:classifiers":[
        {
            "category":"Building & Trades",
            "subcategory":"Cleaning & Sanitation",
            "type":"Services"
        }
    ],
    "sg:phone":"+1 904 781 9889",
    "sg:postcode":"32205",
    "sg:province":"FL",
    "sg:tags":[
        "house"
    ],
    "wof:name":"C J Svc",
    "wof:placetype":"venue"
},
  "geometry": {"coordinates":[-81.74273100000001,30.307217],"type":"Point"}
}