{
  "type": "Feature",
  "properties": {
    "addr:full":"3766 SE Ocean Blvd Stuart FL 34996",
    "addr:housenumber":"3766",
    "addr:postcode":"34996",
    "addr:street":"Se Ocean Blvd",
    "iso:country":"US",
    "sg:address":"3766 SE Ocean Blvd",
    "sg:city":"Stuart",
    "sg:classifiers":[
        {
            "category":"Real Estate",
            "subcategory":"Real Estate Agent",
            "type":"Services"
        }
    ],
    "sg:phone":"+1 772 219 0803",
    "sg:postcode":"34996",
    "sg:province":"FL",
    "sg:tags":[
        "management"
    ],
    "wof:name":"Commercial Property Management",
    "wof:placetype":"venue"
},
  "geometry": {"coordinates":[-80.20098400000001,27.202767],"type":"Point"}
}