{
  "type": "Feature",
  "properties": {
    "iso:country":"US",
    "sg:address":"36120 Emerald Coast Pkwy",
    "sg:city":"Destin",
    "sg:classifiers":[
        {
            "category":"Restaurant",
            "type":"Food & Drink"
        }
    ],
    "sg:menulink":"http://www.allmenus.com/fl/fort-walton-beach/52173-cuvee-beach/menu/",
    "sg:phone":"+1 850 650 8900",
    "sg:postcode":"32541",
    "sg:province":"FL",
    "sg:tags":[
        "seafood",
        "american"
    ],
    "wof:name":"Cuvee Bistro",
    "wof:placetype":"venue"
},
  "geometry": {"coordinates":[-86.400938,30.386004],"type":"Point"}
}