{
  "type": "Feature",
  "properties": {
    "iso:country":"US",
    "sg:address":"400 S Orange Ave",
    "sg:city":"Orlando",
    "sg:classifiers":[
        {
            "category":"Government",
            "subcategory":"Office",
            "type":"Public Place"
        }
    ],
    "sg:phone":"+1 407 246 2244",
    "sg:postcode":"32801",
    "sg:province":"FL",
    "sg:tags":[
        "village"
    ],
    "wof:name":"Orlando Employee Benefits",
    "wof:placetype":"venue"
},
  "geometry": {"coordinates":[-81.378649,28.53701],"type":"Point"}
}