{
  "type": "Feature",
  "properties": {
    "iso:country":"US",
    "sg:address":"11405 Starkey Rd",
    "sg:city":"Largo",
    "sg:classifiers":[
        {
            "category":"Retail",
            "subcategory":"Veterinary Services",
            "type":"Services"
        }
    ],
    "sg:phone":"+1 727 398 1925",
    "sg:postcode":"33773",
    "sg:province":"FL",
    "sg:tags":[
        "veterinarian"
    ],
    "wof:name":"Lucy W Bartlett Dvm",
    "wof:placetype":"venue"
},
  "geometry": {"coordinates":[-82.762299,27.876408],"type":"Point"}
}