{
  "type": "Feature",
  "properties": {
    "iso:country":"US",
    "sg:address":"3221 Sand Lake Rd",
    "sg:city":"Longwood",
    "sg:classifiers":[
        {
            "category":"Education",
            "subcategory":"School",
            "type":"Public Place"
        }
    ],
    "sg:phone":"+1 407 869 8882",
    "sg:postcode":"32779",
    "sg:province":"FL",
    "sg:tags":[
        "consulting",
        "business"
    ],
    "wof:name":"Pace-Brantley Hall",
    "wof:placetype":"venue"
},
  "geometry": {"coordinates":[-81.445639,28.680036],"type":"Point"}
}