{
  "type": "Feature",
  "properties": {
    "addr:full":"11999 49th St N Clearwater FL 33762",
    "addr:housenumber":"11999",
    "addr:postcode":"33762",
    "addr:street":"49Th St N",
    "iso:country":"US",
    "sg:address":"11999 49th St N",
    "sg:city":"Clearwater",
    "sg:classifiers":[
        {
            "category":"Manufacturing",
            "subcategory":"Watercraft",
            "type":"Manufacturing & Wholesale Goods"
        }
    ],
    "sg:phone":"+1 727 573 2213",
    "sg:postcode":"33762",
    "sg:province":"FL",
    "sg:tags":[
        "boat"
    ],
    "wof:name":"Spectre Powerboats",
    "wof:placetype":"venue"
},
  "geometry": {"coordinates":[-82.700242,27.880384],"type":"Point"}
}