{
  "type": "Feature",
  "properties": {
    "addr:full":"286 Holly Rd Vero Beach FL 32963",
    "addr:housenumber":"286",
    "addr:postcode":"32963",
    "addr:street":"Holly Rd",
    "iso:country":"US",
    "sg:address":"286 Holly Rd",
    "sg:city":"Vero Beach",
    "sg:classifiers":[
        {
            "category":"Organizations",
            "subcategory":"Professional Association",
            "type":"Services"
        }
    ],
    "sg:phone":"+1 772 231 0365",
    "sg:postcode":"32963",
    "sg:province":"FL",
    "wof:name":"Florida State Mus Tachers Assn",
    "wof:placetype":"venue"
},
  "geometry": {"coordinates":[-80.36896400000001,27.660789],"type":"Point"}
}