{
  "type": "Feature",
  "properties": {
    "addr:full":"3041 Melson Ave Jacksonville FL 32254",
    "addr:housenumber":"3041",
    "addr:postcode":"32254",
    "addr:street":"Melson Ave",
    "iso:country":"US",
    "sg:address":"3041 Melson Ave",
    "sg:city":"Jacksonville",
    "sg:classifiers":[
        {
            "category":"Home & Garden",
            "subcategory":"Building Materials",
            "type":"Retail Goods"
        }
    ],
    "sg:phone":"+1 904 350 9112",
    "sg:postcode":"32254",
    "sg:province":"FL",
    "wof:name":"Jacksonville Brick & Door",
    "wof:placetype":"venue"
},
  "geometry": {"coordinates":[-81.72290599999999,30.356732],"type":"Point"}
}