{
  "type": "Feature",
  "properties": {
    "addr:full":"5200 US Hwy 98 E Santa Rosa Beach FL 32459",
    "addr:housenumber":"5200",
    "addr:postcode":"32459",
    "addr:street":"Us Hwy 98 E Santa Rosa Beach",
    "iso:country":"US",
    "sg:address":"5200 US Hwy 98 E",
    "sg:city":"Santa Rosa Beach",
    "sg:classifiers":[
        {
            "category":"Organizations",
            "subcategory":"Religious Organization",
            "type":"Services"
        }
    ],
    "sg:phone":"+1 850 231 2660",
    "sg:postcode":"32459",
    "sg:province":"FL",
    "wof:name":"Christian Intl Fmly Church",
    "wof:placetype":"venue"
},
  "geometry": {"coordinates":[-86.097695,30.356074],"type":"Point"}
}