{
  "type": "Feature",
  "properties": {
    "addr:full":"5282 Tiffany Anne Cir West Palm Beach FL 33417",
    "addr:housenumber":"5282",
    "addr:postcode":"33417",
    "addr:street":"Tiffany Anne Cir",
    "iso:country":"US",
    "sg:address":"5282 Tiffany Anne Cir",
    "sg:city":"West Palm Beach",
    "sg:classifiers":[
        {
            "category":"Professional",
            "subcategory":"Computer Services",
            "type":"Services"
        }
    ],
    "sg:phone":"+1 561 688 2392",
    "sg:postcode":"33417",
    "sg:province":"FL",
    "sg:tags":[
        "programing",
        "custom"
    ],
    "wof:name":"Eimaj Software Solutions Inc",
    "wof:placetype":"venue"
},
  "geometry": {"coordinates":[-80.123347,26.735975],"type":"Point"}
}