{
  "type": "Feature",
  "properties": {
    "iso:country":"US",
    "sg:address":"9166 Stonehenge Trl",
    "sg:city":"Tallahassee",
    "sg:classifiers":[
        {
            "category":"Professional",
            "subcategory":"Computer Services",
            "type":"Services"
        }
    ],
    "sg:phone":"+1 850 893 5486",
    "sg:postcode":"32312",
    "sg:province":"FL",
    "wof:name":"Tallahassee Computers LLC",
    "wof:placetype":"venue"
},
  "geometry": {"coordinates":[-84.246528,30.599605],"type":"Point"}
}