{
  "type": "Feature",
  "properties": {
    "iso:country":"US",
    "sg:address":"2442 Aspinwall St",
    "sg:city":"Sarasota",
    "sg:classifiers":[
        {
            "category":"Building & Trades",
            "subcategory":"Pest Control",
            "type":"Services"
        }
    ],
    "sg:phone":"+1 941 953 9797",
    "sg:postcode":"34237",
    "sg:province":"FL",
    "wof:name":"Kelly's Pest Control",
    "wof:placetype":"venue"
},
  "geometry": {"coordinates":[-82.521102,27.339246],"type":"Point"}
}