{
  "type": "Feature",
  "properties": {
    "addr:full":"7650 118th St Jacksonville FL 32244",
    "addr:housenumber":"7650",
    "addr:postcode":"32244",
    "addr:street":"118Th St",
    "iso:country":"US",
    "sg:address":"7650 118th St",
    "sg:city":"Jacksonville",
    "sg:classifiers":[
        {
            "category":"Building & Trades",
            "subcategory":"Construction",
            "type":"Services"
        }
    ],
    "sg:phone":"+1 904 779 7623",
    "sg:postcode":"32244",
    "sg:province":"FL",
    "sg:tags":[
        "hanging",
        "contractor"
    ],
    "wof:name":"Manuel Mata Inc",
    "wof:placetype":"venue"
},
  "geometry": {"coordinates":[-81.777784,30.233047],"type":"Point"}
}