{
  "type": "Feature",
  "properties": {
    "iso:country":"US",
    "sg:address":"5980 Coral Ridge Dr",
    "sg:city":"Pompano Beach",
    "sg:classifiers":[
        {
            "category":"Personal",
            "subcategory":"Beauty Salon",
            "type":"Services"
        }
    ],
    "sg:phone":"+1 954 753 4338",
    "sg:postcode":"33076",
    "sg:province":"FL",
    "sg:tags":[
        "shop"
    ],
    "wof:name":"Jade Nails 2 Inc",
    "wof:placetype":"venue"
},
  "geometry": {"coordinates":[-80.278924,26.304285],"type":"Point"}
}