{
  "type": "Feature",
  "properties": {
    "iso:country":"US",
    "sg:address":"4100 NE 2nd Ave",
    "sg:city":"Miami",
    "sg:classifiers":[
        {
            "category":"Wholesale",
            "subcategory":"Durable Goods & Equipment",
            "type":"Manufacturing & Wholesale Goods"
        }
    ],
    "sg:phone":"+1 305 571 1801",
    "sg:postcode":"33137",
    "sg:province":"FL",
    "sg:tags":[
        "exporter"
    ],
    "wof:name":"Italian Pavilion",
    "wof:placetype":"venue"
},
  "geometry": {"coordinates":[-80.191425,25.814784],"type":"Point"}
}