{
  "type": "Feature",
  "properties": {
    "iso:country":"US",
    "sg:address":"1707 N Monroe St",
    "sg:city":"Tallahassee",
    "sg:classifiers":[
        {
            "category":"Professional",
            "subcategory":"Business Services",
            "type":"Services"
        }
    ],
    "sg:phone":"+1 850 222 7007",
    "sg:postcode":"32303",
    "sg:province":"FL",
    "wof:name":"Glasshopper Gifts & Engraving",
    "wof:placetype":"venue"
},
  "geometry": {"coordinates":[-84.282325,30.46363],"type":"Point"}
}