{
  "type": "Feature",
  "properties": {
    "iso:country":"US",
    "sg:address":"3209 US Hwy 1",
    "sg:city":"Mims",
    "sg:classifiers":[
        {
            "category":"Professional",
            "type":"Services"
        }
    ],
    "sg:phone":"+1 321 267 1607",
    "sg:postcode":"32754",
    "sg:province":"FL",
    "sg:tags":[
        "establishment"
    ],
    "wof:name":"Charles J Hudick Ent Inc",
    "wof:placetype":"venue"
},
  "geometry": {"coordinates":[-80.85571,28.68836],"type":"Point"}
}