{
  "type": "Feature",
  "properties": {
    "addr:full":"3937 Lowson Blvd Delray Beach FL 33445",
    "addr:postcode":"3937;33445",
    "addr:street":"Lowson Blvd",
    "iso:country":"US",
    "sg:address":"3937 Lowson Blvd",
    "sg:city":"Delray Beach",
    "sg:classifiers":[
        {
            "category":"Building & Trades",
            "subcategory":"Construction",
            "type":"Services"
        }
    ],
    "sg:phone":"+1 561 638 4993",
    "sg:postcode":"33445",
    "sg:province":"FL",
    "sg:tags":[
        "general",
        "contractor"
    ],
    "wof:name":"Andoverconstruction",
    "wof:placetype":"venue"
},
  "geometry": {"coordinates":[-80.121711,26.445958],"type":"Point"}
}