{
  "type": "Feature",
  "properties": {
    "iso:country":"US",
    "sg:address":"1075 E Bucknell Ave",
    "sg:city":"Inverness",
    "sg:classifiers":[
        {
            "category":"Retail",
            "subcategory":"Repair Shop",
            "type":"Services"
        }
    ],
    "sg:phone":"+1 352 726 1133",
    "sg:postcode":"34450",
    "sg:province":"FL",
    "sg:tags":[
        "scooter",
        "motorcycle",
        "motor"
    ],
    "wof:name":"Dirt Devil Motor Sports",
    "wof:placetype":"venue"
},
  "geometry": {"coordinates":[-82.31219299999999,28.817179],"type":"Point"}
}