{
  "type": "Feature",
  "properties": {
    "addr:full":"6320 Johnson St Hollywood FL 33024",
    "addr:housenumber":"6320",
    "addr:postcode":"33024",
    "addr:street":"Johnson St",
    "iso:country":"US",
    "sg:address":"6320 Johnson St",
    "sg:city":"Hollywood",
    "sg:classifiers":[
        {
            "category":"Health Services",
            "subcategory":"Clinic",
            "type":"Services"
        }
    ],
    "sg:phone":"+1 954 986 0316",
    "sg:postcode":"33024",
    "sg:province":"FL",
    "wof:name":"Lr Medical Service Inc",
    "wof:placetype":"venue"
},
  "geometry": {"coordinates":[-80.215585,26.017398],"type":"Point"}
}