{
  "type": "Feature",
  "properties": {
    "iso:country":"US",
    "sg:address":"5353 49th St N",
    "sg:city":"St Petersburg",
    "sg:classifiers":[
        {
            "category":"Retail",
            "subcategory":"Auto Repair",
            "type":"Services"
        }
    ],
    "sg:phone":"+1 727 525 4553",
    "sg:postcode":"33709",
    "sg:province":"FL",
    "sg:tags":[
        "repairing",
        "automobile"
    ],
    "wof:name":"J & S Quality Car Care Ctr Inc",
    "wof:placetype":"venue"
},
  "geometry": {"coordinates":[-82.69987999999999,27.820748],"type":"Point"}
}