{
  "type": "Feature",
  "properties": {
    "iso:country":"US",
    "sg:address":"4611 SW 71st Ave",
    "sg:city":"Miami",
    "sg:classifiers":[
        {
            "category":"Professional",
            "type":"Services"
        }
    ],
    "sg:phone":"+1 305 661 0303",
    "sg:postcode":"33155",
    "sg:province":"FL",
    "sg:tags":[
        "arts",
        "artist"
    ],
    "wof:name":"Carlson Studios",
    "wof:placetype":"venue"
},
  "geometry": {"coordinates":[-80.308649,25.726579],"type":"Point"}
}