{
  "type": "Feature",
  "properties": {
    "addr:full":"1510 N Monroe St Tallahassee FL 32303",
    "addr:housenumber":"1510",
    "addr:postcode":"32303",
    "addr:street":"N Monroe St",
    "iso:country":"US",
    "sg:address":"1510 N Monroe St",
    "sg:city":"Tallahassee",
    "sg:classifiers":[
        {
            "category":"Restaurant",
            "type":"Food & Drink"
        }
    ],
    "sg:menulink":"http://www.allmenus.com/fl/tallahassee-central/207102-sonic/menu/",
    "sg:phone":"+1 850 222 9023",
    "sg:postcode":"32303",
    "sg:province":"FL",
    "sg:tags":[
        "burger",
        "american"
    ],
    "wof:name":"Sonic",
    "wof:placetype":"venue"
},
  "geometry": {"coordinates":[-84.28155,30.459482],"type":"Point"}
}