{
  "type": "Feature",
  "properties": {
    "iso:country":"US",
    "sg:address":"3440 E Lake Rd S",
    "sg:city":"Palm Harbor",
    "sg:classifiers":[
        {
            "category":"Real Estate",
            "subcategory":"Real Estate Services",
            "type":"Services"
        }
    ],
    "sg:phone":"+1 727 781 8896",
    "sg:postcode":"34685",
    "sg:province":"FL",
    "sg:tags":[
        "company",
        "title"
    ],
    "wof:name":"Alday Donalson Title Co",
    "wof:placetype":"venue"
},
  "geometry": {"coordinates":[-82.694231,28.097598],"type":"Point"}
}