{
  "type": "Feature",
  "properties": {
    "addr:full":"891 W 29th St Hialeah FL 33012",
    "addr:housenumber":"891",
    "addr:postcode":"33012",
    "addr:street":"W 29Th St",
    "iso:country":"US",
    "sg:address":"891 W 29th St",
    "sg:city":"Hialeah",
    "sg:classifiers":[
        {
            "category":"Social Services",
            "subcategory":"Child Care",
            "type":"Services"
        }
    ],
    "sg:phone":"+1 305 885 2490",
    "sg:postcode":"33012",
    "sg:province":"FL",
    "sg:tags":[
        "day"
    ],
    "wof:name":"We Love Kids Day Care Center",
    "wof:placetype":"venue"
},
  "geometry": {"coordinates":[-80.300102,25.8479],"type":"Point"}
}