{
  "type": "Feature",
  "properties": {
    "addr:full":"1750 S Volusia Ave Ste 1 Orange City FL 32763",
    "addr:housenumber":"1750",
    "addr:postcode":"32763",
    "addr:street":"S Volusia Ave Ste 1",
    "iso:country":"US",
    "sg:address":"1750 S Volusia Ave Ste 1",
    "sg:city":"Orange City",
    "sg:classifiers":[
        {
            "category":"Banks & Credit Unions",
            "subcategory":"Financial Services",
            "type":"Services"
        }
    ],
    "sg:phone":"+1 386 774 2531",
    "sg:postcode":"32763",
    "sg:province":"FL",
    "sg:tags":[
        "broker",
        "mortgage"
    ],
    "wof:name":"Flagship Mortgage Banc",
    "wof:placetype":"venue"
},
  "geometry": {"coordinates":[-81.298897,28.930401],"type":"Point"}
}