{
  "type": "Feature",
  "properties": {
    "addr:full":"2636 Coffee Pot Blvd NE Saint Petersburg FL 33704",
    "addr:housenumber":"2636",
    "addr:postcode":"33704",
    "addr:street":"Coffee Pot Blvd Ne",
    "iso:country":"US",
    "sg:address":"2636 Coffee Pot Blvd NE",
    "sg:city":"Saint Petersburg",
    "sg:classifiers":[
        {
            "category":"Banks & Credit Unions",
            "subcategory":"Investment Brokerage",
            "type":"Services"
        }
    ],
    "sg:phone":"+1 727 823 5964",
    "sg:postcode":"33704",
    "sg:province":"FL",
    "sg:tags":[
        "security"
    ],
    "wof:name":"Stockton Rucker Rhodes",
    "wof:placetype":"venue"
},
  "geometry": {"coordinates":[-82.633228,27.796529],"type":"Point"}
}