{
  "type": "Feature",
  "properties": {
    "iso:country":"US",
    "sg:address":"5791 SW 74th Ter Apt 7",
    "sg:city":"South Miami",
    "sg:classifiers":[
        {
            "category":"Real Estate",
            "subcategory":"Real Estate Operator",
            "type":"Services"
        }
    ],
    "sg:phone":"+1 305 665 9931",
    "sg:postcode":"33143",
    "sg:province":"FL",
    "sg:tags":[
        "apartment"
    ],
    "wof:name":"Palm Plaza Apartments",
    "wof:placetype":"venue"
},
  "geometry": {"coordinates":[-80.287201,25.7019],"type":"Point"}
}