{
  "type": "Feature",
  "properties": {
    "iso:country":"US",
    "sg:address":"9250 W Bay Harbor Dr",
    "sg:city":"Bay Harbor Isles",
    "sg:classifiers":[
        {
            "category":"Wholesale",
            "subcategory":"Jewelry",
            "type":"Manufacturing & Wholesale Goods"
        }
    ],
    "sg:phone":"+1 305 431 6879",
    "sg:postcode":"33154",
    "sg:province":"FL",
    "sg:tags":[
        "broker"
    ],
    "wof:name":"Jaime Grub Assoc Inc",
    "wof:placetype":"venue"
},
  "geometry": {"coordinates":[-80.13254499999999,25.883106],"type":"Point"}
}