{
  "type": "Feature",
  "properties": {
    "iso:country":"US",
    "sg:address":"4916 Glover Ln",
    "sg:city":"Milton",
    "sg:classifiers":[
        {
            "category":"Retail",
            "subcategory":"Auto Repair",
            "type":"Services"
        }
    ],
    "sg:phone":"+1 850 626 9499",
    "sg:postcode":"32570",
    "sg:province":"FL",
    "sg:tags":[
        "general",
        "supply"
    ],
    "wof:name":"Eddie Hobbs Automotive",
    "wof:placetype":"venue"
},
  "geometry": {"coordinates":[-87.06441100000001,30.62339],"type":"Point"}
}