{
  "type": "Feature",
  "properties": {
    "iso:country":"US",
    "sg:address":"1178 Hayes St",
    "sg:city":"Hollywood",
    "sg:classifiers":[
        {
            "category":"Real Estate",
            "subcategory":"Real Estate Agent",
            "type":"Services"
        }
    ],
    "sg:phone":"+1 954 929 9370",
    "sg:postcode":"33019",
    "sg:province":"FL",
    "wof:name":"Scandic Realty Inc",
    "wof:placetype":"venue"
},
  "geometry": {"coordinates":[-80.12964700000001,26.021025],"type":"Point"}
}