{
  "type": "Feature",
  "properties": {
    "addr:full":"3655 NW 58th St Miami FL 33142",
    "addr:housenumber":"3655",
    "addr:postcode":"33142",
    "addr:street":"Nw 58Th St",
    "iso:country":"US",
    "sg:address":"3655 NW 58th St",
    "sg:city":"Miami",
    "sg:classifiers":[
        {
            "category":"Professional",
            "subcategory":"Business Services",
            "type":"Services"
        }
    ],
    "sg:phone":"+1 305 633 9352",
    "sg:postcode":"33142",
    "sg:province":"FL",
    "wof:name":"Unicenter Enterprises Inc",
    "wof:placetype":"venue"
},
  "geometry": {"coordinates":[-80.25621,25.827223],"type":"Point"}
}