{
  "type": "Feature",
  "properties": {
    "iso:country":"US",
    "sg:address":"5975 W Sunrise Blvd",
    "sg:city":"Plantation",
    "sg:classifiers":[
        {
            "category":"Health Services",
            "subcategory":"Doctor",
            "type":"Services"
        }
    ],
    "sg:phone":"+1 954 791 4311",
    "sg:postcode":"33313",
    "sg:province":"FL",
    "sg:tags":[
        "physician",
        "surgeon"
    ],
    "sg:website":"www.obgyndigest.com",
    "wof:name":"South Florida Ob Gyn Svc",
    "wof:placetype":"venue"
},
  "geometry": {"coordinates":[-80.23028100000001,26.135819],"type":"Point"}
}