{
  "type": "Feature",
  "properties": {
    "addr:full":"6153 Central Ave New Port Richey FL 34653",
    "addr:housenumber":"6153",
    "addr:postcode":"34653",
    "addr:street":"Central Ave",
    "iso:country":"US",
    "sg:address":"6153 Central Ave",
    "sg:city":"New Port Richey",
    "sg:classifiers":[
        {
            "category":"Recreation",
            "subcategory":"Marina",
            "type":"Entertainment"
        }
    ],
    "sg:phone":"+1 727 815 1348",
    "sg:postcode":"34653",
    "sg:province":"FL",
    "sg:tags":[
        "repairing",
        "boat"
    ],
    "wof:name":"Kenneth Bunch Jr Boat Repair",
    "wof:placetype":"venue"
},
  "geometry": {"coordinates":[-82.712502,28.251889],"type":"Point"}
}