{
  "type": "Feature",
  "properties": {
    "iso:country":"US",
    "sg:address":"142 Masters Dr",
    "sg:city":"Saint Augustine",
    "sg:classifiers":[
        {
            "category":"Social Services",
            "subcategory":"Child Care",
            "type":"Services"
        }
    ],
    "sg:phone":"+1 904 829 5457",
    "sg:postcode":"32084",
    "sg:province":"FL",
    "sg:tags":[
        "center",
        "day"
    ],
    "wof:name":"Brandts Child Care Center",
    "wof:placetype":"venue"
},
  "geometry": {"coordinates":[-81.33254700000001,29.904654],"type":"Point"}
}