{
  "type": "Feature",
  "properties": {
    "iso:country":"US",
    "sg:address":"5320 Ingleside",
    "sg:city":"Leesburg",
    "sg:classifiers":[
        {
            "category":"Building & Trades",
            "subcategory":"Electrical",
            "type":"Services"
        }
    ],
    "sg:phone":"+1 352 326 0999",
    "sg:postcode":"34748",
    "sg:province":"FL",
    "sg:tags":[
        "electrician"
    ],
    "wof:name":"Arnold Osansky",
    "wof:placetype":"venue"
},
  "geometry": {"coordinates":[-81.86627900000001,28.714205],"type":"Point"}
}