{
  "type": "Feature",
  "properties": {
    "addr:full":"19124 2nd St NE Lutz FL 33549",
    "addr:housenumber":"19124",
    "addr:postcode":"33549",
    "addr:street":"2Nd St Ne",
    "iso:country":"US",
    "sg:address":"19124 2nd St NE",
    "sg:city":"Lutz",
    "sg:classifiers":[
        {
            "category":"Banks & Credit Unions",
            "subcategory":"Investment Brokerage",
            "type":"Services"
        }
    ],
    "sg:phone":"+1 813 909 2341",
    "sg:postcode":"33549",
    "sg:province":"FL",
    "sg:tags":[
        "advisory",
        "financial"
    ],
    "wof:name":"Burney Financial",
    "wof:placetype":"venue"
},
  "geometry": {"coordinates":[-82.45957300000001,28.15489],"type":"Point"}
}