{
  "type": "Feature",
  "properties": {
    "iso:country":"US",
    "sg:address":"525 W Yale St",
    "sg:city":"Orlando",
    "sg:classifiers":[
        {
            "category":"Professional",
            "subcategory":"Business Services",
            "type":"Services"
        }
    ],
    "sg:phone":"+1 407 835 1999",
    "sg:postcode":"32804",
    "sg:province":"FL",
    "wof:name":"Keith McIntyre & Associates",
    "wof:placetype":"venue"
},
  "geometry": {"coordinates":[-81.389032,28.569591],"type":"Point"}
}