{
  "type": "Feature",
  "properties": {
    "iso:country":"US",
    "sg:address":"12100 NW 110th Ave",
    "sg:city":"Reddick",
    "sg:classifiers":[
        {
            "category":"Wholesale",
            "subcategory":"Farm Supplies",
            "type":"Manufacturing & Wholesale Goods"
        }
    ],
    "sg:phone":"+1 352 591 4088",
    "sg:postcode":"32686",
    "sg:province":"FL",
    "sg:tags":[
        "livestock",
        "mfg"
    ],
    "wof:name":"A Bar B Ranch",
    "wof:placetype":"venue"
},
  "geometry": {"coordinates":[-82.305476,29.32365],"type":"Point"}
}