{
  "type": "Feature",
  "properties": {
    "addr:full":"1048 Kane Concourse Bay Harbor Islands FL 33154",
    "addr:housenumber":"1048",
    "addr:postcode":"33154",
    "addr:street":"Kane Concourse",
    "iso:country":"US",
    "sg:address":"1048 Kane Concourse",
    "sg:city":"Bay Harbor Islands",
    "sg:classifiers":[
        {
            "category":"Health Services",
            "subcategory":"Dentist",
            "type":"Services"
        }
    ],
    "sg:phone":"+1 305 867 8080",
    "sg:postcode":"33154",
    "sg:province":"FL",
    "wof:name":"Rosenbluth Morton D D S",
    "wof:placetype":"venue"
},
  "geometry": {"coordinates":[-80.13018099999999,25.88658],"type":"Point"}
}