{
  "type": "Feature",
  "properties": {
    "iso:country":"US",
    "sg:address":"4922 Lillian Hwy",
    "sg:city":"Pensacola",
    "sg:classifiers":[
        {
            "category":"Retail",
            "subcategory":"Auto Repair",
            "type":"Services"
        }
    ],
    "sg:phone":"+1 850 457 8225",
    "sg:postcode":"32506",
    "sg:province":"FL",
    "sg:tags":[
        "repairing",
        "automobile",
        "automotive",
        "general"
    ],
    "wof:name":"Baker's Automotive Specialist",
    "wof:placetype":"venue"
},
  "geometry": {"coordinates":[-87.28259199999999,30.426702],"type":"Point"}
}