{
  "type": "Feature",
  "properties": {
    "addr:full":"3231 Zillah St Tallahassee FL 32305",
    "addr:postcode":"3231;32305",
    "addr:street":"Zillah St",
    "iso:country":"US",
    "sg:address":"3231 Zillah St",
    "sg:city":"Tallahassee",
    "sg:classifiers":[
        {
            "category":"Professional",
            "type":"Services"
        }
    ],
    "sg:phone":"+1 850 656 9622",
    "sg:postcode":"32305",
    "sg:province":"FL",
    "sg:tags":[
        "scientist"
    ],
    "wof:name":"Celso Alaisa Consulting",
    "wof:placetype":"venue"
},
  "geometry": {"coordinates":[-84.268826,30.402101],"type":"Point"}
}