{
  "type": "Feature",
  "properties": {
    "addr:full":"2609 W de Leon St Tampa FL 33609",
    "addr:housenumber":"2609",
    "addr:postcode":"33609",
    "addr:street":"W De Leon St",
    "iso:country":"US",
    "sg:address":"2609 W de Leon St",
    "sg:city":"Tampa",
    "sg:classifiers":[
        {
            "category":"Professional",
            "subcategory":"Engineering",
            "type":"Services"
        }
    ],
    "sg:phone":"+1 813 874 9494",
    "sg:postcode":"33609",
    "sg:province":"FL",
    "sg:tags":[
        "consulting",
        "engineer"
    ],
    "sg:website":"www.carastro.com",
    "wof:name":"Carastro & Associates Inc",
    "wof:placetype":"venue"
},
  "geometry": {"coordinates":[-82.48607199999999,27.938637],"type":"Point"}
}