{
  "type": "Feature",
  "properties": {
    "iso:country":"US",
    "sg:address":"6509 2nd Ave S",
    "sg:city":"Saint Petersburg",
    "sg:classifiers":[
        {
            "category":"Building & Trades",
            "subcategory":"Construction",
            "type":"Services"
        }
    ],
    "sg:phone":"+1 727 381 3044",
    "sg:postcode":"33707",
    "sg:province":"FL",
    "sg:tags":[
        "contractor"
    ],
    "wof:name":"Perfect Joint Grout Systems",
    "wof:placetype":"venue"
},
  "geometry": {"coordinates":[-82.728222,27.769042],"type":"Point"}
}