{
  "type": "Feature",
  "properties": {
    "iso:country":"US",
    "sg:address":"120 University Park Dr",
    "sg:city":"Winter Park",
    "sg:classifiers":[
        {
            "category":"Organizations",
            "subcategory":"Non-profit Organization",
            "type":"Services"
        }
    ],
    "sg:phone":"+1 407 681 6080",
    "sg:postcode":"32792",
    "sg:province":"FL",
    "wof:name":"World Of Knowledge Foundation",
    "wof:placetype":"venue"
},
  "geometry": {"coordinates":[-81.304568,28.596543],"type":"Point"}
}