{
  "type": "Feature",
  "properties": {
    "iso:country":"US",
    "sg:address":"9905 NW 7th Ave",
    "sg:city":"Miami",
    "sg:classifiers":[
        {
            "category":"Autos & Motor Vehicles",
            "subcategory":"Automobile Sales",
            "type":"Retail Goods"
        }
    ],
    "sg:phone":"+1 305 758 7000",
    "sg:postcode":"33150",
    "sg:province":"FL",
    "sg:tags":[
        "car",
        "used",
        "dealer"
    ],
    "wof:name":"Tamiami Auto Sales Inc",
    "wof:placetype":"venue"
},
  "geometry": {"coordinates":[-80.209746,25.866322],"type":"Point"}
}