{
  "type": "Feature",
  "properties": {
    "iso:country":"US",
    "sg:address":"4598 Edgewater Dr",
    "sg:city":"Orlando",
    "sg:classifiers":[
        {
            "category":"Restaurant",
            "type":"Food & Drink"
        }
    ],
    "sg:phone":"+1 407 298 3832",
    "sg:postcode":"32804",
    "sg:province":"FL",
    "wof:name":"Italian Village Pizza",
    "wof:placetype":"venue"
},
  "geometry": {"coordinates":[-81.40435100000001,28.601742],"type":"Point"}
}