{
  "type": "Feature",
  "properties": {
    "iso:country":"US",
    "sg:address":"23020 State Rd 54",
    "sg:city":"Lutz",
    "sg:classifiers":[
        {
            "category":"Shopping",
            "type":"Retail Goods"
        }
    ],
    "sg:phone":"+1 813 909 7724",
    "sg:postcode":"33549",
    "sg:province":"FL",
    "sg:tags":[
        "merchandise"
    ],
    "sg:website":"www.americanpetsupplies.com",
    "wof:name":"American Pet Supply Corp",
    "wof:placetype":"venue"
},
  "geometry": {"coordinates":[-82.432489,28.186039],"type":"Point"}
}