{
  "type": "Feature",
  "properties": {
    "addr:full":"5834 Funston St Hollywood FL 33023",
    "addr:housenumber":"5834",
    "addr:postcode":"33023",
    "addr:street":"Funston St",
    "iso:country":"US",
    "sg:address":"5834 Funston St",
    "sg:city":"Hollywood",
    "sg:classifiers":[
        {
            "category":"Autos & Motor Vehicles",
            "subcategory":"Automobile Sales",
            "type":"Retail Goods"
        }
    ],
    "sg:phone":"+1 954 989 9777",
    "sg:postcode":"33023",
    "sg:province":"FL",
    "sg:tags":[
        "car",
        "dealer"
    ],
    "wof:name":"Regal International Motor Cars",
    "wof:placetype":"venue"
},
  "geometry": {"coordinates":[-80.204734,26.000313],"type":"Point"}
}