{
  "type": "Feature",
  "properties": {
    "iso:country":"US",
    "sg:address":"2705 Rebecca Ln Ste B",
    "sg:city":"Orange City",
    "sg:classifiers":[
        {
            "category":"Health Services",
            "subcategory":"Doctor",
            "type":"Services"
        }
    ],
    "sg:phone":"+1 386 917 0450",
    "sg:postcode":"32763",
    "sg:province":"FL",
    "sg:website":"www.cfpeds.com",
    "wof:name":"Central Florida Pediatrics",
    "wof:placetype":"venue"
},
  "geometry": {"coordinates":[-81.292337,28.906899],"type":"Point"}
}