{
  "type": "Feature",
  "properties": {
    "addr:full":"3650 Miami Ave Melbourne FL 32904",
    "addr:housenumber":"3650",
    "addr:postcode":"32904",
    "addr:street":"Miami Ave",
    "iso:country":"US",
    "sg:address":"3650 Miami Ave",
    "sg:city":"Melbourne",
    "sg:classifiers":[
        {
            "category":"Building & Trades",
            "subcategory":"Construction",
            "type":"Services"
        }
    ],
    "sg:phone":"+1 321 984 7859",
    "sg:postcode":"32904",
    "sg:province":"FL",
    "sg:tags":[
        "stucco",
        "contractor"
    ],
    "wof:name":"Pace Brothers Stucco Contrs",
    "wof:placetype":"venue"
},
  "geometry": {"coordinates":[-80.68496500000001,28.0754],"type":"Point"}
}