{
  "type": "Feature",
  "properties": {
    "iso:country":"US",
    "sg:address":"425 Industrial St",
    "sg:city":"Lake Worth",
    "sg:classifiers":[
        {
            "category":"Retail",
            "subcategory":"Repair Shop",
            "type":"Services"
        }
    ],
    "sg:phone":"+1 561 540 3964",
    "sg:postcode":"33461",
    "sg:province":"FL",
    "sg:tags":[
        "contractor"
    ],
    "wof:name":"Roto-Rooter Services Company",
    "wof:placetype":"venue"
},
  "geometry": {"coordinates":[-80.068138,26.62262],"type":"Point"}
}