{
  "type": "Feature",
  "properties": {
    "addr:full":"420 N Bayshore Blvd Clearwater FL 33759",
    "addr:housenumber":"420",
    "addr:postcode":"33759",
    "addr:street":"N Bayshore Blvd",
    "iso:country":"US",
    "sg:address":"420 N Bayshore Blvd",
    "sg:city":"Clearwater",
    "sg:classifiers":[
        {
            "category":"Professional",
            "subcategory":"Computer Services",
            "type":"Services"
        }
    ],
    "sg:phone":"+1 727 725 1434",
    "sg:postcode":"33759",
    "sg:province":"FL",
    "sg:tags":[
        "home",
        "consulting",
        "page",
        "dev",
        "internet"
    ],
    "wof:name":"Jane Web Smith Inc",
    "wof:placetype":"venue"
},
  "geometry": {"coordinates":[-82.698543,27.97161],"type":"Point"}
}