{
  "type": "Feature",
  "properties": {
    "iso:country":"US",
    "sg:address":"1197 Mayport Rd",
    "sg:city":"Atlantic Beach",
    "sg:classifiers":[
        {
            "category":"Health Services",
            "subcategory":"Health Practitioner",
            "type":"Services"
        }
    ],
    "sg:phone":"+1 904 241 4112",
    "sg:postcode":"32233",
    "sg:province":"FL",
    "sg:tags":[
        "therapist",
        "physical"
    ],
    "wof:name":"Gentle Way Physical Therapy",
    "wof:placetype":"venue"
},
  "geometry": {"coordinates":[-81.416085,30.332333],"type":"Point"}
}