{
  "type": "Feature",
  "properties": {
    "iso:country":"US",
    "sg:address":"6920 150th Ave N",
    "sg:city":"Clearwater",
    "sg:classifiers":[
        {
            "category":"Building & Trades",
            "subcategory":"Cleaning & Sanitation",
            "type":"Services"
        },
        {
            "category":"Retail",
            "subcategory":"Car Wash",
            "type":"Services"
        }
    ],
    "sg:phone":"+1 727 867 7877",
    "sg:postcode":"33764",
    "sg:province":"FL",
    "sg:tags":[
        "washing",
        "pressure",
        "house",
        "contractor",
        "equipment",
        "cleaning-industrial",
        "janitorial"
    ],
    "sg:website":"http://www.rubadubmaid.com",
    "wof:name":"A Rub-A-Dub Maid",
    "wof:placetype":"venue"
},
  "geometry": {"coordinates":[-82.735237,27.90888],"type":"Point"}
}