{
  "type": "Feature",
  "properties": {
    "iso:country":"US",
    "sg:address":"1368 N University Dr",
    "sg:city":"Plantation",
    "sg:classifiers":[
        {
            "category":"Insurance",
            "subcategory":"Insurance Agent",
            "type":"Services"
        }
    ],
    "sg:phone":"+1 954 475 0233",
    "sg:postcode":"33322",
    "sg:province":"FL",
    "wof:name":"Dan Sawyer Insurance",
    "wof:placetype":"venue"
},
  "geometry": {"coordinates":[-80.25311499999999,26.244929],"type":"Point"}
}