{
  "type": "Feature",
  "properties": {
    "iso:country":"US",
    "sg:address":"6600 NW 27th Ave",
    "sg:city":"Miami",
    "sg:classifiers":[
        {
            "category":"Insurance",
            "subcategory":"Insurance Agent",
            "type":"Services"
        }
    ],
    "sg:phone":"+1 305 835 6766",
    "sg:postcode":"33147",
    "sg:province":"FL",
    "wof:name":"R H R Enterprises",
    "wof:placetype":"venue"
},
  "geometry": {"coordinates":[-80.24136,25.834812],"type":"Point"}
}