{
  "type": "Feature",
  "properties": {
    "iso:country":"US",
    "sg:address":"11554 Grove St",
    "sg:city":"Seminole",
    "sg:classifiers":[
        {
            "category":"Wholesale",
            "subcategory":"Machinery & Supplies",
            "type":"Manufacturing & Wholesale Goods"
        }
    ],
    "sg:phone":"+1 727 397 5462",
    "sg:postcode":"33772",
    "sg:province":"FL",
    "sg:tags":[
        "equipment"
    ],
    "wof:name":"Bsh Corp",
    "wof:placetype":"venue"
},
  "geometry": {"coordinates":[-82.79798,27.823778],"type":"Point"}
}