{
  "type": "Feature",
  "properties": {
    "addr:full":"7204 Dusty Rd Riverview FL 33569",
    "addr:housenumber":"7204",
    "addr:postcode":"33569",
    "addr:street":"Dusty Rd",
    "iso:country":"US",
    "sg:address":"7204 Dusty Rd",
    "sg:city":"Riverview",
    "sg:classifiers":[
        {
            "category":"Building & Trades",
            "subcategory":"Construction",
            "type":"Services"
        }
    ],
    "sg:phone":"+1 813 672 0479",
    "sg:postcode":"33569",
    "sg:province":"FL",
    "sg:tags":[
        "carpentry",
        "carpenter",
        "contractor"
    ],
    "wof:name":"R A Fulmore Corp",
    "wof:placetype":"venue"
},
  "geometry": {"coordinates":[-82.30429700000001,27.877601],"type":"Point"}
}