{
  "type": "Feature",
  "properties": {
    "iso:country":"US",
    "sg:address":"4040 Higbee St",
    "sg:city":"Port Charlotte",
    "sg:classifiers":[
        {
            "category":"Building & Trades",
            "subcategory":"Construction",
            "type":"Services"
        }
    ],
    "sg:phone":"+1 941 766 0101",
    "sg:postcode":"33948",
    "sg:province":"FL",
    "sg:tags":[
        "designer",
        "marine",
        "contractor"
    ],
    "wof:name":"M & M Marine Construction",
    "wof:placetype":"venue"
},
  "geometry": {"coordinates":[-82.129959,26.972633],"type":"Point"}
}