{
  "type": "Feature",
  "properties": {
    "iso:country":"US",
    "sg:address":"6677 Sunset Dr",
    "sg:city":"Miami",
    "sg:classifiers":[
        {
            "category":"Home & Garden",
            "subcategory":"Building Materials",
            "type":"Retail Goods"
        }
    ],
    "sg:phone":"+1 786 401 2045",
    "sg:postcode":"33143",
    "sg:province":"FL",
    "wof:name":"Emergency Locksmiths 24 Hour",
    "wof:placetype":"venue"
},
  "geometry": {"coordinates":[-80.30121699999999,25.703841],"type":"Point"}
}