{
  "type": "Feature",
  "properties": {
    "iso:country":"US",
    "sg:address":"2332 SW 67th Ave",
    "sg:city":"Miami",
    "sg:classifiers":[
        {
            "category":"Wholesale",
            "subcategory":"Medical Equipment & Supplies",
            "type":"Manufacturing & Wholesale Goods"
        }
    ],
    "sg:phone":"+1 305 266 2388",
    "sg:postcode":"33155",
    "sg:province":"FL",
    "wof:name":"A P Medical Services Inc",
    "wof:placetype":"venue"
},
  "geometry": {"coordinates":[-80.303618,25.74812],"type":"Point"}
}