{
  "type": "Feature",
  "properties": {
    "addr:full":"6540 Metrowest Blvd # 322 Orlando FL 32835",
    "addr:housenumber":"6540",
    "addr:postcode":"32835",
    "addr:street":"Metrowest Blvd # 322",
    "iso:country":"US",
    "sg:address":"6540 Metrowest Blvd # 322",
    "sg:city":"Orlando",
    "sg:classifiers":[
        {
            "category":"Shopping",
            "type":"Retail Goods"
        }
    ],
    "sg:phone":"+1 248 255 1574",
    "sg:postcode":"32835",
    "sg:province":"FL",
    "sg:tags":[
        "merchandising"
    ],
    "wof:name":"Head International",
    "wof:placetype":"venue"
},
  "geometry": {"coordinates":[-81.47233199999999,28.518238],"type":"Point"}
}