{
  "type": "Feature",
  "properties": {
    "iso:country":"US",
    "sg:address":"634 Coldstream Ct",
    "sg:city":"Naples",
    "sg:classifiers":[
        {
            "category":"Professional",
            "subcategory":"Business Services",
            "type":"Services"
        }
    ],
    "sg:phone":"+1 239 435 1926",
    "sg:postcode":"34104",
    "sg:province":"FL",
    "sg:tags":[
        "management",
        "open",
        "investment"
    ],
    "wof:name":"B R P M",
    "wof:placetype":"venue"
},
  "geometry": {"coordinates":[-81.74992,26.159613],"type":"Point"}
}