{
  "type": "Feature",
  "properties": {
    "iso:country":"US",
    "sg:address":"6213 Apalachee Pkwy",
    "sg:city":"Tallahassee",
    "sg:classifiers":[
        {
            "category":"Manufacturing",
            "subcategory":"Metals",
            "type":"Manufacturing & Wholesale Goods"
        }
    ],
    "sg:phone":"+1 850 878 8857",
    "sg:postcode":"32311",
    "sg:province":"FL",
    "sg:tags":[
        "steel",
        "distributor",
        "mill",
        "warehouse"
    ],
    "wof:name":"Quick Brothers Steel Inc",
    "wof:placetype":"venue"
},
  "geometry": {"coordinates":[-84.172011,30.423226],"type":"Point"}
}