{
  "type": "Feature",
  "properties": {
    "addr:full":"3284 W New Haven Ave Melbourne FL 32904",
    "addr:housenumber":"3284",
    "addr:postcode":"32904",
    "addr:street":"W New Haven Ave",
    "iso:country":"US",
    "sg:address":"3284 W New Haven Ave",
    "sg:city":"Melbourne",
    "sg:classifiers":[
        {
            "category":"Personal",
            "subcategory":"Massage",
            "type":"Services"
        }
    ],
    "sg:phone":"+1 321 626 7160",
    "sg:postcode":"32904",
    "sg:province":"FL",
    "wof:name":"Good Steward Massage A",
    "wof:placetype":"venue"
},
  "geometry": {"coordinates":[-80.676361,28.07897],"type":"Point"}
}