{
  "type": "Feature",
  "properties": {
    "addr:full":"3250 NW 107th Ave Doral FL 33172",
    "addr:housenumber":"3250",
    "addr:postcode":"33172",
    "addr:street":"Nw 107Th Ave",
    "iso:country":"US",
    "sg:address":"3250 NW 107th Ave",
    "sg:city":"Doral",
    "sg:classifiers":[
        {
            "category":"Insurance",
            "subcategory":"Title Insurance",
            "type":"Services"
        }
    ],
    "sg:phone":"+1 305 477 7566",
    "sg:postcode":"33172",
    "sg:province":"FL",
    "wof:name":"Experience Title Solutions Inc",
    "wof:placetype":"venue"
},
  "geometry": {"coordinates":[-80.36937500000001,25.804036],"type":"Point"}
}