{
  "type": "Feature",
  "properties": {
    "addr:full":"7210 NW 74th Ave Miami FL 33166",
    "addr:housenumber":"7210",
    "addr:postcode":"33166",
    "addr:street":"Nw 74Th Ave",
    "iso:country":"US",
    "sg:address":"7210 NW 74th Ave",
    "sg:city":"Miami",
    "sg:classifiers":[
        {
            "category":"Autos & Motor Vehicles",
            "subcategory":"Automobile Sales",
            "type":"Retail Goods"
        }
    ],
    "sg:phone":"+1 305 887 3585",
    "sg:postcode":"33166",
    "sg:province":"FL",
    "sg:tags":[
        "truck"
    ],
    "sg:website":"www.alliedtruck.com",
    "wof:name":"Allied Truck & Machinery Sales",
    "wof:placetype":"venue"
},
  "geometry": {"coordinates":[-80.318191,25.839802],"type":"Point"}
}