{
  "type": "Feature",
  "properties": {
    "addr:full":"100 Winners Ct Lehigh Acres FL 33936",
    "addr:housenumber":"100",
    "addr:postcode":"33936",
    "addr:street":"Winners Ct",
    "iso:country":"US",
    "sg:address":"100 Winners Ct",
    "sg:city":"Lehigh Acres",
    "sg:classifiers":[
        {
            "category":"Building & Trades",
            "subcategory":"Landscaping Services",
            "type":"Services"
        }
    ],
    "sg:phone":"+1 239 303 2335",
    "sg:postcode":"33936",
    "sg:province":"FL",
    "wof:name":"Joseph Ebner Lawn",
    "wof:placetype":"venue"
},
  "geometry": {"coordinates":[-81.61013699999999,26.604836],"type":"Point"}
}