{
  "type": "Feature",
  "properties": {
    "iso:country":"US",
    "sg:address":"1092 Swan St",
    "sg:city":"Melbourne",
    "sg:classifiers":[
        {
            "category":"Community Center",
            "type":"Public Place"
        }
    ],
    "sg:phone":"+1 321 255 4625",
    "sg:postcode":"32935",
    "sg:province":"FL",
    "sg:tags":[
        "recreation"
    ],
    "wof:name":"Carver Park",
    "wof:placetype":"venue"
},
  "geometry": {"coordinates":[-80.63851099999999,28.141606],"type":"Point"}
}