{
  "type": "Feature",
  "properties": {
    "iso:country":"US",
    "sg:address":"1661 W University Pkwy",
    "sg:city":"Sarasota",
    "sg:classifiers":[
        {
            "category":"Manufacturing",
            "subcategory":"Watercraft",
            "type":"Manufacturing & Wholesale Goods"
        }
    ],
    "sg:phone":"+1 941 351 3760",
    "sg:postcode":"34243",
    "sg:province":"FL",
    "sg:tags":[
        "boat"
    ],
    "sg:website":"www.phantomboats.com",
    "wof:name":"Phantom Boats Inc",
    "wof:placetype":"venue"
},
  "geometry": {"coordinates":[-82.53422,27.388848],"type":"Point"}
}