{
  "type": "Feature",
  "properties": {
    "iso:country":"US",
    "sg:address":"808 W Washington St",
    "sg:city":"Orlando",
    "sg:classifiers":[
        {
            "category":"Restaurant",
            "type":"Food & Drink"
        }
    ],
    "sg:menulink":"http://www.allmenus.com/fl/orlando/33972-dexters-of-thornton-park/menu/",
    "sg:phone":"+1 407 648 2777",
    "sg:postcode":"32805",
    "sg:province":"FL",
    "sg:tags":[
        "american"
    ],
    "wof:name":"Dexter's of Thornton Park",
    "wof:placetype":"venue"
},
  "geometry": {"coordinates":[-81.391335,28.543845],"type":"Point"}
}