{
  "type": "Feature",
  "properties": {
    "iso:country":"US",
    "sg:address":"14373 SW 62nd St",
    "sg:city":"Miami",
    "sg:classifiers":[
        {
            "category":"Building & Trades",
            "subcategory":"Construction",
            "type":"Services"
        }
    ],
    "sg:phone":"+1 305 408 9129",
    "sg:postcode":"33183",
    "sg:province":"FL",
    "sg:tags":[
        "house"
    ],
    "wof:name":"Gus Remodeling Service Inc",
    "wof:placetype":"venue"
},
  "geometry": {"coordinates":[-80.42183799999999,25.709301],"type":"Point"}
}