{
  "type": "Feature",
  "properties": {
    "addr:full":"120 Perviz Ave Opa Locka FL 33054",
    "addr:housenumber":"120",
    "addr:postcode":"33054",
    "addr:street":"Perviz Ave;Locka",
    "iso:country":"US",
    "sg:address":"120 Perviz Ave",
    "sg:city":"Opa Locka",
    "sg:classifiers":[
        {
            "category":"Government",
            "subcategory":"Office",
            "type":"Public Place"
        }
    ],
    "sg:phone":"+1 305 687 2886",
    "sg:postcode":"33054",
    "sg:province":"FL",
    "wof:name":"Employment Assistance Ctr",
    "wof:placetype":"venue"
},
  "geometry": {"coordinates":[-80.25290200000001,25.90349],"type":"Point"}
}