{
  "type": "Feature",
  "properties": {
    "iso:country":"US",
    "sg:address":"551 NE 5th St",
    "sg:city":"Pompano Beach",
    "sg:classifiers":[
        {
            "category":"Restaurant",
            "type":"Food & Drink"
        }
    ],
    "sg:phone":"+1 954 782 6667",
    "sg:postcode":"33060",
    "sg:province":"FL",
    "sg:tags":[
        "cafe",
        "catering"
    ],
    "wof:name":"Lakeside Cafe",
    "wof:placetype":"venue"
},
  "geometry": {"coordinates":[-80.117194,26.236228],"type":"Point"}
}