{
  "type": "Feature",
  "properties": {
    "iso:country":"US",
    "sg:address":"846 NW 7th St",
    "sg:city":"Boca Raton",
    "sg:classifiers":[
        {
            "category":"Building & Trades",
            "subcategory":"Construction",
            "type":"Services"
        }
    ],
    "sg:phone":"+1 561 620 2850",
    "sg:postcode":"33486",
    "sg:province":"FL",
    "sg:tags":[
        "contractor"
    ],
    "wof:name":"Solypa Pools Inc",
    "wof:placetype":"venue"
},
  "geometry": {"coordinates":[-80.103275,26.357067],"type":"Point"}
}