{
  "type": "Feature",
  "properties": {
    "addr:full":"912 Linda Ct Royal Palm Beach FL 33411",
    "addr:housenumber":"912",
    "addr:postcode":"33411",
    "addr:street":"Linda Ct",
    "iso:country":"US",
    "sg:address":"912 Linda Ct",
    "sg:city":"Royal Palm Beach",
    "sg:classifiers":[
        {
            "category":"Real Estate",
            "subcategory":"Real Estate Agent",
            "type":"Services"
        },
        {
            "category":"Building & Trades",
            "subcategory":"Landscaping Services",
            "type":"Services"
        }
    ],
    "sg:phone":"+1 561 790 1789",
    "sg:postcode":"33411",
    "sg:province":"FL",
    "sg:tags":[
        "management",
        "landscape"
    ],
    "wof:name":"Grassmart Inc",
    "wof:placetype":"venue"
},
  "geometry": {"coordinates":[-80.226749,26.690966],"type":"Point"}
}