{
  "type": "Feature",
  "properties": {
    "iso:country":"US",
    "sg:address":"2420 Concorde Dr Ste 8",
    "sg:city":"Fort Myers",
    "sg:classifiers":[
        {
            "category":"Retail",
            "subcategory":"Auto Repair",
            "type":"Services"
        }
    ],
    "sg:phone":"+1 239 939 1448",
    "sg:postcode":"33901",
    "sg:province":"FL",
    "wof:name":"Innovative Motorwerkes",
    "wof:placetype":"venue"
},
  "geometry": {"coordinates":[-81.863297,26.603901],"type":"Point"}
}