{
  "type": "Feature",
  "properties": {
    "iso:country":"US",
    "sg:address":"2543 Coolidge Ave",
    "sg:city":"Orlando",
    "sg:classifiers":[
        {
            "category":"Professional",
            "subcategory":"Management & Consulting",
            "type":"Services"
        }
    ],
    "sg:phone":"+1 407 947 2224",
    "sg:postcode":"32804",
    "sg:province":"FL",
    "sg:tags":[
        "break",
        "coffee",
        "supply"
    ],
    "wof:name":"Executive Coffee Svc",
    "wof:placetype":"venue"
},
  "geometry": {"coordinates":[-81.402889,28.574726],"type":"Point"}
}