{
  "type": "Feature",
  "properties": {
    "iso:country":"US",
    "sg:address":"28163 US Hwy 19",
    "sg:city":"Clearwater",
    "sg:classifiers":[
        {
            "category":"Banks & Credit Unions",
            "subcategory":"Bank",
            "type":"Services"
        }
    ],
    "sg:phone":"+1 727 799 6009",
    "sg:postcode":"33761",
    "sg:province":"FL",
    "sg:tags":[
        "mortgage"
    ],
    "wof:name":"NVR",
    "wof:placetype":"venue"
},
  "geometry": {"coordinates":[-82.738078,28.028167],"type":"Point"}
}