{
  "type": "Feature",
  "properties": {
    "addr:full":"1323 E Tennessee St Tallahassee FL 32308",
    "addr:housenumber":"1323",
    "addr:postcode":"32308",
    "addr:street":"E Tennessee St",
    "iso:country":"US",
    "sg:address":"1323 E Tennessee St",
    "sg:city":"Tallahassee",
    "sg:classifiers":[
        {
            "category":"Travel",
            "subcategory":"Travel Agent",
            "type":"Entertainment"
        }
    ],
    "sg:phone":"+1 850 942 8687",
    "sg:postcode":"32308",
    "sg:province":"FL",
    "sg:tags":[
        "bus",
        "charter",
        "agency"
    ],
    "wof:name":"Springdale Tours Inc",
    "wof:placetype":"venue"
},
  "geometry": {"coordinates":[-84.262119,30.447656],"type":"Point"}
}