{
  "type": "Feature",
  "properties": {
    "iso:country":"US",
    "sg:address":"240 SW 58th St",
    "sg:city":"Ocala",
    "sg:classifiers":[
        {
            "category":"Real Estate",
            "subcategory":"Real Estate Services",
            "type":"Services"
        }
    ],
    "sg:phone":"+1 352 624 9700",
    "sg:postcode":"34471",
    "sg:province":"FL",
    "sg:tags":[
        "abstract",
        "title"
    ],
    "wof:name":"Superior Title Ins Agency Mari",
    "wof:placetype":"venue"
},
  "geometry": {"coordinates":[-82.138138,29.130108],"type":"Point"}
}