{
  "type": "Feature",
  "properties": {
    "iso:country":"US",
    "sg:address":"2645 SW 37th Ave",
    "sg:city":"Miami",
    "sg:classifiers":[
        {
            "category":"Health Services",
            "subcategory":"Chiropractor",
            "type":"Services"
        }
    ],
    "sg:phone":"+1 305 774 1119",
    "sg:postcode":"33133",
    "sg:province":"FL",
    "wof:name":"Chiropractic Back Pain Clinic",
    "wof:placetype":"venue"
},
  "geometry": {"coordinates":[-80.254327,25.741709],"type":"Point"}
}