{
  "type": "Feature",
  "properties": {
    "iso:country":"US",
    "sg:address":"3134 Reseda Ct",
    "sg:city":"Tampa",
    "sg:classifiers":[
        {
            "category":"Communications",
            "type":"Services"
        }
    ],
    "sg:phone":"+1 813 960 8497",
    "sg:postcode":"33618",
    "sg:province":"FL",
    "sg:tags":[
        "communication"
    ],
    "wof:name":"Larsen Communications & Profes",
    "wof:placetype":"venue"
},
  "geometry": {"coordinates":[-82.494871,28.066183],"type":"Point"}
}