{
  "type": "Feature",
  "properties": {
    "iso:country":"US",
    "sg:address":"596 Dogtown Rd",
    "sg:city":"Quincy",
    "sg:classifiers":[
        {
            "category":"Farming",
            "subcategory":"Farm",
            "type":"Manufacturing & Wholesale Goods"
        }
    ],
    "sg:phone":"+1 850 627 7392",
    "sg:postcode":"32351",
    "sg:province":"FL",
    "wof:name":"BAB Farm",
    "wof:placetype":"venue"
},
  "geometry": {"coordinates":[-84.501903,30.677079],"type":"Point"}
}