{
  "type": "Feature",
  "properties": {
    "addr:full":"2108 N Federal Hwy Boca Raton FL 33431",
    "addr:housenumber":"2108",
    "addr:postcode":"33431",
    "addr:street":"N Federal Hwy",
    "iso:country":"US",
    "sg:address":"2108 N Federal Hwy",
    "sg:city":"Boca Raton",
    "sg:classifiers":[
        {
            "category":"Real Estate",
            "subcategory":"Real Estate Agent",
            "type":"Services"
        }
    ],
    "sg:phone":"+1 561 362 7233",
    "sg:postcode":"33431",
    "sg:province":"FL",
    "wof:name":"Federal Home Realty",
    "wof:placetype":"venue"
},
  "geometry": {"coordinates":[-80.077169,26.36958],"type":"Point"}
}