{
  "type": "Feature",
  "properties": {
    "addr:full":"5964 Cardiff Ave Cocoa FL 32927",
    "addr:housenumber":"5964",
    "addr:postcode":"32927",
    "addr:street":"Cardiff Ave",
    "iso:country":"US",
    "sg:address":"5964 Cardiff Ave",
    "sg:city":"Cocoa",
    "sg:classifiers":[
        {
            "category":"Professional",
            "subcategory":"Research",
            "type":"Services"
        }
    ],
    "sg:phone":"+1 321 639 7320",
    "sg:postcode":"32927",
    "sg:province":"FL",
    "sg:website":"http://www.parrotfishmusic.com",
    "wof:name":"Parrot Fish Inc",
    "wof:placetype":"venue"
},
  "geometry": {"coordinates":[-80.805283,28.462124],"type":"Point"}
}