{
  "type": "Feature",
  "properties": {
    "iso:country":"US",
    "sg:address":"100 Orange Ave N",
    "sg:city":"Green Cove Spgs",
    "sg:classifiers":[
        {
            "category":"Food & Beverages",
            "subcategory":"Groceries & Convenience Stores",
            "type":"Retail Goods"
        }
    ],
    "sg:phone":"+1 904 284 0949",
    "sg:postcode":"32043",
    "sg:province":"FL",
    "wof:name":"Orange Station",
    "wof:placetype":"venue"
},
  "geometry": {"coordinates":[-81.67986999999999,29.99486],"type":"Point"}
}