{
  "type": "Feature",
  "properties": {
    "iso:country":"US",
    "sg:address":"1598 E Silver Star Rd",
    "sg:city":"Ocoee",
    "sg:classifiers":[
        {
            "category":"Insurance",
            "subcategory":"Insurance Agent",
            "type":"Services"
        }
    ],
    "sg:phone":"+1 407 299 0301",
    "sg:postcode":"34761",
    "sg:province":"FL",
    "wof:name":"Mask Jerry Insurance",
    "wof:placetype":"venue"
},
  "geometry": {"coordinates":[-81.520051,28.573714],"type":"Point"}
}