{
  "type": "Feature",
  "properties": {
    "addr:full":"3424 Fowler St Fort Myers FL 33901",
    "addr:housenumber":"3424",
    "addr:postcode":"33901",
    "addr:street":"Fowler St",
    "iso:country":"US",
    "sg:address":"3424 Fowler St",
    "sg:city":"Fort Myers",
    "sg:classifiers":[
        {
            "category":"Personal",
            "subcategory":"Beauty Salon",
            "type":"Services"
        }
    ],
    "sg:phone":"+1 239 274 3255",
    "sg:postcode":"33901",
    "sg:province":"FL",
    "wof:name":"Marie's",
    "wof:placetype":"venue"
},
  "geometry": {"coordinates":[-81.861994,26.614642],"type":"Point"}
}