{
  "type": "Feature",
  "properties": {
    "iso:country":"US",
    "sg:address":"3500 Pan American Dr",
    "sg:city":"Miami",
    "sg:classifiers":[
        {
            "category":"Government",
            "subcategory":"Court House",
            "type":"Public Place"
        }
    ],
    "sg:phone":"+1 305 250 5360",
    "sg:postcode":"33133",
    "sg:province":"FL",
    "sg:tags":[
        "town",
        "city",
        "planner"
    ],
    "sg:website":"http://www.orangebowlstadium.com",
    "wof:name":"City Clerk",
    "wof:placetype":"venue"
},
  "geometry": {"coordinates":[-80.234131,25.727859],"type":"Point"}
}