{
  "type": "Feature",
  "properties": {
    "iso:country":"US",
    "sg:address":"7641 Currency Dr",
    "sg:city":"Orlando",
    "sg:classifiers":[
        {
            "category":"Building & Trades",
            "subcategory":"Construction",
            "type":"Services"
        }
    ],
    "sg:phone":"+1 407 857 8181",
    "sg:postcode":"32809",
    "sg:province":"FL",
    "sg:tags":[
        "general",
        "contractor"
    ],
    "sg:website":"www.capitolconstructioncorp.com",
    "wof:name":"Capitol Construction",
    "wof:placetype":"venue"
},
  "geometry": {"coordinates":[-81.409643,28.451579],"type":"Point"}
}