{
  "type": "Feature",
  "properties": {
    "iso:country":"US",
    "sg:address":"85 Edgar St",
    "sg:city":"Atlantic Beach",
    "sg:classifiers":[
        {
            "category":"Building & Trades",
            "subcategory":"Cleaning & Sanitation",
            "type":"Services"
        }
    ],
    "sg:phone":"+1 904 246 7823",
    "sg:postcode":"32233",
    "sg:province":"FL",
    "sg:tags":[
        "janitor"
    ],
    "wof:name":"Champs Cleaning & Janitorial",
    "wof:placetype":"venue"
},
  "geometry": {"coordinates":[-81.414507,30.337702],"type":"Point"}
}