{
  "type": "Feature",
  "properties": {
    "iso:country":"US",
    "sg:address":"11925 NE 2nd Ave",
    "sg:city":"Miami",
    "sg:classifiers":[
        {
            "category":"Wholesale",
            "subcategory":"Machinery & Supplies",
            "type":"Manufacturing & Wholesale Goods"
        }
    ],
    "sg:phone":"+1 305 892 0398",
    "sg:postcode":"33161",
    "sg:province":"FL",
    "sg:tags":[
        "equipment",
        "industrial"
    ],
    "wof:name":"Lift Parts Unlimited Inc",
    "wof:placetype":"venue"
},
  "geometry": {"coordinates":[-80.194228,25.885019],"type":"Point"}
}