{
  "type": "Feature",
  "properties": {
    "addr:full":"65 King St Saint Augustine FL 32084",
    "addr:housenumber":"65",
    "addr:postcode":"32084",
    "addr:street":"King St",
    "iso:country":"US",
    "sg:address":"65 King St",
    "sg:city":"Saint Augustine",
    "sg:classifiers":[
        {
            "category":"Shopping",
            "type":"Retail Goods"
        }
    ],
    "sg:phone":"+1 904 829 1925",
    "sg:postcode":"32084",
    "sg:province":"FL",
    "sg:tags":[
        "merchandise"
    ],
    "wof:name":"James Cleman Signature Gallery",
    "wof:placetype":"venue"
},
  "geometry": {"coordinates":[-81.313819,29.892114],"type":"Point"}
}