{
  "type": "Feature",
  "properties": {
    "addr:full":"29524 Crossland Dr Zephyrhills FL 33543",
    "addr:postcode":"29524;33543",
    "addr:street":"Crossland Dr",
    "iso:country":"US",
    "sg:address":"29524 Crossland Dr",
    "sg:city":"Zephyrhills",
    "sg:classifiers":[
        {
            "category":"Communications",
            "type":"Services"
        },
        {
            "category":"Manufacturing",
            "subcategory":"Electronics",
            "type":"Manufacturing & Wholesale Goods"
        }
    ],
    "sg:phone":"+1 813 994 6194",
    "sg:postcode":"33543",
    "sg:province":"FL",
    "sg:tags":[
        "apparatus",
        "mfg"
    ],
    "wof:name":"Meadow Point Productions Inc",
    "wof:placetype":"venue"
},
  "geometry": {"coordinates":[-82.33116099999999,28.172233],"type":"Point"}
}