{
  "type": "Feature",
  "properties": {
    "addr:full":"1075 N A St Jupiter FL 33460",
    "addr:housenumber":"1075",
    "addr:postcode":"33460",
    "addr:street":"N A St",
    "iso:country":"US",
    "sg:address":"1075 N A St",
    "sg:city":"Jupiter",
    "sg:classifiers":[
        {
            "category":"Restaurant",
            "type":"Food & Drink"
        }
    ],
    "sg:phone":"+1 561 743 8166",
    "sg:postcode":"33460",
    "sg:province":"FL",
    "sg:tags":[
        "american"
    ],
    "wof:name":"Jettys Restaurant",
    "wof:placetype":"venue"
},
  "geometry": {"coordinates":[-80.06475399999999,26.628102],"type":"Point"}
}