{
  "type": "Feature",
  "properties": {
    "addr:full":"1122 14th St W Bradenton FL 34205",
    "addr:housenumber":"1122",
    "addr:postcode":"34205",
    "addr:street":"14Th St W",
    "iso:country":"US",
    "sg:address":"1122 14th St W",
    "sg:city":"Bradenton",
    "sg:classifiers":[
        {
            "category":"Retail",
            "subcategory":"Auto Repair",
            "type":"Services"
        }
    ],
    "sg:phone":"+1 941 746 3972",
    "sg:postcode":"34205",
    "sg:province":"FL",
    "sg:tags":[
        "body",
        "automotive",
        "exhaust"
    ],
    "wof:name":"AC Muffler & Brake Service",
    "wof:placetype":"venue"
},
  "geometry": {"coordinates":[-82.575339,27.4904],"type":"Point"}
}