{
  "type": "Feature",
  "properties": {
    "iso:country":"US",
    "sg:address":"5021 NW 34 Ter",
    "sg:city":"Gainesville",
    "sg:classifiers":[
        {
            "category":"Health Services",
            "subcategory":"Health Practitioner",
            "type":"Services"
        }
    ],
    "sg:phone":"+1 352 377 6000",
    "sg:postcode":"32605",
    "sg:province":"FL",
    "wof:name":"Leone Mae Lcsw Lmt",
    "wof:placetype":"venue"
},
  "geometry": {"coordinates":[-82.372843,29.701281],"type":"Point"}
}