{
  "type": "Feature",
  "properties": {
    "iso:country":"US",
    "sg:address":"138 107th Ave",
    "sg:city":"Saint Petersburg",
    "sg:classifiers":[
        {
            "category":"Banks & Credit Unions",
            "subcategory":"Investment Brokerage",
            "type":"Services"
        }
    ],
    "sg:phone":"+1 727 384 5555",
    "sg:postcode":"33706",
    "sg:province":"FL",
    "sg:tags":[
        "security"
    ],
    "wof:name":"Sterling Enterprise Group",
    "wof:placetype":"venue"
},
  "geometry": {"coordinates":[-82.76786199999999,27.769696],"type":"Point"}
}