{
  "type": "Feature",
  "properties": {
    "addr:full":"1301 Hickory St Melbourne FL 32901",
    "addr:housenumber":"1301",
    "addr:postcode":"32901",
    "addr:street":"Hickory St",
    "iso:country":"US",
    "sg:address":"1301 Hickory St",
    "sg:city":"Melbourne",
    "sg:classifiers":[
        {
            "category":"Health Services",
            "subcategory":"Doctor",
            "type":"Services"
        }
    ],
    "sg:phone":"+1 321 984 1981",
    "sg:postcode":"32901",
    "sg:province":"FL",
    "sg:tags":[
        "medical"
    ],
    "wof:name":"Athan P Kartsonis MD",
    "wof:placetype":"venue"
},
  "geometry": {"coordinates":[-80.613421,28.085588],"type":"Point"}
}