{
  "type": "Feature",
  "properties": {
    "iso:country":"US",
    "sg:address":"603 W Landstreet Rd",
    "sg:city":"Orlando",
    "sg:classifiers":[
        {
            "category":"Wholesale",
            "subcategory":"Construction Materials",
            "type":"Manufacturing & Wholesale Goods"
        }
    ],
    "sg:phone":"+1 407 855 2282",
    "sg:postcode":"32824",
    "sg:province":"FL",
    "wof:name":"Hardware Systems",
    "wof:placetype":"venue"
},
  "geometry": {"coordinates":[-81.385497,28.436032],"type":"Point"}
}