{
  "type": "Feature",
  "properties": {
    "addr:full":"1006 US Hwy 17 Haines City FL 33844",
    "addr:housenumber":"1006",
    "addr:postcode":"33844",
    "addr:street":"Us Hwy 17",
    "iso:country":"US",
    "sg:address":"1006 US Hwy 17",
    "sg:city":"Haines City",
    "sg:classifiers":[
        {
            "category":"Wholesale",
            "subcategory":"Auto Parts",
            "type":"Manufacturing & Wholesale Goods"
        }
    ],
    "sg:phone":"+1 863 421 4014",
    "sg:postcode":"33844",
    "sg:province":"FL",
    "sg:tags":[
        "tire"
    ],
    "wof:name":"M C Tires",
    "wof:placetype":"venue"
},
  "geometry": {"coordinates":[-81.618055,28.118617],"type":"Point"}
}