{
  "type": "Feature",
  "properties": {
    "addr:full":"714 Palm St West Palm Beach FL 33401",
    "addr:housenumber":"714",
    "addr:postcode":"33401",
    "addr:street":"Palm St",
    "iso:country":"US",
    "sg:address":"714 Palm St",
    "sg:city":"West Palm Beach",
    "sg:classifiers":[
        {
            "category":"Personal",
            "subcategory":"Beauty Salon",
            "type":"Services"
        }
    ],
    "sg:phone":"+1 561 820 8923",
    "sg:postcode":"33401",
    "sg:province":"FL",
    "sg:tags":[
        "shop"
    ],
    "wof:name":"Robinson Beauty Salon",
    "wof:placetype":"venue"
},
  "geometry": {"coordinates":[-80.05979000000001,26.699382],"type":"Point"}
}