{
  "type": "Feature",
  "properties": {
    "iso:country":"US",
    "sg:address":"10031 SW 72nd St",
    "sg:city":"Miami",
    "sg:classifiers":[
        {
            "category":"Building & Trades",
            "subcategory":"Cleaning & Sanitation",
            "type":"Services"
        }
    ],
    "sg:phone":"+1 305 275 3011",
    "sg:postcode":"33173",
    "sg:province":"FL",
    "sg:tags":[
        "butler",
        "maid"
    ],
    "wof:name":"Florida Estate Health Care Grp",
    "wof:placetype":"venue"
},
  "geometry": {"coordinates":[-80.356315,25.701519],"type":"Point"}
}