{
  "type": "Feature",
  "properties": {
    "addr:full":"962 Tarpon Ave Sebastian FL 32958",
    "addr:housenumber":"962",
    "addr:postcode":"32958",
    "addr:street":"Tarpon Ave",
    "iso:country":"US",
    "sg:address":"962 Tarpon Ave",
    "sg:city":"Sebastian",
    "sg:classifiers":[
        {
            "category":"Professional",
            "subcategory":"Engineering",
            "type":"Services"
        }
    ],
    "sg:phone":"+1 772 299 6499",
    "sg:postcode":"32958",
    "sg:province":"FL",
    "sg:tags":[
        "engineer"
    ],
    "wof:name":"Cad Development Inc",
    "wof:placetype":"venue"
},
  "geometry": {"coordinates":[-80.500626,27.784513],"type":"Point"}
}