{
  "type": "Feature",
  "properties": {
    "iso:country":"US",
    "sg:address":"1503 Pecan St",
    "sg:city":"Nokomis",
    "sg:classifiers":[
        {
            "category":"Insurance",
            "subcategory":"Hazard Insurance",
            "type":"Services"
        }
    ],
    "sg:phone":"+1 941 587 3013",
    "sg:postcode":"34275",
    "sg:province":"FL",
    "sg:tags":[
        "commercial",
        "business"
    ],
    "wof:name":"Stone Securitiey Inc",
    "wof:placetype":"venue"
},
  "geometry": {"coordinates":[-82.432241,27.127447],"type":"Point"}
}