{
  "type": "Feature",
  "properties": {
    "addr:full":"14961 Hole in 1 Cir Fort Myers FL 33919",
    "addr:housenumber":"14961",
    "addr:postcode":"33919",
    "addr:street":"Hole In 1 Cir",
    "iso:country":"US",
    "sg:address":"14961 Hole in 1 Cir",
    "sg:city":"Fort Myers",
    "sg:classifiers":[
        {
            "category":"Sports & Exercise",
            "subcategory":"Golf",
            "type":"Entertainment"
        }
    ],
    "sg:phone":"+1 239 489 3196",
    "sg:postcode":"33919",
    "sg:province":"FL",
    "sg:tags":[
        "course"
    ],
    "wof:name":"Golfview Golf & Racquet Club",
    "wof:placetype":"venue"
},
  "geometry": {"coordinates":[-81.893562,26.528104],"type":"Point"}
}