{
  "type": "Feature",
  "properties": {
    "addr:full":"807 Indus Rd Venice FL 34293",
    "addr:housenumber":"807",
    "addr:postcode":"34293",
    "addr:street":"Indus Rd",
    "iso:country":"US",
    "sg:address":"807 Indus Rd",
    "sg:city":"Venice",
    "sg:classifiers":[
        {
            "category":"Building & Trades",
            "subcategory":"Construction",
            "type":"Services"
        }
    ],
    "sg:phone":"+1 941 497 0536",
    "sg:postcode":"34293",
    "sg:province":"FL",
    "sg:tags":[
        "windows"
    ],
    "wof:name":"American Window Co",
    "wof:placetype":"venue"
},
  "geometry": {"coordinates":[-82.423897,27.054347],"type":"Point"}
}