{
  "type": "Feature",
  "properties": {
    "iso:country":"US",
    "sg:address":"409 E Ash St",
    "sg:city":"Perry",
    "sg:classifiers":[
        {
            "category":"Health Services",
            "subcategory":"Doctor",
            "type":"Services"
        }
    ],
    "sg:phone":"+1 850 838 4991",
    "sg:postcode":"32347",
    "sg:province":"FL",
    "sg:tags":[
        "physician",
        "surgeon"
    ],
    "wof:name":"North Florida Medical Ctr",
    "wof:placetype":"venue"
},
  "geometry": {"coordinates":[-83.579289,30.128225],"type":"Point"}
}