{
  "type": "Feature",
  "properties": {
    "addr:full":"8444 Galveston Ave Jacksonville FL 32211",
    "addr:housenumber":"8444",
    "addr:postcode":"32211",
    "addr:street":"Galveston Ave",
    "iso:country":"US",
    "sg:address":"8444 Galveston Ave",
    "sg:city":"Jacksonville",
    "sg:classifiers":[
        {
            "category":"Building & Trades",
            "subcategory":"Construction",
            "type":"Services"
        }
    ],
    "sg:phone":"+1 904 724 8208",
    "sg:postcode":"32211",
    "sg:province":"FL",
    "sg:tags":[
        "hanging",
        "paper",
        "painting",
        "contractor"
    ],
    "wof:name":"Lewis Painting Contractors",
    "wof:placetype":"venue"
},
  "geometry": {"coordinates":[-81.56746699999999,30.319598],"type":"Point"}
}