{
  "type": "Feature",
  "properties": {
    "iso:country":"US",
    "sg:address":"5000 Norwood Ave",
    "sg:city":"Jacksonville",
    "sg:classifiers":[
        {
            "category":"Professional",
            "subcategory":"Advertising",
            "type":"Services"
        }
    ],
    "sg:phone":"+1 904 768 1828",
    "sg:postcode":"32208",
    "sg:province":"FL",
    "sg:tags":[
        "mailing",
        "shipping"
    ],
    "wof:name":"Mailroom Etc",
    "wof:placetype":"venue"
},
  "geometry": {"coordinates":[-81.66425099999999,30.371924],"type":"Point"}
}