{
  "type": "Feature",
  "properties": {
    "addr:full":"11320 Tara Dr Fort Lauderdale FL 33325",
    "addr:housenumber":"11320",
    "addr:postcode":"33325",
    "addr:street":"Tara Dr",
    "iso:country":"US",
    "sg:address":"11320 Tara Dr",
    "sg:city":"Fort Lauderdale",
    "sg:classifiers":[
        {
            "category":"Wholesale",
            "subcategory":"Non-durable Goods",
            "type":"Manufacturing & Wholesale Goods"
        }
    ],
    "sg:phone":"+1 954 473 8505",
    "sg:postcode":"33325",
    "sg:province":"FL",
    "sg:tags":[
        "automotive",
        "general",
        "representative",
        "merchandise",
        "p"
    ],
    "wof:name":"R W Bernard and Associates",
    "wof:placetype":"venue"
},
  "geometry": {"coordinates":[-80.302989,26.114006],"type":"Point"}
}