{
  "type": "Feature",
  "properties": {
    "iso:country":"US",
    "sg:address":"5465 Citrus Hill Dr",
    "sg:city":"Polk City",
    "sg:classifiers":[
        {
            "category":"Building & Trades",
            "subcategory":"Construction",
            "type":"Services"
        }
    ],
    "sg:phone":"+1 863 984 3883",
    "sg:postcode":"33868",
    "sg:province":"FL",
    "sg:tags":[
        "contractor"
    ],
    "wof:name":"Carl Hyman Contracting",
    "wof:placetype":"venue"
},
  "geometry": {"coordinates":[-81.845609,28.156523],"type":"Point"}
}