{
  "type": "Feature",
  "properties": {
    "addr:full":"1502 E Baker St Plant City FL 33563",
    "addr:housenumber":"1502",
    "addr:postcode":"33563",
    "addr:street":"E Baker St",
    "iso:country":"US",
    "sg:address":"1502 E Baker St",
    "sg:city":"Plant City",
    "sg:classifiers":[
        {
            "category":"Freight",
            "type":"Transportation"
        }
    ],
    "sg:phone":"+1 813 754 5730",
    "sg:postcode":"33563",
    "sg:province":"FL",
    "sg:tags":[
        "trucking"
    ],
    "wof:name":"Dedicated Transportation",
    "wof:placetype":"venue"
},
  "geometry": {"coordinates":[-82.109649,28.01846],"type":"Point"}
}