{
  "type": "Feature",
  "properties": {
    "addr:full":"2506 Island Crossings Way Merritt Island FL 32952",
    "addr:housenumber":"2506",
    "addr:postcode":"32952",
    "addr:street":"Island Crossings Way",
    "iso:country":"US",
    "sg:address":"2506 Island Crossings Way",
    "sg:city":"Merritt Island",
    "sg:classifiers":[
        {
            "category":"Professional",
            "subcategory":"Engineering",
            "type":"Services"
        }
    ],
    "sg:phone":"+1 321 459 0674",
    "sg:postcode":"32952",
    "sg:province":"FL",
    "wof:name":"E-2 Technology Corporation",
    "wof:placetype":"venue"
},
  "geometry": {"coordinates":[-80.668577,28.404195],"type":"Point"}
}