{
  "type": "Feature",
  "properties": {
    "iso:country":"US",
    "sg:address":"325 3rd St N",
    "sg:city":"Naples",
    "sg:classifiers":[
        {
            "category":"Professional",
            "type":"Services"
        }
    ],
    "sg:phone":"+1 239 262 1093",
    "sg:postcode":"34102",
    "sg:province":"FL",
    "wof:name":"Joseph Weber",
    "wof:placetype":"venue"
},
  "geometry": {"coordinates":[-81.804497,26.149967],"type":"Point"}
}