{
  "type": "Feature",
  "properties": {
    "addr:full":"245 N Van Fleet Dr Bartow FL 33830",
    "addr:housenumber":"245",
    "addr:postcode":"33830",
    "addr:street":"N Van Fleet Dr",
    "iso:country":"US",
    "sg:address":"245 N Van Fleet Dr",
    "sg:city":"Bartow",
    "sg:classifiers":[
        {
            "category":"Real Estate",
            "subcategory":"Real Estate Operator",
            "type":"Services"
        }
    ],
    "sg:phone":"+1 863 533 5553",
    "sg:postcode":"33830",
    "sg:province":"FL",
    "sg:tags":[
        "building",
        "apartment"
    ],
    "wof:name":"Palm Aire Apartments Inc",
    "wof:placetype":"venue"
},
  "geometry": {"coordinates":[-81.85326000000001,27.896844],"type":"Point"}
}