{
  "type": "Feature",
  "properties": {
    "addr:full":"1561 Cassat Ave Jacksonville FL 32210",
    "addr:housenumber":"1561",
    "addr:postcode":"32210",
    "addr:street":"Cassat Ave",
    "iso:country":"US",
    "sg:address":"1561 Cassat Ave",
    "sg:city":"Jacksonville",
    "sg:classifiers":[
        {
            "category":"Health Services",
            "subcategory":"Doctor",
            "type":"Services"
        }
    ],
    "sg:phone":"+1 904 981 9919",
    "sg:postcode":"32210",
    "sg:province":"FL",
    "sg:tags":[
        "physician",
        "surgeon"
    ],
    "wof:name":"Duval Imaging",
    "wof:placetype":"venue"
},
  "geometry": {"coordinates":[-81.73038099999999,30.290163],"type":"Point"}
}