{
  "type": "Feature",
  "properties": {
    "addr:full":"3846 Tamiami Trl Punta Gorda FL 33950",
    "addr:housenumber":"3846",
    "addr:postcode":"33950",
    "addr:street":"Tamiami Trl",
    "iso:country":"US",
    "sg:address":"3846 Tamiami Trl",
    "sg:city":"Punta Gorda",
    "sg:classifiers":[
        {
            "category":"Home & Garden",
            "subcategory":"Carpets & Floor Coverings",
            "type":"Retail Goods"
        }
    ],
    "sg:phone":"+1 941 625 3431",
    "sg:postcode":"33950",
    "sg:province":"FL",
    "wof:name":"Sun Carpets",
    "wof:placetype":"venue"
},
  "geometry": {"coordinates":[-82.02914699999999,26.896869],"type":"Point"}
}