{
  "type": "Feature",
  "properties": {
    "addr:full":"1717 Shepherd Rd Lakeland FL 33811",
    "addr:housenumber":"1717",
    "addr:postcode":"33811",
    "addr:street":"Shepherd Rd",
    "iso:country":"US",
    "sg:address":"1717 Shepherd Rd",
    "sg:city":"Lakeland",
    "sg:classifiers":[
        {
            "category":"Retail",
            "subcategory":"Auto Rental",
            "type":"Services"
        }
    ],
    "sg:phone":"+1 863 647 9793",
    "sg:postcode":"33811",
    "sg:province":"FL",
    "sg:tags":[
        "renting",
        "truck",
        "leasing"
    ],
    "wof:name":"U-Haul Co",
    "wof:placetype":"venue"
},
  "geometry": {"coordinates":[-81.986481,27.938536],"type":"Point"}
}