{
  "type": "Feature",
  "properties": {
    "iso:country":"US",
    "sg:address":"904 Ocean Rd",
    "sg:city":"Stuart",
    "sg:classifiers":[
        {
            "category":"Building & Trades",
            "subcategory":"Construction",
            "type":"Services"
        }
    ],
    "sg:phone":"+1 772 287 7726",
    "sg:postcode":"34996",
    "sg:province":"FL",
    "sg:tags":[
        "general",
        "contractor"
    ],
    "wof:name":"Ric Pauly Construction",
    "wof:placetype":"venue"
},
  "geometry": {"coordinates":[-80.22487700000001,27.190183],"type":"Point"}
}