{
  "type": "Feature",
  "properties": {
    "iso:country":"US",
    "sg:address":"8201 NW 66th St",
    "sg:city":"Miami",
    "sg:classifiers":[
        {
            "category":"Transit Center",
            "subcategory":"Freight",
            "type":"Transportation"
        },
        {
            "category":"Professional",
            "subcategory":"Business Services",
            "type":"Services"
        }
    ],
    "sg:phone":"+1 305 718 3551",
    "sg:postcode":"33166",
    "sg:province":"FL",
    "sg:tags":[
        "broker",
        "shipping"
    ],
    "wof:name":"Mic Freight Brokers, Inc",
    "wof:placetype":"venue"
},
  "geometry": {"coordinates":[-80.329987,25.83346],"type":"Point"}
}