{
  "type": "Feature",
  "properties": {
    "addr:full":"4981 SE Sterling Cir Stuart FL 34997",
    "addr:housenumber":"4981",
    "addr:postcode":"34997",
    "addr:street":"Se Sterling Cir",
    "iso:country":"US",
    "sg:address":"4981 SE Sterling Cir",
    "sg:city":"Stuart",
    "sg:classifiers":[
        {
            "category":"Professional",
            "subcategory":"Engineering",
            "type":"Services"
        }
    ],
    "sg:phone":"+1 772 781 6153",
    "sg:postcode":"34997",
    "sg:province":"FL",
    "sg:tags":[
        "chair",
        "book",
        "specialized",
        "mfg"
    ],
    "wof:name":"Adaptive Living",
    "wof:placetype":"venue"
},
  "geometry": {"coordinates":[-80.22530399999999,27.141954],"type":"Point"}
}