{
  "type": "Feature",
  "properties": {
    "addr:full":"19901 Villa Tuscany Way Orlando FL 32821",
    "addr:housenumber":"19901",
    "addr:postcode":"32821",
    "addr:street":"Villa Tuscany Way",
    "iso:country":"US",
    "sg:address":"19901 Villa Tuscany Way",
    "sg:city":"Orlando",
    "sg:classifiers":[
        {
            "category":"Shopping",
            "subcategory":"Gifts & Souvenirs",
            "type":"Retail Goods"
        }
    ],
    "sg:phone":"+1 407 239 1788",
    "sg:postcode":"32821",
    "sg:province":"FL",
    "wof:name":"Ace Specialty Merchandise",
    "wof:placetype":"venue"
},
  "geometry": {"coordinates":[-81.51553699999999,28.349128],"type":"Point"}
}