{
  "type": "Feature",
  "properties": {
    "addr:full":"5236 Commercial Way Spring Hill FL 34606",
    "addr:housenumber":"5236",
    "addr:postcode":"34606",
    "addr:street":"Commercial Way",
    "iso:country":"US",
    "sg:address":"5236 Commercial Way",
    "sg:city":"Spring Hill",
    "sg:classifiers":[
        {
            "category":"Professional",
            "type":"Services"
        }
    ],
    "sg:phone":"+1 352 650 6470",
    "sg:postcode":"34606",
    "sg:province":"FL",
    "wof:name":"Northdale Services",
    "wof:placetype":"venue"
},
  "geometry": {"coordinates":[-82.585999,28.505294],"type":"Point"}
}