{
  "type": "Feature",
  "properties": {
    "addr:full":"10523 US Hwy 19 Port Richey FL 34668",
    "addr:housenumber":"10523",
    "addr:postcode":"34668",
    "addr:street":"Us Hwy 19",
    "iso:country":"US",
    "sg:address":"10523 US Hwy 19",
    "sg:city":"Port Richey",
    "sg:classifiers":[
        {
            "category":"Banks & Credit Unions",
            "subcategory":"Bank",
            "type":"Services"
        }
    ],
    "sg:phone":"+1 727 861 5340",
    "sg:postcode":"34668",
    "sg:province":"FL",
    "sg:tags":[
        "state"
    ],
    "wof:name":"South Trust Bank",
    "wof:placetype":"venue"
},
  "geometry": {"coordinates":[-82.69973299999999,28.311208],"type":"Point"}
}