{
  "type": "Feature",
  "properties": {
    "iso:country":"US",
    "sg:address":"18355 Townsend House Rd",
    "sg:city":"Dade City",
    "sg:classifiers":[
        {
            "category":"Museum",
            "type":"Entertainment"
        }
    ],
    "sg:phone":"+1 352 588 3077",
    "sg:postcode":"33523",
    "sg:province":"FL",
    "sg:tags":[
        "gallery"
    ],
    "wof:name":"Magnolia Memories",
    "wof:placetype":"venue"
},
  "geometry": {"coordinates":[-82.318072,28.426911],"type":"Point"}
}