{
  "type": "Feature",
  "properties": {
    "iso:country":"US",
    "sg:address":"265 Rockwood St NW",
    "sg:city":"Port Charlotte",
    "sg:classifiers":[
        {
            "category":"Building & Trades",
            "subcategory":"Construction",
            "type":"Services"
        }
    ],
    "sg:phone":"+1 941 255 3674",
    "sg:postcode":"33952",
    "sg:province":"FL",
    "sg:tags":[
        "roofing",
        "contractor"
    ],
    "wof:name":"James R Honeywell Roofing",
    "wof:placetype":"venue"
},
  "geometry": {"coordinates":[-82.10977,26.97652],"type":"Point"}
}