{
  "type": "Feature",
  "properties": {
    "iso:country":"US",
    "sg:address":"17971 Nalle Rd",
    "sg:city":"Fort Myers",
    "sg:classifiers":[
        {
            "category":"Freight",
            "type":"Transportation"
        }
    ],
    "sg:phone":"+1 239 731 7841",
    "sg:postcode":"33917",
    "sg:province":"FL",
    "sg:tags":[
        "trucking"
    ],
    "wof:name":"Phillip D Yates Dump Truck Svc",
    "wof:placetype":"venue"
},
  "geometry": {"coordinates":[-81.80176899999999,26.725387],"type":"Point"}
}