{
  "type": "Feature",
  "properties": {
    "iso:country":"US",
    "sg:address":"2025 NW 36th St",
    "sg:city":"Miami",
    "sg:classifiers":[
        {
            "category":"Autos & Motor Vehicles",
            "subcategory":"Automobile Sales",
            "type":"Retail Goods"
        }
    ],
    "sg:phone":"+1 305 637 7477",
    "sg:postcode":"33142",
    "sg:province":"FL",
    "sg:tags":[
        "car",
        "dealer"
    ],
    "wof:name":"KIKI Motors Inc",
    "wof:placetype":"venue"
},
  "geometry": {"coordinates":[-80.230065,25.809471],"type":"Point"}
}