{
  "type": "Feature",
  "properties": {
    "iso:country":"US",
    "sg:address":"18725 US Hwy 331 S",
    "sg:city":"Freeport",
    "sg:classifiers":[
        {
            "category":"Shopping",
            "subcategory":"Used Merchandise",
            "type":"Retail Goods"
        }
    ],
    "sg:phone":"+1 850 835 3311",
    "sg:postcode":"32439",
    "sg:province":"FL",
    "sg:tags":[
        "antique"
    ],
    "wof:name":"Antiques @ The Beach",
    "wof:placetype":"venue"
},
  "geometry": {"coordinates":[-86.131068,30.45535],"type":"Point"}
}