{
  "type": "Feature",
  "properties": {
    "iso:country":"US",
    "sg:address":"444 Brickell Ave Ste 826",
    "sg:city":"Miami",
    "sg:classifiers":[
        {
            "category":"Professional",
            "subcategory":"Management & Consulting",
            "type":"Services"
        },
        {
            "category":"Professional",
            "subcategory":"Employment Agencies",
            "type":"Services"
        }
    ],
    "sg:phone":"+1 305 381 9600",
    "sg:postcode":"33131",
    "sg:province":"FL",
    "sg:tags":[
        "consultant",
        "search",
        "executive"
    ],
    "wof:name":"Ad Hoc Law Associates Inc",
    "wof:placetype":"venue"
},
  "geometry": {"coordinates":[-80.19053599999999,25.769126],"type":"Point"}
}