{
  "type": "Feature",
  "properties": {
    "iso:country":"US",
    "sg:address":"311 Palm Beach Trace Dr",
    "sg:city":"West Palm Beach",
    "sg:classifiers":[
        {
            "category":"Building & Trades",
            "subcategory":"Construction",
            "type":"Services"
        }
    ],
    "sg:phone":"+1 561 792 7511",
    "sg:postcode":"33411",
    "sg:province":"FL",
    "sg:tags":[
        "concrete",
        "finish",
        "contractor"
    ],
    "wof:name":"Decorative Finishing Corp",
    "wof:placetype":"venue"
},
  "geometry": {"coordinates":[-80.227046,26.712709],"type":"Point"}
}