{
  "type": "Feature",
  "properties": {
    "iso:country":"US",
    "sg:address":"4782 SW 75th Ave",
    "sg:city":"Miami",
    "sg:classifiers":[
        {
            "category":"Autos & Motor Vehicles",
            "subcategory":"Auto Supplies",
            "type":"Retail Goods"
        },
        {
            "category":"Retail",
            "subcategory":"Auto Repair",
            "type":"Services"
        }
    ],
    "sg:phone":"+1 305 262 0504",
    "sg:postcode":"33155",
    "sg:province":"FL",
    "sg:tags":[
        "body",
        "repairing",
        "automobile",
        "accessory",
        "part",
        "painting"
    ],
    "wof:name":"Bahama Auto Seat Covers",
    "wof:placetype":"venue"
},
  "geometry": {"coordinates":[-80.316993,25.730933],"type":"Point"}
}