{
  "type": "Feature",
  "properties": {
    "addr:full":"6600 SW 13th St Gainesville FL 32608",
    "addr:housenumber":"6600",
    "addr:postcode":"32608",
    "addr:street":"Sw 13Th St",
    "iso:country":"US",
    "sg:address":"6600 SW 13th St",
    "sg:city":"Gainesville",
    "sg:classifiers":[
        {
            "category":"Retail",
            "subcategory":"Auto Repair",
            "type":"Services"
        }
    ],
    "sg:phone":"+1 352 376 7924",
    "sg:postcode":"32608",
    "sg:province":"FL",
    "sg:tags":[
        "repairing",
        "automobile"
    ],
    "wof:name":"Miller Well & Pump Co",
    "wof:placetype":"venue"
},
  "geometry": {"coordinates":[-82.339128,29.594222],"type":"Point"}
}