{
  "type": "Feature",
  "properties": {
    "addr:full":"17070 Collins Ave Sunny Isles Bch FL 33160",
    "addr:housenumber":"17070",
    "addr:postcode":"33160",
    "addr:street":"Collins Ave",
    "iso:country":"US",
    "sg:address":"17070 Collins Ave",
    "sg:city":"Sunny Isles Bch",
    "sg:classifiers":[
        {
            "category":"Real Estate",
            "subcategory":"Real Estate Agent",
            "type":"Services"
        }
    ],
    "sg:phone":"+1 305 956 3432",
    "sg:postcode":"33160",
    "sg:province":"FL",
    "wof:name":"Aspen International Realty",
    "wof:placetype":"venue"
},
  "geometry": {"coordinates":[-80.121807,25.934276],"type":"Point"}
}