{
  "type": "Feature",
  "properties": {
    "addr:full":"4542 Clark Rd Sarasota FL 34233",
    "addr:housenumber":"4542",
    "addr:postcode":"34233",
    "addr:street":"Clark Rd",
    "iso:country":"US",
    "sg:address":"4542 Clark Rd",
    "sg:city":"Sarasota",
    "sg:classifiers":[
        {
            "category":"Wholesale",
            "subcategory":"Home Furnishings",
            "type":"Manufacturing & Wholesale Goods"
        }
    ],
    "sg:phone":"+1 941 926 7674",
    "sg:postcode":"34233",
    "sg:province":"FL",
    "sg:tags":[
        "closet",
        "accessory"
    ],
    "wof:name":"Affordable Closets",
    "wof:placetype":"venue"
},
  "geometry": {"coordinates":[-82.479833,27.269161],"type":"Point"}
}