{
  "type": "Feature",
  "properties": {
    "addr:full":"699 S Apollo Blvd Melbourne FL 32901",
    "addr:housenumber":"699",
    "addr:postcode":"32901",
    "addr:street":"S Apollo Blvd",
    "iso:country":"US",
    "sg:address":"699 S Apollo Blvd",
    "sg:city":"Melbourne",
    "sg:classifiers":[
        {
            "category":"Home & Garden",
            "subcategory":"Carpets & Floor Coverings",
            "type":"Retail Goods"
        }
    ],
    "sg:phone":"+1 321 725 0021",
    "sg:postcode":"32901",
    "sg:province":"FL",
    "sg:tags":[
        "tile",
        "vinyl"
    ],
    "wof:name":"K & Y Carpet One",
    "wof:placetype":"venue"
},
  "geometry": {"coordinates":[-80.61779900000001,28.09511],"type":"Point"}
}