{
  "type": "Feature",
  "properties": {
    "addr:full":"3930 W Navy Blvd Pensacola FL 32507",
    "addr:housenumber":"3930",
    "addr:postcode":"32507",
    "addr:street":"W Navy Blvd",
    "iso:country":"US",
    "sg:address":"3930 W Navy Blvd",
    "sg:city":"Pensacola",
    "sg:classifiers":[
        {
            "category":"Shopping",
            "subcategory":"Used Merchandise",
            "type":"Retail Goods"
        }
    ],
    "sg:phone":"+1 850 456 7192",
    "sg:postcode":"32507",
    "sg:province":"FL",
    "wof:name":"Garths Antq & Auctn Gallery",
    "wof:placetype":"venue"
},
  "geometry": {"coordinates":[-87.27186500000001,30.408359],"type":"Point"}
}