{
  "type": "Feature",
  "properties": {
    "iso:country":"US",
    "sg:address":"1109 Dona Way",
    "sg:city":"Nokomis",
    "sg:classifiers":[
        {
            "category":"Professional",
            "subcategory":"Business Services",
            "type":"Services"
        }
    ],
    "sg:phone":"+1 941 488 6830",
    "sg:postcode":"34275",
    "sg:province":"FL",
    "wof:name":"Acrylic Technologies Inc",
    "wof:placetype":"venue"
},
  "geometry": {"coordinates":[-82.436418,27.130221],"type":"Point"}
}