{
  "type": "Feature",
  "properties": {
    "iso:country":"US",
    "sg:address":"19535 Gulf Blvd",
    "sg:city":"Indian Rocks Beach",
    "sg:classifiers":[
        {
            "category":"Real Estate",
            "subcategory":"Real Estate Agent",
            "type":"Services"
        }
    ],
    "sg:phone":"+1 727 517 7527",
    "sg:postcode":"33785",
    "sg:province":"FL",
    "wof:name":"Gulf Front Retreats Vac Rntls",
    "wof:placetype":"venue"
},
  "geometry": {"coordinates":[-82.84517099999999,27.852837],"type":"Point"}
}