{
  "type": "Feature",
  "properties": {
    "iso:country":"US",
    "sg:address":"133 Isle of Venice Dr",
    "sg:city":"Fort Lauderdale",
    "sg:classifiers":[
        {
            "category":"Real Estate",
            "subcategory":"Real Estate Operator",
            "type":"Services"
        }
    ],
    "sg:phone":"+1 954 463 8780",
    "sg:postcode":"33301",
    "sg:province":"FL",
    "sg:tags":[
        "building",
        "apartment"
    ],
    "wof:name":"Nantucket Hideaway Apts",
    "wof:placetype":"venue"
},
  "geometry": {"coordinates":[-80.120667,26.12577],"type":"Point"}
}