{
  "type": "Feature",
  "properties": {
    "iso:country":"US",
    "sg:address":"319 W Call St",
    "sg:city":"Starke",
    "sg:classifiers":[
        {
            "category":"Health Services",
            "subcategory":"Doctor",
            "type":"Services"
        }
    ],
    "sg:phone":"+1 904 964 6500",
    "sg:postcode":"32091",
    "sg:province":"FL",
    "sg:tags":[
        "physician",
        "surgeon",
        "medical"
    ],
    "wof:name":"Physicians Care PA",
    "wof:placetype":"venue"
},
  "geometry": {"coordinates":[-82.11227599999999,29.944951],"type":"Point"}
}