{
  "type": "Feature",
  "properties": {
    "iso:country":"US",
    "sg:address":"2850 Mine Mill Rd",
    "sg:city":"Lakeland",
    "sg:phone":"+1 863 666 2455",
    "sg:postcode":"33801",
    "sg:province":"FL",
    "sg:tags":[
        "equipment",
        "commercial"
    ],
    "wof:name":"CPC Baking Business",
    "wof:placetype":"venue"
},
  "geometry": {"coordinates":[-81.90314499999999,28.015484],"type":"Point"}
}