{
  "type": "Feature",
  "properties": {
    "addr:full":"1633 State Hwy 210 Jacksonville FL 32259",
    "addr:housenumber":"1633",
    "addr:postcode":"32259",
    "addr:street":"State Hwy 210",
    "iso:country":"US",
    "sg:address":"1633 State Hwy 210",
    "sg:city":"Jacksonville",
    "sg:classifiers":[
        {
            "category":"Shopping",
            "subcategory":"Gifts & Souvenirs",
            "type":"Retail Goods"
        }
    ],
    "sg:phone":"+1 904 824 5140",
    "sg:postcode":"32259",
    "sg:province":"FL",
    "sg:tags":[
        "shop"
    ],
    "wof:name":"Florida Visitor Ctr",
    "wof:placetype":"venue"
},
  "geometry": {"coordinates":[-81.495976,30.065399],"type":"Point"}
}