{
  "type": "Feature",
  "properties": {
    "iso:country":"US",
    "sg:address":"7301 SW 45th St",
    "sg:city":"Miami",
    "sg:classifiers":[
        {
            "category":"Retail",
            "subcategory":"Auto Repair",
            "type":"Services"
        }
    ],
    "sg:phone":"+1 305 266 7901",
    "sg:postcode":"33155",
    "sg:province":"FL",
    "wof:name":"South Florida Automotive Repair",
    "wof:placetype":"venue"
},
  "geometry": {"coordinates":[-80.314003,25.7285],"type":"Point"}
}