{
  "type": "Feature",
  "properties": {
    "iso:country":"US",
    "sg:address":"2792 Michigan Ave",
    "sg:city":"Kissimmee",
    "sg:classifiers":[
        {
            "category":"Professional",
            "subcategory":"Advertising",
            "type":"Services"
        }
    ],
    "sg:phone":"+1 407 518 7889",
    "sg:postcode":"34744",
    "sg:province":"FL",
    "sg:tags":[
        "distribution"
    ],
    "wof:name":"North American Group Distr",
    "wof:placetype":"venue"
},
  "geometry": {"coordinates":[-81.39134799999999,28.328933],"type":"Point"}
}