{
  "type": "Feature",
  "properties": {
    "iso:country":"US",
    "sg:address":"12669 NW 13th Ct",
    "sg:city":"Sunrise",
    "sg:classifiers":[
        {
            "category":"Real Estate",
            "subcategory":"Real Estate Agent",
            "type":"Services"
        }
    ],
    "sg:phone":"+1 954 914 1098",
    "sg:postcode":"33323",
    "sg:province":"FL",
    "sg:tags":[
        "inspection"
    ],
    "wof:name":"Albright Home Inspections",
    "wof:placetype":"venue"
},
  "geometry": {"coordinates":[-80.318186,26.138659],"type":"Point"}
}