{
  "type": "Feature",
  "properties": {
    "addr:full":"4030 N 30th Ave Hollywood FL 33020",
    "addr:housenumber":"4030",
    "addr:postcode":"33020",
    "addr:street":"N 30Th Ave",
    "iso:country":"US",
    "sg:address":"4030 N 30th Ave",
    "sg:city":"Hollywood",
    "sg:classifiers":[
        {
            "category":"Building & Trades",
            "subcategory":"Construction",
            "type":"Services"
        }
    ],
    "sg:phone":"+1 954 963 3356",
    "sg:postcode":"33020",
    "sg:province":"FL",
    "sg:tags":[
        "tile",
        "dealer",
        "contractor"
    ],
    "wof:name":"Corry's Tile Creations Inc",
    "wof:placetype":"venue"
},
  "geometry": {"coordinates":[-80.169237,26.047341],"type":"Point"}
}