{
  "type": "Feature",
  "properties": {
    "addr:full":"780 W DR MARTIN LUTHER KING JR BLVD SEFFNER FL 33584",
    "addr:housenumber":"780",
    "addr:postcode":"33584",
    "addr:street":"W Dr Martin Luther King Jr Blvd",
    "iso:country":"US",
    "sg:address":"780 W DR MARTIN LUTHER KING JR BLVD",
    "sg:city":"SEFFNER",
    "sg:classifiers":[
        {
            "category":"Home & Garden",
            "subcategory":"Household Appliances",
            "type":"Retail Goods"
        },
        {
            "category":"Communications",
            "subcategory":"Radio Station",
            "type":"Services"
        },
        {
            "category":"Shopping",
            "subcategory":"Computers & Home Electronics",
            "type":"Retail Goods"
        },
        {
            "category":"Home & Garden",
            "subcategory":"Furniture",
            "type":"Retail Goods"
        }
    ],
    "sg:phone":"+1 813 689 5200",
    "sg:postcode":"33584",
    "sg:province":"FL",
    "sg:tags":[
        "renting",
        "television",
        "leasing",
        "radio-renting",
        "equipment",
        "rental"
    ],
    "sg:website":"http://www.rentacenter.com/",
    "wof:name":"Rent-A-Center",
    "wof:placetype":"venue"
},
  "geometry": {"coordinates":[-82.288466,27.981592],"type":"Point"}
}