{
  "type": "Feature",
  "properties": {
    "iso:country":"US",
    "sg:address":"7320 Winder Ct",
    "sg:city":"Lake Worth",
    "sg:classifiers":[
        {
            "category":"Professional",
            "subcategory":"Business Services",
            "type":"Services"
        }
    ],
    "sg:phone":"+1 561 968 9035",
    "sg:postcode":"33467",
    "sg:province":"FL",
    "wof:name":"Bear Facts Inspections",
    "wof:placetype":"venue"
},
  "geometry": {"coordinates":[-80.16047399999999,26.55921],"type":"Point"}
}