{
  "type": "Feature",
  "properties": {
    "iso:country":"US",
    "sg:address":"9989 SW 118th Ct",
    "sg:city":"Miami",
    "sg:classifiers":[
        {
            "category":"Health Services",
            "subcategory":"Doctor",
            "type":"Services"
        }
    ],
    "sg:phone":"+1 305 670 1003",
    "sg:postcode":"33186",
    "sg:province":"FL",
    "sg:tags":[
        "physician",
        "surgeon"
    ],
    "wof:name":"Max Polo MD",
    "wof:placetype":"venue"
},
  "geometry": {"coordinates":[-80.387153,25.675186],"type":"Point"}
}