{
  "type": "Feature",
  "properties": {
    "addr:full":"9350 Fontainebleau Blvd Miami FL 33172",
    "addr:housenumber":"9350",
    "addr:postcode":"33172",
    "addr:street":"Fontainebleau Blvd",
    "iso:country":"US",
    "sg:address":"9350 Fontainebleau Blvd",
    "sg:city":"Miami",
    "sg:classifiers":[
        {
            "category":"Real Estate",
            "subcategory":"Real Estate Operator",
            "type":"Services"
        }
    ],
    "sg:phone":"+1 305 559 1851",
    "sg:postcode":"33172",
    "sg:province":"FL",
    "sg:tags":[
        "apartment"
    ],
    "wof:name":"Fountains Apartments At Fontainebleau Park the",
    "wof:placetype":"venue"
},
  "geometry": {"coordinates":[-80.347702,25.7729],"type":"Point"}
}