{
  "type": "Feature",
  "properties": {
    "addr:full":"830 SW 50th Ave Pompano Beach FL 33068",
    "addr:housenumber":"830",
    "addr:postcode":"33068",
    "addr:street":"Sw 50Th Ave",
    "iso:country":"US",
    "sg:address":"830 SW 50th Ave",
    "sg:city":"Pompano Beach",
    "sg:classifiers":[
        {
            "category":"Personal",
            "subcategory":"Beauty Salon",
            "type":"Services"
        }
    ],
    "sg:phone":"+1 954 757 8886",
    "sg:postcode":"33068",
    "sg:province":"FL",
    "sg:tags":[
        "hair",
        "full"
    ],
    "wof:name":"Saloon 2000 Plus Inc",
    "wof:placetype":"venue"
},
  "geometry": {"coordinates":[-80.19489,26.217835],"type":"Point"}
}