{
  "type": "Feature",
  "properties": {
    "iso:country":"US",
    "sg:address":"670 N Orlando Ave",
    "sg:city":"Maitland",
    "sg:classifiers":[
        {
            "category":"Real Estate",
            "subcategory":"Real Estate Services",
            "type":"Services"
        }
    ],
    "sg:phone":"+1 407 629 9077",
    "sg:postcode":"32751",
    "sg:province":"FL",
    "sg:tags":[
        "company",
        "title"
    ],
    "wof:name":"Title Source USA Inc",
    "wof:placetype":"venue"
},
  "geometry": {"coordinates":[-81.361087,28.634264],"type":"Point"}
}