{
  "type": "Feature",
  "properties": {
    "iso:country":"US",
    "sg:address":"6200 20th St",
    "sg:city":"Vero Beach",
    "sg:classifiers":[
        {
            "category":"Shopping",
            "subcategory":"Gifts & Souvenirs",
            "type":"Retail Goods"
        }
    ],
    "sg:phone":"+1 772 770 3318",
    "sg:postcode":"32966",
    "sg:province":"FL",
    "sg:tags":[
        "engraving"
    ],
    "wof:name":"Things Remembered",
    "wof:placetype":"venue"
},
  "geometry": {"coordinates":[-80.453451,27.639006],"type":"Point"}
}