{
  "type": "Feature",
  "properties": {
    "iso:country":"US",
    "sg:address":"3072 SE Dominica Ter",
    "sg:city":"Stuart",
    "sg:classifiers":[
        {
            "category":"Food & Beverages",
            "subcategory":"Meat & Fish",
            "type":"Retail Goods"
        }
    ],
    "sg:phone":"+1 772 287 5303",
    "sg:postcode":"34997",
    "sg:province":"FL",
    "sg:tags":[
        "frozen"
    ],
    "wof:name":"JLK Produce Inc",
    "wof:placetype":"venue"
},
  "geometry": {"coordinates":[-80.21207200000001,27.151403],"type":"Point"}
}