{
  "type": "Feature",
  "properties": {
    "iso:country":"US",
    "sg:address":"678 Mourning Dove Dr",
    "sg:city":"Sarasota",
    "sg:classifiers":[
        {
            "category":"Communications",
            "type":"Services"
        }
    ],
    "sg:phone":"+1 941 951 6806",
    "sg:postcode":"34236",
    "sg:province":"FL",
    "sg:tags":[
        "communication"
    ],
    "wof:name":"1087 Beneva Tower Inc",
    "wof:placetype":"venue"
},
  "geometry": {"coordinates":[-82.558594,27.311786],"type":"Point"}
}