{
  "type": "Feature",
  "properties": {
    "iso:country":"US",
    "sg:address":"1321 Pineapple Ave",
    "sg:city":"Melbourne",
    "sg:classifiers":[
        {
            "category":"Building & Trades",
            "subcategory":"Construction",
            "type":"Services"
        }
    ],
    "sg:phone":"+1 321 254 3775",
    "sg:postcode":"32935",
    "sg:province":"FL",
    "sg:tags":[
        "general",
        "contractor"
    ],
    "wof:name":"Larry Wright Construction",
    "wof:placetype":"venue"
},
  "geometry": {"coordinates":[-80.62523899999999,28.129289],"type":"Point"}
}