{
  "type": "Feature",
  "properties": {
    "iso:country":"US",
    "sg:address":"7162 SW 117th Ave",
    "sg:city":"Miami",
    "sg:classifiers":[
        {
            "category":"Home & Garden",
            "subcategory":"Furniture",
            "type":"Retail Goods"
        }
    ],
    "sg:phone":"+1 305 595 0977",
    "sg:postcode":"33183",
    "sg:province":"FL",
    "wof:name":"Futon Specialties",
    "wof:placetype":"venue"
},
  "geometry": {"coordinates":[-80.38227500000001,25.701429],"type":"Point"}
}