{
  "type": "Feature",
  "properties": {
    "iso:country":"US",
    "sg:address":"843 SW 11th St",
    "sg:city":"Miami",
    "sg:classifiers":[
        {
            "category":"Building & Trades",
            "subcategory":"Landscaping Services",
            "type":"Services"
        }
    ],
    "sg:phone":"+1 305 285 7141",
    "sg:postcode":"33129",
    "sg:province":"FL",
    "wof:name":"Florida Outdoors",
    "wof:placetype":"venue"
},
  "geometry": {"coordinates":[-80.20744999999999,25.763172],"type":"Point"}
}