{
  "type": "Feature",
  "properties": {
    "iso:country":"US",
    "sg:address":"6951 NW 16th St",
    "sg:city":"Miami",
    "sg:classifiers":[
        {
            "category":"Shopping",
            "subcategory":"Florist",
            "type":"Retail Goods"
        }
    ],
    "sg:phone":"+1 305 477 7707",
    "sg:postcode":"33126",
    "sg:province":"FL",
    "wof:name":"U S Floral Corp",
    "wof:placetype":"venue"
},
  "geometry": {"coordinates":[-80.310097,25.7889],"type":"Point"}
}