{
  "type": "Feature",
  "properties": {
    "addr:full":"4544 Dolphin Dr Lake Worth FL 33463",
    "addr:housenumber":"4544",
    "addr:postcode":"33463",
    "addr:street":"Dolphin Dr",
    "iso:country":"US",
    "sg:address":"4544 Dolphin Dr",
    "sg:city":"Lake Worth",
    "sg:classifiers":[
        {
            "category":"Building & Trades",
            "subcategory":"Cleaning & Sanitation",
            "type":"Services"
        }
    ],
    "sg:phone":"+1 561 968 7758",
    "sg:postcode":"33463",
    "sg:province":"FL",
    "sg:tags":[
        "janitor"
    ],
    "wof:name":"D's Cleaning Svc",
    "wof:placetype":"venue"
},
  "geometry": {"coordinates":[-80.114867,26.562986],"type":"Point"}
}