{
  "type": "Feature",
  "properties": {
    "iso:country":"US",
    "sg:address":"6750 Collins Ave",
    "sg:city":"Miami Beach",
    "sg:classifiers":[
        {
            "category":"Autos & Motor Vehicles",
            "subcategory":"Automobile Sales",
            "type":"Retail Goods"
        }
    ],
    "sg:phone":"+1 305 865 0019",
    "sg:postcode":"33141",
    "sg:province":"FL",
    "wof:name":"South Beach Jeep Rentals Inc",
    "wof:placetype":"venue"
},
  "geometry": {"coordinates":[-80.12042099999999,25.851349],"type":"Point"}
}