{
  "type": "Feature",
  "properties": {
    "addr:full":"1635 S Ridgewood Ave South Daytona FL 32119",
    "addr:housenumber":"1635",
    "addr:postcode":"32119",
    "addr:street":"S Ridgewood Ave South",
    "iso:country":"US",
    "sg:address":"1635 S Ridgewood Ave",
    "sg:city":"South Daytona",
    "sg:classifiers":[
        {
            "category":"Health Services",
            "subcategory":"Clinic",
            "type":"Services"
        }
    ],
    "sg:phone":"+1 386 761 7351",
    "sg:postcode":"32119",
    "sg:province":"FL",
    "sg:tags":[
        "home"
    ],
    "wof:name":"Friends Assisting Seniors",
    "wof:placetype":"venue"
},
  "geometry": {"coordinates":[-81.00784299999999,29.182667],"type":"Point"}
}