{
  "type": "Feature",
  "properties": {
    "iso:country":"US",
    "sg:address":"8711 Lake Calm Ln",
    "sg:city":"Odessa",
    "sg:classifiers":[
        {
            "category":"Transit Center",
            "subcategory":"Freight",
            "type":"Transportation"
        },
        {
            "category":"Freight",
            "type":"Transportation"
        }
    ],
    "sg:phone":"+1 407 754 3799",
    "sg:postcode":"33556",
    "sg:province":"FL",
    "sg:tags":[
        "trucking-heavy",
        "hauling",
        "trucking"
    ],
    "wof:name":"USA Hauling Service",
    "wof:placetype":"venue"
},
  "geometry": {"coordinates":[-82.581716,28.138154],"type":"Point"}
}