{
  "type": "Feature",
  "properties": {
    "addr:full":"7568 Parkside Pl Margate FL 33063",
    "addr:housenumber":"7568",
    "addr:postcode":"33063",
    "addr:street":"Parkside Pl Margate",
    "iso:country":"US",
    "sg:address":"7568 Parkside Pl",
    "sg:city":"Margate",
    "sg:classifiers":[
        {
            "category":"Professional",
            "subcategory":"Management & Consulting",
            "type":"Services"
        },
        {
            "category":"Shopping",
            "subcategory":"Computers & Home Electronics",
            "type":"Retail Goods"
        }
    ],
    "sg:phone":"+1 954 969 0300",
    "sg:postcode":"33063",
    "sg:province":"FL",
    "sg:tags":[
        "equipment",
        "marketing",
        "dealer",
        "consultant"
    ],
    "sg:website":"www.sheltramarketing.com",
    "wof:name":"Sheltra Marketing Consulting",
    "wof:placetype":"venue"
},
  "geometry": {"coordinates":[-80.226955,26.253167],"type":"Point"}
}