{
  "type": "Feature",
  "properties": {
    "addr:full":"11710 Hoyt Ave Tampa FL 33617",
    "addr:housenumber":"11710",
    "addr:postcode":"33617",
    "addr:street":"Hoyt Ave",
    "iso:country":"US",
    "sg:address":"11710 Hoyt Ave",
    "sg:city":"Tampa",
    "sg:classifiers":[
        {
            "category":"Professional",
            "subcategory":"Computer Services",
            "type":"Services"
        }
    ],
    "sg:phone":"+1 813 984 1888",
    "sg:postcode":"33617",
    "sg:province":"FL",
    "sg:tags":[
        "related"
    ],
    "wof:name":"Communication Worldwide",
    "wof:placetype":"venue"
},
  "geometry": {"coordinates":[-82.38175200000001,28.057699],"type":"Point"}
}