{
  "type": "Feature",
  "properties": {
    "addr:full":"6572 Seminole Blvd Seminole FL 33772",
    "addr:housenumber":"6572",
    "addr:postcode":"33772",
    "addr:street":"Seminole Blvd",
    "iso:country":"US",
    "sg:address":"6572 Seminole Blvd",
    "sg:city":"Seminole",
    "sg:classifiers":[
        {
            "category":"Shopping",
            "subcategory":"Computers & Home Electronics",
            "type":"Retail Goods"
        }
    ],
    "sg:phone":"+1 727 391 9499",
    "sg:postcode":"33772",
    "sg:province":"FL",
    "wof:name":"Bay Computers Inc",
    "wof:placetype":"venue"
},
  "geometry": {"coordinates":[-82.787115,27.831772],"type":"Point"}
}