{
  "type": "Feature",
  "properties": {
    "iso:country":"US",
    "sg:address":"4361 SW 75th Ave",
    "sg:city":"Miami",
    "sg:classifiers":[
        {
            "category":"Wholesale",
            "subcategory":"Medical Equipment & Supplies",
            "type":"Manufacturing & Wholesale Goods"
        }
    ],
    "sg:phone":"+1 305 267 3383",
    "sg:postcode":"33155",
    "sg:province":"FL",
    "wof:name":"Optima Medic Equipment",
    "wof:placetype":"venue"
},
  "geometry": {"coordinates":[-80.31675199999999,25.726126],"type":"Point"}
}