{
  "type": "Feature",
  "properties": {
    "iso:country":"US",
    "sg:address":"1352 E 4th Ave",
    "sg:city":"Hialeah",
    "sg:classifiers":[
        {
            "category":"Shopping",
            "subcategory":"Department Store",
            "type":"Retail Goods"
        }
    ],
    "sg:phone":"+1 305 863 6690",
    "sg:postcode":"33010",
    "sg:province":"FL",
    "wof:name":"Pinar Del Rio Dollarstr Inc",
    "wof:placetype":"venue"
},
  "geometry": {"coordinates":[-80.273826,25.834227],"type":"Point"}
}