{
  "type": "Feature",
  "properties": {
    "iso:country":"US",
    "sg:address":"510 E Liberty St",
    "sg:city":"Brooksville",
    "sg:classifiers":[
        {
            "category":"Shopping",
            "subcategory":"Party Supplies",
            "type":"Retail Goods"
        },
        {
            "category":"Shopping",
            "subcategory":"Florist",
            "type":"Retail Goods"
        }
    ],
    "sg:phone":"+1 352 796 3519",
    "sg:postcode":"34601",
    "sg:province":"FL",
    "sg:tags":[
        "wedding"
    ],
    "sg:website":"http://www.westoversflowers.com",
    "wof:name":"Westover's Flowers & Gifts",
    "wof:placetype":"venue"
},
  "geometry": {"coordinates":[-82.381377,28.554199],"type":"Point"}
}