{
  "type": "Feature",
  "properties": {
    "addr:full":"9099 SW 77th Ave Miami FL 33156",
    "addr:housenumber":"9099",
    "addr:postcode":"33156",
    "addr:street":"Sw 77Th Ave",
    "iso:country":"US",
    "sg:address":"9099 SW 77th Ave",
    "sg:city":"Miami",
    "sg:classifiers":[
        {
            "category":"Real Estate",
            "subcategory":"Real Estate Operator",
            "type":"Services"
        }
    ],
    "sg:phone":"+1 305 274 5100",
    "sg:postcode":"33156",
    "sg:province":"FL",
    "sg:tags":[
        "apartment"
    ],
    "wof:name":"Dayland Place",
    "wof:placetype":"venue"
},
  "geometry": {"coordinates":[-80.31914399999999,25.686587],"type":"Point"}
}