{
  "type": "Feature",
  "properties": {
    "iso:country":"US",
    "sg:address":"4096 Deer Trl",
    "sg:city":"Middleburg",
    "sg:classifiers":[
        {
            "category":"Building & Trades",
            "subcategory":"Landscaping Services",
            "type":"Services"
        }
    ],
    "sg:phone":"+1 904 282 3567",
    "sg:postcode":"32068",
    "sg:province":"FL",
    "sg:tags":[
        "tree"
    ],
    "wof:name":"Lem's Tree Service",
    "wof:placetype":"venue"
},
  "geometry": {"coordinates":[-81.85670399999999,30.025964],"type":"Point"}
}