{
  "type": "Feature",
  "properties": {
    "addr:full":"7345 W Oakland Park Blvd Tamarac FL 33319",
    "addr:housenumber":"7345",
    "addr:postcode":"33319",
    "addr:street":"W Oakland Park Blvd",
    "iso:country":"US",
    "sg:address":"7345 W Oakland Park Blvd",
    "sg:city":"Tamarac",
    "sg:classifiers":[
        {
            "category":"Banks & Credit Unions",
            "subcategory":"Bank",
            "type":"Services"
        },
        {
            "category":"Banks & Credit Unions",
            "subcategory":"Financial Services",
            "type":"Services"
        }
    ],
    "sg:phone":"+1 954 746 6668",
    "sg:postcode":"33319",
    "sg:province":"FL",
    "sg:tags":[
        "saving",
        "loan",
        "commercial"
    ],
    "sg:website":"http://www.commerceonline.com/",
    "wof:name":"Commerce Bank",
    "wof:placetype":"venue"
},
  "geometry": {"coordinates":[-80.245484,26.16579],"type":"Point"}
}