{
  "type": "Feature",
  "properties": {
    "iso:country":"US",
    "sg:address":"1821 Alpine Dr",
    "sg:city":"Navarre",
    "sg:classifiers":[
        {
            "category":"Shopping",
            "subcategory":"Gifts & Souvenirs",
            "type":"Retail Goods"
        }
    ],
    "sg:phone":"+1 850 936 1119",
    "sg:postcode":"32566",
    "sg:province":"FL",
    "sg:tags":[
        "shop"
    ],
    "wof:name":"Baskethound",
    "wof:placetype":"venue"
},
  "geometry": {"coordinates":[-86.885364,30.399507],"type":"Point"}
}