{
  "type": "Feature",
  "properties": {
    "iso:country":"US",
    "sg:address":"1391 Lady Marion Ln",
    "sg:city":"Dunedin",
    "sg:classifiers":[
        {
            "category":"Building & Trades",
            "subcategory":"Landscaping Services",
            "type":"Services"
        },
        {
            "category":"Building & Trades",
            "subcategory":"Pest Control",
            "type":"Services"
        }
    ],
    "sg:phone":"+1 727 733 1159",
    "sg:postcode":"34698",
    "sg:province":"FL",
    "sg:tags":[
        "lawn",
        "gardener",
        "maintenance",
        "weed"
    ],
    "sg:website":"http://www.nutrilawnflorida.com",
    "wof:name":"Nutrilawn Inc",
    "wof:placetype":"venue"
},
  "geometry": {"coordinates":[-82.773094,28.022501],"type":"Point"}
}