{
  "type": "Feature",
  "properties": {
    "iso:country":"US",
    "sg:address":"420 W Main St",
    "sg:city":"Avon Park",
    "sg:classifiers":[
        {
            "category":"Shopping",
            "subcategory":"Stationery & Office Supplies",
            "type":"Retail Goods"
        }
    ],
    "sg:phone":"+1 863 453 5577",
    "sg:postcode":"33825",
    "sg:province":"FL",
    "sg:tags":[
        "educational",
        "material"
    ],
    "wof:name":"Apple Core Teacher Supply",
    "wof:placetype":"venue"
},
  "geometry": {"coordinates":[-81.506916,27.595689],"type":"Point"}
}