{
  "type": "Feature",
  "properties": {
    "addr:full":"732 NW 107th St Miami FL 33168",
    "addr:housenumber":"732",
    "addr:postcode":"33168",
    "addr:street":"Nw 107Th St",
    "iso:country":"US",
    "sg:address":"732 NW 107th St",
    "sg:city":"Miami",
    "sg:classifiers":[
        {
            "category":"Manufacturing",
            "subcategory":"Buildings",
            "type":"Manufacturing & Wholesale Goods"
        },
        {
            "category":"Building & Trades",
            "subcategory":"Construction",
            "type":"Services"
        }
    ],
    "sg:phone":"+1 305 403 3993",
    "sg:postcode":"33168",
    "sg:province":"FL",
    "sg:tags":[
        "home",
        "builder",
        "management",
        "contractor"
    ],
    "wof:name":"Alfa & Omega Construction Inc",
    "wof:placetype":"venue"
},
  "geometry": {"coordinates":[-80.210741,25.872827],"type":"Point"}
}