{
  "type": "Feature",
  "properties": {
    "iso:country":"US",
    "sg:address":"353 S US Hwy 1",
    "sg:city":"Jupiter",
    "sg:classifiers":[
        {
            "category":"Restaurant",
            "type":"Food & Drink"
        }
    ],
    "sg:phone":"+1 561 743 4177",
    "sg:postcode":"33477",
    "sg:province":"FL",
    "wof:name":"Sugar Cane Island Bistro",
    "wof:placetype":"venue"
},
  "geometry": {"coordinates":[-80.079007,26.930657],"type":"Point"}
}