{
  "type": "Feature",
  "properties": {
    "iso:country":"US",
    "sg:address":"4314 E 2nd Ave",
    "sg:city":"Hialeah",
    "sg:classifiers":[
        {
            "category":"Restaurant",
            "type":"Food & Drink"
        }
    ],
    "sg:phone":"+1 305 576 6066",
    "sg:postcode":"33013",
    "sg:province":"FL",
    "sg:tags":[
        "greek"
    ],
    "wof:name":"Mandolin Aegean Bistro",
    "wof:placetype":"venue"
},
  "geometry": {"coordinates":[-80.27875,25.861612],"type":"Point"}
}