{
  "type": "Feature",
  "properties": {
    "iso:country":"US",
    "sg:address":"800 S Mills Ave",
    "sg:city":"Orlando",
    "sg:classifiers":[
        {
            "category":"Organizations",
            "subcategory":"Community Association",
            "type":"Services"
        }
    ],
    "sg:phone":"+1 407 898 3481",
    "sg:postcode":"32801",
    "sg:province":"FL",
    "wof:name":"Dental Personnel Placement Service",
    "wof:placetype":"venue"
},
  "geometry": {"coordinates":[-81.364182,28.5322],"type":"Point"}
}