{
  "type": "Feature",
  "properties": {
    "addr:full":"5865 SW 64th Ave Miami FL 33143",
    "addr:housenumber":"5865",
    "addr:postcode":"33143",
    "addr:street":"Sw 64Th Ave",
    "iso:country":"US",
    "sg:address":"5865 SW 64th Ave",
    "sg:city":"Miami",
    "sg:classifiers":[
        {
            "category":"Building & Trades",
            "subcategory":"Construction",
            "type":"Services"
        }
    ],
    "sg:phone":"+1 305 661 4434",
    "sg:postcode":"33143",
    "sg:province":"FL",
    "sg:tags":[
        "residential"
    ],
    "wof:name":"Inverdell Inc",
    "wof:placetype":"venue"
},
  "geometry": {"coordinates":[-80.298123,25.717974],"type":"Point"}
}