{
  "type": "Feature",
  "properties": {
    "iso:country":"US",
    "sg:address":"1321 N 14th St",
    "sg:city":"Leesburg",
    "sg:classifiers":[
        {
            "category":"Travel",
            "subcategory":"Hotels & Motels",
            "type":"Entertainment"
        }
    ],
    "sg:phone":"+1 352 787 3343",
    "sg:postcode":"34748",
    "sg:province":"FL",
    "sg:tags":[
        "lodging"
    ],
    "wof:name":"Budget Inn-Leesburg",
    "wof:placetype":"venue"
},
  "geometry": {"coordinates":[-81.887367,28.829539],"type":"Point"}
}