{
  "type": "Feature",
  "properties": {
    "iso:country":"US",
    "sg:address":"2323 Mace St",
    "sg:city":"Orlando",
    "sg:classifiers":[
        {
            "category":"Building & Trades",
            "subcategory":"Plumbing",
            "type":"Services"
        }
    ],
    "sg:phone":"+1 407 352 7040",
    "sg:postcode":"32839",
    "sg:province":"FL",
    "sg:tags":[
        "conditioning",
        "air",
        "system",
        "contractor"
    ],
    "wof:name":"Cold Wall Inc",
    "wof:placetype":"venue"
},
  "geometry": {"coordinates":[-81.420635,28.480901],"type":"Point"}
}