{
  "type": "Feature",
  "properties": {
    "iso:country":"US",
    "sg:address":"7700 N Kendall Dr",
    "sg:city":"Miami",
    "sg:classifiers":[
        {
            "category":"Professional",
            "subcategory":"Management & Consulting",
            "type":"Services"
        }
    ],
    "sg:phone":"+1 305 412 8185",
    "sg:postcode":"33156",
    "sg:province":"FL",
    "sg:tags":[
        "business"
    ],
    "wof:name":"E S Consultants Inc",
    "wof:placetype":"venue"
},
  "geometry": {"coordinates":[-80.321367,25.68843],"type":"Point"}
}