{
  "type": "Feature",
  "properties": {
    "addr:full":"8123 Lake Serene Dr Orlando FL 32836",
    "addr:housenumber":"8123",
    "addr:postcode":"32836",
    "addr:street":"Lake Serene Dr",
    "iso:country":"US",
    "sg:address":"8123 Lake Serene Dr",
    "sg:city":"Orlando",
    "sg:classifiers":[
        {
            "category":"Communications",
            "subcategory":"Film & Video Production",
            "type":"Services"
        }
    ],
    "sg:phone":"+1 407 903 1886",
    "sg:postcode":"32836",
    "sg:province":"FL",
    "sg:tags":[
        "motion"
    ],
    "wof:name":"Spark Productions",
    "wof:placetype":"venue"
},
  "geometry": {"coordinates":[-81.498929,28.439629],"type":"Point"}
}