{
  "type": "Feature",
  "properties": {
    "addr:full":"249 Center Ct Venice FL 34285",
    "addr:housenumber":"249",
    "addr:postcode":"34285",
    "addr:street":"Center Ct",
    "iso:country":"US",
    "sg:address":"249 Center Ct",
    "sg:city":"Venice",
    "sg:classifiers":[
        {
            "category":"Building & Trades",
            "subcategory":"Construction",
            "type":"Services"
        }
    ],
    "sg:phone":"+1 941 493 3934",
    "sg:postcode":"34285",
    "sg:province":"FL",
    "sg:tags":[
        "house"
    ],
    "wof:name":"Lincoln Homes",
    "wof:placetype":"venue"
},
  "geometry": {"coordinates":[-82.42891899999999,27.080768],"type":"Point"}
}