{
  "type": "Feature",
  "properties": {
    "iso:country":"US",
    "sg:address":"425 N 1st St",
    "sg:city":"Immokalee",
    "sg:classifiers":[
        {
            "category":"Education",
            "subcategory":"Special Training",
            "type":"Public Place"
        }
    ],
    "sg:phone":"+1 239 657 4434",
    "sg:postcode":"34142",
    "sg:province":"FL",
    "sg:tags":[
        "instruction",
        "driving"
    ],
    "sg:website":"www.davidlawrence.com",
    "wof:name":"David Lawrence Ctr-Immokalee",
    "wof:placetype":"venue"
},
  "geometry": {"coordinates":[-81.41754,26.424706],"type":"Point"}
}