{
  "type": "Feature",
  "properties": {
    "iso:country":"US",
    "sg:address":"401 S Sequoia Dr",
    "sg:city":"West Palm Beach",
    "sg:classifiers":[
        {
            "category":"Social Services",
            "subcategory":"Job Training",
            "type":"Services"
        }
    ],
    "sg:phone":"+1 561 687 0888",
    "sg:postcode":"33409",
    "sg:province":"FL",
    "sg:tags":[
        "career",
        "counseling",
        "vocational"
    ],
    "wof:name":"Jay Block Co",
    "wof:placetype":"venue"
},
  "geometry": {"coordinates":[-80.09361,26.711588],"type":"Point"}
}