{
  "type": "Feature",
  "properties": {
    "addr:full":"1635 3rd Ave N Saint Petersburg FL 33713",
    "addr:housenumber":"1635",
    "addr:postcode":"33713",
    "addr:street":"3Rd Ave N",
    "iso:country":"US",
    "sg:address":"1635 3rd Ave N",
    "sg:city":"Saint Petersburg",
    "sg:classifiers":[
        {
            "category":"Utilities",
            "subcategory":"Sewage",
            "type":"Services"
        }
    ],
    "sg:phone":"+1 727 893 7261",
    "sg:postcode":"33713",
    "sg:province":"FL",
    "sg:tags":[
        "executive",
        "system",
        "sewerage"
    ],
    "wof:name":"Dept of Public Works-Utilties",
    "wof:placetype":"venue"
},
  "geometry": {"coordinates":[-82.655761,27.774867],"type":"Point"}
}