{
  "type": "Feature",
  "properties": {
    "iso:country":"US",
    "sg:address":"4895 S Orange Ave",
    "sg:city":"Orlando",
    "sg:classifiers":[
        {
            "category":"Shopping",
            "subcategory":"Music",
            "type":"Retail Goods"
        }
    ],
    "sg:phone":"+1 407 859 8991",
    "sg:postcode":"32806",
    "sg:province":"FL",
    "sg:tags":[
        "compact",
        "record",
        "disc",
        "tape"
    ],
    "wof:name":"East-West Compact Discs & Tape",
    "wof:placetype":"venue"
},
  "geometry": {"coordinates":[-81.37398399999999,28.492742],"type":"Point"}
}