{
  "type": "Feature",
  "properties": {
    "addr:full":"8109 8th St Laurel Hill FL 32567",
    "addr:housenumber":"8109",
    "addr:postcode":"32567",
    "addr:street":"8Th St",
    "iso:country":"US",
    "sg:address":"8109 8th St",
    "sg:city":"Laurel Hill",
    "sg:classifiers":[
        {
            "category":"Building & Trades",
            "subcategory":"Construction",
            "type":"Services"
        }
    ],
    "sg:phone":"+1 850 652 4613",
    "sg:postcode":"32567",
    "sg:province":"FL",
    "sg:tags":[
        "residential"
    ],
    "wof:name":"Reeves Construction Company",
    "wof:placetype":"venue"
},
  "geometry": {"coordinates":[-86.468206,30.960393],"type":"Point"}
}