{
  "type": "Feature",
  "properties": {
    "iso:country":"US",
    "sg:address":"459 W 41st St",
    "sg:city":"Miami Beach",
    "sg:classifiers":[
        {
            "category":"Landmark",
            "subcategory":"Tourist Information",
            "type":"Public Place"
        }
    ],
    "sg:phone":"+1 305 579 0078",
    "sg:postcode":"33140",
    "sg:province":"FL",
    "sg:tags":[
        "tour"
    ],
    "wof:name":"Lynx International Inc",
    "wof:placetype":"venue"
},
  "geometry": {"coordinates":[-80.12879,25.814112],"type":"Point"}
}