{
  "type": "Feature",
  "properties": {
    "addr:full":"1720 Ansley Ct Deltona FL 32725",
    "addr:housenumber":"1720",
    "addr:postcode":"32725",
    "addr:street":"Ansley Ct",
    "iso:country":"US",
    "sg:address":"1720 Ansley Ct",
    "sg:city":"Deltona",
    "sg:classifiers":[
        {
            "category":"Building & Trades",
            "subcategory":"Landscaping Services",
            "type":"Services"
        }
    ],
    "sg:phone":"+1 386 789 9951",
    "sg:postcode":"32725",
    "sg:province":"FL",
    "wof:name":"Georges Lawn Care",
    "wof:placetype":"venue"
},
  "geometry": {"coordinates":[-81.254036,28.910979],"type":"Point"}
}