{
  "type": "Feature",
  "properties": {
    "iso:country":"US",
    "sg:address":"1035 Collier Center Way",
    "sg:city":"Naples",
    "sg:classifiers":[
        {
            "category":"Building & Trades",
            "subcategory":"Construction",
            "type":"Services"
        }
    ],
    "sg:phone":"+1 239 591 8453",
    "sg:postcode":"34110",
    "sg:province":"FL",
    "sg:tags":[
        "designer",
        "dealer",
        "pool",
        "swimming"
    ],
    "wof:name":"Blue Haven Pools & Spas",
    "wof:placetype":"venue"
},
  "geometry": {"coordinates":[-81.795247,26.302972],"type":"Point"}
}