{
  "type": "Feature",
  "properties": {
    "iso:country":"US",
    "sg:address":"525 NW 62nd St",
    "sg:city":"Miami",
    "sg:classifiers":[
        {
            "category":"Park",
            "type":"Public Place"
        }
    ],
    "sg:phone":"+1 305 757 7961",
    "sg:postcode":"33150",
    "sg:province":"FL",
    "wof:name":"Athalie Range Park",
    "wof:placetype":"venue"
},
  "geometry": {"coordinates":[-80.206435,25.832395],"type":"Point"}
}