{
  "type": "Feature",
  "properties": {
    "iso:country":"US",
    "sg:address":"725 Groveland Ave",
    "sg:city":"Venice",
    "sg:classifiers":[
        {
            "category":"Building & Trades",
            "subcategory":"Construction",
            "type":"Services"
        }
    ],
    "sg:phone":"+1 941 484 3475",
    "sg:postcode":"34285",
    "sg:province":"FL",
    "sg:tags":[
        "general",
        "contractor"
    ],
    "wof:name":"David W Green General Contract",
    "wof:placetype":"venue"
},
  "geometry": {"coordinates":[-82.43194099999999,27.096912],"type":"Point"}
}