{
  "type": "Feature",
  "properties": {
    "iso:country":"US",
    "sg:address":"662 Heraldo Ct",
    "sg:city":"Kissimmee",
    "sg:classifiers":[
        {
            "category":"Building & Trades",
            "subcategory":"Construction",
            "type":"Services"
        }
    ],
    "sg:phone":"+1 407 343 0798",
    "sg:postcode":"34758",
    "sg:province":"FL",
    "sg:tags":[
        "residential"
    ],
    "wof:name":"Salvador Perez",
    "wof:placetype":"venue"
},
  "geometry": {"coordinates":[-81.45997300000001,28.15474],"type":"Point"}
}