{
  "type": "Feature",
  "properties": {
    "addr:full":"4397 Saint Johns Pkwy Sanford FL 32771",
    "addr:housenumber":"4397",
    "addr:postcode":"32771",
    "addr:street":"Saint Johns Pkwy",
    "iso:country":"US",
    "sg:address":"4397 Saint Johns Pkwy",
    "sg:city":"Sanford",
    "sg:classifiers":[
        {
            "category":"Professional",
            "type":"Services"
        }
    ],
    "sg:phone":"+1 407 322 9111",
    "sg:postcode":"32771",
    "sg:province":"FL",
    "sg:tags":[
        "establishment"
    ],
    "wof:name":"Atmosphere",
    "wof:placetype":"venue"
},
  "geometry": {"coordinates":[-81.321108,28.803914],"type":"Point"}
}