{
  "type": "Feature",
  "properties": {
    "iso:country":"US",
    "sg:address":"4408 Thomasson Dr",
    "sg:city":"Naples",
    "sg:classifiers":[
        {
            "category":"Fast Food",
            "type":"Food & Drink"
        },
        {
            "category":"Restaurant",
            "type":"Food & Drink"
        },
        {
            "category":"Food & Beverages",
            "subcategory":"Groceries & Convenience Stores",
            "type":"Retail Goods"
        }
    ],
    "sg:phone":"+1 239 775 6521",
    "sg:postcode":"34112",
    "sg:province":"FL",
    "sg:tags":[
        "shop",
        "american",
        "sandwich",
        "take"
    ],
    "sg:website":"http://www.subway.com",
    "wof:name":"Subway",
    "wof:placetype":"venue"
},
  "geometry": {"coordinates":[-81.750916,26.106882],"type":"Point"}
}