{
  "type": "Feature",
  "properties": {
    "iso:country":"US",
    "sg:address":"3 Hollyhock Ct",
    "sg:city":"Homosassa",
    "sg:classifiers":[
        {
            "category":"Wholesale",
            "subcategory":"Computers",
            "type":"Manufacturing & Wholesale Goods"
        }
    ],
    "sg:phone":"+1 352 382 5055",
    "sg:postcode":"34446",
    "sg:province":"FL",
    "sg:tags":[
        "equipment"
    ],
    "wof:name":"Computer Mechanic",
    "wof:placetype":"venue"
},
  "geometry": {"coordinates":[-82.52807300000001,28.717239],"type":"Point"}
}