{
  "type": "Feature",
  "properties": {
    "addr:full":"6620 Manor Beach Rd New Port Richey FL 34652",
    "addr:housenumber":"6620",
    "addr:postcode":"34652",
    "addr:street":"Manor Beach Rd",
    "iso:country":"US",
    "sg:address":"6620 Manor Beach Rd",
    "sg:city":"New Port Richey",
    "sg:classifiers":[
        {
            "category":"Professional",
            "subcategory":"Management & Consulting",
            "type":"Services"
        }
    ],
    "sg:phone":"+1 727 534 9016",
    "sg:postcode":"34652",
    "sg:province":"FL",
    "sg:tags":[
        "environmental",
        "consultant"
    ],
    "wof:name":"Tri Star LLC",
    "wof:placetype":"venue"
},
  "geometry": {"coordinates":[-82.73358899999999,28.255737],"type":"Point"}
}