{
  "type": "Feature",
  "properties": {
    "iso:country":"US",
    "sg:address":"4051 SW 106th Ter",
    "sg:city":"Fort Lauderdale",
    "sg:classifiers":[
        {
            "category":"Shopping",
            "type":"Retail Goods"
        }
    ],
    "sg:phone":"+1 954 689 8900",
    "sg:postcode":"33328",
    "sg:province":"FL",
    "sg:tags":[
        "equipment",
        "sales"
    ],
    "wof:name":"Digital Imaging Toner Tech",
    "wof:placetype":"venue"
},
  "geometry": {"coordinates":[-80.289663,26.066527],"type":"Point"}
}