{
  "type": "Feature",
  "properties": {
    "iso:country":"US",
    "sg:address":"2914 Clay Turner Rd",
    "sg:city":"Plant City",
    "sg:classifiers":[
        {
            "category":"Building & Trades",
            "subcategory":"Construction",
            "type":"Services"
        }
    ],
    "sg:phone":"+1 813 752 0006",
    "sg:postcode":"33566",
    "sg:province":"FL",
    "sg:tags":[
        "fence",
        "contractor"
    ],
    "wof:name":"Peacock & Sons Fencing",
    "wof:placetype":"venue"
},
  "geometry": {"coordinates":[-82.07141300000001,27.978348],"type":"Point"}
}