{
  "type": "Feature",
  "properties": {
    "iso:country":"US",
    "sg:address":"16 Bayview Dr",
    "sg:city":"Shalimar",
    "sg:classifiers":[
        {
            "category":"Professional",
            "subcategory":"Management & Consulting",
            "type":"Services"
        }
    ],
    "sg:phone":"+1 850 651 4077",
    "sg:postcode":"32579",
    "sg:province":"FL",
    "sg:tags":[
        "consultant"
    ],
    "wof:name":"Ronald A Jacob Consultant",
    "wof:placetype":"venue"
},
  "geometry": {"coordinates":[-86.587034,30.467302],"type":"Point"}
}