{
  "type": "Feature",
  "properties": {
    "iso:country":"US",
    "sg:address":"5705 Dixie Ave",
    "sg:city":"Lakeland",
    "sg:classifiers":[
        {
            "category":"Place Of Worship",
            "subcategory":"Church",
            "type":"Public Place"
        },
        {
            "category":"Place Of Worship",
            "type":"Public Place"
        }
    ],
    "sg:phone":"+1 863 816 2025",
    "sg:postcode":"33810",
    "sg:province":"FL",
    "sg:tags":[
        "churches-baptist-general",
        "churches-baptist"
    ],
    "wof:name":"Crystal Springs Church Of Old Regular Baptist",
    "wof:placetype":"venue"
},
  "geometry": {"coordinates":[-81.987717,28.117279],"type":"Point"}
}