{
  "type": "Feature",
  "properties": {
    "iso:country":"US",
    "sg:address":"550 Palm St",
    "sg:city":"West Palm Beach",
    "sg:classifiers":[
        {
            "category":"Shopping",
            "type":"Retail Goods"
        }
    ],
    "sg:phone":"+1 561 805 5901",
    "sg:postcode":"33401",
    "sg:province":"FL",
    "sg:tags":[
        "merchandise"
    ],
    "wof:name":"Illuminationscom Inc",
    "wof:placetype":"venue"
},
  "geometry": {"coordinates":[-80.056623,26.699279],"type":"Point"}
}