{
  "type": "Feature",
  "properties": {
    "iso:country":"US",
    "sg:address":"453 Benjulyn Rd",
    "sg:city":"Cantonment",
    "sg:classifiers":[
        {
            "category":"Building & Trades",
            "subcategory":"Construction",
            "type":"Services"
        }
    ],
    "sg:phone":"+1 850 968 2927",
    "sg:postcode":"32533",
    "sg:province":"FL",
    "sg:tags":[
        "downspouts",
        "gutter",
        "contractor"
    ],
    "wof:name":"L W Ward Signing & Gutters",
    "wof:placetype":"venue"
},
  "geometry": {"coordinates":[-87.30093599999999,30.600521],"type":"Point"}
}