{
  "type": "Feature",
  "properties": {
    "iso:country":"US",
    "sg:address":"1326 Tampa Rd",
    "sg:city":"Palm Harbor",
    "sg:classifiers":[
        {
            "category":"Restaurant",
            "type":"Food & Drink"
        }
    ],
    "sg:phone":"+1 727 786 1752",
    "sg:postcode":"34683",
    "sg:province":"FL",
    "sg:tags":[
        "frozen",
        "yogurt"
    ],
    "wof:name":"Zick Inc",
    "wof:placetype":"venue"
},
  "geometry": {"coordinates":[-82.764737,28.068153],"type":"Point"}
}