{
  "type": "Feature",
  "properties": {
    "addr:full":"1943 NE 148th St Miami FL 33181",
    "addr:housenumber":"1943",
    "addr:postcode":"33181",
    "addr:street":"Ne 148Th St",
    "iso:country":"US",
    "sg:address":"1943 NE 148th St",
    "sg:city":"Miami",
    "sg:classifiers":[
        {
            "category":"Food & Beverages",
            "subcategory":"Ethnic Foods",
            "type":"Retail Goods"
        }
    ],
    "sg:phone":"+1 305 893 8899",
    "sg:postcode":"33181",
    "sg:province":"FL",
    "sg:tags":[
        "grocers-ethnic"
    ],
    "wof:name":"Apocalypse 2000",
    "wof:placetype":"venue"
},
  "geometry": {"coordinates":[-80.16009,25.912269],"type":"Point"}
}