{
  "type": "Feature",
  "properties": {
    "addr:full":"5640 NW 78th Ave Doral FL 33166",
    "addr:housenumber":"5640",
    "addr:postcode":"33166",
    "addr:street":"Nw 78Th Ave",
    "iso:country":"US",
    "sg:address":"5640 NW 78th Ave",
    "sg:city":"Doral",
    "sg:classifiers":[
        {
            "category":"Retail",
            "subcategory":"Auto Repair",
            "type":"Services"
        }
    ],
    "sg:phone":"+1 305 468 0111",
    "sg:postcode":"33166",
    "sg:province":"FL",
    "sg:tags":[
        "repairing",
        "automobile",
        "electrical"
    ],
    "wof:name":"Ms Auto Electric",
    "wof:placetype":"venue"
},
  "geometry": {"coordinates":[-80.323601,25.8248],"type":"Point"}
}