{
  "type": "Feature",
  "properties": {
    "addr:full":"2240 NW 87th Ave Miami FL 33172",
    "addr:housenumber":"2240",
    "addr:postcode":"33172",
    "addr:street":"Nw 87Th Ave",
    "iso:country":"US",
    "sg:address":"2240 NW 87th Ave",
    "sg:city":"Miami",
    "sg:classifiers":[
        {
            "category":"Shopping",
            "type":"Retail Goods"
        }
    ],
    "sg:phone":"+1 800 324 1967",
    "sg:postcode":"33172",
    "sg:province":"FL",
    "sg:tags":[
        "communication",
        "equipment"
    ],
    "wof:name":"Ingeneria As CA Inc",
    "wof:placetype":"venue"
},
  "geometry": {"coordinates":[-80.336997,25.794843],"type":"Point"}
}