{
  "type": "Feature",
  "properties": {
    "iso:country":"US",
    "sg:address":"201 N Franklin Ave #3410",
    "sg:city":"Tampa",
    "sg:classifiers":[
        {
            "category":"Professional",
            "subcategory":"Computer Services",
            "type":"Services"
        }
    ],
    "sg:postcode":"33602",
    "sg:province":"FL",
    "sg:tags":[
        "srm",
        "smartphones"
    ],
    "sg:website":"http://www.gammaengineers.com",
    "wof:name":"Gamma Engineers",
    "wof:placetype":"venue"
},
  "geometry": {"coordinates":[-82.457398,27.946613],"type":"Point"}
}