{
  "type": "Feature",
  "properties": {
    "addr:full":"2424 Cresap St Lakeland FL 33815",
    "addr:housenumber":"2424",
    "addr:postcode":"33815",
    "addr:street":"Cresap St",
    "iso:country":"US",
    "sg:address":"2424 Cresap St",
    "sg:city":"Lakeland",
    "sg:classifiers":[
        {
            "category":"Building & Trades",
            "subcategory":"Construction",
            "type":"Services"
        }
    ],
    "sg:phone":"+1 863 683 1286",
    "sg:postcode":"33815",
    "sg:province":"FL",
    "sg:tags":[
        "roofing",
        "contractor"
    ],
    "wof:name":"All American Roofing",
    "wof:placetype":"venue"
},
  "geometry": {"coordinates":[-81.99522399999999,28.03275],"type":"Point"}
}