{
  "type": "Feature",
  "properties": {
    "addr:full":"795 12th Ave SW Vero Beach FL 32962",
    "addr:housenumber":"795",
    "addr:postcode":"32962",
    "addr:street":"12Th Ave Sw",
    "iso:country":"US",
    "sg:address":"795 12th Ave SW",
    "sg:city":"Vero Beach",
    "sg:classifiers":[
        {
            "category":"Wholesale",
            "subcategory":"Plants",
            "type":"Manufacturing & Wholesale Goods"
        }
    ],
    "sg:phone":"+1 772 562 5789",
    "sg:postcode":"32962",
    "sg:province":"FL",
    "sg:website":"www.horizonnursery.com",
    "wof:name":"Horizon Nursery Wholesale",
    "wof:placetype":"venue"
},
  "geometry": {"coordinates":[-80.397845,27.588801],"type":"Point"}
}