{
  "type": "Feature",
  "properties": {
    "iso:country":"US",
    "sg:address":"6513 Ranger Dr",
    "sg:city":"Tampa",
    "sg:classifiers":[
        {
            "category":"Building & Trades",
            "subcategory":"Construction",
            "type":"Services"
        }
    ],
    "sg:phone":"+1 813 855 2377",
    "sg:postcode":"33615",
    "sg:province":"FL",
    "sg:tags":[
        "hanging",
        "contractor"
    ],
    "wof:name":"Ralphs Painting & Home RE",
    "wof:placetype":"venue"
},
  "geometry": {"coordinates":[-82.60186299999999,28.00872],"type":"Point"}
}