{
  "type": "Feature",
  "properties": {
    "iso:country":"US",
    "sg:address":"14320 7th St",
    "sg:city":"Dade City",
    "sg:classifiers":[
        {
            "category":"Home & Garden",
            "subcategory":"Hardware",
            "type":"Retail Goods"
        }
    ],
    "sg:phone":"+1 352 567 3362",
    "sg:postcode":"33523",
    "sg:province":"FL",
    "wof:name":"Dade City Hardware",
    "wof:placetype":"venue"
},
  "geometry": {"coordinates":[-82.188998,28.366391],"type":"Point"}
}