{
  "type": "Feature",
  "properties": {
    "iso:country":"US",
    "sg:address":"1722 Saint Johns Bluff Rd S",
    "sg:city":"Jacksonville",
    "sg:classifiers":[
        {
            "category":"Retail",
            "subcategory":"Auto Rental",
            "type":"Services"
        }
    ],
    "sg:phone":"+1 904 725 0006",
    "sg:postcode":"32246",
    "sg:province":"FL",
    "sg:tags":[
        "renting",
        "truck",
        "leasing"
    ],
    "wof:name":"Budget Truck Rental",
    "wof:placetype":"venue"
},
  "geometry": {"coordinates":[-81.523331,30.320949],"type":"Point"}
}