{
  "type": "Feature",
  "properties": {
    "iso:country":"US",
    "sg:address":"2755 NW 119th Ave",
    "sg:city":"Plantation",
    "sg:classifiers":[
        {
            "category":"Recreation",
            "subcategory":"Arcade",
            "type":"Entertainment"
        }
    ],
    "sg:phone":"+1 305 688 0675",
    "sg:postcode":"33323",
    "sg:province":"FL",
    "sg:tags":[
        "device",
        "operator",
        "amusement"
    ],
    "wof:name":"Gratigny Amoco",
    "wof:placetype":"venue"
},
  "geometry": {"coordinates":[-80.307089,26.160378],"type":"Point"}
}