{
  "type": "Feature",
  "properties": {
    "iso:country":"US",
    "sg:address":"2 River Falls Dr",
    "sg:city":"Cocoa Beach",
    "sg:classifiers":[
        {
            "category":"Professional",
            "subcategory":"Management & Consulting",
            "type":"Services"
        }
    ],
    "sg:phone":"+1 321 784 1190",
    "sg:postcode":"32931",
    "sg:province":"FL",
    "sg:tags":[
        "fuel"
    ],
    "wof:name":"Vacation Beach Inc",
    "wof:placetype":"venue"
},
  "geometry": {"coordinates":[-80.610607,28.287008],"type":"Point"}
}