{
  "type": "Feature",
  "properties": {
    "iso:country":"US",
    "sg:address":"3030 SW 84th Ave",
    "sg:city":"Miami",
    "sg:classifiers":[
        {
            "category":"Professional",
            "subcategory":"Engineering",
            "type":"Services"
        }
    ],
    "sg:phone":"+1 305 225 5717",
    "sg:postcode":"33155",
    "sg:province":"FL",
    "sg:tags":[
        "engineer"
    ],
    "wof:name":"O L Consulting Inc",
    "wof:placetype":"venue"
},
  "geometry": {"coordinates":[-80.33152,25.742518],"type":"Point"}
}