{
  "type": "Feature",
  "properties": {
    "addr:full":"1316 SW 118th Ter Fort Lauderdale FL 33325",
    "addr:housenumber":"1316",
    "addr:postcode":"33325",
    "addr:street":"Sw 118Th Ter",
    "iso:country":"US",
    "sg:address":"1316 SW 118th Ter",
    "sg:city":"Fort Lauderdale",
    "sg:classifiers":[
        {
            "category":"Professional",
            "type":"Services"
        }
    ],
    "sg:phone":"+1 954 382 0462",
    "sg:postcode":"33325",
    "sg:province":"FL",
    "wof:name":"Christine Dunn Inc",
    "wof:placetype":"venue"
},
  "geometry": {"coordinates":[-80.30672199999999,26.102897],"type":"Point"}
}