{
  "type": "Feature",
  "properties": {
    "addr:full":"997 Texas Pkwy Crestview FL 32536",
    "addr:housenumber":"997",
    "addr:postcode":"32536",
    "addr:street":"Texas Pkwy",
    "iso:country":"US",
    "sg:address":"997 Texas Pkwy",
    "sg:city":"Crestview",
    "sg:classifiers":[
        {
            "category":"Organizations",
            "subcategory":"Religious Organization",
            "type":"Services"
        }
    ],
    "sg:phone":"+1 850 689 2092",
    "sg:postcode":"32536",
    "sg:province":"FL",
    "sg:tags":[
        "church"
    ],
    "wof:name":"Seventh Day Adventist Church",
    "wof:placetype":"venue"
},
  "geometry": {"coordinates":[-86.567942,30.77432],"type":"Point"}
}