{
  "type": "Feature",
  "properties": {
    "addr:full":"7765 Courtyard Run W Boca Raton FL 33433",
    "addr:housenumber":"7765",
    "addr:postcode":"33433",
    "addr:street":"Courtyard Run W",
    "iso:country":"US",
    "sg:address":"7765 Courtyard Run W",
    "sg:city":"Boca Raton",
    "sg:classifiers":[
        {
            "category":"Shopping",
            "type":"Retail Goods"
        }
    ],
    "sg:phone":"+1 561 391 3007",
    "sg:postcode":"33433",
    "sg:province":"FL",
    "sg:tags":[
        "merchandise"
    ],
    "wof:name":"A T C Voicedata Inc",
    "wof:placetype":"venue"
},
  "geometry": {"coordinates":[-80.167001,26.351165],"type":"Point"}
}