{
  "type": "Feature",
  "properties": {
    "addr:full":"16531 Fishhawk Blvd Lithia FL 33547",
    "addr:housenumber":"16531",
    "addr:postcode":"33547",
    "addr:street":"Fishhawk Blvd",
    "iso:country":"US",
    "sg:address":"16531 Fishhawk Blvd",
    "sg:city":"Lithia",
    "sg:classifiers":[
        {
            "category":"Banks & Credit Unions",
            "subcategory":"Bank",
            "type":"Services"
        },
        {
            "category":"Banks & Credit Unions",
            "subcategory":"Financial Services",
            "type":"Services"
        }
    ],
    "sg:phone":"+1 813 574 3170",
    "sg:postcode":"33547",
    "sg:province":"FL",
    "sg:tags":[
        "commercial",
        "financing",
        "saving",
        "loan",
        "mortgage"
    ],
    "sg:website":"http://www.bbt.com/",
    "wof:name":"BB&T",
    "wof:placetype":"venue"
},
  "geometry": {"coordinates":[-82.204887,27.85689],"type":"Point"}
}