{
  "type": "Feature",
  "properties": {
    "addr:full":"8326 Vintage Dr Orlando FL 32835",
    "addr:housenumber":"8326",
    "addr:postcode":"32835",
    "addr:street":"Vintage Dr",
    "iso:country":"US",
    "sg:address":"8326 Vintage Dr",
    "sg:city":"Orlando",
    "sg:classifiers":[
        {
            "category":"Place Of Worship",
            "type":"Public Place"
        }
    ],
    "sg:phone":"+1 407 299 8136",
    "sg:postcode":"32835",
    "sg:province":"FL",
    "sg:tags":[
        "church"
    ],
    "wof:name":"Saint Paul Orthodox Church Of Greater Orlando, I",
    "wof:placetype":"venue"
},
  "geometry": {"coordinates":[-81.49705400000001,28.496521],"type":"Point"}
}