{
  "type": "Feature",
  "properties": {
    "addr:full":"801 Warren Ave Cocoa FL 32922",
    "addr:housenumber":"801",
    "addr:postcode":"32922",
    "addr:street":"Warren Ave",
    "iso:country":"US",
    "sg:address":"801 Warren Ave",
    "sg:city":"Cocoa",
    "sg:classifiers":[
        {
            "category":"Building & Trades",
            "subcategory":"Electrical",
            "type":"Services"
        }
    ],
    "sg:phone":"+1 321 433 1058",
    "sg:postcode":"32922",
    "sg:province":"FL",
    "sg:tags":[
        "electrician"
    ],
    "wof:name":"Tee Electric",
    "wof:placetype":"venue"
},
  "geometry": {"coordinates":[-80.74387400000001,28.365801],"type":"Point"}
}