{
  "type": "Feature",
  "properties": {
    "iso:country":"US",
    "sg:address":"6200 20th St",
    "sg:city":"Vero Beach",
    "sg:classifiers":[
        {
            "category":"Ice Cream",
            "type":"Food & Drink"
        }
    ],
    "sg:menulink":"http://www.allmenus.com/fl/vero-beach/172375-dairy-queen/menu/",
    "sg:phone":"+1 772 562 0007",
    "sg:postcode":"32966",
    "sg:province":"FL",
    "sg:tags":[
        "burger",
        "american"
    ],
    "wof:name":"Dairy Queen",
    "wof:placetype":"venue"
},
  "geometry": {"coordinates":[-80.455314,27.639134],"type":"Point"}
}