{
  "type": "Feature",
  "properties": {
    "addr:full":"1190 Spring Centre S Blvd Altamonte Springs FL 32714",
    "addr:housenumber":"1190",
    "addr:postcode":"32714",
    "addr:street":"Spring Centre S Blvd",
    "iso:country":"US",
    "sg:address":"1190 Spring Centre S Blvd",
    "sg:city":"Altamonte Springs",
    "sg:classifiers":[
        {
            "category":"Fast Food",
            "type":"Food & Drink"
        }
    ],
    "sg:phone":"+1 407 788 2113",
    "sg:postcode":"32714",
    "sg:province":"FL",
    "wof:name":"Burger King",
    "wof:placetype":"venue"
},
  "geometry": {"coordinates":[-81.39276700000001,28.688045],"type":"Point"}
}