{
  "type": "Feature",
  "properties": {
    "iso:country":"US",
    "sg:address":"5018 N 22nd St",
    "sg:city":"Tampa",
    "sg:classifiers":[
        {
            "category":"Retail",
            "subcategory":"Auto Repair",
            "type":"Services"
        }
    ],
    "sg:phone":"+1 813 458 6619",
    "sg:postcode":"33610",
    "sg:province":"FL",
    "sg:tags":[
        "automobile",
        "referral",
        "truck",
        "road",
        "service-automotive"
    ],
    "sg:website":"http://www.affordablepowerwindowrepair.com",
    "wof:name":"Affordable Power Window Repair",
    "wof:placetype":"venue"
},
  "geometry": {"coordinates":[-82.434792,27.99161],"type":"Point"}
}