{
  "type": "Feature",
  "properties": {
    "iso:country":"US",
    "sg:address":"3287 Wallace Lake Rd",
    "sg:city":"Milton",
    "sg:classifiers":[
        {
            "category":"Organizations",
            "subcategory":"Religious Organization",
            "type":"Services"
        }
    ],
    "sg:phone":"+1 850 994 8278",
    "sg:postcode":"32571",
    "sg:province":"FL",
    "sg:tags":[
        "church"
    ],
    "sg:website":"www.wallacebaptistchurch.org",
    "wof:name":"Wallace Baptist Church",
    "wof:placetype":"venue"
},
  "geometry": {"coordinates":[-87.18678300000001,30.684757],"type":"Point"}
}