{
  "type": "Feature",
  "properties": {
    "addr:full":"4920 Datil Pepper Rd St Augustine FL 32086",
    "addr:postcode":"4920;32086",
    "addr:street":"Pepper Rd",
    "iso:country":"US",
    "sg:address":"4920 Datil Pepper Rd",
    "sg:city":"St Augustine",
    "sg:classifiers":[
        {
            "category":"Real Estate",
            "subcategory":"Real Estate Agent",
            "type":"Services"
        }
    ],
    "sg:phone":"+1 904 794 5755",
    "sg:postcode":"32086",
    "sg:province":"FL",
    "sg:tags":[
        "inspection"
    ],
    "wof:name":"All American Home Svc",
    "wof:placetype":"venue"
},
  "geometry": {"coordinates":[-81.32668700000001,29.799375],"type":"Point"}
}