{
  "type": "Feature",
  "properties": {
    "iso:country":"US",
    "sg:address":"2800 E Sunrise Blvd",
    "sg:city":"Fort Lauderdale",
    "sg:classifiers":[
        {
            "category":"Personal",
            "subcategory":"Beauty Salon",
            "type":"Services"
        }
    ],
    "sg:phone":"+1 954 561 8922",
    "sg:postcode":"33304",
    "sg:province":"FL",
    "sg:tags":[
        "shop"
    ],
    "wof:name":"Nancy A Shaller Special Event",
    "wof:placetype":"venue"
},
  "geometry": {"coordinates":[-80.110754,26.137838],"type":"Point"}
}