{
  "type": "Feature",
  "properties": {
    "addr:full":"2435 Ridgewind Way Windermere FL 34786",
    "addr:housenumber":"2435",
    "addr:postcode":"34786",
    "addr:street":"Ridgewind Way",
    "iso:country":"US",
    "sg:address":"2435 Ridgewind Way",
    "sg:city":"Windermere",
    "sg:classifiers":[
        {
            "category":"Professional",
            "subcategory":"Management & Consulting",
            "type":"Services"
        },
        {
            "category":"Professional",
            "subcategory":"Advertising",
            "type":"Services"
        }
    ],
    "sg:phone":"+1 407 876 7978",
    "sg:postcode":"34786",
    "sg:province":"FL",
    "sg:tags":[
        "marketing",
        "program",
        "consultant"
    ],
    "wof:name":"Grant & Assoc",
    "wof:placetype":"venue"
},
  "geometry": {"coordinates":[-81.571732,28.508298],"type":"Point"}
}