{
  "type": "Feature",
  "properties": {
    "iso:country":"US",
    "sg:address":"232 Gala Cir",
    "sg:city":"Daytona Beach",
    "sg:classifiers":[
        {
            "category":"Real Estate",
            "subcategory":"Developer",
            "type":"Services"
        }
    ],
    "sg:phone":"+1 386 274 2900",
    "sg:postcode":"32124",
    "sg:province":"FL",
    "wof:name":"LPGA Home Sales-Top Flight",
    "wof:placetype":"venue"
},
  "geometry": {"coordinates":[-81.11272700000001,29.213036],"type":"Point"}
}