{
  "type": "Feature",
  "properties": {
    "iso:country":"US",
    "sg:address":"15813 Hays Rd",
    "sg:city":"Brooksville",
    "sg:classifiers":[
        {
            "category":"Organizations",
            "subcategory":"Religious Organization",
            "type":"Services"
        }
    ],
    "sg:phone":"+1 727 856 8787",
    "sg:postcode":"34610",
    "sg:province":"FL",
    "sg:tags":[
        "church"
    ],
    "wof:name":"Son Coast Pentecostal Church",
    "wof:placetype":"venue"
},
  "geometry": {"coordinates":[-82.575895,28.386945],"type":"Point"}
}