{
  "type": "Feature",
  "properties": {
    "addr:full":"4801 George Rd Tampa FL 33634",
    "addr:housenumber":"4801",
    "addr:postcode":"33634",
    "addr:street":"George Rd",
    "iso:country":"US",
    "sg:address":"4801 George Rd",
    "sg:city":"Tampa",
    "sg:classifiers":[
        {
            "category":"Wholesale",
            "subcategory":"Stationery",
            "type":"Manufacturing & Wholesale Goods"
        },
        {
            "category":"Shopping",
            "subcategory":"Stationery & Office Supplies",
            "type":"Retail Goods"
        }
    ],
    "sg:phone":"+1 813 290 8868",
    "sg:postcode":"33634",
    "sg:province":"FL",
    "wof:name":"Royal Office Products",
    "wof:placetype":"venue"
},
  "geometry": {"coordinates":[-82.550394,27.98902],"type":"Point"}
}