{
  "type": "Feature",
  "properties": {
    "iso:country":"US",
    "sg:address":"11511 Casey Rd",
    "sg:city":"Tampa",
    "sg:classifiers":[
        {
            "category":"Wholesale",
            "subcategory":"Computers",
            "type":"Manufacturing & Wholesale Goods"
        }
    ],
    "sg:phone":"+1 813 264 6204",
    "sg:postcode":"33618",
    "sg:province":"FL",
    "wof:name":"Visual Inspirations Inc",
    "wof:placetype":"venue"
},
  "geometry": {"coordinates":[-82.51705800000001,28.053221],"type":"Point"}
}