{
  "type": "Feature",
  "properties": {
    "iso:country":"US",
    "sg:address":"1460 Maravilla Ave",
    "sg:city":"Fort Myers",
    "sg:classifiers":[
        {
            "category":"Building & Trades",
            "subcategory":"Construction",
            "type":"Services"
        }
    ],
    "sg:phone":"+1 239 910 5574",
    "sg:postcode":"33901",
    "sg:province":"FL",
    "sg:tags":[
        "contractor"
    ],
    "wof:name":"Millennium Kitchens and Bath",
    "wof:placetype":"venue"
},
  "geometry": {"coordinates":[-81.88342,26.615404],"type":"Point"}
}