{
  "type": "Feature",
  "properties": {
    "iso:country":"US",
    "sg:address":"42110 Fisher Island Dr",
    "sg:city":"Miami Beach",
    "sg:classifiers":[
        {
            "category":"Shopping",
            "subcategory":"Florist",
            "type":"Retail Goods"
        }
    ],
    "sg:phone":"+1 305 531 9401",
    "sg:postcode":"33109",
    "sg:province":"FL",
    "sg:website":"www.oceanflorist.net",
    "wof:name":"Ocean Florist Inc",
    "wof:placetype":"venue"
},
  "geometry": {"coordinates":[-80.14510300000001,25.7623],"type":"Point"}
}