{
  "type": "Feature",
  "properties": {
    "addr:full":"1410 Coral Ridge Dr Pompano Beach FL 33071",
    "addr:housenumber":"1410",
    "addr:postcode":"33071",
    "addr:street":"Coral Ridge Dr",
    "iso:country":"US",
    "sg:address":"1410 Coral Ridge Dr",
    "sg:city":"Pompano Beach",
    "sg:classifiers":[
        {
            "category":"Restaurant",
            "type":"Food & Drink"
        }
    ],
    "sg:menulink":"http://www.allmenus.com/fl/margate/50117-rotelli/menu/",
    "sg:phone":"+1 954 346 3333",
    "sg:postcode":"33071",
    "sg:province":"FL",
    "sg:tags":[
        "american",
        "pizza"
    ],
    "wof:name":"Rotelli",
    "wof:placetype":"venue"
},
  "geometry": {"coordinates":[-80.279627,26.24861],"type":"Point"}
}