{
  "type": "Feature",
  "properties": {
    "addr:full":"3767 Gulf Breeze Pkwy Gulf Breeze FL 32563",
    "addr:housenumber":"3767",
    "addr:postcode":"32563",
    "addr:street":"Gulf Breeze Pkwy",
    "iso:country":"US",
    "sg:address":"3767 Gulf Breeze Pkwy",
    "sg:city":"Gulf Breeze",
    "sg:classifiers":[
        {
            "category":"Deli",
            "type":"Food & Drink"
        }
    ],
    "sg:menulink":"http://www.allmenus.com/fl/gulf-breeze-harold/126043-blimpie-subs--sandwiches/menu/",
    "sg:phone":"+1 850 932 8637",
    "sg:postcode":"32563",
    "sg:province":"FL",
    "sg:tags":[
        "wrap",
        "american",
        "sandwich"
    ],
    "wof:name":"Blimpie Subs & Sandwiches",
    "wof:placetype":"venue"
},
  "geometry": {"coordinates":[-87.06506400000001,30.389995],"type":"Point"}
}