{
  "type": "Feature",
  "properties": {
    "addr:full":"913 Gulf Breeze Pkwy Gulf Breeze FL 32561",
    "addr:housenumber":"913",
    "addr:postcode":"32561",
    "addr:street":"Gulf Breeze Pkwy",
    "iso:country":"US",
    "sg:address":"913 Gulf Breeze Pkwy",
    "sg:city":"Gulf Breeze",
    "sg:classifiers":[
        {
            "category":"Professional",
            "type":"Services"
        }
    ],
    "sg:phone":"+1 850 932 3911",
    "sg:postcode":"32561",
    "sg:province":"FL",
    "sg:tags":[
        "establishment"
    ],
    "wof:name":"J & J Of Pensacola",
    "wof:placetype":"venue"
},
  "geometry": {"coordinates":[-87.16238800000001,30.357301],"type":"Point"}
}