{
  "type": "Feature",
  "properties": {
    "iso:country":"US",
    "sg:address":"499 Alt Keene Rd",
    "sg:city":"Largo",
    "sg:classifiers":[
        {
            "category":"Building & Trades",
            "subcategory":"Construction",
            "type":"Services"
        }
    ],
    "sg:phone":"+1 727 586 4211",
    "sg:postcode":"33771",
    "sg:province":"FL",
    "sg:tags":[
        "development",
        "design"
    ],
    "wof:name":"John B Goodman Ltd Partnership",
    "wof:placetype":"venue"
},
  "geometry": {"coordinates":[-82.768208,27.921492],"type":"Point"}
}