{
  "type": "Feature",
  "properties": {
    "addr:full":"1700 NW 22nd Ct Pompano Beach FL 33069",
    "addr:housenumber":"1700",
    "addr:postcode":"33069",
    "addr:street":"Nw 22Nd Ct",
    "iso:country":"US",
    "sg:address":"1700 NW 22nd Ct",
    "sg:city":"Pompano Beach",
    "sg:classifiers":[
        {
            "category":"Building & Trades",
            "subcategory":"Construction",
            "type":"Services"
        }
    ],
    "sg:phone":"+1 954 960 0635",
    "sg:postcode":"33069",
    "sg:province":"FL",
    "sg:tags":[
        "screen",
        "enclosure"
    ],
    "wof:name":"American Screen Enclosures Inc",
    "wof:placetype":"venue"
},
  "geometry": {"coordinates":[-80.14623400000001,26.258371],"type":"Point"}
}