{
  "type": "Feature",
  "properties": {
    "iso:country":"US",
    "sg:address":"3424 Griffin Rd",
    "sg:city":"Fort Lauderdale",
    "sg:classifiers":[
        {
            "category":"Wholesale",
            "subcategory":"Apparel",
            "type":"Manufacturing & Wholesale Goods"
        }
    ],
    "sg:phone":"+1 954 962 6655",
    "sg:postcode":"33312",
    "sg:province":"FL",
    "sg:tags":[
        "fabric"
    ],
    "wof:name":"Wayne Lagana & Co",
    "wof:placetype":"venue"
},
  "geometry": {"coordinates":[-80.189607,26.062434],"type":"Point"}
}