{
  "type": "Feature",
  "properties": {
    "iso:country":"US",
    "sg:address":"2457 Breakwater Cir",
    "sg:city":"Sarasota",
    "sg:classifiers":[
        {
            "category":"Social Services",
            "subcategory":"Retirement Home",
            "type":"Services"
        }
    ],
    "sg:phone":"+1 941 922 8212",
    "sg:postcode":"34231",
    "sg:province":"FL",
    "sg:tags":[
        "convalescent",
        "nursing"
    ],
    "wof:name":"Jack S Semelsberger Jr",
    "wof:placetype":"venue"
},
  "geometry": {"coordinates":[-82.50738800000001,27.251508],"type":"Point"}
}