{
  "type": "Feature",
  "properties": {
    "iso:country":"US",
    "sg:address":"18222 SW 27th St",
    "sg:city":"Hollywood",
    "sg:classifiers":[
        {
            "category":"Banks & Credit Unions",
            "subcategory":"Investment Brokerage",
            "type":"Services"
        }
    ],
    "sg:phone":"+1 954 430 3217",
    "sg:postcode":"33029",
    "sg:province":"FL",
    "sg:tags":[
        "security",
        "investor"
    ],
    "wof:name":"Yb Broke Investment Club",
    "wof:placetype":"venue"
},
  "geometry": {"coordinates":[-80.388814,25.982152],"type":"Point"}
}