{
  "type": "Feature",
  "properties": {
    "iso:country":"US",
    "sg:address":"1542 W 49th St",
    "sg:city":"Hialeah",
    "sg:classifiers":[
        {
            "category":"Professional",
            "subcategory":"Printing & Photocopies",
            "type":"Services"
        }
    ],
    "sg:phone":"+1 305 828 6555",
    "sg:postcode":"33012",
    "sg:province":"FL",
    "sg:tags":[
        "lithographer"
    ],
    "wof:name":"Lpc Global Print",
    "wof:placetype":"venue"
},
  "geometry": {"coordinates":[-80.313332,25.866525],"type":"Point"}
}