{
  "type": "Feature",
  "properties": {
    "addr:full":"4126 10th Ave N Lake Worth FL 33461",
    "addr:housenumber":"4126",
    "addr:postcode":"33461",
    "addr:street":"10Th Ave N",
    "iso:country":"US",
    "sg:address":"4126 10th Ave N",
    "sg:city":"Lake Worth",
    "sg:classifiers":[
        {
            "category":"Manufacturing",
            "subcategory":"Jewelry",
            "type":"Manufacturing & Wholesale Goods"
        }
    ],
    "sg:phone":"+1 561 433 3838",
    "sg:postcode":"33461",
    "sg:province":"FL",
    "sg:tags":[
        "repair",
        "mfg",
        "watch",
        "custom"
    ],
    "wof:name":"Steves Expert Watch",
    "wof:placetype":"venue"
},
  "geometry": {"coordinates":[-80.10541600000001,26.629091],"type":"Point"}
}