{
  "type": "Feature",
  "properties": {
    "addr:full":"9655 W Flagler St Miami FL 33174",
    "addr:housenumber":"9655",
    "addr:postcode":"33174",
    "addr:street":"W Flagler St",
    "iso:country":"US",
    "sg:address":"9655 W Flagler St",
    "sg:city":"Miami",
    "sg:classifiers":[
        {
            "category":"Fast Food",
            "type":"Food & Drink"
        },
        {
            "category":"Restaurant",
            "type":"Food & Drink"
        }
    ],
    "sg:phone":"+1 305 220 1441",
    "sg:postcode":"33174",
    "sg:province":"FL",
    "sg:tags":[
        "american",
        "hot",
        "hamburger",
        "dog"
    ],
    "sg:website":"http://www.wendys.com",
    "wof:name":"Wendy's",
    "wof:placetype":"venue"
},
  "geometry": {"coordinates":[-80.35306199999999,25.769075],"type":"Point"}
}