{
  "type": "Feature",
  "properties": {
    "iso:country":"US",
    "sg:address":"10101 Cross Creek Blvd",
    "sg:city":"Tampa",
    "sg:classifiers":[
        {
            "category":"Education",
            "subcategory":"School",
            "type":"Public Place"
        }
    ],
    "sg:phone":"+1 813 631 4694",
    "sg:postcode":"33647",
    "sg:province":"FL",
    "wof:name":"Louis Bentio Middle School",
    "wof:placetype":"venue"
},
  "geometry": {"coordinates":[-82.321325,28.142101],"type":"Point"}
}