{
  "type": "Feature",
  "properties": {
    "iso:country":"US",
    "sg:address":"13439 Fountainbleau Dr",
    "sg:city":"Clermont",
    "sg:classifiers":[
        {
            "category":"Building & Trades",
            "subcategory":"Construction",
            "type":"Services"
        }
    ],
    "sg:phone":"+1 407 924 7784",
    "sg:postcode":"34711",
    "sg:province":"FL",
    "sg:tags":[
        "house"
    ],
    "wof:name":"Marlin Construction Services",
    "wof:placetype":"venue"
},
  "geometry": {"coordinates":[-81.669179,28.539788],"type":"Point"}
}