{
  "type": "Feature",
  "properties": {
    "iso:country":"US",
    "sg:address":"8370 NW 27th Ave",
    "sg:city":"Miami",
    "sg:classifiers":[
        {
            "category":"Shopping",
            "subcategory":"Mobile Phones",
            "type":"Retail Goods"
        }
    ],
    "sg:phone":"+1 305 694 1818",
    "sg:postcode":"33147",
    "sg:province":"FL",
    "wof:name":"Something Wireless",
    "wof:placetype":"venue"
},
  "geometry": {"coordinates":[-80.242138,25.850546],"type":"Point"}
}