{
  "type": "Feature",
  "properties": {
    "iso:country":"US",
    "sg:address":"137 US Hwy 92",
    "sg:city":"Debary",
    "sg:classifiers":[
        {
            "category":"Government",
            "subcategory":"Office",
            "type":"Public Place"
        }
    ],
    "sg:phone":"+1 386 668 2040",
    "sg:postcode":"32713",
    "sg:province":"FL",
    "sg:tags":[
        "city"
    ],
    "wof:name":"De Bary City Hall",
    "wof:placetype":"venue"
},
  "geometry": {"coordinates":[-81.31045,28.879051],"type":"Point"}
}