{
  "type": "Feature",
  "properties": {
    "addr:full":"4986 73rd Ave N Pinellas Park FL 33781",
    "addr:housenumber":"4986",
    "addr:postcode":"33781",
    "addr:street":"73Rd Ave N",
    "iso:country":"US",
    "sg:address":"4986 73rd Ave N",
    "sg:city":"Pinellas Park",
    "sg:classifiers":[
        {
            "category":"Building & Trades",
            "subcategory":"Landscaping Services",
            "type":"Services"
        }
    ],
    "sg:phone":"+1 727 546 7535",
    "sg:postcode":"33781",
    "sg:province":"FL",
    "wof:name":"Safari Lawn Care",
    "wof:placetype":"venue"
},
  "geometry": {"coordinates":[-82.700322,27.838215],"type":"Point"}
}