{
  "type": "Feature",
  "properties": {
    "addr:full":"2109 W US Hwy 90 Lake City FL 32055",
    "addr:housenumber":"2109",
    "addr:postcode":"32055",
    "addr:street":"W Us Hwy 90",
    "iso:country":"US",
    "sg:address":"2109 W US Hwy 90",
    "sg:city":"Lake City",
    "sg:classifiers":[
        {
            "category":"Shopping",
            "subcategory":"Pharmacy",
            "type":"Retail Goods"
        }
    ],
    "sg:phone":"+1 386 752 8090",
    "sg:postcode":"32055",
    "sg:province":"FL",
    "wof:name":"Eckerd",
    "wof:placetype":"venue"
},
  "geometry": {"coordinates":[-82.653891,30.18539],"type":"Point"}
}