{
  "type": "Feature",
  "properties": {
    "addr:full":"815 S Central Ave Lakeland FL 33815",
    "addr:housenumber":"815",
    "addr:postcode":"33815",
    "addr:street":"S Central Ave",
    "iso:country":"US",
    "sg:address":"815 S Central Ave",
    "sg:city":"Lakeland",
    "sg:classifiers":[
        {
            "category":"Organizations",
            "subcategory":"Religious Organization",
            "type":"Services"
        }
    ],
    "sg:phone":"+1 863 688 6083",
    "sg:postcode":"33815",
    "sg:province":"FL",
    "wof:name":"Central Bptst Cmnty Ministries",
    "wof:placetype":"venue"
},
  "geometry": {"coordinates":[-81.97362800000001,28.035006],"type":"Point"}
}