{
  "type": "Feature",
  "properties": {
    "iso:country":"US",
    "sg:address":"2635 Skyview Dr",
    "sg:city":"Lakeland",
    "sg:classifiers":[
        {
            "category":"Manufacturing",
            "subcategory":"Buildings",
            "type":"Manufacturing & Wholesale Goods"
        },
        {
            "category":"Building & Trades",
            "subcategory":"Plumbing",
            "type":"Services"
        },
        {
            "category":"Building & Trades",
            "subcategory":"Construction",
            "type":"Services"
        }
    ],
    "sg:phone":"+1 863 644 1211",
    "sg:postcode":"33801",
    "sg:province":"FL",
    "sg:tags":[
        "plumber",
        "industrial",
        "builder",
        "contractor",
        "contractors-commercial",
        "mechanical",
        "home"
    ],
    "sg:website":"http://www.divglobal.com",
    "wof:name":"Diversified Piping",
    "wof:placetype":"venue"
},
  "geometry": {"coordinates":[-81.90683900000001,28.025977],"type":"Point"}
}