{
  "type": "Feature",
  "properties": {
    "iso:country":"US",
    "sg:address":"10936 NW 7th Ave",
    "sg:city":"Miami",
    "sg:classifiers":[
        {
            "category":"Food & Beverages",
            "subcategory":"Groceries & Convenience Stores",
            "type":"Retail Goods"
        }
    ],
    "sg:phone":"+1 305 757 1788",
    "sg:postcode":"33168",
    "sg:province":"FL",
    "sg:tags":[
        "fresh",
        "fruit",
        "meat"
    ],
    "wof:name":"Goodway Supermarket Inc",
    "wof:placetype":"venue"
},
  "geometry": {"coordinates":[-80.210098,25.8757],"type":"Point"}
}