{
  "type": "Feature",
  "properties": {
    "iso:country":"US",
    "sg:address":"1615 NE 53rd St",
    "sg:city":"Pompano Beach",
    "sg:classifiers":[
        {
            "category":"Building & Trades",
            "subcategory":"Construction",
            "type":"Services"
        }
    ],
    "sg:phone":"+1 954 592 6431",
    "sg:postcode":"33064",
    "sg:province":"FL",
    "sg:tags":[
        "contractor"
    ],
    "wof:name":"Aukland Stucco & Plastering Co",
    "wof:placetype":"venue"
},
  "geometry": {"coordinates":[-80.101491,26.296215],"type":"Point"}
}