{
  "type": "Feature",
  "properties": {
    "iso:country":"US",
    "sg:address":"11133 Blue Star Hwy",
    "sg:city":"Quincy",
    "sg:classifiers":[
        {
            "category":"Shopping",
            "subcategory":"Department Store",
            "type":"Retail Goods"
        },
        {
            "category":"Shopping",
            "subcategory":"Discount & Variety Stores",
            "type":"Retail Goods"
        }
    ],
    "sg:phone":"+1 850 856 5421",
    "sg:postcode":"32352",
    "sg:province":"FL",
    "sg:tags":[
        "salvage",
        "surplus",
        "merchandise"
    ],
    "sg:website":"http://www.parramore.com",
    "wof:name":"Parramore, H A Surplus Co",
    "wof:placetype":"venue"
},
  "geometry": {"coordinates":[-84.693742,30.660882],"type":"Point"}
}