{
  "type": "Feature",
  "properties": {
    "iso:country":"US",
    "sg:address":"7 SE 22nd Ave",
    "sg:city":"Pompano Beach",
    "sg:classifiers":[
        {
            "category":"Restaurant",
            "type":"Food & Drink"
        }
    ],
    "sg:phone":"+1 954 943 7705",
    "sg:postcode":"33062",
    "sg:province":"FL",
    "wof:name":"Unique Restaurants",
    "wof:placetype":"venue"
},
  "geometry": {"coordinates":[-80.101927,26.230994],"type":"Point"}
}