{
  "type": "Feature",
  "properties": {
    "addr:full":"1763 Ken Thompson Pkwy Sarasota FL 34236",
    "addr:housenumber":"1763",
    "addr:postcode":"34236",
    "addr:street":"Ken Thompson Pkwy",
    "iso:country":"US",
    "sg:address":"1763 Ken Thompson Pkwy",
    "sg:city":"Sarasota",
    "sg:classifiers":[
        {
            "category":"Social Services",
            "type":"Services"
        },
        {
            "category":"Professional",
            "subcategory":"Employment Agencies",
            "type":"Services"
        },
        {
            "category":"Organizations",
            "subcategory":"Membership Organization",
            "type":"Services"
        }
    ],
    "sg:phone":"+1 941 388 3500",
    "sg:postcode":"34236",
    "sg:province":"FL",
    "sg:tags":[
        "workers'",
        "club",
        "placement",
        "private",
        "volunteer"
    ],
    "wof:name":"Sarasota Outboard Club, Inc.",
    "wof:placetype":"venue"
},
  "geometry": {"coordinates":[-82.57393,27.335722],"type":"Point"}
}