{
  "type": "Feature",
  "properties": {
    "addr:full":"4743 Raleigh St Orlando FL 32811",
    "addr:housenumber":"4743",
    "addr:postcode":"32811",
    "addr:street":"Raleigh St",
    "iso:country":"US",
    "sg:address":"4743 Raleigh St",
    "sg:city":"Orlando",
    "sg:classifiers":[
        {
            "category":"Social Services",
            "subcategory":"Child Care",
            "type":"Services"
        }
    ],
    "sg:phone":"+1 407 578 2548",
    "sg:postcode":"32811",
    "sg:province":"FL",
    "sg:tags":[
        "day"
    ],
    "wof:name":"With Loving Care Learning Ctr",
    "wof:placetype":"venue"
},
  "geometry": {"coordinates":[-81.44124100000001,28.527906],"type":"Point"}
}