{
  "type": "Feature",
  "properties": {
    "iso:country":"US",
    "sg:address":"4835 Collins Ave",
    "sg:city":"Miami Beach",
    "sg:classifiers":[
        {
            "category":"Travel",
            "subcategory":"Hotels & Motels",
            "type":"Entertainment"
        }
    ],
    "sg:phone":"+1 305 538 8666",
    "sg:postcode":"33140",
    "sg:province":"FL",
    "wof:name":"Grand Beach Suites Hotel",
    "wof:placetype":"venue"
},
  "geometry": {"coordinates":[-80.122005,25.823772],"type":"Point"}
}