{
  "type": "Feature",
  "properties": {
    "iso:country":"US",
    "sg:address":"4685 Bucida Rd",
    "sg:city":"Boynton Beach",
    "sg:classifiers":[
        {
            "category":"Autos & Motor Vehicles",
            "subcategory":"Fuel & Gas Station",
            "type":"Retail Goods"
        }
    ],
    "sg:phone":"+1 561 968 2100",
    "sg:postcode":"33436",
    "sg:province":"FL",
    "sg:tags":[
        "oil"
    ],
    "wof:name":"Jopatra Inc",
    "wof:placetype":"venue"
},
  "geometry": {"coordinates":[-80.11836099999999,26.533813],"type":"Point"}
}