{
  "type": "Feature",
  "properties": {
    "addr:full":"9036 N Golfview Dr Dunnellon FL 34434",
    "addr:housenumber":"9036",
    "addr:postcode":"34434",
    "addr:street":"N Golfview Dr",
    "iso:country":"US",
    "sg:address":"9036 N Golfview Dr",
    "sg:city":"Dunnellon",
    "sg:classifiers":[
        {
            "category":"Manufacturing",
            "subcategory":"Textiles",
            "type":"Manufacturing & Wholesale Goods"
        }
    ],
    "sg:phone":"+1 352 489 5210",
    "sg:postcode":"34434",
    "sg:province":"FL",
    "sg:tags":[
        "outerwear",
        "commercial",
        "lithographic",
        "printing",
        "mill",
        "knit"
    ],
    "wof:name":"Some Racket",
    "wof:placetype":"venue"
},
  "geometry": {"coordinates":[-82.475691,28.995535],"type":"Point"}
}