{
  "type": "Feature",
  "properties": {
    "iso:country":"US",
    "sg:address":"2350 NW 102nd Pl",
    "sg:city":"Miami",
    "sg:classifiers":[
        {
            "category":"Wholesale",
            "subcategory":"Computers",
            "type":"Manufacturing & Wholesale Goods"
        },
        {
            "category":"Wholesale",
            "subcategory":"Tobacco Products",
            "type":"Manufacturing & Wholesale Goods"
        }
    ],
    "sg:phone":"+1 305 463 8889",
    "sg:postcode":"33172",
    "sg:province":"FL",
    "sg:tags":[
        "farm"
    ],
    "wof:name":"Tobacco Holdings LLC",
    "wof:placetype":"venue"
},
  "geometry": {"coordinates":[-80.362737,25.794743],"type":"Point"}
}