{
  "type": "Feature",
  "properties": {
    "iso:country":"US",
    "sg:address":"6020 E Bay Blvd",
    "sg:city":"Gulf Breeze",
    "sg:classifiers":[
        {
            "category":"Building & Trades",
            "subcategory":"Construction",
            "type":"Services"
        }
    ],
    "sg:phone":"+1 850 932 0899",
    "sg:postcode":"32563",
    "sg:province":"FL",
    "sg:tags":[
        "house"
    ],
    "wof:name":"Residential Remolding",
    "wof:placetype":"venue"
},
  "geometry": {"coordinates":[-86.97038499999999,30.42532],"type":"Point"}
}