{
  "type": "Feature",
  "properties": {
    "addr:full":"2241 SE West Blackwell Dr Port Saint Lucie FL 34952",
    "addr:housenumber":"2241",
    "addr:postcode":"34952",
    "addr:street":"Se West Blackwell Dr",
    "iso:country":"US",
    "sg:address":"2241 SE West Blackwell Dr",
    "sg:city":"Port Saint Lucie",
    "sg:classifiers":[
        {
            "category":"Manufacturing",
            "subcategory":"Building Materials",
            "type":"Manufacturing & Wholesale Goods"
        }
    ],
    "sg:phone":"+1 772 398 4765",
    "sg:postcode":"34952",
    "sg:province":"FL",
    "sg:tags":[
        "mfg"
    ],
    "wof:name":"Sharkey John E Designs In Wood",
    "wof:placetype":"venue"
},
  "geometry": {"coordinates":[-80.265248,27.273385],"type":"Point"}
}