{
  "type": "Feature",
  "properties": {
    "iso:country":"US",
    "sg:address":"137 Harrison Ave",
    "sg:city":"Panama City",
    "sg:classifiers":[
        {
            "category":"Shopping",
            "subcategory":"Bicycles & Sporting Goods",
            "type":"Retail Goods"
        }
    ],
    "sg:phone":"+1 850 769 2317",
    "sg:postcode":"32401",
    "sg:province":"FL",
    "wof:name":"C and G Sporting Gds Trophy Sp",
    "wof:placetype":"venue"
},
  "geometry": {"coordinates":[-85.66173000000001,30.154137],"type":"Point"}
}