{
  "type": "Feature",
  "properties": {
    "iso:country":"US",
    "sg:address":"3800 S Ocean Dr",
    "sg:city":"Hollywood",
    "sg:classifiers":[
        {
            "category":"Social Services",
            "type":"Services"
        }
    ],
    "sg:phone":"+1 954 458 1906",
    "sg:postcode":"33019",
    "sg:province":"FL",
    "sg:tags":[
        "organization",
        "welfare"
    ],
    "wof:name":"Central Business Club Inc",
    "wof:placetype":"venue"
},
  "geometry": {"coordinates":[-80.11834399999999,25.996847],"type":"Point"}
}