{
  "type": "Feature",
  "properties": {
    "addr:full":"1040 Greenwood Blvd Lake Mary FL 32746",
    "addr:housenumber":"1040",
    "addr:postcode":"32746",
    "addr:street":"Greenwood Blvd",
    "iso:country":"US",
    "sg:address":"1040 Greenwood Blvd",
    "sg:city":"Lake Mary",
    "sg:classifiers":[
        {
            "category":"Travel",
            "subcategory":"Hotels & Motels",
            "type":"Entertainment"
        }
    ],
    "sg:phone":"+1 407 829 2332",
    "sg:postcode":"32746",
    "sg:province":"FL",
    "wof:name":"Homestead Studio Suites Hotel",
    "wof:placetype":"venue"
},
  "geometry": {"coordinates":[-81.347246,28.745529],"type":"Point"}
}