{
  "type": "Feature",
  "properties": {
    "iso:country":"US",
    "sg:address":"1810 Creighton Rd",
    "sg:city":"Pensacola",
    "sg:classifiers":[
        {
            "category":"Real Estate",
            "subcategory":"Real Estate Services",
            "type":"Services"
        },
        {
            "category":"Real Estate",
            "subcategory":"Real Estate Agent",
            "type":"Services"
        }
    ],
    "sg:phone":"+1 850 476 3000",
    "sg:postcode":"32504",
    "sg:province":"FL",
    "sg:tags":[
        "management"
    ],
    "wof:name":"A Able Realty Of NW Fla Inc",
    "wof:placetype":"venue"
},
  "geometry": {"coordinates":[-87.20482199999999,30.495504],"type":"Point"}
}