{
  "type": "Feature",
  "properties": {
    "iso:country":"US",
    "sg:address":"219 Chalet Ave",
    "sg:city":"Indialantic",
    "sg:classifiers":[
        {
            "category":"Building & Trades",
            "subcategory":"Electrical",
            "type":"Services"
        }
    ],
    "sg:phone":"+1 321 952 7660",
    "sg:postcode":"32903",
    "sg:province":"FL",
    "sg:tags":[
        "electrical",
        "contractor"
    ],
    "wof:name":"Able Electric Inc",
    "wof:placetype":"venue"
},
  "geometry": {"coordinates":[-80.57234699999999,28.097626],"type":"Point"}
}