{
  "type": "Feature",
  "properties": {
    "iso:country":"US",
    "sg:address":"1865 N Semoran Blvd",
    "sg:city":"Orlando",
    "sg:classifiers":[
        {
            "category":"Travel",
            "subcategory":"Travel Agent",
            "type":"Entertainment"
        }
    ],
    "sg:phone":"+1 407 260 1744",
    "sg:postcode":"32807",
    "sg:province":"FL",
    "sg:tags":[
        "agency",
        "bureau"
    ],
    "wof:name":"Royale Vacations & Cruises",
    "wof:placetype":"venue"
},
  "geometry": {"coordinates":[-81.310874,28.570517],"type":"Point"}
}