{
  "type": "Feature",
  "properties": {
    "iso:country":"US",
    "sg:address":"5480 58th St N",
    "sg:city":"Saint Petersburg",
    "sg:classifiers":[
        {
            "category":"Real Estate",
            "subcategory":"Real Estate Operator",
            "type":"Services"
        }
    ],
    "sg:phone":"+1 727 541 7788",
    "sg:postcode":"33709",
    "sg:province":"FL",
    "sg:tags":[
        "property",
        "lessor"
    ],
    "wof:name":"All Star The",
    "wof:placetype":"venue"
},
  "geometry": {"coordinates":[-82.712352,27.821188],"type":"Point"}
}