{
  "type": "Feature",
  "properties": {
    "addr:full":"13183 Citrus Way Brooksville FL 34601",
    "addr:housenumber":"13183",
    "addr:postcode":"34601",
    "addr:street":"Citrus Way",
    "iso:country":"US",
    "sg:address":"13183 Citrus Way",
    "sg:city":"Brooksville",
    "sg:classifiers":[
        {
            "category":"Building & Trades",
            "subcategory":"Construction",
            "type":"Services"
        }
    ],
    "sg:phone":"+1 352 799 3131",
    "sg:postcode":"34601",
    "sg:province":"FL",
    "sg:tags":[
        "excavation",
        "utility"
    ],
    "wof:name":"Linton Excavating",
    "wof:placetype":"venue"
},
  "geometry": {"coordinates":[-82.463443,28.616686],"type":"Point"}
}