{
  "type": "Feature",
  "properties": {
    "iso:country":"US",
    "sg:address":"2818 Gary Ln",
    "sg:city":"Lakeland",
    "sg:classifiers":[
        {
            "category":"Professional",
            "subcategory":"Business Services",
            "type":"Services"
        }
    ],
    "sg:phone":"+1 863 619 8031",
    "sg:postcode":"33812",
    "sg:province":"FL",
    "wof:name":"Highsmith Contract Sales",
    "wof:placetype":"venue"
},
  "geometry": {"coordinates":[-81.920929,27.978005],"type":"Point"}
}