{
  "type": "Feature",
  "properties": {
    "addr:full":"13431 SW 56th St Miami FL 33175",
    "addr:housenumber":"13431",
    "addr:postcode":"33175",
    "addr:street":"Sw 56Th St",
    "iso:country":"US",
    "sg:address":"13431 SW 56th St",
    "sg:city":"Miami",
    "sg:classifiers":[
        {
            "category":"Personal",
            "subcategory":"Beauty Salon",
            "type":"Services"
        }
    ],
    "sg:phone":"+1 305 225 5800",
    "sg:postcode":"33175",
    "sg:province":"FL",
    "sg:tags":[
        "shop"
    ],
    "wof:name":"Hair Universal Inc",
    "wof:placetype":"venue"
},
  "geometry": {"coordinates":[-80.412295,25.714565],"type":"Point"}
}