{
  "type": "Feature",
  "properties": {
    "addr:full":"12551 Indian Rocks Rd Largo FL 33774",
    "addr:housenumber":"12551",
    "addr:postcode":"33774",
    "addr:street":"Indian Rocks Rd",
    "iso:country":"US",
    "sg:address":"12551 Indian Rocks Rd",
    "sg:city":"Largo",
    "sg:classifiers":[
        {
            "category":"Manufacturing",
            "subcategory":"Tools & Machinery",
            "type":"Manufacturing & Wholesale Goods"
        }
    ],
    "sg:phone":"+1 727 596 5750",
    "sg:postcode":"33774",
    "sg:province":"FL",
    "sg:tags":[
        "prosthetic",
        "devices",
        "mfg"
    ],
    "wof:name":"Coastal Orthopaedic Designs",
    "wof:placetype":"venue"
},
  "geometry": {"coordinates":[-82.83237,27.887282],"type":"Point"}
}