{
  "type": "Feature",
  "properties": {
    "iso:country":"US",
    "sg:address":"202 Caspian St",
    "sg:city":"Tampa",
    "sg:classifiers":[
        {
            "category":"Wholesale",
            "subcategory":"Vending Machines",
            "type":"Manufacturing & Wholesale Goods"
        }
    ],
    "sg:phone":"+1 813 254 1779",
    "sg:postcode":"33606",
    "sg:province":"FL",
    "sg:tags":[
        "operator"
    ],
    "wof:name":"Brink Distributors Inc",
    "wof:placetype":"venue"
},
  "geometry": {"coordinates":[-82.459688,27.924561],"type":"Point"}
}