{
  "type": "Feature",
  "properties": {
    "iso:country":"US",
    "sg:address":"2206 S Seacrest Blvd",
    "sg:city":"Boynton Beach",
    "sg:classifiers":[
        {
            "category":"Professional",
            "subcategory":"Lawyer & Legal Services",
            "type":"Services"
        }
    ],
    "sg:phone":"+1 561 737 8178",
    "sg:postcode":"33435",
    "sg:province":"FL",
    "wof:name":"Steven Goldfarb Esq",
    "wof:placetype":"venue"
},
  "geometry": {"coordinates":[-80.065702,26.508239],"type":"Point"}
}