{
  "type": "Feature",
  "properties": {
    "iso:country":"US",
    "sg:address":"40 Towne Center Cir",
    "sg:city":"Sanford",
    "sg:classifiers":[
        {
            "category":"Ice Cream",
            "type":"Food & Drink"
        }
    ],
    "sg:menulink":"http://www.allmenus.com/fl/sanford/92383-steak-n-shake/menu/",
    "sg:phone":"+1 407 328 8300",
    "sg:postcode":"32771",
    "sg:province":"FL",
    "sg:tags":[
        "american"
    ],
    "wof:name":"Steak 'n Shake",
    "wof:placetype":"venue"
},
  "geometry": {"coordinates":[-81.33820299999999,28.807143],"type":"Point"}
}