{
  "type": "Feature",
  "properties": {
    "iso:country":"US",
    "sg:address":"1880 Belleair Rd",
    "sg:city":"Clearwater",
    "sg:classifiers":[
        {
            "category":"Real Estate",
            "subcategory":"Real Estate Services",
            "type":"Services"
        },
        {
            "category":"Building & Trades",
            "subcategory":"Construction",
            "type":"Services"
        }
    ],
    "sg:phone":"+1 727 531 1234",
    "sg:postcode":"33764",
    "sg:province":"FL",
    "sg:tags":[
        "management",
        "condominium"
    ],
    "wof:name":"The Association Advisor Inc",
    "wof:placetype":"venue"
},
  "geometry": {"coordinates":[-82.75946500000001,27.938707],"type":"Point"}
}