{
  "type": "Feature",
  "properties": {
    "addr:full":"4242 Gulf Shore Blvd N Naples FL 34103",
    "addr:housenumber":"4242",
    "addr:postcode":"34103",
    "addr:street":"Gulf Shore Blvd N",
    "iso:country":"US",
    "sg:address":"4242 Gulf Shore Blvd N",
    "sg:city":"Naples",
    "sg:classifiers":[
        {
            "category":"Shopping",
            "subcategory":"Clothing, Apparel, & Fashions",
            "type":"Retail Goods"
        }
    ],
    "sg:phone":"+1 239 643 5150",
    "sg:postcode":"34103",
    "sg:province":"FL",
    "sg:tags":[
        "woman",
        "accessory"
    ],
    "wof:name":"H T Chittum & Co",
    "wof:placetype":"venue"
},
  "geometry": {"coordinates":[-81.81338599999999,26.190261],"type":"Point"}
}