{
  "type": "Feature",
  "properties": {
    "iso:country":"US",
    "sg:address":"8178 Cloverglen Cir",
    "sg:city":"Orlando",
    "sg:classifiers":[
        {
            "category":"Freight",
            "type":"Transportation"
        }
    ],
    "sg:phone":"+1 917 939 8137",
    "sg:postcode":"32818",
    "sg:province":"FL",
    "sg:tags":[
        "operator",
        "trucking"
    ],
    "wof:name":"Sancho Trucking Inc",
    "wof:placetype":"venue"
},
  "geometry": {"coordinates":[-81.493154,28.5991],"type":"Point"}
}