{
  "type": "Feature",
  "properties": {
    "addr:full":"1200 Forest Oaks Dr Neptune Beach FL 32266",
    "addr:housenumber":"1200",
    "addr:postcode":"32266",
    "addr:street":"Forest Oaks Dr",
    "iso:country":"US",
    "sg:address":"1200 Forest Oaks Dr",
    "sg:city":"Neptune Beach",
    "sg:classifiers":[
        {
            "category":"Professional",
            "subcategory":"Business Services",
            "type":"Services"
        }
    ],
    "sg:phone":"+1 904 241 1462",
    "sg:postcode":"32266",
    "sg:province":"FL",
    "wof:name":"Rozier Sales Inc",
    "wof:placetype":"venue"
},
  "geometry": {"coordinates":[-81.41188699999999,30.316135],"type":"Point"}
}