{
  "type": "Feature",
  "properties": {
    "iso:country":"US",
    "sg:address":"125 1st St SE",
    "sg:city":"Fort Walton Bch",
    "sg:classifiers":[
        {
            "category":"Retail",
            "subcategory":"Laundry & Dry Cleaning",
            "type":"Services"
        }
    ],
    "sg:phone":"+1 850 243 4556",
    "sg:postcode":"32548",
    "sg:province":"FL",
    "sg:tags":[
        "drycleaning",
        "plant",
        "cleaners"
    ],
    "wof:name":"Bangkok Cleaners",
    "wof:placetype":"venue"
},
  "geometry": {"coordinates":[-86.604585,30.405314],"type":"Point"}
}