{
  "type": "Feature",
  "properties": {
    "iso:country":"US",
    "sg:address":"1860 NW 38th Ave",
    "sg:city":"Fort Lauderdale",
    "sg:classifiers":[
        {
            "category":"Organizations",
            "subcategory":"Religious Organization",
            "type":"Services"
        }
    ],
    "sg:phone":"+1 954 733 5677",
    "sg:postcode":"33311",
    "sg:province":"FL",
    "sg:tags":[
        "church"
    ],
    "wof:name":"Road To Life Deliverance Chr",
    "wof:placetype":"venue"
},
  "geometry": {"coordinates":[-80.199735,26.149867],"type":"Point"}
}