{
  "type": "Feature",
  "properties": {
    "iso:country":"US",
    "sg:address":"2788 E Colonial Dr",
    "sg:city":"Orlando",
    "sg:classifiers":[
        {
            "category":"Shopping",
            "subcategory":"Department Store",
            "type":"Retail Goods"
        }
    ],
    "sg:phone":"+1 407 898 5884",
    "sg:postcode":"32803",
    "sg:province":"FL",
    "sg:tags":[
        "shop"
    ],
    "sg:website":"www.pier1.com",
    "wof:name":"Pier 1 Imports",
    "wof:placetype":"venue"
},
  "geometry": {"coordinates":[-81.34984900000001,28.553141],"type":"Point"}
}