{
  "type": "Feature",
  "properties": {
    "addr:full":"3630 Park St Jacksonville FL 32205",
    "addr:housenumber":"3630",
    "addr:postcode":"32205",
    "addr:street":"Park St",
    "iso:country":"US",
    "sg:address":"3630 Park St",
    "sg:city":"Jacksonville",
    "sg:classifiers":[
        {
            "category":"Restaurant",
            "type":"Food & Drink"
        }
    ],
    "sg:menulink":"http://www.allmenus.com/fl/jacksonville/44952-crush-bistro/menu/",
    "sg:phone":"+1 904 381 0909",
    "sg:postcode":"32205",
    "sg:province":"FL",
    "sg:tags":[
        "french"
    ],
    "wof:name":"Crush Bistro",
    "wof:placetype":"venue"
},
  "geometry": {"coordinates":[-81.710021,30.300487],"type":"Point"}
}