{
  "type": "Feature",
  "properties": {
    "addr:full":"815 E Strawbridge Ave Melbourne FL 32901",
    "addr:housenumber":"815",
    "addr:postcode":"32901",
    "addr:street":"E Strawbridge Ave",
    "iso:country":"US",
    "sg:address":"815 E Strawbridge Ave",
    "sg:city":"Melbourne",
    "sg:classifiers":[
        {
            "category":"Food & Beverages",
            "subcategory":"Candy",
            "type":"Retail Goods"
        }
    ],
    "sg:phone":"+1 321 724 0535",
    "sg:postcode":"32901",
    "sg:province":"FL",
    "sg:tags":[
        "product",
        "confectionery"
    ],
    "wof:name":"Original Grimaldi Candies Inc",
    "wof:placetype":"venue"
},
  "geometry": {"coordinates":[-80.60666000000001,28.079301],"type":"Point"}
}