{
  "type": "Feature",
  "properties": {
    "addr:full":"1555 Indian River Blvd Vero Beach FL 32960",
    "addr:housenumber":"1555",
    "addr:postcode":"32960",
    "addr:street":"Indian River Blvd",
    "iso:country":"US",
    "sg:address":"1555 Indian River Blvd",
    "sg:city":"Vero Beach",
    "sg:classifiers":[
        {
            "category":"Building & Trades",
            "subcategory":"Construction",
            "type":"Services"
        }
    ],
    "sg:phone":"+1 772 299 5960",
    "sg:postcode":"32960",
    "sg:province":"FL",
    "sg:tags":[
        "general",
        "contractor"
    ],
    "wof:name":"Hope Co",
    "wof:placetype":"venue"
},
  "geometry": {"coordinates":[-80.37859899999999,27.62889],"type":"Point"}
}