{
  "type": "Feature",
  "properties": {
    "iso:country":"US",
    "sg:address":"1819 Main St",
    "sg:city":"Sarasota",
    "sg:classifiers":[
        {
            "category":"Social Services",
            "subcategory":"Adult Care",
            "type":"Services"
        },
        {
            "category":"Professional",
            "subcategory":"Management & Consulting",
            "type":"Services"
        }
    ],
    "sg:phone":"+1 941 953 9199",
    "sg:postcode":"34236",
    "sg:province":"FL",
    "sg:tags":[
        "juvenile",
        "managed",
        "center",
        "facility",
        "correction",
        "detention",
        "privately"
    ],
    "sg:website":"www.correctionalservices.com",
    "wof:name":"Correctional Services Corp",
    "wof:placetype":"venue"
},
  "geometry": {"coordinates":[-82.53324000000001,27.336538],"type":"Point"}
}