{
  "type": "Feature",
  "properties": {
    "iso:country":"US",
    "sg:address":"1513 S Alafaya Trl",
    "sg:city":"Orlando",
    "sg:classifiers":[
        {
            "category":"Retail",
            "subcategory":"Veterinary Services",
            "type":"Services"
        }
    ],
    "sg:phone":"+1 407 381 9191",
    "sg:postcode":"32828",
    "sg:province":"FL",
    "wof:name":"Eastwood Animal Hospital",
    "wof:placetype":"venue"
},
  "geometry": {"coordinates":[-81.202415,28.528095],"type":"Point"}
}