{
  "type": "Feature",
  "properties": {
    "iso:country":"US",
    "sg:address":"2706 Sunrise Blvd",
    "sg:city":"Fort Pierce",
    "sg:classifiers":[
        {
            "category":"Social Services",
            "subcategory":"Child Care",
            "type":"Services"
        }
    ],
    "sg:phone":"+1 772 465 3151",
    "sg:postcode":"34982",
    "sg:province":"FL",
    "sg:tags":[
        "center",
        "preschool"
    ],
    "wof:name":"Sunrise Country Pre School",
    "wof:placetype":"venue"
},
  "geometry": {"coordinates":[-80.33753900000001,27.42001],"type":"Point"}
}