{
  "type": "Feature",
  "properties": {
    "iso:country":"US",
    "sg:address":"2501 S Cedar Ln",
    "sg:city":"Panama City",
    "sg:classifiers":[
        {
            "category":"Building & Trades",
            "subcategory":"Construction",
            "type":"Services"
        }
    ],
    "sg:phone":"+1 850 872 1641",
    "sg:postcode":"32405",
    "sg:province":"FL",
    "sg:tags":[
        "maker",
        "cabinet"
    ],
    "wof:name":"Cab-Tech",
    "wof:placetype":"venue"
},
  "geometry": {"coordinates":[-85.624877,30.18058],"type":"Point"}
}