{
  "type": "Feature",
  "properties": {
    "iso:country":"US",
    "sg:address":"2504 W Gardner Ct",
    "sg:city":"Tampa",
    "sg:classifiers":[
        {
            "category":"Structure",
            "subcategory":"Office Building",
            "type":"Public Place"
        }
    ],
    "sg:phone":"+1 813 220 1544",
    "sg:postcode":"33611",
    "sg:province":"FL",
    "sg:tags":[
        "park"
    ],
    "wof:name":"Bdi Properties U.S",
    "wof:placetype":"venue"
},
  "geometry": {"coordinates":[-82.48460799999999,27.8799],"type":"Point"}
}