{
  "type": "Feature",
  "properties": {
    "addr:full":"2899 Belkton St Deltona FL 32738",
    "addr:housenumber":"2899",
    "addr:postcode":"32738",
    "addr:street":"Belkton St",
    "iso:country":"US",
    "sg:address":"2899 Belkton St",
    "sg:city":"Deltona",
    "sg:classifiers":[
        {
            "category":"Building & Trades",
            "subcategory":"Construction",
            "type":"Services"
        }
    ],
    "sg:phone":"+1 386 789 3722",
    "sg:postcode":"32738",
    "sg:province":"FL",
    "sg:tags":[
        "concrete",
        "pumping"
    ],
    "wof:name":"Bellefleur Concrete Pumping",
    "wof:placetype":"venue"
},
  "geometry": {"coordinates":[-81.185963,28.949707],"type":"Point"}
}