{
  "type": "Feature",
  "properties": {
    "iso:country":"US",
    "sg:address":"7512 S Leewynn Dr",
    "sg:city":"Sarasota",
    "sg:classifiers":[
        {
            "category":"Personal",
            "type":"Services"
        }
    ],
    "sg:phone":"+1 941 378 8669",
    "sg:postcode":"34240",
    "sg:province":"FL",
    "wof:name":"All Eyes Home Management Inc",
    "wof:placetype":"venue"
},
  "geometry": {"coordinates":[-82.417737,27.31323],"type":"Point"}
}