{
  "type": "Feature",
  "properties": {
    "iso:country":"US",
    "sg:address":"4361 SE Commerce Ave",
    "sg:city":"Stuart",
    "sg:classifiers":[
        {
            "category":"Manufacturing",
            "subcategory":"Watercraft",
            "type":"Manufacturing & Wholesale Goods"
        }
    ],
    "sg:phone":"+1 772 283 7189",
    "sg:postcode":"34997",
    "sg:province":"FL",
    "wof:name":"Willis Marine Inc",
    "wof:placetype":"venue"
},
  "geometry": {"coordinates":[-80.20896500000001,27.152827],"type":"Point"}
}