{
  "type": "Feature",
  "properties": {
    "addr:full":"670 Bald Eagle Dr Marco Island FL 34145",
    "addr:housenumber":"670",
    "addr:postcode":"34145",
    "addr:street":"Bald Eagle Dr",
    "iso:country":"US",
    "sg:address":"670 Bald Eagle Dr",
    "sg:city":"Marco Island",
    "sg:classifiers":[
        {
            "category":"Bakery",
            "type":"Food & Drink"
        },
        {
            "category":"Coffee & Tea",
            "type":"Food & Drink"
        },
        {
            "category":"Bagels",
            "type":"Food & Drink"
        },
        {
            "category":"Donuts",
            "type":"Food & Drink"
        }
    ],
    "sg:menulink":"http://www.allmenus.com/fl/marco-island/138024-dunkin-donuts/menu/",
    "sg:phone":"+1 941 417 8515",
    "sg:postcode":"34145",
    "sg:province":"FL",
    "sg:tags":[
        "american",
        "pastry"
    ],
    "wof:name":"Dunkin' Donuts",
    "wof:placetype":"venue"
},
  "geometry": {"coordinates":[-81.724577,25.95394],"type":"Point"}
}