{
  "type": "Feature",
  "properties": {
    "addr:full":"350 85th St Miami Beach FL 33141",
    "addr:housenumber":"350",
    "addr:postcode":"33141",
    "addr:street":"85Th St",
    "iso:country":"US",
    "sg:address":"350 85th St",
    "sg:city":"Miami Beach",
    "sg:classifiers":[
        {
            "category":"Real Estate",
            "subcategory":"Real Estate Operator",
            "type":"Services"
        }
    ],
    "sg:phone":"+1 305 868 1381",
    "sg:postcode":"33141",
    "sg:province":"FL",
    "sg:tags":[
        "apartment"
    ],
    "wof:name":"Terry Beach Apartments",
    "wof:placetype":"venue"
},
  "geometry": {"coordinates":[-80.123497,25.870001],"type":"Point"}
}