{
  "type": "Feature",
  "properties": {
    "addr:full":"4915 Boy Scout Ranch Rd Bartow FL 33830",
    "addr:housenumber":"4915",
    "addr:postcode":"33830",
    "addr:street":"Boy Scout Ranch Rd",
    "iso:country":"US",
    "sg:address":"4915 Boy Scout Ranch Rd",
    "sg:city":"Bartow",
    "sg:classifiers":[
        {
            "category":"Real Estate",
            "subcategory":"Real Estate Operator",
            "type":"Services"
        }
    ],
    "sg:phone":"+1 863 646 0846",
    "sg:postcode":"33830",
    "sg:province":"FL",
    "sg:tags":[
        "building",
        "nonresidential"
    ],
    "wof:name":"Shopping Lively",
    "wof:placetype":"venue"
},
  "geometry": {"coordinates":[-81.8612,27.953245],"type":"Point"}
}