{
  "type": "Feature",
  "properties": {
    "iso:country":"US",
    "sg:address":"5831 15th St N",
    "sg:city":"Saint Petersburg",
    "sg:classifiers":[
        {
            "category":"Shopping",
            "subcategory":"Department Store",
            "type":"Retail Goods"
        }
    ],
    "sg:phone":"+1 727 521 4980",
    "sg:postcode":"33703",
    "sg:province":"FL",
    "wof:name":"Royal Dollar Inc",
    "wof:placetype":"venue"
},
  "geometry": {"coordinates":[-82.653295,27.827349],"type":"Point"}
}