{
  "type": "Feature",
  "properties": {
    "iso:country":"US",
    "sg:address":"1775 Blount Rd",
    "sg:city":"Pompano Beach",
    "sg:classifiers":[
        {
            "category":"Manufacturing",
            "subcategory":"Tools & Machinery",
            "type":"Manufacturing & Wholesale Goods"
        }
    ],
    "sg:phone":"+1 954 984 9849",
    "sg:postcode":"33069",
    "sg:province":"FL",
    "sg:tags":[
        "water"
    ],
    "wof:name":"Advanced Aquatronics",
    "wof:placetype":"venue"
},
  "geometry": {"coordinates":[-80.16389700000001,26.25136],"type":"Point"}
}