{
  "type": "Feature",
  "properties": {
    "addr:full":"15900 SW 197th Ave Miami FL 33187",
    "addr:housenumber":"15900",
    "addr:postcode":"33187",
    "addr:street":"Sw 197Th Ave",
    "iso:country":"US",
    "sg:address":"15900 SW 197th Ave",
    "sg:city":"Miami",
    "sg:classifiers":[
        {
            "category":"Professional",
            "subcategory":"Management & Consulting",
            "type":"Services"
        }
    ],
    "sg:phone":"+1 305 251 1798",
    "sg:postcode":"33187",
    "sg:province":"FL",
    "sg:tags":[
        "citrus",
        "grove"
    ],
    "wof:name":"Paul Delgado",
    "wof:placetype":"venue"
},
  "geometry": {"coordinates":[-80.511324,25.616818],"type":"Point"}
}