{
  "type": "Feature",
  "properties": {
    "addr:full":"4259 Cardinal Blvd Daytona Beach FL 32127",
    "addr:housenumber":"4259",
    "addr:postcode":"32127",
    "addr:street":"Cardinal Blvd",
    "iso:country":"US",
    "sg:address":"4259 Cardinal Blvd",
    "sg:city":"Daytona Beach",
    "sg:classifiers":[
        {
            "category":"Autos & Motor Vehicles",
            "subcategory":"Boat Sales",
            "type":"Retail Goods"
        }
    ],
    "sg:phone":"+1 386 767 4281",
    "sg:postcode":"32127",
    "sg:province":"FL",
    "wof:name":"Lucenti Marine Sales Inc",
    "wof:placetype":"venue"
},
  "geometry": {"coordinates":[-80.95428,29.122824],"type":"Point"}
}