{
  "type": "Feature",
  "properties": {
    "iso:country":"US",
    "sg:address":"672 Richmond St",
    "sg:city":"Dunedin",
    "sg:classifiers":[
        {
            "category":"Building & Trades",
            "subcategory":"Electrical",
            "type":"Services"
        }
    ],
    "sg:phone":"+1 727 734 7822",
    "sg:postcode":"34698",
    "sg:province":"FL",
    "sg:tags":[
        "electrical",
        "contractor"
    ],
    "wof:name":"A Livewire Co",
    "wof:placetype":"venue"
},
  "geometry": {"coordinates":[-82.78278899999999,27.998696],"type":"Point"}
}