{
  "type": "Feature",
  "properties": {
    "iso:country":"US",
    "sg:address":"7900 Coral Way",
    "sg:city":"Miami",
    "sg:classifiers":[
        {
            "category":"Place Of Worship",
            "subcategory":"Church",
            "type":"Public Place"
        },
        {
            "category":"Place Of Worship",
            "type":"Public Place"
        }
    ],
    "sg:phone":"+1 305 264 4377",
    "sg:postcode":"33155",
    "sg:province":"FL",
    "sg:tags":[
        "churches-methodist"
    ],
    "wof:name":"Coral Way United Methodist Church",
    "wof:placetype":"venue"
},
  "geometry": {"coordinates":[-80.323639,25.747957],"type":"Point"}
}