{
  "type": "Feature",
  "properties": {
    "iso:country":"US",
    "sg:address":"1060 W 49th St",
    "sg:city":"Hialeah",
    "sg:classifiers":[
        {
            "category":"Education",
            "subcategory":"Vocational School",
            "type":"Public Place"
        }
    ],
    "sg:phone":"+1 305 362 9003",
    "sg:postcode":"33012",
    "sg:province":"FL",
    "sg:tags":[
        "cosmetology"
    ],
    "sg:website":"www.beautyschoolsofamerica.com",
    "wof:name":"Beauty Schools of America",
    "wof:placetype":"venue"
},
  "geometry": {"coordinates":[-80.304604,25.866699],"type":"Point"}
}