{
  "type": "Feature",
  "properties": {
    "iso:country":"US",
    "sg:address":"1019 N Woodland Blvd",
    "sg:city":"De Land",
    "sg:classifiers":[
        {
            "category":"Shopping",
            "type":"Retail Goods"
        }
    ],
    "sg:phone":"+1 386 734 1319",
    "sg:postcode":"32720",
    "sg:province":"FL",
    "sg:tags":[
        "merchandise"
    ],
    "wof:name":"Actel",
    "wof:placetype":"venue"
},
  "geometry": {"coordinates":[-81.30392399999999,29.045517],"type":"Point"}
}