{
  "type": "Feature",
  "properties": {
    "addr:full":"6465 Rubia Cir Apollo Beach FL 33572",
    "addr:postcode":"6465;33572",
    "addr:street":"Rubia Cir",
    "iso:country":"US",
    "sg:address":"6465 Rubia Cir",
    "sg:city":"Apollo Beach",
    "sg:classifiers":[
        {
            "category":"Wholesale",
            "subcategory":"Construction Materials",
            "type":"Manufacturing & Wholesale Goods"
        },
        {
            "category":"Manufacturing",
            "subcategory":"Electronics",
            "type":"Manufacturing & Wholesale Goods"
        }
    ],
    "sg:phone":"+1 813 641 2900",
    "sg:postcode":"33572",
    "sg:province":"FL",
    "sg:tags":[
        "building",
        "for",
        "rep",
        "modular",
        "trailer",
        "manufacturer"
    ],
    "wof:name":"A To Z Modular Buildings Inc",
    "wof:placetype":"venue"
},
  "geometry": {"coordinates":[-82.42756799999999,27.78053],"type":"Point"}
}