{
  "type": "Feature",
  "properties": {
    "iso:country":"US",
    "sg:address":"3725 98th Ter",
    "sg:city":"Pinellas Park",
    "sg:classifiers":[
        {
            "category":"Shopping",
            "type":"Retail Goods"
        }
    ],
    "sg:phone":"+1 727 573 2253",
    "sg:postcode":"33782",
    "sg:province":"FL",
    "sg:tags":[
        "merchandise"
    ],
    "wof:name":"Cakes To You By Shirley",
    "wof:placetype":"venue"
},
  "geometry": {"coordinates":[-82.685089,27.861741],"type":"Point"}
}