{
  "type": "Feature",
  "properties": {
    "iso:country":"US",
    "sg:address":"622 Canal St",
    "sg:city":"New Smyrna Beach",
    "sg:classifiers":[
        {
            "category":"Shopping",
            "subcategory":"Gifts & Souvenirs",
            "type":"Retail Goods"
        }
    ],
    "sg:phone":"+1 386 423 6623",
    "sg:postcode":"32168",
    "sg:province":"FL",
    "sg:tags":[
        "party",
        "supply"
    ],
    "wof:name":"Let's Party",
    "wof:placetype":"venue"
},
  "geometry": {"coordinates":[-80.926453,29.023496],"type":"Point"}
}