{
  "type": "Feature",
  "properties": {
    "addr:full":"342 NE 3rd Ave Delray Beach FL 33444",
    "addr:housenumber":"342",
    "addr:postcode":"33444",
    "addr:street":"Ne 3Rd Ave",
    "iso:country":"US",
    "sg:address":"342 NE 3rd Ave",
    "sg:city":"Delray Beach",
    "sg:classifiers":[
        {
            "category":"Building & Trades",
            "subcategory":"Pest Control",
            "type":"Services"
        }
    ],
    "sg:phone":"+1 561 272 9020",
    "sg:postcode":"33444",
    "sg:province":"FL",
    "wof:name":"Cen-Trust Pest Control",
    "wof:placetype":"venue"
},
  "geometry": {"coordinates":[-80.070294,26.468211],"type":"Point"}
}