{
  "type": "Feature",
  "properties": {
    "addr:full":"2559 SW Hwy 484 Ocala FL 34473",
    "addr:housenumber":"2559",
    "addr:postcode":"34473",
    "addr:street":"Sw Hwy 484",
    "iso:country":"US",
    "sg:address":"2559 SW Hwy 484",
    "sg:city":"Ocala",
    "sg:classifiers":[
        {
            "category":"Travel",
            "subcategory":"Campground",
            "type":"Entertainment"
        }
    ],
    "sg:phone":"+1 352 307 1100",
    "sg:postcode":"34473",
    "sg:province":"FL",
    "sg:tags":[
        "trailer"
    ],
    "wof:name":"Ocala Ranch Rv Park",
    "wof:placetype":"venue"
},
  "geometry": {"coordinates":[-82.15820600000001,29.025575],"type":"Point"}
}