{
  "type": "Feature",
  "properties": {
    "iso:country":"US",
    "sg:address":"1401 Buena Vista Blvd",
    "sg:city":"Panama City",
    "sg:classifiers":[
        {
            "category":"Building & Trades",
            "subcategory":"Construction",
            "type":"Services"
        }
    ],
    "sg:phone":"+1 850 784 0184",
    "sg:postcode":"32401",
    "sg:province":"FL",
    "sg:tags":[
        "floor",
        "laying",
        "contractor"
    ],
    "wof:name":"Houser Floor Coverg",
    "wof:placetype":"venue"
},
  "geometry": {"coordinates":[-85.67959399999999,30.174588],"type":"Point"}
}