{
  "type": "Feature",
  "properties": {
    "iso:country":"US",
    "sg:address":"5864 NW 125th Ter",
    "sg:city":"Pompano Beach",
    "sg:classifiers":[
        {
            "category":"Banks & Credit Unions",
            "subcategory":"Investment Brokerage",
            "type":"Services"
        }
    ],
    "sg:phone":"+1 954 340 7049",
    "sg:postcode":"33076",
    "sg:province":"FL",
    "sg:tags":[
        "advisory"
    ],
    "wof:name":"Ih Financial Services Inc",
    "wof:placetype":"venue"
},
  "geometry": {"coordinates":[-80.29414300000001,26.304484],"type":"Point"}
}