{
  "type": "Feature",
  "properties": {
    "addr:full":"10069 N Florida Ave Tampa FL 33612",
    "addr:housenumber":"10069",
    "addr:postcode":"33612",
    "addr:street":"N Florida Ave",
    "iso:country":"US",
    "sg:address":"10069 N Florida Ave",
    "sg:city":"Tampa",
    "sg:classifiers":[
        {
            "category":"Utilities",
            "subcategory":"Telephone",
            "type":"Services"
        }
    ],
    "sg:phone":"+1 813 885 3779",
    "sg:postcode":"33612",
    "sg:province":"FL",
    "sg:tags":[
        "communications"
    ],
    "wof:name":"Fullsail Group",
    "wof:placetype":"venue"
},
  "geometry": {"coordinates":[-82.459357,28.042803],"type":"Point"}
}