{
  "type": "Feature",
  "properties": {
    "iso:country":"US",
    "sg:address":"456 University Blvd N",
    "sg:city":"Jacksonville",
    "sg:classifiers":[
        {
            "category":"Health Services",
            "subcategory":"Dentist",
            "type":"Services"
        }
    ],
    "sg:phone":"+1 904 721 1400",
    "sg:postcode":"32211",
    "sg:province":"FL",
    "sg:website":"http://www.drverrette.com",
    "wof:name":"Verrette, Richard M DDS MAGD PA",
    "wof:placetype":"venue"
},
  "geometry": {"coordinates":[-81.605492,30.324249],"type":"Point"}
}