{
  "type": "Feature",
  "properties": {
    "iso:country":"US",
    "sg:address":"401 5th Ave S",
    "sg:city":"Naples",
    "sg:classifiers":[
        {
            "category":"Banks & Credit Unions",
            "subcategory":"Investment Brokerage",
            "type":"Services"
        }
    ],
    "sg:phone":"+1 239 263 3500",
    "sg:postcode":"34102",
    "sg:province":"FL",
    "sg:tags":[
        "security"
    ],
    "wof:name":"Quick & Reilly 110",
    "wof:placetype":"venue"
},
  "geometry": {"coordinates":[-81.801278,26.14113],"type":"Point"}
}