{
  "type": "Feature",
  "properties": {
    "iso:country":"US",
    "sg:address":"2620 SW 17th St",
    "sg:city":"Ocala",
    "sg:classifiers":[
        {
            "category":"Wholesale",
            "subcategory":"Machinery & Supplies",
            "type":"Manufacturing & Wholesale Goods"
        }
    ],
    "sg:phone":"+1 352 732 8084",
    "sg:postcode":"34474",
    "sg:province":"FL",
    "sg:tags":[
        "equipment",
        "industrial"
    ],
    "wof:name":"Grainger Inc",
    "wof:placetype":"venue"
},
  "geometry": {"coordinates":[-82.15945600000001,29.17315],"type":"Point"}
}