{
  "type": "Feature",
  "properties": {
    "iso:country":"US",
    "sg:address":"2727 Parrot St",
    "sg:city":"North Port",
    "sg:classifiers":[
        {
            "category":"Freight",
            "type":"Transportation"
        }
    ],
    "sg:phone":"+1 941 628 0653",
    "sg:postcode":"34286",
    "sg:province":"FL",
    "sg:tags":[
        "mover",
        "moving"
    ],
    "wof:name":"First Call Movers",
    "wof:placetype":"venue"
},
  "geometry": {"coordinates":[-82.20613400000001,27.083759],"type":"Point"}
}