{
  "type": "Feature",
  "properties": {
    "iso:country":"US",
    "sg:address":"235 Oak St",
    "sg:city":"Osprey",
    "sg:classifiers":[
        {
            "category":"Place Of Worship",
            "subcategory":"Church",
            "type":"Public Place"
        },
        {
            "category":"Place Of Worship",
            "type":"Public Place"
        }
    ],
    "sg:phone":"+1 941 966 2755",
    "sg:postcode":"34229",
    "sg:province":"FL",
    "sg:tags":[
        "churches-interdenominational",
        "churches-various",
        "denomination"
    ],
    "wof:name":"First Church Of God Of Osprey",
    "wof:placetype":"venue"
},
  "geometry": {"coordinates":[-82.490284,27.19998],"type":"Point"}
}