{
  "type": "Feature",
  "properties": {
    "iso:country":"US",
    "sg:address":"4554 Middlebrook Rd",
    "sg:city":"Orlando",
    "sg:classifiers":[
        {
            "category":"Professional",
            "subcategory":"Management & Consulting",
            "type":"Services"
        }
    ],
    "sg:phone":"+1 407 578 7242",
    "sg:postcode":"32811",
    "sg:province":"FL",
    "sg:tags":[
        "construction"
    ],
    "wof:name":"Paulon Construction Mgmt Corp",
    "wof:placetype":"venue"
},
  "geometry": {"coordinates":[-81.45315600000001,28.497031],"type":"Point"}
}