{
  "type": "Feature",
  "properties": {
    "addr:full":"2010 SW 6th Ave Okeechobee FL 34974",
    "addr:housenumber":"2010",
    "addr:postcode":"34974",
    "addr:street":"Sw 6Th Ave",
    "iso:country":"US",
    "sg:address":"2010 SW 6th Ave",
    "sg:city":"Okeechobee",
    "sg:classifiers":[
        {
            "category":"Building & Trades",
            "subcategory":"Electrical",
            "type":"Services"
        }
    ],
    "sg:phone":"+1 863 763 2097",
    "sg:postcode":"34974",
    "sg:province":"FL",
    "sg:tags":[
        "work",
        "electrical",
        "contractor"
    ],
    "wof:name":"Croslyn Electric Inc",
    "wof:placetype":"venue"
},
  "geometry": {"coordinates":[-80.83571600000001,27.225063],"type":"Point"}
}