{
  "type": "Feature",
  "properties": {
    "addr:full":"4511 NW 25th Pl Fort Lauderdale FL 33313",
    "addr:housenumber":"4511",
    "addr:postcode":"33313",
    "addr:street":"Nw 25Th Pl",
    "iso:country":"US",
    "sg:address":"4511 NW 25th Pl",
    "sg:city":"Fort Lauderdale",
    "sg:classifiers":[
        {
            "category":"Manufacturing",
            "subcategory":"Watercraft",
            "type":"Manufacturing & Wholesale Goods"
        }
    ],
    "sg:phone":"+1 954 486 2749",
    "sg:postcode":"33313",
    "sg:province":"FL",
    "wof:name":"Jolly Busher Detailing Service",
    "wof:placetype":"venue"
},
  "geometry": {"coordinates":[-80.211698,26.157958],"type":"Point"}
}