{
  "type": "Feature",
  "properties": {
    "iso:country":"US",
    "sg:address":"5440 Lyons Rd",
    "sg:city":"Pompano Beach",
    "sg:classifiers":[
        {
            "category":"Professional",
            "subcategory":"Computer Services",
            "type":"Services"
        }
    ],
    "sg:phone":"+1 954 421 3704",
    "sg:postcode":"33073",
    "sg:province":"FL",
    "sg:tags":[
        "related"
    ],
    "wof:name":"Gch Consulting Inc",
    "wof:placetype":"venue"
},
  "geometry": {"coordinates":[-80.186493,26.296565],"type":"Point"}
}