{
  "type": "Feature",
  "properties": {
    "addr:full":"3601 SW 2 Ave Gainesville FL 32607",
    "addr:housenumber":"3601",
    "addr:postcode":"32607",
    "addr:street":"Sw 2 Ave",
    "iso:country":"US",
    "sg:address":"3601 SW 2 Ave",
    "sg:city":"Gainesville",
    "sg:classifiers":[
        {
            "category":"Health Services",
            "subcategory":"Clinic",
            "type":"Services"
        }
    ],
    "sg:phone":"+1 352 378 0333",
    "sg:postcode":"32607",
    "sg:province":"FL",
    "sg:tags":[
        "home"
    ],
    "wof:name":"Interim Healthcare",
    "wof:placetype":"venue"
},
  "geometry": {"coordinates":[-82.376909,29.651004],"type":"Point"}
}