{
  "type": "Feature",
  "properties": {
    "addr:full":"6626 Collins Ave Miami Beach FL 33141",
    "addr:housenumber":"6626",
    "addr:postcode":"33141",
    "addr:street":"Collins Ave",
    "iso:country":"US",
    "sg:address":"6626 Collins Ave",
    "sg:city":"Miami Beach",
    "sg:classifiers":[
        {
            "category":"Arena",
            "subcategory":"Sports Club",
            "type":"Entertainment"
        }
    ],
    "sg:phone":"+1 305 866 5900",
    "sg:postcode":"33141",
    "sg:province":"FL",
    "sg:tags":[
        "martial art"
    ],
    "wof:name":"Academy Capoeira Abolicion",
    "wof:placetype":"venue"
},
  "geometry": {"coordinates":[-80.12020099999999,25.85],"type":"Point"}
}