{
  "type": "Feature",
  "properties": {
    "iso:country":"US",
    "sg:address":"2110 S Patrick Dr",
    "sg:city":"Satellite Beach",
    "sg:classifiers":[
        {
            "category":"Professional",
            "type":"Services"
        }
    ],
    "sg:phone":"+1 321 984 9635",
    "sg:postcode":"32937",
    "sg:province":"FL",
    "wof:name":"Thomas R Huff",
    "wof:placetype":"venue"
},
  "geometry": {"coordinates":[-80.598568,28.141921],"type":"Point"}
}