{
  "type": "Feature",
  "properties": {
    "iso:country":"US",
    "sg:address":"10794 SW 24th St",
    "sg:city":"Miami",
    "sg:classifiers":[
        {
            "category":"Shopping",
            "subcategory":"Comic Books",
            "type":"Retail Goods"
        }
    ],
    "sg:phone":"+1 305 223 2770",
    "sg:postcode":"33165",
    "sg:province":"FL",
    "wof:name":"Anime & Comics",
    "wof:placetype":"venue"
},
  "geometry": {"coordinates":[-80.36964,25.746571],"type":"Point"}
}