{
  "type": "Feature",
  "properties": {
    "iso:country":"US",
    "sg:address":"103 E 23rd St",
    "sg:city":"Panama City",
    "sg:classifiers":[
        {
            "category":"Autos & Motor Vehicles",
            "subcategory":"Auto Supplies",
            "type":"Retail Goods"
        }
    ],
    "sg:phone":"+1 850 784 6708",
    "sg:postcode":"32405",
    "sg:province":"FL",
    "sg:tags":[
        "automobile",
        "parts"
    ],
    "sg:website":"www.advanceautoparts.com",
    "wof:name":"Advance Auto Parts Inc",
    "wof:placetype":"venue"
},
  "geometry": {"coordinates":[-85.654188,30.189645],"type":"Point"}
}