{
  "type": "Feature",
  "properties": {
    "addr:full":"1626 Williamsburg Sq Lakeland FL 33803",
    "addr:housenumber":"1626",
    "addr:postcode":"33803",
    "addr:street":"Williamsburg Sq",
    "iso:country":"US",
    "sg:address":"1626 Williamsburg Sq",
    "sg:city":"Lakeland",
    "sg:classifiers":[
        {
            "category":"Real Estate",
            "subcategory":"Real Estate Agent",
            "type":"Services"
        }
    ],
    "sg:phone":"+1 863 646 6637",
    "sg:postcode":"33803",
    "sg:province":"FL",
    "wof:name":"Chosen Realty",
    "wof:placetype":"venue"
},
  "geometry": {"coordinates":[-81.933094,28.005065],"type":"Point"}
}