{
  "type": "Feature",
  "properties": {
    "addr:full":"6518 Steeplechase Dr Tampa FL 33625",
    "addr:housenumber":"6518",
    "addr:postcode":"33625",
    "addr:street":"Steeplechase Dr",
    "iso:country":"US",
    "sg:address":"6518 Steeplechase Dr",
    "sg:city":"Tampa",
    "sg:classifiers":[
        {
            "category":"Building & Trades",
            "subcategory":"Construction",
            "type":"Services"
        }
    ],
    "sg:phone":"+1 813 760 1802",
    "sg:postcode":"33625",
    "sg:province":"FL",
    "sg:tags":[
        "altering",
        "concrete",
        "remodeling",
        "contractor"
    ],
    "wof:name":"Bay Southern Builders, Inc.",
    "wof:placetype":"venue"
},
  "geometry": {"coordinates":[-82.564483,28.093309],"type":"Point"}
}