{
  "type": "Feature",
  "properties": {
    "iso:country":"US",
    "sg:address":"6107 Anno Ave",
    "sg:city":"Orlando",
    "sg:classifiers":[
        {
            "category":"Professional",
            "subcategory":"Business Services",
            "type":"Services"
        }
    ],
    "sg:phone":"+1 407 888 8002",
    "sg:postcode":"32809",
    "sg:province":"FL",
    "sg:tags":[
        "convention"
    ],
    "sg:website":"www.csandl.com",
    "wof:name":"Canavan Scenic & Light Inc",
    "wof:placetype":"venue"
},
  "geometry": {"coordinates":[-81.371863,28.470135],"type":"Point"}
}