{
  "type": "Feature",
  "properties": {
    "addr:full":"1801 Lee Rd Ste 320 Winter Park FL 32789",
    "addr:housenumber":"1801",
    "addr:postcode":"32789",
    "addr:street":"Lee Rd Ste 320",
    "iso:country":"US",
    "sg:address":"1801 Lee Rd Ste 320",
    "sg:city":"Winter Park",
    "sg:classifiers":[
        {
            "category":"Professional",
            "subcategory":"Lawyer & Legal Services",
            "type":"Services"
        }
    ],
    "sg:phone":"+1 407 644 9670",
    "sg:postcode":"32789",
    "sg:province":"FL",
    "wof:name":"Littman Adam Ross PA",
    "wof:placetype":"venue"
},
  "geometry": {"coordinates":[-81.372902,28.606001],"type":"Point"}
}