{
  "type": "Feature",
  "properties": {
    "iso:country":"US",
    "sg:address":"8701 World Center Dr",
    "sg:city":"Orlando",
    "sg:classifiers":[
        {
            "category":"Travel",
            "subcategory":"Hotels & Motels",
            "type":"Entertainment"
        }
    ],
    "sg:phone":"+1 407 239 4200",
    "sg:postcode":"32821",
    "sg:province":"FL",
    "sg:website":"http://ad.doubleclick.net/clk;227431036;51131029;p?http://www.marriott.com/hotels/travel/MCOWC",
    "wof:name":"Orlando World Center",
    "wof:placetype":"venue"
},
  "geometry": {"coordinates":[-81.508568,28.3599],"type":"Point"}
}