{
  "type": "Feature",
  "properties": {
    "addr:full":"1102 S Florida Ave Lakeland FL 33803",
    "addr:housenumber":"1102",
    "addr:postcode":"33803",
    "addr:street":"S Florida Ave",
    "iso:country":"US",
    "sg:address":"1102 S Florida Ave",
    "sg:city":"Lakeland",
    "sg:classifiers":[
        {
            "category":"Professional",
            "subcategory":"Accounting & Tax Preparation",
            "type":"Services"
        },
        {
            "category":"Professional",
            "subcategory":"Lawyer & Legal Services",
            "type":"Services"
        }
    ],
    "sg:phone":"+1 800 896 5536",
    "sg:postcode":"33803",
    "sg:province":"FL",
    "sg:tags":[
        "attorney",
        "return",
        "representative",
        "taxes-consultants"
    ],
    "sg:website":"http://www.jkharris.com/?ml_source=yellowpages",
    "wof:name":"JK Harris & Company",
    "wof:placetype":"venue"
},
  "geometry": {"coordinates":[-81.957077,28.028558],"type":"Point"}
}