{
  "type": "Feature",
  "properties": {
    "addr:full":"7558 Southland Blvd Orlando FL 32809",
    "addr:housenumber":"7558",
    "addr:postcode":"32809",
    "addr:street":"Southland Blvd",
    "iso:country":"US",
    "sg:address":"7558 Southland Blvd",
    "sg:city":"Orlando",
    "sg:classifiers":[
        {
            "category":"Professional",
            "subcategory":"Research",
            "type":"Services"
        }
    ],
    "sg:phone":"+1 407 926 1900",
    "sg:postcode":"32809",
    "sg:province":"FL",
    "sg:tags":[
        "organization",
        "noncommercial"
    ],
    "wof:name":"Cyterra Corporation",
    "wof:placetype":"venue"
},
  "geometry": {"coordinates":[-81.40662,28.454418],"type":"Point"}
}