{
  "type": "Feature",
  "properties": {
    "iso:country":"US",
    "sg:address":"1230 N Federal Hwy",
    "sg:city":"Pompano Beach",
    "sg:classifiers":[
        {
            "category":"Building & Trades",
            "subcategory":"Plumbing",
            "type":"Services"
        }
    ],
    "sg:phone":"+1 954 941 3747",
    "sg:postcode":"33062",
    "sg:province":"FL",
    "sg:tags":[
        "plumbing",
        "contractor"
    ],
    "wof:name":"Tri-County Plumbing Svc",
    "wof:placetype":"venue"
},
  "geometry": {"coordinates":[-80.101495,26.246611],"type":"Point"}
}