{
  "type": "Feature",
  "properties": {
    "addr:full":"10501 NW 3rd St Fort Lauderdale FL 33324",
    "addr:housenumber":"10501",
    "addr:postcode":"33324",
    "addr:street":"Nw 3Rd St",
    "iso:country":"US",
    "sg:address":"10501 NW 3rd St",
    "sg:city":"Fort Lauderdale",
    "sg:classifiers":[
        {
            "category":"Shopping",
            "subcategory":"Computers & Home Electronics",
            "type":"Retail Goods"
        }
    ],
    "sg:phone":"+1 954 530 3553",
    "sg:postcode":"33324",
    "sg:province":"FL",
    "wof:name":"Microchip Data Systems",
    "wof:placetype":"venue"
},
  "geometry": {"coordinates":[-80.28929100000001,26.123632],"type":"Point"}
}