{
  "type": "Feature",
  "properties": {
    "iso:country":"US",
    "sg:address":"500 SW 93rd Pl",
    "sg:city":"Miami",
    "sg:classifiers":[
        {
            "category":"Building & Trades",
            "subcategory":"Construction",
            "type":"Services"
        }
    ],
    "sg:phone":"+1 305 220 0541",
    "sg:postcode":"33174",
    "sg:province":"FL",
    "sg:tags":[
        "contractor"
    ],
    "wof:name":"EMD Paint & Texture Corp",
    "wof:placetype":"venue"
},
  "geometry": {"coordinates":[-80.34810899999999,25.764813],"type":"Point"}
}