{
  "type": "Feature",
  "properties": {
    "iso:country":"US",
    "sg:address":"18852 Dixie Hwy",
    "sg:city":"Miami",
    "sg:classifiers":[
        {
            "category":"Insurance",
            "subcategory":"Insurance Agent",
            "type":"Services"
        }
    ],
    "sg:phone":"+1 305 225 0225",
    "sg:postcode":"33157",
    "sg:province":"FL",
    "wof:name":"Florida No-Fault Insurance",
    "wof:placetype":"venue"
},
  "geometry": {"coordinates":[-80.35874200000001,25.590168],"type":"Point"}
}