{
  "type": "Feature",
  "properties": {
    "addr:full":"3328 NE 11th Ave Fort Lauderdale FL 33334",
    "addr:housenumber":"3328",
    "addr:postcode":"33334",
    "addr:street":"Ne 11Th Ave",
    "iso:country":"US",
    "sg:address":"3328 NE 11th Ave",
    "sg:city":"Fort Lauderdale",
    "sg:classifiers":[
        {
            "category":"Building & Trades",
            "subcategory":"Construction",
            "type":"Services"
        }
    ],
    "sg:phone":"+1 954 561 4900",
    "sg:postcode":"33334",
    "sg:province":"FL",
    "sg:tags":[
        "house"
    ],
    "wof:name":"First Southern Constructi",
    "wof:placetype":"venue"
},
  "geometry": {"coordinates":[-80.13230900000001,26.169291],"type":"Point"}
}