{
  "type": "Feature",
  "properties": {
    "iso:country":"US",
    "sg:address":"17720 NW 73rd Ave 105-2",
    "sg:city":"Hialeah",
    "sg:classifiers":[
        {
            "category":"Structure",
            "subcategory":"Warehouse",
            "type":"Public Place"
        }
    ],
    "sg:phone":"+1 305 951 2360",
    "sg:postcode":"33015",
    "sg:province":"FL",
    "sg:tags":[
        "warehouses-merchandise",
        "warehouses-public-commercial"
    ],
    "wof:name":"E.M.C.B. Inc",
    "wof:placetype":"venue"
},
  "geometry": {"coordinates":[-80.320351,25.93836],"type":"Point"}
}