{
  "type": "Feature",
  "properties": {
    "iso:country":"US",
    "sg:address":"9550 Parksouth Ct",
    "sg:city":"Orlando",
    "sg:classifiers":[
        {
            "category":"Professional",
            "subcategory":"Management & Consulting",
            "type":"Services"
        }
    ],
    "sg:phone":"+1 407 240 9052",
    "sg:postcode":"32837",
    "sg:province":"FL",
    "sg:tags":[
        "consultant",
        "training"
    ],
    "wof:name":"Simcon Training Ctr",
    "wof:placetype":"venue"
},
  "geometry": {"coordinates":[-81.413456,28.428628],"type":"Point"}
}