{
  "type": "Feature",
  "properties": {
    "addr:full":"101413 Overseas Hwy Key Largo FL 33037",
    "addr:housenumber":"101413",
    "addr:postcode":"33037",
    "addr:street":"Overseas Hwy",
    "iso:country":"US",
    "sg:address":"101413 Overseas Hwy",
    "sg:city":"Key Largo",
    "sg:classifiers":[
        {
            "category":"Health Services",
            "subcategory":"Doctor",
            "type":"Services"
        }
    ],
    "sg:phone":"+1 305 451 5455",
    "sg:postcode":"33037",
    "sg:province":"FL",
    "sg:tags":[
        "physician",
        "surgeon"
    ],
    "wof:name":"Charles A Kosove DO",
    "wof:placetype":"venue"
},
  "geometry": {"coordinates":[-80.429779,25.104743],"type":"Point"}
}