{
  "type": "Feature",
  "properties": {
    "addr:full":"1295 Gulf Shore Blvd S Naples FL 34102",
    "addr:housenumber":"1295",
    "addr:postcode":"34102",
    "addr:street":"Gulf Shore Blvd S",
    "iso:country":"US",
    "sg:address":"1295 Gulf Shore Blvd S",
    "sg:city":"Naples",
    "sg:classifiers":[
        {
            "category":"Travel",
            "subcategory":"Hotels & Motels",
            "type":"Entertainment"
        },
        {
            "category":"Real Estate",
            "subcategory":"Real Estate Operator",
            "type":"Services"
        }
    ],
    "sg:phone":"+1 239 261 7313",
    "sg:postcode":"34102",
    "sg:province":"FL",
    "sg:tags":[
        "building",
        "apartment"
    ],
    "sg:website":"www.marineraptsmotel.com",
    "wof:name":"Mariner Apartment Motel",
    "wof:placetype":"venue"
},
  "geometry": {"coordinates":[-81.80459999999999,26.131767],"type":"Point"}
}