{
  "type": "Feature",
  "properties": {
    "iso:country":"US",
    "sg:address":"697 Stanford Dr",
    "sg:city":"Altamonte Springs",
    "sg:classifiers":[
        {
            "category":"Building & Trades",
            "subcategory":"Landscaping Services",
            "type":"Services"
        }
    ],
    "sg:phone":"+1 407 869 4921",
    "sg:postcode":"32714",
    "sg:province":"FL",
    "sg:tags":[
        "landscape"
    ],
    "wof:name":"Caballero S Javier Landscaping",
    "wof:placetype":"venue"
},
  "geometry": {"coordinates":[-81.41030000000001,28.656772],"type":"Point"}
}