{
  "type": "Feature",
  "properties": {
    "addr:full":"4690 NW 113th Ave Sunrise FL 33323",
    "addr:housenumber":"4690",
    "addr:postcode":"33323",
    "addr:street":"Nw 113Th Ave",
    "iso:country":"US",
    "sg:address":"4690 NW 113th Ave",
    "sg:city":"Sunrise",
    "sg:classifiers":[
        {
            "category":"Real Estate",
            "subcategory":"Real Estate Operator",
            "type":"Services"
        }
    ],
    "sg:phone":"+1 954 572 5000",
    "sg:postcode":"33323",
    "sg:province":"FL",
    "sg:tags":[
        "apartment"
    ],
    "wof:name":"Allison Coelho",
    "wof:placetype":"venue"
},
  "geometry": {"coordinates":[-80.298739,26.183233],"type":"Point"}
}