{
  "type": "Feature",
  "properties": {
    "iso:country":"US",
    "sg:address":"1100 S Ponce de Leon Blvd",
    "sg:city":"St Augustine",
    "sg:classifiers":[
        {
            "category":"Building & Trades",
            "subcategory":"Construction",
            "type":"Services"
        }
    ],
    "sg:phone":"+1 904 814 6241",
    "sg:postcode":"32084",
    "sg:province":"FL",
    "sg:tags":[
        "contractor"
    ],
    "wof:name":"Robert JL Laurence Building",
    "wof:placetype":"venue"
},
  "geometry": {"coordinates":[-81.324759,29.878726],"type":"Point"}
}