{
  "type": "Feature",
  "properties": {
    "iso:country":"US",
    "sg:address":"23272 Abrade Ave",
    "sg:city":"Port Charlotte",
    "sg:classifiers":[
        {
            "category":"Wholesale",
            "subcategory":"Drugs",
            "type":"Manufacturing & Wholesale Goods"
        }
    ],
    "sg:phone":"+1 941 235 9572",
    "sg:postcode":"33980",
    "sg:province":"FL",
    "wof:name":"Claaudio Di Wenezia",
    "wof:placetype":"venue"
},
  "geometry": {"coordinates":[-82.065822,27.005376],"type":"Point"}
}