{
  "type": "Feature",
  "properties": {
    "iso:country":"US",
    "sg:address":"3000 Dunn Ave",
    "sg:city":"Jacksonville",
    "sg:classifiers":[
        {
            "category":"Real Estate",
            "subcategory":"Real Estate Operator",
            "type":"Services"
        }
    ],
    "sg:phone":"+1 904 766 0002",
    "sg:postcode":"32218",
    "sg:province":"FL",
    "sg:tags":[
        "apartment"
    ],
    "wof:name":"Madison Woods Apartments",
    "wof:placetype":"venue"
},
  "geometry": {"coordinates":[-81.69928299999999,30.438681],"type":"Point"}
}