{
  "type": "Feature",
  "properties": {
    "iso:country":"US",
    "sg:address":"2450 W 5th Ave",
    "sg:city":"Hialeah",
    "sg:classifiers":[
        {
            "category":"Manufacturing",
            "subcategory":"Retail Goods",
            "type":"Manufacturing & Wholesale Goods"
        }
    ],
    "sg:phone":"+1 305 576 9770",
    "sg:postcode":"33010",
    "sg:province":"FL",
    "sg:tags":[
        "handbags-wholesale",
        "manufacturer"
    ],
    "wof:name":"B & B Handbags Inc",
    "wof:placetype":"venue"
},
  "geometry": {"coordinates":[-80.29192399999999,25.843894],"type":"Point"}
}