{
  "type": "Feature",
  "properties": {
    "iso:country":"US",
    "sg:address":"6531 102nd Ave",
    "sg:city":"Pinellas Park",
    "sg:classifiers":[
        {
            "category":"Shopping",
            "subcategory":"Jewelry",
            "type":"Retail Goods"
        }
    ],
    "sg:phone":"+1 727 548 0275",
    "sg:postcode":"33782",
    "sg:province":"FL",
    "wof:name":"Omega Pawn & Jewelers",
    "wof:placetype":"venue"
},
  "geometry": {"coordinates":[-82.728651,27.864703],"type":"Point"}
}