{
  "type": "Feature",
  "properties": {
    "addr:full":"621 Crystal Mist Ave Sebastian FL 32958",
    "addr:housenumber":"621",
    "addr:postcode":"32958",
    "addr:street":"Crystal Mist Ave",
    "iso:country":"US",
    "sg:address":"621 Crystal Mist Ave",
    "sg:city":"Sebastian",
    "sg:classifiers":[
        {
            "category":"Building & Trades",
            "subcategory":"Landscaping Services",
            "type":"Services"
        }
    ],
    "sg:phone":"+1 772 388 0994",
    "sg:postcode":"32958",
    "sg:province":"FL",
    "wof:name":"Judy & Johns Lawn Service Inc",
    "wof:placetype":"venue"
},
  "geometry": {"coordinates":[-80.49002299999999,27.762589],"type":"Point"}
}