{
  "type": "Feature",
  "properties": {
    "addr:full":"574 Eagle Run Lakeland FL 33809",
    "addr:housenumber":"574",
    "addr:postcode":"33809",
    "addr:street":"Eagle Run",
    "iso:country":"US",
    "sg:address":"574 Eagle Run",
    "sg:city":"Lakeland",
    "sg:classifiers":[
        {
            "category":"Real Estate",
            "subcategory":"Real Estate Agent",
            "type":"Services"
        }
    ],
    "sg:phone":"+1 863 853 3616",
    "sg:postcode":"33809",
    "sg:province":"FL",
    "wof:name":"Grothe Properties",
    "wof:placetype":"venue"
},
  "geometry": {"coordinates":[-81.945386,28.123935],"type":"Point"}
}