{
  "type": "Feature",
  "properties": {
    "addr:full":"6024 S Orange Ave Orlando FL 32809",
    "addr:housenumber":"6024",
    "addr:postcode":"32809",
    "addr:street":"S Orange Ave",
    "iso:country":"US",
    "sg:address":"6024 S Orange Ave",
    "sg:city":"Orlando",
    "sg:classifiers":[
        {
            "category":"Personal",
            "subcategory":"Beauty Salon",
            "type":"Services"
        }
    ],
    "sg:phone":"+1 407 855 7288",
    "sg:postcode":"32809",
    "sg:province":"FL",
    "wof:name":"Hair 1",
    "wof:placetype":"venue"
},
  "geometry": {"coordinates":[-81.36894599999999,28.471557],"type":"Point"}
}