{
  "type": "Feature",
  "properties": {
    "iso:country":"US",
    "sg:address":"7506 NW 58th St",
    "sg:city":"Fort Lauderdale",
    "sg:classifiers":[
        {
            "category":"Home & Garden",
            "subcategory":"Home Furnishings",
            "type":"Retail Goods"
        }
    ],
    "sg:phone":"+1 954 803 4355",
    "sg:postcode":"33321",
    "sg:province":"FL",
    "wof:name":"Louis Giannotta Inc",
    "wof:placetype":"venue"
},
  "geometry": {"coordinates":[-80.25202899999999,26.196842],"type":"Point"}
}