{
  "type": "Feature",
  "properties": {
    "addr:full":"114 Sycamore Ln Lake Helen FL 32744",
    "addr:housenumber":"114",
    "addr:postcode":"32744",
    "addr:street":"Sycamore Ln",
    "iso:country":"US",
    "sg:address":"114 Sycamore Ln",
    "sg:city":"Lake Helen",
    "sg:classifiers":[
        {
            "category":"Shopping",
            "subcategory":"Bicycles & Sporting Goods",
            "type":"Retail Goods"
        }
    ],
    "sg:phone":"+1 386 228 2786",
    "sg:postcode":"32744",
    "sg:province":"FL",
    "sg:tags":[
        "equipment",
        "fishing"
    ],
    "wof:name":"B & GS Bass Shop",
    "wof:placetype":"venue"
},
  "geometry": {"coordinates":[-81.217578,28.982083],"type":"Point"}
}