{
  "type": "Feature",
  "properties": {
    "addr:full":"201 Arkona Ct West Palm Beach FL 33401",
    "addr:housenumber":"201",
    "addr:postcode":"33401",
    "addr:street":"Arkona Ct",
    "iso:country":"US",
    "sg:address":"201 Arkona Ct",
    "sg:city":"West Palm Beach",
    "sg:classifiers":[
        {
            "category":"Professional",
            "subcategory":"Lawyer & Legal Services",
            "type":"Services"
        }
    ],
    "sg:phone":"+1 561 659 5201",
    "sg:postcode":"33401",
    "sg:province":"FL",
    "sg:tags":[
        "attorney"
    ],
    "wof:name":"Parks & Braxton",
    "wof:placetype":"venue"
},
  "geometry": {"coordinates":[-80.051464,26.700115],"type":"Point"}
}