{
  "type": "Feature",
  "properties": {
    "addr:full":"9000 Forest Oaks Blvd Spring Hill FL 34606",
    "addr:housenumber":"9000",
    "addr:postcode":"34606",
    "addr:street":"Forest Oaks Blvd",
    "iso:country":"US",
    "sg:address":"9000 Forest Oaks Blvd",
    "sg:city":"Spring Hill",
    "sg:classifiers":[
        {
            "category":"Building & Trades",
            "subcategory":"Construction",
            "type":"Services"
        }
    ],
    "sg:phone":"+1 352 666 4053",
    "sg:postcode":"34606",
    "sg:province":"FL",
    "sg:tags":[
        "carpentry",
        "contractor"
    ],
    "wof:name":"Jose Dardiz",
    "wof:placetype":"venue"
},
  "geometry": {"coordinates":[-82.575289,28.486796],"type":"Point"}
}