{
  "type": "Feature",
  "properties": {
    "iso:country":"US",
    "sg:address":"666 6th St N",
    "sg:city":"Saint Petersburg",
    "sg:classifiers":[
        {
            "category":"Health Services",
            "subcategory":"Doctor",
            "type":"Services"
        }
    ],
    "sg:phone":"+1 727 896 4900",
    "sg:postcode":"33701",
    "sg:province":"FL",
    "sg:tags":[
        "medical"
    ],
    "wof:name":"Hernea Center The",
    "wof:placetype":"venue"
},
  "geometry": {"coordinates":[-82.64167,27.778927],"type":"Point"}
}