{
  "type": "Feature",
  "properties": {
    "addr:full":"6062 17th St E Bradenton FL 34203",
    "addr:housenumber":"6062",
    "addr:postcode":"34203",
    "addr:street":"17Th St",
    "iso:country":"US",
    "sg:address":"6062 17th St E",
    "sg:city":"Bradenton",
    "sg:classifiers":[
        {
            "category":"Wholesale",
            "subcategory":"Auto Parts",
            "type":"Manufacturing & Wholesale Goods"
        }
    ],
    "sg:phone":"+1 941 753 4500",
    "sg:postcode":"34203",
    "sg:province":"FL",
    "sg:tags":[
        "automobile",
        "rebuilt"
    ],
    "wof:name":"Azbell Alternative Auto Parts",
    "wof:placetype":"venue"
},
  "geometry": {"coordinates":[-82.54364,27.43259],"type":"Point"}
}