{
  "type": "Feature",
  "properties": {
    "iso:country":"US",
    "sg:address":"815 S Main St",
    "sg:city":"Jacksonville",
    "sg:classifiers":[
        {
            "category":"Professional",
            "type":"Services"
        }
    ],
    "sg:phone":"+1 904 858 1271",
    "sg:postcode":"32207",
    "sg:province":"FL",
    "sg:tags":[
        "establishment"
    ],
    "wof:name":"Airland Gbl",
    "wof:placetype":"venue"
},
  "geometry": {"coordinates":[-81.658767,30.317374],"type":"Point"}
}