{
  "type": "Feature",
  "properties": {
    "iso:country":"US",
    "sg:address":"525 NE 3rd Ave",
    "sg:city":"Delray Beach",
    "sg:classifiers":[
        {
            "category":"Professional",
            "subcategory":"Accounting & Tax Preparation",
            "type":"Services"
        }
    ],
    "sg:phone":"+1 561 736 1675",
    "sg:postcode":"33444",
    "sg:province":"FL",
    "sg:tags":[
        "accountant"
    ],
    "sg:website":"www.rkcw.com",
    "wof:name":"Rodriguez Kinzbrunner Coniglio",
    "wof:placetype":"venue"
},
  "geometry": {"coordinates":[-80.069288,26.471397],"type":"Point"}
}