{
  "type": "Feature",
  "properties": {
    "iso:country":"US",
    "sg:address":"1421 Hawthorne Dr",
    "sg:city":"Sebring",
    "sg:classifiers":[
        {
            "category":"Manufacturing",
            "subcategory":"Metals",
            "type":"Manufacturing & Wholesale Goods"
        }
    ],
    "sg:phone":"+1 863 385 5019",
    "sg:postcode":"33870",
    "sg:province":"FL",
    "sg:tags":[
        "product",
        "fabricated",
        "mfg"
    ],
    "wof:name":"Allied Tech Services",
    "wof:placetype":"venue"
},
  "geometry": {"coordinates":[-81.44761699999999,27.507039],"type":"Point"}
}