{
  "type": "Feature",
  "properties": {
    "iso:country":"US",
    "sg:address":"1990 NW 20th St",
    "sg:city":"Miami",
    "sg:classifiers":[
        {
            "category":"Shopping",
            "subcategory":"Clothing, Apparel, & Fashions",
            "type":"Retail Goods"
        }
    ],
    "sg:phone":"+1 305 324 5403",
    "sg:postcode":"33142",
    "sg:province":"FL",
    "sg:tags":[
        "accessory",
        "clothing",
        "women's"
    ],
    "wof:name":"20 20 Fashions of Miami Miami",
    "wof:placetype":"venue"
},
  "geometry": {"coordinates":[-80.228104,25.794701],"type":"Point"}
}