{
  "type": "Feature",
  "properties": {
    "iso:country":"US",
    "sg:address":"2875 Garland Rd",
    "sg:city":"Naples",
    "sg:classifiers":[
        {
            "category":"Restaurant",
            "type":"Food & Drink"
        }
    ],
    "sg:phone":"+1 239 348 1908",
    "sg:postcode":"34117",
    "sg:province":"FL",
    "sg:tags":[
        "eating"
    ],
    "wof:name":"Taste Catering",
    "wof:placetype":"venue"
},
  "geometry": {"coordinates":[-81.65454099999999,26.177508],"type":"Point"}
}