{
  "type": "Feature",
  "properties": {
    "iso:country":"US",
    "sg:address":"401 Wyoming Ave",
    "sg:city":"St Cloud",
    "sg:classifiers":[
        {
            "category":"Wholesale",
            "subcategory":"Scrap",
            "type":"Manufacturing & Wholesale Goods"
        }
    ],
    "sg:phone":"+1 407 891 6349",
    "sg:postcode":"34769",
    "sg:province":"FL",
    "sg:tags":[
        "recycling",
        "center"
    ],
    "wof:name":"Sun Up Sun Down",
    "wof:placetype":"venue"
},
  "geometry": {"coordinates":[-81.271092,28.253535],"type":"Point"}
}