{
  "type": "Feature",
  "properties": {
    "iso:country":"US",
    "sg:address":"3362 San Jose Blvd",
    "sg:city":"Jacksonville",
    "sg:classifiers":[
        {
            "category":"Restaurant",
            "type":"Food & Drink"
        }
    ],
    "sg:phone":"+1 904 399 2765",
    "sg:postcode":"32207",
    "sg:province":"FL",
    "sg:tags":[
        "eating"
    ],
    "wof:name":"Convivium Cooking Inc",
    "wof:placetype":"venue"
},
  "geometry": {"coordinates":[-81.651518,30.291279],"type":"Point"}
}