{
  "type": "Feature",
  "properties": {
    "addr:full":"311 N Palmway Lake Worth FL 33460",
    "addr:housenumber":"311",
    "addr:postcode":"33460",
    "addr:street":"N Palmway",
    "iso:country":"US",
    "sg:address":"311 N Palmway",
    "sg:city":"Lake Worth",
    "sg:classifiers":[
        {
            "category":"Wholesale",
            "subcategory":"Groceries",
            "type":"Manufacturing & Wholesale Goods"
        }
    ],
    "sg:phone":"+1 561 586 0048",
    "sg:postcode":"33460",
    "sg:province":"FL",
    "sg:tags":[
        "food",
        "broker"
    ],
    "sg:website":"www.internaturalmarketing.com",
    "wof:name":"Inter Natural Marketing",
    "wof:placetype":"venue"
},
  "geometry": {"coordinates":[-80.05039499999999,26.61997],"type":"Point"}
}