{
  "type": "Feature",
  "properties": {
    "iso:country":"US",
    "sg:address":"837 Palm St",
    "sg:city":"Marco Island",
    "sg:classifiers":[
        {
            "category":"Real Estate",
            "subcategory":"Real Estate Operator",
            "type":"Services"
        }
    ],
    "sg:phone":"+1 239 642 0579",
    "sg:postcode":"34145",
    "sg:province":"FL",
    "sg:tags":[
        "building",
        "nonresidential"
    ],
    "wof:name":"Marco Dolphin Properties Inc",
    "wof:placetype":"venue"
},
  "geometry": {"coordinates":[-81.730949,25.972095],"type":"Point"}
}