{
  "type": "Feature",
  "properties": {
    "addr:full":"430 SW 11th St Miami FL 33130",
    "addr:housenumber":"430",
    "addr:postcode":"33130",
    "addr:street":"Sw 11Th St",
    "iso:country":"US",
    "sg:address":"430 SW 11th St",
    "sg:city":"Miami",
    "sg:classifiers":[
        {
            "category":"Building & Trades",
            "subcategory":"Construction",
            "type":"Services"
        }
    ],
    "sg:phone":"+1 305 545 9983",
    "sg:postcode":"33130",
    "sg:province":"FL",
    "sg:tags":[
        "contractor"
    ],
    "wof:name":"Welldone Contractors Inc",
    "wof:placetype":"venue"
},
  "geometry": {"coordinates":[-80.201447,25.763184],"type":"Point"}
}