{
  "type": "Feature",
  "properties": {
    "iso:country":"US",
    "sg:address":"1016 SE 4th St",
    "sg:city":"Belle Glade",
    "sg:classifiers":[
        {
            "category":"Real Estate",
            "subcategory":"Surveying",
            "type":"Services"
        }
    ],
    "sg:phone":"+1 561 996 6615",
    "sg:postcode":"33430",
    "sg:province":"FL",
    "sg:tags":[
        "surveyor"
    ],
    "wof:name":"PAG Surveyors Inc",
    "wof:placetype":"venue"
},
  "geometry": {"coordinates":[-80.66648499999999,26.672691],"type":"Point"}
}