{
  "type": "Feature",
  "properties": {
    "iso:country":"US",
    "sg:address":"13757 SW 9th Ter",
    "sg:city":"Miami",
    "sg:classifiers":[
        {
            "category":"Building & Trades",
            "subcategory":"Construction",
            "type":"Services"
        }
    ],
    "sg:phone":"+1 305 480 9035",
    "sg:postcode":"33184",
    "sg:province":"FL",
    "sg:tags":[
        "contractor"
    ],
    "wof:name":"Marble & Tile Installation Cor",
    "wof:placetype":"venue"
},
  "geometry": {"coordinates":[-80.417467,25.758422],"type":"Point"}
}