{
  "type": "Feature",
  "properties": {
    "iso:country":"US",
    "sg:address":"13090 N Miami Ave",
    "sg:city":"North Miami",
    "sg:classifiers":[
        {
            "category":"Retail",
            "subcategory":"Portrait Studio",
            "type":"Services"
        }
    ],
    "sg:phone":"+1 305 681 6811",
    "sg:postcode":"33168",
    "sg:province":"FL",
    "sg:tags":[
        "photographer"
    ],
    "wof:name":"Modern Studio Photo",
    "wof:placetype":"venue"
},
  "geometry": {"coordinates":[-80.19895099999999,25.894542],"type":"Point"}
}