{
  "type": "Feature",
  "properties": {
    "iso:country":"US",
    "sg:address":"4680 43rd Ct",
    "sg:city":"Vero Beach",
    "sg:classifiers":[
        {
            "category":"Recreation",
            "type":"Entertainment"
        }
    ],
    "sg:phone":"+1 772 770 5236",
    "sg:postcode":"32967",
    "sg:province":"FL",
    "sg:tags":[
        "parks"
    ],
    "wof:name":"Gifford Park",
    "wof:placetype":"venue"
},
  "geometry": {"coordinates":[-80.430103,27.67549],"type":"Point"}
}