{
  "type": "Feature",
  "properties": {
    "iso:country":"US",
    "sg:address":"146 Biscayne Blvd",
    "sg:city":"Miami",
    "sg:classifiers":[
        {
            "category":"Travel",
            "subcategory":"Hotels & Motels",
            "type":"Entertainment"
        }
    ],
    "sg:phone":"+1 305 358 4555",
    "sg:postcode":"33132",
    "sg:province":"FL",
    "sg:tags":[
        "lodging"
    ],
    "sg:website":"www.hotelesriande.com",
    "wof:name":"Riande Continental Hotel at Bayside",
    "wof:placetype":"venue"
},
  "geometry": {"coordinates":[-80.187887,25.775746],"type":"Point"}
}