{
  "type": "Feature",
  "properties": {
    "iso:country":"US",
    "sg:address":"105 NW 62nd St",
    "sg:city":"Miami",
    "sg:classifiers":[
        {
            "category":"Retail",
            "subcategory":"Laundry & Dry Cleaning",
            "type":"Services"
        }
    ],
    "sg:phone":"+1 305 762 6986",
    "sg:postcode":"33150",
    "sg:province":"FL",
    "wof:name":"Coin Laundry",
    "wof:placetype":"venue"
},
  "geometry": {"coordinates":[-80.19856,25.832611],"type":"Point"}
}