{
  "type": "Feature",
  "properties": {
    "iso:country":"US",
    "sg:address":"225 Hibiscus St",
    "sg:city":"Tavernier",
    "sg:classifiers":[
        {
            "category":"Professional",
            "subcategory":"Business Services",
            "type":"Services"
        }
    ],
    "sg:phone":"+1 305 852 4877",
    "sg:postcode":"33070",
    "sg:province":"FL",
    "wof:name":"Ironwood Enterprises Inc",
    "wof:placetype":"venue"
},
  "geometry": {"coordinates":[-80.542129,24.996875],"type":"Point"}
}