{
  "type": "Feature",
  "properties": {
    "iso:country":"US",
    "sg:address":"2351 Douglas Rd",
    "sg:city":"Miami",
    "sg:classifiers":[
        {
            "category":"Real Estate",
            "subcategory":"Real Estate Operator",
            "type":"Services"
        }
    ],
    "sg:phone":"+1 305 569 6110",
    "sg:postcode":"33145",
    "sg:province":"FL",
    "sg:tags":[
        "apartment"
    ],
    "wof:name":"Gables Terrace Condominiums",
    "wof:placetype":"venue"
},
  "geometry": {"coordinates":[-80.25414499999999,25.746634],"type":"Point"}
}