{
  "type": "Feature",
  "properties": {
    "iso:country":"US",
    "sg:address":"947 Torchwood Dr",
    "sg:city":"De Land",
    "sg:classifiers":[
        {
            "category":"Professional",
            "subcategory":"Engineering",
            "type":"Services"
        }
    ],
    "sg:phone":"+1 386 738 3669",
    "sg:postcode":"32724",
    "sg:province":"FL",
    "wof:name":"Whelen Engineering",
    "wof:placetype":"venue"
},
  "geometry": {"coordinates":[-81.293628,28.994708],"type":"Point"}
}