{
  "type": "Feature",
  "properties": {
    "iso:country":"US",
    "sg:address":"233 Harbor Dr",
    "sg:city":"Cape Canaveral",
    "sg:classifiers":[
        {
            "category":"Home & Garden",
            "subcategory":"Building Materials",
            "type":"Retail Goods"
        }
    ],
    "sg:phone":"+1 321 799 0050",
    "sg:postcode":"32920",
    "sg:province":"FL",
    "wof:name":"Beach Windows & Doors",
    "wof:placetype":"venue"
},
  "geometry": {"coordinates":[-80.601375,28.398884],"type":"Point"}
}