{
  "type": "Feature",
  "properties": {
    "addr:full":"3616 W Flagler St Miami FL 33135",
    "addr:housenumber":"3616",
    "addr:postcode":"33135",
    "addr:street":"W Flagler St",
    "iso:country":"US",
    "sg:address":"3616 W Flagler St",
    "sg:city":"Miami",
    "sg:classifiers":[
        {
            "category":"Manufacturing",
            "subcategory":"Printing",
            "type":"Manufacturing & Wholesale Goods"
        }
    ],
    "sg:phone":"+1 305 445 9215",
    "sg:postcode":"33135",
    "sg:province":"FL",
    "sg:tags":[
        "printer"
    ],
    "wof:name":"Columbus Instant Printing",
    "wof:placetype":"venue"
},
  "geometry": {"coordinates":[-80.253889,25.771792],"type":"Point"}
}