{
  "type": "Feature",
  "properties": {
    "addr:full":"347 N Birch Rd Fort Lauderdale FL 33304",
    "addr:housenumber":"347",
    "addr:postcode":"33304",
    "addr:street":"N Birch Rd",
    "iso:country":"US",
    "sg:address":"347 N Birch Rd",
    "sg:city":"Fort Lauderdale",
    "sg:classifiers":[
        {
            "category":"Wholesale",
            "subcategory":"Machinery & Supplies",
            "type":"Manufacturing & Wholesale Goods"
        }
    ],
    "sg:phone":"+1 954 525 3954",
    "sg:postcode":"33304",
    "sg:province":"FL",
    "sg:tags":[
        "equipment",
        "industrial"
    ],
    "wof:name":"Griffin Automation South FL",
    "wof:placetype":"venue"
},
  "geometry": {"coordinates":[-80.105862,26.128],"type":"Point"}
}