{
  "type": "Feature",
  "properties": {
    "iso:country":"US",
    "sg:address":"1721 NE 19th Ave",
    "sg:city":"Ocala",
    "sg:classifiers":[
        {
            "category":"Manufacturing",
            "subcategory":"Tools & Machinery",
            "type":"Manufacturing & Wholesale Goods"
        }
    ],
    "sg:phone":"+1 352 622 1213",
    "sg:postcode":"34470",
    "sg:province":"FL",
    "sg:tags":[
        "commercial",
        "sharpener",
        "knife",
        "mfg"
    ],
    "wof:name":"Tru Hone Corporation",
    "wof:placetype":"venue"
},
  "geometry": {"coordinates":[-82.111524,29.20468],"type":"Point"}
}