{
  "type": "Feature",
  "properties": {
    "addr:full":"512 SW Badger Ter Port Saint Lucie FL 34953",
    "addr:housenumber":"512",
    "addr:postcode":"34953",
    "addr:street":"Sw Badger Ter;Lucie",
    "iso:country":"US",
    "sg:address":"512 SW Badger Ter",
    "sg:city":"Port Saint Lucie",
    "sg:classifiers":[
        {
            "category":"Social Services",
            "type":"Services"
        }
    ],
    "sg:phone":"+1 561 998 3071",
    "sg:postcode":"34953",
    "sg:province":"FL",
    "sg:tags":[
        "worker"
    ],
    "wof:name":"Proxy Care Management Inc",
    "wof:placetype":"venue"
},
  "geometry": {"coordinates":[-80.363618,27.269572],"type":"Point"}
}