{
  "type": "Feature",
  "properties": {
    "addr:full":"1632 Bream Dr Seville FL 32190",
    "addr:housenumber":"1632",
    "addr:postcode":"32190",
    "addr:street":"Bream Dr",
    "iso:country":"US",
    "sg:address":"1632 Bream Dr",
    "sg:city":"Seville",
    "sg:classifiers":[
        {
            "category":"Retail",
            "subcategory":"Auto Repair",
            "type":"Services"
        }
    ],
    "sg:phone":"+1 386 749 3812",
    "sg:postcode":"32190",
    "sg:province":"FL",
    "sg:tags":[
        "diesel",
        "general"
    ],
    "wof:name":"Bomar Enterprises",
    "wof:placetype":"venue"
},
  "geometry": {"coordinates":[-81.541352,29.309383],"type":"Point"}
}