{
  "type": "Feature",
  "properties": {
    "addr:full":"44 NE 1st St Pompano Beach FL 33060",
    "addr:housenumber":"44",
    "addr:postcode":"33060",
    "addr:street":"Ne 1St St",
    "iso:country":"US",
    "sg:address":"44 NE 1st St",
    "sg:city":"Pompano Beach",
    "sg:classifiers":[
        {
            "category":"Wholesale",
            "subcategory":"Electrical",
            "type":"Manufacturing & Wholesale Goods"
        }
    ],
    "sg:phone":"+1 954 785 3533",
    "sg:postcode":"33060",
    "sg:province":"FL",
    "sg:tags":[
        "lighting",
        "retail",
        "fixture"
    ],
    "sg:website":"www.acelightingpompano.com",
    "wof:name":"Ace Lighting Inc",
    "wof:placetype":"venue"
},
  "geometry": {"coordinates":[-80.12468,26.232349],"type":"Point"}
}