{
  "type": "Feature",
  "properties": {
    "addr:full":"5133 Muldoon St Crestview FL 32539",
    "addr:housenumber":"5133",
    "addr:postcode":"32539",
    "addr:street":"Muldoon St",
    "iso:country":"US",
    "sg:address":"5133 Muldoon St",
    "sg:city":"Crestview",
    "sg:classifiers":[
        {
            "category":"Shopping",
            "subcategory":"Crafts & Fabrics",
            "type":"Retail Goods"
        }
    ],
    "sg:phone":"+1 850 682 1569",
    "sg:postcode":"32539",
    "sg:province":"FL",
    "sg:tags":[
        "sewing"
    ],
    "wof:name":"Vels Fabric Shop",
    "wof:placetype":"venue"
},
  "geometry": {"coordinates":[-86.545439,30.746451],"type":"Point"}
}