{
  "type": "Feature",
  "properties": {
    "addr:full":"15600 NW 7th Ave Miami FL 33169",
    "addr:housenumber":"15600",
    "addr:postcode":"33169",
    "addr:street":"Nw 7Th Ave",
    "iso:country":"US",
    "sg:address":"15600 NW 7th Ave",
    "sg:city":"Miami",
    "sg:classifiers":[
        {
            "category":"Personal",
            "subcategory":"Beauty Salon",
            "type":"Services"
        }
    ],
    "sg:phone":"+1 305 769 1296",
    "sg:postcode":"33169",
    "sg:province":"FL",
    "wof:name":"James Olson Hair Nail & More",
    "wof:placetype":"venue"
},
  "geometry": {"coordinates":[-80.21191899999999,25.917434],"type":"Point"}
}