{
  "type": "Feature",
  "properties": {
    "iso:country":"US",
    "sg:address":"10200 Snug Harbor Rd NE",
    "sg:city":"St Petersburg",
    "sg:classifiers":[
        {
            "category":"Building & Trades",
            "subcategory":"Construction",
            "type":"Services"
        }
    ],
    "sg:phone":"+1 727 578 6022",
    "sg:postcode":"33702",
    "sg:province":"FL",
    "sg:tags":[
        "general",
        "contractor"
    ],
    "wof:name":"Jay Gee Development LLC",
    "wof:placetype":"venue"
},
  "geometry": {"coordinates":[-82.616519,27.863653],"type":"Point"}
}