{
  "type": "Feature",
  "properties": {
    "addr:full":"1 Meadows Park Ln Boynton Beach FL 33436",
    "addr:housenumber":"1",
    "addr:postcode":"33436",
    "addr:street":"Meadows Park Ln",
    "iso:country":"US",
    "sg:address":"1 Meadows Park Ln",
    "sg:city":"Boynton Beach",
    "sg:classifiers":[
        {
            "category":"Professional",
            "subcategory":"Management & Consulting",
            "type":"Services"
        }
    ],
    "sg:phone":"+1 561 641 2622",
    "sg:postcode":"33436",
    "sg:province":"FL",
    "sg:tags":[
        "consultant",
        "business"
    ],
    "wof:name":"Jeff Pasquale-Coaching",
    "wof:placetype":"venue"
},
  "geometry": {"coordinates":[-80.09779,26.562244],"type":"Point"}
}