{
  "type": "Feature",
  "properties": {
    "iso:country":"US",
    "sg:address":"370 Westwind Ct",
    "sg:city":"Lake Mary",
    "sg:classifiers":[
        {
            "category":"Building & Trades",
            "subcategory":"Construction",
            "type":"Services"
        }
    ],
    "sg:phone":"+1 407 330 1854",
    "sg:postcode":"32746",
    "sg:province":"FL",
    "sg:tags":[
        "hanging",
        "contractor"
    ],
    "wof:name":"Lyndons Professional Painting",
    "wof:placetype":"venue"
},
  "geometry": {"coordinates":[-81.34121500000001,28.743986],"type":"Point"}
}