{
  "type": "Feature",
  "properties": {
    "iso:country":"US",
    "sg:address":"6201 Sheldon Rd",
    "sg:city":"Tampa",
    "sg:classifiers":[
        {
            "category":"Organizations",
            "subcategory":"Religious Organization",
            "type":"Services"
        }
    ],
    "sg:phone":"+1 813 886 1437",
    "sg:postcode":"33615",
    "sg:province":"FL",
    "sg:tags":[
        "church"
    ],
    "wof:name":"Jehovah's Witnesses-Town",
    "wof:placetype":"venue"
},
  "geometry": {"coordinates":[-82.583371,28.00284],"type":"Point"}
}