{
  "type": "Feature",
  "properties": {
    "iso:country":"US",
    "sg:address":"5205 US Hwy 1 S",
    "sg:city":"Saint Augustine",
    "sg:classifiers":[
        {
            "category":"Organizations",
            "subcategory":"Religious Organization",
            "type":"Services"
        }
    ],
    "sg:phone":"+1 904 471 3747",
    "sg:postcode":"32086",
    "sg:province":"FL",
    "wof:name":"St Anastasia Catholic Church",
    "wof:placetype":"venue"
},
  "geometry": {"coordinates":[-81.319418,29.794109],"type":"Point"}
}