{
  "type": "Feature",
  "properties": {
    "addr:full":"2545 W 80th St Hialeah FL 33016",
    "addr:housenumber":"2545",
    "addr:postcode":"33016",
    "addr:street":"W 80Th St",
    "iso:country":"US",
    "sg:address":"2545 W 80th St",
    "sg:city":"Hialeah",
    "sg:classifiers":[
        {
            "category":"Education",
            "subcategory":"Special Training",
            "type":"Public Place"
        }
    ],
    "sg:phone":"+1 305 825 0808",
    "sg:postcode":"33016",
    "sg:province":"FL",
    "sg:tags":[
        "school",
        "instruction",
        "art"
    ],
    "wof:name":"Gi Gi S Academy",
    "wof:placetype":"venue"
},
  "geometry": {"coordinates":[-80.33540000000001,25.895235],"type":"Point"}
}