{
  "type": "Feature",
  "properties": {
    "addr:full":"802 Fisher Rd Winter Springs FL 32708",
    "addr:housenumber":"802",
    "addr:postcode":"32708",
    "addr:street":"Fisher Rd",
    "iso:country":"US",
    "sg:address":"802 Fisher Rd",
    "sg:city":"Winter Springs",
    "sg:classifiers":[
        {
            "category":"Travel",
            "subcategory":"Travel Agent",
            "type":"Entertainment"
        }
    ],
    "sg:phone":"+1 407 699 4207",
    "sg:postcode":"32708",
    "sg:province":"FL",
    "sg:tags":[
        "operator",
        "tour"
    ],
    "wof:name":"Mystic Moon Workshop",
    "wof:placetype":"venue"
},
  "geometry": {"coordinates":[-81.286338,28.674482],"type":"Point"}
}