{
  "type": "Feature",
  "properties": {
    "iso:country":"US",
    "sg:address":"14691 SW 39 Cir",
    "sg:city":"Ocala",
    "sg:classifiers":[
        {
            "category":"Building & Trades",
            "subcategory":"Landscaping Services",
            "type":"Services"
        }
    ],
    "sg:phone":"+1 352 347 1047",
    "sg:postcode":"34473",
    "sg:province":"FL",
    "sg:tags":[
        "lawn",
        "maintenance",
        "grounds"
    ],
    "wof:name":"Mario C Decarli Sr Lawn Care",
    "wof:placetype":"venue"
},
  "geometry": {"coordinates":[-82.18027499999999,29.000513],"type":"Point"}
}