{
  "type": "Feature",
  "properties": {
    "addr:full":"2514 W Kennedy Blvd Tampa FL 33609",
    "addr:housenumber":"2514",
    "addr:postcode":"33609",
    "addr:street":"W Kennedy Blvd",
    "iso:country":"US",
    "sg:address":"2514 W Kennedy Blvd",
    "sg:city":"Tampa",
    "sg:classifiers":[
        {
            "category":"Restaurant",
            "type":"Food & Drink"
        }
    ],
    "sg:menulink":"http://www.allmenus.com/fl/tampa/160218-burger-king/menu/",
    "sg:phone":"+1 813 874 5922",
    "sg:postcode":"33609",
    "sg:province":"FL",
    "sg:tags":[
        "burger",
        "american"
    ],
    "wof:name":"Burger King",
    "wof:placetype":"venue"
},
  "geometry": {"coordinates":[-82.485837,27.944355],"type":"Point"}
}