{
  "type": "Feature",
  "properties": {
    "iso:country":"US",
    "sg:address":"8700 W Flagler St Ste 150",
    "sg:city":"Miami",
    "sg:classifiers":[
        {
            "category":"Banks & Credit Unions",
            "subcategory":"Bank",
            "type":"Services"
        }
    ],
    "sg:phone":"+1 305 225 2522",
    "sg:postcode":"33174",
    "sg:province":"FL",
    "wof:name":"Ocean Bank",
    "wof:placetype":"venue"
},
  "geometry": {"coordinates":[-80.336403,25.769501],"type":"Point"}
}