{
  "type": "Feature",
  "properties": {
    "iso:country":"US",
    "sg:address":"8122 Citrus Park Town Center Mall",
    "sg:city":"Tampa",
    "sg:classifiers":[
        {
            "category":"Shopping",
            "subcategory":"Shoes",
            "type":"Retail Goods"
        }
    ],
    "sg:phone":"+1 813 926 6429",
    "sg:postcode":"33625",
    "sg:province":"FL",
    "wof:name":"Journeys",
    "wof:placetype":"venue"
},
  "geometry": {"coordinates":[-82.57510600000001,28.068725],"type":"Point"}
}