{
  "type": "Feature",
  "properties": {
    "iso:country":"US",
    "sg:address":"1937 Pembroke Rd",
    "sg:city":"Hollywood",
    "sg:classifiers":[
        {
            "category":"Restaurant",
            "type":"Food & Drink"
        }
    ],
    "sg:phone":"+1 954 921 2955",
    "sg:postcode":"33020",
    "sg:province":"FL",
    "sg:tags":[
        "eating"
    ],
    "wof:name":"Hunan Pavilion",
    "wof:placetype":"venue"
},
  "geometry": {"coordinates":[-80.145988,25.99675],"type":"Point"}
}