{
  "type": "Feature",
  "properties": {
    "iso:country":"US",
    "sg:address":"18651 SW 128th Ave",
    "sg:city":"Miami",
    "sg:classifiers":[
        {
            "category":"Professional",
            "subcategory":"Management & Consulting",
            "type":"Services"
        }
    ],
    "sg:phone":"+1 305 251 8194",
    "sg:postcode":"33177",
    "sg:province":"FL",
    "wof:name":"Management Tactics Internation",
    "wof:placetype":"venue"
},
  "geometry": {"coordinates":[-80.399283,25.594571],"type":"Point"}
}