{
  "type": "Feature",
  "properties": {
    "addr:full":"515 Marcum Rd Lakeland FL 33809",
    "addr:housenumber":"515",
    "addr:postcode":"33809",
    "addr:street":"Marcum Rd",
    "iso:country":"US",
    "sg:address":"515 Marcum Rd",
    "sg:city":"Lakeland",
    "sg:classifiers":[
        {
            "category":"Communications",
            "subcategory":"Film & Video Production",
            "type":"Services"
        }
    ],
    "sg:phone":"+1 863 858 0579",
    "sg:postcode":"33809",
    "sg:province":"FL",
    "sg:tags":[
        "tv",
        "radio",
        "services-commercial",
        "companies-film"
    ],
    "wof:name":"Strongerman Productions",
    "wof:placetype":"venue"
},
  "geometry": {"coordinates":[-81.96412599999999,28.128141],"type":"Point"}
}