{
  "type": "Feature",
  "properties": {
    "addr:full":"171 62nd St Marathon FL 33050",
    "addr:housenumber":"171",
    "addr:postcode":"33050",
    "addr:street":"62Nd St",
    "iso:country":"US",
    "sg:address":"171 62nd St",
    "sg:city":"Marathon",
    "sg:classifiers":[
        {
            "category":"Organizations",
            "subcategory":"Religious Organization",
            "type":"Services"
        }
    ],
    "sg:phone":"+1 305 289 5858",
    "sg:postcode":"33050",
    "sg:province":"FL",
    "sg:tags":[
        "church"
    ],
    "wof:name":"Mision Hispana Iglesia Gtsmn",
    "wof:placetype":"venue"
},
  "geometry": {"coordinates":[-81.070128,24.716351],"type":"Point"}
}