{
  "type": "Feature",
  "properties": {
    "iso:country":"US",
    "sg:address":"6205 Thomas Dr",
    "sg:city":"Panama City",
    "sg:classifiers":[
        {
            "category":"Real Estate",
            "subcategory":"Real Estate Operator",
            "type":"Services"
        }
    ],
    "sg:phone":"+1 850 234 2626",
    "sg:postcode":"32408",
    "sg:province":"FL",
    "sg:tags":[
        "condominium"
    ],
    "wof:name":"Nautical Watch Hm Owners Assn",
    "wof:placetype":"venue"
},
  "geometry": {"coordinates":[-85.765643,30.151331],"type":"Point"}
}