{
  "type": "Feature",
  "properties": {
    "iso:country":"US",
    "sg:address":"2801 SE Monroe St",
    "sg:city":"Stuart",
    "sg:classifiers":[
        {
            "category":"Home & Garden",
            "subcategory":"Household Appliances",
            "type":"Retail Goods"
        },
        {
            "category":"Building & Trades",
            "subcategory":"Construction",
            "type":"Services"
        },
        {
            "category":"Building & Trades",
            "subcategory":"Electrical",
            "type":"Services"
        }
    ],
    "sg:phone":"+1 772 221 8698",
    "sg:postcode":"34997",
    "sg:province":"FL",
    "sg:tags":[
        "repair",
        "purifying",
        "duct",
        "system",
        "specialty",
        "equipment",
        "fitting",
        "heating",
        "cleaning",
        "contractor",
        "air conditioning"
    ],
    "sg:website":"http://gearyair.com",
    "wof:name":"Geary Air",
    "wof:placetype":"venue"
},
  "geometry": {"coordinates":[-80.21532500000001,27.152915],"type":"Point"}
}