{
  "type": "Feature",
  "properties": {
    "iso:country":"US",
    "sg:address":"1055 NE 174th St",
    "sg:city":"Miami",
    "sg:classifiers":[
        {
            "category":"Professional",
            "subcategory":"Management & Consulting",
            "type":"Services"
        }
    ],
    "sg:phone":"+1 305 999 9608",
    "sg:postcode":"33162",
    "sg:province":"FL",
    "sg:tags":[
        "consultant",
        "business"
    ],
    "wof:name":"Michael Katz",
    "wof:placetype":"venue"
},
  "geometry": {"coordinates":[-80.17849200000001,25.93568],"type":"Point"}
}