{
  "type": "Feature",
  "properties": {
    "addr:full":"1201 Cassat Ave Jacksonville FL 32205",
    "addr:housenumber":"1201",
    "addr:postcode":"32205",
    "addr:street":"Cassat Ave",
    "iso:country":"US",
    "sg:address":"1201 Cassat Ave",
    "sg:city":"Jacksonville",
    "sg:classifiers":[
        {
            "category":"Real Estate",
            "subcategory":"Real Estate Agent",
            "type":"Services"
        }
    ],
    "sg:phone":"+1 904 387 0475",
    "sg:postcode":"32205",
    "sg:province":"FL",
    "wof:name":"Cunninghams Realty",
    "wof:placetype":"venue"
},
  "geometry": {"coordinates":[-81.73052800000001,30.302403],"type":"Point"}
}