{
  "type": "Feature",
  "properties": {
    "iso:country":"US",
    "sg:address":"4880 Placida Rd Ste G",
    "sg:city":"Englewood",
    "sg:classifiers":[
        {
            "category":"Real Estate",
            "subcategory":"Real Estate Services",
            "type":"Services"
        },
        {
            "category":"Real Estate",
            "subcategory":"Real Estate Agent",
            "type":"Services"
        }
    ],
    "sg:phone":"+1 941 698 1617",
    "sg:postcode":"34224",
    "sg:province":"FL",
    "sg:tags":[
        "management"
    ],
    "wof:name":"E B B Tide Realty Inc",
    "wof:placetype":"venue"
},
  "geometry": {"coordinates":[-82.31174799999999,26.899001],"type":"Point"}
}