{
  "type": "Feature",
  "properties": {
    "addr:full":"3033 NW North River Dr Ste 3 Miami FL 33142",
    "addr:housenumber":"3033",
    "addr:postcode":"33142",
    "addr:street":"Nw North River Dr Ste 3",
    "iso:country":"US",
    "sg:address":"3033 NW North River Dr Ste 3",
    "sg:city":"Miami",
    "sg:classifiers":[
        {
            "category":"Organizations",
            "subcategory":"Professional Association",
            "type":"Services"
        }
    ],
    "sg:phone":"+1 305 637 7977",
    "sg:postcode":"33142",
    "sg:province":"FL",
    "sg:tags":[
        "business",
        "trade"
    ],
    "sg:website":"http://www.miamirivermarinegroup.com",
    "wof:name":"South Fla Rgonal Maritime Exch",
    "wof:placetype":"venue"
},
  "geometry": {"coordinates":[-80.244551,25.796661],"type":"Point"}
}