{
  "type": "Feature",
  "properties": {
    "addr:full":"2121 Wood St Sarasota FL 34237",
    "addr:housenumber":"2121",
    "addr:postcode":"34237",
    "addr:street":"Wood St",
    "iso:country":"US",
    "sg:address":"2121 Wood St",
    "sg:city":"Sarasota",
    "sg:classifiers":[
        {
            "category":"Real Estate",
            "subcategory":"Real Estate Operator",
            "type":"Services"
        }
    ],
    "sg:phone":"+1 941 366 7461",
    "sg:postcode":"34237",
    "sg:province":"FL",
    "sg:tags":[
        "apartment"
    ],
    "wof:name":"City Walk Condominiums",
    "wof:placetype":"venue"
},
  "geometry": {"coordinates":[-82.526291,27.328475],"type":"Point"}
}