{
  "type": "Feature",
  "properties": {
    "iso:country":"US",
    "sg:address":"1719 Mango Cir",
    "sg:city":"West Palm Beach",
    "sg:classifiers":[
        {
            "category":"Building & Trades",
            "subcategory":"Construction",
            "type":"Services"
        }
    ],
    "sg:phone":"+1 561 968 1484",
    "sg:postcode":"33406",
    "sg:province":"FL",
    "sg:tags":[
        "contractor"
    ],
    "wof:name":"Provenzale Michael L S",
    "wof:placetype":"venue"
},
  "geometry": {"coordinates":[-80.076629,26.656628],"type":"Point"}
}