{
  "type": "Feature",
  "properties": {
    "iso:country":"US",
    "sg:address":"14641 Palmetto Palm Ave",
    "sg:city":"Hialeah",
    "sg:classifiers":[
        {
            "category":"Utilities",
            "subcategory":"Telephone",
            "type":"Services"
        }
    ],
    "sg:phone":"+1 305 828 8495",
    "sg:postcode":"33014",
    "sg:province":"FL",
    "sg:tags":[
        "communications"
    ],
    "wof:name":"Telephone/Data Plus",
    "wof:placetype":"venue"
},
  "geometry": {"coordinates":[-80.31128,25.906874],"type":"Point"}
}