{
  "type": "Feature",
  "properties": {
    "iso:country":"US",
    "sg:address":"2744 Andes Way",
    "sg:city":"Saint Cloud",
    "sg:classifiers":[
        {
            "category":"Shopping",
            "subcategory":"Catalog Store",
            "type":"Retail Goods"
        }
    ],
    "sg:phone":"+1 407 892 1549",
    "sg:postcode":"34769",
    "sg:province":"FL",
    "sg:tags":[
        "mail",
        "house"
    ],
    "wof:name":"Homers Sport Cds Collectibles",
    "wof:placetype":"venue"
},
  "geometry": {"coordinates":[-81.278554,28.232655],"type":"Point"}
}