{
  "type": "Feature",
  "properties": {
    "iso:country":"US",
    "sg:address":"3178 SW 8th St",
    "sg:city":"Miami",
    "sg:classifiers":[
        {
            "category":"Wholesale",
            "subcategory":"Non-durable Goods",
            "type":"Manufacturing & Wholesale Goods"
        }
    ],
    "sg:phone":"+1 954 640 5200",
    "sg:postcode":"33135",
    "sg:province":"FL",
    "sg:tags":[
        "dry",
        "goods-wholesale"
    ],
    "wof:name":"Auction Direct Auto Wholesale Inc",
    "wof:placetype":"venue"
},
  "geometry": {"coordinates":[-80.24651900000001,25.764932],"type":"Point"}
}