{
  "type": "Feature",
  "properties": {
    "addr:full":"100 N Woodland Blvd Deland FL 32720",
    "addr:housenumber":"100",
    "addr:postcode":"32720",
    "addr:street":"N Woodland Blvd",
    "iso:country":"US",
    "sg:address":"100 N Woodland Blvd",
    "sg:city":"Deland",
    "sg:classifiers":[
        {
            "category":"Professional",
            "type":"Services"
        }
    ],
    "sg:phone":"+1 386 738 7676",
    "sg:postcode":"32720",
    "sg:province":"FL",
    "sg:tags":[
        "establishment"
    ],
    "wof:name":"Athens Inc",
    "wof:placetype":"venue"
},
  "geometry": {"coordinates":[-81.30344599999999,29.028975],"type":"Point"}
}