{
  "type": "Feature",
  "properties": {
    "iso:country":"US",
    "sg:address":"8815 Conroy Windermere Rd",
    "sg:city":"Orlando",
    "sg:classifiers":[
        {
            "category":"Manufacturing",
            "subcategory":"Building Materials",
            "type":"Manufacturing & Wholesale Goods"
        }
    ],
    "sg:phone":"+1 321 297 5979",
    "sg:postcode":"32835",
    "sg:province":"FL",
    "sg:tags":[
        "cement-wholesale",
        "cement",
        "manufacturer"
    ],
    "wof:name":"Supply , The",
    "wof:placetype":"venue"
},
  "geometry": {"coordinates":[-81.50627799999999,28.4937],"type":"Point"}
}