{
  "type": "Feature",
  "properties": {
    "addr:full":"1101 SE Pruitt Rd Port St Lucie FL 34952",
    "addr:housenumber":"1101",
    "addr:postcode":"34952",
    "addr:street":"Se Pruitt Rd;St",
    "iso:country":"US",
    "sg:address":"1101 SE Pruitt Rd",
    "sg:city":"Port St Lucie",
    "sg:classifiers":[
        {
            "category":"Banks & Credit Unions",
            "subcategory":"Bank",
            "type":"Services"
        }
    ],
    "sg:phone":"+1 772 335 0200",
    "sg:postcode":"34952",
    "sg:province":"FL",
    "wof:name":"First National Bank & Trust Co",
    "wof:placetype":"venue"
},
  "geometry": {"coordinates":[-80.31762000000001,27.258025],"type":"Point"}
}