{
  "type": "Feature",
  "properties": {
    "addr:full":"449 10th Ave W Palmetto FL 34221",
    "addr:housenumber":"449",
    "addr:postcode":"34221",
    "addr:street":"10Th Ave W",
    "iso:country":"US",
    "sg:address":"449 10th Ave W",
    "sg:city":"Palmetto",
    "sg:classifiers":[
        {
            "category":"Real Estate",
            "subcategory":"Real Estate Agent",
            "type":"Services"
        }
    ],
    "sg:phone":"+1 941 722 8551",
    "sg:postcode":"34221",
    "sg:province":"FL",
    "wof:name":"Homes By The Sea Realty",
    "wof:placetype":"venue"
},
  "geometry": {"coordinates":[-82.57569599999999,27.51461],"type":"Point"}
}