{
  "type": "Feature",
  "properties": {
    "iso:country":"US",
    "sg:address":"529 Grand Vista Trl",
    "sg:city":"Leesburg",
    "sg:classifiers":[
        {
            "category":"Professional",
            "subcategory":"Employment Agencies",
            "type":"Services"
        }
    ],
    "sg:phone":"+1 352 323 4930",
    "sg:postcode":"34748",
    "sg:province":"FL",
    "wof:name":"ODonnell Associates",
    "wof:placetype":"venue"
},
  "geometry": {"coordinates":[-81.94377,28.82836],"type":"Point"}
}