{
  "type": "Feature",
  "properties": {
    "addr:full":"6311 Mallard Trace Dr Tallahassee FL 32312",
    "addr:housenumber":"6311",
    "addr:postcode":"32312",
    "addr:street":"Mallard Trace Dr",
    "iso:country":"US",
    "sg:address":"6311 Mallard Trace Dr",
    "sg:city":"Tallahassee",
    "sg:classifiers":[
        {
            "category":"Professional",
            "subcategory":"Business Services",
            "type":"Services"
        }
    ],
    "sg:phone":"+1 850 385 2054",
    "sg:postcode":"32312",
    "sg:province":"FL",
    "sg:tags":[
        "fence-sales",
        "event",
        "contractor"
    ],
    "wof:name":"White Pickett Fence Production",
    "wof:placetype":"venue"
},
  "geometry": {"coordinates":[-84.276517,30.563822],"type":"Point"}
}