{
  "type": "Feature",
  "properties": {
    "iso:country":"US",
    "sg:address":"595 N Nova Rd",
    "sg:city":"Ormond Beach",
    "sg:classifiers":[
        {
            "category":"Building & Trades",
            "subcategory":"Equipment Rental",
            "type":"Services"
        }
    ],
    "sg:phone":"+1 386 673 4495",
    "sg:postcode":"32174",
    "sg:province":"FL",
    "sg:tags":[
        "leasing"
    ],
    "wof:name":"Lasalle National Leasing Corp",
    "wof:placetype":"venue"
},
  "geometry": {"coordinates":[-81.087636,29.293704],"type":"Point"}
}