{
  "type": "Feature",
  "properties": {
    "iso:country":"US",
    "sg:address":"2412 S Gelman Pl",
    "sg:city":"Tampa",
    "sg:classifiers":[
        {
            "category":"Train Station",
            "subcategory":"Rail",
            "type":"Transportation"
        }
    ],
    "sg:phone":"+1 813 241 2244",
    "sg:postcode":"33619",
    "sg:province":"FL",
    "sg:tags":[
        "stairway",
        "accessory",
        "rails",
        "railing"
    ],
    "wof:name":"All Coast Manufacturing Inc",
    "wof:placetype":"venue"
},
  "geometry": {"coordinates":[-82.39843,27.92318],"type":"Point"}
}