{
  "type": "Feature",
  "properties": {
    "addr:full":"5417 SW 86 Dr Gainesville FL 32608",
    "addr:housenumber":"5417",
    "addr:postcode":"32608",
    "addr:street":"Sw 86 Dr",
    "iso:country":"US",
    "sg:address":"5417 SW 86 Dr",
    "sg:city":"Gainesville",
    "sg:classifiers":[
        {
            "category":"Freight",
            "type":"Transportation"
        }
    ],
    "sg:phone":"+1 352 378 6282",
    "sg:postcode":"32608",
    "sg:province":"FL",
    "wof:name":"C Fertina Ltd",
    "wof:placetype":"venue"
},
  "geometry": {"coordinates":[-82.434473,29.603354],"type":"Point"}
}