{
  "type": "Feature",
  "properties": {
    "iso:country":"US",
    "sg:address":"1651 Keri Island Rd",
    "sg:city":"Naples",
    "sg:classifiers":[
        {
            "category":"Professional",
            "type":"Services"
        }
    ],
    "sg:phone":"+1 239 353 1740",
    "sg:postcode":"34120",
    "sg:province":"FL",
    "wof:name":"Tophats Sutlery Inc",
    "wof:placetype":"venue"
},
  "geometry": {"coordinates":[-81.639218,26.258041],"type":"Point"}
}