{
  "type": "Feature",
  "properties": {
    "iso:country":"US",
    "sg:address":"20161 NE 16th Pl",
    "sg:city":"Miami",
    "sg:classifiers":[
        {
            "category":"Shopping",
            "subcategory":"Jewelry",
            "type":"Retail Goods"
        },
        {
            "category":"Wholesale",
            "subcategory":"Jewelry",
            "type":"Manufacturing & Wholesale Goods"
        }
    ],
    "sg:phone":"+1 305 690 6205",
    "sg:postcode":"33179",
    "sg:province":"FL",
    "sg:tags":[
        "watch"
    ],
    "wof:name":"Dimitri Casa Corp",
    "wof:placetype":"venue"
},
  "geometry": {"coordinates":[-80.16885000000001,25.963863],"type":"Point"}
}