{
  "type": "Feature",
  "properties": {
    "iso:country":"US",
    "sg:address":"3010 S Emerson St",
    "sg:city":"Tampa",
    "sg:classifiers":[
        {
            "category":"Professional",
            "subcategory":"Accounting & Tax Preparation",
            "type":"Services"
        }
    ],
    "sg:phone":"+1 813 837 4652",
    "sg:postcode":"33629",
    "sg:province":"FL",
    "sg:tags":[
        "accountant"
    ],
    "wof:name":"Hyman Larry S",
    "wof:placetype":"venue"
},
  "geometry": {"coordinates":[-82.519594,27.918957],"type":"Point"}
}