{
  "type": "Feature",
  "properties": {
    "iso:country":"US",
    "sg:address":"7491 NW 1st St",
    "sg:city":"Pompano Beach",
    "sg:classifiers":[
        {
            "category":"Real Estate",
            "subcategory":"Real Estate Agent",
            "type":"Services"
        }
    ],
    "sg:phone":"+1 954 979 9903",
    "sg:postcode":"33063",
    "sg:province":"FL",
    "wof:name":"Palm Lakes Assoc Inc",
    "wof:placetype":"venue"
},
  "geometry": {"coordinates":[-80.223877,26.231318],"type":"Point"}
}