{
  "type": "Feature",
  "properties": {
    "addr:full":"849 SE 8th Ave Deerfield Beach FL 33441",
    "addr:housenumber":"849",
    "addr:postcode":"33441",
    "addr:street":"Se 8Th Ave",
    "iso:country":"US",
    "sg:address":"849 SE 8th Ave",
    "sg:city":"Deerfield Beach",
    "sg:classifiers":[
        {
            "category":"Education",
            "subcategory":"Dance Studio",
            "type":"Public Place"
        }
    ],
    "sg:phone":"+1 954 426 2259",
    "sg:postcode":"33441",
    "sg:province":"FL",
    "wof:name":"Dance Academy Deerfield Beach",
    "wof:placetype":"venue"
},
  "geometry": {"coordinates":[-80.094005,26.306363],"type":"Point"}
}