{
  "type": "Feature",
  "properties": {
    "iso:country":"US",
    "sg:address":"975 Mar Walt Dr",
    "sg:city":"Fort Walton Bch",
    "sg:classifiers":[
        {
            "category":"Professional",
            "subcategory":"Lawyer & Legal Services",
            "type":"Services"
        }
    ],
    "sg:phone":"+1 850 863 5297",
    "sg:postcode":"32547",
    "sg:province":"FL",
    "sg:tags":[
        "attorney"
    ],
    "wof:name":"William D Brannon",
    "wof:placetype":"venue"
},
  "geometry": {"coordinates":[-86.632144,30.454472],"type":"Point"}
}