{
  "type": "Feature",
  "properties": {
    "addr:full":"2920 Plymouth Sorrento Rd Apopka FL 32712",
    "addr:housenumber":"2920",
    "addr:postcode":"32712",
    "addr:street":"Plymouth Sorrento Rd",
    "iso:country":"US",
    "sg:address":"2920 Plymouth Sorrento Rd",
    "sg:city":"Apopka",
    "sg:classifiers":[
        {
            "category":"Wholesale",
            "subcategory":"Plants",
            "type":"Manufacturing & Wholesale Goods"
        }
    ],
    "sg:phone":"+1 407 889 0330",
    "sg:postcode":"32712",
    "sg:province":"FL",
    "sg:tags":[
        "nursery",
        "tree"
    ],
    "wof:name":"Dean's Enterprises",
    "wof:placetype":"venue"
},
  "geometry": {"coordinates":[-81.557777,28.725304],"type":"Point"}
}