{
  "type": "Feature",
  "properties": {
    "iso:country":"US",
    "sg:address":"820 S 15th St",
    "sg:city":"Fort Pierce",
    "sg:classifiers":[
        {
            "category":"Building & Trades",
            "subcategory":"Construction",
            "type":"Services"
        }
    ],
    "sg:phone":"+1 772 461 1941",
    "sg:postcode":"34950",
    "sg:province":"FL",
    "sg:tags":[
        "house"
    ],
    "wof:name":"Right On Time Construction",
    "wof:placetype":"venue"
},
  "geometry": {"coordinates":[-80.33902,27.439607],"type":"Point"}
}