{
  "type": "Feature",
  "properties": {
    "addr:full":"5959 NW 37th Ave Miami FL 33142",
    "addr:housenumber":"5959",
    "addr:postcode":"33142",
    "addr:street":"Nw 37Th Ave",
    "iso:country":"US",
    "sg:address":"5959 NW 37th Ave",
    "sg:city":"Miami",
    "sg:classifiers":[
        {
            "category":"Food & Beverages",
            "subcategory":"Specialty",
            "type":"Retail Goods"
        }
    ],
    "sg:phone":"+1 305 637 7678",
    "sg:postcode":"33142",
    "sg:province":"FL",
    "sg:tags":[
        "vitamin"
    ],
    "wof:name":"Navarro Wholesale",
    "wof:placetype":"venue"
},
  "geometry": {"coordinates":[-80.2572,25.828064],"type":"Point"}
}