{
  "type": "Feature",
  "properties": {
    "iso:country":"US",
    "sg:address":"3771 NW 51st St",
    "sg:city":"Miami",
    "sg:classifiers":[
        {
            "category":"Building & Trades",
            "subcategory":"Construction",
            "type":"Services"
        }
    ],
    "sg:phone":"+1 305 634 5455",
    "sg:postcode":"33142",
    "sg:province":"FL",
    "sg:tags":[
        "contractor"
    ],
    "wof:name":"Mx Marble & Granite Inc",
    "wof:placetype":"venue"
},
  "geometry": {"coordinates":[-80.257513,25.820271],"type":"Point"}
}