{
  "type": "Feature",
  "properties": {
    "addr:full":"5461 SE Maricamp Rd Ocala FL 34480",
    "addr:housenumber":"5461",
    "addr:postcode":"34480",
    "addr:street":"Se Maricamp Rd",
    "iso:country":"US",
    "sg:address":"5461 SE Maricamp Rd",
    "sg:city":"Ocala",
    "sg:classifiers":[
        {
            "category":"Recreation",
            "type":"Entertainment"
        }
    ],
    "sg:phone":"+1 352 624 4222",
    "sg:postcode":"34480",
    "sg:province":"FL",
    "sg:tags":[
        "skating",
        "rink"
    ],
    "wof:name":"Skate Mania",
    "wof:placetype":"venue"
},
  "geometry": {"coordinates":[-82.057306,29.140903],"type":"Point"}
}