{
  "type": "Feature",
  "properties": {
    "iso:country":"US",
    "sg:address":"10221 Emerald Coast Pkwy W",
    "sg:city":"Destin",
    "sg:classifiers":[
        {
            "category":"Shopping",
            "subcategory":"Jewelry",
            "type":"Retail Goods"
        }
    ],
    "sg:phone":"+1 850 654 5660",
    "sg:postcode":"32550",
    "sg:province":"FL",
    "sg:tags":[
        "jeweler"
    ],
    "wof:name":"Susan Allen Designs Fine Jwlry",
    "wof:placetype":"venue"
},
  "geometry": {"coordinates":[-86.345838,30.376406],"type":"Point"}
}