{
  "type": "Feature",
  "properties": {
    "iso:country":"US",
    "sg:address":"1621 Alden Rd",
    "sg:city":"Orlando",
    "sg:classifiers":[
        {
            "category":"Professional",
            "type":"Services"
        }
    ],
    "sg:phone":"+1 407 206 0110",
    "sg:postcode":"32803",
    "sg:province":"FL",
    "sg:tags":[
        "sculptor"
    ],
    "wof:name":"Chris Scala Studio Inc",
    "wof:placetype":"venue"
},
  "geometry": {"coordinates":[-81.372046,28.566251],"type":"Point"}
}