{
  "type": "Feature",
  "properties": {
    "addr:full":"5801 S Dale Mabry Hwy Tampa FL 33611",
    "addr:housenumber":"5801",
    "addr:postcode":"33611",
    "addr:street":"S Dale Mabry Hwy",
    "iso:country":"US",
    "sg:address":"5801 S Dale Mabry Hwy",
    "sg:city":"Tampa",
    "sg:classifiers":[
        {
            "category":"Food & Beverages",
            "subcategory":"Groceries & Convenience Stores",
            "type":"Retail Goods"
        }
    ],
    "sg:phone":"+1 813 831 4876",
    "sg:postcode":"33611",
    "sg:province":"FL",
    "sg:tags":[
        "grocer"
    ],
    "wof:name":"Discount Food Mart",
    "wof:placetype":"venue"
},
  "geometry": {"coordinates":[-82.50649199999999,27.881991],"type":"Point"}
}