{
  "type": "Feature",
  "properties": {
    "addr:full":"6137 Bass Hwy Saint Cloud FL 34771",
    "addr:housenumber":"6137",
    "addr:postcode":"34771",
    "addr:street":"Bass Hwy",
    "iso:country":"US",
    "sg:address":"6137 Bass Hwy",
    "sg:city":"Saint Cloud",
    "sg:classifiers":[
        {
            "category":"Shopping",
            "type":"Retail Goods"
        }
    ],
    "sg:phone":"+1 407 957 1015",
    "sg:postcode":"34771",
    "sg:province":"FL",
    "sg:tags":[
        "merchandise"
    ],
    "wof:name":"Phone Center",
    "wof:placetype":"venue"
},
  "geometry": {"coordinates":[-81.190594,28.258306],"type":"Point"}
}