{
  "type": "Feature",
  "properties": {
    "iso:country":"US",
    "sg:address":"20803 Biscayne Blvd",
    "sg:city":"Miami",
    "sg:classifiers":[
        {
            "category":"Professional",
            "subcategory":"Lawyer & Legal Services",
            "type":"Services"
        }
    ],
    "sg:phone":"+1 305 935 6888",
    "sg:postcode":"33180",
    "sg:province":"FL",
    "sg:tags":[
        "attorney",
        "law",
        "commercial"
    ],
    "wof:name":"Grisales-Racini, Oscar",
    "wof:placetype":"venue"
},
  "geometry": {"coordinates":[-80.14494999999999,25.967931],"type":"Point"}
}