{
  "type": "Feature",
  "properties": {
    "iso:country":"US",
    "sg:address":"1075 42nd St NW",
    "sg:city":"Winter Haven",
    "sg:classifiers":[
        {
            "category":"Retail",
            "subcategory":"Auto Rental",
            "type":"Services"
        }
    ],
    "sg:phone":"+1 863 967 6607",
    "sg:postcode":"33881",
    "sg:province":"FL",
    "sg:tags":[
        "truck",
        "trailer",
        "utility"
    ],
    "wof:name":"Ryder",
    "wof:placetype":"venue"
},
  "geometry": {"coordinates":[-81.77603999999999,28.034707],"type":"Point"}
}