{
  "type": "Feature",
  "properties": {
    "iso:country":"US",
    "sg:address":"10481 SW 62nd St",
    "sg:city":"Miami",
    "sg:classifiers":[
        {
            "category":"Personal",
            "type":"Services"
        }
    ],
    "sg:phone":"+1 305 260 9193",
    "sg:postcode":"33173",
    "sg:province":"FL",
    "sg:tags":[
        "party",
        "planning",
        "event"
    ],
    "wof:name":"Paradise Party Rental",
    "wof:placetype":"venue"
},
  "geometry": {"coordinates":[-80.36439799999999,25.710625],"type":"Point"}
}