{
  "type": "Feature",
  "properties": {
    "iso:country":"US",
    "sg:address":"2300 Jetport Dr",
    "sg:city":"Orlando",
    "sg:classifiers":[
        {
            "category":"Manufacturing",
            "subcategory":"Watercraft",
            "type":"Manufacturing & Wholesale Goods"
        }
    ],
    "sg:phone":"+1 407 851 4360",
    "sg:postcode":"32809",
    "sg:province":"FL",
    "sg:tags":[
        "boat"
    ],
    "sg:website":"www.regalboats.com",
    "wof:name":"Regal Marine Industries Inc",
    "wof:placetype":"venue"
},
  "geometry": {"coordinates":[-81.350883,28.449762],"type":"Point"}
}