{
  "type": "Feature",
  "properties": {
    "iso:country":"US",
    "sg:address":"1862 NW 54th Ave",
    "sg:city":"Margate",
    "sg:classifiers":[
        {
            "category":"Retail",
            "subcategory":"Repair Shop",
            "type":"Services"
        },
        {
            "category":"Building & Trades",
            "subcategory":"Plumbing",
            "type":"Services"
        }
    ],
    "sg:phone":"+1 954 969 7722",
    "sg:postcode":"33063",
    "sg:province":"FL",
    "sg:tags":[
        "appliance",
        "contractor"
    ],
    "wof:name":"Cool Zone Air Conditioning",
    "wof:placetype":"venue"
},
  "geometry": {"coordinates":[-80.198115,26.251044],"type":"Point"}
}