{
  "type": "Feature",
  "properties": {
    "addr:full":"1702 S Washington Ave Titusville FL 32780",
    "addr:housenumber":"1702",
    "addr:postcode":"32780",
    "addr:street":"S Washington Ave",
    "iso:country":"US",
    "sg:address":"1702 S Washington Ave",
    "sg:city":"Titusville",
    "sg:classifiers":[
        {
            "category":"Real Estate",
            "subcategory":"Developer",
            "type":"Services"
        }
    ],
    "sg:phone":"+1 321 267 5504",
    "sg:postcode":"32780",
    "sg:province":"FL",
    "wof:name":"6969 Development Corporation",
    "wof:placetype":"venue"
},
  "geometry": {"coordinates":[-80.805019,28.594835],"type":"Point"}
}