{
  "type": "Feature",
  "properties": {
    "iso:country":"US",
    "sg:address":"520 Nixon St",
    "sg:city":"Jacksonville",
    "sg:classifiers":[
        {
            "category":"Retail",
            "subcategory":"Auto Repair",
            "type":"Services"
        }
    ],
    "sg:phone":"+1 904 384 0074",
    "sg:postcode":"32204",
    "sg:province":"FL",
    "sg:tags":[
        "repairing",
        "automobile"
    ],
    "wof:name":"Fms Maintenance",
    "wof:placetype":"venue"
},
  "geometry": {"coordinates":[-81.694552,30.323],"type":"Point"}
}