{
  "type": "Feature",
  "properties": {
    "addr:full":"8000 Lake Underhill Rd Orlando FL 32822",
    "addr:housenumber":"8000",
    "addr:postcode":"32822",
    "addr:street":"Lake Underhill Rd",
    "iso:country":"US",
    "sg:address":"8000 Lake Underhill Rd",
    "sg:city":"Orlando",
    "sg:classifiers":[
        {
            "category":"Wholesale",
            "subcategory":"Medical Equipment & Supplies",
            "type":"Manufacturing & Wholesale Goods"
        },
        {
            "category":"Shopping",
            "subcategory":"Pharmacy",
            "type":"Retail Goods"
        }
    ],
    "sg:phone":"+1 407 658 1045",
    "sg:postcode":"32822",
    "sg:province":"FL",
    "sg:tags":[
        "health",
        "aid",
        "home",
        "first",
        "care"
    ],
    "sg:website":"http://www.walgreens.com",
    "wof:name":"Walgreen Drug Stores",
    "wof:placetype":"venue"
},
  "geometry": {"coordinates":[-81.27715000000001,28.53916],"type":"Point"}
}