{
  "type": "Feature",
  "properties": {
    "addr:full":"4151 Lake Worth Rd Lake Worth FL 33461",
    "addr:housenumber":"4151",
    "addr:postcode":"33461",
    "addr:street":"Lake Worth Rd",
    "iso:country":"US",
    "sg:address":"4151 Lake Worth Rd",
    "sg:city":"Lake Worth",
    "sg:classifiers":[
        {
            "category":"Government",
            "subcategory":"Post Office",
            "type":"Public Place"
        }
    ],
    "sg:phone":"+1 561 357 7864",
    "sg:postcode":"33461",
    "sg:province":"FL",
    "wof:name":"US Post Office",
    "wof:placetype":"venue"
},
  "geometry": {"coordinates":[-80.105007,26.617939],"type":"Point"}
}