{
  "type": "Feature",
  "properties": {
    "addr:full":"798 W Lumsden Rd Brandon FL 33511",
    "addr:housenumber":"798",
    "addr:postcode":"33511",
    "addr:street":"W Lumsden Rd",
    "iso:country":"US",
    "sg:address":"798 W Lumsden Rd",
    "sg:city":"Brandon",
    "sg:classifiers":[
        {
            "category":"Retail",
            "subcategory":"Laundry & Dry Cleaning",
            "type":"Services"
        }
    ],
    "sg:phone":"+1 813 653 9611",
    "sg:postcode":"33511",
    "sg:province":"FL",
    "sg:tags":[
        "cleaners"
    ],
    "wof:name":"Signature Cleaners",
    "wof:placetype":"venue"
},
  "geometry": {"coordinates":[-82.296117,27.923187],"type":"Point"}
}