{
  "type": "Feature",
  "properties": {
    "addr:full":"6100 W Colonial Dr Orlando FL 32808",
    "addr:housenumber":"6100",
    "addr:postcode":"32808",
    "addr:street":"W Colonial Dr",
    "iso:country":"US",
    "sg:address":"6100 W Colonial Dr",
    "sg:city":"Orlando",
    "sg:classifiers":[
        {
            "category":"Building & Trades",
            "subcategory":"Equipment Rental",
            "type":"Services"
        }
    ],
    "sg:phone":"+1 407 295 1944",
    "sg:postcode":"32808",
    "sg:province":"FL",
    "sg:tags":[
        "appliance"
    ],
    "wof:name":"Rent Way",
    "wof:placetype":"venue"
},
  "geometry": {"coordinates":[-81.465569,28.552148],"type":"Point"}
}