{
  "type": "Feature",
  "properties": {
    "addr:full":"425 Cypress Creek Cir Oldsmar FL 34677",
    "addr:housenumber":"425",
    "addr:postcode":"34677",
    "addr:street":"Cypress Creek Cir",
    "iso:country":"US",
    "sg:address":"425 Cypress Creek Cir",
    "sg:city":"Oldsmar",
    "sg:classifiers":[
        {
            "category":"Real Estate",
            "subcategory":"Real Estate Agent",
            "type":"Services"
        }
    ],
    "sg:phone":"+1 727 789 2866",
    "sg:postcode":"34677",
    "sg:province":"FL",
    "sg:tags":[
        "consultant"
    ],
    "wof:name":"Seacom Corp",
    "wof:placetype":"venue"
},
  "geometry": {"coordinates":[-82.70114599999999,28.063937],"type":"Point"}
}