{
  "type": "Feature",
  "properties": {
    "iso:country":"US",
    "sg:address":"4461 NE 30th Ave",
    "sg:city":"Pompano Beach",
    "sg:classifiers":[
        {
            "category":"Building & Trades",
            "subcategory":"Construction",
            "type":"Services"
        }
    ],
    "sg:phone":"+1 954 341 2448",
    "sg:postcode":"33064",
    "sg:province":"FL",
    "sg:tags":[
        "contractor"
    ],
    "wof:name":"Super Gutter & Screen",
    "wof:placetype":"venue"
},
  "geometry": {"coordinates":[-80.083004,26.286305],"type":"Point"}
}