{
  "type": "Feature",
  "properties": {
    "iso:country":"US",
    "sg:address":"7349 NW 54th St",
    "sg:city":"Miami",
    "sg:classifiers":[
        {
            "category":"Wholesale",
            "subcategory":"Machinery & Supplies",
            "type":"Manufacturing & Wholesale Goods"
        }
    ],
    "sg:phone":"+1 305 882 1139",
    "sg:postcode":"33166",
    "sg:province":"FL",
    "sg:tags":[
        "instrument",
        "aircraft",
        "avionics",
        "broker"
    ],
    "wof:name":"Aviaplus, Inc",
    "wof:placetype":"venue"
},
  "geometry": {"coordinates":[-80.31736100000001,25.822557],"type":"Point"}
}