{
  "type": "Feature",
  "properties": {
    "addr:full":"2704 Bee Ridge Rd Sarasota FL 34239",
    "addr:housenumber":"2704",
    "addr:postcode":"34239",
    "addr:street":"Bee Ridge Rd",
    "iso:country":"US",
    "sg:address":"2704 Bee Ridge Rd",
    "sg:city":"Sarasota",
    "sg:classifiers":[
        {
            "category":"Real Estate",
            "subcategory":"Real Estate Services",
            "type":"Services"
        }
    ],
    "sg:phone":"+1 941 923 2291",
    "sg:postcode":"34239",
    "sg:province":"FL",
    "sg:tags":[
        "company",
        "title"
    ],
    "wof:name":"Luhlnam Title Of Sarasota Lllp",
    "wof:placetype":"venue"
},
  "geometry": {"coordinates":[-82.514235,27.298758],"type":"Point"}
}