{
  "type": "Feature",
  "properties": {
    "iso:country":"US",
    "sg:address":"7841 SW 180th St",
    "sg:city":"Miami",
    "sg:classifiers":[
        {
            "category":"Insurance",
            "subcategory":"Hazard Insurance",
            "type":"Services"
        }
    ],
    "sg:phone":"+1 305 971 8737",
    "sg:postcode":"33157",
    "sg:province":"FL",
    "sg:tags":[
        "carrier"
    ],
    "wof:name":"Island Wide Marine",
    "wof:placetype":"venue"
},
  "geometry": {"coordinates":[-80.318939,25.603539],"type":"Point"}
}