{
  "type": "Feature",
  "properties": {
    "iso:country":"US",
    "sg:address":"15290 NW 34th Ave",
    "sg:city":"Opa Locka",
    "sg:classifiers":[
        {
            "category":"Manufacturing",
            "subcategory":"Tools & Machinery",
            "type":"Manufacturing & Wholesale Goods"
        }
    ],
    "sg:phone":"+1 305 688 1750",
    "sg:postcode":"33054",
    "sg:province":"FL",
    "sg:tags":[
        "machine",
        "shop"
    ],
    "wof:name":"Fabco Manufacturing Corp",
    "wof:placetype":"venue"
},
  "geometry": {"coordinates":[-80.25716,25.91209],"type":"Point"}
}