{
  "type": "Feature",
  "properties": {
    "iso:country":"US",
    "sg:address":"202 Loruna Dr",
    "sg:city":"Gulf Breeze",
    "sg:classifiers":[
        {
            "category":"Manufacturing",
            "subcategory":"Printing",
            "type":"Manufacturing & Wholesale Goods"
        }
    ],
    "sg:phone":"+1 850 934 0680",
    "sg:postcode":"32561",
    "sg:province":"FL",
    "sg:tags":[
        "i",
        "lithographic",
        "commercial",
        "typesetting"
    ],
    "wof:name":"A 2 Z Graphics",
    "wof:placetype":"venue"
},
  "geometry": {"coordinates":[-87.176299,30.3616],"type":"Point"}
}