{
  "type": "Feature",
  "properties": {
    "addr:full":"7108 Fairway Dr Palm Beach Gdns FL 33418",
    "addr:housenumber":"7108",
    "addr:postcode":"33418",
    "addr:street":"Fairway Dr Palm",
    "iso:country":"US",
    "sg:address":"7108 Fairway Dr",
    "sg:city":"Palm Beach Gdns",
    "sg:classifiers":[
        {
            "category":"Banks & Credit Unions",
            "subcategory":"Investment Brokerage",
            "type":"Services"
        }
    ],
    "sg:phone":"+1 561 622 1098",
    "sg:postcode":"33418",
    "sg:province":"FL",
    "sg:tags":[
        "advisory",
        "financial"
    ],
    "wof:name":"Raymond James & Assoc Inc",
    "wof:placetype":"venue"
},
  "geometry": {"coordinates":[-80.13352399999999,26.836697],"type":"Point"}
}