{
  "type": "Feature",
  "properties": {
    "addr:full":"13041 SW 200th Ter Miami FL 33177",
    "addr:housenumber":"13041",
    "addr:postcode":"33177",
    "addr:street":"Sw 200Th Ter",
    "iso:country":"US",
    "sg:address":"13041 SW 200th Ter",
    "sg:city":"Miami",
    "sg:classifiers":[
        {
            "category":"Retail",
            "subcategory":"Auto Repair",
            "type":"Services"
        }
    ],
    "sg:phone":"+1 305 232 5700",
    "sg:postcode":"33177",
    "sg:province":"FL",
    "sg:tags":[
        "glass",
        "coating",
        "tinting"
    ],
    "wof:name":"Fifty Dollar Window Tinting",
    "wof:placetype":"venue"
},
  "geometry": {"coordinates":[-80.403415,25.579103],"type":"Point"}
}