{
  "type": "Feature",
  "properties": {
    "addr:full":"1610 N Hercules Ave Ste I Clearwater FL 33765",
    "addr:housenumber":"1610",
    "addr:postcode":"33765",
    "addr:street":"N Hercules Ave Ste I",
    "iso:country":"US",
    "sg:address":"1610 N Hercules Ave Ste I",
    "sg:city":"Clearwater",
    "sg:classifiers":[
        {
            "category":"Wholesale",
            "subcategory":"Painting Supplies",
            "type":"Manufacturing & Wholesale Goods"
        },
        {
            "category":"Shopping",
            "subcategory":"Crafts & Fabrics",
            "type":"Retail Goods"
        }
    ],
    "sg:phone":"+1 727 447 1981",
    "sg:postcode":"33765",
    "sg:province":"FL",
    "sg:tags":[
        "goods-wholesale",
        "art",
        "manufacturer"
    ],
    "wof:name":"The Big Game Company",
    "wof:placetype":"venue"
},
  "geometry": {"coordinates":[-82.754605,27.981348],"type":"Point"}
}