{
  "type": "Feature",
  "properties": {
    "addr:full":"7045 Beracasa Way Boca Raton FL 33433",
    "addr:housenumber":"7045",
    "addr:postcode":"33433",
    "addr:street":"Beracasa Way",
    "iso:country":"US",
    "sg:address":"7045 Beracasa Way",
    "sg:city":"Boca Raton",
    "sg:classifiers":[
        {
            "category":"Cinema",
            "subcategory":"Movie Rental",
            "type":"Entertainment"
        }
    ],
    "sg:phone":"+1 561 750 1005",
    "sg:postcode":"33433",
    "sg:province":"FL",
    "sg:tags":[
        "video",
        "tape"
    ],
    "wof:name":"Blockbuster",
    "wof:placetype":"venue"
},
  "geometry": {"coordinates":[-80.155964,26.351056],"type":"Point"}
}