{
  "type": "Feature",
  "properties": {
    "iso:country":"US",
    "sg:address":"1240 Providence Blvd",
    "sg:city":"Deltona",
    "sg:classifiers":[
        {
            "category":"Shopping",
            "type":"Retail Goods"
        }
    ],
    "sg:phone":"+1 386 574 0344",
    "sg:postcode":"32725",
    "sg:province":"FL",
    "sg:tags":[
        "art",
        "gallery",
        "dealer"
    ],
    "wof:name":"Dicount Art & Framing",
    "wof:placetype":"venue"
},
  "geometry": {"coordinates":[-81.24069900000001,28.882909],"type":"Point"}
}