{
  "type": "Feature",
  "properties": {
    "addr:full":"1680 Metropolitan Cir Tallahassee FL 32308",
    "addr:housenumber":"1680",
    "addr:postcode":"32308",
    "addr:street":"Metropolitan Cir",
    "iso:country":"US",
    "sg:address":"1680 Metropolitan Cir",
    "sg:city":"Tallahassee",
    "sg:classifiers":[
        {
            "category":"Retail",
            "subcategory":"Funeral Services",
            "type":"Services"
        }
    ],
    "sg:phone":"+1 850 591 8012",
    "sg:postcode":"32308",
    "sg:province":"FL",
    "sg:tags":[
        "director"
    ],
    "wof:name":"Alderwoods",
    "wof:placetype":"venue"
},
  "geometry": {"coordinates":[-84.250946,30.498307],"type":"Point"}
}