{
  "type": "Feature",
  "properties": {
    "iso:country":"US",
    "sg:address":"2271 Weston Ln",
    "sg:city":"Orlando",
    "sg:classifiers":[
        {
            "category":"Insurance",
            "subcategory":"Insurance Agent",
            "type":"Services"
        },
        {
            "category":"Insurance",
            "subcategory":"Hazard Insurance",
            "type":"Services"
        },
        {
            "category":"Insurance",
            "subcategory":"Title Insurance",
            "type":"Services"
        }
    ],
    "sg:phone":"+1 407 219 3389",
    "sg:postcode":"32810",
    "sg:province":"FL",
    "sg:tags":[
        "property",
        "casualty",
        "homeowner"
    ],
    "wof:name":"T Ervin",
    "wof:placetype":"venue"
},
  "geometry": {"coordinates":[-81.41300200000001,28.612941],"type":"Point"}
}