{
  "type": "Feature",
  "properties": {
    "iso:country":"US",
    "sg:address":"426 Grand Royal Cir",
    "sg:city":"Winter Garden",
    "sg:classifiers":[
        {
            "category":"Shopping",
            "subcategory":"Catalog Store",
            "type":"Retail Goods"
        }
    ],
    "sg:phone":"+1 407 654 9806",
    "sg:postcode":"34787",
    "sg:province":"FL",
    "sg:tags":[
        "mail",
        "house"
    ],
    "wof:name":"Techway Inc",
    "wof:placetype":"venue"
},
  "geometry": {"coordinates":[-81.58117300000001,28.554218],"type":"Point"}
}