{
  "type": "Feature",
  "properties": {
    "iso:country":"US",
    "sg:address":"7550 Hinson St Apt 9D",
    "sg:city":"Orlando",
    "sg:classifiers":[
        {
            "category":"Real Estate",
            "subcategory":"Real Estate Services",
            "type":"Services"
        }
    ],
    "sg:phone":"+1 407 351 0440",
    "sg:postcode":"32819",
    "sg:province":"FL",
    "sg:tags":[
        "management",
        "condominium"
    ],
    "wof:name":"Condominium Association",
    "wof:placetype":"venue"
},
  "geometry": {"coordinates":[-81.486277,28.451813],"type":"Point"}
}