{
  "type": "Feature",
  "properties": {
    "iso:country":"US",
    "sg:address":"272 W New England Ave",
    "sg:city":"Winter Park",
    "sg:classifiers":[
        {
            "category":"Personal",
            "subcategory":"Beauty Salon",
            "type":"Services"
        }
    ],
    "sg:phone":"+1 407 599 9493",
    "sg:postcode":"32789",
    "sg:province":"FL",
    "sg:tags":[
        "shop"
    ],
    "wof:name":"Ricci Capricci Salon",
    "wof:placetype":"venue"
},
  "geometry": {"coordinates":[-81.35426699999999,28.595809],"type":"Point"}
}