{
  "type": "Feature",
  "properties": {
    "iso:country":"US",
    "sg:address":"17711 76th St",
    "sg:city":"Live Oak",
    "sg:classifiers":[
        {
            "category":"Retail",
            "subcategory":"Animal Services",
            "type":"Services"
        }
    ],
    "sg:phone":"+1 386 362 6569",
    "sg:postcode":"32060",
    "sg:province":"FL",
    "wof:name":"Bluebird Farm",
    "wof:placetype":"venue"
},
  "geometry": {"coordinates":[-83.117492,30.312043],"type":"Point"}
}