{
  "type": "Feature",
  "properties": {
    "addr:full":"439 Lakeview Dr Fort Lauderdale FL 33326",
    "addr:housenumber":"439",
    "addr:postcode":"33326",
    "addr:street":"Lakeview Dr",
    "iso:country":"US",
    "sg:address":"439 Lakeview Dr",
    "sg:city":"Fort Lauderdale",
    "sg:classifiers":[
        {
            "category":"Professional",
            "type":"Services"
        }
    ],
    "sg:phone":"+1 954 389 5043",
    "sg:postcode":"33326",
    "sg:province":"FL",
    "wof:name":"Decoware Inc",
    "wof:placetype":"venue"
},
  "geometry": {"coordinates":[-80.384486,26.120619],"type":"Point"}
}