{
  "type": "Feature",
  "properties": {
    "iso:country":"US",
    "sg:address":"209 Dunlawton Ave",
    "sg:city":"Daytona Beach",
    "sg:classifiers":[
        {
            "category":"Real Estate",
            "subcategory":"Real Estate Agent",
            "type":"Services"
        }
    ],
    "sg:phone":"+1 386 788 8007",
    "sg:postcode":"32127",
    "sg:province":"FL",
    "wof:name":"Newcertifiedappraisalcom",
    "wof:placetype":"venue"
},
  "geometry": {"coordinates":[-80.98932000000001,29.143206],"type":"Point"}
}