{
  "type": "Feature",
  "properties": {
    "addr:full":"1820 Tamiami Trl S Venice FL 34293",
    "addr:housenumber":"1820",
    "addr:postcode":"34293",
    "addr:street":"Tamiami Trl S",
    "iso:country":"US",
    "sg:address":"1820 Tamiami Trl S",
    "sg:city":"Venice",
    "sg:classifiers":[
        {
            "category":"Professional",
            "type":"Services"
        },
        {
            "category":"Restaurant",
            "type":"Food & Drink"
        },
        {
            "category":"Fast Food",
            "type":"Food & Drink"
        }
    ],
    "sg:phone":"+1 941 493 9716",
    "sg:postcode":"34293",
    "sg:province":"FL",
    "sg:tags":[
        "delivery",
        "take",
        "pizza"
    ],
    "sg:website":"http://www.pizzahut.com",
    "wof:name":"Pizza Hut",
    "wof:placetype":"venue"
},
  "geometry": {"coordinates":[-82.41957499999999,27.066347],"type":"Point"}
}