{
  "type": "Feature",
  "properties": {
    "addr:full":"1111 W Lee St Pensacola FL 32501",
    "addr:housenumber":"1111",
    "addr:postcode":"32501",
    "addr:street":"W Lee St",
    "iso:country":"US",
    "sg:address":"1111 W Lee St",
    "sg:city":"Pensacola",
    "sg:classifiers":[
        {
            "category":"Place Of Worship",
            "type":"Public Place"
        }
    ],
    "sg:phone":"+1 850 434 6828",
    "sg:postcode":"32501",
    "sg:province":"FL",
    "sg:tags":[
        "church"
    ],
    "wof:name":"Ultra-God Enterprises",
    "wof:placetype":"venue"
},
  "geometry": {"coordinates":[-87.23205400000001,30.426596],"type":"Point"}
}