{
  "type": "Feature",
  "properties": {
    "iso:country":"US",
    "sg:address":"5286 Seminole Blvd",
    "sg:city":"St Petersburg",
    "sg:classifiers":[
        {
            "category":"Shopping",
            "subcategory":"Florist",
            "type":"Retail Goods"
        }
    ],
    "sg:phone":"+1 727 391 9981",
    "sg:postcode":"33708",
    "sg:province":"FL",
    "sg:website":"www.beachfloristinc.com",
    "wof:name":"Beach Florist Inc",
    "wof:placetype":"venue"
},
  "geometry": {"coordinates":[-82.78694400000001,27.820218],"type":"Point"}
}