{
  "type": "Feature",
  "properties": {
    "iso:country":"US",
    "sg:address":"705 Drywood Ave",
    "sg:city":"Fern Park",
    "sg:classifiers":[
        {
            "category":"Retail",
            "subcategory":"Laundry & Dry Cleaning",
            "type":"Services"
        }
    ],
    "sg:phone":"+1 407 332 0936",
    "sg:postcode":"32730",
    "sg:province":"FL",
    "sg:tags":[
        "repairing",
        "rug",
        "carpet"
    ],
    "wof:name":"Jerry Louden Carpet Repair",
    "wof:placetype":"venue"
},
  "geometry": {"coordinates":[-81.342479,28.647246],"type":"Point"}
}