{
  "type": "Feature",
  "properties": {
    "addr:full":"225 S SR-7 Margate FL 33068",
    "addr:housenumber":"225",
    "addr:postcode":"33068",
    "addr:street":"S Sr-7 Margate",
    "iso:country":"US",
    "sg:address":"225 S SR-7",
    "sg:city":"Margate",
    "sg:classifiers":[
        {
            "category":"Restaurant",
            "type":"Food & Drink"
        }
    ],
    "sg:menulink":"http://www.allmenus.com/fl/margate/163603-rallys/menu/",
    "sg:phone":"+1 954 972 1755",
    "sg:postcode":"33068",
    "sg:province":"FL",
    "sg:tags":[
        "sandwich",
        "dog",
        "burger",
        "hot",
        "wrap",
        "american"
    ],
    "wof:name":"Rally's",
    "wof:placetype":"venue"
},
  "geometry": {"coordinates":[-80.204661,26.228147],"type":"Point"}
}