{
  "type": "Feature",
  "properties": {
    "addr:full":"2427 E Mall Dr Fort Myers FL 33901",
    "addr:housenumber":"2427",
    "addr:postcode":"33901",
    "addr:street":"E Mall Dr",
    "iso:country":"US",
    "sg:address":"2427 E Mall Dr",
    "sg:city":"Fort Myers",
    "sg:classifiers":[
        {
            "category":"Real Estate",
            "subcategory":"Real Estate Operator",
            "type":"Services"
        }
    ],
    "sg:phone":"+1 239 936 2250",
    "sg:postcode":"33901",
    "sg:province":"FL",
    "sg:tags":[
        "building",
        "apartment"
    ],
    "wof:name":"Edison Point APT",
    "wof:placetype":"venue"
},
  "geometry": {"coordinates":[-81.864419,26.599943],"type":"Point"}
}