{
  "type": "Feature",
  "properties": {
    "addr:full":"4999 NW 9th Ave Fort Lauderdale FL 33309",
    "addr:housenumber":"4999",
    "addr:postcode":"33309",
    "addr:street":"Nw 9Th Ave",
    "iso:country":"US",
    "sg:address":"4999 NW 9th Ave",
    "sg:city":"Fort Lauderdale",
    "sg:classifiers":[
        {
            "category":"Autos & Motor Vehicles",
            "subcategory":"Fuel & Gas Station",
            "type":"Retail Goods"
        }
    ],
    "sg:phone":"+1 954 491 0094",
    "sg:postcode":"33309",
    "sg:province":"FL",
    "sg:tags":[
        "station",
        "gasoline"
    ],
    "wof:name":"Powerline Amoco",
    "wof:placetype":"venue"
},
  "geometry": {"coordinates":[-80.155146,26.187853],"type":"Point"}
}