{
  "type": "Feature",
  "properties": {
    "iso:country":"US",
    "sg:address":"5005 N Wickham Rd",
    "sg:city":"Melbourne",
    "sg:classifiers":[
        {
            "category":"Insurance",
            "subcategory":"Insurance Agent",
            "type":"Services"
        }
    ],
    "sg:phone":"+1 321 751 1677",
    "sg:postcode":"32940",
    "sg:province":"FL",
    "wof:name":"A Professional Insurance",
    "wof:placetype":"venue"
},
  "geometry": {"coordinates":[-80.671893,28.197027],"type":"Point"}
}