{
  "type": "Feature",
  "properties": {
    "addr:full":"1070 E Indiantown Rd Jupiter FL 33477",
    "addr:housenumber":"1070",
    "addr:postcode":"33477",
    "addr:street":"E Indiantown Rd",
    "iso:country":"US",
    "sg:address":"1070 E Indiantown Rd",
    "sg:city":"Jupiter",
    "sg:classifiers":[
        {
            "category":"Shopping",
            "subcategory":"Used Merchandise",
            "type":"Retail Goods"
        }
    ],
    "sg:phone":"+1 561 575 3880",
    "sg:postcode":"33477",
    "sg:province":"FL",
    "sg:tags":[
        "junk"
    ],
    "wof:name":"Junk It",
    "wof:placetype":"venue"
},
  "geometry": {"coordinates":[-80.074648,26.933805],"type":"Point"}
}