{
  "type": "Feature",
  "properties": {
    "iso:country":"US",
    "sg:address":"995 Fish Hook Cv",
    "sg:city":"Bradenton",
    "sg:classifiers":[
        {
            "category":"Sports & Exercise",
            "subcategory":"Golf",
            "type":"Entertainment"
        }
    ],
    "sg:phone":"+1 941 744 9881",
    "sg:postcode":"34212",
    "sg:province":"FL",
    "sg:tags":[
        "courses-private"
    ],
    "wof:name":"Waterlefe Golf And River Club",
    "wof:placetype":"venue"
},
  "geometry": {"coordinates":[-82.44156700000001,27.516439],"type":"Point"}
}