{
  "type": "Feature",
  "properties": {
    "iso:country":"US",
    "sg:address":"51 Beal Pkwy NW",
    "sg:city":"Fort Walton Bch",
    "sg:classifiers":[
        {
            "category":"Professional",
            "subcategory":"Lawyer & Legal Services",
            "type":"Services"
        }
    ],
    "sg:phone":"+1 850 244 7104",
    "sg:postcode":"32548",
    "sg:province":"FL",
    "sg:tags":[
        "attorney"
    ],
    "wof:name":"Curtis Brannon Law Offices",
    "wof:placetype":"venue"
},
  "geometry": {"coordinates":[-86.613755,30.417589],"type":"Point"}
}