{
  "type": "Feature",
  "properties": {
    "iso:country":"US",
    "sg:address":"1210 SE 8th Ct",
    "sg:city":"Deerfield Beach",
    "sg:classifiers":[
        {
            "category":"Shopping",
            "subcategory":"Beauty & Cosmetics",
            "type":"Retail Goods"
        }
    ],
    "sg:phone":"+1 954 698 6558",
    "sg:postcode":"33441",
    "sg:province":"FL",
    "sg:tags":[
        "merchandise"
    ],
    "wof:name":"World Wide Perfume Oils Inc",
    "wof:placetype":"venue"
},
  "geometry": {"coordinates":[-80.08696500000001,26.306636],"type":"Point"}
}