{
  "type": "Feature",
  "properties": {
    "iso:country":"US",
    "sg:address":"4330 Peppertree St",
    "sg:city":"Cocoa",
    "sg:classifiers":[
        {
            "category":"Autos & Motor Vehicles",
            "subcategory":"Auto Supplies",
            "type":"Retail Goods"
        }
    ],
    "sg:phone":"+1 321 242 9644",
    "sg:postcode":"32926",
    "sg:province":"FL",
    "sg:tags":[
        "automobile",
        "parts"
    ],
    "wof:name":"Wizard Automotive",
    "wof:placetype":"venue"
},
  "geometry": {"coordinates":[-80.80986799999999,28.42872],"type":"Point"}
}