{
  "type": "Feature",
  "properties": {
    "iso:country":"US",
    "sg:address":"1551 N Franklin St",
    "sg:city":"Tampa",
    "sg:classifiers":[
        {
            "category":"Social Services",
            "type":"Services"
        }
    ],
    "sg:phone":"+1 813 229 1288",
    "sg:postcode":"33602",
    "sg:province":"FL",
    "sg:tags":[
        "organization",
        "welfare"
    ],
    "wof:name":"Church Women United Of Tampa",
    "wof:placetype":"venue"
},
  "geometry": {"coordinates":[-82.46009599999999,27.958295],"type":"Point"}
}