{
  "type": "Feature",
  "properties": {
    "iso:country":"US",
    "sg:address":"8811 NW 23rd Ave",
    "sg:city":"Miami",
    "sg:classifiers":[
        {
            "category":"Professional",
            "subcategory":"Business Services",
            "type":"Services"
        }
    ],
    "sg:phone":"+1 305 418 5035",
    "sg:postcode":"33147",
    "sg:province":"FL",
    "sg:tags":[
        "delivery",
        "courier"
    ],
    "wof:name":"Heat Express Inc",
    "wof:placetype":"venue"
},
  "geometry": {"coordinates":[-80.23589200000001,25.854625],"type":"Point"}
}