{
  "type": "Feature",
  "properties": {
    "addr:full":"103 Westward Dr Miami FL 33166",
    "addr:housenumber":"103",
    "addr:postcode":"33166",
    "addr:street":"Westward Dr",
    "iso:country":"US",
    "sg:address":"103 Westward Dr",
    "sg:city":"Miami",
    "sg:classifiers":[
        {
            "category":"Arts & Performance",
            "subcategory":"Theater",
            "type":"Entertainment"
        }
    ],
    "sg:phone":"+1 305 885 5200",
    "sg:postcode":"33166",
    "sg:province":"FL",
    "sg:tags":[
        "production",
        "music"
    ],
    "wof:name":"Turis Music Enterprise Inc",
    "wof:placetype":"venue"
},
  "geometry": {"coordinates":[-80.284316,25.8212],"type":"Point"}
}