{
  "type": "Feature",
  "properties": {
    "iso:country":"US",
    "sg:address":"356 SW N Quick Cir",
    "sg:city":"Port St Lucie",
    "sg:classifiers":[
        {
            "category":"Building & Trades",
            "subcategory":"Electrical",
            "type":"Services"
        }
    ],
    "sg:phone":"+1 772 785 6100",
    "sg:postcode":"34953",
    "sg:province":"FL",
    "sg:tags":[
        "electric",
        "contractor"
    ],
    "wof:name":"Medlin Electric",
    "wof:placetype":"venue"
},
  "geometry": {"coordinates":[-80.36032899999999,27.216532],"type":"Point"}
}