{
  "type": "Feature",
  "properties": {
    "iso:country":"US",
    "sg:address":"5507 S Congress Ave",
    "sg:city":"Lake Worth",
    "sg:classifiers":[
        {
            "category":"Education",
            "subcategory":"Special Training",
            "type":"Public Place"
        }
    ],
    "sg:phone":"+1 561 304 3466",
    "sg:postcode":"33462",
    "sg:province":"FL",
    "sg:tags":[
        "center"
    ],
    "wof:name":"Medvance Institute",
    "wof:placetype":"venue"
},
  "geometry": {"coordinates":[-80.092399,26.595398],"type":"Point"}
}