{
  "type": "Feature",
  "properties": {
    "iso:country":"US",
    "sg:address":"6425 Highway 90",
    "sg:city":"Milton",
    "sg:classifiers":[
        {
            "category":"Manufacturing",
            "subcategory":"Rubber & Plastics",
            "type":"Manufacturing & Wholesale Goods"
        },
        {
            "category":"Autos & Motor Vehicles",
            "subcategory":"Auto Supplies",
            "type":"Retail Goods"
        },
        {
            "category":"Retail",
            "subcategory":"Auto Repair",
            "type":"Services"
        }
    ],
    "sg:phone":"+1 850 623 2236",
    "sg:postcode":"32570",
    "sg:province":"FL",
    "sg:tags":[
        "recap",
        "retread",
        "tires-wholesale",
        "tire",
        "manufacturer"
    ],
    "sg:website":"http://www.coopertire.com/html/",
    "wof:name":"Eagle Tire Service Center",
    "wof:placetype":"venue"
},
  "geometry": {"coordinates":[-87.054647,30.612776],"type":"Point"}
}