{
  "type": "Feature",
  "properties": {
    "iso:country":"US",
    "sg:address":"7200 Normandy Blvd",
    "sg:city":"Jacksonville",
    "sg:classifiers":[
        {
            "category":"Restaurant",
            "type":"Food & Drink"
        }
    ],
    "sg:menulink":"http://www.allmenus.com/fl/jacksonville/81259-papa-johns-pizza/menu/",
    "sg:phone":"+1 904 695 9300",
    "sg:postcode":"32205",
    "sg:province":"FL",
    "sg:tags":[
        "american",
        "pizza"
    ],
    "wof:name":"Papa John's Pizza",
    "wof:placetype":"venue"
},
  "geometry": {"coordinates":[-81.766002,30.29979],"type":"Point"}
}