{
  "type": "Feature",
  "properties": {
    "addr:full":"10641 N Kendall Dr Miami FL 33176",
    "addr:housenumber":"10641",
    "addr:postcode":"33176",
    "addr:street":"N Kendall Dr",
    "iso:country":"US",
    "sg:address":"10641 N Kendall Dr",
    "sg:city":"Miami",
    "sg:classifiers":[
        {
            "category":"Deli",
            "type":"Food & Drink"
        },
        {
            "category":"Food & Beverages",
            "subcategory":"Bakery",
            "type":"Retail Goods"
        }
    ],
    "sg:phone":"+1 305 595 8614",
    "sg:postcode":"33176",
    "sg:province":"FL",
    "sg:tags":[
        "sandwich"
    ],
    "wof:name":"Yglesias Cuban Cafe Corp",
    "wof:placetype":"venue"
},
  "geometry": {"coordinates":[-80.365285,25.687165],"type":"Point"}
}