{
  "type": "Feature",
  "properties": {
    "iso:country":"US",
    "sg:address":"4451 Pine Forest Rd",
    "sg:city":"Milton",
    "sg:classifiers":[
        {
            "category":"Organizations",
            "subcategory":"Membership Organization",
            "type":"Services"
        },
        {
            "category":"Government",
            "subcategory":"Office",
            "type":"Public Place"
        }
    ],
    "sg:phone":"+1 850 626 1827",
    "sg:postcode":"32583",
    "sg:province":"FL",
    "sg:tags":[
        "executive"
    ],
    "sg:website":"www.santarosa.fl.gov",
    "wof:name":"Santa Rosa County Animal Svcs",
    "wof:placetype":"venue"
},
  "geometry": {"coordinates":[-87.069159,30.596788],"type":"Point"}
}