{
  "type": "Feature",
  "properties": {
    "addr:full":"99 NW 183rd St Ste 110 Miami FL 33169",
    "addr:housenumber":"99",
    "addr:postcode":"33169",
    "addr:street":"Nw 183Rd St Ste 110",
    "iso:country":"US",
    "sg:address":"99 NW 183rd St Ste 110",
    "sg:city":"Miami",
    "sg:classifiers":[
        {
            "category":"Community Center",
            "subcategory":"Senior",
            "type":"Public Place"
        },
        {
            "category":"Social Services",
            "subcategory":"Adult Care",
            "type":"Services"
        }
    ],
    "sg:phone":"+1 305 654 3553",
    "sg:postcode":"33169",
    "sg:province":"FL",
    "sg:tags":[
        "counseling",
        "citizen"
    ],
    "wof:name":"Enhanced Elderly Care",
    "wof:placetype":"venue"
},
  "geometry": {"coordinates":[-80.20313299999999,25.94268],"type":"Point"}
}