{
  "type": "Feature",
  "properties": {
    "addr:full":"650 del Prado Blvd S Cape Coral FL 33990",
    "addr:housenumber":"650",
    "addr:postcode":"33990",
    "addr:street":"Del Prado Blvd S",
    "iso:country":"US",
    "sg:address":"650 del Prado Blvd S",
    "sg:city":"Cape Coral",
    "sg:classifiers":[
        {
            "category":"Health Services",
            "subcategory":"Doctor",
            "type":"Services"
        }
    ],
    "sg:phone":"+1 239 772 6630",
    "sg:postcode":"33990",
    "sg:province":"FL",
    "sg:tags":[
        "medical"
    ],
    "wof:name":"Womens Breast Health Center",
    "wof:placetype":"venue"
},
  "geometry": {"coordinates":[-81.940845,26.637263],"type":"Point"}
}