{
  "type": "Feature",
  "properties": {
    "iso:country":"US",
    "sg:address":"772 Brevity Ave NE",
    "sg:city":"Palm Bay",
    "sg:classifiers":[
        {
            "category":"Organizations",
            "subcategory":"Religious Organization",
            "type":"Services"
        }
    ],
    "sg:phone":"+1 321 953 3569",
    "sg:postcode":"32905",
    "sg:province":"FL",
    "wof:name":"Life Line Ministries Inc",
    "wof:placetype":"venue"
},
  "geometry": {"coordinates":[-80.619039,28.016719],"type":"Point"}
}