{
  "type": "Feature",
  "properties": {
    "iso:country":"US",
    "sg:address":"3911 W Waters Ave",
    "sg:city":"Tampa",
    "sg:classifiers":[
        {
            "category":"Personal",
            "type":"Services"
        }
    ],
    "sg:phone":"+1 813 935 3424",
    "sg:postcode":"33614",
    "sg:province":"FL",
    "sg:tags":[
        "consultant",
        "program",
        "health",
        "fitness"
    ],
    "wof:name":"Johnston Fitness Corp",
    "wof:placetype":"venue"
},
  "geometry": {"coordinates":[-82.508895,28.025526],"type":"Point"}
}