{
  "type": "Feature",
  "properties": {
    "iso:country":"US",
    "sg:address":"1025 W Moreno St",
    "sg:city":"Pensacola",
    "sg:classifiers":[
        {
            "category":"Restaurant",
            "type":"Food & Drink"
        }
    ],
    "sg:phone":"+1 850 434 6412",
    "sg:postcode":"32501",
    "sg:province":"FL",
    "sg:tags":[
        "eating"
    ],
    "wof:name":"Sunshine Garden Cafe",
    "wof:placetype":"venue"
},
  "geometry": {"coordinates":[-87.231804,30.428683],"type":"Point"}
}