{
  "type": "Feature",
  "properties": {
    "addr:full":"260 Crandon Blvd Key Biscayne FL 33149",
    "addr:housenumber":"260",
    "addr:postcode":"33149",
    "addr:street":"Crandon Blvd",
    "iso:country":"US",
    "sg:address":"260 Crandon Blvd",
    "sg:city":"Key Biscayne",
    "sg:classifiers":[
        {
            "category":"Shopping",
            "subcategory":"Bicycles & Sporting Goods",
            "type":"Retail Goods"
        },
        {
            "category":"Sports & Exercise",
            "subcategory":"Bicycle Rental",
            "type":"Entertainment"
        }
    ],
    "sg:phone":"+1 305 361 5555",
    "sg:postcode":"33149",
    "sg:province":"FL",
    "sg:tags":[
        "bike"
    ],
    "wof:name":"Key Biscayne Bicycle Rentals",
    "wof:placetype":"venue"
},
  "geometry": {"coordinates":[-80.163101,25.696501],"type":"Point"}
}