{
  "type": "Feature",
  "properties": {
    "iso:country":"US",
    "sg:address":"8079 SW 86th Ter",
    "sg:city":"Miami",
    "sg:classifiers":[
        {
            "category":"Shopping",
            "subcategory":"Books",
            "type":"Retail Goods"
        }
    ],
    "sg:phone":"+1 305 274 4697",
    "sg:postcode":"33143",
    "sg:province":"FL",
    "wof:name":"Afb Booksellers Inc",
    "wof:placetype":"venue"
},
  "geometry": {"coordinates":[-80.324584,25.68948],"type":"Point"}
}