{
  "type": "Feature",
  "properties": {
    "addr:full":"5105 Manatee Ave W Bradenton FL 34209",
    "addr:housenumber":"5105",
    "addr:postcode":"34209",
    "addr:street":"Manatee Ave W",
    "iso:country":"US",
    "sg:address":"5105 Manatee Ave W",
    "sg:city":"Bradenton",
    "sg:classifiers":[
        {
            "category":"Real Estate",
            "subcategory":"Real Estate Agent",
            "type":"Services"
        }
    ],
    "sg:phone":"+1 941 792 2111",
    "sg:postcode":"34209",
    "sg:province":"FL",
    "sg:website":"www.century21allaces.com",
    "wof:name":"All Aces Realty",
    "wof:placetype":"venue"
},
  "geometry": {"coordinates":[-82.61213600000001,27.495979],"type":"Point"}
}