{
  "type": "Feature",
  "properties": {
    "addr:full":"2452 Gulf Gate Dr Sarasota FL 34231",
    "addr:housenumber":"2452",
    "addr:postcode":"34231",
    "addr:street":"Gulf Gate Dr",
    "iso:country":"US",
    "sg:address":"2452 Gulf Gate Dr",
    "sg:city":"Sarasota",
    "sg:classifiers":[
        {
            "category":"Wholesale",
            "subcategory":"Chemicals & Plastics",
            "type":"Manufacturing & Wholesale Goods"
        }
    ],
    "sg:phone":"+1 941 923 4696",
    "sg:postcode":"34231",
    "sg:province":"FL",
    "wof:name":"Sanitary Chemicals Sarasota",
    "wof:placetype":"venue"
},
  "geometry": {"coordinates":[-82.512913,27.258686],"type":"Point"}
}