{
  "type": "Feature",
  "properties": {
    "iso:country":"US",
    "sg:address":"5239 S Dale Mabry Hwy",
    "sg:city":"Tampa",
    "sg:classifiers":[
        {
            "category":"Autos & Motor Vehicles",
            "subcategory":"Auto Supplies",
            "type":"Retail Goods"
        }
    ],
    "sg:phone":"+1 813 839 2250",
    "sg:postcode":"33611",
    "sg:province":"FL",
    "sg:tags":[
        "equipment",
        "racing",
        "car",
        "automobile"
    ],
    "wof:name":"Automotive Audio Performance",
    "wof:placetype":"venue"
},
  "geometry": {"coordinates":[-82.506471,27.889057],"type":"Point"}
}