{
  "type": "Feature",
  "properties": {
    "iso:country":"US",
    "sg:address":"18330 Coral Chase Dr",
    "sg:city":"Boca Raton",
    "sg:classifiers":[
        {
            "category":"Shopping",
            "subcategory":"Florist",
            "type":"Retail Goods"
        }
    ],
    "sg:phone":"+1 561 451 9699",
    "sg:postcode":"33498",
    "sg:province":"FL",
    "wof:name":"Boca's Tropical Gardens",
    "wof:placetype":"venue"
},
  "geometry": {"coordinates":[-80.22334499999999,26.402502],"type":"Point"}
}