{
  "type": "Feature",
  "properties": {
    "iso:country":"US",
    "sg:address":"4036 Shoal Line Blvd",
    "sg:city":"Hernando Beach",
    "sg:classifiers":[
        {
            "category":"Building & Trades",
            "subcategory":"Pest Control",
            "type":"Services"
        }
    ],
    "sg:phone":"+1 352 597 6833",
    "sg:postcode":"34607",
    "sg:province":"FL",
    "wof:name":"HPT Inc",
    "wof:placetype":"venue"
},
  "geometry": {"coordinates":[-82.650234,28.481671],"type":"Point"}
}