{
  "type": "Feature",
  "properties": {
    "iso:country":"US",
    "sg:address":"104 Kapok Cres",
    "sg:city":"West Palm Beach",
    "sg:classifiers":[
        {
            "category":"Banks & Credit Unions",
            "subcategory":"Financial Services",
            "type":"Services"
        }
    ],
    "sg:phone":"+1 561 790 7046",
    "sg:postcode":"33411",
    "sg:province":"FL",
    "sg:tags":[
        "investor"
    ],
    "wof:name":"Jam Pro Investments Inc",
    "wof:placetype":"venue"
},
  "geometry": {"coordinates":[-80.23937100000001,26.688552],"type":"Point"}
}