{
  "type": "Feature",
  "properties": {
    "addr:full":"3840 Coconut Creek Pkwy Pompano Beach FL 33066",
    "addr:housenumber":"3840",
    "addr:postcode":"33066",
    "addr:street":"Coconut Creek Pkwy",
    "iso:country":"US",
    "sg:address":"3840 Coconut Creek Pkwy",
    "sg:city":"Pompano Beach",
    "sg:classifiers":[
        {
            "category":"Utilities",
            "subcategory":"Telephone",
            "type":"Services"
        }
    ],
    "sg:phone":"+1 954 984 0411",
    "sg:postcode":"33066",
    "sg:province":"FL",
    "sg:tags":[
        "telecommunication",
        "sales"
    ],
    "wof:name":"Global Systems Telecom",
    "wof:placetype":"venue"
},
  "geometry": {"coordinates":[-80.17274,26.244959],"type":"Point"}
}