{
  "type": "Feature",
  "properties": {
    "iso:country":"US",
    "sg:address":"7457 103rd St",
    "sg:city":"Jacksonville",
    "sg:classifiers":[
        {
            "category":"Food & Beverages",
            "subcategory":"Specialty",
            "type":"Retail Goods"
        },
        {
            "category":"Wholesale",
            "subcategory":"Durable Goods & Equipment",
            "type":"Manufacturing & Wholesale Goods"
        }
    ],
    "sg:phone":"+1 904 778 9100",
    "sg:postcode":"32210",
    "sg:province":"FL",
    "sg:tags":[
        "oriental"
    ],
    "wof:name":"J G M Asian Market Inc",
    "wof:placetype":"venue"
},
  "geometry": {"coordinates":[-81.769559,30.24837],"type":"Point"}
}