{
  "type": "Feature",
  "properties": {
    "iso:country":"US",
    "sg:address":"225 Minutemen Cswy",
    "sg:city":"Cocoa Beach",
    "sg:classifiers":[
        {
            "category":"Shopping",
            "subcategory":"Gifts & Souvenirs",
            "type":"Retail Goods"
        }
    ],
    "sg:phone":"+1 321 799 3799",
    "sg:postcode":"32931",
    "sg:province":"FL",
    "sg:tags":[
        "used",
        "jewelry",
        "merchandise"
    ],
    "wof:name":"Collection Connection",
    "wof:placetype":"venue"
},
  "geometry": {"coordinates":[-80.610921,28.318516],"type":"Point"}
}