{
  "type": "Feature",
  "properties": {
    "iso:country":"US",
    "sg:address":"25149 Blue Sink Rd",
    "sg:city":"Howey In The Hills",
    "sg:classifiers":[
        {
            "category":"Building & Trades",
            "subcategory":"Construction",
            "type":"Services"
        }
    ],
    "sg:phone":"+1 352 324 9715",
    "sg:postcode":"34737",
    "sg:province":"FL",
    "sg:tags":[
        "contractor"
    ],
    "wof:name":"IR Welder Inc",
    "wof:placetype":"venue"
},
  "geometry": {"coordinates":[-81.811932,28.707654],"type":"Point"}
}