{
  "type": "Feature",
  "properties": {
    "addr:full":"2203 N Lois Ave Bsmt Tampa FL 33607",
    "addr:housenumber":"2203",
    "addr:postcode":"33607",
    "addr:street":"N Lois Ave",
    "iso:country":"US",
    "sg:address":"2203 N Lois Ave Bsmt",
    "sg:city":"Tampa",
    "sg:classifiers":[
        {
            "category":"Personal",
            "subcategory":"Massage",
            "type":"Services"
        }
    ],
    "sg:phone":"+1 813 348 1373",
    "sg:postcode":"33607",
    "sg:province":"FL",
    "wof:name":"Amys Massage Therapy",
    "wof:placetype":"venue"
},
  "geometry": {"coordinates":[-82.513786,27.961214],"type":"Point"}
}