{
  "type": "Feature",
  "properties": {
    "iso:country":"US",
    "sg:address":"139 E Pine St",
    "sg:city":"Orlando",
    "sg:classifiers":[
        {
            "category":"Shopping",
            "subcategory":"Stationery & Office Supplies",
            "type":"Retail Goods"
        },
        {
            "category":"Manufacturing",
            "subcategory":"Rubber & Plastics",
            "type":"Manufacturing & Wholesale Goods"
        },
        {
            "category":"Manufacturing",
            "subcategory":"Signs",
            "type":"Manufacturing & Wholesale Goods"
        }
    ],
    "sg:phone":"+1 407 423 2500",
    "sg:postcode":"32801",
    "sg:province":"FL",
    "sg:tags":[
        "stamp",
        "store"
    ],
    "sg:website":"http://www.clubkayak.com",
    "wof:name":"Central Florida Stamp And Sign & Pencrafters Of Orlando Inc",
    "wof:placetype":"venue"
},
  "geometry": {"coordinates":[-81.376766,28.541339],"type":"Point"}
}