{
  "type": "Feature",
  "properties": {
    "addr:full":"2215 Winkler Ave Fort Myers FL 33901",
    "addr:housenumber":"2215",
    "addr:postcode":"33901",
    "addr:street":"Winkler Ave",
    "iso:country":"US",
    "sg:address":"2215 Winkler Ave",
    "sg:city":"Fort Myers",
    "sg:classifiers":[
        {
            "category":"Real Estate",
            "subcategory":"Real Estate Agent",
            "type":"Services"
        }
    ],
    "sg:phone":"+1 239 728 6200",
    "sg:postcode":"33901",
    "sg:province":"FL",
    "sg:tags":[
        "desk",
        "space"
    ],
    "wof:name":"Aros",
    "wof:placetype":"venue"
},
  "geometry": {"coordinates":[-81.866147,26.604383],"type":"Point"}
}