{
  "type": "Feature",
  "properties": {
    "iso:country":"US",
    "sg:address":"3000 N 12th Ave",
    "sg:city":"Pensacola",
    "sg:classifiers":[
        {
            "category":"Retail",
            "subcategory":"Car Wash",
            "type":"Services"
        },
        {
            "category":"Retail",
            "subcategory":"Auto Repair",
            "type":"Services"
        }
    ],
    "sg:phone":"+1 850 436 8718",
    "sg:postcode":"32503",
    "sg:province":"FL",
    "sg:tags":[
        "automotive",
        "detail",
        "clean",
        "automobile"
    ],
    "wof:name":"Bumper To Bumper Detailing Inc",
    "wof:placetype":"venue"
},
  "geometry": {"coordinates":[-87.20759099999999,30.445567],"type":"Point"}
}