{
  "type": "Feature",
  "properties": {
    "iso:country":"US",
    "sg:address":"1004 Hook Dr",
    "sg:city":"Spring Hill",
    "sg:classifiers":[
        {
            "category":"Professional",
            "subcategory":"Computer Services",
            "type":"Services"
        }
    ],
    "sg:phone":"+1 352 799 3051",
    "sg:postcode":"34608",
    "sg:province":"FL",
    "sg:tags":[
        "related"
    ],
    "wof:name":"Pcs Inc",
    "wof:placetype":"venue"
},
  "geometry": {"coordinates":[-82.54740700000001,28.445949],"type":"Point"}
}