{
  "type": "Feature",
  "properties": {
    "iso:country":"US",
    "sg:address":"10255 General Dr",
    "sg:city":"Orlando",
    "sg:classifiers":[
        {
            "category":"Food & Beverages",
            "subcategory":"Groceries & Convenience Stores",
            "type":"Retail Goods"
        }
    ],
    "sg:phone":"+1 407 857 6025",
    "sg:postcode":"32824",
    "sg:province":"FL",
    "sg:tags":[
        "chip",
        "potato"
    ],
    "wof:name":"Snyders Of Hanover",
    "wof:placetype":"venue"
},
  "geometry": {"coordinates":[-81.388285,28.416817],"type":"Point"}
}