{
  "type": "Feature",
  "properties": {
    "iso:country":"US",
    "sg:address":"6110 Waverly Rd",
    "sg:city":"Weeki Wachee",
    "sg:classifiers":[
        {
            "category":"Building & Trades",
            "subcategory":"Landscaping Services",
            "type":"Services"
        }
    ],
    "sg:phone":"+1 352 596 3867",
    "sg:postcode":"34607",
    "sg:province":"FL",
    "sg:tags":[
        "tree"
    ],
    "wof:name":"Panzner's Tree Svc",
    "wof:placetype":"venue"
},
  "geometry": {"coordinates":[-82.62041000000001,28.533263],"type":"Point"}
}