{
  "type": "Feature",
  "properties": {
    "iso:country":"US",
    "sg:address":"599 John Anderson Dr",
    "sg:city":"Ormond Beach",
    "sg:classifiers":[
        {
            "category":"Professional",
            "subcategory":"Management & Consulting",
            "type":"Services"
        }
    ],
    "sg:phone":"+1 386 673 0302",
    "sg:postcode":"32176",
    "sg:province":"FL",
    "sg:tags":[
        "consultant",
        "business"
    ],
    "wof:name":"Merrell Health & Human Svc",
    "wof:placetype":"venue"
},
  "geometry": {"coordinates":[-81.053877,29.302573],"type":"Point"}
}