{
  "type": "Feature",
  "properties": {
    "iso:country":"US",
    "sg:address":"4910 W Knollwood St",
    "sg:city":"Tampa",
    "sg:classifiers":[
        {
            "category":"Manufacturing",
            "subcategory":"Building Materials",
            "type":"Manufacturing & Wholesale Goods"
        }
    ],
    "sg:phone":"+1 813 884 1441",
    "sg:postcode":"33634",
    "sg:province":"FL",
    "sg:tags":[
        "shutter",
        "wood",
        "mfg"
    ],
    "sg:website":"www.americanlouveredproducts.com",
    "wof:name":"American Louvered Products Co",
    "wof:placetype":"venue"
},
  "geometry": {"coordinates":[-82.530492,28.007846],"type":"Point"}
}