{
  "type": "Feature",
  "properties": {
    "iso:country":"US",
    "sg:address":"706 N Myrtle Ave",
    "sg:city":"Clearwater",
    "sg:classifiers":[
        {
            "category":"Communications",
            "subcategory":"Radio Station",
            "type":"Services"
        }
    ],
    "sg:phone":"+1 727 441 3311",
    "sg:postcode":"33755",
    "sg:province":"FL",
    "sg:tags":[
        "company",
        "broadcasting"
    ],
    "wof:name":"WTAN",
    "wof:placetype":"venue"
},
  "geometry": {"coordinates":[-82.795987,27.973543],"type":"Point"}
}