{
  "type": "Feature",
  "properties": {
    "addr:full":"4948 Eaglesmere Dr Orlando FL 32819",
    "addr:housenumber":"4948",
    "addr:postcode":"32819",
    "addr:street":"Eaglesmere Dr",
    "iso:country":"US",
    "sg:address":"4948 Eaglesmere Dr",
    "sg:city":"Orlando",
    "sg:classifiers":[
        {
            "category":"Retail",
            "subcategory":"Repair Shop",
            "type":"Services"
        }
    ],
    "sg:phone":"+1 407 352 7600",
    "sg:postcode":"32819",
    "sg:province":"FL",
    "wof:name":"Hiperon Cleaning Corp",
    "wof:placetype":"venue"
},
  "geometry": {"coordinates":[-81.462806,28.489178],"type":"Point"}
}