{
  "type": "Feature",
  "properties": {
    "iso:country":"US",
    "sg:address":"5333 Fairfield Way",
    "sg:city":"Fort Myers",
    "sg:classifiers":[
        {
            "category":"Health Services",
            "subcategory":"Doctor",
            "type":"Services"
        }
    ],
    "sg:phone":"+1 239 437 3264",
    "sg:postcode":"33919",
    "sg:province":"FL",
    "sg:tags":[
        "medical"
    ],
    "wof:name":"RSM Basec Inc",
    "wof:placetype":"venue"
},
  "geometry": {"coordinates":[-81.895815,26.577225],"type":"Point"}
}