{
  "type": "Feature",
  "properties": {
    "addr:full":"320 N 6th Ave Wauchula FL 33873",
    "addr:housenumber":"320",
    "addr:postcode":"33873",
    "addr:street":"N 6Th Ave",
    "iso:country":"US",
    "sg:address":"320 N 6th Ave",
    "sg:city":"Wauchula",
    "sg:classifiers":[
        {
            "category":"Retail",
            "subcategory":"Funeral Services",
            "type":"Services"
        }
    ],
    "sg:phone":"+1 863 773 3001",
    "sg:postcode":"33873",
    "sg:province":"FL",
    "sg:tags":[
        "director"
    ],
    "wof:name":"Speights Funeral Home Inc",
    "wof:placetype":"venue"
},
  "geometry": {"coordinates":[-81.812524,27.550953],"type":"Point"}
}