{
  "type": "Feature",
  "properties": {
    "iso:country":"US",
    "sg:address":"4800 NW 2nd Ter",
    "sg:city":"Boca Raton",
    "sg:classifiers":[
        {
            "category":"Retail",
            "subcategory":"Animal Services",
            "type":"Services"
        }
    ],
    "sg:phone":"+1 561 241 5648",
    "sg:postcode":"33431",
    "sg:province":"FL",
    "wof:name":"Pet Pourrie",
    "wof:placetype":"venue"
},
  "geometry": {"coordinates":[-80.086026,26.392017],"type":"Point"}
}