{
  "type": "Feature",
  "properties": {
    "iso:country":"US",
    "sg:address":"1403 25th Ave E",
    "sg:city":"Bradenton",
    "sg:classifiers":[
        {
            "category":"Professional",
            "subcategory":"Detective & Security Services",
            "type":"Services"
        }
    ],
    "sg:phone":"+1 941 748 0184",
    "sg:postcode":"34208",
    "sg:province":"FL",
    "sg:tags":[
        "system"
    ],
    "wof:name":"Signal 65 Security",
    "wof:placetype":"venue"
},
  "geometry": {"coordinates":[-82.546637,27.477772],"type":"Point"}
}