{
  "type": "Feature",
  "properties": {
    "iso:country":"US",
    "sg:address":"4300 Bayou Blvd",
    "sg:city":"Pensacola",
    "sg:classifiers":[
        {
            "category":"Real Estate",
            "subcategory":"Real Estate Agent",
            "type":"Services"
        }
    ],
    "sg:phone":"+1 850 477 7887",
    "sg:postcode":"32503",
    "sg:province":"FL",
    "sg:tags":[
        "appraiser"
    ],
    "wof:name":"Dickerson & Associates",
    "wof:placetype":"venue"
},
  "geometry": {"coordinates":[-87.204313,30.465933],"type":"Point"}
}