{
  "type": "Feature",
  "properties": {
    "addr:full":"782 NW 42nd Ave Ste 629 Miami FL 33126",
    "addr:housenumber":"782",
    "addr:postcode":"33126",
    "addr:street":"Nw 42Nd Ave Ste 629",
    "iso:country":"US",
    "sg:address":"782 NW 42nd Ave Ste 629",
    "sg:city":"Miami",
    "sg:classifiers":[
        {
            "category":"Professional",
            "subcategory":"Accounting & Tax Preparation",
            "type":"Services"
        }
    ],
    "sg:phone":"+1 305 443 3046",
    "sg:postcode":"33126",
    "sg:province":"FL",
    "sg:tags":[
        "accountant",
        "bookkeeping",
        "public",
        "accountants-certified"
    ],
    "wof:name":"Navarro Osvaldo CPA",
    "wof:placetype":"venue"
},
  "geometry": {"coordinates":[-80.264099,25.7796],"type":"Point"}
}