{
  "type": "Feature",
  "properties": {
    "addr:full":"603 Oakleaf Blvd Oldsmar FL 34677",
    "addr:housenumber":"603",
    "addr:postcode":"34677",
    "addr:street":"Oakleaf Blvd",
    "iso:country":"US",
    "sg:address":"603 Oakleaf Blvd",
    "sg:city":"Oldsmar",
    "sg:classifiers":[
        {
            "category":"Banks & Credit Unions",
            "subcategory":"Bank",
            "type":"Services"
        }
    ],
    "sg:phone":"+1 727 525 4284",
    "sg:postcode":"34677",
    "sg:province":"FL",
    "sg:tags":[
        "broker",
        "mortgage"
    ],
    "wof:name":"Southern Trust Lending Inc",
    "wof:placetype":"venue"
},
  "geometry": {"coordinates":[-82.690057,28.038534],"type":"Point"}
}