{
  "type": "Feature",
  "properties": {
    "iso:country":"US",
    "sg:address":"2905 Lakeview Dr # A",
    "sg:city":"Fern Park",
    "sg:classifiers":[
        {
            "category":"Health Services",
            "subcategory":"Health Practitioner",
            "type":"Services"
        }
    ],
    "sg:phone":"+1 407 830 0068",
    "sg:postcode":"32730",
    "sg:province":"FL",
    "sg:tags":[
        "acupuncture"
    ],
    "wof:name":"Acupuncture Center of Greater Orlando",
    "wof:placetype":"venue"
},
  "geometry": {"coordinates":[-81.34320099999999,28.660601],"type":"Point"}
}