{
  "type": "Feature",
  "properties": {
    "iso:country":"US",
    "sg:address":"4700 NW 27th Ave",
    "sg:city":"Boca Raton",
    "sg:classifiers":[
        {
            "category":"Professional",
            "type":"Services"
        }
    ],
    "sg:phone":"+1 561 988 0375",
    "sg:postcode":"33434",
    "sg:province":"FL",
    "wof:name":"Naomi Berger Inc",
    "wof:placetype":"venue"
},
  "geometry": {"coordinates":[-80.143642,26.391659],"type":"Point"}
}