{
  "type": "Feature",
  "properties": {
    "iso:country":"US",
    "sg:address":"231 SW 14th St",
    "sg:city":"Pompano Beach",
    "sg:classifiers":[
        {
            "category":"Professional",
            "subcategory":"Secretarial Services",
            "type":"Services"
        }
    ],
    "sg:phone":"+1 954 788 5690",
    "sg:postcode":"33060",
    "sg:province":"FL",
    "sg:tags":[
        "typing"
    ],
    "wof:name":"DSC Processing Svc Inc",
    "wof:placetype":"venue"
},
  "geometry": {"coordinates":[-80.128107,26.212541],"type":"Point"}
}