{
  "type": "Feature",
  "properties": {
    "iso:country":"US",
    "sg:address":"301 Health Park Blvd",
    "sg:city":"St Augustine",
    "sg:classifiers":[
        {
            "category":"Health Services",
            "subcategory":"Doctor",
            "type":"Services"
        }
    ],
    "sg:phone":"+1 904 829 8677",
    "sg:postcode":"32086",
    "sg:province":"FL",
    "sg:tags":[
        "physician",
        "medical",
        "surgeon"
    ],
    "wof:name":"Luiz C Kuntz MD",
    "wof:placetype":"venue"
},
  "geometry": {"coordinates":[-81.320784,29.862493],"type":"Point"}
}