{
  "type": "Feature",
  "properties": {
    "addr:full":"11555 Wild Cat Ln New Port Richey FL 34654",
    "addr:housenumber":"11555",
    "addr:postcode":"34654",
    "addr:street":"Wild Cat Ln",
    "iso:country":"US",
    "sg:address":"11555 Wild Cat Ln",
    "sg:city":"New Port Richey",
    "sg:classifiers":[
        {
            "category":"Building & Trades",
            "subcategory":"Construction",
            "type":"Services"
        }
    ],
    "sg:phone":"+1 727 856 6453",
    "sg:postcode":"34654",
    "sg:province":"FL",
    "sg:tags":[
        "floor",
        "laying",
        "contractor"
    ],
    "wof:name":"Skelton Flooring Inc",
    "wof:placetype":"venue"
},
  "geometry": {"coordinates":[-82.64231700000001,28.322983],"type":"Point"}
}