{
  "type": "Feature",
  "properties": {
    "iso:country":"US",
    "sg:address":"18505 SW 104th St",
    "sg:city":"Miami",
    "sg:classifiers":[
        {
            "category":"Building & Trades",
            "subcategory":"Plumbing",
            "type":"Services"
        }
    ],
    "sg:phone":"+1 305 235 6562",
    "sg:postcode":"33196",
    "sg:province":"FL",
    "wof:name":"E Z Home Remodeling & Plumbing",
    "wof:placetype":"venue"
},
  "geometry": {"coordinates":[-80.35968,25.597326],"type":"Point"}
}