{
  "type": "Feature",
  "properties": {
    "iso:country":"US",
    "sg:address":"301 W Atlantic Ave",
    "sg:city":"Delray Beach",
    "sg:classifiers":[
        {
            "category":"Real Estate",
            "subcategory":"Real Estate Services",
            "type":"Services"
        }
    ],
    "sg:phone":"+1 561 278 6070",
    "sg:postcode":"33444",
    "sg:province":"FL",
    "sg:tags":[
        "company",
        "title"
    ],
    "wof:name":"New World Title",
    "wof:placetype":"venue"
},
  "geometry": {"coordinates":[-80.076724,26.461697],"type":"Point"}
}