{
  "type": "Feature",
  "properties": {
    "addr:full":"2691 River Reach Dr Naples FL 34104",
    "addr:housenumber":"2691",
    "addr:postcode":"34104",
    "addr:street":"River Reach Dr",
    "iso:country":"US",
    "sg:address":"2691 River Reach Dr",
    "sg:city":"Naples",
    "sg:classifiers":[
        {
            "category":"Building & Trades",
            "subcategory":"Landscaping Services",
            "type":"Services"
        }
    ],
    "sg:phone":"+1 239 261 2229",
    "sg:postcode":"34104",
    "sg:province":"FL",
    "wof:name":"Tuff Turf",
    "wof:placetype":"venue"
},
  "geometry": {"coordinates":[-81.76913399999999,26.164732],"type":"Point"}
}