{
  "type": "Feature",
  "properties": {
    "addr:full":"414 Crescent St Fort Myers Beach FL 33931",
    "addr:housenumber":"414",
    "addr:postcode":"33931",
    "addr:street":"Crescent St",
    "iso:country":"US",
    "sg:address":"414 Crescent St",
    "sg:city":"Fort Myers Beach",
    "sg:classifiers":[
        {
            "category":"Travel",
            "subcategory":"Hotels & Motels",
            "type":"Entertainment"
        }
    ],
    "sg:phone":"+1 239 463 9258",
    "sg:postcode":"33931",
    "sg:province":"FL",
    "sg:tags":[
        "operation"
    ],
    "wof:name":"Matanzas Inn",
    "wof:placetype":"venue"
},
  "geometry": {"coordinates":[-81.953756,26.455877],"type":"Point"}
}