{
  "type": "Feature",
  "properties": {
    "iso:country":"US",
    "sg:address":"3410 S Dale Mabry Hwy",
    "sg:city":"Tampa",
    "sg:classifiers":[
        {
            "category":"Personal",
            "subcategory":"Beauty Salon",
            "type":"Services"
        }
    ],
    "sg:phone":"+1 813 835 7049",
    "sg:postcode":"33629",
    "sg:province":"FL",
    "wof:name":"Salon Taspen",
    "wof:placetype":"venue"
},
  "geometry": {"coordinates":[-82.506002,27.912586],"type":"Point"}
}