{
  "type": "Feature",
  "properties": {
    "addr:full":"2239 NW 75th Ave Pompano Beach FL 33063",
    "addr:housenumber":"2239",
    "addr:postcode":"33063",
    "addr:street":"Nw 75Th Ave",
    "iso:country":"US",
    "sg:address":"2239 NW 75th Ave",
    "sg:city":"Pompano Beach",
    "sg:classifiers":[
        {
            "category":"Building & Trades",
            "subcategory":"Construction",
            "type":"Services"
        }
    ],
    "sg:phone":"+1 954 972 3627",
    "sg:postcode":"33063",
    "sg:province":"FL",
    "sg:tags":[
        "hanging",
        "contractor"
    ],
    "wof:name":"JM Painting",
    "wof:placetype":"venue"
},
  "geometry": {"coordinates":[-80.225019,26.25706],"type":"Point"}
}