{
  "type": "Feature",
  "properties": {
    "iso:country":"US",
    "sg:address":"1665 Canterbury Dr",
    "sg:city":"Indialantic",
    "sg:classifiers":[
        {
            "category":"Real Estate",
            "subcategory":"Architect",
            "type":"Services"
        }
    ],
    "sg:phone":"+1 321 727 3123",
    "sg:postcode":"32903",
    "sg:province":"FL",
    "sg:tags":[
        "residential",
        "designer"
    ],
    "wof:name":"Scalero Associates Inc",
    "wof:placetype":"venue"
},
  "geometry": {"coordinates":[-80.58197800000001,28.106461],"type":"Point"}
}