{
  "type": "Feature",
  "properties": {
    "iso:country":"US",
    "sg:address":"2101 Park Center Dr",
    "sg:city":"Orlando",
    "sg:classifiers":[
        {
            "category":"Shopping",
            "subcategory":"Computers & Home Electronics",
            "type":"Retail Goods"
        }
    ],
    "sg:phone":"+1 407 472 8100",
    "sg:postcode":"32835",
    "sg:province":"FL",
    "sg:tags":[
        "software"
    ],
    "wof:name":"Software Certifications",
    "wof:placetype":"venue"
},
  "geometry": {"coordinates":[-81.47292,28.520028],"type":"Point"}
}