{
  "type": "Feature",
  "properties": {
    "iso:country":"US",
    "sg:address":"217 Parkside Ave",
    "sg:city":"Orange Park",
    "sg:classifiers":[
        {
            "category":"Education",
            "subcategory":"Special Training",
            "type":"Public Place"
        }
    ],
    "sg:phone":"+1 904 375 0320",
    "sg:postcode":"32065",
    "sg:province":"FL",
    "sg:tags":[
        "instruction",
        "driving"
    ],
    "wof:name":"All-Rite Traffic School",
    "wof:placetype":"venue"
},
  "geometry": {"coordinates":[-81.76966,30.130498],"type":"Point"}
}