{
  "type": "Feature",
  "properties": {
    "iso:country":"US",
    "sg:address":"600 E Washington St",
    "sg:city":"Orlando",
    "sg:classifiers":[
        {
            "category":"Professional",
            "subcategory":"Advertising",
            "type":"Services"
        }
    ],
    "sg:phone":"+1 407 849 0100",
    "sg:postcode":"32801",
    "sg:province":"FL",
    "sg:tags":[
        "agency"
    ],
    "wof:name":"Fry Hammond Barr Incorporated",
    "wof:placetype":"venue"
},
  "geometry": {"coordinates":[-81.36847400000001,28.543647],"type":"Point"}
}