{
  "type": "Feature",
  "properties": {
    "iso:country":"US",
    "sg:address":"12781 SW 42nd St",
    "sg:city":"Miami",
    "sg:classifiers":[
        {
            "category":"Health Services",
            "subcategory":"Clinic",
            "type":"Services"
        },
        {
            "category":"Health Services",
            "subcategory":"Medical Lab",
            "type":"Services"
        }
    ],
    "sg:phone":"+1 305 553 2220",
    "sg:postcode":"33175",
    "sg:province":"FL",
    "wof:name":"Pataky Medical Center",
    "wof:placetype":"venue"
},
  "geometry": {"coordinates":[-80.401242,25.729659],"type":"Point"}
}