{
  "type": "Feature",
  "properties": {
    "iso:country":"US",
    "sg:address":"5757 Stafford Springs Trl",
    "sg:city":"Orlando",
    "sg:classifiers":[
        {
            "category":"Building & Trades",
            "subcategory":"Cleaning & Sanitation",
            "type":"Services"
        }
    ],
    "sg:phone":"+1 407 384 6018",
    "sg:postcode":"32829",
    "sg:province":"FL",
    "wof:name":"As Clean As It Gets Inc",
    "wof:placetype":"venue"
},
  "geometry": {"coordinates":[-81.2723,28.480123],"type":"Point"}
}