{
  "type": "Feature",
  "properties": {
    "iso:country":"US",
    "sg:address":"1224 SW 19th St",
    "sg:city":"Miami",
    "sg:classifiers":[
        {
            "category":"Retail",
            "subcategory":"Self-service Laundry",
            "type":"Services"
        }
    ],
    "sg:phone":"+1 305 858 6784",
    "sg:postcode":"33145",
    "sg:province":"FL",
    "sg:tags":[
        "coin"
    ],
    "wof:name":"Flaminco Coin Laundry",
    "wof:placetype":"venue"
},
  "geometry": {"coordinates":[-80.21579699999999,25.754586],"type":"Point"}
}