{
  "type": "Feature",
  "properties": {
    "iso:country":"US",
    "sg:address":"804 S Woodlyn Dr",
    "sg:city":"Tampa",
    "sg:classifiers":[
        {
            "category":"Professional",
            "type":"Services"
        }
    ],
    "sg:phone":"+1 813 875 5585",
    "sg:postcode":"33609",
    "sg:province":"FL",
    "wof:name":"Lesley Groves Inc",
    "wof:placetype":"venue"
},
  "geometry": {"coordinates":[-82.492259,27.936347],"type":"Point"}
}