{
  "type": "Feature",
  "properties": {
    "iso:country":"US",
    "sg:address":"3032 NW 63rd St",
    "sg:city":"Miami",
    "sg:classifiers":[
        {
            "category":"Professional",
            "subcategory":"Business Services",
            "type":"Services"
        }
    ],
    "sg:phone":"+1 305 836 5011",
    "sg:postcode":"33147",
    "sg:province":"FL",
    "sg:tags":[
        "fund",
        "promotion",
        "raising"
    ],
    "wof:name":"Showtime Connection",
    "wof:placetype":"venue"
},
  "geometry": {"coordinates":[-80.246661,25.83174],"type":"Point"}
}