{
  "type": "Feature",
  "properties": {
    "addr:full":"9400 SW 87th Ave Miami FL 33176",
    "addr:housenumber":"9400",
    "addr:postcode":"33176",
    "addr:street":"Sw 87Th Ave",
    "iso:country":"US",
    "sg:address":"9400 SW 87th Ave",
    "sg:city":"Miami",
    "sg:classifiers":[
        {
            "category":"Restaurant",
            "type":"Food & Drink"
        }
    ],
    "sg:phone":"+1 305 279 2218",
    "sg:postcode":"33176",
    "sg:province":"FL",
    "sg:tags":[
        "eating"
    ],
    "wof:name":"Events By Premier South",
    "wof:placetype":"venue"
},
  "geometry": {"coordinates":[-80.335376,25.680806],"type":"Point"}
}