{
  "type": "Feature",
  "properties": {
    "addr:full":"401 60th St W Bradenton FL 34209",
    "addr:housenumber":"401",
    "addr:postcode":"34209",
    "addr:street":"60Th St W",
    "iso:country":"US",
    "sg:address":"401 60th St W",
    "sg:city":"Bradenton",
    "sg:classifiers":[
        {
            "category":"Personal",
            "subcategory":"Beauty Salon",
            "type":"Services"
        }
    ],
    "sg:phone":"+1 941 798 3144",
    "sg:postcode":"34209",
    "sg:province":"FL",
    "sg:tags":[
        "shop"
    ],
    "wof:name":"Totally You & Hair Studio",
    "wof:placetype":"venue"
},
  "geometry": {"coordinates":[-82.621397,27.496348],"type":"Point"}
}