{
  "type": "Feature",
  "properties": {
    "addr:full":"2835 Williamsburg St Sarasota FL 34231",
    "addr:housenumber":"2835",
    "addr:postcode":"34231",
    "addr:street":"Williamsburg St",
    "iso:country":"US",
    "sg:address":"2835 Williamsburg St",
    "sg:city":"Sarasota",
    "sg:classifiers":[
        {
            "category":"Building & Trades",
            "subcategory":"Construction",
            "type":"Services"
        }
    ],
    "sg:phone":"+1 941 927 7819",
    "sg:postcode":"34231",
    "sg:province":"FL",
    "sg:tags":[
        "contractor"
    ],
    "wof:name":"Marble Mastery",
    "wof:placetype":"venue"
},
  "geometry": {"coordinates":[-82.512675,27.266117],"type":"Point"}
}