{
  "type": "Feature",
  "properties": {
    "iso:country":"US",
    "sg:address":"2755 S Federal Hwy",
    "sg:city":"Boynton Beach",
    "sg:classifiers":[
        {
            "category":"Food & Beverages",
            "subcategory":"Groceries & Convenience Stores",
            "type":"Retail Goods"
        }
    ],
    "sg:phone":"+1 561 364 9065",
    "sg:postcode":"33435",
    "sg:province":"FL",
    "sg:tags":[
        "beer",
        "wine"
    ],
    "wof:name":"First Stop Foods",
    "wof:placetype":"venue"
},
  "geometry": {"coordinates":[-80.05998099999999,26.504577],"type":"Point"}
}