{
  "type": "Feature",
  "properties": {
    "iso:country":"US",
    "sg:address":"423 Lafayette Blvd",
    "sg:city":"Oldsmar",
    "sg:classifiers":[
        {
            "category":"Recreation",
            "type":"Entertainment"
        }
    ],
    "sg:phone":"+1 813 854 2997",
    "sg:postcode":"34677",
    "sg:province":"FL",
    "sg:tags":[
        "center"
    ],
    "wof:name":"Oldsmar City Recreation Ctr",
    "wof:placetype":"venue"
},
  "geometry": {"coordinates":[-82.65747399999999,28.031129],"type":"Point"}
}