{
  "type": "Feature",
  "properties": {
    "addr:full":"8520 N Nebraska Ave Tampa FL 33604",
    "addr:housenumber":"8520",
    "addr:postcode":"33604",
    "addr:street":"N Nebraska Ave",
    "iso:country":"US",
    "sg:address":"8520 N Nebraska Ave",
    "sg:city":"Tampa",
    "sg:classifiers":[
        {
            "category":"Shopping",
            "subcategory":"Used Merchandise",
            "type":"Retail Goods"
        }
    ],
    "sg:phone":"+1 813 932 1230",
    "sg:postcode":"33604",
    "sg:province":"FL",
    "sg:tags":[
        "furniture"
    ],
    "wof:name":"A-1 Bargain Store",
    "wof:placetype":"venue"
},
  "geometry": {"coordinates":[-82.45132599999999,28.026802],"type":"Point"}
}