{
  "type": "Feature",
  "properties": {
    "addr:full":"146 Ave C Port St Joe FL 32456",
    "addr:housenumber":"146",
    "addr:postcode":"32456",
    "addr:street":"Ave C;St",
    "iso:country":"US",
    "sg:address":"146 Ave C",
    "sg:city":"Port St Joe",
    "sg:classifiers":[
        {
            "category":"Organizations",
            "subcategory":"Religious Organization",
            "type":"Services"
        }
    ],
    "sg:phone":"+1 850 229 6179",
    "sg:postcode":"32456",
    "sg:province":"FL",
    "sg:tags":[
        "church"
    ],
    "wof:name":"New Bethel AME Church Annex",
    "wof:placetype":"venue"
},
  "geometry": {"coordinates":[-85.30467400000001,29.819618],"type":"Point"}
}