{
  "type": "Feature",
  "properties": {
    "iso:country":"US",
    "sg:address":"100 W Cypress Creek Rd",
    "sg:city":"Fort Lauderdale",
    "sg:classifiers":[
        {
            "category":"Professional",
            "subcategory":"Management & Consulting",
            "type":"Services"
        }
    ],
    "sg:phone":"+1 954 771 7373",
    "sg:postcode":"33309",
    "sg:province":"FL",
    "sg:tags":[
        "fuel"
    ],
    "wof:name":"Rockwell Asset Management",
    "wof:placetype":"venue"
},
  "geometry": {"coordinates":[-80.14832699999999,26.203467],"type":"Point"}
}