{
  "type": "Feature",
  "properties": {
    "addr:full":"18241 NE 4th Ct Miami FL 33162",
    "addr:housenumber":"18241",
    "addr:postcode":"33162",
    "addr:street":"Ne 4Th Ct",
    "iso:country":"US",
    "sg:address":"18241 NE 4th Ct",
    "sg:city":"Miami",
    "sg:classifiers":[
        {
            "category":"Restaurant",
            "type":"Food & Drink"
        }
    ],
    "sg:phone":"+1 305 654 1854",
    "sg:postcode":"33162",
    "sg:province":"FL",
    "sg:tags":[
        "parlor",
        "ice",
        "cream"
    ],
    "wof:name":"Froz Fruit Delight",
    "wof:placetype":"venue"
},
  "geometry": {"coordinates":[-80.192156,25.943666],"type":"Point"}
}