{
  "type": "Feature",
  "properties": {
    "iso:country":"US",
    "sg:address":"1201 Summerfield Ct",
    "sg:city":"Orange Park",
    "sg:classifiers":[
        {
            "category":"Farming",
            "subcategory":"Farm & Veterinary Services",
            "type":"Manufacturing & Wholesale Goods"
        }
    ],
    "sg:phone":"+1 904 215 0060",
    "sg:postcode":"32073",
    "sg:province":"FL",
    "sg:tags":[
        "preparation",
        "soil"
    ],
    "wof:name":"Probedomain",
    "wof:placetype":"venue"
},
  "geometry": {"coordinates":[-81.74821900000001,30.141759],"type":"Point"}
}