{
  "type": "Feature",
  "properties": {
    "iso:country":"US",
    "sg:address":"4656 SW 72 Ave",
    "sg:city":"Miami",
    "sg:classifiers":[
        {
            "category":"Education",
            "subcategory":"School",
            "type":"Public Place"
        },
        {
            "category":"Personal",
            "subcategory":"Adult",
            "type":"Services"
        }
    ],
    "sg:phone":"+1 305 975 6227",
    "sg:postcode":"33155",
    "sg:province":"FL",
    "sg:tags":[
        "midwife"
    ],
    "sg:website":"www.motherpathdoulamiami.com/",
    "wof:name":"Motherpath Doula & Childbirth Education",
    "wof:placetype":"venue"
},
  "geometry": {"coordinates":[-80.31073600000001,25.726293],"type":"Point"}
}