{
  "type": "Feature",
  "properties": {
    "iso:country":"US",
    "sg:address":"4314 State Hwy 5",
    "sg:city":"Jacksonville",
    "sg:classifiers":[
        {
            "category":"Building & Trades",
            "subcategory":"Construction",
            "type":"Services"
        }
    ],
    "sg:phone":"+1 904 693 3007",
    "sg:postcode":"32207",
    "sg:province":"FL",
    "sg:tags":[
        "floor",
        "laying",
        "contractor"
    ],
    "wof:name":"Stamps Connection North Fla",
    "wof:placetype":"venue"
},
  "geometry": {"coordinates":[-81.627557,30.279069],"type":"Point"}
}