{
  "type": "Feature",
  "properties": {
    "iso:country":"US",
    "sg:address":"188 Carver Ave",
    "sg:city":"Atmore",
    "sg:classifiers":[
        {
            "category":"Organizations",
            "subcategory":"Religious Organization",
            "type":"Services"
        }
    ],
    "sg:phone":"+1 251 368 5750",
    "sg:postcode":"36502",
    "sg:province":"FL",
    "sg:tags":[
        "methodist",
        "church"
    ],
    "wof:name":"Methodist Church",
    "wof:placetype":"venue"
},
  "geometry": {"coordinates":[-87.479795,31.034909],"type":"Point"}
}