{
  "type": "Feature",
  "properties": {
    "iso:country":"US",
    "sg:address":"366 NW Alice St",
    "sg:city":"Stuart",
    "sg:classifiers":[
        {
            "category":"Arts & Performance",
            "subcategory":"Theater",
            "type":"Entertainment"
        }
    ],
    "sg:phone":"+1 772 334 0056",
    "sg:postcode":"34994",
    "sg:province":"FL",
    "sg:tags":[
        "group"
    ],
    "wof:name":"Paragon Entertainment Inc",
    "wof:placetype":"venue"
},
  "geometry": {"coordinates":[-80.249393,27.216836],"type":"Point"}
}