{
  "type": "Feature",
  "properties": {
    "addr:full":"1512 S Orange Ave Orlando FL 32806",
    "addr:housenumber":"1512",
    "addr:postcode":"32806",
    "addr:street":"S Orange Ave",
    "iso:country":"US",
    "sg:address":"1512 S Orange Ave",
    "sg:city":"Orlando",
    "sg:classifiers":[
        {
            "category":"Shopping",
            "subcategory":"Pharmacy",
            "type":"Retail Goods"
        }
    ],
    "sg:phone":"+1 407 649 6877",
    "sg:postcode":"32806",
    "sg:province":"FL",
    "wof:name":"Healthscript Pharmacy",
    "wof:placetype":"venue"
},
  "geometry": {"coordinates":[-81.376519,28.524929],"type":"Point"}
}