{
  "type": "Feature",
  "properties": {
    "addr:full":"14475 S Dixie Hwy Miami FL 33176",
    "addr:housenumber":"14475",
    "addr:postcode":"33176",
    "addr:street":"S Dixie Hwy",
    "iso:country":"US",
    "sg:address":"14475 S Dixie Hwy",
    "sg:city":"Miami",
    "sg:classifiers":[
        {
            "category":"Building & Trades",
            "subcategory":"Locksmith",
            "type":"Services"
        }
    ],
    "sg:phone":"+1 786 581 2440",
    "sg:postcode":"33176",
    "sg:province":"FL",
    "sg:tags":[
        "key"
    ],
    "wof:name":"Anytime Emergency Locksmith",
    "wof:placetype":"venue"
},
  "geometry": {"coordinates":[-80.33768499999999,25.635584],"type":"Point"}
}