{
  "type": "Feature",
  "properties": {
    "addr:full":"151 Southhall Ln Maitland FL 32751",
    "addr:housenumber":"151",
    "addr:postcode":"32751",
    "addr:street":"Southhall Ln",
    "iso:country":"US",
    "sg:address":"151 Southhall Ln",
    "sg:city":"Maitland",
    "sg:classifiers":[
        {
            "category":"Insurance",
            "subcategory":"Insurance Agent",
            "type":"Services"
        }
    ],
    "sg:phone":"+1 407 660 1918",
    "sg:postcode":"32751",
    "sg:province":"FL",
    "wof:name":"John Hancock",
    "wof:placetype":"venue"
},
  "geometry": {"coordinates":[-81.396428,28.628384],"type":"Point"}
}