{
  "type": "Feature",
  "properties": {
    "iso:country":"US",
    "sg:address":"3646 Henderson Blvd",
    "sg:city":"Tampa",
    "sg:phone":"+1 813 748 8818",
    "sg:postcode":"33609",
    "sg:province":"FL",
    "wof:name":"La DI DA Interiors",
    "wof:placetype":"venue"
},
  "geometry": {"coordinates":[-82.502903,27.936396],"type":"Point"}
}