{
  "type": "Feature",
  "properties": {
    "iso:country":"US",
    "sg:address":"665 N Dixie Fwy",
    "sg:city":"New Smyrna Beach",
    "sg:classifiers":[
        {
            "category":"Health Services",
            "subcategory":"Doctor",
            "type":"Services"
        }
    ],
    "sg:phone":"+1 386 423 5259",
    "sg:postcode":"32168",
    "sg:province":"FL",
    "sg:tags":[
        "medical"
    ],
    "wof:name":"Dougherty Chiropractic Clinic",
    "wof:placetype":"venue"
},
  "geometry": {"coordinates":[-80.929928,29.032899],"type":"Point"}
}