{
  "type": "Feature",
  "properties": {
    "iso:country":"US",
    "sg:address":"5520 W Flagler St",
    "sg:city":"Miami",
    "sg:classifiers":[
        {
            "category":"Building & Trades",
            "subcategory":"Electrical",
            "type":"Services"
        }
    ],
    "sg:phone":"+1 305 264 1400",
    "sg:postcode":"33134",
    "sg:province":"FL",
    "sg:tags":[
        "electrical",
        "contractor"
    ],
    "wof:name":"R-3 Corp",
    "wof:placetype":"venue"
},
  "geometry": {"coordinates":[-80.28529,25.770831],"type":"Point"}
}