{
  "type": "Feature",
  "properties": {
    "addr:full":"9499 NE 2nd Ave Fl 1st Miami Shores FL 33138",
    "addr:housenumber":"9499",
    "addr:postcode":"33138",
    "addr:street":"Ne 2Nd Ave",
    "iso:country":"US",
    "sg:address":"9499 NE 2nd Ave Fl 1st",
    "sg:city":"Miami Shores",
    "sg:classifiers":[
        {
            "category":"Banks & Credit Unions",
            "subcategory":"Bank",
            "type":"Services"
        },
        {
            "category":"Banks & Credit Unions",
            "subcategory":"Financial Services",
            "type":"Services"
        }
    ],
    "sg:phone":"+1 305 757 5511",
    "sg:postcode":"33138",
    "sg:province":"FL",
    "sg:tags":[
        "broker",
        "mortgage"
    ],
    "sg:website":"www.bankofamerica.com",
    "wof:name":"Bank of America",
    "wof:placetype":"venue"
},
  "geometry": {"coordinates":[-80.19338,25.862577],"type":"Point"}
}