{
  "type": "Feature",
  "properties": {
    "addr:full":"1901 Leonid Rd Jacksonville FL 32218",
    "addr:housenumber":"1901",
    "addr:postcode":"32218",
    "addr:street":"Leonid Rd",
    "iso:country":"US",
    "sg:address":"1901 Leonid Rd",
    "sg:city":"Jacksonville",
    "sg:classifiers":[
        {
            "category":"Organizations",
            "subcategory":"Religious Organization",
            "type":"Services"
        }
    ],
    "sg:phone":"+1 904 751 2404",
    "sg:postcode":"32218",
    "sg:province":"FL",
    "wof:name":"Northside Presbyterian Church",
    "wof:placetype":"venue"
},
  "geometry": {"coordinates":[-81.678192,30.429906],"type":"Point"}
}