{
  "type": "Feature",
  "properties": {
    "addr:full":"10019 Autumn Ln Pensacola FL 32514",
    "addr:housenumber":"10019",
    "addr:postcode":"32514",
    "addr:street":"Autumn Ln",
    "iso:country":"US",
    "sg:address":"10019 Autumn Ln",
    "sg:city":"Pensacola",
    "sg:classifiers":[
        {
            "category":"Real Estate",
            "subcategory":"Real Estate Services",
            "type":"Services"
        },
        {
            "category":"Real Estate",
            "subcategory":"Real Estate Agent",
            "type":"Services"
        }
    ],
    "sg:phone":"+1 850 478 5544",
    "sg:postcode":"32514",
    "sg:province":"FL",
    "sg:tags":[
        "management"
    ],
    "wof:name":"Mix Lisa Old South Properties",
    "wof:placetype":"venue"
},
  "geometry": {"coordinates":[-87.225769,30.54162],"type":"Point"}
}