{
  "type": "Feature",
  "properties": {
    "addr:full":"402 Beverly Pkwy Pensacola FL 32505",
    "addr:housenumber":"402",
    "addr:postcode":"32505",
    "addr:street":"Beverly Pkwy",
    "iso:country":"US",
    "sg:address":"402 Beverly Pkwy",
    "sg:city":"Pensacola",
    "sg:classifiers":[
        {
            "category":"Autos & Motor Vehicles",
            "subcategory":"Automobile Sales",
            "type":"Retail Goods"
        }
    ],
    "sg:phone":"+1 850 433 3328",
    "sg:postcode":"32505",
    "sg:province":"FL",
    "sg:tags":[
        "car",
        "dealer"
    ],
    "wof:name":"United Auto",
    "wof:placetype":"venue"
},
  "geometry": {"coordinates":[-87.25160700000001,30.464226],"type":"Point"}
}