{
  "type": "Feature",
  "properties": {
    "iso:country":"US",
    "sg:address":"4431 SW 64th Ave",
    "sg:city":"Fort Lauderdale",
    "sg:classifiers":[
        {
            "category":"Health Services",
            "subcategory":"Doctor",
            "type":"Services"
        }
    ],
    "sg:phone":"+1 954 791 5500",
    "sg:postcode":"33314",
    "sg:province":"FL",
    "sg:tags":[
        "physician"
    ],
    "wof:name":"Gerald R Safier Dr",
    "wof:placetype":"venue"
},
  "geometry": {"coordinates":[-80.232253,26.067038],"type":"Point"}
}