{
  "type": "Feature",
  "properties": {
    "iso:country":"US",
    "sg:address":"796 Hawks Blf",
    "sg:city":"Clermont",
    "sg:classifiers":[
        {
            "category":"Coffee & Tea",
            "type":"Food & Drink"
        },
        {
            "category":"Restaurant",
            "type":"Food & Drink"
        }
    ],
    "sg:phone":"+1 352 404 9777",
    "sg:postcode":"34711",
    "sg:province":"FL",
    "sg:tags":[
        "espresso"
    ],
    "wof:name":"Clermont Cafe",
    "wof:placetype":"venue"
},
  "geometry": {"coordinates":[-81.70041999999999,28.557417],"type":"Point"}
}