{
  "type": "Feature",
  "properties": {
    "iso:country":"US",
    "sg:address":"3120 Southgate Cir",
    "sg:city":"Sarasota",
    "sg:classifiers":[
        {
            "category":"Professional",
            "subcategory":"Secretarial Services",
            "type":"Services"
        }
    ],
    "sg:phone":"+1 941 923 7222",
    "sg:postcode":"34239",
    "sg:province":"FL",
    "sg:tags":[
        "reporting",
        "resume"
    ],
    "wof:name":"Sincerely Yours",
    "wof:placetype":"venue"
},
  "geometry": {"coordinates":[-82.51484000000001,27.305595],"type":"Point"}
}