{
  "type": "Feature",
  "properties": {
    "iso:country":"US",
    "sg:address":"7578 Cape Verde Ln",
    "sg:city":"Lake Worth",
    "sg:classifiers":[
        {
            "category":"Shopping",
            "subcategory":"Clothing, Apparel, & Fashions",
            "type":"Retail Goods"
        }
    ],
    "sg:phone":"+1 561 687 7387",
    "sg:postcode":"33467",
    "sg:province":"FL",
    "wof:name":"R M Originals",
    "wof:placetype":"venue"
},
  "geometry": {"coordinates":[-80.18542100000001,26.562758],"type":"Point"}
}