{
  "type": "Feature",
  "properties": {
    "iso:country":"US",
    "sg:address":"310 Westshore Plz",
    "sg:city":"Tampa",
    "sg:classifiers":[
        {
            "category":"Shopping",
            "subcategory":"Clothing, Apparel, & Fashions",
            "type":"Retail Goods"
        }
    ],
    "sg:phone":"+1 813 281 2321",
    "sg:postcode":"33609",
    "sg:province":"FL",
    "sg:tags":[
        "sportswear"
    ],
    "wof:name":"Sports Fan Attick Inc",
    "wof:placetype":"venue"
},
  "geometry": {"coordinates":[-82.52739800000001,27.946521],"type":"Point"}
}