{
  "type": "Feature",
  "properties": {
    "iso:country":"US",
    "sg:address":"10148 Ford Rd",
    "sg:city":"Bryceville",
    "sg:classifiers":[
        {
            "category":"Professional",
            "subcategory":"Detective & Security Services",
            "type":"Services"
        }
    ],
    "sg:phone":"+1 904 879 5185",
    "sg:postcode":"32009",
    "sg:province":"FL",
    "sg:tags":[
        "information",
        "bureau"
    ],
    "wof:name":"Mikes Repair Service",
    "wof:placetype":"venue"
},
  "geometry": {"coordinates":[-81.88138499999999,30.436043],"type":"Point"}
}