{
  "type": "Feature",
  "properties": {
    "addr:full":"507 N New York Ave Winter Park FL 32789",
    "addr:housenumber":"507",
    "addr:postcode":"32789",
    "addr:street":"N New York Ave",
    "iso:country":"US",
    "sg:address":"507 N New York Ave",
    "sg:city":"Winter Park",
    "sg:classifiers":[
        {
            "category":"Real Estate",
            "subcategory":"Real Estate Agent",
            "type":"Services"
        }
    ],
    "sg:phone":"+1 407 975 3311",
    "sg:postcode":"32789",
    "sg:province":"FL",
    "wof:name":"Florida Living Properties Inc",
    "wof:placetype":"venue"
},
  "geometry": {"coordinates":[-81.352869,28.601923],"type":"Point"}
}