{
  "type": "Feature",
  "properties": {
    "iso:country":"US",
    "sg:address":"1670 Thomas St",
    "sg:city":"Englewood",
    "sg:classifiers":[
        {
            "category":"Building & Trades",
            "subcategory":"Construction",
            "type":"Services"
        }
    ],
    "sg:phone":"+1 941 474 1000",
    "sg:postcode":"34223",
    "sg:province":"FL",
    "sg:tags":[
        "contractor"
    ],
    "wof:name":"Gary Bradshaw",
    "wof:placetype":"venue"
},
  "geometry": {"coordinates":[-82.401121,27.012748],"type":"Point"}
}