{
  "type": "Feature",
  "properties": {
    "iso:country":"US",
    "sg:address":"5008 Millenia Blvd",
    "sg:city":"Orlando",
    "sg:classifiers":[
        {
            "category":"Retail",
            "subcategory":"Car Wash",
            "type":"Services"
        }
    ],
    "sg:phone":"+1 407 354 4897",
    "sg:postcode":"32839",
    "sg:province":"FL",
    "sg:tags":[
        "carwash"
    ],
    "wof:name":"Gustavo Dumont Auto Detailing",
    "wof:placetype":"venue"
},
  "geometry": {"coordinates":[-81.440845,28.484946],"type":"Point"}
}