{
  "type": "Feature",
  "properties": {
    "addr:full":"1645 W Main St Inverness FL 34450",
    "addr:housenumber":"1645",
    "addr:postcode":"34450",
    "addr:street":"W Main St",
    "iso:country":"US",
    "sg:address":"1645 W Main St",
    "sg:city":"Inverness",
    "sg:classifiers":[
        {
            "category":"Real Estate",
            "subcategory":"Real Estate Agent",
            "type":"Services"
        }
    ],
    "sg:phone":"+1 352 726 6668",
    "sg:postcode":"34450",
    "sg:province":"FL",
    "wof:name":"J W Mortin Realastate Inc",
    "wof:placetype":"venue"
},
  "geometry": {"coordinates":[-82.34886400000001,28.835974],"type":"Point"}
}