{
  "type": "Feature",
  "properties": {
    "iso:country":"US",
    "sg:address":"1368 Elcon Dr",
    "sg:city":"Melbourne",
    "sg:classifiers":[
        {
            "category":"Restaurant",
            "type":"Food & Drink"
        }
    ],
    "sg:phone":"+1 321 727 8174",
    "sg:postcode":"32904",
    "sg:province":"FL",
    "sg:tags":[
        "eating"
    ],
    "wof:name":"Red Rooster Quiltworks",
    "wof:placetype":"venue"
},
  "geometry": {"coordinates":[-80.641772,28.05082],"type":"Point"}
}