{
  "type": "Feature",
  "properties": {
    "addr:full":"1138 Edgewood Ave S Jacksonville FL 32205",
    "addr:housenumber":"1138",
    "addr:postcode":"32205",
    "addr:street":"Edgewood Ave S",
    "iso:country":"US",
    "sg:address":"1138 Edgewood Ave S",
    "sg:city":"Jacksonville",
    "sg:classifiers":[
        {
            "category":"Building & Trades",
            "subcategory":"Construction",
            "type":"Services"
        }
    ],
    "sg:phone":"+1 904 908 0063",
    "sg:postcode":"32205",
    "sg:province":"FL",
    "sg:tags":[
        "waterproofing",
        "contractor"
    ],
    "wof:name":"C E Painting & Caulking",
    "wof:placetype":"venue"
},
  "geometry": {"coordinates":[-81.715553,30.310011],"type":"Point"}
}