{
  "type": "Feature",
  "properties": {
    "iso:country":"US",
    "sg:address":"30000 SW 168th Ct",
    "sg:city":"Homestead",
    "sg:classifiers":[
        {
            "category":"Building & Trades",
            "subcategory":"Landscaping Services",
            "type":"Services"
        }
    ],
    "sg:phone":"+1 305 248 9173",
    "sg:postcode":"33030",
    "sg:province":"FL",
    "wof:name":"Davis & Sons",
    "wof:placetype":"venue"
},
  "geometry": {"coordinates":[-80.46417099999999,25.4876],"type":"Point"}
}