{
  "type": "Feature",
  "properties": {
    "iso:country":"US",
    "sg:address":"189 Hague Ct",
    "sg:city":"Spring Hill",
    "sg:classifiers":[
        {
            "category":"Retail",
            "subcategory":"Car Wash",
            "type":"Services"
        }
    ],
    "sg:phone":"+1 352 398 3865",
    "sg:postcode":"34606",
    "sg:province":"FL",
    "sg:tags":[
        "automobile",
        "detail",
        "clean"
    ],
    "wof:name":"Ryan M Odell Detailing",
    "wof:placetype":"venue"
},
  "geometry": {"coordinates":[-82.610349,28.435069],"type":"Point"}
}