{
  "type": "Feature",
  "properties": {
    "iso:country":"US",
    "sg:address":"5617 NW 7th St",
    "sg:city":"Miami",
    "sg:classifiers":[
        {
            "category":"Taxi",
            "type":"Transportation"
        }
    ],
    "sg:phone":"+1 305 263 3000",
    "sg:postcode":"33126",
    "sg:province":"FL",
    "wof:name":"Miami Cab",
    "wof:placetype":"venue"
},
  "geometry": {"coordinates":[-80.286726,25.778187],"type":"Point"}
}