{
  "type": "Feature",
  "properties": {
    "addr:full":"336 Milestone Dr Tallahassee FL 32312",
    "addr:housenumber":"336",
    "addr:postcode":"32312",
    "addr:street":"Milestone Dr",
    "iso:country":"US",
    "sg:address":"336 Milestone Dr",
    "sg:city":"Tallahassee",
    "sg:classifiers":[
        {
            "category":"Building & Trades",
            "subcategory":"Electrical",
            "type":"Services"
        }
    ],
    "sg:phone":"+1 850 545 2119",
    "sg:postcode":"32312",
    "sg:province":"FL",
    "sg:tags":[
        "electrician",
        "contractor"
    ],
    "wof:name":"A & L Electric",
    "wof:placetype":"venue"
},
  "geometry": {"coordinates":[-84.270332,30.55271],"type":"Point"}
}