{
  "type": "Feature",
  "properties": {
    "addr:full":"2066 N Florida Ave Hernando FL 34442",
    "addr:housenumber":"2066",
    "addr:postcode":"34442",
    "addr:street":"N Florida Ave",
    "iso:country":"US",
    "sg:address":"2066 N Florida Ave",
    "sg:city":"Hernando",
    "sg:classifiers":[
        {
            "category":"Home & Garden",
            "subcategory":"Home Furnishings",
            "type":"Retail Goods"
        }
    ],
    "sg:phone":"+1 352 726 8092",
    "sg:postcode":"34442",
    "sg:province":"FL",
    "sg:tags":[
        "curtain",
        "fabric",
        "drapery"
    ],
    "wof:name":"Greiner's Window Fashions",
    "wof:placetype":"venue"
},
  "geometry": {"coordinates":[-82.370221,28.893488],"type":"Point"}
}