{
  "type": "Feature",
  "properties": {
    "addr:full":"1914 Hillman Farms Rd De Leon Springs FL 32130",
    "addr:housenumber":"1914",
    "addr:postcode":"32130",
    "addr:street":"Hillman Farms Rd De Leon",
    "iso:country":"US",
    "sg:address":"1914 Hillman Farms Rd",
    "sg:city":"De Leon Springs",
    "sg:classifiers":[
        {
            "category":"Building & Trades",
            "subcategory":"Construction",
            "type":"Services"
        }
    ],
    "sg:phone":"+1 386 985 2255",
    "sg:postcode":"32130",
    "sg:province":"FL",
    "wof:name":"Slims Landclearing Inc",
    "wof:placetype":"venue"
},
  "geometry": {"coordinates":[-81.30666100000001,29.189574],"type":"Point"}
}