{
  "type": "Feature",
  "properties": {
    "iso:country":"US",
    "sg:address":"7148 Bonaventure Dr",
    "sg:city":"Tampa",
    "sg:classifiers":[
        {
            "category":"Food & Beverages",
            "subcategory":"Groceries & Convenience Stores",
            "type":"Retail Goods"
        }
    ],
    "sg:phone":"+1 813 281 1902",
    "sg:postcode":"33607",
    "sg:province":"FL",
    "sg:tags":[
        "market"
    ],
    "wof:name":"Rocky Point Market",
    "wof:placetype":"venue"
},
  "geometry": {"coordinates":[-82.561211,27.971575],"type":"Point"}
}