{
  "type": "Feature",
  "properties": {
    "iso:country":"US",
    "sg:address":"1381 Ohio Ave",
    "sg:city":"Dunedin",
    "sg:classifiers":[
        {
            "category":"Arts & Performance",
            "subcategory":"Theater",
            "type":"Entertainment"
        }
    ],
    "sg:phone":"+1 727 733 9005",
    "sg:postcode":"34698",
    "sg:province":"FL",
    "sg:tags":[
        "bureau"
    ],
    "wof:name":"Themes N' Schemes",
    "wof:placetype":"venue"
},
  "geometry": {"coordinates":[-82.767242,28.024454],"type":"Point"}
}