{
  "type": "Feature",
  "properties": {
    "iso:country":"US",
    "sg:address":"1500 NW 65th Ave",
    "sg:city":"Plantation",
    "sg:classifiers":[
        {
            "category":"Autos & Motor Vehicles",
            "subcategory":"Automobile Sales",
            "type":"Retail Goods"
        }
    ],
    "sg:phone":"+1 954 581 7766",
    "sg:postcode":"33313",
    "sg:province":"FL",
    "sg:tags":[
        "car",
        "used"
    ],
    "wof:name":"American Auto Carriage",
    "wof:placetype":"venue"
},
  "geometry": {"coordinates":[-80.235936,26.144654],"type":"Point"}
}