{
  "type": "Feature",
  "properties": {
    "iso:country":"US",
    "sg:address":"25850 Blue Jay Pl",
    "sg:city":"Zephyrhills",
    "sg:classifiers":[
        {
            "category":"Building & Trades",
            "subcategory":"Construction",
            "type":"Services"
        }
    ],
    "sg:phone":"+1 813 973 8922",
    "sg:postcode":"33544",
    "sg:province":"FL",
    "sg:tags":[
        "contractor"
    ],
    "wof:name":"Diamond Contracting Inc",
    "wof:placetype":"venue"
},
  "geometry": {"coordinates":[-82.38811,28.279052],"type":"Point"}
}