{
  "type": "Feature",
  "properties": {
    "iso:country":"US",
    "sg:address":"3600 42nd St S",
    "sg:city":"St Petersburg",
    "sg:classifiers":[
        {
            "category":"Wholesale",
            "subcategory":"Construction Materials",
            "type":"Manufacturing & Wholesale Goods"
        },
        {
            "category":"Shopping",
            "type":"Retail Goods"
        }
    ],
    "sg:phone":"+1 727 521 0636",
    "sg:postcode":"33711",
    "sg:province":"FL",
    "sg:tags":[
        "granite",
        "merchandise"
    ],
    "wof:name":"Granite Masters",
    "wof:placetype":"venue"
},
  "geometry": {"coordinates":[-82.69040099999999,27.735638],"type":"Point"}
}