{
  "type": "Feature",
  "properties": {
    "iso:country":"US",
    "sg:address":"7100 NE 2nd Ave",
    "sg:city":"Miami",
    "sg:classifiers":[
        {
            "category":"Autos & Motor Vehicles",
            "subcategory":"Automobile Sales",
            "type":"Retail Goods"
        }
    ],
    "sg:phone":"+1 305 754 5400",
    "sg:postcode":"33138",
    "sg:province":"FL",
    "sg:tags":[
        "car",
        "dealer"
    ],
    "wof:name":"Eben-Etzers Auto Sales",
    "wof:placetype":"venue"
},
  "geometry": {"coordinates":[-80.192525,25.840532],"type":"Point"}
}