{
  "type": "Feature",
  "properties": {
    "iso:country":"US",
    "sg:address":"3000 SW 3rd Ave",
    "sg:city":"Miami",
    "sg:classifiers":[
        {
            "category":"Deli",
            "type":"Food & Drink"
        }
    ],
    "sg:phone":"+1 305 854 2410",
    "sg:postcode":"33129",
    "sg:province":"FL",
    "sg:tags":[
        "delicatessen"
    ],
    "wof:name":"Ferreiro Delicatessen & Fine C",
    "wof:placetype":"venue"
},
  "geometry": {"coordinates":[-80.211693,25.75309],"type":"Point"}
}