{
  "type": "Feature",
  "properties": {
    "iso:country":"US",
    "sg:address":"11173 105th Ln N",
    "sg:city":"Largo",
    "sg:classifiers":[
        {
            "category":"Shopping",
            "type":"Retail Goods"
        }
    ],
    "sg:phone":"+1 727 455 7678",
    "sg:postcode":"33773",
    "sg:province":"FL",
    "sg:tags":[
        "merchandise"
    ],
    "wof:name":"Michael Willetts Cleanup",
    "wof:placetype":"venue"
},
  "geometry": {"coordinates":[-82.78534999999999,27.873761],"type":"Point"}
}