{
  "type": "Feature",
  "properties": {
    "iso:country":"US",
    "sg:address":"10700 Caribbean Blvd",
    "sg:city":"Miami",
    "sg:classifiers":[
        {
            "category":"Autos & Motor Vehicles",
            "subcategory":"Automobile Sales",
            "type":"Retail Goods"
        }
    ],
    "sg:phone":"+1 305 233 1130",
    "sg:postcode":"33189",
    "sg:province":"FL",
    "sg:tags":[
        "car",
        "used"
    ],
    "wof:name":"Car Dome Inc",
    "wof:placetype":"venue"
},
  "geometry": {"coordinates":[-80.364774,25.577064],"type":"Point"}
}