{
  "type": "Feature",
  "properties": {
    "iso:country":"US",
    "sg:address":"271 16th St NE",
    "sg:city":"Naples",
    "sg:classifiers":[
        {
            "category":"Real Estate",
            "subcategory":"Real Estate Agent",
            "type":"Services"
        }
    ],
    "sg:phone":"+1 239 352 8592",
    "sg:postcode":"34120",
    "sg:province":"FL",
    "wof:name":"Joe Olivera Inc",
    "wof:placetype":"venue"
},
  "geometry": {"coordinates":[-81.574455,26.242975],"type":"Point"}
}