{
  "type": "Feature",
  "properties": {
    "iso:country":"US",
    "sg:address":"14050 Town Loop Blvd",
    "sg:city":"Orlando",
    "sg:classifiers":[
        {
            "category":"Health Services",
            "subcategory":"Clinic",
            "type":"Services"
        }
    ],
    "sg:phone":"+1 407 239 6441",
    "sg:postcode":"32837",
    "sg:province":"FL",
    "sg:tags":[
        "osteopathic"
    ],
    "wof:name":"Allan T Pratt Do",
    "wof:placetype":"venue"
},
  "geometry": {"coordinates":[-81.42047100000001,28.3617],"type":"Point"}
}