{
  "type": "Feature",
  "properties": {
    "iso:country":"US",
    "sg:address":"7125 Fruitville Rd",
    "sg:city":"Sarasota",
    "sg:classifiers":[
        {
            "category":"Travel",
            "subcategory":"Hotels & Motels",
            "type":"Entertainment"
        }
    ],
    "sg:phone":"+1 941 371 8758",
    "sg:postcode":"34240",
    "sg:province":"FL",
    "sg:tags":[
        "resort",
        "restaurant"
    ],
    "wof:name":"Toucans Restaurant",
    "wof:placetype":"venue"
},
  "geometry": {"coordinates":[-82.427249,27.338355],"type":"Point"}
}