{
  "type": "Feature",
  "properties": {
    "iso:country":"US",
    "sg:address":"12941 NW 2nd St",
    "sg:city":"Pembroke Pines",
    "sg:classifiers":[
        {
            "category":"Professional",
            "subcategory":"Research",
            "type":"Services"
        }
    ],
    "sg:phone":"+1 954 441 2215",
    "sg:postcode":"33028",
    "sg:province":"FL",
    "sg:website":"www.dslfinder.net",
    "wof:name":"DSLFINDER.NET",
    "wof:placetype":"venue"
},
  "geometry": {"coordinates":[-80.322052,26.009144],"type":"Point"}
}