{
  "type": "Feature",
  "properties": {
    "addr:full":"24 N Market St # 404 Jacksonville FL 32202",
    "addr:housenumber":"24",
    "addr:postcode":"32202",
    "addr:street":"N Market St # 404",
    "iso:country":"US",
    "sg:address":"24 N Market St # 404",
    "sg:city":"Jacksonville",
    "sg:classifiers":[
        {
            "category":"Professional",
            "subcategory":"Lawyer & Legal Services",
            "type":"Services"
        }
    ],
    "sg:phone":"+1 904 356 8618",
    "sg:postcode":"32202",
    "sg:province":"FL",
    "sg:tags":[
        "practice",
        "attorney",
        "criminal",
        "law"
    ],
    "wof:name":"Armstrong & Stripling",
    "wof:placetype":"venue"
},
  "geometry": {"coordinates":[-81.654298,30.32559],"type":"Point"}
}