{
  "type": "Feature",
  "properties": {
    "iso:country":"US",
    "sg:address":"350 Gulf Blvd",
    "sg:city":"Indian Rocks Beach",
    "sg:classifiers":[
        {
            "category":"Health Services",
            "subcategory":"Medical Lab",
            "type":"Services"
        }
    ],
    "sg:phone":"+1 727 596 5966",
    "sg:postcode":"33785",
    "sg:province":"FL",
    "sg:tags":[
        "laboratory"
    ],
    "wof:name":"M J Henderson Enterprises LLC",
    "wof:placetype":"venue"
},
  "geometry": {"coordinates":[-82.850488,27.881512],"type":"Point"}
}