{
  "type": "Feature",
  "properties": {
    "addr:full":"519 Cleveland St Clearwater FL 33755",
    "addr:housenumber":"519",
    "addr:postcode":"33755",
    "addr:street":"Cleveland St",
    "iso:country":"US",
    "sg:address":"519 Cleveland St",
    "sg:city":"Clearwater",
    "sg:classifiers":[
        {
            "category":"Wholesale",
            "subcategory":"Non-durable Goods",
            "type":"Manufacturing & Wholesale Goods"
        }
    ],
    "sg:phone":"+1 727 631 0707",
    "sg:postcode":"33755",
    "sg:province":"FL",
    "sg:tags":[
        "advertising"
    ],
    "wof:name":"Bi-USA Inc",
    "wof:placetype":"venue"
},
  "geometry": {"coordinates":[-82.79875699999999,27.965559],"type":"Point"}
}