{
  "type": "Feature",
  "properties": {
    "addr:full":"4830 W Kennedy Blvd Tampa FL 33609",
    "addr:housenumber":"4830",
    "addr:postcode":"33609",
    "addr:street":"W Kennedy Blvd",
    "iso:country":"US",
    "sg:address":"4830 W Kennedy Blvd",
    "sg:city":"Tampa",
    "sg:classifiers":[
        {
            "category":"Retail",
            "subcategory":"Laundry & Dry Cleaning",
            "type":"Services"
        }
    ],
    "sg:phone":"+1 813 281 2580",
    "sg:postcode":"33609",
    "sg:province":"FL",
    "sg:tags":[
        "cleaners"
    ],
    "wof:name":"Classic Cleaners",
    "wof:placetype":"venue"
},
  "geometry": {"coordinates":[-82.525744,27.944759],"type":"Point"}
}