{
  "type": "Feature",
  "properties": {
    "iso:country":"US",
    "sg:address":"4405 NW 73rd Ave",
    "sg:city":"Miami",
    "sg:classifiers":[
        {
            "category":"Freight",
            "type":"Transportation"
        }
    ],
    "sg:phone":"+1 305 599 1812",
    "sg:postcode":"33166",
    "sg:province":"FL",
    "wof:name":"Sky Postal Inc",
    "wof:placetype":"venue"
},
  "geometry": {"coordinates":[-80.315331,25.814389],"type":"Point"}
}