{
  "type": "Feature",
  "properties": {
    "addr:full":"23775 SW 122nd Ave Homestead FL 33032",
    "addr:housenumber":"23775",
    "addr:postcode":"33032",
    "addr:street":"Sw 122Nd Ave",
    "iso:country":"US",
    "sg:address":"23775 SW 122nd Ave",
    "sg:city":"Homestead",
    "sg:classifiers":[
        {
            "category":"Building & Trades",
            "subcategory":"Construction",
            "type":"Services"
        }
    ],
    "sg:phone":"+1 305 258 4337",
    "sg:postcode":"33032",
    "sg:province":"FL",
    "sg:tags":[
        "house",
        "family"
    ],
    "wof:name":"American Design Construction",
    "wof:placetype":"venue"
},
  "geometry": {"coordinates":[-80.388271,25.545798],"type":"Point"}
}