{
  "type": "Feature",
  "properties": {
    "iso:country":"US",
    "sg:address":"16160 SW 250th St",
    "sg:city":"Homestead",
    "sg:classifiers":[
        {
            "category":"Building & Trades",
            "subcategory":"Construction",
            "type":"Services"
        }
    ],
    "sg:phone":"+1 305 248 2838",
    "sg:postcode":"33031",
    "sg:province":"FL",
    "sg:tags":[
        "hanging",
        "painter",
        "contractor"
    ],
    "wof:name":"H & F Painting Corp",
    "wof:placetype":"venue"
},
  "geometry": {"coordinates":[-80.452006,25.534161],"type":"Point"}
}