{
  "type": "Feature",
  "properties": {
    "iso:country":"US",
    "sg:address":"4 Seatrout St",
    "sg:city":"Ponte Vedra Beach",
    "sg:classifiers":[
        {
            "category":"Building & Trades",
            "subcategory":"Construction",
            "type":"Services"
        }
    ],
    "sg:phone":"+1 904 543 1300",
    "sg:postcode":"32082",
    "sg:province":"FL",
    "sg:tags":[
        "contractor"
    ],
    "wof:name":"Sunlight Solutions",
    "wof:placetype":"venue"
},
  "geometry": {"coordinates":[-81.390293,30.236206],"type":"Point"}
}