{
  "type": "Feature",
  "properties": {
    "iso:country":"US",
    "sg:address":"107 Moccasin Creek Dr",
    "sg:city":"Palatka",
    "sg:classifiers":[
        {
            "category":"Building & Trades",
            "subcategory":"Construction",
            "type":"Services"
        }
    ],
    "sg:phone":"+1 904 613 9788",
    "sg:postcode":"32177",
    "sg:province":"FL",
    "sg:tags":[
        "restoration",
        "cleaning",
        "patio",
        "deck"
    ],
    "wof:name":"Zippy's Pressure Wash",
    "wof:placetype":"venue"
},
  "geometry": {"coordinates":[-81.653228,29.718062],"type":"Point"}
}