{
  "type": "Feature",
  "properties": {
    "addr:full":"261 Winter Springs Way Jacksonville FL 32225",
    "addr:housenumber":"261",
    "addr:postcode":"32225",
    "addr:street":"Winter Springs Way",
    "iso:country":"US",
    "sg:address":"261 Winter Springs Way",
    "sg:city":"Jacksonville",
    "sg:classifiers":[
        {
            "category":"Building & Trades",
            "subcategory":"Landscaping Services",
            "type":"Services"
        }
    ],
    "sg:phone":"+1 904 221 9456",
    "sg:postcode":"32225",
    "sg:province":"FL",
    "wof:name":"Discount Lawn Care Inc",
    "wof:placetype":"venue"
},
  "geometry": {"coordinates":[-81.47126,30.32704],"type":"Point"}
}