{
  "type": "Feature",
  "properties": {
    "iso:country":"US",
    "sg:address":"123 E Morse Blvd",
    "sg:city":"Winter Park",
    "sg:classifiers":[
        {
            "category":"Home & Garden",
            "subcategory":"Furniture",
            "type":"Retail Goods"
        }
    ],
    "sg:phone":"+1 407 691 0404",
    "sg:postcode":"32789",
    "sg:province":"FL",
    "sg:tags":[
        "store"
    ],
    "wof:name":"The Baraka Collection",
    "wof:placetype":"venue"
},
  "geometry": {"coordinates":[-81.35057500000001,28.597975],"type":"Point"}
}