{
  "type": "Feature",
  "properties": {
    "iso:country":"US",
    "sg:address":"2494 Stonebridge Dr",
    "sg:city":"Orange Park",
    "sg:classifiers":[
        {
            "category":"Real Estate",
            "subcategory":"Real Estate Operator",
            "type":"Services"
        }
    ],
    "sg:phone":"+1 904 276 0795",
    "sg:postcode":"32065",
    "sg:province":"FL",
    "sg:tags":[
        "building",
        "nonresidential"
    ],
    "wof:name":"Byers Properties Inc",
    "wof:placetype":"venue"
},
  "geometry": {"coordinates":[-81.760964,30.149549],"type":"Point"}
}