{
  "type": "Feature",
  "properties": {
    "iso:country":"US",
    "sg:address":"11415 S Dixie Hwy",
    "sg:city":"Miami",
    "sg:classifiers":[
        {
            "category":"Restaurant",
            "type":"Food & Drink"
        }
    ],
    "sg:phone":"+1 305 378 4000",
    "sg:postcode":"33156",
    "sg:province":"FL",
    "sg:tags":[
        "traditional",
        "american"
    ],
    "sg:website":"www.flanigans.net",
    "wof:name":"Flanigan's Seafood Bar & Grill",
    "wof:placetype":"venue"
},
  "geometry": {"coordinates":[-80.324051,25.664334],"type":"Point"}
}