{
  "type": "Feature",
  "properties": {
    "addr:full":"4395 SW 117th Ave Miami FL 33175",
    "addr:housenumber":"4395",
    "addr:postcode":"33175",
    "addr:street":"Sw 117Th Ave",
    "iso:country":"US",
    "sg:address":"4395 SW 117th Ave",
    "sg:city":"Miami",
    "sg:classifiers":[
        {
            "category":"Building & Trades",
            "subcategory":"Construction",
            "type":"Services"
        }
    ],
    "sg:phone":"+1 305 221 3260",
    "sg:postcode":"33175",
    "sg:province":"FL",
    "sg:tags":[
        "contractor"
    ],
    "wof:name":"Carus & Son Tile & Marble Inc",
    "wof:placetype":"venue"
},
  "geometry": {"coordinates":[-80.38289,25.725542],"type":"Point"}
}