{
  "type": "Feature",
  "properties": {
    "addr:full":"3720 Inverrary Dr Fort Lauderdale FL 33319",
    "addr:housenumber":"3720",
    "addr:postcode":"33319",
    "addr:street":"Inverrary Dr",
    "iso:country":"US",
    "sg:address":"3720 Inverrary Dr",
    "sg:city":"Fort Lauderdale",
    "sg:classifiers":[
        {
            "category":"Professional",
            "subcategory":"Art Services",
            "type":"Services"
        }
    ],
    "sg:phone":"+1 954 484 5520",
    "sg:postcode":"33319",
    "sg:province":"FL",
    "sg:tags":[
        "commercial",
        "design"
    ],
    "wof:name":"Castle Forge",
    "wof:placetype":"venue"
},
  "geometry": {"coordinates":[-80.227689,26.17095],"type":"Point"}
}