{
  "type": "Feature",
  "properties": {
    "iso:country":"US",
    "sg:address":"5502 Central Florida Pkwy",
    "sg:city":"Orlando",
    "sg:classifiers":[
        {
            "category":"Autos & Motor Vehicles",
            "subcategory":"Fuel & Gas Station",
            "type":"Retail Goods"
        }
    ],
    "sg:phone":"+1 407 239 8686",
    "sg:postcode":"32821",
    "sg:province":"FL",
    "sg:tags":[
        "oil"
    ],
    "wof:name":"Mobil Oil Corp",
    "wof:placetype":"venue"
},
  "geometry": {"coordinates":[-81.450739,28.407839],"type":"Point"}
}