{
  "type": "Feature",
  "properties": {
    "iso:country":"US",
    "sg:address":"331 31st St W",
    "sg:city":"Bradenton",
    "sg:classifiers":[
        {
            "category":"Retail",
            "subcategory":"Animal Services",
            "type":"Services"
        }
    ],
    "sg:phone":"+1 941 747 4342",
    "sg:postcode":"34205",
    "sg:province":"FL",
    "sg:tags":[
        "breeder",
        "mastiff"
    ],
    "wof:name":"Oaklane Mastiffs",
    "wof:placetype":"venue"
},
  "geometry": {"coordinates":[-82.59245799999999,27.496932],"type":"Point"}
}