{
  "type": "Feature",
  "properties": {
    "iso:country":"US",
    "sg:address":"28 Quail Ln",
    "sg:city":"Jacksonville Beach",
    "sg:classifiers":[
        {
            "category":"Building & Trades",
            "subcategory":"Construction",
            "type":"Services"
        }
    ],
    "sg:phone":"+1 904 246 1771",
    "sg:postcode":"32250",
    "sg:province":"FL",
    "sg:tags":[
        "hanging",
        "painting",
        "hand",
        "contractor"
    ],
    "wof:name":"Labor By Lucas",
    "wof:placetype":"venue"
},
  "geometry": {"coordinates":[-81.404805,30.27345],"type":"Point"}
}