{
  "type": "Feature",
  "properties": {
    "addr:full":"4427 US Hwy 90 Milton FL 32571",
    "addr:housenumber":"4427",
    "addr:postcode":"32571",
    "addr:street":"Us Hwy 90",
    "iso:country":"US",
    "sg:address":"4427 US Hwy 90",
    "sg:city":"Milton",
    "sg:classifiers":[
        {
            "category":"Shopping",
            "subcategory":"Optical Goods",
            "type":"Retail Goods"
        }
    ],
    "sg:phone":"+1 850 994 8400",
    "sg:postcode":"32571",
    "sg:province":"FL",
    "sg:tags":[
        "medical"
    ],
    "sg:website":"www.centerforsight.org",
    "wof:name":"Center For Sight",
    "wof:placetype":"venue"
},
  "geometry": {"coordinates":[-87.138634,30.603575],"type":"Point"}
}