{
  "type": "Feature",
  "properties": {
    "addr:full":"3778 SW 127th Ave Miami FL 33175",
    "addr:housenumber":"3778",
    "addr:postcode":"33175",
    "addr:street":"Sw 127Th Ave",
    "iso:country":"US",
    "sg:address":"3778 SW 127th Ave",
    "sg:city":"Miami",
    "sg:classifiers":[
        {
            "category":"Building & Trades",
            "subcategory":"Landscaping Services",
            "type":"Services"
        }
    ],
    "sg:phone":"+1 305 220 5429",
    "sg:postcode":"33175",
    "sg:province":"FL",
    "sg:tags":[
        "lawn"
    ],
    "wof:name":"Liliana Aguilar Landscape",
    "wof:placetype":"venue"
},
  "geometry": {"coordinates":[-80.399754,25.733597],"type":"Point"}
}