{
  "type": "Feature",
  "properties": {
    "addr:full":"5539 Marine Pkwy New Port Richey FL 34652",
    "addr:housenumber":"5539",
    "addr:postcode":"34652",
    "addr:street":"Marine Pkwy",
    "iso:country":"US",
    "sg:address":"5539 Marine Pkwy",
    "sg:city":"New Port Richey",
    "sg:classifiers":[
        {
            "category":"Health Services",
            "subcategory":"Medical Lab",
            "type":"Services"
        }
    ],
    "sg:phone":"+1 727 848 1073",
    "sg:postcode":"34652",
    "sg:province":"FL",
    "sg:tags":[
        "laboratory"
    ],
    "wof:name":"Quest Diagnostics",
    "wof:placetype":"venue"
},
  "geometry": {"coordinates":[-82.721152,28.234176],"type":"Point"}
}