{
  "type": "Feature",
  "properties": {
    "iso:country":"US",
    "sg:address":"2277 Trade Center Way",
    "sg:city":"Naples",
    "sg:classifiers":[
        {
            "category":"Professional",
            "subcategory":"Business Services",
            "type":"Services"
        }
    ],
    "sg:phone":"+1 239 514 2700",
    "sg:postcode":"34109",
    "sg:province":"FL",
    "sg:tags":[
        "interior",
        "consultant",
        "design",
        "decorator"
    ],
    "wof:name":"Vanderbilts",
    "wof:placetype":"venue"
},
  "geometry": {"coordinates":[-81.780294,26.225196],"type":"Point"}
}