{
  "type": "Feature",
  "properties": {
    "iso:country":"US",
    "sg:address":"20651 Wildcat Run Dr",
    "sg:city":"Estero",
    "sg:classifiers":[
        {
            "category":"Manufacturing",
            "subcategory":"Toys & Sporting Goods",
            "type":"Manufacturing & Wholesale Goods"
        }
    ],
    "sg:phone":"+1 239 498 0908",
    "sg:postcode":"33928",
    "sg:province":"FL",
    "sg:tags":[
        "mfg"
    ],
    "wof:name":"Upright Caddy Co",
    "wof:placetype":"venue"
},
  "geometry": {"coordinates":[-81.74829800000001,26.428012],"type":"Point"}
}