{
  "type": "Feature",
  "properties": {
    "iso:country":"US",
    "sg:address":"543 W Pine Rd",
    "sg:city":"Melbourne",
    "sg:classifiers":[
        {
            "category":"Professional",
            "subcategory":"Accounting & Tax Preparation",
            "type":"Services"
        }
    ],
    "sg:phone":"+1 321 725 2103",
    "sg:postcode":"32904",
    "sg:province":"FL",
    "sg:tags":[
        "accountant"
    ],
    "wof:name":"Jeanne B Libbee CPA",
    "wof:placetype":"venue"
},
  "geometry": {"coordinates":[-80.67008,28.088972],"type":"Point"}
}