{
  "type": "Feature",
  "properties": {
    "iso:country":"US",
    "sg:address":"14375 SW 119th Ave",
    "sg:city":"Miami",
    "sg:classifiers":[
        {
            "category":"Real Estate",
            "subcategory":"Real Estate Operator",
            "type":"Services"
        }
    ],
    "sg:phone":"+1 305 234 7488",
    "sg:postcode":"33186",
    "sg:province":"FL",
    "sg:tags":[
        "apartment"
    ],
    "wof:name":"Xena International Llc",
    "wof:placetype":"venue"
},
  "geometry": {"coordinates":[-80.38663099999999,25.634181],"type":"Point"}
}