{
  "type": "Feature",
  "properties": {
    "iso:country":"US",
    "sg:address":"12732 Jan St",
    "sg:city":"San Antonio",
    "sg:classifiers":[
        {
            "category":"Building & Trades",
            "subcategory":"Landscaping Services",
            "type":"Services"
        }
    ],
    "sg:phone":"+1 352 588 0603",
    "sg:postcode":"33576",
    "sg:province":"FL",
    "wof:name":"Sharkys Landscaping",
    "wof:placetype":"venue"
},
  "geometry": {"coordinates":[-82.310699,28.34337],"type":"Point"}
}