{
  "type": "Feature",
  "properties": {
    "iso:country":"US",
    "sg:address":"16980 NE 19 Ave",
    "sg:city":"Miami",
    "sg:classifiers":[
        {
            "category":"Personal",
            "type":"Services"
        }
    ],
    "sg:phone":"+1 800 583 0010",
    "sg:postcode":"33162",
    "sg:province":"FL",
    "sg:tags":[
        "mover"
    ],
    "sg:website":"intlmove.com/",
    "wof:name":"International Movers",
    "wof:placetype":"venue"
},
  "geometry": {"coordinates":[-80.162391,25.932147],"type":"Point"}
}