{
  "type": "Feature",
  "properties": {
    "iso:country":"US",
    "sg:address":"6210 N Federal Hwy",
    "sg:city":"Fort Lauderdale",
    "sg:classifiers":[
        {
            "category":"Banks & Credit Unions",
            "subcategory":"Investment Brokerage",
            "type":"Services"
        }
    ],
    "sg:phone":"+1 954 489 9222",
    "sg:postcode":"33308",
    "sg:province":"FL",
    "sg:tags":[
        "security"
    ],
    "wof:name":"Siebert Financial Corp",
    "wof:placetype":"venue"
},
  "geometry": {"coordinates":[-80.108062,26.206518],"type":"Point"}
}