{
  "type": "Feature",
  "properties": {
    "iso:country":"US",
    "sg:address":"11003 SW 58th Avenue Rd",
    "sg:city":"Ocala",
    "sg:classifiers":[
        {
            "category":"Building & Trades",
            "subcategory":"Construction",
            "type":"Services"
        }
    ],
    "sg:phone":"+1 352 854 0077",
    "sg:postcode":"34476",
    "sg:province":"FL",
    "sg:tags":[
        "home",
        "carpentry",
        "improvement",
        "contractor"
    ],
    "wof:name":"Georges Home Improvements Inc",
    "wof:placetype":"venue"
},
  "geometry": {"coordinates":[-82.21701899999999,29.062405],"type":"Point"}
}