{
  "type": "Feature",
  "properties": {
    "addr:full":"5112 Lake Catalina Dr Boca Raton FL 33496",
    "addr:housenumber":"5112",
    "addr:postcode":"33496",
    "addr:street":"Lake Catalina Dr",
    "iso:country":"US",
    "sg:address":"5112 Lake Catalina Dr",
    "sg:city":"Boca Raton",
    "sg:classifiers":[
        {
            "category":"Wholesale",
            "subcategory":"Chemicals & Plastics",
            "type":"Manufacturing & Wholesale Goods"
        }
    ],
    "sg:phone":"+1 561 989 9440",
    "sg:postcode":"33496",
    "sg:province":"FL",
    "wof:name":"Chasin Industries Inc",
    "wof:placetype":"venue"
},
  "geometry": {"coordinates":[-80.126255,26.413025],"type":"Point"}
}