{
  "type": "Feature",
  "properties": {
    "addr:full":"4757 S University Dr Davie FL 33328",
    "addr:housenumber":"4757",
    "addr:postcode":"33328",
    "addr:street":"S University Dr",
    "iso:country":"US",
    "sg:address":"4757 S University Dr",
    "sg:city":"Davie",
    "sg:classifiers":[
        {
            "category":"Health Services",
            "subcategory":"Doctor",
            "type":"Services"
        }
    ],
    "sg:phone":"+1 954 434 3331",
    "sg:postcode":"33328",
    "sg:province":"FL",
    "sg:tags":[
        "dentist"
    ],
    "wof:name":"Joann Di Bella DDS",
    "wof:placetype":"venue"
},
  "geometry": {"coordinates":[-80.25211,26.063248],"type":"Point"}
}