{
  "type": "Feature",
  "properties": {
    "addr:full":"1920 Park Meadows Dr Fort Myers FL 33907",
    "addr:housenumber":"1920",
    "addr:postcode":"33907",
    "addr:street":"Park Meadows Dr",
    "iso:country":"US",
    "sg:address":"1920 Park Meadows Dr",
    "sg:city":"Fort Myers",
    "sg:classifiers":[
        {
            "category":"Real Estate",
            "subcategory":"Real Estate Services",
            "type":"Services"
        }
    ],
    "sg:phone":"+1 239 275 1121",
    "sg:postcode":"33907",
    "sg:province":"FL",
    "sg:tags":[
        "management",
        "property"
    ],
    "wof:name":"Century 21 Gold Star Realty",
    "wof:placetype":"venue"
},
  "geometry": {"coordinates":[-81.87550400000001,26.566999],"type":"Point"}
}