{
  "type": "Feature",
  "properties": {
    "iso:country":"US",
    "sg:address":"168 Flamingo Rd",
    "sg:city":"Edgewater",
    "sg:classifiers":[
        {
            "category":"Shopping",
            "type":"Retail Goods"
        }
    ],
    "sg:phone":"+1 386 409 9041",
    "sg:postcode":"32141",
    "sg:province":"FL",
    "sg:tags":[
        "merchandise"
    ],
    "wof:name":"Reefer Rocks",
    "wof:placetype":"venue"
},
  "geometry": {"coordinates":[-80.87444000000001,28.934056],"type":"Point"}
}