{
  "type": "Feature",
  "properties": {
    "iso:country":"US",
    "sg:address":"8813 SW 132nd St",
    "sg:city":"Miami",
    "sg:classifiers":[
        {
            "category":"Manufacturing",
            "subcategory":"Tools & Machinery",
            "type":"Manufacturing & Wholesale Goods"
        },
        {
            "category":"Retail",
            "subcategory":"Repair Shop",
            "type":"Services"
        },
        {
            "category":"Wholesale",
            "subcategory":"Home Furnishings",
            "type":"Manufacturing & Wholesale Goods"
        }
    ],
    "sg:phone":"+1 786 293 1993",
    "sg:postcode":"33176",
    "sg:province":"FL",
    "sg:tags":[
        "lampshade",
        "lamp",
        "shade",
        "shades-wholesale",
        "manufacturer"
    ],
    "wof:name":"Lightorama Lamps And Shades Inc",
    "wof:placetype":"venue"
},
  "geometry": {"coordinates":[-80.33675100000001,25.647499],"type":"Point"}
}