{
  "type": "Feature",
  "properties": {
    "addr:full":"1715 E 9th Ave Tampa FL 33605",
    "addr:housenumber":"1715",
    "addr:postcode":"33605",
    "addr:street":"E 9Th Ave",
    "iso:country":"US",
    "sg:address":"1715 E 9th Ave",
    "sg:city":"Tampa",
    "sg:classifiers":[
        {
            "category":"Professional",
            "subcategory":"Advertising",
            "type":"Services"
        }
    ],
    "sg:phone":"+1 813 281 0088",
    "sg:postcode":"33605",
    "sg:province":"FL",
    "sg:tags":[
        "counselor"
    ],
    "sg:website":"www.robertscommunications.com",
    "wof:name":"Roberts Communications Mktg",
    "wof:placetype":"venue"
},
  "geometry": {"coordinates":[-82.439385,27.96161],"type":"Point"}
}