{
  "type": "Feature",
  "properties": {
    "iso:country":"US",
    "sg:address":"2555 US Hwy 27",
    "sg:city":"Sebring",
    "sg:classifiers":[
        {
            "category":"Professional",
            "subcategory":"Secretarial Services",
            "type":"Services"
        }
    ],
    "sg:phone":"+1 863 382 9533",
    "sg:postcode":"33870",
    "sg:province":"FL",
    "sg:tags":[
        "reporting"
    ],
    "wof:name":"Medquist Transcription Ltd",
    "wof:placetype":"venue"
},
  "geometry": {"coordinates":[-81.44502199999999,27.472147],"type":"Point"}
}