{
  "type": "Feature",
  "properties": {
    "addr:full":"10232 US Hwy 1 Port St Lucie FL 34952",
    "addr:housenumber":"10232",
    "addr:postcode":"34952",
    "addr:street":"Us Hwy 1",
    "iso:country":"US",
    "sg:address":"10232 US Hwy 1",
    "sg:city":"Port St Lucie",
    "sg:classifiers":[
        {
            "category":"Shopping",
            "subcategory":"Department Store",
            "type":"Retail Goods"
        }
    ],
    "sg:phone":"+1 772 335 9981",
    "sg:postcode":"34952",
    "sg:province":"FL",
    "sg:tags":[
        "shop"
    ],
    "wof:name":"Dollar Tree",
    "wof:placetype":"venue"
},
  "geometry": {"coordinates":[-80.290932,27.276068],"type":"Point"}
}