{
  "type": "Feature",
  "properties": {
    "iso:country":"US",
    "sg:address":"14018 N Boulevard",
    "sg:city":"Tampa",
    "sg:classifiers":[
        {
            "category":"Social Services",
            "subcategory":"Child Care",
            "type":"Services"
        },
        {
            "category":"Education",
            "subcategory":"Preschool",
            "type":"Public Place"
        },
        {
            "category":"Education",
            "subcategory":"School",
            "type":"Public Place"
        }
    ],
    "sg:phone":"+1 813 968 4321",
    "sg:postcode":"33613",
    "sg:province":"FL",
    "sg:tags":[
        "kindergarten",
        "nursery",
        "k-",
        "private",
        "day"
    ],
    "wof:name":"Montessori Institute Of Higher Learning",
    "wof:placetype":"venue"
},
  "geometry": {"coordinates":[-82.467536,28.075251],"type":"Point"}
}