{
  "type": "Feature",
  "properties": {
    "addr:full":"4162 W 12th Ave Hialeah FL 33012",
    "addr:housenumber":"4162",
    "addr:postcode":"33012",
    "addr:street":"W 12Th Ave",
    "iso:country":"US",
    "sg:address":"4162 W 12th Ave",
    "sg:city":"Hialeah",
    "sg:classifiers":[
        {
            "category":"Education",
            "subcategory":"Vocational School",
            "type":"Public Place"
        }
    ],
    "sg:phone":"+1 305 556 1424",
    "sg:postcode":"33012",
    "sg:province":"FL",
    "wof:name":"Praxis Institute",
    "wof:placetype":"venue"
},
  "geometry": {"coordinates":[-80.30670000000001,25.859041],"type":"Point"}
}