{
  "type": "Feature",
  "properties": {
    "addr:full":"13838 Amberleigh Rd Orlando FL 32837",
    "addr:postcode":"13838;32837",
    "addr:street":"Amberleigh Rd",
    "iso:country":"US",
    "sg:address":"13838 Amberleigh Rd",
    "sg:city":"Orlando",
    "sg:classifiers":[
        {
            "category":"Shopping",
            "subcategory":"Computers & Home Electronics",
            "type":"Retail Goods"
        }
    ],
    "sg:phone":"+1 407 825 9959",
    "sg:postcode":"32837",
    "sg:province":"FL",
    "sg:tags":[
        "software"
    ],
    "wof:name":"Zillions Development Corp",
    "wof:placetype":"venue"
},
  "geometry": {"coordinates":[-81.40073,28.36085],"type":"Point"}
}