{
  "type": "Feature",
  "properties": {
    "addr:full":"3310 NW 91 St Gainesville FL 32606",
    "addr:housenumber":"3310",
    "addr:postcode":"32606",
    "addr:street":"Nw 91 St",
    "iso:country":"US",
    "sg:address":"3310 NW 91 St",
    "sg:city":"Gainesville",
    "sg:classifiers":[
        {
            "category":"Real Estate",
            "subcategory":"Real Estate Operator",
            "type":"Services"
        }
    ],
    "sg:phone":"+1 352 378 1190",
    "sg:postcode":"32606",
    "sg:province":"FL",
    "sg:tags":[
        "building",
        "apartment"
    ],
    "wof:name":"Santa Fe Trace Apartments",
    "wof:placetype":"venue"
},
  "geometry": {"coordinates":[-82.439024,29.683684],"type":"Point"}
}