{
  "type": "Feature",
  "properties": {
    "addr:full":"6302 Benjamin Rd Tampa FL 33634",
    "addr:housenumber":"6302",
    "addr:postcode":"33634",
    "addr:street":"Benjamin Rd",
    "iso:country":"US",
    "sg:address":"6302 Benjamin Rd",
    "sg:city":"Tampa",
    "sg:classifiers":[
        {
            "category":"Manufacturing",
            "subcategory":"Printing",
            "type":"Manufacturing & Wholesale Goods"
        }
    ],
    "sg:phone":"+1 813 960 0225",
    "sg:postcode":"33634",
    "sg:province":"FL",
    "sg:tags":[
        "company",
        "printer"
    ],
    "sg:website":"www.tampa508.alphagraphics.com",
    "wof:name":"Alpha Graphics",
    "wof:placetype":"venue"
},
  "geometry": {"coordinates":[-82.54201999999999,28.006367],"type":"Point"}
}