{
  "type": "Feature",
  "properties": {
    "iso:country":"US",
    "sg:address":"8202 NW Miami Ct",
    "sg:city":"Miami",
    "sg:classifiers":[
        {
            "category":"Building & Trades",
            "subcategory":"Plumbing",
            "type":"Services"
        }
    ],
    "sg:phone":"+1 305 751 8875",
    "sg:postcode":"33150",
    "sg:province":"FL",
    "sg:tags":[
        "contractor"
    ],
    "wof:name":"Backflow & Cross Connection Sp",
    "wof:placetype":"venue"
},
  "geometry": {"coordinates":[-80.198066,25.849794],"type":"Point"}
}