{
  "type": "Feature",
  "properties": {
    "iso:country":"US",
    "sg:address":"12520 Rawhide Dr",
    "sg:city":"Tampa",
    "sg:classifiers":[
        {
            "category":"Building & Trades",
            "subcategory":"Construction",
            "type":"Services"
        }
    ],
    "sg:phone":"+1 813 855 7745",
    "sg:postcode":"33626",
    "sg:province":"FL",
    "sg:tags":[
        "painting",
        "painter",
        "contractor"
    ],
    "sg:website":"http://www.mpspainting.com",
    "wof:name":"M P S Painting Inc",
    "wof:placetype":"venue"
},
  "geometry": {"coordinates":[-82.63717699999999,28.04867],"type":"Point"}
}