{
  "type": "Feature",
  "properties": {
    "iso:country":"US",
    "sg:address":"2406 E Washington St",
    "sg:city":"Orlando",
    "sg:classifiers":[
        {
            "category":"Retail",
            "subcategory":"Animal Services",
            "type":"Services"
        }
    ],
    "sg:phone":"+1 407 896 8969",
    "sg:postcode":"32803",
    "sg:province":"FL",
    "wof:name":"Supreme Dog Grooming Services",
    "wof:placetype":"venue"
},
  "geometry": {"coordinates":[-81.34987700000001,28.544061],"type":"Point"}
}