{
  "type": "Feature",
  "properties": {
    "iso:country":"US",
    "sg:address":"15873 NW 16th Ct",
    "sg:city":"Pembroke Pines",
    "sg:classifiers":[
        {
            "category":"Building & Trades",
            "subcategory":"Construction",
            "type":"Services"
        }
    ],
    "sg:phone":"+1 954 614 0590",
    "sg:postcode":"33028",
    "sg:province":"FL",
    "sg:tags":[
        "layer",
        "carpet"
    ],
    "wof:name":"Aymer Hernandez Carpeting",
    "wof:placetype":"venue"
},
  "geometry": {"coordinates":[-80.360029,26.026594],"type":"Point"}
}