{
  "type": "Feature",
  "properties": {
    "addr:full":"3161 NE 5th Ave Oakland Park FL 33334",
    "addr:housenumber":"3161",
    "addr:postcode":"33334",
    "addr:street":"Ne 5Th Ave",
    "iso:country":"US",
    "sg:address":"3161 NE 5th Ave",
    "sg:city":"Oakland Park",
    "sg:classifiers":[
        {
            "category":"Wholesale",
            "subcategory":"Construction Materials",
            "type":"Manufacturing & Wholesale Goods"
        }
    ],
    "sg:phone":"+1 954 564 4188",
    "sg:postcode":"33334",
    "sg:province":"FL",
    "sg:tags":[
        "fence"
    ],
    "wof:name":"A8K Metal Works",
    "wof:placetype":"venue"
},
  "geometry": {"coordinates":[-80.140474,26.167222],"type":"Point"}
}