{
  "type": "Feature",
  "properties": {
    "iso:country":"US",
    "sg:address":"404 US Hwy 92",
    "sg:city":"Haines City",
    "sg:classifiers":[
        {
            "category":"Food & Beverages",
            "subcategory":"Groceries & Convenience Stores",
            "type":"Retail Goods"
        }
    ],
    "sg:phone":"+1 863 421 9260",
    "sg:postcode":"33844",
    "sg:province":"FL",
    "wof:name":"Davenport Food Inc",
    "wof:placetype":"venue"
},
  "geometry": {"coordinates":[-81.723153,28.095587],"type":"Point"}
}