{
  "type": "Feature",
  "properties": {
    "addr:full":"1201 W Pine St Orlando FL 32805",
    "addr:housenumber":"1201",
    "addr:postcode":"32805",
    "addr:street":"W Pine St",
    "iso:country":"US",
    "sg:address":"1201 W Pine St",
    "sg:city":"Orlando",
    "sg:classifiers":[
        {
            "category":"Building & Trades",
            "subcategory":"Construction",
            "type":"Services"
        }
    ],
    "sg:phone":"+1 407 650 3555",
    "sg:postcode":"32805",
    "sg:province":"FL",
    "sg:tags":[
        "fireproofing"
    ],
    "sg:website":"http://www.allstatesfireproofing.net",
    "wof:name":"Allstates Fireproofing Inc",
    "wof:placetype":"venue"
},
  "geometry": {"coordinates":[-81.39591299999999,28.541059],"type":"Point"}
}