{
  "type": "Feature",
  "properties": {
    "iso:country":"US",
    "sg:address":"4043 13th St",
    "sg:city":"Saint Cloud",
    "sg:classifiers":[
        {
            "category":"Restaurant",
            "type":"Food & Drink"
        }
    ],
    "sg:menulink":"http://www.allmenus.com/fl/st-cloud/57443-chen-house/menu/",
    "sg:phone":"+1 407 891 2895",
    "sg:postcode":"34769",
    "sg:province":"FL",
    "sg:tags":[
        "asian",
        "chinese"
    ],
    "wof:name":"Chen House",
    "wof:placetype":"venue"
},
  "geometry": {"coordinates":[-81.31248100000001,28.250534],"type":"Point"}
}