{
  "type": "Feature",
  "properties": {
    "addr:full":"1314 E Las Olas Blvd Fort Lauderdale FL 33301",
    "addr:housenumber":"1314",
    "addr:postcode":"33301",
    "addr:street":"E Las Olas Blvd",
    "iso:country":"US",
    "sg:address":"1314 E Las Olas Blvd",
    "sg:city":"Fort Lauderdale",
    "sg:classifiers":[
        {
            "category":"Recreation",
            "type":"Entertainment"
        }
    ],
    "sg:phone":"+1 954 524 0084",
    "sg:postcode":"33301",
    "sg:province":"FL",
    "sg:tags":[
        "guide"
    ],
    "wof:name":"White Phantom",
    "wof:placetype":"venue"
},
  "geometry": {"coordinates":[-80.128919,26.11932],"type":"Point"}
}