{
  "type": "Feature",
  "properties": {
    "iso:country":"US",
    "sg:address":"3013 Homasassa Rd",
    "sg:city":"Sarasota",
    "sg:classifiers":[
        {
            "category":"Recreation",
            "type":"Entertainment"
        }
    ],
    "sg:phone":"+1 941 925 9642",
    "sg:postcode":"34239",
    "sg:province":"FL",
    "wof:name":"Shivans Orient Express",
    "wof:placetype":"venue"
},
  "geometry": {"coordinates":[-82.50998199999999,27.301662],"type":"Point"}
}