{
  "type": "Feature",
  "properties": {
    "addr:full":"17189 Pines Blvd Hollywood FL 33027",
    "addr:housenumber":"17189",
    "addr:postcode":"33027",
    "addr:street":"Pines Blvd",
    "iso:country":"US",
    "sg:address":"17189 Pines Blvd",
    "sg:city":"Hollywood",
    "sg:classifiers":[
        {
            "category":"Retail",
            "subcategory":"Veterinary Services",
            "type":"Services"
        }
    ],
    "sg:phone":"+1 954 431 7979",
    "sg:postcode":"33027",
    "sg:province":"FL",
    "sg:tags":[
        "veterinarian"
    ],
    "wof:name":"Dr Ferber's Animal Hospital",
    "wof:placetype":"venue"
},
  "geometry": {"coordinates":[-80.375541,26.007806],"type":"Point"}
}