{
  "type": "Feature",
  "properties": {
    "iso:country":"US",
    "sg:address":"8644 Brierwood Rd",
    "sg:city":"Jacksonville",
    "sg:classifiers":[
        {
            "category":"Manufacturing",
            "subcategory":"Lumber",
            "type":"Manufacturing & Wholesale Goods"
        }
    ],
    "sg:phone":"+1 904 737 9363",
    "sg:postcode":"32217",
    "sg:province":"FL",
    "sg:tags":[
        "real",
        "lessor",
        "tract",
        "operation",
        "property",
        "timber"
    ],
    "wof:name":"Thomas Thomasville Enterprises",
    "wof:placetype":"venue"
},
  "geometry": {"coordinates":[-81.59753600000001,30.224045],"type":"Point"}
}