{
  "type": "Feature",
  "properties": {
    "addr:full":"626 SE Clifton Ln Port Saint Lucie FL 34983",
    "addr:housenumber":"626",
    "addr:postcode":"34983",
    "addr:street":"Se Clifton Ln",
    "iso:country":"US",
    "sg:address":"626 SE Clifton Ln",
    "sg:city":"Port Saint Lucie",
    "sg:classifiers":[
        {
            "category":"Freight",
            "type":"Transportation"
        }
    ],
    "sg:phone":"+1 772 344 0809",
    "sg:postcode":"34983",
    "sg:province":"FL",
    "wof:name":"A Class Moving",
    "wof:placetype":"venue"
},
  "geometry": {"coordinates":[-80.33817999999999,27.31316],"type":"Point"}
}