{
  "type": "Feature",
  "properties": {
    "addr:full":"995 46th Ave N St Petersburg FL 33703",
    "addr:housenumber":"995",
    "addr:postcode":"33703",
    "addr:street":"46Th Ave N",
    "iso:country":"US",
    "sg:address":"995 46th Ave N",
    "sg:city":"St Petersburg",
    "sg:classifiers":[
        {
            "category":"Professional",
            "type":"Services"
        }
    ],
    "sg:phone":"+1 727 526 7553",
    "sg:postcode":"33703",
    "sg:province":"FL",
    "sg:tags":[
        "writer"
    ],
    "wof:name":"Moorhead & Moorhead",
    "wof:placetype":"venue"
},
  "geometry": {"coordinates":[-82.64707,27.814011],"type":"Point"}
}