{
  "type": "Feature",
  "properties": {
    "iso:country":"US",
    "sg:address":"1722 del Prado Blvd S",
    "sg:city":"Cape Coral",
    "sg:classifiers":[
        {
            "category":"Professional",
            "type":"Services"
        }
    ],
    "sg:phone":"+1 239 574 2340",
    "sg:postcode":"33990",
    "sg:province":"FL",
    "sg:tags":[
        "establishment"
    ],
    "wof:name":"Del Prado Office Corp",
    "wof:placetype":"venue"
},
  "geometry": {"coordinates":[-81.940907,26.617661],"type":"Point"}
}