{
  "type": "Feature",
  "properties": {
    "iso:country":"US",
    "sg:address":"411 E Sheridan St",
    "sg:city":"Dania",
    "sg:classifiers":[
        {
            "category":"Retail",
            "subcategory":"Laundry & Dry Cleaning",
            "type":"Services"
        }
    ],
    "sg:phone":"+1 954 921 7700",
    "sg:postcode":"33004",
    "sg:province":"FL",
    "wof:name":"Premier Cleaners",
    "wof:placetype":"venue"
},
  "geometry": {"coordinates":[-80.137176,26.033843],"type":"Point"}
}