{
  "type": "Feature",
  "properties": {
    "addr:full":"10075 Yamato Rd Boca Raton FL 33498",
    "addr:postcode":"10075;33498",
    "addr:street":"Yamato Rd",
    "iso:country":"US",
    "sg:address":"10075 Yamato Rd",
    "sg:city":"Boca Raton",
    "sg:classifiers":[
        {
            "category":"Retail",
            "subcategory":"Self-service Laundry",
            "type":"Services"
        },
        {
            "category":"Retail",
            "subcategory":"Laundry & Dry Cleaning",
            "type":"Services"
        }
    ],
    "sg:phone":"+1 561 451 1244",
    "sg:postcode":"33498",
    "sg:province":"FL",
    "sg:tags":[
        "cleaners",
        "coin"
    ],
    "wof:name":"Olympic Dry Cleaners",
    "wof:placetype":"venue"
},
  "geometry": {"coordinates":[-80.211163,26.39376],"type":"Point"}
}