{
  "type": "Feature",
  "properties": {
    "addr:full":"848 Airport Rd Destin FL 32541",
    "addr:housenumber":"848",
    "addr:postcode":"32541",
    "addr:street":"Airport Rd",
    "iso:country":"US",
    "sg:address":"848 Airport Rd",
    "sg:city":"Destin",
    "sg:classifiers":[
        {
            "category":"Government",
            "subcategory":"Fire Station",
            "type":"Public Place"
        }
    ],
    "sg:phone":"+1 850 837 8413",
    "sg:postcode":"32541",
    "sg:province":"FL",
    "sg:tags":[
        "department"
    ],
    "wof:name":"Destin Fire Dept",
    "wof:placetype":"venue"
},
  "geometry": {"coordinates":[-86.47875999999999,30.396535],"type":"Point"}
}