{
  "type": "Feature",
  "properties": {
    "iso:country":"US",
    "sg:address":"14313 Joan Dr",
    "sg:city":"Palm Beach Gardens",
    "sg:classifiers":[
        {
            "category":"Building & Trades",
            "subcategory":"Construction",
            "type":"Services"
        }
    ],
    "sg:phone":"+1 561 627 7368",
    "sg:postcode":"33410",
    "sg:province":"FL",
    "sg:tags":[
        "house"
    ],
    "wof:name":"James T Chalk",
    "wof:placetype":"venue"
},
  "geometry": {"coordinates":[-80.076517,26.886672],"type":"Point"}
}