{
  "type": "Feature",
  "properties": {
    "addr:full":"9948 Dean Oaks Ct Orlando FL 32825",
    "addr:housenumber":"9948",
    "addr:postcode":"32825",
    "addr:street":"Dean Oaks Ct",
    "iso:country":"US",
    "sg:address":"9948 Dean Oaks Ct",
    "sg:city":"Orlando",
    "sg:classifiers":[
        {
            "category":"Retail",
            "subcategory":"Auto Repair",
            "type":"Services"
        }
    ],
    "sg:phone":"+1 407 273 6814",
    "sg:postcode":"32825",
    "sg:province":"FL",
    "sg:tags":[
        "general"
    ],
    "wof:name":"Auto Bee Concepts Inc",
    "wof:placetype":"venue"
},
  "geometry": {"coordinates":[-81.24521,28.550787],"type":"Point"}
}