{
  "type": "Feature",
  "properties": {
    "addr:full":"6929 W University Ave Gainesville FL 32607",
    "addr:housenumber":"6929",
    "addr:postcode":"32607",
    "addr:street":"W University Ave",
    "iso:country":"US",
    "sg:address":"6929 W University Ave",
    "sg:city":"Gainesville",
    "sg:classifiers":[
        {
            "category":"Real Estate",
            "subcategory":"Real Estate Operator",
            "type":"Services"
        }
    ],
    "sg:phone":"+1 352 332 4011",
    "sg:postcode":"32607",
    "sg:province":"FL",
    "sg:tags":[
        "building",
        "apartment"
    ],
    "wof:name":"Bentwood Apartments Ltd",
    "wof:placetype":"venue"
},
  "geometry": {"coordinates":[-82.41480300000001,29.653161],"type":"Point"}
}