{
  "type": "Feature",
  "properties": {
    "addr:full":"12415 Gulf Blvd Saint Petersburg FL 33706",
    "addr:housenumber":"12415",
    "addr:postcode":"33706",
    "addr:street":"Gulf Blvd",
    "iso:country":"US",
    "sg:address":"12415 Gulf Blvd",
    "sg:city":"Saint Petersburg",
    "sg:classifiers":[
        {
            "category":"Organizations",
            "subcategory":"Community Association",
            "type":"Services"
        }
    ],
    "sg:phone":"+1 727 363 4558",
    "sg:postcode":"33706",
    "sg:province":"FL",
    "sg:tags":[
        "development"
    ],
    "wof:name":"Treasure Is Citz Respsbl Progr",
    "wof:placetype":"venue"
},
  "geometry": {"coordinates":[-82.780387,27.779494],"type":"Point"}
}