{
  "type": "Feature",
  "properties": {
    "addr:full":"6011 Benjamin Rd Ste 101B Tampa FL 33634",
    "addr:housenumber":"6011",
    "addr:postcode":"33634",
    "addr:street":"Benjamin Rd Ste 101B",
    "iso:country":"US",
    "sg:address":"6011 Benjamin Rd Ste 101B",
    "sg:city":"Tampa",
    "sg:classifiers":[
        {
            "category":"Health Services",
            "subcategory":"Doctor",
            "type":"Services"
        },
        {
            "category":"Health Services",
            "subcategory":"Nursing And Care Facility",
            "type":"Services"
        }
    ],
    "sg:phone":"+1 813 249 1500",
    "sg:postcode":"33634",
    "sg:province":"FL",
    "sg:tags":[
        "physician",
        "surgeon",
        "management",
        "pain"
    ],
    "sg:website":"http://www.innovativepumpsolutions.com",
    "wof:name":"Innovative Pump Solutions",
    "wof:placetype":"venue"
},
  "geometry": {"coordinates":[-82.542023,28.002859],"type":"Point"}
}