{
  "type": "Feature",
  "properties": {
    "addr:full":"6900 NW 77th St Tamarac FL 33321",
    "addr:housenumber":"6900",
    "addr:postcode":"33321",
    "addr:street":"Nw 77Th St",
    "iso:country":"US",
    "sg:address":"6900 NW 77th St",
    "sg:city":"Tamarac",
    "sg:classifiers":[
        {
            "category":"Communications",
            "type":"Services"
        }
    ],
    "sg:phone":"+1 954 726 4927",
    "sg:postcode":"33321",
    "sg:province":"FL",
    "wof:name":"Vanguard Village Comm 2",
    "wof:placetype":"venue"
},
  "geometry": {"coordinates":[-80.245047,26.217098],"type":"Point"}
}