{
  "type": "Feature",
  "properties": {
    "addr:full":"2000 NE 49th St Pompano Beach FL 33064",
    "addr:housenumber":"2000",
    "addr:postcode":"33064",
    "addr:street":"Ne 49Th St",
    "iso:country":"US",
    "sg:address":"2000 NE 49th St",
    "sg:city":"Pompano Beach",
    "sg:classifiers":[
        {
            "category":"Shopping",
            "subcategory":"Jewelry",
            "type":"Retail Goods"
        }
    ],
    "sg:phone":"+1 954 425 0050",
    "sg:postcode":"33064",
    "sg:province":"FL",
    "wof:name":"Don Pawn Shop",
    "wof:placetype":"venue"
},
  "geometry": {"coordinates":[-80.09518199999999,26.291658],"type":"Point"}
}