{
  "type": "Feature",
  "properties": {
    "addr:full":"201 Old Dixie Hwy Riviera Beach FL 33404",
    "addr:housenumber":"201",
    "addr:postcode":"33404",
    "addr:street":"Old Dixie Hwy",
    "iso:country":"US",
    "sg:address":"201 Old Dixie Hwy",
    "sg:city":"Riviera Beach",
    "sg:classifiers":[
        {
            "category":"Food & Beverages",
            "subcategory":"Groceries & Convenience Stores",
            "type":"Retail Goods"
        }
    ],
    "sg:phone":"+1 561 844 0021",
    "sg:postcode":"33404",
    "sg:province":"FL",
    "sg:tags":[
        "grocer"
    ],
    "wof:name":"Old Dixie Market",
    "wof:placetype":"venue"
},
  "geometry": {"coordinates":[-80.060125,26.765608],"type":"Point"}
}