{
  "type": "Feature",
  "properties": {
    "iso:country":"US",
    "sg:address":"4698 Dusk Ct",
    "sg:city":"Jacksonville",
    "sg:classifiers":[
        {
            "category":"Building & Trades",
            "subcategory":"Construction",
            "type":"Services"
        }
    ],
    "sg:phone":"+1 904 730 0882",
    "sg:postcode":"32207",
    "sg:province":"FL",
    "sg:tags":[
        "contractor",
        "fence-sales"
    ],
    "sg:website":"http://www.silvermanfence.com/",
    "wof:name":"Silverman Fence",
    "wof:placetype":"venue"
},
  "geometry": {"coordinates":[-81.62645500000001,30.272483],"type":"Point"}
}