{
  "type": "Feature",
  "properties": {
    "addr:full":"201 Hilda St Kissimmee FL 34741",
    "addr:housenumber":"201",
    "addr:postcode":"34741",
    "addr:street":"Hilda St",
    "iso:country":"US",
    "sg:address":"201 Hilda St",
    "sg:city":"Kissimmee",
    "sg:classifiers":[
        {
            "category":"Health Services",
            "subcategory":"Doctor",
            "type":"Services"
        }
    ],
    "sg:phone":"+1 407 870 0808",
    "sg:postcode":"34741",
    "sg:province":"FL",
    "sg:tags":[
        "medical"
    ],
    "wof:name":"Keller Alan L MD Facs",
    "wof:placetype":"venue"
},
  "geometry": {"coordinates":[-81.40894,28.317442],"type":"Point"}
}