{
  "type": "Feature",
  "properties": {
    "iso:country":"US",
    "sg:address":"5638 Antietam Dr",
    "sg:city":"Sarasota",
    "sg:classifiers":[
        {
            "category":"Real Estate",
            "subcategory":"Real Estate Agent",
            "type":"Services"
        }
    ],
    "sg:phone":"+1 941 924 4165",
    "sg:postcode":"34231",
    "sg:province":"FL",
    "wof:name":"Fitzgerald Family Realty Inc",
    "wof:placetype":"venue"
},
  "geometry": {"coordinates":[-82.516662,27.270978],"type":"Point"}
}