{
  "type": "Feature",
  "properties": {
    "iso:country":"US",
    "sg:address":"14250 SW 136th St",
    "sg:city":"Miami",
    "sg:classifiers":[
        {
            "category":"Wholesale",
            "subcategory":"Electrical",
            "type":"Manufacturing & Wholesale Goods"
        },
        {
            "category":"Manufacturing",
            "subcategory":"Tools & Machinery",
            "type":"Manufacturing & Wholesale Goods"
        }
    ],
    "sg:phone":"+1 305 251 9771",
    "sg:postcode":"33186",
    "sg:province":"FL",
    "sg:tags":[
        "distributor",
        "export",
        "diesel",
        "generator"
    ],
    "sg:website":"www.americanpower.com",
    "wof:name":"American Power Systems Corp",
    "wof:placetype":"venue"
},
  "geometry": {"coordinates":[-80.42583500000001,25.640781],"type":"Point"}
}