{
  "type": "Feature",
  "properties": {
    "iso:country":"US",
    "sg:address":"425 Quay Assisi",
    "sg:city":"New Smyrna Beach",
    "sg:classifiers":[
        {
            "category":"Banks & Credit Unions",
            "subcategory":"Financial Services",
            "type":"Services"
        }
    ],
    "sg:phone":"+1 386 423 4287",
    "sg:postcode":"32169",
    "sg:province":"FL",
    "sg:tags":[
        "company",
        "holding"
    ],
    "wof:name":"Wilkins Partnership Limited",
    "wof:placetype":"venue"
},
  "geometry": {"coordinates":[-80.91230400000001,29.042261],"type":"Point"}
}