{
  "type": "Feature",
  "properties": {
    "iso:country":"US",
    "sg:address":"2374 SE Patio Cir",
    "sg:city":"Port Saint Lucie",
    "sg:classifiers":[
        {
            "category":"Building & Trades",
            "subcategory":"Electrical",
            "type":"Services"
        }
    ],
    "sg:phone":"+1 772 335 3546",
    "sg:postcode":"34952",
    "sg:province":"FL",
    "sg:tags":[
        "electrical",
        "contractor"
    ],
    "wof:name":"Daniel Foley Electric",
    "wof:placetype":"venue"
},
  "geometry": {"coordinates":[-80.280784,27.287729],"type":"Point"}
}