{
  "type": "Feature",
  "properties": {
    "iso:country":"US",
    "sg:address":"5450 Griffin Rd",
    "sg:city":"Davie",
    "sg:classifiers":[
        {
            "category":"Professional",
            "subcategory":"Engineering",
            "type":"Services"
        }
    ],
    "sg:phone":"+1 954 584 6115",
    "sg:postcode":"33314",
    "sg:province":"FL",
    "sg:tags":[
        "civil",
        "engineer"
    ],
    "wof:name":"Soilprobe Engineering & Test",
    "wof:placetype":"venue"
},
  "geometry": {"coordinates":[-80.220293,26.065329],"type":"Point"}
}