{
  "type": "Feature",
  "properties": {
    "addr:full":"1101 Lost Lake Rd Chipley FL 32428",
    "addr:housenumber":"1101",
    "addr:postcode":"32428",
    "addr:street":"Lost Lake Rd",
    "iso:country":"US",
    "sg:address":"1101 Lost Lake Rd",
    "sg:city":"Chipley",
    "sg:classifiers":[
        {
            "category":"Travel",
            "subcategory":"Hotels & Motels",
            "type":"Entertainment"
        }
    ],
    "sg:phone":"+1 850 415 6484",
    "sg:postcode":"32428",
    "sg:province":"FL",
    "wof:name":"Days Inn",
    "wof:placetype":"venue"
},
  "geometry": {"coordinates":[-85.55001,30.750393],"type":"Point"}
}