{
  "type": "Feature",
  "properties": {
    "iso:country":"US",
    "sg:address":"4364 34th St",
    "sg:city":"Orlando",
    "sg:classifiers":[
        {
            "category":"Manufacturing",
            "subcategory":"Tools & Machinery",
            "type":"Manufacturing & Wholesale Goods"
        }
    ],
    "sg:phone":"+1 407 843 1300",
    "sg:postcode":"32811",
    "sg:province":"FL",
    "sg:tags":[
        "packaging",
        "mfg"
    ],
    "wof:name":"Stone Container Corporation",
    "wof:placetype":"venue"
},
  "geometry": {"coordinates":[-81.430772,28.505775],"type":"Point"}
}