{
  "type": "Feature",
  "properties": {
    "addr:full":"1030 Alderside St Jacksonville FL 32208",
    "addr:postcode":"1030;32208",
    "addr:street":"Alderside St",
    "iso:country":"US",
    "sg:address":"1030 Alderside St",
    "sg:city":"Jacksonville",
    "sg:classifiers":[
        {
            "category":"Personal",
            "subcategory":"Beauty Salon",
            "type":"Services"
        }
    ],
    "sg:phone":"+1 904 765 9952",
    "sg:postcode":"32208",
    "sg:province":"FL",
    "wof:name":"Aleah's Hair Design",
    "wof:placetype":"venue"
},
  "geometry": {"coordinates":[-81.672068,30.377886],"type":"Point"}
}