{
  "type": "Feature",
  "properties": {
    "iso:country":"US",
    "sg:address":"3451 Executive Way",
    "sg:city":"Miramar",
    "sg:classifiers":[
        {
            "category":"Wholesale",
            "subcategory":"Medical Equipment & Supplies",
            "type":"Manufacturing & Wholesale Goods"
        }
    ],
    "sg:phone":"+1 954 431 1118",
    "sg:postcode":"33025",
    "sg:province":"FL",
    "sg:tags":[
        "physician",
        "surgeon"
    ],
    "wof:name":"DME Discount",
    "wof:placetype":"venue"
},
  "geometry": {"coordinates":[-80.28613799999999,25.977764],"type":"Point"}
}