{
  "type": "Feature",
  "properties": {
    "addr:full":"4367 SW 10th Pl Deerfield Beach FL 33442",
    "addr:housenumber":"4367",
    "addr:postcode":"33442",
    "addr:street":"Sw 10Th Pl",
    "iso:country":"US",
    "sg:address":"4367 SW 10th Pl",
    "sg:city":"Deerfield Beach",
    "sg:classifiers":[
        {
            "category":"Personal",
            "type":"Services"
        }
    ],
    "sg:phone":"+1 954 596 0040",
    "sg:postcode":"33442",
    "sg:province":"FL",
    "sg:tags":[
        "credit",
        "debt",
        "counseling"
    ],
    "wof:name":"Setna Solutions Inc",
    "wof:placetype":"venue"
},
  "geometry": {"coordinates":[-80.162797,26.302909],"type":"Point"}
}