{
  "type": "Feature",
  "properties": {
    "addr:full":"5462 Grand Park Pl Boca Raton FL 33486",
    "addr:housenumber":"5462",
    "addr:postcode":"33486",
    "addr:street":"Grand Park Pl",
    "iso:country":"US",
    "sg:address":"5462 Grand Park Pl",
    "sg:city":"Boca Raton",
    "sg:classifiers":[
        {
            "category":"Real Estate",
            "subcategory":"Real Estate Operator",
            "type":"Services"
        }
    ],
    "sg:phone":"+1 561 347 8495",
    "sg:postcode":"33486",
    "sg:province":"FL",
    "sg:tags":[
        "building",
        "nonresidential"
    ],
    "wof:name":"Mlk Properties Inc",
    "wof:placetype":"venue"
},
  "geometry": {"coordinates":[-80.126722,26.35923],"type":"Point"}
}