{
  "type": "Feature",
  "properties": {
    "iso:country":"US",
    "sg:address":"2530 Blanding Blvd",
    "sg:city":"Middleburg",
    "sg:classifiers":[
        {
            "category":"Restaurant",
            "type":"Food & Drink"
        }
    ],
    "sg:menulink":"http://www.allmenus.com/fl/middleburg-clay-hill/169481-wendys/menu/",
    "sg:phone":"+1 904 291 1157",
    "sg:postcode":"32068",
    "sg:province":"FL",
    "sg:tags":[
        "burger",
        "american",
        "soup"
    ],
    "wof:name":"Wendy's",
    "wof:placetype":"venue"
},
  "geometry": {"coordinates":[-81.874318,30.062569],"type":"Point"}
}