{
  "type": "Feature",
  "properties": {
    "addr:full":"207 N Lakeshore Blvd Howey In The Hills FL 34737",
    "addr:housenumber":"207",
    "addr:postcode":"34737",
    "addr:street":"N Lakeshore Blvd",
    "iso:country":"US",
    "sg:address":"207 N Lakeshore Blvd",
    "sg:city":"Howey In The Hills",
    "sg:classifiers":[
        {
            "category":"Manufacturing",
            "subcategory":"Building Materials",
            "type":"Manufacturing & Wholesale Goods"
        }
    ],
    "sg:phone":"+1 352 324 3623",
    "sg:postcode":"34737",
    "sg:province":"FL",
    "sg:tags":[
        "mfg",
        "wood",
        "kitchen",
        "cabinet"
    ],
    "wof:name":"Ron Hartman Custom Cabinets",
    "wof:placetype":"venue"
},
  "geometry": {"coordinates":[-81.77045200000001,28.716248],"type":"Point"}
}