{
  "type": "Feature",
  "properties": {
    "iso:country":"US",
    "sg:address":"2772 Elkcam Blvd",
    "sg:city":"Deltona",
    "sg:classifiers":[
        {
            "category":"Restaurant",
            "type":"Food & Drink"
        }
    ],
    "sg:phone":"+1 904 532 1694",
    "sg:postcode":"32738",
    "sg:province":"FL",
    "sg:tags":[
        "eating"
    ],
    "wof:name":"Don Taco Inc",
    "wof:placetype":"venue"
},
  "geometry": {"coordinates":[-81.190442,28.926459],"type":"Point"}
}