{
  "type": "Feature",
  "properties": {
    "addr:full":"1319 W Fletcher Ave Tampa FL 33612",
    "addr:housenumber":"1319",
    "addr:postcode":"33612",
    "addr:street":"W Fletcher Ave",
    "iso:country":"US",
    "sg:address":"1319 W Fletcher Ave",
    "sg:city":"Tampa",
    "sg:classifiers":[
        {
            "category":"Professional",
            "subcategory":"Lawyer & Legal Services",
            "type":"Services"
        }
    ],
    "sg:phone":"+1 813 969 0440",
    "sg:postcode":"33612",
    "sg:province":"FL",
    "sg:tags":[
        "attorney"
    ],
    "wof:name":"Joe Episcopo",
    "wof:placetype":"venue"
},
  "geometry": {"coordinates":[-82.47401600000001,28.069483],"type":"Point"}
}