{
  "type": "Feature",
  "properties": {
    "iso:country":"US",
    "sg:address":"169 E Flagler St",
    "sg:city":"Miami",
    "sg:classifiers":[
        {
            "category":"Shopping",
            "subcategory":"Jewelry",
            "type":"Retail Goods"
        }
    ],
    "sg:phone":"+1 305 377 1516",
    "sg:postcode":"33131",
    "sg:province":"FL",
    "sg:tags":[
        "diamond"
    ],
    "wof:name":"Adr",
    "wof:placetype":"venue"
},
  "geometry": {"coordinates":[-80.190663,25.774207],"type":"Point"}
}