{
  "type": "Feature",
  "properties": {
    "iso:country":"US",
    "sg:address":"813 N Nob Hill Rd",
    "sg:city":"Plantation",
    "sg:classifiers":[
        {
            "category":"Real Estate",
            "subcategory":"Real Estate Agent",
            "type":"Services"
        }
    ],
    "sg:phone":"+1 954 693 9300",
    "sg:postcode":"33324",
    "sg:province":"FL",
    "sg:website":"www.wizrealty.com",
    "wof:name":"Wiz Realty",
    "wof:placetype":"venue"
},
  "geometry": {"coordinates":[-80.28760200000001,26.134744],"type":"Point"}
}