{
  "type": "Feature",
  "properties": {
    "iso:country":"US",
    "sg:address":"1720 W US Hwy 90",
    "sg:city":"Lake City",
    "sg:classifiers":[
        {
            "category":"Banks & Credit Unions",
            "subcategory":"Bank",
            "type":"Services"
        }
    ],
    "sg:phone":"+1 386 752 3322",
    "sg:postcode":"32055",
    "sg:province":"FL",
    "sg:tags":[
        "state",
        "commercial"
    ],
    "sg:website":"www.ccbanc.com",
    "wof:name":"Columbia County Bank",
    "wof:placetype":"venue"
},
  "geometry": {"coordinates":[-82.650811,30.187833],"type":"Point"}
}