{
  "type": "Feature",
  "properties": {
    "iso:country":"US",
    "sg:address":"80 Biscayne Blvd",
    "sg:city":"Miami",
    "sg:classifiers":[
        {
            "category":"Banks & Credit Unions",
            "subcategory":"Investment Brokerage",
            "type":"Services"
        }
    ],
    "sg:phone":"+1 305 377 1940",
    "sg:postcode":"33132",
    "sg:province":"FL",
    "sg:tags":[
        "exchange"
    ],
    "wof:name":"Consolidated Group Intl",
    "wof:placetype":"venue"
},
  "geometry": {"coordinates":[-80.187349,25.774481],"type":"Point"}
}