{
  "type": "Feature",
  "properties": {
    "iso:country":"US",
    "sg:address":"3613 Silver Lace Ln",
    "sg:city":"Boynton Beach",
    "sg:classifiers":[
        {
            "category":"Real Estate",
            "subcategory":"Real Estate Agent",
            "type":"Services"
        }
    ],
    "sg:phone":"+1 561 736 2988",
    "sg:postcode":"33436",
    "sg:province":"FL",
    "wof:name":"Martincavage Brokerage Rl Est",
    "wof:placetype":"venue"
},
  "geometry": {"coordinates":[-80.100758,26.528911],"type":"Point"}
}