{
  "type": "Feature",
  "properties": {
    "addr:full":"3394 SE Brown Rd Arcadia FL 34266",
    "addr:housenumber":"3394",
    "addr:postcode":"34266",
    "addr:street":"Se Brown Rd",
    "iso:country":"US",
    "sg:address":"3394 SE Brown Rd",
    "sg:city":"Arcadia",
    "sg:classifiers":[
        {
            "category":"Transit Center",
            "subcategory":"Freight",
            "type":"Transportation"
        },
        {
            "category":"Freight",
            "type":"Transportation"
        }
    ],
    "sg:phone":"+1 863 494 7800",
    "sg:postcode":"34266",
    "sg:province":"FL",
    "sg:tags":[
        "local",
        "trucking-motor",
        "trucking"
    ],
    "sg:website":"http://www.oldskoolphreak.com",
    "wof:name":"Orange Blossom Hauling Inc",
    "wof:placetype":"venue"
},
  "geometry": {"coordinates":[-81.81977999999999,27.201944],"type":"Point"}
}