{
  "type": "Feature",
  "properties": {
    "addr:full":"4303 Waring Rd Lakeland FL 33811",
    "addr:housenumber":"4303",
    "addr:postcode":"33811",
    "addr:street":"Waring Rd",
    "iso:country":"US",
    "sg:address":"4303 Waring Rd",
    "sg:city":"Lakeland",
    "sg:classifiers":[
        {
            "category":"Social Services",
            "subcategory":"Child Care",
            "type":"Services"
        }
    ],
    "sg:phone":"+1 863 647 3978",
    "sg:postcode":"33811",
    "sg:province":"FL",
    "wof:name":"Waring Oaks Academy",
    "wof:placetype":"venue"
},
  "geometry": {"coordinates":[-81.99896200000001,27.985275],"type":"Point"}
}