{
  "type": "Feature",
  "properties": {
    "iso:country":"US",
    "sg:address":"15233 SW 31st Ln",
    "sg:city":"Miami",
    "sg:classifiers":[
        {
            "category":"Manufacturing",
            "subcategory":"Building Materials",
            "type":"Manufacturing & Wholesale Goods"
        }
    ],
    "sg:phone":"+1 305 552 1086",
    "sg:postcode":"33185",
    "sg:province":"FL",
    "sg:tags":[
        "frames",
        "doors",
        "accessory"
    ],
    "wof:name":"JC Commercial Doors Inc",
    "wof:placetype":"venue"
},
  "geometry": {"coordinates":[-80.440769,25.737547],"type":"Point"}
}