{
  "type": "Feature",
  "properties": {
    "addr:full":"1111 Crestwood Blvd Lake Worth FL 33460",
    "addr:housenumber":"1111",
    "addr:postcode":"33460",
    "addr:street":"Crestwood Blvd",
    "iso:country":"US",
    "sg:address":"1111 Crestwood Blvd",
    "sg:city":"Lake Worth",
    "sg:classifiers":[
        {
            "category":"Professional",
            "subcategory":"Detective & Security Services",
            "type":"Services"
        }
    ],
    "sg:phone":"+1 561 588 1802",
    "sg:postcode":"33460",
    "sg:province":"FL",
    "sg:tags":[
        "private",
        "investigator"
    ],
    "wof:name":"R D Strohcker Invstgation Svcs",
    "wof:placetype":"venue"
},
  "geometry": {"coordinates":[-80.058144,26.631911],"type":"Point"}
}