{
  "type": "Feature",
  "properties": {
    "addr:full":"7110 NW 42nd St Pompano Beach FL 33065",
    "addr:housenumber":"7110",
    "addr:postcode":"33065",
    "addr:street":"Nw 42Nd St",
    "iso:country":"US",
    "sg:address":"7110 NW 42nd St",
    "sg:city":"Pompano Beach",
    "sg:classifiers":[
        {
            "category":"Professional",
            "subcategory":"Business Services",
            "type":"Services"
        }
    ],
    "sg:phone":"+1 954 755 0336",
    "sg:postcode":"33065",
    "sg:province":"FL",
    "wof:name":"John Decicco Enterprises Inc",
    "wof:placetype":"venue"
},
  "geometry": {"coordinates":[-80.22049199999999,26.2823],"type":"Point"}
}