{
  "type": "Feature",
  "properties": {
    "addr:full":"13125 S John Young Pkwy Orlando FL 32837",
    "addr:housenumber":"13125",
    "addr:postcode":"32837",
    "addr:street":"S John Young Pkwy",
    "iso:country":"US",
    "sg:address":"13125 S John Young Pkwy",
    "sg:city":"Orlando",
    "sg:classifiers":[
        {
            "category":"Personal",
            "type":"Services"
        },
        {
            "category":"Retail",
            "subcategory":"Storage",
            "type":"Services"
        }
    ],
    "sg:phone":"+1 407 240 3090",
    "sg:postcode":"32837",
    "sg:province":"FL",
    "sg:tags":[
        "moving-self",
        "full",
        "automobile",
        "household",
        "recreational",
        "commercial",
        "campers-storage",
        "vehicle",
        "mover",
        "self"
    ],
    "sg:website":"http://www.extraspace.com/Storage/Facilities/US/Florida/Orlando/501229/Facility.aspx#cid=ypps",
    "wof:name":"Extra Space Storage - Self Storage Orlando",
    "wof:placetype":"venue"
},
  "geometry": {"coordinates":[-81.425692,28.375086],"type":"Point"}
}