{
  "type": "Feature",
  "properties": {
    "addr:full":"729 Edgewood Ave S Jacksonville FL 32205",
    "addr:housenumber":"729",
    "addr:postcode":"32205",
    "addr:street":"Edgewood Ave S",
    "iso:country":"US",
    "sg:address":"729 Edgewood Ave S",
    "sg:city":"Jacksonville",
    "sg:classifiers":[
        {
            "category":"Retail",
            "subcategory":"Funeral Services",
            "type":"Services"
        }
    ],
    "sg:phone":"+1 904 355 5641",
    "sg:postcode":"32205",
    "sg:province":"FL",
    "sg:tags":[
        "home"
    ],
    "wof:name":"SCI",
    "wof:placetype":"venue"
},
  "geometry": {"coordinates":[-81.721183,30.315105],"type":"Point"}
}