{
  "type": "Feature",
  "properties": {
    "iso:country":"US",
    "sg:address":"1687 Goodwood Dr",
    "sg:city":"Tallahassee",
    "sg:classifiers":[
        {
            "category":"Professional",
            "subcategory":"Management & Consulting",
            "type":"Services"
        }
    ],
    "sg:phone":"+1 850 422 0027",
    "sg:postcode":"32308",
    "sg:province":"FL",
    "sg:tags":[
        "consultant"
    ],
    "wof:name":"Cuneo Creative Consultants",
    "wof:placetype":"venue"
},
  "geometry": {"coordinates":[-84.25203999999999,30.46602],"type":"Point"}
}