{
  "type": "Feature",
  "properties": {
    "iso:country":"US",
    "sg:address":"3107 Stirling Rd",
    "sg:city":"Fort Lauderdale",
    "sg:classifiers":[
        {
            "category":"Professional",
            "subcategory":"Lawyer & Legal Services",
            "type":"Services"
        }
    ],
    "sg:phone":"+1 954 455 8685",
    "sg:postcode":"33312",
    "sg:province":"FL",
    "sg:tags":[
        "attorney"
    ],
    "sg:website":"www.torallaw.com",
    "wof:name":"Toral Associates",
    "wof:placetype":"venue"
},
  "geometry": {"coordinates":[-80.185957,26.047382],"type":"Point"}
}