{
  "type": "Feature",
  "properties": {
    "iso:country":"US",
    "sg:address":"700 SW 3 Ave",
    "sg:city":"Miami",
    "sg:classifiers":[
        {
            "category":"Building & Trades",
            "subcategory":"Locksmith",
            "type":"Services"
        }
    ],
    "sg:phone":"+1 305 908 6170",
    "sg:postcode":"33101",
    "sg:province":"FL",
    "sg:tags":[
        "key"
    ],
    "wof:name":"A Locksmith 0 0 24 7",
    "wof:placetype":"venue"
},
  "geometry": {"coordinates":[-80.199262,25.767194],"type":"Point"}
}