{
  "type": "Feature",
  "properties": {
    "addr:full":"31313 Inez St Deland FL 32720",
    "addr:postcode":"31313;32720",
    "addr:street":"Inez St",
    "iso:country":"US",
    "sg:address":"31313 Inez St",
    "sg:city":"Deland",
    "sg:classifiers":[
        {
            "category":"Retail",
            "subcategory":"Auto Repair",
            "type":"Services"
        }
    ],
    "sg:phone":"+1 386 736 8005",
    "sg:postcode":"32720",
    "sg:province":"FL",
    "sg:tags":[
        "repairing",
        "automobile"
    ],
    "wof:name":"M&R Undercar Inc",
    "wof:placetype":"venue"
},
  "geometry": {"coordinates":[-81.43630899999999,28.990327],"type":"Point"}
}