{
  "type": "Feature",
  "properties": {
    "iso:country":"US",
    "sg:address":"2213 Tamiami Trl",
    "sg:city":"Bradenton",
    "sg:classifiers":[
        {
            "category":"Personal",
            "subcategory":"Beauty Salon",
            "type":"Services"
        }
    ],
    "sg:phone":"+1 941 746 6880",
    "sg:postcode":"34205",
    "sg:province":"FL",
    "wof:name":"Tlc Hair Designs",
    "wof:placetype":"venue"
},
  "geometry": {"coordinates":[-82.575323,27.479638],"type":"Point"}
}