{
  "type": "Feature",
  "properties": {
    "iso:country":"US",
    "sg:address":"1460 NE State Road 16",
    "sg:city":"Starke",
    "sg:classifiers":[
        {
            "category":"Manufacturing",
            "subcategory":"Furniture",
            "type":"Manufacturing & Wholesale Goods"
        }
    ],
    "sg:phone":"+1 904 964 4320",
    "sg:postcode":"32091",
    "sg:province":"FL",
    "sg:tags":[
        "fixtures-wholesale",
        "store",
        "manufacturer"
    ],
    "wof:name":"Acore Shelving & Products Inc",
    "wof:placetype":"venue"
},
  "geometry": {"coordinates":[-82.07104699999999,29.954206],"type":"Point"}
}