{
  "type": "Feature",
  "properties": {
    "iso:country":"US",
    "sg:address":"10366 SE US Hwy 441",
    "sg:city":"Belleview",
    "sg:classifiers":[
        {
            "category":"Building & Trades",
            "subcategory":"Construction",
            "type":"Services"
        }
    ],
    "sg:phone":"+1 352 307 0207",
    "sg:postcode":"34420",
    "sg:province":"FL",
    "sg:tags":[
        "resurfacing",
        "laying",
        "refinishing",
        "floor"
    ],
    "wof:name":"Martin V Bailey Flooring",
    "wof:placetype":"venue"
},
  "geometry": {"coordinates":[-82.071753,29.07135],"type":"Point"}
}