{
  "type": "Feature",
  "properties": {
    "addr:full":"282 Ave D Port St Joe FL 32456",
    "addr:housenumber":"282",
    "addr:postcode":"32456",
    "addr:street":"Ave D;St",
    "iso:country":"US",
    "sg:address":"282 Ave D",
    "sg:city":"Port St Joe",
    "sg:classifiers":[
        {
            "category":"Organizations",
            "subcategory":"Religious Organization",
            "type":"Services"
        }
    ],
    "sg:phone":"+1 850 227 3218",
    "sg:postcode":"32456",
    "sg:province":"FL",
    "sg:tags":[
        "clergy"
    ],
    "wof:name":"Chester F Davis",
    "wof:placetype":"venue"
},
  "geometry": {"coordinates":[-85.301777,29.820434],"type":"Point"}
}