{
  "type": "Feature",
  "properties": {
    "addr:full":"1331 Julio Ln Orlando FL 32807",
    "addr:housenumber":"1331",
    "addr:postcode":"32807",
    "addr:street":"Julio Ln",
    "iso:country":"US",
    "sg:address":"1331 Julio Ln",
    "sg:city":"Orlando",
    "sg:classifiers":[
        {
            "category":"Real Estate",
            "subcategory":"Real Estate Operator",
            "type":"Services"
        }
    ],
    "sg:phone":"+1 407 273 0124",
    "sg:postcode":"32807",
    "sg:province":"FL",
    "sg:tags":[
        "property",
        "lessor"
    ],
    "wof:name":"4079299939",
    "wof:placetype":"venue"
},
  "geometry": {"coordinates":[-81.313113,28.525801],"type":"Point"}
}