{
  "type": "Feature",
  "properties": {
    "addr:full":"12954 Forrest Dr Seminole FL 33776",
    "addr:housenumber":"12954",
    "addr:postcode":"33776",
    "addr:street":"Forrest Dr",
    "iso:country":"US",
    "sg:address":"12954 Forrest Dr",
    "sg:city":"Seminole",
    "sg:classifiers":[
        {
            "category":"Home & Garden",
            "subcategory":"Garden Supply",
            "type":"Retail Goods"
        }
    ],
    "sg:phone":"+1 727 398 3093",
    "sg:postcode":"33776",
    "sg:province":"FL",
    "wof:name":"Suncoast Irrigation Inc",
    "wof:placetype":"venue"
},
  "geometry": {"coordinates":[-82.81816600000001,27.856768],"type":"Point"}
}