{
  "type": "Feature",
  "properties": {
    "iso:country":"US",
    "sg:address":"2761 Coral Way",
    "sg:city":"Coral Gables",
    "sg:classifiers":[
        {
            "category":"Restaurant",
            "type":"Food & Drink"
        }
    ],
    "sg:phone":"+1 305 444 3080",
    "sg:postcode":"33145",
    "sg:province":"FL",
    "wof:name":"La Cremita Cafeteria",
    "wof:placetype":"venue"
},
  "geometry": {"coordinates":[-80.238998,25.750299],"type":"Point"}
}