{
  "type": "Feature",
  "properties": {
    "iso:country":"US",
    "sg:address":"4860 W Kennedy Blvd",
    "sg:city":"Tampa",
    "sg:classifiers":[
        {
            "category":"Restaurant",
            "type":"Food & Drink"
        }
    ],
    "sg:menulink":"http://www.allmenus.com/fl/tampa/255161-shulas-american-steakhouse/menu/",
    "sg:phone":"+1 813 286 4366",
    "sg:postcode":"33609",
    "sg:province":"FL",
    "sg:tags":[
        "american",
        "steakhouse"
    ],
    "wof:name":"Shula's American Steakhouse",
    "wof:placetype":"venue"
},
  "geometry": {"coordinates":[-82.526791,27.944755],"type":"Point"}
}