{
  "type": "Feature",
  "properties": {
    "iso:country":"US",
    "sg:address":"930 E University Ave",
    "sg:city":"Gainesville",
    "sg:classifiers":[
        {
            "category":"Professional",
            "type":"Services"
        }
    ],
    "sg:phone":"+1 352 367 2903",
    "sg:postcode":"32601",
    "sg:province":"FL",
    "wof:name":"Ksp Inc",
    "wof:placetype":"venue"
},
  "geometry": {"coordinates":[-82.313698,29.652024],"type":"Point"}
}