{
  "type": "Feature",
  "properties": {
    "iso:country":"US",
    "sg:address":"1631 Hillcrest St",
    "sg:city":"Orlando",
    "sg:classifiers":[
        {
            "category":"Personal",
            "subcategory":"Beauty Salon",
            "type":"Services"
        }
    ],
    "sg:phone":"+1 407 898 0041",
    "sg:postcode":"32803",
    "sg:province":"FL",
    "sg:tags":[
        "school"
    ],
    "wof:name":"Advantage Academy-Nails",
    "wof:placetype":"venue"
},
  "geometry": {"coordinates":[-81.35857300000001,28.552336],"type":"Point"}
}