{
  "type": "Feature",
  "properties": {
    "iso:country":"US",
    "sg:address":"6521 S Suncoast Blvd",
    "sg:city":"Homosassa",
    "sg:classifiers":[
        {
            "category":"Autos & Motor Vehicles",
            "subcategory":"Automobile Sales",
            "type":"Retail Goods"
        }
    ],
    "sg:phone":"+1 352 621 3990",
    "sg:postcode":"34446",
    "sg:province":"FL",
    "sg:tags":[
        "car",
        "dealer"
    ],
    "wof:name":"Manatee Auto Sales",
    "wof:placetype":"venue"
},
  "geometry": {"coordinates":[-82.553268,28.762826],"type":"Point"}
}