{
  "type": "Feature",
  "properties": {
    "iso:country":"US",
    "sg:address":"101 W 12th St",
    "sg:city":"Jacksonville",
    "sg:classifiers":[
        {
            "category":"Education",
            "subcategory":"School",
            "type":"Public Place"
        }
    ],
    "sg:phone":"+1 904 630 6550",
    "sg:postcode":"32206",
    "sg:province":"FL",
    "sg:website":"www.rocket.org",
    "wof:name":"Andrew A Robinson Elementary",
    "wof:placetype":"venue"
},
  "geometry": {"coordinates":[-81.656837,30.35078],"type":"Point"}
}