{
  "type": "Feature",
  "properties": {
    "addr:full":"1804 N Dixie Hwy West Palm Beach FL 33407",
    "addr:housenumber":"1804",
    "addr:postcode":"33407",
    "addr:street":"N Dixie Hwy",
    "iso:country":"US",
    "sg:address":"1804 N Dixie Hwy",
    "sg:city":"West Palm Beach",
    "sg:classifiers":[
        {
            "category":"Building & Trades",
            "subcategory":"Construction",
            "type":"Services"
        }
    ],
    "sg:phone":"+1 561 655 9277",
    "sg:postcode":"33407",
    "sg:province":"FL",
    "sg:tags":[
        "general",
        "contractor"
    ],
    "sg:website":"www.sloaneconstruction.com",
    "wof:name":"Sloane Construction Co",
    "wof:placetype":"venue"
},
  "geometry": {"coordinates":[-80.052989,26.728786],"type":"Point"}
}