{
  "type": "Feature",
  "properties": {
    "addr:full":"3100 N 75th Ave Hollywood FL 33024",
    "addr:housenumber":"3100",
    "addr:postcode":"33024",
    "addr:street":"N 75Th Ave",
    "iso:country":"US",
    "sg:address":"3100 N 75th Ave",
    "sg:city":"Hollywood",
    "sg:classifiers":[
        {
            "category":"Social Services",
            "subcategory":"Child Care",
            "type":"Services"
        }
    ],
    "sg:phone":"+1 954 987 7260",
    "sg:postcode":"33024",
    "sg:province":"FL",
    "sg:tags":[
        "school",
        "day"
    ],
    "wof:name":"Lyceesranco American",
    "wof:placetype":"venue"
},
  "geometry": {"coordinates":[-80.239396,26.0372],"type":"Point"}
}