{
  "type": "Feature",
  "properties": {
    "addr:full":"4711 Lexington Ave Jacksonville FL 32210",
    "addr:housenumber":"4711",
    "addr:postcode":"32210",
    "addr:street":"Lexington Ave",
    "iso:country":"US",
    "sg:address":"4711 Lexington Ave",
    "sg:city":"Jacksonville",
    "sg:classifiers":[
        {
            "category":"Professional",
            "subcategory":"Accounting & Tax Preparation",
            "type":"Services"
        }
    ],
    "sg:phone":"+1 904 388 0651",
    "sg:postcode":"32210",
    "sg:province":"FL",
    "sg:tags":[
        "accountant",
        "business"
    ],
    "wof:name":"Gillis and Gillis Inc",
    "wof:placetype":"venue"
},
  "geometry": {"coordinates":[-81.72800599999999,30.28317],"type":"Point"}
}