{
  "type": "Feature",
  "properties": {
    "iso:country":"US",
    "sg:address":"635 S Woodland Blvd",
    "sg:city":"DeLand",
    "sg:classifiers":[
        {
            "category":"Restaurant",
            "type":"Food & Drink"
        }
    ],
    "sg:phone":"+1 386 734 8181",
    "sg:postcode":"32720",
    "sg:province":"FL",
    "sg:tags":[
        "breakfast",
        "eating",
        "brunch"
    ],
    "wof:name":"Doug & Lil's Potato Patch",
    "wof:placetype":"venue"
},
  "geometry": {"coordinates":[-81.30274900000001,29.018077],"type":"Point"}
}