{
  "type": "Feature",
  "properties": {
    "addr:full":"14545 Military Trl Delray Beach FL 33484",
    "addr:housenumber":"14545",
    "addr:postcode":"33484",
    "addr:street":"Military Trl",
    "iso:country":"US",
    "sg:address":"14545 Military Trl",
    "sg:city":"Delray Beach",
    "sg:classifiers":[
        {
            "category":"Building & Trades",
            "subcategory":"Landscaping Services",
            "type":"Services"
        }
    ],
    "sg:phone":"+1 561 495 7784",
    "sg:postcode":"33484",
    "sg:province":"FL",
    "wof:name":"US Lawns of South Palm Beach",
    "wof:placetype":"venue"
},
  "geometry": {"coordinates":[-80.122668,26.461138],"type":"Point"}
}