{
  "type": "Feature",
  "properties": {
    "iso:country":"US",
    "sg:address":"4950 SE 44th Avenue Rd",
    "sg:city":"Ocala",
    "sg:classifiers":[
        {
            "category":"Building & Trades",
            "subcategory":"Construction",
            "type":"Services"
        }
    ],
    "sg:phone":"+1 352 694 3609",
    "sg:postcode":"34480",
    "sg:province":"FL",
    "sg:tags":[
        "contractor",
        "painting",
        "hanging"
    ],
    "wof:name":"Jerri Davis' Painting",
    "wof:placetype":"venue"
},
  "geometry": {"coordinates":[-82.077119,29.137771],"type":"Point"}
}