{
  "type": "Feature",
  "properties": {
    "iso:country":"US",
    "sg:address":"918 S Joy Cir",
    "sg:city":"Marco Island",
    "sg:classifiers":[
        {
            "category":"Shopping",
            "type":"Retail Goods"
        }
    ],
    "sg:phone":"+1 239 389 7669",
    "sg:postcode":"34145",
    "sg:province":"FL",
    "sg:tags":[
        "art",
        "gallery",
        "dealer"
    ],
    "sg:website":"www.lauramostaghel.com",
    "wof:name":"Mostaghel & Mostaghel",
    "wof:placetype":"venue"
},
  "geometry": {"coordinates":[-81.72712199999999,25.949447],"type":"Point"}
}