{
  "type": "Feature",
  "properties": {
    "iso:country":"US",
    "sg:address":"185 N Holiday Rd",
    "sg:city":"Destin",
    "sg:classifiers":[
        {
            "category":"Building & Trades",
            "subcategory":"Construction",
            "type":"Services"
        }
    ],
    "sg:phone":"+1 850 650 4386",
    "sg:postcode":"32550",
    "sg:province":"FL",
    "sg:tags":[
        "designer",
        "dealer",
        "pool",
        "swimming"
    ],
    "sg:website":"www.tamtechpools.com",
    "wof:name":"About Pools",
    "wof:placetype":"venue"
},
  "geometry": {"coordinates":[-86.379205,30.387259],"type":"Point"}
}