{
  "type": "Feature",
  "properties": {
    "iso:country":"US",
    "sg:address":"16650 W Dixie Hwy",
    "sg:city":"Miami",
    "sg:classifiers":[
        {
            "category":"Health Services",
            "subcategory":"Nursing And Care Facility",
            "type":"Services"
        }
    ],
    "sg:phone":"+1 305 945 7447",
    "sg:postcode":"33160",
    "sg:province":"FL",
    "sg:tags":[
        "skilled"
    ],
    "wof:name":"Watercrest Nursing & Rehab",
    "wof:placetype":"venue"
},
  "geometry": {"coordinates":[-80.15611800000001,25.929202],"type":"Point"}
}