{
  "type": "Feature",
  "properties": {
    "iso:country":"US",
    "sg:address":"11902 Debary Ct",
    "sg:city":"Orlando",
    "sg:classifiers":[
        {
            "category":"Professional",
            "type":"Services"
        }
    ],
    "sg:phone":"+1 407 238 0308",
    "sg:postcode":"32821",
    "sg:province":"FL",
    "wof:name":"Maria Isernia PA",
    "wof:placetype":"venue"
},
  "geometry": {"coordinates":[-81.449519,28.392541],"type":"Point"}
}