{
  "type": "Feature",
  "properties": {
    "iso:country":"US",
    "sg:address":"5196 NW 6th Ct",
    "sg:city":"Delray Beach",
    "sg:classifiers":[
        {
            "category":"Real Estate",
            "subcategory":"Real Estate Agent",
            "type":"Services"
        }
    ],
    "sg:phone":"+1 561 495 6275",
    "sg:postcode":"33445",
    "sg:province":"FL",
    "wof:name":"Bathie Mark Grandin",
    "wof:placetype":"venue"
},
  "geometry": {"coordinates":[-80.12069200000001,26.472336],"type":"Point"}
}