{
  "type": "Feature",
  "properties": {
    "addr:full":"4124 Oakhurst Cir W Sarasota FL 34233",
    "addr:housenumber":"4124",
    "addr:postcode":"34233",
    "addr:street":"Oakhurst Cir W",
    "iso:country":"US",
    "sg:address":"4124 Oakhurst Cir W",
    "sg:city":"Sarasota",
    "sg:classifiers":[
        {
            "category":"Building & Trades",
            "subcategory":"Construction",
            "type":"Services"
        }
    ],
    "sg:phone":"+1 941 377 7183",
    "sg:postcode":"34233",
    "sg:province":"FL",
    "sg:tags":[
        "residential"
    ],
    "wof:name":"Lin Graber Construction",
    "wof:placetype":"venue"
},
  "geometry": {"coordinates":[-82.476494,27.29408],"type":"Point"}
}