{
  "type": "Feature",
  "properties": {
    "iso:country":"US",
    "sg:address":"4300 Mildred Bass Rd",
    "sg:city":"St Cloud",
    "sg:classifiers":[
        {
            "category":"Professional",
            "subcategory":"Business Services",
            "type":"Services"
        }
    ],
    "sg:phone":"+1 407 891 0471",
    "sg:postcode":"34772",
    "sg:province":"FL",
    "wof:name":"Orin & Orin",
    "wof:placetype":"venue"
},
  "geometry": {"coordinates":[-81.266458,28.158927],"type":"Point"}
}