{
  "type": "Feature",
  "properties": {
    "iso:country":"US",
    "sg:address":"33 E Flagler St",
    "sg:city":"Miami",
    "sg:classifiers":[
        {
            "category":"Shopping",
            "subcategory":"Jewelry",
            "type":"Retail Goods"
        }
    ],
    "sg:phone":"+1 305 379 3800",
    "sg:postcode":"33131",
    "sg:province":"FL",
    "sg:website":"www.richardsjewelry.com",
    "wof:name":"Richard's Gems & Jewelry",
    "wof:placetype":"venue"
},
  "geometry": {"coordinates":[-80.19319900000001,25.7743],"type":"Point"}
}