{
  "type": "Feature",
  "properties": {
    "addr:full":"275 Maple Ave Palm Harbor FL 34684",
    "addr:housenumber":"275",
    "addr:postcode":"34684",
    "addr:street":"Maple Ave",
    "iso:country":"US",
    "sg:address":"275 Maple Ave",
    "sg:city":"Palm Harbor",
    "sg:classifiers":[
        {
            "category":"Manufacturing",
            "subcategory":"Rubber & Plastics",
            "type":"Manufacturing & Wholesale Goods"
        }
    ],
    "sg:phone":"+1 727 934 0007",
    "sg:postcode":"34684",
    "sg:province":"FL",
    "sg:tags":[
        "coating",
        "manufacturer"
    ],
    "wof:name":"Sunrock Inc",
    "wof:placetype":"venue"
},
  "geometry": {"coordinates":[-82.732437,28.105282],"type":"Point"}
}