{
  "type": "Feature",
  "properties": {
    "addr:full":"6350 NW 74th Ave Miami FL 33166",
    "addr:housenumber":"6350",
    "addr:postcode":"33166",
    "addr:street":"Nw 74Th Ave",
    "iso:country":"US",
    "sg:address":"6350 NW 74th Ave",
    "sg:city":"Miami",
    "sg:classifiers":[
        {
            "category":"Wholesale",
            "subcategory":"Hardware",
            "type":"Manufacturing & Wholesale Goods"
        }
    ],
    "sg:phone":"+1 305 717 0955",
    "sg:postcode":"33166",
    "sg:province":"FL",
    "sg:tags":[
        "distributor",
        "units-manufacturers",
        "refrigeration",
        "heating",
        "con"
    ],
    "sg:website":"http://www.uri.com",
    "wof:name":"U R I F9",
    "wof:placetype":"venue"
},
  "geometry": {"coordinates":[-80.317875,25.83119],"type":"Point"}
}