{
  "type": "Feature",
  "properties": {
    "iso:country":"US",
    "sg:address":"8998 High Cotton Ln",
    "sg:city":"Fort Myers",
    "sg:classifiers":[
        {
            "category":"Restaurant",
            "type":"Food & Drink"
        }
    ],
    "sg:phone":"+1 239 337 1922",
    "sg:postcode":"33905",
    "sg:province":"FL",
    "sg:tags":[
        "eating",
        "desert",
        "ice",
        "mfg"
    ],
    "wof:name":"Haagen-Dazs",
    "wof:placetype":"venue"
},
  "geometry": {"coordinates":[-81.808184,26.642534],"type":"Point"}
}