{
  "type": "Feature",
  "properties": {
    "iso:country":"US",
    "sg:address":"500 E Horatio Ave",
    "sg:city":"Maitland",
    "sg:classifiers":[
        {
            "category":"Personal",
            "subcategory":"Beauty Salon",
            "type":"Services"
        }
    ],
    "sg:phone":"+1 407 647 0460",
    "sg:postcode":"32751",
    "sg:province":"FL",
    "sg:tags":[
        "shop"
    ],
    "wof:name":"Hair By Randy Ogburn",
    "wof:placetype":"venue"
},
  "geometry": {"coordinates":[-81.361054,28.627509],"type":"Point"}
}