{
  "type": "Feature",
  "properties": {
    "addr:full":"914 Alameda St Orlando FL 32804",
    "addr:housenumber":"914",
    "addr:postcode":"32804",
    "addr:street":"Alameda St",
    "iso:country":"US",
    "sg:address":"914 Alameda St",
    "sg:city":"Orlando",
    "sg:classifiers":[
        {
            "category":"Shopping",
            "type":"Retail Goods"
        }
    ],
    "sg:phone":"+1 407 246 6968",
    "sg:postcode":"32804",
    "sg:province":"FL",
    "sg:tags":[
        "merchandise"
    ],
    "wof:name":"Biotek Assoc Inc",
    "wof:placetype":"venue"
},
  "geometry": {"coordinates":[-81.393327,28.556974],"type":"Point"}
}