{
  "type": "Feature",
  "properties": {
    "addr:full":"2450 Tim Gamble Pl Tallahassee FL 32308",
    "addr:postcode":"2450;32308",
    "addr:street":"Gamble Pl",
    "iso:country":"US",
    "sg:address":"2450 Tim Gamble Pl",
    "sg:city":"Tallahassee",
    "sg:classifiers":[
        {
            "category":"Professional",
            "subcategory":"Computer Services",
            "type":"Services"
        }
    ],
    "sg:phone":"+1 850 671 4007",
    "sg:postcode":"32308",
    "sg:province":"FL",
    "sg:tags":[
        "internet"
    ],
    "wof:name":"Network Tallahassee Inc",
    "wof:placetype":"venue"
},
  "geometry": {"coordinates":[-84.23800199999999,30.475516],"type":"Point"}
}