{
  "type": "Feature",
  "properties": {
    "iso:country":"US",
    "sg:address":"4351 Castille Ct",
    "sg:city":"Milton",
    "sg:classifiers":[
        {
            "category":"Shopping",
            "subcategory":"Clothing, Apparel, & Fashions",
            "type":"Retail Goods"
        }
    ],
    "sg:phone":"+1 850 995 0162",
    "sg:postcode":"32571",
    "sg:province":"FL",
    "sg:tags":[
        "wear"
    ],
    "wof:name":"Mark & Hollys Kids Boutique",
    "wof:placetype":"venue"
},
  "geometry": {"coordinates":[-87.09945999999999,30.594014],"type":"Point"}
}