{
  "type": "Feature",
  "properties": {
    "addr:full":"801 N Scenic Hwy Frostproof FL 33843",
    "addr:housenumber":"801",
    "addr:postcode":"33843",
    "addr:street":"N Scenic Hwy",
    "iso:country":"US",
    "sg:address":"801 N Scenic Hwy",
    "sg:city":"Frostproof",
    "sg:classifiers":[
        {
            "category":"Restaurant",
            "type":"Food & Drink"
        }
    ],
    "sg:phone":"+1 863 635 6688",
    "sg:postcode":"33843",
    "sg:province":"FL",
    "sg:tags":[
        "eating"
    ],
    "wof:name":"China Garden Restaurant",
    "wof:placetype":"venue"
},
  "geometry": {"coordinates":[-81.530669,27.757076],"type":"Point"}
}