{
  "type": "Feature",
  "properties": {
    "iso:country":"US",
    "sg:address":"4113 S US Highway 17-92",
    "sg:city":"Debary",
    "sg:classifiers":[
        {
            "category":"Autos & Motor Vehicles",
            "subcategory":"Automobile Sales",
            "type":"Retail Goods"
        }
    ],
    "sg:phone":"+1 386 668 7535",
    "sg:postcode":"32713",
    "sg:province":"FL",
    "sg:tags":[
        "car"
    ],
    "sg:website":"www.chrysler.com",
    "wof:name":"Metro Chrysler Plymouth Jeep Inc",
    "wof:placetype":"venue"
},
  "geometry": {"coordinates":[-81.30538799999999,28.896689],"type":"Point"}
}