{
  "type": "Feature",
  "properties": {
    "iso:country":"US",
    "sg:address":"1227 W Robinson St",
    "sg:city":"Orlando",
    "sg:classifiers":[
        {
            "category":"Building & Trades",
            "subcategory":"Construction",
            "type":"Services"
        }
    ],
    "sg:phone":"+1 407 425 1712",
    "sg:postcode":"32805",
    "sg:province":"FL",
    "sg:tags":[
        "carpentry",
        "contractor"
    ],
    "wof:name":"Cabinet Facers",
    "wof:placetype":"venue"
},
  "geometry": {"coordinates":[-81.39729800000001,28.545747],"type":"Point"}
}