{
  "type": "Feature",
  "properties": {
    "iso:country":"US",
    "sg:address":"9251 Bratt Rd",
    "sg:city":"Century",
    "sg:classifiers":[
        {
            "category":"Building & Trades",
            "subcategory":"Construction",
            "type":"Services"
        }
    ],
    "sg:phone":"+1 850 426 1978",
    "sg:postcode":"32535",
    "sg:province":"FL",
    "sg:tags":[
        "clearing",
        "land",
        "leveling"
    ],
    "wof:name":"Coastal Bobcat Svc",
    "wof:placetype":"venue"
},
  "geometry": {"coordinates":[-87.406029,30.958143],"type":"Point"}
}