{
  "type": "Feature",
  "properties": {
    "iso:country":"US",
    "sg:address":"2968 W Gulf To Lake Hwy",
    "sg:city":"Lecanto",
    "sg:classifiers":[
        {
            "category":"Home & Garden",
            "subcategory":"Home Furnishings",
            "type":"Retail Goods"
        },
        {
            "category":"Home & Garden",
            "subcategory":"Building Materials",
            "type":"Retail Goods"
        },
        {
            "category":"Manufacturing",
            "subcategory":"Building Materials",
            "type":"Manufacturing & Wholesale Goods"
        }
    ],
    "sg:phone":"+1 352 746 1998",
    "sg:postcode":"34461",
    "sg:province":"FL",
    "sg:tags":[
        "blind",
        "draperies",
        "installation",
        "doors",
        "vertical",
        "curtains",
        "blinds-venetian",
        "accessory",
        "window",
        "shade",
        "frames"
    ],
    "wof:name":"Vertical Blind Factory Inc",
    "wof:placetype":"venue"
},
  "geometry": {"coordinates":[-82.4829,28.851783],"type":"Point"}
}