{
  "type": "Feature",
  "properties": {
    "addr:full":"1002 Iowa Ave Lynn Haven FL 32444",
    "addr:housenumber":"1002",
    "addr:postcode":"32444",
    "addr:street":"Iowa Ave",
    "iso:country":"US",
    "sg:address":"1002 Iowa Ave",
    "sg:city":"Lynn Haven",
    "sg:classifiers":[
        {
            "category":"Manufacturing",
            "subcategory":"Lumber",
            "type":"Manufacturing & Wholesale Goods"
        }
    ],
    "sg:phone":"+1 850 265 5157",
    "sg:postcode":"32444",
    "sg:province":"FL",
    "sg:tags":[
        "operation",
        "timber",
        "tract"
    ],
    "wof:name":"CB Waller Enterprises Ltd",
    "wof:placetype":"venue"
},
  "geometry": {"coordinates":[-85.64083599999999,30.240576],"type":"Point"}
}