{
  "type": "Feature",
  "properties": {
    "addr:full":"501 Briny Ave Pompano Beach FL 33062",
    "addr:housenumber":"501",
    "addr:postcode":"33062",
    "addr:street":"Briny Ave",
    "iso:country":"US",
    "sg:address":"501 Briny Ave",
    "sg:city":"Pompano Beach",
    "sg:classifiers":[
        {
            "category":"Organizations",
            "subcategory":"Community Association",
            "type":"Services"
        }
    ],
    "sg:phone":"+1 954 941 7650",
    "sg:postcode":"33062",
    "sg:province":"FL",
    "sg:tags":[
        "condominium",
        "for",
        "time"
    ],
    "wof:name":"Seaside Beach Club",
    "wof:placetype":"venue"
},
  "geometry": {"coordinates":[-80.09023500000001,26.228088],"type":"Point"}
}