{
  "type": "Feature",
  "properties": {
    "addr:full":"1904 SW 180th Ter Hollywood FL 33029",
    "addr:housenumber":"1904",
    "addr:postcode":"33029",
    "addr:street":"Sw 180Th Ter",
    "iso:country":"US",
    "sg:address":"1904 SW 180th Ter",
    "sg:city":"Hollywood",
    "sg:classifiers":[
        {
            "category":"Shopping",
            "subcategory":"Jewelry",
            "type":"Retail Goods"
        }
    ],
    "sg:phone":"+1 305 215 0845",
    "sg:postcode":"33029",
    "sg:province":"FL",
    "wof:name":"Aroland",
    "wof:placetype":"venue"
},
  "geometry": {"coordinates":[-80.388239,25.990689],"type":"Point"}
}