{
  "type": "Feature",
  "properties": {
    "iso:country":"US",
    "sg:address":"160 Santee Dr",
    "sg:city":"Panama City",
    "sg:classifiers":[
        {
            "category":"Recreation",
            "type":"Entertainment"
        }
    ],
    "sg:phone":"+1 850 747 0108",
    "sg:postcode":"32404",
    "sg:province":"FL",
    "wof:name":"Golden Heart Billiards",
    "wof:placetype":"venue"
},
  "geometry": {"coordinates":[-85.605941,30.159876],"type":"Point"}
}