{
  "type": "Feature",
  "properties": {
    "addr:full":"207 Wright Pkwy NW Fort Walton Beach FL 32548",
    "addr:housenumber":"207",
    "addr:postcode":"32548",
    "addr:street":"Wright Pkwy Nw",
    "iso:country":"US",
    "sg:address":"207 Wright Pkwy NW",
    "sg:city":"Fort Walton Beach",
    "sg:classifiers":[
        {
            "category":"Recreation",
            "type":"Entertainment"
        }
    ],
    "sg:phone":"+1 850 244 0098",
    "sg:postcode":"32548",
    "sg:province":"FL",
    "wof:name":"Natural Act Fishing Adventures",
    "wof:placetype":"venue"
},
  "geometry": {"coordinates":[-86.638907,30.425117],"type":"Point"}
}