{
  "type": "Feature",
  "properties": {
    "iso:country":"US",
    "sg:address":"7060 SW 10th St",
    "sg:city":"Fort Lauderdale",
    "sg:classifiers":[
        {
            "category":"Shopping",
            "subcategory":"Stationery & Office Supplies",
            "type":"Retail Goods"
        }
    ],
    "sg:phone":"+1 954 577 4281",
    "sg:postcode":"33317",
    "sg:province":"FL",
    "wof:name":"Royal Office Products",
    "wof:placetype":"venue"
},
  "geometry": {"coordinates":[-80.24602400000001,26.107336],"type":"Point"}
}