{
  "type": "Feature",
  "properties": {
    "iso:country":"US",
    "sg:address":"150 Williamson Blvd",
    "sg:city":"Ormond Beach",
    "sg:classifiers":[
        {
            "category":"Restaurant",
            "type":"Food & Drink"
        }
    ],
    "sg:menulink":"http://www.allmenus.com/fl/ormond-beach/39205-applebees/menu/",
    "sg:phone":"+1 386 672 0733",
    "sg:postcode":"32174",
    "sg:province":"FL",
    "sg:tags":[
        "burger",
        "american",
        "sandwich",
        "soup"
    ],
    "wof:name":"Applebee's",
    "wof:placetype":"venue"
},
  "geometry": {"coordinates":[-81.11331300000001,29.255269],"type":"Point"}
}