{
  "type": "Feature",
  "properties": {
    "iso:country":"US",
    "sg:address":"5006 Co Rd 214",
    "sg:city":"Keystone Heights",
    "sg:classifiers":[
        {
            "category":"Education",
            "subcategory":"School",
            "type":"Public Place"
        }
    ],
    "sg:phone":"+1 352 473 3159",
    "sg:postcode":"32656",
    "sg:province":"FL",
    "wof:name":"Morningstar Christian School",
    "wof:placetype":"venue"
},
  "geometry": {"coordinates":[-81.934174,29.799324],"type":"Point"}
}