{
  "type": "Feature",
  "properties": {
    "addr:full":"6182 William Mills St Jacksonville FL 32226",
    "addr:housenumber":"6182",
    "addr:postcode":"32226",
    "addr:street":"William Mills St",
    "iso:country":"US",
    "sg:address":"6182 William Mills St",
    "sg:city":"Jacksonville",
    "sg:classifiers":[
        {
            "category":"Government",
            "subcategory":"Office",
            "type":"Public Place"
        }
    ],
    "sg:phone":"+1 904 696 6417",
    "sg:postcode":"32226",
    "sg:province":"FL",
    "sg:tags":[
        "government-united",
        "state"
    ],
    "wof:name":"Us Cape Canaveral Detachment",
    "wof:placetype":"venue"
},
  "geometry": {"coordinates":[-81.531965,30.396265],"type":"Point"}
}