{
  "type": "Feature",
  "properties": {
    "iso:country":"US",
    "sg:address":"7645 Land O Lakes Blvd",
    "sg:city":"Land O Lakes",
    "sg:classifiers":[
        {
            "category":"Restaurant",
            "type":"Food & Drink"
        }
    ],
    "sg:phone":"+1 813 235 6349",
    "sg:postcode":"34638",
    "sg:province":"FL",
    "wof:name":"Pizza Milano",
    "wof:placetype":"venue"
},
  "geometry": {"coordinates":[-82.473975,28.258159],"type":"Point"}
}