{
  "type": "Feature",
  "properties": {
    "addr:full":"720 Tamiami Trl N Naples FL 34102",
    "addr:housenumber":"720",
    "addr:postcode":"34102",
    "addr:street":"Tamiami Trl N",
    "iso:country":"US",
    "sg:address":"720 Tamiami Trl N",
    "sg:city":"Naples",
    "sg:classifiers":[
        {
            "category":"Food & Beverages",
            "subcategory":"Liquor & Beverages",
            "type":"Retail Goods"
        }
    ],
    "sg:phone":"+1 239 434 6565",
    "sg:postcode":"34102",
    "sg:province":"FL",
    "sg:tags":[
        "alcoholic"
    ],
    "wof:name":"Priced Right Liquors",
    "wof:placetype":"venue"
},
  "geometry": {"coordinates":[-81.797022,26.157365],"type":"Point"}
}