{
  "type": "Feature",
  "properties": {
    "iso:country":"US",
    "sg:address":"144 W Leon Ln",
    "sg:city":"Cocoa Beach",
    "sg:classifiers":[
        {
            "category":"Building & Trades",
            "subcategory":"Electrical",
            "type":"Services"
        }
    ],
    "sg:phone":"+1 321 784 8704",
    "sg:postcode":"32931",
    "sg:province":"FL",
    "sg:tags":[
        "installation"
    ],
    "wof:name":"Michael D Lemire Shutter",
    "wof:placetype":"venue"
},
  "geometry": {"coordinates":[-80.608475,28.364637],"type":"Point"}
}