{
  "type": "Feature",
  "properties": {
    "iso:country":"US",
    "sg:address":"651 W Indiantown Rd",
    "sg:city":"Jupiter",
    "sg:classifiers":[
        {
            "category":"Health Services",
            "subcategory":"Doctor",
            "type":"Services"
        }
    ],
    "sg:phone":"+1 561 744 1887",
    "sg:postcode":"33458",
    "sg:province":"FL",
    "sg:tags":[
        "dentist"
    ],
    "wof:name":"Freedman & Haas",
    "wof:placetype":"venue"
},
  "geometry": {"coordinates":[-80.10495899999999,26.934059],"type":"Point"}
}