{
  "type": "Feature",
  "properties": {
    "addr:full":"1375 Jackson St Fort Myers FL 33901",
    "addr:housenumber":"1375",
    "addr:postcode":"33901",
    "addr:street":"Jackson St",
    "iso:country":"US",
    "sg:address":"1375 Jackson St",
    "sg:city":"Fort Myers",
    "sg:classifiers":[
        {
            "category":"Professional",
            "subcategory":"Management & Consulting",
            "type":"Services"
        }
    ],
    "sg:phone":"+1 239 334 3366",
    "sg:postcode":"33901",
    "sg:province":"FL",
    "sg:tags":[
        "consultant",
        "business"
    ],
    "wof:name":"LA Rue Planning & Mgmt Svc",
    "wof:placetype":"venue"
},
  "geometry": {"coordinates":[-81.86931,26.646343],"type":"Point"}
}