{
  "type": "Feature",
  "properties": {
    "iso:country":"US",
    "sg:address":"18341 NE 21st Ct",
    "sg:city":"North Miami Beach",
    "sg:classifiers":[
        {
            "category":"Shopping",
            "subcategory":"Stationery & Office Supplies",
            "type":"Retail Goods"
        }
    ],
    "sg:phone":"+1 305 931 5942",
    "sg:postcode":"33179",
    "sg:province":"FL",
    "sg:tags":[
        "equipment"
    ],
    "wof:name":"Century Construction of Miami Inc",
    "wof:placetype":"venue"
},
  "geometry": {"coordinates":[-80.158203,25.944799],"type":"Point"}
}