{
  "type": "Feature",
  "properties": {
    "iso:country":"US",
    "sg:address":"1904 Old Bainbridge Rd",
    "sg:city":"Tallahassee",
    "sg:classifiers":[
        {
            "category":"Insurance",
            "subcategory":"Insurance Agent",
            "type":"Services"
        }
    ],
    "sg:phone":"+1 850 222 2886",
    "sg:postcode":"32303",
    "sg:province":"FL",
    "wof:name":"Affordable Insurance",
    "wof:placetype":"venue"
},
  "geometry": {"coordinates":[-84.301158,30.464133],"type":"Point"}
}