{
  "type": "Feature",
  "properties": {
    "addr:full":"1137 Harrison Ave Panama City FL 32401",
    "addr:housenumber":"1137",
    "addr:postcode":"32401",
    "addr:street":"Harrison Ave",
    "iso:country":"US",
    "sg:address":"1137 Harrison Ave",
    "sg:city":"Panama City",
    "sg:classifiers":[
        {
            "category":"Insurance",
            "subcategory":"Insurance Agent",
            "type":"Services"
        }
    ],
    "sg:phone":"+1 850 819 4585",
    "sg:postcode":"32401",
    "sg:province":"FL",
    "wof:name":"TJM Benefits Inc",
    "wof:placetype":"venue"
},
  "geometry": {"coordinates":[-85.66030600000001,30.169024],"type":"Point"}
}