{
  "type": "Feature",
  "properties": {
    "iso:country":"US",
    "sg:address":"2215 NW 36th St",
    "sg:city":"Miami",
    "sg:classifiers":[
        {
            "category":"Banks & Credit Unions",
            "subcategory":"Bank",
            "type":"Services"
        }
    ],
    "sg:phone":"+1 305 638 2010",
    "sg:postcode":"33142",
    "sg:province":"FL",
    "sg:tags":[
        "financing",
        "management",
        "company",
        "real estate"
    ],
    "wof:name":"Consumer Loan Servicing Inc",
    "wof:placetype":"venue"
},
  "geometry": {"coordinates":[-80.23279700000001,25.809394],"type":"Point"}
}