{
  "type": "Feature",
  "properties": {
    "addr:full":"2919 Gulf Shore Blvd N Naples FL 34103",
    "addr:housenumber":"2919",
    "addr:postcode":"34103",
    "addr:street":"Gulf Shore Blvd N",
    "iso:country":"US",
    "sg:address":"2919 Gulf Shore Blvd N",
    "sg:city":"Naples",
    "sg:classifiers":[
        {
            "category":"Personal",
            "subcategory":"Barber",
            "type":"Services"
        }
    ],
    "sg:phone":"+1 239 261 2747",
    "sg:postcode":"34103",
    "sg:province":"FL",
    "wof:name":"Barber Pete",
    "wof:placetype":"venue"
},
  "geometry": {"coordinates":[-81.813941,26.18598],"type":"Point"}
}