{
  "type": "Feature",
  "properties": {
    "iso:country":"US",
    "sg:address":"826 85th St",
    "sg:city":"Miami Beach",
    "sg:classifiers":[
        {
            "category":"Real Estate",
            "subcategory":"Real Estate Operator",
            "type":"Services"
        }
    ],
    "sg:phone":"+1 305 861 4314",
    "sg:postcode":"33141",
    "sg:province":"FL",
    "sg:tags":[
        "building",
        "apartment"
    ],
    "wof:name":"Lolita Apts",
    "wof:placetype":"venue"
},
  "geometry": {"coordinates":[-80.12634300000001,25.869724],"type":"Point"}
}