{
  "type": "Feature",
  "properties": {
    "addr:full":"6229 NW 23rd Rd Boca Raton FL 33434",
    "addr:housenumber":"6229",
    "addr:postcode":"33434",
    "addr:street":"Nw 23Rd Rd",
    "iso:country":"US",
    "sg:address":"6229 NW 23rd Rd",
    "sg:city":"Boca Raton",
    "sg:classifiers":[
        {
            "category":"Health Services",
            "subcategory":"Doctor",
            "type":"Services"
        }
    ],
    "sg:phone":"+1 561 477 0773",
    "sg:postcode":"33434",
    "sg:province":"FL",
    "sg:tags":[
        "medical"
    ],
    "wof:name":"Garrison Sobel Dr",
    "wof:placetype":"venue"
},
  "geometry": {"coordinates":[-80.140388,26.371146],"type":"Point"}
}