{
  "type": "Feature",
  "properties": {
    "addr:full":"234 Altamonte Commerce Blvd Altamonte Spgs FL 32714",
    "addr:housenumber":"234",
    "addr:postcode":"32714",
    "addr:street":"Altamonte Commerce Blvd;Spgs",
    "iso:country":"US",
    "sg:address":"234 Altamonte Commerce Blvd",
    "sg:city":"Altamonte Spgs",
    "sg:classifiers":[
        {
            "category":"Building & Trades",
            "subcategory":"Construction",
            "type":"Services"
        }
    ],
    "sg:phone":"+1 407 339 4001",
    "sg:postcode":"32714",
    "sg:province":"FL",
    "sg:tags":[
        "general",
        "contractor"
    ],
    "sg:website":"www.rarogers.com",
    "wof:name":"R A Rogers Construction",
    "wof:placetype":"venue"
},
  "geometry": {"coordinates":[-81.390913,28.67381],"type":"Point"}
}