{
  "type": "Feature",
  "properties": {
    "addr:full":"1001 Sawgrass Corporate Pkwy Sunrise FL 33323",
    "addr:housenumber":"1001",
    "addr:postcode":"33323",
    "addr:street":"Sawgrass Corporate Pkwy",
    "iso:country":"US",
    "sg:address":"1001 Sawgrass Corporate Pkwy",
    "sg:city":"Sunrise",
    "sg:classifiers":[
        {
            "category":"Wholesale",
            "subcategory":"Sporting Goods",
            "type":"Manufacturing & Wholesale Goods"
        }
    ],
    "sg:phone":"+1 954 377 4925",
    "sg:postcode":"33323",
    "sg:province":"FL",
    "sg:website":"www.valorcorp.com",
    "wof:name":"Valor Corp",
    "wof:placetype":"venue"
},
  "geometry": {"coordinates":[-80.334793,26.135687],"type":"Point"}
}