{
  "type": "Feature",
  "properties": {
    "iso:country":"US",
    "sg:address":"4420 5th St W",
    "sg:city":"Bradenton",
    "sg:classifiers":[
        {
            "category":"Professional",
            "subcategory":"Business Services",
            "type":"Services"
        }
    ],
    "sg:phone":"+1 941 747 9006",
    "sg:postcode":"34207",
    "sg:province":"FL",
    "sg:tags":[
        "holding"
    ],
    "wof:name":"Cjkm Holdings",
    "wof:placetype":"venue"
},
  "geometry": {"coordinates":[-82.567038,27.462129],"type":"Point"}
}