{
  "type": "Feature",
  "properties": {
    "addr:full":"763 Arthur Godfrey Rd Ste A Miami Beach FL 33140",
    "addr:housenumber":"763",
    "addr:postcode":"33140",
    "addr:street":"Arthur Godfrey Rd Ste A",
    "iso:country":"US",
    "sg:address":"763 Arthur Godfrey Rd Ste A",
    "sg:city":"Miami Beach",
    "sg:classifiers":[
        {
            "category":"Real Estate",
            "subcategory":"Real Estate Services",
            "type":"Services"
        }
    ],
    "sg:phone":"+1 305 672 0492",
    "sg:postcode":"33140",
    "sg:province":"FL",
    "sg:tags":[
        "management",
        "property"
    ],
    "wof:name":"Auerbach Associates Inc",
    "wof:placetype":"venue"
},
  "geometry": {"coordinates":[-80.13249999999999,25.8139],"type":"Point"}
}