{
  "type": "Feature",
  "properties": {
    "addr:full":"9128 Picot Ct Boynton Beach FL 33472",
    "addr:housenumber":"9128",
    "addr:postcode":"33472",
    "addr:street":"Picot Ct",
    "iso:country":"US",
    "sg:address":"9128 Picot Ct",
    "sg:city":"Boynton Beach",
    "sg:classifiers":[
        {
            "category":"Banks & Credit Unions",
            "subcategory":"Investment Brokerage",
            "type":"Services"
        }
    ],
    "sg:phone":"+1 561 734 1367",
    "sg:postcode":"33472",
    "sg:province":"FL",
    "sg:tags":[
        "advisory"
    ],
    "wof:name":"Gateway Financial Service",
    "wof:placetype":"venue"
},
  "geometry": {"coordinates":[-80.13288,26.541953],"type":"Point"}
}