{
  "type": "Feature",
  "properties": {
    "addr:full":"583 Pondella Rd Fort Myers FL 33903",
    "addr:housenumber":"583",
    "addr:postcode":"33903",
    "addr:street":"Pondella Rd",
    "iso:country":"US",
    "sg:address":"583 Pondella Rd",
    "sg:city":"Fort Myers",
    "sg:classifiers":[
        {
            "category":"Shopping",
            "subcategory":"Musical Instruments",
            "type":"Retail Goods"
        }
    ],
    "sg:phone":"+1 239 997 3006",
    "sg:postcode":"33903",
    "sg:province":"FL",
    "wof:name":"House of Drums",
    "wof:placetype":"venue"
},
  "geometry": {"coordinates":[-81.90212699999999,26.667276],"type":"Point"}
}