{
  "type": "Feature",
  "properties": {
    "iso:country":"US",
    "sg:address":"2424 Oakes Blvd",
    "sg:city":"Naples",
    "sg:classifiers":[
        {
            "category":"Real Estate",
            "subcategory":"Real Estate Operator",
            "type":"Services"
        }
    ],
    "sg:phone":"+1 239 514 3703",
    "sg:postcode":"34119",
    "sg:province":"FL",
    "sg:tags":[
        "condominium"
    ],
    "wof:name":"Huntington Lakes Gate House",
    "wof:placetype":"venue"
},
  "geometry": {"coordinates":[-81.734904,26.271677],"type":"Point"}
}