{
  "type": "Feature",
  "properties": {
    "addr:full":"2 N Semoran Blvd Orlando FL 32807",
    "addr:housenumber":"2",
    "addr:postcode":"32807",
    "addr:street":"N Semoran Blvd",
    "iso:country":"US",
    "sg:address":"2 N Semoran Blvd",
    "sg:city":"Orlando",
    "sg:classifiers":[
        {
            "category":"Banks & Credit Unions",
            "subcategory":"Bank",
            "type":"Services"
        }
    ],
    "sg:phone":"+1 407 273 4500",
    "sg:postcode":"32807",
    "sg:province":"FL",
    "sg:tags":[
        "banker",
        "mortgage"
    ],
    "wof:name":"Preferred International",
    "wof:placetype":"venue"
},
  "geometry": {"coordinates":[-81.31066199999999,28.546298],"type":"Point"}
}