{
  "type": "Feature",
  "properties": {
    "iso:country":"US",
    "sg:address":"5550 26th St W",
    "sg:city":"Bradenton",
    "sg:classifiers":[
        {
            "category":"Professional",
            "subcategory":"Accounting & Tax Preparation",
            "type":"Services"
        }
    ],
    "sg:phone":"+1 941 752 7074",
    "sg:postcode":"34207",
    "sg:province":"FL",
    "wof:name":"Shook Yvonne E",
    "wof:placetype":"venue"
},
  "geometry": {"coordinates":[-82.587722,27.443324],"type":"Point"}
}