{
  "type": "Feature",
  "properties": {
    "addr:full":"400 Mandalay Ave Clearwater FL 33767",
    "addr:housenumber":"400",
    "addr:postcode":"33767",
    "addr:street":"Mandalay Ave",
    "iso:country":"US",
    "sg:address":"400 Mandalay Ave",
    "sg:city":"Clearwater",
    "sg:classifiers":[
        {
            "category":"Travel",
            "subcategory":"Hotels & Motels",
            "type":"Entertainment"
        }
    ],
    "sg:phone":"+1 727 461 3222",
    "sg:postcode":"33767",
    "sg:province":"FL",
    "sg:tags":[
        "operation",
        "eating",
        "drinking"
    ],
    "wof:name":"Hilton Clearwater Beach Resort",
    "wof:placetype":"venue"
},
  "geometry": {"coordinates":[-82.827449,27.978875],"type":"Point"}
}