{
  "type": "Feature",
  "properties": {
    "iso:country":"US",
    "sg:address":"45 Ocean Ct",
    "sg:city":"St Augustine",
    "sg:classifiers":[
        {
            "category":"Building & Trades",
            "subcategory":"Cleaning & Sanitation",
            "type":"Services"
        }
    ],
    "sg:phone":"+1 904 471 9520",
    "sg:postcode":"32080",
    "sg:province":"FL",
    "sg:tags":[
        "janitor"
    ],
    "wof:name":"Bobbie Coleman Cleaning",
    "wof:placetype":"venue"
},
  "geometry": {"coordinates":[-81.275544,29.847929],"type":"Point"}
}