{
  "type": "Feature",
  "properties": {
    "iso:country":"US",
    "sg:address":"201 S Elm Ave",
    "sg:city":"Sanford",
    "sg:classifiers":[
        {
            "category":"Place Of Worship",
            "subcategory":"Church",
            "type":"Public Place"
        },
        {
            "category":"Place Of Worship",
            "type":"Public Place"
        },
        {
            "category":"Organizations",
            "subcategory":"Religious Organization",
            "type":"Services"
        }
    ],
    "sg:phone":"+1 407 321 8389",
    "sg:postcode":"32771",
    "sg:province":"FL",
    "sg:tags":[
        "god",
        "churches-church",
        "churches-pentecostal"
    ],
    "wof:name":"Shower Down Blessings Church",
    "wof:placetype":"venue"
},
  "geometry": {"coordinates":[-81.271118,28.810801],"type":"Point"}
}