{
  "type": "Feature",
  "properties": {
    "addr:full":"2717 NW 62nd St Fort Lauderdale FL 33309",
    "addr:housenumber":"2717",
    "addr:postcode":"33309",
    "addr:street":"Nw 62Nd St",
    "iso:country":"US",
    "sg:address":"2717 NW 62nd St",
    "sg:city":"Fort Lauderdale",
    "sg:classifiers":[
        {
            "category":"Organizations",
            "subcategory":"Professional Association",
            "type":"Services"
        }
    ],
    "sg:phone":"+1 954 972 9256",
    "sg:postcode":"33309",
    "sg:province":"FL",
    "sg:tags":[
        "chambers",
        "commerce"
    ],
    "wof:name":"American Chamber Of Christians",
    "wof:placetype":"venue"
},
  "geometry": {"coordinates":[-80.18322499999999,26.202645],"type":"Point"}
}