{
  "type": "Feature",
  "properties": {
    "iso:country":"US",
    "sg:address":"14804 Windy Mount Cir",
    "sg:city":"Clermont",
    "sg:classifiers":[
        {
            "category":"Professional",
            "type":"Services"
        }
    ],
    "sg:phone":"+1 352 243 4950",
    "sg:postcode":"34711",
    "sg:province":"FL",
    "wof:name":"Praco Services Inc",
    "wof:placetype":"venue"
},
  "geometry": {"coordinates":[-81.707948,28.52219],"type":"Point"}
}