{
  "type": "Feature",
  "properties": {
    "iso:country":"US",
    "sg:address":"960 S Orlando Ave",
    "sg:city":"Winter Park",
    "sg:classifiers":[
        {
            "category":"Banks & Credit Unions",
            "subcategory":"Bank",
            "type":"Services"
        }
    ],
    "sg:phone":"+1 407 644 2777",
    "sg:postcode":"32789",
    "sg:province":"FL",
    "sg:tags":[
        "loan",
        "real estate"
    ],
    "wof:name":"Security First Title Partners",
    "wof:placetype":"venue"
},
  "geometry": {"coordinates":[-81.365066,28.589101],"type":"Point"}
}