{
  "type": "Feature",
  "properties": {
    "iso:country":"US",
    "sg:address":"2499 Enterprise Rd Ste D",
    "sg:city":"Orange City",
    "sg:classifiers":[
        {
            "category":"Health Services",
            "subcategory":"Dentist",
            "type":"Services"
        }
    ],
    "sg:phone":"+1 386 775 9575",
    "sg:postcode":"32763",
    "sg:province":"FL",
    "wof:name":"Four Towns Dental Services Inc",
    "wof:placetype":"venue"
},
  "geometry": {"coordinates":[-81.2966,28.9196],"type":"Point"}
}