{
  "type": "Feature",
  "properties": {
    "iso:country":"US",
    "sg:address":"16047 Marsh Quail Rd",
    "sg:city":"Weeki Wachee",
    "sg:classifiers":[
        {
            "category":"Building & Trades",
            "subcategory":"Landscaping Services",
            "type":"Services"
        }
    ],
    "sg:phone":"+1 352 263 8818",
    "sg:postcode":"34614",
    "sg:province":"FL",
    "sg:tags":[
        "lawn",
        "maintenance",
        "grounds"
    ],
    "wof:name":"Jarrad Day's Property Maintena",
    "wof:placetype":"venue"
},
  "geometry": {"coordinates":[-82.53943200000001,28.653028],"type":"Point"}
}