{
  "type": "Feature",
  "properties": {
    "iso:country":"US",
    "sg:address":"301 A Philip Randolph Blvd",
    "sg:city":"Jacksonville",
    "sg:classifiers":[
        {
            "category":"Shopping",
            "subcategory":"Bicycles & Sporting Goods",
            "type":"Retail Goods"
        }
    ],
    "sg:phone":"+1 904 355 9919",
    "sg:postcode":"32202",
    "sg:province":"FL",
    "wof:name":"Jacksonville Baseball Club",
    "wof:placetype":"venue"
},
  "geometry": {"coordinates":[-81.64361100000001,30.326047],"type":"Point"}
}