{
  "type": "Feature",
  "properties": {
    "addr:full":"16461 SW 75th St Miami FL 33193",
    "addr:housenumber":"16461",
    "addr:postcode":"33193",
    "addr:street":"Sw 75Th St",
    "iso:country":"US",
    "sg:address":"16461 SW 75th St",
    "sg:city":"Miami",
    "sg:classifiers":[
        {
            "category":"Manufacturing",
            "subcategory":"Tools & Machinery",
            "type":"Manufacturing & Wholesale Goods"
        }
    ],
    "sg:phone":"+1 305 608 0897",
    "sg:postcode":"33193",
    "sg:province":"FL",
    "sg:tags":[
        "cutting",
        "gear"
    ],
    "wof:name":"707 Tactical Gear Inc",
    "wof:placetype":"venue"
},
  "geometry": {"coordinates":[-80.46071600000001,25.695998],"type":"Point"}
}