{
  "type": "Feature",
  "properties": {
    "iso:country":"US",
    "sg:address":"151 S New York Ave",
    "sg:city":"Winter Park",
    "sg:classifiers":[
        {
            "category":"Retail",
            "subcategory":"Auto Repair",
            "type":"Services"
        }
    ],
    "sg:phone":"+1 407 647 7015",
    "sg:postcode":"32789",
    "sg:province":"FL",
    "sg:tags":[
        "automobile",
        "electric"
    ],
    "wof:name":"Carl's Auto Electric",
    "wof:placetype":"venue"
},
  "geometry": {"coordinates":[-81.35278599999999,28.596763],"type":"Point"}
}