{
  "type": "Feature",
  "properties": {
    "iso:country":"US",
    "sg:address":"268 Water's Edge Dr S",
    "sg:city":"Ponte Vedra Beach",
    "sg:classifiers":[
        {
            "category":"Restaurant",
            "type":"Food & Drink"
        }
    ],
    "sg:phone":"+1 904 280 0302",
    "sg:postcode":"32082",
    "sg:province":"FL",
    "sg:tags":[
        "eating"
    ],
    "wof:name":"Moes Sothwestern Grill Moes",
    "wof:placetype":"venue"
},
  "geometry": {"coordinates":[-81.402317,30.208089],"type":"Point"}
}