{
  "type": "Feature",
  "properties": {
    "iso:country":"US",
    "sg:address":"100 SE 27th Ave",
    "sg:city":"Boynton Beach",
    "sg:classifiers":[
        {
            "category":"Social Services",
            "subcategory":"Child Care",
            "type":"Services"
        }
    ],
    "sg:phone":"+1 561 586 2766",
    "sg:postcode":"33435",
    "sg:province":"FL",
    "wof:name":"Abagail Denson Child Care",
    "wof:placetype":"venue"
},
  "geometry": {"coordinates":[-80.065331,26.503615],"type":"Point"}
}