{
  "type": "Feature",
  "properties": {
    "iso:country":"US",
    "sg:address":"14118 US Hwy 41",
    "sg:city":"Spring Hill",
    "sg:classifiers":[
        {
            "category":"Wholesale",
            "subcategory":"Construction Materials",
            "type":"Manufacturing & Wholesale Goods"
        }
    ],
    "sg:phone":"+1 813 929 9522",
    "sg:postcode":"34610",
    "sg:province":"FL",
    "wof:name":"Cook Sheds",
    "wof:placetype":"venue"
},
  "geometry": {"coordinates":[-82.494877,28.370301],"type":"Point"}
}