{
  "type": "Feature",
  "properties": {
    "addr:full":"7605 Santa Barbara Dr Fort Pierce FL 34951",
    "addr:housenumber":"7605",
    "addr:postcode":"34951",
    "addr:street":"Santa Barbara Dr",
    "iso:country":"US",
    "sg:address":"7605 Santa Barbara Dr",
    "sg:city":"Fort Pierce",
    "sg:classifiers":[
        {
            "category":"Education",
            "subcategory":"Library",
            "type":"Public Place"
        }
    ],
    "sg:phone":"+1 772 462 6870",
    "sg:postcode":"34951",
    "sg:province":"FL",
    "sg:website":"www.st-lucie.lib.fl.us",
    "wof:name":"Lakewood Park Branch Library",
    "wof:placetype":"venue"
},
  "geometry": {"coordinates":[-80.401718,27.523615],"type":"Point"}
}