{
  "type": "Feature",
  "properties": {
    "addr:full":"15836 Savona Way Naples FL 34110",
    "addr:postcode":"15836;34110",
    "addr:street":"Savona Way",
    "iso:country":"US",
    "sg:address":"15836 Savona Way",
    "sg:city":"Naples",
    "sg:classifiers":[
        {
            "category":"Real Estate",
            "subcategory":"Real Estate Agent",
            "type":"Services"
        }
    ],
    "sg:phone":"+1 239 596 6668",
    "sg:postcode":"34110",
    "sg:province":"FL",
    "wof:name":"Bonita Bay Group Inc",
    "wof:placetype":"venue"
},
  "geometry": {"coordinates":[-81.76806999999999,26.311978],"type":"Point"}
}