{
  "type": "Feature",
  "properties": {
    "iso:country":"US",
    "sg:address":"1021 Atlantic Blvd",
    "sg:city":"Atlantic Beach",
    "sg:classifiers":[
        {
            "category":"Restaurant",
            "type":"Food & Drink"
        }
    ],
    "sg:menulink":"http://www.allmenus.com/fl/jacksonville/198124-ristorantes-sequinos-/menu/",
    "sg:phone":"+1 904 249 0101",
    "sg:postcode":"32233",
    "sg:province":"FL",
    "sg:tags":[
        "italian"
    ],
    "wof:name":"Ristorantes Sequinos ",
    "wof:placetype":"venue"
},
  "geometry": {"coordinates":[-81.41276000000001,30.324534],"type":"Point"}
}