{
  "type": "Feature",
  "properties": {
    "iso:country":"US",
    "sg:address":"7925 NW 12th St",
    "sg:city":"Doral",
    "sg:classifiers":[
        {
            "category":"Health Services",
            "subcategory":"Doctor",
            "type":"Services"
        },
        {
            "category":"Health Services",
            "subcategory":"Clinic",
            "type":"Services"
        }
    ],
    "sg:phone":"+1 305 442 8800",
    "sg:postcode":"33126",
    "sg:province":"FL",
    "sg:tags":[
        "psychological",
        "psychologist"
    ],
    "wof:name":"Law Enforcement Psychological & Counseling Associates",
    "wof:placetype":"venue"
},
  "geometry": {"coordinates":[-80.32525800000001,25.782683],"type":"Point"}
}