{
  "type": "Feature",
  "properties": {
    "addr:full":"1255 Belle Ave Unit 120 Winter Springs FL 32708",
    "addr:housenumber":"1255;120",
    "addr:postcode":"32708",
    "addr:street":"Belle Ave Unit",
    "iso:country":"US",
    "sg:address":"1255 Belle Ave Unit 120",
    "sg:city":"Winter Springs",
    "sg:classifiers":[
        {
            "category":"Shopping",
            "subcategory":"Antiques",
            "type":"Retail Goods"
        }
    ],
    "sg:phone":"+1 407 695 0007",
    "sg:postcode":"32708",
    "sg:province":"FL",
    "sg:website":"www.antiquefurniturerestorations...",
    "wof:name":"Antique Furniture Restoration Studio",
    "wof:placetype":"venue"
},
  "geometry": {"coordinates":[-81.315307,28.697312],"type":"Point"}
}