{
  "type": "Feature",
  "properties": {
    "iso:country":"US",
    "sg:address":"639 W 14th St",
    "sg:city":"Apopka",
    "sg:classifiers":[
        {
            "category":"Building & Trades",
            "subcategory":"Cleaning & Sanitation",
            "type":"Services"
        }
    ],
    "sg:phone":"+1 407 814 0509",
    "sg:postcode":"32703",
    "sg:province":"FL",
    "sg:tags":[
        "maintenance"
    ],
    "wof:name":"Top Notch Cleaning Serv Inc",
    "wof:placetype":"venue"
},
  "geometry": {"coordinates":[-81.518878,28.661138],"type":"Point"}
}