{
  "type": "Feature",
  "properties": {
    "iso:country":"US",
    "sg:address":"4409 Metzger Rd",
    "sg:city":"Fort Pierce",
    "sg:classifiers":[
        {
            "category":"Building & Trades",
            "subcategory":"Construction",
            "type":"Services"
        }
    ],
    "sg:phone":"+1 772 489 6699",
    "sg:postcode":"34947",
    "sg:province":"FL",
    "sg:tags":[
        "demolition",
        "contractor"
    ],
    "wof:name":"LEB Demolition & Consulting",
    "wof:placetype":"venue"
},
  "geometry": {"coordinates":[-80.37085999999999,27.454785],"type":"Point"}
}