{
  "type": "Feature",
  "properties": {
    "addr:full":"5301 Blue Lagoon Dr Miami FL 33126",
    "addr:housenumber":"5301",
    "addr:postcode":"33126",
    "addr:street":"Blue Lagoon Dr",
    "iso:country":"US",
    "sg:address":"5301 Blue Lagoon Dr",
    "sg:city":"Miami",
    "sg:classifiers":[
        {
            "category":"Insurance",
            "subcategory":"Hazard Insurance",
            "type":"Services"
        }
    ],
    "sg:phone":"+1 305 262 7001",
    "sg:postcode":"33126",
    "sg:province":"FL",
    "sg:tags":[
        "commercial",
        "business"
    ],
    "wof:name":"Horan Goldman Of Florida Ins",
    "wof:placetype":"venue"
},
  "geometry": {"coordinates":[-80.28327,25.781893],"type":"Point"}
}