{
  "type": "Feature",
  "properties": {
    "addr:full":"260 95th St Ste 206 Surfside FL 33154",
    "addr:housenumber":"260",
    "addr:postcode":"33154",
    "addr:street":"95Th St Ste 206",
    "iso:country":"US",
    "sg:address":"260 95th St Ste 206",
    "sg:city":"Surfside",
    "sg:classifiers":[
        {
            "category":"Health Services",
            "subcategory":"Health Practitioner",
            "type":"Services"
        }
    ],
    "sg:phone":"+1 305 861 0078",
    "sg:postcode":"33154",
    "sg:province":"FL",
    "sg:tags":[
        "acupuncture"
    ],
    "wof:name":"Surfside Pain Control Center Inc",
    "wof:placetype":"venue"
},
  "geometry": {"coordinates":[-80.12309999999999,25.885201],"type":"Point"}
}