{
  "type": "Feature",
  "properties": {
    "addr:full":"2621 Cameron Ave Sanford FL 32773",
    "addr:housenumber":"2621",
    "addr:postcode":"32773",
    "addr:street":"Cameron Ave",
    "iso:country":"US",
    "sg:address":"2621 Cameron Ave",
    "sg:city":"Sanford",
    "sg:classifiers":[
        {
            "category":"Shopping",
            "subcategory":"Clothing, Apparel, & Fashions",
            "type":"Retail Goods"
        }
    ],
    "sg:phone":"+1 407 688 0080",
    "sg:postcode":"32773",
    "sg:province":"FL",
    "sg:tags":[
        "item",
        "boutique"
    ],
    "wof:name":"Jackie's Boutique",
    "wof:placetype":"venue"
},
  "geometry": {"coordinates":[-81.21430599999999,28.783667],"type":"Point"}
}