{
  "type": "Feature",
  "properties": {
    "iso:country":"US",
    "sg:address":"189 Azalea Point Dr S",
    "sg:city":"Ponte Vedra Beach",
    "sg:classifiers":[
        {
            "category":"Organizations",
            "subcategory":"Membership Organization",
            "type":"Services"
        }
    ],
    "sg:phone":"+1 904 285 8937",
    "sg:postcode":"32082",
    "sg:province":"FL",
    "wof:name":"Explorer Baseball Association",
    "wof:placetype":"venue"
},
  "geometry": {"coordinates":[-81.380391,30.176229],"type":"Point"}
}