{
  "type": "Feature",
  "properties": {
    "addr:full":"502 E Olympia Ave Punta Gorda FL 33950",
    "addr:housenumber":"502",
    "addr:postcode":"33950",
    "addr:street":"E Olympia Ave",
    "iso:country":"US",
    "sg:address":"502 E Olympia Ave",
    "sg:city":"Punta Gorda",
    "sg:classifiers":[
        {
            "category":"Health Services",
            "subcategory":"Doctor",
            "type":"Services"
        }
    ],
    "sg:phone":"+1 941 575 2358",
    "sg:postcode":"33950",
    "sg:province":"FL",
    "sg:tags":[
        "physician",
        "surgeon"
    ],
    "wof:name":"Southwest Florida Assoc",
    "wof:placetype":"venue"
},
  "geometry": {"coordinates":[-82.04256100000001,26.938785],"type":"Point"}
}