{
  "type": "Feature",
  "properties": {
    "iso:country":"US",
    "sg:address":"5506 S Lake Ave",
    "sg:city":"West Palm Beach",
    "sg:classifiers":[
        {
            "category":"Social Services",
            "type":"Services"
        }
    ],
    "sg:phone":"+1 561 582 2229",
    "sg:postcode":"33405",
    "sg:province":"FL",
    "sg:tags":[
        "organization",
        "welfare"
    ],
    "wof:name":"El Milagro Alcoholic Annyms",
    "wof:placetype":"venue"
},
  "geometry": {"coordinates":[-80.061589,26.66406],"type":"Point"}
}