{
  "type": "Feature",
  "properties": {
    "addr:full":"100 Madeira Ave Coral Gables FL 33134",
    "addr:housenumber":"100",
    "addr:postcode":"33134",
    "addr:street":"Madeira Ave",
    "iso:country":"US",
    "sg:address":"100 Madeira Ave",
    "sg:city":"Coral Gables",
    "sg:classifiers":[
        {
            "category":"Real Estate",
            "subcategory":"Architect",
            "type":"Services"
        }
    ],
    "sg:phone":"+1 305 442 8410",
    "sg:postcode":"33134",
    "sg:province":"FL",
    "sg:tags":[
        "architectural"
    ],
    "wof:name":"Buckler Architects",
    "wof:placetype":"venue"
},
  "geometry": {"coordinates":[-80.258865,25.755914],"type":"Point"}
}