{
  "type": "Feature",
  "properties": {
    "addr:full":"100 Old Town Hammock Ln Crawfordville FL 32327",
    "addr:housenumber":"100",
    "addr:postcode":"32327",
    "addr:street":"Old;Hammock Ln",
    "iso:country":"US",
    "sg:address":"100 Old Town Hammock Ln",
    "sg:city":"Crawfordville",
    "sg:classifiers":[
        {
            "category":"Manufacturing",
            "subcategory":"Buildings",
            "type":"Manufacturing & Wholesale Goods"
        },
        {
            "category":"Building & Trades",
            "subcategory":"Construction",
            "type":"Services"
        }
    ],
    "sg:phone":"+1 850 926 9038",
    "sg:postcode":"32327",
    "sg:province":"FL",
    "sg:tags":[
        "home",
        "builder",
        "contractor"
    ],
    "wof:name":"Tc's Home Improvement Solutions",
    "wof:placetype":"venue"
},
  "geometry": {"coordinates":[-84.33950299999999,30.145572],"type":"Point"}
}