{
  "type": "Feature",
  "properties": {
    "iso:country":"US",
    "sg:address":"2528 Monterey Ct",
    "sg:city":"Fort Lauderdale",
    "sg:classifiers":[
        {
            "category":"Shopping",
            "subcategory":"Jewelry",
            "type":"Retail Goods"
        }
    ],
    "sg:phone":"+1 954 722 6899",
    "sg:postcode":"33327",
    "sg:province":"FL",
    "wof:name":"SAI Jewelers Inc",
    "wof:placetype":"venue"
},
  "geometry": {"coordinates":[-80.404106,26.095539],"type":"Point"}
}