{
  "type": "Feature",
  "properties": {
    "iso:country":"US",
    "sg:address":"3421 SE 2nd Pl",
    "sg:city":"Cape Coral",
    "sg:classifiers":[
        {
            "category":"Retail",
            "subcategory":"Repair Shop",
            "type":"Services"
        }
    ],
    "sg:phone":"+1 239 549 2302",
    "sg:postcode":"33904",
    "sg:province":"FL",
    "sg:tags":[
        "appliance"
    ],
    "wof:name":"Appliance Craft",
    "wof:placetype":"venue"
},
  "geometry": {"coordinates":[-81.96799799999999,26.587763],"type":"Point"}
}