{
  "type": "Feature",
  "properties": {
    "addr:full":"600 NE 33rd St Pompano Beach FL 33064",
    "addr:housenumber":"600",
    "addr:postcode":"33064",
    "addr:street":"Ne 33Rd St",
    "iso:country":"US",
    "sg:address":"600 NE 33rd St",
    "sg:city":"Pompano Beach",
    "sg:classifiers":[
        {
            "category":"Building & Trades",
            "subcategory":"Construction",
            "type":"Services"
        }
    ],
    "sg:phone":"+1 954 786 9060",
    "sg:postcode":"33064",
    "sg:province":"FL",
    "sg:tags":[
        "paving",
        "contractor"
    ],
    "wof:name":"America Pavers Contractors Inc",
    "wof:placetype":"venue"
},
  "geometry": {"coordinates":[-80.11382999999999,26.271618],"type":"Point"}
}