{
  "type": "Feature",
  "properties": {
    "addr:full":"30021 SW 147th Ave Homestead FL 33033",
    "addr:housenumber":"30021",
    "addr:postcode":"33033",
    "addr:street":"Sw 147Th Ave",
    "iso:country":"US",
    "sg:address":"30021 SW 147th Ave",
    "sg:city":"Homestead",
    "sg:classifiers":[
        {
            "category":"Building & Trades",
            "subcategory":"Construction",
            "type":"Services"
        }
    ],
    "sg:phone":"+1 786 325 7283",
    "sg:postcode":"33033",
    "sg:province":"FL",
    "sg:tags":[
        "residential"
    ],
    "wof:name":"Rudy O Iraeta",
    "wof:placetype":"venue"
},
  "geometry": {"coordinates":[-80.42847500000001,25.48776],"type":"Point"}
}