{
  "type": "Feature",
  "properties": {
    "addr:full":"8001 S Orange Blossom Trl Orlando FL 32809",
    "addr:housenumber":"8001",
    "addr:postcode":"32809",
    "addr:street":"S Orange Blossom Trl",
    "iso:country":"US",
    "sg:address":"8001 S Orange Blossom Trl",
    "sg:city":"Orlando",
    "sg:classifiers":[
        {
            "category":"Shopping",
            "subcategory":"Clothing, Apparel, & Fashions",
            "type":"Retail Goods"
        }
    ],
    "sg:phone":"+1 407 856 0034",
    "sg:postcode":"32809",
    "sg:province":"FL",
    "wof:name":"Cache",
    "wof:placetype":"venue"
},
  "geometry": {"coordinates":[-81.401563,28.447588],"type":"Point"}
}