{
  "type": "Feature",
  "properties": {
    "iso:country":"US",
    "sg:address":"1086 Cavern Dr",
    "sg:city":"Apopka",
    "sg:classifiers":[
        {
            "category":"Professional",
            "subcategory":"Management & Consulting",
            "type":"Services"
        }
    ],
    "sg:phone":"+1 407 886 5663",
    "sg:postcode":"32712",
    "sg:province":"FL",
    "sg:tags":[
        "consultant",
        "resource",
        "human"
    ],
    "wof:name":"H R Department Inc",
    "wof:placetype":"venue"
},
  "geometry": {"coordinates":[-81.49581499999999,28.712026],"type":"Point"}
}