{
  "type": "Feature",
  "properties": {
    "addr:full":"9880 Belgrade Rd Miami FL 33157",
    "addr:housenumber":"9880",
    "addr:postcode":"33157",
    "addr:street":"Belgrade Rd",
    "iso:country":"US",
    "sg:address":"9880 Belgrade Rd",
    "sg:city":"Miami",
    "sg:classifiers":[
        {
            "category":"Building & Trades",
            "subcategory":"Construction",
            "type":"Services"
        }
    ],
    "sg:phone":"+1 305 252 2567",
    "sg:postcode":"33157",
    "sg:province":"FL",
    "sg:tags":[
        "contractor"
    ],
    "wof:name":"Miami Sundown Corp",
    "wof:placetype":"venue"
},
  "geometry": {"coordinates":[-80.351719,25.592865],"type":"Point"}
}