{
  "type": "Feature",
  "properties": {
    "addr:full":"316 N. Park Ave. Winter Park FL 32789",
    "addr:housenumber":"316",
    "addr:postcode":"32789",
    "addr:street":"N. Park Ave.",
    "iso:country":"US",
    "sg:address":"316 N. Park Ave.",
    "sg:city":"Winter Park",
    "sg:classifiers":[
        {
            "category":"Home & Garden",
            "subcategory":"Home Furnishings",
            "type":"Retail Goods"
        }
    ],
    "sg:phone":"+1 407 644 0211",
    "sg:postcode":"32789",
    "sg:province":"FL",
    "sg:tags":[
        "decor"
    ],
    "sg:website":"www.villafiorenza.com",
    "wof:name":"The Villa Fiorenza",
    "wof:placetype":"venue"
},
  "geometry": {"coordinates":[-81.35105299999999,28.59979],"type":"Point"}
}