{
  "type": "Feature",
  "properties": {
    "iso:country":"US",
    "sg:address":"3414 Chelsea St",
    "sg:city":"Orlando",
    "sg:classifiers":[
        {
            "category":"Professional",
            "subcategory":"Computer Services",
            "type":"Services"
        }
    ],
    "sg:phone":"+1 407 894 0008",
    "sg:postcode":"32803",
    "sg:province":"FL",
    "sg:tags":[
        "publisher",
        "software",
        "developer"
    ],
    "wof:name":"Tony Hayden Productions",
    "wof:placetype":"venue"
},
  "geometry": {"coordinates":[-81.34195699999999,28.562884],"type":"Point"}
}