{
  "type": "Feature",
  "properties": {
    "iso:country":"US",
    "sg:address":"1241 Semoran Blvd",
    "sg:city":"Casselberry",
    "sg:classifiers":[
        {
            "category":"Government",
            "subcategory":"Office",
            "type":"Public Place"
        }
    ],
    "sg:phone":"+1 407 679 4499",
    "sg:postcode":"32707",
    "sg:province":"FL",
    "sg:tags":[
        "policy"
    ],
    "wof:name":"Orlando District Office",
    "wof:placetype":"venue"
},
  "geometry": {"coordinates":[-81.322534,28.639473],"type":"Point"}
}