{
  "type": "Feature",
  "properties": {
    "iso:country":"US",
    "sg:address":"34 Don Blizzard Rd",
    "sg:city":"Freeport",
    "sg:classifiers":[
        {
            "category":"Shopping",
            "subcategory":"Computers & Home Electronics",
            "type":"Retail Goods"
        }
    ],
    "sg:phone":"+1 850 835 4447",
    "sg:postcode":"32439",
    "sg:province":"FL",
    "sg:tags":[
        "equipment",
        "electronic",
        "supply"
    ],
    "wof:name":"Tandex",
    "wof:placetype":"venue"
},
  "geometry": {"coordinates":[-86.208708,30.494273],"type":"Point"}
}