{
  "type": "Feature",
  "properties": {
    "addr:full":"398 Sarah Rd SW Palm Bay FL 32908",
    "addr:housenumber":"398",
    "addr:postcode":"32908",
    "addr:street":"Sarah Rd Sw",
    "iso:country":"US",
    "sg:address":"398 Sarah Rd SW",
    "sg:city":"Palm Bay",
    "sg:classifiers":[
        {
            "category":"Building & Trades",
            "subcategory":"Construction",
            "type":"Services"
        }
    ],
    "sg:phone":"+1 321 768 0880",
    "sg:postcode":"32908",
    "sg:province":"FL",
    "sg:tags":[
        "home",
        "improvement"
    ],
    "wof:name":"Clifford Cartwright Home Rpr",
    "wof:placetype":"venue"
},
  "geometry": {"coordinates":[-80.696984,27.993191],"type":"Point"}
}