{
  "type": "Feature",
  "properties": {
    "addr:full":"1198 Arkansas Ave SE Palm Bay FL 32909",
    "addr:housenumber":"1198",
    "addr:postcode":"32909",
    "addr:street":"Arkansas Ave Se",
    "iso:country":"US",
    "sg:address":"1198 Arkansas Ave SE",
    "sg:city":"Palm Bay",
    "sg:classifiers":[
        {
            "category":"Building & Trades",
            "subcategory":"Construction",
            "type":"Services"
        }
    ],
    "sg:phone":"+1 321 952 7460",
    "sg:postcode":"32909",
    "sg:province":"FL",
    "sg:tags":[
        "concrete",
        "contractor"
    ],
    "wof:name":"Decorative Con Resurfacing",
    "wof:placetype":"venue"
},
  "geometry": {"coordinates":[-80.64440399999999,27.97305],"type":"Point"}
}