{
  "type": "Feature",
  "properties": {
    "iso:country":"US",
    "sg:address":"6832 NW 77th Ct",
    "sg:city":"Miami",
    "sg:classifiers":[
        {
            "category":"Professional",
            "subcategory":"Management & Consulting",
            "type":"Services"
        }
    ],
    "sg:phone":"+1 305 994 9203",
    "sg:postcode":"33166",
    "sg:province":"FL",
    "sg:tags":[
        "logistics"
    ],
    "wof:name":"Caribean Logistics Inc",
    "wof:placetype":"venue"
},
  "geometry": {"coordinates":[-80.322391,25.835651],"type":"Point"}
}