{
  "type": "Feature",
  "properties": {
    "addr:full":"4250 S Florida Ave Lakeland FL 33813",
    "addr:housenumber":"4250",
    "addr:postcode":"33813",
    "addr:street":"S Florida Ave",
    "iso:country":"US",
    "sg:address":"4250 S Florida Ave",
    "sg:city":"Lakeland",
    "sg:classifiers":[
        {
            "category":"Professional",
            "subcategory":"Accounting & Tax Preparation",
            "type":"Services"
        }
    ],
    "sg:phone":"+1 863 648 2300",
    "sg:postcode":"33813",
    "sg:province":"FL",
    "sg:tags":[
        "accountant"
    ],
    "wof:name":"Bryant & Co",
    "wof:placetype":"venue"
},
  "geometry": {"coordinates":[-81.95684300000001,27.986608],"type":"Point"}
}