{
  "type": "Feature",
  "properties": {
    "addr:full":"630 SW 113th Ter Hollywood FL 33025",
    "addr:housenumber":"630",
    "addr:postcode":"33025",
    "addr:street":"Sw 113Th Ter",
    "iso:country":"US",
    "sg:address":"630 SW 113th Ter",
    "sg:city":"Hollywood",
    "sg:classifiers":[
        {
            "category":"Freight",
            "type":"Transportation"
        }
    ],
    "sg:phone":"+1 954 432 8941",
    "sg:postcode":"33025",
    "sg:province":"FL",
    "sg:tags":[
        "operator",
        "local",
        "trucking"
    ],
    "wof:name":"Eccles Transport Inc",
    "wof:placetype":"venue"
},
  "geometry": {"coordinates":[-80.297135,26.002891],"type":"Point"}
}