{
  "type": "Feature",
  "properties": {
    "addr:full":"201 Alhambra Cir Miami FL 33134",
    "addr:housenumber":"201",
    "addr:postcode":"33134",
    "addr:street":"Alhambra Cir",
    "iso:country":"US",
    "sg:address":"201 Alhambra Cir",
    "sg:city":"Miami",
    "sg:classifiers":[
        {
            "category":"Professional",
            "type":"Services"
        }
    ],
    "sg:phone":"+1 305 263 7280",
    "sg:postcode":"33134",
    "sg:province":"FL",
    "wof:name":"Oro Arte USA Inc",
    "wof:placetype":"venue"
},
  "geometry": {"coordinates":[-80.26077600000001,25.751977],"type":"Point"}
}