{
  "type": "Feature",
  "properties": {
    "iso:country":"US",
    "sg:address":"228 87th Ave NE",
    "sg:city":"St Petersburg",
    "sg:classifiers":[
        {
            "category":"Professional",
            "subcategory":"Advertising",
            "type":"Services"
        }
    ],
    "sg:phone":"+1 727 578 2017",
    "sg:postcode":"33702",
    "sg:province":"FL",
    "sg:tags":[
        "mail"
    ],
    "wof:name":"Mailings & Miscellaneous",
    "wof:placetype":"venue"
},
  "geometry": {"coordinates":[-82.63136,27.850651],"type":"Point"}
}