{
  "type": "Feature",
  "properties": {
    "iso:country":"US",
    "sg:address":"20533 Old Cutler Rd",
    "sg:city":"Miami",
    "sg:classifiers":[
        {
            "category":"Health Services",
            "subcategory":"Doctor",
            "type":"Services"
        }
    ],
    "sg:phone":"+1 305 252 0088",
    "sg:postcode":"33189",
    "sg:province":"FL",
    "sg:tags":[
        "dentist"
    ],
    "wof:name":"David Cabanzon DDS",
    "wof:placetype":"venue"
},
  "geometry": {"coordinates":[-80.33680099999999,25.578263],"type":"Point"}
}