{
  "type": "Feature",
  "properties": {
    "addr:full":"404 Washington Ave Miami Beach FL 33139",
    "addr:housenumber":"404",
    "addr:postcode":"33139",
    "addr:street":"Washington Ave",
    "iso:country":"US",
    "sg:address":"404 Washington Ave",
    "sg:city":"Miami Beach",
    "sg:classifiers":[
        {
            "category":"Communications",
            "subcategory":"Film & Video Production",
            "type":"Services"
        }
    ],
    "sg:phone":"+1 305 538 0955",
    "sg:postcode":"33139",
    "sg:province":"FL",
    "sg:tags":[
        "studio",
        "facility"
    ],
    "wof:name":"Badner Group",
    "wof:placetype":"venue"
},
  "geometry": {"coordinates":[-80.134214,25.77451],"type":"Point"}
}