{
  "type": "Feature",
  "properties": {
    "iso:country":"US",
    "sg:address":"219 NW 12th Ave",
    "sg:city":"Miami",
    "sg:classifiers":[
        {
            "category":"Travel",
            "subcategory":"Travel Agent",
            "type":"Entertainment"
        }
    ],
    "sg:phone":"+1 305 545 1515",
    "sg:postcode":"33128",
    "sg:province":"FL",
    "sg:tags":[
        "agency"
    ],
    "wof:name":"Kidney Specialty Center",
    "wof:placetype":"venue"
},
  "geometry": {"coordinates":[-80.21471099999999,25.77562],"type":"Point"}
}