{
  "type": "Feature",
  "properties": {
    "addr:full":"450 SW 88th Ter Hollywood FL 33025",
    "addr:housenumber":"450",
    "addr:postcode":"33025",
    "addr:street":"Sw 88Th Ter",
    "iso:country":"US",
    "sg:address":"450 SW 88th Ter",
    "sg:city":"Hollywood",
    "sg:classifiers":[
        {
            "category":"Real Estate",
            "subcategory":"Developer",
            "type":"Services"
        }
    ],
    "sg:phone":"+1 954 437 4663",
    "sg:postcode":"33025",
    "sg:province":"FL",
    "sg:tags":[
        "contractor"
    ],
    "wof:name":"Triangle Developers Corp",
    "wof:placetype":"venue"
},
  "geometry": {"coordinates":[-80.262698,26.00636],"type":"Point"}
}