{
  "type": "Feature",
  "properties": {
    "addr:full":"6409 Woodville Hwy Tallahassee FL 32305",
    "addr:housenumber":"6409",
    "addr:postcode":"32305",
    "addr:street":"Woodville Hwy",
    "iso:country":"US",
    "sg:address":"6409 Woodville Hwy",
    "sg:city":"Tallahassee",
    "sg:classifiers":[
        {
            "category":"Building & Trades",
            "subcategory":"Construction",
            "type":"Services"
        }
    ],
    "sg:phone":"+1 850 942 1004",
    "sg:postcode":"32305",
    "sg:province":"FL",
    "sg:tags":[
        "television",
        "telephone",
        "cable",
        "contractor"
    ],
    "wof:name":"Sunshine Utilities Inc",
    "wof:placetype":"venue"
},
  "geometry": {"coordinates":[-84.260898,30.354524],"type":"Point"}
}