{
  "type": "Feature",
  "properties": {
    "iso:country":"US",
    "sg:address":"963 4th Ave S",
    "sg:city":"Naples",
    "sg:classifiers":[
        {
            "category":"Banks & Credit Unions",
            "subcategory":"Bank",
            "type":"Services"
        }
    ],
    "sg:phone":"+1 239 261 9490",
    "sg:postcode":"34102",
    "sg:province":"FL",
    "sg:tags":[
        "mortgage"
    ],
    "wof:name":"World Savings Bank",
    "wof:placetype":"venue"
},
  "geometry": {"coordinates":[-81.794354,26.143109],"type":"Point"}
}