{
  "type": "Feature",
  "properties": {
    "addr:full":"661 Blanding Blvd Orange Park FL 32073",
    "addr:housenumber":"661",
    "addr:postcode":"32073",
    "addr:street":"Blanding Blvd",
    "iso:country":"US",
    "sg:address":"661 Blanding Blvd",
    "sg:city":"Orange Park",
    "sg:classifiers":[
        {
            "category":"Restaurant",
            "type":"Food & Drink"
        }
    ],
    "sg:menulink":"http://www.allmenus.com/fl/orange-park/111833-subway/menu/",
    "sg:phone":"+1 904 276 7926",
    "sg:postcode":"32073",
    "sg:province":"FL",
    "sg:tags":[
        "american",
        "sandwich"
    ],
    "wof:name":"Subway",
    "wof:placetype":"venue"
},
  "geometry": {"coordinates":[-81.75501800000001,30.149122],"type":"Point"}
}