{
  "type": "Feature",
  "properties": {
    "iso:country":"US",
    "sg:address":"6241 SW 8th St",
    "sg:city":"West Miami",
    "sg:classifiers":[
        {
            "category":"Travel",
            "subcategory":"Hotels & Motels",
            "type":"Entertainment"
        }
    ],
    "sg:phone":"+1 305 263 6615",
    "sg:postcode":"33144",
    "sg:province":"FL",
    "wof:name":"Starlite West Motel",
    "wof:placetype":"venue"
},
  "geometry": {"coordinates":[-80.296997,25.763201],"type":"Point"}
}