{
  "type": "Feature",
  "properties": {
    "addr:full":"4703 W Hillsborough Ave Tampa FL 33614",
    "addr:housenumber":"4703",
    "addr:postcode":"33614",
    "addr:street":"W Hillsborough Ave",
    "iso:country":"US",
    "sg:address":"4703 W Hillsborough Ave",
    "sg:city":"Tampa",
    "sg:classifiers":[
        {
            "category":"Food & Beverages",
            "subcategory":"Groceries & Convenience Stores",
            "type":"Retail Goods"
        }
    ],
    "sg:phone":"+1 813 249 6042",
    "sg:postcode":"33614",
    "sg:province":"FL",
    "wof:name":"Metro Market",
    "wof:placetype":"venue"
},
  "geometry": {"coordinates":[-82.521174,27.996196],"type":"Point"}
}