{
  "type": "Feature",
  "properties": {
    "iso:country":"US",
    "sg:address":"120 Dennison Rd",
    "sg:city":"Lutz",
    "sg:classifiers":[
        {
            "category":"Building & Trades",
            "subcategory":"Construction",
            "type":"Services"
        },
        {
            "category":"Manufacturing",
            "subcategory":"Watercraft",
            "type":"Manufacturing & Wholesale Goods"
        }
    ],
    "sg:phone":"+1 813 431 0975",
    "sg:postcode":"33548",
    "sg:province":"FL",
    "sg:tags":[
        "designer",
        "marine",
        "contractor"
    ],
    "wof:name":"Keske Robert Mobile Marine Svc",
    "wof:placetype":"venue"
},
  "geometry": {"coordinates":[-82.46270699999999,28.122099],"type":"Point"}
}