{
  "type": "Feature",
  "properties": {
    "iso:country":"US",
    "sg:address":"2755 NW 82nd Ave",
    "sg:city":"Doral",
    "sg:classifiers":[
        {
            "category":"Real Estate",
            "subcategory":"Architect",
            "type":"Services"
        },
        {
            "category":"Wholesale",
            "subcategory":"Construction Materials",
            "type":"Manufacturing & Wholesale Goods"
        }
    ],
    "sg:phone":"+1 305 406 3434",
    "sg:postcode":"33122",
    "sg:province":"FL",
    "sg:tags":[
        "illustrator",
        "architectural"
    ],
    "wof:name":"Izopoli Group LLC",
    "wof:placetype":"venue"
},
  "geometry": {"coordinates":[-80.328979,25.799713],"type":"Point"}
}