{
  "type": "Feature",
  "properties": {
    "addr:full":"2705 Tamiami Trl Punta Gorda FL 33950",
    "addr:housenumber":"2705",
    "addr:postcode":"33950",
    "addr:street":"Tamiami Trl",
    "iso:country":"US",
    "sg:address":"2705 Tamiami Trl",
    "sg:city":"Punta Gorda",
    "sg:classifiers":[
        {
            "category":"Travel",
            "subcategory":"Travel Agent",
            "type":"Entertainment"
        }
    ],
    "sg:phone":"+1 941 639 0999",
    "sg:postcode":"33950",
    "sg:province":"FL",
    "sg:tags":[
        "agency",
        "bureau"
    ],
    "sg:website":"www.oldtowntravel.com",
    "wof:name":"Old Town Travel Inc",
    "wof:placetype":"venue"
},
  "geometry": {"coordinates":[-82.04632100000001,26.915314],"type":"Point"}
}