{
  "type": "Feature",
  "properties": {
    "iso:country":"US",
    "sg:address":"1890 Spruce Creek Blvd",
    "sg:city":"Daytona Beach",
    "sg:classifiers":[
        {
            "category":"Health Services",
            "subcategory":"Doctor",
            "type":"Services"
        }
    ],
    "sg:phone":"+1 386 304 8941",
    "sg:postcode":"32128",
    "sg:province":"FL",
    "sg:tags":[
        "medical"
    ],
    "wof:name":"Dr Dj Belcher PA",
    "wof:placetype":"venue"
},
  "geometry": {"coordinates":[-81.05271999999999,29.080658],"type":"Point"}
}