{
  "type": "Feature",
  "properties": {
    "addr:full":"5445 NW 24th St Margate FL 33063",
    "addr:housenumber":"5445",
    "addr:postcode":"33063",
    "addr:street":"Nw 24Th St Margate",
    "iso:country":"US",
    "sg:address":"5445 NW 24th St",
    "sg:city":"Margate",
    "sg:classifiers":[
        {
            "category":"Wholesale",
            "subcategory":"Machinery & Supplies",
            "type":"Manufacturing & Wholesale Goods"
        },
        {
            "category":"Autos & Motor Vehicles",
            "subcategory":"Automobile Sales",
            "type":"Retail Goods"
        }
    ],
    "sg:phone":"+1 954 973 7511",
    "sg:postcode":"33063",
    "sg:province":"FL",
    "sg:tags":[
        "equipment",
        "aircraft",
        "parts"
    ],
    "wof:name":"Strider Aviation Inc",
    "wof:placetype":"venue"
},
  "geometry": {"coordinates":[-80.20036,26.257138],"type":"Point"}
}