{
  "type": "Feature",
  "properties": {
    "iso:country":"US",
    "sg:address":"1398 State Road 436",
    "sg:city":"Casselberry",
    "sg:classifiers":[
        {
            "category":"Real Estate",
            "subcategory":"Real Estate Services",
            "type":"Services"
        }
    ],
    "sg:phone":"+1 407 679 2900",
    "sg:postcode":"32707",
    "sg:province":"FL",
    "sg:tags":[
        "management",
        "property"
    ],
    "wof:name":"Ava Mena Limited Company",
    "wof:placetype":"venue"
},
  "geometry": {"coordinates":[-81.316704,28.6276],"type":"Point"}
}