{
  "type": "Feature",
  "properties": {
    "iso:country":"US",
    "sg:address":"1763 Coral Way",
    "sg:city":"Coral Gables",
    "sg:classifiers":[
        {
            "category":"Health Services",
            "subcategory":"Doctor",
            "type":"Services"
        }
    ],
    "sg:phone":"+1 305 860 2944",
    "sg:postcode":"33145",
    "sg:province":"FL",
    "wof:name":"Joel P Kallan MD PA",
    "wof:placetype":"venue"
},
  "geometry": {"coordinates":[-80.223285,25.75104],"type":"Point"}
}