{
  "type": "Feature",
  "properties": {
    "addr:full":"7350 S Tamiami Trl Ste 49 Sarasota FL 34231",
    "addr:housenumber":"7350",
    "addr:postcode":"34231",
    "addr:street":"S Tamiami Trl Ste 49",
    "iso:country":"US",
    "sg:address":"7350 S Tamiami Trl Ste 49",
    "sg:city":"Sarasota",
    "sg:classifiers":[
        {
            "category":"Professional",
            "subcategory":"Computer Services",
            "type":"Services"
        },
        {
            "category":"Internet Cafe",
            "subcategory":"None",
            "type":"Food & Drink"
        }
    ],
    "sg:phone":"+1 678 840 2583",
    "sg:postcode":"34231",
    "sg:province":"FL",
    "sg:tags":[
        "product",
        "software"
    ],
    "wof:name":"Code Blue Consulting",
    "wof:placetype":"venue"
},
  "geometry": {"coordinates":[-82.51286,27.24855],"type":"Point"}
}