{
  "type": "Feature",
  "properties": {
    "addr:full":"1382 SW Patricia Ave Port Saint Lucie FL 34953",
    "addr:housenumber":"1382",
    "addr:postcode":"34953",
    "addr:street":"Sw Patricia Ave",
    "iso:country":"US",
    "sg:address":"1382 SW Patricia Ave",
    "sg:city":"Port Saint Lucie",
    "sg:classifiers":[
        {
            "category":"Retail",
            "subcategory":"Repair Shop",
            "type":"Services"
        }
    ],
    "sg:phone":"+1 772 871 0270",
    "sg:postcode":"34953",
    "sg:province":"FL",
    "wof:name":"Arts Locksmith Service",
    "wof:placetype":"venue"
},
  "geometry": {"coordinates":[-80.391645,27.24196],"type":"Point"}
}