{
  "type": "Feature",
  "properties": {
    "iso:country":"US",
    "sg:address":"18 NW 1st Ave",
    "sg:city":"Fort Lauderdale",
    "sg:classifiers":[
        {
            "category":"Restaurant",
            "type":"Food & Drink"
        }
    ],
    "sg:phone":"+1 954 728 8485",
    "sg:postcode":"33301",
    "sg:province":"FL",
    "sg:tags":[
        "eating"
    ],
    "wof:name":"B T Food Express",
    "wof:placetype":"venue"
},
  "geometry": {"coordinates":[-80.14450600000001,26.123006],"type":"Point"}
}