{
  "type": "Feature",
  "properties": {
    "iso:country":"US",
    "sg:address":"527 W Valley Dr",
    "sg:city":"Bonita Springs",
    "sg:classifiers":[
        {
            "category":"Local Transit",
            "type":"Transportation"
        }
    ],
    "sg:phone":"+1 239 495 0442",
    "sg:postcode":"34134",
    "sg:province":"FL",
    "wof:name":"VIP Southwest Transportation",
    "wof:placetype":"venue"
},
  "geometry": {"coordinates":[-81.825299,26.325967],"type":"Point"}
}