{
  "type": "Feature",
  "properties": {
    "addr:full":"545 NE 23rd St Fort Lauderdale FL 33305",
    "addr:housenumber":"545",
    "addr:postcode":"33305",
    "addr:street":"Ne 23Rd St",
    "iso:country":"US",
    "sg:address":"545 NE 23rd St",
    "sg:city":"Fort Lauderdale",
    "sg:classifiers":[
        {
            "category":"Health Services",
            "subcategory":"Nursing And Care Facility",
            "type":"Services"
        }
    ],
    "sg:phone":"+1 954 566 7255",
    "sg:postcode":"33305",
    "sg:province":"FL",
    "sg:tags":[
        "skilled",
        "home",
        "retirement",
        "community"
    ],
    "wof:name":"Comfort Care Retirement Home",
    "wof:placetype":"venue"
},
  "geometry": {"coordinates":[-80.13897,26.156942],"type":"Point"}
}