{
  "type": "Feature",
  "properties": {
    "iso:country":"US",
    "sg:address":"17951 Hamilton Rd",
    "sg:city":"Dade City",
    "sg:classifiers":[
        {
            "category":"Farming",
            "subcategory":"Livestock Farm",
            "type":"Manufacturing & Wholesale Goods"
        }
    ],
    "sg:phone":"+1 352 521 0134",
    "sg:postcode":"33523",
    "sg:province":"FL",
    "sg:tags":[
        "ranch"
    ],
    "wof:name":"A Little Everglades Ranch",
    "wof:placetype":"venue"
},
  "geometry": {"coordinates":[-82.179175,28.4172],"type":"Point"}
}