{
  "type": "Feature",
  "properties": {
    "iso:country":"US",
    "sg:address":"545 Wood St",
    "sg:city":"Dunedin",
    "sg:classifiers":[
        {
            "category":"Organizations",
            "subcategory":"Religious Organization",
            "type":"Services"
        }
    ],
    "sg:phone":"+1 727 734 5779",
    "sg:postcode":"34698",
    "sg:province":"FL",
    "sg:tags":[
        "church"
    ],
    "wof:name":"Church Of Christ Dunedin",
    "wof:placetype":"venue"
},
  "geometry": {"coordinates":[-82.78375699999999,28.011363],"type":"Point"}
}