{
  "type": "Feature",
  "properties": {
    "iso:country":"US",
    "sg:address":"944 Clint Moore Rd",
    "sg:city":"Boca Raton",
    "sg:classifiers":[
        {
            "category":"Professional",
            "subcategory":"Business Services",
            "type":"Services"
        }
    ],
    "sg:phone":"+1 561 999 0336",
    "sg:postcode":"33487",
    "sg:province":"FL",
    "sg:tags":[
        "interior",
        "consulting",
        "fashion",
        "design"
    ],
    "wof:name":"Room Service Inc",
    "wof:placetype":"venue"
},
  "geometry": {"coordinates":[-80.104185,26.408164],"type":"Point"}
}