{
  "type": "Feature",
  "properties": {
    "addr:full":"4343 W Newberry Rd Ste 12 Gainesville FL 32607",
    "addr:housenumber":"4343",
    "addr:postcode":"32607",
    "addr:street":"W Newberry Rd Ste 12",
    "iso:country":"US",
    "sg:address":"4343 W Newberry Rd Ste 12",
    "sg:city":"Gainesville",
    "sg:classifiers":[
        {
            "category":"Health Services",
            "subcategory":"Doctor",
            "type":"Services"
        }
    ],
    "sg:phone":"+1 352 375 6279",
    "sg:postcode":"32607",
    "sg:province":"FL",
    "sg:tags":[
        "medicine",
        "physician",
        "practice",
        "surgeons",
        "family"
    ],
    "wof:name":"Velasquez Roger Md & Velasquez Elizabeth",
    "wof:placetype":"venue"
},
  "geometry": {"coordinates":[-82.36444899999999,29.650435],"type":"Point"}
}