{
  "type": "Feature",
  "properties": {
    "addr:full":"3301 Coral Way Miami FL 33145",
    "addr:housenumber":"3301",
    "addr:postcode":"33145",
    "addr:street":"Coral Way",
    "iso:country":"US",
    "sg:address":"3301 Coral Way",
    "sg:city":"Miami",
    "sg:classifiers":[
        {
            "category":"Shopping",
            "subcategory":"Department Store",
            "type":"Retail Goods"
        }
    ],
    "sg:phone":"+1 786 662 6025",
    "sg:postcode":"33145",
    "sg:province":"FL",
    "sg:website":"about.nordstrom.com/MapPoint/Map...",
    "wof:name":"Nordstrom Rack",
    "wof:placetype":"venue"
},
  "geometry": {"coordinates":[-80.249675,25.750443],"type":"Point"}
}