{
  "type": "Feature",
  "properties": {
    "iso:country":"US",
    "sg:address":"7850 SW 8th St",
    "sg:city":"Miami",
    "sg:phone":"+1 786 493 2705",
    "sg:postcode":"33144",
    "sg:province":"FL",
    "wof:name":"Kiko Moving",
    "wof:placetype":"venue"
},
  "geometry": {"coordinates":[-80.324223,25.762173],"type":"Point"}
}