{
  "type": "Feature",
  "properties": {
    "iso:country":"US",
    "sg:address":"299 Interstate Ct",
    "sg:city":"Sarasota",
    "sg:classifiers":[
        {
            "category":"Building & Trades",
            "subcategory":"Construction",
            "type":"Services"
        }
    ],
    "sg:phone":"+1 941 378 5800",
    "sg:postcode":"34240",
    "sg:province":"FL",
    "sg:tags":[
        "resurfacing",
        "laying",
        "refinishing",
        "floor"
    ],
    "wof:name":"Afco Designer Flooring",
    "wof:placetype":"venue"
},
  "geometry": {"coordinates":[-82.445628,27.332375],"type":"Point"}
}