{
  "type": "Feature",
  "properties": {
    "iso:country":"US",
    "sg:address":"30039 US Hwy 19",
    "sg:city":"Clearwater",
    "sg:classifiers":[
        {
            "category":"Shopping",
            "subcategory":"Clothing, Apparel, & Fashions",
            "type":"Retail Goods"
        }
    ],
    "sg:phone":"+1 727 771 8131",
    "sg:postcode":"33761",
    "sg:province":"FL",
    "sg:tags":[
        "tailor"
    ],
    "wof:name":"Curlew Tailors & Dry Cleaners",
    "wof:placetype":"venue"
},
  "geometry": {"coordinates":[-82.73847600000001,28.048261],"type":"Point"}
}