{
  "type": "Feature",
  "properties": {
    "addr:full":"4360 Carraway Pl Sanford FL 32771",
    "addr:housenumber":"4360",
    "addr:postcode":"32771",
    "addr:street":"Carraway Pl",
    "iso:country":"US",
    "sg:address":"4360 Carraway Pl",
    "sg:city":"Sanford",
    "sg:classifiers":[
        {
            "category":"Restaurant",
            "type":"Food & Drink"
        }
    ],
    "sg:phone":"+1 407 322 8800",
    "sg:postcode":"32771",
    "sg:province":"FL",
    "wof:name":"Hidden Harbour Deli",
    "wof:placetype":"venue"
},
  "geometry": {"coordinates":[-81.32731099999999,28.833986],"type":"Point"}
}