{
  "type": "Feature",
  "properties": {
    "iso:country":"US",
    "sg:address":"7600 Atlantic Blvd",
    "sg:city":"Jacksonville",
    "sg:classifiers":[
        {
            "category":"Retail",
            "subcategory":"Auto Repair",
            "type":"Services"
        }
    ],
    "sg:phone":"+1 904 721 9911",
    "sg:postcode":"32211",
    "sg:province":"FL",
    "sg:tags":[
        "body"
    ],
    "wof:name":"C & G Customs",
    "wof:placetype":"venue"
},
  "geometry": {"coordinates":[-81.577975,30.313397],"type":"Point"}
}