{
  "type": "Feature",
  "properties": {
    "iso:country":"US",
    "sg:address":"221 W State Road 434",
    "sg:city":"Longwood",
    "sg:classifiers":[
        {
            "category":"Social Services",
            "subcategory":"Child Care",
            "type":"Services"
        }
    ],
    "sg:phone":"+1 407 339 3232",
    "sg:postcode":"32750",
    "sg:province":"FL",
    "sg:tags":[
        "day"
    ],
    "wof:name":"Small Wonder Academy Inc",
    "wof:placetype":"venue"
},
  "geometry": {"coordinates":[-81.349164,28.698007],"type":"Point"}
}