{
  "type": "Feature",
  "properties": {
    "iso:country":"US",
    "sg:address":"54 NW 34th Ave",
    "sg:city":"Miami",
    "sg:classifiers":[
        {
            "category":"Banks & Credit Unions",
            "subcategory":"Financial Services",
            "type":"Services"
        }
    ],
    "sg:phone":"+1 305 220 8213",
    "sg:postcode":"33125",
    "sg:province":"FL",
    "sg:tags":[
        "investor"
    ],
    "wof:name":"Lucky Bamboo Investments Corp",
    "wof:placetype":"venue"
},
  "geometry": {"coordinates":[-80.25087600000001,25.773181],"type":"Point"}
}