{
  "type": "Feature",
  "properties": {
    "addr:full":"1182 SW 7th St Boca Raton FL 33486",
    "addr:housenumber":"1182",
    "addr:postcode":"33486",
    "addr:street":"Sw 7Th St",
    "iso:country":"US",
    "sg:address":"1182 SW 7th St",
    "sg:city":"Boca Raton",
    "sg:classifiers":[
        {
            "category":"Shopping",
            "subcategory":"Clothing, Apparel, & Fashions",
            "type":"Retail Goods"
        }
    ],
    "sg:phone":"+1 561 392 0192",
    "sg:postcode":"33486",
    "sg:province":"FL",
    "sg:tags":[
        "tailor"
    ],
    "wof:name":"St Mark Tailors",
    "wof:placetype":"venue"
},
  "geometry": {"coordinates":[-80.10887,26.343304],"type":"Point"}
}