{
  "type": "Feature",
  "properties": {
    "iso:country":"US",
    "sg:address":"5980 Lakehurst Dr",
    "sg:city":"Orlando",
    "sg:classifiers":[
        {
            "category":"Autos & Motor Vehicles",
            "subcategory":"Boat Sales",
            "type":"Retail Goods"
        }
    ],
    "sg:phone":"+1 407 354 3300",
    "sg:postcode":"32819",
    "sg:province":"FL",
    "sg:tags":[
        "dealer",
        "sales"
    ],
    "wof:name":"Dealer's Choice Marine",
    "wof:placetype":"venue"
},
  "geometry": {"coordinates":[-81.46128899999999,28.45322],"type":"Point"}
}