{
  "type": "Feature",
  "properties": {
    "addr:full":"471 SE 15th Ave Pompano Beach FL 33060",
    "addr:housenumber":"471",
    "addr:postcode":"33060",
    "addr:street":"Se 15Th Ave",
    "iso:country":"US",
    "sg:address":"471 SE 15th Ave",
    "sg:city":"Pompano Beach",
    "sg:classifiers":[
        {
            "category":"Professional",
            "subcategory":"Lawyer & Legal Services",
            "type":"Services"
        }
    ],
    "sg:phone":"+1 954 781 1441",
    "sg:postcode":"33060",
    "sg:province":"FL",
    "sg:tags":[
        "attorney"
    ],
    "wof:name":"Robert Mc Causland",
    "wof:placetype":"venue"
},
  "geometry": {"coordinates":[-80.10844,26.228675],"type":"Point"}
}