{
  "type": "Feature",
  "properties": {
    "addr:full":"9652 Tavernier Dr Boca Raton FL 33496",
    "addr:postcode":"9652;33496",
    "addr:street":"Tavernier Dr",
    "iso:country":"US",
    "sg:address":"9652 Tavernier Dr",
    "sg:city":"Boca Raton",
    "sg:classifiers":[
        {
            "category":"Building & Trades",
            "subcategory":"Construction",
            "type":"Services"
        }
    ],
    "sg:phone":"+1 561 218 0660",
    "sg:postcode":"33496",
    "sg:province":"FL",
    "sg:tags":[
        "general",
        "contractor"
    ],
    "wof:name":"Do-All Contracting Svc Inc",
    "wof:placetype":"venue"
},
  "geometry": {"coordinates":[-80.199023,26.394677],"type":"Point"}
}