{
  "type": "Feature",
  "properties": {
    "iso:country":"US",
    "sg:address":"3131 SW 22nd St",
    "sg:city":"Coral Gables",
    "sg:classifiers":[
        {
            "category":"Shopping",
            "subcategory":"Used Merchandise",
            "type":"Retail Goods"
        }
    ],
    "sg:phone":"+1 305 567 3131",
    "sg:postcode":"33145",
    "sg:province":"FL",
    "sg:tags":[
        "antique"
    ],
    "wof:name":"Coral Way Antiques",
    "wof:placetype":"venue"
},
  "geometry": {"coordinates":[-80.244963,25.750223],"type":"Point"}
}