{
  "type": "Feature",
  "properties": {
    "addr:full":"1429 Chaffee Dr Titusville FL 32780",
    "addr:housenumber":"1429",
    "addr:postcode":"32780",
    "addr:street":"Chaffee Dr",
    "iso:country":"US",
    "sg:address":"1429 Chaffee Dr",
    "sg:city":"Titusville",
    "sg:classifiers":[
        {
            "category":"Retail",
            "subcategory":"Repair Shop",
            "type":"Services"
        },
        {
            "category":"Building & Trades",
            "subcategory":"Plumbing",
            "type":"Services"
        }
    ],
    "sg:phone":"+1 321 269 0309",
    "sg:postcode":"32780",
    "sg:province":"FL",
    "sg:tags":[
        "plumbing",
        "contractor"
    ],
    "wof:name":"Certified Plumbing Of Brevard",
    "wof:placetype":"venue"
},
  "geometry": {"coordinates":[-80.816985,28.525717],"type":"Point"}
}