{
  "type": "Feature",
  "properties": {
    "iso:country":"US",
    "sg:address":"801 Industrial Ct",
    "sg:city":"Labelle",
    "sg:classifiers":[
        {
            "category":"Wholesale",
            "subcategory":"Auto Parts",
            "type":"Manufacturing & Wholesale Goods"
        }
    ],
    "sg:phone":"+1 863 675 4769",
    "sg:postcode":"33935",
    "sg:province":"FL",
    "sg:tags":[
        "automobile",
        "rebuilt"
    ],
    "wof:name":"T & M Used Auto Parts",
    "wof:placetype":"venue"
},
  "geometry": {"coordinates":[-81.426717,26.749316],"type":"Point"}
}