{
  "type": "Feature",
  "properties": {
    "addr:full":"98 12th St Apalachicola FL 32320",
    "addr:housenumber":"98",
    "addr:postcode":"32320",
    "addr:street":"12Th St",
    "iso:country":"US",
    "sg:address":"98 12th St",
    "sg:city":"Apalachicola",
    "sg:classifiers":[
        {
            "category":"Education",
            "subcategory":"School",
            "type":"Public Place"
        }
    ],
    "sg:phone":"+1 850 653 8857",
    "sg:postcode":"32320",
    "sg:province":"FL",
    "wof:name":"Chapman Elementary School",
    "wof:placetype":"venue"
},
  "geometry": {"coordinates":[-84.98965,29.721239],"type":"Point"}
}