{
  "type": "Feature",
  "properties": {
    "addr:full":"7979 NW 21st St Ste Lim5128 Doral FL 33122",
    "addr:housenumber":"7979",
    "addr:postcode":"33122",
    "addr:street":"Nw 21St St Ste Lim5128",
    "iso:country":"US",
    "sg:address":"7979 NW 21st St Ste Lim5128",
    "sg:city":"Doral",
    "sg:classifiers":[
        {
            "category":"Shopping",
            "subcategory":"Computers & Home Electronics",
            "type":"Retail Goods"
        },
        {
            "category":"Professional",
            "subcategory":"Computer Services",
            "type":"Services"
        }
    ],
    "sg:phone":"+1 786 991 2142",
    "sg:postcode":"33122",
    "sg:province":"FL",
    "sg:tags":[
        "graphic",
        "network",
        "supply",
        "consultant",
        "system",
        "hardware",
        "designer",
        "design",
        "online"
    ],
    "wof:name":"gamer.pe sac",
    "wof:placetype":"venue"
},
  "geometry": {"coordinates":[-80.324257,25.793393],"type":"Point"}
}