{
  "type": "Feature",
  "properties": {
    "addr:full":"5150 Tamiami Trl N Naples FL 34103",
    "addr:housenumber":"5150",
    "addr:postcode":"34103",
    "addr:street":"Tamiami Trl N",
    "iso:country":"US",
    "sg:address":"5150 Tamiami Trl N",
    "sg:city":"Naples",
    "sg:classifiers":[
        {
            "category":"Banks & Credit Unions",
            "subcategory":"Investment Brokerage",
            "type":"Services"
        }
    ],
    "sg:phone":"+1 239 263 7375",
    "sg:postcode":"34103",
    "sg:province":"FL",
    "sg:tags":[
        "consultant",
        "planning",
        "financial"
    ],
    "wof:name":"Goodman Financial Group",
    "wof:placetype":"venue"
},
  "geometry": {"coordinates":[-81.80031099999999,26.209217],"type":"Point"}
}