{
  "type": "Feature",
  "properties": {
    "addr:full":"6406 N 43rd St Tampa FL 33610",
    "addr:housenumber":"6406",
    "addr:postcode":"33610",
    "addr:street":"N 43Rd St",
    "iso:country":"US",
    "sg:address":"6406 N 43rd St",
    "sg:city":"Tampa",
    "sg:classifiers":[
        {
            "category":"Social Services",
            "subcategory":"Child Care",
            "type":"Services"
        }
    ],
    "sg:phone":"+1 813 849 1487",
    "sg:postcode":"33610",
    "sg:province":"FL",
    "sg:tags":[
        "day"
    ],
    "wof:name":"Helping Hand Day Nursery Inc",
    "wof:placetype":"venue"
},
  "geometry": {"coordinates":[-82.410166,28.006322],"type":"Point"}
}