{
  "type": "Feature",
  "properties": {
    "iso:country":"US",
    "sg:address":"5748 12th Ave NW",
    "sg:city":"Naples",
    "sg:classifiers":[
        {
            "category":"Recreation",
            "type":"Entertainment"
        }
    ],
    "sg:phone":"+1 239 566 2470",
    "sg:postcode":"34119",
    "sg:province":"FL",
    "sg:tags":[
        "diving",
        "instruction"
    ],
    "wof:name":"Mike Sawatzki's Scuba Diving",
    "wof:placetype":"venue"
},
  "geometry": {"coordinates":[-81.717581,26.252454],"type":"Point"}
}