{
  "type": "Feature",
  "properties": {
    "iso:country":"US",
    "sg:address":"22327 Adorn Ave",
    "sg:city":"Port Charlotte",
    "sg:classifiers":[
        {
            "category":"Building & Trades",
            "subcategory":"Cleaning & Sanitation",
            "type":"Services"
        }
    ],
    "sg:phone":"+1 941 625 4655",
    "sg:postcode":"33952",
    "sg:province":"FL",
    "sg:tags":[
        "sidewalk",
        "patio"
    ],
    "wof:name":"Preferred Pressure Cleaners",
    "wof:placetype":"venue"
},
  "geometry": {"coordinates":[-82.079869,27.008414],"type":"Point"}
}