{
  "type": "Feature",
  "properties": {
    "addr:full":"1304 SW Pinetree Trl Stuart FL 34997",
    "addr:housenumber":"1304",
    "addr:postcode":"34997",
    "addr:street":"Sw Pinetree Trl",
    "iso:country":"US",
    "sg:address":"1304 SW Pinetree Trl",
    "sg:city":"Stuart",
    "sg:classifiers":[
        {
            "category":"Building & Trades",
            "subcategory":"Construction",
            "type":"Services"
        }
    ],
    "sg:phone":"+1 772 221 8153",
    "sg:postcode":"34997",
    "sg:province":"FL",
    "sg:tags":[
        "contractor"
    ],
    "wof:name":"Charles Skinner",
    "wof:placetype":"venue"
},
  "geometry": {"coordinates":[-80.27104199999999,27.10759],"type":"Point"}
}