{
  "type": "Feature",
  "properties": {
    "iso:country":"US",
    "sg:address":"734 W Colonial Dr",
    "sg:city":"Orlando",
    "sg:classifiers":[
        {
            "category":"Organizations",
            "subcategory":"Professional Association",
            "type":"Services"
        }
    ],
    "sg:phone":"+1 407 254 5912",
    "sg:postcode":"32804",
    "sg:province":"FL",
    "wof:name":"Acorn Housing",
    "wof:placetype":"venue"
},
  "geometry": {"coordinates":[-81.390827,28.552923],"type":"Point"}
}