{
  "type": "Feature",
  "properties": {
    "addr:full":"10803 Old Lakeland Hwy Dade City FL 33525",
    "addr:housenumber":"10803",
    "addr:postcode":"33525",
    "addr:street":"Old Lakeland Hwy",
    "iso:country":"US",
    "sg:address":"10803 Old Lakeland Hwy",
    "sg:city":"Dade City",
    "sg:classifiers":[
        {
            "category":"Home & Garden",
            "subcategory":"Household Appliances",
            "type":"Retail Goods"
        }
    ],
    "sg:phone":"+1 352 523 0035",
    "sg:postcode":"33525",
    "sg:province":"FL",
    "wof:name":"Appliances Unlimited",
    "wof:placetype":"venue"
},
  "geometry": {"coordinates":[-82.156959,28.31705],"type":"Point"}
}