{
  "type": "Feature",
  "properties": {
    "addr:full":"901 Beryl Dr Rockledge FL 32955",
    "addr:housenumber":"901",
    "addr:postcode":"32955",
    "addr:street":"Beryl Dr",
    "iso:country":"US",
    "sg:address":"901 Beryl Dr",
    "sg:city":"Rockledge",
    "sg:classifiers":[
        {
            "category":"Building & Trades",
            "subcategory":"Construction",
            "type":"Services"
        }
    ],
    "sg:phone":"+1 321 634 5572",
    "sg:postcode":"32955",
    "sg:province":"FL",
    "sg:tags":[
        "hanging",
        "contractor"
    ],
    "wof:name":"Philip Craig Painting",
    "wof:placetype":"venue"
},
  "geometry": {"coordinates":[-80.72929499999999,28.314995],"type":"Point"}
}