{
  "type": "Feature",
  "properties": {
    "addr:full":"803 Derby Ave Apopka FL 32703",
    "addr:housenumber":"803",
    "addr:postcode":"32703",
    "addr:street":"Derby Ave",
    "iso:country":"US",
    "sg:address":"803 Derby Ave",
    "sg:city":"Apopka",
    "sg:classifiers":[
        {
            "category":"Farming",
            "subcategory":"Nursery",
            "type":"Manufacturing & Wholesale Goods"
        }
    ],
    "sg:phone":"+1 407 889 8771",
    "sg:postcode":"32703",
    "sg:province":"FL",
    "sg:tags":[
        "greenhouse"
    ],
    "wof:name":"Florikan Corp",
    "wof:placetype":"venue"
},
  "geometry": {"coordinates":[-81.50805800000001,28.663882],"type":"Point"}
}