{
  "type": "Feature",
  "properties": {
    "iso:country":"US",
    "sg:address":"3402 Airfield Dr W",
    "sg:city":"Lakeland",
    "sg:classifiers":[
        {
            "category":"Government",
            "subcategory":"Office",
            "type":"Public Place"
        }
    ],
    "sg:phone":"+1 863 648 3305",
    "sg:postcode":"33811",
    "sg:province":"FL",
    "sg:tags":[
        "transportation"
    ],
    "wof:name":"Airport Traffic Control Tower",
    "wof:placetype":"venue"
},
  "geometry": {"coordinates":[-82.018383,27.996437],"type":"Point"}
}