{
  "type": "Feature",
  "properties": {
    "iso:country":"US",
    "sg:address":"300 S Adams St",
    "sg:city":"Tallahassee",
    "sg:classifiers":[
        {
            "category":"Government",
            "subcategory":"Office",
            "type":"Public Place"
        }
    ],
    "sg:phone":"+1 850 891 8600",
    "sg:postcode":"32301",
    "sg:province":"FL",
    "sg:tags":[
        "development"
    ],
    "wof:name":"Tallahassee Leon Cnty Plg Dept",
    "wof:placetype":"venue"
},
  "geometry": {"coordinates":[-84.28191,30.439545],"type":"Point"}
}