{
  "type": "Feature",
  "properties": {
    "iso:country":"US",
    "sg:address":"4230 Stoney Point Rd",
    "sg:city":"Melbourne",
    "sg:classifiers":[
        {
            "category":"Communications",
            "subcategory":"Newspaper",
            "type":"Services"
        },
        {
            "category":"Wholesale",
            "subcategory":"Books, Periodicals, & Newspapers",
            "type":"Manufacturing & Wholesale Goods"
        }
    ],
    "sg:phone":"+1 321 757 9205",
    "sg:postcode":"32940",
    "sg:province":"FL",
    "sg:tags":[
        "news",
        "dealers-wholesale"
    ],
    "wof:name":"Baby Boomer Newspaper",
    "wof:placetype":"venue"
},
  "geometry": {"coordinates":[-80.699028,28.198011],"type":"Point"}
}