{
  "type": "Feature",
  "properties": {
    "iso:country":"US",
    "sg:address":"17000 NW 42nd Ave",
    "sg:city":"Opa Locka",
    "sg:classifiers":[
        {
            "category":"Professional",
            "subcategory":"Accounting & Tax Preparation",
            "type":"Services"
        }
    ],
    "sg:phone":"+1 305 625 7753",
    "sg:postcode":"33055",
    "sg:province":"FL",
    "sg:tags":[
        "billing"
    ],
    "wof:name":"K C Billing Svc Inc",
    "wof:placetype":"venue"
},
  "geometry": {"coordinates":[-80.26885799999999,25.929125],"type":"Point"}
}