{
  "type": "Feature",
  "properties": {
    "iso:country":"US",
    "sg:address":"206 Olson Ave",
    "sg:city":"Fort Pierce",
    "sg:classifiers":[
        {
            "category":"Wholesale",
            "subcategory":"Hardware",
            "type":"Manufacturing & Wholesale Goods"
        }
    ],
    "sg:phone":"+1 772 461 5650",
    "sg:postcode":"34946",
    "sg:province":"FL",
    "sg:tags":[
        "marine"
    ],
    "wof:name":"Monark Marine",
    "wof:placetype":"venue"
},
  "geometry": {"coordinates":[-80.337067,27.481965],"type":"Point"}
}