{
  "type": "Feature",
  "properties": {
    "addr:full":"3211 Ponce de Leon Blvd. Suite 102 Coral Gables FL 33134",
    "addr:housenumber":"3211",
    "addr:postcode":"33134",
    "addr:street":"Ponce De Leon Blvd. Suite 102",
    "iso:country":"US",
    "sg:address":"3211 Ponce de Leon Blvd. Suite 102",
    "sg:city":"Coral Gables",
    "sg:classifiers":[
        {
            "category":"Professional",
            "subcategory":"Computer Services",
            "type":"Services"
        }
    ],
    "sg:phone":"+1 305 704 7940",
    "sg:postcode":"33134",
    "sg:province":"FL",
    "sg:tags":[
        "mobile-coupons",
        "mobile-deals",
        "mobile-marketing"
    ],
    "sg:website":"http://www.shooger.com",
    "wof:name":"Shooger",
    "wof:placetype":"venue"
},
  "geometry": {"coordinates":[-80.258267,25.742078],"type":"Point"}
}