{
  "type": "Feature",
  "properties": {
    "addr:full":"3625 20th St Vero Beach FL 32960",
    "addr:housenumber":"3625",
    "addr:postcode":"32960",
    "addr:street":"20Th St",
    "iso:country":"US",
    "sg:address":"3625 20th St",
    "sg:city":"Vero Beach",
    "sg:classifiers":[
        {
            "category":"Professional",
            "subcategory":"Engineering",
            "type":"Services"
        }
    ],
    "sg:phone":"+1 772 562 8580",
    "sg:postcode":"32960",
    "sg:province":"FL",
    "sg:tags":[
        "engineer"
    ],
    "sg:website":"www.coastaltechcorp.com",
    "wof:name":"Coastal Technology Corp",
    "wof:placetype":"venue"
},
  "geometry": {"coordinates":[-80.42324000000001,27.638295],"type":"Point"}
}