{
  "type": "Feature",
  "properties": {
    "iso:country":"US",
    "sg:address":"17555 S Dixie Hwy",
    "sg:city":"Miami",
    "sg:classifiers":[
        {
            "category":"Education",
            "subcategory":"Preschool",
            "type":"Public Place"
        },
        {
            "category":"Education",
            "subcategory":"School",
            "type":"Public Place"
        }
    ],
    "sg:phone":"+1 305 253 3225",
    "sg:postcode":"33157",
    "sg:province":"FL",
    "sg:tags":[
        "elementary"
    ],
    "wof:name":"Montessori School-Winhold School",
    "wof:placetype":"venue"
},
  "geometry": {"coordinates":[-80.34880099999999,25.6054],"type":"Point"}
}