{
  "type": "Feature",
  "properties": {
    "addr:full":"123 Hickory Creek Dr Brandon FL 33511",
    "addr:housenumber":"123",
    "addr:postcode":"33511",
    "addr:street":"Hickory Creek Dr",
    "iso:country":"US",
    "sg:address":"123 Hickory Creek Dr",
    "sg:city":"Brandon",
    "sg:classifiers":[
        {
            "category":"Real Estate",
            "subcategory":"Real Estate Operator",
            "type":"Services"
        }
    ],
    "sg:phone":"+1 813 654 8623",
    "sg:postcode":"33511",
    "sg:province":"FL",
    "sg:tags":[
        "building",
        "apartment"
    ],
    "wof:name":"S & K Enterprises",
    "wof:placetype":"venue"
},
  "geometry": {"coordinates":[-82.280647,27.872904],"type":"Point"}
}