{
  "type": "Feature",
  "properties": {
    "addr:full":"2580 SE 6th St Pompano Beach FL 33062",
    "addr:housenumber":"2580",
    "addr:postcode":"33062",
    "addr:street":"Se 6Th St",
    "iso:country":"US",
    "sg:address":"2580 SE 6th St",
    "sg:city":"Pompano Beach",
    "sg:classifiers":[
        {
            "category":"Home & Garden",
            "subcategory":"Hardware",
            "type":"Retail Goods"
        }
    ],
    "sg:phone":"+1 954 943 9493",
    "sg:postcode":"33062",
    "sg:province":"FL",
    "wof:name":"Snap-On Tools",
    "wof:placetype":"venue"
},
  "geometry": {"coordinates":[-80.09671299999999,26.225814],"type":"Point"}
}