{
  "type": "Feature",
  "properties": {
    "addr:full":"804 Chamberlain Blvd Wauchula FL 33873",
    "addr:housenumber":"804",
    "addr:postcode":"33873",
    "addr:street":"Chamberlain Blvd",
    "iso:country":"US",
    "sg:address":"804 Chamberlain Blvd",
    "sg:city":"Wauchula",
    "sg:classifiers":[
        {
            "category":"Social Services",
            "subcategory":"Child Care",
            "type":"Services"
        }
    ],
    "sg:phone":"+1 863 767 0800",
    "sg:postcode":"33873",
    "sg:province":"FL",
    "sg:tags":[
        "nursery",
        "day"
    ],
    "wof:name":"Island Of Adventure Ccc",
    "wof:placetype":"venue"
},
  "geometry": {"coordinates":[-81.79779600000001,27.528959],"type":"Point"}
}