{
  "type": "Feature",
  "properties": {
    "iso:country":"US",
    "sg:address":"1733 Rodman St",
    "sg:city":"Hollywood",
    "sg:classifiers":[
        {
            "category":"Building & Trades",
            "subcategory":"Construction",
            "type":"Services"
        }
    ],
    "sg:phone":"+1 954 921 5744",
    "sg:postcode":"33020",
    "sg:province":"FL",
    "sg:tags":[
        "general",
        "contractor"
    ],
    "wof:name":"Rob Allen Restoration Inc",
    "wof:placetype":"venue"
},
  "geometry": {"coordinates":[-80.142098,26.001478],"type":"Point"}
}