{
  "type": "Feature",
  "properties": {
    "iso:country":"US",
    "sg:address":"3851 Allen Rd",
    "sg:city":"Zephyrhills",
    "sg:classifiers":[
        {
            "category":"Professional",
            "subcategory":"Employment Agencies",
            "type":"Services"
        },
        {
            "category":"Professional",
            "subcategory":"Business Services",
            "type":"Services"
        }
    ],
    "sg:phone":"+1 813 715 1075",
    "sg:postcode":"33541",
    "sg:province":"FL",
    "sg:tags":[
        "consultants-referral",
        "consultant",
        "coach"
    ],
    "wof:name":"Krouse Consulting Services",
    "wof:placetype":"venue"
},
  "geometry": {"coordinates":[-82.20487900000001,28.213658],"type":"Point"}
}