{
  "type": "Feature",
  "properties": {
    "addr:full":"501 Ave C SW Winter Haven FL 33880",
    "addr:housenumber":"501",
    "addr:postcode":"33880",
    "addr:street":"Ave C Sw",
    "iso:country":"US",
    "sg:address":"501 Ave C SW",
    "sg:city":"Winter Haven",
    "sg:classifiers":[
        {
            "category":"Retail",
            "subcategory":"Auto Repair",
            "type":"Services"
        }
    ],
    "sg:phone":"+1 863 299 1474",
    "sg:postcode":"33880",
    "sg:province":"FL",
    "sg:tags":[
        "repairing",
        "automobile"
    ],
    "wof:name":"Will-Press Complete Automotive",
    "wof:placetype":"venue"
},
  "geometry": {"coordinates":[-81.732778,28.018762],"type":"Point"}
}