{
  "type": "Feature",
  "properties": {
    "addr:full":"3190 Springhill Rd Tallahassee FL 32305",
    "addr:housenumber":"3190",
    "addr:postcode":"32305",
    "addr:street":"Springhill Rd",
    "iso:country":"US",
    "sg:address":"3190 Springhill Rd",
    "sg:city":"Tallahassee",
    "sg:classifiers":[
        {
            "category":"Organizations",
            "subcategory":"Non-profit Organization",
            "type":"Services"
        }
    ],
    "sg:phone":"+1 850 575 5007",
    "sg:postcode":"32305",
    "sg:province":"FL",
    "sg:tags":[
        "information",
        "alcoholism",
        "treatment"
    ],
    "wof:name":"Non-Secure Programs Inc",
    "wof:placetype":"venue"
},
  "geometry": {"coordinates":[-84.30573800000001,30.407694],"type":"Point"}
}