{
  "type": "Feature",
  "properties": {
    "iso:country":"US",
    "sg:address":"6630 20th St",
    "sg:city":"Vero Beach",
    "sg:classifiers":[
        {
            "category":"Communications",
            "type":"Services"
        }
    ],
    "sg:phone":"+1 772 231 1013",
    "sg:postcode":"32966",
    "sg:province":"FL",
    "wof:name":"Trans Florida Communications",
    "wof:placetype":"venue"
},
  "geometry": {"coordinates":[-80.464456,27.639045],"type":"Point"}
}