{
  "type": "Feature",
  "properties": {
    "iso:country":"US",
    "sg:address":"2271 N Washington Blvd",
    "sg:city":"Sarasota",
    "sg:classifiers":[
        {
            "category":"Restaurant",
            "type":"Food & Drink"
        }
    ],
    "sg:phone":"+1 941 952 0650",
    "sg:postcode":"34234",
    "sg:province":"FL",
    "sg:tags":[
        "eating"
    ],
    "wof:name":"Taqueria Aguascalientes",
    "wof:placetype":"venue"
},
  "geometry": {"coordinates":[-82.530475,27.356658],"type":"Point"}
}