{
  "type": "Feature",
  "properties": {
    "addr:full":"3425 S Atlantic Ave Daytona Bch Shrs FL 32118",
    "addr:housenumber":"3425",
    "addr:postcode":"32118",
    "addr:street":"S Atlantic Ave;Bch",
    "iso:country":"US",
    "sg:address":"3425 S Atlantic Ave",
    "sg:city":"Daytona Bch Shrs",
    "sg:classifiers":[
        {
            "category":"Real Estate",
            "subcategory":"Real Estate Operator",
            "type":"Services"
        }
    ],
    "sg:phone":"+1 386 304 3456",
    "sg:postcode":"32118",
    "sg:province":"FL",
    "sg:tags":[
        "condominium"
    ],
    "wof:name":"Towers Ten Condominium Assoc",
    "wof:placetype":"venue"
},
  "geometry": {"coordinates":[-80.96907,29.151361],"type":"Point"}
}