{
  "type": "Feature",
  "properties": {
    "iso:country":"US",
    "sg:address":"16619 NW 71st Ct",
    "sg:city":"Hialeah",
    "sg:classifiers":[
        {
            "category":"Shopping",
            "subcategory":"Computers & Home Electronics",
            "type":"Retail Goods"
        }
    ],
    "sg:phone":"+1 305 824 3770",
    "sg:postcode":"33014",
    "sg:province":"FL",
    "wof:name":"Mt Solutions Inc",
    "wof:placetype":"venue"
},
  "geometry": {"coordinates":[-80.317312,25.924022],"type":"Point"}
}