{
  "type": "Feature",
  "properties": {
    "addr:full":"2924 Knights Ln E Jacksonville FL 32216",
    "addr:housenumber":"2924",
    "addr:postcode":"32216",
    "addr:street":"Knights Ln E",
    "iso:country":"US",
    "sg:address":"2924 Knights Ln E",
    "sg:city":"Jacksonville",
    "sg:classifiers":[
        {
            "category":"Government",
            "subcategory":"Office",
            "type":"Public Place"
        }
    ],
    "sg:phone":"+1 904 732 5124",
    "sg:postcode":"32216",
    "sg:province":"FL",
    "sg:tags":[
        "village"
    ],
    "wof:name":"Jacksonville Truancy Ctr",
    "wof:placetype":"venue"
},
  "geometry": {"coordinates":[-81.59448999999999,30.271862],"type":"Point"}
}