{
  "type": "Feature",
  "properties": {
    "addr:full":"2755 Kirby Ave NE Palm Bay FL 32905",
    "addr:housenumber":"2755",
    "addr:postcode":"32905",
    "addr:street":"Kirby Ave Ne",
    "iso:country":"US",
    "sg:address":"2755 Kirby Ave NE",
    "sg:city":"Palm Bay",
    "sg:classifiers":[
        {
            "category":"Manufacturing",
            "subcategory":"Retail Goods",
            "type":"Manufacturing & Wholesale Goods"
        }
    ],
    "sg:phone":"+1 321 253 0541",
    "sg:postcode":"32905",
    "sg:province":"FL",
    "sg:tags":[
        "assembly",
        "fabricating"
    ],
    "sg:website":"www.mcati.com",
    "wof:name":"Mc Assembly",
    "wof:placetype":"venue"
},
  "geometry": {"coordinates":[-80.59123700000001,28.045146],"type":"Point"}
}