{
  "type": "Feature",
  "properties": {
    "addr:full":"404 Jenks Ave Panama City FL 32401",
    "addr:housenumber":"404",
    "addr:postcode":"32401",
    "addr:street":"Jenks Ave",
    "iso:country":"US",
    "sg:address":"404 Jenks Ave",
    "sg:city":"Panama City",
    "sg:classifiers":[
        {
            "category":"Insurance",
            "subcategory":"Insurance Agent",
            "type":"Services"
        }
    ],
    "sg:phone":"+1 850 784 6900",
    "sg:postcode":"32401",
    "sg:province":"FL",
    "sg:tags":[
        "processing"
    ],
    "sg:website":"www.healthcarerecovery.com",
    "wof:name":"Hrc Inc",
    "wof:placetype":"venue"
},
  "geometry": {"coordinates":[-85.662615,30.157],"type":"Point"}
}