{
  "type": "Feature",
  "properties": {
    "addr:full":"1844 Springtime Ave Clearwater FL 33755",
    "addr:housenumber":"1844",
    "addr:postcode":"33755",
    "addr:street":"Springtime Ave",
    "iso:country":"US",
    "sg:address":"1844 Springtime Ave",
    "sg:city":"Clearwater",
    "sg:classifiers":[
        {
            "category":"Restaurant",
            "type":"Food & Drink"
        }
    ],
    "sg:phone":"+1 727 446 3764",
    "sg:postcode":"33755",
    "sg:province":"FL",
    "sg:tags":[
        "eating"
    ],
    "wof:name":"Aloe Vera Skin Cream Co",
    "wof:placetype":"venue"
},
  "geometry": {"coordinates":[-82.78841199999999,27.988081],"type":"Point"}
}