{
  "type": "Feature",
  "properties": {
    "addr:full":"1401 Tamiami Trl Punta Gorda FL 33950",
    "addr:housenumber":"1401",
    "addr:postcode":"33950",
    "addr:street":"Tamiami Trl",
    "iso:country":"US",
    "sg:address":"1401 Tamiami Trl",
    "sg:city":"Punta Gorda",
    "sg:classifiers":[
        {
            "category":"Banks & Credit Unions",
            "subcategory":"Bank",
            "type":"Services"
        }
    ],
    "sg:phone":"+1 941 575 8315",
    "sg:postcode":"33950",
    "sg:province":"FL",
    "sg:tags":[
        "state",
        "commercial"
    ],
    "wof:name":"AmSouth",
    "wof:placetype":"venue"
},
  "geometry": {"coordinates":[-82.047399,26.925189],"type":"Point"}
}