{
  "type": "Feature",
  "properties": {
    "addr:full":"1477 Meadowlark Dr Deltona FL 32725",
    "addr:housenumber":"1477",
    "addr:postcode":"32725",
    "addr:street":"Meadowlark Dr",
    "iso:country":"US",
    "sg:address":"1477 Meadowlark Dr",
    "sg:city":"Deltona",
    "sg:classifiers":[
        {
            "category":"Professional",
            "subcategory":"Business Services",
            "type":"Services"
        }
    ],
    "sg:phone":"+1 407 474 5397",
    "sg:postcode":"32725",
    "sg:province":"FL",
    "wof:name":"M & F Designs",
    "wof:placetype":"venue"
},
  "geometry": {"coordinates":[-81.240477,28.90419],"type":"Point"}
}