{
  "type": "Feature",
  "properties": {
    "iso:country":"US",
    "sg:address":"8566 Forest Oaks Blvd",
    "sg:city":"Spring Hill",
    "sg:classifiers":[
        {
            "category":"Professional",
            "subcategory":"Business Services",
            "type":"Services"
        }
    ],
    "sg:phone":"+1 352 686 0379",
    "sg:postcode":"34606",
    "sg:province":"FL",
    "sg:tags":[
        "store",
        "variety"
    ],
    "wof:name":"Wrap Pak-N-Ship",
    "wof:placetype":"venue"
},
  "geometry": {"coordinates":[-82.57659700000001,28.486716],"type":"Point"}
}