{
  "type": "Feature",
  "properties": {
    "iso:country":"US",
    "sg:address":"2301 Lakeland Hills Blvd",
    "sg:city":"Lakeland",
    "sg:classifiers":[
        {
            "category":"Communications",
            "subcategory":"Radio Station",
            "type":"Services"
        }
    ],
    "sg:phone":"+1 863 614 9006",
    "sg:postcode":"33805",
    "sg:province":"FL",
    "sg:tags":[
        "company",
        "broadcasting"
    ],
    "wof:name":"WXYT Infinity Broadcasting",
    "wof:placetype":"venue"
},
  "geometry": {"coordinates":[-81.95328499999999,28.074675],"type":"Point"}
}