{
  "type": "Feature",
  "properties": {
    "addr:full":"860 Lemon St Sebring FL 33870",
    "addr:housenumber":"860",
    "addr:postcode":"33870",
    "addr:street":"Lemon St",
    "iso:country":"US",
    "sg:address":"860 Lemon St",
    "sg:city":"Sebring",
    "sg:classifiers":[
        {
            "category":"Organizations",
            "subcategory":"Religious Organization",
            "type":"Services"
        }
    ],
    "sg:phone":"+1 863 385 4291",
    "sg:postcode":"33870",
    "sg:province":"FL",
    "sg:tags":[
        "church"
    ],
    "wof:name":"Church Of God In Christ",
    "wof:placetype":"venue"
},
  "geometry": {"coordinates":[-81.432208,27.501147],"type":"Point"}
}