{
  "type": "Feature",
  "properties": {
    "iso:country":"US",
    "sg:address":"770 N State Road 7",
    "sg:city":"Plantation",
    "sg:classifiers":[
        {
            "category":"Autos & Motor Vehicles",
            "subcategory":"Auto Supplies",
            "type":"Retail Goods"
        },
        {
            "category":"Retail",
            "subcategory":"Auto Repair",
            "type":"Services"
        }
    ],
    "sg:phone":"+1 954 828 0797",
    "sg:postcode":"33317",
    "sg:province":"FL",
    "sg:tags":[
        "transmission",
        "truck"
    ],
    "sg:website":"http://www.realpagessites.com/transmissionking",
    "wof:name":"Transmission King",
    "wof:placetype":"venue"
},
  "geometry": {"coordinates":[-80.20224899999999,26.131543],"type":"Point"}
}