{
  "type": "Feature",
  "properties": {
    "iso:country":"US",
    "sg:address":"9445 Blind Pass Rd",
    "sg:city":"Saint Petersburg",
    "sg:classifiers":[
        {
            "category":"Organizations",
            "subcategory":"Community Association",
            "type":"Services"
        }
    ],
    "sg:phone":"+1 727 367 5659",
    "sg:postcode":"33706",
    "sg:province":"FL",
    "sg:tags":[
        "condominium"
    ],
    "wof:name":"St Petersburg Beach Yacht",
    "wof:placetype":"venue"
},
  "geometry": {"coordinates":[-82.757965,27.755538],"type":"Point"}
}