{
  "type": "Feature",
  "properties": {
    "addr:full":"25 S Magnolia Ave Orlando FL 32801",
    "addr:housenumber":"25",
    "addr:postcode":"32801",
    "addr:street":"S Magnolia Ave",
    "iso:country":"US",
    "sg:address":"25 S Magnolia Ave",
    "sg:city":"Orlando",
    "sg:classifiers":[
        {
            "category":"Real Estate",
            "subcategory":"Real Estate Agent",
            "type":"Services"
        }
    ],
    "sg:phone":"+1 407 872 6277",
    "sg:postcode":"32801",
    "sg:province":"FL",
    "wof:name":"Real Estate Team",
    "wof:placetype":"venue"
},
  "geometry": {"coordinates":[-81.37738,28.541526],"type":"Point"}
}