{
  "type": "Feature",
  "properties": {
    "addr:full":"3409 N Armenia Ave Tampa FL 33607",
    "addr:housenumber":"3409",
    "addr:postcode":"33607",
    "addr:street":"N Armenia Ave",
    "iso:country":"US",
    "sg:address":"3409 N Armenia Ave",
    "sg:city":"Tampa",
    "sg:classifiers":[
        {
            "category":"Personal",
            "subcategory":"Barber",
            "type":"Services"
        }
    ],
    "sg:phone":"+1 813 877 7441",
    "sg:postcode":"33607",
    "sg:province":"FL",
    "sg:tags":[
        "shop"
    ],
    "wof:name":"Tijerazo Hair Stylist Inc",
    "wof:placetype":"venue"
},
  "geometry": {"coordinates":[-82.48477,27.970301],"type":"Point"}
}