{
  "type": "Feature",
  "properties": {
    "iso:country":"US",
    "sg:address":"5217 NW 35th Ct",
    "sg:city":"Miami",
    "sg:classifiers":[
        {
            "category":"Autos & Motor Vehicles",
            "subcategory":"Automobile Sales",
            "type":"Retail Goods"
        }
    ],
    "sg:phone":"+1 305 633 9755",
    "sg:postcode":"33142",
    "sg:province":"FL",
    "sg:tags":[
        "new",
        "used",
        "car"
    ],
    "wof:name":"AA Motors",
    "wof:placetype":"venue"
},
  "geometry": {"coordinates":[-80.253857,25.82175],"type":"Point"}
}