{
  "type": "Feature",
  "properties": {
    "addr:full":"2950 SW 22nd Ter Miami FL 33145",
    "addr:housenumber":"2950",
    "addr:postcode":"33145",
    "addr:street":"Sw 22Nd Ter",
    "iso:country":"US",
    "sg:address":"2950 SW 22nd Ter",
    "sg:city":"Miami",
    "sg:classifiers":[
        {
            "category":"Professional",
            "subcategory":"Business Services",
            "type":"Services"
        }
    ],
    "sg:phone":"+1 305 447 0071",
    "sg:postcode":"33145",
    "sg:province":"FL",
    "sg:tags":[
        "exporter"
    ],
    "wof:name":"South Point Studios",
    "wof:placetype":"venue"
},
  "geometry": {"coordinates":[-80.241364,25.749315],"type":"Point"}
}