{
  "type": "Feature",
  "properties": {
    "addr:full":"9840 NW 77th Ave Hialeah FL 33016",
    "addr:housenumber":"9840",
    "addr:postcode":"33016",
    "addr:street":"Nw 77Th Ave",
    "iso:country":"US",
    "sg:address":"9840 NW 77th Ave",
    "sg:city":"Hialeah",
    "sg:classifiers":[
        {
            "category":"Home & Garden",
            "subcategory":"Furniture",
            "type":"Retail Goods"
        }
    ],
    "sg:phone":"+1 305 823 9800",
    "sg:postcode":"33016",
    "sg:province":"FL",
    "sg:tags":[
        "store"
    ],
    "sg:website":"www.rattanshack.com",
    "wof:name":"Rattan Shack",
    "wof:placetype":"venue"
},
  "geometry": {"coordinates":[-80.323097,25.863899],"type":"Point"}
}