{
  "type": "Feature",
  "properties": {
    "iso:country":"US",
    "sg:address":"45 Via Mizner",
    "sg:city":"Palm Beach",
    "sg:classifiers":[
        {
            "category":"Real Estate",
            "subcategory":"Developer",
            "type":"Services"
        }
    ],
    "sg:phone":"+1 561 655 6505",
    "sg:postcode":"33480",
    "sg:province":"FL",
    "wof:name":"Aston Development Corp",
    "wof:placetype":"venue"
},
  "geometry": {"coordinates":[-80.039878,26.701041],"type":"Point"}
}