{
  "type": "Feature",
  "properties": {
    "iso:country":"US",
    "sg:address":"3932 Rca Blvd",
    "sg:city":"Palm Beach Gardens",
    "sg:classifiers":[
        {
            "category":"Professional",
            "subcategory":"Management & Consulting",
            "type":"Services"
        }
    ],
    "sg:phone":"+1 561 627 1810",
    "sg:postcode":"33410",
    "sg:province":"FL",
    "sg:tags":[
        "ind",
        "environmental",
        "construction"
    ],
    "wof:name":"Rep Associates Inc",
    "wof:placetype":"venue"
},
  "geometry": {"coordinates":[-80.096813,26.837917],"type":"Point"}
}