{
  "type": "Feature",
  "properties": {
    "iso:country":"US",
    "sg:address":"9747 NW 32nd St",
    "sg:city":"Doral",
    "sg:classifiers":[
        {
            "category":"Wholesale",
            "subcategory":"Books, Periodicals, & Newspapers",
            "type":"Manufacturing & Wholesale Goods"
        }
    ],
    "sg:phone":"+1 305 639 2903",
    "sg:postcode":"33172",
    "sg:province":"FL",
    "sg:tags":[
        "toys-wholesale",
        "manufacturer"
    ],
    "wof:name":"Gameworld Intl Corp",
    "wof:placetype":"venue"
},
  "geometry": {"coordinates":[-80.354345,25.803787],"type":"Point"}
}