{
  "type": "Feature",
  "properties": {
    "addr:full":"626 Marsh Landing Pkwy Jacksonville Beach FL 32250",
    "addr:housenumber":"626",
    "addr:postcode":"32250",
    "addr:street":"Marsh Landing Pkwy",
    "iso:country":"US",
    "sg:address":"626 Marsh Landing Pkwy",
    "sg:city":"Jacksonville Beach",
    "sg:classifiers":[
        {
            "category":"Ice Cream",
            "type":"Food & Drink"
        }
    ],
    "sg:menulink":"http://www.allmenus.com/fl/jacksonville/184631-cold-stone-creamery/menu/",
    "sg:phone":"+1 904 280 7484",
    "sg:postcode":"32250",
    "sg:province":"FL",
    "sg:tags":[
        "smoothy",
        "juice",
        "american"
    ],
    "wof:name":"Cold Stone Creamery",
    "wof:placetype":"venue"
},
  "geometry": {"coordinates":[-81.392416,30.255678],"type":"Point"}
}