{
  "type": "Feature",
  "properties": {
    "iso:country":"US",
    "sg:address":"1128 N Tamiami Trl",
    "sg:city":"Fort Myers",
    "sg:classifiers":[
        {
            "category":"Building & Trades",
            "subcategory":"Construction",
            "type":"Services"
        }
    ],
    "sg:phone":"+1 239 997 3100",
    "sg:postcode":"33903",
    "sg:province":"FL",
    "sg:tags":[
        "roofing",
        "contractor"
    ],
    "wof:name":"Porto & Garcia Roofing",
    "wof:placetype":"venue"
},
  "geometry": {"coordinates":[-81.87880199999999,26.665226],"type":"Point"}
}