{
  "type": "Feature",
  "properties": {
    "iso:country":"US",
    "sg:address":"4606 SW 186th Way",
    "sg:city":"Miramar",
    "sg:classifiers":[
        {
            "category":"Health Services",
            "subcategory":"Hospital",
            "type":"Services"
        }
    ],
    "sg:phone":"+1 757 589 4976",
    "sg:postcode":"33029",
    "sg:province":"FL",
    "sg:tags":[
        "equipment",
        "supply"
    ],
    "wof:name":"Tidewater Management",
    "wof:placetype":"venue"
},
  "geometry": {"coordinates":[-80.394761,25.965245],"type":"Point"}
}