{
  "type": "Feature",
  "properties": {
    "iso:country":"US",
    "sg:address":"8007 NW 29th St",
    "sg:city":"Miami",
    "sg:classifiers":[
        {
            "category":"Banks & Credit Unions",
            "subcategory":"Financial Services",
            "type":"Services"
        }
    ],
    "sg:phone":"+1 305 591 7710",
    "sg:postcode":"33122",
    "sg:province":"FL",
    "sg:tags":[
        "company",
        "holding"
    ],
    "wof:name":"International Holdings Inc",
    "wof:placetype":"venue"
},
  "geometry": {"coordinates":[-80.327805,25.800832],"type":"Point"}
}