{
  "type": "Feature",
  "properties": {
    "addr:full":"12255 NW Hwy 225A Reddick FL 32686",
    "addr:housenumber":"12255",
    "addr:postcode":"32686",
    "addr:street":"Nw Hwy 225A",
    "iso:country":"US",
    "sg:address":"12255 NW Hwy 225A",
    "sg:city":"Reddick",
    "sg:classifiers":[
        {
            "category":"Manufacturing",
            "subcategory":"Printing",
            "type":"Manufacturing & Wholesale Goods"
        }
    ],
    "sg:phone":"+1 352 591 1189",
    "sg:postcode":"32686",
    "sg:province":"FL",
    "sg:tags":[
        "publisher"
    ],
    "wof:name":"Idelson-Gnocchi LTD Publisher",
    "wof:placetype":"venue"
},
  "geometry": {"coordinates":[-82.24685100000001,29.326131],"type":"Point"}
}