{
  "type": "Feature",
  "properties": {
    "iso:country":"US",
    "sg:address":"4230 SE 61st St",
    "sg:city":"Ocala",
    "sg:classifiers":[
        {
            "category":"Building & Trades",
            "subcategory":"Construction",
            "type":"Services"
        }
    ],
    "sg:phone":"+1 352 629 6215",
    "sg:postcode":"34480",
    "sg:province":"FL",
    "sg:tags":[
        "painter"
    ],
    "wof:name":"Jim Windham Painting",
    "wof:placetype":"venue"
},
  "geometry": {"coordinates":[-82.07504900000001,29.125939],"type":"Point"}
}