{
  "type": "Feature",
  "properties": {
    "iso:country":"US",
    "sg:address":"18400 SW 97th Ave",
    "sg:city":"Miami",
    "sg:classifiers":[
        {
            "category":"Banks & Credit Unions",
            "subcategory":"Financial Services",
            "type":"Services"
        }
    ],
    "sg:phone":"+1 305 235 6884",
    "sg:postcode":"33157",
    "sg:province":"FL",
    "sg:tags":[
        "broker",
        "mortgage"
    ],
    "wof:name":"Choice One Mortgage Corporation",
    "wof:placetype":"venue"
},
  "geometry": {"coordinates":[-80.348198,25.5987],"type":"Point"}
}