{
  "type": "Feature",
  "properties": {
    "iso:country":"US",
    "sg:address":"416 US Hwy 41",
    "sg:city":"Ruskin",
    "sg:classifiers":[
        {
            "category":"Social Services",
            "subcategory":"Child Care",
            "type":"Services"
        }
    ],
    "sg:phone":"+1 813 671 5264",
    "sg:postcode":"33570",
    "sg:province":"FL",
    "wof:name":"Redlands Christian Migrant",
    "wof:placetype":"venue"
},
  "geometry": {"coordinates":[-82.433999,27.722422],"type":"Point"}
}