{
  "type": "Feature",
  "properties": {
    "iso:country":"US",
    "sg:address":"225 NE 59th St",
    "sg:city":"Miami",
    "sg:classifiers":[
        {
            "category":"Museum",
            "type":"Entertainment"
        }
    ],
    "sg:phone":"+1 305 757 5307",
    "sg:postcode":"33137",
    "sg:province":"FL",
    "sg:tags":[
        "organization",
        "arts",
        "information"
    ],
    "wof:name":"Haitian Cultural Arts Alliance",
    "wof:placetype":"venue"
},
  "geometry": {"coordinates":[-80.19044100000001,25.829877],"type":"Point"}
}