{
  "type": "Feature",
  "properties": {
    "iso:country":"US",
    "sg:address":"4775 Mercantile Ave",
    "sg:city":"Naples",
    "sg:classifiers":[
        {
            "category":"Retail",
            "subcategory":"Car Wash",
            "type":"Services"
        },
        {
            "category":"Retail",
            "subcategory":"Auto Repair",
            "type":"Services"
        }
    ],
    "sg:phone":"+1 239 643 2886",
    "sg:postcode":"34104",
    "sg:province":"FL",
    "sg:tags":[
        "coating",
        "tinting",
        "trade",
        "glass",
        "carwash",
        "contractor"
    ],
    "wof:name":"Jogene's Auto Detailing",
    "wof:placetype":"venue"
},
  "geometry": {"coordinates":[-81.752602,26.166301],"type":"Point"}
}