{
  "type": "Feature",
  "properties": {
    "addr:full":"225 W 15th St Panama City FL 32401",
    "addr:housenumber":"225",
    "addr:postcode":"32401",
    "addr:street":"W 15Th St",
    "iso:country":"US",
    "sg:address":"225 W 15th St",
    "sg:city":"Panama City",
    "sg:classifiers":[
        {
            "category":"Home & Garden",
            "subcategory":"Carpets & Floor Coverings",
            "type":"Retail Goods"
        }
    ],
    "sg:phone":"+1 850 215 9116",
    "sg:postcode":"32401",
    "sg:province":"FL",
    "sg:tags":[
        "material"
    ],
    "wof:name":"Hardwood Liquidators Inc",
    "wof:placetype":"venue"
},
  "geometry": {"coordinates":[-85.663192,30.175092],"type":"Point"}
}