{
  "type": "Feature",
  "properties": {
    "addr:full":"1936 Hillview St Sarasota FL 34239",
    "addr:housenumber":"1936",
    "addr:postcode":"34239",
    "addr:street":"Hillview St",
    "iso:country":"US",
    "sg:address":"1936 Hillview St",
    "sg:city":"Sarasota",
    "sg:classifiers":[
        {
            "category":"Shopping",
            "subcategory":"Bicycles & Sporting Goods",
            "type":"Retail Goods"
        }
    ],
    "sg:phone":"+1 941 366 7702",
    "sg:postcode":"34239",
    "sg:province":"FL",
    "wof:name":"Fletchs",
    "wof:placetype":"venue"
},
  "geometry": {"coordinates":[-82.53033499999999,27.316335],"type":"Point"}
}