{
  "type": "Feature",
  "properties": {
    "iso:country":"US",
    "sg:address":"507 Massachusetts Ave",
    "sg:city":"Fort Walton Bch",
    "sg:classifiers":[
        {
            "category":"Shopping",
            "subcategory":"Hobbies, Toys, & Games",
            "type":"Retail Goods"
        }
    ],
    "sg:phone":"+1 850 864 1604",
    "sg:postcode":"32547",
    "sg:province":"FL",
    "sg:tags":[
        "doll"
    ],
    "wof:name":"M & M Dolls",
    "wof:placetype":"venue"
},
  "geometry": {"coordinates":[-86.64827,30.437799],"type":"Point"}
}