{
  "type": "Feature",
  "properties": {
    "addr:full":"2352 Olander St Green Cove Spgs FL 32043",
    "addr:housenumber":"2352",
    "addr:postcode":"32043",
    "addr:street":"Olander St",
    "iso:country":"US",
    "sg:address":"2352 Olander St",
    "sg:city":"Green Cove Spgs",
    "sg:classifiers":[
        {
            "category":"Insurance",
            "subcategory":"Hazard Insurance",
            "type":"Services"
        }
    ],
    "sg:phone":"+1 904 406 2067",
    "sg:postcode":"32043",
    "sg:province":"FL",
    "sg:tags":[
        "warranty",
        "program"
    ],
    "wof:name":"Home Warranty Pros",
    "wof:placetype":"venue"
},
  "geometry": {"coordinates":[-81.813075,30.072651],"type":"Point"}
}