{
  "type": "Feature",
  "properties": {
    "iso:country":"US",
    "sg:address":"955 Harbour Bay Dr",
    "sg:city":"Tampa",
    "sg:classifiers":[
        {
            "category":"Professional",
            "subcategory":"Business Services",
            "type":"Services"
        }
    ],
    "sg:phone":"+1 813 831 1338",
    "sg:postcode":"33602",
    "sg:province":"FL",
    "sg:tags":[
        "interior",
        "consultant",
        "design",
        "decorator"
    ],
    "wof:name":"Snooty Hooty",
    "wof:placetype":"venue"
},
  "geometry": {"coordinates":[-82.450237,27.932252],"type":"Point"}
}