{
  "type": "Feature",
  "properties": {
    "iso:country":"US",
    "sg:address":"225 Reid Ave",
    "sg:city":"Port St Joe",
    "sg:classifiers":[
        {
            "category":"Building & Trades",
            "subcategory":"Construction",
            "type":"Services"
        }
    ],
    "sg:phone":"+1 850 227 1945",
    "sg:postcode":"32456",
    "sg:province":"FL",
    "sg:tags":[
        "general",
        "contractor"
    ],
    "wof:name":"Jerry's Framing Crew",
    "wof:placetype":"venue"
},
  "geometry": {"coordinates":[-85.3034,29.814351],"type":"Point"}
}