{
  "type": "Feature",
  "properties": {
    "iso:country":"US",
    "sg:address":"5307 Harmony Pl",
    "sg:city":"Kissimmee",
    "sg:classifiers":[
        {
            "category":"Home & Garden",
            "subcategory":"Furniture",
            "type":"Retail Goods"
        }
    ],
    "sg:phone":"+1 407 870 0482",
    "sg:postcode":"34758",
    "sg:province":"FL",
    "wof:name":"Rest Assured Property",
    "wof:placetype":"venue"
},
  "geometry": {"coordinates":[-81.496377,28.229682],"type":"Point"}
}