{
  "type": "Feature",
  "properties": {
    "iso:country":"US",
    "sg:address":"7956 Hollyridge Rd",
    "sg:city":"Jacksonville",
    "sg:classifiers":[
        {
            "category":"Banks & Credit Unions",
            "subcategory":"Financial Services",
            "type":"Services"
        }
    ],
    "sg:phone":"+1 904 642 1179",
    "sg:postcode":"32256",
    "sg:province":"FL",
    "sg:tags":[
        "investor"
    ],
    "wof:name":"Sg Investments Inc",
    "wof:placetype":"venue"
},
  "geometry": {"coordinates":[-81.54677599999999,30.225915],"type":"Point"}
}