{
  "type": "Feature",
  "properties": {
    "addr:full":"316 N John Young Pkwy Kissimmee FL 34741",
    "addr:housenumber":"316",
    "addr:postcode":"34741",
    "addr:street":"N John Young Pkwy",
    "iso:country":"US",
    "sg:address":"316 N John Young Pkwy",
    "sg:city":"Kissimmee",
    "sg:classifiers":[
        {
            "category":"Insurance",
            "subcategory":"Insurance Agent",
            "type":"Services"
        }
    ],
    "sg:phone":"+1 407 847 0229",
    "sg:postcode":"34741",
    "sg:province":"FL",
    "wof:name":"State Farm Insurance",
    "wof:placetype":"venue"
},
  "geometry": {"coordinates":[-81.416033,28.295496],"type":"Point"}
}