{
  "type": "Feature",
  "properties": {
    "iso:country":"US",
    "sg:address":"4236 W Waters Ave",
    "sg:city":"Tampa",
    "sg:classifiers":[
        {
            "category":"Retail",
            "subcategory":"Auto Repair",
            "type":"Services"
        }
    ],
    "sg:phone":"+1 813 806 0781",
    "sg:postcode":"33614",
    "sg:province":"FL",
    "sg:tags":[
        "repairing",
        "automobile",
        "general"
    ],
    "wof:name":"A R Auto Repair",
    "wof:placetype":"venue"
},
  "geometry": {"coordinates":[-82.515522,28.025364],"type":"Point"}
}