{
  "type": "Feature",
  "properties": {
    "iso:country":"US",
    "sg:address":"865 91st Ave N",
    "sg:city":"Naples",
    "sg:classifiers":[
        {
            "category":"Building & Trades",
            "subcategory":"Construction",
            "type":"Services"
        }
    ],
    "sg:phone":"+1 239 594 0005",
    "sg:postcode":"34108",
    "sg:province":"FL",
    "sg:tags":[
        "hanging",
        "contractor"
    ],
    "wof:name":"Designer Decorating Co",
    "wof:placetype":"venue"
},
  "geometry": {"coordinates":[-81.80365500000001,26.254351],"type":"Point"}
}