{
  "type": "Feature",
  "properties": {
    "iso:country":"US",
    "sg:address":"1 Herald Plz",
    "sg:city":"Miami",
    "sg:classifiers":[
        {
            "category":"Wholesale",
            "subcategory":"Books, Periodicals, & Newspapers",
            "type":"Manufacturing & Wholesale Goods"
        }
    ],
    "sg:phone":"+1 305 376 2708",
    "sg:postcode":"33132",
    "sg:province":"FL",
    "sg:tags":[
        "publishers-periodical"
    ],
    "wof:name":"Condo Living",
    "wof:placetype":"venue"
},
  "geometry": {"coordinates":[-80.18646200000001,25.787251],"type":"Point"}
}