{
  "type": "Feature",
  "properties": {
    "addr:full":"2386 Oklahoma St West Palm Beach FL 33406",
    "addr:housenumber":"2386",
    "addr:postcode":"33406",
    "addr:street":"Oklahoma St",
    "iso:country":"US",
    "sg:address":"2386 Oklahoma St",
    "sg:city":"West Palm Beach",
    "sg:classifiers":[
        {
            "category":"Building & Trades",
            "subcategory":"Landscaping Services",
            "type":"Services"
        }
    ],
    "sg:phone":"+1 561 684 9907",
    "sg:postcode":"33406",
    "sg:province":"FL",
    "sg:tags":[
        "lawn",
        "maintenance",
        "grounds"
    ],
    "wof:name":"R & M Lawn Inc",
    "wof:placetype":"venue"
},
  "geometry": {"coordinates":[-80.078729,26.667665],"type":"Point"}
}