{
  "type": "Feature",
  "properties": {
    "iso:country":"US",
    "sg:address":"2459 Cheney Hwy Suite 63",
    "sg:city":"Titusville",
    "sg:classifiers":[
        {
            "category":"Professional",
            "type":"Services"
        },
        {
            "category":"Personal",
            "type":"Services"
        },
        {
            "category":"Retail",
            "subcategory":"Storage",
            "type":"Services"
        }
    ],
    "sg:phone":"+1 321 373 4690",
    "sg:postcode":"32780",
    "sg:province":"FL",
    "sg:tags":[
        "industrial",
        "household",
        "material",
        "commercial",
        "movers-commercial",
        "full",
        "moving",
        "services-labor",
        "mover"
    ],
    "sg:website":"http://www.allmysons.com/melbourne/index.aspx?YPBranch=Melbourne",
    "wof:name":"All My Sons Moving & Storage of Melbourne, Inc.",
    "wof:placetype":"venue"
},
  "geometry": {"coordinates":[-80.832115,28.557719],"type":"Point"}
}