{
  "type": "Feature",
  "properties": {
    "iso:country":"US",
    "sg:address":"1105 E 21st St",
    "sg:city":"Jacksonville",
    "sg:classifiers":[
        {
            "category":"Food & Beverages",
            "subcategory":"Groceries & Convenience Stores",
            "type":"Retail Goods"
        }
    ],
    "sg:phone":"+1 904 632 0005",
    "sg:postcode":"32206",
    "sg:province":"FL",
    "wof:name":"Butler's Place",
    "wof:placetype":"venue"
},
  "geometry": {"coordinates":[-81.639194,30.357475],"type":"Point"}
}