{
  "type": "Feature",
  "properties": {
    "iso:country":"US",
    "sg:address":"6627 Marina Pointe Village Ct",
    "sg:city":"Tampa",
    "sg:classifiers":[
        {
            "category":"Wholesale",
            "subcategory":"Drugs",
            "type":"Manufacturing & Wholesale Goods"
        }
    ],
    "sg:phone":"+1 813 814 9056",
    "sg:postcode":"33635",
    "sg:province":"FL",
    "wof:name":"Just Face It",
    "wof:placetype":"venue"
},
  "geometry": {"coordinates":[-82.61375200000001,28.006823],"type":"Point"}
}