{
  "type": "Feature",
  "properties": {
    "iso:country":"US",
    "sg:address":"18320 SW 149th Ave",
    "sg:city":"Miami",
    "sg:classifiers":[
        {
            "category":"Restaurant",
            "type":"Food & Drink"
        }
    ],
    "sg:phone":"+1 305 971 0499",
    "sg:postcode":"33187",
    "sg:province":"FL",
    "sg:tags":[
        "eating"
    ],
    "wof:name":"Vincents Bakery Cafe & Catrg",
    "wof:placetype":"venue"
},
  "geometry": {"coordinates":[-80.433914,25.602627],"type":"Point"}
}