{
  "type": "Feature",
  "properties": {
    "addr:full":"3300 Bonita Beach Rd Bonita Springs FL 34134",
    "addr:housenumber":"3300",
    "addr:postcode":"34134",
    "addr:street":"Bonita Beach Rd",
    "iso:country":"US",
    "sg:address":"3300 Bonita Beach Rd",
    "sg:city":"Bonita Springs",
    "sg:classifiers":[
        {
            "category":"Shopping",
            "subcategory":"Shoes",
            "type":"Retail Goods"
        }
    ],
    "sg:phone":"+1 239 498 1913",
    "sg:postcode":"34134",
    "sg:province":"FL",
    "wof:name":"El Rodeo",
    "wof:placetype":"venue"
},
  "geometry": {"coordinates":[-81.80703099999999,26.330565],"type":"Point"}
}