{
  "type": "Feature",
  "properties": {
    "iso:country":"US",
    "sg:address":"2641 NW 2nd St",
    "sg:city":"Okeechobee",
    "sg:classifiers":[
        {
            "category":"Personal",
            "subcategory":"Beauty Salon",
            "type":"Services"
        }
    ],
    "sg:phone":"+1 863 357 2596",
    "sg:postcode":"34972",
    "sg:province":"FL",
    "sg:tags":[
        "shop"
    ],
    "wof:name":"Dixon Curl",
    "wof:placetype":"venue"
},
  "geometry": {"coordinates":[-80.856776,27.245411],"type":"Point"}
}