{
  "type": "Feature",
  "properties": {
    "iso:country":"US",
    "sg:address":"1500 NW Ave L",
    "sg:city":"Belle Glade",
    "sg:classifiers":[
        {
            "category":"Professional",
            "subcategory":"Lawyer & Legal Services",
            "type":"Services"
        }
    ],
    "sg:phone":"+1 561 993 3836",
    "sg:postcode":"33430",
    "sg:province":"FL",
    "sg:tags":[
        "attorney"
    ],
    "wof:name":"Legal Aid Society-Palm Beach",
    "wof:placetype":"venue"
},
  "geometry": {"coordinates":[-80.68158699999999,26.696804],"type":"Point"}
}