{
  "type": "Feature",
  "properties": {
    "addr:full":"3105 W Henry Ave Tampa FL 33614",
    "addr:housenumber":"3105",
    "addr:postcode":"33614",
    "addr:street":"W Henry Ave",
    "iso:country":"US",
    "sg:address":"3105 W Henry Ave",
    "sg:city":"Tampa",
    "sg:classifiers":[
        {
            "category":"Manufacturing",
            "subcategory":"Tools & Machinery",
            "type":"Manufacturing & Wholesale Goods"
        }
    ],
    "sg:phone":"+1 813 876 7368",
    "sg:postcode":"33614",
    "sg:province":"FL",
    "sg:tags":[
        "residential",
        "lighting",
        "fixture",
        "mfg"
    ],
    "wof:name":"Paul Hazelton Lighting",
    "wof:placetype":"venue"
},
  "geometry": {"coordinates":[-82.496639,27.999513],"type":"Point"}
}