{
  "type": "Feature",
  "properties": {
    "iso:country":"US",
    "sg:address":"650 Palm Ave",
    "sg:city":"Hialeah",
    "sg:classifiers":[
        {
            "category":"Restaurant",
            "type":"Food & Drink"
        }
    ],
    "sg:phone":"+1 305 888 9698",
    "sg:postcode":"33010",
    "sg:province":"FL",
    "sg:tags":[
        "cuban"
    ],
    "wof:name":"Latin America Cafeteria & Restaurant",
    "wof:placetype":"venue"
},
  "geometry": {"coordinates":[-80.281949,25.827842],"type":"Point"}
}