{
  "type": "Feature",
  "properties": {
    "addr:full":"1119 S 6th Ave Wauchula FL 33873",
    "addr:housenumber":"1119",
    "addr:postcode":"33873",
    "addr:street":"S 6Th Ave",
    "iso:country":"US",
    "sg:address":"1119 S 6th Ave",
    "sg:city":"Wauchula",
    "sg:classifiers":[
        {
            "category":"Personal",
            "subcategory":"Beauty Salon",
            "type":"Services"
        },
        {
            "category":"Personal",
            "subcategory":"Nail Salon",
            "type":"Services"
        }
    ],
    "sg:phone":"+1 863 773 2555",
    "sg:postcode":"33873",
    "sg:province":"FL",
    "wof:name":"Sky Nail",
    "wof:placetype":"venue"
},
  "geometry": {"coordinates":[-81.80931699999999,27.530945],"type":"Point"}
}