{
  "type": "Feature",
  "properties": {
    "iso:country":"US",
    "sg:address":"3206 S Hopkins Ave",
    "sg:city":"Titusville",
    "sg:classifiers":[
        {
            "category":"Building & Trades",
            "subcategory":"Construction",
            "type":"Services"
        }
    ],
    "sg:phone":"+1 321 383 1476",
    "sg:postcode":"32780",
    "sg:province":"FL",
    "sg:tags":[
        "residential",
        "t"
    ],
    "wof:name":"Barton Pntg Wllcovering Prints",
    "wof:placetype":"venue"
},
  "geometry": {"coordinates":[-80.80504500000001,28.580912],"type":"Point"}
}