{
  "type": "Feature",
  "properties": {
    "iso:country":"US",
    "sg:address":"8300 Ulmerton Rd",
    "sg:city":"Largo",
    "sg:classifiers":[
        {
            "category":"Autos & Motor Vehicles",
            "subcategory":"Auto Supplies",
            "type":"Retail Goods"
        }
    ],
    "sg:phone":"+1 727 330 7768",
    "sg:postcode":"33771",
    "sg:province":"FL",
    "sg:tags":[
        "tire"
    ],
    "wof:name":"Enterprise Mobile Tire Service",
    "wof:placetype":"venue"
},
  "geometry": {"coordinates":[-82.75398300000001,27.894329],"type":"Point"}
}