{
  "type": "Feature",
  "properties": {
    "iso:country":"US",
    "sg:address":"31 S Federal Hwy",
    "sg:city":"Lake Worth",
    "sg:classifiers":[
        {
            "category":"Health Services",
            "subcategory":"Podiatrist",
            "type":"Services"
        }
    ],
    "sg:phone":"+1 561 586 3100",
    "sg:postcode":"33460",
    "sg:province":"FL",
    "wof:name":"Lake Worth Podiatry Center",
    "wof:placetype":"venue"
},
  "geometry": {"coordinates":[-80.05253,26.614916],"type":"Point"}
}