{
  "type": "Feature",
  "properties": {
    "addr:full":"2905 Long Lake Dr Titusville FL 32780",
    "addr:housenumber":"2905",
    "addr:postcode":"32780",
    "addr:street":"Long Lake Dr",
    "iso:country":"US",
    "sg:address":"2905 Long Lake Dr",
    "sg:city":"Titusville",
    "sg:classifiers":[
        {
            "category":"Building & Trades",
            "subcategory":"Construction",
            "type":"Services"
        }
    ],
    "sg:phone":"+1 321 267 7221",
    "sg:postcode":"32780",
    "sg:province":"FL",
    "sg:tags":[
        "house"
    ],
    "wof:name":"Reese Wingate Home Repair",
    "wof:placetype":"venue"
},
  "geometry": {"coordinates":[-80.84269,28.508806],"type":"Point"}
}