{
  "type": "Feature",
  "properties": {
    "addr:full":"21101 SW 198th Ave Miami FL 33187",
    "addr:housenumber":"21101",
    "addr:postcode":"33187",
    "addr:street":"Sw 198Th Ave",
    "iso:country":"US",
    "sg:address":"21101 SW 198th Ave",
    "sg:city":"Miami",
    "sg:classifiers":[
        {
            "category":"Freight",
            "type":"Transportation"
        }
    ],
    "sg:phone":"+1 305 885 8009",
    "sg:postcode":"33187",
    "sg:province":"FL",
    "sg:tags":[
        "operator",
        "trucking"
    ],
    "wof:name":"L C E Transport Inc",
    "wof:placetype":"venue"
},
  "geometry": {"coordinates":[-80.512693,25.567203],"type":"Point"}
}