{
  "type": "Feature",
  "properties": {
    "iso:country":"US",
    "sg:address":"6101 Southridge Rd",
    "sg:city":"Milton",
    "sg:classifiers":[
        {
            "category":"Professional",
            "type":"Services"
        }
    ],
    "sg:phone":"+1 850 623 1079",
    "sg:postcode":"32570",
    "sg:province":"FL",
    "wof:name":"Advanced Stress Methods Inc",
    "wof:placetype":"venue"
},
  "geometry": {"coordinates":[-87.063733,30.784884],"type":"Point"}
}