{
  "type": "Feature",
  "properties": {
    "iso:country":"US",
    "sg:address":"930 S Shore Dr",
    "sg:city":"Miami Beach",
    "sg:classifiers":[
        {
            "category":"Shopping",
            "type":"Retail Goods"
        }
    ],
    "sg:phone":"+1 305 297 6055",
    "sg:postcode":"33141",
    "sg:province":"FL",
    "sg:tags":[
        "merchandise"
    ],
    "wof:name":"Scrubs To You Inc",
    "wof:placetype":"venue"
},
  "geometry": {"coordinates":[-80.14359399999999,25.854649],"type":"Point"}
}