{
  "type": "Feature",
  "properties": {
    "addr:full":"1400 Pleasant Hill Rd Kissimmee FL 34741",
    "addr:housenumber":"1400",
    "addr:postcode":"34741",
    "addr:street":"Pleasant Hill Rd",
    "iso:country":"US",
    "sg:address":"1400 Pleasant Hill Rd",
    "sg:city":"Kissimmee",
    "sg:classifiers":[
        {
            "category":"Building & Trades",
            "subcategory":"Construction",
            "type":"Services"
        }
    ],
    "sg:phone":"+1 407 847 4443",
    "sg:postcode":"34741",
    "sg:province":"FL",
    "sg:tags":[
        "contractor"
    ],
    "wof:name":"Horizontal Dewatering Inc",
    "wof:placetype":"venue"
},
  "geometry": {"coordinates":[-81.436021,28.267349],"type":"Point"}
}