{
  "type": "Feature",
  "properties": {
    "addr:full":"1245 SW 2nd Ave Miami FL 33130",
    "addr:housenumber":"1245",
    "addr:postcode":"33130",
    "addr:street":"Sw 2Nd Ave",
    "iso:country":"US",
    "sg:address":"1245 SW 2nd Ave",
    "sg:city":"Miami",
    "sg:classifiers":[
        {
            "category":"Building & Trades",
            "subcategory":"Locksmith",
            "type":"Services"
        }
    ],
    "sg:phone":"+1 305 423 2508",
    "sg:postcode":"33130",
    "sg:province":"FL",
    "sg:tags":[
        "key"
    ],
    "wof:name":"1 After Drinking Locksmith Rescue",
    "wof:placetype":"venue"
},
  "geometry": {"coordinates":[-80.19709400000001,25.762013],"type":"Point"}
}