{
  "type": "Feature",
  "properties": {
    "iso:country":"US",
    "sg:address":"740 Swaying Palm Dr",
    "sg:city":"Apopka",
    "sg:classifiers":[
        {
            "category":"Professional",
            "subcategory":"Engineering",
            "type":"Services"
        }
    ],
    "sg:phone":"+1 407 880 2444",
    "sg:postcode":"32712",
    "sg:province":"FL",
    "sg:tags":[
        "engineer"
    ],
    "wof:name":"Remelt Technologies Inc",
    "wof:placetype":"venue"
},
  "geometry": {"coordinates":[-81.478213,28.695153],"type":"Point"}
}