{
  "type": "Feature",
  "properties": {
    "iso:country":"US",
    "sg:address":"1902 Cypress Lake Dr",
    "sg:city":"Orlando",
    "sg:classifiers":[
        {
            "category":"Manufacturing",
            "subcategory":"Tools & Machinery",
            "type":"Manufacturing & Wholesale Goods"
        }
    ],
    "sg:phone":"+1 407 996 4112",
    "sg:postcode":"32837",
    "sg:province":"FL",
    "sg:tags":[
        "building",
        "equipment",
        "lighting",
        "mfg"
    ],
    "wof:name":"Fouth Phas Lightn Prdctn Rsrc",
    "wof:placetype":"venue"
},
  "geometry": {"coordinates":[-81.398623,28.414541],"type":"Point"}
}