{
  "type": "Feature",
  "properties": {
    "addr:full":"3620 NW 76th St Miami FL 33147",
    "addr:housenumber":"3620",
    "addr:postcode":"33147",
    "addr:street":"Nw 76Th St",
    "iso:country":"US",
    "sg:address":"3620 NW 76th St",
    "sg:city":"Miami",
    "sg:classifiers":[
        {
            "category":"Transit Center",
            "subcategory":"Freight",
            "type":"Transportation"
        }
    ],
    "sg:phone":"+1 305 836 9005",
    "sg:postcode":"33147",
    "sg:province":"FL",
    "sg:tags":[
        "trucking-light",
        "hauling"
    ],
    "wof:name":"D & C Trucking Inc",
    "wof:placetype":"venue"
},
  "geometry": {"coordinates":[-80.256415,25.843266],"type":"Point"}
}