{
  "type": "Feature",
  "properties": {
    "addr:full":"8125 25th Ct E Sarasota FL 34243",
    "addr:housenumber":"8125",
    "addr:postcode":"34243",
    "addr:street":"25Th Ct E",
    "iso:country":"US",
    "sg:address":"8125 25th Ct E",
    "sg:city":"Sarasota",
    "sg:classifiers":[
        {
            "category":"Shopping",
            "subcategory":"Bicycles & Sporting Goods",
            "type":"Retail Goods"
        },
        {
            "category":"Wholesale",
            "subcategory":"Chemicals & Plastics",
            "type":"Manufacturing & Wholesale Goods"
        },
        {
            "category":"Manufacturing",
            "subcategory":"Building Materials",
            "type":"Manufacturing & Wholesale Goods"
        },
        {
            "category":"Government",
            "subcategory":"Post Office",
            "type":"Public Place"
        }
    ],
    "sg:phone":"+1 941 360 2200",
    "sg:postcode":"34243",
    "sg:province":"FL",
    "sg:tags":[
        "supply",
        "equipment",
        "painter",
        "distributor",
        "manufacturer",
        "supplies-wholesale",
        "pool",
        "swimming"
    ],
    "wof:name":"Hornerxpress-Manasota Inc",
    "wof:placetype":"venue"
},
  "geometry": {"coordinates":[-82.532331,27.395215],"type":"Point"}
}