{
  "type": "Feature",
  "properties": {
    "iso:country":"US",
    "sg:address":"4914 17th Pl SW",
    "sg:city":"Naples",
    "sg:classifiers":[
        {
            "category":"Home & Garden",
            "subcategory":"Building Materials",
            "type":"Retail Goods"
        }
    ],
    "sg:phone":"+1 239 417 1642",
    "sg:postcode":"34116",
    "sg:province":"FL",
    "wof:name":"Primitivo Lara Screen Repair",
    "wof:placetype":"venue"
},
  "geometry": {"coordinates":[-81.704925,26.195989],"type":"Point"}
}