{
  "type": "Feature",
  "properties": {
    "addr:full":"5922 Okeechobee Rd West Palm Beach FL 33417",
    "addr:housenumber":"5922",
    "addr:postcode":"33417",
    "addr:street":"Okeechobee Rd",
    "iso:country":"US",
    "sg:address":"5922 Okeechobee Rd",
    "sg:city":"West Palm Beach",
    "sg:classifiers":[
        {
            "category":"Professional",
            "subcategory":"Accounting & Tax Preparation",
            "type":"Services"
        }
    ],
    "sg:phone":"+1 561 684 7661",
    "sg:postcode":"33417",
    "sg:province":"FL",
    "sg:tags":[
        "consultant"
    ],
    "wof:name":"Superior Tax & Accounting",
    "wof:placetype":"venue"
},
  "geometry": {"coordinates":[-80.13403599999999,26.707282],"type":"Point"}
}