{
  "type": "Feature",
  "properties": {
    "addr:full":"2037 N University Dr Sunrise FL 33322",
    "addr:housenumber":"2037",
    "addr:postcode":"33322",
    "addr:street":"N University Dr",
    "iso:country":"US",
    "sg:address":"2037 N University Dr",
    "sg:city":"Sunrise",
    "sg:classifiers":[
        {
            "category":"Personal",
            "subcategory":"Beauty Salon",
            "type":"Services"
        }
    ],
    "sg:phone":"+1 954 616 1089",
    "sg:postcode":"33322",
    "sg:province":"FL",
    "sg:tags":[
        "hair",
        "stylist"
    ],
    "wof:name":"Maxie Unisex Salon",
    "wof:placetype":"venue"
},
  "geometry": {"coordinates":[-80.257181,26.150333],"type":"Point"}
}