{
  "type": "Feature",
  "properties": {
    "iso:country":"US",
    "sg:address":"1600 Blue Jay Cir",
    "sg:city":"Fort Lauderdale",
    "sg:classifiers":[
        {
            "category":"Wholesale",
            "subcategory":"Auto Parts",
            "type":"Manufacturing & Wholesale Goods"
        }
    ],
    "sg:phone":"+1 954 389 3392",
    "sg:postcode":"33327",
    "sg:province":"FL",
    "wof:name":"Best America Inc",
    "wof:placetype":"venue"
},
  "geometry": {"coordinates":[-80.40857699999999,26.122242],"type":"Point"}
}