{
  "type": "Feature",
  "properties": {
    "addr:full":"11005 SE 66th Ter Belleview FL 34420",
    "addr:housenumber":"11005",
    "addr:postcode":"34420",
    "addr:street":"Se 66Th Ter",
    "iso:country":"US",
    "sg:address":"11005 SE 66th Ter",
    "sg:city":"Belleview",
    "sg:classifiers":[
        {
            "category":"Professional",
            "subcategory":"Computer Services",
            "type":"Services"
        }
    ],
    "sg:phone":"+1 352 307 3237",
    "sg:postcode":"34420",
    "sg:province":"FL",
    "wof:name":"Micro Systems Concepts Group",
    "wof:placetype":"venue"
},
  "geometry": {"coordinates":[-82.041495,29.061396],"type":"Point"}
}