{
  "type": "Feature",
  "properties": {
    "addr:full":"15062 Copeland Way Brooksville FL 34604",
    "addr:housenumber":"15062",
    "addr:postcode":"34604",
    "addr:street":"Copeland Way",
    "iso:country":"US",
    "sg:address":"15062 Copeland Way",
    "sg:city":"Brooksville",
    "sg:classifiers":[
        {
            "category":"Transit Center",
            "subcategory":"Freight",
            "type":"Transportation"
        },
        {
            "category":"Freight",
            "type":"Transportation"
        }
    ],
    "sg:phone":"+1 813 784 2878",
    "sg:postcode":"34604",
    "sg:province":"FL",
    "sg:tags":[
        "local",
        "trucking-motor",
        "trucking"
    ],
    "wof:name":"Reyez Trucking",
    "wof:placetype":"venue"
},
  "geometry": {"coordinates":[-82.478703,28.483012],"type":"Point"}
}