{
  "type": "Feature",
  "properties": {
    "addr:full":"296 S Ferdon Blvd Crestview FL 32536",
    "addr:housenumber":"296",
    "addr:postcode":"32536",
    "addr:street":"S Ferdon Blvd",
    "iso:country":"US",
    "sg:address":"296 S Ferdon Blvd",
    "sg:city":"Crestview",
    "sg:classifiers":[
        {
            "category":"Professional",
            "subcategory":"Lawyer & Legal Services",
            "type":"Services"
        }
    ],
    "sg:phone":"+1 850 683 3940",
    "sg:postcode":"32536",
    "sg:province":"FL",
    "sg:tags":[
        "attorney",
        "criminal",
        "estate",
        "wills",
        "practice",
        "planning",
        "trust",
        "law"
    ],
    "wof:name":"Mynard Ryan Attorney At Law",
    "wof:placetype":"venue"
},
  "geometry": {"coordinates":[-86.56674099999999,30.756677],"type":"Point"}
}