{
  "type": "Feature",
  "properties": {
    "addr:full":"3830 S Nova Rd Daytona Beach FL 32127",
    "addr:housenumber":"3830",
    "addr:postcode":"32127",
    "addr:street":"S Nova Rd",
    "iso:country":"US",
    "sg:address":"3830 S Nova Rd",
    "sg:city":"Daytona Beach",
    "sg:classifiers":[
        {
            "category":"Shopping",
            "subcategory":"Discount & Variety Stores",
            "type":"Retail Goods"
        },
        {
            "category":"Shopping",
            "subcategory":"Department Store",
            "type":"Retail Goods"
        }
    ],
    "sg:phone":"+1 386 760 8737",
    "sg:postcode":"32127",
    "sg:province":"FL",
    "sg:tags":[
        "shop"
    ],
    "wof:name":"Big Lots",
    "wof:placetype":"venue"
},
  "geometry": {"coordinates":[-81.003913,29.125628],"type":"Point"}
}