{
  "type": "Feature",
  "properties": {
    "addr:full":"1720 W Cass St Tampa FL 33606",
    "addr:housenumber":"1720",
    "addr:postcode":"33606",
    "addr:street":"W Cass St",
    "iso:country":"US",
    "sg:address":"1720 W Cass St",
    "sg:city":"Tampa",
    "sg:classifiers":[
        {
            "category":"Building & Trades",
            "subcategory":"Construction",
            "type":"Services"
        }
    ],
    "sg:phone":"+1 813 258 5524",
    "sg:postcode":"33606",
    "sg:province":"FL",
    "sg:tags":[
        "general",
        "contractor"
    ],
    "sg:website":"www.trimarconstruction.com",
    "wof:name":"Trimar Construction",
    "wof:placetype":"venue"
},
  "geometry": {"coordinates":[-82.47846800000001,27.949768],"type":"Point"}
}