{
  "type": "Feature",
  "properties": {
    "iso:country":"US",
    "sg:address":"157 Jackson St",
    "sg:city":"Altamonte Spgs",
    "sg:classifiers":[
        {
            "category":"Professional",
            "type":"Services"
        }
    ],
    "sg:phone":"+1 407 767 2401",
    "sg:postcode":"32701",
    "sg:province":"FL",
    "sg:tags":[
        "establishment"
    ],
    "wof:name":"Thelee N Style Inc",
    "wof:placetype":"venue"
},
  "geometry": {"coordinates":[-81.34981999999999,28.668598],"type":"Point"}
}