{
  "type": "Feature",
  "properties": {
    "iso:country":"US",
    "sg:address":"2074 Polo Gardens Dr",
    "sg:city":"Wellington",
    "sg:classifiers":[
        {
            "category":"Shopping",
            "subcategory":"Clothing, Apparel, & Fashions",
            "type":"Retail Goods"
        }
    ],
    "sg:phone":"+1 561 790 9335",
    "sg:postcode":"33414",
    "sg:province":"FL",
    "sg:tags":[
        "apparel",
        "accessory",
        "women's"
    ],
    "wof:name":"Sunny Day Wares",
    "wof:placetype":"venue"
},
  "geometry": {"coordinates":[-80.244321,26.650695],"type":"Point"}
}