{
  "type": "Feature",
  "properties": {
    "iso:country":"US",
    "sg:address":"228 Obrien Rd",
    "sg:city":"Casselberry",
    "sg:classifiers":[
        {
            "category":"Building & Trades",
            "subcategory":"Construction",
            "type":"Services"
        }
    ],
    "sg:phone":"+1 407 260 5813",
    "sg:postcode":"32730",
    "sg:province":"FL",
    "sg:tags":[
        "contractor"
    ],
    "wof:name":"J Townsend Pressure Cleaning",
    "wof:placetype":"venue"
},
  "geometry": {"coordinates":[-81.355255,28.648486],"type":"Point"}
}