{
  "type": "Feature",
  "properties": {
    "addr:full":"1861 N Pine Island Rd Fort Lauderdale FL 33322",
    "addr:housenumber":"1861",
    "addr:postcode":"33322",
    "addr:street":"N Pine Island Rd",
    "iso:country":"US",
    "sg:address":"1861 N Pine Island Rd",
    "sg:city":"Fort Lauderdale",
    "sg:classifiers":[
        {
            "category":"Restaurant",
            "type":"Food & Drink"
        }
    ],
    "sg:phone":"+1 954 424 0808",
    "sg:postcode":"33322",
    "sg:province":"FL",
    "sg:tags":[
        "eating"
    ],
    "wof:name":"Thai Thai Restaurant",
    "wof:placetype":"venue"
},
  "geometry": {"coordinates":[-80.269355,26.144749],"type":"Point"}
}