{
  "type": "Feature",
  "properties": {
    "addr:full":"850 Tallevast Rd Sarasota FL 34243",
    "addr:housenumber":"850",
    "addr:postcode":"34243",
    "addr:street":"Tallevast Rd",
    "iso:country":"US",
    "sg:address":"850 Tallevast Rd",
    "sg:city":"Sarasota",
    "sg:classifiers":[
        {
            "category":"Organizations",
            "subcategory":"Labor Organization",
            "type":"Services"
        }
    ],
    "sg:phone":"+1 941 351 8232",
    "sg:postcode":"34243",
    "sg:province":"FL",
    "wof:name":"National Postal Mail Handlers",
    "wof:placetype":"venue"
},
  "geometry": {"coordinates":[-82.55628400000001,27.406383],"type":"Point"}
}