{
  "type": "Feature",
  "properties": {
    "iso:country":"US",
    "sg:address":"1433 SE Village Green Dr",
    "sg:city":"Port St Lucie",
    "sg:classifiers":[
        {
            "category":"Retail",
            "subcategory":"Auto Repair",
            "type":"Services"
        }
    ],
    "sg:phone":"+1 772 337 1280",
    "sg:postcode":"34952",
    "sg:province":"FL",
    "sg:tags":[
        "automotive",
        "electrical",
        "electric",
        "automobile"
    ],
    "wof:name":"Advance Auto Electric Inc",
    "wof:placetype":"venue"
},
  "geometry": {"coordinates":[-80.306635,27.305999],"type":"Point"}
}