{
  "type": "Feature",
  "properties": {
    "iso:country":"US",
    "sg:address":"5901 S Pine Ave",
    "sg:city":"Ocala",
    "sg:classifiers":[
        {
            "category":"Autos & Motor Vehicles",
            "subcategory":"Automobile Sales",
            "type":"Retail Goods"
        }
    ],
    "sg:phone":"+1 352 351 0123",
    "sg:postcode":"34480",
    "sg:province":"FL",
    "sg:tags":[
        "car",
        "dealer"
    ],
    "wof:name":"Don Scott Motors Inc",
    "wof:placetype":"venue"
},
  "geometry": {"coordinates":[-82.103376,29.127518],"type":"Point"}
}