{
  "type": "Feature",
  "properties": {
    "iso:country":"US",
    "sg:address":"12119 Bishopsford Dr",
    "sg:city":"Tampa",
    "sg:classifiers":[
        {
            "category":"Professional",
            "subcategory":"Engineering",
            "type":"Services"
        }
    ],
    "sg:phone":"+1 813 854 3246",
    "sg:postcode":"33626",
    "sg:province":"FL",
    "sg:tags":[
        "engineer"
    ],
    "wof:name":"Taylor Engineering Mech Cnslnt",
    "wof:placetype":"venue"
},
  "geometry": {"coordinates":[-82.629183,28.06462],"type":"Point"}
}