{
  "type": "Feature",
  "properties": {
    "addr:full":"520 NW 165th Street Rd Miami FL 33169",
    "addr:housenumber":"520",
    "addr:postcode":"33169",
    "addr:street":"Nw 165Th Street Rd",
    "iso:country":"US",
    "sg:address":"520 NW 165th Street Rd",
    "sg:city":"Miami",
    "sg:classifiers":[
        {
            "category":"Manufacturing",
            "subcategory":"Electronics",
            "type":"Manufacturing & Wholesale Goods"
        }
    ],
    "sg:phone":"+1 305 944 8868",
    "sg:postcode":"33169",
    "sg:province":"FL",
    "sg:tags":[
        "telecommunications-equipment",
        "supply"
    ],
    "wof:name":"Alcon Miami Corp",
    "wof:placetype":"venue"
},
  "geometry": {"coordinates":[-80.20998299999999,25.923043],"type":"Point"}
}