{
  "type": "Feature",
  "properties": {
    "iso:country":"US",
    "sg:address":"14811 Tulip Dr",
    "sg:city":"Tampa",
    "sg:classifiers":[
        {
            "category":"Professional",
            "subcategory":"Art Services",
            "type":"Services"
        }
    ],
    "sg:phone":"+1 813 963 0315",
    "sg:postcode":"33613",
    "sg:province":"FL",
    "sg:tags":[
        "commercial",
        "design"
    ],
    "wof:name":"Graphics By Rick",
    "wof:placetype":"venue"
},
  "geometry": {"coordinates":[-82.46389000000001,28.083842],"type":"Point"}
}