{
  "type": "Feature",
  "properties": {
    "iso:country":"US",
    "sg:address":"55 S Palm Ave",
    "sg:city":"Sarasota",
    "sg:classifiers":[
        {
            "category":"Restaurant",
            "type":"Food & Drink"
        }
    ],
    "sg:phone":"+1 941 364 8742",
    "sg:postcode":"34236",
    "sg:province":"FL",
    "wof:name":"Grovers Grill",
    "wof:placetype":"venue"
},
  "geometry": {"coordinates":[-82.540583,27.331907],"type":"Point"}
}