{
  "type": "Feature",
  "properties": {
    "addr:full":"9337 Atlantic Blvd Jacksonville FL 32225",
    "addr:housenumber":"9337",
    "addr:postcode":"32225",
    "addr:street":"Atlantic Blvd",
    "iso:country":"US",
    "sg:address":"9337 Atlantic Blvd",
    "sg:city":"Jacksonville",
    "sg:classifiers":[
        {
            "category":"Home & Garden",
            "subcategory":"Home Furnishings",
            "type":"Retail Goods"
        }
    ],
    "sg:phone":"+1 904 720 1806",
    "sg:postcode":"32225",
    "sg:province":"FL",
    "sg:tags":[
        "housewares"
    ],
    "wof:name":"Bed Bath & Beyond",
    "wof:placetype":"venue"
},
  "geometry": {"coordinates":[-81.55511300000001,30.318724],"type":"Point"}
}