{
  "type": "Feature",
  "properties": {
    "addr:full":"805 Lincoln Rd Miami Beach FL 33139",
    "addr:housenumber":"805",
    "addr:postcode":"33139",
    "addr:street":"Lincoln Rd",
    "iso:country":"US",
    "sg:address":"805 Lincoln Rd",
    "sg:city":"Miami Beach",
    "sg:classifiers":[
        {
            "category":"Shopping",
            "subcategory":"Optician",
            "type":"Retail Goods"
        }
    ],
    "sg:phone":"+1 305 531 5080",
    "sg:postcode":"33139",
    "sg:province":"FL",
    "sg:tags":[
        "eyewear"
    ],
    "sg:website":"www.solsticestores.com",
    "wof:name":"Solstice",
    "wof:placetype":"venue"
},
  "geometry": {"coordinates":[-80.136703,25.7904],"type":"Point"}
}