{
  "type": "Feature",
  "properties": {
    "addr:full":"401 Opa Locka Blvd Miami FL 33168",
    "addr:housenumber":"401",
    "addr:postcode":"33168",
    "addr:street":"Locka Blvd",
    "iso:country":"US",
    "sg:address":"401 Opa Locka Blvd",
    "sg:city":"Miami",
    "sg:classifiers":[
        {
            "category":"Restaurant",
            "type":"Food & Drink"
        }
    ],
    "sg:phone":"+1 305 688 3287",
    "sg:postcode":"33168",
    "sg:province":"FL",
    "sg:tags":[
        "eating"
    ],
    "wof:name":"Subway",
    "wof:placetype":"venue"
},
  "geometry": {"coordinates":[-80.205753,25.899953],"type":"Point"}
}