{
  "type": "Feature",
  "properties": {
    "addr:full":"110 E Bloomingdale Ave Brandon FL 33511",
    "addr:housenumber":"110",
    "addr:postcode":"33511",
    "addr:street":"E Bloomingdale Ave",
    "iso:country":"US",
    "sg:address":"110 E Bloomingdale Ave",
    "sg:city":"Brandon",
    "sg:classifiers":[
        {
            "category":"Health Services",
            "subcategory":"Health Practitioner",
            "type":"Services"
        }
    ],
    "sg:phone":"+1 813 341 2200",
    "sg:postcode":"33511",
    "sg:province":"FL",
    "sg:tags":[
        "acupuncture"
    ],
    "wof:name":"Bloomingdale Acupunture",
    "wof:placetype":"venue"
},
  "geometry": {"coordinates":[-82.282202,27.893749],"type":"Point"}
}