{
  "type": "Feature",
  "properties": {
    "iso:country":"US",
    "sg:address":"109 S Parsons Ave",
    "sg:city":"Brandon",
    "sg:classifiers":[
        {
            "category":"Insurance",
            "subcategory":"Insurance Agent",
            "type":"Services"
        }
    ],
    "sg:phone":"+1 813 684 7551",
    "sg:postcode":"33511",
    "sg:province":"FL",
    "sg:tags":[
        "agency"
    ],
    "wof:name":"Llerandi Insurance Group Inc",
    "wof:placetype":"venue"
},
  "geometry": {"coordinates":[-82.285873,27.935949],"type":"Point"}
}