{
  "type": "Feature",
  "properties": {
    "iso:country":"US",
    "sg:address":"10801 SW 62nd Ave",
    "sg:city":"Miami",
    "sg:classifiers":[
        {
            "category":"Professional",
            "subcategory":"Accounting & Tax Preparation",
            "type":"Services"
        }
    ],
    "sg:phone":"+1 305 669 3800",
    "sg:postcode":"33156",
    "sg:province":"FL",
    "sg:tags":[
        "record",
        "consulting",
        "management"
    ],
    "wof:name":"Bluemed Consulting",
    "wof:placetype":"venue"
},
  "geometry": {"coordinates":[-80.29435700000001,25.670891],"type":"Point"}
}