{
  "type": "Feature",
  "properties": {
    "iso:country":"US",
    "sg:address":"1850 Lee Rd Ste 111",
    "sg:city":"Winter Park",
    "sg:classifiers":[
        {
            "category":"Professional",
            "subcategory":"Lawyer & Legal Services",
            "type":"Services"
        }
    ],
    "sg:phone":"+1 407 740 5931",
    "sg:postcode":"32789",
    "sg:province":"FL",
    "wof:name":"Phipps Linda K Atty",
    "wof:placetype":"venue"
},
  "geometry": {"coordinates":[-81.372704,28.605801],"type":"Point"}
}