{
  "type": "Feature",
  "properties": {
    "addr:full":"2023 Park Ave Orange Park FL 32073",
    "addr:housenumber":"2023",
    "addr:postcode":"32073",
    "addr:street":"Park Ave",
    "iso:country":"US",
    "sg:address":"2023 Park Ave",
    "sg:city":"Orange Park",
    "sg:classifiers":[
        {
            "category":"Restaurant",
            "type":"Food & Drink"
        }
    ],
    "sg:phone":"+1 904 269 1331",
    "sg:postcode":"32073",
    "sg:province":"FL",
    "sg:tags":[
        "eating"
    ],
    "wof:name":"Ristorante Sarnelli's",
    "wof:placetype":"venue"
},
  "geometry": {"coordinates":[-81.701058,30.164662],"type":"Point"}
}