{
  "type": "Feature",
  "properties": {
    "iso:country":"US",
    "sg:address":"5849 Dasher Ct",
    "sg:city":"Port Richey",
    "sg:classifiers":[
        {
            "category":"Professional",
            "subcategory":"Management & Consulting",
            "type":"Services"
        },
        {
            "category":"Wholesale",
            "subcategory":"Durable Goods & Equipment",
            "type":"Manufacturing & Wholesale Goods"
        }
    ],
    "sg:phone":"+1 727 834 9400",
    "sg:postcode":"34668",
    "sg:province":"FL",
    "sg:tags":[
        "design",
        "importer",
        "frequency",
        "radio",
        "unit"
    ],
    "wof:name":"Next Generation Home Products",
    "wof:placetype":"venue"
},
  "geometry": {"coordinates":[-82.717251,28.276518],"type":"Point"}
}