{
  "type": "Feature",
  "properties": {
    "iso:country":"US",
    "sg:address":"11250 NW 20th St",
    "sg:city":"Miami",
    "sg:classifiers":[
        {
            "category":"Real Estate",
            "subcategory":"Real Estate Services",
            "type":"Services"
        }
    ],
    "sg:phone":"+1 305 663 0313",
    "sg:postcode":"33172",
    "sg:province":"FL",
    "sg:website":"www.goldcoastschools.com",
    "wof:name":"Gold Coast School of Real Estate",
    "wof:placetype":"venue"
},
  "geometry": {"coordinates":[-80.380353,25.791333],"type":"Point"}
}