{
  "type": "Feature",
  "properties": {
    "iso:country":"US",
    "sg:address":"1100 Crosswinds Lndg",
    "sg:city":"Fort Walton Beach",
    "sg:classifiers":[
        {
            "category":"Real Estate",
            "subcategory":"Real Estate Operator",
            "type":"Services"
        }
    ],
    "sg:phone":"+1 850 864 5350",
    "sg:postcode":"32547",
    "sg:province":"FL",
    "sg:tags":[
        "dwelling"
    ],
    "wof:name":"Nancy W McIntosh",
    "wof:placetype":"venue"
},
  "geometry": {"coordinates":[-86.635549,30.458394],"type":"Point"}
}