{
  "type": "Feature",
  "properties": {
    "iso:country":"US",
    "sg:address":"211 Austin St",
    "sg:city":"Longwood",
    "sg:classifiers":[
        {
            "category":"Building & Trades",
            "subcategory":"Construction",
            "type":"Services"
        }
    ],
    "sg:phone":"+1 407 328 6716",
    "sg:postcode":"32750",
    "sg:province":"FL",
    "sg:tags":[
        "floor",
        "laying",
        "contractor"
    ],
    "wof:name":"Prime Flooring Inc",
    "wof:placetype":"venue"
},
  "geometry": {"coordinates":[-81.32485,28.733923],"type":"Point"}
}