{
  "type": "Feature",
  "properties": {
    "addr:full":"9484 S Orange Blossom Trl Orlando FL 32837",
    "addr:housenumber":"9484",
    "addr:postcode":"32837",
    "addr:street":"S Orange Blossom Trl",
    "iso:country":"US",
    "sg:address":"9484 S Orange Blossom Trl",
    "sg:city":"Orlando",
    "sg:classifiers":[
        {
            "category":"Shopping",
            "subcategory":"Party Supplies",
            "type":"Retail Goods"
        },
        {
            "category":"Shopping",
            "subcategory":"Bridal",
            "type":"Retail Goods"
        }
    ],
    "sg:phone":"+1 407 854 0259",
    "sg:postcode":"32837",
    "sg:province":"FL",
    "sg:tags":[
        "shop",
        "wedding"
    ],
    "sg:website":"http://discountbridal.org",
    "wof:name":"Ever After Formal Wear Inc",
    "wof:placetype":"venue"
},
  "geometry": {"coordinates":[-81.40471599999999,28.422704],"type":"Point"}
}