{
  "type": "Feature",
  "properties": {
    "iso:country":"US",
    "sg:address":"14 San Sebastian Ave",
    "sg:city":"Miami",
    "sg:classifiers":[
        {
            "category":"Professional",
            "subcategory":"Lawyer & Legal Services",
            "type":"Services"
        }
    ],
    "sg:phone":"+1 305 442 8605",
    "sg:postcode":"33134",
    "sg:province":"FL",
    "wof:name":"Todd M Wernstrom",
    "wof:placetype":"venue"
},
  "geometry": {"coordinates":[-80.25622300000001,25.74268],"type":"Point"}
}