{
  "type": "Feature",
  "properties": {
    "iso:country":"US",
    "sg:address":"1142 Coral Way",
    "sg:city":"Coral Gables",
    "sg:classifiers":[
        {
            "category":"Education",
            "subcategory":"Preschool",
            "type":"Public Place"
        },
        {
            "category":"Education",
            "subcategory":"School",
            "type":"Public Place"
        }
    ],
    "sg:phone":"+1 305 444 6366",
    "sg:postcode":"33134",
    "sg:province":"FL",
    "sg:tags":[
        "elementary"
    ],
    "wof:name":"St Philip's Episcopal School",
    "wof:placetype":"venue"
},
  "geometry": {"coordinates":[-80.27889999999999,25.7488],"type":"Point"}
}