{
  "type": "Feature",
  "properties": {
    "iso:country":"US",
    "sg:address":"2482 W Brandon Blvd",
    "sg:city":"Brandon",
    "sg:classifiers":[
        {
            "category":"Shopping",
            "subcategory":"Gifts & Souvenirs",
            "type":"Retail Goods"
        }
    ],
    "sg:phone":"+1 813 654 7788",
    "sg:postcode":"33511",
    "sg:province":"FL",
    "sg:tags":[
        "shop"
    ],
    "wof:name":"One Eagle Place",
    "wof:placetype":"venue"
},
  "geometry": {"coordinates":[-82.323097,27.939063],"type":"Point"}
}