{
  "type": "Feature",
  "properties": {
    "iso:country":"US",
    "sg:address":"3781 SE Canvasback Pl",
    "sg:city":"Stuart",
    "sg:classifiers":[
        {
            "category":"Building & Trades",
            "subcategory":"Cleaning & Sanitation",
            "type":"Services"
        }
    ],
    "sg:phone":"+1 772 223 1874",
    "sg:postcode":"34997",
    "sg:province":"FL",
    "sg:tags":[
        "maintenance"
    ],
    "wof:name":"Pioneer Services",
    "wof:placetype":"venue"
},
  "geometry": {"coordinates":[-80.20451,27.123721],"type":"Point"}
}