{
  "type": "Feature",
  "properties": {
    "iso:country":"US",
    "sg:address":"2807 Imperial Point Ter",
    "sg:city":"Clermont",
    "sg:classifiers":[
        {
            "category":"Professional",
            "subcategory":"Detective & Security Services",
            "type":"Services"
        }
    ],
    "sg:phone":"+1 352 243 1873",
    "sg:postcode":"34711",
    "sg:province":"FL",
    "sg:tags":[
        "equipment",
        "system",
        "consultant"
    ],
    "wof:name":"Ultra Guard Security Systems",
    "wof:placetype":"venue"
},
  "geometry": {"coordinates":[-81.700299,28.497035],"type":"Point"}
}