{
  "type": "Feature",
  "properties": {
    "iso:country":"US",
    "sg:address":"6736 Gall Blvd",
    "sg:city":"Zephyrhills",
    "sg:classifiers":[
        {
            "category":"Travel",
            "subcategory":"Hotels & Motels",
            "type":"Entertainment"
        }
    ],
    "sg:phone":"+1 813 782 1214",
    "sg:postcode":"33542",
    "sg:province":"FL",
    "sg:tags":[
        "operation",
        "business"
    ],
    "wof:name":"Crystal Springs Motor Inn",
    "wof:placetype":"venue"
},
  "geometry": {"coordinates":[-82.188119,28.25562],"type":"Point"}
}