{
  "type": "Feature",
  "properties": {
    "iso:country":"US",
    "sg:address":"1261 Eglin Pkwy",
    "sg:city":"Shalimar",
    "sg:classifiers":[
        {
            "category":"Insurance",
            "subcategory":"Hazard Insurance",
            "type":"Services"
        },
        {
            "category":"Professional",
            "subcategory":"Business Services",
            "type":"Services"
        }
    ],
    "sg:phone":"+1 850 651 1644",
    "sg:postcode":"32579",
    "sg:province":"FL",
    "sg:tags":[
        "bond"
    ],
    "sg:website":"www.battlesbailbonds.com",
    "wof:name":"Battles Bail Bonds",
    "wof:placetype":"venue"
},
  "geometry": {"coordinates":[-86.579053,30.446642],"type":"Point"}
}