{
  "type": "Feature",
  "properties": {
    "iso:country":"US",
    "sg:address":"7150 W 20th Ave",
    "sg:city":"Hialeah",
    "sg:classifiers":[
        {
            "category":"Health Services",
            "subcategory":"Doctor",
            "type":"Services"
        }
    ],
    "sg:phone":"+1 305 822 9035",
    "sg:postcode":"33016",
    "sg:province":"FL",
    "wof:name":"Hillman Edward J MD",
    "wof:placetype":"venue"
},
  "geometry": {"coordinates":[-80.324573,25.886612],"type":"Point"}
}