{
  "type": "Feature",
  "properties": {
    "iso:country":"US",
    "sg:address":"1243 Gondola Ln",
    "sg:city":"Boynton Beach",
    "sg:classifiers":[
        {
            "category":"Retail",
            "subcategory":"Auto Repair",
            "type":"Services"
        }
    ],
    "sg:phone":"+1 561 742 0624",
    "sg:postcode":"33426",
    "sg:province":"FL",
    "sg:tags":[
        "body"
    ],
    "wof:name":"Franche Custom Trim Inc",
    "wof:placetype":"venue"
},
  "geometry": {"coordinates":[-80.087163,26.52994],"type":"Point"}
}