{
  "type": "Feature",
  "properties": {
    "iso:country":"US",
    "sg:address":"701 Lincoln Rd",
    "sg:city":"Miami Beach",
    "sg:classifiers":[
        {
            "category":"Health Services",
            "subcategory":"Doctor",
            "type":"Services"
        }
    ],
    "sg:phone":"+1 305 558 7393",
    "sg:postcode":"33139",
    "sg:province":"FL",
    "sg:tags":[
        "physician",
        "surgeon"
    ],
    "wof:name":"Jose E Ribas MD",
    "wof:placetype":"venue"
},
  "geometry": {"coordinates":[-80.136551,25.790554],"type":"Point"}
}