{
  "type": "Feature",
  "properties": {
    "iso:country":"US",
    "sg:address":"8213 Shubert St",
    "sg:city":"Orlando",
    "sg:classifiers":[
        {
            "category":"Insurance",
            "subcategory":"Insurance Agent",
            "type":"Services"
        }
    ],
    "sg:phone":"+1 407 299 1796",
    "sg:postcode":"32818",
    "sg:province":"FL",
    "wof:name":"Gary D Mullins",
    "wof:placetype":"venue"
},
  "geometry": {"coordinates":[-81.499661,28.609738],"type":"Point"}
}