{
  "type": "Feature",
  "properties": {
    "addr:full":"17560 Atlantic Blvd Miami FL 33160",
    "addr:housenumber":"17560",
    "addr:postcode":"33160",
    "addr:street":"Atlantic Blvd",
    "iso:country":"US",
    "sg:address":"17560 Atlantic Blvd",
    "sg:city":"Miami",
    "sg:classifiers":[
        {
            "category":"Manufacturing",
            "subcategory":"Printing",
            "type":"Manufacturing & Wholesale Goods"
        }
    ],
    "sg:phone":"+1 305 932 4556",
    "sg:postcode":"33160",
    "sg:province":"FL",
    "sg:tags":[
        "lithographic",
        "commercial"
    ],
    "wof:name":"Voice Image Press Cmmnications",
    "wof:placetype":"venue"
},
  "geometry": {"coordinates":[-80.122713,25.939215],"type":"Point"}
}