{
  "type": "Feature",
  "properties": {
    "iso:country":"US",
    "sg:address":"5870 Miami Lakes Dr E",
    "sg:city":"Hialeah",
    "sg:classifiers":[
        {
            "category":"Wholesale",
            "subcategory":"Furniture",
            "type":"Manufacturing & Wholesale Goods"
        }
    ],
    "sg:phone":"+1 305 826 1255",
    "sg:postcode":"33014",
    "sg:province":"FL",
    "sg:tags":[
        "computer"
    ],
    "wof:name":"Rta Products LLC",
    "wof:placetype":"venue"
},
  "geometry": {"coordinates":[-80.294971,25.909664],"type":"Point"}
}