{
  "type": "Feature",
  "properties": {
    "iso:country":"US",
    "sg:address":"2720 N Harbor City Blvd",
    "sg:city":"Melbourne",
    "sg:classifiers":[
        {
            "category":"Banks & Credit Unions",
            "subcategory":"Bank",
            "type":"Services"
        }
    ],
    "sg:phone":"+1 321 757 3570",
    "sg:postcode":"32935",
    "sg:province":"FL",
    "sg:tags":[
        "loan",
        "real estate"
    ],
    "wof:name":"Morgan Financial",
    "wof:placetype":"venue"
},
  "geometry": {"coordinates":[-80.638603,28.148392],"type":"Point"}
}