{
  "type": "Feature",
  "properties": {
    "addr:full":"326 N Magnolia Ave Orlando FL 32801",
    "addr:housenumber":"326",
    "addr:postcode":"32801",
    "addr:street":"N Magnolia Ave",
    "iso:country":"US",
    "sg:address":"326 N Magnolia Ave",
    "sg:city":"Orlando",
    "sg:classifiers":[
        {
            "category":"Professional",
            "type":"Services"
        }
    ],
    "sg:phone":"+1 407 899 0000",
    "sg:postcode":"32801",
    "sg:province":"FL",
    "sg:tags":[
        "paging",
        "signaling"
    ],
    "wof:name":"Mobilecomm Inc",
    "wof:placetype":"venue"
},
  "geometry": {"coordinates":[-81.377579,28.545775],"type":"Point"}
}