{
  "type": "Feature",
  "properties": {
    "addr:full":"16541 Nacombs Ln Spring Hill FL 34610",
    "addr:housenumber":"16541",
    "addr:postcode":"34610",
    "addr:street":"Nacombs Ln",
    "iso:country":"US",
    "sg:address":"16541 Nacombs Ln",
    "sg:city":"Spring Hill",
    "sg:classifiers":[
        {
            "category":"Wholesale",
            "subcategory":"Vending Machines",
            "type":"Manufacturing & Wholesale Goods"
        }
    ],
    "sg:phone":"+1 727 856 4133",
    "sg:postcode":"34610",
    "sg:province":"FL",
    "sg:tags":[
        "operator"
    ],
    "wof:name":"Avanti Vending Services",
    "wof:placetype":"venue"
},
  "geometry": {"coordinates":[-82.541804,28.418314],"type":"Point"}
}