{
  "type": "Feature",
  "properties": {
    "addr:full":"710 Cypress Gardens Blvd Winter Haven FL 33880",
    "addr:housenumber":"710",
    "addr:postcode":"33880",
    "addr:street":"Cypress Gardens Blvd",
    "iso:country":"US",
    "sg:address":"710 Cypress Gardens Blvd",
    "sg:city":"Winter Haven",
    "sg:classifiers":[
        {
            "category":"Professional",
            "subcategory":"Business Services",
            "type":"Services"
        }
    ],
    "sg:phone":"+1 863 401 8492",
    "sg:postcode":"33880",
    "sg:province":"FL",
    "sg:tags":[
        "appraiser"
    ],
    "wof:name":"Treasure Hunters Isa Prsnl",
    "wof:placetype":"venue"
},
  "geometry": {"coordinates":[-81.717225,28.004136],"type":"Point"}
}