{
  "type": "Feature",
  "properties": {
    "iso:country":"US",
    "sg:address":"9140 Bonita Beach Rd",
    "sg:city":"Bonita Springs",
    "sg:classifiers":[
        {
            "category":"Professional",
            "subcategory":"Business Services",
            "type":"Services"
        }
    ],
    "sg:phone":"+1 239 947 6717",
    "sg:postcode":"34135",
    "sg:province":"FL",
    "sg:tags":[
        "notary"
    ],
    "wof:name":"Quick Pack & Ship",
    "wof:placetype":"venue"
},
  "geometry": {"coordinates":[-81.799744,26.330662],"type":"Point"}
}