{
  "type": "Feature",
  "properties": {
    "iso:country":"US",
    "sg:address":"2201 Elkton Ct",
    "sg:city":"Fort Myers",
    "sg:classifiers":[
        {
            "category":"Shopping",
            "subcategory":"Jewelry",
            "type":"Retail Goods"
        }
    ],
    "sg:phone":"+1 239 275 1993",
    "sg:postcode":"33907",
    "sg:province":"FL",
    "wof:name":"Judy Dominek Fine Jewelry Appraisal Services",
    "wof:placetype":"venue"
},
  "geometry": {"coordinates":[-81.864998,26.5709],"type":"Point"}
}