{
  "type": "Feature",
  "properties": {
    "iso:country":"US",
    "sg:address":"1337 Blossom Cir",
    "sg:city":"Tallahassee",
    "sg:classifiers":[
        {
            "category":"Organizations",
            "subcategory":"Religious Organization",
            "type":"Services"
        }
    ],
    "sg:phone":"+1 850 576 3651",
    "sg:postcode":"32305",
    "sg:province":"FL",
    "wof:name":"Horace Smith Ministries Inc",
    "wof:placetype":"venue"
},
  "geometry": {"coordinates":[-84.305239,30.405798],"type":"Point"}
}