{
  "type": "Feature",
  "properties": {
    "iso:country":"US",
    "sg:address":"3101 Pga Blvd",
    "sg:city":"Palm Beach Gdns",
    "sg:classifiers":[
        {
            "category":"Shopping",
            "subcategory":"Clothing, Apparel, & Fashions",
            "type":"Retail Goods"
        }
    ],
    "sg:phone":"+1 561 775 0383",
    "sg:postcode":"33410",
    "sg:province":"FL",
    "sg:tags":[
        "furnishing"
    ],
    "wof:name":"Brooks Brothers",
    "wof:placetype":"venue"
},
  "geometry": {"coordinates":[-80.085559,26.845069],"type":"Point"}
}