{
  "type": "Feature",
  "properties": {
    "addr:full":"1099 Shadick Dr Orange City FL 32763",
    "addr:housenumber":"1099",
    "addr:postcode":"32763",
    "addr:street":"Shadick Dr",
    "iso:country":"US",
    "sg:address":"1099 Shadick Dr",
    "sg:city":"Orange City",
    "sg:classifiers":[
        {
            "category":"Building & Trades",
            "subcategory":"Plumbing",
            "type":"Services"
        }
    ],
    "sg:phone":"+1 386 775 2521",
    "sg:postcode":"32763",
    "sg:province":"FL",
    "sg:tags":[
        "air",
        "heating",
        "conditioning",
        "contractor"
    ],
    "wof:name":"Von-Aire Inc",
    "wof:placetype":"venue"
},
  "geometry": {"coordinates":[-81.28482200000001,28.93871],"type":"Point"}
}