{
  "type": "Feature",
  "properties": {
    "iso:country":"US",
    "sg:address":"4410 W Newberry Rd Ste A4",
    "sg:city":"Gainesville",
    "sg:classifiers":[
        {
            "category":"Health Services",
            "subcategory":"Clinic",
            "type":"Services"
        }
    ],
    "sg:phone":"+1 352 374 2818",
    "sg:postcode":"32607",
    "sg:province":"FL",
    "sg:tags":[
        "welfare"
    ],
    "wof:name":"Lewis Health Care",
    "wof:placetype":"venue"
},
  "geometry": {"coordinates":[-82.36444899999999,29.650435],"type":"Point"}
}