{
  "type": "Feature",
  "properties": {
    "iso:country":"US",
    "sg:address":"360 Wilshire Blvd",
    "sg:city":"Casselberry",
    "sg:classifiers":[
        {
            "category":"Insurance",
            "subcategory":"Hazard Insurance",
            "type":"Services"
        }
    ],
    "sg:phone":"+1 407 261 2363",
    "sg:postcode":"32707",
    "sg:province":"FL",
    "wof:name":"B & L Insurance Agency",
    "wof:placetype":"venue"
},
  "geometry": {"coordinates":[-81.329983,28.649729],"type":"Point"}
}