{
  "type": "Feature",
  "properties": {
    "iso:country":"US",
    "sg:address":"23454 SW Tiger Lake Blvd",
    "sg:city":"Dunnellon",
    "sg:classifiers":[
        {
            "category":"Building & Trades",
            "subcategory":"Construction",
            "type":"Services"
        }
    ],
    "sg:phone":"+1 352 465 3129",
    "sg:postcode":"34431",
    "sg:province":"FL",
    "sg:tags":[
        "contractor"
    ],
    "wof:name":"X Stream Pressure",
    "wof:placetype":"venue"
},
  "geometry": {"coordinates":[-82.508261,29.127482],"type":"Point"}
}