{
  "type": "Feature",
  "properties": {
    "iso:country":"US",
    "sg:address":"765 Cortaro Dr",
    "sg:city":"Ruskin",
    "sg:classifiers":[
        {
            "category":"Shopping",
            "subcategory":"Musical Instruments",
            "type":"Retail Goods"
        }
    ],
    "sg:phone":"+1 813 633 9688",
    "sg:postcode":"33573",
    "sg:province":"FL",
    "sg:tags":[
        "organs"
    ],
    "wof:name":"Organ Orphanage",
    "wof:placetype":"venue"
},
  "geometry": {"coordinates":[-82.37106900000001,27.714223],"type":"Point"}
}