{
  "type": "Feature",
  "properties": {
    "addr:full":"1526 51st Ave E Ellenton FL 34222",
    "addr:housenumber":"1526",
    "addr:postcode":"34222",
    "addr:street":"51St Ave E",
    "iso:country":"US",
    "sg:address":"1526 51st Ave E",
    "sg:city":"Ellenton",
    "sg:classifiers":[
        {
            "category":"Restaurant",
            "type":"Food & Drink"
        }
    ],
    "sg:phone":"+1 941 722 7970",
    "sg:postcode":"34222",
    "sg:province":"FL",
    "sg:tags":[
        "eating"
    ],
    "wof:name":"Subway",
    "wof:placetype":"venue"
},
  "geometry": {"coordinates":[-82.51281400000001,27.528453],"type":"Point"}
}