{
  "type": "Feature",
  "properties": {
    "addr:full":"9526 Argyle Forest Blvd B2 Jacksonville FL 32222",
    "addr:housenumber":"9526",
    "addr:postcode":"b2;32222",
    "addr:street":"Argyle Forest Blvd",
    "iso:country":"US",
    "sg:address":"9526 Argyle Forest Blvd B2",
    "sg:city":"Jacksonville",
    "sg:classifiers":[
        {
            "category":"Food & Beverages",
            "subcategory":"Specialty",
            "type":"Retail Goods"
        }
    ],
    "sg:phone":"+1 904 755 8932",
    "sg:postcode":"32222",
    "sg:province":"FL",
    "sg:tags":[
        "product",
        "health",
        "diet"
    ],
    "wof:name":"Gnchomeinvestors",
    "wof:placetype":"venue"
},
  "geometry": {"coordinates":[-81.826183,30.195641],"type":"Point"}
}