{
  "type": "Feature",
  "properties": {
    "iso:country":"US",
    "sg:address":"6150 S Congress Ave",
    "sg:city":"Lantana",
    "sg:classifiers":[
        {
            "category":"Restaurant",
            "type":"Food & Drink"
        }
    ],
    "sg:phone":"+1 561 642 5334",
    "sg:postcode":"33462",
    "sg:province":"FL",
    "wof:name":"Beauvais Carribean Restaurant",
    "wof:placetype":"venue"
},
  "geometry": {"coordinates":[-80.093874,26.586606],"type":"Point"}
}