{
  "type": "Feature",
  "properties": {
    "addr:full":"7355 Rosewood Cir Boca Raton FL 33487",
    "addr:housenumber":"7355",
    "addr:postcode":"33487",
    "addr:street":"Rosewood Cir",
    "iso:country":"US",
    "sg:address":"7355 Rosewood Cir",
    "sg:city":"Boca Raton",
    "sg:classifiers":[
        {
            "category":"Building & Trades",
            "subcategory":"Construction",
            "type":"Services"
        }
    ],
    "sg:phone":"+1 561 997 2403",
    "sg:postcode":"33487",
    "sg:province":"FL",
    "sg:tags":[
        "carpenter"
    ],
    "wof:name":"Brian L Campbell Carpentry",
    "wof:placetype":"venue"
},
  "geometry": {"coordinates":[-80.086637,26.417181],"type":"Point"}
}