{
  "type": "Feature",
  "properties": {
    "addr:full":"637 S 6th Ave Wauchula FL 33873",
    "addr:housenumber":"637",
    "addr:postcode":"33873",
    "addr:street":"S 6Th Ave",
    "iso:country":"US",
    "sg:address":"637 S 6th Ave",
    "sg:city":"Wauchula",
    "sg:classifiers":[
        {
            "category":"Wholesale",
            "subcategory":"Fruits & Vegetables",
            "type":"Manufacturing & Wholesale Goods"
        }
    ],
    "sg:phone":"+1 863 773 5708",
    "sg:postcode":"33873",
    "sg:province":"FL",
    "wof:name":"Sevart & Sons",
    "wof:placetype":"venue"
},
  "geometry": {"coordinates":[-81.810153,27.541069],"type":"Point"}
}