{
  "type": "Feature",
  "properties": {
    "addr:full":"8680 Commodity Cir Orlando FL 32819",
    "addr:housenumber":"8680",
    "addr:postcode":"32819",
    "addr:street":"Commodity Cir",
    "iso:country":"US",
    "sg:address":"8680 Commodity Cir",
    "sg:city":"Orlando",
    "sg:classifiers":[
        {
            "category":"Real Estate",
            "subcategory":"Developer",
            "type":"Services"
        }
    ],
    "sg:phone":"+1 407 859 8900",
    "sg:postcode":"32819",
    "sg:province":"FL",
    "wof:name":"Crescent One",
    "wof:placetype":"venue"
},
  "geometry": {"coordinates":[-81.429957,28.446386],"type":"Point"}
}