{
  "type": "Feature",
  "properties": {
    "iso:country":"US",
    "sg:address":"4646 Parkmore Plaza Dr",
    "sg:city":"Milton",
    "sg:classifiers":[
        {
            "category":"Building & Trades",
            "subcategory":"Construction",
            "type":"Services"
        }
    ],
    "sg:phone":"+1 850 626 0391",
    "sg:postcode":"32570",
    "sg:province":"FL",
    "sg:tags":[
        "roofing",
        "contractor"
    ],
    "wof:name":"Salter Roofing Co",
    "wof:placetype":"venue"
},
  "geometry": {"coordinates":[-87.064668,30.60376],"type":"Point"}
}