{
  "type": "Feature",
  "properties": {
    "iso:country":"US",
    "sg:address":"1518 W Vine St",
    "sg:city":"Kissimmee",
    "sg:classifiers":[
        {
            "category":"Real Estate",
            "subcategory":"Real Estate Agent",
            "type":"Services"
        }
    ],
    "sg:phone":"+1 407 847 8811",
    "sg:postcode":"34741",
    "sg:province":"FL",
    "wof:name":"IPG Realty",
    "wof:placetype":"venue"
},
  "geometry": {"coordinates":[-81.41907999999999,28.304475],"type":"Point"}
}