{
  "type": "Feature",
  "properties": {
    "addr:full":"811 Cypress Village Blvd Ruskin FL 33573",
    "addr:housenumber":"811",
    "addr:postcode":"33573",
    "addr:street":"Cypress Village Blvd",
    "iso:country":"US",
    "sg:address":"811 Cypress Village Blvd",
    "sg:city":"Ruskin",
    "sg:classifiers":[
        {
            "category":"Insurance",
            "subcategory":"Title Insurance",
            "type":"Services"
        }
    ],
    "sg:phone":"+1 813 633 3330",
    "sg:postcode":"33573",
    "sg:province":"FL",
    "wof:name":"South Bay Title Insurance Inc",
    "wof:placetype":"venue"
},
  "geometry": {"coordinates":[-82.381028,27.722446],"type":"Point"}
}