{
  "type": "Feature",
  "properties": {
    "iso:country":"US",
    "sg:address":"13095 NE 44th Ct",
    "sg:city":"Anthony",
    "sg:classifiers":[
        {
            "category":"Building & Trades",
            "subcategory":"Electrical",
            "type":"Services"
        }
    ],
    "sg:phone":"+1 352 622 5722",
    "sg:postcode":"32617",
    "sg:province":"FL",
    "sg:tags":[
        "electrician"
    ],
    "wof:name":"Hurricane Electric Company Inc",
    "wof:placetype":"venue"
},
  "geometry": {"coordinates":[-82.075391,29.340606],"type":"Point"}
}