{
  "type": "Feature",
  "properties": {
    "addr:full":"1843 S Tamiami Trl Osprey FL 34229",
    "addr:housenumber":"1843",
    "addr:postcode":"34229",
    "addr:street":"S Tamiami Trl Osprey",
    "iso:country":"US",
    "sg:address":"1843 S Tamiami Trl",
    "sg:city":"Osprey",
    "sg:classifiers":[
        {
            "category":"Recreation",
            "type":"Entertainment"
        }
    ],
    "sg:phone":"+1 941 483 5944",
    "sg:postcode":"34229",
    "sg:province":"FL",
    "sg:tags":[
        "parks"
    ],
    "sg:website":"www.stateparks.org",
    "wof:name":"Parks & Recreation",
    "wof:placetype":"venue"
},
  "geometry": {"coordinates":[-82.490111,27.216259],"type":"Point"}
}