{
  "type": "Feature",
  "properties": {
    "addr:full":"10735 SW 216th St Miami FL 33170",
    "addr:housenumber":"10735",
    "addr:postcode":"33170",
    "addr:street":"Sw 216Th St",
    "iso:country":"US",
    "sg:address":"10735 SW 216th St",
    "sg:city":"Miami",
    "sg:classifiers":[
        {
            "category":"Organizations",
            "subcategory":"Religious Organization",
            "type":"Services"
        }
    ],
    "sg:phone":"+1 305 278 3927",
    "sg:postcode":"33170",
    "sg:province":"FL",
    "sg:tags":[
        "church"
    ],
    "wof:name":"Holy Ghost Tabernacle",
    "wof:placetype":"venue"
},
  "geometry": {"coordinates":[-80.364656,25.566609],"type":"Point"}
}