{
  "type": "Feature",
  "properties": {
    "iso:country":"US",
    "sg:address":"515 Habitat Blvd",
    "sg:city":"Osprey",
    "sg:classifiers":[
        {
            "category":"Building & Trades",
            "subcategory":"Construction",
            "type":"Services"
        }
    ],
    "sg:phone":"+1 941 966 3035",
    "sg:postcode":"34229",
    "sg:province":"FL",
    "sg:tags":[
        "home",
        "builder"
    ],
    "wof:name":"Lee Wetherington Homes",
    "wof:placetype":"venue"
},
  "geometry": {"coordinates":[-82.476671,27.178506],"type":"Point"}
}