{
  "type": "Feature",
  "properties": {
    "addr:full":"4510 E 10th Ln Hialeah FL 33013",
    "addr:housenumber":"4510",
    "addr:postcode":"33013",
    "addr:street":"E 10Th Ln",
    "iso:country":"US",
    "sg:address":"4510 E 10th Ln",
    "sg:city":"Hialeah",
    "sg:classifiers":[
        {
            "category":"Autos & Motor Vehicles",
            "subcategory":"Boat Sales",
            "type":"Retail Goods"
        },
        {
            "category":"Manufacturing",
            "subcategory":"Watercraft",
            "type":"Manufacturing & Wholesale Goods"
        }
    ],
    "sg:phone":"+1 305 753 2397",
    "sg:postcode":"33013",
    "sg:province":"FL",
    "sg:tags":[
        "distributor",
        "builder",
        "manufacturer"
    ],
    "sg:website":"http://www.competitionboats.com/",
    "wof:name":"Competition Boats",
    "wof:placetype":"venue"
},
  "geometry": {"coordinates":[-80.261385,25.86387],"type":"Point"}
}