{
  "type": "Feature",
  "properties": {
    "iso:country":"US",
    "sg:address":"11626 Columbia Park Dr W",
    "sg:city":"Jacksonville",
    "sg:classifiers":[
        {
            "category":"Wholesale",
            "subcategory":"Machinery & Supplies",
            "type":"Manufacturing & Wholesale Goods"
        }
    ],
    "sg:phone":"+1 904 260 4003",
    "sg:postcode":"32258",
    "sg:province":"FL",
    "sg:tags":[
        "rotating",
        "equipment"
    ],
    "wof:name":"Turbocare Inc",
    "wof:placetype":"venue"
},
  "geometry": {"coordinates":[-81.53920599999999,30.156216],"type":"Point"}
}