{
  "type": "Feature",
  "properties": {
    "iso:country":"US",
    "sg:address":"5537 8th St SW",
    "sg:city":"Coral Gables",
    "sg:classifiers":[
        {
            "category":"Insurance",
            "subcategory":"Insurance Agent",
            "type":"Services"
        }
    ],
    "sg:phone":"+1 305 267 9314",
    "sg:postcode":"33134",
    "sg:province":"FL",
    "wof:name":"Blue Moon Insurance Corp",
    "wof:placetype":"venue"
},
  "geometry": {"coordinates":[-80.285022,25.763745],"type":"Point"}
}