{
  "type": "Feature",
  "properties": {
    "iso:country":"US",
    "sg:address":"4565 Duhme Rd",
    "sg:city":"St Petersburg",
    "sg:classifiers":[
        {
            "category":"Personal",
            "type":"Services"
        }
    ],
    "sg:phone":"+1 727 392 1233",
    "sg:postcode":"33708",
    "sg:province":"FL",
    "sg:tags":[
        "therapist",
        "massage"
    ],
    "wof:name":"Health Touch",
    "wof:placetype":"venue"
},
  "geometry": {"coordinates":[-82.79338,27.812859],"type":"Point"}
}