{
  "type": "Feature",
  "properties": {
    "iso:country":"US",
    "sg:address":"2721 Forsyth Rd",
    "sg:city":"Winter Park",
    "sg:classifiers":[
        {
            "category":"Wholesale",
            "subcategory":"Durable Goods & Equipment",
            "type":"Manufacturing & Wholesale Goods"
        },
        {
            "category":"Manufacturing",
            "subcategory":"Tools & Machinery",
            "type":"Manufacturing & Wholesale Goods"
        }
    ],
    "sg:phone":"+1 407 679 3395",
    "sg:postcode":"32792",
    "sg:province":"FL",
    "sg:tags":[
        "laser",
        "system",
        "mfg"
    ],
    "wof:name":"A C Materials Inc",
    "wof:placetype":"venue"
},
  "geometry": {"coordinates":[-81.294568,28.586615],"type":"Point"}
}