{
  "type": "Feature",
  "properties": {
    "iso:country":"US",
    "sg:address":"15076 SW 51st St",
    "sg:city":"Fort Lauderdale",
    "sg:classifiers":[
        {
            "category":"Wholesale",
            "subcategory":"Non-durable Goods",
            "type":"Manufacturing & Wholesale Goods"
        }
    ],
    "sg:phone":"+1 954 880 0542",
    "sg:postcode":"33331",
    "sg:province":"FL",
    "wof:name":"Authentic African Imports Inc",
    "wof:placetype":"venue"
},
  "geometry": {"coordinates":[-80.34889800000001,26.057483],"type":"Point"}
}