{
  "type": "Feature",
  "properties": {
    "addr:full":"5127 Bloomingdale Ave Tampa FL 33619",
    "addr:housenumber":"5127",
    "addr:postcode":"33619",
    "addr:street":"Bloomingdale Ave",
    "iso:country":"US",
    "sg:address":"5127 Bloomingdale Ave",
    "sg:city":"Tampa",
    "sg:classifiers":[
        {
            "category":"Manufacturing",
            "subcategory":"Metals",
            "type":"Manufacturing & Wholesale Goods"
        }
    ],
    "sg:phone":"+1 813 677 7184",
    "sg:postcode":"33619",
    "sg:province":"FL",
    "sg:tags":[
        "bridge",
        "fabrication"
    ],
    "wof:name":"Tampa Steel Erecting Co",
    "wof:placetype":"venue"
},
  "geometry": {"coordinates":[-82.40012,27.893643],"type":"Point"}
}