{
  "type": "Feature",
  "properties": {
    "addr:full":"6097 Blueberry Ln Crestview FL 32536",
    "addr:housenumber":"6097",
    "addr:postcode":"32536",
    "addr:street":"Blueberry Ln",
    "iso:country":"US",
    "sg:address":"6097 Blueberry Ln",
    "sg:city":"Crestview",
    "sg:classifiers":[
        {
            "category":"Organizations",
            "subcategory":"Membership Organization",
            "type":"Services"
        }
    ],
    "sg:phone":"+1 850 682 7750",
    "sg:postcode":"32536",
    "sg:province":"FL",
    "wof:name":"Northwest Florida Visionaries",
    "wof:placetype":"venue"
},
  "geometry": {"coordinates":[-86.556415,30.816343],"type":"Point"}
}