{
  "type": "Feature",
  "properties": {
    "iso:country":"US",
    "sg:address":"1220 Linton Blvd",
    "sg:city":"Delray Beach",
    "sg:classifiers":[
        {
            "category":"Restaurant",
            "type":"Food & Drink"
        }
    ],
    "sg:menulink":"http://www.allmenus.com/fl/boynton-beach-delray-beach/187115-mcdonalds/menu/",
    "sg:phone":"+1 561 274 6858",
    "sg:postcode":"33444",
    "sg:province":"FL",
    "sg:tags":[
        "burger",
        "american"
    ],
    "wof:name":"McDonald's",
    "wof:placetype":"venue"
},
  "geometry": {"coordinates":[-80.085516,26.438958],"type":"Point"}
}