{
  "type": "Feature",
  "properties": {
    "addr:full":"9800 4th St N Saint Petersburg FL 33702",
    "addr:housenumber":"9800",
    "addr:postcode":"33702",
    "addr:street":"4Th St N",
    "iso:country":"US",
    "sg:address":"9800 4th St N",
    "sg:city":"Saint Petersburg",
    "sg:classifiers":[
        {
            "category":"Banks & Credit Unions",
            "subcategory":"Bank",
            "type":"Services"
        }
    ],
    "sg:phone":"+1 727 576 5600",
    "sg:postcode":"33702",
    "sg:province":"FL",
    "sg:tags":[
        "mortgage"
    ],
    "wof:name":"Union Planters Bank",
    "wof:placetype":"venue"
},
  "geometry": {"coordinates":[-82.638817,27.862136],"type":"Point"}
}