{
  "type": "Feature",
  "properties": {
    "iso:country":"US",
    "sg:address":"104 Woodmill Rd",
    "sg:city":"Longwood",
    "sg:classifiers":[
        {
            "category":"Professional",
            "type":"Services"
        },
        {
            "category":"Professional",
            "subcategory":"Advertising",
            "type":"Services"
        }
    ],
    "sg:phone":"+1 407 862 6566",
    "sg:postcode":"32779",
    "sg:province":"FL",
    "sg:tags":[
        "product",
        "fair",
        "trade",
        "exposition",
        "advertising-promotional",
        "shows"
    ],
    "wof:name":"Impak Enterprises",
    "wof:placetype":"venue"
},
  "geometry": {"coordinates":[-81.399062,28.691269],"type":"Point"}
}