{
  "type": "Feature",
  "properties": {
    "addr:full":"1380 W Flagler St Miami FL 33135",
    "addr:housenumber":"1380",
    "addr:postcode":"33135",
    "addr:street":"W Flagler St",
    "iso:country":"US",
    "sg:address":"1380 W Flagler St",
    "sg:city":"Miami",
    "sg:classifiers":[
        {
            "category":"Real Estate",
            "subcategory":"Real Estate Agent",
            "type":"Services"
        }
    ],
    "sg:phone":"+1 305 649 7755",
    "sg:postcode":"33135",
    "sg:province":"FL",
    "wof:name":"Peba 14th Street Property Inc",
    "wof:placetype":"venue"
},
  "geometry": {"coordinates":[-80.217159,25.773356],"type":"Point"}
}