{
  "type": "Feature",
  "properties": {
    "iso:country":"US",
    "sg:address":"31250 Singletary Rd",
    "sg:city":"Myakka City",
    "sg:classifiers":[
        {
            "category":"Building & Trades",
            "subcategory":"Construction",
            "type":"Services"
        }
    ],
    "sg:phone":"+1 941 322 6222",
    "sg:postcode":"34251",
    "sg:province":"FL",
    "sg:tags":[
        "concrete",
        "contractor"
    ],
    "wof:name":"Yoder Pumping LLC",
    "wof:placetype":"venue"
},
  "geometry": {"coordinates":[-82.221705,27.344341],"type":"Point"}
}