{
  "type": "Feature",
  "properties": {
    "addr:full":"11612 N Nebraska Ave Tampa FL 33612",
    "addr:housenumber":"11612",
    "addr:postcode":"33612",
    "addr:street":"N Nebraska Ave",
    "iso:country":"US",
    "sg:address":"11612 N Nebraska Ave",
    "sg:city":"Tampa",
    "sg:classifiers":[
        {
            "category":"Shopping",
            "subcategory":"Shoes",
            "type":"Retail Goods"
        }
    ],
    "sg:phone":"+1 813 971 9880",
    "sg:postcode":"33612",
    "sg:province":"FL",
    "wof:name":"Kim Nam",
    "wof:placetype":"venue"
},
  "geometry": {"coordinates":[-82.451268,28.054407],"type":"Point"}
}