{
  "type": "Feature",
  "properties": {
    "iso:country":"US",
    "sg:address":"525 Quail Pt",
    "sg:city":"Jupiter",
    "sg:classifiers":[
        {
            "category":"Real Estate",
            "subcategory":"Real Estate Agent",
            "type":"Services"
        }
    ],
    "sg:phone":"+1 561 745 6269",
    "sg:postcode":"33458",
    "sg:province":"FL",
    "wof:name":"Savery Realty Group LLC",
    "wof:placetype":"venue"
},
  "geometry": {"coordinates":[-80.13120499999999,26.905078],"type":"Point"}
}