{
  "type": "Feature",
  "properties": {
    "addr:full":"2242 Saye Dr E Jacksonville FL 32225",
    "addr:housenumber":"2242",
    "addr:postcode":"32225",
    "addr:street":"Saye Dr E",
    "iso:country":"US",
    "sg:address":"2242 Saye Dr E",
    "sg:city":"Jacksonville",
    "sg:classifiers":[
        {
            "category":"Real Estate",
            "subcategory":"Real Estate Agent",
            "type":"Services"
        }
    ],
    "sg:phone":"+1 904 620 8628",
    "sg:postcode":"32225",
    "sg:province":"FL",
    "sg:tags":[
        "appraiser"
    ],
    "wof:name":"First Coast Appraisal Svc Inc",
    "wof:placetype":"venue"
},
  "geometry": {"coordinates":[-81.54254899999999,30.357224],"type":"Point"}
}