{
  "type": "Feature",
  "properties": {
    "addr:full":"216 Richfield Dr Lake Placid FL 33852",
    "addr:housenumber":"216",
    "addr:postcode":"33852",
    "addr:street":"Richfield Dr",
    "iso:country":"US",
    "sg:address":"216 Richfield Dr",
    "sg:city":"Lake Placid",
    "sg:classifiers":[
        {
            "category":"Farming",
            "subcategory":"Farm & Veterinary Services",
            "type":"Manufacturing & Wholesale Goods"
        }
    ],
    "sg:phone":"+1 863 531 0001",
    "sg:postcode":"33852",
    "sg:province":"FL",
    "sg:tags":[
        "crop",
        "harvesting"
    ],
    "wof:name":"Jst Harvesting",
    "wof:placetype":"venue"
},
  "geometry": {"coordinates":[-81.362953,27.287812],"type":"Point"}
}