{
  "type": "Feature",
  "properties": {
    "iso:country":"US",
    "sg:address":"4419 W Estrella St",
    "sg:city":"Tampa",
    "sg:classifiers":[
        {
            "category":"Building & Trades",
            "subcategory":"Plumbing",
            "type":"Services"
        }
    ],
    "sg:phone":"+1 813 287 1088",
    "sg:postcode":"33629",
    "sg:province":"FL",
    "sg:tags":[
        "contractor",
        "mfg"
    ],
    "wof:name":"Carrier",
    "wof:placetype":"venue"
},
  "geometry": {"coordinates":[-82.519942,27.928566],"type":"Point"}
}