{
  "type": "Feature",
  "properties": {
    "addr:full":"1191 E Newport Center Dr Deerfield Beach FL 33442",
    "addr:housenumber":"1191",
    "addr:postcode":"33442",
    "addr:street":"E Newport Center Dr",
    "iso:country":"US",
    "sg:address":"1191 E Newport Center Dr",
    "sg:city":"Deerfield Beach",
    "sg:classifiers":[
        {
            "category":"Professional",
            "subcategory":"Employment Agencies",
            "type":"Services"
        }
    ],
    "sg:phone":"+1 954 570 8300",
    "sg:postcode":"33442",
    "sg:province":"FL",
    "sg:tags":[
        "temporary"
    ],
    "wof:name":"Unified Resources Inc",
    "wof:placetype":"venue"
},
  "geometry": {"coordinates":[-80.123718,26.301904],"type":"Point"}
}