{
  "type": "Feature",
  "properties": {
    "addr:full":"804 Sandringham Ln Lutz FL 33549",
    "addr:housenumber":"804",
    "addr:postcode":"33549",
    "addr:street":"Sandringham Ln",
    "iso:country":"US",
    "sg:address":"804 Sandringham Ln",
    "sg:city":"Lutz",
    "sg:classifiers":[
        {
            "category":"Professional",
            "subcategory":"Secretarial Services",
            "type":"Services"
        }
    ],
    "sg:phone":"+1 813 949 8344",
    "sg:postcode":"33549",
    "sg:province":"FL",
    "sg:tags":[
        "convention",
        "court",
        "reporter"
    ],
    "wof:name":"Freshour Reporting",
    "wof:placetype":"venue"
},
  "geometry": {"coordinates":[-82.453092,28.10693],"type":"Point"}
}