{
  "type": "Feature",
  "properties": {
    "iso:country":"US",
    "sg:address":"4925 SW 35th Ter",
    "sg:city":"Fort Lauderdale",
    "sg:classifiers":[
        {
            "category":"Restaurant",
            "type":"Food & Drink"
        }
    ],
    "sg:phone":"+1 954 986 7013",
    "sg:postcode":"33312",
    "sg:province":"FL",
    "sg:tags":[
        "eating"
    ],
    "wof:name":"Lankrys Kosher Gourmet Inc",
    "wof:placetype":"venue"
},
  "geometry": {"coordinates":[-80.192702,26.061224],"type":"Point"}
}