{
  "type": "Feature",
  "properties": {
    "iso:country":"US",
    "sg:address":"7800 Industrial Rd",
    "sg:city":"Melbourne",
    "sg:classifiers":[
        {
            "category":"Freight",
            "type":"Transportation"
        }
    ],
    "sg:phone":"+1 321 723 6500",
    "sg:postcode":"32904",
    "sg:province":"FL",
    "sg:tags":[
        "record",
        "general"
    ],
    "wof:name":"D'Ville Warehouses",
    "wof:placetype":"venue"
},
  "geometry": {"coordinates":[-80.67714700000001,28.098332],"type":"Point"}
}