{
  "type": "Feature",
  "properties": {
    "addr:full":"4101 NW 89th Blvd Gainesville FL 32606",
    "addr:housenumber":"4101",
    "addr:postcode":"32606",
    "addr:street":"Nw 89Th Blvd",
    "iso:country":"US",
    "sg:address":"4101 NW 89th Blvd",
    "sg:city":"Gainesville",
    "sg:classifiers":[
        {
            "category":"Health Services",
            "subcategory":"Doctor",
            "type":"Services"
        },
        {
            "category":"Health Services",
            "subcategory":"Hospital",
            "type":"Services"
        },
        {
            "category":"Health Services",
            "subcategory":"Health Practitioner",
            "type":"Services"
        },
        {
            "category":"Health Services",
            "subcategory":"Clinic",
            "type":"Services"
        }
    ],
    "sg:phone":"+1 352 265 5481",
    "sg:postcode":"32606",
    "sg:province":"FL",
    "sg:tags":[
        "physician",
        "information",
        "drug",
        "alcoholism",
        "abuse",
        "treatment",
        "surgeon",
        "addiction"
    ],
    "wof:name":"Florida Recovery Ctr",
    "wof:placetype":"venue"
},
  "geometry": {"coordinates":[-82.43692799999999,29.68895],"type":"Point"}
}