{
  "type": "Feature",
  "properties": {
    "iso:country":"US",
    "sg:address":"3814 S Kenwood Ave",
    "sg:city":"Tampa",
    "sg:classifiers":[
        {
            "category":"Building & Trades",
            "subcategory":"Construction",
            "type":"Services"
        }
    ],
    "sg:phone":"+1 813 832 5613",
    "sg:postcode":"33611",
    "sg:province":"FL",
    "sg:tags":[
        "residential"
    ],
    "wof:name":"Urban Estates Inc",
    "wof:placetype":"venue"
},
  "geometry": {"coordinates":[-82.49824599999999,27.906568],"type":"Point"}
}