{
  "type": "Feature",
  "properties": {
    "addr:full":"990 W 15th St Panama City FL 32401",
    "addr:housenumber":"990",
    "addr:postcode":"32401",
    "addr:street":"W 15Th St",
    "iso:country":"US",
    "sg:address":"990 W 15th St",
    "sg:city":"Panama City",
    "sg:classifiers":[
        {
            "category":"Autos & Motor Vehicles",
            "subcategory":"Automobile Sales",
            "type":"Retail Goods"
        }
    ],
    "sg:phone":"+1 850 747 7480",
    "sg:postcode":"32401",
    "sg:province":"FL",
    "sg:tags":[
        "car",
        "dealer"
    ],
    "wof:name":"Cook-Whitehead Ford",
    "wof:placetype":"venue"
},
  "geometry": {"coordinates":[-85.673777,30.175319],"type":"Point"}
}