{
  "type": "Feature",
  "properties": {
    "addr:full":"4562 State Hwy 20 Niceville FL 32578",
    "addr:housenumber":"4562",
    "addr:postcode":"32578",
    "addr:street":"State Hwy 20",
    "iso:country":"US",
    "sg:address":"4562 State Hwy 20",
    "sg:city":"Niceville",
    "sg:classifiers":[
        {
            "category":"Shopping",
            "subcategory":"Pharmacy",
            "type":"Retail Goods"
        }
    ],
    "sg:phone":"+1 850 897 8550",
    "sg:postcode":"32578",
    "sg:province":"FL",
    "wof:name":"Eckerd Drugs",
    "wof:placetype":"venue"
},
  "geometry": {"coordinates":[-86.418881,30.485165],"type":"Point"}
}