{
  "type": "Feature",
  "properties": {
    "iso:country":"US",
    "sg:address":"137 Hidden Springs Cir",
    "sg:city":"Kissimmee",
    "sg:classifiers":[
        {
            "category":"Building & Trades",
            "subcategory":"Cleaning & Sanitation",
            "type":"Services"
        }
    ],
    "sg:phone":"+1 407 344 0967",
    "sg:postcode":"34743",
    "sg:province":"FL",
    "sg:tags":[
        "janitor"
    ],
    "wof:name":"Laurentina Barbosa Cleaning",
    "wof:placetype":"venue"
},
  "geometry": {"coordinates":[-81.35136300000001,28.340899],"type":"Point"}
}