{
  "type": "Feature",
  "properties": {
    "iso:country":"US",
    "sg:address":"105 Colonia Ln W",
    "sg:city":"Nokomis",
    "sg:classifiers":[
        {
            "category":"Retail",
            "subcategory":"Repair Shop",
            "type":"Services"
        }
    ],
    "sg:phone":"+1 941 223 6277",
    "sg:postcode":"34275",
    "sg:province":"FL",
    "sg:tags":[
        "related"
    ],
    "wof:name":"Tim Carr's Repairs",
    "wof:placetype":"venue"
},
  "geometry": {"coordinates":[-82.450776,27.114799],"type":"Point"}
}