{
  "type": "Feature",
  "properties": {
    "addr:full":"3037 Riverside Dr Pompano Beach FL 33065",
    "addr:housenumber":"3037",
    "addr:postcode":"33065",
    "addr:street":"Riverside Dr",
    "iso:country":"US",
    "sg:address":"3037 Riverside Dr",
    "sg:city":"Pompano Beach",
    "sg:classifiers":[
        {
            "category":"Freight",
            "type":"Transportation"
        }
    ],
    "sg:phone":"+1 954 752 5375",
    "sg:postcode":"33065",
    "sg:province":"FL",
    "sg:tags":[
        "operator",
        "local",
        "trucking"
    ],
    "wof:name":"Roberto Ojeda Trucking",
    "wof:placetype":"venue"
},
  "geometry": {"coordinates":[-80.235327,26.266294],"type":"Point"}
}