{
  "type": "Feature",
  "properties": {
    "addr:full":"1000 N Mills Ave Orlando FL 32803",
    "addr:housenumber":"1000",
    "addr:postcode":"32803",
    "addr:street":"N Mills Ave",
    "iso:country":"US",
    "sg:address":"1000 N Mills Ave",
    "sg:city":"Orlando",
    "sg:classifiers":[
        {
            "category":"Autos & Motor Vehicles",
            "subcategory":"Automobile Sales",
            "type":"Retail Goods"
        }
    ],
    "sg:phone":"+1 407 898 1121",
    "sg:postcode":"32803",
    "sg:province":"FL",
    "sg:tags":[
        "car",
        "dealer"
    ],
    "wof:name":"Car Port",
    "wof:placetype":"venue"
},
  "geometry": {"coordinates":[-81.364447,28.559486],"type":"Point"}
}