{
  "type": "Feature",
  "properties": {
    "iso:country":"US",
    "sg:address":"9309 Old Kings Rd S",
    "sg:city":"Jacksonville",
    "sg:classifiers":[
        {
            "category":"Real Estate",
            "subcategory":"Developer",
            "type":"Services"
        }
    ],
    "sg:phone":"+1 904 737 9322",
    "sg:postcode":"32257",
    "sg:province":"FL",
    "sg:tags":[
        "company",
        "land"
    ],
    "wof:name":"Capstone Development LLC",
    "wof:placetype":"venue"
},
  "geometry": {"coordinates":[-81.583386,30.209296],"type":"Point"}
}