{
  "type": "Feature",
  "properties": {
    "iso:country":"US",
    "sg:address":"26 N Palm Ave",
    "sg:city":"Deland",
    "sg:classifiers":[
        {
            "category":"Professional",
            "subcategory":"Business Services",
            "type":"Services"
        }
    ],
    "sg:phone":"+1 386 736 6439",
    "sg:postcode":"32724",
    "sg:province":"FL",
    "sg:tags":[
        "consultant",
        "coach"
    ],
    "wof:name":"Linda Rogers Consulting",
    "wof:placetype":"venue"
},
  "geometry": {"coordinates":[-81.26110300000001,29.049781],"type":"Point"}
}