{
  "type": "Feature",
  "properties": {
    "iso:country":"US",
    "sg:address":"86 E Nine Mile Rd",
    "sg:city":"Pensacola",
    "sg:classifiers":[
        {
            "category":"Retail",
            "subcategory":"Auto Repair",
            "type":"Services"
        }
    ],
    "sg:phone":"+1 850 477 1433",
    "sg:postcode":"32534",
    "sg:province":"FL",
    "sg:tags":[
        "transmission",
        "automotive"
    ],
    "wof:name":"Gene's Transmissions",
    "wof:placetype":"venue"
},
  "geometry": {"coordinates":[-87.271013,30.533311],"type":"Point"}
}