{
  "type": "Feature",
  "properties": {
    "iso:country":"US",
    "sg:address":"4617 Rosemary St",
    "sg:city":"Middleburg",
    "sg:classifiers":[
        {
            "category":"Professional",
            "subcategory":"Business Services",
            "type":"Services"
        }
    ],
    "sg:phone":"+1 904 282 3456",
    "sg:postcode":"32068",
    "sg:province":"FL",
    "wof:name":"Black Creek Home Insptn Svc",
    "wof:placetype":"venue"
},
  "geometry": {"coordinates":[-81.90064599999999,30.04259],"type":"Point"}
}