{
  "type": "Feature",
  "properties": {
    "iso:country":"US",
    "sg:address":"408 Tyler Ave",
    "sg:city":"Cape Canaveral",
    "sg:classifiers":[
        {
            "category":"Building & Trades",
            "subcategory":"Construction",
            "type":"Services"
        }
    ],
    "sg:phone":"+1 321 536 0665",
    "sg:postcode":"32920",
    "sg:province":"FL",
    "sg:tags":[
        "contractor"
    ],
    "wof:name":"Showcase Exteriors Inc",
    "wof:placetype":"venue"
},
  "geometry": {"coordinates":[-80.60002299999999,28.385711],"type":"Point"}
}