{
  "type": "Feature",
  "properties": {
    "addr:full":"2709 Swamp Cabbage Ct Fort Myers FL 33901",
    "addr:housenumber":"2709",
    "addr:postcode":"33901",
    "addr:street":"Swamp Cabbage Ct",
    "iso:country":"US",
    "sg:address":"2709 Swamp Cabbage Ct",
    "sg:city":"Fort Myers",
    "sg:classifiers":[
        {
            "category":"Health Services",
            "subcategory":"Clinic",
            "type":"Services"
        }
    ],
    "sg:phone":"+1 239 275 5165",
    "sg:postcode":"33901",
    "sg:province":"FL",
    "sg:tags":[
        "home"
    ],
    "wof:name":"Associated Home Health",
    "wof:placetype":"venue"
},
  "geometry": {"coordinates":[-81.858085,26.601504],"type":"Point"}
}