{
  "type": "Feature",
  "properties": {
    "addr:full":"1034 Tawny Eagle Dr Groveland FL 34736",
    "addr:housenumber":"1034",
    "addr:postcode":"34736",
    "addr:street":"Tawny Eagle Dr",
    "iso:country":"US",
    "sg:address":"1034 Tawny Eagle Dr",
    "sg:city":"Groveland",
    "sg:classifiers":[
        {
            "category":"Recreation",
            "subcategory":"Marina",
            "type":"Entertainment"
        }
    ],
    "sg:phone":"+1 352 536 1436",
    "sg:postcode":"34736",
    "sg:province":"FL",
    "wof:name":"Bogliolo Marina",
    "wof:placetype":"venue"
},
  "geometry": {"coordinates":[-81.821727,28.575104],"type":"Point"}
}