{
  "type": "Feature",
  "properties": {
    "addr:full":"7279 NW 127th Way Pompano Beach FL 33076",
    "addr:housenumber":"7279",
    "addr:postcode":"33076",
    "addr:street":"Nw 127Th Way",
    "iso:country":"US",
    "sg:address":"7279 NW 127th Way",
    "sg:city":"Pompano Beach",
    "sg:classifiers":[
        {
            "category":"Building & Trades",
            "subcategory":"Construction",
            "type":"Services"
        }
    ],
    "sg:phone":"+1 954 755 4887",
    "sg:postcode":"33076",
    "sg:province":"FL",
    "sg:tags":[
        "residential"
    ],
    "wof:name":"Amrald Inc",
    "wof:placetype":"venue"
},
  "geometry": {"coordinates":[-80.29393899999999,26.321359],"type":"Point"}
}