{
  "type": "Feature",
  "properties": {
    "addr:full":"3883 SE Lake Weir Ave Ocala FL 34480",
    "addr:housenumber":"3883",
    "addr:postcode":"34480",
    "addr:street":"Se Lake Weir Ave",
    "iso:country":"US",
    "sg:address":"3883 SE Lake Weir Ave",
    "sg:city":"Ocala",
    "sg:classifiers":[
        {
            "category":"Professional",
            "subcategory":"Advertising",
            "type":"Services"
        }
    ],
    "sg:phone":"+1 352 732 4490",
    "sg:postcode":"34480",
    "sg:province":"FL",
    "sg:tags":[
        "distribution"
    ],
    "wof:name":"Diversified Distribution",
    "wof:placetype":"venue"
},
  "geometry": {"coordinates":[-82.11573199999999,29.148985],"type":"Point"}
}