{
  "type": "Feature",
  "properties": {
    "iso:country":"US",
    "sg:address":"3939 S Tamiami Trl",
    "sg:city":"Sarasota",
    "sg:classifiers":[
        {
            "category":"Manufacturing",
            "subcategory":"Printing",
            "type":"Manufacturing & Wholesale Goods"
        }
    ],
    "sg:phone":"+1 941 922 1563",
    "sg:postcode":"34231",
    "sg:province":"FL",
    "sg:tags":[
        "printer"
    ],
    "sg:website":"www.sirspeedy.com",
    "wof:name":"Sir Speedy Printing Ctr",
    "wof:placetype":"venue"
},
  "geometry": {"coordinates":[-82.53046000000001,27.298433],"type":"Point"}
}