{
  "type": "Feature",
  "properties": {
    "iso:country":"US",
    "sg:address":"669 Harold Ave",
    "sg:city":"Winter Park",
    "sg:classifiers":[
        {
            "category":"Building & Trades",
            "subcategory":"Plumbing",
            "type":"Services"
        }
    ],
    "sg:phone":"+1 407 629 6920",
    "sg:postcode":"32789",
    "sg:province":"FL",
    "sg:tags":[
        "air",
        "heating",
        "contractor",
        "system",
        "conditioning"
    ],
    "wof:name":"One Stop Cooling & Heating Inc",
    "wof:placetype":"venue"
},
  "geometry": {"coordinates":[-81.37185100000001,28.591984],"type":"Point"}
}