{
  "type": "Feature",
  "properties": {
    "iso:country":"US",
    "sg:address":"500 NW 60 St",
    "sg:city":"Gainesville",
    "sg:classifiers":[
        {
            "category":"Travel",
            "subcategory":"Travel Agent",
            "type":"Entertainment"
        }
    ],
    "sg:phone":"+1 352 331 3024",
    "sg:postcode":"32607",
    "sg:province":"FL",
    "sg:tags":[
        "agency"
    ],
    "wof:name":"Head Office Phone 8002422816",
    "wof:placetype":"venue"
},
  "geometry": {"coordinates":[-82.406463,29.65743],"type":"Point"}
}