{
  "type": "Feature",
  "properties": {
    "iso:country":"US",
    "sg:address":"2961 Placida Rd",
    "sg:city":"Englewood",
    "sg:classifiers":[
        {
            "category":"Real Estate",
            "subcategory":"Real Estate Agent",
            "type":"Services"
        }
    ],
    "sg:phone":"+1 941 964 1618",
    "sg:postcode":"34224",
    "sg:province":"FL",
    "wof:name":"Beach Front Properties",
    "wof:placetype":"venue"
},
  "geometry": {"coordinates":[-82.324611,26.908187],"type":"Point"}
}