{
  "type": "Feature",
  "properties": {
    "addr:full":"2180 W Atlantic Ave Delray Beach FL 33444",
    "addr:housenumber":"2180",
    "addr:postcode":"33444",
    "addr:street":"W Atlantic Ave",
    "iso:country":"US",
    "sg:address":"2180 W Atlantic Ave",
    "sg:city":"Delray Beach",
    "sg:classifiers":[
        {
            "category":"Government",
            "subcategory":"Office",
            "type":"Public Place"
        }
    ],
    "sg:phone":"+1 561 274 0441",
    "sg:postcode":"33444",
    "sg:province":"FL",
    "wof:name":"Dundee's Congress",
    "wof:placetype":"venue"
},
  "geometry": {"coordinates":[-80.09205300000001,26.461253],"type":"Point"}
}