{
  "type": "Feature",
  "properties": {
    "addr:full":"25830 Co Rd 561 Astatula FL 34705",
    "addr:housenumber":"25830",
    "addr:postcode":"34705",
    "addr:street":"Co Rd 561",
    "iso:country":"US",
    "sg:address":"25830 Co Rd 561",
    "sg:city":"Astatula",
    "sg:classifiers":[
        {
            "category":"Retail",
            "subcategory":"Repair Shop",
            "type":"Services"
        }
    ],
    "sg:phone":"+1 352 742 2277",
    "sg:postcode":"34705",
    "sg:province":"FL",
    "sg:tags":[
        "electrical"
    ],
    "wof:name":"Astatula Appliance Repair",
    "wof:placetype":"venue"
},
  "geometry": {"coordinates":[-81.73049399999999,28.723658],"type":"Point"}
}