{
  "type": "Feature",
  "properties": {
    "iso:country":"US",
    "sg:address":"417 NW 2nd Ave",
    "sg:city":"Hallandale",
    "sg:classifiers":[
        {
            "category":"Personal",
            "subcategory":"Beauty Salon",
            "type":"Services"
        }
    ],
    "sg:phone":"+1 954 456 4503",
    "sg:postcode":"33009",
    "sg:province":"FL",
    "sg:tags":[
        "shop"
    ],
    "wof:name":"Peterson Buty Salon & Nail Svc",
    "wof:placetype":"venue"
},
  "geometry": {"coordinates":[-80.150642,25.990828],"type":"Point"}
}