{
  "type": "Feature",
  "properties": {
    "addr:full":"105 Commerce St Lake Mary FL 32746",
    "addr:housenumber":"105",
    "addr:postcode":"32746",
    "addr:street":"Commerce St",
    "iso:country":"US",
    "sg:address":"105 Commerce St",
    "sg:city":"Lake Mary",
    "sg:classifiers":[
        {
            "category":"Wholesale",
            "subcategory":"Computers",
            "type":"Manufacturing & Wholesale Goods"
        }
    ],
    "sg:phone":"+1 407 804 5570",
    "sg:postcode":"32746",
    "sg:province":"FL",
    "wof:name":"Kinetics Inc",
    "wof:placetype":"venue"
},
  "geometry": {"coordinates":[-81.36323,28.740008],"type":"Point"}
}