{
  "type": "Feature",
  "properties": {
    "iso:country":"US",
    "sg:address":"23451 Moreland Ave",
    "sg:city":"Port Charlotte",
    "sg:classifiers":[
        {
            "category":"Building & Trades",
            "subcategory":"Construction",
            "type":"Services"
        }
    ],
    "sg:phone":"+1 941 625 2788",
    "sg:postcode":"33954",
    "sg:province":"FL",
    "sg:tags":[
        "pavement",
        "marking"
    ],
    "wof:name":"Asphalt Sealing",
    "wof:placetype":"venue"
},
  "geometry": {"coordinates":[-82.05833199999999,27.031164],"type":"Point"}
}