{
  "type": "Feature",
  "properties": {
    "iso:country":"US",
    "sg:address":"133 E Merritt Island Cswy",
    "sg:city":"Merritt Island",
    "sg:classifiers":[
        {
            "category":"Shopping",
            "subcategory":"Optician",
            "type":"Retail Goods"
        },
        {
            "category":"Shopping",
            "subcategory":"Jewelry",
            "type":"Retail Goods"
        }
    ],
    "sg:phone":"+1 321 453 7938",
    "sg:postcode":"32952",
    "sg:province":"FL",
    "sg:tags":[
        "watch",
        "eyewear"
    ],
    "sg:website":"www2.sunglasshut.com",
    "wof:name":"Sunglass Hut International",
    "wof:placetype":"venue"
},
  "geometry": {"coordinates":[-80.69771,28.356932],"type":"Point"}
}