{
  "type": "Feature",
  "properties": {
    "addr:full":"16851 NW 60th Ave Trenton FL 32693",
    "addr:housenumber":"16851",
    "addr:postcode":"32693",
    "addr:street":"Nw 60Th Ave",
    "iso:country":"US",
    "sg:address":"16851 NW 60th Ave",
    "sg:city":"Trenton",
    "sg:phone":"+1 352 463 2896",
    "sg:postcode":"32693",
    "sg:province":"FL",
    "sg:tags":[
        "farm",
        "field",
        "corn",
        "crop"
    ],
    "wof:name":"Red Hollow Farms",
    "wof:placetype":"venue"
},
  "geometry": {"coordinates":[-82.87326,29.57301],"type":"Point"}
}