{
  "type": "Feature",
  "properties": {
    "addr:full":"4743 Wildwood Dr Milton FL 32570",
    "addr:housenumber":"4743",
    "addr:postcode":"32570",
    "addr:street":"Wildwood Dr",
    "iso:country":"US",
    "sg:address":"4743 Wildwood Dr",
    "sg:city":"Milton",
    "sg:classifiers":[
        {
            "category":"Freight",
            "type":"Transportation"
        }
    ],
    "sg:phone":"+1 850 623 9968",
    "sg:postcode":"32570",
    "sg:province":"FL",
    "sg:tags":[
        "delivery",
        "operator",
        "local",
        "trucking"
    ],
    "wof:name":"James Weekley's Recycle",
    "wof:placetype":"venue"
},
  "geometry": {"coordinates":[-87.056493,30.606057],"type":"Point"}
}