{
  "type": "Feature",
  "properties": {
    "iso:country":"US",
    "sg:address":"620 17th Ave W",
    "sg:city":"Bradenton",
    "sg:classifiers":[
        {
            "category":"Autos & Motor Vehicles",
            "subcategory":"Boat Sales",
            "type":"Retail Goods"
        }
    ],
    "sg:phone":"+1 941 748 3707",
    "sg:postcode":"34205",
    "sg:province":"FL",
    "sg:tags":[
        "dealer",
        "sales"
    ],
    "wof:name":"Darrelly's Marine Ctr",
    "wof:placetype":"venue"
},
  "geometry": {"coordinates":[-82.570409,27.484488],"type":"Point"}
}