{
  "type": "Feature",
  "properties": {
    "iso:country":"US",
    "sg:address":"5491 Division Dr",
    "sg:city":"Fort Myers",
    "sg:classifiers":[
        {
            "category":"Wholesale",
            "subcategory":"Machinery & Supplies",
            "type":"Manufacturing & Wholesale Goods"
        },
        {
            "category":"Manufacturing",
            "subcategory":"Tools & Machinery",
            "type":"Manufacturing & Wholesale Goods"
        }
    ],
    "sg:phone":"+1 239 690 0600",
    "sg:postcode":"33905",
    "sg:province":"FL",
    "sg:tags":[
        "heavy",
        "equipment",
        "pump",
        "construction",
        "mfg"
    ],
    "wof:name":"Thompson Pump & Mfg Co Inc",
    "wof:placetype":"venue"
},
  "geometry": {"coordinates":[-81.804693,26.665784],"type":"Point"}
}