{
  "type": "Feature",
  "properties": {
    "iso:country":"US",
    "sg:address":"3296 Main St",
    "sg:city":"Cottondale",
    "sg:classifiers":[
        {
            "category":"Professional",
            "subcategory":"Engineering",
            "type":"Services"
        },
        {
            "category":"Professional",
            "subcategory":"Management & Consulting",
            "type":"Services"
        },
        {
            "category":"Professional",
            "subcategory":"Business Services",
            "type":"Services"
        },
        {
            "category":"Organizations",
            "subcategory":"Membership Organization",
            "type":"Services"
        }
    ],
    "sg:phone":"+1 850 352 2299",
    "sg:postcode":"32431",
    "sg:province":"FL",
    "sg:tags":[
        "product",
        "consultant",
        "environmental",
        "ecological",
        "conservation",
        "engineer"
    ],
    "sg:website":"http://www.mallard.com",
    "wof:name":"Mallard Inc",
    "wof:placetype":"venue"
},
  "geometry": {"coordinates":[-85.37676999999999,30.806216],"type":"Point"}
}