{
  "type": "Feature",
  "properties": {
    "addr:full":"8701 SW 137th Ave Miami FL 33183",
    "addr:housenumber":"8701",
    "addr:postcode":"33183",
    "addr:street":"Sw 137Th Ave",
    "iso:country":"US",
    "sg:address":"8701 SW 137th Ave",
    "sg:city":"Miami",
    "sg:classifiers":[
        {
            "category":"Professional",
            "type":"Services"
        }
    ],
    "sg:phone":"+1 786 293 1424",
    "sg:postcode":"33183",
    "sg:province":"FL",
    "wof:name":"Julia H Riquelme PA",
    "wof:placetype":"venue"
},
  "geometry": {"coordinates":[-80.41649200000001,25.686121],"type":"Point"}
}