{
  "type": "Feature",
  "properties": {
    "iso:country":"US",
    "sg:address":"2610 Boggy Creek Rd",
    "sg:city":"Kissimmee",
    "sg:classifiers":[
        {
            "category":"Food & Beverages",
            "subcategory":"Liquor & Beverages",
            "type":"Retail Goods"
        }
    ],
    "sg:phone":"+1 407 344 4000",
    "sg:postcode":"34744",
    "sg:province":"FL",
    "sg:tags":[
        "alcoholic"
    ],
    "wof:name":"Party Liquors",
    "wof:placetype":"venue"
},
  "geometry": {"coordinates":[-81.33750999999999,28.321865],"type":"Point"}
}