{
  "type": "Feature",
  "properties": {
    "addr:full":"4444 US Hwy 98 Lakeland FL 33810",
    "addr:housenumber":"4444",
    "addr:postcode":"33810",
    "addr:street":"Us Hwy 98",
    "iso:country":"US",
    "sg:address":"4444 US Hwy 98",
    "sg:city":"Lakeland",
    "sg:phone":"+1 863 816 0685",
    "sg:postcode":"33810",
    "sg:province":"FL",
    "sg:tags":[
        "farm",
        "corn",
        "soybean"
    ],
    "wof:name":"Lavern Saxe",
    "wof:placetype":"venue"
},
  "geometry": {"coordinates":[-81.97638499999999,28.166922],"type":"Point"}
}