{
  "type": "Feature",
  "properties": {
    "iso:country":"US",
    "sg:address":"448 Bond Dr",
    "sg:city":"De Funiak Springs",
    "sg:classifiers":[
        {
            "category":"Building & Trades",
            "subcategory":"Construction",
            "type":"Services"
        }
    ],
    "sg:phone":"+1 850 892 4850",
    "sg:postcode":"32435",
    "sg:province":"FL",
    "sg:tags":[
        "builder",
        "operative"
    ],
    "wof:name":"Jackson Family Homes",
    "wof:placetype":"venue"
},
  "geometry": {"coordinates":[-86.172262,30.663211],"type":"Point"}
}