{
  "type": "Feature",
  "properties": {
    "iso:country":"US",
    "sg:address":"1500 N University Dr",
    "sg:city":"Coral Springs",
    "sg:classifiers":[
        {
            "category":"Organizations",
            "subcategory":"Non-profit Organization",
            "type":"Services"
        }
    ],
    "sg:phone":"+1 954 346 8663",
    "sg:postcode":"33071",
    "sg:province":"FL",
    "sg:tags":[
        "information",
        "alcoholism",
        "treatment"
    ],
    "wof:name":"A Center For Positive Growth",
    "wof:placetype":"venue"
},
  "geometry": {"coordinates":[-80.25307100000001,26.249447],"type":"Point"}
}