{
  "type": "Feature",
  "properties": {
    "addr:full":"1785 S Patrick Dr Indian Hrbr Bch FL 32937",
    "addr:housenumber":"1785",
    "addr:postcode":"32937",
    "addr:street":"S Patrick Dr Indian Hrbr",
    "iso:country":"US",
    "sg:address":"1785 S Patrick Dr",
    "sg:city":"Indian Hrbr Bch",
    "sg:classifiers":[
        {
            "category":"Manufacturing",
            "subcategory":"Chemicals & Compounds",
            "type":"Manufacturing & Wholesale Goods"
        }
    ],
    "sg:phone":"+1 321 773 2454",
    "sg:postcode":"32937",
    "sg:province":"FL",
    "sg:tags":[
        "prep",
        "perfume"
    ],
    "wof:name":"Valjean Corp",
    "wof:placetype":"venue"
},
  "geometry": {"coordinates":[-80.60380000000001,28.160329],"type":"Point"}
}