{
  "type": "Feature",
  "properties": {
    "iso:country":"US",
    "sg:address":"259 Seaboard Ave",
    "sg:city":"Venice",
    "sg:classifiers":[
        {
            "category":"Building & Trades",
            "subcategory":"Plumbing",
            "type":"Services"
        }
    ],
    "sg:phone":"+1 941 488 0360",
    "sg:postcode":"34285",
    "sg:province":"FL",
    "sg:tags":[
        "plumbing",
        "contractor"
    ],
    "wof:name":"TNT Plumbing",
    "wof:placetype":"venue"
},
  "geometry": {"coordinates":[-82.437352,27.096913],"type":"Point"}
}