{
  "type": "Feature",
  "properties": {
    "addr:full":"1261 NW 23rd St Miami FL 33142",
    "addr:housenumber":"1261",
    "addr:postcode":"33142",
    "addr:street":"Nw 23Rd St",
    "iso:country":"US",
    "sg:address":"1261 NW 23rd St",
    "sg:city":"Miami",
    "sg:classifiers":[
        {
            "category":"Home & Garden",
            "subcategory":"Home Furnishings",
            "type":"Retail Goods"
        }
    ],
    "sg:phone":"+1 305 634 0672",
    "sg:postcode":"33142",
    "sg:province":"FL",
    "sg:tags":[
        "refinish",
        "bathtub",
        "sinks-repair"
    ],
    "wof:name":"Bathroom & Kitchen Sales",
    "wof:placetype":"venue"
},
  "geometry": {"coordinates":[-80.21654700000001,25.798643],"type":"Point"}
}