{
  "type": "Feature",
  "properties": {
    "iso:country":"US",
    "sg:address":"2632 W State Rd 434",
    "sg:city":"Longwood",
    "sg:classifiers":[
        {
            "category":"Home & Garden",
            "subcategory":"Building Materials",
            "type":"Retail Goods"
        }
    ],
    "sg:phone":"+1 407 262 0495",
    "sg:postcode":"32779",
    "sg:province":"FL",
    "sg:tags":[
        "glass",
        "window",
        "plate"
    ],
    "wof:name":"Glass Depot",
    "wof:placetype":"venue"
},
  "geometry": {"coordinates":[-81.40890400000001,28.688013],"type":"Point"}
}