{
  "type": "Feature",
  "properties": {
    "addr:full":"1902 Tamiami Trl Venice FL 34293",
    "addr:housenumber":"1902",
    "addr:postcode":"34293",
    "addr:street":"Tamiami Trl",
    "iso:country":"US",
    "sg:address":"1902 Tamiami Trl",
    "sg:city":"Venice",
    "sg:classifiers":[
        {
            "category":"Home & Garden",
            "subcategory":"Carpets & Floor Coverings",
            "type":"Retail Goods"
        }
    ],
    "sg:phone":"+1 941 408 9044",
    "sg:postcode":"34293",
    "sg:province":"FL",
    "sg:tags":[
        "dealer",
        "rug"
    ],
    "wof:name":"Ken Smith Tile & Carpet",
    "wof:placetype":"venue"
},
  "geometry": {"coordinates":[-82.415654,27.060817],"type":"Point"}
}