{
  "type": "Feature",
  "properties": {
    "addr:full":"1019 5th St Neptune Beach FL 32266",
    "addr:housenumber":"1019",
    "addr:postcode":"32266",
    "addr:street":"5Th St",
    "iso:country":"US",
    "sg:address":"1019 5th St",
    "sg:city":"Neptune Beach",
    "sg:classifiers":[
        {
            "category":"Utilities",
            "subcategory":"Water",
            "type":"Services"
        }
    ],
    "sg:phone":"+1 904 270 2419",
    "sg:postcode":"32266",
    "sg:province":"FL",
    "sg:tags":[
        "supply"
    ],
    "wof:name":"Neptune Beach Water Plant",
    "wof:placetype":"venue"
},
  "geometry": {"coordinates":[-81.40026,30.314323],"type":"Point"}
}