{
  "type": "Feature",
  "properties": {
    "addr:full":"10780 W Flagler St Miami FL 33174",
    "addr:housenumber":"10780",
    "addr:postcode":"33174",
    "addr:street":"W Flagler St",
    "iso:country":"US",
    "sg:address":"10780 W Flagler St",
    "sg:city":"Miami",
    "sg:classifiers":[
        {
            "category":"Building & Trades",
            "subcategory":"Equipment Rental",
            "type":"Services"
        }
    ],
    "sg:phone":"+1 305 553 3235",
    "sg:postcode":"33174",
    "sg:province":"FL",
    "sg:tags":[
        "party",
        "supply"
    ],
    "wof:name":"Delicias Dominicanas",
    "wof:placetype":"venue"
},
  "geometry": {"coordinates":[-80.37131599999999,25.768343],"type":"Point"}
}