{
  "type": "Feature",
  "properties": {
    "addr:full":"7544 W McNab Rd Pompano Beach FL 33068",
    "addr:housenumber":"7544",
    "addr:postcode":"33068",
    "addr:street":"W Mcnab Rd",
    "iso:country":"US",
    "sg:address":"7544 W McNab Rd",
    "sg:city":"Pompano Beach",
    "sg:classifiers":[
        {
            "category":"Autos & Motor Vehicles",
            "subcategory":"Fuel & Gas Station",
            "type":"Retail Goods"
        }
    ],
    "sg:phone":"+1 954 721 0191",
    "sg:postcode":"33068",
    "sg:province":"FL",
    "sg:tags":[
        "automotive",
        "station",
        "repair"
    ],
    "wof:name":"Chevron",
    "wof:placetype":"venue"
},
  "geometry": {"coordinates":[-80.228049,26.208362],"type":"Point"}
}