{
  "type": "Feature",
  "properties": {
    "addr:full":"54 Cardamon Dr Orlando FL 32825",
    "addr:housenumber":"54",
    "addr:postcode":"32825",
    "addr:street":"Cardamon Dr",
    "iso:country":"US",
    "sg:address":"54 Cardamon Dr",
    "sg:city":"Orlando",
    "sg:classifiers":[
        {
            "category":"Building & Trades",
            "subcategory":"Construction",
            "type":"Services"
        }
    ],
    "sg:phone":"+1 407 277 9066",
    "sg:postcode":"32825",
    "sg:province":"FL",
    "sg:tags":[
        "mason",
        "masonry",
        "industrial",
        "contractors-commercial",
        "contractor"
    ],
    "wof:name":"Win Lowe Masonry",
    "wof:placetype":"venue"
},
  "geometry": {"coordinates":[-81.261324,28.546005],"type":"Point"}
}