{
  "type": "Feature",
  "properties": {
    "addr:full":"175 W Granada Blvd Ormond Beach FL 32174",
    "addr:housenumber":"175",
    "addr:postcode":"32174",
    "addr:street":"W Granada Blvd",
    "iso:country":"US",
    "sg:address":"175 W Granada Blvd",
    "sg:city":"Ormond Beach",
    "sg:classifiers":[
        {
            "category":"Banks & Credit Unions",
            "subcategory":"Bank",
            "type":"Services"
        }
    ],
    "sg:phone":"+1 386 677 8222",
    "sg:postcode":"32174",
    "sg:province":"FL",
    "sg:tags":[
        "national",
        "commercial"
    ],
    "wof:name":"Bank Of America",
    "wof:placetype":"venue"
},
  "geometry": {"coordinates":[-81.06191800000001,29.283181],"type":"Point"}
}