{
  "type": "Feature",
  "properties": {
    "addr:full":"2706 Lee Blvd Lehigh Acres FL 33971",
    "addr:housenumber":"2706",
    "addr:postcode":"33971",
    "addr:street":"Lee Blvd",
    "iso:country":"US",
    "sg:address":"2706 Lee Blvd",
    "sg:city":"Lehigh Acres",
    "sg:classifiers":[
        {
            "category":"Bakery",
            "type":"Food & Drink"
        },
        {
            "category":"Coffee & Tea",
            "type":"Food & Drink"
        },
        {
            "category":"Bagels",
            "type":"Food & Drink"
        },
        {
            "category":"Donuts",
            "type":"Food & Drink"
        }
    ],
    "sg:menulink":"http://www.allmenus.com/fl/lehigh-acres/138021-dunkin-donuts/menu/",
    "sg:phone":"+1 239 369 0111",
    "sg:postcode":"33971",
    "sg:province":"FL",
    "sg:tags":[
        "american",
        "pastry"
    ],
    "wof:name":"Dunkin' Donuts",
    "wof:placetype":"venue"
},
  "geometry": {"coordinates":[-81.668313,26.617725],"type":"Point"}
}