{
  "type": "Feature",
  "properties": {
    "addr:full":"387 W Broadway St Oviedo FL 32765",
    "addr:housenumber":"387",
    "addr:postcode":"32765",
    "addr:street":"W Broadway St",
    "iso:country":"US",
    "sg:address":"387 W Broadway St",
    "sg:city":"Oviedo",
    "sg:classifiers":[
        {
            "category":"Social Services",
            "subcategory":"Child Care",
            "type":"Services"
        }
    ],
    "sg:phone":"+1 407 365 5621",
    "sg:postcode":"32765",
    "sg:province":"FL",
    "sg:tags":[
        "day"
    ],
    "wof:name":"Center In Oviedo Learning",
    "wof:placetype":"venue"
},
  "geometry": {"coordinates":[-81.215895,28.670339],"type":"Point"}
}