{
  "type": "Feature",
  "properties": {
    "addr:full":"4297 Juniper Ter Boynton Beach FL 33436",
    "addr:housenumber":"4297",
    "addr:postcode":"33436",
    "addr:street":"Juniper Ter",
    "iso:country":"US",
    "sg:address":"4297 Juniper Ter",
    "sg:city":"Boynton Beach",
    "sg:classifiers":[
        {
            "category":"Building & Trades",
            "subcategory":"Construction",
            "type":"Services"
        }
    ],
    "sg:phone":"+1 561 737 4841",
    "sg:postcode":"33436",
    "sg:province":"FL",
    "sg:tags":[
        "hanging",
        "contractor"
    ],
    "wof:name":"Departments By Dave",
    "wof:placetype":"venue"
},
  "geometry": {"coordinates":[-80.111097,26.537197],"type":"Point"}
}