{
  "type": "Feature",
  "properties": {
    "iso:country":"US",
    "sg:address":"8001 S Orange Blossom Trl",
    "sg:city":"Orlando",
    "sg:classifiers":[
        {
            "category":"Bakery",
            "type":"Food & Drink"
        }
    ],
    "sg:menulink":"http://www.allmenus.com/fl/orlando/224223-cinnzeo/menu/",
    "sg:phone":"+1 407 857 5660",
    "sg:postcode":"32809",
    "sg:province":"FL",
    "sg:tags":[
        "american",
        "pastry"
    ],
    "wof:name":"Cinnzeo",
    "wof:placetype":"venue"
},
  "geometry": {"coordinates":[-81.40092300000001,28.449566],"type":"Point"}
}