{
  "type": "Feature",
  "properties": {
    "iso:country":"US",
    "sg:address":"700 S Federal Hwy",
    "sg:city":"Boca Raton",
    "sg:classifiers":[
        {
            "category":"Professional",
            "subcategory":"Lawyer & Legal Services",
            "type":"Services"
        }
    ],
    "sg:phone":"+1 561 393 5660",
    "sg:postcode":"33432",
    "sg:province":"FL",
    "sg:tags":[
        "attorney"
    ],
    "wof:name":"Adorno & Yoss PA",
    "wof:placetype":"venue"
},
  "geometry": {"coordinates":[-80.08626700000001,26.342767],"type":"Point"}
}