{
  "type": "Feature",
  "properties": {
    "iso:country":"US",
    "sg:address":"5618 Windrift Ln",
    "sg:city":"Boca Raton",
    "sg:classifiers":[
        {
            "category":"Shopping",
            "subcategory":"Shoes",
            "type":"Retail Goods"
        }
    ],
    "sg:phone":"+1 561 447 0771",
    "sg:postcode":"33433",
    "sg:province":"FL",
    "wof:name":"Shoes Sandy",
    "wof:placetype":"venue"
},
  "geometry": {"coordinates":[-80.13092899999999,26.343299],"type":"Point"}
}