{
  "type": "Feature",
  "properties": {
    "iso:country":"US",
    "sg:address":"7303 NW 4 Blvd",
    "sg:city":"Gainesville",
    "sg:classifiers":[
        {
            "category":"Food & Beverages",
            "subcategory":"Groceries & Convenience Stores",
            "type":"Retail Goods"
        }
    ],
    "sg:phone":"+1 352 332 4014",
    "sg:postcode":"32607",
    "sg:province":"FL",
    "wof:name":"Winn-Dixie",
    "wof:placetype":"venue"
},
  "geometry": {"coordinates":[-82.418115,29.656048],"type":"Point"}
}