{
  "type": "Feature",
  "properties": {
    "iso:country":"US",
    "sg:address":"465 NE 36th St",
    "sg:city":"Boca Raton",
    "sg:classifiers":[
        {
            "category":"Wholesale",
            "subcategory":"Hardware",
            "type":"Manufacturing & Wholesale Goods"
        }
    ],
    "sg:phone":"+1 561 994 7677",
    "sg:postcode":"33431",
    "sg:province":"FL",
    "sg:tags":[
        "water"
    ],
    "wof:name":"A Perfectly Clear Solution",
    "wof:placetype":"venue"
},
  "geometry": {"coordinates":[-80.080055,26.382967],"type":"Point"}
}