{
  "type": "Feature",
  "properties": {
    "iso:country":"US",
    "sg:address":"1314 Bay Club Cir",
    "sg:city":"Tampa",
    "sg:classifiers":[
        {
            "category":"Organizations",
            "subcategory":"Community Association",
            "type":"Services"
        }
    ],
    "sg:phone":"+1 813 287 8697",
    "sg:postcode":"33607",
    "sg:province":"FL",
    "sg:tags":[
        "club"
    ],
    "wof:name":"Bay Club",
    "wof:placetype":"venue"
},
  "geometry": {"coordinates":[-82.56720300000001,27.965376],"type":"Point"}
}