{
  "type": "Feature",
  "properties": {
    "addr:full":"333 NW 3rd Ave Ocala FL 34475",
    "addr:housenumber":"333",
    "addr:postcode":"34475",
    "addr:street":"Nw 3Rd Ave",
    "iso:country":"US",
    "sg:address":"333 NW 3rd Ave",
    "sg:city":"Ocala",
    "sg:classifiers":[
        {
            "category":"Professional",
            "subcategory":"Lawyer & Legal Services",
            "type":"Services"
        }
    ],
    "sg:phone":"+1 352 732 7750",
    "sg:postcode":"34475",
    "sg:province":"FL",
    "sg:tags":[
        "attorney"
    ],
    "wof:name":"Klein & Klein PA",
    "wof:placetype":"venue"
},
  "geometry": {"coordinates":[-82.139383,29.190051],"type":"Point"}
}