{
  "type": "Feature",
  "properties": {
    "iso:country":"US",
    "sg:address":"360 N Delaware Ave",
    "sg:city":"Deland",
    "sg:classifiers":[
        {
            "category":"Shopping",
            "subcategory":"Computers & Home Electronics",
            "type":"Retail Goods"
        }
    ],
    "sg:phone":"+1 386 734 3338",
    "sg:postcode":"32720",
    "sg:province":"FL",
    "sg:tags":[
        "equipment",
        "satellite",
        "system"
    ],
    "wof:name":"Precision Satellites",
    "wof:placetype":"venue"
},
  "geometry": {"coordinates":[-81.31023500000001,29.031901],"type":"Point"}
}