{
  "type": "Feature",
  "properties": {
    "iso:country":"US",
    "sg:address":"755 S State Rd 7",
    "sg:city":"Fort Lauderdale",
    "sg:classifiers":[
        {
            "category":"Professional",
            "subcategory":"Accounting & Tax Preparation",
            "type":"Services"
        }
    ],
    "sg:phone":"+1 954 327 7997",
    "sg:postcode":"33317",
    "sg:province":"FL",
    "sg:tags":[
        "consultant",
        "return"
    ],
    "wof:name":"Azoy Tax Financial Services",
    "wof:placetype":"venue"
},
  "geometry": {"coordinates":[-80.201821,26.112219],"type":"Point"}
}