{
  "type": "Feature",
  "properties": {
    "addr:full":"180 Crandon Blvd Ste 115 Key Biscayne FL 33149",
    "addr:housenumber":"180",
    "addr:postcode":"33149",
    "addr:street":"Crandon Blvd Ste 115",
    "iso:country":"US",
    "sg:address":"180 Crandon Blvd Ste 115",
    "sg:city":"Key Biscayne",
    "sg:classifiers":[
        {
            "category":"Building & Trades",
            "subcategory":"Construction",
            "type":"Services"
        }
    ],
    "sg:phone":"+1 305 361 6966",
    "sg:postcode":"33149",
    "sg:province":"FL",
    "sg:tags":[
        "contractor"
    ],
    "wof:name":"Interscope General Contractors Corp",
    "wof:placetype":"venue"
},
  "geometry": {"coordinates":[-80.162903,25.697901],"type":"Point"}
}