{
  "type": "Feature",
  "properties": {
    "iso:country":"US",
    "sg:address":"4963 Cobia Dr SE",
    "sg:city":"St Petersburg",
    "sg:classifiers":[
        {
            "category":"Shopping",
            "subcategory":"Catalog Store",
            "type":"Retail Goods"
        }
    ],
    "sg:phone":"+1 727 422 3328",
    "sg:postcode":"33705",
    "sg:province":"FL",
    "sg:tags":[
        "mail",
        "order"
    ],
    "wof:name":"Culmer Assoc",
    "wof:placetype":"venue"
},
  "geometry": {"coordinates":[-82.63064300000001,27.724223],"type":"Point"}
}