{
  "type": "Feature",
  "properties": {
    "iso:country":"US",
    "sg:address":"29162 US Hwy 19",
    "sg:city":"Clearwater",
    "sg:classifiers":[
        {
            "category":"Building & Trades",
            "subcategory":"Cleaning & Sanitation",
            "type":"Services"
        }
    ],
    "sg:phone":"+1 727 787 7087",
    "sg:postcode":"33761",
    "sg:province":"FL",
    "sg:tags":[
        "maintenance"
    ],
    "wof:name":"Duct Busters",
    "wof:placetype":"venue"
},
  "geometry": {"coordinates":[-82.73830700000001,28.037119],"type":"Point"}
}