{
  "type": "Feature",
  "properties": {
    "iso:country":"US",
    "sg:address":"1821 W Brandon Blvd",
    "sg:city":"Brandon",
    "sg:classifiers":[
        {
            "category":"Home & Garden",
            "subcategory":"Home Furnishings",
            "type":"Retail Goods"
        },
        {
            "category":"Home & Garden",
            "subcategory":"Furniture",
            "type":"Retail Goods"
        }
    ],
    "sg:phone":"+1 813 651 0099",
    "sg:postcode":"33511",
    "sg:province":"FL",
    "sg:tags":[
        "furniture-children's",
        "store"
    ],
    "sg:website":"http://www.rooms2go.com",
    "wof:name":"Rooms To Go",
    "wof:placetype":"venue"
},
  "geometry": {"coordinates":[-82.313124,27.937599],"type":"Point"}
}