{
  "type": "Feature",
  "properties": {
    "iso:country":"US",
    "sg:address":"2236 W Palma Cir",
    "sg:city":"West Palm Beach",
    "sg:classifiers":[
        {
            "category":"Shopping",
            "subcategory":"Gifts & Souvenirs",
            "type":"Retail Goods"
        }
    ],
    "sg:phone":"+1 561 642 1571",
    "sg:postcode":"33415",
    "sg:province":"FL",
    "sg:tags":[
        "postcard"
    ],
    "wof:name":"Old Time Florida Publications",
    "wof:placetype":"venue"
},
  "geometry": {"coordinates":[-80.11608,26.645899],"type":"Point"}
}