{
  "type": "Feature",
  "properties": {
    "addr:full":"918 Skipper Ave Fort Walton Bch FL 32547",
    "addr:housenumber":"918",
    "addr:postcode":"32547",
    "addr:street":"Skipper Ave Fort",
    "iso:country":"US",
    "sg:address":"918 Skipper Ave",
    "sg:city":"Fort Walton Bch",
    "sg:classifiers":[
        {
            "category":"Retail",
            "subcategory":"Auto Repair",
            "type":"Services"
        }
    ],
    "sg:phone":"+1 850 863 1983",
    "sg:postcode":"32547",
    "sg:province":"FL",
    "sg:tags":[
        "automobile",
        "electric"
    ],
    "wof:name":"Jodash Auto Repair",
    "wof:placetype":"venue"
},
  "geometry": {"coordinates":[-86.604778,30.447749],"type":"Point"}
}