{
  "type": "Feature",
  "properties": {
    "iso:country":"US",
    "sg:address":"3191 SW 22nd St",
    "sg:city":"Coral Gables",
    "sg:classifiers":[
        {
            "category":"Professional",
            "subcategory":"Lawyer & Legal Services",
            "type":"Services"
        }
    ],
    "sg:phone":"+1 305 774 6300",
    "sg:postcode":"33145",
    "sg:province":"FL",
    "sg:tags":[
        "attorney"
    ],
    "wof:name":"Pila & Assoc",
    "wof:placetype":"venue"
},
  "geometry": {"coordinates":[-80.24415399999999,25.750242],"type":"Point"}
}