{
  "type": "Feature",
  "properties": {
    "iso:country":"US",
    "sg:address":"9030 Ridgeland Dr",
    "sg:city":"Miami",
    "sg:classifiers":[
        {
            "category":"Real Estate",
            "subcategory":"Real Estate Agent",
            "type":"Services"
        }
    ],
    "sg:phone":"+1 305 238 6453",
    "sg:postcode":"33157",
    "sg:province":"FL",
    "wof:name":"Cutler Realty",
    "wof:placetype":"venue"
},
  "geometry": {"coordinates":[-80.33899599999999,25.585174],"type":"Point"}
}