{
  "type": "Feature",
  "properties": {
    "iso:country":"US",
    "sg:address":"1717 Staimford Ct",
    "sg:city":"West Palm Beach",
    "sg:classifiers":[
        {
            "category":"Home & Garden",
            "subcategory":"Building Materials",
            "type":"Retail Goods"
        }
    ],
    "sg:phone":"+1 561 784 7305",
    "sg:postcode":"33414",
    "sg:province":"FL",
    "wof:name":"Adrian Alvarez Wallpaper",
    "wof:placetype":"venue"
},
  "geometry": {"coordinates":[-80.264398,26.656479],"type":"Point"}
}