{
  "type": "Feature",
  "properties": {
    "iso:country":"US",
    "sg:address":"1018 New York Ave",
    "sg:city":"St Cloud",
    "sg:classifiers":[
        {
            "category":"Restaurant",
            "type":"Food & Drink"
        }
    ],
    "sg:phone":"+1 407 957 2271",
    "sg:postcode":"34769",
    "sg:province":"FL",
    "wof:name":"Nannie's Kitchen Inc",
    "wof:placetype":"venue"
},
  "geometry": {"coordinates":[-81.283624,28.248784],"type":"Point"}
}