{
  "type": "Feature",
  "properties": {
    "addr:full":"6289 W Sunrise Blvd Plantation FL 33313",
    "addr:housenumber":"6289",
    "addr:postcode":"33313",
    "addr:street":"W Sunrise Blvd",
    "iso:country":"US",
    "sg:address":"6289 W Sunrise Blvd",
    "sg:city":"Plantation",
    "sg:classifiers":[
        {
            "category":"Health Services",
            "subcategory":"Health Practitioner",
            "type":"Services"
        }
    ],
    "sg:phone":"+1 954 791 4551",
    "sg:postcode":"33313",
    "sg:province":"FL",
    "sg:tags":[
        "nurse",
        "registry"
    ],
    "sg:website":"www.accuratehealthcare.org",
    "wof:name":"Accurate Health Care Inc",
    "wof:placetype":"venue"
},
  "geometry": {"coordinates":[-80.232945,26.13581],"type":"Point"}
}