{
  "type": "Feature",
  "properties": {
    "addr:full":"3199 Village Ln Port Charlotte FL 33953",
    "addr:housenumber":"3199",
    "addr:postcode":"33953",
    "addr:street":"Village Ln",
    "iso:country":"US",
    "sg:address":"3199 Village Ln",
    "sg:city":"Port Charlotte",
    "sg:classifiers":[
        {
            "category":"Autos & Motor Vehicles",
            "subcategory":"Automobile Sales",
            "type":"Retail Goods"
        }
    ],
    "sg:phone":"+1 941 627 8972",
    "sg:postcode":"33953",
    "sg:province":"FL",
    "wof:name":"Golf Buggy Gear",
    "wof:placetype":"venue"
},
  "geometry": {"coordinates":[-82.218772,26.981845],"type":"Point"}
}