{
  "type": "Feature",
  "properties": {
    "addr:full":"1268 Camberly Ct Heathrow FL 32746",
    "addr:housenumber":"1268",
    "addr:postcode":"32746",
    "addr:street":"Camberly Ct",
    "iso:country":"US",
    "sg:address":"1268 Camberly Ct",
    "sg:city":"Heathrow",
    "sg:classifiers":[
        {
            "category":"Professional",
            "type":"Services"
        }
    ],
    "sg:phone":"+1 407 804 0090",
    "sg:postcode":"32746",
    "sg:province":"FL",
    "sg:tags":[
        "establishment"
    ],
    "wof:name":"Sportravel International",
    "wof:placetype":"venue"
},
  "geometry": {"coordinates":[-81.371529,28.772184],"type":"Point"}
}