{
  "type": "Feature",
  "properties": {
    "iso:country":"US",
    "sg:address":"5143 W Rio Vista Ave",
    "sg:city":"Tampa",
    "sg:classifiers":[
        {
            "category":"Wholesale",
            "subcategory":"Electrical",
            "type":"Manufacturing & Wholesale Goods"
        }
    ],
    "sg:phone":"+1 941 764 9733",
    "sg:postcode":"33634",
    "sg:province":"FL",
    "sg:tags":[
        "equipment",
        "material"
    ],
    "sg:website":"www.cccne.com",
    "wof:name":"Computer Cable Connection Inc",
    "wof:placetype":"venue"
},
  "geometry": {"coordinates":[-82.526338,27.999737],"type":"Point"}
}