{
  "type": "Feature",
  "properties": {
    "iso:country":"US",
    "sg:address":"12928 Chris Pl",
    "sg:city":"Thonotosassa",
    "sg:classifiers":[
        {
            "category":"Home & Garden",
            "subcategory":"Mobile Homes",
            "type":"Retail Goods"
        }
    ],
    "sg:phone":"+1 813 986 2301",
    "sg:postcode":"33592",
    "sg:province":"FL",
    "wof:name":"Nature Home Park",
    "wof:placetype":"venue"
},
  "geometry": {"coordinates":[-82.32767699999999,28.081201],"type":"Point"}
}