{
  "type": "Feature",
  "properties": {
    "addr:full":"3425 13th St St Cloud FL 34769",
    "addr:housenumber":"3425",
    "addr:postcode":"34769",
    "addr:street":"13Th St",
    "iso:country":"US",
    "sg:address":"3425 13th St",
    "sg:city":"St Cloud",
    "sg:classifiers":[
        {
            "category":"Retail",
            "subcategory":"Auto Rental",
            "type":"Services"
        }
    ],
    "sg:phone":"+1 407 957 1330",
    "sg:postcode":"34769",
    "sg:province":"FL",
    "sg:tags":[
        "renting",
        "automobile"
    ],
    "wof:name":"Enterprise Rent-A-Car",
    "wof:placetype":"venue"
},
  "geometry": {"coordinates":[-81.30827499999999,28.248168],"type":"Point"}
}