{
  "type": "Feature",
  "properties": {
    "addr:full":"2986 Noland St Marianna FL 32446",
    "addr:housenumber":"2986",
    "addr:postcode":"32446",
    "addr:street":"Noland St",
    "iso:country":"US",
    "sg:address":"2986 Noland St",
    "sg:city":"Marianna",
    "sg:classifiers":[
        {
            "category":"Shopping",
            "type":"Retail Goods"
        }
    ],
    "sg:phone":"+1 850 526 7410",
    "sg:postcode":"32446",
    "sg:province":"FL",
    "sg:tags":[
        "merchandise"
    ],
    "wof:name":"Tactical Street Warrior LLC",
    "wof:placetype":"venue"
},
  "geometry": {"coordinates":[-85.221214,30.778677],"type":"Point"}
}