{
  "type": "Feature",
  "properties": {
    "iso:country":"US",
    "sg:address":"2601 2nd Ave",
    "sg:city":"Tampa",
    "sg:classifiers":[
        {
            "category":"Wholesale",
            "subcategory":"Hardware",
            "type":"Manufacturing & Wholesale Goods"
        }
    ],
    "sg:phone":"+1 813 870 0340",
    "sg:postcode":"33605",
    "sg:province":"FL",
    "sg:tags":[
        "equipment",
        "commercial",
        "refrigeration",
        "general"
    ],
    "wof:name":"Rodar Leasing Corporation",
    "wof:placetype":"venue"
},
  "geometry": {"coordinates":[-82.429405,27.956629],"type":"Point"}
}