{
  "type": "Feature",
  "properties": {
    "addr:full":"45 NW 203rd Ter Miami FL 33169",
    "addr:housenumber":"45",
    "addr:postcode":"33169",
    "addr:street":"Nw 203Rd Ter",
    "iso:country":"US",
    "sg:address":"45 NW 203rd Ter",
    "sg:city":"Miami",
    "sg:classifiers":[
        {
            "category":"Real Estate",
            "subcategory":"Real Estate Operator",
            "type":"Services"
        }
    ],
    "sg:phone":"+1 305 655 9988",
    "sg:postcode":"33169",
    "sg:province":"FL",
    "sg:tags":[
        "apartment"
    ],
    "wof:name":"Lake Terraces Apartments Inc",
    "wof:placetype":"venue"
},
  "geometry": {"coordinates":[-80.20245199999999,25.961858],"type":"Point"}
}