{
  "type": "Feature",
  "properties": {
    "addr:full":"13611 Park Blvd Seminole FL 33776",
    "addr:housenumber":"13611",
    "addr:postcode":"33776",
    "addr:street":"Park Blvd",
    "iso:country":"US",
    "sg:address":"13611 Park Blvd",
    "sg:city":"Seminole",
    "sg:classifiers":[
        {
            "category":"Recreation",
            "type":"Entertainment"
        }
    ],
    "sg:phone":"+1 727 319 2288",
    "sg:postcode":"33776",
    "sg:province":"FL",
    "sg:tags":[
        "charter",
        "boat"
    ],
    "wof:name":"Bayshore Yacht Charters Inc",
    "wof:placetype":"venue"
},
  "geometry": {"coordinates":[-82.826746,27.84381],"type":"Point"}
}