{
  "type": "Feature",
  "properties": {
    "addr:full":"1907 Collier Pkwy Lutz FL 33549",
    "addr:housenumber":"1907",
    "addr:postcode":"33549",
    "addr:street":"Collier Pkwy",
    "iso:country":"US",
    "sg:address":"1907 Collier Pkwy",
    "sg:city":"Lutz",
    "sg:classifiers":[
        {
            "category":"Shopping",
            "subcategory":"Used Merchandise",
            "type":"Retail Goods"
        }
    ],
    "sg:phone":"+1 813 909 4427",
    "sg:postcode":"33549",
    "sg:province":"FL",
    "sg:tags":[
        "shop",
        "consignment"
    ],
    "wof:name":"Exchanging Hands",
    "wof:placetype":"venue"
},
  "geometry": {"coordinates":[-82.43791,28.185809],"type":"Point"}
}