{
  "type": "Feature",
  "properties": {
    "iso:country":"US",
    "sg:address":"1524 Smith St",
    "sg:city":"Orange Park",
    "sg:classifiers":[
        {
            "category":"Wholesale",
            "subcategory":"Machinery & Supplies",
            "type":"Manufacturing & Wholesale Goods"
        },
        {
            "category":"Manufacturing",
            "subcategory":"Tools & Machinery",
            "type":"Manufacturing & Wholesale Goods"
        }
    ],
    "sg:phone":"+1 904 728 0261",
    "sg:postcode":"32073",
    "sg:province":"FL",
    "sg:tags":[
        "installation",
        "design",
        "inspection",
        "sprinkler",
        "system"
    ],
    "wof:name":"Aegis Fire Protection Systems",
    "wof:placetype":"venue"
},
  "geometry": {"coordinates":[-81.703192,30.170677],"type":"Point"}
}