{
  "type": "Feature",
  "properties": {
    "iso:country":"US",
    "sg:address":"501 Eglin Pkwy",
    "sg:city":"Fort Walton Bch",
    "sg:classifiers":[
        {
            "category":"Retail",
            "subcategory":"Auto Rental",
            "type":"Services"
        }
    ],
    "sg:phone":"+1 850 862 4265",
    "sg:postcode":"32547",
    "sg:province":"FL",
    "sg:tags":[
        "renting",
        "leasing",
        "trailer"
    ],
    "wof:name":"U-Haul Co",
    "wof:placetype":"venue"
},
  "geometry": {"coordinates":[-86.599403,30.440113],"type":"Point"}
}