{
  "type": "Feature",
  "properties": {
    "addr:full":"1 King St Saint Augustine FL 32084",
    "addr:housenumber":"1",
    "addr:postcode":"32084",
    "addr:street":"King St",
    "iso:country":"US",
    "sg:address":"1 King St",
    "sg:city":"Saint Augustine",
    "sg:classifiers":[
        {
            "category":"Banks & Credit Unions",
            "subcategory":"Investment Brokerage",
            "type":"Services"
        }
    ],
    "sg:phone":"+1 904 826 3900",
    "sg:postcode":"32084",
    "sg:province":"FL",
    "sg:tags":[
        "security"
    ],
    "wof:name":"Anderson & Strudwick Inc",
    "wof:placetype":"venue"
},
  "geometry": {"coordinates":[-81.310946,29.89226],"type":"Point"}
}