{
  "type": "Feature",
  "properties": {
    "addr:full":"400 S Florida Ave Lakeland FL 33801",
    "addr:housenumber":"400",
    "addr:postcode":"33801",
    "addr:street":"S Florida Ave",
    "iso:country":"US",
    "sg:address":"400 S Florida Ave",
    "sg:city":"Lakeland",
    "sg:classifiers":[
        {
            "category":"Social Services",
            "subcategory":"Adult Care",
            "type":"Services"
        }
    ],
    "sg:phone":"+1 863 683 1000",
    "sg:postcode":"33801",
    "sg:province":"FL",
    "sg:tags":[
        "home",
        "residential"
    ],
    "sg:website":"www.lakemortonplaza.com",
    "wof:name":"Lake Morton Plaza",
    "wof:placetype":"venue"
},
  "geometry": {"coordinates":[-81.95717399999999,28.039568],"type":"Point"}
}