{
  "type": "Feature",
  "properties": {
    "iso:country":"US",
    "sg:address":"4525 Bee Ridge Rd",
    "sg:city":"Sarasota",
    "sg:classifiers":[
        {
            "category":"Shopping",
            "type":"Retail Goods"
        }
    ],
    "sg:phone":"+1 941 379 2220",
    "sg:postcode":"34233",
    "sg:province":"FL",
    "sg:tags":[
        "cards",
        "sport",
        "baseball",
        "memorabilia"
    ],
    "wof:name":"Catcher's Mitt",
    "wof:placetype":"venue"
},
  "geometry": {"coordinates":[-82.47907499999999,27.298814],"type":"Point"}
}