{
  "type": "Feature",
  "properties": {
    "addr:full":"5750 Zip Dr Fort Myers FL 33905",
    "addr:housenumber":"5750",
    "addr:postcode":"33905",
    "addr:street":"Zip Dr",
    "iso:country":"US",
    "sg:address":"5750 Zip Dr",
    "sg:city":"Fort Myers",
    "sg:classifiers":[
        {
            "category":"Home & Garden",
            "subcategory":"Building Materials",
            "type":"Retail Goods"
        }
    ],
    "sg:phone":"+1 239 693 7720",
    "sg:postcode":"33905",
    "sg:province":"FL",
    "sg:tags":[
        "shutter"
    ],
    "wof:name":"Affordable Storm & Security",
    "wof:placetype":"venue"
},
  "geometry": {"coordinates":[-81.806921,26.65851],"type":"Point"}
}