{
  "type": "Feature",
  "properties": {
    "iso:country":"US",
    "sg:address":"1115 61st Avenue Ter E",
    "sg:city":"Bradenton",
    "sg:classifiers":[
        {
            "category":"Farming",
            "subcategory":"Livestock Farm",
            "type":"Manufacturing & Wholesale Goods"
        }
    ],
    "sg:phone":"+1 941 755 2460",
    "sg:postcode":"34203",
    "sg:province":"FL",
    "sg:tags":[
        "beef",
        "feedlot",
        "cattle"
    ],
    "wof:name":"Chancey Citrus & Cattle",
    "wof:placetype":"venue"
},
  "geometry": {"coordinates":[-82.55203400000001,27.431564],"type":"Point"}
}