{
  "type": "Feature",
  "properties": {
    "addr:full":"3290 US Hwy 1 S Saint Augustine FL 32086",
    "addr:housenumber":"3290",
    "addr:postcode":"32086",
    "addr:street":"Us Hwy 1 S",
    "iso:country":"US",
    "sg:address":"3290 US Hwy 1 S",
    "sg:city":"Saint Augustine",
    "sg:classifiers":[
        {
            "category":"Manufacturing",
            "subcategory":"Printing",
            "type":"Manufacturing & Wholesale Goods"
        }
    ],
    "sg:phone":"+1 904 794 0011",
    "sg:postcode":"32086",
    "sg:province":"FL",
    "sg:tags":[
        "custom",
        "publishing",
        "internet"
    ],
    "wof:name":"Saint George Publishing & Prtg",
    "wof:placetype":"venue"
},
  "geometry": {"coordinates":[-81.32226799999999,29.833579],"type":"Point"}
}