{
  "type": "Feature",
  "properties": {
    "iso:country":"US",
    "sg:address":"1101 S Rogers Cir",
    "sg:city":"Boca Raton",
    "sg:classifiers":[
        {
            "category":"Building & Trades",
            "subcategory":"Construction",
            "type":"Services"
        }
    ],
    "sg:phone":"+1 561 997 8520",
    "sg:postcode":"33487",
    "sg:province":"FL",
    "sg:tags":[
        "house"
    ],
    "wof:name":"Courchene Development Corp",
    "wof:placetype":"venue"
},
  "geometry": {"coordinates":[-80.109779,26.403416],"type":"Point"}
}