{
  "type": "Feature",
  "properties": {
    "iso:country":"US",
    "sg:address":"5085 Sunset Ct",
    "sg:city":"Windermere",
    "sg:classifiers":[
        {
            "category":"Real Estate",
            "subcategory":"Real Estate Services",
            "type":"Services"
        },
        {
            "category":"Real Estate",
            "subcategory":"Real Estate Agent",
            "type":"Services"
        }
    ],
    "sg:phone":"+1 407 557 5757",
    "sg:postcode":"34786",
    "sg:province":"FL",
    "sg:tags":[
        "buyer",
        "broker"
    ],
    "wof:name":"Capitalist Realty",
    "wof:placetype":"venue"
},
  "geometry": {"coordinates":[-81.516424,28.494414],"type":"Point"}
}