{
  "type": "Feature",
  "properties": {
    "iso:country":"US",
    "sg:address":"723 17th St N",
    "sg:city":"St Petersburg",
    "sg:classifiers":[
        {
            "category":"Organizations",
            "subcategory":"Religious Organization",
            "type":"Services"
        }
    ],
    "sg:phone":"+1 727 822 7932",
    "sg:postcode":"33713",
    "sg:province":"FL",
    "wof:name":"Theosophical Society",
    "wof:placetype":"venue"
},
  "geometry": {"coordinates":[-82.65588,27.781132],"type":"Point"}
}