{
  "type": "Feature",
  "properties": {
    "addr:full":"2930 Langley Ave Pensacola FL 32504",
    "addr:housenumber":"2930",
    "addr:postcode":"32504",
    "addr:street":"Langley Ave",
    "iso:country":"US",
    "sg:address":"2930 Langley Ave",
    "sg:city":"Pensacola",
    "sg:classifiers":[
        {
            "category":"Health Services",
            "subcategory":"Clinic",
            "type":"Services"
        }
    ],
    "sg:phone":"+1 850 494 1220",
    "sg:postcode":"32504",
    "sg:province":"FL",
    "sg:tags":[
        "allied"
    ],
    "wof:name":"Insurance Examiners Inc",
    "wof:placetype":"venue"
},
  "geometry": {"coordinates":[-87.188875,30.487884],"type":"Point"}
}