{
  "type": "Feature",
  "properties": {
    "iso:country":"US",
    "sg:address":"7575 Dr Phillips Blvd",
    "sg:city":"Orlando",
    "sg:classifiers":[
        {
            "category":"Health Services",
            "subcategory":"Doctor",
            "type":"Services"
        }
    ],
    "sg:phone":"+1 877 252 8167",
    "sg:postcode":"32819",
    "sg:province":"FL",
    "sg:tags":[
        "physician",
        "family",
        "practice",
        "surgeons",
        "medicine",
        "dermatology"
    ],
    "sg:website":"http://www.sandlakedermatology.com",
    "wof:name":"Crotty Christopher P Md",
    "wof:placetype":"venue"
},
  "geometry": {"coordinates":[-81.487968,28.451521],"type":"Point"}
}