{
  "type": "Feature",
  "properties": {
    "iso:country":"US",
    "sg:address":"2010 Westmont St",
    "sg:city":"Jacksonville",
    "sg:classifiers":[
        {
            "category":"Personal",
            "subcategory":"Barber",
            "type":"Services"
        }
    ],
    "sg:phone":"+1 904 346 3207",
    "sg:postcode":"32207",
    "sg:province":"FL",
    "sg:tags":[
        "shop"
    ],
    "wof:name":"Bellecraft Hair Replacement",
    "wof:placetype":"venue"
},
  "geometry": {"coordinates":[-81.64162399999999,30.298799],"type":"Point"}
}