{
  "type": "Feature",
  "properties": {
    "iso:country":"US",
    "sg:address":"1750 25th St",
    "sg:city":"Vero Beach",
    "sg:classifiers":[
        {
            "category":"Government",
            "subcategory":"Office",
            "type":"Public Place"
        }
    ],
    "sg:phone":"+1 772 226 1412",
    "sg:postcode":"32960",
    "sg:province":"FL",
    "wof:name":"Indian River County Elections",
    "wof:placetype":"venue"
},
  "geometry": {"coordinates":[-80.402334,27.644345],"type":"Point"}
}