{
  "type": "Feature",
  "properties": {
    "iso:country":"US",
    "sg:address":"1001 Brickell Bay Dr Fl 9",
    "sg:city":"Miami",
    "sg:classifiers":[
        {
            "category":"Education",
            "subcategory":"Special Training",
            "type":"Public Place"
        }
    ],
    "sg:phone":"+1 305 373 5500",
    "sg:postcode":"33131",
    "sg:province":"FL",
    "sg:tags":[
        "educational"
    ],
    "wof:name":"Fundacion Carlos Beltran, Inc.",
    "wof:placetype":"venue"
},
  "geometry": {"coordinates":[-80.19006899999999,25.763619],"type":"Point"}
}