{
  "type": "Feature",
  "properties": {
    "addr:full":"1930 Park Meadows Dr Fort Myers FL 33907",
    "addr:housenumber":"1930",
    "addr:postcode":"33907",
    "addr:street":"Park Meadows Dr",
    "iso:country":"US",
    "sg:address":"1930 Park Meadows Dr",
    "sg:city":"Fort Myers",
    "sg:classifiers":[
        {
            "category":"Banks & Credit Unions",
            "subcategory":"Financial Services",
            "type":"Services"
        }
    ],
    "sg:phone":"+1 239 931 5626",
    "sg:postcode":"33907",
    "sg:province":"FL",
    "sg:tags":[
        "broker",
        "mortgage"
    ],
    "wof:name":"Davidson & Neary Mortgage Brokers",
    "wof:placetype":"venue"
},
  "geometry": {"coordinates":[-81.874447,26.567023],"type":"Point"}
}