{
  "type": "Feature",
  "properties": {
    "iso:country":"US",
    "sg:address":"14241 SW 143rd Ct",
    "sg:city":"Miami",
    "sg:classifiers":[
        {
            "category":"Professional",
            "subcategory":"Engineering",
            "type":"Services"
        }
    ],
    "sg:phone":"+1 305 232 2340",
    "sg:postcode":"33186",
    "sg:province":"FL",
    "sg:tags":[
        "consulting",
        "engineer"
    ],
    "sg:website":"http://www.downrite.com",
    "wof:name":"Down-Rite Engineering Corp",
    "wof:placetype":"venue"
},
  "geometry": {"coordinates":[-80.42600400000001,25.635013],"type":"Point"}
}