{
  "type": "Feature",
  "properties": {
    "addr:full":"5770 W Irlo Bronsn Mmrl Hwy Kissimmee FL 34746",
    "addr:housenumber":"5770",
    "addr:postcode":"34746",
    "addr:street":"W Irlo Bronsn Mmrl Hwy",
    "iso:country":"US",
    "sg:address":"5770 W Irlo Bronsn Mmrl Hwy",
    "sg:city":"Kissimmee",
    "sg:classifiers":[
        {
            "category":"Airline",
            "type":"Transportation"
        },
        {
            "category":"Retail",
            "subcategory":"Auto Repair",
            "type":"Services"
        }
    ],
    "sg:phone":"+1 407 396 0928",
    "sg:postcode":"34746",
    "sg:province":"FL",
    "sg:tags":[
        "airport"
    ],
    "wof:name":"Budget",
    "wof:placetype":"venue"
},
  "geometry": {"coordinates":[-81.51599899999999,28.332701],"type":"Point"}
}