{
  "type": "Feature",
  "properties": {
    "iso:country":"US",
    "sg:address":"1064 Orange Woods Blvd",
    "sg:city":"Rockledge",
    "sg:classifiers":[
        {
            "category":"Building & Trades",
            "subcategory":"Electrical",
            "type":"Services"
        }
    ],
    "sg:phone":"+1 321 631 0538",
    "sg:postcode":"32955",
    "sg:province":"FL",
    "sg:tags":[
        "electrical",
        "electric",
        "contractor"
    ],
    "wof:name":"Larry Hall's Electric Inc",
    "wof:placetype":"venue"
},
  "geometry": {"coordinates":[-80.74797700000001,28.307877],"type":"Point"}
}