{
  "type": "Feature",
  "properties": {
    "addr:full":"3030 N Rocky Point Dr Tampa FL 33607",
    "addr:housenumber":"3030",
    "addr:postcode":"33607",
    "addr:street":"N Rocky Point Dr",
    "iso:country":"US",
    "sg:address":"3030 N Rocky Point Dr",
    "sg:city":"Tampa",
    "sg:classifiers":[
        {
            "category":"Utilities",
            "subcategory":"Telephone",
            "type":"Services"
        }
    ],
    "sg:phone":"+1 813 282 7769",
    "sg:postcode":"33607",
    "sg:province":"FL",
    "sg:tags":[
        "communications"
    ],
    "wof:name":"Sales Office",
    "wof:placetype":"venue"
},
  "geometry": {"coordinates":[-82.56802500000001,27.967886],"type":"Point"}
}