{
  "type": "Feature",
  "properties": {
    "addr:full":"14306 N Dale Mabry Hwy Tampa FL 33618",
    "addr:housenumber":"14306",
    "addr:postcode":"33618",
    "addr:street":"N Dale Mabry Hwy",
    "iso:country":"US",
    "sg:address":"14306 N Dale Mabry Hwy",
    "sg:city":"Tampa",
    "sg:classifiers":[
        {
            "category":"Home & Garden",
            "subcategory":"Carpets & Floor Coverings",
            "type":"Retail Goods"
        }
    ],
    "sg:phone":"+1 813 961 1362",
    "sg:postcode":"33618",
    "sg:province":"FL",
    "wof:name":"Naffco Carpet & Blinds",
    "wof:placetype":"venue"
},
  "geometry": {"coordinates":[-82.50681,28.076339],"type":"Point"}
}