{
  "type": "Feature",
  "properties": {
    "iso:country":"US",
    "sg:address":"15794 SW 141st St",
    "sg:city":"Miami",
    "sg:classifiers":[
        {
            "category":"Parking",
            "subcategory":"Garage",
            "type":"Transportation"
        }
    ],
    "sg:phone":"+1 305 254 2104",
    "sg:postcode":"33196",
    "sg:province":"FL",
    "sg:tags":[
        "lot"
    ],
    "wof:name":"Valet Express Parking System I",
    "wof:placetype":"venue"
},
  "geometry": {"coordinates":[-80.4495,25.63568],"type":"Point"}
}