{
  "type": "Feature",
  "properties": {
    "addr:full":"9251 NE State Rd 24 Bronson FL 32621",
    "addr:housenumber":"9251;24",
    "addr:postcode":"32621",
    "addr:street":"Ne State Rd",
    "iso:country":"US",
    "sg:address":"9251 NE State Rd 24",
    "sg:city":"Bronson",
    "sg:classifiers":[
        {
            "category":"Building & Trades",
            "subcategory":"Construction",
            "type":"Services"
        }
    ],
    "sg:phone":"+1 352 486 1588",
    "sg:postcode":"32621",
    "sg:province":"FL",
    "sg:tags":[
        "contractor"
    ],
    "wof:name":"Sothard Contractors",
    "wof:placetype":"venue"
},
  "geometry": {"coordinates":[-82.621369,29.464],"type":"Point"}
}