{
  "type": "Feature",
  "properties": {
    "iso:country":"US",
    "sg:address":"495 Baker Ave",
    "sg:city":"Bartow",
    "sg:classifiers":[
        {
            "category":"Organizations",
            "subcategory":"Religious Organization",
            "type":"Services"
        }
    ],
    "sg:phone":"+1 863 533 8633",
    "sg:postcode":"33830",
    "sg:province":"FL",
    "sg:tags":[
        "church"
    ],
    "wof:name":"Ebenezer Seventh Day Adventist",
    "wof:placetype":"venue"
},
  "geometry": {"coordinates":[-81.853612,27.898992],"type":"Point"}
}