{
  "type": "Feature",
  "properties": {
    "addr:full":"2788 Summerdale Dr Clearwater FL 33761",
    "addr:housenumber":"2788",
    "addr:postcode":"33761",
    "addr:street":"Summerdale Dr",
    "iso:country":"US",
    "sg:address":"2788 Summerdale Dr",
    "sg:city":"Clearwater",
    "sg:classifiers":[
        {
            "category":"Retail",
            "subcategory":"Repair Shop",
            "type":"Services"
        }
    ],
    "sg:phone":"+1 727 796 0292",
    "sg:postcode":"33761",
    "sg:province":"FL",
    "sg:tags":[
        "locksmith"
    ],
    "wof:name":"Countryside Locksmith",
    "wof:placetype":"venue"
},
  "geometry": {"coordinates":[-82.73399000000001,28.023469],"type":"Point"}
}