{
  "type": "Feature",
  "properties": {
    "addr:full":"418 S Sanford Ave Sanford FL 32771",
    "addr:housenumber":"418",
    "addr:postcode":"32771",
    "addr:street":"S Sanford Ave",
    "iso:country":"US",
    "sg:address":"418 S Sanford Ave",
    "sg:city":"Sanford",
    "sg:classifiers":[
        {
            "category":"Personal",
            "subcategory":"Barber",
            "type":"Services"
        }
    ],
    "sg:phone":"+1 407 323 0535",
    "sg:postcode":"32771",
    "sg:province":"FL",
    "wof:name":"Beverly's Hair Cutting Svc",
    "wof:placetype":"venue"
},
  "geometry": {"coordinates":[-81.265016,28.808246],"type":"Point"}
}