{
  "type": "Feature",
  "properties": {
    "iso:country":"US",
    "sg:address":"2200 SW 97th Ave",
    "sg:city":"Miami",
    "sg:classifiers":[
        {
            "category":"Building & Trades",
            "subcategory":"Equipment Rental",
            "type":"Services"
        }
    ],
    "sg:phone":"+1 305 992 3207",
    "sg:postcode":"33165",
    "sg:province":"FL",
    "sg:tags":[
        "yard",
        "leasing",
        "store"
    ],
    "wof:name":"Rcl Equipment Rental",
    "wof:placetype":"venue"
},
  "geometry": {"coordinates":[-80.351697,25.748624],"type":"Point"}
}