{
  "type": "Feature",
  "properties": {
    "addr:full":"500 Ave A Satellite Beach FL 32951",
    "addr:housenumber":"500",
    "addr:postcode":"32951",
    "addr:street":"Ave A Satellite Beach",
    "iso:country":"US",
    "sg:address":"500 Ave A",
    "sg:city":"Satellite Beach",
    "sg:classifiers":[
        {
            "category":"Food & Beverages",
            "subcategory":"Groceries & Convenience Stores",
            "type":"Retail Goods"
        }
    ],
    "sg:phone":"+1 321 773 7732",
    "sg:postcode":"32951",
    "sg:province":"FL",
    "wof:name":"Bam Of America Corp",
    "wof:placetype":"venue"
},
  "geometry": {"coordinates":[-80.56612699999999,28.069414],"type":"Point"}
}