{
  "type": "Feature",
  "properties": {
    "iso:country":"US",
    "sg:address":"1496 Old Kings Rd",
    "sg:city":"Daytona Beach",
    "sg:classifiers":[
        {
            "category":"Utilities",
            "subcategory":"Telephone",
            "type":"Services"
        }
    ],
    "sg:phone":"+1 386 258 5792",
    "sg:postcode":"32117",
    "sg:province":"FL",
    "sg:tags":[
        "communications"
    ],
    "wof:name":"Sparkling Spirit",
    "wof:placetype":"venue"
},
  "geometry": {"coordinates":[-81.06573400000001,29.242887],"type":"Point"}
}