{
  "type": "Feature",
  "properties": {
    "iso:country":"US",
    "sg:address":"4221 W Boy Scout Blvd",
    "sg:city":"Tampa",
    "sg:classifiers":[
        {
            "category":"Banks & Credit Unions",
            "subcategory":"Bank",
            "type":"Services"
        }
    ],
    "sg:phone":"+1 813 226 0980",
    "sg:postcode":"33607",
    "sg:province":"FL",
    "wof:name":"RBC Centura Bank",
    "wof:placetype":"venue"
},
  "geometry": {"coordinates":[-82.51399600000001,27.965262],"type":"Point"}
}