{
  "type": "Feature",
  "properties": {
    "addr:full":"991 Gannet Ave NW Palm Bay FL 32907",
    "addr:housenumber":"991",
    "addr:postcode":"32907",
    "addr:street":"Gannet Ave Nw",
    "iso:country":"US",
    "sg:address":"991 Gannet Ave NW",
    "sg:city":"Palm Bay",
    "sg:classifiers":[
        {
            "category":"Wholesale",
            "subcategory":"Toys & Hobbies",
            "type":"Manufacturing & Wholesale Goods"
        }
    ],
    "sg:phone":"+1 321 768 6933",
    "sg:postcode":"32907",
    "sg:province":"FL",
    "wof:name":"Crafted Creations",
    "wof:placetype":"venue"
},
  "geometry": {"coordinates":[-80.725177,28.023547],"type":"Point"}
}