{
  "type": "Feature",
  "properties": {
    "addr:full":"880 NW 1st Ave Boca Raton FL 33432",
    "addr:housenumber":"880",
    "addr:postcode":"33432",
    "addr:street":"Nw 1St Ave",
    "iso:country":"US",
    "sg:address":"880 NW 1st Ave",
    "sg:city":"Boca Raton",
    "sg:classifiers":[
        {
            "category":"Building & Trades",
            "subcategory":"Construction",
            "type":"Services"
        }
    ],
    "sg:phone":"+1 561 368 5797",
    "sg:postcode":"33432",
    "sg:province":"FL",
    "sg:tags":[
        "specializing",
        "development",
        "site",
        "contractor",
        "paving",
        "ex"
    ],
    "wof:name":"Asphalt Consultants Inc",
    "wof:placetype":"venue"
},
  "geometry": {"coordinates":[-80.087901,26.357646],"type":"Point"}
}