{
  "type": "Feature",
  "properties": {
    "iso:country":"US",
    "sg:address":"16442 Gaskin St",
    "sg:city":"Blountstown",
    "sg:classifiers":[
        {
            "category":"Retail",
            "subcategory":"Repair Shop",
            "type":"Services"
        }
    ],
    "sg:phone":"+1 850 674 5207",
    "sg:postcode":"32424",
    "sg:province":"FL",
    "sg:tags":[
        "upholsterer"
    ],
    "wof:name":"Schrock Upholstery",
    "wof:placetype":"venue"
},
  "geometry": {"coordinates":[-85.04847700000001,30.436703],"type":"Point"}
}