{
  "type": "Feature",
  "properties": {
    "iso:country":"US",
    "sg:address":"718 95th Ave N",
    "sg:city":"Naples",
    "sg:classifiers":[
        {
            "category":"Building & Trades",
            "subcategory":"Construction",
            "type":"Services"
        }
    ],
    "sg:phone":"+1 239 514 4066",
    "sg:postcode":"34108",
    "sg:province":"FL",
    "sg:tags":[
        "residential"
    ],
    "wof:name":"Haase Construction Co",
    "wof:placetype":"venue"
},
  "geometry": {"coordinates":[-81.80511199999999,26.257952],"type":"Point"}
}