{
  "type": "Feature",
  "properties": {
    "iso:country":"US",
    "sg:address":"2225 Sea Island Cir",
    "sg:city":"Lakeland",
    "sg:classifiers":[
        {
            "category":"Building & Trades",
            "subcategory":"Construction",
            "type":"Services"
        }
    ],
    "sg:phone":"+1 863 815 8564",
    "sg:postcode":"33810",
    "sg:province":"FL",
    "sg:tags":[
        "house"
    ],
    "wof:name":"Webster Construction & Consult",
    "wof:placetype":"venue"
},
  "geometry": {"coordinates":[-81.99291599999999,28.082189],"type":"Point"}
}