{
  "type": "Feature",
  "properties": {
    "addr:full":"5805 Blue Lagoon Dr # 200 Miami FL 33126",
    "addr:housenumber":"5805",
    "addr:postcode":"33126",
    "addr:street":"Blue Lagoon Dr # 200",
    "iso:country":"US",
    "sg:address":"5805 Blue Lagoon Dr # 200",
    "sg:city":"Miami",
    "sg:classifiers":[
        {
            "category":"Professional",
            "subcategory":"Accounting & Tax Preparation",
            "type":"Services"
        }
    ],
    "sg:phone":"+1 305 448 3898",
    "sg:postcode":"33126",
    "sg:province":"FL",
    "sg:tags":[
        "bookkeeping"
    ],
    "wof:name":"Alonso & Garcia, P.A.",
    "wof:placetype":"venue"
},
  "geometry": {"coordinates":[-80.291422,25.782937],"type":"Point"}
}