{
  "type": "Feature",
  "properties": {
    "iso:country":"US",
    "sg:address":"455 NE 23rd Ter Apt 4",
    "sg:city":"Miami",
    "sg:classifiers":[
        {
            "category":"Taxi",
            "type":"Transportation"
        }
    ],
    "sg:phone":"+1 305 965 5636",
    "sg:postcode":"33137",
    "sg:province":"FL",
    "wof:name":"A+ Limousine Inc",
    "wof:placetype":"venue"
},
  "geometry": {"coordinates":[-80.187986,25.799566],"type":"Point"}
}