{
  "type": "Feature",
  "properties": {
    "iso:country":"US",
    "sg:address":"5619 International Dr",
    "sg:city":"Orlando",
    "sg:classifiers":[
        {
            "category":"Shopping",
            "type":"Retail Goods"
        }
    ],
    "sg:phone":"+1 407 351 5966",
    "sg:postcode":"32819",
    "sg:province":"FL",
    "sg:tags":[
        "merchandise"
    ],
    "wof:name":"Ariel Sunglasses",
    "wof:placetype":"venue"
},
  "geometry": {"coordinates":[-81.458489,28.462415],"type":"Point"}
}