{
  "type": "Feature",
  "properties": {
    "iso:country":"US",
    "sg:address":"7275 Winding Lake Cir",
    "sg:city":"Oviedo",
    "sg:classifiers":[
        {
            "category":"Professional",
            "subcategory":"Detective & Security Services",
            "type":"Services"
        }
    ],
    "sg:phone":"+1 407 971 9788",
    "sg:postcode":"32765",
    "sg:province":"FL",
    "sg:tags":[
        "bodyguard",
        "patrol",
        "guard"
    ],
    "wof:name":"Infinity Protection Service, Inc",
    "wof:placetype":"venue"
},
  "geometry": {"coordinates":[-81.24976700000001,28.643841],"type":"Point"}
}