{
  "type": "Feature",
  "properties": {
    "iso:country":"US",
    "sg:address":"206 S Hopkins Ave",
    "sg:city":"Titusville",
    "sg:classifiers":[
        {
            "category":"Social Services",
            "subcategory":"Child Care",
            "type":"Services"
        }
    ],
    "sg:phone":"+1 321 268 3660",
    "sg:postcode":"32796",
    "sg:province":"FL",
    "sg:tags":[
        "kindergarten",
        "academic",
        "school"
    ],
    "wof:name":"First United Methodist Prschl",
    "wof:placetype":"venue"
},
  "geometry": {"coordinates":[-80.808397,28.61267],"type":"Point"}
}