{
  "type": "Feature",
  "properties": {
    "iso:country":"US",
    "sg:address":"400 S Orange Ave Ste 6",
    "sg:city":"Orlando",
    "sg:classifiers":[
        {
            "category":"Government",
            "subcategory":"Office",
            "type":"Public Place"
        }
    ],
    "sg:phone":"+1 407 246 2775",
    "sg:postcode":"32801",
    "sg:province":"FL",
    "wof:name":"Orlando Transportation Bureau",
    "wof:placetype":"venue"
},
  "geometry": {"coordinates":[-81.378929,28.538401],"type":"Point"}
}