{
  "type": "Feature",
  "properties": {
    "iso:country":"US",
    "sg:address":"6880 46th Ave N",
    "sg:city":"St Petersburg",
    "sg:classifiers":[
        {
            "category":"Manufacturing",
            "subcategory":"Apparel",
            "type":"Manufacturing & Wholesale Goods"
        }
    ],
    "sg:phone":"+1 727 544 0543",
    "sg:postcode":"33709",
    "sg:province":"FL",
    "sg:tags":[
        "clothing"
    ],
    "wof:name":"Max Cabana Clothing Co",
    "wof:placetype":"venue"
},
  "geometry": {"coordinates":[-82.734088,27.813558],"type":"Point"}
}