{
  "type": "Feature",
  "properties": {
    "iso:country":"US",
    "sg:address":"21943 Remson Ter",
    "sg:city":"Boca Raton",
    "sg:classifiers":[
        {
            "category":"Professional",
            "type":"Services"
        }
    ],
    "sg:phone":"+1 561 417 5458",
    "sg:postcode":"33433",
    "sg:province":"FL",
    "wof:name":"Kim Shea PA",
    "wof:placetype":"venue"
},
  "geometry": {"coordinates":[-80.148743,26.351229],"type":"Point"}
}