{
  "type": "Feature",
  "properties": {
    "iso:country":"US",
    "sg:address":"2878 S Osceola Ave",
    "sg:city":"Orlando",
    "sg:classifiers":[
        {
            "category":"Banks & Credit Unions",
            "subcategory":"Financial Services",
            "type":"Services"
        },
        {
            "category":"Banks & Credit Unions",
            "subcategory":"Investment Brokerage",
            "type":"Services"
        },
        {
            "category":"Banks & Credit Unions",
            "subcategory":"Bank",
            "type":"Services"
        },
        {
            "category":"Real Estate",
            "subcategory":"Developer",
            "type":"Services"
        }
    ],
    "sg:phone":"+1 407 481 2289",
    "sg:postcode":"32806",
    "sg:province":"FL",
    "sg:tags":[
        "advisory",
        "management",
        "investing",
        "broker",
        "stock",
        "bond"
    ],
    "wof:name":"Doudney Investment Company Inc",
    "wof:placetype":"venue"
},
  "geometry": {"coordinates":[-81.370216,28.51005],"type":"Point"}
}