{
  "type": "Feature",
  "properties": {
    "iso:country":"US",
    "sg:address":"3912 Lake Alfred Rd",
    "sg:city":"Winter Haven",
    "sg:classifiers":[
        {
            "category":"Building & Trades",
            "subcategory":"Electrical",
            "type":"Services"
        }
    ],
    "sg:phone":"+1 863 956 4044",
    "sg:postcode":"33881",
    "sg:province":"FL",
    "sg:tags":[
        "electric",
        "contractor"
    ],
    "wof:name":"Frost Electric",
    "wof:placetype":"venue"
},
  "geometry": {"coordinates":[-81.732744,28.071344],"type":"Point"}
}