{
  "type": "Feature",
  "properties": {
    "iso:country":"US",
    "sg:address":"9955 E Bay Harbor Dr",
    "sg:city":"Miami Beach",
    "sg:classifiers":[
        {
            "category":"Professional",
            "subcategory":"Business Services",
            "type":"Services"
        }
    ],
    "sg:phone":"+1 305 715 7405",
    "sg:postcode":"33154",
    "sg:province":"FL",
    "wof:name":"Alarm Response Monitoring Brks",
    "wof:placetype":"venue"
},
  "geometry": {"coordinates":[-80.130754,25.890111],"type":"Point"}
}