{
  "type": "Feature",
  "properties": {
    "addr:full":"8635 NW 21st Ct Pompano Beach FL 33071",
    "addr:housenumber":"8635",
    "addr:postcode":"33071",
    "addr:street":"Nw 21St Ct",
    "iso:country":"US",
    "sg:address":"8635 NW 21st Ct",
    "sg:city":"Pompano Beach",
    "sg:classifiers":[
        {
            "category":"Building & Trades",
            "subcategory":"Construction",
            "type":"Services"
        }
    ],
    "sg:phone":"+1 954 341 9734",
    "sg:postcode":"33071",
    "sg:province":"FL",
    "sg:tags":[
        "steel",
        "erection",
        "structural"
    ],
    "wof:name":"Alamia Inc Richard T",
    "wof:placetype":"venue"
},
  "geometry": {"coordinates":[-80.241066,26.257433],"type":"Point"}
}