{
  "type": "Feature",
  "properties": {
    "addr:full":"70 Pine Forrest Dr Haines City FL 33844",
    "addr:housenumber":"70",
    "addr:postcode":"33844",
    "addr:street":"Pine Forrest Dr",
    "iso:country":"US",
    "sg:address":"70 Pine Forrest Dr",
    "sg:city":"Haines City",
    "sg:classifiers":[
        {
            "category":"Farming",
            "subcategory":"Nursery",
            "type":"Manufacturing & Wholesale Goods"
        }
    ],
    "sg:phone":"+1 863 421 2360",
    "sg:postcode":"33844",
    "sg:province":"FL",
    "sg:tags":[
        "greenhouse"
    ],
    "wof:name":"Magic Orchids Farm",
    "wof:placetype":"venue"
},
  "geometry": {"coordinates":[-81.55646900000001,28.056782],"type":"Point"}
}