{
  "type": "Feature",
  "properties": {
    "addr:full":"9553 Harding Ave Surfside FL 33154",
    "addr:housenumber":"9553",
    "addr:postcode":"33154",
    "addr:street":"Harding Ave",
    "iso:country":"US",
    "sg:address":"9553 Harding Ave",
    "sg:city":"Surfside",
    "sg:classifiers":[
        {
            "category":"Professional",
            "subcategory":"Business Services",
            "type":"Services"
        }
    ],
    "sg:phone":"+1 305 864 7775",
    "sg:postcode":"33154",
    "sg:province":"FL",
    "sg:tags":[
        "interior",
        "consultant",
        "design",
        "decorator"
    ],
    "wof:name":"International Interiors",
    "wof:placetype":"venue"
},
  "geometry": {"coordinates":[-80.123563,25.886091],"type":"Point"}
}