{
  "type": "Feature",
  "properties": {
    "iso:country":"US",
    "sg:address":"3636 Commercial Way",
    "sg:city":"Spring Hill",
    "sg:classifiers":[
        {
            "category":"Shopping",
            "subcategory":"Clothing, Apparel, & Fashions",
            "type":"Retail Goods"
        }
    ],
    "sg:phone":"+1 352 683 5090",
    "sg:postcode":"34606",
    "sg:province":"FL",
    "wof:name":"Genesis Thrift Boutique",
    "wof:placetype":"venue"
},
  "geometry": {"coordinates":[-82.60683400000001,28.482845],"type":"Point"}
}