{
  "type": "Feature",
  "properties": {
    "addr:full":"1318 Homestead Rd N Lehigh Acres FL 33936",
    "addr:housenumber":"1318",
    "addr:postcode":"33936",
    "addr:street":"Homestead Rd N",
    "iso:country":"US",
    "sg:address":"1318 Homestead Rd N",
    "sg:city":"Lehigh Acres",
    "sg:classifiers":[
        {
            "category":"Professional",
            "subcategory":"Accounting & Tax Preparation",
            "type":"Services"
        }
    ],
    "sg:phone":"+1 239 369 0502",
    "sg:postcode":"33936",
    "sg:province":"FL",
    "sg:tags":[
        "return",
        "filing"
    ],
    "wof:name":"H & R Block Tax Svc",
    "wof:placetype":"venue"
},
  "geometry": {"coordinates":[-81.65334799999999,26.609963],"type":"Point"}
}