{
  "type": "Feature",
  "properties": {
    "iso:country":"US",
    "sg:address":"2105 Vulcan Rd",
    "sg:city":"Apopka",
    "sg:classifiers":[
        {
            "category":"Utilities",
            "subcategory":"Recycling",
            "type":"Services"
        },
        {
            "category":"Manufacturing",
            "subcategory":"Building Materials",
            "type":"Manufacturing & Wholesale Goods"
        }
    ],
    "sg:phone":"+1 407 290 8010",
    "sg:postcode":"32703",
    "sg:province":"FL",
    "sg:tags":[
        "aggregate",
        "concrete"
    ],
    "wof:name":"Angelo's Recycled Materials",
    "wof:placetype":"venue"
},
  "geometry": {"coordinates":[-81.46791,28.635106],"type":"Point"}
}