{
  "type": "Feature",
  "properties": {
    "addr:full":"242 S McDuff Ave Jacksonville FL 32254",
    "addr:housenumber":"242",
    "addr:postcode":"32254",
    "addr:street":"S Mcduff Ave",
    "iso:country":"US",
    "sg:address":"242 S McDuff Ave",
    "sg:city":"Jacksonville",
    "sg:classifiers":[
        {
            "category":"Personal",
            "subcategory":"Beauty Salon",
            "type":"Services"
        }
    ],
    "sg:phone":"+1 904 387 3219",
    "sg:postcode":"32254",
    "sg:province":"FL",
    "sg:tags":[
        "shop"
    ],
    "wof:name":"Belinda's Beauty Salon",
    "wof:placetype":"venue"
},
  "geometry": {"coordinates":[-81.70557599999999,30.326364],"type":"Point"}
}