{
  "type": "Feature",
  "properties": {
    "addr:full":"24527 Bonnet Rd Astor FL 32102",
    "addr:housenumber":"24527",
    "addr:postcode":"32102",
    "addr:street":"Bonnet Rd",
    "iso:country":"US",
    "sg:address":"24527 Bonnet Rd",
    "sg:city":"Astor",
    "sg:classifiers":[
        {
            "category":"Home & Garden",
            "subcategory":"Carpets & Floor Coverings",
            "type":"Retail Goods"
        }
    ],
    "sg:phone":"+1 352 759 2103",
    "sg:postcode":"32102",
    "sg:province":"FL",
    "wof:name":"Barnes Carpet Layer",
    "wof:placetype":"venue"
},
  "geometry": {"coordinates":[-81.53439899999999,29.173507],"type":"Point"}
}