{
  "type": "Feature",
  "properties": {
    "iso:country":"US",
    "sg:address":"806 E Sugarland Hwy",
    "sg:city":"Clewiston",
    "sg:classifiers":[
        {
            "category":"Food & Beverages",
            "subcategory":"Groceries & Convenience Stores",
            "type":"Retail Goods"
        }
    ],
    "sg:phone":"+1 863 983 7474",
    "sg:postcode":"33440",
    "sg:province":"FL",
    "sg:tags":[
        "grocer"
    ],
    "wof:name":"LA Frontrea",
    "wof:placetype":"venue"
},
  "geometry": {"coordinates":[-80.92078600000001,26.754341],"type":"Point"}
}