{
  "type": "Feature",
  "properties": {
    "addr:full":"1933 NW 21st Ter Miami FL 33142",
    "addr:housenumber":"1933",
    "addr:postcode":"33142",
    "addr:street":"Nw 21St Ter",
    "iso:country":"US",
    "sg:address":"1933 NW 21st Ter",
    "sg:city":"Miami",
    "sg:classifiers":[
        {
            "category":"Freight",
            "type":"Transportation"
        }
    ],
    "sg:phone":"+1 305 325 1457",
    "sg:postcode":"33142",
    "sg:province":"FL",
    "sg:tags":[
        "by",
        "air"
    ],
    "sg:website":"www.allamericancargo.com",
    "wof:name":"Servicios Nicaraguenses Corp",
    "wof:placetype":"venue"
},
  "geometry": {"coordinates":[-80.229192,25.796506],"type":"Point"}
}