{
  "type": "Feature",
  "properties": {
    "addr:full":"5910 E Colonial Dr Orlando FL 32807",
    "addr:housenumber":"5910",
    "addr:postcode":"32807",
    "addr:street":"E Colonial Dr",
    "iso:country":"US",
    "sg:address":"5910 E Colonial Dr",
    "sg:city":"Orlando",
    "sg:classifiers":[
        {
            "category":"Restaurant",
            "type":"Food & Drink"
        }
    ],
    "sg:phone":"+1 407 382 6579",
    "sg:postcode":"32807",
    "sg:province":"FL",
    "wof:name":"Mi Viejo San Juan",
    "wof:placetype":"venue"
},
  "geometry": {"coordinates":[-81.30811799999999,28.559074],"type":"Point"}
}