{
  "type": "Feature",
  "properties": {
    "addr:full":"7708 Newlan Dr Orlando FL 32818",
    "addr:housenumber":"7708",
    "addr:postcode":"32818",
    "addr:street":"Newlan Dr",
    "iso:country":"US",
    "sg:address":"7708 Newlan Dr",
    "sg:city":"Orlando",
    "sg:classifiers":[
        {
            "category":"Building & Trades",
            "subcategory":"Construction",
            "type":"Services"
        }
    ],
    "sg:phone":"+1 407 291 7634",
    "sg:postcode":"32818",
    "sg:province":"FL",
    "sg:tags":[
        "home",
        "builder"
    ],
    "wof:name":"Robinson Hills Model Ctr",
    "wof:placetype":"venue"
},
  "geometry": {"coordinates":[-81.490976,28.611801],"type":"Point"}
}