{
  "type": "Feature",
  "properties": {
    "addr:full":"1250 W State Road 434 Longwood FL 32750",
    "addr:housenumber":"1250",
    "addr:postcode":"32750",
    "addr:street":"W State Road 434",
    "iso:country":"US",
    "sg:address":"1250 W State Road 434",
    "sg:city":"Longwood",
    "sg:classifiers":[
        {
            "category":"Health Services",
            "subcategory":"Doctor",
            "type":"Services"
        }
    ],
    "sg:phone":"+1 407 260 8227",
    "sg:postcode":"32750",
    "sg:province":"FL",
    "sg:tags":[
        "medicine",
        "internal"
    ],
    "wof:name":"Ranganathan Sam",
    "wof:placetype":"venue"
},
  "geometry": {"coordinates":[-81.367401,28.6971],"type":"Point"}
}