{
  "type": "Feature",
  "properties": {
    "iso:country":"US",
    "sg:address":"4824 NW 167th St",
    "sg:city":"Hialeah",
    "sg:classifiers":[
        {
            "category":"Place Of Worship",
            "type":"Public Place"
        },
        {
            "category":"Organizations",
            "subcategory":"Religious Organization",
            "type":"Services"
        }
    ],
    "sg:phone":"+1 305 624 1582",
    "sg:postcode":"33014",
    "sg:province":"FL",
    "sg:tags":[
        "church"
    ],
    "wof:name":"Faith Christian Ctr",
    "wof:placetype":"venue"
},
  "geometry": {"coordinates":[-80.278339,25.92491],"type":"Point"}
}