{
  "type": "Feature",
  "properties": {
    "addr:full":"811 NW 196th Ter Miami FL 33169",
    "addr:housenumber":"811",
    "addr:postcode":"33169",
    "addr:street":"Nw 196Th Ter",
    "iso:country":"US",
    "sg:address":"811 NW 196th Ter",
    "sg:city":"Miami",
    "sg:classifiers":[
        {
            "category":"Shopping",
            "subcategory":"Clothing, Apparel, & Fashions",
            "type":"Retail Goods"
        }
    ],
    "sg:phone":"+1 305 770 4195",
    "sg:postcode":"33169",
    "sg:province":"FL",
    "wof:name":"Omni Present Creations Inc",
    "wof:placetype":"venue"
},
  "geometry": {"coordinates":[-80.215856,25.954619],"type":"Point"}
}