{
  "type": "Feature",
  "properties": {
    "addr:full":"221 Duval St Key West FL 33040",
    "addr:housenumber":"221",
    "addr:postcode":"33040",
    "addr:street":"Duval St",
    "iso:country":"US",
    "sg:address":"221 Duval St",
    "sg:city":"Key West",
    "sg:classifiers":[
        {
            "category":"Restaurant",
            "type":"Food & Drink"
        }
    ],
    "sg:menulink":"http://www.allmenus.com/fl/key-west/58866-capt-marios-seafood-buffet/menu/",
    "sg:phone":"+1 305 292 0090",
    "sg:postcode":"33040",
    "sg:province":"FL",
    "sg:tags":[
        "seafood",
        "american"
    ],
    "wof:name":"Capt Mario's Seafood Buffet",
    "wof:placetype":"venue"
},
  "geometry": {"coordinates":[-81.80457800000001,24.558426],"type":"Point"}
}