{
  "type": "Feature",
  "properties": {
    "addr:full":"9310 Old Kings Rd S Jacksonville FL 32257",
    "addr:housenumber":"9310",
    "addr:postcode":"32257",
    "addr:street":"Old Kings Rd",
    "iso:country":"US",
    "sg:address":"9310 Old Kings Rd S",
    "sg:city":"Jacksonville",
    "sg:classifiers":[
        {
            "category":"Building & Trades",
            "subcategory":"Construction",
            "type":"Services"
        }
    ],
    "sg:phone":"+1 904 732 7396",
    "sg:postcode":"32257",
    "sg:province":"FL",
    "sg:tags":[
        "contractor"
    ],
    "wof:name":"Young American Homes Inc",
    "wof:placetype":"venue"
},
  "geometry": {"coordinates":[-81.583536,30.209347],"type":"Point"}
}