{
  "type": "Feature",
  "properties": {
    "iso:country":"US",
    "sg:address":"1200 Sarno Rd",
    "sg:city":"Melbourne",
    "sg:classifiers":[
        {
            "category":"Restaurant",
            "type":"Food & Drink"
        }
    ],
    "sg:menulink":"http://www.allmenus.com/fl/melbourne/187359-mcdonalds/menu/",
    "sg:phone":"+1 321 254 4267",
    "sg:postcode":"32935",
    "sg:province":"FL",
    "sg:tags":[
        "burger",
        "american"
    ],
    "wof:name":"McDonald's",
    "wof:placetype":"venue"
},
  "geometry": {"coordinates":[-80.638622,28.121533],"type":"Point"}
}