{
  "type": "Feature",
  "properties": {
    "iso:country":"US",
    "sg:address":"1007 Lotus St",
    "sg:city":"Lake Placid",
    "sg:classifiers":[
        {
            "category":"Building & Trades",
            "subcategory":"Landscaping Services",
            "type":"Services"
        }
    ],
    "sg:phone":"+1 863 699 6599",
    "sg:postcode":"33852",
    "sg:province":"FL",
    "sg:tags":[
        "landscape"
    ],
    "wof:name":"Duane Neiderman & Associates",
    "wof:placetype":"venue"
},
  "geometry": {"coordinates":[-81.331749,27.319824],"type":"Point"}
}