{
  "type": "Feature",
  "properties": {
    "addr:full":"10887 N Military Trl Palm Beach Gardens FL 33410",
    "addr:housenumber":"10887",
    "addr:postcode":"33410",
    "addr:street":"N Military Trl",
    "iso:country":"US",
    "sg:address":"10887 N Military Trl",
    "sg:city":"Palm Beach Gardens",
    "sg:classifiers":[
        {
            "category":"Health Services",
            "subcategory":"Doctor",
            "type":"Services"
        }
    ],
    "sg:phone":"+1 561 622 3339",
    "sg:postcode":"33410",
    "sg:province":"FL",
    "wof:name":"Donald R Picard DDS Ms",
    "wof:placetype":"venue"
},
  "geometry": {"coordinates":[-80.10529200000001,26.837298],"type":"Point"}
}