{
  "type": "Feature",
  "properties": {
    "iso:country":"US",
    "sg:address":"750 NE 7th Ave",
    "sg:city":"Dania",
    "sg:classifiers":[
        {
            "category":"Retail",
            "subcategory":"Repair Shop",
            "type":"Services"
        }
    ],
    "sg:phone":"+1 954 921 8170",
    "sg:postcode":"33004",
    "sg:province":"FL",
    "sg:tags":[
        "yacht"
    ],
    "wof:name":"Mega Marine Yacht Service Inc",
    "wof:placetype":"venue"
},
  "geometry": {"coordinates":[-80.131467,26.061939],"type":"Point"}
}