{
  "type": "Feature",
  "properties": {
    "iso:country":"US",
    "sg:address":"4820 NW 74th Pl",
    "sg:city":"Pompano Beach",
    "sg:classifiers":[
        {
            "category":"Building & Trades",
            "subcategory":"Landscaping Services",
            "type":"Services"
        }
    ],
    "sg:phone":"+1 954 421 3400",
    "sg:postcode":"33073",
    "sg:province":"FL",
    "wof:name":"Lighthouse Point Ldscpg Design",
    "wof:placetype":"venue"
},
  "geometry": {"coordinates":[-80.199365,26.323084],"type":"Point"}
}