{
  "type": "Feature",
  "properties": {
    "iso:country":"US",
    "sg:address":"5925 Edgewater Dr",
    "sg:city":"Orlando",
    "sg:classifiers":[
        {
            "category":"Retail",
            "subcategory":"Veterinary Services",
            "type":"Services"
        },
        {
            "category":"Retail",
            "subcategory":"Pet Boarding",
            "type":"Services"
        }
    ],
    "sg:phone":"+1 407 293 0212",
    "sg:postcode":"32810",
    "sg:province":"FL",
    "sg:tags":[
        "veterinarian",
        "boarding/pet",
        "sitting"
    ],
    "wof:name":"Bowen Gary I DVM",
    "wof:placetype":"venue"
},
  "geometry": {"coordinates":[-81.41680100000001,28.611401],"type":"Point"}
}