{
  "type": "Feature",
  "properties": {
    "addr:full":"4241 E 4th Ave Hialeah FL 33013",
    "addr:housenumber":"4241",
    "addr:postcode":"33013",
    "addr:street":"E 4Th Ave",
    "iso:country":"US",
    "sg:address":"4241 E 4th Ave",
    "sg:city":"Hialeah",
    "sg:classifiers":[
        {
            "category":"Shopping",
            "subcategory":"Clothing, Apparel, & Fashions",
            "type":"Retail Goods"
        }
    ],
    "sg:phone":"+1 786 413 0242",
    "sg:postcode":"33013",
    "sg:province":"FL",
    "wof:name":"Nena Fashions",
    "wof:placetype":"venue"
},
  "geometry": {"coordinates":[-80.274569,25.861234],"type":"Point"}
}