{
  "type": "Feature",
  "properties": {
    "iso:country":"US",
    "sg:address":"13800 State Rd 545",
    "sg:city":"Winter Garden",
    "sg:classifiers":[
        {
            "category":"Travel",
            "subcategory":"Hotels & Motels",
            "type":"Entertainment"
        }
    ],
    "sg:phone":"+1 407 239 8775",
    "sg:postcode":"34787",
    "sg:province":"FL",
    "sg:tags":[
        "operation"
    ],
    "wof:name":"Resorts USA Inc",
    "wof:placetype":"venue"
},
  "geometry": {"coordinates":[-81.645527,28.370724],"type":"Point"}
}