{
  "type": "Feature",
  "properties": {
    "addr:full":"114 SW 10th St Fort Lauderdale FL 33315",
    "addr:housenumber":"114",
    "addr:postcode":"33315",
    "addr:street":"Sw 10Th St",
    "iso:country":"US",
    "sg:address":"114 SW 10th St",
    "sg:city":"Fort Lauderdale",
    "sg:classifiers":[
        {
            "category":"Real Estate",
            "subcategory":"Architect",
            "type":"Services"
        }
    ],
    "sg:phone":"+1 954 467 7892",
    "sg:postcode":"33315",
    "sg:province":"FL",
    "wof:name":"Russell C Chase Architect Inc",
    "wof:placetype":"venue"
},
  "geometry": {"coordinates":[-80.143996,26.110221],"type":"Point"}
}