{
  "type": "Feature",
  "properties": {
    "addr:full":"202 S 22nd St Tampa FL 33605",
    "addr:housenumber":"202",
    "addr:postcode":"33605",
    "addr:street":"S 22Nd St",
    "iso:country":"US",
    "sg:address":"202 S 22nd St",
    "sg:city":"Tampa",
    "sg:classifiers":[
        {
            "category":"Professional",
            "subcategory":"Computer Services",
            "type":"Services"
        }
    ],
    "sg:phone":"+1 813 248 3787",
    "sg:postcode":"33605",
    "sg:province":"FL",
    "sg:tags":[
        "consultant"
    ],
    "wof:name":"Baybridge Solutions",
    "wof:placetype":"venue"
},
  "geometry": {"coordinates":[-82.43462700000001,27.94727],"type":"Point"}
}