{
  "type": "Feature",
  "properties": {
    "addr:full":"598 Ave A Satellite Beach FL 32951",
    "addr:housenumber":"598",
    "addr:postcode":"32951",
    "addr:street":"Ave A Satellite Beach",
    "iso:country":"US",
    "sg:address":"598 Ave A",
    "sg:city":"Satellite Beach",
    "sg:classifiers":[
        {
            "category":"Shopping",
            "subcategory":"Jewelry",
            "type":"Retail Goods"
        }
    ],
    "sg:phone":"+1 321 777 7628",
    "sg:postcode":"32951",
    "sg:province":"FL",
    "sg:tags":[
        "operation"
    ],
    "wof:name":"Ocean Side State Jewelers",
    "wof:placetype":"venue"
},
  "geometry": {"coordinates":[-80.563147,28.069423],"type":"Point"}
}