{
  "type": "Feature",
  "properties": {
    "iso:country":"US",
    "sg:address":"2068 Apricot Dr",
    "sg:city":"Deltona",
    "sg:classifiers":[
        {
            "category":"Building & Trades",
            "subcategory":"Landscaping Services",
            "type":"Services"
        }
    ],
    "sg:phone":"+1 386 789 5727",
    "sg:postcode":"32725",
    "sg:province":"FL",
    "sg:tags":[
        "landscape"
    ],
    "wof:name":"Bray Brothers Landscaping",
    "wof:placetype":"venue"
},
  "geometry": {"coordinates":[-81.264332,28.92192],"type":"Point"}
}