{
  "type": "Feature",
  "properties": {
    "addr:full":"722 Savage Ct Longwood FL 32750",
    "addr:housenumber":"722",
    "addr:postcode":"32750",
    "addr:street":"Savage Ct",
    "iso:country":"US",
    "sg:address":"722 Savage Ct",
    "sg:city":"Longwood",
    "sg:classifiers":[
        {
            "category":"Professional",
            "subcategory":"Computer Services",
            "type":"Services"
        }
    ],
    "sg:phone":"+1 407 660 2228",
    "sg:postcode":"32750",
    "sg:province":"FL",
    "sg:tags":[
        "repair"
    ],
    "sg:website":"www.acculetters.com",
    "wof:name":"Acculetters Llc",
    "wof:placetype":"venue"
},
  "geometry": {"coordinates":[-81.360136,28.696675],"type":"Point"}
}