{
  "type": "Feature",
  "properties": {
    "addr:full":"5193 Hawks Nest Dr Milton FL 32570",
    "addr:housenumber":"5193",
    "addr:postcode":"32570",
    "addr:street":"Hawks Nest Dr",
    "iso:country":"US",
    "sg:address":"5193 Hawks Nest Dr",
    "sg:city":"Milton",
    "sg:classifiers":[
        {
            "category":"Recreation",
            "subcategory":"Marina",
            "type":"Entertainment"
        }
    ],
    "sg:phone":"+1 850 623 2446",
    "sg:postcode":"32570",
    "sg:province":"FL",
    "sg:tags":[
        "repairing",
        "boat"
    ],
    "wof:name":"Hull 9 Yards",
    "wof:placetype":"venue"
},
  "geometry": {"coordinates":[-87.067177,30.621839],"type":"Point"}
}