{
  "type": "Feature",
  "properties": {
    "iso:country":"US",
    "sg:address":"3208 W Rogers Ave",
    "sg:city":"Tampa",
    "sg:classifiers":[
        {
            "category":"Real Estate",
            "subcategory":"Real Estate Agent",
            "type":"Services"
        }
    ],
    "sg:phone":"+1 813 839 1751",
    "sg:postcode":"33611",
    "sg:province":"FL",
    "wof:name":"Kirby Appraisal Group Inc",
    "wof:placetype":"venue"
},
  "geometry": {"coordinates":[-82.497885,27.886439],"type":"Point"}
}