{
  "type": "Feature",
  "properties": {
    "iso:country":"US",
    "sg:address":"14290 SW 232nd St",
    "sg:city":"Miami",
    "sg:classifiers":[
        {
            "category":"Building & Trades",
            "subcategory":"Landscaping Services",
            "type":"Services"
        }
    ],
    "sg:phone":"+1 305 233 3139",
    "sg:postcode":"33170",
    "sg:province":"FL",
    "sg:tags":[
        "consultant",
        "designer",
        "landscape",
        "contractor"
    ],
    "wof:name":"Signature Trees & Palms",
    "wof:placetype":"venue"
},
  "geometry": {"coordinates":[-80.422495,25.551196],"type":"Point"}
}