{
  "type": "Feature",
  "properties": {
    "iso:country":"US",
    "sg:address":"8061 NW 155th St",
    "sg:city":"Hialeah",
    "sg:classifiers":[
        {
            "category":"Professional",
            "subcategory":"Lawyer & Legal Services",
            "type":"Services"
        }
    ],
    "sg:phone":"+1 305 825 7080",
    "sg:postcode":"33016",
    "sg:province":"FL",
    "wof:name":"Javier L Vazquez PA",
    "wof:placetype":"venue"
},
  "geometry": {"coordinates":[-80.33196700000001,25.914675],"type":"Point"}
}