{
  "type": "Feature",
  "properties": {
    "iso:country":"US",
    "sg:address":"336 S Lakeview Dr",
    "sg:city":"Lake Helen",
    "sg:classifiers":[
        {
            "category":"Food & Beverages",
            "subcategory":"Candy",
            "type":"Retail Goods"
        }
    ],
    "sg:phone":"+1 386 774 2862",
    "sg:postcode":"32744",
    "sg:province":"FL",
    "sg:tags":[
        "confectionery"
    ],
    "wof:name":"A Taste Of Country",
    "wof:placetype":"venue"
},
  "geometry": {"coordinates":[-81.231821,28.980444],"type":"Point"}
}