{
  "type": "Feature",
  "properties": {
    "addr:full":"10017 US Hwy 19 Port Richey FL 34668",
    "addr:housenumber":"10017",
    "addr:postcode":"34668",
    "addr:street":"Us Hwy 19",
    "iso:country":"US",
    "sg:address":"10017 US Hwy 19",
    "sg:city":"Port Richey",
    "sg:classifiers":[
        {
            "category":"Home & Garden",
            "subcategory":"Building Materials",
            "type":"Retail Goods"
        }
    ],
    "sg:phone":"+1 727 869 2711",
    "sg:postcode":"34668",
    "sg:province":"FL",
    "wof:name":"Home Depot",
    "wof:placetype":"venue"
},
  "geometry": {"coordinates":[-82.704967,28.30106],"type":"Point"}
}