{
  "type": "Feature",
  "properties": {
    "addr:full":"5370 Harbor Island Ct Vero Beach FL 32967",
    "addr:housenumber":"5370",
    "addr:postcode":"32967",
    "addr:street":"Harbor Island Ct",
    "iso:country":"US",
    "sg:address":"5370 Harbor Island Ct",
    "sg:city":"Vero Beach",
    "sg:classifiers":[
        {
            "category":"Manufacturing",
            "subcategory":"Metals",
            "type":"Manufacturing & Wholesale Goods"
        }
    ],
    "sg:phone":"+1 772 778 7364",
    "sg:postcode":"32967",
    "sg:province":"FL",
    "sg:tags":[
        "product",
        "primary"
    ],
    "wof:name":"Nightingale Metals Inc",
    "wof:placetype":"venue"
},
  "geometry": {"coordinates":[-80.395944,27.690728],"type":"Point"}
}