{
  "type": "Feature",
  "properties": {
    "iso:country":"US",
    "sg:address":"1550 NW 10th Ave Ste 200",
    "sg:city":"Miami",
    "sg:classifiers":[
        {
            "category":"Banks & Credit Unions",
            "subcategory":"Financial Services",
            "type":"Services"
        }
    ],
    "sg:phone":"+1 305 243 6920",
    "sg:postcode":"33136",
    "sg:province":"FL",
    "sg:tags":[
        "information",
        "consumer"
    ],
    "wof:name":"Cancer Information Service Of Umc",
    "wof:placetype":"venue"
},
  "geometry": {"coordinates":[-80.211079,25.789747],"type":"Point"}
}