{
  "type": "Feature",
  "properties": {
    "addr:full":"375 E 49th St Ste 2 Hialeah FL 33013",
    "addr:housenumber":"375",
    "addr:postcode":"33013",
    "addr:street":"E 49Th St Ste 2",
    "iso:country":"US",
    "sg:address":"375 E 49th St Ste 2",
    "sg:city":"Hialeah",
    "sg:classifiers":[
        {
            "category":"Community Center",
            "type":"Public Place"
        }
    ],
    "sg:phone":"+1 305 823 5655",
    "sg:postcode":"33013",
    "sg:province":"FL",
    "sg:tags":[
        "medical"
    ],
    "wof:name":"Well Being Rehab Medical Center",
    "wof:placetype":"venue"
},
  "geometry": {"coordinates":[-80.275299,25.867201],"type":"Point"}
}