{
  "type": "Feature",
  "properties": {
    "addr:full":"3254 16th St N St Petersburg FL 33704",
    "addr:housenumber":"3254",
    "addr:postcode":"33704",
    "addr:street":"16Th St N",
    "iso:country":"US",
    "sg:address":"3254 16th St N",
    "sg:city":"St Petersburg",
    "sg:classifiers":[
        {
            "category":"Insurance",
            "subcategory":"Insurance Agent",
            "type":"Services"
        }
    ],
    "sg:phone":"+1 727 822 3346",
    "sg:postcode":"33704",
    "sg:province":"FL",
    "wof:name":"Ringler Associates Inc",
    "wof:placetype":"venue"
},
  "geometry": {"coordinates":[-82.655061,27.802468],"type":"Point"}
}