{
  "type": "Feature",
  "properties": {
    "addr:full":"1655 S State Hwy 7 North Lauderdale FL 33068",
    "addr:housenumber":"1655",
    "addr:postcode":"33068",
    "addr:street":"S State Hwy 7",
    "iso:country":"US",
    "sg:address":"1655 S State Hwy 7",
    "sg:city":"North Lauderdale",
    "sg:classifiers":[
        {
            "category":"Banks & Credit Unions",
            "subcategory":"Bank",
            "type":"Services"
        }
    ],
    "sg:phone":"+1 954 968 1942",
    "sg:postcode":"33068",
    "sg:province":"FL",
    "sg:tags":[
        "cashing",
        "check"
    ],
    "wof:name":"Broward Check Cashing Inc",
    "wof:placetype":"venue"
},
  "geometry": {"coordinates":[-80.20416,26.205999],"type":"Point"}
}