{
  "type": "Feature",
  "properties": {
    "iso:country":"US",
    "sg:address":"2604 State Hwy 77",
    "sg:city":"Lynn Haven",
    "sg:classifiers":[
        {
            "category":"Restaurant",
            "type":"Food & Drink"
        }
    ],
    "sg:phone":"+1 850 914 2604",
    "sg:postcode":"32444",
    "sg:province":"FL",
    "wof:name":"Wendy's",
    "wof:placetype":"venue"
},
  "geometry": {"coordinates":[-85.649596,30.218568],"type":"Point"}
}