{
  "type": "Feature",
  "properties": {
    "addr:full":"12415 Automobile Blvd Clearwater FL 33762",
    "addr:housenumber":"12415",
    "addr:postcode":"33762",
    "addr:street":"Automobile Blvd",
    "iso:country":"US",
    "sg:address":"12415 Automobile Blvd",
    "sg:city":"Clearwater",
    "sg:classifiers":[
        {
            "category":"Airline",
            "type":"Transportation"
        }
    ],
    "sg:phone":"+1 800 238 5355",
    "sg:postcode":"33762",
    "sg:province":"FL",
    "sg:tags":[
        "courier",
        "air"
    ],
    "wof:name":"Federal Express Corporation",
    "wof:placetype":"venue"
},
  "geometry": {"coordinates":[-82.69618,27.885032],"type":"Point"}
}