{
  "type": "Feature",
  "properties": {
    "iso:country":"US",
    "sg:address":"1601 Jackson St",
    "sg:city":"Fort Myers",
    "sg:classifiers":[
        {
            "category":"Professional",
            "subcategory":"Lawyer & Legal Services",
            "type":"Services"
        }
    ],
    "sg:phone":"+1 239 332 3000",
    "sg:postcode":"33901",
    "sg:province":"FL",
    "sg:tags":[
        "personal",
        "injury"
    ],
    "wof:name":"Bernardo Joseph J Attorney At Law",
    "wof:placetype":"venue"
},
  "geometry": {"coordinates":[-81.868202,26.643999],"type":"Point"}
}