{
  "type": "Feature",
  "properties": {
    "iso:country":"US",
    "sg:address":"1925 Brickell Ave",
    "sg:city":"Miami",
    "sg:classifiers":[
        {
            "category":"Shopping",
            "type":"Retail Goods"
        }
    ],
    "sg:phone":"+1 305 859 2239",
    "sg:postcode":"33129",
    "sg:province":"FL",
    "sg:tags":[
        "merchandise"
    ],
    "wof:name":"Pet Network",
    "wof:placetype":"venue"
},
  "geometry": {"coordinates":[-80.197,25.755068],"type":"Point"}
}