{
  "type": "Feature",
  "properties": {
    "addr:full":"5615 Dayflower Cir Tallahassee FL 32311",
    "addr:housenumber":"5615",
    "addr:postcode":"32311",
    "addr:street":"Dayflower Cir",
    "iso:country":"US",
    "sg:address":"5615 Dayflower Cir",
    "sg:city":"Tallahassee",
    "sg:classifiers":[
        {
            "category":"Wholesale",
            "subcategory":"Construction Materials",
            "type":"Manufacturing & Wholesale Goods"
        },
        {
            "category":"Home & Garden",
            "subcategory":"Building Materials",
            "type":"Retail Goods"
        }
    ],
    "sg:phone":"+1 850 656 8775",
    "sg:postcode":"32311",
    "sg:province":"FL",
    "sg:tags":[
        "windows-wholesale",
        "window",
        "manufacturer"
    ],
    "wof:name":"We Wash Windows",
    "wof:placetype":"venue"
},
  "geometry": {"coordinates":[-84.107974,30.38225],"type":"Point"}
}