{
  "type": "Feature",
  "properties": {
    "iso:country":"US",
    "sg:address":"500 S Howard Ave",
    "sg:city":"Tampa",
    "sg:classifiers":[
        {
            "category":"Personal",
            "subcategory":"Beauty Salon",
            "type":"Services"
        }
    ],
    "sg:phone":"+1 813 259 1331",
    "sg:postcode":"33606",
    "sg:province":"FL",
    "sg:tags":[
        "make",
        "studio"
    ],
    "wof:name":"Soho Make-Up Studio",
    "wof:placetype":"venue"
},
  "geometry": {"coordinates":[-82.483003,27.938619],"type":"Point"}
}