{
  "type": "Feature",
  "properties": {
    "addr:full":"622 W Union St Jacksonville FL 32202",
    "addr:housenumber":"622",
    "addr:postcode":"32202",
    "addr:street":"W Union St",
    "iso:country":"US",
    "sg:address":"622 W Union St",
    "sg:city":"Jacksonville",
    "sg:classifiers":[
        {
            "category":"Organizations",
            "subcategory":"Religious Organization",
            "type":"Services"
        }
    ],
    "sg:phone":"+1 904 355 1205",
    "sg:postcode":"32202",
    "sg:province":"FL",
    "wof:name":"Trinity Baptist Church",
    "wof:placetype":"venue"
},
  "geometry": {"coordinates":[-81.66452,30.333923],"type":"Point"}
}