{
  "type": "Feature",
  "properties": {
    "iso:country":"US",
    "sg:address":"12315 SW 119th Ter",
    "sg:city":"Miami",
    "sg:classifiers":[
        {
            "category":"Organizations",
            "subcategory":"Non-profit Organization",
            "type":"Services"
        }
    ],
    "sg:phone":"+1 305 969 8700",
    "sg:postcode":"33186",
    "sg:province":"FL",
    "wof:name":"Access Catholic Charities",
    "wof:placetype":"venue"
},
  "geometry": {"coordinates":[-80.39487,25.656914],"type":"Point"}
}