{
  "type": "Feature",
  "properties": {
    "addr:full":"101 NE 48th Ct Fort Lauderdale FL 33334",
    "addr:housenumber":"101",
    "addr:postcode":"33334",
    "addr:street":"Ne 48Th Ct",
    "iso:country":"US",
    "sg:address":"101 NE 48th Ct",
    "sg:city":"Fort Lauderdale",
    "sg:classifiers":[
        {
            "category":"Building & Trades",
            "subcategory":"Construction",
            "type":"Services"
        }
    ],
    "sg:phone":"+1 954 202 9955",
    "sg:postcode":"33334",
    "sg:province":"FL",
    "sg:tags":[
        "sandblasting"
    ],
    "wof:name":"Us Sandblasting",
    "wof:placetype":"venue"
},
  "geometry": {"coordinates":[-80.14703299999999,26.187168],"type":"Point"}
}