{
  "type": "Feature",
  "properties": {
    "iso:country":"US",
    "sg:address":"6808 Lillian Rd",
    "sg:city":"Jacksonville",
    "sg:classifiers":[
        {
            "category":"Communications",
            "type":"Services"
        }
    ],
    "sg:phone":"+1 904 723 5280",
    "sg:postcode":"32211",
    "sg:province":"FL",
    "wof:name":"Dog Communications",
    "wof:placetype":"venue"
},
  "geometry": {"coordinates":[-81.58671699999999,30.331202],"type":"Point"}
}