{
  "type": "Feature",
  "properties": {
    "iso:country":"US",
    "sg:address":"7315 43rd St E",
    "sg:city":"Sarasota",
    "sg:classifiers":[
        {
            "category":"Building & Trades",
            "subcategory":"Construction",
            "type":"Services"
        }
    ],
    "sg:phone":"+1 941 358 5382",
    "sg:postcode":"34243",
    "sg:province":"FL",
    "sg:tags":[
        "house"
    ],
    "wof:name":"B & L Home Improvement",
    "wof:placetype":"venue"
},
  "geometry": {"coordinates":[-82.50787200000001,27.409361],"type":"Point"}
}