{
  "type": "Feature",
  "properties": {
    "addr:full":"10804 Luscombe Ct New Port Richey FL 34654",
    "addr:housenumber":"10804",
    "addr:postcode":"34654",
    "addr:street":"Luscombe Ct",
    "iso:country":"US",
    "sg:address":"10804 Luscombe Ct",
    "sg:city":"New Port Richey",
    "sg:classifiers":[
        {
            "category":"Professional",
            "subcategory":"Business Services",
            "type":"Services"
        }
    ],
    "sg:phone":"+1 727 817 1997",
    "sg:postcode":"34654",
    "sg:province":"FL",
    "sg:tags":[
        "broker"
    ],
    "wof:name":"South Comm Inc",
    "wof:placetype":"venue"
},
  "geometry": {"coordinates":[-82.636545,28.278441],"type":"Point"}
}