{
  "type": "Feature",
  "properties": {
    "iso:country":"US",
    "sg:address":"801 Edgewood Ave W",
    "sg:city":"Jacksonville",
    "sg:classifiers":[
        {
            "category":"Restaurant",
            "type":"Food & Drink"
        }
    ],
    "sg:phone":"+1 904 924 8008",
    "sg:postcode":"32208",
    "sg:province":"FL",
    "wof:name":"Gas Express Food & Beverages",
    "wof:placetype":"venue"
},
  "geometry": {"coordinates":[-81.66981699999999,30.392401],"type":"Point"}
}