{
  "type": "Feature",
  "properties": {
    "iso:country":"US",
    "sg:address":"111 S Orion Ave",
    "sg:city":"Clearwater",
    "sg:classifiers":[
        {
            "category":"Recreation",
            "type":"Entertainment"
        }
    ],
    "sg:phone":"+1 727 742 8404",
    "sg:postcode":"33765",
    "sg:province":"FL",
    "sg:tags":[
        "center"
    ],
    "wof:name":"John Thiry Recreation",
    "wof:placetype":"venue"
},
  "geometry": {"coordinates":[-82.761815,27.96506],"type":"Point"}
}