{
  "type": "Feature",
  "properties": {
    "iso:country":"US",
    "sg:address":"2357 Palm Ter",
    "sg:city":"West Palm Beach",
    "sg:classifiers":[
        {
            "category":"Insurance",
            "subcategory":"Insurance Agent",
            "type":"Services"
        }
    ],
    "sg:phone":"+1 561 967 7666",
    "sg:postcode":"33406",
    "sg:province":"FL",
    "wof:name":"Robert Carlson Insurance Inc",
    "wof:placetype":"venue"
},
  "geometry": {"coordinates":[-80.07797100000001,26.64313],"type":"Point"}
}