{
  "type": "Feature",
  "properties": {
    "iso:country":"US",
    "sg:address":"301 Caravan Cir",
    "sg:city":"Jacksonville",
    "sg:classifiers":[
        {
            "category":"Building & Trades",
            "subcategory":"Construction",
            "type":"Services"
        }
    ],
    "sg:phone":"+1 904 724 5849",
    "sg:postcode":"32216",
    "sg:province":"FL",
    "sg:tags":[
        "contractor"
    ],
    "wof:name":"Rachid Siding Inc",
    "wof:placetype":"venue"
},
  "geometry": {"coordinates":[-81.565108,30.311712],"type":"Point"}
}