{
  "type": "Feature",
  "properties": {
    "iso:country":"US",
    "sg:address":"6355 Cocoa Ln",
    "sg:city":"Ruskin",
    "sg:classifiers":[
        {
            "category":"Personal",
            "type":"Services"
        }
    ],
    "sg:phone":"+1 813 645 3644",
    "sg:postcode":"33572",
    "sg:province":"FL",
    "sg:tags":[
        "pet",
        "exercising"
    ],
    "wof:name":"Wags & Whiskers",
    "wof:placetype":"venue"
},
  "geometry": {"coordinates":[-82.423006,27.777624],"type":"Point"}
}