{
  "type": "Feature",
  "properties": {
    "addr:full":"1900 US Hwy 19 Holiday FL 34691",
    "addr:housenumber":"1900",
    "addr:postcode":"34691",
    "addr:street":"Us Hwy 19",
    "iso:country":"US",
    "sg:address":"1900 US Hwy 19",
    "sg:city":"Holiday",
    "sg:classifiers":[
        {
            "category":"Shopping",
            "subcategory":"Computers & Home Electronics",
            "type":"Retail Goods"
        }
    ],
    "sg:phone":"+1 727 938 7665",
    "sg:postcode":"34691",
    "sg:province":"FL",
    "wof:name":"Radio Shack",
    "wof:placetype":"venue"
},
  "geometry": {"coordinates":[-82.74003500000001,28.186312],"type":"Point"}
}