{
  "type": "Feature",
  "properties": {
    "addr:full":"3227 NW 27th St Miami FL 33142",
    "addr:housenumber":"3227",
    "addr:postcode":"33142",
    "addr:street":"Nw 27Th St",
    "iso:country":"US",
    "sg:address":"3227 NW 27th St",
    "sg:city":"Miami",
    "sg:classifiers":[
        {
            "category":"Wholesale",
            "subcategory":"Scrap",
            "type":"Manufacturing & Wholesale Goods"
        }
    ],
    "sg:phone":"+1 305 633 2241",
    "sg:postcode":"33142",
    "sg:province":"FL",
    "sg:tags":[
        "metal",
        "iron"
    ],
    "wof:name":"All Florida Scrap Metal",
    "wof:placetype":"venue"
},
  "geometry": {"coordinates":[-80.24892,25.800482],"type":"Point"}
}