{
  "type": "Feature",
  "properties": {
    "addr:full":"405 8th St S Naples FL 34102",
    "addr:housenumber":"405",
    "addr:postcode":"34102",
    "addr:street":"8Th St S",
    "iso:country":"US",
    "sg:address":"405 8th St S",
    "sg:city":"Naples",
    "sg:classifiers":[
        {
            "category":"Banks & Credit Unions",
            "subcategory":"Bank",
            "type":"Services"
        }
    ],
    "sg:phone":"+1 239 659 1119",
    "sg:postcode":"34102",
    "sg:province":"FL",
    "wof:name":"B B & T",
    "wof:placetype":"venue"
},
  "geometry": {"coordinates":[-81.796177,26.142329],"type":"Point"}
}