{
  "type": "Feature",
  "properties": {
    "addr:full":"9856 S Orange Ave Orlando FL 32824",
    "addr:housenumber":"9856",
    "addr:postcode":"32824",
    "addr:street":"S Orange Ave",
    "iso:country":"US",
    "sg:address":"9856 S Orange Ave",
    "sg:city":"Orlando",
    "sg:classifiers":[
        {
            "category":"Transit Center",
            "subcategory":"Freight",
            "type":"Transportation"
        }
    ],
    "sg:phone":"+1 407 859 8750",
    "sg:postcode":"32824",
    "sg:province":"FL",
    "sg:tags":[
        "forklift",
        "truck"
    ],
    "sg:website":"http://www.midfloridaforklift.com",
    "wof:name":"Mid-Florida Material Handling Inc",
    "wof:placetype":"venue"
},
  "geometry": {"coordinates":[-81.37119,28.423257],"type":"Point"}
}