{
  "type": "Feature",
  "properties": {
    "iso:country":"US",
    "sg:address":"821 E Buchanon Ave",
    "sg:city":"Orlando",
    "sg:classifiers":[
        {
            "category":"Autos & Motor Vehicles",
            "subcategory":"Automobile Sales",
            "type":"Retail Goods"
        }
    ],
    "sg:phone":"+1 407 601 5953",
    "sg:postcode":"32809",
    "sg:province":"FL",
    "sg:tags":[
        "new",
        "used",
        "car"
    ],
    "wof:name":"Best Choice Car Sales",
    "wof:placetype":"venue"
},
  "geometry": {"coordinates":[-81.36756099999999,28.467162],"type":"Point"}
}