{
  "type": "Feature",
  "properties": {
    "iso:country":"US",
    "sg:address":"813 SE 9th Ave",
    "sg:city":"Deerfield Beach",
    "sg:classifiers":[
        {
            "category":"Real Estate",
            "subcategory":"Real Estate Operator",
            "type":"Services"
        }
    ],
    "sg:phone":"+1 954 570 7690",
    "sg:postcode":"33441",
    "sg:province":"FL",
    "sg:tags":[
        "building",
        "apartment"
    ],
    "wof:name":"Deltown Properties Inc",
    "wof:placetype":"venue"
},
  "geometry": {"coordinates":[-80.09138900000001,26.307454],"type":"Point"}
}