{
  "type": "Feature",
  "properties": {
    "iso:country":"US",
    "sg:address":"10630 NW 83rd Ct",
    "sg:city":"Parkland",
    "sg:classifiers":[
        {
            "category":"Communications",
            "subcategory":"Film & Video Production",
            "type":"Services"
        }
    ],
    "sg:phone":"+1 954 340 7834",
    "sg:postcode":"33076",
    "sg:province":"FL",
    "sg:tags":[
        "tv",
        "radio",
        "services-commercial",
        "companies-film"
    ],
    "wof:name":"Alvideo Production Inc",
    "wof:placetype":"venue"
},
  "geometry": {"coordinates":[-80.270155,26.333502],"type":"Point"}
}