{
  "type": "Feature",
  "properties": {
    "addr:full":"16000 SW 200th St Miami FL 33187",
    "addr:housenumber":"16000",
    "addr:postcode":"33187",
    "addr:street":"Sw 200Th St",
    "iso:country":"US",
    "sg:address":"16000 SW 200th St",
    "sg:city":"Miami",
    "sg:classifiers":[
        {
            "category":"Farming",
            "subcategory":"Nursery",
            "type":"Manufacturing & Wholesale Goods"
        },
        {
            "category":"Manufacturing",
            "subcategory":"Paper Products",
            "type":"Manufacturing & Wholesale Goods"
        }
    ],
    "sg:phone":"+1 786 573 4000",
    "sg:postcode":"33187",
    "sg:province":"FL",
    "sg:tags":[
        "bamboo",
        "tree",
        "nurseries-plants"
    ],
    "wof:name":"Quails Way Nursery",
    "wof:placetype":"venue"
},
  "geometry": {"coordinates":[-80.517303,25.6159],"type":"Point"}
}