{
  "type": "Feature",
  "properties": {
    "iso:country":"US",
    "sg:address":"1300 N Atlantic Ave",
    "sg:city":"Cocoa Beach",
    "sg:classifiers":[
        {
            "category":"Shopping",
            "subcategory":"Clothing, Apparel, & Fashions",
            "type":"Retail Goods"
        }
    ],
    "sg:phone":"+1 321 799 4641",
    "sg:postcode":"32931",
    "sg:province":"FL",
    "sg:tags":[
        "shop",
        "bridal"
    ],
    "wof:name":"Space Coast Bridal & Event",
    "wof:placetype":"venue"
},
  "geometry": {"coordinates":[-80.61040800000001,28.335231],"type":"Point"}
}