{
  "type": "Feature",
  "properties": {
    "addr:full":"5101 NW 79th Ave Miami FL 33166",
    "addr:housenumber":"5101",
    "addr:postcode":"33166",
    "addr:street":"Nw 79Th Ave",
    "iso:country":"US",
    "sg:address":"5101 NW 79th Ave",
    "sg:city":"Miami",
    "sg:classifiers":[
        {
            "category":"Manufacturing",
            "subcategory":"Buildings",
            "type":"Manufacturing & Wholesale Goods"
        }
    ],
    "sg:phone":"+1 305 698 8990",
    "sg:postcode":"33166",
    "sg:province":"FL",
    "sg:tags":[
        "prefabricated",
        "wood",
        "mfg"
    ],
    "wof:name":"EMB Group Inc",
    "wof:placetype":"venue"
},
  "geometry": {"coordinates":[-80.325525,25.819854],"type":"Point"}
}