{
  "type": "Feature",
  "properties": {
    "addr:full":"265 Shore Dr E Miami FL 33133",
    "addr:housenumber":"265",
    "addr:postcode":"33133",
    "addr:street":"Shore Dr E",
    "iso:country":"US",
    "sg:address":"265 Shore Dr E",
    "sg:city":"Miami",
    "sg:phone":"+1 305 756 6000",
    "sg:postcode":"33133",
    "sg:province":"FL",
    "sg:tags":[
        "equipment",
        "commercial"
    ],
    "wof:name":"Miami Displays Inc",
    "wof:placetype":"venue"
},
  "geometry": {"coordinates":[-80.21543200000001,25.744554],"type":"Point"}
}