{
  "type": "Feature",
  "properties": {
    "addr:full":"889 Windover Ct New Smyrna Beach FL 32169",
    "addr:housenumber":"889",
    "addr:postcode":"32169",
    "addr:street":"Windover Ct",
    "iso:country":"US",
    "sg:address":"889 Windover Ct",
    "sg:city":"New Smyrna Beach",
    "sg:classifiers":[
        {
            "category":"Building & Trades",
            "subcategory":"Cleaning & Sanitation",
            "type":"Services"
        }
    ],
    "sg:phone":"+1 386 427 9388",
    "sg:postcode":"32169",
    "sg:province":"FL",
    "sg:tags":[
        "maintenance"
    ],
    "wof:name":"Sunshine",
    "wof:placetype":"venue"
},
  "geometry": {"coordinates":[-80.87505400000001,29.001125],"type":"Point"}
}