{
  "type": "Feature",
  "properties": {
    "iso:country":"US",
    "sg:address":"410 Segovia Rd",
    "sg:city":"Saint Augustine",
    "sg:classifiers":[
        {
            "category":"Building & Trades",
            "subcategory":"Construction",
            "type":"Services"
        }
    ],
    "sg:phone":"+1 904 669 4978",
    "sg:postcode":"32086",
    "sg:province":"FL",
    "sg:tags":[
        "residential",
        "builder"
    ],
    "wof:name":"Covenant Homes of St Augustine",
    "wof:placetype":"venue"
},
  "geometry": {"coordinates":[-81.32007400000001,29.840654],"type":"Point"}
}