{
  "type": "Feature",
  "properties": {
    "iso:country":"US",
    "sg:address":"4200 Tamiami Trl",
    "sg:city":"Port Charlotte",
    "sg:classifiers":[
        {
            "category":"Building & Trades",
            "subcategory":"Construction",
            "type":"Services"
        }
    ],
    "sg:phone":"+1 941 627 4262",
    "sg:postcode":"33980",
    "sg:province":"FL",
    "sg:tags":[
        "road",
        "contractor"
    ],
    "wof:name":"Highway Dept & Motor Vehicle",
    "wof:placetype":"venue"
},
  "geometry": {"coordinates":[-82.078216,26.96748],"type":"Point"}
}