{
  "type": "Feature",
  "properties": {
    "addr:full":"550 N New Hampshire Ave Tavares FL 32778",
    "addr:housenumber":"550",
    "addr:postcode":"32778",
    "addr:street":"N New Hampshire Ave",
    "iso:country":"US",
    "sg:address":"550 N New Hampshire Ave",
    "sg:city":"Tavares",
    "sg:classifiers":[
        {
            "category":"Freight",
            "type":"Transportation"
        }
    ],
    "sg:phone":"+1 352 343 8400",
    "sg:postcode":"32778",
    "sg:province":"FL",
    "sg:tags":[
        "commercial",
        "storage"
    ],
    "wof:name":"U-Store-Mini-Warehouses",
    "wof:placetype":"venue"
},
  "geometry": {"coordinates":[-81.72784900000001,28.806518],"type":"Point"}
}