{
  "type": "Feature",
  "properties": {
    "iso:country":"US",
    "sg:address":"1317 Adams St",
    "sg:city":"Hollywood",
    "sg:classifiers":[
        {
            "category":"Health Services",
            "subcategory":"Clinic",
            "type":"Services"
        }
    ],
    "sg:phone":"+1 954 921 5588",
    "sg:postcode":"33019",
    "sg:province":"FL",
    "sg:tags":[
        "home"
    ],
    "wof:name":"A Family Member Home Care",
    "wof:placetype":"venue"
},
  "geometry": {"coordinates":[-80.13449,26.005339],"type":"Point"}
}