{
  "type": "Feature",
  "properties": {
    "iso:country":"US",
    "sg:address":"5879 S Congress Ave",
    "sg:city":"Lantana",
    "sg:classifiers":[
        {
            "category":"Restaurant",
            "type":"Food & Drink"
        }
    ],
    "sg:phone":"+1 561 967 0333",
    "sg:postcode":"33462",
    "sg:province":"FL",
    "wof:name":"Payathai",
    "wof:placetype":"venue"
},
  "geometry": {"coordinates":[-80.093762,26.592581],"type":"Point"}
}