{
  "type": "Feature",
  "properties": {
    "addr:full":"1170 Tree Swallow Dr Winter Springs FL 32708",
    "addr:housenumber":"1170",
    "addr:postcode":"32708",
    "addr:street":"Tree Swallow Dr",
    "iso:country":"US",
    "sg:address":"1170 Tree Swallow Dr",
    "sg:city":"Winter Springs",
    "sg:classifiers":[
        {
            "category":"Building & Trades",
            "subcategory":"Cleaning & Sanitation",
            "type":"Services"
        }
    ],
    "sg:phone":"+1 407 810 7270",
    "sg:postcode":"32708",
    "sg:province":"FL",
    "sg:tags":[
        "home"
    ],
    "sg:website":"straightandsimplecleaning.com/",
    "wof:name":"Straight and Simple Carpet and Tile Cleaning and Restoration",
    "wof:placetype":"venue"
},
  "geometry": {"coordinates":[-81.26337700000001,28.69879],"type":"Point"}
}