{
  "type": "Feature",
  "properties": {
    "iso:country":"US",
    "sg:address":"7601 NW 74th Ave",
    "sg:city":"Medley",
    "sg:classifiers":[
        {
            "category":"Wholesale",
            "subcategory":"Hardware",
            "type":"Manufacturing & Wholesale Goods"
        }
    ],
    "sg:phone":"+1 305 882 0688",
    "sg:postcode":"33166",
    "sg:province":"FL",
    "sg:tags":[
        "hardware-wholesale",
        "hardware-builders",
        "manufacturer"
    ],
    "wof:name":"Orgill Brothers & Co",
    "wof:placetype":"venue"
},
  "geometry": {"coordinates":[-80.319221,25.842979],"type":"Point"}
}