{
  "type": "Feature",
  "properties": {
    "iso:country":"US",
    "sg:address":"5520 SW 163rd Ave",
    "sg:city":"Fort Lauderdale",
    "sg:classifiers":[
        {
            "category":"Farming",
            "subcategory":"Orchard",
            "type":"Manufacturing & Wholesale Goods"
        }
    ],
    "sg:phone":"+1 954 434 5785",
    "sg:postcode":"33331",
    "sg:province":"FL",
    "sg:tags":[
        "fruit",
        "tree"
    ],
    "wof:name":"Marys Grove",
    "wof:placetype":"venue"
},
  "geometry": {"coordinates":[-80.365649,26.048593],"type":"Point"}
}