{
  "type": "Feature",
  "properties": {
    "addr:full":"2541 NW 95th St Miami FL 33147",
    "addr:housenumber":"2541",
    "addr:postcode":"33147",
    "addr:street":"Nw 95Th St",
    "iso:country":"US",
    "sg:address":"2541 NW 95th St",
    "sg:city":"Miami",
    "sg:classifiers":[
        {
            "category":"Retail",
            "subcategory":"Repair Shop",
            "type":"Services"
        }
    ],
    "sg:phone":"+1 305 693 5740",
    "sg:postcode":"33147",
    "sg:province":"FL",
    "sg:tags":[
        "television",
        "radio",
        "radio-service"
    ],
    "wof:name":"Casamayor Tv",
    "wof:placetype":"venue"
},
  "geometry": {"coordinates":[-80.240616,25.860772],"type":"Point"}
}