{
  "type": "Feature",
  "properties": {
    "addr:full":"9180 W Bay Harbor Dr Miami Beach FL 33154",
    "addr:housenumber":"9180",
    "addr:postcode":"33154",
    "addr:street":"W Bay Harbor Dr",
    "iso:country":"US",
    "sg:address":"9180 W Bay Harbor Dr",
    "sg:city":"Miami Beach",
    "sg:classifiers":[
        {
            "category":"Real Estate",
            "subcategory":"Real Estate Agent",
            "type":"Services"
        }
    ],
    "sg:phone":"+1 305 861 0536",
    "sg:postcode":"33154",
    "sg:province":"FL",
    "wof:name":"Bay Rock Condominum Assn",
    "wof:placetype":"venue"
},
  "geometry": {"coordinates":[-80.13160999999999,25.882509],"type":"Point"}
}