{
  "type": "Feature",
  "properties": {
    "addr:full":"2451 Seminole Rd Fort Pierce FL 34951",
    "addr:housenumber":"2451",
    "addr:postcode":"34951",
    "addr:street":"Seminole Rd",
    "iso:country":"US",
    "sg:address":"2451 Seminole Rd",
    "sg:city":"Fort Pierce",
    "sg:classifiers":[
        {
            "category":"Wholesale",
            "subcategory":"Groceries",
            "type":"Manufacturing & Wholesale Goods"
        }
    ],
    "sg:phone":"+1 772 465 6341",
    "sg:postcode":"34951",
    "sg:province":"FL",
    "sg:tags":[
        "citrus",
        "harvest",
        "packing",
        "co"
    ],
    "wof:name":"Tropic Sun Fruit Co Inc",
    "wof:placetype":"venue"
},
  "geometry": {"coordinates":[-80.407245,27.483658],"type":"Point"}
}