{
  "type": "Feature",
  "properties": {
    "iso:country":"US",
    "sg:address":"4603 NW 37th Ave",
    "sg:city":"Miami",
    "sg:classifiers":[
        {
            "category":"Retail",
            "subcategory":"Auto Repair",
            "type":"Services"
        }
    ],
    "sg:phone":"+1 305 635 5200",
    "sg:postcode":"33142",
    "sg:province":"FL",
    "sg:tags":[
        "repairing",
        "automobile"
    ],
    "wof:name":"Ruddy's Automotive Svc",
    "wof:placetype":"venue"
},
  "geometry": {"coordinates":[-80.25671,25.816755],"type":"Point"}
}