{
  "type": "Feature",
  "properties": {
    "addr:full":"4630 N University Dr Pompano Beach FL 33067",
    "addr:housenumber":"4630",
    "addr:postcode":"33067",
    "addr:street":"N University Dr",
    "iso:country":"US",
    "sg:address":"4630 N University Dr",
    "sg:city":"Pompano Beach",
    "sg:classifiers":[
        {
            "category":"Building & Trades",
            "subcategory":"Landscaping Services",
            "type":"Services"
        }
    ],
    "sg:phone":"+1 561 793 1989",
    "sg:postcode":"33067",
    "sg:province":"FL",
    "sg:tags":[
        "landscape"
    ],
    "wof:name":"Ultimate Cleaning & Ldscpg",
    "wof:placetype":"venue"
},
  "geometry": {"coordinates":[-80.25008200000001,26.289722],"type":"Point"}
}