{
  "type": "Feature",
  "properties": {
    "iso:country":"US",
    "sg:address":"2645 Old Dixie Hwy",
    "sg:city":"Kissimmee",
    "sg:classifiers":[
        {
            "category":"Home & Garden",
            "subcategory":"Furniture",
            "type":"Retail Goods"
        }
    ],
    "sg:phone":"+1 407 846 2122",
    "sg:postcode":"34744",
    "sg:province":"FL",
    "sg:tags":[
        "store"
    ],
    "wof:name":"Smithy's Kissimmee Furniture & Appliances",
    "wof:placetype":"venue"
},
  "geometry": {"coordinates":[-81.399418,28.32422],"type":"Point"}
}