{
  "type": "Feature",
  "properties": {
    "addr:full":"3900 Bear Head Rd Crestview FL 32539",
    "addr:housenumber":"3900",
    "addr:postcode":"32539",
    "addr:street":"Bear Head Rd",
    "iso:country":"US",
    "sg:address":"3900 Bear Head Rd",
    "sg:city":"Crestview",
    "sg:classifiers":[
        {
            "category":"Home & Garden",
            "subcategory":"Furniture",
            "type":"Retail Goods"
        }
    ],
    "sg:phone":"+1 850 683 0541",
    "sg:postcode":"32539",
    "sg:province":"FL",
    "sg:tags":[
        "cabinet"
    ],
    "wof:name":"Stewart Enterprises",
    "wof:placetype":"venue"
},
  "geometry": {"coordinates":[-86.46855600000001,30.768137],"type":"Point"}
}