{
  "type": "Feature",
  "properties": {
    "addr:full":"12958 N Dale Mabry Hwy Tampa FL 33618",
    "addr:housenumber":"12958",
    "addr:postcode":"33618",
    "addr:street":"N Dale Mabry Hwy",
    "iso:country":"US",
    "sg:address":"12958 N Dale Mabry Hwy",
    "sg:city":"Tampa",
    "sg:classifiers":[
        {
            "category":"Professional",
            "subcategory":"Lawyer & Legal Services",
            "type":"Services"
        }
    ],
    "sg:phone":"+1 727 507 8999",
    "sg:postcode":"33618",
    "sg:province":"FL",
    "wof:name":"Frank P Verdi PA",
    "wof:placetype":"venue"
},
  "geometry": {"coordinates":[-82.504046,28.063309],"type":"Point"}
}