{
  "type": "Feature",
  "properties": {
    "iso:country":"US",
    "sg:address":"1721 E Commercial Blvd",
    "sg:city":"Fort Lauderdale",
    "sg:classifiers":[
        {
            "category":"Shopping",
            "subcategory":"Beauty & Cosmetics",
            "type":"Retail Goods"
        }
    ],
    "sg:phone":"+1 954 492 4092",
    "sg:postcode":"33334",
    "sg:province":"FL",
    "sg:tags":[
        "shop",
        "equipment",
        "salon",
        "barber",
        "supply"
    ],
    "wof:name":"Sally Beauty Company Inc",
    "wof:placetype":"venue"
},
  "geometry": {"coordinates":[-80.12284,26.189096],"type":"Point"}
}