{
  "type": "Feature",
  "properties": {
    "iso:country":"US",
    "sg:address":"1758 Tamiami Trl",
    "sg:city":"Venice",
    "sg:classifiers":[
        {
            "category":"Home & Garden",
            "subcategory":"Household Appliances",
            "type":"Retail Goods"
        }
    ],
    "sg:phone":"+1 941 493 1481",
    "sg:postcode":"34293",
    "sg:province":"FL",
    "wof:name":"De Sears",
    "wof:placetype":"venue"
},
  "geometry": {"coordinates":[-82.42068399999999,27.067812],"type":"Point"}
}