{
  "type": "Feature",
  "properties": {
    "iso:country":"US",
    "sg:address":"9960 SW 143rd St",
    "sg:city":"Miami",
    "sg:classifiers":[
        {
            "category":"Real Estate",
            "subcategory":"Surveying",
            "type":"Services"
        }
    ],
    "sg:phone":"+1 305 256 9707",
    "sg:postcode":"33176",
    "sg:province":"FL",
    "sg:tags":[
        "appraiser"
    ],
    "wof:name":"Rodriguez",
    "wof:placetype":"venue"
},
  "geometry": {"coordinates":[-80.355238,25.636784],"type":"Point"}
}