{
  "type": "Feature",
  "properties": {
    "addr:full":"19410 Gulfstream Dr Jupiter FL 33469",
    "addr:postcode":"19410;33469",
    "addr:street":"Gulfstream Dr",
    "iso:country":"US",
    "sg:address":"19410 Gulfstream Dr",
    "sg:city":"Jupiter",
    "sg:classifiers":[
        {
            "category":"Building & Trades",
            "subcategory":"Construction",
            "type":"Services"
        }
    ],
    "sg:phone":"+1 561 743 6326",
    "sg:postcode":"33469",
    "sg:province":"FL",
    "sg:tags":[
        "restoration",
        "cleaning",
        "patio",
        "deck"
    ],
    "wof:name":"Dave Stewart Pressure Cleaning",
    "wof:placetype":"venue"
},
  "geometry": {"coordinates":[-80.10623099999999,26.961604],"type":"Point"}
}