{
  "type": "Feature",
  "properties": {
    "iso:country":"US",
    "sg:address":"8306 Pamlico St",
    "sg:city":"Orlando",
    "sg:classifiers":[
        {
            "category":"Organizations",
            "subcategory":"Religious Organization",
            "type":"Services"
        }
    ],
    "sg:phone":"+1 407 678 2988",
    "sg:postcode":"32817",
    "sg:province":"FL",
    "wof:name":"Janet Dipietro Ministries",
    "wof:placetype":"venue"
},
  "geometry": {"coordinates":[-81.276827,28.592427],"type":"Point"}
}