{
  "type": "Feature",
  "properties": {
    "addr:full":"2724 N Hiawassee Rd Orlando FL 32818",
    "addr:housenumber":"2724",
    "addr:postcode":"32818",
    "addr:street":"N Hiawassee Rd",
    "iso:country":"US",
    "sg:address":"2724 N Hiawassee Rd",
    "sg:city":"Orlando",
    "sg:classifiers":[
        {
            "category":"Food & Beverages",
            "subcategory":"Groceries & Convenience Stores",
            "type":"Retail Goods"
        }
    ],
    "sg:phone":"+1 407 298 5013",
    "sg:postcode":"32818",
    "sg:province":"FL",
    "wof:name":"Publix Super Market 318",
    "wof:placetype":"venue"
},
  "geometry": {"coordinates":[-81.476114,28.57957],"type":"Point"}
}