{
  "type": "Feature",
  "properties": {
    "iso:country":"US",
    "sg:address":"4588 Tamiami Trl N",
    "sg:city":"Naples",
    "sg:classifiers":[
        {
            "category":"Health Services",
            "subcategory":"Doctor",
            "type":"Services"
        }
    ],
    "sg:phone":"+1 239 261 8200",
    "sg:postcode":"34103",
    "sg:province":"FL",
    "wof:name":"James Lowdermilk DDS",
    "wof:placetype":"venue"
},
  "geometry": {"coordinates":[-81.800139,26.199328],"type":"Point"}
}