{
  "type": "Feature",
  "properties": {
    "iso:country":"US",
    "sg:address":"13108 S Dixie Hwy",
    "sg:city":"Miami",
    "sg:classifiers":[
        {
            "category":"Shopping",
            "subcategory":"Bicycles & Sporting Goods",
            "type":"Retail Goods"
        },
        {
            "category":"Sports & Exercise",
            "subcategory":"Playing Field",
            "type":"Entertainment"
        }
    ],
    "sg:phone":"+1 786 242 3733",
    "sg:postcode":"33156",
    "sg:province":"FL",
    "sg:tags":[
        "bike",
        "instruction",
        "fitness"
    ],
    "sg:website":"www.elitecycling.net",
    "wof:name":"Elite Cycling",
    "wof:placetype":"venue"
},
  "geometry": {"coordinates":[-80.18189099999999,25.896106],"type":"Point"}
}