{
  "type": "Feature",
  "properties": {
    "iso:country":"US",
    "sg:address":"14425 Country Walk Dr",
    "sg:city":"Miami",
    "sg:classifiers":[
        {
            "category":"Sports & Exercise",
            "subcategory":"Gym",
            "type":"Entertainment"
        }
    ],
    "sg:phone":"+1 305 252 1593",
    "sg:postcode":"33186",
    "sg:province":"FL",
    "sg:tags":[
        "club",
        "health",
        "studio",
        "gymnasium"
    ],
    "wof:name":"Curves For Women",
    "wof:placetype":"venue"
},
  "geometry": {"coordinates":[-80.42772100000001,25.629597],"type":"Point"}
}