{
  "type": "Feature",
  "properties": {
    "iso:country":"US",
    "sg:address":"332 SE 41st St",
    "sg:city":"Keystone Heights",
    "sg:classifiers":[
        {
            "category":"Manufacturing",
            "subcategory":"Textiles",
            "type":"Manufacturing & Wholesale Goods"
        }
    ],
    "sg:phone":"+1 352 473 9676",
    "sg:postcode":"32656",
    "sg:province":"FL",
    "sg:tags":[
        "design",
        "t"
    ],
    "wof:name":"Mikes Design & Printing",
    "wof:placetype":"venue"
},
  "geometry": {"coordinates":[-82.04957,29.776898],"type":"Point"}
}