{
  "type": "Feature",
  "properties": {
    "iso:country":"US",
    "sg:address":"265 S 18th St",
    "sg:city":"Defuniak Springs",
    "sg:classifiers":[
        {
            "category":"Retail",
            "subcategory":"Auto Repair",
            "type":"Services"
        }
    ],
    "sg:phone":"+1 850 892 7066",
    "sg:postcode":"32435",
    "sg:province":"FL",
    "sg:tags":[
        "automobile",
        "electric"
    ],
    "wof:name":"Finley Auto Electric",
    "wof:placetype":"venue"
},
  "geometry": {"coordinates":[-86.126133,30.719995],"type":"Point"}
}