{
  "type": "Feature",
  "properties": {
    "addr:full":"700 SW 10th St Deerfield Beach FL 33441",
    "addr:housenumber":"700",
    "addr:postcode":"33441",
    "addr:street":"Sw 10Th St",
    "iso:country":"US",
    "sg:address":"700 SW 10th St",
    "sg:city":"Deerfield Beach",
    "sg:classifiers":[
        {
            "category":"Food & Beverages",
            "subcategory":"Groceries & Convenience Stores",
            "type":"Retail Goods"
        }
    ],
    "sg:phone":"+1 954 420 0808",
    "sg:postcode":"33441",
    "sg:province":"FL",
    "sg:tags":[
        "a",
        "mini",
        "deli",
        "market",
        "operates"
    ],
    "wof:name":"Brazilian Depot Inc",
    "wof:placetype":"venue"
},
  "geometry": {"coordinates":[-80.11438800000001,26.304671],"type":"Point"}
}