{
  "type": "Feature",
  "properties": {
    "addr:full":"3900 SW 2nd Ct Fort Lauderdale FL 33312",
    "addr:housenumber":"3900",
    "addr:postcode":"33312",
    "addr:street":"Sw 2Nd Ct",
    "iso:country":"US",
    "sg:address":"3900 SW 2nd Ct",
    "sg:city":"Fort Lauderdale",
    "sg:classifiers":[
        {
            "category":"Building & Trades",
            "subcategory":"Pest Control",
            "type":"Services"
        }
    ],
    "sg:phone":"+1 954 583 1281",
    "sg:postcode":"33312",
    "sg:province":"FL",
    "wof:name":"Dead Bug Edwards Inc",
    "wof:placetype":"venue"
},
  "geometry": {"coordinates":[-80.201499,26.118296],"type":"Point"}
}