{
  "type": "Feature",
  "properties": {
    "iso:country":"US",
    "sg:address":"1207 United St",
    "sg:city":"Key West",
    "sg:classifiers":[
        {
            "category":"Ice Cream",
            "type":"Food & Drink"
        }
    ],
    "sg:menulink":"http://www.allmenus.com/fl/key-west/172435-dairy-queen/menu/",
    "sg:phone":"+1 305 293 3737",
    "sg:postcode":"33040",
    "sg:province":"FL",
    "sg:tags":[
        "burger",
        "american"
    ],
    "wof:name":"Dairy Queen",
    "wof:placetype":"venue"
},
  "geometry": {"coordinates":[-81.78879999999999,24.553671],"type":"Point"}
}