{
  "type": "Feature",
  "properties": {
    "addr:full":"6422 Ridge Rd Port Richey FL 34668",
    "addr:housenumber":"6422",
    "addr:postcode":"34668",
    "addr:street":"Ridge Rd",
    "iso:country":"US",
    "sg:address":"6422 Ridge Rd",
    "sg:city":"Port Richey",
    "sg:classifiers":[
        {
            "category":"Utilities",
            "subcategory":"Mobile Phone",
            "type":"Services"
        }
    ],
    "sg:phone":"+1 727 844 0180",
    "sg:postcode":"34668",
    "sg:province":"FL",
    "sg:tags":[
        "telephone",
        "cellular"
    ],
    "wof:name":"National Wireless",
    "wof:placetype":"venue"
},
  "geometry": {"coordinates":[-82.707318,28.280538],"type":"Point"}
}