{
  "type": "Feature",
  "properties": {
    "iso:country":"US",
    "sg:address":"30522 US Hwy 19 N",
    "sg:city":"Palm Harbor",
    "sg:classifiers":[
        {
            "category":"Health Services",
            "subcategory":"Doctor",
            "type":"Services"
        }
    ],
    "sg:phone":"+1 727 772 0819",
    "sg:postcode":"34684",
    "sg:province":"FL",
    "sg:tags":[
        "medical"
    ],
    "wof:name":"Center For Orhtpdc Injry Dsodr",
    "wof:placetype":"venue"
},
  "geometry": {"coordinates":[-82.73877,28.051088],"type":"Point"}
}