{
  "type": "Feature",
  "properties": {
    "addr:full":"4944 W Irlo Bronson Memorial Hwy Kissimmee FL 34746",
    "addr:housenumber":"4944",
    "addr:postcode":"34746",
    "addr:street":"W Irlo Bronson Memorial Hwy",
    "iso:country":"US",
    "sg:address":"4944 W Irlo Bronson Memorial Hwy",
    "sg:city":"Kissimmee",
    "sg:phone":"+1 407 396 4455",
    "sg:postcode":"34746",
    "sg:province":"FL",
    "sg:website":"http://www.royalcelebrationorlando.com",
    "wof:name":"Quality Inn Lake Cecile",
    "wof:placetype":"venue"
},
  "geometry": {"coordinates":[-81.481667,28.33285],"type":"Point"}
}