{
  "type": "Feature",
  "properties": {
    "addr:full":"5771 Fairway Park Ct Boynton Beach FL 33437",
    "addr:housenumber":"5771",
    "addr:postcode":"33437",
    "addr:street":"Fairway Park Ct",
    "iso:country":"US",
    "sg:address":"5771 Fairway Park Ct",
    "sg:city":"Boynton Beach",
    "sg:classifiers":[
        {
            "category":"Freight",
            "type":"Transportation"
        }
    ],
    "sg:phone":"+1 561 736 0301",
    "sg:postcode":"33437",
    "sg:province":"FL",
    "wof:name":"All Tran Tbsnt",
    "wof:placetype":"venue"
},
  "geometry": {"coordinates":[-80.135543,26.499918],"type":"Point"}
}