{
  "type": "Feature",
  "properties": {
    "iso:country":"US",
    "sg:address":"3844 Golf Village Loop",
    "sg:city":"Lakeland",
    "sg:classifiers":[
        {
            "category":"Communications",
            "type":"Services"
        }
    ],
    "sg:phone":"+1 863 859 5970",
    "sg:postcode":"33809",
    "sg:province":"FL",
    "wof:name":"Ruthven Communications",
    "wof:placetype":"venue"
},
  "geometry": {"coordinates":[-81.967395,28.094015],"type":"Point"}
}