{
  "type": "Feature",
  "properties": {
    "addr:full":"5448 3rd St St Augustine FL 32080",
    "addr:housenumber":"5448",
    "addr:postcode":"32080",
    "addr:street":"3Rd St",
    "iso:country":"US",
    "sg:address":"5448 3rd St",
    "sg:city":"St Augustine",
    "sg:classifiers":[
        {
            "category":"Personal",
            "type":"Services"
        },
        {
            "category":"Retail",
            "subcategory":"Animal Services",
            "type":"Services"
        }
    ],
    "sg:phone":"+1 904 471 6535",
    "sg:postcode":"32080",
    "sg:province":"FL",
    "sg:tags":[
        "pet",
        "boarding",
        "sitting"
    ],
    "wof:name":"Pet Pourri Sitter Service",
    "wof:placetype":"venue"
},
  "geometry": {"coordinates":[-81.264808,29.79308],"type":"Point"}
}