{
  "type": "Feature",
  "properties": {
    "addr:full":"360 8th Ave N Saint Petersburg FL 33715",
    "addr:housenumber":"360",
    "addr:postcode":"33715",
    "addr:street":"8Th Ave N",
    "iso:country":"US",
    "sg:address":"360 8th Ave N",
    "sg:city":"Saint Petersburg",
    "sg:classifiers":[
        {
            "category":"Professional",
            "subcategory":"Accounting & Tax Preparation",
            "type":"Services"
        }
    ],
    "sg:phone":"+1 727 865 7898",
    "sg:postcode":"33715",
    "sg:province":"FL",
    "wof:name":"Happy Hooper Inc",
    "wof:placetype":"venue"
},
  "geometry": {"coordinates":[-82.729168,27.690588],"type":"Point"}
}