{
  "type": "Feature",
  "properties": {
    "iso:country":"US",
    "sg:address":"8635 Fleming Grant Rd",
    "sg:city":"Sebastian",
    "sg:classifiers":[
        {
            "category":"Building & Trades",
            "subcategory":"Landscaping Services",
            "type":"Services"
        }
    ],
    "sg:phone":"+1 772 664 4474",
    "sg:postcode":"32976",
    "sg:province":"FL",
    "wof:name":"Simons Lawn Service",
    "wof:placetype":"venue"
},
  "geometry": {"coordinates":[-80.517152,27.867594],"type":"Point"}
}