{
  "type": "Feature",
  "properties": {
    "addr:full":"124 Bullard Pkwy Tampa FL 33617",
    "addr:housenumber":"124",
    "addr:postcode":"33617",
    "addr:street":"Bullard Pkwy",
    "iso:country":"US",
    "sg:address":"124 Bullard Pkwy",
    "sg:city":"Tampa",
    "sg:classifiers":[
        {
            "category":"Government",
            "subcategory":"Fire Station",
            "type":"Public Place"
        }
    ],
    "sg:phone":"+1 813 989 7121",
    "sg:postcode":"33617",
    "sg:province":"FL",
    "sg:tags":[
        "department",
        "fighter"
    ],
    "wof:name":"Temple Terrace Fire Department",
    "wof:placetype":"venue"
},
  "geometry": {"coordinates":[-82.39205800000001,28.032601],"type":"Point"}
}