{
  "type": "Feature",
  "properties": {
    "addr:full":"7901 209th St E Myakka City FL 34202",
    "addr:housenumber":"7901",
    "addr:postcode":"34202",
    "addr:street":"209Th St E;City",
    "iso:country":"US",
    "sg:address":"7901 209th St E",
    "sg:city":"Myakka City",
    "sg:classifiers":[
        {
            "category":"Building & Trades",
            "subcategory":"Construction",
            "type":"Services"
        }
    ],
    "sg:phone":"+1 941 322 9339",
    "sg:postcode":"34202",
    "sg:province":"FL",
    "sg:tags":[
        "control",
        "corrosion"
    ],
    "wof:name":"Corrosion Solutions Inc",
    "wof:placetype":"venue"
},
  "geometry": {"coordinates":[-82.32847599999999,27.396281],"type":"Point"}
}