{
  "type": "Feature",
  "properties": {
    "iso:country":"US",
    "sg:address":"1408 S Andrews Ave",
    "sg:city":"Fort Lauderdale",
    "sg:classifiers":[
        {
            "category":"Professional",
            "subcategory":"Lawyer & Legal Services",
            "type":"Services"
        }
    ],
    "sg:phone":"+1 954 760 7775",
    "sg:postcode":"33316",
    "sg:province":"FL",
    "wof:name":"Gary Maisel PA",
    "wof:placetype":"venue"
},
  "geometry": {"coordinates":[-80.142554,26.103427],"type":"Point"}
}