{
  "type": "Feature",
  "properties": {
    "iso:country":"US",
    "sg:address":"830 A1a N",
    "sg:city":"Ponte Vedra Beach",
    "sg:classifiers":[
        {
            "category":"Bars & Pubs",
            "type":"Food & Drink"
        }
    ],
    "sg:menulink":"http://www.allmenus.com/fl/ponte-vedra/49300-down-south-barbque/menu/",
    "sg:phone":"+1 904 273 9902",
    "sg:postcode":"32082",
    "sg:province":"FL",
    "sg:tags":[
        "barbecue",
        "american"
    ],
    "wof:name":"Down South Barbque",
    "wof:placetype":"venue"
},
  "geometry": {"coordinates":[-81.38059699999999,30.197565],"type":"Point"}
}