{
  "type": "Feature",
  "properties": {
    "addr:full":"1964 Indian Creek Dr Fort Myers FL 33917",
    "addr:housenumber":"1964",
    "addr:postcode":"33917",
    "addr:street":"Indian Creek Dr",
    "iso:country":"US",
    "sg:address":"1964 Indian Creek Dr",
    "sg:city":"Fort Myers",
    "sg:classifiers":[
        {
            "category":"Building & Trades",
            "subcategory":"Construction",
            "type":"Services"
        }
    ],
    "sg:phone":"+1 239 997 8400",
    "sg:postcode":"33917",
    "sg:province":"FL",
    "sg:tags":[
        "handyman"
    ],
    "wof:name":"Southwest Florida Property",
    "wof:placetype":"venue"
},
  "geometry": {"coordinates":[-81.85607299999999,26.690563],"type":"Point"}
}