{
  "type": "Feature",
  "properties": {
    "addr:full":"11513 US Hwy 301 Thonotosassa FL 33592",
    "addr:housenumber":"11513",
    "addr:postcode":"33592",
    "addr:street":"Us Hwy 301",
    "iso:country":"US",
    "sg:address":"11513 US Hwy 301",
    "sg:city":"Thonotosassa",
    "sg:classifiers":[
        {
            "category":"Home & Garden",
            "subcategory":"Mobile Homes",
            "type":"Retail Goods"
        }
    ],
    "sg:phone":"+1 813 986 3385",
    "sg:postcode":"33592",
    "sg:province":"FL",
    "sg:tags":[
        "supply"
    ],
    "wof:name":"Ancove Mobile Home Supply",
    "wof:placetype":"venue"
},
  "geometry": {"coordinates":[-82.324742,28.055387],"type":"Point"}
}