{
  "type": "Feature",
  "properties": {
    "addr:full":"24208 Production Cir Bonita Springs FL 34135",
    "addr:housenumber":"24208",
    "addr:postcode":"34135",
    "addr:street":"Production Cir",
    "iso:country":"US",
    "sg:address":"24208 Production Cir",
    "sg:city":"Bonita Springs",
    "sg:classifiers":[
        {
            "category":"Personal",
            "subcategory":"Beauty Salon",
            "type":"Services"
        }
    ],
    "sg:phone":"+1 239 498 9017",
    "sg:postcode":"34135",
    "sg:province":"FL",
    "sg:tags":[
        "lawn",
        "landscape",
        "care"
    ],
    "sg:website":"www.kaulbarslawns.com",
    "wof:name":"Kaulbars Lawns Inc",
    "wof:placetype":"venue"
},
  "geometry": {"coordinates":[-81.806905,26.389589],"type":"Point"}
}