{
  "type": "Feature",
  "properties": {
    "addr:full":"7725 Gall Blvd Zephyrhills FL 33541",
    "addr:housenumber":"7725",
    "addr:postcode":"33541",
    "addr:street":"Gall Blvd",
    "iso:country":"US",
    "sg:address":"7725 Gall Blvd",
    "sg:city":"Zephyrhills",
    "sg:classifiers":[
        {
            "category":"Shopping",
            "subcategory":"Beauty & Cosmetics",
            "type":"Retail Goods"
        }
    ],
    "sg:phone":"+1 813 788 4067",
    "sg:postcode":"33541",
    "sg:province":"FL",
    "sg:tags":[
        "equipment",
        "supply"
    ],
    "wof:name":"Sally Beauty Supply",
    "wof:placetype":"venue"
},
  "geometry": {"coordinates":[-82.18836899999999,28.27075],"type":"Point"}
}