{
  "type": "Feature",
  "properties": {
    "iso:country":"US",
    "sg:address":"4108 Mulligan Ct W",
    "sg:city":"Sebring",
    "sg:classifiers":[
        {
            "category":"Professional",
            "subcategory":"Business Services",
            "type":"Services"
        }
    ],
    "sg:phone":"+1 863 385 2683",
    "sg:postcode":"33872",
    "sg:province":"FL",
    "wof:name":"Rick Whidden Drafting",
    "wof:placetype":"venue"
},
  "geometry": {"coordinates":[-81.508419,27.483597],"type":"Point"}
}