{
  "type": "Feature",
  "properties": {
    "iso:country":"US",
    "sg:address":"2514 S Laurel Ave",
    "sg:city":"Sanford",
    "sg:classifiers":[
        {
            "category":"Government",
            "subcategory":"Fire Station",
            "type":"Public Place"
        },
        {
            "category":"Wholesale",
            "subcategory":"Machinery & Supplies",
            "type":"Manufacturing & Wholesale Goods"
        },
        {
            "category":"Shopping",
            "type":"Retail Goods"
        }
    ],
    "sg:phone":"+1 407 322 0015",
    "sg:postcode":"32773",
    "sg:province":"FL",
    "sg:tags":[
        "extinguisher",
        "consultant",
        "equipment",
        "protection",
        "safety",
        "department",
        "clothing"
    ],
    "wof:name":"Tri County Fire Equipment Inc",
    "wof:placetype":"venue"
},
  "geometry": {"coordinates":[-81.271991,28.785223],"type":"Point"}
}