{
  "type": "Feature",
  "properties": {
    "addr:full":"1690 20th Ct SW Vero Beach FL 32962",
    "addr:housenumber":"1690",
    "addr:postcode":"32962",
    "addr:street":"20Th Ct Sw",
    "iso:country":"US",
    "sg:address":"1690 20th Ct SW",
    "sg:city":"Vero Beach",
    "sg:classifiers":[
        {
            "category":"Wholesale",
            "subcategory":"Machinery & Supplies",
            "type":"Manufacturing & Wholesale Goods"
        }
    ],
    "sg:phone":"+1 772 794 9232",
    "sg:postcode":"32962",
    "sg:province":"FL",
    "sg:tags":[
        "equipment",
        "establishment"
    ],
    "wof:name":"George Dix",
    "wof:placetype":"venue"
},
  "geometry": {"coordinates":[-80.406925,27.572527],"type":"Point"}
}