{
  "type": "Feature",
  "properties": {
    "iso:country":"US",
    "sg:address":"4806 Seaboard Ave",
    "sg:city":"Jacksonville",
    "sg:classifiers":[
        {
            "category":"Professional",
            "subcategory":"Accounting & Tax Preparation",
            "type":"Services"
        }
    ],
    "sg:phone":"+1 904 771 1342",
    "sg:postcode":"32210",
    "sg:province":"FL",
    "sg:tags":[
        "billing"
    ],
    "wof:name":"North Fl Billing Svc",
    "wof:placetype":"venue"
},
  "geometry": {"coordinates":[-81.727923,30.256422],"type":"Point"}
}