{
  "type": "Feature",
  "properties": {
    "iso:country":"US",
    "sg:address":"5120 SE Abshier Blvd",
    "sg:city":"Belleview",
    "sg:classifiers":[
        {
            "category":"Restaurant",
            "type":"Food & Drink"
        }
    ],
    "sg:menulink":"http://www.allmenus.com/fl/belleview/189572-kfc---kentucky-fried-chicken/menu/",
    "sg:phone":"+1 352 245 5663",
    "sg:postcode":"34420",
    "sg:province":"FL",
    "sg:tags":[
        "american",
        "chicken"
    ],
    "wof:name":"KFC - Kentucky Fried Chicken",
    "wof:placetype":"venue"
},
  "geometry": {"coordinates":[-82.063914,29.060784],"type":"Point"}
}