{
  "type": "Feature",
  "properties": {
    "iso:country":"US",
    "sg:address":"297 Torpoint Gate Rd",
    "sg:city":"Longwood",
    "sg:classifiers":[
        {
            "category":"Building & Trades",
            "subcategory":"Construction",
            "type":"Services"
        }
    ],
    "sg:phone":"+1 407 682 6389",
    "sg:postcode":"32779",
    "sg:province":"FL",
    "sg:tags":[
        "handyman"
    ],
    "wof:name":"Daniel Amat's Svc",
    "wof:placetype":"venue"
},
  "geometry": {"coordinates":[-81.45246,28.681036],"type":"Point"}
}