{
  "type": "Feature",
  "properties": {
    "iso:country":"US",
    "sg:address":"114 E Dr Martin Luther King Jr Blvd",
    "sg:city":"Plant City",
    "sg:classifiers":[
        {
            "category":"Personal",
            "type":"Services"
        },
        {
            "category":"Sports & Exercise",
            "subcategory":"Gym",
            "type":"Entertainment"
        }
    ],
    "sg:phone":"+1 813 757 6038",
    "sg:postcode":"33566",
    "sg:province":"FL",
    "sg:tags":[
        "fitness",
        "program",
        "physical",
        "facility"
    ],
    "wof:name":"Power Shop Fitness",
    "wof:placetype":"venue"
},
  "geometry": {"coordinates":[-82.122991,28.014383],"type":"Point"}
}