{
  "type": "Feature",
  "properties": {
    "addr:full":"3644 SW Archer Rd Gainesville FL 32608",
    "addr:housenumber":"3644",
    "addr:postcode":"32608",
    "addr:street":"Sw Archer Rd",
    "iso:country":"US",
    "sg:address":"3644 SW Archer Rd",
    "sg:city":"Gainesville",
    "sg:classifiers":[
        {
            "category":"Shopping",
            "subcategory":"Hobbies, Toys, & Games",
            "type":"Retail Goods"
        }
    ],
    "sg:phone":"+1 352 377 9797",
    "sg:postcode":"32608",
    "sg:province":"FL",
    "sg:tags":[
        "craft",
        "supply"
    ],
    "sg:website":"www.michaels.com",
    "wof:name":"Michaels Arts & Crafts Store",
    "wof:placetype":"venue"
},
  "geometry": {"coordinates":[-82.38015799999999,29.620493],"type":"Point"}
}