{
  "type": "Feature",
  "properties": {
    "addr:full":"2180 Immokalee Rd Naples FL 34142",
    "addr:housenumber":"2180",
    "addr:postcode":"34142",
    "addr:street":"Immokalee Rd",
    "iso:country":"US",
    "sg:address":"2180 Immokalee Rd",
    "sg:city":"Naples",
    "sg:classifiers":[
        {
            "category":"Social Services",
            "type":"Services"
        }
    ],
    "sg:phone":"+1 239 596 1720",
    "sg:postcode":"34142",
    "sg:province":"FL",
    "sg:tags":[
        "counselor",
        "marriage",
        "family"
    ],
    "wof:name":"Delta Foundation",
    "wof:placetype":"venue"
},
  "geometry": {"coordinates":[-81.48845900000001,26.499072],"type":"Point"}
}