{
  "type": "Feature",
  "properties": {
    "addr:full":"4200 W Oakland Park Blvd Lauderdale Lakes FL 33313",
    "addr:housenumber":"4200",
    "addr:postcode":"33313",
    "addr:street":"W Oakland Park Blvd",
    "iso:country":"US",
    "sg:address":"4200 W Oakland Park Blvd",
    "sg:city":"Lauderdale Lakes",
    "sg:classifiers":[
        {
            "category":"Manufacturing",
            "subcategory":"Retail Goods",
            "type":"Manufacturing & Wholesale Goods"
        }
    ],
    "sg:phone":"+1 954 777 3065",
    "sg:postcode":"33313",
    "sg:province":"FL",
    "sg:tags":[
        "manufacturer"
    ],
    "wof:name":"Suncoast Industries",
    "wof:placetype":"venue"
},
  "geometry": {"coordinates":[-80.204063,26.1648],"type":"Point"}
}