{
  "type": "Feature",
  "properties": {
    "addr:full":"3626 E Industrial Way Riviera Beach FL 33404",
    "addr:housenumber":"3626",
    "addr:postcode":"33404",
    "addr:street":"E Industrial Way",
    "iso:country":"US",
    "sg:address":"3626 E Industrial Way",
    "sg:city":"Riviera Beach",
    "sg:classifiers":[
        {
            "category":"Home & Garden",
            "subcategory":"Garden Supply",
            "type":"Retail Goods"
        }
    ],
    "sg:phone":"+1 561 844 9100",
    "sg:postcode":"33404",
    "sg:province":"FL",
    "sg:tags":[
        "engine"
    ],
    "wof:name":"Engine Master Svc Inc",
    "wof:placetype":"venue"
},
  "geometry": {"coordinates":[-80.09363500000001,26.785404],"type":"Point"}
}