{
  "type": "Feature",
  "properties": {
    "iso:country":"US",
    "sg:address":"6635 Yarberry Ln",
    "sg:city":"Naples",
    "sg:classifiers":[
        {
            "category":"Building & Trades",
            "subcategory":"Cleaning & Sanitation",
            "type":"Services"
        }
    ],
    "sg:phone":"+1 239 592 6931",
    "sg:postcode":"34109",
    "sg:province":"FL",
    "sg:tags":[
        "maintenance"
    ],
    "wof:name":"Mary C Leon Janitorial Svc",
    "wof:placetype":"venue"
},
  "geometry": {"coordinates":[-81.774575,26.228559],"type":"Point"}
}