{
  "type": "Feature",
  "properties": {
    "addr:full":"860 US Hwy 1 North Palm Beach FL 33408",
    "addr:housenumber":"860",
    "addr:postcode":"33408",
    "addr:street":"Us Hwy 1 North",
    "iso:country":"US",
    "sg:address":"860 US Hwy 1",
    "sg:city":"North Palm Beach",
    "sg:classifiers":[
        {
            "category":"Professional",
            "subcategory":"Credit Reporting & Collection",
            "type":"Services"
        }
    ],
    "sg:phone":"+1 561 721 9570",
    "sg:postcode":"33408",
    "sg:province":"FL",
    "sg:tags":[
        "agency"
    ],
    "wof:name":"Accounts Recovery Bureau",
    "wof:placetype":"venue"
},
  "geometry": {"coordinates":[-80.054802,26.799524],"type":"Point"}
}