{
  "type": "Feature",
  "properties": {
    "iso:country":"US",
    "sg:address":"5463 Lyons Rd",
    "sg:city":"Coconut Creek",
    "sg:classifiers":[
        {
            "category":"Restaurant",
            "type":"Food & Drink"
        }
    ],
    "sg:menulink":"http://www.allmenus.com/fl/deerfield-beach/247217-crispers/menu/",
    "sg:phone":"+1 954 354 1600",
    "sg:postcode":"33073",
    "sg:province":"FL",
    "sg:tags":[
        "american"
    ],
    "wof:name":"Crispers",
    "wof:placetype":"venue"
},
  "geometry": {"coordinates":[-80.186536,26.297477],"type":"Point"}
}