{
  "type": "Feature",
  "properties": {
    "addr:full":"219 Westshore Plz Tampa FL 33609",
    "addr:housenumber":"219",
    "addr:postcode":"33609",
    "addr:street":"Westshore Plz",
    "iso:country":"US",
    "sg:address":"219 Westshore Plz",
    "sg:city":"Tampa",
    "sg:classifiers":[
        {
            "category":"Restaurant",
            "type":"Food & Drink"
        }
    ],
    "sg:menulink":"http://www.allmenus.com/fl/tampa/6823-pf-changs/menu/",
    "sg:phone":"+1 813 289 8400",
    "sg:postcode":"33609",
    "sg:province":"FL",
    "sg:tags":[
        "japanese",
        "chinese",
        "asian"
    ],
    "wof:name":"P.F. Chang's",
    "wof:placetype":"venue"
},
  "geometry": {"coordinates":[-82.527295,27.94586],"type":"Point"}
}