{
  "type": "Feature",
  "properties": {
    "addr:full":"4100 N 29th Ter Hollywood FL 33020",
    "addr:housenumber":"4100",
    "addr:postcode":"33020",
    "addr:street":"N 29Th Ter",
    "iso:country":"US",
    "sg:address":"4100 N 29th Ter",
    "sg:city":"Hollywood",
    "sg:classifiers":[
        {
            "category":"Shopping",
            "subcategory":"Gifts & Souvenirs",
            "type":"Retail Goods"
        }
    ],
    "sg:phone":"+1 954 926 2962",
    "sg:postcode":"33020",
    "sg:province":"FL",
    "sg:tags":[
        "shop"
    ],
    "wof:name":"East Coast Annie",
    "wof:placetype":"venue"
},
  "geometry": {"coordinates":[-80.16679999999999,26.04264],"type":"Point"}
}