{
  "type": "Feature",
  "properties": {
    "addr:full":"5403 W Gray St Tampa FL 33609",
    "addr:housenumber":"5403",
    "addr:postcode":"33609",
    "addr:street":"W Gray St",
    "iso:country":"US",
    "sg:address":"5403 W Gray St",
    "sg:city":"Tampa",
    "sg:classifiers":[
        {
            "category":"Manufacturing",
            "subcategory":"Tools & Machinery",
            "type":"Manufacturing & Wholesale Goods"
        }
    ],
    "sg:phone":"+1 813 288 8006",
    "sg:postcode":"33609",
    "sg:province":"FL",
    "sg:tags":[
        "transformer",
        "electronic",
        "ballast",
        "mfg"
    ],
    "sg:website":"www.hatchtransformers.com",
    "wof:name":"Hatch Transformers Inc",
    "wof:placetype":"venue"
},
  "geometry": {"coordinates":[-82.534516,27.948641],"type":"Point"}
}