{
  "type": "Feature",
  "properties": {
    "addr:full":"11330 Compass Point Dr Fort Myers FL 33908",
    "addr:housenumber":"11330",
    "addr:postcode":"33908",
    "addr:street":"Compass Point Dr",
    "iso:country":"US",
    "sg:address":"11330 Compass Point Dr",
    "sg:city":"Fort Myers",
    "sg:classifiers":[
        {
            "category":"Professional",
            "subcategory":"Business Services",
            "type":"Services"
        }
    ],
    "sg:phone":"+1 239 454 3215",
    "sg:postcode":"33908",
    "sg:province":"FL",
    "sg:tags":[
        "interior",
        "consultant",
        "design",
        "decorator"
    ],
    "wof:name":"Patricia Gaetas Interiors",
    "wof:placetype":"venue"
},
  "geometry": {"coordinates":[-81.942409,26.526768],"type":"Point"}
}