{
  "type": "Feature",
  "properties": {
    "addr:full":"4450 SW 61st Ave Davie FL 33314",
    "addr:housenumber":"4450",
    "addr:postcode":"33314",
    "addr:street":"Sw 61St Ave",
    "iso:country":"US",
    "sg:address":"4450 SW 61st Ave",
    "sg:city":"Davie",
    "sg:classifiers":[
        {
            "category":"Home & Garden",
            "subcategory":"Furniture",
            "type":"Retail Goods"
        }
    ],
    "sg:phone":"+1 954 792 6020",
    "sg:postcode":"33314",
    "sg:province":"FL",
    "sg:tags":[
        "equipment",
        "kitchen",
        "cabinet"
    ],
    "wof:name":"Shoreline Mica",
    "wof:placetype":"venue"
},
  "geometry": {"coordinates":[-80.22812500000001,26.069181],"type":"Point"}
}