{
  "type": "Feature",
  "properties": {
    "iso:country":"US",
    "sg:address":"15495 SW 288th St",
    "sg:city":"Homestead",
    "sg:classifiers":[
        {
            "category":"Real Estate",
            "subcategory":"Real Estate Operator",
            "type":"Services"
        }
    ],
    "sg:phone":"+1 305 245 6311",
    "sg:postcode":"33033",
    "sg:province":"FL",
    "sg:tags":[
        "manager"
    ],
    "wof:name":"Biscayne Palm Club",
    "wof:placetype":"venue"
},
  "geometry": {"coordinates":[-80.442508,25.499459],"type":"Point"}
}