{
  "type": "Feature",
  "properties": {
    "iso:country":"US",
    "sg:address":"1855 Parental Home Rd",
    "sg:city":"Jacksonville",
    "sg:classifiers":[
        {
            "category":"Personal",
            "type":"Services"
        }
    ],
    "sg:phone":"+1 904 645 6337",
    "sg:postcode":"32216",
    "sg:province":"FL",
    "sg:tags":[
        "retail",
        "costume",
        "gift",
        "accessory"
    ],
    "sg:website":"www.makebelieve.com",
    "wof:name":"Make Believe Costumes",
    "wof:placetype":"venue"
},
  "geometry": {"coordinates":[-81.578322,30.288086],"type":"Point"}
}