{
  "type": "Feature",
  "properties": {
    "iso:country":"US",
    "sg:address":"500 N West Shore Blvd # 800",
    "sg:city":"Tampa",
    "sg:classifiers":[
        {
            "category":"Professional",
            "subcategory":"Employment Agencies",
            "type":"Services"
        }
    ],
    "sg:phone":"+1 877 208 9919",
    "sg:postcode":"33609",
    "sg:province":"FL",
    "wof:name":"Viant, Inc.",
    "wof:placetype":"venue"
},
  "geometry": {"coordinates":[-82.524193,27.94854],"type":"Point"}
}