{
  "type": "Feature",
  "properties": {
    "addr:full":"1411 N Pine Hills Rd Orlando FL 32808",
    "addr:housenumber":"1411",
    "addr:postcode":"32808",
    "addr:street":"N Pine Hills Rd",
    "iso:country":"US",
    "sg:address":"1411 N Pine Hills Rd",
    "sg:city":"Orlando",
    "sg:classifiers":[
        {
            "category":"Banks & Credit Unions",
            "subcategory":"Investment Brokerage",
            "type":"Services"
        },
        {
            "category":"Insurance",
            "subcategory":"Hazard Insurance",
            "type":"Services"
        }
    ],
    "sg:phone":"+1 407 295 7474",
    "sg:postcode":"32808",
    "sg:province":"FL",
    "sg:tags":[
        "agent",
        "resume"
    ],
    "wof:name":"Orley B Burey Inc",
    "wof:placetype":"venue"
},
  "geometry": {"coordinates":[-81.45217100000001,28.573712],"type":"Point"}
}