{
  "type": "Feature",
  "properties": {
    "iso:country":"US",
    "sg:address":"4400 Pine St",
    "sg:city":"Cocoa",
    "sg:classifiers":[
        {
            "category":"Building & Trades",
            "subcategory":"Landscaping Services",
            "type":"Services"
        }
    ],
    "sg:phone":"+1 321 632 1294",
    "sg:postcode":"32926",
    "sg:province":"FL",
    "sg:tags":[
        "landscape"
    ],
    "wof:name":"Ciccone & Sons Ldscp Mgt Inc",
    "wof:placetype":"venue"
},
  "geometry": {"coordinates":[-80.82687,28.424684],"type":"Point"}
}