{
  "type": "Feature",
  "properties": {
    "addr:full":"11388 SE US Hwy 301 Belleview FL 34420",
    "addr:postcode":"11388;34420",
    "addr:street":"Se Us Hwy 301",
    "iso:country":"US",
    "sg:address":"11388 SE US Hwy 301",
    "sg:city":"Belleview",
    "sg:classifiers":[
        {
            "category":"Home & Garden",
            "subcategory":"Building Materials",
            "type":"Retail Goods"
        }
    ],
    "sg:phone":"+1 352 245 1542",
    "sg:postcode":"34420",
    "sg:province":"FL",
    "sg:tags":[
        "glass",
        "window",
        "plate"
    ],
    "wof:name":"Autoglass Express Inc",
    "wof:placetype":"venue"
},
  "geometry": {"coordinates":[-82.049003,29.056942],"type":"Point"}
}