{
  "type": "Feature",
  "properties": {
    "addr:full":"1830 E Colonial Dr Orlando FL 32803",
    "addr:housenumber":"1830",
    "addr:postcode":"32803",
    "addr:street":"E Colonial Dr",
    "iso:country":"US",
    "sg:address":"1830 E Colonial Dr",
    "sg:city":"Orlando",
    "sg:classifiers":[
        {
            "category":"Personal",
            "subcategory":"Beauty Salon",
            "type":"Services"
        }
    ],
    "sg:phone":"+1 407 897 5253",
    "sg:postcode":"32803",
    "sg:province":"FL",
    "sg:tags":[
        "shop"
    ],
    "wof:name":"Instyle Design",
    "wof:placetype":"venue"
},
  "geometry": {"coordinates":[-81.357529,28.553061],"type":"Point"}
}