{
  "type": "Feature",
  "properties": {
    "iso:country":"US",
    "sg:address":"11760 SW 40th St Ste 323",
    "sg:city":"Miami",
    "sg:classifiers":[
        {
            "category":"Health Services",
            "subcategory":"Doctor",
            "type":"Services"
        }
    ],
    "sg:phone":"+1 305 223 9815",
    "sg:postcode":"33175",
    "sg:province":"FL",
    "wof:name":"Negret L J MD Faafp",
    "wof:placetype":"venue"
},
  "geometry": {"coordinates":[-80.385902,25.731899],"type":"Point"}
}