{
  "type": "Feature",
  "properties": {
    "iso:country":"US",
    "sg:address":"1645 Palm Beach Lakes Blvd",
    "sg:city":"Loxahatchee",
    "sg:classifiers":[
        {
            "category":"Real Estate",
            "subcategory":"Real Estate Agent",
            "type":"Services"
        }
    ],
    "sg:phone":"+1 561 684 2221",
    "sg:postcode":"33401",
    "sg:province":"FL",
    "wof:name":"CB Richard Ellis Inc",
    "wof:placetype":"venue"
},
  "geometry": {"coordinates":[-80.081982,26.724908],"type":"Point"}
}