{
  "type": "Feature",
  "properties": {
    "iso:country":"US",
    "sg:address":"7862 Sailboat Key Blvd S",
    "sg:city":"Saint Petersburg",
    "sg:classifiers":[
        {
            "category":"Wholesale",
            "subcategory":"Groceries",
            "type":"Manufacturing & Wholesale Goods"
        }
    ],
    "sg:phone":"+1 727 363 1555",
    "sg:postcode":"33707",
    "sg:province":"FL",
    "wof:name":"Erickson International",
    "wof:placetype":"venue"
},
  "geometry": {"coordinates":[-82.748828,27.751022],"type":"Point"}
}