{
  "type": "Feature",
  "properties": {
    "addr:full":"9267 N 56th St Tampa FL 33617",
    "addr:housenumber":"9267",
    "addr:postcode":"33617",
    "addr:street":"N 56Th St",
    "iso:country":"US",
    "sg:address":"9267 N 56th St",
    "sg:city":"Tampa",
    "sg:classifiers":[
        {
            "category":"Personal",
            "subcategory":"Beauty Salon",
            "type":"Services"
        }
    ],
    "sg:phone":"+1 813 988 3813",
    "sg:postcode":"33617",
    "sg:province":"FL",
    "sg:tags":[
        "hair"
    ],
    "wof:name":"Supercuts",
    "wof:placetype":"venue"
},
  "geometry": {"coordinates":[-82.393394,28.032889],"type":"Point"}
}