{
  "type": "Feature",
  "properties": {
    "addr:full":"21 W Columbia St Orlando FL 32806",
    "addr:housenumber":"21",
    "addr:postcode":"32806",
    "addr:street":"W Columbia St",
    "iso:country":"US",
    "sg:address":"21 W Columbia St",
    "sg:city":"Orlando",
    "sg:classifiers":[
        {
            "category":"Health Services",
            "subcategory":"Doctor",
            "type":"Services"
        }
    ],
    "sg:phone":"+1 407 245 1400",
    "sg:postcode":"32806",
    "sg:province":"FL",
    "sg:tags":[
        "medical"
    ],
    "wof:name":"Physician Associates Fla PA",
    "wof:placetype":"venue"
},
  "geometry": {"coordinates":[-81.37763,28.527966],"type":"Point"}
}