{
  "type": "Feature",
  "properties": {
    "addr:full":"3615 S Florida Ave Lakeland FL 33803",
    "addr:housenumber":"3615",
    "addr:postcode":"33803",
    "addr:street":"S Florida Ave",
    "iso:country":"US",
    "sg:address":"3615 S Florida Ave",
    "sg:city":"Lakeland",
    "sg:classifiers":[
        {
            "category":"Shopping",
            "subcategory":"Department Store",
            "type":"Retail Goods"
        }
    ],
    "sg:phone":"+1 863 647 3316",
    "sg:postcode":"33803",
    "sg:province":"FL",
    "sg:tags":[
        "shop",
        "clothing"
    ],
    "sg:website":"http://www.marshallsonline.com",
    "wof:name":"Marshalls",
    "wof:placetype":"venue"
},
  "geometry": {"coordinates":[-81.957123,27.99822],"type":"Point"}
}