{
  "type": "Feature",
  "properties": {
    "iso:country":"US",
    "sg:address":"1314 Prudential Dr",
    "sg:city":"Jacksonville",
    "sg:classifiers":[
        {
            "category":"Restaurant",
            "type":"Food & Drink"
        }
    ],
    "sg:menulink":"http://www.allmenus.com/fl/jacksonville/38624-wine-cellar/menu/",
    "sg:phone":"+1 904 398 8989",
    "sg:postcode":"32207",
    "sg:province":"FL",
    "sg:tags":[
        "american"
    ],
    "wof:name":"Wine Cellar",
    "wof:placetype":"venue"
},
  "geometry": {"coordinates":[-81.657087,30.316009],"type":"Point"}
}