{
  "type": "Feature",
  "properties": {
    "iso:country":"US",
    "sg:address":"1951 Pine Ridge Rd",
    "sg:city":"Naples",
    "sg:classifiers":[
        {
            "category":"Shopping",
            "subcategory":"Florist",
            "type":"Retail Goods"
        }
    ],
    "sg:phone":"+1 239 513 1644",
    "sg:postcode":"34109",
    "sg:province":"FL",
    "wof:name":"All Flowers",
    "wof:placetype":"venue"
},
  "geometry": {"coordinates":[-81.778749,26.211565],"type":"Point"}
}