{
  "type": "Feature",
  "properties": {
    "iso:country":"US",
    "sg:address":"1898 Harbor Ln",
    "sg:city":"Naples",
    "sg:classifiers":[
        {
            "category":"Building & Trades",
            "subcategory":"Electrical",
            "type":"Services"
        }
    ],
    "sg:phone":"+1 239 774 1560",
    "sg:postcode":"34104",
    "sg:province":"FL",
    "sg:tags":[
        "electrical",
        "contractor"
    ],
    "wof:name":"Norton Electric",
    "wof:placetype":"venue"
},
  "geometry": {"coordinates":[-81.77849000000001,26.140524],"type":"Point"}
}