{
  "type": "Feature",
  "properties": {
    "iso:country":"US",
    "sg:address":"3102 43rd St W",
    "sg:city":"Bradenton",
    "sg:classifiers":[
        {
            "category":"Organizations",
            "subcategory":"Membership Organization",
            "type":"Services"
        }
    ],
    "sg:phone":"+1 941 794 6252",
    "sg:postcode":"34209",
    "sg:province":"FL",
    "wof:name":"Magic of Manatee Sweet Adline",
    "wof:placetype":"venue"
},
  "geometry": {"coordinates":[-82.60415999999999,27.473085],"type":"Point"}
}