{
  "type": "Feature",
  "properties": {
    "iso:country":"US",
    "sg:address":"5095 Datil Pepper Rd",
    "sg:city":"St Augustine",
    "sg:classifiers":[
        {
            "category":"Building & Trades",
            "subcategory":"Electrical",
            "type":"Services"
        }
    ],
    "sg:phone":"+1 904 797 0212",
    "sg:postcode":"32086",
    "sg:province":"FL",
    "sg:tags":[
        "electrical",
        "electric",
        "contractor"
    ],
    "wof:name":"Jones Electric",
    "wof:placetype":"venue"
},
  "geometry": {"coordinates":[-81.324637,29.793404],"type":"Point"}
}