{
  "type": "Feature",
  "properties": {
    "iso:country":"US",
    "sg:address":"2534 Colonel Ford Dr",
    "sg:city":"Lakeland",
    "sg:classifiers":[
        {
            "category":"Travel",
            "subcategory":"Travel Agent",
            "type":"Entertainment"
        }
    ],
    "sg:phone":"+1 863 619 5490",
    "sg:postcode":"33813",
    "sg:province":"FL",
    "sg:tags":[
        "agency"
    ],
    "wof:name":"Blue Sky Travel Svcs Inc",
    "wof:placetype":"venue"
},
  "geometry": {"coordinates":[-81.916591,27.944179],"type":"Point"}
}