{
  "type": "Feature",
  "properties": {
    "iso:country":"US",
    "sg:address":"123 Reedy Creek Dr",
    "sg:city":"Frostproof",
    "sg:classifiers":[
        {
            "category":"Farming",
            "subcategory":"Nursery",
            "type":"Manufacturing & Wholesale Goods"
        }
    ],
    "sg:phone":"+1 863 635 5276",
    "sg:postcode":"33843",
    "sg:province":"FL",
    "sg:tags":[
        "ornamental"
    ],
    "wof:name":"Reedy Creek Nursery Inc",
    "wof:placetype":"venue"
},
  "geometry": {"coordinates":[-81.475722,27.711025],"type":"Point"}
}