{
  "type": "Feature",
  "properties": {
    "iso:country":"US",
    "sg:address":"311 Anastasia Blvd",
    "sg:city":"St Augustine",
    "sg:classifiers":[
        {
            "category":"Food & Beverages",
            "subcategory":"Fruits & Vegetables",
            "type":"Retail Goods"
        }
    ],
    "sg:phone":"+1 904 824 5637",
    "sg:postcode":"32080",
    "sg:province":"FL",
    "sg:tags":[
        "produce"
    ],
    "wof:name":"Stewarts Produce Inc",
    "wof:placetype":"venue"
},
  "geometry": {"coordinates":[-81.29928700000001,29.891402],"type":"Point"}
}