{
  "type": "Feature",
  "properties": {
    "addr:full":"16495 NW 49th Ave Hialeah FL 33014",
    "addr:housenumber":"16495",
    "addr:postcode":"33014",
    "addr:street":"Nw 49Th Ave",
    "iso:country":"US",
    "sg:address":"16495 NW 49th Ave",
    "sg:city":"Hialeah",
    "sg:classifiers":[
        {
            "category":"Home & Garden",
            "subcategory":"Carpets & Floor Coverings",
            "type":"Retail Goods"
        }
    ],
    "sg:phone":"+1 305 628 0415",
    "sg:postcode":"33014",
    "sg:province":"FL",
    "sg:tags":[
        "rug"
    ],
    "wof:name":"Oriental Rugs Enterprise Inc",
    "wof:placetype":"venue"
},
  "geometry": {"coordinates":[-80.280638,25.923244],"type":"Point"}
}