{
  "type": "Feature",
  "properties": {
    "iso:country":"US",
    "sg:address":"1212 E Gore St",
    "sg:city":"Orlando",
    "sg:classifiers":[
        {
            "category":"Health Services",
            "subcategory":"Doctor",
            "type":"Services"
        }
    ],
    "sg:phone":"+1 407 894 6618",
    "sg:postcode":"32806",
    "sg:province":"FL",
    "sg:tags":[
        "physician",
        "surgeon",
        "surgeons",
        "infectious",
        "disease"
    ],
    "wof:name":"Mid Florida Infectious Disease Pa",
    "wof:placetype":"venue"
},
  "geometry": {"coordinates":[-81.363981,28.531292],"type":"Point"}
}