{
  "type": "Feature",
  "properties": {
    "iso:country":"US",
    "sg:address":"401 Venture Dr",
    "sg:city":"South Daytona",
    "sg:classifiers":[
        {
            "category":"Health Services",
            "subcategory":"Health Practitioner",
            "type":"Services"
        }
    ],
    "sg:phone":"+1 386 763 0084",
    "sg:postcode":"32119",
    "sg:province":"FL",
    "sg:tags":[
        "therapist",
        "physical"
    ],
    "wof:name":"Ability Health Svc",
    "wof:placetype":"venue"
},
  "geometry": {"coordinates":[-80.994781,29.152966],"type":"Point"}
}