{
  "type": "Feature",
  "properties": {
    "iso:country":"US",
    "sg:address":"1089 N Collier Blvd",
    "sg:city":"Marco Island",
    "sg:classifiers":[
        {
            "category":"Banks & Credit Unions",
            "subcategory":"Bank",
            "type":"Services"
        }
    ],
    "sg:phone":"+1 239 389 0500",
    "sg:postcode":"34145",
    "sg:province":"FL",
    "sg:tags":[
        "loan",
        "real estate"
    ],
    "wof:name":"Mortgage Creations",
    "wof:placetype":"venue"
},
  "geometry": {"coordinates":[-81.72443699999999,25.954296],"type":"Point"}
}