{
  "type": "Feature",
  "properties": {
    "addr:full":"1600 Winchester Rd N Saint Petersburg FL 33710",
    "addr:housenumber":"1600",
    "addr:postcode":"33710",
    "addr:street":"Winchester Rd N",
    "iso:country":"US",
    "sg:address":"1600 Winchester Rd N",
    "sg:city":"Saint Petersburg",
    "sg:classifiers":[
        {
            "category":"Building & Trades",
            "subcategory":"Construction",
            "type":"Services"
        }
    ],
    "sg:phone":"+1 727 345 8164",
    "sg:postcode":"33710",
    "sg:province":"FL",
    "sg:tags":[
        "builder",
        "operative"
    ],
    "wof:name":"Sharp Communications & Co",
    "wof:placetype":"venue"
},
  "geometry": {"coordinates":[-82.714979,27.788123],"type":"Point"}
}