{
  "type": "Feature",
  "properties": {
    "iso:country":"US",
    "sg:address":"4413 N Hale Ave",
    "sg:city":"Tampa",
    "sg:classifiers":[
        {
            "category":"Manufacturing",
            "subcategory":"Building Materials",
            "type":"Manufacturing & Wholesale Goods"
        }
    ],
    "sg:phone":"+1 813 350 9847",
    "sg:postcode":"33614",
    "sg:province":"FL",
    "sg:tags":[
        "mfg",
        "kitchen",
        "formica",
        "cabinet"
    ],
    "wof:name":"M&N Casework",
    "wof:placetype":"venue"
},
  "geometry": {"coordinates":[-82.51076500000001,27.983719],"type":"Point"}
}