{
  "type": "Feature",
  "properties": {
    "iso:country":"US",
    "sg:address":"1645 E 9th St",
    "sg:city":"Jacksonville",
    "sg:classifiers":[
        {
            "category":"Organizations",
            "subcategory":"Religious Organization",
            "type":"Services"
        }
    ],
    "sg:phone":"+1 904 355 0474",
    "sg:postcode":"32206",
    "sg:province":"FL",
    "wof:name":"United Full Gospel Of Christ",
    "wof:placetype":"venue"
},
  "geometry": {"coordinates":[-81.63302,30.346333],"type":"Point"}
}