{
  "type": "Feature",
  "properties": {
    "addr:full":"260 Crandon Blvd Key Biscayne FL 33149",
    "addr:housenumber":"260",
    "addr:postcode":"33149",
    "addr:street":"Crandon Blvd",
    "iso:country":"US",
    "sg:address":"260 Crandon Blvd",
    "sg:city":"Key Biscayne",
    "sg:classifiers":[
        {
            "category":"Personal",
            "subcategory":"Beauty Salon",
            "type":"Services"
        }
    ],
    "sg:phone":"+1 305 365 2166",
    "sg:postcode":"33149",
    "sg:province":"FL",
    "wof:name":"Diana Poitier's Salon",
    "wof:placetype":"venue"
},
  "geometry": {"coordinates":[-80.16283300000001,25.693841],"type":"Point"}
}