{
  "type": "Feature",
  "properties": {
    "addr:full":"10434 NW 31st Ter Doral FL 33172",
    "addr:housenumber":"10434",
    "addr:postcode":"33172",
    "addr:street":"Nw 31St Ter",
    "iso:country":"US",
    "sg:address":"10434 NW 31st Ter",
    "sg:city":"Doral",
    "sg:classifiers":[
        {
            "category":"Professional",
            "subcategory":"Testing Lab",
            "type":"Services"
        }
    ],
    "sg:phone":"+1 305 994 8031",
    "sg:postcode":"33172",
    "sg:province":"FL",
    "sg:tags":[
        "laboratory",
        "business",
        "calibration"
    ],
    "sg:website":"www.insco.us",
    "wof:name":"Insco Metrology Inc",
    "wof:placetype":"venue"
},
  "geometry": {"coordinates":[-80.367116,25.803157],"type":"Point"}
}