{
  "type": "Feature",
  "properties": {
    "addr:full":"7607 S Florida Ave Floral City FL 34436",
    "addr:housenumber":"7607",
    "addr:postcode":"34436",
    "addr:street":"S Florida Ave",
    "iso:country":"US",
    "sg:address":"7607 S Florida Ave",
    "sg:city":"Floral City",
    "sg:classifiers":[
        {
            "category":"Wholesale",
            "subcategory":"Fruits & Vegetables",
            "type":"Manufacturing & Wholesale Goods"
        }
    ],
    "sg:phone":"+1 352 637 3880",
    "sg:postcode":"34436",
    "sg:province":"FL",
    "sg:tags":[
        "shipper"
    ],
    "wof:name":"Ferris Farms Inc",
    "wof:placetype":"venue"
},
  "geometry": {"coordinates":[-82.29675400000001,28.752179],"type":"Point"}
}