{
  "type": "Feature",
  "properties": {
    "iso:country":"US",
    "sg:address":"8900 Woodgate Manor Ct",
    "sg:city":"Fort Myers",
    "sg:classifiers":[
        {
            "category":"Shopping",
            "subcategory":"Pharmacy",
            "type":"Retail Goods"
        }
    ],
    "sg:phone":"+1 239 415 7048",
    "sg:postcode":"33908",
    "sg:province":"FL",
    "wof:name":"Affordable Canadian Rx Svc",
    "wof:placetype":"venue"
},
  "geometry": {"coordinates":[-81.900719,26.488609],"type":"Point"}
}