{
  "type": "Feature",
  "properties": {
    "iso:country":"US",
    "sg:address":"1715 Lakeside Ave",
    "sg:city":"St Augustine",
    "sg:classifiers":[
        {
            "category":"Wholesale",
            "subcategory":"Electrical",
            "type":"Manufacturing & Wholesale Goods"
        }
    ],
    "sg:phone":"+1 904 826 0730",
    "sg:postcode":"32084",
    "sg:province":"FL",
    "sg:tags":[
        "equipment",
        "electric",
        "supply"
    ],
    "wof:name":"City Electric Supply Co",
    "wof:placetype":"venue"
},
  "geometry": {"coordinates":[-81.331532,29.868409],"type":"Point"}
}