{
  "type": "Feature",
  "properties": {
    "iso:country":"US",
    "sg:address":"1625 Center St",
    "sg:city":"Deland",
    "sg:classifiers":[
        {
            "category":"Wholesale",
            "subcategory":"Electrical",
            "type":"Manufacturing & Wholesale Goods"
        }
    ],
    "sg:phone":"+1 386 738 3296",
    "sg:postcode":"32720",
    "sg:province":"FL",
    "sg:tags":[
        "control",
        "security",
        "system"
    ],
    "wof:name":"SKS Alarms",
    "wof:placetype":"venue"
},
  "geometry": {"coordinates":[-81.35968699999999,29.002265],"type":"Point"}
}