{
  "type": "Feature",
  "properties": {
    "iso:country":"US",
    "sg:address":"4052 Gulf of Mexico Dr",
    "sg:city":"Longboat Key",
    "sg:classifiers":[
        {
            "category":"Recreation",
            "type":"Entertainment"
        }
    ],
    "sg:phone":"+1 941 316 1980",
    "sg:postcode":"34228",
    "sg:province":"FL",
    "sg:tags":[
        "center"
    ],
    "wof:name":"Bayfront Park Recreation Ctr",
    "wof:placetype":"venue"
},
  "geometry": {"coordinates":[-82.641154,27.38972],"type":"Point"}
}