{
  "type": "Feature",
  "properties": {
    "iso:country":"US",
    "sg:address":"3611 Kingswood Dr",
    "sg:city":"Sarasota",
    "sg:classifiers":[
        {
            "category":"Home & Garden",
            "subcategory":"Building Materials",
            "type":"Retail Goods"
        }
    ],
    "sg:phone":"+1 941 378 9574",
    "sg:postcode":"34232",
    "sg:province":"FL",
    "sg:tags":[
        "windows"
    ],
    "wof:name":"Holly Window & Doors Spec Inc",
    "wof:placetype":"venue"
},
  "geometry": {"coordinates":[-82.456202,27.300918],"type":"Point"}
}