{
  "type": "Feature",
  "properties": {
    "iso:country":"US",
    "sg:address":"2828 S Tamiami Trl",
    "sg:city":"Sarasota",
    "sg:classifiers":[
        {
            "category":"Health Services",
            "subcategory":"Doctor",
            "type":"Services"
        }
    ],
    "sg:phone":"+1 941 957 0200",
    "sg:postcode":"34239",
    "sg:province":"FL",
    "sg:tags":[
        "physician",
        "surgeon"
    ],
    "wof:name":"Progressive Medical",
    "wof:placetype":"venue"
},
  "geometry": {"coordinates":[-82.530141,27.307731],"type":"Point"}
}