{
  "type": "Feature",
  "properties": {
    "iso:country":"US",
    "sg:address":"4163 Amber Ln",
    "sg:city":"Palm Harbor",
    "sg:classifiers":[
        {
            "category":"Professional",
            "subcategory":"Management & Consulting",
            "type":"Services"
        }
    ],
    "sg:phone":"+1 727 784 2626",
    "sg:postcode":"34685",
    "sg:province":"FL",
    "sg:tags":[
        "marketing",
        "program"
    ],
    "wof:name":"Timeline Marketing Group",
    "wof:placetype":"venue"
},
  "geometry": {"coordinates":[-82.69823,28.11021],"type":"Point"}
}