{
  "type": "Feature",
  "properties": {
    "addr:full":"2000 Universal Studios Plz Orlando FL 32819",
    "addr:housenumber":"2000",
    "addr:postcode":"32819",
    "addr:street":"Universal Studios",
    "iso:country":"US",
    "sg:address":"2000 Universal Studios Plz",
    "sg:city":"Orlando",
    "sg:classifiers":[
        {
            "category":"Professional",
            "subcategory":"Advertising",
            "type":"Services"
        }
    ],
    "sg:phone":"+1 407 363 2066",
    "sg:postcode":"32819",
    "sg:province":"FL",
    "sg:tags":[
        "advertising-broadcast",
        "agency",
        "film"
    ],
    "sg:website":"http://www.aztecamex.com",
    "wof:name":"Azteca America Orlando",
    "wof:placetype":"venue"
},
  "geometry": {"coordinates":[-81.471481,28.477819],"type":"Point"}
}