{
  "type": "Feature",
  "properties": {
    "iso:country":"US",
    "sg:address":"711 W Fletcher Ave",
    "sg:city":"Tampa",
    "sg:classifiers":[
        {
            "category":"Professional",
            "subcategory":"Lawyer & Legal Services",
            "type":"Services"
        }
    ],
    "sg:phone":"+1 813 908 6256",
    "sg:postcode":"33612",
    "sg:province":"FL",
    "sg:tags":[
        "attorney"
    ],
    "sg:website":"www.tampabayestateplanning.com",
    "wof:name":"Michael Lins Law Office",
    "wof:placetype":"venue"
},
  "geometry": {"coordinates":[-82.46623,28.0694],"type":"Point"}
}