{
  "type": "Feature",
  "properties": {
    "iso:country":"US",
    "sg:address":"11720 Strand Way",
    "sg:city":"Hollywood",
    "sg:classifiers":[
        {
            "category":"Banks & Credit Unions",
            "subcategory":"Investment Brokerage",
            "type":"Services"
        },
        {
            "category":"Insurance",
            "subcategory":"Hazard Insurance",
            "type":"Services"
        }
    ],
    "sg:phone":"+1 954 435 7818",
    "sg:postcode":"33026",
    "sg:province":"FL",
    "sg:tags":[
        "agent",
        "resume"
    ],
    "wof:name":"Donald B Hall & Company",
    "wof:placetype":"venue"
},
  "geometry": {"coordinates":[-80.303061,26.033133],"type":"Point"}
}