{
  "type": "Feature",
  "properties": {
    "iso:country":"US",
    "sg:address":"4760 Tamiami Trl N",
    "sg:city":"Naples",
    "sg:classifiers":[
        {
            "category":"Real Estate",
            "subcategory":"Real Estate Agent",
            "type":"Services"
        }
    ],
    "sg:phone":"+1 239 659 1112",
    "sg:postcode":"34103",
    "sg:province":"FL",
    "wof:name":"Ixora Realty",
    "wof:placetype":"venue"
},
  "geometry": {"coordinates":[-81.80020399999999,26.203094],"type":"Point"}
}