{
  "type": "Feature",
  "properties": {
    "iso:country":"US",
    "sg:address":"5329 S River Rd",
    "sg:city":"Jacksonville",
    "sg:classifiers":[
        {
            "category":"Building & Trades",
            "subcategory":"Construction",
            "type":"Services"
        }
    ],
    "sg:phone":"+1 904 744 3124",
    "sg:postcode":"32211",
    "sg:province":"FL",
    "sg:tags":[
        "general",
        "contractor"
    ],
    "wof:name":"Belk & Ashworth Contracting",
    "wof:placetype":"venue"
},
  "geometry": {"coordinates":[-81.603662,30.341116],"type":"Point"}
}