{
  "type": "Feature",
  "properties": {
    "addr:full":"13601 Mc Cormick Dr Tampa FL 33626",
    "addr:housenumber":"13601",
    "addr:postcode":"33626",
    "addr:street":"Mc Cormick Dr",
    "iso:country":"US",
    "sg:address":"13601 Mc Cormick Dr",
    "sg:city":"Tampa",
    "sg:classifiers":[
        {
            "category":"Manufacturing",
            "subcategory":"Tools & Machinery",
            "type":"Manufacturing & Wholesale Goods"
        }
    ],
    "sg:phone":"+1 813 855 5768",
    "sg:postcode":"33626",
    "sg:province":"FL",
    "sg:tags":[
        "machine",
        "shop",
        "precision"
    ],
    "wof:name":"Tampa Bay Machining Inc",
    "wof:placetype":"venue"
},
  "geometry": {"coordinates":[-82.646361,28.061725],"type":"Point"}
}