{
  "type": "Feature",
  "properties": {
    "addr:full":"11340 SW 208th Dr Miami FL 33189",
    "addr:housenumber":"11340",
    "addr:postcode":"33189",
    "addr:street":"Sw 208Th Dr",
    "iso:country":"US",
    "sg:address":"11340 SW 208th Dr",
    "sg:city":"Miami",
    "sg:classifiers":[
        {
            "category":"Manufacturing",
            "subcategory":"Tools & Machinery",
            "type":"Manufacturing & Wholesale Goods"
        }
    ],
    "sg:phone":"+1 305 235 4190",
    "sg:postcode":"33189",
    "sg:province":"FL",
    "sg:tags":[
        "farm",
        "equipment",
        "industrial",
        "mfg"
    ],
    "wof:name":"American Conveyor Corp",
    "wof:placetype":"venue"
},
  "geometry": {"coordinates":[-80.37621799999999,25.573297],"type":"Point"}
}