{
  "type": "Feature",
  "properties": {
    "addr:full":"8601 US Hwy 1 Port Saint Lucie FL 34982",
    "addr:housenumber":"8601",
    "addr:postcode":"34982",
    "addr:street":"Us Hwy 1",
    "iso:country":"US",
    "sg:address":"8601 US Hwy 1",
    "sg:city":"Port Saint Lucie",
    "sg:classifiers":[
        {
            "category":"Real Estate",
            "subcategory":"Real Estate Agent",
            "type":"Services"
        }
    ],
    "sg:phone":"+1 772 485 1038",
    "sg:postcode":"34982",
    "sg:province":"FL",
    "wof:name":"Hawkins Realty",
    "wof:placetype":"venue"
},
  "geometry": {"coordinates":[-80.31128699999999,27.310594],"type":"Point"}
}