{
  "type": "Feature",
  "properties": {
    "iso:country":"US",
    "sg:address":"4154 Haines Rd N",
    "sg:city":"St Petersburg",
    "sg:classifiers":[
        {
            "category":"Retail",
            "subcategory":"Laundry & Dry Cleaning",
            "type":"Services"
        }
    ],
    "sg:phone":"+1 727 209 0573",
    "sg:postcode":"33703",
    "sg:province":"FL",
    "wof:name":"Wash N' Go Laundry",
    "wof:placetype":"venue"
},
  "geometry": {"coordinates":[-82.65498599999999,27.810731],"type":"Point"}
}