{
  "type": "Feature",
  "properties": {
    "iso:country":"US",
    "sg:address":"3853 Cleveland Ave Ste A",
    "sg:city":"Fort Myers",
    "sg:classifiers":[
        {
            "category":"Shopping",
            "subcategory":"Pharmacy",
            "type":"Retail Goods"
        }
    ],
    "sg:phone":"+1 239 939 1116",
    "sg:postcode":"33901",
    "sg:province":"FL",
    "sg:tags":[
        "drugstore"
    ],
    "wof:name":"Kmart Stores",
    "wof:placetype":"venue"
},
  "geometry": {"coordinates":[-81.87190200000001,26.6061],"type":"Point"}
}