{
  "type": "Feature",
  "properties": {
    "iso:country":"US",
    "sg:address":"307 E Atlantic Ave",
    "sg:city":"Delray Beach",
    "sg:classifiers":[
        {
            "category":"Restaurant",
            "type":"Food & Drink"
        }
    ],
    "sg:phone":"+1 561 243 2404",
    "sg:postcode":"33483",
    "sg:province":"FL",
    "wof:name":"Loco's Only",
    "wof:placetype":"venue"
},
  "geometry": {"coordinates":[-80.069102,26.461726],"type":"Point"}
}