{
  "type": "Feature",
  "properties": {
    "iso:country":"US",
    "sg:address":"5100 N 9th Ave",
    "sg:city":"Pensacola",
    "sg:classifiers":[
        {
            "category":"Restaurant",
            "type":"Food & Drink"
        }
    ],
    "sg:menulink":"http://www.allmenus.com/fl/pensacola/179759-chick-fil-a/menu/",
    "sg:phone":"+1 850 477 7979",
    "sg:postcode":"32504",
    "sg:province":"FL",
    "sg:tags":[
        "wrap",
        "soup",
        "american",
        "sandwich",
        "salad"
    ],
    "wof:name":"Chick-fil-A",
    "wof:placetype":"venue"
},
  "geometry": {"coordinates":[-87.211434,30.474436],"type":"Point"}
}