{
  "type": "Feature",
  "properties": {
    "addr:full":"384 S Main St Belle Glade FL 33430",
    "addr:housenumber":"384",
    "addr:postcode":"33430",
    "addr:street":"S Main St",
    "iso:country":"US",
    "sg:address":"384 S Main St",
    "sg:city":"Belle Glade",
    "sg:classifiers":[
        {
            "category":"Restaurant",
            "type":"Food & Drink"
        }
    ],
    "sg:phone":"+1 561 993 3855",
    "sg:postcode":"33430",
    "sg:province":"FL",
    "sg:tags":[
        "eating"
    ],
    "wof:name":"Belle Glade Bakery",
    "wof:placetype":"venue"
},
  "geometry": {"coordinates":[-80.66789300000001,26.683274],"type":"Point"}
}