{
  "type": "Feature",
  "properties": {
    "addr:full":"2110 Sevilla Way Naples FL 34109",
    "addr:housenumber":"2110",
    "addr:postcode":"34109",
    "addr:street":"Sevilla Way",
    "iso:country":"US",
    "sg:address":"2110 Sevilla Way",
    "sg:city":"Naples",
    "sg:classifiers":[
        {
            "category":"Wholesale",
            "subcategory":"Toys & Hobbies",
            "type":"Manufacturing & Wholesale Goods"
        }
    ],
    "sg:phone":"+1 239 596 6069",
    "sg:postcode":"34109",
    "sg:province":"FL",
    "wof:name":"Art E Fact LLC",
    "wof:placetype":"venue"
},
  "geometry": {"coordinates":[-81.779166,26.236215],"type":"Point"}
}