{
  "type": "Feature",
  "properties": {
    "iso:country":"US",
    "sg:address":"240 Sheline Dr",
    "sg:city":"Havana",
    "sg:classifiers":[
        {
            "category":"Building & Trades",
            "subcategory":"Construction",
            "type":"Services"
        }
    ],
    "sg:phone":"+1 850 539 0810",
    "sg:postcode":"32333",
    "sg:province":"FL",
    "sg:tags":[
        "contractor"
    ],
    "wof:name":"Black Dog Kitchens Inc",
    "wof:placetype":"venue"
},
  "geometry": {"coordinates":[-84.47228699999999,30.534777],"type":"Point"}
}