{
  "type": "Feature",
  "properties": {
    "addr:full":"5630 Matanzas Dr Sebring FL 33872",
    "addr:housenumber":"5630",
    "addr:postcode":"33872",
    "addr:street":"Matanzas Dr",
    "iso:country":"US",
    "sg:address":"5630 Matanzas Dr",
    "sg:city":"Sebring",
    "sg:classifiers":[
        {
            "category":"Real Estate",
            "subcategory":"Real Estate Agent",
            "type":"Services"
        }
    ],
    "sg:phone":"+1 863 382 9199",
    "sg:postcode":"33872",
    "sg:province":"FL",
    "sg:tags":[
        "condominium"
    ],
    "wof:name":"Linkside Condominium Assn",
    "wof:placetype":"venue"
},
  "geometry": {"coordinates":[-81.52465599999999,27.521192],"type":"Point"}
}