{
  "type": "Feature",
  "properties": {
    "addr:full":"150 N US Hwy 1 Jupiter FL 33469",
    "addr:housenumber":"150",
    "addr:postcode":"33469",
    "addr:street":"N Us Hwy 1",
    "iso:country":"US",
    "sg:address":"150 N US Hwy 1",
    "sg:city":"Jupiter",
    "sg:classifiers":[
        {
            "category":"Health Services",
            "subcategory":"Doctor",
            "type":"Services"
        }
    ],
    "sg:phone":"+1 561 371 4336",
    "sg:postcode":"33469",
    "sg:province":"FL",
    "sg:tags":[
        "medical"
    ],
    "wof:name":"All For Health Inc",
    "wof:placetype":"venue"
},
  "geometry": {"coordinates":[-80.084695,26.961206],"type":"Point"}
}