{
  "type": "Feature",
  "properties": {
    "iso:country":"US",
    "sg:address":"439 US Hwy 29",
    "sg:city":"Cantonment",
    "sg:classifiers":[
        {
            "category":"Home & Garden",
            "subcategory":"Hardware",
            "type":"Retail Goods"
        }
    ],
    "sg:phone":"+1 850 968 2415",
    "sg:postcode":"32533",
    "sg:province":"FL",
    "sg:tags":[
        "merchandise"
    ],
    "wof:name":"Reynolds Hardware 2",
    "wof:placetype":"venue"
},
  "geometry": {"coordinates":[-87.323812,30.616338],"type":"Point"}
}