{
  "type": "Feature",
  "properties": {
    "iso:country":"US",
    "sg:address":"496 Saddell Bay Loop",
    "sg:city":"Ocoee",
    "sg:classifiers":[
        {
            "category":"Wholesale",
            "subcategory":"Machinery & Supplies",
            "type":"Manufacturing & Wholesale Goods"
        }
    ],
    "sg:phone":"+1 407 656 9925",
    "sg:postcode":"34761",
    "sg:province":"FL",
    "sg:tags":[
        "electrical",
        "rep",
        "electronic",
        "pump",
        "mfg"
    ],
    "wof:name":"Industrial Pumps Inc",
    "wof:placetype":"venue"
},
  "geometry": {"coordinates":[-81.55093100000001,28.533093],"type":"Point"}
}