{
  "type": "Feature",
  "properties": {
    "addr:full":"9609 Westgate Cir Pensacola FL 32507",
    "addr:housenumber":"9609",
    "addr:postcode":"32507",
    "addr:street":"Westgate Cir",
    "iso:country":"US",
    "sg:address":"9609 Westgate Cir",
    "sg:city":"Pensacola",
    "sg:classifiers":[
        {
            "category":"Building & Trades",
            "subcategory":"Construction",
            "type":"Services"
        }
    ],
    "sg:phone":"+1 850 937 0061",
    "sg:postcode":"32507",
    "sg:province":"FL",
    "sg:tags":[
        "porch",
        "enclosure",
        "patio",
        "deck"
    ],
    "wof:name":"Markos Patios",
    "wof:placetype":"venue"
},
  "geometry": {"coordinates":[-87.34573,30.340907],"type":"Point"}
}