{
  "type": "Feature",
  "properties": {
    "addr:full":"8403 S Tamiami Trl Sarasota FL 34238",
    "addr:housenumber":"8403",
    "addr:postcode":"34238",
    "addr:street":"S Tamiami Trl",
    "iso:country":"US",
    "sg:address":"8403 S Tamiami Trl",
    "sg:city":"Sarasota",
    "sg:classifiers":[
        {
            "category":"Retail",
            "subcategory":"Car Wash",
            "type":"Services"
        }
    ],
    "sg:phone":"+1 941 926 3900",
    "sg:postcode":"34238",
    "sg:province":"FL",
    "sg:tags":[
        "polishing",
        "washing"
    ],
    "wof:name":"Tropical Car Wash & Auto Salon",
    "wof:placetype":"venue"
},
  "geometry": {"coordinates":[-82.494072,27.228407],"type":"Point"}
}