{
  "type": "Feature",
  "properties": {
    "iso:country":"US",
    "sg:address":"1517 Central Ave",
    "sg:city":"St Petersburg",
    "sg:classifiers":[
        {
            "category":"Autos & Motor Vehicles",
            "subcategory":"Fuel & Gas Station",
            "type":"Retail Goods"
        }
    ],
    "sg:phone":"+1 727 823 0960",
    "sg:postcode":"33705",
    "sg:province":"FL",
    "sg:tags":[
        "oil"
    ],
    "wof:name":"Sam's Shell",
    "wof:placetype":"venue"
},
  "geometry": {"coordinates":[-82.654742,27.771178],"type":"Point"}
}