{
  "type": "Feature",
  "properties": {
    "addr:full":"2909 Circle Ridge Dr Orange Park FL 32065",
    "addr:housenumber":"2909",
    "addr:postcode":"32065",
    "addr:street":"Circle Ridge Dr",
    "iso:country":"US",
    "sg:address":"2909 Circle Ridge Dr",
    "sg:city":"Orange Park",
    "sg:classifiers":[
        {
            "category":"Building & Trades",
            "subcategory":"Electrical",
            "type":"Services"
        }
    ],
    "sg:phone":"+1 904 272 4036",
    "sg:postcode":"32065",
    "sg:province":"FL",
    "sg:tags":[
        "electrical",
        "contractor"
    ],
    "wof:name":"Warfuel Electric",
    "wof:placetype":"venue"
},
  "geometry": {"coordinates":[-81.76606099999999,30.149725],"type":"Point"}
}