{
  "type": "Feature",
  "properties": {
    "addr:full":"200 Valley Dr Longwood FL 32779",
    "addr:housenumber":"200",
    "addr:postcode":"32779",
    "addr:street":"Valley Dr",
    "iso:country":"US",
    "sg:address":"200 Valley Dr",
    "sg:city":"Longwood",
    "sg:classifiers":[
        {
            "category":"Professional",
            "subcategory":"Detective & Security Services",
            "type":"Services"
        }
    ],
    "sg:phone":"+1 407 774 8995",
    "sg:postcode":"32779",
    "sg:province":"FL",
    "sg:tags":[
        "agency"
    ],
    "wof:name":"Command Group Investigations",
    "wof:placetype":"venue"
},
  "geometry": {"coordinates":[-81.428651,28.702239],"type":"Point"}
}