{
  "type": "Feature",
  "properties": {
    "iso:country":"US",
    "sg:address":"311 E Morse Blvd",
    "sg:city":"Winter Park",
    "sg:classifiers":[
        {
            "category":"Real Estate",
            "subcategory":"Real Estate Operator",
            "type":"Services"
        }
    ],
    "sg:phone":"+1 407 647 7160",
    "sg:postcode":"32789",
    "sg:province":"FL",
    "sg:tags":[
        "apartment"
    ],
    "wof:name":"Whispering Waters Apts",
    "wof:placetype":"venue"
},
  "geometry": {"coordinates":[-81.34850299999999,28.5979],"type":"Point"}
}