{
  "type": "Feature",
  "properties": {
    "addr:full":"8485 Bird Rd Miami FL 33155",
    "addr:housenumber":"8485",
    "addr:postcode":"33155",
    "addr:street":"Bird Rd",
    "iso:country":"US",
    "sg:address":"8485 Bird Rd",
    "sg:city":"Miami",
    "sg:classifiers":[
        {
            "category":"Health Services",
            "subcategory":"Doctor",
            "type":"Services"
        }
    ],
    "sg:phone":"+1 305 551 3412",
    "sg:postcode":"33155",
    "sg:province":"FL",
    "sg:tags":[
        "podiatrist"
    ],
    "wof:name":"Bird Road Medical Center Inc",
    "wof:placetype":"venue"
},
  "geometry": {"coordinates":[-80.33338999999999,25.734143],"type":"Point"}
}