{
  "type": "Feature",
  "properties": {
    "addr:full":"3653 S Orlando Dr Sanford FL 32773",
    "addr:housenumber":"3653",
    "addr:postcode":"32773",
    "addr:street":"S Orlando Dr",
    "iso:country":"US",
    "sg:address":"3653 S Orlando Dr",
    "sg:city":"Sanford",
    "sg:classifiers":[
        {
            "category":"Health Services",
            "subcategory":"Optometrist",
            "type":"Services"
        }
    ],
    "sg:phone":"+1 407 328 1172",
    "sg:postcode":"32773",
    "sg:province":"FL",
    "wof:name":"Stephen Sindlinger Dr",
    "wof:placetype":"venue"
},
  "geometry": {"coordinates":[-81.28576700000001,28.759221],"type":"Point"}
}