{
  "type": "Feature",
  "properties": {
    "iso:country":"US",
    "sg:address":"4135 Gall Blvd",
    "sg:city":"Zephyrhills",
    "sg:classifiers":[
        {
            "category":"Home & Garden",
            "subcategory":"Household Appliances",
            "type":"Retail Goods"
        }
    ],
    "sg:phone":"+1 813 782 4771",
    "sg:postcode":"33542",
    "sg:province":"FL",
    "sg:tags":[
        "electric"
    ],
    "wof:name":"Plymale Appliance Inc",
    "wof:placetype":"venue"
},
  "geometry": {"coordinates":[-82.179993,28.21865],"type":"Point"}
}