{
  "type": "Feature",
  "properties": {
    "iso:country":"US",
    "sg:address":"6336 San Juan Ave",
    "sg:city":"Jacksonville",
    "sg:classifiers":[
        {
            "category":"Banks & Credit Unions",
            "subcategory":"Bank",
            "type":"Services"
        }
    ],
    "sg:phone":"+1 904 695 2224",
    "sg:postcode":"32210",
    "sg:province":"FL",
    "sg:tags":[
        "depository",
        "banking",
        "check",
        "cashing"
    ],
    "wof:name":"Uncle Sams Check Cashing Inc",
    "wof:placetype":"venue"
},
  "geometry": {"coordinates":[-81.74588900000001,30.281983],"type":"Point"}
}