{
  "type": "Feature",
  "properties": {
    "addr:full":"542 Biscayne Dr Satellite Beach FL 32937",
    "addr:housenumber":"542",
    "addr:postcode":"32937",
    "addr:street":"Biscayne Dr",
    "iso:country":"US",
    "sg:address":"542 Biscayne Dr",
    "sg:city":"Satellite Beach",
    "sg:classifiers":[
        {
            "category":"Building & Trades",
            "subcategory":"Construction",
            "type":"Services"
        }
    ],
    "sg:phone":"+1 321 779 9963",
    "sg:postcode":"32937",
    "sg:province":"FL",
    "sg:tags":[
        "house"
    ],
    "wof:name":"Danny Tamblyn Construction",
    "wof:placetype":"venue"
},
  "geometry": {"coordinates":[-80.58982899999999,28.148233],"type":"Point"}
}