{
  "type": "Feature",
  "properties": {
    "addr:full":"21820 Co Rd 236 High Springs FL 32643",
    "addr:housenumber":"21820;236",
    "addr:postcode":"32643",
    "addr:street":"Co Rd",
    "iso:country":"US",
    "sg:address":"21820 Co Rd 236",
    "sg:city":"High Springs",
    "sg:classifiers":[
        {
            "category":"Building & Trades",
            "subcategory":"Construction",
            "type":"Services"
        }
    ],
    "sg:phone":"+1 386 454 7867",
    "sg:postcode":"32643",
    "sg:province":"FL",
    "sg:tags":[
        "well",
        "drilling"
    ],
    "wof:name":"North Florida Water Systs Inc",
    "wof:placetype":"venue"
},
  "geometry": {"coordinates":[-82.573205,29.855023],"type":"Point"}
}