{
  "type": "Feature",
  "properties": {
    "addr:full":"4007 San Bernado Dr Jacksonville FL 32217",
    "addr:housenumber":"4007",
    "addr:postcode":"32217",
    "addr:street":"San Bernado Dr",
    "iso:country":"US",
    "sg:address":"4007 San Bernado Dr",
    "sg:city":"Jacksonville",
    "sg:classifiers":[
        {
            "category":"Retail",
            "subcategory":"Repair Shop",
            "type":"Services"
        }
    ],
    "sg:phone":"+1 904 636 0790",
    "sg:postcode":"32217",
    "sg:province":"FL",
    "sg:tags":[
        "gas",
        "equipment",
        "electrical"
    ],
    "wof:name":"Gas Appliance Specialists Inc",
    "wof:placetype":"venue"
},
  "geometry": {"coordinates":[-81.61062200000001,30.225015],"type":"Point"}
}