{
  "type": "Feature",
  "properties": {
    "iso:country":"US",
    "sg:address":"21360 Race Horse Ln",
    "sg:city":"Brooksville",
    "sg:classifiers":[
        {
            "category":"Real Estate",
            "subcategory":"Surveying",
            "type":"Services"
        }
    ],
    "sg:phone":"+1 352 848 1188",
    "sg:postcode":"34604",
    "sg:province":"FL",
    "wof:name":"Universal Field Services Inc",
    "wof:placetype":"venue"
},
  "geometry": {"coordinates":[-82.377043,28.484618],"type":"Point"}
}