{
  "type": "Feature",
  "properties": {
    "iso:country":"US",
    "sg:address":"6869 Phillips Parkway Dr S",
    "sg:city":"Jacksonville",
    "sg:classifiers":[
        {
            "category":"Professional",
            "subcategory":"Management & Consulting",
            "type":"Services"
        }
    ],
    "sg:phone":"+1 904 997 0044",
    "sg:postcode":"32256",
    "sg:province":"FL",
    "sg:tags":[
        "lake"
    ],
    "sg:website":"http://www.charlesaquatics.com",
    "wof:name":"Charles Aquatics Inc",
    "wof:placetype":"venue"
},
  "geometry": {"coordinates":[-81.53654299999999,30.166405],"type":"Point"}
}