{
  "type": "Feature",
  "properties": {
    "iso:country":"US",
    "sg:address":"6701 SW 116th Ct",
    "sg:city":"Miami",
    "sg:classifiers":[
        {
            "category":"Professional",
            "type":"Services"
        }
    ],
    "sg:phone":"+1 305 227 6304",
    "sg:postcode":"33173",
    "sg:province":"FL",
    "sg:tags":[
        "establishment"
    ],
    "wof:name":"Family Rescue Foundation",
    "wof:placetype":"venue"
},
  "geometry": {"coordinates":[-80.38144200000001,25.705994],"type":"Point"}
}