{
  "type": "Feature",
  "properties": {
    "iso:country":"US",
    "sg:address":"1794 Club Ct",
    "sg:city":"Orlando",
    "sg:classifiers":[
        {
            "category":"Building & Trades",
            "subcategory":"Construction",
            "type":"Services"
        }
    ],
    "sg:phone":"+1 407 468 0347",
    "sg:postcode":"32807",
    "sg:province":"FL",
    "sg:tags":[
        "masonry",
        "contractor"
    ],
    "wof:name":"Baker Masonry",
    "wof:placetype":"venue"
},
  "geometry": {"coordinates":[-81.3139,28.570363],"type":"Point"}
}