{
  "type": "Feature",
  "properties": {
    "iso:country":"US",
    "sg:address":"1302 Clements Rd",
    "sg:city":"Jacksonville",
    "sg:classifiers":[
        {
            "category":"Recreation",
            "subcategory":"Campground",
            "type":"Entertainment"
        }
    ],
    "sg:phone":"+1 904 891 2397",
    "sg:postcode":"32211",
    "sg:province":"FL",
    "sg:tags":[
        "recreational",
        "park",
        "vehicle"
    ],
    "wof:name":"Elizabeth S Pettigrew",
    "wof:placetype":"venue"
},
  "geometry": {"coordinates":[-81.56671799999999,30.33407],"type":"Point"}
}