{
  "type": "Feature",
  "properties": {
    "addr:full":"11 Island Ave E Miami Beach FL 33139",
    "addr:housenumber":"11",
    "addr:postcode":"33139",
    "addr:street":"Island Ave E",
    "iso:country":"US",
    "sg:address":"11 Island Ave E",
    "sg:city":"Miami Beach",
    "sg:classifiers":[
        {
            "category":"Banks & Credit Unions",
            "subcategory":"Financial Services",
            "type":"Services"
        }
    ],
    "sg:phone":"+1 305 538 7565",
    "sg:postcode":"33139",
    "sg:province":"FL",
    "sg:tags":[
        "trust",
        "management"
    ],
    "wof:name":"Dorothy S Oren Trust",
    "wof:placetype":"venue"
},
  "geometry": {"coordinates":[-80.147012,25.790758],"type":"Point"}
}