{
  "type": "Feature",
  "properties": {
    "iso:country":"US",
    "sg:address":"941 4th St",
    "sg:city":"Miami Beach",
    "sg:classifiers":[
        {
            "category":"Personal",
            "subcategory":"Beauty Salon",
            "type":"Services"
        }
    ],
    "sg:phone":"+1 305 868 2264",
    "sg:postcode":"33139",
    "sg:province":"FL",
    "sg:tags":[
        "hair"
    ],
    "sg:website":"www.camisalon.com",
    "wof:name":"Cami Salon",
    "wof:placetype":"venue"
},
  "geometry": {"coordinates":[-80.13810700000001,25.773697],"type":"Point"}
}