{
  "type": "Feature",
  "properties": {
    "iso:country":"US",
    "sg:address":"705 Pondella Rd",
    "sg:city":"Fort Myers",
    "sg:classifiers":[
        {
            "category":"Shopping",
            "subcategory":"Bicycles & Sporting Goods",
            "type":"Retail Goods"
        }
    ],
    "sg:phone":"+1 239 995 3616",
    "sg:postcode":"33903",
    "sg:province":"FL",
    "sg:tags":[
        "gun",
        "gunsmith"
    ],
    "wof:name":"Jack's Gun Sales",
    "wof:placetype":"venue"
},
  "geometry": {"coordinates":[-81.906976,26.667188],"type":"Point"}
}