{
  "type": "Feature",
  "properties": {
    "iso:country":"US",
    "sg:address":"102 Commercial Center Dr",
    "sg:city":"Ruskin",
    "sg:classifiers":[
        {
            "category":"Restaurant",
            "type":"Food & Drink"
        }
    ],
    "sg:menulink":"http://www.allmenus.com/fl/ruskin/246529-bob-evans-restaurants/menu/",
    "sg:phone":"+1 813 634 9940",
    "sg:postcode":"33573",
    "sg:province":"FL",
    "sg:tags":[
        "american"
    ],
    "wof:name":"Bob Evans Restaurants",
    "wof:placetype":"venue"
},
  "geometry": {"coordinates":[-82.377803,27.710807],"type":"Point"}
}