{
  "type": "Feature",
  "properties": {
    "addr:full":"1100 Kingsford Cir Mulberry FL 33860",
    "addr:housenumber":"1100",
    "addr:postcode":"33860",
    "addr:street":"Kingsford Cir",
    "iso:country":"US",
    "sg:address":"1100 Kingsford Cir",
    "sg:city":"Mulberry",
    "sg:classifiers":[
        {
            "category":"Retail",
            "subcategory":"Repair Shop",
            "type":"Services"
        }
    ],
    "sg:phone":"+1 863 425 4577",
    "sg:postcode":"33860",
    "sg:province":"FL",
    "sg:tags":[
        "electric",
        "motor"
    ],
    "wof:name":"Street Electric Corp",
    "wof:placetype":"venue"
},
  "geometry": {"coordinates":[-81.971346,27.886583],"type":"Point"}
}