{
  "type": "Feature",
  "properties": {
    "iso:country":"US",
    "sg:address":"173 W Hillsboro St",
    "sg:city":"Lake City",
    "sg:classifiers":[
        {
            "category":"Banks & Credit Unions",
            "subcategory":"Financial Services",
            "type":"Services"
        }
    ],
    "sg:phone":"+1 386 752 5646",
    "sg:postcode":"32055",
    "sg:province":"FL",
    "sg:tags":[
        "company",
        "holding"
    ],
    "wof:name":"First Columbia Bancorp Inc",
    "wof:placetype":"venue"
},
  "geometry": {"coordinates":[-82.638177,30.192785],"type":"Point"}
}