{
  "type": "Feature",
  "properties": {
    "addr:full":"4015 N Armenia Ave Tampa FL 33607",
    "addr:housenumber":"4015",
    "addr:postcode":"33607",
    "addr:street":"N Armenia Ave",
    "iso:country":"US",
    "sg:address":"4015 N Armenia Ave",
    "sg:city":"Tampa",
    "sg:classifiers":[
        {
            "category":"Health Services",
            "subcategory":"Chiropractor",
            "type":"Services"
        }
    ],
    "sg:phone":"+1 813 873 2003",
    "sg:postcode":"33607",
    "sg:province":"FL",
    "sg:website":"www.axischiropracticandrehab.net",
    "wof:name":"Axis Chiropractic & Rehab Ctr",
    "wof:placetype":"venue"
},
  "geometry": {"coordinates":[-82.484729,27.974342],"type":"Point"}
}