{
  "type": "Feature",
  "properties": {
    "iso:country":"US",
    "sg:address":"2976 Cleveland Ave",
    "sg:city":"Fort Myers",
    "sg:classifiers":[
        {
            "category":"Building & Trades",
            "subcategory":"Landscaping Services",
            "type":"Services"
        }
    ],
    "sg:phone":"+1 239 332 4423",
    "sg:postcode":"33901",
    "sg:province":"FL",
    "sg:tags":[
        "tree"
    ],
    "wof:name":"Fun Three",
    "wof:placetype":"venue"
},
  "geometry": {"coordinates":[-81.87235699999999,26.623725],"type":"Point"}
}