{
  "type": "Feature",
  "properties": {
    "addr:full":"251 N Coconut Ln Miami Beach FL 33139",
    "addr:housenumber":"251",
    "addr:postcode":"33139",
    "addr:street":"N Coconut Ln",
    "iso:country":"US",
    "sg:address":"251 N Coconut Ln",
    "sg:city":"Miami Beach",
    "sg:classifiers":[
        {
            "category":"Real Estate",
            "subcategory":"Developer",
            "type":"Services"
        }
    ],
    "sg:phone":"+1 305 532 5184",
    "sg:postcode":"33139",
    "sg:province":"FL",
    "wof:name":"Bob Hummer Inc",
    "wof:placetype":"venue"
},
  "geometry": {"coordinates":[-80.16546,25.781825],"type":"Point"}
}