{
  "type": "Feature",
  "properties": {
    "iso:country":"US",
    "sg:address":"655 96th St",
    "sg:city":"Surfside",
    "sg:classifiers":[
        {
            "category":"Professional",
            "subcategory":"Business Services",
            "type":"Services"
        },
        {
            "category":"Government",
            "subcategory":"Post Office",
            "type":"Public Place"
        }
    ],
    "sg:phone":"+1 800 275 8777",
    "sg:postcode":"33154",
    "sg:province":"FL",
    "sg:tags":[
        "mail",
        "shipping"
    ],
    "sg:website":"http://www.usps.com",
    "wof:name":"USPS - United States Post Office - CPU Bal Harbour",
    "wof:placetype":"venue"
},
  "geometry": {"coordinates":[-80.126679,25.886973],"type":"Point"}
}