{
  "type": "Feature",
  "properties": {
    "iso:country":"US",
    "sg:address":"6550 Bayshore Rd",
    "sg:city":"Fort Myers",
    "sg:classifiers":[
        {
            "category":"Autos & Motor Vehicles",
            "subcategory":"Automobile Sales",
            "type":"Retail Goods"
        }
    ],
    "sg:phone":"+1 239 543 8500",
    "sg:postcode":"33917",
    "sg:province":"FL",
    "sg:tags":[
        "car",
        "dealer"
    ],
    "wof:name":"Trade Dan Preown Car",
    "wof:placetype":"venue"
},
  "geometry": {"coordinates":[-81.846649,26.702423],"type":"Point"}
}