{
  "type": "Feature",
  "properties": {
    "addr:full":"1210 Malabar Rd Malabar FL 32950",
    "addr:housenumber":"1210",
    "addr:postcode":"32950",
    "addr:street":"Malabar Rd",
    "iso:country":"US",
    "sg:address":"1210 Malabar Rd",
    "sg:city":"Malabar",
    "sg:classifiers":[
        {
            "category":"Food & Beverages",
            "subcategory":"Groceries & Convenience Stores",
            "type":"Retail Goods"
        }
    ],
    "sg:phone":"+1 321 723 9677",
    "sg:postcode":"32950",
    "sg:province":"FL",
    "sg:tags":[
        "shop",
        "sandwich"
    ],
    "wof:name":"Mash Hoagies Subs & Salads Unit 102",
    "wof:placetype":"venue"
},
  "geometry": {"coordinates":[-80.597407,27.998138],"type":"Point"}
}