{
  "type": "Feature",
  "properties": {
    "iso:country":"US",
    "sg:address":"121 Flagship Dr",
    "sg:city":"Lutz",
    "sg:classifiers":[
        {
            "category":"Professional",
            "subcategory":"Research",
            "type":"Services"
        }
    ],
    "sg:phone":"+1 813 597 0400",
    "sg:postcode":"33549",
    "sg:province":"FL",
    "wof:name":"Information Research",
    "wof:placetype":"venue"
},
  "geometry": {"coordinates":[-82.462768,28.134849],"type":"Point"}
}