{
  "type": "Feature",
  "properties": {
    "addr:full":"2754 Rosselle St Jacksonville FL 32205",
    "addr:housenumber":"2754",
    "addr:postcode":"32205",
    "addr:street":"Rosselle St",
    "iso:country":"US",
    "sg:address":"2754 Rosselle St",
    "sg:city":"Jacksonville",
    "sg:classifiers":[
        {
            "category":"Professional",
            "subcategory":"Business Services",
            "type":"Services"
        }
    ],
    "sg:phone":"+1 904 389 0264",
    "sg:postcode":"32205",
    "sg:province":"FL",
    "wof:name":"SGS North America Inc",
    "wof:placetype":"venue"
},
  "geometry": {"coordinates":[-81.698764,30.319133],"type":"Point"}
}