{
  "type": "Feature",
  "properties": {
    "iso:country":"US",
    "sg:address":"555 W Granada Blvd",
    "sg:city":"Ormond Beach",
    "sg:classifiers":[
        {
            "category":"Health Services",
            "subcategory":"Clinic",
            "type":"Services"
        }
    ],
    "sg:phone":"+1 386 672 3381",
    "sg:postcode":"32174",
    "sg:province":"FL",
    "sg:tags":[
        "home"
    ],
    "sg:website":"www.seniorhomecare.net",
    "wof:name":"Senior Home Care Inc",
    "wof:placetype":"venue"
},
  "geometry": {"coordinates":[-81.071224,29.279735],"type":"Point"}
}