{
  "type": "Feature",
  "properties": {
    "iso:country":"US",
    "sg:address":"10899 SW 72nd St",
    "sg:city":"Miami",
    "sg:classifiers":[
        {
            "category":"Professional",
            "type":"Services"
        }
    ],
    "sg:phone":"+1 305 595 3596",
    "sg:postcode":"33173",
    "sg:province":"FL",
    "wof:name":"Clearguard",
    "wof:placetype":"venue"
},
  "geometry": {"coordinates":[-80.370053,25.701035],"type":"Point"}
}