{
  "type": "Feature",
  "properties": {
    "addr:full":"819 Cedarcrest Ct Sarasota FL 34232",
    "addr:housenumber":"819",
    "addr:postcode":"34232",
    "addr:street":"Cedarcrest Ct",
    "iso:country":"US",
    "sg:address":"819 Cedarcrest Ct",
    "sg:city":"Sarasota",
    "sg:classifiers":[
        {
            "category":"Building & Trades",
            "subcategory":"Construction",
            "type":"Services"
        }
    ],
    "sg:phone":"+1 941 371 7032",
    "sg:postcode":"34232",
    "sg:province":"FL",
    "sg:tags":[
        "contractor"
    ],
    "wof:name":"Christopher E Woodson Sr",
    "wof:placetype":"venue"
},
  "geometry": {"coordinates":[-82.49141899999999,27.329372],"type":"Point"}
}