{
  "type": "Feature",
  "properties": {
    "addr:full":"240 SE 30th St Cape Coral FL 33904",
    "addr:housenumber":"240",
    "addr:postcode":"33904",
    "addr:street":"Se 30Th St",
    "iso:country":"US",
    "sg:address":"240 SE 30th St",
    "sg:city":"Cape Coral",
    "sg:classifiers":[
        {
            "category":"Restaurant",
            "type":"Food & Drink"
        }
    ],
    "sg:phone":"+1 239 574 4913",
    "sg:postcode":"33904",
    "sg:province":"FL",
    "sg:tags":[
        "eating"
    ],
    "wof:name":"Lunch Ala Cart",
    "wof:placetype":"venue"
},
  "geometry": {"coordinates":[-81.970732,26.596468],"type":"Point"}
}