{
  "type": "Feature",
  "properties": {
    "iso:country":"US",
    "sg:address":"6710 Wiley Rd",
    "sg:city":"Jacksonville",
    "sg:classifiers":[
        {
            "category":"Social Services",
            "type":"Services"
        }
    ],
    "sg:phone":"+1 904 783 6589",
    "sg:postcode":"32210",
    "sg:province":"FL",
    "sg:tags":[
        "executive"
    ],
    "wof:name":"Community & Senior Services",
    "wof:placetype":"venue"
},
  "geometry": {"coordinates":[-81.75794399999999,30.279242],"type":"Point"}
}