{
  "type": "Feature",
  "properties": {
    "iso:country":"US",
    "sg:address":"5137 Wolf Rd",
    "sg:city":"Brooksville",
    "sg:classifiers":[
        {
            "category":"Building & Trades",
            "subcategory":"Landscaping Services",
            "type":"Services"
        }
    ],
    "sg:phone":"+1 352 799 1596",
    "sg:postcode":"34604",
    "sg:province":"FL",
    "wof:name":"Williamson Landscape Services",
    "wof:placetype":"venue"
},
  "geometry": {"coordinates":[-82.442612,28.506606],"type":"Point"}
}