{
  "type": "Feature",
  "properties": {
    "addr:full":"10289 Ulmerton Rd Largo FL 33771",
    "addr:housenumber":"10289",
    "addr:postcode":"33771",
    "addr:street":"Ulmerton Rd",
    "iso:country":"US",
    "sg:address":"10289 Ulmerton Rd",
    "sg:city":"Largo",
    "sg:classifiers":[
        {
            "category":"Shopping",
            "type":"Retail Goods"
        }
    ],
    "sg:phone":"+1 727 586 6203",
    "sg:postcode":"33771",
    "sg:province":"FL",
    "sg:tags":[
        "telephone",
        "cellular"
    ],
    "wof:name":"Verizon Wireless",
    "wof:placetype":"venue"
},
  "geometry": {"coordinates":[-82.77924899999999,27.894568],"type":"Point"}
}