{
  "type": "Feature",
  "properties": {
    "iso:country":"US",
    "sg:address":"2501 Coral Springs Dr",
    "sg:city":"Pompano Beach",
    "sg:classifiers":[
        {
            "category":"Wholesale",
            "subcategory":"Sporting Goods",
            "type":"Manufacturing & Wholesale Goods"
        }
    ],
    "sg:phone":"+1 954 345 2200",
    "sg:postcode":"33065",
    "sg:province":"FL",
    "wof:name":"Mullins Park",
    "wof:placetype":"venue"
},
  "geometry": {"coordinates":[-80.265997,26.259086],"type":"Point"}
}