{
  "type": "Feature",
  "properties": {
    "addr:full":"1257 3rd St S Jacksonville Bch FL 32250",
    "addr:housenumber":"1257",
    "addr:postcode":"32250",
    "addr:street":"3Rd St S",
    "iso:country":"US",
    "sg:address":"1257 3rd St S",
    "sg:city":"Jacksonville Bch",
    "sg:classifiers":[
        {
            "category":"Personal",
            "subcategory":"Beauty Salon",
            "type":"Services"
        }
    ],
    "sg:phone":"+1 904 241 3151",
    "sg:postcode":"32250",
    "sg:province":"FL",
    "sg:tags":[
        "shop"
    ],
    "wof:name":"Frangipani Hair Studio Inc",
    "wof:placetype":"venue"
},
  "geometry": {"coordinates":[-81.389325,30.27662],"type":"Point"}
}