{
  "type": "Feature",
  "properties": {
    "iso:country":"US",
    "sg:address":"932 Mason Ave",
    "sg:city":"Daytona Beach",
    "sg:classifiers":[
        {
            "category":"Retail",
            "subcategory":"Veterinary Services",
            "type":"Services"
        }
    ],
    "sg:phone":"+1 386 255 1407",
    "sg:postcode":"32117",
    "sg:province":"FL",
    "sg:tags":[
        "veterinarian"
    ],
    "wof:name":"Driftwood Animal Hospital",
    "wof:placetype":"venue"
},
  "geometry": {"coordinates":[-81.047275,29.219739],"type":"Point"}
}