{
  "type": "Feature",
  "properties": {
    "iso:country":"US",
    "sg:address":"24751 SW 144th Ave",
    "sg:city":"Homestead",
    "sg:classifiers":[
        {
            "category":"Home & Garden",
            "subcategory":"Garden Supply",
            "type":"Retail Goods"
        }
    ],
    "sg:phone":"+1 305 258 0639",
    "sg:postcode":"33032",
    "sg:province":"FL",
    "sg:tags":[
        "center"
    ],
    "wof:name":"Morningside Gardens",
    "wof:placetype":"venue"
},
  "geometry": {"coordinates":[-80.423378,25.537113],"type":"Point"}
}