{
  "type": "Feature",
  "properties": {
    "addr:full":"10521 Mahogany Key Cir Miami FL 33196",
    "addr:housenumber":"10521",
    "addr:postcode":"33196",
    "addr:street":"Mahogany Key Cir",
    "iso:country":"US",
    "sg:address":"10521 Mahogany Key Cir",
    "sg:city":"Miami",
    "sg:classifiers":[
        {
            "category":"Banks & Credit Unions",
            "subcategory":"Financial Services",
            "type":"Services"
        }
    ],
    "sg:phone":"+1 305 408 2881",
    "sg:postcode":"33196",
    "sg:province":"FL",
    "sg:tags":[
        "trust",
        "investment",
        "real estate"
    ],
    "wof:name":"Ewd Investment Corp",
    "wof:placetype":"venue"
},
  "geometry": {"coordinates":[-80.436438,25.668396],"type":"Point"}
}