{
  "type": "Feature",
  "properties": {
    "iso:country":"US",
    "sg:address":"5850 Deacon Rd",
    "sg:city":"Sarasota",
    "sg:classifiers":[
        {
            "category":"Home & Garden",
            "subcategory":"Carpets & Floor Coverings",
            "type":"Retail Goods"
        }
    ],
    "sg:phone":"+1 941 922 5541",
    "sg:postcode":"34238",
    "sg:province":"FL",
    "sg:tags":[
        "material"
    ],
    "wof:name":"Pinnacle Buildings Prods Inc",
    "wof:placetype":"venue"
},
  "geometry": {"coordinates":[-82.47776399999999,27.266013],"type":"Point"}
}