{
  "type": "Feature",
  "properties": {
    "addr:full":"103 Tangelo Ct Maitland FL 32751",
    "addr:housenumber":"103",
    "addr:postcode":"32751",
    "addr:street":"Tangelo Ct",
    "iso:country":"US",
    "sg:address":"103 Tangelo Ct",
    "sg:city":"Maitland",
    "sg:classifiers":[
        {
            "category":"Real Estate",
            "subcategory":"Real Estate Services",
            "type":"Services"
        },
        {
            "category":"Real Estate",
            "subcategory":"Real Estate Agent",
            "type":"Services"
        }
    ],
    "sg:phone":"+1 407 478 4777",
    "sg:postcode":"32751",
    "sg:province":"FL",
    "sg:tags":[
        "buyer",
        "broker"
    ],
    "wof:name":"Fl Home Realty Professional Group",
    "wof:placetype":"venue"
},
  "geometry": {"coordinates":[-81.351821,28.625341],"type":"Point"}
}