{
  "type": "Feature",
  "properties": {
    "iso:country":"US",
    "sg:address":"2345 Friendly Rd",
    "sg:city":"Fernandina Beach",
    "sg:classifiers":[
        {
            "category":"Freight",
            "type":"Transportation"
        }
    ],
    "sg:phone":"+1 904 261 2733",
    "sg:postcode":"32034",
    "sg:province":"FL",
    "sg:tags":[
        "broker",
        "trucking"
    ],
    "wof:name":"Aim Integrated",
    "wof:placetype":"venue"
},
  "geometry": {"coordinates":[-81.46712599999999,30.633545],"type":"Point"}
}