{
  "type": "Feature",
  "properties": {
    "iso:country":"US",
    "sg:address":"14411 Dixie Hwy",
    "sg:city":"Miami",
    "sg:classifiers":[
        {
            "category":"Health Services",
            "subcategory":"Doctor",
            "type":"Services"
        }
    ],
    "sg:phone":"+1 786 573 4777",
    "sg:postcode":"33176",
    "sg:province":"FL",
    "sg:tags":[
        "clinic"
    ],
    "wof:name":"Medicine Man Pain Management",
    "wof:placetype":"venue"
},
  "geometry": {"coordinates":[-80.339253,25.632673],"type":"Point"}
}