{
  "type": "Feature",
  "properties": {
    "addr:full":"3714 S Dixie Hwy West Palm Beach FL 33405",
    "addr:housenumber":"3714",
    "addr:postcode":"33405",
    "addr:street":"S Dixie Hwy",
    "iso:country":"US",
    "sg:address":"3714 S Dixie Hwy",
    "sg:city":"West Palm Beach",
    "sg:classifiers":[
        {
            "category":"Shopping",
            "subcategory":"Used Merchandise",
            "type":"Retail Goods"
        }
    ],
    "sg:phone":"+1 561 655 0899",
    "sg:postcode":"33405",
    "sg:province":"FL",
    "sg:tags":[
        "antique"
    ],
    "wof:name":"J & M Antiques",
    "wof:placetype":"venue"
},
  "geometry": {"coordinates":[-80.05470099999999,26.67711],"type":"Point"}
}