{
  "type": "Feature",
  "properties": {
    "iso:country":"US",
    "sg:address":"9533 NW 52nd Ct",
    "sg:city":"Fort Lauderdale",
    "sg:classifiers":[
        {
            "category":"Manufacturing",
            "subcategory":"Signs",
            "type":"Manufacturing & Wholesale Goods"
        }
    ],
    "sg:phone":"+1 954 742 0018",
    "sg:postcode":"33351",
    "sg:province":"FL",
    "sg:tags":[
        "specialty",
        "mfg"
    ],
    "wof:name":"Specilties By Gallant Graphics",
    "wof:placetype":"venue"
},
  "geometry": {"coordinates":[-80.279258,26.188069],"type":"Point"}
}