{
  "type": "Feature",
  "properties": {
    "addr:full":"1504 N Broadwalk Hollywood FL 33019",
    "addr:housenumber":"1504",
    "addr:postcode":"33019",
    "addr:street":"N Broadwalk",
    "iso:country":"US",
    "sg:address":"1504 N Broadwalk",
    "sg:city":"Hollywood",
    "sg:classifiers":[
        {
            "category":"Manufacturing",
            "subcategory":"Food",
            "type":"Manufacturing & Wholesale Goods"
        },
        {
            "category":"Restaurant",
            "type":"Food & Drink"
        },
        {
            "category":"Ice Cream",
            "type":"Food & Drink"
        }
    ],
    "sg:phone":"+1 954 926 1112",
    "sg:postcode":"33019",
    "sg:province":"FL",
    "sg:tags":[
        "frozen",
        "dessert",
        "desserts-manufacturers",
        "distributor"
    ],
    "wof:name":"Boardwalk Ice Cream",
    "wof:placetype":"venue"
},
  "geometry": {"coordinates":[-80.11511900000001,26.021294],"type":"Point"}
}