{
  "type": "Feature",
  "properties": {
    "addr:full":"11797 S Old Jones Rd Floral City FL 34436",
    "addr:housenumber":"11797",
    "addr:postcode":"34436",
    "addr:street":"S Old Jones Rd",
    "iso:country":"US",
    "sg:address":"11797 S Old Jones Rd",
    "sg:city":"Floral City",
    "sg:classifiers":[
        {
            "category":"Building & Trades",
            "subcategory":"Construction",
            "type":"Services"
        }
    ],
    "sg:phone":"+1 352 860 1335",
    "sg:postcode":"34436",
    "sg:province":"FL",
    "sg:tags":[
        "house",
        "improvement",
        "home"
    ],
    "wof:name":"Rick Knechtels Home Repair",
    "wof:placetype":"venue"
},
  "geometry": {"coordinates":[-82.37884,28.691005],"type":"Point"}
}