{
  "type": "Feature",
  "properties": {
    "addr:full":"546 E Call St Tallahassee FL 32301",
    "addr:housenumber":"546",
    "addr:postcode":"32301",
    "addr:street":"E Call St",
    "iso:country":"US",
    "sg:address":"546 E Call St",
    "sg:city":"Tallahassee",
    "sg:classifiers":[
        {
            "category":"Professional",
            "subcategory":"Management & Consulting",
            "type":"Services"
        }
    ],
    "sg:phone":"+1 850 222 4634",
    "sg:postcode":"32301",
    "sg:province":"FL",
    "sg:tags":[
        "consultant",
        "business"
    ],
    "sg:website":"www.lampl-herbert.com",
    "wof:name":"Lampl/Herbert Consultants Inc",
    "wof:placetype":"venue"
},
  "geometry": {"coordinates":[-84.274767,30.443669],"type":"Point"}
}