{
  "type": "Feature",
  "properties": {
    "iso:country":"US",
    "sg:address":"1570 NE 191st St",
    "sg:city":"Miami",
    "sg:classifiers":[
        {
            "category":"Professional",
            "subcategory":"Business Services",
            "type":"Services"
        },
        {
            "category":"Government",
            "subcategory":"Post Office",
            "type":"Public Place"
        }
    ],
    "sg:phone":"+1 305 894 6804",
    "sg:postcode":"33179",
    "sg:province":"FL",
    "sg:tags":[
        "delivery",
        "messenger",
        "courier"
    ],
    "wof:name":"Expedite Messenger Services, Inc.",
    "wof:placetype":"venue"
},
  "geometry": {"coordinates":[-80.169183,25.951324],"type":"Point"}
}