{
  "type": "Feature",
  "properties": {
    "addr:full":"1747 Evans Rd Melbourne FL 32904",
    "addr:housenumber":"1747",
    "addr:postcode":"32904",
    "addr:street":"Evans Rd",
    "iso:country":"US",
    "sg:address":"1747 Evans Rd",
    "sg:city":"Melbourne",
    "sg:classifiers":[
        {
            "category":"Health Services",
            "subcategory":"Chiropractor",
            "type":"Services"
        }
    ],
    "sg:phone":"+1 321 951 9222",
    "sg:postcode":"32904",
    "sg:province":"FL",
    "sg:tags":[
        "chiropractic"
    ],
    "wof:name":"Stelter Thomas J Chiropractor",
    "wof:placetype":"venue"
},
  "geometry": {"coordinates":[-80.654421,28.083087],"type":"Point"}
}