{
  "type": "Feature",
  "properties": {
    "addr:full":"969 NE 45th St Fort Lauderdale FL 33334",
    "addr:housenumber":"969",
    "addr:postcode":"33334",
    "addr:street":"Ne 45Th St",
    "iso:country":"US",
    "sg:address":"969 NE 45th St",
    "sg:city":"Fort Lauderdale",
    "sg:classifiers":[
        {
            "category":"Shopping",
            "subcategory":"Used Merchandise",
            "type":"Retail Goods"
        }
    ],
    "sg:phone":"+1 954 958 9093",
    "sg:postcode":"33334",
    "sg:province":"FL",
    "wof:name":"Sterling Antiques",
    "wof:placetype":"venue"
},
  "geometry": {"coordinates":[-80.134226,26.183245],"type":"Point"}
}