{
  "type": "Feature",
  "properties": {
    "addr:full":"10480 NE Jacksonville Rd Anthony FL 32617",
    "addr:housenumber":"10480",
    "addr:postcode":"32617",
    "addr:street":"Ne Jacksonville Rd",
    "iso:country":"US",
    "sg:address":"10480 NE Jacksonville Rd",
    "sg:city":"Anthony",
    "sg:classifiers":[
        {
            "category":"Shopping",
            "subcategory":"Clothing, Apparel, & Fashions",
            "type":"Retail Goods"
        }
    ],
    "sg:phone":"+1 352 402 9808",
    "sg:postcode":"32617",
    "sg:province":"FL",
    "wof:name":"Bobby Sock Farm",
    "wof:placetype":"venue"
},
  "geometry": {"coordinates":[-82.11515900000001,29.306393],"type":"Point"}
}