{
  "type": "Feature",
  "properties": {
    "addr:full":"1323 W Fletcher Ave Tampa FL 33612",
    "addr:housenumber":"1323",
    "addr:postcode":"33612",
    "addr:street":"W Fletcher Ave",
    "iso:country":"US",
    "sg:address":"1323 W Fletcher Ave",
    "sg:city":"Tampa",
    "sg:classifiers":[
        {
            "category":"Real Estate",
            "subcategory":"Real Estate Agent",
            "type":"Services"
        }
    ],
    "sg:phone":"+1 813 265 1815",
    "sg:postcode":"33612",
    "sg:province":"FL",
    "wof:name":"Larson Williams Real Est LLC",
    "wof:placetype":"venue"
},
  "geometry": {"coordinates":[-82.474009,28.069483],"type":"Point"}
}