{
  "type": "Feature",
  "properties": {
    "iso:country":"US",
    "sg:address":"2450 Poinciana Ct",
    "sg:city":"Fort Lauderdale",
    "sg:classifiers":[
        {
            "category":"Professional",
            "subcategory":"Lawyer & Legal Services",
            "type":"Services"
        }
    ],
    "sg:phone":"+1 954 468 2464",
    "sg:postcode":"33327",
    "sg:province":"FL",
    "wof:name":"Bruce March Esq",
    "wof:placetype":"venue"
},
  "geometry": {"coordinates":[-80.40588200000001,26.103586],"type":"Point"}
}