{
  "type": "Feature",
  "properties": {
    "addr:full":"105 Wildwood Ave Edgewater FL 32132",
    "addr:housenumber":"105",
    "addr:postcode":"32132",
    "addr:street":"Wildwood Ave",
    "iso:country":"US",
    "sg:address":"105 Wildwood Ave",
    "sg:city":"Edgewater",
    "sg:classifiers":[
        {
            "category":"Personal",
            "subcategory":"Beauty Salon",
            "type":"Services"
        }
    ],
    "sg:phone":"+1 386 424 6118",
    "sg:postcode":"32132",
    "sg:province":"FL",
    "wof:name":"Reflections Beauty Salon",
    "wof:placetype":"venue"
},
  "geometry": {"coordinates":[-80.91220800000001,28.9996],"type":"Point"}
}