{
  "type": "Feature",
  "properties": {
    "addr:full":"1855 University Pkwy Sarasota FL 34243",
    "addr:housenumber":"1855",
    "addr:postcode":"34243",
    "addr:street":"University Pkwy",
    "iso:country":"US",
    "sg:address":"1855 University Pkwy",
    "sg:city":"Sarasota",
    "sg:classifiers":[
        {
            "category":"Professional",
            "subcategory":"Art Services",
            "type":"Services"
        }
    ],
    "sg:phone":"+1 941 359 9155",
    "sg:postcode":"34243",
    "sg:province":"FL",
    "sg:tags":[
        "photographer"
    ],
    "wof:name":"Lunardi Photography",
    "wof:placetype":"venue"
},
  "geometry": {"coordinates":[-82.53190600000001,27.388889],"type":"Point"}
}