{
  "type": "Feature",
  "properties": {
    "iso:country":"US",
    "sg:address":"1425 Piedmont Dr",
    "sg:city":"Tallahassee",
    "sg:classifiers":[
        {
            "category":"Organizations",
            "subcategory":"Professional Association",
            "type":"Services"
        }
    ],
    "sg:phone":"+1 850 681 2003",
    "sg:postcode":"32308",
    "sg:province":"FL",
    "sg:tags":[
        "business"
    ],
    "wof:name":"Florida Auto Joint Undwrt As",
    "wof:placetype":"venue"
},
  "geometry": {"coordinates":[-84.255663,30.495283],"type":"Point"}
}