{
  "type": "Feature",
  "properties": {
    "addr:full":"7029 Commonwealth Ave Jacksonville FL 32220",
    "addr:housenumber":"7029",
    "addr:postcode":"32220",
    "addr:street":"Commonwealth Ave",
    "iso:country":"US",
    "sg:address":"7029 Commonwealth Ave",
    "sg:city":"Jacksonville",
    "sg:classifiers":[
        {
            "category":"Manufacturing",
            "subcategory":"Glass & Minerals",
            "type":"Manufacturing & Wholesale Goods"
        },
        {
            "category":"Retail",
            "subcategory":"Auto Repair",
            "type":"Services"
        }
    ],
    "sg:phone":"+1 904 693 4114",
    "sg:postcode":"32220",
    "sg:province":"FL",
    "sg:tags":[
        "plate",
        "shape",
        "glass-wholesale",
        "window",
        "special",
        "circle",
        "windshield",
        "glass-auto",
        "manufacturer"
    ],
    "sg:website":"http://www.guardianautoglass.com",
    "wof:name":"Guardian Auto Glass",
    "wof:placetype":"venue"
},
  "geometry": {"coordinates":[-81.762894,30.335791],"type":"Point"}
}