{
  "type": "Feature",
  "properties": {
    "iso:country":"US",
    "sg:address":"701 NW Federal Hwy",
    "sg:city":"Stuart",
    "sg:classifiers":[
        {
            "category":"Insurance",
            "subcategory":"Hazard Insurance",
            "type":"Services"
        },
        {
            "category":"Insurance",
            "subcategory":"Insurance Agent",
            "type":"Services"
        }
    ],
    "sg:phone":"+1 772 232 9371",
    "sg:postcode":"34994",
    "sg:province":"FL",
    "sg:tags":[
        "brokerage",
        "property",
        "marine",
        "casualty"
    ],
    "sg:website":"www.insuremarine.com",
    "wof:name":"Paul Lynch & Associates Inc",
    "wof:placetype":"venue"
},
  "geometry": {"coordinates":[-80.262002,27.218022],"type":"Point"}
}