{
  "type": "Feature",
  "properties": {
    "addr:full":"1400 N Killian Dr Lake Park FL 33403",
    "addr:housenumber":"1400",
    "addr:postcode":"33403",
    "addr:street":"N Killian Dr",
    "iso:country":"US",
    "sg:address":"1400 N Killian Dr",
    "sg:city":"Lake Park",
    "sg:classifiers":[
        {
            "category":"Retail",
            "subcategory":"Auto Repair",
            "type":"Services"
        }
    ],
    "sg:phone":"+1 561 844 8648",
    "sg:postcode":"33403",
    "sg:province":"FL",
    "sg:tags":[
        "repairing",
        "automobile",
        "general"
    ],
    "sg:website":"www.tenaska.com",
    "wof:name":"Medical Center Garage",
    "wof:placetype":"venue"
},
  "geometry": {"coordinates":[-80.080049,26.805621],"type":"Point"}
}