{
  "type": "Feature",
  "properties": {
    "addr:full":"6162 Cleveland Rd Jacksonville FL 32209",
    "addr:housenumber":"6162",
    "addr:postcode":"32209",
    "addr:street":"Cleveland Rd",
    "iso:country":"US",
    "sg:address":"6162 Cleveland Rd",
    "sg:city":"Jacksonville",
    "sg:classifiers":[
        {
            "category":"Personal",
            "subcategory":"Beauty Salon",
            "type":"Services"
        }
    ],
    "sg:phone":"+1 904 766 2404",
    "sg:postcode":"32209",
    "sg:province":"FL",
    "sg:tags":[
        "shop"
    ],
    "wof:name":"Natural Attraction",
    "wof:placetype":"venue"
},
  "geometry": {"coordinates":[-81.71617500000001,30.378339],"type":"Point"}
}