{
  "type": "Feature",
  "properties": {
    "iso:country":"US",
    "sg:address":"4950 S Peninsula Dr",
    "sg:city":"Daytona Beach",
    "sg:classifiers":[
        {
            "category":"Recreation",
            "type":"Entertainment"
        }
    ],
    "sg:phone":"+1 386 767 7676",
    "sg:postcode":"32127",
    "sg:province":"FL",
    "sg:tags":[
        "guide"
    ],
    "wof:name":"Critter Fleet",
    "wof:placetype":"venue"
},
  "geometry": {"coordinates":[-80.924497,29.078856],"type":"Point"}
}