{
  "type": "Feature",
  "properties": {
    "addr:full":"1738 Armistead Pl Tallahassee FL 32308",
    "addr:housenumber":"1738",
    "addr:postcode":"32308",
    "addr:street":"Armistead Pl",
    "iso:country":"US",
    "sg:address":"1738 Armistead Pl",
    "sg:city":"Tallahassee",
    "sg:classifiers":[
        {
            "category":"Wholesale",
            "subcategory":"Office Equipment",
            "type":"Manufacturing & Wholesale Goods"
        }
    ],
    "sg:phone":"+1 850 385 6131",
    "sg:postcode":"32308",
    "sg:province":"FL",
    "sg:tags":[
        "residential",
        "broker",
        "operates"
    ],
    "wof:name":"Trotman Equipment Company",
    "wof:placetype":"venue"
},
  "geometry": {"coordinates":[-84.249916,30.47315],"type":"Point"}
}