{
  "type": "Feature",
  "properties": {
    "iso:country":"US",
    "sg:address":"4060 Sheridan St",
    "sg:city":"Hollywood",
    "sg:classifiers":[
        {
            "category":"Health Services",
            "subcategory":"Doctor",
            "type":"Services"
        }
    ],
    "sg:phone":"+1 954 987 6200",
    "sg:postcode":"33021",
    "sg:province":"FL",
    "sg:tags":[
        "physician",
        "surgeon"
    ],
    "wof:name":"Sheridan Management Svc LTD",
    "wof:placetype":"venue"
},
  "geometry": {"coordinates":[-80.182276,26.032848],"type":"Point"}
}