{
  "type": "Feature",
  "properties": {
    "iso:country":"US",
    "sg:address":"450 W Cocoa Beach Cswy",
    "sg:city":"Cocoa Beach",
    "sg:classifiers":[
        {
            "category":"Manufacturing",
            "subcategory":"Petroleum Products",
            "type":"Manufacturing & Wholesale Goods"
        }
    ],
    "sg:phone":"+1 321 784 6144",
    "sg:postcode":"32931",
    "sg:province":"FL",
    "sg:tags":[
        "asphalt"
    ],
    "wof:name":"Freehill Asphalt",
    "wof:placetype":"venue"
},
  "geometry": {"coordinates":[-80.612325,28.357794],"type":"Point"}
}