{
  "type": "Feature",
  "properties": {
    "addr:full":"6535 SW 18th St Miami FL 33155",
    "addr:housenumber":"6535",
    "addr:postcode":"33155",
    "addr:street":"Sw 18Th St",
    "iso:country":"US",
    "sg:address":"6535 SW 18th St",
    "sg:city":"Miami",
    "sg:classifiers":[
        {
            "category":"Airline",
            "type":"Transportation"
        }
    ],
    "sg:phone":"+1 305 871 7100",
    "sg:postcode":"33155",
    "sg:province":"FL",
    "sg:tags":[
        "ticket",
        "agency"
    ],
    "wof:name":"G A C",
    "wof:placetype":"venue"
},
  "geometry": {"coordinates":[-80.30197099999999,25.753911],"type":"Point"}
}