{
  "type": "Feature",
  "properties": {
    "iso:country":"US",
    "sg:address":"6815 S Dixie Hwy",
    "sg:city":"West Palm Beach",
    "sg:classifiers":[
        {
            "category":"Health Services",
            "subcategory":"Doctor",
            "type":"Services"
        }
    ],
    "sg:phone":"+1 561 585 8484",
    "sg:postcode":"33405",
    "sg:province":"FL",
    "sg:tags":[
        "dentist"
    ],
    "wof:name":"Dental Associates-Palm Beaches",
    "wof:placetype":"venue"
},
  "geometry": {"coordinates":[-80.056105,26.654406],"type":"Point"}
}