{
  "type": "Feature",
  "properties": {
    "addr:full":"2114 Boles Ln Westville FL 32464",
    "addr:housenumber":"2114",
    "addr:postcode":"32464",
    "addr:street":"Boles Ln",
    "iso:country":"US",
    "sg:address":"2114 Boles Ln",
    "sg:city":"Westville",
    "sg:classifiers":[
        {
            "category":"Building & Trades",
            "subcategory":"Construction",
            "type":"Services"
        }
    ],
    "sg:phone":"+1 850 548 5436",
    "sg:postcode":"32464",
    "sg:province":"FL",
    "sg:tags":[
        "sandblasting",
        "painting",
        "contractor"
    ],
    "wof:name":"Dixie Sand Blasting & Painting",
    "wof:placetype":"venue"
},
  "geometry": {"coordinates":[-85.882881,30.832953],"type":"Point"}
}