{
  "type": "Feature",
  "properties": {
    "iso:country":"US",
    "sg:address":"5437 Hermosa St",
    "sg:city":"Orlando",
    "sg:classifiers":[
        {
            "category":"Professional",
            "subcategory":"Engineering",
            "type":"Services"
        },
        {
            "category":"Building & Trades",
            "subcategory":"Construction",
            "type":"Services"
        },
        {
            "category":"Home & Garden",
            "subcategory":"Household Appliances",
            "type":"Retail Goods"
        }
    ],
    "sg:phone":"+1 407 468 7808",
    "sg:postcode":"32807",
    "sg:province":"FL",
    "sg:tags":[
        "major",
        "system",
        "appliances-small",
        "specialty",
        "equipment",
        "heating",
        "contractor",
        "air conditioning"
    ],
    "wof:name":"English Air Inc",
    "wof:placetype":"venue"
},
  "geometry": {"coordinates":[-81.31553599999999,28.538093],"type":"Point"}
}