{
  "type": "Feature",
  "properties": {
    "iso:country":"US",
    "sg:address":"10251 SW 109th St",
    "sg:city":"Miami",
    "sg:classifiers":[
        {
            "category":"Manufacturing",
            "subcategory":"Chemicals & Compounds",
            "type":"Manufacturing & Wholesale Goods"
        }
    ],
    "sg:phone":"+1 305 595 9821",
    "sg:postcode":"33176",
    "sg:province":"FL",
    "sg:tags":[
        "preparation",
        "toilet",
        "manufacturer",
        "cosmetics-wholesale",
        "mfg"
    ],
    "wof:name":"Olga Alfonso",
    "wof:placetype":"venue"
},
  "geometry": {"coordinates":[-80.36117900000001,25.667809],"type":"Point"}
}