{
  "type": "Feature",
  "properties": {
    "iso:country":"US",
    "sg:address":"20330 NW 2nd St",
    "sg:city":"Hollywood",
    "sg:classifiers":[
        {
            "category":"Wholesale",
            "subcategory":"Machinery & Supplies",
            "type":"Manufacturing & Wholesale Goods"
        }
    ],
    "sg:phone":"+1 954 435 3312",
    "sg:postcode":"33029",
    "sg:province":"FL",
    "sg:tags":[
        "equipment"
    ],
    "wof:name":"Export Machinery Inc",
    "wof:placetype":"venue"
},
  "geometry": {"coordinates":[-80.42048699999999,26.008703],"type":"Point"}
}