{
  "type": "Feature",
  "properties": {
    "addr:full":"3211 Mahan Dr Tallahassee FL 32308",
    "addr:housenumber":"3211",
    "addr:postcode":"32308",
    "addr:street":"Mahan Dr",
    "iso:country":"US",
    "sg:address":"3211 Mahan Dr",
    "sg:city":"Tallahassee",
    "sg:classifiers":[
        {
            "category":"Food & Beverages",
            "subcategory":"Groceries & Convenience Stores",
            "type":"Retail Goods"
        }
    ],
    "sg:phone":"+1 850 877 9822",
    "sg:postcode":"32308",
    "sg:province":"FL",
    "sg:website":"www.circlek.com",
    "wof:name":"Circle K",
    "wof:placetype":"venue"
},
  "geometry": {"coordinates":[-84.222583,30.461946],"type":"Point"}
}