{
  "type": "Feature",
  "properties": {
    "iso:country":"US",
    "sg:address":"400 SW 73rd Street Rd",
    "sg:city":"Ocala",
    "sg:classifiers":[
        {
            "category":"Building & Trades",
            "subcategory":"Construction",
            "type":"Services"
        }
    ],
    "sg:phone":"+1 352 237 2632",
    "sg:postcode":"34476",
    "sg:province":"FL",
    "sg:tags":[
        "house",
        "contractor"
    ],
    "wof:name":"Hensley Builders Inc",
    "wof:placetype":"venue"
},
  "geometry": {"coordinates":[-82.138481,29.112736],"type":"Point"}
}