{
  "type": "Feature",
  "properties": {
    "addr:full":"9703 S Dixie Hwy Ste 15 Miami FL 33156",
    "addr:housenumber":"9703",
    "addr:postcode":"33156",
    "addr:street":"S Dixie Hwy Ste 15",
    "iso:country":"US",
    "sg:address":"9703 S Dixie Hwy Ste 15",
    "sg:city":"Miami",
    "sg:classifiers":[
        {
            "category":"Professional",
            "subcategory":"Lawyer & Legal Services",
            "type":"Services"
        }
    ],
    "sg:phone":"+1 305 661 0424",
    "sg:postcode":"33156",
    "sg:province":"FL",
    "wof:name":"Doscher Daniel Atty",
    "wof:placetype":"venue"
},
  "geometry": {"coordinates":[-80.316399,25.680201],"type":"Point"}
}