{
  "type": "Feature",
  "properties": {
    "iso:country":"US",
    "sg:address":"420 Palm Beach Trace Dr",
    "sg:city":"West Palm Beach",
    "sg:classifiers":[
        {
            "category":"Professional",
            "subcategory":"Credit Reporting & Collection",
            "type":"Services"
        }
    ],
    "sg:phone":"+1 561 791 9328",
    "sg:postcode":"33411",
    "sg:province":"FL",
    "sg:tags":[
        "bus",
        "school"
    ],
    "wof:name":"Transportation Department",
    "wof:placetype":"venue"
},
  "geometry": {"coordinates":[-80.227143,26.712831],"type":"Point"}
}