{
  "type": "Feature",
  "properties": {
    "addr:full":"2721 S Woodland Blvd Deland FL 32720",
    "addr:housenumber":"2721",
    "addr:postcode":"32720",
    "addr:street":"S Woodland Blvd",
    "iso:country":"US",
    "sg:address":"2721 S Woodland Blvd",
    "sg:city":"Deland",
    "sg:classifiers":[
        {
            "category":"Insurance",
            "subcategory":"Insurance Agent",
            "type":"Services"
        }
    ],
    "sg:phone":"+1 386 736 5700",
    "sg:postcode":"32720",
    "sg:province":"FL",
    "wof:name":"Great Florida Insurance",
    "wof:placetype":"venue"
},
  "geometry": {"coordinates":[-81.299367,28.980325],"type":"Point"}
}