{
  "type": "Feature",
  "properties": {
    "addr:full":"2825 10th Ave SE Naples FL 34117",
    "addr:housenumber":"2825",
    "addr:postcode":"34117",
    "addr:street":"10Th Ave Se",
    "iso:country":"US",
    "sg:address":"2825 10th Ave SE",
    "sg:city":"Naples",
    "sg:classifiers":[
        {
            "category":"Building & Trades",
            "subcategory":"Construction",
            "type":"Services"
        }
    ],
    "sg:phone":"+1 239 404 0990",
    "sg:postcode":"34117",
    "sg:province":"FL",
    "sg:tags":[
        "framing",
        "contractor"
    ],
    "wof:name":"Trevino's Custom Carpentry",
    "wof:placetype":"venue"
},
  "geometry": {"coordinates":[-81.548892,26.21236],"type":"Point"}
}