{
  "type": "Feature",
  "properties": {
    "iso:country":"US",
    "sg:address":"6870 Sta Point Ct",
    "sg:city":"Winter Park",
    "sg:classifiers":[
        {
            "category":"Arts & Performance",
            "subcategory":"Arts Center",
            "type":"Entertainment"
        }
    ],
    "sg:phone":"+1 407 657 8774",
    "sg:postcode":"32792",
    "sg:province":"FL",
    "sg:tags":[
        "performing"
    ],
    "wof:name":"Chelle Stack's Brown's Gymnastic Centers",
    "wof:placetype":"venue"
},
  "geometry": {"coordinates":[-81.296402,28.589001],"type":"Point"}
}