{
  "type": "Feature",
  "properties": {
    "iso:country":"US",
    "sg:address":"4400 W Colonial Dr",
    "sg:city":"Orlando",
    "sg:classifiers":[
        {
            "category":"Retail",
            "subcategory":"Auto Repair",
            "type":"Services"
        }
    ],
    "sg:phone":"+1 407 295 3155",
    "sg:postcode":"32808",
    "sg:province":"FL",
    "sg:tags":[
        "transmission"
    ],
    "wof:name":"Transco Transmission",
    "wof:placetype":"venue"
},
  "geometry": {"coordinates":[-81.434169,28.552615],"type":"Point"}
}