{
  "type": "Feature",
  "properties": {
    "iso:country":"US",
    "sg:address":"1475 Ringtail Rd",
    "sg:city":"Venice",
    "sg:classifiers":[
        {
            "category":"Professional",
            "type":"Services"
        }
    ],
    "sg:phone":"+1 941 493 7465",
    "sg:postcode":"34293",
    "sg:province":"FL",
    "wof:name":"Digitech Systems Inc",
    "wof:placetype":"venue"
},
  "geometry": {"coordinates":[-82.43261699999999,27.053065],"type":"Point"}
}