{
  "type": "Feature",
  "properties": {
    "addr:full":"1267 Coral Way Miami FL 33145",
    "addr:housenumber":"1267",
    "addr:postcode":"33145",
    "addr:street":"Coral Way",
    "iso:country":"US",
    "sg:address":"1267 Coral Way",
    "sg:city":"Miami",
    "sg:classifiers":[
        {
            "category":"Health Services",
            "subcategory":"Health Practitioner",
            "type":"Services"
        }
    ],
    "sg:phone":"+1 305 302 4523",
    "sg:postcode":"33145",
    "sg:province":"FL",
    "sg:tags":[
        "nutritionist",
        "therapy",
        "physical"
    ],
    "sg:website":"www.morphelife.com",
    "wof:name":"Morphe",
    "wof:placetype":"venue"
},
  "geometry": {"coordinates":[-80.215914,25.751337],"type":"Point"}
}