{
  "type": "Feature",
  "properties": {
    "iso:country":"US",
    "sg:address":"210 S Daytona Ave",
    "sg:city":"Flagler Beach",
    "sg:classifiers":[
        {
            "category":"Banks & Credit Unions",
            "subcategory":"Investment Brokerage",
            "type":"Services"
        }
    ],
    "sg:phone":"+1 386 439 4430",
    "sg:postcode":"32136",
    "sg:province":"FL",
    "sg:tags":[
        "advisory",
        "financial"
    ],
    "wof:name":"Dynamics Financial Works Inc",
    "wof:placetype":"venue"
},
  "geometry": {"coordinates":[-81.129306,29.480227],"type":"Point"}
}