{
  "type": "Feature",
  "properties": {
    "iso:country":"US",
    "sg:address":"14286 Beach Blvd",
    "sg:city":"Jacksonville Beach",
    "sg:classifiers":[
        {
            "category":"Retail",
            "subcategory":"Photofinishing",
            "type":"Services"
        }
    ],
    "sg:phone":"+1 904 223 1801",
    "sg:postcode":"32250",
    "sg:province":"FL",
    "sg:tags":[
        "film",
        "developing"
    ],
    "wof:name":"Rush One-Hour Photo",
    "wof:placetype":"venue"
},
  "geometry": {"coordinates":[-81.441652,30.287774],"type":"Point"}
}