{
  "type": "Feature",
  "properties": {
    "iso:country":"US",
    "sg:address":"17313 Carriage Way",
    "sg:city":"Odessa",
    "sg:classifiers":[
        {
            "category":"Real Estate",
            "subcategory":"Real Estate Services",
            "type":"Services"
        },
        {
            "category":"Real Estate",
            "subcategory":"Real Estate Agent",
            "type":"Services"
        }
    ],
    "sg:phone":"+1 813 926 3186",
    "sg:postcode":"33556",
    "sg:province":"FL",
    "sg:tags":[
        "buyer",
        "broker"
    ],
    "wof:name":"Great Blue Real Estate Marketing Systems",
    "wof:placetype":"venue"
},
  "geometry": {"coordinates":[-82.561403,28.123216],"type":"Point"}
}