{
  "type": "Feature",
  "properties": {
    "iso:country":"US",
    "sg:address":"900 Virginia Ave",
    "sg:city":"Fort Pierce",
    "sg:classifiers":[
        {
            "category":"Professional",
            "subcategory":"Accounting & Tax Preparation",
            "type":"Services"
        }
    ],
    "sg:phone":"+1 772 465 0550",
    "sg:postcode":"34982",
    "sg:province":"FL",
    "sg:tags":[
        "accountant"
    ],
    "wof:name":"Business Service Center Inc",
    "wof:placetype":"venue"
},
  "geometry": {"coordinates":[-80.33291,27.4254],"type":"Point"}
}