{
  "type": "Feature",
  "properties": {
    "iso:country":"US",
    "sg:address":"2429 Burlington Ln",
    "sg:city":"Sarasota",
    "sg:classifiers":[
        {
            "category":"Shopping",
            "type":"Retail Goods"
        }
    ],
    "sg:phone":"+1 941 927 6595",
    "sg:postcode":"34231",
    "sg:province":"FL",
    "sg:tags":[
        "used",
        "merchandise"
    ],
    "wof:name":"Auction US Inc",
    "wof:placetype":"venue"
},
  "geometry": {"coordinates":[-82.52101,27.27722],"type":"Point"}
}