{
  "type": "Feature",
  "properties": {
    "addr:full":"4233 W Commercial Blvd Fort Lauderdale FL 33319",
    "addr:housenumber":"4233",
    "addr:postcode":"33319",
    "addr:street":"W Commercial Blvd",
    "iso:country":"US",
    "sg:address":"4233 W Commercial Blvd",
    "sg:city":"Fort Lauderdale",
    "sg:classifiers":[
        {
            "category":"Shopping",
            "type":"Retail Goods"
        },
        {
            "category":"Shopping",
            "subcategory":"Shoes",
            "type":"Retail Goods"
        }
    ],
    "sg:phone":"+1 954 486 4610",
    "sg:postcode":"33319",
    "sg:province":"FL",
    "sg:tags":[
        "wholesale",
        "orthopedic",
        "appliance"
    ],
    "wof:name":"Branier Orthopedic Care Center",
    "wof:placetype":"venue"
},
  "geometry": {"coordinates":[-80.20713499999999,26.187321],"type":"Point"}
}