{
  "type": "Feature",
  "properties": {
    "addr:full":"1531 Edgar Pl Sarasota FL 34240",
    "addr:housenumber":"1531",
    "addr:postcode":"34240",
    "addr:street":"Edgar Pl",
    "iso:country":"US",
    "sg:address":"1531 Edgar Pl",
    "sg:city":"Sarasota",
    "sg:classifiers":[
        {
            "category":"Wholesale",
            "subcategory":"Hardware",
            "type":"Manufacturing & Wholesale Goods"
        }
    ],
    "sg:phone":"+1 941 378 0727",
    "sg:postcode":"34240",
    "sg:province":"FL",
    "sg:tags":[
        "building",
        "plumbing",
        "material"
    ],
    "sg:website":"http://www.broedell.com",
    "wof:name":"Broedell Plumbing Supply Inc",
    "wof:placetype":"venue"
},
  "geometry": {"coordinates":[-82.44283,27.321859],"type":"Point"}
}