{
  "type": "Feature",
  "properties": {
    "iso:country":"US",
    "sg:address":"822 E Base St",
    "sg:city":"Madison",
    "sg:classifiers":[
        {
            "category":"Place Of Worship",
            "subcategory":"Church",
            "type":"Public Place"
        },
        {
            "category":"Place Of Worship",
            "type":"Public Place"
        }
    ],
    "sg:phone":"+1 850 973 4917",
    "sg:postcode":"32340",
    "sg:province":"FL",
    "sg:tags":[
        "churches-seventh-day",
        "adventist",
        "christian",
        "churches-advent"
    ],
    "wof:name":"Seventh Day Adventist",
    "wof:placetype":"venue"
},
  "geometry": {"coordinates":[-83.402995,30.469141],"type":"Point"}
}