{
  "type": "Feature",
  "properties": {
    "addr:full":"2614 NW 69 Ter Gainesville FL 32606",
    "addr:housenumber":"2614",
    "addr:postcode":"32606",
    "addr:street":"Nw 69 Ter",
    "iso:country":"US",
    "sg:address":"2614 NW 69 Ter",
    "sg:city":"Gainesville",
    "sg:classifiers":[
        {
            "category":"Shopping",
            "subcategory":"Clothing, Apparel, & Fashions",
            "type":"Retail Goods"
        }
    ],
    "sg:phone":"+1 352 378 5679",
    "sg:postcode":"32606",
    "sg:province":"FL",
    "wof:name":"Dianes Designs",
    "wof:placetype":"venue"
},
  "geometry": {"coordinates":[-82.41654699999999,29.6766],"type":"Point"}
}