{
  "type": "Feature",
  "properties": {
    "iso:country":"US",
    "sg:address":"945-2 Phillips St",
    "sg:city":"Jacksonville",
    "sg:classifiers":[
        {
            "category":"Shopping",
            "subcategory":"Stationery & Office Supplies",
            "type":"Retail Goods"
        },
        {
            "category":"Wholesale",
            "subcategory":"Office Equipment",
            "type":"Manufacturing & Wholesale Goods"
        }
    ],
    "sg:phone":"+1 904 260 0911",
    "sg:postcode":"32207",
    "sg:province":"FL",
    "sg:tags":[
        "furniture"
    ],
    "sg:website":"http://www.totalop-jax.com",
    "wof:name":"Total Office Products",
    "wof:placetype":"venue"
},
  "geometry": {"coordinates":[-81.661444,30.31131],"type":"Point"}
}