{
  "type": "Feature",
  "properties": {
    "addr:full":"1149 SW 7th St Fort Lauderdale FL 33312",
    "addr:housenumber":"1149",
    "addr:postcode":"33312",
    "addr:street":"Sw 7Th St",
    "iso:country":"US",
    "sg:address":"1149 SW 7th St",
    "sg:city":"Fort Lauderdale",
    "sg:classifiers":[
        {
            "category":"Restaurant",
            "type":"Food & Drink"
        }
    ],
    "sg:menulink":"http://www.allmenus.com/fl/fort-lauderdale/163212-rallys/menu/",
    "sg:phone":"+1 954 321 6690",
    "sg:postcode":"33312",
    "sg:province":"FL",
    "sg:tags":[
        "sandwich",
        "dog",
        "burger",
        "hot",
        "wrap",
        "american"
    ],
    "wof:name":"Rally's",
    "wof:placetype":"venue"
},
  "geometry": {"coordinates":[-80.157398,26.113152],"type":"Point"}
}