{
  "type": "Feature",
  "properties": {
    "addr:full":"1500 State Hwy 436 Fern Park FL 32730",
    "addr:housenumber":"1500",
    "addr:postcode":"32730",
    "addr:street":"State Hwy 436 Fern Park",
    "iso:country":"US",
    "sg:address":"1500 State Hwy 436",
    "sg:city":"Fern Park",
    "sg:classifiers":[
        {
            "category":"Retail",
            "subcategory":"Auto Repair",
            "type":"Services"
        }
    ],
    "sg:phone":"+1 407 834 1065",
    "sg:postcode":"32730",
    "sg:province":"FL",
    "sg:tags":[
        "repairing",
        "automobile"
    ],
    "sg:website":"www.icecoldauto.com",
    "wof:name":"Ice Cold Auto Air Of Seminole",
    "wof:placetype":"venue"
},
  "geometry": {"coordinates":[-81.342332,28.660946],"type":"Point"}
}