{
  "type": "Feature",
  "properties": {
    "addr:full":"900 S Miami Ave #182 Miami FL 33130",
    "addr:housenumber":"900",
    "addr:postcode":"33130",
    "addr:street":"S Miami Ave # 182",
    "iso:country":"US",
    "sg:address":"900 S Miami Ave #182",
    "sg:city":"Miami",
    "sg:classifiers":[
        {
            "category":"Shopping",
            "subcategory":"Shoes",
            "type":"Retail Goods"
        }
    ],
    "sg:phone":"+1 305 379 9300",
    "sg:postcode":"33130",
    "sg:province":"FL",
    "sg:tags":[
        "store"
    ],
    "wof:name":"Joanna Paige",
    "wof:placetype":"venue"
},
  "geometry": {"coordinates":[-80.19351,25.765241],"type":"Point"}
}