{
  "type": "Feature",
  "properties": {
    "iso:country":"US",
    "sg:address":"7818 NW 71st St",
    "sg:city":"Miami",
    "sg:classifiers":[
        {
            "category":"Wholesale",
            "subcategory":"Hardware",
            "type":"Manufacturing & Wholesale Goods"
        },
        {
            "category":"Building & Trades",
            "subcategory":"Equipment Rental",
            "type":"Services"
        },
        {
            "category":"Home & Garden",
            "subcategory":"Hardware",
            "type":"Retail Goods"
        }
    ],
    "sg:phone":"+1 305 468 9899",
    "sg:postcode":"33166",
    "sg:province":"FL",
    "sg:tags":[
        "contractor",
        "hardware-builders",
        "store",
        "supply"
    ],
    "wof:name":"A 1 Benexport",
    "wof:placetype":"venue"
},
  "geometry": {"coordinates":[-80.327985,25.837992],"type":"Point"}
}