{
  "type": "Feature",
  "properties": {
    "iso:country":"US",
    "sg:address":"280 Mojave Ct",
    "sg:city":"Merritt Island",
    "sg:classifiers":[
        {
            "category":"Professional",
            "type":"Services"
        }
    ],
    "sg:phone":"+1 321 432 6523",
    "sg:postcode":"32952",
    "sg:province":"FL",
    "wof:name":"Atmosphere Makers Incorporated",
    "wof:placetype":"venue"
},
  "geometry": {"coordinates":[-80.69419600000001,28.342512],"type":"Point"}
}