{
  "type": "Feature",
  "properties": {
    "addr:full":"8736 Seminole Blvd Seminole FL 33772",
    "addr:housenumber":"8736",
    "addr:postcode":"33772",
    "addr:street":"Seminole Blvd",
    "iso:country":"US",
    "sg:address":"8736 Seminole Blvd",
    "sg:city":"Seminole",
    "sg:classifiers":[
        {
            "category":"Building & Trades",
            "subcategory":"Electrical",
            "type":"Services"
        }
    ],
    "sg:phone":"+1 727 398 6604",
    "sg:postcode":"33772",
    "sg:province":"FL",
    "sg:tags":[
        "electric",
        "contractor"
    ],
    "wof:name":"Graham Electric",
    "wof:placetype":"venue"
},
  "geometry": {"coordinates":[-82.787194,27.851367],"type":"Point"}
}