{
  "type": "Feature",
  "properties": {
    "iso:country":"US",
    "sg:address":"1791 NW 1st Ave",
    "sg:city":"Boca Raton",
    "sg:classifiers":[
        {
            "category":"Wholesale",
            "subcategory":"Construction Materials",
            "type":"Manufacturing & Wholesale Goods"
        }
    ],
    "sg:phone":"+1 561 988 5544",
    "sg:postcode":"33432",
    "sg:province":"FL",
    "sg:tags":[
        "tile",
        "retail",
        "marble"
    ],
    "wof:name":"World of Tile & Marble Inc",
    "wof:placetype":"venue"
},
  "geometry": {"coordinates":[-80.086658,26.363747],"type":"Point"}
}