{
  "type": "Feature",
  "properties": {
    "addr:full":"390 W Carroll St Kissimmee FL 34741",
    "addr:housenumber":"390",
    "addr:postcode":"34741",
    "addr:street":"W Carroll St",
    "iso:country":"US",
    "sg:address":"390 W Carroll St",
    "sg:city":"Kissimmee",
    "sg:classifiers":[
        {
            "category":"Food & Beverages",
            "subcategory":"Groceries & Convenience Stores",
            "type":"Retail Goods"
        }
    ],
    "sg:phone":"+1 407 931 2881",
    "sg:postcode":"34741",
    "sg:province":"FL",
    "sg:tags":[
        "grocer"
    ],
    "wof:name":"80 Food Mart",
    "wof:placetype":"venue"
},
  "geometry": {"coordinates":[-81.40687200000001,28.326021],"type":"Point"}
}