{
  "type": "Feature",
  "properties": {
    "addr:full":"9019 NW 152nd Ln Hialeah FL 33018",
    "addr:housenumber":"9019",
    "addr:postcode":"33018",
    "addr:street":"Nw 152Nd Ln",
    "iso:country":"US",
    "sg:address":"9019 NW 152nd Ln",
    "sg:city":"Hialeah",
    "sg:classifiers":[
        {
            "category":"Professional",
            "type":"Services"
        }
    ],
    "sg:phone":"+1 305 231 0881",
    "sg:postcode":"33018",
    "sg:province":"FL",
    "wof:name":"Direct 2u Inc",
    "wof:placetype":"venue"
},
  "geometry": {"coordinates":[-80.347758,25.912115],"type":"Point"}
}