{
  "type": "Feature",
  "properties": {
    "addr:full":"199 Aurora Blvd Orange Park FL 32073",
    "addr:housenumber":"199",
    "addr:postcode":"32073",
    "addr:street":"Aurora Blvd",
    "iso:country":"US",
    "sg:address":"199 Aurora Blvd",
    "sg:city":"Orange Park",
    "sg:classifiers":[
        {
            "category":"Home & Garden",
            "subcategory":"Carpets & Floor Coverings",
            "type":"Retail Goods"
        }
    ],
    "sg:phone":"+1 904 838 6705",
    "sg:postcode":"32073",
    "sg:province":"FL",
    "sg:tags":[
        "consulting",
        "us"
    ],
    "wof:name":"Carpet Floor Covering",
    "wof:placetype":"venue"
},
  "geometry": {"coordinates":[-81.74263999999999,30.17768],"type":"Point"}
}