{
  "type": "Feature",
  "properties": {
    "addr:full":"2000 Park Cir Leesburg FL 34748",
    "addr:housenumber":"2000",
    "addr:postcode":"34748",
    "addr:street":"Park Cir",
    "iso:country":"US",
    "sg:address":"2000 Park Cir",
    "sg:city":"Leesburg",
    "sg:classifiers":[
        {
            "category":"Real Estate",
            "subcategory":"Real Estate Operator",
            "type":"Services"
        }
    ],
    "sg:phone":"+1 352 326 3300",
    "sg:postcode":"34748",
    "sg:province":"FL",
    "sg:tags":[
        "apartment"
    ],
    "wof:name":"Mt Clair Village Apts",
    "wof:placetype":"venue"
},
  "geometry": {"coordinates":[-81.91636699999999,28.82472],"type":"Point"}
}