{
  "type": "Feature",
  "properties": {
    "addr:full":"18544 127th Dr N Jupiter FL 33478",
    "addr:housenumber":"18544",
    "addr:postcode":"33478",
    "addr:street":"127Th Dr N",
    "iso:country":"US",
    "sg:address":"18544 127th Dr N",
    "sg:city":"Jupiter",
    "sg:classifiers":[
        {
            "category":"Professional",
            "subcategory":"Business Services",
            "type":"Services"
        }
    ],
    "sg:phone":"+1 561 743 5963",
    "sg:postcode":"33478",
    "sg:province":"FL",
    "wof:name":"John Woodstock Design",
    "wof:placetype":"venue"
},
  "geometry": {"coordinates":[-80.23479,26.950453],"type":"Point"}
}