{
  "type": "Feature",
  "properties": {
    "addr:full":"952 Northlake Blvd Lake Park FL 33403",
    "addr:housenumber":"952",
    "addr:postcode":"33403",
    "addr:street":"Northlake Blvd",
    "iso:country":"US",
    "sg:address":"952 Northlake Blvd",
    "sg:city":"Lake Park",
    "sg:classifiers":[
        {
            "category":"Restaurant",
            "type":"Food & Drink"
        }
    ],
    "sg:phone":"+1 561 863 1212",
    "sg:postcode":"33403",
    "sg:province":"FL",
    "sg:tags":[
        "eating"
    ],
    "wof:name":"Miami Subs & Grill",
    "wof:placetype":"venue"
},
  "geometry": {"coordinates":[-80.07605599999999,26.808087],"type":"Point"}
}