{
  "type": "Feature",
  "properties": {
    "addr:full":"55 Lower Bridge Rd Crawfordville FL 32327",
    "addr:housenumber":"55",
    "addr:postcode":"32327",
    "addr:street":"Lower Bridge Rd",
    "iso:country":"US",
    "sg:address":"55 Lower Bridge Rd",
    "sg:city":"Crawfordville",
    "sg:classifiers":[
        {
            "category":"Organizations",
            "subcategory":"Religious Organization",
            "type":"Services"
        }
    ],
    "sg:phone":"+1 850 926 3122",
    "sg:postcode":"32327",
    "sg:province":"FL",
    "wof:name":"Christian Academy",
    "wof:placetype":"venue"
},
  "geometry": {"coordinates":[-84.371809,30.176956],"type":"Point"}
}