{
  "type": "Feature",
  "properties": {
    "addr:full":"6187 NW 167th St Hialeah FL 33015",
    "addr:housenumber":"6187",
    "addr:postcode":"33015",
    "addr:street":"Nw 167Th St",
    "iso:country":"US",
    "sg:address":"6187 NW 167th St",
    "sg:city":"Hialeah",
    "sg:classifiers":[
        {
            "category":"Building & Trades",
            "subcategory":"Construction",
            "type":"Services"
        }
    ],
    "sg:phone":"+1 305 557 8238",
    "sg:postcode":"33015",
    "sg:province":"FL",
    "sg:tags":[
        "home",
        "improvement"
    ],
    "wof:name":"SDP Enterprises Inc",
    "wof:placetype":"venue"
},
  "geometry": {"coordinates":[-80.30383399999999,25.925205],"type":"Point"}
}