{
  "type": "Feature",
  "properties": {
    "addr:full":"16 NE 4th St Fort Lauderdale FL 33301",
    "addr:housenumber":"16",
    "addr:postcode":"33301",
    "addr:street":"Ne 4Th St",
    "iso:country":"US",
    "sg:address":"16 NE 4th St",
    "sg:city":"Fort Lauderdale",
    "sg:classifiers":[
        {
            "category":"Wholesale",
            "subcategory":"Apparel",
            "type":"Manufacturing & Wholesale Goods"
        }
    ],
    "sg:phone":"+1 954 779 7100",
    "sg:postcode":"33301",
    "sg:province":"FL",
    "sg:tags":[
        "clothing"
    ],
    "wof:name":"B K Hamburg Corporation",
    "wof:placetype":"venue"
},
  "geometry": {"coordinates":[-80.14267100000001,26.126075],"type":"Point"}
}