{
  "type": "Feature",
  "properties": {
    "addr:full":"1747 Drew St Clearwater FL 33755",
    "addr:housenumber":"1747",
    "addr:postcode":"33755",
    "addr:street":"Drew St",
    "iso:country":"US",
    "sg:address":"1747 Drew St",
    "sg:city":"Clearwater",
    "sg:classifiers":[
        {
            "category":"Shopping",
            "subcategory":"Florist",
            "type":"Retail Goods"
        }
    ],
    "sg:phone":"+1 727 461 0887",
    "sg:postcode":"33755",
    "sg:province":"FL",
    "sg:website":"http://www.mostlyrosesflorists.com",
    "wof:name":"Mostly Roses",
    "wof:placetype":"venue"
},
  "geometry": {"coordinates":[-82.764938,27.967979],"type":"Point"}
}