{
  "type": "Feature",
  "properties": {
    "addr:full":"1040 Seminole Dr Fort Lauderdale FL 33304",
    "addr:housenumber":"1040",
    "addr:postcode":"33304",
    "addr:street":"Seminole Dr",
    "iso:country":"US",
    "sg:address":"1040 Seminole Dr",
    "sg:city":"Fort Lauderdale",
    "sg:classifiers":[
        {
            "category":"Professional",
            "subcategory":"Management & Consulting",
            "type":"Services"
        }
    ],
    "sg:phone":"+1 954 567 4140",
    "sg:postcode":"33304",
    "sg:province":"FL",
    "sg:tags":[
        "business"
    ],
    "wof:name":"Vp Bioventures LLC",
    "wof:placetype":"venue"
},
  "geometry": {"coordinates":[-80.110764,26.138025],"type":"Point"}
}