{
  "type": "Feature",
  "properties": {
    "iso:country":"US",
    "sg:address":"8320 NW 14th St",
    "sg:city":"Doral",
    "sg:classifiers":[
        {
            "category":"Shopping",
            "subcategory":"Tobacco",
            "type":"Retail Goods"
        }
    ],
    "sg:phone":"+1 305 500 9216",
    "sg:postcode":"33126",
    "sg:province":"FL",
    "sg:tags":[
        "shop"
    ],
    "wof:name":"M C Enterprises Llc",
    "wof:placetype":"venue"
},
  "geometry": {"coordinates":[-80.33090199999999,25.7864],"type":"Point"}
}