{
  "type": "Feature",
  "properties": {
    "iso:country":"US",
    "sg:address":"37592 US Hwy 19 N",
    "sg:city":"Palm Harbor",
    "sg:classifiers":[
        {
            "category":"Wholesale",
            "subcategory":"Machinery & Supplies",
            "type":"Manufacturing & Wholesale Goods"
        },
        {
            "category":"Home & Garden",
            "subcategory":"Hardware",
            "type":"Retail Goods"
        }
    ],
    "sg:phone":"+1 727 942 8168",
    "sg:postcode":"34684",
    "sg:province":"FL",
    "sg:tags":[
        "sprinkler"
    ],
    "wof:name":"T W C Distributors Inc",
    "wof:placetype":"venue"
},
  "geometry": {"coordinates":[-82.739937,28.113048],"type":"Point"}
}