{
  "type": "Feature",
  "properties": {
    "iso:country":"US",
    "sg:address":"6936 Madrid Ave",
    "sg:city":"Jacksonville",
    "sg:classifiers":[
        {
            "category":"Health Services",
            "subcategory":"Podiatrist",
            "type":"Services"
        }
    ],
    "sg:phone":"+1 904 696 1500",
    "sg:postcode":"32217",
    "sg:province":"FL",
    "wof:name":"Dr William J Namen II",
    "wof:placetype":"venue"
},
  "geometry": {"coordinates":[-81.638109,30.252258],"type":"Point"}
}