{
  "type": "Feature",
  "properties": {
    "iso:country":"US",
    "sg:address":"826 NW 132nd Ct",
    "sg:city":"Miami",
    "sg:classifiers":[
        {
            "category":"Wholesale",
            "subcategory":"Non-durable Goods",
            "type":"Manufacturing & Wholesale Goods"
        }
    ],
    "sg:phone":"+1 305 225 1960",
    "sg:postcode":"33182",
    "sg:province":"FL",
    "wof:name":"Bior Corporation",
    "wof:placetype":"venue"
},
  "geometry": {"coordinates":[-80.409423,25.777472],"type":"Point"}
}