{
  "type": "Feature",
  "properties": {
    "iso:country":"US",
    "sg:address":"4995 NW 72nd Ave",
    "sg:city":"Miami",
    "sg:classifiers":[
        {
            "category":"Health Services",
            "subcategory":"Chiropractor",
            "type":"Services"
        }
    ],
    "sg:phone":"+1 305 994 9474",
    "sg:postcode":"33166",
    "sg:province":"FL",
    "wof:name":"Raffa Wlc",
    "wof:placetype":"venue"
},
  "geometry": {"coordinates":[-80.313276,25.818811],"type":"Point"}
}