{
  "type": "Feature",
  "properties": {
    "iso:country":"US",
    "sg:address":"1553 San Marco Blvd",
    "sg:city":"Jacksonville",
    "sg:classifiers":[
        {
            "category":"Professional",
            "subcategory":"Computer Services",
            "type":"Services"
        }
    ],
    "sg:phone":"+1 904 399 3211",
    "sg:postcode":"32207",
    "sg:province":"FL",
    "sg:website":"www.jysc.com",
    "wof:name":"A Java",
    "wof:placetype":"venue"
},
  "geometry": {"coordinates":[-81.660456,30.309004],"type":"Point"}
}