{
  "type": "Feature",
  "properties": {
    "addr:full":"9114 Windjammer Ln Orlando FL 32819",
    "addr:housenumber":"9114",
    "addr:postcode":"32819",
    "addr:street":"Windjammer Ln",
    "iso:country":"US",
    "sg:address":"9114 Windjammer Ln",
    "sg:city":"Orlando",
    "sg:classifiers":[
        {
            "category":"Shopping",
            "subcategory":"Jewelry",
            "type":"Retail Goods"
        }
    ],
    "sg:phone":"+1 407 876 6601",
    "sg:postcode":"32819",
    "sg:province":"FL",
    "wof:name":"C Miller Jewelry",
    "wof:placetype":"venue"
},
  "geometry": {"coordinates":[-81.513509,28.473228],"type":"Point"}
}