{
  "type": "Feature",
  "properties": {
    "iso:country":"US",
    "sg:address":"807 E Bloomingdale Ave",
    "sg:city":"Brandon",
    "sg:classifiers":[
        {
            "category":"Shopping",
            "type":"Retail Goods"
        }
    ],
    "sg:phone":"+1 813 685 2462",
    "sg:postcode":"33511",
    "sg:province":"FL",
    "sg:tags":[
        "merchandise"
    ],
    "wof:name":"X Hear",
    "wof:placetype":"venue"
},
  "geometry": {"coordinates":[-82.27180300000001,27.89356],"type":"Point"}
}