{
  "type": "Feature",
  "properties": {
    "addr:full":"4402 S Chirper Dr Lecanto FL 34461",
    "addr:housenumber":"4402",
    "addr:postcode":"34461",
    "addr:street":"S Chirper Dr",
    "iso:country":"US",
    "sg:address":"4402 S Chirper Dr",
    "sg:city":"Lecanto",
    "sg:classifiers":[
        {
            "category":"Retail",
            "subcategory":"Auto Repair",
            "type":"Services"
        }
    ],
    "sg:phone":"+1 352 302 9858",
    "sg:postcode":"34461",
    "sg:province":"FL",
    "sg:tags":[
        "wrecker"
    ],
    "wof:name":"Adam's 24 Hour Towing",
    "wof:placetype":"venue"
},
  "geometry": {"coordinates":[-82.48554799999999,28.798454],"type":"Point"}
}