{
  "type": "Feature",
  "properties": {
    "addr:full":"9797 Bay Pines Blvd N St Petersburg FL 33708",
    "addr:housenumber":"9797",
    "addr:postcode":"33708",
    "addr:street":"Bay Pines Blvd N",
    "iso:country":"US",
    "sg:address":"9797 Bay Pines Blvd N",
    "sg:city":"St Petersburg",
    "sg:classifiers":[
        {
            "category":"Education",
            "subcategory":"Special Training",
            "type":"Public Place"
        }
    ],
    "sg:phone":"+1 727 521 1117",
    "sg:postcode":"33708",
    "sg:province":"FL",
    "sg:tags":[
        "reading",
        "instruction",
        "improvement"
    ],
    "wof:name":"Literacy Council-St Petersburg",
    "wof:placetype":"venue"
},
  "geometry": {"coordinates":[-82.772689,27.813927],"type":"Point"}
}