{
  "type": "Feature",
  "properties": {
    "addr:full":"5921 Beneva Rd Sarasota FL 34238",
    "addr:postcode":"5921;34238",
    "addr:street":"Beneva Rd",
    "iso:country":"US",
    "sg:address":"5921 Beneva Rd",
    "sg:city":"Sarasota",
    "sg:classifiers":[
        {
            "category":"Professional",
            "subcategory":"Detective & Security Services",
            "type":"Services"
        }
    ],
    "sg:phone":"+1 941 922 7599",
    "sg:postcode":"34238",
    "sg:province":"FL",
    "sg:tags":[
        "investigator"
    ],
    "wof:name":"Florida Claims Bureau Inc",
    "wof:placetype":"venue"
},
  "geometry": {"coordinates":[-82.49753800000001,27.268748],"type":"Point"}
}