{
  "type": "Feature",
  "properties": {
    "addr:full":"11490 Emerald Coast Pkwy W Destin FL 32550",
    "addr:housenumber":"11490",
    "addr:postcode":"32550",
    "addr:street":"Emerald Coast Pkwy W",
    "iso:country":"US",
    "sg:address":"11490 Emerald Coast Pkwy W",
    "sg:city":"Destin",
    "sg:classifiers":[
        {
            "category":"Professional",
            "type":"Services"
        }
    ],
    "sg:phone":"+1 850 337 3469",
    "sg:postcode":"32550",
    "sg:province":"FL",
    "sg:tags":[
        "establishment"
    ],
    "wof:name":"Florida's Great Northwest Inc",
    "wof:placetype":"venue"
},
  "geometry": {"coordinates":[-86.36235600000001,30.38417],"type":"Point"}
}