{
  "type": "Feature",
  "properties": {
    "iso:country":"US",
    "sg:address":"2311 Ave D",
    "sg:city":"Fort Pierce",
    "sg:classifiers":[
        {
            "category":"Taxi",
            "type":"Transportation"
        }
    ],
    "sg:phone":"+1 772 465 2222",
    "sg:postcode":"34950",
    "sg:province":"FL",
    "sg:tags":[
        "taxicab"
    ],
    "wof:name":"Coe Taxi Cab Svc",
    "wof:placetype":"venue"
},
  "geometry": {"coordinates":[-80.348789,27.452894],"type":"Point"}
}