{
  "type": "Feature",
  "properties": {
    "addr:full":"2700 SW 37th Ave Coconut Grove FL 33133",
    "addr:housenumber":"2700",
    "addr:postcode":"33133",
    "addr:street":"Sw 37Th Ave",
    "iso:country":"US",
    "sg:address":"2700 SW 37th Ave",
    "sg:city":"Coconut Grove",
    "sg:classifiers":[
        {
            "category":"Professional",
            "subcategory":"Lawyer & Legal Services",
            "type":"Services"
        }
    ],
    "sg:phone":"+1 305 444 0013",
    "sg:postcode":"33133",
    "sg:province":"FL",
    "sg:tags":[
        "attorney"
    ],
    "wof:name":"Maria T Lopez",
    "wof:placetype":"venue"
},
  "geometry": {"coordinates":[-80.254233,25.741066],"type":"Point"}
}