{
  "type": "Feature",
  "properties": {
    "iso:country":"US",
    "sg:address":"420 Hamilton Ave",
    "sg:city":"Deland",
    "sg:classifiers":[
        {
            "category":"Manufacturing",
            "subcategory":"Printing",
            "type":"Manufacturing & Wholesale Goods"
        },
        {
            "category":"Professional",
            "subcategory":"Advertising",
            "type":"Services"
        },
        {
            "category":"Manufacturing",
            "subcategory":"Textiles",
            "type":"Manufacturing & Wholesale Goods"
        },
        {
            "category":"Shopping",
            "subcategory":"Bicycles & Sporting Goods",
            "type":"Retail Goods"
        }
    ],
    "sg:phone":"+1 386 740 7212",
    "sg:postcode":"32724",
    "sg:province":"FL",
    "sg:tags":[
        "fabrics-wholesale",
        "outdoor",
        "imaging",
        "manufacturer",
        "digital"
    ],
    "sg:website":"http://www.ballfabrics.com",
    "wof:name":"Ball Fabrics, Inc.",
    "wof:placetype":"venue"
},
  "geometry": {"coordinates":[-81.298035,29.061987],"type":"Point"}
}