{
  "type": "Feature",
  "properties": {
    "iso:country":"US",
    "sg:address":"12195 SW 39th Ln",
    "sg:city":"Ocala",
    "sg:classifiers":[
        {
            "category":"Building & Trades",
            "subcategory":"Construction",
            "type":"Services"
        }
    ],
    "sg:phone":"+1 352 873 8779",
    "sg:postcode":"34481",
    "sg:province":"FL",
    "sg:tags":[
        "general",
        "contractor"
    ],
    "wof:name":"Jerry Mack Construction",
    "wof:placetype":"venue"
},
  "geometry": {"coordinates":[-82.315462,29.148864],"type":"Point"}
}