{
  "type": "Feature",
  "properties": {
    "iso:country":"US",
    "sg:address":"2934 Griffinview Dr",
    "sg:city":"Lady Lake",
    "sg:classifiers":[
        {
            "category":"Building & Trades",
            "subcategory":"Landscaping Services",
            "type":"Services"
        }
    ],
    "sg:phone":"+1 352 750 4274",
    "sg:postcode":"32159",
    "sg:province":"FL",
    "wof:name":"Jz Lawn Care",
    "wof:placetype":"venue"
},
  "geometry": {"coordinates":[-81.904763,28.90886],"type":"Point"}
}