{
  "type": "Feature",
  "properties": {
    "addr:full":"1857 Wells Rd Orange Park FL 32073",
    "addr:housenumber":"1857",
    "addr:postcode":"32073",
    "addr:street":"Wells Rd",
    "iso:country":"US",
    "sg:address":"1857 Wells Rd",
    "sg:city":"Orange Park",
    "sg:classifiers":[
        {
            "category":"Professional",
            "subcategory":"Lawyer & Legal Services",
            "type":"Services"
        }
    ],
    "sg:phone":"+1 904 278 6964",
    "sg:postcode":"32073",
    "sg:province":"FL",
    "sg:tags":[
        "attorney"
    ],
    "wof:name":"Barnes Barnes & Cohen PA",
    "wof:placetype":"venue"
},
  "geometry": {"coordinates":[-81.732474,30.186994],"type":"Point"}
}