{
  "type": "Feature",
  "properties": {
    "iso:country":"US",
    "sg:address":"2657 Ringling Blvd",
    "sg:city":"Sarasota",
    "sg:classifiers":[
        {
            "category":"Home & Garden",
            "subcategory":"Furniture",
            "type":"Retail Goods"
        },
        {
            "category":"Wholesale",
            "subcategory":"Furniture",
            "type":"Manufacturing & Wholesale Goods"
        }
    ],
    "sg:phone":"+1 941 952 9271",
    "sg:postcode":"34237",
    "sg:province":"FL",
    "sg:tags":[
        "contractor"
    ],
    "wof:name":"Furniture Design Concepts LLC",
    "wof:placetype":"venue"
},
  "geometry": {"coordinates":[-82.517096,27.336542],"type":"Point"}
}