{
  "type": "Feature",
  "properties": {
    "iso:country":"US",
    "sg:address":"3250 NE Candice Ave",
    "sg:city":"Jensen Beach",
    "sg:classifiers":[
        {
            "category":"Building & Trades",
            "subcategory":"Construction",
            "type":"Services"
        }
    ],
    "sg:phone":"+1 772 334 9800",
    "sg:postcode":"34957",
    "sg:province":"FL",
    "sg:tags":[
        "house",
        "general",
        "contractor"
    ],
    "wof:name":"George H Pastor & Sons",
    "wof:placetype":"venue"
},
  "geometry": {"coordinates":[-80.227929,27.244831],"type":"Point"}
}