{
  "type": "Feature",
  "properties": {
    "addr:full":"51 Dale Dr Winter Haven FL 33880",
    "addr:housenumber":"51",
    "addr:postcode":"33880",
    "addr:street":"Dale Dr",
    "iso:country":"US",
    "sg:address":"51 Dale Dr",
    "sg:city":"Winter Haven",
    "sg:classifiers":[
        {
            "category":"Shopping",
            "subcategory":"Jewelry",
            "type":"Retail Goods"
        }
    ],
    "sg:phone":"+1 863 293 7223",
    "sg:postcode":"33880",
    "sg:province":"FL",
    "sg:tags":[
        "jeweler"
    ],
    "wof:name":"Bead Utiful",
    "wof:placetype":"venue"
},
  "geometry": {"coordinates":[-81.78042499999999,27.981534],"type":"Point"}
}