{
  "type": "Feature",
  "properties": {
    "iso:country":"US",
    "sg:address":"1013 Neely St",
    "sg:city":"Oviedo",
    "sg:classifiers":[
        {
            "category":"Retail",
            "subcategory":"Laundry & Dry Cleaning",
            "type":"Services"
        }
    ],
    "sg:phone":"+1 407 971 9223",
    "sg:postcode":"32765",
    "sg:province":"FL",
    "sg:tags":[
        "cleaner",
        "commercial"
    ],
    "wof:name":"Pressed 4 Time",
    "wof:placetype":"venue"
},
  "geometry": {"coordinates":[-81.194813,28.64405],"type":"Point"}
}