{
  "type": "Feature",
  "properties": {
    "addr:full":"205 McKean St Auburndale FL 33823",
    "addr:housenumber":"205",
    "addr:postcode":"33823",
    "addr:street":"Mckean St",
    "iso:country":"US",
    "sg:address":"205 McKean St",
    "sg:city":"Auburndale",
    "sg:classifiers":[
        {
            "category":"Retail",
            "subcategory":"Repair Shop",
            "type":"Services"
        }
    ],
    "sg:phone":"+1 863 551 9387",
    "sg:postcode":"33823",
    "sg:province":"FL",
    "wof:name":"Aries LP & Natural Gas Service",
    "wof:placetype":"venue"
},
  "geometry": {"coordinates":[-81.79686599999999,28.067812],"type":"Point"}
}