{
  "type": "Feature",
  "properties": {
    "addr:full":"594 Darkwood Ave Ocoee FL 34761",
    "addr:housenumber":"594",
    "addr:postcode":"34761",
    "addr:street":"Darkwood Ave",
    "iso:country":"US",
    "sg:address":"594 Darkwood Ave",
    "sg:city":"Ocoee",
    "sg:classifiers":[
        {
            "category":"Education",
            "subcategory":"Special Training",
            "type":"Public Place"
        }
    ],
    "sg:phone":"+1 407 905 9044",
    "sg:postcode":"34761",
    "sg:province":"FL",
    "sg:tags":[
        "educational"
    ],
    "wof:name":"Pinnacle Education Institute",
    "wof:placetype":"venue"
},
  "geometry": {"coordinates":[-81.53445600000001,28.535153],"type":"Point"}
}