{
  "type": "Feature",
  "properties": {
    "iso:country":"US",
    "sg:address":"2695 NW 56th St",
    "sg:city":"Fort Lauderdale",
    "sg:classifiers":[
        {
            "category":"Wholesale",
            "subcategory":"Machinery & Supplies",
            "type":"Manufacturing & Wholesale Goods"
        }
    ],
    "sg:phone":"+1 954 776 4030",
    "sg:postcode":"33309",
    "sg:province":"FL",
    "sg:tags":[
        "aircraft",
        "avionics"
    ],
    "wof:name":"Tropic Radio Inc",
    "wof:placetype":"venue"
},
  "geometry": {"coordinates":[-80.182811,26.195112],"type":"Point"}
}