{
  "type": "Feature",
  "properties": {
    "iso:country":"US",
    "sg:address":"8383 N Davis Hwy",
    "sg:city":"Pensacola",
    "sg:classifiers":[
        {
            "category":"Health Services",
            "subcategory":"Doctor",
            "type":"Services"
        }
    ],
    "sg:phone":"+1 850 494 5360",
    "sg:postcode":"32514",
    "sg:province":"FL",
    "sg:tags":[
        "physician",
        "surgeon"
    ],
    "wof:name":"Radiology Department",
    "wof:placetype":"venue"
},
  "geometry": {"coordinates":[-87.217062,30.515093],"type":"Point"}
}