{
  "type": "Feature",
  "properties": {
    "iso:country":"US",
    "sg:address":"4230 Lafayette St",
    "sg:city":"Marianna",
    "sg:classifiers":[
        {
            "category":"Government",
            "subcategory":"Office",
            "type":"Public Place"
        }
    ],
    "sg:phone":"+1 850 482 9592",
    "sg:postcode":"32446",
    "sg:province":"FL",
    "sg:tags":[
        "state",
        "resource"
    ],
    "wof:name":"Child Support Enforcement",
    "wof:placetype":"venue"
},
  "geometry": {"coordinates":[-85.243719,30.781422],"type":"Point"}
}