{
  "type": "Feature",
  "properties": {
    "iso:country":"US",
    "sg:address":"230 Altamonte Commerce Blvd",
    "sg:city":"Altamonte Spgs",
    "sg:classifiers":[
        {
            "category":"Retail",
            "subcategory":"Veterinary Services",
            "type":"Services"
        }
    ],
    "sg:phone":"+1 407 862 6892",
    "sg:postcode":"32714",
    "sg:province":"FL",
    "sg:tags":[
        "hospital",
        "animal"
    ],
    "wof:name":"Westmonte Animal Clinic",
    "wof:placetype":"venue"
},
  "geometry": {"coordinates":[-81.39084200000001,28.673803],"type":"Point"}
}