{
  "type": "Feature",
  "properties": {
    "addr:full":"400 Eastbridge Dr Oviedo FL 32765",
    "addr:housenumber":"400",
    "addr:postcode":"32765",
    "addr:street":"Eastbridge Dr",
    "iso:country":"US",
    "sg:address":"400 Eastbridge Dr",
    "sg:city":"Oviedo",
    "sg:classifiers":[
        {
            "category":"Professional",
            "subcategory":"Computer Services",
            "type":"Services"
        }
    ],
    "sg:phone":"+1 407 971 0951",
    "sg:postcode":"32765",
    "sg:province":"FL",
    "sg:tags":[
        "information",
        "retrieval"
    ],
    "wof:name":"Visible Light LLC",
    "wof:placetype":"venue"
},
  "geometry": {"coordinates":[-81.184645,28.665398],"type":"Point"}
}