{
  "type": "Feature",
  "properties": {
    "addr:full":"918 Crystal Cresst Ter Crystal River FL 34429",
    "addr:housenumber":"918",
    "addr:postcode":"34429",
    "addr:street":"Crystal Cresst Ter",
    "iso:country":"US",
    "sg:address":"918 Crystal Cresst Ter",
    "sg:city":"Crystal River",
    "sg:classifiers":[
        {
            "category":"Building & Trades",
            "subcategory":"Equipment Rental",
            "type":"Services"
        }
    ],
    "sg:phone":"+1 352 795 1818",
    "sg:postcode":"34429",
    "sg:province":"FL",
    "sg:tags":[
        "medical",
        "merchandise"
    ],
    "wof:name":"American Homepatient",
    "wof:placetype":"venue"
},
  "geometry": {"coordinates":[-82.573645,28.8755],"type":"Point"}
}