{
  "type": "Feature",
  "properties": {
    "iso:country":"US",
    "sg:address":"15630 McGregor Blvd",
    "sg:city":"Fort Myers",
    "sg:classifiers":[
        {
            "category":"Building & Trades",
            "subcategory":"Construction",
            "type":"Services"
        }
    ],
    "sg:phone":"+1 239 437 8500",
    "sg:postcode":"33908",
    "sg:province":"FL",
    "sg:tags":[
        "house"
    ],
    "wof:name":"Blue Chip Contracting Inc",
    "wof:placetype":"venue"
},
  "geometry": {"coordinates":[-81.947703,26.515344],"type":"Point"}
}