{
  "type": "Feature",
  "properties": {
    "iso:country":"US",
    "sg:address":"631 Beal Pkwy NW",
    "sg:city":"Fort Walton Bch",
    "sg:classifiers":[
        {
            "category":"Retail",
            "subcategory":"Auto Rental",
            "type":"Services"
        }
    ],
    "sg:phone":"+1 850 863 2134",
    "sg:postcode":"32547",
    "sg:province":"FL",
    "sg:tags":[
        "renting",
        "truck",
        "leasing"
    ],
    "wof:name":"Movers World Van Lines Inc",
    "wof:placetype":"venue"
},
  "geometry": {"coordinates":[-86.63953600000001,30.430545],"type":"Point"}
}