{
  "type": "Feature",
  "properties": {
    "iso:country":"US",
    "sg:address":"6301 46th St N",
    "sg:city":"Pinellas Park",
    "sg:classifiers":[
        {
            "category":"Retail",
            "subcategory":"Auto Repair",
            "type":"Services"
        }
    ],
    "sg:phone":"+1 727 525 6456",
    "sg:postcode":"33781",
    "sg:province":"FL",
    "sg:tags":[
        "machine",
        "automotive",
        "shop"
    ],
    "wof:name":"FICHTNER Automotive Machine",
    "wof:placetype":"venue"
},
  "geometry": {"coordinates":[-82.695922,27.831028],"type":"Point"}
}