{
  "type": "Feature",
  "properties": {
    "addr:full":"2763 Central Ave St Petersburg FL 33713",
    "addr:housenumber":"2763",
    "addr:postcode":"33713",
    "addr:street":"Central Ave",
    "iso:country":"US",
    "sg:address":"2763 Central Ave",
    "sg:city":"St Petersburg",
    "sg:classifiers":[
        {
            "category":"Retail",
            "subcategory":"Auto Repair",
            "type":"Services"
        }
    ],
    "sg:phone":"+1 727 327 4688",
    "sg:postcode":"33713",
    "sg:province":"FL",
    "sg:tags":[
        "repairing",
        "automobile",
        "general"
    ],
    "wof:name":"Slim's Service",
    "wof:placetype":"venue"
},
  "geometry": {"coordinates":[-82.670506,27.771068],"type":"Point"}
}