{
  "type": "Feature",
  "properties": {
    "iso:country":"US",
    "sg:address":"1600 4th St S",
    "sg:city":"St Petersburg",
    "sg:classifiers":[
        {
            "category":"Shopping",
            "type":"Retail Goods"
        }
    ],
    "sg:phone":"+1 727 894 2653",
    "sg:postcode":"33701",
    "sg:province":"FL",
    "sg:tags":[
        "art",
        "gallery",
        "merchandise",
        "dealer"
    ],
    "wof:name":"Salt Creek Art Works",
    "wof:placetype":"venue"
},
  "geometry": {"coordinates":[-82.63849399999999,27.754227],"type":"Point"}
}