{
  "type": "Feature",
  "properties": {
    "iso:country":"US",
    "sg:address":"156 Palm Beach Trace Dr",
    "sg:city":"West Palm Beach",
    "sg:classifiers":[
        {
            "category":"Building & Trades",
            "subcategory":"Construction",
            "type":"Services"
        }
    ],
    "sg:phone":"+1 561 758 5623",
    "sg:postcode":"33411",
    "sg:province":"FL",
    "sg:tags":[
        "contractor"
    ],
    "wof:name":"Arriba Pavers",
    "wof:placetype":"venue"
},
  "geometry": {"coordinates":[-80.22705000000001,26.71287],"type":"Point"}
}