{
  "type": "Feature",
  "properties": {
    "addr:full":"15181 Harding Ave Clearwater FL 33760",
    "addr:housenumber":"15181",
    "addr:postcode":"33760",
    "addr:street":"Harding Ave",
    "iso:country":"US",
    "sg:address":"15181 Harding Ave",
    "sg:city":"Clearwater",
    "sg:classifiers":[
        {
            "category":"Manufacturing",
            "subcategory":"Motor Vehicles & Parts",
            "type":"Manufacturing & Wholesale Goods"
        }
    ],
    "sg:phone":"+1 727 535 2165",
    "sg:postcode":"33760",
    "sg:province":"FL",
    "sg:tags":[
        "propane",
        "repair",
        "mfg",
        "supply",
        "floor"
    ],
    "wof:name":"J D R Engineering Inc",
    "wof:placetype":"venue"
},
  "geometry": {"coordinates":[-82.712453,27.910323],"type":"Point"}
}