{
  "type": "Feature",
  "properties": {
    "addr:full":"8053 W McNab Rd Fort Lauderdale FL 33321",
    "addr:housenumber":"8053",
    "addr:postcode":"33321",
    "addr:street":"W Mcnab Rd",
    "iso:country":"US",
    "sg:address":"8053 W McNab Rd",
    "sg:city":"Fort Lauderdale",
    "sg:classifiers":[
        {
            "category":"Real Estate",
            "subcategory":"Real Estate Agent",
            "type":"Services"
        }
    ],
    "sg:phone":"+1 954 969 5588",
    "sg:postcode":"33321",
    "sg:province":"FL",
    "wof:name":"Homes R US South Florida In",
    "wof:placetype":"venue"
},
  "geometry": {"coordinates":[-80.235669,26.208508],"type":"Point"}
}