{
  "type": "Feature",
  "properties": {
    "addr:full":"1581 SW 193rd Ave Hollywood FL 33029",
    "addr:housenumber":"1581",
    "addr:postcode":"33029",
    "addr:street":"Sw 193Rd Ave",
    "iso:country":"US",
    "sg:address":"1581 SW 193rd Ave",
    "sg:city":"Hollywood",
    "sg:classifiers":[
        {
            "category":"Personal",
            "subcategory":"Beauty Salon",
            "type":"Services"
        }
    ],
    "sg:phone":"+1 800 405 9466",
    "sg:postcode":"33029",
    "sg:province":"FL",
    "sg:tags":[
        "hair",
        "specialty"
    ],
    "wof:name":"Kids Super Salon",
    "wof:placetype":"venue"
},
  "geometry": {"coordinates":[-80.405224,25.99487],"type":"Point"}
}