{
  "type": "Feature",
  "properties": {
    "iso:country":"US",
    "sg:address":"11315 Corporate Blvd",
    "sg:city":"Orlando",
    "sg:classifiers":[
        {
            "category":"Government",
            "subcategory":"Office",
            "type":"Public Place"
        }
    ],
    "sg:phone":"+1 407 249 9771",
    "sg:postcode":"32817",
    "sg:province":"FL",
    "sg:tags":[
        "government-united",
        "state"
    ],
    "wof:name":"U S Government Dept Of Defense",
    "wof:placetype":"venue"
},
  "geometry": {"coordinates":[-81.22349699999999,28.601696],"type":"Point"}
}