{
  "type": "Feature",
  "properties": {
    "addr:full":"274 Apollo Beach Blvd Ruskin FL 33572",
    "addr:housenumber":"274",
    "addr:postcode":"33572",
    "addr:street":"Apollo Beach Blvd",
    "iso:country":"US",
    "sg:address":"274 Apollo Beach Blvd",
    "sg:city":"Ruskin",
    "sg:classifiers":[
        {
            "category":"Autos & Motor Vehicles",
            "subcategory":"Auto Supplies",
            "type":"Retail Goods"
        }
    ],
    "sg:phone":"+1 813 649 0818",
    "sg:postcode":"33572",
    "sg:province":"FL",
    "sg:tags":[
        "tire"
    ],
    "wof:name":"Carriage Works",
    "wof:placetype":"venue"
},
  "geometry": {"coordinates":[-82.394178,27.770368],"type":"Point"}
}