{
  "type": "Feature",
  "properties": {
    "addr:full":"389 N Alafaya Trl Orlando FL 32828",
    "addr:housenumber":"389",
    "addr:postcode":"32828",
    "addr:street":"N Alafaya Trl",
    "iso:country":"US",
    "sg:address":"389 N Alafaya Trl",
    "sg:city":"Orlando",
    "sg:classifiers":[
        {
            "category":"Shopping",
            "type":"Retail Goods"
        }
    ],
    "sg:phone":"+1 407 282 1553",
    "sg:postcode":"32828",
    "sg:province":"FL",
    "sg:tags":[
        "candle",
        "cosmetic",
        "perfume"
    ],
    "sg:website":"http://www.bathandbodyworks.com/",
    "wof:name":"Bath & Body Works",
    "wof:placetype":"venue"
},
  "geometry": {"coordinates":[-81.20421,28.551455],"type":"Point"}
}