{
  "type": "Feature",
  "properties": {
    "addr:full":"10137 W Oakland Park Blvd Fort Lauderdale FL 33351",
    "addr:housenumber":"10137",
    "addr:postcode":"33351",
    "addr:street":"W Oakland Park Blvd",
    "iso:country":"US",
    "sg:address":"10137 W Oakland Park Blvd",
    "sg:city":"Fort Lauderdale",
    "sg:classifiers":[
        {
            "category":"Shopping",
            "subcategory":"Shoes",
            "type":"Retail Goods"
        }
    ],
    "sg:phone":"+1 954 747 3797",
    "sg:postcode":"33351",
    "sg:province":"FL",
    "wof:name":"Annias Discount Shoes Inc",
    "wof:placetype":"venue"
},
  "geometry": {"coordinates":[-80.29264499999999,26.169914],"type":"Point"}
}