{
  "type": "Feature",
  "properties": {
    "iso:country":"US",
    "sg:address":"6132 Fort King Rd",
    "sg:city":"Zephyrhills",
    "sg:classifiers":[
        {
            "category":"Personal",
            "subcategory":"Beauty Salon",
            "type":"Services"
        }
    ],
    "sg:phone":"+1 813 782 4001",
    "sg:postcode":"33542",
    "sg:province":"FL",
    "wof:name":"Cutting Edge Beauty Salon",
    "wof:placetype":"venue"
},
  "geometry": {"coordinates":[-82.188631,28.246884],"type":"Point"}
}