{
  "type": "Feature",
  "properties": {
    "iso:country":"US",
    "sg:address":"7848 Falling Leaf Pl",
    "sg:city":"Melbourne",
    "sg:classifiers":[
        {
            "category":"Shopping",
            "subcategory":"Computers & Home Electronics",
            "type":"Retail Goods"
        }
    ],
    "sg:phone":"+1 321 259 7867",
    "sg:postcode":"32940",
    "sg:province":"FL",
    "sg:tags":[
        "software"
    ],
    "wof:name":"Denali Software Inc",
    "wof:placetype":"venue"
},
  "geometry": {"coordinates":[-80.70016099999999,28.23997],"type":"Point"}
}