{
  "type": "Feature",
  "properties": {
    "iso:country":"US",
    "sg:address":"650 Kane Ct",
    "sg:city":"Oviedo",
    "sg:classifiers":[
        {
            "category":"Building & Trades",
            "subcategory":"Construction",
            "type":"Services"
        },
        {
            "category":"Home & Garden",
            "subcategory":"Carpets & Floor Coverings",
            "type":"Retail Goods"
        }
    ],
    "sg:phone":"+1 407 977 0717",
    "sg:postcode":"32765",
    "sg:province":"FL",
    "sg:tags":[
        "material",
        "installation",
        "flooring",
        "contractor"
    ],
    "wof:name":"Regal Flooring Inc",
    "wof:placetype":"venue"
},
  "geometry": {"coordinates":[-81.219105,28.663933],"type":"Point"}
}