{
  "type": "Feature",
  "properties": {
    "iso:country":"US",
    "sg:address":"1533 State St",
    "sg:city":"Sarasota",
    "sg:classifiers":[
        {
            "category":"Shopping",
            "subcategory":"Jewelry",
            "type":"Retail Goods"
        }
    ],
    "sg:phone":"+1 941 951 2283",
    "sg:postcode":"34236",
    "sg:province":"FL",
    "sg:tags":[
        "designer"
    ],
    "wof:name":"Cavern Jewelers The",
    "wof:placetype":"venue"
},
  "geometry": {"coordinates":[-82.539199,27.335739],"type":"Point"}
}