{
  "type": "Feature",
  "properties": {
    "addr:full":"1723 SE 47th Ter Cape Coral FL 33904",
    "addr:housenumber":"1723",
    "addr:postcode":"33904",
    "addr:street":"Se 47Th Ter",
    "iso:country":"US",
    "sg:address":"1723 SE 47th Ter",
    "sg:city":"Cape Coral",
    "sg:classifiers":[
        {
            "category":"Building & Trades",
            "subcategory":"Construction",
            "type":"Services"
        }
    ],
    "sg:phone":"+1 239 549 0676",
    "sg:postcode":"33904",
    "sg:province":"FL",
    "sg:tags":[
        "home",
        "general",
        "family",
        "contractor"
    ],
    "wof:name":"Aloia Construction Inc",
    "wof:placetype":"venue"
},
  "geometry": {"coordinates":[-81.940555,26.563801],"type":"Point"}
}