{
  "type": "Feature",
  "properties": {
    "addr:full":"200 S Forest Ave Avon Park FL 33825",
    "addr:housenumber":"200",
    "addr:postcode":"33825",
    "addr:street":"S Forest Ave",
    "iso:country":"US",
    "sg:address":"200 S Forest Ave",
    "sg:city":"Avon Park",
    "sg:classifiers":[
        {
            "category":"Organizations",
            "subcategory":"Religious Organization",
            "type":"Services"
        }
    ],
    "sg:phone":"+1 863 453 4692",
    "sg:postcode":"33825",
    "sg:province":"FL",
    "sg:tags":[
        "church"
    ],
    "wof:name":"Church Of Christ",
    "wof:placetype":"venue"
},
  "geometry": {"coordinates":[-81.50299099999999,27.593819],"type":"Point"}
}