{
  "type": "Feature",
  "properties": {
    "addr:full":"468 Eagle Ridge Dr Lake Wales FL 33837",
    "addr:housenumber":"468",
    "addr:postcode":"33837",
    "addr:street":"Eagle Ridge Dr",
    "iso:country":"US",
    "sg:address":"468 Eagle Ridge Dr",
    "sg:city":"Lake Wales",
    "sg:classifiers":[
        {
            "category":"Shopping",
            "subcategory":"Jewelry",
            "type":"Retail Goods"
        }
    ],
    "sg:phone":"+1 863 679 8197",
    "sg:postcode":"33837",
    "sg:province":"FL",
    "sg:tags":[
        "jeweler"
    ],
    "wof:name":"Kay Jewelers",
    "wof:placetype":"venue"
},
  "geometry": {"coordinates":[-81.61828800000001,28.192137],"type":"Point"}
}