{
  "type": "Feature",
  "properties": {
    "iso:country":"US",
    "sg:address":"31 SW 57th Ave",
    "sg:city":"Miami",
    "sg:classifiers":[
        {
            "category":"Wholesale",
            "subcategory":"Construction Materials",
            "type":"Manufacturing & Wholesale Goods"
        },
        {
            "category":"Wholesale",
            "subcategory":"Machinery & Supplies",
            "type":"Manufacturing & Wholesale Goods"
        },
        {
            "category":"Home & Garden",
            "subcategory":"Building Materials",
            "type":"Retail Goods"
        },
        {
            "category":"Manufacturing",
            "subcategory":"Tools & Machinery",
            "type":"Manufacturing & Wholesale Goods"
        },
        {
            "category":"Wholesale",
            "subcategory":"Home Furnishings",
            "type":"Manufacturing & Wholesale Goods"
        },
        {
            "category":"Professional",
            "subcategory":"Engineering",
            "type":"Services"
        }
    ],
    "sg:phone":"+1 305 266 1571",
    "sg:postcode":"33144",
    "sg:province":"FL",
    "sg:tags":[
        "heater",
        "valve",
        "fixture",
        "system",
        "water",
        "equipment",
        "part",
        "plumbing",
        "fixtures",
        "supplies-wholesale",
        "air conditioning",
        "manufacturer"
    ],
    "sg:website":"http://www-ferguson-com.netsolads.com/index.shtml?_nsag=39482",
    "wof:name":"Lawrence Plumbing Supply, Co., a Wolseley Company",
    "wof:placetype":"venue"
},
  "geometry": {"coordinates":[-80.288116,25.770241],"type":"Point"}
}