{
  "type": "Feature",
  "properties": {
    "iso:country":"US",
    "sg:address":"7652 Ashley Park Ct",
    "sg:city":"Orlando",
    "sg:classifiers":[
        {
            "category":"Professional",
            "subcategory":"Accounting & Tax Preparation",
            "type":"Services"
        }
    ],
    "sg:phone":"+1 407 578 8300",
    "sg:postcode":"32835",
    "sg:province":"FL",
    "sg:tags":[
        "return"
    ],
    "wof:name":"Westbrook Kent William CPA",
    "wof:placetype":"venue"
},
  "geometry": {"coordinates":[-81.485687,28.507589],"type":"Point"}
}