{
  "type": "Feature",
  "properties": {
    "addr:full":"420 49th St E Palmetto FL 34221",
    "addr:housenumber":"420",
    "addr:postcode":"34221",
    "addr:street":"49Th St E",
    "iso:country":"US",
    "sg:address":"420 49th St E",
    "sg:city":"Palmetto",
    "sg:classifiers":[
        {
            "category":"Place Of Worship",
            "subcategory":"Church",
            "type":"Public Place"
        },
        {
            "category":"Place Of Worship",
            "type":"Public Place"
        }
    ],
    "sg:phone":"+1 941 721 4519",
    "sg:postcode":"34221",
    "sg:province":"FL",
    "sg:tags":[
        "churches-interdenominational",
        "churches-various",
        "denomination"
    ],
    "wof:name":"American Reformed Fellowship",
    "wof:placetype":"venue"
},
  "geometry": {"coordinates":[-82.559952,27.557989],"type":"Point"}
}