{
  "type": "Feature",
  "properties": {
    "addr:full":"8205 E Bay Blvd Navarre FL 32566",
    "addr:housenumber":"8205",
    "addr:postcode":"32566",
    "addr:street":"E Bay Blvd",
    "iso:country":"US",
    "sg:address":"8205 E Bay Blvd",
    "sg:city":"Navarre",
    "sg:classifiers":[
        {
            "category":"Government",
            "subcategory":"Fire Station",
            "type":"Public Place"
        }
    ],
    "sg:phone":"+1 850 939 5018",
    "sg:postcode":"32566",
    "sg:province":"FL",
    "sg:tags":[
        "department"
    ],
    "wof:name":"Holley-Navarre Volunteer Fire",
    "wof:placetype":"venue"
},
  "geometry": {"coordinates":[-86.884012,30.432486],"type":"Point"}
}