{
  "type": "Feature",
  "properties": {
    "addr:full":"8028 Dar Ln Zephyrhills FL 33541",
    "addr:postcode":"8028;33541",
    "addr:street":"Dar Ln",
    "iso:country":"US",
    "sg:address":"8028 Dar Ln",
    "sg:city":"Zephyrhills",
    "sg:classifiers":[
        {
            "category":"Building & Trades",
            "subcategory":"Plumbing",
            "type":"Services"
        }
    ],
    "sg:phone":"+1 813 782 4436",
    "sg:postcode":"33541",
    "sg:province":"FL",
    "sg:tags":[
        "plumbing",
        "contractor"
    ],
    "wof:name":"Jim Mattice Plumbing",
    "wof:placetype":"venue"
},
  "geometry": {"coordinates":[-82.199163,28.275521],"type":"Point"}
}