{
  "type": "Feature",
  "properties": {
    "iso:country":"US",
    "sg:address":"14651 Cleveland Ave",
    "sg:city":"Fort Myers",
    "sg:classifiers":[
        {
            "category":"Professional",
            "type":"Services"
        }
    ],
    "sg:phone":"+1 239 995 2272",
    "sg:postcode":"33903",
    "sg:province":"FL",
    "wof:name":"Double Dragon",
    "wof:placetype":"venue"
},
  "geometry": {"coordinates":[-81.899395,26.677374],"type":"Point"}
}