{
  "type": "Feature",
  "properties": {
    "iso:country":"US",
    "sg:address":"1 Collany Rd",
    "sg:city":"St Petersburg",
    "sg:classifiers":[
        {
            "category":"Real Estate",
            "subcategory":"Real Estate Agent",
            "type":"Services"
        }
    ],
    "sg:phone":"+1 727 866 6937",
    "sg:postcode":"33715",
    "sg:province":"FL",
    "sg:tags":[
        "consultant"
    ],
    "wof:name":"Fort De Soto Boat & Trailer",
    "wof:placetype":"venue"
},
  "geometry": {"coordinates":[-82.72879399999999,27.675675],"type":"Point"}
}