{
  "type": "Feature",
  "properties": {
    "iso:country":"US",
    "sg:address":"8565 Coral Way Ste 102",
    "sg:city":"Miami",
    "sg:classifiers":[
        {
            "category":"Coffee & Tea",
            "type":"Food & Drink"
        },
        {
            "category":"Donuts",
            "subcategory":"None",
            "type":"Food & Drink"
        }
    ],
    "sg:phone":"+1 305 261 1932",
    "sg:postcode":"33155",
    "sg:province":"FL",
    "sg:tags":[
        "shop",
        "espresso",
        "restaurant"
    ],
    "sg:website":"www.dunkindonuts.com",
    "wof:name":"Dunkin Donuts",
    "wof:placetype":"venue"
},
  "geometry": {"coordinates":[-80.333764,25.747768],"type":"Point"}
}