{
  "type": "Feature",
  "properties": {
    "iso:country":"US",
    "sg:address":"2870 Greenbrooke St",
    "sg:city":"Malabar",
    "sg:classifiers":[
        {
            "category":"Government",
            "subcategory":"Office",
            "type":"Public Place"
        }
    ],
    "sg:phone":"+1 321 952 4523",
    "sg:postcode":"32950",
    "sg:province":"FL",
    "wof:name":"Brevard County Mosquito Div",
    "wof:placetype":"venue"
},
  "geometry": {"coordinates":[-80.564442,27.963066],"type":"Point"}
}