{
  "type": "Feature",
  "properties": {
    "iso:country":"US",
    "sg:address":"2951 NW 49th Ave",
    "sg:city":"Fort Lauderdale",
    "sg:classifiers":[
        {
            "category":"Health Services",
            "subcategory":"Doctor",
            "type":"Services"
        }
    ],
    "sg:phone":"+1 954 739 2511",
    "sg:postcode":"33313",
    "sg:province":"FL",
    "wof:name":"Health Care Associates S Fla",
    "wof:placetype":"venue"
},
  "geometry": {"coordinates":[-80.217274,26.164006],"type":"Point"}
}