{
  "type": "Feature",
  "properties": {
    "iso:country":"US",
    "sg:address":"1376 Auburn Ct",
    "sg:city":"Boynton Beach",
    "sg:classifiers":[
        {
            "category":"Professional",
            "type":"Services"
        }
    ],
    "sg:phone":"+1 305 266 8525",
    "sg:postcode":"33436",
    "sg:province":"FL",
    "wof:name":"Jerry Fleisher",
    "wof:placetype":"venue"
},
  "geometry": {"coordinates":[-80.10143100000001,26.562665],"type":"Point"}
}