{
  "type": "Feature",
  "properties": {
    "iso:country":"US",
    "sg:address":"95 S Federal Hwy",
    "sg:city":"Boca Raton",
    "sg:classifiers":[
        {
            "category":"Banks & Credit Unions",
            "subcategory":"Investment Brokerage",
            "type":"Services"
        }
    ],
    "sg:phone":"+1 561 394 6664",
    "sg:postcode":"33432",
    "sg:province":"FL",
    "sg:tags":[
        "advisory"
    ],
    "wof:name":"Fleet",
    "wof:placetype":"venue"
},
  "geometry": {"coordinates":[-80.086476,26.349524],"type":"Point"}
}