{
  "type": "Feature",
  "properties": {
    "iso:country":"US",
    "sg:address":"475 Bridle Path Way",
    "sg:city":"Tarpon Springs",
    "sg:classifiers":[
        {
            "category":"Freight",
            "type":"Transportation"
        }
    ],
    "sg:phone":"+1 727 423 1202",
    "sg:postcode":"34688",
    "sg:province":"FL",
    "sg:tags":[
        "delivery"
    ],
    "wof:name":"Johnson Delivery Services Inc",
    "wof:placetype":"venue"
},
  "geometry": {"coordinates":[-82.692235,28.139122],"type":"Point"}
}