{
  "type": "Feature",
  "properties": {
    "addr:full":"390 Evergreen Cir Destin FL 32541",
    "addr:housenumber":"390",
    "addr:postcode":"32541",
    "addr:street":"Evergreen Cir",
    "iso:country":"US",
    "sg:address":"390 Evergreen Cir",
    "sg:city":"Destin",
    "sg:classifiers":[
        {
            "category":"Professional",
            "subcategory":"Management & Consulting",
            "type":"Services"
        }
    ],
    "sg:phone":"+1 850 650 8188",
    "sg:postcode":"32541",
    "sg:province":"FL",
    "sg:tags":[
        "consultant",
        "publishing"
    ],
    "wof:name":"Coastal House & Home",
    "wof:placetype":"venue"
},
  "geometry": {"coordinates":[-86.499526,30.399579],"type":"Point"}
}