{
  "type": "Feature",
  "properties": {
    "iso:country":"US",
    "sg:address":"7511 Los Pinos Blvd",
    "sg:city":"Miami",
    "sg:classifiers":[
        {
            "category":"Professional",
            "subcategory":"Business Services",
            "type":"Services"
        }
    ],
    "sg:phone":"+1 305 666 2446",
    "sg:postcode":"33143",
    "sg:province":"FL",
    "wof:name":"Susan Lunden",
    "wof:placetype":"venue"
},
  "geometry": {"coordinates":[-80.262145,25.698722],"type":"Point"}
}