{
  "type": "Feature",
  "properties": {
    "addr:full":"2772 Elkcam Blvd Deltona FL 32738",
    "addr:housenumber":"2772",
    "addr:postcode":"32738",
    "addr:street":"Elkcam Blvd",
    "iso:country":"US",
    "sg:address":"2772 Elkcam Blvd",
    "sg:city":"Deltona",
    "sg:classifiers":[
        {
            "category":"Banks & Credit Unions",
            "subcategory":"Bank",
            "type":"Services"
        }
    ],
    "sg:phone":"+1 386 532 4930",
    "sg:postcode":"32738",
    "sg:province":"FL",
    "sg:tags":[
        "loan",
        "real estate"
    ],
    "wof:name":"Esprit Mortgage Svc",
    "wof:placetype":"venue"
},
  "geometry": {"coordinates":[-81.190442,28.926459],"type":"Point"}
}