{
  "type": "Feature",
  "properties": {
    "addr:full":"5209 Timuquana Rd Jacksonville FL 32210",
    "addr:housenumber":"5209",
    "addr:postcode":"32210",
    "addr:street":"Timuquana Rd",
    "iso:country":"US",
    "sg:address":"5209 Timuquana Rd",
    "sg:city":"Jacksonville",
    "sg:classifiers":[
        {
            "category":"Banks & Credit Unions",
            "subcategory":"Bank",
            "type":"Services"
        }
    ],
    "sg:phone":"+1 904 772 0656",
    "sg:postcode":"32210",
    "sg:province":"FL",
    "sg:tags":[
        "loan",
        "real estate"
    ],
    "wof:name":"Home Mortgage Loan",
    "wof:placetype":"venue"
},
  "geometry": {"coordinates":[-81.71714900000001,30.247546],"type":"Point"}
}