{
  "type": "Feature",
  "properties": {
    "iso:country":"US",
    "sg:address":"940 Bunker View Dr",
    "sg:city":"Apollo Beach",
    "sg:classifiers":[
        {
            "category":"Real Estate",
            "subcategory":"Real Estate Agent",
            "type":"Services"
        }
    ],
    "sg:phone":"+1 813 645 4860",
    "sg:postcode":"33572",
    "sg:province":"FL",
    "wof:name":"I Pie Inc",
    "wof:placetype":"venue"
},
  "geometry": {"coordinates":[-82.421117,27.761287],"type":"Point"}
}