{
  "type": "Feature",
  "properties": {
    "addr:full":"3056 S State Rd 7 Miramar FL 33023",
    "addr:housenumber":"3056;7",
    "addr:postcode":"33023",
    "addr:street":"S State Rd",
    "iso:country":"US",
    "sg:address":"3056 S State Rd 7",
    "sg:city":"Miramar",
    "sg:classifiers":[
        {
            "category":"Retail",
            "subcategory":"Self-service Laundry",
            "type":"Services"
        }
    ],
    "sg:phone":"+1 954 966 2455",
    "sg:postcode":"33023",
    "sg:province":"FL",
    "wof:name":"Wash & Dry USA",
    "wof:placetype":"venue"
},
  "geometry": {"coordinates":[-80.206591,25.982235],"type":"Point"}
}