{
  "type": "Feature",
  "properties": {
    "iso:country":"US",
    "sg:address":"1014 Symphony Isles Blvd",
    "sg:city":"Apollo Beach",
    "sg:classifiers":[
        {
            "category":"Real Estate",
            "subcategory":"Real Estate Agent",
            "type":"Services"
        }
    ],
    "sg:phone":"+1 813 641 3355",
    "sg:postcode":"33572",
    "sg:province":"FL",
    "wof:name":"R E Maxwell Realty Inc",
    "wof:placetype":"venue"
},
  "geometry": {"coordinates":[-82.428162,27.768763],"type":"Point"}
}