{
  "type": "Feature",
  "properties": {
    "iso:country":"US",
    "sg:address":"8961 SW 142nd Ave",
    "sg:city":"Miami",
    "sg:classifiers":[
        {
            "category":"Real Estate",
            "subcategory":"Real Estate Services",
            "type":"Services"
        }
    ],
    "sg:phone":"+1 866 528 7831",
    "sg:postcode":"33186",
    "sg:province":"FL",
    "sg:tags":[
        "apartment",
        "rental",
        "finder"
    ],
    "sg:website":"http://miami.citysearch.com/profile/external/2555543/miami_fl/kings_colony.html?publisher=yellowpages&reference_id=1&placement=ypwebsitemip",
    "wof:name":"Kings Colony",
    "wof:placetype":"venue"
},
  "geometry": {"coordinates":[-80.424003,25.683045],"type":"Point"}
}