{
  "type": "Feature",
  "properties": {
    "addr:full":"420 E Sample Rd Pompano Beach FL 33064",
    "addr:housenumber":"420",
    "addr:postcode":"33064",
    "addr:street":"E Sample Rd",
    "iso:country":"US",
    "sg:address":"420 E Sample Rd",
    "sg:city":"Pompano Beach",
    "sg:classifiers":[
        {
            "category":"Retail",
            "subcategory":"Laundry & Dry Cleaning",
            "type":"Services"
        }
    ],
    "sg:phone":"+1 954 781 4572",
    "sg:postcode":"33064",
    "sg:province":"FL",
    "sg:tags":[
        "cleaners"
    ],
    "wof:name":"Dry Cleaners",
    "wof:placetype":"venue"
},
  "geometry": {"coordinates":[-80.119362,26.275088],"type":"Point"}
}