{
  "type": "Feature",
  "properties": {
    "iso:country":"US",
    "sg:address":"740 S Moon Dr",
    "sg:city":"Venice",
    "sg:classifiers":[
        {
            "category":"Building & Trades",
            "subcategory":"Construction",
            "type":"Services"
        }
    ],
    "sg:phone":"+1 941 966 3917",
    "sg:postcode":"34292",
    "sg:province":"FL",
    "sg:tags":[
        "contractor"
    ],
    "wof:name":"Aaron Kommuck",
    "wof:placetype":"venue"
},
  "geometry": {"coordinates":[-82.34279100000001,27.121645],"type":"Point"}
}