{
  "type": "Feature",
  "properties": {
    "addr:full":"2510 Catalonia Way S St Petersburg FL 33712",
    "addr:housenumber":"2510",
    "addr:postcode":"33712",
    "addr:street":"Catalonia Way S",
    "iso:country":"US",
    "sg:address":"2510 Catalonia Way S",
    "sg:city":"St Petersburg",
    "sg:classifiers":[
        {
            "category":"Building & Trades",
            "subcategory":"Electrical",
            "type":"Services"
        }
    ],
    "sg:phone":"+1 727 327 1724",
    "sg:postcode":"33712",
    "sg:province":"FL",
    "sg:tags":[
        "electric",
        "contractor"
    ],
    "wof:name":"Roberson Electric Inc",
    "wof:placetype":"venue"
},
  "geometry": {"coordinates":[-82.66597299999999,27.729826],"type":"Point"}
}