{
  "type": "Feature",
  "properties": {
    "iso:country":"US",
    "sg:address":"2741 SW 86th Way",
    "sg:city":"Fort Lauderdale",
    "sg:classifiers":[
        {
            "category":"Building & Trades",
            "subcategory":"Construction",
            "type":"Services"
        }
    ],
    "sg:phone":"+1 954 473 9334",
    "sg:postcode":"33328",
    "sg:province":"FL",
    "sg:tags":[
        "house"
    ],
    "wof:name":"Mr Handyman",
    "wof:placetype":"venue"
},
  "geometry": {"coordinates":[-80.26268399999999,26.08573],"type":"Point"}
}