{
  "type": "Feature",
  "properties": {
    "addr:full":"2631 Maguire Rd Ocoee FL 34761",
    "addr:housenumber":"2631",
    "addr:postcode":"34761",
    "addr:street":"Maguire Rd",
    "iso:country":"US",
    "sg:address":"2631 Maguire Rd",
    "sg:city":"Ocoee",
    "sg:classifiers":[
        {
            "category":"Retail",
            "subcategory":"Storage",
            "type":"Services"
        }
    ],
    "sg:phone":"+1 407 654 3037",
    "sg:postcode":"34761",
    "sg:province":"FL",
    "sg:tags":[
        "self",
        "commercial",
        "household"
    ],
    "wof:name":"Maguire Road Self Storage",
    "wof:placetype":"venue"
},
  "geometry": {"coordinates":[-81.541898,28.532134],"type":"Point"}
}