{
  "type": "Feature",
  "properties": {
    "iso:country":"US",
    "sg:address":"9258 Lazy Ln",
    "sg:city":"Tampa",
    "sg:classifiers":[
        {
            "category":"Wholesale",
            "subcategory":"Medical Equipment & Supplies",
            "type":"Manufacturing & Wholesale Goods"
        }
    ],
    "sg:phone":"+1 813 915 1433",
    "sg:postcode":"33614",
    "sg:province":"FL",
    "sg:tags":[
        "janitorial"
    ],
    "wof:name":"Diversified Product Supplier",
    "wof:placetype":"venue"
},
  "geometry": {"coordinates":[-82.506232,28.035034],"type":"Point"}
}