{
  "type": "Feature",
  "properties": {
    "iso:country":"US",
    "sg:address":"2104 Corporate Dr",
    "sg:city":"Boynton Beach",
    "sg:classifiers":[
        {
            "category":"Wholesale",
            "subcategory":"Construction Materials",
            "type":"Manufacturing & Wholesale Goods"
        }
    ],
    "sg:phone":"+1 561 733 7097",
    "sg:postcode":"33426",
    "sg:province":"FL",
    "wof:name":"Harmon Inc",
    "wof:placetype":"venue"
},
  "geometry": {"coordinates":[-80.077161,26.513605],"type":"Point"}
}