{
  "type": "Feature",
  "properties": {
    "addr:full":"16 Laurel Oaks Cir Ormond Beach FL 32174",
    "addr:housenumber":"16",
    "addr:postcode":"32174",
    "addr:street":"Laurel Oaks Cir",
    "iso:country":"US",
    "sg:address":"16 Laurel Oaks Cir",
    "sg:city":"Ormond Beach",
    "sg:classifiers":[
        {
            "category":"Professional",
            "subcategory":"Accounting & Tax Preparation",
            "type":"Services"
        }
    ],
    "sg:phone":"+1 386 672 7884",
    "sg:postcode":"32174",
    "sg:province":"FL",
    "sg:tags":[
        "accountant"
    ],
    "wof:name":"Accounting By Carneal",
    "wof:placetype":"venue"
},
  "geometry": {"coordinates":[-81.06733199999999,29.264119],"type":"Point"}
}