{
  "type": "Feature",
  "properties": {
    "iso:country":"US",
    "sg:address":"8034 W 21st Ln",
    "sg:city":"Hialeah",
    "sg:classifiers":[
        {
            "category":"Retail",
            "subcategory":"Repair Shop",
            "type":"Services"
        }
    ],
    "sg:phone":"+1 305 826 5988",
    "sg:postcode":"33016",
    "sg:province":"FL",
    "sg:tags":[
        "scooter",
        "motorcycle",
        "motor"
    ],
    "wof:name":"Nelson Cycle",
    "wof:placetype":"venue"
},
  "geometry": {"coordinates":[-80.328058,25.895996],"type":"Point"}
}