{
  "type": "Feature",
  "properties": {
    "addr:full":"2135 N Market St Jacksonville FL 32206",
    "addr:housenumber":"2135",
    "addr:postcode":"32206",
    "addr:street":"N Market St",
    "iso:country":"US",
    "sg:address":"2135 N Market St",
    "sg:city":"Jacksonville",
    "sg:classifiers":[
        {
            "category":"Bakery",
            "type":"Food & Drink"
        }
    ],
    "sg:phone":"+1 904 354 7039",
    "sg:postcode":"32206",
    "sg:province":"FL",
    "wof:name":"Merita Bakery Garage",
    "wof:placetype":"venue"
},
  "geometry": {"coordinates":[-81.650565,30.350154],"type":"Point"}
}