{
  "type": "Feature",
  "properties": {
    "iso:country":"US",
    "sg:address":"2533 US Hwy 19",
    "sg:city":"Holiday",
    "sg:classifiers":[
        {
            "category":"Food & Beverages",
            "subcategory":"Groceries & Convenience Stores",
            "type":"Retail Goods"
        }
    ],
    "sg:phone":"+1 727 939 9099",
    "sg:postcode":"34691",
    "sg:province":"FL",
    "sg:tags":[
        "operator",
        "local",
        "trucking"
    ],
    "wof:name":"Golden Eagle Euro Food",
    "wof:placetype":"venue"
},
  "geometry": {"coordinates":[-82.73997300000001,28.197242],"type":"Point"}
}