{
  "type": "Feature",
  "properties": {
    "addr:full":"338 SW Tulip Blvd Port St Lucie FL 34953",
    "addr:housenumber":"338",
    "addr:postcode":"34953",
    "addr:street":"Sw Tulip Blvd",
    "iso:country":"US",
    "sg:address":"338 SW Tulip Blvd",
    "sg:city":"Port St Lucie",
    "sg:classifiers":[
        {
            "category":"Building & Trades",
            "subcategory":"Construction",
            "type":"Services"
        }
    ],
    "sg:phone":"+1 772 871 6756",
    "sg:postcode":"34953",
    "sg:province":"FL",
    "sg:tags":[
        "home",
        "builder"
    ],
    "wof:name":"Adams Homes Model Hm Pt St LC",
    "wof:placetype":"venue"
},
  "geometry": {"coordinates":[-80.357567,27.256416],"type":"Point"}
}