{
  "type": "Feature",
  "properties": {
    "addr:full":"2059 N University Dr Coral Springs FL 33071",
    "addr:housenumber":"2059",
    "addr:postcode":"33071",
    "addr:street":"N University Dr",
    "iso:country":"US",
    "sg:address":"2059 N University Dr",
    "sg:city":"Coral Springs",
    "sg:classifiers":[
        {
            "category":"Health Services",
            "subcategory":"Optometrist",
            "type":"Services"
        }
    ],
    "sg:phone":"+1 954 753 1100",
    "sg:postcode":"33071",
    "sg:province":"FL",
    "wof:name":"Reisch & Gendal's Vision World",
    "wof:placetype":"venue"
},
  "geometry": {"coordinates":[-80.2505,26.257519],"type":"Point"}
}