{
  "type": "Feature",
  "properties": {
    "iso:country":"US",
    "sg:address":"222 Carica Rd",
    "sg:city":"Naples",
    "sg:classifiers":[
        {
            "category":"Insurance",
            "subcategory":"Insurance Agent",
            "type":"Services"
        }
    ],
    "sg:phone":"+1 239 593 1800",
    "sg:postcode":"34108",
    "sg:province":"FL",
    "sg:tags":[
        "accident"
    ],
    "wof:name":"Hr & Health Benefits Solutions",
    "wof:placetype":"venue"
},
  "geometry": {"coordinates":[-81.788945,26.244216],"type":"Point"}
}