{
  "type": "Feature",
  "properties": {
    "addr:full":"3501 S Tamiami Trl Sarasota FL 34239",
    "addr:housenumber":"3501",
    "addr:postcode":"34239",
    "addr:street":"S Tamiami Trl",
    "iso:country":"US",
    "sg:address":"3501 S Tamiami Trl",
    "sg:city":"Sarasota",
    "sg:classifiers":[
        {
            "category":"Shopping",
            "subcategory":"Clothing, Apparel, & Fashions",
            "type":"Retail Goods"
        }
    ],
    "sg:phone":"+1 941 365 2881",
    "sg:postcode":"34239",
    "sg:province":"FL",
    "sg:tags":[
        "furnishing"
    ],
    "wof:name":"Wall Street For Men",
    "wof:placetype":"venue"
},
  "geometry": {"coordinates":[-82.530362,27.30212],"type":"Point"}
}