{
  "type": "Feature",
  "properties": {
    "iso:country":"US",
    "sg:address":"4300 Clarcona Ocoee Rd",
    "sg:city":"Orlando",
    "sg:classifiers":[
        {
            "category":"Retail",
            "subcategory":"Laundry & Dry Cleaning",
            "type":"Services"
        }
    ],
    "sg:phone":"+1 407 296 9563",
    "sg:postcode":"32810",
    "sg:province":"FL",
    "sg:tags":[
        "cleaners"
    ],
    "wof:name":"UCR Drycleaners",
    "wof:placetype":"venue"
},
  "geometry": {"coordinates":[-81.43232999999999,28.612758],"type":"Point"}
}