{
  "type": "Feature",
  "properties": {
    "iso:country":"US",
    "sg:address":"17315 Dona Michelle Dr",
    "sg:city":"Tampa",
    "sg:classifiers":[
        {
            "category":"Banks & Credit Unions",
            "subcategory":"Bank",
            "type":"Services"
        }
    ],
    "sg:phone":"+1 813 837 2451",
    "sg:postcode":"33647",
    "sg:province":"FL",
    "wof:name":"Grow Financial Federal Cu",
    "wof:placetype":"venue"
},
  "geometry": {"coordinates":[-82.371968,28.122863],"type":"Point"}
}