{
  "type": "Feature",
  "properties": {
    "iso:country":"US",
    "sg:address":"12 E Monument Ave",
    "sg:city":"Kissimmee",
    "sg:classifiers":[
        {
            "category":"Health Services",
            "subcategory":"Health Practitioner",
            "type":"Services"
        }
    ],
    "sg:phone":"+1 407 847 3337",
    "sg:postcode":"34741",
    "sg:province":"FL",
    "sg:tags":[
        "pathologist",
        "speech"
    ],
    "wof:name":"Central Florida Speech Pthlgst",
    "wof:placetype":"venue"
},
  "geometry": {"coordinates":[-81.405979,28.292946],"type":"Point"}
}