{
  "type": "Feature",
  "properties": {
    "addr:full":"6580 NW 22nd Ave Miami FL 33147",
    "addr:housenumber":"6580",
    "addr:postcode":"33147",
    "addr:street":"Nw 22Nd Ave",
    "iso:country":"US",
    "sg:address":"6580 NW 22nd Ave",
    "sg:city":"Miami",
    "sg:classifiers":[
        {
            "category":"Restaurant",
            "type":"Food & Drink"
        }
    ],
    "sg:phone":"+1 305 691 6161",
    "sg:postcode":"33147",
    "sg:province":"FL",
    "wof:name":"Mazie's Soul Food Take-Out",
    "wof:placetype":"venue"
},
  "geometry": {"coordinates":[-80.233101,25.8344],"type":"Point"}
}