{
  "type": "Feature",
  "properties": {
    "iso:country":"US",
    "sg:address":"6282 Forest Hill Blvd",
    "sg:city":"Greenacres",
    "sg:classifiers":[
        {
            "category":"Food & Beverages",
            "subcategory":"Groceries & Convenience Stores",
            "type":"Retail Goods"
        }
    ],
    "sg:phone":"+1 561 968 5808",
    "sg:postcode":"33415",
    "sg:province":"FL",
    "wof:name":"Quick Stop 2900",
    "wof:placetype":"venue"
},
  "geometry": {"coordinates":[-80.142314,26.651493],"type":"Point"}
}