{
  "type": "Feature",
  "properties": {
    "iso:country":"US",
    "sg:address":"3215 NE 184th St",
    "sg:city":"Miami",
    "sg:classifiers":[
        {
            "category":"Home & Garden",
            "subcategory":"Furniture",
            "type":"Retail Goods"
        }
    ],
    "sg:phone":"+1 305 466 2033",
    "sg:postcode":"33160",
    "sg:province":"FL",
    "wof:name":"Dipal Italian Office Furniture",
    "wof:placetype":"venue"
},
  "geometry": {"coordinates":[-80.135755,25.946922],"type":"Point"}
}