{
  "type": "Feature",
  "properties": {
    "addr:full":"4306 SE Federal Hwy Fort Pierce FL 34997",
    "addr:housenumber":"4306",
    "addr:postcode":"34997",
    "addr:street":"Se Federal Hwy",
    "iso:country":"US",
    "sg:address":"4306 SE Federal Hwy",
    "sg:city":"Fort Pierce",
    "sg:classifiers":[
        {
            "category":"Building & Trades",
            "subcategory":"Construction",
            "type":"Services"
        }
    ],
    "sg:phone":"+1 772 465 2700",
    "sg:postcode":"34997",
    "sg:province":"FL",
    "sg:tags":[
        "swimming",
        "pool",
        "contractor"
    ],
    "wof:name":"Bruhn Industries Inc",
    "wof:placetype":"venue"
},
  "geometry": {"coordinates":[-80.218006,27.151205],"type":"Point"}
}