{
  "type": "Feature",
  "properties": {
    "iso:country":"US",
    "sg:address":"1547 University Blvd W",
    "sg:city":"Jacksonville",
    "sg:classifiers":[
        {
            "category":"Retail",
            "subcategory":"Laundry & Dry Cleaning",
            "type":"Services"
        }
    ],
    "sg:phone":"+1 904 731 0866",
    "sg:postcode":"32217",
    "sg:province":"FL",
    "wof:name":"Best Alterations",
    "wof:placetype":"venue"
},
  "geometry": {"coordinates":[-81.64444399999999,30.260977],"type":"Point"}
}