{
  "type": "Feature",
  "properties": {
    "iso:country":"US",
    "sg:address":"4261 Shetland Ct",
    "sg:city":"Naples",
    "sg:classifiers":[
        {
            "category":"Building & Trades",
            "subcategory":"Landscaping Services",
            "type":"Services"
        }
    ],
    "sg:phone":"+1 239 732 5010",
    "sg:postcode":"34112",
    "sg:province":"FL",
    "sg:tags":[
        "lawn",
        "maintenance",
        "grounds"
    ],
    "wof:name":"Donald E Aubin Lawn Mntnc",
    "wof:placetype":"venue"
},
  "geometry": {"coordinates":[-81.747488,26.119862],"type":"Point"}
}