{
  "type": "Feature",
  "properties": {
    "addr:full":"1120 East Kennedy Blvd. Suite 230 Tampa FL 33611",
    "addr:housenumber":"1120",
    "addr:postcode":"33611",
    "addr:street":"East Kennedy Blvd. Suite 230",
    "iso:country":"US",
    "sg:address":"1120 East Kennedy Blvd. Suite 230",
    "sg:city":"Tampa",
    "sg:classifiers":[
        {
            "category":"Professional",
            "subcategory":"Management & Consulting",
            "type":"Services"
        }
    ],
    "sg:phone":"+1 813 849 4255",
    "sg:postcode":"33611",
    "sg:province":"FL",
    "sg:tags":[
        "customer-satisfaction-full-service-internet-services-surveys--research-marketing-consultants-qualitative-research-marketing-research-beverages--food-marketing-research-focus-group-moderators-marketing-research-health-care--medical-market-research-marketin"
    ],
    "sg:website":"http://www.studyhallresearch.com",
    "wof:name":"Study Hall Research",
    "wof:placetype":"venue"
},
  "geometry": {"coordinates":[-82.487886,27.893597],"type":"Point"}
}