{
  "type": "Feature",
  "properties": {
    "addr:full":"1614 Kings Rd Jacksonville FL 32209",
    "addr:housenumber":"1614",
    "addr:postcode":"32209",
    "addr:street":"Kings Rd",
    "iso:country":"US",
    "sg:address":"1614 Kings Rd",
    "sg:city":"Jacksonville",
    "sg:classifiers":[
        {
            "category":"Food & Beverages",
            "subcategory":"Groceries & Convenience Stores",
            "type":"Retail Goods"
        }
    ],
    "sg:phone":"+1 904 359 2009",
    "sg:postcode":"32209",
    "sg:province":"FL",
    "sg:tags":[
        "gasoline"
    ],
    "wof:name":"Amoco",
    "wof:placetype":"venue"
},
  "geometry": {"coordinates":[-81.68282499999999,30.343545],"type":"Point"}
}