{
  "type": "Feature",
  "properties": {
    "addr:full":"19705 SW 136th St Miami FL 33196",
    "addr:housenumber":"19705",
    "addr:postcode":"33196",
    "addr:street":"Sw 136Th St",
    "iso:country":"US",
    "sg:address":"19705 SW 136th St",
    "sg:city":"Miami",
    "sg:classifiers":[
        {
            "category":"Social Services",
            "subcategory":"Job Training",
            "type":"Services"
        }
    ],
    "sg:phone":"+1 305 252 9932",
    "sg:postcode":"33196",
    "sg:province":"FL",
    "sg:tags":[
        "employment"
    ],
    "wof:name":"Strike Force K-9 Service",
    "wof:placetype":"venue"
},
  "geometry": {"coordinates":[-80.512225,25.63771],"type":"Point"}
}