{
  "type": "Feature",
  "properties": {
    "iso:country":"US",
    "sg:address":"12700 Gulf Blvd",
    "sg:city":"Saint Petersburg",
    "sg:classifiers":[
        {
            "category":"Organizations",
            "subcategory":"Membership Organization",
            "type":"Services"
        }
    ],
    "sg:phone":"+1 727 360 7037",
    "sg:postcode":"33706",
    "sg:province":"FL",
    "wof:name":"Nordvind Condominium Assn",
    "wof:placetype":"venue"
},
  "geometry": {"coordinates":[-82.782251,27.782193],"type":"Point"}
}