{
  "type": "Feature",
  "properties": {
    "iso:country":"US",
    "sg:address":"2400 E Las Olas Blvd",
    "sg:city":"Fort Lauderdale",
    "sg:classifiers":[
        {
            "category":"Communications",
            "subcategory":"Film & Video Production",
            "type":"Services"
        }
    ],
    "sg:phone":"+1 954 741 2225",
    "sg:postcode":"33301",
    "sg:province":"FL",
    "sg:tags":[
        "taping"
    ],
    "wof:name":"Trial By Video Inc",
    "wof:placetype":"venue"
},
  "geometry": {"coordinates":[-80.113648,26.120064],"type":"Point"}
}