{
  "type": "Feature",
  "properties": {
    "iso:country":"US",
    "sg:address":"15421 W Dixie Hwy Unit 7",
    "sg:city":"North Miami Beach",
    "sg:classifiers":[
        {
            "category":"Professional",
            "subcategory":"Computer Services",
            "type":"Services"
        }
    ],
    "sg:phone":"+1 305 948 3439",
    "sg:postcode":"33162",
    "sg:province":"FL",
    "sg:tags":[
        "repair"
    ],
    "wof:name":"Monteiro Codicas",
    "wof:placetype":"venue"
},
  "geometry": {"coordinates":[-80.160698,25.9175],"type":"Point"}
}