{
  "type": "Feature",
  "properties": {
    "iso:country":"US",
    "sg:address":"3711 W Lloyd St",
    "sg:city":"Pensacola",
    "sg:classifiers":[
        {
            "category":"Taxi",
            "type":"Transportation"
        }
    ],
    "sg:phone":"+1 850 433 4499",
    "sg:postcode":"32505",
    "sg:province":"FL",
    "wof:name":"Phoenix Taxi",
    "wof:placetype":"venue"
},
  "geometry": {"coordinates":[-87.258567,30.425862],"type":"Point"}
}