{
  "type": "Feature",
  "properties": {
    "addr:full":"4111 NW 33rd Ln Cape Coral FL 33993",
    "addr:housenumber":"4111",
    "addr:postcode":"33993",
    "addr:street":"Nw 33Rd Ln",
    "iso:country":"US",
    "sg:address":"4111 NW 33rd Ln",
    "sg:city":"Cape Coral",
    "sg:classifiers":[
        {
            "category":"Building & Trades",
            "subcategory":"Construction",
            "type":"Services"
        }
    ],
    "sg:phone":"+1 239 282 2644",
    "sg:postcode":"33993",
    "sg:province":"FL",
    "sg:tags":[
        "carpentry",
        "contractor"
    ],
    "wof:name":"Greg Cimeno Carpentry Inc",
    "wof:placetype":"venue"
},
  "geometry": {"coordinates":[-82.05688499999999,26.716922],"type":"Point"}
}