{
  "type": "Feature",
  "properties": {
    "addr:full":"1283 State Hwy 47 Lake City FL 32055",
    "addr:housenumber":"1283",
    "addr:postcode":"32055",
    "addr:street":"State Hwy 47",
    "iso:country":"US",
    "sg:address":"1283 State Hwy 47",
    "sg:city":"Lake City",
    "sg:classifiers":[
        {
            "category":"Professional",
            "subcategory":"Research",
            "type":"Services"
        }
    ],
    "sg:phone":"+1 386 755 3019",
    "sg:postcode":"32055",
    "sg:province":"FL",
    "sg:tags":[
        "laboratory"
    ],
    "wof:name":"CHC Labs",
    "wof:placetype":"venue"
},
  "geometry": {"coordinates":[-82.639262,30.180457],"type":"Point"}
}