{
  "type": "Feature",
  "properties": {
    "iso:country":"US",
    "sg:address":"4626 SW 186th Way",
    "sg:city":"Hollywood",
    "sg:classifiers":[
        {
            "category":"Travel",
            "subcategory":"Travel Agent",
            "type":"Entertainment"
        }
    ],
    "sg:phone":"+1 954 450 7304",
    "sg:postcode":"33029",
    "sg:province":"FL",
    "sg:tags":[
        "operator",
        "tour"
    ],
    "wof:name":"Millennium Hotel & Tour",
    "wof:placetype":"venue"
},
  "geometry": {"coordinates":[-80.39481000000001,25.964824],"type":"Point"}
}