{
  "type": "Feature",
  "properties": {
    "addr:full":"60 Oceanway Ave Jacksonville FL 32218",
    "addr:housenumber":"60",
    "addr:postcode":"32218",
    "addr:street":"Oceanway Ave",
    "iso:country":"US",
    "sg:address":"60 Oceanway Ave",
    "sg:city":"Jacksonville",
    "sg:classifiers":[
        {
            "category":"Building & Trades",
            "subcategory":"Construction",
            "type":"Services"
        }
    ],
    "sg:phone":"+1 904 757 3964",
    "sg:postcode":"32218",
    "sg:province":"FL",
    "sg:tags":[
        "maker",
        "cabinet"
    ],
    "wof:name":"Duval Fixture Co",
    "wof:placetype":"venue"
},
  "geometry": {"coordinates":[-81.63083,30.466458],"type":"Point"}
}