{
  "type": "Feature",
  "properties": {
    "iso:country":"US",
    "sg:address":"405 S Dale Mabry Hwy",
    "sg:city":"Tampa",
    "sg:classifiers":[
        {
            "category":"Home & Garden",
            "subcategory":"Building Materials",
            "type":"Retail Goods"
        },
        {
            "category":"Building & Trades",
            "subcategory":"Construction",
            "type":"Services"
        }
    ],
    "sg:phone":"+1 813 875 7540",
    "sg:postcode":"33609",
    "sg:province":"FL",
    "sg:tags":[
        "builder",
        "gazebo",
        "patio"
    ],
    "wof:name":"Archadeck",
    "wof:placetype":"venue"
},
  "geometry": {"coordinates":[-82.50573,27.941182],"type":"Point"}
}