{
  "type": "Feature",
  "properties": {
    "addr:full":"8750 Ortega Park Dr Navarre FL 32566",
    "addr:housenumber":"8750",
    "addr:postcode":"32566",
    "addr:street":"Ortega Park Dr",
    "iso:country":"US",
    "sg:address":"8750 Ortega Park Dr",
    "sg:city":"Navarre",
    "sg:classifiers":[
        {
            "category":"Health Services",
            "subcategory":"Doctor",
            "type":"Services"
        }
    ],
    "sg:phone":"+1 850 939 5550",
    "sg:postcode":"32566",
    "sg:province":"FL",
    "sg:tags":[
        "physician",
        "surgeon"
    ],
    "wof:name":"Navarre Pediatrics",
    "wof:placetype":"venue"
},
  "geometry": {"coordinates":[-86.857511,30.403138],"type":"Point"}
}