{
  "type": "Feature",
  "properties": {
    "addr:full":"175 Tyler Ave Englewood FL 34223",
    "addr:housenumber":"175",
    "addr:postcode":"34223",
    "addr:street":"Tyler Ave",
    "iso:country":"US",
    "sg:address":"175 Tyler Ave",
    "sg:city":"Englewood",
    "sg:classifiers":[
        {
            "category":"Real Estate",
            "subcategory":"Developer",
            "type":"Services"
        }
    ],
    "sg:phone":"+1 941 475 6499",
    "sg:postcode":"34223",
    "sg:province":"FL",
    "sg:tags":[
        "investing"
    ],
    "wof:name":"Complete Properties",
    "wof:placetype":"venue"
},
  "geometry": {"coordinates":[-82.357148,26.952621],"type":"Point"}
}