{
  "type": "Feature",
  "properties": {
    "iso:country":"US",
    "sg:address":"701 Rose St",
    "sg:city":"Umatilla",
    "sg:classifiers":[
        {
            "category":"Autos & Motor Vehicles",
            "subcategory":"Auto Supplies",
            "type":"Retail Goods"
        }
    ],
    "sg:phone":"+1 352 771 0404",
    "sg:postcode":"32784",
    "sg:province":"FL",
    "sg:tags":[
        "equipment",
        "racing",
        "car",
        "automobile"
    ],
    "wof:name":"A R Machine",
    "wof:placetype":"venue"
},
  "geometry": {"coordinates":[-81.65444599999999,28.921749],"type":"Point"}
}