{
  "type": "Feature",
  "properties": {
    "iso:country":"US",
    "sg:address":"5050 Edwards St",
    "sg:city":"Jacksonville",
    "sg:classifiers":[
        {
            "category":"Building & Trades",
            "subcategory":"Construction",
            "type":"Services"
        }
    ],
    "sg:phone":"+1 904 786 4999",
    "sg:postcode":"32254",
    "sg:province":"FL",
    "sg:tags":[
        "concrete",
        "contractor"
    ],
    "wof:name":"Total Concrete Repair",
    "wof:placetype":"venue"
},
  "geometry": {"coordinates":[-81.56022400000001,30.389323],"type":"Point"}
}