{
  "type": "Feature",
  "properties": {
    "addr:full":"1112 Breakwater Ct Marco Island FL 34145",
    "addr:housenumber":"1112",
    "addr:postcode":"34145",
    "addr:street":"Breakwater Ct",
    "iso:country":"US",
    "sg:address":"1112 Breakwater Ct",
    "sg:city":"Marco Island",
    "sg:classifiers":[
        {
            "category":"Building & Trades",
            "subcategory":"Construction",
            "type":"Services"
        }
    ],
    "sg:phone":"+1 239 642 9073",
    "sg:postcode":"34145",
    "sg:province":"FL",
    "sg:tags":[
        "residential"
    ],
    "wof:name":"Handy Man",
    "wof:placetype":"venue"
},
  "geometry": {"coordinates":[-81.718143,25.929407],"type":"Point"}
}