{
  "type": "Feature",
  "properties": {
    "iso:country":"US",
    "sg:address":"206 S Jefferson St",
    "sg:city":"Beverly Hills",
    "sg:classifiers":[
        {
            "category":"Wholesale",
            "subcategory":"Vending Machines",
            "type":"Manufacturing & Wholesale Goods"
        }
    ],
    "sg:phone":"+1 352 746 2034",
    "sg:postcode":"34465",
    "sg:province":"FL",
    "sg:tags":[
        "operator"
    ],
    "wof:name":"S I Vending",
    "wof:placetype":"venue"
},
  "geometry": {"coordinates":[-82.464721,28.915442],"type":"Point"}
}