{
  "type": "Feature",
  "properties": {
    "iso:country":"US",
    "sg:address":"975 Imperial Golf Course Blvd",
    "sg:city":"Naples",
    "sg:classifiers":[
        {
            "category":"Health Services",
            "subcategory":"Doctor",
            "type":"Services"
        }
    ],
    "sg:phone":"+1 239 594 9355",
    "sg:postcode":"34110",
    "sg:province":"FL",
    "sg:tags":[
        "physician",
        "surgeon"
    ],
    "wof:name":"Chelation Center Of Naples",
    "wof:placetype":"venue"
},
  "geometry": {"coordinates":[-81.801044,26.289284],"type":"Point"}
}