{
  "type": "Feature",
  "properties": {
    "addr:full":"34748 Appaloosa Trl Zephyrhills FL 33541",
    "addr:housenumber":"34748",
    "addr:postcode":"33541",
    "addr:street":"Appaloosa Trl",
    "iso:country":"US",
    "sg:address":"34748 Appaloosa Trl",
    "sg:city":"Zephyrhills",
    "sg:classifiers":[
        {
            "category":"Building & Trades",
            "subcategory":"Cleaning & Sanitation",
            "type":"Services"
        }
    ],
    "sg:phone":"+1 813 780 8548",
    "sg:postcode":"33541",
    "sg:province":"FL",
    "sg:tags":[
        "janitor"
    ],
    "wof:name":"Zelaya Cleaning Svc",
    "wof:placetype":"venue"
},
  "geometry": {"coordinates":[-82.246224,28.214271],"type":"Point"}
}