{
  "type": "Feature",
  "properties": {
    "addr:full":"12700 Metro Pkwy Ste 12 Fort Myers FL 33912",
    "addr:housenumber":"12700",
    "addr:postcode":"myers fl 33912",
    "addr:street":"Metro Pkwy Ste 12",
    "iso:country":"US",
    "sg:address":"12700 Metro Pkwy Ste 12",
    "sg:city":"Fort Myers",
    "sg:classifiers":[
        {
            "category":"Building & Trades",
            "subcategory":"Construction",
            "type":"Services"
        }
    ],
    "sg:phone":"+1 239 561 5411",
    "sg:postcode":"33912",
    "sg:province":"FL",
    "sg:tags":[
        "interior",
        "design"
    ],
    "sg:website":"www.floridawoodcreations.com",
    "wof:name":"Florida Wood Creations Inc",
    "wof:placetype":"venue"
},
  "geometry": {"coordinates":[-81.852997,26.557301],"type":"Point"}
}