{
  "type": "Feature",
  "properties": {
    "addr:full":"3805 Mockingbird Dr Vero Beach FL 32963",
    "addr:housenumber":"3805",
    "addr:postcode":"32963",
    "addr:street":"Mockingbird Dr",
    "iso:country":"US",
    "sg:address":"3805 Mockingbird Dr",
    "sg:city":"Vero Beach",
    "sg:classifiers":[
        {
            "category":"Manufacturing",
            "subcategory":"Glass & Minerals",
            "type":"Manufacturing & Wholesale Goods"
        }
    ],
    "sg:phone":"+1 772 234 2940",
    "sg:postcode":"32963",
    "sg:province":"FL",
    "sg:tags":[
        "product",
        "mfg",
        "except",
        "concrete",
        "precast",
        "brick",
        "block"
    ],
    "wof:name":"Precast Products Inc",
    "wof:placetype":"venue"
},
  "geometry": {"coordinates":[-80.36459499999999,27.660461],"type":"Point"}
}