{
  "type": "Feature",
  "properties": {
    "iso:country":"US",
    "sg:address":"100 E Atlantic Ave",
    "sg:city":"Delray Beach",
    "sg:classifiers":[
        {
            "category":"Professional",
            "subcategory":"Management & Consulting",
            "type":"Services"
        }
    ],
    "sg:phone":"+1 561 266 8817",
    "sg:postcode":"33444",
    "sg:province":"FL",
    "sg:tags":[
        "public",
        "relations"
    ],
    "wof:name":"Communication Group The",
    "wof:placetype":"venue"
},
  "geometry": {"coordinates":[-80.071083,26.461644],"type":"Point"}
}