{
  "type": "Feature",
  "properties": {
    "iso:country":"US",
    "sg:address":"215 5th St",
    "sg:city":"West Palm Beach",
    "sg:classifiers":[
        {
            "category":"Professional",
            "subcategory":"Accounting & Tax Preparation",
            "type":"Services"
        }
    ],
    "sg:phone":"+1 561 659 3066",
    "sg:postcode":"33401",
    "sg:province":"FL",
    "sg:tags":[
        "accountant"
    ],
    "wof:name":"Payne & Mitchell",
    "wof:placetype":"venue"
},
  "geometry": {"coordinates":[-80.051006,26.717922],"type":"Point"}
}