{
  "type": "Feature",
  "properties": {
    "addr:full":"450 Famu Way Tallahassee FL 32301",
    "addr:housenumber":"450",
    "addr:postcode":"32301",
    "addr:street":"Famu Way",
    "iso:country":"US",
    "sg:address":"450 Famu Way",
    "sg:city":"Tallahassee",
    "sg:classifiers":[
        {
            "category":"Building & Trades",
            "subcategory":"Construction",
            "type":"Services"
        }
    ],
    "sg:phone":"+1 850 671 5646",
    "sg:postcode":"32301",
    "sg:province":"FL",
    "sg:tags":[
        "painter"
    ],
    "wof:name":"John The Painter Inc",
    "wof:placetype":"venue"
},
  "geometry": {"coordinates":[-84.28878899999999,30.431893],"type":"Point"}
}