{
  "type": "Feature",
  "properties": {
    "iso:country":"US",
    "sg:address":"1748 Broken Bow Ct",
    "sg:city":"Jacksonville",
    "sg:classifiers":[
        {
            "category":"Retail",
            "subcategory":"Auto Repair",
            "type":"Services"
        }
    ],
    "sg:phone":"+1 904 642 0163",
    "sg:postcode":"32225",
    "sg:province":"FL",
    "sg:tags":[
        "general"
    ],
    "wof:name":"Bruces Mobile Car Care",
    "wof:placetype":"venue"
},
  "geometry": {"coordinates":[-81.475345,30.357268],"type":"Point"}
}