{
  "type": "Feature",
  "properties": {
    "iso:country":"US",
    "sg:address":"37350 US Hwy 19 N",
    "sg:city":"Palm Harbor",
    "sg:classifiers":[
        {
            "category":"Real Estate",
            "subcategory":"Developer",
            "type":"Services"
        }
    ],
    "sg:phone":"+1 727 937 4560",
    "sg:postcode":"34684",
    "sg:province":"FL",
    "sg:tags":[
        "mobile",
        "home"
    ],
    "wof:name":"Tarpon Lakeview Mobile Home Pk",
    "wof:placetype":"venue"
},
  "geometry": {"coordinates":[-82.739895,28.110781],"type":"Point"}
}