{
  "type": "Feature",
  "properties": {
    "addr:full":"1601 E 4th Ave Tampa FL 33605",
    "addr:housenumber":"1601",
    "addr:postcode":"33605",
    "addr:street":"E 4Th Ave",
    "iso:country":"US",
    "sg:address":"1601 E 4th Ave",
    "sg:city":"Tampa",
    "sg:classifiers":[
        {
            "category":"Building & Trades",
            "subcategory":"Construction",
            "type":"Services"
        }
    ],
    "sg:phone":"+1 813 242 6116",
    "sg:postcode":"33605",
    "sg:province":"FL",
    "wof:name":"Stone Age Pavers Inc",
    "wof:placetype":"venue"
},
  "geometry": {"coordinates":[-82.440471,27.958116],"type":"Point"}
}