{
  "type": "Feature",
  "properties": {
    "iso:country":"US",
    "sg:address":"13790 Coconut Ave",
    "sg:city":"North Palm Beach",
    "sg:classifiers":[
        {
            "category":"Building & Trades",
            "subcategory":"Construction",
            "type":"Services"
        }
    ],
    "sg:phone":"+1 561 626 1023",
    "sg:postcode":"33408",
    "sg:province":"FL",
    "sg:tags":[
        "house"
    ],
    "wof:name":"Al Montana Builders",
    "wof:placetype":"venue"
},
  "geometry": {"coordinates":[-80.05794,26.879111],"type":"Point"}
}