{
  "type": "Feature",
  "properties": {
    "iso:country":"US",
    "sg:address":"4101 Vinkemulder Rd",
    "sg:city":"Coconut Creek",
    "sg:classifiers":[
        {
            "category":"Building & Trades",
            "subcategory":"Cleaning & Sanitation",
            "type":"Services"
        },
        {
            "category":"Building & Trades",
            "subcategory":"Landscaping Services",
            "type":"Services"
        }
    ],
    "sg:phone":"+1 954 973 3333",
    "sg:postcode":"33073",
    "sg:province":"FL",
    "sg:tags":[
        "landscape",
        "maintenance",
        "contractor"
    ],
    "wof:name":"Complete Property Maintenance",
    "wof:placetype":"venue"
},
  "geometry": {"coordinates":[-80.18177,26.285947],"type":"Point"}
}