{
  "type": "Feature",
  "properties": {
    "addr:full":"2301 NW 34th Ave Fort Lauderdale FL 33311",
    "addr:housenumber":"2301",
    "addr:postcode":"33311",
    "addr:street":"Nw 34Th Ave",
    "iso:country":"US",
    "sg:address":"2301 NW 34th Ave",
    "sg:city":"Fort Lauderdale",
    "sg:classifiers":[
        {
            "category":"Personal",
            "subcategory":"Beauty Salon",
            "type":"Services"
        }
    ],
    "sg:phone":"+1 954 972 0011",
    "sg:postcode":"33311",
    "sg:province":"FL",
    "sg:tags":[
        "shop"
    ],
    "wof:name":"Touch of Class Unisex Salon",
    "wof:placetype":"venue"
},
  "geometry": {"coordinates":[-80.192961,26.156093],"type":"Point"}
}