{
  "type": "Feature",
  "properties": {
    "iso:country":"US",
    "sg:address":"6551 N Palafox St",
    "sg:city":"Pensacola",
    "sg:classifiers":[
        {
            "category":"Organizations",
            "subcategory":"Labor Organization",
            "type":"Services"
        }
    ],
    "sg:phone":"+1 850 476 2906",
    "sg:postcode":"32503",
    "sg:province":"FL",
    "wof:name":"Escambia Education Association",
    "wof:placetype":"venue"
},
  "geometry": {"coordinates":[-87.25038600000001,30.48792],"type":"Point"}
}