{
  "type": "Feature",
  "properties": {
    "iso:country":"US",
    "sg:address":"718 King St",
    "sg:city":"Cocoa",
    "sg:classifiers":[
        {
            "category":"Retail",
            "subcategory":"Auto Repair",
            "type":"Services"
        }
    ],
    "sg:phone":"+1 321 636 8646",
    "sg:postcode":"32922",
    "sg:province":"FL",
    "sg:tags":[
        "repairing",
        "automobile",
        "radiator"
    ],
    "wof:name":"Cocoa Radiator Inc",
    "wof:placetype":"venue"
},
  "geometry": {"coordinates":[-80.738432,28.355708],"type":"Point"}
}