{
  "type": "Feature",
  "properties": {
    "iso:country":"US",
    "sg:address":"3993 Tyrone Blvd N",
    "sg:city":"St Petersburg",
    "sg:classifiers":[
        {
            "category":"Shopping",
            "type":"Retail Goods"
        }
    ],
    "sg:phone":"+1 727 381 2144",
    "sg:postcode":"33709",
    "sg:province":"FL",
    "sg:tags":[
        "art",
        "gallery",
        "merchandise",
        "dealer"
    ],
    "wof:name":"Art Mart",
    "wof:placetype":"venue"
},
  "geometry": {"coordinates":[-82.750147,27.80679],"type":"Point"}
}