{
  "type": "Feature",
  "properties": {
    "addr:full":"20437 State Rd 7 Boca Raton FL 33498",
    "addr:housenumber":"20437",
    "addr:postcode":"33498",
    "addr:street":"State Rd 7",
    "iso:country":"US",
    "sg:address":"20437 State Rd 7",
    "sg:city":"Boca Raton",
    "sg:classifiers":[
        {
            "category":"Shopping",
            "type":"Retail Goods"
        }
    ],
    "sg:phone":"+1 561 558 9580",
    "sg:postcode":"33498",
    "sg:province":"FL",
    "sg:tags":[
        "religious",
        "merchandise"
    ],
    "wof:name":"Yiddish Keit",
    "wof:placetype":"venue"
},
  "geometry": {"coordinates":[-80.203557,26.370285],"type":"Point"}
}