{
  "type": "Feature",
  "properties": {
    "iso:country":"US",
    "sg:address":"12550 Biscayne Blvd Ste 602",
    "sg:city":"Miami",
    "sg:classifiers":[
        {
            "category":"Real Estate",
            "subcategory":"Real Estate Agent",
            "type":"Services"
        }
    ],
    "sg:phone":"+1 305 571 8530",
    "sg:postcode":"33181",
    "sg:province":"FL",
    "sg:website":"www.plumpads.com",
    "wof:name":"Plum Pads Premium Properties",
    "wof:placetype":"venue"
},
  "geometry": {"coordinates":[-80.163911,25.89227],"type":"Point"}
}