{
  "type": "Feature",
  "properties": {
    "iso:country":"US",
    "sg:address":"1140 Motel Dr",
    "sg:city":"Chipley",
    "sg:classifiers":[
        {
            "category":"Travel",
            "subcategory":"Hotels & Motels",
            "type":"Entertainment"
        }
    ],
    "sg:phone":"+1 850 415 1111",
    "sg:postcode":"32428",
    "sg:province":"FL",
    "sg:tags":[
        "lodging"
    ],
    "sg:website":"http://www.comfortinn.com/hotel-chipley-florida-FL751",
    "wof:name":"Comfort Inn & Suites",
    "wof:placetype":"venue"
},
  "geometry": {"coordinates":[-85.551635,30.749918],"type":"Point"}
}