{
  "type": "Feature",
  "properties": {
    "iso:country":"US",
    "sg:address":"151 Wymore Rd Ste 2000",
    "sg:city":"Altamonte Springs",
    "sg:classifiers":[
        {
            "category":"Education",
            "subcategory":"University",
            "type":"Public Place"
        }
    ],
    "sg:phone":"+1 407 774 6200",
    "sg:postcode":"32714",
    "sg:province":"FL",
    "sg:tags":[
        "college"
    ],
    "sg:website":"www.mountainstate.edu/orlando",
    "wof:name":"Mountain State University Orlando",
    "wof:placetype":"venue"
},
  "geometry": {"coordinates":[-81.390191,28.660498],"type":"Point"}
}