{
  "type": "Feature",
  "properties": {
    "addr:full":"1410 NW 78 AVENUE Miami FL 33126",
    "addr:housenumber":"1410",
    "addr:postcode":"33126",
    "addr:street":"Nw 78 Avenue",
    "iso:country":"US",
    "sg:address":"1410 NW 78 AVENUE",
    "sg:city":"Miami",
    "sg:classifiers":[
        {
            "category":"Insurance",
            "subcategory":"Hazard Insurance",
            "type":"Services"
        }
    ],
    "sg:phone":"+1 305 591 4740",
    "sg:postcode":"33126",
    "sg:province":"FL",
    "sg:website":"www.progressive.com",
    "wof:name":"Progressive Insurance Claims Concierge",
    "wof:placetype":"venue"
},
  "geometry": {"coordinates":[-80.322689,25.78689],"type":"Point"}
}