{
  "type": "Feature",
  "properties": {
    "iso:country":"US",
    "sg:address":"5507 SW 25th Ct",
    "sg:city":"Hollywood",
    "sg:classifiers":[
        {
            "category":"Retail",
            "subcategory":"Auto Repair",
            "type":"Services"
        }
    ],
    "sg:phone":"+1 954 986 6998",
    "sg:postcode":"33023",
    "sg:province":"FL",
    "sg:tags":[
        "repairing",
        "automobile"
    ],
    "wof:name":"Anderson's Automotive",
    "wof:placetype":"venue"
},
  "geometry": {"coordinates":[-80.19843899999999,25.987275],"type":"Point"}
}