{
  "type": "Feature",
  "properties": {
    "addr:full":"1342 San Felepe Ct Winter Springs FL 32708",
    "addr:housenumber":"1342",
    "addr:postcode":"32708",
    "addr:street":"San Felepe Ct",
    "iso:country":"US",
    "sg:address":"1342 San Felepe Ct",
    "sg:city":"Winter Springs",
    "sg:classifiers":[
        {
            "category":"Building & Trades",
            "subcategory":"Construction",
            "type":"Services"
        }
    ],
    "sg:phone":"+1 407 709 3246",
    "sg:postcode":"32708",
    "sg:province":"FL",
    "sg:tags":[
        "coping",
        "plastering",
        "tiling",
        "pool",
        "swimming"
    ],
    "wof:name":"Fiber Tech Of Central Fl Inc",
    "wof:placetype":"venue"
},
  "geometry": {"coordinates":[-81.26181099999999,28.653697],"type":"Point"}
}