{
  "type": "Feature",
  "properties": {
    "iso:country":"US",
    "sg:address":"20287 Ladner Ave",
    "sg:city":"Port Charlotte",
    "sg:classifiers":[
        {
            "category":"Recreation",
            "type":"Entertainment"
        }
    ],
    "sg:phone":"+1 941 626 6055",
    "sg:postcode":"33954",
    "sg:province":"FL",
    "sg:tags":[
        "guide"
    ],
    "wof:name":"All American Fishing Charters",
    "wof:placetype":"venue"
},
  "geometry": {"coordinates":[-82.113974,27.019387],"type":"Point"}
}