{
  "type": "Feature",
  "properties": {
    "iso:country":"US",
    "sg:address":"540 N Maitland Ave",
    "sg:city":"Maitland",
    "sg:classifiers":[
        {
            "category":"Education",
            "subcategory":"Dance Studio",
            "type":"Public Place"
        }
    ],
    "sg:phone":"+1 407 599 5560",
    "sg:postcode":"32751",
    "sg:province":"FL",
    "sg:website":"www.colbycenter.com",
    "wof:name":"Colby Center For Dance",
    "wof:placetype":"venue"
},
  "geometry": {"coordinates":[-81.36555300000001,28.632686],"type":"Point"}
}