{
  "type": "Feature",
  "properties": {
    "addr:full":"3900 75th St W Bradenton FL 34209",
    "addr:housenumber":"3900",
    "addr:postcode":"34209",
    "addr:street":"75Th St W",
    "iso:country":"US",
    "sg:address":"3900 75th St W",
    "sg:city":"Bradenton",
    "sg:classifiers":[
        {
            "category":"Real Estate",
            "subcategory":"Real Estate Services",
            "type":"Services"
        },
        {
            "category":"Real Estate",
            "subcategory":"Real Estate Operator",
            "type":"Services"
        }
    ],
    "sg:phone":"+1 941 792 8333",
    "sg:postcode":"34209",
    "sg:province":"FL",
    "sg:tags":[
        "vacancy",
        "apartment",
        "rental",
        "finder",
        "listing"
    ],
    "sg:website":"http://www.colonialprop.com",
    "wof:name":"Colonial Village At Palm Sola",
    "wof:placetype":"venue"
},
  "geometry": {"coordinates":[-82.636841,27.466535],"type":"Point"}
}