{
  "type": "Feature",
  "properties": {
    "iso:country":"US",
    "sg:address":"8651 Treasure Cay Ln",
    "sg:city":"Orlando",
    "sg:classifiers":[
        {
            "category":"Travel",
            "subcategory":"Hotels & Motels",
            "type":"Entertainment"
        }
    ],
    "sg:phone":"+1 407 238 2300",
    "sg:postcode":"32836",
    "sg:province":"FL",
    "sg:tags":[
        "resort"
    ],
    "sg:website":"www.cypresspointe.net",
    "wof:name":"Cypress Pointe Resort Hoa",
    "wof:placetype":"venue"
},
  "geometry": {"coordinates":[-81.50239500000001,28.390147],"type":"Point"}
}