{
  "type": "Feature",
  "properties": {
    "addr:full":"1520 Royal Palm Square Blvd Fort Myers FL 33919",
    "addr:housenumber":"1520",
    "addr:postcode":"33919",
    "addr:street":"Royal Palm Square Blvd",
    "iso:country":"US",
    "sg:address":"1520 Royal Palm Square Blvd",
    "sg:city":"Fort Myers",
    "sg:classifiers":[
        {
            "category":"Professional",
            "subcategory":"Engineering",
            "type":"Services"
        }
    ],
    "sg:phone":"+1 239 936 0789",
    "sg:postcode":"33919",
    "sg:province":"FL",
    "sg:tags":[
        "engineer"
    ],
    "wof:name":"HSA Engineers & Scientists",
    "wof:placetype":"venue"
},
  "geometry": {"coordinates":[-81.885408,26.594124],"type":"Point"}
}