{
  "type": "Feature",
  "properties": {
    "addr:full":"421 Linden Ln Lake Wales FL 33853",
    "addr:housenumber":"421",
    "addr:postcode":"33853",
    "addr:street":"Linden Ln",
    "iso:country":"US",
    "sg:address":"421 Linden Ln",
    "sg:city":"Lake Wales",
    "sg:classifiers":[
        {
            "category":"Health Services",
            "subcategory":"Doctor",
            "type":"Services"
        }
    ],
    "sg:phone":"+1 863 421 7600",
    "sg:postcode":"33853",
    "sg:province":"FL",
    "sg:tags":[
        "physician",
        "surgeon"
    ],
    "wof:name":"Heart Of Florida Ob/Gyn",
    "wof:placetype":"venue"
},
  "geometry": {"coordinates":[-81.56392700000001,27.896229],"type":"Point"}
}