{
  "type": "Feature",
  "properties": {
    "addr:full":"750 35th Ave SW Vero Beach FL 32968",
    "addr:housenumber":"750",
    "addr:postcode":"32968",
    "addr:street":"35Th Ave Sw",
    "iso:country":"US",
    "sg:address":"750 35th Ave SW",
    "sg:city":"Vero Beach",
    "sg:classifiers":[
        {
            "category":"Retail",
            "subcategory":"Auto Repair",
            "type":"Services"
        }
    ],
    "sg:phone":"+1 772 567 6195",
    "sg:postcode":"32968",
    "sg:province":"FL",
    "sg:tags":[
        "general"
    ],
    "wof:name":"Stepanek S Auto Repair",
    "wof:placetype":"venue"
},
  "geometry": {"coordinates":[-80.422844,27.589957],"type":"Point"}
}