{
  "type": "Feature",
  "properties": {
    "iso:country":"US",
    "sg:address":"20047 NW 85th Ave",
    "sg:city":"Hialeah",
    "sg:classifiers":[
        {
            "category":"Wholesale",
            "subcategory":"Durable Goods & Equipment",
            "type":"Manufacturing & Wholesale Goods"
        }
    ],
    "sg:phone":"+1 305 829 3728",
    "sg:postcode":"33015",
    "sg:province":"FL",
    "wof:name":"Inexco Enterprises",
    "wof:placetype":"venue"
},
  "geometry": {"coordinates":[-80.34041000000001,25.955259],"type":"Point"}
}