{
  "type": "Feature",
  "properties": {
    "addr:full":"8481 S John Young Pkwy Orlando FL 32819",
    "addr:housenumber":"8481",
    "addr:postcode":"32819",
    "addr:street":"S John Young Pkwy",
    "iso:country":"US",
    "sg:address":"8481 S John Young Pkwy",
    "sg:city":"Orlando",
    "sg:classifiers":[
        {
            "category":"Banks & Credit Unions",
            "subcategory":"Bank",
            "type":"Services"
        }
    ],
    "sg:phone":"+1 407 352 9098",
    "sg:postcode":"32819",
    "sg:province":"FL",
    "sg:tags":[
        "personal",
        "loan",
        "institution"
    ],
    "wof:name":"Lendmark Financial Services",
    "wof:placetype":"venue"
},
  "geometry": {"coordinates":[-81.427511,28.443772],"type":"Point"}
}