{
  "type": "Feature",
  "properties": {
    "iso:country":"US",
    "sg:address":"5216 US Hwy 98",
    "sg:city":"Lakeland",
    "sg:classifiers":[
        {
            "category":"Personal",
            "type":"Services"
        }
    ],
    "sg:phone":"+1 863 853 2656",
    "sg:postcode":"33809",
    "sg:province":"FL",
    "sg:tags":[
        "therapist",
        "massage"
    ],
    "wof:name":"Tranquil Body",
    "wof:placetype":"venue"
},
  "geometry": {"coordinates":[-81.973817,28.108451],"type":"Point"}
}