{
  "type": "Feature",
  "properties": {
    "addr:full":"744 NE 19th Ave Fort Lauderdale FL 33304",
    "addr:housenumber":"744",
    "addr:postcode":"33304",
    "addr:street":"Ne 19Th Ave",
    "iso:country":"US",
    "sg:address":"744 NE 19th Ave",
    "sg:city":"Fort Lauderdale",
    "sg:classifiers":[
        {
            "category":"Real Estate",
            "subcategory":"Real Estate Operator",
            "type":"Services"
        }
    ],
    "sg:phone":"+1 954 522 1615",
    "sg:postcode":"33304",
    "sg:province":"FL",
    "sg:tags":[
        "apartment"
    ],
    "wof:name":"Harry R Lorenz",
    "wof:placetype":"venue"
},
  "geometry": {"coordinates":[-80.12091100000001,26.133979],"type":"Point"}
}