{
  "type": "Feature",
  "properties": {
    "iso:country":"US",
    "sg:address":"67 Calcutta Ct",
    "sg:city":"Indialantic",
    "sg:classifiers":[
        {
            "category":"Food & Beverages",
            "subcategory":"Specialty",
            "type":"Retail Goods"
        }
    ],
    "sg:phone":"+1 321 777 1260",
    "sg:postcode":"32903",
    "sg:province":"FL",
    "wof:name":"A T Naturals Inc",
    "wof:placetype":"venue"
},
  "geometry": {"coordinates":[-80.58547900000001,28.13628],"type":"Point"}
}