{
  "type": "Feature",
  "properties": {
    "iso:country":"US",
    "sg:address":"10701 Snug Harbor Rd NE",
    "sg:city":"St Petersburg",
    "sg:classifiers":[
        {
            "category":"Freight",
            "type":"Transportation"
        }
    ],
    "sg:phone":"+1 727 579 4795",
    "sg:postcode":"33702",
    "sg:province":"FL",
    "sg:tags":[
        "mover"
    ],
    "wof:name":"Mini Moves Of St Petersburg",
    "wof:placetype":"venue"
},
  "geometry": {"coordinates":[-82.618561,27.869386],"type":"Point"}
}