{
  "type": "Feature",
  "properties": {
    "iso:country":"US",
    "sg:address":"5140 Coconut Creek Pkwy",
    "sg:city":"Pompano Beach",
    "sg:classifiers":[
        {
            "category":"Professional",
            "subcategory":"Lawyer & Legal Services",
            "type":"Services"
        }
    ],
    "sg:phone":"+1 954 978 2488",
    "sg:postcode":"33063",
    "sg:province":"FL",
    "wof:name":"Kohan & Ew J PA",
    "wof:placetype":"venue"
},
  "geometry": {"coordinates":[-80.19968,26.244389],"type":"Point"}
}