{
  "type": "Feature",
  "properties": {
    "iso:country":"US",
    "sg:address":"1906 Municipal Ln",
    "sg:city":"Melbourne",
    "sg:classifiers":[
        {
            "category":"Personal",
            "subcategory":"Beauty Salon",
            "type":"Services"
        }
    ],
    "sg:phone":"+1 321 728 1010",
    "sg:postcode":"32901",
    "sg:province":"FL",
    "wof:name":"Judi's Hair Styling",
    "wof:placetype":"venue"
},
  "geometry": {"coordinates":[-80.606105,28.078489],"type":"Point"}
}