{
  "type": "Feature",
  "properties": {
    "iso:country":"US",
    "sg:address":"424 S Washington Blvd",
    "sg:city":"Sarasota",
    "sg:classifiers":[
        {
            "category":"Retail",
            "subcategory":"Auto Repair",
            "type":"Services"
        }
    ],
    "sg:phone":"+1 941 951 7888",
    "sg:postcode":"34236",
    "sg:province":"FL",
    "sg:tags":[
        "body",
        "special",
        "mfg"
    ],
    "wof:name":"Signs Now",
    "wof:placetype":"venue"
},
  "geometry": {"coordinates":[-82.531047,27.333355],"type":"Point"}
}