{
  "type": "Feature",
  "properties": {
    "addr:full":"246 3rd St Neptune Beach FL 32266",
    "addr:housenumber":"246",
    "addr:postcode":"32266",
    "addr:street":"3Rd St",
    "iso:country":"US",
    "sg:address":"246 3rd St",
    "sg:city":"Neptune Beach",
    "sg:classifiers":[
        {
            "category":"Health Services",
            "subcategory":"Health Practitioner",
            "type":"Services"
        }
    ],
    "sg:phone":"+1 904 249 3755",
    "sg:postcode":"32266",
    "sg:province":"FL",
    "wof:name":"Patricia A Stacey Msw Lcsw",
    "wof:placetype":"venue"
},
  "geometry": {"coordinates":[-81.398054,30.323032],"type":"Point"}
}