{
  "type": "Feature",
  "properties": {
    "iso:country":"US",
    "sg:address":"2554 N Miami Ave",
    "sg:city":"Miami",
    "sg:classifiers":[
        {
            "category":"Shopping",
            "subcategory":"Shoes",
            "type":"Retail Goods"
        }
    ],
    "sg:phone":"+1 305 792 6911",
    "sg:postcode":"33127",
    "sg:province":"FL",
    "wof:name":"Shoe B Doo Inc",
    "wof:placetype":"venue"
},
  "geometry": {"coordinates":[-80.19508500000001,25.801195],"type":"Point"}
}