{
  "type": "Feature",
  "properties": {
    "iso:country":"US",
    "sg:address":"11096 NW 114th St",
    "sg:city":"Chiefland",
    "sg:classifiers":[
        {
            "category":"Professional",
            "subcategory":"Computer Services",
            "type":"Services"
        }
    ],
    "sg:phone":"+1 352 490 0980",
    "sg:postcode":"32626",
    "sg:province":"FL",
    "sg:tags":[
        "isp",
        "provider",
        "internet"
    ],
    "wof:name":"Kathy Hughes Dsl Line",
    "wof:placetype":"venue"
},
  "geometry": {"coordinates":[-82.95756,29.49477],"type":"Point"}
}