{
  "type": "Feature",
  "properties": {
    "iso:country":"US",
    "sg:address":"5139 W Idlewild Ave",
    "sg:city":"Tampa",
    "sg:classifiers":[
        {
            "category":"Professional",
            "subcategory":"Advertising",
            "type":"Services"
        }
    ],
    "sg:phone":"+1 813 254 6881",
    "sg:postcode":"33634",
    "sg:province":"FL",
    "sg:tags":[
        "distribution"
    ],
    "wof:name":"Zoriel Distributors",
    "wof:placetype":"venue"
},
  "geometry": {"coordinates":[-82.53165799999999,28.002113],"type":"Point"}
}