{
  "type": "Feature",
  "properties": {
    "iso:country":"US",
    "sg:address":"2700 Croton Rd",
    "sg:city":"Melbourne",
    "sg:classifiers":[
        {
            "category":"Real Estate",
            "subcategory":"Real Estate Operator",
            "type":"Services"
        }
    ],
    "sg:phone":"+1 321 242 0613",
    "sg:postcode":"32935",
    "sg:province":"FL",
    "sg:tags":[
        "building",
        "apartment"
    ],
    "wof:name":"Courtyard On The Green",
    "wof:placetype":"venue"
},
  "geometry": {"coordinates":[-80.655096,28.146867],"type":"Point"}
}