{
  "type": "Feature",
  "properties": {
    "addr:full":"1717 W Flagler St Miami FL 33135",
    "addr:housenumber":"1717",
    "addr:postcode":"33135",
    "addr:street":"W Flagler St",
    "iso:country":"US",
    "sg:address":"1717 W Flagler St",
    "sg:city":"Miami",
    "sg:classifiers":[
        {
            "category":"Shopping",
            "subcategory":"Jewelry",
            "type":"Retail Goods"
        }
    ],
    "sg:phone":"+1 305 649 7740",
    "sg:postcode":"33135",
    "sg:province":"FL",
    "sg:tags":[
        "jeweler"
    ],
    "wof:name":"LA Frontera Jewelry & Pawn",
    "wof:placetype":"venue"
},
  "geometry": {"coordinates":[-80.223164,25.773066],"type":"Point"}
}