{
  "type": "Feature",
  "properties": {
    "iso:country":"US",
    "sg:address":"1507 SE 28th Ct",
    "sg:city":"Ocala",
    "sg:classifiers":[
        {
            "category":"Food & Beverages",
            "subcategory":"Fruits & Vegetables",
            "type":"Retail Goods"
        }
    ],
    "sg:phone":"+1 352 624 0495",
    "sg:postcode":"34471",
    "sg:province":"FL",
    "sg:tags":[
        "produce"
    ],
    "wof:name":"Fresh Planet Produce Inc",
    "wof:placetype":"venue"
},
  "geometry": {"coordinates":[-82.09848100000001,29.174231],"type":"Point"}
}