{
  "type": "Feature",
  "properties": {
    "iso:country":"US",
    "sg:address":"6624 Beamer Way",
    "sg:city":"Orlando",
    "sg:classifiers":[
        {
            "category":"Home & Garden",
            "subcategory":"Building Materials",
            "type":"Retail Goods"
        },
        {
            "category":"Retail",
            "subcategory":"Auto Repair",
            "type":"Services"
        }
    ],
    "sg:phone":"+1 407 249 2125",
    "sg:postcode":"32807",
    "sg:province":"FL",
    "sg:tags":[
        "door",
        "general"
    ],
    "wof:name":"Chris Berrian Garage Doors Inc",
    "wof:placetype":"venue"
},
  "geometry": {"coordinates":[-81.29413099999999,28.542297],"type":"Point"}
}