{
  "type": "Feature",
  "properties": {
    "iso:country":"US",
    "sg:address":"3940 NW 94th Ave",
    "sg:city":"Hollywood",
    "sg:classifiers":[
        {
            "category":"Sports & Exercise",
            "subcategory":"Gym",
            "type":"Entertainment"
        }
    ],
    "sg:phone":"+1 954 430 8263",
    "sg:postcode":"33024",
    "sg:province":"FL",
    "sg:tags":[
        "fitness",
        "physical",
        "facility"
    ],
    "wof:name":"Emerald Fitness Clothes Inc",
    "wof:placetype":"venue"
},
  "geometry": {"coordinates":[-80.27207900000001,26.041175],"type":"Point"}
}