{
  "type": "Feature",
  "properties": {
    "iso:country":"US",
    "sg:address":"605 Desoto Ln",
    "sg:city":"Indian Hrbr Bch",
    "sg:classifiers":[
        {
            "category":"Building & Trades",
            "subcategory":"Construction",
            "type":"Services"
        }
    ],
    "sg:phone":"+1 321 536 0850",
    "sg:postcode":"32937",
    "sg:province":"FL",
    "sg:tags":[
        "designer",
        "dealer",
        "pool",
        "swimming"
    ],
    "wof:name":"Spectrum Pools & Spas",
    "wof:placetype":"venue"
},
  "geometry": {"coordinates":[-80.60522899999999,28.164811],"type":"Point"}
}