{
  "type": "Feature",
  "properties": {
    "addr:full":"9005 SW 73rd Pl Miami FL 33176",
    "addr:housenumber":"9005",
    "addr:postcode":"33176",
    "addr:street":"Sw 73Rd Pl",
    "iso:country":"US",
    "sg:address":"9005 SW 73rd Pl",
    "sg:city":"Miami",
    "sg:classifiers":[
        {
            "category":"Restaurant",
            "type":"Food & Drink"
        }
    ],
    "sg:postcode":"33176",
    "sg:province":"FL",
    "wof:name":"Sqt. Cafe",
    "wof:placetype":"venue"
},
  "geometry": {"coordinates":[-80.31403400000001,25.697542],"type":"Point"}
}