{
  "type": "Feature",
  "properties": {
    "iso:country":"US",
    "sg:address":"26 Bellemeade Cir",
    "sg:city":"Largo",
    "sg:classifiers":[
        {
            "category":"Building & Trades",
            "subcategory":"Construction",
            "type":"Services"
        }
    ],
    "sg:phone":"+1 727 584 1826",
    "sg:postcode":"33770",
    "sg:province":"FL",
    "sg:tags":[
        "house"
    ],
    "wof:name":"Hassell Free Remodeling",
    "wof:placetype":"venue"
},
  "geometry": {"coordinates":[-82.801788,27.920769],"type":"Point"}
}