{
  "type": "Feature",
  "properties": {
    "iso:country":"US",
    "sg:address":"1402 9th Ave E",
    "sg:city":"Bradenton",
    "sg:classifiers":[
        {
            "category":"Building & Trades",
            "subcategory":"Construction",
            "type":"Services"
        }
    ],
    "sg:phone":"+1 941 748 7815",
    "sg:postcode":"34208",
    "sg:province":"FL",
    "sg:tags":[
        "windows",
        "carpentry",
        "contractor"
    ],
    "wof:name":"Raydon Window Co",
    "wof:placetype":"venue"
},
  "geometry": {"coordinates":[-82.547567,27.491448],"type":"Point"}
}