{
  "type": "Feature",
  "properties": {
    "addr:full":"7660 Hooper Rd West Palm Beach FL 33411",
    "addr:housenumber":"7660",
    "addr:postcode":"33411",
    "addr:street":"Hooper Rd",
    "iso:country":"US",
    "sg:address":"7660 Hooper Rd",
    "sg:city":"West Palm Beach",
    "sg:classifiers":[
        {
            "category":"Retail",
            "subcategory":"Auto Repair",
            "type":"Services"
        }
    ],
    "sg:phone":"+1 561 793 9090",
    "sg:postcode":"33411",
    "sg:province":"FL",
    "sg:tags":[
        "repairing",
        "tire"
    ],
    "wof:name":"Liberty Tires",
    "wof:placetype":"venue"
},
  "geometry": {"coordinates":[-80.16706000000001,26.680733],"type":"Point"}
}