{
  "type": "Feature",
  "properties": {
    "addr:full":"627 Lemon St Port Orange FL 32127",
    "addr:housenumber":"627",
    "addr:postcode":"32127",
    "addr:street":"Lemon St",
    "iso:country":"US",
    "sg:address":"627 Lemon St",
    "sg:city":"Port Orange",
    "sg:classifiers":[
        {
            "category":"Retail",
            "subcategory":"Auto Repair",
            "type":"Services"
        }
    ],
    "sg:phone":"+1 386 322 6266",
    "sg:postcode":"32127",
    "sg:province":"FL",
    "sg:tags":[
        "repairing",
        "automobile"
    ],
    "wof:name":"E R Auto Tech",
    "wof:placetype":"venue"
},
  "geometry": {"coordinates":[-80.99261300000001,29.141962],"type":"Point"}
}