{
  "type": "Feature",
  "properties": {
    "iso:country":"US",
    "sg:address":"10021 NW 27th Ter",
    "sg:city":"Doral",
    "sg:classifiers":[
        {
            "category":"Shopping",
            "subcategory":"Tobacco",
            "type":"Retail Goods"
        }
    ],
    "sg:phone":"+1 305 594 5767",
    "sg:postcode":"33172",
    "sg:province":"FL",
    "sg:tags":[
        "cigarette",
        "cigar",
        "dealer"
    ],
    "wof:name":"Kendall Tobacco",
    "wof:placetype":"venue"
},
  "geometry": {"coordinates":[-80.360955,25.79958],"type":"Point"}
}