{
  "type": "Feature",
  "properties": {
    "addr:full":"1109 3rd Ave N Lake Worth FL 33460",
    "addr:housenumber":"1109",
    "addr:postcode":"33460",
    "addr:street":"3Rd Ave N",
    "iso:country":"US",
    "sg:address":"1109 3rd Ave N",
    "sg:city":"Lake Worth",
    "sg:classifiers":[
        {
            "category":"Autos & Motor Vehicles",
            "subcategory":"Auto Supplies",
            "type":"Retail Goods"
        }
    ],
    "sg:phone":"+1 561 662 5115",
    "sg:postcode":"33460",
    "sg:province":"FL",
    "sg:tags":[
        "automobile",
        "stereo",
        "radio"
    ],
    "wof:name":"Raydio Ray's Inc",
    "wof:placetype":"venue"
},
  "geometry": {"coordinates":[-80.060154,26.619079],"type":"Point"}
}