{
  "type": "Feature",
  "properties": {
    "iso:country":"US",
    "sg:address":"20093 E Pennsylvania Ave",
    "sg:city":"Dunnellon",
    "sg:classifiers":[
        {
            "category":"Health Services",
            "subcategory":"Optometrist",
            "type":"Services"
        }
    ],
    "sg:phone":"+1 352 489 2438",
    "sg:postcode":"34432",
    "sg:province":"FL",
    "wof:name":"John E Creamer OD",
    "wof:placetype":"venue"
},
  "geometry": {"coordinates":[-82.455068,29.049552],"type":"Point"}
}