{
  "type": "Feature",
  "properties": {
    "addr:full":"5475 Groves Ct Pensacola FL 32504",
    "addr:housenumber":"5475",
    "addr:postcode":"32504",
    "addr:street":"Groves Ct",
    "iso:country":"US",
    "sg:address":"5475 Groves Ct",
    "sg:city":"Pensacola",
    "sg:classifiers":[
        {
            "category":"Home & Garden",
            "subcategory":"Carpets & Floor Coverings",
            "type":"Retail Goods"
        }
    ],
    "sg:phone":"+1 850 477 4506",
    "sg:postcode":"32504",
    "sg:province":"FL",
    "wof:name":"Haworth Floor Coverings",
    "wof:placetype":"venue"
},
  "geometry": {"coordinates":[-87.173343,30.484502],"type":"Point"}
}