{
  "type": "Feature",
  "properties": {
    "iso:country":"US",
    "sg:address":"741 Front St Ste 310",
    "sg:city":"Celebration",
    "sg:classifiers":[
        {
            "category":"Health Services",
            "subcategory":"Dentist",
            "type":"Services"
        }
    ],
    "sg:phone":"+1 407 566 2431",
    "sg:postcode":"34747",
    "sg:province":"FL",
    "wof:name":"Celebration Dental Group",
    "wof:placetype":"venue"
},
  "geometry": {"coordinates":[-81.54055,28.318007],"type":"Point"}
}