{
  "type": "Feature",
  "properties": {
    "iso:country":"US",
    "sg:address":"14301 SW 119th Ave",
    "sg:city":"Miami",
    "sg:classifiers":[
        {
            "category":"Organizations",
            "subcategory":"Religious Organization",
            "type":"Services"
        }
    ],
    "sg:phone":"+1 305 234 9600",
    "sg:postcode":"33186",
    "sg:province":"FL",
    "sg:tags":[
        "churches-community",
        "church"
    ],
    "sg:website":"www.miamivineyard.com",
    "wof:name":"Miami Vineyard Community Church",
    "wof:placetype":"venue"
},
  "geometry": {"coordinates":[-80.386703,25.6355],"type":"Point"}
}