{
  "type": "Feature",
  "properties": {
    "iso:country":"US",
    "sg:address":"1225 Clearlake Rd",
    "sg:city":"Cocoa",
    "sg:classifiers":[
        {
            "category":"Education",
            "subcategory":"School",
            "type":"Public Place"
        }
    ],
    "sg:phone":"+1 321 633 3660",
    "sg:postcode":"32922",
    "sg:province":"FL",
    "wof:name":"Clearlake Middle School",
    "wof:placetype":"venue"
},
  "geometry": {"coordinates":[-80.755077,28.375719],"type":"Point"}
}