{
  "type": "Feature",
  "properties": {
    "iso:country":"US",
    "sg:address":"7875 Palmer Blvd",
    "sg:city":"Sarasota",
    "sg:classifiers":[
        {
            "category":"Building & Trades",
            "subcategory":"Construction",
            "type":"Services"
        }
    ],
    "sg:phone":"+1 941 377 3958",
    "sg:postcode":"34240",
    "sg:province":"FL",
    "sg:tags":[
        "residential",
        "carpentry",
        "carpenter",
        "contractor"
    ],
    "wof:name":"Richard Zehr Construction Inc",
    "wof:placetype":"venue"
},
  "geometry": {"coordinates":[-82.411317,27.322342],"type":"Point"}
}