{
  "type": "Feature",
  "properties": {
    "iso:country":"US",
    "sg:address":"4162 S Atlantic Ave",
    "sg:city":"New Smyrna Beach",
    "sg:classifiers":[
        {
            "category":"Sports & Exercise",
            "subcategory":"Gym",
            "type":"Entertainment"
        }
    ],
    "sg:phone":"+1 386 445 7193",
    "sg:postcode":"32169",
    "sg:province":"FL",
    "sg:tags":[
        "fitness",
        "physical",
        "facility"
    ],
    "wof:name":"Curves For Women",
    "wof:placetype":"venue"
},
  "geometry": {"coordinates":[-80.87469299999999,29.00147],"type":"Point"}
}