{
  "type": "Feature",
  "properties": {
    "addr:full":"1442 NW 82nd Ave Doral FL 33126",
    "addr:housenumber":"1442",
    "addr:postcode":"33126",
    "addr:street":"Nw 82Nd Ave",
    "iso:country":"US",
    "sg:address":"1442 NW 82nd Ave",
    "sg:city":"Doral",
    "sg:classifiers":[
        {
            "category":"Manufacturing",
            "subcategory":"Metals",
            "type":"Manufacturing & Wholesale Goods"
        }
    ],
    "sg:phone":"+1 305 591 0142",
    "sg:postcode":"33126",
    "sg:province":"FL",
    "sg:tags":[
        "steel",
        "sheet",
        "work-manufacturers",
        "fabricator",
        "mill"
    ],
    "wof:name":"Home & Garden Industries, Inc.",
    "wof:placetype":"venue"
},
  "geometry": {"coordinates":[-80.328768,25.786762],"type":"Point"}
}