{
  "type": "Feature",
  "properties": {
    "iso:country":"US",
    "sg:address":"5303 S Florida Ave",
    "sg:city":"Lakeland",
    "sg:classifiers":[
        {
            "category":"Home & Garden",
            "subcategory":"Furniture",
            "type":"Retail Goods"
        }
    ],
    "sg:phone":"+1 863 644 8311",
    "sg:postcode":"33813",
    "sg:province":"FL",
    "wof:name":"Source Futons & Waterbeds",
    "wof:placetype":"venue"
},
  "geometry": {"coordinates":[-81.964294,27.968472],"type":"Point"}
}