{
  "type": "Feature",
  "properties": {
    "iso:country":"US",
    "sg:address":"650 W Baya Ave",
    "sg:city":"Lake City",
    "sg:classifiers":[
        {
            "category":"Shopping",
            "subcategory":"Pharmacy",
            "type":"Retail Goods"
        }
    ],
    "sg:phone":"+1 386 755 2770",
    "sg:postcode":"32025",
    "sg:province":"FL",
    "wof:name":"Eckerd",
    "wof:placetype":"venue"
},
  "geometry": {"coordinates":[-82.64539000000001,30.18713],"type":"Point"}
}