{
  "type": "Feature",
  "properties": {
    "iso:country":"US",
    "sg:address":"601 Universe Blvd., Suite 203",
    "sg:city":"Jupiter",
    "sg:classifiers":[
        {
            "category":"Health Services",
            "subcategory":"Doctor",
            "type":"Services"
        }
    ],
    "sg:phone":"+1 561 253 3777",
    "sg:postcode":"33458",
    "sg:province":"FL",
    "sg:tags":[
        "physician",
        "surgeon",
        "anesthesiology",
        "surgeons"
    ],
    "wof:name":"Mid Fl Anesthesia Assoc Inc",
    "wof:placetype":"venue"
},
  "geometry": {"coordinates":[-80.103892,26.891272],"type":"Point"}
}