{
  "type": "Feature",
  "properties": {
    "iso:country":"US",
    "sg:address":"101 S Garden Ave",
    "sg:city":"Clearwater",
    "sg:classifiers":[
        {
            "category":"Restaurant",
            "type":"Food & Drink"
        }
    ],
    "sg:phone":"+1 727 443 5351",
    "sg:postcode":"33756",
    "sg:province":"FL",
    "wof:name":"Emily's Restaurant Iv",
    "wof:placetype":"venue"
},
  "geometry": {"coordinates":[-82.798689,27.963876],"type":"Point"}
}