{
  "type": "Feature",
  "properties": {
    "addr:full":"3664 SW Quail Meadow Trl Palm City FL 34990",
    "addr:housenumber":"3664",
    "addr:postcode":"34990",
    "addr:street":"Sw Quail Meadow Trl",
    "iso:country":"US",
    "sg:address":"3664 SW Quail Meadow Trl",
    "sg:city":"Palm City",
    "sg:classifiers":[
        {
            "category":"Banks & Credit Unions",
            "subcategory":"Financial Services",
            "type":"Services"
        }
    ],
    "sg:phone":"+1 772 781 0400",
    "sg:postcode":"34990",
    "sg:province":"FL",
    "sg:tags":[
        "investor"
    ],
    "wof:name":"Caywood Holdings Ltd",
    "wof:placetype":"venue"
},
  "geometry": {"coordinates":[-80.30399,27.170096],"type":"Point"}
}