{
  "type": "Feature",
  "properties": {
    "iso:country":"US",
    "sg:address":"100 S Parsons Ave",
    "sg:city":"Brandon",
    "sg:classifiers":[
        {
            "category":"Manufacturing",
            "subcategory":"Signs",
            "type":"Manufacturing & Wholesale Goods"
        }
    ],
    "sg:phone":"+1 813 684 9979",
    "sg:postcode":"33511",
    "sg:province":"FL",
    "sg:tags":[
        "specialty",
        "mfg"
    ],
    "wof:name":"Brandon Signs Inc",
    "wof:placetype":"venue"
},
  "geometry": {"coordinates":[-82.285798,27.935789],"type":"Point"}
}