{
  "type": "Feature",
  "properties": {
    "addr:full":"412 Palmetto St New Smyrna Beach FL 32168",
    "addr:housenumber":"412",
    "addr:postcode":"32168",
    "addr:street":"Palmetto St",
    "iso:country":"US",
    "sg:address":"412 Palmetto St",
    "sg:city":"New Smyrna Beach",
    "sg:classifiers":[
        {
            "category":"Health Services",
            "subcategory":"Doctor",
            "type":"Services"
        }
    ],
    "sg:phone":"+1 386 427 4752",
    "sg:postcode":"32168",
    "sg:province":"FL",
    "sg:tags":[
        "medical"
    ],
    "wof:name":"M Emdadul Haque MD",
    "wof:placetype":"venue"
},
  "geometry": {"coordinates":[-80.922832,29.020824],"type":"Point"}
}