{
  "type": "Feature",
  "properties": {
    "addr:full":"2608 NW 97th Ave Miami FL 33172",
    "addr:housenumber":"2608",
    "addr:postcode":"33172",
    "addr:street":"Nw 97Th Ave",
    "iso:country":"US",
    "sg:address":"2608 NW 97th Ave",
    "sg:city":"Miami",
    "sg:classifiers":[
        {
            "category":"Insurance",
            "subcategory":"Insurance Agent",
            "type":"Services"
        }
    ],
    "sg:phone":"+1 305 593 0600",
    "sg:postcode":"33172",
    "sg:province":"FL",
    "sg:tags":[
        "broker"
    ],
    "wof:name":"Westland South Insurance Agcy",
    "wof:placetype":"venue"
},
  "geometry": {"coordinates":[-80.35323099999999,25.798307],"type":"Point"}
}