{
  "type": "Feature",
  "properties": {
    "addr:full":"169 Industrial Loop Dr S Orange Park FL 32073",
    "addr:housenumber":"169",
    "addr:postcode":"32073",
    "addr:street":"Industrial Loop Dr S;Park",
    "iso:country":"US",
    "sg:address":"169 Industrial Loop Dr S",
    "sg:city":"Orange Park",
    "sg:classifiers":[
        {
            "category":"Autos & Motor Vehicles",
            "subcategory":"Auto Supplies",
            "type":"Retail Goods"
        }
    ],
    "sg:phone":"+1 904 783 2210",
    "sg:postcode":"32073",
    "sg:province":"FL",
    "wof:name":"Car Quest Auto Parts",
    "wof:placetype":"venue"
},
  "geometry": {"coordinates":[-81.714495,30.179477],"type":"Point"}
}