{
  "type": "Feature",
  "properties": {
    "iso:country":"US",
    "sg:address":"104 Crandon Blvd",
    "sg:city":"Key Biscayne",
    "sg:classifiers":[
        {
            "category":"Building & Trades",
            "subcategory":"Construction",
            "type":"Services"
        }
    ],
    "sg:phone":"+1 305 361 8711",
    "sg:postcode":"33149",
    "sg:province":"FL",
    "sg:tags":[
        "general",
        "contractor"
    ],
    "wof:name":"CDC Builders",
    "wof:placetype":"venue"
},
  "geometry": {"coordinates":[-80.163042,25.697321],"type":"Point"}
}