{
  "type": "Feature",
  "properties": {
    "iso:country":"US",
    "sg:address":"3998 Fau Blvd",
    "sg:city":"Boca Raton",
    "sg:classifiers":[
        {
            "category":"Real Estate",
            "subcategory":"Real Estate Agent",
            "type":"Services"
        }
    ],
    "sg:phone":"+1 561 998 9326",
    "sg:postcode":"33431",
    "sg:province":"FL",
    "sg:tags":[
        "appraiser"
    ],
    "sg:website":"www.adw-appraisers.com",
    "wof:name":"Aucamp Dellenback & Whitney",
    "wof:placetype":"venue"
},
  "geometry": {"coordinates":[-80.097982,26.386107],"type":"Point"}
}