{
  "type": "Feature",
  "properties": {
    "iso:country":"US",
    "sg:address":"21850 N River Rd",
    "sg:city":"Alva",
    "sg:classifiers":[
        {
            "category":"Building & Trades",
            "subcategory":"Construction",
            "type":"Services"
        }
    ],
    "sg:phone":"+1 239 728 3731",
    "sg:postcode":"33920",
    "sg:province":"FL",
    "sg:tags":[
        "concrete",
        "contractor"
    ],
    "wof:name":"Dale Newell Concrete Inc",
    "wof:placetype":"venue"
},
  "geometry": {"coordinates":[-81.603847,26.725681],"type":"Point"}
}