{
  "type": "Feature",
  "properties": {
    "iso:country":"US",
    "sg:address":"140 W Broad St",
    "sg:city":"Groveland",
    "sg:classifiers":[
        {
            "category":"Restaurant",
            "type":"Food & Drink"
        },
        {
            "category":"Bakery",
            "type":"Food & Drink"
        }
    ],
    "sg:phone":"+1 352 429 5601",
    "sg:postcode":"34736",
    "sg:province":"FL",
    "wof:name":"Panchos Bakery",
    "wof:placetype":"venue"
},
  "geometry": {"coordinates":[-81.855884,28.560577],"type":"Point"}
}