{
  "type": "Feature",
  "properties": {
    "iso:country":"US",
    "sg:address":"512 S Pineapple Ave",
    "sg:city":"Sarasota",
    "sg:classifiers":[
        {
            "category":"Home & Garden",
            "subcategory":"Home Furnishings",
            "type":"Retail Goods"
        }
    ],
    "sg:phone":"+1 941 373 0830",
    "sg:postcode":"34236",
    "sg:province":"FL",
    "sg:tags":[
        "mirror"
    ],
    "wof:name":"August Third Inc",
    "wof:placetype":"venue"
},
  "geometry": {"coordinates":[-82.53916599999999,27.331929],"type":"Point"}
}