{
  "type": "Feature",
  "properties": {
    "iso:country":"US",
    "sg:address":"1200 N Central Ave",
    "sg:city":"Kissimmee",
    "sg:classifiers":[
        {
            "category":"Building & Trades",
            "subcategory":"Construction",
            "type":"Services"
        }
    ],
    "sg:phone":"+1 407 933 8444",
    "sg:postcode":"34741",
    "sg:province":"FL",
    "sg:tags":[
        "general",
        "contractor"
    ],
    "wof:name":"Canco General Contractors Inc",
    "wof:placetype":"venue"
},
  "geometry": {"coordinates":[-81.407855,28.303597],"type":"Point"}
}