{
  "type": "Feature",
  "properties": {
    "addr:full":"10201 Hammocks Blvd Miami FL 33196",
    "addr:housenumber":"10201",
    "addr:postcode":"33196",
    "addr:street":"Hammocks Blvd",
    "iso:country":"US",
    "sg:address":"10201 Hammocks Blvd",
    "sg:city":"Miami",
    "sg:classifiers":[
        {
            "category":"Professional",
            "subcategory":"Business Services",
            "type":"Services"
        },
        {
            "category":"Government",
            "subcategory":"Office",
            "type":"Public Place"
        },
        {
            "category":"Personal",
            "type":"Services"
        }
    ],
    "sg:phone":"+1 305 388 2942",
    "sg:postcode":"33196",
    "sg:province":"FL",
    "sg:tags":[
        "department",
        "transportation",
        "motor",
        "vehicle"
    ],
    "wof:name":"Hammocks Auto Tag Agency Inc",
    "wof:placetype":"venue"
},
  "geometry": {"coordinates":[-80.444068,25.673127],"type":"Point"}
}