{
  "type": "Feature",
  "properties": {
    "iso:country":"US",
    "sg:address":"707 Toulon Dr",
    "sg:city":"Kissimmee",
    "sg:classifiers":[
        {
            "category":"Building & Trades",
            "subcategory":"Construction",
            "type":"Services"
        }
    ],
    "sg:phone":"+1 407 846 2996",
    "sg:postcode":"34759",
    "sg:province":"FL",
    "sg:tags":[
        "house"
    ],
    "wof:name":"Jualco Construction Services",
    "wof:placetype":"venue"
},
  "geometry": {"coordinates":[-81.437365,28.108911],"type":"Point"}
}