{
  "type": "Feature",
  "properties": {
    "iso:country":"US",
    "sg:address":"10001 Magnolia Pointe",
    "sg:city":"Fort Myers",
    "sg:classifiers":[
        {
            "category":"Real Estate",
            "subcategory":"Real Estate Agent",
            "type":"Services"
        }
    ],
    "sg:phone":"+1 239 437 1684",
    "sg:postcode":"33919",
    "sg:province":"FL",
    "wof:name":"Magnolia Pointe",
    "wof:placetype":"venue"
},
  "geometry": {"coordinates":[-81.920475,26.556849],"type":"Point"}
}