{
  "type": "Feature",
  "properties": {
    "addr:full":"21127 White Oak Ave Boca Raton FL 33428",
    "addr:housenumber":"21127",
    "addr:postcode":"33428",
    "addr:street":"White Oak Ave",
    "iso:country":"US",
    "sg:address":"21127 White Oak Ave",
    "sg:city":"Boca Raton",
    "sg:classifiers":[
        {
            "category":"Building & Trades",
            "subcategory":"Construction",
            "type":"Services"
        }
    ],
    "sg:phone":"+1 561 483 3006",
    "sg:postcode":"33428",
    "sg:province":"FL",
    "sg:tags":[
        "general",
        "home",
        "contractor",
        "remodeling",
        "custom"
    ],
    "wof:name":"Swc Building & Design Inc",
    "wof:placetype":"venue"
},
  "geometry": {"coordinates":[-80.19023199999999,26.362247],"type":"Point"}
}