{
  "type": "Feature",
  "properties": {
    "iso:country":"US",
    "sg:address":"3714 Silver Star Rd",
    "sg:city":"Orlando",
    "sg:classifiers":[
        {
            "category":"Wholesale",
            "subcategory":"Hardware",
            "type":"Manufacturing & Wholesale Goods"
        }
    ],
    "sg:phone":"+1 407 297 7278",
    "sg:postcode":"32808",
    "sg:province":"FL",
    "sg:tags":[
        "screw"
    ],
    "sg:website":"www.grabberman.com",
    "wof:name":"Grabber Construction Products",
    "wof:placetype":"venue"
},
  "geometry": {"coordinates":[-81.425398,28.578014],"type":"Point"}
}