{
  "type": "Feature",
  "properties": {
    "iso:country":"US",
    "sg:address":"1400 36th Ave E",
    "sg:city":"Ellenton",
    "sg:classifiers":[
        {
            "category":"Real Estate",
            "subcategory":"Developer",
            "type":"Services"
        }
    ],
    "sg:phone":"+1 941 748 1011",
    "sg:postcode":"34222",
    "sg:province":"FL",
    "sg:tags":[
        "cemetery"
    ],
    "wof:name":"Mansion Memorial Park Sls Off",
    "wof:placetype":"venue"
},
  "geometry": {"coordinates":[-82.528122,27.525821],"type":"Point"}
}