{
  "type": "Feature",
  "properties": {
    "iso:country":"US",
    "sg:address":"3756 Essex Pl",
    "sg:city":"Bonita Springs",
    "sg:classifiers":[
        {
            "category":"Personal",
            "type":"Services"
        }
    ],
    "sg:phone":"+1 239 947 6432",
    "sg:postcode":"34134",
    "sg:province":"FL",
    "sg:tags":[
        "house",
        "sitter"
    ],
    "wof:name":"Guardian Angel Home Watchers",
    "wof:placetype":"venue"
},
  "geometry": {"coordinates":[-81.81554300000001,26.321496],"type":"Point"}
}