{
  "type": "Feature",
  "properties": {
    "iso:country":"US",
    "sg:address":"5647 Naples Blvd",
    "sg:city":"Naples",
    "sg:classifiers":[
        {
            "category":"Professional",
            "subcategory":"Management & Consulting",
            "type":"Services"
        }
    ],
    "sg:phone":"+1 239 598 0072",
    "sg:postcode":"34109",
    "sg:province":"FL",
    "sg:tags":[
        "construction"
    ],
    "wof:name":"Blitz Construction LTD Co",
    "wof:placetype":"venue"
},
  "geometry": {"coordinates":[-81.77003000000001,26.219157],"type":"Point"}
}