{
  "type": "Feature",
  "properties": {
    "iso:country":"US",
    "sg:address":"6161 9th St N",
    "sg:city":"St Petersburg",
    "sg:classifiers":[
        {
            "category":"Professional",
            "subcategory":"Accounting & Tax Preparation",
            "type":"Services"
        }
    ],
    "sg:phone":"+1 727 520 7676",
    "sg:postcode":"33703",
    "sg:province":"FL",
    "sg:tags":[
        "payroll"
    ],
    "wof:name":"Encorehr LLC",
    "wof:placetype":"venue"
},
  "geometry": {"coordinates":[-82.646817,27.827642],"type":"Point"}
}