{
  "type": "Feature",
  "properties": {
    "addr:full":"407 Flomich St Holly Hill FL 32117",
    "addr:housenumber":"407",
    "addr:postcode":"32117",
    "addr:street":"Flomich St",
    "iso:country":"US",
    "sg:address":"407 Flomich St",
    "sg:city":"Holly Hill",
    "sg:classifiers":[
        {
            "category":"Wholesale",
            "subcategory":"Scrap",
            "type":"Manufacturing & Wholesale Goods"
        }
    ],
    "sg:phone":"+1 386 673 1281",
    "sg:postcode":"32117",
    "sg:province":"FL",
    "sg:tags":[
        "recycling",
        "center"
    ],
    "sg:website":"www.almetrecyclesurplus.com",
    "wof:name":"Almet Recycle & Surplus",
    "wof:placetype":"venue"
},
  "geometry": {"coordinates":[-81.049694,29.254458],"type":"Point"}
}