{
  "type": "Feature",
  "properties": {
    "iso:country":"US",
    "sg:address":"300 Galen Dr",
    "sg:city":"Key Biscayne",
    "sg:classifiers":[
        {
            "category":"Professional",
            "type":"Services"
        }
    ],
    "sg:phone":"+1 305 365 3931",
    "sg:postcode":"33149",
    "sg:province":"FL",
    "wof:name":"Ties of Hope Inc",
    "wof:placetype":"venue"
},
  "geometry": {"coordinates":[-80.160962,25.690975],"type":"Point"}
}