{
  "type": "Feature",
  "properties": {
    "iso:country":"US",
    "sg:address":"207 N Main St",
    "sg:city":"Auburndale",
    "sg:classifiers":[
        {
            "category":"Shopping",
            "subcategory":"Bicycles & Sporting Goods",
            "type":"Retail Goods"
        }
    ],
    "sg:phone":"+1 863 967 3211",
    "sg:postcode":"33823",
    "sg:province":"FL",
    "sg:tags":[
        "equipment",
        "skateboard"
    ],
    "wof:name":"Faded Glitter",
    "wof:placetype":"venue"
},
  "geometry": {"coordinates":[-81.788622,28.070844],"type":"Point"}
}