{
  "type": "Feature",
  "properties": {
    "iso:country":"US",
    "sg:address":"1371 S Missouri Ave",
    "sg:city":"Clearwater",
    "sg:classifiers":[
        {
            "category":"Retail",
            "subcategory":"Auto Repair",
            "type":"Services"
        }
    ],
    "sg:phone":"+1 727 443 6392",
    "sg:postcode":"33756",
    "sg:province":"FL",
    "sg:tags":[
        "repairing",
        "automobile"
    ],
    "wof:name":"Nicks Auto Repair",
    "wof:placetype":"venue"
},
  "geometry": {"coordinates":[-82.78748899999999,27.951303],"type":"Point"}
}