{
  "type": "Feature",
  "properties": {
    "iso:country":"US",
    "sg:address":"1061 Panacea Blvd",
    "sg:city":"North Port",
    "sg:classifiers":[
        {
            "category":"Retail",
            "subcategory":"Laundry & Dry Cleaning",
            "type":"Services"
        }
    ],
    "sg:phone":"+1 941 426 5346",
    "sg:postcode":"34289",
    "sg:province":"FL",
    "sg:tags":[
        "drycleaning",
        "plant"
    ],
    "wof:name":"Quality Care Cleaners",
    "wof:placetype":"venue"
},
  "geometry": {"coordinates":[-82.154811,27.086315],"type":"Point"}
}