{
  "type": "Feature",
  "properties": {
    "iso:country":"US",
    "sg:address":"36107 Timbertop Ln",
    "sg:city":"Fruitland Park",
    "sg:classifiers":[
        {
            "category":"Building & Trades",
            "subcategory":"Construction",
            "type":"Services"
        }
    ],
    "sg:phone":"+1 352 314 9117",
    "sg:postcode":"34731",
    "sg:province":"FL",
    "sg:tags":[
        "contractor"
    ],
    "wof:name":"Ceramic Tile Management Inc",
    "wof:placetype":"venue"
},
  "geometry": {"coordinates":[-81.936837,28.873595],"type":"Point"}
}