{
  "type": "Feature",
  "properties": {
    "iso:country":"US",
    "sg:address":"1025 Barefoot Cir",
    "sg:city":"Sebastian",
    "sg:classifiers":[
        {
            "category":"Building & Trades",
            "subcategory":"Construction",
            "type":"Services"
        }
    ],
    "sg:phone":"+1 772 664 7983",
    "sg:postcode":"32976",
    "sg:province":"FL",
    "sg:tags":[
        "restoration",
        "cleaning",
        "patio",
        "deck"
    ],
    "wof:name":"Greg Smith Pressure Washing",
    "wof:placetype":"venue"
},
  "geometry": {"coordinates":[-80.52999800000001,27.886016],"type":"Point"}
}