{
  "type": "Feature",
  "properties": {
    "addr:full":"360 State Ln Orlando FL 32801",
    "addr:housenumber":"360",
    "addr:postcode":"32801",
    "addr:street":"State Ln",
    "iso:country":"US",
    "sg:address":"360 State Ln",
    "sg:city":"Orlando",
    "sg:classifiers":[
        {
            "category":"Bars & Pubs",
            "type":"Food & Drink"
        }
    ],
    "sg:phone":"+1 407 244 0299",
    "sg:postcode":"32801",
    "sg:province":"FL",
    "sg:tags":[
        "club",
        "night"
    ],
    "wof:name":"Screamers",
    "wof:placetype":"venue"
},
  "geometry": {"coordinates":[-81.380298,28.546407],"type":"Point"}
}