{
  "type": "Feature",
  "properties": {
    "addr:full":"8616 Bridle Path Ct Fort Lauderdale FL 33328",
    "addr:housenumber":"8616",
    "addr:postcode":"33328",
    "addr:street":"Bridle Path Ct",
    "iso:country":"US",
    "sg:address":"8616 Bridle Path Ct",
    "sg:city":"Fort Lauderdale",
    "sg:classifiers":[
        {
            "category":"Building & Trades",
            "subcategory":"Electrical",
            "type":"Services"
        }
    ],
    "sg:phone":"+1 954 474 5557",
    "sg:postcode":"33328",
    "sg:province":"FL",
    "sg:tags":[
        "electrical",
        "contractor"
    ],
    "wof:name":"Ace Telecom Consulting Group",
    "wof:placetype":"venue"
},
  "geometry": {"coordinates":[-80.263559,26.071821],"type":"Point"}
}