{
  "type": "Feature",
  "properties": {
    "iso:country":"US",
    "sg:address":"12701 S John Young Pkwy",
    "sg:city":"Orlando",
    "sg:classifiers":[
        {
            "category":"Real Estate",
            "subcategory":"Real Estate Agent",
            "type":"Services"
        }
    ],
    "sg:phone":"+1 407 851 4000",
    "sg:postcode":"32837",
    "sg:province":"FL",
    "wof:name":"Luxury Realty",
    "wof:placetype":"venue"
},
  "geometry": {"coordinates":[-81.42572199999999,28.379094],"type":"Point"}
}