{
  "type": "Feature",
  "properties": {
    "addr:full":"770 Kilbourne Ave Englewood FL 34223",
    "addr:housenumber":"770",
    "addr:postcode":"34223",
    "addr:street":"Kilbourne Ave",
    "iso:country":"US",
    "sg:address":"770 Kilbourne Ave",
    "sg:city":"Englewood",
    "sg:classifiers":[
        {
            "category":"Organizations",
            "subcategory":"Religious Organization",
            "type":"Services"
        }
    ],
    "sg:phone":"+1 941 474 9595",
    "sg:postcode":"34223",
    "sg:province":"FL",
    "sg:tags":[
        "church"
    ],
    "sg:website":"www.straphaelsonline.org",
    "wof:name":"St Raphael's Church",
    "wof:placetype":"venue"
},
  "geometry": {"coordinates":[-82.369246,26.975295],"type":"Point"}
}