{
  "type": "Feature",
  "properties": {
    "iso:country":"US",
    "sg:address":"101 N Plumosa St Ste B",
    "sg:city":"Merritt Island",
    "sg:classifiers":[
        {
            "category":"Banks & Credit Unions",
            "subcategory":"Atm",
            "type":"Services"
        }
    ],
    "sg:phone":"+1 321 452 1991",
    "sg:postcode":"32953",
    "sg:province":"FL",
    "sg:tags":[
        "bankruptcy"
    ],
    "wof:name":"Bess Carole Suzanne",
    "wof:placetype":"venue"
},
  "geometry": {"coordinates":[-80.692246,28.357794],"type":"Point"}
}