{
  "type": "Feature",
  "properties": {
    "iso:country":"US",
    "sg:address":"3030 SW Segovia St",
    "sg:city":"Port Saint Lucie",
    "sg:classifiers":[
        {
            "category":"Building & Trades",
            "subcategory":"Construction",
            "type":"Services"
        }
    ],
    "sg:phone":"+1 772 336 9565",
    "sg:postcode":"34953",
    "sg:province":"FL",
    "sg:tags":[
        "hanging",
        "contractor"
    ],
    "wof:name":"J&W Painting Svc",
    "wof:placetype":"venue"
},
  "geometry": {"coordinates":[-80.392994,27.253644],"type":"Point"}
}