{
  "type": "Feature",
  "properties": {
    "addr:full":"5580 NE 4th Ct Ste 4 Miami FL 33137",
    "addr:housenumber":"5580",
    "addr:postcode":"33137",
    "addr:street":"Ne 4Th Ct Ste 4",
    "iso:country":"US",
    "sg:address":"5580 NE 4th Ct Ste 4",
    "sg:city":"Miami",
    "sg:classifiers":[
        {
            "category":"Shopping",
            "subcategory":"Clothing, Apparel, & Fashions",
            "type":"Retail Goods"
        }
    ],
    "sg:phone":"+1 305 756 1010",
    "sg:postcode":"33137",
    "sg:province":"FL",
    "sg:tags":[
        "men's",
        "clothing",
        "women's"
    ],
    "sg:website":"www.stylelabmiami.com",
    "wof:name":"Style Lab",
    "wof:placetype":"venue"
},
  "geometry": {"coordinates":[-80.187045,25.827674],"type":"Point"}
}