{
  "type": "Feature",
  "properties": {
    "iso:country":"US",
    "sg:address":"4245 Cardinal Blvd",
    "sg:city":"Daytona Beach",
    "sg:classifiers":[
        {
            "category":"Building & Trades",
            "subcategory":"Construction",
            "type":"Services"
        }
    ],
    "sg:phone":"+1 386 756 6765",
    "sg:postcode":"32127",
    "sg:province":"FL",
    "sg:tags":[
        "contractor"
    ],
    "wof:name":"Pro Plastering",
    "wof:placetype":"venue"
},
  "geometry": {"coordinates":[-80.955685,29.125371],"type":"Point"}
}