{
  "type": "Feature",
  "properties": {
    "iso:country":"US",
    "sg:address":"2448 Clematis St",
    "sg:city":"Sarasota",
    "sg:classifiers":[
        {
            "category":"Building & Trades",
            "subcategory":"Plumbing",
            "type":"Services"
        }
    ],
    "sg:phone":"+1 941 365 7397",
    "sg:postcode":"34239",
    "sg:province":"FL",
    "sg:tags":[
        "contractor"
    ],
    "wof:name":"Jeff Light Plumbing",
    "wof:placetype":"venue"
},
  "geometry": {"coordinates":[-82.521123,27.313291],"type":"Point"}
}