{
  "type": "Feature",
  "properties": {
    "iso:country":"US",
    "sg:address":"737 NW 15th Ave",
    "sg:city":"Miami",
    "sg:classifiers":[
        {
            "category":"Professional",
            "subcategory":"Art Services",
            "type":"Services"
        }
    ],
    "sg:phone":"+1 305 642 4440",
    "sg:postcode":"33125",
    "sg:province":"FL",
    "sg:tags":[
        "photography",
        "photographers-commercial",
        "commercial"
    ],
    "wof:name":"Greg Schnder Crtive Phtography",
    "wof:placetype":"venue"
},
  "geometry": {"coordinates":[-80.22028400000001,25.780554],"type":"Point"}
}