{
  "type": "Feature",
  "properties": {
    "addr:full":"744 Jefferson Ave Miami Beach FL 33139",
    "addr:housenumber":"744",
    "addr:postcode":"33139",
    "addr:street":"Jefferson Ave",
    "iso:country":"US",
    "sg:address":"744 Jefferson Ave",
    "sg:city":"Miami Beach",
    "sg:classifiers":[
        {
            "category":"Food & Beverages",
            "subcategory":"Specialty",
            "type":"Retail Goods"
        }
    ],
    "sg:phone":"+1 305 534 6039",
    "sg:postcode":"33139",
    "sg:province":"FL",
    "wof:name":"Caffe Barone",
    "wof:placetype":"venue"
},
  "geometry": {"coordinates":[-80.137367,25.777712],"type":"Point"}
}