{
  "type": "Feature",
  "properties": {
    "iso:country":"US",
    "sg:address":"1704 Atlantic St",
    "sg:city":"Melbourne Beach",
    "sg:classifiers":[
        {
            "category":"Personal",
            "subcategory":"Beauty Salon",
            "type":"Services"
        }
    ],
    "sg:phone":"+1 321 259 1814",
    "sg:postcode":"32951",
    "sg:province":"FL",
    "wof:name":"Celtic Cuts",
    "wof:placetype":"venue"
},
  "geometry": {"coordinates":[-80.553308,28.059225],"type":"Point"}
}