{
  "type": "Feature",
  "properties": {
    "addr:full":"1985 Cope Ln Pensacola FL 32526",
    "addr:housenumber":"1985",
    "addr:postcode":"32526",
    "addr:street":"Cope Ln",
    "iso:country":"US",
    "sg:address":"1985 Cope Ln",
    "sg:city":"Pensacola",
    "sg:classifiers":[
        {
            "category":"Professional",
            "subcategory":"Engineering",
            "type":"Services"
        }
    ],
    "sg:phone":"+1 850 944 5555",
    "sg:postcode":"32526",
    "sg:province":"FL",
    "sg:tags":[
        "engineer"
    ],
    "wof:name":"Universal Engineering",
    "wof:placetype":"venue"
},
  "geometry": {"coordinates":[-87.305319,30.494922],"type":"Point"}
}