{
  "type": "Feature",
  "properties": {
    "iso:country":"US",
    "sg:address":"11478 SW 74th Ter",
    "sg:city":"Miami",
    "sg:classifiers":[
        {
            "category":"Building & Trades",
            "subcategory":"Construction",
            "type":"Services"
        }
    ],
    "sg:phone":"+1 305 598 5489",
    "sg:postcode":"33173",
    "sg:province":"FL",
    "sg:tags":[
        "drywall",
        "contractor"
    ],
    "wof:name":"Mesa Drywall Corp",
    "wof:placetype":"venue"
},
  "geometry": {"coordinates":[-80.38006900000001,25.698197],"type":"Point"}
}