{
  "type": "Feature",
  "properties": {
    "addr:full":"19625 Wyndham Lakes Dr Odessa FL 33556",
    "addr:housenumber":"19625",
    "addr:postcode":"33556",
    "addr:street":"Wyndham Lakes Dr",
    "iso:country":"US",
    "sg:address":"19625 Wyndham Lakes Dr",
    "sg:city":"Odessa",
    "sg:classifiers":[
        {
            "category":"Shopping",
            "type":"Retail Goods"
        }
    ],
    "sg:phone":"+1 813 792 8988",
    "sg:postcode":"33556",
    "sg:province":"FL",
    "sg:tags":[
        "merchandise"
    ],
    "wof:name":"Pet Appeal",
    "wof:placetype":"venue"
},
  "geometry": {"coordinates":[-82.58832099999999,28.166681],"type":"Point"}
}