{
  "type": "Feature",
  "properties": {
    "addr:full":"2615 N Hiatus Rd Hollywood FL 33026",
    "addr:housenumber":"2615",
    "addr:postcode":"33026",
    "addr:street":"N Hiatus Rd",
    "iso:country":"US",
    "sg:address":"2615 N Hiatus Rd",
    "sg:city":"Hollywood",
    "sg:classifiers":[
        {
            "category":"Wholesale",
            "subcategory":"Computers",
            "type":"Manufacturing & Wholesale Goods"
        },
        {
            "category":"Professional",
            "subcategory":"Computer Services",
            "type":"Services"
        }
    ],
    "sg:phone":"+1 954 337 1444",
    "sg:postcode":"33026",
    "sg:province":"FL",
    "sg:tags":[
        "repair",
        "software",
        "equipment-service",
        "equipment"
    ],
    "sg:website":"http://www.computersights.net",
    "wof:name":"Computer Sights",
    "wof:placetype":"venue"
},
  "geometry": {"coordinates":[-80.29688,26.031189],"type":"Point"}
}