{
  "type": "Feature",
  "properties": {
    "addr:full":"201 S Biscayne Blvd Miami FL 33131",
    "addr:housenumber":"201",
    "addr:postcode":"33131",
    "addr:street":"S Biscayne Blvd",
    "iso:country":"US",
    "sg:address":"201 S Biscayne Blvd",
    "sg:city":"Miami",
    "sg:classifiers":[
        {
            "category":"Professional",
            "subcategory":"Lawyer & Legal Services",
            "type":"Services"
        }
    ],
    "sg:phone":"+1 305 371 6421",
    "sg:postcode":"33131",
    "sg:province":"FL",
    "sg:tags":[
        "attorney",
        "criminal",
        "law"
    ],
    "wof:name":"Srebnick, Howard M",
    "wof:placetype":"venue"
},
  "geometry": {"coordinates":[-80.187134,25.772663],"type":"Point"}
}