{
  "type": "Feature",
  "properties": {
    "iso:country":"US",
    "sg:address":"1928 S Orange Blossom Trl",
    "sg:city":"Apopka",
    "sg:classifiers":[
        {
            "category":"Building & Trades",
            "subcategory":"Plumbing",
            "type":"Services"
        }
    ],
    "sg:phone":"+1 407 886 5379",
    "sg:postcode":"32703",
    "sg:province":"FL",
    "sg:tags":[
        "conditioning",
        "air",
        "system",
        "contractor"
    ],
    "wof:name":"Libby Twins Heating & Air",
    "wof:placetype":"venue"
},
  "geometry": {"coordinates":[-81.461992,28.646976],"type":"Point"}
}