{
  "type": "Feature",
  "properties": {
    "addr:full":"4308 NE 5th Ter Fort Lauderdale FL 33334",
    "addr:housenumber":"4308",
    "addr:postcode":"33334",
    "addr:street":"Ne 5Th Ter",
    "iso:country":"US",
    "sg:address":"4308 NE 5th Ter",
    "sg:city":"Fort Lauderdale",
    "sg:classifiers":[
        {
            "category":"Home & Garden",
            "subcategory":"Building Materials",
            "type":"Retail Goods"
        },
        {
            "category":"Retail",
            "subcategory":"Repair Shop",
            "type":"Services"
        }
    ],
    "sg:phone":"+1 954 396 4211",
    "sg:postcode":"33334",
    "sg:province":"FL",
    "sg:tags":[
        "windows",
        "window",
        "door",
        "contractor"
    ],
    "wof:name":"Buckley Window Corp",
    "wof:placetype":"venue"
},
  "geometry": {"coordinates":[-80.139762,26.181397],"type":"Point"}
}