{
  "type": "Feature",
  "properties": {
    "iso:country":"US",
    "sg:address":"98 Miracle Strip Pkwy",
    "sg:city":"Fort Walton Bch",
    "sg:classifiers":[
        {
            "category":"Real Estate",
            "subcategory":"Architect",
            "type":"Services"
        }
    ],
    "sg:phone":"+1 850 243 0453",
    "sg:postcode":"32548",
    "sg:province":"FL",
    "sg:tags":[
        "home",
        "planning",
        "design"
    ],
    "wof:name":"Cross Design & Illustrating",
    "wof:placetype":"venue"
},
  "geometry": {"coordinates":[-86.60657,30.403626],"type":"Point"}
}