{
  "type": "Feature",
  "properties": {
    "iso:country":"US",
    "sg:address":"2837 S Brown Ave",
    "sg:city":"Orlando",
    "sg:classifiers":[
        {
            "category":"Retail",
            "subcategory":"Auto Repair",
            "type":"Services"
        }
    ],
    "sg:phone":"+1 407 896 8289",
    "sg:postcode":"32806",
    "sg:province":"FL",
    "sg:tags":[
        "general"
    ],
    "wof:name":"Thomas Byrnes Truck Repair",
    "wof:placetype":"venue"
},
  "geometry": {"coordinates":[-81.361796,28.510119],"type":"Point"}
}