{
  "type": "Feature",
  "properties": {
    "iso:country":"US",
    "sg:address":"8565 NW 68th St",
    "sg:city":"Miami",
    "sg:classifiers":[
        {
            "category":"Freight",
            "type":"Transportation"
        }
    ],
    "sg:phone":"+1 305 463 0430",
    "sg:postcode":"33166",
    "sg:province":"FL",
    "sg:tags":[
        "arrangement"
    ],
    "wof:name":"Providence Service Inc",
    "wof:placetype":"venue"
},
  "geometry": {"coordinates":[-80.33605799999999,25.835331],"type":"Point"}
}