{
  "type": "Feature",
  "properties": {
    "iso:country":"US",
    "sg:address":"38520 N 86th St",
    "sg:city":"Pahokee",
    "sg:classifiers":[
        {
            "category":"Real Estate",
            "subcategory":"Real Estate Operator",
            "type":"Services"
        }
    ],
    "sg:phone":"+1 561 924 2648",
    "sg:postcode":"33476",
    "sg:province":"FL",
    "sg:tags":[
        "apartment"
    ],
    "wof:name":"Sugar Cane Villas LTD",
    "wof:placetype":"venue"
},
  "geometry": {"coordinates":[-80.654794,26.807555],"type":"Point"}
}