{
  "type": "Feature",
  "properties": {
    "iso:country":"US",
    "sg:address":"11 Hollyhock Ct",
    "sg:city":"Homosassa",
    "sg:classifiers":[
        {
            "category":"Building & Trades",
            "subcategory":"Construction",
            "type":"Services"
        }
    ],
    "sg:phone":"+1 352 382 4852",
    "sg:postcode":"34446",
    "sg:province":"FL",
    "sg:tags":[
        "concrete",
        "contractor"
    ],
    "wof:name":"B & D Custom Concrete Inc",
    "wof:placetype":"venue"
},
  "geometry": {"coordinates":[-82.53026800000001,28.720249],"type":"Point"}
}