{
  "type": "Feature",
  "properties": {
    "addr:full":"1902 NW 97th Ave Pompano Beach FL 33071",
    "addr:housenumber":"1902",
    "addr:postcode":"33071",
    "addr:street":"Nw 97Th Ave",
    "iso:country":"US",
    "sg:address":"1902 NW 97th Ave",
    "sg:city":"Pompano Beach",
    "sg:classifiers":[
        {
            "category":"Building & Trades",
            "subcategory":"Construction",
            "type":"Services"
        }
    ],
    "sg:phone":"+1 954 340 8737",
    "sg:postcode":"33071",
    "sg:province":"FL",
    "sg:tags":[
        "hanging",
        "contractor"
    ],
    "wof:name":"Metro Painting",
    "wof:placetype":"venue"
},
  "geometry": {"coordinates":[-80.25497900000001,26.25206],"type":"Point"}
}