{
  "type": "Feature",
  "properties": {
    "addr:full":"3320 W Main St Mims FL 32754",
    "addr:housenumber":"3320",
    "addr:postcode":"32754",
    "addr:street":"W Main St",
    "iso:country":"US",
    "sg:address":"3320 W Main St",
    "sg:city":"Mims",
    "sg:classifiers":[
        {
            "category":"Wholesale",
            "subcategory":"Furniture",
            "type":"Manufacturing & Wholesale Goods"
        }
    ],
    "sg:phone":"+1 321 385 0630",
    "sg:postcode":"32754",
    "sg:province":"FL",
    "wof:name":"Lo Brothers Enterprises Inc",
    "wof:placetype":"venue"
},
  "geometry": {"coordinates":[-80.846678,28.664756],"type":"Point"}
}