{
  "type": "Feature",
  "properties": {
    "iso:country":"US",
    "sg:address":"13337 SW 116th Ct",
    "sg:city":"Miami",
    "sg:classifiers":[
        {
            "category":"Freight",
            "type":"Transportation"
        }
    ],
    "sg:phone":"+1 305 235 8717",
    "sg:postcode":"33176",
    "sg:province":"FL",
    "wof:name":"Flipper Transportation Express",
    "wof:placetype":"venue"
},
  "geometry": {"coordinates":[-80.381795,25.644605],"type":"Point"}
}