{
  "type": "Feature",
  "properties": {
    "iso:country":"US",
    "sg:address":"1731 University Blvd S",
    "sg:city":"Jacksonville",
    "sg:classifiers":[
        {
            "category":"Health Services",
            "subcategory":"Doctor",
            "type":"Services"
        }
    ],
    "sg:phone":"+1 904 725 6544",
    "sg:postcode":"32216",
    "sg:province":"FL",
    "sg:tags":[
        "medical"
    ],
    "wof:name":"Jacksonville Family Practice",
    "wof:placetype":"venue"
},
  "geometry": {"coordinates":[-81.599368,30.313771],"type":"Point"}
}