{
  "type": "Feature",
  "properties": {
    "iso:country":"US",
    "sg:address":"1613 Lee Rd",
    "sg:city":"Winter Park",
    "sg:classifiers":[
        {
            "category":"Personal",
            "subcategory":"Nail Salon",
            "type":"Services"
        }
    ],
    "sg:phone":"+1 407 644 1693",
    "sg:postcode":"32789",
    "sg:province":"FL",
    "wof:name":"Tlc Spa and Nails",
    "wof:placetype":"venue"
},
  "geometry": {"coordinates":[-81.369781,28.606166],"type":"Point"}
}