{
  "type": "Feature",
  "properties": {
    "iso:country":"US",
    "sg:address":"221 Nicholson Dr",
    "sg:city":"Davenport",
    "sg:classifiers":[
        {
            "category":"Building & Trades",
            "subcategory":"Construction",
            "type":"Services"
        }
    ],
    "sg:phone":"+1 863 420 3711",
    "sg:postcode":"33837",
    "sg:province":"FL",
    "sg:tags":[
        "house"
    ],
    "wof:name":"Luis Lazaney Contracting",
    "wof:placetype":"venue"
},
  "geometry": {"coordinates":[-81.63383399999999,28.206327],"type":"Point"}
}