{
  "type": "Feature",
  "properties": {
    "iso:country":"US",
    "sg:address":"2001 W Atlantic Ave",
    "sg:city":"Delray Beach",
    "sg:classifiers":[
        {
            "category":"Wholesale",
            "subcategory":"Metals & Minerals",
            "type":"Manufacturing & Wholesale Goods"
        }
    ],
    "sg:phone":"+1 561 279 4000",
    "sg:postcode":"33445",
    "sg:province":"FL",
    "sg:tags":[
        "center"
    ],
    "wof:name":"Gco",
    "wof:placetype":"venue"
},
  "geometry": {"coordinates":[-80.09184399999999,26.461392],"type":"Point"}
}