{
  "type": "Feature",
  "properties": {
    "iso:country":"US",
    "sg:address":"620 NW 106th Ter",
    "sg:city":"Hollywood",
    "sg:classifiers":[
        {
            "category":"Wholesale",
            "subcategory":"Drugs",
            "type":"Manufacturing & Wholesale Goods"
        }
    ],
    "sg:phone":"+1 954 450 4943",
    "sg:postcode":"33026",
    "sg:province":"FL",
    "wof:name":"Nutrients To Go Inc",
    "wof:placetype":"venue"
},
  "geometry": {"coordinates":[-80.28858200000001,26.013348],"type":"Point"}
}