{
  "type": "Feature",
  "properties": {
    "iso:country":"US",
    "sg:address":"1485 NE 25th St",
    "sg:city":"Pompano Beach",
    "sg:classifiers":[
        {
            "category":"Building & Trades",
            "subcategory":"Construction",
            "type":"Services"
        }
    ],
    "sg:phone":"+1 954 781 7639",
    "sg:postcode":"33064",
    "sg:province":"FL",
    "sg:tags":[
        "house"
    ],
    "wof:name":"Bic Const Co Inc",
    "wof:placetype":"venue"
},
  "geometry": {"coordinates":[-80.10333799999999,26.262289],"type":"Point"}
}