{
  "type": "Feature",
  "properties": {
    "iso:country":"US",
    "sg:address":"4566 Glebe Farm Rd N",
    "sg:city":"Sarasota",
    "sg:classifiers":[
        {
            "category":"Education",
            "subcategory":"Dance Studio",
            "type":"Public Place"
        }
    ],
    "sg:phone":"+1 941 378 3019",
    "sg:postcode":"34235",
    "sg:province":"FL",
    "wof:name":"Machol Inc",
    "wof:placetype":"venue"
},
  "geometry": {"coordinates":[-82.476241,27.355767],"type":"Point"}
}