{
  "type": "Feature",
  "properties": {
    "iso:country":"US",
    "sg:address":"5522 NW 43 St",
    "sg:city":"Gainesville",
    "sg:classifiers":[
        {
            "category":"Real Estate",
            "subcategory":"Real Estate Agent",
            "type":"Services"
        }
    ],
    "sg:phone":"+1 352 371 2118",
    "sg:postcode":"32653",
    "sg:province":"FL",
    "sg:tags":[
        "finding",
        "apartment",
        "rental"
    ],
    "sg:website":"www.bosshardtrealty.com",
    "wof:name":"Bosshardt Property Management",
    "wof:placetype":"venue"
},
  "geometry": {"coordinates":[-82.388955,29.703745],"type":"Point"}
}