{
  "type": "Feature",
  "properties": {
    "iso:country":"US",
    "sg:address":"202 Lennox Rd W",
    "sg:city":"Palm Harbor",
    "sg:classifiers":[
        {
            "category":"Freight",
            "type":"Transportation"
        }
    ],
    "sg:phone":"+1 727 938 0673",
    "sg:postcode":"34683",
    "sg:province":"FL",
    "wof:name":"Priority One Logistics Inc",
    "wof:placetype":"venue"
},
  "geometry": {"coordinates":[-82.746554,28.113695],"type":"Point"}
}