{
  "type": "Feature",
  "properties": {
    "addr:full":"4101 E 11th Ave Hialeah FL 33013",
    "addr:housenumber":"4101",
    "addr:postcode":"33013",
    "addr:street":"E 11Th Ave",
    "iso:country":"US",
    "sg:address":"4101 E 11th Ave",
    "sg:city":"Hialeah",
    "sg:classifiers":[
        {
            "category":"Wholesale",
            "subcategory":"Motor Vehicles",
            "type":"Manufacturing & Wholesale Goods"
        }
    ],
    "sg:phone":"+1 305 769 0310",
    "sg:postcode":"33013",
    "sg:province":"FL",
    "sg:tags":[
        "automobile",
        "truck",
        "broker"
    ],
    "wof:name":"Automobile Enterprises Distr",
    "wof:placetype":"venue"
},
  "geometry": {"coordinates":[-80.260536,25.861974],"type":"Point"}
}