{
  "type": "Feature",
  "properties": {
    "addr:full":"1401 SE 9th Ct Hialeah FL 33010",
    "addr:housenumber":"1401",
    "addr:postcode":"33010",
    "addr:street":"Se 9Th Ct",
    "iso:country":"US",
    "sg:address":"1401 SE 9th Ct",
    "sg:city":"Hialeah",
    "sg:classifiers":[
        {
            "category":"Government",
            "subcategory":"Department Of Motor Vehicles",
            "type":"Public Place"
        }
    ],
    "sg:phone":"+1 305 888 2992",
    "sg:postcode":"33010",
    "sg:province":"FL",
    "sg:tags":[
        "truck",
        "trailer"
    ],
    "wof:name":"Trailmobile",
    "wof:placetype":"venue"
},
  "geometry": {"coordinates":[-80.261612,25.810301],"type":"Point"}
}