{
  "type": "Feature",
  "properties": {
    "iso:country":"US",
    "sg:address":"9180 Wiles Rd",
    "sg:city":"Pompano Beach",
    "sg:classifiers":[
        {
            "category":"Restaurant",
            "type":"Food & Drink"
        }
    ],
    "sg:menulink":"http://www.allmenus.com/fl/deerfield-beach/187087-mcdonalds/menu/",
    "sg:phone":"+1 954 341 4349",
    "sg:postcode":"33067",
    "sg:province":"FL",
    "sg:tags":[
        "burger",
        "american"
    ],
    "wof:name":"McDonald's",
    "wof:placetype":"venue"
},
  "geometry": {"coordinates":[-80.247652,26.286879],"type":"Point"}
}