{
  "type": "Feature",
  "properties": {
    "iso:country":"US",
    "sg:address":"1001 Tuscanny St",
    "sg:city":"Brandon",
    "sg:classifiers":[
        {
            "category":"Manufacturing",
            "subcategory":"Retail Goods",
            "type":"Manufacturing & Wholesale Goods"
        }
    ],
    "sg:phone":"+1 813 641 9685",
    "sg:postcode":"33511",
    "sg:province":"FL",
    "sg:tags":[
        "manufacturer"
    ],
    "wof:name":"Charles Industries",
    "wof:placetype":"venue"
},
  "geometry": {"coordinates":[-82.264748,27.927038],"type":"Point"}
}