{
  "type": "Feature",
  "properties": {
    "iso:country":"US",
    "sg:address":"9014 Fountain Rd",
    "sg:city":"Lake Worth",
    "sg:classifiers":[
        {
            "category":"Local Transit",
            "type":"Transportation"
        }
    ],
    "sg:phone":"+1 561 902 4100",
    "sg:postcode":"33467",
    "sg:province":"FL",
    "sg:tags":[
        "passenger"
    ],
    "wof:name":"Bridge Limousine Services",
    "wof:placetype":"venue"
},
  "geometry": {"coordinates":[-80.18973200000001,26.60716],"type":"Point"}
}