{
  "type": "Feature",
  "properties": {
    "iso:country":"US",
    "sg:address":"1165 S State Rd 415",
    "sg:city":"New Smyrna Beach",
    "sg:classifiers":[
        {
            "category":"Real Estate",
            "subcategory":"Real Estate Operator",
            "type":"Services"
        }
    ],
    "sg:phone":"+1 386 428 1998",
    "sg:postcode":"32168",
    "sg:province":"FL",
    "sg:tags":[
        "mobile",
        "home",
        "community"
    ],
    "wof:name":"Lake Ashby Mobile Home Park",
    "wof:placetype":"venue"
},
  "geometry": {"coordinates":[-81.106268,28.937467],"type":"Point"}
}