{
  "type": "Feature",
  "properties": {
    "addr:full":"1608 Sequoia Dr Tallahassee FL 32301",
    "addr:housenumber":"1608",
    "addr:postcode":"32301",
    "addr:street":"Sequoia Dr",
    "iso:country":"US",
    "sg:address":"1608 Sequoia Dr",
    "sg:city":"Tallahassee",
    "sg:classifiers":[
        {
            "category":"Freight",
            "type":"Transportation"
        }
    ],
    "sg:phone":"+1 850 878 8823",
    "sg:postcode":"32301",
    "sg:province":"FL",
    "sg:tags":[
        "courier"
    ],
    "wof:name":"Services Galore Inc",
    "wof:placetype":"venue"
},
  "geometry": {"coordinates":[-84.25304300000001,30.448222],"type":"Point"}
}