{
  "type": "Feature",
  "properties": {
    "iso:country":"US",
    "sg:address":"20120 NE 10th Place Way",
    "sg:city":"Miami",
    "sg:classifiers":[
        {
            "category":"Shopping",
            "subcategory":"Antiques",
            "type":"Retail Goods"
        }
    ],
    "sg:phone":"+1 305 249 9523",
    "sg:postcode":"33179",
    "sg:province":"FL",
    "sg:tags":[
        "dealers-wholesale"
    ],
    "wof:name":"Asher Shahar Inc",
    "wof:placetype":"venue"
},
  "geometry": {"coordinates":[-80.180682,25.961089],"type":"Point"}
}