{
  "type": "Feature",
  "properties": {
    "addr:full":"3700 W 12th Ave Ste 313 Hialeah FL 33012",
    "addr:housenumber":"3700",
    "addr:postcode":"33012",
    "addr:street":"W 12Th Ave Ste 313",
    "iso:country":"US",
    "sg:address":"3700 W 12th Ave Ste 313",
    "sg:city":"Hialeah",
    "sg:classifiers":[
        {
            "category":"Professional",
            "subcategory":"Advertising",
            "type":"Services"
        }
    ],
    "sg:phone":"+1 305 822 5403",
    "sg:postcode":"33012",
    "sg:province":"FL",
    "sg:tags":[
        "mail",
        "direct"
    ],
    "wof:name":"B-Back Promotions, Inc.",
    "wof:placetype":"venue"
},
  "geometry": {"coordinates":[-80.30651899999999,25.855249],"type":"Point"}
}