{
  "type": "Feature",
  "properties": {
    "addr:full":"1811 NW 29th St Fort Lauderdale FL 33311",
    "addr:housenumber":"1811",
    "addr:postcode":"33311",
    "addr:street":"Nw 29Th St",
    "iso:country":"US",
    "sg:address":"1811 NW 29th St",
    "sg:city":"Fort Lauderdale",
    "sg:classifiers":[
        {
            "category":"Manufacturing",
            "subcategory":"Food",
            "type":"Manufacturing & Wholesale Goods"
        }
    ],
    "sg:phone":"+1 954 485 6730",
    "sg:postcode":"33311",
    "sg:province":"FL",
    "sg:tags":[
        "gourmet",
        "bakery",
        "bread"
    ],
    "wof:name":"Naturally Delicious Inc",
    "wof:placetype":"venue"
},
  "geometry": {"coordinates":[-80.168052,26.162623],"type":"Point"}
}