{
  "type": "Feature",
  "properties": {
    "addr:full":"440 NW 72ST ST Hialeah FL 33012",
    "addr:housenumber":"440",
    "addr:postcode":"33012",
    "addr:street":"Nw 72St St",
    "iso:country":"US",
    "sg:address":"440 NW 72ST ST",
    "sg:city":"Hialeah",
    "sg:classifiers":[
        {
            "category":"Health Services",
            "subcategory":"Optometrist",
            "type":"Services"
        },
        {
            "category":"Health Services",
            "subcategory":"Clinic",
            "type":"Services"
        },
        {
            "category":"Health Services",
            "subcategory":"Doctor",
            "type":"Services"
        }
    ],
    "sg:phone":"+1 305 828 5071",
    "sg:postcode":"33012",
    "sg:province":"FL",
    "sg:tags":[
        "physician",
        "optometry",
        "medical",
        "surgeons",
        "pediatrics-ophthalmology",
        "optometrists-od-pediatric",
        "surgeon"
    ],
    "wof:name":"Dr Sterns Visual Health Centers",
    "wof:placetype":"venue"
},
  "geometry": {"coordinates":[-80.317871,25.86768],"type":"Point"}
}