{
  "type": "Feature",
  "properties": {
    "addr:full":"342 N Grant St Longwood FL 32750",
    "addr:housenumber":"342",
    "addr:postcode":"32750",
    "addr:street":"N Grant St",
    "iso:country":"US",
    "sg:address":"342 N Grant St",
    "sg:city":"Longwood",
    "sg:classifiers":[
        {
            "category":"Retail",
            "subcategory":"Auto Repair",
            "type":"Services"
        }
    ],
    "sg:phone":"+1 407 260 6354",
    "sg:postcode":"32750",
    "sg:province":"FL",
    "sg:tags":[
        "general"
    ],
    "wof:name":"Oyler Automotive",
    "wof:placetype":"venue"
},
  "geometry": {"coordinates":[-81.338094,28.702687],"type":"Point"}
}