{
  "type": "Feature",
  "properties": {
    "iso:country":"US",
    "sg:address":"1805 Copeland St",
    "sg:city":"Jacksonville",
    "sg:classifiers":[
        {
            "category":"Manufacturing",
            "subcategory":"Tools & Machinery",
            "type":"Manufacturing & Wholesale Goods"
        }
    ],
    "sg:phone":"+1 904 355 9301",
    "sg:postcode":"32204",
    "sg:province":"FL",
    "sg:tags":[
        "recording",
        "medium",
        "mfg"
    ],
    "wof:name":"EZ Link",
    "wof:placetype":"venue"
},
  "geometry": {"coordinates":[-81.683626,30.309066],"type":"Point"}
}