{
  "type": "Feature",
  "properties": {
    "iso:country":"US",
    "sg:address":"5058 Airport Pulling Rd N",
    "sg:city":"Naples",
    "sg:classifiers":[
        {
            "category":"Real Estate",
            "subcategory":"Real Estate Operator",
            "type":"Services"
        }
    ],
    "sg:phone":"+1 239 435 0160",
    "sg:postcode":"34109",
    "sg:province":"FL",
    "sg:tags":[
        "mall",
        "shopping",
        "center"
    ],
    "wof:name":"Carillon Place",
    "wof:placetype":"venue"
},
  "geometry": {"coordinates":[-81.768407,26.211671],"type":"Point"}
}