{
  "type": "Feature",
  "properties": {
    "addr:full":"1381 N Palm Ave Hollywood FL 33026",
    "addr:housenumber":"1381",
    "addr:postcode":"33026",
    "addr:street":"N Palm Ave",
    "iso:country":"US",
    "sg:address":"1381 N Palm Ave",
    "sg:city":"Hollywood",
    "sg:classifiers":[
        {
            "category":"Retail",
            "subcategory":"Laundry & Dry Cleaning",
            "type":"Services"
        }
    ],
    "sg:phone":"+1 954 431 8902",
    "sg:postcode":"33026",
    "sg:province":"FL",
    "wof:name":"Dry Cleaner",
    "wof:placetype":"venue"
},
  "geometry": {"coordinates":[-80.280359,26.021917],"type":"Point"}
}