{
  "type": "Feature",
  "properties": {
    "iso:country":"US",
    "sg:address":"2209 Glen Mist Dr",
    "sg:city":"Valrico",
    "sg:classifiers":[
        {
            "category":"Building & Trades",
            "subcategory":"Construction",
            "type":"Services"
        }
    ],
    "sg:phone":"+1 813 684 3688",
    "sg:postcode":"33594",
    "sg:province":"FL",
    "sg:tags":[
        "home",
        "contractor",
        "general"
    ],
    "wof:name":"Donald F Vold Construction Inc",
    "wof:placetype":"venue"
},
  "geometry": {"coordinates":[-82.226283,27.910796],"type":"Point"}
}