{
  "type": "Feature",
  "properties": {
    "iso:country":"US",
    "sg:address":"7814 Leo Kidd Ave",
    "sg:city":"Port Richey",
    "sg:classifiers":[
        {
            "category":"Building & Trades",
            "subcategory":"Plumbing",
            "type":"Services"
        }
    ],
    "sg:phone":"+1 727 848 6174",
    "sg:postcode":"34668",
    "sg:province":"FL",
    "sg:tags":[
        "plumbing",
        "contractor"
    ],
    "wof:name":"Skagg's Plumbing",
    "wof:placetype":"venue"
},
  "geometry": {"coordinates":[-82.71546499999999,28.27251],"type":"Point"}
}