{
  "type": "Feature",
  "properties": {
    "addr:full":"12101 S Dixie Hwy Miami FL 33156",
    "addr:housenumber":"12101",
    "addr:postcode":"33156",
    "addr:street":"S Dixie Hwy",
    "iso:country":"US",
    "sg:address":"12101 S Dixie Hwy",
    "sg:city":"Miami",
    "sg:classifiers":[
        {
            "category":"Shopping",
            "subcategory":"Clothing, Apparel, & Fashions",
            "type":"Retail Goods"
        }
    ],
    "sg:phone":"+1 305 254 1575",
    "sg:postcode":"33156",
    "sg:province":"FL",
    "sg:tags":[
        "clothing",
        "women's"
    ],
    "wof:name":"D'or #5",
    "wof:placetype":"venue"
},
  "geometry": {"coordinates":[-80.327248,25.657995],"type":"Point"}
}