{
  "type": "Feature",
  "properties": {
    "iso:country":"US",
    "sg:address":"4300 10th Ave N",
    "sg:city":"Lake Worth",
    "sg:classifiers":[
        {
            "category":"Education",
            "subcategory":"Special Training",
            "type":"Public Place"
        }
    ],
    "sg:phone":"+1 561 330 7007",
    "sg:postcode":"33461",
    "sg:province":"FL",
    "sg:tags":[
        "instruction",
        "driving"
    ],
    "wof:name":"A Driving & Traffic School",
    "wof:placetype":"venue"
},
  "geometry": {"coordinates":[-80.111707,26.629363],"type":"Point"}
}