{
  "type": "Feature",
  "properties": {
    "iso:country":"US",
    "sg:address":"1532 Land O Lakes Blvd",
    "sg:city":"Lutz",
    "sg:classifiers":[
        {
            "category":"Shopping",
            "subcategory":"Clothing, Apparel, & Fashions",
            "type":"Retail Goods"
        }
    ],
    "sg:phone":"+1 813 929 8161",
    "sg:postcode":"33549",
    "sg:province":"FL",
    "wof:name":"Storm Erotica Creations",
    "wof:placetype":"venue"
},
  "geometry": {"coordinates":[-82.464281,28.178094],"type":"Point"}
}