{
  "type": "Feature",
  "properties": {
    "iso:country":"US",
    "sg:address":"2335 E Atlantic Blvd",
    "sg:city":"Pompano Beach",
    "sg:classifiers":[
        {
            "category":"Shopping",
            "subcategory":"Computers & Home Electronics",
            "type":"Retail Goods"
        }
    ],
    "sg:phone":"+1 954 943 2322",
    "sg:postcode":"33062",
    "sg:province":"FL",
    "sg:tags":[
        "software"
    ],
    "wof:name":"Bluesuitmom Com",
    "wof:placetype":"venue"
},
  "geometry": {"coordinates":[-80.10029,26.231943],"type":"Point"}
}