{
  "type": "Feature",
  "properties": {
    "iso:country":"US",
    "sg:address":"4300 18th St W",
    "sg:city":"Bradenton",
    "sg:classifiers":[
        {
            "category":"Professional",
            "subcategory":"Management & Consulting",
            "type":"Services"
        }
    ],
    "sg:phone":"+1 941 758 1923",
    "sg:postcode":"34205",
    "sg:province":"FL",
    "sg:tags":[
        "marketing",
        "program"
    ],
    "wof:name":"Mulholland Marketing",
    "wof:placetype":"venue"
},
  "geometry": {"coordinates":[-82.578981,27.46247],"type":"Point"}
}