{
  "type": "Feature",
  "properties": {
    "addr:full":"3191 Coral Way Ste 623 Coral Gables FL 33145",
    "addr:housenumber":"3191",
    "addr:postcode":"33145",
    "addr:street":"Coral Way Ste 623",
    "iso:country":"US",
    "sg:address":"3191 Coral Way Ste 623",
    "sg:city":"Coral Gables",
    "sg:classifiers":[
        {
            "category":"Professional",
            "subcategory":"Lawyer & Legal Services",
            "type":"Services"
        }
    ],
    "sg:phone":"+1 305 444 4303",
    "sg:postcode":"33145",
    "sg:province":"FL",
    "wof:name":"Law Office of Wahid and Vizcaino PA",
    "wof:placetype":"venue"
},
  "geometry": {"coordinates":[-80.24539,25.750387],"type":"Point"}
}