{
  "type": "Feature",
  "properties": {
    "iso:country":"US",
    "sg:address":"2298 NW 21st Ter",
    "sg:city":"Miami",
    "sg:classifiers":[
        {
            "category":"Wholesale",
            "subcategory":"Apparel",
            "type":"Manufacturing & Wholesale Goods"
        }
    ],
    "sg:phone":"+1 305 633 4449",
    "sg:postcode":"33142",
    "sg:province":"FL",
    "wof:name":"Gico Co",
    "wof:placetype":"venue"
},
  "geometry": {"coordinates":[-80.23258,25.796338],"type":"Point"}
}