{
  "type": "Feature",
  "properties": {
    "addr:full":"13055 Park Blvd Seminole FL 33776",
    "addr:housenumber":"13055",
    "addr:postcode":"33776",
    "addr:street":"Park Blvd",
    "iso:country":"US",
    "sg:address":"13055 Park Blvd",
    "sg:city":"Seminole",
    "sg:classifiers":[
        {
            "category":"Freight",
            "type":"Transportation"
        }
    ],
    "sg:phone":"+1 727 397 8424",
    "sg:postcode":"33776",
    "sg:province":"FL",
    "sg:tags":[
        "warehouse"
    ],
    "sg:website":"www.workshopwarehouse.com",
    "wof:name":"Oakhurst Management Inc",
    "wof:placetype":"venue"
},
  "geometry": {"coordinates":[-82.818089,27.843726],"type":"Point"}
}