{
  "type": "Feature",
  "properties": {
    "iso:country":"US",
    "sg:address":"19101 Mystic Pointe Dr",
    "sg:city":"Miami",
    "sg:classifiers":[
        {
            "category":"Real Estate",
            "subcategory":"Real Estate Agent",
            "type":"Services"
        }
    ],
    "sg:phone":"+1 305 852 4656",
    "sg:postcode":"33180",
    "sg:province":"FL",
    "wof:name":"Paradise To Reality & Back",
    "wof:placetype":"venue"
},
  "geometry": {"coordinates":[-80.128113,25.953922],"type":"Point"}
}