{
  "type": "Feature",
  "properties": {
    "iso:country":"US",
    "sg:address":"1582 Garden Ave",
    "sg:city":"Daytona Beach",
    "sg:classifiers":[
        {
            "category":"Manufacturing",
            "subcategory":"Metals",
            "type":"Manufacturing & Wholesale Goods"
        },
        {
            "category":"Wholesale",
            "subcategory":"Metals & Minerals",
            "type":"Manufacturing & Wholesale Goods"
        }
    ],
    "sg:phone":"+1 386 677 0210",
    "sg:postcode":"32117",
    "sg:province":"FL",
    "sg:tags":[
        "building",
        "prefabricated",
        "aluminum",
        "mfg"
    ],
    "wof:name":"Budget Aluminum",
    "wof:placetype":"venue"
},
  "geometry": {"coordinates":[-81.050361,29.25305],"type":"Point"}
}