{
  "type": "Feature",
  "properties": {
    "iso:country":"US",
    "sg:address":"255 SW 96th Ln",
    "sg:city":"Ocala",
    "sg:classifiers":[
        {
            "category":"Building & Trades",
            "subcategory":"Electrical",
            "type":"Services"
        }
    ],
    "sg:phone":"+1 352 873 8400",
    "sg:postcode":"34476",
    "sg:province":"FL",
    "sg:tags":[
        "electrical",
        "electric",
        "contractor"
    ],
    "wof:name":"Crandon Electric Co Inc",
    "wof:placetype":"venue"
},
  "geometry": {"coordinates":[-82.144553,29.081028],"type":"Point"}
}