{
  "type": "Feature",
  "properties": {
    "iso:country":"US",
    "sg:address":"2455 S Okeechobee Rd",
    "sg:city":"Hialeah",
    "sg:classifiers":[
        {
            "category":"Personal",
            "subcategory":"Barber",
            "type":"Services"
        }
    ],
    "sg:phone":"+1 305 887 9136",
    "sg:postcode":"33010",
    "sg:province":"FL",
    "sg:tags":[
        "shop"
    ],
    "wof:name":"Heribertos Barber Shop",
    "wof:placetype":"venue"
},
  "geometry": {"coordinates":[-80.30918699999999,25.844144],"type":"Point"}
}