{
  "type": "Feature",
  "properties": {
    "addr:full":"7210 NW 43rd St Miami FL 33166",
    "addr:housenumber":"7210",
    "addr:postcode":"33166",
    "addr:street":"Nw 43Rd St",
    "iso:country":"US",
    "sg:address":"7210 NW 43rd St",
    "sg:city":"Miami",
    "sg:classifiers":[
        {
            "category":"Wholesale",
            "subcategory":"Durable Goods & Equipment",
            "type":"Manufacturing & Wholesale Goods"
        }
    ],
    "sg:phone":"+1 305 599 8505",
    "sg:postcode":"33166",
    "sg:province":"FL",
    "sg:tags":[
        "exporter"
    ],
    "wof:name":"Ocean Rider Sandals & Belts",
    "wof:placetype":"venue"
},
  "geometry": {"coordinates":[-80.31518199999999,25.813353],"type":"Point"}
}