{
  "type": "Feature",
  "properties": {
    "iso:country":"US",
    "sg:address":"6500 Prado Blvd",
    "sg:city":"Coral Gables",
    "sg:classifiers":[
        {
            "category":"Organizations",
            "subcategory":"Professional Association",
            "type":"Services"
        },
        {
            "category":"Organizations",
            "subcategory":"Community Association",
            "type":"Services"
        }
    ],
    "sg:phone":"+1 305 661 4080",
    "sg:postcode":"33143",
    "sg:province":"FL",
    "wof:name":"Tahiti Beach Homeowners Assn",
    "wof:placetype":"venue"
},
  "geometry": {"coordinates":[-80.25645799999999,25.703989],"type":"Point"}
}