{
  "type": "Feature",
  "properties": {
    "iso:country":"US",
    "sg:address":"4360 Peters Rd",
    "sg:city":"Plantation",
    "sg:classifiers":[
        {
            "category":"Professional",
            "type":"Services"
        },
        {
            "category":"Professional",
            "subcategory":"Advertising",
            "type":"Services"
        }
    ],
    "sg:phone":"+1 954 583 3900",
    "sg:postcode":"33317",
    "sg:province":"FL",
    "sg:tags":[
        "sample",
        "product",
        "service-circular",
        "fair",
        "agency",
        "specialty",
        "trade",
        "distributing",
        "exposition",
        "advertising-promotional",
        "shows"
    ],
    "sg:website":"http://www.sepub.com",
    "wof:name":"Southeast Publications",
    "wof:placetype":"venue"
},
  "geometry": {"coordinates":[-80.206463,26.106255],"type":"Point"}
}