{
  "type": "Feature",
  "properties": {
    "iso:country":"US",
    "sg:address":"9931 SW 23rd St",
    "sg:city":"Fort Lauderdale",
    "sg:classifiers":[
        {
            "category":"Wholesale",
            "subcategory":"Apparel",
            "type":"Manufacturing & Wholesale Goods"
        }
    ],
    "sg:phone":"+1 954 476 0089",
    "sg:postcode":"33324",
    "sg:province":"FL",
    "sg:tags":[
        "clothing"
    ],
    "wof:name":"Zucco Boutique",
    "wof:placetype":"venue"
},
  "geometry": {"coordinates":[-80.26663600000001,26.093658],"type":"Point"}
}