{
  "type": "Feature",
  "properties": {
    "addr:full":"5637 Pierce St Hollywood FL 33021",
    "addr:housenumber":"5637",
    "addr:postcode":"33021",
    "addr:street":"Pierce St",
    "iso:country":"US",
    "sg:address":"5637 Pierce St",
    "sg:city":"Hollywood",
    "sg:classifiers":[
        {
            "category":"Building & Trades",
            "subcategory":"Electrical",
            "type":"Services"
        }
    ],
    "sg:phone":"+1 954 962 5504",
    "sg:postcode":"33021",
    "sg:province":"FL",
    "sg:tags":[
        "electrical",
        "contractor"
    ],
    "wof:name":"Dissel Alarms",
    "wof:placetype":"venue"
},
  "geometry": {"coordinates":[-80.20098299999999,26.015051],"type":"Point"}
}