{
  "type": "Feature",
  "properties": {
    "iso:country":"US",
    "sg:address":"940 NW 123rd Ct",
    "sg:city":"Miami",
    "sg:classifiers":[
        {
            "category":"Freight",
            "type":"Transportation"
        }
    ],
    "sg:phone":"+1 305 227 2265",
    "sg:postcode":"33182",
    "sg:province":"FL",
    "sg:tags":[
        "operator",
        "trucking"
    ],
    "wof:name":"Maurie S Getter W Katia A",
    "wof:placetype":"venue"
},
  "geometry": {"coordinates":[-80.393451,25.778569],"type":"Point"}
}