{
  "type": "Feature",
  "properties": {
    "addr:full":"24201 SW Martin Hwy Okeechobee FL 34974",
    "addr:housenumber":"24201",
    "addr:postcode":"34974",
    "addr:street":"Sw Martin Hwy",
    "iso:country":"US",
    "sg:address":"24201 SW Martin Hwy",
    "sg:city":"Okeechobee",
    "sg:classifiers":[
        {
            "category":"Government",
            "subcategory":"Fire Station",
            "type":"Public Place"
        }
    ],
    "sg:phone":"+1 772 597 2800",
    "sg:postcode":"34974",
    "sg:province":"FL",
    "sg:tags":[
        "county",
        "protection"
    ],
    "wof:name":"Fire Department",
    "wof:placetype":"venue"
},
  "geometry": {"coordinates":[-80.585966,27.162179],"type":"Point"}
}