{
  "type": "Feature",
  "properties": {
    "iso:country":"US",
    "sg:address":"6207 NW 164th St",
    "sg:city":"Alachua",
    "sg:classifiers":[
        {
            "category":"Building & Trades",
            "subcategory":"Construction",
            "type":"Services"
        },
        {
            "category":"Military Area",
            "subcategory":"Armory",
            "type":"Public Place"
        }
    ],
    "sg:phone":"+1 386 462 4507",
    "sg:postcode":"32615",
    "sg:province":"FL",
    "sg:tags":[
        "repair",
        "fence-sales",
        "fence",
        "contractor"
    ],
    "wof:name":"Cloverleaf Fencing",
    "wof:placetype":"venue"
},
  "geometry": {"coordinates":[-82.517143,29.712653],"type":"Point"}
}