{
  "type": "Feature",
  "properties": {
    "addr:full":"314 Angle Rd Fort Pierce FL 34947",
    "addr:housenumber":"314",
    "addr:postcode":"34947",
    "addr:street":"Angle Rd",
    "iso:country":"US",
    "sg:address":"314 Angle Rd",
    "sg:city":"Fort Pierce",
    "sg:classifiers":[
        {
            "category":"Retail",
            "subcategory":"Auto Repair",
            "type":"Services"
        }
    ],
    "sg:phone":"+1 772 461 8855",
    "sg:postcode":"34947",
    "sg:province":"FL",
    "sg:tags":[
        "body",
        "automobile",
        "painting"
    ],
    "wof:name":"Cleveland's Auto & Truck Rpr",
    "wof:placetype":"venue"
},
  "geometry": {"coordinates":[-80.359375,27.450091],"type":"Point"}
}