{
  "type": "Feature",
  "properties": {
    "iso:country":"US",
    "sg:address":"3900 NW 79th Ave Ste 455",
    "sg:city":"Doral",
    "sg:classifiers":[
        {
            "category":"Insurance",
            "subcategory":"Hazard Insurance",
            "type":"Services"
        }
    ],
    "sg:phone":"+1 305 513 9703",
    "sg:postcode":"33166",
    "sg:province":"FL",
    "sg:tags":[
        "commercial",
        "business"
    ],
    "sg:website":"http://www.myels.com",
    "wof:name":"Employee Leasing Solutions",
    "wof:placetype":"venue"
},
  "geometry": {"coordinates":[-80.32531,25.809401],"type":"Point"}
}