{
  "type": "Feature",
  "properties": {
    "iso:country":"US",
    "sg:address":"126 S Lake Parker Ave",
    "sg:city":"Lakeland",
    "sg:classifiers":[
        {
            "category":"Retail",
            "subcategory":"Auto Rental",
            "type":"Services"
        }
    ],
    "sg:phone":"+1 863 666 3238",
    "sg:postcode":"33801",
    "sg:province":"FL",
    "sg:tags":[
        "car",
        "used",
        "leasing",
        "sales"
    ],
    "wof:name":"Rent-A-Wreck",
    "wof:placetype":"venue"
},
  "geometry": {"coordinates":[-81.940718,28.043292],"type":"Point"}
}