{
  "type": "Feature",
  "properties": {
    "iso:country":"US",
    "sg:address":"7170 E Calypso Loop",
    "sg:city":"Inverness",
    "sg:classifiers":[
        {
            "category":"Professional",
            "subcategory":"Lawyer & Legal Services",
            "type":"Services"
        }
    ],
    "sg:phone":"+1 352 726 3645",
    "sg:postcode":"34453",
    "sg:province":"FL",
    "sg:tags":[
        "attorney"
    ],
    "wof:name":"Lonnie F Daughtery",
    "wof:placetype":"venue"
},
  "geometry": {"coordinates":[-82.31483,28.881761],"type":"Point"}
}