{
  "type": "Feature",
  "properties": {
    "iso:country":"US",
    "sg:address":"906 W Hallandale Beach Blvd",
    "sg:city":"Hallandale Beach",
    "sg:classifiers":[
        {
            "category":"Local Transit",
            "type":"Transportation"
        }
    ],
    "sg:phone":"+1 954 987 1533",
    "sg:postcode":"33009",
    "sg:province":"FL",
    "sg:tags":[
        "limousine"
    ],
    "wof:name":"Stuart's Car & Limo Svc",
    "wof:placetype":"venue"
},
  "geometry": {"coordinates":[-80.15971999999999,25.985303],"type":"Point"}
}