{
  "type": "Feature",
  "properties": {
    "addr:full":"7448 Wiles Rd Coral Springs FL 33067",
    "addr:housenumber":"7448",
    "addr:postcode":"33067",
    "addr:street":"Wiles Rd",
    "iso:country":"US",
    "sg:address":"7448 Wiles Rd",
    "sg:city":"Coral Springs",
    "sg:classifiers":[
        {
            "category":"Shopping",
            "subcategory":"Clothing, Apparel, & Fashions",
            "type":"Retail Goods"
        }
    ],
    "sg:phone":"+1 954 753 8670",
    "sg:postcode":"33067",
    "sg:province":"FL",
    "sg:tags":[
        "tailor"
    ],
    "wof:name":"Alterations By Tina",
    "wof:placetype":"venue"
},
  "geometry": {"coordinates":[-80.22679100000001,26.286619],"type":"Point"}
}