{
  "type": "Feature",
  "properties": {
    "iso:country":"US",
    "sg:address":"4627 N Davis Hwy",
    "sg:city":"Pensacola",
    "sg:classifiers":[
        {
            "category":"Health Services",
            "subcategory":"Doctor",
            "type":"Services"
        }
    ],
    "sg:phone":"+1 850 476 2602",
    "sg:postcode":"32503",
    "sg:province":"FL",
    "sg:tags":[
        "dentist"
    ],
    "wof:name":"John H Hinman III DDS",
    "wof:placetype":"venue"
},
  "geometry": {"coordinates":[-87.224295,30.464934],"type":"Point"}
}