{
  "type": "Feature",
  "properties": {
    "addr:full":"5 Via Angelica Palm Beach Gardens FL 33418",
    "addr:postcode":"33418",
    "addr:street":"Via Angelica",
    "iso:country":"US",
    "sg:address":"5 Via Angelica",
    "sg:city":"Palm Beach Gardens",
    "sg:classifiers":[
        {
            "category":"Professional",
            "subcategory":"Credit Reporting & Collection",
            "type":"Services"
        }
    ],
    "sg:phone":"+1 561 624 7383",
    "sg:postcode":"33418",
    "sg:province":"FL",
    "wof:name":"Gd Receivables Inc",
    "wof:placetype":"venue"
},
  "geometry": {"coordinates":[-80.134272,26.822042],"type":"Point"}
}