{
  "type": "Feature",
  "properties": {
    "addr:full":"301 Bay St Ocoee FL 34761",
    "addr:housenumber":"301",
    "addr:postcode":"34761",
    "addr:street":"Bay St",
    "iso:country":"US",
    "sg:address":"301 Bay St",
    "sg:city":"Ocoee",
    "sg:classifiers":[
        {
            "category":"Building & Trades",
            "subcategory":"Landscaping Services",
            "type":"Services"
        }
    ],
    "sg:phone":"+1 407 654 2250",
    "sg:postcode":"34761",
    "sg:province":"FL",
    "wof:name":"Baileys Lawn Service",
    "wof:placetype":"venue"
},
  "geometry": {"coordinates":[-81.5476,28.566072],"type":"Point"}
}