{
  "type": "Feature",
  "properties": {
    "iso:country":"US",
    "sg:address":"1190 W Boynton Beach Blvd",
    "sg:city":"Boynton Beach",
    "sg:classifiers":[
        {
            "category":"Sports & Exercise",
            "subcategory":"Bowling",
            "type":"Entertainment"
        }
    ],
    "sg:phone":"+1 561 734 1500",
    "sg:postcode":"33426",
    "sg:province":"FL",
    "sg:tags":[
        "center"
    ],
    "sg:website":"www.amf.com",
    "wof:name":"AMF Boynton Beach Lanes",
    "wof:placetype":"venue"
},
  "geometry": {"coordinates":[-80.083682,26.528025],"type":"Point"}
}