{
  "type": "Feature",
  "properties": {
    "addr:full":"1137 Oakhill St Seffner FL 33584",
    "addr:housenumber":"1137",
    "addr:postcode":"33584",
    "addr:street":"Oakhill St",
    "iso:country":"US",
    "sg:address":"1137 Oakhill St",
    "sg:city":"Seffner",
    "sg:classifiers":[
        {
            "category":"Building & Trades",
            "subcategory":"Construction",
            "type":"Services"
        },
        {
            "category":"Military Area",
            "subcategory":"Armory",
            "type":"Public Place"
        }
    ],
    "sg:phone":"+1 813 689 0115",
    "sg:postcode":"33584",
    "sg:province":"FL",
    "sg:tags":[
        "repair",
        "fence-sales",
        "fence",
        "contractor"
    ],
    "wof:name":"Ocean Bay Fence Inc",
    "wof:placetype":"venue"
},
  "geometry": {"coordinates":[-82.29250399999999,27.9884],"type":"Point"}
}