{
  "type": "Feature",
  "properties": {
    "addr:full":"601 Orchard Ave Ormond Beach FL 32174",
    "addr:housenumber":"601",
    "addr:postcode":"32174",
    "addr:street":"Orchard Ave",
    "iso:country":"US",
    "sg:address":"601 Orchard Ave",
    "sg:city":"Ormond Beach",
    "sg:classifiers":[
        {
            "category":"Health Services",
            "subcategory":"Nursing And Care Facility",
            "type":"Services"
        }
    ],
    "sg:phone":"+1 386 672 4654",
    "sg:postcode":"32174",
    "sg:province":"FL",
    "sg:tags":[
        "home",
        "retirement",
        "community"
    ],
    "wof:name":"KOZY Korner Assisted Living",
    "wof:placetype":"venue"
},
  "geometry": {"coordinates":[-81.05890599999999,29.262658],"type":"Point"}
}