{
  "type": "Feature",
  "properties": {
    "addr:full":"11900 SW 26th St Fort Lauderdale FL 33325",
    "addr:housenumber":"11900",
    "addr:postcode":"33325",
    "addr:street":"Sw 26Th St",
    "iso:country":"US",
    "sg:address":"11900 SW 26th St",
    "sg:city":"Fort Lauderdale",
    "sg:classifiers":[
        {
            "category":"Real Estate",
            "subcategory":"Real Estate Agent",
            "type":"Services"
        }
    ],
    "sg:phone":"+1 954 723 0505",
    "sg:postcode":"33325",
    "sg:province":"FL",
    "wof:name":"Haughton Inc",
    "wof:placetype":"venue"
},
  "geometry": {"coordinates":[-80.30797,26.087561],"type":"Point"}
}