{
  "type": "Feature",
  "properties": {
    "iso:country":"US",
    "sg:address":"255 N Congress Ave",
    "sg:city":"Delray Beach",
    "sg:classifiers":[
        {
            "category":"Manufacturing",
            "subcategory":"Tools & Machinery",
            "type":"Manufacturing & Wholesale Goods"
        }
    ],
    "sg:phone":"+1 561 272 0770",
    "sg:postcode":"33445",
    "sg:province":"FL",
    "sg:tags":[
        "manufacture",
        "steel",
        "sheet",
        "die",
        "m",
        "machine",
        "fishing",
        "reel"
    ],
    "sg:website":"www.tiborreel.com",
    "wof:name":"Juracsik Ted Tool & Die",
    "wof:placetype":"venue"
},
  "geometry": {"coordinates":[-80.093478,26.467871],"type":"Point"}
}