{
  "type": "Feature",
  "properties": {
    "iso:country":"US",
    "sg:address":"4219 E 19th Ave",
    "sg:city":"Tampa",
    "sg:classifiers":[
        {
            "category":"Farming",
            "subcategory":"Dairy Farm",
            "type":"Manufacturing & Wholesale Goods"
        },
        {
            "category":"Wholesale",
            "subcategory":"Dairy",
            "type":"Manufacturing & Wholesale Goods"
        }
    ],
    "sg:phone":"+1 813 621 7805",
    "sg:postcode":"33605",
    "sg:province":"FL",
    "sg:tags":[
        "product"
    ],
    "sg:website":"www.deansfoods.com",
    "wof:name":"T G Lee Foods Inc",
    "wof:placetype":"venue"
},
  "geometry": {"coordinates":[-82.41280399999999,27.968434],"type":"Point"}
}