{
  "type": "Feature",
  "properties": {
    "iso:country":"US",
    "sg:address":"1581 Bella Cruz Dr",
    "sg:city":"Lady Lake",
    "sg:classifiers":[
        {
            "category":"Shopping",
            "subcategory":"Pharmacy",
            "type":"Retail Goods"
        }
    ],
    "sg:phone":"+1 352 750 9200",
    "sg:postcode":"32159",
    "sg:province":"FL",
    "wof:name":"Walgreens",
    "wof:placetype":"venue"
},
  "geometry": {"coordinates":[-81.95830599999999,28.951703],"type":"Point"}
}