{
  "type": "Feature",
  "properties": {
    "iso:country":"US",
    "sg:address":"887 Ocoee Apopka Rd",
    "sg:city":"Apopka",
    "sg:classifiers":[
        {
            "category":"Building & Trades",
            "subcategory":"Cleaning & Sanitation",
            "type":"Services"
        }
    ],
    "sg:phone":"+1 407 814 8800",
    "sg:postcode":"32703",
    "sg:province":"FL",
    "sg:tags":[
        "marble",
        "terrazzo"
    ],
    "wof:name":"Precision Marble Of Central Fl",
    "wof:placetype":"venue"
},
  "geometry": {"coordinates":[-81.520179,28.665967],"type":"Point"}
}