{
  "type": "Feature",
  "properties": {
    "iso:country":"US",
    "sg:address":"6827 Amberjack Ln",
    "sg:city":"Port Richey",
    "sg:classifiers":[
        {
            "category":"Arts & Performance",
            "subcategory":"Theater",
            "type":"Entertainment"
        }
    ],
    "sg:phone":"+1 727 863 0068",
    "sg:postcode":"34667",
    "sg:province":"FL",
    "sg:tags":[
        "group"
    ],
    "wof:name":"Richey Community Orchestra",
    "wof:placetype":"venue"
},
  "geometry": {"coordinates":[-82.698956,28.346172],"type":"Point"}
}