{
  "type": "Feature",
  "properties": {
    "addr:full":"11965 49th St N Clearwater FL 33762",
    "addr:housenumber":"11965",
    "addr:postcode":"33762",
    "addr:street":"49Th St N",
    "iso:country":"US",
    "sg:address":"11965 49th St N",
    "sg:city":"Clearwater",
    "sg:classifiers":[
        {
            "category":"Autos & Motor Vehicles",
            "subcategory":"Auto Supplies",
            "type":"Retail Goods"
        }
    ],
    "sg:phone":"+1 727 592 0661",
    "sg:postcode":"33762",
    "sg:province":"FL",
    "sg:tags":[
        "recap",
        "repair",
        "retread",
        "tire",
        "sale"
    ],
    "wof:name":"Millenium Tire Service",
    "wof:placetype":"venue"
},
  "geometry": {"coordinates":[-82.700205,27.880798],"type":"Point"}
}