{
  "type": "Feature",
  "properties": {
    "iso:country":"US",
    "sg:address":"1205 Pennsylvania Ave",
    "sg:city":"Lynn Haven",
    "sg:classifiers":[
        {
            "category":"Building & Trades",
            "subcategory":"Construction",
            "type":"Services"
        }
    ],
    "sg:phone":"+1 850 265 0215",
    "sg:postcode":"32444",
    "sg:province":"FL",
    "sg:tags":[
        "hanging",
        "contractor"
    ],
    "wof:name":"Professional Painting",
    "wof:placetype":"venue"
},
  "geometry": {"coordinates":[-85.64755100000001,30.239165],"type":"Point"}
}