{
  "type": "Feature",
  "properties": {
    "iso:country":"US",
    "sg:address":"2350 Bradford St",
    "sg:city":"Jacksonville",
    "sg:classifiers":[
        {
            "category":"Professional",
            "type":"Services"
        }
    ],
    "sg:phone":"+1 904 388 0168",
    "sg:postcode":"32209",
    "sg:province":"FL",
    "wof:name":"Ronald A Colleton",
    "wof:placetype":"venue"
},
  "geometry": {"coordinates":[-81.702472,30.335769],"type":"Point"}
}