{
  "type": "Feature",
  "properties": {
    "iso:country":"US",
    "sg:address":"5900 Wedgewood Village Cir",
    "sg:city":"Lake Worth",
    "sg:classifiers":[
        {
            "category":"Professional",
            "subcategory":"Lawyer & Legal Services",
            "type":"Services"
        }
    ],
    "sg:phone":"+1 561 967 2521",
    "sg:postcode":"33463",
    "sg:province":"FL",
    "wof:name":"Dohertys Professional Law",
    "wof:placetype":"venue"
},
  "geometry": {"coordinates":[-80.13808400000001,26.574772],"type":"Point"}
}