{
  "type": "Feature",
  "properties": {
    "iso:country":"US",
    "sg:address":"1790 Biarritz Cir",
    "sg:city":"Tarpon Springs",
    "sg:classifiers":[
        {
            "category":"Organizations",
            "subcategory":"Community Association",
            "type":"Services"
        }
    ],
    "sg:phone":"+1 727 943 5181",
    "sg:postcode":"34689",
    "sg:province":"FL",
    "sg:tags":[
        "membership"
    ],
    "wof:name":"Day Cruise Association",
    "wof:placetype":"venue"
},
  "geometry": {"coordinates":[-82.74421,28.168097],"type":"Point"}
}