{
  "type": "Feature",
  "properties": {
    "addr:full":"4195 SE Fairway Ct Stuart FL 34997",
    "addr:housenumber":"4195",
    "addr:postcode":"34997",
    "addr:street":"Se Fairway Ct",
    "iso:country":"US",
    "sg:address":"4195 SE Fairway Ct",
    "sg:city":"Stuart",
    "sg:classifiers":[
        {
            "category":"Real Estate",
            "subcategory":"Real Estate Agent",
            "type":"Services"
        }
    ],
    "sg:phone":"+1 772 283 8404",
    "sg:postcode":"34997",
    "sg:province":"FL",
    "wof:name":"Kelley Mac Realty",
    "wof:placetype":"venue"
},
  "geometry": {"coordinates":[-80.20007,27.165363],"type":"Point"}
}