{
  "type": "Feature",
  "properties": {
    "addr:full":"8354 S Dixie Hwy Miami FL 33143",
    "addr:housenumber":"8354",
    "addr:postcode":"33143",
    "addr:street":"S Dixie Hwy",
    "iso:country":"US",
    "sg:address":"8354 S Dixie Hwy",
    "sg:city":"Miami",
    "sg:classifiers":[
        {
            "category":"Shopping",
            "subcategory":"Crafts & Fabrics",
            "type":"Retail Goods"
        }
    ],
    "sg:phone":"+1 305 665 6793",
    "sg:postcode":"33143",
    "sg:province":"FL",
    "sg:tags":[
        "art",
        "supply"
    ],
    "wof:name":"Michaels Arts & Crafts",
    "wof:placetype":"venue"
},
  "geometry": {"coordinates":[-80.30390199999999,25.692801],"type":"Point"}
}