{
  "type": "Feature",
  "properties": {
    "addr:full":"221 Southern Blvd West Palm Beach FL 33405",
    "addr:housenumber":"221",
    "addr:postcode":"33405",
    "addr:street":"Southern Blvd",
    "iso:country":"US",
    "sg:address":"221 Southern Blvd",
    "sg:city":"West Palm Beach",
    "sg:classifiers":[
        {
            "category":"Professional",
            "subcategory":"Accounting & Tax Preparation",
            "type":"Services"
        }
    ],
    "sg:phone":"+1 561 655 5100",
    "sg:postcode":"33405",
    "sg:province":"FL",
    "sg:tags":[
        "accountant"
    ],
    "wof:name":"Guthrie Jacobs & Eubanks",
    "wof:placetype":"venue"
},
  "geometry": {"coordinates":[-80.05155999999999,26.675709],"type":"Point"}
}