{
  "type": "Feature",
  "properties": {
    "addr:full":"400 8th St N Naples FL 34102",
    "addr:housenumber":"400",
    "addr:postcode":"34102",
    "addr:street":"8Th St N",
    "iso:country":"US",
    "sg:address":"400 8th St N",
    "sg:city":"Naples",
    "sg:classifiers":[
        {
            "category":"Health Services",
            "subcategory":"Doctor",
            "type":"Services"
        }
    ],
    "sg:phone":"+1 239 649 3337",
    "sg:postcode":"34102",
    "sg:province":"FL",
    "sg:tags":[
        "medical"
    ],
    "wof:name":"Carolyn Venable MD",
    "wof:placetype":"venue"
},
  "geometry": {"coordinates":[-81.797719,26.1527],"type":"Point"}
}