{
  "type": "Feature",
  "properties": {
    "iso:country":"US",
    "sg:address":"1209 N Harbor City Blvd",
    "sg:city":"Melbourne",
    "sg:classifiers":[
        {
            "category":"Food & Beverages",
            "subcategory":"Bakery",
            "type":"Retail Goods"
        }
    ],
    "sg:phone":"+1 321 751 6447",
    "sg:postcode":"32935",
    "sg:province":"FL",
    "sg:tags":[
        "bagel"
    ],
    "wof:name":"Bagelicious",
    "wof:placetype":"venue"
},
  "geometry": {"coordinates":[-80.63022599999999,28.127094],"type":"Point"}
}