{
  "type": "Feature",
  "properties": {
    "iso:country":"US",
    "sg:address":"5264 Clayton Ct",
    "sg:city":"Fort Myers",
    "sg:classifiers":[
        {
            "category":"Social Services",
            "type":"Services"
        }
    ],
    "sg:phone":"+1 239 939 5504",
    "sg:postcode":"33907",
    "sg:province":"FL",
    "wof:name":"Genesis 3 Counseling Center",
    "wof:placetype":"venue"
},
  "geometry": {"coordinates":[-81.874027,26.584651],"type":"Point"}
}