{
  "type": "Feature",
  "properties": {
    "addr:full":"16551 Garden Blvd Cape Coral FL 33909",
    "addr:housenumber":"16551",
    "addr:postcode":"33909",
    "addr:street":"Garden Blvd",
    "iso:country":"US",
    "sg:address":"16551 Garden Blvd",
    "sg:city":"Cape Coral",
    "sg:classifiers":[
        {
            "category":"Building & Trades",
            "subcategory":"Landscaping Services",
            "type":"Services"
        }
    ],
    "sg:phone":"+1 239 574 1620",
    "sg:postcode":"33909",
    "sg:province":"FL",
    "sg:tags":[
        "mowing"
    ],
    "wof:name":"J & D Tractor Mowing Svc",
    "wof:placetype":"venue"
},
  "geometry": {"coordinates":[-81.926282,26.706192],"type":"Point"}
}