{
  "type": "Feature",
  "properties": {
    "iso:country":"US",
    "sg:address":"13411 SW 56th St",
    "sg:city":"Miami",
    "sg:classifiers":[
        {
            "category":"Shopping",
            "subcategory":"Discount & Variety Stores",
            "type":"Retail Goods"
        }
    ],
    "sg:phone":"+1 305 220 0041",
    "sg:postcode":"33175",
    "sg:province":"FL",
    "wof:name":"Karinas Dollar Discount",
    "wof:placetype":"venue"
},
  "geometry": {"coordinates":[-80.412381,25.714561],"type":"Point"}
}