{
  "type": "Feature",
  "properties": {
    "iso:country":"US",
    "sg:address":"2362 N Forsyth Rd",
    "sg:city":"Orlando",
    "sg:classifiers":[
        {
            "category":"Professional",
            "subcategory":"Employment Agencies",
            "type":"Services"
        }
    ],
    "sg:phone":"+1 407 677 6937",
    "sg:postcode":"32807",
    "sg:province":"FL",
    "sg:tags":[
        "help",
        "contractor"
    ],
    "wof:name":"Power Staffing",
    "wof:placetype":"venue"
},
  "geometry": {"coordinates":[-81.294594,28.578553],"type":"Point"}
}