{
  "type": "Feature",
  "properties": {
    "iso:country":"US",
    "sg:address":"1237 W 8th St",
    "sg:city":"Jacksonville",
    "sg:classifiers":[
        {
            "category":"Social Services",
            "subcategory":"Child Care",
            "type":"Services"
        }
    ],
    "sg:phone":"+1 904 356 0096",
    "sg:postcode":"32209",
    "sg:province":"FL",
    "sg:tags":[
        "day"
    ],
    "wof:name":"Stars Ville Childcare",
    "wof:placetype":"venue"
},
  "geometry": {"coordinates":[-81.675134,30.347404],"type":"Point"}
}