{
  "type": "Feature",
  "properties": {
    "iso:country":"US",
    "sg:address":"16430 S Tamiami Trl",
    "sg:city":"Fort Myers",
    "sg:classifiers":[
        {
            "category":"Home & Garden",
            "subcategory":"Carpets & Floor Coverings",
            "type":"Retail Goods"
        }
    ],
    "sg:phone":"+1 239 213 3310",
    "sg:postcode":"33908",
    "sg:province":"FL",
    "sg:tags":[
        "rug",
        "carpeting"
    ],
    "wof:name":"Wayne Wiles Floor Coverings",
    "wof:placetype":"venue"
},
  "geometry": {"coordinates":[-81.856753,26.502828],"type":"Point"}
}