{
  "type": "Feature",
  "properties": {
    "iso:country":"US",
    "sg:address":"2570 Atlantic Blvd",
    "sg:city":"Jacksonville",
    "sg:classifiers":[
        {
            "category":"Shopping",
            "type":"Retail Goods"
        }
    ],
    "sg:phone":"+1 904 306 0402",
    "sg:postcode":"32207",
    "sg:province":"FL",
    "sg:tags":[
        "merchandise"
    ],
    "wof:name":"Jacksonville Hearing Aid Inc",
    "wof:placetype":"venue"
},
  "geometry": {"coordinates":[-81.637541,30.305912],"type":"Point"}
}