{
  "type": "Feature",
  "properties": {
    "addr:full":"1500 E International Speedway Blvd Deland FL 32724",
    "addr:housenumber":"1500",
    "addr:postcode":"32724",
    "addr:street":"E International Speedway Blvd",
    "iso:country":"US",
    "sg:address":"1500 E International Speedway Blvd",
    "sg:city":"Deland",
    "sg:classifiers":[
        {
            "category":"Organizations",
            "subcategory":"Religious Organization",
            "type":"Services"
        }
    ],
    "sg:phone":"+1 386 736 2948",
    "sg:postcode":"32724",
    "sg:province":"FL",
    "sg:tags":[
        "church"
    ],
    "sg:website":"www.firstassemblydeland.com",
    "wof:name":"First Assembly Of God",
    "wof:placetype":"venue"
},
  "geometry": {"coordinates":[-81.27347399999999,29.058446],"type":"Point"}
}