{
  "type": "Feature",
  "properties": {
    "addr:full":"12620 Biscayne Blvd North Miami FL 33181",
    "addr:housenumber":"12620",
    "addr:postcode":"33181",
    "addr:street":"Biscayne Blvd",
    "iso:country":"US",
    "sg:address":"12620 Biscayne Blvd",
    "sg:city":"North Miami",
    "sg:classifiers":[
        {
            "category":"Banks & Credit Unions",
            "subcategory":"Bank",
            "type":"Services"
        }
    ],
    "sg:phone":"+1 305 892 1792",
    "sg:postcode":"33181",
    "sg:province":"FL",
    "sg:website":"www.commerceonline.com",
    "wof:name":"Commerce Bank",
    "wof:placetype":"venue"
},
  "geometry": {"coordinates":[-80.18707999999999,25.8792],"type":"Point"}
}