{
  "type": "Feature",
  "properties": {
    "iso:country":"US",
    "sg:address":"1211 6th St SE",
    "sg:city":"Winter Haven",
    "sg:classifiers":[
        {
            "category":"Insurance",
            "subcategory":"Insurance Agent",
            "type":"Services"
        }
    ],
    "sg:phone":"+1 863 294 1034",
    "sg:postcode":"33880",
    "sg:province":"FL",
    "wof:name":"Nationwide",
    "wof:placetype":"venue"
},
  "geometry": {"coordinates":[-81.718543,28.009476],"type":"Point"}
}