{
  "type": "Feature",
  "properties": {
    "iso:country":"US",
    "sg:address":"821 Big Tree Rd",
    "sg:city":"Daytona Beach",
    "sg:classifiers":[
        {
            "category":"Health Services",
            "subcategory":"Doctor",
            "type":"Services"
        }
    ],
    "sg:phone":"+1 386 767 8383",
    "sg:postcode":"32119",
    "sg:province":"FL",
    "wof:name":"Russell Bizette DDS",
    "wof:placetype":"venue"
},
  "geometry": {"coordinates":[-81.018027,29.168449],"type":"Point"}
}