{
  "type": "Feature",
  "properties": {
    "iso:country":"US",
    "sg:address":"11900 Atlantic Blvd",
    "sg:city":"Jacksonville",
    "sg:classifiers":[
        {
            "category":"Restaurant",
            "type":"Food & Drink"
        }
    ],
    "sg:menulink":"http://www.allmenus.com/fl/jacksonville/232389-larrys-giant-subs/menu/",
    "sg:phone":"+1 904 221 7827",
    "sg:postcode":"32225",
    "sg:province":"FL",
    "sg:tags":[
        "wrap",
        "american",
        "sandwich"
    ],
    "wof:name":"Larry's Giant Subs",
    "wof:placetype":"venue"
},
  "geometry": {"coordinates":[-81.495002,30.320575],"type":"Point"}
}