{
  "type": "Feature",
  "properties": {
    "iso:country":"US",
    "sg:address":"1336 20th St N",
    "sg:city":"St Petersburg",
    "sg:classifiers":[
        {
            "category":"Wholesale",
            "subcategory":"Drugs",
            "type":"Manufacturing & Wholesale Goods"
        }
    ],
    "sg:phone":"+1 727 895 5845",
    "sg:postcode":"33713",
    "sg:province":"FL",
    "sg:tags":[
        "cosmetic"
    ],
    "wof:name":"Ocean Potion",
    "wof:placetype":"venue"
},
  "geometry": {"coordinates":[-82.659279,27.784736],"type":"Point"}
}