{
  "type": "Feature",
  "properties": {
    "addr:full":"500 E Lake Howard Dr Winter Haven FL 33881",
    "addr:housenumber":"500",
    "addr:postcode":"33881",
    "addr:street":"E Lake Howard Dr",
    "iso:country":"US",
    "sg:address":"500 E Lake Howard Dr",
    "sg:city":"Winter Haven",
    "sg:classifiers":[
        {
            "category":"Professional",
            "subcategory":"Employment Agencies",
            "type":"Services"
        }
    ],
    "sg:phone":"+1 863 508 1100",
    "sg:postcode":"33881",
    "sg:province":"FL",
    "sg:tags":[
        "opportunity"
    ],
    "sg:website":"www.polkworks.org",
    "wof:name":"One Stop Career Ctr",
    "wof:placetype":"venue"
},
  "geometry": {"coordinates":[-81.734707,28.025615],"type":"Point"}
}