{
  "type": "Feature",
  "properties": {
    "iso:country":"US",
    "sg:address":"1260 S Federal Hwy",
    "sg:city":"Boynton Beach",
    "sg:classifiers":[
        {
            "category":"Professional",
            "subcategory":"Accounting & Tax Preparation",
            "type":"Services"
        }
    ],
    "sg:phone":"+1 561 737 7900",
    "sg:postcode":"33435",
    "sg:province":"FL",
    "sg:tags":[
        "accountant"
    ],
    "wof:name":"Traylor Gratton & Beaumont",
    "wof:placetype":"venue"
},
  "geometry": {"coordinates":[-80.058796,26.516912],"type":"Point"}
}