{
  "type": "Feature",
  "properties": {
    "iso:country":"US",
    "sg:address":"1501 NW 3rd St",
    "sg:city":"Miami",
    "sg:classifiers":[
        {
            "category":"Communications",
            "subcategory":"Newspaper",
            "type":"Services"
        }
    ],
    "sg:phone":"+1 305 643 9801",
    "sg:postcode":"33125",
    "sg:province":"FL",
    "sg:website":"http://www.apme.com",
    "wof:name":"The Associated Press",
    "wof:placetype":"venue"
},
  "geometry": {"coordinates":[-80.219742,25.77626],"type":"Point"}
}