{
  "type": "Feature",
  "properties": {
    "iso:country":"US",
    "sg:address":"980 Montgomery Rd",
    "sg:city":"Altamonte Springs",
    "sg:classifiers":[
        {
            "category":"Professional",
            "type":"Services"
        }
    ],
    "sg:phone":"+1 407 774 7166",
    "sg:postcode":"32714",
    "sg:province":"FL",
    "wof:name":"Grove Court Assisted Living",
    "wof:placetype":"venue"
},
  "geometry": {"coordinates":[-81.402789,28.687184],"type":"Point"}
}