{
  "type": "Feature",
  "properties": {
    "iso:country":"US",
    "sg:address":"1671 SW Biltmore St",
    "sg:city":"Port Saint Lucie",
    "sg:classifiers":[
        {
            "category":"Wholesale",
            "subcategory":"Construction Materials",
            "type":"Manufacturing & Wholesale Goods"
        }
    ],
    "sg:phone":"+1 772 475 6106",
    "sg:postcode":"34984",
    "sg:province":"FL",
    "wof:name":"Souza David W Granite Stone",
    "wof:placetype":"venue"
},
  "geometry": {"coordinates":[-80.367053,27.292234],"type":"Point"}
}