{
  "type": "Feature",
  "properties": {
    "iso:country":"US",
    "sg:address":"22 Hastings Ln",
    "sg:city":"Boynton Beach",
    "sg:classifiers":[
        {
            "category":"Real Estate",
            "subcategory":"Developer",
            "type":"Services"
        }
    ],
    "sg:phone":"+1 561 432 4203",
    "sg:postcode":"33426",
    "sg:province":"FL",
    "wof:name":"Douville Development Inc",
    "wof:placetype":"venue"
},
  "geometry": {"coordinates":[-80.08446600000001,26.564656],"type":"Point"}
}