{
  "type": "Feature",
  "properties": {
    "iso:country":"US",
    "sg:address":"2455 N Atlantic Ave",
    "sg:city":"Daytona Beach",
    "sg:classifiers":[
        {
            "category":"Food & Beverages",
            "subcategory":"Groceries & Convenience Stores",
            "type":"Retail Goods"
        }
    ],
    "sg:phone":"+1 386 677 5150",
    "sg:postcode":"32118",
    "sg:province":"FL",
    "sg:tags":[
        "supermarket"
    ],
    "wof:name":"Publix Super Market 52",
    "wof:placetype":"venue"
},
  "geometry": {"coordinates":[-81.02673900000001,29.264228],"type":"Point"}
}