{
  "type": "Feature",
  "properties": {
    "iso:country":"US",
    "sg:address":"1042 37th St",
    "sg:city":"Orlando",
    "sg:classifiers":[
        {
            "category":"Home & Garden",
            "subcategory":"Building Materials",
            "type":"Retail Goods"
        },
        {
            "category":"Building & Trades",
            "subcategory":"Construction",
            "type":"Services"
        }
    ],
    "sg:phone":"+1 407 648 9185",
    "sg:postcode":"32805",
    "sg:province":"FL",
    "sg:tags":[
        "concrete",
        "staining",
        "contractor"
    ],
    "wof:name":"Concrete Transformations",
    "wof:placetype":"venue"
},
  "geometry": {"coordinates":[-81.39315499999999,28.505482],"type":"Point"}
}