{
  "type": "Feature",
  "properties": {
    "addr:full":"3520 Vista Ct Miami FL 33133",
    "addr:housenumber":"3520",
    "addr:postcode":"33133",
    "addr:street":"Vista Ct",
    "iso:country":"US",
    "sg:address":"3520 Vista Ct",
    "sg:city":"Miami",
    "sg:classifiers":[
        {
            "category":"Wholesale",
            "subcategory":"Fruits & Vegetables",
            "type":"Manufacturing & Wholesale Goods"
        }
    ],
    "sg:phone":"+1 305 860 9611",
    "sg:postcode":"33133",
    "sg:province":"FL",
    "sg:tags":[
        "veggie"
    ],
    "wof:name":"Frontera Produce",
    "wof:placetype":"venue"
},
  "geometry": {"coordinates":[-80.224379,25.737949],"type":"Point"}
}