{
  "type": "Feature",
  "properties": {
    "iso:country":"US",
    "sg:address":"7583 Springfield Lake Dr",
    "sg:city":"Lake Worth",
    "sg:classifiers":[
        {
            "category":"Health Services",
            "subcategory":"Doctor",
            "type":"Services"
        }
    ],
    "sg:phone":"+1 561 432 8188",
    "sg:postcode":"33467",
    "sg:province":"FL",
    "sg:tags":[
        "medical"
    ],
    "wof:name":"Center For Integrated Med",
    "wof:placetype":"venue"
},
  "geometry": {"coordinates":[-80.16417800000001,26.557431],"type":"Point"}
}