{
  "type": "Feature",
  "properties": {
    "iso:country":"US",
    "sg:address":"1410 Bennet Rd",
    "sg:city":"Orlando",
    "sg:classifiers":[
        {
            "category":"Building & Trades",
            "subcategory":"Construction",
            "type":"Services"
        }
    ],
    "sg:phone":"+1 407 898 5549",
    "sg:postcode":"32803",
    "sg:province":"FL",
    "sg:tags":[
        "floor",
        "laying",
        "contractor"
    ],
    "wof:name":"H&H Flooring",
    "wof:placetype":"venue"
},
  "geometry": {"coordinates":[-81.33375700000001,28.566138],"type":"Point"}
}