{
  "type": "Feature",
  "properties": {
    "addr:full":"10591 Safety Ln Fort Myers FL 33908",
    "addr:postcode":"10591;33908",
    "addr:street":"Safety Ln",
    "iso:country":"US",
    "sg:address":"10591 Safety Ln",
    "sg:city":"Fort Myers",
    "sg:classifiers":[
        {
            "category":"Communications",
            "subcategory":"Radio Station",
            "type":"Services"
        }
    ],
    "sg:phone":"+1 239 433 9962",
    "sg:postcode":"33908",
    "sg:province":"FL",
    "wof:name":"Renda Broadcasting Corp",
    "wof:placetype":"venue"
},
  "geometry": {"coordinates":[-81.935501,26.5068],"type":"Point"}
}