{
  "type": "Feature",
  "properties": {
    "addr:full":"2705 Okeechobee Blvd West Palm Beach FL 33409",
    "addr:housenumber":"2705",
    "addr:postcode":"33409",
    "addr:street":"Okeechobee Blvd",
    "iso:country":"US",
    "sg:address":"2705 Okeechobee Blvd",
    "sg:city":"West Palm Beach",
    "sg:classifiers":[
        {
            "category":"Restaurant",
            "type":"Food & Drink"
        }
    ],
    "sg:menulink":"http://www.allmenus.com/fl/west-palm-beach/11424-dennys/menu/",
    "sg:phone":"+1 561 686 6664",
    "sg:postcode":"33409",
    "sg:province":"FL",
    "sg:tags":[
        "american",
        "diner"
    ],
    "wof:name":"Denny's",
    "wof:placetype":"venue"
},
  "geometry": {"coordinates":[-80.09448,26.707268],"type":"Point"}
}