{
  "type": "Feature",
  "properties": {
    "iso:country":"US",
    "sg:address":"1777 NW 89th Ter",
    "sg:city":"Miami",
    "sg:classifiers":[
        {
            "category":"Shopping",
            "subcategory":"Catalog Store",
            "type":"Retail Goods"
        }
    ],
    "sg:phone":"+1 305 693 5880",
    "sg:postcode":"33147",
    "sg:province":"FL",
    "sg:tags":[
        "mail",
        "order",
        "online"
    ],
    "wof:name":"Cb Enterprises",
    "wof:placetype":"venue"
},
  "geometry": {"coordinates":[-80.227294,25.856045],"type":"Point"}
}