{
  "type": "Feature",
  "properties": {
    "addr:full":"17455 NW 75th Pl Hialeah FL 33015",
    "addr:housenumber":"17455",
    "addr:postcode":"33015",
    "addr:street":"Nw 75Th Pl",
    "iso:country":"US",
    "sg:address":"17455 NW 75th Pl",
    "sg:city":"Hialeah",
    "sg:classifiers":[
        {
            "category":"Building & Trades",
            "subcategory":"Construction",
            "type":"Services"
        }
    ],
    "sg:phone":"+1 305 821 3839",
    "sg:postcode":"33015",
    "sg:province":"FL",
    "sg:tags":[
        "tile",
        "dealer"
    ],
    "wof:name":"Ismar Marble Polishing",
    "wof:placetype":"venue"
},
  "geometry": {"coordinates":[-80.323528,25.939966],"type":"Point"}
}