{
  "type": "Feature",
  "properties": {
    "iso:country":"US",
    "sg:address":"1832 N Crystal Lake Dr",
    "sg:city":"Lakeland",
    "sg:classifiers":[
        {
            "category":"Professional",
            "subcategory":"Employment Agencies",
            "type":"Services"
        }
    ],
    "sg:phone":"+1 863 665 3256",
    "sg:postcode":"33801",
    "sg:province":"FL",
    "wof:name":"Rams Staffing",
    "wof:placetype":"venue"
},
  "geometry": {"coordinates":[-81.92581,28.025932],"type":"Point"}
}