{
  "type": "Feature",
  "properties": {
    "iso:country":"US",
    "sg:address":"4225 el Mar Dr",
    "sg:city":"Fort Lauderdale",
    "sg:classifiers":[
        {
            "category":"Professional",
            "subcategory":"Computer Services",
            "type":"Services"
        }
    ],
    "sg:phone":"+1 954 493 8040",
    "sg:postcode":"33308",
    "sg:province":"FL",
    "sg:tags":[
        "agency",
        "employment",
        "related"
    ],
    "wof:name":"Experts Inc",
    "wof:placetype":"venue"
},
  "geometry": {"coordinates":[-80.09618399999999,26.187115],"type":"Point"}
}