{
  "type": "Feature",
  "properties": {
    "iso:country":"US",
    "sg:address":"5809 Spring Lake Dr",
    "sg:city":"Lakeland",
    "sg:classifiers":[
        {
            "category":"Building & Trades",
            "subcategory":"Construction",
            "type":"Services"
        }
    ],
    "sg:phone":"+1 863 647 3397",
    "sg:postcode":"33811",
    "sg:province":"FL",
    "sg:tags":[
        "painter"
    ],
    "wof:name":"Paul Painting Inc",
    "wof:placetype":"venue"
},
  "geometry": {"coordinates":[-82.01740100000001,27.959283],"type":"Point"}
}