{
  "type": "Feature",
  "properties": {
    "addr:full":"6865 W 10th Ave Hialeah FL 33014",
    "addr:housenumber":"6865",
    "addr:postcode":"33014",
    "addr:street":"W 10Th Ave",
    "iso:country":"US",
    "sg:address":"6865 W 10th Ave",
    "sg:city":"Hialeah",
    "sg:classifiers":[
        {
            "category":"Insurance",
            "subcategory":"Life Insurance",
            "type":"Services"
        }
    ],
    "sg:phone":"+1 305 542 2163",
    "sg:postcode":"33014",
    "sg:province":"FL",
    "wof:name":"Onyx Underwriters Inc",
    "wof:placetype":"venue"
},
  "geometry": {"coordinates":[-80.303121,25.884973],"type":"Point"}
}