{
  "type": "Feature",
  "properties": {
    "addr:full":"235 Joel Blvd Lehigh Acres FL 33972",
    "addr:housenumber":"235",
    "addr:postcode":"33972",
    "addr:street":"Joel Blvd",
    "iso:country":"US",
    "sg:address":"235 Joel Blvd",
    "sg:city":"Lehigh Acres",
    "sg:classifiers":[
        {
            "category":"Autos & Motor Vehicles",
            "subcategory":"Automobile Sales",
            "type":"Retail Goods"
        }
    ],
    "sg:phone":"+1 239 303 0895",
    "sg:postcode":"33972",
    "sg:province":"FL",
    "sg:tags":[
        "car",
        "dealer"
    ],
    "wof:name":"Texas Auto Mart Inc",
    "wof:placetype":"venue"
},
  "geometry": {"coordinates":[-81.606613,26.607377],"type":"Point"}
}