{
  "type": "Feature",
  "properties": {
    "addr:full":"292 N Spring St Crestview FL 32536",
    "addr:housenumber":"292",
    "addr:postcode":"32536",
    "addr:street":"N Spring St",
    "iso:country":"US",
    "sg:address":"292 N Spring St",
    "sg:city":"Crestview",
    "sg:classifiers":[
        {
            "category":"Building & Trades",
            "subcategory":"Construction",
            "type":"Services"
        }
    ],
    "sg:phone":"+1 850 683 3553",
    "sg:postcode":"32536",
    "sg:province":"FL",
    "sg:tags":[
        "contractor"
    ],
    "wof:name":"Terry Sowell Roofing",
    "wof:placetype":"venue"
},
  "geometry": {"coordinates":[-86.572039,30.757345],"type":"Point"}
}