{
  "type": "Feature",
  "properties": {
    "iso:country":"US",
    "sg:address":"2891 2nd Ave NE",
    "sg:city":"Crestview",
    "sg:classifiers":[
        {
            "category":"Building & Trades",
            "subcategory":"Construction",
            "type":"Services"
        }
    ],
    "sg:phone":"+1 850 689 0042",
    "sg:postcode":"32539",
    "sg:province":"FL",
    "sg:tags":[
        "industrial",
        "contractors-commercial",
        "contractor"
    ],
    "wof:name":"Alpha Portable Buildings",
    "wof:placetype":"venue"
},
  "geometry": {"coordinates":[-86.551672,30.776578],"type":"Point"}
}