{
  "type": "Feature",
  "properties": {
    "addr:full":"1355 Challen Ave Jacksonville FL 32205",
    "addr:housenumber":"1355",
    "addr:postcode":"32205",
    "addr:street":"Challen Ave",
    "iso:country":"US",
    "sg:address":"1355 Challen Ave",
    "sg:city":"Jacksonville",
    "sg:classifiers":[
        {
            "category":"Professional",
            "subcategory":"Management & Consulting",
            "type":"Services"
        }
    ],
    "sg:phone":"+1 904 387 1921",
    "sg:postcode":"32205",
    "sg:province":"FL",
    "sg:tags":[
        "consultant",
        "medical",
        "legal"
    ],
    "wof:name":"Linda Brandt-Comer",
    "wof:placetype":"venue"
},
  "geometry": {"coordinates":[-81.70865499999999,30.305418],"type":"Point"}
}