{
  "type": "Feature",
  "properties": {
    "iso:country":"US",
    "sg:address":"1330 Knox McRae Dr",
    "sg:city":"Titusville",
    "sg:classifiers":[
        {
            "category":"Travel",
            "subcategory":"Hotels & Motels",
            "type":"Entertainment"
        }
    ],
    "sg:phone":"+1 321 268 2413",
    "sg:postcode":"32780",
    "sg:province":"FL",
    "sg:tags":[
        "resort"
    ],
    "wof:name":"Vacation Villas Inc",
    "wof:placetype":"venue"
},
  "geometry": {"coordinates":[-80.820015,28.571369],"type":"Point"}
}