{
  "type": "Feature",
  "properties": {
    "addr:full":"160 International Pkwy Lake Mary FL 32746",
    "addr:housenumber":"160",
    "addr:postcode":"32746",
    "addr:street":"International Pkwy",
    "iso:country":"US",
    "sg:address":"160 International Pkwy",
    "sg:city":"Lake Mary",
    "sg:classifiers":[
        {
            "category":"Banks & Credit Unions",
            "subcategory":"Bank",
            "type":"Services"
        }
    ],
    "sg:phone":"+1 407 333 4202",
    "sg:postcode":"32746",
    "sg:province":"FL",
    "sg:tags":[
        "personal",
        "institution"
    ],
    "wof:name":"GE",
    "wof:placetype":"venue"
},
  "geometry": {"coordinates":[-81.36779799999999,28.757697],"type":"Point"}
}