{
  "type": "Feature",
  "properties": {
    "iso:country":"US",
    "sg:address":"2229 W 69th St",
    "sg:city":"Hialeah",
    "sg:classifiers":[
        {
            "category":"School Buses",
            "type":"Transportation"
        }
    ],
    "sg:phone":"+1 305 364 7599",
    "sg:postcode":"33016",
    "sg:province":"FL",
    "wof:name":"Jimenez Yazmin",
    "wof:placetype":"venue"
},
  "geometry": {"coordinates":[-80.331716,25.885161],"type":"Point"}
}