{
  "type": "Feature",
  "properties": {
    "addr:full":"7325 NW 35th St Miami FL 33122",
    "addr:housenumber":"7325",
    "addr:postcode":"33122",
    "addr:street":"Nw 35Th St",
    "iso:country":"US",
    "sg:address":"7325 NW 35th St",
    "sg:city":"Miami",
    "sg:classifiers":[
        {
            "category":"Retail",
            "subcategory":"Funeral Services",
            "type":"Services"
        }
    ],
    "sg:phone":"+1 305 406 2280",
    "sg:postcode":"33122",
    "sg:province":"FL",
    "sg:tags":[
        "director"
    ],
    "wof:name":"Funeral Store Inc",
    "wof:placetype":"venue"
},
  "geometry": {"coordinates":[-80.31710699999999,25.806176],"type":"Point"}
}