{
  "type": "Feature",
  "properties": {
    "iso:country":"US",
    "sg:address":"347 Tuscany G",
    "sg:city":"Delray Beach",
    "sg:classifiers":[
        {
            "category":"Shopping",
            "type":"Retail Goods"
        }
    ],
    "sg:phone":"+1 561 865 8031",
    "sg:postcode":"33446",
    "sg:province":"FL",
    "sg:tags":[
        "merchandise"
    ],
    "wof:name":"Herbert Potish",
    "wof:placetype":"venue"
},
  "geometry": {"coordinates":[-80.151627,26.446556],"type":"Point"}
}