{
  "type": "Feature",
  "properties": {
    "iso:country":"US",
    "sg:address":"4206 Sebring Pkwy",
    "sg:city":"Sebring",
    "sg:classifiers":[
        {
            "category":"Wholesale",
            "subcategory":"Medical Equipment & Supplies",
            "type":"Manufacturing & Wholesale Goods"
        },
        {
            "category":"Communications",
            "type":"Services"
        }
    ],
    "sg:phone":"+1 863 382 9210",
    "sg:postcode":"33870",
    "sg:province":"FL",
    "sg:tags":[
        "speech-language",
        "hearing",
        "pathologist",
        "device",
        "assistive",
        "aid"
    ],
    "wof:name":"Digital Hearing Aid Outlet Inc",
    "wof:placetype":"venue"
},
  "geometry": {"coordinates":[-81.49238099999999,27.514863],"type":"Point"}
}