{
  "type": "Feature",
  "properties": {
    "iso:country":"US",
    "sg:address":"22 Hibiscus Dr",
    "sg:city":"Ormond Beach",
    "sg:classifiers":[
        {
            "category":"Manufacturing",
            "subcategory":"Printing",
            "type":"Manufacturing & Wholesale Goods"
        }
    ],
    "sg:phone":"+1 386 441 4987",
    "sg:postcode":"32176",
    "sg:province":"FL",
    "sg:tags":[
        "decal"
    ],
    "wof:name":"Carved Glass Co",
    "wof:placetype":"venue"
},
  "geometry": {"coordinates":[-81.06155,29.324685],"type":"Point"}
}