{
  "type": "Feature",
  "properties": {
    "addr:full":"14975 SE 160th Ave Weirsdale FL 32195",
    "addr:housenumber":"14975",
    "addr:postcode":"32195",
    "addr:street":"Se 160Th Ave",
    "iso:country":"US",
    "sg:address":"14975 SE 160th Ave",
    "sg:city":"Weirsdale",
    "sg:classifiers":[
        {
            "category":"Farming",
            "subcategory":"Farm",
            "type":"Manufacturing & Wholesale Goods"
        }
    ],
    "sg:phone":"+1 352 821 1902",
    "sg:postcode":"32195",
    "sg:province":"FL",
    "wof:name":"Ahmed Pavon",
    "wof:placetype":"venue"
},
  "geometry": {"coordinates":[-81.88763299999999,29.002474],"type":"Point"}
}