{
  "type": "Feature",
  "properties": {
    "iso:country":"US",
    "sg:address":"3152 Little Rd. Suite 199",
    "sg:city":"Trinity",
    "sg:classifiers":[
        {
            "category":"Wholesale",
            "subcategory":"Medical Equipment & Supplies",
            "type":"Manufacturing & Wholesale Goods"
        },
        {
            "category":"Retail",
            "subcategory":"Repair Shop",
            "type":"Services"
        },
        {
            "category":"Shopping",
            "subcategory":"Pharmacy",
            "type":"Retail Goods"
        }
    ],
    "sg:phone":"+1 866 426 0721",
    "sg:postcode":"34655",
    "sg:province":"FL",
    "sg:tags":[
        "repairing",
        "aids-parts",
        "hearing",
        "device",
        "health",
        "aid",
        "assistive",
        "home",
        "care"
    ],
    "sg:website":"http://hearrightnow.com",
    "wof:name":"Hear Right Now",
    "wof:placetype":"venue"
},
  "geometry": {"coordinates":[-82.66628300000001,28.203241],"type":"Point"}
}