{
  "type": "Feature",
  "properties": {
    "addr:full":"1200 W New York Ave Deland FL 32720",
    "addr:housenumber":"1200",
    "addr:postcode":"32720",
    "addr:street":"W New York Ave",
    "iso:country":"US",
    "sg:address":"1200 W New York Ave",
    "sg:city":"Deland",
    "sg:classifiers":[
        {
            "category":"Social Services",
            "subcategory":"Adult Care",
            "type":"Services"
        }
    ],
    "sg:phone":"+1 386 738 9986",
    "sg:postcode":"32720",
    "sg:province":"FL",
    "sg:tags":[
        "home",
        "residential"
    ],
    "wof:name":"Good Shephard ACLF",
    "wof:placetype":"venue"
},
  "geometry": {"coordinates":[-81.326804,29.027893],"type":"Point"}
}