{
  "type": "Feature",
  "properties": {
    "addr:full":"3915 E Colonial Dr Orlando FL 32803",
    "addr:housenumber":"3915",
    "addr:postcode":"32803",
    "addr:street":"E Colonial Dr",
    "iso:country":"US",
    "sg:address":"3915 E Colonial Dr",
    "sg:city":"Orlando",
    "sg:classifiers":[
        {
            "category":"Communications",
            "type":"Services"
        }
    ],
    "sg:phone":"+1 407 895 5789",
    "sg:postcode":"32803",
    "sg:province":"FL",
    "wof:name":"USA Mobility Inc",
    "wof:placetype":"venue"
},
  "geometry": {"coordinates":[-81.335623,28.553523],"type":"Point"}
}