{
  "type": "Feature",
  "properties": {
    "addr:full":"28023 Us Highway 19 N Clearwater FL 33761",
    "addr:postcode":"28023;33761",
    "addr:street":"Us Highway 19 N",
    "iso:country":"US",
    "sg:address":"28023 Us Highway 19 N",
    "sg:city":"Clearwater",
    "sg:classifiers":[
        {
            "category":"Restaurant",
            "type":"Food & Drink"
        }
    ],
    "sg:menulink":"http://www.allmenus.com/fl/clearwater/48412-red-lobster/menu/",
    "sg:phone":"+1 727 799 3816",
    "sg:postcode":"33761",
    "sg:province":"FL",
    "sg:tags":[
        "seafood",
        "american"
    ],
    "wof:name":"Red Lobster",
    "wof:placetype":"venue"
},
  "geometry": {"coordinates":[-82.738077,28.027023],"type":"Point"}
}