{
  "type": "Feature",
  "properties": {
    "addr:full":"4576 Coastal Hwy Saint Augustine FL 32084",
    "addr:housenumber":"4576",
    "addr:postcode":"32084",
    "addr:street":"Coastal Hwy",
    "iso:country":"US",
    "sg:address":"4576 Coastal Hwy",
    "sg:city":"Saint Augustine",
    "sg:classifiers":[
        {
            "category":"Shopping",
            "subcategory":"Florist",
            "type":"Retail Goods"
        }
    ],
    "sg:phone":"+1 904 826 0709",
    "sg:postcode":"32084",
    "sg:province":"FL",
    "wof:name":"Flowers Foliage Fd",
    "wof:placetype":"venue"
},
  "geometry": {"coordinates":[-81.307586,29.962162],"type":"Point"}
}