{
  "type": "Feature",
  "properties": {
    "iso:country":"US",
    "sg:address":"7537 NW 18th Dr",
    "sg:city":"Hollywood",
    "sg:classifiers":[
        {
            "category":"Real Estate",
            "subcategory":"Real Estate Services",
            "type":"Services"
        },
        {
            "category":"Banks & Credit Unions",
            "subcategory":"Financial Services",
            "type":"Services"
        }
    ],
    "sg:phone":"+1 954 651 5501",
    "sg:postcode":"33024",
    "sg:province":"FL",
    "sg:tags":[
        "loan",
        "processing"
    ],
    "wof:name":"Sunny Mortgage",
    "wof:placetype":"venue"
},
  "geometry": {"coordinates":[-80.239363,26.025062],"type":"Point"}
}