{
  "type": "Feature",
  "properties": {
    "iso:country":"US",
    "sg:address":"590 W 84th St",
    "sg:city":"Hialeah",
    "sg:classifiers":[
        {
            "category":"Food & Beverages",
            "subcategory":"Specialty",
            "type":"Retail Goods"
        }
    ],
    "sg:phone":"+1 305 821 4380",
    "sg:postcode":"33014",
    "sg:province":"FL",
    "sg:tags":[
        "tea",
        "coffee"
    ],
    "wof:name":"Greenwich Mills Co",
    "wof:placetype":"venue"
},
  "geometry": {"coordinates":[-80.29272899999999,25.898703],"type":"Point"}
}