{
  "type": "Feature",
  "properties": {
    "iso:country":"US",
    "sg:address":"15 SW 55th Avenue Rd",
    "sg:city":"Coral Gables",
    "sg:classifiers":[
        {
            "category":"Home & Garden",
            "subcategory":"Home Furnishings",
            "type":"Retail Goods"
        }
    ],
    "sg:phone":"+1 305 263 8355",
    "sg:postcode":"33134",
    "sg:province":"FL",
    "sg:tags":[
        "upholstery",
        "fabric"
    ],
    "wof:name":"Jose Upholstery",
    "wof:placetype":"venue"
},
  "geometry": {"coordinates":[-80.285082,25.770066],"type":"Point"}
}