{
  "type": "Feature",
  "properties": {
    "addr:full":"2711 SE 24th Ct Cape Coral FL 33904",
    "addr:housenumber":"2711",
    "addr:postcode":"33904",
    "addr:street":"Se 24Th Ct",
    "iso:country":"US",
    "sg:address":"2711 SE 24th Ct",
    "sg:city":"Cape Coral",
    "sg:classifiers":[
        {
            "category":"Professional",
            "type":"Services"
        }
    ],
    "sg:phone":"+1 239 242 7471",
    "sg:postcode":"33904",
    "sg:province":"FL",
    "wof:name":"Pga Appraisial Inc",
    "wof:placetype":"venue"
},
  "geometry": {"coordinates":[-81.916926,26.603541],"type":"Point"}
}