{
  "type": "Feature",
  "properties": {
    "iso:country":"US",
    "sg:address":"2002 Del Prado Blvd S",
    "sg:city":"Cape Coral",
    "sg:classifiers":[
        {
            "category":"Health Services",
            "subcategory":"Doctor",
            "type":"Services"
        }
    ],
    "sg:phone":"+1 239 573 1606",
    "sg:postcode":"33990",
    "sg:province":"FL",
    "sg:tags":[
        "medicine",
        "internal"
    ],
    "wof:name":"Michele A Candelore DO",
    "wof:placetype":"venue"
},
  "geometry": {"coordinates":[-81.941002,26.615101],"type":"Point"}
}