{
  "type": "Feature",
  "properties": {
    "iso:country":"US",
    "sg:address":"2190 Tamiami Trl S",
    "sg:city":"Venice",
    "sg:classifiers":[
        {
            "category":"Building & Trades",
            "subcategory":"Equipment Rental",
            "type":"Services"
        }
    ],
    "sg:phone":"+1 941 492 3721",
    "sg:postcode":"34293",
    "sg:province":"FL",
    "sg:tags":[
        "yard",
        "leasing",
        "store"
    ],
    "wof:name":"Alamar Rentals & Manageme",
    "wof:placetype":"venue"
},
  "geometry": {"coordinates":[-82.410495,27.053823],"type":"Point"}
}