{
  "type": "Feature",
  "properties": {
    "iso:country":"US",
    "sg:address":"4480 Higate Rd",
    "sg:city":"Spring Hill",
    "sg:classifiers":[
        {
            "category":"Shopping",
            "subcategory":"Hobbies, Toys, & Games",
            "type":"Retail Goods"
        }
    ],
    "sg:phone":"+1 352 684 7822",
    "sg:postcode":"34609",
    "sg:province":"FL",
    "wof:name":"Toys 2000 Inc",
    "wof:placetype":"venue"
},
  "geometry": {"coordinates":[-82.51794599999999,28.500357],"type":"Point"}
}