{
  "type": "Feature",
  "properties": {
    "iso:country":"US",
    "sg:address":"8767 SW 129th St",
    "sg:city":"Miami",
    "sg:classifiers":[
        {
            "category":"Professional",
            "subcategory":"Management & Consulting",
            "type":"Services"
        }
    ],
    "sg:phone":"+1 305 969 7907",
    "sg:postcode":"33176",
    "sg:province":"FL",
    "sg:tags":[
        "business"
    ],
    "wof:name":"Leska Hamaty",
    "wof:placetype":"venue"
},
  "geometry": {"coordinates":[-80.338413,25.650659],"type":"Point"}
}