{
  "type": "Feature",
  "properties": {
    "addr:full":"7223 NW 79th Ter Medley FL 33166",
    "addr:housenumber":"7223",
    "addr:postcode":"33166",
    "addr:street":"Nw 79Th Ter",
    "iso:country":"US",
    "sg:address":"7223 NW 79th Ter",
    "sg:city":"Medley",
    "sg:classifiers":[
        {
            "category":"Utilities",
            "subcategory":"Recycling",
            "type":"Services"
        }
    ],
    "sg:phone":"+1 305 805 0302",
    "sg:postcode":"33166",
    "sg:province":"FL",
    "wof:name":"OJ Scrap Metal Inc",
    "wof:placetype":"venue"
},
  "geometry": {"coordinates":[-80.31472599999999,25.845702],"type":"Point"}
}