{
  "type": "Feature",
  "properties": {
    "iso:country":"US",
    "sg:address":"9113 Vineyard Lake Dr",
    "sg:city":"Plantation",
    "sg:classifiers":[
        {
            "category":"Professional",
            "subcategory":"Computer Services",
            "type":"Services"
        }
    ],
    "sg:phone":"+1 954 472 3722",
    "sg:postcode":"33324",
    "sg:province":"FL",
    "wof:name":"Concord Networks Inc",
    "wof:placetype":"venue"
},
  "geometry": {"coordinates":[-80.270039,26.134688],"type":"Point"}
}