{
  "type": "Feature",
  "properties": {
    "iso:country":"US",
    "sg:address":"7320 Central Ave",
    "sg:city":"Saint Petersburg",
    "sg:classifiers":[
        {
            "category":"Shopping",
            "type":"Retail Goods"
        }
    ],
    "sg:phone":"+1 727 343 5451",
    "sg:postcode":"33707",
    "sg:province":"FL",
    "sg:tags":[
        "merchandise"
    ],
    "wof:name":"Peacocks Pet Shop",
    "wof:placetype":"venue"
},
  "geometry": {"coordinates":[-82.74094700000001,27.770735],"type":"Point"}
}