{
  "type": "Feature",
  "properties": {
    "addr:full":"1050 Endeavor Ct North Venice FL 34275",
    "addr:housenumber":"1050",
    "addr:postcode":"34275",
    "addr:street":"Endeavor Ct North",
    "iso:country":"US",
    "sg:address":"1050 Endeavor Ct",
    "sg:city":"North Venice",
    "sg:classifiers":[
        {
            "category":"Professional",
            "subcategory":"Testing Lab",
            "type":"Services"
        }
    ],
    "sg:phone":"+1 941 488 8103",
    "sg:postcode":"34275",
    "sg:province":"FL",
    "sg:tags":[
        "laboratory"
    ],
    "sg:website":"www.sanderslabs.net",
    "wof:name":"Sanders Laboratories Inc",
    "wof:placetype":"venue"
},
  "geometry": {"coordinates":[-82.40394499999999,27.142093],"type":"Point"}
}