{
  "type": "Feature",
  "properties": {
    "iso:country":"US",
    "sg:address":"906 Fish Hatchery Rd",
    "sg:city":"Lakeland",
    "sg:classifiers":[
        {
            "category":"Transit Center",
            "subcategory":"Freight",
            "type":"Transportation"
        },
        {
            "category":"Freight",
            "type":"Transportation"
        }
    ],
    "sg:phone":"+1 863 665 8659",
    "sg:postcode":"33801",
    "sg:province":"FL",
    "sg:tags":[
        "local",
        "trucking-motor",
        "trucking"
    ],
    "wof:name":"Daniel Hardy",
    "wof:placetype":"venue"
},
  "geometry": {"coordinates":[-81.895715,28.052679],"type":"Point"}
}