{
  "type": "Feature",
  "properties": {
    "iso:country":"US",
    "sg:address":"1101 E 1st St",
    "sg:city":"Sanford",
    "sg:classifiers":[
        {
            "category":"Government",
            "subcategory":"Office",
            "type":"Public Place"
        }
    ],
    "sg:phone":"+1 407 665 1105",
    "sg:postcode":"32771",
    "sg:province":"FL",
    "sg:website":"www.seminolecountyfl.gov",
    "wof:name":"Seminole County Geographic",
    "wof:placetype":"venue"
},
  "geometry": {"coordinates":[-81.25683600000001,28.81142],"type":"Point"}
}