{
  "type": "Feature",
  "properties": {
    "iso:country":"US",
    "sg:address":"530 Tremont Ave",
    "sg:city":"Palm Bay",
    "sg:classifiers":[
        {
            "category":"Shopping",
            "subcategory":"Bicycles & Sporting Goods",
            "type":"Retail Goods"
        }
    ],
    "sg:phone":"+1 321 409 8732",
    "sg:postcode":"32908",
    "sg:province":"FL",
    "wof:name":"Greenwood Nascar Collectibles",
    "wof:placetype":"venue"
},
  "geometry": {"coordinates":[-80.67926300000001,27.985663],"type":"Point"}
}