{
  "type": "Feature",
  "properties": {
    "iso:country":"US",
    "sg:address":"1110 W Commercial Blvd",
    "sg:city":"Fort Lauderdale",
    "sg:classifiers":[
        {
            "category":"Insurance",
            "subcategory":"Insurance Agent",
            "type":"Services"
        }
    ],
    "sg:phone":"+1 954 958 1211",
    "sg:postcode":"33309",
    "sg:province":"FL",
    "wof:name":"Coastal Homeowners Ins Spec",
    "wof:placetype":"venue"
},
  "geometry": {"coordinates":[-80.158281,26.188254],"type":"Point"}
}