{
  "type": "Feature",
  "properties": {
    "addr:full":"8715 US Hwy 1 Port Saint Lucie FL 34982",
    "addr:housenumber":"8715",
    "addr:postcode":"34982",
    "addr:street":"Us Hwy 1",
    "iso:country":"US",
    "sg:address":"8715 US Hwy 1",
    "sg:city":"Port Saint Lucie",
    "sg:classifiers":[
        {
            "category":"Autos & Motor Vehicles",
            "subcategory":"Motorcycle Sales",
            "type":"Retail Goods"
        }
    ],
    "sg:phone":"+1 772 878 6588",
    "sg:postcode":"34982",
    "sg:province":"FL",
    "wof:name":"World of Chrome",
    "wof:placetype":"venue"
},
  "geometry": {"coordinates":[-80.310991,27.310011],"type":"Point"}
}