{
  "type": "Feature",
  "properties": {
    "addr:full":"2134 Main St Dunedin FL 34698",
    "addr:housenumber":"2134",
    "addr:postcode":"34698",
    "addr:street":"Main St",
    "iso:country":"US",
    "sg:address":"2134 Main St",
    "sg:city":"Dunedin",
    "sg:classifiers":[
        {
            "category":"Personal",
            "subcategory":"Beauty Salon",
            "type":"Services"
        }
    ],
    "sg:phone":"+1 727 734 3008",
    "sg:postcode":"34698",
    "sg:province":"FL",
    "wof:name":"Fantastic Sam's",
    "wof:placetype":"venue"
},
  "geometry": {"coordinates":[-82.749402,28.019449],"type":"Point"}
}