{
  "type": "Feature",
  "properties": {
    "addr:full":"4201 Baymeadows Rd Jacksonville FL 32217",
    "addr:housenumber":"4201",
    "addr:postcode":"32217",
    "addr:street":"Baymeadows Rd",
    "iso:country":"US",
    "sg:address":"4201 Baymeadows Rd",
    "sg:city":"Jacksonville",
    "sg:classifiers":[
        {
            "category":"Real Estate",
            "subcategory":"Real Estate Services",
            "type":"Services"
        }
    ],
    "sg:phone":"+1 904 425 6688",
    "sg:postcode":"32217",
    "sg:province":"FL",
    "sg:tags":[
        "company",
        "title"
    ],
    "wof:name":"Sun Region Title & Abstract",
    "wof:placetype":"venue"
},
  "geometry": {"coordinates":[-81.60929,30.21893],"type":"Point"}
}