{
  "type": "Feature",
  "properties": {
    "iso:country":"US",
    "sg:address":"25521 SW 141st Ave",
    "sg:city":"Homestead",
    "sg:classifiers":[
        {
            "category":"Manufacturing",
            "subcategory":"Retail Goods",
            "type":"Manufacturing & Wholesale Goods"
        }
    ],
    "sg:phone":"+1 305 257 2968",
    "sg:postcode":"33032",
    "sg:province":"FL",
    "sg:tags":[
        "assembly",
        "fabricating"
    ],
    "wof:name":"Rick's Prefab",
    "wof:placetype":"venue"
},
  "geometry": {"coordinates":[-80.419911,25.530148],"type":"Point"}
}