{
  "type": "Feature",
  "properties": {
    "iso:country":"US",
    "sg:address":"1937 Hollywood Blvd",
    "sg:city":"Hollywood",
    "sg:classifiers":[
        {
            "category":"Retail",
            "subcategory":"Portrait Studio",
            "type":"Services"
        }
    ],
    "sg:phone":"+1 954 923 5441",
    "sg:postcode":"33020",
    "sg:province":"FL",
    "sg:tags":[
        "photo"
    ],
    "sg:website":"www.wilcostudio.com",
    "wof:name":"Wilco Studios Photography",
    "wof:placetype":"venue"
},
  "geometry": {"coordinates":[-80.146283,26.011592],"type":"Point"}
}