{
  "type": "Feature",
  "properties": {
    "iso:country":"US",
    "sg:address":"8930 Bay Colony Dr",
    "sg:city":"Naples",
    "sg:classifiers":[
        {
            "category":"Real Estate",
            "subcategory":"Real Estate Agent",
            "type":"Services"
        }
    ],
    "sg:phone":"+1 239 596 3676",
    "sg:postcode":"34108",
    "sg:province":"FL",
    "wof:name":"Salerno Of Bay Colony",
    "wof:placetype":"venue"
},
  "geometry": {"coordinates":[-81.819429,26.251032],"type":"Point"}
}