{
  "type": "Feature",
  "properties": {
    "iso:country":"US",
    "sg:address":"9981 S Healthpark Dr",
    "sg:city":"Fort Myers",
    "sg:classifiers":[
        {
            "category":"Health Services",
            "subcategory":"Doctor",
            "type":"Services"
        }
    ],
    "sg:phone":"+1 239 481 5477",
    "sg:postcode":"33908",
    "sg:province":"FL",
    "sg:tags":[
        "obstetrician",
        "gynecologist"
    ],
    "wof:name":"Maternal Fetal Medicine of SW Florida",
    "wof:placetype":"venue"
},
  "geometry": {"coordinates":[-81.915497,26.503901],"type":"Point"}
}