{
  "type": "Feature",
  "properties": {
    "iso:country":"US",
    "sg:address":"1609 Shirley Ct",
    "sg:city":"Lake Worth",
    "sg:classifiers":[
        {
            "category":"Building & Trades",
            "subcategory":"Construction",
            "type":"Services"
        }
    ],
    "sg:phone":"+1 561 723 4207",
    "sg:postcode":"33462",
    "sg:province":"FL",
    "sg:tags":[
        "hanging",
        "contractor"
    ],
    "wof:name":"Moyers Sign Pavement Marking",
    "wof:placetype":"venue"
},
  "geometry": {"coordinates":[-80.06825000000001,26.594332],"type":"Point"}
}