{
  "type": "Feature",
  "properties": {
    "addr:full":"19204 NW 60th Ct Hialeah FL 33015",
    "addr:housenumber":"19204",
    "addr:postcode":"33015",
    "addr:street":"Nw 60Th Ct",
    "iso:country":"US",
    "sg:address":"19204 NW 60th Ct",
    "sg:city":"Hialeah",
    "sg:classifiers":[
        {
            "category":"Building & Trades",
            "subcategory":"Electrical",
            "type":"Services"
        }
    ],
    "sg:phone":"+1 954 252 5160",
    "sg:postcode":"33015",
    "sg:province":"FL",
    "sg:tags":[
        "control",
        "regulator",
        "system",
        "controls"
    ],
    "wof:name":"Sanyca Electronics Inc",
    "wof:placetype":"venue"
},
  "geometry": {"coordinates":[-80.298378,25.948004],"type":"Point"}
}