{
  "type": "Feature",
  "properties": {
    "iso:country":"US",
    "sg:address":"337 6th Ave",
    "sg:city":"Indialantic",
    "sg:classifiers":[
        {
            "category":"Health Services",
            "subcategory":"Dentist",
            "type":"Services"
        }
    ],
    "sg:phone":"+1 321 723 5244",
    "sg:postcode":"32903",
    "sg:province":"FL",
    "wof:name":"Mansfield Jessica L DDS PA",
    "wof:placetype":"venue"
},
  "geometry": {"coordinates":[-80.57139599999999,28.089428],"type":"Point"}
}