{
  "type": "Feature",
  "properties": {
    "iso:country":"US",
    "sg:address":"4821 N Orange Blossom Trl",
    "sg:city":"Orlando",
    "sg:classifiers":[
        {
            "category":"Personal",
            "subcategory":"Tattoo Parlor",
            "type":"Services"
        }
    ],
    "sg:phone":"+1 407 297 0086",
    "sg:postcode":"32810",
    "sg:province":"FL",
    "sg:tags":[
        "tattooing"
    ],
    "wof:name":"Da Shop Tatz Studio",
    "wof:placetype":"venue"
},
  "geometry": {"coordinates":[-81.419939,28.603615],"type":"Point"}
}