{
  "type": "Feature",
  "properties": {
    "iso:country":"US",
    "sg:address":"18511 Rustic Woods Trl",
    "sg:city":"Odessa",
    "sg:classifiers":[
        {
            "category":"Farming",
            "subcategory":"Farm",
            "type":"Manufacturing & Wholesale Goods"
        }
    ],
    "sg:phone":"+1 813 920 4727",
    "sg:postcode":"33556",
    "sg:province":"FL",
    "sg:tags":[
        "crop",
        "general"
    ],
    "wof:name":"Snelson Farm",
    "wof:placetype":"venue"
},
  "geometry": {"coordinates":[-82.63251099999999,28.147395],"type":"Point"}
}