{
  "type": "Feature",
  "properties": {
    "iso:country":"US",
    "sg:address":"2996 Main St",
    "sg:city":"Vernon",
    "sg:classifiers":[
        {
            "category":"Government",
            "subcategory":"Office",
            "type":"Public Place"
        }
    ],
    "sg:phone":"+1 850 535 2444",
    "sg:postcode":"32462",
    "sg:province":"FL",
    "sg:tags":[
        "township",
        "government-city",
        "village"
    ],
    "wof:name":"Vernon City Of",
    "wof:placetype":"venue"
},
  "geometry": {"coordinates":[-85.71219600000001,30.62505],"type":"Point"}
}