{
  "type": "Feature",
  "properties": {
    "iso:country":"US",
    "sg:address":"4050 SW Savona Blvd",
    "sg:city":"Port St Lucie",
    "sg:classifiers":[
        {
            "category":"Organizations",
            "subcategory":"Religious Organization",
            "type":"Services"
        }
    ],
    "sg:phone":"+1 772 336 0067",
    "sg:postcode":"34953",
    "sg:province":"FL",
    "sg:tags":[
        "church"
    ],
    "wof:name":"Treasure Coast Church-God Ctr",
    "wof:placetype":"venue"
},
  "geometry": {"coordinates":[-80.385069,27.224479],"type":"Point"}
}