{
  "type": "Feature",
  "properties": {
    "iso:country":"US",
    "sg:address":"175 E 5th St",
    "sg:city":"Apopka",
    "sg:classifiers":[
        {
            "category":"Government",
            "subcategory":"Office",
            "type":"Public Place"
        }
    ],
    "sg:phone":"+1 407 703 1713",
    "sg:postcode":"32703",
    "sg:province":"FL",
    "sg:tags":[
        "village"
    ],
    "sg:website":"www.apopka.net",
    "wof:name":"Apopka City Building Div",
    "wof:placetype":"venue"
},
  "geometry": {"coordinates":[-81.50942999999999,28.671971],"type":"Point"}
}