{
  "type": "Feature",
  "properties": {
    "iso:country":"US",
    "sg:address":"6712 Stirling Rd",
    "sg:city":"Hollywood",
    "sg:classifiers":[
        {
            "category":"Manufacturing",
            "subcategory":"Printing",
            "type":"Manufacturing & Wholesale Goods"
        }
    ],
    "sg:phone":"+1 954 987 5145",
    "sg:postcode":"33024",
    "sg:province":"FL",
    "sg:tags":[
        "printer"
    ],
    "wof:name":"Universal Business Svc Inc",
    "wof:placetype":"venue"
},
  "geometry": {"coordinates":[-80.22326,26.046234],"type":"Point"}
}