{
  "type": "Feature",
  "properties": {
    "iso:country":"US",
    "sg:address":"2888 Ringling Blvd",
    "sg:city":"Sarasota",
    "sg:classifiers":[
        {
            "category":"Recreation",
            "type":"Entertainment"
        }
    ],
    "sg:phone":"+1 941 365 0999",
    "sg:postcode":"34237",
    "sg:province":"FL",
    "sg:tags":[
        "organization",
        "religious"
    ],
    "wof:name":"Taoist Tai CHI Socty of Srsota",
    "wof:placetype":"venue"
},
  "geometry": {"coordinates":[-82.511516,27.336387],"type":"Point"}
}