{
  "type": "Feature",
  "properties": {
    "iso:country":"US",
    "sg:address":"8463 N Carl G Rose Hwy",
    "sg:city":"Hernando",
    "sg:classifiers":[
        {
            "category":"Manufacturing",
            "subcategory":"Printing",
            "type":"Manufacturing & Wholesale Goods"
        }
    ],
    "sg:phone":"+1 352 341 0940",
    "sg:postcode":"34442",
    "sg:province":"FL",
    "sg:tags":[
        "printer"
    ],
    "wof:name":"Amco Printing",
    "wof:placetype":"venue"
},
  "geometry": {"coordinates":[-82.352085,28.986051],"type":"Point"}
}