{
  "type": "Feature",
  "properties": {
    "iso:country":"US",
    "sg:address":"1406 Rail Head Blvd",
    "sg:city":"Naples",
    "sg:classifiers":[
        {
            "category":"Building & Trades",
            "subcategory":"Construction",
            "type":"Services"
        }
    ],
    "sg:phone":"+1 239 591 3677",
    "sg:postcode":"34110",
    "sg:province":"FL",
    "sg:tags":[
        "fire",
        "restoration",
        "damage"
    ],
    "wof:name":"Gulf Coast Development",
    "wof:placetype":"venue"
},
  "geometry": {"coordinates":[-81.791016,26.309004],"type":"Point"}
}