{
  "type": "Feature",
  "properties": {
    "iso:country":"US",
    "sg:address":"35 Sombrero Blvd",
    "sg:city":"Marathon",
    "sg:classifiers":[
        {
            "category":"Recreation",
            "subcategory":"Marina",
            "type":"Entertainment"
        }
    ],
    "sg:phone":"+1 305 743 0000",
    "sg:postcode":"33050",
    "sg:province":"FL",
    "wof:name":"Sombrero Marina & Dockside Lng",
    "wof:placetype":"venue"
},
  "geometry": {"coordinates":[-81.07648399999999,24.713949],"type":"Point"}
}