{
  "type": "Feature",
  "properties": {
    "iso:country":"US",
    "sg:address":"1509 Palm Ave",
    "sg:city":"Fort Myers",
    "sg:classifiers":[
        {
            "category":"Arts & Performance",
            "subcategory":"Music",
            "type":"Entertainment"
        }
    ],
    "sg:phone":"+1 239 337 7464",
    "sg:postcode":"33916",
    "sg:province":"FL",
    "sg:tags":[
        "dj"
    ],
    "wof:name":"Sean Corey Entertainment",
    "wof:placetype":"venue"
},
  "geometry": {"coordinates":[-81.856786,26.651001],"type":"Point"}
}