{
  "type": "Feature",
  "properties": {
    "addr:full":"1571 W 38th Pl Hialeah FL 33012",
    "addr:housenumber":"1571",
    "addr:postcode":"33012",
    "addr:street":"W 38Th Pl",
    "iso:country":"US",
    "sg:address":"1571 W 38th Pl",
    "sg:city":"Hialeah",
    "sg:classifiers":[
        {
            "category":"Autos & Motor Vehicles",
            "subcategory":"Auto Supplies",
            "type":"Retail Goods"
        },
        {
            "category":"Retail",
            "subcategory":"Auto Repair",
            "type":"Services"
        }
    ],
    "sg:phone":"+1 305 557 4508",
    "sg:postcode":"33012",
    "sg:province":"FL",
    "sg:tags":[
        "equipment",
        "automobile",
        "air",
        "conditioning",
        "general"
    ],
    "wof:name":"Paradise Auto Air Conditioning",
    "wof:placetype":"venue"
},
  "geometry": {"coordinates":[-80.31146,25.856745],"type":"Point"}
}