{
  "type": "Feature",
  "properties": {
    "addr:full":"337 US Hwy 92 Seffner FL 33584",
    "addr:housenumber":"337",
    "addr:postcode":"33584",
    "addr:street":"Us Hwy 92",
    "iso:country":"US",
    "sg:address":"337 US Hwy 92",
    "sg:city":"Seffner",
    "sg:classifiers":[
        {
            "category":"Home & Garden",
            "subcategory":"Building Materials",
            "type":"Retail Goods"
        }
    ],
    "sg:phone":"+1 813 571 9762",
    "sg:postcode":"33584",
    "sg:province":"FL",
    "sg:tags":[
        "sporting",
        "bathroom",
        "supply"
    ],
    "wof:name":"Internet Marketing",
    "wof:placetype":"venue"
},
  "geometry": {"coordinates":[-82.275255,28.007059],"type":"Point"}
}