{
  "type": "Feature",
  "properties": {
    "iso:country":"US",
    "sg:address":"3703 Parkridge Cir",
    "sg:city":"Sarasota",
    "sg:classifiers":[
        {
            "category":"Place Of Worship",
            "subcategory":"Church",
            "type":"Public Place"
        },
        {
            "category":"Place Of Worship",
            "type":"Public Place"
        }
    ],
    "sg:phone":"+1 941 400 4618",
    "sg:postcode":"34243",
    "sg:province":"FL",
    "sg:tags":[
        "churches-baptist-general",
        "churches-baptist"
    ],
    "wof:name":"Glaxosmthkline Hldngs Ame",
    "wof:placetype":"venue"
},
  "geometry": {"coordinates":[-82.49997399999999,27.385697],"type":"Point"}
}