{
  "type": "Feature",
  "properties": {
    "iso:country":"US",
    "sg:address":"2136 Littles Ln",
    "sg:city":"Crestview",
    "sg:classifiers":[
        {
            "category":"Building & Trades",
            "subcategory":"Construction",
            "type":"Services"
        }
    ],
    "sg:phone":"+1 850 682 7375",
    "sg:postcode":"32536",
    "sg:province":"FL",
    "sg:tags":[
        "painter"
    ],
    "wof:name":"Randy Little's Progressive",
    "wof:placetype":"venue"
},
  "geometry": {"coordinates":[-86.59558199999999,30.705251],"type":"Point"}
}