{
  "type": "Feature",
  "properties": {
    "iso:country":"US",
    "sg:address":"10561 Bonita Dr",
    "sg:city":"Bonita Springs",
    "sg:classifiers":[
        {
            "category":"Professional",
            "subcategory":"Employment Agencies",
            "type":"Services"
        }
    ],
    "sg:phone":"+1 239 947 9997",
    "sg:postcode":"34135",
    "sg:province":"FL",
    "sg:tags":[
        "help",
        "contractor"
    ],
    "wof:name":"Tee Off Temps Inc",
    "wof:placetype":"venue"
},
  "geometry": {"coordinates":[-81.779,26.349289],"type":"Point"}
}