{
  "type": "Feature",
  "properties": {
    "addr:full":"7770 Preserve Ln Naples FL 34119",
    "addr:housenumber":"7770",
    "addr:postcode":"34119",
    "addr:street":"Preserve Ln",
    "iso:country":"US",
    "sg:address":"7770 Preserve Ln",
    "sg:city":"Naples",
    "sg:classifiers":[
        {
            "category":"Education",
            "subcategory":"Dance Studio",
            "type":"Public Place"
        }
    ],
    "sg:phone":"+1 239 596 6045",
    "sg:postcode":"34119",
    "sg:province":"FL",
    "sg:tags":[
        "instruction",
        "dancing"
    ],
    "wof:name":"Dance City Productions",
    "wof:placetype":"venue"
},
  "geometry": {"coordinates":[-81.710077,26.27331],"type":"Point"}
}