{
  "type": "Feature",
  "properties": {
    "addr:full":"1719 Blanding Blvd Jacksonville FL 32210",
    "addr:housenumber":"1719",
    "addr:postcode":"32210",
    "addr:street":"Blanding Blvd",
    "iso:country":"US",
    "sg:address":"1719 Blanding Blvd",
    "sg:city":"Jacksonville",
    "sg:classifiers":[
        {
            "category":"Professional",
            "subcategory":"Lawyer & Legal Services",
            "type":"Services"
        }
    ],
    "sg:phone":"+1 904 384 6784",
    "sg:postcode":"32210",
    "sg:province":"FL",
    "sg:tags":[
        "attorney"
    ],
    "wof:name":"Oberdorfer & Barry PA",
    "wof:placetype":"venue"
},
  "geometry": {"coordinates":[-81.724102,30.287627],"type":"Point"}
}