{
  "type": "Feature",
  "properties": {
    "iso:country":"US",
    "sg:address":"2102 Maple Leaf Dr E",
    "sg:city":"Jacksonville",
    "sg:classifiers":[
        {
            "category":"Real Estate",
            "subcategory":"Architect",
            "type":"Services"
        }
    ],
    "sg:phone":"+1 904 744 3484",
    "sg:postcode":"32211",
    "sg:province":"FL",
    "sg:tags":[
        "architectural"
    ],
    "wof:name":"Designdraft Studios",
    "wof:placetype":"venue"
},
  "geometry": {"coordinates":[-81.59481,30.344018],"type":"Point"}
}