{
  "type": "Feature",
  "properties": {
    "iso:country":"US",
    "sg:address":"10808 NW 58th St",
    "sg:city":"Doral",
    "sg:classifiers":[
        {
            "category":"Shopping",
            "subcategory":"Mobile Phones",
            "type":"Retail Goods"
        }
    ],
    "sg:phone":"+1 305 629 9043",
    "sg:postcode":"33178",
    "sg:province":"FL",
    "wof:name":"USA Wireless",
    "wof:placetype":"venue"
},
  "geometry": {"coordinates":[-80.372156,25.826018],"type":"Point"}
}