{
  "type": "Feature",
  "properties": {
    "addr:full":"7357 Greenbriar Pkwy Orlando FL 32819",
    "addr:housenumber":"7357",
    "addr:postcode":"32819",
    "addr:street":"Greenbriar Pkwy",
    "iso:country":"US",
    "sg:address":"7357 Greenbriar Pkwy",
    "sg:city":"Orlando",
    "sg:classifiers":[
        {
            "category":"Government",
            "subcategory":"Office",
            "type":"Public Place"
        }
    ],
    "sg:phone":"+1 407 352 9898",
    "sg:postcode":"32819",
    "sg:province":"FL",
    "sg:tags":[
        "state",
        "program",
        "health"
    ],
    "wof:name":"PCS Health System",
    "wof:placetype":"venue"
},
  "geometry": {"coordinates":[-81.45462000000001,28.452699],"type":"Point"}
}