{
  "type": "Feature",
  "properties": {
    "addr:full":"703 N Flamingo Rd Hollywood FL 33028",
    "addr:housenumber":"703",
    "addr:postcode":"33028",
    "addr:street":"N Flamingo Rd",
    "iso:country":"US",
    "sg:address":"703 N Flamingo Rd",
    "sg:city":"Hollywood",
    "sg:classifiers":[
        {
            "category":"Health Services",
            "subcategory":"Hospital",
            "type":"Services"
        },
        {
            "category":"Health Services",
            "subcategory":"Doctor",
            "type":"Services"
        }
    ],
    "sg:phone":"+1 954 433 7125",
    "sg:postcode":"33028",
    "sg:province":"FL",
    "sg:tags":[
        "medical",
        "general",
        "specialty",
        "physical"
    ],
    "wof:name":"Memorial Hospital West Fitness",
    "wof:placetype":"venue"
},
  "geometry": {"coordinates":[-80.312095,26.013411],"type":"Point"}
}