{
  "type": "Feature",
  "properties": {
    "addr:full":"6006 49th St N St Petersburg FL 33709",
    "addr:housenumber":"6006",
    "addr:postcode":"33709",
    "addr:street":"49Th St N",
    "iso:country":"US",
    "sg:address":"6006 49th St N",
    "sg:city":"St Petersburg",
    "sg:classifiers":[
        {
            "category":"Health Services",
            "subcategory":"Doctor",
            "type":"Services"
        }
    ],
    "sg:phone":"+1 727 527 9779",
    "sg:postcode":"33709",
    "sg:province":"FL",
    "sg:tags":[
        "physician",
        "surgeon"
    ],
    "wof:name":"Vinay Badhwar MD",
    "wof:placetype":"venue"
},
  "geometry": {"coordinates":[-82.699989,27.827306],"type":"Point"}
}