{
  "type": "Feature",
  "properties": {
    "iso:country":"US",
    "sg:address":"120 NW 25th St",
    "sg:city":"Miami",
    "sg:classifiers":[
        {
            "category":"Real Estate",
            "subcategory":"Real Estate Services",
            "type":"Services"
        },
        {
            "category":"Real Estate",
            "subcategory":"Real Estate Agent",
            "type":"Services"
        }
    ],
    "sg:phone":"+1 305 572 0611",
    "sg:postcode":"33127",
    "sg:province":"FL",
    "sg:tags":[
        "buyer",
        "management",
        "broker"
    ],
    "wof:name":"Dtm",
    "wof:placetype":"venue"
},
  "geometry": {"coordinates":[-80.197497,25.800767],"type":"Point"}
}