{
  "type": "Feature",
  "properties": {
    "iso:country":"US",
    "sg:address":"5021 W Laurel St",
    "sg:city":"Tampa",
    "sg:classifiers":[
        {
            "category":"Wholesale",
            "subcategory":"Durable Goods & Equipment",
            "type":"Manufacturing & Wholesale Goods"
        }
    ],
    "sg:phone":"+1 813 289 1600",
    "sg:postcode":"33607",
    "sg:province":"FL",
    "sg:tags":[
        "representative",
        "manufacturer"
    ],
    "wof:name":"Southeastern Electrical Sales",
    "wof:placetype":"venue"
},
  "geometry": {"coordinates":[-82.528926,27.956054],"type":"Point"}
}