{
  "type": "Feature",
  "properties": {
    "iso:country":"US",
    "sg:address":"773 Lucern Cir",
    "sg:city":"Ormond Beach",
    "sg:classifiers":[
        {
            "category":"Professional",
            "subcategory":"Management & Consulting",
            "type":"Services"
        }
    ],
    "sg:phone":"+1 386 451 5390",
    "sg:postcode":"32174",
    "sg:province":"FL",
    "sg:tags":[
        "business"
    ],
    "wof:name":"Acuri Enterprises Inc",
    "wof:placetype":"venue"
},
  "geometry": {"coordinates":[-81.070065,29.302823],"type":"Point"}
}