{
  "type": "Feature",
  "properties": {
    "iso:country":"US",
    "sg:address":"6209 Mcintosh Rd",
    "sg:city":"Sarasota",
    "sg:classifiers":[
        {
            "category":"Shopping",
            "subcategory":"Florist",
            "type":"Retail Goods"
        }
    ],
    "sg:phone":"+1 941 922 3200",
    "sg:postcode":"34238",
    "sg:province":"FL",
    "wof:name":"Floral Expressions By Russ",
    "wof:placetype":"venue"
},
  "geometry": {"coordinates":[-82.48107899999999,27.262851],"type":"Point"}
}