{
  "type": "Feature",
  "properties": {
    "addr:full":"2304 Vinkara Dr Tallahassee FL 32303",
    "addr:housenumber":"2304",
    "addr:postcode":"32303",
    "addr:street":"Vinkara Dr",
    "iso:country":"US",
    "sg:address":"2304 Vinkara Dr",
    "sg:city":"Tallahassee",
    "sg:classifiers":[
        {
            "category":"Communications",
            "subcategory":"Film & Video Production",
            "type":"Services"
        }
    ],
    "sg:phone":"+1 850 212 5550",
    "sg:postcode":"32303",
    "sg:province":"FL",
    "sg:tags":[
        "recording",
        "equipment",
        "studio"
    ],
    "wof:name":"Log Cabin Studio",
    "wof:placetype":"venue"
},
  "geometry": {"coordinates":[-84.321855,30.471265],"type":"Point"}
}