{
  "type": "Feature",
  "properties": {
    "addr:full":"119 E Lucy St Homestead FL 33034",
    "addr:housenumber":"119",
    "addr:postcode":"33034",
    "addr:street":"E Lucy St",
    "iso:country":"US",
    "sg:address":"119 E Lucy St",
    "sg:city":"Homestead",
    "sg:classifiers":[
        {
            "category":"Wholesale",
            "subcategory":"Hardware",
            "type":"Manufacturing & Wholesale Goods"
        }
    ],
    "sg:phone":"+1 305 245 1003",
    "sg:postcode":"33034",
    "sg:province":"FL",
    "sg:tags":[
        "tool"
    ],
    "wof:name":"A & R Tool Distributors",
    "wof:placetype":"venue"
},
  "geometry": {"coordinates":[-80.473096,25.462466],"type":"Point"}
}