{
  "type": "Feature",
  "properties": {
    "iso:country":"US",
    "sg:address":"1620 Washington Ave",
    "sg:city":"Miami Beach",
    "sg:classifiers":[
        {
            "category":"Shopping",
            "subcategory":"Bicycles & Sporting Goods",
            "type":"Retail Goods"
        },
        {
            "category":"Sports & Exercise",
            "subcategory":"Bicycle Rental",
            "type":"Entertainment"
        }
    ],
    "sg:phone":"+1 305 532 1954",
    "sg:postcode":"33139",
    "sg:province":"FL",
    "sg:tags":[
        "bike"
    ],
    "sg:website":"www.fritzsmiamibeach.com/about-i...",
    "wof:name":"Fritz's Skate Bike & Surf Retail",
    "wof:placetype":"venue"
},
  "geometry": {"coordinates":[-80.13191399999999,25.789762],"type":"Point"}
}