{
  "type": "Feature",
  "properties": {
    "iso:country":"US",
    "sg:address":"3403 S US Hwy 1",
    "sg:city":"Fort Pierce",
    "sg:classifiers":[
        {
            "category":"Retail",
            "subcategory":"Repair Shop",
            "type":"Services"
        }
    ],
    "sg:phone":"+1 772 461 4030",
    "sg:postcode":"34982",
    "sg:province":"FL",
    "sg:tags":[
        "taxidermist"
    ],
    "wof:name":"Bob's Trophy Master Fishmounts",
    "wof:placetype":"venue"
},
  "geometry": {"coordinates":[-80.325813,27.403869],"type":"Point"}
}