{
  "type": "Feature",
  "properties": {
    "iso:country":"US",
    "sg:address":"9440 W Fishbowl Dr",
    "sg:city":"Homosassa",
    "sg:classifiers":[
        {
            "category":"Freight",
            "type":"Transportation"
        }
    ],
    "sg:phone":"+1 352 628 3820",
    "sg:postcode":"34448",
    "sg:province":"FL",
    "sg:tags":[
        "operator",
        "trucking"
    ],
    "wof:name":"Rebuck Corp",
    "wof:placetype":"venue"
},
  "geometry": {"coordinates":[-82.59074099999999,28.797008],"type":"Point"}
}