{
  "type": "Feature",
  "properties": {
    "iso:country":"US",
    "sg:address":"2913 Lithia Pinecrest Rd",
    "sg:city":"Valrico",
    "sg:classifiers":[
        {
            "category":"Building & Trades",
            "subcategory":"Electrical",
            "type":"Services"
        }
    ],
    "sg:phone":"+1 813 689 2071",
    "sg:postcode":"33596",
    "sg:province":"FL",
    "sg:tags":[
        "electric",
        "contractor"
    ],
    "wof:name":"Bennett Electric & Sons Inc",
    "wof:placetype":"venue"
},
  "geometry": {"coordinates":[-82.25278900000001,27.903775],"type":"Point"}
}