{
  "type": "Feature",
  "properties": {
    "iso:country":"US",
    "sg:address":"6931 Crane Ave",
    "sg:city":"Jacksonville",
    "sg:classifiers":[
        {
            "category":"Building & Trades",
            "subcategory":"Construction",
            "type":"Services"
        }
    ],
    "sg:phone":"+1 904 724 5199",
    "sg:postcode":"32216",
    "sg:province":"FL",
    "sg:tags":[
        "contractor"
    ],
    "wof:name":"LTD Tile Inc",
    "wof:placetype":"venue"
},
  "geometry": {"coordinates":[-81.585207,30.307966],"type":"Point"}
}