{
  "type": "Feature",
  "properties": {
    "addr:full":"121 Hickory Creek Blvd Brandon FL 33511",
    "addr:housenumber":"121",
    "addr:postcode":"33511",
    "addr:street":"Hickory Creek Blvd",
    "iso:country":"US",
    "sg:address":"121 Hickory Creek Blvd",
    "sg:city":"Brandon",
    "sg:classifiers":[
        {
            "category":"Banks & Credit Unions",
            "subcategory":"Financial Services",
            "type":"Services"
        }
    ],
    "sg:phone":"+1 813 685 7744",
    "sg:postcode":"33511",
    "sg:province":"FL",
    "sg:tags":[
        "investment",
        "closed"
    ],
    "wof:name":"Cimafranca Investments Lt",
    "wof:placetype":"venue"
},
  "geometry": {"coordinates":[-82.28543500000001,27.873858],"type":"Point"}
}