{
  "type": "Feature",
  "properties": {
    "iso:country":"US",
    "sg:address":"1631 Del Prado Blvd S",
    "sg:city":"Cape Coral",
    "sg:classifiers":[
        {
            "category":"Shopping",
            "subcategory":"Pharmacy",
            "type":"Retail Goods"
        },
        {
            "category":"Food & Beverages",
            "subcategory":"Groceries & Convenience Stores",
            "type":"Retail Goods"
        }
    ],
    "sg:phone":"+1 239 574 9183",
    "sg:postcode":"33990",
    "sg:province":"FL",
    "sg:tags":[
        "drugstore"
    ],
    "sg:website":"www.publix.com",
    "wof:name":"Publix Super Markets",
    "wof:placetype":"venue"
},
  "geometry": {"coordinates":[-81.940577,26.620621],"type":"Point"}
}