{
  "type": "Feature",
  "properties": {
    "addr:full":"829 W Charing Crosse Cir Lake Mary FL 32746",
    "addr:housenumber":"829",
    "addr:postcode":"32746",
    "addr:street":"W Charing Crosse Cir",
    "iso:country":"US",
    "sg:address":"829 W Charing Crosse Cir",
    "sg:city":"Lake Mary",
    "sg:classifiers":[
        {
            "category":"Building & Trades",
            "subcategory":"Construction",
            "type":"Services"
        }
    ],
    "sg:phone":"+1 407 247 9556",
    "sg:postcode":"32746",
    "sg:province":"FL",
    "sg:tags":[
        "tile",
        "dealer",
        "contractor"
    ],
    "wof:name":"Girem Tile Works",
    "wof:placetype":"venue"
},
  "geometry": {"coordinates":[-81.352738,28.736143],"type":"Point"}
}