{
  "type": "Feature",
  "properties": {
    "iso:country":"US",
    "sg:address":"1920 Windsor Oak Dr",
    "sg:city":"Apopka",
    "sg:classifiers":[
        {
            "category":"Professional",
            "subcategory":"Computer Services",
            "type":"Services"
        }
    ],
    "sg:phone":"+1 407 886 1049",
    "sg:postcode":"32703",
    "sg:province":"FL",
    "sg:tags":[
        "internet"
    ],
    "wof:name":"Verti Quest Technologies",
    "wof:placetype":"venue"
},
  "geometry": {"coordinates":[-81.474476,28.647368],"type":"Point"}
}