{
  "type": "Feature",
  "properties": {
    "iso:country":"US",
    "sg:address":"8104 NW 74th Ter",
    "sg:city":"Fort Lauderdale",
    "sg:classifiers":[
        {
            "category":"Home & Garden",
            "subcategory":"Building Materials",
            "type":"Retail Goods"
        }
    ],
    "sg:phone":"+1 954 721 1800",
    "sg:postcode":"33321",
    "sg:province":"FL",
    "wof:name":"Wall Designs By Steve",
    "wof:placetype":"venue"
},
  "geometry": {"coordinates":[-80.250427,26.223568],"type":"Point"}
}