{
  "type": "Feature",
  "properties": {
    "iso:country":"US",
    "sg:address":"118 Live Oaks Blvd",
    "sg:city":"Casselberry",
    "sg:classifiers":[
        {
            "category":"Home & Garden",
            "subcategory":"Household Appliances",
            "type":"Retail Goods"
        },
        {
            "category":"Building & Trades",
            "subcategory":"Construction",
            "type":"Services"
        }
    ],
    "sg:phone":"+1 407 331 4477",
    "sg:postcode":"32707",
    "sg:province":"FL",
    "sg:tags":[
        "major",
        "dishwashing",
        "system",
        "machine",
        "contractor",
        "air conditioning"
    ],
    "wof:name":"A C Mechanix Heat & Air Inc",
    "wof:placetype":"venue"
},
  "geometry": {"coordinates":[-81.345524,28.664533],"type":"Point"}
}