{
  "type": "Feature",
  "properties": {
    "addr:full":"400 NW 2nd Ave Miami FL 33128",
    "addr:housenumber":"400",
    "addr:postcode":"33128",
    "addr:street":"Nw 2Nd Ave",
    "iso:country":"US",
    "sg:address":"400 NW 2nd Ave",
    "sg:city":"Miami",
    "sg:classifiers":[
        {
            "category":"Landmark",
            "subcategory":"Tourist Information",
            "type":"Public Place"
        }
    ],
    "sg:phone":"+1 305 373 1647",
    "sg:postcode":"33128",
    "sg:province":"FL",
    "sg:tags":[
        "tour"
    ],
    "wof:name":"Tropical Tours",
    "wof:placetype":"venue"
},
  "geometry": {"coordinates":[-80.197701,25.778299],"type":"Point"}
}