{
  "type": "Feature",
  "properties": {
    "addr:full":"1790 Sand Lake Rd Orlando FL 32809",
    "addr:housenumber":"1790",
    "addr:postcode":"32809",
    "addr:street":"Sand Lake Rd",
    "iso:country":"US",
    "sg:address":"1790 Sand Lake Rd",
    "sg:city":"Orlando",
    "sg:classifiers":[
        {
            "category":"Professional",
            "subcategory":"Business Services",
            "type":"Services"
        }
    ],
    "sg:phone":"+1 407 812 1707",
    "sg:postcode":"32809",
    "sg:province":"FL",
    "sg:tags":[
        "exporter"
    ],
    "wof:name":"Innovation Salon & Spa",
    "wof:placetype":"venue"
},
  "geometry": {"coordinates":[-81.40423800000001,28.450184],"type":"Point"}
}