{
  "type": "Feature",
  "properties": {
    "iso:country":"US",
    "sg:address":"1421 E Oakland Park Blvd",
    "sg:city":"Oakland Park",
    "sg:classifiers":[
        {
            "category":"Real Estate",
            "subcategory":"Real Estate Agent",
            "type":"Services"
        }
    ],
    "sg:phone":"+1 954 568 0063",
    "sg:postcode":"33334",
    "sg:province":"FL",
    "wof:name":"Costamar Realty",
    "wof:placetype":"venue"
},
  "geometry": {"coordinates":[-80.12833999999999,26.167063],"type":"Point"}
}