{
  "type": "Feature",
  "properties": {
    "addr:full":"292 Fannie Rd Flomaton FL 36441",
    "addr:housenumber":"292",
    "addr:postcode":"36441",
    "addr:street":"Fannie Rd",
    "iso:country":"US",
    "sg:address":"292 Fannie Rd",
    "sg:city":"Flomaton",
    "sg:classifiers":[
        {
            "category":"Professional",
            "type":"Services"
        }
    ],
    "sg:phone":"+1 251 296 5770",
    "sg:postcode":"36441",
    "sg:province":"FL",
    "wof:name":"F & L Trk",
    "wof:placetype":"venue"
},
  "geometry": {"coordinates":[-87.229643,30.999343],"type":"Point"}
}