{
  "type": "Feature",
  "properties": {
    "iso:country":"US",
    "sg:address":"11838 Front Beach Rd",
    "sg:city":"Panama City Bch",
    "sg:classifiers":[
        {
            "category":"Autos & Motor Vehicles",
            "subcategory":"Automobile Sales",
            "type":"Retail Goods"
        }
    ],
    "sg:phone":"+1 850 233 1235",
    "sg:postcode":"32407",
    "sg:province":"FL",
    "sg:tags":[
        "cart"
    ],
    "wof:name":"Naskart Speedway Of Panama",
    "wof:placetype":"venue"
},
  "geometry": {"coordinates":[-85.82837000000001,30.189327],"type":"Point"}
}