{
  "type": "Feature",
  "properties": {
    "iso:country":"US",
    "sg:address":"9105 S Dadeland Blvd",
    "sg:city":"Miami",
    "sg:classifiers":[
        {
            "category":"Freight",
            "type":"Transportation"
        },
        {
            "category":"Airline",
            "type":"Transportation"
        }
    ],
    "sg:phone":"+1 305 670 3402",
    "sg:postcode":"33156",
    "sg:province":"FL",
    "sg:tags":[
        "cargo",
        "company",
        "carrier",
        "air"
    ],
    "wof:name":"Custom Air Transport Inc",
    "wof:placetype":"venue"
},
  "geometry": {"coordinates":[-80.312056,25.687141],"type":"Point"}
}