{
  "type": "Feature",
  "properties": {
    "iso:country":"US",
    "sg:address":"209 N Florida St",
    "sg:city":"Bushnell",
    "sg:classifiers":[
        {
            "category":"Government",
            "subcategory":"Office",
            "type":"Public Place"
        }
    ],
    "sg:phone":"+1 352 259 1400",
    "sg:postcode":"33513",
    "sg:province":"FL",
    "wof:name":"Sumter County E-911 Adm",
    "wof:placetype":"venue"
},
  "geometry": {"coordinates":[-82.11048,28.663578],"type":"Point"}
}