{
  "type": "Feature",
  "properties": {
    "addr:full":"101 NE 122nd St North Miami FL 33161",
    "addr:housenumber":"101",
    "addr:postcode":"33161",
    "addr:street":"Ne 122Nd St",
    "iso:country":"US",
    "sg:address":"101 NE 122nd St",
    "sg:city":"North Miami",
    "sg:classifiers":[
        {
            "category":"Building & Trades",
            "subcategory":"Construction",
            "type":"Services"
        }
    ],
    "sg:phone":"+1 305 948 4705",
    "sg:postcode":"33161",
    "sg:province":"FL",
    "sg:tags":[
        "demolition",
        "contractor"
    ],
    "wof:name":"Coastal Inc",
    "wof:placetype":"venue"
},
  "geometry": {"coordinates":[-80.194366,25.88743],"type":"Point"}
}