{
  "type": "Feature",
  "properties": {
    "addr:full":"5112 E Colonial Dr Orlando FL 32803",
    "addr:housenumber":"5112",
    "addr:postcode":"32803",
    "addr:street":"E Colonial Dr",
    "iso:country":"US",
    "sg:address":"5112 E Colonial Dr",
    "sg:city":"Orlando",
    "sg:classifiers":[
        {
            "category":"Home & Garden",
            "subcategory":"Furniture",
            "type":"Retail Goods"
        }
    ],
    "sg:phone":"+1 407 894 6666",
    "sg:postcode":"32803",
    "sg:province":"FL",
    "wof:name":"Kane's Furniture Co",
    "wof:placetype":"venue"
},
  "geometry": {"coordinates":[-81.321957,28.55345],"type":"Point"}
}