{
  "type": "Feature",
  "properties": {
    "addr:full":"15220 Coral Isle Ct Fort Myers FL 33919",
    "addr:housenumber":"15220",
    "addr:postcode":"33919",
    "addr:street":"Coral Isle Ct",
    "iso:country":"US",
    "sg:address":"15220 Coral Isle Ct",
    "sg:city":"Fort Myers",
    "sg:classifiers":[
        {
            "category":"Building & Trades",
            "subcategory":"Construction",
            "type":"Services"
        }
    ],
    "sg:phone":"+1 239 415 0333",
    "sg:postcode":"33919",
    "sg:province":"FL",
    "sg:tags":[
        "painter"
    ],
    "wof:name":"Faux & Murals By C Studtmann",
    "wof:placetype":"venue"
},
  "geometry": {"coordinates":[-81.908098,26.521954],"type":"Point"}
}