{
  "type": "Feature",
  "properties": {
    "iso:country":"US",
    "sg:address":"1498 Park Ave",
    "sg:city":"Orange Park",
    "sg:classifiers":[
        {
            "category":"Shopping",
            "subcategory":"Clothing, Apparel, & Fashions",
            "type":"Retail Goods"
        }
    ],
    "sg:phone":"+1 904 278 7942",
    "sg:postcode":"32073",
    "sg:province":"FL",
    "sg:tags":[
        "wear"
    ],
    "wof:name":"Tots To Teens",
    "wof:placetype":"venue"
},
  "geometry": {"coordinates":[-81.701489,30.172075],"type":"Point"}
}