{
  "type": "Feature",
  "properties": {
    "iso:country":"US",
    "sg:address":"2689 W 76th St",
    "sg:city":"Hialeah",
    "sg:classifiers":[
        {
            "category":"Wholesale",
            "subcategory":"Non-durable Goods",
            "type":"Manufacturing & Wholesale Goods"
        },
        {
            "category":"Manufacturing",
            "subcategory":"Glass & Minerals",
            "type":"Manufacturing & Wholesale Goods"
        }
    ],
    "sg:phone":"+1 305 558 3877",
    "sg:postcode":"33016",
    "sg:province":"FL",
    "sg:tags":[
        "dry",
        "goods-wholesale",
        "glass-wholesale",
        "shape",
        "circle",
        "glass-block",
        "special",
        "manufacturer"
    ],
    "sg:website":"http://www.albumcrafters.com",
    "wof:name":"Authentic Glass Inc",
    "wof:placetype":"venue"
},
  "geometry": {"coordinates":[-80.337754,25.891506],"type":"Point"}
}