{
  "type": "Feature",
  "properties": {
    "addr:full":"11900 Stoneybrook Golf Dr Estero FL 33928",
    "addr:housenumber":"11900",
    "addr:postcode":"33928",
    "addr:street":"Stoneybrook Golf Dr",
    "iso:country":"US",
    "sg:address":"11900 Stoneybrook Golf Dr",
    "sg:city":"Estero",
    "sg:classifiers":[
        {
            "category":"Education",
            "subcategory":"School",
            "type":"Public Place"
        }
    ],
    "sg:phone":"+1 239 947 7500",
    "sg:postcode":"33928",
    "sg:province":"FL",
    "wof:name":"Pinewoods Elementary",
    "wof:placetype":"venue"
},
  "geometry": {"coordinates":[-81.773624,26.425464],"type":"Point"}
}