{
  "type": "Feature",
  "properties": {
    "iso:country":"US",
    "sg:address":"100 W Gore St Ste 300",
    "sg:city":"Orlando",
    "sg:classifiers":[
        {
            "category":"Health Services",
            "subcategory":"Doctor",
            "type":"Services"
        }
    ],
    "sg:phone":"+1 407 841 6710",
    "sg:postcode":"32806",
    "sg:province":"FL",
    "sg:tags":[
        "physician",
        "surgeon"
    ],
    "wof:name":"Robert M Duplis Md Pa",
    "wof:placetype":"venue"
},
  "geometry": {"coordinates":[-81.380112,28.531139],"type":"Point"}
}