{
  "type": "Feature",
  "properties": {
    "iso:country":"US",
    "sg:address":"1102 N Woodland Blvd",
    "sg:city":"Deland",
    "sg:classifiers":[
        {
            "category":"Retail",
            "subcategory":"Car Wash",
            "type":"Services"
        }
    ],
    "sg:phone":"+1 386 734 4795",
    "sg:postcode":"32720",
    "sg:province":"FL",
    "sg:tags":[
        "carwash",
        "automobile",
        "detail",
        "clean"
    ],
    "wof:name":"Spotless Detailing Inc",
    "wof:placetype":"venue"
},
  "geometry": {"coordinates":[-81.304051,29.046875],"type":"Point"}
}