{
  "type": "Feature",
  "properties": {
    "iso:country":"US",
    "sg:address":"4917 E Colonial Dr",
    "sg:city":"Orlando",
    "sg:classifiers":[
        {
            "category":"Personal",
            "subcategory":"Beauty Salon",
            "type":"Services"
        }
    ],
    "sg:phone":"+1 407 895 7176",
    "sg:postcode":"32803",
    "sg:province":"FL",
    "wof:name":"On Cue Styles",
    "wof:placetype":"venue"
},
  "geometry": {"coordinates":[-81.32270200000001,28.553518],"type":"Point"}
}