{
  "type": "Feature",
  "properties": {
    "iso:country":"US",
    "sg:address":"502 NW 101st Ave",
    "sg:city":"Pompano Beach",
    "sg:classifiers":[
        {
            "category":"Wholesale",
            "subcategory":"Non-durable Goods",
            "type":"Manufacturing & Wholesale Goods"
        }
    ],
    "sg:phone":"+1 954 345 0055",
    "sg:postcode":"33071",
    "sg:province":"FL",
    "sg:tags":[
        "novelty",
        "jewelry",
        "gift"
    ],
    "wof:name":"Frnaz Georg Interprises Inc",
    "wof:placetype":"venue"
},
  "geometry": {"coordinates":[-80.261335,26.235877],"type":"Point"}
}