{
  "type": "Feature",
  "properties": {
    "addr:full":"10396 Grove St Fort Lauderdale FL 33328",
    "addr:housenumber":"10396",
    "addr:postcode":"33328",
    "addr:street":"Grove St",
    "iso:country":"US",
    "sg:address":"10396 Grove St",
    "sg:city":"Fort Lauderdale",
    "sg:classifiers":[
        {
            "category":"Professional",
            "subcategory":"Computer Services",
            "type":"Services"
        }
    ],
    "sg:phone":"+1 954 680 6855",
    "sg:postcode":"33328",
    "sg:province":"FL",
    "sg:tags":[
        "programing",
        "custom"
    ],
    "wof:name":"Electric Product Solutions",
    "wof:placetype":"venue"
},
  "geometry": {"coordinates":[-80.28435899999999,26.059435],"type":"Point"}
}