{
  "type": "Feature",
  "properties": {
    "addr:full":"1416 Oldfield Dr Tallahassee FL 32308",
    "addr:housenumber":"1416",
    "addr:postcode":"32308",
    "addr:street":"Oldfield Dr",
    "iso:country":"US",
    "sg:address":"1416 Oldfield Dr",
    "sg:city":"Tallahassee",
    "sg:classifiers":[
        {
            "category":"Real Estate",
            "subcategory":"Real Estate Agent",
            "type":"Services"
        }
    ],
    "sg:phone":"+1 850 523 0618",
    "sg:postcode":"32308",
    "sg:province":"FL",
    "wof:name":"Gould Realty",
    "wof:placetype":"venue"
},
  "geometry": {"coordinates":[-84.251502,30.484109],"type":"Point"}
}