{
  "type": "Feature",
  "properties": {
    "iso:country":"US",
    "sg:address":"1923 NW 22nd St",
    "sg:city":"Stuart",
    "sg:classifiers":[
        {
            "category":"Insurance",
            "subcategory":"Insurance Agent",
            "type":"Services"
        }
    ],
    "sg:phone":"+1 772 692 0071",
    "sg:postcode":"34994",
    "sg:province":"FL",
    "wof:name":"Michael Galen Insurance A",
    "wof:placetype":"venue"
},
  "geometry": {"coordinates":[-80.278447,27.232598],"type":"Point"}
}