{
  "type": "Feature",
  "properties": {
    "addr:full":"883 Vanderbilt Beach Rd Naples FL 34108",
    "addr:housenumber":"883",
    "addr:postcode":"34108",
    "addr:street":"Vanderbilt Beach Rd",
    "iso:country":"US",
    "sg:address":"883 Vanderbilt Beach Rd",
    "sg:city":"Naples",
    "sg:classifiers":[
        {
            "category":"Retail",
            "subcategory":"Laundry & Dry Cleaning",
            "type":"Services"
        }
    ],
    "sg:phone":"+1 239 949 1677",
    "sg:postcode":"34108",
    "sg:province":"FL",
    "sg:tags":[
        "drycleaning",
        "plant",
        "cleaners"
    ],
    "wof:name":"Same Day Dry Cleaners",
    "wof:placetype":"venue"
},
  "geometry": {"coordinates":[-81.81646000000001,26.252841],"type":"Point"}
}