{
  "type": "Feature",
  "properties": {
    "iso:country":"US",
    "sg:address":"2909 Minnesota Ave",
    "sg:city":"Lynn Haven",
    "sg:classifiers":[
        {
            "category":"Real Estate",
            "subcategory":"Real Estate Agent",
            "type":"Services"
        }
    ],
    "sg:phone":"+1 850 873 6766",
    "sg:postcode":"32444",
    "sg:province":"FL",
    "sg:tags":[
        "apartment",
        "sharing"
    ],
    "wof:name":"Pinnacle At Hammock Place Apts",
    "wof:placetype":"venue"
},
  "geometry": {"coordinates":[-85.645426,30.217355],"type":"Point"}
}