{
  "type": "Feature",
  "properties": {
    "addr:full":"629 N Semoran Blvd Orlando FL 32807",
    "addr:housenumber":"629",
    "addr:postcode":"32807",
    "addr:street":"N Semoran Blvd",
    "iso:country":"US",
    "sg:address":"629 N Semoran Blvd",
    "sg:city":"Orlando",
    "sg:classifiers":[
        {
            "category":"Wholesale",
            "subcategory":"Office Equipment",
            "type":"Manufacturing & Wholesale Goods"
        }
    ],
    "sg:phone":"+1 407 832 7403",
    "sg:postcode":"32807",
    "sg:province":"FL",
    "sg:tags":[
        "vault",
        "safe"
    ],
    "wof:name":"Just Safes",
    "wof:placetype":"venue"
},
  "geometry": {"coordinates":[-81.310632,28.550759],"type":"Point"}
}