{
  "type": "Feature",
  "properties": {
    "iso:country":"US",
    "sg:address":"3237 Connector Dr",
    "sg:city":"Tallahassee",
    "sg:classifiers":[
        {
            "category":"Shopping",
            "subcategory":"Hobbies, Toys, & Games",
            "type":"Retail Goods"
        }
    ],
    "sg:phone":"+1 850 562 4141",
    "sg:postcode":"32303",
    "sg:province":"FL",
    "wof:name":"Glass Productions",
    "wof:placetype":"venue"
},
  "geometry": {"coordinates":[-84.345051,30.494826],"type":"Point"}
}