{
  "type": "Feature",
  "properties": {
    "iso:country":"US",
    "sg:address":"4955 Riveredge Dr",
    "sg:city":"Titusville",
    "sg:classifiers":[
        {
            "category":"Food & Beverages",
            "subcategory":"Groceries & Convenience Stores",
            "type":"Retail Goods"
        }
    ],
    "sg:phone":"+1 321 383 4940",
    "sg:postcode":"32780",
    "sg:province":"FL",
    "sg:tags":[
        "landscape"
    ],
    "wof:name":"Cleary Michael Curb Appea",
    "wof:placetype":"venue"
},
  "geometry": {"coordinates":[-80.793555,28.548893],"type":"Point"}
}