{
  "type": "Feature",
  "properties": {
    "iso:country":"US",
    "sg:address":"2901 S Bayshore Dr",
    "sg:city":"Miami",
    "sg:classifiers":[
        {
            "category":"Professional",
            "type":"Services"
        },
        {
            "category":"Arts & Performance",
            "subcategory":"Theater",
            "type":"Entertainment"
        }
    ],
    "sg:phone":"+1 305 447 9108",
    "sg:postcode":"33133",
    "sg:province":"FL",
    "sg:tags":[
        "live",
        "music"
    ],
    "wof:name":"Ted Maliaris Conglomerate Inc",
    "wof:placetype":"venue"
},
  "geometry": {"coordinates":[-80.240032,25.72627],"type":"Point"}
}