{
  "type": "Feature",
  "properties": {
    "iso:country":"US",
    "sg:address":"2072 SW Racquet Club Dr",
    "sg:city":"Palm City",
    "sg:classifiers":[
        {
            "category":"Restaurant",
            "type":"Food & Drink"
        }
    ],
    "sg:phone":"+1 772 286 2208",
    "sg:postcode":"34990",
    "sg:province":"FL",
    "sg:tags":[
        "eating"
    ],
    "wof:name":"Flamboyant Hummingbird Bisgtro",
    "wof:placetype":"venue"
},
  "geometry": {"coordinates":[-80.299995,27.184324],"type":"Point"}
}