{
  "type": "Feature",
  "properties": {
    "addr:full":"11043 Crystal Springs Rd Jacksonville FL 32221",
    "addr:housenumber":"11043",
    "addr:postcode":"32221",
    "addr:street":"Crystal Springs Rd",
    "iso:country":"US",
    "sg:address":"11043 Crystal Springs Rd",
    "sg:city":"Jacksonville",
    "sg:classifiers":[
        {
            "category":"Utilities",
            "subcategory":"Mobile Phone",
            "type":"Services"
        }
    ],
    "sg:phone":"+1 904 695 9151",
    "sg:postcode":"32221",
    "sg:province":"FL",
    "sg:tags":[
        "telephone",
        "cellular"
    ],
    "wof:name":"Cell One Family Communication",
    "wof:placetype":"venue"
},
  "geometry": {"coordinates":[-81.842455,30.302497],"type":"Point"}
}