{
  "type": "Feature",
  "properties": {
    "iso:country":"US",
    "sg:address":"6801 Sheldon Rd",
    "sg:city":"Tampa",
    "sg:classifiers":[
        {
            "category":"Health Services",
            "subcategory":"Doctor",
            "type":"Services"
        }
    ],
    "sg:phone":"+1 813 885 1770",
    "sg:postcode":"33615",
    "sg:province":"FL",
    "sg:tags":[
        "physician",
        "surgeon"
    ],
    "wof:name":"Bayside Pediatrics",
    "wof:placetype":"venue"
},
  "geometry": {"coordinates":[-82.58329500000001,28.011685],"type":"Point"}
}