{
  "type": "Feature",
  "properties": {
    "iso:country":"US",
    "sg:address":"3546 Blanding Blvd",
    "sg:city":"Jacksonville",
    "sg:classifiers":[
        {
            "category":"Restaurant",
            "type":"Food & Drink"
        }
    ],
    "sg:phone":"+1 904 772 7866",
    "sg:postcode":"32210",
    "sg:province":"FL",
    "sg:website":"www.furrs.net",
    "wof:name":"Stevie B's Southern Buffet",
    "wof:placetype":"venue"
},
  "geometry": {"coordinates":[-81.734915,30.271944],"type":"Point"}
}