{
  "type": "Feature",
  "properties": {
    "addr:full":"2700 E Martin Luther King Jr Blvd Tampa FL 33610",
    "addr:housenumber":"2700",
    "addr:postcode":"33610",
    "addr:street":"E Martin Luther King Jr Blvd",
    "iso:country":"US",
    "sg:address":"2700 E Martin Luther King Jr Blvd",
    "sg:city":"Tampa",
    "sg:classifiers":[
        {
            "category":"Health Services",
            "subcategory":"Health Practitioner",
            "type":"Services"
        }
    ],
    "sg:phone":"+1 813 877 1930",
    "sg:postcode":"33610",
    "sg:province":"FL",
    "sg:tags":[
        "therapist",
        "physical"
    ],
    "wof:name":"Physiotherapy Associates Inc",
    "wof:placetype":"venue"
},
  "geometry": {"coordinates":[-82.428658,27.981441],"type":"Point"}
}