{
  "type": "Feature",
  "properties": {
    "iso:country":"US",
    "sg:address":"7095 SW 47th St",
    "sg:city":"Miami",
    "sg:classifiers":[
        {
            "category":"Shopping",
            "subcategory":"Used Merchandise",
            "type":"Retail Goods"
        }
    ],
    "sg:phone":"+1 305 666 0391",
    "sg:postcode":"33155",
    "sg:province":"FL",
    "sg:tags":[
        "antique"
    ],
    "wof:name":"ESC Inc",
    "wof:placetype":"venue"
},
  "geometry": {"coordinates":[-80.308643,25.726495],"type":"Point"}
}