{
  "type": "Feature",
  "properties": {
    "addr:full":"8434 SW 163rd Pl Miami FL 33193",
    "addr:housenumber":"8434",
    "addr:postcode":"33193",
    "addr:street":"Sw 163Rd Pl",
    "iso:country":"US",
    "sg:address":"8434 SW 163rd Pl",
    "sg:city":"Miami",
    "sg:classifiers":[
        {
            "category":"Wholesale",
            "subcategory":"Durable Goods & Equipment",
            "type":"Manufacturing & Wholesale Goods"
        }
    ],
    "sg:phone":"+1 305 385 6821",
    "sg:postcode":"33193",
    "sg:province":"FL",
    "sg:tags":[
        "professional"
    ],
    "wof:name":"On-Line Frames Inc",
    "wof:placetype":"venue"
},
  "geometry": {"coordinates":[-80.457713,25.686166],"type":"Point"}
}