{
  "type": "Feature",
  "properties": {
    "addr:full":"5935 NW 12th Ave Miami FL 33127",
    "addr:housenumber":"5935",
    "addr:postcode":"33127",
    "addr:street":"Nw 12Th Ave",
    "iso:country":"US",
    "sg:address":"5935 NW 12th Ave",
    "sg:city":"Miami",
    "sg:classifiers":[
        {
            "category":"Health Services",
            "subcategory":"Doctor",
            "type":"Services"
        }
    ],
    "sg:phone":"+1 305 757 1872",
    "sg:postcode":"33127",
    "sg:province":"FL",
    "sg:tags":[
        "clinic"
    ],
    "wof:name":"Around The Clock Medical Ctr",
    "wof:placetype":"venue"
},
  "geometry": {"coordinates":[-80.21643400000001,25.830043],"type":"Point"}
}