{
  "type": "Feature",
  "properties": {
    "iso:country":"US",
    "sg:address":"101 Sidonia Ave",
    "sg:city":"Coral Gables",
    "sg:classifiers":[
        {
            "category":"Professional",
            "subcategory":"Management & Consulting",
            "type":"Services"
        }
    ],
    "sg:phone":"+1 305 476 8068",
    "sg:postcode":"33134",
    "sg:province":"FL",
    "sg:tags":[
        "fuel"
    ],
    "wof:name":"Design Management & Builders",
    "wof:placetype":"venue"
},
  "geometry": {"coordinates":[-80.258764,25.759764],"type":"Point"}
}