{
  "type": "Feature",
  "properties": {
    "addr:full":"9398 Atlantic Blvd Jacksonville FL 32225",
    "addr:housenumber":"9398",
    "addr:postcode":"32225",
    "addr:street":"Atlantic Blvd",
    "iso:country":"US",
    "sg:address":"9398 Atlantic Blvd",
    "sg:city":"Jacksonville",
    "sg:classifiers":[
        {
            "category":"Restaurant",
            "type":"Food & Drink"
        }
    ],
    "sg:menulink":"http://www.allmenus.com/fl/jacksonville/179705-chick-fil-a/menu/",
    "sg:phone":"+1 904 724 4828",
    "sg:postcode":"32225",
    "sg:province":"FL",
    "sg:tags":[
        "wrap",
        "soup",
        "american",
        "sandwich",
        "salad"
    ],
    "wof:name":"Chick-fil-A",
    "wof:placetype":"venue"
},
  "geometry": {"coordinates":[-81.555262,30.318067],"type":"Point"}
}