{
  "type": "Feature",
  "properties": {
    "addr:full":"1214 Soltman Ave Fort Pierce FL 34950",
    "addr:housenumber":"1214",
    "addr:postcode":"34950",
    "addr:street":"Soltman Ave",
    "iso:country":"US",
    "sg:address":"1214 Soltman Ave",
    "sg:city":"Fort Pierce",
    "sg:classifiers":[
        {
            "category":"Building & Trades",
            "subcategory":"Construction",
            "type":"Services"
        }
    ],
    "sg:phone":"+1 772 464 7951",
    "sg:postcode":"34950",
    "sg:province":"FL",
    "sg:tags":[
        "house"
    ],
    "wof:name":"Scott E Waters",
    "wof:placetype":"venue"
},
  "geometry": {"coordinates":[-80.345889,27.435297],"type":"Point"}
}