{
  "type": "Feature",
  "properties": {
    "addr:full":"5815 SW 68th St South Miami FL 33143",
    "addr:housenumber":"5815",
    "addr:postcode":"33143",
    "addr:street":"Sw 68Th St",
    "iso:country":"US",
    "sg:address":"5815 SW 68th St",
    "sg:city":"South Miami",
    "sg:classifiers":[
        {
            "category":"Professional",
            "subcategory":"Computer Services",
            "type":"Services"
        }
    ],
    "sg:phone":"+1 305 669 6049",
    "sg:postcode":"33143",
    "sg:province":"FL",
    "sg:tags":[
        "repair"
    ],
    "sg:website":"www.preemo.com",
    "wof:name":"Preemo Computer Repair",
    "wof:placetype":"venue"
},
  "geometry": {"coordinates":[-80.287786,25.707988],"type":"Point"}
}