{
  "type": "Feature",
  "properties": {
    "addr:full":"5995 SW 71st St South Miami FL 33143",
    "addr:housenumber":"5995",
    "addr:postcode":"33143",
    "addr:street":"Sw 71St St",
    "iso:country":"US",
    "sg:address":"5995 SW 71st St",
    "sg:city":"South Miami",
    "sg:classifiers":[
        {
            "category":"Health Services",
            "subcategory":"Clinic",
            "type":"Services"
        }
    ],
    "sg:phone":"+1 305 661 0088",
    "sg:postcode":"33143",
    "sg:province":"FL",
    "wof:name":"South Miami Health Clinic",
    "wof:placetype":"venue"
},
  "geometry": {"coordinates":[-80.291093,25.705173],"type":"Point"}
}