{
  "type": "Feature",
  "properties": {
    "iso:country":"US",
    "sg:address":"600 Oak St",
    "sg:city":"Port Orange",
    "sg:classifiers":[
        {
            "category":"Retail",
            "subcategory":"Auto Repair",
            "type":"Services"
        }
    ],
    "sg:phone":"+1 386 322 3909",
    "sg:postcode":"32127",
    "sg:province":"FL",
    "sg:tags":[
        "scooter",
        "motorcycle",
        "motor"
    ],
    "wof:name":"Briteside Metal Polishsing",
    "wof:placetype":"venue"
},
  "geometry": {"coordinates":[-80.991056,29.136599],"type":"Point"}
}