{
  "type": "Feature",
  "properties": {
    "iso:country":"US",
    "sg:address":"110 S Federal Hwy",
    "sg:city":"Pompano Beach",
    "sg:classifiers":[
        {
            "category":"Retail",
            "subcategory":"Auto Repair",
            "type":"Services"
        }
    ],
    "sg:phone":"+1 954 786 0359",
    "sg:postcode":"33062",
    "sg:province":"FL",
    "sg:tags":[
        "automobile",
        "tinting"
    ],
    "wof:name":"TLC Auto Salon",
    "wof:placetype":"venue"
},
  "geometry": {"coordinates":[-80.102782,26.231051],"type":"Point"}
}