{
  "type": "Feature",
  "properties": {
    "iso:country":"US",
    "sg:address":"802 Ingraham Ave",
    "sg:city":"Haines City",
    "sg:classifiers":[
        {
            "category":"Local Transit",
            "type":"Transportation"
        }
    ],
    "sg:phone":"+1 863 422 6245",
    "sg:postcode":"33844",
    "sg:province":"FL",
    "sg:tags":[
        "operator",
        "bus",
        "line",
        "trucking"
    ],
    "wof:name":"Greyhound Bus Lines",
    "wof:placetype":"venue"
},
  "geometry": {"coordinates":[-81.624168,28.109677],"type":"Point"}
}