{
  "type": "Feature",
  "properties": {
    "iso:country":"US",
    "sg:address":"1023 S 50th St",
    "sg:city":"Tampa",
    "sg:classifiers":[
        {
            "category":"Wholesale",
            "subcategory":"Hardware",
            "type":"Manufacturing & Wholesale Goods"
        },
        {
            "category":"Building & Trades",
            "subcategory":"Equipment Rental",
            "type":"Services"
        },
        {
            "category":"Home & Garden",
            "subcategory":"Hardware",
            "type":"Retail Goods"
        }
    ],
    "sg:phone":"+1 813 248 4971",
    "sg:postcode":"33619",
    "sg:province":"FL",
    "sg:tags":[
        "contractor",
        "hardware-builders",
        "store",
        "supply"
    ],
    "wof:name":"GS Equipment",
    "wof:placetype":"venue"
},
  "geometry": {"coordinates":[-82.401916,27.937551],"type":"Point"}
}