{
  "type": "Feature",
  "properties": {
    "addr:full":"860 1st Ave N Naples FL 34102",
    "addr:housenumber":"860",
    "addr:postcode":"34102",
    "addr:street":"1St Ave N",
    "iso:country":"US",
    "sg:address":"860 1st Ave N",
    "sg:city":"Naples",
    "sg:classifiers":[
        {
            "category":"Health Services",
            "subcategory":"Doctor",
            "type":"Services"
        }
    ],
    "sg:phone":"+1 239 590 4299",
    "sg:postcode":"34102",
    "sg:province":"FL",
    "sg:tags":[
        "medical"
    ],
    "wof:name":"Ross Chris Rosioru MD",
    "wof:placetype":"venue"
},
  "geometry": {"coordinates":[-81.79647,26.148317],"type":"Point"}
}