{
  "type": "Feature",
  "properties": {
    "iso:country":"US",
    "sg:address":"775 8th St",
    "sg:city":"Vero Beach",
    "sg:classifiers":[
        {
            "category":"Home & Garden",
            "subcategory":"Carpets & Floor Coverings",
            "type":"Retail Goods"
        }
    ],
    "sg:phone":"+1 772 778 4977",
    "sg:postcode":"32962",
    "sg:province":"FL",
    "wof:name":"Curren Carpet",
    "wof:placetype":"venue"
},
  "geometry": {"coordinates":[-80.38756600000001,27.615984],"type":"Point"}
}