{
  "type": "Feature",
  "properties": {
    "addr:full":"5680 Suncreek Ct Orlando FL 32839",
    "addr:housenumber":"5680",
    "addr:postcode":"32839",
    "addr:street":"Suncreek Ct",
    "iso:country":"US",
    "sg:address":"5680 Suncreek Ct",
    "sg:city":"Orlando",
    "sg:classifiers":[
        {
            "category":"Communications",
            "subcategory":"Film & Video Production",
            "type":"Services"
        }
    ],
    "sg:phone":"+1 407 859 7084",
    "sg:postcode":"32839",
    "sg:province":"FL",
    "sg:tags":[
        "taping"
    ],
    "wof:name":"Axiom Production Videographics",
    "wof:placetype":"venue"
},
  "geometry": {"coordinates":[-81.416793,28.477268],"type":"Point"}
}