{
  "type": "Feature",
  "properties": {
    "addr:full":"16656 Warfield Hwy Indiantown FL 34956",
    "addr:housenumber":"16656",
    "addr:postcode":"34956",
    "addr:street":"Warfield Hwy",
    "iso:country":"US",
    "sg:address":"16656 Warfield Hwy",
    "sg:city":"Indiantown",
    "sg:classifiers":[
        {
            "category":"Building & Trades",
            "subcategory":"Construction",
            "type":"Services"
        }
    ],
    "sg:phone":"+1 772 597 2347",
    "sg:postcode":"34956",
    "sg:province":"FL",
    "sg:tags":[
        "general",
        "contractor"
    ],
    "wof:name":"Martinique Construction Inc",
    "wof:placetype":"venue"
},
  "geometry": {"coordinates":[-80.48128,27.030222],"type":"Point"}
}