{
  "type": "Feature",
  "properties": {
    "iso:country":"US",
    "sg:address":"304 N Scenic Hwy",
    "sg:city":"Frostproof",
    "sg:classifiers":[
        {
            "category":"Personal",
            "subcategory":"Beauty Salon",
            "type":"Services"
        }
    ],
    "sg:phone":"+1 863 635 4281",
    "sg:postcode":"33843",
    "sg:province":"FL",
    "sg:tags":[
        "cosmetologist"
    ],
    "wof:name":"Patty Pittman's Beauty Salon",
    "wof:placetype":"venue"
},
  "geometry": {"coordinates":[-81.53055999999999,27.748686],"type":"Point"}
}