{
  "type": "Feature",
  "properties": {
    "iso:country":"US",
    "sg:address":"6221 SE 113th St",
    "sg:city":"Belleview",
    "sg:classifiers":[
        {
            "category":"Organizations",
            "subcategory":"Community Association",
            "type":"Services"
        }
    ],
    "sg:phone":"+1 352 245 9378",
    "sg:postcode":"34420",
    "sg:province":"FL",
    "sg:tags":[
        "club"
    ],
    "wof:name":"General Casimer Pulaski Club",
    "wof:placetype":"venue"
},
  "geometry": {"coordinates":[-82.04691699999999,29.057902],"type":"Point"}
}