{
  "type": "Feature",
  "properties": {
    "addr:full":"516 N Old Dixie Hwy Jupiter FL 33458",
    "addr:housenumber":"516",
    "addr:postcode":"33458",
    "addr:street":"N Old Dixie Hwy",
    "iso:country":"US",
    "sg:address":"516 N Old Dixie Hwy",
    "sg:city":"Jupiter",
    "sg:classifiers":[
        {
            "category":"Retail",
            "subcategory":"Auto Repair",
            "type":"Services"
        }
    ],
    "sg:phone":"+1 561 746 0058",
    "sg:postcode":"33458",
    "sg:province":"FL",
    "sg:tags":[
        "body",
        "automobile",
        "painting",
        "repairing"
    ],
    "wof:name":"East Coast Collision Inc",
    "wof:placetype":"venue"
},
  "geometry": {"coordinates":[-80.09396599999999,26.93855],"type":"Point"}
}