{
  "type": "Feature",
  "properties": {
    "iso:country":"US",
    "sg:address":"2705 S Park Rd",
    "sg:city":"Hallandale",
    "sg:classifiers":[
        {
            "category":"Manufacturing",
            "subcategory":"Metals",
            "type":"Manufacturing & Wholesale Goods"
        }
    ],
    "sg:phone":"+1 954 963 4302",
    "sg:postcode":"33009",
    "sg:province":"FL",
    "sg:tags":[
        "metalwork",
        "architectural",
        "mfg"
    ],
    "wof:name":"Arista Fence & Railing",
    "wof:placetype":"venue"
},
  "geometry": {"coordinates":[-80.17079699999999,25.986728],"type":"Point"}
}