{
  "type": "Feature",
  "properties": {
    "iso:country":"US",
    "sg:address":"103 NE Tuscawilla Ave",
    "sg:city":"Ocala",
    "sg:classifiers":[
        {
            "category":"Place Of Worship",
            "type":"Public Place"
        }
    ],
    "sg:phone":"+1 352 671 6790",
    "sg:postcode":"34470",
    "sg:province":"FL",
    "sg:tags":[
        "church"
    ],
    "wof:name":"Potters House Of Ocala",
    "wof:placetype":"venue"
},
  "geometry": {"coordinates":[-82.13227000000001,29.188092],"type":"Point"}
}