{
  "type": "Feature",
  "properties": {
    "iso:country":"US",
    "sg:address":"6565 Collins Ave",
    "sg:city":"Miami Beach",
    "sg:classifiers":[
        {
            "category":"Real Estate",
            "subcategory":"Real Estate Services",
            "type":"Services"
        }
    ],
    "sg:phone":"+1 305 866 8855",
    "sg:postcode":"33141",
    "sg:province":"FL",
    "wof:name":"Sussman Joel B Rl Est",
    "wof:placetype":"venue"
},
  "geometry": {"coordinates":[-80.1203,25.849001],"type":"Point"}
}