{
  "type": "Feature",
  "properties": {
    "iso:country":"US",
    "sg:address":"1501 Middle Gulf Dr",
    "sg:city":"Sanibel",
    "sg:classifiers":[
        {
            "category":"Real Estate",
            "subcategory":"Real Estate Operator",
            "type":"Services"
        }
    ],
    "sg:phone":"+1 239 472 2443",
    "sg:postcode":"33957",
    "sg:province":"FL",
    "sg:tags":[
        "condominium"
    ],
    "wof:name":"Sundial West Condominium Assn",
    "wof:placetype":"venue"
},
  "geometry": {"coordinates":[-82.04963499999999,26.433992],"type":"Point"}
}