{
  "type": "Feature",
  "properties": {
    "iso:country":"US",
    "sg:address":"2236 E Co Hwy 30A",
    "sg:city":"Santa Rosa Beach",
    "sg:classifiers":[
        {
            "category":"Shopping",
            "subcategory":"Hobbies, Toys, & Games",
            "type":"Retail Goods"
        }
    ],
    "sg:phone":"+1 850 534 0345",
    "sg:postcode":"32459",
    "sg:province":"FL",
    "wof:name":"Bears At The Beach",
    "wof:placetype":"venue"
},
  "geometry": {"coordinates":[-86.137939,30.319717],"type":"Point"}
}