{
  "type": "Feature",
  "properties": {
    "iso:country":"US",
    "sg:address":"402 Centre St",
    "sg:city":"Fernandina Beach",
    "sg:classifiers":[
        {
            "category":"Shopping",
            "subcategory":"Crafts & Fabrics",
            "type":"Retail Goods"
        }
    ],
    "sg:phone":"+1 904 261 1129",
    "sg:postcode":"32034",
    "sg:province":"FL",
    "sg:tags":[
        "sewing"
    ],
    "wof:name":"Classy Needle",
    "wof:placetype":"venue"
},
  "geometry": {"coordinates":[-81.46209399999999,30.671034],"type":"Point"}
}