{
  "type": "Feature",
  "properties": {
    "addr:full":"4445 W 16th Ave Hialeah FL 33012",
    "addr:housenumber":"4445",
    "addr:postcode":"33012",
    "addr:street":"W 16Th Ave",
    "iso:country":"US",
    "sg:address":"4445 W 16th Ave",
    "sg:city":"Hialeah",
    "sg:classifiers":[
        {
            "category":"Community Center",
            "type":"Public Place"
        }
    ],
    "sg:phone":"+1 786 245 6130",
    "sg:postcode":"33012",
    "sg:province":"FL",
    "sg:tags":[
        "medical"
    ],
    "wof:name":"Custer Medical Center",
    "wof:placetype":"venue"
},
  "geometry": {"coordinates":[-80.314741,25.862831],"type":"Point"}
}