{
  "type": "Feature",
  "properties": {
    "iso:country":"US",
    "sg:address":"12155 SW 131st Ave",
    "sg:city":"Miami",
    "sg:classifiers":[
        {
            "category":"Wholesale",
            "subcategory":"Medical Equipment & Supplies",
            "type":"Manufacturing & Wholesale Goods"
        }
    ],
    "sg:phone":"+1 305 378 9795",
    "sg:postcode":"33186",
    "sg:province":"FL",
    "wof:name":"Unimed Corp",
    "wof:placetype":"venue"
},
  "geometry": {"coordinates":[-80.40640999999999,25.654188],"type":"Point"}
}