{
  "type": "Feature",
  "properties": {
    "addr:full":"8531 Bass Lake Dr New Port Richey FL 34654",
    "addr:housenumber":"8531",
    "addr:postcode":"34654",
    "addr:street":"Bass Lake Dr",
    "iso:country":"US",
    "sg:address":"8531 Bass Lake Dr",
    "sg:city":"New Port Richey",
    "sg:classifiers":[
        {
            "category":"Building & Trades",
            "subcategory":"Construction",
            "type":"Services"
        }
    ],
    "sg:phone":"+1 727 842 4079",
    "sg:postcode":"34654",
    "sg:province":"FL",
    "sg:tags":[
        "contractor"
    ],
    "wof:name":"Timothy Hollywood Lathing",
    "wof:placetype":"venue"
},
  "geometry": {"coordinates":[-82.665572,28.280659],"type":"Point"}
}