{
  "type": "Feature",
  "properties": {
    "iso:country":"US",
    "sg:address":"2000 Principal Ln",
    "sg:city":"Fort Walton Bch",
    "sg:classifiers":[
        {
            "category":"Social Services",
            "subcategory":"Job Training",
            "type":"Services"
        }
    ],
    "sg:phone":"+1 850 862 1859",
    "sg:postcode":"32547",
    "sg:province":"FL",
    "sg:tags":[
        "rehabilitation"
    ],
    "wof:name":"Alliance Care",
    "wof:placetype":"venue"
},
  "geometry": {"coordinates":[-86.63151000000001,30.451306],"type":"Point"}
}