{
  "type": "Feature",
  "properties": {
    "addr:full":"7881 Deni Dr Fort Myers FL 33917",
    "addr:housenumber":"7881",
    "addr:postcode":"33917",
    "addr:street":"Deni Dr",
    "iso:country":"US",
    "sg:address":"7881 Deni Dr",
    "sg:city":"Fort Myers",
    "sg:classifiers":[
        {
            "category":"Professional",
            "subcategory":"Engineering",
            "type":"Services"
        }
    ],
    "sg:phone":"+1 678 428 7836",
    "sg:postcode":"33917",
    "sg:province":"FL",
    "wof:name":"Stevens Technical Services",
    "wof:placetype":"venue"
},
  "geometry": {"coordinates":[-81.82674299999999,26.70607],"type":"Point"}
}