{
  "type": "Feature",
  "properties": {
    "iso:country":"US",
    "sg:address":"6925 112th Cir N",
    "sg:city":"Largo",
    "sg:classifiers":[
        {
            "category":"Organizations",
            "subcategory":"Non-profit Organization",
            "type":"Services"
        }
    ],
    "sg:phone":"+1 727 544 4433",
    "sg:postcode":"33773",
    "sg:province":"FL",
    "sg:tags":[
        "social"
    ],
    "wof:name":"Watson Center For The Blind",
    "wof:placetype":"venue"
},
  "geometry": {"coordinates":[-82.73430999999999,27.874132],"type":"Point"}
}