{
  "type": "Feature",
  "properties": {
    "addr:full":"2477 N John Young Pkwy Orlando FL 32804",
    "addr:housenumber":"2477",
    "addr:postcode":"32804",
    "addr:street":"N John Young Pkwy",
    "iso:country":"US",
    "sg:address":"2477 N John Young Pkwy",
    "sg:city":"Orlando",
    "sg:classifiers":[
        {
            "category":"Retail",
            "subcategory":"Auto Repair",
            "type":"Services"
        }
    ],
    "sg:phone":"+1 407 880 1001",
    "sg:postcode":"32804",
    "sg:province":"FL",
    "sg:tags":[
        "glass",
        "coating",
        "tinting"
    ],
    "sg:website":"www.tintbymasters.com",
    "wof:name":"Tint By Masters",
    "wof:placetype":"venue"
},
  "geometry": {"coordinates":[-81.415944,28.572466],"type":"Point"}
}