{
  "type": "Feature",
  "properties": {
    "addr:full":"325 Ocean Dr Miami Beach FL 33139",
    "addr:housenumber":"325",
    "addr:postcode":"33139",
    "addr:street":"Ocean Dr",
    "iso:country":"US",
    "sg:address":"325 Ocean Dr",
    "sg:city":"Miami Beach",
    "sg:classifiers":[
        {
            "category":"Professional",
            "subcategory":"Management & Consulting",
            "type":"Services"
        }
    ],
    "sg:phone":"+1 305 672 1395",
    "sg:postcode":"33139",
    "sg:province":"FL",
    "sg:tags":[
        "marketing",
        "program"
    ],
    "wof:name":"South Beach Divas Inc",
    "wof:placetype":"venue"
},
  "geometry": {"coordinates":[-80.13222500000001,25.772953],"type":"Point"}
}