{
  "type": "Feature",
  "properties": {
    "iso:country":"US",
    "sg:address":"2051 Indian Rd",
    "sg:city":"West Palm Beach",
    "sg:classifiers":[
        {
            "category":"Retail",
            "subcategory":"Auto Repair",
            "type":"Services"
        }
    ],
    "sg:phone":"+1 561 684 2828",
    "sg:postcode":"33409",
    "sg:province":"FL",
    "sg:tags":[
        "repairing",
        "automobile"
    ],
    "wof:name":"B & K's Svc Ctr",
    "wof:placetype":"venue"
},
  "geometry": {"coordinates":[-80.10427,26.709145],"type":"Point"}
}