{
  "type": "Feature",
  "properties": {
    "iso:country":"US",
    "sg:address":"729 W Church St",
    "sg:city":"Orlando",
    "sg:classifiers":[
        {
            "category":"Professional",
            "subcategory":"Advertising",
            "type":"Services"
        }
    ],
    "sg:phone":"+1 407 849 0077",
    "sg:postcode":"32805",
    "sg:province":"FL",
    "sg:tags":[
        "distribution"
    ],
    "wof:name":"S & G Warehouse Distributors",
    "wof:placetype":"venue"
},
  "geometry": {"coordinates":[-81.389454,28.540214],"type":"Point"}
}