{
  "type": "Feature",
  "properties": {
    "addr:full":"2505 State Hwy 60 Valrico FL 33594",
    "addr:housenumber":"2505",
    "addr:postcode":"33594",
    "addr:street":"State Hwy 60",
    "iso:country":"US",
    "sg:address":"2505 State Hwy 60",
    "sg:city":"Valrico",
    "sg:classifiers":[
        {
            "category":"Real Estate",
            "subcategory":"Real Estate Agent",
            "type":"Services"
        }
    ],
    "sg:phone":"+1 813 685 2961",
    "sg:postcode":"33594",
    "sg:province":"FL",
    "sg:tags":[
        "business"
    ],
    "wof:name":"Appraisal Services of Brandon",
    "wof:placetype":"venue"
},
  "geometry": {"coordinates":[-82.241038,27.937808],"type":"Point"}
}