{
  "type": "Feature",
  "properties": {
    "iso:country":"US",
    "sg:address":"2020 Tally Rd",
    "sg:city":"Leesburg",
    "sg:classifiers":[
        {
            "category":"Government",
            "subcategory":"Office",
            "type":"Public Place"
        }
    ],
    "sg:phone":"+1 352 360 6598",
    "sg:postcode":"34748",
    "sg:province":"FL",
    "wof:name":"Children & Families Dept",
    "wof:placetype":"venue"
},
  "geometry": {"coordinates":[-81.893747,28.835956],"type":"Point"}
}