{
  "type": "Feature",
  "properties": {
    "iso:country":"US",
    "sg:address":"10450 SW 157th Ct",
    "sg:city":"Miami",
    "sg:classifiers":[
        {
            "category":"Professional",
            "type":"Services"
        }
    ],
    "sg:phone":"+1 305 385 2519",
    "sg:postcode":"33196",
    "sg:province":"FL",
    "wof:name":"Velocity Systems",
    "wof:placetype":"venue"
},
  "geometry": {"coordinates":[-80.449766,25.668696],"type":"Point"}
}