{
  "type": "Feature",
  "properties": {
    "iso:country":"US",
    "sg:address":"16 Wedgewood Ln",
    "sg:city":"Palm Coast",
    "sg:classifiers":[
        {
            "category":"Professional",
            "subcategory":"Detective & Security Services",
            "type":"Services"
        }
    ],
    "sg:phone":"+1 386 445 3285",
    "sg:postcode":"32164",
    "sg:province":"FL",
    "wof:name":"Memory & Smith Assoc",
    "wof:placetype":"venue"
},
  "geometry": {"coordinates":[-81.242818,29.545751],"type":"Point"}
}