{
  "type": "Feature",
  "properties": {
    "iso:country":"US",
    "sg:address":"17307 Gulf Blvd",
    "sg:city":"Saint Petersburg",
    "sg:classifiers":[
        {
            "category":"Restaurant",
            "type":"Food & Drink"
        }
    ],
    "sg:menulink":"http://www.allmenus.com/fl/boca-ciega/37145-the-wine-cellar/menu/",
    "sg:phone":"+1 727 393 3491",
    "sg:postcode":"33708",
    "sg:province":"FL",
    "sg:tags":[
        "mediterranean"
    ],
    "wof:name":"The Wine Cellar",
    "wof:placetype":"venue"
},
  "geometry": {"coordinates":[-82.82683,27.822003],"type":"Point"}
}