{
  "type": "Feature",
  "properties": {
    "addr:full":"5927 NE 5th Ave Miami FL 33137",
    "addr:housenumber":"5927",
    "addr:postcode":"33137",
    "addr:street":"Ne 5Th Ave",
    "iso:country":"US",
    "sg:address":"5927 NE 5th Ave",
    "sg:city":"Miami",
    "sg:classifiers":[
        {
            "category":"Building & Trades",
            "subcategory":"Landscaping Services",
            "type":"Services"
        }
    ],
    "sg:phone":"+1 305 620 1042",
    "sg:postcode":"33137",
    "sg:province":"FL",
    "sg:tags":[
        "lawn",
        "maintenance",
        "grounds"
    ],
    "wof:name":"T & E Brothers Lawn Inc",
    "wof:placetype":"venue"
},
  "geometry": {"coordinates":[-80.18588699999999,25.83122],"type":"Point"}
}