{
  "type": "Feature",
  "properties": {
    "addr:full":"7110 E 14th Ave Tampa FL 33619",
    "addr:housenumber":"7110",
    "addr:postcode":"33619",
    "addr:street":"E 14Th Ave",
    "iso:country":"US",
    "sg:address":"7110 E 14th Ave",
    "sg:city":"Tampa",
    "sg:classifiers":[
        {
            "category":"Professional",
            "subcategory":"Business Services",
            "type":"Services"
        }
    ],
    "sg:phone":"+1 813 627 0303",
    "sg:postcode":"33619",
    "sg:province":"FL",
    "sg:tags":[
        "repossessing"
    ],
    "sg:website":"www.nighthawkrecovery.net",
    "wof:name":"Nighthawk",
    "wof:placetype":"venue"
},
  "geometry": {"coordinates":[-82.3738,27.965034],"type":"Point"}
}