{
  "type": "Feature",
  "properties": {
    "addr:full":"6247 Beach Blvd Jacksonville FL 32216",
    "addr:housenumber":"6247",
    "addr:postcode":"32216",
    "addr:street":"Beach Blvd",
    "iso:country":"US",
    "sg:address":"6247 Beach Blvd",
    "sg:city":"Jacksonville",
    "sg:classifiers":[
        {
            "category":"Wholesale",
            "subcategory":"Machinery & Supplies",
            "type":"Manufacturing & Wholesale Goods"
        }
    ],
    "sg:phone":"+1 904 724 6922",
    "sg:postcode":"32216",
    "sg:province":"FL",
    "sg:tags":[
        "equipment",
        "laundry"
    ],
    "wof:name":"Stan Dunn Laundry Equipment",
    "wof:placetype":"venue"
},
  "geometry": {"coordinates":[-81.59900399999999,30.291745],"type":"Point"}
}