{
  "type": "Feature",
  "properties": {
    "addr:full":"217 N Westmonte Dr Altamonte Spgs FL 32714",
    "addr:housenumber":"217",
    "addr:postcode":"32714",
    "addr:street":"N Westmonte Dr Altamonte Spgs",
    "iso:country":"US",
    "sg:address":"217 N Westmonte Dr",
    "sg:city":"Altamonte Spgs",
    "sg:classifiers":[
        {
            "category":"Building & Trades",
            "subcategory":"Construction",
            "type":"Services"
        }
    ],
    "sg:phone":"+1 407 339 7050",
    "sg:postcode":"32714",
    "sg:province":"FL",
    "sg:tags":[
        "home",
        "builder"
    ],
    "wof:name":"Reed Contractors",
    "wof:placetype":"venue"
},
  "geometry": {"coordinates":[-81.39349799999999,28.663152],"type":"Point"}
}