{
  "type": "Feature",
  "properties": {
    "addr:full":"5240 N Atlantic Ave Cocoa Beach FL 32931",
    "addr:housenumber":"5240",
    "addr:postcode":"32931",
    "addr:street":"N Atlantic Ave",
    "iso:country":"US",
    "sg:address":"5240 N Atlantic Ave",
    "sg:city":"Cocoa Beach",
    "sg:classifiers":[
        {
            "category":"Professional",
            "type":"Services"
        }
    ],
    "sg:phone":"+1 321 783 1805",
    "sg:postcode":"32931",
    "sg:province":"FL",
    "sg:tags":[
        "establishment"
    ],
    "wof:name":"Cocoa Beach Pier Commissary",
    "wof:placetype":"venue"
},
  "geometry": {"coordinates":[-80.606977,28.365261],"type":"Point"}
}