{
  "type": "Feature",
  "properties": {
    "iso:country":"US",
    "sg:address":"4140 US Hwy 19",
    "sg:city":"New Port Richey",
    "sg:classifiers":[
        {
            "category":"Real Estate",
            "subcategory":"Real Estate Agent",
            "type":"Services"
        }
    ],
    "sg:phone":"+1 727 849 6507",
    "sg:postcode":"34652",
    "sg:province":"FL",
    "sg:tags":[
        "broker"
    ],
    "wof:name":"Davis Clarke Realtors Inc",
    "wof:placetype":"venue"
},
  "geometry": {"coordinates":[-82.73672000000001,28.217921],"type":"Point"}
}