{
  "type": "Feature",
  "properties": {
    "iso:country":"US",
    "sg:address":"6090 NW 186th St",
    "sg:city":"Hialeah",
    "sg:classifiers":[
        {
            "category":"Freight",
            "type":"Transportation"
        }
    ],
    "sg:phone":"+1 305 620 0232",
    "sg:postcode":"33015",
    "sg:province":"FL",
    "sg:tags":[
        "courier"
    ],
    "wof:name":"MBP Courier Cargo Svc",
    "wof:placetype":"venue"
},
  "geometry": {"coordinates":[-80.298716,25.942352],"type":"Point"}
}