{
  "type": "Feature",
  "properties": {
    "addr:full":"6801 Gulfport Blvd S Saint Petersburg FL 33707",
    "addr:housenumber":"6801",
    "addr:postcode":"33707",
    "addr:street":"Gulfport Blvd S",
    "iso:country":"US",
    "sg:address":"6801 Gulfport Blvd S",
    "sg:city":"Saint Petersburg",
    "sg:classifiers":[
        {
            "category":"Health Services",
            "subcategory":"Doctor",
            "type":"Services"
        }
    ],
    "sg:phone":"+1 727 347 2273",
    "sg:postcode":"33707",
    "sg:province":"FL",
    "sg:tags":[
        "medical"
    ],
    "wof:name":"Medic Care Walk In Clinic",
    "wof:placetype":"venue"
},
  "geometry": {"coordinates":[-82.73605999999999,27.759259],"type":"Point"}
}