{
  "type": "Feature",
  "properties": {
    "iso:country":"US",
    "sg:address":"2465 Royal Rd",
    "sg:city":"Deland",
    "sg:classifiers":[
        {
            "category":"Building & Trades",
            "subcategory":"Construction",
            "type":"Services"
        }
    ],
    "sg:phone":"+1 386 734 8385",
    "sg:postcode":"32724",
    "sg:province":"FL",
    "sg:tags":[
        "downspouts",
        "gutter"
    ],
    "wof:name":"Don Beer Seemless Gutters",
    "wof:placetype":"venue"
},
  "geometry": {"coordinates":[-81.29246999999999,28.98682],"type":"Point"}
}