{
  "type": "Feature",
  "properties": {
    "iso:country":"US",
    "sg:address":"2311 S 35th St",
    "sg:city":"Fort Pierce",
    "sg:classifiers":[
        {
            "category":"Restaurant",
            "type":"Food & Drink"
        }
    ],
    "sg:menulink":"http://www.allmenus.com/fl/fort-pierce/38580-big-apple-pizza/menu/",
    "sg:phone":"+1 772 466 8303",
    "sg:postcode":"34981",
    "sg:province":"FL",
    "sg:tags":[
        "american",
        "pizza"
    ],
    "wof:name":"Big Apple Pizza",
    "wof:placetype":"venue"
},
  "geometry": {"coordinates":[-80.360497,27.425251],"type":"Point"}
}