{
  "type": "Feature",
  "properties": {
    "iso:country":"US",
    "sg:address":"8955 SW 87th Ct",
    "sg:city":"Miami",
    "sg:classifiers":[
        {
            "category":"Health Services",
            "subcategory":"Doctor",
            "type":"Services"
        }
    ],
    "sg:phone":"+1 305 596 4440",
    "sg:postcode":"33176",
    "sg:province":"FL",
    "sg:tags":[
        "physician",
        "surgeon",
        "medical"
    ],
    "wof:name":"Luis R Pardon MD",
    "wof:placetype":"venue"
},
  "geometry": {"coordinates":[-80.335455,25.685336],"type":"Point"}
}