{
  "type": "Feature",
  "properties": {
    "addr:full":"3 SW 129th Ave Hollywood FL 33027",
    "addr:housenumber":"3",
    "addr:postcode":"33027",
    "addr:street":"Sw 129Th Ave",
    "iso:country":"US",
    "sg:address":"3 SW 129th Ave",
    "sg:city":"Hollywood",
    "sg:classifiers":[
        {
            "category":"Health Services",
            "subcategory":"Doctor",
            "type":"Services"
        }
    ],
    "sg:phone":"+1 954 450 6447",
    "sg:postcode":"33027",
    "sg:province":"FL",
    "wof:name":"Jose Dominguez",
    "wof:placetype":"venue"
},
  "geometry": {"coordinates":[-80.320318,26.007845],"type":"Point"}
}