{
  "type": "Feature",
  "properties": {
    "iso:country":"US",
    "sg:address":"4013 Broadway",
    "sg:city":"West Palm Beach",
    "sg:classifiers":[
        {
            "category":"Restaurant",
            "type":"Food & Drink"
        }
    ],
    "sg:phone":"+1 561 840 7991",
    "sg:postcode":"33407",
    "sg:province":"FL",
    "sg:tags":[
        "eating"
    ],
    "wof:name":"Magalie International Rest",
    "wof:placetype":"venue"
},
  "geometry": {"coordinates":[-80.056605,26.748789],"type":"Point"}
}