{
  "type": "Feature",
  "properties": {
    "iso:country":"US",
    "sg:address":"5039 Central Avenue St. Petersburg",
    "sg:classifiers":[
        {
            "category":"Professional",
            "subcategory":"Computer Services",
            "type":"Services"
        }
    ],
    "sg:phone":"+1 941 727 9040",
    "sg:postcode":"337108240",
    "sg:province":"FL",
    "sg:tags":[
        "sourcing",
        "industrial-products",
        "procurement"
    ],
    "sg:website":"http://www.streamline-alliance.com",
    "wof:name":"Streamline Alliance",
    "wof:placetype":"venue"
},
  "geometry": {"coordinates":[-74.629615,39.229932],"type":"Point"}
}