{
  "type": "Feature",
  "properties": {
    "addr:full":"1802 Oglesby Ave Winter Park FL 32789",
    "addr:housenumber":"1802",
    "addr:postcode":"32789",
    "addr:street":"Oglesby Ave",
    "iso:country":"US",
    "sg:address":"1802 Oglesby Ave",
    "sg:city":"Winter Park",
    "sg:classifiers":[
        {
            "category":"Shopping",
            "subcategory":"Used Merchandise",
            "type":"Retail Goods"
        }
    ],
    "sg:phone":"+1 321 972 1811",
    "sg:postcode":"32789",
    "sg:province":"FL",
    "sg:tags":[
        "vintage",
        "consignment"
    ],
    "wof:name":"Selective Designs",
    "wof:placetype":"venue"
},
  "geometry": {"coordinates":[-81.37430500000001,28.591294],"type":"Point"}
}