{
  "type": "Feature",
  "properties": {
    "addr:full":"532 Fuller Ave Deltona FL 32725",
    "addr:housenumber":"532",
    "addr:postcode":"32725",
    "addr:street":"Fuller Ave",
    "iso:country":"US",
    "sg:address":"532 Fuller Ave",
    "sg:city":"Deltona",
    "sg:classifiers":[
        {
            "category":"Building & Trades",
            "subcategory":"Electrical",
            "type":"Services"
        }
    ],
    "sg:phone":"+1 386 453 5044",
    "sg:postcode":"32725",
    "sg:province":"FL",
    "sg:tags":[
        "electrical",
        "contractor"
    ],
    "wof:name":"Lorenzo Arzon",
    "wof:placetype":"venue"
},
  "geometry": {"coordinates":[-81.246084,28.877819],"type":"Point"}
}