{
  "type": "Feature",
  "properties": {
    "addr:full":"7123 N US Hwy 441 Ocala FL 34475",
    "addr:housenumber":"7123",
    "addr:postcode":"34475",
    "addr:street":"N Us Hwy 441",
    "iso:country":"US",
    "sg:address":"7123 N US Hwy 441",
    "sg:city":"Ocala",
    "sg:classifiers":[
        {
            "category":"Restaurant",
            "type":"Food & Drink"
        }
    ],
    "sg:phone":"+1 352 369 3926",
    "sg:postcode":"34475",
    "sg:province":"FL",
    "wof:name":"China Wall",
    "wof:placetype":"venue"
},
  "geometry": {"coordinates":[-82.15192399999999,29.264211],"type":"Point"}
}