{
  "type": "Feature",
  "properties": {
    "iso:country":"US",
    "sg:address":"12020 6th St E",
    "sg:city":"Saint Petersburg",
    "sg:classifiers":[
        {
            "category":"Building & Trades",
            "subcategory":"Construction",
            "type":"Services"
        }
    ],
    "sg:phone":"+1 727 395 0100",
    "sg:postcode":"33706",
    "sg:province":"FL",
    "sg:tags":[
        "maine"
    ],
    "wof:name":"Buccaneer Docks Inc",
    "wof:placetype":"venue"
},
  "geometry": {"coordinates":[-82.767606,27.780098],"type":"Point"}
}