{
  "type": "Feature",
  "properties": {
    "iso:country":"US",
    "sg:address":"11521 SW 153rd Ct",
    "sg:city":"Miami",
    "sg:classifiers":[
        {
            "category":"Banks & Credit Unions",
            "subcategory":"Financial Services",
            "type":"Services"
        }
    ],
    "sg:phone":"+1 305 752 2962",
    "sg:postcode":"33196",
    "sg:province":"FL",
    "sg:tags":[
        "investor"
    ],
    "wof:name":"Fhm Investments Inc",
    "wof:placetype":"venue"
},
  "geometry": {"coordinates":[-80.443247,25.659573],"type":"Point"}
}