{
  "type": "Feature",
  "properties": {
    "iso:country":"US",
    "sg:address":"3 W Lemon St",
    "sg:city":"Beverly Hills",
    "sg:classifiers":[
        {
            "category":"Real Estate",
            "subcategory":"Real Estate Agent",
            "type":"Services"
        }
    ],
    "sg:phone":"+1 352 746 9770",
    "sg:postcode":"34465",
    "sg:province":"FL",
    "sg:tags":[
        "manager"
    ],
    "wof:name":"P&R Mid Florida Rlty Svcs Inc",
    "wof:placetype":"venue"
},
  "geometry": {"coordinates":[-82.457323,28.930357],"type":"Point"}
}