{
  "type": "Feature",
  "properties": {
    "iso:country":"US",
    "sg:address":"1905 Montmarte Dr",
    "sg:city":"Jacksonville",
    "sg:classifiers":[
        {
            "category":"Building & Trades",
            "subcategory":"Construction",
            "type":"Services"
        }
    ],
    "sg:phone":"+1 904 695 9959",
    "sg:postcode":"32210",
    "sg:province":"FL",
    "sg:tags":[
        "handyman"
    ],
    "wof:name":"Hannigans Helping Hands",
    "wof:placetype":"venue"
},
  "geometry": {"coordinates":[-81.777084,30.282657],"type":"Point"}
}