{
  "type": "Feature",
  "properties": {
    "addr:full":"3639 Cortez Rd W Bradenton FL 34210",
    "addr:housenumber":"3639",
    "addr:postcode":"34210",
    "addr:street":"Cortez Rd W",
    "iso:country":"US",
    "sg:address":"3639 Cortez Rd W",
    "sg:city":"Bradenton",
    "sg:classifiers":[
        {
            "category":"Professional",
            "subcategory":"Accounting & Tax Preparation",
            "type":"Services"
        }
    ],
    "sg:phone":"+1 941 755 5633",
    "sg:postcode":"34210",
    "sg:province":"FL",
    "sg:tags":[
        "accountant"
    ],
    "wof:name":"Jim G Germer Financial Svc",
    "wof:placetype":"venue"
},
  "geometry": {"coordinates":[-82.59912799999999,27.4623],"type":"Point"}
}