{
  "type": "Feature",
  "properties": {
    "iso:country":"US",
    "sg:address":"6710 Hartsworth Dr",
    "sg:city":"Lakeland",
    "sg:classifiers":[
        {
            "category":"Real Estate",
            "subcategory":"Real Estate Services",
            "type":"Services"
        },
        {
            "category":"Real Estate",
            "subcategory":"Real Estate Agent",
            "type":"Services"
        }
    ],
    "sg:phone":"+1 863 647 5650",
    "sg:postcode":"33813",
    "sg:province":"FL",
    "sg:tags":[
        "buyer",
        "broker"
    ],
    "wof:name":"Hartford Estates",
    "wof:placetype":"venue"
},
  "geometry": {"coordinates":[-81.90781699999999,27.944793],"type":"Point"}
}