{
  "type": "Feature",
  "properties": {
    "iso:country":"US",
    "sg:address":"4511 N Himes Avenue Suite 200",
    "sg:city":"Tampa",
    "sg:classifiers":[
        {
            "category":"Professional",
            "subcategory":"Business Services",
            "type":"Services"
        }
    ],
    "sg:phone":"+1 407 682 2222",
    "sg:postcode":"33614",
    "sg:province":"FL",
    "sg:tags":[
        "internet-marketing-internet-marketing-consulting-local-search-marketing-pay-per-click-managment-reputation-management-seo-services-seo-search-engine-optimization-search-engine-marketing-social-networking-video-seo-vseo-video-search-engine-optimization-web"
    ],
    "sg:website":"http://www.smtusa.com",
    "wof:name":"Sales & Marketing Technologies",
    "wof:placetype":"venue"
},
  "geometry": {"coordinates":[-82.501276,27.982094],"type":"Point"}
}