{
  "type": "Feature",
  "properties": {
    "iso:country":"US",
    "sg:address":"3234 S Florida Ave",
    "sg:city":"Lakeland",
    "sg:classifiers":[
        {
            "category":"Home & Garden",
            "subcategory":"Furniture",
            "type":"Retail Goods"
        }
    ],
    "sg:phone":"+1 863 647 2888",
    "sg:postcode":"33803",
    "sg:province":"FL",
    "wof:name":"Freight Sales Carpet",
    "wof:placetype":"venue"
},
  "geometry": {"coordinates":[-81.95692200000001,28.006127],"type":"Point"}
}