{
  "type": "Feature",
  "properties": {
    "iso:country":"US",
    "sg:address":"2017 Reigler Rd",
    "sg:city":"Land O Lakes",
    "sg:classifiers":[
        {
            "category":"Organizations",
            "subcategory":"Religious Organization",
            "type":"Services"
        }
    ],
    "sg:phone":"+1 813 949 5516",
    "sg:postcode":"34639",
    "sg:province":"FL",
    "sg:tags":[
        "a",
        "baptist",
        "company",
        "through",
        "holding",
        "church",
        "functioning"
    ],
    "sg:website":"www.myrtlelake.org",
    "wof:name":"Myrtle Lake Baptist Church",
    "wof:placetype":"venue"
},
  "geometry": {"coordinates":[-82.434501,28.18771],"type":"Point"}
}