{
  "type": "Feature",
  "properties": {
    "addr:full":"7106 SW 117th Ave Miami FL 33183",
    "addr:housenumber":"7106",
    "addr:postcode":"33183",
    "addr:street":"Sw 117Th Ave",
    "iso:country":"US",
    "sg:address":"7106 SW 117th Ave",
    "sg:city":"Miami",
    "sg:classifiers":[
        {
            "category":"Banks & Credit Unions",
            "subcategory":"Bank",
            "type":"Services"
        }
    ],
    "sg:phone":"+1 305 274 0009",
    "sg:postcode":"33183",
    "sg:province":"FL",
    "sg:tags":[
        "cashing",
        "check"
    ],
    "wof:name":"Check Cashing USA",
    "wof:placetype":"venue"
},
  "geometry": {"coordinates":[-80.382299,25.701903],"type":"Point"}
}