{
  "type": "Feature",
  "properties": {
    "addr:full":"8291 NW 88th Ave Tamarac FL 33321",
    "addr:housenumber":"8291",
    "addr:postcode":"33321",
    "addr:street":"Nw 88Th Ave",
    "iso:country":"US",
    "sg:address":"8291 NW 88th Ave",
    "sg:city":"Tamarac",
    "sg:classifiers":[
        {
            "category":"Health Services",
            "subcategory":"Health Practitioner",
            "type":"Services"
        },
        {
            "category":"Health Services",
            "subcategory":"Chiropractor",
            "type":"Services"
        }
    ],
    "sg:phone":"+1 954 724 9208",
    "sg:postcode":"33321",
    "sg:province":"FL",
    "sg:tags":[
        "acupuncture",
        "medicine",
        "alternative",
        "chiropractic"
    ],
    "wof:name":"Tamarac Physicians Office",
    "wof:placetype":"venue"
},
  "geometry": {"coordinates":[-80.26980399999999,26.227566],"type":"Point"}
}