{
  "type": "Feature",
  "properties": {
    "iso:country":"US",
    "sg:address":"1208 Capital Cir SE",
    "sg:city":"Tallahassee",
    "sg:classifiers":[
        {
            "category":"Food & Beverages",
            "subcategory":"Bakery",
            "type":"Retail Goods"
        }
    ],
    "sg:phone":"+1 850 942 7422",
    "sg:postcode":"32301",
    "sg:province":"FL",
    "sg:tags":[
        "baker"
    ],
    "wof:name":"Merita Bread",
    "wof:placetype":"venue"
},
  "geometry": {"coordinates":[-84.226856,30.427597],"type":"Point"}
}