{
  "type": "Feature",
  "properties": {
    "addr:full":"530 W Sample Rd Pompano Beach FL 33064",
    "addr:housenumber":"530",
    "addr:postcode":"33064",
    "addr:street":"W Sample Rd",
    "iso:country":"US",
    "sg:address":"530 W Sample Rd",
    "sg:city":"Pompano Beach",
    "sg:classifiers":[
        {
            "category":"Banks & Credit Unions",
            "subcategory":"Bank",
            "type":"Services"
        }
    ],
    "sg:phone":"+1 954 781 3378",
    "sg:postcode":"33064",
    "sg:province":"FL",
    "sg:tags":[
        "cashing",
        "check"
    ],
    "wof:name":"Check Cashing Store",
    "wof:placetype":"venue"
},
  "geometry": {"coordinates":[-80.130551,26.274885],"type":"Point"}
}