{
  "type": "Feature",
  "properties": {
    "iso:country":"US",
    "sg:address":"7021 International Dr",
    "sg:city":"Orlando",
    "sg:classifiers":[
        {
            "category":"Restaurant",
            "type":"Food & Drink"
        }
    ],
    "sg:menulink":"http://www.allmenus.com/fl/southwest-orange/29743-chilis/menu/",
    "sg:phone":"+1 407 352 7618",
    "sg:postcode":"32819",
    "sg:province":"FL",
    "sg:tags":[
        "burger",
        "american",
        "sandwich",
        "tex-mex",
        "soup"
    ],
    "wof:name":"Chili's",
    "wof:placetype":"venue"
},
  "geometry": {"coordinates":[-81.470799,28.457253],"type":"Point"}
}