{
  "type": "Feature",
  "properties": {
    "addr:full":"5586 W Flagler St Coral Gables FL 33134",
    "addr:housenumber":"5586",
    "addr:postcode":"33134",
    "addr:street":"W Flagler St",
    "iso:country":"US",
    "sg:address":"5586 W Flagler St",
    "sg:city":"Coral Gables",
    "sg:classifiers":[
        {
            "category":"Building & Trades",
            "subcategory":"Locksmith",
            "type":"Services"
        }
    ],
    "sg:phone":"+1 786 228 5676",
    "sg:postcode":"33134",
    "sg:province":"FL",
    "sg:tags":[
        "key"
    ],
    "wof:name":"Available Locksmith In Coral Gables",
    "wof:placetype":"venue"
},
  "geometry": {"coordinates":[-80.285813,25.770997],"type":"Point"}
}