{
  "type": "Feature",
  "properties": {
    "addr:full":"3495 S Orange Blossom Trl Orlando FL 32839",
    "addr:housenumber":"3495",
    "addr:postcode":"32839",
    "addr:street":"S Orange Blossom Trl",
    "iso:country":"US",
    "sg:address":"3495 S Orange Blossom Trl",
    "sg:city":"Orlando",
    "sg:classifiers":[
        {
            "category":"Autos & Motor Vehicles",
            "subcategory":"Automobile Sales",
            "type":"Retail Goods"
        }
    ],
    "sg:phone":"+1 407 236 0033",
    "sg:postcode":"32839",
    "sg:province":"FL",
    "sg:tags":[
        "car",
        "dealer"
    ],
    "wof:name":"Auto Brokers",
    "wof:placetype":"venue"
},
  "geometry": {"coordinates":[-81.39686,28.507329],"type":"Point"}
}