{
  "type": "Feature",
  "properties": {
    "addr:full":"790 Dolphin Ave Key Largo FL 33037",
    "addr:housenumber":"790",
    "addr:postcode":"33037",
    "addr:street":"Dolphin Ave",
    "iso:country":"US",
    "sg:address":"790 Dolphin Ave",
    "sg:city":"Key Largo",
    "sg:classifiers":[
        {
            "category":"Shopping",
            "subcategory":"Computers & Home Electronics",
            "type":"Retail Goods"
        }
    ],
    "sg:phone":"+1 305 451 5000",
    "sg:postcode":"33037",
    "sg:province":"FL",
    "wof:name":"Absolute Electronics",
    "wof:placetype":"venue"
},
  "geometry": {"coordinates":[-80.395336,25.139958],"type":"Point"}
}