{
  "type": "Feature",
  "properties": {
    "iso:country":"US",
    "sg:address":"2921 E Colonial Dr",
    "sg:city":"Orlando",
    "sg:classifiers":[
        {
            "category":"Military Area",
            "type":"Public Place"
        }
    ],
    "sg:phone":"+1 407 896 1588",
    "sg:postcode":"32803",
    "sg:province":"FL",
    "sg:tags":[
        "force",
        "armed",
        "recruiting"
    ],
    "wof:name":"U S Air Force Recruiting",
    "wof:placetype":"venue"
},
  "geometry": {"coordinates":[-81.346636,28.553366],"type":"Point"}
}