{
  "type": "Feature",
  "properties": {
    "iso:country":"US",
    "sg:address":"13256 SW 136th Ter",
    "sg:city":"Miami",
    "sg:classifiers":[
        {
            "category":"Wholesale",
            "subcategory":"Home Furnishings",
            "type":"Manufacturing & Wholesale Goods"
        }
    ],
    "sg:phone":"+1 305 238 9001",
    "sg:postcode":"33186",
    "sg:province":"FL",
    "sg:tags":[
        "fabrics-wholesale",
        "upholstery",
        "manufacturer"
    ],
    "wof:name":"Tmiami.Com Incorporated",
    "wof:placetype":"venue"
},
  "geometry": {"coordinates":[-80.406756,25.64073],"type":"Point"}
}