{
  "type": "Feature",
  "properties": {
    "addr:full":"2389 S Summerwood Pt Inverness FL 34450",
    "addr:housenumber":"2389",
    "addr:postcode":"34450",
    "addr:street":"S Summerwood Pt",
    "iso:country":"US",
    "sg:address":"2389 S Summerwood Pt",
    "sg:city":"Inverness",
    "sg:classifiers":[
        {
            "category":"Real Estate",
            "subcategory":"Real Estate Agent",
            "type":"Services"
        }
    ],
    "sg:phone":"+1 352 726 8868",
    "sg:postcode":"34450",
    "sg:province":"FL",
    "wof:name":"Castro Realty",
    "wof:placetype":"venue"
},
  "geometry": {"coordinates":[-82.281161,28.826304],"type":"Point"}
}