{
  "type": "Feature",
  "properties": {
    "iso:country":"US",
    "sg:address":"1957 Souvenir Dr",
    "sg:city":"Clearwater",
    "sg:classifiers":[
        {
            "category":"Health Services",
            "subcategory":"Clinic",
            "type":"Services"
        }
    ],
    "sg:phone":"+1 727 657 5397",
    "sg:postcode":"33755",
    "sg:province":"FL",
    "sg:tags":[
        "mental"
    ],
    "wof:name":"Preeminent Finishes, Inc.",
    "wof:placetype":"venue"
},
  "geometry": {"coordinates":[-82.77294999999999,27.992216],"type":"Point"}
}