{
  "type": "Feature",
  "properties": {
    "iso:country":"US",
    "sg:address":"3375 Burns Rd",
    "sg:city":"Palm Beach Gardens",
    "sg:classifiers":[
        {
            "category":"Health Services",
            "subcategory":"Doctor",
            "type":"Services"
        }
    ],
    "sg:phone":"+1 561 625 0073",
    "sg:postcode":"33410",
    "sg:province":"FL",
    "sg:tags":[
        "medical"
    ],
    "wof:name":"Essam Attia MD",
    "wof:placetype":"venue"
},
  "geometry": {"coordinates":[-80.083006,26.830553],"type":"Point"}
}