{
  "type": "Feature",
  "properties": {
    "addr:full":"3775 Felda St Cocoa FL 32926",
    "addr:housenumber":"3775",
    "addr:postcode":"32926",
    "addr:street":"Felda St",
    "iso:country":"US",
    "sg:address":"3775 Felda St",
    "sg:city":"Cocoa",
    "sg:classifiers":[
        {
            "category":"Professional",
            "subcategory":"Business Services",
            "type":"Services"
        }
    ],
    "sg:phone":"+1 321 631 4325",
    "sg:postcode":"32926",
    "sg:province":"FL",
    "sg:tags":[
        "recording",
        "studio"
    ],
    "wof:name":"SOLO Creative Media Inc",
    "wof:placetype":"venue"
},
  "geometry": {"coordinates":[-80.802385,28.420873],"type":"Point"}
}