{
  "type": "Feature",
  "properties": {
    "iso:country":"US",
    "sg:address":"4198 W 18th Ln",
    "sg:city":"Hialeah",
    "sg:classifiers":[
        {
            "category":"Wholesale",
            "subcategory":"Painting Supplies",
            "type":"Manufacturing & Wholesale Goods"
        }
    ],
    "sg:phone":"+1 305 827 9508",
    "sg:postcode":"33012",
    "sg:province":"FL",
    "sg:tags":[
        "paint-wholesale",
        "manufacturer"
    ],
    "wof:name":"Continental Paint And Body",
    "wof:placetype":"venue"
},
  "geometry": {"coordinates":[-80.319923,25.860109],"type":"Point"}
}