{
  "type": "Feature",
  "properties": {
    "iso:country":"US",
    "sg:address":"1040 E 3rd St",
    "sg:city":"Hialeah",
    "sg:classifiers":[
        {
            "category":"Professional",
            "subcategory":"Business Services",
            "type":"Services"
        }
    ],
    "sg:phone":"+1 305 882 0544",
    "sg:postcode":"33010",
    "sg:province":"FL",
    "sg:tags":[
        "cloth",
        "cutting"
    ],
    "wof:name":"Lastra Cutting Service Inc",
    "wof:placetype":"venue"
},
  "geometry": {"coordinates":[-80.26099499999999,25.825015],"type":"Point"}
}