{
  "type": "Feature",
  "properties": {
    "addr:full":"1000 W Beacon Rd Lakeland FL 33803",
    "addr:housenumber":"1000",
    "addr:postcode":"33803",
    "addr:street":"W Beacon Rd",
    "iso:country":"US",
    "sg:address":"1000 W Beacon Rd",
    "sg:city":"Lakeland",
    "sg:classifiers":[
        {
            "category":"Real Estate",
            "subcategory":"Real Estate Agent",
            "type":"Services"
        }
    ],
    "sg:phone":"+1 863 665 4900",
    "sg:postcode":"33803",
    "sg:province":"FL",
    "wof:name":"Bob Stanley Buildings-Lease",
    "wof:placetype":"venue"
},
  "geometry": {"coordinates":[-81.96718799999999,28.018607],"type":"Point"}
}