{
  "type": "Feature",
  "properties": {
    "iso:country":"US",
    "sg:address":"4021 SW 28th St",
    "sg:city":"Hollywood",
    "sg:classifiers":[
        {
            "category":"Shopping",
            "subcategory":"Clothing, Apparel, & Fashions",
            "type":"Retail Goods"
        }
    ],
    "sg:phone":"+1 954 295 2092",
    "sg:postcode":"33023",
    "sg:province":"FL",
    "sg:tags":[
        "family"
    ],
    "wof:name":"Drobe Doctor",
    "wof:placetype":"venue"
},
  "geometry": {"coordinates":[-80.18492500000001,25.985437],"type":"Point"}
}