{
  "type": "Feature",
  "properties": {
    "iso:country":"US",
    "sg:address":"1125 38th St W",
    "sg:city":"Bradenton",
    "sg:classifiers":[
        {
            "category":"Building & Trades",
            "subcategory":"Construction",
            "type":"Services"
        }
    ],
    "sg:phone":"+1 941 747 5005",
    "sg:postcode":"34205",
    "sg:province":"FL",
    "sg:tags":[
        "restoration",
        "cleaning",
        "patio",
        "deck"
    ],
    "wof:name":"Bright & White Pressure",
    "wof:placetype":"venue"
},
  "geometry": {"coordinates":[-82.59882500000001,27.488633],"type":"Point"}
}