{
  "type": "Feature",
  "properties": {
    "addr:full":"2931 W 12th Ave Hialeah FL 33012",
    "addr:housenumber":"2931",
    "addr:postcode":"33012",
    "addr:street":"W 12Th Ave",
    "iso:country":"US",
    "sg:address":"2931 W 12th Ave",
    "sg:city":"Hialeah",
    "sg:classifiers":[
        {
            "category":"Shopping",
            "subcategory":"Jewelry",
            "type":"Retail Goods"
        }
    ],
    "sg:phone":"+1 305 885 2073",
    "sg:postcode":"33012",
    "sg:province":"FL",
    "sg:tags":[
        "shop",
        "used",
        "pawn",
        "merchandise"
    ],
    "wof:name":"Yes Cash II",
    "wof:placetype":"venue"
},
  "geometry": {"coordinates":[-80.30639600000001,25.848101],"type":"Point"}
}