{
  "type": "Feature",
  "properties": {
    "iso:country":"US",
    "sg:address":"1200 E Colonial Dr",
    "sg:city":"Orlando",
    "sg:classifiers":[
        {
            "category":"Insurance",
            "subcategory":"Insurance Agent",
            "type":"Services"
        }
    ],
    "sg:phone":"+1 407 898 2454",
    "sg:postcode":"32803",
    "sg:province":"FL",
    "wof:name":"Ralph Kararian Auto Insurance",
    "wof:placetype":"venue"
},
  "geometry": {"coordinates":[-81.36267100000001,28.553136],"type":"Point"}
}