{
  "type": "Feature",
  "properties": {
    "addr:full":"5731 NW 36th St Miami FL 33166",
    "addr:housenumber":"5731",
    "addr:postcode":"33166",
    "addr:street":"Nw 36Th St",
    "iso:country":"US",
    "sg:address":"5731 NW 36th St",
    "sg:city":"Miami",
    "sg:classifiers":[
        {
            "category":"Restaurant",
            "type":"Food & Drink"
        }
    ],
    "sg:menulink":"http://www.allmenus.com/fl/miami/71302-pizza-hut/menu/",
    "sg:phone":"+1 305 871 3179",
    "sg:postcode":"33166",
    "sg:province":"FL",
    "sg:tags":[
        "american",
        "pizza"
    ],
    "wof:name":"Pizza Hut",
    "wof:placetype":"venue"
},
  "geometry": {"coordinates":[-80.29101199999999,25.807889],"type":"Point"}
}