{
  "type": "Feature",
  "properties": {
    "iso:country":"US",
    "sg:address":"201 W Cypress St",
    "sg:city":"Kissimmee",
    "sg:classifiers":[
        {
            "category":"Professional",
            "subcategory":"Business Services",
            "type":"Services"
        }
    ],
    "sg:phone":"+1 407 870 2505",
    "sg:postcode":"34741",
    "sg:province":"FL",
    "sg:tags":[
        "embroidery"
    ],
    "wof:name":"Embroidery Gift USA Inc",
    "wof:placetype":"venue"
},
  "geometry": {"coordinates":[-81.404972,28.305796],"type":"Point"}
}