{
  "type": "Feature",
  "properties": {
    "iso:country":"US",
    "sg:address":"200 Congress Park Dr",
    "sg:city":"Delray Beach",
    "sg:classifiers":[
        {
            "category":"Banks & Credit Unions",
            "subcategory":"Investment Brokerage",
            "type":"Services"
        }
    ],
    "sg:phone":"+1 561 276 4606",
    "sg:postcode":"33445",
    "sg:province":"FL",
    "sg:tags":[
        "advisory",
        "financial"
    ],
    "wof:name":"Freedom Financial Solutions",
    "wof:placetype":"venue"
},
  "geometry": {"coordinates":[-80.09585800000001,26.456856],"type":"Point"}
}