{
  "type": "Feature",
  "properties": {
    "iso:country":"US",
    "sg:address":"3225 SW 106th Ave",
    "sg:city":"Miami",
    "sg:classifiers":[
        {
            "category":"Manufacturing",
            "subcategory":"Signs",
            "type":"Manufacturing & Wholesale Goods"
        }
    ],
    "sg:phone":"+1 305 554 7377",
    "sg:postcode":"33165",
    "sg:province":"FL",
    "sg:tags":[
        "specialty",
        "mfg"
    ],
    "wof:name":"Fiuza Signs",
    "wof:placetype":"venue"
},
  "geometry": {"coordinates":[-80.366844,25.738005],"type":"Point"}
}