{
  "type": "Feature",
  "properties": {
    "iso:country":"US",
    "sg:address":"210 Forest Hill Dr",
    "sg:city":"Cocoa",
    "sg:classifiers":[
        {
            "category":"Building & Trades",
            "subcategory":"Landscaping Services",
            "type":"Services"
        }
    ],
    "sg:phone":"+1 321 504 6300",
    "sg:postcode":"32926",
    "sg:province":"FL",
    "sg:tags":[
        "lawn",
        "maintenance",
        "grounds"
    ],
    "wof:name":"Joseph Ambrose Acres Lawncare",
    "wof:placetype":"venue"
},
  "geometry": {"coordinates":[-80.749109,28.403905],"type":"Point"}
}