{
  "type": "Feature",
  "properties": {
    "iso:country":"US",
    "sg:address":"3714 SE 3rd Ave",
    "sg:city":"Cape Coral",
    "sg:classifiers":[
        {
            "category":"Retail",
            "subcategory":"Repair Shop",
            "type":"Services"
        }
    ],
    "sg:phone":"+1 239 549 8744",
    "sg:postcode":"33904",
    "sg:province":"FL",
    "sg:tags":[
        "electrical"
    ],
    "wof:name":"Chucks TV Servicce",
    "wof:placetype":"venue"
},
  "geometry": {"coordinates":[-81.966765,26.579434],"type":"Point"}
}