{
  "type": "Feature",
  "properties": {
    "iso:country":"US",
    "sg:address":"15921 Shady Hills Rd",
    "sg:city":"Brooksville",
    "sg:classifiers":[
        {
            "category":"Building & Trades",
            "subcategory":"Construction",
            "type":"Services"
        }
    ],
    "sg:phone":"+1 727 856 0258",
    "sg:postcode":"34610",
    "sg:province":"FL",
    "sg:tags":[
        "clearing",
        "land",
        "leveling"
    ],
    "wof:name":"Fortner Tractor Svc",
    "wof:placetype":"venue"
},
  "geometry": {"coordinates":[-82.551215,28.388573],"type":"Point"}
}