{
  "type": "Feature",
  "properties": {
    "iso:country":"US",
    "sg:address":"2145 Lincoln Ave",
    "sg:city":"Opa Locka",
    "sg:classifiers":[
        {
            "category":"Food & Beverages",
            "subcategory":"Groceries & Convenience Stores",
            "type":"Retail Goods"
        }
    ],
    "sg:phone":"+1 305 769 0860",
    "sg:postcode":"33054",
    "sg:province":"FL",
    "sg:tags":[
        "grocer"
    ],
    "wof:name":"Imperial Supermarket",
    "wof:placetype":"venue"
},
  "geometry": {"coordinates":[-80.235558,25.910787],"type":"Point"}
}