{
  "type": "Feature",
  "properties": {
    "iso:country":"US",
    "sg:address":"2447 57th St",
    "sg:city":"Sarasota",
    "sg:classifiers":[
        {
            "category":"Professional",
            "subcategory":"Management & Consulting",
            "type":"Services"
        }
    ],
    "sg:phone":"+1 941 360 8200",
    "sg:postcode":"34243",
    "sg:province":"FL",
    "sg:tags":[
        "advisory",
        "financial"
    ],
    "wof:name":"Chiusano & Company",
    "wof:placetype":"venue"
},
  "geometry": {"coordinates":[-82.514757,27.383529],"type":"Point"}
}