{
  "type": "Feature",
  "properties": {
    "addr:full":"4410 Broadway West Palm Beach FL 33407",
    "addr:housenumber":"4410",
    "addr:postcode":"33407",
    "addr:street":"Broadway",
    "iso:country":"US",
    "sg:address":"4410 Broadway",
    "sg:city":"West Palm Beach",
    "sg:classifiers":[
        {
            "category":"Autos & Motor Vehicles",
            "subcategory":"Automobile Sales",
            "type":"Retail Goods"
        }
    ],
    "sg:phone":"+1 561 844 0961",
    "sg:postcode":"33407",
    "sg:province":"FL",
    "sg:tags":[
        "used"
    ],
    "wof:name":"Forty-Third Street Motors",
    "wof:placetype":"venue"
},
  "geometry": {"coordinates":[-80.05614300000001,26.752077],"type":"Point"}
}