{
  "type": "Feature",
  "properties": {
    "iso:country":"US",
    "sg:address":"316 Florida Ave",
    "sg:city":"Gulf Breeze",
    "sg:classifiers":[
        {
            "category":"Organizations",
            "subcategory":"Professional Association",
            "type":"Services"
        }
    ],
    "sg:phone":"+1 850 932 3467",
    "sg:postcode":"32561",
    "sg:province":"FL",
    "sg:tags":[
        "business"
    ],
    "wof:name":"Pilot Class 43-D",
    "wof:placetype":"venue"
},
  "geometry": {"coordinates":[-87.18241399999999,30.35522],"type":"Point"}
}