{
  "type": "Feature",
  "properties": {
    "addr:full":"1840 W 49th St Hialeah FL 33012",
    "addr:housenumber":"1840",
    "addr:postcode":"33012",
    "addr:street":"W 49Th St",
    "iso:country":"US",
    "sg:address":"1840 W 49th St",
    "sg:city":"Hialeah",
    "sg:classifiers":[
        {
            "category":"Professional",
            "subcategory":"Lawyer & Legal Services",
            "type":"Services"
        }
    ],
    "sg:phone":"+1 305 557 1750",
    "sg:postcode":"33012",
    "sg:province":"FL",
    "wof:name":"Corey Joseph M Jr Atty",
    "wof:placetype":"venue"
},
  "geometry": {"coordinates":[-80.31950399999999,25.866501],"type":"Point"}
}