{
  "type": "Feature",
  "properties": {
    "addr:full":"10960 NW 48th Ter Doral FL 33178",
    "addr:housenumber":"10960",
    "addr:postcode":"33178",
    "addr:street":"Nw 48Th Ter",
    "iso:country":"US",
    "sg:address":"10960 NW 48th Ter",
    "sg:city":"Doral",
    "sg:classifiers":[
        {
            "category":"Shopping",
            "subcategory":"Pharmacy",
            "type":"Retail Goods"
        }
    ],
    "sg:phone":"+1 786 336 0689",
    "sg:postcode":"33178",
    "sg:province":"FL",
    "wof:name":"Classic Pharmacy",
    "wof:placetype":"venue"
},
  "geometry": {"coordinates":[-80.355119,25.817451],"type":"Point"}
}