{
  "type": "Feature",
  "properties": {
    "iso:country":"US",
    "sg:address":"2591 Lake Silver Rd",
    "sg:city":"Crestview",
    "sg:classifiers":[
        {
            "category":"Building & Trades",
            "subcategory":"Plumbing",
            "type":"Services"
        }
    ],
    "sg:phone":"+1 850 682 8683",
    "sg:postcode":"32536",
    "sg:province":"FL",
    "sg:tags":[
        "plumber",
        "industrial",
        "contractors-commercial"
    ],
    "wof:name":"Wetless Plumbing",
    "wof:placetype":"venue"
},
  "geometry": {"coordinates":[-86.57511700000001,30.82206],"type":"Point"}
}