{
  "type": "Feature",
  "properties": {
    "iso:country":"US",
    "sg:address":"1985 Mayport Rd",
    "sg:city":"Atlantic Beach",
    "sg:classifiers":[
        {
            "category":"Retail",
            "subcategory":"Car Wash",
            "type":"Services"
        }
    ],
    "sg:phone":"+1 904 249 2620",
    "sg:postcode":"32233",
    "sg:province":"FL",
    "sg:tags":[
        "automobile",
        "detail",
        "clean"
    ],
    "wof:name":"A Touch Of Class Detailing",
    "wof:placetype":"venue"
},
  "geometry": {"coordinates":[-81.41330600000001,30.344523],"type":"Point"}
}