{
  "type": "Feature",
  "properties": {
    "iso:country":"US",
    "sg:address":"4399 Collins Rd",
    "sg:city":"Weeki Wachee",
    "sg:classifiers":[
        {
            "category":"Building & Trades",
            "subcategory":"Cleaning & Sanitation",
            "type":"Services"
        }
    ],
    "sg:phone":"+1 352 686 6959",
    "sg:postcode":"34606",
    "sg:province":"FL",
    "sg:tags":[
        "janitor"
    ],
    "wof:name":"Kuick Clean Janitorial",
    "wof:placetype":"venue"
},
  "geometry": {"coordinates":[-82.570386,28.495788],"type":"Point"}
}