{
  "type": "Feature",
  "properties": {
    "addr:full":"8766 Sunset Dr Palm Beach Gardens FL 33410",
    "addr:housenumber":"8766",
    "addr:postcode":"33410",
    "addr:street":"Sunset Dr",
    "iso:country":"US",
    "sg:address":"8766 Sunset Dr",
    "sg:city":"Palm Beach Gardens",
    "sg:classifiers":[
        {
            "category":"Building & Trades",
            "subcategory":"Landscaping Services",
            "type":"Services"
        }
    ],
    "sg:phone":"+1 561 603 1689",
    "sg:postcode":"33410",
    "sg:province":"FL",
    "wof:name":"Joseph E Schroth Lawn",
    "wof:placetype":"venue"
},
  "geometry": {"coordinates":[-80.099869,26.803881],"type":"Point"}
}