{
  "type": "Feature",
  "properties": {
    "addr:full":"341 N Pennsylvania Ave Winter Park FL 32789",
    "addr:housenumber":"341",
    "addr:postcode":"32789",
    "addr:street":"N Pennsylvania Ave",
    "iso:country":"US",
    "sg:address":"341 N Pennsylvania Ave",
    "sg:city":"Winter Park",
    "sg:classifiers":[
        {
            "category":"Food & Beverages",
            "subcategory":"Groceries & Convenience Stores",
            "type":"Retail Goods"
        }
    ],
    "sg:phone":"+1 407 628 1833",
    "sg:postcode":"32789",
    "sg:province":"FL",
    "sg:tags":[
        "grocer"
    ],
    "wof:name":"Frank's Market",
    "wof:placetype":"venue"
},
  "geometry": {"coordinates":[-81.357001,28.599977],"type":"Point"}
}