{
  "type": "Feature",
  "properties": {
    "addr:full":"8872 Heckscher Dr Jacksonville FL 32226",
    "addr:housenumber":"8872",
    "addr:postcode":"32226",
    "addr:street":"Heckscher Dr",
    "iso:country":"US",
    "sg:address":"8872 Heckscher Dr",
    "sg:city":"Jacksonville",
    "sg:classifiers":[
        {
            "category":"Building & Trades",
            "subcategory":"Construction",
            "type":"Services"
        }
    ],
    "sg:phone":"+1 904 251 3664",
    "sg:postcode":"32226",
    "sg:province":"FL",
    "sg:tags":[
        "contractor"
    ],
    "wof:name":"Wynn Drywall Inc",
    "wof:placetype":"venue"
},
  "geometry": {"coordinates":[-81.454245,30.38652],"type":"Point"}
}