{
  "type": "Feature",
  "properties": {
    "iso:country":"US",
    "sg:address":"4498 N Alafaya Trl",
    "sg:city":"Orlando",
    "sg:classifiers":[
        {
            "category":"Restaurant",
            "type":"Food & Drink"
        }
    ],
    "sg:menulink":"http://www.allmenus.com/fl/union-park/285158-luya-chinese-restaurant/menu/",
    "sg:phone":"+1 407 243 6630",
    "sg:postcode":"32826",
    "sg:province":"FL",
    "sg:tags":[
        "asian",
        "chinese"
    ],
    "wof:name":"Luya Chinese Restaurant",
    "wof:placetype":"venue"
},
  "geometry": {"coordinates":[-81.20770899999999,28.605146],"type":"Point"}
}