{
  "type": "Feature",
  "properties": {
    "iso:country":"US",
    "sg:address":"2128 W Flagler St",
    "sg:city":"Miami",
    "sg:classifiers":[
        {
            "category":"Health Services",
            "subcategory":"Chiropractor",
            "type":"Services"
        }
    ],
    "sg:phone":"+1 305 649 2500",
    "sg:postcode":"33135",
    "sg:province":"FL",
    "wof:name":"William A Hall DC",
    "wof:placetype":"venue"
},
  "geometry": {"coordinates":[-80.230898,25.772493],"type":"Point"}
}