{
  "type": "Feature",
  "properties": {
    "iso:country":"US",
    "sg:address":"5401 W Oak Ridge Rd",
    "sg:city":"Orlando",
    "sg:classifiers":[
        {
            "category":"Shopping",
            "subcategory":"Bicycles & Sporting Goods",
            "type":"Retail Goods"
        }
    ],
    "sg:phone":"+1 407 903 0445",
    "sg:postcode":"32819",
    "sg:province":"FL",
    "wof:name":"Impact Sports",
    "wof:placetype":"venue"
},
  "geometry": {"coordinates":[-81.44777499999999,28.472135],"type":"Point"}
}