{
  "type": "Feature",
  "properties": {
    "iso:country":"US",
    "sg:address":"4729 Winslow Beacon",
    "sg:city":"Sarasota",
    "sg:classifiers":[
        {
            "category":"Professional",
            "subcategory":"Art Services",
            "type":"Services"
        }
    ],
    "sg:phone":"+1 941 544 6026",
    "sg:postcode":"34235",
    "sg:province":"FL",
    "sg:tags":[
        "photographer"
    ],
    "wof:name":"Joseph C Mc Andrew",
    "wof:placetype":"venue"
},
  "geometry": {"coordinates":[-82.47342,27.35857],"type":"Point"}
}