{
  "type": "Feature",
  "properties": {
    "iso:country":"US",
    "sg:address":"12874 US Hwy 301",
    "sg:city":"Dade City",
    "sg:classifiers":[
        {
            "category":"Insurance",
            "subcategory":"Insurance Agent",
            "type":"Services"
        }
    ],
    "sg:phone":"+1 352 567 5555",
    "sg:postcode":"33525",
    "sg:province":"FL",
    "wof:name":"Aladin Insurance",
    "wof:placetype":"venue"
},
  "geometry": {"coordinates":[-82.187528,28.344051],"type":"Point"}
}