{
  "type": "Feature",
  "properties": {
    "iso:country":"US",
    "sg:address":"1055 Kensington Park Dr",
    "sg:city":"Altamonte Springs",
    "sg:classifiers":[
        {
            "category":"Real Estate",
            "subcategory":"Real Estate Operator",
            "type":"Services"
        }
    ],
    "sg:phone":"+1 407 862 5210",
    "sg:postcode":"32714",
    "sg:province":"FL",
    "sg:tags":[
        "property",
        "lessor"
    ],
    "wof:name":"Mamath Management LLC",
    "wof:placetype":"venue"
},
  "geometry": {"coordinates":[-81.39943100000001,28.68538],"type":"Point"}
}