{
  "type": "Feature",
  "properties": {
    "iso:country":"US",
    "sg:address":"50 Berkshire Ln",
    "sg:city":"Palm Coast",
    "sg:classifiers":[
        {
            "category":"Social Services",
            "type":"Services"
        }
    ],
    "sg:phone":"+1 386 246 4108",
    "sg:postcode":"32137",
    "sg:province":"FL",
    "wof:name":"Abundant Life Ministries-Hope",
    "wof:placetype":"venue"
},
  "geometry": {"coordinates":[-81.235309,29.557454],"type":"Point"}
}