{
  "type": "Feature",
  "properties": {
    "iso:country":"US",
    "sg:address":"2425 Brooks St",
    "sg:city":"Sanford",
    "sg:classifiers":[
        {
            "category":"Bars & Pubs",
            "type":"Food & Drink"
        }
    ],
    "sg:phone":"+1 407 328 1715",
    "sg:postcode":"32773",
    "sg:province":"FL",
    "sg:tags":[
        "drinking"
    ],
    "wof:name":"Straight Up Pub",
    "wof:placetype":"venue"
},
  "geometry": {"coordinates":[-81.235803,28.760369],"type":"Point"}
}