{
  "type": "Feature",
  "properties": {
    "addr:full":"18205 Biscayne Blvd Aventura FL 33160",
    "addr:housenumber":"18205",
    "addr:postcode":"33160",
    "addr:street":"Biscayne Blvd",
    "iso:country":"US",
    "sg:address":"18205 Biscayne Blvd",
    "sg:city":"Aventura",
    "sg:classifiers":[
        {
            "category":"Real Estate",
            "subcategory":"Real Estate Services",
            "type":"Services"
        },
        {
            "category":"Real Estate",
            "subcategory":"Real Estate Agent",
            "type":"Services"
        }
    ],
    "sg:phone":"+1 305 933 0788",
    "sg:postcode":"33160",
    "sg:province":"FL",
    "sg:tags":[
        "buyer",
        "broker"
    ],
    "wof:name":"Watson Darlene Beachfront Realty Short Sales Div",
    "wof:placetype":"venue"
},
  "geometry": {"coordinates":[-80.14787200000001,25.944139],"type":"Point"}
}