{
  "type": "Feature",
  "properties": {
    "iso:country":"US",
    "sg:address":"3259 Garden St",
    "sg:city":"Titusville",
    "sg:classifiers":[
        {
            "category":"Shopping",
            "subcategory":"Department Store",
            "type":"Retail Goods"
        }
    ],
    "sg:phone":"+1 321 264 1969",
    "sg:postcode":"32796",
    "sg:province":"FL",
    "sg:website":"http://www.bealls.com/",
    "wof:name":"Bealls Department Store",
    "wof:placetype":"venue"
},
  "geometry": {"coordinates":[-80.842417,28.618329],"type":"Point"}
}