{
  "type": "Feature",
  "properties": {
    "addr:full":"2176 NE 123rd St North Miami FL 33181",
    "addr:housenumber":"2176",
    "addr:postcode":"33181",
    "addr:street":"Ne 123Rd St",
    "iso:country":"US",
    "sg:address":"2176 NE 123rd St",
    "sg:city":"North Miami",
    "sg:classifiers":[
        {
            "category":"Restaurant",
            "type":"Food & Drink"
        }
    ],
    "sg:phone":"+1 305 892 1118",
    "sg:postcode":"33181",
    "sg:province":"FL",
    "wof:name":"Thai Treat",
    "wof:placetype":"venue"
},
  "geometry": {"coordinates":[-80.155197,25.8894],"type":"Point"}
}