{
  "type": "Feature",
  "properties": {
    "iso:country":"US",
    "sg:address":"203 John Sims Pkwy",
    "sg:city":"Niceville",
    "sg:classifiers":[
        {
            "category":"Government",
            "subcategory":"Office",
            "type":"Public Place"
        }
    ],
    "sg:phone":"+1 850 651 7300",
    "sg:postcode":"32578",
    "sg:province":"FL",
    "sg:tags":[
        "county",
        "taxation"
    ],
    "wof:name":"Okaloosa County Tax Collector",
    "wof:placetype":"venue"
},
  "geometry": {"coordinates":[-86.487178,30.520666],"type":"Point"}
}