{
  "type": "Feature",
  "properties": {
    "addr:full":"1671 NW 103rd Ave Fort Lauderdale FL 33322",
    "addr:housenumber":"1671",
    "addr:postcode":"33322",
    "addr:street":"Nw 103Rd Ave",
    "iso:country":"US",
    "sg:address":"1671 NW 103rd Ave",
    "sg:city":"Fort Lauderdale",
    "sg:classifiers":[
        {
            "category":"Building & Trades",
            "subcategory":"Cleaning & Sanitation",
            "type":"Services"
        }
    ],
    "sg:phone":"+1 954 424 2901",
    "sg:postcode":"33322",
    "sg:province":"FL",
    "sg:tags":[
        "funeral",
        "maintenance"
    ],
    "wof:name":"Exclusive Family Estates Inc",
    "wof:placetype":"venue"
},
  "geometry": {"coordinates":[-80.287525,26.144645],"type":"Point"}
}