{
  "type": "Feature",
  "properties": {
    "iso:country":"US",
    "sg:address":"5801 NE 14th Ave",
    "sg:city":"Fort Lauderdale",
    "sg:classifiers":[
        {
            "category":"Manufacturing",
            "subcategory":"Apparel",
            "type":"Manufacturing & Wholesale Goods"
        }
    ],
    "sg:phone":"+1 954 776 6959",
    "sg:postcode":"33334",
    "sg:province":"FL",
    "sg:tags":[
        "household",
        "furnishing",
        "mfg"
    ],
    "wof:name":"Emergency Linen Supply",
    "wof:placetype":"venue"
},
  "geometry": {"coordinates":[-80.131551,26.201204],"type":"Point"}
}