{
  "type": "Feature",
  "properties": {
    "iso:country":"US",
    "sg:address":"1543 Kingsley Ave",
    "sg:city":"Orange Park",
    "sg:classifiers":[
        {
            "category":"Professional",
            "subcategory":"Lawyer & Legal Services",
            "type":"Services"
        }
    ],
    "sg:phone":"+1 904 353 5579",
    "sg:postcode":"32073",
    "sg:province":"FL",
    "wof:name":"Bivens Burney PA and Assoc",
    "wof:placetype":"venue"
},
  "geometry": {"coordinates":[-81.730131,30.164518],"type":"Point"}
}