{
  "type": "Feature",
  "properties": {
    "addr:full":"7301 N University Dr Tamarac FL 33321",
    "addr:housenumber":"7301",
    "addr:postcode":"33321",
    "addr:street":"N University Dr",
    "iso:country":"US",
    "sg:address":"7301 N University Dr",
    "sg:city":"Tamarac",
    "sg:classifiers":[
        {
            "category":"Health Services",
            "subcategory":"Health Practitioner",
            "type":"Services"
        }
    ],
    "sg:phone":"+1 954 720 0412",
    "sg:postcode":"33321",
    "sg:province":"FL",
    "sg:tags":[
        "psychologist"
    ],
    "wof:name":"Bird Of Paradise Psychological",
    "wof:placetype":"venue"
},
  "geometry": {"coordinates":[-80.252483,26.212782],"type":"Point"}
}