{
  "type": "Feature",
  "properties": {
    "iso:country":"US",
    "sg:address":"1840 W 9th St",
    "sg:city":"Jacksonville",
    "sg:classifiers":[
        {
            "category":"Education",
            "subcategory":"School",
            "type":"Public Place"
        }
    ],
    "sg:phone":"+1 904 630 6640",
    "sg:postcode":"32209",
    "sg:province":"FL",
    "wof:name":"James Wldon Jhnson Middle Schl",
    "wof:placetype":"venue"
},
  "geometry": {"coordinates":[-81.68774500000001,30.348367],"type":"Point"}
}