{
  "type": "Feature",
  "properties": {
    "iso:country":"US",
    "sg:address":"530 E Ash St",
    "sg:city":"Perry",
    "sg:classifiers":[
        {
            "category":"Shopping",
            "type":"Retail Goods"
        }
    ],
    "sg:phone":"+1 850 584 8106",
    "sg:postcode":"32347",
    "sg:province":"FL",
    "sg:tags":[
        "monument"
    ],
    "wof:name":"Burns Monument & Vault Co",
    "wof:placetype":"venue"
},
  "geometry": {"coordinates":[-83.572796,30.128465],"type":"Point"}
}