{
  "type": "Feature",
  "properties": {
    "iso:country":"US",
    "sg:address":"3539 Apalachee Pkwy",
    "sg:city":"Tallahassee",
    "sg:classifiers":[
        {
            "category":"Shopping",
            "type":"Retail Goods"
        }
    ],
    "sg:phone":"+1 850 224 2146",
    "sg:postcode":"32311",
    "sg:province":"FL",
    "sg:tags":[
        "item",
        "boutique"
    ],
    "wof:name":"Goody Goodies And More A Boutique",
    "wof:placetype":"venue"
},
  "geometry": {"coordinates":[-84.214685,30.428143],"type":"Point"}
}