{
  "type": "Feature",
  "properties": {
    "iso:country":"US",
    "sg:address":"2252 S Kirkman Rd",
    "sg:city":"Orlando",
    "sg:classifiers":[
        {
            "category":"Professional",
            "subcategory":"Management & Consulting",
            "type":"Services"
        }
    ],
    "sg:phone":"+1 407 299 1156",
    "sg:postcode":"32811",
    "sg:province":"FL",
    "sg:tags":[
        "marketing",
        "program"
    ],
    "wof:name":"Stellar Marketing",
    "wof:placetype":"venue"
},
  "geometry": {"coordinates":[-81.459193,28.51667],"type":"Point"}
}