{
  "type": "Feature",
  "properties": {
    "iso:country":"US",
    "sg:address":"55 Bay Bridge Dr",
    "sg:city":"Gulf Breeze",
    "sg:classifiers":[
        {
            "category":"Banks & Credit Unions",
            "subcategory":"Financial Services",
            "type":"Services"
        }
    ],
    "sg:phone":"+1 850 934 3535",
    "sg:postcode":"32561",
    "sg:province":"FL",
    "sg:tags":[
        "investor"
    ],
    "wof:name":"Shawshank Investments LLC",
    "wof:placetype":"venue"
},
  "geometry": {"coordinates":[-87.17530600000001,30.370674],"type":"Point"}
}