{
  "type": "Feature",
  "properties": {
    "addr:full":"7101 SW 99th Ave Ste 109B Miami FL 33173",
    "addr:housenumber":"7101",
    "addr:postcode":"33173",
    "addr:street":"Sw 99Th Ave Ste 109B",
    "iso:country":"US",
    "sg:address":"7101 SW 99th Ave Ste 109B",
    "sg:city":"Miami",
    "sg:classifiers":[
        {
            "category":"Professional",
            "subcategory":"Lawyer & Legal Services",
            "type":"Services"
        }
    ],
    "sg:phone":"+1 305 559 1888",
    "sg:postcode":"33173",
    "sg:province":"FL",
    "wof:name":"Zaldivar Raquel Puig",
    "wof:placetype":"venue"
},
  "geometry": {"coordinates":[-80.35404200000001,25.702421],"type":"Point"}
}