{
  "type": "Feature",
  "properties": {
    "iso:country":"US",
    "sg:address":"500 SW 109th Ave",
    "sg:city":"Miami",
    "sg:classifiers":[
        {
            "category":"Professional",
            "type":"Services"
        }
    ],
    "sg:phone":"+1 305 485 0338",
    "sg:postcode":"33174",
    "sg:province":"FL",
    "sg:tags":[
        "establishment"
    ],
    "wof:name":"Craig A Smith & Assoc",
    "wof:placetype":"venue"
},
  "geometry": {"coordinates":[-80.372573,25.763368],"type":"Point"}
}