{
  "type": "Feature",
  "properties": {
    "iso:country":"US",
    "sg:address":"4060 S Tamiami Trl",
    "sg:city":"Osprey",
    "sg:classifiers":[
        {
            "category":"Banks & Credit Unions",
            "subcategory":"Investment Brokerage",
            "type":"Services"
        },
        {
            "category":"Banks & Credit Unions",
            "subcategory":"Financial Services",
            "type":"Services"
        }
    ],
    "sg:phone":"+1 941 918 2777",
    "sg:postcode":"34229",
    "sg:province":"FL",
    "sg:tags":[
        "advisory",
        "planner"
    ],
    "wof:name":"Welch & Associates Inc",
    "wof:placetype":"venue"
},
  "geometry": {"coordinates":[-82.489895,27.19506],"type":"Point"}
}