{
  "type": "Feature",
  "properties": {
    "iso:country":"US",
    "sg:address":"5606 Park Blvd",
    "sg:city":"Pinellas Park",
    "sg:classifiers":[
        {
            "category":"Retail",
            "subcategory":"Repair Shop",
            "type":"Services"
        }
    ],
    "sg:phone":"+1 727 545 3667",
    "sg:postcode":"33781",
    "sg:province":"FL",
    "sg:tags":[
        "key",
        "locksmith"
    ],
    "wof:name":"John's Key Shop Inc",
    "wof:placetype":"venue"
},
  "geometry": {"coordinates":[-82.711541,27.839125],"type":"Point"}
}