{
  "type": "Feature",
  "properties": {
    "iso:country":"US",
    "sg:address":"603 Ridge Blvd",
    "sg:city":"Daytona Beach",
    "sg:classifiers":[
        {
            "category":"Wholesale",
            "subcategory":"Home Furnishings",
            "type":"Manufacturing & Wholesale Goods"
        }
    ],
    "sg:phone":"+1 386 760 5770",
    "sg:postcode":"32119",
    "sg:province":"FL",
    "wof:name":"Anns Pottery & Things",
    "wof:placetype":"venue"
},
  "geometry": {"coordinates":[-81.007136,29.164523],"type":"Point"}
}