{
  "type": "Feature",
  "properties": {
    "addr:full":"200 A Ln Cocoa FL 32926",
    "addr:housenumber":"200",
    "addr:postcode":"32926",
    "addr:street":"A Ln",
    "iso:country":"US",
    "sg:address":"200 A Ln",
    "sg:city":"Cocoa",
    "sg:classifiers":[
        {
            "category":"Shopping",
            "subcategory":"Florist",
            "type":"Retail Goods"
        }
    ],
    "sg:phone":"+1 321 633 7673",
    "sg:postcode":"32926",
    "sg:province":"FL",
    "wof:name":"A Basket Of Love Florist",
    "wof:placetype":"venue"
},
  "geometry": {"coordinates":[-80.78858700000001,28.354822],"type":"Point"}
}