{
  "type": "Feature",
  "properties": {
    "addr:full":"12 J Crawfordville FL 32327",
    "addr:housenumber":"12",
    "addr:postcode":"32327",
    "addr:street":"J Crawfordville",
    "iso:country":"US",
    "sg:address":"12 J",
    "sg:city":"Crawfordville",
    "sg:classifiers":[
        {
            "category":"Travel",
            "subcategory":"Travel Agent",
            "type":"Entertainment"
        }
    ],
    "sg:phone":"+1 850 421 5009",
    "sg:postcode":"32327",
    "sg:province":"FL",
    "sg:tags":[
        "cruise"
    ],
    "wof:name":"Cruise Planners",
    "wof:placetype":"venue"
},
  "geometry": {"coordinates":[-84.358064,30.179117],"type":"Point"}
}