{
  "type": "Feature",
  "properties": {
    "addr:full":"8833 Tamiami Trl Naples FL 34113",
    "addr:housenumber":"8833",
    "addr:postcode":"34113",
    "addr:street":"Tamiami Trl",
    "iso:country":"US",
    "sg:address":"8833 Tamiami Trl",
    "sg:city":"Naples",
    "sg:classifiers":[
        {
            "category":"Home & Garden",
            "subcategory":"Furniture",
            "type":"Retail Goods"
        }
    ],
    "sg:phone":"+1 239 775 8185",
    "sg:postcode":"34113",
    "sg:province":"FL",
    "wof:name":"Reyes Furniture",
    "wof:placetype":"venue"
},
  "geometry": {"coordinates":[-81.740072,26.098827],"type":"Point"}
}