{
  "type": "Feature",
  "properties": {
    "addr:full":"484 Mandalay Ave Clearwater FL 33767",
    "addr:housenumber":"484",
    "addr:postcode":"33767",
    "addr:street":"Mandalay Ave",
    "iso:country":"US",
    "sg:address":"484 Mandalay Ave",
    "sg:city":"Clearwater",
    "sg:classifiers":[
        {
            "category":"Real Estate",
            "subcategory":"Real Estate Agent",
            "type":"Services"
        }
    ],
    "sg:phone":"+1 727 446 6233",
    "sg:postcode":"33767",
    "sg:province":"FL",
    "wof:name":"Coronado 100 Realty Inc",
    "wof:placetype":"venue"
},
  "geometry": {"coordinates":[-82.82708599999999,27.981547],"type":"Point"}
}