{
  "type": "Feature",
  "properties": {
    "addr:full":"527 Freeman St Longwood FL 32750",
    "addr:housenumber":"527",
    "addr:postcode":"32750",
    "addr:street":"Freeman St",
    "iso:country":"US",
    "sg:address":"527 Freeman St",
    "sg:city":"Longwood",
    "sg:classifiers":[
        {
            "category":"Shopping",
            "subcategory":"Clothing, Apparel, & Fashions",
            "type":"Retail Goods"
        }
    ],
    "sg:phone":"+1 407 321 1077",
    "sg:postcode":"32750",
    "sg:province":"FL",
    "wof:name":"S H Fashions",
    "wof:placetype":"venue"
},
  "geometry": {"coordinates":[-81.346338,28.703045],"type":"Point"}
}