{
  "type": "Feature",
  "properties": {
    "iso:country":"US",
    "sg:address":"4885 Belvedere Rd",
    "sg:city":"Haverhill",
    "sg:classifiers":[
        {
            "category":"Building & Trades",
            "subcategory":"Landscaping Services",
            "type":"Services"
        }
    ],
    "sg:phone":"+1 561 294 2976",
    "sg:postcode":"33415",
    "sg:province":"FL",
    "sg:tags":[
        "landscape",
        "contractor"
    ],
    "wof:name":"Berduo Lawn & Landscaping",
    "wof:placetype":"venue"
},
  "geometry": {"coordinates":[-80.117834,26.692251],"type":"Point"}
}