{
  "type": "Feature",
  "properties": {
    "addr:full":"5437 Timberleaf Blvd Orlando FL 32811",
    "addr:housenumber":"5437",
    "addr:postcode":"32811",
    "addr:street":"Timberleaf Blvd",
    "iso:country":"US",
    "sg:address":"5437 Timberleaf Blvd",
    "sg:city":"Orlando",
    "sg:classifiers":[
        {
            "category":"Recreation",
            "type":"Entertainment"
        }
    ],
    "sg:phone":"+1 407 578 3407",
    "sg:postcode":"32811",
    "sg:province":"FL",
    "sg:tags":[
        "center"
    ],
    "wof:name":"Timberleaf Recreation Ctr",
    "wof:placetype":"venue"
},
  "geometry": {"coordinates":[-81.45217,28.529728],"type":"Point"}
}