{
  "type": "Feature",
  "properties": {
    "addr:full":"2317 Bannerman Rd Tallahassee FL 32312",
    "addr:housenumber":"2317",
    "addr:postcode":"32312",
    "addr:street":"Bannerman Rd",
    "iso:country":"US",
    "sg:address":"2317 Bannerman Rd",
    "sg:city":"Tallahassee",
    "sg:classifiers":[
        {
            "category":"Organizations",
            "subcategory":"Religious Organization",
            "type":"Services"
        }
    ],
    "sg:phone":"+1 850 893 7472",
    "sg:postcode":"32312",
    "sg:province":"FL",
    "sg:website":"www.cpcusa.org",
    "wof:name":"Christ Presbyterian Church",
    "wof:placetype":"venue"
},
  "geometry": {"coordinates":[-84.240649,30.580808],"type":"Point"}
}