{
  "type": "Feature",
  "properties": {
    "iso:country":"US",
    "sg:address":"1228 Cleveland St",
    "sg:city":"Clearwater",
    "sg:classifiers":[
        {
            "category":"Food & Beverages",
            "subcategory":"Groceries & Convenience Stores",
            "type":"Retail Goods"
        }
    ],
    "sg:phone":"+1 727 466 6868",
    "sg:postcode":"33755",
    "sg:province":"FL",
    "wof:name":"Julio Torres",
    "wof:placetype":"venue"
},
  "geometry": {"coordinates":[-82.78630800000001,27.965707],"type":"Point"}
}