{
  "type": "Feature",
  "properties": {
    "iso:country":"US",
    "sg:address":"2798 Elkcam Blvd",
    "sg:city":"Deltona",
    "sg:classifiers":[
        {
            "category":"Food & Beverages",
            "subcategory":"Groceries & Convenience Stores",
            "type":"Retail Goods"
        }
    ],
    "sg:phone":"+1 386 789 4461",
    "sg:postcode":"32738",
    "sg:province":"FL",
    "sg:website":"www.thepantry.com",
    "wof:name":"Kangaroo Express #1273",
    "wof:placetype":"venue"
},
  "geometry": {"coordinates":[-81.18812699999999,28.928486],"type":"Point"}
}