{
  "type": "Feature",
  "properties": {
    "addr:full":"5037 Ringwood Meadows Sarasota FL 34235",
    "addr:housenumber":"5037",
    "addr:postcode":"34235",
    "addr:street":"Ringwood Meadows",
    "iso:country":"US",
    "sg:address":"5037 Ringwood Meadows",
    "sg:city":"Sarasota",
    "sg:classifiers":[
        {
            "category":"Real Estate",
            "subcategory":"Real Estate Agent",
            "type":"Services"
        }
    ],
    "sg:phone":"+1 941 377 2300",
    "sg:postcode":"34235",
    "sg:province":"FL",
    "wof:name":"MCA",
    "wof:placetype":"venue"
},
  "geometry": {"coordinates":[-82.466438,27.362931],"type":"Point"}
}