{
  "type": "Feature",
  "properties": {
    "iso:country":"US",
    "sg:address":"3643 North Rd",
    "sg:city":"Naples",
    "sg:classifiers":[
        {
            "category":"Professional",
            "subcategory":"Business Services",
            "type":"Services"
        }
    ],
    "sg:phone":"+1 239 643 7773",
    "sg:postcode":"34104",
    "sg:province":"FL",
    "sg:tags":[
        "lecture",
        "bureau",
        "seminar"
    ],
    "wof:name":"Preparing For Birth & Beyond",
    "wof:placetype":"venue"
},
  "geometry": {"coordinates":[-81.761792,26.146124],"type":"Point"}
}