{
  "type": "Feature",
  "properties": {
    "addr:full":"6504 Thomas Dr Panama City Bch FL 32408",
    "addr:housenumber":"6504",
    "addr:postcode":"32408",
    "addr:street":"Thomas Dr",
    "iso:country":"US",
    "sg:address":"6504 Thomas Dr",
    "sg:city":"Panama City Bch",
    "sg:classifiers":[
        {
            "category":"Real Estate",
            "subcategory":"Real Estate Agent",
            "type":"Services"
        }
    ],
    "sg:phone":"+1 850 236 9113",
    "sg:postcode":"32408",
    "sg:province":"FL",
    "sg:website":"www.homesandlandonthebeach.com",
    "wof:name":"Donna Stokes",
    "wof:placetype":"venue"
},
  "geometry": {"coordinates":[-85.766795,30.152759],"type":"Point"}
}