{
  "type": "Feature",
  "properties": {
    "iso:country":"US",
    "sg:address":"1955 Upper Beechwood Ave",
    "sg:city":"Sarasota",
    "sg:classifiers":[
        {
            "category":"Autos & Motor Vehicles",
            "subcategory":"Auto Supplies",
            "type":"Retail Goods"
        }
    ],
    "sg:phone":"+1 941 924 1241",
    "sg:postcode":"34231",
    "sg:province":"FL",
    "sg:tags":[
        "automotive",
        "repair"
    ],
    "wof:name":"NAPA Auto Parts",
    "wof:placetype":"venue"
},
  "geometry": {"coordinates":[-82.527371,27.26552],"type":"Point"}
}