{
  "type": "Feature",
  "properties": {
    "addr:full":"3801 Danny Bryan Blvd Tampa FL 33619",
    "addr:housenumber":"3801",
    "addr:postcode":"33619",
    "addr:street":"Danny Bryan Blvd",
    "iso:country":"US",
    "sg:address":"3801 Danny Bryan Blvd",
    "sg:city":"Tampa",
    "sg:classifiers":[
        {
            "category":"Place Of Worship",
            "subcategory":"Church",
            "type":"Public Place"
        },
        {
            "category":"Place Of Worship",
            "type":"Public Place"
        },
        {
            "category":"Organizations",
            "subcategory":"Religious Organization",
            "type":"Services"
        }
    ],
    "sg:phone":"+1 813 621 4264",
    "sg:postcode":"33619",
    "sg:province":"FL",
    "sg:tags":[
        "god",
        "churches-church",
        "churches-pentecostal"
    ],
    "wof:name":"Holy Church Of God",
    "wof:placetype":"venue"
},
  "geometry": {"coordinates":[-82.363389,27.980294],"type":"Point"}
}