{
  "type": "Feature",
  "properties": {
    "iso:country":"US",
    "sg:address":"7400 NW 30th Ave",
    "sg:city":"Miami",
    "sg:classifiers":[
        {
            "category":"Utilities",
            "subcategory":"Natural Gas",
            "type":"Services"
        }
    ],
    "sg:phone":"+1 800 656 3368",
    "sg:postcode":"33147",
    "sg:province":"FL",
    "sg:tags":[
        "repairing",
        "lines-installation"
    ],
    "sg:website":"http://www.siegelgas.com",
    "wof:name":"Siegel Gas & Oil Corp",
    "wof:placetype":"venue"
},
  "geometry": {"coordinates":[-80.245667,25.841539],"type":"Point"}
}