{
  "type": "Feature",
  "properties": {
    "addr:full":"1920 Strauch Rd Clearwater FL 33760",
    "addr:postcode":"1920;33760",
    "addr:street":"Strauch Rd",
    "iso:country":"US",
    "sg:address":"1920 Strauch Rd",
    "sg:city":"Clearwater",
    "sg:classifiers":[
        {
            "category":"Building & Trades",
            "subcategory":"Landscaping Services",
            "type":"Services"
        }
    ],
    "sg:phone":"+1 727 535 0357",
    "sg:postcode":"33760",
    "sg:province":"FL",
    "wof:name":"Glenns Lawn & Home Care",
    "wof:placetype":"venue"
},
  "geometry": {"coordinates":[-82.718941,27.926921],"type":"Point"}
}