{
  "type": "Feature",
  "properties": {
    "addr:full":"2730 Davie Blvd Fort Lauderdale FL 33312",
    "addr:housenumber":"2730",
    "addr:postcode":"33312",
    "addr:street":"Davie Blvd",
    "iso:country":"US",
    "sg:address":"2730 Davie Blvd",
    "sg:city":"Fort Lauderdale",
    "sg:classifiers":[
        {
            "category":"Shopping",
            "subcategory":"Clothing, Apparel, & Fashions",
            "type":"Retail Goods"
        }
    ],
    "sg:phone":"+1 954 321 8774",
    "sg:postcode":"33312",
    "sg:province":"FL",
    "sg:tags":[
        "designer"
    ],
    "wof:name":"Sissi Enterprises Corp",
    "wof:placetype":"venue"
},
  "geometry": {"coordinates":[-80.179013,26.106181],"type":"Point"}
}