{
  "type": "Feature",
  "properties": {
    "iso:country":"US",
    "sg:address":"2238 Gulf Gate Dr",
    "sg:city":"Sarasota",
    "sg:classifiers":[
        {
            "category":"Restaurant",
            "type":"Food & Drink"
        }
    ],
    "sg:phone":"+1 941 927 8424",
    "sg:postcode":"34231",
    "sg:province":"FL",
    "sg:tags":[
        "eating"
    ],
    "wof:name":"Thailand Restaurant",
    "wof:placetype":"venue"
},
  "geometry": {"coordinates":[-82.51976000000001,27.259025],"type":"Point"}
}