{
  "type": "Feature",
  "properties": {
    "iso:country":"US",
    "sg:address":"900 Florida Ave",
    "sg:city":"Lynn Haven",
    "sg:classifiers":[
        {
            "category":"Shopping",
            "type":"Retail Goods"
        }
    ],
    "sg:phone":"+1 850 265 9847",
    "sg:postcode":"32444",
    "sg:province":"FL",
    "sg:tags":[
        "merchandise"
    ],
    "wof:name":"Old Bank Coins",
    "wof:placetype":"venue"
},
  "geometry": {"coordinates":[-85.649818,30.243775],"type":"Point"}
}