{
  "type": "Feature",
  "properties": {
    "addr:full":"2623 W Cervantes St Pensacola FL 32505",
    "addr:housenumber":"2623",
    "addr:postcode":"32505",
    "addr:street":"W Cervantes St",
    "iso:country":"US",
    "sg:address":"2623 W Cervantes St",
    "sg:city":"Pensacola",
    "sg:classifiers":[
        {
            "category":"Organizations",
            "subcategory":"Community Association",
            "type":"Services"
        }
    ],
    "sg:phone":"+1 850 432 0068",
    "sg:postcode":"32505",
    "sg:province":"FL",
    "sg:tags":[
        "club"
    ],
    "wof:name":"Alano Club",
    "wof:placetype":"venue"
},
  "geometry": {"coordinates":[-87.24777899999999,30.420886],"type":"Point"}
}