{
  "type": "Feature",
  "properties": {
    "addr:full":"3250 Cypress Glen Way Naples FL 34109",
    "addr:housenumber":"3250",
    "addr:postcode":"34109",
    "addr:street":"Cypress Glen Way",
    "iso:country":"US",
    "sg:address":"3250 Cypress Glen Way",
    "sg:city":"Naples",
    "sg:classifiers":[
        {
            "category":"Wholesale",
            "subcategory":"Jewelry",
            "type":"Manufacturing & Wholesale Goods"
        }
    ],
    "sg:phone":"+1 239 596 0347",
    "sg:postcode":"34109",
    "sg:province":"FL",
    "sg:tags":[
        "jeweler"
    ],
    "wof:name":"Henry Jimenez Fine Jewel",
    "wof:placetype":"venue"
},
  "geometry": {"coordinates":[-81.756364,26.213463],"type":"Point"}
}