{
  "type": "Feature",
  "properties": {
    "iso:country":"US",
    "sg:address":"502 E Bridgers Ave",
    "sg:city":"Auburndale",
    "sg:classifiers":[
        {
            "category":"Freight",
            "type":"Transportation"
        }
    ],
    "sg:phone":"+1 863 967 1101",
    "sg:postcode":"33823",
    "sg:province":"FL",
    "sg:tags":[
        "operator",
        "local",
        "trucking"
    ],
    "wof:name":"Comcar Industries",
    "wof:placetype":"venue"
},
  "geometry": {"coordinates":[-81.77470099999999,28.063449],"type":"Point"}
}