{
  "type": "Feature",
  "properties": {
    "addr:full":"1401 NE 117th St Miami FL 33161",
    "addr:housenumber":"1401",
    "addr:postcode":"33161",
    "addr:street":"Ne 117Th St",
    "iso:country":"US",
    "sg:address":"1401 NE 117th St",
    "sg:city":"Miami",
    "sg:classifiers":[
        {
            "category":"Professional",
            "subcategory":"Detective & Security Services",
            "type":"Services"
        }
    ],
    "sg:phone":"+1 305 893 2452",
    "sg:postcode":"33161",
    "sg:province":"FL",
    "sg:tags":[
        "agency"
    ],
    "wof:name":"South Florida Detective Bureau",
    "wof:placetype":"venue"
},
  "geometry": {"coordinates":[-80.16613599999999,25.883397],"type":"Point"}
}