{
  "type": "Feature",
  "properties": {
    "addr:full":"5333 Yancy Dr Milton FL 32571",
    "addr:housenumber":"5333",
    "addr:postcode":"32571",
    "addr:street":"Yancy Dr",
    "iso:country":"US",
    "sg:address":"5333 Yancy Dr",
    "sg:city":"Milton",
    "sg:classifiers":[
        {
            "category":"Building & Trades",
            "subcategory":"Cleaning & Sanitation",
            "type":"Services"
        }
    ],
    "sg:phone":"+1 850 995 9151",
    "sg:postcode":"32571",
    "sg:province":"FL",
    "sg:tags":[
        "maintenance"
    ],
    "wof:name":"Anchor Cleaning Service",
    "wof:placetype":"venue"
},
  "geometry": {"coordinates":[-87.119299,30.630949],"type":"Point"}
}