{
  "type": "Feature",
  "properties": {
    "addr:full":"5950 Lakehurst Dr Orlando FL 32819",
    "addr:housenumber":"5950",
    "addr:postcode":"32819",
    "addr:street":"Lakehurst Dr",
    "iso:country":"US",
    "sg:address":"5950 Lakehurst Dr",
    "sg:city":"Orlando",
    "sg:classifiers":[
        {
            "category":"Manufacturing",
            "subcategory":"Tools & Machinery",
            "type":"Manufacturing & Wholesale Goods"
        }
    ],
    "sg:phone":"+1 407 351 0211",
    "sg:postcode":"32819",
    "sg:province":"FL",
    "sg:tags":[
        "lighting",
        "fixture"
    ],
    "wof:name":"Holophane Amer Elec Lightning",
    "wof:placetype":"venue"
},
  "geometry": {"coordinates":[-81.461079,28.453651],"type":"Point"}
}