{
  "type": "Feature",
  "properties": {
    "addr:full":"102 Magnolia Ln Tampa FL 33610",
    "addr:housenumber":"102",
    "addr:postcode":"33610",
    "addr:street":"Magnolia Ln",
    "iso:country":"US",
    "sg:address":"102 Magnolia Ln",
    "sg:city":"Tampa",
    "sg:classifiers":[
        {
            "category":"Real Estate",
            "subcategory":"Developer",
            "type":"Services"
        }
    ],
    "sg:phone":"+1 813 621 3268",
    "sg:postcode":"33610",
    "sg:province":"FL",
    "sg:tags":[
        "mobile",
        "home"
    ],
    "wof:name":"Davpam Mobile Home Community",
    "wof:placetype":"venue"
},
  "geometry": {"coordinates":[-82.31780000000001,27.985273],"type":"Point"}
}