{
  "type": "Feature",
  "properties": {
    "iso:country":"US",
    "sg:address":"1610 Skinner St",
    "sg:city":"Lakeland",
    "sg:classifiers":[
        {
            "category":"Shopping",
            "subcategory":"Florist",
            "type":"Retail Goods"
        }
    ],
    "sg:phone":"+1 863 688 3895",
    "sg:postcode":"33801",
    "sg:province":"FL",
    "wof:name":"Designer Silks",
    "wof:placetype":"venue"
},
  "geometry": {"coordinates":[-81.930649,28.028331],"type":"Point"}
}