{
  "type": "Feature",
  "properties": {
    "iso:country":"US",
    "sg:address":"777 S Flagler Dr",
    "sg:city":"West Palm Beach",
    "sg:classifiers":[
        {
            "category":"Professional",
            "subcategory":"Lawyer & Legal Services",
            "type":"Services"
        }
    ],
    "sg:phone":"+1 561 515 6056",
    "sg:postcode":"33401",
    "sg:province":"FL",
    "sg:tags":[
        "attorney"
    ],
    "wof:name":"Christoper Chopin Atty At Law",
    "wof:placetype":"venue"
},
  "geometry": {"coordinates":[-80.04883,26.70647],"type":"Point"}
}