{
  "type": "Feature",
  "properties": {
    "addr:full":"180 Gulf Stream Way Dania FL 33004",
    "addr:housenumber":"180",
    "addr:postcode":"33004",
    "addr:street":"Gulf Stream Way",
    "iso:country":"US",
    "sg:address":"180 Gulf Stream Way",
    "sg:city":"Dania",
    "sg:classifiers":[
        {
            "category":"Shopping",
            "type":"Retail Goods"
        }
    ],
    "sg:phone":"+1 954 925 7630",
    "sg:postcode":"33004",
    "sg:province":"FL",
    "sg:tags":[
        "equipment",
        "supply",
        "divers'"
    ],
    "sg:website":"http://www.diversdirect.com",
    "wof:name":"Divers Direct",
    "wof:placetype":"venue"
},
  "geometry": {"coordinates":[-80.16555700000001,26.058041],"type":"Point"}
}