{
  "type": "Feature",
  "properties": {
    "addr:full":"303 E Altamonte Dr Ste 1750 Altamonte Springs FL 32701",
    "addr:housenumber":"303",
    "addr:postcode":"32701",
    "addr:street":"E Altamonte Dr Ste 1750",
    "iso:country":"US",
    "sg:address":"303 E Altamonte Dr Ste 1750",
    "sg:city":"Altamonte Springs",
    "sg:classifiers":[
        {
            "category":"Restaurant",
            "type":"Food & Drink"
        }
    ],
    "sg:phone":"+1 407 331 8803",
    "sg:postcode":"32701",
    "sg:province":"FL",
    "sg:tags":[
        "thai"
    ],
    "sg:website":"www.facebook.com/pages/Altamonte...",
    "wof:name":"Phat Thai Caf?",
    "wof:placetype":"venue"
},
  "geometry": {"coordinates":[-81.381822,28.664015],"type":"Point"}
}