{
  "type": "Feature",
  "properties": {
    "iso:country":"US",
    "sg:address":"5369 Bamboo Ct",
    "sg:city":"Orlando",
    "sg:classifiers":[
        {
            "category":"Building & Trades",
            "subcategory":"Cleaning & Sanitation",
            "type":"Services"
        }
    ],
    "sg:phone":"+1 407 246 7220",
    "sg:postcode":"32811",
    "sg:province":"FL",
    "sg:tags":[
        "maintenance"
    ],
    "wof:name":"Maids Quarters Inc",
    "wof:placetype":"venue"
},
  "geometry": {"coordinates":[-81.452698,28.496615],"type":"Point"}
}