{
  "type": "Feature",
  "properties": {
    "iso:country":"US",
    "sg:address":"5600 SW 4th Ct",
    "sg:city":"Fort Lauderdale",
    "sg:classifiers":[
        {
            "category":"Building & Trades",
            "subcategory":"Construction",
            "type":"Services"
        }
    ],
    "sg:phone":"+1 954 473 6249",
    "sg:postcode":"33317",
    "sg:province":"FL",
    "sg:tags":[
        "house"
    ],
    "wof:name":"JP Home Improvements",
    "wof:placetype":"venue"
},
  "geometry": {"coordinates":[-80.22777499999999,26.115309],"type":"Point"}
}