{
  "type": "Feature",
  "properties": {
    "addr:full":"11960 SE US Hwy 301 Belleview FL 34420",
    "addr:postcode":"11960;34420",
    "addr:street":"Se Us Hwy 301",
    "iso:country":"US",
    "sg:address":"11960 SE US Hwy 301",
    "sg:city":"Belleview",
    "sg:classifiers":[
        {
            "category":"Food & Beverages",
            "subcategory":"Groceries & Convenience Stores",
            "type":"Retail Goods"
        },
        {
            "category":"Autos & Motor Vehicles",
            "subcategory":"Fuel & Gas Station",
            "type":"Retail Goods"
        }
    ],
    "sg:phone":"+1 352 245 9239",
    "sg:postcode":"34420",
    "sg:province":"FL",
    "sg:tags":[
        "oil"
    ],
    "wof:name":"Sunny's BP Inc",
    "wof:placetype":"venue"
},
  "geometry": {"coordinates":[-82.046269,29.048208],"type":"Point"}
}