{
  "type": "Feature",
  "properties": {
    "addr:full":"302 N Howard Ave Tampa FL 33606",
    "addr:housenumber":"302",
    "addr:postcode":"33606",
    "addr:street":"N Howard Ave",
    "iso:country":"US",
    "sg:address":"302 N Howard Ave",
    "sg:city":"Tampa",
    "sg:classifiers":[
        {
            "category":"Social Services",
            "subcategory":"Child Care",
            "type":"Services"
        }
    ],
    "sg:phone":"+1 813 259 9940",
    "sg:postcode":"33606",
    "sg:province":"FL",
    "sg:tags":[
        "day"
    ],
    "wof:name":"Higher Learning Academy Inc",
    "wof:placetype":"venue"
},
  "geometry": {"coordinates":[-82.483062,27.947682],"type":"Point"}
}