{
  "type": "Feature",
  "properties": {
    "addr:full":"835 NW 7th St Miami FL 33136",
    "addr:housenumber":"835",
    "addr:postcode":"33136",
    "addr:street":"Nw 7Th St",
    "iso:country":"US",
    "sg:address":"835 NW 7th St",
    "sg:city":"Miami",
    "sg:classifiers":[
        {
            "category":"Travel",
            "subcategory":"Travel Agent",
            "type":"Entertainment"
        }
    ],
    "sg:phone":"+1 305 548 3262",
    "sg:postcode":"33136",
    "sg:province":"FL",
    "sg:tags":[
        "tour",
        "promoter"
    ],
    "sg:website":"www.blackhistorytours.com",
    "wof:name":"Black History Tours",
    "wof:placetype":"venue"
},
  "geometry": {"coordinates":[-80.208485,25.780731],"type":"Point"}
}