{
  "type": "Feature",
  "properties": {
    "iso:country":"US",
    "sg:address":"3050 NW 41st St",
    "sg:city":"Fort Lauderdale",
    "sg:classifiers":[
        {
            "category":"Education",
            "subcategory":"School",
            "type":"Public Place"
        }
    ],
    "sg:phone":"+1 954 497 3800",
    "sg:postcode":"33309",
    "sg:province":"FL",
    "wof:name":"Boyd H Anderson High School",
    "wof:placetype":"venue"
},
  "geometry": {"coordinates":[-80.18695700000001,26.177683],"type":"Point"}
}