{
  "type": "Feature",
  "properties": {
    "iso:country":"US",
    "sg:address":"4100 73rd St N",
    "sg:city":"St Petersburg",
    "sg:classifiers":[
        {
            "category":"Building & Trades",
            "subcategory":"Electrical",
            "type":"Services"
        }
    ],
    "sg:phone":"+1 727 545 9884",
    "sg:postcode":"33709",
    "sg:province":"FL",
    "sg:tags":[
        "electric",
        "contractor"
    ],
    "wof:name":"Mitton Electric",
    "wof:placetype":"venue"
},
  "geometry": {"coordinates":[-82.739687,27.809727],"type":"Point"}
}