{
  "type": "Feature",
  "properties": {
    "iso:country":"US",
    "sg:address":"9280 Bay Plaza Blvd",
    "sg:city":"Tampa",
    "sg:classifiers":[
        {
            "category":"Professional",
            "subcategory":"Management & Consulting",
            "type":"Services"
        }
    ],
    "sg:phone":"+1 813 664 0993",
    "sg:postcode":"33619",
    "sg:province":"FL",
    "sg:tags":[
        "consultant",
        "broker"
    ],
    "wof:name":"Ashdale Group Inc",
    "wof:placetype":"venue"
},
  "geometry": {"coordinates":[-82.348164,27.946904],"type":"Point"}
}