{
  "type": "Feature",
  "properties": {
    "addr:full":"5738 W Hallandale Beach Blvd Hollywood FL 33023",
    "addr:housenumber":"5738",
    "addr:postcode":"33023",
    "addr:street":"W Hallandale Beach Blvd",
    "iso:country":"US",
    "sg:address":"5738 W Hallandale Beach Blvd",
    "sg:city":"Hollywood",
    "sg:classifiers":[
        {
            "category":"Utilities",
            "subcategory":"Mobile Phone",
            "type":"Services"
        }
    ],
    "sg:phone":"+1 954 983 8605",
    "sg:postcode":"33023",
    "sg:province":"FL",
    "sg:tags":[
        "telephone",
        "cellular"
    ],
    "wof:name":"AMS Bi-Cell",
    "wof:placetype":"venue"
},
  "geometry": {"coordinates":[-80.202399,25.984575],"type":"Point"}
}