{
  "type": "Feature",
  "properties": {
    "addr:full":"530 NE 47th St Boca Raton FL 33431",
    "addr:housenumber":"530",
    "addr:postcode":"33431",
    "addr:street":"Ne 47Th St",
    "iso:country":"US",
    "sg:address":"530 NE 47th St",
    "sg:city":"Boca Raton",
    "sg:classifiers":[
        {
            "category":"Real Estate",
            "subcategory":"Real Estate Operator",
            "type":"Services"
        }
    ],
    "sg:phone":"+1 561 395 5591",
    "sg:postcode":"33431",
    "sg:province":"FL",
    "sg:tags":[
        "building",
        "apartment"
    ],
    "wof:name":"Boca Winds Apts",
    "wof:placetype":"venue"
},
  "geometry": {"coordinates":[-80.077135,26.391408],"type":"Point"}
}