{
  "type": "Feature",
  "properties": {
    "iso:country":"US",
    "sg:address":"3002 Sir Hamilton Cir",
    "sg:city":"Titusville",
    "sg:classifiers":[
        {
            "category":"Health Services",
            "subcategory":"Clinic",
            "type":"Services"
        }
    ],
    "sg:phone":"+1 321 264 5777",
    "sg:postcode":"32780",
    "sg:province":"FL",
    "sg:tags":[
        "specialty",
        "outpatient"
    ],
    "wof:name":"Lonser Center The",
    "wof:placetype":"venue"
},
  "geometry": {"coordinates":[-80.807877,28.582167],"type":"Point"}
}