{
  "type": "Feature",
  "properties": {
    "addr:full":"540 Chase Hammock Rd Merritt Island FL 32953",
    "addr:housenumber":"540",
    "addr:postcode":"32953",
    "addr:street":"Chase Hammock Rd",
    "iso:country":"US",
    "sg:address":"540 Chase Hammock Rd",
    "sg:city":"Merritt Island",
    "sg:classifiers":[
        {
            "category":"Building & Trades",
            "subcategory":"Construction",
            "type":"Services"
        }
    ],
    "sg:phone":"+1 321 453 2244",
    "sg:postcode":"32953",
    "sg:province":"FL",
    "sg:tags":[
        "general",
        "contractor"
    ],
    "wof:name":"Southern Comfort Builders Inc",
    "wof:placetype":"venue"
},
  "geometry": {"coordinates":[-80.708465,28.44906],"type":"Point"}
}