{
  "type": "Feature",
  "properties": {
    "iso:country":"US",
    "sg:address":"2618 Bristol Hwy",
    "sg:city":"Quincy",
    "sg:phone":"+1 850 442 4117",
    "sg:postcode":"32330",
    "sg:province":"FL",
    "sg:tags":[
        "vegetable",
        "farm"
    ],
    "wof:name":"Juniper Tomato Growers",
    "wof:placetype":"venue"
},
  "geometry": {"coordinates":[-84.759925,30.540575],"type":"Point"}
}