{
  "type": "Feature",
  "properties": {
    "iso:country":"US",
    "sg:address":"314 Venetian Dr",
    "sg:city":"Delray Beach",
    "sg:classifiers":[
        {
            "category":"Travel",
            "subcategory":"Hotels & Motels",
            "type":"Entertainment"
        }
    ],
    "sg:phone":"+1 561 276 6371",
    "sg:postcode":"33483",
    "sg:province":"FL",
    "sg:tags":[
        "resort"
    ],
    "wof:name":"Tahiti Cove",
    "wof:placetype":"venue"
},
  "geometry": {"coordinates":[-80.06211399999999,26.456189],"type":"Point"}
}