{
  "type": "Feature",
  "properties": {
    "addr:full":"1802 James L Redman Pkwy Plant City FL 33563",
    "addr:housenumber":"1802",
    "addr:postcode":"33563",
    "addr:street":"James L Redman Pkwy",
    "iso:country":"US",
    "sg:address":"1802 James L Redman Pkwy",
    "sg:city":"Plant City",
    "sg:classifiers":[
        {
            "category":"Shopping",
            "subcategory":"Pharmacy",
            "type":"Retail Goods"
        }
    ],
    "sg:phone":"+1 813 752 5843",
    "sg:postcode":"33563",
    "sg:province":"FL",
    "sg:website":"www.walgreens.com",
    "wof:name":"Walgreens",
    "wof:placetype":"venue"
},
  "geometry": {"coordinates":[-82.121414,27.996435],"type":"Point"}
}