{
  "type": "Feature",
  "properties": {
    "iso:country":"US",
    "sg:address":"7690 Bryan Dairy Rd",
    "sg:city":"Largo",
    "sg:classifiers":[
        {
            "category":"Autos & Motor Vehicles",
            "subcategory":"Fuel & Gas Station",
            "type":"Retail Goods"
        }
    ],
    "sg:phone":"+1 727 544 9494",
    "sg:postcode":"33777",
    "sg:province":"FL",
    "sg:tags":[
        "oil"
    ],
    "wof:name":"Petro-Quad Inc",
    "wof:placetype":"venue"
},
  "geometry": {"coordinates":[-82.743362,27.872141],"type":"Point"}
}