{
  "type": "Feature",
  "properties": {
    "iso:country":"US",
    "sg:address":"220 E Ventura Ave",
    "sg:city":"Clewiston",
    "sg:classifiers":[
        {
            "category":"Real Estate",
            "subcategory":"Real Estate Operator",
            "type":"Services"
        }
    ],
    "sg:phone":"+1 863 983 7272",
    "sg:postcode":"33440",
    "sg:province":"FL",
    "sg:tags":[
        "apartment"
    ],
    "wof:name":"Von Mach Apts",
    "wof:placetype":"venue"
},
  "geometry": {"coordinates":[-80.93303,26.752411],"type":"Point"}
}