{
  "type": "Feature",
  "properties": {
    "addr:full":"4760 Pine Tree Dr Miami Beach FL 33140",
    "addr:housenumber":"4760",
    "addr:postcode":"33140",
    "addr:street":"Pine Tree Dr",
    "iso:country":"US",
    "sg:address":"4760 Pine Tree Dr",
    "sg:city":"Miami Beach",
    "sg:classifiers":[
        {
            "category":"Social Services",
            "subcategory":"Child Care",
            "type":"Services"
        }
    ],
    "sg:phone":"+1 305 534 8234",
    "sg:postcode":"33140",
    "sg:province":"FL",
    "sg:tags":[
        "day"
    ],
    "wof:name":"St John's Child Care Center",
    "wof:placetype":"venue"
},
  "geometry": {"coordinates":[-80.12550400000001,25.823299],"type":"Point"}
}