{
  "type": "Feature",
  "properties": {
    "iso:country":"US",
    "sg:address":"24625 Lester Way",
    "sg:city":"Eustis",
    "sg:classifiers":[
        {
            "category":"Building & Trades",
            "subcategory":"Landscaping Services",
            "type":"Services"
        }
    ],
    "sg:phone":"+1 352 483 2332",
    "sg:postcode":"32736",
    "sg:province":"FL",
    "wof:name":"Pro-Scape",
    "wof:placetype":"venue"
},
  "geometry": {"coordinates":[-81.549091,28.889716],"type":"Point"}
}