{
  "type": "Feature",
  "properties": {
    "addr:full":"350 Bus Park Way Royal Palm Beach FL 33411",
    "addr:housenumber":"350",
    "addr:postcode":"33411",
    "addr:street":"Bus Park Way",
    "iso:country":"US",
    "sg:address":"350 Bus Park Way",
    "sg:city":"Royal Palm Beach",
    "sg:classifiers":[
        {
            "category":"Home & Garden",
            "subcategory":"Furniture",
            "type":"Retail Goods"
        }
    ],
    "sg:phone":"+1 561 793 8265",
    "sg:postcode":"33411",
    "sg:province":"FL",
    "sg:tags":[
        "cabinet"
    ],
    "wof:name":"Cabinet Solvers",
    "wof:placetype":"venue"
},
  "geometry": {"coordinates":[-80.206461,26.699416],"type":"Point"}
}