{
  "type": "Feature",
  "properties": {
    "addr:full":"8340 SW 103rd St Miami FL 33156",
    "addr:housenumber":"8340",
    "addr:postcode":"33156",
    "addr:street":"Sw 103Rd St",
    "iso:country":"US",
    "sg:address":"8340 SW 103rd St",
    "sg:city":"Miami",
    "sg:classifiers":[
        {
            "category":"Insurance",
            "subcategory":"Insurance Agent",
            "type":"Services"
        }
    ],
    "sg:phone":"+1 305 595 2632",
    "sg:postcode":"33156",
    "sg:province":"FL",
    "wof:name":"Bill Hardy Insurance Assoc",
    "wof:placetype":"venue"
},
  "geometry": {"coordinates":[-80.32910099999999,25.674516],"type":"Point"}
}