{
  "type": "Feature",
  "properties": {
    "iso:country":"US",
    "sg:address":"920 NE 35th St",
    "sg:city":"Ocala",
    "sg:classifiers":[
        {
            "category":"Social Services",
            "subcategory":"Child Care",
            "type":"Services"
        }
    ],
    "sg:phone":"+1 352 690 6868",
    "sg:postcode":"34479",
    "sg:province":"FL",
    "wof:name":"Building Blocks",
    "wof:placetype":"venue"
},
  "geometry": {"coordinates":[-82.124093,29.222999],"type":"Point"}
}