{
  "type": "Feature",
  "properties": {
    "addr:full":"615 Oak St Boynton Beach FL 33435",
    "addr:housenumber":"615",
    "addr:postcode":"33435",
    "addr:street":"Oak St",
    "iso:country":"US",
    "sg:address":"615 Oak St",
    "sg:city":"Boynton Beach",
    "sg:classifiers":[
        {
            "category":"Building & Trades",
            "subcategory":"Plumbing",
            "type":"Services"
        }
    ],
    "sg:phone":"+1 561 364 9203",
    "sg:postcode":"33435",
    "sg:province":"FL",
    "sg:tags":[
        "plumbing",
        "contractor"
    ],
    "wof:name":"O'Hara's Plumbing",
    "wof:placetype":"venue"
},
  "geometry": {"coordinates":[-80.05492,26.545563],"type":"Point"}
}