{
  "type": "Feature",
  "properties": {
    "iso:country":"US",
    "sg:address":"430 S Dixie Hwy",
    "sg:city":"Coral Gables",
    "sg:classifiers":[
        {
            "category":"Health Services",
            "subcategory":"Health Practitioner",
            "type":"Services"
        }
    ],
    "sg:phone":"+1 305 740 0740",
    "sg:postcode":"33146",
    "sg:province":"FL",
    "sg:tags":[
        "acupuncture"
    ],
    "wof:name":"Anasseri Shiva",
    "wof:placetype":"venue"
},
  "geometry": {"coordinates":[-80.26260600000001,25.725384],"type":"Point"}
}