{
  "type": "Feature",
  "properties": {
    "addr:full":"5380 Catalyst Ave Sarasota FL 34233",
    "addr:postcode":"5380;34233",
    "addr:street":"Catalyst Ave",
    "iso:country":"US",
    "sg:address":"5380 Catalyst Ave",
    "sg:city":"Sarasota",
    "sg:classifiers":[
        {
            "category":"Home & Garden",
            "subcategory":"Building Materials",
            "type":"Retail Goods"
        }
    ],
    "sg:phone":"+1 941 925 0847",
    "sg:postcode":"34233",
    "sg:province":"FL",
    "sg:tags":[
        "screen",
        "window"
    ],
    "wof:name":"Vanishing Screens",
    "wof:placetype":"venue"
},
  "geometry": {"coordinates":[-82.47499000000001,27.273586],"type":"Point"}
}