{
  "type": "Feature",
  "properties": {
    "addr:full":"1236 SW Tropical Ter Stuart FL 34997",
    "addr:housenumber":"1236",
    "addr:postcode":"34997",
    "addr:street":"Sw Tropical Ter",
    "iso:country":"US",
    "sg:address":"1236 SW Tropical Ter",
    "sg:city":"Stuart",
    "sg:classifiers":[
        {
            "category":"Shopping",
            "subcategory":"Catalog Store",
            "type":"Retail Goods"
        }
    ],
    "sg:phone":"+1 772 221 8417",
    "sg:postcode":"34997",
    "sg:province":"FL",
    "sg:tags":[
        "mail",
        "house"
    ],
    "wof:name":"Uncharted Isle",
    "wof:placetype":"venue"
},
  "geometry": {"coordinates":[-80.270697,27.107001],"type":"Point"}
}