{
  "type": "Feature",
  "properties": {
    "iso:country":"US",
    "sg:address":"520 NE 162nd St",
    "sg:city":"Miami",
    "sg:classifiers":[
        {
            "category":"Communications",
            "subcategory":"Film & Video Production",
            "type":"Services"
        }
    ],
    "sg:phone":"+1 305 956 5819",
    "sg:postcode":"33162",
    "sg:province":"FL",
    "sg:tags":[
        "services-commercial"
    ],
    "wof:name":"J Video Productions",
    "wof:placetype":"venue"
},
  "geometry": {"coordinates":[-80.189671,25.92406],"type":"Point"}
}