{
  "type": "Feature",
  "properties": {
    "addr:full":"842 Reading St SE Palm Bay FL 32909",
    "addr:housenumber":"842",
    "addr:postcode":"32909",
    "addr:street":"Reading St Se",
    "iso:country":"US",
    "sg:address":"842 Reading St SE",
    "sg:city":"Palm Bay",
    "sg:classifiers":[
        {
            "category":"Manufacturing",
            "subcategory":"Tools & Machinery",
            "type":"Manufacturing & Wholesale Goods"
        }
    ],
    "sg:phone":"+1 321 725 0701",
    "sg:postcode":"32909",
    "sg:province":"FL",
    "sg:tags":[
        "industrial",
        "mfg"
    ],
    "wof:name":"S D Long",
    "wof:placetype":"venue"
},
  "geometry": {"coordinates":[-80.648256,27.930242],"type":"Point"}
}