{
  "type": "Feature",
  "properties": {
    "iso:country":"US",
    "sg:address":"1215 SE 2nd Ave",
    "sg:city":"Fort Lauderdale",
    "sg:classifiers":[
        {
            "category":"Insurance",
            "subcategory":"Insurance Agent",
            "type":"Services"
        }
    ],
    "sg:phone":"+1 954 523 7001",
    "sg:postcode":"33316",
    "sg:province":"FL",
    "wof:name":"D C Brown & Co Inc",
    "wof:placetype":"venue"
},
  "geometry": {"coordinates":[-80.14103299999999,26.106273],"type":"Point"}
}