{
  "type": "Feature",
  "properties": {
    "iso:country":"US",
    "sg:address":"3512 Coco Lake Dr",
    "sg:city":"Pompano Beach",
    "sg:classifiers":[
        {
            "category":"Professional",
            "subcategory":"Engineering",
            "type":"Services"
        }
    ],
    "sg:phone":"+1 954 698 0162",
    "sg:postcode":"33073",
    "sg:province":"FL",
    "sg:tags":[
        "consultant",
        "construction",
        "electrical"
    ],
    "wof:name":"Tri-State Engrg & Mgt Conslt",
    "wof:placetype":"venue"
},
  "geometry": {"coordinates":[-80.176011,26.29448],"type":"Point"}
}